{
  "type": "Feature",
  "properties": {
    "addr:full":"2 Unwin St Rosehill NSW 2142",
    "addr:housenumber":"2",
    "addr:postcode":"2142",
    "addr:street":"Unwin St",
    "iso:country":"AU",
    "sg:address":"2 Unwin St",
    "sg:city":"Rosehill",
    "sg:classifiers":[
        {
            "category":"Cafe",
            "type":"Food & Drink"
        }
    ],
    "sg:phone":"+61 2 9682 6553",
    "sg:postcode":"2142",
    "sg:province":"NSW",
    "wof:name":"Chestnut Cafe",
    "wof:placetype":"venue"
},
  "geometry": {"coordinates":[151.02479553200001,-33.8273048401],"type":"Point"}
}