{
  "type": "Feature",
  "properties": {
    "addr:full":"899 Victoria Rd West Ryde NSW 2114",
    "addr:housenumber":"899",
    "addr:postcode":"2114",
    "addr:street":"Victoria Rd",
    "iso:country":"AU",
    "sg:address":"899 Victoria Rd",
    "sg:city":"West Ryde",
    "sg:classifiers":[
        {
            "category":"Retail",
            "subcategory":"Auto Repair",
            "type":"Services"
        }
    ],
    "sg:phone":"+61 2 9809 5698",
    "sg:postcode":"2114",
    "sg:province":"NSW",
    "sg:tags":[
        "repairer",
        "motor",
        "engineer"
    ],
    "wof:name":"Sandy's Auto Repairs Pty Ltd",
    "wof:placetype":"venue"
},
  "geometry": {"coordinates":[151.08807373100001,-33.8078155518],"type":"Point"}
}