{
  "type": "Feature",
  "properties": {
    "addr:full":"44 Kensington Rd Rose Park SA 5067",
    "addr:housenumber":"44",
    "addr:postcode":"5067",
    "addr:street":"Kensington Rd Rose",
    "iso:country":"AU",
    "sg:address":"44 Kensington Rd",
    "sg:city":"Rose Park",
    "sg:classifiers":[
        {
            "category":"Professional",
            "subcategory":"Management & Consulting",
            "type":"Services"
        }
    ],
    "sg:phone":"+61 412 830 830",
    "sg:postcode":"5067",
    "sg:province":"SA",
    "sg:tags":[
        "consultant"
    ],
    "wof:name":"Vroom And Associates",
    "wof:placetype":"venue"
},
  "geometry": {"coordinates":[138.62878418,-34.9277153015],"type":"Point"}
}