{
  "type": "Feature",
  "properties": {
    "iso:country":"AU",
    "sg:address":"11 Beatrice Ave",
    "sg:city":"Heidelberg West",
    "sg:classifiers":[
        {
            "category":"Autos & Motor Vehicles",
            "subcategory":"Auto Supplies",
            "type":"Retail Goods"
        }
    ],
    "sg:phone":"+61 3 9457 3141",
    "sg:postcode":"3081",
    "sg:province":"VIC",
    "sg:tags":[
        "wheel",
        "automotive",
        "rim"
    ],
    "wof:name":"Neway Wheel Repairs Pty Ltd",
    "wof:placetype":"venue"
},
  "geometry": {"coordinates":[145.05152893100001,-37.7304077148],"type":"Point"}
}