{
  "type": "Feature",
  "properties": {
    "addr:full":"27 Mayneview St Milton QLD 4064",
    "addr:housenumber":"27",
    "addr:postcode":"4064",
    "addr:street":"Mayneview St",
    "iso:country":"AU",
    "sg:address":"27 Mayneview St",
    "sg:city":"Milton",
    "sg:classifiers":[
        {
            "category":"Professional",
            "subcategory":"Computer Services",
            "type":"Services"
        }
    ],
    "sg:phone":"+61 7 3369 8855",
    "sg:postcode":"4064",
    "sg:province":"QLD",
    "sg:tags":[
        "training"
    ],
    "wof:name":"AWA Technology Services",
    "wof:placetype":"venue"
},
  "geometry": {"coordinates":[153.00645446799999,-27.465297699],"type":"Point"}
}