{
  "type": "Feature",
  "properties": {
    "addr:full":"PO Box 26 Dayboro QLD 4521",
    "addr:postcode":"4521",
    "iso:country":"AU",
    "sg:address":"PO Box 26",
    "sg:city":"Dayboro",
    "sg:classifiers":[
        {
            "category":"Building & Trades",
            "subcategory":"Construction",
            "type":"Services"
        }
    ],
    "sg:phone":"+61 412 377 358",
    "sg:postcode":"4521",
    "sg:province":"QLD",
    "sg:tags":[
        "contractor"
    ],
    "wof:name":"Ergon Constructions",
    "wof:placetype":"venue"
},
  "geometry": {"coordinates":[152.823654,-27.196529],"type":"Point"}
}