{
  "type": "Feature",
  "properties": {
    "addr:full":"3 Garnett Rd East Maitland NSW 2323",
    "addr:housenumber":"3",
    "addr:postcode":"2323",
    "addr:street":"Garnett Rd",
    "iso:country":"AU",
    "sg:address":"3 Garnett Rd",
    "sg:city":"East Maitland",
    "sg:classifiers":[
        {
            "category":"Cafe",
            "type":"Food & Drink"
        }
    ],
    "sg:phone":"+61 2 4933 5644",
    "sg:postcode":"2323",
    "sg:province":"NSW",
    "wof:name":"Reader's Cafe",
    "wof:placetype":"venue"
},
  "geometry": {"coordinates":[151.59121704099999,-32.7604675293],"type":"Point"}
}