{
  "type": "Feature",
  "properties": {
    "addr:full":"229 Lr Dandenong Rd Mordialloc VIC 3195",
    "addr:housenumber":"229",
    "addr:postcode":"3195",
    "addr:street":"Dandenong Rd",
    "iso:country":"AU",
    "sg:address":"229 Lr Dandenong Rd",
    "sg:city":"Mordialloc",
    "sg:classifiers":[
        {
            "category":"Building & Trades",
            "subcategory":"Equipment Rental",
            "type":"Services"
        }
    ],
    "sg:phone":"+61 3 9580 8588",
    "sg:postcode":"3195",
    "sg:province":"VIC",
    "sg:tags":[
        "crane",
        "hire"
    ],
    "wof:name":"Gleason Cranes Pty Ltd",
    "wof:placetype":"venue"
},
  "geometry": {"coordinates":[145.09568786599999,-37.9848060608],"type":"Point"}
}