{
  "type": "Feature",
  "properties": {
    "addr:full":"77 Ingrid Rd Kareela NSW 2232",
    "addr:housenumber":"77",
    "addr:postcode":"2232",
    "addr:street":"Ingrid Rd",
    "iso:country":"AU",
    "sg:address":"77 Ingrid Rd",
    "sg:city":"Kareela",
    "sg:classifiers":[
        {
            "category":"Building & Trades",
            "subcategory":"Construction",
            "type":"Services"
        }
    ],
    "sg:phone":"+61 418 444 330",
    "sg:postcode":"2232",
    "sg:province":"NSW",
    "sg:tags":[
        "plasterboard",
        "plasterer",
        "fixer"
    ],
    "wof:name":"Dunn Larry",
    "wof:placetype":"venue"
},
  "geometry": {"coordinates":[151.08543395999999,-34.0134353638],"type":"Point"}
}