{
  "type": "Feature",
  "properties": {
    "addr:full":"9 Albatross Drv Rowville VIC 3178",
    "addr:housenumber":"9",
    "addr:postcode":"3178",
    "addr:street":"Albatross Drv",
    "iso:country":"AU",
    "sg:address":"9 Albatross Drv",
    "sg:city":"Rowville",
    "sg:classifiers":[
        {
            "category":"Transit Center",
            "subcategory":"Freight",
            "type":"Transportation"
        }
    ],
    "sg:phone":"+61 409 160 472",
    "sg:postcode":"3178",
    "sg:province":"VIC",
    "sg:tags":[
        "turner",
        "wood"
    ],
    "wof:name":"Cass Wayne",
    "wof:placetype":"venue"
},
  "geometry": {"coordinates":[145.266113281,-37.9026603699],"type":"Point"}
}