{
  "type": "Feature",
  "properties": {
    "addr:full":"11 Kippax Pl Shalvey NSW 2770",
    "addr:housenumber":"11",
    "addr:postcode":"2770",
    "addr:street":"Kippax Pl",
    "iso:country":"AU",
    "sg:address":"11 Kippax Pl",
    "sg:city":"Shalvey",
    "sg:classifiers":[
        {
            "category":"Professional",
            "subcategory":"Detective & Security Services",
            "type":"Services"
        }
    ],
    "sg:phone":"+61 2 9835 2004",
    "sg:postcode":"2770",
    "sg:province":"NSW",
    "sg:tags":[
        "guard",
        "patrol"
    ],
    "wof:name":"Shalvey Security Services Pty Ltd",
    "wof:placetype":"venue"
},
  "geometry": {"coordinates":[150.811035156,-33.7307434082],"type":"Point"}
}