{
  "type": "Feature",
  "properties": {
    "iso:country":"AU",
    "sg:address":"72 Weston St",
    "sg:city":"Dulwich Hill",
    "sg:classifiers":[
        {
            "category":"Building & Trades",
            "subcategory":"Construction",
            "type":"Services"
        }
    ],
    "sg:phone":"+61 2 9569 9104",
    "sg:postcode":"2203",
    "sg:province":"NSW",
    "sg:tags":[
        "contractor"
    ],
    "wof:name":"Summer Hill Building Services",
    "wof:placetype":"venue"
},
  "geometry": {"coordinates":[151.13975500000001,-33.898338],"type":"Point"}
}