{
  "type": "Feature",
  "properties": {
    "addr:full":"30 French Rd Greenvale VIC 3059",
    "addr:housenumber":"30",
    "addr:postcode":"3059",
    "addr:street":"French Rd",
    "iso:country":"AU",
    "sg:address":"30 French Rd",
    "sg:city":"Greenvale",
    "sg:classifiers":[
        {
            "category":"Farming",
            "subcategory":"Poultry Farm",
            "type":"Manufacturing & Wholesale Goods"
        }
    ],
    "sg:phone":"+61 3 9333 1538",
    "sg:postcode":"3059",
    "sg:province":"VIC",
    "sg:tags":[
        "farmer"
    ],
    "wof:name":"Greenvale Poultry Farm",
    "wof:placetype":"venue"
},
  "geometry": {"coordinates":[144.88517761200001,-37.63514328],"type":"Point"}
}