{
  "type": "Feature",
  "properties": {
    "addr:full":"46 Gladys St Kelso QLD 4815",
    "addr:housenumber":"46",
    "addr:postcode":"4815",
    "addr:street":"Gladys St",
    "iso:country":"AU",
    "sg:address":"46 Gladys St",
    "sg:city":"Kelso",
    "sg:classifiers":[
        {
            "category":"Home & Garden",
            "subcategory":"Building Materials",
            "type":"Retail Goods"
        }
    ],
    "sg:phone":"+61 413 619 654",
    "sg:postcode":"4815",
    "sg:province":"QLD",
    "sg:tags":[
        "tile",
        "roofing"
    ],
    "wof:name":"Cobra Roofing PTY. LTD.",
    "wof:placetype":"venue"
},
  "geometry": {"coordinates":[146.72787500000001,-19.381317],"type":"Point"}
}