{
  "type": "Feature",
  "properties": {
    "iso:country":"AU",
    "sg:address":"27 Victoria Rd",
    "sg:city":"Punchbowl",
    "sg:classifiers":[
        {
            "category":"Building & Trades",
            "subcategory":"Landscaping Services",
            "type":"Services"
        }
    ],
    "sg:phone":"+61 410 302 169",
    "sg:postcode":"2196",
    "sg:province":"NSW",
    "sg:tags":[
        "stump",
        "tree",
        "felling",
        "removal"
    ],
    "wof:name":"Sky Is The Limit",
    "wof:placetype":"venue"
},
  "geometry": {"coordinates":[151.052933,-33.92857],"type":"Point"}
}