{
  "type": "Feature",
  "properties": {
    "iso:country":"AU",
    "sg:address":"63 Purchase Rd",
    "sg:city":"Cherrybrook",
    "sg:classifiers":[
        {
            "category":"Health Services",
            "subcategory":"Health Practitioner",
            "type":"Services"
        }
    ],
    "sg:phone":"+61 2 9481 8113",
    "sg:postcode":"2126",
    "sg:province":"NSW",
    "sg:tags":[
        "acupuncture"
    ],
    "wof:name":"Acupuncture & Chinese Herbal Clinic",
    "wof:placetype":"venue"
},
  "geometry": {"coordinates":[151.03927612300001,-33.718132019],"type":"Point"}
}