{
  "type": "Feature",
  "properties": {
    "addr:full":"Shop 4, &#039;Key Largo&#039;, 6- 8 Aerodrome Rd Maroochydore QLD 4558",
    "addr:housenumber":"shop 4 & # 039;8",
    "addr:postcode":"4558",
    "addr:street":"6;Aerodrome Rd",
    "iso:country":"AU",
    "sg:address":"Shop 4, &#039;Key Largo&#039;, 6- 8 Aerodrome Rd",
    "sg:city":"Maroochydore",
    "sg:classifiers":[
        {
            "category":"Real Estate",
            "subcategory":"Real Estate Agent",
            "type":"Services"
        }
    ],
    "sg:phone":"+61 7 5479 6133",
    "sg:postcode":"4558",
    "sg:province":"QLD",
    "wof:name":"Hayes & Co Real Estate",
    "wof:placetype":"venue"
},
  "geometry": {"coordinates":[153.10438537600001,-26.6621131897],"type":"Point"}
}