{
  "type": "Feature",
  "properties": {
    "addr:full":"3/ 21 Divine Crt Phillip ACT 2606",
    "addr:housenumber":"/ 21",
    "addr:postcode":"2606",
    "addr:street":"Divine Crt",
    "iso:country":"AU",
    "sg:address":"3/ 21 Divine Crt",
    "sg:city":"Phillip",
    "sg:classifiers":[
        {
            "category":"Retail",
            "subcategory":"Auto Repair",
            "type":"Services"
        }
    ],
    "sg:phone":"+61 2 6232 5262",
    "sg:postcode":"2606",
    "sg:province":"ACT",
    "sg:tags":[
        "repairer",
        "motor",
        "engineer"
    ],
    "wof:name":"K & M Automotive Services",
    "wof:placetype":"venue"
},
  "geometry": {"coordinates":[149.08631897000001,-35.3499984741],"type":"Point"}
}