{
  "type": "Feature",
  "properties": {
    "iso:country":"AU",
    "sg:address":"Endell St",
    "sg:city":"Bridgeman Downs",
    "sg:classifiers":[
        {
            "category":"Building & Trades",
            "subcategory":"Construction",
            "type":"Services"
        }
    ],
    "sg:phone":"+61 7 3863 2444",
    "sg:postcode":"4035",
    "sg:province":"QLD",
    "sg:tags":[
        "contractor"
    ],
    "wof:name":"Sanderson RJ Builders",
    "wof:placetype":"venue"
},
  "geometry": {"coordinates":[152.99408,-27.362459],"type":"Point"}
}