{
  "type": "Feature",
  "properties": {
    "addr:full":"100 Lymburner Drv Hillarys WA 6025",
    "addr:housenumber":"100",
    "addr:postcode":"6025",
    "addr:street":"Lymburner Drv",
    "iso:country":"AU",
    "sg:address":"100 Lymburner Drv",
    "sg:city":"Hillarys",
    "sg:classifiers":[
        {
            "category":"Home & Garden",
            "subcategory":"Building Materials",
            "type":"Retail Goods"
        }
    ],
    "sg:phone":"+61 412 096 350",
    "sg:postcode":"6025",
    "sg:province":"WA",
    "sg:tags":[
        "retaining",
        "wall"
    ],
    "wof:name":"Rock Hard Stonemasons",
    "wof:placetype":"venue"
},
  "geometry": {"coordinates":[115.751876831,-31.8119869232],"type":"Point"}
}