{
  "type": "Feature",
  "properties": {
    "addr:full":"2 Portrush Rd Payneham SA 5070",
    "addr:housenumber":"2",
    "addr:postcode":"5070",
    "addr:street":"Portrush Rd",
    "iso:country":"AU",
    "sg:address":"2 Portrush Rd",
    "sg:city":"Payneham",
    "sg:classifiers":[
        {
            "category":"Manufacturing",
            "subcategory":"Building Materials",
            "type":"Manufacturing & Wholesale Goods"
        }
    ],
    "sg:phone":"+61 8 8336 7644",
    "sg:postcode":"5070",
    "sg:province":"SA",
    "sg:tags":[
        "equipment",
        "handling"
    ],
    "wof:name":"Teklogix",
    "wof:placetype":"venue"
},
  "geometry": {"coordinates":[138.63929748499999,-34.8966178894],"type":"Point"}
}