{
  "type": "Feature",
  "properties": {
    "addr:full":"3 Wyndella St West Launceston TAS 7250",
    "addr:housenumber":"3",
    "addr:postcode":"7250",
    "addr:street":"Wyndella St West",
    "iso:country":"AU",
    "sg:address":"3 Wyndella St",
    "sg:city":"West Launceston",
    "sg:classifiers":[
        {
            "category":"Building & Trades",
            "subcategory":"Construction",
            "type":"Services"
        }
    ],
    "sg:phone":"+61 417 151 271",
    "sg:postcode":"7250",
    "sg:province":"TAS",
    "sg:tags":[
        "contractor"
    ],
    "wof:name":"TJ Parker",
    "wof:placetype":"venue"
},
  "geometry": {"coordinates":[147.12661743199999,-41.4540596008],"type":"Point"}
}