{
  "type": "Feature",
  "properties": {
    "addr:full":"8 Wiranda Crt Windsor Downs NSW 2756",
    "addr:housenumber":"8",
    "addr:postcode":"2756",
    "addr:street":"Wiranda Crt",
    "iso:country":"AU",
    "sg:address":"8 Wiranda Crt",
    "sg:city":"Windsor Downs",
    "sg:classifiers":[
        {
            "category":"Building & Trades",
            "subcategory":"Construction",
            "type":"Services"
        }
    ],
    "sg:phone":"+61 2 4574 2145",
    "sg:postcode":"2756",
    "sg:province":"NSW",
    "sg:tags":[
        "fencing",
        "contractor"
    ],
    "wof:name":"Waycor Fencing",
    "wof:placetype":"venue"
},
  "geometry": {"coordinates":[150.81263732900001,-33.6576423645],"type":"Point"}
}