{
  "type": "Feature",
  "properties": {
    "addr:full":"30 Maryland St Stanthorpe QLD 4380",
    "addr:housenumber":"30",
    "addr:postcode":"4380",
    "addr:street":"Maryland St",
    "iso:country":"AU",
    "sg:address":"30 Maryland St",
    "sg:city":"Stanthorpe",
    "sg:classifiers":[
        {
            "category":"Casinos & Gambling",
            "type":"Entertainment"
        }
    ],
    "sg:phone":"+61 7 4681 4460",
    "sg:postcode":"4380",
    "sg:province":"QLD",
    "sg:tags":[
        "lottery",
        "agent"
    ],
    "wof:name":"Red Lion Casket Agency",
    "wof:placetype":"venue"
},
  "geometry": {"coordinates":[151.93370100000001,-28.656013],"type":"Point"}
}