{
  "type": "Feature",
  "properties": {
    "addr:full":"7 View Crt Palm Beach QLD 4221",
    "addr:housenumber":"7",
    "addr:postcode":"4221",
    "addr:street":"View Crt",
    "iso:country":"AU",
    "sg:address":"7 View Crt",
    "sg:city":"Palm Beach",
    "sg:classifiers":[
        {
            "category":"Social Services",
            "subcategory":"Retirement Home",
            "type":"Services"
        }
    ],
    "sg:phone":"+61 7 5576 3883",
    "sg:postcode":"4221",
    "sg:province":"QLD",
    "sg:tags":[
        "environmental",
        "consultant",
        "pollution"
    ],
    "wof:name":"Craig Hill Acoustics",
    "wof:placetype":"venue"
},
  "geometry": {"coordinates":[153.45489501899999,-28.1166400909],"type":"Point"}
}