{
  "type": "Feature",
  "properties": {
    "iso:country":"AU",
    "sg:address":"19 Baird Ave",
    "sg:city":"Ryde",
    "sg:classifiers":[
        {
            "category":"Communications",
            "type":"Services"
        }
    ],
    "sg:phone":"+61 2 9809 0602",
    "sg:postcode":"2112",
    "sg:province":"NSW",
    "sg:tags":[
        "translation"
    ],
    "wof:name":"Italink- Italian Interpreting & Translating Services",
    "wof:placetype":"venue"
},
  "geometry": {"coordinates":[151.115692139,-33.8151626587],"type":"Point"}
}