{
  "type": "Feature",
  "properties": {
    "addr:full":"Burke St Maryborough VIC 3465",
    "addr:postcode":"3465",
    "addr:street":"Burke St",
    "iso:country":"AU",
    "sg:address":"Burke St",
    "sg:city":"Maryborough",
    "sg:classifiers":[
        {
            "category":"Education",
            "subcategory":"School",
            "type":"Public Place"
        }
    ],
    "sg:phone":"+61 3 5460 4440",
    "sg:postcode":"3465",
    "sg:province":"VIC",
    "sg:tags":[
        "co-educational"
    ],
    "wof:name":"St Augustine's Primary School",
    "wof:placetype":"venue"
},
  "geometry": {"coordinates":[143.73870849599999,-37.0500068665],"type":"Point"}
}