{
  "type": "Feature",
  "properties": {
    "addr:full":"179 Parramatta Rd Homebush West NSW 2140",
    "addr:housenumber":"179",
    "addr:postcode":"2140",
    "addr:street":"Parramatta Rd",
    "iso:country":"AU",
    "sg:address":"179 Parramatta Rd",
    "sg:city":"Homebush West",
    "sg:classifiers":[
        {
            "category":"Manufacturing",
            "subcategory":"Food",
            "type":"Manufacturing & Wholesale Goods"
        }
    ],
    "sg:phone":"+61 2 9746 1232",
    "sg:postcode":"2140",
    "sg:province":"NSW",
    "sg:tags":[
        "product",
        "nut",
        "edible"
    ],
    "wof:name":"Duncan Mann Pty Ltd",
    "wof:placetype":"venue"
},
  "geometry": {"coordinates":[151.074905395,-33.860534668],"type":"Point"}
}