{
  "type": "Feature",
  "properties": {
    "addr:full":"20 Crows Nest Rd Waverton NSW 2060",
    "addr:housenumber":"20",
    "addr:postcode":"2060",
    "addr:street":"Crows Nest Rd",
    "iso:country":"AU",
    "sg:address":"20 Crows Nest Rd",
    "sg:city":"Waverton",
    "sg:classifiers":[
        {
            "category":"Professional",
            "subcategory":"Computer Services",
            "type":"Services"
        }
    ],
    "sg:phone":"+61 2 9966 1000",
    "sg:postcode":"2060",
    "sg:province":"NSW",
    "sg:tags":[
        "consultant",
        "system"
    ],
    "wof:name":"Mazaroo Pty Ltd",
    "wof:placetype":"venue"
},
  "geometry": {"coordinates":[151.19947814899999,-33.8355026245],"type":"Point"}
}