{
  "type": "Feature",
  "properties": {
    "addr:full":"SJOG Healthcare Subiaco Clinic Suite 318 / Subiaco WA 6008",
    "addr:housenumber":"318 /",
    "addr:postcode":"6008",
    "iso:country":"AU",
    "sg:address":"SJOG Healthcare Subiaco Clinic Suite 318",
    "sg:city":"/ Subiaco",
    "sg:classifiers":[
        {
            "category":"Health Services",
            "subcategory":"Doctor",
            "type":"Services"
        }
    ],
    "sg:phone":"+61 8 9366 1655",
    "sg:postcode":"6008",
    "sg:province":"WA",
    "sg:tags":[
        "medical",
        "practitioner"
    ],
    "wof:name":"Paul Robert Dr",
    "wof:placetype":"venue"
},
  "geometry": {"coordinates":[115.829772949,-31.943567276],"type":"Point"}
}