{
  "type": "Feature",
  "properties": {
    "addr:full":"217 Barrington St Bibra Lake WA 6163",
    "addr:housenumber":"217",
    "addr:postcode":"6163",
    "addr:street":"Barrington St",
    "iso:country":"AU",
    "sg:address":"217 Barrington St",
    "sg:city":"Bibra Lake",
    "sg:classifiers":[
        {
            "category":"Wholesale",
            "subcategory":"Durable Goods & Equipment",
            "type":"Manufacturing & Wholesale Goods"
        }
    ],
    "sg:phone":"+61 8 9434 1134",
    "sg:postcode":"6163",
    "sg:province":"WA",
    "sg:tags":[
        "abrasive",
        "blasting"
    ],
    "wof:name":"Phoenix Corrosion Control",
    "wof:placetype":"venue"
},
  "geometry": {"coordinates":[115.811401,-32.116741],"type":"Point"}
}