{
  "type": "Feature",
  "properties": {
    "addr:full":"114 Drummond St Bedford WA 6052",
    "addr:housenumber":"114",
    "addr:postcode":"6052",
    "addr:street":"Drummond St",
    "iso:country":"AU",
    "sg:address":"114 Drummond St",
    "sg:city":"Bedford",
    "sg:classifiers":[
        {
            "category":"Building & Trades",
            "subcategory":"Equipment Rental",
            "type":"Services"
        }
    ],
    "sg:phone":"+61 419 854 265",
    "sg:postcode":"6052",
    "sg:province":"WA",
    "sg:tags":[
        "crane",
        "hire"
    ],
    "wof:name":"S & M Veenstra Truck & Hiab Hire",
    "wof:placetype":"venue"
},
  "geometry": {"coordinates":[115.88746643099999,-31.9084358215],"type":"Point"}
}