{
  "type": "Feature",
  "properties": {
    "addr:full":"1 / 5 Dendy St Brighton VIC 3186",
    "addr:housenumber":"/ 5",
    "addr:postcode":"3186",
    "addr:street":"Dendy St",
    "iso:country":"AU",
    "sg:address":"1 / 5 Dendy St",
    "sg:city":"Brighton",
    "sg:classifiers":[
        {
            "category":"Building & Trades",
            "subcategory":"Cleaning & Sanitation",
            "type":"Services"
        }
    ],
    "sg:phone":"+61 417 772 273",
    "sg:postcode":"3186",
    "sg:province":"VIC",
    "sg:tags":[
        "window"
    ],
    "wof:name":"A Divine Shine",
    "wof:placetype":"venue"
},
  "geometry": {"coordinates":[144.98944091800001,-37.9188842773],"type":"Point"}
}