{
  "type": "Feature",
  "properties": {
    "addr:full":"Private Medical Centre RMH, Suite 3, Royal Parade Parkville VIC 3052",
    "addr:housenumber":"3",
    "addr:postcode":"3052",
    "addr:street":"Royal Parade",
    "iso:country":"AU",
    "sg:address":"Private Medical Centre RMH, Suite 3, Royal Parade",
    "sg:city":"Parkville",
    "sg:classifiers":[
        {
            "category":"Health Services",
            "subcategory":"Doctor",
            "type":"Services"
        }
    ],
    "sg:phone":"+61 3 9347 5722",
    "sg:postcode":"3052",
    "sg:province":"VIC",
    "sg:tags":[
        "medical",
        "practitioner"
    ],
    "wof:name":"Atkinson Noel R",
    "wof:placetype":"venue"
},
  "geometry": {"coordinates":[144.957595825,-37.7969017029],"type":"Point"}
}