{
  "type": "Feature",
  "properties": {
    "iso:country":"AU",
    "sg:address":"PO Box 115",
    "sg:city":"Wilston",
    "sg:classifiers":[
        {
            "category":"Building & Trades",
            "subcategory":"Landscaping Services",
            "type":"Services"
        }
    ],
    "sg:phone":"+61 7 3357 5850",
    "sg:postcode":"4051",
    "sg:province":"QLD",
    "sg:tags":[
        "architect",
        "landscape"
    ],
    "wof:name":"Out & Out Landscape Design",
    "wof:placetype":"venue"
},
  "geometry": {"coordinates":[153.019622803,-27.4321994781],"type":"Point"}
}