{
  "type": "Feature",
  "properties": {
    "iso:country":"AU",
    "sg:address":"158 Sutton St",
    "sg:city":"Warragul",
    "sg:classifiers":[
        {
            "category":"Professional",
            "subcategory":"Art Services",
            "type":"Services"
        }
    ],
    "sg:phone":"+61 3 5622 1893",
    "sg:postcode":"3820",
    "sg:province":"VIC",
    "sg:tags":[
        "decorator",
        "painter"
    ],
    "wof:name":"J L W Painting & Decorating",
    "wof:placetype":"venue"
},
  "geometry": {"coordinates":[145.938553,-38.153084],"type":"Point"}
}