{
  "type": "Feature",
  "properties": {
    "addr:full":"33 Myall St Oatley NSW 2223",
    "addr:housenumber":"33",
    "addr:postcode":"2223",
    "addr:street":"Myall St",
    "iso:country":"AU",
    "sg:address":"33 Myall St",
    "sg:city":"Oatley",
    "sg:classifiers":[
        {
            "category":"Professional",
            "subcategory":"Computer Services",
            "type":"Services"
        }
    ],
    "sg:phone":"+61 2 9580 3837",
    "sg:postcode":"2223",
    "sg:province":"NSW",
    "sg:tags":[
        "on-line",
        "provider"
    ],
    "wof:name":"D G Systems Pty Ltd",
    "wof:placetype":"venue"
},
  "geometry": {"coordinates":[151.07388305699999,-33.9748344421],"type":"Point"}
}