{
  "type": "Feature",
  "properties": {
    "addr:full":"26 Griffe St Nakara NT 0810",
    "addr:housenumber":"26",
    "addr:postcode":"nt 0810",
    "addr:street":"Griffe St",
    "iso:country":"AU",
    "sg:address":"26 Griffe St",
    "sg:city":"Nakara",
    "sg:classifiers":[
        {
            "category":"Personal",
            "subcategory":"Nail Salon",
            "type":"Services"
        }
    ],
    "sg:phone":"+61 8 8945 9510",
    "sg:postcode":"0810",
    "sg:province":"NT",
    "sg:tags":[
        "artificial"
    ],
    "wof:name":"Vanida's Studio",
    "wof:placetype":"venue"
},
  "geometry": {"coordinates":[130.87530517600001,-12.3679132462],"type":"Point"}
}