{
  "type": "Feature",
  "properties": {
    "addr:full":"Helm St Kangaroo Flat VIC 3555",
    "addr:postcode":"3555",
    "addr:street":"Helm St",
    "iso:country":"AU",
    "sg:address":"Helm St",
    "sg:city":"Kangaroo Flat",
    "sg:classifiers":[
        {
            "category":"Retail",
            "subcategory":"Funeral Services",
            "type":"Services"
        }
    ],
    "sg:phone":"+61 3 5446 1566",
    "sg:postcode":"3555",
    "sg:province":"VIC",
    "sg:tags":[
        "cemetery"
    ],
    "wof:name":"Kangaroo Flat Cemetery",
    "wof:placetype":"venue"
},
  "geometry": {"coordinates":[144.23942565900001,-36.7968215942],"type":"Point"}
}