{
  "type": "Feature",
  "properties": {
    "iso:country":"AU",
    "sg:address":"470 Ipswich Rd",
    "sg:city":"Annerley",
    "sg:classifiers":[
        {
            "category":"Shopping",
            "subcategory":"Clothing, Apparel, & Fashions",
            "type":"Retail Goods"
        }
    ],
    "sg:phone":"+61 7 3892 6202",
    "sg:postcode":"4103",
    "sg:province":"QLD",
    "sg:tags":[
        "recycled",
        "clothing"
    ],
    "wof:name":"Aid For The Blind Op Shop",
    "wof:placetype":"venue"
},
  "geometry": {"coordinates":[153.03282165499999,-27.5101013184],"type":"Point"}
}