{
  "type": "Feature",
  "properties": {
    "iso:country":"AU",
    "sg:address":"Building B, Level 3 480 Victoria Rd",
    "sg:city":"Gladesville",
    "sg:classifiers":[
        {
            "category":"Utilities",
            "subcategory":"Telephone",
            "type":"Services"
        }
    ],
    "sg:phone":"+61 2 9879 8400",
    "sg:postcode":"2111",
    "sg:province":"NSW",
    "sg:tags":[
        "installation",
        "system",
        "maintenance"
    ],
    "wof:name":"Downer Engineering",
    "wof:placetype":"venue"
},
  "geometry": {"coordinates":[151.120651245,-33.8215560913],"type":"Point"}
}