{
  "type": "Feature",
  "properties": {
    "addr:full":"16 Canfield Crs Traralgon VIC 3844",
    "addr:housenumber":"16",
    "addr:postcode":"3844",
    "addr:street":"Canfield Crs",
    "iso:country":"AU",
    "sg:address":"16 Canfield Crs",
    "sg:city":"Traralgon",
    "sg:classifiers":[
        {
            "category":"Professional",
            "subcategory":"Accounting & Tax Preparation",
            "type":"Services"
        }
    ],
    "sg:phone":"+61 3 5174 2620",
    "sg:postcode":"3844",
    "sg:province":"VIC",
    "sg:tags":[
        "accountant",
        "auditor"
    ],
    "wof:name":"Gwenda Kerr",
    "wof:placetype":"venue"
},
  "geometry": {"coordinates":[146.53814697300001,-38.1949501038],"type":"Point"}
}