{
  "type": "Feature",
  "properties": {
    "addr:full":"Lot 213 Melbourne St Moora WA 6510",
    "addr:postcode":"6510",
    "addr:street":"Melbourne St",
    "iso:country":"AU",
    "sg:address":"Lot 213 Melbourne St",
    "sg:city":"Moora",
    "sg:classifiers":[
        {
            "category":"Wholesale",
            "subcategory":"Machinery & Supplies",
            "type":"Manufacturing & Wholesale Goods"
        }
    ],
    "sg:phone":"+61 438 413 182",
    "sg:postcode":"6510",
    "sg:province":"WA",
    "sg:tags":[
        "agricultural"
    ],
    "wof:name":"Harvest Clean",
    "wof:placetype":"venue"
},
  "geometry": {"coordinates":[116.01088,-30.639824],"type":"Point"}
}