{
  "type": "Feature",
  "properties": {
    "addr:full":"4/ 210 Scott St Cairns QLD 4870",
    "addr:housenumber":"/ 210",
    "addr:postcode":"4870",
    "addr:street":"Scott St",
    "iso:country":"AU",
    "sg:address":"4/ 210 Scott St",
    "sg:city":"Cairns",
    "sg:classifiers":[
        {
            "category":"Professional",
            "subcategory":"Computer Services",
            "type":"Services"
        }
    ],
    "sg:phone":"+61 7 4047 8810",
    "sg:postcode":"4870",
    "sg:province":"QLD",
    "sg:tags":[
        "tele-communications",
        "consultant"
    ],
    "wof:name":"Silcar Communications",
    "wof:placetype":"venue"
},
  "geometry": {"coordinates":[145.75094604500001,-16.9410743713],"type":"Point"}
}