{
  "type": "Feature",
  "properties": {
    "iso:country":"AU",
    "sg:address":"Garden City House 125 Riseley St",
    "sg:city":"Booragoon",
    "sg:classifiers":[
        {
            "category":"Health Services",
            "subcategory":"Doctor",
            "type":"Services"
        }
    ],
    "sg:phone":"+61 8 9364 7858",
    "sg:postcode":"6154",
    "sg:province":"WA",
    "sg:tags":[
        "medical",
        "practitioner"
    ],
    "wof:name":"Battino R A",
    "wof:placetype":"venue"
},
  "geometry": {"coordinates":[115.83802,-32.032337],"type":"Point"}
}