{
  "type": "Feature",
  "properties": {
    "iso:country":"AU",
    "sg:address":"85 Mell Rd",
    "sg:city":"Spearwood",
    "sg:classifiers":[
        {
            "category":"Education",
            "subcategory":"Special Training",
            "type":"Public Place"
        }
    ],
    "sg:phone":"+61 8 9434 3744",
    "sg:postcode":"6163",
    "sg:province":"WA",
    "sg:tags":[
        "development"
    ],
    "sg:website":"http://www.astpl.com",
    "wof:name":"Australian Skills Training",
    "wof:placetype":"venue"
},
  "geometry": {"coordinates":[115.779457,-32.104671],"type":"Point"}
}