{
  "type": "Feature",
  "properties": {
    "iso:country":"AU",
    "sg:address":"Fox Island Rd",
    "sg:city":"Gunbower",
    "sg:classifiers":[
        {
            "category":"Farming",
            "subcategory":"Farm",
            "type":"Manufacturing & Wholesale Goods"
        }
    ],
    "sg:phone":"+61 3 5487 1264",
    "sg:postcode":"3566",
    "sg:province":"VIC",
    "sg:tags":[
        "farmer"
    ],
    "wof:name":"Jones G M&F L",
    "wof:placetype":"venue"
},
  "geometry": {"coordinates":[144.363281,-35.95607],"type":"Point"}
}