{
  "type": "Feature",
  "properties": {
    "addr:full":"25- 37 Jarvis Rd Elizabeth Vale SA 5112",
    "addr:housenumber":"37",
    "addr:postcode":"5112",
    "addr:street":"Jarvis Rd",
    "iso:country":"AU",
    "sg:address":"25- 37 Jarvis Rd",
    "sg:city":"Elizabeth Vale",
    "sg:classifiers":[
        {
            "category":"Health Services",
            "subcategory":"Doctor",
            "type":"Services"
        }
    ],
    "sg:phone":"+61 8 8250 9050",
    "sg:postcode":"5112",
    "sg:province":"SA",
    "sg:tags":[
        "medical",
        "practitioner"
    ],
    "wof:name":"Limaye S B Dr",
    "wof:placetype":"venue"
},
  "geometry": {"coordinates":[138.655685425,-34.7546539307],"type":"Point"}
}