{
  "type": "Feature",
  "properties": {
    "iso:country":"AU",
    "sg:address":"Lot 6/ 3 Appin Pl St",
    "sg:city":"Marys",
    "sg:classifiers":[
        {
            "category":"Building & Trades",
            "subcategory":"Construction",
            "type":"Services"
        }
    ],
    "sg:phone":"+61 2 9833 1350",
    "sg:postcode":"2760",
    "sg:province":"NSW",
    "sg:tags":[
        "fencing",
        "contractor"
    ],
    "wof:name":"Gel Constructions",
    "wof:placetype":"venue"
},
  "geometry": {"coordinates":[150.770355225,-33.7418479919],"type":"Point"}
}