{
  "type": "Feature",
  "properties": {
    "iso:country":"AU",
    "sg:address":"28 Fielding St",
    "sg:city":"Gayndah",
    "sg:classifiers":[
        {
            "category":"Education",
            "subcategory":"Kindergarten",
            "type":"Public Place"
        }
    ],
    "sg:phone":"+61 7 4161 1244",
    "sg:postcode":"4625",
    "sg:province":"QLD",
    "sg:tags":[
        "pre-schools"
    ],
    "wof:name":"Gayndah Kindergarten Association",
    "wof:placetype":"venue"
},
  "geometry": {"coordinates":[151.603607,-25.628746],"type":"Point"}
}