{
  "type": "Feature",
  "properties": {
    "addr:full":"160 York St Albany WA 6330",
    "addr:housenumber":"160",
    "addr:postcode":"6330",
    "addr:street":"York St",
    "iso:country":"AU",
    "sg:address":"160 York St",
    "sg:city":"Albany",
    "sg:classifiers":[
        {
            "category":"Shopping",
            "subcategory":"Music",
            "type":"Retail Goods"
        }
    ],
    "sg:phone":"+61 8 9841 8597",
    "sg:postcode":"6330",
    "sg:province":"WA",
    "sg:tags":[
        "store"
    ],
    "wof:name":"Leading Edge Music",
    "wof:placetype":"venue"
},
  "geometry": {"coordinates":[117.88392639200001,-35.0254745483],"type":"Point"}
}