{
  "type": "Feature",
  "properties": {
    "addr:full":"Shop 6, Regency Plaza Shopng Cntr Cnr Beaudesert & Regents Park QLD 4118",
    "addr:housenumber":"shop 6",
    "addr:postcode":"beaudesert;4118",
    "addr:street":"Regency Plaza Shopng Cntr Cnr",
    "iso:country":"AU",
    "sg:address":"Shop 6, Regency Plaza Shopng Cntr Cnr Beaudesert &",
    "sg:city":"Regents Park",
    "sg:classifiers":[
        {
            "category":"Personal",
            "subcategory":"Beauty Salon",
            "type":"Services"
        }
    ],
    "sg:phone":"+61 7 3800 3489",
    "sg:postcode":"4118",
    "sg:province":"QLD",
    "sg:tags":[
        "hairdresser"
    ],
    "wof:name":"Regency In Vogue Hair Design",
    "wof:placetype":"venue"
},
  "geometry": {"coordinates":[153.04530334500001,-27.6703472137],"type":"Point"}
}