{
  "type": "Feature",
  "properties": {
    "iso:country":"AU",
    "sg:address":"119- 121 The Entrance Rd",
    "sg:city":"The Entrance",
    "sg:classifiers":[
        {
            "category":"Food & Beverages",
            "subcategory":"Bakery",
            "type":"Retail Goods"
        }
    ],
    "sg:phone":"+61 2 4333 5556",
    "sg:postcode":"2261",
    "sg:province":"NSW",
    "sg:tags":[
        "cake",
        "shop",
        "pastry"
    ],
    "wof:name":"Cold Rock Ice Creamery",
    "wof:placetype":"venue"
},
  "geometry": {"coordinates":[151.494675,-33.345848],"type":"Point"}
}