{
  "type": "Feature",
  "properties": {
    "addr:full":"160 New Town Rd New Town TAS 7008",
    "addr:housenumber":"160",
    "addr:postcode":"7008",
    "addr:street":"New Town Rd",
    "iso:country":"AU",
    "sg:address":"160 New Town Rd",
    "sg:city":"New Town",
    "sg:classifiers":[
        {
            "category":"Government",
            "subcategory":"Court House",
            "type":"Public Place"
        }
    ],
    "sg:phone":"+61 3 6228 0313",
    "sg:postcode":"7008",
    "sg:province":"TAS",
    "sg:tags":[
        "personal",
        "marriage",
        "family",
        "counselling"
    ],
    "wof:name":"Lifeline Hobart Inc",
    "wof:placetype":"venue"
},
  "geometry": {"coordinates":[147.30480957,-42.8590507507],"type":"Point"}
}