{
  "type": "Feature",
  "properties": {
    "iso:country":"AU",
    "sg:address":"Cnr Railway & Albert Sts",
    "sg:city":"Wickham",
    "sg:classifiers":[
        {
            "category":"Home & Garden",
            "subcategory":"Carpets & Floor Coverings",
            "type":"Retail Goods"
        }
    ],
    "sg:phone":"+61 2 4962 2477",
    "sg:postcode":"2293",
    "sg:province":"NSW",
    "sg:tags":[
        "tile",
        "wall"
    ],
    "wof:name":"Indent Trading",
    "wof:placetype":"venue"
},
  "geometry": {"coordinates":[151.75677490199999,-32.9197235107],"type":"Point"}
}