{
  "type": "Feature",
  "properties": {
    "addr:full":"U11 9 Milford St East Victoria Park WA 6101",
    "addr:housenumber":"u11 9",
    "addr:postcode":"6101",
    "addr:street":"Milford St",
    "iso:country":"AU",
    "sg:address":"U11 9 Milford St",
    "sg:city":"East Victoria Park",
    "sg:classifiers":[
        {
            "category":"Professional",
            "subcategory":"Accounting & Tax Preparation",
            "type":"Services"
        }
    ],
    "sg:phone":"+61 8 9472 4321",
    "sg:postcode":"6101",
    "sg:province":"WA",
    "sg:tags":[
        "jukebox"
    ],
    "wof:name":"A AAAB Amusements Party Hire",
    "wof:placetype":"venue"
},
  "geometry": {"coordinates":[115.915359497,-31.9908828735],"type":"Point"}
}