{
  "type": "Feature",
  "properties": {
    "addr:full":"116 Charles Ave Minnamurra NSW 2533",
    "addr:housenumber":"116",
    "addr:postcode":"2533",
    "addr:street":"Charles Ave",
    "iso:country":"AU",
    "sg:address":"116 Charles Ave",
    "sg:city":"Minnamurra",
    "sg:classifiers":[
        {
            "category":"Personal",
            "subcategory":"Beauty Salon",
            "type":"Services"
        }
    ],
    "sg:phone":"+61 2 4237 7270",
    "sg:postcode":"2533",
    "sg:province":"NSW",
    "sg:tags":[
        "hairdresser"
    ],
    "wof:name":"Janice Robyn Hair Stylist",
    "wof:placetype":"venue"
},
  "geometry": {"coordinates":[150.85145568900001,-34.6211166382],"type":"Point"}
}