{
  "type": "Feature",
  "properties": {
    "addr:full":"6 Alice St Jannali NSW 2226",
    "addr:housenumber":"6",
    "addr:postcode":"2226",
    "addr:street":"Alice St",
    "iso:country":"AU",
    "sg:address":"6 Alice St",
    "sg:city":"Jannali",
    "sg:classifiers":[
        {
            "category":"Education",
            "subcategory":"Kindergarten",
            "type":"Public Place"
        }
    ],
    "sg:phone":"+61 2 9528 4422",
    "sg:postcode":"2226",
    "sg:province":"NSW",
    "sg:tags":[
        "pre-schools"
    ],
    "wof:name":"Jannali Pre School Kindergarten",
    "wof:placetype":"venue"
},
  "geometry": {"coordinates":[151.06394958499999,-34.0185813904],"type":"Point"}
}