{
  "type": "Feature",
  "properties": {
    "iso:country":"AU",
    "sg:address":"116 Parkes St",
    "sg:city":"Helensburgh",
    "sg:classifiers":[
        {
            "category":"Building & Trades",
            "subcategory":"Plumbing",
            "type":"Services"
        }
    ],
    "sg:phone":"+61 2 4294 2931",
    "sg:postcode":"2508",
    "sg:province":"NSW",
    "sg:tags":[
        "plumber",
        "gasfitters"
    ],
    "wof:name":"Andy Offord",
    "wof:placetype":"venue"
},
  "geometry": {"coordinates":[150.979492,-34.191059],"type":"Point"}
}