{
  "type": "Feature",
  "properties": {
    "addr:full":"55 Wilkes Crt Mernda VIC 3754",
    "addr:housenumber":"55",
    "addr:postcode":"3754",
    "addr:street":"Wilkes Crt",
    "iso:country":"AU",
    "sg:address":"55 Wilkes Crt",
    "sg:city":"Mernda",
    "sg:classifiers":[
        {
            "category":"Farming",
            "subcategory":"Nursery",
            "type":"Manufacturing & Wholesale Goods"
        }
    ],
    "sg:phone":"+61 3 9717 3484",
    "sg:postcode":"3754",
    "sg:province":"VIC",
    "wof:name":"Plantwize Nursery",
    "wof:placetype":"venue"
},
  "geometry": {"coordinates":[145.06303399999999,-37.577267],"type":"Point"}
}