{
  "type": "Feature",
  "properties": {
    "iso:country":"AU",
    "sg:address":"106 Hill St",
    "sg:city":"Toowoomba",
    "sg:classifiers":[
        {
            "category":"Shopping",
            "subcategory":"Antiques",
            "type":"Retail Goods"
        }
    ],
    "sg:phone":"+61 7 4637 9959",
    "sg:postcode":"4350",
    "sg:province":"QLD",
    "sg:tags":[
        "collectable",
        "memorabilia"
    ],
    "wof:name":"Lifeline's Once Was Collectable Shop",
    "wof:placetype":"venue"
},
  "geometry": {"coordinates":[151.93742399999999,-27.560596],"type":"Point"}
}