{
  "type": "Feature",
  "properties": {
    "iso:country":"AU",
    "sg:address":"342 Montague Rd",
    "sg:city":"West End",
    "sg:classifiers":[
        {
            "category":"Manufacturing",
            "subcategory":"Food",
            "type":"Manufacturing & Wholesale Goods"
        }
    ],
    "sg:phone":"+61 7 3844 8414",
    "sg:postcode":"4101",
    "sg:province":"QLD",
    "sg:tags":[
        "function",
        "catering"
    ],
    "wof:name":"Nicolas Fine Foods",
    "wof:placetype":"venue"
},
  "geometry": {"coordinates":[153.003631592,-27.4829673767],"type":"Point"}
}