{
  "type": "Feature",
  "properties": {
    "addr:full":"30 Ackworth Crs Warwick WA 6024",
    "addr:housenumber":"30",
    "addr:postcode":"6024",
    "addr:street":"Ackworth Crs",
    "iso:country":"AU",
    "sg:address":"30 Ackworth Crs",
    "sg:city":"Warwick",
    "sg:classifiers":[
        {
            "category":"Professional",
            "subcategory":"Accounting & Tax Preparation",
            "type":"Services"
        }
    ],
    "sg:phone":"+61 8 9448 1156",
    "sg:postcode":"6024",
    "sg:province":"WA",
    "sg:tags":[
        "bookkeeping"
    ],
    "wof:name":"Edwards Bookkeeping",
    "wof:placetype":"venue"
},
  "geometry": {"coordinates":[115.80818176299999,-31.844959259],"type":"Point"}
}