{
  "type": "Feature",
  "properties": {
    "addr:full":"79 Bowen St Goondiwindi QLD 4390",
    "addr:housenumber":"79",
    "addr:postcode":"4390",
    "addr:street":"Bowen St",
    "iso:country":"AU",
    "sg:address":"79 Bowen St",
    "sg:city":"Goondiwindi",
    "sg:classifiers":[
        {
            "category":"Shopping",
            "subcategory":"Bicycles & Sporting Goods",
            "type":"Retail Goods"
        }
    ],
    "sg:phone":"+61 7 4671 4323",
    "sg:postcode":"4390",
    "sg:province":"QLD",
    "sg:tags":[
        "chemical",
        "equipment",
        "pool",
        "swimming"
    ],
    "wof:name":"Katmar Pools And Landscaping Pty Ltd",
    "wof:placetype":"venue"
},
  "geometry": {"coordinates":[150.310913086,-28.5486736298],"type":"Point"}
}