{
  "type": "Feature",
  "properties": {
    "addr:full":"36 Bantry Bay Rd Frenchs Forest NSW 2086",
    "addr:housenumber":"36",
    "addr:postcode":"2086",
    "addr:street":"Bantry Bay Rd",
    "iso:country":"AU",
    "sg:address":"36 Bantry Bay Rd",
    "sg:city":"Frenchs Forest",
    "sg:classifiers":[
        {
            "category":"Fast Food",
            "type":"Food & Drink"
        }
    ],
    "sg:phone":"+61 2 9453 9499",
    "sg:postcode":"2086",
    "sg:province":"NSW",
    "sg:tags":[
        "away",
        "take"
    ],
    "wof:name":"Two J's Cafe And Take Away",
    "wof:placetype":"venue"
},
  "geometry": {"coordinates":[151.23306274399999,-33.7513847351],"type":"Point"}
}