{
  "type": "Feature",
  "properties": {
    "addr:full":"621 Airport Ave Bankstown Airport NSW 2200",
    "addr:housenumber":"621",
    "addr:postcode":"2200",
    "addr:street":"Airport Ave",
    "iso:country":"AU",
    "sg:address":"621 Airport Ave",
    "sg:city":"Bankstown Airport",
    "sg:classifiers":[
        {
            "category":"Building & Trades",
            "subcategory":"Pest Control",
            "type":"Services"
        }
    ],
    "sg:phone":"+61 2 9791 0222",
    "sg:postcode":"2200",
    "sg:province":"NSW",
    "sg:tags":[
        "airport"
    ],
    "wof:name":"Concept Aviation Supplies Pty Ltd",
    "wof:placetype":"venue"
},
  "geometry": {"coordinates":[150.991455,-33.919544],"type":"Point"}
}