{
  "type": "Feature",
  "properties": {
    "iso:country":"AU",
    "sg:address":"140 Scarborough Beach Rd",
    "sg:city":"Mt Hawthorn",
    "sg:classifiers":[
        {
            "category":"Building & Trades",
            "subcategory":"Construction",
            "type":"Services"
        }
    ],
    "sg:phone":"+61 8 9443 9077",
    "sg:postcode":"6016",
    "sg:province":"WA",
    "sg:tags":[
        "contractor"
    ],
    "wof:name":"Nova Homes WA",
    "wof:placetype":"venue"
},
  "geometry": {"coordinates":[115.83988952599999,-31.9217586517],"type":"Point"}
}