{
  "type": "Feature",
  "properties": {
    "addr:full":"2 Princes Ave Caulfield East VIC 3145",
    "addr:housenumber":"2",
    "addr:postcode":"3145",
    "addr:street":"Princes Ave",
    "iso:country":"AU",
    "sg:address":"2 Princes Ave",
    "sg:city":"Caulfield East",
    "sg:classifiers":[
        {
            "category":"Retail",
            "subcategory":"Event Space",
            "type":"Services"
        }
    ],
    "sg:phone":"+61 3 9903 2596",
    "sg:postcode":"3145",
    "sg:province":"VIC",
    "sg:tags":[
        "function",
        "organiser"
    ],
    "wof:name":"Chisholm Hall",
    "wof:placetype":"venue"
},
  "geometry": {"coordinates":[145.04301452600001,-37.8770332336],"type":"Point"}
}