{
  "type": "Feature",
  "properties": {
    "iso:country":"AU",
    "sg:address":"523 High St",
    "sg:city":"Preston",
    "sg:classifiers":[
        {
            "category":"Fast Food",
            "type":"Food & Drink"
        }
    ],
    "sg:phone":"+61 3 9470 1222",
    "sg:postcode":"3072",
    "sg:province":"VIC",
    "sg:tags":[
        "away",
        "take"
    ],
    "wof:name":"High On Burgers",
    "wof:placetype":"venue"
},
  "geometry": {"coordinates":[145.004074097,-37.7363014221],"type":"Point"}
}