{
  "type": "Feature",
  "properties": {
    "addr:full":"Unit 1/89- 101 Factory Rd Oxley QLD 4075",
    "addr:housenumber":"101",
    "addr:postcode":"4075",
    "addr:street":"Factory Rd",
    "iso:country":"AU",
    "sg:address":"Unit 1/89- 101 Factory Rd",
    "sg:city":"Oxley",
    "sg:classifiers":[
        {
            "category":"Communications",
            "type":"Services"
        }
    ],
    "sg:phone":"+61 7 3278 6444",
    "sg:postcode":"4075",
    "sg:province":"QLD",
    "sg:tags":[
        "equipment",
        "radio"
    ],
    "wof:name":"Standard Communications Pty Ltd",
    "wof:placetype":"venue"
},
  "geometry": {"coordinates":[152.983932495,-27.5701236725],"type":"Point"}
}