{
  "type": "Feature",
  "properties": {
    "addr:full":"144 Jacksons Rd Noble Park VIC 3174",
    "addr:housenumber":"144",
    "addr:postcode":"3174",
    "addr:street":"Jacksons Rd",
    "iso:country":"AU",
    "sg:address":"144 Jacksons Rd",
    "sg:city":"Noble Park",
    "sg:classifiers":[
        {
            "category":"Building & Trades",
            "subcategory":"Cleaning & Sanitation",
            "type":"Services"
        }
    ],
    "sg:phone":"+61 3 9774 8883",
    "sg:postcode":"3174",
    "sg:province":"VIC",
    "sg:tags":[
        "cleaner",
        "repairer",
        "roof"
    ],
    "wof:name":"The Price is Right Roofing",
    "wof:placetype":"venue"
},
  "geometry": {"coordinates":[145.19200134299999,-37.9432678223],"type":"Point"}
}