{
  "type": "Feature",
  "properties": {
    "addr:full":"Level 1/ 320 Urana Rd Lavington NSW 2641",
    "addr:housenumber":"/ 320",
    "addr:postcode":"2641",
    "addr:street":"Urana Rd",
    "iso:country":"AU",
    "sg:address":"Level 1/ 320 Urana Rd",
    "sg:city":"Lavington",
    "sg:classifiers":[
        {
            "category":"Organizations",
            "subcategory":"Professional Association",
            "type":"Services"
        }
    ],
    "sg:phone":"+61 2 6025 8455",
    "sg:postcode":"2641",
    "sg:province":"NSW",
    "sg:tags":[
        "organisation",
        "business"
    ],
    "wof:name":"Business Enterprise Centre Murray Home Professional",
    "wof:placetype":"venue"
},
  "geometry": {"coordinates":[146.93295288100001,-36.0512886047],"type":"Point"}
}