{
  "type": "Feature",
  "properties": {
    "addr:full":"President Ave Andrews Farm SA 5114",
    "addr:postcode":"5114",
    "addr:street":"President Ave Andrews",
    "iso:country":"AU",
    "sg:address":"President Ave",
    "sg:city":"Andrews Farm",
    "sg:classifiers":[
        {
            "category":"Building & Trades",
            "subcategory":"Construction",
            "type":"Services"
        }
    ],
    "sg:phone":"+61 8 8254 2299",
    "sg:postcode":"5114",
    "sg:province":"SA",
    "sg:tags":[
        "contractor"
    ],
    "wof:name":"Hickinbotham Homes Pty Ltd",
    "wof:placetype":"venue"
},
  "geometry": {"coordinates":[138.66484069800001,-34.6738777161],"type":"Point"}
}