{
  "type": "Feature",
  "properties": {
    "addr:full":"Shp1/ 45 Clarence St Sydney NSW 2000",
    "addr:housenumber":"45",
    "addr:postcode":"2000",
    "addr:street":"Clarence St",
    "iso:country":"AU",
    "sg:address":"Shp1/ 45 Clarence St",
    "sg:city":"Sydney",
    "sg:classifiers":[
        {
            "category":"Cafe",
            "type":"Food & Drink"
        }
    ],
    "sg:phone":"+61 2 9299 5218",
    "sg:postcode":"2000",
    "sg:province":"NSW",
    "wof:name":"Bar Xpresso",
    "wof:placetype":"venue"
},
  "geometry": {"coordinates":[151.20510864299999,-33.8659744263],"type":"Point"}
}