{
  "type": "Feature",
  "properties": {
    "addr:full":"Suite 101, 156 Pacific Hwy Greenwich NSW 2065",
    "addr:housenumber":"156",
    "addr:postcode":"2065",
    "addr:street":"Pacific Hwy",
    "iso:country":"AU",
    "sg:address":"Suite 101, 156 Pacific Hwy",
    "sg:city":"Greenwich",
    "sg:classifiers":[
        {
            "category":"Professional",
            "subcategory":"Research",
            "type":"Services"
        }
    ],
    "sg:phone":"+61 2 9436 3800",
    "sg:postcode":"2065",
    "sg:province":"NSW",
    "sg:tags":[
        "market"
    ],
    "wof:name":"Field Force Pty Ltd",
    "wof:placetype":"venue"
},
  "geometry": {"coordinates":[151.18771362300001,-33.824344635],"type":"Point"}
}