{
  "type": "Feature",
  "properties": {
    "addr:full":"52 Settlement Rd Bundoora VIC 3083",
    "addr:housenumber":"52",
    "addr:postcode":"3083",
    "addr:street":"Settlement Rd",
    "iso:country":"AU",
    "sg:address":"52 Settlement Rd",
    "sg:city":"Bundoora",
    "sg:classifiers":[
        {
            "category":"Professional",
            "subcategory":"Accounting & Tax Preparation",
            "type":"Services"
        }
    ],
    "sg:phone":"+61 3 9467 7842",
    "sg:postcode":"3083",
    "sg:province":"VIC",
    "sg:tags":[
        "accountant",
        "auditor"
    ],
    "wof:name":"Georgy M",
    "wof:placetype":"venue"
},
  "geometry": {"coordinates":[145.054290772,-37.6971702576],"type":"Point"}
}