{
  "type": "Feature",
  "properties": {
    "addr:full":"182 Fulham Rd Gulliver QLD 4812",
    "addr:housenumber":"182",
    "addr:postcode":"4812",
    "addr:street":"Fulham Rd",
    "iso:country":"AU",
    "sg:address":"182 Fulham Rd",
    "sg:city":"Gulliver",
    "sg:classifiers":[
        {
            "category":"Health Services",
            "subcategory":"Health Practitioner",
            "type":"Services"
        }
    ],
    "sg:phone":"+61 7 4775 5755",
    "sg:postcode":"4812",
    "sg:province":"QLD",
    "sg:tags":[
        "osteopath"
    ],
    "wof:name":"Lamb, Peter",
    "wof:placetype":"venue"
},
  "geometry": {"coordinates":[146.76980599999999,-19.288845],"type":"Point"}
}