{
  "type": "Feature",
  "properties": {
    "addr:full":"422- 430 Swan St Richmond VIC 3121",
    "addr:housenumber":"430",
    "addr:postcode":"3121",
    "addr:street":"Swan St",
    "iso:country":"AU",
    "sg:address":"422- 430 Swan St",
    "sg:city":"Richmond",
    "sg:classifiers":[
        {
            "category":"Retail",
            "subcategory":"Storage",
            "type":"Services"
        }
    ],
    "sg:phone":"+61 3 9427 9300",
    "sg:postcode":"3121",
    "sg:province":"VIC",
    "wof:name":"Guardian Storage",
    "wof:placetype":"venue"
},
  "geometry": {"coordinates":[145.00596618599999,-37.8266487122],"type":"Point"}
}