{
  "type": "Feature",
  "properties": {
    "addr:full":"Unit 11 / 2 Collin St West Perth WA 6005",
    "addr:housenumber":"/ 2",
    "addr:postcode":"6005",
    "addr:street":"Collin St",
    "iso:country":"AU",
    "sg:address":"Unit 11 / 2 Collin St",
    "sg:city":"West Perth",
    "sg:classifiers":[
        {
            "category":"Education",
            "subcategory":"Special Training",
            "type":"Public Place"
        }
    ],
    "sg:phone":"+61 8 9226 1958",
    "sg:postcode":"6005",
    "sg:province":"WA",
    "sg:tags":[
        "development"
    ],
    "wof:name":"D.E. Tomkinson Pty Ltd",
    "wof:placetype":"venue"
},
  "geometry": {"coordinates":[115.840759277,-31.9521503448],"type":"Point"}
}