{
  "type": "Feature",
  "properties": {
    "addr:full":"5 Hale Ave Nowra NSW 2541",
    "addr:housenumber":"5",
    "addr:postcode":"2541",
    "addr:street":"Hale Ave",
    "iso:country":"AU",
    "sg:address":"5 Hale Ave",
    "sg:city":"Nowra",
    "sg:classifiers":[
        {
            "category":"Building & Trades",
            "subcategory":"Cleaning & Sanitation",
            "type":"Services"
        }
    ],
    "sg:phone":"+61 2 4421 4451",
    "sg:postcode":"2541",
    "sg:province":"NSW",
    "sg:tags":[
        "window"
    ],
    "wof:name":"Tony's Window Cleaning Service",
    "wof:placetype":"venue"
},
  "geometry": {"coordinates":[150.599365234,-34.8852119446],"type":"Point"}
}