{
  "type": "Feature",
  "properties": {
    "addr:full":"Cnr Golden Gve & Grenfell Rds Surrey Downs SA 5126",
    "addr:postcode":"5126",
    "addr:street":"Cnr Golden",
    "iso:country":"AU",
    "sg:address":"Cnr Golden Gve & Grenfell Rds",
    "sg:city":"Surrey Downs",
    "sg:classifiers":[
        {
            "category":"Health Services",
            "subcategory":"Dentist",
            "type":"Services"
        }
    ],
    "sg:phone":"+61 8 8251 2344",
    "sg:postcode":"5126",
    "sg:province":"SA",
    "wof:name":"Family Dental Centre",
    "wof:placetype":"venue"
},
  "geometry": {"coordinates":[138.70602417000001,-34.8061332703],"type":"Point"}
}