{
  "type": "Feature",
  "properties": {
    "iso:country":"AU",
    "sg:address":"63 Maude St",
    "sg:city":"Victor Harbor",
    "sg:classifiers":[
        {
            "category":"Autos & Motor Vehicles",
            "subcategory":"Automobile Sales",
            "type":"Retail Goods"
        }
    ],
    "sg:phone":"+61 8 8552 1519",
    "sg:postcode":"5211",
    "sg:province":"SA",
    "sg:tags":[
        "car",
        "used"
    ],
    "wof:name":"Victor Harbor Used Cars",
    "wof:placetype":"venue"
},
  "geometry": {"coordinates":[138.60179138199999,-35.5598487854],"type":"Point"}
}