{
  "type": "Feature",
  "properties": {
    "addr:full":"Shop 3 Heathridge Shopping Cntr 89 Caridean St Heathridge WA 6027",
    "addr:housenumber":"shop 3;89",
    "addr:postcode":"6027",
    "addr:street":"Shopping Cntr;St",
    "iso:country":"AU",
    "sg:address":"Shop 3 Heathridge Shopping Cntr 89 Caridean St",
    "sg:city":"Heathridge",
    "sg:classifiers":[
        {
            "category":"Personal",
            "subcategory":"Beauty Salon",
            "type":"Services"
        }
    ],
    "sg:phone":"+61 8 9307 5794",
    "sg:postcode":"6027",
    "sg:province":"WA",
    "sg:tags":[
        "hairdresser"
    ],
    "wof:name":"Cutting Crew",
    "wof:placetype":"venue"
},
  "geometry": {"coordinates":[115.76252746599999,-31.7593135834],"type":"Point"}
}