{
  "type": "Feature",
  "properties": {
    "addr:full":"12 Triangle Crt Noarlunga Downs SA 5168",
    "addr:housenumber":"12",
    "addr:postcode":"5168",
    "addr:street":"Triangle Crt",
    "iso:country":"AU",
    "sg:address":"12 Triangle Crt",
    "sg:city":"Noarlunga Downs",
    "sg:classifiers":[
        {
            "category":"Building & Trades",
            "subcategory":"Plumbing",
            "type":"Services"
        }
    ],
    "sg:phone":"+61 419 804 698",
    "sg:postcode":"5168",
    "sg:province":"SA",
    "sg:tags":[
        "plumber",
        "gasfitters"
    ],
    "wof:name":"John Martin Plumbing & Property Maintenance",
    "wof:placetype":"venue"
},
  "geometry": {"coordinates":[138.501342773,-35.1568870544],"type":"Point"}
}