{
  "type": "Feature",
  "properties": {
    "addr:full":"U2/ 56 Harley St Strathdale VIC 3550",
    "addr:housenumber":"56",
    "addr:postcode":"3550",
    "addr:street":"U2 /;Harley St",
    "iso:country":"AU",
    "sg:address":"U2/ 56 Harley St",
    "sg:city":"Strathdale",
    "sg:classifiers":[
        {
            "category":"Sports & Exercise",
            "subcategory":"Gym",
            "type":"Entertainment"
        }
    ],
    "sg:phone":"+61 3 5444 5003",
    "sg:postcode":"3550",
    "sg:province":"VIC",
    "sg:tags":[
        "health",
        "fitness"
    ],
    "wof:name":"Trim & Tone",
    "wof:placetype":"venue"
},
  "geometry": {"coordinates":[144.31671142600001,-36.7724952698],"type":"Point"}
}