{
  "type": "Feature",
  "properties": {
    "iso:country":"AU",
    "sg:address":"30 Beaulieu Crs",
    "sg:city":"Carindale",
    "sg:classifiers":[
        {
            "category":"Home & Garden",
            "subcategory":"Carpets & Floor Coverings",
            "type":"Retail Goods"
        }
    ],
    "sg:phone":"+61 438 124 058",
    "sg:postcode":"4152",
    "sg:province":"QLD",
    "sg:tags":[
        "tile",
        "wall",
        "layer"
    ],
    "wof:name":"Fachin & Fachin Tiling Service",
    "wof:placetype":"venue"
},
  "geometry": {"coordinates":[153.102005005,-27.5056304932],"type":"Point"}
}