{
  "type": "Feature",
  "properties": {
    "addr:full":"2 The Kingsway St Cronulla NSW 2230",
    "addr:housenumber":"2",
    "addr:postcode":"2230",
    "addr:street":"The Kingsway St",
    "iso:country":"AU",
    "sg:address":"2 The Kingsway St",
    "sg:city":"Cronulla",
    "sg:classifiers":[
        {
            "category":"Restaurant",
            "type":"Food & Drink"
        }
    ],
    "sg:phone":"+61 2 9523 8888",
    "sg:postcode":"2230",
    "sg:province":"NSW",
    "wof:name":"Sealevel Restaurant",
    "wof:placetype":"venue"
},
  "geometry": {"coordinates":[151.153366089,-34.055229187],"type":"Point"}
}