{
  "type": "Feature",
  "properties": {
    "addr:full":"16 Production Pl Penrith NSW 2750",
    "addr:housenumber":"16",
    "addr:postcode":"2750",
    "addr:street":"Production Pl",
    "iso:country":"AU",
    "sg:address":"16 Production Pl",
    "sg:city":"Penrith",
    "sg:classifiers":[
        {
            "category":"Utilities",
            "subcategory":"Electric",
            "type":"Services"
        }
    ],
    "sg:phone":"+61 2 4731 1111",
    "sg:postcode":"2750",
    "sg:province":"NSW",
    "sg:tags":[
        "electrical",
        "contractor"
    ],
    "wof:name":"J & M Costa Enterprises Pty Ltd",
    "wof:placetype":"venue"
},
  "geometry": {"coordinates":[150.68463134800001,-33.7683525085],"type":"Point"}
}