{
  "type": "Feature",
  "properties": {
    "addr:full":"Suite 1, Ormond House, 109 Yarra St Geelong VIC 3220",
    "addr:housenumber":"109",
    "addr:postcode":"3220",
    "addr:street":"Yarra St",
    "iso:country":"AU",
    "sg:address":"Suite 1, Ormond House, 109 Yarra St",
    "sg:city":"Geelong",
    "sg:classifiers":[
        {
            "category":"Organizations",
            "subcategory":"Labor Organization",
            "type":"Services"
        }
    ],
    "sg:phone":"+61 3 5222 6633",
    "sg:postcode":"3220",
    "sg:province":"VIC",
    "sg:tags":[
        "union"
    ],
    "wof:name":"Australian Education Union Victorian Branch",
    "wof:placetype":"venue"
},
  "geometry": {"coordinates":[144.361954,-38.151237],"type":"Point"}
}