{
  "type": "Feature",
  "properties": {
    "iso:country":"AU",
    "sg:address":"47 Frome St",
    "sg:city":"Griffith",
    "sg:classifiers":[
        {
            "category":"Building & Trades",
            "subcategory":"Construction",
            "type":"Services"
        }
    ],
    "sg:phone":"+61 2 6239 7119",
    "sg:postcode":"2603",
    "sg:province":"ACT",
    "sg:tags":[
        "brick",
        "paving"
    ],
    "wof:name":"Focus Landscaping & Paving",
    "wof:placetype":"venue"
},
  "geometry": {"coordinates":[149.143676758,-35.3251495361],"type":"Point"}
}