{
  "type": "Feature",
  "properties": {
    "iso:country":"AU",
    "sg:address":"PO Box 2179",
    "sg:city":"Crestmead",
    "sg:classifiers":[
        {
            "category":"Commercial Area",
            "type":"Public Place"
        }
    ],
    "sg:phone":"+61 7 3386 0515",
    "sg:postcode":"4132",
    "sg:province":"QLD",
    "sg:tags":[
        "clothing",
        "label"
    ],
    "wof:name":"Cashs (Australia) Pty Ltd",
    "wof:placetype":"venue"
},
  "geometry": {"coordinates":[153.10435485799999,-27.6893997192],"type":"Point"}
}