{
  "type": "Feature",
  "properties": {
    "addr:full":"685 Main St Kangaroo Point QLD 4169",
    "addr:housenumber":"685",
    "addr:postcode":"4169",
    "addr:street":"Main St",
    "iso:country":"AU",
    "sg:address":"685 Main St",
    "sg:city":"Kangaroo Point",
    "sg:classifiers":[
        {
            "category":"Autos & Motor Vehicles",
            "subcategory":"Automobile Sales",
            "type":"Retail Goods"
        }
    ],
    "sg:phone":"+61 7 3391 8755",
    "sg:postcode":"4169",
    "sg:province":"QLD",
    "sg:tags":[
        "car",
        "used"
    ],
    "wof:name":"Nolan John Wholesale Cars",
    "wof:placetype":"venue"
},
  "geometry": {"coordinates":[153.03565979000001,-27.4808979034],"type":"Point"}
}