{
  "type": "Feature",
  "properties": {
    "addr:full":"146 Collier St Newdegate WA 6355",
    "addr:housenumber":"146",
    "addr:postcode":"6355",
    "addr:street":"Collier St",
    "iso:country":"AU",
    "sg:address":"146 Collier St",
    "sg:city":"Newdegate",
    "sg:classifiers":[
        {
            "category":"Wholesale",
            "subcategory":"Machinery & Supplies",
            "type":"Manufacturing & Wholesale Goods"
        }
    ],
    "sg:phone":"+61 8 9871 1514",
    "sg:postcode":"6355",
    "sg:province":"WA",
    "sg:tags":[
        "agricultural"
    ],
    "wof:name":"Hall G C & Co",
    "wof:placetype":"venue"
},
  "geometry": {"coordinates":[119.02343,-33.094368],"type":"Point"}
}