{
  "type": "Feature",
  "properties": {
    "iso:country":"AU",
    "sg:address":"12 Stapleton St",
    "sg:city":"Firle",
    "sg:classifiers":[
        {
            "category":"Utilities",
            "subcategory":"Electric",
            "type":"Services"
        }
    ],
    "sg:phone":"+61 8 8364 5331",
    "sg:postcode":"5070",
    "sg:province":"SA",
    "sg:tags":[
        "electrical",
        "contractor"
    ],
    "wof:name":"Peter Litchfield Electrical Services",
    "wof:placetype":"venue"
},
  "geometry": {"coordinates":[138.64996337900001,-34.9078102112],"type":"Point"}
}