{
  "type": "Feature",
  "properties": {
    "iso:country":"AU",
    "sg:address":"Unit 3a 2",
    "sg:city":"-8 Peninsula Blv Seaford",
    "sg:classifiers":[
        {
            "category":"Building & Trades",
            "subcategory":"Construction",
            "type":"Services"
        }
    ],
    "sg:phone":"+61 3 9786 0400",
    "sg:postcode":"3198",
    "sg:province":"VIC",
    "sg:tags":[
        "roof"
    ],
    "wof:name":"Meridian Roofing Pty Ltd",
    "wof:placetype":"venue"
},
  "geometry": {"coordinates":[145.140228272,-38.1147575378],"type":"Point"}
}