{
  "type": "Feature",
  "properties": {
    "iso:country":"AU",
    "sg:address":"22 Portland Pl",
    "sg:city":"New Lambton",
    "sg:classifiers":[
        {
            "category":"Shopping",
            "subcategory":"Clothing, Apparel, & Fashions",
            "type":"Retail Goods"
        }
    ],
    "sg:phone":"+61 2 4956 4318",
    "sg:postcode":"2305",
    "sg:province":"NSW",
    "sg:tags":[
        "recycled",
        "clothing"
    ],
    "wof:name":"Second To None Recycled Clothing",
    "wof:placetype":"venue"
},
  "geometry": {"coordinates":[151.713486,-32.924992],"type":"Point"}
}