{
  "type": "Feature",
  "properties": {
    "iso:country":"AU",
    "sg:address":"25 Minoa St",
    "sg:city":"Woodridge",
    "sg:classifiers":[
        {
            "category":"Professional",
            "subcategory":"Art Services",
            "type":"Services"
        }
    ],
    "sg:phone":"+61 415 929 925",
    "sg:postcode":"4114",
    "sg:province":"QLD",
    "sg:tags":[
        "decorator",
        "painter"
    ],
    "wof:name":"All Nations Painting Solution",
    "wof:placetype":"venue"
},
  "geometry": {"coordinates":[153.11468505900001,-27.6335582733],"type":"Point"}
}