{
  "type": "Feature",
  "properties": {
    "iso:country":"AU",
    "sg:address":"874 Beaufort St",
    "sg:city":"Inglewood",
    "sg:classifiers":[
        {
            "category":"Wholesale",
            "subcategory":"Apparel",
            "type":"Manufacturing & Wholesale Goods"
        }
    ],
    "sg:phone":"+61 8 9272 2299",
    "sg:postcode":"6052",
    "sg:province":"WA",
    "sg:tags":[
        "wholesaler",
        "mfrs",
        "uniform"
    ],
    "wof:name":"High Country Menswear Pty Ltd",
    "wof:placetype":"venue"
},
  "geometry": {"coordinates":[115.885231018,-31.9221534729],"type":"Point"}
}