{
  "type": "Feature",
  "properties": {
    "addr:full":"137 Reed St Greenway ACT 2900",
    "addr:housenumber":"137",
    "addr:postcode":"2900",
    "addr:street":"Reed St",
    "iso:country":"AU",
    "sg:address":"137 Reed St",
    "sg:city":"Greenway",
    "sg:classifiers":[
        {
            "category":"Restaurant",
            "type":"Food & Drink"
        }
    ],
    "sg:phone":"+61 2 6293 9366",
    "sg:postcode":"2900",
    "sg:province":"ACT",
    "wof:name":"Aft Cafe & Brasserie",
    "wof:placetype":"venue"
},
  "geometry": {"coordinates":[149.07159423799999,-35.4163856506],"type":"Point"}
}