{
  "type": "Feature",
  "properties": {
    "iso:country":"AU",
    "sg:address":"467 Victoria St",
    "sg:city":"Brunswick West",
    "sg:classifiers":[
        {
            "category":"Personal",
            "subcategory":"Beauty Salon",
            "type":"Services"
        }
    ],
    "sg:phone":"+61 3 9380 1805",
    "sg:postcode":"3055",
    "sg:province":"VIC",
    "wof:name":"Salon Crew Skin & Body",
    "wof:placetype":"venue"
},
  "geometry": {"coordinates":[144.94729614299999,-37.7650299072],"type":"Point"}
}