{
  "type": "Feature",
  "properties": {
    "addr:full":"152 Pakington St Kew North VIC 3101",
    "addr:housenumber":"152",
    "addr:postcode":"3101",
    "addr:street":"Pakington St",
    "iso:country":"AU",
    "sg:address":"152 Pakington St",
    "sg:city":"Kew North",
    "sg:classifiers":[
        {
            "category":"Social Services",
            "subcategory":"Child Care",
            "type":"Services"
        }
    ],
    "sg:phone":"+61 3 9853 9466",
    "sg:postcode":"3101",
    "sg:province":"VIC",
    "sg:tags":[
        "support",
        "health"
    ],
    "wof:name":"Maternal & Child Health Centres",
    "wof:placetype":"venue"
},
  "geometry": {"coordinates":[145.03614807100001,-37.7963104248],"type":"Point"}
}