{
  "type": "Feature",
  "properties": {
    "iso:country":"AU",
    "sg:address":"Angus Smith Drv",
    "sg:city":"Douglas",
    "sg:classifiers":[
        {
            "category":"Food & Beverages",
            "subcategory":"Bakery",
            "type":"Retail Goods"
        }
    ],
    "sg:phone":"+61 7 4775 7680",
    "sg:postcode":"4814",
    "sg:province":"QLD",
    "sg:tags":[
        "cake",
        "shop",
        "pastry"
    ],
    "wof:name":"Jean-Pierre Patisserie",
    "wof:placetype":"venue"
},
  "geometry": {"coordinates":[146.738235,-19.326199],"type":"Point"}
}