{
  "type": "Feature",
  "properties": {
    "addr:full":"35 Dobell Ave Sunbury VIC 3429",
    "addr:housenumber":"35",
    "addr:postcode":"3429",
    "addr:street":"Dobell Ave",
    "iso:country":"AU",
    "sg:address":"35 Dobell Ave",
    "sg:city":"Sunbury",
    "sg:classifiers":[
        {
            "category":"Social Services",
            "subcategory":"Child Care",
            "type":"Services"
        }
    ],
    "sg:phone":"+61 3 9744 3924",
    "sg:postcode":"3429",
    "sg:province":"VIC",
    "sg:tags":[
        "support",
        "health"
    ],
    "wof:name":"Maternal & Child Health Centres",
    "wof:placetype":"venue"
},
  "geometry": {"coordinates":[144.70472717300001,-37.5770378113],"type":"Point"}
}