{
  "type": "Feature",
  "properties": {
    "iso:country":"AU",
    "sg:address":"44 Teevan St",
    "sg:city":"Stafford",
    "sg:classifiers":[
        {
            "category":"Utilities",
            "subcategory":"Electric",
            "type":"Services"
        }
    ],
    "sg:phone":"+61 7 3356 8897",
    "sg:postcode":"4053",
    "sg:province":"QLD",
    "sg:tags":[
        "electrical",
        "contractor"
    ],
    "wof:name":"Morris Ron",
    "wof:placetype":"venue"
},
  "geometry": {"coordinates":[153.006027222,-27.4081439972],"type":"Point"}
}