{
  "type": "Feature",
  "properties": {
    "addr:full":"3 Rose St Maroochydore QLD 4558",
    "addr:housenumber":"3",
    "addr:postcode":"4558",
    "addr:street":"Rose St",
    "iso:country":"AU",
    "sg:address":"3 Rose St",
    "sg:city":"Maroochydore",
    "sg:classifiers":[
        {
            "category":"Shopping",
            "subcategory":"Computers & Home Electronics",
            "type":"Retail Goods"
        }
    ],
    "sg:phone":"+61 7 5443 6721",
    "sg:postcode":"4558",
    "sg:province":"QLD",
    "sg:tags":[
        "hi-fi",
        "equipment"
    ],
    "wof:name":"Complete Audio",
    "wof:placetype":"venue"
},
  "geometry": {"coordinates":[153.096893311,-26.6594638824],"type":"Point"}
}