{
  "type": "Feature",
  "properties": {
    "addr:full":"PO Box 1147 Bunbury Private Boxes WA 6231",
    "addr:postcode":"6231",
    "iso:country":"AU",
    "sg:address":"PO Box 1147",
    "sg:city":"Bunbury Private Boxes",
    "sg:classifiers":[
        {
            "category":"Building & Trades",
            "subcategory":"Construction",
            "type":"Services"
        }
    ],
    "sg:phone":"+61 8 9728 1252",
    "sg:postcode":"6231",
    "sg:province":"WA",
    "sg:tags":[
        "plasterboard",
        "plasterer",
        "fixer"
    ],
    "wof:name":"City Ceilings",
    "wof:placetype":"venue"
},
  "geometry": {"coordinates":[115.636993,-33.32711],"type":"Point"}
}