{
  "type": "Feature",
  "properties": {
    "addr:full":"61 Whiting St Artarmon NSW 2064",
    "addr:housenumber":"61",
    "addr:postcode":"2064",
    "addr:street":"Whiting St",
    "iso:country":"AU",
    "sg:address":"61 Whiting St",
    "sg:city":"Artarmon",
    "sg:classifiers":[
        {
            "category":"Manufacturing",
            "subcategory":"Chemicals & Compounds",
            "type":"Manufacturing & Wholesale Goods"
        }
    ],
    "sg:phone":"+61 2 9436 4540",
    "sg:postcode":"2064",
    "sg:province":"NSW",
    "sg:tags":[
        "electroplating"
    ],
    "wof:name":"Artarmon Electroplating Pty Ltd",
    "wof:placetype":"venue"
},
  "geometry": {"coordinates":[151.181716919,-33.8158302307],"type":"Point"}
}