{
  "type": "Feature",
  "properties": {
    "addr:full":"Telephone Sales, Suite 8a Lvl 8, 46-56 Kippax St Surry Hills NSW 2010",
    "addr:housenumber":"suite;46-56",
    "addr:postcode":"2010",
    "addr:street":"Kippax St",
    "iso:country":"AU",
    "sg:address":"Telephone Sales, Suite 8a Lvl 8, 46-56 Kippax St",
    "sg:city":"Surry Hills",
    "sg:classifiers":[
        {
            "category":"Travel",
            "subcategory":"Travel Agent",
            "type":"Entertainment"
        }
    ],
    "sg:phone":"+61 1300 360 960",
    "sg:postcode":"2010",
    "sg:province":"NSW",
    "sg:tags":[
        "consultant"
    ],
    "wof:name":"STA Travel",
    "wof:placetype":"venue"
},
  "geometry": {"coordinates":[151.20985412600001,-33.8847160339],"type":"Point"}
}