{
  "type": "Feature",
  "properties": {
    "addr:full":"6117 Frankford Rd East Devonport TAS 7310",
    "addr:housenumber":"6117",
    "addr:postcode":"7310",
    "addr:street":"Frankford Rd",
    "iso:country":"AU",
    "sg:address":"6117 Frankford Rd",
    "sg:city":"East Devonport",
    "sg:classifiers":[
        {
            "category":"Building & Trades",
            "subcategory":"Plumbing",
            "type":"Services"
        }
    ],
    "sg:phone":"+61 3 6427 8083",
    "sg:postcode":"7310",
    "sg:province":"TAS",
    "sg:tags":[
        "plumber",
        "gasfitters"
    ],
    "wof:name":"Kelly G Plumbing Service",
    "wof:placetype":"venue"
},
  "geometry": {"coordinates":[146.410842895,-41.1986885071],"type":"Point"}
}