{
  "type": "Feature",
  "properties": {
    "iso:country":"AU",
    "sg:address":"Shp 1/ 29 Napoleon St",
    "sg:city":"Cottesloe",
    "sg:classifiers":[
        {
            "category":"Cafe",
            "type":"Food & Drink"
        }
    ],
    "sg:phone":"+61 8 9284 3830",
    "sg:postcode":"6011",
    "sg:province":"WA",
    "wof:name":"Leaf Tea Merchants",
    "wof:placetype":"venue"
},
  "geometry": {"coordinates":[115.76245880099999,-31.9980430603],"type":"Point"}
}