{
  "type": "Feature",
  "properties": {
    "addr:full":"54 Albert St Creswick VIC 3363",
    "addr:housenumber":"54",
    "addr:postcode":"3363",
    "addr:street":"Albert St",
    "iso:country":"AU",
    "sg:address":"54 Albert St",
    "sg:city":"Creswick",
    "sg:classifiers":[
        {
            "category":"Health Services",
            "subcategory":"Health Practitioner",
            "type":"Services"
        }
    ],
    "sg:phone":"+61 3 5345 8196",
    "sg:postcode":"3363",
    "sg:province":"VIC",
    "sg:tags":[
        "reiki"
    ],
    "wof:name":"Star Virtue",
    "wof:placetype":"venue"
},
  "geometry": {"coordinates":[143.89520263700001,-37.4225082397],"type":"Point"}
}