{
  "type": "Feature",
  "properties": {
    "addr:full":"905/ 168 Kent St Sydney NSW 2000",
    "addr:housenumber":"905 / 168",
    "addr:postcode":"2000",
    "addr:street":"Kent St",
    "iso:country":"AU",
    "sg:address":"905/ 168 Kent St",
    "sg:city":"Sydney",
    "sg:classifiers":[
        {
            "category":"Health Services",
            "subcategory":"Doctor",
            "type":"Services"
        }
    ],
    "sg:phone":"+61 2 9247 0075",
    "sg:postcode":"2000",
    "sg:province":"NSW",
    "sg:tags":[
        "medical",
        "practitioner"
    ],
    "wof:name":"Thomson Neal L",
    "wof:placetype":"venue"
},
  "geometry": {"coordinates":[151.20404052699999,-33.8622817993],"type":"Point"}
}