{
  "type": "Feature",
  "properties": {
    "addr:full":"Unit 1 190- 192 Canterbury Rd Canterbury NSW 2193",
    "addr:housenumber":"190 192",
    "addr:postcode":"2193",
    "addr:street":"Canterbury Rd",
    "iso:country":"AU",
    "sg:address":"Unit 1 190- 192 Canterbury Rd",
    "sg:city":"Canterbury",
    "sg:classifiers":[
        {
            "category":"Professional",
            "subcategory":"Engineering",
            "type":"Services"
        }
    ],
    "sg:phone":"+61 2 9718 8164",
    "sg:postcode":"2193",
    "sg:province":"NSW",
    "sg:tags":[
        "engineer",
        "structural"
    ],
    "wof:name":"Romeika & Gatsos",
    "wof:placetype":"venue"
},
  "geometry": {"coordinates":[151.12048300000001,-33.911446],"type":"Point"}
}