{
  "type": "Feature",
  "properties": {
    "iso:country":"AU",
    "sg:address":"20 Bogong St",
    "sg:city":"Riverhills",
    "sg:classifiers":[
        {
            "category":"Social Services",
            "subcategory":"Child Care",
            "type":"Services"
        }
    ],
    "sg:phone":"+61 7 3376 1665",
    "sg:postcode":"4074",
    "sg:province":"QLD",
    "wof:name":"Kindyworld Riverhills",
    "wof:placetype":"venue"
},
  "geometry": {"coordinates":[152.911941528,-27.5592193604],"type":"Point"}
}