{
  "type": "Feature",
  "properties": {
    "iso:country":"AU",
    "sg:address":"6 Emerald St",
    "sg:city":"Aldershot",
    "sg:classifiers":[
        {
            "category":"Building & Trades",
            "subcategory":"Construction",
            "type":"Services"
        }
    ],
    "sg:phone":"+61 408 316 774",
    "sg:postcode":"4650",
    "sg:province":"QLD",
    "sg:tags":[
        "polishing",
        "sanding",
        "floor"
    ],
    "wof:name":"All Districts Floor Sanding & Polishing",
    "wof:placetype":"venue"
},
  "geometry": {"coordinates":[152.66784699999999,-25.465317],"type":"Point"}
}