{
  "type": "Feature",
  "properties": {
    "iso:country":"AU",
    "sg:address":"165 Buckley St",
    "sg:city":"Footscray",
    "sg:classifiers":[
        {
            "category":"Home & Garden",
            "subcategory":"Household Appliances",
            "type":"Retail Goods"
        }
    ],
    "sg:phone":"+61 415 513 582",
    "sg:postcode":"3011",
    "sg:province":"VIC",
    "sg:tags":[
        "heating",
        "system"
    ],
    "wof:name":"Attard's Plumbing & Heating",
    "wof:placetype":"venue"
},
  "geometry": {"coordinates":[144.89015197800001,-37.8030128479],"type":"Point"}
}