{
  "type": "Feature",
  "properties": {
    "iso:country":"AU",
    "sg:address":"Unit 11/ 28 Victoria Rd",
    "sg:city":"Rydalmere",
    "sg:classifiers":[
        {
            "category":"Professional",
            "type":"Services"
        }
    ],
    "sg:phone":"+61 2 9955 2975",
    "sg:postcode":"2116",
    "sg:province":"NSW",
    "sg:tags":[
        "transport"
    ],
    "wof:name":"Australia Overnight Trucking Co Pty Ltd",
    "wof:placetype":"venue"
},
  "geometry": {"coordinates":[151.160812378,-33.9116668701],"type":"Point"}
}