{
  "type": "Feature",
  "properties": {
    "iso:country":"AU",
    "sg:address":"Ennerdale La",
    "sg:city":"Darlington",
    "sg:classifiers":[
        {
            "category":"Retail",
            "subcategory":"Animal Services",
            "type":"Services"
        }
    ],
    "sg:phone":"+61 3 5599 5333",
    "sg:postcode":"3271",
    "sg:province":"VIC",
    "sg:tags":[
        "breeder",
        "sheep",
        "stud",
        "cattle"
    ],
    "wof:name":"Ennerdale Proprietors",
    "wof:placetype":"venue"
},
  "geometry": {"coordinates":[142.95083618199999,-37.8240089417],"type":"Point"}
}