{
  "type": "Feature",
  "properties": {
    "iso:country":"AU",
    "sg:address":"28 Suni Drv",
    "sg:city":"Old Bar",
    "sg:classifiers":[
        {
            "category":"Professional",
            "subcategory":"Accounting & Tax Preparation",
            "type":"Services"
        }
    ],
    "sg:phone":"+61 2 6553 6540",
    "sg:postcode":"2430",
    "sg:province":"NSW",
    "sg:tags":[
        "bookkeeping"
    ],
    "wof:name":"Bindaree Business Services",
    "wof:placetype":"venue"
},
  "geometry": {"coordinates":[152.580917,-31.969509],"type":"Point"}
}