{
  "type": "Feature",
  "properties": {
    "addr:full":"Level 1 No.4 Wolf Street Newcastle NSW 2300",
    "addr:postcode":"2300",
    "addr:street":"Wolf Street",
    "iso:country":"AU",
    "sg:address":"Level 1 No.4 Wolf Street",
    "sg:city":"Newcastle",
    "sg:classifiers":[
        {
            "category":"Banks & Credit Unions",
            "subcategory":"Investment Brokerage",
            "type":"Services"
        }
    ],
    "sg:phone":"+61 2 4929 2033",
    "sg:postcode":"2300",
    "sg:province":"NSW",
    "sg:tags":[
        "debt",
        "collection"
    ],
    "wof:name":"Denis Veitch & Associates",
    "wof:placetype":"venue"
},
  "geometry": {"coordinates":[151.77934300000001,-32.928207],"type":"Point"}
}