{
  "type": "Feature",
  "properties": {
    "iso:country":"AU",
    "sg:address":"Salcott Rd",
    "sg:city":"Girrawheen",
    "sg:classifiers":[
        {
            "category":"Education",
            "subcategory":"School",
            "type":"Public Place"
        }
    ],
    "sg:phone":"+61 8 9342 7377",
    "sg:postcode":"6064",
    "sg:province":"WA",
    "wof:name":"Emmanuel Christian School Girrawheen",
    "wof:placetype":"venue"
},
  "geometry": {"coordinates":[115.845611572,-31.8454360962],"type":"Point"}
}