{
  "type": "Feature",
  "properties": {
    "addr:full":"147 Martyn St Parramatta Park QLD 4870",
    "addr:housenumber":"147",
    "addr:postcode":"4870",
    "addr:street":"Martyn St",
    "iso:country":"AU",
    "sg:address":"147 Martyn St",
    "sg:city":"Parramatta Park",
    "sg:classifiers":[
        {
            "category":"Health Services",
            "subcategory":"Doctor",
            "type":"Services"
        }
    ],
    "sg:phone":"+61 7 4051 8222",
    "sg:postcode":"4870",
    "sg:province":"QLD",
    "sg:tags":[
        "medical",
        "practitioner"
    ],
    "wof:name":"Bossingham D H",
    "wof:placetype":"venue"
},
  "geometry": {"coordinates":[145.759765625,-16.9156703949],"type":"Point"}
}