{
  "type": "Feature",
  "properties": {
    "iso:country":"AU",
    "sg:address":"123-A Bathurst St",
    "sg:city":"Hobart",
    "sg:classifiers":[
        {
            "category":"Fast Food",
            "type":"Food & Drink"
        }
    ],
    "sg:phone":"+61 407 279 993",
    "sg:postcode":"7000",
    "sg:province":"TAS",
    "sg:tags":[
        "away",
        "take"
    ],
    "wof:name":"Taste of Persia",
    "wof:placetype":"venue"
},
  "geometry": {"coordinates":[147.32453918499999,-42.8814888],"type":"Point"}
}