{
  "type": "Feature",
  "properties": {
    "iso:country":"AU",
    "sg:address":"U32/ 20 Tucks Rd",
    "sg:city":"Seven Hills",
    "sg:classifiers":[
        {
            "category":"Banks & Credit Unions",
            "subcategory":"Investment Brokerage",
            "type":"Services"
        }
    ],
    "sg:phone":"+61 2 9838 7500",
    "sg:postcode":"2147",
    "sg:province":"NSW",
    "sg:tags":[
        "shutter",
        "louvre"
    ],
    "wof:name":"Vollay Aluminium Shutter Systems",
    "wof:placetype":"venue"
},
  "geometry": {"coordinates":[150.95669555699999,-33.7793998718],"type":"Point"}
}