{
  "type": "Feature",
  "properties": {
    "addr:full":"2/ 3 Marina Cl Mt Kuring-gai NSW 2080",
    "addr:housenumber":"/ 3",
    "addr:postcode":"2080",
    "addr:street":"Marina Cl",
    "iso:country":"AU",
    "sg:address":"2/ 3 Marina Cl",
    "sg:city":"Mt Kuring-gai",
    "sg:classifiers":[
        {
            "category":"Shopping",
            "subcategory":"Clothing, Apparel, & Fashions",
            "type":"Retail Goods"
        }
    ],
    "sg:phone":"+61 2 9457 6665",
    "sg:postcode":"2080",
    "sg:province":"NSW",
    "sg:tags":[
        "textile",
        "designer"
    ],
    "wof:name":"Jack Whoppy",
    "wof:placetype":"venue"
},
  "geometry": {"coordinates":[151.280487061,-33.7011680603],"type":"Point"}
}