{
  "type": "Feature",
  "properties": {
    "addr:full":"292A Springvale Rd Springvale VIC 3171",
    "addr:housenumber":"292a",
    "addr:postcode":"3171",
    "addr:street":"Springvale Rd",
    "iso:country":"AU",
    "sg:address":"292A Springvale Rd",
    "sg:city":"Springvale",
    "sg:classifiers":[
        {
            "category":"Personal",
            "subcategory":"Beauty Salon",
            "type":"Services"
        }
    ],
    "sg:phone":"+61 3 9548 2582",
    "sg:postcode":"3171",
    "sg:province":"VIC",
    "sg:tags":[
        "hairdresser"
    ],
    "wof:name":"Simplicity Hair Studio",
    "wof:placetype":"venue"
},
  "geometry": {"coordinates":[145.151977539,-37.9525756836],"type":"Point"}
}