{
  "type": "Feature",
  "properties": {
    "addr:full":"5 Pineview Crt Lysterfield VIC 3156",
    "addr:housenumber":"5",
    "addr:postcode":"3156",
    "addr:street":"Pineview Crt",
    "iso:country":"AU",
    "sg:address":"5 Pineview Crt",
    "sg:city":"Lysterfield",
    "sg:classifiers":[
        {
            "category":"Banks & Credit Unions",
            "subcategory":"Financial Services",
            "type":"Services"
        }
    ],
    "sg:phone":"+61 3 9748 9994",
    "sg:postcode":"3156",
    "sg:province":"VIC",
    "sg:tags":[
        "loan",
        "finance",
        "mortgage"
    ],
    "wof:name":"Choice Home Loans",
    "wof:placetype":"venue"
},
  "geometry": {"coordinates":[145.27798461899999,-37.9228477478],"type":"Point"}
}