{
  "type": "Feature",
  "properties": {
    "addr:full":"Main St Mitiamo VIC 3573",
    "addr:postcode":"3573",
    "addr:street":"Main St",
    "iso:country":"AU",
    "sg:address":"Main St",
    "sg:city":"Mitiamo",
    "sg:classifiers":[
        {
            "category":"Sports & Exercise",
            "subcategory":"Gym",
            "type":"Entertainment"
        }
    ],
    "sg:phone":"+61 428 579 513",
    "sg:postcode":"3573",
    "sg:province":"VIC",
    "sg:tags":[
        "health",
        "fitness"
    ],
    "wof:name":"Mitiamo Outdoor Pool",
    "wof:placetype":"venue"
},
  "geometry": {"coordinates":[144.23142999999999,-36.211182],"type":"Point"}
}