{
  "type": "Feature",
  "properties": {
    "addr:full":"6- 8 Leo St Fawkner VIC 3060",
    "addr:housenumber":"8",
    "addr:postcode":"3060",
    "addr:street":"Leo St",
    "iso:country":"AU",
    "sg:address":"6- 8 Leo St",
    "sg:city":"Fawkner",
    "sg:classifiers":[
        {
            "category":"Building & Trades",
            "subcategory":"Construction",
            "type":"Services"
        }
    ],
    "sg:phone":"+61 3 9324 1704",
    "sg:postcode":"3060",
    "sg:province":"VIC",
    "sg:tags":[
        "fencing",
        "contractor"
    ],
    "wof:name":"Image Wave Pty Ltd",
    "wof:placetype":"venue"
},
  "geometry": {"coordinates":[144.96299743599999,-37.7081680298],"type":"Point"}
}