{
  "type": "Feature",
  "properties": {
    "addr:full":"Elphin Crs Wongan Hills WA 6603",
    "addr:postcode":"6603",
    "addr:street":"Elphin Crs",
    "iso:country":"AU",
    "sg:address":"Elphin Crs",
    "sg:city":"Wongan Hills",
    "sg:classifiers":[
        {
            "category":"Utilities",
            "subcategory":"Electric",
            "type":"Services"
        }
    ],
    "sg:phone":"+61 8 9671 1779",
    "sg:postcode":"6603",
    "sg:province":"WA",
    "sg:tags":[
        "electrical",
        "contractor"
    ],
    "wof:name":"Sinclair R & S G",
    "wof:placetype":"venue"
},
  "geometry": {"coordinates":[116.71910095200001,-30.8961391449],"type":"Point"}
}