{
  "type": "Feature",
  "properties": {
    "iso:country":"AU",
    "sg:address":"11 Cowcher Pl",
    "sg:city":"Belmont",
    "sg:classifiers":[
        {
            "category":"Manufacturing",
            "subcategory":"Tools & Machinery",
            "type":"Manufacturing & Wholesale Goods"
        }
    ],
    "sg:phone":"+61 8 9475 0264",
    "sg:postcode":"6104",
    "sg:province":"WA",
    "sg:tags":[
        "fastener",
        "industrial"
    ],
    "wof:name":"Caddy Industrial Sales",
    "wof:placetype":"venue"
},
  "geometry": {"coordinates":[115.93080139200001,-31.9552440643],"type":"Point"}
}