{
  "type": "Feature",
  "properties": {
    "iso:country":"AU",
    "sg:address":"2 McBride St",
    "sg:city":"Cockatoo",
    "sg:classifiers":[
        {
            "category":"Food & Beverages",
            "subcategory":"Groceries & Convenience Stores",
            "type":"Retail Goods"
        }
    ],
    "sg:phone":"+61 3 5968 8369",
    "sg:postcode":"3781",
    "sg:province":"VIC",
    "wof:name":"Cockatoo General Store",
    "wof:placetype":"venue"
},
  "geometry": {"coordinates":[145.491226,-37.935833],"type":"Point"}
}