{
  "type": "Feature",
  "properties": {
    "addr:full":"Eighth St Wonthella WA 6530",
    "addr:postcode":"6530",
    "addr:street":"Eighth St",
    "iso:country":"AU",
    "sg:address":"Eighth St",
    "sg:city":"Wonthella",
    "sg:classifiers":[
        {
            "category":"Arena",
            "subcategory":"Sports Club",
            "type":"Entertainment"
        }
    ],
    "sg:phone":"+61 8 9964 2752",
    "sg:postcode":"6530",
    "sg:province":"WA",
    "sg:tags":[
        "organisation",
        "sporting"
    ],
    "wof:name":"Geraldton Netball Association (Inc)",
    "wof:placetype":"venue"
},
  "geometry": {"coordinates":[114.624809265,-28.7683296204],"type":"Point"}
}