{
  "type": "Feature",
  "properties": {
    "iso:country":"AU",
    "sg:address":"355 Heidelberg Rd",
    "sg:city":"Northcote",
    "sg:classifiers":[
        {
            "category":"Utilities",
            "subcategory":"Electric",
            "type":"Services"
        }
    ],
    "sg:phone":"+61 3 9482 2467",
    "sg:postcode":"3070",
    "sg:province":"VIC",
    "sg:tags":[
        "electrical",
        "contractor"
    ],
    "wof:name":"Jays Electrics Pty Ltd",
    "wof:placetype":"venue"
},
  "geometry": {"coordinates":[145.01263399999999,-37.783894],"type":"Point"}
}