{
  "type": "Feature",
  "properties": {
    "addr:full":"Unit 20, 60- 66 Richmond Rd Keswick SA 5035",
    "addr:housenumber":"60 66",
    "addr:postcode":"5035",
    "addr:street":"Richmond Rd",
    "iso:country":"AU",
    "sg:address":"Unit 20, 60- 66 Richmond Rd",
    "sg:city":"Keswick",
    "sg:classifiers":[
        {
            "category":"Building & Trades",
            "subcategory":"Construction",
            "type":"Services"
        }
    ],
    "sg:phone":"+61 1300 360 031",
    "sg:postcode":"5035",
    "sg:province":"SA",
    "sg:tags":[
        "equipment",
        "system",
        "automation"
    ],
    "wof:name":"Hawker Richardson",
    "wof:placetype":"venue"
},
  "geometry": {"coordinates":[138.57615661599999,-34.9419822693],"type":"Point"}
}