{
  "type": "Feature",
  "properties": {
    "addr:full":"19 Cook St Tamworth NSW 2340",
    "addr:housenumber":"19",
    "addr:postcode":"2340",
    "addr:street":"Cook St",
    "iso:country":"AU",
    "sg:address":"19 Cook St",
    "sg:city":"Tamworth",
    "sg:classifiers":[
        {
            "category":"Professional",
            "type":"Services"
        }
    ],
    "sg:phone":"+61 2 6762 3588",
    "sg:postcode":"2340",
    "sg:province":"NSW",
    "sg:tags":[
        "valuer"
    ],
    "wof:name":"Rundles Auctions",
    "wof:placetype":"venue"
},
  "geometry": {"coordinates":[150.89349365199999,-31.0946273804],"type":"Point"}
}