{
  "type": "Feature",
  "properties": {
    "iso:country":"AU",
    "sg:address":"6 O'loghlen St",
    "sg:city":"Latham",
    "sg:classifiers":[
        {
            "category":"Personal",
            "subcategory":"Beauty Salon",
            "type":"Services"
        }
    ],
    "sg:phone":"+61 2 6278 6807",
    "sg:postcode":"2615",
    "sg:province":"ACT",
    "sg:tags":[
        "wig",
        "hairpiece"
    ],
    "wof:name":"Aquilinas Salon",
    "wof:placetype":"venue"
},
  "geometry": {"coordinates":[149.03219604500001,-35.225479126],"type":"Point"}
}