{
  "type": "Feature",
  "properties": {
    "addr:full":"PO Box 248 Kingsford NSW 2032",
    "addr:postcode":"2032",
    "iso:country":"AU",
    "sg:address":"PO Box 248",
    "sg:city":"Kingsford",
    "sg:classifiers":[
        {
            "category":"Building & Trades",
            "subcategory":"Plumbing",
            "type":"Services"
        }
    ],
    "sg:phone":"+61 412 082 229",
    "sg:postcode":"2032",
    "sg:province":"NSW",
    "sg:tags":[
        "plumber",
        "gasfitters"
    ],
    "wof:name":"Maroubra Plumbing",
    "wof:placetype":"venue"
},
  "geometry": {"coordinates":[151.227493286,-33.9234886169],"type":"Point"}
}