{
  "type": "Feature",
  "properties": {
    "iso:country":"AU",
    "sg:address":"2 Magnolia Pl",
    "sg:city":"Yeppoon",
    "sg:classifiers":[
        {
            "category":"Manufacturing",
            "subcategory":"Food",
            "type":"Manufacturing & Wholesale Goods"
        }
    ],
    "sg:phone":"+61 7 4939 8045",
    "sg:postcode":"4703",
    "sg:province":"QLD",
    "sg:tags":[
        "function",
        "catering"
    ],
    "wof:name":"The Olive Catering Group",
    "wof:placetype":"venue"
},
  "geometry": {"coordinates":[150.752319336,-23.1489830017],"type":"Point"}
}