{
  "type": "Feature",
  "properties": {
    "addr:full":"43 Spencer St Jandakot WA 6164",
    "addr:housenumber":"43",
    "addr:postcode":"6164",
    "addr:street":"Spencer St",
    "iso:country":"AU",
    "sg:address":"43 Spencer St",
    "sg:city":"Jandakot",
    "sg:classifiers":[
        {
            "category":"Wholesale",
            "subcategory":"Machinery & Supplies",
            "type":"Manufacturing & Wholesale Goods"
        }
    ],
    "sg:phone":"+61 8 9417 4447",
    "sg:postcode":"6164",
    "sg:province":"WA",
    "sg:tags":[
        "distributor",
        "crane",
        "mfrs"
    ],
    "sg:website":"http://www.vectorlifting.com.au",
    "wof:name":"Vector Lifting",
    "wof:placetype":"venue"
},
  "geometry": {"coordinates":[115.845558,-32.122425],"type":"Point"}
}