{
  "type": "Feature",
  "properties": {
    "addr:full":"19 Warren St Nyngan NSW 2825",
    "addr:housenumber":"19",
    "addr:postcode":"2825",
    "addr:street":"Warren St",
    "iso:country":"AU",
    "sg:address":"19 Warren St",
    "sg:city":"Nyngan",
    "sg:classifiers":[
        {
            "category":"Food & Beverages",
            "subcategory":"Groceries & Convenience Stores",
            "type":"Retail Goods"
        }
    ],
    "sg:phone":"+61 2 6832 1079",
    "sg:postcode":"2825",
    "sg:province":"NSW",
    "wof:name":"Arandale W & M",
    "wof:placetype":"venue"
},
  "geometry": {"coordinates":[147.18890380900001,-31.5636196136],"type":"Point"}
}