{
  "type": "Feature",
  "properties": {
    "addr:full":"Shop 1 The Woolworths Centre Renmark SA 5341",
    "addr:housenumber":"shop 1",
    "addr:postcode":"5341",
    "addr:street":"The",
    "iso:country":"AU",
    "sg:address":"Shop 1",
    "sg:city":"The Woolworths Centre Renmark",
    "sg:classifiers":[
        {
            "category":"Shopping",
            "subcategory":"Clothing, Apparel, & Fashions",
            "type":"Retail Goods"
        }
    ],
    "sg:phone":"+61 8 8586 4276",
    "sg:postcode":"5341",
    "sg:province":"SA",
    "sg:tags":[
        "lady",
        "wear"
    ],
    "wof:name":"Rockmans Stores Pty Limited",
    "wof:placetype":"venue"
},
  "geometry": {"coordinates":[140.74554443400001,-34.1753692627],"type":"Point"}
}