{
  "type": "Feature",
  "properties": {
    "iso:country":"AU",
    "sg:address":"1st Floor 1693a Burwood Hwy",
    "sg:city":"Belgrave",
    "sg:classifiers":[
        {
            "category":"Professional",
            "subcategory":"Accounting & Tax Preparation",
            "type":"Services"
        }
    ],
    "sg:phone":"+61 3 9752 5552",
    "sg:postcode":"3160",
    "sg:province":"VIC",
    "sg:tags":[
        "accountant",
        "auditor"
    ],
    "wof:name":"Stevensons Tax Consulting",
    "wof:placetype":"venue"
},
  "geometry": {"coordinates":[145.35487365700001,-37.9084243774],"type":"Point"}
}