{
  "type": "Feature",
  "properties": {
    "iso:country":"AU",
    "sg:address":"301 Malop St",
    "sg:city":"Geelong",
    "sg:classifiers":[
        {
            "category":"Building & Trades",
            "subcategory":"Construction",
            "type":"Services"
        }
    ],
    "sg:phone":"+61 3 5222 8588",
    "sg:postcode":"3220",
    "sg:province":"VIC",
    "sg:tags":[
        "contractor"
    ],
    "wof:name":"Edge Building & Design",
    "wof:placetype":"venue"
},
  "geometry": {"coordinates":[144.372543,-38.150406],"type":"Point"}
}