{
  "type": "Feature",
  "properties": {
    "addr:full":"Shop 2, 16 Harvest Crt Southport QLD 4215",
    "addr:housenumber":"shop;16",
    "addr:postcode":"4215",
    "addr:street":"Harvest Crt",
    "iso:country":"AU",
    "sg:address":"Shop 2, 16 Harvest Crt",
    "sg:city":"Southport",
    "sg:classifiers":[
        {
            "category":"Sports & Exercise",
            "subcategory":"Sports Center",
            "type":"Entertainment"
        }
    ],
    "sg:phone":"+61 7 5531 0267",
    "sg:postcode":"4215",
    "sg:province":"QLD",
    "sg:tags":[
        "card",
        "memorabilia"
    ],
    "wof:name":"Race Gallery",
    "wof:placetype":"venue"
},
  "geometry": {"coordinates":[153.40956115700001,-27.9786968231],"type":"Point"}
}