{
  "type": "Feature",
  "properties": {
    "iso:country":"AU",
    "sg:address":"99 Banksia Rd",
    "sg:city":"Greenacre",
    "sg:classifiers":[
        {
            "category":"Home & Garden",
            "subcategory":"Building Materials",
            "type":"Retail Goods"
        }
    ],
    "sg:phone":"+61 405 161 600",
    "sg:postcode":"2190",
    "sg:province":"NSW",
    "sg:tags":[
        "lawn",
        "cutting",
        "maintenance"
    ],
    "wof:name":"Southside Mowing Services",
    "wof:placetype":"venue"
},
  "geometry": {"coordinates":[151.047806,-33.90731],"type":"Point"}
}