{
  "type": "Feature",
  "properties": {
    "addr:full":"3 Windhover Crt Baulkham Hills NSW 2153",
    "addr:housenumber":"3",
    "addr:postcode":"2153",
    "addr:street":"Windhover Crt",
    "iso:country":"AU",
    "sg:address":"3 Windhover Crt",
    "sg:city":"Baulkham Hills",
    "sg:classifiers":[
        {
            "category":"Shopping",
            "subcategory":"Computers & Home Electronics",
            "type":"Retail Goods"
        }
    ],
    "sg:phone":"+61 2 9838 4580",
    "sg:postcode":"2153",
    "sg:province":"NSW",
    "sg:tags":[
        "equipment",
        "part",
        "electronic"
    ],
    "wof:name":"CT Automation Products",
    "wof:placetype":"venue"
},
  "geometry": {"coordinates":[150.95794677699999,-33.750125885],"type":"Point"}
}