{
  "type": "Feature",
  "properties": {
    "addr:full":"264 Fitzgerald St Northam WA 6401",
    "addr:housenumber":"264",
    "addr:postcode":"6401",
    "addr:street":"Fitzgerald St",
    "iso:country":"AU",
    "sg:address":"264 Fitzgerald St",
    "sg:city":"Northam",
    "sg:classifiers":[
        {
            "category":"Retail",
            "subcategory":"Funeral Services",
            "type":"Services"
        }
    ],
    "sg:phone":"+61 8 9622 1411",
    "sg:postcode":"6401",
    "sg:province":"WA",
    "sg:tags":[
        "director"
    ],
    "wof:name":"Purslowe Funeral Homes",
    "wof:placetype":"venue"
},
  "geometry": {"coordinates":[116.670089722,-31.6547794342],"type":"Point"}
}