{
  "type": "Feature",
  "properties": {
    "addr:full":"Chelsea Village Unit 1 & 2 145 Stirling Hwy Nedlands WA 6009",
    "addr:housenumber":"&;145",
    "addr:postcode":"6009",
    "addr:street":"Stirling Hwy",
    "iso:country":"AU",
    "sg:address":"Chelsea Village Unit 1 & 2 145 Stirling Hwy",
    "sg:city":"Nedlands",
    "sg:classifiers":[
        {
            "category":"Bus Stop",
            "subcategory":"None",
            "type":"Transportation"
        }
    ],
    "sg:phone":"+61 8 9389 8439",
    "sg:postcode":"6009",
    "sg:province":"WA",
    "sg:tags":[
        "industrial",
        "fabric"
    ],
    "wof:name":"Tessuti Village Agency",
    "wof:placetype":"venue"
},
  "geometry": {"coordinates":[115.815811,-31.976608],"type":"Point"}
}