{
  "type": "Feature",
  "properties": {
    "addr:full":"1 Martin Pl Sydney NSW 2000",
    "addr:housenumber":"1",
    "addr:postcode":"2000",
    "addr:street":"Martin Pl",
    "iso:country":"AU",
    "sg:address":"1 Martin Pl",
    "sg:city":"Sydney",
    "sg:classifiers":[
        {
            "category":"Travel",
            "subcategory":"Hotels & Motels",
            "type":"Entertainment"
        }
    ],
    "sg:phone":"+61 2 8223 1111",
    "sg:postcode":"2000",
    "sg:province":"NSW",
    "sg:tags":[
        "accommodation"
    ],
    "wof:name":"The Westin Sydney",
    "wof:placetype":"venue"
},
  "geometry": {"coordinates":[151.207763672,-33.8676071167],"type":"Point"}
}