{
  "type": "Feature",
  "properties": {
    "iso:country":"AU",
    "sg:address":"8 Perdita St",
    "sg:city":"Bellbird Park",
    "sg:classifiers":[
        {
            "category":"Real Estate",
            "subcategory":"Surveying",
            "type":"Services"
        }
    ],
    "sg:phone":"+61 413 333 371",
    "sg:postcode":"4300",
    "sg:province":"QLD",
    "sg:tags":[
        "surveyor",
        "quantity"
    ],
    "wof:name":"Darrin Evans Quantity Surveying Services",
    "wof:placetype":"venue"
},
  "geometry": {"coordinates":[152.89320373499999,-27.6300773621],"type":"Point"}
}