{
  "type": "Feature",
  "properties": {
    "addr:full":"Oak St Chinchilla QLD 4413",
    "addr:postcode":"4413",
    "addr:street":"Oak St",
    "iso:country":"AU",
    "sg:address":"Oak St",
    "sg:city":"Chinchilla",
    "sg:classifiers":[
        {
            "category":"Autos & Motor Vehicles",
            "subcategory":"Automobile Sales",
            "type":"Retail Goods"
        }
    ],
    "sg:phone":"+61 7 4668 9200",
    "sg:postcode":"4413",
    "sg:province":"QLD",
    "sg:tags":[
        "car",
        "used"
    ],
    "wof:name":"Ron Hyslop For Cars",
    "wof:placetype":"venue"
},
  "geometry": {"coordinates":[150.63322448700001,-26.7359428406],"type":"Point"}
}