{
  "type": "Feature",
  "properties": {
    "addr:full":"Cnr Denham & Barrett Sts Bracken Ridge QLD 4017",
    "addr:postcode":"4017",
    "iso:country":"AU",
    "sg:address":"Cnr Denham & Barrett Sts",
    "sg:city":"Bracken Ridge",
    "sg:classifiers":[
        {
            "category":"Bars & Pubs",
            "subcategory":"Nightclub",
            "type":"Food & Drink"
        }
    ],
    "sg:phone":"+61 7 3269 7011",
    "sg:postcode":"4017",
    "sg:province":"QLD",
    "sg:tags":[
        "discotheque"
    ],
    "wof:name":"Rumjungle",
    "wof:placetype":"venue"
},
  "geometry": {"coordinates":[153.04156494099999,-27.3315677643],"type":"Point"}
}