{
  "type": "Feature",
  "properties": {
    "addr:full":"28 Sexton Rd Inglewood WA 6052",
    "addr:housenumber":"28",
    "addr:postcode":"6052",
    "addr:street":"Sexton Rd",
    "iso:country":"AU",
    "sg:address":"28 Sexton Rd",
    "sg:city":"Inglewood",
    "sg:classifiers":[
        {
            "category":"Building & Trades",
            "subcategory":"Locksmith",
            "type":"Services"
        }
    ],
    "sg:phone":"+61 8 9370 2887",
    "sg:postcode":"6052",
    "sg:province":"WA",
    "sg:tags":[
        "strongroom",
        "safe",
        "door"
    ],
    "wof:name":"Keywest Lock Service & Sales Pty Ltd",
    "wof:placetype":"venue"
},
  "geometry": {"coordinates":[115.884788513,-31.9135971069],"type":"Point"}
}