{
  "type": "Feature",
  "properties": {
    "addr:full":"37 Marsengo Rd Bateman WA 6150",
    "addr:housenumber":"37",
    "addr:postcode":"6150",
    "addr:street":"Marsengo Rd",
    "iso:country":"AU",
    "sg:address":"37 Marsengo Rd",
    "sg:city":"Bateman",
    "sg:classifiers":[
        {
            "category":"Home & Garden",
            "subcategory":"Household Appliances",
            "type":"Retail Goods"
        }
    ],
    "sg:phone":"+61 8 9313 5425",
    "sg:postcode":"6150",
    "sg:province":"WA",
    "sg:tags":[
        "heating",
        "system"
    ],
    "wof:name":"R.R.R. Rentals",
    "wof:placetype":"venue"
},
  "geometry": {"coordinates":[115.848282,-32.058228],"type":"Point"}
}