{
  "type": "Feature",
  "properties": {
    "iso:country":"AU",
    "sg:address":"Golf Course Rd",
    "sg:city":"Heywood",
    "sg:classifiers":[
        {
            "category":"Building & Trades",
            "subcategory":"Construction",
            "type":"Services"
        }
    ],
    "sg:phone":"+61 3 5527 1435",
    "sg:postcode":"3304",
    "sg:province":"VIC",
    "sg:tags":[
        "contractor"
    ],
    "wof:name":"Hoggan G M & M M",
    "wof:placetype":"venue"
},
  "geometry": {"coordinates":[141.628372192,-38.167842865],"type":"Point"}
}