{
  "type": "Feature",
  "properties": {
    "addr:full":"12 Philip Ave Victor Harbor SA 5211",
    "addr:housenumber":"12",
    "addr:postcode":"5211",
    "addr:street":"Philip Ave",
    "iso:country":"AU",
    "sg:address":"12 Philip Ave",
    "sg:city":"Victor Harbor",
    "sg:classifiers":[
        {
            "category":"Communications",
            "subcategory":"Television Station",
            "type":"Services"
        }
    ],
    "sg:phone":"+61 418 855 481",
    "sg:postcode":"5211",
    "sg:province":"SA",
    "sg:tags":[
        "mfrs",
        "tank",
        "installation",
        "septic"
    ],
    "wof:name":"South Coast Septic Systems",
    "wof:placetype":"venue"
},
  "geometry": {"coordinates":[138.605957031,-35.559803009],"type":"Point"}
}