{
  "type": "Feature",
  "properties": {
    "addr:full":"39 Victoria St Smithfield NSW 2164",
    "addr:housenumber":"39",
    "addr:postcode":"2164",
    "addr:street":"Victoria St",
    "iso:country":"AU",
    "sg:address":"39 Victoria St",
    "sg:city":"Smithfield",
    "sg:classifiers":[
        {
            "category":"Wholesale",
            "subcategory":"Machinery & Supplies",
            "type":"Manufacturing & Wholesale Goods"
        }
    ],
    "sg:phone":"+61 2 9604 8822",
    "sg:postcode":"2164",
    "sg:province":"NSW",
    "sg:tags":[
        "equipment",
        "welding"
    ],
    "wof:name":"Epitech Products Pty Ltd",
    "wof:placetype":"venue"
},
  "geometry": {"coordinates":[150.939285278,-33.8513221741],"type":"Point"}
}