{
  "type": "Feature",
  "properties": {
    "iso:country":"AU",
    "sg:address":"Shop 364",
    "sg:city":"Westfield Shoppingtown Chatswood",
    "sg:classifiers":[
        {
            "category":"Personal",
            "subcategory":"Beauty Salon",
            "type":"Services"
        }
    ],
    "sg:phone":"+61 2 9419 6434",
    "sg:postcode":"2067",
    "sg:province":"NSW",
    "sg:tags":[
        "hairdresser"
    ],
    "wof:name":"Hair &#039;N&#039; Care",
    "wof:placetype":"venue"
},
  "geometry": {"coordinates":[151.19012451200001,-33.7924385071],"type":"Point"}
}