{
  "type": "Feature",
  "properties": {
    "addr:full":"261 Lawson St Hamilton South NSW 2303",
    "addr:housenumber":"261",
    "addr:postcode":"2303",
    "addr:street":"Lawson St",
    "iso:country":"AU",
    "sg:address":"261 Lawson St",
    "sg:city":"Hamilton South",
    "sg:classifiers":[
        {
            "category":"Retail",
            "subcategory":"Veterinary Services",
            "type":"Services"
        }
    ],
    "sg:phone":"+61 2 4961 1511",
    "sg:postcode":"2303",
    "sg:province":"NSW",
    "sg:tags":[
        "surgeon"
    ],
    "wof:name":"David O&#039;Hara",
    "wof:placetype":"venue"
},
  "geometry": {"coordinates":[151.74704,-32.935791],"type":"Point"}
}