{
  "type": "Feature",
  "properties": {
    "iso:country":"AU",
    "sg:address":"2/ 538 Gympie Rd",
    "sg:city":"Kedron",
    "sg:classifiers":[
        {
            "category":"Retail",
            "subcategory":"Funeral Services",
            "type":"Services"
        }
    ],
    "sg:phone":"+61 7 3630 5022",
    "sg:postcode":"4031",
    "sg:province":"QLD",
    "sg:tags":[
        "director"
    ],
    "wof:name":"Simplicity Funerals",
    "wof:placetype":"venue"
},
  "geometry": {"coordinates":[153.03062399999999,-27.394178],"type":"Point"}
}