{
  "type": "Feature",
  "properties": {
    "addr:full":"222-226 McDougall St Toowoomba QLD 4350",
    "addr:housenumber":"222-226",
    "addr:postcode":"4350",
    "addr:street":"Mcdougall St",
    "iso:country":"AU",
    "sg:address":"222-226 McDougall St",
    "sg:city":"Toowoomba",
    "sg:classifiers":[
        {
            "category":"Wholesale",
            "subcategory":"Fruits & Vegetables",
            "type":"Manufacturing & Wholesale Goods"
        }
    ],
    "sg:phone":"+61 7 4633 1011",
    "sg:postcode":"4350",
    "sg:province":"QLD",
    "sg:tags":[
        "produce",
        "grain"
    ],
    "wof:name":"Q.P.D.",
    "wof:placetype":"venue"
},
  "geometry": {"coordinates":[151.90739400000001,-27.560493],"type":"Point"}
}