{
  "type": "Feature",
  "properties": {
    "addr:full":"174 Lawrence St Wodonga VIC 3689",
    "addr:housenumber":"174",
    "addr:postcode":"3689",
    "addr:street":"Lawrence St",
    "iso:country":"AU",
    "sg:address":"174 Lawrence St",
    "sg:city":"Wodonga",
    "sg:classifiers":[
        {
            "category":"Professional",
            "subcategory":"Employment Agencies",
            "type":"Services"
        }
    ],
    "sg:phone":"+61 2 6055 0800",
    "sg:postcode":"3689",
    "sg:province":"VIC",
    "wof:name":"Workways Association Inc. Employment Services",
    "wof:placetype":"venue"
},
  "geometry": {"coordinates":[146.88673399999999,-36.124199],"type":"Point"}
}