{
  "type": "Feature",
  "properties": {
    "iso:country":"AU",
    "sg:address":"19 Pearl Bay Ave",
    "sg:city":"Mosman",
    "sg:classifiers":[
        {
            "category":"Professional",
            "subcategory":"Management & Consulting",
            "type":"Services"
        }
    ],
    "sg:phone":"+61 2 9969 0560",
    "sg:postcode":"2088",
    "sg:province":"NSW",
    "sg:tags":[
        "consultant"
    ],
    "wof:name":"Bates & Associates",
    "wof:placetype":"venue"
},
  "geometry": {"coordinates":[151.24249267600001,-33.8103523254],"type":"Point"}
}