{
  "type": "Feature",
  "properties": {
    "addr:full":"8/ 25 Victoria St Wollongong NSW 2500",
    "addr:housenumber":"/ 25",
    "addr:postcode":"2500",
    "addr:street":"Victoria St",
    "iso:country":"AU",
    "sg:address":"8/ 25 Victoria St",
    "sg:city":"Wollongong",
    "sg:classifiers":[
        {
            "category":"Education",
            "subcategory":"Special Training",
            "type":"Public Place"
        }
    ],
    "sg:phone":"+61 2 4225 7721",
    "sg:postcode":"2500",
    "sg:province":"NSW",
    "sg:tags":[
        "tuition-educational"
    ],
    "wof:name":"Numberworks",
    "wof:placetype":"venue"
},
  "geometry": {"coordinates":[150.89091500000001,-34.422142],"type":"Point"}
}