{
  "type": "Feature",
  "properties": {
    "iso:country":"AU",
    "sg:address":"1D Byth St",
    "sg:city":"Stafford",
    "sg:classifiers":[
        {
            "category":"Home & Garden",
            "subcategory":"Home Furnishings",
            "type":"Retail Goods"
        }
    ],
    "sg:phone":"+61 7 3856 0144",
    "sg:postcode":"4053",
    "sg:province":"QLD",
    "sg:tags":[
        "shower",
        "screen"
    ],
    "wof:name":"Stylewise Security & Glass",
    "wof:placetype":"venue"
},
  "geometry": {"coordinates":[153.00738525400001,-27.409942627],"type":"Point"}
}