{
  "type": "Feature",
  "properties": {
    "iso:country":"AU",
    "sg:address":"1 Resthaven Ave",
    "sg:city":"Charmhaven",
    "sg:classifiers":[
        {
            "category":"Travel",
            "subcategory":"Resort",
            "type":"Entertainment"
        }
    ],
    "sg:phone":"+61 2 4393 9564",
    "sg:postcode":"2263",
    "sg:province":"NSW",
    "sg:tags":[
        "club",
        "caravan"
    ],
    "wof:name":"Caravan Club Of Australia",
    "wof:placetype":"venue"
},
  "geometry": {"coordinates":[151.504868,-33.226318],"type":"Point"}
}