{
  "type": "Feature",
  "properties": {
    "iso:country":"AU",
    "sg:address":"32 Bokhara Rd",
    "sg:city":"Caulfield South",
    "sg:classifiers":[
        {
            "category":"Sports & Exercise",
            "subcategory":"Gym",
            "type":"Entertainment"
        }
    ],
    "sg:phone":"+61 413 414 620",
    "sg:postcode":"3162",
    "sg:province":"VIC",
    "sg:tags":[
        "meditation"
    ],
    "wof:name":"Embrace Meditation & Personal Development",
    "wof:placetype":"venue"
},
  "geometry": {"coordinates":[145.03128051799999,-37.8933448792],"type":"Point"}
}