{
  "type": "Feature",
  "properties": {
    "addr:full":"U1/ 88 Millswyn St South Yarra VIC 3141",
    "addr:postcode":"3141",
    "addr:street":"U1 / 88 Millswyn St",
    "iso:country":"AU",
    "sg:address":"U1/ 88 Millswyn St",
    "sg:city":"South Yarra",
    "sg:classifiers":[
        {
            "category":"Transit Center",
            "subcategory":"Passenger",
            "type":"Transportation"
        }
    ],
    "sg:phone":"+61 3 9867 3901",
    "sg:postcode":"3141",
    "sg:province":"VIC",
    "sg:tags":[
        "retail",
        "toiletry",
        "perfume"
    ],
    "wof:name":"Fleurage",
    "wof:placetype":"venue"
},
  "geometry": {"coordinates":[144.980560303,-37.8353919983],"type":"Point"}
}