{
  "type": "Feature",
  "properties": {
    "iso:country":"AU",
    "sg:address":"27 West Church St",
    "sg:city":"Deloraine",
    "sg:classifiers":[
        {
            "category":"Manufacturing",
            "subcategory":"Signs",
            "type":"Manufacturing & Wholesale Goods"
        }
    ],
    "sg:phone":"+61 3 6362 3568",
    "sg:postcode":"7304",
    "sg:province":"TAS",
    "sg:tags":[
        "traffic",
        "safety"
    ],
    "wof:name":"Tranex Equipment",
    "wof:placetype":"venue"
},
  "geometry": {"coordinates":[146.652374,-41.52327],"type":"Point"}
}