{
  "type": "Feature",
  "properties": {
    "addr:full":"PO Box 247 Paddington QLD 4064",
    "addr:postcode":"4064",
    "iso:country":"AU",
    "sg:address":"PO Box 247",
    "sg:city":"Paddington",
    "sg:classifiers":[
        {
            "category":"Home & Garden",
            "subcategory":"Carpets & Floor Coverings",
            "type":"Retail Goods"
        }
    ],
    "sg:phone":"+61 7 3353 3191",
    "sg:postcode":"4064",
    "sg:province":"QLD",
    "sg:tags":[
        "flooring",
        "parquet"
    ],
    "wof:name":"JB Floor Sanding Pty Ltd",
    "wof:placetype":"venue"
},
  "geometry": {"coordinates":[153.00668335,-27.4619503021],"type":"Point"}
}