{
  "type": "Feature",
  "properties": {
    "addr:full":"11 Main St Grenfell NSW 2810",
    "addr:housenumber":"11",
    "addr:postcode":"2810",
    "addr:street":"Main St",
    "iso:country":"AU",
    "sg:address":"11 Main St",
    "sg:city":"Grenfell",
    "sg:classifiers":[
        {
            "category":"Shopping",
            "subcategory":"Department Store",
            "type":"Retail Goods"
        }
    ],
    "sg:phone":"+61 2 6343 2777",
    "sg:postcode":"2810",
    "sg:province":"NSW",
    "sg:tags":[
        "wool"
    ],
    "wof:name":"Western Wool Marketing Grenfell, NSW",
    "wof:placetype":"venue"
},
  "geometry": {"coordinates":[148.158203125,-33.894153595],"type":"Point"}
}