{
  "type": "Feature",
  "properties": {
    "iso:country":"AU",
    "sg:address":"Shp 13 433 Belgrave-Gembrook Rd",
    "sg:city":"Emerald",
    "sg:classifiers":[
        {
            "category":"Food & Beverages",
            "subcategory":"Bakery",
            "type":"Retail Goods"
        }
    ],
    "sg:phone":"+61 3 5968 6388",
    "sg:postcode":"3782",
    "sg:province":"VIC",
    "sg:tags":[
        "baker"
    ],
    "wof:name":"Lake Bakery",
    "wof:placetype":"venue"
},
  "geometry": {"coordinates":[145.464111,-37.922821],"type":"Point"}
}