{
  "type": "Feature",
  "properties": {
    "iso:country":"AU",
    "sg:address":"62- 68 New England Hwy",
    "sg:city":"Muswellbrook",
    "sg:classifiers":[
        {
            "category":"Travel",
            "subcategory":"Hotels & Motels",
            "type":"Entertainment"
        }
    ],
    "sg:phone":"+61 2 6543 1188",
    "sg:postcode":"2333",
    "sg:province":"NSW",
    "wof:name":"Hermitage Motel Muswellbrook",
    "wof:placetype":"venue"
},
  "geometry": {"coordinates":[150.89886474599999,-32.2148246765],"type":"Point"}
}