{
  "type": "Feature",
  "properties": {
    "iso:country":"AU",
    "sg:address":"Unit 15/ 4A Foundry Rd",
    "sg:city":"Seven Hills",
    "sg:classifiers":[
        {
            "category":"Government",
            "subcategory":"Department Of Motor Vehicles",
            "type":"Public Place"
        }
    ],
    "sg:phone":"+61 2 9838 7272",
    "sg:postcode":"2147",
    "sg:province":"NSW",
    "sg:tags":[
        "wholesaler",
        "mfrs",
        "accessory"
    ],
    "wof:name":"Motorsport Connections",
    "wof:placetype":"venue"
},
  "geometry": {"coordinates":[150.95562744099999,-33.7669715881],"type":"Point"}
}