{
  "type": "Feature",
  "properties": {
    "addr:full":"10 Hank St Heatherbrae NSW 2324",
    "addr:housenumber":"10",
    "addr:postcode":"2324",
    "addr:street":"Hank St",
    "iso:country":"AU",
    "sg:address":"10 Hank St",
    "sg:city":"Heatherbrae",
    "sg:classifiers":[
        {
            "category":"Food & Beverages",
            "subcategory":"Bakery",
            "type":"Retail Goods"
        }
    ],
    "sg:phone":"+61 2 4987 7105",
    "sg:postcode":"2324",
    "sg:province":"NSW",
    "sg:tags":[
        "baker"
    ],
    "wof:name":"Heatherbrae Bakery",
    "wof:placetype":"venue"
},
  "geometry": {"coordinates":[151.727127075,-32.791885376],"type":"Point"}
}