{
  "type": "Feature",
  "properties": {
    "addr:full":"PO Box 172 Mt Nebo QLD 4520",
    "addr:postcode":"4520",
    "iso:country":"AU",
    "sg:address":"PO Box 172",
    "sg:city":"Mt Nebo",
    "sg:classifiers":[
        {
            "category":"Mining & Drilling",
            "type":"Manufacturing & Wholesale Goods"
        }
    ],
    "sg:phone":"+61 7 3289 8329",
    "sg:postcode":"4520",
    "sg:province":"QLD",
    "sg:tags":[
        "geologist"
    ],
    "wof:name":"Gavin Gonsal",
    "wof:placetype":"venue"
},
  "geometry": {"coordinates":[152.78985599999999,-27.39813],"type":"Point"}
}