{
  "type": "Feature",
  "properties": {
    "iso:country":"AU",
    "sg:address":"63 Randell St",
    "sg:city":"Mannum",
    "sg:classifiers":[
        {
            "category":"Shopping",
            "subcategory":"Clothing, Apparel, & Fashions",
            "type":"Retail Goods"
        }
    ],
    "sg:phone":"+61 8 8569 2261",
    "sg:postcode":"5238",
    "sg:province":"SA",
    "sg:tags":[
        "lady",
        "wear"
    ],
    "wof:name":"Marion's Boutique",
    "wof:placetype":"venue"
},
  "geometry": {"coordinates":[139.31211852999999,-34.9140129089],"type":"Point"}
}