{
  "type": "Feature",
  "properties": {
    "iso:country":"AU",
    "sg:address":"Factory42 65 Canterbury Rd",
    "sg:city":"Montrose",
    "sg:classifiers":[
        {
            "category":"Building & Trades",
            "subcategory":"Construction",
            "type":"Services"
        }
    ],
    "sg:phone":"+61 3 9761 9024",
    "sg:postcode":"3765",
    "sg:province":"VIC",
    "sg:tags":[
        "roof"
    ],
    "wof:name":"M & K Enterprises Pty Ltd",
    "wof:placetype":"venue"
},
  "geometry": {"coordinates":[145.32728576700001,-37.8151245117],"type":"Point"}
}