{
  "type": "Feature",
  "properties": {
    "addr:full":"DFO Moorabin, Shop 55 Chadstone VIC 3148",
    "addr:housenumber":"55",
    "addr:postcode":"3148",
    "iso:country":"AU",
    "sg:address":"DFO Moorabin, Shop 55",
    "sg:city":"Chadstone",
    "sg:classifiers":[
        {
            "category":"Shopping",
            "type":"Retail Goods"
        }
    ],
    "sg:phone":"+61 3 9585 1900",
    "sg:postcode":"3148",
    "sg:province":"VIC",
    "sg:tags":[
        "clearance",
        "factory",
        "outlet"
    ],
    "wof:name":"Speedo",
    "wof:placetype":"venue"
},
  "geometry": {"coordinates":[145.07882690400001,-37.8825950623],"type":"Point"}
}