{
  "type": "Feature",
  "properties": {
    "addr:full":"28 Airport Rd Brooklyn Park SA 5032",
    "addr:housenumber":"28",
    "addr:postcode":"5032",
    "addr:street":"Airport Rd",
    "iso:country":"AU",
    "sg:address":"28 Airport Rd",
    "sg:city":"Brooklyn Park",
    "sg:classifiers":[
        {
            "category":"Building & Trades",
            "subcategory":"Construction",
            "type":"Services"
        }
    ],
    "sg:phone":"+61 8 8443 5309",
    "sg:postcode":"5032",
    "sg:province":"SA",
    "sg:tags":[
        "joinery"
    ],
    "wof:name":"Crammond Joinery",
    "wof:placetype":"venue"
},
  "geometry": {"coordinates":[138.54234314000001,-34.9291763306],"type":"Point"}
}