{
  "type": "Feature",
  "properties": {
    "addr:full":"331 Morgan St Broken Hill NSW 2880",
    "addr:housenumber":"331",
    "addr:postcode":"2880",
    "addr:street":"Morgan St",
    "iso:country":"AU",
    "sg:address":"331 Morgan St",
    "sg:city":"Broken Hill",
    "sg:classifiers":[
        {
            "category":"Retail",
            "subcategory":"Auto Repair",
            "type":"Services"
        }
    ],
    "sg:phone":"+61 8 8087 3984",
    "sg:postcode":"2880",
    "sg:province":"NSW",
    "sg:tags":[
        "repairer",
        "motor",
        "engineer"
    ],
    "wof:name":"R.J.D. Automotive & General Engineering",
    "wof:placetype":"venue"
},
  "geometry": {"coordinates":[141.456375122,-31.9451217651],"type":"Point"}
}