{
  "type": "Feature",
  "properties": {
    "addr:full":"Level 3, 460 Collins St Melbourne VIC 3000",
    "addr:housenumber":"460",
    "addr:postcode":"3000",
    "addr:street":"Collins St",
    "iso:country":"AU",
    "sg:address":"Level 3, 460 Collins St",
    "sg:city":"Melbourne",
    "sg:classifiers":[
        {
            "category":"Real Estate",
            "subcategory":"Real Estate Agent",
            "type":"Services"
        }
    ],
    "sg:phone":"+61 3 9621 3300",
    "sg:postcode":"3000",
    "sg:province":"VIC",
    "wof:name":"L J Hooker",
    "wof:placetype":"venue"
},
  "geometry": {"coordinates":[144.95892334000001,-37.8175544739],"type":"Point"}
}