{
  "type": "Feature",
  "properties": {
    "iso:country":"AU",
    "sg:address":"2 179 Sturt St",
    "sg:city":"Adelaide",
    "sg:classifiers":[
        {
            "category":"Personal",
            "subcategory":"Beauty Salon",
            "type":"Services"
        }
    ],
    "sg:phone":"+61 415 289 899",
    "sg:postcode":"5000",
    "sg:province":"SA",
    "sg:tags":[
        "hairdresser"
    ],
    "wof:name":"Elles Hair",
    "wof:placetype":"venue"
},
  "geometry": {"coordinates":[138.591964722,-34.933467865],"type":"Point"}
}