{
  "type": "Feature",
  "properties": {
    "addr:full":"102 Hume St Wodonga NSW 3689",
    "addr:housenumber":"102",
    "addr:postcode":"3689",
    "addr:street":"Hume St",
    "iso:country":"AU",
    "sg:address":"102 Hume St",
    "sg:city":"Wodonga",
    "sg:classifiers":[
        {
            "category":"Health Services",
            "subcategory":"Health Practitioner",
            "type":"Services"
        }
    ],
    "sg:phone":"+61 2 6020 8924",
    "sg:postcode":"3689",
    "sg:province":"NSW",
    "sg:tags":[
        "psychologist"
    ],
    "wof:name":"Mark Lamont",
    "wof:placetype":"venue"
},
  "geometry": {"coordinates":[146.88609299999999,-36.123039],"type":"Point"}
}