{
  "type": "Feature",
  "properties": {
    "addr:full":"55 Pitt St Dodges Ferry TAS 7173",
    "addr:housenumber":"55",
    "addr:postcode":"7173",
    "addr:street":"Pitt St",
    "iso:country":"AU",
    "sg:address":"55 Pitt St",
    "sg:city":"Dodges Ferry",
    "sg:classifiers":[
        {
            "category":"Building & Trades",
            "subcategory":"Construction",
            "type":"Services"
        }
    ],
    "sg:phone":"+61 3 6265 8753",
    "sg:postcode":"7173",
    "sg:province":"TAS",
    "sg:tags":[
        "joinery"
    ],
    "wof:name":"C Projects",
    "wof:placetype":"venue"
},
  "geometry": {"coordinates":[147.62892150900001,-42.8650970459],"type":"Point"}
}