{
  "type": "Feature",
  "properties": {
    "addr:full":"41 Armstrong St Middle Park VIC 3206",
    "addr:housenumber":"41",
    "addr:postcode":"3206",
    "addr:street":"Armstrong St",
    "iso:country":"AU",
    "sg:address":"41 Armstrong St",
    "sg:city":"Middle Park",
    "sg:classifiers":[
        {
            "category":"Health Services",
            "subcategory":"Doctor",
            "type":"Services"
        }
    ],
    "sg:phone":"+61 3 9699 4626",
    "sg:postcode":"3206",
    "sg:province":"VIC",
    "sg:tags":[
        "medical",
        "practitioner"
    ],
    "wof:name":"Whitmarsh Lisa Dr",
    "wof:placetype":"venue"
},
  "geometry": {"coordinates":[144.96366882300001,-37.8514137268],"type":"Point"}
}