{
  "type": "Feature",
  "properties": {
    "addr:full":"400 Pinjar Rd Wanneroo WA 6065",
    "addr:housenumber":"400",
    "addr:postcode":"6065",
    "addr:street":"Pinjar Rd",
    "iso:country":"AU",
    "sg:address":"400 Pinjar Rd",
    "sg:city":"Wanneroo",
    "sg:classifiers":[
        {
            "category":"Home & Garden",
            "subcategory":"Garden Supply",
            "type":"Retail Goods"
        }
    ],
    "sg:phone":"+61 8 9306 1788",
    "sg:postcode":"6065",
    "sg:province":"WA",
    "sg:tags":[
        "turf",
        "lawn"
    ],
    "wof:name":"Sir Walter",
    "wof:placetype":"venue"
},
  "geometry": {"coordinates":[115.80377960200001,-31.7097663879],"type":"Point"}
}