{
  "type": "Feature",
  "properties": {
    "iso:country":"AU",
    "sg:address":"31 Shirlow St",
    "sg:city":"Marrickville",
    "sg:classifiers":[
        {
            "category":"Food & Beverages",
            "subcategory":"Specialty",
            "type":"Retail Goods"
        }
    ],
    "sg:phone":"+61 2 9517 1765",
    "sg:postcode":"2204",
    "sg:province":"NSW",
    "sg:tags":[
        "delicacy"
    ],
    "wof:name":"Pacific Food Pty Ltd",
    "wof:placetype":"venue"
},
  "geometry": {"coordinates":[151.16751099999999,-33.911316],"type":"Point"}
}