{
  "type": "Feature",
  "properties": {
    "iso:country":"AU",
    "sg:address":"231 McKinnon Rd",
    "sg:city":"McKinnon",
    "sg:classifiers":[
        {
            "category":"Health Services",
            "subcategory":"Nursing And Care Facility",
            "type":"Services"
        }
    ],
    "sg:phone":"+61 3 9576 8111",
    "sg:postcode":"3204",
    "sg:province":"VIC",
    "sg:tags":[
        "home"
    ],
    "wof:name":"Claremont Terrace",
    "wof:placetype":"venue"
},
  "geometry": {"coordinates":[145.041565,-37.911324],"type":"Point"}
}