{
  "type": "Feature",
  "properties": {
    "addr:full":"1 Macquarie St Tamworth NSW 2340",
    "addr:housenumber":"1",
    "addr:postcode":"2340",
    "addr:street":"Macquarie St",
    "iso:country":"AU",
    "sg:address":"1 Macquarie St",
    "sg:city":"Tamworth",
    "sg:classifiers":[
        {
            "category":"Communications",
            "type":"Services"
        }
    ],
    "sg:phone":"+61 2 6766 3928",
    "sg:postcode":"2340",
    "sg:province":"NSW",
    "sg:tags":[
        "equipment",
        "satellite"
    ],
    "wof:name":"PeelTV Services P/L",
    "wof:placetype":"venue"
},
  "geometry": {"coordinates":[150.92535400400001,-31.0849742889],"type":"Point"}
}