{
  "type": "Feature",
  "properties": {
    "addr:full":"29 Cross La Mortdale NSW 2223",
    "addr:housenumber":"29",
    "addr:postcode":"2223",
    "addr:street":"Cross La",
    "iso:country":"AU",
    "sg:address":"29 Cross La",
    "sg:city":"Mortdale",
    "sg:classifiers":[
        {
            "category":"Food & Beverages",
            "subcategory":"Specialty",
            "type":"Retail Goods"
        }
    ],
    "sg:phone":"+61 2 9594 5598",
    "sg:postcode":"2223",
    "sg:province":"NSW",
    "sg:tags":[
        "product",
        "health"
    ],
    "wof:name":"Mortdale Health Foods",
    "wof:placetype":"venue"
},
  "geometry": {"coordinates":[151.080276489,-33.9685249329],"type":"Point"}
}