{
  "type": "Feature",
  "properties": {
    "iso:country":"AU",
    "sg:address":"201 Memorial Ave",
    "sg:city":"Ettalong",
    "sg:classifiers":[
        {
            "category":"Real Estate",
            "subcategory":"Real Estate Agent",
            "type":"Services"
        }
    ],
    "sg:phone":"+61 2 4341 1367",
    "sg:postcode":"2257",
    "sg:province":"NSW",
    "wof:name":"Ettalong Real Estate Agency Pty Ltd",
    "wof:placetype":"venue"
},
  "geometry": {"coordinates":[151.33514404300001,-33.514957428],"type":"Point"}
}