{
  "type": "Feature",
  "properties": {
    "addr:full":"236 Rundle St Adelaide SA 5000",
    "addr:housenumber":"236",
    "addr:postcode":"5000",
    "addr:street":"Rundle St",
    "iso:country":"AU",
    "sg:address":"236 Rundle St",
    "sg:city":"Adelaide",
    "sg:classifiers":[
        {
            "category":"Ice Cream",
            "type":"Food & Drink"
        }
    ],
    "sg:phone":"+61 8 8227 2631",
    "sg:postcode":"5000",
    "sg:province":"SA",
    "sg:tags":[
        "retail"
    ],
    "wof:name":"Cold Rock Ice Creamery",
    "wof:placetype":"venue"
},
  "geometry": {"coordinates":[138.60826110799999,-34.922416687],"type":"Point"}
}