{
  "type": "Feature",
  "properties": {
    "addr:full":"1374 Malvern Rd Malvern VIC 3144",
    "addr:housenumber":"1374",
    "addr:postcode":"3144",
    "addr:street":"Malvern Rd",
    "iso:country":"AU",
    "sg:address":"1374 Malvern Rd",
    "sg:city":"Malvern",
    "sg:classifiers":[
        {
            "category":"Health Services",
            "subcategory":"Health Practitioner",
            "type":"Services"
        }
    ],
    "sg:phone":"+61 3 9525 2022",
    "sg:postcode":"3144",
    "sg:province":"VIC",
    "sg:tags":[
        "homoeopath"
    ],
    "wof:name":"Gough Margaret, Greendale Natural Therapies",
    "wof:placetype":"venue"
},
  "geometry": {"coordinates":[145.041625977,-37.8532562256],"type":"Point"}
}