{
  "type": "Feature",
  "properties": {
    "iso:country":"AU",
    "sg:address":"5/ 42 Aero Rd",
    "sg:city":"Ingleburn",
    "sg:classifiers":[
        {
            "category":"Professional",
            "subcategory":"Art Services",
            "type":"Services"
        }
    ],
    "sg:phone":"+61 2 9605 9499",
    "sg:postcode":"2565",
    "sg:province":"NSW",
    "sg:tags":[
        "graphic",
        "designer"
    ],
    "wof:name":"Snap Printing",
    "wof:placetype":"venue"
},
  "geometry": {"coordinates":[150.86424255399999,-33.9916801453],"type":"Point"}
}