{
  "type": "Feature",
  "properties": {
    "addr:full":"Suite 7, 2 St Johns Ave Gordon NSW 2072",
    "addr:housenumber":"2",
    "addr:postcode":"2072",
    "addr:street":"St Johns Ave",
    "iso:country":"AU",
    "sg:address":"Suite 7, 2 St Johns Ave",
    "sg:city":"Gordon",
    "sg:classifiers":[
        {
            "category":"Health Services",
            "subcategory":"Dentist",
            "type":"Services"
        }
    ],
    "sg:phone":"+61 2 9499 3409",
    "sg:postcode":"2072",
    "sg:province":"NSW",
    "sg:tags":[
        "dental",
        "prosthetist"
    ],
    "wof:name":"Association Of Dental Prosthetists Inc",
    "wof:placetype":"venue"
},
  "geometry": {"coordinates":[151.153900147,-33.7563438416],"type":"Point"}
}