{
  "type": "Feature",
  "properties": {
    "addr:full":"15 Kitchener Ave Burswood WA 6100",
    "addr:housenumber":"15",
    "addr:postcode":"6100",
    "addr:street":"Kitchener Ave",
    "iso:country":"AU",
    "sg:address":"15 Kitchener Ave",
    "sg:city":"Burswood",
    "sg:classifiers":[
        {
            "category":"Parking",
            "type":"Transportation"
        }
    ],
    "sg:phone":"+61 8 9470 5823",
    "sg:postcode":"6100",
    "sg:province":"WA",
    "sg:tags":[
        "equipment",
        "system"
    ],
    "wof:name":"Romex Australia Pty Ltd",
    "wof:placetype":"venue"
},
  "geometry": {"coordinates":[115.89958190900001,-31.9654216766],"type":"Point"}
}