{
  "type": "Feature",
  "properties": {
    "addr:full":"2 Dural St Hornsby NSW 2077",
    "addr:housenumber":"2",
    "addr:postcode":"2077",
    "addr:street":"Dural St",
    "iso:country":"AU",
    "sg:address":"2 Dural St",
    "sg:city":"Hornsby",
    "sg:classifiers":[
        {
            "category":"Restaurant",
            "type":"Food & Drink"
        }
    ],
    "sg:phone":"+61 2 9477 1988",
    "sg:postcode":"2077",
    "sg:province":"NSW",
    "wof:name":"Bambino's Pizza & Pasta",
    "wof:placetype":"venue"
},
  "geometry": {"coordinates":[151.096969605,-33.7025108337],"type":"Point"}
}