{
  "type": "Feature",
  "properties": {
    "iso:country":"AU",
    "sg:address":"4 Alliance St",
    "sg:city":"East Maitland",
    "sg:classifiers":[
        {
            "category":"Building & Trades",
            "subcategory":"Landscaping Services",
            "type":"Services"
        }
    ],
    "sg:phone":"+61 434 230 298",
    "sg:postcode":"2323",
    "sg:province":"NSW",
    "sg:tags":[
        "inspection"
    ],
    "wof:name":"Ace Approvals Certification & Building Services",
    "wof:placetype":"venue"
},
  "geometry": {"coordinates":[151.597732544,-32.7541656494],"type":"Point"}
}