{
  "type": "Feature",
  "properties": {
    "iso:country":"AU",
    "sg:address":"98a Muller Rd",
    "sg:city":"Greenacres",
    "sg:classifiers":[
        {
            "category":"Building & Trades",
            "subcategory":"Construction",
            "type":"Services"
        }
    ],
    "sg:phone":"+61 8 8367 6119",
    "sg:postcode":"5086",
    "sg:province":"SA",
    "sg:tags":[
        "fencing",
        "contractor"
    ],
    "wof:name":"Flavio Sandstone Pty Ltd",
    "wof:placetype":"venue"
},
  "geometry": {"coordinates":[138.631134033,-34.8712997437],"type":"Point"}
}