{
  "type": "Feature",
  "properties": {
    "addr:full":"595 Flinders St Townsville QLD 4810",
    "addr:housenumber":"595",
    "addr:postcode":"4810",
    "addr:street":"Flinders St",
    "iso:country":"AU",
    "sg:address":"595 Flinders St",
    "sg:city":"Townsville",
    "sg:classifiers":[
        {
            "category":"Professional",
            "subcategory":"Computer Services",
            "type":"Services"
        }
    ],
    "sg:phone":"+61 7 4772 1144",
    "sg:postcode":"4810",
    "sg:province":"QLD",
    "sg:tags":[
        "information"
    ],
    "wof:name":"Brazier Motti",
    "wof:placetype":"venue"
},
  "geometry": {"coordinates":[146.809235,-19.266979],"type":"Point"}
}