{
  "type": "Feature",
  "properties": {
    "addr:full":"100 Milners Rd Yarra Junction VIC 3797",
    "addr:housenumber":"100",
    "addr:postcode":"3797",
    "addr:street":"Milners Rd",
    "iso:country":"AU",
    "sg:address":"100 Milners Rd",
    "sg:city":"Yarra Junction",
    "sg:classifiers":[
        {
            "category":"Professional",
            "subcategory":"Secretarial Services",
            "type":"Services"
        }
    ],
    "sg:phone":"+61 417 522 765",
    "sg:postcode":"3797",
    "sg:province":"VIC",
    "sg:tags":[
        "typing"
    ],
    "wof:name":"Lisken Secretarial Services",
    "wof:placetype":"venue"
},
  "geometry": {"coordinates":[145.61961364699999,-37.7933502197],"type":"Point"}
}