{
  "type": "Feature",
  "properties": {
    "addr:full":"24 Container St Tingalpa QLD 4173",
    "addr:postcode":"4173",
    "addr:street":"St",
    "iso:country":"AU",
    "sg:address":"24 Container St",
    "sg:city":"Tingalpa",
    "sg:classifiers":[
        {
            "category":"Retail",
            "subcategory":"Auto Repair",
            "type":"Services"
        }
    ],
    "sg:phone":"+61 7 3890 3900",
    "sg:postcode":"4173",
    "sg:province":"QLD",
    "sg:tags":[
        "muffler",
        "exhaust",
        "system"
    ],
    "wof:name":"Undacar Parts (QLD) Pty Ltd",
    "wof:placetype":"venue"
},
  "geometry": {"coordinates":[153.10926818900001,-27.4738464355],"type":"Point"}
}