{
  "type": "Feature",
  "properties": {
    "iso:country":"AU",
    "sg:address":"30A John St",
    "sg:city":"Rosewood",
    "sg:classifiers":[
        {
            "category":"Banks & Credit Unions",
            "subcategory":"Bank",
            "type":"Services"
        }
    ],
    "sg:phone":"+61 7 5464 2503",
    "sg:postcode":"4340",
    "sg:province":"QLD",
    "wof:name":"Bendigo Community Bank",
    "wof:placetype":"venue"
},
  "geometry": {"coordinates":[152.59092712399999,-27.63621521],"type":"Point"}
}