{
  "type": "Feature",
  "properties": {
    "addr:full":"Lot 58 Windsor Rd Kellyville NSW 2155",
    "addr:postcode":"2155",
    "addr:street":"Windsor Rd",
    "iso:country":"AU",
    "sg:address":"Lot 58 Windsor Rd",
    "sg:city":"Kellyville",
    "sg:classifiers":[
        {
            "category":"Home & Garden",
            "subcategory":"Garden Supply",
            "type":"Retail Goods"
        }
    ],
    "sg:phone":"+61 2 9629 8622",
    "sg:postcode":"2155",
    "sg:province":"NSW",
    "sg:tags":[
        "shed"
    ],
    "wof:name":"Shed Man The",
    "wof:placetype":"venue"
},
  "geometry": {"coordinates":[150.95787048299999,-33.7124977112],"type":"Point"}
}