{
  "type": "Feature",
  "properties": {
    "addr:full":"3 Homelands Ave Carlingford NSW 2118",
    "addr:housenumber":"3",
    "addr:postcode":"2118",
    "addr:street":"Homelands Ave",
    "iso:country":"AU",
    "sg:address":"3 Homelands Ave",
    "sg:city":"Carlingford",
    "sg:classifiers":[
        {
            "category":"Travel",
            "subcategory":"Hostel",
            "type":"Entertainment"
        }
    ],
    "sg:phone":"+61 2 8832 2027",
    "sg:postcode":"2118",
    "sg:province":"NSW",
    "sg:tags":[
        "home"
    ],
    "wof:name":"BCS Hayfield Court",
    "wof:placetype":"venue"
},
  "geometry": {"coordinates":[151.043823242,-33.7882461548],"type":"Point"}
}