{
  "type": "Feature",
  "properties": {
    "addr:full":"254A Lower Heidelberg Rd Ivanhoe East VIC 3079",
    "addr:housenumber":"254a",
    "addr:postcode":"3079",
    "addr:street":"Lower Heidelberg Rd",
    "iso:country":"AU",
    "sg:address":"254A Lower Heidelberg Rd",
    "sg:city":"Ivanhoe East",
    "sg:classifiers":[
        {
            "category":"Health Services",
            "subcategory":"Doctor",
            "type":"Services"
        }
    ],
    "sg:phone":"+61 3 9497 1694",
    "sg:postcode":"3079",
    "sg:province":"VIC",
    "sg:tags":[
        "podiatrist"
    ],
    "wof:name":"East Ivanhoe Podiatry",
    "wof:placetype":"venue"
},
  "geometry": {"coordinates":[145.059646606,-37.7729721069],"type":"Point"}
}