{
  "type": "Feature",
  "properties": {
    "iso:country":"AU",
    "sg:address":"1 Maroondah Hwy",
    "sg:city":"Ringwood",
    "sg:classifiers":[
        {
            "category":"Retail",
            "subcategory":"Veterinary Services",
            "type":"Services"
        }
    ],
    "sg:phone":"+61 3 9870 6440",
    "sg:postcode":"3134",
    "sg:province":"VIC",
    "sg:tags":[
        "surgeon"
    ],
    "wof:name":"Kim Rosenberg Dr",
    "wof:placetype":"venue"
},
  "geometry": {"coordinates":[145.213653564,-37.8170661926],"type":"Point"}
}