{
  "type": "Feature",
  "properties": {
    "addr:full":"Shop 16 Windsor Town Centre 6- 16 Kable St Windsor NSW 2756",
    "addr:housenumber":"shop 16;16",
    "addr:postcode":"2756",
    "addr:street":"Kable St",
    "iso:country":"AU",
    "sg:address":"Shop 16 Windsor Town Centre 6- 16 Kable St",
    "sg:city":"Windsor",
    "sg:classifiers":[
        {
            "category":"Food & Beverages",
            "subcategory":"Bakery",
            "type":"Retail Goods"
        }
    ],
    "sg:phone":"+61 2 4577 8033",
    "sg:postcode":"2756",
    "sg:province":"NSW",
    "sg:tags":[
        "baker"
    ],
    "wof:name":"Windsor Bakery",
    "wof:placetype":"venue"
},
  "geometry": {"coordinates":[150.821243286,-33.6054229736],"type":"Point"}
}