{
  "type": "Feature",
  "properties": {
    "iso:country":"AU",
    "sg:address":"Shp 61",
    "sg:city":"Harbourside Shopng Cntr, +91 Middle Cleveland",
    "sg:classifiers":[
        {
            "category":"Travel",
            "subcategory":"Travel Agent",
            "type":"Entertainment"
        }
    ],
    "sg:phone":"+61 7 3286 7900",
    "sg:postcode":"4163",
    "sg:province":"QLD",
    "sg:tags":[
        "consultant"
    ],
    "wof:name":"Harvey World Travel",
    "wof:placetype":"venue"
},
  "geometry": {"coordinates":[153.26783752399999,-27.5260181427],"type":"Point"}
}