{
  "type": "Feature",
  "properties": {
    "addr:full":"40 Loganlea Rd Waterford West QLD 4133",
    "addr:housenumber":"40",
    "addr:postcode":"4133",
    "addr:street":"Loganlea Rd",
    "iso:country":"AU",
    "sg:address":"40 Loganlea Rd",
    "sg:city":"Waterford West",
    "sg:classifiers":[
        {
            "category":"Real Estate",
            "subcategory":"Real Estate Agent",
            "type":"Services"
        }
    ],
    "sg:phone":"+61 7 3299 7733",
    "sg:postcode":"4133",
    "sg:province":"QLD",
    "wof:name":"Professionals - Waterford",
    "wof:placetype":"venue"
},
  "geometry": {"coordinates":[153.13661193900001,-27.6883678436],"type":"Point"}
}