{
  "type": "Feature",
  "properties": {
    "addr:full":"PO Box 5047 Moreland West VIC 3055",
    "addr:postcode":"3055",
    "addr:street":"West",
    "iso:country":"AU",
    "sg:address":"PO Box 5047",
    "sg:city":"Moreland West",
    "sg:classifiers":[
        {
            "category":"Banks & Credit Unions",
            "subcategory":"Financial Services",
            "type":"Services"
        }
    ],
    "sg:phone":"+61 3 9745 2233",
    "sg:postcode":"3055",
    "sg:province":"VIC",
    "sg:tags":[
        "planning"
    ],
    "wof:name":"Standard Capital",
    "wof:placetype":"venue"
},
  "geometry": {"coordinates":[144.940307617,-37.7639198303],"type":"Point"}
}