{
  "type": "Feature",
  "properties": {
    "iso:country":"AU",
    "sg:address":"Shp6/ 23 Simpson St",
    "sg:city":"Mt Isa",
    "sg:classifiers":[
        {
            "category":"Personal",
            "subcategory":"Beauty Salon",
            "type":"Services"
        }
    ],
    "sg:phone":"+61 7 4749 4755",
    "sg:postcode":"4825",
    "sg:province":"QLD",
    "sg:tags":[
        "hairdresser"
    ],
    "wof:name":"Bellaobsessions",
    "wof:placetype":"venue"
},
  "geometry": {"coordinates":[139.494247,-20.726301],"type":"Point"}
}