{
  "type": "Feature",
  "properties": {
    "iso:country":"AU",
    "sg:address":"Cnr Brisbane Rd & Bergin St",
    "sg:city":"Booval",
    "sg:classifiers":[
        {
            "category":"Retail",
            "subcategory":"Event Space",
            "type":"Services"
        }
    ],
    "sg:phone":"+61 7 3282 1577",
    "sg:postcode":"4304",
    "sg:province":"QLD",
    "sg:tags":[
        "venue",
        "reception",
        "wedding"
    ],
    "wof:name":"Swags Family Restaurant",
    "wof:placetype":"venue"
},
  "geometry": {"coordinates":[152.78590393100001,-27.6139144897],"type":"Point"}
}