{
  "type": "Feature",
  "properties": {
    "addr:full":"339 Walnut Ave Mildura VIC 3500",
    "addr:housenumber":"339",
    "addr:postcode":"3500",
    "addr:street":"Walnut Ave",
    "iso:country":"AU",
    "sg:address":"339 Walnut Ave",
    "sg:city":"Mildura",
    "sg:classifiers":[
        {
            "category":"Food & Beverages",
            "subcategory":"Bakery",
            "type":"Retail Goods"
        }
    ],
    "sg:phone":"+61 3 5023 7244",
    "sg:postcode":"3500",
    "sg:province":"VIC",
    "sg:tags":[
        "baker"
    ],
    "wof:name":"Buttercup Bakeries",
    "wof:placetype":"venue"
},
  "geometry": {"coordinates":[142.13911438,-34.1959915161],"type":"Point"}
}