{
  "type": "Feature",
  "properties": {
    "addr:full":"54 Paulson Rd Campbellfield VIC 3061",
    "addr:housenumber":"54",
    "addr:postcode":"3061",
    "addr:street":"Paulson Rd",
    "iso:country":"AU",
    "sg:address":"54 Paulson Rd",
    "sg:city":"Campbellfield",
    "sg:classifiers":[
        {
            "category":"Professional",
            "subcategory":"Printing & Photocopies",
            "type":"Services"
        }
    ],
    "sg:phone":"+61 3 9359 4077",
    "sg:postcode":"3061",
    "sg:province":"VIC",
    "sg:tags":[
        "screen",
        "printer"
    ],
    "wof:name":"Screen House Effect Pty Ltd",
    "wof:placetype":"venue"
},
  "geometry": {"coordinates":[144.96191406200001,-37.6803588867],"type":"Point"}
}