{
  "type": "Feature",
  "properties": {
    "addr:full":"21 Dilston Rd Dilston TAS 7252",
    "addr:housenumber":"21",
    "addr:postcode":"7252",
    "addr:street":"Dilston Rd",
    "iso:country":"AU",
    "sg:address":"21 Dilston Rd",
    "sg:city":"Dilston",
    "sg:classifiers":[
        {
            "category":"Shopping",
            "subcategory":"Gifts & Souvenirs",
            "type":"Retail Goods"
        }
    ],
    "sg:phone":"+61 3 6328 1303",
    "sg:postcode":"7252",
    "sg:province":"TAS",
    "sg:tags":[
        "shop",
        "supply"
    ],
    "wof:name":"DILSTON DISTRIBUTORS PTY LTD",
    "wof:placetype":"venue"
},
  "geometry": {"coordinates":[147.06861877399999,-41.3301506042],"type":"Point"}
}