{
  "type": "Feature",
  "properties": {
    "addr:full":"23 Sutherland St Coburg VIC 3058",
    "addr:housenumber":"23",
    "addr:postcode":"3058",
    "addr:street":"Sutherland St",
    "iso:country":"AU",
    "sg:address":"23 Sutherland St",
    "sg:city":"Coburg",
    "sg:classifiers":[
        {
            "category":"Building & Trades",
            "subcategory":"Construction",
            "type":"Services"
        }
    ],
    "sg:phone":"+61 417 563 005",
    "sg:postcode":"3058",
    "sg:province":"VIC",
    "sg:tags":[
        "home",
        "air conditioning"
    ],
    "wof:name":"D & S Heating And Cooling Pty Ltd",
    "wof:placetype":"venue"
},
  "geometry": {"coordinates":[144.9609375,-37.7386245728],"type":"Point"}
}