{
  "type": "Feature",
  "properties": {
    "addr:full":"325 Grenfell Rd Redwood Park SA 5097",
    "addr:housenumber":"325",
    "addr:postcode":"5097",
    "addr:street":"Grenfell Rd",
    "iso:country":"AU",
    "sg:address":"325 Grenfell Rd",
    "sg:city":"Redwood Park",
    "sg:classifiers":[
        {
            "category":"Structure",
            "subcategory":"Building",
            "type":"Public Place"
        }
    ],
    "sg:phone":"+61 8 8289 4725",
    "sg:postcode":"5097",
    "sg:province":"SA",
    "sg:tags":[
        "sail",
        "shade"
    ],
    "wof:name":"Shade Styles Pty Ltd",
    "wof:placetype":"venue"
},
  "geometry": {"coordinates":[138.709884644,-34.806186676],"type":"Point"}
}