{
  "type": "Feature",
  "properties": {
    "addr:full":"12 Maxflo Crt Highett VIC 3190",
    "addr:housenumber":"12",
    "addr:postcode":"3190",
    "addr:street":"Maxflo Crt",
    "iso:country":"AU",
    "sg:address":"12 Maxflo Crt",
    "sg:city":"Highett",
    "sg:classifiers":[
        {
            "category":"Health Services",
            "subcategory":"Nursing And Care Facility",
            "type":"Services"
        }
    ],
    "sg:phone":"+61 3 9532 0833",
    "sg:postcode":"3190",
    "sg:province":"VIC",
    "sg:tags":[
        "home"
    ],
    "wof:name":"Rosehill Nursing Home",
    "wof:placetype":"venue"
},
  "geometry": {"coordinates":[145.03248596200001,-37.952960968],"type":"Point"}
}