{
  "type": "Feature",
  "properties": {
    "iso:country":"AU",
    "sg:address":"7 Sweet St",
    "sg:city":"Winnellie",
    "sg:classifiers":[
        {
            "category":"Retail",
            "subcategory":"Auto Repair",
            "type":"Services"
        }
    ],
    "sg:phone":"+61 8 8947 1373",
    "sg:postcode":"0820",
    "sg:province":"NT",
    "sg:tags":[
        "automotive",
        "air conditioning"
    ],
    "wof:name":"Top North Auto Airconditioning",
    "wof:placetype":"venue"
},
  "geometry": {"coordinates":[130.87234497099999,-12.4293355942],"type":"Point"}
}