{
  "type": "Feature",
  "properties": {
    "addr:full":"Wilkinson Rd Murtho SA 5341",
    "addr:postcode":"5341",
    "addr:street":"Wilkinson Rd",
    "iso:country":"AU",
    "sg:address":"Wilkinson Rd",
    "sg:city":"Murtho",
    "sg:classifiers":[
        {
            "category":"Communications",
            "subcategory":"News Services",
            "type":"Services"
        }
    ],
    "sg:phone":"+61 1800 422 683",
    "sg:postcode":"5341",
    "sg:province":"SA",
    "sg:tags":[
        "information",
        "tourist",
        "attractions"
    ],
    "wof:name":"Above Renmark Houseboats",
    "wof:placetype":"venue"
},
  "geometry": {"coordinates":[140.741333008,-34.1757888794],"type":"Point"}
}