{
  "type": "Feature",
  "properties": {
    "iso:country":"AU",
    "sg:address":"3 Faraday Rd",
    "sg:city":"Padstow",
    "sg:classifiers":[
        {
            "category":"Health Services",
            "subcategory":"Doctor",
            "type":"Services"
        }
    ],
    "sg:phone":"+61 2 9773 0719",
    "sg:postcode":"2211",
    "sg:province":"NSW",
    "sg:tags":[
        "medical",
        "practitioner"
    ],
    "wof:name":"Papp P",
    "wof:placetype":"venue"
},
  "geometry": {"coordinates":[151.034515,-33.953564],"type":"Point"}
}