{
  "type": "Feature",
  "properties": {
    "addr:full":"146 Gardiners Rd Maclean NSW 2463",
    "addr:housenumber":"146",
    "addr:postcode":"2463",
    "addr:street":"Gardiners Rd",
    "iso:country":"AU",
    "sg:address":"146 Gardiners Rd",
    "sg:city":"Maclean",
    "sg:classifiers":[
        {
            "category":"Building & Trades",
            "subcategory":"Plumbing",
            "type":"Services"
        }
    ],
    "sg:phone":"+61 2 6645 1666",
    "sg:postcode":"2463",
    "sg:province":"NSW",
    "sg:tags":[
        "plumber",
        "gasfitters"
    ],
    "wof:name":"AMA Plumbing Services",
    "wof:placetype":"venue"
},
  "geometry": {"coordinates":[153.24717712399999,-29.4641628265],"type":"Point"}
}