{
  "type": "Feature",
  "properties": {
    "iso:country":"AU",
    "sg:address":"4 Hunt Crt",
    "sg:city":"Wantirna South",
    "sg:classifiers":[
        {
            "category":"Manufacturing",
            "subcategory":"Chemicals & Compounds",
            "type":"Manufacturing & Wholesale Goods"
        }
    ],
    "sg:phone":"+61 408 127 544",
    "sg:postcode":"3152",
    "sg:province":"VIC",
    "sg:tags":[
        "oil",
        "recovery",
        "dispersal",
        "spill"
    ],
    "wof:name":"Oil Spill Emergency Clean Up Squad",
    "wof:placetype":"venue"
},
  "geometry": {"coordinates":[145.224334717,-37.8883132935],"type":"Point"}
}