{
  "type": "Feature",
  "properties": {
    "iso:country":"AU",
    "sg:address":"Bruce Hwy",
    "sg:city":"Childers",
    "sg:classifiers":[
        {
            "category":"Autos & Motor Vehicles",
            "subcategory":"Fuel & Gas Station",
            "type":"Retail Goods"
        }
    ],
    "sg:phone":"+61 7 4126 2199",
    "sg:postcode":"4660",
    "sg:province":"QLD",
    "wof:name":"BP Australia Limited",
    "wof:placetype":"venue"
},
  "geometry": {"coordinates":[152.28631591800001,-25.2373962402],"type":"Point"}
}