{
  "type": "Feature",
  "properties": {
    "addr:full":"56 Lyell Hwy Hamilton TAS 7140",
    "addr:housenumber":"56",
    "addr:postcode":"7140",
    "addr:street":"Lyell Hwy",
    "iso:country":"AU",
    "sg:address":"56 Lyell Hwy",
    "sg:city":"Hamilton",
    "sg:classifiers":[
        {
            "category":"Cafe",
            "type":"Food & Drink"
        }
    ],
    "sg:phone":"+61 3 6286 3206",
    "sg:postcode":"7140",
    "sg:province":"TAS",
    "wof:name":"Platter Pies Cafe",
    "wof:placetype":"venue"
},
  "geometry": {"coordinates":[146.885696,-42.604034],"type":"Point"}
}