{
  "type": "Feature",
  "properties": {
    "addr:full":"22 Garfield Rd Riverstone NSW 2765",
    "addr:housenumber":"22",
    "addr:postcode":"2765",
    "addr:street":"Garfield Rd",
    "iso:country":"AU",
    "sg:address":"22 Garfield Rd",
    "sg:city":"Riverstone",
    "sg:classifiers":[
        {
            "category":"Cafe",
            "type":"Food & Drink"
        }
    ],
    "sg:phone":"+61 2 9627 1328",
    "sg:postcode":"2765",
    "sg:province":"NSW",
    "wof:name":"Zomps Cafe",
    "wof:placetype":"venue"
},
  "geometry": {"coordinates":[150.861602783,-33.6795196533],"type":"Point"}
}