{
  "type": "Feature",
  "properties": {
    "addr:full":"11 Beete St Welshpool WA 6106",
    "addr:housenumber":"11",
    "addr:postcode":"6106",
    "addr:street":"Beete St",
    "iso:country":"AU",
    "sg:address":"11 Beete St",
    "sg:city":"Welshpool",
    "sg:classifiers":[
        {
            "category":"Shopping",
            "subcategory":"Stationery & Office Supplies",
            "type":"Retail Goods"
        }
    ],
    "sg:phone":"+61 8 9353 2744",
    "sg:postcode":"6106",
    "sg:province":"WA",
    "sg:tags":[
        "packaging",
        "equipment",
        "sealing",
        "filling"
    ],
    "wof:name":"Integrated Packaging",
    "wof:placetype":"venue"
},
  "geometry": {"coordinates":[115.943580627,-31.9845371246],"type":"Point"}
}