{
  "type": "Feature",
  "properties": {
    "iso:country":"AU",
    "sg:address":"Unit 1/ 192 Maurius St",
    "sg:city":"Tamworth",
    "sg:classifiers":[
        {
            "category":"Banks & Credit Unions",
            "subcategory":"Investment Brokerage",
            "type":"Services"
        }
    ],
    "sg:phone":"+61 2 6761 2755",
    "sg:postcode":"2340",
    "sg:province":"NSW",
    "sg:tags":[
        "broker"
    ],
    "wof:name":"Bartercard North West NSW",
    "wof:placetype":"venue"
},
  "geometry": {"coordinates":[150.93389892600001,-31.0952568054],"type":"Point"}
}