{
  "type": "Feature",
  "properties": {
    "addr:full":"38 Gielgud Crs McDowall QLD 4053",
    "addr:housenumber":"38",
    "addr:postcode":"4053",
    "addr:street":"Gielgud Crs",
    "iso:country":"AU",
    "sg:address":"38 Gielgud Crs",
    "sg:city":"McDowall",
    "sg:classifiers":[
        {
            "category":"Professional",
            "subcategory":"Detective & Security Services",
            "type":"Services"
        }
    ],
    "sg:phone":"+61 7 3353 1696",
    "sg:postcode":"4053",
    "sg:province":"QLD",
    "sg:tags":[
        "consultant",
        "system"
    ],
    "wof:name":"Northern Security Services (Qld) Pty Ltd",
    "wof:placetype":"venue"
},
  "geometry": {"coordinates":[152.98908996599999,-27.3877601624],"type":"Point"}
}