{
  "type": "Feature",
  "properties": {
    "addr:full":"Shop G34, Centrepoint, 270 Little Collins St Melbourne VIC 3000",
    "addr:housenumber":"g34;270",
    "addr:postcode":"3000",
    "addr:street":"Little Collins St",
    "iso:country":"AU",
    "sg:address":"Shop G34, Centrepoint, 270 Little Collins St",
    "sg:city":"Melbourne",
    "sg:classifiers":[
        {
            "category":"Shopping",
            "subcategory":"Clothing, Apparel, & Fashions",
            "type":"Retail Goods"
        }
    ],
    "sg:phone":"+61 3 9639 8943",
    "sg:postcode":"3000",
    "sg:province":"VIC",
    "sg:tags":[
        "menswear"
    ],
    "wof:name":"Jag",
    "wof:placetype":"venue"
},
  "geometry": {"coordinates":[144.96563720699999,-37.8147659302],"type":"Point"}
}