{
  "type": "Feature",
  "properties": {
    "iso:country":"AU",
    "sg:address":"548 Kalamunda Rd",
    "sg:city":"High Wycombe",
    "sg:classifiers":[
        {
            "category":"Retail",
            "subcategory":"Veterinary Services",
            "type":"Services"
        }
    ],
    "sg:phone":"+61 8 9454 6915",
    "sg:postcode":"6057",
    "sg:province":"WA",
    "sg:tags":[
        "surgeon"
    ],
    "wof:name":"High Wycombe Vet Hospital",
    "wof:placetype":"venue"
},
  "geometry": {"coordinates":[116.003112793,-31.9349689484],"type":"Point"}
}