{
  "type": "Feature",
  "properties": {
    "iso:country":"AU",
    "sg:address":"230 Swam d St",
    "sg:city":"Richmond",
    "sg:classifiers":[
        {
            "category":"Shopping",
            "subcategory":"Gifts & Souvenirs",
            "type":"Retail Goods"
        }
    ],
    "sg:phone":"+61 3 9428 0286",
    "sg:postcode":"3121",
    "sg:province":"VIC",
    "sg:tags":[
        "print",
        "poster",
        "pictures"
    ],
    "wof:name":"Bordeaux Picture Framing Wholesale Pty Ltd",
    "wof:placetype":"venue"
},
  "geometry": {"coordinates":[144.99945068400001,-37.8170204163],"type":"Point"}
}