{
  "type": "Feature",
  "properties": {
    "iso:country":"AU",
    "sg:address":"78 Todd St",
    "sg:city":"Railway Estate",
    "sg:classifiers":[
        {
            "category":"Building & Trades",
            "subcategory":"Construction",
            "type":"Services"
        }
    ],
    "sg:phone":"+61 7 4721 5955",
    "sg:postcode":"4810",
    "sg:province":"QLD",
    "sg:tags":[
        "installation",
        "air conditioning"
    ],
    "wof:name":"Brett Andrews Airconditioning And Electrical Pty Ltd",
    "wof:placetype":"venue"
},
  "geometry": {"coordinates":[146.822372,-19.2803],"type":"Point"}
}