{
  "type": "Feature",
  "properties": {
    "addr:full":"53 Sandergrove Rd Strathalbyn SA 5255",
    "addr:housenumber":"53",
    "addr:postcode":"5255",
    "addr:street":"Sandergrove Rd",
    "iso:country":"AU",
    "sg:address":"53 Sandergrove Rd",
    "sg:city":"Strathalbyn",
    "sg:classifiers":[
        {
            "category":"Home & Garden",
            "subcategory":"Garden Supply",
            "type":"Retail Goods"
        }
    ],
    "sg:phone":"+61 8 8536 2477",
    "sg:postcode":"5255",
    "sg:province":"SA",
    "sg:tags":[
        "fertilizer"
    ],
    "wof:name":"Whittam Fertilizer Services",
    "wof:placetype":"venue"
},
  "geometry": {"coordinates":[138.886260986,-35.2632789612],"type":"Point"}
}