{
  "type": "Feature",
  "properties": {
    "addr:full":"48 Harvest Rd Greenbank QLD 4124",
    "addr:housenumber":"48",
    "addr:postcode":"4124",
    "addr:street":"Harvest Rd",
    "iso:country":"AU",
    "sg:address":"48 Harvest Rd",
    "sg:city":"Greenbank",
    "sg:classifiers":[
        {
            "category":"Home & Garden",
            "subcategory":"Building Materials",
            "type":"Retail Goods"
        }
    ],
    "sg:phone":"+61 7 3297 5054",
    "sg:postcode":"4124",
    "sg:province":"QLD",
    "sg:tags":[
        "retaining",
        "wall"
    ],
    "wof:name":"Re-Tain (Qld) Pty Ltd",
    "wof:placetype":"venue"
},
  "geometry": {"coordinates":[152.93772888199999,-27.717792511],"type":"Point"}
}