{
  "type": "Feature",
  "properties": {
    "addr:full":"335 Alison Rd Coogee NSW 2034",
    "addr:housenumber":"335",
    "addr:postcode":"2034",
    "addr:street":"Alison Rd",
    "iso:country":"AU",
    "sg:address":"335 Alison Rd",
    "sg:city":"Coogee",
    "sg:classifiers":[
        {
            "category":"Building & Trades",
            "subcategory":"Plumbing",
            "type":"Services"
        }
    ],
    "sg:phone":"+61 2 9665 8309",
    "sg:postcode":"2034",
    "sg:province":"NSW",
    "sg:tags":[
        "plumber",
        "gasfitters"
    ],
    "wof:name":"Williams D P",
    "wof:placetype":"venue"
},
  "geometry": {"coordinates":[151.256134033,-33.9156341553],"type":"Point"}
}