{
  "type": "Feature",
  "properties": {
    "addr:full":"13A Main St Cobram VIC 3644",
    "addr:housenumber":"13a",
    "addr:postcode":"3644",
    "addr:street":"Main St",
    "iso:country":"AU",
    "sg:address":"13A Main St",
    "sg:city":"Cobram",
    "sg:classifiers":[
        {
            "category":"Professional",
            "subcategory":"Accounting & Tax Preparation",
            "type":"Services"
        }
    ],
    "sg:phone":"+61 3 5872 1033",
    "sg:postcode":"3644",
    "sg:province":"VIC",
    "sg:tags":[
        "bookkeeping"
    ],
    "wof:name":"Thirteen A",
    "wof:placetype":"venue"
},
  "geometry": {"coordinates":[145.64686584500001,-35.9210624695],"type":"Point"}
}