{
  "type": "Feature",
  "properties": {
    "iso:country":"AU",
    "sg:address":"Shop 5, 20 Park Rd",
    "sg:city":"Milton",
    "sg:classifiers":[
        {
            "category":"Personal",
            "subcategory":"Beauty Salon",
            "type":"Services"
        }
    ],
    "sg:phone":"+61 7 3369 8877",
    "sg:postcode":"4064",
    "sg:province":"QLD",
    "sg:tags":[
        "hairdresser"
    ],
    "wof:name":"Ego Hair",
    "wof:placetype":"venue"
},
  "geometry": {"coordinates":[153.00462341299999,-27.4705600739],"type":"Point"}
}