{
  "type": "Feature",
  "properties": {
    "iso:country":"AU",
    "sg:address":"382 Sussex St",
    "sg:city":"Sydney",
    "sg:classifiers":[
        {
            "category":"Education",
            "subcategory":"University",
            "type":"Public Place"
        }
    ],
    "sg:phone":"+61 2 9267 6122",
    "sg:postcode":"2000",
    "sg:province":"NSW",
    "sg:tags":[
        "educational",
        "organisation",
        "cultural"
    ],
    "wof:name":"Nan Tien Temple (IBAA - International Buddhist Association Of Australia)",
    "wof:placetype":"venue"
},
  "geometry": {"coordinates":[151.20474243199999,-33.8765106201],"type":"Point"}
}