{
  "type": "Feature",
  "properties": {
    "iso:country":"AU",
    "sg:address":"13 Pheasant St",
    "sg:city":"Burwood",
    "sg:classifiers":[
        {
            "category":"Education",
            "subcategory":"Kindergarten",
            "type":"Public Place"
        }
    ],
    "sg:phone":"+61 3 9808 9724",
    "sg:postcode":"3125",
    "sg:province":"VIC",
    "sg:tags":[
        "pre-schools"
    ],
    "wof:name":"St Scholastica's Pre-School Centre",
    "wof:placetype":"venue"
},
  "geometry": {"coordinates":[145.125442505,-37.8516845703],"type":"Point"}
}