{
  "type": "Feature",
  "properties": {
    "iso:country":"AU",
    "sg:address":"Unit 22/ 8 Dennis Rd",
    "sg:city":"Springwood",
    "sg:classifiers":[
        {
            "category":"Real Estate",
            "subcategory":"Surveying",
            "type":"Services"
        }
    ],
    "sg:phone":"+61 7 3208 9006",
    "sg:postcode":"4127",
    "sg:province":"QLD",
    "sg:tags":[
        "building",
        "surveyor"
    ],
    "wof:name":"Alister Marr Fastrack Building Certification",
    "wof:placetype":"venue"
},
  "geometry": {"coordinates":[153.127716064,-27.621301651],"type":"Point"}
}