{
  "type": "Feature",
  "properties": {
    "addr:full":"270 Kynoch Rd Palm Tree QLD 4352",
    "addr:housenumber":"270",
    "addr:postcode":"4352",
    "addr:street":"Kynoch Rd",
    "iso:country":"AU",
    "sg:address":"270 Kynoch Rd",
    "sg:city":"Palm Tree",
    "sg:classifiers":[
        {
            "category":"Building & Trades",
            "subcategory":"Construction",
            "type":"Services"
        }
    ],
    "sg:phone":"+61 7 4697 8292",
    "sg:postcode":"4352",
    "sg:province":"QLD",
    "sg:tags":[
        "fencing",
        "contractor"
    ],
    "wof:name":"RG & HM Thomson",
    "wof:placetype":"venue"
},
  "geometry": {"coordinates":[152.140793,-27.390301],"type":"Point"}
}