{
  "type": "Feature",
  "properties": {
    "addr:full":"Shop L02/EK07 Penrith Plz 585 High St Penrith NSW 2750",
    "addr:housenumber":"l02;ek07;585",
    "addr:postcode":"2750",
    "addr:street":"Penrith Plz;High St",
    "iso:country":"AU",
    "sg:address":"Shop L02/EK07 Penrith Plz 585 High St",
    "sg:city":"Penrith",
    "sg:classifiers":[
        {
            "category":"Cafe",
            "type":"Food & Drink"
        }
    ],
    "sg:phone":"+61 2 4732 5755",
    "sg:postcode":"2750",
    "sg:province":"NSW",
    "wof:name":"Gloria Jean's Coffees",
    "wof:placetype":"venue"
},
  "geometry": {"coordinates":[150.68374633799999,-33.7659645081],"type":"Point"}
}