{
  "type": "Feature",
  "properties": {
    "addr:full":"4 Tenville Crt Yamanto QLD 4305",
    "addr:housenumber":"4",
    "addr:postcode":"4305",
    "addr:street":"Tenville Crt",
    "iso:country":"AU",
    "sg:address":"4 Tenville Crt",
    "sg:city":"Yamanto",
    "sg:classifiers":[
        {
            "category":"Building & Trades",
            "subcategory":"Plumbing",
            "type":"Services"
        }
    ],
    "sg:phone":"+61 417 629 617",
    "sg:postcode":"4305",
    "sg:province":"QLD",
    "sg:tags":[
        "plumber",
        "gasfitters"
    ],
    "wof:name":"Terry Gillam Plumbing",
    "wof:placetype":"venue"
},
  "geometry": {"coordinates":[152.76008605999999,-27.6918315887],"type":"Point"}
}