{
  "type": "Feature",
  "properties": {
    "addr:full":"86 MacLeod St Bairnsdale VIC 3875",
    "addr:housenumber":"86",
    "addr:postcode":"3875",
    "addr:street":"Macleod St",
    "iso:country":"AU",
    "sg:address":"86 MacLeod St",
    "sg:city":"Bairnsdale",
    "sg:classifiers":[
        {
            "category":"Autos & Motor Vehicles",
            "subcategory":"Auto Supplies",
            "type":"Retail Goods"
        }
    ],
    "sg:phone":"+61 3 5152 3202",
    "sg:postcode":"3875",
    "sg:province":"VIC",
    "sg:tags":[
        "part",
        "cycles",
        "accessory"
    ],
    "wof:name":"J.R's Mower & Motorcycle",
    "wof:placetype":"venue"
},
  "geometry": {"coordinates":[147.63082885700001,-37.8273048401],"type":"Point"}
}