{
  "type": "Feature",
  "properties": {
    "iso:country":"AU",
    "sg:address":"2 Cherokee Rd",
    "sg:city":"Jandakot",
    "sg:classifiers":[
        {
            "category":"Building & Trades",
            "subcategory":"Construction",
            "type":"Services"
        }
    ],
    "sg:phone":"+61 8 9414 1223",
    "sg:postcode":"6164",
    "sg:province":"WA",
    "sg:tags":[
        "welding"
    ],
    "wof:name":"Jandakot Welding & Engineering",
    "wof:placetype":"venue"
},
  "geometry": {"coordinates":[115.880524,-32.088924],"type":"Point"}
}