{
  "type": "Feature",
  "properties": {
    "addr:full":"66 Compton Rd Underwood QLD 4119",
    "addr:housenumber":"66",
    "addr:postcode":"4119",
    "addr:street":"Compton Rd",
    "iso:country":"AU",
    "sg:address":"66 Compton Rd",
    "sg:city":"Underwood",
    "sg:classifiers":[
        {
            "category":"Home & Garden",
            "subcategory":"Building Materials",
            "type":"Retail Goods"
        }
    ],
    "sg:phone":"+61 13 24 52",
    "sg:postcode":"4119",
    "sg:province":"QLD",
    "sg:tags":[
        "merchant",
        "glass",
        "glazier"
    ],
    "wof:name":"O&#039;Brien",
    "wof:placetype":"venue"
},
  "geometry": {"coordinates":[153.109283447,-27.6194667816],"type":"Point"}
}