{
  "type": "Feature",
  "properties": {
    "addr:full":"19 Princes Domain Drv Hallam VIC 3803",
    "addr:housenumber":"19",
    "addr:postcode":"3803",
    "addr:street":"Princes Domain Drv",
    "iso:country":"AU",
    "sg:address":"19 Princes Domain Drv",
    "sg:city":"Hallam",
    "sg:classifiers":[
        {
            "category":"Professional",
            "subcategory":"Accounting & Tax Preparation",
            "type":"Services"
        }
    ],
    "sg:phone":"+61 3 9702 3420",
    "sg:postcode":"3803",
    "sg:province":"VIC",
    "sg:tags":[
        "accountant",
        "auditor"
    ],
    "wof:name":"Able Accounting & Bookkeeping",
    "wof:placetype":"venue"
},
  "geometry": {"coordinates":[145.26573181099999,-38.0026435852],"type":"Point"}
}