{
  "type": "Feature",
  "properties": {
    "iso:country":"AU",
    "sg:address":"3/76- 82 Maroondah Hwy",
    "sg:city":"Ringwood",
    "sg:classifiers":[
        {
            "category":"Home & Garden",
            "subcategory":"Carpets & Floor Coverings",
            "type":"Retail Goods"
        }
    ],
    "sg:phone":"+61 3 9879 1622",
    "sg:postcode":"3134",
    "sg:province":"VIC",
    "sg:tags":[
        "wood"
    ],
    "wof:name":"Floorworld",
    "wof:placetype":"venue"
},
  "geometry": {"coordinates":[145.22569274899999,-37.8166275024],"type":"Point"}
}