{
  "type": "Feature",
  "properties": {
    "addr:full":"38 Digby Rd Erina NSW 2250",
    "addr:housenumber":"38",
    "addr:postcode":"2250",
    "addr:street":"Digby Rd",
    "iso:country":"AU",
    "sg:address":"38 Digby Rd",
    "sg:city":"Erina",
    "sg:classifiers":[
        {
            "category":"Building & Trades",
            "subcategory":"Construction",
            "type":"Services"
        }
    ],
    "sg:phone":"+61 414 434 075",
    "sg:postcode":"2250",
    "sg:province":"NSW",
    "sg:tags":[
        "contractor"
    ],
    "wof:name":"Melnik Building Services",
    "wof:placetype":"venue"
},
  "geometry": {"coordinates":[151.38481140100001,-33.4281616211],"type":"Point"}
}