{
  "type": "Feature",
  "properties": {
    "addr:full":"Unit 4/ 35 Chapple St Gladstone QLD 4680",
    "addr:housenumber":"35",
    "addr:postcode":"4680",
    "addr:street":"Chapple St",
    "iso:country":"AU",
    "sg:address":"Unit 4/ 35 Chapple St",
    "sg:city":"Gladstone",
    "sg:classifiers":[
        {
            "category":"Transit Center",
            "subcategory":"Freight",
            "type":"Transportation"
        }
    ],
    "sg:phone":"+61 7 4972 0700",
    "sg:postcode":"4680",
    "sg:province":"QLD",
    "sg:tags":[
        "ship",
        "provedores"
    ],
    "wof:name":"Shipstores Pty Ltd",
    "wof:placetype":"venue"
},
  "geometry": {"coordinates":[151.240600586,-23.8425617218],"type":"Point"}
}