{
  "type": "Feature",
  "properties": {
    "addr:full":"7 Amersham Crs Butler WA 6032",
    "addr:housenumber":"7",
    "addr:postcode":"6032",
    "addr:street":"Amersham Crs",
    "iso:country":"AU",
    "sg:address":"7 Amersham Crs",
    "sg:city":"Butler",
    "sg:classifiers":[
        {
            "category":"Education",
            "subcategory":"School",
            "type":"Public Place"
        }
    ],
    "sg:phone":"+61 8 9562 4344",
    "sg:postcode":"6032",
    "sg:province":"WA",
    "sg:tags":[
        "state",
        "except",
        "nsw"
    ],
    "wof:name":"Schools Government (Public)",
    "wof:placetype":"venue"
},
  "geometry": {"coordinates":[115.75560760499999,-31.6355400085],"type":"Point"}
}