{
  "type": "Feature",
  "properties": {
    "iso:country":"AU",
    "sg:address":"Shop 1 107 Station St",
    "sg:city":"Ferntree Gully",
    "sg:classifiers":[
        {
            "category":"Education",
            "subcategory":"Vocational School",
            "type":"Public Place"
        }
    ],
    "sg:phone":"+61 3 9758 0990",
    "sg:postcode":"3156",
    "sg:province":"VIC",
    "sg:tags":[
        "cake",
        "decorating",
        "decorator"
    ],
    "wof:name":"Jennifer Anne's Cakes",
    "wof:placetype":"venue"
},
  "geometry": {"coordinates":[145.29458618199999,-37.882270813],"type":"Point"}
}