{
  "type": "Feature",
  "properties": {
    "iso:country":"AU",
    "sg:address":"16- 28 Parramatta Rd",
    "sg:city":"Summer Hill",
    "sg:classifiers":[
        {
            "category":"Home & Garden",
            "subcategory":"Garden Supply",
            "type":"Retail Goods"
        }
    ],
    "sg:phone":"+61 2 9798 5155",
    "sg:postcode":"2130",
    "sg:province":"NSW",
    "sg:tags":[
        "statuary",
        "fountains",
        "sundial"
    ],
    "wof:name":"Menduni Garden Artistry",
    "wof:placetype":"venue"
},
  "geometry": {"coordinates":[151.14291381800001,-33.8884811401],"type":"Point"}
}