{
  "type": "Feature",
  "properties": {
    "addr:full":"357 Bay St Brighton North VIC 3186",
    "addr:housenumber":"357",
    "addr:postcode":"3186",
    "addr:street":"Bay St",
    "iso:country":"AU",
    "sg:address":"357 Bay St",
    "sg:city":"Brighton North",
    "sg:classifiers":[
        {
            "category":"Shopping",
            "subcategory":"Crafts & Fabrics",
            "type":"Retail Goods"
        }
    ],
    "sg:phone":"+61 3 9596 5389",
    "sg:postcode":"3186",
    "sg:province":"VIC",
    "sg:tags":[
        "supply"
    ],
    "wof:name":"Embroidery Den The",
    "wof:placetype":"venue"
},
  "geometry": {"coordinates":[145.00413513199999,-37.9055900574],"type":"Point"}
}