{
  "type": "Feature",
  "properties": {
    "addr:full":"1/ 42 Kurrajong St Mt Druitt NSW 2770",
    "addr:housenumber":"/ 42",
    "addr:postcode":"2770",
    "addr:street":"Kurrajong St Mt",
    "iso:country":"AU",
    "sg:address":"1/ 42 Kurrajong St",
    "sg:city":"Mt Druitt",
    "sg:classifiers":[
        {
            "category":"Building & Trades",
            "subcategory":"Construction",
            "type":"Services"
        }
    ],
    "sg:phone":"+61 2 9832 9122",
    "sg:postcode":"2770",
    "sg:province":"NSW",
    "sg:tags":[
        "home",
        "air conditioning"
    ],
    "wof:name":"Signature Appliances Pty Ltd",
    "wof:placetype":"venue"
},
  "geometry": {"coordinates":[150.81271362300001,-33.7657661438],"type":"Point"}
}