{
  "type": "Feature",
  "properties": {
    "addr:full":"457 Brooker Hwy Moonah TAS 7009",
    "addr:housenumber":"457",
    "addr:postcode":"7009",
    "addr:street":"Brooker Hwy",
    "iso:country":"AU",
    "sg:address":"457 Brooker Hwy",
    "sg:city":"Moonah",
    "sg:classifiers":[
        {
            "category":"Retail",
            "subcategory":"Repair Shop",
            "type":"Services"
        }
    ],
    "sg:phone":"+61 3 6272 5980",
    "sg:postcode":"7009",
    "sg:province":"TAS",
    "sg:tags":[
        "upholsterer"
    ],
    "wof:name":"C.H. Gearman Upholstery",
    "wof:placetype":"venue"
},
  "geometry": {"coordinates":[147.296875,-42.8324279785],"type":"Point"}
}