{
  "type": "Feature",
  "properties": {
    "addr:full":"45 Alderbrook Ave Mulgrave VIC 3170",
    "addr:housenumber":"45",
    "addr:postcode":"3170",
    "addr:street":"Alderbrook Ave",
    "iso:country":"AU",
    "sg:address":"45 Alderbrook Ave",
    "sg:city":"Mulgrave",
    "sg:classifiers":[
        {
            "category":"Building & Trades",
            "subcategory":"Construction",
            "type":"Services"
        }
    ],
    "sg:phone":"+61 3 9701 1355",
    "sg:postcode":"3170",
    "sg:province":"VIC",
    "sg:tags":[
        "renovation",
        "alterations",
        "extension",
        "contractor"
    ],
    "wof:name":"Horvath John",
    "wof:placetype":"venue"
},
  "geometry": {"coordinates":[145.20416259800001,-37.9286422729],"type":"Point"}
}