{
  "type": "Feature",
  "properties": {
    "iso:country":"AU",
    "sg:address":"124 Bridport St",
    "sg:city":"Albert Park",
    "sg:classifiers":[
        {
            "category":"Shopping",
            "subcategory":"Department Store",
            "type":"Retail Goods"
        }
    ],
    "sg:phone":"+61 3 9690 6633",
    "sg:postcode":"3206",
    "sg:province":"VIC",
    "sg:tags":[
        "wool"
    ],
    "wof:name":"Wool Baa",
    "wof:placetype":"venue"
},
  "geometry": {"coordinates":[144.956116,-37.840443],"type":"Point"}
}