{
  "type": "Feature",
  "properties": {
    "addr:full":"124 Bridport St Albert Park VIC 3206",
    "addr:housenumber":"124",
    "addr:postcode":"3206",
    "addr:street":"Bridport St",
    "iso:country":"AU",
    "sg:address":"124 Bridport St",
    "sg:city":"Albert Park",
    "sg:classifiers":[
        {
            "category":"Shopping",
            "subcategory":"Department Store",
            "type":"Retail Goods"
        }
    ],
    "sg:phone":"+61 3 9690 6633",
    "sg:postcode":"3206",
    "sg:province":"VIC",
    "sg:tags":[
        "wool"
    ],
    "wof:name":"Wool Baa",
    "wof:placetype":"venue"
},
  "geometry": {"coordinates":[144.95611600000001,-37.840443],"type":"Point"}
}