{
  "type": "Feature",
  "properties": {
    "addr:full":"39 Weyba St Sunshine Beach QLD 4567",
    "addr:housenumber":"39",
    "addr:postcode":"4567",
    "addr:street":"Weyba St",
    "iso:country":"AU",
    "sg:address":"39 Weyba St",
    "sg:city":"Sunshine Beach",
    "sg:classifiers":[
        {
            "category":"Utilities",
            "subcategory":"Electric",
            "type":"Services"
        }
    ],
    "sg:phone":"+61 7 5473 5999",
    "sg:postcode":"4567",
    "sg:province":"QLD",
    "sg:tags":[
        "electrical",
        "contractor"
    ],
    "wof:name":"Ryan Electrical",
    "wof:placetype":"venue"
},
  "geometry": {"coordinates":[153.07890319800001,-26.4088382721],"type":"Point"}
}