{
  "type": "Feature",
  "properties": {
    "addr:full":"23 Brigantine St Byron Bay NSW 2481",
    "addr:housenumber":"23",
    "addr:postcode":"2481",
    "addr:street":"Brigantine St",
    "iso:country":"AU",
    "sg:address":"23 Brigantine St",
    "sg:city":"Byron Bay",
    "sg:classifiers":[
        {
            "category":"Shopping",
            "subcategory":"Shoes",
            "type":"Retail Goods"
        }
    ],
    "sg:phone":"+61 2 6685 7413",
    "sg:postcode":"2481",
    "sg:province":"NSW",
    "sg:tags":[
        "footwear"
    ],
    "wof:name":"Bliss Shoes",
    "wof:placetype":"venue"
},
  "geometry": {"coordinates":[153.58152770999999,-28.6354885101],"type":"Point"}
}