{
  "type": "Feature",
  "properties": {
    "iso:country":"AU",
    "sg:address":"25 Katanning St",
    "sg:city":"Bayswater",
    "sg:classifiers":[
        {
            "category":"Home & Garden",
            "subcategory":"Building Materials",
            "type":"Retail Goods"
        }
    ],
    "sg:phone":"+61 8 9279 3880",
    "sg:postcode":"6053",
    "sg:province":"WA",
    "sg:tags":[
        "secondhand"
    ],
    "sg:website":"http://www.vinsansalvage.com.au",
    "wof:name":"Vinsan Salvage",
    "wof:placetype":"venue"
},
  "geometry": {"coordinates":[115.92980194099999,-31.9194736481],"type":"Point"}
}