{
  "type": "Feature",
  "properties": {
    "addr:full":"2 Darghan St Glebe NSW 2037",
    "addr:housenumber":"2",
    "addr:postcode":"2037",
    "addr:street":"Darghan St",
    "iso:country":"AU",
    "sg:address":"2 Darghan St",
    "sg:city":"Glebe",
    "sg:classifiers":[
        {
            "category":"Professional",
            "subcategory":"Computer Services",
            "type":"Services"
        }
    ],
    "sg:phone":"+61 2 9552 2066",
    "sg:postcode":"2037",
    "sg:province":"NSW",
    "sg:tags":[
        "consultant",
        "system"
    ],
    "wof:name":"Information Design Pty Ltd",
    "wof:placetype":"venue"
},
  "geometry": {"coordinates":[151.190963745,-33.87890625],"type":"Point"}
}