{
  "type": "Feature",
  "properties": {
    "addr:full":"139 Weaponess Rd Wembley Downs WA 6019",
    "addr:housenumber":"139",
    "addr:postcode":"6019",
    "addr:street":"Weaponess Rd",
    "iso:country":"AU",
    "sg:address":"139 Weaponess Rd",
    "sg:city":"Wembley Downs",
    "sg:classifiers":[
        {
            "category":"Health Services",
            "subcategory":"Dentist",
            "type":"Services"
        }
    ],
    "sg:phone":"+61 8 9341 3331",
    "sg:postcode":"6019",
    "sg:province":"WA",
    "wof:name":"Lifestyle Dental Studio",
    "wof:placetype":"venue"
},
  "geometry": {"coordinates":[115.772850037,-31.9112606049],"type":"Point"}
}