{
  "type": "Feature",
  "properties": {
    "addr:full":"275 Princes Hwy Unanderra NSW 2526",
    "addr:housenumber":"275",
    "addr:postcode":"2526",
    "addr:street":"Princes Hwy",
    "iso:country":"AU",
    "sg:address":"275 Princes Hwy",
    "sg:city":"Unanderra",
    "sg:classifiers":[
        {
            "category":"Commercial Area",
            "type":"Public Place"
        }
    ],
    "sg:phone":"+61 2 4271 5666",
    "sg:postcode":"2526",
    "sg:province":"NSW",
    "sg:tags":[
        "heavy",
        "carrier"
    ],
    "wof:name":"Verdons Transport",
    "wof:placetype":"venue"
},
  "geometry": {"coordinates":[150.832321167,-34.4667701721],"type":"Point"}
}