{
  "type": "Feature",
  "properties": {
    "iso:country":"AU",
    "sg:address":"41 Swan St",
    "sg:city":"Blackburn South",
    "sg:classifiers":[
        {
            "category":"Personal",
            "subcategory":"Massage",
            "type":"Services"
        }
    ],
    "sg:phone":"+61 414 658 044",
    "sg:postcode":"3130",
    "sg:province":"VIC",
    "sg:tags":[
        "therapy"
    ],
    "wof:name":"Advantage Remedial Massage Therapies",
    "wof:placetype":"venue"
},
  "geometry": {"coordinates":[145.139205933,-37.8402633667],"type":"Point"}
}