{
  "type": "Feature",
  "properties": {
    "addr:full":"155 Docker St Wagga Wagga NSW 2650",
    "addr:housenumber":"155",
    "addr:postcode":"2650",
    "addr:street":"Docker St",
    "iso:country":"AU",
    "sg:address":"155 Docker St",
    "sg:city":"Wagga Wagga",
    "sg:classifiers":[
        {
            "category":"Organizations",
            "subcategory":"Community Association",
            "type":"Services"
        }
    ],
    "sg:phone":"+61 2 6921 6369",
    "sg:postcode":"2650",
    "sg:province":"NSW",
    "sg:tags":[
        "organisation",
        "family",
        "welfare"
    ],
    "wof:name":"Aboriginal Childrens Service",
    "wof:placetype":"venue"
},
  "geometry": {"coordinates":[147.35949707,-35.1101341248],"type":"Point"}
}