{
  "type": "Feature",
  "properties": {
    "iso:country":"AU",
    "sg:address":"1 Burlington Crs",
    "sg:city":"Leopold",
    "sg:classifiers":[
        {
            "category":"Building & Trades",
            "subcategory":"Construction",
            "type":"Services"
        }
    ],
    "sg:phone":"+61 3 5250 3669",
    "sg:postcode":"3224",
    "sg:province":"VIC",
    "sg:tags":[
        "concrete",
        "contractor"
    ],
    "wof:name":"A & B Concreting Contractors",
    "wof:placetype":"venue"
},
  "geometry": {"coordinates":[144.46253999999999,-38.196381],"type":"Point"}
}