{
  "type": "Feature",
  "properties": {
    "addr:full":"447 Homer St Earlwood NSW 2206",
    "addr:housenumber":"447",
    "addr:postcode":"2206",
    "addr:street":"Homer St",
    "iso:country":"AU",
    "sg:address":"447 Homer St",
    "sg:city":"Earlwood",
    "sg:classifiers":[
        {
            "category":"Education",
            "subcategory":"Kindergarten",
            "type":"Public Place"
        }
    ],
    "sg:phone":"+61 2 9718 1185",
    "sg:postcode":"2206",
    "sg:province":"NSW",
    "sg:tags":[
        "pre-schools"
    ],
    "wof:name":"Earlwood Uniting Church Pre-School",
    "wof:placetype":"venue"
},
  "geometry": {"coordinates":[151.11990399999999,-33.928017],"type":"Point"}
}