{
  "type": "Feature",
  "properties": {
    "addr:full":"101 Switch Back Rd Chirnside Park VIC 3116",
    "addr:housenumber":"101",
    "addr:postcode":"3116",
    "addr:street":"Switch Back Rd",
    "iso:country":"AU",
    "sg:address":"101 Switch Back Rd",
    "sg:city":"Chirnside Park",
    "sg:classifiers":[
        {
            "category":"Personal",
            "subcategory":"Piercing",
            "type":"Services"
        }
    ],
    "sg:phone":"+61 408 306 109",
    "sg:postcode":"3116",
    "sg:province":"VIC",
    "sg:tags":[
        "body",
        "ear"
    ],
    "wof:name":"Dracco Piercing",
    "wof:placetype":"venue"
},
  "geometry": {"coordinates":[145.325119019,-37.7444496155],"type":"Point"}
}