{
  "type": "Feature",
  "properties": {
    "addr:full":"49- 53 Church St Parramatta NSW 2151",
    "addr:housenumber":"53",
    "addr:postcode":"2151",
    "addr:street":"Church St",
    "iso:country":"AU",
    "sg:address":"49- 53 Church St",
    "sg:city":"Parramatta",
    "sg:classifiers":[
        {
            "category":"Autos & Motor Vehicles",
            "subcategory":"Automobile Sales",
            "type":"Retail Goods"
        }
    ],
    "sg:phone":"+61 2 9841 4000",
    "sg:postcode":"2151",
    "sg:province":"NSW",
    "sg:tags":[
        "car",
        "new"
    ],
    "wof:name":"Audi Centre Parramatta",
    "wof:placetype":"venue"
},
  "geometry": {"coordinates":[151.00405883799999,-33.8222122192],"type":"Point"}
}