{
  "type": "Feature",
  "properties": {
    "iso:country":"AU",
    "sg:address":"369 Grieve Rd",
    "sg:city":"Rochedale",
    "sg:classifiers":[
        {
            "category":"Manufacturing",
            "subcategory":"Building Materials",
            "type":"Manufacturing & Wholesale Goods"
        }
    ],
    "sg:phone":"+61 7 3341 2331",
    "sg:postcode":"4123",
    "sg:province":"QLD",
    "sg:tags":[
        "concrete",
        "product"
    ],
    "wof:name":"Con-Tread Concrete Products",
    "wof:placetype":"venue"
},
  "geometry": {"coordinates":[153.132446289,-27.5572738647],"type":"Point"}
}