{
  "type": "Feature",
  "properties": {
    "iso:country":"AU",
    "sg:address":"31 Proprietary St",
    "sg:city":"Tingalpa",
    "sg:classifiers":[
        {
            "category":"Health Services",
            "subcategory":"Chiropractor",
            "type":"Services"
        }
    ],
    "sg:phone":"+61 7 3254 3644",
    "sg:postcode":"4173",
    "sg:province":"QLD",
    "wof:name":"Spinal Care Australia",
    "wof:placetype":"venue"
},
  "geometry": {"coordinates":[153.10763549800001,-27.4735774994],"type":"Point"}
}