{
  "type": "Feature",
  "properties": {
    "addr:full":"86 Victoria St Victor Harbor SA 5211",
    "addr:housenumber":"86",
    "addr:postcode":"5211",
    "addr:street":"Victoria St",
    "iso:country":"AU",
    "sg:address":"86 Victoria St",
    "sg:city":"Victor Harbor",
    "sg:classifiers":[
        {
            "category":"Government",
            "subcategory":"Fire Station",
            "type":"Public Place"
        }
    ],
    "sg:phone":"+61 8 8552 6422",
    "sg:postcode":"5211",
    "sg:province":"SA",
    "sg:tags":[
        "spring",
        "shock",
        "absorbers",
        "suspension"
    ],
    "wof:name":"Pedders Suspension",
    "wof:placetype":"venue"
},
  "geometry": {"coordinates":[138.61454773,-35.5581130981],"type":"Point"}
}