{
  "type": "Feature",
  "properties": {
    "addr:full":"Level 1 45 Toorak Rd South Yarra VIC 3141",
    "addr:housenumber":"45",
    "addr:postcode":"3141",
    "addr:street":"Toorak Rd",
    "iso:country":"AU",
    "sg:address":"Level 1 45 Toorak Rd",
    "sg:city":"South Yarra",
    "sg:classifiers":[
        {
            "category":"Personal",
            "subcategory":"Beauty Salon",
            "type":"Services"
        }
    ],
    "sg:phone":"+61 3 9821 4600",
    "sg:postcode":"3141",
    "sg:province":"VIC",
    "wof:name":"Environ-Skincare",
    "wof:placetype":"venue"
},
  "geometry": {"coordinates":[144.988189697,-37.8383865356],"type":"Point"}
}