{
  "type": "Feature",
  "properties": {
    "addr:full":"Ash Ave Springfield Lakes QLD 4300",
    "addr:postcode":"4300",
    "addr:street":"Ash Ave Springfield",
    "iso:country":"AU",
    "sg:address":"Ash Ave",
    "sg:city":"Springfield Lakes",
    "sg:classifiers":[
        {
            "category":"Building & Trades",
            "subcategory":"Construction",
            "type":"Services"
        }
    ],
    "sg:phone":"+61 7 3437 8751",
    "sg:postcode":"4300",
    "sg:province":"QLD",
    "sg:tags":[
        "contractor"
    ],
    "wof:name":"Coral Homes Pty Ltd",
    "wof:placetype":"venue"
},
  "geometry": {"coordinates":[152.91961669899999,-27.6705875397],"type":"Point"}
}