{
  "type": "Feature",
  "properties": {
    "addr:full":"Moy Pocket Rd Kenilworth QLD 4574",
    "addr:postcode":"4574",
    "addr:street":"Rd",
    "iso:country":"AU",
    "sg:address":"Moy Pocket Rd",
    "sg:city":"Kenilworth",
    "sg:classifiers":[
        {
            "category":"Manufacturing",
            "subcategory":"Building Materials",
            "type":"Manufacturing & Wholesale Goods"
        }
    ],
    "sg:phone":"+61 7 5446 0390",
    "sg:postcode":"4574",
    "sg:province":"QLD",
    "sg:tags":[
        "stone",
        "product",
        "supply"
    ],
    "wof:name":"Sunshine Coast Quarries",
    "wof:placetype":"venue"
},
  "geometry": {"coordinates":[152.75788900000001,-26.549416],"type":"Point"}
}