{
  "type": "Feature",
  "properties": {
    "addr:full":"Cnr Best Rd & McKenzie Blvd Seven Hills NSW 2147",
    "addr:postcode":"2147",
    "addr:street":"Cnr Best Rd & Mckenzie Blvd",
    "iso:country":"AU",
    "sg:address":"Cnr Best Rd & McKenzie Blvd",
    "sg:city":"Seven Hills",
    "sg:classifiers":[
        {
            "category":"Personal",
            "subcategory":"Beauty Salon",
            "type":"Services"
        }
    ],
    "sg:phone":"+61 2 9896 1124",
    "sg:postcode":"2147",
    "sg:province":"NSW",
    "sg:tags":[
        "hairdresser"
    ],
    "wof:name":"Riv-its Hair & Beauty",
    "wof:placetype":"venue"
},
  "geometry": {"coordinates":[150.93513488799999,-33.775478363],"type":"Point"}
}