{
  "type": "Feature",
  "properties": {
    "iso:country":"AU",
    "sg:address":"83 Shillington Way",
    "sg:city":"Thornlie",
    "sg:classifiers":[
        {
            "category":"Retail",
            "subcategory":"Storage",
            "type":"Services"
        }
    ],
    "sg:phone":"+61 8 9452 0200",
    "sg:postcode":"6108",
    "sg:province":"WA",
    "sg:tags":[
        "removal",
        "furniture"
    ],
    "sg:website":"http://www.aardvarkremovals.com.au",
    "wof:name":"A. Aardvark Removals Pty Ltd",
    "wof:placetype":"venue"
},
  "geometry": {"coordinates":[115.945556641,-32.0584449768],"type":"Point"}
}