{
  "type": "Feature",
  "properties": {
    "addr:full":"10 Helen St Heidelberg West VIC 3081",
    "addr:housenumber":"10",
    "addr:postcode":"3081",
    "addr:street":"Helen St",
    "iso:country":"AU",
    "sg:address":"10 Helen St",
    "sg:city":"Heidelberg West",
    "sg:classifiers":[
        {
            "category":"Shopping",
            "subcategory":"Bicycles & Sporting Goods",
            "type":"Retail Goods"
        }
    ],
    "sg:phone":"+61 3 9457 4137",
    "sg:postcode":"3081",
    "sg:province":"VIC",
    "sg:tags":[
        "water",
        "equipment",
        "skiing"
    ],
    "wof:name":"A 1 Jet Ski Hire",
    "wof:placetype":"venue"
},
  "geometry": {"coordinates":[145.052932739,-37.7342796326],"type":"Point"}
}