{
  "type": "Feature",
  "properties": {
    "addr:full":"296 Bridge Rd Richmond VIC 3121",
    "addr:housenumber":"296",
    "addr:postcode":"3121",
    "addr:street":"Bridge Rd",
    "iso:country":"AU",
    "sg:address":"296 Bridge Rd",
    "sg:city":"Richmond",
    "sg:classifiers":[
        {
            "category":"Food & Beverages",
            "subcategory":"Bakery",
            "type":"Retail Goods"
        }
    ],
    "sg:phone":"+61 3 9428 7701",
    "sg:postcode":"3121",
    "sg:province":"VIC",
    "sg:tags":[
        "cake",
        "shop",
        "pastry"
    ],
    "wof:name":"Elegant Cake",
    "wof:placetype":"venue"
},
  "geometry": {"coordinates":[145.00114440900001,-37.8188743591],"type":"Point"}
}