{
  "type": "Feature",
  "properties": {
    "addr:full":"\"Gnangara\" Greengully Rd Glenlyon VIC 3461",
    "addr:postcode":"3461",
    "addr:street":"Greengully Rd",
    "iso:country":"AU",
    "sg:address":"\"Gnangara\" Greengully Rd",
    "sg:city":"Glenlyon",
    "sg:classifiers":[
        {
            "category":"Farming",
            "subcategory":"Farm & Veterinary Services",
            "type":"Manufacturing & Wholesale Goods"
        }
    ],
    "sg:phone":"+61 3 5348 7623",
    "sg:postcode":"3461",
    "sg:province":"VIC",
    "sg:tags":[
        "blacksmith",
        "farrier"
    ],
    "wof:name":"Edwards P",
    "wof:placetype":"venue"
},
  "geometry": {"coordinates":[144.23284912099999,-37.2910041809],"type":"Point"}
}