{
  "type": "Feature",
  "properties": {
    "addr:full":"585 La Trobe St Melbourne VIC 3000",
    "addr:housenumber":"585",
    "addr:postcode":"3000",
    "addr:street":"La Trobe St",
    "iso:country":"AU",
    "sg:address":"585 La Trobe St",
    "sg:city":"Melbourne",
    "sg:classifiers":[
        {
            "category":"Travel",
            "subcategory":"Hotels & Motels",
            "type":"Entertainment"
        }
    ],
    "sg:phone":"+61 3 9321 0900",
    "sg:postcode":"3000",
    "sg:province":"VIC",
    "sg:tags":[
        "accommodation"
    ],
    "sg:website":"http://www.hview.com.au",
    "wof:name":"HarbourView Apartment Hotel",
    "wof:placetype":"venue"
},
  "geometry": {"coordinates":[144.95176696799999,-37.8131942749],"type":"Point"}
}