{
  "type": "Feature",
  "properties": {
    "addr:full":"&#034;Tecoma&#034; M S 189 281 Buttsworth Rd Kingaroy QLD 4610",
    "addr:housenumber":"s;281",
    "addr:postcode":"4610",
    "addr:street":"189;Buttsworth Rd",
    "iso:country":"AU",
    "sg:address":"&#034;Tecoma&#034; M S 189 281 Buttsworth Rd",
    "sg:city":"Kingaroy",
    "sg:classifiers":[
        {
            "category":"Farming",
            "subcategory":"Farm",
            "type":"Manufacturing & Wholesale Goods"
        }
    ],
    "sg:phone":"+61 7 4162 2298",
    "sg:postcode":"4610",
    "sg:province":"QLD",
    "sg:tags":[
        "farmer"
    ],
    "wof:name":"Buttsworth R K & B M",
    "wof:placetype":"venue"
},
  "geometry": {"coordinates":[151.85118102999999,-26.5685100555],"type":"Point"}
}