{
  "type": "Feature",
  "properties": {
    "addr:full":"5 Wanda Rd Caulfield North VIC 3161",
    "addr:housenumber":"5",
    "addr:postcode":"3161",
    "addr:street":"Wanda Rd",
    "iso:country":"AU",
    "sg:address":"5 Wanda Rd",
    "sg:city":"Caulfield North",
    "sg:classifiers":[
        {
            "category":"Professional",
            "subcategory":"Management & Consulting",
            "type":"Services"
        }
    ],
    "sg:phone":"+61 3 9509 8839",
    "sg:postcode":"3161",
    "sg:province":"VIC",
    "sg:tags":[
        "consultant"
    ],
    "wof:name":"Oxley International Pty Ltd",
    "wof:placetype":"venue"
},
  "geometry": {"coordinates":[145.024902344,-37.8677444458],"type":"Point"}
}