{
  "type": "Feature",
  "properties": {
    "addr:full":"Shop 2 Tuloa Ave Hawks Nest NSW 2324",
    "addr:housenumber":"shop 2",
    "addr:postcode":"2324",
    "addr:street":"Tuloa Ave",
    "iso:country":"AU",
    "sg:address":"Shop 2 Tuloa Ave",
    "sg:city":"Hawks Nest",
    "sg:classifiers":[
        {
            "category":"Shopping",
            "subcategory":"Clothing, Apparel, & Fashions",
            "type":"Retail Goods"
        }
    ],
    "sg:phone":"+61 2 4997 1060",
    "sg:postcode":"2324",
    "sg:province":"NSW",
    "sg:tags":[
        "sportswear"
    ],
    "wof:name":"Mungo Road Surf Shop",
    "wof:placetype":"venue"
},
  "geometry": {"coordinates":[152.17762756400001,-32.671081543],"type":"Point"}
}