{
  "type": "Feature",
  "properties": {
    "addr:full":"Cooper St Stawell VIC 3380",
    "addr:postcode":"3380",
    "addr:street":"Cooper St",
    "iso:country":"AU",
    "sg:address":"Cooper St",
    "sg:city":"Stawell",
    "sg:classifiers":[
        {
            "category":"Education",
            "subcategory":"School",
            "type":"Public Place"
        }
    ],
    "sg:phone":"+61 3 5358 1661",
    "sg:postcode":"3380",
    "sg:province":"VIC",
    "sg:tags":[
        "state",
        "except",
        "nsw"
    ],
    "wof:name":"Stawell West Primary School",
    "wof:placetype":"venue"
},
  "geometry": {"coordinates":[142.766311645,-37.0632743835],"type":"Point"}
}