{
  "type": "Feature",
  "properties": {
    "addr:full":"95 William St Port Macquarie NSW 2444",
    "addr:housenumber":"95",
    "addr:postcode":"2444",
    "addr:street":"William St",
    "iso:country":"AU",
    "sg:address":"95 William St",
    "sg:city":"Port Macquarie",
    "sg:classifiers":[
        {
            "category":"Health Services",
            "subcategory":"Optometrist",
            "type":"Services"
        }
    ],
    "sg:phone":"+61 2 6583 7333",
    "sg:postcode":"2444",
    "sg:province":"NSW",
    "wof:name":"Grimshaw S",
    "wof:placetype":"venue"
},
  "geometry": {"coordinates":[152.906082,-31.431387],"type":"Point"}
}