{
  "type": "Feature",
  "properties": {
    "addr:full":"4a 9 Jersey Bayswater VIC 3153",
    "addr:housenumber":"4a 9",
    "addr:postcode":"3153",
    "iso:country":"AU",
    "sg:address":"4a 9",
    "sg:city":"Jersey Bayswater",
    "sg:classifiers":[
        {
            "category":"Professional",
            "subcategory":"Engineering",
            "type":"Services"
        }
    ],
    "sg:phone":"+61 3 9729 2277",
    "sg:postcode":"3153",
    "sg:province":"VIC",
    "sg:tags":[
        "engineer"
    ],
    "wof:name":"Spirax Sarco Pty Ltd",
    "wof:placetype":"venue"
},
  "geometry": {"coordinates":[145.28013610799999,-37.839099884],"type":"Point"}
}