{
  "type": "Feature",
  "properties": {
    "iso:country":"AU",
    "sg:address":"Shop 4 Hosking Crs",
    "sg:city":"Glenfield",
    "sg:classifiers":[
        {
            "category":"Manufacturing",
            "subcategory":"Motor Vehicles & Parts",
            "type":"Manufacturing & Wholesale Goods"
        }
    ],
    "sg:phone":"+61 2 9618 7004",
    "sg:postcode":"2167",
    "sg:province":"NSW",
    "sg:tags":[
        "replacement"
    ],
    "wof:name":"Brennan Spare Parts",
    "wof:placetype":"venue"
},
  "geometry": {"coordinates":[150.83888244600001,-33.9313812256],"type":"Point"}
}