{
  "type": "Feature",
  "properties": {
    "addr:full":"49 Hunter St Hornsby NSW 2077",
    "addr:housenumber":"49",
    "addr:postcode":"2077",
    "addr:street":"Hunter St",
    "iso:country":"AU",
    "sg:address":"49 Hunter St",
    "sg:city":"Hornsby",
    "sg:classifiers":[
        {
            "category":"Retail",
            "subcategory":"Auto Repair",
            "type":"Services"
        }
    ],
    "sg:phone":"+61 2 9987 1522",
    "sg:postcode":"2077",
    "sg:province":"NSW",
    "sg:tags":[
        "repairer",
        "motor",
        "engineer"
    ],
    "wof:name":"Autohous Northshore",
    "wof:placetype":"venue"
},
  "geometry": {"coordinates":[151.10081481899999,-33.702003479],"type":"Point"}
}