{
  "type": "Feature",
  "properties": {
    "addr:full":"20 Collins Rd Dromana VIC 3936",
    "addr:housenumber":"20",
    "addr:postcode":"3936",
    "addr:street":"Collins Rd",
    "iso:country":"AU",
    "sg:address":"20 Collins Rd",
    "sg:city":"Dromana",
    "sg:classifiers":[
        {
            "category":"Retail",
            "subcategory":"Auto Repair",
            "type":"Services"
        }
    ],
    "sg:phone":"+61 3 5987 1500",
    "sg:postcode":"3936",
    "sg:province":"VIC",
    "sg:tags":[
        "clutch",
        "brake"
    ],
    "wof:name":"Wise Automotive Services",
    "wof:placetype":"venue"
},
  "geometry": {"coordinates":[144.98925781200001,-38.3332595825],"type":"Point"}
}