{
  "type": "Feature",
  "properties": {
    "addr:full":"PO Box 28 Red Hill South VIC 3937",
    "addr:postcode":"3937",
    "iso:country":"AU",
    "sg:address":"PO Box 28",
    "sg:city":"Red Hill South",
    "sg:classifiers":[
        {
            "category":"Education",
            "subcategory":"University",
            "type":"Public Place"
        }
    ],
    "sg:phone":"+61 3 5989 2490",
    "sg:postcode":"3937",
    "sg:province":"VIC",
    "sg:tags":[
        "sewing",
        "dressmaking",
        "tuition"
    ],
    "wof:name":"Peninsula Sewing Studio",
    "wof:placetype":"venue"
},
  "geometry": {"coordinates":[145.043655395,-38.3980789185],"type":"Point"}
}