{
  "type": "Feature",
  "properties": {
    "addr:full":"26 Brokenwood Pl Baulkham Hills NSW 2153",
    "addr:housenumber":"26",
    "addr:postcode":"2153",
    "addr:street":"Brokenwood Pl",
    "iso:country":"AU",
    "sg:address":"26 Brokenwood Pl",
    "sg:city":"Baulkham Hills",
    "sg:classifiers":[
        {
            "category":"Home & Garden",
            "subcategory":"Carpets & Floor Coverings",
            "type":"Retail Goods"
        }
    ],
    "sg:phone":"+61 414 850 512",
    "sg:postcode":"2153",
    "sg:province":"NSW",
    "sg:tags":[
        "tile",
        "wall",
        "layer"
    ],
    "wof:name":"Huntington N W",
    "wof:placetype":"venue"
},
  "geometry": {"coordinates":[151.037567139,-33.7268447876],"type":"Point"}
}