{
  "type": "Feature",
  "properties": {
    "addr:full":"9 Sheehan St Redcliffe QLD 4020",
    "addr:housenumber":"9",
    "addr:postcode":"4020",
    "addr:street":"Sheehan St",
    "iso:country":"AU",
    "sg:address":"9 Sheehan St",
    "sg:city":"Redcliffe",
    "sg:classifiers":[
        {
            "category":"Retail",
            "subcategory":"Repair Shop",
            "type":"Services"
        }
    ],
    "sg:phone":"+61 7 3284 1357",
    "sg:postcode":"4020",
    "sg:province":"QLD",
    "sg:tags":[
        "upholsterer"
    ],
    "wof:name":"MTV Upholstery",
    "wof:placetype":"venue"
},
  "geometry": {"coordinates":[153.106628,-27.228666],"type":"Point"}
}