{
  "type": "Feature",
  "properties": {
    "addr:full":"1- 13 Hoddle St Richmond VIC 3121",
    "addr:housenumber":"13",
    "addr:postcode":"3121",
    "addr:street":"1;Hoddle St",
    "iso:country":"AU",
    "sg:address":"1- 13 Hoddle St",
    "sg:city":"Richmond",
    "sg:classifiers":[
        {
            "category":"Shopping",
            "subcategory":"Mobile Phones",
            "type":"Retail Goods"
        }
    ],
    "sg:phone":"+61 13 31 88",
    "sg:postcode":"3121",
    "sg:province":"VIC",
    "sg:tags":[
        "telephone",
        "accessory"
    ],
    "wof:name":"3 Authorised Dealer",
    "wof:placetype":"venue"
},
  "geometry": {"coordinates":[144.991500855,-37.8100738525],"type":"Point"}
}