{
  "type": "Feature",
  "properties": {
    "addr:full":"259 McCullough St Sunnybank QLD 4109",
    "addr:housenumber":"259",
    "addr:postcode":"4109",
    "addr:street":"Mccullough St",
    "iso:country":"AU",
    "sg:address":"259 McCullough St",
    "sg:city":"Sunnybank",
    "sg:classifiers":[
        {
            "category":"Health Services",
            "subcategory":"Doctor",
            "type":"Services"
        }
    ],
    "sg:phone":"+61 7 3345 7171",
    "sg:postcode":"4109",
    "sg:province":"QLD",
    "sg:tags":[
        "medical",
        "practitioner"
    ],
    "wof:name":"O&#039;Neill John C",
    "wof:placetype":"venue"
},
  "geometry": {"coordinates":[153.06211852999999,-27.5718421936],"type":"Point"}
}