{
  "type": "Feature",
  "properties": {
    "addr:full":"Shp 2/ 78 Audley St Petersham NSW 2049",
    "addr:housenumber":"/ 78",
    "addr:postcode":"2049",
    "addr:street":"Audley St",
    "iso:country":"AU",
    "sg:address":"Shp 2/ 78 Audley St",
    "sg:city":"Petersham",
    "sg:classifiers":[
        {
            "category":"Personal",
            "subcategory":"Beauty Salon",
            "type":"Services"
        }
    ],
    "sg:phone":"+61 2 9560 7770",
    "sg:postcode":"2049",
    "sg:province":"NSW",
    "sg:tags":[
        "hairdresser"
    ],
    "wof:name":"Do Or Dye",
    "wof:placetype":"venue"
},
  "geometry": {"coordinates":[151.153976,-33.89608],"type":"Point"}
}