{
  "type": "Feature",
  "properties": {
    "addr:full":"4 Carawa St Blacksmiths NSW 2281",
    "addr:housenumber":"4",
    "addr:postcode":"2281",
    "addr:street":"Carawa St",
    "iso:country":"AU",
    "sg:address":"4 Carawa St",
    "sg:city":"Blacksmiths",
    "sg:classifiers":[
        {
            "category":"Government",
            "subcategory":"Fire Station",
            "type":"Public Place"
        }
    ],
    "sg:phone":"+61 2 4972 0880",
    "sg:postcode":"2281",
    "sg:province":"NSW",
    "sg:tags":[
        "equipment",
        "protection",
        "consultant"
    ],
    "wof:name":"Akron Brass",
    "wof:placetype":"venue"
},
  "geometry": {"coordinates":[151.65504455600001,-33.0741119385],"type":"Point"}
}