{
  "type": "Feature",
  "properties": {
    "addr:full":"3A, 74 Shirley Rd Wollstonecraft NSW 2065",
    "addr:housenumber":"74",
    "addr:postcode":"2065",
    "addr:street":"Shirley Rd",
    "iso:country":"AU",
    "sg:address":"3A, 74 Shirley Rd",
    "sg:city":"Wollstonecraft",
    "sg:classifiers":[
        {
            "category":"Professional",
            "subcategory":"Management & Consulting",
            "type":"Services"
        }
    ],
    "sg:phone":"+61 2 9232 1732",
    "sg:postcode":"2065",
    "sg:province":"NSW",
    "sg:tags":[
        "consultant"
    ],
    "wof:name":"Tass Thassim & Associates",
    "wof:placetype":"venue"
},
  "geometry": {"coordinates":[151.19520568900001,-33.8316116333],"type":"Point"}
}