{
  "type": "Feature",
  "properties": {
    "addr:full":"58 Spencer Rd Nerang QLD 4211",
    "addr:housenumber":"58",
    "addr:postcode":"4211",
    "addr:street":"Spencer Rd",
    "iso:country":"AU",
    "sg:address":"58 Spencer Rd",
    "sg:city":"Nerang",
    "sg:classifiers":[
        {
            "category":"Industrial Area",
            "type":"Public Place"
        }
    ],
    "sg:phone":"+61 7 5596 1750",
    "sg:postcode":"4211",
    "sg:province":"QLD",
    "sg:tags":[
        "rural",
        "shed"
    ],
    "wof:name":"Tuff-Span",
    "wof:placetype":"venue"
},
  "geometry": {"coordinates":[153.340744019,-28.0037288666],"type":"Point"}
}