{
  "type": "Feature",
  "properties": {
    "addr:full":"259 Payneham Rd Joslin SA 5070",
    "addr:housenumber":"259",
    "addr:postcode":"5070",
    "addr:street":"Payneham Rd",
    "iso:country":"AU",
    "sg:address":"259 Payneham Rd",
    "sg:city":"Joslin",
    "sg:classifiers":[
        {
            "category":"Personal",
            "subcategory":"Massage",
            "type":"Services"
        }
    ],
    "sg:phone":"+61 8 8362 5551",
    "sg:postcode":"5070",
    "sg:province":"SA",
    "sg:tags":[
        "therapy"
    ],
    "wof:name":"Carolyn Quixley",
    "wof:placetype":"venue"
},
  "geometry": {"coordinates":[138.633666992,-34.9025001526],"type":"Point"}
}