{
  "type": "Feature",
  "properties": {
    "iso:country":"AU",
    "sg:address":"1 Stuart Hwy",
    "sg:city":"Darwin",
    "sg:classifiers":[
        {
            "category":"Autos & Motor Vehicles",
            "subcategory":"Automobile Sales",
            "type":"Retail Goods"
        }
    ],
    "sg:phone":"+61 8 8946 0000",
    "sg:postcode":"0800",
    "sg:province":"NT",
    "sg:tags":[
        "car",
        "new"
    ],
    "wof:name":"Bridge Autos Mercedes-Benz",
    "wof:placetype":"venue"
},
  "geometry": {"coordinates":[130.839157105,-12.4543743134],"type":"Point"}
}