{
  "type": "Feature",
  "properties": {
    "addr:full":"285 Argent St Broken Hill NSW 2880",
    "addr:housenumber":"285",
    "addr:postcode":"2880",
    "addr:street":"Argent St",
    "iso:country":"AU",
    "sg:address":"285 Argent St",
    "sg:city":"Broken Hill",
    "sg:classifiers":[
        {
            "category":"Airline",
            "type":"Transportation"
        }
    ],
    "sg:phone":"+61 8 8087 7900",
    "sg:postcode":"2880",
    "sg:province":"NSW",
    "sg:tags":[
        "agent"
    ],
    "wof:name":"Harvey World Travel",
    "wof:placetype":"venue"
},
  "geometry": {"coordinates":[141.46502685600001,-31.9587841034],"type":"Point"}
}