{
  "type": "Feature",
  "properties": {
    "iso:country":"AU",
    "sg:address":"85 Musgrave Rd",
    "sg:city":"Coopers Plains",
    "sg:classifiers":[
        {
            "category":"Building & Trades",
            "subcategory":"Construction",
            "type":"Services"
        }
    ],
    "sg:phone":"+61 7 3277 7255",
    "sg:postcode":"4108",
    "sg:province":"QLD",
    "sg:tags":[
        "distributor",
        "platform",
        "work",
        "mfrs",
        "elevating"
    ],
    "wof:name":"Haulotte Group",
    "wof:placetype":"venue"
},
  "geometry": {"coordinates":[153.02699279800001,-27.5614910126],"type":"Point"}
}