{
  "type": "Feature",
  "properties": {
    "addr:full":"386 wellard Rd Wellard WA 6170",
    "addr:housenumber":"386",
    "addr:postcode":"6170",
    "addr:street":"Wellard Rd",
    "iso:country":"AU",
    "sg:address":"386 wellard Rd",
    "sg:city":"Wellard",
    "sg:classifiers":[
        {
            "category":"Education",
            "subcategory":"School",
            "type":"Public Place"
        }
    ],
    "sg:phone":"+61 8 9439 3499",
    "sg:postcode":"6170",
    "sg:province":"WA",
    "wof:name":"Peter Carnley Anglican Community School",
    "wof:placetype":"venue"
},
  "geometry": {"coordinates":[115.836288,-32.271084],"type":"Point"}
}