{
  "type": "Feature",
  "properties": {
    "addr:full":"Duggan St Toowoomba QLD 4350",
    "addr:postcode":"4350",
    "addr:street":"Duggan St",
    "iso:country":"AU",
    "sg:address":"Duggan St",
    "sg:city":"Toowoomba",
    "sg:classifiers":[
        {
            "category":"Shopping",
            "subcategory":"Clothing, Apparel, & Fashions",
            "type":"Retail Goods"
        }
    ],
    "sg:phone":"+61 7 4639 1568",
    "sg:postcode":"4350",
    "sg:province":"QLD",
    "sg:tags":[
        "jean"
    ],
    "wof:name":"Gasoline Alley",
    "wof:placetype":"venue"
},
  "geometry": {"coordinates":[151.952179,-27.563],"type":"Point"}
}