{
  "type": "Feature",
  "properties": {
    "iso:country":"AU",
    "sg:address":"63 Commercial St",
    "sg:city":"Korumburra",
    "sg:classifiers":[
        {
            "category":"Professional",
            "subcategory":"Printing & Photocopies",
            "type":"Services"
        }
    ],
    "sg:phone":"+61 3 5655 2328",
    "sg:postcode":"3950",
    "sg:province":"VIC",
    "sg:tags":[
        "trophy"
    ],
    "wof:name":"Gordon Parry Gift Store",
    "wof:placetype":"venue"
},
  "geometry": {"coordinates":[145.82281494099999,-38.4323501587],"type":"Point"}
}