{
  "type": "Feature",
  "properties": {
    "addr:full":"19 Hutcheson St Albion QLD 4010",
    "addr:housenumber":"19",
    "addr:postcode":"4010",
    "addr:street":"Hutcheson St",
    "iso:country":"AU",
    "sg:address":"19 Hutcheson St",
    "sg:city":"Albion",
    "sg:classifiers":[
        {
            "category":"Taxi",
            "type":"Transportation"
        }
    ],
    "sg:phone":"+61 7 3262 9600",
    "sg:postcode":"4010",
    "sg:province":"QLD",
    "sg:tags":[
        "cab"
    ],
    "wof:name":"Delta Taxi Management Pty Ltd",
    "wof:placetype":"venue"
},
  "geometry": {"coordinates":[153.044845581,-27.4393539429],"type":"Point"}
}