{
  "type": "Feature",
  "properties": {
    "addr:full":"780 Melbourne Rd Sorrento VIC 3943",
    "addr:housenumber":"780",
    "addr:postcode":"3943",
    "addr:street":"Melbourne Rd",
    "iso:country":"AU",
    "sg:address":"780 Melbourne Rd",
    "sg:city":"Sorrento",
    "sg:classifiers":[
        {
            "category":"Travel",
            "subcategory":"Hotels & Motels",
            "type":"Entertainment"
        }
    ],
    "sg:phone":"+61 3 5984 1356",
    "sg:postcode":"3943",
    "sg:province":"VIC",
    "wof:name":"Golden Chain Sorrento Beach Motel",
    "wof:placetype":"venue"
},
  "geometry": {"coordinates":[144.740036011,-38.345916748],"type":"Point"}
}