{
  "type": "Feature",
  "properties": {
    "addr:full":"16 Grace Park Ave Springvale VIC 3171",
    "addr:housenumber":"16",
    "addr:postcode":"3171",
    "addr:street":"Grace Park Ave",
    "iso:country":"AU",
    "sg:address":"16 Grace Park Ave",
    "sg:city":"Springvale",
    "sg:classifiers":[
        {
            "category":"Education",
            "subcategory":"University",
            "type":"Public Place"
        }
    ],
    "sg:phone":"+61 3 9574 6399",
    "sg:postcode":"3171",
    "sg:province":"VIC",
    "sg:tags":[
        "educational",
        "organisation",
        "cultural"
    ],
    "wof:name":"Springvale Neighbourhood Literacy Centre",
    "wof:placetype":"venue"
},
  "geometry": {"coordinates":[145.15292358400001,-37.9557495117],"type":"Point"}
}