{
  "type": "Feature",
  "properties": {
    "iso:country":"AU",
    "sg:address":"74 Sunnybanks Drv",
    "sg:city":"Strathalbyn",
    "sg:classifiers":[
        {
            "category":"Building & Trades",
            "subcategory":"Construction",
            "type":"Services"
        }
    ],
    "sg:phone":"+61 8 9964 4066",
    "sg:postcode":"6530",
    "sg:province":"WA",
    "sg:tags":[
        "ceiling"
    ],
    "wof:name":"Stribley Mervyn & Co",
    "wof:placetype":"venue"
},
  "geometry": {"coordinates":[114.64617157000001,-28.7579708099],"type":"Point"}
}