{
  "type": "Feature",
  "properties": {
    "addr:full":"Cnr Kemp & Elbow Sts Kempsey West NSW 2440",
    "addr:postcode":"2440",
    "addr:street":"Cnr;Sts",
    "iso:country":"AU",
    "sg:address":"Cnr Kemp & Elbow Sts",
    "sg:city":"Kempsey West",
    "sg:classifiers":[
        {
            "category":"Retail",
            "subcategory":"Repair Shop",
            "type":"Services"
        }
    ],
    "sg:phone":"+61 2 6562 7389",
    "sg:postcode":"2440",
    "sg:province":"NSW",
    "sg:tags":[
        "machine",
        "repairs",
        "part",
        "dryer",
        "washing"
    ],
    "wof:name":"Appliance Traders (N.S.W.)",
    "wof:placetype":"venue"
},
  "geometry": {"coordinates":[152.83627300000001,-31.057512],"type":"Point"}
}