{
  "type": "Feature",
  "properties": {
    "addr:full":"3 Pioneer Rd Grovedale VIC 3216",
    "addr:housenumber":"3",
    "addr:postcode":"3216",
    "addr:street":"Pioneer Rd",
    "iso:country":"AU",
    "sg:address":"3 Pioneer Rd",
    "sg:city":"Grovedale",
    "sg:classifiers":[
        {
            "category":"Health Services",
            "subcategory":"Chiropractor",
            "type":"Services"
        }
    ],
    "sg:phone":"+61 3 5241 1500",
    "sg:postcode":"3216",
    "sg:province":"VIC",
    "wof:name":"Pioneer Family Chiropractic",
    "wof:placetype":"venue"
},
  "geometry": {"coordinates":[144.34048461899999,-38.2031478882],"type":"Point"}
}