{
  "type": "Feature",
  "properties": {
    "iso:country":"AU",
    "sg:address":"Suite 4, 100 Gladesville Rd",
    "sg:city":"Patterson Lakes",
    "sg:classifiers":[
        {
            "category":"Professional",
            "subcategory":"Accounting & Tax Preparation",
            "type":"Services"
        }
    ],
    "sg:phone":"+61 3 9585 8644",
    "sg:postcode":"3197",
    "sg:province":"VIC",
    "sg:tags":[
        "deduction",
        "payroll"
    ],
    "sg:website":"http://www.crowbiz.com.au",
    "wof:name":"Crow Business Services",
    "wof:placetype":"venue"
},
  "geometry": {"coordinates":[145.14454650900001,-38.0672492981],"type":"Point"}
}