{
  "type": "Feature",
  "properties": {
    "addr:full":"53 Duporth Ave Maroochydore QLD 4558",
    "addr:housenumber":"53",
    "addr:postcode":"4558",
    "addr:street":"Duporth Ave",
    "iso:country":"AU",
    "sg:address":"53 Duporth Ave",
    "sg:city":"Maroochydore",
    "sg:classifiers":[
        {
            "category":"Real Estate",
            "subcategory":"Surveying",
            "type":"Services"
        }
    ],
    "sg:phone":"+61 7 5443 4265",
    "sg:postcode":"4558",
    "sg:province":"QLD",
    "sg:tags":[
        "surveyor",
        "quantity"
    ],
    "sg:website":"http://www.grahamlukins.com.au",
    "wof:name":"Graham Lukins Partnership",
    "wof:placetype":"venue"
},
  "geometry": {"coordinates":[153.08926391599999,-26.6496944427],"type":"Point"}
}