{
  "type": "Feature",
  "properties": {
    "addr:full":"415 Princes Hwy Officer VIC 3809",
    "addr:housenumber":"415",
    "addr:postcode":"3809",
    "addr:street":"Princes Hwy",
    "iso:country":"AU",
    "sg:address":"415 Princes Hwy",
    "sg:city":"Officer",
    "sg:phone":"+61 3 5943 1222",
    "sg:postcode":"3809",
    "sg:province":"VIC",
    "sg:website":"http://www.pumpstanksirrigation.com.au",
    "wof:name":"Pakenham Tanks & Irrigation",
    "wof:placetype":"venue"
},
  "geometry": {"coordinates":[145.406036,-38.059364],"type":"Point"}
}