{
  "type": "Feature",
  "properties": {
    "addr:full":"Shp 10 / &#034;Forster Tower&#034; Forster NSW 2428",
    "addr:housenumber":"10",
    "addr:postcode":"2428",
    "iso:country":"AU",
    "sg:address":"Shp 10",
    "sg:city":"/ &#034;Forster Tower&#034; Forster",
    "sg:classifiers":[
        {
            "category":"Real Estate",
            "subcategory":"Real Estate Operator",
            "type":"Services"
        }
    ],
    "sg:phone":"+61 2 6554 7688",
    "sg:postcode":"2428",
    "sg:province":"NSW",
    "sg:tags":[
        "building",
        "consultant",
        "management"
    ],
    "wof:name":"Asco Private Certifiers Pty Ltd",
    "wof:placetype":"venue"
},
  "geometry": {"coordinates":[152.51892100000001,-32.19128],"type":"Point"}
}