{
  "type": "Feature",
  "properties": {
    "addr:full":"109 Gray St Hamilton VIC 3300",
    "addr:housenumber":"109",
    "addr:postcode":"3300",
    "addr:street":"Gray St",
    "iso:country":"AU",
    "sg:address":"109 Gray St",
    "sg:city":"Hamilton",
    "sg:classifiers":[
        {
            "category":"Food & Beverages",
            "subcategory":"Specialty",
            "type":"Retail Goods"
        }
    ],
    "sg:phone":"+61 3 5572 4550",
    "sg:postcode":"3300",
    "sg:province":"VIC",
    "sg:tags":[
        "product",
        "health"
    ],
    "wof:name":"Rosies Healthy Foods",
    "wof:placetype":"venue"
},
  "geometry": {"coordinates":[142.0234375,-37.7434883118],"type":"Point"}
}