{
  "type": "Feature",
  "properties": {
    "iso:country":"AU",
    "sg:address":"531 Hay St",
    "sg:city":"Subiaco",
    "sg:classifiers":[
        {
            "category":"Shopping",
            "subcategory":"Antiques",
            "type":"Retail Goods"
        }
    ],
    "sg:phone":"+61 8 9381 7005",
    "sg:postcode":"6008",
    "sg:province":"WA",
    "wof:name":"Petticoat Lane",
    "wof:placetype":"venue"
},
  "geometry": {"coordinates":[115.821548462,-31.9472122192],"type":"Point"}
}