{
  "type": "Feature",
  "properties": {
    "iso:country":"AU",
    "sg:address":"181a Victoria Rd",
    "sg:city":"Drummoyne",
    "sg:classifiers":[
        {
            "category":"Personal",
            "subcategory":"Beauty Salon",
            "type":"Services"
        }
    ],
    "sg:phone":"+61 2 9181 3969",
    "sg:postcode":"2047",
    "sg:province":"NSW",
    "sg:tags":[
        "hairdresser"
    ],
    "wof:name":"Re Vamp Hair Design",
    "wof:placetype":"venue"
},
  "geometry": {"coordinates":[151.154922,-33.851646],"type":"Point"}
}