{
  "type": "Feature",
  "properties": {
    "addr:full":"18 Timothy Ave Castle Hill NSW 2154",
    "addr:housenumber":"18",
    "addr:postcode":"2154",
    "addr:street":"Timothy Ave",
    "iso:country":"AU",
    "sg:address":"18 Timothy Ave",
    "sg:city":"Castle Hill",
    "sg:classifiers":[
        {
            "category":"Building & Trades",
            "subcategory":"Construction",
            "type":"Services"
        }
    ],
    "sg:phone":"+61 2 9899 5757",
    "sg:postcode":"2154",
    "sg:province":"NSW",
    "sg:tags":[
        "contractor"
    ],
    "wof:name":"Amys Home Improvements",
    "wof:placetype":"venue"
},
  "geometry": {"coordinates":[151.01226806599999,-33.7379722595],"type":"Point"}
}