{
  "type": "Feature",
  "properties": {
    "addr:full":"Unit 6, 610 Great Western Hwy Girraween NSW 2145",
    "addr:housenumber":"610",
    "addr:postcode":"2145",
    "addr:street":"Great Western Hwy",
    "iso:country":"AU",
    "sg:address":"Unit 6, 610 Great Western Hwy",
    "sg:city":"Girraween",
    "sg:classifiers":[
        {
            "category":"Retail",
            "subcategory":"Auto Repair",
            "type":"Services"
        }
    ],
    "sg:phone":"+61 2 9636 4646",
    "sg:postcode":"2145",
    "sg:province":"NSW",
    "sg:tags":[
        "transmission",
        "automotive",
        "car"
    ],
    "wof:name":"All About Gearboxes",
    "wof:placetype":"venue"
},
  "geometry": {"coordinates":[150.94143676799999,-33.8083496094],"type":"Point"}
}