{
  "type": "Feature",
  "properties": {
    "addr:full":"103 Burrendah Rd Jindalee QLD 4074",
    "addr:housenumber":"103",
    "addr:postcode":"4074",
    "addr:street":"Burrendah Rd",
    "iso:country":"AU",
    "sg:address":"103 Burrendah Rd",
    "sg:city":"Jindalee",
    "sg:classifiers":[
        {
            "category":"Organizations",
            "subcategory":"Professional Association",
            "type":"Services"
        }
    ],
    "sg:phone":"+61 7 3715 5999",
    "sg:postcode":"4074",
    "sg:province":"QLD",
    "sg:tags":[
        "web",
        "internet"
    ],
    "wof:name":"Fat Galah Design",
    "wof:placetype":"venue"
},
  "geometry": {"coordinates":[152.93467712399999,-27.5296115875],"type":"Point"}
}