{
  "type": "Feature",
  "properties": {
    "addr:full":"U2/ 31 Through Rd Ringwood North VIC 3134",
    "addr:housenumber":"31",
    "addr:postcode":"3134",
    "addr:street":"U2 /;Through Rd",
    "iso:country":"AU",
    "sg:address":"U2/ 31 Through Rd",
    "sg:city":"Ringwood North",
    "sg:classifiers":[
        {
            "category":"Social Services",
            "subcategory":"Retirement Home",
            "type":"Services"
        }
    ],
    "sg:phone":"+61 3 9876 0019",
    "sg:postcode":"3134",
    "sg:province":"VIC",
    "sg:tags":[
        "t-shirt",
        "supplier"
    ],
    "wof:name":"Airbrush Now",
    "wof:placetype":"venue"
},
  "geometry": {"coordinates":[145.22988891599999,-37.7991333008],"type":"Point"}
}