{
  "type": "Feature",
  "properties": {
    "addr:full":"300 Wellington Rd Mulgrave VIC 3170",
    "addr:housenumber":"300",
    "addr:postcode":"3170",
    "addr:street":"Wellington Rd",
    "iso:country":"AU",
    "sg:address":"300 Wellington Rd",
    "sg:city":"Mulgrave",
    "sg:classifiers":[
        {
            "category":"Professional",
            "subcategory":"Printing & Photocopies",
            "type":"Services"
        }
    ],
    "sg:phone":"+61 3 9271 6100",
    "sg:postcode":"3170",
    "sg:province":"VIC",
    "sg:tags":[
        "photocopier"
    ],
    "wof:name":"Toshiba (Australia) Pty Limited",
    "wof:placetype":"venue"
},
  "geometry": {"coordinates":[145.15573120100001,-37.918422699],"type":"Point"}
}