{
  "type": "Feature",
  "properties": {
    "addr:full":"39 Brisbane Ave Barton ACT 2600",
    "addr:housenumber":"39",
    "addr:postcode":"2600",
    "addr:street":"Brisbane Ave",
    "iso:country":"AU",
    "sg:address":"39 Brisbane Ave",
    "sg:city":"Barton",
    "sg:classifiers":[
        {
            "category":"Organizations",
            "subcategory":"Professional Association",
            "type":"Services"
        }
    ],
    "sg:phone":"+61 2 6273 4333",
    "sg:postcode":"2600",
    "sg:province":"ACT",
    "sg:tags":[
        "organisation",
        "business"
    ],
    "wof:name":"Mtaa",
    "wof:placetype":"venue"
},
  "geometry": {"coordinates":[149.13243102999999,-35.3092918396],"type":"Point"}
}