{
  "type": "Feature",
  "properties": {
    "addr:full":"5 Macquarie St Taree NSW 2430",
    "addr:housenumber":"5",
    "addr:postcode":"2430",
    "addr:street":"Macquarie St",
    "iso:country":"AU",
    "sg:address":"5 Macquarie St",
    "sg:city":"Taree",
    "sg:classifiers":[
        {
            "category":"Professional",
            "subcategory":"Management & Consulting",
            "type":"Services"
        }
    ],
    "sg:phone":"+61 2 6551 0636",
    "sg:postcode":"2430",
    "sg:province":"NSW",
    "sg:tags":[
        "consultant",
        "educational"
    ],
    "wof:name":"Taree Community College",
    "wof:placetype":"venue"
},
  "geometry": {"coordinates":[152.463043,-31.91091],"type":"Point"}
}