{
  "type": "Feature",
  "properties": {
    "addr:full":"8 Ambrose St Rockingham WA 6168",
    "addr:housenumber":"8",
    "addr:postcode":"6168",
    "addr:street":"Ambrose St",
    "iso:country":"AU",
    "sg:address":"8 Ambrose St",
    "sg:city":"Rockingham",
    "sg:classifiers":[
        {
            "category":"Autos & Motor Vehicles",
            "subcategory":"Automobile Sales",
            "type":"Retail Goods"
        }
    ],
    "sg:phone":"+61 8 9591 1600",
    "sg:postcode":"6168",
    "sg:province":"WA",
    "sg:tags":[
        "car",
        "used"
    ],
    "wof:name":"Choice Auto's",
    "wof:placetype":"venue"
},
  "geometry": {"coordinates":[115.74572000000001,-32.275948],"type":"Point"}
}