{
  "type": "Feature",
  "properties": {
    "addr:full":"39 Partridge St Glenelg SA 5045",
    "addr:housenumber":"39",
    "addr:postcode":"5045",
    "addr:street":"Partridge St",
    "iso:country":"AU",
    "sg:address":"39 Partridge St",
    "sg:city":"Glenelg",
    "sg:classifiers":[
        {
            "category":"Education",
            "subcategory":"School",
            "type":"Public Place"
        }
    ],
    "sg:phone":"+61 8 8295 4317",
    "sg:postcode":"5045",
    "sg:province":"SA",
    "sg:tags":[
        "co-educational"
    ],
    "wof:name":"St Peter's Woodlands",
    "wof:placetype":"venue"
},
  "geometry": {"coordinates":[138.51795999999999,-34.984879],"type":"Point"}
}