{
  "type": "Feature",
  "properties": {
    "addr:full":"Lev 1, 229 Great North Rd Five Dock NSW 2046",
    "addr:housenumber":"229",
    "addr:postcode":"2046",
    "addr:street":"Great North Rd",
    "iso:country":"AU",
    "sg:address":"Lev 1, 229 Great North Rd",
    "sg:city":"Five Dock",
    "sg:classifiers":[
        {
            "category":"Health Services",
            "subcategory":"Doctor",
            "type":"Services"
        }
    ],
    "sg:phone":"+61 2 9713 4011",
    "sg:postcode":"2046",
    "sg:province":"NSW",
    "sg:tags":[
        "medical",
        "practitioner"
    ],
    "wof:name":"Borody Thomas J Professor",
    "wof:placetype":"venue"
},
  "geometry": {"coordinates":[151.130066,-33.865555],"type":"Point"}
}