{
  "type": "Feature",
  "properties": {
    "addr:full":"Peach Tree Arcade Shop17/ Hay St Port Macquarie NSW 2444",
    "addr:housenumber":"peach tree arcade shop17",
    "addr:postcode":"2444",
    "addr:street":"Hay St",
    "iso:country":"AU",
    "sg:address":"Peach Tree Arcade Shop17/ Hay St",
    "sg:city":"Port Macquarie",
    "sg:classifiers":[
        {
            "category":"Manufacturing",
            "subcategory":"Food",
            "type":"Manufacturing & Wholesale Goods"
        }
    ],
    "sg:phone":"+61 2 6584 1120",
    "sg:postcode":"2444",
    "sg:province":"NSW",
    "sg:tags":[
        "function",
        "catering"
    ],
    "wof:name":"Luxe Fine Food Cafe & Catering",
    "wof:placetype":"venue"
},
  "geometry": {"coordinates":[152.909515,-31.429291],"type":"Point"}
}