{
  "type": "Feature",
  "properties": {
    "addr:full":"Shop 27 Carillon Shopng Cntr Perth WA 6000",
    "addr:housenumber":"shop 27",
    "addr:postcode":"6000",
    "addr:street":"Carillon Shopng Cntr",
    "iso:country":"AU",
    "sg:address":"Shop 27 Carillon Shopng Cntr",
    "sg:city":"Perth",
    "sg:classifiers":[
        {
            "category":"Fast Food",
            "type":"Food & Drink"
        }
    ],
    "sg:phone":"+61 8 9322 3320",
    "sg:postcode":"6000",
    "sg:province":"WA",
    "sg:tags":[
        "away",
        "take"
    ],
    "wof:name":"Gourmet Salads",
    "wof:placetype":"venue"
},
  "geometry": {"coordinates":[115.852546692,-31.9546794891],"type":"Point"}
}