{
  "type": "Feature",
  "properties": {
    "iso:country":"AU",
    "sg:address":"180 Erskine Rd",
    "sg:city":"Griffith",
    "sg:classifiers":[
        {
            "category":"Farming",
            "subcategory":"Farm",
            "type":"Manufacturing & Wholesale Goods"
        }
    ],
    "sg:phone":"+61 2 6964 5909",
    "sg:postcode":"2680",
    "sg:province":"NSW",
    "sg:tags":[
        "farmer"
    ],
    "wof:name":"NSW Farmers Association",
    "wof:placetype":"venue"
},
  "geometry": {"coordinates":[146.031555,-34.294205],"type":"Point"}
}