{
  "type": "Feature",
  "properties": {
    "addr:full":"14 Winchcombe Ave Haberfield NSW 2045",
    "addr:housenumber":"14",
    "addr:postcode":"2045",
    "addr:street":"Winchcombe Ave",
    "iso:country":"AU",
    "sg:address":"14 Winchcombe Ave",
    "sg:city":"Haberfield",
    "sg:classifiers":[
        {
            "category":"Real Estate",
            "subcategory":"Architect",
            "type":"Services"
        }
    ],
    "sg:phone":"+61 2 9716 0541",
    "sg:postcode":"2045",
    "sg:province":"NSW",
    "wof:name":"Archnet Designs",
    "wof:placetype":"venue"
},
  "geometry": {"coordinates":[151.13717700000001,-33.880444],"type":"Point"}
}