{
  "type": "Feature",
  "properties": {
    "iso:country":"AU",
    "sg:address":"9 Pitt Way",
    "sg:city":"Booragoon",
    "sg:classifiers":[
        {
            "category":"Military Area",
            "subcategory":"Armory",
            "type":"Public Place"
        }
    ],
    "sg:phone":"+61 8 9330 2000",
    "sg:postcode":"6154",
    "sg:province":"WA",
    "sg:tags":[
        "teleconferencing"
    ],
    "sg:website":"http://www.avi.com.au",
    "wof:name":"AVI Pty Ltd",
    "wof:placetype":"venue"
},
  "geometry": {"coordinates":[115.824806,-32.042927],"type":"Point"}
}