{
  "type": "Feature",
  "properties": {
    "iso:country":"AU",
    "sg:address":"K 14/ 1 Hyatts Rd",
    "sg:city":"Plumpton",
    "sg:classifiers":[
        {
            "category":"Shopping",
            "subcategory":"Mobile Phones",
            "type":"Retail Goods"
        }
    ],
    "sg:phone":"+61 2 9675 7442",
    "sg:postcode":"2761",
    "sg:province":"NSW",
    "sg:tags":[
        "telephone",
        "accessory"
    ],
    "wof:name":"Mo's Mobiles Plumpton",
    "wof:placetype":"venue"
},
  "geometry": {"coordinates":[150.837204,-33.736286],"type":"Point"}
}