{
  "type": "Feature",
  "properties": {
    "addr:full":"491a Forest Rd Penshurst NSW 2222",
    "addr:housenumber":"491a",
    "addr:postcode":"2222",
    "addr:street":"Forest Rd",
    "iso:country":"AU",
    "sg:address":"491a Forest Rd",
    "sg:city":"Penshurst",
    "sg:classifiers":[
        {
            "category":"Food & Beverages",
            "subcategory":"Liquor & Beverages",
            "type":"Retail Goods"
        }
    ],
    "sg:phone":"+61 2 9580 2884",
    "sg:postcode":"2222",
    "sg:province":"NSW",
    "sg:tags":[
        "store"
    ],
    "wof:name":"Penshurst West Liquor Stop",
    "wof:placetype":"venue"
},
  "geometry": {"coordinates":[151.07949829099999,-33.9622535706],"type":"Point"}
}