{
  "type": "Feature",
  "properties": {
    "addr:full":"Suite 2 274- 276 Springvale Rd Glen Waverley VIC 3150",
    "addr:housenumber":"274 276",
    "addr:postcode":"3150",
    "addr:street":"Springvale Rd",
    "iso:country":"AU",
    "sg:address":"Suite 2 274- 276 Springvale Rd",
    "sg:city":"Glen Waverley",
    "sg:classifiers":[
        {
            "category":"Health Services",
            "subcategory":"Chiropractor",
            "type":"Services"
        }
    ],
    "sg:phone":"+61 3 9574 9666",
    "sg:postcode":"3150",
    "sg:province":"VIC",
    "wof:name":"Hart Pieter C DC (USA)",
    "wof:placetype":"venue"
},
  "geometry": {"coordinates":[145.16560363799999,-37.8821258545],"type":"Point"}
}