{
  "type": "Feature",
  "properties": {
    "addr:full":"46 Kintore Ave Adelaide SA 5000",
    "addr:housenumber":"46",
    "addr:postcode":"5000",
    "addr:street":"Kintore Ave",
    "iso:country":"AU",
    "sg:address":"46 Kintore Ave",
    "sg:city":"Adelaide",
    "sg:classifiers":[
        {
            "category":"Shopping",
            "subcategory":"Musical Instruments",
            "type":"Retail Goods"
        }
    ],
    "sg:phone":"+61 8 8303 4339",
    "sg:postcode":"5000",
    "sg:province":"SA",
    "sg:tags":[
        "musician",
        "agent"
    ],
    "wof:name":"Jazz Co-ordinator (S.A.)",
    "wof:placetype":"venue"
},
  "geometry": {"coordinates":[138.601837158,-34.9206390381],"type":"Point"}
}