{
  "type": "Feature",
  "properties": {
    "addr:full":"256 Albany Hwy Victoria Park WA 6100",
    "addr:housenumber":"256",
    "addr:postcode":"6100",
    "addr:street":"Albany Hwy Victoria",
    "iso:country":"AU",
    "sg:address":"256 Albany Hwy",
    "sg:city":"Victoria Park",
    "sg:classifiers":[
        {
            "category":"Professional",
            "subcategory":"Printing & Photocopies",
            "type":"Services"
        }
    ],
    "sg:phone":"+61 8 9470 5422",
    "sg:postcode":"6100",
    "sg:province":"WA",
    "sg:tags":[
        "rubber",
        "stamp",
        "metal"
    ],
    "wof:name":"Stamp-It",
    "wof:placetype":"venue"
},
  "geometry": {"coordinates":[115.89256286600001,-31.9707641602],"type":"Point"}
}