{
  "type": "Feature",
  "properties": {
    "addr:full":"26 Combermere St Essendon VIC 3040",
    "addr:housenumber":"26",
    "addr:postcode":"3040",
    "addr:street":"Combermere St",
    "iso:country":"AU",
    "sg:address":"26 Combermere St",
    "sg:city":"Essendon",
    "sg:classifiers":[
        {
            "category":"Building & Trades",
            "subcategory":"Landscaping Services",
            "type":"Services"
        }
    ],
    "sg:phone":"+61 3 9337 5937",
    "sg:postcode":"3040",
    "sg:province":"VIC",
    "sg:tags":[
        "designer",
        "landscape",
        "contractor"
    ],
    "wof:name":"Pink Magnolia Pty Ltd",
    "wof:placetype":"venue"
},
  "geometry": {"coordinates":[144.904006958,-37.758102417],"type":"Point"}
}