{
  "type": "Feature",
  "properties": {
    "iso:country":"AU",
    "sg:address":"182 Tufnell Rd",
    "sg:city":"Banyo",
    "sg:classifiers":[
        {
            "category":"Health Services",
            "subcategory":"Health Practitioner",
            "type":"Services"
        }
    ],
    "sg:phone":"+61 7 3267 0272",
    "sg:postcode":"4014",
    "sg:province":"QLD",
    "sg:tags":[
        "physiotherapist"
    ],
    "wof:name":"Lawrence Townsend Physiotherapy",
    "wof:placetype":"venue"
},
  "geometry": {"coordinates":[153.07713317899999,-27.3746070862],"type":"Point"}
}