{
  "type": "Feature",
  "properties": {
    "addr:full":"8 Gladstone St Glen Iris VIC 3146",
    "addr:housenumber":"8",
    "addr:postcode":"3146",
    "addr:street":"Gladstone St",
    "iso:country":"AU",
    "sg:address":"8 Gladstone St",
    "sg:city":"Glen Iris",
    "sg:classifiers":[
        {
            "category":"Mining & Drilling",
            "type":"Manufacturing & Wholesale Goods"
        }
    ],
    "sg:phone":"+61 3 9885 4225",
    "sg:postcode":"3146",
    "sg:province":"VIC",
    "sg:tags":[
        "geologist"
    ],
    "wof:name":"Nick Crase & Associates Pty Ltd",
    "wof:placetype":"venue"
},
  "geometry": {"coordinates":[145.06477355999999,-37.860874176],"type":"Point"}
}