{
  "type": "Feature",
  "properties": {
    "iso:country":"AU",
    "sg:address":"26 McLarty Pl",
    "sg:city":"Waroona",
    "sg:classifiers":[
        {
            "category":"Professional",
            "type":"Services"
        }
    ],
    "sg:phone":"+61 8 9733 1561",
    "sg:postcode":"6215",
    "sg:province":"WA",
    "sg:tags":[
        "transport"
    ],
    "wof:name":"Mitchell M & J",
    "wof:placetype":"venue"
},
  "geometry": {"coordinates":[115.925087,-32.854675],"type":"Point"}
}