{
  "type": "Feature",
  "properties": {
    "addr:full":"10 Derek St West Busselton WA 6280",
    "addr:housenumber":"10",
    "addr:postcode":"6280",
    "addr:street":"Derek St West",
    "iso:country":"AU",
    "sg:address":"10 Derek St",
    "sg:city":"West Busselton",
    "sg:classifiers":[
        {
            "category":"Utilities",
            "subcategory":"Electric",
            "type":"Services"
        }
    ],
    "sg:phone":"+61 8 9751 2168",
    "sg:postcode":"6280",
    "sg:province":"WA",
    "sg:tags":[
        "electrical",
        "contractor"
    ],
    "wof:name":"Callegari Electrical Contractors",
    "wof:placetype":"venue"
},
  "geometry": {"coordinates":[115.303291321,-33.6577682495],"type":"Point"}
}