{
  "type": "Feature",
  "properties": {
    "iso:country":"AU",
    "sg:address":"Level 2, 28 Burke Rd",
    "sg:city":"Malvern East",
    "sg:classifiers":[
        {
            "category":"Banks & Credit Unions",
            "subcategory":"Bank",
            "type":"Services"
        }
    ],
    "sg:phone":"+61 3 9572 3550",
    "sg:postcode":"3145",
    "sg:province":"VIC",
    "sg:tags":[
        "equipment",
        "sale",
        "point"
    ],
    "sg:website":"http://www.op-tech.com.au",
    "wof:name":"OP Technology Australia",
    "wof:placetype":"venue"
},
  "geometry": {"coordinates":[145.04830932600001,-37.8760910034],"type":"Point"}
}