{
  "type": "Feature",
  "properties": {
    "addr:full":"Suite 110, Goldsbrough Mort Building, 243 Pyrmont Pyrmont NSW 2009",
    "addr:housenumber":"243",
    "addr:postcode":"2009",
    "addr:street":"Pyrmont",
    "iso:country":"AU",
    "sg:address":"Suite 110, Goldsbrough Mort Building, 243 Pyrmont",
    "sg:city":"Pyrmont",
    "sg:classifiers":[
        {
            "category":"Banks & Credit Unions",
            "subcategory":"Bank",
            "type":"Services"
        }
    ],
    "sg:phone":"+61 1800 666 969",
    "sg:postcode":"2009",
    "sg:province":"NSW",
    "sg:tags":[
        "broker",
        "mortgage"
    ],
    "wof:name":"Mortgagemaker",
    "wof:placetype":"venue"
},
  "geometry": {"coordinates":[151.19711303700001,-33.8734931946],"type":"Point"}
}