{
  "type": "Feature",
  "properties": {
    "addr:full":"34 Smith St Southport QLD 4215",
    "addr:housenumber":"34",
    "addr:postcode":"4215",
    "addr:street":"Smith St",
    "iso:country":"AU",
    "sg:address":"34 Smith St",
    "sg:city":"Southport",
    "sg:classifiers":[
        {
            "category":"Autos & Motor Vehicles",
            "subcategory":"Boat Sales",
            "type":"Retail Goods"
        }
    ],
    "sg:phone":"+61 7 5591 6150",
    "sg:postcode":"4215",
    "sg:province":"QLD",
    "sg:tags":[
        "builder",
        "yacht",
        "repairer"
    ],
    "wof:name":"Nitro Marine",
    "wof:placetype":"venue"
},
  "geometry": {"coordinates":[153.404785156,-27.9635047913],"type":"Point"}
}