{
  "type": "Feature",
  "properties": {
    "iso:country":"AU",
    "sg:address":"Roche Rd",
    "sg:city":"Pemberton",
    "sg:classifiers":[
        {
            "category":"Farming",
            "subcategory":"Farm",
            "type":"Manufacturing & Wholesale Goods"
        }
    ],
    "sg:phone":"+61 8 9776 1096",
    "sg:postcode":"6260",
    "sg:province":"WA",
    "sg:tags":[
        "farmer"
    ],
    "wof:name":"Roche D",
    "wof:placetype":"venue"
},
  "geometry": {"coordinates":[116.05683136,-34.4056053162],"type":"Point"}
}