{
  "type": "Feature",
  "properties": {
    "addr:full":"Shop 35-36 Forrest Chase Perth WA 6000",
    "addr:housenumber":"35-36",
    "addr:postcode":"6000",
    "addr:street":"Forrest Chase",
    "iso:country":"AU",
    "sg:address":"Shop 35-36 Forrest Chase",
    "sg:city":"Perth",
    "sg:classifiers":[
        {
            "category":"Shopping",
            "subcategory":"Clothing, Apparel, & Fashions",
            "type":"Retail Goods"
        }
    ],
    "sg:phone":"+61 8 9221 3935",
    "sg:postcode":"6000",
    "sg:province":"WA",
    "sg:tags":[
        "lady",
        "wear"
    ],
    "wof:name":"Sportsgirl Pty Ltd",
    "wof:placetype":"venue"
},
  "geometry": {"coordinates":[115.859138489,-31.9527645111],"type":"Point"}
}