{
  "type": "Feature",
  "properties": {
    "addr:full":"Emily St Innisfail QLD 4860",
    "addr:postcode":"4860",
    "addr:street":"Emily St",
    "iso:country":"AU",
    "sg:address":"Emily St",
    "sg:city":"Innisfail",
    "sg:classifiers":[
        {
            "category":"Education",
            "subcategory":"School",
            "type":"Public Place"
        }
    ],
    "sg:phone":"+61 7 4061 0328",
    "sg:postcode":"4860",
    "sg:province":"QLD",
    "sg:tags":[
        "state",
        "except",
        "nsw"
    ],
    "wof:name":"Innisfail Preschool",
    "wof:placetype":"venue"
},
  "geometry": {"coordinates":[146.02748107900001,-17.5185756683],"type":"Point"}
}