{
  "type": "Feature",
  "properties": {
    "iso:country":"AU",
    "sg:address":"110 Campbell St",
    "sg:city":"Rockhampton",
    "sg:classifiers":[
        {
            "category":"Organizations",
            "subcategory":"Labor Organization",
            "type":"Services"
        }
    ],
    "sg:phone":"+61 7 4922 5390",
    "sg:postcode":"4700",
    "sg:province":"QLD",
    "sg:tags":[
        "union"
    ],
    "wof:name":"Queensland Nurses Union Of Employees",
    "wof:placetype":"venue"
},
  "geometry": {"coordinates":[150.51074218799999,-23.3857555389],"type":"Point"}
}