{
  "type": "Feature",
  "properties": {
    "iso:country":"AU",
    "sg:address":"172 Welsford St",
    "sg:city":"Shepparton",
    "sg:classifiers":[
        {
            "category":"Shopping",
            "subcategory":"Beauty & Cosmetics",
            "type":"Retail Goods"
        }
    ],
    "sg:phone":"+61 3 5821 3399",
    "sg:postcode":"3630",
    "sg:province":"VIC",
    "wof:name":"Family Care Pharmacy",
    "wof:placetype":"venue"
},
  "geometry": {"coordinates":[145.39749145499999,-36.3817939758],"type":"Point"}
}