{
  "type": "Feature",
  "properties": {
    "addr:full":"167 Cross Keys Rd Salisbury SA 5108",
    "addr:housenumber":"167",
    "addr:postcode":"5108",
    "addr:street":"Cross Keys Rd",
    "iso:country":"AU",
    "sg:address":"167 Cross Keys Rd",
    "sg:city":"Salisbury",
    "sg:classifiers":[
        {
            "category":"Farming",
            "subcategory":"Dairy Farm",
            "type":"Manufacturing & Wholesale Goods"
        }
    ],
    "sg:phone":"+61 8 8282 5678",
    "sg:postcode":"5108",
    "sg:province":"SA",
    "sg:tags":[
        "wholesaler",
        "product",
        "mfrs"
    ],
    "wof:name":"National Foods Limited",
    "wof:placetype":"venue"
},
  "geometry": {"coordinates":[138.60598754899999,-34.8199653625],"type":"Point"}
}