{
  "type": "Feature",
  "properties": {
    "addr:full":"13/ 60 Manning St Tuncurry NSW 2428",
    "addr:housenumber":"13 / 60",
    "addr:postcode":"2428",
    "addr:street":"Manning St",
    "iso:country":"AU",
    "sg:address":"13/ 60 Manning St",
    "sg:city":"Tuncurry",
    "sg:classifiers":[
        {
            "category":"Real Estate",
            "subcategory":"Real Estate Services",
            "type":"Services"
        }
    ],
    "sg:phone":"+61 2 6555 5392",
    "sg:postcode":"2428",
    "sg:province":"NSW",
    "sg:tags":[
        "valuer"
    ],
    "wof:name":"Robert Gould & Associates",
    "wof:placetype":"venue"
},
  "geometry": {"coordinates":[152.49992399999999,-32.176212],"type":"Point"}
}