{
  "type": "Feature",
  "properties": {
    "iso:country":"AU",
    "sg:address":"13/ 60 Manning St",
    "sg:city":"Tuncurry",
    "sg:classifiers":[
        {
            "category":"Real Estate",
            "subcategory":"Real Estate Services",
            "type":"Services"
        }
    ],
    "sg:phone":"+61 2 6555 5392",
    "sg:postcode":"2428",
    "sg:province":"NSW",
    "sg:tags":[
        "valuer"
    ],
    "wof:name":"Robert Gould & Associates",
    "wof:placetype":"venue"
},
  "geometry": {"coordinates":[152.499924,-32.176212],"type":"Point"}
}