{
  "type": "Feature",
  "properties": {
    "addr:full":"10- 12 Hughes St Leongatha VIC 3953",
    "addr:housenumber":"12",
    "addr:postcode":"3953",
    "addr:street":"Hughes St",
    "iso:country":"AU",
    "sg:address":"10- 12 Hughes St",
    "sg:city":"Leongatha",
    "sg:classifiers":[
        {
            "category":"Shopping",
            "type":"Retail Goods"
        }
    ],
    "sg:phone":"+61 3 5662 4388",
    "sg:postcode":"3953",
    "sg:province":"VIC",
    "sg:tags":[
        "agent",
        "stock"
    ],
    "wof:name":"Rodwell's & Co",
    "wof:placetype":"venue"
},
  "geometry": {"coordinates":[145.94667053200001,-38.4736785889],"type":"Point"}
}