{
  "type": "Feature",
  "properties": {
    "addr:full":"GPO Box 437 Brisbane QLD 4001",
    "addr:postcode":"4001",
    "iso:country":"AU",
    "sg:address":"GPO Box 437",
    "sg:city":"Brisbane",
    "sg:classifiers":[
        {
            "category":"Professional",
            "subcategory":"Employment Agencies",
            "type":"Services"
        }
    ],
    "sg:phone":"+61 7 3229 3033",
    "sg:postcode":"4001",
    "sg:province":"QLD",
    "wof:name":"Qld Intercultural Services",
    "wof:placetype":"venue"
},
  "geometry": {"coordinates":[152.889602661,-27.5978679657],"type":"Point"}
}