{
  "type": "Feature",
  "properties": {
    "iso:country":"AU",
    "sg:address":"Shop 9, Warner Village Shpng Cntr, Cnr Old North &",
    "sg:city":"Warner",
    "sg:classifiers":[
        {
            "category":"Health Services",
            "subcategory":"Dentist",
            "type":"Services"
        }
    ],
    "sg:phone":"+61 7 3882 3200",
    "sg:postcode":"4500",
    "sg:province":"QLD",
    "wof:name":"Teo Nicholas & Associates",
    "wof:placetype":"venue"
},
  "geometry": {"coordinates":[152.96087646500001,-27.3231163025],"type":"Point"}
}