{
  "type": "Feature",
  "properties": {
    "addr:full":"122 Craig Rd Dimbulah QLD 4872",
    "addr:housenumber":"122",
    "addr:postcode":"4872",
    "addr:street":"Craig Rd",
    "iso:country":"AU",
    "sg:address":"122 Craig Rd",
    "sg:city":"Dimbulah",
    "sg:classifiers":[
        {
            "category":"Farming",
            "subcategory":"Farm",
            "type":"Manufacturing & Wholesale Goods"
        }
    ],
    "sg:phone":"+61 7 4093 1161",
    "sg:postcode":"4872",
    "sg:province":"QLD",
    "sg:tags":[
        "farmer"
    ],
    "wof:name":"Balzarolo L & G",
    "wof:placetype":"venue"
},
  "geometry": {"coordinates":[145.15609741200001,-17.1319789886],"type":"Point"}
}