{
  "type": "Feature",
  "properties": {
    "addr:full":"851 Princes Hwy Springvale VIC 3171",
    "addr:housenumber":"851",
    "addr:postcode":"3171",
    "addr:street":"Princes Hwy",
    "iso:country":"AU",
    "sg:address":"851 Princes Hwy",
    "sg:city":"Springvale",
    "sg:classifiers":[
        {
            "category":"Wholesale",
            "subcategory":"Auto Parts",
            "type":"Manufacturing & Wholesale Goods"
        }
    ],
    "sg:phone":"+61 3 9546 8474",
    "sg:postcode":"3171",
    "sg:province":"VIC",
    "sg:tags":[
        "recyclers"
    ],
    "wof:name":"Murray's Truck Wrecking",
    "wof:placetype":"venue"
},
  "geometry": {"coordinates":[145.153564453,-37.931350708],"type":"Point"}
}