{
  "type": "Feature",
  "properties": {
    "iso:country":"AU",
    "sg:address":"31 Circuit Crt",
    "sg:city":"Hendon",
    "sg:classifiers":[
        {
            "category":"Manufacturing",
            "subcategory":"Glass & Minerals",
            "type":"Manufacturing & Wholesale Goods"
        }
    ],
    "sg:phone":"+61 8 8345 0611",
    "sg:postcode":"5014",
    "sg:province":"SA",
    "sg:tags":[
        "merchant",
        "granite",
        "marble"
    ],
    "wof:name":"EMR Marble + Granite Pty Ltd",
    "wof:placetype":"venue"
},
  "geometry": {"coordinates":[138.517868042,-34.8799629211],"type":"Point"}
}