{
  "type": "Feature",
  "properties": {
    "addr:full":"53 Lawford Crs Griffith NSW 2680",
    "addr:housenumber":"53",
    "addr:postcode":"2680",
    "addr:street":"Lawford Crs",
    "iso:country":"AU",
    "sg:address":"53 Lawford Crs",
    "sg:city":"Griffith",
    "sg:classifiers":[
        {
            "category":"Health Services",
            "subcategory":"Optometrist",
            "type":"Services"
        }
    ],
    "sg:phone":"+61 2 6962 4762",
    "sg:postcode":"2680",
    "sg:province":"NSW",
    "wof:name":"Mathers Paul",
    "wof:placetype":"venue"
},
  "geometry": {"coordinates":[146.05032299999999,-34.28944],"type":"Point"}
}