{
  "type": "Feature",
  "properties": {
    "addr:full":"Hurricane Drv Raby NSW 2566",
    "addr:postcode":"2566",
    "addr:street":"Hurricane Drv",
    "iso:country":"AU",
    "sg:address":"Hurricane Drv",
    "sg:city":"Raby",
    "sg:classifiers":[
        {
            "category":"Food & Beverages",
            "subcategory":"Liquor & Beverages",
            "type":"Retail Goods"
        }
    ],
    "sg:phone":"+61 2 9603 9455",
    "sg:postcode":"2566",
    "sg:province":"NSW",
    "sg:tags":[
        "store"
    ],
    "wof:name":"Bootlegger Deliveries",
    "wof:placetype":"venue"
},
  "geometry": {"coordinates":[150.82000732399999,-34.0260772705],"type":"Point"}
}