{
  "type": "Feature",
  "properties": {
    "iso:country":"AU",
    "sg:address":"1-11 Rothesay Ave St",
    "sg:city":"Marys",
    "sg:classifiers":[
        {
            "category":"Professional",
            "subcategory":"Accounting & Tax Preparation",
            "type":"Services"
        }
    ],
    "sg:phone":"+61 1300 650 141",
    "sg:postcode":"5042",
    "sg:province":"SA",
    "sg:tags":[
        "wholesaler",
        "stove",
        "mfrs",
        "range"
    ],
    "wof:name":"Tudor Appliances",
    "wof:placetype":"venue"
},
  "geometry": {"coordinates":[138.576721,-34.998653],"type":"Point"}
}