{
  "type": "Feature",
  "properties": {
    "iso:country":"AU",
    "sg:address":"21 Beaumont Crs",
    "sg:city":"Lalor",
    "sg:classifiers":[
        {
            "category":"Building & Trades",
            "subcategory":"Construction",
            "type":"Services"
        }
    ],
    "sg:phone":"+61 417 372 334",
    "sg:postcode":"3075",
    "sg:province":"VIC",
    "sg:tags":[
        "plasterboard",
        "plasterer",
        "fixer"
    ],
    "wof:name":"A.S Croxford",
    "wof:placetype":"venue"
},
  "geometry": {"coordinates":[144.759933472,-37.6905555725],"type":"Point"}
}