{
  "type": "Feature",
  "properties": {
    "addr:full":"21 Hampton St Hurstville Grove NSW 2220",
    "addr:housenumber":"21",
    "addr:postcode":"2220",
    "addr:street":"Hampton St",
    "iso:country":"AU",
    "sg:address":"21 Hampton St",
    "sg:city":"Hurstville Grove",
    "sg:classifiers":[
        {
            "category":"Building & Trades",
            "subcategory":"Construction",
            "type":"Services"
        }
    ],
    "sg:phone":"+61 418 216 369",
    "sg:postcode":"2220",
    "sg:province":"NSW",
    "sg:tags":[
        "contractor"
    ],
    "wof:name":"Riddle Renovations Pty Ltd",
    "wof:placetype":"venue"
},
  "geometry": {"coordinates":[151.09353637699999,-33.9740219116],"type":"Point"}
}