{
  "type": "Feature",
  "properties": {
    "iso:country":"AU",
    "sg:address":"Jennings St",
    "sg:city":"Laverton",
    "sg:classifiers":[
        {
            "category":"Arena",
            "subcategory":"Sports Club",
            "type":"Entertainment"
        }
    ],
    "sg:phone":"+61 3 9932 3070",
    "sg:postcode":"3028",
    "sg:province":"VIC",
    "sg:tags":[
        "defence",
        "supply",
        "self",
        "instruction",
        "martial art"
    ],
    "wof:name":"Goshin-Ryu Karate Association",
    "wof:placetype":"venue"
},
  "geometry": {"coordinates":[144.774765,-37.856842],"type":"Point"}
}