{
  "type": "Feature",
  "properties": {
    "iso:country":"AU",
    "sg:address":"PO Box 3106",
    "sg:city":"Darra",
    "sg:classifiers":[
        {
            "category":"Retail",
            "subcategory":"Driving School",
            "type":"Services"
        }
    ],
    "sg:phone":"+61 7 3879 3879",
    "sg:postcode":"4076",
    "sg:province":"QLD",
    "wof:name":"Auto Training Centre",
    "wof:placetype":"venue"
},
  "geometry": {"coordinates":[152.95223999000001,-27.5656299591],"type":"Point"}
}