{
  "type": "Feature",
  "properties": {
    "addr:full":"109b Main Rd Monbulk VIC 3793",
    "addr:housenumber":"109b",
    "addr:postcode":"3793",
    "addr:street":"Main Rd",
    "iso:country":"AU",
    "sg:address":"109b Main Rd",
    "sg:city":"Monbulk",
    "sg:classifiers":[
        {
            "category":"Fast Food",
            "type":"Food & Drink"
        }
    ],
    "sg:phone":"+61 3 9756 7633",
    "sg:postcode":"3793",
    "sg:province":"VIC",
    "sg:tags":[
        "away",
        "take"
    ],
    "wof:name":"Mountain Grande Takeaway",
    "wof:placetype":"venue"
},
  "geometry": {"coordinates":[145.40638732900001,-37.8741188049],"type":"Point"}
}