{
  "type": "Feature",
  "properties": {
    "addr:full":"61 Woodside Rd Nairne SA 5252",
    "addr:housenumber":"61",
    "addr:postcode":"5252",
    "addr:street":"Woodside Rd",
    "iso:country":"AU",
    "sg:address":"61 Woodside Rd",
    "sg:city":"Nairne",
    "sg:classifiers":[
        {
            "category":"Farming",
            "subcategory":"Farm & Veterinary Services",
            "type":"Manufacturing & Wholesale Goods"
        }
    ],
    "sg:phone":"+61 8 8388 6700",
    "sg:postcode":"5252",
    "sg:province":"SA",
    "sg:tags":[
        "agricultural",
        "advisory"
    ],
    "wof:name":"Holton Weather Forecasting Pty Ltd",
    "wof:placetype":"venue"
},
  "geometry": {"coordinates":[138.902435303,-35.0337295532],"type":"Point"}
}