{
  "type": "Feature",
  "properties": {
    "addr:full":"Shop 3 Orion Greater Springfield Town Centre Nambour QLD 4560",
    "addr:housenumber":"shop 3",
    "addr:postcode":"4560",
    "addr:street":"Orion Greater",
    "iso:country":"AU",
    "sg:address":"Shop 3",
    "sg:city":"Orion Greater Springfield Town Centre Nambour",
    "sg:classifiers":[
        {
            "category":"Personal",
            "subcategory":"Beauty Salon",
            "type":"Services"
        }
    ],
    "sg:phone":"+61 7 3470 0480",
    "sg:postcode":"4560",
    "sg:province":"QLD",
    "sg:tags":[
        "hairdresser"
    ],
    "wof:name":"Price Attack",
    "wof:placetype":"venue"
},
  "geometry": {"coordinates":[152.972167969,-26.609369278],"type":"Point"}
}