{
  "type": "Feature",
  "properties": {
    "iso:country":"AU",
    "sg:address":"25 Walkers Drv",
    "sg:city":"Maleny",
    "sg:classifiers":[
        {
            "category":"Health Services",
            "subcategory":"Health Practitioner",
            "type":"Services"
        }
    ],
    "sg:phone":"+61 7 5494 3862",
    "sg:postcode":"4552",
    "sg:province":"QLD",
    "sg:tags":[
        "acupuncture"
    ],
    "wof:name":"Brunner, Edith Lilly",
    "wof:placetype":"venue"
},
  "geometry": {"coordinates":[152.85162353499999,-26.7719097137],"type":"Point"}
}