{
  "type": "Feature",
  "properties": {
    "addr:full":"1/ 36 Randall St Slacks Creek QLD 4127",
    "addr:housenumber":"/ 36",
    "addr:postcode":"4127",
    "addr:street":"Randall St",
    "iso:country":"AU",
    "sg:address":"1/ 36 Randall St",
    "sg:city":"Slacks Creek",
    "sg:classifiers":[
        {
            "category":"Autos & Motor Vehicles",
            "subcategory":"Auto Supplies",
            "type":"Retail Goods"
        }
    ],
    "sg:phone":"+61 7 3808 5907",
    "sg:postcode":"4127",
    "sg:province":"QLD",
    "sg:tags":[
        "accessory"
    ],
    "wof:name":"E Tech Express Pty Ltd",
    "wof:placetype":"venue"
},
  "geometry": {"coordinates":[153.121704102,-27.6248626709],"type":"Point"}
}