{
  "type": "Feature",
  "properties": {
    "addr:full":"191/ 95 Grafton St Bondi Junction NSW 2022",
    "addr:housenumber":"191 / 95",
    "addr:postcode":"2022",
    "addr:street":"Grafton St",
    "iso:country":"AU",
    "sg:address":"191/ 95 Grafton St",
    "sg:city":"Bondi Junction",
    "sg:classifiers":[
        {
            "category":"Personal",
            "type":"Services"
        }
    ],
    "sg:phone":"+61 2 9387 5588",
    "sg:postcode":"2022",
    "sg:province":"NSW",
    "sg:tags":[
        "reducing",
        "treatment",
        "weight"
    ],
    "wof:name":"Cambridge Diet Pty Ltd",
    "wof:placetype":"venue"
},
  "geometry": {"coordinates":[151.249099731,-33.8910675049],"type":"Point"}
}