{
  "type": "Feature",
  "properties": {
    "iso:country":"AU",
    "sg:address":"Suite 1",
    "sg:city":"8A, 1st Floor Belconnen Churches Centre Benja",
    "sg:classifiers":[
        {
            "category":"Health Services",
            "subcategory":"Doctor",
            "type":"Services"
        }
    ],
    "sg:phone":"+61 2 6251 5149",
    "sg:postcode":"2617",
    "sg:province":"ACT",
    "sg:tags":[
        "podiatrist"
    ],
    "wof:name":"Belconnen Podiatry Services",
    "wof:placetype":"venue"
},
  "geometry": {"coordinates":[149.067337036,-35.2395133972],"type":"Point"}
}