{
  "type": "Feature",
  "properties": {
    "iso:country":"AU",
    "sg:address":"Shp 5/ 295 Ellison Rd",
    "sg:city":"Geebung",
    "sg:classifiers":[
        {
            "category":"Personal",
            "subcategory":"Beauty Salon",
            "type":"Services"
        }
    ],
    "sg:phone":"+61 7 3359 7638",
    "sg:postcode":"4034",
    "sg:province":"QLD",
    "sg:tags":[
        "hairdresser"
    ],
    "wof:name":"Split Endz Hair Salon",
    "wof:placetype":"venue"
},
  "geometry": {"coordinates":[153.038864,-27.374573],"type":"Point"}
}