{
  "type": "Feature",
  "properties": {
    "iso:country":"AU",
    "sg:address":"92 Malcom Rd",
    "sg:city":"Braeside",
    "sg:classifiers":[
        {
            "category":"Wholesale",
            "subcategory":"Home Furnishings",
            "type":"Manufacturing & Wholesale Goods"
        }
    ],
    "sg:phone":"+61 3 9580 3488",
    "sg:postcode":"3195",
    "sg:province":"VIC",
    "sg:tags":[
        "wholesaler",
        "mfrs",
        "manchester"
    ],
    "wof:name":"Egyptian Cotton Specialists",
    "wof:placetype":"venue"
},
  "geometry": {"coordinates":[145.112625122,-38.0012817383],"type":"Point"}
}