{
  "type": "Feature",
  "properties": {
    "addr:full":"Glen Davis Rd Capertee NSW 2846",
    "addr:postcode":"2846",
    "addr:street":"Davis Rd",
    "iso:country":"AU",
    "sg:address":"Glen Davis Rd",
    "sg:city":"Capertee",
    "sg:classifiers":[
        {
            "category":"Wholesale",
            "subcategory":"Farm Supplies",
            "type":"Manufacturing & Wholesale Goods"
        }
    ],
    "sg:phone":"+61 2 6379 7250",
    "sg:postcode":"2846",
    "sg:province":"NSW",
    "sg:tags":[
        "equipment"
    ],
    "wof:name":"A C Sales & Contracting",
    "wof:placetype":"venue"
},
  "geometry": {"coordinates":[149.984634,-33.145355],"type":"Point"}
}