{
  "type": "Feature",
  "properties": {
    "iso:country":"AU",
    "sg:address":"12 Yarrimbah Drv",
    "sg:city":"Nerang",
    "sg:classifiers":[
        {
            "category":"Building & Trades",
            "subcategory":"Construction",
            "type":"Services"
        }
    ],
    "sg:phone":"+61 7 5502 1301",
    "sg:postcode":"4211",
    "sg:province":"QLD",
    "sg:tags":[
        "repair",
        "maintenance",
        "contractor"
    ],
    "wof:name":"Queensland Maintenance Solutions Pty Ltd",
    "wof:placetype":"venue"
},
  "geometry": {"coordinates":[153.31440734899999,-27.9924736023],"type":"Point"}
}