{
  "type": "Feature",
  "properties": {
    "addr:full":"PO Box 6034 Waikiki WA 6169",
    "addr:postcode":"6169",
    "iso:country":"AU",
    "sg:address":"PO Box 6034",
    "sg:city":"Waikiki",
    "sg:classifiers":[
        {
            "category":"Building & Trades",
            "subcategory":"Pest Control",
            "type":"Services"
        }
    ],
    "sg:phone":"+61 407 476 713",
    "sg:postcode":"6169",
    "sg:province":"WA",
    "wof:name":"Luckens Pest Control",
    "wof:placetype":"venue"
},
  "geometry": {"coordinates":[115.753502,-32.31778],"type":"Point"}
}