{
  "type": "Feature",
  "properties": {
    "iso:country":"AU",
    "sg:address":"134 Princes Hwy",
    "sg:city":"Batemans Bay",
    "sg:classifiers":[
        {
            "category":"Home & Garden",
            "subcategory":"Hardware",
            "type":"Retail Goods"
        }
    ],
    "sg:phone":"+61 2 4472 5001",
    "sg:postcode":"2536",
    "sg:province":"NSW",
    "sg:tags":[
        "plumber",
        "supply"
    ],
    "wof:name":"Tradelink Plumbing Centres",
    "wof:placetype":"venue"
},
  "geometry": {"coordinates":[150.14486694300001,-35.7744140625],"type":"Point"}
}