{
  "type": "Feature",
  "properties": {
    "addr:full":"26 Birdbush St Elizabeth North SA 5113",
    "addr:housenumber":"26",
    "addr:postcode":"5113",
    "addr:street":"Birdbush St",
    "iso:country":"AU",
    "sg:address":"26 Birdbush St",
    "sg:city":"Elizabeth North",
    "sg:classifiers":[
        {
            "category":"Building & Trades",
            "subcategory":"Cleaning & Sanitation",
            "type":"Services"
        }
    ],
    "sg:phone":"+61 419 845 082",
    "sg:postcode":"5113",
    "sg:province":"SA",
    "sg:tags":[
        "window"
    ],
    "wof:name":"Wilkinson's Window Cleaning & Lawnmowing Service",
    "wof:placetype":"venue"
},
  "geometry": {"coordinates":[138.675216675,-34.6974754333],"type":"Point"}
}