{
  "type": "Feature",
  "properties": {
    "iso:country":"AU",
    "sg:address":"41 Balo St",
    "sg:city":"Moree",
    "sg:classifiers":[
        {
            "category":"Building & Trades",
            "subcategory":"Construction",
            "type":"Services"
        }
    ],
    "sg:phone":"+61 2 6752 4657",
    "sg:postcode":"2400",
    "sg:province":"NSW",
    "sg:tags":[
        "contractor"
    ],
    "wof:name":"Bob Kelly",
    "wof:placetype":"venue"
},
  "geometry": {"coordinates":[149.84175109899999,-29.4638767242],"type":"Point"}
}