{
  "type": "Feature",
  "properties": {
    "iso:country":"AU",
    "sg:address":"134 Alexandra St St",
    "sg:city":"Kilda East",
    "sg:classifiers":[
        {
            "category":"Health Services",
            "subcategory":"Health Practitioner",
            "type":"Services"
        }
    ],
    "sg:phone":"+61 412 203 263",
    "sg:postcode":"3183",
    "sg:province":"VIC",
    "sg:tags":[
        "acupuncture"
    ],
    "wof:name":"Colquist Shantell",
    "wof:placetype":"venue"
},
  "geometry": {"coordinates":[145.00404357900001,-37.8602600098],"type":"Point"}
}