{
  "type": "Feature",
  "properties": {
    "addr:full":"88 Stephen Tce St Peters SA 5069",
    "addr:housenumber":"88",
    "addr:postcode":"5069",
    "addr:street":"Stephen Tce",
    "iso:country":"AU",
    "sg:address":"88 Stephen Tce St",
    "sg:city":"Peters",
    "sg:classifiers":[
        {
            "category":"Autos & Motor Vehicles",
            "subcategory":"Fuel & Gas Station",
            "type":"Retail Goods"
        }
    ],
    "sg:phone":"+61 8 8362 1147",
    "sg:postcode":"5069",
    "sg:province":"SA",
    "wof:name":"St Peters Auto Repairs",
    "wof:placetype":"venue"
},
  "geometry": {"coordinates":[138.623504639,-34.9047203064],"type":"Point"}
}