{
  "type": "Feature",
  "properties": {
    "addr:full":"12 Hearne St Mortdale NSW 2223",
    "addr:housenumber":"12",
    "addr:postcode":"2223",
    "addr:street":"Hearne St",
    "iso:country":"AU",
    "sg:address":"12 Hearne St",
    "sg:city":"Mortdale",
    "sg:classifiers":[
        {
            "category":"Retail",
            "subcategory":"Auto Repair",
            "type":"Services"
        }
    ],
    "sg:phone":"+61 2 9534 4933",
    "sg:postcode":"2223",
    "sg:province":"NSW",
    "sg:tags":[
        "beater",
        "painter",
        "panel"
    ],
    "wof:name":"Oliveri Tony Smash Repairs",
    "wof:placetype":"venue"
},
  "geometry": {"coordinates":[151.06738281200001,-33.9652557373],"type":"Point"}
}