{
  "type": "Feature",
  "properties": {
    "addr:full":"62a Mission Hill Rd Penguin TAS 7316",
    "addr:housenumber":"62a",
    "addr:postcode":"7316",
    "addr:street":"Mission Hill Rd",
    "iso:country":"AU",
    "sg:address":"62a Mission Hill Rd",
    "sg:city":"Penguin",
    "sg:classifiers":[
        {
            "category":"Building & Trades",
            "subcategory":"Pest Control",
            "type":"Services"
        }
    ],
    "sg:phone":"+61 3 6437 2462",
    "sg:postcode":"7316",
    "sg:province":"TAS",
    "sg:tags":[
        "breastfeeding",
        "support"
    ],
    "wof:name":"Australian Breastfeeding Association",
    "wof:placetype":"venue"
},
  "geometry": {"coordinates":[146.05885314899999,-41.1137771606],"type":"Point"}
}