{
  "type": "Feature",
  "properties": {
    "iso:country":"AU",
    "sg:address":"279 Bunnerong Rd",
    "sg:city":"Pagewood",
    "sg:classifiers":[
        {
            "category":"Fast Food",
            "type":"Food & Drink"
        }
    ],
    "sg:phone":"+61 2 9344 6347",
    "sg:postcode":"2035",
    "sg:province":"NSW",
    "sg:tags":[
        "away",
        "take"
    ],
    "wof:name":"KFC",
    "wof:placetype":"venue"
},
  "geometry": {"coordinates":[151.22682189899999,-33.9439659119],"type":"Point"}
}