{
  "type": "Feature",
  "properties": {
    "iso:country":"AU",
    "sg:address":"28 Elderslie Rd",
    "sg:city":"Brighton",
    "sg:classifiers":[
        {
            "category":"Wholesale",
            "subcategory":"Metals & Minerals",
            "type":"Manufacturing & Wholesale Goods"
        }
    ],
    "sg:phone":"+61 3 6268 1833",
    "sg:postcode":"7030",
    "sg:province":"TAS",
    "sg:tags":[
        "steel",
        "stainless",
        "product",
        "equipment"
    ],
    "wof:name":"Hill Sheet Metal",
    "wof:placetype":"venue"
},
  "geometry": {"coordinates":[147.245361328,-42.7021560669],"type":"Point"}
}