{
  "type": "Feature",
  "properties": {
    "iso:country":"AU",
    "sg:address":"111 Bedford Rd",
    "sg:city":"Andergrove",
    "sg:classifiers":[
        {
            "category":"Personal",
            "subcategory":"Beauty Salon",
            "type":"Services"
        }
    ],
    "sg:phone":"+61 7 4955 2472",
    "sg:postcode":"4740",
    "sg:province":"QLD",
    "sg:tags":[
        "hairdresser"
    ],
    "wof:name":"Blondies For Hair",
    "wof:placetype":"venue"
},
  "geometry": {"coordinates":[149.181656,-21.106298],"type":"Point"}
}