{
  "type": "Feature",
  "properties": {
    "addr:full":"252 Polo Rd Goondiwindi QLD 4390",
    "addr:housenumber":"252",
    "addr:postcode":"4390",
    "addr:street":"Polo Rd",
    "iso:country":"AU",
    "sg:address":"252 Polo Rd",
    "sg:city":"Goondiwindi",
    "sg:classifiers":[
        {
            "category":"Professional",
            "subcategory":"Printing & Photocopies",
            "type":"Services"
        }
    ],
    "sg:phone":"+61 7 4671 3230",
    "sg:postcode":"4390",
    "sg:province":"QLD",
    "sg:tags":[
        "embroidery"
    ],
    "wof:name":"Lisas Screen Art & Embroidery",
    "wof:placetype":"venue"
},
  "geometry": {"coordinates":[150.31526184099999,-28.5154819489],"type":"Point"}
}