{
  "type": "Feature",
  "properties": {
    "addr:full":"Shop 2, 13 Benabrow Ave Bellara QLD 4507",
    "addr:housenumber":"shop;13",
    "addr:postcode":"4507",
    "addr:street":"Benabrow Ave",
    "iso:country":"AU",
    "sg:address":"Shop 2, 13 Benabrow Ave",
    "sg:city":"Bellara",
    "sg:classifiers":[
        {
            "category":"Professional",
            "subcategory":"Accounting & Tax Preparation",
            "type":"Services"
        }
    ],
    "sg:phone":"+61 7 3408 6566",
    "sg:postcode":"4507",
    "sg:province":"QLD",
    "sg:tags":[
        "accountant",
        "auditor"
    ],
    "wof:name":"Wagner & Co Chartered Accountants",
    "wof:placetype":"venue"
},
  "geometry": {"coordinates":[153.14840698200001,-27.0677318573],"type":"Point"}
}