{
  "type": "Feature",
  "properties": {
    "iso:country":"AU",
    "sg:address":"Albert St",
    "sg:city":"Medical Centre East Melbourne",
    "sg:classifiers":[
        {
            "category":"Personal",
            "subcategory":"Massage",
            "type":"Services"
        }
    ],
    "sg:phone":"+61 3 9419 9988",
    "sg:postcode":"3002",
    "sg:province":"VIC",
    "sg:tags":[
        "therapy"
    ],
    "wof:name":"Claughton Gemma",
    "wof:placetype":"venue"
},
  "geometry": {"coordinates":[144.97874450699999,-37.8099021912],"type":"Point"}
}