{
  "type": "Feature",
  "properties": {
    "iso:country":"AU",
    "sg:address":"Carpentry Training Centre 8 Diligent Drv",
    "sg:city":"Bayswater",
    "sg:classifiers":[
        {
            "category":"Education",
            "subcategory":"Special Training",
            "type":"Public Place"
        }
    ],
    "sg:phone":"+61 1300 365 022",
    "sg:postcode":"3153",
    "sg:province":"VIC",
    "sg:tags":[
        "development"
    ],
    "wof:name":"MEGT (Aust) Ltd",
    "wof:placetype":"venue"
},
  "geometry": {"coordinates":[145.27984619099999,-37.826007843],"type":"Point"}
}