{
  "type": "Feature",
  "properties": {
    "iso:country":"AU",
    "sg:address":"PO Box 3103",
    "sg:city":"Nedlands Broadway",
    "sg:classifiers":[
        {
            "category":"Health Services",
            "subcategory":"Doctor",
            "type":"Services"
        }
    ],
    "sg:phone":"+61 438 867 593",
    "sg:postcode":"6009",
    "sg:province":"WA",
    "sg:tags":[
        "medical",
        "practitioner"
    ],
    "wof:name":"Lim Barry Dr",
    "wof:placetype":"venue"
},
  "geometry": {"coordinates":[115.81455200000001,-31.985407],"type":"Point"}
}