{
  "type": "Feature",
  "properties": {
    "addr:full":"10 Oxford St Woollahra NSW 2025",
    "addr:housenumber":"10",
    "addr:postcode":"2025",
    "addr:street":"Oxford St",
    "iso:country":"AU",
    "sg:address":"10 Oxford St",
    "sg:city":"Woollahra",
    "sg:classifiers":[
        {
            "category":"Restaurant",
            "type":"Food & Drink"
        }
    ],
    "sg:phone":"+61 2 9331 2325",
    "sg:postcode":"2025",
    "sg:province":"NSW",
    "wof:name":"Claude's Restaurant",
    "wof:placetype":"venue"
},
  "geometry": {"coordinates":[151.232223511,-33.888507843],"type":"Point"}
}