{
  "type": "Feature",
  "properties": {
    "addr:full":"1909 Albany Hwy Maddington WA 6109",
    "addr:housenumber":"1909",
    "addr:postcode":"6109",
    "addr:street":"Albany Hwy",
    "iso:country":"AU",
    "sg:address":"1909 Albany Hwy",
    "sg:city":"Maddington",
    "sg:classifiers":[
        {
            "category":"Autos & Motor Vehicles",
            "subcategory":"Auto Supplies",
            "type":"Retail Goods"
        }
    ],
    "sg:phone":"+61 8 9493 4678",
    "sg:postcode":"6109",
    "sg:province":"WA",
    "sg:tags":[
        "accessory"
    ],
    "wof:name":"Georges Auto Parts & Batteries",
    "wof:placetype":"venue"
},
  "geometry": {"coordinates":[115.984153748,-32.051361084],"type":"Point"}
}