{
  "type": "Feature",
  "properties": {
    "addr:full":"21 Antares St Southern Cross WA 6426",
    "addr:housenumber":"21",
    "addr:postcode":"6426",
    "addr:street":"Antares St",
    "iso:country":"AU",
    "sg:address":"21 Antares St",
    "sg:city":"Southern Cross",
    "sg:classifiers":[
        {
            "category":"Travel",
            "subcategory":"Hotels & Motels",
            "type":"Entertainment"
        }
    ],
    "sg:phone":"+61 8 9049 1202",
    "sg:postcode":"6426",
    "sg:province":"WA",
    "sg:tags":[
        "accommodation"
    ],
    "wof:name":"Club Hotel Southern Cross",
    "wof:placetype":"venue"
},
  "geometry": {"coordinates":[119.326859,-31.230433],"type":"Point"}
}