{
  "type": "Feature",
  "properties": {
    "addr:full":"37 Loftus St Lawson NSW 2783",
    "addr:housenumber":"37",
    "addr:postcode":"2783",
    "addr:street":"Loftus St",
    "iso:country":"AU",
    "sg:address":"37 Loftus St",
    "sg:city":"Lawson",
    "sg:phone":"+61 2 4759 2052",
    "sg:postcode":"2783",
    "sg:province":"NSW",
    "wof:name":"Complete Tank Services",
    "wof:placetype":"venue"
},
  "geometry": {"coordinates":[150.424682617,-33.7207946777],"type":"Point"}
}