{
  "type": "Feature",
  "properties": {
    "addr:full":"Shop 10/ 67 Main Hurstbridge Rd Diamond Creek VIC 3089",
    "addr:housenumber":"shop 10 / 67",
    "addr:postcode":"3089",
    "addr:street":"Main Hurstbridge Rd",
    "iso:country":"AU",
    "sg:address":"Shop 10/ 67 Main Hurstbridge Rd",
    "sg:city":"Diamond Creek",
    "sg:classifiers":[
        {
            "category":"Real Estate",
            "subcategory":"Real Estate Agent",
            "type":"Services"
        }
    ],
    "sg:phone":"+61 3 9438 4422",
    "sg:postcode":"3089",
    "sg:province":"VIC",
    "wof:name":"Mason White McDougall",
    "wof:placetype":"venue"
},
  "geometry": {"coordinates":[145.158646,-37.67355],"type":"Point"}
}