{
  "type": "Feature",
  "properties": {
    "iso:country":"AU",
    "sg:address":"69 Bendigo Rd",
    "sg:city":"Kerang",
    "sg:classifiers":[
        {
            "category":"Shopping",
            "subcategory":"Stationery & Office Supplies",
            "type":"Retail Goods"
        }
    ],
    "sg:phone":"+61 3 5450 4411",
    "sg:postcode":"3579",
    "sg:province":"VIC",
    "wof:name":"J.I. Paper & Office Products",
    "wof:placetype":"venue"
},
  "geometry": {"coordinates":[143.91792297399999,-35.7366409302],"type":"Point"}
}