{
  "type": "Feature",
  "properties": {
    "iso:country":"AU",
    "sg:address":"Shed 3/ 16 Belconnen Crs",
    "sg:city":"Brendale",
    "sg:classifiers":[
        {
            "category":"Autos & Motor Vehicles",
            "subcategory":"Automobile Sales",
            "type":"Retail Goods"
        }
    ],
    "sg:phone":"+61 7 3205 2788",
    "sg:postcode":"4500",
    "sg:province":"QLD",
    "sg:tags":[
        "car",
        "used"
    ],
    "wof:name":"Gil Roberts",
    "wof:placetype":"venue"
},
  "geometry": {"coordinates":[152.97711181599999,-27.2541675568],"type":"Point"}
}