{
  "type": "Feature",
  "properties": {
    "iso:country":"AU",
    "sg:address":"20 Battersby St",
    "sg:city":"Zillmere",
    "sg:classifiers":[
        {
            "category":"Retail",
            "subcategory":"Storage",
            "type":"Services"
        }
    ],
    "sg:phone":"+61 7 3265 2213",
    "sg:postcode":"4034",
    "sg:province":"QLD",
    "sg:tags":[
        "removal",
        "furniture"
    ],
    "wof:name":"Bird Furniture Transport",
    "wof:placetype":"venue"
},
  "geometry": {"coordinates":[153.04444899999999,-27.354895],"type":"Point"}
}