{
  "type": "Feature",
  "properties": {
    "addr:full":"5 Johnstone Rd Brendale QLD 4500",
    "addr:housenumber":"5",
    "addr:postcode":"4500",
    "addr:street":"Johnstone Rd",
    "iso:country":"AU",
    "sg:address":"5 Johnstone Rd",
    "sg:city":"Brendale",
    "sg:classifiers":[
        {
            "category":"Banks & Credit Unions",
            "subcategory":"Financial Services",
            "type":"Services"
        }
    ],
    "sg:phone":"+61 7 3881 1445",
    "sg:postcode":"4500",
    "sg:province":"QLD",
    "sg:tags":[
        "equipment",
        "chain"
    ],
    "wof:name":"John L. Robertson Pty Ltd",
    "wof:placetype":"venue"
},
  "geometry": {"coordinates":[152.98797607399999,-27.3214206696],"type":"Point"}
}