{
  "type": "Feature",
  "properties": {
    "addr:full":"Darkana Rd Balhannah SA 5242",
    "addr:postcode":"5242",
    "addr:street":"Darkana Rd",
    "iso:country":"AU",
    "sg:address":"Darkana Rd",
    "sg:city":"Balhannah",
    "sg:classifiers":[
        {
            "category":"Home & Garden",
            "subcategory":"Home Furnishings",
            "type":"Retail Goods"
        }
    ],
    "sg:phone":"+61 8 8388 4416",
    "sg:postcode":"5242",
    "sg:province":"SA",
    "sg:tags":[
        "shower",
        "screen"
    ],
    "wof:name":"Braydern Pty Ltd",
    "wof:placetype":"venue"
},
  "geometry": {"coordinates":[138.829315186,-34.9907493591],"type":"Point"}
}