{
  "type": "Feature",
  "properties": {
    "addr:full":"7 Keys St Beaumaris VIC 3193",
    "addr:housenumber":"7",
    "addr:postcode":"3193",
    "addr:street":"Keys St",
    "iso:country":"AU",
    "sg:address":"7 Keys St",
    "sg:city":"Beaumaris",
    "sg:classifiers":[
        {
            "category":"Personal",
            "subcategory":"Beauty Salon",
            "type":"Services"
        }
    ],
    "sg:phone":"+61 3 9589 4688",
    "sg:postcode":"3193",
    "sg:province":"VIC",
    "sg:tags":[
        "hairdresser"
    ],
    "wof:name":"Beaumaris Village Coiffure",
    "wof:placetype":"venue"
},
  "geometry": {"coordinates":[145.041290283,-37.992149353],"type":"Point"}
}