{
  "type": "Feature",
  "properties": {
    "iso:country":"AU",
    "sg:address":"18 Bourke St",
    "sg:city":"Bunbury",
    "sg:classifiers":[
        {
            "category":"Retail",
            "subcategory":"Repair Shop",
            "type":"Services"
        }
    ],
    "sg:phone":"+61 8 9721 8718",
    "sg:postcode":"6230",
    "sg:province":"WA",
    "sg:tags":[
        "machine",
        "repairs",
        "part",
        "dryer",
        "washing"
    ],
    "wof:name":"Vacuum World Sales & Service",
    "wof:placetype":"venue"
},
  "geometry": {"coordinates":[115.642342,-33.334091],"type":"Point"}
}