{
  "type": "Feature",
  "properties": {
    "addr:full":"Suite 5, 104 William St Five Dock NSW 2046",
    "addr:housenumber":"104",
    "addr:postcode":"2046",
    "addr:street":"William St",
    "iso:country":"AU",
    "sg:address":"Suite 5, 104 William St",
    "sg:city":"Five Dock",
    "sg:classifiers":[
        {
            "category":"Personal",
            "subcategory":"Hair Removal",
            "type":"Services"
        }
    ],
    "sg:phone":"+61 2 9715 5559",
    "sg:postcode":"2046",
    "sg:province":"NSW",
    "wof:name":"Nliven Skin Therapy",
    "wof:placetype":"venue"
},
  "geometry": {"coordinates":[151.12033099999999,-33.866573],"type":"Point"}
}