{
  "type": "Feature",
  "properties": {
    "iso:country":"AU",
    "sg:address":"PO Box 43176",
    "sg:city":"Casuarina",
    "sg:classifiers":[
        {
            "category":"Building & Trades",
            "subcategory":"Cleaning & Sanitation",
            "type":"Services"
        }
    ],
    "sg:phone":"+61 8 8945 0059",
    "sg:postcode":"0810",
    "sg:province":"NT",
    "sg:tags":[
        "grease",
        "trap"
    ],
    "wof:name":"Darwin Water Services",
    "wof:placetype":"venue"
},
  "geometry": {"coordinates":[130.88352966299999,-12.3699102402],"type":"Point"}
}