{
  "type": "Feature",
  "properties": {
    "iso:country":"AU",
    "sg:address":"Eungella Rd",
    "sg:city":"Mirani",
    "sg:classifiers":[
        {
            "category":"Manufacturing",
            "subcategory":"Metals",
            "type":"Manufacturing & Wholesale Goods"
        }
    ],
    "sg:phone":"+61 7 4959 1381",
    "sg:postcode":"4754",
    "sg:province":"QLD",
    "sg:tags":[
        "steel",
        "fabricator",
        "mfrs"
    ],
    "wof:name":"Bryan Industries Pty Ltd",
    "wof:placetype":"venue"
},
  "geometry": {"coordinates":[148.862167,-21.15876],"type":"Point"}
}