{
  "type": "Feature",
  "properties": {
    "addr:full":"Level 2, 969 Burke Rd Hawthorn East VIC 3123",
    "addr:housenumber":"969",
    "addr:postcode":"3123",
    "addr:street":"Burke Rd",
    "iso:country":"AU",
    "sg:address":"Level 2, 969 Burke Rd",
    "sg:city":"Hawthorn East",
    "sg:classifiers":[
        {
            "category":"Professional",
            "subcategory":"Accounting & Tax Preparation",
            "type":"Services"
        }
    ],
    "sg:phone":"+61 3 9813 5522",
    "sg:postcode":"3123",
    "sg:province":"VIC",
    "sg:tags":[
        "accountant",
        "auditor"
    ],
    "wof:name":"Knights J R & Associates",
    "wof:placetype":"venue"
},
  "geometry": {"coordinates":[145.057907105,-37.8242225647],"type":"Point"}
}