{
  "type": "Feature",
  "properties": {
    "addr:full":"210 Charleton St Chandler QLD 4155",
    "addr:housenumber":"210",
    "addr:postcode":"4155",
    "addr:street":"Charleton St",
    "iso:country":"AU",
    "sg:address":"210 Charleton St",
    "sg:city":"Chandler",
    "sg:classifiers":[
        {
            "category":"Building & Trades",
            "subcategory":"Construction",
            "type":"Services"
        }
    ],
    "sg:phone":"+61 417 553 515",
    "sg:postcode":"4155",
    "sg:province":"QLD",
    "sg:tags":[
        "home",
        "air conditioning"
    ],
    "wof:name":"Energy Air",
    "wof:placetype":"venue"
},
  "geometry": {"coordinates":[153.16517639200001,-27.5107803345],"type":"Point"}
}