{
  "type": "Feature",
  "properties": {
    "iso:country":"AU",
    "sg:address":"68 Seaview Rd",
    "sg:city":"Tennyson",
    "sg:classifiers":[
        {
            "category":"Professional",
            "subcategory":"Engineering",
            "type":"Services"
        }
    ],
    "sg:phone":"+61 418 836 522",
    "sg:postcode":"5022",
    "sg:province":"SA",
    "sg:tags":[
        "engineer"
    ],
    "wof:name":"Ofteng",
    "wof:placetype":"venue"
},
  "geometry": {"coordinates":[138.48550415,-34.8858337402],"type":"Point"}
}