{
  "type": "Feature",
  "properties": {
    "addr:full":"Unit 5/ 3 York Rd Ingleburn NSW 2565",
    "addr:postcode":"2565",
    "addr:street":"York Rd",
    "iso:country":"AU",
    "sg:address":"Unit 5/ 3 York Rd",
    "sg:city":"Ingleburn",
    "sg:classifiers":[
        {
            "category":"Utilities",
            "subcategory":"Electric",
            "type":"Services"
        }
    ],
    "sg:phone":"+61 2 9605 7800",
    "sg:postcode":"2565",
    "sg:province":"NSW",
    "sg:tags":[
        "electrical",
        "contractor"
    ],
    "wof:name":"C J Grose Intergrating Telecommunications",
    "wof:placetype":"venue"
},
  "geometry": {"coordinates":[150.86329650900001,-33.9910430908],"type":"Point"}
}