{
  "type": "Feature",
  "properties": {
    "addr:full":"Lot 9 Ballina Airport Drv Ballina NSW 2478",
    "addr:postcode":"2478",
    "addr:street":"Airport Drv",
    "iso:country":"AU",
    "sg:address":"Lot 9 Ballina Airport Drv",
    "sg:city":"Ballina",
    "sg:classifiers":[
        {
            "category":"Manufacturing",
            "subcategory":"Aerospace",
            "type":"Manufacturing & Wholesale Goods"
        }
    ],
    "sg:phone":"+61 2 6686 7758",
    "sg:postcode":"2478",
    "sg:province":"NSW",
    "sg:tags":[
        "equipment",
        "aircraft",
        "maintenance"
    ],
    "wof:name":"Ballina Aircraft Refinishes",
    "wof:placetype":"venue"
},
  "geometry": {"coordinates":[153.59291076700001,-28.801197052],"type":"Point"}
}