{
  "type": "Feature",
  "properties": {
    "addr:full":"14 Reddy Drv Caboolture QLD 4510",
    "addr:housenumber":"14",
    "addr:postcode":"4510",
    "addr:street":"Reddy Drv",
    "iso:country":"AU",
    "sg:address":"14 Reddy Drv",
    "sg:city":"Caboolture",
    "sg:classifiers":[
        {
            "category":"Building & Trades",
            "subcategory":"Construction",
            "type":"Services"
        }
    ],
    "sg:phone":"+61 7 5428 2879",
    "sg:postcode":"4510",
    "sg:province":"QLD",
    "sg:tags":[
        "contractor"
    ],
    "wof:name":"G.J. Gardner. Homes",
    "wof:placetype":"venue"
},
  "geometry": {"coordinates":[152.96821600000001,-27.0791],"type":"Point"}
}