{
  "type": "Feature",
  "properties": {
    "iso:country":"AU",
    "sg:address":"165 Koroit St",
    "sg:city":"Warrnambool",
    "sg:classifiers":[
        {
            "category":"Banks & Credit Unions",
            "subcategory":"Financial Services",
            "type":"Services"
        }
    ],
    "sg:phone":"+61 1800 630 705",
    "sg:postcode":"3280",
    "sg:province":"VIC",
    "sg:tags":[
        "planning"
    ],
    "wof:name":"St Andrew's Financial Services",
    "wof:placetype":"venue"
},
  "geometry": {"coordinates":[142.482345581,-38.3831596375],"type":"Point"}
}