{
  "type": "Feature",
  "properties": {
    "addr:full":"23 Orange St Fruitgrove QLD 4113",
    "addr:housenumber":"23",
    "addr:postcode":"4113",
    "addr:street":"Orange St Fruitgrove",
    "iso:country":"AU",
    "sg:address":"23 Orange St",
    "sg:city":"Fruitgrove",
    "sg:classifiers":[
        {
            "category":"Wholesale",
            "subcategory":"Home Furnishings",
            "type":"Manufacturing & Wholesale Goods"
        }
    ],
    "sg:phone":"+61 7 3841 1244",
    "sg:postcode":"4113",
    "sg:province":"QLD",
    "sg:tags":[
        "wholesaler",
        "mfrs",
        "kitchenware"
    ],
    "wof:name":"Snaith Industries Pty Ltd",
    "wof:placetype":"venue"
},
  "geometry": {"coordinates":[153.079315186,-27.5952854156],"type":"Point"}
}