{
  "type": "Feature",
  "properties": {
    "addr:full":"6 Theiss Crs Muswellbrook NSW 2333",
    "addr:housenumber":"6",
    "addr:postcode":"2333",
    "addr:street":"Theiss Crs",
    "iso:country":"AU",
    "sg:address":"6 Theiss Crs",
    "sg:city":"Muswellbrook",
    "sg:classifiers":[
        {
            "category":"Building & Trades",
            "subcategory":"Locksmith",
            "type":"Services"
        }
    ],
    "sg:phone":"+61 2 6541 1913",
    "sg:postcode":"2333",
    "sg:province":"NSW",
    "sg:tags":[
        "strongroom",
        "safe",
        "door"
    ],
    "wof:name":"Elks Security Locksmiths & Alarm Services",
    "wof:placetype":"venue"
},
  "geometry": {"coordinates":[150.88752746599999,-32.2689208984],"type":"Point"}
}