{
  "type": "Feature",
  "properties": {
    "addr:full":"4/ 16 Norman Rd Croydon VIC 3136",
    "addr:housenumber":"/ 16",
    "addr:postcode":"3136",
    "addr:street":"Norman Rd",
    "iso:country":"AU",
    "sg:address":"4/ 16 Norman Rd",
    "sg:city":"Croydon",
    "sg:classifiers":[
        {
            "category":"Health Services",
            "subcategory":"Health Practitioner",
            "type":"Services"
        }
    ],
    "sg:phone":"+61 3 9725 7190",
    "sg:postcode":"3136",
    "sg:province":"VIC",
    "sg:tags":[
        "naturopath"
    ],
    "wof:name":"Elsa Parker",
    "wof:placetype":"venue"
},
  "geometry": {"coordinates":[145.28474426299999,-37.7879524231],"type":"Point"}
}