{
  "type": "Feature",
  "properties": {
    "iso:country":"AU",
    "sg:address":"112-118 Bowen St",
    "sg:city":"Spring Hill",
    "sg:classifiers":[
        {
            "category":"Banks & Credit Unions",
            "subcategory":"Bureau De Change",
            "type":"Services"
        }
    ],
    "sg:phone":"+61 7 3839 6326",
    "sg:postcode":"4004",
    "sg:province":"QLD",
    "sg:tags":[
        "photography",
        "video",
        "school"
    ],
    "wof:name":"Brisbane College Of Photography & Art",
    "wof:placetype":"venue"
},
  "geometry": {"coordinates":[153.028442383,-27.4627552032],"type":"Point"}
}