{
  "type": "Feature",
  "properties": {
    "addr:full":"8 Gregory St Queanbeyan NSW 2620",
    "addr:housenumber":"8",
    "addr:postcode":"2620",
    "addr:street":"Gregory St",
    "iso:country":"AU",
    "sg:address":"8 Gregory St",
    "sg:city":"Queanbeyan",
    "sg:classifiers":[
        {
            "category":"Home & Garden",
            "subcategory":"Furniture",
            "type":"Retail Goods"
        }
    ],
    "sg:phone":"+61 2 6297 8872",
    "sg:postcode":"2620",
    "sg:province":"NSW",
    "sg:tags":[
        "repair",
        "restoration"
    ],
    "wof:name":"Smart Upholstery Pty Ltd",
    "wof:placetype":"venue"
},
  "geometry": {"coordinates":[149.209915161,-35.3504943848],"type":"Point"}
}