{
  "type": "Feature",
  "properties": {
    "addr:full":"136 Gladstone Ave Coniston NSW 2500",
    "addr:housenumber":"136",
    "addr:postcode":"2500",
    "addr:street":"Gladstone Ave",
    "iso:country":"AU",
    "sg:address":"136 Gladstone Ave",
    "sg:city":"Coniston",
    "sg:classifiers":[
        {
            "category":"Autos & Motor Vehicles",
            "subcategory":"Fuel & Gas Station",
            "type":"Retail Goods"
        }
    ],
    "sg:phone":"+61 2 4227 3539",
    "sg:postcode":"2500",
    "sg:province":"NSW",
    "wof:name":"Coniston Service Station",
    "wof:placetype":"venue"
},
  "geometry": {"coordinates":[150.885223,-34.437004],"type":"Point"}
}