{
  "type": "Feature",
  "properties": {
    "iso:country":"AU",
    "sg:address":"18 Birubi Crs",
    "sg:city":"Bilgola Plateau",
    "sg:classifiers":[
        {
            "category":"Real Estate",
            "subcategory":"Architect",
            "type":"Services"
        }
    ],
    "sg:phone":"+61 2 9973 1801",
    "sg:postcode":"2107",
    "sg:province":"NSW",
    "wof:name":"Colin Dalton & Associates Pty Ltd",
    "wof:placetype":"venue"
},
  "geometry": {"coordinates":[151.32403564399999,-33.6429901123],"type":"Point"}
}