{
  "type": "Feature",
  "properties": {
    "addr:full":"3/ 50 McEvoy St Waterloo NSW 2017",
    "addr:housenumber":"/ 50",
    "addr:postcode":"2017",
    "addr:street":"Mcevoy St",
    "iso:country":"AU",
    "sg:address":"3/ 50 McEvoy St",
    "sg:city":"Waterloo",
    "sg:classifiers":[
        {
            "category":"Social Services",
            "subcategory":"Retirement Home",
            "type":"Services"
        }
    ],
    "sg:phone":"+61 2 9319 0513",
    "sg:postcode":"2017",
    "sg:province":"NSW",
    "sg:tags":[
        "t-shirt",
        "supplier"
    ],
    "wof:name":"Crown Clothing Australia",
    "wof:placetype":"venue"
},
  "geometry": {"coordinates":[151.20297241200001,-33.9011611938],"type":"Point"}
}