{
  "type": "Feature",
  "properties": {
    "addr:full":"PO Box 988 Cloverdale Prvte Bxes WA 6985",
    "addr:postcode":"6985",
    "iso:country":"AU",
    "sg:address":"PO Box 988",
    "sg:city":"Cloverdale Prvte Bxes",
    "sg:classifiers":[
        {
            "category":"Bars & Pubs",
            "subcategory":"Lounge",
            "type":"Food & Drink"
        }
    ],
    "sg:phone":"+61 8 9478 3427",
    "sg:postcode":"6985",
    "sg:province":"WA",
    "sg:tags":[
        "water",
        "filter",
        "drinking"
    ],
    "wof:name":"A AAABAL Waterfilters",
    "wof:placetype":"venue"
},
  "geometry": {"coordinates":[115.934341,-31.96364],"type":"Point"}
}