{
  "type": "Feature",
  "properties": {
    "addr:full":"173 Henley Beach Rd Mile End SA 5031",
    "addr:housenumber":"173",
    "addr:postcode":"5031",
    "addr:street":"Henley Beach Rd",
    "iso:country":"AU",
    "sg:address":"173 Henley Beach Rd",
    "sg:city":"Mile End",
    "sg:classifiers":[
        {
            "category":"Fast Food",
            "type":"Food & Drink"
        }
    ],
    "sg:phone":"+61 8 8352 4422",
    "sg:postcode":"5031",
    "sg:province":"SA",
    "sg:tags":[
        "away",
        "take"
    ],
    "wof:name":"Subway",
    "wof:placetype":"venue"
},
  "geometry": {"coordinates":[138.56109619099999,-34.9243431091],"type":"Point"}
}