{
  "type": "Feature",
  "properties": {
    "addr:full":"PO Box 99 Highett VIC 3190",
    "addr:postcode":"3190",
    "iso:country":"AU",
    "sg:address":"PO Box 99",
    "sg:city":"Highett",
    "sg:classifiers":[
        {
            "category":"Health Services",
            "subcategory":"Nursing And Care Facility",
            "type":"Services"
        }
    ],
    "sg:phone":"+61 3 9584 8110",
    "sg:postcode":"3190",
    "sg:province":"VIC",
    "sg:tags":[
        "home"
    ],
    "wof:name":"Residential Care Placements",
    "wof:placetype":"venue"
},
  "geometry": {"coordinates":[145.04006957999999,-37.9506187439],"type":"Point"}
}