{
  "type": "Feature",
  "properties": {
    "addr:full":"3/ 52 Mundarra Rd Echuca South VIC 3564",
    "addr:housenumber":"/ 52",
    "addr:postcode":"3564",
    "addr:street":"Mundarra Rd",
    "iso:country":"AU",
    "sg:address":"3/ 52 Mundarra Rd",
    "sg:city":"Echuca South",
    "sg:classifiers":[
        {
            "category":"Retail",
            "subcategory":"Auto Repair",
            "type":"Services"
        }
    ],
    "sg:phone":"+61 3 5482 4266",
    "sg:postcode":"3564",
    "sg:province":"VIC",
    "sg:tags":[
        "electrical"
    ],
    "wof:name":"G & N Auto Electrical",
    "wof:placetype":"venue"
},
  "geometry": {"coordinates":[144.75845336899999,-36.140789032],"type":"Point"}
}