{
  "type": "Feature",
  "properties": {
    "addr:full":"88 Bramston St Tarragindi QLD 4121",
    "addr:housenumber":"88",
    "addr:postcode":"4121",
    "addr:street":"Bramston St",
    "iso:country":"AU",
    "sg:address":"88 Bramston St",
    "sg:city":"Tarragindi",
    "sg:classifiers":[
        {
            "category":"Manufacturing",
            "subcategory":"Wood Products",
            "type":"Manufacturing & Wholesale Goods"
        }
    ],
    "sg:phone":"+61 7 3832 3003",
    "sg:postcode":"4121",
    "sg:province":"QLD",
    "sg:tags":[
        "polisher",
        "french"
    ],
    "wof:name":"M & N Upholsterers",
    "wof:placetype":"venue"
},
  "geometry": {"coordinates":[153.04139709500001,-27.5290699005],"type":"Point"}
}