{
  "type": "Feature",
  "properties": {
    "addr:full":"30 Poplar St Caulfield South VIC 3162",
    "addr:housenumber":"30",
    "addr:postcode":"3162",
    "addr:street":"Poplar St",
    "iso:country":"AU",
    "sg:address":"30 Poplar St",
    "sg:city":"Caulfield South",
    "sg:classifiers":[
        {
            "category":"Real Estate",
            "subcategory":"Surveying",
            "type":"Services"
        }
    ],
    "sg:phone":"+61 3 9532 8065",
    "sg:postcode":"3162",
    "sg:province":"VIC",
    "sg:tags":[
        "surveyor",
        "land"
    ],
    "wof:name":"S R W Surveyors Pty Ltd",
    "wof:placetype":"venue"
},
  "geometry": {"coordinates":[145.01968383799999,-37.8886795044],"type":"Point"}
}