{
  "type": "Feature",
  "properties": {
    "addr:full":"113b Pratten St Dalby QLD 4405",
    "addr:housenumber":"113b",
    "addr:postcode":"4405",
    "addr:street":"Pratten St",
    "iso:country":"AU",
    "sg:address":"113b Pratten St",
    "sg:city":"Dalby",
    "sg:classifiers":[
        {
            "category":"Utilities",
            "subcategory":"Electric",
            "type":"Services"
        }
    ],
    "sg:phone":"+61 7 4662 4006",
    "sg:postcode":"4405",
    "sg:province":"QLD",
    "sg:tags":[
        "electrical",
        "contractor"
    ],
    "wof:name":"Jurgen Klapper Electrical Pty Ltd",
    "wof:placetype":"venue"
},
  "geometry": {"coordinates":[151.26112365700001,-27.1799354553],"type":"Point"}
}