{
  "type": "Feature",
  "properties": {
    "iso:country":"AU",
    "sg:address":"PO Box 8238",
    "sg:city":"Broome",
    "sg:classifiers":[
        {
            "category":"Retail",
            "subcategory":"Car Wash",
            "type":"Services"
        }
    ],
    "sg:phone":"+61 8 9192 5000",
    "sg:postcode":"6725",
    "sg:province":"WA",
    "sg:tags":[
        "truck",
        "cleaning"
    ],
    "wof:name":"Pearl Coast Auto Detailers",
    "wof:placetype":"venue"
},
  "geometry": {"coordinates":[122.223739624,-17.9676647186],"type":"Point"}
}