{
  "type": "Feature",
  "properties": {
    "addr:full":"27 Detroit Crs Corio VIC 3214",
    "addr:housenumber":"27",
    "addr:postcode":"3214",
    "addr:street":"Detroit Crs",
    "iso:country":"AU",
    "sg:address":"27 Detroit Crs",
    "sg:city":"Corio",
    "sg:classifiers":[
        {
            "category":"Personal",
            "subcategory":"Beauty Salon",
            "type":"Services"
        }
    ],
    "sg:phone":"+61 3 5275 1817",
    "sg:postcode":"3214",
    "sg:province":"VIC",
    "sg:tags":[
        "hairdresser"
    ],
    "wof:name":"Jean Rowe Hair Studio",
    "wof:placetype":"venue"
},
  "geometry": {"coordinates":[144.35643005399999,-38.0738601685],"type":"Point"}
}