{
  "type": "Feature",
  "properties": {
    "iso:country":"AU",
    "sg:address":"2a Sussex St",
    "sg:city":"Glenelg",
    "sg:classifiers":[
        {
            "category":"Cafe",
            "type":"Food & Drink"
        }
    ],
    "sg:phone":"+61 8 8295 3599",
    "sg:postcode":"5045",
    "sg:province":"SA",
    "wof:name":"Zest Cafe Gallery",
    "wof:placetype":"venue"
},
  "geometry": {"coordinates":[138.514053,-34.980042],"type":"Point"}
}