{
  "type": "Feature",
  "properties": {
    "addr:full":"31 Aerodrome Rd Brandon QLD 4808",
    "addr:housenumber":"31",
    "addr:postcode":"4808",
    "addr:street":"Aerodrome Rd",
    "iso:country":"AU",
    "sg:address":"31 Aerodrome Rd",
    "sg:city":"Brandon",
    "sg:classifiers":[
        {
            "category":"Food & Beverages",
            "subcategory":"Farmers Market",
            "type":"Retail Goods"
        }
    ],
    "sg:phone":"+61 7 4782 5660",
    "sg:postcode":"4808",
    "sg:province":"QLD",
    "sg:tags":[
        "beekeeper"
    ],
    "wof:name":"G & A Apiaries Australia P/L",
    "wof:placetype":"venue"
},
  "geometry": {"coordinates":[147.334747314,-19.5902442932],"type":"Point"}
}