{
  "type": "Feature",
  "properties": {
    "addr:full":"Suite 29, 18 Stirling Hwy Nedlands WA 6009",
    "addr:housenumber":"18",
    "addr:postcode":"6009",
    "addr:street":"Stirling Hwy",
    "iso:country":"AU",
    "sg:address":"Suite 29, 18 Stirling Hwy",
    "sg:city":"Nedlands",
    "sg:classifiers":[
        {
            "category":"Communications",
            "type":"Services"
        }
    ],
    "sg:phone":"+61 8 9389 1099",
    "sg:postcode":"6009",
    "sg:province":"WA",
    "sg:tags":[
        "equipment",
        "satellite"
    ],
    "wof:name":"T.C. Communications",
    "wof:placetype":"venue"
},
  "geometry": {"coordinates":[115.81398,-31.977015],"type":"Point"}
}