{
  "type": "Feature",
  "properties": {
    "addr:full":"1 Sharon Rd Batemans Bay NSW 2536",
    "addr:housenumber":"1",
    "addr:postcode":"2536",
    "addr:street":"Sharon Rd",
    "iso:country":"AU",
    "sg:address":"1 Sharon Rd",
    "sg:city":"Batemans Bay",
    "sg:classifiers":[
        {
            "category":"Professional",
            "subcategory":"Engineering",
            "type":"Services"
        }
    ],
    "sg:phone":"+61 2 4472 5618",
    "sg:postcode":"2536",
    "sg:province":"NSW",
    "sg:tags":[
        "diesel",
        "engineer"
    ],
    "wof:name":"Bay Diesel & Machining",
    "wof:placetype":"venue"
},
  "geometry": {"coordinates":[150.17326355,-35.7199363708],"type":"Point"}
}