{
  "type": "Feature",
  "properties": {
    "addr:full":"67 Maribyrnong Rd Ascot Vale VIC 3032",
    "addr:housenumber":"67",
    "addr:postcode":"3032",
    "addr:street":"Maribyrnong Rd",
    "iso:country":"AU",
    "sg:address":"67 Maribyrnong Rd",
    "sg:city":"Ascot Vale",
    "sg:classifiers":[
        {
            "category":"Health Services",
            "subcategory":"Chiropractor",
            "type":"Services"
        }
    ],
    "sg:phone":"+61 3 9375 3333",
    "sg:postcode":"3032",
    "sg:province":"VIC",
    "wof:name":"The Parker Clinic",
    "wof:placetype":"venue"
},
  "geometry": {"coordinates":[144.91932700000001,-37.772156],"type":"Point"}
}