{
  "type": "Feature",
  "properties": {
    "addr:full":"2789 Gold Coast Hwy Broadbeach QLD 4218",
    "addr:housenumber":"2789",
    "addr:postcode":"4218",
    "addr:street":"Gold Coast Hwy",
    "iso:country":"AU",
    "sg:address":"2789 Gold Coast Hwy",
    "sg:city":"Broadbeach",
    "sg:classifiers":[
        {
            "category":"Fast Food",
            "type":"Food & Drink"
        }
    ],
    "sg:phone":"+61 7 5592 1199",
    "sg:postcode":"4218",
    "sg:province":"QLD",
    "sg:tags":[
        "away",
        "take"
    ],
    "wof:name":"Trawler Seafood Restaurant",
    "wof:placetype":"venue"
},
  "geometry": {"coordinates":[153.429290772,-28.0199146271],"type":"Point"}
}