{
  "type": "Feature",
  "properties": {
    "addr:full":"PO Box 627 Mittagong NSW 2575",
    "addr:postcode":"2575",
    "iso:country":"AU",
    "sg:address":"PO Box 627",
    "sg:city":"Mittagong",
    "sg:classifiers":[
        {
            "category":"Autos & Motor Vehicles",
            "subcategory":"Auto Supplies",
            "type":"Retail Goods"
        }
    ],
    "sg:phone":"+61 2 4872 2561",
    "sg:postcode":"2575",
    "sg:province":"NSW",
    "sg:tags":[
        "accessory"
    ],
    "wof:name":"4WD Off Road Driver Training",
    "wof:placetype":"venue"
},
  "geometry": {"coordinates":[150.44688415499999,-34.4510002136],"type":"Point"}
}