{
  "type": "Feature",
  "properties": {
    "iso:country":"AU",
    "sg:address":"5A River Rd West",
    "sg:city":"Parramatta",
    "sg:classifiers":[
        {
            "category":"Home & Garden",
            "subcategory":"Garden Supply",
            "type":"Retail Goods"
        }
    ],
    "sg:phone":"+61 2 9687 4688",
    "sg:postcode":"2150",
    "sg:province":"NSW",
    "sg:tags":[
        "equipment"
    ],
    "wof:name":"Sydney Pot Factory P/L",
    "wof:placetype":"venue"
},
  "geometry": {"coordinates":[151.01829528799999,-33.8166732788],"type":"Point"}
}