{
  "type": "Feature",
  "properties": {
    "addr:full":"18 Arcoona Ave Rostrevor SA 5073",
    "addr:housenumber":"18",
    "addr:postcode":"5073",
    "addr:street":"Arcoona Ave",
    "iso:country":"AU",
    "sg:address":"18 Arcoona Ave",
    "sg:city":"Rostrevor",
    "sg:classifiers":[
        {
            "category":"Building & Trades",
            "subcategory":"Construction",
            "type":"Services"
        }
    ],
    "sg:phone":"+61 8 8365 9999",
    "sg:postcode":"5073",
    "sg:province":"SA",
    "sg:tags":[
        "contractor"
    ],
    "wof:name":"Advanced Building Concepts",
    "wof:placetype":"venue"
},
  "geometry": {"coordinates":[138.694915772,-34.8941268921],"type":"Point"}
}