{
  "type": "Feature",
  "properties": {
    "iso:country":"AU",
    "sg:address":"1 Bretton St",
    "sg:city":"Warrnambool",
    "sg:classifiers":[
        {
            "category":"Manufacturing",
            "subcategory":"Petroleum Products",
            "type":"Manufacturing & Wholesale Goods"
        }
    ],
    "sg:phone":"+61 417 526 416",
    "sg:postcode":"3280",
    "sg:province":"VIC",
    "sg:tags":[
        "lubricant"
    ],
    "wof:name":"Stevenson R A & J C Nulon Products",
    "wof:placetype":"venue"
},
  "geometry": {"coordinates":[142.502883911,-38.3720245361],"type":"Point"}
}