{
  "type": "Feature",
  "properties": {
    "addr:full":"8 & 9, 20B Upper Jones Bay Wharf Pyrmont NSW 2009",
    "addr:housenumber":"20b",
    "addr:postcode":"2009",
    "addr:street":"9;Upper Jones Bay Wharf",
    "iso:country":"AU",
    "sg:address":"8 & 9, 20B Upper Jones Bay Wharf",
    "sg:city":"Pyrmont",
    "sg:classifiers":[
        {
            "category":"Professional",
            "subcategory":"Employment Agencies",
            "type":"Services"
        }
    ],
    "sg:phone":"+61 2 9566 2322",
    "sg:postcode":"2009",
    "sg:province":"NSW",
    "sg:tags":[
        "provider",
        "internet"
    ],
    "wof:name":"Netwave",
    "wof:placetype":"venue"
},
  "geometry": {"coordinates":[151.19398498499999,-33.8675575256],"type":"Point"}
}