{
  "type": "Feature",
  "properties": {
    "addr:full":"Chapel Rd Keysborough VIC 3173",
    "addr:postcode":"3173",
    "addr:street":"Chapel Rd",
    "iso:country":"AU",
    "sg:address":"Chapel Rd",
    "sg:city":"Keysborough",
    "sg:classifiers":[
        {
            "category":"Building & Trades",
            "subcategory":"Plumbing",
            "type":"Services"
        }
    ],
    "sg:phone":"+61 3 9798 6691",
    "sg:postcode":"3173",
    "sg:province":"VIC",
    "sg:tags":[
        "plumber",
        "gasfitters"
    ],
    "wof:name":"Bowman D & E Plumbing",
    "wof:placetype":"venue"
},
  "geometry": {"coordinates":[145.160766602,-38.0049133301],"type":"Point"}
}