{
  "type": "Feature",
  "properties": {
    "iso:country":"AU",
    "sg:address":"Factory 2 14 Apollo Crt",
    "sg:city":"Blackburn",
    "sg:classifiers":[
        {
            "category":"Building & Trades",
            "subcategory":"Construction",
            "type":"Services"
        }
    ],
    "sg:phone":"+61 3 9878 7999",
    "sg:postcode":"3130",
    "sg:province":"VIC",
    "sg:tags":[
        "pool",
        "swimming"
    ],
    "wof:name":"Euro Dersign Interiors",
    "wof:placetype":"venue"
},
  "geometry": {"coordinates":[145.16204834000001,-37.8201370239],"type":"Point"}
}