{
  "type": "Feature",
  "properties": {
    "addr:full":"Shop 7 Raby Bay Harbour, 152 Shore St Cleveland QLD 4163",
    "addr:housenumber":"shop 7;152",
    "addr:postcode":"4163",
    "addr:street":"Bay Harbour;Shore St",
    "iso:country":"AU",
    "sg:address":"Shop 7 Raby Bay Harbour, 152 Shore St",
    "sg:city":"Cleveland",
    "sg:classifiers":[
        {
            "category":"Real Estate",
            "subcategory":"Real Estate Agent",
            "type":"Services"
        }
    ],
    "sg:phone":"+61 7 3286 6888",
    "sg:postcode":"4163",
    "sg:province":"QLD",
    "wof:name":"Cleveland Real Estate Agencies Pty Ltd",
    "wof:placetype":"venue"
},
  "geometry": {"coordinates":[153.26927185100001,-27.5245552063],"type":"Point"}
}