{
  "type": "Feature",
  "properties": {
    "addr:full":"291 Marrickville Rd Marrickville NSW 1475",
    "addr:housenumber":"291",
    "addr:postcode":"1475",
    "addr:street":"Marrickville Rd",
    "iso:country":"AU",
    "sg:address":"291 Marrickville Rd",
    "sg:city":"Marrickville",
    "sg:classifiers":[
        {
            "category":"Restaurant",
            "type":"Food & Drink"
        }
    ],
    "sg:phone":"+61 2 8512 1022",
    "sg:postcode":"1475",
    "sg:province":"NSW",
    "sg:tags":[
        "pizza"
    ],
    "wof:name":"Dominos Pizza",
    "wof:placetype":"venue"
},
  "geometry": {"coordinates":[151.154830933,-33.909942627],"type":"Point"}
}