{
  "type": "Feature",
  "properties": {
    "iso:country":"AU",
    "sg:address":"87 Main Rd",
    "sg:city":"Balhannah",
    "sg:classifiers":[
        {
            "category":"Wholesale",
            "subcategory":"Wine & Distilled Alcoholic Beverages",
            "type":"Manufacturing & Wholesale Goods"
        }
    ],
    "sg:phone":"+61 8 8388 4449",
    "sg:postcode":"5242",
    "sg:province":"SA",
    "sg:tags":[
        "collector",
        "bottle"
    ],
    "wof:name":"Balhannah Recycling Centre",
    "wof:placetype":"venue"
},
  "geometry": {"coordinates":[138.82699585,-34.9902992249],"type":"Point"}
}