{
  "type": "Feature",
  "properties": {
    "addr:full":"12 Warne St Katoomba NSW 2780",
    "addr:housenumber":"12",
    "addr:postcode":"2780",
    "addr:street":"Warne St",
    "iso:country":"AU",
    "sg:address":"12 Warne St",
    "sg:city":"Katoomba",
    "sg:classifiers":[
        {
            "category":"Professional",
            "subcategory":"Art Services",
            "type":"Services"
        }
    ],
    "sg:phone":"+61 2 4782 5236",
    "sg:postcode":"2780",
    "sg:province":"NSW",
    "sg:tags":[
        "graphic",
        "designer"
    ],
    "wof:name":"Barry Moss & Associates",
    "wof:placetype":"venue"
},
  "geometry": {"coordinates":[150.31871032699999,-33.7188568115],"type":"Point"}
}