{
  "type": "Feature",
  "properties": {
    "iso:country":"AU",
    "sg:address":"5D, Level 5, Capitol Arcade, 113 Swanston St",
    "sg:city":"Melbourne",
    "sg:classifiers":[
        {
            "category":"Manufacturing",
            "subcategory":"Jewelry",
            "type":"Manufacturing & Wholesale Goods"
        }
    ],
    "sg:phone":"+61 412 854 834",
    "sg:postcode":"3001",
    "sg:province":"VIC",
    "sg:tags":[
        "mfrg",
        "jeweller"
    ],
    "wof:name":"Jewellery Connections",
    "wof:placetype":"venue"
},
  "geometry": {"coordinates":[144.96621704099999,-37.8151702881],"type":"Point"}
}