{
  "type": "Feature",
  "properties": {
    "addr:full":"47 Mabel St Cunnamulla QLD 4490",
    "addr:housenumber":"47",
    "addr:postcode":"4490",
    "addr:street":"Mabel St",
    "iso:country":"AU",
    "sg:address":"47 Mabel St",
    "sg:city":"Cunnamulla",
    "sg:classifiers":[
        {
            "category":"Professional",
            "type":"Services"
        }
    ],
    "sg:phone":"+61 7 4655 2105",
    "sg:postcode":"4490",
    "sg:province":"QLD",
    "sg:tags":[
        "transport"
    ],
    "wof:name":"Arnold Simpson",
    "wof:placetype":"venue"
},
  "geometry": {"coordinates":[145.693527222,-28.0679969788],"type":"Point"}
}