{
  "type": "Feature",
  "properties": {
    "addr:full":"5 Yeeda Rd Golden Bay WA 6174",
    "addr:housenumber":"5",
    "addr:postcode":"6174",
    "addr:street":"Yeeda Rd",
    "iso:country":"AU",
    "sg:address":"5 Yeeda Rd",
    "sg:city":"Golden Bay",
    "sg:classifiers":[
        {
            "category":"Professional",
            "subcategory":"Accounting & Tax Preparation",
            "type":"Services"
        }
    ],
    "sg:phone":"+61 8 9537 2859",
    "sg:postcode":"6174",
    "sg:province":"WA",
    "sg:tags":[
        "consultant",
        "taxation"
    ],
    "wof:name":"Golden Bay Tax & Accounting",
    "wof:placetype":"venue"
},
  "geometry": {"coordinates":[115.752258,-32.429012],"type":"Point"}
}