{
  "type": "Feature",
  "properties": {
    "addr:full":"18 Saracen St Caloundra QLD 4551",
    "addr:housenumber":"18",
    "addr:postcode":"4551",
    "addr:street":"Saracen St",
    "iso:country":"AU",
    "sg:address":"18 Saracen St",
    "sg:city":"Caloundra",
    "sg:classifiers":[
        {
            "category":"Home & Garden",
            "subcategory":"Carpets & Floor Coverings",
            "type":"Retail Goods"
        }
    ],
    "sg:phone":"+61 401 928 382",
    "sg:postcode":"4551",
    "sg:province":"QLD",
    "sg:tags":[
        "tile",
        "wall",
        "layer"
    ],
    "wof:name":"Adam Hauzer Precision Tiling",
    "wof:placetype":"venue"
},
  "geometry": {"coordinates":[153.12818908700001,-26.7773227692],"type":"Point"}
}