{
  "type": "Feature",
  "properties": {
    "addr:full":"Lot 101 Cosgrove Rd Enfield NSW 2136",
    "addr:postcode":"2136",
    "addr:street":"Cosgrove Rd",
    "iso:country":"AU",
    "sg:address":"Lot 101 Cosgrove Rd",
    "sg:city":"Enfield",
    "sg:classifiers":[
        {
            "category":"Shopping",
            "type":"Retail Goods"
        }
    ],
    "sg:phone":"+61 2 8244 8671",
    "sg:postcode":"2136",
    "sg:province":"NSW",
    "sg:tags":[
        "equipment",
        "safety",
        "accessory"
    ],
    "wof:name":"Deck Guardrail Australia Pty Ltd",
    "wof:placetype":"venue"
},
  "geometry": {"coordinates":[151.075119019,-33.8985519409],"type":"Point"}
}