{
  "type": "Feature",
  "properties": {
    "iso:country":"AU",
    "sg:address":"32 Elgin St",
    "sg:city":"Sale",
    "sg:classifiers":[
        {
            "category":"Building & Trades",
            "subcategory":"Plumbing",
            "type":"Services"
        }
    ],
    "sg:phone":"+61 3 5143 2452",
    "sg:postcode":"3850",
    "sg:province":"VIC",
    "sg:tags":[
        "plumber",
        "gasfitters"
    ],
    "wof:name":"Gaslec Services Pty Ltd",
    "wof:placetype":"venue"
},
  "geometry": {"coordinates":[147.078582764,-38.1088066101],"type":"Point"}
}