{
  "type": "Feature",
  "properties": {
    "iso:country":"AU",
    "sg:address":"26 Glenfine Ave",
    "sg:city":"Hamlyn Heights",
    "sg:classifiers":[
        {
            "category":"Education",
            "subcategory":"School",
            "type":"Public Place"
        }
    ],
    "sg:phone":"+61 3 5278 2117",
    "sg:postcode":"3215",
    "sg:province":"VIC",
    "sg:tags":[
        "co-educational"
    ],
    "wof:name":"Holy Spirit Primary School",
    "wof:placetype":"venue"
},
  "geometry": {"coordinates":[144.323562622,-38.1264877319],"type":"Point"}
}