{
  "type": "Feature",
  "properties": {
    "addr:full":"General Aviation, Hangar 7, Tom McDonald Drv Cairns QLD 4870",
    "addr:postcode":"4870",
    "addr:street":"Tom Mcdonald Drv",
    "iso:country":"AU",
    "sg:address":"General Aviation, Hangar 7, Tom McDonald Drv",
    "sg:city":"Cairns",
    "sg:classifiers":[
        {
            "category":"Professional",
            "subcategory":"Testing Lab",
            "type":"Services"
        }
    ],
    "sg:phone":"+61 7 4035 9537",
    "sg:postcode":"4870",
    "sg:province":"QLD",
    "sg:tags":[
        "inspection"
    ],
    "wof:name":"Hinterland Aero Engineering Pty Ltd",
    "wof:placetype":"venue"
},
  "geometry": {"coordinates":[145.745071411,-16.879447937],"type":"Point"}
}