{
  "type": "Feature",
  "properties": {
    "addr:full":"543 Station St Box Hill VIC 3128",
    "addr:housenumber":"543",
    "addr:postcode":"3128",
    "addr:street":"Station St",
    "iso:country":"AU",
    "sg:address":"543 Station St",
    "sg:city":"Box Hill",
    "sg:classifiers":[
        {
            "category":"Real Estate",
            "subcategory":"Real Estate Agent",
            "type":"Services"
        }
    ],
    "sg:phone":"+61 3 9899 6999",
    "sg:postcode":"3128",
    "sg:province":"VIC",
    "wof:name":"Webb Philip Pty Ltd",
    "wof:placetype":"venue"
},
  "geometry": {"coordinates":[145.12342834500001,-37.8210258484],"type":"Point"}
}