{
  "type": "Feature",
  "properties": {
    "iso:country":"AU",
    "sg:address":"29 Simons Rd",
    "sg:city":"Leopold",
    "sg:classifiers":[
        {
            "category":"Professional",
            "subcategory":"Art Services",
            "type":"Services"
        }
    ],
    "sg:phone":"+61 3 5250 2824",
    "sg:postcode":"3224",
    "sg:province":"VIC",
    "sg:tags":[
        "blackboard",
        "chalkboard"
    ],
    "wof:name":"Classic Blackboard Signs",
    "wof:placetype":"venue"
},
  "geometry": {"coordinates":[144.46991,-38.18766],"type":"Point"}
}