{
  "type": "Feature",
  "properties": {
    "addr:full":"846 Nicholson St Fitzroy North VIC 3068",
    "addr:housenumber":"846",
    "addr:postcode":"3068",
    "addr:street":"Nicholson St",
    "iso:country":"AU",
    "sg:address":"846 Nicholson St",
    "sg:city":"Fitzroy North",
    "sg:classifiers":[
        {
            "category":"Health Services",
            "subcategory":"Doctor",
            "type":"Services"
        }
    ],
    "sg:phone":"+61 3 9481 4128",
    "sg:postcode":"3068",
    "sg:province":"VIC",
    "sg:tags":[
        "medical",
        "practitioner"
    ],
    "wof:name":"Shannos Anthony",
    "wof:placetype":"venue"
},
  "geometry": {"coordinates":[144.978424072,-37.7788238525],"type":"Point"}
}