{
  "type": "Feature",
  "properties": {
    "addr:full":"Unit 4, 25- 33 Alfred Rd Chipping Norton NSW 2170",
    "addr:housenumber":"25 33",
    "addr:postcode":"2170",
    "addr:street":"Alfred Rd",
    "iso:country":"AU",
    "sg:address":"Unit 4, 25- 33 Alfred Rd",
    "sg:city":"Chipping Norton",
    "sg:classifiers":[
        {
            "category":"Home & Garden",
            "subcategory":"Hardware",
            "type":"Retail Goods"
        }
    ],
    "sg:phone":"+61 2 9726 4453",
    "sg:postcode":"2170",
    "sg:province":"NSW",
    "sg:tags":[
        "nut",
        "bolt"
    ],
    "wof:name":"Stainless Supplies",
    "wof:placetype":"venue"
},
  "geometry": {"coordinates":[150.96441650400001,-33.9229736328],"type":"Point"}
}