{
  "type": "Feature",
  "properties": {
    "addr:full":"Embassy Hotel, 92 North Tce Adelaide SA 5000",
    "addr:housenumber":"92",
    "addr:postcode":"5000",
    "addr:street":"North Tce",
    "iso:country":"AU",
    "sg:address":"Embassy Hotel, 92 North Tce",
    "sg:city":"Adelaide",
    "sg:classifiers":[
        {
            "category":"Travel",
            "subcategory":"Hotels & Motels",
            "type":"Entertainment"
        }
    ],
    "sg:phone":"+61 8 8410 9988",
    "sg:postcode":"5000",
    "sg:province":"SA",
    "sg:tags":[
        "pub"
    ],
    "wof:name":"Bar Rouge",
    "wof:placetype":"venue"
},
  "geometry": {"coordinates":[138.60076904300001,-34.9256401062],"type":"Point"}
}