{
  "type": "Feature",
  "properties": {
    "iso:country":"AU",
    "sg:address":"Chickiba Drv",
    "sg:city":"East Ballina",
    "sg:classifiers":[
        {
            "category":"Education",
            "subcategory":"School",
            "type":"Public Place"
        }
    ],
    "sg:phone":"+61 2 6686 0503",
    "sg:postcode":"2478",
    "sg:province":"NSW",
    "sg:tags":[
        "state",
        "-",
        "nsw"
    ],
    "wof:name":"Southern Cross Public School",
    "wof:placetype":"venue"
},
  "geometry": {"coordinates":[153.58860778799999,-28.850856781],"type":"Point"}
}