{
  "type": "Feature",
  "properties": {
    "addr:full":"14a Hannah St Beecroft NSW 2119",
    "addr:housenumber":"14a",
    "addr:postcode":"2119",
    "addr:street":"Hannah St",
    "iso:country":"AU",
    "sg:address":"14a Hannah St",
    "sg:city":"Beecroft",
    "sg:classifiers":[
        {
            "category":"Fast Food",
            "type":"Food & Drink"
        }
    ],
    "sg:phone":"+61 2 9484 0960",
    "sg:postcode":"2119",
    "sg:province":"NSW",
    "sg:tags":[
        "away",
        "take"
    ],
    "wof:name":"Beecroft Gourmet Chicken & Salads",
    "wof:placetype":"venue"
},
  "geometry": {"coordinates":[151.06533813499999,-33.749256134],"type":"Point"}
}