{
  "type": "Feature",
  "properties": {
    "addr:full":"Leopold St Croydon Park NSW 2133",
    "addr:postcode":"2133",
    "addr:street":"Leopold St",
    "iso:country":"AU",
    "sg:address":"Leopold St",
    "sg:city":"Croydon Park",
    "sg:classifiers":[
        {
            "category":"Building & Trades",
            "subcategory":"Plumbing",
            "type":"Services"
        }
    ],
    "sg:phone":"+61 2 9798 2862",
    "sg:postcode":"2133",
    "sg:province":"NSW",
    "sg:tags":[
        "plumber",
        "gasfitters"
    ],
    "wof:name":"Peters Plumbing",
    "wof:placetype":"venue"
},
  "geometry": {"coordinates":[151.115432739,-33.8947105408],"type":"Point"}
}