{
  "type": "Feature",
  "properties": {
    "iso:country":"AU",
    "sg:address":"142 Bellevue Pde",
    "sg:city":"Carlton",
    "sg:classifiers":[
        {
            "category":"Retail",
            "subcategory":"Auto Repair",
            "type":"Services"
        }
    ],
    "sg:phone":"+61 2 9546 6222",
    "sg:postcode":"2218",
    "sg:province":"NSW",
    "sg:tags":[
        "beater",
        "painter",
        "panel"
    ],
    "wof:name":"Peter Peter Panel Beater",
    "wof:placetype":"venue"
},
  "geometry": {"coordinates":[151.11587499999999,-33.978363],"type":"Point"}
}