{
  "type": "Feature",
  "properties": {
    "addr:full":"113 Johnston Rd Bass Hill NSW 2197",
    "addr:housenumber":"113",
    "addr:postcode":"2197",
    "addr:street":"Johnston Rd",
    "iso:country":"AU",
    "sg:address":"113 Johnston Rd",
    "sg:city":"Bass Hill",
    "sg:classifiers":[
        {
            "category":"Health Services",
            "subcategory":"Doctor",
            "type":"Services"
        }
    ],
    "sg:phone":"+61 2 9727 7249",
    "sg:postcode":"2197",
    "sg:province":"NSW",
    "sg:tags":[
        "medical",
        "practitioner"
    ],
    "wof:name":"White Crescent Medical Services Pty Ltd",
    "wof:placetype":"venue"
},
  "geometry": {"coordinates":[150.99092099999999,-33.900982],"type":"Point"}
}