{
  "type": "Feature",
  "properties": {
    "addr:full":"1 Delaneys Rd Warrandyte South VIC 3134",
    "addr:housenumber":"1",
    "addr:postcode":"3134",
    "addr:street":"Delaneys Rd",
    "iso:country":"AU",
    "sg:address":"1 Delaneys Rd",
    "sg:city":"Warrandyte South",
    "sg:classifiers":[
        {
            "category":"Retail",
            "subcategory":"Event Space",
            "type":"Services"
        }
    ],
    "sg:phone":"+61 3 9876 4044",
    "sg:postcode":"3134",
    "sg:province":"VIC",
    "sg:tags":[
        "venue",
        "reception",
        "wedding"
    ],
    "wof:name":"Vines Restaurant of the Yarra Valley",
    "wof:placetype":"venue"
},
  "geometry": {"coordinates":[145.24513244600001,-37.7678413391],"type":"Point"}
}