{
  "type": "Feature",
  "properties": {
    "addr:full":"4 Thanet Crt Ringwood VIC 3134",
    "addr:housenumber":"4",
    "addr:postcode":"3134",
    "addr:street":"Thanet Crt",
    "iso:country":"AU",
    "sg:address":"4 Thanet Crt",
    "sg:city":"Ringwood",
    "sg:classifiers":[
        {
            "category":"Autos & Motor Vehicles",
            "subcategory":"Automobile Sales",
            "type":"Retail Goods"
        }
    ],
    "sg:phone":"+61 3 9879 1961",
    "sg:postcode":"3134",
    "sg:province":"VIC",
    "sg:tags":[
        "car",
        "used"
    ],
    "wof:name":"Alpine Affaire",
    "wof:placetype":"venue"
},
  "geometry": {"coordinates":[145.226806641,-37.8172035217],"type":"Point"}
}