{
  "type": "Feature",
  "properties": {
    "addr:full":"269 Main Rd Derwent Park TAS 7009",
    "addr:housenumber":"269",
    "addr:postcode":"7009",
    "addr:street":"Main Rd",
    "iso:country":"AU",
    "sg:address":"269 Main Rd",
    "sg:city":"Derwent Park",
    "sg:classifiers":[
        {
            "category":"Home & Garden",
            "subcategory":"Hardware",
            "type":"Retail Goods"
        }
    ],
    "sg:phone":"+61 3 6272 1960",
    "sg:postcode":"7009",
    "sg:province":"TAS",
    "sg:tags":[
        "repair",
        "tool",
        "power"
    ],
    "wof:name":"A1 Power Tools",
    "wof:placetype":"venue"
},
  "geometry": {"coordinates":[147.286254883,-42.8357124329],"type":"Point"}
}