{
  "type": "Feature",
  "properties": {
    "iso:country":"AU",
    "sg:address":"97-99 Smart Rd",
    "sg:city":"Modbury",
    "sg:classifiers":[
        {
            "category":"Health Services",
            "subcategory":"Doctor",
            "type":"Services"
        }
    ],
    "sg:phone":"+61 8 8396 7092",
    "sg:postcode":"5092",
    "sg:province":"SA",
    "sg:tags":[
        "nurse",
        "nursing"
    ],
    "wof:name":"Health Force",
    "wof:placetype":"venue"
},
  "geometry": {"coordinates":[138.69546508799999,-34.8332176208],"type":"Point"}
}