{
  "type": "Feature",
  "properties": {
    "addr:full":"31 Hume St Crows Nest NSW 2065",
    "addr:housenumber":"31",
    "addr:postcode":"2065",
    "addr:street":"Hume St",
    "iso:country":"AU",
    "sg:address":"31 Hume St",
    "sg:city":"Crows Nest",
    "sg:classifiers":[
        {
            "category":"Organizations",
            "subcategory":"Professional Association",
            "type":"Services"
        }
    ],
    "sg:phone":"+61 2 9966 8794",
    "sg:postcode":"2065",
    "sg:province":"NSW",
    "sg:tags":[
        "web",
        "internet"
    ],
    "wof:name":"Pulse Creative Design Pty Ltd",
    "wof:placetype":"venue"
},
  "geometry": {"coordinates":[151.20013427699999,-33.8252639771],"type":"Point"}
}