{
  "type": "Feature",
  "properties": {
    "addr:full":"61 Edgbaston Rd Beverly Hills NSW 2209",
    "addr:housenumber":"61",
    "addr:postcode":"2209",
    "addr:street":"Edgbaston Rd",
    "iso:country":"AU",
    "sg:address":"61 Edgbaston Rd",
    "sg:city":"Beverly Hills",
    "sg:classifiers":[
        {
            "category":"Retail",
            "subcategory":"Auto Rental",
            "type":"Services"
        }
    ],
    "sg:phone":"+61 2 9584 3325",
    "sg:postcode":"2209",
    "sg:province":"NSW",
    "sg:tags":[
        "chauffeur",
        "car",
        "hire",
        "driven",
        "limousine"
    ],
    "wof:name":"A & B City Metro Vintage Wedding Cars",
    "wof:placetype":"venue"
},
  "geometry": {"coordinates":[151.07577499999999,-33.953152],"type":"Point"}
}