{
  "type": "Feature",
  "properties": {
    "iso:country":"AU",
    "sg:address":"14 Loquat Valley Rd",
    "sg:city":"Bayview",
    "sg:classifiers":[
        {
            "category":"Bars & Pubs",
            "subcategory":"Lounge",
            "type":"Food & Drink"
        }
    ],
    "sg:phone":"+61 416 018 882",
    "sg:postcode":"2104",
    "sg:province":"NSW",
    "sg:tags":[
        "water",
        "filter",
        "drinking"
    ],
    "wof:name":"Rory Cox Enterprises Pty Ltd",
    "wof:placetype":"venue"
},
  "geometry": {"coordinates":[151.294693,-33.658424],"type":"Point"}
}