{
  "type": "Feature",
  "properties": {
    "addr:full":"Factory 4 Highway Trade Centre Princes Hwy Pambula NSW 2549",
    "addr:housenumber":"4",
    "addr:postcode":"2549",
    "addr:street":"Highway Trade Centre Princes Hwy",
    "iso:country":"AU",
    "sg:address":"Factory 4 Highway Trade Centre Princes Hwy",
    "sg:city":"Pambula",
    "sg:classifiers":[
        {
            "category":"Wholesale",
            "subcategory":"Office Equipment",
            "type":"Manufacturing & Wholesale Goods"
        }
    ],
    "sg:phone":"+61 2 6495 6884",
    "sg:postcode":"2549",
    "sg:province":"NSW",
    "sg:tags":[
        "nail",
        "nailing"
    ],
    "wof:name":"Pambula Power Tools",
    "wof:placetype":"venue"
},
  "geometry": {"coordinates":[149.87449645999999,-36.9297676086],"type":"Point"}
}