{
  "type": "Feature",
  "properties": {
    "addr:full":"Shop 2 37-39 Bultje St Dubbo NSW 2830",
    "addr:housenumber":"shop 2",
    "addr:postcode":"37-39;2830",
    "addr:street":"Bultje St",
    "iso:country":"AU",
    "sg:address":"Shop 2 37-39 Bultje St",
    "sg:city":"Dubbo",
    "sg:classifiers":[
        {
            "category":"Personal",
            "subcategory":"Beauty Salon",
            "type":"Services"
        }
    ],
    "sg:phone":"+61 2 6884 4164",
    "sg:postcode":"2830",
    "sg:province":"NSW",
    "sg:tags":[
        "hairdresser"
    ],
    "wof:name":"Sharon Fardell's Hair Studio",
    "wof:placetype":"venue"
},
  "geometry": {"coordinates":[148.60272216800001,-32.2511672974],"type":"Point"}
}