{
  "type": "Feature",
  "properties": {
    "addr:full":"1 Araluen Pl Camden South NSW 2570",
    "addr:housenumber":"1",
    "addr:postcode":"2570",
    "addr:street":"Pl",
    "iso:country":"AU",
    "sg:address":"1 Araluen Pl",
    "sg:city":"Camden South",
    "sg:classifiers":[
        {
            "category":"Building & Trades",
            "subcategory":"Construction",
            "type":"Services"
        }
    ],
    "sg:phone":"+61 2 4655 9659",
    "sg:postcode":"2570",
    "sg:province":"NSW",
    "sg:tags":[
        "contractor"
    ],
    "wof:name":"Benayla Constructions Pty Ltd",
    "wof:placetype":"venue"
},
  "geometry": {"coordinates":[150.701904297,-34.0830841064],"type":"Point"}
}