{
  "type": "Feature",
  "properties": {
    "addr:full":"623 Harris St Ultimo NSW 2007",
    "addr:housenumber":"623",
    "addr:postcode":"2007",
    "addr:street":"Harris St",
    "iso:country":"AU",
    "sg:address":"623 Harris St",
    "sg:city":"Ultimo",
    "sg:classifiers":[
        {
            "category":"Personal",
            "type":"Services"
        }
    ],
    "sg:phone":"+61 2 9281 5066",
    "sg:postcode":"2007",
    "sg:province":"NSW",
    "sg:tags":[
        "career",
        "counselling"
    ],
    "wof:name":"Building Careers Centre Inc",
    "wof:placetype":"venue"
},
  "geometry": {"coordinates":[151.199783325,-33.8800430298],"type":"Point"}
}