{
  "type": "Feature",
  "properties": {
    "iso:country":"AU",
    "sg:address":"Shop 5/ 40 Pacific Ave",
    "sg:city":"Miami",
    "sg:classifiers":[
        {
            "category":"Personal",
            "subcategory":"Beauty Salon",
            "type":"Services"
        }
    ],
    "sg:phone":"+61 7 5572 6680",
    "sg:postcode":"4220",
    "sg:province":"QLD",
    "sg:tags":[
        "hairdresser"
    ],
    "wof:name":"Miramar Hair & Beauty",
    "wof:placetype":"venue"
},
  "geometry": {"coordinates":[153.435012817,-28.0632324219],"type":"Point"}
}