{
  "type": "Feature",
  "properties": {
    "addr:full":"27 Earle St Doonside NSW 2767",
    "addr:housenumber":"27",
    "addr:postcode":"2767",
    "addr:street":"Earle St",
    "iso:country":"AU",
    "sg:address":"27 Earle St",
    "sg:city":"Doonside",
    "sg:classifiers":[
        {
            "category":"Social Services",
            "subcategory":"Child Care",
            "type":"Services"
        }
    ],
    "sg:phone":"+61 2 9622 5168",
    "sg:postcode":"2767",
    "sg:province":"NSW",
    "wof:name":"Care Bear Kindergarten",
    "wof:placetype":"venue"
},
  "geometry": {"coordinates":[150.87196350100001,-33.7615089417],"type":"Point"}
}