{
  "type": "Feature",
  "properties": {
    "addr:full":"9 Byron St Williamstown VIC 3016",
    "addr:housenumber":"9",
    "addr:postcode":"3016",
    "addr:street":"Byron St",
    "iso:country":"AU",
    "sg:address":"9 Byron St",
    "sg:city":"Williamstown",
    "sg:classifiers":[
        {
            "category":"Wholesale",
            "subcategory":"Machinery & Supplies",
            "type":"Manufacturing & Wholesale Goods"
        }
    ],
    "sg:phone":"+61 3 9397 0119",
    "sg:postcode":"3016",
    "sg:province":"VIC",
    "sg:tags":[
        "rigging",
        "equipment",
        "hoisting"
    ],
    "wof:name":"John L. Robertson Pty Ltd",
    "wof:placetype":"venue"
},
  "geometry": {"coordinates":[144.86109924300001,-37.8530769348],"type":"Point"}
}