{
  "type": "Feature",
  "properties": {
    "addr:full":"5 Chokolich St Wangara WA 6065",
    "addr:housenumber":"5",
    "addr:postcode":"6065",
    "addr:street":"Chokolich St",
    "iso:country":"AU",
    "sg:address":"5 Chokolich St",
    "sg:city":"Wangara",
    "sg:classifiers":[
        {
            "category":"Manufacturing",
            "subcategory":"Furniture",
            "type":"Manufacturing & Wholesale Goods"
        }
    ],
    "sg:phone":"+61 8 9409 9179",
    "sg:postcode":"6065",
    "sg:province":"WA",
    "sg:tags":[
        "builder",
        "designer",
        "custom"
    ],
    "sg:website":"http://www.truecraftfurniture.com.au",
    "wof:name":"Truecraft Furniture",
    "wof:placetype":"venue"
},
  "geometry": {"coordinates":[115.815940857,-31.790391922],"type":"Point"}
}