{
  "type": "Feature",
  "properties": {
    "addr:full":"25 Doveton St North Ballarat VIC 3350",
    "addr:housenumber":"25",
    "addr:postcode":"3350",
    "addr:street":"Doveton St North",
    "iso:country":"AU",
    "sg:address":"25 Doveton St",
    "sg:city":"North Ballarat",
    "sg:classifiers":[
        {
            "category":"Shopping",
            "type":"Retail Goods"
        }
    ],
    "sg:phone":"+61 3 5331 2293",
    "sg:postcode":"3350",
    "sg:province":"VIC",
    "sg:tags":[
        "produce",
        "grain"
    ],
    "wof:name":"Smith L A",
    "wof:placetype":"venue"
},
  "geometry": {"coordinates":[143.854828,-37.562378],"type":"Point"}
}