{
  "type": "Feature",
  "properties": {
    "addr:full":"1 Kenmore Rd Kenmore QLD 4069",
    "addr:housenumber":"1",
    "addr:postcode":"4069",
    "addr:street":"Kenmore Rd",
    "iso:country":"AU",
    "sg:address":"1 Kenmore Rd",
    "sg:city":"Kenmore",
    "sg:classifiers":[
        {
            "category":"Education",
            "subcategory":"School",
            "type":"Public Place"
        }
    ],
    "sg:phone":"+61 7 3378 8943",
    "sg:postcode":"4069",
    "sg:province":"QLD",
    "wof:name":"Our Lady Of The Rosary O.S.H.C.",
    "wof:placetype":"venue"
},
  "geometry": {"coordinates":[152.93754577600001,-27.5106067657],"type":"Point"}
}