{
  "type": "Feature",
  "properties": {
    "iso:country":"AU",
    "sg:address":"220 Preston Point Rd",
    "sg:city":"Bicton",
    "sg:classifiers":[
        {
            "category":"Health Services",
            "subcategory":"Doctor",
            "type":"Services"
        }
    ],
    "sg:phone":"+61 8 9339 8634",
    "sg:postcode":"6157",
    "sg:province":"WA",
    "sg:tags":[
        "nurse",
        "nursing"
    ],
    "wof:name":"Aged Care Staffing Agency",
    "wof:placetype":"venue"
},
  "geometry": {"coordinates":[115.782944,-32.030193],"type":"Point"}
}