{
  "type": "Feature",
  "properties": {
    "iso:country":"AU",
    "sg:address":"92 Curlewis St",
    "sg:city":"Bondi Beach",
    "sg:classifiers":[
        {
            "category":"Retail",
            "subcategory":"Auto Repair",
            "type":"Services"
        }
    ],
    "sg:phone":"+61 2 9300 0141",
    "sg:postcode":"2026",
    "sg:province":"NSW",
    "sg:tags":[
        "repairer",
        "motor",
        "engineer"
    ],
    "wof:name":"Bondi Garage",
    "wof:placetype":"venue"
},
  "geometry": {"coordinates":[151.272338867,-33.8874320984],"type":"Point"}
}