{
  "type": "Feature",
  "properties": {
    "addr:full":"331 Rocky Point Rd Sans Souci NSW 2219",
    "addr:housenumber":"331",
    "addr:postcode":"2219",
    "addr:street":"Rocky Point Rd",
    "iso:country":"AU",
    "sg:address":"331 Rocky Point Rd",
    "sg:city":"Sans Souci",
    "sg:classifiers":[
        {
            "category":"Personal",
            "subcategory":"Massage",
            "type":"Services"
        }
    ],
    "sg:phone":"+61 2 9529 8922",
    "sg:postcode":"2219",
    "sg:province":"NSW",
    "sg:tags":[
        "therapy"
    ],
    "wof:name":"Inspa",
    "wof:placetype":"venue"
},
  "geometry": {"coordinates":[151.13209499999999,-33.991825],"type":"Point"}
}