{
  "type": "Feature",
  "properties": {
    "iso:country":"AU",
    "sg:address":"Shop 3, 39 Knuckey St",
    "sg:city":"Darwin",
    "sg:classifiers":[
        {
            "category":"Home & Garden",
            "subcategory":"Kitchen Supply",
            "type":"Retail Goods"
        }
    ],
    "sg:phone":"+61 8 8981 2611",
    "sg:postcode":"0800",
    "sg:province":"NT",
    "sg:tags":[
        "sharpening"
    ],
    "wof:name":"While U Wait Sharpening",
    "wof:placetype":"venue"
},
  "geometry": {"coordinates":[130.84237670900001,-12.4620227814],"type":"Point"}
}