{
  "type": "Feature",
  "properties": {
    "addr:full":"33 Jarrah St Wodonga VIC 3690",
    "addr:housenumber":"33",
    "addr:postcode":"3690",
    "addr:street":"Jarrah St",
    "iso:country":"AU",
    "sg:address":"33 Jarrah St",
    "sg:city":"Wodonga",
    "sg:classifiers":[
        {
            "category":"Utilities",
            "subcategory":"Electric",
            "type":"Services"
        }
    ],
    "sg:phone":"+61 412 691 004",
    "sg:postcode":"3690",
    "sg:province":"VIC",
    "sg:tags":[
        "electrical",
        "contractor"
    ],
    "wof:name":"McLachlan Craig",
    "wof:placetype":"venue"
},
  "geometry": {"coordinates":[146.880584717,-36.1393890381],"type":"Point"}
}