{
  "type": "Feature",
  "properties": {
    "addr:full":"Lvl4/ 405 Bourke St Melbourne VIC 3000",
    "addr:housenumber":"405",
    "addr:postcode":"3000",
    "addr:street":"Bourke St",
    "iso:country":"AU",
    "sg:address":"Lvl4/ 405 Bourke St",
    "sg:city":"Melbourne",
    "sg:classifiers":[
        {
            "category":"Education",
            "subcategory":"Special Training",
            "type":"Public Place"
        }
    ],
    "sg:phone":"+61 3 9642 0088",
    "sg:postcode":"3000",
    "sg:province":"VIC",
    "sg:tags":[
        "development"
    ],
    "wof:name":"Della International College Pty Ltd",
    "wof:placetype":"venue"
},
  "geometry": {"coordinates":[144.96220398,-37.8146591187],"type":"Point"}
}