{
  "type": "Feature",
  "properties": {
    "addr:full":"2 Lethbridge St Penrith NSW 2750",
    "addr:housenumber":"2",
    "addr:postcode":"2750",
    "addr:street":"Lethbridge St",
    "iso:country":"AU",
    "sg:address":"2 Lethbridge St",
    "sg:city":"Penrith",
    "sg:classifiers":[
        {
            "category":"Health Services",
            "subcategory":"Health Practitioner",
            "type":"Services"
        }
    ],
    "sg:phone":"+61 2 4721 3198",
    "sg:postcode":"2750",
    "sg:province":"NSW",
    "sg:tags":[
        "naturopath"
    ],
    "wof:name":"John Miller-Crispe",
    "wof:placetype":"venue"
},
  "geometry": {"coordinates":[150.70082092300001,-33.7668495178],"type":"Point"}
}