{
  "type": "Feature",
  "properties": {
    "addr:full":"414 Belmore River Left Bank Rd Belmore River NSW 2440",
    "addr:housenumber":"414",
    "addr:postcode":"2440",
    "addr:street":"Belmore River Left Bank Rd Belmore",
    "iso:country":"AU",
    "sg:address":"414 Belmore River Left Bank Rd",
    "sg:city":"Belmore River",
    "sg:classifiers":[
        {
            "category":"Banks & Credit Unions",
            "subcategory":"Financial Services",
            "type":"Services"
        }
    ],
    "sg:phone":"+61 2 6567 5198",
    "sg:postcode":"2440",
    "sg:province":"NSW",
    "sg:tags":[
        "planning"
    ],
    "wof:name":"Elite Super Pty Ltd",
    "wof:placetype":"venue"
},
  "geometry": {"coordinates":[152.96980300000001,-31.117664],"type":"Point"}
}