{
  "type": "Feature",
  "properties": {
    "addr:full":"680 Port Rd Beverley SA 5009",
    "addr:housenumber":"680",
    "addr:postcode":"5009",
    "addr:street":"Port Rd",
    "iso:country":"AU",
    "sg:address":"680 Port Rd",
    "sg:city":"Beverley",
    "sg:classifiers":[
        {
            "category":"Wholesale",
            "subcategory":"Machinery & Supplies",
            "type":"Manufacturing & Wholesale Goods"
        }
    ],
    "sg:phone":"+61 8 8243 1451",
    "sg:postcode":"5009",
    "sg:province":"SA",
    "sg:tags":[
        "engine",
        "petrol"
    ],
    "wof:name":"Hughes Mechanical",
    "wof:placetype":"venue"
},
  "geometry": {"coordinates":[138.54762268100001,-34.8894767761],"type":"Point"}
}