{
  "type": "Feature",
  "properties": {
    "addr:full":"5 10 O'Hart Cl Charmhaven NSW 2263",
    "addr:housenumber":"10",
    "addr:postcode":"2263",
    "addr:street":"5;Cl Charmhaven",
    "iso:country":"AU",
    "sg:address":"5 10 O'Hart Cl",
    "sg:city":"Charmhaven",
    "sg:classifiers":[
        {
            "category":"Autos & Motor Vehicles",
            "subcategory":"Boat Sales",
            "type":"Retail Goods"
        }
    ],
    "sg:phone":"+61 2 4367 6898",
    "sg:postcode":"2263",
    "sg:province":"NSW",
    "sg:tags":[
        "builder",
        "yacht",
        "repairer"
    ],
    "wof:name":"Coastal Outboard Sales & Service",
    "wof:placetype":"venue"
},
  "geometry": {"coordinates":[151.501068,-33.236889],"type":"Point"}
}