{
  "type": "Feature",
  "properties": {
    "addr:full":"176 Coventry St South Melbourne VIC 3205",
    "addr:housenumber":"176",
    "addr:postcode":"3205",
    "addr:street":"Coventry St",
    "iso:country":"AU",
    "sg:address":"176 Coventry St",
    "sg:city":"South Melbourne",
    "sg:classifiers":[
        {
            "category":"Home & Garden",
            "subcategory":"Carpets & Floor Coverings",
            "type":"Retail Goods"
        }
    ],
    "sg:phone":"+61 3 9690 8333",
    "sg:postcode":"3205",
    "sg:province":"VIC",
    "sg:tags":[
        "wood"
    ],
    "wof:name":"The Solid Timber Flooring Co.",
    "wof:placetype":"venue"
},
  "geometry": {"coordinates":[144.96397400000001,-37.830624],"type":"Point"}
}