{
  "type": "Feature",
  "properties": {
    "addr:full":"5 Bremen Dr Salisbury South SA 5106",
    "addr:housenumber":"5",
    "addr:postcode":"5106",
    "addr:street":"Bremen Dr",
    "iso:country":"AU",
    "sg:address":"5 Bremen Dr",
    "sg:city":"Salisbury South",
    "sg:classifiers":[
        {
            "category":"Manufacturing",
            "subcategory":"Metals",
            "type":"Manufacturing & Wholesale Goods"
        }
    ],
    "sg:phone":"+61 8 8281 1211",
    "sg:postcode":"5106",
    "sg:province":"SA",
    "sg:tags":[
        "cutting"
    ],
    "wof:name":"A & B Industries Pty Ltd",
    "wof:placetype":"venue"
},
  "geometry": {"coordinates":[138.635895,-34.783485],"type":"Point"}
}