{
  "type": "Feature",
  "properties": {
    "addr:full":"8 Jellicoe St Concord NSW 2137",
    "addr:housenumber":"8",
    "addr:postcode":"2137",
    "addr:street":"Jellicoe St",
    "iso:country":"AU",
    "sg:address":"8 Jellicoe St",
    "sg:city":"Concord",
    "sg:classifiers":[
        {
            "category":"Utilities",
            "subcategory":"Electric",
            "type":"Services"
        }
    ],
    "sg:phone":"+61 2 9743 2515",
    "sg:postcode":"2137",
    "sg:province":"NSW",
    "sg:tags":[
        "electrical",
        "contractor"
    ],
    "wof:name":"Ross Forrest",
    "wof:placetype":"venue"
},
  "geometry": {"coordinates":[151.104736328,-33.8567428589],"type":"Point"}
}