{
  "type": "Feature",
  "properties": {
    "iso:country":"AU",
    "sg:address":"Ste 5b/ 140 Margaret St",
    "sg:city":"Toowoomba City",
    "sg:classifiers":[
        {
            "category":"Banks & Credit Unions",
            "subcategory":"Financial Services",
            "type":"Services"
        }
    ],
    "sg:phone":"+61 7 4638 4720",
    "sg:postcode":"4350",
    "sg:province":"QLD",
    "sg:tags":[
        "planning"
    ],
    "wof:name":"White Eagle Financial Planning",
    "wof:placetype":"venue"
},
  "geometry": {"coordinates":[151.954605,-27.561024],"type":"Point"}
}