{
  "type": "Feature",
  "properties": {
    "addr:full":"2 York Rd Port Pirie SA 5540",
    "addr:housenumber":"2",
    "addr:postcode":"5540",
    "addr:street":"York Rd",
    "iso:country":"AU",
    "sg:address":"2 York Rd",
    "sg:city":"Port Pirie",
    "sg:classifiers":[
        {
            "category":"Personal",
            "subcategory":"Beauty Salon",
            "type":"Services"
        }
    ],
    "sg:phone":"+61 8 8632 2681",
    "sg:postcode":"5540",
    "sg:province":"SA",
    "sg:tags":[
        "hairdresser"
    ],
    "wof:name":"Tanya On York",
    "wof:placetype":"venue"
},
  "geometry": {"coordinates":[138.00367736800001,-33.1773834229],"type":"Point"}
}