{
  "type": "Feature",
  "properties": {
    "addr:full":"35 McLachlan St Horsham VIC 3400",
    "addr:housenumber":"35",
    "addr:postcode":"3400",
    "addr:street":"Mclachlan St",
    "iso:country":"AU",
    "sg:address":"35 McLachlan St",
    "sg:city":"Horsham",
    "sg:classifiers":[
        {
            "category":"Banks & Credit Unions",
            "subcategory":"Financial Services",
            "type":"Services"
        }
    ],
    "sg:phone":"+61 3 5381 1655",
    "sg:postcode":"3400",
    "sg:province":"VIC",
    "sg:tags":[
        "planning"
    ],
    "wof:name":"Wimmera Financial Solutions",
    "wof:placetype":"venue"
},
  "geometry": {"coordinates":[142.198196411,-36.7132339478],"type":"Point"}
}