{
  "type": "Feature",
  "properties": {
    "iso:country":"AU",
    "sg:address":"15 Bong Bong St",
    "sg:city":"Dapto",
    "sg:classifiers":[
        {
            "category":"Personal",
            "subcategory":"Nail Salon",
            "type":"Services"
        }
    ],
    "sg:phone":"+61 2 4262 2615",
    "sg:postcode":"2530",
    "sg:province":"NSW",
    "sg:tags":[
        "artificial"
    ],
    "wof:name":"Kylies Style",
    "wof:placetype":"venue"
},
  "geometry": {"coordinates":[150.79226684599999,-34.4938926697],"type":"Point"}
}