{
  "type": "Feature",
  "properties": {
    "iso:country":"AU",
    "sg:address":"405 Ghazeepore Rd",
    "sg:city":"Mt Duneed",
    "sg:classifiers":[
        {
            "category":"Professional",
            "type":"Services"
        }
    ],
    "sg:phone":"+61 3 5264 5217",
    "sg:postcode":"3216",
    "sg:province":"VIC",
    "sg:tags":[
        "buyer",
        "merchant",
        "wool"
    ],
    "wof:name":"Branagh D & G",
    "wof:placetype":"venue"
},
  "geometry": {"coordinates":[144.29710388199999,-38.2388801575],"type":"Point"}
}