{
  "type": "Feature",
  "properties": {
    "addr:full":"Shop 2/ 155 Tongarra Rd Albion Park NSW 2527",
    "addr:housenumber":"shop 2 / 155",
    "addr:postcode":"2527",
    "addr:street":"Tongarra Rd",
    "iso:country":"AU",
    "sg:address":"Shop 2/ 155 Tongarra Rd",
    "sg:city":"Albion Park",
    "sg:classifiers":[
        {
            "category":"Manufacturing",
            "subcategory":"Motor Vehicles & Parts",
            "type":"Manufacturing & Wholesale Goods"
        }
    ],
    "sg:phone":"+61 2 4256 9400",
    "sg:postcode":"2527",
    "sg:province":"NSW",
    "sg:tags":[
        "replacement"
    ],
    "wof:name":"Centenary Auto Parts",
    "wof:placetype":"venue"
},
  "geometry": {"coordinates":[150.77731323200001,-34.5705375671],"type":"Point"}
}