{
  "type": "Feature",
  "properties": {
    "iso:country":"AU",
    "sg:address":"126 Pascoe Vale Rd",
    "sg:city":"Moonee Ponds",
    "sg:classifiers":[
        {
            "category":"Real Estate",
            "subcategory":"Architect",
            "type":"Services"
        }
    ],
    "sg:phone":"+61 3 9370 4421",
    "sg:postcode":"3039",
    "sg:province":"VIC",
    "wof:name":"Honson Jack G",
    "wof:placetype":"venue"
},
  "geometry": {"coordinates":[144.926086,-37.761169],"type":"Point"}
}