{
  "type": "Feature",
  "properties": {
    "addr:full":"4 Buggy Crs McKellar ACT 2617",
    "addr:housenumber":"4",
    "addr:postcode":"2617",
    "addr:street":"Buggy Crs",
    "iso:country":"AU",
    "sg:address":"4 Buggy Crs",
    "sg:city":"McKellar",
    "sg:classifiers":[
        {
            "category":"Personal",
            "type":"Services"
        }
    ],
    "sg:phone":"+61 2 6258 9685",
    "sg:postcode":"2617",
    "sg:province":"ACT",
    "sg:tags":[
        "reducing",
        "treatment",
        "weight"
    ],
    "wof:name":"Herbalife Australasia Pty Ltd",
    "wof:placetype":"venue"
},
  "geometry": {"coordinates":[149.073776245,-35.2174797058],"type":"Point"}
}