{
  "type": "Feature",
  "properties": {
    "iso:country":"AU",
    "sg:address":"56 High St",
    "sg:city":"Broadford",
    "sg:classifiers":[
        {
            "category":"Shopping",
            "type":"Retail Goods"
        }
    ],
    "sg:phone":"+61 3 5784 1123",
    "sg:postcode":"3658",
    "sg:province":"VIC",
    "sg:tags":[
        "produce",
        "grain"
    ],
    "wof:name":"Broadford Produce & Farm Supplies",
    "wof:placetype":"venue"
},
  "geometry": {"coordinates":[145.04527282699999,-37.2051086426],"type":"Point"}
}