{
  "type": "Feature",
  "properties": {
    "addr:full":"Shop 6, 248- 296 Clyde Rd Berwick VIC 3806",
    "addr:housenumber":"shop 6;296",
    "addr:postcode":"248;3806",
    "addr:street":"Clyde Rd",
    "iso:country":"AU",
    "sg:address":"Shop 6, 248- 296 Clyde Rd",
    "sg:city":"Berwick",
    "sg:classifiers":[
        {
            "category":"Communications",
            "subcategory":"Film & Video Production",
            "type":"Services"
        }
    ],
    "sg:phone":"+61 3 9702 2600",
    "sg:postcode":"3806",
    "sg:province":"VIC",
    "sg:tags":[
        "dvd",
        "library"
    ],
    "wof:name":"Civic Video Pty Ltd",
    "wof:placetype":"venue"
},
  "geometry": {"coordinates":[145.338790894,-38.0557365417],"type":"Point"}
}