{
  "type": "Feature",
  "properties": {
    "addr:full":"602 Skipton St Ballarat VIC 3350",
    "addr:housenumber":"602",
    "addr:postcode":"3350",
    "addr:street":"Skipton St",
    "iso:country":"AU",
    "sg:address":"602 Skipton St",
    "sg:city":"Ballarat",
    "sg:classifiers":[
        {
            "category":"Retail",
            "subcategory":"Auto Repair",
            "type":"Services"
        }
    ],
    "sg:phone":"+61 3 5336 1000",
    "sg:postcode":"3350",
    "sg:province":"VIC",
    "sg:tags":[
        "wheel",
        "balancing",
        "alignment"
    ],
    "wof:name":"Tyrepower",
    "wof:placetype":"venue"
},
  "geometry": {"coordinates":[143.85450700000001,-37.567726],"type":"Point"}
}