{
  "type": "Feature",
  "properties": {
    "addr:full":"84 Sunnyholt Rd Blacktown NSW 2148",
    "addr:housenumber":"84",
    "addr:postcode":"2148",
    "addr:street":"Sunnyholt Rd",
    "iso:country":"AU",
    "sg:address":"84 Sunnyholt Rd",
    "sg:city":"Blacktown",
    "sg:classifiers":[
        {
            "category":"Building & Trades",
            "subcategory":"Equipment Rental",
            "type":"Services"
        }
    ],
    "sg:phone":"+61 2 9672 3121",
    "sg:postcode":"2148",
    "sg:province":"NSW",
    "sg:tags":[
        "party",
        "hire"
    ],
    "wof:name":"Alert Party & Event Hire",
    "wof:placetype":"venue"
},
  "geometry": {"coordinates":[150.911575317,-33.7714233398],"type":"Point"}
}