{
  "type": "Feature",
  "properties": {
    "addr:full":"30 Janefield St Mowbray TAS 7248",
    "addr:housenumber":"30",
    "addr:postcode":"7248",
    "addr:street":"Janefield St",
    "iso:country":"AU",
    "sg:address":"30 Janefield St",
    "sg:city":"Mowbray",
    "sg:classifiers":[
        {
            "category":"Social Services",
            "subcategory":"Retirement Home",
            "type":"Services"
        }
    ],
    "sg:phone":"+61 3 6324 5500",
    "sg:postcode":"7248",
    "sg:province":"TAS",
    "sg:tags":[
        "village"
    ],
    "wof:name":"Mowbray Links Lifestyle Village",
    "wof:placetype":"venue"
},
  "geometry": {"coordinates":[147.136352539,-41.4006843567],"type":"Point"}
}