{
  "type": "Feature",
  "properties": {
    "addr:full":"61- 63 Smith St Summer Hill (Sydney) NSW 2130",
    "addr:housenumber":"63",
    "addr:postcode":"2130",
    "addr:street":"Smith St",
    "iso:country":"AU",
    "sg:address":"61- 63 Smith St",
    "sg:city":"Summer Hill (Sydney)",
    "sg:classifiers":[
        {
            "category":"Government",
            "subcategory":"Post Office",
            "type":"Public Place"
        }
    ],
    "sg:phone":"+61 2 9716 6188",
    "sg:postcode":"2130",
    "sg:province":"NSW",
    "sg:tags":[
        "chair",
        "manufacturer"
    ],
    "wof:name":"Kebbel Furniture (Int'l) Pty Ltd",
    "wof:placetype":"venue"
},
  "geometry": {"coordinates":[151.13607788100001,-33.8915023804],"type":"Point"}
}