{
  "type": "Feature",
  "properties": {
    "iso:country":"AU",
    "sg:address":"5 Glenburn Rd",
    "sg:city":"Kinglake",
    "sg:classifiers":[
        {
            "category":"Health Services",
            "subcategory":"Doctor",
            "type":"Services"
        }
    ],
    "sg:phone":"+61 3 5786 1388",
    "sg:postcode":"3763",
    "sg:province":"VIC",
    "sg:tags":[
        "medical",
        "practitioner"
    ],
    "wof:name":"Up There Cazaly Medical Centre",
    "wof:placetype":"venue"
},
  "geometry": {"coordinates":[145.34135437,-37.5301704407],"type":"Point"}
}