{
  "type": "Feature",
  "properties": {
    "iso:country":"AU",
    "sg:address":"11 Landsborough St",
    "sg:city":"Normanton",
    "sg:classifiers":[
        {
            "category":"Travel",
            "subcategory":"Hotels & Motels",
            "type":"Entertainment"
        }
    ],
    "sg:phone":"+61 7 4745 1290",
    "sg:postcode":"4890",
    "sg:province":"QLD",
    "wof:name":"Gulfland Motel & Caravan Park",
    "wof:placetype":"venue"
},
  "geometry": {"coordinates":[141.07864379899999,-17.6703414917],"type":"Point"}
}