{
  "type": "Feature",
  "properties": {
    "iso:country":"AU",
    "sg:address":"428 Huntingdale Rd",
    "sg:city":"Mt Waverley",
    "sg:classifiers":[
        {
            "category":"Real Estate",
            "subcategory":"Real Estate Agent",
            "type":"Services"
        }
    ],
    "sg:phone":"+61 3 9888 2550",
    "sg:postcode":"3149",
    "sg:province":"VIC",
    "wof:name":"Sean Darbyshire Real Estate Pty Ltd",
    "wof:placetype":"venue"
},
  "geometry": {"coordinates":[145.10919189399999,-37.8823013306],"type":"Point"}
}