{
  "type": "Feature",
  "properties": {
    "addr:full":"919 Bairnsdale - Dargo Rd Bairnsdale VIC 3875",
    "addr:housenumber":"919",
    "addr:postcode":"3875",
    "addr:street":"Bairnsdale Dargo Rd",
    "iso:country":"AU",
    "sg:address":"919 Bairnsdale - Dargo Rd",
    "sg:city":"Bairnsdale",
    "sg:classifiers":[
        {
            "category":"Retail",
            "subcategory":"Auto Repair",
            "type":"Services"
        }
    ],
    "sg:phone":"+61 3 5157 1234",
    "sg:postcode":"3875",
    "sg:province":"VIC",
    "sg:tags":[
        "bus",
        "truck"
    ],
    "wof:name":"Hillside Diesel Services",
    "wof:placetype":"venue"
},
  "geometry": {"coordinates":[147.48602294899999,-37.8110618591],"type":"Point"}
}