{
  "type": "Feature",
  "properties": {
    "addr:full":"88 Kelleway Ave Nicholls ACT 2913",
    "addr:housenumber":"88",
    "addr:postcode":"2913",
    "addr:street":"Kelleway Ave",
    "iso:country":"AU",
    "sg:address":"88 Kelleway Ave",
    "sg:city":"Nicholls",
    "sg:classifiers":[
        {
            "category":"Food & Beverages",
            "subcategory":"Liquor & Beverages",
            "type":"Retail Goods"
        }
    ],
    "sg:phone":"+61 2 6241 7122",
    "sg:postcode":"2913",
    "sg:province":"ACT",
    "sg:tags":[
        "store"
    ],
    "wof:name":"Local Liquor",
    "wof:placetype":"venue"
},
  "geometry": {"coordinates":[149.09713745100001,-35.1830253601],"type":"Point"}
}