{
  "type": "Feature",
  "properties": {
    "iso:country":"AU",
    "sg:address":"73 Sewell St",
    "sg:city":"East Fremantle",
    "sg:classifiers":[
        {
            "category":"Health Services",
            "subcategory":"Health Practitioner",
            "type":"Services"
        }
    ],
    "sg:phone":"+61 8 9339 5459",
    "sg:postcode":"6158",
    "sg:province":"WA",
    "sg:tags":[
        "naturopath"
    ],
    "wof:name":"Garde Bronia",
    "wof:placetype":"venue"
},
  "geometry": {"coordinates":[115.761139,-32.04599],"type":"Point"}
}