{
  "type": "Feature",
  "properties": {
    "addr:full":"7 Norton St Wangaratta VIC 3677",
    "addr:housenumber":"7",
    "addr:postcode":"3677",
    "addr:street":"Norton St",
    "iso:country":"AU",
    "sg:address":"7 Norton St",
    "sg:city":"Wangaratta",
    "sg:classifiers":[
        {
            "category":"Banks & Credit Unions",
            "subcategory":"Bank",
            "type":"Services"
        }
    ],
    "sg:phone":"+61 427 217 655",
    "sg:postcode":"3677",
    "sg:province":"VIC",
    "sg:tags":[
        "broker",
        "mortgage"
    ],
    "wof:name":"Choice Home Loans",
    "wof:placetype":"venue"
},
  "geometry": {"coordinates":[146.32307434099999,-36.3548126221],"type":"Point"}
}