{
  "type": "Feature",
  "properties": {
    "iso:country":"AU",
    "sg:address":"34 Wingecarribee St",
    "sg:city":"Bowral",
    "sg:classifiers":[
        {
            "category":"Shopping",
            "subcategory":"Computers & Home Electronics",
            "type":"Retail Goods"
        }
    ],
    "sg:phone":"+61 2 4861 3200",
    "sg:postcode":"2576",
    "sg:province":"NSW",
    "sg:tags":[
        "equipment",
        "part",
        "electronic"
    ],
    "wof:name":"Leading Edge Electronics",
    "wof:placetype":"venue"
},
  "geometry": {"coordinates":[150.41880798299999,-34.4787712097],"type":"Point"}
}