{
  "type": "Feature",
  "properties": {
    "addr:full":"857 Canning Hwy Applecross WA 6153",
    "addr:housenumber":"857",
    "addr:postcode":"6153",
    "addr:street":"Canning Hwy",
    "iso:country":"AU",
    "sg:address":"857 Canning Hwy",
    "sg:city":"Applecross",
    "sg:classifiers":[
        {
            "category":"Health Services",
            "subcategory":"Doctor",
            "type":"Services"
        }
    ],
    "sg:phone":"+61 8 9364 6633",
    "sg:postcode":"6153",
    "sg:province":"WA",
    "sg:tags":[
        "medical",
        "practitioner"
    ],
    "wof:name":"Reynolds Road 7 Day Medical Centre",
    "wof:placetype":"venue"
},
  "geometry": {"coordinates":[115.84301000000001,-32.01585],"type":"Point"}
}