{
  "type": "Feature",
  "properties": {
    "addr:full":"34 Luisini Rd Wangara WA 6065",
    "addr:housenumber":"34",
    "addr:postcode":"6065",
    "addr:street":"Luisini Rd",
    "iso:country":"AU",
    "sg:address":"34 Luisini Rd",
    "sg:city":"Wangara",
    "sg:classifiers":[
        {
            "category":"Building & Trades",
            "subcategory":"Construction",
            "type":"Services"
        }
    ],
    "sg:phone":"+61 8 9409 9022",
    "sg:postcode":"6065",
    "sg:province":"WA",
    "sg:tags":[
        "pool",
        "swimming"
    ],
    "wof:name":"Treacy Fencing",
    "wof:placetype":"venue"
},
  "geometry": {"coordinates":[115.827407837,-31.7972297668],"type":"Point"}
}