{
  "type": "Feature",
  "properties": {
    "addr:full":"199 Muirhead Rd Willaura VIC 3379",
    "addr:housenumber":"199",
    "addr:postcode":"3379",
    "addr:street":"Muirhead Rd",
    "iso:country":"AU",
    "sg:address":"199 Muirhead Rd",
    "sg:city":"Willaura",
    "sg:classifiers":[
        {
            "category":"Industrial Area",
            "type":"Public Place"
        }
    ],
    "sg:phone":"+61 3 5354 1307",
    "sg:postcode":"3379",
    "sg:province":"VIC",
    "sg:tags":[
        "rural",
        "shed"
    ],
    "wof:name":"RC Steel Fabrication",
    "wof:placetype":"venue"
},
  "geometry": {"coordinates":[142.62448120100001,-37.4530487061],"type":"Point"}
}