{
  "type": "Feature",
  "properties": {
    "addr:full":"27 Prince Edward Rd Seaforth NSW 2092",
    "addr:housenumber":"27",
    "addr:postcode":"2092",
    "addr:street":"Prince Edward Rd",
    "iso:country":"AU",
    "sg:address":"27 Prince Edward Rd",
    "sg:city":"Seaforth",
    "sg:classifiers":[
        {
            "category":"Professional",
            "subcategory":"Art Services",
            "type":"Services"
        }
    ],
    "sg:phone":"+61 2 9949 5545",
    "sg:postcode":"2092",
    "sg:province":"NSW",
    "sg:tags":[
        "graphic",
        "designer"
    ],
    "wof:name":"Rick Reynolds Graphic Design",
    "wof:placetype":"venue"
},
  "geometry": {"coordinates":[151.241363525,-33.7852630615],"type":"Point"}
}