{
  "type": "Feature",
  "properties": {
    "addr:full":"1/ 16 Blackburn Sq Berwick VIC 3806",
    "addr:housenumber":"/ 16",
    "addr:postcode":"3806",
    "addr:street":"Blackburn Sq",
    "iso:country":"AU",
    "sg:address":"1/ 16 Blackburn Sq",
    "sg:city":"Berwick",
    "sg:classifiers":[
        {
            "category":"Airline",
            "type":"Transportation"
        }
    ],
    "sg:phone":"+61 1800 237 427",
    "sg:postcode":"3806",
    "sg:province":"VIC",
    "sg:tags":[
        "surveyor",
        "aerial"
    ],
    "wof:name":"Aerial Impressions",
    "wof:placetype":"venue"
},
  "geometry": {"coordinates":[145.34538269000001,-38.0299606323],"type":"Point"}
}