{
  "type": "Feature",
  "properties": {
    "addr:full":"51 Grafton St Cairns QLD 4870",
    "addr:housenumber":"51",
    "addr:postcode":"4870",
    "addr:street":"Grafton St",
    "iso:country":"AU",
    "sg:address":"51 Grafton St",
    "sg:city":"Cairns",
    "sg:classifiers":[
        {
            "category":"Professional",
            "subcategory":"Management & Consulting",
            "type":"Services"
        }
    ],
    "sg:phone":"+61 7 4051 8788",
    "sg:postcode":"4870",
    "sg:province":"QLD",
    "sg:tags":[
        "consultant",
        "migration"
    ],
    "wof:name":"Carol Shipway",
    "wof:placetype":"venue"
},
  "geometry": {"coordinates":[145.77603149399999,-16.9244499207],"type":"Point"}
}