{
  "type": "Feature",
  "properties": {
    "addr:full":"37 Nelsons Rd Uralla NSW 2358",
    "addr:housenumber":"37",
    "addr:postcode":"2358",
    "addr:street":"Nelsons Rd",
    "iso:country":"AU",
    "sg:address":"37 Nelsons Rd",
    "sg:city":"Uralla",
    "sg:classifiers":[
        {
            "category":"Shopping",
            "subcategory":"Clothing, Apparel, & Fashions",
            "type":"Retail Goods"
        }
    ],
    "sg:phone":"+61 2 6778 4504",
    "sg:postcode":"2358",
    "sg:province":"NSW",
    "sg:tags":[
        "uniform"
    ],
    "wof:name":"New England Workwear",
    "wof:placetype":"venue"
},
  "geometry": {"coordinates":[151.51458740199999,-30.6027832031],"type":"Point"}
}