{
  "type": "Feature",
  "properties": {
    "iso:country":"AU",
    "sg:address":"901 Macarthur St",
    "sg:city":"Lake Wendouree",
    "sg:classifiers":[
        {
            "category":"Personal",
            "subcategory":"Beauty Salon",
            "type":"Services"
        }
    ],
    "sg:phone":"+61 3 5331 5844",
    "sg:postcode":"3355",
    "sg:province":"VIC",
    "wof:name":"Touche Skin & Body",
    "wof:placetype":"venue"
},
  "geometry": {"coordinates":[143.84903,-37.55003],"type":"Point"}
}