{
  "type": "Feature",
  "properties": {
    "addr:full":"Lot 2 Brabazon Rd Gleneagle QLD 4285",
    "addr:postcode":"4285",
    "addr:street":"Brabazon Rd",
    "iso:country":"AU",
    "sg:address":"Lot 2 Brabazon Rd",
    "sg:city":"Gleneagle",
    "sg:classifiers":[
        {
            "category":"Home & Garden",
            "subcategory":"Building Materials",
            "type":"Retail Goods"
        }
    ],
    "sg:phone":"+61 7 5543 1577",
    "sg:postcode":"4285",
    "sg:province":"QLD",
    "sg:tags":[
        "lawn",
        "cutting",
        "maintenance"
    ],
    "wof:name":"Cowie MA",
    "wof:placetype":"venue"
},
  "geometry": {"coordinates":[152.951584,-27.943274],"type":"Point"}
}