{
  "type": "Feature",
  "properties": {
    "addr:full":"Princess Ave Albany WA 6330",
    "addr:postcode":"6330",
    "addr:street":"Princess Ave",
    "iso:country":"AU",
    "sg:address":"Princess Ave",
    "sg:city":"Albany",
    "sg:classifiers":[
        {
            "category":"Farming",
            "subcategory":"Farm",
            "type":"Manufacturing & Wholesale Goods"
        }
    ],
    "sg:phone":"+61 8 9841 8814",
    "sg:postcode":"6330",
    "sg:province":"WA",
    "sg:tags":[
        "farmer"
    ],
    "wof:name":"Attwell Ray",
    "wof:placetype":"venue"
},
  "geometry": {"coordinates":[117.844711304,-35.0489883423],"type":"Point"}
}