{
  "type": "Feature",
  "properties": {
    "iso:country":"AU",
    "sg:address":"23 Action Rd",
    "sg:city":"Malaga",
    "sg:classifiers":[
        {
            "category":"Professional",
            "subcategory":"Detective & Security Services",
            "type":"Services"
        }
    ],
    "sg:phone":"+61 8 9248 6633",
    "sg:postcode":"6090",
    "sg:province":"WA",
    "sg:tags":[
        "consultant",
        "system"
    ],
    "sg:website":"http://www.protection1.com.au",
    "wof:name":"Protection 1 Pty Ltd",
    "wof:placetype":"venue"
},
  "geometry": {"coordinates":[115.88227081300001,-31.8463745117],"type":"Point"}
}