{
  "type": "Feature",
  "properties": {
    "addr:full":"1071 Dandenong Rd Malvern East VIC 3145",
    "addr:housenumber":"1071",
    "addr:postcode":"3145",
    "addr:street":"Dandenong Rd",
    "iso:country":"AU",
    "sg:address":"1071 Dandenong Rd",
    "sg:city":"Malvern East",
    "sg:classifiers":[
        {
            "category":"Professional",
            "subcategory":"Art Services",
            "type":"Services"
        }
    ],
    "sg:phone":"+61 418 325 902",
    "sg:postcode":"3145",
    "sg:province":"VIC",
    "sg:tags":[
        "decorator",
        "painter"
    ],
    "wof:name":"Parklane Painting",
    "wof:placetype":"venue"
},
  "geometry": {"coordinates":[145.05586242699999,-37.8832817078],"type":"Point"}
}