{
  "type": "Feature",
  "properties": {
    "addr:full":"55 Canton Beach Rd Toukley NSW 2263",
    "addr:housenumber":"55",
    "addr:postcode":"2263",
    "addr:street":"Canton Beach Rd",
    "iso:country":"AU",
    "sg:address":"55 Canton Beach Rd",
    "sg:city":"Toukley",
    "sg:classifiers":[
        {
            "category":"Personal",
            "subcategory":"Beauty Salon",
            "type":"Services"
        }
    ],
    "sg:phone":"+61 2 4397 2255",
    "sg:postcode":"2263",
    "sg:province":"NSW",
    "sg:tags":[
        "hairdresser"
    ],
    "wof:name":"Static Hair Studio",
    "wof:placetype":"venue"
},
  "geometry": {"coordinates":[151.54072600000001,-33.264473],"type":"Point"}
}