{
  "type": "Feature",
  "properties": {
    "addr:full":"Showroom 26, 85 - 91 Keilor Park Dve Tullamarine VIC 3043",
    "addr:housenumber":"85 91",
    "addr:postcode":"3043",
    "addr:street":"Keilor Park Dve",
    "iso:country":"AU",
    "sg:address":"Showroom 26, 85 - 91 Keilor Park Dve",
    "sg:city":"Tullamarine",
    "sg:classifiers":[
        {
            "category":"Retail",
            "subcategory":"Auto Rental",
            "type":"Services"
        }
    ],
    "sg:phone":"+61 3 9310 4533",
    "sg:postcode":"3043",
    "sg:province":"VIC",
    "sg:tags":[
        "chauffeur",
        "car",
        "hire",
        "driven",
        "limousine"
    ],
    "wof:name":"wwwWeddingCars",
    "wof:placetype":"venue"
},
  "geometry": {"coordinates":[144.85911560100001,-37.7127304077],"type":"Point"}
}