{
  "type": "Feature",
  "properties": {
    "addr:full":"Cnr Victoria & Archer Sts Chatswood NSW 2067",
    "addr:postcode":"2067",
    "addr:street":"Cnr",
    "iso:country":"AU",
    "sg:address":"Cnr Victoria & Archer Sts",
    "sg:city":"Chatswood",
    "sg:classifiers":[
        {
            "category":"Food & Beverages",
            "subcategory":"Supermarket",
            "type":"Retail Goods"
        }
    ],
    "sg:phone":"+61 2 9419 6302",
    "sg:postcode":"2067",
    "sg:province":"NSW",
    "sg:tags":[
        "grocery",
        "store"
    ],
    "wof:name":"Kmart Australia",
    "wof:placetype":"venue"
},
  "geometry": {"coordinates":[151.183868408,-33.796081543],"type":"Point"}
}