{
  "type": "Feature",
  "properties": {
    "addr:full":"Shop 3 -4 Mt Eliza Shopping Centre Mt Eliza VIC 3930",
    "addr:housenumber":"shop;-4",
    "addr:postcode":"3930",
    "addr:street":"Mt",
    "iso:country":"AU",
    "sg:address":"Shop 3",
    "sg:city":"-4 Mt Eliza Shopping Centre Mt Eliza",
    "sg:classifiers":[
        {
            "category":"Health Services",
            "subcategory":"Doctor",
            "type":"Services"
        }
    ],
    "sg:phone":"+61 3 9708 8611",
    "sg:postcode":"3930",
    "sg:province":"VIC",
    "sg:tags":[
        "medical",
        "practitioner"
    ],
    "wof:name":"The Strand Medical & Specialist Suites",
    "wof:placetype":"venue"
},
  "geometry": {"coordinates":[145.09501648,-38.1936798096],"type":"Point"}
}