{
  "type": "Feature",
  "properties": {
    "addr:full":"14 Old Gympie Rd Kallangur QLD 4503",
    "addr:housenumber":"14",
    "addr:postcode":"4503",
    "addr:street":"Old Gympie Rd",
    "iso:country":"AU",
    "sg:address":"14 Old Gympie Rd",
    "sg:city":"Kallangur",
    "sg:classifiers":[
        {
            "category":"Health Services",
            "subcategory":"Doctor",
            "type":"Services"
        }
    ],
    "sg:phone":"+61 7 3886 1683",
    "sg:postcode":"4503",
    "sg:province":"QLD",
    "sg:tags":[
        "occupational",
        "safety"
    ],
    "wof:name":"B & Y Safety Systems",
    "wof:placetype":"venue"
},
  "geometry": {"coordinates":[152.99147033700001,-27.2481040955],"type":"Point"}
}