{
  "type": "Feature",
  "properties": {
    "addr:full":"PO Box 777 Manunda QLD 4870",
    "addr:postcode":"4870",
    "iso:country":"AU",
    "sg:address":"PO Box 777",
    "sg:city":"Manunda",
    "sg:classifiers":[
        {
            "category":"Building & Trades",
            "subcategory":"Construction",
            "type":"Services"
        }
    ],
    "sg:phone":"+61 7 4053 1988",
    "sg:postcode":"4870",
    "sg:province":"QLD",
    "sg:tags":[
        "earth",
        "excavating",
        "moving",
        "contractor"
    ],
    "wof:name":"Diggers Mini Excavator Hire Pty Ltd",
    "wof:placetype":"venue"
},
  "geometry": {"coordinates":[145.74989318900001,-16.9132595062],"type":"Point"}
}