{
  "type": "Feature",
  "properties": {
    "addr:full":"U25/ 20 Commercial Rd Melbourne VIC 3000",
    "addr:housenumber":"20",
    "addr:postcode":"3000",
    "addr:street":"/;Commercial Rd",
    "iso:country":"AU",
    "sg:address":"U25/ 20 Commercial Rd",
    "sg:city":"Melbourne",
    "sg:classifiers":[
        {
            "category":"Real Estate",
            "subcategory":"Developer",
            "type":"Services"
        }
    ],
    "sg:phone":"+61 3 9867 2451",
    "sg:postcode":"3000",
    "sg:province":"VIC",
    "sg:tags":[
        "development"
    ],
    "wof:name":"Boom Properties Pty Ltd",
    "wof:placetype":"venue"
},
  "geometry": {"coordinates":[144.97915649399999,-37.8447799683],"type":"Point"}
}