{
  "type": "Feature",
  "properties": {
    "addr:full":"Unit 7, 84 Bells Line Of Rd North Richmond NSW 2754",
    "addr:housenumber":"84",
    "addr:postcode":"2754",
    "addr:street":"Bells Line Of Rd",
    "iso:country":"AU",
    "sg:address":"Unit 7, 84 Bells Line Of Rd",
    "sg:city":"North Richmond",
    "sg:classifiers":[
        {
            "category":"Home & Garden",
            "subcategory":"Hardware",
            "type":"Retail Goods"
        }
    ],
    "sg:phone":"+61 2 4571 3800",
    "sg:postcode":"2754",
    "sg:province":"NSW",
    "sg:tags":[
        "repair",
        "tool",
        "power"
    ],
    "wof:name":"Hire Force",
    "wof:placetype":"venue"
},
  "geometry": {"coordinates":[150.71777343799999,-33.5778236389],"type":"Point"}
}