{
  "type": "Feature",
  "properties": {
    "addr:full":"Level 1, 38 Swan St Wollongong NSW 2500",
    "addr:housenumber":"38",
    "addr:postcode":"2500",
    "addr:street":"Swan St",
    "iso:country":"AU",
    "sg:address":"Level 1, 38 Swan St",
    "sg:city":"Wollongong",
    "sg:classifiers":[
        {
            "category":"Professional",
            "subcategory":"Employment Agencies",
            "type":"Services"
        }
    ],
    "sg:phone":"+61 2 4227 2017",
    "sg:postcode":"2500",
    "sg:province":"NSW",
    "wof:name":"Ready Workforce",
    "wof:placetype":"venue"
},
  "geometry": {"coordinates":[150.89372299999999,-34.435394],"type":"Point"}
}