{
  "type": "Feature",
  "properties": {
    "addr:full":"2b William St Singleton NSW 2330",
    "addr:housenumber":"2b",
    "addr:postcode":"2330",
    "addr:street":"William St",
    "iso:country":"AU",
    "sg:address":"2b William St",
    "sg:city":"Singleton",
    "sg:classifiers":[
        {
            "category":"Fast Food",
            "type":"Food & Drink"
        }
    ],
    "sg:phone":"+61 2 6571 3555",
    "sg:postcode":"2330",
    "sg:province":"NSW",
    "sg:tags":[
        "away",
        "take"
    ],
    "wof:name":"Domino's Pizza",
    "wof:placetype":"venue"
},
  "geometry": {"coordinates":[151.16902200000001,-32.564259],"type":"Point"}
}