{
  "type": "Feature",
  "properties": {
    "iso:country":"AU",
    "sg:address":"15 Fairview Rd",
    "sg:city":"Mt Waverley",
    "sg:classifiers":[
        {
            "category":"Utilities",
            "subcategory":"Electric",
            "type":"Services"
        }
    ],
    "sg:phone":"+61 418 360 464",
    "sg:postcode":"3149",
    "sg:province":"VIC",
    "sg:tags":[
        "electrical",
        "contractor"
    ],
    "wof:name":"Georges Electrics",
    "wof:placetype":"venue"
},
  "geometry": {"coordinates":[145.11416625999999,-37.8662872314],"type":"Point"}
}