{
  "type": "Feature",
  "properties": {
    "iso:country":"AU",
    "sg:address":"8 Lawson St",
    "sg:city":"Tolga",
    "sg:classifiers":[
        {
            "category":"Professional",
            "subcategory":"Business Services",
            "type":"Services"
        }
    ],
    "sg:phone":"+61 7 4095 4205",
    "sg:postcode":"4882",
    "sg:province":"QLD",
    "sg:tags":[
        "livestock",
        "transport"
    ],
    "wof:name":"Maitland Phillip",
    "wof:placetype":"venue"
},
  "geometry": {"coordinates":[145.47999572800001,-17.220413208],"type":"Point"}
}