{
  "type": "Feature",
  "properties": {
    "iso:country":"AU",
    "sg:address":"106 Percival Rd",
    "sg:city":"Stanmore",
    "sg:classifiers":[
        {
            "category":"Banks & Credit Unions",
            "subcategory":"Investment Brokerage",
            "type":"Services"
        }
    ],
    "sg:phone":"+61 2 9560 4311",
    "sg:postcode":"2048",
    "sg:province":"NSW",
    "sg:tags":[
        "management",
        "property"
    ],
    "wof:name":"Elders Annandale/Stanmore",
    "wof:placetype":"venue"
},
  "geometry": {"coordinates":[151.164108,-33.893604],"type":"Point"}
}