{
  "type": "Feature",
  "properties": {
    "addr:full":"Suite 2, 146 Pennant St North Parramatta NSW 2151",
    "addr:housenumber":"146",
    "addr:postcode":"2151",
    "addr:street":"Pennant St",
    "iso:country":"AU",
    "sg:address":"Suite 2, 146 Pennant St",
    "sg:city":"North Parramatta",
    "sg:classifiers":[
        {
            "category":"Professional",
            "subcategory":"Accounting & Tax Preparation",
            "type":"Services"
        }
    ],
    "sg:phone":"+61 2 9890 9494",
    "sg:postcode":"2151",
    "sg:province":"NSW",
    "sg:tags":[
        "accountant",
        "auditor"
    ],
    "wof:name":"All States Taxation Services",
    "wof:placetype":"venue"
},
  "geometry": {"coordinates":[151.021759033,-33.8057975769],"type":"Point"}
}