{
  "type": "Feature",
  "properties": {
    "addr:full":"685 New Dookie Rd Shepparton VIC 3630",
    "addr:housenumber":"685",
    "addr:postcode":"3630",
    "addr:street":"New Dookie Rd",
    "iso:country":"AU",
    "sg:address":"685 New Dookie Rd",
    "sg:city":"Shepparton",
    "sg:classifiers":[
        {
            "category":"Education",
            "subcategory":"School",
            "type":"Public Place"
        }
    ],
    "sg:phone":"+61 3 5829 9852",
    "sg:postcode":"3630",
    "sg:province":"VIC",
    "wof:name":"Isik College Shepparton Campus",
    "wof:placetype":"venue"
},
  "geometry": {"coordinates":[145.490890503,-36.3645896912],"type":"Point"}
}