{
  "type": "Feature",
  "properties": {
    "addr:full":"152 Mascoma St Strathmore VIC 3041",
    "addr:housenumber":"152",
    "addr:postcode":"3041",
    "addr:street":"Mascoma St",
    "iso:country":"AU",
    "sg:address":"152 Mascoma St",
    "sg:city":"Strathmore",
    "sg:classifiers":[
        {
            "category":"Personal",
            "subcategory":"Beauty Salon",
            "type":"Services"
        }
    ],
    "sg:phone":"+61 3 9338 8803",
    "sg:postcode":"3041",
    "sg:province":"VIC",
    "sg:tags":[
        "hairdresser"
    ],
    "wof:name":"Split Ends Hair Design",
    "wof:placetype":"venue"
},
  "geometry": {"coordinates":[144.907714844,-37.7192192078],"type":"Point"}
}