{
  "type": "Feature",
  "properties": {
    "iso:country":"AU",
    "sg:address":"21 Pritchard St",
    "sg:city":"Swan Hill",
    "sg:classifiers":[
        {
            "category":"Personal",
            "subcategory":"Massage",
            "type":"Services"
        }
    ],
    "sg:phone":"+61 3 5034 6222",
    "sg:postcode":"3585",
    "sg:province":"NSW",
    "sg:tags":[
        "therapy"
    ],
    "wof:name":"Taylor Uebergang",
    "wof:placetype":"venue"
},
  "geometry": {"coordinates":[143.551315,-35.337563],"type":"Point"}
}