{
  "type": "Feature",
  "properties": {
    "addr:full":"334 Boundary Rd Laverton North VIC 3026",
    "addr:housenumber":"334",
    "addr:postcode":"3026",
    "addr:street":"Boundary Rd",
    "iso:country":"AU",
    "sg:address":"334 Boundary Rd",
    "sg:city":"Laverton North",
    "sg:classifiers":[
        {
            "category":"Professional",
            "subcategory":"Detective & Security Services",
            "type":"Services"
        }
    ],
    "sg:phone":"+61 3 9369 7699",
    "sg:postcode":"3026",
    "sg:province":"VIC",
    "sg:tags":[
        "consultant",
        "laser"
    ],
    "wof:name":"Dowding & Mills",
    "wof:placetype":"venue"
},
  "geometry": {"coordinates":[144.777985,-37.812634],"type":"Point"}
}