{
  "type": "Feature",
  "properties": {
    "iso:country":"AU",
    "sg:address":"Cavendish St",
    "sg:city":"Mittagong",
    "sg:classifiers":[
        {
            "category":"Home & Garden",
            "subcategory":"Building Materials",
            "type":"Retail Goods"
        }
    ],
    "sg:phone":"+61 2 4871 1700",
    "sg:postcode":"2575",
    "sg:province":"NSW",
    "sg:tags":[
        "fencing"
    ],
    "wof:name":"Home Mittagong Timber & Trade Centre",
    "wof:placetype":"venue"
},
  "geometry": {"coordinates":[150.433868408,-34.4485092163],"type":"Point"}
}