{
  "type": "Feature",
  "properties": {
    "iso:country":"AU",
    "sg:address":"Lambton Rd",
    "sg:city":"Broadmeadow",
    "sg:classifiers":[
        {
            "category":"Sports & Exercise",
            "subcategory":"Sports Center",
            "type":"Entertainment"
        }
    ],
    "sg:phone":"+61 2 4962 2531",
    "sg:postcode":"2292",
    "sg:province":"NSW",
    "sg:tags":[
        "coach",
        "tennis"
    ],
    "wof:name":"District Park Tennis Courts",
    "wof:placetype":"venue"
},
  "geometry": {"coordinates":[151.73300170900001,-32.9236335754],"type":"Point"}
}