{
  "type": "Feature",
  "properties": {
    "addr:full":"45 Graham Crt Hoppers Crossing VIC 3029",
    "addr:housenumber":"45",
    "addr:postcode":"3029",
    "addr:street":"Graham Crt",
    "iso:country":"AU",
    "sg:address":"45 Graham Crt",
    "sg:city":"Hoppers Crossing",
    "sg:classifiers":[
        {
            "category":"Home & Garden",
            "subcategory":"Furniture",
            "type":"Retail Goods"
        }
    ],
    "sg:phone":"+61 3 9267 2900",
    "sg:postcode":"3029",
    "sg:province":"VIC",
    "sg:tags":[
        "business"
    ],
    "wof:name":"Contour Commercial Interiors",
    "wof:placetype":"venue"
},
  "geometry": {"coordinates":[144.72929400000001,-37.873234],"type":"Point"}
}