{
  "type": "Feature",
  "properties": {
    "addr:full":"Unit 2/ 19 Hughes St Batemans Bay NSW 2536",
    "addr:housenumber":"19",
    "addr:postcode":"2536",
    "addr:street":"Hughes St",
    "iso:country":"AU",
    "sg:address":"Unit 2/ 19 Hughes St",
    "sg:city":"Batemans Bay",
    "sg:classifiers":[
        {
            "category":"Government",
            "subcategory":"Fire Station",
            "type":"Public Place"
        }
    ],
    "sg:phone":"+61 2 4472 7788",
    "sg:postcode":"2536",
    "sg:province":"NSW",
    "sg:tags":[
        "equipment",
        "protection",
        "consultant"
    ],
    "wof:name":"Fire & Life Safety Pty Ltd",
    "wof:placetype":"venue"
},
  "geometry": {"coordinates":[150.178192139,-35.720085144],"type":"Point"}
}