{
  "type": "Feature",
  "properties": {
    "iso:country":"AU",
    "sg:address":"10 Kingsford St",
    "sg:city":"Fairy Meadow",
    "sg:classifiers":[
        {
            "category":"Banks & Credit Unions",
            "subcategory":"Bureau De Change",
            "type":"Services"
        }
    ],
    "sg:phone":"+61 2 4284 5414",
    "sg:postcode":"2519",
    "sg:province":"NSW",
    "sg:tags":[
        "control",
        "equipment",
        "compressed",
        "air"
    ],
    "wof:name":"Hitemp Pneumatics",
    "wof:placetype":"venue"
},
  "geometry": {"coordinates":[150.89724699999999,-34.389118],"type":"Point"}
}