{
  "type": "Feature",
  "properties": {
    "addr:full":"2 Ingot Rd Diggers Rest VIC 3427",
    "addr:housenumber":"2",
    "addr:postcode":"3427",
    "addr:street":"Ingot Rd",
    "iso:country":"AU",
    "sg:address":"2 Ingot Rd",
    "sg:city":"Diggers Rest",
    "sg:classifiers":[
        {
            "category":"Utilities",
            "subcategory":"Electric",
            "type":"Services"
        }
    ],
    "sg:phone":"+61 417 560 672",
    "sg:postcode":"3427",
    "sg:province":"VIC",
    "sg:tags":[
        "electrical",
        "contractor"
    ],
    "wof:name":"Thorne Electrical Pty Ltd",
    "wof:placetype":"venue"
},
  "geometry": {"coordinates":[144.71185302699999,-37.6193161011],"type":"Point"}
}