{
  "type": "Feature",
  "properties": {
    "addr:full":"924 Woodville Rd Villawood NSW 2163",
    "addr:housenumber":"924",
    "addr:postcode":"2163",
    "addr:street":"Woodville Rd",
    "iso:country":"AU",
    "sg:address":"924 Woodville Rd",
    "sg:city":"Villawood",
    "sg:classifiers":[
        {
            "category":"Travel",
            "subcategory":"Hotels & Motels",
            "type":"Entertainment"
        }
    ],
    "sg:phone":"+61 2 9724 4231",
    "sg:postcode":"2163",
    "sg:province":"NSW",
    "sg:tags":[
        "accommodation"
    ],
    "wof:name":"Villawood Hotel",
    "wof:placetype":"venue"
},
  "geometry": {"coordinates":[150.97486877399999,-33.8861122131],"type":"Point"}
}