{
  "type": "Feature",
  "properties": {
    "iso:country":"AU",
    "sg:address":"9 Murrell St",
    "sg:city":"Wangaratta",
    "sg:classifiers":[
        {
            "category":"Communications",
            "subcategory":"Television Station",
            "type":"Services"
        }
    ],
    "sg:phone":"+61 3 5722 3955",
    "sg:postcode":"3678",
    "sg:province":"VIC",
    "sg:tags":[
        "mfrs",
        "tank",
        "installation",
        "septic"
    ],
    "wof:name":"Precast Concrete Wangaratta",
    "wof:placetype":"venue"
},
  "geometry": {"coordinates":[146.295578003,-36.3709983826],"type":"Point"}
}