{
  "type": "Feature",
  "properties": {
    "addr:full":"13 Sayer St Midland WA 6056",
    "addr:housenumber":"13",
    "addr:postcode":"6056",
    "addr:street":"Sayer St",
    "iso:country":"AU",
    "sg:address":"13 Sayer St",
    "sg:city":"Midland",
    "sg:classifiers":[
        {
            "category":"Health Services",
            "subcategory":"Medical Lab",
            "type":"Services"
        }
    ],
    "sg:phone":"+61 8 9250 1715",
    "sg:postcode":"6056",
    "sg:province":"WA",
    "sg:tags":[
        "laboratory",
        "dental"
    ],
    "wof:name":"Chroma Ceramics",
    "wof:placetype":"venue"
},
  "geometry": {"coordinates":[116.01007842999999,-31.8918075562],"type":"Point"}
}