{
  "type": "Feature",
  "properties": {
    "addr:full":"18 Old Mill Road Bannockburn QLD 4207",
    "addr:housenumber":"18",
    "addr:postcode":"4207",
    "addr:street":"Old Mill Road",
    "iso:country":"AU",
    "sg:address":"18 Old Mill Road",
    "sg:city":"Bannockburn",
    "sg:classifiers":[
        {
            "category":"Manufacturing",
            "subcategory":"Tools & Machinery",
            "type":"Manufacturing & Wholesale Goods"
        }
    ],
    "sg:phone":"+61 7 5546 5062",
    "sg:postcode":"4207",
    "sg:province":"QLD",
    "sg:tags":[
        "earth",
        "excavating",
        "moving",
        "equipment"
    ],
    "wof:name":"ALR Earthmoving Repairs",
    "wof:placetype":"venue"
},
  "geometry": {"coordinates":[153.19297790499999,-27.7630825043],"type":"Point"}
}