{
  "type": "Feature",
  "properties": {
    "iso:country":"AU",
    "sg:address":"169 Glenayr Ave",
    "sg:city":"Bondi Beach",
    "sg:classifiers":[
        {
            "category":"Health Services",
            "subcategory":"Health Practitioner",
            "type":"Services"
        }
    ],
    "sg:phone":"+61 2 9300 0343",
    "sg:postcode":"2026",
    "sg:province":"NSW",
    "sg:tags":[
        "physiotherapist"
    ],
    "sg:website":"http://www.physiotherapy.asn.au",
    "wof:name":"Michael Schnabl Physiotherapy",
    "wof:placetype":"venue"
},
  "geometry": {"coordinates":[151.270874023,-33.8882904053],"type":"Point"}
}