{
  "type": "Feature",
  "properties": {
    "addr:full":"95 Carrington St Revesby NSW 2212",
    "addr:housenumber":"95",
    "addr:postcode":"2212",
    "addr:street":"Carrington St",
    "iso:country":"AU",
    "sg:address":"95 Carrington St",
    "sg:city":"Revesby",
    "sg:classifiers":[
        {
            "category":"Manufacturing",
            "subcategory":"Tools & Machinery",
            "type":"Manufacturing & Wholesale Goods"
        }
    ],
    "sg:phone":"+61 2 9772 2000",
    "sg:postcode":"2212",
    "sg:province":"NSW",
    "sg:tags":[
        "toolmaker"
    ],
    "sg:website":"http://www.stamco-tool.com",
    "wof:name":"Metco Press Metal Products Pty Ltd",
    "wof:placetype":"venue"
},
  "geometry": {"coordinates":[151.00747699999999,-33.940189],"type":"Point"}
}