{
  "type": "Feature",
  "properties": {
    "iso:country":"AU",
    "sg:address":"95 Carrington St",
    "sg:city":"Revesby",
    "sg:classifiers":[
        {
            "category":"Manufacturing",
            "subcategory":"Tools & Machinery",
            "type":"Manufacturing & Wholesale Goods"
        }
    ],
    "sg:phone":"+61 2 9772 2000",
    "sg:postcode":"2212",
    "sg:province":"NSW",
    "sg:tags":[
        "toolmaker"
    ],
    "sg:website":"http://www.stamco-tool.com",
    "wof:name":"Metco Press Metal Products Pty Ltd",
    "wof:placetype":"venue"
},
  "geometry": {"coordinates":[151.007477,-33.940189],"type":"Point"}
}