{
  "type": "Feature",
  "properties": {
    "addr:full":"52 Borella Road (Cnr Drome St) Albury NSW 2640",
    "addr:housenumber":"52",
    "addr:postcode":"2640",
    "addr:street":"Borella Road Cnr Drome St",
    "iso:country":"AU",
    "sg:address":"52 Borella Road",
    "sg:city":"(Cnr Drome St) Albury",
    "sg:classifiers":[
        {
            "category":"Retail",
            "subcategory":"Auto Rental",
            "type":"Services"
        }
    ],
    "sg:phone":"+61 2 6021 6463",
    "sg:postcode":"2640",
    "sg:province":"NSW",
    "sg:tags":[
        "car",
        "hire",
        "minibus"
    ],
    "wof:name":"Europcar",
    "wof:placetype":"venue"
},
  "geometry": {"coordinates":[146.92874145499999,-36.0765075684],"type":"Point"}
}