{
  "type": "Feature",
  "properties": {
    "addr:full":"Suite 2a, 23- 25 Bay St Double Bay NSW 1360",
    "addr:housenumber":"25",
    "addr:postcode":"1360",
    "addr:street":"Bay St",
    "iso:country":"AU",
    "sg:address":"Suite 2a, 23- 25 Bay St",
    "sg:city":"Double Bay",
    "sg:classifiers":[
        {
            "category":"Real Estate",
            "subcategory":"Real Estate Agent",
            "type":"Services"
        }
    ],
    "sg:phone":"+61 2 9362 3111",
    "sg:postcode":"1360",
    "sg:province":"NSW",
    "wof:name":"Coventry Hall First National",
    "wof:placetype":"venue"
},
  "geometry": {"coordinates":[151.241622925,-33.8778419495],"type":"Point"}
}