{
  "type": "Feature",
  "properties": {
    "addr:full":"24 Woonah St Chadstone VIC 3148",
    "addr:housenumber":"24",
    "addr:postcode":"3148",
    "addr:street":"Woonah St",
    "iso:country":"AU",
    "sg:address":"24 Woonah St",
    "sg:city":"Chadstone",
    "sg:classifiers":[
        {
            "category":"Professional",
            "subcategory":"Detective & Security Services",
            "type":"Services"
        }
    ],
    "sg:phone":"+61 3 9888 2555",
    "sg:postcode":"3148",
    "sg:province":"VIC",
    "sg:tags":[
        "investigator"
    ],
    "wof:name":"Camtech Video Surveillance",
    "wof:placetype":"venue"
},
  "geometry": {"coordinates":[145.098266602,-37.8744277954],"type":"Point"}
}