{
  "type": "Feature",
  "properties": {
    "addr:full":"247 Vincent St Cessnock NSW 2325",
    "addr:housenumber":"247",
    "addr:postcode":"2325",
    "addr:street":"Vincent St",
    "iso:country":"AU",
    "sg:address":"247 Vincent St",
    "sg:city":"Cessnock",
    "sg:classifiers":[
        {
            "category":"Retail",
            "subcategory":"Repair Shop",
            "type":"Services"
        }
    ],
    "sg:phone":"+61 2 4990 2926",
    "sg:postcode":"2325",
    "sg:province":"NSW",
    "sg:tags":[
        "windscreen"
    ],
    "wof:name":"T & L Automotive Repairs",
    "wof:placetype":"venue"
},
  "geometry": {"coordinates":[151.35487365700001,-32.841506958],"type":"Point"}
}