{
  "type": "Feature",
  "properties": {
    "iso:country":"AU",
    "sg:address":"515 High St",
    "sg:city":"Northcote",
    "sg:classifiers":[
        {
            "category":"Professional",
            "subcategory":"Accounting & Tax Preparation",
            "type":"Services"
        }
    ],
    "sg:phone":"+61 3 9489 4746",
    "sg:postcode":"3070",
    "sg:province":"VIC",
    "sg:tags":[
        "accountant",
        "auditor"
    ],
    "wof:name":"Chris Accountancy",
    "wof:placetype":"venue"
},
  "geometry": {"coordinates":[144.999374,-37.764877],"type":"Point"}
}