{
  "type": "Feature",
  "properties": {
    "addr:full":"382 Great Western Hwy St Marys NSW 2760",
    "addr:housenumber":"382",
    "addr:postcode":"2760",
    "addr:street":"Great Western Hwy",
    "iso:country":"AU",
    "sg:address":"382 Great Western Hwy",
    "sg:city":"St Marys",
    "sg:classifiers":[
        {
            "category":"Retail",
            "subcategory":"Repair Shop",
            "type":"Services"
        }
    ],
    "sg:phone":"+61 2 9833 9688",
    "sg:postcode":"2760",
    "sg:province":"NSW",
    "sg:tags":[
        "handbag"
    ],
    "wof:name":"Direct Shoe Warehouse",
    "wof:placetype":"venue"
},
  "geometry": {"coordinates":[150.770874023,-33.769405365],"type":"Point"}
}