{
  "type": "Feature",
  "properties": {
    "addr:full":"2 Rosny Hill Rd Bellerive TAS 7018",
    "addr:housenumber":"2",
    "addr:postcode":"7018",
    "addr:street":"Rosny Hill Rd",
    "iso:country":"AU",
    "sg:address":"2 Rosny Hill Rd",
    "sg:city":"Bellerive",
    "sg:classifiers":[
        {
            "category":"Building & Trades",
            "subcategory":"Equipment Rental",
            "type":"Services"
        }
    ],
    "sg:phone":"+61 3 6245 0241",
    "sg:postcode":"7018",
    "sg:province":"TAS",
    "sg:tags":[
        "renting",
        "trailer"
    ],
    "wof:name":"Trailer Hire",
    "wof:placetype":"venue"
},
  "geometry": {"coordinates":[147.370925903,-42.8688278198],"type":"Point"}
}