{
  "type": "Feature",
  "properties": {
    "iso:country":"AU",
    "sg:address":"PO Box 214",
    "sg:city":"Drayton North",
    "sg:classifiers":[
        {
            "category":"Sports & Exercise",
            "subcategory":"Sports Center",
            "type":"Entertainment"
        }
    ],
    "sg:phone":"+61 7 4635 9999",
    "sg:postcode":"4350",
    "sg:province":"QLD",
    "sg:tags":[
        "ground"
    ],
    "wof:name":"Toowoomba Indoor Sporting Arenas",
    "wof:placetype":"venue"
},
  "geometry": {"coordinates":[151.924622,-27.580484],"type":"Point"}
}