{
  "type": "Feature",
  "properties": {
    "addr:full":"4 Riversdale Rd Yarra Junction VIC 3797",
    "addr:housenumber":"4",
    "addr:postcode":"3797",
    "addr:street":"Riversdale Rd",
    "iso:country":"AU",
    "sg:address":"4 Riversdale Rd",
    "sg:city":"Yarra Junction",
    "sg:classifiers":[
        {
            "category":"Manufacturing",
            "subcategory":"Lumber",
            "type":"Manufacturing & Wholesale Goods"
        }
    ],
    "sg:phone":"+61 3 5967 1052",
    "sg:postcode":"3797",
    "sg:province":"VIC",
    "sg:tags":[
        "sawmillers"
    ],
    "wof:name":"Lakes Hardwood & Sawmilling Pty Ltd",
    "wof:placetype":"venue"
},
  "geometry": {"coordinates":[145.62599182100001,-37.7842521667],"type":"Point"}
}