{
  "type": "Feature",
  "properties": {
    "addr:full":"526 Brighton Rd Brighton SA 5048",
    "addr:housenumber":"526",
    "addr:postcode":"5048",
    "addr:street":"Brighton Rd",
    "iso:country":"AU",
    "sg:address":"526 Brighton Rd",
    "sg:city":"Brighton",
    "sg:classifiers":[
        {
            "category":"Health Services",
            "subcategory":"Doctor",
            "type":"Services"
        }
    ],
    "sg:phone":"+61 8 8298 4166",
    "sg:postcode":"5048",
    "sg:province":"SA",
    "sg:tags":[
        "podiatrist"
    ],
    "wof:name":"Deen Astrid",
    "wof:placetype":"venue"
},
  "geometry": {"coordinates":[138.52362099999999,-35.022724],"type":"Point"}
}