{
  "type": "Feature",
  "properties": {
    "addr:full":"1851 Albany Hwy Maddington WA 6109",
    "addr:housenumber":"1851",
    "addr:postcode":"6109",
    "addr:street":"Albany Hwy",
    "iso:country":"AU",
    "sg:address":"1851 Albany Hwy",
    "sg:city":"Maddington",
    "sg:classifiers":[
        {
            "category":"Retail",
            "subcategory":"Auto Repair",
            "type":"Services"
        }
    ],
    "sg:phone":"+61 8 9459 6388",
    "sg:postcode":"6109",
    "sg:province":"WA",
    "sg:tags":[
        "recapping",
        "repairing",
        "retreading",
        "tyre"
    ],
    "wof:name":"Maddington Tyre & Suspension",
    "wof:placetype":"venue"
},
  "geometry": {"coordinates":[115.97863006599999,-32.0490570068],"type":"Point"}
}