{
  "type": "Feature",
  "properties": {
    "addr:full":"108 Vincent St Cessnock NSW 2325",
    "addr:housenumber":"108",
    "addr:postcode":"2325",
    "addr:street":"Vincent St",
    "iso:country":"AU",
    "sg:address":"108 Vincent St",
    "sg:city":"Cessnock",
    "sg:classifiers":[
        {
            "category":"Health Services",
            "subcategory":"Dentist",
            "type":"Services"
        }
    ],
    "sg:phone":"+61 2 4990 1279",
    "sg:postcode":"2325",
    "sg:province":"NSW",
    "wof:name":"Ward Alexys",
    "wof:placetype":"venue"
},
  "geometry": {"coordinates":[151.356201172,-32.8363189697],"type":"Point"}
}