{
  "type": "Feature",
  "properties": {
    "addr:full":"64 Greenvale Drv Greenvale VIC 3059",
    "addr:housenumber":"64",
    "addr:postcode":"3059",
    "addr:street":"Greenvale Drv",
    "iso:country":"AU",
    "sg:address":"64 Greenvale Drv",
    "sg:city":"Greenvale",
    "sg:classifiers":[
        {
            "category":"Education",
            "subcategory":"Library",
            "type":"Public Place"
        }
    ],
    "sg:phone":"+61 3 9333 2068",
    "sg:postcode":"3059",
    "sg:province":"VIC",
    "sg:tags":[
        "equipment",
        "supply"
    ],
    "wof:name":"EAS Services",
    "wof:placetype":"venue"
},
  "geometry": {"coordinates":[144.88731384299999,-37.6432800293],"type":"Point"}
}