{
  "type": "Feature",
  "properties": {
    "addr:full":"7/24- 26 Endurance Ave Queanbeyan ACT 2620",
    "addr:housenumber":"/;26",
    "addr:postcode":"2620",
    "addr:street":"24;Endurance Ave",
    "iso:country":"AU",
    "sg:address":"7/24- 26 Endurance Ave",
    "sg:city":"Queanbeyan",
    "sg:classifiers":[
        {
            "category":"Home & Garden",
            "subcategory":"Furniture",
            "type":"Retail Goods"
        }
    ],
    "sg:phone":"+61 2 6299 7521",
    "sg:postcode":"2620",
    "sg:province":"ACT",
    "sg:tags":[
        "repair",
        "restoration"
    ],
    "wof:name":"F & O Commercial Upholstery",
    "wof:placetype":"venue"
},
  "geometry": {"coordinates":[149.24729919399999,-35.3405570984],"type":"Point"}
}