{
  "type": "Feature",
  "properties": {
    "addr:full":"178 High St Prahran VIC 3181",
    "addr:housenumber":"178",
    "addr:postcode":"3181",
    "addr:street":"High St",
    "iso:country":"AU",
    "sg:address":"178 High St",
    "sg:city":"Prahran",
    "sg:classifiers":[
        {
            "category":"Professional",
            "subcategory":"Business Services",
            "type":"Services"
        }
    ],
    "sg:phone":"+61 3 9529 2692",
    "sg:postcode":"3181",
    "sg:province":"VIC",
    "sg:tags":[
        "fashion",
        "agent"
    ],
    "wof:name":"Basu S Importing Co",
    "wof:placetype":"venue"
},
  "geometry": {"coordinates":[144.994216919,-37.85206604],"type":"Point"}
}