{
  "type": "Feature",
  "properties": {
    "addr:full":"405 Burragorang Rd Mt Hunter NSW 2570",
    "addr:housenumber":"405",
    "addr:postcode":"2570",
    "addr:street":"Burragorang Rd",
    "iso:country":"AU",
    "sg:address":"405 Burragorang Rd",
    "sg:city":"Mt Hunter",
    "sg:classifiers":[
        {
            "category":"Farming",
            "subcategory":"Nursery",
            "type":"Manufacturing & Wholesale Goods"
        }
    ],
    "sg:phone":"+61 2 4654 5397",
    "sg:postcode":"2570",
    "sg:province":"NSW",
    "wof:name":"Jensen's Garden Centre Wholesale & Retail",
    "wof:placetype":"venue"
},
  "geometry": {"coordinates":[150.611618042,-34.0666999817],"type":"Point"}
}