{
  "type": "Feature",
  "properties": {
    "addr:full":"10 Leswell St Bondi Junction NSW 2022",
    "addr:housenumber":"10",
    "addr:postcode":"2022",
    "addr:street":"Leswell St",
    "iso:country":"AU",
    "sg:address":"10 Leswell St",
    "sg:city":"Bondi Junction",
    "sg:classifiers":[
        {
            "category":"Banks & Credit Unions",
            "subcategory":"Financial Services",
            "type":"Services"
        }
    ],
    "sg:phone":"+61 2 9388 9977",
    "sg:postcode":"2022",
    "sg:province":"NSW",
    "sg:tags":[
        "planning"
    ],
    "wof:name":"Eastbay Financial Services Pty Ltd",
    "wof:placetype":"venue"
},
  "geometry": {"coordinates":[151.24456787099999,-33.8906784058],"type":"Point"}
}