{
  "type": "Feature",
  "properties": {
    "addr:full":"27 Melville St Kincumber NSW 2251",
    "addr:housenumber":"27",
    "addr:postcode":"2251",
    "addr:street":"Melville St",
    "iso:country":"AU",
    "sg:address":"27 Melville St",
    "sg:city":"Kincumber",
    "sg:classifiers":[
        {
            "category":"Professional",
            "subcategory":"Accounting & Tax Preparation",
            "type":"Services"
        }
    ],
    "sg:phone":"+61 2 4368 2128",
    "sg:postcode":"2251",
    "sg:province":"NSW",
    "sg:tags":[
        "bookkeeping"
    ],
    "wof:name":"Booker Taylor Bookkeeping",
    "wof:placetype":"venue"
},
  "geometry": {"coordinates":[151.403686523,-33.468662262],"type":"Point"}
}