{
  "type": "Feature",
  "properties": {
    "addr:full":"132 Southwood Rd Partington QLD 4811",
    "addr:housenumber":"132",
    "addr:postcode":"4811",
    "addr:street":"Southwood Rd",
    "iso:country":"AU",
    "sg:address":"132 Southwood Rd",
    "sg:city":"Partington",
    "sg:classifiers":[
        {
            "category":"Military Area",
            "subcategory":"Army Base",
            "type":"Public Place"
        }
    ],
    "sg:phone":"+61 7 4778 4366",
    "sg:postcode":"4811",
    "sg:province":"QLD",
    "sg:tags":[
        "wholesaler",
        "mfrs",
        "cement",
        "supply"
    ],
    "wof:name":"Southwood Oil Supply",
    "wof:placetype":"venue"
},
  "geometry": {"coordinates":[146.85531599999999,-19.347849],"type":"Point"}
}