{
  "type": "Feature",
  "properties": {
    "iso:country":"AU",
    "sg:address":"18 Kennedy St",
    "sg:city":"Bentleigh East",
    "sg:classifiers":[
        {
            "category":"Real Estate",
            "subcategory":"Architect",
            "type":"Services"
        }
    ],
    "sg:phone":"+61 412 374 378",
    "sg:postcode":"3165",
    "sg:province":"VIC",
    "wof:name":"Ileris Christopher",
    "wof:placetype":"venue"
},
  "geometry": {"coordinates":[145.07696533199999,-37.9195518494],"type":"Point"}
}