{
  "type": "Feature",
  "properties": {
    "addr:full":"8 Patrol St Jamboree Heights QLD 4074",
    "addr:postcode":"4074",
    "addr:street":"Patrol St",
    "iso:country":"AU",
    "sg:address":"8 Patrol St",
    "sg:city":"Jamboree Heights",
    "sg:classifiers":[
        {
            "category":"Building & Trades",
            "subcategory":"Construction",
            "type":"Services"
        }
    ],
    "sg:phone":"+61 7 3376 3375",
    "sg:postcode":"4074",
    "sg:province":"QLD",
    "sg:tags":[
        "contractor"
    ],
    "wof:name":"Garry Franke Constructions",
    "wof:placetype":"venue"
},
  "geometry": {"coordinates":[152.93208313,-27.5525665283],"type":"Point"}
}