{
  "type": "Feature",
  "properties": {
    "addr:full":"84 Ingleston Rd Wakerley QLD 4154",
    "addr:housenumber":"84",
    "addr:postcode":"4154",
    "addr:street":"Ingleston Rd",
    "iso:country":"AU",
    "sg:address":"84 Ingleston Rd",
    "sg:city":"Wakerley",
    "sg:classifiers":[
        {
            "category":"Military Area",
            "subcategory":"Naval Base",
            "type":"Public Place"
        }
    ],
    "sg:phone":"+61 7 3890 2000",
    "sg:postcode":"4154",
    "sg:province":"QLD",
    "sg:tags":[
        "stand",
        "rack"
    ],
    "wof:name":"Gisler Wire Products Pty Ltd",
    "wof:placetype":"venue"
},
  "geometry": {"coordinates":[153.142669678,-27.4816169739],"type":"Point"}
}