{
  "type": "Feature",
  "properties": {
    "addr:full":"121 Toolooa St Gladstone QLD 4680",
    "addr:housenumber":"121",
    "addr:postcode":"4680",
    "addr:street":"Toolooa St",
    "iso:country":"AU",
    "sg:address":"121 Toolooa St",
    "sg:city":"Gladstone",
    "sg:classifiers":[
        {
            "category":"Fast Food",
            "type":"Food & Drink"
        }
    ],
    "sg:phone":"+61 7 4972 3732",
    "sg:postcode":"4680",
    "sg:province":"QLD",
    "sg:tags":[
        "away",
        "take"
    ],
    "wof:name":"Norms Take-Away",
    "wof:placetype":"venue"
},
  "geometry": {"coordinates":[151.26948547399999,-23.8573741913],"type":"Point"}
}