{
  "type": "Feature",
  "properties": {
    "addr:full":"54 Leewood Drv Orange NSW 2800",
    "addr:housenumber":"54",
    "addr:postcode":"2800",
    "addr:street":"Leewood Drv",
    "iso:country":"AU",
    "sg:address":"54 Leewood Drv",
    "sg:city":"Orange",
    "sg:classifiers":[
        {
            "category":"Commercial Area",
            "type":"Public Place"
        }
    ],
    "sg:phone":"+61 2 6362 7111",
    "sg:postcode":"2800",
    "sg:province":"NSW",
    "sg:tags":[
        "heavy",
        "carrier"
    ],
    "wof:name":"Ferguson Freighters Pty Ltd",
    "wof:placetype":"venue"
},
  "geometry": {"coordinates":[149.10675048799999,-33.3094062805],"type":"Point"}
}