{
  "type": "Feature",
  "properties": {
    "addr:full":"221 Kerr St Fitzroy VIC 3065",
    "addr:housenumber":"221",
    "addr:postcode":"3065",
    "addr:street":"Kerr St",
    "iso:country":"AU",
    "sg:address":"221 Kerr St",
    "sg:city":"Fitzroy",
    "sg:classifiers":[
        {
            "category":"Health Services",
            "subcategory":"Clinic",
            "type":"Services"
        }
    ],
    "sg:phone":"+61 3 9486 9688",
    "sg:postcode":"3065",
    "sg:province":"VIC",
    "sg:tags":[
        "aromatherapy"
    ],
    "wof:name":"Purity Australia Pty Ltd",
    "wof:placetype":"venue"
},
  "geometry": {"coordinates":[144.98373413100001,-37.7971191406],"type":"Point"}
}