{
  "type": "Feature",
  "properties": {
    "addr:full":"80 Kingsford Smith Drv Albion QLD 4010",
    "addr:housenumber":"80",
    "addr:postcode":"4010",
    "addr:street":"Kingsford Smith Drv",
    "iso:country":"AU",
    "sg:address":"80 Kingsford Smith Drv",
    "sg:city":"Albion",
    "sg:classifiers":[
        {
            "category":"Communications",
            "subcategory":"Television Station",
            "type":"Services"
        }
    ],
    "sg:phone":"+61 7 3862 6210",
    "sg:postcode":"4010",
    "sg:province":"QLD",
    "sg:tags":[
        "equipment",
        "laser"
    ],
    "wof:name":"Kennedy C R",
    "wof:placetype":"venue"
},
  "geometry": {"coordinates":[153.04705810600001,-27.4411182404],"type":"Point"}
}