{
  "type": "Feature",
  "properties": {
    "addr:full":"33 Victoria Ave Concord West NSW 2138",
    "addr:housenumber":"33",
    "addr:postcode":"2138",
    "addr:street":"Victoria Ave",
    "iso:country":"AU",
    "sg:address":"33 Victoria Ave",
    "sg:city":"Concord West",
    "sg:classifiers":[
        {
            "category":"Food & Beverages",
            "subcategory":"Supermarket",
            "type":"Retail Goods"
        }
    ],
    "sg:phone":"+61 2 9743 4101",
    "sg:postcode":"2138",
    "sg:province":"NSW",
    "sg:tags":[
        "grocery",
        "store"
    ],
    "wof:name":"Concord West Mini Market",
    "wof:placetype":"venue"
},
  "geometry": {"coordinates":[151.08648681599999,-33.8478317261],"type":"Point"}
}