{
  "type": "Feature",
  "properties": {
    "iso:country":"AU",
    "sg:address":"18- 20 Cleg St",
    "sg:city":"Artarmon",
    "sg:classifiers":[
        {
            "category":"Food & Beverages",
            "subcategory":"Liquor & Beverages",
            "type":"Retail Goods"
        }
    ],
    "sg:phone":"+61 2 9966 0944",
    "sg:postcode":"2064",
    "sg:province":"NSW",
    "sg:tags":[
        "merchant",
        "spirit",
        "wine"
    ],
    "wof:name":"Inglewood Wines Pty Ltd",
    "wof:placetype":"venue"
},
  "geometry": {"coordinates":[151.18946838400001,-33.8155212402],"type":"Point"}
}