{
  "type": "Feature",
  "properties": {
    "addr:full":"55 Commercial Rd Port Adelaide SA 5015",
    "addr:housenumber":"55",
    "addr:postcode":"5015",
    "addr:street":"Commercial Rd",
    "iso:country":"AU",
    "sg:address":"55 Commercial Rd",
    "sg:city":"Port Adelaide",
    "sg:classifiers":[
        {
            "category":"Travel",
            "subcategory":"Hotels & Motels",
            "type":"Entertainment"
        }
    ],
    "sg:phone":"+61 8 8447 1708",
    "sg:postcode":"5015",
    "sg:province":"SA",
    "sg:tags":[
        "accommodation"
    ],
    "wof:name":"Port Admiral Hotel The",
    "wof:placetype":"venue"
},
  "geometry": {"coordinates":[138.508255005,-34.8484191895],"type":"Point"}
}