{
  "type": "Feature",
  "properties": {
    "addr:full":"Unit 1B/ 33 York Rd Penrith NSW 2750",
    "addr:housenumber":"unit 1b / 33",
    "addr:postcode":"2750",
    "addr:street":"York Rd",
    "iso:country":"AU",
    "sg:address":"Unit 1B/ 33 York Rd",
    "sg:city":"Penrith",
    "sg:classifiers":[
        {
            "category":"Retail",
            "subcategory":"Auto Repair",
            "type":"Services"
        }
    ],
    "sg:phone":"+61 2 4721 3132",
    "sg:postcode":"2750",
    "sg:province":"NSW",
    "sg:tags":[
        "repairer",
        "motor",
        "engineer"
    ],
    "wof:name":"Bob Rea Engine Reconditioning",
    "wof:placetype":"venue"
},
  "geometry": {"coordinates":[150.715606689,-33.756149292],"type":"Point"}
}