{
  "type": "Feature",
  "properties": {
    "iso:country":"AU",
    "sg:address":"Springfield Medical Centre Topaz Rd",
    "sg:city":"Springfield",
    "sg:classifiers":[
        {
            "category":"Shopping",
            "subcategory":"Optical Goods",
            "type":"Retail Goods"
        }
    ],
    "sg:phone":"+61 7 3818 6555",
    "sg:postcode":"4300",
    "sg:province":"QLD",
    "sg:tags":[
        "dispenser",
        "prescription"
    ],
    "wof:name":"Fell Paul",
    "wof:placetype":"venue"
},
  "geometry": {"coordinates":[152.916778564,-27.6517810822],"type":"Point"}
}