{
  "type": "Feature",
  "properties": {
    "addr:full":"452 Blaxlands Ridge Rd Kurrajong NSW 2758",
    "addr:housenumber":"452",
    "addr:postcode":"2758",
    "addr:street":"Blaxlands Ridge Rd",
    "iso:country":"AU",
    "sg:address":"452 Blaxlands Ridge Rd",
    "sg:city":"Kurrajong",
    "sg:classifiers":[
        {
            "category":"Building & Trades",
            "subcategory":"Plumbing",
            "type":"Services"
        }
    ],
    "sg:phone":"+61 407 299 934",
    "sg:postcode":"2758",
    "sg:province":"NSW",
    "sg:tags":[
        "plumber",
        "gasfitters"
    ],
    "wof:name":"Hawkesbury Nepean Plumbing",
    "wof:placetype":"venue"
},
  "geometry": {"coordinates":[150.76167297399999,-33.49559021],"type":"Point"}
}