{
  "type": "Feature",
  "properties": {
    "addr:full":"Lot 165 Garfield St Gladstone QLD 4680",
    "addr:postcode":"4680",
    "addr:street":"Garfield St",
    "iso:country":"AU",
    "sg:address":"Lot 165 Garfield St",
    "sg:city":"Gladstone",
    "sg:classifiers":[
        {
            "category":"Home & Garden",
            "subcategory":"Building Materials",
            "type":"Retail Goods"
        }
    ],
    "sg:phone":"+61 7 4972 8897",
    "sg:postcode":"4680",
    "sg:province":"QLD",
    "sg:tags":[
        "fencing"
    ],
    "wof:name":"C.Q. Frames & Trusses",
    "wof:placetype":"venue"
},
  "geometry": {"coordinates":[151.23036193900001,-23.8528347015],"type":"Point"}
}