{
  "type": "Feature",
  "properties": {
    "addr:full":"Unit 1c, 5 Salisbury Rd Castle Hill NSW 2154",
    "addr:housenumber":"unit;5",
    "addr:postcode":"2154",
    "addr:street":"Salisbury Rd",
    "iso:country":"AU",
    "sg:address":"Unit 1c, 5 Salisbury Rd",
    "sg:city":"Castle Hill",
    "sg:classifiers":[
        {
            "category":"Professional",
            "subcategory":"Computer Services",
            "type":"Services"
        }
    ],
    "sg:phone":"+61 2 9659 8887",
    "sg:postcode":"2154",
    "sg:province":"NSW",
    "sg:tags":[
        "package",
        "software"
    ],
    "wof:name":"Caz Software",
    "wof:placetype":"venue"
},
  "geometry": {"coordinates":[150.97428894000001,-33.7298698425],"type":"Point"}
}