{
  "type": "Feature",
  "properties": {
    "addr:full":"4 Park La Grafton NSW 2460",
    "addr:housenumber":"4",
    "addr:postcode":"2460",
    "addr:street":"Park La",
    "iso:country":"AU",
    "sg:address":"4 Park La",
    "sg:city":"Grafton",
    "sg:classifiers":[
        {
            "category":"Home & Garden",
            "subcategory":"Building Materials",
            "type":"Retail Goods"
        }
    ],
    "sg:phone":"+61 2 6643 2593",
    "sg:postcode":"2460",
    "sg:province":"NSW",
    "sg:tags":[
        "lawn",
        "cutting",
        "maintenance"
    ],
    "wof:name":"AC & CS Mowing Service",
    "wof:placetype":"venue"
},
  "geometry": {"coordinates":[152.93119812,-29.6783561707],"type":"Point"}
}