{
  "type": "Feature",
  "properties": {
    "addr:full":"Shop 5 Weaver St Stansbury SA 5582",
    "addr:housenumber":"shop 5",
    "addr:postcode":"5582",
    "addr:street":"Weaver St",
    "iso:country":"AU",
    "sg:address":"Shop 5 Weaver St",
    "sg:city":"Stansbury",
    "sg:classifiers":[
        {
            "category":"Personal",
            "subcategory":"Beauty Salon",
            "type":"Services"
        }
    ],
    "sg:phone":"+61 8 8852 4229",
    "sg:postcode":"5582",
    "sg:province":"SA",
    "sg:tags":[
        "hairdresser"
    ],
    "wof:name":"Hair at the Bay",
    "wof:placetype":"venue"
},
  "geometry": {"coordinates":[137.79737854000001,-34.9097557068],"type":"Point"}
}