{
  "type": "Feature",
  "properties": {
    "iso:country":"AU",
    "sg:address":"134 Main St",
    "sg:city":"Greensborough",
    "sg:classifiers":[
        {
            "category":"Autos & Motor Vehicles",
            "subcategory":"Auto Supplies",
            "type":"Retail Goods"
        }
    ],
    "sg:phone":"+61 3 9432 9418",
    "sg:postcode":"3088",
    "sg:province":"VIC",
    "sg:tags":[
        "battery",
        "automotive"
    ],
    "wof:name":"Beaurepaires",
    "wof:placetype":"venue"
},
  "geometry": {"coordinates":[145.10643005399999,-37.7020606995],"type":"Point"}
}