{
  "type": "Feature",
  "properties": {
    "addr:full":"Dawson Hwy Gladstone QLD 4680",
    "addr:postcode":"4680",
    "addr:street":"Dawson Hwy",
    "iso:country":"AU",
    "sg:address":"Dawson Hwy",
    "sg:city":"Gladstone",
    "sg:classifiers":[
        {
            "category":"Shopping",
            "subcategory":"Department Store",
            "type":"Retail Goods"
        }
    ],
    "sg:phone":"+61 7 4978 2155",
    "sg:postcode":"4680",
    "sg:province":"QLD",
    "wof:name":"Kmart",
    "wof:placetype":"venue"
},
  "geometry": {"coordinates":[151.24740600600001,-23.8580608368],"type":"Point"}
}