{
  "type": "Feature",
  "properties": {
    "addr:full":"2 Rochester Drv Mt Warren Park QLD 4207",
    "addr:housenumber":"2",
    "addr:postcode":"4207",
    "addr:street":"Rochester Drv Mt Warren",
    "iso:country":"AU",
    "sg:address":"2 Rochester Drv",
    "sg:city":"Mt Warren Park",
    "sg:classifiers":[
        {
            "category":"Health Services",
            "subcategory":"Doctor",
            "type":"Services"
        }
    ],
    "sg:phone":"+61 7 3287 1243",
    "sg:postcode":"4207",
    "sg:province":"QLD",
    "sg:tags":[
        "medical",
        "practitioner"
    ],
    "wof:name":"Weston David",
    "wof:placetype":"venue"
},
  "geometry": {"coordinates":[153.21263122600001,-27.7250003815],"type":"Point"}
}