{
  "type": "Feature",
  "properties": {
    "addr:full":"59 Aldebaran St Richlands QLD 4077",
    "addr:housenumber":"59",
    "addr:postcode":"4077",
    "addr:street":"Aldebaran St",
    "iso:country":"AU",
    "sg:address":"59 Aldebaran St",
    "sg:city":"Richlands",
    "sg:classifiers":[
        {
            "category":"Education",
            "subcategory":"Music School",
            "type":"Public Place"
        }
    ],
    "sg:phone":"+61 7 3879 6662",
    "sg:postcode":"4077",
    "sg:province":"QLD",
    "sg:tags":[
        "choir",
        "bands",
        "orchestra"
    ],
    "wof:name":"Swing Central",
    "wof:placetype":"venue"
},
  "geometry": {"coordinates":[152.96087646500001,-27.6027622223],"type":"Point"}
}