{
  "type": "Feature",
  "properties": {
    "addr:full":"1109 Sydney Rd Coburg North VIC 3058",
    "addr:housenumber":"1109",
    "addr:postcode":"3058",
    "addr:street":"Sydney Rd",
    "iso:country":"AU",
    "sg:address":"1109 Sydney Rd",
    "sg:city":"Coburg North",
    "sg:classifiers":[
        {
            "category":"Banks & Credit Unions",
            "subcategory":"Investment Brokerage",
            "type":"Services"
        }
    ],
    "sg:phone":"+61 3 9354 5898",
    "sg:postcode":"3058",
    "sg:province":"VIC",
    "sg:tags":[
        "finance",
        "broker"
    ],
    "wof:name":"Ezy Corp Finance",
    "wof:placetype":"venue"
},
  "geometry": {"coordinates":[144.96307373100001,-37.7208023071],"type":"Point"}
}