{
  "type": "Feature",
  "properties": {
    "iso:country":"AU",
    "sg:address":"11 Rosemary Drv",
    "sg:city":"Modbury North",
    "sg:classifiers":[
        {
            "category":"Retail",
            "subcategory":"Auto Repair",
            "type":"Services"
        }
    ],
    "sg:phone":"+61 439 841 073",
    "sg:postcode":"5092",
    "sg:province":"SA",
    "sg:tags":[
        "beater",
        "painter",
        "panel"
    ],
    "wof:name":"C & C Crash Repairs",
    "wof:placetype":"venue"
},
  "geometry": {"coordinates":[138.67213439899999,-34.8220176697],"type":"Point"}
}