{
  "type": "Feature",
  "properties": {
    "addr:full":"355 St Kilda Rd, Melb Melbourne VIC 3004",
    "addr:housenumber":"355",
    "addr:postcode":"3004",
    "addr:street":"St Kilda Rd",
    "iso:country":"AU",
    "sg:address":"355 St",
    "sg:city":"Kilda Rd, Melb Melbourne",
    "sg:classifiers":[
        {
            "category":"Education",
            "subcategory":"School",
            "type":"Public Place"
        }
    ],
    "sg:phone":"+61 3 9865 7555",
    "sg:postcode":"3004",
    "sg:province":"VIC",
    "sg:tags":[
        "boy"
    ],
    "wof:name":"Melbourne Grammar School",
    "wof:placetype":"venue"
},
  "geometry": {"coordinates":[144.973556519,-37.8333702087],"type":"Point"}
}