{
  "type": "Feature",
  "properties": {
    "addr:full":"112 Boniface St Archerfield QLD 4108",
    "addr:housenumber":"112",
    "addr:postcode":"4108",
    "addr:street":"Boniface St",
    "iso:country":"AU",
    "sg:address":"112 Boniface St",
    "sg:city":"Archerfield",
    "sg:classifiers":[
        {
            "category":"Retail",
            "subcategory":"Auto Repair",
            "type":"Services"
        }
    ],
    "sg:phone":"+61 7 3277 3839",
    "sg:postcode":"4108",
    "sg:province":"QLD",
    "sg:tags":[
        "bus",
        "truck"
    ],
    "wof:name":"Kerrin O'Brien Truck Repair Pty Ltd",
    "wof:placetype":"venue"
},
  "geometry": {"coordinates":[153.02008056599999,-27.5635871887],"type":"Point"}
}