{
  "type": "Feature",
  "properties": {
    "addr:full":"27 Production Ave Kogarah NSW 2217",
    "addr:housenumber":"27",
    "addr:postcode":"2217",
    "addr:street":"Production Ave",
    "iso:country":"AU",
    "sg:address":"27 Production Ave",
    "sg:city":"Kogarah",
    "sg:classifiers":[
        {
            "category":"Manufacturing",
            "subcategory":"Motor Vehicles & Parts",
            "type":"Manufacturing & Wholesale Goods"
        }
    ],
    "sg:phone":"+61 2 9587 4000",
    "sg:postcode":"2217",
    "sg:province":"NSW",
    "sg:tags":[
        "replacement"
    ],
    "wof:name":"Gearhead Driveline Components",
    "wof:placetype":"venue"
},
  "geometry": {"coordinates":[151.13912999999999,-33.978447],"type":"Point"}
}