{
  "type": "Feature",
  "properties": {
    "addr:full":"19 Glynburn Rd Glynde SA 5070",
    "addr:housenumber":"19",
    "addr:postcode":"5070",
    "addr:street":"Glynburn Rd",
    "iso:country":"AU",
    "sg:address":"19 Glynburn Rd",
    "sg:city":"Glynde",
    "sg:classifiers":[
        {
            "category":"Banks & Credit Unions",
            "subcategory":"Financial Services",
            "type":"Services"
        }
    ],
    "sg:phone":"+61 8 8337 9666",
    "sg:postcode":"5070",
    "sg:province":"SA",
    "sg:tags":[
        "planning"
    ],
    "wof:name":"Wigzell Stephen",
    "wof:placetype":"venue"
},
  "geometry": {"coordinates":[138.656524658,-34.8918952942],"type":"Point"}
}