{
  "type": "Feature",
  "properties": {
    "addr:full":"7 Jackson Rd Lalor Park NSW 2147",
    "addr:housenumber":"7",
    "addr:postcode":"2147",
    "addr:street":"Jackson Rd",
    "iso:country":"AU",
    "sg:address":"7 Jackson Rd",
    "sg:city":"Lalor Park",
    "sg:classifiers":[
        {
            "category":"Building & Trades",
            "subcategory":"Construction",
            "type":"Services"
        }
    ],
    "sg:phone":"+61 2 9621 1161",
    "sg:postcode":"2147",
    "sg:province":"NSW",
    "sg:tags":[
        "roof"
    ],
    "wof:name":"Peters Restorations Pty Ltd",
    "wof:placetype":"venue"
},
  "geometry": {"coordinates":[150.924758911,-33.7562942505],"type":"Point"}
}