{
  "type": "Feature",
  "properties": {
    "addr:full":"Tramway St Ferny Grove QLD 4055",
    "addr:postcode":"4055",
    "addr:street":"Tramway St",
    "iso:country":"AU",
    "sg:address":"Tramway St",
    "sg:city":"Ferny Grove",
    "sg:classifiers":[
        {
            "category":"Arena",
            "subcategory":"Sports Club",
            "type":"Entertainment"
        }
    ],
    "sg:phone":"+61 7 3351 5856",
    "sg:postcode":"4055",
    "sg:province":"QLD",
    "sg:tags":[
        "australian",
        "football",
        "rule"
    ],
    "wof:name":"Ferny Grove & Districts Junior Australian Football Club",
    "wof:placetype":"venue"
},
  "geometry": {"coordinates":[152.93812560999999,-27.4064426422],"type":"Point"}
}