{
  "type": "Feature",
  "properties": {
    "addr:full":"303 Glynburn Rd Kensington Park SA 5068",
    "addr:housenumber":"303",
    "addr:postcode":"5068",
    "addr:street":"Glynburn Rd",
    "iso:country":"AU",
    "sg:address":"303 Glynburn Rd",
    "sg:city":"Kensington Park",
    "sg:classifiers":[
        {
            "category":"Health Services",
            "subcategory":"Doctor",
            "type":"Services"
        }
    ],
    "sg:phone":"+61 8 8331 8541",
    "sg:postcode":"5068",
    "sg:province":"SA",
    "sg:tags":[
        "medical",
        "practitioner"
    ],
    "wof:name":"Tsakalos V (Basil) E Dr",
    "wof:placetype":"venue"
},
  "geometry": {"coordinates":[138.65826415999999,-34.9154205322],"type":"Point"}
}