{
  "type": "Feature",
  "properties": {
    "iso:country":"AU",
    "sg:address":"48 Oakdale Rd",
    "sg:city":"Gateshead",
    "sg:classifiers":[
        {
            "category":"Education",
            "subcategory":"Special Training",
            "type":"Public Place"
        }
    ],
    "sg:phone":"+61 2 4942 3133",
    "sg:postcode":"2290",
    "sg:province":"NSW",
    "sg:tags":[
        "development"
    ],
    "wof:name":"Lake Macquarie Business Centre",
    "wof:placetype":"venue"
},
  "geometry": {"coordinates":[151.70179748499999,-32.9924049377],"type":"Point"}
}