{
  "type": "Feature",
  "properties": {
    "iso:country":"AU",
    "sg:address":"120 Fourteenth Ave",
    "sg:city":"Hoxton Park",
    "sg:classifiers":[
        {
            "category":"Banks & Credit Unions",
            "subcategory":"Investment Brokerage",
            "type":"Services"
        }
    ],
    "sg:phone":"+61 416 201 266",
    "sg:postcode":"2171",
    "sg:province":"NSW",
    "sg:tags":[
        "paint",
        "supply",
        "removal"
    ],
    "wof:name":"Aeroblast Abrasive Blasting Pty Ltd",
    "wof:placetype":"venue"
},
  "geometry": {"coordinates":[150.84434509299999,-33.9228782654],"type":"Point"}
}