{
  "type": "Feature",
  "properties": {
    "addr:full":"46 Mackay St Wangaratta VIC 3677",
    "addr:housenumber":"46",
    "addr:postcode":"3677",
    "addr:street":"Mackay St",
    "iso:country":"AU",
    "sg:address":"46 Mackay St",
    "sg:city":"Wangaratta",
    "sg:classifiers":[
        {
            "category":"Retail",
            "subcategory":"Repair Shop",
            "type":"Services"
        }
    ],
    "sg:phone":"+61 407 229 377",
    "sg:postcode":"3677",
    "sg:province":"VIC",
    "sg:tags":[
        "upholsterer"
    ],
    "wof:name":"Riverland Canvas & Upholstery",
    "wof:placetype":"venue"
},
  "geometry": {"coordinates":[146.32049560600001,-36.3528823853],"type":"Point"}
}