{
  "type": "Feature",
  "properties": {
    "addr:full":"37 Grose Wold Rd Grose Wold NSW 2753",
    "addr:housenumber":"37",
    "addr:postcode":"2753",
    "addr:street":"Grose Wold Rd",
    "iso:country":"AU",
    "sg:address":"37 Grose Wold Rd",
    "sg:city":"Grose Wold",
    "sg:classifiers":[
        {
            "category":"Education",
            "subcategory":"Kindergarten",
            "type":"Public Place"
        }
    ],
    "sg:phone":"+61 2 4572 2278",
    "sg:postcode":"2753",
    "sg:province":"NSW",
    "sg:tags":[
        "pre-schools"
    ],
    "wof:name":"Grose Wold Pre School & Long Day Care Centre",
    "wof:placetype":"venue"
},
  "geometry": {"coordinates":[150.68649292000001,-33.6007728577],"type":"Point"}
}