{
  "type": "Feature",
  "properties": {
    "iso:country":"AU",
    "sg:address":"60 Bryson St",
    "sg:city":"Canterbury",
    "sg:classifiers":[
        {
            "category":"Home & Garden",
            "subcategory":"Building Materials",
            "type":"Retail Goods"
        }
    ],
    "sg:phone":"+61 3 9836 3361",
    "sg:postcode":"3126",
    "sg:province":"VIC",
    "sg:tags":[
        "insect",
        "screen"
    ],
    "wof:name":"Classic Hardware Bronze & Stainless Steel Flywire",
    "wof:placetype":"venue"
},
  "geometry": {"coordinates":[145.08119201700001,-37.8292236328],"type":"Point"}
}