{
  "type": "Feature",
  "properties": {
    "addr:full":"Fore St Canterbury NSW 2193",
    "addr:postcode":"2193",
    "addr:street":"Fore St",
    "iso:country":"AU",
    "sg:address":"Fore St",
    "sg:city":"Canterbury",
    "sg:classifiers":[
        {
            "category":"Retail",
            "subcategory":"Auto Repair",
            "type":"Services"
        }
    ],
    "sg:phone":"+61 2 9787 3335",
    "sg:postcode":"2193",
    "sg:province":"NSW",
    "sg:tags":[
        "repairer",
        "motor",
        "engineer"
    ],
    "wof:name":"M & R Auto Repairs",
    "wof:placetype":"venue"
},
  "geometry": {"coordinates":[151.115433,-33.9137],"type":"Point"}
}