{
  "type": "Feature",
  "properties": {
    "addr:full":"5 Quat Quatta Ave Elsternwick VIC 3185",
    "addr:housenumber":"5",
    "addr:postcode":"3185",
    "addr:street":"Quat Quatta Ave",
    "iso:country":"AU",
    "sg:address":"5 Quat Quatta Ave",
    "sg:city":"Elsternwick",
    "sg:classifiers":[
        {
            "category":"Professional",
            "subcategory":"Computer Services",
            "type":"Services"
        }
    ],
    "sg:phone":"+61 3 9532 9499",
    "sg:postcode":"3185",
    "sg:province":"VIC",
    "sg:tags":[
        "repairs",
        "upgrade",
        "equipment"
    ],
    "wof:name":"Wefix Computers Pty Ltd",
    "wof:placetype":"venue"
},
  "geometry": {"coordinates":[144.99696350100001,-37.8781776428],"type":"Point"}
}