{
  "type": "Feature",
  "properties": {
    "addr:full":"22a Belmore Rd Punchbowl NSW 2196",
    "addr:housenumber":"22a",
    "addr:postcode":"2196",
    "addr:street":"Belmore Rd",
    "iso:country":"AU",
    "sg:address":"22a Belmore Rd",
    "sg:city":"Punchbowl",
    "sg:classifiers":[
        {
            "category":"Retail",
            "subcategory":"Auto Repair",
            "type":"Services"
        }
    ],
    "sg:phone":"+61 2 9534 8144",
    "sg:postcode":"2196",
    "sg:province":"NSW",
    "sg:tags":[
        "repairer",
        "motor",
        "engineer"
    ],
    "wof:name":"Dart Automotive",
    "wof:placetype":"venue"
},
  "geometry": {"coordinates":[151.05602999999999,-33.933449],"type":"Point"}
}