{
  "type": "Feature",
  "properties": {
    "addr:full":"89 Manilla St Manilla NSW 2346",
    "addr:housenumber":"89",
    "addr:postcode":"2346",
    "addr:street":"Manilla St",
    "iso:country":"AU",
    "sg:address":"89 Manilla St",
    "sg:city":"Manilla",
    "sg:classifiers":[
        {
            "category":"Food & Beverages",
            "subcategory":"Supermarket",
            "type":"Retail Goods"
        }
    ],
    "sg:phone":"+61 2 6785 1482",
    "sg:postcode":"2346",
    "sg:province":"NSW",
    "sg:tags":[
        "grocery",
        "store"
    ],
    "wof:name":"Parkview Superette",
    "wof:placetype":"venue"
},
  "geometry": {"coordinates":[150.720504761,-30.748550415],"type":"Point"}
}