{
  "type": "Feature",
  "properties": {
    "addr:full":"99 Moreland St Footscray VIC 3011",
    "addr:housenumber":"99",
    "addr:postcode":"3011",
    "addr:street":"Moreland St",
    "iso:country":"AU",
    "sg:address":"99 Moreland St",
    "sg:city":"Footscray",
    "sg:classifiers":[
        {
            "category":"Retail",
            "subcategory":"Storage",
            "type":"Services"
        }
    ],
    "sg:phone":"+61 3 9689 6670",
    "sg:postcode":"3011",
    "sg:province":"VIC",
    "wof:name":"Budget Self Storage",
    "wof:placetype":"venue"
},
  "geometry": {"coordinates":[144.905563355,-37.8053436279],"type":"Point"}
}