{
  "type": "Feature",
  "properties": {
    "addr:full":"155 Darley St Mona Vale NSW 2103",
    "addr:housenumber":"155",
    "addr:postcode":"2103",
    "addr:street":"Darley St",
    "iso:country":"AU",
    "sg:address":"155 Darley St",
    "sg:city":"Mona Vale",
    "sg:classifiers":[
        {
            "category":"Education",
            "subcategory":"Kindergarten",
            "type":"Public Place"
        }
    ],
    "sg:phone":"+61 2 9997 1605",
    "sg:postcode":"2103",
    "sg:province":"NSW",
    "sg:tags":[
        "pre-schools"
    ],
    "wof:name":"Darley Street Kindergarten",
    "wof:placetype":"venue"
},
  "geometry": {"coordinates":[151.300247192,-33.6712150574],"type":"Point"}
}