{
  "type": "Feature",
  "properties": {
    "iso:country":"AU",
    "sg:address":"Tully Falls Rd",
    "sg:city":"Ravenshoe",
    "sg:classifiers":[
        {
            "category":"Manufacturing",
            "subcategory":"Lumber",
            "type":"Manufacturing & Wholesale Goods"
        }
    ],
    "sg:phone":"+61 7 4097 6177",
    "sg:postcode":"4872",
    "sg:province":"QLD",
    "sg:tags":[
        "sawmillers"
    ],
    "wof:name":"Ravenshoe Timbers Pty Ltd",
    "wof:placetype":"venue"
},
  "geometry": {"coordinates":[145.733612061,-16.8785266876],"type":"Point"}
}