{
  "type": "Feature",
  "properties": {
    "addr:full":"22 Second Ave Box Hill North VIC 3129",
    "addr:housenumber":"22",
    "addr:postcode":"3129",
    "addr:street":"Second Ave",
    "iso:country":"AU",
    "sg:address":"22 Second Ave",
    "sg:city":"Box Hill North",
    "sg:classifiers":[
        {
            "category":"Retail",
            "subcategory":"Auto Repair",
            "type":"Services"
        }
    ],
    "sg:phone":"+61 3 9890 4107",
    "sg:postcode":"3129",
    "sg:province":"VIC",
    "sg:tags":[
        "repairer",
        "motor",
        "engineer"
    ],
    "wof:name":"Fratelli Motors",
    "wof:placetype":"venue"
},
  "geometry": {"coordinates":[145.13923645,-37.8009567261],"type":"Point"}
}