{
  "type": "Feature",
  "properties": {
    "addr:full":"17 Alexandra St Mirani QLD 4754",
    "addr:housenumber":"17",
    "addr:postcode":"4754",
    "addr:street":"Alexandra St",
    "iso:country":"AU",
    "sg:address":"17 Alexandra St",
    "sg:city":"Mirani",
    "sg:classifiers":[
        {
            "category":"Fast Food",
            "type":"Food & Drink"
        }
    ],
    "sg:phone":"+61 7 4959 1500",
    "sg:postcode":"4754",
    "sg:province":"QLD",
    "sg:tags":[
        "away",
        "take"
    ],
    "wof:name":"Pioneer Valley Diner",
    "wof:placetype":"venue"
},
  "geometry": {"coordinates":[148.86399800000001,-21.158602],"type":"Point"}
}