{
  "type": "Feature",
  "properties": {
    "addr:full":"Albert St Upper Ferntree Gully VIC 3156",
    "addr:postcode":"3156",
    "addr:street":"Albert St",
    "iso:country":"AU",
    "sg:address":"Albert St",
    "sg:city":"Upper Ferntree Gully",
    "sg:classifiers":[
        {
            "category":"Health Services",
            "subcategory":"Doctor",
            "type":"Services"
        }
    ],
    "sg:phone":"+61 3 9764 6240",
    "sg:postcode":"3156",
    "sg:province":"VIC",
    "sg:tags":[
        "medical",
        "practitioner"
    ],
    "wof:name":"Radclin Medical Imaging",
    "wof:placetype":"venue"
},
  "geometry": {"coordinates":[145.311645508,-37.897983551],"type":"Point"}
}