{
  "type": "Feature",
  "properties": {
    "addr:full":"63 Forest Rd Arncliffe NSW 2205",
    "addr:housenumber":"63",
    "addr:postcode":"2205",
    "addr:street":"Forest Rd",
    "iso:country":"AU",
    "sg:address":"63 Forest Rd",
    "sg:city":"Arncliffe",
    "sg:classifiers":[
        {
            "category":"Health Services",
            "subcategory":"Doctor",
            "type":"Services"
        }
    ],
    "sg:phone":"+61 2 9556 3844",
    "sg:postcode":"2205",
    "sg:province":"NSW",
    "sg:tags":[
        "medical",
        "practitioner"
    ],
    "wof:name":"Iskander N Dr",
    "wof:placetype":"venue"
},
  "geometry": {"coordinates":[151.143967,-33.939213],"type":"Point"}
}