{
  "type": "Feature",
  "properties": {
    "addr:full":"Oxenham Drv Elizabeth SA 5112",
    "addr:postcode":"5112",
    "addr:street":"Oxenham Drv",
    "iso:country":"AU",
    "sg:address":"Oxenham Drv",
    "sg:city":"Elizabeth",
    "sg:classifiers":[
        {
            "category":"Shopping",
            "subcategory":"Department Store",
            "type":"Retail Goods"
        }
    ],
    "sg:phone":"+61 8 8393 5300",
    "sg:postcode":"5112",
    "sg:province":"SA",
    "wof:name":"John Martin Retailers Ltd",
    "wof:placetype":"venue"
},
  "geometry": {"coordinates":[138.668624878,-34.7168540955],"type":"Point"}
}