{
  "type": "Feature",
  "properties": {
    "addr:full":"56 McMinn St Darwin NT 0800",
    "addr:housenumber":"56",
    "addr:postcode":"nt 0800",
    "addr:street":"Mcminn St",
    "iso:country":"AU",
    "sg:address":"56 McMinn St",
    "sg:city":"Darwin",
    "sg:classifiers":[
        {
            "category":"Arts & Performance",
            "subcategory":"Theater",
            "type":"Entertainment"
        }
    ],
    "sg:phone":"+61 8 8924 4184",
    "sg:postcode":"0800",
    "sg:province":"NT",
    "sg:tags":[
        "theatre"
    ],
    "wof:name":"Darwin Theatre Company",
    "wof:placetype":"venue"
},
  "geometry": {"coordinates":[130.84205627399999,-12.4566783905],"type":"Point"}
}