{
  "type": "Feature",
  "properties": {
    "addr:full":"50 Rushdale St Scoresby VIC 3179",
    "addr:housenumber":"50",
    "addr:postcode":"3179",
    "addr:street":"Rushdale St",
    "iso:country":"AU",
    "sg:address":"50 Rushdale St",
    "sg:city":"Scoresby",
    "sg:classifiers":[
        {
            "category":"Manufacturing",
            "subcategory":"Metals",
            "type":"Manufacturing & Wholesale Goods"
        }
    ],
    "sg:phone":"+61 3 9763 0431",
    "sg:postcode":"3179",
    "sg:province":"VIC",
    "sg:tags":[
        "steel",
        "fabricator",
        "mfrs"
    ],
    "wof:name":"All Range Steel Fabrication",
    "wof:placetype":"venue"
},
  "geometry": {"coordinates":[145.25531005900001,-37.8997268677],"type":"Point"}
}