{
  "type": "Feature",
  "properties": {
    "addr:full":"5 Karabah Pl Frenchs Forest NSW 2086",
    "addr:housenumber":"5",
    "addr:postcode":"2086",
    "addr:street":"Karabah Pl",
    "iso:country":"AU",
    "sg:address":"5 Karabah Pl",
    "sg:city":"Frenchs Forest",
    "sg:classifiers":[
        {
            "category":"Home & Garden",
            "subcategory":"Building Materials",
            "type":"Retail Goods"
        }
    ],
    "sg:phone":"+61 2 9451 2467",
    "sg:postcode":"2086",
    "sg:province":"NSW",
    "sg:tags":[
        "lawn",
        "cutting",
        "maintenance"
    ],
    "wof:name":"North of The Harbour Lawn Mowing Service",
    "wof:placetype":"venue"
},
  "geometry": {"coordinates":[151.24708557100001,-33.7486801147],"type":"Point"}
}