{
  "type": "Feature",
  "properties": {
    "addr:full":"189 Leichhardt St Brisbane QLD 4000",
    "addr:housenumber":"189",
    "addr:postcode":"4000",
    "addr:street":"Leichhardt St",
    "iso:country":"AU",
    "sg:address":"189 Leichhardt St",
    "sg:city":"Brisbane",
    "sg:classifiers":[
        {
            "category":"Retail",
            "subcategory":"Event Space",
            "type":"Services"
        }
    ],
    "sg:phone":"+61 7 3831 5000",
    "sg:postcode":"4000",
    "sg:province":"QLD",
    "sg:tags":[
        "venue",
        "reception",
        "wedding"
    ],
    "wof:name":"Ridge Central Hotel",
    "wof:placetype":"venue"
},
  "geometry": {"coordinates":[153.02607727,-27.4624729156],"type":"Point"}
}