{
  "type": "Feature",
  "properties": {
    "iso:country":"AU",
    "sg:address":"Lot 212/ Mayo Rd",
    "sg:city":"Gidgegannup",
    "sg:classifiers":[
        {
            "category":"Utilities",
            "type":"Services"
        }
    ],
    "sg:phone":"+61 417 907 865",
    "sg:postcode":"6083",
    "sg:province":"WA",
    "sg:tags":[
        "refrigeration",
        "industrial",
        "commercial",
        "retail"
    ],
    "wof:name":"Dutton's Mechanical Building Services",
    "wof:placetype":"venue"
},
  "geometry": {"coordinates":[116.253601074,-31.7670345306],"type":"Point"}
}