{
  "type": "Feature",
  "properties": {
    "iso:country":"AU",
    "sg:address":"113 Thompson St",
    "sg:city":"Hamilton",
    "sg:classifiers":[
        {
            "category":"Cafe",
            "type":"Food & Drink"
        }
    ],
    "sg:phone":"+61 3 5572 5923",
    "sg:postcode":"3300",
    "sg:province":"VIC",
    "wof:name":"Woodys Cafe Bar",
    "wof:placetype":"venue"
},
  "geometry": {"coordinates":[142.02226257300001,-37.7430343628],"type":"Point"}
}