{
  "type": "Feature",
  "properties": {
    "addr:full":"17 Cronulla St Cronulla NSW 2230",
    "addr:housenumber":"17",
    "addr:postcode":"2230",
    "addr:street":"Cronulla St",
    "iso:country":"AU",
    "sg:address":"17 Cronulla St",
    "sg:city":"Cronulla",
    "sg:classifiers":[
        {
            "category":"Food & Beverages",
            "subcategory":"Bakery",
            "type":"Retail Goods"
        }
    ],
    "sg:phone":"+61 2 9523 1036",
    "sg:postcode":"2230",
    "sg:province":"NSW",
    "sg:tags":[
        "baker"
    ],
    "wof:name":"Golden Hot Bread",
    "wof:placetype":"venue"
},
  "geometry": {"coordinates":[151.152709961,-34.0522994995],"type":"Point"}
}