{
  "type": "Feature",
  "properties": {
    "addr:full":"3 Tor Pl City Beach WA 6015",
    "addr:housenumber":"3",
    "addr:postcode":"6015",
    "addr:street":"Tor Pl",
    "iso:country":"AU",
    "sg:address":"3 Tor Pl",
    "sg:city":"City Beach",
    "sg:classifiers":[
        {
            "category":"School Buses",
            "type":"Transportation"
        }
    ],
    "sg:phone":"+61 8 9385 7472",
    "sg:postcode":"6015",
    "sg:province":"WA",
    "sg:tags":[
        "nanny"
    ],
    "wof:name":"Au Pair Australia",
    "wof:placetype":"venue"
},
  "geometry": {"coordinates":[115.760063171,-31.943069458],"type":"Point"}
}