{
  "type": "Feature",
  "properties": {
    "iso:country":"AU",
    "sg:address":"Cnr North Pde & Belmore Ave",
    "sg:city":"Mt Druitt",
    "sg:classifiers":[
        {
            "category":"Social Services",
            "subcategory":"Child Care",
            "type":"Services"
        }
    ],
    "sg:phone":"+61 2 9625 7280",
    "sg:postcode":"2770",
    "sg:province":"NSW",
    "wof:name":"John Armitage Centre",
    "wof:placetype":"venue"
},
  "geometry": {"coordinates":[150.81552124000001,-33.768573761],"type":"Point"}
}