{
  "type": "Feature",
  "properties": {
    "addr:full":"316 Penhurst St Willoughby NSW 2068",
    "addr:housenumber":"316",
    "addr:postcode":"2068",
    "addr:street":"Penhurst St",
    "iso:country":"AU",
    "sg:address":"316 Penhurst St",
    "sg:city":"Willoughby",
    "sg:classifiers":[
        {
            "category":"Autos & Motor Vehicles",
            "subcategory":"Fuel & Gas Station",
            "type":"Retail Goods"
        }
    ],
    "sg:phone":"+61 2 9417 6713",
    "sg:postcode":"2068",
    "sg:province":"NSW",
    "wof:name":"BP Australia Pty Ltd",
    "wof:placetype":"venue"
},
  "geometry": {"coordinates":[151.19612121599999,-33.7941703796],"type":"Point"}
}