{
  "type": "Feature",
  "properties": {
    "iso:country":"AU",
    "sg:address":"246 Parry St",
    "sg:city":"Newcastle West",
    "sg:classifiers":[
        {
            "category":"Arts & Performance",
            "subcategory":"Art Gallery",
            "type":"Entertainment"
        }
    ],
    "sg:phone":"+61 2 4940 8066",
    "sg:postcode":"2302",
    "sg:province":"NSW",
    "wof:name":"Newcastle Art Space",
    "wof:placetype":"venue"
},
  "geometry": {"coordinates":[151.752899,-32.923065],"type":"Point"}
}