{
  "type": "Feature",
  "properties": {
    "iso:country":"AU",
    "sg:address":"87 Penshurst St",
    "sg:city":"Willoughby",
    "sg:classifiers":[
        {
            "category":"Government",
            "subcategory":"City Hall",
            "type":"Public Place"
        }
    ],
    "sg:phone":"+61 2 9958 8729",
    "sg:postcode":"2068",
    "sg:province":"NSW",
    "wof:name":"Masonic Halls & Centres",
    "wof:placetype":"venue"
},
  "geometry": {"coordinates":[151.19889831500001,-33.8006362915],"type":"Point"}
}