{
  "type": "Feature",
  "properties": {
    "addr:full":"1 Geoff Russell Ave Kinross WA 6028",
    "addr:housenumber":"1",
    "addr:postcode":"6028",
    "addr:street":"Geoff Russell Ave",
    "iso:country":"AU",
    "sg:address":"1 Geoff Russell Ave",
    "sg:city":"Kinross",
    "sg:classifiers":[
        {
            "category":"Professional",
            "subcategory":"Testing Lab",
            "type":"Services"
        }
    ],
    "sg:phone":"+61 439 972 561",
    "sg:postcode":"6028",
    "sg:province":"WA",
    "sg:tags":[
        "inspection"
    ],
    "wof:name":"Perth Testing & Tagging",
    "wof:placetype":"venue"
},
  "geometry": {"coordinates":[115.734237671,-31.7167301178],"type":"Point"}
}