{
  "type": "Feature",
  "properties": {
    "iso:country":"AU",
    "sg:address":"585 Beach Rd",
    "sg:city":"Warwick",
    "sg:classifiers":[
        {
            "category":"Health Services",
            "subcategory":"Doctor",
            "type":"Services"
        }
    ],
    "sg:phone":"+61 8 9448 5561",
    "sg:postcode":"6024",
    "sg:province":"WA",
    "sg:tags":[
        "medical",
        "practitioner"
    ],
    "wof:name":"Evans Dale V.",
    "wof:placetype":"venue"
},
  "geometry": {"coordinates":[115.808570862,-31.8455200195],"type":"Point"}
}