{
  "type": "Feature",
  "properties": {
    "addr:full":"PO Box 10285 Gouger Street SA 5000",
    "addr:postcode":"5000",
    "addr:street":"Gouger Street",
    "iso:country":"AU",
    "sg:address":"PO Box 10285",
    "sg:city":"Gouger Street",
    "sg:classifiers":[
        {
            "category":"Home & Garden",
            "subcategory":"Furniture",
            "type":"Retail Goods"
        }
    ],
    "sg:phone":"+61 1300 130 298",
    "sg:postcode":"5000",
    "sg:province":"SA",
    "sg:tags":[
        "business"
    ],
    "wof:name":"DATAFILE",
    "wof:placetype":"venue"
},
  "geometry": {"coordinates":[138.59999084500001,-34.9301147461],"type":"Point"}
}