{
  "type": "Feature",
  "properties": {
    "addr:full":"31 Tellen St Mullaloo WA 6027",
    "addr:housenumber":"31",
    "addr:postcode":"6027",
    "addr:street":"Tellen St",
    "iso:country":"AU",
    "sg:address":"31 Tellen St",
    "sg:city":"Mullaloo",
    "sg:classifiers":[
        {
            "category":"Bars & Pubs",
            "subcategory":"Nightclub",
            "type":"Food & Drink"
        }
    ],
    "sg:phone":"+61 412 904 970",
    "sg:postcode":"6027",
    "sg:province":"WA",
    "sg:tags":[
        "karaoke"
    ],
    "wof:name":"Jon McKenzie's Stage Lights Karaoke Show",
    "wof:placetype":"venue"
},
  "geometry": {"coordinates":[115.748451233,-31.7812633514],"type":"Point"}
}