{
  "type": "Feature",
  "properties": {
    "addr:full":"PO Box 1112 Indooroopilly QLD 4068",
    "addr:postcode":"4068",
    "iso:country":"AU",
    "sg:address":"PO Box 1112",
    "sg:city":"Indooroopilly",
    "sg:classifiers":[
        {
            "category":"Building & Trades",
            "subcategory":"Plumbing",
            "type":"Services"
        }
    ],
    "sg:phone":"+61 7 3878 4444",
    "sg:postcode":"4068",
    "sg:province":"QLD",
    "sg:tags":[
        "plumber",
        "gasfitters"
    ],
    "wof:name":"Conrad Martens Plumbing Service",
    "wof:placetype":"venue"
},
  "geometry": {"coordinates":[152.97575378400001,-27.4989395142],"type":"Point"}
}