{
  "type": "Feature",
  "properties": {
    "iso:country":"AU",
    "sg:address":"32 Enterprise Drv",
    "sg:city":"Beresfield",
    "sg:classifiers":[
        {
            "category":"Industrial Area",
            "type":"Public Place"
        }
    ],
    "sg:phone":"+61 2 4966 5866",
    "sg:postcode":"2322",
    "sg:province":"NSW",
    "sg:tags":[
        "rural",
        "shed"
    ],
    "wof:name":"Glenwood Rural Buildings",
    "wof:placetype":"venue"
},
  "geometry": {"coordinates":[151.64088439899999,-32.8106842041],"type":"Point"}
}