{
  "type": "Feature",
  "properties": {
    "addr:full":"Murray Valley Hwy Lake Charm VIC 3581",
    "addr:postcode":"3581",
    "addr:street":"Valley Hwy",
    "iso:country":"AU",
    "sg:address":"Murray Valley Hwy",
    "sg:city":"Lake Charm",
    "sg:classifiers":[
        {
            "category":"Utilities",
            "subcategory":"Electric",
            "type":"Services"
        }
    ],
    "sg:phone":"+61 418 500 397",
    "sg:postcode":"3581",
    "sg:province":"VIC",
    "sg:tags":[
        "electrical",
        "contractor"
    ],
    "wof:name":"Casey Gillen Electrical",
    "wof:placetype":"venue"
},
  "geometry": {"coordinates":[143.79046630900001,-35.5871620178],"type":"Point"}
}