{
  "type": "Feature",
  "properties": {
    "iso:country":"AU",
    "sg:address":"37-39 Dooen Rd",
    "sg:city":"Horsham",
    "sg:classifiers":[
        {
            "category":"Retail",
            "subcategory":"Event Space",
            "type":"Services"
        }
    ],
    "sg:phone":"+61 3 5382 5013",
    "sg:postcode":"3400",
    "sg:province":"VIC",
    "sg:tags":[
        "venue",
        "reception",
        "wedding"
    ],
    "wof:name":"Glen Logan Restaurant",
    "wof:placetype":"venue"
},
  "geometry": {"coordinates":[142.20950317399999,-36.7080841064],"type":"Point"}
}