{
  "type": "Feature",
  "properties": {
    "addr:full":"2/ 14 Peninsula Blv Seaford VIC 3198",
    "addr:housenumber":"/ 14",
    "addr:postcode":"3198",
    "addr:street":"Peninsula Blv",
    "iso:country":"AU",
    "sg:address":"2/ 14 Peninsula Blv",
    "sg:city":"Seaford",
    "sg:classifiers":[
        {
            "category":"Retail",
            "subcategory":"Laundry & Dry Cleaning",
            "type":"Services"
        }
    ],
    "sg:phone":"+61 3 8796 3577",
    "sg:postcode":"3198",
    "sg:province":"VIC",
    "sg:tags":[
        "equipment",
        "supply"
    ],
    "wof:name":"Kannegiesser Australia Pty Ltd",
    "wof:placetype":"venue"
},
  "geometry": {"coordinates":[145.139572144,-38.1147079468],"type":"Point"}
}