{
  "type": "Feature",
  "properties": {
    "addr:full":"103 North St Toowoomba QLD 4350",
    "addr:housenumber":"103",
    "addr:postcode":"4350",
    "addr:street":"North St",
    "iso:country":"AU",
    "sg:address":"103 North St",
    "sg:city":"Toowoomba",
    "sg:classifiers":[
        {
            "category":"Retail",
            "subcategory":"Auto Repair",
            "type":"Services"
        }
    ],
    "sg:phone":"+61 7 4632 7418",
    "sg:postcode":"4350",
    "sg:province":"QLD",
    "sg:tags":[
        "repairer",
        "motor",
        "engineer"
    ],
    "wof:name":"Toowoomba Car Doctors",
    "wof:placetype":"venue"
},
  "geometry": {"coordinates":[151.928787,-27.538321],"type":"Point"}
}