{
  "type": "Feature",
  "properties": {
    "iso:country":"AU",
    "sg:address":"223 Victoria Hwy",
    "sg:city":"Kununurra",
    "sg:classifiers":[
        {
            "category":"Wholesale",
            "subcategory":"Machinery & Supplies",
            "type":"Manufacturing & Wholesale Goods"
        }
    ],
    "sg:phone":"+61 8 9169 1688",
    "sg:postcode":"6743",
    "sg:province":"WA",
    "sg:tags":[
        "equipment",
        "welding"
    ],
    "wof:name":"Rogers Tyre & Machinery Service",
    "wof:placetype":"venue"
},
  "geometry": {"coordinates":[128.74482727,-15.778169632],"type":"Point"}
}