{
  "type": "Feature",
  "properties": {
    "iso:country":"AU",
    "sg:address":"3 Depot Rd",
    "sg:city":"Mudgee",
    "sg:classifiers":[
        {
            "category":"Retail",
            "subcategory":"Auto Repair",
            "type":"Services"
        }
    ],
    "sg:phone":"+61 2 6372 7581",
    "sg:postcode":"2850",
    "sg:province":"NSW",
    "sg:tags":[
        "repairer",
        "motor",
        "engineer"
    ],
    "wof:name":"Everything Mechanical",
    "wof:placetype":"venue"
},
  "geometry": {"coordinates":[149.58818099999999,-32.600014],"type":"Point"}
}