{
  "type": "Feature",
  "properties": {
    "iso:country":"AU",
    "sg:address":"U2/ 11 Augusta St",
    "sg:city":"Willetton",
    "sg:classifiers":[
        {
            "category":"Farming",
            "subcategory":"Fish & Marine Products",
            "type":"Manufacturing & Wholesale Goods"
        }
    ],
    "sg:phone":"+61 8 9354 4124",
    "sg:postcode":"6155",
    "sg:province":"WA",
    "sg:tags":[
        "wholesaler",
        "mfrs",
        "swimwear"
    ],
    "wof:name":"Skids",
    "wof:placetype":"venue"
},
  "geometry": {"coordinates":[115.879936,-32.04089],"type":"Point"}
}