{
  "type": "Feature",
  "properties": {
    "addr:full":"328 Mt Cotton Rd Capalaba QLD 4157",
    "addr:housenumber":"328",
    "addr:postcode":"4157",
    "addr:street":"Mt Cotton Rd",
    "iso:country":"AU",
    "sg:address":"328 Mt Cotton Rd",
    "sg:city":"Capalaba",
    "sg:classifiers":[
        {
            "category":"Personal",
            "type":"Services"
        }
    ],
    "sg:phone":"+61 1300 887 060",
    "sg:postcode":"4157",
    "sg:province":"QLD",
    "sg:tags":[
        "reducing",
        "treatment",
        "weight"
    ],
    "wof:name":"Oxy-Slim",
    "wof:placetype":"venue"
},
  "geometry": {"coordinates":[153.19380188,-27.5519962311],"type":"Point"}
}