{
  "type": "Feature",
  "properties": {
    "addr:full":"PO Box 604 Alderley QLD 4051",
    "addr:postcode":"4051",
    "iso:country":"AU",
    "sg:address":"PO Box 604",
    "sg:city":"Alderley",
    "sg:classifiers":[
        {
            "category":"Utilities",
            "subcategory":"Electric",
            "type":"Services"
        }
    ],
    "sg:phone":"+61 419 996 603",
    "sg:postcode":"4051",
    "sg:province":"QLD",
    "sg:tags":[
        "electrical",
        "contractor"
    ],
    "wof:name":"C Hudnott Electrical",
    "wof:placetype":"venue"
},
  "geometry": {"coordinates":[153.00590515100001,-27.417427063],"type":"Point"}
}