{
  "type": "Feature",
  "properties": {
    "addr:full":"Level 1 102-104 Station Rd Seven Hills NSW 2147",
    "addr:housenumber":"102-104",
    "addr:postcode":"2147",
    "addr:street":"Station Rd",
    "iso:country":"AU",
    "sg:address":"Level 1 102-104 Station Rd",
    "sg:city":"Seven Hills",
    "sg:classifiers":[
        {
            "category":"Education",
            "subcategory":"Dance Studio",
            "type":"Public Place"
        }
    ],
    "sg:phone":"+61 438 632 623",
    "sg:postcode":"2147",
    "sg:province":"NSW",
    "sg:tags":[
        "venue",
        "tuition"
    ],
    "wof:name":"Lisa Holt",
    "wof:placetype":"venue"
},
  "geometry": {"coordinates":[150.944458008,-33.7747077942],"type":"Point"}
}