{
  "type": "Feature",
  "properties": {
    "addr:full":"Cnr Northern Rd & Maxwell St Penrith NSW 2750",
    "addr:postcode":"2750",
    "addr:street":"Cnr Northern Rd & Maxwell St",
    "iso:country":"AU",
    "sg:address":"Cnr Northern Rd & Maxwell St",
    "sg:city":"Penrith",
    "sg:classifiers":[
        {
            "category":"Travel",
            "subcategory":"Hotels & Motels",
            "type":"Entertainment"
        }
    ],
    "sg:phone":"+61 2 4736 4466",
    "sg:postcode":"2750",
    "sg:province":"NSW",
    "sg:tags":[
        "pub"
    ],
    "wof:name":"Pioneer Tavern",
    "wof:placetype":"venue"
},
  "geometry": {"coordinates":[150.68772888199999,-33.7720794678],"type":"Point"}
}