{
  "type": "Feature",
  "properties": {
    "addr:full":"10- 11 Colrado Crt Hallam VIC 3803",
    "addr:housenumber":"11",
    "addr:postcode":"3803",
    "addr:street":"Colrado Crt",
    "iso:country":"AU",
    "sg:address":"10- 11 Colrado Crt",
    "sg:city":"Hallam",
    "sg:classifiers":[
        {
            "category":"Wholesale",
            "subcategory":"Machinery & Supplies",
            "type":"Manufacturing & Wholesale Goods"
        }
    ],
    "sg:phone":"+61 3 9706 7837",
    "sg:postcode":"3803",
    "sg:province":"VIC",
    "sg:tags":[
        "equipment",
        "laboratory"
    ],
    "wof:name":"IDM Instruments Pty Ltd",
    "wof:placetype":"venue"
},
  "geometry": {"coordinates":[145.27447509800001,-38.0145721436],"type":"Point"}
}