{
  "type": "Feature",
  "properties": {
    "addr:full":"17 Capri Crs Avondale Heights VIC 3034",
    "addr:housenumber":"17",
    "addr:postcode":"3034",
    "addr:street":"Capri Crs",
    "iso:country":"AU",
    "sg:address":"17 Capri Crs",
    "sg:city":"Avondale Heights",
    "sg:classifiers":[
        {
            "category":"Building & Trades",
            "subcategory":"Construction",
            "type":"Services"
        }
    ],
    "sg:phone":"+61 3 9337 2332",
    "sg:postcode":"3034",
    "sg:province":"VIC",
    "sg:tags":[
        "contractor"
    ],
    "wof:name":"ANJ Constructions",
    "wof:placetype":"venue"
},
  "geometry": {"coordinates":[144.774338,-37.757866],"type":"Point"}
}