{
  "type": "Feature",
  "properties": {
    "addr:full":"445 - 447 Gardeners Rd Rosebery NSW 2018",
    "addr:housenumber":"445 447",
    "addr:postcode":"2018",
    "addr:street":"Gardeners Rd",
    "iso:country":"AU",
    "sg:address":"445 - 447 Gardeners Rd",
    "sg:city":"Rosebery",
    "sg:classifiers":[
        {
            "category":"Farming",
            "subcategory":"Poultry Farm",
            "type":"Manufacturing & Wholesale Goods"
        }
    ],
    "sg:phone":"+61 2 9667 2555",
    "sg:postcode":"2018",
    "sg:province":"NSW",
    "sg:tags":[
        "breeder",
        "bird"
    ],
    "wof:name":"Birdsville",
    "wof:placetype":"venue"
},
  "geometry": {"coordinates":[151.20010375999999,-33.9220962524],"type":"Point"}
}