{
  "type": "Feature",
  "properties": {
    "iso:country":"AU",
    "sg:address":"11 Cozens St",
    "sg:city":"Brunswick",
    "sg:classifiers":[
        {
            "category":"Manufacturing",
            "subcategory":"Furniture",
            "type":"Manufacturing & Wholesale Goods"
        }
    ],
    "sg:phone":"+61 3 9383 3444",
    "sg:postcode":"3056",
    "sg:province":"VIC",
    "sg:tags":[
        "builder",
        "designer",
        "custom"
    ],
    "wof:name":"Origin Didier",
    "wof:placetype":"venue"
},
  "geometry": {"coordinates":[144.96322631800001,-37.7562866211],"type":"Point"}
}