{
  "type": "Feature",
  "properties": {
    "addr:full":"259 Geelong Rd Footscray West VIC 3012",
    "addr:housenumber":"259",
    "addr:postcode":"3012",
    "addr:street":"Geelong Rd",
    "iso:country":"AU",
    "sg:address":"259 Geelong Rd",
    "sg:city":"Footscray West",
    "sg:classifiers":[
        {
            "category":"Health Services",
            "subcategory":"Doctor",
            "type":"Services"
        }
    ],
    "sg:phone":"+61 3 9687 7767",
    "sg:postcode":"3012",
    "sg:province":"VIC",
    "sg:tags":[
        "medical",
        "practitioner"
    ],
    "wof:name":"Rozario S & Rawet R J Drs",
    "wof:placetype":"venue"
},
  "geometry": {"coordinates":[144.881988525,-37.804775238],"type":"Point"}
}