{
  "type": "Feature",
  "properties": {
    "addr:full":"2 Torpy St Orange NSW 2800",
    "addr:housenumber":"2",
    "addr:postcode":"2800",
    "addr:street":"Torpy St",
    "iso:country":"AU",
    "sg:address":"2 Torpy St",
    "sg:city":"Orange",
    "sg:classifiers":[
        {
            "category":"Home & Garden",
            "subcategory":"Building Materials",
            "type":"Retail Goods"
        }
    ],
    "sg:phone":"+61 414 844 209",
    "sg:postcode":"2800",
    "sg:province":"NSW",
    "sg:tags":[
        "retaining",
        "wall"
    ],
    "wof:name":"Pave N' Scape Paving and Landscape Contracting",
    "wof:placetype":"venue"
},
  "geometry": {"coordinates":[149.09777832,-33.2894172668],"type":"Point"}
}