{
  "type": "Feature",
  "properties": {
    "addr:full":"1 Wampi Pl James Creek NSW 2463",
    "addr:housenumber":"1",
    "addr:postcode":"2463",
    "addr:street":"Wampi Pl",
    "iso:country":"AU",
    "sg:address":"1 Wampi Pl",
    "sg:city":"James Creek",
    "sg:classifiers":[
        {
            "category":"Home & Garden",
            "subcategory":"Garden Supply",
            "type":"Retail Goods"
        }
    ],
    "sg:phone":"+61 2 6646 0345",
    "sg:postcode":"2463",
    "sg:province":"NSW",
    "sg:tags":[
        "equipment"
    ],
    "wof:name":"Cement Creations",
    "wof:placetype":"venue"
},
  "geometry": {"coordinates":[153.24859619099999,-29.4563293457],"type":"Point"}
}