{
  "type": "Feature",
  "properties": {
    "addr:full":"93 Kennedy Drv Tweed Heads West QLD 2485",
    "addr:housenumber":"93",
    "addr:postcode":"2485",
    "addr:street":"Kennedy Drv",
    "iso:country":"AU",
    "sg:address":"93 Kennedy Drv",
    "sg:city":"Tweed Heads West",
    "sg:classifiers":[
        {
            "category":"Retail",
            "subcategory":"Repair Shop",
            "type":"Services"
        }
    ],
    "sg:phone":"+61 7 5599 1099",
    "sg:postcode":"2485",
    "sg:province":"QLD",
    "sg:tags":[
        "maintenance",
        "pool",
        "swimming"
    ],
    "wof:name":"Adrian's Pool Services",
    "wof:placetype":"venue"
},
  "geometry": {"coordinates":[153.54066467300001,-28.179693222],"type":"Point"}
}