{
  "type": "Feature",
  "properties": {
    "iso:country":"AU",
    "sg:address":"Shp3/ 13 Toorbul St",
    "sg:city":"Bongaree",
    "sg:classifiers":[
        {
            "category":"Shopping",
            "subcategory":"Crafts & Fabrics",
            "type":"Retail Goods"
        }
    ],
    "sg:phone":"+61 7 3408 0643",
    "sg:postcode":"4507",
    "sg:province":"QLD",
    "sg:tags":[
        "supply"
    ],
    "wof:name":"Annabelles Beads",
    "wof:placetype":"venue"
},
  "geometry": {"coordinates":[153.15951538100001,-27.085018158],"type":"Point"}
}