{
  "type": "Feature",
  "properties": {
    "addr:full":"Suite 4/ 83 Grandview St Pymble NSW 2073",
    "addr:housenumber":"83",
    "addr:postcode":"2073",
    "addr:street":"Grandview St",
    "iso:country":"AU",
    "sg:address":"Suite 4/ 83 Grandview St",
    "sg:city":"Pymble",
    "sg:classifiers":[
        {
            "category":"Health Services",
            "subcategory":"Doctor",
            "type":"Services"
        }
    ],
    "sg:phone":"+61 2 9988 3477",
    "sg:postcode":"2073",
    "sg:province":"NSW",
    "sg:tags":[
        "medical",
        "practitioner"
    ],
    "wof:name":"Grandview Street Pymble Medical Practice",
    "wof:placetype":"venue"
},
  "geometry": {"coordinates":[151.142303467,-33.7444229126],"type":"Point"}
}