{
  "type": "Feature",
  "properties": {
    "iso:country":"AU",
    "sg:address":"37 Heathcote Rd",
    "sg:city":"Moorebank",
    "sg:classifiers":[
        {
            "category":"Banks & Credit Unions",
            "subcategory":"Financial Services",
            "type":"Services"
        }
    ],
    "sg:phone":"+61 2 8706 2100",
    "sg:postcode":"2170",
    "sg:province":"NSW",
    "sg:tags":[
        "equipment",
        "chain"
    ],
    "wof:name":"BSC Motion Technology",
    "wof:placetype":"venue"
},
  "geometry": {"coordinates":[150.93809509299999,-33.9378013611],"type":"Point"}
}