{
  "type": "Feature",
  "properties": {
    "addr:full":"Unit 2A, 87 Webster Rd Stafford QLD 4053",
    "addr:housenumber":"unit 2a 87",
    "addr:postcode":"4053",
    "addr:street":"Webster Rd",
    "iso:country":"AU",
    "sg:address":"Unit 2A, 87 Webster Rd",
    "sg:city":"Stafford",
    "sg:classifiers":[
        {
            "category":"Professional",
            "subcategory":"Business Services",
            "type":"Services"
        }
    ],
    "sg:phone":"+61 1300 790 405",
    "sg:postcode":"4053",
    "sg:province":"QLD",
    "sg:tags":[
        "drafting"
    ],
    "wof:name":"Dow Royle & Associates Pty Ltd",
    "wof:placetype":"venue"
},
  "geometry": {"coordinates":[153.01626586899999,-27.4153842926],"type":"Point"}
}