{
  "type": "Feature",
  "properties": {
    "iso:country":"AU",
    "sg:address":"222 Koree Island Rd",
    "sg:city":"Beechwood",
    "sg:classifiers":[
        {
            "category":"Professional",
            "subcategory":"Business Services",
            "type":"Services"
        }
    ],
    "sg:phone":"+61 427 258 131",
    "sg:postcode":"2446",
    "sg:province":"NSW",
    "sg:tags":[
        "livestock",
        "transport"
    ],
    "wof:name":"Collins Livestock Transport",
    "wof:placetype":"venue"
},
  "geometry": {"coordinates":[152.66670199999999,-31.455551],"type":"Point"}
}