{
  "type": "Feature",
  "properties": {
    "addr:full":"11 Lowan Rd Windsor Gardens SA 5087",
    "addr:housenumber":"11",
    "addr:postcode":"5087",
    "addr:street":"Lowan Rd",
    "iso:country":"AU",
    "sg:address":"11 Lowan Rd",
    "sg:city":"Windsor Gardens",
    "sg:classifiers":[
        {
            "category":"Building & Trades",
            "subcategory":"Landscaping Services",
            "type":"Services"
        }
    ],
    "sg:phone":"+61 8 8369 1626",
    "sg:postcode":"5087",
    "sg:province":"SA",
    "sg:tags":[
        "inspection"
    ],
    "wof:name":"A.A. Abmass Advisory Services",
    "wof:placetype":"venue"
},
  "geometry": {"coordinates":[138.662200928,-34.8621101379],"type":"Point"}
}