{
  "type": "Feature",
  "properties": {
    "addr:full":"3/ 806 Anzac Pde Maroubra NSW 2035",
    "addr:housenumber":"/ 806",
    "addr:postcode":"2035",
    "addr:street":"Anzac Pde",
    "iso:country":"AU",
    "sg:address":"3/ 806 Anzac Pde",
    "sg:city":"Maroubra",
    "sg:classifiers":[
        {
            "category":"Health Services",
            "subcategory":"Doctor",
            "type":"Services"
        }
    ],
    "sg:phone":"+61 2 9344 6311",
    "sg:postcode":"2035",
    "sg:province":"NSW",
    "sg:tags":[
        "medical",
        "practitioner"
    ],
    "wof:name":"W Bye Dr",
    "wof:placetype":"venue"
},
  "geometry": {"coordinates":[151.239135742,-33.9389152527],"type":"Point"}
}