{
  "type": "Feature",
  "properties": {
    "iso:country":"AU",
    "sg:address":"Bussell Hwy",
    "sg:city":"Margaret River",
    "sg:classifiers":[
        {
            "category":"Manufacturing",
            "subcategory":"Glass & Minerals",
            "type":"Manufacturing & Wholesale Goods"
        }
    ],
    "sg:phone":"+61 8 9757 4575",
    "sg:postcode":"6285",
    "sg:province":"WA",
    "sg:tags":[
        "blowing"
    ],
    "wof:name":"Karri Glass",
    "wof:placetype":"venue"
},
  "geometry": {"coordinates":[115.07350921600001,-33.9533653259],"type":"Point"}
}