{
  "type": "Feature",
  "properties": {
    "iso:country":"AU",
    "sg:address":"40 Marshall Ave",
    "sg:city":"Kealba",
    "sg:classifiers":[
        {
            "category":"Building & Trades",
            "subcategory":"Construction",
            "type":"Services"
        }
    ],
    "sg:phone":"+61 500 888 812",
    "sg:postcode":"3021",
    "sg:province":"VIC",
    "sg:tags":[
        "management"
    ],
    "wof:name":"P M Australasia Pty Ltd",
    "wof:placetype":"venue"
},
  "geometry": {"coordinates":[144.82624799999999,-37.744297],"type":"Point"}
}