{
  "type": "Feature",
  "properties": {
    "iso:country":"AU",
    "sg:address":"Suite 2/ 78",
    "sg:city":"Osmond Tce Norwood",
    "sg:classifiers":[
        {
            "category":"Health Services",
            "subcategory":"Optometrist",
            "type":"Services"
        }
    ],
    "sg:phone":"+61 8 8332 1444",
    "sg:postcode":"5067",
    "sg:province":"SA",
    "wof:name":"O&#039;Brien David",
    "wof:placetype":"venue"
},
  "geometry": {"coordinates":[138.63203430199999,-34.9235191345],"type":"Point"}
}