{
  "type": "Feature",
  "properties": {
    "addr:full":"41 Ovens St Wangaratta VIC 3677",
    "addr:housenumber":"41",
    "addr:postcode":"3677",
    "addr:street":"Ovens St",
    "iso:country":"AU",
    "sg:address":"41 Ovens St",
    "sg:city":"Wangaratta",
    "sg:classifiers":[
        {
            "category":"Education",
            "subcategory":"School",
            "type":"Public Place"
        }
    ],
    "sg:phone":"+61 3 5722 3304",
    "sg:postcode":"3677",
    "sg:province":"VIC",
    "sg:tags":[
        "co-educational"
    ],
    "wof:name":"Cathedral College",
    "wof:placetype":"venue"
},
  "geometry": {"coordinates":[146.32240295400001,-36.3552703857],"type":"Point"}
}