{
  "type": "Feature",
  "properties": {
    "addr:full":"4 Lawrence Ave West Perth WA 6005",
    "addr:housenumber":"4",
    "addr:postcode":"6005",
    "addr:street":"Lawrence Ave",
    "iso:country":"AU",
    "sg:address":"4 Lawrence Ave",
    "sg:city":"West Perth",
    "sg:classifiers":[
        {
            "category":"Mining & Drilling",
            "type":"Manufacturing & Wholesale Goods"
        }
    ],
    "sg:phone":"+61 8 9322 3600",
    "sg:postcode":"6005",
    "sg:province":"WA",
    "sg:tags":[
        "geologist"
    ],
    "wof:name":"Mackay & Schnellmann Pty Ltd",
    "wof:placetype":"venue"
},
  "geometry": {"coordinates":[115.84223938,-31.9458656311],"type":"Point"}
}