{
  "type": "Feature",
  "properties": {
    "iso:country":"AU",
    "sg:address":"34 Collins St",
    "sg:city":"Annandale",
    "sg:classifiers":[
        {
            "category":"Education",
            "subcategory":"School",
            "type":"Public Place"
        }
    ],
    "sg:phone":"+61 2 9519 3974",
    "sg:postcode":"2038",
    "sg:province":"NSW",
    "wof:name":"St Brendan's School",
    "wof:placetype":"venue"
},
  "geometry": {"coordinates":[151.17018127399999,-33.8839225769],"type":"Point"}
}