{
  "type": "Feature",
  "properties": {
    "iso:country":"AU",
    "sg:address":"51 Brookfield Rd",
    "sg:city":"Kenmore",
    "sg:classifiers":[
        {
            "category":"Banks & Credit Unions",
            "subcategory":"Bank",
            "type":"Services"
        }
    ],
    "sg:phone":"+61 1300 659 644",
    "sg:postcode":"4069",
    "sg:province":"QLD",
    "sg:tags":[
        "broker",
        "mortgage"
    ],
    "wof:name":"Centenary Home Loans",
    "wof:placetype":"venue"
},
  "geometry": {"coordinates":[152.93533325199999,-27.5067424774],"type":"Point"}
}