{
  "type": "Feature",
  "properties": {
    "addr:full":"Suite 12 Westmead Private Hospital Cnr Mons & Darcy Rds Westmead NSW 2145",
    "addr:postcode":"2145",
    "addr:street":"Cnr Mons & Darcy Rds",
    "iso:country":"AU",
    "sg:address":"Suite 12 Westmead Private Hospital Cnr Mons & Darcy Rds",
    "sg:city":"Westmead",
    "sg:classifiers":[
        {
            "category":"Health Services",
            "subcategory":"Doctor",
            "type":"Services"
        }
    ],
    "sg:phone":"+61 2 9633 2088",
    "sg:postcode":"2145",
    "sg:province":"NSW",
    "sg:tags":[
        "medical",
        "practitioner"
    ],
    "wof:name":"Brooks Andrew J",
    "wof:placetype":"venue"
},
  "geometry": {"coordinates":[150.98353576700001,-33.8027458191],"type":"Point"}
}