{
  "type": "Feature",
  "properties": {
    "iso:country":"AU",
    "sg:address":"191 Stirling Hwy",
    "sg:city":"Nedlands",
    "sg:classifiers":[
        {
            "category":"Banks & Credit Unions",
            "subcategory":"Financial Services",
            "type":"Services"
        }
    ],
    "sg:phone":"+61 8 9386 9171",
    "sg:postcode":"6009",
    "sg:province":"WA",
    "sg:tags":[
        "settlement",
        "nt",
        "agent",
        "wa"
    ],
    "wof:name":"Currie & Reeves",
    "wof:placetype":"venue"
},
  "geometry": {"coordinates":[115.815842,-31.976597],"type":"Point"}
}