{
  "type": "Feature",
  "properties": {
    "addr:full":"Cnr Patrick & William Sts Laidley QLD 4341",
    "addr:postcode":"4341",
    "addr:street":"Cnr",
    "iso:country":"AU",
    "sg:address":"Cnr Patrick & William Sts",
    "sg:city":"Laidley",
    "sg:classifiers":[
        {
            "category":"Travel",
            "subcategory":"Hotels & Motels",
            "type":"Entertainment"
        }
    ],
    "sg:phone":"+61 7 5465 1103",
    "sg:postcode":"4341",
    "sg:province":"QLD",
    "sg:tags":[
        "accommodation"
    ],
    "wof:name":"Laidley Hotel",
    "wof:placetype":"venue"
},
  "geometry": {"coordinates":[152.38941955600001,-27.6451702118],"type":"Point"}
}