{
  "type": "Feature",
  "properties": {
    "addr:full":"50 Pacific Hwy Tuggerah NSW 2259",
    "addr:housenumber":"50",
    "addr:postcode":"2259",
    "addr:street":"Pacific Hwy",
    "iso:country":"AU",
    "sg:address":"50 Pacific Hwy",
    "sg:city":"Tuggerah",
    "sg:classifiers":[
        {
            "category":"Home & Garden",
            "subcategory":"Garden Supply",
            "type":"Retail Goods"
        }
    ],
    "sg:phone":"+61 2 4352 2875",
    "sg:postcode":"2259",
    "sg:province":"NSW",
    "sg:tags":[
        "landscape"
    ],
    "wof:name":"Harold Rusten",
    "wof:placetype":"venue"
},
  "geometry": {"coordinates":[151.41270446799999,-33.315486908],"type":"Point"}
}