{
  "type": "Feature",
  "properties": {
    "addr:full":"114 Waton St Werribee VIC 3030",
    "addr:housenumber":"114",
    "addr:postcode":"3030",
    "addr:street":"Waton St",
    "iso:country":"AU",
    "sg:address":"114 Waton St",
    "sg:city":"Werribee",
    "sg:classifiers":[
        {
            "category":"Personal",
            "subcategory":"Massage",
            "type":"Services"
        }
    ],
    "sg:phone":"+61 412 715 414",
    "sg:postcode":"3030",
    "sg:province":"VIC",
    "sg:tags":[
        "therapy"
    ],
    "wof:name":"Mike Tullio",
    "wof:placetype":"venue"
},
  "geometry": {"coordinates":[144.66151400000001,-37.903755],"type":"Point"}
}