{
  "type": "Feature",
  "properties": {
    "addr:full":"PO Box 6030 Hammondville NSW 2170",
    "addr:postcode":"2170",
    "iso:country":"AU",
    "sg:address":"PO Box 6030",
    "sg:city":"Hammondville",
    "sg:classifiers":[
        {
            "category":"Utilities",
            "subcategory":"Electric",
            "type":"Services"
        }
    ],
    "sg:phone":"+61 419 213 308",
    "sg:postcode":"2170",
    "sg:province":"NSW",
    "sg:tags":[
        "electrical",
        "contractor"
    ],
    "wof:name":"SMK Electrical Installations",
    "wof:placetype":"venue"
},
  "geometry": {"coordinates":[150.95053100600001,-33.948890686],"type":"Point"}
}