{
  "type": "Feature",
  "properties": {
    "addr:full":"334 Karrinyup Rd Karrinyup WA 6018",
    "addr:housenumber":"334",
    "addr:postcode":"6018",
    "addr:street":"Karrinyup Rd",
    "iso:country":"AU",
    "sg:address":"334 Karrinyup Rd",
    "sg:city":"Karrinyup",
    "sg:classifiers":[
        {
            "category":"Health Services",
            "subcategory":"Chiropractor",
            "type":"Services"
        }
    ],
    "sg:phone":"+61 8 9446 4809",
    "sg:postcode":"6018",
    "sg:province":"WA",
    "wof:name":"Dillon Paul",
    "wof:placetype":"venue"
},
  "geometry": {"coordinates":[115.770782471,-31.8734512329],"type":"Point"}
}