{
  "type": "Feature",
  "properties": {
    "addr:full":"Queen St Brisbane QLD 4000",
    "addr:postcode":"4000",
    "addr:street":"Queen St",
    "iso:country":"AU",
    "sg:address":"Queen St",
    "sg:city":"Brisbane",
    "sg:classifiers":[
        {
            "category":"Personal",
            "subcategory":"Nail Salon",
            "type":"Services"
        }
    ],
    "sg:phone":"+61 7 3210 6999",
    "sg:postcode":"4000",
    "sg:province":"QLD",
    "sg:tags":[
        "artificial"
    ],
    "wof:name":"Amanda Rochford Nails",
    "wof:placetype":"venue"
},
  "geometry": {"coordinates":[153.02577209500001,-27.4692306519],"type":"Point"}
}