{
  "type": "Feature",
  "properties": {
    "iso:country":"AU",
    "sg:address":"PO Box 554",
    "sg:city":"Torquay",
    "sg:classifiers":[
        {
            "category":"Home & Garden",
            "subcategory":"Building Materials",
            "type":"Retail Goods"
        }
    ],
    "sg:phone":"+61 427 119 931",
    "sg:postcode":"3228",
    "sg:province":"VIC",
    "sg:tags":[
        "lawn",
        "cutting",
        "maintenance"
    ],
    "wof:name":"Aireys Inlet Slashing",
    "wof:placetype":"venue"
},
  "geometry": {"coordinates":[144.31811500000001,-38.329899],"type":"Point"}
}