{
  "type": "Feature",
  "properties": {
    "iso:country":"AU",
    "sg:address":"72 Preddys Rd",
    "sg:city":"Bexley",
    "sg:classifiers":[
        {
            "category":"Insurance",
            "subcategory":"Insurance Agent",
            "type":"Services"
        }
    ],
    "sg:phone":"+61 2 9554 9122",
    "sg:postcode":"2207",
    "sg:province":"NSW",
    "wof:name":"Harman Insurance & Investment Planners Pty Ltd",
    "wof:placetype":"venue"
},
  "geometry": {"coordinates":[151.116806,-33.951923],"type":"Point"}
}