{
  "type": "Feature",
  "properties": {
    "addr:full":"U2/ 11 Didswith St Woolloongabba QLD 4102",
    "addr:postcode":"4102",
    "addr:street":"U2 / 11 Didswith St",
    "iso:country":"AU",
    "sg:address":"U2/ 11 Didswith St",
    "sg:city":"Woolloongabba",
    "sg:classifiers":[
        {
            "category":"Parking",
            "type":"Transportation"
        }
    ],
    "sg:phone":"+61 7 3392 2003",
    "sg:postcode":"4102",
    "sg:province":"QLD",
    "sg:tags":[
        "equipment",
        "system"
    ],
    "wof:name":"S & B Parking Services Pty Ltd",
    "wof:placetype":"venue"
},
  "geometry": {"coordinates":[153.04719543499999,-27.4901428223],"type":"Point"}
}