{
  "type": "Feature",
  "properties": {
    "addr:full":"10 Edwin St Mortlake NSW 2137",
    "addr:housenumber":"10",
    "addr:postcode":"2137",
    "addr:street":"Edwin St",
    "iso:country":"AU",
    "sg:address":"10 Edwin St",
    "sg:city":"Mortlake",
    "sg:classifiers":[
        {
            "category":"Utilities",
            "subcategory":"Electric",
            "type":"Services"
        }
    ],
    "sg:phone":"+61 2 9736 2355",
    "sg:postcode":"2137",
    "sg:province":"NSW",
    "sg:tags":[
        "tube",
        "lamps",
        "globe"
    ],
    "wof:name":"Lamp Replacements Australia Pty Ltd",
    "wof:placetype":"venue"
},
  "geometry": {"coordinates":[151.10740661599999,-33.8417396545],"type":"Point"}
}