{
  "type": "Feature",
  "properties": {
    "iso:country":"AU",
    "sg:address":"309 Goodwood Rd",
    "sg:city":"Kings Park",
    "sg:classifiers":[
        {
            "category":"Health Services",
            "subcategory":"Health Practitioner",
            "type":"Services"
        }
    ],
    "sg:phone":"+61 8 8271 0303",
    "sg:postcode":"5034",
    "sg:province":"SA",
    "sg:tags":[
        "psychologist"
    ],
    "wof:name":"Ask Dr Alex Consultant Psychology Group",
    "wof:placetype":"venue"
},
  "geometry": {"coordinates":[138.590774536,-34.9638824463],"type":"Point"}
}