{
  "type": "Feature",
  "properties": {
    "addr:full":"2 Ulah Crt Noosa Heads QLD 4567",
    "addr:housenumber":"2",
    "addr:postcode":"4567",
    "addr:street":"Ulah Crt",
    "iso:country":"AU",
    "sg:address":"2 Ulah Crt",
    "sg:city":"Noosa Heads",
    "sg:classifiers":[
        {
            "category":"Building & Trades",
            "subcategory":"Cleaning & Sanitation",
            "type":"Services"
        }
    ],
    "sg:phone":"+61 439 724 217",
    "sg:postcode":"4567",
    "sg:province":"QLD",
    "sg:tags":[
        "window"
    ],
    "wof:name":"Crystal Clean Windows",
    "wof:placetype":"venue"
},
  "geometry": {"coordinates":[153.08946227999999,-26.4055461884],"type":"Point"}
}