{
  "type": "Feature",
  "properties": {
    "addr:full":"28 Anthony St South Perth WA 6151",
    "addr:housenumber":"28",
    "addr:postcode":"6151",
    "addr:street":"Anthony St South",
    "iso:country":"AU",
    "sg:address":"28 Anthony St",
    "sg:city":"South Perth",
    "sg:classifiers":[
        {
            "category":"Real Estate",
            "subcategory":"Architect",
            "type":"Services"
        }
    ],
    "sg:phone":"+61 8 9474 2212",
    "sg:postcode":"6151",
    "sg:province":"WA",
    "sg:tags":[
        "building",
        "designer"
    ],
    "wof:name":"Ian Harris Architect",
    "wof:placetype":"venue"
},
  "geometry": {"coordinates":[115.869888,-31.981073],"type":"Point"}
}