{
  "type": "Feature",
  "properties": {
    "addr:full":"U11/ 256 Musgrave Rd Salisbury QLD 4107",
    "addr:postcode":"4107",
    "addr:street":"/ 256 Musgrave Rd",
    "iso:country":"AU",
    "sg:address":"U11/ 256 Musgrave Rd",
    "sg:city":"Salisbury",
    "sg:classifiers":[
        {
            "category":"Shopping",
            "subcategory":"Stationery & Office Supplies",
            "type":"Retail Goods"
        }
    ],
    "sg:phone":"+61 7 3277 9492",
    "sg:postcode":"4107",
    "sg:province":"QLD",
    "sg:tags":[
        "packaging",
        "material"
    ],
    "wof:name":"Unesco Packing Pty Ltd",
    "wof:placetype":"venue"
},
  "geometry": {"coordinates":[153.03515625,-27.562412262],"type":"Point"}
}