{
  "type": "Feature",
  "properties": {
    "addr:full":"293 Macquarie St Hobart TAS 7000",
    "addr:housenumber":"293",
    "addr:postcode":"7000",
    "addr:street":"Macquarie St",
    "iso:country":"AU",
    "sg:address":"293 Macquarie St",
    "sg:city":"Hobart",
    "sg:classifiers":[
        {
            "category":"Real Estate",
            "subcategory":"Architect",
            "type":"Services"
        }
    ],
    "sg:phone":"+61 414 259 543",
    "sg:postcode":"7000",
    "sg:province":"TAS",
    "wof:name":"Padas John",
    "wof:placetype":"venue"
},
  "geometry": {"coordinates":[147.32052612300001,-42.8900527954],"type":"Point"}
}