{
  "type": "Feature",
  "properties": {
    "addr:full":"39 Rhodes St Hillsdale NSW 2036",
    "addr:housenumber":"39",
    "addr:postcode":"2036",
    "addr:street":"Rhodes St",
    "iso:country":"AU",
    "sg:address":"39 Rhodes St",
    "sg:city":"Hillsdale",
    "sg:classifiers":[
        {
            "category":"Fast Food",
            "type":"Food & Drink"
        }
    ],
    "sg:phone":"+61 2 9661 7913",
    "sg:postcode":"2036",
    "sg:province":"NSW",
    "sg:tags":[
        "away",
        "take"
    ],
    "wof:name":"Hillsdale Burgers",
    "wof:placetype":"venue"
},
  "geometry": {"coordinates":[151.22662353499999,-33.9526824951],"type":"Point"}
}