{
  "type": "Feature",
  "properties": {
    "iso:country":"AU",
    "sg:address":"Factory 13 / 134 Springvale Rd",
    "sg:city":"Springvale",
    "sg:classifiers":[
        {
            "category":"Home & Garden",
            "subcategory":"Carpets & Floor Coverings",
            "type":"Retail Goods"
        }
    ],
    "sg:phone":"+61 3 9548 2220",
    "sg:postcode":"3171",
    "sg:province":"VIC",
    "sg:tags":[
        "wood"
    ],
    "wof:name":"G C Floors Pty Ltd",
    "wof:placetype":"venue"
},
  "geometry": {"coordinates":[145.15322875999999,-37.9453163147],"type":"Point"}
}