{
  "type": "Feature",
  "properties": {
    "addr:full":"21 The Mall, Bayswater Rd Croydon South VIC 3136",
    "addr:housenumber":"21",
    "addr:postcode":"3136",
    "addr:street":"The Mall Bayswater Rd",
    "iso:country":"AU",
    "sg:address":"21 The Mall, Bayswater Rd",
    "sg:city":"Croydon South",
    "sg:classifiers":[
        {
            "category":"Personal",
            "subcategory":"Beauty Salon",
            "type":"Services"
        }
    ],
    "sg:phone":"+61 3 9723 4985",
    "sg:postcode":"3136",
    "sg:province":"VIC",
    "sg:tags":[
        "hairdresser"
    ],
    "wof:name":"Hair A Targe",
    "wof:placetype":"venue"
},
  "geometry": {"coordinates":[145.27027893100001,-37.8115234375],"type":"Point"}
}