{
  "type": "Feature",
  "properties": {
    "iso:country":"AU",
    "sg:address":"73 Nerang St",
    "sg:city":"Southport",
    "sg:classifiers":[
        {
            "category":"Health Services",
            "subcategory":"Doctor",
            "type":"Services"
        }
    ],
    "sg:phone":"+61 1800 777 877",
    "sg:postcode":"4215",
    "sg:province":"QLD",
    "sg:tags":[
        "medical",
        "practitioner"
    ],
    "wof:name":"Sullivan Nicolaides Pathology",
    "wof:placetype":"venue"
},
  "geometry": {"coordinates":[153.41123962399999,-27.9689426422],"type":"Point"}
}