{
  "type": "Feature",
  "properties": {
    "addr:full":"15 Chapman Ave Castle Hill NSW 2154",
    "addr:housenumber":"15",
    "addr:postcode":"2154",
    "addr:street":"Chapman Ave",
    "iso:country":"AU",
    "sg:address":"15 Chapman Ave",
    "sg:city":"Castle Hill",
    "sg:classifiers":[
        {
            "category":"Professional",
            "subcategory":"Computer Services",
            "type":"Services"
        }
    ],
    "sg:phone":"+61 2 9680 9655",
    "sg:postcode":"2154",
    "sg:province":"NSW",
    "sg:tags":[
        "consultant",
        "system"
    ],
    "wof:name":"IQ Technology Pty Ltd",
    "wof:placetype":"venue"
},
  "geometry": {"coordinates":[150.99415588400001,-33.7301902771],"type":"Point"}
}