{
  "type": "Feature",
  "properties": {
    "addr:full":"75 Channon St Gympie QLD 4570",
    "addr:housenumber":"75",
    "addr:postcode":"4570",
    "addr:street":"Channon St",
    "iso:country":"AU",
    "sg:address":"75 Channon St",
    "sg:city":"Gympie",
    "sg:classifiers":[
        {
            "category":"Health Services",
            "subcategory":"Optometrist",
            "type":"Services"
        }
    ],
    "sg:phone":"+61 7 5483 8366",
    "sg:postcode":"4570",
    "sg:province":"QLD",
    "wof:name":"Hanks Anthony",
    "wof:placetype":"venue"
},
  "geometry": {"coordinates":[152.664154053,-26.184879303],"type":"Point"}
}