{
  "type": "Feature",
  "properties": {
    "iso:country":"AU",
    "sg:address":"148 Iindah Rd East",
    "sg:city":"Maryborough",
    "sg:classifiers":[
        {
            "category":"Professional",
            "subcategory":"Art Services",
            "type":"Services"
        }
    ],
    "sg:phone":"+61 7 4122 3380",
    "sg:postcode":"4650",
    "sg:province":"QLD",
    "sg:tags":[
        "artist"
    ],
    "wof:name":"Brush Tales Studio",
    "wof:placetype":"venue"
},
  "geometry": {"coordinates":[152.68829299999999,-25.562351],"type":"Point"}
}