{
  "type": "Feature",
  "properties": {
    "iso:country":"AU",
    "sg:address":"Cnr Anderson & Pease Sts",
    "sg:city":"Manunda",
    "sg:classifiers":[
        {
            "category":"Health Services",
            "subcategory":"Dentist",
            "type":"Services"
        }
    ],
    "sg:phone":"+61 7 4046 3535",
    "sg:postcode":"4870",
    "sg:province":"QLD",
    "wof:name":"John Thomas",
    "wof:placetype":"venue"
},
  "geometry": {"coordinates":[145.741500855,-16.913690567],"type":"Point"}
}