{
  "type": "Feature",
  "properties": {
    "addr:full":"555 Tallwood Rd Forest Reefs NSW 2798",
    "addr:housenumber":"555",
    "addr:postcode":"2798",
    "addr:street":"Tallwood Rd",
    "iso:country":"AU",
    "sg:address":"555 Tallwood Rd",
    "sg:city":"Forest Reefs",
    "sg:classifiers":[
        {
            "category":"Farming",
            "subcategory":"Vineyard",
            "type":"Manufacturing & Wholesale Goods"
        }
    ],
    "sg:phone":"+61 2 6366 5168",
    "sg:postcode":"2798",
    "sg:province":"NSW",
    "sg:tags":[
        "winery"
    ],
    "wof:name":"Gold Dust Wines",
    "wof:placetype":"venue"
},
  "geometry": {"coordinates":[149.08653259299999,-33.454750061],"type":"Point"}
}