{
  "type": "Feature",
  "properties": {
    "addr:full":"58 Edward St Sunshine Beach QLD 4567",
    "addr:housenumber":"58",
    "addr:postcode":"4567",
    "addr:street":"Edward St",
    "iso:country":"AU",
    "sg:address":"58 Edward St",
    "sg:city":"Sunshine Beach",
    "sg:classifiers":[
        {
            "category":"Education",
            "subcategory":"Special Training",
            "type":"Public Place"
        }
    ],
    "sg:phone":"+61 7 5447 4258",
    "sg:postcode":"4567",
    "sg:province":"QLD",
    "sg:tags":[
        "development"
    ],
    "wof:name":"Saleah Pty Ltd",
    "wof:placetype":"venue"
},
  "geometry": {"coordinates":[153.105270386,-26.4072971344],"type":"Point"}
}