{
  "type": "Feature",
  "properties": {
    "addr:full":"209 Chesterpass Rd Albany WA 6330",
    "addr:housenumber":"209",
    "addr:postcode":"6330",
    "addr:street":"Chesterpass Rd",
    "iso:country":"AU",
    "sg:address":"209 Chesterpass Rd",
    "sg:city":"Albany",
    "sg:classifiers":[
        {
            "category":"Shopping",
            "subcategory":"Clothing, Apparel, & Fashions",
            "type":"Retail Goods"
        }
    ],
    "sg:phone":"+61 8 9841 7883",
    "sg:postcode":"6330",
    "sg:province":"WA",
    "sg:tags":[
        "style",
        "clothing",
        "western",
        "accessory"
    ],
    "wof:name":"Europa Saddleworld",
    "wof:placetype":"venue"
},
  "geometry": {"coordinates":[117.87600707999999,-34.9855957031],"type":"Point"}
}