{
  "type": "Feature",
  "properties": {
    "addr:full":"52 Georges River Rd Croydon Park NSW 2133",
    "addr:housenumber":"52",
    "addr:postcode":"2133",
    "addr:street":"Georges River Rd",
    "iso:country":"AU",
    "sg:address":"52 Georges River Rd",
    "sg:city":"Croydon Park",
    "sg:classifiers":[
        {
            "category":"Home & Garden",
            "subcategory":"Hardware",
            "type":"Retail Goods"
        }
    ],
    "sg:phone":"+61 2 9798 7665",
    "sg:postcode":"2133",
    "sg:province":"NSW",
    "sg:tags":[
        "plumber",
        "supply"
    ],
    "wof:name":"7 Days Plumbing & Bathroom Supplies",
    "wof:placetype":"venue"
},
  "geometry": {"coordinates":[151.11416625999999,-33.8940849304],"type":"Point"}
}