{
  "type": "Feature",
  "properties": {
    "iso:country":"AU",
    "sg:address":"22 Commerce St",
    "sg:city":"Wauchope",
    "sg:classifiers":[
        {
            "category":"Home & Garden",
            "subcategory":"Carpets & Floor Coverings",
            "type":"Retail Goods"
        }
    ],
    "sg:phone":"+61 2 6586 4144",
    "sg:postcode":"2446",
    "sg:province":"NSW",
    "sg:tags":[
        "wood"
    ],
    "wof:name":"Australasian Sports Floors Horner Pty Ltd",
    "wof:placetype":"venue"
},
  "geometry": {"coordinates":[152.73419200000001,-31.485367],"type":"Point"}
}