{
  "type": "Feature",
  "properties": {
    "addr:full":"271 Macdonnell Rd Clontarf QLD 4019",
    "addr:housenumber":"271",
    "addr:postcode":"4019",
    "addr:street":"Macdonnell Rd",
    "iso:country":"AU",
    "sg:address":"271 Macdonnell Rd",
    "sg:city":"Clontarf",
    "sg:classifiers":[
        {
            "category":"Retail",
            "subcategory":"Auto Repair",
            "type":"Services"
        }
    ],
    "sg:phone":"+61 7 3284 5704",
    "sg:postcode":"4019",
    "sg:province":"QLD",
    "sg:tags":[
        "repairer",
        "motor",
        "engineer"
    ],
    "wof:name":"R & R Mechanical & Service Centre",
    "wof:placetype":"venue"
},
  "geometry": {"coordinates":[153.08692932100001,-27.2345695496],"type":"Point"}
}