{
  "type": "Feature",
  "properties": {
    "addr:full":"Chaffeys Rd McLaren Vale SA 5171",
    "addr:postcode":"5171",
    "addr:street":"Chaffeys Rd",
    "iso:country":"AU",
    "sg:address":"Chaffeys Rd",
    "sg:city":"McLaren Vale",
    "sg:classifiers":[
        {
            "category":"Farming",
            "subcategory":"Vineyard",
            "type":"Manufacturing & Wholesale Goods"
        }
    ],
    "sg:phone":"+61 8 8323 8305",
    "sg:postcode":"5171",
    "sg:province":"SA",
    "sg:tags":[
        "winery"
    ],
    "wof:name":"Coriole Vineyards",
    "wof:placetype":"venue"
},
  "geometry": {"coordinates":[138.55369567899999,-35.1822776794],"type":"Point"}
}