{
  "type": "Feature",
  "properties": {
    "iso:country":"AU",
    "sg:address":"232 Adelaide St",
    "sg:city":"Maryborough",
    "sg:classifiers":[
        {
            "category":"Banks & Credit Unions",
            "subcategory":"Financial Services",
            "type":"Services"
        }
    ],
    "sg:phone":"+61 7 4122 2511",
    "sg:postcode":"4650",
    "sg:province":"QLD",
    "sg:tags":[
        "financier"
    ],
    "wof:name":"CBFC Limited",
    "wof:placetype":"venue"
},
  "geometry": {"coordinates":[152.70220900000001,-25.537832],"type":"Point"}
}