{
  "type": "Feature",
  "properties": {
    "iso:country":"AU",
    "sg:address":"Lot 32 Wedderburn Rd",
    "sg:city":"Wedderburn",
    "sg:classifiers":[
        {
            "category":"Home & Garden",
            "subcategory":"Building Materials",
            "type":"Retail Goods"
        }
    ],
    "sg:phone":"+61 2 4634 1491",
    "sg:postcode":"2560",
    "sg:province":"NSW",
    "sg:tags":[
        "retaining",
        "wall"
    ],
    "wof:name":"Parker's Paving & Landscaping Pty. Ltd.",
    "wof:placetype":"venue"
},
  "geometry": {"coordinates":[150.8125,-34.126449585],"type":"Point"}
}