{
  "type": "Feature",
  "properties": {
    "addr:full":"11b Byron Rd Armadale WA 6112",
    "addr:housenumber":"11b",
    "addr:postcode":"6112",
    "addr:street":"Byron Rd",
    "iso:country":"AU",
    "sg:address":"11b Byron Rd",
    "sg:city":"Armadale",
    "sg:classifiers":[
        {
            "category":"Manufacturing",
            "subcategory":"Musical Instruments",
            "type":"Manufacturing & Wholesale Goods"
        }
    ],
    "sg:phone":"+61 8 9497 2212",
    "sg:postcode":"6112",
    "sg:province":"WA",
    "sg:tags":[
        "repair",
        "maker"
    ],
    "wof:name":"Brady Drum Company Pty Ltd",
    "wof:placetype":"venue"
},
  "geometry": {"coordinates":[116.01361846899999,-32.1730651855],"type":"Point"}
}