{
  "type": "Feature",
  "properties": {
    "addr:full":"159 Ocean St Narrabeen NSW 2101",
    "addr:housenumber":"159",
    "addr:postcode":"2101",
    "addr:street":"Ocean St",
    "iso:country":"AU",
    "sg:address":"159 Ocean St",
    "sg:city":"Narrabeen",
    "sg:classifiers":[
        {
            "category":"Shopping",
            "subcategory":"Stationery & Office Supplies",
            "type":"Retail Goods"
        }
    ],
    "sg:phone":"+61 418 274 826",
    "sg:postcode":"2101",
    "sg:province":"NSW",
    "sg:tags":[
        "partition"
    ],
    "wof:name":"Jawill Interiors Pty Ltd",
    "wof:placetype":"venue"
},
  "geometry": {"coordinates":[151.3022,-33.70916],"type":"Point"}
}