{
  "type": "Feature",
  "properties": {
    "addr:full":"Shop 11/ 45 Candlewood Blv Joondalup WA 6027",
    "addr:housenumber":"shop 11 / 45",
    "addr:postcode":"6027",
    "addr:street":"Candlewood Blv",
    "iso:country":"AU",
    "sg:address":"Shop 11/ 45 Candlewood Blv",
    "sg:city":"Joondalup",
    "sg:classifiers":[
        {
            "category":"Fast Food",
            "type":"Food & Drink"
        }
    ],
    "sg:phone":"+61 8 9300 0383",
    "sg:postcode":"6027",
    "sg:province":"WA",
    "sg:tags":[
        "away",
        "take"
    ],
    "wof:name":"Candlewood Village Chinese Restaurant",
    "wof:placetype":"venue"
},
  "geometry": {"coordinates":[115.764663696,-31.7290077209],"type":"Point"}
}