{
  "type": "Feature",
  "properties": {
    "addr:full":"Shop A 10 Kingaroy St Kingaroy QLD 4610",
    "addr:housenumber":"10",
    "addr:postcode":"4610",
    "addr:street":"A;Kingaroy St",
    "iso:country":"AU",
    "sg:address":"Shop A 10 Kingaroy St",
    "sg:city":"Kingaroy",
    "sg:classifiers":[
        {
            "category":"Wholesale",
            "subcategory":"Machinery & Supplies",
            "type":"Manufacturing & Wholesale Goods"
        }
    ],
    "sg:phone":"+61 13 13 62",
    "sg:postcode":"4610",
    "sg:province":"QLD",
    "sg:tags":[
        "equipment",
        "hydraulic"
    ],
    "wof:name":"Enzed Kingaroy",
    "wof:placetype":"venue"
},
  "geometry": {"coordinates":[151.836593628,-26.5616226196],"type":"Point"}
}