{
  "type": "Feature",
  "properties": {
    "addr:full":"12 Tramway St Tempe NSW 2044",
    "addr:housenumber":"12",
    "addr:postcode":"2044",
    "addr:street":"Tramway St",
    "iso:country":"AU",
    "sg:address":"12 Tramway St",
    "sg:city":"Tempe",
    "sg:classifiers":[
        {
            "category":"Building & Trades",
            "subcategory":"Construction",
            "type":"Services"
        }
    ],
    "sg:phone":"+61 2 9558 2435",
    "sg:postcode":"2044",
    "sg:province":"NSW",
    "sg:tags":[
        "joinery"
    ],
    "wof:name":"Marrickville Joinery",
    "wof:placetype":"venue"
},
  "geometry": {"coordinates":[151.15971400000001,-33.923199],"type":"Point"}
}