{
  "type": "Feature",
  "properties": {
    "iso:country":"AU",
    "sg:address":"12 Dilop Drv",
    "sg:city":"Epping",
    "sg:classifiers":[
        {
            "category":"Wholesale",
            "subcategory":"Furniture",
            "type":"Manufacturing & Wholesale Goods"
        }
    ],
    "sg:phone":"+61 3 9401 3266",
    "sg:postcode":"3076",
    "sg:province":"VIC",
    "sg:tags":[
        "wholesaler",
        "mfrs"
    ],
    "wof:name":"Five Star Furniture (Vic) Pty Ltd",
    "wof:placetype":"venue"
},
  "geometry": {"coordinates":[145.01846313499999,-37.6431732178],"type":"Point"}
}