{
  "type": "Feature",
  "properties": {
    "iso:country":"AU",
    "sg:address":"Aslett Drv",
    "sg:city":"Kalgoorlie",
    "sg:classifiers":[
        {
            "category":"Sports & Exercise",
            "subcategory":"Golf",
            "type":"Entertainment"
        }
    ],
    "sg:phone":"+61 8 9021 2525",
    "sg:postcode":"6430",
    "sg:province":"WA",
    "sg:tags":[
        "club"
    ],
    "wof:name":"Hannan's Golf Club",
    "wof:placetype":"venue"
},
  "geometry": {"coordinates":[121.451789856,-30.7344150543],"type":"Point"}
}