{
  "type": "Feature",
  "properties": {
    "iso:country":"AU",
    "sg:address":"Level 1, 61 Station St",
    "sg:city":"Malvern",
    "sg:classifiers":[
        {
            "category":"Professional",
            "subcategory":"Art Services",
            "type":"Services"
        }
    ],
    "sg:phone":"+61 3 9500 8677",
    "sg:postcode":"3144",
    "sg:province":"VIC",
    "sg:tags":[
        "graphic",
        "designer"
    ],
    "wof:name":"Sage Creative Pty Ltd",
    "wof:placetype":"venue"
},
  "geometry": {"coordinates":[145.02972412099999,-37.8659858704],"type":"Point"}
}