{
  "type": "Feature",
  "properties": {
    "addr:full":"90- 122 Queen Mall Brisbane QLD 4000",
    "addr:housenumber":"122",
    "addr:postcode":"4000",
    "addr:street":"90;Queen Mall",
    "iso:country":"AU",
    "sg:address":"90- 122",
    "sg:city":"Queen Mall Brisbane",
    "sg:classifiers":[
        {
            "category":"Recreation",
            "subcategory":"Amusement Park",
            "type":"Entertainment"
        }
    ],
    "sg:phone":"+61 7 3405 7900",
    "sg:postcode":"4000",
    "sg:province":"QLD",
    "wof:name":"Timezone",
    "wof:placetype":"venue"
},
  "geometry": {"coordinates":[153.02487182600001,-27.4697418213],"type":"Point"}
}