{
  "type": "Feature",
  "properties": {
    "iso:country":"AU",
    "sg:address":"46 Eleanor St",
    "sg:city":"Footscray",
    "sg:classifiers":[
        {
            "category":"Health Services",
            "subcategory":"Doctor",
            "type":"Services"
        }
    ],
    "sg:phone":"+61 3 9318 4446",
    "sg:postcode":"3011",
    "sg:province":"VIC",
    "sg:tags":[
        "medical",
        "practitioner"
    ],
    "wof:name":"Siles Charles Dr",
    "wof:placetype":"venue"
},
  "geometry": {"coordinates":[144.885223389,-37.7930221558],"type":"Point"}
}