{
  "type": "Feature",
  "properties": {
    "addr:full":"209 Henley Beach Rd Torrensville SA 5031",
    "addr:housenumber":"209",
    "addr:postcode":"5031",
    "addr:street":"Henley Beach Rd",
    "iso:country":"AU",
    "sg:address":"209 Henley Beach Rd",
    "sg:city":"Torrensville",
    "sg:classifiers":[
        {
            "category":"Manufacturing",
            "subcategory":"Jewelry",
            "type":"Manufacturing & Wholesale Goods"
        }
    ],
    "sg:phone":"+61 8 8351 9077",
    "sg:postcode":"5031",
    "sg:province":"SA",
    "sg:tags":[
        "mfrg",
        "jeweller"
    ],
    "wof:name":"S. A Jewellers",
    "wof:placetype":"venue"
},
  "geometry": {"coordinates":[138.55795288100001,-34.9244880676],"type":"Point"}
}