{
  "type": "Feature",
  "properties": {
    "iso:country":"AU",
    "sg:address":"U3/ 27 Phillip St",
    "sg:city":"Penrith",
    "sg:classifiers":[
        {
            "category":"Manufacturing",
            "subcategory":"Metals",
            "type":"Manufacturing & Wholesale Goods"
        }
    ],
    "sg:phone":"+61 2 4731 1239",
    "sg:postcode":"2750",
    "sg:province":"NSW",
    "sg:tags":[
        "polisher"
    ],
    "wof:name":"McCoy Moulding & Polishing",
    "wof:placetype":"venue"
},
  "geometry": {"coordinates":[150.716262817,-33.7561225891],"type":"Point"}
}