{
  "type": "Feature",
  "properties": {
    "addr:full":"59 Morgan St Mt Morgan QLD 4714",
    "addr:housenumber":"59",
    "addr:postcode":"4714",
    "addr:street":"Morgan St",
    "iso:country":"AU",
    "sg:address":"59 Morgan St",
    "sg:city":"Mt Morgan",
    "sg:classifiers":[
        {
            "category":"Shopping",
            "subcategory":"Clothing, Apparel, & Fashions",
            "type":"Retail Goods"
        }
    ],
    "sg:phone":"+61 7 4938 1789",
    "sg:postcode":"4714",
    "sg:province":"QLD",
    "sg:tags":[
        "boutique"
    ],
    "wof:name":"Corals Budget Boutique",
    "wof:placetype":"venue"
},
  "geometry": {"coordinates":[150.388473511,-23.6452655792],"type":"Point"}
}