{
  "type": "Feature",
  "properties": {
    "iso:country":"AU",
    "sg:address":"110 Wollamai St",
    "sg:city":"Finley",
    "sg:classifiers":[
        {
            "category":"Education",
            "subcategory":"Music School",
            "type":"Public Place"
        }
    ],
    "sg:phone":"+61 3 5883 1053",
    "sg:postcode":"2713",
    "sg:province":"NSW",
    "sg:tags":[
        "teacher"
    ],
    "wof:name":"Kindermusik With Libby",
    "wof:placetype":"venue"
},
  "geometry": {"coordinates":[145.57112121599999,-35.6348495483],"type":"Point"}
}