{
  "type": "Feature",
  "properties": {
    "iso:country":"AU",
    "sg:address":"Upstairs, 249 Victoria St",
    "sg:city":"Darlinghurst",
    "sg:classifiers":[
        {
            "category":"Organizations",
            "subcategory":"Professional Association",
            "type":"Services"
        }
    ],
    "sg:phone":"+61 2 9356 8751",
    "sg:postcode":"2010",
    "sg:province":"NSW",
    "sg:tags":[
        "web",
        "internet"
    ],
    "wof:name":"Fast Media t/a backend.com",
    "wof:placetype":"venue"
},
  "geometry": {"coordinates":[151.221237183,-33.8784103394],"type":"Point"}
}