{
  "type": "Feature",
  "properties": {
    "addr:full":"43 Cumberland Rd Auburn NSW 2144",
    "addr:housenumber":"43",
    "addr:postcode":"2144",
    "addr:street":"Cumberland Rd",
    "iso:country":"AU",
    "sg:address":"43 Cumberland Rd",
    "sg:city":"Auburn",
    "sg:classifiers":[
        {
            "category":"Food & Beverages",
            "subcategory":"Groceries & Convenience Stores",
            "type":"Retail Goods"
        }
    ],
    "sg:phone":"+61 2 9649 8132",
    "sg:postcode":"2144",
    "sg:province":"NSW",
    "wof:name":"Attie H",
    "wof:placetype":"venue"
},
  "geometry": {"coordinates":[151.02574157699999,-33.8497886658],"type":"Point"}
}