{
  "type": "Feature",
  "properties": {
    "addr:full":"The Kiama Trade Centre Unit 2, 6 Brown St Kiama NSW 2533",
    "addr:housenumber":"6",
    "addr:postcode":"2533",
    "addr:street":"Brown St",
    "iso:country":"AU",
    "sg:address":"The Kiama Trade Centre Unit 2, 6 Brown St",
    "sg:city":"Kiama",
    "sg:classifiers":[
        {
            "category":"Autos & Motor Vehicles",
            "subcategory":"Auto Supplies",
            "type":"Retail Goods"
        }
    ],
    "sg:phone":"+61 2 4232 1336",
    "sg:postcode":"2533",
    "sg:province":"NSW",
    "sg:tags":[
        "tyre"
    ],
    "wof:name":"Kiama Tyre Service",
    "wof:placetype":"venue"
},
  "geometry": {"coordinates":[150.84881591800001,-34.6646575928],"type":"Point"}
}