{
  "type": "Feature",
  "properties": {
    "iso:country":"AU",
    "sg:address":"28 Gidley St",
    "sg:city":"St Marys",
    "sg:classifiers":[
        {
            "category":"Organizations",
            "subcategory":"Non-profit Organization",
            "type":"Services"
        }
    ],
    "sg:phone":"+61 2 9623 9855",
    "sg:postcode":"2760",
    "sg:province":"NSW",
    "sg:tags":[
        "support",
        "disability",
        "organisation"
    ],
    "wof:name":"NADO Inc (Nepean Area Disabilities Organisation)",
    "wof:placetype":"venue"
},
  "geometry": {"coordinates":[150.77540588400001,-33.7673187256],"type":"Point"}
}