{
  "type": "Feature",
  "properties": {
    "addr:full":"The Baptist Theological College of NSW & ACT 120 Herring Rd Eastwood NSW 2122",
    "addr:housenumber":"120",
    "addr:postcode":"2122",
    "addr:street":"Herring Rd",
    "iso:country":"AU",
    "sg:address":"The Baptist Theological College of NSW & ACT 120 Herring Rd",
    "sg:city":"Eastwood",
    "sg:classifiers":[
        {
            "category":"Farming",
            "subcategory":"Livestock Farm",
            "type":"Manufacturing & Wholesale Goods"
        }
    ],
    "sg:phone":"+61 2 9878 0201",
    "sg:postcode":"2122",
    "sg:province":"NSW",
    "sg:tags":[
        "school",
        "theological"
    ],
    "wof:name":"Morling College",
    "wof:placetype":"venue"
},
  "geometry": {"coordinates":[151.11508178700001,-33.7798843384],"type":"Point"}
}