{
  "type": "Feature",
  "properties": {
    "addr:full":"Shop 83 B, Macquarie Cntr North Ryde NSW 2113",
    "addr:housenumber":"shop 83 b",
    "addr:postcode":"2113",
    "addr:street":"Macquarie Cntr",
    "iso:country":"AU",
    "sg:address":"Shop 83",
    "sg:city":"B, Macquarie Cntr North Ryde",
    "sg:classifiers":[
        {
            "category":"Building & Trades",
            "subcategory":"Locksmith",
            "type":"Services"
        }
    ],
    "sg:phone":"+61 2 9887 3433",
    "sg:postcode":"2113",
    "sg:province":"NSW",
    "sg:tags":[
        "lock"
    ],
    "wof:name":"Macquarie Locksmiths",
    "wof:placetype":"venue"
},
  "geometry": {"coordinates":[151.11436462399999,-33.7759208679],"type":"Point"}
}