{
  "type": "Feature",
  "properties": {
    "addr:full":"214 Timor St Warrnambool VIC 3280",
    "addr:housenumber":"214",
    "addr:postcode":"3280",
    "addr:street":"Timor St",
    "iso:country":"AU",
    "sg:address":"214 Timor St",
    "sg:city":"Warrnambool",
    "sg:classifiers":[
        {
            "category":"Bars & Pubs",
            "subcategory":"Nightclub",
            "type":"Food & Drink"
        }
    ],
    "sg:phone":"+61 3 5562 0741",
    "sg:postcode":"3280",
    "sg:province":"VIC",
    "sg:tags":[
        "discotheque"
    ],
    "wof:name":"Gallery Club & Bistro",
    "wof:placetype":"venue"
},
  "geometry": {"coordinates":[142.48042297399999,-38.384437561],"type":"Point"}
}