{
  "type": "Feature",
  "properties": {
    "addr:full":"Unit 11 4- 8 Queen St Bentley WA 6102",
    "addr:housenumber":"4 8",
    "addr:postcode":"6102",
    "addr:street":"Queen St",
    "iso:country":"AU",
    "sg:address":"Unit 11 4- 8 Queen St",
    "sg:city":"Bentley",
    "sg:classifiers":[
        {
            "category":"Professional",
            "subcategory":"Engineering",
            "type":"Services"
        }
    ],
    "sg:phone":"+61 8 9451 1882",
    "sg:postcode":"6102",
    "sg:province":"WA",
    "sg:tags":[
        "engineer"
    ],
    "wof:name":"Forwes Technologies Pty Ltd",
    "wof:placetype":"venue"
},
  "geometry": {"coordinates":[115.919593811,-32.0029525757],"type":"Point"}
}