{
  "type": "Feature",
  "properties": {
    "addr:full":"22 George St Morwell VIC 3840",
    "addr:housenumber":"22",
    "addr:postcode":"3840",
    "addr:street":"George St",
    "iso:country":"AU",
    "sg:address":"22 George St",
    "sg:city":"Morwell",
    "sg:classifiers":[
        {
            "category":"Professional",
            "subcategory":"Printing & Photocopies",
            "type":"Services"
        }
    ],
    "sg:phone":"+61 3 5134 1235",
    "sg:postcode":"3840",
    "sg:province":"VIC",
    "sg:tags":[
        "screen",
        "printer"
    ],
    "wof:name":"Bright-A-Print",
    "wof:placetype":"venue"
},
  "geometry": {"coordinates":[146.39520263700001,-38.2383728027],"type":"Point"}
}