{
  "type": "Feature",
  "properties": {
    "addr:full":"13 Pell Crs Mooroopna VIC 3629",
    "addr:housenumber":"13",
    "addr:postcode":"3629",
    "addr:street":"Pell Crs",
    "iso:country":"AU",
    "sg:address":"13 Pell Crs",
    "sg:city":"Mooroopna",
    "sg:classifiers":[
        {
            "category":"Personal",
            "subcategory":"Massage",
            "type":"Services"
        }
    ],
    "sg:phone":"+61 3 5825 4545",
    "sg:postcode":"3629",
    "sg:province":"VIC",
    "sg:tags":[
        "therapy"
    ],
    "wof:name":"Nicole Spedding",
    "wof:placetype":"venue"
},
  "geometry": {"coordinates":[145.35250854500001,-36.3956413269],"type":"Point"}
}