{
  "type": "Feature",
  "properties": {
    "addr:full":"43 Grove Ave Marleston SA 5033",
    "addr:housenumber":"43",
    "addr:postcode":"5033",
    "addr:street":"Grove Ave",
    "iso:country":"AU",
    "sg:address":"43 Grove Ave",
    "sg:city":"Marleston",
    "sg:classifiers":[
        {
            "category":"Professional",
            "subcategory":"Engineering",
            "type":"Services"
        }
    ],
    "sg:phone":"+61 8 8293 5363",
    "sg:postcode":"5033",
    "sg:province":"SA",
    "sg:tags":[
        "precision",
        "engineer"
    ],
    "wof:name":"Precision Engineers Pty Ltd",
    "wof:placetype":"venue"
},
  "geometry": {"coordinates":[138.56280517600001,-34.9469261169],"type":"Point"}
}