{
  "type": "Feature",
  "properties": {
    "iso:country":"AU",
    "sg:address":"Suite 9 2081 Moggill Rd",
    "sg:city":"Kenmore",
    "sg:classifiers":[
        {
            "category":"Health Services",
            "subcategory":"Doctor",
            "type":"Services"
        }
    ],
    "sg:phone":"+61 1300 792 299",
    "sg:postcode":"4069",
    "sg:province":"QLD",
    "sg:tags":[
        "medical",
        "practitioner"
    ],
    "wof:name":"Richardson Angela Dr",
    "wof:placetype":"venue"
},
  "geometry": {"coordinates":[152.93812560999999,-27.5089797974],"type":"Point"}
}