{
  "type": "Feature",
  "properties": {
    "iso:country":"AU",
    "sg:address":"253 Vulture St",
    "sg:city":"South Brisbane",
    "sg:classifiers":[
        {
            "category":"Health Services",
            "subcategory":"Doctor",
            "type":"Services"
        }
    ],
    "sg:phone":"+61 7 3844 5624",
    "sg:postcode":"4101",
    "sg:province":"QLD",
    "sg:tags":[
        "medical",
        "practitioner"
    ],
    "wof:name":"McEvoy David",
    "wof:placetype":"venue"
},
  "geometry": {"coordinates":[153.02403259299999,-27.4829101562],"type":"Point"}
}