{
  "type": "Feature",
  "properties": {
    "addr:full":"84 Stephenson St Richmond VIC 3121",
    "addr:housenumber":"84",
    "addr:postcode":"3121",
    "addr:street":"Stephenson St",
    "iso:country":"AU",
    "sg:address":"84 Stephenson St",
    "sg:city":"Richmond",
    "sg:classifiers":[
        {
            "category":"Professional",
            "subcategory":"Art Services",
            "type":"Services"
        }
    ],
    "sg:phone":"+61 3 9427 8453",
    "sg:postcode":"3121",
    "sg:province":"VIC",
    "sg:tags":[
        "picture",
        "frame",
        "framing"
    ],
    "wof:name":"Colour Square Pty Ltd",
    "wof:placetype":"venue"
},
  "geometry": {"coordinates":[144.99339294399999,-37.8285903931],"type":"Point"}
}