{
  "type": "Feature",
  "properties": {
    "addr:full":"720 London Rd Chandler QLD 4155",
    "addr:housenumber":"720",
    "addr:postcode":"4155",
    "addr:street":"London Rd",
    "iso:country":"AU",
    "sg:address":"720 London Rd",
    "sg:city":"Chandler",
    "sg:classifiers":[
        {
            "category":"Building & Trades",
            "subcategory":"Landscaping Services",
            "type":"Services"
        }
    ],
    "sg:phone":"+61 7 3823 1180",
    "sg:postcode":"4155",
    "sg:province":"QLD",
    "sg:tags":[
        "stump",
        "tree",
        "felling",
        "removal"
    ],
    "wof:name":"A Chomp",
    "wof:placetype":"venue"
},
  "geometry": {"coordinates":[153.16523742699999,-27.5038642883],"type":"Point"}
}