{
  "type": "Feature",
  "properties": {
    "iso:country":"AU",
    "sg:address":"285 Buckley Rd",
    "sg:city":"North Moriac",
    "sg:classifiers":[
        {
            "category":"Farming",
            "subcategory":"Farm",
            "type":"Manufacturing & Wholesale Goods"
        }
    ],
    "sg:phone":"+61 3 5266 1420",
    "sg:postcode":"3240",
    "sg:province":"VIC",
    "sg:tags":[
        "farmer"
    ],
    "wof:name":"Bradley K C, I J & P",
    "wof:placetype":"venue"
},
  "geometry": {"coordinates":[144.10069274899999,-38.1905059814],"type":"Point"}
}