{
  "type": "Feature",
  "properties": {
    "addr:full":"48 River St Dubbo NSW 2830",
    "addr:housenumber":"48",
    "addr:postcode":"2830",
    "addr:street":"River St",
    "iso:country":"AU",
    "sg:address":"48 River St",
    "sg:city":"Dubbo",
    "sg:classifiers":[
        {
            "category":"Farming",
            "subcategory":"Dairy Farm",
            "type":"Manufacturing & Wholesale Goods"
        }
    ],
    "sg:phone":"+61 2 6882 4299",
    "sg:postcode":"2830",
    "sg:province":"NSW",
    "wof:name":"Dairy Farmers",
    "wof:placetype":"venue"
},
  "geometry": {"coordinates":[148.613845825,-32.2341957092],"type":"Point"}
}