{
  "type": "Feature",
  "properties": {
    "addr:full":"Suite 49 Eastlakes Shopping Centre Eastlakes NSW 2018",
    "addr:postcode":"2018",
    "iso:country":"AU",
    "sg:address":"Suite 49",
    "sg:city":"Eastlakes Shopping Centre Eastlakes",
    "sg:classifiers":[
        {
            "category":"Professional",
            "subcategory":"Accounting & Tax Preparation",
            "type":"Services"
        }
    ],
    "sg:phone":"+61 2 9667 3850",
    "sg:postcode":"2018",
    "sg:province":"NSW",
    "sg:tags":[
        "consultant",
        "taxation"
    ],
    "wof:name":"Charter Interlink Taxation Services (Eastlakes) Pty Ltd",
    "wof:placetype":"venue"
},
  "geometry": {"coordinates":[151.21107482900001,-33.9239883423],"type":"Point"}
}