{
  "type": "Feature",
  "properties": {
    "addr:full":"19 Canning St Bega NSW 2550",
    "addr:housenumber":"19",
    "addr:postcode":"2550",
    "addr:street":"Canning St",
    "iso:country":"AU",
    "sg:address":"19 Canning St",
    "sg:city":"Bega",
    "sg:classifiers":[
        {
            "category":"Health Services",
            "subcategory":"Doctor",
            "type":"Services"
        }
    ],
    "sg:phone":"+61 2 6492 4569",
    "sg:postcode":"2550",
    "sg:province":"NSW",
    "sg:tags":[
        "medical",
        "practitioner"
    ],
    "wof:name":"Thomson Andrew C",
    "wof:placetype":"venue"
},
  "geometry": {"coordinates":[149.844436645,-36.6734313965],"type":"Point"}
}