{
  "type": "Feature",
  "properties": {
    "addr:full":"358 Railway Pde Beckenham WA 6107",
    "addr:housenumber":"358",
    "addr:postcode":"6107",
    "addr:street":"Railway Pde",
    "iso:country":"AU",
    "sg:address":"358 Railway Pde",
    "sg:city":"Beckenham",
    "sg:classifiers":[
        {
            "category":"Professional",
            "subcategory":"Accounting & Tax Preparation",
            "type":"Services"
        }
    ],
    "sg:phone":"+61 8 9350 5928",
    "sg:postcode":"6107",
    "sg:province":"WA",
    "sg:tags":[
        "accountant",
        "auditor"
    ],
    "wof:name":"Pabst Wendy M",
    "wof:placetype":"venue"
},
  "geometry": {"coordinates":[115.942070007,-32.0112113953],"type":"Point"}
}