{
  "type": "Feature",
  "properties": {
    "iso:country":"AU",
    "sg:address":"25 McKenzie St",
    "sg:city":"Ceduna",
    "sg:classifiers":[
        {
            "category":"Utilities",
            "subcategory":"Electric",
            "type":"Services"
        }
    ],
    "sg:phone":"+61 8 8625 2046",
    "sg:postcode":"5690",
    "sg:province":"SA",
    "sg:tags":[
        "electrical",
        "contractor"
    ],
    "wof:name":"Michael Ross Electrical",
    "wof:placetype":"venue"
},
  "geometry": {"coordinates":[133.677978516,-32.1251487732],"type":"Point"}
}