{
  "type": "Feature",
  "properties": {
    "addr:full":"70 Pacific Rd Palm Beach NSW 2108",
    "addr:housenumber":"70",
    "addr:postcode":"2108",
    "addr:street":"Pacific Rd",
    "iso:country":"AU",
    "sg:address":"70 Pacific Rd",
    "sg:city":"Palm Beach",
    "sg:classifiers":[
        {
            "category":"Professional",
            "subcategory":"Management & Consulting",
            "type":"Services"
        }
    ],
    "sg:phone":"+61 2 9974 5716",
    "sg:postcode":"2108",
    "sg:province":"NSW",
    "sg:tags":[
        "consultant"
    ],
    "wof:name":"Rydo Pty Ltd",
    "wof:placetype":"venue"
},
  "geometry": {"coordinates":[151.32575988799999,-33.6031684875],"type":"Point"}
}