{
  "type": "Feature",
  "properties": {
    "iso:country":"AU",
    "sg:address":"Torrens Hall Batchelor St",
    "sg:city":"Torrens",
    "sg:classifiers":[
        {
            "category":"Education",
            "subcategory":"Dance Studio",
            "type":"Public Place"
        }
    ],
    "sg:phone":"+61 2 6293 1322",
    "sg:postcode":"2607",
    "sg:province":"ACT",
    "sg:tags":[
        "venue",
        "tuition"
    ],
    "wof:name":"Rachael Strong Dance Academy",
    "wof:placetype":"venue"
},
  "geometry": {"coordinates":[149.08792114299999,-35.3724708557],"type":"Point"}
}