{
  "type": "Feature",
  "properties": {
    "addr:full":"128 Glendale Rd Glendale QLD 4711",
    "addr:housenumber":"128",
    "addr:postcode":"4711",
    "addr:street":"Glendale Rd",
    "iso:country":"AU",
    "sg:address":"128 Glendale Rd",
    "sg:city":"Glendale",
    "sg:classifiers":[
        {
            "category":"Building & Trades",
            "subcategory":"Equipment Rental",
            "type":"Services"
        }
    ],
    "sg:phone":"+61 7 4936 1096",
    "sg:postcode":"4711",
    "sg:province":"QLD",
    "sg:tags":[
        "crane",
        "hire"
    ],
    "wof:name":"Robinson's Crane Hire",
    "wof:placetype":"venue"
},
  "geometry": {"coordinates":[150.48324585,-23.2490444183],"type":"Point"}
}