{
  "type": "Feature",
  "properties": {
    "addr:full":"Cnr Gordon Rd & Kulin Way Mandurah WA 6210",
    "addr:housenumber":"cnr",
    "addr:postcode":"6210",
    "addr:street":"Gordon Rd & Kulin Way",
    "iso:country":"AU",
    "sg:address":"Cnr Gordon Rd & Kulin Way",
    "sg:city":"Mandurah",
    "sg:classifiers":[
        {
            "category":"Farming",
            "subcategory":"Farm & Veterinary Services",
            "type":"Manufacturing & Wholesale Goods"
        }
    ],
    "sg:phone":"+61 13 24 11",
    "sg:postcode":"6210",
    "sg:province":"WA",
    "sg:tags":[
        "irrigation",
        "reticulation",
        "system"
    ],
    "wof:name":"Total Eden",
    "wof:placetype":"venue"
},
  "geometry": {"coordinates":[115.771584,-32.50766],"type":"Point"}
}