{
  "type": "Feature",
  "properties": {
    "addr:full":"70- 72 Loudon St Sandgate QLD 4017",
    "addr:housenumber":"72",
    "addr:postcode":"4017",
    "addr:street":"Loudon St",
    "iso:country":"AU",
    "sg:address":"70- 72 Loudon St",
    "sg:city":"Sandgate",
    "sg:classifiers":[
        {
            "category":"Building & Trades",
            "subcategory":"Cleaning & Sanitation",
            "type":"Services"
        }
    ],
    "sg:phone":"+61 1800 333 198",
    "sg:postcode":"4017",
    "sg:province":"QLD",
    "sg:tags":[
        "industrial",
        "commercial",
        "contractor"
    ],
    "wof:name":"Andrews Group Services",
    "wof:placetype":"venue"
},
  "geometry": {"coordinates":[153.07037353499999,-27.321062088],"type":"Point"}
}