{
  "type": "Feature",
  "properties": {
    "addr:full":"Unit 2/ 360 Lytton Rd Morningside QLD 4170",
    "addr:housenumber":"/ 360",
    "addr:postcode":"4170",
    "addr:street":"Lytton Rd",
    "iso:country":"AU",
    "sg:address":"Unit 2/ 360 Lytton Rd",
    "sg:city":"Morningside",
    "sg:classifiers":[
        {
            "category":"Wholesale",
            "subcategory":"Furniture",
            "type":"Manufacturing & Wholesale Goods"
        }
    ],
    "sg:phone":"+61 7 3217 9344",
    "sg:postcode":"4170",
    "sg:province":"QLD",
    "sg:tags":[
        "wholesaler",
        "mfrs"
    ],
    "wof:name":"Eagle Furniture Qld",
    "wof:placetype":"venue"
},
  "geometry": {"coordinates":[153.07986450199999,-27.4560813904],"type":"Point"}
}