{
  "type": "Feature",
  "properties": {
    "addr:full":"Shop 189 Whitford City Shopng Cntr Hillarys WA 6025",
    "addr:housenumber":"189",
    "addr:postcode":"6025",
    "iso:country":"AU",
    "sg:address":"Shop 189",
    "sg:city":"Whitford City Shopng Cntr Hillarys",
    "sg:classifiers":[
        {
            "category":"Communications",
            "subcategory":"Film & Video Production",
            "type":"Services"
        }
    ],
    "sg:phone":"+61 8 9401 0334",
    "sg:postcode":"6025",
    "sg:province":"WA",
    "sg:tags":[
        "dvd",
        "library"
    ],
    "wof:name":"Whitford City Video",
    "wof:placetype":"venue"
},
  "geometry": {"coordinates":[115.74561309800001,-31.8076992035],"type":"Point"}
}