{
  "type": "Feature",
  "properties": {
    "addr:full":"140 William St East Sydney NSW 2010",
    "addr:housenumber":"140",
    "addr:postcode":"2010",
    "addr:street":"William St East",
    "iso:country":"AU",
    "sg:address":"140 William St",
    "sg:city":"East Sydney",
    "sg:classifiers":[
        {
            "category":"Real Estate",
            "subcategory":"Architect",
            "type":"Services"
        }
    ],
    "sg:phone":"+61 2 9332 1061",
    "sg:postcode":"2010",
    "sg:province":"NSW",
    "wof:name":"D&#039;Ettorre Renato",
    "wof:placetype":"venue"
},
  "geometry": {"coordinates":[151.218475342,-33.8744697571],"type":"Point"}
}