{
  "type": "Feature",
  "properties": {
    "addr:full":"24 Whelan Ave Moorebank NSW 2170",
    "addr:housenumber":"24",
    "addr:postcode":"2170",
    "addr:street":"Whelan Ave",
    "iso:country":"AU",
    "sg:address":"24 Whelan Ave",
    "sg:city":"Moorebank",
    "sg:classifiers":[
        {
            "category":"Arts & Performance",
            "subcategory":"Music",
            "type":"Entertainment"
        }
    ],
    "sg:phone":"+61 2 9824 1223",
    "sg:postcode":"2170",
    "sg:province":"NSW",
    "sg:tags":[
        "mobile",
        "jockey",
        "disc"
    ],
    "wof:name":"Underground Entertainment",
    "wof:placetype":"venue"
},
  "geometry": {"coordinates":[150.945404053,-33.9247627258],"type":"Point"}
}