{
  "type": "Feature",
  "properties": {
    "iso:country":"AU",
    "sg:address":"736 Canterbury Rd",
    "sg:city":"Surrey Hills",
    "sg:classifiers":[
        {
            "category":"Shopping",
            "subcategory":"Antiques",
            "type":"Retail Goods"
        }
    ],
    "sg:phone":"+61 3 9898 6010",
    "sg:postcode":"3127",
    "sg:province":"VIC",
    "sg:tags":[
        "restoration",
        "reproduction"
    ],
    "wof:name":"And So To Bed",
    "wof:placetype":"venue"
},
  "geometry": {"coordinates":[145.10748290999999,-37.8271865845],"type":"Point"}
}