{
  "type": "Feature",
  "properties": {
    "addr:full":"Shop 15, Anson St Plaza Orange NSW 2800",
    "addr:housenumber":"shop 15",
    "addr:postcode":"2800",
    "addr:street":"Anson St Plaza",
    "iso:country":"AU",
    "sg:address":"Shop 15, Anson St",
    "sg:city":"Plaza Orange",
    "sg:classifiers":[
        {
            "category":"Retail",
            "subcategory":"Laundry & Dry Cleaning",
            "type":"Services"
        }
    ],
    "sg:phone":"+61 2 6362 9999",
    "sg:postcode":"2800",
    "sg:province":"NSW",
    "sg:tags":[
        "manicurist"
    ],
    "wof:name":"Image Maker Nails",
    "wof:placetype":"venue"
},
  "geometry": {"coordinates":[149.094680786,-33.3032951355],"type":"Point"}
}