{
  "type": "Feature",
  "properties": {
    "iso:country":"AU",
    "sg:address":"Downie Ave",
    "sg:city":"Bucasia",
    "sg:classifiers":[
        {
            "category":"Autos & Motor Vehicles",
            "subcategory":"Fuel & Gas Station",
            "type":"Retail Goods"
        }
    ],
    "sg:phone":"+61 7 4954 7270",
    "sg:postcode":"4750",
    "sg:province":"QLD",
    "wof:name":"Mobil Bucasia",
    "wof:placetype":"venue"
},
  "geometry": {"coordinates":[149.15711999999999,-21.037153],"type":"Point"}
}