{
  "type": "Feature",
  "properties": {
    "iso:country":"AU",
    "sg:address":"Suite 1/ 400 Chapel Rd",
    "sg:city":"Bankstown",
    "sg:classifiers":[
        {
            "category":"Cafe",
            "type":"Food & Drink"
        }
    ],
    "sg:phone":"+61 2 9709 2901",
    "sg:postcode":"2200",
    "sg:province":"NSW",
    "wof:name":"Lunch Avenue",
    "wof:placetype":"venue"
},
  "geometry": {"coordinates":[151.033615,-33.915531],"type":"Point"}
}