{
  "type": "Feature",
  "properties": {
    "addr:full":"U6/ 6 College St Manly NSW 2095",
    "addr:housenumber":"6",
    "addr:postcode":"2095",
    "addr:street":"U6 /;College St",
    "iso:country":"AU",
    "sg:address":"U6/ 6 College St",
    "sg:city":"Manly",
    "sg:classifiers":[
        {
            "category":"Retail",
            "subcategory":"Event Space",
            "type":"Services"
        }
    ],
    "sg:phone":"+61 2 9976 0699",
    "sg:postcode":"2095",
    "sg:province":"NSW",
    "sg:tags":[
        "function",
        "organiser"
    ],
    "wof:name":"High As A Keyte",
    "wof:placetype":"venue"
},
  "geometry": {"coordinates":[151.292434692,-33.8022918701],"type":"Point"}
}