{
  "type": "Feature",
  "properties": {
    "addr:full":"Cnr Boat Harbour Drv & Main St Pialba QLD 4655",
    "addr:postcode":"4655",
    "addr:street":"Boat Harbour Drv & Main St",
    "iso:country":"AU",
    "sg:address":"Cnr Boat Harbour Drv & Main St",
    "sg:city":"Pialba",
    "sg:classifiers":[
        {
            "category":"Retail",
            "subcategory":"Auto Repair",
            "type":"Services"
        }
    ],
    "sg:phone":"+61 7 4124 2492",
    "sg:postcode":"4655",
    "sg:province":"QLD",
    "sg:tags":[
        "wheel",
        "balancing",
        "alignment"
    ],
    "wof:name":"Fraser Coast Products Pty Ltd",
    "wof:placetype":"venue"
},
  "geometry": {"coordinates":[152.83824200000001,-25.287683],"type":"Point"}
}