{
  "type": "Feature",
  "properties": {
    "iso:country":"AU",
    "sg:address":"12 Tumut St",
    "sg:city":"Cooma",
    "sg:classifiers":[
        {
            "category":"Building & Trades",
            "subcategory":"Construction",
            "type":"Services"
        }
    ],
    "sg:phone":"+61 408 484 165",
    "sg:postcode":"2630",
    "sg:province":"NSW",
    "sg:tags":[
        "earth",
        "excavating",
        "moving",
        "contractor"
    ],
    "wof:name":"Bradley O J & D B",
    "wof:placetype":"venue"
},
  "geometry": {"coordinates":[149.116531372,-36.2361183167],"type":"Point"}
}