{
  "type": "Feature",
  "properties": {
    "iso:country":"AU",
    "sg:address":"53 Martin Pl",
    "sg:city":"Sydney",
    "sg:classifiers":[
        {
            "category":"Cafe",
            "type":"Food & Drink"
        }
    ],
    "sg:phone":"+61 2 8257 1600",
    "sg:postcode":"2000",
    "sg:province":"NSW",
    "wof:name":"Lindt Chocolat Caf\ufffd",
    "wof:placetype":"venue"
},
  "geometry": {"coordinates":[151.210693359,-33.8678741455],"type":"Point"}
}