{
  "type": "Feature",
  "properties": {
    "iso:country":"AU",
    "sg:address":"29 Camfield Drv",
    "sg:city":"Heatherbrae",
    "sg:classifiers":[
        {
            "category":"Train Station",
            "subcategory":"Light Rail",
            "type":"Transportation"
        }
    ],
    "sg:phone":"+61 2 4980 3688",
    "sg:postcode":"2324",
    "sg:province":"NSW",
    "sg:tags":[
        "equipment",
        "energy",
        "solar"
    ],
    "wof:name":"Coastline Pools Spas & Saunas Pty Ltd",
    "wof:placetype":"venue"
},
  "geometry": {"coordinates":[151.74221801799999,-32.7821807861],"type":"Point"}
}