{
  "type": "Feature",
  "properties": {
    "iso:country":"AU",
    "sg:address":"23 Hammett St",
    "sg:city":"Currajong",
    "sg:classifiers":[
        {
            "category":"Home & Garden",
            "subcategory":"Furniture",
            "type":"Retail Goods"
        }
    ],
    "sg:phone":"+61 7 4779 5913",
    "sg:postcode":"4812",
    "sg:province":"QLD",
    "sg:tags":[
        "repair",
        "restoration"
    ],
    "wof:name":"Bond's Motor Trimming & Upholstery",
    "wof:placetype":"venue"
},
  "geometry": {"coordinates":[146.77810700000001,-19.278669],"type":"Point"}
}