{
  "type": "Feature",
  "properties": {
    "addr:full":"264 Reynolds Rd Eltham VIC 3095",
    "addr:housenumber":"264",
    "addr:postcode":"3095",
    "addr:street":"Reynolds Rd",
    "iso:country":"AU",
    "sg:address":"264 Reynolds Rd",
    "sg:city":"Eltham",
    "sg:classifiers":[
        {
            "category":"Utilities",
            "subcategory":"Electric",
            "type":"Services"
        }
    ],
    "sg:phone":"+61 3 9439 2446",
    "sg:postcode":"3095",
    "sg:province":"VIC",
    "sg:tags":[
        "electrical",
        "contractor"
    ],
    "wof:name":"R M W Electrical",
    "wof:placetype":"venue"
},
  "geometry": {"coordinates":[145.172805786,-37.7256126404],"type":"Point"}
}