{
  "type": "Feature",
  "properties": {
    "addr:full":"Shp5/ 476 Portrush Rd Linden Park SA 5065",
    "addr:housenumber":"476",
    "addr:postcode":"5065",
    "addr:street":"Portrush Rd",
    "iso:country":"AU",
    "sg:address":"Shp5/ 476 Portrush Rd",
    "sg:city":"Linden Park",
    "sg:classifiers":[
        {
            "category":"Restaurant",
            "type":"Food & Drink"
        }
    ],
    "sg:phone":"+61 8 8379 8888",
    "sg:postcode":"5065",
    "sg:province":"SA",
    "wof:name":"Burnside Food & Wine Noodle Bistro",
    "wof:placetype":"venue"
},
  "geometry": {"coordinates":[138.64312744099999,-34.9460105896],"type":"Point"}
}