{
  "type": "Feature",
  "properties": {
    "addr:full":"U4- 101 Belmont Ave Belmont WA 6104",
    "addr:housenumber":"101",
    "addr:postcode":"6104",
    "addr:street":"U4;Belmont Ave",
    "iso:country":"AU",
    "sg:address":"U4- 101 Belmont Ave",
    "sg:city":"Belmont",
    "sg:classifiers":[
        {
            "category":"Building & Trades",
            "subcategory":"Construction",
            "type":"Services"
        }
    ],
    "sg:phone":"+61 8 9479 7677",
    "sg:postcode":"6104",
    "sg:province":"WA",
    "sg:tags":[
        "installation",
        "air conditioning"
    ],
    "wof:name":"Ableair",
    "wof:placetype":"venue"
},
  "geometry": {"coordinates":[115.925613403,-31.9591960907],"type":"Point"}
}