{
  "type": "Feature",
  "properties": {
    "addr:full":"189 Phillip St Waterloo NSW 2017",
    "addr:housenumber":"189",
    "addr:postcode":"2017",
    "addr:street":"Phillip St",
    "iso:country":"AU",
    "sg:address":"189 Phillip St",
    "sg:city":"Waterloo",
    "sg:classifiers":[
        {
            "category":"Professional",
            "subcategory":"Business Services",
            "type":"Services"
        }
    ],
    "sg:phone":"+61 2 9310 3431",
    "sg:postcode":"2017",
    "sg:province":"NSW",
    "sg:tags":[
        "fashion",
        "agent"
    ],
    "wof:name":"John Groves Fashion Agencies",
    "wof:placetype":"venue"
},
  "geometry": {"coordinates":[151.21144104000001,-33.8968467712],"type":"Point"}
}