{
  "type": "Feature",
  "properties": {
    "iso:country":"AU",
    "sg:address":"18 Goulburn St",
    "sg:city":"Sydney",
    "sg:classifiers":[
        {
            "category":"Restaurant",
            "type":"Food & Drink"
        }
    ],
    "sg:phone":"+61 2 9267 2586",
    "sg:postcode":"2000",
    "sg:province":"NSW",
    "wof:name":"B.B.Q. King Restaurant",
    "wof:placetype":"venue"
},
  "geometry": {"coordinates":[151.20501709000001,-33.8775138855],"type":"Point"}
}