{
  "type": "Feature",
  "properties": {
    "addr:full":"260 South Pine Rd Enoggera QLD 4051",
    "addr:housenumber":"260",
    "addr:postcode":"4051",
    "addr:street":"South Pine Rd",
    "iso:country":"AU",
    "sg:address":"260 South Pine Rd",
    "sg:city":"Enoggera",
    "sg:classifiers":[
        {
            "category":"Banks & Credit Unions",
            "subcategory":"Bank",
            "type":"Services"
        }
    ],
    "sg:phone":"+61 7 3355 5043",
    "sg:postcode":"4051",
    "sg:province":"QLD",
    "sg:tags":[
        "castor"
    ],
    "wof:name":"L & M Equipment",
    "wof:placetype":"venue"
},
  "geometry": {"coordinates":[152.993682861,-27.4175167084],"type":"Point"}
}