{
  "type": "Feature",
  "properties": {
    "iso:country":"AU",
    "sg:address":"Suite 404, 379 - 383 Pitt St",
    "sg:city":"Sydney",
    "sg:classifiers":[
        {
            "category":"Real Estate",
            "subcategory":"Real Estate Agent",
            "type":"Services"
        }
    ],
    "sg:phone":"+61 2 9283 6280",
    "sg:postcode":"2000",
    "sg:province":"NSW",
    "wof:name":"Drake Property Pty Ltd",
    "wof:placetype":"venue"
},
  "geometry": {"coordinates":[151.20765685999999,-33.8765296936],"type":"Point"}
}