{
  "type": "Feature",
  "properties": {
    "addr:full":"Level 1, 33 Bromley Rd Emu Plains NSW 2750",
    "addr:housenumber":"33",
    "addr:postcode":"2750",
    "addr:street":"Bromley Rd",
    "iso:country":"AU",
    "sg:address":"Level 1, 33 Bromley Rd",
    "sg:city":"Emu Plains",
    "sg:classifiers":[
        {
            "category":"Communications",
            "type":"Services"
        }
    ],
    "sg:phone":"+61 2 4735 7000",
    "sg:postcode":"2750",
    "sg:province":"NSW",
    "sg:tags":[
        "data"
    ],
    "wof:name":"Planet Netcom",
    "wof:placetype":"venue"
},
  "geometry": {"coordinates":[150.649932861,-33.7438201904],"type":"Point"}
}