{
  "type": "Feature",
  "properties": {
    "addr:full":"Unit 4 18- 28 Gray St Kilkenny SA 5009",
    "addr:housenumber":"18 28",
    "addr:postcode":"5009",
    "addr:street":"Gray St",
    "iso:country":"AU",
    "sg:address":"Unit 4 18- 28 Gray St",
    "sg:city":"Kilkenny",
    "sg:classifiers":[
        {
            "category":"Building & Trades",
            "subcategory":"Construction",
            "type":"Services"
        }
    ],
    "sg:phone":"+61 8 8243 2111",
    "sg:postcode":"5009",
    "sg:province":"SA",
    "sg:tags":[
        "roof"
    ],
    "wof:name":"Hi-Tech Roofing Services Pty Ltd",
    "wof:placetype":"venue"
},
  "geometry": {"coordinates":[138.55218505900001,-34.8727264404],"type":"Point"}
}