{
  "type": "Feature",
  "properties": {
    "addr:full":"96- 98 Mooringe Ave North Plympton SA 5037",
    "addr:housenumber":"98",
    "addr:postcode":"5037",
    "addr:street":"Mooringe Ave North",
    "iso:country":"AU",
    "sg:address":"96- 98 Mooringe Ave",
    "sg:city":"North Plympton",
    "sg:classifiers":[
        {
            "category":"Home & Garden",
            "subcategory":"Home Furnishings",
            "type":"Retail Goods"
        }
    ],
    "sg:phone":"+61 13 25 43",
    "sg:postcode":"5037",
    "sg:province":"SA",
    "sg:tags":[
        "shower",
        "screen"
    ],
    "wof:name":"Regency Shower Screens",
    "wof:placetype":"venue"
},
  "geometry": {"coordinates":[138.542312622,-34.9601783752],"type":"Point"}
}