{
  "type": "Feature",
  "properties": {
    "addr:full":"Safeway Shopping Plaza 310 High St Shepparton VIC 3630",
    "addr:housenumber":"310",
    "addr:postcode":"3630",
    "addr:street":"High St",
    "iso:country":"AU",
    "sg:address":"Safeway Shopping Plaza 310 High St",
    "sg:city":"Shepparton",
    "sg:classifiers":[
        {
            "category":"Fast Food",
            "type":"Food & Drink"
        }
    ],
    "sg:phone":"+61 3 5831 2593",
    "sg:postcode":"3630",
    "sg:province":"VIC",
    "sg:tags":[
        "away",
        "take"
    ],
    "wof:name":"Shepparton Charcoal Chicken",
    "wof:placetype":"venue"
},
  "geometry": {"coordinates":[145.412033081,-36.3829536438],"type":"Point"}
}