{
  "type": "Feature",
  "properties": {
    "iso:country":"AU",
    "sg:address":"Busy Bee Complex Suite 6/ 52 Minorie Drv",
    "sg:city":"Toormina",
    "sg:classifiers":[
        {
            "category":"Shopping",
            "subcategory":"Party Supplies",
            "type":"Retail Goods"
        }
    ],
    "sg:phone":"+61 2 6653 3082",
    "sg:postcode":"2452",
    "sg:province":"NSW",
    "sg:tags":[
        "hire",
        "costume"
    ],
    "wof:name":"Broadway",
    "wof:placetype":"venue"
},
  "geometry": {"coordinates":[153.094391,-30.354893],"type":"Point"}
}