{
  "type": "Feature",
  "properties": {
    "iso:country":"AU",
    "sg:address":"22 Oval Ave",
    "sg:city":"Woodville South",
    "sg:classifiers":[
        {
            "category":"Utilities",
            "subcategory":"Natural Gas",
            "type":"Services"
        }
    ],
    "sg:phone":"+61 8 8268 7447",
    "sg:postcode":"5011",
    "sg:province":"SA",
    "sg:tags":[
        "solid",
        "plasterer"
    ],
    "wof:name":"Androvic Plastering",
    "wof:placetype":"venue"
},
  "geometry": {"coordinates":[138.53692626899999,-34.8862304688],"type":"Point"}
}