{
  "type": "Feature",
  "properties": {
    "addr:full":"10-12 Adolph St Richmond VIC 3121",
    "addr:postcode":"10-12;3121",
    "addr:street":"Adolph St",
    "iso:country":"AU",
    "sg:address":"10-12 Adolph St",
    "sg:city":"Richmond",
    "sg:classifiers":[
        {
            "category":"Professional",
            "subcategory":"Computer Services",
            "type":"Services"
        }
    ],
    "sg:phone":"+61 3 9299 1999",
    "sg:postcode":"3121",
    "sg:province":"VIC",
    "sg:tags":[
        "tele-communications",
        "consultant"
    ],
    "wof:name":"Commcord Communications",
    "wof:placetype":"venue"
},
  "geometry": {"coordinates":[144.996292114,-37.8268508911],"type":"Point"}
}