{
  "type": "Feature",
  "properties": {
    "addr:full":"54 Ragaffun Drv Hallett Cove SA 5158",
    "addr:housenumber":"54",
    "addr:postcode":"5158",
    "addr:street":"Ragaffun Drv",
    "iso:country":"AU",
    "sg:address":"54 Ragaffun Drv",
    "sg:city":"Hallett Cove",
    "sg:classifiers":[
        {
            "category":"Building & Trades",
            "subcategory":"Pest Control",
            "type":"Services"
        }
    ],
    "sg:phone":"+61 416 008 775",
    "sg:postcode":"5158",
    "sg:province":"SA",
    "sg:tags":[
        "breastfeeding",
        "support"
    ],
    "wof:name":"Jill Bruce",
    "wof:placetype":"venue"
},
  "geometry": {"coordinates":[138.52340698200001,-35.0731048584],"type":"Point"}
}