{
  "type": "Feature",
  "properties": {
    "addr:full":"Unit 2, 112- 114 Batt St Penrith NSW 2750",
    "addr:housenumber":"112 114",
    "addr:postcode":"2750",
    "addr:street":"Batt St",
    "iso:country":"AU",
    "sg:address":"Unit 2, 112- 114 Batt St",
    "sg:city":"Penrith",
    "sg:classifiers":[
        {
            "category":"Home & Garden",
            "subcategory":"Hardware",
            "type":"Retail Goods"
        }
    ],
    "sg:phone":"+61 2 4721 7855",
    "sg:postcode":"2750",
    "sg:province":"NSW",
    "sg:tags":[
        "plumber",
        "supply"
    ],
    "wof:name":"Plumbers Supplies",
    "wof:placetype":"venue"
},
  "geometry": {"coordinates":[150.68226623499999,-33.7675895691],"type":"Point"}
}