{
  "type": "Feature",
  "properties": {
    "addr:full":"Saleyards Rd Deniliquin NSW 2710",
    "addr:postcode":"2710",
    "addr:street":"Saleyards Rd",
    "iso:country":"AU",
    "sg:address":"Saleyards Rd",
    "sg:city":"Deniliquin",
    "sg:classifiers":[
        {
            "category":"Farming",
            "subcategory":"Crops",
            "type":"Manufacturing & Wholesale Goods"
        }
    ],
    "sg:phone":"+61 3 5881 2499",
    "sg:postcode":"2710",
    "sg:province":"NSW",
    "sg:tags":[
        "miller",
        "rice"
    ],
    "wof:name":"Ricegrowers' Co-Operative Limited",
    "wof:placetype":"venue"
},
  "geometry": {"coordinates":[144.951446533,-35.5481796265],"type":"Point"}
}