{
  "type": "Feature",
  "properties": {
    "addr:full":"29 Barklya Pl Marsden QLD 4132",
    "addr:housenumber":"29",
    "addr:postcode":"4132",
    "addr:street":"Barklya Pl",
    "iso:country":"AU",
    "sg:address":"29 Barklya Pl",
    "sg:city":"Marsden",
    "sg:classifiers":[
        {
            "category":"Personal",
            "subcategory":"Beauty Salon",
            "type":"Services"
        }
    ],
    "sg:phone":"+61 7 3805 5145",
    "sg:postcode":"4132",
    "sg:province":"QLD",
    "sg:tags":[
        "hairdresser"
    ],
    "wof:name":"Slender You Hairdressing",
    "wof:placetype":"venue"
},
  "geometry": {"coordinates":[153.11378479000001,-27.6799468994],"type":"Point"}
}