{
  "type": "Feature",
  "properties": {
    "addr:full":"10/288- 302 Lawrence St Alexandria NSW 2015",
    "addr:housenumber":"10 / 288 302",
    "addr:postcode":"2015",
    "addr:street":"Lawrence St",
    "iso:country":"AU",
    "sg:address":"10/288- 302 Lawrence St",
    "sg:city":"Alexandria",
    "sg:classifiers":[
        {
            "category":"Social Services",
            "subcategory":"Retirement Home",
            "type":"Services"
        }
    ],
    "sg:phone":"+61 2 9519 1777",
    "sg:postcode":"2015",
    "sg:province":"NSW",
    "sg:tags":[
        "t-shirt",
        "supplier"
    ],
    "wof:name":"Freelance Corporate",
    "wof:placetype":"venue"
},
  "geometry": {"coordinates":[151.18971252399999,-33.9073677063],"type":"Point"}
}