{
  "type": "Feature",
  "properties": {
    "addr:full":"61 Simpson Drv Padbury WA 6025",
    "addr:housenumber":"61",
    "addr:postcode":"6025",
    "addr:street":"Simpson Drv",
    "iso:country":"AU",
    "sg:address":"61 Simpson Drv",
    "sg:city":"Padbury",
    "sg:classifiers":[
        {
            "category":"Building & Trades",
            "subcategory":"Construction",
            "type":"Services"
        }
    ],
    "sg:phone":"+61 411 871 085",
    "sg:postcode":"6025",
    "sg:province":"WA",
    "sg:tags":[
        "fitting",
        "line",
        "electric",
        "power"
    ],
    "wof:name":"Cable Power",
    "wof:placetype":"venue"
},
  "geometry": {"coordinates":[115.768913269,-31.802362442],"type":"Point"}
}