{
  "type": "Feature",
  "properties": {
    "addr:full":"156 Newtown Rd Wetherill Park NSW 2164",
    "addr:housenumber":"156",
    "addr:postcode":"2164",
    "addr:street":"Newtown Rd",
    "iso:country":"AU",
    "sg:address":"156 Newtown Rd",
    "sg:city":"Wetherill Park",
    "sg:classifiers":[
        {
            "category":"Professional",
            "type":"Services"
        }
    ],
    "sg:phone":"+61 2 9756 0886",
    "sg:postcode":"2164",
    "sg:province":"NSW",
    "sg:tags":[
        "packaging",
        "filling",
        "assembling"
    ],
    "wof:name":"Express Packaging Pty Ltd",
    "wof:placetype":"venue"
},
  "geometry": {"coordinates":[150.89126586899999,-33.8389015198],"type":"Point"}
}