{
  "type": "Feature",
  "properties": {
    "addr:full":"8 Sport St Kedron QLD 4031",
    "addr:housenumber":"8",
    "addr:postcode":"4031",
    "addr:street":"Sport St",
    "iso:country":"AU",
    "sg:address":"8 Sport St",
    "sg:city":"Kedron",
    "sg:classifiers":[
        {
            "category":"Professional",
            "subcategory":"Art Services",
            "type":"Services"
        }
    ],
    "sg:phone":"+61 422 271 025",
    "sg:postcode":"4031",
    "sg:province":"QLD",
    "sg:tags":[
        "decorator",
        "painter"
    ],
    "wof:name":"Matherson K B",
    "wof:placetype":"venue"
},
  "geometry": {"coordinates":[153.03225699999999,-27.400015],"type":"Point"}
}