{
  "type": "Feature",
  "properties": {
    "addr:full":"2 Grenda Drv Mill Park VIC 3082",
    "addr:housenumber":"2",
    "addr:postcode":"3082",
    "addr:street":"Grenda Drv",
    "iso:country":"AU",
    "sg:address":"2 Grenda Drv",
    "sg:city":"Mill Park",
    "sg:classifiers":[
        {
            "category":"Fast Food",
            "type":"Food & Drink"
        }
    ],
    "sg:phone":"+61 3 9436 4777",
    "sg:postcode":"3082",
    "sg:province":"VIC",
    "sg:tags":[
        "away",
        "take"
    ],
    "wof:name":"Shark Shack Fish & Chips",
    "wof:placetype":"venue"
},
  "geometry": {"coordinates":[145.047271728,-37.6679344177],"type":"Point"}
}