{
  "type": "Feature",
  "properties": {
    "iso:country":"AU",
    "sg:address":"39 Portland Pde",
    "sg:city":"Redland Bay",
    "sg:classifiers":[
        {
            "category":"Autos & Motor Vehicles",
            "subcategory":"Auto Supplies",
            "type":"Retail Goods"
        }
    ],
    "sg:phone":"+61 7 3206 8419",
    "sg:postcode":"4165",
    "sg:province":"QLD",
    "sg:tags":[
        "camper-trailers",
        "caravan",
        "equipment"
    ],
    "wof:name":"Johnnos Camper Trailers Brisbane Bayside South",
    "wof:placetype":"venue"
},
  "geometry": {"coordinates":[153.289306641,-27.6263103485],"type":"Point"}
}