{
  "type": "Feature",
  "properties": {
    "addr:full":"Halidon St Ingle Farm SA 5098",
    "addr:postcode":"5098",
    "addr:street":"Halidon St",
    "iso:country":"AU",
    "sg:address":"Halidon St",
    "sg:city":"Ingle Farm",
    "sg:classifiers":[
        {
            "category":"Education",
            "subcategory":"School",
            "type":"Public Place"
        }
    ],
    "sg:phone":"+61 8 8264 5166",
    "sg:postcode":"5098",
    "sg:province":"SA",
    "sg:tags":[
        "state",
        "except",
        "nsw"
    ],
    "wof:name":"Ingle Farm East Primary",
    "wof:placetype":"venue"
},
  "geometry": {"coordinates":[138.65223693900001,-34.8346061707],"type":"Point"}
}