{
  "type": "Feature",
  "properties": {
    "addr:full":"19 Mill St Horsham VIC 3400",
    "addr:housenumber":"19",
    "addr:postcode":"3400",
    "addr:street":"Mill St",
    "iso:country":"AU",
    "sg:address":"19 Mill St",
    "sg:city":"Horsham",
    "sg:classifiers":[
        {
            "category":"Utilities",
            "subcategory":"Fuel Oil & Lpg",
            "type":"Services"
        }
    ],
    "sg:phone":"+61 3 5382 5155",
    "sg:postcode":"3400",
    "sg:province":"VIC",
    "sg:tags":[
        "merchant"
    ],
    "wof:name":"Balgee Oil Pty Ltd",
    "wof:placetype":"venue"
},
  "geometry": {"coordinates":[142.19993591299999,-36.7065048218],"type":"Point"}
}