{
  "type": "Feature",
  "properties": {
    "addr:full":"73 Mount Gambier Rd Millicent SA 5280",
    "addr:housenumber":"73",
    "addr:postcode":"5280",
    "addr:street":"Mount Gambier Rd",
    "iso:country":"AU",
    "sg:address":"73 Mount Gambier Rd",
    "sg:city":"Millicent",
    "sg:classifiers":[
        {
            "category":"Professional",
            "subcategory":"Accounting & Tax Preparation",
            "type":"Services"
        }
    ],
    "sg:phone":"+61 8 8733 3199",
    "sg:postcode":"5280",
    "sg:province":"SA",
    "sg:tags":[
        "consultant",
        "taxation"
    ],
    "wof:name":"H&R Block",
    "wof:placetype":"venue"
},
  "geometry": {"coordinates":[140.360062,-37.603672],"type":"Point"}
}