{
  "type": "Feature",
  "properties": {
    "addr:full":"25 Eastment St Northcote VIC 3070",
    "addr:housenumber":"25",
    "addr:postcode":"3070",
    "addr:street":"Eastment St",
    "iso:country":"AU",
    "sg:address":"25 Eastment St",
    "sg:city":"Northcote",
    "sg:classifiers":[
        {
            "category":"Building & Trades",
            "subcategory":"Construction",
            "type":"Services"
        }
    ],
    "sg:phone":"+61 3 9489 1366",
    "sg:postcode":"3070",
    "sg:province":"VIC",
    "sg:tags":[
        "polishing",
        "sanding",
        "floor"
    ],
    "wof:name":"Greensborough Floor Surfacing Co Ltd",
    "wof:placetype":"venue"
},
  "geometry": {"coordinates":[144.997467,-37.774017],"type":"Point"}
}