{
  "type": "Feature",
  "properties": {
    "addr:full":"21 Webber Pde Keilor East VIC 3033",
    "addr:housenumber":"21",
    "addr:postcode":"3033",
    "addr:street":"Webber Pde",
    "iso:country":"AU",
    "sg:address":"21 Webber Pde",
    "sg:city":"Keilor East",
    "sg:classifiers":[
        {
            "category":"Building & Trades",
            "subcategory":"Equipment Rental",
            "type":"Services"
        }
    ],
    "sg:phone":"+61 3 9336 3166",
    "sg:postcode":"3033",
    "sg:province":"VIC",
    "sg:tags":[
        "builder",
        "contractor"
    ],
    "wof:name":"Aluminium Scaffolds (Vic) Pty Ltd",
    "wof:placetype":"venue"
},
  "geometry": {"coordinates":[144.85557600000001,-37.735622],"type":"Point"}
}