{
  "type": "Feature",
  "properties": {
    "addr:full":"Gisborne St Wellington NSW 2820",
    "addr:postcode":"2820",
    "addr:street":"Gisborne St",
    "iso:country":"AU",
    "sg:address":"Gisborne St",
    "sg:city":"Wellington",
    "sg:classifiers":[
        {
            "category":"Organizations",
            "subcategory":"Community Association",
            "type":"Services"
        }
    ],
    "sg:phone":"+61 2 6845 1100",
    "sg:postcode":"2820",
    "sg:province":"NSW",
    "sg:tags":[
        "organisation",
        "family",
        "welfare"
    ],
    "wof:name":"Home Care Service Of NSW",
    "wof:placetype":"venue"
},
  "geometry": {"coordinates":[148.94433593799999,-32.5493965149],"type":"Point"}
}