{
  "type": "Feature",
  "properties": {
    "iso:country":"AU",
    "sg:address":"131 North St",
    "sg:city":"Toowoomba",
    "sg:classifiers":[
        {
            "category":"Professional",
            "subcategory":"Business Services",
            "type":"Services"
        }
    ],
    "sg:phone":"+61 416 298 466",
    "sg:postcode":"4350",
    "sg:province":"QLD",
    "sg:tags":[
        "record",
        "management",
        "storage"
    ],
    "wof:name":"Info Stor",
    "wof:placetype":"venue"
},
  "geometry": {"coordinates":[151.928696,-27.538311],"type":"Point"}
}