{
  "type": "Feature",
  "properties": {
    "addr:full":"Lvl 1, 605- 9 Doncaster Rd Doncaster VIC 3108",
    "addr:housenumber":"605 9",
    "addr:postcode":"3108",
    "addr:street":"Doncaster Rd",
    "iso:country":"AU",
    "sg:address":"Lvl 1, 605- 9 Doncaster Rd",
    "sg:city":"Doncaster",
    "sg:classifiers":[
        {
            "category":"Banks & Credit Unions",
            "subcategory":"Financial Services",
            "type":"Services"
        }
    ],
    "sg:phone":"+61 3 9840 1166",
    "sg:postcode":"3108",
    "sg:province":"VIC",
    "sg:tags":[
        "planning"
    ],
    "wof:name":"Rhonda Martins Financial Services",
    "wof:placetype":"venue"
},
  "geometry": {"coordinates":[145.123703003,-37.7873344421],"type":"Point"}
}