{
  "type": "Feature",
  "properties": {
    "addr:full":"32 Cowper St Granville NSW 2142",
    "addr:housenumber":"32",
    "addr:postcode":"2142",
    "addr:street":"Cowper St",
    "iso:country":"AU",
    "sg:address":"32 Cowper St",
    "sg:city":"Granville",
    "sg:classifiers":[
        {
            "category":"Retail",
            "subcategory":"Auto Repair",
            "type":"Services"
        }
    ],
    "sg:phone":"+61 2 9897 9166",
    "sg:postcode":"2142",
    "sg:province":"NSW",
    "sg:tags":[
        "repairer",
        "motor",
        "engineer"
    ],
    "wof:name":"A.M. Automatics",
    "wof:placetype":"venue"
},
  "geometry": {"coordinates":[151.013305664,-33.8320808411],"type":"Point"}
}