{
  "type": "Feature",
  "properties": {
    "addr:full":"2 Bridge St Stanmore NSW 2048",
    "addr:housenumber":"2",
    "addr:postcode":"2048",
    "addr:street":"Bridge St",
    "iso:country":"AU",
    "sg:address":"2 Bridge St",
    "sg:city":"Stanmore",
    "sg:classifiers":[
        {
            "category":"Home & Garden",
            "subcategory":"Hardware",
            "type":"Retail Goods"
        }
    ],
    "sg:phone":"+61 2 9937 2122",
    "sg:postcode":"2048",
    "sg:province":"NSW",
    "sg:tags":[
        "product",
        "treatment",
        "floor"
    ],
    "wof:name":"Slipgard Australia Pty Ltd",
    "wof:placetype":"venue"
},
  "geometry": {"coordinates":[151.18588299999999,-33.900429],"type":"Point"}
}