{
  "type": "Feature",
  "properties": {
    "addr:full":"7 Bassett St East, Mona Vale NSW 2103",
    "addr:housenumber":"7",
    "addr:postcode":"2103",
    "addr:street":"Bassett St East",
    "iso:country":"AU",
    "sg:address":"7 Bassett St",
    "sg:city":"East, Mona Vale",
    "sg:classifiers":[
        {
            "category":"Building & Trades",
            "subcategory":"Construction",
            "type":"Services"
        }
    ],
    "sg:phone":"+61 2 9999 0545",
    "sg:postcode":"2103",
    "sg:province":"NSW",
    "sg:tags":[
        "contractor"
    ],
    "wof:name":"B & K Beuzeville",
    "wof:placetype":"venue"
},
  "geometry": {"coordinates":[151.31404113799999,-33.6746520996],"type":"Point"}
}