{
  "type": "Feature",
  "properties": {
    "iso:country":"AU",
    "sg:address":"PO Box 247",
    "sg:city":"West Burleigh",
    "sg:classifiers":[
        {
            "category":"Professional",
            "subcategory":"Printing & Photocopies",
            "type":"Services"
        }
    ],
    "sg:phone":"+61 7 5534 8694",
    "sg:postcode":"4219",
    "sg:province":"QLD",
    "sg:tags":[
        "trophy"
    ],
    "wof:name":"Surfside Engraving",
    "wof:placetype":"venue"
},
  "geometry": {"coordinates":[153.44146728499999,-28.112159729],"type":"Point"}
}