{
  "type": "Feature",
  "properties": {
    "addr:full":"89 Francis Greenway Drv Cherrybrook NSW 2126",
    "addr:housenumber":"89",
    "addr:postcode":"2126",
    "addr:street":"Francis Greenway Drv",
    "iso:country":"AU",
    "sg:address":"89 Francis Greenway Drv",
    "sg:city":"Cherrybrook",
    "sg:classifiers":[
        {
            "category":"Personal",
            "subcategory":"Massage",
            "type":"Services"
        }
    ],
    "sg:phone":"+61 2 9484 3169",
    "sg:postcode":"2126",
    "sg:province":"NSW",
    "sg:tags":[
        "therapy"
    ],
    "wof:name":"Jacka Sylvia",
    "wof:placetype":"venue"
},
  "geometry": {"coordinates":[151.05276489299999,-33.7235298157],"type":"Point"}
}