{
  "type": "Feature",
  "properties": {
    "iso:country":"AU",
    "sg:address":"80 Torquay Rd",
    "sg:city":"Pialba",
    "sg:classifiers":[
        {
            "category":"Home & Garden",
            "subcategory":"Household Appliances",
            "type":"Retail Goods"
        }
    ],
    "sg:phone":"+61 7 4128 2111",
    "sg:postcode":"4655",
    "sg:province":"QLD",
    "sg:tags":[
        "equipment",
        "gas"
    ],
    "wof:name":"Gas Cylinder The",
    "wof:placetype":"venue"
},
  "geometry": {"coordinates":[152.846695,-25.28492],"type":"Point"}
}