{
  "type": "Feature",
  "properties": {
    "iso:country":"AU",
    "sg:address":"Maroondah Hwy",
    "sg:city":"Croydon",
    "sg:classifiers":[
        {
            "category":"Food & Beverages",
            "subcategory":"Liquor & Beverages",
            "type":"Retail Goods"
        }
    ],
    "sg:phone":"+61 3 9870 4928",
    "sg:postcode":"3136",
    "sg:province":"VIC",
    "sg:tags":[
        "store"
    ],
    "wof:name":"Mayerling Cellars",
    "wof:placetype":"venue"
},
  "geometry": {"coordinates":[145.274002075,-37.7874526978],"type":"Point"}
}