{
  "type": "Feature",
  "properties": {
    "iso:country":"AU",
    "sg:address":"1024 Gold Coast Springbrook Rd",
    "sg:city":"Neranwood",
    "sg:classifiers":[
        {
            "category":"Retail",
            "subcategory":"Event Space",
            "type":"Services"
        }
    ],
    "sg:phone":"+61 7 5530 3400",
    "sg:postcode":"4213",
    "sg:province":"QLD",
    "sg:tags":[
        "venue",
        "reception",
        "wedding"
    ],
    "wof:name":"Polly's Country Kitchen & Neranwood Function Centre",
    "wof:placetype":"venue"
},
  "geometry": {"coordinates":[153.323760986,-28.1010551453],"type":"Point"}
}