{
  "type": "Feature",
  "properties": {
    "iso:country":"AU",
    "sg:address":"26 Nelson Rd",
    "sg:city":"North Strathfield",
    "sg:classifiers":[
        {
            "category":"Retail",
            "subcategory":"Repair Shop",
            "type":"Services"
        }
    ],
    "sg:phone":"+61 418 481 055",
    "sg:postcode":"2137",
    "sg:province":"NSW",
    "sg:tags":[
        "leadlights"
    ],
    "wof:name":"Laios Leadlights",
    "wof:placetype":"venue"
},
  "geometry": {"coordinates":[151.09144592300001,-33.8610420227],"type":"Point"}
}