{
  "type": "Feature",
  "properties": {
    "addr:full":"Underwood Rd Rochedale QLD 4123",
    "addr:postcode":"4123",
    "addr:street":"Underwood Rd",
    "iso:country":"AU",
    "sg:address":"Underwood Rd",
    "sg:city":"Rochedale",
    "sg:classifiers":[
        {
            "category":"Personal",
            "subcategory":"Beauty Salon",
            "type":"Services"
        }
    ],
    "sg:phone":"+61 7 3341 5623",
    "sg:postcode":"4123",
    "sg:province":"QLD",
    "sg:tags":[
        "hairdresser"
    ],
    "wof:name":"Medina Marie Hair & Beauty Salon",
    "wof:placetype":"venue"
},
  "geometry": {"coordinates":[153.117263794,-27.5947475433],"type":"Point"}
}