{
  "type": "Feature",
  "properties": {
    "addr:full":"Unit 4/ 1201 The Horsley Drive Wetherill Park NSW 2164",
    "addr:housenumber":"/ 1201",
    "addr:postcode":"2164",
    "addr:street":"The Horsley Drive",
    "iso:country":"AU",
    "sg:address":"Unit 4/ 1201 The Horsley Drive",
    "sg:city":"Wetherill Park",
    "sg:classifiers":[
        {
            "category":"Retail",
            "subcategory":"Repair Shop",
            "type":"Services"
        }
    ],
    "sg:phone":"+61 2 9756 0110",
    "sg:postcode":"2164",
    "sg:province":"NSW",
    "sg:tags":[
        "maintenance",
        "pool",
        "swimming"
    ],
    "wof:name":"Stroud Pool & Spa Equipment",
    "wof:placetype":"venue"
},
  "geometry": {"coordinates":[150.894073486,-33.8518638611],"type":"Point"}
}