{
  "type": "Feature",
  "properties": {
    "addr:full":"62a Belair Rd Hawthorn SA 5062",
    "addr:housenumber":"62a",
    "addr:postcode":"5062",
    "addr:street":"Belair Rd",
    "iso:country":"AU",
    "sg:address":"62a Belair Rd",
    "sg:city":"Hawthorn",
    "sg:classifiers":[
        {
            "category":"Health Services",
            "subcategory":"Chiropractor",
            "type":"Services"
        }
    ],
    "sg:phone":"+61 8 8373 0488",
    "sg:postcode":"5062",
    "sg:province":"SA",
    "wof:name":"Kingswood Chiropractic Clinic",
    "wof:placetype":"venue"
},
  "geometry": {"coordinates":[138.608688355,-34.9683227539],"type":"Point"}
}