{
  "type": "Feature",
  "properties": {
    "addr:full":"209n Pakington Rd Walcha NSW 2354",
    "addr:housenumber":"209n",
    "addr:postcode":"2354",
    "addr:street":"Pakington Rd",
    "iso:country":"AU",
    "sg:address":"209n Pakington Rd",
    "sg:city":"Walcha",
    "sg:classifiers":[
        {
            "category":"Insurance",
            "subcategory":"Insurance Agent",
            "type":"Services"
        }
    ],
    "sg:phone":"+61 2 6779 1076",
    "sg:postcode":"2354",
    "sg:province":"NSW",
    "sg:tags":[
        "wool",
        "broker"
    ],
    "wof:name":"TWG Wool",
    "wof:placetype":"venue"
},
  "geometry": {"coordinates":[151.595825195,-30.9844818115],"type":"Point"}
}