{
  "type": "Feature",
  "properties": {
    "addr:full":"Shop 16 Wanneroo Shopping Centre Wanneroo WA 6065",
    "addr:housenumber":"shop 16",
    "addr:postcode":"6065",
    "addr:street":"Wanneroo Shopping",
    "iso:country":"AU",
    "sg:address":"Shop 16",
    "sg:city":"Wanneroo Shopping Centre Wanneroo",
    "sg:classifiers":[
        {
            "category":"Government",
            "subcategory":"Post Office",
            "type":"Public Place"
        }
    ],
    "sg:phone":"+61 13 13 18",
    "sg:postcode":"6065",
    "sg:province":"WA",
    "sg:tags":[
        "postal"
    ],
    "wof:name":"Australia Post",
    "wof:placetype":"venue"
},
  "geometry": {"coordinates":[115.785743713,-31.7233104706],"type":"Point"}
}