{
  "type": "Feature",
  "properties": {
    "iso:country":"AU",
    "sg:address":"18/ 359 Southport-Nerang Rd",
    "sg:city":"Ashmore",
    "sg:classifiers":[
        {
            "category":"Education",
            "subcategory":"Dance Studio",
            "type":"Public Place"
        }
    ],
    "sg:phone":"+61 7 5597 7101",
    "sg:postcode":"4214",
    "sg:province":"QLD",
    "sg:tags":[
        "venue",
        "tuition"
    ],
    "wof:name":"Sheridan's Studio 1",
    "wof:placetype":"venue"
},
  "geometry": {"coordinates":[153.3490448,-27.9821128845],"type":"Point"}
}