{
  "type": "Feature",
  "properties": {
    "addr:full":"77 Lead St Yass NSW 2582",
    "addr:housenumber":"77",
    "addr:postcode":"2582",
    "addr:street":"Lead St",
    "iso:country":"AU",
    "sg:address":"77 Lead St",
    "sg:city":"Yass",
    "sg:classifiers":[
        {
            "category":"Health Services",
            "subcategory":"Dentist",
            "type":"Services"
        }
    ],
    "sg:phone":"+61 2 6226 1015",
    "sg:postcode":"2582",
    "sg:province":"NSW",
    "wof:name":"Robinson Jean Dr",
    "wof:placetype":"venue"
},
  "geometry": {"coordinates":[148.91232299800001,-34.8442230225],"type":"Point"}
}