{
  "type": "Feature",
  "properties": {
    "addr:full":"459 Albany Hwy Victoria Park WA 6100",
    "addr:housenumber":"459",
    "addr:postcode":"6100",
    "addr:street":"Albany Hwy Victoria",
    "iso:country":"AU",
    "sg:address":"459 Albany Hwy",
    "sg:city":"Victoria Park",
    "sg:classifiers":[
        {
            "category":"Recreation",
            "subcategory":"Fishing",
            "type":"Entertainment"
        }
    ],
    "sg:phone":"+61 8 9362 3162",
    "sg:postcode":"6100",
    "sg:province":"WA",
    "sg:tags":[
        "tackle"
    ],
    "wof:name":"Westackle",
    "wof:placetype":"venue"
},
  "geometry": {"coordinates":[115.897987366,-31.9761447906],"type":"Point"}
}