{
  "type": "Feature",
  "properties": {
    "iso:country":"AU",
    "sg:address":"Factory 2 5 Levanswell Rd",
    "sg:city":"Moorabbin",
    "sg:classifiers":[
        {
            "category":"Retail",
            "subcategory":"Auto Repair",
            "type":"Services"
        }
    ],
    "sg:phone":"+61 3 9532 2528",
    "sg:postcode":"3189",
    "sg:province":"VIC",
    "sg:tags":[
        "beater",
        "painter",
        "panel"
    ],
    "wof:name":"Perfect Image Panels",
    "wof:placetype":"venue"
},
  "geometry": {"coordinates":[145.06137085,-37.9440689087],"type":"Point"}
}