{
  "type": "Feature",
  "properties": {
    "addr:full":"23 Adelaide St Fremantle WA 6160",
    "addr:housenumber":"23",
    "addr:postcode":"6160",
    "addr:street":"Adelaide St",
    "iso:country":"AU",
    "sg:address":"23 Adelaide St",
    "sg:city":"Fremantle",
    "sg:classifiers":[
        {
            "category":"Personal",
            "subcategory":"Beauty Salon",
            "type":"Services"
        }
    ],
    "sg:phone":"+61 8 9335 4304",
    "sg:postcode":"6160",
    "sg:province":"WA",
    "sg:tags":[
        "hairdresser"
    ],
    "wof:name":"Beyond The Fringe",
    "wof:placetype":"venue"
},
  "geometry": {"coordinates":[115.748672,-32.052467],"type":"Point"}
}