{
  "type": "Feature",
  "properties": {
    "iso:country":"AU",
    "sg:address":"Levi St",
    "sg:city":"Farrell Flat",
    "sg:classifiers":[
        {
            "category":"Wholesale",
            "subcategory":"Farm Supplies",
            "type":"Manufacturing & Wholesale Goods"
        }
    ],
    "sg:phone":"+61 8 8843 8151",
    "sg:postcode":"5416",
    "sg:province":"SA",
    "sg:tags":[
        "equipment"
    ],
    "wof:name":"Ashmore Engineering Pty Ltd",
    "wof:placetype":"venue"
},
  "geometry": {"coordinates":[138.794830322,-33.8258476257],"type":"Point"}
}