{
  "type": "Feature",
  "properties": {
    "iso:country":"AU",
    "sg:address":"40 Stubbs St,",
    "sg:city":"Kensington",
    "sg:classifiers":[
        {
            "category":"Building & Trades",
            "subcategory":"Locksmith",
            "type":"Services"
        }
    ],
    "sg:phone":"+61 3 9372 5599",
    "sg:postcode":"3031",
    "sg:province":"VIC",
    "sg:tags":[
        "strongroom",
        "safe",
        "door"
    ],
    "wof:name":"Australian Safe Supplies",
    "wof:placetype":"venue"
},
  "geometry": {"coordinates":[144.935577,-37.790379],"type":"Point"}
}