{
  "type": "Feature",
  "properties": {
    "addr:full":"1 Windzor St Salisbury SA 5108",
    "addr:housenumber":"1",
    "addr:postcode":"5108",
    "addr:street":"Windzor St",
    "iso:country":"AU",
    "sg:address":"1 Windzor St",
    "sg:city":"Salisbury",
    "sg:classifiers":[
        {
            "category":"Building & Trades",
            "subcategory":"Landscaping Services",
            "type":"Services"
        }
    ],
    "sg:phone":"+61 401 217 999",
    "sg:postcode":"5108",
    "sg:province":"SA",
    "sg:tags":[
        "stump",
        "tree",
        "felling",
        "removal"
    ],
    "wof:name":"Statewide Tree Service",
    "wof:placetype":"venue"
},
  "geometry": {"coordinates":[138.63291931099999,-34.7633171082],"type":"Point"}
}