{
  "type": "Feature",
  "properties": {
    "iso:country":"AU",
    "sg:address":"44 Wittenoom St",
    "sg:city":"Collie",
    "sg:classifiers":[
        {
            "category":"Travel",
            "subcategory":"Hotels & Motels",
            "type":"Entertainment"
        }
    ],
    "sg:phone":"+61 8 9734 5655",
    "sg:postcode":"6225",
    "sg:province":"WA",
    "wof:name":"Banksia Motel - Collie",
    "wof:placetype":"venue"
},
  "geometry": {"coordinates":[116.155457,-33.362244],"type":"Point"}
}