{
  "type": "Feature",
  "properties": {
    "iso:country":"AU",
    "sg:address":"12 Edelmaier St",
    "sg:city":"Bayswater",
    "sg:classifiers":[
        {
            "category":"Manufacturing",
            "subcategory":"Metals",
            "type":"Manufacturing & Wholesale Goods"
        }
    ],
    "sg:phone":"+61 3 9729 0644",
    "sg:postcode":"3153",
    "sg:province":"VIC",
    "sg:tags":[
        "wholesaler",
        "aluminium",
        "mfrs"
    ],
    "wof:name":"Aluminium Express (Australia) Pty Ltd",
    "wof:placetype":"venue"
},
  "geometry": {"coordinates":[145.27525329599999,-37.84532547],"type":"Point"}
}