{
  "type": "Feature",
  "properties": {
    "addr:full":"PO Box 476 Gordonvale QLD 4865",
    "addr:postcode":"4865",
    "iso:country":"AU",
    "sg:address":"PO Box 476",
    "sg:city":"Gordonvale",
    "sg:classifiers":[
        {
            "category":"Building & Trades",
            "subcategory":"Construction",
            "type":"Services"
        }
    ],
    "sg:phone":"+61 7 4056 1781",
    "sg:postcode":"4865",
    "sg:province":"QLD",
    "sg:tags":[
        "contractor"
    ],
    "wof:name":"Piccolo Constructions",
    "wof:placetype":"venue"
},
  "geometry": {"coordinates":[145.78074645999999,-17.0994606018],"type":"Point"}
}