{
  "type": "Feature",
  "properties": {
    "iso:country":"AU",
    "sg:address":"1 May Rd",
    "sg:city":"Lalor",
    "sg:classifiers":[
        {
            "category":"Organizations",
            "subcategory":"Community Association",
            "type":"Services"
        }
    ],
    "sg:phone":"+61 3 9464 5870",
    "sg:postcode":"3075",
    "sg:province":"VIC",
    "sg:tags":[
        "organisation",
        "family",
        "welfare"
    ],
    "wof:name":"Society of St Vincent De Paul Centres",
    "wof:placetype":"venue"
},
  "geometry": {"coordinates":[145.004180908,-37.8470993042],"type":"Point"}
}