{
  "type": "Feature",
  "properties": {
    "addr:full":"135 Manningham Rd Bulleen VIC 3105",
    "addr:housenumber":"135",
    "addr:postcode":"3105",
    "addr:street":"Manningham Rd",
    "iso:country":"AU",
    "sg:address":"135 Manningham Rd",
    "sg:city":"Bulleen",
    "sg:classifiers":[
        {
            "category":"Health Services",
            "subcategory":"Chiropractor",
            "type":"Services"
        }
    ],
    "sg:phone":"+61 3 9852 0055",
    "sg:postcode":"3105",
    "sg:province":"VIC",
    "wof:name":"Halkias Kon",
    "wof:placetype":"venue"
},
  "geometry": {"coordinates":[145.09574890100001,-37.7678489685],"type":"Point"}
}