{
  "type": "Feature",
  "properties": {
    "addr:full":"6 Venetta Rd Glenorie NSW 2157",
    "addr:housenumber":"6",
    "addr:postcode":"2157",
    "addr:street":"Venetta Rd",
    "iso:country":"AU",
    "sg:address":"6 Venetta Rd",
    "sg:city":"Glenorie",
    "sg:classifiers":[
        {
            "category":"Building & Trades",
            "subcategory":"Construction",
            "type":"Services"
        }
    ],
    "sg:phone":"+61 2 9652 1122",
    "sg:postcode":"2157",
    "sg:province":"NSW",
    "sg:tags":[
        "contractor"
    ],
    "wof:name":"Cooper A J",
    "wof:placetype":"venue"
},
  "geometry": {"coordinates":[151.00941467300001,-33.620716095],"type":"Point"}
}