{
  "type": "Feature",
  "properties": {
    "addr:full":"165 High St Belmont VIC 3216",
    "addr:housenumber":"165",
    "addr:postcode":"3216",
    "addr:street":"High St",
    "iso:country":"AU",
    "sg:address":"165 High St",
    "sg:city":"Belmont",
    "sg:classifiers":[
        {
            "category":"Food & Beverages",
            "subcategory":"Bakery",
            "type":"Retail Goods"
        }
    ],
    "sg:phone":"+61 3 5243 8550",
    "sg:postcode":"3216",
    "sg:province":"VIC",
    "sg:tags":[
        "baker"
    ],
    "wof:name":"Bakers Delight",
    "wof:placetype":"venue"
},
  "geometry": {"coordinates":[144.343307495,-38.1747207642],"type":"Point"}
}