{
  "type": "Feature",
  "properties": {
    "iso:country":"AU",
    "sg:address":"238 Hannell St",
    "sg:city":"Maryville",
    "sg:classifiers":[
        {
            "category":"Shopping",
            "subcategory":"Pets & Pet Supplies",
            "type":"Retail Goods"
        }
    ],
    "sg:phone":"+61 2 4969 4020",
    "sg:postcode":"2293",
    "sg:province":"NSW",
    "sg:tags":[
        "food"
    ],
    "wof:name":"Harbourside Aquarium",
    "wof:placetype":"venue"
},
  "geometry": {"coordinates":[151.75869750999999,-32.9111709595],"type":"Point"}
}