{
  "type": "Feature",
  "properties": {
    "iso:country":"AU",
    "sg:address":"Level 1/ 85 Denham St",
    "sg:city":"Townsville",
    "sg:classifiers":[
        {
            "category":"Professional",
            "subcategory":"Engineering",
            "type":"Services"
        }
    ],
    "sg:phone":"+61 7 4772 3144",
    "sg:postcode":"4810",
    "sg:province":"QLD",
    "sg:tags":[
        "consulting",
        "engineer"
    ],
    "wof:name":"M G F Consultants (NQ) Pty Ltd",
    "wof:placetype":"venue"
},
  "geometry": {"coordinates":[146.81680299999999,-19.256685],"type":"Point"}
}