{
  "type": "Feature",
  "properties": {
    "iso:country":"AU",
    "sg:address":"13/ 68 Garden St",
    "sg:city":"Como",
    "sg:classifiers":[
        {
            "category":"Personal",
            "type":"Services"
        }
    ],
    "sg:phone":"+61 8 9367 6149",
    "sg:postcode":"6152",
    "sg:province":"WA",
    "sg:tags":[
        "reducing",
        "treatment",
        "weight"
    ],
    "wof:name":"Herbalife Como",
    "wof:placetype":"venue"
},
  "geometry": {"coordinates":[115.862358,-31.989685],"type":"Point"}
}