{
  "type": "Feature",
  "properties": {
    "iso:country":"AU",
    "sg:address":"10 Cherry Crt",
    "sg:city":"Morley",
    "sg:classifiers":[
        {
            "category":"Social Services",
            "subcategory":"Child Care",
            "type":"Services"
        }
    ],
    "sg:phone":"+61 8 9279 1173",
    "sg:postcode":"6062",
    "sg:province":"WA",
    "wof:name":"Cherry Court Early Learning Centre",
    "wof:placetype":"venue"
},
  "geometry": {"coordinates":[115.91986084,-31.8948745728],"type":"Point"}
}