{
  "type": "Feature",
  "properties": {
    "addr:full":"31- 33 Ricketty St Mascot NSW 2020",
    "addr:housenumber":"33",
    "addr:postcode":"2020",
    "addr:street":"Ricketty St",
    "iso:country":"AU",
    "sg:address":"31- 33 Ricketty St",
    "sg:city":"Mascot",
    "sg:classifiers":[
        {
            "category":"Retail",
            "subcategory":"Storage",
            "type":"Services"
        }
    ],
    "sg:phone":"+61 2 9313 4144",
    "sg:postcode":"2020",
    "sg:province":"NSW",
    "sg:tags":[
        "removal",
        "furniture"
    ],
    "wof:name":"Affordable Removals",
    "wof:placetype":"venue"
},
  "geometry": {"coordinates":[151.184082031,-33.9213943481],"type":"Point"}
}