{
  "type": "Feature",
  "properties": {
    "addr:full":"Shop K17 Westfield Shoppingtown Cobbs Rd Tuggerah NSW 2259",
    "addr:housenumber":"k17",
    "addr:postcode":"2259",
    "addr:street":"Cobbs Rd",
    "iso:country":"AU",
    "sg:address":"Shop K17 Westfield Shoppingtown Cobbs Rd",
    "sg:city":"Tuggerah",
    "sg:classifiers":[
        {
            "category":"Ice Cream",
            "type":"Food & Drink"
        }
    ],
    "sg:phone":"+61 2 4353 5270",
    "sg:postcode":"2259",
    "sg:province":"NSW",
    "sg:tags":[
        "retail"
    ],
    "wof:name":"Norgen-Vaaz Ice Cream",
    "wof:placetype":"venue"
},
  "geometry": {"coordinates":[151.417205811,-33.307674408],"type":"Point"}
}