{
  "type": "Feature",
  "properties": {
    "addr:full":"147 Old Maryborough Rd Pialba QLD 4655",
    "addr:housenumber":"147",
    "addr:postcode":"4655",
    "addr:street":"Old Maryborough Rd",
    "iso:country":"AU",
    "sg:address":"147 Old Maryborough Rd",
    "sg:city":"Pialba",
    "sg:classifiers":[
        {
            "category":"Shopping",
            "type":"Retail Goods"
        }
    ],
    "sg:phone":"+61 7 4124 4633",
    "sg:postcode":"4655",
    "sg:province":"QLD",
    "sg:tags":[
        "equipment",
        "safety",
        "accessory"
    ],
    "wof:name":"Fraser Coast Fire & Safety Protection",
    "wof:placetype":"venue"
},
  "geometry": {"coordinates":[152.83461,-25.283794],"type":"Point"}
}