{
  "type": "Feature",
  "properties": {
    "addr:full":"Lvl 4 Inergise House 135 Wickham Tce Brisbane QLD 4000",
    "addr:housenumber":"135",
    "addr:postcode":"4000",
    "addr:street":"Wickham Tce",
    "iso:country":"AU",
    "sg:address":"Lvl 4 Inergise House 135",
    "sg:city":"Wickham Tce Brisbane",
    "sg:classifiers":[
        {
            "category":"Travel",
            "subcategory":"Travel Agent",
            "type":"Entertainment"
        }
    ],
    "sg:phone":"+61 7 3230 5800",
    "sg:postcode":"4000",
    "sg:province":"QLD",
    "sg:tags":[
        "consultant"
    ],
    "wof:name":"Galileo Southern Cross",
    "wof:placetype":"venue"
},
  "geometry": {"coordinates":[153.02549743599999,-27.4646282196],"type":"Point"}
}