{
  "type": "Feature",
  "properties": {
    "iso:country":"AU",
    "sg:address":"10 Dixon St",
    "sg:city":"Abbotsbury",
    "sg:classifiers":[
        {
            "category":"Real Estate",
            "subcategory":"Surveying",
            "type":"Services"
        }
    ],
    "sg:phone":"+61 2 9823 4341",
    "sg:postcode":"2176",
    "sg:province":"NSW",
    "sg:tags":[
        "surveyor",
        "land"
    ],
    "wof:name":"Domenico Zampieri Pty Ltd",
    "wof:placetype":"venue"
},
  "geometry": {"coordinates":[150.86715698200001,-33.8748550415],"type":"Point"}
}