{
  "type": "Feature",
  "properties": {
    "addr:full":"4/ 100 Campbell St Bowen Hills QLD 4006",
    "addr:housenumber":"/ 100",
    "addr:postcode":"4006",
    "addr:street":"Campbell St",
    "iso:country":"AU",
    "sg:address":"4/ 100 Campbell St",
    "sg:city":"Bowen Hills",
    "sg:classifiers":[
        {
            "category":"Professional",
            "subcategory":"Detective & Security Services",
            "type":"Services"
        }
    ],
    "sg:phone":"+61 1800 225 232",
    "sg:postcode":"4006",
    "sg:province":"QLD",
    "sg:tags":[
        "consultant",
        "system"
    ],
    "wof:name":"Ascom Nira Pty Ltd",
    "wof:placetype":"venue"
},
  "geometry": {"coordinates":[153.03204345699999,-27.4467792511],"type":"Point"}
}