{
  "type": "Feature",
  "properties": {
    "addr:full":"937 Burnett Heads Rd Bundaberg QLD 4670",
    "addr:housenumber":"937",
    "addr:postcode":"4670",
    "addr:street":"Burnett Heads Rd",
    "iso:country":"AU",
    "sg:address":"937 Burnett Heads Rd",
    "sg:city":"Bundaberg",
    "sg:classifiers":[
        {
            "category":"Communications",
            "subcategory":"News Services",
            "type":"Services"
        }
    ],
    "sg:phone":"+61 7 4159 3977",
    "sg:postcode":"4670",
    "sg:province":"QLD",
    "sg:tags":[
        "information",
        "tourist",
        "attractions"
    ],
    "wof:name":"Bundy Water Slide",
    "wof:placetype":"venue"
},
  "geometry": {"coordinates":[152.41665649399999,-24.7928123474],"type":"Point"}
}