{
  "type": "Feature",
  "properties": {
    "addr:full":"11 Norman St Port Pirie SA 5540",
    "addr:housenumber":"11",
    "addr:postcode":"5540",
    "addr:street":"Norman St",
    "iso:country":"AU",
    "sg:address":"11 Norman St",
    "sg:city":"Port Pirie",
    "sg:classifiers":[
        {
            "category":"Food & Beverages",
            "subcategory":"Supermarket",
            "type":"Retail Goods"
        }
    ],
    "sg:phone":"+61 8 8632 2744",
    "sg:postcode":"5540",
    "sg:province":"SA",
    "sg:tags":[
        "grocery",
        "store"
    ],
    "wof:name":"Woolworths (S.A.) Pty Ltd",
    "wof:placetype":"venue"
},
  "geometry": {"coordinates":[138.01002502399999,-33.1791000366],"type":"Point"}
}