{
  "type": "Feature",
  "properties": {
    "addr:full":"U1/ 13 Nichols St Surry Hills NSW 2010",
    "addr:housenumber":"13",
    "addr:postcode":"2010",
    "addr:street":"U1 /;St",
    "iso:country":"AU",
    "sg:address":"U1/ 13 Nichols St",
    "sg:city":"Surry Hills",
    "sg:classifiers":[
        {
            "category":"Organizations",
            "subcategory":"Professional Association",
            "type":"Services"
        }
    ],
    "sg:phone":"+61 2 8003 4583",
    "sg:postcode":"2010",
    "sg:province":"NSW",
    "sg:tags":[
        "web",
        "internet"
    ],
    "wof:name":"Shifted Pixels",
    "wof:placetype":"venue"
},
  "geometry": {"coordinates":[151.21647644000001,-33.8844909668],"type":"Point"}
}