{
  "type": "Feature",
  "properties": {
    "addr:full":"40 George St Launceston TAS 7250",
    "addr:housenumber":"40",
    "addr:postcode":"7250",
    "addr:street":"George St",
    "iso:country":"AU",
    "sg:address":"40 George St",
    "sg:city":"Launceston",
    "sg:classifiers":[
        {
            "category":"Professional",
            "subcategory":"Employment Agencies",
            "type":"Services"
        }
    ],
    "sg:phone":"+61 3 6331 4600",
    "sg:postcode":"7250",
    "sg:province":"TAS",
    "wof:name":"Coopers Recruitment",
    "wof:placetype":"venue"
},
  "geometry": {"coordinates":[147.13888549800001,-41.4346122742],"type":"Point"}
}