{
  "type": "Feature",
  "properties": {
    "addr:full":"61 Queen St Ayr QLD 4807",
    "addr:housenumber":"61",
    "addr:postcode":"4807",
    "addr:street":"Queen St",
    "iso:country":"AU",
    "sg:address":"61 Queen St",
    "sg:city":"Ayr",
    "sg:classifiers":[
        {
            "category":"Autos & Motor Vehicles",
            "subcategory":"Automobile Sales",
            "type":"Retail Goods"
        }
    ],
    "sg:phone":"+61 7 4783 1487",
    "sg:postcode":"4807",
    "sg:province":"QLD",
    "sg:tags":[
        "car",
        "new"
    ],
    "wof:name":"Subaru",
    "wof:placetype":"venue"
},
  "geometry": {"coordinates":[147.40815734899999,-19.5725231171],"type":"Point"}
}