{
  "type": "Feature",
  "properties": {
    "addr:full":"2 Narooma Drv Ocean Shores NSW 2483",
    "addr:housenumber":"2",
    "addr:postcode":"2483",
    "addr:street":"Narooma Drv",
    "iso:country":"AU",
    "sg:address":"2 Narooma Drv",
    "sg:city":"Ocean Shores",
    "sg:classifiers":[
        {
            "category":"Local Transit",
            "type":"Transportation"
        }
    ],
    "sg:phone":"+61 2 6680 4359",
    "sg:postcode":"2483",
    "sg:province":"NSW",
    "sg:tags":[
        "surveyor",
        "hydrographic"
    ],
    "wof:name":"G.P.S. & Hydrographic Services Pty Ltd",
    "wof:placetype":"venue"
},
  "geometry": {"coordinates":[153.542770386,-28.5204029083],"type":"Point"}
}