{
  "type": "Feature",
  "properties": {
    "iso:country":"AU",
    "sg:address":"Shp 34",
    "sg:city":"a, Golden Grove Vlge Shopng Cntr, Cnr Golden",
    "sg:classifiers":[
        {
            "category":"Banks & Credit Unions",
            "subcategory":"Financial Services",
            "type":"Services"
        }
    ],
    "sg:phone":"+61 8 8289 4466",
    "sg:postcode":"5125",
    "sg:province":"SA",
    "sg:tags":[
        "loan",
        "finance",
        "mortgage"
    ],
    "wof:name":"Wizard",
    "wof:placetype":"venue"
},
  "geometry": {"coordinates":[138.710724,-34.765987],"type":"Point"}
}