{
  "type": "Feature",
  "properties": {
    "addr:full":"1010 Glen Huntly Rd Glen Huntly VIC 3163",
    "addr:housenumber":"1010",
    "addr:postcode":"3163",
    "addr:street":"Glen Huntly Rd",
    "iso:country":"AU",
    "sg:address":"1010 Glen Huntly Rd",
    "sg:city":"Glen Huntly",
    "sg:classifiers":[
        {
            "category":"Retail",
            "subcategory":"Repair Shop",
            "type":"Services"
        }
    ],
    "sg:phone":"+61 3 9572 3300",
    "sg:postcode":"3163",
    "sg:province":"VIC",
    "sg:tags":[
        "upholsterer"
    ],
    "wof:name":"Arkady Relin",
    "wof:placetype":"venue"
},
  "geometry": {"coordinates":[145.051437378,-37.8905181885],"type":"Point"}
}