{
  "type": "Feature",
  "properties": {
    "addr:full":"2/29- 31 Cronulla St Cronulla NSW 2230",
    "addr:housenumber":"/;31",
    "addr:postcode":"2230",
    "addr:street":"29;St",
    "iso:country":"AU",
    "sg:address":"2/29- 31 Cronulla St",
    "sg:city":"Cronulla",
    "sg:classifiers":[
        {
            "category":"Shopping",
            "subcategory":"Shoes",
            "type":"Retail Goods"
        }
    ],
    "sg:phone":"+61 2 9527 2121",
    "sg:postcode":"2230",
    "sg:province":"NSW",
    "sg:tags":[
        "footwear"
    ],
    "wof:name":"Payless Shoes Pty Limited",
    "wof:placetype":"venue"
},
  "geometry": {"coordinates":[151.15255737300001,-34.0527076721],"type":"Point"}
}