{
  "type": "Feature",
  "properties": {
    "addr:full":"70 - 74 WestGate Drv Altona North VIC 3025",
    "addr:housenumber":"74",
    "addr:postcode":"3025",
    "addr:street":"Westgate Drv",
    "iso:country":"AU",
    "sg:address":"70 - 74 WestGate Drv",
    "sg:city":"Altona North",
    "sg:classifiers":[
        {
            "category":"Social Services",
            "subcategory":"Child Care",
            "type":"Services"
        }
    ],
    "sg:phone":"+61 3 8369 9777",
    "sg:postcode":"3025",
    "sg:province":"VIC",
    "sg:tags":[
        "equipment",
        "identification"
    ],
    "wof:name":"Austab Labels P/L",
    "wof:placetype":"venue"
},
  "geometry": {"coordinates":[144.820053,-37.831993],"type":"Point"}
}