{
  "type": "Feature",
  "properties": {
    "addr:full":"47 Dehavilland Rd Mordialloc VIC 3195",
    "addr:housenumber":"47",
    "addr:postcode":"3195",
    "addr:street":"Dehavilland Rd",
    "iso:country":"AU",
    "sg:address":"47 Dehavilland Rd",
    "sg:city":"Mordialloc",
    "sg:classifiers":[
        {
            "category":"Shopping",
            "subcategory":"Clothing, Apparel, & Fashions",
            "type":"Retail Goods"
        }
    ],
    "sg:phone":"+61 3 9587 6870",
    "sg:postcode":"3195",
    "sg:province":"VIC",
    "sg:tags":[
        "sportswear"
    ],
    "wof:name":"Scorpion Sportswear Pty Ltd",
    "wof:placetype":"venue"
},
  "geometry": {"coordinates":[145.100341797,-37.9901161194],"type":"Point"}
}