{
  "type": "Feature",
  "properties": {
    "addr:full":"3 Gerald St Marrickville NSW 2204",
    "addr:housenumber":"3",
    "addr:postcode":"2204",
    "addr:street":"Gerald St",
    "iso:country":"AU",
    "sg:address":"3 Gerald St",
    "sg:city":"Marrickville",
    "sg:classifiers":[
        {
            "category":"Building & Trades",
            "subcategory":"Electrical",
            "type":"Services"
        }
    ],
    "sg:phone":"+61 2 9519 4566",
    "sg:postcode":"2204",
    "sg:province":"NSW",
    "sg:tags":[
        "wholesaler",
        "equipment",
        "magnetic",
        "mfrs"
    ],
    "wof:name":"Robinson's",
    "wof:placetype":"venue"
},
  "geometry": {"coordinates":[151.161362,-33.913799],"type":"Point"}
}