{
  "type": "Feature",
  "properties": {
    "addr:full":"11 Abbotts Rd Dandenong VIC 3175",
    "addr:housenumber":"11",
    "addr:postcode":"3175",
    "addr:street":"Abbotts Rd",
    "iso:country":"AU",
    "sg:address":"11 Abbotts Rd",
    "sg:city":"Dandenong",
    "sg:classifiers":[
        {
            "category":"Farming",
            "subcategory":"Crops",
            "type":"Manufacturing & Wholesale Goods"
        }
    ],
    "sg:phone":"+61 3 9706 5330",
    "sg:postcode":"3175",
    "sg:province":"VIC",
    "sg:tags":[
        "warehousing"
    ],
    "wof:name":"Southern Cross Logistics Pty Ltd",
    "wof:placetype":"venue"
},
  "geometry": {"coordinates":[145.21722412099999,-38.0321540833],"type":"Point"}
}