{
  "type": "Feature",
  "properties": {
    "addr:full":"121 Westall Rd Clayton South VIC 3169",
    "addr:housenumber":"121",
    "addr:postcode":"3169",
    "addr:street":"Westall Rd",
    "iso:country":"AU",
    "sg:address":"121 Westall Rd",
    "sg:city":"Clayton South",
    "sg:classifiers":[
        {
            "category":"Retail",
            "subcategory":"Auto Repair",
            "type":"Services"
        }
    ],
    "sg:phone":"+61 3 9547 8422",
    "sg:postcode":"3169",
    "sg:province":"VIC",
    "sg:tags":[
        "transmission",
        "automotive",
        "car"
    ],
    "wof:name":"Capri Spares",
    "wof:placetype":"venue"
},
  "geometry": {"coordinates":[145.13819885300001,-37.9496269226],"type":"Point"}
}