{
  "type": "Feature",
  "properties": {
    "iso:country":"AU",
    "sg:address":"30 Brisbane St",
    "sg:city":"Mackay",
    "sg:classifiers":[
        {
            "category":"Health Services",
            "subcategory":"Optometrist",
            "type":"Services"
        }
    ],
    "sg:phone":"+61 7 4953 1444",
    "sg:postcode":"4740",
    "sg:province":"QLD",
    "wof:name":"Hartley & Dolan",
    "wof:placetype":"venue"
},
  "geometry": {"coordinates":[149.187836,-21.14414],"type":"Point"}
}