{
  "type": "Feature",
  "properties": {
    "iso:country":"AU",
    "sg:address":"81 Laparoo St",
    "sg:city":"Griffith",
    "sg:classifiers":[
        {
            "category":"Home & Garden",
            "subcategory":"Garden Supply",
            "type":"Retail Goods"
        }
    ],
    "sg:phone":"+61 2 6295 2046",
    "sg:postcode":"2603",
    "sg:province":"ACT",
    "sg:tags":[
        "equipment"
    ],
    "wof:name":"Emmanual Papadakis",
    "wof:placetype":"venue"
},
  "geometry": {"coordinates":[149.14610290499999,-35.3248291016],"type":"Point"}
}