{
  "type": "Feature",
  "properties": {
    "addr:full":"Suite 201, 10- 12 Clarke St Crows Nest NSW 2065",
    "addr:housenumber":"12",
    "addr:postcode":"2065",
    "addr:street":"Clarke St",
    "iso:country":"AU",
    "sg:address":"Suite 201, 10- 12 Clarke St",
    "sg:city":"Crows Nest",
    "sg:classifiers":[
        {
            "category":"Professional",
            "subcategory":"Computer Services",
            "type":"Services"
        }
    ],
    "sg:phone":"+61 2 9436 2788",
    "sg:postcode":"2065",
    "sg:province":"NSW",
    "sg:tags":[
        "package",
        "software"
    ],
    "wof:name":"Softgen Pacific Pty Ltd",
    "wof:placetype":"venue"
},
  "geometry": {"coordinates":[151.19993591299999,-33.8257446289],"type":"Point"}
}