{
  "type": "Feature",
  "properties": {
    "addr:full":"20 Woodbeck St Beenleigh QLD 4207",
    "addr:housenumber":"20",
    "addr:postcode":"4207",
    "addr:street":"Woodbeck St",
    "iso:country":"AU",
    "sg:address":"20 Woodbeck St",
    "sg:city":"Beenleigh",
    "sg:classifiers":[
        {
            "category":"Home & Garden",
            "subcategory":"Building Materials",
            "type":"Retail Goods"
        }
    ],
    "sg:phone":"+61 416 223 018",
    "sg:postcode":"4207",
    "sg:province":"QLD",
    "sg:tags":[
        "anti-corrosive",
        "composition",
        "flooring"
    ],
    "wof:name":"Cahill David",
    "wof:placetype":"venue"
},
  "geometry": {"coordinates":[153.20036315900001,-27.707780838],"type":"Point"}
}