{
  "type": "Feature",
  "properties": {
    "addr:full":"35-37 Calala La Tamworth NSW 2340",
    "addr:housenumber":"35-37",
    "addr:postcode":"2340",
    "addr:street":"Calala La",
    "iso:country":"AU",
    "sg:address":"35-37 Calala La",
    "sg:city":"Tamworth",
    "sg:classifiers":[
        {
            "category":"Farming",
            "subcategory":"Nursery",
            "type":"Manufacturing & Wholesale Goods"
        }
    ],
    "sg:phone":"+61 2 6765 9733",
    "sg:postcode":"2340",
    "sg:province":"NSW",
    "wof:name":"Calala Nursery",
    "wof:placetype":"venue"
},
  "geometry": {"coordinates":[150.93739318900001,-31.1255931854],"type":"Point"}
}