{
  "type": "Feature",
  "properties": {
    "addr:full":"183 Eleventh Rd Armadale WA 6112",
    "addr:housenumber":"183",
    "addr:postcode":"6112",
    "addr:street":"Eleventh Rd",
    "iso:country":"AU",
    "sg:address":"183 Eleventh Rd",
    "sg:city":"Armadale",
    "sg:classifiers":[
        {
            "category":"Retail",
            "subcategory":"Laundry & Dry Cleaning",
            "type":"Services"
        }
    ],
    "sg:phone":"+61 8 9399 7919",
    "sg:postcode":"6112",
    "sg:province":"WA",
    "sg:tags":[
        "breeder",
        "alpaca",
        "llama"
    ],
    "wof:name":"Encantador Alpaca Stud",
    "wof:placetype":"venue"
},
  "geometry": {"coordinates":[115.99289703399999,-32.1723937988],"type":"Point"}
}