{
  "type": "Feature",
  "properties": {
    "iso:country":"AU",
    "sg:address":"U4/ 1 Mcroyle St",
    "sg:city":"Wacol",
    "sg:classifiers":[
        {
            "category":"Manufacturing",
            "subcategory":"Tools & Machinery",
            "type":"Manufacturing & Wholesale Goods"
        }
    ],
    "sg:phone":"+61 7 3879 4755",
    "sg:postcode":"4076",
    "sg:province":"QLD",
    "sg:tags":[
        "toolmaker"
    ],
    "wof:name":"Ramjet Tooling Pty Ltd",
    "wof:placetype":"venue"
},
  "geometry": {"coordinates":[152.936737061,-27.5976467133],"type":"Point"}
}