{
  "type": "Feature",
  "properties": {
    "iso:country":"AU",
    "sg:address":"30 Greenfield Pde",
    "sg:city":"Bankstown",
    "sg:classifiers":[
        {
            "category":"Banks & Credit Unions",
            "subcategory":"Financial Services",
            "type":"Services"
        }
    ],
    "sg:phone":"+61 2 9790 1630",
    "sg:postcode":"2200",
    "sg:province":"NSW",
    "sg:tags":[
        "management",
        "risk"
    ],
    "wof:name":"International Money Express Pty Ltd",
    "wof:placetype":"venue"
},
  "geometry": {"coordinates":[151.032013,-33.919632],"type":"Point"}
}