{
  "type": "Feature",
  "properties": {
    "addr:full":"27 Breese St Brunswick VIC 3056",
    "addr:housenumber":"27",
    "addr:postcode":"3056",
    "addr:street":"Breese St",
    "iso:country":"AU",
    "sg:address":"27 Breese St",
    "sg:city":"Brunswick",
    "sg:classifiers":[
        {
            "category":"Manufacturing",
            "subcategory":"Apparel",
            "type":"Manufacturing & Wholesale Goods"
        }
    ],
    "sg:phone":"+61 3 9383 6939",
    "sg:postcode":"3056",
    "sg:province":"VIC",
    "sg:tags":[
        "wholesaler",
        "mfrs",
        "footwear"
    ],
    "wof:name":"France Shoes",
    "wof:placetype":"venue"
},
  "geometry": {"coordinates":[144.961334228,-37.762752533],"type":"Point"}
}