{
  "type": "Feature",
  "properties": {
    "iso:country":"AU",
    "sg:address":"8 Druid Pl",
    "sg:city":"Strathfieldsaye",
    "sg:classifiers":[
        {
            "category":"Utilities",
            "type":"Services"
        }
    ],
    "sg:phone":"+61 3 5439 4281",
    "sg:postcode":"3551",
    "sg:province":"VIC",
    "sg:tags":[
        "refrigeration",
        "industrial",
        "commercial",
        "retail"
    ],
    "wof:name":"Carmichael Airconditioning & Refrigeration",
    "wof:placetype":"venue"
},
  "geometry": {"coordinates":[144.34014892600001,-36.7962799072],"type":"Point"}
}