{
  "type": "Feature",
  "properties": {
    "addr:full":"515 Old South Head Rd Rose Bay NSW 2029",
    "addr:housenumber":"515",
    "addr:postcode":"2029",
    "addr:street":"Old South Head Rd",
    "iso:country":"AU",
    "sg:address":"515 Old South Head Rd",
    "sg:city":"Rose Bay",
    "sg:classifiers":[
        {
            "category":"Health Services",
            "subcategory":"Medical Lab",
            "type":"Services"
        }
    ],
    "sg:phone":"+61 2 9388 2671",
    "sg:postcode":"2029",
    "sg:province":"NSW",
    "sg:tags":[
        "laboratory",
        "dental"
    ],
    "wof:name":"Jankovic D",
    "wof:placetype":"venue"
},
  "geometry": {"coordinates":[151.273239136,-33.874256134],"type":"Point"}
}