{
  "type": "Feature",
  "properties": {
    "iso:country":"AU",
    "sg:address":"77 Cardo Drv",
    "sg:city":"Lavington",
    "sg:classifiers":[
        {
            "category":"Building & Trades",
            "subcategory":"Plumbing",
            "type":"Services"
        }
    ],
    "sg:phone":"+61 2 6025 3628",
    "sg:postcode":"2641",
    "sg:province":"NSW",
    "sg:tags":[
        "plumber",
        "gasfitters"
    ],
    "wof:name":"Reis (Ben)",
    "wof:placetype":"venue"
},
  "geometry": {"coordinates":[146.952362061,-36.030582428],"type":"Point"}
}