{
  "type": "Feature",
  "properties": {
    "addr:full":"150 Stirling Hwy Nedlands WA 6009",
    "addr:housenumber":"150",
    "addr:postcode":"6009",
    "addr:street":"Stirling Hwy",
    "iso:country":"AU",
    "sg:address":"150 Stirling Hwy",
    "sg:city":"Nedlands",
    "sg:classifiers":[
        {
            "category":"Professional",
            "subcategory":"Art Services",
            "type":"Services"
        }
    ],
    "sg:phone":"+61 8 9389 8466",
    "sg:postcode":"6009",
    "sg:province":"WA",
    "sg:tags":[
        "interior",
        "decorator"
    ],
    "wof:name":"Boulevarde Interiors Pty Ltd",
    "wof:placetype":"venue"
},
  "geometry": {"coordinates":[115.795433,-31.980682],"type":"Point"}
}