{
  "type": "Feature",
  "properties": {
    "addr:full":"11 Welman St Launceston TAS 7250",
    "addr:housenumber":"11",
    "addr:postcode":"7250",
    "addr:street":"Welman St",
    "iso:country":"AU",
    "sg:address":"11 Welman St",
    "sg:city":"Launceston",
    "sg:classifiers":[
        {
            "category":"Real Estate",
            "subcategory":"Surveying",
            "type":"Services"
        }
    ],
    "sg:phone":"+61 3 6334 1679",
    "sg:postcode":"7250",
    "sg:province":"TAS",
    "sg:tags":[
        "surveyor",
        "quantity"
    ],
    "wof:name":"R J Vaughan & Associates",
    "wof:placetype":"venue"
},
  "geometry": {"coordinates":[147.14447021500001,-41.4371070862],"type":"Point"}
}