{
  "type": "Feature",
  "properties": {
    "addr:full":"10 Arthur St Cabramatta NSW 2166",
    "addr:housenumber":"10",
    "addr:postcode":"2166",
    "addr:street":"Arthur St",
    "iso:country":"AU",
    "sg:address":"10 Arthur St",
    "sg:city":"Cabramatta",
    "sg:classifiers":[
        {
            "category":"Health Services",
            "subcategory":"Optometrist",
            "type":"Services"
        }
    ],
    "sg:phone":"+61 2 9725 6635",
    "sg:postcode":"2166",
    "sg:province":"NSW",
    "wof:name":"Nguyen Tu Khan &#034;Diane&#034;",
    "wof:placetype":"venue"
},
  "geometry": {"coordinates":[150.93782043499999,-33.8946800232],"type":"Point"}
}