{
  "type": "Feature",
  "properties": {
    "addr:full":"49 Serpentine Rd Erina Heights NSW 2260",
    "addr:housenumber":"49",
    "addr:postcode":"2260",
    "addr:street":"Serpentine Rd",
    "iso:country":"AU",
    "sg:address":"49 Serpentine Rd",
    "sg:city":"Erina Heights",
    "sg:classifiers":[
        {
            "category":"Social Services",
            "subcategory":"Child Care",
            "type":"Services"
        }
    ],
    "sg:phone":"+61 2 4367 3000",
    "sg:postcode":"2260",
    "sg:province":"NSW",
    "wof:name":"Kids Academy",
    "wof:placetype":"venue"
},
  "geometry": {"coordinates":[151.41224700000001,-33.431374],"type":"Point"}
}