{
  "type": "Feature",
  "properties": {
    "iso:country":"AU",
    "sg:address":"9 Cassowary Crescent",
    "sg:city":"Condon",
    "sg:classifiers":[
        {
            "category":"Professional",
            "subcategory":"Computer Services",
            "type":"Services"
        }
    ],
    "sg:phone":"+61 7 4723 7275",
    "sg:postcode":"4815",
    "sg:province":"QLD",
    "sg:tags":[
        "repairs",
        "upgrade",
        "equipment"
    ],
    "wof:name":"Dial-a-Computer Tech",
    "wof:placetype":"venue"
},
  "geometry": {"coordinates":[146.719513,-19.319851],"type":"Point"}
}