{
  "type": "Feature",
  "properties": {
    "iso:country":"AU",
    "sg:address":"38 Charming St",
    "sg:city":"Hampton East",
    "sg:classifiers":[
        {
            "category":"Banks & Credit Unions",
            "subcategory":"Bank",
            "type":"Services"
        }
    ],
    "sg:phone":"+61 421 993 966",
    "sg:postcode":"3188",
    "sg:province":"VIC",
    "sg:tags":[
        "broker",
        "mortgage"
    ],
    "wof:name":"CAR Consulting Pty Ltd",
    "wof:placetype":"venue"
},
  "geometry": {"coordinates":[145.03260803200001,-37.9346847534],"type":"Point"}
}