{
  "type": "Feature",
  "properties": {
    "iso:country":"AU",
    "sg:address":"Shop 2 48- 52 Rooke St",
    "sg:city":"Devonport",
    "sg:classifiers":[
        {
            "category":"Shopping",
            "subcategory":"Music",
            "type":"Retail Goods"
        }
    ],
    "sg:phone":"+61 3 6423 3982",
    "sg:postcode":"7310",
    "sg:province":"TAS",
    "sg:tags":[
        "store"
    ],
    "wof:name":"Sanity",
    "wof:placetype":"venue"
},
  "geometry": {"coordinates":[146.36074829099999,-41.1800308228],"type":"Point"}
}