{
  "type": "Feature",
  "properties": {
    "addr:full":"Shop 6 / 525 David St Albury NSW 2640",
    "addr:housenumber":"shop 6 / 525",
    "addr:postcode":"2640",
    "addr:street":"David St",
    "iso:country":"AU",
    "sg:address":"Shop 6 / 525 David St",
    "sg:city":"Albury",
    "sg:classifiers":[
        {
            "category":"Utilities",
            "subcategory":"Telephone",
            "type":"Services"
        }
    ],
    "sg:phone":"+61 1300 843 663",
    "sg:postcode":"2640",
    "sg:province":"NSW",
    "sg:tags":[
        "equipment",
        "system"
    ],
    "wof:name":"ReConnect Communications",
    "wof:placetype":"venue"
},
  "geometry": {"coordinates":[146.92100524899999,-36.0806694031],"type":"Point"}
}