{
  "type": "Feature",
  "properties": {
    "addr:full":"70 Davenport St Southport QLD 4215",
    "addr:housenumber":"70",
    "addr:postcode":"4215",
    "addr:street":"Davenport St",
    "iso:country":"AU",
    "sg:address":"70 Davenport St",
    "sg:city":"Southport",
    "sg:classifiers":[
        {
            "category":"Landmark",
            "subcategory":"Fountain",
            "type":"Public Place"
        }
    ],
    "sg:phone":"+61 7 5531 4544",
    "sg:postcode":"4215",
    "sg:province":"QLD",
    "sg:tags":[
        "wholesaler",
        "spring",
        "mfrs"
    ],
    "wof:name":"Pedders Suspension",
    "wof:placetype":"venue"
},
  "geometry": {"coordinates":[153.41140747099999,-27.9659061432],"type":"Point"}
}