{
  "type": "Feature",
  "properties": {
    "iso:country":"AU",
    "sg:address":"13 Palmerston St",
    "sg:city":"Warragul",
    "sg:classifiers":[
        {
            "category":"Casinos & Gambling",
            "type":"Entertainment"
        }
    ],
    "sg:phone":"+61 3 5622 0030",
    "sg:postcode":"3820",
    "sg:province":"VIC",
    "sg:tags":[
        "lottery",
        "agent"
    ],
    "wof:name":"Lucky Link Lotto",
    "wof:placetype":"venue"
},
  "geometry": {"coordinates":[145.930557,-38.161362],"type":"Point"}
}