{
  "type": "Feature",
  "properties": {
    "addr:full":"65 Indus St Camp Hill QLD 4152",
    "addr:housenumber":"65",
    "addr:postcode":"4152",
    "addr:street":"Indus St",
    "iso:country":"AU",
    "sg:address":"65 Indus St",
    "sg:city":"Camp Hill",
    "sg:classifiers":[
        {
            "category":"Health Services",
            "subcategory":"Health Practitioner",
            "type":"Services"
        }
    ],
    "sg:phone":"+61 7 3395 2059",
    "sg:postcode":"4152",
    "sg:province":"QLD",
    "sg:tags":[
        "alternative"
    ],
    "wof:name":"Reconnective Healing @ Holistic Terapy Centre",
    "wof:placetype":"venue"
},
  "geometry": {"coordinates":[153.07986450199999,-27.5041675568],"type":"Point"}
}