{
  "type": "Feature",
  "properties": {
    "addr:full":"5 Jason Crt Donvale VIC 3111",
    "addr:housenumber":"5",
    "addr:postcode":"3111",
    "addr:street":"Jason Crt",
    "iso:country":"AU",
    "sg:address":"5 Jason Crt",
    "sg:city":"Donvale",
    "sg:classifiers":[
        {
            "category":"Building & Trades",
            "subcategory":"Construction",
            "type":"Services"
        }
    ],
    "sg:phone":"+61 409 761 665",
    "sg:postcode":"3111",
    "sg:province":"VIC",
    "sg:tags":[
        "contractor"
    ],
    "wof:name":"Manart Construction Pty Ltd",
    "wof:placetype":"venue"
},
  "geometry": {"coordinates":[145.08421325699999,-37.7855377197],"type":"Point"}
}