{
  "type": "Feature",
  "properties": {
    "iso:country":"AU",
    "sg:address":"2 Craigie Pl",
    "sg:city":"Mundaring",
    "sg:classifiers":[
        {
            "category":"Wholesale",
            "subcategory":"Machinery & Supplies",
            "type":"Manufacturing & Wholesale Goods"
        }
    ],
    "sg:phone":"+61 412 529 042",
    "sg:postcode":"6073",
    "sg:province":"WA",
    "sg:tags":[
        "engineer"
    ],
    "wof:name":"Lexal",
    "wof:placetype":"venue"
},
  "geometry": {"coordinates":[116.16153717,-31.9041461945],"type":"Point"}
}