{
  "type": "Feature",
  "properties": {
    "addr:full":"Majors Creek Rd Araluen NSW 2622",
    "addr:postcode":"2622",
    "addr:street":"Majors Creek Rd",
    "iso:country":"AU",
    "sg:address":"Majors Creek Rd",
    "sg:city":"Araluen",
    "sg:classifiers":[
        {
            "category":"Farming",
            "subcategory":"Berry Farm",
            "type":"Manufacturing & Wholesale Goods"
        }
    ],
    "sg:phone":"+61 2 4846 4024",
    "sg:postcode":"2622",
    "sg:province":"NSW",
    "sg:tags":[
        "fruit",
        "grower"
    ],
    "wof:name":"Wisbey Noel & Bev",
    "wof:placetype":"venue"
},
  "geometry": {"coordinates":[149.744430542,-35.5623931885],"type":"Point"}
}