{
  "type": "Feature",
  "properties": {
    "iso:country":"AU",
    "sg:address":"11 Colebard St East",
    "sg:city":"Archerfield",
    "sg:classifiers":[
        {
            "category":"Autos & Motor Vehicles",
            "subcategory":"Auto Supplies",
            "type":"Retail Goods"
        }
    ],
    "sg:phone":"+61 7 3277 3220",
    "sg:postcode":"4108",
    "sg:province":"QLD",
    "sg:tags":[
        "equipment",
        "part",
        "truck"
    ],
    "wof:name":"Crisp-Air",
    "wof:placetype":"venue"
},
  "geometry": {"coordinates":[153.004669189,-27.5774555206],"type":"Point"}
}