{
  "type": "Feature",
  "properties": {
    "iso:country":"AU",
    "sg:address":"61 Dulwich Ave",
    "sg:city":"Dulwich",
    "sg:classifiers":[
        {
            "category":"Education",
            "subcategory":"Special Training",
            "type":"Public Place"
        }
    ],
    "sg:phone":"+61 412 955 171",
    "sg:postcode":"5065",
    "sg:province":"SA",
    "sg:tags":[
        "development"
    ],
    "wof:name":"Professional Workplace Solutions",
    "wof:placetype":"venue"
},
  "geometry": {"coordinates":[138.631134033,-34.9348983765],"type":"Point"}
}