{
  "type": "Feature",
  "properties": {
    "addr:full":"10 Grace St Watsonia VIC 3087",
    "addr:housenumber":"10",
    "addr:postcode":"3087",
    "addr:street":"Grace St",
    "iso:country":"AU",
    "sg:address":"10 Grace St",
    "sg:city":"Watsonia",
    "sg:classifiers":[
        {
            "category":"Health Services",
            "subcategory":"Chiropractor",
            "type":"Services"
        }
    ],
    "sg:phone":"+61 3 9434 3086",
    "sg:postcode":"3087",
    "sg:province":"VIC",
    "wof:name":"Dynes Dr Peter",
    "wof:placetype":"venue"
},
  "geometry": {"coordinates":[145.08241272000001,-37.710193634],"type":"Point"}
}