{
  "type": "Feature",
  "properties": {
    "addr:full":"174 Union Rd Surrey Hills VIC 3127",
    "addr:housenumber":"174",
    "addr:postcode":"3127",
    "addr:street":"Union Rd",
    "iso:country":"AU",
    "sg:address":"174 Union Rd",
    "sg:city":"Surrey Hills",
    "sg:classifiers":[
        {
            "category":"Health Services",
            "subcategory":"Doctor",
            "type":"Services"
        }
    ],
    "sg:phone":"+61 3 9836 1366",
    "sg:postcode":"3127",
    "sg:province":"VIC",
    "sg:tags":[
        "medical",
        "practitioner"
    ],
    "wof:name":"Surrey Hills Travel Medicine",
    "wof:placetype":"venue"
},
  "geometry": {"coordinates":[145.09771728499999,-37.8224906921],"type":"Point"}
}