{
  "type": "Feature",
  "properties": {
    "addr:full":"23 Victoria St Jannali NSW 2226",
    "addr:housenumber":"23",
    "addr:postcode":"2226",
    "addr:street":"Victoria St",
    "iso:country":"AU",
    "sg:address":"23 Victoria St",
    "sg:city":"Jannali",
    "sg:classifiers":[
        {
            "category":"Professional",
            "subcategory":"Employment Agencies",
            "type":"Services"
        }
    ],
    "sg:phone":"+61 2 8004 2727",
    "sg:postcode":"2226",
    "sg:province":"NSW",
    "sg:tags":[
        "occupational",
        "therapist"
    ],
    "sg:website":"http://www.sensationalkidsot.com.au",
    "wof:name":"Sensational Kids OT",
    "wof:placetype":"venue"
},
  "geometry": {"coordinates":[151.06272888199999,-34.017288208],"type":"Point"}
}