{
  "type": "Feature",
  "properties": {
    "addr:full":"49 Main Rd Huonville TAS 7109",
    "addr:housenumber":"49",
    "addr:postcode":"7109",
    "addr:street":"Main Rd",
    "iso:country":"AU",
    "sg:address":"49 Main Rd",
    "sg:city":"Huonville",
    "sg:classifiers":[
        {
            "category":"Health Services",
            "subcategory":"Doctor",
            "type":"Services"
        }
    ],
    "sg:phone":"+61 3 6264 1666",
    "sg:postcode":"7109",
    "sg:province":"TAS",
    "sg:tags":[
        "medical",
        "practitioner"
    ],
    "wof:name":"Ireland Stephen Dr",
    "wof:placetype":"venue"
},
  "geometry": {"coordinates":[147.04881286599999,-43.0298423767],"type":"Point"}
}