{
  "type": "Feature",
  "properties": {
    "addr:full":"130 Fifteenth St Renmark SA 5341",
    "addr:housenumber":"130",
    "addr:postcode":"5341",
    "addr:street":"Fifteenth St",
    "iso:country":"AU",
    "sg:address":"130 Fifteenth St",
    "sg:city":"Renmark",
    "sg:classifiers":[
        {
            "category":"Home & Garden",
            "subcategory":"Carpets & Floor Coverings",
            "type":"Retail Goods"
        }
    ],
    "sg:phone":"+61 8 8586 6797",
    "sg:postcode":"5341",
    "sg:province":"SA",
    "sg:tags":[
        "tile",
        "wall"
    ],
    "wof:name":"Beaumont Tiles",
    "wof:placetype":"venue"
},
  "geometry": {"coordinates":[140.747802734,-34.172328949],"type":"Point"}
}