{
  "type": "Feature",
  "properties": {
    "iso:country":"AU",
    "sg:address":"9 Hexham St",
    "sg:city":"Warranwood",
    "sg:classifiers":[
        {
            "category":"Professional",
            "subcategory":"Computer Services",
            "type":"Services"
        }
    ],
    "sg:phone":"+61 3 9876 6195",
    "sg:postcode":"3134",
    "sg:province":"VIC",
    "sg:tags":[
        "consultant",
        "system"
    ],
    "wof:name":"SoftClick",
    "wof:placetype":"venue"
},
  "geometry": {"coordinates":[145.24310302699999,-37.7784805298],"type":"Point"}
}