{
  "type": "Feature",
  "properties": {
    "addr:full":"Elizabeth St Nathalia VIC 3638",
    "addr:postcode":"3638",
    "addr:street":"Elizabeth St",
    "iso:country":"AU",
    "sg:address":"Elizabeth St",
    "sg:city":"Nathalia",
    "sg:classifiers":[
        {
            "category":"Retail",
            "subcategory":"Auto Repair",
            "type":"Services"
        }
    ],
    "sg:phone":"+61 3 5866 2473",
    "sg:postcode":"3638",
    "sg:province":"VIC",
    "sg:tags":[
        "wheel",
        "balancing",
        "alignment"
    ],
    "wof:name":"Tyrepower",
    "wof:placetype":"venue"
},
  "geometry": {"coordinates":[145.203811645,-36.0518035889],"type":"Point"}
}