{
  "type": "Feature",
  "properties": {
    "iso:country":"AU",
    "sg:address":"Cnr Cahill & Mafeking Sts",
    "sg:city":"Kalgoorlie",
    "sg:classifiers":[
        {
            "category":"Education",
            "subcategory":"School",
            "type":"Public Place"
        }
    ],
    "sg:phone":"+61 8 9021 2542",
    "sg:postcode":"6430",
    "sg:province":"WA",
    "sg:tags":[
        "state",
        "except",
        "nsw"
    ],
    "wof:name":"East Kalgoorlie Primary School",
    "wof:placetype":"venue"
},
  "geometry": {"coordinates":[121.484046936,-30.7465343475],"type":"Point"}
}