{
  "type": "Feature",
  "properties": {
    "iso:country":"AU",
    "sg:address":"30 Swift St",
    "sg:city":"Ballina",
    "sg:classifiers":[
        {
            "category":"Social Services",
            "subcategory":"Child Care",
            "type":"Services"
        }
    ],
    "sg:phone":"+61 2 6681 1790",
    "sg:postcode":"2478",
    "sg:province":"NSW",
    "wof:name":"Ballina Out Of School Hours & Vacation Care",
    "wof:placetype":"venue"
},
  "geometry": {"coordinates":[153.56590270999999,-28.8686790466],"type":"Point"}
}