{
  "type": "Feature",
  "properties": {
    "addr:full":"23 Robb St Belmont NSW 2280",
    "addr:housenumber":"23",
    "addr:postcode":"2280",
    "addr:street":"Robb St",
    "iso:country":"AU",
    "sg:address":"23 Robb St",
    "sg:city":"Belmont",
    "sg:classifiers":[
        {
            "category":"Personal",
            "subcategory":"Massage",
            "type":"Services"
        }
    ],
    "sg:phone":"+61 2 4945 3380",
    "sg:postcode":"2280",
    "sg:province":"NSW",
    "sg:tags":[
        "therapy"
    ],
    "wof:name":"Belmont Remedial Massage Clinic",
    "wof:placetype":"venue"
},
  "geometry": {"coordinates":[151.65687560999999,-33.0302276611],"type":"Point"}
}