{
  "type": "Feature",
  "properties": {
    "iso:country":"AU",
    "sg:address":"5 Marine Pde",
    "sg:city":"Manly",
    "sg:classifiers":[
        {
            "category":"Social Services",
            "subcategory":"Retirement Home",
            "type":"Services"
        }
    ],
    "sg:phone":"+61 2 9976 2270",
    "sg:postcode":"2095",
    "sg:province":"NSW",
    "sg:tags":[
        "environmental",
        "consultant",
        "pollution"
    ],
    "wof:name":"Clark Paul Consultancy",
    "wof:placetype":"venue"
},
  "geometry": {"coordinates":[151.29360961899999,-33.8009986877],"type":"Point"}
}