{
  "type": "Feature",
  "properties": {
    "iso:country":"AU",
    "sg:address":"Park St",
    "sg:city":"Rockhampton",
    "sg:classifiers":[
        {
            "category":"Home & Garden",
            "subcategory":"Building Materials",
            "type":"Retail Goods"
        }
    ],
    "sg:phone":"+61 7 4928 5244",
    "sg:postcode":"4700",
    "sg:province":"QLD",
    "sg:tags":[
        "pre-mixed",
        "concrete"
    ],
    "wof:name":"Readymix",
    "wof:placetype":"venue"
},
  "geometry": {"coordinates":[150.50599670400001,-23.3634967804],"type":"Point"}
}