{
  "type": "Feature",
  "properties": {
    "iso:country":"AU",
    "sg:address":"25 Kalang Rd",
    "sg:city":"Camberwell",
    "sg:classifiers":[
        {
            "category":"Professional",
            "subcategory":"Management & Consulting",
            "type":"Services"
        }
    ],
    "sg:phone":"+61 3 9809 4762",
    "sg:postcode":"3124",
    "sg:province":"VIC",
    "sg:tags":[
        "consultant"
    ],
    "wof:name":"Grail Quest Solutions",
    "wof:placetype":"venue"
},
  "geometry": {"coordinates":[145.07997131400001,-37.8439865112],"type":"Point"}
}