{
  "type": "Feature",
  "properties": {
    "addr:full":"Unit 3/ 7 Boona St Forster NSW 2428",
    "addr:housenumber":"7",
    "addr:postcode":"2428",
    "addr:street":"Boona St",
    "iso:country":"AU",
    "sg:address":"Unit 3/ 7 Boona St",
    "sg:city":"Forster",
    "sg:classifiers":[
        {
            "category":"Retail",
            "subcategory":"Repair Shop",
            "type":"Services"
        }
    ],
    "sg:phone":"+61 2 6555 5149",
    "sg:postcode":"2428",
    "sg:province":"NSW",
    "sg:tags":[
        "upholsterer"
    ],
    "wof:name":"Shoreline Trimming",
    "wof:placetype":"venue"
},
  "geometry": {"coordinates":[152.52418499999999,-32.198414],"type":"Point"}
}