{
  "type": "Feature",
  "properties": {
    "iso:country":"AU",
    "sg:address":"UR4/ 391 Park Rd",
    "sg:city":"Regents Park",
    "sg:classifiers":[
        {
            "category":"Railroad",
            "type":"Transportation"
        }
    ],
    "sg:phone":"+61 2 8717 9200",
    "sg:postcode":"2143",
    "sg:province":"NSW",
    "sg:tags":[
        "equipment",
        "railway",
        "construction",
        "material"
    ],
    "wof:name":"Delkor Rail Pty Ltd",
    "wof:placetype":"venue"
},
  "geometry": {"coordinates":[151.023925781,-33.881942749],"type":"Point"}
}