{
  "type": "Feature",
  "properties": {
    "addr:full":"12 Fairbairn Rd Busselton WA 6280",
    "addr:housenumber":"12",
    "addr:postcode":"6280",
    "addr:street":"Fairbairn Rd",
    "iso:country":"AU",
    "sg:address":"12 Fairbairn Rd",
    "sg:city":"Busselton",
    "sg:classifiers":[
        {
            "category":"Health Services",
            "subcategory":"Health Practitioner",
            "type":"Services"
        }
    ],
    "sg:phone":"+61 8 9754 3546",
    "sg:postcode":"6280",
    "sg:province":"WA",
    "sg:tags":[
        "naturopath"
    ],
    "wof:name":"Fairbairn Clinic",
    "wof:placetype":"venue"
},
  "geometry": {"coordinates":[115.349113464,-33.6502456665],"type":"Point"}
}