{
  "type": "Feature",
  "properties": {
    "addr:full":"25 Dawson St Croydon NSW 2132",
    "addr:housenumber":"25",
    "addr:postcode":"2132",
    "addr:street":"Dawson St",
    "iso:country":"AU",
    "sg:address":"25 Dawson St",
    "sg:city":"Croydon",
    "sg:classifiers":[
        {
            "category":"Building & Trades",
            "subcategory":"Landscaping Services",
            "type":"Services"
        }
    ],
    "sg:phone":"+61 2 9745 3839",
    "sg:postcode":"2132",
    "sg:province":"NSW",
    "sg:tags":[
        "designer",
        "landscape",
        "contractor"
    ],
    "wof:name":"Catalyst Landscape Design",
    "wof:placetype":"venue"
},
  "geometry": {"coordinates":[151.11770629899999,-33.8723526001],"type":"Point"}
}