{
  "type": "Feature",
  "properties": {
    "addr:full":"56 Iron St North Parramatta NSW 2151",
    "addr:housenumber":"56",
    "addr:postcode":"2151",
    "addr:street":"Iron St",
    "iso:country":"AU",
    "sg:address":"56 Iron St",
    "sg:city":"North Parramatta",
    "sg:classifiers":[
        {
            "category":"Social Services",
            "subcategory":"Child Care",
            "type":"Services"
        }
    ],
    "sg:phone":"+61 2 9630 1055",
    "sg:postcode":"2151",
    "sg:province":"NSW",
    "wof:name":"Parramatta Preschool & Long Day Care",
    "wof:placetype":"venue"
},
  "geometry": {"coordinates":[151.00462341299999,-33.7944984436],"type":"Point"}
}