{
  "type": "Feature",
  "properties": {
    "addr:full":"Suite 2, 52 Burelli St Wollongong NSW 2500",
    "addr:housenumber":"52",
    "addr:postcode":"2500",
    "addr:street":"Burelli St",
    "iso:country":"AU",
    "sg:address":"Suite 2, 52 Burelli St",
    "sg:city":"Wollongong",
    "sg:classifiers":[
        {
            "category":"Banks & Credit Unions",
            "subcategory":"Investment Brokerage",
            "type":"Services"
        }
    ],
    "sg:phone":"+61 2 4228 1100",
    "sg:postcode":"2500",
    "sg:province":"NSW",
    "wof:name":"Spinelli Paul",
    "wof:placetype":"venue"
},
  "geometry": {"coordinates":[150.896942,-34.426426],"type":"Point"}
}