{
  "type": "Feature",
  "properties": {
    "iso:country":"AU",
    "sg:address":"Shop 84, Jackson Court Shopping Centre",
    "sg:city":"Doncaster East",
    "sg:classifiers":[
        {
            "category":"Personal",
            "subcategory":"Tanning Parlor",
            "type":"Services"
        }
    ],
    "sg:phone":"+61 3 9840 1116",
    "sg:postcode":"3109",
    "sg:province":"VIC",
    "sg:tags":[
        "solarium"
    ],
    "wof:name":"Sunlounge Tanning Studios",
    "wof:placetype":"venue"
},
  "geometry": {"coordinates":[145.14805602999999,-37.7886924744],"type":"Point"}
}