{
  "type": "Feature",
  "properties": {
    "addr:full":"Unit 12/ 92a Mona Vale Rd Warriewood NSW 2102",
    "addr:housenumber":"/ 92a",
    "addr:postcode":"2102",
    "addr:street":"Mona Vale Rd",
    "iso:country":"AU",
    "sg:address":"Unit 12/ 92a Mona Vale Rd",
    "sg:city":"Warriewood",
    "sg:classifiers":[
        {
            "category":"Professional",
            "subcategory":"Business Services",
            "type":"Services"
        }
    ],
    "sg:phone":"+61 2 9516 3344",
    "sg:postcode":"2102",
    "sg:province":"NSW",
    "sg:tags":[
        "salesperson"
    ],
    "wof:name":"Blue Swimmer Group",
    "wof:placetype":"venue"
},
  "geometry": {"coordinates":[151.28919999999999,-33.676109],"type":"Point"}
}