{
  "type": "Feature",
  "properties": {
    "addr:full":"PO Box 108 Yarrawonga VIC 3730",
    "addr:postcode":"3730",
    "iso:country":"AU",
    "sg:address":"PO Box 108",
    "sg:city":"Yarrawonga",
    "sg:classifiers":[
        {
            "category":"Home & Garden",
            "subcategory":"Household Appliances",
            "type":"Retail Goods"
        }
    ],
    "sg:phone":"+61 3 5744 3066",
    "sg:postcode":"3730",
    "sg:province":"VIC",
    "sg:tags":[
        "heating",
        "system"
    ],
    "wof:name":"Yarrawonga Heating & Cooling",
    "wof:placetype":"venue"
},
  "geometry": {"coordinates":[146.00526428200001,-36.017490387],"type":"Point"}
}