{
  "type": "Feature",
  "properties": {
    "iso:country":"AU",
    "sg:address":"MS 110 Haden Trapp Rd",
    "sg:city":"Coalbank",
    "sg:classifiers":[
        {
            "category":"Landmark",
            "subcategory":"Square",
            "type":"Public Place"
        }
    ],
    "sg:phone":"+61 7 4692 6143",
    "sg:postcode":"4352",
    "sg:province":"QLD",
    "sg:tags":[
        "product",
        "ostrich",
        "farmer"
    ],
    "wof:name":"Doug & Margaret Nothdurft",
    "wof:placetype":"venue"
},
  "geometry": {"coordinates":[151.86099200000001,-27.106613],"type":"Point"}
}