{
  "type": "Feature",
  "properties": {
    "addr:full":"Manifold St Woolsthorpe VIC 3276",
    "addr:postcode":"3276",
    "addr:street":"Manifold St",
    "iso:country":"AU",
    "sg:address":"Manifold St",
    "sg:city":"Woolsthorpe",
    "sg:classifiers":[
        {
            "category":"Building & Trades",
            "subcategory":"Construction",
            "type":"Services"
        }
    ],
    "sg:phone":"+61 3 5569 2356",
    "sg:postcode":"3276",
    "sg:province":"VIC",
    "sg:tags":[
        "earth",
        "excavating",
        "moving",
        "contractor"
    ],
    "wof:name":"L Davidson & Sons",
    "wof:placetype":"venue"
},
  "geometry": {"coordinates":[142.43199157699999,-38.1830101013],"type":"Point"}
}