{
  "type": "Feature",
  "properties": {
    "iso:country":"AU",
    "sg:address":"418a Unwins Bridge Rd",
    "sg:city":"Tempe",
    "sg:classifiers":[
        {
            "category":"Professional",
            "subcategory":"Accounting & Tax Preparation",
            "type":"Services"
        }
    ],
    "sg:phone":"+61 2 9558 5388",
    "sg:postcode":"2044",
    "sg:province":"NSW",
    "sg:tags":[
        "consultant",
        "taxation"
    ],
    "wof:name":"Alfa Tax Consultants Pty Ltd",
    "wof:placetype":"venue"
},
  "geometry": {"coordinates":[151.15777600000001,-33.922756],"type":"Point"}
}