{
  "type": "Feature",
  "properties": {
    "iso:country":"AU",
    "sg:address":"152 Lambton Rd",
    "sg:city":"Broadmeadow",
    "sg:classifiers":[
        {
            "category":"Health Services",
            "subcategory":"Doctor",
            "type":"Services"
        }
    ],
    "sg:phone":"+61 1800 152 737",
    "sg:postcode":"2292",
    "sg:province":"NSW",
    "sg:tags":[
        "medical",
        "practitioner"
    ],
    "wof:name":"The Laservision Centre",
    "wof:placetype":"venue"
},
  "geometry": {"coordinates":[151.72450256400001,-32.9231719971],"type":"Point"}
}