{
  "type": "Feature",
  "properties": {
    "addr:full":"1 Stott Rd Welshpool WA 6106",
    "addr:housenumber":"1",
    "addr:postcode":"6106",
    "addr:street":"Stott Rd",
    "iso:country":"AU",
    "sg:address":"1 Stott Rd",
    "sg:city":"Welshpool",
    "sg:classifiers":[
        {
            "category":"Wholesale",
            "subcategory":"Machinery & Supplies",
            "type":"Manufacturing & Wholesale Goods"
        }
    ],
    "sg:phone":"+61 8 9351 9352",
    "sg:postcode":"6106",
    "sg:province":"WA",
    "wof:name":"Haco-Kingsland Australia",
    "wof:placetype":"venue"
},
  "geometry": {"coordinates":[115.960037231,-31.9938640594],"type":"Point"}
}