{
  "type": "Feature",
  "properties": {
    "addr:full":"1 McAuley Drv Ballarat VIC 3350",
    "addr:housenumber":"1",
    "addr:postcode":"3350",
    "addr:street":"Mcauley Drv",
    "iso:country":"AU",
    "sg:address":"1 McAuley Drv",
    "sg:city":"Ballarat",
    "sg:classifiers":[
        {
            "category":"Professional",
            "subcategory":"Art Services",
            "type":"Services"
        }
    ],
    "sg:phone":"+61 3 5334 7188",
    "sg:postcode":"3350",
    "sg:province":"VIC",
    "sg:tags":[
        "artist"
    ],
    "wof:name":"Wade Perrett Artist",
    "wof:placetype":"venue"
},
  "geometry": {"coordinates":[143.90501399999999,-37.554127],"type":"Point"}
}