{
  "type": "Feature",
  "properties": {
    "addr:full":"Factory 3/ 215 Nicholson St Brunswick VIC 3056",
    "addr:housenumber":"/ 215",
    "addr:postcode":"3056",
    "addr:street":"Nicholson St",
    "iso:country":"AU",
    "sg:address":"Factory 3/ 215 Nicholson St",
    "sg:city":"Brunswick",
    "sg:classifiers":[
        {
            "category":"Retail",
            "subcategory":"Laundry & Dry Cleaning",
            "type":"Services"
        }
    ],
    "sg:phone":"+61 3 9380 2859",
    "sg:postcode":"3056",
    "sg:province":"VIC",
    "sg:tags":[
        "ironing"
    ],
    "wof:name":"Designers Pressing Service",
    "wof:placetype":"venue"
},
  "geometry": {"coordinates":[144.979934692,-37.7678146362],"type":"Point"}
}