{
  "type": "Feature",
  "properties": {
    "iso:country":"AU",
    "sg:address":"Level 4 Imperial Arcade 83-85 Castlereagh St",
    "sg:city":"Sydney",
    "sg:classifiers":[
        {
            "category":"Education",
            "subcategory":"Dance Studio",
            "type":"Public Place"
        }
    ],
    "sg:phone":"+61 2 9232 7000",
    "sg:postcode":"2000",
    "sg:province":"NSW",
    "sg:tags":[
        "instruction",
        "language"
    ],
    "wof:name":"Academy Of English",
    "wof:placetype":"venue"
},
  "geometry": {"coordinates":[151.209442139,-33.86977005],"type":"Point"}
}