{
  "type": "Feature",
  "properties": {
    "addr:full":"80 Smith St Broulee NSW 2537",
    "addr:housenumber":"80",
    "addr:postcode":"2537",
    "addr:street":"Smith St",
    "iso:country":"AU",
    "sg:address":"80 Smith St",
    "sg:city":"Broulee",
    "sg:classifiers":[
        {
            "category":"Building & Trades",
            "subcategory":"Construction",
            "type":"Services"
        }
    ],
    "sg:phone":"+61 2 4471 6971",
    "sg:postcode":"2537",
    "sg:province":"NSW",
    "sg:tags":[
        "contractor"
    ],
    "wof:name":"Aussie Steel Homes Nature Coast",
    "wof:placetype":"venue"
},
  "geometry": {"coordinates":[150.175292969,-35.8506546021],"type":"Point"}
}