{
  "type": "Feature",
  "properties": {
    "addr:full":"88a Kent St East Victoria Park WA 6101",
    "addr:housenumber":"88a",
    "addr:postcode":"6101",
    "addr:street":"Kent St",
    "iso:country":"AU",
    "sg:address":"88a Kent St",
    "sg:city":"East Victoria Park",
    "sg:classifiers":[
        {
            "category":"Communications",
            "type":"Services"
        }
    ],
    "sg:phone":"+61 8 9362 2405",
    "sg:postcode":"6101",
    "sg:province":"WA",
    "sg:tags":[
        "public",
        "system",
        "address"
    ],
    "wof:name":"Audio West",
    "wof:placetype":"venue"
},
  "geometry": {"coordinates":[115.89749145499999,-31.9842624664],"type":"Point"}
}