{
  "type": "Feature",
  "properties": {
    "iso:country":"AU",
    "sg:address":"436 Main Rd",
    "sg:city":"Glenorchy",
    "sg:classifiers":[
        {
            "category":"Autos & Motor Vehicles",
            "subcategory":"Fuel & Gas Station",
            "type":"Retail Goods"
        }
    ],
    "sg:phone":"+61 3 6272 7462",
    "sg:postcode":"7010",
    "sg:province":"TAS",
    "wof:name":"BP Glenorchy",
    "wof:placetype":"venue"
},
  "geometry": {"coordinates":[147.269897461,-42.8309669495],"type":"Point"}
}