{
  "type": "Feature",
  "properties": {
    "addr:full":"30-34 Young St Cowra NSW 2794",
    "addr:housenumber":"30-34",
    "addr:postcode":"2794",
    "addr:street":"Young St",
    "iso:country":"AU",
    "sg:address":"30-34 Young St",
    "sg:city":"Cowra",
    "sg:classifiers":[
        {
            "category":"Professional",
            "subcategory":"Engineering",
            "type":"Services"
        }
    ],
    "sg:phone":"+61 2 6341 2244",
    "sg:postcode":"2794",
    "sg:province":"NSW",
    "sg:tags":[
        "engineer"
    ],
    "wof:name":"Lachlan Engineering Services",
    "wof:placetype":"venue"
},
  "geometry": {"coordinates":[148.673660278,-33.8423843384],"type":"Point"}
}