{
  "type": "Feature",
  "properties": {
    "iso:country":"AU",
    "sg:address":"3 Fan Palm Crt",
    "sg:city":"Ulladulla",
    "sg:classifiers":[
        {
            "category":"Professional",
            "subcategory":"Business Services",
            "type":"Services"
        }
    ],
    "sg:phone":"+61 2 4454 2887",
    "sg:postcode":"2539",
    "sg:province":"NSW",
    "sg:tags":[
        "drafting"
    ],
    "wof:name":"ADS Drafting & Design",
    "wof:placetype":"venue"
},
  "geometry": {"coordinates":[150.45700073200001,-35.3464164734],"type":"Point"}
}