{
  "type": "Feature",
  "properties": {
    "addr:full":"46 Portland Rd Heywood VIC 3304",
    "addr:housenumber":"46",
    "addr:postcode":"3304",
    "addr:street":"Portland Rd",
    "iso:country":"AU",
    "sg:address":"46 Portland Rd",
    "sg:city":"Heywood",
    "sg:classifiers":[
        {
            "category":"Farming",
            "subcategory":"Farm",
            "type":"Manufacturing & Wholesale Goods"
        }
    ],
    "sg:phone":"+61 3 5527 1620",
    "sg:postcode":"3304",
    "sg:province":"VIC",
    "sg:tags":[
        "farmer"
    ],
    "wof:name":"Wilson Syd",
    "wof:placetype":"venue"
},
  "geometry": {"coordinates":[141.90667724599999,-38.1882171631],"type":"Point"}
}