{
  "type": "Feature",
  "properties": {
    "addr:full":"47 Harpin St Bendigo VIC 3550",
    "addr:housenumber":"47",
    "addr:postcode":"3550",
    "addr:street":"Harpin St",
    "iso:country":"AU",
    "sg:address":"47 Harpin St",
    "sg:city":"Bendigo",
    "sg:classifiers":[
        {
            "category":"Travel",
            "subcategory":"Hostel",
            "type":"Entertainment"
        }
    ],
    "sg:phone":"+61 3 5444 4050",
    "sg:postcode":"3550",
    "sg:province":"VIC",
    "sg:tags":[
        "home"
    ],
    "wof:name":"Bentleys Aged Care",
    "wof:placetype":"venue"
},
  "geometry": {"coordinates":[144.30560302699999,-36.7525215149],"type":"Point"}
}