{
  "type": "Feature",
  "properties": {
    "iso:country":"AU",
    "sg:address":"24 Hill St",
    "sg:city":"Camden",
    "sg:classifiers":[
        {
            "category":"Banks & Credit Unions",
            "subcategory":"Financial Services",
            "type":"Services"
        }
    ],
    "sg:phone":"+61 2 8205 1228",
    "sg:postcode":"2570",
    "sg:province":"NSW",
    "sg:tags":[
        "planning"
    ],
    "sg:website":"http://www.fpa.asn.au",
    "wof:name":"Stevens & Associates Financial Services P/L",
    "wof:placetype":"venue"
},
  "geometry": {"coordinates":[150.69778442399999,-34.0550613403],"type":"Point"}
}