{
  "type": "Feature",
  "properties": {
    "addr:full":"Clyde St Studios, Studio 6/ 92 Clyde St St Kilda VIC 3182",
    "addr:housenumber":"92",
    "addr:postcode":"3182",
    "addr:street":"Clyde;Clyde St",
    "iso:country":"AU",
    "sg:address":"Clyde St Studios, Studio 6/ 92 Clyde St",
    "sg:city":"St Kilda",
    "sg:classifiers":[
        {
            "category":"Personal",
            "subcategory":"Massage",
            "type":"Services"
        }
    ],
    "sg:phone":"+61 412 942 798",
    "sg:postcode":"3182",
    "sg:province":"VIC",
    "sg:tags":[
        "therapy"
    ],
    "wof:name":"Live Life Massage",
    "wof:placetype":"venue"
},
  "geometry": {"coordinates":[144.981079102,-37.8638496399],"type":"Point"}
}