{
  "type": "Feature",
  "properties": {
    "addr:full":"65 Lindsay St Launceston TAS 7250",
    "addr:housenumber":"65",
    "addr:postcode":"7250",
    "addr:street":"Lindsay St",
    "iso:country":"AU",
    "sg:address":"65 Lindsay St",
    "sg:city":"Launceston",
    "sg:classifiers":[
        {
            "category":"Mining & Drilling",
            "type":"Manufacturing & Wholesale Goods"
        }
    ],
    "sg:phone":"+61 3 6334 0133",
    "sg:postcode":"7250",
    "sg:province":"TAS",
    "sg:tags":[
        "concrete",
        "breaking",
        "grinding",
        "sawing"
    ],
    "wof:name":"Schouten Concrete Constructions Pty Ltd",
    "wof:placetype":"venue"
},
  "geometry": {"coordinates":[147.13406372099999,-41.4304885864],"type":"Point"}
}