{
  "type": "Feature",
  "properties": {
    "iso:country":"AU",
    "sg:address":"116 Watton St",
    "sg:city":"Werribee",
    "sg:classifiers":[
        {
            "category":"Structure",
            "subcategory":"Bridge",
            "type":"Public Place"
        }
    ],
    "sg:phone":"+61 3 9741 3555",
    "sg:postcode":"3030",
    "sg:province":"VIC",
    "sg:tags":[
        "chainsaw",
        "brushcutters"
    ],
    "wof:name":"Biland Trading",
    "wof:placetype":"venue"
},
  "geometry": {"coordinates":[144.65664699999999,-37.903748],"type":"Point"}
}