{
  "type": "Feature",
  "properties": {
    "addr:full":"1a Ormond St Paddington NSW 2021",
    "addr:housenumber":"1a",
    "addr:postcode":"2021",
    "addr:street":"Ormond St",
    "iso:country":"AU",
    "sg:address":"1a Ormond St",
    "sg:city":"Paddington",
    "sg:classifiers":[
        {
            "category":"Retail",
            "subcategory":"Auto Repair",
            "type":"Services"
        }
    ],
    "sg:phone":"+61 2 9331 4289",
    "sg:postcode":"2021",
    "sg:province":"NSW",
    "sg:tags":[
        "repairer",
        "motor",
        "engineer"
    ],
    "wof:name":"LR Prestige Performance",
    "wof:placetype":"venue"
},
  "geometry": {"coordinates":[151.22674560600001,-33.8845367432],"type":"Point"}
}