{
  "type": "Feature",
  "properties": {
    "iso:country":"AU",
    "sg:address":"23 Chard Rd",
    "sg:city":"Brookvale",
    "sg:classifiers":[
        {
            "category":"Retail",
            "subcategory":"Auto Repair",
            "type":"Services"
        }
    ],
    "sg:phone":"+61 2 9939 7720",
    "sg:postcode":"2100",
    "sg:province":"NSW",
    "sg:tags":[
        "repairer",
        "motor",
        "engineer"
    ],
    "wof:name":"Northside Hi-Performance Centre",
    "wof:placetype":"venue"
},
  "geometry": {"coordinates":[151.27403259299999,-33.7634124756],"type":"Point"}
}