{
  "type": "Feature",
  "properties": {
    "iso:country":"AU",
    "sg:address":"20 Jewell Pde",
    "sg:city":"North Fremantle",
    "sg:classifiers":[
        {
            "category":"Mining & Drilling",
            "type":"Manufacturing & Wholesale Goods"
        }
    ],
    "sg:phone":"+61 8 9430 7232",
    "sg:postcode":"6159",
    "sg:province":"WA",
    "sg:tags":[
        "equipment",
        "quarrying",
        "supply"
    ],
    "wof:name":"Australian Mining Technologies",
    "wof:placetype":"venue"
},
  "geometry": {"coordinates":[115.753113,-32.03558],"type":"Point"}
}