{
  "type": "Feature",
  "properties": {
    "iso:country":"AU",
    "sg:address":"RP 44929",
    "sg:city":"Harrogate",
    "sg:classifiers":[
        {
            "category":"Building & Trades",
            "subcategory":"Landscaping Services",
            "type":"Services"
        }
    ],
    "sg:phone":"+61 428 600 075",
    "sg:postcode":"5244",
    "sg:province":"SA",
    "sg:tags":[
        "stump",
        "tree",
        "felling",
        "removal"
    ],
    "wof:name":"Trees By Burke",
    "wof:placetype":"venue"
},
  "geometry": {"coordinates":[138.94154357900001,-34.9844398499],"type":"Point"}
}