{
  "type": "Feature",
  "properties": {
    "iso:country":"AU",
    "sg:address":"PO Box 222",
    "sg:city":"Leumeah",
    "sg:classifiers":[
        {
            "category":"Building & Trades",
            "subcategory":"Landscaping Services",
            "type":"Services"
        }
    ],
    "sg:phone":"+61 1300 446 773",
    "sg:postcode":"2560",
    "sg:province":"NSW",
    "sg:tags":[
        "consultant"
    ],
    "wof:name":"Buildit Constructions Inspection Service",
    "wof:placetype":"venue"
},
  "geometry": {"coordinates":[150.83424377399999,-34.0516700745],"type":"Point"}
}