{
  "type": "Feature",
  "properties": {
    "iso:country":"AU",
    "sg:address":"George Town Airport North St",
    "sg:city":"George Town",
    "sg:classifiers":[
        {
            "category":"Education",
            "subcategory":"Special Training",
            "type":"Public Place"
        }
    ],
    "sg:phone":"+61 3 6382 4700",
    "sg:postcode":"7253",
    "sg:province":"TAS",
    "sg:tags":[
        "school",
        "flying"
    ],
    "wof:name":"Freedom Flight Pty Ltd",
    "wof:placetype":"venue"
},
  "geometry": {"coordinates":[146.83401489299999,-41.0845298767],"type":"Point"}
}