{
  "type": "Feature",
  "properties": {
    "addr:full":"1/3A Smart St Mall Mandurah WA 6210",
    "addr:housenumber":"/ 3a",
    "addr:postcode":"6210",
    "addr:street":"Smart St Mall",
    "iso:country":"AU",
    "sg:address":"1/3A Smart St",
    "sg:city":"Mall Mandurah",
    "sg:classifiers":[
        {
            "category":"Shopping",
            "subcategory":"Clothing, Apparel, & Fashions",
            "type":"Retail Goods"
        }
    ],
    "sg:phone":"+61 8 9535 5955",
    "sg:postcode":"6210",
    "sg:province":"WA",
    "sg:tags":[
        "maternity",
        "wear"
    ],
    "wof:name":"Pea In A Pod",
    "wof:placetype":"venue"
},
  "geometry": {"coordinates":[115.719398,-32.533474],"type":"Point"}
}