{
  "type": "Feature",
  "properties": {
    "iso:country":"AU",
    "sg:address":"Factory 3/ 21 Eugene Tce",
    "sg:city":"Ringwood",
    "sg:classifiers":[
        {
            "category":"Building & Trades",
            "subcategory":"Construction",
            "type":"Services"
        }
    ],
    "sg:phone":"+61 3 9879 2929",
    "sg:postcode":"3134",
    "sg:province":"VIC",
    "sg:tags":[
        "welding"
    ],
    "wof:name":"Gyra Engineering Pty Ltd",
    "wof:placetype":"venue"
},
  "geometry": {"coordinates":[145.21890258799999,-37.8254547119],"type":"Point"}
}