{
  "type": "Feature",
  "properties": {
    "addr:full":"234 Wells Rd Chelsea Heights VIC 3196",
    "addr:housenumber":"234",
    "addr:postcode":"3196",
    "addr:street":"Wells Rd",
    "iso:country":"AU",
    "sg:address":"234 Wells Rd",
    "sg:city":"Chelsea Heights",
    "sg:classifiers":[
        {
            "category":"Personal",
            "subcategory":"Hair Removal",
            "type":"Services"
        }
    ],
    "sg:phone":"+61 3 9773 9366",
    "sg:postcode":"3196",
    "sg:province":"VIC",
    "wof:name":"Tara's Beautique",
    "wof:placetype":"venue"
},
  "geometry": {"coordinates":[145.141815186,-38.0477104187],"type":"Point"}
}