{
  "type": "Feature",
  "properties": {
    "iso:country":"AU",
    "sg:address":"7/ 5 Steel St",
    "sg:city":"Blacktown",
    "sg:classifiers":[
        {
            "category":"Retail",
            "subcategory":"Auto Repair",
            "type":"Services"
        }
    ],
    "sg:phone":"+61 2 9671 3608",
    "sg:postcode":"2148",
    "sg:province":"NSW",
    "sg:tags":[
        "body",
        "motor",
        "trimmer"
    ],
    "wof:name":"Bob's Auto Upholstery",
    "wof:placetype":"venue"
},
  "geometry": {"coordinates":[150.91432189899999,-33.7562599182],"type":"Point"}
}