{
  "type": "Feature",
  "properties": {
    "iso:country":"AU",
    "sg:address":"383 Kiamba Rd",
    "sg:city":"Yandina",
    "sg:classifiers":[
        {
            "category":"Wholesale",
            "subcategory":"Furniture",
            "type":"Manufacturing & Wholesale Goods"
        }
    ],
    "sg:phone":"+61 7 5446 7797",
    "sg:postcode":"4561",
    "sg:province":"QLD",
    "sg:tags":[
        "wholesaler",
        "mfrs"
    ],
    "wof:name":"Solid Wood Furniture & Kitchens",
    "wof:placetype":"venue"
},
  "geometry": {"coordinates":[152.91734314000001,-26.5599651337],"type":"Point"}
}