{
  "type": "Feature",
  "properties": {
    "addr:full":"25 Higgerson Ave Engadine NSW 2233",
    "addr:housenumber":"25",
    "addr:postcode":"2233",
    "addr:street":"Higgerson Ave",
    "iso:country":"AU",
    "sg:address":"25 Higgerson Ave",
    "sg:city":"Engadine",
    "sg:classifiers":[
        {
            "category":"Shopping",
            "subcategory":"Clothing, Apparel, & Fashions",
            "type":"Retail Goods"
        }
    ],
    "sg:phone":"+61 2 9548 6008",
    "sg:postcode":"2233",
    "sg:province":"NSW",
    "sg:tags":[
        "accessory"
    ],
    "wof:name":"Sky Trade",
    "wof:placetype":"venue"
},
  "geometry": {"coordinates":[151.00547790499999,-34.071937561],"type":"Point"}
}