{
  "type": "Feature",
  "properties": {
    "iso:country":"AU",
    "sg:address":"PO Box 232",
    "sg:city":"Coogee",
    "sg:classifiers":[
        {
            "category":"Communications",
            "type":"Services"
        }
    ],
    "sg:phone":"+61 414 392 711",
    "sg:postcode":"2034",
    "sg:province":"NSW",
    "sg:tags":[
        "translation"
    ],
    "wof:name":"Alfonso Isabel",
    "wof:placetype":"venue"
},
  "geometry": {"coordinates":[151.25601196299999,-33.9207305908],"type":"Point"}
}