{
  "type": "Feature",
  "properties": {
    "addr:full":"Ross La Lennox Head NSW 2478",
    "addr:postcode":"2478",
    "addr:street":"La",
    "iso:country":"AU",
    "sg:address":"Ross La",
    "sg:city":"Lennox Head",
    "sg:classifiers":[
        {
            "category":"Place Of Worship",
            "subcategory":"Monastery",
            "type":"Public Place"
        }
    ],
    "sg:phone":"+61 2 6687 6022",
    "sg:postcode":"2478",
    "sg:province":"NSW",
    "sg:tags":[
        "residential",
        "village"
    ],
    "wof:name":"The Sanctuary Mobile Home Park Pty Ltd",
    "wof:placetype":"venue"
},
  "geometry": {"coordinates":[153.59307861299999,-28.7865028381],"type":"Point"}
}