{
  "type": "Feature",
  "properties": {
    "iso:country":"AU",
    "sg:address":"Level 4, 10 Help St",
    "sg:city":"Chatswood",
    "sg:classifiers":[
        {
            "category":"Banks & Credit Unions",
            "subcategory":"Financial Services",
            "type":"Services"
        }
    ],
    "sg:phone":"+61 2 9419 4777",
    "sg:postcode":"2067",
    "sg:province":"NSW",
    "sg:tags":[
        "advisory",
        "planning",
        "retirement"
    ],
    "wof:name":"Bleakleys Limited",
    "wof:placetype":"venue"
},
  "geometry": {"coordinates":[151.18182373100001,-33.7952423096],"type":"Point"}
}