{
  "type": "Feature",
  "properties": {
    "iso:country":"AU",
    "sg:address":"8- 12 Pakington St",
    "sg:city":"Geelong West",
    "sg:classifiers":[
        {
            "category":"Shopping",
            "subcategory":"Computers & Home Electronics",
            "type":"Retail Goods"
        }
    ],
    "sg:phone":"+61 3 5227 6888",
    "sg:postcode":"3218",
    "sg:province":"VIC",
    "sg:tags":[
        "hardware",
        "equipment"
    ],
    "wof:name":"BCC Computers",
    "wof:placetype":"venue"
},
  "geometry": {"coordinates":[144.34994506800001,-38.1329231262],"type":"Point"}
}