{
  "type": "Feature",
  "properties": {
    "addr:full":"Suite 2/ 990 Albany Hwy East Victoria Park WA 6101",
    "addr:housenumber":"/ 990",
    "addr:postcode":"6101",
    "addr:street":"Albany Hwy",
    "iso:country":"AU",
    "sg:address":"Suite 2/ 990 Albany Hwy",
    "sg:city":"East Victoria Park",
    "sg:classifiers":[
        {
            "category":"Professional",
            "subcategory":"Accounting & Tax Preparation",
            "type":"Services"
        }
    ],
    "sg:phone":"+61 8 9361 0911",
    "sg:postcode":"6101",
    "sg:province":"WA",
    "sg:tags":[
        "accountant",
        "auditor"
    ],
    "wof:name":"Clark & Associates",
    "wof:placetype":"venue"
},
  "geometry": {"coordinates":[115.909927368,-31.9915313721],"type":"Point"}
}