{
  "type": "Feature",
  "properties": {
    "addr:full":"21 Foster St Parkside SA 5063",
    "addr:housenumber":"21",
    "addr:postcode":"5063",
    "addr:street":"Foster St",
    "iso:country":"AU",
    "sg:address":"21 Foster St",
    "sg:city":"Parkside",
    "sg:classifiers":[
        {
            "category":"Health Services",
            "subcategory":"Doctor",
            "type":"Services"
        }
    ],
    "sg:phone":"+61 417 853 635",
    "sg:postcode":"5063",
    "sg:province":"SA",
    "sg:tags":[
        "nurse",
        "nursing"
    ],
    "wof:name":"St Louis Lifestyles",
    "wof:placetype":"venue"
},
  "geometry": {"coordinates":[138.62077331500001,-34.9505386353],"type":"Point"}
}