{
  "type": "Feature",
  "properties": {
    "addr:full":"4/ 27 Redleaf Ave Wahroonga NSW 2076",
    "addr:housenumber":"/ 27",
    "addr:postcode":"2076",
    "addr:street":"Redleaf Ave",
    "iso:country":"AU",
    "sg:address":"4/ 27 Redleaf Ave",
    "sg:city":"Wahroonga",
    "sg:classifiers":[
        {
            "category":"Government",
            "subcategory":"Court House",
            "type":"Public Place"
        }
    ],
    "sg:phone":"+61 2 9489 6725",
    "sg:postcode":"2076",
    "sg:province":"NSW",
    "sg:tags":[
        "personal",
        "marriage",
        "family",
        "counselling"
    ],
    "wof:name":"Henry Robyn",
    "wof:placetype":"venue"
},
  "geometry": {"coordinates":[151.11721801799999,-33.7188339233],"type":"Point"}
}