{
  "type": "Feature",
  "properties": {
    "iso:country":"AU",
    "sg:address":"Shop 10 Sunland Plaza, Hervey&#039;s Range Rd",
    "sg:city":"Condon",
    "sg:classifiers":[
        {
            "category":"Banks & Credit Unions",
            "subcategory":"Financial Services",
            "type":"Services"
        }
    ],
    "sg:phone":"+61 7 4723 1855",
    "sg:postcode":"4815",
    "sg:province":"QLD",
    "sg:tags":[
        "building",
        "society"
    ],
    "wof:name":"Mackay Permanent Building Society Ltd",
    "wof:placetype":"venue"
},
  "geometry": {"coordinates":[146.719513,-19.319851],"type":"Point"}
}