{
  "type": "Feature",
  "properties": {
    "addr:full":"221 Tugrah Rd Devonport TAS 7310",
    "addr:housenumber":"221",
    "addr:postcode":"7310",
    "addr:street":"Tugrah Rd",
    "iso:country":"AU",
    "sg:address":"221 Tugrah Rd",
    "sg:city":"Devonport",
    "sg:classifiers":[
        {
            "category":"Commercial Area",
            "type":"Public Place"
        }
    ],
    "sg:phone":"+61 3 6424 2843",
    "sg:postcode":"7310",
    "sg:province":"TAS",
    "sg:tags":[
        "heavy",
        "carrier"
    ],
    "wof:name":"Boyd Rodney Carriers",
    "wof:placetype":"venue"
},
  "geometry": {"coordinates":[146.30722045900001,-41.199344635],"type":"Point"}
}