{
  "type": "Feature",
  "properties": {
    "addr:full":"PO Box 99 Cobden VIC 3266",
    "addr:postcode":"3266",
    "iso:country":"AU",
    "sg:address":"PO Box 99",
    "sg:city":"Cobden",
    "sg:classifiers":[
        {
            "category":"Commercial Area",
            "type":"Public Place"
        }
    ],
    "sg:phone":"+61 3 5595 1294",
    "sg:postcode":"3266",
    "sg:province":"VIC",
    "sg:tags":[
        "heavy",
        "carrier"
    ],
    "wof:name":"AS & SJ Fenton General Carrier",
    "wof:placetype":"venue"
},
  "geometry": {"coordinates":[143.080245972,-38.3289299011],"type":"Point"}
}