{
  "type": "Feature",
  "properties": {
    "addr:full":"4 Lyell St Fyshwick ACT 2609",
    "addr:housenumber":"4",
    "addr:postcode":"2609",
    "addr:street":"Lyell St",
    "iso:country":"AU",
    "sg:address":"4 Lyell St",
    "sg:city":"Fyshwick",
    "sg:classifiers":[
        {
            "category":"Building & Trades",
            "subcategory":"Construction",
            "type":"Services"
        }
    ],
    "sg:phone":"+61 402 286 595",
    "sg:postcode":"2609",
    "sg:province":"ACT",
    "sg:tags":[
        "welding"
    ],
    "wof:name":"Weldwise",
    "wof:placetype":"venue"
},
  "geometry": {"coordinates":[149.17347717300001,-35.3289527893],"type":"Point"}
}