{
  "type": "Feature",
  "properties": {
    "addr:full":"Gr Fl, 245 Cardigan St Carlton VIC 3053",
    "addr:housenumber":"245",
    "addr:postcode":"3053",
    "addr:street":"Gr;Cardigan St",
    "iso:country":"AU",
    "sg:address":"Gr Fl, 245 Cardigan St",
    "sg:city":"Carlton",
    "sg:classifiers":[
        {
            "category":"Professional",
            "subcategory":"Employment Agencies",
            "type":"Services"
        }
    ],
    "sg:phone":"+61 3 9348 1577",
    "sg:postcode":"3053",
    "sg:province":"VIC",
    "sg:tags":[
        "consultant",
        "casting"
    ],
    "wof:name":"Artists Technologies 2 Pty Ltd",
    "wof:placetype":"venue"
},
  "geometry": {"coordinates":[144.965240478,-37.8009490967],"type":"Point"}
}