{
  "type": "Feature",
  "properties": {
    "addr:full":"10 Kikenny Crt Sorrento QLD 4217",
    "addr:housenumber":"10",
    "addr:postcode":"4217",
    "addr:street":"Kikenny Crt",
    "iso:country":"AU",
    "sg:address":"10 Kikenny Crt",
    "sg:city":"Sorrento",
    "sg:classifiers":[
        {
            "category":"Autos & Motor Vehicles",
            "subcategory":"Automobile Sales",
            "type":"Retail Goods"
        }
    ],
    "sg:phone":"+61 419 999 777",
    "sg:postcode":"4217",
    "sg:province":"QLD",
    "sg:tags":[
        "car",
        "used"
    ],
    "wof:name":"Bennett Peter Wholesale Cars",
    "wof:placetype":"venue"
},
  "geometry": {"coordinates":[153.39878845199999,-28.0204277039],"type":"Point"}
}