{
  "type": "Feature",
  "properties": {
    "iso:country":"AU",
    "sg:address":"Shop 14, Meadow Springs Shopping Centre",
    "sg:city":"Mandurah",
    "sg:classifiers":[
        {
            "category":"Shopping",
            "subcategory":"Optical Goods",
            "type":"Retail Goods"
        }
    ],
    "sg:phone":"+61 8 9581 9955",
    "sg:postcode":"6210",
    "sg:province":"WA",
    "sg:tags":[
        "dispenser",
        "prescription"
    ],
    "wof:name":"Optomize",
    "wof:placetype":"venue"
},
  "geometry": {"coordinates":[115.748917,-32.495216],"type":"Point"}
}