{
  "type": "Feature",
  "properties": {
    "addr:full":"19 Burranjurra Ave Coomba NSW 2428",
    "addr:housenumber":"19",
    "addr:postcode":"2428",
    "addr:street":"Burranjurra Ave",
    "iso:country":"AU",
    "sg:address":"19 Burranjurra Ave",
    "sg:city":"Coomba",
    "sg:classifiers":[
        {
            "category":"Utilities",
            "subcategory":"Electric",
            "type":"Services"
        }
    ],
    "sg:phone":"+61 2 6554 2070",
    "sg:postcode":"2428",
    "sg:province":"NSW",
    "sg:tags":[
        "electrical",
        "contractor"
    ],
    "wof:name":"Davidson W M",
    "wof:placetype":"venue"
},
  "geometry": {"coordinates":[152.472992,-32.242542],"type":"Point"}
}