{
  "type": "Feature",
  "properties": {
    "iso:country":"AU",
    "sg:address":"43 Oswald St",
    "sg:city":"Innaloo",
    "sg:classifiers":[
        {
            "category":"Home & Garden",
            "subcategory":"Building Materials",
            "type":"Retail Goods"
        }
    ],
    "sg:phone":"+61 8 9446 8781",
    "sg:postcode":"6018",
    "sg:province":"WA",
    "sg:tags":[
        "retaining",
        "wall"
    ],
    "wof:name":"Michael Figliomeni",
    "wof:placetype":"venue"
},
  "geometry": {"coordinates":[115.799766541,-31.8997859955],"type":"Point"}
}