{
  "type": "Feature",
  "properties": {
    "addr:full":"362 McKenzie St Toowoomba QLD 4350",
    "addr:housenumber":"362",
    "addr:postcode":"4350",
    "addr:street":"Mckenzie St",
    "iso:country":"AU",
    "sg:address":"362 McKenzie St",
    "sg:city":"Toowoomba",
    "sg:classifiers":[
        {
            "category":"Personal",
            "subcategory":"Massage",
            "type":"Services"
        }
    ],
    "sg:phone":"+61 7 4687 6200",
    "sg:postcode":"4350",
    "sg:province":"QLD",
    "sg:tags":[
        "therapy"
    ],
    "wof:name":"Ian & Anna Lee",
    "wof:placetype":"venue"
},
  "geometry": {"coordinates":[151.96916200000001,-27.59914],"type":"Point"}
}