{
  "type": "Feature",
  "properties": {
    "addr:full":"Suite 4, Jack Simmons Centre, 33 Harbour Drv Coffs Harbour NSW 2450",
    "addr:housenumber":"33",
    "addr:postcode":"2450",
    "addr:street":"Harbour Drv",
    "iso:country":"AU",
    "sg:address":"Suite 4, Jack Simmons Centre, 33 Harbour Drv",
    "sg:city":"Coffs Harbour",
    "sg:classifiers":[
        {
            "category":"Professional",
            "subcategory":"Accounting & Tax Preparation",
            "type":"Services"
        }
    ],
    "sg:phone":"+61 2 6651 6877",
    "sg:postcode":"2450",
    "sg:province":"NSW",
    "sg:tags":[
        "bookkeeping"
    ],
    "wof:name":"Northcoast Books & Accounting Services",
    "wof:placetype":"venue"
},
  "geometry": {"coordinates":[153.11531099999999,-30.296902],"type":"Point"}
}