{
  "type": "Feature",
  "properties": {
    "addr:full":"2/ 38 Assembly Drv Tullamarine VIC 3043",
    "addr:housenumber":"/ 38",
    "addr:postcode":"3043",
    "addr:street":"Assembly Drv",
    "iso:country":"AU",
    "sg:address":"2/ 38 Assembly Drv",
    "sg:city":"Tullamarine",
    "sg:classifiers":[
        {
            "category":"Military Area",
            "subcategory":"Air Force Base",
            "type":"Public Place"
        }
    ],
    "sg:phone":"+61 3 9335 3658",
    "sg:postcode":"3043",
    "sg:province":"VIC",
    "sg:tags":[
        "equipment",
        "speed",
        "variation"
    ],
    "wof:name":"Austech Industrial Pty Ltd",
    "wof:placetype":"venue"
},
  "geometry": {"coordinates":[144.86395263700001,-37.708316803],"type":"Point"}
}