{
  "type": "Feature",
  "properties": {
    "addr:full":"4 Ormond Rd East Geelong VIC 3219",
    "addr:housenumber":"4",
    "addr:postcode":"3219",
    "addr:street":"Ormond Rd",
    "iso:country":"AU",
    "sg:address":"4 Ormond Rd",
    "sg:city":"East Geelong",
    "sg:classifiers":[
        {
            "category":"Professional",
            "subcategory":"Art Services",
            "type":"Services"
        }
    ],
    "sg:phone":"+61 3 5222 8391",
    "sg:postcode":"3219",
    "sg:province":"VIC",
    "sg:tags":[
        "interior",
        "decorator"
    ],
    "wof:name":"Vamp Design",
    "wof:placetype":"venue"
},
  "geometry": {"coordinates":[144.37150573700001,-38.1552391052],"type":"Point"}
}