{
  "type": "Feature",
  "properties": {
    "iso:country":"AU",
    "sg:address":"9 Robert St",
    "sg:city":"Atherton",
    "sg:classifiers":[
        {
            "category":"Retail",
            "subcategory":"Auto Repair",
            "type":"Services"
        }
    ],
    "sg:phone":"+61 7 4091 1122",
    "sg:postcode":"4883",
    "sg:province":"QLD",
    "sg:tags":[
        "clutch",
        "brake"
    ],
    "wof:name":"Goodyear Auto Service Centre",
    "wof:placetype":"venue"
},
  "geometry": {"coordinates":[145.47567749000001,-17.2686424255],"type":"Point"}
}