{
  "type": "Feature",
  "properties": {
    "iso:country":"AU",
    "sg:address":"50 Riddoch St",
    "sg:city":"Penola",
    "sg:classifiers":[
        {
            "category":"Shopping",
            "subcategory":"Clothing, Apparel, & Fashions",
            "type":"Retail Goods"
        }
    ],
    "sg:phone":"+61 8 8737 4077",
    "sg:postcode":"5277",
    "sg:province":"SA",
    "sg:tags":[
        "lady",
        "wear"
    ],
    "wof:name":"Live Life Designs",
    "wof:placetype":"venue"
},
  "geometry": {"coordinates":[140.838211,-37.379967],"type":"Point"}
}