{
  "type": "Feature",
  "properties": {
    "addr:full":"29 Gordon Rd W Dianella WA 6059",
    "addr:housenumber":"29",
    "addr:postcode":"6059",
    "addr:street":"Gordon Rd W",
    "iso:country":"AU",
    "sg:address":"29 Gordon Rd",
    "sg:city":"W Dianella",
    "sg:classifiers":[
        {
            "category":"Banks & Credit Unions",
            "subcategory":"Investment Brokerage",
            "type":"Services"
        }
    ],
    "sg:phone":"+61 8 9376 1204",
    "sg:postcode":"6059",
    "sg:province":"WA",
    "sg:tags":[
        "finance",
        "broker"
    ],
    "wof:name":"Mansion Capital",
    "wof:placetype":"venue"
},
  "geometry": {"coordinates":[115.872177124,-31.8793907166],"type":"Point"}
}