{
  "type": "Feature",
  "properties": {
    "addr:full":"149 King St Warrawong NSW 2502",
    "addr:housenumber":"149",
    "addr:postcode":"2502",
    "addr:street":"King St",
    "iso:country":"AU",
    "sg:address":"149 King St",
    "sg:city":"Warrawong",
    "sg:classifiers":[
        {
            "category":"Manufacturing",
            "subcategory":"Furniture",
            "type":"Manufacturing & Wholesale Goods"
        }
    ],
    "sg:phone":"+61 2 4276 4836",
    "sg:postcode":"2502",
    "sg:province":"NSW",
    "sg:tags":[
        "builder",
        "designer",
        "custom"
    ],
    "wof:name":"Finishing Touch Custom Made Furniture",
    "wof:placetype":"venue"
},
  "geometry": {"coordinates":[150.88926699999999,-34.497326],"type":"Point"}
}