{
  "type": "Feature",
  "properties": {
    "iso:country":"AU",
    "sg:address":"Seventh St",
    "sg:city":"Renmark",
    "sg:classifiers":[
        {
            "category":"Farming",
            "subcategory":"Berry Farm",
            "type":"Manufacturing & Wholesale Goods"
        }
    ],
    "sg:phone":"+61 8 8595 3235",
    "sg:postcode":"5341",
    "sg:province":"SA",
    "sg:tags":[
        "fruit",
        "grower"
    ],
    "wof:name":"Bennett M L",
    "wof:placetype":"venue"
},
  "geometry": {"coordinates":[140.73699951200001,-34.1401748657],"type":"Point"}
}