{
  "type": "Feature",
  "properties": {
    "iso:country":"AU",
    "sg:address":"Level 1, Queen Victoria Women&#039;s Centre 210 Lo",
    "sg:city":"Melbourne",
    "sg:classifiers":[
        {
            "category":"Health Services",
            "subcategory":"Health Practitioner",
            "type":"Services"
        }
    ],
    "sg:phone":"+61 422 541 871",
    "sg:postcode":"3000",
    "sg:province":"VIC",
    "sg:tags":[
        "osteopath"
    ],
    "wof:name":"Lonsdale Osteopathy & Massage",
    "wof:placetype":"venue"
},
  "geometry": {"coordinates":[144.965774536,-37.8111152649],"type":"Point"}
}