{
  "type": "Feature",
  "properties": {
    "addr:full":"48 Fairbrother St Belmont WA 6104",
    "addr:housenumber":"48",
    "addr:postcode":"6104",
    "addr:street":"Fairbrother St",
    "iso:country":"AU",
    "sg:address":"48 Fairbrother St",
    "sg:city":"Belmont",
    "sg:classifiers":[
        {
            "category":"Retail",
            "subcategory":"Auto Repair",
            "type":"Services"
        }
    ],
    "sg:phone":"+61 8 9277 9320",
    "sg:postcode":"6104",
    "sg:province":"WA",
    "sg:tags":[
        "repairer",
        "motor",
        "engineer"
    ],
    "wof:name":"Hold Serv",
    "wof:placetype":"venue"
},
  "geometry": {"coordinates":[115.929077148,-31.9513301849],"type":"Point"}
}