{
  "type": "Feature",
  "properties": {
    "addr:full":"3 Phipps St Oatley NSW 2223",
    "addr:housenumber":"3",
    "addr:postcode":"2223",
    "addr:street":"Phipps St",
    "iso:country":"AU",
    "sg:address":"3 Phipps St",
    "sg:city":"Oatley",
    "sg:classifiers":[
        {
            "category":"Health Services",
            "subcategory":"Health Practitioner",
            "type":"Services"
        }
    ],
    "sg:phone":"+61 2 9580 2359",
    "sg:postcode":"2223",
    "sg:province":"NSW",
    "sg:tags":[
        "physiotherapist"
    ],
    "wof:name":"Oatley West Pysiotherapy & Sports Injury Clinic",
    "wof:placetype":"venue"
},
  "geometry": {"coordinates":[151.08299255399999,-33.9914398193],"type":"Point"}
}