{
  "type": "Feature",
  "properties": {
    "iso:country":"AU",
    "sg:address":"33 Osmand St",
    "sg:city":"Wanniassa",
    "sg:classifiers":[
        {
            "category":"Health Services",
            "subcategory":"Health Practitioner",
            "type":"Services"
        }
    ],
    "sg:phone":"+61 2 6231 4386",
    "sg:postcode":"2903",
    "sg:province":"ACT",
    "sg:tags":[
        "psychologist"
    ],
    "wof:name":"Scarborough Mark",
    "wof:placetype":"venue"
},
  "geometry": {"coordinates":[149.08851623499999,-35.3916702271],"type":"Point"}
}