{
  "type": "Feature",
  "properties": {
    "addr:full":"3/12- 16 McLeans Rd Bundoora VIC 3083",
    "addr:housenumber":"/;16",
    "addr:postcode":"3083",
    "addr:street":"12;Mcleans Rd",
    "iso:country":"AU",
    "sg:address":"3/12- 16 McLeans Rd",
    "sg:city":"Bundoora",
    "sg:classifiers":[
        {
            "category":"Real Estate",
            "subcategory":"Surveying",
            "type":"Services"
        }
    ],
    "sg:phone":"+61 3 9466 9099",
    "sg:postcode":"3083",
    "sg:province":"VIC",
    "sg:tags":[
        "building",
        "surveyor"
    ],
    "wof:name":"CDS Certified Design Services",
    "wof:placetype":"venue"
},
  "geometry": {"coordinates":[145.05833435100001,-37.6944236755],"type":"Point"}
}