{
  "type": "Feature",
  "properties": {
    "addr:full":"Ilparpa Rd Alice Springs NT 0870",
    "addr:postcode":"nt 0870",
    "addr:street":"Ilparpa Rd",
    "iso:country":"AU",
    "sg:address":"Ilparpa Rd",
    "sg:city":"Alice Springs",
    "sg:classifiers":[
        {
            "category":"Communications",
            "subcategory":"News Services",
            "type":"Services"
        }
    ],
    "sg:phone":"+61 8 8955 5595",
    "sg:postcode":"0870",
    "sg:province":"NT",
    "sg:tags":[
        "information",
        "tourist",
        "attractions"
    ],
    "wof:name":"Alice Limousine Tours",
    "wof:placetype":"venue"
},
  "geometry": {"coordinates":[133.84825134299999,-23.7506732941],"type":"Point"}
}