{
  "type": "Feature",
  "properties": {
    "iso:country":"AU",
    "sg:address":"53 Deniliquin St",
    "sg:city":"Tocumwal",
    "sg:classifiers":[
        {
            "category":"Personal",
            "subcategory":"Beauty Salon",
            "type":"Services"
        }
    ],
    "sg:phone":"+61 3 5874 2098",
    "sg:postcode":"2714",
    "sg:province":"NSW",
    "sg:tags":[
        "hairdresser"
    ],
    "wof:name":"Rusties Hairdressing",
    "wof:placetype":"venue"
},
  "geometry": {"coordinates":[145.56715393100001,-35.8122406006],"type":"Point"}
}