{
  "type": "Feature",
  "properties": {
    "addr:full":"23 Hagelthorn St Wonthaggi VIC 3995",
    "addr:housenumber":"23",
    "addr:postcode":"3995",
    "addr:street":"Hagelthorn St",
    "iso:country":"AU",
    "sg:address":"23 Hagelthorn St",
    "sg:city":"Wonthaggi",
    "sg:classifiers":[
        {
            "category":"Building & Trades",
            "subcategory":"Plumbing",
            "type":"Services"
        }
    ],
    "sg:phone":"+61 3 5672 3147",
    "sg:postcode":"3995",
    "sg:province":"VIC",
    "sg:tags":[
        "plumber",
        "gasfitters"
    ],
    "wof:name":"Fleming John",
    "wof:placetype":"venue"
},
  "geometry": {"coordinates":[145.59663399999999,-38.610271],"type":"Point"}
}