{
  "type": "Feature",
  "properties": {
    "iso:country":"AU",
    "sg:address":"Shop 44 Sunshine Plaza Crn Hapshire and Service Rd",
    "sg:city":"Sunshine",
    "sg:classifiers":[
        {
            "category":"Shopping",
            "type":"Retail Goods"
        }
    ],
    "sg:phone":"+61 3 9364 9010",
    "sg:postcode":"3020",
    "sg:province":"VIC",
    "sg:tags":[
        "repair",
        "travel"
    ],
    "wof:name":"Baggage Boutique The",
    "wof:placetype":"venue"
},
  "geometry": {"coordinates":[144.83904999999999,-37.796932],"type":"Point"}
}