{
  "type": "Feature",
  "properties": {
    "addr:full":"Shop 4, 2 Cumberland Ave Smithfield (Cairns) QLD 4350",
    "addr:housenumber":"shop;2",
    "addr:postcode":"4350",
    "addr:street":"Cumberland Ave",
    "iso:country":"AU",
    "sg:address":"Shop 4, 2 Cumberland Ave",
    "sg:city":"Smithfield (Cairns)",
    "sg:classifiers":[
        {
            "category":"Retail",
            "subcategory":"Veterinary Services",
            "type":"Services"
        }
    ],
    "sg:phone":"+61 7 4038 1666",
    "sg:postcode":"4350",
    "sg:province":"QLD",
    "sg:tags":[
        "surgeon"
    ],
    "wof:name":"Veterinary Diagnostic Services",
    "wof:placetype":"venue"
},
  "geometry": {"coordinates":[151.92860400000001,-27.586323],"type":"Point"}
}