{
  "type": "Feature",
  "properties": {
    "addr:full":"5 Wambool St Bulimba QLD 4171",
    "addr:housenumber":"5",
    "addr:postcode":"4171",
    "addr:street":"Wambool St",
    "iso:country":"AU",
    "sg:address":"5 Wambool St",
    "sg:city":"Bulimba",
    "sg:classifiers":[
        {
            "category":"Fast Food",
            "type":"Food & Drink"
        }
    ],
    "sg:phone":"+61 7 3217 9222",
    "sg:postcode":"4171",
    "sg:province":"QLD",
    "sg:tags":[
        "away",
        "take"
    ],
    "wof:name":"Tomato Brothers Restaurants",
    "wof:placetype":"venue"
},
  "geometry": {"coordinates":[153.05938720699999,-27.4510269165],"type":"Point"}
}