{
  "type": "Feature",
  "properties": {
    "addr:full":"40 Caramut Rd Warrnambool VIC 3280",
    "addr:housenumber":"40",
    "addr:postcode":"3280",
    "addr:street":"Caramut Rd",
    "iso:country":"AU",
    "sg:address":"40 Caramut Rd",
    "sg:city":"Warrnambool",
    "sg:classifiers":[
        {
            "category":"Shopping",
            "type":"Retail Goods"
        }
    ],
    "sg:phone":"+61 3 5562 2899",
    "sg:postcode":"3280",
    "sg:province":"VIC",
    "sg:tags":[
        "agent",
        "stock"
    ],
    "wof:name":"Elders Ltd",
    "wof:placetype":"venue"
},
  "geometry": {"coordinates":[142.46060180699999,-38.3594932556],"type":"Point"}
}