{
  "type": "Feature",
  "properties": {
    "addr:full":"82 Buckland Rd Nundah QLD 4012",
    "addr:housenumber":"82",
    "addr:postcode":"4012",
    "addr:street":"Buckland Rd",
    "iso:country":"AU",
    "sg:address":"82 Buckland Rd",
    "sg:city":"Nundah",
    "sg:classifiers":[
        {
            "category":"Communications",
            "subcategory":"Film & Video Production",
            "type":"Services"
        }
    ],
    "sg:phone":"+61 7 3256 6990",
    "sg:postcode":"4012",
    "sg:province":"QLD",
    "sg:tags":[
        "dvd",
        "library"
    ],
    "wof:name":"Video Ezy",
    "wof:placetype":"venue"
},
  "geometry": {"coordinates":[153.06138610799999,-27.4036750793],"type":"Point"}
}