{
  "type": "Feature",
  "properties": {
    "addr:full":"86 Oxford St Paddington NSW 2021",
    "addr:housenumber":"86",
    "addr:postcode":"2021",
    "addr:street":"Oxford St",
    "iso:country":"AU",
    "sg:address":"86 Oxford St",
    "sg:city":"Paddington",
    "sg:classifiers":[
        {
            "category":"Fast Food",
            "type":"Food & Drink"
        }
    ],
    "sg:phone":"+61 2 9331 4183",
    "sg:postcode":"2021",
    "sg:province":"NSW",
    "sg:tags":[
        "away",
        "take"
    ],
    "wof:name":"Indian Home Diner",
    "wof:placetype":"venue"
},
  "geometry": {"coordinates":[151.22114563,-33.8833503723],"type":"Point"}
}