{
  "type": "Feature",
  "properties": {
    "addr:full":"17 Dalwood Crs Malak NT 0812",
    "addr:housenumber":"17",
    "addr:postcode":"nt 0812",
    "addr:street":"Dalwood Crs",
    "iso:country":"AU",
    "sg:address":"17 Dalwood Crs",
    "sg:city":"Malak",
    "sg:classifiers":[
        {
            "category":"Education",
            "subcategory":"School",
            "type":"Public Place"
        }
    ],
    "sg:phone":"+61 8 8927 9596",
    "sg:postcode":"0812",
    "sg:province":"NT",
    "sg:tags":[
        "co-educational"
    ],
    "wof:name":"Darwin Adventist Primary School",
    "wof:placetype":"venue"
},
  "geometry": {"coordinates":[130.90194700000001,-12.39768],"type":"Point"}
}