{
  "type": "Feature",
  "properties": {
    "addr:full":"1 Wark Pde Bathurst NSW 2795",
    "addr:housenumber":"1",
    "addr:postcode":"2795",
    "addr:street":"Wark Pde",
    "iso:country":"AU",
    "sg:address":"1 Wark Pde",
    "sg:city":"Bathurst",
    "sg:classifiers":[
        {
            "category":"Health Services",
            "subcategory":"Doctor",
            "type":"Services"
        }
    ],
    "sg:phone":"+61 2 6332 5500",
    "sg:postcode":"2795",
    "sg:province":"NSW",
    "sg:tags":[
        "medical",
        "practitioner"
    ],
    "wof:name":"Central West Skin Clinic",
    "wof:placetype":"venue"
},
  "geometry": {"coordinates":[149.54583740199999,-33.4047813416],"type":"Point"}
}