{
  "type": "Feature",
  "properties": {
    "addr:full":"U3/ 1645 Ipswich Rd Rocklea QLD 4106",
    "addr:housenumber":"1645",
    "addr:postcode":"4106",
    "addr:street":"U3 /;Ipswich Rd",
    "iso:country":"AU",
    "sg:address":"U3/ 1645 Ipswich Rd",
    "sg:city":"Rocklea",
    "sg:classifiers":[
        {
            "category":"Building & Trades",
            "subcategory":"Landscaping Services",
            "type":"Services"
        }
    ],
    "sg:phone":"+61 7 3875 1444",
    "sg:postcode":"4106",
    "sg:province":"QLD",
    "sg:tags":[
        "designer",
        "landscape",
        "contractor"
    ],
    "wof:name":"Marsupial Landscape Management Pty Ltd",
    "wof:placetype":"venue"
},
  "geometry": {"coordinates":[153.00718689000001,-27.5559310913],"type":"Point"}
}