{
  "type": "Feature",
  "properties": {
    "iso:country":"AU",
    "sg:address":"85 Fletcher St",
    "sg:city":"Adamstown",
    "sg:classifiers":[
        {
            "category":"Building & Trades",
            "subcategory":"Construction",
            "type":"Services"
        }
    ],
    "sg:phone":"+61 2 4957 3488",
    "sg:postcode":"2289",
    "sg:province":"NSW",
    "sg:tags":[
        "contractor"
    ],
    "wof:name":"Parker R T Pty Ltd",
    "wof:placetype":"venue"
},
  "geometry": {"coordinates":[151.71693420400001,-32.9388275146],"type":"Point"}
}