{
  "type": "Feature",
  "properties": {
    "addr:full":"28 Channel Hwy Kingston TAS 7050",
    "addr:housenumber":"28",
    "addr:postcode":"7050",
    "addr:street":"Channel Hwy",
    "iso:country":"AU",
    "sg:address":"28 Channel Hwy",
    "sg:city":"Kingston",
    "sg:classifiers":[
        {
            "category":"Real Estate",
            "subcategory":"Real Estate Agent",
            "type":"Services"
        }
    ],
    "sg:phone":"+61 3 6229 4044",
    "sg:postcode":"7050",
    "sg:province":"TAS",
    "wof:name":"Metro Realty",
    "wof:placetype":"venue"
},
  "geometry": {"coordinates":[147.31053199999999,-42.975277],"type":"Point"}
}