{
  "type": "Feature",
  "properties": {
    "iso:country":"AU",
    "sg:address":"Ste 12/ 16-32 Hulme Crt",
    "sg:city":"Myaree",
    "sg:classifiers":[
        {
            "category":"Professional",
            "subcategory":"Accounting & Tax Preparation",
            "type":"Services"
        }
    ],
    "sg:phone":"+61 8 9317 4814",
    "sg:postcode":"6154",
    "sg:province":"WA",
    "sg:tags":[
        "consultant",
        "taxation"
    ],
    "wof:name":"Sentinel Partners Pty Ltd",
    "wof:placetype":"venue"
},
  "geometry": {"coordinates":[115.812462,-32.044807],"type":"Point"}
}