{
  "type": "Feature",
  "properties": {
    "iso:country":"AU",
    "sg:address":"Gordon Village Arcade 8/ 767 Pacific Hwy",
    "sg:city":"Gordon",
    "sg:classifiers":[
        {
            "category":"Health Services",
            "subcategory":"Doctor",
            "type":"Services"
        }
    ],
    "sg:phone":"+61 2 9498 1888",
    "sg:postcode":"2072",
    "sg:province":"NSW",
    "sg:tags":[
        "medical",
        "practitioner"
    ],
    "wof:name":"Elion Carol",
    "wof:placetype":"venue"
},
  "geometry": {"coordinates":[151.152786255,-33.755153656],"type":"Point"}
}