{
  "type": "Feature",
  "properties": {
    "addr:full":"20 Metropolitan Ave Nunawading VIC 3131",
    "addr:housenumber":"20",
    "addr:postcode":"3131",
    "addr:street":"Metropolitan Ave",
    "iso:country":"AU",
    "sg:address":"20 Metropolitan Ave",
    "sg:city":"Nunawading",
    "sg:classifiers":[
        {
            "category":"Professional",
            "type":"Services"
        }
    ],
    "sg:phone":"+61 3 9894 2177",
    "sg:postcode":"3131",
    "sg:province":"VIC",
    "sg:tags":[
        "shop",
        "fitting"
    ],
    "wof:name":"Advertising Industries",
    "wof:placetype":"venue"
},
  "geometry": {"coordinates":[145.16796875,-37.8198051453],"type":"Point"}
}