{
  "type": "Feature",
  "properties": {
    "addr:full":"11 Hubson Pl Adelaide SA 5000",
    "addr:housenumber":"11",
    "addr:postcode":"5000",
    "addr:street":"Hubson Pl",
    "iso:country":"AU",
    "sg:address":"11 Hubson Pl",
    "sg:city":"Adelaide",
    "sg:classifiers":[
        {
            "category":"Real Estate",
            "subcategory":"Surveying",
            "type":"Services"
        }
    ],
    "sg:phone":"+61 8 8376 8788",
    "sg:postcode":"5000",
    "sg:province":"SA",
    "sg:tags":[
        "surveyor",
        "quantity"
    ],
    "wof:name":"Herron Todd White",
    "wof:placetype":"venue"
},
  "geometry": {"coordinates":[138.59608459500001,-34.931854248],"type":"Point"}
}