{
  "type": "Feature",
  "properties": {
    "addr:full":"Lot 3 39 Clifton Rd Clifton Beach QLD 4879",
    "addr:housenumber":"39",
    "addr:postcode":"4879",
    "addr:street":"Clifton Rd",
    "iso:country":"AU",
    "sg:address":"Lot 3 39 Clifton Rd",
    "sg:city":"Clifton Beach",
    "sg:classifiers":[
        {
            "category":"Professional",
            "subcategory":"Research",
            "type":"Services"
        }
    ],
    "sg:phone":"+61 7 4055 3053",
    "sg:postcode":"4879",
    "sg:province":"QLD",
    "sg:tags":[
        "pearler"
    ],
    "wof:name":"Roko Pearls",
    "wof:placetype":"venue"
},
  "geometry": {"coordinates":[145.67497253400001,-16.7712917328],"type":"Point"}
}