{
  "type": "Feature",
  "properties": {
    "iso:country":"AU",
    "sg:address":"43 Shinnick Drv",
    "sg:city":"Oakhurst",
    "sg:classifiers":[
        {
            "category":"Building & Trades",
            "subcategory":"Construction",
            "type":"Services"
        }
    ],
    "sg:phone":"+61 2 9835 2486",
    "sg:postcode":"2761",
    "sg:province":"NSW",
    "sg:tags":[
        "fencing",
        "contractor"
    ],
    "wof:name":"KMI Fencing Contractor",
    "wof:placetype":"venue"
},
  "geometry": {"coordinates":[150.83168000000001,-33.741177],"type":"Point"}
}