{
  "type": "Feature",
  "properties": {
    "iso:country":"AU",
    "sg:address":"McDonald St",
    "sg:city":"Miriam Vale",
    "sg:classifiers":[
        {
            "category":"Arena",
            "subcategory":"Sports Club",
            "type":"Entertainment"
        }
    ],
    "sg:phone":"+61 7 4974 5500",
    "sg:postcode":"4677",
    "sg:province":"QLD",
    "sg:tags":[
        "league",
        "rugby"
    ],
    "wof:name":"Miriamvale Magpies J.R.L.F.C.",
    "wof:placetype":"venue"
},
  "geometry": {"coordinates":[151.56358337399999,-24.3308544159],"type":"Point"}
}