{
  "type": "Feature",
  "properties": {
    "addr:full":"24 Sale St Orange NSW 2800",
    "addr:housenumber":"24",
    "addr:postcode":"2800",
    "addr:street":"Sale St",
    "iso:country":"AU",
    "sg:address":"24 Sale St",
    "sg:city":"Orange",
    "sg:classifiers":[
        {
            "category":"Real Estate",
            "subcategory":"Real Estate Agent",
            "type":"Services"
        }
    ],
    "sg:phone":"+61 2 6362 0211",
    "sg:postcode":"2800",
    "sg:province":"NSW",
    "wof:name":"Ray White Real Estate",
    "wof:placetype":"venue"
},
  "geometry": {"coordinates":[149.09654235799999,-33.282333374],"type":"Point"}
}