{
  "type": "Feature",
  "properties": {
    "addr:full":"441 Warrigal Rd Moorabbin VIC 3189",
    "addr:housenumber":"441",
    "addr:postcode":"3189",
    "addr:street":"Warrigal Rd",
    "iso:country":"AU",
    "sg:address":"441 Warrigal Rd",
    "sg:city":"Moorabbin",
    "sg:classifiers":[
        {
            "category":"Wholesale",
            "subcategory":"Music Publishers",
            "type":"Manufacturing & Wholesale Goods"
        }
    ],
    "sg:phone":"+61 3 9553 0671",
    "sg:postcode":"3189",
    "sg:province":"VIC",
    "sg:tags":[
        "wholesaler",
        "dvd",
        "mfrs",
        "cd"
    ],
    "wof:name":"Digit-Technology",
    "wof:placetype":"venue"
},
  "geometry": {"coordinates":[145.077560425,-37.9479370117],"type":"Point"}
}