{
  "type": "Feature",
  "properties": {
    "addr:full":"31 Argyle Pl Carlton VIC 3053",
    "addr:housenumber":"31",
    "addr:postcode":"3053",
    "addr:street":"Argyle Pl",
    "iso:country":"AU",
    "sg:address":"31 Argyle Pl",
    "sg:city":"Carlton",
    "sg:classifiers":[
        {
            "category":"Communications",
            "type":"Services"
        }
    ],
    "sg:phone":"+61 3 9347 5107",
    "sg:postcode":"3053",
    "sg:province":"VIC",
    "sg:tags":[
        "translation"
    ],
    "wof:name":"Arabic Advanced And Academic Translation",
    "wof:placetype":"venue"
},
  "geometry": {"coordinates":[144.96522522000001,-37.8035354614],"type":"Point"}
}