{
  "type": "Feature",
  "properties": {
    "addr:full":"Hay St Klemzig SA 5087",
    "addr:postcode":"5087",
    "addr:street":"Hay St",
    "iso:country":"AU",
    "sg:address":"Hay St",
    "sg:city":"Klemzig",
    "sg:classifiers":[
        {
            "category":"Education",
            "subcategory":"School",
            "type":"Public Place"
        }
    ],
    "sg:phone":"+61 8 8261 1944",
    "sg:postcode":"5087",
    "sg:province":"SA",
    "sg:tags":[
        "state",
        "except",
        "nsw"
    ],
    "wof:name":"Klemzig Primary",
    "wof:placetype":"venue"
},
  "geometry": {"coordinates":[138.63706970199999,-34.8780288696],"type":"Point"}
}