{
  "type": "Feature",
  "properties": {
    "iso:country":"AU",
    "sg:address":"36 Angus Ave",
    "sg:city":"Kandos",
    "sg:classifiers":[
        {
            "category":"Communications",
            "subcategory":"Film & Video Production",
            "type":"Services"
        }
    ],
    "sg:phone":"+61 2 6379 4699",
    "sg:postcode":"2848",
    "sg:province":"NSW",
    "sg:tags":[
        "dvd",
        "library"
    ],
    "wof:name":"Kandos New Release Video",
    "wof:placetype":"venue"
},
  "geometry": {"coordinates":[149.97494499999999,-32.858929],"type":"Point"}
}