{
  "type": "Feature",
  "properties": {
    "addr:full":"Cnr Canberra Ave & Ipswich St Fyshwick ACT 2609",
    "addr:postcode":"2609",
    "addr:street":"Canberra Ave &;St",
    "iso:country":"AU",
    "sg:address":"Cnr Canberra Ave & Ipswich St",
    "sg:city":"Fyshwick",
    "sg:classifiers":[
        {
            "category":"Retail",
            "subcategory":"Auto Repair",
            "type":"Services"
        }
    ],
    "sg:phone":"+61 2 6280 6994",
    "sg:postcode":"2609",
    "sg:province":"ACT",
    "sg:tags":[
        "repairer",
        "motor",
        "engineer"
    ],
    "wof:name":"Kevin's Auto Repairs",
    "wof:placetype":"venue"
},
  "geometry": {"coordinates":[149.17048645,-35.3345298767],"type":"Point"}
}