{
  "type": "Feature",
  "properties": {
    "addr:full":"112 Molonglo St Bungendore NSW 2621",
    "addr:housenumber":"112",
    "addr:postcode":"2621",
    "addr:street":"Molonglo St",
    "iso:country":"AU",
    "sg:address":"112 Molonglo St",
    "sg:city":"Bungendore",
    "sg:classifiers":[
        {
            "category":"Retail",
            "subcategory":"Veterinary Services",
            "type":"Services"
        }
    ],
    "sg:phone":"+61 2 6238 1133",
    "sg:postcode":"2621",
    "sg:province":"NSW",
    "sg:tags":[
        "surgeon"
    ],
    "wof:name":"Laing Jack",
    "wof:placetype":"venue"
},
  "geometry": {"coordinates":[149.43841552699999,-35.2538909912],"type":"Point"}
}