{
  "type": "Feature",
  "properties": {
    "addr:full":"23 Woorama Rd The Gap QLD 4061",
    "addr:housenumber":"23",
    "addr:postcode":"4061",
    "addr:street":"Woorama Rd",
    "iso:country":"AU",
    "sg:address":"23 Woorama Rd",
    "sg:city":"The Gap",
    "sg:classifiers":[
        {
            "category":"Professional",
            "subcategory":"Computer Services",
            "type":"Services"
        }
    ],
    "sg:phone":"+61 403 731 715",
    "sg:postcode":"4061",
    "sg:province":"QLD",
    "sg:tags":[
        "repairs",
        "upgrade",
        "equipment"
    ],
    "wof:name":"R & R Computer Technologies",
    "wof:placetype":"venue"
},
  "geometry": {"coordinates":[152.939453125,-27.4342708588],"type":"Point"}
}