{
  "type": "Feature",
  "properties": {
    "iso:country":"AU",
    "sg:address":"PO Box 5168",
    "sg:city":"Elanora Heights",
    "sg:classifiers":[
        {
            "category":"Building & Trades",
            "subcategory":"Plumbing",
            "type":"Services"
        }
    ],
    "sg:phone":"+61 403 218 290",
    "sg:postcode":"2101",
    "sg:province":"NSW",
    "sg:tags":[
        "plumber",
        "gasfitters"
    ],
    "wof:name":"Woods Plumbing",
    "wof:placetype":"venue"
},
  "geometry": {"coordinates":[151.279678,-33.701031],"type":"Point"}
}