{
  "type": "Feature",
  "properties": {
    "addr:full":"175 Riding Rd Balmoral QLD 4171",
    "addr:housenumber":"175",
    "addr:postcode":"4171",
    "addr:street":"Riding Rd",
    "iso:country":"AU",
    "sg:address":"175 Riding Rd",
    "sg:city":"Balmoral",
    "sg:classifiers":[
        {
            "category":"Food & Beverages",
            "subcategory":"Liquor & Beverages",
            "type":"Retail Goods"
        }
    ],
    "sg:phone":"+61 7 3899 9099",
    "sg:postcode":"4171",
    "sg:province":"QLD",
    "sg:tags":[
        "store"
    ],
    "wof:name":"Liquor King",
    "wof:placetype":"venue"
},
  "geometry": {"coordinates":[153.06364440900001,-27.4619026184],"type":"Point"}
}