{
  "type": "Feature",
  "properties": {
    "addr:full":"475 Hummerston St Mt Helena WA 6082",
    "addr:housenumber":"475",
    "addr:postcode":"6082",
    "addr:street":"Hummerston St",
    "iso:country":"AU",
    "sg:address":"475 Hummerston St",
    "sg:city":"Mt Helena",
    "sg:classifiers":[
        {
            "category":"Farming",
            "subcategory":"Nursery",
            "type":"Manufacturing & Wholesale Goods"
        }
    ],
    "sg:phone":"+61 8 9572 1311",
    "sg:postcode":"6082",
    "sg:province":"WA",
    "wof:name":"Rare Tree Company The",
    "wof:placetype":"venue"
},
  "geometry": {"coordinates":[116.221862793,-31.8842201233],"type":"Point"}
}