{
  "type": "Feature",
  "properties": {
    "addr:full":"49 Cochrane St Brighton VIC 3186",
    "addr:housenumber":"49",
    "addr:postcode":"3186",
    "addr:street":"Cochrane St",
    "iso:country":"AU",
    "sg:address":"49 Cochrane St",
    "sg:city":"Brighton",
    "sg:classifiers":[
        {
            "category":"Professional",
            "subcategory":"Art Services",
            "type":"Services"
        }
    ],
    "sg:phone":"+61 3 9596 3907",
    "sg:postcode":"3186",
    "sg:province":"VIC",
    "sg:tags":[
        "interior",
        "designer"
    ],
    "wof:name":"Shillcombe Interiors",
    "wof:placetype":"venue"
},
  "geometry": {"coordinates":[144.99838256800001,-37.9018096924],"type":"Point"}
}