{
  "type": "Feature",
  "properties": {
    "addr:full":"4 Courtenay Ave Cranbourne North VIC 3977",
    "addr:housenumber":"4",
    "addr:postcode":"3977",
    "addr:street":"Courtenay Ave",
    "iso:country":"AU",
    "sg:address":"4 Courtenay Ave",
    "sg:city":"Cranbourne North",
    "sg:classifiers":[
        {
            "category":"Building & Trades",
            "subcategory":"Construction",
            "type":"Services"
        }
    ],
    "sg:phone":"+61 3 5995 8636",
    "sg:postcode":"3977",
    "sg:province":"VIC",
    "sg:tags":[
        "plasterboard",
        "plasterer",
        "fixer"
    ],
    "wof:name":"Ice Plaster",
    "wof:placetype":"venue"
},
  "geometry": {"coordinates":[145.274200439,-38.0777015686],"type":"Point"}
}