{
  "type": "Feature",
  "properties": {
    "addr:full":"12 Elysium Rd Carrara QLD 4211",
    "addr:housenumber":"12",
    "addr:postcode":"4211",
    "addr:street":"Elysium Rd",
    "iso:country":"AU",
    "sg:address":"12 Elysium Rd",
    "sg:city":"Carrara",
    "sg:classifiers":[
        {
            "category":"Building & Trades",
            "subcategory":"Construction",
            "type":"Services"
        }
    ],
    "sg:phone":"+61 7 5525 1711",
    "sg:postcode":"4211",
    "sg:province":"QLD",
    "sg:tags":[
        "earth",
        "excavating",
        "moving",
        "contractor"
    ],
    "wof:name":"Bill McGrath Pty Ltd",
    "wof:placetype":"venue"
},
  "geometry": {"coordinates":[153.35545349099999,-28.0331459045],"type":"Point"}
}