{
  "type": "Feature",
  "properties": {
    "addr:full":"1st Flr 451 Golden Four Drv Tugun QLD 4224",
    "addr:housenumber":"451",
    "addr:postcode":"4224",
    "addr:street":"Golden Four Drv",
    "iso:country":"AU",
    "sg:address":"1st Flr 451 Golden Four Drv",
    "sg:city":"Tugun",
    "sg:classifiers":[
        {
            "category":"Health Services",
            "subcategory":"Health Practitioner",
            "type":"Services"
        }
    ],
    "sg:phone":"+61 7 5534 7411",
    "sg:postcode":"4224",
    "sg:province":"QLD",
    "sg:tags":[
        "physiotherapist"
    ],
    "wof:name":"Anna Wood",
    "wof:placetype":"venue"
},
  "geometry": {"coordinates":[153.49436950699999,-28.1431369781],"type":"Point"}
}