{
  "type": "Feature",
  "properties": {
    "iso:country":"AU",
    "sg:address":"1a Raymond Rd",
    "sg:city":"Thirroul",
    "sg:classifiers":[
        {
            "category":"Government",
            "subcategory":"Customs House",
            "type":"Public Place"
        }
    ],
    "sg:phone":"+61 2 4267 4833",
    "sg:postcode":"2515",
    "sg:province":"NSW",
    "sg:tags":[
        "title",
        "management",
        "stratum"
    ],
    "wof:name":"Dougmal Real Estate Thirroul",
    "wof:placetype":"venue"
},
  "geometry": {"coordinates":[150.922195,-34.315838],"type":"Point"}
}