{
  "type": "Feature",
  "properties": {
    "addr:full":"1a Raymond Rd Thirroul NSW 2515",
    "addr:housenumber":"1a",
    "addr:postcode":"2515",
    "addr:street":"Raymond Rd",
    "iso:country":"AU",
    "sg:address":"1a Raymond Rd",
    "sg:city":"Thirroul",
    "sg:classifiers":[
        {
            "category":"Government",
            "subcategory":"Customs House",
            "type":"Public Place"
        }
    ],
    "sg:phone":"+61 2 4267 4833",
    "sg:postcode":"2515",
    "sg:province":"NSW",
    "sg:tags":[
        "title",
        "management",
        "stratum"
    ],
    "wof:name":"Dougmal Real Estate Thirroul",
    "wof:placetype":"venue"
},
  "geometry": {"coordinates":[150.92219499999999,-34.315838],"type":"Point"}
}