{
  "type": "Feature",
  "properties": {
    "addr:full":"168 Tippett St Gulliver QLD 4812",
    "addr:housenumber":"168",
    "addr:postcode":"4812",
    "addr:street":"Tippett St",
    "iso:country":"AU",
    "sg:address":"168 Tippett St",
    "sg:city":"Gulliver",
    "sg:classifiers":[
        {
            "category":"Real Estate",
            "subcategory":"Real Estate Agent",
            "type":"Services"
        }
    ],
    "sg:phone":"+61 7 4779 7335",
    "sg:postcode":"4812",
    "sg:province":"QLD",
    "wof:name":"Arch Real Estate",
    "wof:placetype":"venue"
},
  "geometry": {"coordinates":[146.773483,-19.282131],"type":"Point"}
}