{
  "type": "Feature",
  "properties": {
    "iso:country":"AU",
    "sg:address":"King St",
    "sg:city":"Campbelltown",
    "sg:classifiers":[
        {
            "category":"Health Services",
            "subcategory":"Doctor",
            "type":"Services"
        }
    ],
    "sg:phone":"+61 2 4628 4383",
    "sg:postcode":"2560",
    "sg:province":"NSW",
    "sg:tags":[
        "medical",
        "practitioner"
    ],
    "wof:name":"Levy L",
    "wof:placetype":"venue"
},
  "geometry": {"coordinates":[150.818603516,-34.0633811951],"type":"Point"}
}