{
  "type": "Feature",
  "properties": {
    "addr:full":"PO Box 1016 Portland VIC 3305",
    "addr:postcode":"3305",
    "iso:country":"AU",
    "sg:address":"PO Box 1016",
    "sg:city":"Portland",
    "sg:classifiers":[
        {
            "category":"Building & Trades",
            "subcategory":"Landscaping Services",
            "type":"Services"
        }
    ],
    "sg:phone":"+61 427 235 631",
    "sg:postcode":"3305",
    "sg:province":"VIC",
    "sg:tags":[
        "control",
        "weed"
    ],
    "wof:name":"South west Ag Spray",
    "wof:placetype":"venue"
},
  "geometry": {"coordinates":[141.61425781200001,-38.3552894592],"type":"Point"}
}