{
  "type": "Feature",
  "properties": {
    "addr:full":"5 Green St Thomastown VIC 3074",
    "addr:housenumber":"5",
    "addr:postcode":"3074",
    "addr:street":"Green St",
    "iso:country":"AU",
    "sg:address":"5 Green St",
    "sg:city":"Thomastown",
    "sg:classifiers":[
        {
            "category":"Building & Trades",
            "subcategory":"Equipment Rental",
            "type":"Services"
        }
    ],
    "sg:phone":"+61 3 9464 6811",
    "sg:postcode":"3074",
    "sg:province":"VIC",
    "sg:tags":[
        "crane",
        "hire"
    ],
    "wof:name":"Metcalf Crane Services Pty Ltd",
    "wof:placetype":"venue"
},
  "geometry": {"coordinates":[145.03744506800001,-37.694065094],"type":"Point"}
}