{
  "type": "Feature",
  "properties": {
    "addr:full":"4 Southam St Brunswick West VIC 3055",
    "addr:housenumber":"4",
    "addr:postcode":"3055",
    "addr:street":"Southam St",
    "iso:country":"AU",
    "sg:address":"4 Southam St",
    "sg:city":"Brunswick West",
    "sg:classifiers":[
        {
            "category":"Government",
            "subcategory":"Post Office",
            "type":"Public Place"
        }
    ],
    "sg:phone":"+61 438 118 799",
    "sg:postcode":"3055",
    "sg:province":"VIC",
    "sg:tags":[
        "chair",
        "manufacturer"
    ],
    "wof:name":"Furniture Maker Not Carpenter",
    "wof:placetype":"venue"
},
  "geometry": {"coordinates":[144.931182861,-37.7519340515],"type":"Point"}
}