{
  "type": "Feature",
  "properties": {
    "iso:country":"AU",
    "sg:address":"66 Riverside Rd",
    "sg:city":"Chipping Norton",
    "sg:classifiers":[
        {
            "category":"Home & Garden",
            "subcategory":"Building Materials",
            "type":"Retail Goods"
        }
    ],
    "sg:phone":"+61 2 9755 3984",
    "sg:postcode":"2170",
    "sg:province":"NSW",
    "sg:tags":[
        "supply"
    ],
    "wof:name":"Riverside Second Hand Building Supplies",
    "wof:placetype":"venue"
},
  "geometry": {"coordinates":[150.96839904800001,-33.919128418],"type":"Point"}
}