{
  "type": "Feature",
  "properties": {
    "addr:full":"9 Commerce St Taree NSW 2430",
    "addr:housenumber":"9",
    "addr:postcode":"2430",
    "addr:street":"Commerce St",
    "iso:country":"AU",
    "sg:address":"9 Commerce St",
    "sg:city":"Taree",
    "sg:classifiers":[
        {
            "category":"Travel",
            "subcategory":"Hotels & Motels",
            "type":"Entertainment"
        }
    ],
    "sg:phone":"+61 2 6552 1614",
    "sg:postcode":"2430",
    "sg:province":"NSW",
    "wof:name":"Agincourt Motel",
    "wof:placetype":"venue"
},
  "geometry": {"coordinates":[152.457245,-31.915003],"type":"Point"}
}