{
  "type": "Feature",
  "properties": {
    "iso:country":"AU",
    "sg:address":"8 Chapel Rd",
    "sg:city":"Bankstown",
    "sg:classifiers":[
        {
            "category":"Fast Food",
            "type":"Food & Drink"
        }
    ],
    "sg:phone":"+61 2 9708 5297",
    "sg:postcode":"2200",
    "sg:province":"NSW",
    "sg:tags":[
        "away",
        "take"
    ],
    "wof:name":"Manaham Food Bar",
    "wof:placetype":"venue"
},
  "geometry": {"coordinates":[151.031586,-33.92065],"type":"Point"}
}