{
  "type": "Feature",
  "properties": {
    "addr:full":"Unit 2/ 12 Sunset Ave Warilla NSW 2528",
    "addr:postcode":"2528",
    "addr:street":"Sunset Ave",
    "iso:country":"AU",
    "sg:address":"Unit 2/ 12 Sunset Ave",
    "sg:city":"Warilla",
    "sg:classifiers":[
        {
            "category":"Professional",
            "subcategory":"Detective & Security Services",
            "type":"Services"
        }
    ],
    "sg:phone":"+61 2 4297 3140",
    "sg:postcode":"2528",
    "sg:province":"NSW",
    "sg:tags":[
        "consultant",
        "system"
    ],
    "wof:name":"Shellharbour Security Systems Pty Ltd",
    "wof:placetype":"venue"
},
  "geometry": {"coordinates":[150.85914611800001,-34.5579376221],"type":"Point"}
}