{
  "type": "Feature",
  "properties": {
    "iso:country":"AU",
    "sg:address":"Prospect Rd",
    "sg:city":"Bendigo",
    "sg:classifiers":[
        {
            "category":"Utilities",
            "type":"Services"
        }
    ],
    "sg:phone":"+61 3 5441 4404",
    "sg:postcode":"3550",
    "sg:province":"VIC",
    "sg:tags":[
        "refrigeration",
        "industrial",
        "commercial",
        "retail"
    ],
    "wof:name":"Gordon Brothers Industries Pty Ltd",
    "wof:placetype":"venue"
},
  "geometry": {"coordinates":[144.313522339,-36.7433319092],"type":"Point"}
}