{
  "type": "Feature",
  "properties": {
    "addr:full":"Suite 2, 10 Norton St Leichhardt NSW 2040",
    "addr:housenumber":"10",
    "addr:postcode":"2040",
    "addr:street":"Norton St",
    "iso:country":"AU",
    "sg:address":"Suite 2, 10 Norton St",
    "sg:city":"Leichhardt",
    "sg:classifiers":[
        {
            "category":"Professional",
            "subcategory":"Employment Agencies",
            "type":"Services"
        }
    ],
    "sg:phone":"+61 2 9518 0008",
    "sg:postcode":"2040",
    "sg:province":"NSW",
    "sg:tags":[
        "entertainer",
        "agent"
    ],
    "wof:name":"In Nobody's Shadow Pty Ltd",
    "wof:placetype":"venue"
},
  "geometry": {"coordinates":[151.15741,-33.887543],"type":"Point"}
}