{
  "type": "Feature",
  "properties": {
    "addr:full":"23 Manchester St Dulwich Hill NSW 2203",
    "addr:housenumber":"23",
    "addr:postcode":"2203",
    "addr:street":"Manchester St",
    "iso:country":"AU",
    "sg:address":"23 Manchester St",
    "sg:city":"Dulwich Hill",
    "sg:classifiers":[
        {
            "category":"Utilities",
            "subcategory":"Electric",
            "type":"Services"
        }
    ],
    "sg:phone":"+61 2 9560 2082",
    "sg:postcode":"2203",
    "sg:province":"NSW",
    "sg:tags":[
        "transformer"
    ],
    "sg:website":"http://www.hansomtransformers.com.au",
    "wof:name":"Hansom J S Pty Ltd Transformers",
    "wof:placetype":"venue"
},
  "geometry": {"coordinates":[151.13642899999999,-33.899677],"type":"Point"}
}