{
  "type": "Feature",
  "properties": {
    "addr:full":"PO Box 265 Corio VIC 3214",
    "addr:postcode":"3214",
    "iso:country":"AU",
    "sg:address":"PO Box 265",
    "sg:city":"Corio",
    "sg:classifiers":[
        {
            "category":"Building & Trades",
            "subcategory":"Equipment Rental",
            "type":"Services"
        }
    ],
    "sg:phone":"+61 412 521 906",
    "sg:postcode":"3214",
    "sg:province":"VIC",
    "sg:tags":[
        "crane",
        "hire"
    ],
    "wof:name":"Statewide Crane Trucks P/L",
    "wof:placetype":"venue"
},
  "geometry": {"coordinates":[144.35643005399999,-38.0738601685],"type":"Point"}
}