{
  "type": "Feature",
  "properties": {
    "addr:full":"75 Studio Drv Oxenford QLD 4210",
    "addr:housenumber":"75",
    "addr:postcode":"4210",
    "addr:street":"Studio Drv",
    "iso:country":"AU",
    "sg:address":"75 Studio Drv",
    "sg:city":"Oxenford",
    "sg:classifiers":[
        {
            "category":"Social Services",
            "subcategory":"Child Care",
            "type":"Services"
        }
    ],
    "sg:phone":"+61 7 5573 4124",
    "sg:postcode":"4210",
    "sg:province":"QLD",
    "sg:tags":[
        "baby",
        "sitter"
    ],
    "wof:name":"Kare For Kids",
    "wof:placetype":"venue"
},
  "geometry": {"coordinates":[153.321243286,-27.923412323],"type":"Point"}
}