{
  "type": "Feature",
  "properties": {
    "addr:full":"88- 90 Great North Rd Five Dock NSW 2046",
    "addr:housenumber":"90",
    "addr:postcode":"2046",
    "addr:street":"Great North Rd",
    "iso:country":"AU",
    "sg:address":"88- 90 Great North Rd",
    "sg:city":"Five Dock",
    "sg:classifiers":[
        {
            "category":"Banks & Credit Unions",
            "subcategory":"Bank",
            "type":"Services"
        }
    ],
    "sg:phone":"+61 13 13 14",
    "sg:postcode":"2046",
    "sg:province":"NSW",
    "wof:name":"ANZ",
    "wof:placetype":"venue"
},
  "geometry": {"coordinates":[151.12974500000001,-33.868717],"type":"Point"}
}