{
  "type": "Feature",
  "properties": {
    "addr:full":"367 North Rd Caulfield South VIC 3162",
    "addr:housenumber":"367",
    "addr:postcode":"3162",
    "addr:street":"North Rd",
    "iso:country":"AU",
    "sg:address":"367 North Rd",
    "sg:city":"Caulfield South",
    "sg:classifiers":[
        {
            "category":"Professional",
            "subcategory":"Engineering",
            "type":"Services"
        }
    ],
    "sg:phone":"+61 3 9578 5844",
    "sg:postcode":"3162",
    "sg:province":"VIC",
    "sg:tags":[
        "consulting",
        "engineer"
    ],
    "wof:name":"Keays Engineering Pty Ltd",
    "wof:placetype":"venue"
},
  "geometry": {"coordinates":[145.02897644000001,-37.9023895264],"type":"Point"}
}