{
  "type": "Feature",
  "properties": {
    "addr:full":"Kent St Woolloongabba QLD 4102",
    "addr:postcode":"4102",
    "addr:street":"Kent St",
    "iso:country":"AU",
    "sg:address":"Kent St",
    "sg:city":"Woolloongabba",
    "sg:classifiers":[
        {
            "category":"Organizations",
            "subcategory":"Non-profit Organization",
            "type":"Services"
        }
    ],
    "sg:phone":"+61 7 3391 3686",
    "sg:postcode":"4102",
    "sg:province":"QLD",
    "sg:tags":[
        "support",
        "disability",
        "organisation"
    ],
    "wof:name":"QBIC Industries",
    "wof:placetype":"venue"
},
  "geometry": {"coordinates":[153.02986145,-27.4993114471],"type":"Point"}
}