{
  "type": "Feature",
  "properties": {
    "addr:full":"39 Fairway St Nedlands WA 6009",
    "addr:housenumber":"39",
    "addr:postcode":"6009",
    "addr:street":"Fairway St",
    "iso:country":"AU",
    "sg:address":"39 Fairway St",
    "sg:city":"Nedlands",
    "sg:classifiers":[
        {
            "category":"Professional",
            "subcategory":"Research",
            "type":"Services"
        }
    ],
    "sg:phone":"+61 8 9389 8421",
    "sg:postcode":"6009",
    "sg:province":"WA",
    "sg:tags":[
        "industrial",
        "scientific"
    ],
    "wof:name":"CSIRO Engineering & Mining",
    "wof:placetype":"venue"
},
  "geometry": {"coordinates":[115.81546,-31.981274],"type":"Point"}
}