{
  "type": "Feature",
  "properties": {
    "addr:full":"16 Byron St Box Hill South VIC 3128",
    "addr:housenumber":"16",
    "addr:postcode":"3128",
    "addr:street":"Byron St",
    "iso:country":"AU",
    "sg:address":"16 Byron St",
    "sg:city":"Box Hill South",
    "sg:classifiers":[
        {
            "category":"Building & Trades",
            "subcategory":"Plumbing",
            "type":"Services"
        }
    ],
    "sg:phone":"+61 414 290 867",
    "sg:postcode":"3128",
    "sg:province":"VIC",
    "sg:tags":[
        "plumber",
        "gasfitters"
    ],
    "wof:name":"trades@call",
    "wof:placetype":"venue"
},
  "geometry": {"coordinates":[145.11412048299999,-37.8340835571],"type":"Point"}
}