{
  "type": "Feature",
  "properties": {
    "addr:full":"10 Mt Barron St Balnarring VIC 3926",
    "addr:housenumber":"10",
    "addr:postcode":"3926",
    "addr:street":"Mt Barron St",
    "iso:country":"AU",
    "sg:address":"10 Mt Barron St",
    "sg:city":"Balnarring",
    "sg:classifiers":[
        {
            "category":"Building & Trades",
            "subcategory":"Construction",
            "type":"Services"
        }
    ],
    "sg:phone":"+61 3 5983 2553",
    "sg:postcode":"3926",
    "sg:province":"VIC",
    "sg:tags":[
        "polishing",
        "sanding",
        "floor"
    ],
    "wof:name":"Viking Floor Service & Design",
    "wof:placetype":"venue"
},
  "geometry": {"coordinates":[145.131469727,-38.3693008423],"type":"Point"}
}