{
  "type": "Feature",
  "properties": {
    "addr:full":"3-4/ 79 Princes Hwy Fairy Meadow NSW 2519",
    "addr:housenumber":"3-4 / 79",
    "addr:postcode":"2519",
    "addr:street":"Princes Hwy",
    "iso:country":"AU",
    "sg:address":"3-4/ 79 Princes Hwy",
    "sg:city":"Fairy Meadow",
    "sg:phone":"+61 1800 005 755",
    "sg:postcode":"2519",
    "sg:province":"NSW",
    "wof:name":"Filtech",
    "wof:placetype":"venue"
},
  "geometry": {"coordinates":[150.89228800000001,-34.396713],"type":"Point"}
}