{
  "type": "Feature",
  "properties": {
    "addr:full":"1 Gartrell St Burnside SA 5066",
    "addr:housenumber":"1",
    "addr:postcode":"5066",
    "addr:street":"Gartrell St",
    "iso:country":"AU",
    "sg:address":"1 Gartrell St",
    "sg:city":"Burnside",
    "sg:classifiers":[
        {
            "category":"Building & Trades",
            "subcategory":"Construction",
            "type":"Services"
        }
    ],
    "sg:phone":"+61 8 8332 8311",
    "sg:postcode":"5066",
    "sg:province":"SA",
    "sg:tags":[
        "joiner",
        "carpenter"
    ],
    "wof:name":"Robert Walker",
    "wof:placetype":"venue"
},
  "geometry": {"coordinates":[138.66229248100001,-34.9366607666],"type":"Point"}
}