{
  "type": "Feature",
  "properties": {
    "addr:full":"18 Veda Ave Mt Martha VIC 3934",
    "addr:housenumber":"18",
    "addr:postcode":"3934",
    "addr:street":"Veda Ave Mt Martha",
    "iso:country":"AU",
    "sg:address":"18 Veda Ave",
    "sg:city":"Mt Martha",
    "sg:classifiers":[
        {
            "category":"Utilities",
            "subcategory":"Electric",
            "type":"Services"
        }
    ],
    "sg:phone":"+61 3 5976 4469",
    "sg:postcode":"3934",
    "sg:province":"VIC",
    "sg:tags":[
        "electrical",
        "contractor"
    ],
    "wof:name":"S.R. OZLEC",
    "wof:placetype":"venue"
},
  "geometry": {"coordinates":[145.045013428,-38.2549819946],"type":"Point"}
}