{
  "type": "Feature",
  "properties": {
    "iso:country":"AU",
    "sg:address":"PO Box 234",
    "sg:city":"Helensburgh",
    "sg:classifiers":[
        {
            "category":"Shopping",
            "subcategory":"Musical Instruments",
            "type":"Retail Goods"
        }
    ],
    "sg:phone":"+61 412 974 391",
    "sg:postcode":"2508",
    "sg:province":"NSW",
    "sg:tags":[
        "musician",
        "agent"
    ],
    "wof:name":"Coggan Darren",
    "wof:placetype":"venue"
},
  "geometry": {"coordinates":[150.98178100000001,-34.19223],"type":"Point"}
}