{
  "type": "Feature",
  "properties": {
    "iso:country":"AU",
    "sg:address":"Shop 8/ 152 Shore St West",
    "sg:city":"Cleveland",
    "sg:classifiers":[
        {
            "category":"Shopping",
            "subcategory":"Crafts & Fabrics",
            "type":"Retail Goods"
        }
    ],
    "sg:phone":"+61 7 3286 6031",
    "sg:postcode":"4163",
    "sg:province":"QLD",
    "sg:tags":[
        "supply"
    ],
    "wof:name":"Magic Moments Scrapbooks",
    "wof:placetype":"venue"
},
  "geometry": {"coordinates":[153.26690673799999,-27.5269832611],"type":"Point"}
}