{
  "type": "Feature",
  "properties": {
    "addr:full":"615 Waterdale Rd Heidelberg West VIC 3081",
    "addr:housenumber":"615",
    "addr:postcode":"3081",
    "addr:street":"Waterdale Rd",
    "iso:country":"AU",
    "sg:address":"615 Waterdale Rd",
    "sg:city":"Heidelberg West",
    "sg:classifiers":[
        {
            "category":"Retail",
            "subcategory":"Auto Repair",
            "type":"Services"
        }
    ],
    "sg:phone":"+61 3 9459 3563",
    "sg:postcode":"3081",
    "sg:province":"VIC",
    "sg:tags":[
        "electrical"
    ],
    "wof:name":"Waterdale Auto Electrics Pty Ltd",
    "wof:placetype":"venue"
},
  "geometry": {"coordinates":[145.04905700699999,-37.7340240479],"type":"Point"}
}