{
  "type": "Feature",
  "properties": {
    "addr:full":"Dyraaba St Casino NSW 2470",
    "addr:postcode":"2470",
    "iso:country":"AU",
    "sg:address":"Dyraaba St",
    "sg:city":"Casino",
    "sg:classifiers":[
        {
            "category":"Wholesale",
            "subcategory":"Farm Supplies",
            "type":"Manufacturing & Wholesale Goods"
        }
    ],
    "sg:phone":"+61 2 6661 2100",
    "sg:postcode":"2470",
    "sg:province":"NSW",
    "sg:tags":[
        "equipment"
    ],
    "wof:name":"Norco Rural Stores",
    "wof:placetype":"venue"
},
  "geometry": {"coordinates":[153.048706055,-28.8557949066],"type":"Point"}
}