{
  "type": "Feature",
  "properties": {
    "addr:full":"7 Haynes Crt Aspendale VIC 3195",
    "addr:housenumber":"7",
    "addr:postcode":"3195",
    "addr:street":"Haynes Crt",
    "iso:country":"AU",
    "sg:address":"7 Haynes Crt",
    "sg:city":"Aspendale",
    "sg:classifiers":[
        {
            "category":"Shopping",
            "subcategory":"Computers & Home Electronics",
            "type":"Retail Goods"
        }
    ],
    "sg:phone":"+61 3 9580 9144",
    "sg:postcode":"3195",
    "sg:province":"VIC",
    "sg:tags":[
        "equipment",
        "part",
        "electronic"
    ],
    "wof:name":"Nalmos Components",
    "wof:placetype":"venue"
},
  "geometry": {"coordinates":[145.124801636,-38.0253372192],"type":"Point"}
}