{
  "type": "Feature",
  "properties": {
    "addr:full":"31c Sennell St North Parramatta NSW 2151",
    "addr:housenumber":"31c",
    "addr:postcode":"2151",
    "addr:street":"Sennell St",
    "iso:country":"AU",
    "sg:address":"31c Sennell St",
    "sg:city":"North Parramatta",
    "sg:classifiers":[
        {
            "category":"Shopping",
            "subcategory":"Beauty & Cosmetics",
            "type":"Retail Goods"
        }
    ],
    "sg:phone":"+61 2 9683 4574",
    "sg:postcode":"2151",
    "sg:province":"NSW",
    "sg:tags":[
        "equipment",
        "salon",
        "supply"
    ],
    "wof:name":"On Hand Nails Waxing & Training",
    "wof:placetype":"venue"
},
  "geometry": {"coordinates":[151.010131836,-33.7986602783],"type":"Point"}
}