{
  "type": "Feature",
  "properties": {
    "addr:full":"Loop Rd Hobart International Airport Cambridge TAS 7170",
    "addr:postcode":"7170",
    "addr:street":"Loop Rd",
    "iso:country":"AU",
    "sg:address":"Loop Rd",
    "sg:city":"Hobart International Airport Cambridge",
    "sg:classifiers":[
        {
            "category":"Retail",
            "subcategory":"Auto Rental",
            "type":"Services"
        }
    ],
    "sg:phone":"+61 3 6248 4035",
    "sg:postcode":"7170",
    "sg:province":"TAS",
    "sg:tags":[
        "car",
        "hire",
        "minibus"
    ],
    "wof:name":"Cruisin&#039; Tasmania",
    "wof:placetype":"venue"
},
  "geometry": {"coordinates":[147.441650391,-42.8367195129],"type":"Point"}
}