{
  "type": "Feature",
  "properties": {
    "iso:country":"AU",
    "sg:address":"2261 Point Nepean Rd",
    "sg:city":"Rye",
    "sg:classifiers":[
        {
            "category":"Retail",
            "subcategory":"Veterinary Services",
            "type":"Services"
        }
    ],
    "sg:phone":"+61 3 5985 6644",
    "sg:postcode":"3941",
    "sg:province":"VIC",
    "sg:tags":[
        "surgeon"
    ],
    "wof:name":"Kingston Heather & John",
    "wof:placetype":"venue"
},
  "geometry": {"coordinates":[144.82675170900001,-38.3709907532],"type":"Point"}
}