{
  "type": "Feature",
  "properties": {
    "addr:full":"10 Norris Rd Rowville VIC 3178",
    "addr:housenumber":"10",
    "addr:postcode":"3178",
    "addr:street":"Norris Rd",
    "iso:country":"AU",
    "sg:address":"10 Norris Rd",
    "sg:city":"Rowville",
    "sg:classifiers":[
        {
            "category":"Building & Trades",
            "subcategory":"Construction",
            "type":"Services"
        }
    ],
    "sg:phone":"+61 414 458 120",
    "sg:postcode":"3178",
    "sg:province":"VIC",
    "sg:tags":[
        "renovation",
        "alterations",
        "extension",
        "contractor"
    ],
    "wof:name":"Knock on Carpentry Services",
    "wof:placetype":"venue"
},
  "geometry": {"coordinates":[145.2449646,-37.9143486023],"type":"Point"}
}