{
  "type": "Feature",
  "properties": {
    "addr:full":"156 Ryans Rd Nundah QLD 4012",
    "addr:housenumber":"156",
    "addr:postcode":"4012",
    "addr:street":"Ryans Rd",
    "iso:country":"AU",
    "sg:address":"156 Ryans Rd",
    "sg:city":"Nundah",
    "sg:classifiers":[
        {
            "category":"Farming",
            "subcategory":"Crops",
            "type":"Manufacturing & Wholesale Goods"
        }
    ],
    "sg:phone":"+61 7 3266 1700",
    "sg:postcode":"4012",
    "sg:province":"QLD",
    "sg:tags":[
        "warehousing"
    ],
    "wof:name":"Stellar Warehousing & Distribution",
    "wof:placetype":"venue"
},
  "geometry": {"coordinates":[153.06272888199999,-27.3985538483],"type":"Point"}
}