{
  "type": "Feature",
  "properties": {
    "iso:country":"AU",
    "sg:address":"139 East St",
    "sg:city":"Rockhampton",
    "sg:classifiers":[
        {
            "category":"Manufacturing",
            "subcategory":"Jewelry",
            "type":"Manufacturing & Wholesale Goods"
        }
    ],
    "sg:phone":"+61 7 4927 1855",
    "sg:postcode":"4700",
    "sg:province":"QLD",
    "sg:tags":[
        "mfrg",
        "jeweller"
    ],
    "wof:name":"Phil Peel Jeweller",
    "wof:placetype":"venue"
},
  "geometry": {"coordinates":[150.52137756400001,-23.3892612457],"type":"Point"}
}