{
  "type": "Feature",
  "properties": {
    "iso:country":"AU",
    "sg:address":"Suite 201/8- 10 Brodie Spark Drv",
    "sg:city":"Wolli Creek",
    "sg:classifiers":[
        {
            "category":"Banks & Credit Unions",
            "subcategory":"Investment Brokerage",
            "type":"Services"
        }
    ],
    "sg:phone":"+61 2 9556 1184",
    "sg:postcode":"2205",
    "sg:province":"NSW",
    "sg:tags":[
        "management",
        "property"
    ],
    "wof:name":"Wentworth Management Services (NSW) Pty Ltd",
    "wof:placetype":"venue"
},
  "geometry": {"coordinates":[151.15495300000001,-33.930752],"type":"Point"}
}