{
  "type": "Feature",
  "properties": {
    "iso:country":"AU",
    "sg:address":"63 Christie St",
    "sg:city":"St Leonards",
    "sg:classifiers":[
        {
            "category":"Professional",
            "subcategory":"Engineering",
            "type":"Services"
        }
    ],
    "sg:phone":"+61 2 9411 1633",
    "sg:postcode":"2065",
    "sg:province":"NSW",
    "sg:tags":[
        "consulting",
        "engineer"
    ],
    "wof:name":"Ho & Lee Engineering Consultants Pty Ltd",
    "wof:placetype":"venue"
},
  "geometry": {"coordinates":[151.195846558,-33.8241729736],"type":"Point"}
}