{
  "type": "Feature",
  "properties": {
    "iso:country":"AU",
    "sg:address":"Lvl 1 Franklin Whf",
    "sg:city":"Hobart",
    "sg:classifiers":[
        {
            "category":"Real Estate",
            "subcategory":"Surveying",
            "type":"Services"
        }
    ],
    "sg:phone":"+61 3 6233 8801",
    "sg:postcode":"7000",
    "sg:province":"TAS",
    "sg:tags":[
        "surveyor",
        "marine",
        "cargo"
    ],
    "wof:name":"Marine & Safety Tasmania",
    "wof:placetype":"venue"
},
  "geometry": {"coordinates":[147.31086730999999,-42.8757209778],"type":"Point"}
}