{
  "type": "Feature",
  "properties": {
    "iso:country":"AU",
    "sg:address":"37 Maple St",
    "sg:city":"Maleny",
    "sg:classifiers":[
        {
            "category":"Cafe",
            "type":"Food & Drink"
        }
    ],
    "sg:phone":"+61 7 5494 2860",
    "sg:postcode":"4552",
    "sg:province":"QLD",
    "wof:name":"Colin James Fine Foods",
    "wof:placetype":"venue"
},
  "geometry": {"coordinates":[152.849411011,-26.7579975128],"type":"Point"}
}