{
  "type": "Feature",
  "properties": {
    "addr:full":"8 Wenvoe St Devonport TAS 7310",
    "addr:housenumber":"8",
    "addr:postcode":"7310",
    "addr:street":"Wenvoe St",
    "iso:country":"AU",
    "sg:address":"8 Wenvoe St",
    "sg:city":"Devonport",
    "sg:classifiers":[
        {
            "category":"Health Services",
            "subcategory":"Doctor",
            "type":"Services"
        }
    ],
    "sg:phone":"+61 3 6498 7600",
    "sg:postcode":"7310",
    "sg:province":"TAS",
    "sg:tags":[
        "medical",
        "practitioner"
    ],
    "wof:name":"Naiker Vini",
    "wof:placetype":"venue"
},
  "geometry": {"coordinates":[146.36094665499999,-41.1817398071],"type":"Point"}
}