{
  "type": "Feature",
  "properties": {
    "iso:country":"AU",
    "sg:address":"136 Orchardleigh St",
    "sg:city":"Guildford",
    "sg:classifiers":[
        {
            "category":"Building & Trades",
            "subcategory":"Construction",
            "type":"Services"
        }
    ],
    "sg:phone":"+61 2 9632 9604",
    "sg:postcode":"2161",
    "sg:province":"NSW",
    "sg:tags":[
        "polishing",
        "sanding",
        "floor"
    ],
    "wof:name":"Top Floor Sanding",
    "wof:placetype":"venue"
},
  "geometry": {"coordinates":[150.98548889200001,-33.8665847778],"type":"Point"}
}