{
  "type": "Feature",
  "properties": {
    "addr:full":"Unit 2/ 15 Howleys Rd Notting Hill VIC 3168",
    "addr:housenumber":"15",
    "addr:postcode":"3168",
    "addr:street":"Howleys Rd",
    "iso:country":"AU",
    "sg:address":"Unit 2/ 15 Howleys Rd",
    "sg:city":"Notting Hill",
    "sg:classifiers":[
        {
            "category":"Building & Trades",
            "subcategory":"Cleaning & Sanitation",
            "type":"Services"
        }
    ],
    "sg:phone":"+61 3 9543 9775",
    "sg:postcode":"3168",
    "sg:province":"VIC",
    "sg:tags":[
        "industrial",
        "commercial",
        "contractor"
    ],
    "wof:name":"Australian Service Industries",
    "wof:placetype":"venue"
},
  "geometry": {"coordinates":[145.137908936,-37.9019165039],"type":"Point"}
}