{
  "type": "Feature",
  "properties": {
    "iso:country":"AU",
    "sg:address":"162 Eric St",
    "sg:city":"Goodna",
    "sg:classifiers":[
        {
            "category":"Retail",
            "subcategory":"Auto Repair",
            "type":"Services"
        }
    ],
    "sg:phone":"+61 7 3288 4741",
    "sg:postcode":"4300",
    "sg:province":"QLD",
    "sg:tags":[
        "repairer",
        "motor",
        "engineer"
    ],
    "wof:name":"Gary & Kham Workshop",
    "wof:placetype":"venue"
},
  "geometry": {"coordinates":[152.89300537099999,-27.6179199219],"type":"Point"}
}