{
  "type": "Feature",
  "properties": {
    "addr:full":"142 Highland Tce St Lucia QLD 4067",
    "addr:housenumber":"142",
    "addr:postcode":"4067",
    "addr:street":"Highland Tce",
    "iso:country":"AU",
    "sg:address":"142 Highland Tce St",
    "sg:city":"Lucia",
    "sg:classifiers":[
        {
            "category":"Health Services",
            "subcategory":"Doctor",
            "type":"Services"
        }
    ],
    "sg:phone":"+61 7 3871 1390",
    "sg:postcode":"4067",
    "sg:province":"QLD",
    "sg:tags":[
        "medical",
        "practitioner"
    ],
    "wof:name":"Pillay S P Dr",
    "wof:placetype":"venue"
},
  "geometry": {"coordinates":[153.00080871599999,-27.5038013458],"type":"Point"}
}