{
  "type": "Feature",
  "properties": {
    "iso:country":"AU",
    "sg:address":"67 Kremzow Rd",
    "sg:city":"Brendale",
    "sg:classifiers":[
        {
            "category":"Banks & Credit Unions",
            "subcategory":"Bank",
            "type":"Services"
        }
    ],
    "sg:phone":"+61 7 3205 6622",
    "sg:postcode":"4500",
    "sg:province":"QLD",
    "sg:tags":[
        "castor"
    ],
    "wof:name":"B and# D Engineering",
    "wof:placetype":"venue"
},
  "geometry": {"coordinates":[152.973556519,-27.316242218],"type":"Point"}
}