{
  "type": "Feature",
  "properties": {
    "addr:full":"Suite 17, 631 Pittwater Dee Why NSW 2099",
    "addr:housenumber":"631",
    "addr:postcode":"2099",
    "addr:street":"Pittwater",
    "iso:country":"AU",
    "sg:address":"Suite 17, 631 Pittwater",
    "sg:city":"Dee Why",
    "sg:classifiers":[
        {
            "category":"Professional",
            "subcategory":"Business Services",
            "type":"Services"
        }
    ],
    "sg:phone":"+61 2 9984 1322",
    "sg:postcode":"2099",
    "sg:province":"NSW",
    "sg:tags":[
        "management",
        "event"
    ],
    "wof:name":"The Event Firm",
    "wof:placetype":"venue"
},
  "geometry": {"coordinates":[151.28286743199999,-33.7556304932],"type":"Point"}
}