{
  "type": "Feature",
  "properties": {
    "iso:country":"AU",
    "sg:address":"227 Prospect Rd",
    "sg:city":"Prospect",
    "sg:classifiers":[
        {
            "category":"Autos & Motor Vehicles",
            "subcategory":"Automobile Sales",
            "type":"Retail Goods"
        }
    ],
    "sg:phone":"+61 8 8344 7655",
    "sg:postcode":"5082",
    "sg:province":"SA",
    "sg:tags":[
        "car",
        "used"
    ],
    "wof:name":"European Cars Prospect",
    "wof:placetype":"venue"
},
  "geometry": {"coordinates":[138.593307495,-34.8742141724],"type":"Point"}
}