{
  "type": "Feature",
  "properties": {
    "addr:full":"Graham Rd Narrogin WA 6312",
    "addr:postcode":"6312",
    "addr:street":"Graham Rd",
    "iso:country":"AU",
    "sg:address":"Graham Rd",
    "sg:city":"Narrogin",
    "sg:classifiers":[
        {
            "category":"Professional",
            "subcategory":"Engineering",
            "type":"Services"
        }
    ],
    "sg:phone":"+61 8 9881 4427",
    "sg:postcode":"6312",
    "sg:province":"WA",
    "sg:tags":[
        "engineer"
    ],
    "wof:name":"Borgas Engineering",
    "wof:placetype":"venue"
},
  "geometry": {"coordinates":[117.177978516,-32.9510574341],"type":"Point"}
}