{
  "type": "Feature",
  "properties": {
    "addr:full":"3 Gooray St Glen Forrest WA 6071",
    "addr:housenumber":"3",
    "addr:postcode":"6071",
    "addr:street":"Gooray St Glen",
    "iso:country":"AU",
    "sg:address":"3 Gooray St",
    "sg:city":"Glen Forrest",
    "sg:classifiers":[
        {
            "category":"Home & Garden",
            "subcategory":"Hardware",
            "type":"Retail Goods"
        }
    ],
    "sg:phone":"+61 432 339 120",
    "sg:postcode":"6071",
    "sg:province":"WA",
    "sg:tags":[
        "compressor",
        "air"
    ],
    "wof:name":"Pneu-Install",
    "wof:placetype":"venue"
},
  "geometry": {"coordinates":[116.108413696,-31.9100990295],"type":"Point"}
}