{
  "type": "Feature",
  "properties": {
    "iso:country":"AU",
    "sg:address":"Gardiners Rd",
    "sg:city":"Maclean",
    "sg:classifiers":[
        {
            "category":"Home & Garden",
            "subcategory":"Building Materials",
            "type":"Retail Goods"
        }
    ],
    "sg:phone":"+61 2 6645 3631",
    "sg:postcode":"2463",
    "sg:province":"NSW",
    "sg:tags":[
        "lawn",
        "cutting",
        "maintenance"
    ],
    "wof:name":"Prestige Lawn Solutions",
    "wof:placetype":"venue"
},
  "geometry": {"coordinates":[153.230545044,-29.4647083282],"type":"Point"}
}