{
  "type": "Feature",
  "properties": {
    "addr:full":"143 Industrial Rd Oak Flats NSW 2529",
    "addr:housenumber":"143",
    "addr:postcode":"2529",
    "addr:street":"Industrial Rd",
    "iso:country":"AU",
    "sg:address":"143 Industrial Rd",
    "sg:city":"Oak Flats",
    "sg:classifiers":[
        {
            "category":"Home & Garden",
            "subcategory":"Carpets & Floor Coverings",
            "type":"Retail Goods"
        }
    ],
    "sg:phone":"+61 2 4257 8933",
    "sg:postcode":"2529",
    "sg:province":"NSW",
    "sg:tags":[
        "wood"
    ],
    "wof:name":"Carpet One Shellharbour",
    "wof:placetype":"venue"
},
  "geometry": {"coordinates":[150.80563354500001,-34.565372467],"type":"Point"}
}