{
  "type": "Feature",
  "properties": {
    "iso:country":"AU",
    "sg:address":"6 Torquay Rd",
    "sg:city":"Pialba",
    "sg:classifiers":[
        {
            "category":"Home & Garden",
            "subcategory":"Carpets & Floor Coverings",
            "type":"Retail Goods"
        }
    ],
    "sg:phone":"+61 7 4124 8511",
    "sg:postcode":"4655",
    "sg:province":"QLD",
    "sg:tags":[
        "wood"
    ],
    "wof:name":"Rob Nissens Floor Covering Centre",
    "wof:placetype":"venue"
},
  "geometry": {"coordinates":[152.84002699999999,-25.281515],"type":"Point"}
}