{
  "type": "Feature",
  "properties": {
    "iso:country":"AU",
    "sg:address":"11 Burramine Crt",
    "sg:city":"Frankston",
    "sg:classifiers":[
        {
            "category":"Professional",
            "subcategory":"Engineering",
            "type":"Services"
        }
    ],
    "sg:phone":"+61 418 347 308",
    "sg:postcode":"3199",
    "sg:province":"VIC",
    "sg:tags":[
        "engineer"
    ],
    "wof:name":"Corr Electrics Pty Ltd",
    "wof:placetype":"venue"
},
  "geometry": {"coordinates":[145.13259887699999,-38.1743087769],"type":"Point"}
}