{
  "type": "Feature",
  "properties": {
    "iso:country":"AU",
    "sg:address":"5/ 800 Old Illawarra Rd",
    "sg:city":"Menai",
    "sg:classifiers":[
        {
            "category":"Autos & Motor Vehicles",
            "subcategory":"Motorcycle Sales",
            "type":"Retail Goods"
        }
    ],
    "sg:phone":"+61 2 9532 0002",
    "sg:postcode":"2234",
    "sg:province":"NSW",
    "sg:tags":[
        "outboard"
    ],
    "wof:name":"Menai Marine",
    "wof:placetype":"venue"
},
  "geometry": {"coordinates":[151.01048278799999,-34.0173721313],"type":"Point"}
}