{
  "type": "Feature",
  "properties": {
    "addr:full":"241 Carlisle St Balaclava VIC 3183",
    "addr:housenumber":"241",
    "addr:postcode":"3183",
    "addr:street":"Carlisle St",
    "iso:country":"AU",
    "sg:address":"241 Carlisle St",
    "sg:city":"Balaclava",
    "sg:classifiers":[
        {
            "category":"Health Services",
            "subcategory":"Doctor",
            "type":"Services"
        }
    ],
    "sg:phone":"+61 3 9527 7134",
    "sg:postcode":"3183",
    "sg:province":"VIC",
    "sg:tags":[
        "medical",
        "practitioner"
    ],
    "wof:name":"Grokop S",
    "wof:placetype":"venue"
},
  "geometry": {"coordinates":[144.994796753,-37.8690376282],"type":"Point"}
}