{
  "type": "Feature",
  "properties": {
    "iso:country":"AU",
    "sg:address":"10/ 9 George Rd",
    "sg:city":"Salamander Bay",
    "sg:classifiers":[
        {
            "category":"Building & Trades",
            "subcategory":"Construction",
            "type":"Services"
        }
    ],
    "sg:phone":"+61 2 4982 7822",
    "sg:postcode":"2317",
    "sg:province":"NSW",
    "sg:tags":[
        "management"
    ],
    "wof:name":"McDowell Homes",
    "wof:placetype":"venue"
},
  "geometry": {"coordinates":[152.074997,-32.726624],"type":"Point"}
}