{
  "type": "Feature",
  "properties": {
    "iso:country":"AU",
    "sg:address":"PO Box 852",
    "sg:city":"West Perth",
    "sg:classifiers":[
        {
            "category":"Utilities",
            "subcategory":"Fuel Oil & Lpg",
            "type":"Services"
        }
    ],
    "sg:phone":"+61 8 9225 6585",
    "sg:postcode":"6005",
    "sg:province":"WA",
    "sg:tags":[
        "olive"
    ],
    "wof:name":"The Fresh Olive Company",
    "wof:placetype":"venue"
},
  "geometry": {"coordinates":[115.8465271,-31.9449996948],"type":"Point"}
}