{
  "type": "Feature",
  "properties": {
    "addr:full":"102 Mollison St Kyneton VIC 3444",
    "addr:housenumber":"102",
    "addr:postcode":"3444",
    "addr:street":"Mollison St",
    "iso:country":"AU",
    "sg:address":"102 Mollison St",
    "sg:city":"Kyneton",
    "sg:classifiers":[
        {
            "category":"Personal",
            "subcategory":"Massage",
            "type":"Services"
        }
    ],
    "sg:phone":"+61 3 5422 3146",
    "sg:postcode":"3444",
    "sg:province":"VIC",
    "sg:tags":[
        "therapy"
    ],
    "wof:name":"Kyneton Chemical Free",
    "wof:placetype":"venue"
},
  "geometry": {"coordinates":[144.45355224599999,-37.2483139038],"type":"Point"}
}