{
  "type": "Feature",
  "properties": {
    "addr:full":"Buderim Central Shopping Cent. 7 Lindsay Rd Buderim QLD 4556",
    "addr:housenumber":"7",
    "addr:postcode":"4556",
    "addr:street":"Lindsay Rd",
    "iso:country":"AU",
    "sg:address":"Buderim Central Shopping Cent. 7 Lindsay Rd",
    "sg:city":"Buderim",
    "sg:classifiers":[
        {
            "category":"Personal",
            "subcategory":"Beauty Salon",
            "type":"Services"
        }
    ],
    "sg:phone":"+61 7 5445 3874",
    "sg:postcode":"4556",
    "sg:province":"QLD",
    "sg:tags":[
        "hairdresser"
    ],
    "wof:name":"Michelles",
    "wof:placetype":"venue"
},
  "geometry": {"coordinates":[153.05026245100001,-26.6841888428],"type":"Point"}
}