{
  "type": "Feature",
  "properties": {
    "addr:full":"237 Abbotsford St North Melbourne VIC 3051",
    "addr:housenumber":"237",
    "addr:postcode":"3051",
    "addr:street":"Abbotsford St",
    "iso:country":"AU",
    "sg:address":"237 Abbotsford St",
    "sg:city":"North Melbourne",
    "sg:classifiers":[
        {
            "category":"Structure",
            "subcategory":"Bridge",
            "type":"Public Place"
        }
    ],
    "sg:phone":"+61 3 9328 4157",
    "sg:postcode":"3051",
    "sg:province":"VIC",
    "sg:tags":[
        "chainsaw",
        "brushcutters"
    ],
    "wof:name":"A.C. James Service",
    "wof:placetype":"venue"
},
  "geometry": {"coordinates":[144.94552612300001,-37.8016738892],"type":"Point"}
}