{
  "type": "Feature",
  "properties": {
    "addr:full":"17a Brougham St Eltham VIC 3095",
    "addr:housenumber":"17a",
    "addr:postcode":"3095",
    "addr:street":"Brougham St",
    "iso:country":"AU",
    "sg:address":"17a Brougham St",
    "sg:city":"Eltham",
    "sg:classifiers":[
        {
            "category":"Retail",
            "subcategory":"Auto Repair",
            "type":"Services"
        }
    ],
    "sg:phone":"+61 3 9439 2233",
    "sg:postcode":"3095",
    "sg:province":"VIC",
    "sg:tags":[
        "repairer",
        "motor",
        "engineer"
    ],
    "wof:name":"Eltham Motors",
    "wof:placetype":"venue"
},
  "geometry": {"coordinates":[145.1381073,-37.7215881348],"type":"Point"}
}