{
  "type": "Feature",
  "properties": {
    "addr:full":"2a Bryant St Maryborough VIC 3465",
    "addr:housenumber":"2a",
    "addr:postcode":"3465",
    "addr:street":"Bryant St",
    "iso:country":"AU",
    "sg:address":"2a Bryant St",
    "sg:city":"Maryborough",
    "sg:classifiers":[
        {
            "category":"Arena",
            "subcategory":"Sports Club",
            "type":"Entertainment"
        }
    ],
    "sg:phone":"+61 3 5461 3602",
    "sg:postcode":"3465",
    "sg:province":"VIC",
    "sg:tags":[
        "australian",
        "football",
        "rule"
    ],
    "wof:name":"Maryborough Castlemaine District Football League",
    "wof:placetype":"venue"
},
  "geometry": {"coordinates":[143.75117492699999,-37.0535507202],"type":"Point"}
}