{
  "type": "Feature",
  "properties": {
    "addr:full":"212 Pakenham St Echuca VIC 3564",
    "addr:housenumber":"212",
    "addr:postcode":"3564",
    "addr:street":"Pakenham St",
    "iso:country":"AU",
    "sg:address":"212 Pakenham St",
    "sg:city":"Echuca",
    "sg:classifiers":[
        {
            "category":"Retail",
            "subcategory":"Repair Shop",
            "type":"Services"
        }
    ],
    "sg:phone":"+61 3 5480 7975",
    "sg:postcode":"3564",
    "sg:province":"VIC",
    "sg:tags":[
        "mending",
        "clothing",
        "alteration"
    ],
    "wof:name":"Sew & Sew Alterations & Dress Making",
    "wof:placetype":"venue"
},
  "geometry": {"coordinates":[144.75111389200001,-36.128036499],"type":"Point"}
}