{
  "type": "Feature",
  "properties": {
    "addr:full":"Lot 3 Middle Rd Gracemere QLD 4702",
    "addr:postcode":"4702",
    "addr:street":"Middle Rd",
    "iso:country":"AU",
    "sg:address":"Lot 3 Middle Rd",
    "sg:city":"Gracemere",
    "sg:classifiers":[
        {
            "category":"Mining & Drilling",
            "type":"Manufacturing & Wholesale Goods"
        }
    ],
    "sg:phone":"+61 7 4933 1500",
    "sg:postcode":"4702",
    "sg:province":"QLD",
    "sg:tags":[
        "equipment",
        "quarrying",
        "supply"
    ],
    "wof:name":"Code &#039;D&#039; Engineering",
    "wof:placetype":"venue"
},
  "geometry": {"coordinates":[150.45228576700001,-23.4472332001],"type":"Point"}
}