{
  "type": "Feature",
  "properties": {
    "iso:country":"AU",
    "sg:address":"Unit 27 8 Wells St",
    "sg:city":"South Melbourne",
    "sg:classifiers":[
        {
            "category":"Professional",
            "subcategory":"Computer Services",
            "type":"Services"
        }
    ],
    "sg:phone":"+61 3 9686 5488",
    "sg:postcode":"3205",
    "sg:province":"VIC",
    "sg:tags":[
        "consultant",
        "system"
    ],
    "wof:name":"Metro Systems",
    "wof:placetype":"venue"
},
  "geometry": {"coordinates":[144.96894800000001,-37.826202],"type":"Point"}
}