{
  "type": "Feature",
  "properties": {
    "addr:full":"C/-Coats Patons Complex Launceston TAS 7250",
    "addr:postcode":"7250",
    "addr:street":"C /",
    "iso:country":"AU",
    "sg:address":"C/-Coats Patons Complex",
    "sg:city":"Launceston",
    "sg:classifiers":[
        {
            "category":"Retail",
            "subcategory":"Auto Repair",
            "type":"Services"
        }
    ],
    "sg:phone":"+61 418 769 411",
    "sg:postcode":"7250",
    "sg:province":"TAS",
    "sg:tags":[
        "repairer",
        "motor",
        "engineer"
    ],
    "wof:name":"Custom To Classic Automotive",
    "wof:placetype":"venue"
},
  "geometry": {"coordinates":[147.138504028,-41.4452018738],"type":"Point"}
}