{
  "type": "Feature",
  "properties": {
    "addr:full":"34 Kingsford Drv Brunswick Heads NSW 2483",
    "addr:housenumber":"34",
    "addr:postcode":"2483",
    "addr:street":"Kingsford Drv",
    "iso:country":"AU",
    "sg:address":"34 Kingsford Drv",
    "sg:city":"Brunswick Heads",
    "sg:classifiers":[
        {
            "category":"Personal",
            "subcategory":"Beauty Salon",
            "type":"Services"
        }
    ],
    "sg:phone":"+61 2 6685 1648",
    "sg:postcode":"2483",
    "sg:province":"NSW",
    "wof:name":"Relax & wax",
    "wof:placetype":"venue"
},
  "geometry": {"coordinates":[153.545410156,-28.5573692322],"type":"Point"}
}