{
  "type": "Feature",
  "properties": {
    "iso:country":"AU",
    "sg:address":"24 Glenwood Ave",
    "sg:city":"Helena Valley",
    "sg:classifiers":[
        {
            "category":"Professional",
            "subcategory":"Secretarial Services",
            "type":"Services"
        }
    ],
    "sg:phone":"+61 8 9294 2323",
    "sg:postcode":"6056",
    "sg:province":"WA",
    "sg:tags":[
        "typing"
    ],
    "wof:name":"Snap Secretarial",
    "wof:placetype":"venue"
},
  "geometry": {"coordinates":[116.044372559,-31.9178161621],"type":"Point"}
}