{
  "type": "Feature",
  "properties": {
    "iso:country":"AU",
    "sg:address":"Beck St",
    "sg:city":"Dalby",
    "sg:classifiers":[
        {
            "category":"Education",
            "subcategory":"Kindergarten",
            "type":"Public Place"
        }
    ],
    "sg:phone":"+61 7 4662 3586",
    "sg:postcode":"4405",
    "sg:province":"QLD",
    "sg:tags":[
        "pre-schools"
    ],
    "wof:name":"Dalby Beck St Kindergarten Assoc Inc",
    "wof:placetype":"venue"
},
  "geometry": {"coordinates":[151.26812744099999,-27.175693512],"type":"Point"}
}