{
  "type": "Feature",
  "properties": {
    "iso:country":"AU",
    "sg:address":"126 Sheridan St",
    "sg:city":"Cairns",
    "sg:classifiers":[
        {
            "category":"Shopping",
            "subcategory":"News",
            "type":"Retail Goods"
        }
    ],
    "sg:phone":"+61 7 4051 2151",
    "sg:postcode":"4870",
    "sg:province":"QLD",
    "sg:tags":[
        "magazine",
        "periodical"
    ],
    "wof:name":"Sheridan St News",
    "wof:placetype":"venue"
},
  "geometry": {"coordinates":[145.769332886,-16.9181308746],"type":"Point"}
}