{
  "type": "Feature",
  "properties": {
    "addr:full":"Tamar Crt Exeter TAS 7275",
    "addr:postcode":"7275",
    "addr:street":"Tamar Crt",
    "iso:country":"AU",
    "sg:address":"Tamar Crt",
    "sg:city":"Exeter",
    "sg:classifiers":[
        {
            "category":"Government",
            "subcategory":"Post Office",
            "type":"Public Place"
        }
    ],
    "sg:phone":"+61 3 6394 4211",
    "sg:postcode":"7275",
    "sg:province":"TAS",
    "sg:tags":[
        "postal"
    ],
    "wof:name":"Australia Post",
    "wof:placetype":"venue"
},
  "geometry": {"coordinates":[146.944946289,-41.2923202515],"type":"Point"}
}