{
  "type": "Feature",
  "properties": {
    "iso:country":"AU",
    "sg:address":"Unit 5, 22 Irvine Drv",
    "sg:city":"Malaga",
    "sg:classifiers":[
        {
            "category":"Manufacturing",
            "subcategory":"Metals",
            "type":"Manufacturing & Wholesale Goods"
        }
    ],
    "sg:phone":"+61 8 9209 2982",
    "sg:postcode":"6090",
    "sg:province":"WA",
    "sg:tags":[
        "fabricator",
        "aluminium"
    ],
    "wof:name":"Armalite Fabrication",
    "wof:placetype":"venue"
},
  "geometry": {"coordinates":[115.886360169,-31.8593902588],"type":"Point"}
}