{
  "type": "Feature",
  "properties": {
    "addr:full":"PO Box 813 Brookvale NSW 2100",
    "addr:postcode":"2100",
    "iso:country":"AU",
    "sg:address":"PO Box 813",
    "sg:city":"Brookvale",
    "sg:classifiers":[
        {
            "category":"Professional",
            "subcategory":"Computer Services",
            "type":"Services"
        }
    ],
    "sg:phone":"+61 412 444 968",
    "sg:postcode":"2100",
    "sg:province":"NSW",
    "sg:tags":[
        "training"
    ],
    "wof:name":"Fastrack Computer Skills",
    "wof:placetype":"venue"
},
  "geometry": {"coordinates":[151.273071289,-33.7611312866],"type":"Point"}
}