{
  "type": "Feature",
  "properties": {
    "addr:full":"7/ 188 The Entrance Rd Erina NSW 2250",
    "addr:housenumber":"/ 188",
    "addr:postcode":"2250",
    "addr:street":"The Entrance Rd",
    "iso:country":"AU",
    "sg:address":"7/ 188 The Entrance Rd",
    "sg:city":"Erina",
    "sg:classifiers":[
        {
            "category":"Professional",
            "subcategory":"Detective & Security Services",
            "type":"Services"
        }
    ],
    "sg:phone":"+61 2 4367 8266",
    "sg:postcode":"2250",
    "sg:province":"NSW",
    "sg:tags":[
        "consultant",
        "system"
    ],
    "wof:name":"ACS",
    "wof:placetype":"venue"
},
  "geometry": {"coordinates":[151.385375977,-33.4359664917],"type":"Point"}
}