{
  "type": "Feature",
  "properties": {
    "addr:full":"5 High St Dee Why NSW 2099",
    "addr:housenumber":"5",
    "addr:postcode":"2099",
    "addr:street":"High St",
    "iso:country":"AU",
    "sg:address":"5 High St",
    "sg:city":"Dee Why",
    "sg:classifiers":[
        {
            "category":"Building & Trades",
            "subcategory":"Construction",
            "type":"Services"
        }
    ],
    "sg:phone":"+61 2 9982 5695",
    "sg:postcode":"2099",
    "sg:province":"NSW",
    "sg:tags":[
        "rendering",
        "cement"
    ],
    "wof:name":"Finocchiaro Benito",
    "wof:placetype":"venue"
},
  "geometry": {"coordinates":[151.281448364,-33.7504310608],"type":"Point"}
}