{
  "type": "Feature",
  "properties": {
    "addr:full":"67 River St Dubbo NSW 2830",
    "addr:housenumber":"67",
    "addr:postcode":"2830",
    "addr:street":"River St",
    "iso:country":"AU",
    "sg:address":"67 River St",
    "sg:city":"Dubbo",
    "sg:classifiers":[
        {
            "category":"Retail",
            "subcategory":"Car Wash",
            "type":"Services"
        }
    ],
    "sg:phone":"+61 2 6884 1235",
    "sg:postcode":"2830",
    "sg:province":"NSW",
    "sg:tags":[
        "truck",
        "cleaning"
    ],
    "wof:name":"J.R. Cleaning & Car Detailing",
    "wof:placetype":"venue"
},
  "geometry": {"coordinates":[148.61134338400001,-32.2342147827],"type":"Point"}
}