{
  "type": "Feature",
  "properties": {
    "addr:full":"12 Walsh St Vista SA 5091",
    "addr:housenumber":"12",
    "addr:postcode":"5091",
    "addr:street":"Walsh St",
    "iso:country":"AU",
    "sg:address":"12 Walsh St",
    "sg:city":"Vista",
    "sg:classifiers":[
        {
            "category":"Real Estate",
            "subcategory":"Surveying",
            "type":"Services"
        }
    ],
    "sg:phone":"+61 8 8396 4710",
    "sg:postcode":"5091",
    "sg:province":"SA",
    "sg:tags":[
        "surveyor",
        "land"
    ],
    "wof:name":"Grantley D Leith",
    "wof:placetype":"venue"
},
  "geometry": {"coordinates":[138.72125244099999,-34.8320083618],"type":"Point"}
}