{
  "type": "Feature",
  "properties": {
    "iso:country":"AU",
    "sg:address":"53 Redcliffe Pde",
    "sg:city":"Redcliffe",
    "sg:classifiers":[
        {
            "category":"Real Estate",
            "subcategory":"Real Estate Agent",
            "type":"Services"
        }
    ],
    "sg:phone":"+61 7 3283 8444",
    "sg:postcode":"4020",
    "sg:province":"QLD",
    "wof:name":"Hermans Real Estate",
    "wof:placetype":"venue"
},
  "geometry": {"coordinates":[153.11532600000001,-27.228338],"type":"Point"}
}