{
  "type": "Feature",
  "properties": {
    "addr:full":"Unit 4, 44 Queen St Campbelltown NSW 2560",
    "addr:housenumber":"44",
    "addr:postcode":"2560",
    "addr:street":"Queen St",
    "iso:country":"AU",
    "sg:address":"Unit 4, 44 Queen St",
    "sg:city":"Campbelltown",
    "sg:classifiers":[
        {
            "category":"Professional",
            "subcategory":"Detective & Security Services",
            "type":"Services"
        }
    ],
    "sg:phone":"+61 2 4620 5238",
    "sg:postcode":"2560",
    "sg:province":"NSW",
    "sg:tags":[
        "consultant",
        "system"
    ],
    "wof:name":"House Guard Pty Ltd",
    "wof:placetype":"venue"
},
  "geometry": {"coordinates":[150.820388794,-34.0600318909],"type":"Point"}
}