{
  "type": "Feature",
  "properties": {
    "iso:country":"AU",
    "sg:address":"161 Pakington St",
    "sg:city":"Geelong West",
    "sg:classifiers":[
        {
            "category":"Professional",
            "subcategory":"Art Services",
            "type":"Services"
        }
    ],
    "sg:phone":"+61 3 5223 1050",
    "sg:postcode":"3218",
    "sg:province":"VIC",
    "sg:tags":[
        "picture",
        "frame",
        "framing"
    ],
    "wof:name":"Portrait Shop The",
    "wof:placetype":"venue"
},
  "geometry": {"coordinates":[144.34796142600001,-38.141658783],"type":"Point"}
}