{
  "type": "Feature",
  "properties": {
    "iso:country":"AU",
    "sg:address":"5/ 52 Mileham St",
    "sg:city":"Windsor",
    "sg:classifiers":[
        {
            "category":"Autos & Motor Vehicles",
            "subcategory":"Auto Supplies",
            "type":"Retail Goods"
        }
    ],
    "sg:phone":"+61 2 4577 3195",
    "sg:postcode":"2756",
    "sg:province":"NSW",
    "sg:tags":[
        "equipment",
        "part",
        "truck"
    ],
    "wof:name":"Windsor Truck Bits",
    "wof:placetype":"venue"
},
  "geometry": {"coordinates":[150.814453125,-33.6146774292],"type":"Point"}
}