{
  "type": "Feature",
  "properties": {
    "addr:full":"Beeches Tavern, 165 Altone Rd Beechboro WA 6063",
    "addr:housenumber":"165",
    "addr:postcode":"6063",
    "addr:street":"Altone Rd",
    "iso:country":"AU",
    "sg:address":"Beeches Tavern, 165 Altone Rd",
    "sg:city":"Beechboro",
    "sg:classifiers":[
        {
            "category":"Food & Beverages",
            "subcategory":"Liquor & Beverages",
            "type":"Retail Goods"
        }
    ],
    "sg:phone":"+61 8 9279 3888",
    "sg:postcode":"6063",
    "sg:province":"WA",
    "sg:tags":[
        "store"
    ],
    "wof:name":"Sip'n Save Beechboro",
    "wof:placetype":"venue"
},
  "geometry": {"coordinates":[115.944908142,-31.8700008392],"type":"Point"}
}