{
  "type": "Feature",
  "properties": {
    "iso:country":"AU",
    "sg:address":"Shop 4, 14 - 28 Whitecross Rd",
    "sg:city":"Winmalee",
    "sg:classifiers":[
        {
            "category":"Fast Food",
            "type":"Food & Drink"
        }
    ],
    "sg:phone":"+61 2 4754 1500",
    "sg:postcode":"2777",
    "sg:province":"NSW",
    "sg:tags":[
        "away",
        "take"
    ],
    "wof:name":"Homers Burgers, Seafood & Chickens Pty Ltd",
    "wof:placetype":"venue"
},
  "geometry": {"coordinates":[150.60906982399999,-33.6700210571],"type":"Point"}
}