{
  "type": "Feature",
  "properties": {
    "addr:full":"Lot 8 Serpentine Way Mandurah WA 6210",
    "addr:housenumber":"8",
    "addr:postcode":"6210",
    "addr:street":"Serpentine Way",
    "iso:country":"AU",
    "sg:address":"Lot 8",
    "sg:city":"Serpentine Way Mandurah",
    "sg:classifiers":[
        {
            "category":"Retail",
            "subcategory":"Auto Repair",
            "type":"Services"
        }
    ],
    "sg:phone":"+61 439 948 220",
    "sg:postcode":"6210",
    "sg:province":"WA",
    "sg:tags":[
        "repairer",
        "motor",
        "engineer"
    ],
    "wof:name":"Estuary Mobile Mechanical Services",
    "wof:placetype":"venue"
},
  "geometry": {"coordinates":[115.79254899999999,-32.47131],"type":"Point"}
}