{
  "type": "Feature",
  "properties": {
    "addr:full":"25 Diagnal Rd Mt Barker SA 5251",
    "addr:housenumber":"25",
    "addr:postcode":"5251",
    "addr:street":"Diagnal Rd",
    "iso:country":"AU",
    "sg:address":"25 Diagnal Rd",
    "sg:city":"Mt Barker",
    "sg:classifiers":[
        {
            "category":"Autos & Motor Vehicles",
            "subcategory":"Auto Supplies",
            "type":"Retail Goods"
        }
    ],
    "sg:phone":"+61 8 8391 2421",
    "sg:postcode":"5251",
    "sg:province":"SA",
    "sg:tags":[
        "oil",
        "spirit"
    ],
    "wof:name":"Fleurieu Petroloeum",
    "wof:placetype":"venue"
},
  "geometry": {"coordinates":[138.85125732399999,-35.0545692444],"type":"Point"}
}