{
  "type": "Feature",
  "properties": {
    "iso:country":"AU",
    "sg:address":"1st Floor, 75 Watsonia Rd",
    "sg:city":"Watsonia",
    "sg:classifiers":[
        {
            "category":"Personal",
            "subcategory":"Beauty Salon",
            "type":"Services"
        }
    ],
    "sg:phone":"+61 3 9435 5063",
    "sg:postcode":"3087",
    "sg:province":"VIC",
    "sg:tags":[
        "hairdresser"
    ],
    "wof:name":"Marjon's Hair & Beauty Centre",
    "wof:placetype":"venue"
},
  "geometry": {"coordinates":[145.08273315400001,-37.7096214294],"type":"Point"}
}