{
  "type": "Feature",
  "properties": {
    "iso:country":"AU",
    "sg:address":"266 Oxford St",
    "sg:city":"Paddington",
    "sg:classifiers":[
        {
            "category":"Shopping",
            "subcategory":"Clothing, Apparel, & Fashions",
            "type":"Retail Goods"
        }
    ],
    "sg:phone":"+61 2 9331 4340",
    "sg:postcode":"2021",
    "sg:province":"NSW",
    "sg:tags":[
        "lady",
        "wear"
    ],
    "wof:name":"Esprit Retail Pty Ltd",
    "wof:placetype":"venue"
},
  "geometry": {"coordinates":[151.22755432100001,-33.8853111267],"type":"Point"}
}