{
  "type": "Feature",
  "properties": {
    "iso:country":"AU",
    "sg:address":"12 Young St",
    "sg:city":"East Maitland",
    "sg:classifiers":[
        {
            "category":"Building & Trades",
            "subcategory":"Electrical",
            "type":"Services"
        }
    ],
    "sg:phone":"+61 2 4933 8033",
    "sg:postcode":"2323",
    "sg:province":"NSW",
    "sg:tags":[
        "repair",
        "generator",
        "electric",
        "motor"
    ],
    "wof:name":"Donnelly G & D Pty Ltd",
    "wof:placetype":"venue"
},
  "geometry": {"coordinates":[151.59963989299999,-32.7533111572],"type":"Point"}
}