{
  "type": "Feature",
  "properties": {
    "iso:country":"AU",
    "sg:address":"113 Boundary St",
    "sg:city":"South Townsville",
    "sg:classifiers":[
        {
            "category":"Manufacturing",
            "subcategory":"Motor Vehicles & Parts",
            "type":"Manufacturing & Wholesale Goods"
        }
    ],
    "sg:phone":"+61 7 4771 4403",
    "sg:postcode":"4810",
    "sg:province":"QLD",
    "sg:tags":[
        "engine",
        "equipment",
        "diesel"
    ],
    "wof:name":"Champayne Diesel Services",
    "wof:placetype":"venue"
},
  "geometry": {"coordinates":[146.823776,-19.26969],"type":"Point"}
}