{
  "type": "Feature",
  "properties": {
    "addr:full":"Wilmot Rd Forth TAS 7310",
    "addr:postcode":"7310",
    "addr:street":"Wilmot Rd",
    "iso:country":"AU",
    "sg:address":"Wilmot Rd",
    "sg:city":"Forth",
    "sg:classifiers":[
        {
            "category":"Organizations",
            "subcategory":"Professional Association",
            "type":"Services"
        }
    ],
    "sg:phone":"+61 3 6428 2975",
    "sg:postcode":"7310",
    "sg:province":"TAS",
    "sg:tags":[
        "web",
        "internet"
    ],
    "wof:name":"Forth Valley Computing",
    "wof:placetype":"venue"
},
  "geometry": {"coordinates":[146.247436523,-41.1963882446],"type":"Point"}
}