{
  "type": "Feature",
  "properties": {
    "addr:full":"136-142 Main Neerim Rd Neerim South VIC 3831",
    "addr:housenumber":"136-142",
    "addr:postcode":"3831",
    "addr:street":"Main Neerim Rd",
    "iso:country":"AU",
    "sg:address":"136-142 Main Neerim Rd",
    "sg:city":"Neerim South",
    "sg:classifiers":[
        {
            "category":"Utilities",
            "subcategory":"Water",
            "type":"Services"
        }
    ],
    "sg:phone":"+61 3 5628 1176",
    "sg:postcode":"3831",
    "sg:province":"VIC",
    "sg:tags":[
        "cartage"
    ],
    "wof:name":"Water on Wheels",
    "wof:placetype":"venue"
},
  "geometry": {"coordinates":[145.95446799999999,-38.016869],"type":"Point"}
}