{
  "type": "Feature",
  "properties": {
    "addr:full":"115 Crusoe Rd Kangaroo Flat VIC 3555",
    "addr:housenumber":"115",
    "addr:postcode":"3555",
    "addr:street":"Crusoe Rd",
    "iso:country":"AU",
    "sg:address":"115 Crusoe Rd",
    "sg:city":"Kangaroo Flat",
    "sg:classifiers":[
        {
            "category":"Personal",
            "subcategory":"Massage",
            "type":"Services"
        }
    ],
    "sg:phone":"+61 3 5447 1510",
    "sg:postcode":"3555",
    "sg:province":"VIC",
    "sg:tags":[
        "therapy"
    ],
    "wof:name":"Barry Gaylard",
    "wof:placetype":"venue"
},
  "geometry": {"coordinates":[144.23274230999999,-36.8140563965],"type":"Point"}
}