{
  "type": "Feature",
  "properties": {
    "iso:country":"AU",
    "sg:address":"111 Commercial Rd",
    "sg:city":"Port Adelaide",
    "sg:classifiers":[
        {
            "category":"Shopping",
            "subcategory":"Computers & Home Electronics",
            "type":"Retail Goods"
        }
    ],
    "sg:phone":"+61 8 8241 2760",
    "sg:postcode":"5015",
    "sg:province":"SA",
    "sg:tags":[
        "equipment",
        "supply"
    ],
    "wof:name":"IT Warehouse",
    "wof:placetype":"venue"
},
  "geometry": {"coordinates":[138.506393433,-34.8453865051],"type":"Point"}
}