{
  "type": "Feature",
  "properties": {
    "iso:country":"AU",
    "sg:address":"1008 Old Princes Hwy",
    "sg:city":"Engadine",
    "sg:classifiers":[
        {
            "category":"Communications",
            "subcategory":"Film & Video Production",
            "type":"Services"
        }
    ],
    "sg:phone":"+61 2 9520 7816",
    "sg:postcode":"2233",
    "sg:province":"NSW",
    "sg:tags":[
        "dvd",
        "library"
    ],
    "wof:name":"Video Ezy",
    "wof:placetype":"venue"
},
  "geometry": {"coordinates":[151.015060425,-34.0645027161],"type":"Point"}
}