{
  "type": "Feature",
  "properties": {
    "iso:country":"AU",
    "sg:address":"Cnr Bridge & Curzon Sts",
    "sg:city":"Toowoomba",
    "sg:classifiers":[
        {
            "category":"Shopping",
            "subcategory":"Party Supplies",
            "type":"Retail Goods"
        }
    ],
    "sg:phone":"+61 7 4639 4800",
    "sg:postcode":"4352",
    "sg:province":"QLD",
    "sg:tags":[
        "hire",
        "costume"
    ],
    "wof:name":"Teiki Costume Hire & Sales",
    "wof:placetype":"venue"
},
  "geometry": {"coordinates":[151.97320556599999,-27.5633144379],"type":"Point"}
}