{
  "type": "Feature",
  "properties": {
    "addr:full":"Unit 2, 31 Yampi Way Willetton WA 6155",
    "addr:housenumber":"31",
    "addr:postcode":"6155",
    "addr:street":"Yampi Way",
    "iso:country":"AU",
    "sg:address":"Unit 2, 31 Yampi Way",
    "sg:city":"Willetton",
    "sg:phone":"+61 8 9457 8780",
    "sg:postcode":"6155",
    "sg:province":"WA",
    "wof:name":"A Auto Tint Perth",
    "wof:placetype":"venue"
},
  "geometry": {"coordinates":[115.88661999999999,-32.04248],"type":"Point"}
}