{
  "type": "Feature",
  "properties": {
    "iso:country":"AU",
    "sg:address":"84 McCoy St",
    "sg:city":"Myaree",
    "sg:classifiers":[
        {
            "category":"Building & Trades",
            "subcategory":"Pest Control",
            "type":"Services"
        }
    ],
    "sg:phone":"+61 8 9330 6587",
    "sg:postcode":"6154",
    "sg:province":"WA",
    "sg:tags":[
        "equipment",
        "abattoir",
        "machinery"
    ],
    "wof:name":"Jupiter Steel Fabrications",
    "wof:placetype":"venue"
},
  "geometry": {"coordinates":[115.821358,-32.043362],"type":"Point"}
}