{
  "type": "Feature",
  "properties": {
    "addr:full":"3 Walter St Moorabbin VIC 3189",
    "addr:housenumber":"3",
    "addr:postcode":"3189",
    "addr:street":"Walter St",
    "iso:country":"AU",
    "sg:address":"3 Walter St",
    "sg:city":"Moorabbin",
    "sg:classifiers":[
        {
            "category":"Home & Garden",
            "subcategory":"Hardware",
            "type":"Retail Goods"
        }
    ],
    "sg:phone":"+61 3 9555 0848",
    "sg:postcode":"3189",
    "sg:province":"VIC",
    "sg:tags":[
        "trolley",
        "truck",
        "hand"
    ],
    "wof:name":"Rapini",
    "wof:placetype":"venue"
},
  "geometry": {"coordinates":[145.064987183,-37.9396591187],"type":"Point"}
}