{
  "type": "Feature",
  "properties": {
    "addr:full":"St Lukes Church Hall Heyden St Mosman NSW 2088",
    "addr:postcode":"2088",
    "addr:street":"Heyden St",
    "iso:country":"AU",
    "sg:address":"St Lukes Church Hall Heyden St",
    "sg:city":"Mosman",
    "sg:classifiers":[
        {
            "category":"Recreation",
            "type":"Entertainment"
        }
    ],
    "sg:phone":"+61 2 9144 7951",
    "sg:postcode":"2088",
    "sg:province":"NSW",
    "sg:tags":[
        "children's",
        "play",
        "programme"
    ],
    "wof:name":"GymbaROO",
    "wof:placetype":"venue"
},
  "geometry": {"coordinates":[151.24026489299999,-33.8244895935],"type":"Point"}
}