{
  "type": "Feature",
  "properties": {
    "addr:full":"PO Box 870 Narrabeen NSW 2101",
    "addr:postcode":"2101",
    "iso:country":"AU",
    "sg:address":"PO Box 870",
    "sg:city":"Narrabeen",
    "sg:classifiers":[
        {
            "category":"Building & Trades",
            "subcategory":"Landscaping Services",
            "type":"Services"
        }
    ],
    "sg:phone":"+61 2 9944 8222",
    "sg:postcode":"2101",
    "sg:province":"NSW",
    "sg:tags":[
        "inspection"
    ],
    "wof:name":"The Certification Group Pty Ltd",
    "wof:placetype":"venue"
},
  "geometry": {"coordinates":[151.298416,-33.720211],"type":"Point"}
}