{
  "type": "Feature",
  "properties": {
    "iso:country":"AU",
    "sg:address":"32 Jubille Ave",
    "sg:city":"Carlton",
    "sg:classifiers":[
        {
            "category":"Personal",
            "subcategory":"Beauty Salon",
            "type":"Services"
        }
    ],
    "sg:phone":"+61 2 9588 5262",
    "sg:postcode":"2218",
    "sg:province":"NSW",
    "sg:tags":[
        "hairdresser"
    ],
    "wof:name":"Joanne Michaels Hair Design",
    "wof:placetype":"venue"
},
  "geometry": {"coordinates":[151.126648,-33.97084],"type":"Point"}
}