{
  "type": "Feature",
  "properties": {
    "addr:full":"30/ 100 Moralla Ave Runaway Bay QLD 4216",
    "addr:housenumber":"30 / 100",
    "addr:postcode":"4216",
    "addr:street":"Moralla Ave",
    "iso:country":"AU",
    "sg:address":"30/ 100 Moralla Ave",
    "sg:city":"Runaway Bay",
    "sg:classifiers":[
        {
            "category":"Real Estate",
            "subcategory":"Real Estate Services",
            "type":"Services"
        }
    ],
    "sg:phone":"+61 438 730 634",
    "sg:postcode":"4216",
    "sg:province":"QLD",
    "sg:tags":[
        "consultant",
        "property"
    ],
    "wof:name":"RJM Consultants PTY LTD",
    "wof:placetype":"venue"
},
  "geometry": {"coordinates":[153.39869689899999,-27.9212703705],"type":"Point"}
}