{
  "type": "Feature",
  "properties": {
    "addr:full":"2 / 1a Neutron Pl Rowville VIC 3178",
    "addr:housenumber":"/ 1a",
    "addr:postcode":"3178",
    "addr:street":"Neutron Pl",
    "iso:country":"AU",
    "sg:address":"2 / 1a Neutron Pl",
    "sg:city":"Rowville",
    "sg:classifiers":[
        {
            "category":"Manufacturing",
            "subcategory":"Metals",
            "type":"Manufacturing & Wholesale Goods"
        }
    ],
    "sg:phone":"+61 3 9763 2366",
    "sg:postcode":"3178",
    "sg:province":"VIC",
    "sg:tags":[
        "fabricator",
        "aluminium"
    ],
    "wof:name":"Alchemy Australia Pty Ltd",
    "wof:placetype":"venue"
},
  "geometry": {"coordinates":[145.24707031200001,-37.9058265686],"type":"Point"}
}