{
  "type": "Feature",
  "properties": {
    "iso:country":"AU",
    "sg:address":"98 Newton Rd",
    "sg:city":"Campbelltown",
    "sg:classifiers":[
        {
            "category":"Travel",
            "subcategory":"Hostel",
            "type":"Entertainment"
        }
    ],
    "sg:phone":"+61 8 8336 1101",
    "sg:postcode":"5074",
    "sg:province":"SA",
    "sg:tags":[
        "home"
    ],
    "wof:name":"Bellara Village",
    "wof:placetype":"venue"
},
  "geometry": {"coordinates":[138.67149352999999,-34.8767127991],"type":"Point"}
}