{
  "type": "Feature",
  "properties": {
    "addr:full":"34 Summerlea Rd Mt Dandenong VIC 3767",
    "addr:housenumber":"34",
    "addr:postcode":"3767",
    "addr:street":"Summerlea Rd",
    "iso:country":"AU",
    "sg:address":"34 Summerlea Rd",
    "sg:city":"Mt Dandenong",
    "sg:classifiers":[
        {
            "category":"Professional",
            "subcategory":"Art Services",
            "type":"Services"
        }
    ],
    "sg:phone":"+61 3 9751 2022",
    "sg:postcode":"3767",
    "sg:province":"VIC",
    "sg:tags":[
        "interior",
        "designer"
    ],
    "wof:name":"E.D.M. Design & Atelier Pty Ltd",
    "wof:placetype":"venue"
},
  "geometry": {"coordinates":[145.35737609899999,-37.8430290222],"type":"Point"}
}