{
  "type": "Feature",
  "properties": {
    "iso:country":"AU",
    "sg:address":"5a/ 406 Bilsen Rd",
    "sg:city":"Geebung",
    "sg:classifiers":[
        {
            "category":"Wholesale",
            "subcategory":"Home Furnishings",
            "type":"Manufacturing & Wholesale Goods"
        }
    ],
    "sg:phone":"+61 7 3865 4522",
    "sg:postcode":"4034",
    "sg:province":"QLD",
    "sg:tags":[
        "wholesaler",
        "bedding",
        "mfrs",
        "bed"
    ],
    "wof:name":"A.H. Beard Pty Ltd",
    "wof:placetype":"venue"
},
  "geometry": {"coordinates":[153.055756,-27.371794],"type":"Point"}
}