{
  "type": "Feature",
  "properties": {
    "addr:full":"Unit 5, 18b Little St Camden NSW 2570",
    "addr:housenumber":"18b",
    "addr:postcode":"2570",
    "addr:street":"Little St",
    "iso:country":"AU",
    "sg:address":"Unit 5, 18b Little St",
    "sg:city":"Camden",
    "sg:classifiers":[
        {
            "category":"Professional",
            "subcategory":"Printing & Photocopies",
            "type":"Services"
        }
    ],
    "sg:phone":"+61 2 4655 5355",
    "sg:postcode":"2570",
    "sg:province":"NSW",
    "sg:tags":[
        "textile",
        "clothing"
    ],
    "wof:name":"Flash Signs & Promotions",
    "wof:placetype":"venue"
},
  "geometry": {"coordinates":[150.69261169399999,-34.0609054565],"type":"Point"}
}