{
  "type": "Feature",
  "properties": {
    "addr:full":"10 Albury St Wagga Wagga NSW 2650",
    "addr:housenumber":"10",
    "addr:postcode":"2650",
    "addr:street":"Albury St",
    "iso:country":"AU",
    "sg:address":"10 Albury St",
    "sg:city":"Wagga Wagga",
    "sg:classifiers":[
        {
            "category":"Personal",
            "subcategory":"Massage",
            "type":"Services"
        }
    ],
    "sg:phone":"+61 2 6921 3161",
    "sg:postcode":"2650",
    "sg:province":"NSW",
    "sg:tags":[
        "therapy"
    ],
    "wof:name":"Doyle Sandra & Tony",
    "wof:placetype":"venue"
},
  "geometry": {"coordinates":[147.35731506400001,-35.1117744446],"type":"Point"}
}