{
  "type": "Feature",
  "properties": {
    "addr:full":"\"Craiglee\" Mintaro Rd Manoora SA 5414",
    "addr:postcode":"5414",
    "addr:street":"Mintaro Rd",
    "iso:country":"AU",
    "sg:address":"\"Craiglee\" Mintaro Rd",
    "sg:city":"Manoora",
    "sg:classifiers":[
        {
            "category":"Farming",
            "subcategory":"Farm",
            "type":"Manufacturing & Wholesale Goods"
        }
    ],
    "sg:phone":"+61 8 8848 4241",
    "sg:postcode":"5414",
    "sg:province":"SA",
    "sg:tags":[
        "farmer"
    ],
    "wof:name":"Craiglee Proprietors",
    "wof:placetype":"venue"
},
  "geometry": {"coordinates":[138.799102783,-33.9931983948],"type":"Point"}
}