{
  "type": "Feature",
  "properties": {
    "addr:full":"Harper St Caversham WA 6055",
    "addr:postcode":"6055",
    "addr:street":"Harper St",
    "iso:country":"AU",
    "sg:address":"Harper St",
    "sg:city":"Caversham",
    "sg:classifiers":[
        {
            "category":"Professional",
            "type":"Services"
        }
    ],
    "sg:phone":"+61 8 9261 9800",
    "sg:postcode":"6055",
    "sg:province":"WA",
    "sg:tags":[
        "transport"
    ],
    "wof:name":"Temple Freights WA",
    "wof:placetype":"venue"
},
  "geometry": {"coordinates":[115.97154999999999,-31.883018],"type":"Point"}
}