{
  "type": "Feature",
  "properties": {
    "iso:country":"AU",
    "sg:address":"3 Shields Crs",
    "sg:city":"Booragoon",
    "sg:classifiers":[
        {
            "category":"Shopping",
            "subcategory":"Crafts & Fabrics",
            "type":"Retail Goods"
        }
    ],
    "sg:phone":"+61 8 9330 8990",
    "sg:postcode":"6154",
    "sg:province":"WA",
    "sg:tags":[
        "synthetic",
        "canvas",
        "product"
    ],
    "wof:name":"Fiesta Canvas",
    "wof:placetype":"venue"
},
  "geometry": {"coordinates":[115.832329,-32.036018],"type":"Point"}
}