{
  "type": "Feature",
  "properties": {
    "iso:country":"AU",
    "sg:address":"3 Nelson St",
    "sg:city":"Coburg",
    "sg:classifiers":[
        {
            "category":"Manufacturing",
            "subcategory":"Motor Vehicles & Parts",
            "type":"Manufacturing & Wholesale Goods"
        }
    ],
    "sg:phone":"+61 3 9354 6274",
    "sg:postcode":"3058",
    "sg:province":"VIC",
    "sg:tags":[
        "wholesaler",
        "cycle",
        "mfrs",
        "accessory"
    ],
    "wof:name":"Racebike Developments",
    "wof:placetype":"venue"
},
  "geometry": {"coordinates":[144.95880126899999,-37.743976593],"type":"Point"}
}