{
  "type": "Feature",
  "properties": {
    "addr:full":"Shop 16, Somerville Plaza 17 Eramosa Rd West Somerville VIC 3912",
    "addr:housenumber":"shop 16;17",
    "addr:postcode":"3912",
    "addr:street":"Somerville Plaza;Eramosa Rd",
    "iso:country":"AU",
    "sg:address":"Shop 16, Somerville Plaza 17 Eramosa Rd West",
    "sg:city":"Somerville",
    "sg:classifiers":[
        {
            "category":"Autos & Motor Vehicles",
            "subcategory":"Auto Supplies",
            "type":"Retail Goods"
        }
    ],
    "sg:phone":"+61 3 5977 9384",
    "sg:postcode":"3912",
    "sg:province":"VIC",
    "sg:tags":[
        "accessory"
    ],
    "wof:name":"Autopro",
    "wof:placetype":"venue"
},
  "geometry": {"coordinates":[145.172897339,-38.223400116],"type":"Point"}
}