{
  "type": "Feature",
  "properties": {
    "addr:full":"Richard St Bourke NSW 2840",
    "addr:postcode":"2840",
    "addr:street":"Richard St",
    "iso:country":"AU",
    "sg:address":"Richard St",
    "sg:city":"Bourke",
    "sg:classifiers":[
        {
            "category":"Travel",
            "subcategory":"Hotels & Motels",
            "type":"Entertainment"
        }
    ],
    "sg:phone":"+61 2 6872 2151",
    "sg:postcode":"2840",
    "sg:province":"NSW",
    "sg:tags":[
        "accommodation"
    ],
    "wof:name":"Central Australian Hotel",
    "wof:placetype":"venue"
},
  "geometry": {"coordinates":[145.937805,-30.088543],"type":"Point"}
}