{
  "type": "Feature",
  "properties": {
    "iso:country":"AU",
    "sg:address":"32 Vestan Drv",
    "sg:city":"Morwell",
    "sg:classifiers":[
        {
            "category":"Retail",
            "subcategory":"Car Wash",
            "type":"Services"
        }
    ],
    "sg:phone":"+61 3 5134 5760",
    "sg:postcode":"3840",
    "sg:province":"VIC",
    "sg:tags":[
        "truck",
        "cleaning"
    ],
    "wof:name":"Jumbo Car Wash",
    "wof:placetype":"venue"
},
  "geometry": {"coordinates":[146.43511962900001,-38.234462738],"type":"Point"}
}