{
  "type": "Feature",
  "properties": {
    "addr:full":"Lot 120 Mooligunn Rd Karratha WA 6714",
    "addr:postcode":"6714",
    "addr:street":"Mooligunn Rd",
    "iso:country":"AU",
    "sg:address":"Lot 120 Mooligunn Rd",
    "sg:city":"Karratha",
    "sg:classifiers":[
        {
            "category":"Wholesale",
            "subcategory":"Machinery & Supplies",
            "type":"Manufacturing & Wholesale Goods"
        }
    ],
    "sg:phone":"+61 8 9144 4577",
    "sg:postcode":"6714",
    "sg:province":"WA",
    "sg:tags":[
        "rigging",
        "equipment",
        "hoisting"
    ],
    "wof:name":"Bullivants Sling-Rig",
    "wof:placetype":"venue"
},
  "geometry": {"coordinates":[116.862258911,-20.7657222748],"type":"Point"}
}