{
  "type": "Feature",
  "properties": {
    "addr:full":"Level 1/ 96 Barrier St Fyshwick ACT 2609",
    "addr:housenumber":"/ 96",
    "addr:postcode":"2609",
    "addr:street":"Barrier St",
    "iso:country":"AU",
    "sg:address":"Level 1/ 96 Barrier St",
    "sg:city":"Fyshwick",
    "sg:classifiers":[
        {
            "category":"Professional",
            "subcategory":"Computer Services",
            "type":"Services"
        }
    ],
    "sg:phone":"+61 2 6280 6244",
    "sg:postcode":"2609",
    "sg:province":"ACT",
    "sg:tags":[
        "consultant",
        "system"
    ],
    "wof:name":"DPM Consulting",
    "wof:placetype":"venue"
},
  "geometry": {"coordinates":[149.167892456,-35.3261451721],"type":"Point"}
}