{
  "type": "Feature",
  "properties": {
    "iso:country":"AU",
    "sg:address":"170a Wardell Rd",
    "sg:city":"Dulwich Hill",
    "sg:classifiers":[
        {
            "category":"Health Services",
            "subcategory":"Doctor",
            "type":"Services"
        }
    ],
    "sg:phone":"+61 2 9559 2511",
    "sg:postcode":"2203",
    "sg:province":"NSW",
    "sg:tags":[
        "medical",
        "practitioner"
    ],
    "wof:name":"Halasz Elisabeth Dr",
    "wof:placetype":"venue"
},
  "geometry": {"coordinates":[151.144653,-33.907345],"type":"Point"}
}