{
  "type": "Feature",
  "properties": {
    "iso:country":"AU",
    "sg:address":"U 4B/ 176 Main St",
    "sg:city":"Osborne Park",
    "sg:classifiers":[
        {
            "category":"Professional",
            "subcategory":"Accounting & Tax Preparation",
            "type":"Services"
        }
    ],
    "sg:phone":"+61 8 9349 5705",
    "sg:postcode":"6017",
    "sg:province":"WA",
    "sg:tags":[
        "accountant",
        "auditor"
    ],
    "wof:name":"Joseph Catenacci Pty Ltd",
    "wof:placetype":"venue"
},
  "geometry": {"coordinates":[115.828422546,-31.8994445801],"type":"Point"}
}