{
  "type": "Feature",
  "properties": {
    "iso:country":"AU",
    "sg:address":"Anzac Ave",
    "sg:city":"Kippa-Ring",
    "sg:classifiers":[
        {
            "category":"Shopping",
            "subcategory":"Clothing, Apparel, & Fashions",
            "type":"Retail Goods"
        }
    ],
    "sg:phone":"+61 7 3883 1677",
    "sg:postcode":"4021",
    "sg:province":"QLD",
    "sg:tags":[
        "menswear"
    ],
    "wof:name":"Lowes",
    "wof:placetype":"venue"
},
  "geometry": {"coordinates":[153.087357,-27.226927],"type":"Point"}
}