{
  "type": "Feature",
  "properties": {
    "addr:full":"80 Ocean St Victor Harbor SA 5211",
    "addr:housenumber":"80",
    "addr:postcode":"5211",
    "addr:street":"Ocean St",
    "iso:country":"AU",
    "sg:address":"80 Ocean St",
    "sg:city":"Victor Harbor",
    "sg:classifiers":[
        {
            "category":"Real Estate",
            "subcategory":"Real Estate Agent",
            "type":"Services"
        }
    ],
    "sg:phone":"+61 8 8552 6999",
    "sg:postcode":"5211",
    "sg:province":"SA",
    "wof:name":"McGees National Property Consultants",
    "wof:placetype":"venue"
},
  "geometry": {"coordinates":[138.62298584000001,-35.5520248413],"type":"Point"}
}