{
  "type": "Feature",
  "properties": {
    "addr:full":"Factory 2, 245 Holt Pde Thomastown VIC 3074",
    "addr:housenumber":"245",
    "addr:postcode":"3074",
    "addr:street":"Holt Pde",
    "iso:country":"AU",
    "sg:address":"Factory 2, 245 Holt Pde",
    "sg:city":"Thomastown",
    "sg:classifiers":[
        {
            "category":"Building & Trades",
            "subcategory":"Electrical",
            "type":"Services"
        }
    ],
    "sg:phone":"+61 3 9465 8744",
    "sg:postcode":"3074",
    "sg:province":"VIC",
    "sg:tags":[
        "repair",
        "generator",
        "electric",
        "motor"
    ],
    "wof:name":"Renegade Rewind",
    "wof:placetype":"venue"
},
  "geometry": {"coordinates":[145.02926635700001,-37.6961021423],"type":"Point"}
}