{
  "type": "Feature",
  "properties": {
    "addr:full":"2 Pandora Crs Greystanes NSW 2145",
    "addr:housenumber":"2",
    "addr:postcode":"2145",
    "addr:street":"Pandora Crs",
    "iso:country":"AU",
    "sg:address":"2 Pandora Crs",
    "sg:city":"Greystanes",
    "sg:classifiers":[
        {
            "category":"Manufacturing",
            "subcategory":"Food",
            "type":"Manufacturing & Wholesale Goods"
        }
    ],
    "sg:phone":"+61 1300 722 144",
    "sg:postcode":"2145",
    "sg:province":"NSW",
    "sg:tags":[
        "function",
        "catering"
    ],
    "wof:name":"A fingerfoods.com.au",
    "wof:placetype":"venue"
},
  "geometry": {"coordinates":[150.94769287099999,-33.8190307617],"type":"Point"}
}