{
  "type": "Feature",
  "properties": {
    "addr:full":"PO Box 3068 Bracken Ridge QLD 4017",
    "addr:postcode":"4017",
    "iso:country":"AU",
    "sg:address":"PO Box 3068",
    "sg:city":"Bracken Ridge",
    "sg:classifiers":[
        {
            "category":"Organizations",
            "subcategory":"Membership Organization",
            "type":"Services"
        }
    ],
    "sg:phone":"+61 7 3833 4376",
    "sg:postcode":"4017",
    "sg:province":"QLD",
    "sg:tags":[
        "support",
        "health",
        "organisation"
    ],
    "wof:name":"Lymphoedema Association Of Queensland Inc",
    "wof:placetype":"venue"
},
  "geometry": {"coordinates":[153.026245117,-27.3311405182],"type":"Point"}
}