{
  "type": "Feature",
  "properties": {
    "iso:country":"AU",
    "sg:address":"Elizabeth Arcade, 99 Elizabeth St",
    "sg:city":"Brisbane",
    "sg:classifiers":[
        {
            "category":"Personal",
            "subcategory":"Beauty Salon",
            "type":"Services"
        }
    ],
    "sg:phone":"+61 1300 791 699",
    "sg:postcode":"4000",
    "sg:province":"QLD",
    "sg:tags":[
        "supply",
        "artist",
        "make-up"
    ],
    "wof:name":"Napoleon Perdis Academy",
    "wof:placetype":"venue"
},
  "geometry": {"coordinates":[153.025558472,-27.4709091187],"type":"Point"}
}