{
  "type": "Feature",
  "properties": {
    "addr:full":"242 Marius St Tamworth NSW 2340",
    "addr:housenumber":"242",
    "addr:postcode":"2340",
    "addr:street":"Marius St",
    "iso:country":"AU",
    "sg:address":"242 Marius St",
    "sg:city":"Tamworth",
    "sg:classifiers":[
        {
            "category":"Building & Trades",
            "subcategory":"Landscaping Services",
            "type":"Services"
        }
    ],
    "sg:phone":"+61 2 6766 4441",
    "sg:postcode":"2340",
    "sg:province":"NSW",
    "sg:tags":[
        "consultant"
    ],
    "wof:name":"David Cohen Consulting Engineers Pty Ltd",
    "wof:placetype":"venue"
},
  "geometry": {"coordinates":[150.935180664,-31.0926952362],"type":"Point"}
}