{
  "type": "Feature",
  "properties": {
    "iso:country":"AU",
    "sg:address":"St",
    "sg:city":"Mark&#039;s House Chermside",
    "sg:classifiers":[
        {
            "category":"Health Services",
            "subcategory":"Nursing And Care Facility",
            "type":"Services"
        }
    ],
    "sg:phone":"+61 7 3621 4635",
    "sg:postcode":"4032",
    "sg:province":"QLD",
    "sg:tags":[
        "home"
    ],
    "wof:name":"Wesley Mission Brisbane",
    "wof:placetype":"venue"
},
  "geometry": {"coordinates":[153.033936,-27.38636],"type":"Point"}
}