{
  "type": "Feature",
  "properties": {
    "addr:full":"Shop H4 Peninsula Fair 272 Anzac Ave Kippa-Ring QLD 4021",
    "addr:housenumber":"h4;272",
    "addr:postcode":"4021",
    "addr:street":"Peninsula Fair;Anzac Ave",
    "iso:country":"AU",
    "sg:address":"Shop H4 Peninsula Fair 272 Anzac Ave",
    "sg:city":"Kippa-Ring",
    "sg:classifiers":[
        {
            "category":"Cafe",
            "type":"Food & Drink"
        }
    ],
    "sg:phone":"+61 7 3889 5111",
    "sg:postcode":"4021",
    "sg:province":"QLD",
    "wof:name":"Starbucks Coffee Company (Australia) Pty Ltd",
    "wof:placetype":"venue"
},
  "geometry": {"coordinates":[153.087357,-27.226927],"type":"Point"}
}