{
  "type": "Feature",
  "properties": {
    "addr:full":"50 Pacific Hwy Wyong NSW 2259",
    "addr:housenumber":"50",
    "addr:postcode":"2259",
    "addr:street":"Pacific Hwy",
    "iso:country":"AU",
    "sg:address":"50 Pacific Hwy",
    "sg:city":"Wyong",
    "sg:classifiers":[
        {
            "category":"Fast Food",
            "type":"Food & Drink"
        }
    ],
    "sg:phone":"+61 2 4352 2191",
    "sg:postcode":"2259",
    "sg:province":"NSW",
    "sg:tags":[
        "away",
        "take"
    ],
    "wof:name":"Wan Wah Chinese Restaurant",
    "wof:placetype":"venue"
},
  "geometry": {"coordinates":[151.42427063,-33.2860450745],"type":"Point"}
}