{
  "type": "Feature",
  "properties": {
    "addr:full":"Unit 2, 112 Compton Rd Woodridge QLD 4114",
    "addr:housenumber":"112",
    "addr:postcode":"4114",
    "addr:street":"Compton Rd",
    "iso:country":"AU",
    "sg:address":"Unit 2, 112 Compton Rd",
    "sg:city":"Woodridge",
    "sg:classifiers":[
        {
            "category":"Wholesale",
            "subcategory":"Metals & Minerals",
            "type":"Manufacturing & Wholesale Goods"
        }
    ],
    "sg:phone":"+61 7 3299 2971",
    "sg:postcode":"4114",
    "sg:province":"QLD",
    "sg:tags":[
        "steel",
        "stainless",
        "product",
        "equipment"
    ],
    "wof:name":"T & H Sheetmetal Pty Ltd",
    "wof:placetype":"venue"
},
  "geometry": {"coordinates":[153.095703125,-27.6793766022],"type":"Point"}
}