{
  "type": "Feature",
  "properties": {
    "addr:full":"Cnr Calam & Compton Rds Sunnybank Hills QLD 4109",
    "addr:postcode":"4109",
    "addr:street":"Cnr",
    "iso:country":"AU",
    "sg:address":"Cnr Calam & Compton Rds",
    "sg:city":"Sunnybank Hills",
    "sg:classifiers":[
        {
            "category":"Government",
            "subcategory":"Post Office",
            "type":"Public Place"
        }
    ],
    "sg:phone":"+61 13 13 18",
    "sg:postcode":"4109",
    "sg:province":"QLD",
    "sg:tags":[
        "postal"
    ],
    "wof:name":"Sunnybank Hills Post Office",
    "wof:placetype":"venue"
},
  "geometry": {"coordinates":[153.055587769,-27.6049785614],"type":"Point"}
}