{
  "type": "Feature",
  "properties": {
    "addr:full":"470 Eleventh St Mildura VIC 3500",
    "addr:housenumber":"470",
    "addr:postcode":"3500",
    "addr:street":"Eleventh St",
    "iso:country":"AU",
    "sg:address":"470 Eleventh St",
    "sg:city":"Mildura",
    "sg:classifiers":[
        {
            "category":"Building & Trades",
            "subcategory":"Electrical",
            "type":"Services"
        }
    ],
    "sg:phone":"+61 3 5023 5829",
    "sg:postcode":"3500",
    "sg:province":"VIC",
    "sg:tags":[
        "pottery",
        "porcelain",
        "teacher",
        "ceramics"
    ],
    "wof:name":"Bette Lewis Ceramics",
    "wof:placetype":"venue"
},
  "geometry": {"coordinates":[142.13746643100001,-34.1726608276],"type":"Point"}
}