{
  "type": "Feature",
  "properties": {
    "addr:full":"29 High St Arno Bay SA 5603",
    "addr:housenumber":"29",
    "addr:postcode":"5603",
    "addr:street":"High St",
    "iso:country":"AU",
    "sg:address":"29 High St",
    "sg:city":"Arno Bay",
    "sg:classifiers":[
        {
            "category":"Retail",
            "subcategory":"Repair Shop",
            "type":"Services"
        }
    ],
    "sg:phone":"+61 8 8628 0124",
    "sg:postcode":"5603",
    "sg:province":"SA",
    "sg:tags":[
        "upholsterer"
    ],
    "wof:name":"Arno Bay Tarp & Upholstery",
    "wof:placetype":"venue"
},
  "geometry": {"coordinates":[136.56933599999999,-33.909569],"type":"Point"}
}