{
  "type": "Feature",
  "properties": {
    "addr:full":"132 Jersey Rd Woollahra NSW 2025",
    "addr:housenumber":"132",
    "addr:postcode":"2025",
    "addr:street":"Jersey Rd",
    "iso:country":"AU",
    "sg:address":"132 Jersey Rd",
    "sg:city":"Woollahra",
    "sg:classifiers":[
        {
            "category":"Home & Garden",
            "subcategory":"Carpets & Floor Coverings",
            "type":"Retail Goods"
        }
    ],
    "sg:phone":"+61 2 9327 7410",
    "sg:postcode":"2025",
    "sg:province":"NSW",
    "sg:tags":[
        "double",
        "window",
        "glazed"
    ],
    "sg:website":"http://www.soundblock.com.au",
    "wof:name":"Soundblock Solutions",
    "wof:placetype":"venue"
},
  "geometry": {"coordinates":[151.23568725600001,-33.887172699],"type":"Point"}
}