{
  "type": "Feature",
  "properties": {
    "iso:country":"AU",
    "sg:address":"126a Canterbury Rd",
    "sg:city":"Heathmont",
    "sg:classifiers":[
        {
            "category":"Cafe",
            "type":"Food & Drink"
        }
    ],
    "sg:phone":"+61 3 9720 3499",
    "sg:postcode":"3135",
    "sg:province":"VIC",
    "wof:name":"Purple Onion The",
    "wof:placetype":"venue"
},
  "geometry": {"coordinates":[145.24647522000001,-37.8285903931],"type":"Point"}
}