{
  "type": "Feature",
  "properties": {
    "addr:full":"2 Edden St West Wallsend NSW 2286",
    "addr:housenumber":"2",
    "addr:postcode":"2286",
    "addr:street":"Edden St",
    "iso:country":"AU",
    "sg:address":"2 Edden St",
    "sg:city":"West Wallsend",
    "sg:classifiers":[
        {
            "category":"Commercial Area",
            "type":"Public Place"
        }
    ],
    "sg:phone":"+61 2 4953 2653",
    "sg:postcode":"2286",
    "sg:province":"NSW",
    "sg:tags":[
        "heavy",
        "carrier"
    ],
    "wof:name":"Petersen B R",
    "wof:placetype":"venue"
},
  "geometry": {"coordinates":[151.58714294399999,-32.906337738],"type":"Point"}
}