{
  "type": "Feature",
  "properties": {
    "iso:country":"AU",
    "sg:address":"3 Keating St",
    "sg:city":"Lidcombe",
    "sg:classifiers":[
        {
            "category":"Professional",
            "subcategory":"Management & Consulting",
            "type":"Services"
        }
    ],
    "sg:phone":"+61 2 9643 3638",
    "sg:postcode":"2141",
    "sg:province":"NSW",
    "sg:tags":[
        "consultant",
        "educational"
    ],
    "wof:name":"Inner Western Sydney Business education Partnership",
    "wof:placetype":"venue"
},
  "geometry": {"coordinates":[151.045944214,-33.8598251343],"type":"Point"}
}