{
  "type": "Feature",
  "properties": {
    "addr:full":"96 Bloomfield St Cleveland QLD 4163",
    "addr:housenumber":"96",
    "addr:postcode":"4163",
    "addr:street":"Bloomfield St",
    "iso:country":"AU",
    "sg:address":"96 Bloomfield St",
    "sg:city":"Cleveland",
    "sg:classifiers":[
        {
            "category":"Manufacturing",
            "subcategory":"Furniture",
            "type":"Manufacturing & Wholesale Goods"
        }
    ],
    "sg:phone":"+61 7 3286 4222",
    "sg:postcode":"4163",
    "sg:province":"QLD",
    "sg:tags":[
        "builder",
        "designer",
        "custom"
    ],
    "wof:name":"Decorators Emporium",
    "wof:placetype":"venue"
},
  "geometry": {"coordinates":[153.26719665499999,-27.5272655487],"type":"Point"}
}