{
  "type": "Feature",
  "properties": {
    "iso:country":"AU",
    "sg:address":"Bass Hwy",
    "sg:city":"Bass",
    "sg:classifiers":[
        {
            "category":"Restaurant",
            "type":"Food & Drink"
        }
    ],
    "sg:phone":"+61 3 5678 2367",
    "sg:postcode":"3991",
    "sg:province":"VIC",
    "wof:name":"Choo Choo's Bass",
    "wof:placetype":"venue"
},
  "geometry": {"coordinates":[145.467392,-38.480789],"type":"Point"}
}