{
  "type": "Feature",
  "properties": {
    "iso:country":"AU",
    "sg:address":"1387 Gympie Rd",
    "sg:city":"Aspley",
    "sg:classifiers":[
        {
            "category":"Autos & Motor Vehicles",
            "subcategory":"Automobile Sales",
            "type":"Retail Goods"
        }
    ],
    "sg:phone":"+61 7 3862 9899",
    "sg:postcode":"4034",
    "sg:province":"QLD",
    "sg:tags":[
        "car",
        "used"
    ],
    "wof:name":"Phoenix Prestige Cars",
    "wof:placetype":"venue"
},
  "geometry": {"coordinates":[153.017334,-27.361164],"type":"Point"}
}