{
  "type": "Feature",
  "properties": {
    "addr:full":"510 Nepean Hwy Frankston VIC 3199",
    "addr:housenumber":"510",
    "addr:postcode":"3199",
    "addr:street":"Nepean Hwy",
    "iso:country":"AU",
    "sg:address":"510 Nepean Hwy",
    "sg:city":"Frankston",
    "sg:classifiers":[
        {
            "category":"Travel",
            "subcategory":"Hotels & Motels",
            "type":"Entertainment"
        }
    ],
    "sg:phone":"+61 3 9783 7255",
    "sg:postcode":"3199",
    "sg:province":"VIC",
    "sg:tags":[
        "pub"
    ],
    "wof:name":"Daveys Hotel",
    "wof:placetype":"venue"
},
  "geometry": {"coordinates":[145.118743897,-38.1461410522],"type":"Point"}
}