{
  "type": "Feature",
  "properties": {
    "iso:country":"AU",
    "sg:address":"163 Adelaide St",
    "sg:city":"Maryborough",
    "sg:classifiers":[
        {
            "category":"Shopping",
            "subcategory":"Jewelry",
            "type":"Retail Goods"
        }
    ],
    "sg:phone":"+61 7 4121 3373",
    "sg:postcode":"4650",
    "sg:province":"QLD",
    "sg:tags":[
        "jeweller"
    ],
    "wof:name":"Gillhespy T.J.",
    "wof:placetype":"venue"
},
  "geometry": {"coordinates":[152.700989,-25.539587],"type":"Point"}
}