{
  "type": "Feature",
  "properties": {
    "iso:country":"AU",
    "sg:address":"Burton St",
    "sg:city":"Vincentia",
    "sg:classifiers":[
        {
            "category":"Food & Beverages",
            "subcategory":"Liquor & Beverages",
            "type":"Retail Goods"
        }
    ],
    "sg:phone":"+61 2 4441 5353",
    "sg:postcode":"2540",
    "sg:province":"NSW",
    "sg:tags":[
        "store"
    ],
    "wof:name":"Vincentia Cellars",
    "wof:placetype":"venue"
},
  "geometry": {"coordinates":[150.67523193400001,-35.0698394775],"type":"Point"}
}