{
  "type": "Feature",
  "properties": {
    "addr:full":"Unit 8, 178 Station Rd Burpengary QLD 4505",
    "addr:housenumber":"178",
    "addr:postcode":"4505",
    "addr:street":"Station Rd",
    "iso:country":"AU",
    "sg:address":"Unit 8, 178 Station Rd",
    "sg:city":"Burpengary",
    "sg:classifiers":[
        {
            "category":"Manufacturing",
            "subcategory":"Rubber & Plastics",
            "type":"Manufacturing & Wholesale Goods"
        }
    ],
    "sg:phone":"+61 7 3888 3333",
    "sg:postcode":"4505",
    "sg:province":"QLD",
    "sg:tags":[
        "wholesaler",
        "product",
        "mfrs"
    ],
    "wof:name":"Arunta Plastics Pty Ltd",
    "wof:placetype":"venue"
},
  "geometry": {"coordinates":[152.97601318400001,-27.1537952423],"type":"Point"}
}