{
  "type": "Feature",
  "properties": {
    "addr:full":"64 Bland St Ashfield NSW 2131",
    "addr:housenumber":"64",
    "addr:postcode":"2131",
    "addr:street":"Bland St",
    "iso:country":"AU",
    "sg:address":"64 Bland St",
    "sg:city":"Ashfield",
    "sg:classifiers":[
        {
            "category":"Education",
            "subcategory":"Kindergarten",
            "type":"Public Place"
        }
    ],
    "sg:phone":"+61 2 9797 6392",
    "sg:postcode":"2131",
    "sg:province":"NSW",
    "sg:tags":[
        "pre-schools"
    ],
    "wof:name":"St John's Pre-School Ashfield Inc",
    "wof:placetype":"venue"
},
  "geometry": {"coordinates":[151.12762451200001,-33.8825035095],"type":"Point"}
}