{
  "type": "Feature",
  "properties": {
    "addr:full":"138 Wood St Mackay QLD 4740",
    "addr:housenumber":"138",
    "addr:postcode":"4740",
    "addr:street":"Wood St",
    "iso:country":"AU",
    "sg:address":"138 Wood St",
    "sg:city":"Mackay",
    "sg:classifiers":[
        {
            "category":"Utilities",
            "subcategory":"Electric",
            "type":"Services"
        }
    ],
    "sg:phone":"+61 7 4953 1309",
    "sg:postcode":"4740",
    "sg:province":"QLD",
    "sg:tags":[
        "electrical",
        "contractor"
    ],
    "wof:name":"G & L Electrical",
    "wof:placetype":"venue"
},
  "geometry": {"coordinates":[149.18504300000001,-21.145887],"type":"Point"}
}