{
  "type": "Feature",
  "properties": {
    "iso:country":"AU",
    "sg:address":"39 Claremont Ave",
    "sg:city":"Adamstown",
    "sg:classifiers":[
        {
            "category":"Building & Trades",
            "subcategory":"Pest Control",
            "type":"Services"
        }
    ],
    "sg:phone":"+61 2 4952 5301",
    "sg:postcode":"2289",
    "sg:province":"NSW",
    "wof:name":"Alien Pest Control",
    "wof:placetype":"venue"
},
  "geometry": {"coordinates":[151.71820068400001,-32.9460983276],"type":"Point"}
}