{
  "type": "Feature",
  "properties": {
    "addr:full":"38 Second Ave Box Hill North VIC 3129",
    "addr:housenumber":"38",
    "addr:postcode":"3129",
    "addr:street":"Second Ave",
    "iso:country":"AU",
    "sg:address":"38 Second Ave",
    "sg:city":"Box Hill North",
    "sg:classifiers":[
        {
            "category":"Real Estate",
            "subcategory":"Real Estate Agent",
            "type":"Services"
        }
    ],
    "sg:phone":"+61 3 9012 5381",
    "sg:postcode":"3129",
    "sg:province":"VIC",
    "sg:tags":[
        "export"
    ],
    "wof:name":"Ausphil Corp",
    "wof:placetype":"venue"
},
  "geometry": {"coordinates":[145.13900756800001,-37.8023796082],"type":"Point"}
}