{
  "type": "Feature",
  "properties": {
    "addr:full":"3 Tom Thumb Ave Nowra South NSW 2541",
    "addr:housenumber":"3",
    "addr:postcode":"2541",
    "addr:street":"Tom Thumb Ave",
    "iso:country":"AU",
    "sg:address":"3 Tom Thumb Ave",
    "sg:city":"Nowra South",
    "sg:classifiers":[
        {
            "category":"Real Estate",
            "subcategory":"Architect",
            "type":"Services"
        }
    ],
    "sg:phone":"+61 2 4422 8023",
    "sg:postcode":"2541",
    "sg:province":"NSW",
    "sg:tags":[
        "builder",
        "repairer",
        "ship"
    ],
    "wof:name":"Kennedy Shipwrights Pty Ltd",
    "wof:placetype":"venue"
},
  "geometry": {"coordinates":[150.58021545400001,-34.9150543213],"type":"Point"}
}