{
  "type": "Feature",
  "properties": {
    "addr:full":"518 Argent St Broken Hill NSW 2880",
    "addr:housenumber":"518",
    "addr:postcode":"2880",
    "addr:street":"Argent St",
    "iso:country":"AU",
    "sg:address":"518 Argent St",
    "sg:city":"Broken Hill",
    "sg:classifiers":[
        {
            "category":"Structure",
            "subcategory":"Bridge",
            "type":"Public Place"
        }
    ],
    "sg:phone":"+61 8 8087 4460",
    "sg:postcode":"2880",
    "sg:province":"NSW",
    "sg:tags":[
        "chainsaw",
        "brushcutters"
    ],
    "wof:name":"Stihl Chainsaws & Brushcutters",
    "wof:placetype":"venue"
},
  "geometry": {"coordinates":[141.47279357900001,-31.9537124634],"type":"Point"}
}