{
  "type": "Feature",
  "properties": {
    "addr:full":"Stipa St Goolgowi NSW 2652",
    "addr:postcode":"2652",
    "addr:street":"Stipa St",
    "iso:country":"AU",
    "sg:address":"Stipa St",
    "sg:city":"Goolgowi",
    "sg:classifiers":[
        {
            "category":"Organizations",
            "subcategory":"Community Association",
            "type":"Services"
        }
    ],
    "sg:phone":"+61 2 6965 1306",
    "sg:postcode":"2652",
    "sg:province":"NSW",
    "sg:tags":[
        "organisation",
        "family",
        "welfare"
    ],
    "wof:name":"Home & Community Care Centre (HACC)",
    "wof:placetype":"venue"
},
  "geometry": {"coordinates":[145.71083068900001,-33.9794883728],"type":"Point"}
}