{
  "type": "Feature",
  "properties": {
    "addr:full":"13 Gilbert Rd Preston VIC 3072",
    "addr:housenumber":"13",
    "addr:postcode":"3072",
    "addr:street":"Gilbert Rd",
    "iso:country":"AU",
    "sg:address":"13 Gilbert Rd",
    "sg:city":"Preston",
    "sg:classifiers":[
        {
            "category":"Food & Beverages",
            "subcategory":"Bakery",
            "type":"Retail Goods"
        }
    ],
    "sg:phone":"+61 3 9480 3059",
    "sg:postcode":"3072",
    "sg:province":"VIC",
    "sg:tags":[
        "baker"
    ],
    "wof:name":"Gilbert Road Bakehouse",
    "wof:placetype":"venue"
},
  "geometry": {"coordinates":[144.98797607399999,-37.7504959106],"type":"Point"}
}