{
  "type": "Feature",
  "properties": {
    "addr:full":"Shop 1111 Westfield Shopping Centre Carousel, Canningto WA 6107",
    "addr:housenumber":"1111",
    "addr:postcode":"6107",
    "addr:street":"Westfield",
    "iso:country":"AU",
    "sg:address":"Shop 1111",
    "sg:city":"Westfield Shopping Centre Carousel, Canningto",
    "sg:classifiers":[
        {
            "category":"Shopping",
            "subcategory":"Mobile Phones",
            "type":"Retail Goods"
        }
    ],
    "sg:phone":"+61 8 9358 0400",
    "sg:postcode":"6107",
    "sg:province":"WA",
    "sg:tags":[
        "telephone",
        "accessory"
    ],
    "wof:name":"Vodafone",
    "wof:placetype":"venue"
},
  "geometry": {"coordinates":[115.940353394,-32.0163536072],"type":"Point"}
}