{
  "type": "Feature",
  "properties": {
    "addr:full":"6 Rowe St Malaga WA 6090",
    "addr:housenumber":"6",
    "addr:postcode":"6090",
    "addr:street":"Rowe St",
    "iso:country":"AU",
    "sg:address":"6 Rowe St",
    "sg:city":"Malaga",
    "sg:classifiers":[
        {
            "category":"Railroad",
            "type":"Transportation"
        }
    ],
    "sg:phone":"+61 8 9248 6639",
    "sg:postcode":"6090",
    "sg:province":"WA",
    "sg:tags":[
        "equipment",
        "railway",
        "construction",
        "material"
    ],
    "wof:name":"Aries-Hyrail",
    "wof:placetype":"venue"
},
  "geometry": {"coordinates":[115.88873291,-31.8569030762],"type":"Point"}
}