{
  "type": "Feature",
  "properties": {
    "iso:country":"AU",
    "sg:address":"211 Windsor Rd",
    "sg:city":"Vineyard",
    "sg:classifiers":[
        {
            "category":"Wholesale",
            "subcategory":"Painting Supplies",
            "type":"Manufacturing & Wholesale Goods"
        }
    ],
    "sg:phone":"+61 2 4587 9525",
    "sg:postcode":"2765",
    "sg:province":"NSW",
    "sg:tags":[
        "product",
        "cleaning"
    ],
    "wof:name":"Cleanline Direct",
    "wof:placetype":"venue"
},
  "geometry": {"coordinates":[150.866088867,-33.6519622803],"type":"Point"}
}