{
  "type": "Feature",
  "properties": {
    "iso:country":"AU",
    "sg:address":"15 Seventeenth Ave",
    "sg:city":"Mt Isa",
    "sg:phone":"+61 7 4749 1777",
    "sg:postcode":"4825",
    "sg:province":"QLD",
    "wof:name":"Sun-X Windscreen Centre",
    "wof:placetype":"venue"
},
  "geometry": {"coordinates":[139.487106,-20.741592],"type":"Point"}
}