{
  "type": "Feature",
  "properties": {
    "addr:full":"15 Seventeenth Ave Mt Isa QLD 4825",
    "addr:housenumber":"15",
    "addr:postcode":"4825",
    "addr:street":"Seventeenth Ave",
    "iso:country":"AU",
    "sg:address":"15 Seventeenth Ave",
    "sg:city":"Mt Isa",
    "sg:phone":"+61 7 4749 1777",
    "sg:postcode":"4825",
    "sg:province":"QLD",
    "wof:name":"Sun-X Windscreen Centre",
    "wof:placetype":"venue"
},
  "geometry": {"coordinates":[139.48710600000001,-20.741592],"type":"Point"}
}