{
  "type": "Feature",
  "properties": {
    "iso:country":"AU",
    "sg:address":"Level 3, 4 Cross St",
    "sg:city":"Hurstville",
    "sg:classifiers":[
        {
            "category":"Education",
            "subcategory":"Dance Studio",
            "type":"Public Place"
        }
    ],
    "sg:phone":"+61 2 9579 6244",
    "sg:postcode":"2220",
    "sg:province":"NSW",
    "sg:tags":[
        "instruction",
        "language"
    ],
    "wof:name":"Cambridge Business College",
    "wof:placetype":"venue"
},
  "geometry": {"coordinates":[151.10432434099999,-33.9657096863],"type":"Point"}
}