{
  "type": "Feature",
  "properties": {
    "addr:full":"Unit 1 377 Railway Rd Shenton Park WA 6008",
    "addr:housenumber":"377",
    "addr:postcode":"6008",
    "addr:street":"Railway Rd",
    "iso:country":"AU",
    "sg:address":"Unit 1 377 Railway Rd",
    "sg:city":"Shenton Park",
    "sg:classifiers":[
        {
            "category":"Professional",
            "subcategory":"Business Services",
            "type":"Services"
        }
    ],
    "sg:phone":"+61 8 9388 8846",
    "sg:postcode":"6008",
    "sg:province":"WA",
    "sg:tags":[
        "drafting"
    ],
    "wof:name":"GDD (WA) Pty Ltd",
    "wof:placetype":"venue"
},
  "geometry": {"coordinates":[115.805519104,-31.9605541229],"type":"Point"}
}