{
  "type": "Feature",
  "properties": {
    "addr:full":"Level 10, 71 Queens Rd Melbourne VIC 3000",
    "addr:housenumber":"71",
    "addr:postcode":"3000",
    "addr:street":"Queens Rd",
    "iso:country":"AU",
    "sg:address":"Level 10, 71 Queens Rd",
    "sg:city":"Melbourne",
    "sg:classifiers":[
        {
            "category":"Insurance",
            "subcategory":"Hazard Insurance",
            "type":"Services"
        }
    ],
    "sg:phone":"+61 3 9520 9827",
    "sg:postcode":"3000",
    "sg:province":"VIC",
    "sg:tags":[
        "fire",
        "accident",
        "marine"
    ],
    "wof:name":"Richard Oliver Underwriting Managers",
    "wof:placetype":"venue"
},
  "geometry": {"coordinates":[144.97877502399999,-37.8514328003],"type":"Point"}
}