{
  "type": "Feature",
  "properties": {
    "addr:full":"55 Cypress St Newstead TAS 7250",
    "addr:housenumber":"55",
    "addr:postcode":"7250",
    "addr:street":"Cypress St",
    "iso:country":"AU",
    "sg:address":"55 Cypress St",
    "sg:city":"Newstead",
    "sg:classifiers":[
        {
            "category":"Building & Trades",
            "subcategory":"Equipment Rental",
            "type":"Services"
        }
    ],
    "sg:phone":"+61 419 431 589",
    "sg:postcode":"7250",
    "sg:province":"TAS",
    "sg:tags":[
        "crane",
        "hire"
    ],
    "sg:website":"http://www.cranescombined.com.au",
    "wof:name":"Cranes Combined Pty Ltd",
    "wof:placetype":"venue"
},
  "geometry": {"coordinates":[147.15765380900001,-41.4318122864],"type":"Point"}
}