{
  "type": "Feature",
  "properties": {
    "addr:full":"13 Bay St Botany NSW 2019",
    "addr:housenumber":"13",
    "addr:postcode":"2019",
    "addr:street":"Bay St",
    "iso:country":"AU",
    "sg:address":"13 Bay St",
    "sg:city":"Botany",
    "sg:classifiers":[
        {
            "category":"Manufacturing",
            "subcategory":"Food",
            "type":"Manufacturing & Wholesale Goods"
        }
    ],
    "sg:phone":"+61 2 9316 5314",
    "sg:postcode":"2019",
    "sg:province":"NSW",
    "sg:tags":[
        "function",
        "catering"
    ],
    "wof:name":"Ramasa Catering",
    "wof:placetype":"venue"
},
  "geometry": {"coordinates":[151.192092895,-33.9449424744],"type":"Point"}
}