{
  "type": "Feature",
  "properties": {
    "iso:country":"AU",
    "sg:address":"21 McPherson St",
    "sg:city":"Horsham",
    "sg:classifiers":[
        {
            "category":"Government",
            "subcategory":"Court House",
            "type":"Public Place"
        }
    ],
    "sg:phone":"+61 3 5382 0926",
    "sg:postcode":"3400",
    "sg:province":"VIC",
    "sg:tags":[
        "personal",
        "marriage",
        "family",
        "counselling"
    ],
    "wof:name":"Wendy Popple",
    "wof:placetype":"venue"
},
  "geometry": {"coordinates":[142.20506286599999,-36.7111244202],"type":"Point"}
}