{
  "type": "Feature",
  "properties": {
    "addr:full":"52 Plucks Rd Arana Hills QLD 4054",
    "addr:housenumber":"52",
    "addr:postcode":"4054",
    "addr:street":"Plucks Rd",
    "iso:country":"AU",
    "sg:address":"52 Plucks Rd",
    "sg:city":"Arana Hills",
    "sg:classifiers":[
        {
            "category":"Social Services",
            "subcategory":"Child Care",
            "type":"Services"
        }
    ],
    "sg:phone":"+61 7 3351 2552",
    "sg:postcode":"4054",
    "sg:province":"QLD",
    "wof:name":"Montessori Kindergarten & Preschool",
    "wof:placetype":"venue"
},
  "geometry": {"coordinates":[152.955352783,-27.3911724091],"type":"Point"}
}