{
  "type": "Feature",
  "properties": {
    "iso:country":"AU",
    "sg:address":"256 Stanmore Rd",
    "sg:city":"Stanmore",
    "sg:classifiers":[
        {
            "category":"Food & Beverages",
            "subcategory":"Supermarket",
            "type":"Retail Goods"
        }
    ],
    "sg:phone":"+61 2 9560 5653",
    "sg:postcode":"2048",
    "sg:province":"NSW",
    "sg:tags":[
        "grocery",
        "store"
    ],
    "wof:name":"Stanmore Supermarket",
    "wof:placetype":"venue"
},
  "geometry": {"coordinates":[151.16156,-33.896378],"type":"Point"}
}