{
  "type": "Feature",
  "properties": {
    "addr:full":"293 Geelong Rd Footscray West VIC 3012",
    "addr:housenumber":"293",
    "addr:postcode":"3012",
    "addr:street":"Geelong Rd",
    "iso:country":"AU",
    "sg:address":"293 Geelong Rd",
    "sg:city":"Footscray West",
    "sg:classifiers":[
        {
            "category":"Personal",
            "subcategory":"Beauty Salon",
            "type":"Services"
        }
    ],
    "sg:phone":"+61 3 9687 9549",
    "sg:postcode":"3012",
    "sg:province":"VIC",
    "sg:tags":[
        "hairdresser"
    ],
    "wof:name":"Anastasia's Hairdesign",
    "wof:placetype":"venue"
},
  "geometry": {"coordinates":[144.87916564899999,-37.8063087463],"type":"Point"}
}