{
  "type": "Feature",
  "properties": {
    "iso:country":"AU",
    "sg:address":"212 Russell St",
    "sg:city":"Bathurst",
    "sg:classifiers":[
        {
            "category":"Health Services",
            "subcategory":"Doctor",
            "type":"Services"
        }
    ],
    "sg:phone":"+61 2 6331 9163",
    "sg:postcode":"2795",
    "sg:province":"NSW",
    "sg:tags":[
        "medical",
        "practitioner"
    ],
    "wof:name":"Frukacz Andrew Dr",
    "wof:placetype":"venue"
},
  "geometry": {"coordinates":[149.57522582999999,-33.414352417],"type":"Point"}
}