{
  "type": "Feature",
  "properties": {
    "addr:full":"McCracken St Kensington VIC 3031",
    "addr:postcode":"3031",
    "addr:street":"Mccracken St",
    "iso:country":"AU",
    "sg:address":"McCracken St",
    "sg:city":"Kensington",
    "sg:classifiers":[
        {
            "category":"Arena",
            "subcategory":"Sports Club",
            "type":"Entertainment"
        }
    ],
    "sg:phone":"+61 3 9376 1093",
    "sg:postcode":"3031",
    "sg:province":"VIC",
    "sg:tags":[
        "defence",
        "supply",
        "self",
        "instruction",
        "martial art"
    ],
    "wof:name":"Military Tae Kwon-Do Australia",
    "wof:placetype":"venue"
},
  "geometry": {"coordinates":[144.927628,-37.793858],"type":"Point"}
}