{
  "type": "Feature",
  "properties": {
    "addr:full":"12 Clematis St Gympie QLD 4570",
    "addr:housenumber":"12",
    "addr:postcode":"4570",
    "addr:street":"Clematis St",
    "iso:country":"AU",
    "sg:address":"12 Clematis St",
    "sg:city":"Gympie",
    "sg:classifiers":[
        {
            "category":"Home & Garden",
            "subcategory":"Garden Supply",
            "type":"Retail Goods"
        }
    ],
    "sg:phone":"+61 7 5482 2866",
    "sg:postcode":"4570",
    "sg:province":"QLD",
    "sg:tags":[
        "landscape"
    ],
    "wof:name":"Anderleigh Sandstone & Slate",
    "wof:placetype":"venue"
},
  "geometry": {"coordinates":[152.655593872,-26.1864700317],"type":"Point"}
}