{
  "type": "Feature",
  "properties": {
    "addr:full":"24- 28 Nepean Hwy Mentone VIC 3194",
    "addr:housenumber":"28",
    "addr:postcode":"3194",
    "addr:street":"Nepean Hwy",
    "iso:country":"AU",
    "sg:address":"24- 28 Nepean Hwy",
    "sg:city":"Mentone",
    "sg:classifiers":[
        {
            "category":"Autos & Motor Vehicles",
            "subcategory":"Auto Supplies",
            "type":"Retail Goods"
        }
    ],
    "sg:phone":"+61 3 9585 2977",
    "sg:postcode":"3194",
    "sg:province":"VIC",
    "sg:tags":[
        "automotive",
        "stereo",
        "radio"
    ],
    "wof:name":"Strathfield",
    "wof:placetype":"venue"
},
  "geometry": {"coordinates":[145.06570434599999,-37.9761199951],"type":"Point"}
}