{
  "type": "Feature",
  "properties": {
    "iso:country":"AU",
    "sg:address":"Hardy&#039;s Rd",
    "sg:city":"Mudgeeraba",
    "sg:classifiers":[
        {
            "category":"Building & Trades",
            "subcategory":"Construction",
            "type":"Services"
        }
    ],
    "sg:phone":"+61 7 5530 5036",
    "sg:postcode":"4213",
    "sg:province":"QLD",
    "sg:tags":[
        "contractor"
    ],
    "wof:name":"Green D J & Son",
    "wof:placetype":"venue"
},
  "geometry": {"coordinates":[153.35005188,-28.0869445801],"type":"Point"}
}