{
  "type": "Feature",
  "properties": {
    "iso:country":"AU",
    "sg:address":"PO Box 10",
    "sg:city":"Boyanup",
    "sg:classifiers":[
        {
            "category":"Professional",
            "subcategory":"Detective & Security Services",
            "type":"Services"
        }
    ],
    "sg:phone":"+61 407 301 405",
    "sg:postcode":"6237",
    "sg:province":"WA",
    "sg:tags":[
        "investigator"
    ],
    "wof:name":"Harmonic Investigations & Security",
    "wof:placetype":"venue"
},
  "geometry": {"coordinates":[115.727707,-33.482281],"type":"Point"}
}