{
  "type": "Feature",
  "properties": {
    "iso:country":"AU",
    "sg:address":"49 Hunter St",
    "sg:city":"Hornsby",
    "sg:classifiers":[
        {
            "category":"Retail",
            "subcategory":"Auto Repair",
            "type":"Services"
        }
    ],
    "sg:phone":"+61 2 9987 1533",
    "sg:postcode":"2077",
    "sg:province":"NSW",
    "sg:tags":[
        "automotive",
        "air conditioning"
    ],
    "wof:name":"Sydney-Wide Auto Air Conditioning",
    "wof:placetype":"venue"
},
  "geometry": {"coordinates":[151.10081481899999,-33.702003479],"type":"Point"}
}