{
  "type": "Feature",
  "properties": {
    "iso:country":"AU",
    "sg:address":"147 Ryans St",
    "sg:city":"Green Fields",
    "sg:classifiers":[
        {
            "category":"Professional",
            "subcategory":"Employment Agencies",
            "type":"Services"
        }
    ],
    "sg:phone":"+61 8 8285 1073",
    "sg:postcode":"5107",
    "sg:province":"SA",
    "sg:tags":[
        "consultant",
        "casting"
    ],
    "wof:name":"Ned Kelly Casting Agent",
    "wof:placetype":"venue"
},
  "geometry": {"coordinates":[138.602615356,-34.7916641235],"type":"Point"}
}