{
  "type": "Feature",
  "properties": {
    "iso:country":"AU",
    "sg:address":"5 Caribbean Drv",
    "sg:city":"Safety Bay",
    "sg:classifiers":[
        {
            "category":"Building & Trades",
            "subcategory":"Locksmith",
            "type":"Services"
        }
    ],
    "sg:phone":"+61 8 9527 2981",
    "sg:postcode":"6169",
    "sg:province":"WA",
    "sg:tags":[
        "equipment",
        "operating",
        "door",
        "gate"
    ],
    "wof:name":"Auto Door Systems",
    "wof:placetype":"venue"
},
  "geometry": {"coordinates":[115.742447,-32.307823],"type":"Point"}
}