{
  "type": "Feature",
  "properties": {
    "iso:country":"AU",
    "sg:address":"2/ 2 Rawson St",
    "sg:city":"Newtown",
    "sg:classifiers":[
        {
            "category":"Professional",
            "subcategory":"Business Services",
            "type":"Services"
        }
    ],
    "sg:phone":"+61 2 9519 3978",
    "sg:postcode":"2042",
    "sg:province":"NSW",
    "sg:tags":[
        "management",
        "event"
    ],
    "wof:name":"A Red Letter Day",
    "wof:placetype":"venue"
},
  "geometry": {"coordinates":[151.17704800000001,-33.900223],"type":"Point"}
}