{
  "type": "Feature",
  "properties": {
    "iso:country":"AU",
    "sg:address":"Coolibah Drv",
    "sg:city":"Greenwood",
    "sg:classifiers":[
        {
            "category":"Food & Beverages",
            "subcategory":"Supermarket",
            "type":"Retail Goods"
        }
    ],
    "sg:phone":"+61 8 9448 4143",
    "sg:postcode":"6024",
    "sg:province":"WA",
    "sg:tags":[
        "grocery",
        "store"
    ],
    "wof:name":"Foodland Stores",
    "wof:placetype":"venue"
},
  "geometry": {"coordinates":[115.80129241900001,-31.832326889],"type":"Point"}
}