{
  "type": "Feature",
  "properties": {
    "iso:country":"AU",
    "sg:address":"1107 - 1109 Latrobe St",
    "sg:city":"Ballarat",
    "sg:classifiers":[
        {
            "category":"Wholesale",
            "subcategory":"Furniture",
            "type":"Manufacturing & Wholesale Goods"
        }
    ],
    "sg:phone":"+61 3 5335 5189",
    "sg:postcode":"3350",
    "sg:province":"VIC",
    "sg:tags":[
        "wholesaler",
        "mfrs"
    ],
    "wof:name":"Asia on Latrobe",
    "wof:placetype":"venue"
},
  "geometry": {"coordinates":[143.816544,-37.570648],"type":"Point"}
}