{
  "type": "Feature",
  "properties": {
    "iso:country":"AU",
    "sg:address":"213 Invermay Rd",
    "sg:city":"Invermay",
    "sg:classifiers":[
        {
            "category":"Professional",
            "subcategory":"Art Services",
            "type":"Services"
        }
    ],
    "sg:phone":"+61 3 6326 6788",
    "sg:postcode":"7248",
    "sg:province":"TAS",
    "sg:tags":[
        "picture",
        "frame",
        "framing"
    ],
    "wof:name":"Black & White Photographics",
    "wof:placetype":"venue"
},
  "geometry": {"coordinates":[147.13450622600001,-41.4187660217],"type":"Point"}
}