{
  "type": "Feature",
  "properties": {
    "iso:country":"AU",
    "sg:address":"20 Skylark St",
    "sg:city":"Inala",
    "sg:classifiers":[
        {
            "category":"Organizations",
            "subcategory":"Membership Organization",
            "type":"Services"
        }
    ],
    "sg:phone":"+61 7 3879 0046",
    "sg:postcode":"4077",
    "sg:province":"QLD",
    "sg:tags":[
        "support",
        "health",
        "organisation"
    ],
    "wof:name":"60 & Better Program",
    "wof:placetype":"venue"
},
  "geometry": {"coordinates":[152.98155212399999,-27.5994281769],"type":"Point"}
}