{
  "type": "Feature",
  "properties": {
    "iso:country":"AU",
    "sg:address":"14 Trebartha St",
    "sg:city":"Bass Hill",
    "sg:classifiers":[
        {
            "category":"Travel",
            "subcategory":"Hostel",
            "type":"Entertainment"
        }
    ],
    "sg:phone":"+61 2 9645 3220",
    "sg:postcode":"2197",
    "sg:province":"NSW",
    "sg:tags":[
        "home"
    ],
    "wof:name":"The Salvation Army Weeroona Village",
    "wof:placetype":"venue"
},
  "geometry": {"coordinates":[151.00309799999999,-33.900013],"type":"Point"}
}