{
  "type": "Feature",
  "properties": {
    "addr:full":"11 Groves Rd Gympie QLD 4570",
    "addr:housenumber":"11",
    "addr:postcode":"4570",
    "addr:street":"Groves Rd",
    "iso:country":"AU",
    "sg:address":"11 Groves Rd",
    "sg:city":"Gympie",
    "sg:classifiers":[
        {
            "category":"Retail",
            "subcategory":"Auto Repair",
            "type":"Services"
        }
    ],
    "sg:phone":"+61 7 5483 6234",
    "sg:postcode":"4570",
    "sg:province":"QLD",
    "sg:tags":[
        "repairer",
        "motor",
        "engineer"
    ],
    "wof:name":"Morgan I W",
    "wof:placetype":"venue"
},
  "geometry": {"coordinates":[152.65484619099999,-26.1560459137],"type":"Point"}
}