{
  "type": "Feature",
  "properties": {
    "addr:full":"402 Bobbin Head Rd North Turramurra NSW 2074",
    "addr:housenumber":"402",
    "addr:postcode":"2074",
    "addr:street":"Bobbin Head Rd",
    "iso:country":"AU",
    "sg:address":"402 Bobbin Head Rd",
    "sg:city":"North Turramurra",
    "sg:classifiers":[
        {
            "category":"Health Services",
            "subcategory":"Nursing And Care Facility",
            "type":"Services"
        }
    ],
    "sg:phone":"+61 2 9632 3144",
    "sg:postcode":"2074",
    "sg:province":"NSW",
    "sg:tags":[
        "home"
    ],
    "wof:name":"Southern Cross Nursing Home",
    "wof:placetype":"venue"
},
  "geometry": {"coordinates":[151.14810180699999,-33.7002563477],"type":"Point"}
}