{
  "type": "Feature",
  "properties": {
    "iso:country":"AU",
    "sg:address":"Heroes Ave",
    "sg:city":"Emerald",
    "sg:classifiers":[
        {
            "category":"Education",
            "subcategory":"School",
            "type":"Public Place"
        }
    ],
    "sg:phone":"+61 3 5968 4311",
    "sg:postcode":"3782",
    "sg:province":"VIC",
    "sg:tags":[
        "state",
        "except",
        "nsw"
    ],
    "wof:name":"Emerald Primary School",
    "wof:placetype":"venue"
},
  "geometry": {"coordinates":[145.441147,-37.933254],"type":"Point"}
}