{
  "type": "Feature",
  "properties": {
    "addr:full":"59 Goodwood Rd Wayville SA 5034",
    "addr:housenumber":"59",
    "addr:postcode":"5034",
    "addr:street":"Goodwood Rd",
    "iso:country":"AU",
    "sg:address":"59 Goodwood Rd",
    "sg:city":"Wayville",
    "sg:classifiers":[
        {
            "category":"Wholesale",
            "subcategory":"Construction Materials",
            "type":"Manufacturing & Wholesale Goods"
        }
    ],
    "sg:phone":"+61 8 8272 3704",
    "sg:postcode":"5034",
    "sg:province":"SA",
    "sg:tags":[
        "wholesaler",
        "lighting",
        "mfrs",
        "accessory"
    ],
    "wof:name":"Cidalume",
    "wof:placetype":"venue"
},
  "geometry": {"coordinates":[138.589553833,-34.9472389221],"type":"Point"}
}