{
  "type": "Feature",
  "properties": {
    "addr:full":"115 Currumburra Rd Ashmore QLD 4214",
    "addr:housenumber":"115",
    "addr:postcode":"4214",
    "addr:street":"Currumburra Rd",
    "iso:country":"AU",
    "sg:address":"115 Currumburra Rd",
    "sg:city":"Ashmore",
    "sg:classifiers":[
        {
            "category":"Retail",
            "subcategory":"Laundry & Dry Cleaning",
            "type":"Services"
        }
    ],
    "sg:phone":"+61 7 5597 1294",
    "sg:postcode":"4214",
    "sg:province":"QLD",
    "sg:tags":[
        "manicurist"
    ],
    "wof:name":"Beauty On The Terrace",
    "wof:placetype":"venue"
},
  "geometry": {"coordinates":[153.38218689000001,-27.9868030548],"type":"Point"}
}