{
  "type": "Feature",
  "properties": {
    "iso:country":"AU",
    "sg:address":"65 Errina Rd",
    "sg:city":"Alexander Heights",
    "sg:classifiers":[
        {
            "category":"Professional",
            "subcategory":"Computer Services",
            "type":"Services"
        }
    ],
    "sg:phone":"+61 8 9343 5105",
    "sg:postcode":"6064",
    "sg:province":"WA",
    "sg:tags":[
        "training"
    ],
    "wof:name":"StepWise Computing",
    "wof:placetype":"venue"
},
  "geometry": {"coordinates":[115.855712891,-31.8279018402],"type":"Point"}
}