{
  "type": "Feature",
  "properties": {
    "addr:full":"Thiele Rd Pompoota SA 5238",
    "addr:postcode":"5238",
    "addr:street":"Thiele Rd",
    "iso:country":"AU",
    "sg:address":"Thiele Rd",
    "sg:city":"Pompoota",
    "sg:classifiers":[
        {
            "category":"Farming",
            "subcategory":"Dairy Farm",
            "type":"Manufacturing & Wholesale Goods"
        }
    ],
    "sg:phone":"+61 8 8535 4230",
    "sg:postcode":"5238",
    "sg:province":"SA",
    "wof:name":"Duell W A & S O",
    "wof:placetype":"venue"
},
  "geometry": {"coordinates":[139.35208129899999,-34.9979057312],"type":"Point"}
}