{
  "type": "Feature",
  "properties": {
    "iso:country":"AU",
    "sg:address":"43 North Rd",
    "sg:city":"Bassendean",
    "sg:classifiers":[
        {
            "category":"Building & Trades",
            "subcategory":"Landscaping Services",
            "type":"Services"
        }
    ],
    "sg:phone":"+61 8 9279 9266",
    "sg:postcode":"6054",
    "sg:province":"WA",
    "sg:tags":[
        "designer",
        "landscape",
        "contractor"
    ],
    "wof:name":"Neil Hansen Landscapes",
    "wof:placetype":"venue"
},
  "geometry": {"coordinates":[115.960037231,-31.9067516327],"type":"Point"}
}