{
  "type": "Feature",
  "properties": {
    "addr:full":"3 Karingal Pl Moree NSW 2400",
    "addr:housenumber":"3",
    "addr:postcode":"2400",
    "addr:street":"Karingal Pl",
    "iso:country":"AU",
    "sg:address":"3 Karingal Pl",
    "sg:city":"Moree",
    "sg:classifiers":[
        {
            "category":"Professional",
            "subcategory":"Management & Consulting",
            "type":"Services"
        }
    ],
    "sg:phone":"+61 2 6752 5377",
    "sg:postcode":"2400",
    "sg:province":"NSW",
    "sg:tags":[
        "consultant",
        "business"
    ],
    "wof:name":"Franannie Pty Ltd",
    "wof:placetype":"venue"
},
  "geometry": {"coordinates":[149.81765747099999,-29.4598693848],"type":"Point"}
}