{
  "type": "Feature",
  "properties": {
    "iso:country":"AU",
    "sg:address":"17 Walkers Ave",
    "sg:city":"Newnham",
    "sg:classifiers":[
        {
            "category":"Real Estate",
            "subcategory":"Real Estate Operator",
            "type":"Services"
        }
    ],
    "sg:phone":"+61 418 130 619",
    "sg:postcode":"7248",
    "sg:province":"TAS",
    "sg:tags":[
        "concrete",
        "pumping"
    ],
    "wof:name":"P.M. Concreting Pty Ltd",
    "wof:placetype":"venue"
},
  "geometry": {"coordinates":[147.12857055699999,-41.3943214417],"type":"Point"}
}