{
  "type": "Feature",
  "properties": {
    "addr:full":"Townsend Rd Buderim QLD 4556",
    "addr:postcode":"4556",
    "addr:street":"Townsend Rd",
    "iso:country":"AU",
    "sg:address":"Townsend Rd",
    "sg:city":"Buderim",
    "sg:classifiers":[
        {
            "category":"Social Services",
            "subcategory":"Retirement Home",
            "type":"Services"
        }
    ],
    "sg:phone":"+61 7 5476 8900",
    "sg:postcode":"4556",
    "sg:province":"QLD",
    "sg:tags":[
        "village"
    ],
    "sg:website":"http://www.edenlea.com.au",
    "wof:name":"EdenLea On Buderim",
    "wof:placetype":"venue"
},
  "geometry": {"coordinates":[153.04440307600001,-26.6907463074],"type":"Point"}
}