{
  "type": "Feature",
  "properties": {
    "iso:country":"AU",
    "sg:address":"7 Charman Ave",
    "sg:city":"Emerald",
    "sg:classifiers":[
        {
            "category":"Professional",
            "subcategory":"Detective & Security Services",
            "type":"Services"
        }
    ],
    "sg:phone":"+61 3 5968 5671",
    "sg:postcode":"3782",
    "sg:province":"VIC",
    "sg:tags":[
        "consultant",
        "system"
    ],
    "wof:name":"Security Response",
    "wof:placetype":"venue"
},
  "geometry": {"coordinates":[145.447845,-37.91795],"type":"Point"}
}