{
  "type": "Feature",
  "properties": {
    "addr:full":"2 Windsor St Woodford QLD 4514",
    "addr:housenumber":"2",
    "addr:postcode":"4514",
    "addr:street":"Windsor St",
    "iso:country":"AU",
    "sg:address":"2 Windsor St",
    "sg:city":"Woodford",
    "sg:classifiers":[
        {
            "category":"Utilities",
            "subcategory":"Electric",
            "type":"Services"
        }
    ],
    "sg:phone":"+61 7 5496 1308",
    "sg:postcode":"4514",
    "sg:province":"QLD",
    "sg:tags":[
        "electrical",
        "contractor"
    ],
    "wof:name":"Kilcoy Electrical Service",
    "wof:placetype":"venue"
},
  "geometry": {"coordinates":[152.76921100000001,-26.939917],"type":"Point"}
}