{
  "type": "Feature",
  "properties": {
    "addr:full":"Wyeebo St Merimbula NSW 2548",
    "addr:postcode":"2548",
    "addr:street":"Wyeebo St",
    "iso:country":"AU",
    "sg:address":"Wyeebo St",
    "sg:city":"Merimbula",
    "sg:classifiers":[
        {
            "category":"Health Services",
            "subcategory":"Hospital",
            "type":"Services"
        }
    ],
    "sg:phone":"+61 13 12 33",
    "sg:postcode":"2548",
    "sg:province":"NSW",
    "sg:tags":[
        "ambulance"
    ],
    "wof:name":"Ambulance Service Of NSW",
    "wof:placetype":"venue"
},
  "geometry": {"coordinates":[149.92506408700001,-36.8925437927],"type":"Point"}
}