{
  "type": "Feature",
  "properties": {
    "addr:full":"46 Dandenong St Dandenong VIC 3175",
    "addr:housenumber":"46",
    "addr:postcode":"3175",
    "addr:street":"Dandenong St",
    "iso:country":"AU",
    "sg:address":"46 Dandenong St",
    "sg:city":"Dandenong",
    "sg:classifiers":[
        {
            "category":"Fast Food",
            "type":"Food & Drink"
        }
    ],
    "sg:phone":"+61 3 9791 6950",
    "sg:postcode":"3175",
    "sg:province":"VIC",
    "sg:tags":[
        "away",
        "take"
    ],
    "wof:name":"Dandenong Street Cafe",
    "wof:placetype":"venue"
},
  "geometry": {"coordinates":[145.19921875,-37.9952087402],"type":"Point"}
}