{
  "type": "Feature",
  "properties": {
    "addr:full":"2 Niblick St Kingsbury VIC 3083",
    "addr:housenumber":"2",
    "addr:postcode":"3083",
    "addr:street":"Niblick St",
    "iso:country":"AU",
    "sg:address":"2 Niblick St",
    "sg:city":"Kingsbury",
    "sg:classifiers":[
        {
            "category":"Building & Trades",
            "subcategory":"Construction",
            "type":"Services"
        }
    ],
    "sg:phone":"+61 3 9469 4521",
    "sg:postcode":"3083",
    "sg:province":"VIC",
    "sg:tags":[
        "renovation",
        "alterations",
        "extension",
        "contractor"
    ],
    "wof:name":"K & D Turner Homecare",
    "wof:placetype":"venue"
},
  "geometry": {"coordinates":[145.0365448,-37.7156410217],"type":"Point"}
}