{
  "type": "Feature",
  "properties": {
    "addr:full":"6 Woolcock Rd Longwood SA 5153",
    "addr:housenumber":"6",
    "addr:postcode":"5153",
    "addr:street":"Woolcock Rd",
    "iso:country":"AU",
    "sg:address":"6 Woolcock Rd",
    "sg:city":"Longwood",
    "sg:classifiers":[
        {
            "category":"Building & Trades",
            "subcategory":"Construction",
            "type":"Services"
        }
    ],
    "sg:phone":"+61 8 8388 2422",
    "sg:postcode":"5153",
    "sg:province":"SA",
    "sg:tags":[
        "stonework",
        "stone",
        "mason"
    ],
    "wof:name":"Livingstone Art",
    "wof:placetype":"venue"
},
  "geometry": {"coordinates":[138.72442626899999,-35.0471382141],"type":"Point"}
}