{
  "type": "Feature",
  "properties": {
    "addr:full":"31 Julia St Portland VIC 3305",
    "addr:housenumber":"31",
    "addr:postcode":"3305",
    "addr:street":"Julia St",
    "iso:country":"AU",
    "sg:address":"31 Julia St",
    "sg:city":"Portland",
    "sg:classifiers":[
        {
            "category":"Banks & Credit Unions",
            "subcategory":"Investment Brokerage",
            "type":"Services"
        }
    ],
    "sg:phone":"+61 3 5523 3611",
    "sg:postcode":"3305",
    "sg:province":"VIC",
    "wof:name":"Quadrant Securities Pty Ltd",
    "wof:placetype":"venue"
},
  "geometry": {"coordinates":[141.604446411,-38.3485183716],"type":"Point"}
}