{
  "type": "Feature",
  "properties": {
    "addr:full":"362 Malvern Rd Prahran VIC 3181",
    "addr:housenumber":"362",
    "addr:postcode":"3181",
    "addr:street":"Malvern Rd",
    "iso:country":"AU",
    "sg:address":"362 Malvern Rd",
    "sg:city":"Prahran",
    "sg:classifiers":[
        {
            "category":"Fast Food",
            "type":"Food & Drink"
        }
    ],
    "sg:phone":"+61 3 9510 3668",
    "sg:postcode":"3181",
    "sg:province":"VIC",
    "sg:tags":[
        "away",
        "take"
    ],
    "wof:name":"Green Dragon Take Away Food",
    "wof:placetype":"venue"
},
  "geometry": {"coordinates":[144.99887085,-37.847618103],"type":"Point"}
}