{
  "type": "Feature",
  "properties": {
    "iso:country":"AU",
    "sg:address":"2/ 300 Forest Rd",
    "sg:city":"Hurstville",
    "sg:classifiers":[
        {
            "category":"Manufacturing",
            "subcategory":"Chemicals & Compounds",
            "type":"Manufacturing & Wholesale Goods"
        }
    ],
    "sg:phone":"+61 2 9460 8480",
    "sg:postcode":"2220",
    "sg:province":"NSW",
    "sg:tags":[
        "agricultural"
    ],
    "wof:name":"United Phosphorus Ltd",
    "wof:placetype":"venue"
},
  "geometry": {"coordinates":[151.10264587399999,-33.966632843],"type":"Point"}
}