{
  "type": "Feature",
  "properties": {
    "iso:country":"AU",
    "sg:address":"Lake Wyeba Drv",
    "sg:city":"Noosaville",
    "sg:classifiers":[
        {
            "category":"Social Services",
            "subcategory":"Retirement Home",
            "type":"Services"
        }
    ],
    "sg:phone":"+61 7 5474 4480",
    "sg:postcode":"4566",
    "sg:province":"QLD",
    "sg:tags":[
        "village"
    ],
    "wof:name":"Noosa Waters Retirement Village",
    "wof:placetype":"venue"
},
  "geometry": {"coordinates":[153.05192565900001,-26.4149684906],"type":"Point"}
}