{
  "type": "Feature",
  "properties": {
    "iso:country":"AU",
    "sg:address":"9 Victoria St",
    "sg:city":"Mackay",
    "sg:classifiers":[
        {
            "category":"Wholesale",
            "subcategory":"Scrap",
            "type":"Manufacturing & Wholesale Goods"
        }
    ],
    "sg:phone":"+61 7 4957 2889",
    "sg:postcode":"4740",
    "sg:province":"QLD",
    "sg:tags":[
        "merchant",
        "metal"
    ],
    "wof:name":"Jetson Salvage & Scrap Metal",
    "wof:placetype":"venue"
},
  "geometry": {"coordinates":[149.190536,-21.141642],"type":"Point"}
}