{
  "type": "Feature",
  "properties": {
    "iso:country":"AU",
    "sg:address":"349 Connection Rd",
    "sg:city":"Mooloolah",
    "sg:classifiers":[
        {
            "category":"Utilities",
            "type":"Services"
        }
    ],
    "sg:phone":"+61 7 5494 7226",
    "sg:postcode":"4553",
    "sg:province":"QLD",
    "sg:tags":[
        "refrigeration",
        "industrial",
        "commercial",
        "retail"
    ],
    "wof:name":"Raddatz Refrigeration & Air Conditioning Services",
    "wof:placetype":"venue"
},
  "geometry": {"coordinates":[152.962738,-26.764833],"type":"Point"}
}