{
  "type": "Feature",
  "properties": {
    "addr:full":"Shop 3 33 Roche St Dalby QLD 4405",
    "addr:housenumber":"shop;33",
    "addr:postcode":"4405",
    "addr:street":"Roche St",
    "iso:country":"AU",
    "sg:address":"Shop 3 33 Roche St",
    "sg:city":"Dalby",
    "sg:classifiers":[
        {
            "category":"Personal",
            "subcategory":"Beauty Salon",
            "type":"Services"
        }
    ],
    "sg:phone":"+61 7 4662 4107",
    "sg:postcode":"4405",
    "sg:province":"QLD",
    "sg:tags":[
        "hairdresser"
    ],
    "wof:name":"Cynergi Hair Studio",
    "wof:placetype":"venue"
},
  "geometry": {"coordinates":[151.26446533199999,-27.182559967],"type":"Point"}
}