{
  "type": "Feature",
  "properties": {
    "addr:full":"14/ 199 Pacific Hwy North Sydney NSW 2060",
    "addr:housenumber":"14 / 199",
    "addr:postcode":"2060",
    "addr:street":"Pacific Hwy",
    "iso:country":"AU",
    "sg:address":"14/ 199 Pacific Hwy",
    "sg:city":"North Sydney",
    "sg:classifiers":[
        {
            "category":"Health Services",
            "subcategory":"Health Practitioner",
            "type":"Services"
        }
    ],
    "sg:phone":"+61 2 9460 2634",
    "sg:postcode":"2060",
    "sg:province":"NSW",
    "sg:tags":[
        "acupuncture"
    ],
    "wof:name":"Werczynska, Urszula",
    "wof:placetype":"venue"
},
  "geometry": {"coordinates":[151.20596313499999,-33.8367195129],"type":"Point"}
}