{
  "type": "Feature",
  "properties": {
    "iso:country":"AU",
    "sg:address":"66 King William Rd",
    "sg:city":"Goodwood",
    "sg:classifiers":[
        {
            "category":"Manufacturing",
            "subcategory":"Food",
            "type":"Manufacturing & Wholesale Goods"
        }
    ],
    "sg:phone":"+61 8 8271 8262",
    "sg:postcode":"5034",
    "sg:province":"SA",
    "sg:tags":[
        "function",
        "catering"
    ],
    "wof:name":"Restaurant 66",
    "wof:placetype":"venue"
},
  "geometry": {"coordinates":[138.59965515100001,-34.9513244629],"type":"Point"}
}