{
  "type": "Feature",
  "properties": {
    "iso:country":"AU",
    "sg:address":"80 Creek St",
    "sg:city":"Jindera",
    "sg:classifiers":[
        {
            "category":"Social Services",
            "subcategory":"Child Care",
            "type":"Services"
        }
    ],
    "sg:phone":"+61 2 6026 3877",
    "sg:postcode":"2642",
    "sg:province":"NSW",
    "wof:name":"Hume Billabong Family Day Care",
    "wof:placetype":"venue"
},
  "geometry": {"coordinates":[146.88531494099999,-35.9534721375],"type":"Point"}
}