{
  "type": "Feature",
  "properties": {
    "addr:full":"44 Fitzpatrick St Revesby NSW 2212",
    "addr:housenumber":"44",
    "addr:postcode":"2212",
    "addr:street":"Fitzpatrick St",
    "iso:country":"AU",
    "sg:address":"44 Fitzpatrick St",
    "sg:city":"Revesby",
    "sg:classifiers":[
        {
            "category":"Retail",
            "subcategory":"Animal Services",
            "type":"Services"
        }
    ],
    "sg:phone":"+61 2 9774 3272",
    "sg:postcode":"2212",
    "sg:province":"NSW",
    "sg:tags":[
        "breeder",
        "sheep",
        "stud",
        "cattle"
    ],
    "wof:name":"Australian Rural Industries Pty Limited",
    "wof:placetype":"venue"
},
  "geometry": {"coordinates":[151.00256300000001,-33.938232],"type":"Point"}
}