{
  "type": "Feature",
  "properties": {
    "iso:country":"AU",
    "sg:address":"3 Giana Crt",
    "sg:city":"Ringwood",
    "sg:classifiers":[
        {
            "category":"Real Estate",
            "subcategory":"Architect",
            "type":"Services"
        }
    ],
    "sg:phone":"+61 3 9870 2393",
    "sg:postcode":"3134",
    "sg:province":"VIC",
    "wof:name":"Thomson Russell",
    "wof:placetype":"venue"
},
  "geometry": {"coordinates":[145.21669006400001,-37.7996711731],"type":"Point"}
}