{
  "type": "Feature",
  "properties": {
    "iso:country":"AU",
    "sg:address":"103 Allambi Ave",
    "sg:city":"Broadbeach Waters",
    "sg:classifiers":[
        {
            "category":"Building & Trades",
            "subcategory":"Construction",
            "type":"Services"
        }
    ],
    "sg:phone":"+61 417 797 594",
    "sg:postcode":"4218",
    "sg:province":"QLD",
    "sg:tags":[
        "contractor"
    ],
    "wof:name":"Cove Constructions Qld",
    "wof:placetype":"venue"
},
  "geometry": {"coordinates":[153.42440795900001,-28.0244197845],"type":"Point"}
}