{
  "type": "Feature",
  "properties": {
    "addr:full":"22 Spurway St Ermington NSW 2115",
    "addr:housenumber":"22",
    "addr:postcode":"2115",
    "addr:street":"Spurway St",
    "iso:country":"AU",
    "sg:address":"22 Spurway St",
    "sg:city":"Ermington",
    "sg:classifiers":[
        {
            "category":"Utilities",
            "subcategory":"Refuse",
            "type":"Services"
        }
    ],
    "sg:phone":"+61 412 828 529",
    "sg:postcode":"2115",
    "sg:province":"NSW",
    "sg:tags":[
        "remover",
        "rubbish"
    ],
    "wof:name":"A Cheap Truck Load",
    "wof:placetype":"venue"
},
  "geometry": {"coordinates":[151.05555725100001,-33.8109321594],"type":"Point"}
}