{
  "type": "Feature",
  "properties": {
    "addr:full":"74 A Melbourne St North Adelaide SA 5006",
    "addr:housenumber":"74 a",
    "addr:postcode":"5006",
    "addr:street":"Melbourne St",
    "iso:country":"AU",
    "sg:address":"74 A Melbourne St",
    "sg:city":"North Adelaide",
    "sg:classifiers":[
        {
            "category":"Personal",
            "subcategory":"Beauty Salon",
            "type":"Services"
        }
    ],
    "sg:phone":"+61 8 8361 8688",
    "sg:postcode":"5006",
    "sg:province":"SA",
    "sg:tags":[
        "hairdresser"
    ],
    "wof:name":"Arlene Hume",
    "wof:placetype":"venue"
},
  "geometry": {"coordinates":[138.601196289,-34.9105758667],"type":"Point"}
}