{
  "type": "Feature",
  "properties": {
    "iso:country":"AU",
    "sg:address":"PO Box 266",
    "sg:city":"Churchill",
    "sg:classifiers":[
        {
            "category":"Retail",
            "subcategory":"Repair Shop",
            "type":"Services"
        }
    ],
    "sg:phone":"+61 3 5122 2324",
    "sg:postcode":"3842",
    "sg:province":"VIC",
    "sg:tags":[
        "restorer",
        "repairer",
        "carpet"
    ],
    "wof:name":"Ken & Janines Carpet Cleaning",
    "wof:placetype":"venue"
},
  "geometry": {"coordinates":[146.42181396500001,-38.3153915405],"type":"Point"}
}