{
  "type": "Feature",
  "properties": {
    "iso:country":"AU",
    "sg:address":"U3/ 8",
    "sg:city":"Pitt Way Booragoon",
    "sg:classifiers":[
        {
            "category":"Shopping",
            "subcategory":"Computers & Home Electronics",
            "type":"Retail Goods"
        }
    ],
    "sg:phone":"+61 8 9330 7666",
    "sg:postcode":"6154",
    "sg:province":"WA",
    "sg:tags":[
        "small",
        "equipment",
        "business"
    ],
    "wof:name":"Ynot Computer Systems",
    "wof:placetype":"venue"
},
  "geometry": {"coordinates":[115.824501,-32.043064],"type":"Point"}
}