{
  "type": "Feature",
  "properties": {
    "addr:full":"1306 Centre Rd Clayton VIC 3168",
    "addr:housenumber":"1306",
    "addr:postcode":"3168",
    "addr:street":"Centre Rd",
    "iso:country":"AU",
    "sg:address":"1306 Centre Rd",
    "sg:city":"Clayton",
    "sg:classifiers":[
        {
            "category":"Shopping",
            "subcategory":"Computers & Home Electronics",
            "type":"Retail Goods"
        }
    ],
    "sg:phone":"+61 3 9543 9155",
    "sg:postcode":"3168",
    "sg:province":"VIC",
    "sg:tags":[
        "small",
        "equipment",
        "business"
    ],
    "wof:name":"Alfatek Computers",
    "wof:placetype":"venue"
},
  "geometry": {"coordinates":[145.11598205600001,-37.9282493591],"type":"Point"}
}