{
  "type": "Feature",
  "properties": {
    "addr:full":"1286 Plenty Rd Bundoora VIC 3083",
    "addr:housenumber":"1286",
    "addr:postcode":"3083",
    "addr:street":"Plenty Rd",
    "iso:country":"AU",
    "sg:address":"1286 Plenty Rd",
    "sg:city":"Bundoora",
    "sg:classifiers":[
        {
            "category":"Industrial Area",
            "type":"Public Place"
        }
    ],
    "sg:phone":"+61 419 353 950",
    "sg:postcode":"3083",
    "sg:province":"VIC",
    "sg:tags":[
        "rural",
        "shed"
    ],
    "wof:name":"Steel True Constructions",
    "wof:placetype":"venue"
},
  "geometry": {"coordinates":[145.058425903,-37.7004318237],"type":"Point"}
}