{
  "type": "Feature",
  "properties": {
    "addr:full":"19 Fisher St Auburn NSW 2144",
    "addr:housenumber":"19",
    "addr:postcode":"2144",
    "addr:street":"Fisher St",
    "iso:country":"AU",
    "sg:address":"19 Fisher St",
    "sg:city":"Auburn",
    "sg:classifiers":[
        {
            "category":"Wholesale",
            "subcategory":"Machinery & Supplies",
            "type":"Manufacturing & Wholesale Goods"
        }
    ],
    "sg:phone":"+61 2 9647 1400",
    "sg:postcode":"2144",
    "sg:province":"NSW",
    "sg:tags":[
        "equipment",
        "hydraulic"
    ],
    "wof:name":"Imperial Eastman Pty Ltd",
    "wof:placetype":"venue"
},
  "geometry": {"coordinates":[151.03822326700001,-33.8344192505],"type":"Point"}
}