{
  "type": "Feature",
  "properties": {
    "addr:full":"52-56 Hoey St Ayr QLD 4807",
    "addr:housenumber":"52-56",
    "addr:postcode":"4807",
    "addr:street":"Hoey St",
    "iso:country":"AU",
    "sg:address":"52-56 Hoey St",
    "sg:city":"Ayr",
    "sg:classifiers":[
        {
            "category":"Professional",
            "type":"Services"
        }
    ],
    "sg:phone":"+61 7 4783 4111",
    "sg:postcode":"4807",
    "sg:province":"QLD",
    "sg:tags":[
        "spray",
        "painting"
    ],
    "wof:name":"Stephen Scuderi Crash Repairs",
    "wof:placetype":"venue"
},
  "geometry": {"coordinates":[147.396774292,-19.5738506317],"type":"Point"}
}