{
  "type": "Feature",
  "properties": {
    "addr:full":"6 Loudoun St Dalby QLD 4405",
    "addr:housenumber":"6",
    "addr:postcode":"4405",
    "addr:street":"Loudoun St",
    "iso:country":"AU",
    "sg:address":"6 Loudoun St",
    "sg:city":"Dalby",
    "sg:classifiers":[
        {
            "category":"Retail",
            "subcategory":"Auto Repair",
            "type":"Services"
        }
    ],
    "sg:phone":"+61 407 674 015",
    "sg:postcode":"4405",
    "sg:province":"QLD",
    "sg:tags":[
        "electrical"
    ],
    "wof:name":"Tate Auto Electrics",
    "wof:placetype":"venue"
},
  "geometry": {"coordinates":[151.24667358400001,-27.185552597],"type":"Point"}
}