{
  "type": "Feature",
  "properties": {
    "iso:country":"AU",
    "sg:address":"66 Bellvue Rd",
    "sg:city":"Golden Square",
    "sg:classifiers":[
        {
            "category":"Retail",
            "subcategory":"Auto Repair",
            "type":"Services"
        }
    ],
    "sg:phone":"+61 3 5444 4490",
    "sg:postcode":"3555",
    "sg:province":"VIC",
    "sg:tags":[
        "repairer",
        "motor",
        "engineer"
    ],
    "wof:name":"Dahl's Service Centre",
    "wof:placetype":"venue"
},
  "geometry": {"coordinates":[144.27000427199999,-36.7804489136],"type":"Point"}
}