{
  "type": "Feature",
  "properties": {
    "addr:full":"PO Box 6038 Vermont South VIC 3133",
    "addr:postcode":"3133",
    "iso:country":"AU",
    "sg:address":"PO Box 6038",
    "sg:city":"Vermont South",
    "sg:classifiers":[
        {
            "category":"Utilities",
            "subcategory":"Telephone",
            "type":"Services"
        }
    ],
    "sg:phone":"+61 3 9801 9536",
    "sg:postcode":"3133",
    "sg:province":"VIC",
    "sg:tags":[
        "installation",
        "system",
        "maintenance"
    ],
    "wof:name":"Semcom Pty Ltd",
    "wof:placetype":"venue"
},
  "geometry": {"coordinates":[145.185348511,-37.8567008972],"type":"Point"}
}