{
  "type": "Feature",
  "properties": {
    "addr:full":"312 Rowe St Eastwood NSW 2122",
    "addr:housenumber":"312",
    "addr:postcode":"2122",
    "addr:street":"Rowe St",
    "iso:country":"AU",
    "sg:address":"312 Rowe St",
    "sg:city":"Eastwood",
    "sg:classifiers":[
        {
            "category":"Home & Garden",
            "subcategory":"Building Materials",
            "type":"Retail Goods"
        }
    ],
    "sg:phone":"+61 1800 631 487",
    "sg:postcode":"2122",
    "sg:province":"NSW",
    "sg:tags":[
        "lawn",
        "cutting",
        "maintenance"
    ],
    "wof:name":"Paul's Better Lawns",
    "wof:placetype":"venue"
},
  "geometry": {"coordinates":[151.07334899899999,-33.79271698],"type":"Point"}
}