{
  "type": "Feature",
  "properties": {
    "iso:country":"AU",
    "sg:address":"Shop 1 104 Shannon Ave",
    "sg:city":"Geelong West",
    "sg:classifiers":[
        {
            "category":"Home & Garden",
            "subcategory":"Garden Supply",
            "type":"Retail Goods"
        }
    ],
    "sg:phone":"+61 3 5222 6730",
    "sg:postcode":"3218",
    "sg:province":"VIC",
    "sg:tags":[
        "equipment",
        "hydroponics"
    ],
    "wof:name":"Victorian Hydroponics Geelong",
    "wof:placetype":"venue"
},
  "geometry": {"coordinates":[144.33738708499999,-38.1362342834],"type":"Point"}
}