{
  "type": "Feature",
  "properties": {
    "addr:full":"153 San Mateo Ave Mildura VIC 3500",
    "addr:housenumber":"153",
    "addr:postcode":"3500",
    "addr:street":"San Mateo Ave",
    "iso:country":"AU",
    "sg:address":"153 San Mateo Ave",
    "sg:city":"Mildura",
    "sg:classifiers":[
        {
            "category":"Retail",
            "subcategory":"Storage",
            "type":"Services"
        }
    ],
    "sg:phone":"+61 3 5021 2570",
    "sg:postcode":"3500",
    "sg:province":"VIC",
    "sg:tags":[
        "shelving",
        "system"
    ],
    "wof:name":"Oxleys",
    "wof:placetype":"venue"
},
  "geometry": {"coordinates":[142.16305542000001,-34.1928939819],"type":"Point"}
}