{
  "type": "Feature",
  "properties": {
    "addr:full":"Unit 1/ 223 Ewing Rd Woodridge QLD 4114",
    "addr:housenumber":"/ 223",
    "addr:postcode":"4114",
    "addr:street":"Ewing Rd",
    "iso:country":"AU",
    "sg:address":"Unit 1/ 223 Ewing Rd",
    "sg:city":"Woodridge",
    "sg:classifiers":[
        {
            "category":"Personal",
            "subcategory":"Skin Care",
            "type":"Services"
        }
    ],
    "sg:phone":"+61 7 3808 7096",
    "sg:postcode":"4114",
    "sg:province":"QLD",
    "sg:tags":[
        "leather",
        "merchant"
    ],
    "wof:name":"Shann Leather",
    "wof:placetype":"venue"
},
  "geometry": {"coordinates":[153.11094665499999,-27.6217575073],"type":"Point"}
}