{
  "type": "Feature",
  "properties": {
    "addr:full":"187 Angas St Adelaide SA 5000",
    "addr:housenumber":"187",
    "addr:postcode":"5000",
    "addr:street":"Angas St",
    "iso:country":"AU",
    "sg:address":"187 Angas St",
    "sg:city":"Adelaide",
    "sg:classifiers":[
        {
            "category":"Travel",
            "subcategory":"Hotels & Motels",
            "type":"Entertainment"
        }
    ],
    "sg:phone":"+61 8 8223 6879",
    "sg:postcode":"5000",
    "sg:province":"SA",
    "sg:tags":[
        "pub"
    ],
    "wof:name":"Seven Stars Hotel",
    "wof:placetype":"venue"
},
  "geometry": {"coordinates":[138.608032227,-34.9298591614],"type":"Point"}
}