{
  "type": "Feature",
  "properties": {
    "addr:full":"5 Bankside St Nathan QLD 4111",
    "addr:housenumber":"5",
    "addr:postcode":"4111",
    "addr:street":"Bankside St Nathan",
    "iso:country":"AU",
    "sg:address":"5 Bankside St",
    "sg:city":"Nathan",
    "sg:classifiers":[
        {
            "category":"Insurance",
            "subcategory":"Hazard Insurance",
            "type":"Services"
        }
    ],
    "sg:phone":"+61 7 3373 8622",
    "sg:postcode":"4111",
    "sg:province":"QLD",
    "sg:tags":[
        "loss",
        "adjuster",
        "assessor"
    ],
    "wof:name":"Engineering Insurance Claims & Inspection Service",
    "wof:placetype":"venue"
},
  "geometry": {"coordinates":[153.04205322300001,-27.5434837341],"type":"Point"}
}