{
  "type": "Feature",
  "properties": {
    "iso:country":"AU",
    "sg:address":"PO Box 335",
    "sg:city":"Strathfield",
    "sg:classifiers":[
        {
            "category":"Health Services",
            "subcategory":"Doctor",
            "type":"Services"
        }
    ],
    "sg:phone":"+61 2 9746 9546",
    "sg:postcode":"2135",
    "sg:province":"NSW",
    "sg:tags":[
        "nurse",
        "nursing"
    ],
    "wof:name":"Auscare Multicultural Home & Community Services",
    "wof:placetype":"venue"
},
  "geometry": {"coordinates":[151.08122253400001,-33.8791313171],"type":"Point"}
}