{
  "type": "Feature",
  "properties": {
    "addr:full":"Factory 3, 132 North Rd Warragul VIC 3820",
    "addr:housenumber":"132",
    "addr:postcode":"3820",
    "addr:street":"North Rd",
    "iso:country":"AU",
    "sg:address":"Factory 3, 132 North Rd",
    "sg:city":"Warragul",
    "sg:classifiers":[
        {
            "category":"Building & Trades",
            "subcategory":"Construction",
            "type":"Services"
        }
    ],
    "sg:phone":"+61 13 63 60",
    "sg:postcode":"3820",
    "sg:province":"VIC",
    "sg:tags":[
        "window",
        "tinting"
    ],
    "wof:name":"Tint.A.Car",
    "wof:placetype":"venue"
},
  "geometry": {"coordinates":[145.947205,-38.166962],"type":"Point"}
}