{
  "type": "Feature",
  "properties": {
    "addr:full":"South Gippsland Hwy Longford VIC 3851",
    "addr:postcode":"3851",
    "addr:street":"South Gippsland Hwy",
    "iso:country":"AU",
    "sg:address":"South Gippsland Hwy",
    "sg:city":"Longford",
    "sg:classifiers":[
        {
            "category":"Education",
            "subcategory":"School",
            "type":"Public Place"
        }
    ],
    "sg:phone":"+61 3 5149 7210",
    "sg:postcode":"3851",
    "sg:province":"VIC",
    "sg:tags":[
        "state",
        "except",
        "nsw"
    ],
    "wof:name":"Longford Primary School",
    "wof:placetype":"venue"
},
  "geometry": {"coordinates":[147.088134766,-38.1708488464],"type":"Point"}
}