{
  "type": "Feature",
  "properties": {
    "iso:country":"AU",
    "sg:address":"741 Geelong Rd",
    "sg:city":"Brooklyn",
    "sg:classifiers":[
        {
            "category":"Professional",
            "subcategory":"Employment Agencies",
            "type":"Services"
        }
    ],
    "sg:phone":"+61 3 9314 4242",
    "sg:postcode":"3012",
    "sg:province":"VIC",
    "sg:tags":[
        "vic",
        "escort"
    ],
    "sg:website":"http://www.thegentlemansclub.com.au",
    "wof:name":"Club 741",
    "wof:placetype":"venue"
},
  "geometry": {"coordinates":[144.882736206,-37.8040008545],"type":"Point"}
}