{
  "type": "Feature",
  "properties": {
    "iso:country":"AU",
    "sg:address":"264 Belmore Rd",
    "sg:city":"Riverwood",
    "sg:classifiers":[
        {
            "category":"Health Services",
            "subcategory":"Doctor",
            "type":"Services"
        }
    ],
    "sg:phone":"+61 2 9533 5100",
    "sg:postcode":"2210",
    "sg:province":"NSW",
    "sg:tags":[
        "medical",
        "practitioner"
    ],
    "wof:name":"Harrison Brian Dr",
    "wof:placetype":"venue"
},
  "geometry": {"coordinates":[151.052658,-33.949715],"type":"Point"}
}