{
  "type": "Feature",
  "properties": {
    "addr:full":"56 Maritana St Kalgoorlie WA 6430",
    "addr:housenumber":"56",
    "addr:postcode":"6430",
    "addr:street":"Maritana St",
    "iso:country":"AU",
    "sg:address":"56 Maritana St",
    "sg:city":"Kalgoorlie",
    "sg:classifiers":[
        {
            "category":"Professional",
            "subcategory":"Computer Services",
            "type":"Services"
        }
    ],
    "sg:phone":"+61 8 9021 3330",
    "sg:postcode":"6430",
    "sg:province":"WA",
    "sg:tags":[
        "repairs",
        "upgrade",
        "equipment"
    ],
    "wof:name":"Main Marketing Services",
    "wof:placetype":"venue"
},
  "geometry": {"coordinates":[121.472717285,-30.7448635101],"type":"Point"}
}