{
  "type": "Feature",
  "properties": {
    "addr:full":"2/ 7 Young St Vaucluse NSW 2030",
    "addr:housenumber":"/ 7",
    "addr:postcode":"2030",
    "addr:street":"Young St",
    "iso:country":"AU",
    "sg:address":"2/ 7 Young St",
    "sg:city":"Vaucluse",
    "sg:classifiers":[
        {
            "category":"Building & Trades",
            "subcategory":"Plumbing",
            "type":"Services"
        }
    ],
    "sg:phone":"+61 414 445 727",
    "sg:postcode":"2030",
    "sg:province":"NSW",
    "sg:tags":[
        "plumber",
        "gasfitters"
    ],
    "wof:name":"Steve The Plumber",
    "wof:placetype":"venue"
},
  "geometry": {"coordinates":[151.281738281,-33.8598251343],"type":"Point"}
}