{
  "type": "Feature",
  "properties": {
    "addr:full":"28 lemon St Mildura VIC 3500",
    "addr:housenumber":"28",
    "addr:postcode":"3500",
    "addr:street":"Lemon St",
    "iso:country":"AU",
    "sg:address":"28 lemon St",
    "sg:city":"Mildura",
    "sg:classifiers":[
        {
            "category":"Autos & Motor Vehicles",
            "subcategory":"Automobile Sales",
            "type":"Retail Goods"
        }
    ],
    "sg:phone":"+61 419 866 839",
    "sg:postcode":"3500",
    "sg:province":"VIC",
    "sg:tags":[
        "equipment",
        "trailer"
    ],
    "wof:name":"Mildura Custom Built Trailers",
    "wof:placetype":"venue"
},
  "geometry": {"coordinates":[142.166625977,-34.1872024536],"type":"Point"}
}