{
  "type": "Feature",
  "properties": {
    "addr:full":"5/ 83 Cox Ave Kingswood NSW 2747",
    "addr:housenumber":"/ 83",
    "addr:postcode":"2747",
    "addr:street":"Cox Ave",
    "iso:country":"AU",
    "sg:address":"5/ 83 Cox Ave",
    "sg:city":"Kingswood",
    "sg:classifiers":[
        {
            "category":"Retail",
            "subcategory":"Auto Repair",
            "type":"Services"
        }
    ],
    "sg:phone":"+61 2 4721 3675",
    "sg:postcode":"2747",
    "sg:province":"NSW",
    "sg:tags":[
        "repairer",
        "motor",
        "engineer"
    ],
    "wof:name":"KLR Automotive",
    "wof:placetype":"venue"
},
  "geometry": {"coordinates":[150.715606689,-33.756149292],"type":"Point"}
}