{
  "type": "Feature",
  "properties": {
    "addr:full":"25 Thompson St Cootamundra NSW 2590",
    "addr:housenumber":"25",
    "addr:postcode":"2590",
    "addr:street":"Thompson St",
    "iso:country":"AU",
    "sg:address":"25 Thompson St",
    "sg:city":"Cootamundra",
    "sg:classifiers":[
        {
            "category":"Health Services",
            "subcategory":"Doctor",
            "type":"Services"
        }
    ],
    "sg:phone":"+61 2 6942 2336",
    "sg:postcode":"2590",
    "sg:province":"NSW",
    "sg:tags":[
        "medical",
        "practitioner"
    ],
    "wof:name":"Datoo M R",
    "wof:placetype":"venue"
},
  "geometry": {"coordinates":[148.02943420400001,-34.6369132996],"type":"Point"}
}