{
  "type": "Feature",
  "properties": {
    "addr:full":"Cnr Bailey & Nicholson Sts Bairnsdale VIC 3875",
    "addr:postcode":"3875",
    "addr:street":"Cnr",
    "iso:country":"AU",
    "sg:address":"Cnr Bailey & Nicholson Sts",
    "sg:city":"Bairnsdale",
    "sg:classifiers":[
        {
            "category":"Personal",
            "subcategory":"Beauty Salon",
            "type":"Services"
        }
    ],
    "sg:phone":"+61 3 5153 1442",
    "sg:postcode":"3875",
    "sg:province":"VIC",
    "sg:tags":[
        "hairdresser"
    ],
    "wof:name":"Mirror Image Hair & Beauty",
    "wof:placetype":"venue"
},
  "geometry": {"coordinates":[147.61708068900001,-37.8277397156],"type":"Point"}
}