{
  "type": "Feature",
  "properties": {
    "addr:full":"73 Beach Rd Mentone VIC 3194",
    "addr:housenumber":"73",
    "addr:postcode":"3194",
    "addr:street":"Beach Rd",
    "iso:country":"AU",
    "sg:address":"73 Beach Rd",
    "sg:city":"Mentone",
    "sg:classifiers":[
        {
            "category":"Personal",
            "subcategory":"Beauty Salon",
            "type":"Services"
        }
    ],
    "sg:phone":"+61 3 9584 2210",
    "sg:postcode":"3194",
    "sg:province":"VIC",
    "sg:tags":[
        "hairdresser"
    ],
    "wof:name":"Ixi-Z Haircutters Workshop",
    "wof:placetype":"venue"
},
  "geometry": {"coordinates":[145.060424805,-37.9887962341],"type":"Point"}
}