{
  "type": "Feature",
  "properties": {
    "addr:full":"145 West Tamar Rd Launceston TAS 7250",
    "addr:housenumber":"145",
    "addr:postcode":"7250",
    "addr:street":"West Tamar Rd",
    "iso:country":"AU",
    "sg:address":"145 West Tamar Rd",
    "sg:city":"Launceston",
    "sg:classifiers":[
        {
            "category":"Organizations",
            "subcategory":"Professional Association",
            "type":"Services"
        }
    ],
    "sg:phone":"+61 1300 768 494",
    "sg:postcode":"7250",
    "sg:province":"TAS",
    "sg:tags":[
        "web",
        "internet"
    ],
    "wof:name":"Tassienet",
    "wof:placetype":"venue"
},
  "geometry": {"coordinates":[147.11369323700001,-41.4253845215],"type":"Point"}
}