{
  "type": "Feature",
  "properties": {
    "iso:country":"AU",
    "sg:address":"28 Monro Ave",
    "sg:city":"Kirrawee",
    "sg:classifiers":[
        {
            "category":"Wholesale",
            "subcategory":"Machinery & Supplies",
            "type":"Manufacturing & Wholesale Goods"
        }
    ],
    "sg:phone":"+61 2 9521 2177",
    "sg:postcode":"2232",
    "sg:province":"NSW",
    "sg:tags":[
        "equipment",
        "laboratory"
    ],
    "wof:name":"Bio-Scientific Pty Ltd",
    "wof:placetype":"venue"
},
  "geometry": {"coordinates":[151.07388305699999,-34.0311317444],"type":"Point"}
}