{
  "type": "Feature",
  "properties": {
    "addr:full":"26 Capricorn Ave Doncaster East VIC 3109",
    "addr:housenumber":"26",
    "addr:postcode":"3109",
    "addr:street":"Capricorn Ave",
    "iso:country":"AU",
    "sg:address":"26 Capricorn Ave",
    "sg:city":"Doncaster East",
    "sg:classifiers":[
        {
            "category":"Real Estate",
            "subcategory":"Real Estate Agent",
            "type":"Services"
        }
    ],
    "sg:phone":"+61 408 958 855",
    "sg:postcode":"3109",
    "sg:province":"VIC",
    "wof:name":"Danaher Realty",
    "wof:placetype":"venue"
},
  "geometry": {"coordinates":[145.16888427699999,-37.7795448303],"type":"Point"}
}