{
  "type": "Feature",
  "properties": {
    "addr:full":"17 Capua Pl Avalon NSW 2107",
    "addr:housenumber":"17",
    "addr:postcode":"2107",
    "addr:street":"Capua Pl",
    "iso:country":"AU",
    "sg:address":"17 Capua Pl",
    "sg:city":"Avalon",
    "sg:classifiers":[
        {
            "category":"Professional",
            "subcategory":"Engineering",
            "type":"Services"
        }
    ],
    "sg:phone":"+61 2 9918 3575",
    "sg:postcode":"2107",
    "sg:province":"NSW",
    "sg:tags":[
        "electronic",
        "engineer"
    ],
    "wof:name":"Champion Electronics",
    "wof:placetype":"venue"
},
  "geometry": {"coordinates":[151.320755005,-33.6279792786],"type":"Point"}
}