{
  "type": "Feature",
  "properties": {
    "iso:country":"AU",
    "sg:address":"1 Yabini Crt",
    "sg:city":"Bunbury",
    "sg:classifiers":[
        {
            "category":"Professional",
            "subcategory":"Business Services",
            "type":"Services"
        }
    ],
    "sg:phone":"+61 8 9721 6105",
    "sg:postcode":"6230",
    "sg:province":"WA",
    "sg:tags":[
        "drafting"
    ],
    "wof:name":"G & S Ghasseb Drafting",
    "wof:placetype":"venue"
},
  "geometry": {"coordinates":[115.621521,-33.355377],"type":"Point"}
}