{
  "type": "Feature",
  "properties": {
    "addr:full":"16 Degen Rd Capalaba QLD 4157",
    "addr:housenumber":"16",
    "addr:postcode":"4157",
    "addr:street":"Degen Rd",
    "iso:country":"AU",
    "sg:address":"16 Degen Rd",
    "sg:city":"Capalaba",
    "sg:classifiers":[
        {
            "category":"Building & Trades",
            "subcategory":"Construction",
            "type":"Services"
        }
    ],
    "sg:phone":"+61 7 3245 6110",
    "sg:postcode":"4157",
    "sg:province":"QLD",
    "sg:tags":[
        "contractor"
    ],
    "wof:name":"Toscano Constructions Pty Ltd",
    "wof:placetype":"venue"
},
  "geometry": {"coordinates":[153.19937133799999,-27.5499687195],"type":"Point"}
}