{
  "type": "Feature",
  "properties": {
    "addr:full":"Ballard St Comet QLD 4702",
    "addr:postcode":"4702",
    "addr:street":"Ballard St",
    "iso:country":"AU",
    "sg:address":"Ballard St",
    "sg:city":"Comet",
    "sg:classifiers":[
        {
            "category":"Travel",
            "subcategory":"Hotels & Motels",
            "type":"Entertainment"
        }
    ],
    "sg:phone":"+61 7 4984 5133",
    "sg:postcode":"4702",
    "sg:province":"QLD",
    "sg:tags":[
        "accommodation"
    ],
    "wof:name":"Comet Hotel",
    "wof:placetype":"venue"
},
  "geometry": {"coordinates":[148.547805786,-23.6050071716],"type":"Point"}
}