{
  "type": "Feature",
  "properties": {
    "iso:country":"AU",
    "sg:address":"40 Power St",
    "sg:city":"Dandenong",
    "sg:classifiers":[
        {
            "category":"Banks & Credit Unions",
            "subcategory":"Financial Services",
            "type":"Services"
        }
    ],
    "sg:phone":"+61 3 9794 8841",
    "sg:postcode":"3175",
    "sg:province":"VIC",
    "sg:tags":[
        "financier"
    ],
    "wof:name":"Developmentofall Pty Ltd",
    "wof:placetype":"venue"
},
  "geometry": {"coordinates":[145.22547912600001,-37.9893836975],"type":"Point"}
}