{
  "type": "Feature",
  "properties": {
    "addr:full":"Quadrant Business Park 3/ 15 Pickering St Mulgrave VIC 3170",
    "addr:housenumber":"/ 15",
    "addr:postcode":"3170",
    "addr:street":"Park;Pickering St",
    "iso:country":"AU",
    "sg:address":"Quadrant Business Park 3/ 15 Pickering St",
    "sg:city":"Mulgrave",
    "sg:classifiers":[
        {
            "category":"Utilities",
            "subcategory":"Telephone",
            "type":"Services"
        }
    ],
    "sg:phone":"+61 3 8562 0112",
    "sg:postcode":"3170",
    "sg:province":"VIC",
    "sg:tags":[
        "equipment",
        "system"
    ],
    "wof:name":"Aria Communications",
    "wof:placetype":"venue"
},
  "geometry": {"coordinates":[145.15428161599999,-37.9071655273],"type":"Point"}
}