{
  "type": "Feature",
  "properties": {
    "addr:full":"Railway Ave Merredin WA 6415",
    "addr:postcode":"6415",
    "addr:street":"Railway Ave",
    "iso:country":"AU",
    "sg:address":"Railway Ave",
    "sg:city":"Merredin",
    "sg:classifiers":[
        {
            "category":"Building & Trades",
            "subcategory":"Landscaping Services",
            "type":"Services"
        }
    ],
    "sg:phone":"+61 8 9041 3390",
    "sg:postcode":"6415",
    "sg:province":"WA",
    "sg:tags":[
        "control",
        "weed"
    ],
    "wof:name":"CWC Professional Ag Contractors",
    "wof:placetype":"venue"
},
  "geometry": {"coordinates":[118.271659851,-31.4816169739],"type":"Point"}
}