{
  "type": "Feature",
  "properties": {
    "addr:full":"12 Horace St Oberon NSW 2787",
    "addr:housenumber":"12",
    "addr:postcode":"2787",
    "addr:street":"Horace St",
    "iso:country":"AU",
    "sg:address":"12 Horace St",
    "sg:city":"Oberon",
    "sg:classifiers":[
        {
            "category":"Home & Garden",
            "subcategory":"Building Materials",
            "type":"Retail Goods"
        }
    ],
    "sg:phone":"+61 2 6336 0033",
    "sg:postcode":"2787",
    "sg:province":"NSW",
    "sg:tags":[
        "pre-mixed",
        "concrete"
    ],
    "wof:name":"Readymix",
    "wof:placetype":"venue"
},
  "geometry": {"coordinates":[149.859085083,-33.69739151],"type":"Point"}
}