{
  "type": "Feature",
  "properties": {
    "iso:country":"AU",
    "sg:address":"18- 22 Bancell St",
    "sg:city":"Campbellfield",
    "sg:classifiers":[
        {
            "category":"Professional",
            "type":"Services"
        }
    ],
    "sg:phone":"+61 3 9357 4433",
    "sg:postcode":"3061",
    "sg:province":"VIC",
    "sg:tags":[
        "shop",
        "fitting"
    ],
    "wof:name":"Downunder Exhibitions Pty Ltd",
    "wof:placetype":"venue"
},
  "geometry": {"coordinates":[144.96429443400001,-37.6827888489],"type":"Point"}
}