{
  "type": "Feature",
  "properties": {
    "addr:full":"337 Main Rd Emerald VIC 3782",
    "addr:housenumber":"337",
    "addr:postcode":"3782",
    "addr:street":"Main Rd",
    "iso:country":"AU",
    "sg:address":"337 Main Rd",
    "sg:city":"Emerald",
    "sg:classifiers":[
        {
            "category":"Health Services",
            "subcategory":"Dentist",
            "type":"Services"
        }
    ],
    "sg:phone":"+61 3 5968 5736",
    "sg:postcode":"3782",
    "sg:province":"VIC",
    "wof:name":"Emerald Family Dental Care",
    "wof:placetype":"venue"
},
  "geometry": {"coordinates":[145.441193,-37.932167],"type":"Point"}
}