{
  "type": "Feature",
  "properties": {
    "iso:country":"AU",
    "sg:address":"9-17 Young St",
    "sg:city":"Neutral Bay",
    "sg:classifiers":[
        {
            "category":"Education",
            "subcategory":"Dance Studio",
            "type":"Public Place"
        }
    ],
    "sg:phone":"+61 2 9953 0603",
    "sg:postcode":"2089",
    "sg:province":"NSW",
    "sg:tags":[
        "venue",
        "tuition"
    ],
    "wof:name":"Flamencology Dance Studio",
    "wof:placetype":"venue"
},
  "geometry": {"coordinates":[151.22148132300001,-33.8308143616],"type":"Point"}
}