{
  "type": "Feature",
  "properties": {
    "addr:full":"6 Swallow St Macleay Island QLD 4184",
    "addr:housenumber":"6",
    "addr:postcode":"4184",
    "addr:street":"Swallow St",
    "iso:country":"AU",
    "sg:address":"6 Swallow St",
    "sg:city":"Macleay Island",
    "sg:classifiers":[
        {
            "category":"Building & Trades",
            "subcategory":"Landscaping Services",
            "type":"Services"
        }
    ],
    "sg:phone":"+61 408 151 730",
    "sg:postcode":"4184",
    "sg:province":"QLD",
    "sg:tags":[
        "stump",
        "tree",
        "felling",
        "removal"
    ],
    "wof:name":"The Gutter Guys",
    "wof:placetype":"venue"
},
  "geometry": {"coordinates":[153.351165772,-27.6096897125],"type":"Point"}
}