{
  "type": "Feature",
  "properties": {
    "addr:full":"252 Hyde St Yarraville VIC 3013",
    "addr:housenumber":"252",
    "addr:postcode":"3013",
    "addr:street":"Hyde St",
    "iso:country":"AU",
    "sg:address":"252 Hyde St",
    "sg:city":"Yarraville",
    "sg:classifiers":[
        {
            "category":"Banks & Credit Unions",
            "subcategory":"Bank",
            "type":"Services"
        }
    ],
    "sg:phone":"+61 3 9689 9999",
    "sg:postcode":"3013",
    "sg:province":"VIC",
    "sg:tags":[
        "line",
        "marking",
        "road"
    ],
    "wof:name":"Kirwan Linemarking Contractors",
    "wof:placetype":"venue"
},
  "geometry": {"coordinates":[144.89584350600001,-37.8210372925],"type":"Point"}
}