{
  "type": "Feature",
  "properties": {
    "addr:full":"64-70 Oke St Ouyen VIC 3490",
    "addr:housenumber":"64-70",
    "addr:postcode":"3490",
    "addr:street":"Oke St",
    "iso:country":"AU",
    "sg:address":"64-70 Oke St",
    "sg:city":"Ouyen",
    "sg:classifiers":[
        {
            "category":"Food & Beverages",
            "subcategory":"Supermarket",
            "type":"Retail Goods"
        }
    ],
    "sg:phone":"+61 3 5092 1383",
    "sg:postcode":"3490",
    "sg:province":"VIC",
    "sg:tags":[
        "grocery",
        "store"
    ],
    "wof:name":"Jason's I.G.A. Plus Liquor",
    "wof:placetype":"venue"
},
  "geometry": {"coordinates":[142.31463623100001,-35.0673484802],"type":"Point"}
}