{
  "type": "Feature",
  "properties": {
    "iso:country":"AU",
    "sg:address":"7-Lot 55 Shanahan Rd",
    "sg:city":"Bunbury",
    "sg:classifiers":[
        {
            "category":"Retail",
            "subcategory":"Storage",
            "type":"Services"
        }
    ],
    "sg:phone":"+61 8 9726 2650",
    "sg:postcode":"6230",
    "sg:province":"WA",
    "sg:tags":[
        "removal",
        "furniture"
    ],
    "wof:name":"Wridgways",
    "wof:placetype":"venue"
},
  "geometry": {"coordinates":[115.67266100000001,-33.364113],"type":"Point"}
}