{
  "type": "Feature",
  "properties": {
    "addr:full":"PO Box 33 Potts Point NSW 1335",
    "addr:postcode":"1335",
    "iso:country":"AU",
    "sg:address":"PO Box 33",
    "sg:city":"Potts Point",
    "sg:classifiers":[
        {
            "category":"Health Services",
            "subcategory":"Health Practitioner",
            "type":"Services"
        }
    ],
    "sg:phone":"+61 2 9357 5557",
    "sg:postcode":"1335",
    "sg:province":"NSW",
    "sg:tags":[
        "psychotherapist"
    ],
    "wof:name":"Coggins Caroline",
    "wof:placetype":"venue"
},
  "geometry": {"coordinates":[151.223678589,-33.8665313721],"type":"Point"}
}