{
  "type": "Feature",
  "properties": {
    "addr:full":"Shop 317A, Greensborough Shopping Cntr 25 Main Greensborough VIC 3088",
    "addr:housenumber":"317a;25",
    "addr:postcode":"3088",
    "addr:street":"Greensborough Shopping Cntr;Main",
    "iso:country":"AU",
    "sg:address":"Shop 317A, Greensborough Shopping Cntr 25 Main",
    "sg:city":"Greensborough",
    "sg:classifiers":[
        {
            "category":"Shopping",
            "subcategory":"Mobile Phones",
            "type":"Retail Goods"
        }
    ],
    "sg:phone":"+61 3 9434 2733",
    "sg:postcode":"3088",
    "sg:province":"VIC",
    "sg:tags":[
        "telephone",
        "accessory"
    ],
    "wof:name":"C2One# Communications#",
    "wof:placetype":"venue"
},
  "geometry": {"coordinates":[145.08177185100001,-37.7151069641],"type":"Point"}
}