{
  "type": "Feature",
  "properties": {
    "iso:country":"AU",
    "sg:address":"Unit 10, 121 Gormandston Rd",
    "sg:city":"Derwent Park",
    "sg:classifiers":[
        {
            "category":"Shopping",
            "subcategory":"Optical Goods",
            "type":"Retail Goods"
        }
    ],
    "sg:phone":"+61 3 6272 1785",
    "sg:postcode":"7009",
    "sg:province":"TAS",
    "sg:tags":[
        "supply"
    ],
    "wof:name":"Longman Optical",
    "wof:placetype":"venue"
},
  "geometry": {"coordinates":[147.297729492,-42.8359489441],"type":"Point"}
}