{
  "type": "Feature",
  "properties": {
    "addr:full":"55 Bourke St Launceston TAS 7250",
    "addr:housenumber":"55",
    "addr:postcode":"7250",
    "addr:street":"Bourke St",
    "iso:country":"AU",
    "sg:address":"55 Bourke St",
    "sg:city":"Launceston",
    "sg:classifiers":[
        {
            "category":"Education",
            "subcategory":"School",
            "type":"Public Place"
        }
    ],
    "sg:phone":"+61 3 6331 1011",
    "sg:postcode":"7250",
    "sg:province":"TAS",
    "wof:name":"Sacred Heart School",
    "wof:placetype":"venue"
},
  "geometry": {"coordinates":[147.132614136,-41.443523407],"type":"Point"}
}