{
  "type": "Feature",
  "properties": {
    "addr:full":"26 Bourke St Blacks Beach QLD 4740",
    "addr:housenumber":"26",
    "addr:postcode":"4740",
    "addr:street":"Bourke St",
    "iso:country":"AU",
    "sg:address":"26 Bourke St",
    "sg:city":"Blacks Beach",
    "sg:classifiers":[
        {
            "category":"Retail",
            "subcategory":"Event Space",
            "type":"Services"
        }
    ],
    "sg:phone":"+61 7 4969 6250",
    "sg:postcode":"4740",
    "sg:province":"QLD",
    "sg:tags":[
        "venue",
        "reception",
        "wedding"
    ],
    "wof:name":"Melaleucas Restaurant & Conference Centre",
    "wof:placetype":"venue"
},
  "geometry": {"coordinates":[149.18959000000001,-21.054316],"type":"Point"}
}