{
  "type": "Feature",
  "properties": {
    "addr:full":"7 Victor St Chatswood NSW 2067",
    "addr:housenumber":"7",
    "addr:postcode":"2067",
    "addr:street":"Victor St",
    "iso:country":"AU",
    "sg:address":"7 Victor St",
    "sg:city":"Chatswood",
    "sg:classifiers":[
        {
            "category":"Organizations",
            "subcategory":"Non-profit Organization",
            "type":"Services"
        }
    ],
    "sg:phone":"+61 2 9777 7840",
    "sg:postcode":"2067",
    "sg:province":"NSW",
    "sg:tags":[
        "support",
        "disability",
        "organisation"
    ],
    "wof:name":"Disabled Alternative Road Travel Service",
    "wof:placetype":"venue"
},
  "geometry": {"coordinates":[151.183151245,-33.7990722656],"type":"Point"}
}