{
  "type": "Feature",
  "properties": {
    "iso:country":"AU",
    "sg:address":"70 Eastern Rd",
    "sg:city":"Turramurra",
    "sg:classifiers":[
        {
            "category":"Professional",
            "subcategory":"Art Services",
            "type":"Services"
        }
    ],
    "sg:phone":"+61 2 9489 2075",
    "sg:postcode":"2074",
    "sg:province":"NSW",
    "sg:tags":[
        "picture",
        "frame",
        "framing"
    ],
    "wof:name":"Pallas Gallery The",
    "wof:placetype":"venue"
},
  "geometry": {"coordinates":[151.130004883,-33.7241401672],"type":"Point"}
}