{
  "type": "Feature",
  "properties": {
    "addr:full":"Kingston Dr Australind WA 6233",
    "addr:postcode":"6233",
    "addr:street":"Kingston Dr",
    "iso:country":"AU",
    "sg:address":"Kingston Dr",
    "sg:city":"Australind",
    "sg:classifiers":[
        {
            "category":"Cafe",
            "type":"Food & Drink"
        }
    ],
    "sg:phone":"+61 8 9796 0114",
    "sg:postcode":"6233",
    "sg:province":"WA",
    "wof:name":"Kingston Supa Deli & Cafe",
    "wof:placetype":"venue"
},
  "geometry": {"coordinates":[115.742722,-33.264835],"type":"Point"}
}