{
  "type": "Feature",
  "properties": {
    "addr:full":"PO Box 95 Austinmer NSW 2515",
    "addr:postcode":"2515",
    "iso:country":"AU",
    "sg:address":"PO Box 95",
    "sg:city":"Austinmer",
    "sg:classifiers":[
        {
            "category":"Real Estate",
            "subcategory":"Real Estate Services",
            "type":"Services"
        }
    ],
    "sg:phone":"+61 2 4268 6133",
    "sg:postcode":"2515",
    "sg:province":"NSW",
    "sg:tags":[
        "valuer"
    ],
    "wof:name":"Malcolm Craig & Associates",
    "wof:placetype":"venue"
},
  "geometry": {"coordinates":[150.93481399999999,-34.305931],"type":"Point"}
}