{
  "type": "Feature",
  "properties": {
    "addr:full":"36 High St Toowong QLD 4066",
    "addr:housenumber":"36",
    "addr:postcode":"4066",
    "addr:street":"High St",
    "iso:country":"AU",
    "sg:address":"36 High St",
    "sg:city":"Toowong",
    "sg:classifiers":[
        {
            "category":"Real Estate",
            "subcategory":"Real Estate Agent",
            "type":"Services"
        }
    ],
    "sg:phone":"+61 7 3371 9991",
    "sg:postcode":"4066",
    "sg:province":"QLD",
    "wof:name":"Rialto Real Estate Agents Toowong",
    "wof:placetype":"venue"
},
  "geometry": {"coordinates":[152.991821289,-27.4866638184],"type":"Point"}
}