{
  "type": "Feature",
  "properties": {
    "addr:full":"50 Creek Reserve Rd Boolaroo NSW 2284",
    "addr:housenumber":"50",
    "addr:postcode":"2284",
    "addr:street":"Creek Reserve Rd",
    "iso:country":"AU",
    "sg:address":"50 Creek Reserve Rd",
    "sg:city":"Boolaroo",
    "sg:classifiers":[
        {
            "category":"Wholesale",
            "subcategory":"Machinery & Supplies",
            "type":"Manufacturing & Wholesale Goods"
        }
    ],
    "sg:phone":"+61 2 4950 8000",
    "sg:postcode":"2284",
    "sg:province":"NSW",
    "sg:tags":[
        "equipment",
        "hydraulic"
    ],
    "wof:name":"Accumulators. Q. H. P.",
    "wof:placetype":"venue"
},
  "geometry": {"coordinates":[151.62373352,-32.9430465698],"type":"Point"}
}