{
  "type": "Feature",
  "properties": {
    "iso:country":"AU",
    "sg:address":"15- 17 West Fyans St",
    "sg:city":"Newtown",
    "sg:classifiers":[
        {
            "category":"Home & Garden",
            "subcategory":"Carpets & Floor Coverings",
            "type":"Retail Goods"
        }
    ],
    "sg:phone":"+61 3 5224 2941",
    "sg:postcode":"3351",
    "sg:province":"VIC",
    "sg:tags":[
        "tile",
        "wall"
    ],
    "wof:name":"Tile Mart",
    "wof:placetype":"venue"
},
  "geometry": {"coordinates":[143.66409300000001,-37.706371],"type":"Point"}
}