{
  "type": "Feature",
  "properties": {
    "addr:full":"45 Drummond St Belmore NSW 2192",
    "addr:housenumber":"45",
    "addr:postcode":"2192",
    "addr:street":"Drummond St",
    "iso:country":"AU",
    "sg:address":"45 Drummond St",
    "sg:city":"Belmore",
    "sg:classifiers":[
        {
            "category":"Government",
            "subcategory":"Department Of Motor Vehicles",
            "type":"Public Place"
        }
    ],
    "sg:phone":"+61 2 9787 1444",
    "sg:postcode":"2192",
    "sg:province":"NSW",
    "sg:tags":[
        "wholesaler",
        "mfrs",
        "accessory"
    ],
    "wof:name":"Universal Spares",
    "wof:placetype":"venue"
},
  "geometry": {"coordinates":[151.091995,-33.922504],"type":"Point"}
}