{
  "type": "Feature",
  "properties": {
    "addr:full":"8 Hartwick Crt Mt Duneed VIC 3216",
    "addr:housenumber":"8",
    "addr:postcode":"3216",
    "addr:street":"Hartwick Crt Mt Duneed",
    "iso:country":"AU",
    "sg:address":"8 Hartwick Crt",
    "sg:city":"Mt Duneed",
    "sg:classifiers":[
        {
            "category":"Utilities",
            "subcategory":"Refuse",
            "type":"Services"
        }
    ],
    "sg:phone":"+61 418 923 772",
    "sg:postcode":"3216",
    "sg:province":"VIC",
    "sg:tags":[
        "remover",
        "rubbish"
    ],
    "wof:name":"Bay City Waste Containers",
    "wof:placetype":"venue"
},
  "geometry": {"coordinates":[144.31956481899999,-38.206703186],"type":"Point"}
}