{
  "type": "Feature",
  "properties": {
    "addr:full":"Oldford St Davoren Park SA 5113",
    "addr:postcode":"5113",
    "iso:country":"AU",
    "sg:address":"Oldford St",
    "sg:city":"Davoren Park",
    "sg:classifiers":[
        {
            "category":"Education",
            "subcategory":"School",
            "type":"Public Place"
        }
    ],
    "sg:phone":"+61 8 8287 1866",
    "sg:postcode":"5113",
    "sg:province":"SA",
    "sg:tags":[
        "state",
        "except",
        "nsw"
    ],
    "wof:name":"Swallowcliffe Primary Out Of School Hours Care",
    "wof:placetype":"venue"
},
  "geometry": {"coordinates":[138.664672852,-34.6967353821],"type":"Point"}
}