{
  "type": "Feature",
  "properties": {
    "addr:full":"23 McGeehan Crs Myrtleford VIC 3737",
    "addr:housenumber":"23",
    "addr:postcode":"3737",
    "addr:street":"Mcgeehan Crs",
    "iso:country":"AU",
    "sg:address":"23 McGeehan Crs",
    "sg:city":"Myrtleford",
    "sg:classifiers":[
        {
            "category":"Professional",
            "subcategory":"Engineering",
            "type":"Services"
        }
    ],
    "sg:phone":"+61 3 5752 2474",
    "sg:postcode":"3737",
    "sg:province":"VIC",
    "sg:tags":[
        "precision",
        "engineer"
    ],
    "wof:name":"TJD Engineering Pty Ltd",
    "wof:placetype":"venue"
},
  "geometry": {"coordinates":[146.71754455600001,-36.553440094],"type":"Point"}
}