{
  "type": "Feature",
  "properties": {
    "iso:country":"AU",
    "sg:address":"Shop 4- 5",
    "sg:city":"Pacific Fair Broadbeach",
    "sg:classifiers":[
        {
            "category":"Personal",
            "subcategory":"Beauty Salon",
            "type":"Services"
        }
    ],
    "sg:phone":"+61 7 5575 5545",
    "sg:postcode":"4218",
    "sg:province":"QLD",
    "sg:tags":[
        "hairdresser"
    ],
    "wof:name":"Rodney Wayne",
    "wof:placetype":"venue"
},
  "geometry": {"coordinates":[153.43754577600001,-28.0635948181],"type":"Point"}
}