{
  "type": "Feature",
  "properties": {
    "iso:country":"AU",
    "sg:address":"PO Box 513",
    "sg:city":"Palmwoods",
    "sg:classifiers":[
        {
            "category":"Mining & Drilling",
            "type":"Manufacturing & Wholesale Goods"
        }
    ],
    "sg:phone":"+61 7 5445 0799",
    "sg:postcode":"4555",
    "sg:province":"QLD",
    "sg:tags":[
        "boring",
        "contractor"
    ],
    "wof:name":"Colliers Under Road Boring Pty Ltd",
    "wof:placetype":"venue"
},
  "geometry": {"coordinates":[152.956207275,-26.6875400543],"type":"Point"}
}