{
  "type": "Feature",
  "properties": {
    "addr:full":"13 Lawndale Ave North Rocks NSW 2151",
    "addr:housenumber":"13",
    "addr:postcode":"2151",
    "addr:street":"Lawndale Ave",
    "iso:country":"AU",
    "sg:address":"13 Lawndale Ave",
    "sg:city":"North Rocks",
    "sg:classifiers":[
        {
            "category":"Shopping",
            "subcategory":"Computers & Home Electronics",
            "type":"Retail Goods"
        }
    ],
    "sg:phone":"+61 2 9873 3377",
    "sg:postcode":"2151",
    "sg:province":"NSW",
    "sg:tags":[
        "hi-fi",
        "equipment"
    ],
    "wof:name":"Panasonic Independent Retailer & Service",
    "wof:placetype":"venue"
},
  "geometry": {"coordinates":[151.02577209500001,-33.7693328857],"type":"Point"}
}