{
  "type": "Feature",
  "properties": {
    "addr:full":"2 Jorja Pl Kellyville NSW 2155",
    "addr:housenumber":"2",
    "addr:postcode":"2155",
    "addr:street":"Jorja Pl",
    "iso:country":"AU",
    "sg:address":"2 Jorja Pl",
    "sg:city":"Kellyville",
    "sg:classifiers":[
        {
            "category":"Building & Trades",
            "subcategory":"Plumbing",
            "type":"Services"
        }
    ],
    "sg:phone":"+61 2 9629 3300",
    "sg:postcode":"2155",
    "sg:province":"NSW",
    "sg:tags":[
        "plumber",
        "gasfitters"
    ],
    "wof:name":"Parnell A",
    "wof:placetype":"venue"
},
  "geometry": {"coordinates":[150.95445251500001,-33.701625824],"type":"Point"}
}