{
  "type": "Feature",
  "properties": {
    "iso:country":"AU",
    "sg:address":"PO Box 320",
    "sg:city":"Ramsgate",
    "sg:classifiers":[
        {
            "category":"Retail",
            "subcategory":"Auto Rental",
            "type":"Services"
        }
    ],
    "sg:phone":"+61 2 9587 3446",
    "sg:postcode":"2217",
    "sg:province":"NSW",
    "sg:tags":[
        "chauffeur",
        "car",
        "hire",
        "driven",
        "limousine"
    ],
    "wof:name":"Convertible Wedding Cars",
    "wof:placetype":"venue"
},
  "geometry": {"coordinates":[151.13807700000001,-33.984421],"type":"Point"}
}