{
  "type": "Feature",
  "properties": {
    "addr:full":"49 Queen St Blackstone QLD 4304",
    "addr:housenumber":"49",
    "addr:postcode":"4304",
    "addr:street":"Queen St",
    "iso:country":"AU",
    "sg:address":"49 Queen St",
    "sg:city":"Blackstone",
    "sg:classifiers":[
        {
            "category":"Retail",
            "subcategory":"Auto Repair",
            "type":"Services"
        }
    ],
    "sg:phone":"+61 7 3282 4606",
    "sg:postcode":"4304",
    "sg:province":"QLD",
    "sg:tags":[
        "repairer",
        "motor",
        "engineer"
    ],
    "wof:name":"Blackstone Auto Repairs",
    "wof:placetype":"venue"
},
  "geometry": {"coordinates":[152.805252075,-27.6237812042],"type":"Point"}
}