{
  "type": "Feature",
  "properties": {
    "iso:country":"AU",
    "sg:address":"PO Box 88",
    "sg:city":"Underwood",
    "sg:classifiers":[
        {
            "category":"Professional",
            "subcategory":"Detective & Security Services",
            "type":"Services"
        }
    ],
    "sg:phone":"+61 7 3341 6900",
    "sg:postcode":"4119",
    "sg:province":"QLD",
    "sg:tags":[
        "consultant",
        "system"
    ],
    "wof:name":"Citysafe Security (Qld)",
    "wof:placetype":"venue"
},
  "geometry": {"coordinates":[153.11244201700001,-27.6068191528],"type":"Point"}
}