{
  "type": "Feature",
  "properties": {
    "addr:full":"151- 153 Scott St Cairns QLD 4870",
    "addr:housenumber":"153",
    "addr:postcode":"4870",
    "addr:street":"Scott St",
    "iso:country":"AU",
    "sg:address":"151- 153 Scott St",
    "sg:city":"Cairns",
    "sg:classifiers":[
        {
            "category":"Wholesale",
            "subcategory":"Machinery & Supplies",
            "type":"Manufacturing & Wholesale Goods"
        }
    ],
    "sg:phone":"+61 7 4051 2266",
    "sg:postcode":"4870",
    "sg:province":"QLD",
    "sg:tags":[
        "engineer"
    ],
    "wof:name":"Atkins Carlyl Ltd",
    "wof:placetype":"venue"
},
  "geometry": {"coordinates":[145.756103516,-16.9373245239],"type":"Point"}
}