{
  "type": "Feature",
  "properties": {
    "iso:country":"AU",
    "sg:address":"Warehouse 3, 37 Collins St",
    "sg:city":"Kangaroo Flat",
    "sg:classifiers":[
        {
            "category":"Manufacturing",
            "subcategory":"Paper Products",
            "type":"Manufacturing & Wholesale Goods"
        }
    ],
    "sg:phone":"+61 3 5447 0954",
    "sg:postcode":"3555",
    "sg:province":"VIC",
    "sg:tags":[
        "bag"
    ],
    "wof:name":"Threlfall Packaging",
    "wof:placetype":"venue"
},
  "geometry": {"coordinates":[144.23265075699999,-36.7935752869],"type":"Point"}
}