{
  "type": "Feature",
  "properties": {
    "addr:full":"309 Lonsdale St Dandenong VIC 3175",
    "addr:housenumber":"309",
    "addr:postcode":"3175",
    "addr:street":"Lonsdale St",
    "iso:country":"AU",
    "sg:address":"309 Lonsdale St",
    "sg:city":"Dandenong",
    "sg:classifiers":[
        {
            "category":"Fast Food",
            "type":"Food & Drink"
        }
    ],
    "sg:phone":"+61 3 9793 3998",
    "sg:postcode":"3175",
    "sg:province":"VIC",
    "sg:tags":[
        "away",
        "take"
    ],
    "wof:name":"Fresh Noodles",
    "wof:placetype":"venue"
},
  "geometry": {"coordinates":[145.21383667000001,-37.9863471985],"type":"Point"}
}