{
  "type": "Feature",
  "properties": {
    "addr:full":"Kangaroo Point Marina Pacific Hwy Brooklyn NSW 2083",
    "addr:postcode":"2083",
    "addr:street":"Pacific Hwy",
    "iso:country":"AU",
    "sg:address":"Kangaroo Point Marina Pacific Hwy",
    "sg:city":"Brooklyn",
    "sg:classifiers":[
        {
            "category":"Recreation",
            "subcategory":"Boat Charter",
            "type":"Entertainment"
        }
    ],
    "sg:phone":"+61 2 9985 7344",
    "sg:postcode":"2083",
    "sg:province":"NSW",
    "sg:tags":[
        "hire",
        "drive"
    ],
    "wof:name":"Sydney's Hawkesbury Houseboats Holidays",
    "wof:placetype":"venue"
},
  "geometry": {"coordinates":[151.17124939000001,-33.596622467],"type":"Point"}
}