{
  "type": "Feature",
  "properties": {
    "iso:country":"AU",
    "sg:address":"105 Wentworth St",
    "sg:city":"South Hobart",
    "sg:classifiers":[
        {
            "category":"Professional",
            "subcategory":"Art Services",
            "type":"Services"
        }
    ],
    "sg:phone":"+61 3 6223 2002",
    "sg:postcode":"7004",
    "sg:province":"TAS",
    "sg:tags":[
        "interior",
        "decorator"
    ],
    "wof:name":"Harmon W F",
    "wof:placetype":"venue"
},
  "geometry": {"coordinates":[147.300292969,-42.8965492249],"type":"Point"}
}