{
  "type": "Feature",
  "properties": {
    "addr:full":"44 Butcher St Strathdale VIC 3550",
    "addr:housenumber":"44",
    "addr:postcode":"3550",
    "addr:street":"Butcher St",
    "iso:country":"AU",
    "sg:address":"44 Butcher St",
    "sg:city":"Strathdale",
    "sg:classifiers":[
        {
            "category":"Professional",
            "subcategory":"Art Services",
            "type":"Services"
        }
    ],
    "sg:phone":"+61 3 5441 6109",
    "sg:postcode":"3550",
    "sg:province":"VIC",
    "sg:tags":[
        "decorator",
        "painter"
    ],
    "wof:name":"Berry David",
    "wof:placetype":"venue"
},
  "geometry": {"coordinates":[144.317993164,-36.7745552063],"type":"Point"}
}