{
  "type": "Feature",
  "properties": {
    "addr:full":"913 - 915 Beaufort St Inglewood WA 6052",
    "addr:housenumber":"915",
    "addr:postcode":"6052",
    "addr:street":"Beaufort St",
    "iso:country":"AU",
    "sg:address":"913 - 915 Beaufort St",
    "sg:city":"Inglewood",
    "sg:classifiers":[
        {
            "category":"Professional",
            "type":"Services"
        }
    ],
    "sg:phone":"+61 8 9271 6273",
    "sg:postcode":"6052",
    "sg:province":"WA",
    "sg:tags":[
        "overlocking",
        "rug",
        "carpet"
    ],
    "wof:name":"Stan's Rug Centre",
    "wof:placetype":"venue"
},
  "geometry": {"coordinates":[115.886642456,-31.9209861755],"type":"Point"}
}