{
  "type": "Feature",
  "properties": {
    "iso:country":"AU",
    "sg:address":"1 Marine Drv",
    "sg:city":"Wollongong",
    "sg:classifiers":[
        {
            "category":"Restaurant",
            "type":"Food & Drink"
        }
    ],
    "sg:phone":"+61 2 4228 7111",
    "sg:postcode":"2500",
    "sg:province":"NSW",
    "wof:name":"Dunes RCB",
    "wof:placetype":"venue"
},
  "geometry": {"coordinates":[150.906113,-34.422699],"type":"Point"}
}