{
  "type": "Feature",
  "properties": {
    "iso:country":"AU",
    "sg:address":"195 Howick St",
    "sg:city":"Bathurst",
    "sg:classifiers":[
        {
            "category":"Fast Food",
            "type":"Food & Drink"
        }
    ],
    "sg:phone":"+61 2 6332 2966",
    "sg:postcode":"2795",
    "sg:province":"NSW",
    "sg:tags":[
        "away",
        "take"
    ],
    "wof:name":"Uncle Joes Pizzas",
    "wof:placetype":"venue"
},
  "geometry": {"coordinates":[149.58050537099999,-33.4160385132],"type":"Point"}
}