{
  "type": "Feature",
  "properties": {
    "addr:full":"Evans St Woodville SA 5011",
    "addr:postcode":"5011",
    "addr:street":"Evans St",
    "iso:country":"AU",
    "sg:address":"Evans St",
    "sg:city":"Woodville",
    "sg:classifiers":[
        {
            "category":"Education",
            "subcategory":"School",
            "type":"Public Place"
        }
    ],
    "sg:phone":"+61 8 8243 2454",
    "sg:postcode":"5011",
    "sg:province":"SA",
    "sg:tags":[
        "state",
        "except",
        "nsw"
    ],
    "wof:name":"Woodville Primary After School Care Centre",
    "wof:placetype":"venue"
},
  "geometry": {"coordinates":[138.53155517600001,-34.8805351257],"type":"Point"}
}