{
  "type": "Feature",
  "properties": {
    "addr:full":"296 Ryans Rd Eltham North VIC 3095",
    "addr:housenumber":"296",
    "addr:postcode":"3095",
    "addr:street":"Ryans Rd",
    "iso:country":"AU",
    "sg:address":"296 Ryans Rd",
    "sg:city":"Eltham North",
    "sg:classifiers":[
        {
            "category":"Social Services",
            "subcategory":"Child Care",
            "type":"Services"
        }
    ],
    "sg:phone":"+61 3 9431 4947",
    "sg:postcode":"3095",
    "sg:province":"VIC",
    "wof:name":"Eltham North Child Care",
    "wof:placetype":"venue"
},
  "geometry": {"coordinates":[145.14251709000001,-37.6901550293],"type":"Point"}
}