{
  "type": "Feature",
  "properties": {
    "iso:country":"AU",
    "sg:address":"Leetes La",
    "sg:city":"Budgewoi",
    "sg:classifiers":[
        {
            "category":"Building & Trades",
            "subcategory":"Construction",
            "type":"Services"
        }
    ],
    "sg:phone":"+61 409 625 665",
    "sg:postcode":"2262",
    "sg:province":"NSW",
    "sg:tags":[
        "earth",
        "excavating",
        "moving",
        "contractor"
    ],
    "wof:name":"McKool Site Works",
    "wof:placetype":"venue"
},
  "geometry": {"coordinates":[151.548935,-33.232632],"type":"Point"}
}