{
  "type": "Feature",
  "properties": {
    "addr:full":"127 Wheatsheaf Rd Glenroy VIC 3046",
    "addr:housenumber":"127",
    "addr:postcode":"3046",
    "addr:street":"Wheatsheaf Rd",
    "iso:country":"AU",
    "sg:address":"127 Wheatsheaf Rd",
    "sg:city":"Glenroy",
    "sg:classifiers":[
        {
            "category":"Health Services",
            "subcategory":"Doctor",
            "type":"Services"
        }
    ],
    "sg:phone":"+61 3 9300 1244",
    "sg:postcode":"3046",
    "sg:province":"VIC",
    "sg:tags":[
        "medical",
        "practitioner"
    ],
    "wof:name":"Lung D.Y.",
    "wof:placetype":"venue"
},
  "geometry": {"coordinates":[144.919555664,-37.7066459656],"type":"Point"}
}