{
  "type": "Feature",
  "properties": {
    "addr:full":"82 Fullarton Rd Norwood SA 5067",
    "addr:housenumber":"82",
    "addr:postcode":"5067",
    "addr:street":"Fullarton Rd",
    "iso:country":"AU",
    "sg:address":"82 Fullarton Rd",
    "sg:city":"Norwood",
    "sg:classifiers":[
        {
            "category":"Professional",
            "subcategory":"Accounting & Tax Preparation",
            "type":"Services"
        }
    ],
    "sg:phone":"+61 8 8130 2000",
    "sg:postcode":"5067",
    "sg:province":"SA",
    "sg:tags":[
        "accountant",
        "auditor"
    ],
    "wof:name":"Lewis N J",
    "wof:placetype":"venue"
},
  "geometry": {"coordinates":[138.623504639,-34.9236068726],"type":"Point"}
}