{
  "type": "Feature",
  "properties": {
    "addr:full":"16B McDonald St West Osborne Park WA 6017",
    "addr:housenumber":"16b",
    "addr:postcode":"6017",
    "addr:street":"Mcdonald St West",
    "iso:country":"AU",
    "sg:address":"16B McDonald St West",
    "sg:city":"Osborne Park",
    "sg:classifiers":[
        {
            "category":"Retail",
            "subcategory":"Auto Repair",
            "type":"Services"
        }
    ],
    "sg:phone":"+61 8 9444 4494",
    "sg:postcode":"6017",
    "sg:province":"WA",
    "sg:tags":[
        "electrical"
    ],
    "wof:name":"Sisko's Mobile Auto Electrics & Air Conditioning",
    "wof:placetype":"venue"
},
  "geometry": {"coordinates":[115.820518494,-31.9060955048],"type":"Point"}
}