{
  "type": "Feature",
  "properties": {
    "addr:full":"119a Thompsons Rd Bulleen VIC 3105",
    "addr:housenumber":"119a",
    "addr:postcode":"3105",
    "addr:street":"Thompsons Rd",
    "iso:country":"AU",
    "sg:address":"119a Thompsons Rd",
    "sg:city":"Bulleen",
    "sg:classifiers":[
        {
            "category":"Fast Food",
            "type":"Food & Drink"
        }
    ],
    "sg:phone":"+61 3 9850 7575",
    "sg:postcode":"3105",
    "sg:province":"VIC",
    "sg:tags":[
        "away",
        "take"
    ],
    "wof:name":"Bulleen Fish Shop The",
    "wof:placetype":"venue"
},
  "geometry": {"coordinates":[145.091339111,-37.7748985291],"type":"Point"}
}