{
  "type": "Feature",
  "properties": {
    "addr:full":"Carseldine Medical Centre Beams Rd Carseldine QLD 4034",
    "addr:postcode":"4034",
    "addr:street":"Beams Rd",
    "iso:country":"AU",
    "sg:address":"Carseldine Medical Centre Beams Rd",
    "sg:city":"Carseldine",
    "sg:classifiers":[
        {
            "category":"Health Services",
            "subcategory":"Health Practitioner",
            "type":"Services"
        }
    ],
    "sg:phone":"+61 7 3263 1240",
    "sg:postcode":"4034",
    "sg:province":"QLD",
    "sg:tags":[
        "dietitian"
    ],
    "wof:name":"Nicola Fox Dietitians",
    "wof:placetype":"venue"
},
  "geometry": {"coordinates":[153.01542699999999,-27.346355],"type":"Point"}
}