{
  "type": "Feature",
  "properties": {
    "addr:full":"3 Carrington St Rosalie QLD 4064",
    "addr:housenumber":"3",
    "addr:postcode":"4064",
    "addr:street":"Carrington St",
    "iso:country":"AU",
    "sg:address":"3 Carrington St",
    "sg:city":"Rosalie",
    "sg:classifiers":[
        {
            "category":"Shopping",
            "subcategory":"Beauty & Cosmetics",
            "type":"Retail Goods"
        }
    ],
    "sg:phone":"+61 7 3368 2050",
    "sg:postcode":"4064",
    "sg:province":"QLD",
    "wof:name":"Chrisandra Coram",
    "wof:placetype":"venue"
},
  "geometry": {"coordinates":[152.99261474599999,-27.4660205841],"type":"Point"}
}