{
  "type": "Feature",
  "properties": {
    "addr:full":"First Floor, 19 - 21 Watt St Gosford NSW 2250",
    "addr:postcode":"2250",
    "addr:street":"Floor;21 Watt St",
    "iso:country":"AU",
    "sg:address":"First Floor, 19 - 21 Watt St",
    "sg:city":"Gosford",
    "sg:classifiers":[
        {
            "category":"Banks & Credit Unions",
            "subcategory":"Financial Services",
            "type":"Services"
        }
    ],
    "sg:phone":"+61 2 4324 3288",
    "sg:postcode":"2250",
    "sg:province":"NSW",
    "sg:tags":[
        "planning"
    ],
    "sg:website":"http://www.harwoods.com.au",
    "wof:name":"Harwoods Chartered Accountants",
    "wof:placetype":"venue"
},
  "geometry": {"coordinates":[151.34405517600001,-33.4228363037],"type":"Point"}
}