{
  "type": "Feature",
  "properties": {
    "iso:country":"AU",
    "sg:address":"64 Copeland St",
    "sg:city":"Liverpool",
    "sg:classifiers":[
        {
            "category":"Building & Trades",
            "subcategory":"Cleaning & Sanitation",
            "type":"Services"
        }
    ],
    "sg:phone":"+61 418 260 099",
    "sg:postcode":"2170",
    "sg:province":"NSW",
    "sg:tags":[
        "industrial",
        "commercial",
        "contractor"
    ],
    "wof:name":"Liverpool Cleaning Pty Ltd",
    "wof:placetype":"venue"
},
  "geometry": {"coordinates":[150.919158936,-33.922164917],"type":"Point"}
}