{
  "type": "Feature",
  "properties": {
    "addr:full":"Lot 338 Ninth Ave Llandilo NSW 2747",
    "addr:postcode":"2747",
    "addr:street":"Ninth Ave",
    "iso:country":"AU",
    "sg:address":"Lot 338 Ninth Ave",
    "sg:city":"Llandilo",
    "sg:classifiers":[
        {
            "category":"Food & Beverages",
            "subcategory":"Groceries & Convenience Stores",
            "type":"Retail Goods"
        }
    ],
    "sg:phone":"+61 2 4777 4856",
    "sg:postcode":"2747",
    "sg:province":"NSW",
    "sg:tags":[
        "merchant",
        "egg"
    ],
    "wof:name":"J.P. Bugeja",
    "wof:placetype":"venue"
},
  "geometry": {"coordinates":[150.75445556599999,-33.7158088684],"type":"Point"}
}