{
  "type": "Feature",
  "properties": {
    "iso:country":"AU",
    "sg:address":"5 Jamboree Ave",
    "sg:city":"Frankston",
    "sg:classifiers":[
        {
            "category":"Wholesale",
            "subcategory":"Machinery & Supplies",
            "type":"Manufacturing & Wholesale Goods"
        }
    ],
    "sg:phone":"+61 3 9770 2804",
    "sg:postcode":"3199",
    "sg:province":"VIC",
    "sg:tags":[
        "chemist"
    ],
    "wof:name":"Havenhall Pty Ltd",
    "wof:placetype":"venue"
},
  "geometry": {"coordinates":[145.120437622,-38.1578407288],"type":"Point"}
}