{
  "type": "Feature",
  "properties": {
    "iso:country":"AU",
    "sg:address":"Glencoe Pde",
    "sg:city":"Mandurah",
    "sg:classifiers":[
        {
            "category":"Health Services",
            "subcategory":"Doctor",
            "type":"Services"
        }
    ],
    "sg:phone":"+61 8 9535 5928",
    "sg:postcode":"6210",
    "sg:province":"WA",
    "sg:tags":[
        "medical",
        "practitioner"
    ],
    "wof:name":"Mayne Western Diagnostic Pathology Laboratory & Collection Centres",
    "wof:placetype":"venue"
},
  "geometry": {"coordinates":[115.705322,-32.539303],"type":"Point"}
}