{
  "type": "Feature",
  "properties": {
    "addr:full":"170 Ferry St Maryborough QLD 4650",
    "addr:housenumber":"170",
    "addr:postcode":"4650",
    "addr:street":"Ferry St",
    "iso:country":"AU",
    "sg:address":"170 Ferry St",
    "sg:city":"Maryborough",
    "sg:classifiers":[
        {
            "category":"Travel",
            "subcategory":"Hotels & Motels",
            "type":"Entertainment"
        }
    ],
    "sg:phone":"+61 7 4121 3217",
    "sg:postcode":"4650",
    "sg:province":"QLD",
    "sg:tags":[
        "accommodation"
    ],
    "wof:name":"Shamrock Hotel",
    "wof:placetype":"venue"
},
  "geometry": {"coordinates":[152.70095800000001,-25.529272],"type":"Point"}
}