{
  "type": "Feature",
  "properties": {
    "iso:country":"AU",
    "sg:address":"Lot 51 Bains Rd",
    "sg:city":"Woodcroft",
    "sg:classifiers":[
        {
            "category":"Farming",
            "subcategory":"Farm & Veterinary Services",
            "type":"Manufacturing & Wholesale Goods"
        }
    ],
    "sg:phone":"+61 8 8325 0266",
    "sg:postcode":"5162",
    "sg:province":"SA",
    "sg:tags":[
        "blacksmith",
        "farrier"
    ],
    "wof:name":"Billingham Barry",
    "wof:placetype":"venue"
},
  "geometry": {"coordinates":[138.55662536599999,-35.1139678955],"type":"Point"}
}