{
  "type": "Feature",
  "properties": {
    "iso:country":"AU",
    "sg:address":"Lot 7 Industrial Ave",
    "sg:city":"Crows Nest",
    "sg:classifiers":[
        {
            "category":"Government",
            "subcategory":"Fire Station",
            "type":"Public Place"
        }
    ],
    "sg:phone":"+61 7 4698 1898",
    "sg:postcode":"4355",
    "sg:province":"QLD",
    "sg:tags":[
        "equipment",
        "protection",
        "consultant"
    ],
    "wof:name":"AAA Engineering Technologies Pty Ltd",
    "wof:placetype":"venue"
},
  "geometry": {"coordinates":[152.05249000000001,-27.278709],"type":"Point"}
}