{
  "type": "Feature",
  "properties": {
    "addr:full":"Unit 4, 21 Huntingdale Rd Burwood VIC 3125",
    "addr:housenumber":"21",
    "addr:postcode":"3125",
    "addr:street":"Huntingdale Rd",
    "iso:country":"AU",
    "sg:address":"Unit 4, 21 Huntingdale Rd",
    "sg:city":"Burwood",
    "sg:classifiers":[
        {
            "category":"Shopping",
            "subcategory":"Stationery & Office Supplies",
            "type":"Retail Goods"
        }
    ],
    "sg:phone":"+61 3 9808 0777",
    "sg:postcode":"3125",
    "sg:province":"VIC",
    "sg:tags":[
        "packaging",
        "equipment",
        "sealing",
        "filling"
    ],
    "wof:name":"Graphic Packaging International Aust Pty Ltd",
    "wof:placetype":"venue"
},
  "geometry": {"coordinates":[145.11361694300001,-37.8568000793],"type":"Point"}
}