{
  "type": "Feature",
  "properties": {
    "iso:country":"AU",
    "sg:address":"43 Forsyth St",
    "sg:city":"O'Connor",
    "sg:classifiers":[
        {
            "category":"Communications",
            "type":"Services"
        }
    ],
    "sg:phone":"+61 8 9331 1833",
    "sg:postcode":"6163",
    "sg:province":"WA",
    "sg:tags":[
        "public",
        "system",
        "address"
    ],
    "sg:website":"http://www.avtechnologies.com.au",
    "wof:name":"AV Technologies WA",
    "wof:placetype":"venue"
},
  "geometry": {"coordinates":[115.792931,-32.055248],"type":"Point"}
}