{
  "type": "Feature",
  "properties": {
    "addr:full":"169 Princes Hwy Ulladulla NSW 2539",
    "addr:housenumber":"169",
    "addr:postcode":"2539",
    "addr:street":"Princes Hwy",
    "iso:country":"AU",
    "sg:address":"169 Princes Hwy",
    "sg:city":"Ulladulla",
    "sg:classifiers":[
        {
            "category":"Autos & Motor Vehicles",
            "subcategory":"Automobile Sales",
            "type":"Retail Goods"
        }
    ],
    "sg:phone":"+61 2 4455 1166",
    "sg:postcode":"2539",
    "sg:province":"NSW",
    "sg:tags":[
        "car",
        "new"
    ],
    "wof:name":"Alan May Holden",
    "wof:placetype":"venue"
},
  "geometry": {"coordinates":[150.47268676799999,-35.3641624451],"type":"Point"}
}