{
  "type": "Feature",
  "properties": {
    "addr:full":"Shp 7a/ 171 Queen St Campbelltown NSW 2560",
    "addr:housenumber":"7a / 171",
    "addr:postcode":"2560",
    "addr:street":"Queen St",
    "iso:country":"AU",
    "sg:address":"Shp 7a/ 171 Queen St",
    "sg:city":"Campbelltown",
    "sg:classifiers":[
        {
            "category":"Personal",
            "subcategory":"Beauty Salon",
            "type":"Services"
        }
    ],
    "sg:phone":"+61 2 4628 0766",
    "sg:postcode":"2560",
    "sg:province":"NSW",
    "wof:name":"Nail & Beauty On Safari",
    "wof:placetype":"venue"
},
  "geometry": {"coordinates":[150.81398010300001,-34.0667762756],"type":"Point"}
}