{
  "type": "Feature",
  "properties": {
    "addr:full":"61-63 Enterprise Ave Berwick VIC 3806",
    "addr:housenumber":"61-63",
    "addr:postcode":"3806",
    "addr:street":"Enterprise Ave",
    "iso:country":"AU",
    "sg:address":"61-63 Enterprise Ave",
    "sg:city":"Berwick",
    "sg:classifiers":[
        {
            "category":"Home & Garden",
            "subcategory":"Garden Supply",
            "type":"Retail Goods"
        }
    ],
    "sg:phone":"+61 3 9769 9733",
    "sg:postcode":"3806",
    "sg:province":"VIC",
    "sg:tags":[
        "nursery"
    ],
    "wof:name":"Transplant Systems Pty Ltd",
    "wof:placetype":"venue"
},
  "geometry": {"coordinates":[145.33677673299999,-38.0362548828],"type":"Point"}
}