{
  "type": "Feature",
  "properties": {
    "iso:country":"AU",
    "sg:address":"Unit 14/ 115 Grand Boulevard",
    "sg:city":"Joondalup",
    "sg:classifiers":[
        {
            "category":"Health Services",
            "subcategory":"Doctor",
            "type":"Services"
        }
    ],
    "sg:phone":"+61 8 9301 0299",
    "sg:postcode":"6027",
    "sg:province":"WA",
    "sg:tags":[
        "nurse",
        "nursing"
    ],
    "wof:name":"White Oak",
    "wof:placetype":"venue"
},
  "geometry": {"coordinates":[115.770202637,-31.7415313721],"type":"Point"}
}