{
  "type": "Feature",
  "properties": {
    "addr:full":"Shop 1, Cnr Broadmeadows Rd & Ann-Maree Cl Maroochydore QLD 4558",
    "addr:housenumber":"shop 1",
    "addr:postcode":"4558",
    "addr:street":"Cnr Broadmeadows Rd & Ann-Maree Cl",
    "iso:country":"AU",
    "sg:address":"Shop 1, Cnr Broadmeadows Rd",
    "sg:city":"& Ann-Maree Cl Maroochydore",
    "sg:classifiers":[
        {
            "category":"Professional",
            "subcategory":"Testing Lab",
            "type":"Services"
        }
    ],
    "sg:phone":"+61 7 5443 6988",
    "sg:postcode":"4558",
    "sg:province":"QLD",
    "sg:tags":[
        "soil",
        "investigation"
    ],
    "wof:name":"Geo-Investigations Pty Ltd",
    "wof:placetype":"venue"
},
  "geometry": {"coordinates":[153.08218383799999,-26.6512565613],"type":"Point"}
}