{
  "type": "Feature",
  "properties": {
    "iso:country":"AU",
    "sg:address":"86 Warwick Rd",
    "sg:city":"Sunshine North",
    "sg:classifiers":[
        {
            "category":"Retail",
            "subcategory":"Auto Repair",
            "type":"Services"
        }
    ],
    "sg:phone":"+61 3 9311 0538",
    "sg:postcode":"3020",
    "sg:province":"VIC",
    "sg:tags":[
        "gas",
        "conversion",
        "natural",
        "lp",
        "vehicle"
    ],
    "wof:name":"Mechgas",
    "wof:placetype":"venue"
},
  "geometry": {"coordinates":[144.836426,-37.768505],"type":"Point"}
}