{
  "type": "Feature",
  "properties": {
    "addr:full":"Arndale Shopping Centre Shop 22 224 Mount Dandenong Rd Croydon VIC 3136",
    "addr:housenumber":"shop 22 224",
    "addr:postcode":"3136",
    "addr:street":"Mount Dandenong Rd",
    "iso:country":"AU",
    "sg:address":"Arndale Shopping Centre Shop 22 224 Mount Dandenong Rd",
    "sg:city":"Croydon",
    "sg:classifiers":[
        {
            "category":"Communications",
            "subcategory":"Film & Video Production",
            "type":"Services"
        }
    ],
    "sg:phone":"+61 3 9725 4222",
    "sg:postcode":"3136",
    "sg:province":"VIC",
    "sg:tags":[
        "dvd",
        "library"
    ],
    "wof:name":"Video Busters",
    "wof:placetype":"venue"
},
  "geometry": {"coordinates":[145.28520202600001,-37.7992324829],"type":"Point"}
}