{
  "type": "Feature",
  "properties": {
    "addr:full":"133 Belmore St Yarrawonga VIC 3730",
    "addr:housenumber":"133",
    "addr:postcode":"3730",
    "addr:street":"Belmore St",
    "iso:country":"AU",
    "sg:address":"133 Belmore St",
    "sg:city":"Yarrawonga",
    "sg:classifiers":[
        {
            "category":"Personal",
            "subcategory":"Beauty Salon",
            "type":"Services"
        }
    ],
    "sg:phone":"+61 3 5744 3079",
    "sg:postcode":"3730",
    "sg:province":"VIC",
    "sg:tags":[
        "hairdresser"
    ],
    "wof:name":"Rob's Hair Fashions",
    "wof:placetype":"venue"
},
  "geometry": {"coordinates":[146.00422668499999,-36.0140762329],"type":"Point"}
}