{
  "type": "Feature",
  "properties": {
    "addr:full":"79 Moore Ave Montrose VIC 3765",
    "addr:housenumber":"79",
    "addr:postcode":"3765",
    "addr:street":"Moore Ave",
    "iso:country":"AU",
    "sg:address":"79 Moore Ave",
    "sg:city":"Montrose",
    "sg:classifiers":[
        {
            "category":"Communications",
            "subcategory":"Television Station",
            "type":"Services"
        }
    ],
    "sg:phone":"+61 3 9728 4282",
    "sg:postcode":"3765",
    "sg:province":"VIC",
    "sg:tags":[
        "mfrs",
        "tank",
        "installation",
        "septic"
    ],
    "wof:name":"Great Divide Plumbing Service",
    "wof:placetype":"venue"
},
  "geometry": {"coordinates":[145.36593627900001,-37.802406311],"type":"Point"}
}