{
  "type": "Feature",
  "properties": {
    "addr:full":"1st Floor, Suite 4 Lake Macquarie Fair Mt Hutton NSW 2290",
    "addr:postcode":"2290",
    "addr:street":"Mt",
    "iso:country":"AU",
    "sg:address":"1st Floor, Suite 4 Lake Macquarie Fair",
    "sg:city":"Mt Hutton",
    "sg:classifiers":[
        {
            "category":"Health Services",
            "subcategory":"Dentist",
            "type":"Services"
        }
    ],
    "sg:phone":"+61 2 4948 7651",
    "sg:postcode":"2290",
    "sg:province":"NSW",
    "wof:name":"Huynh Dieu",
    "wof:placetype":"venue"
},
  "geometry": {"coordinates":[151.68333435100001,-32.9921875],"type":"Point"}
}