{
  "type": "Feature",
  "properties": {
    "addr:full":"3B/ 721 Gympie Rd Lawnton QLD 4501",
    "addr:housenumber":"3b / 721",
    "addr:postcode":"4501",
    "addr:street":"Gympie Rd",
    "iso:country":"AU",
    "sg:address":"3B/ 721 Gympie Rd",
    "sg:city":"Lawnton",
    "sg:classifiers":[
        {
            "category":"Commercial Area",
            "type":"Public Place"
        }
    ],
    "sg:phone":"+61 7 3205 5011",
    "sg:postcode":"4501",
    "sg:province":"QLD",
    "sg:tags":[
        "bar",
        "domestic"
    ],
    "wof:name":"Pub World",
    "wof:placetype":"venue"
},
  "geometry": {"coordinates":[152.98243713400001,-27.2799491882],"type":"Point"}
}