{
  "type": "Feature",
  "properties": {
    "addr:full":"188 Collins St Melbourne VIC 3000",
    "addr:housenumber":"188",
    "addr:postcode":"3000",
    "addr:street":"Collins St",
    "iso:country":"AU",
    "sg:address":"188 Collins St",
    "sg:city":"Melbourne",
    "sg:classifiers":[
        {
            "category":"Cinema",
            "subcategory":"Movie Theater",
            "type":"Entertainment"
        }
    ],
    "sg:phone":"+61 3 9650 1500",
    "sg:postcode":"3000",
    "sg:province":"VIC",
    "wof:name":"Athenaeum Theatre",
    "wof:placetype":"venue"
},
  "geometry": {"coordinates":[144.96749877900001,-37.8150672913],"type":"Point"}
}