{
  "type": "Feature",
  "properties": {
    "addr:full":"36 Sydenham Rd Marrickville NSW 2204",
    "addr:housenumber":"36",
    "addr:postcode":"2204",
    "addr:street":"Sydenham Rd",
    "iso:country":"AU",
    "sg:address":"36 Sydenham Rd",
    "sg:city":"Marrickville",
    "sg:classifiers":[
        {
            "category":"Cafe",
            "type":"Food & Drink"
        }
    ],
    "sg:phone":"+61 2 9565 2770",
    "sg:postcode":"2204",
    "sg:province":"NSW",
    "wof:name":"Sanjoes Eatery",
    "wof:placetype":"venue"
},
  "geometry": {"coordinates":[151.165131,-33.91206],"type":"Point"}
}