{
  "type": "Feature",
  "properties": {
    "addr:full":"30 Gillam Drv Kelmscott WA 6111",
    "addr:housenumber":"30",
    "addr:postcode":"6111",
    "addr:street":"Gillam Drv",
    "iso:country":"AU",
    "sg:address":"30 Gillam Drv",
    "sg:city":"Kelmscott",
    "sg:classifiers":[
        {
            "category":"Retail",
            "subcategory":"Storage",
            "type":"Services"
        }
    ],
    "sg:phone":"+61 8 9390 0033",
    "sg:postcode":"6111",
    "sg:province":"WA",
    "wof:name":"Storage-Mart Self Storage",
    "wof:placetype":"venue"
},
  "geometry": {"coordinates":[116.007469177,-32.1288108826],"type":"Point"}
}