{
  "type": "Feature",
  "properties": {
    "addr:full":"Wattle St Yorkeys Knob QLD 4878",
    "addr:postcode":"4878",
    "addr:street":"Wattle St",
    "iso:country":"AU",
    "sg:address":"Wattle St",
    "sg:city":"Yorkeys Knob",
    "sg:classifiers":[
        {
            "category":"Manufacturing",
            "subcategory":"Food",
            "type":"Manufacturing & Wholesale Goods"
        }
    ],
    "sg:phone":"+61 414 768 859",
    "sg:postcode":"4878",
    "sg:province":"QLD",
    "sg:tags":[
        "function",
        "catering"
    ],
    "wof:name":"Cairns Spit Roast & Gourmet BBQs Catering Services",
    "wof:placetype":"venue"
},
  "geometry": {"coordinates":[145.72161865199999,-16.8103694916],"type":"Point"}
}