{
  "type": "Feature",
  "properties": {
    "addr:full":"Ocean St Geraldton WA 6530",
    "addr:postcode":"6530",
    "addr:street":"Ocean St",
    "iso:country":"AU",
    "sg:address":"Ocean St",
    "sg:city":"Geraldton",
    "sg:classifiers":[
        {
            "category":"Manufacturing",
            "subcategory":"Metals",
            "type":"Manufacturing & Wholesale Goods"
        }
    ],
    "sg:phone":"+61 8 9921 2211",
    "sg:postcode":"6530",
    "sg:province":"WA",
    "sg:tags":[
        "cutting"
    ],
    "wof:name":"The Sheetmetal Factory",
    "wof:placetype":"venue"
},
  "geometry": {"coordinates":[114.589538574,-28.7801990509],"type":"Point"}
}