{
  "type": "Feature",
  "properties": {
    "iso:country":"AU",
    "sg:address":"101 Angelo St",
    "sg:city":"South Perth",
    "sg:classifiers":[
        {
            "category":"Building & Trades",
            "subcategory":"Construction",
            "type":"Services"
        }
    ],
    "sg:phone":"+61 418 906 124",
    "sg:postcode":"6151",
    "sg:province":"WA",
    "sg:tags":[
        "contractor"
    ],
    "wof:name":"Mountford C J & H Builder",
    "wof:placetype":"venue"
},
  "geometry": {"coordinates":[115.866508,-31.98148],"type":"Point"}
}