{
  "type": "Feature",
  "properties": {
    "iso:country":"AU",
    "sg:address":"115 Mcintyre Rd",
    "sg:city":"Sunshine North",
    "sg:classifiers":[
        {
            "category":"Retail",
            "subcategory":"Auto Repair",
            "type":"Services"
        }
    ],
    "sg:phone":"+61 3 9311 0507",
    "sg:postcode":"3020",
    "sg:province":"VIC",
    "sg:tags":[
        "clutch",
        "brake"
    ],
    "wof:name":"Best Brakes & Clutches",
    "wof:placetype":"venue"
},
  "geometry": {"coordinates":[144.83038300000001,-37.767242],"type":"Point"}
}