{
  "type": "Feature",
  "properties": {
    "addr:full":"1, 28 Hill St Tweed Heads NSW 2485",
    "addr:housenumber":"28",
    "addr:postcode":"2485",
    "addr:street":"1;Hill St",
    "iso:country":"AU",
    "sg:address":"1, 28 Hill St",
    "sg:city":"Tweed Heads",
    "sg:classifiers":[
        {
            "category":"Building & Trades",
            "subcategory":"Cleaning & Sanitation",
            "type":"Services"
        }
    ],
    "sg:phone":"+61 418 278 817",
    "sg:postcode":"2485",
    "sg:province":"NSW",
    "sg:tags":[
        "industrial",
        "commercial",
        "contractor"
    ],
    "wof:name":"G J Lipshus",
    "wof:placetype":"venue"
},
  "geometry": {"coordinates":[153.54751586899999,-28.1672515869],"type":"Point"}
}