{
  "type": "Feature",
  "properties": {
    "iso:country":"AU",
    "sg:address":"Bldg8b/ 50 Kawana Way",
    "sg:city":"Birtinya",
    "sg:classifiers":[
        {
            "category":"Sports & Exercise",
            "subcategory":"Gym",
            "type":"Entertainment"
        }
    ],
    "sg:phone":"+61 7 5493 5099",
    "sg:postcode":"4575",
    "sg:province":"QLD",
    "sg:tags":[
        "health",
        "fitness"
    ],
    "wof:name":"Beach House Health & Fitness Centre",
    "wof:placetype":"venue"
},
  "geometry": {"coordinates":[153.120895,-26.730053],"type":"Point"}
}