{
  "type": "Feature",
  "properties": {
    "addr:full":"402 Chapel St South Yarra VIC 3141",
    "addr:housenumber":"402",
    "addr:postcode":"3141",
    "addr:street":"Chapel St",
    "iso:country":"AU",
    "sg:address":"402 Chapel St",
    "sg:city":"South Yarra",
    "sg:classifiers":[
        {
            "category":"Arts & Performance",
            "subcategory":"Art Gallery",
            "type":"Entertainment"
        }
    ],
    "sg:phone":"+61 3 9826 9690",
    "sg:postcode":"3141",
    "sg:province":"VIC",
    "wof:name":"Visions Framing Gallery",
    "wof:placetype":"venue"
},
  "geometry": {"coordinates":[144.99465942399999,-37.8450164795],"type":"Point"}
}