{
  "type": "Feature",
  "properties": {
    "iso:country":"AU",
    "sg:address":"Unit 4/ 129 Robinson Rd",
    "sg:city":"East Geebung",
    "sg:classifiers":[
        {
            "category":"Professional",
            "subcategory":"Printing & Photocopies",
            "type":"Services"
        }
    ],
    "sg:phone":"+61 7 3865 7066",
    "sg:postcode":"4034",
    "sg:province":"QLD",
    "sg:tags":[
        "screen",
        "printer"
    ],
    "wof:name":"Noahs Art T-Shirt Printing",
    "wof:placetype":"venue"
},
  "geometry": {"coordinates":[153.055496,-27.369349],"type":"Point"}
}