{
  "type": "Feature",
  "properties": {
    "addr:full":"153 Dewars Rd Woodside VIC 3874",
    "addr:housenumber":"153",
    "addr:postcode":"3874",
    "addr:street":"Dewars Rd",
    "iso:country":"AU",
    "sg:address":"153 Dewars Rd",
    "sg:city":"Woodside",
    "sg:classifiers":[
        {
            "category":"Professional",
            "subcategory":"Computer Services",
            "type":"Services"
        }
    ],
    "sg:phone":"+61 3 5187 1364",
    "sg:postcode":"3874",
    "sg:province":"VIC",
    "sg:tags":[
        "repairs",
        "upgrade",
        "equipment"
    ],
    "wof:name":"R.A.D. Computers",
    "wof:placetype":"venue"
},
  "geometry": {"coordinates":[146.91838073700001,-38.4928741455],"type":"Point"}
}