{
  "type": "Feature",
  "properties": {
    "addr:full":"31 Graham Rd Clayton South VIC 3169",
    "addr:housenumber":"31",
    "addr:postcode":"3169",
    "addr:street":"Graham Rd",
    "iso:country":"AU",
    "sg:address":"31 Graham Rd",
    "sg:city":"Clayton South",
    "sg:classifiers":[
        {
            "category":"Wholesale",
            "subcategory":"Machinery & Supplies",
            "type":"Manufacturing & Wholesale Goods"
        }
    ],
    "sg:phone":"+61 3 9547 0122",
    "sg:postcode":"3169",
    "sg:province":"VIC",
    "sg:tags":[
        "machine",
        "tool",
        "engineer"
    ],
    "wof:name":"Engineering Sales & Machinery Pty Ltd",
    "wof:placetype":"venue"
},
  "geometry": {"coordinates":[145.13702392600001,-37.9524993896],"type":"Point"}
}