{
  "type": "Feature",
  "properties": {
    "iso:country":"AU",
    "sg:address":"2 Bell St",
    "sg:city":"Yarra Glen",
    "sg:classifiers":[
        {
            "category":"Landmark",
            "subcategory":"Unesco World Heritage Site",
            "type":"Public Place"
        }
    ],
    "sg:phone":"+61 3 9730 2422",
    "sg:postcode":"3775",
    "sg:province":"VIC",
    "sg:tags":[
        "balloon",
        "hot",
        "air"
    ],
    "wof:name":"Peregrine Ballooning",
    "wof:placetype":"venue"
},
  "geometry": {"coordinates":[145.374893,-37.659405],"type":"Point"}
}