{
  "type": "Feature",
  "properties": {
    "addr:full":"4A Dwyer St Webberton Geraldton WA 6530",
    "addr:housenumber":"4a",
    "addr:postcode":"6530",
    "addr:street":"Dwyer St",
    "iso:country":"AU",
    "sg:address":"4A Dwyer St Webberton",
    "sg:city":"Geraldton",
    "sg:classifiers":[
        {
            "category":"Professional",
            "subcategory":"Detective & Security Services",
            "type":"Services"
        }
    ],
    "sg:phone":"+61 408 930 780",
    "sg:postcode":"6530",
    "sg:province":"WA",
    "sg:tags":[
        "equipment",
        "window",
        "doors"
    ],
    "wof:name":"Parker Aluminium Windows",
    "wof:placetype":"venue"
},
  "geometry": {"coordinates":[114.637489319,-28.7582645416],"type":"Point"}
}