{
  "type": "Feature",
  "properties": {
    "iso:country":"AU",
    "sg:address":"97 Yarra St",
    "sg:city":"Geelong",
    "sg:classifiers":[
        {
            "category":"Banks & Credit Unions",
            "subcategory":"Financial Services",
            "type":"Services"
        }
    ],
    "sg:phone":"+61 3 5222 2355",
    "sg:postcode":"3220",
    "sg:province":"VIC",
    "sg:tags":[
        "planning"
    ],
    "wof:name":"GL Financial Planning",
    "wof:placetype":"venue"
},
  "geometry": {"coordinates":[144.36218299999999,-38.150681],"type":"Point"}
}