{
  "type": "Feature",
  "properties": {
    "iso:country":"AU",
    "sg:address":"7- 10 Firth St",
    "sg:city":"Arncliffe",
    "sg:classifiers":[
        {
            "category":"Social Services",
            "subcategory":"Child Care",
            "type":"Services"
        }
    ],
    "sg:phone":"+61 2 9567 2019",
    "sg:postcode":"2205",
    "sg:province":"NSW",
    "wof:name":"Macedonian Community Child Care Centre Ilinden",
    "wof:placetype":"venue"
},
  "geometry": {"coordinates":[151.146973,-33.935905],"type":"Point"}
}