{
  "type": "Feature",
  "properties": {
    "addr:full":"14 Logrunner Drv Morayfield QLD 4506",
    "addr:housenumber":"14",
    "addr:postcode":"4506",
    "addr:street":"Logrunner Drv",
    "iso:country":"AU",
    "sg:address":"14 Logrunner Drv",
    "sg:city":"Morayfield",
    "sg:classifiers":[
        {
            "category":"Building & Trades",
            "subcategory":"Construction",
            "type":"Services"
        }
    ],
    "sg:phone":"+61 438 152 773",
    "sg:postcode":"4506",
    "sg:province":"QLD",
    "sg:tags":[
        "concrete",
        "contractor"
    ],
    "wof:name":"AR Concrete To Kerb Soloution",
    "wof:placetype":"venue"
},
  "geometry": {"coordinates":[152.92190551799999,-27.1142139435],"type":"Point"}
}