{
  "type": "Feature",
  "properties": {
    "addr:full":"Cnr Marine & Warner Sts Coolangatta QLD 4225",
    "addr:postcode":"4225",
    "iso:country":"AU",
    "sg:address":"Cnr Marine & Warner Sts",
    "sg:city":"Coolangatta",
    "sg:classifiers":[
        {
            "category":"Travel",
            "subcategory":"Hotels & Motels",
            "type":"Entertainment"
        }
    ],
    "sg:phone":"+61 7 5589 6888",
    "sg:postcode":"4225",
    "sg:province":"QLD",
    "sg:tags":[
        "pub"
    ],
    "wof:name":"Coolangatta Hotel",
    "wof:placetype":"venue"
},
  "geometry": {"coordinates":[153.510986328,-28.1607666016],"type":"Point"}
}