{
  "type": "Feature",
  "properties": {
    "addr:full":"Sutton St Pinjarra WA 6208",
    "addr:postcode":"6208",
    "addr:street":"Sutton St",
    "iso:country":"AU",
    "sg:address":"Sutton St",
    "sg:city":"Pinjarra",
    "sg:classifiers":[
        {
            "category":"Travel",
            "subcategory":"Travel Agent",
            "type":"Entertainment"
        }
    ],
    "sg:phone":"+61 8 9531 6752",
    "sg:postcode":"6208",
    "sg:province":"WA",
    "sg:tags":[
        "tour",
        "holiday",
        "adventure"
    ],
    "wof:name":"ALCOA Tours",
    "wof:placetype":"venue"
},
  "geometry": {"coordinates":[115.86309799999999,-32.614029],"type":"Point"}
}