{
  "type": "Feature",
  "properties": {
    "iso:country":"AU",
    "sg:address":"44 Victor St",
    "sg:city":"Hilton",
    "sg:classifiers":[
        {
            "category":"Health Services",
            "subcategory":"Doctor",
            "type":"Services"
        }
    ],
    "sg:phone":"+61 8 9337 1577",
    "sg:postcode":"6163",
    "sg:province":"WA",
    "sg:tags":[
        "medical",
        "practitioner"
    ],
    "wof:name":"Mikosza R T",
    "wof:placetype":"venue"
},
  "geometry": {"coordinates":[115.781219,-32.06303],"type":"Point"}
}