{
  "type": "Feature",
  "properties": {
    "addr:full":"Shop 16 , Macquarie Shopping Centre, North Ryde NSW 2113",
    "addr:housenumber":"shop 16",
    "addr:postcode":"2113",
    "addr:street":"Macquarie Shopping",
    "iso:country":"AU",
    "sg:address":"Shop 16",
    "sg:city":", Macquarie Shopping Centre, North Ryde",
    "sg:classifiers":[
        {
            "category":"Shopping",
            "subcategory":"Computers & Home Electronics",
            "type":"Retail Goods"
        }
    ],
    "sg:phone":"+61 2 9887 1714",
    "sg:postcode":"2113",
    "sg:province":"NSW",
    "sg:tags":[
        "equipment",
        "part",
        "electronic"
    ],
    "wof:name":"Tandy",
    "wof:placetype":"venue"
},
  "geometry": {"coordinates":[151.12094116200001,-33.7941093445],"type":"Point"}
}