{
  "type": "Feature",
  "properties": {
    "iso:country":"AU",
    "sg:address":"22 Emmerson St",
    "sg:city":"North Perth",
    "sg:classifiers":[
        {
            "category":"Arena",
            "subcategory":"Sports Club",
            "type":"Entertainment"
        }
    ],
    "sg:phone":"+61 8 9228 9399",
    "sg:postcode":"6006",
    "sg:province":"WA",
    "sg:tags":[
        "organisation",
        "sporting"
    ],
    "wof:name":"Gymnastics Western Australia",
    "wof:placetype":"venue"
},
  "geometry": {"coordinates":[115.85075378400001,-31.9342041016],"type":"Point"}
}