{
  "type": "Feature",
  "properties": {
    "iso:country":"AU",
    "sg:address":"Shp 39",
    "sg:city":"Waverley Gardens Shopng Cntr Mulgrave",
    "sg:classifiers":[
        {
            "category":"Banks & Credit Unions",
            "subcategory":"Bank",
            "type":"Services"
        }
    ],
    "sg:phone":"+61 13 20 32",
    "sg:postcode":"3170",
    "sg:province":"VIC",
    "wof:name":"Westpac",
    "wof:placetype":"venue"
},
  "geometry": {"coordinates":[145.122146606,-37.8839416504],"type":"Point"}
}