{
  "type": "Feature",
  "properties": {
    "addr:full":"U1/ 321 Main St Mornington VIC 3931",
    "addr:housenumber":"321",
    "addr:postcode":"3931",
    "addr:street":"U1 /;Main St",
    "iso:country":"AU",
    "sg:address":"U1/ 321 Main St",
    "sg:city":"Mornington",
    "sg:classifiers":[
        {
            "category":"Professional",
            "subcategory":"Accounting & Tax Preparation",
            "type":"Services"
        }
    ],
    "sg:phone":"+61 3 5973 6577",
    "sg:postcode":"3931",
    "sg:province":"VIC",
    "sg:tags":[
        "accountant",
        "auditor"
    ],
    "wof:name":"Ej Walsh & Associates",
    "wof:placetype":"venue"
},
  "geometry": {"coordinates":[145.04298400900001,-38.2267990112],"type":"Point"}
}