{
  "type": "Feature",
  "properties": {
    "iso:country":"AU",
    "sg:address":"13 Upwey St",
    "sg:city":"Prospect",
    "sg:classifiers":[
        {
            "category":"Professional",
            "subcategory":"Art Services",
            "type":"Services"
        }
    ],
    "sg:phone":"+61 2 9621 3376",
    "sg:postcode":"2148",
    "sg:province":"NSW",
    "sg:tags":[
        "decorator",
        "painter"
    ],
    "wof:name":"Decore Painting Services P/L",
    "wof:placetype":"venue"
},
  "geometry": {"coordinates":[150.906692505,-33.7925338745],"type":"Point"}
}