{
  "type": "Feature",
  "properties": {
    "iso:country":"AU",
    "sg:address":"37 Gorge Rd",
    "sg:city":"South Morang",
    "sg:classifiers":[
        {
            "category":"Health Services",
            "subcategory":"Dentist",
            "type":"Services"
        }
    ],
    "sg:phone":"+61 3 9437 9999",
    "sg:postcode":"3752",
    "sg:province":"VIC",
    "wof:name":"Aung John Dr",
    "wof:placetype":"venue"
},
  "geometry": {"coordinates":[145.090363,-37.651566],"type":"Point"}
}