{
  "type": "Feature",
  "properties": {
    "iso:country":"AU",
    "sg:address":"51 Park St",
    "sg:city":"South Melbourne",
    "sg:classifiers":[
        {
            "category":"Building & Trades",
            "subcategory":"Construction",
            "type":"Services"
        }
    ],
    "sg:phone":"+61 3 9699 9331",
    "sg:postcode":"3205",
    "sg:province":"VIC",
    "sg:tags":[
        "contractor"
    ],
    "wof:name":"Commercial Industrial Construction Group Pty Ltd",
    "wof:placetype":"venue"
},
  "geometry": {"coordinates":[144.968582,-37.833328],"type":"Point"}
}