{
  "type": "Feature",
  "properties": {
    "addr:full":"7/ 136 Cochranes Rd Moorabbin VIC 3189",
    "addr:housenumber":"/ 136",
    "addr:postcode":"3189",
    "addr:street":"Cochranes Rd",
    "iso:country":"AU",
    "sg:address":"7/ 136 Cochranes Rd",
    "sg:city":"Moorabbin",
    "sg:classifiers":[
        {
            "category":"Shopping",
            "subcategory":"Pets & Pet Supplies",
            "type":"Retail Goods"
        }
    ],
    "sg:phone":"+61 3 9555 2422",
    "sg:postcode":"3189",
    "sg:province":"VIC",
    "sg:tags":[
        "shop",
        "supplier"
    ],
    "wof:name":"W R K Enterprises",
    "wof:placetype":"venue"
},
  "geometry": {"coordinates":[145.074493408,-37.9438552856],"type":"Point"}
}