{
  "type": "Feature",
  "properties": {
    "iso:country":"AU",
    "sg:address":"44 Auburn St",
    "sg:city":"Wollongong",
    "sg:classifiers":[
        {
            "category":"Building & Trades",
            "subcategory":"Construction",
            "type":"Services"
        }
    ],
    "sg:phone":"+61 2 4226 5599",
    "sg:postcode":"2500",
    "sg:province":"NSW",
    "sg:tags":[
        "home",
        "air conditioning"
    ],
    "sg:website":"http://www.alpineaircon.com.au",
    "wof:name":"Alpine Refrigeration & Air Conditioning",
    "wof:placetype":"venue"
},
  "geometry": {"coordinates":[150.888748,-34.42997],"type":"Point"}
}