{
  "type": "Feature",
  "properties": {
    "addr:full":"5a 82 Todd Street Alice Springs NT 0870",
    "addr:housenumber":"82",
    "addr:postcode":"nt 0870",
    "addr:street":"Todd Street",
    "iso:country":"AU",
    "sg:address":"5a 82 Todd Street",
    "sg:city":"Alice Springs",
    "sg:classifiers":[
        {
            "category":"Health Services",
            "subcategory":"Health Practitioner",
            "type":"Services"
        }
    ],
    "sg:phone":"+61 8 8953 8822",
    "sg:postcode":"0870",
    "sg:province":"NT",
    "sg:tags":[
        "physiotherapist"
    ],
    "wof:name":"Red Centre Physiotherapy",
    "wof:placetype":"venue"
},
  "geometry": {"coordinates":[133.88157653799999,-23.7017822266],"type":"Point"}
}