{
  "type": "Feature",
  "properties": {
    "iso:country":"AU",
    "sg:address":"280 Beenak Rd",
    "sg:city":"Wandin",
    "sg:classifiers":[
        {
            "category":"Social Services",
            "subcategory":"Adult Care",
            "type":"Services"
        }
    ],
    "sg:phone":"+61 438 350 315",
    "sg:postcode":"3139",
    "sg:province":"VIC",
    "sg:tags":[
        "towing"
    ],
    "wof:name":"Rock n' Roll Towing",
    "wof:placetype":"venue"
},
  "geometry": {"coordinates":[145.44583129899999,-37.7945365906],"type":"Point"}
}