{
  "type": "Feature",
  "properties": {
    "addr:full":"Munno Para Shopping City Main North Rd Munno Para SA 5115",
    "addr:postcode":"5115",
    "addr:street":"Main North Rd",
    "iso:country":"AU",
    "sg:address":"Munno Para Shopping City Main North Rd",
    "sg:city":"Munno Para",
    "sg:classifiers":[
        {
            "category":"Ice Cream",
            "type":"Food & Drink"
        }
    ],
    "sg:phone":"+61 8 8284 1546",
    "sg:postcode":"5115",
    "sg:province":"SA",
    "sg:tags":[
        "retail"
    ],
    "wof:name":"Wendys",
    "wof:placetype":"venue"
},
  "geometry": {"coordinates":[138.696334839,-34.6786766052],"type":"Point"}
}