{
  "type": "Feature",
  "properties": {
    "addr:full":"381 Tooronga Rd Hawthorn East VIC 3123",
    "addr:housenumber":"381",
    "addr:postcode":"3123",
    "addr:street":"Tooronga Rd",
    "iso:country":"AU",
    "sg:address":"381 Tooronga Rd",
    "sg:city":"Hawthorn East",
    "sg:classifiers":[
        {
            "category":"Travel",
            "subcategory":"Hostel",
            "type":"Entertainment"
        }
    ],
    "sg:phone":"+61 1300 133 414",
    "sg:postcode":"3123",
    "sg:province":"VIC",
    "sg:tags":[
        "home"
    ],
    "sg:website":"http://www.bluecross.com.au",
    "wof:name":"Blue Cross",
    "wof:placetype":"venue"
},
  "geometry": {"coordinates":[145.047409058,-37.8310127258],"type":"Point"}
}