{
  "type": "Feature",
  "properties": {
    "iso:country":"AU",
    "sg:address":"163 Clovelly Rd",
    "sg:city":"Clovelly",
    "sg:classifiers":[
        {
            "category":"Arts & Performance",
            "subcategory":"Art Gallery",
            "type":"Entertainment"
        }
    ],
    "sg:phone":"+61 2 9314 7708",
    "sg:postcode":"2031",
    "sg:province":"NSW",
    "wof:name":"James Harvey Gallery",
    "wof:placetype":"venue"
},
  "geometry": {"coordinates":[151.251831055,-33.9099807739],"type":"Point"}
}