{
  "type": "Feature",
  "properties": {
    "iso:country":"AU",
    "sg:address":"PO Box 1275",
    "sg:city":"Darlinghurst",
    "sg:classifiers":[
        {
            "category":"Professional",
            "subcategory":"Business Services",
            "type":"Services"
        }
    ],
    "sg:phone":"+61 2 9311 4099",
    "sg:postcode":"1300",
    "sg:province":"NSW",
    "sg:tags":[
        "record",
        "management",
        "storage"
    ],
    "wof:name":"Provenance Consulting Services Pty Ltd",
    "wof:placetype":"venue"
},
  "geometry": {"coordinates":[151.220306397,-33.8782997131],"type":"Point"}
}