{
  "type": "Feature",
  "properties": {
    "iso:country":"AU",
    "sg:address":"&#034;The Hub&#034; Wynyard St",
    "sg:city":"Tumut",
    "sg:classifiers":[
        {
            "category":"Banks & Credit Unions",
            "subcategory":"Bank",
            "type":"Services"
        }
    ],
    "sg:phone":"+61 2 6947 3535",
    "sg:postcode":"2720",
    "sg:province":"NSW",
    "wof:name":"St.George Bank Limited",
    "wof:placetype":"venue"
},
  "geometry": {"coordinates":[148.224884,-35.300838],"type":"Point"}
}