{
  "type": "Feature",
  "properties": {
    "addr:full":"13 Veronica Crs Narara NSW 2250",
    "addr:housenumber":"13",
    "addr:postcode":"2250",
    "addr:street":"Veronica Crs",
    "iso:country":"AU",
    "sg:address":"13 Veronica Crs",
    "sg:city":"Narara",
    "sg:classifiers":[
        {
            "category":"Banks & Credit Unions",
            "subcategory":"Bank",
            "type":"Services"
        }
    ],
    "sg:phone":"+61 2 4322 1585",
    "sg:postcode":"2250",
    "sg:province":"NSW",
    "sg:tags":[
        "society"
    ],
    "wof:name":"Credit Union Foundation",
    "wof:placetype":"venue"
},
  "geometry": {"coordinates":[151.336990356,-33.40625],"type":"Point"}
}