{
  "type": "Feature",
  "properties": {
    "addr:full":"845 Beaufort St Inglewood WA 6052",
    "addr:housenumber":"845",
    "addr:postcode":"6052",
    "addr:street":"Beaufort St",
    "iso:country":"AU",
    "sg:address":"845 Beaufort St",
    "sg:city":"Inglewood",
    "sg:classifiers":[
        {
            "category":"Wholesale",
            "subcategory":"Painting Supplies",
            "type":"Manufacturing & Wholesale Goods"
        }
    ],
    "sg:phone":"+61 8 9271 2088",
    "sg:postcode":"6052",
    "sg:province":"WA",
    "sg:tags":[
        "painter"
    ],
    "wof:name":"Bonanza Paints",
    "wof:placetype":"venue"
},
  "geometry": {"coordinates":[115.88375854500001,-31.9230098724],"type":"Point"}
}