{
  "type": "Feature",
  "properties": {
    "addr:full":"197 Harbourside Darling Harbour NSW 2000",
    "addr:housenumber":"197",
    "addr:postcode":"2000",
    "addr:street":"Harbourside",
    "iso:country":"AU",
    "sg:address":"197 Harbourside",
    "sg:city":"Darling Harbour",
    "sg:classifiers":[
        {
            "category":"Restaurant",
            "type":"Food & Drink"
        }
    ],
    "sg:phone":"+61 2 9281 3711",
    "sg:postcode":"2000",
    "sg:province":"NSW",
    "sg:website":"http://www.jordonsrestaurant.com.au",
    "wof:name":"Jordons Seafood Restaurant",
    "wof:placetype":"venue"
},
  "geometry": {"coordinates":[151.19822692899999,-33.8725891113],"type":"Point"}
}