{
  "type": "Feature",
  "properties": {
    "addr:full":"Bay 2, 28a Acacia Ave Port Macquarie NSW 2444",
    "addr:housenumber":"2 28a",
    "addr:postcode":"2444",
    "addr:street":"Acacia Ave",
    "iso:country":"AU",
    "sg:address":"Bay 2, 28a Acacia Ave",
    "sg:city":"Port Macquarie",
    "sg:classifiers":[
        {
            "category":"Professional",
            "subcategory":"Printing & Photocopies",
            "type":"Services"
        }
    ],
    "sg:phone":"+61 2 6581 5323",
    "sg:postcode":"2444",
    "sg:province":"NSW",
    "sg:tags":[
        "embroidery"
    ],
    "wof:name":"Carls One Stop Printing",
    "wof:placetype":"venue"
},
  "geometry": {"coordinates":[152.88987700000001,-31.445696],"type":"Point"}
}