{
  "type": "Feature",
  "properties": {
    "iso:country":"AU",
    "sg:address":"16 Cobblers St",
    "sg:city":"Seven Mile Beach",
    "sg:classifiers":[
        {
            "category":"Professional",
            "subcategory":"Art Services",
            "type":"Services"
        }
    ],
    "sg:phone":"+61 3 6248 6987",
    "sg:postcode":"7170",
    "sg:province":"TAS",
    "sg:tags":[
        "interior",
        "decorator"
    ],
    "wof:name":"Amanda Brettingham-Moore",
    "wof:placetype":"venue"
},
  "geometry": {"coordinates":[147.50907898,-42.8549118042],"type":"Point"}
}