{
  "type": "Feature",
  "properties": {
    "iso:country":"AU",
    "sg:address":"Shop 2, Brinsmead Shopping Plaza, 101 Pease St",
    "sg:city":"Cairns",
    "sg:classifiers":[
        {
            "category":"Personal",
            "subcategory":"Beauty Salon",
            "type":"Services"
        }
    ],
    "sg:phone":"+61 7 4053 3922",
    "sg:postcode":"4870",
    "sg:province":"QLD",
    "wof:name":"Total Beauty Salon",
    "wof:placetype":"venue"
},
  "geometry": {"coordinates":[145.741699219,-16.9092788696],"type":"Point"}
}