{
  "type": "Feature",
  "properties": {
    "addr:full":"69 Presto Ave Outer Harbour QLD 4740",
    "addr:housenumber":"69",
    "addr:postcode":"4740",
    "addr:street":"Presto Ave Outer",
    "iso:country":"AU",
    "sg:address":"69 Presto Ave",
    "sg:city":"Outer Harbour",
    "sg:classifiers":[
        {
            "category":"Wholesale",
            "subcategory":"Machinery & Supplies",
            "type":"Manufacturing & Wholesale Goods"
        }
    ],
    "sg:phone":"+61 7 4955 6186",
    "sg:postcode":"4740",
    "sg:province":"QLD",
    "sg:tags":[
        "distributor",
        "crane",
        "mfrs"
    ],
    "wof:name":"KCI Konecranes",
    "wof:placetype":"venue"
},
  "geometry": {"coordinates":[149.21170000000001,-21.109825],"type":"Point"}
}