{
  "type": "Feature",
  "properties": {
    "iso:country":"AU",
    "sg:address":"29 Jarrah Drv",
    "sg:city":"Braeside",
    "sg:classifiers":[
        {
            "category":"Home & Garden",
            "subcategory":"Home Furnishings",
            "type":"Retail Goods"
        }
    ],
    "sg:phone":"+61 3 9588 1793",
    "sg:postcode":"3195",
    "sg:province":"VIC",
    "sg:tags":[
        "shower",
        "screen"
    ],
    "wof:name":"Tracer Aluminium Aust Pty Ltd",
    "wof:placetype":"venue"
},
  "geometry": {"coordinates":[145.11085510300001,-38.0035095215],"type":"Point"}
}