{
  "type": "Feature",
  "properties": {
    "iso:country":"AU",
    "sg:address":"18 Griffith Ave",
    "sg:city":"North Bondi",
    "sg:classifiers":[
        {
            "category":"Building & Trades",
            "subcategory":"Construction",
            "type":"Services"
        }
    ],
    "sg:phone":"+61 2 9365 5543",
    "sg:postcode":"2026",
    "sg:province":"NSW",
    "sg:tags":[
        "contractor"
    ],
    "wof:name":"Adam L. Kovkin Constructions",
    "wof:placetype":"venue"
},
  "geometry": {"coordinates":[151.27296447800001,-33.8842086792],"type":"Point"}
}