{
  "type": "Feature",
  "properties": {
    "addr:full":"35 Tenth St Mildura VIC 3500",
    "addr:housenumber":"35",
    "addr:postcode":"3500",
    "addr:street":"Tenth St",
    "iso:country":"AU",
    "sg:address":"35 Tenth St",
    "sg:city":"Mildura",
    "sg:classifiers":[
        {
            "category":"Retail",
            "subcategory":"Auto Repair",
            "type":"Services"
        }
    ],
    "sg:phone":"+61 3 5021 2358",
    "sg:postcode":"3500",
    "sg:province":"VIC",
    "sg:tags":[
        "repairer",
        "motor",
        "engineer"
    ],
    "wof:name":"Phil Smith Automotive",
    "wof:placetype":"venue"
},
  "geometry": {"coordinates":[142.16737365700001,-34.1950645447],"type":"Point"}
}