{
  "type": "Feature",
  "properties": {
    "addr:full":"29 Harcourt St Weetangera ACT 2614",
    "addr:housenumber":"29",
    "addr:postcode":"2614",
    "addr:street":"Harcourt St Weetangera",
    "iso:country":"AU",
    "sg:address":"29 Harcourt St",
    "sg:city":"Weetangera",
    "sg:classifiers":[
        {
            "category":"Professional",
            "subcategory":"Computer Services",
            "type":"Services"
        }
    ],
    "sg:phone":"+61 2 6278 3156",
    "sg:postcode":"2614",
    "sg:province":"ACT",
    "sg:tags":[
        "consultant",
        "system"
    ],
    "wof:name":"Jebel Consultant Group Pty Ltd",
    "wof:placetype":"venue"
},
  "geometry": {"coordinates":[149.049591064,-35.2563362122],"type":"Point"}
}