{
  "type": "Feature",
  "properties": {
    "addr:full":"4 Harding Rd Warrandyte South VIC 3134",
    "addr:housenumber":"4",
    "addr:postcode":"3134",
    "addr:street":"Harding Rd",
    "iso:country":"AU",
    "sg:address":"4 Harding Rd",
    "sg:city":"Warrandyte South",
    "sg:classifiers":[
        {
            "category":"Building & Trades",
            "subcategory":"Plumbing",
            "type":"Services"
        }
    ],
    "sg:phone":"+61 3 9844 0668",
    "sg:postcode":"3134",
    "sg:province":"VIC",
    "sg:tags":[
        "plumber",
        "gasfitters"
    ],
    "wof:name":"Smead Plumbing",
    "wof:placetype":"venue"
},
  "geometry": {"coordinates":[145.233520508,-37.7502365112],"type":"Point"}
}