{
  "type": "Feature",
  "properties": {
    "addr:full":"2 Forge St Welshpool WA 6106",
    "addr:housenumber":"2",
    "addr:postcode":"6106",
    "addr:street":"Forge St",
    "iso:country":"AU",
    "sg:address":"2 Forge St",
    "sg:city":"Welshpool",
    "sg:classifiers":[
        {
            "category":"Building & Trades",
            "subcategory":"Equipment Rental",
            "type":"Services"
        }
    ],
    "sg:phone":"+61 1800 812 424",
    "sg:postcode":"6106",
    "sg:province":"WA",
    "sg:tags":[
        "demolition",
        "contractor"
    ],
    "wof:name":"McMahon Services",
    "wof:placetype":"venue"
},
  "geometry": {"coordinates":[115.93122863799999,-31.9888458252],"type":"Point"}
}