{
  "type": "Feature",
  "properties": {
    "addr:full":"Lot 21 Old Pacific Hwy Palmdale NSW 2258",
    "addr:postcode":"2258",
    "addr:street":"Old Pacific Hwy",
    "iso:country":"AU",
    "sg:address":"Lot 21 Old Pacific Hwy",
    "sg:city":"Palmdale",
    "sg:classifiers":[
        {
            "category":"Retail",
            "subcategory":"Funeral Services",
            "type":"Services"
        }
    ],
    "sg:phone":"+61 2 4334 2455",
    "sg:postcode":"2258",
    "sg:province":"NSW",
    "sg:tags":[
        "cremation"
    ],
    "wof:name":"Coastwide Funeral Home",
    "wof:placetype":"venue"
},
  "geometry": {"coordinates":[151.37402343799999,-33.33177948],"type":"Point"}
}