{
  "type": "Feature",
  "properties": {
    "addr:full":"60 Main Rd Moonah TAS 7009",
    "addr:housenumber":"60",
    "addr:postcode":"7009",
    "addr:street":"Main Rd",
    "iso:country":"AU",
    "sg:address":"60 Main Rd",
    "sg:city":"Moonah",
    "sg:classifiers":[
        {
            "category":"Professional",
            "subcategory":"Research",
            "type":"Services"
        }
    ],
    "sg:phone":"+61 3 6211 1222",
    "sg:postcode":"7009",
    "sg:province":"TAS",
    "sg:tags":[
        "market"
    ],
    "wof:name":"Enterprise Marketing & Research Services",
    "wof:placetype":"venue"
},
  "geometry": {"coordinates":[147.295776367,-42.847984314],"type":"Point"}
}