{
  "type": "Feature",
  "properties": {
    "iso:country":"AU",
    "sg:address":"63 Kitchner St",
    "sg:city":"Trafalgar",
    "sg:classifiers":[
        {
            "category":"Utilities",
            "subcategory":"Electric",
            "type":"Services"
        }
    ],
    "sg:phone":"+61 3 5633 1332",
    "sg:postcode":"3824",
    "sg:province":"VIC",
    "sg:tags":[
        "electrical",
        "contractor"
    ],
    "wof:name":"Thomas Ray Electrcial Contractor",
    "wof:placetype":"venue"
},
  "geometry": {"coordinates":[146.156158,-38.209545],"type":"Point"}
}