{
  "type": "Feature",
  "properties": {
    "iso:country":"AU",
    "sg:address":"Unit 2/ 5 Blamey Pl",
    "sg:city":"O'Connor",
    "sg:classifiers":[
        {
            "category":"Shopping",
            "subcategory":"Pets & Pet Supplies",
            "type":"Retail Goods"
        }
    ],
    "sg:phone":"+61 8 9331 3149",
    "sg:postcode":"6163",
    "sg:province":"WA",
    "sg:tags":[
        "equipment",
        "foundry"
    ],
    "wof:name":"Oborne Patternmakers",
    "wof:placetype":"venue"
},
  "geometry": {"coordinates":[115.78904,-32.056858],"type":"Point"}
}