{
  "type": "Feature",
  "properties": {
    "addr:full":"Unit 7/ 28 Central Park Ave Ashmore QLD 4214",
    "addr:postcode":"4214",
    "addr:street":"Central Park Ave",
    "iso:country":"AU",
    "sg:address":"Unit 7/ 28 Central Park Ave",
    "sg:city":"Ashmore",
    "sg:classifiers":[
        {
            "category":"Professional",
            "subcategory":"Detective & Security Services",
            "type":"Services"
        }
    ],
    "sg:phone":"+61 7 5597 3333",
    "sg:postcode":"4214",
    "sg:province":"QLD",
    "sg:tags":[
        "consultant",
        "system"
    ],
    "wof:name":"Tank Security (Qld) Pty Ltd",
    "wof:placetype":"venue"
},
  "geometry": {"coordinates":[153.35978698700001,-27.9873371124],"type":"Point"}
}