{
  "type": "Feature",
  "properties": {
    "addr:full":"908- 910 Victoria Rd West Ryde NSW 2114",
    "addr:housenumber":"910",
    "addr:postcode":"2114",
    "addr:street":"Victoria Rd",
    "iso:country":"AU",
    "sg:address":"908- 910 Victoria Rd",
    "sg:city":"West Ryde",
    "sg:classifiers":[
        {
            "category":"Home & Garden",
            "subcategory":"Building Materials",
            "type":"Retail Goods"
        }
    ],
    "sg:phone":"+61 2 9807 7777",
    "sg:postcode":"2114",
    "sg:province":"NSW",
    "sg:tags":[
        "ventilating",
        "equipment",
        "system"
    ],
    "wof:name":"Buildserv Ventilation",
    "wof:placetype":"venue"
},
  "geometry": {"coordinates":[151.088058472,-33.8078155518],"type":"Point"}
}