{
  "type": "Feature",
  "properties": {
    "addr:full":"318 Ingleton St Exmouth WA 6707",
    "addr:housenumber":"318",
    "addr:postcode":"6707",
    "addr:street":"Ingleton St",
    "iso:country":"AU",
    "sg:address":"318 Ingleton St",
    "sg:city":"Exmouth",
    "sg:classifiers":[
        {
            "category":"Building & Trades",
            "subcategory":"Cleaning & Sanitation",
            "type":"Services"
        }
    ],
    "sg:phone":"+61 8 9949 1570",
    "sg:postcode":"6707",
    "sg:province":"WA",
    "sg:tags":[
        "industrial",
        "commercial",
        "contractor"
    ],
    "wof:name":"Exmouth Carpet Care",
    "wof:placetype":"venue"
},
  "geometry": {"coordinates":[114.118896484,-21.9356193542],"type":"Point"}
}