{
  "type": "Feature",
  "properties": {
    "addr:full":"5 Clarendon St Benalla VIC 3672",
    "addr:housenumber":"5",
    "addr:postcode":"3672",
    "addr:street":"Clarendon St",
    "iso:country":"AU",
    "sg:address":"5 Clarendon St",
    "sg:city":"Benalla",
    "sg:classifiers":[
        {
            "category":"Retail",
            "subcategory":"Car Wash",
            "type":"Services"
        }
    ],
    "sg:phone":"+61 415 436 145",
    "sg:postcode":"3672",
    "sg:province":"VIC",
    "sg:tags":[
        "truck",
        "cleaning"
    ],
    "wof:name":"R & M Detailing",
    "wof:placetype":"venue"
},
  "geometry": {"coordinates":[145.99357599999999,-36.548901],"type":"Point"}
}