{
  "type": "Feature",
  "properties": {
    "iso:country":"AU",
    "sg:address":"23 Denison St",
    "sg:city":"Hamilton",
    "sg:classifiers":[
        {
            "category":"Health Services",
            "subcategory":"Doctor",
            "type":"Services"
        }
    ],
    "sg:phone":"+61 2 4969 1066",
    "sg:postcode":"2303",
    "sg:province":"NSW",
    "sg:tags":[
        "medical",
        "practitioner"
    ],
    "wof:name":"Dr C Harrington",
    "wof:placetype":"venue"
},
  "geometry": {"coordinates":[151.739273,-32.925159],"type":"Point"}
}