{
  "type": "Feature",
  "properties": {
    "addr:full":"Shop 13 Virginia Shopping Cntr Virginia SA 5120",
    "addr:housenumber":"shop 13",
    "addr:postcode":"5120",
    "addr:street":"Virginia Shopping Cntr",
    "iso:country":"AU",
    "sg:address":"Shop 13 Virginia Shopping Cntr",
    "sg:city":"Virginia",
    "sg:classifiers":[
        {
            "category":"Education",
            "subcategory":"School",
            "type":"Public Place"
        }
    ],
    "sg:phone":"+61 8 8380 9997",
    "sg:postcode":"5120",
    "sg:province":"SA",
    "sg:tags":[
        "supply"
    ],
    "wof:name":"899 Office Supplies",
    "wof:placetype":"venue"
},
  "geometry": {"coordinates":[138.56080627399999,-34.6675415039],"type":"Point"}
}