{
  "type": "Feature",
  "properties": {
    "addr:full":"100 Beach Rd Christies Beach SA 5165",
    "addr:housenumber":"100",
    "addr:postcode":"5165",
    "addr:street":"Beach Rd",
    "iso:country":"AU",
    "sg:address":"100 Beach Rd",
    "sg:city":"Christies Beach",
    "sg:classifiers":[
        {
            "category":"Health Services",
            "subcategory":"Doctor",
            "type":"Services"
        }
    ],
    "sg:phone":"+61 8 8384 4444",
    "sg:postcode":"5165",
    "sg:province":"SA",
    "sg:tags":[
        "medical",
        "practitioner"
    ],
    "wof:name":"Fong Sonnie",
    "wof:placetype":"venue"
},
  "geometry": {"coordinates":[138.481033325,-35.1390457153],"type":"Point"}
}