{
  "type": "Feature",
  "properties": {
    "addr:full":"48 Boss Ave Marleston SA 5033",
    "addr:housenumber":"48",
    "addr:postcode":"5033",
    "addr:street":"Boss Ave",
    "iso:country":"AU",
    "sg:address":"48 Boss Ave",
    "sg:city":"Marleston",
    "sg:classifiers":[
        {
            "category":"Mining & Drilling",
            "type":"Manufacturing & Wholesale Goods"
        }
    ],
    "sg:phone":"+61 413 339 333",
    "sg:postcode":"5033",
    "sg:province":"SA",
    "sg:tags":[
        "boring",
        "contractor"
    ],
    "wof:name":"A.A. Boring & Drilling",
    "wof:placetype":"venue"
},
  "geometry": {"coordinates":[138.55470275900001,-34.9470977783],"type":"Point"}
}