{
  "type": "Feature",
  "properties": {
    "addr:full":"PO Box 65 Sanctuary Point NSW 2540",
    "addr:postcode":"2540",
    "iso:country":"AU",
    "sg:address":"PO Box 65",
    "sg:city":"Sanctuary Point",
    "sg:classifiers":[
        {
            "category":"Retail",
            "subcategory":"Auto Rental",
            "type":"Services"
        }
    ],
    "sg:phone":"+61 2 4443 8888",
    "sg:postcode":"2540",
    "sg:province":"NSW",
    "sg:tags":[
        "chauffeur",
        "car",
        "hire",
        "driven",
        "limousine"
    ],
    "wof:name":"Jervis Bay Airport Express",
    "wof:placetype":"venue"
},
  "geometry": {"coordinates":[150.62261962900001,-35.1057090759],"type":"Point"}
}