{
  "type": "Feature",
  "properties": {
    "addr:full":"232 Hoskins St Temora NSW 2666",
    "addr:housenumber":"232",
    "addr:postcode":"2666",
    "addr:street":"Hoskins St",
    "iso:country":"AU",
    "sg:address":"232 Hoskins St",
    "sg:city":"Temora",
    "sg:classifiers":[
        {
            "category":"Banks & Credit Unions",
            "subcategory":"Bank",
            "type":"Services"
        }
    ],
    "sg:phone":"+61 2 6977 2808",
    "sg:postcode":"2666",
    "sg:province":"NSW",
    "wof:name":"St.George Bank Limited",
    "wof:placetype":"venue"
},
  "geometry": {"coordinates":[147.53421020499999,-34.4482116699],"type":"Point"}
}