{
  "type": "Feature",
  "properties": {
    "addr:full":"2 Royal Pl St Clair NSW 2759",
    "addr:housenumber":"2",
    "addr:postcode":"2759",
    "addr:street":"Royal Pl St",
    "iso:country":"AU",
    "sg:address":"2 Royal Pl",
    "sg:city":"St Clair",
    "sg:classifiers":[
        {
            "category":"Professional",
            "subcategory":"Art Services",
            "type":"Services"
        }
    ],
    "sg:phone":"+61 2 9834 3646",
    "sg:postcode":"2759",
    "sg:province":"NSW",
    "sg:tags":[
        "decorator",
        "painter"
    ],
    "wof:name":"Alfy Painting",
    "wof:placetype":"venue"
},
  "geometry": {"coordinates":[150.79444885300001,-33.7904701233],"type":"Point"}
}