{
  "type": "Feature",
  "properties": {
    "addr:full":"41 Jonal Drv Mawson Lakes SA 5095",
    "addr:housenumber":"41",
    "addr:postcode":"5095",
    "addr:street":"Jonal Drv",
    "iso:country":"AU",
    "sg:address":"41 Jonal Drv",
    "sg:city":"Mawson Lakes",
    "sg:classifiers":[
        {
            "category":"Retail",
            "subcategory":"Storage",
            "type":"Services"
        }
    ],
    "sg:phone":"+61 8 8260 7611",
    "sg:postcode":"5095",
    "sg:province":"SA",
    "sg:tags":[
        "removal",
        "furniture"
    ],
    "wof:name":"Reynella Removals",
    "wof:placetype":"venue"
},
  "geometry": {"coordinates":[138.601486206,-34.8235626221],"type":"Point"}
}