{
  "type": "Feature",
  "properties": {
    "addr:full":"34- 36 Lakeside Ave Reservoir VIC 3073",
    "addr:housenumber":"36",
    "addr:postcode":"3073",
    "addr:street":"Lakeside Ave",
    "iso:country":"AU",
    "sg:address":"34- 36 Lakeside Ave",
    "sg:city":"Reservoir",
    "sg:classifiers":[
        {
            "category":"Shopping",
            "subcategory":"Stationery & Office Supplies",
            "type":"Retail Goods"
        }
    ],
    "sg:phone":"+61 3 9474 4200",
    "sg:postcode":"3073",
    "sg:province":"VIC",
    "sg:tags":[
        "packaging",
        "material"
    ],
    "wof:name":"Silawrap International",
    "wof:placetype":"venue"
},
  "geometry": {"coordinates":[144.98866272000001,-37.7073631287],"type":"Point"}
}