{
  "type": "Feature",
  "properties": {
    "addr:full":"Shop 76 Warringah Mall Brookvale NSW 2100",
    "addr:housenumber":"shop 76 warringah mall",
    "addr:postcode":"2100",
    "iso:country":"AU",
    "sg:address":"Shop 76 Warringah Mall",
    "sg:city":"Brookvale",
    "sg:classifiers":[
        {
            "category":"Shopping",
            "subcategory":"Clothing, Apparel, & Fashions",
            "type":"Retail Goods"
        }
    ],
    "sg:phone":"+61 2 9905 3908",
    "sg:postcode":"2100",
    "sg:province":"NSW",
    "sg:tags":[
        "lady",
        "wear"
    ],
    "wof:name":"Sussan",
    "wof:placetype":"venue"
},
  "geometry": {"coordinates":[151.27386474599999,-33.7549552917],"type":"Point"}
}