{
  "type": "Feature",
  "properties": {
    "iso:country":"AU",
    "sg:address":"56- 60 Munibung Rd",
    "sg:city":"Cardiff",
    "sg:classifiers":[
        {
            "category":"Building & Trades",
            "subcategory":"Construction",
            "type":"Services"
        }
    ],
    "sg:phone":"+61 2 4956 7133",
    "sg:postcode":"2285",
    "sg:province":"NSW",
    "sg:tags":[
        "window",
        "timber"
    ],
    "wof:name":"Trend Windows & Doors",
    "wof:placetype":"venue"
},
  "geometry": {"coordinates":[151.64268493599999,-32.9430084229],"type":"Point"}
}