{
  "type": "Feature",
  "properties": {
    "addr:full":"101 Evans St Sunbury VIC 3429",
    "addr:housenumber":"101",
    "addr:postcode":"3429",
    "addr:street":"Evans St",
    "iso:country":"AU",
    "sg:address":"101 Evans St",
    "sg:city":"Sunbury",
    "sg:classifiers":[
        {
            "category":"Food & Beverages",
            "subcategory":"Bakery",
            "type":"Retail Goods"
        }
    ],
    "sg:phone":"+61 3 9744 1560",
    "sg:postcode":"3429",
    "sg:province":"VIC",
    "sg:tags":[
        "baker"
    ],
    "wof:name":"Lai Bakery",
    "wof:placetype":"venue"
},
  "geometry": {"coordinates":[144.72836303700001,-37.5813064575],"type":"Point"}
}