{
  "type": "Feature",
  "properties": {
    "addr:full":"188 Albert St Brisbane QLD 4000",
    "addr:housenumber":"188",
    "addr:postcode":"4000",
    "addr:street":"Albert St",
    "iso:country":"AU",
    "sg:address":"188 Albert St",
    "sg:city":"Brisbane",
    "sg:classifiers":[
        {
            "category":"Shopping",
            "subcategory":"Clothing, Apparel, & Fashions",
            "type":"Retail Goods"
        }
    ],
    "sg:phone":"+61 7 3221 7278",
    "sg:postcode":"4000",
    "sg:province":"QLD",
    "sg:tags":[
        "lady",
        "wear"
    ],
    "wof:name":"Stiletto",
    "wof:placetype":"venue"
},
  "geometry": {"coordinates":[153.02679443400001,-27.4714126587],"type":"Point"}
}