{
  "type": "Feature",
  "properties": {
    "addr:full":"1240 Glenhuntly Rd Glen Huntly VIC 3163",
    "addr:housenumber":"1240",
    "addr:postcode":"3163",
    "addr:street":"Glenhuntly Rd",
    "iso:country":"AU",
    "sg:address":"1240 Glenhuntly Rd",
    "sg:city":"Glen Huntly",
    "sg:classifiers":[
        {
            "category":"Sports & Exercise",
            "subcategory":"Gym",
            "type":"Entertainment"
        }
    ],
    "sg:phone":"+61 417 396 375",
    "sg:postcode":"3163",
    "sg:province":"VIC",
    "sg:tags":[
        "personal",
        "trainer",
        "fitness"
    ],
    "wof:name":"Stef Hanson Personal Training",
    "wof:placetype":"venue"
},
  "geometry": {"coordinates":[145.045944214,-37.8899688721],"type":"Point"}
}