{
  "type": "Feature",
  "properties": {
    "addr:full":"734 Beaufort St Mt Lawley WA 6050",
    "addr:housenumber":"734",
    "addr:postcode":"6050",
    "addr:street":"Beaufort St",
    "iso:country":"AU",
    "sg:address":"734 Beaufort St",
    "sg:city":"Mt Lawley",
    "sg:classifiers":[
        {
            "category":"Education",
            "subcategory":"University",
            "type":"Public Place"
        }
    ],
    "sg:phone":"+61 8 9271 6816",
    "sg:postcode":"6050",
    "sg:province":"WA",
    "sg:tags":[
        "educational",
        "organisation",
        "cultural"
    ],
    "wof:name":"Hungarian Community Hall",
    "wof:placetype":"venue"
},
  "geometry": {"coordinates":[115.876831055,-31.9292125702],"type":"Point"}
}