{
  "type": "Feature",
  "properties": {
    "addr:full":"17 Seymour St Traralgon VIC 3844",
    "addr:housenumber":"17",
    "addr:postcode":"3844",
    "addr:street":"Seymour St",
    "iso:country":"AU",
    "sg:address":"17 Seymour St",
    "sg:city":"Traralgon",
    "sg:classifiers":[
        {
            "category":"Food & Beverages",
            "subcategory":"Supermarket",
            "type":"Retail Goods"
        }
    ],
    "sg:phone":"+61 3 5174 2488",
    "sg:postcode":"3844",
    "sg:province":"VIC",
    "sg:tags":[
        "grocery",
        "store"
    ],
    "wof:name":"NQR Supermarket Clearance Outlets",
    "wof:placetype":"venue"
},
  "geometry": {"coordinates":[146.53903198200001,-38.1964149475],"type":"Point"}
}