{
  "type": "Feature",
  "properties": {
    "addr:full":"12 Anne St Port Macquarie NSW 2444",
    "addr:housenumber":"12",
    "addr:postcode":"2444",
    "addr:street":"Anne St",
    "iso:country":"AU",
    "sg:address":"12 Anne St",
    "sg:city":"Port Macquarie",
    "sg:classifiers":[
        {
            "category":"Personal",
            "type":"Services"
        }
    ],
    "sg:phone":"+61 2 6584 7077",
    "sg:postcode":"2444",
    "sg:province":"NSW",
    "sg:tags":[
        "gift"
    ],
    "wof:name":"Baskets By Design",
    "wof:placetype":"venue"
},
  "geometry": {"coordinates":[152.911179,-31.438734],"type":"Point"}
}