{
  "type": "Feature",
  "properties": {
    "addr:full":"22A Canberra St Randwick NSW 2031",
    "addr:housenumber":"22a",
    "addr:postcode":"2031",
    "addr:street":"Canberra St",
    "iso:country":"AU",
    "sg:address":"22A Canberra St",
    "sg:city":"Randwick",
    "sg:classifiers":[
        {
            "category":"Health Services",
            "subcategory":"Health Practitioner",
            "type":"Services"
        }
    ],
    "sg:phone":"+61 2 9398 3621",
    "sg:postcode":"2031",
    "sg:province":"NSW",
    "sg:tags":[
        "physiotherapist"
    ],
    "wof:name":"Canberra Street Physiotherapy and Allied Health Centre",
    "wof:placetype":"venue"
},
  "geometry": {"coordinates":[151.24357605,-33.9247550964],"type":"Point"}
}