{
  "type": "Feature",
  "properties": {
    "addr:full":"35 Derinya Drv Frankston South VIC 3199",
    "addr:housenumber":"35",
    "addr:postcode":"3199",
    "addr:street":"Derinya Drv",
    "iso:country":"AU",
    "sg:address":"35 Derinya Drv",
    "sg:city":"Frankston South",
    "sg:classifiers":[
        {
            "category":"Education",
            "subcategory":"Special Training",
            "type":"Public Place"
        }
    ],
    "sg:phone":"+61 3 9787 8591",
    "sg:postcode":"3199",
    "sg:province":"VIC",
    "sg:tags":[
        "development"
    ],
    "sg:website":"http://www.interactiveevents.com.au",
    "wof:name":"Interactive Events",
    "wof:placetype":"venue"
},
  "geometry": {"coordinates":[145.12478637699999,-38.1730728149],"type":"Point"}
}