{
  "type": "Feature",
  "properties": {
    "addr:full":"1 Birch St South Bunbury WA 6230",
    "addr:housenumber":"1",
    "addr:postcode":"6230",
    "addr:street":"Birch St South",
    "iso:country":"AU",
    "sg:address":"1 Birch St",
    "sg:city":"South Bunbury",
    "sg:classifiers":[
        {
            "category":"Manufacturing",
            "subcategory":"Jewelry",
            "type":"Manufacturing & Wholesale Goods"
        }
    ],
    "sg:phone":"+61 8 9792 5742",
    "sg:postcode":"6230",
    "sg:province":"WA",
    "sg:tags":[
        "mfrg",
        "jeweller"
    ],
    "wof:name":"Mystic Blue",
    "wof:placetype":"venue"
},
  "geometry": {"coordinates":[115.625587,-33.337681],"type":"Point"}
}