{
  "type": "Feature",
  "properties": {
    "addr:full":"Un 3/ 7 Cowderoy St St Kilda West VIC 3182",
    "addr:postcode":"3182",
    "addr:street":"Cowderoy St",
    "iso:country":"AU",
    "sg:address":"Un 3/ 7 Cowderoy St",
    "sg:city":"St Kilda West",
    "sg:classifiers":[
        {
            "category":"Professional",
            "subcategory":"Engineering",
            "type":"Services"
        }
    ],
    "sg:phone":"+61 3 9537 2292",
    "sg:postcode":"3182",
    "sg:province":"VIC",
    "sg:tags":[
        "consulting",
        "engineer"
    ],
    "wof:name":"Barden Consulting Engineers Pty Ltd",
    "wof:placetype":"venue"
},
  "geometry": {"coordinates":[144.97102355999999,-37.856628418],"type":"Point"}
}