{
  "type": "Feature",
  "properties": {
    "iso:country":"AU",
    "sg:address":"Suite 3a, 12 Ferry St",
    "sg:city":"Nerang",
    "sg:classifiers":[
        {
            "category":"Wholesale",
            "subcategory":"Non-durable Goods",
            "type":"Manufacturing & Wholesale Goods"
        }
    ],
    "sg:phone":"+61 7 5596 5883",
    "sg:postcode":"4211",
    "sg:province":"QLD",
    "sg:tags":[
        "wholesaler",
        "mfrs",
        "cosmetic"
    ],
    "wof:name":"Australian Beauty Professionals",
    "wof:placetype":"venue"
},
  "geometry": {"coordinates":[153.33674621599999,-27.9896621704],"type":"Point"}
}