{
  "type": "Feature",
  "properties": {
    "addr:full":"58 Days Rd Grange QLD 4051",
    "addr:housenumber":"58",
    "addr:postcode":"4051",
    "addr:street":"Days Rd",
    "iso:country":"AU",
    "sg:address":"58 Days Rd",
    "sg:city":"Grange",
    "sg:classifiers":[
        {
            "category":"Shopping",
            "subcategory":"Stationery & Office Supplies",
            "type":"Retail Goods"
        }
    ],
    "sg:phone":"+61 7 3356 3244",
    "sg:postcode":"4051",
    "sg:province":"QLD",
    "sg:tags":[
        "equipment",
        "display",
        "exhibition"
    ],
    "wof:name":"A Head Signs",
    "wof:placetype":"venue"
},
  "geometry": {"coordinates":[153.02052307100001,-27.4268779755],"type":"Point"}
}