{
  "type": "Feature",
  "properties": {
    "iso:country":"AU",
    "sg:address":"85 Bentinck St",
    "sg:city":"Portland",
    "sg:classifiers":[
        {
            "category":"Food & Beverages",
            "subcategory":"Fruits & Vegetables",
            "type":"Retail Goods"
        }
    ],
    "sg:phone":"+61 3 5523 1335",
    "sg:postcode":"3305",
    "sg:province":"VIC",
    "sg:tags":[
        "consultant",
        "catering"
    ],
    "wof:name":"Port Of Call",
    "wof:placetype":"venue"
},
  "geometry": {"coordinates":[141.60609435999999,-38.3488426208],"type":"Point"}
}