{
  "type": "Feature",
  "properties": {
    "addr:full":"7 Ainsley Crt Westfield WA 6111",
    "addr:housenumber":"7",
    "addr:postcode":"6111",
    "addr:street":"Ainsley Crt",
    "iso:country":"AU",
    "sg:address":"7 Ainsley Crt",
    "sg:city":"Westfield",
    "sg:classifiers":[
        {
            "category":"Personal",
            "type":"Services"
        }
    ],
    "sg:phone":"+61 411 043 620",
    "sg:postcode":"6111",
    "sg:province":"WA",
    "sg:tags":[
        "reducing",
        "treatment",
        "weight"
    ],
    "wof:name":"Herbal Life",
    "wof:placetype":"venue"
},
  "geometry": {"coordinates":[115.993476868,-32.1204338074],"type":"Point"}
}