{
  "type": "Feature",
  "properties": {
    "addr:full":"Cotlew St Ashmore QLD 4214",
    "addr:postcode":"4214",
    "addr:street":"Cotlew St",
    "iso:country":"AU",
    "sg:address":"Cotlew St",
    "sg:city":"Ashmore",
    "sg:classifiers":[
        {
            "category":"Education",
            "subcategory":"Music School",
            "type":"Public Place"
        }
    ],
    "sg:phone":"+61 7 5564 9553",
    "sg:postcode":"4214",
    "sg:province":"QLD",
    "sg:tags":[
        "singing",
        "teacher"
    ],
    "wof:name":"Gold Coast Voice Studio",
    "wof:placetype":"venue"
},
  "geometry": {"coordinates":[153.382720947,-27.9863300323],"type":"Point"}
}