{
  "type": "Feature",
  "properties": {
    "iso:country":"AU",
    "sg:address":"Unit 2/ 24 Eddie Rd",
    "sg:city":"Minchinbury",
    "sg:classifiers":[
        {
            "category":"Arts & Performance",
            "subcategory":"Dance",
            "type":"Entertainment"
        }
    ],
    "sg:phone":"+61 2 9832 3688",
    "sg:postcode":"2770",
    "sg:province":"NSW",
    "sg:tags":[
        "theatrical",
        "ballet",
        "tuition"
    ],
    "wof:name":"Donna Jeans Danceforce",
    "wof:placetype":"venue"
},
  "geometry": {"coordinates":[150.81625366200001,-33.7845077515],"type":"Point"}
}