{
  "type": "Feature",
  "properties": {
    "iso:country":"AU",
    "sg:address":"6 Wolseley Rd",
    "sg:city":"Mosman",
    "sg:classifiers":[
        {
            "category":"Professional",
            "subcategory":"Art Services",
            "type":"Services"
        }
    ],
    "sg:phone":"+61 414 555 199",
    "sg:postcode":"2088",
    "sg:province":"NSW",
    "sg:tags":[
        "decorator",
        "painter"
    ],
    "wof:name":"Annette Barlow - Wall To Wall Art/Mural/Fine Art & Paint Faux Finishes",
    "wof:placetype":"venue"
},
  "geometry": {"coordinates":[151.25454711899999,-33.8329734802],"type":"Point"}
}