{
  "type": "Feature",
  "properties": {
    "addr:full":"8 Glenelg Crt Melton South VIC 3338",
    "addr:housenumber":"8",
    "addr:postcode":"3338",
    "addr:street":"Glenelg Crt",
    "iso:country":"AU",
    "sg:address":"8 Glenelg Crt",
    "sg:city":"Melton South",
    "sg:classifiers":[
        {
            "category":"Insurance",
            "subcategory":"Hazard Insurance",
            "type":"Services"
        }
    ],
    "sg:phone":"+61 3 9743 2275",
    "sg:postcode":"3338",
    "sg:province":"VIC",
    "sg:tags":[
        "fire",
        "accident",
        "marine"
    ],
    "wof:name":"Arthur J Neumann & Associates",
    "wof:placetype":"venue"
},
  "geometry": {"coordinates":[144.564133,-37.699604],"type":"Point"}
}