{
  "type": "Feature",
  "properties": {
    "iso:country":"AU",
    "sg:address":"416 Hume Hwy",
    "sg:city":"Yagoona",
    "sg:classifiers":[
        {
            "category":"Retail",
            "subcategory":"Car Wash",
            "type":"Services"
        }
    ],
    "sg:phone":"+61 2 9793 7001",
    "sg:postcode":"2199",
    "sg:province":"NSW",
    "sg:tags":[
        "truck",
        "cleaning"
    ],
    "wof:name":"Sparkles Carwash Coffee Lounge Pty Limited",
    "wof:placetype":"venue"
},
  "geometry": {"coordinates":[151.014053,-33.905441],"type":"Point"}
}