{
  "type": "Feature",
  "properties": {
    "addr:full":"31 Goldie St Wynyard TAS 7325",
    "addr:housenumber":"31",
    "addr:postcode":"7325",
    "addr:street":"Goldie St",
    "iso:country":"AU",
    "sg:address":"31 Goldie St",
    "sg:city":"Wynyard",
    "sg:classifiers":[
        {
            "category":"Home & Garden",
            "subcategory":"Carpets & Floor Coverings",
            "type":"Retail Goods"
        }
    ],
    "sg:phone":"+61 3 6442 4027",
    "sg:postcode":"7325",
    "sg:province":"TAS",
    "wof:name":"Flloor & Wall FX",
    "wof:placetype":"venue"
},
  "geometry": {"coordinates":[145.727676,-40.989075],"type":"Point"}
}