{
  "type": "Feature",
  "properties": {
    "iso:country":"AU",
    "sg:address":"659 Stanley St",
    "sg:city":"Woolloongabba",
    "sg:classifiers":[
        {
            "category":"Shopping",
            "subcategory":"Party Supplies",
            "type":"Retail Goods"
        }
    ],
    "sg:phone":"+61 7 3255 1990",
    "sg:postcode":"4102",
    "sg:province":"QLD",
    "sg:tags":[
        "hire",
        "costume"
    ],
    "sg:website":"http://www.disguises.com.au",
    "wof:name":"Disguises Fancy Dress Costume Hire",
    "wof:placetype":"venue"
},
  "geometry": {"coordinates":[153.030883789,-27.4859313965],"type":"Point"}
}