{
  "type": "Feature",
  "properties": {
    "iso:country":"AU",
    "sg:address":"U 5/ 27 Crompton Rd",
    "sg:city":"Rockingham",
    "sg:classifiers":[
        {
            "category":"Home & Garden",
            "subcategory":"Building Materials",
            "type":"Retail Goods"
        }
    ],
    "sg:phone":"+61 8 9592 8886",
    "sg:postcode":"6168",
    "sg:province":"WA",
    "sg:tags":[
        "balustrading"
    ],
    "wof:name":"A 1 Stairs & Balustrading",
    "wof:placetype":"venue"
},
  "geometry": {"coordinates":[115.76696800000001,-32.274837],"type":"Point"}
}