{
  "type": "Feature",
  "properties": {
    "iso:country":"AU",
    "sg:address":"Lot- 1 Activity St",
    "sg:city":"Maryborough",
    "sg:classifiers":[
        {
            "category":"Manufacturing",
            "subcategory":"Wood Products",
            "type":"Manufacturing & Wholesale Goods"
        }
    ],
    "sg:phone":"+61 7 4123 3488",
    "sg:postcode":"4650",
    "sg:province":"QLD",
    "sg:tags":[
        "machinist"
    ],
    "wof:name":"Austral Timber & Dowel",
    "wof:placetype":"venue"
},
  "geometry": {"coordinates":[152.66566499999999,-25.492714],"type":"Point"}
}