{
  "type": "Feature",
  "properties": {
    "iso:country":"AU",
    "sg:address":"367 Old Hawkesbury Rd",
    "sg:city":"Vineyard",
    "sg:classifiers":[
        {
            "category":"Utilities",
            "subcategory":"Electric",
            "type":"Services"
        }
    ],
    "sg:phone":"+61 2 9627 2006",
    "sg:postcode":"2765",
    "sg:province":"NSW",
    "sg:tags":[
        "electrical",
        "contractor"
    ],
    "wof:name":"Smalls Pole Hire",
    "wof:placetype":"venue"
},
  "geometry": {"coordinates":[150.85777282699999,-33.6429138184],"type":"Point"}
}