{
  "type": "Feature",
  "properties": {
    "addr:full":"69 York St Beenleigh QLD 4207",
    "addr:housenumber":"69",
    "addr:postcode":"4207",
    "addr:street":"York St",
    "iso:country":"AU",
    "sg:address":"69 York St",
    "sg:city":"Beenleigh",
    "sg:classifiers":[
        {
            "category":"Professional",
            "subcategory":"Accounting & Tax Preparation",
            "type":"Services"
        }
    ],
    "sg:phone":"+61 7 3807 0264",
    "sg:postcode":"4207",
    "sg:province":"QLD",
    "sg:tags":[
        "accountant",
        "auditor"
    ],
    "wof:name":"H&R Block",
    "wof:placetype":"venue"
},
  "geometry": {"coordinates":[153.20111084000001,-27.7149028778],"type":"Point"}
}