{
  "type": "Feature",
  "properties": {
    "addr:full":"89 Winifred St Oak Park VIC 3046",
    "addr:housenumber":"89",
    "addr:postcode":"3046",
    "addr:street":"Winifred St",
    "iso:country":"AU",
    "sg:address":"89 Winifred St",
    "sg:city":"Oak Park",
    "sg:classifiers":[
        {
            "category":"Retail",
            "subcategory":"Auto Repair",
            "type":"Services"
        }
    ],
    "sg:phone":"+61 418 388 076",
    "sg:postcode":"3046",
    "sg:province":"VIC",
    "sg:tags":[
        "muffler",
        "exhaust",
        "system"
    ],
    "wof:name":"Monark Exhaust Service",
    "wof:placetype":"venue"
},
  "geometry": {"coordinates":[144.91212463400001,-37.718120575],"type":"Point"}
}