{
  "type": "Feature",
  "properties": {
    "iso:country":"AU",
    "sg:address":"9 Free St",
    "sg:city":"Beerwah",
    "sg:classifiers":[
        {
            "category":"Education",
            "subcategory":"Kindergarten",
            "type":"Public Place"
        }
    ],
    "sg:phone":"+61 7 5494 6346",
    "sg:postcode":"4519",
    "sg:province":"QLD",
    "sg:tags":[
        "pre-schools"
    ],
    "wof:name":"C&K Beerwah & District Community Kindergarten",
    "wof:placetype":"venue"
},
  "geometry": {"coordinates":[152.95784,-26.85771],"type":"Point"}
}