{
  "type": "Feature",
  "properties": {
    "addr:full":"8 Hallmark Drv Narre Warren South VIC 3805",
    "addr:housenumber":"8",
    "addr:postcode":"3805",
    "addr:street":"Hallmark Drv",
    "iso:country":"AU",
    "sg:address":"8 Hallmark Drv",
    "sg:city":"Narre Warren South",
    "sg:classifiers":[
        {
            "category":"Professional",
            "subcategory":"Art Services",
            "type":"Services"
        }
    ],
    "sg:phone":"+61 3 9704 5945",
    "sg:postcode":"3805",
    "sg:province":"VIC",
    "sg:tags":[
        "graphic",
        "designer"
    ],
    "wof:name":"Swampe Graphics",
    "wof:placetype":"venue"
},
  "geometry": {"coordinates":[145.28608700000001,-38.064007],"type":"Point"}
}