{
  "type": "Feature",
  "properties": {
    "iso:country":"AU",
    "sg:address":"501 Victoria St",
    "sg:city":"Abbotsford",
    "sg:classifiers":[
        {
            "category":"Food & Beverages",
            "subcategory":"Liquor & Beverages",
            "type":"Retail Goods"
        }
    ],
    "sg:phone":"+61 3 9427 7525",
    "sg:postcode":"3067",
    "sg:province":"VIC",
    "sg:tags":[
        "store"
    ],
    "wof:name":"McCoppins",
    "wof:placetype":"venue"
},
  "geometry": {"coordinates":[145.00312805199999,-37.8106689453],"type":"Point"}
}