{
  "type": "Feature",
  "properties": {
    "addr:full":"53 Emily St Seymour VIC 3660",
    "addr:housenumber":"53",
    "addr:postcode":"3660",
    "addr:street":"Emily St",
    "iso:country":"AU",
    "sg:address":"53 Emily St",
    "sg:city":"Seymour",
    "sg:classifiers":[
        {
            "category":"Travel",
            "subcategory":"Hotels & Motels",
            "type":"Entertainment"
        }
    ],
    "sg:phone":"+61 3 5792 2800",
    "sg:postcode":"3660",
    "sg:province":"VIC",
    "wof:name":"New Crossing Place Motel",
    "wof:placetype":"venue"
},
  "geometry": {"coordinates":[145.131134033,-37.0187644958],"type":"Point"}
}