{
  "type": "Feature",
  "properties": {
    "iso:country":"AU",
    "sg:address":"158 Margaret St",
    "sg:city":"Toowoomba",
    "sg:classifiers":[
        {
            "category":"Government",
            "subcategory":"Court House",
            "type":"Public Place"
        }
    ],
    "sg:phone":"+61 7 4639 6276",
    "sg:postcode":"4350",
    "sg:province":"QLD",
    "sg:tags":[
        "personal",
        "marriage",
        "family",
        "counselling"
    ],
    "sg:website":"http://www.counselling.infosalad.info",
    "wof:name":"Heritage Counselling & Educational Services",
    "wof:placetype":"venue"
},
  "geometry": {"coordinates":[151.95517,-27.561338],"type":"Point"}
}