{
  "type": "Feature",
  "properties": {
    "addr:full":"Unit 1, 291 Argent St Broken Hill NSW 2880",
    "addr:housenumber":"291",
    "addr:postcode":"2880",
    "addr:street":"Argent St",
    "iso:country":"AU",
    "sg:address":"Unit 1, 291 Argent St",
    "sg:city":"Broken Hill",
    "sg:classifiers":[
        {
            "category":"Education",
            "subcategory":"Special Training",
            "type":"Public Place"
        }
    ],
    "sg:phone":"+61 1300 652 236",
    "sg:postcode":"2880",
    "sg:province":"NSW",
    "sg:tags":[
        "development"
    ],
    "wof:name":"Australian Business Limited Apprenticeships Centre",
    "wof:placetype":"venue"
},
  "geometry": {"coordinates":[141.465133667,-31.9587135315],"type":"Point"}
}