{
  "type": "Feature",
  "properties": {
    "iso:country":"AU",
    "sg:address":"Condies Arcade 161 Mary St",
    "sg:city":"Gympie",
    "sg:classifiers":[
        {
            "category":"Shopping",
            "subcategory":"Clothing, Apparel, & Fashions",
            "type":"Retail Goods"
        }
    ],
    "sg:phone":"+61 7 5482 8655",
    "sg:postcode":"4570",
    "sg:province":"QLD",
    "sg:tags":[
        "boutique"
    ],
    "wof:name":"Kaya Boutique",
    "wof:placetype":"venue"
},
  "geometry": {"coordinates":[152.661056519,-26.1894741058],"type":"Point"}
}