{
  "type": "Feature",
  "properties": {
    "iso:country":"AU",
    "sg:address":"Shp1/ 149 Morley Drv East",
    "sg:city":"Kiara",
    "sg:classifiers":[
        {
            "category":"Fast Food",
            "type":"Food & Drink"
        }
    ],
    "sg:phone":"+61 8 6278 2888",
    "sg:postcode":"6054",
    "sg:province":"WA",
    "sg:tags":[
        "away",
        "take"
    ],
    "wof:name":"Bua Thai Takeaway",
    "wof:placetype":"venue"
},
  "geometry": {"coordinates":[115.937362671,-31.8873157501],"type":"Point"}
}