{
  "type": "Feature",
  "properties": {
    "addr:full":"6 William St Paddington NSW 2021",
    "addr:housenumber":"6",
    "addr:postcode":"2021",
    "addr:street":"William St",
    "iso:country":"AU",
    "sg:address":"6 William St",
    "sg:city":"Paddington",
    "sg:classifiers":[
        {
            "category":"Shopping",
            "subcategory":"Bridal",
            "type":"Retail Goods"
        }
    ],
    "sg:phone":"+61 2 9361 4427",
    "sg:postcode":"2021",
    "sg:province":"NSW",
    "sg:tags":[
        "hire",
        "wear"
    ],
    "wof:name":"Petal Bridal Couture",
    "wof:placetype":"venue"
},
  "geometry": {"coordinates":[151.228973389,-33.8858985901],"type":"Point"}
}