{
  "type": "Feature",
  "properties": {
    "addr:full":"Daniel St Leichhardt NSW 2040",
    "addr:postcode":"2040",
    "addr:street":"Daniel St",
    "iso:country":"AU",
    "sg:address":"Daniel St",
    "sg:city":"Leichhardt",
    "sg:classifiers":[
        {
            "category":"Professional",
            "subcategory":"Art Services",
            "type":"Services"
        }
    ],
    "sg:phone":"+61 2 9568 6194",
    "sg:postcode":"2040",
    "sg:province":"NSW",
    "sg:tags":[
        "graphic",
        "designer"
    ],
    "wof:name":"Colour By Design",
    "wof:placetype":"venue"
},
  "geometry": {"coordinates":[151.146805,-33.881813],"type":"Point"}
}