{
  "type": "Feature",
  "properties": {
    "iso:country":"AU",
    "sg:address":"High Schl Anzac Pde",
    "sg:city":"Chifley",
    "sg:classifiers":[
        {
            "category":"Education",
            "subcategory":"School",
            "type":"Public Place"
        }
    ],
    "sg:phone":"+61 2 9661 8000",
    "sg:postcode":"2036",
    "sg:province":"NSW",
    "sg:tags":[
        "state",
        "-",
        "nsw"
    ],
    "wof:name":"Matraville Evening College",
    "wof:placetype":"venue"
},
  "geometry": {"coordinates":[151.24446105999999,-33.9661750793],"type":"Point"}
}