{
  "type": "Feature",
  "properties": {
    "iso:country":"AU",
    "sg:address":"Federal Office Suite 4, 11",
    "sg:city":"Railway Chatswood",
    "sg:classifiers":[
        {
            "category":"Health Services",
            "subcategory":"Health Practitioner",
            "type":"Services"
        }
    ],
    "sg:phone":"+61 2 9410 0099",
    "sg:postcode":"2057",
    "sg:province":"NSW",
    "sg:tags":[
        "osteopath"
    ],
    "wof:name":"Australian Osteopathic Association",
    "wof:placetype":"venue"
},
  "geometry": {"coordinates":[151.18014500000001,-33.79377],"type":"Point"}
}