{
  "type": "Feature",
  "properties": {
    "iso:country":"AU",
    "sg:address":"252 Princes Hwy",
    "sg:city":"Sylvania Heights",
    "sg:classifiers":[
        {
            "category":"Manufacturing",
            "subcategory":"Food",
            "type":"Manufacturing & Wholesale Goods"
        }
    ],
    "sg:phone":"+61 2 9544 6960",
    "sg:postcode":"2224",
    "sg:province":"NSW",
    "sg:tags":[
        "function",
        "catering"
    ],
    "wof:name":"Gourmet Wizard",
    "wof:placetype":"venue"
},
  "geometry": {"coordinates":[151.09454345699999,-34.0133171082],"type":"Point"}
}