{
  "type": "Feature",
  "properties": {
    "addr:full":"57 Rawson Rd Guildford NSW 2161",
    "addr:housenumber":"57",
    "addr:postcode":"2161",
    "addr:street":"Rawson Rd",
    "iso:country":"AU",
    "sg:address":"57 Rawson Rd",
    "sg:city":"Guildford",
    "sg:classifiers":[
        {
            "category":"Home & Garden",
            "subcategory":"Carpets & Floor Coverings",
            "type":"Retail Goods"
        }
    ],
    "sg:phone":"+61 404 046 781",
    "sg:postcode":"2161",
    "sg:province":"NSW",
    "sg:tags":[
        "tile",
        "wall"
    ],
    "wof:name":"Asmar Tiling",
    "wof:placetype":"venue"
},
  "geometry": {"coordinates":[150.99296569800001,-33.8610992432],"type":"Point"}
}