{
  "type": "Feature",
  "properties": {
    "addr:full":"6 Pandorea St Everton Hills QLD 4053",
    "addr:housenumber":"6",
    "addr:postcode":"4053",
    "addr:street":"Pandorea St",
    "iso:country":"AU",
    "sg:address":"6 Pandorea St",
    "sg:city":"Everton Hills",
    "sg:classifiers":[
        {
            "category":"Home & Garden",
            "subcategory":"Carpets & Floor Coverings",
            "type":"Retail Goods"
        }
    ],
    "sg:phone":"+61 412 413 980",
    "sg:postcode":"4053",
    "sg:province":"QLD",
    "sg:tags":[
        "tile",
        "wall",
        "layer"
    ],
    "wof:name":"A. Alba Tiling",
    "wof:placetype":"venue"
},
  "geometry": {"coordinates":[152.968017578,-27.3945941925],"type":"Point"}
}