{
  "type": "Feature",
  "properties": {
    "addr:full":"42 Docker St Wagga Wagga NSW 2650",
    "addr:housenumber":"42",
    "addr:postcode":"2650",
    "addr:street":"Docker St",
    "iso:country":"AU",
    "sg:address":"42 Docker St",
    "sg:city":"Wagga Wagga",
    "sg:classifiers":[
        {
            "category":"Health Services",
            "subcategory":"Doctor",
            "type":"Services"
        }
    ],
    "sg:phone":"+61 2 6925 3877",
    "sg:postcode":"2650",
    "sg:province":"NSW",
    "sg:tags":[
        "medical",
        "practitioner"
    ],
    "wof:name":"Smith John Paul Dr",
    "wof:placetype":"venue"
},
  "geometry": {"coordinates":[147.35588073700001,-35.1183624268],"type":"Point"}
}