{
  "type": "Feature",
  "properties": {
    "iso:country":"AU",
    "sg:address":"42 Frawley Rd",
    "sg:city":"Eumemmerring",
    "sg:classifiers":[
        {
            "category":"Government",
            "subcategory":"Post Office",
            "type":"Public Place"
        }
    ],
    "sg:phone":"+61 3 9793 5722",
    "sg:postcode":"3177",
    "sg:province":"VIC",
    "sg:tags":[
        "box",
        "mail"
    ],
    "wof:name":"A Architectural Letterbox Co",
    "wof:placetype":"venue"
},
  "geometry": {"coordinates":[145.25279235799999,-37.9967842102],"type":"Point"}
}