{
  "type": "Feature",
  "properties": {
    "addr:full":"10 Crusade Pl Cronulla NSW 2230",
    "addr:housenumber":"10",
    "addr:postcode":"2230",
    "addr:street":"Crusade Pl",
    "iso:country":"AU",
    "sg:address":"10 Crusade Pl",
    "sg:city":"Cronulla",
    "sg:classifiers":[
        {
            "category":"Utilities",
            "subcategory":"Electric",
            "type":"Services"
        }
    ],
    "sg:phone":"+61 2 9524 2772",
    "sg:postcode":"2230",
    "sg:province":"NSW",
    "sg:tags":[
        "electrical",
        "contractor"
    ],
    "wof:name":"Prior Electrical Services Pty Ltd",
    "wof:placetype":"venue"
},
  "geometry": {"coordinates":[151.13352966299999,-34.0491485596],"type":"Point"}
}