{
  "type": "Feature",
  "properties": {
    "iso:country":"AU",
    "sg:address":"20 Aldinga St",
    "sg:city":"Brendale",
    "sg:classifiers":[
        {
            "category":"Wholesale",
            "subcategory":"Machinery & Supplies",
            "type":"Manufacturing & Wholesale Goods"
        }
    ],
    "sg:phone":"+61 7 3881 2544",
    "sg:postcode":"4500",
    "sg:province":"QLD",
    "sg:tags":[
        "distributor",
        "crane",
        "mfrs"
    ],
    "wof:name":"Australasia 600 Cranes",
    "wof:placetype":"venue"
},
  "geometry": {"coordinates":[152.97911071799999,-27.3190803528],"type":"Point"}
}