{
  "type": "Feature",
  "properties": {
    "addr:full":"Studley Rd Heidelberg VIC 3084",
    "addr:postcode":"3084",
    "addr:street":"Studley Rd",
    "iso:country":"AU",
    "sg:address":"Studley Rd",
    "sg:city":"Heidelberg",
    "sg:classifiers":[
        {
            "category":"Banks & Credit Unions",
            "subcategory":"Bank",
            "type":"Services"
        }
    ],
    "sg:phone":"+61 3 9496 5181",
    "sg:postcode":"3084",
    "sg:province":"VIC",
    "sg:tags":[
        "society"
    ],
    "wof:name":"Pulse Credit Union",
    "wof:placetype":"venue"
},
  "geometry": {"coordinates":[145.060791016,-37.7568092346],"type":"Point"}
}