{
  "type": "Feature",
  "properties": {
    "addr:full":"12- 16 St John St Launceston TAS 7250",
    "addr:housenumber":"16",
    "addr:postcode":"7250",
    "addr:street":"St John St",
    "iso:country":"AU",
    "sg:address":"12- 16 St John St",
    "sg:city":"Launceston",
    "sg:classifiers":[
        {
            "category":"Travel",
            "subcategory":"Travel Agent",
            "type":"Entertainment"
        }
    ],
    "sg:phone":"+61 1300 655 145",
    "sg:postcode":"7250",
    "sg:province":"TAS",
    "sg:tags":[
        "consultant"
    ],
    "wof:name":"Tasmania Travel Centre",
    "wof:placetype":"venue"
},
  "geometry": {"coordinates":[147.13555908199999,-41.433139801],"type":"Point"}
}