{
  "type": "Feature",
  "properties": {
    "addr:full":"20 Manchester St Hawthorn VIC 3122",
    "addr:housenumber":"20",
    "addr:postcode":"3122",
    "addr:street":"Manchester St",
    "iso:country":"AU",
    "sg:address":"20 Manchester St",
    "sg:city":"Hawthorn",
    "sg:classifiers":[
        {
            "category":"Professional",
            "subcategory":"Printing & Photocopies",
            "type":"Services"
        }
    ],
    "sg:phone":"+61 3 8800 3889",
    "sg:postcode":"3122",
    "sg:province":"VIC",
    "sg:tags":[
        "publishing",
        "desktop"
    ],
    "wof:name":"Blackfeather Productions",
    "wof:placetype":"venue"
},
  "geometry": {"coordinates":[145.04000854500001,-37.8278923035],"type":"Point"}
}