{
  "type": "Feature",
  "properties": {
    "iso:country":"AU",
    "sg:address":"7 Peachtree Rd",
    "sg:city":"Penrith",
    "sg:classifiers":[
        {
            "category":"Wholesale",
            "subcategory":"Auto Parts",
            "type":"Manufacturing & Wholesale Goods"
        }
    ],
    "sg:phone":"+61 2 4732 3499",
    "sg:postcode":"2750",
    "sg:province":"NSW",
    "sg:tags":[
        "recyclers"
    ],
    "wof:name":"Penrith Auto Wreckers Pty Ltd",
    "wof:placetype":"venue"
},
  "geometry": {"coordinates":[150.97297668499999,-33.7875022888],"type":"Point"}
}