{
  "type": "Feature",
  "properties": {
    "iso:country":"AU",
    "sg:address":"PO Box 1278",
    "sg:city":"Bunbury",
    "sg:classifiers":[
        {
            "category":"Wholesale",
            "subcategory":"Construction Materials",
            "type":"Manufacturing & Wholesale Goods"
        }
    ],
    "sg:phone":"+61 417 663 639",
    "sg:postcode":"6231",
    "sg:province":"WA",
    "sg:tags":[
        "lift"
    ],
    "wof:name":"Otis Elevator Company Pty Ltd",
    "wof:placetype":"venue"
},
  "geometry": {"coordinates":[115.636993,-33.32711],"type":"Point"}
}