{
  "type": "Feature",
  "properties": {
    "addr:full":"425 Elizabeth St Surry Hills NSW 2010",
    "addr:housenumber":"425",
    "addr:postcode":"2010",
    "addr:street":"Elizabeth St",
    "iso:country":"AU",
    "sg:address":"425 Elizabeth St",
    "sg:city":"Surry Hills",
    "sg:classifiers":[
        {
            "category":"Professional",
            "subcategory":"Business Services",
            "type":"Services"
        }
    ],
    "sg:phone":"+61 2 9212 6367",
    "sg:postcode":"2010",
    "sg:province":"NSW",
    "sg:tags":[
        "broker"
    ],
    "wof:name":"Delta Pacific Business For Sale",
    "wof:placetype":"venue"
},
  "geometry": {"coordinates":[151.208053589,-33.8855285645],"type":"Point"}
}