{
  "type": "Feature",
  "properties": {
    "iso:country":"AU",
    "sg:address":"1/ 9 Hotham St",
    "sg:city":"Hughesdale",
    "sg:classifiers":[
        {
            "category":"Professional",
            "subcategory":"Secretarial Services",
            "type":"Services"
        }
    ],
    "sg:phone":"+61 419 807 498",
    "sg:postcode":"3166",
    "sg:province":"VIC",
    "sg:tags":[
        "typing"
    ],
    "wof:name":"Janelle Clarke Administrative Services",
    "wof:placetype":"venue"
},
  "geometry": {"coordinates":[145.078613281,-37.900478363],"type":"Point"}
}