{
  "type": "Feature",
  "properties": {
    "addr:full":"9 Katandra Crt Bayswater VIC 3153",
    "addr:housenumber":"9",
    "addr:postcode":"3153",
    "addr:street":"Katandra Crt",
    "iso:country":"AU",
    "sg:address":"9 Katandra Crt",
    "sg:city":"Bayswater",
    "sg:classifiers":[
        {
            "category":"Real Estate",
            "subcategory":"Architect",
            "type":"Services"
        }
    ],
    "sg:phone":"+61 3 9729 5083",
    "sg:postcode":"3153",
    "sg:province":"VIC",
    "sg:tags":[
        "building",
        "designer"
    ],
    "wof:name":"Pockett Ramsay J & Associates Pty Ltd",
    "wof:placetype":"venue"
},
  "geometry": {"coordinates":[145.25338745100001,-37.8545875549],"type":"Point"}
}