{
  "type": "Feature",
  "properties": {
    "iso:country":"AU",
    "sg:address":"712 Geelong Rd",
    "sg:city":"Brooklyn",
    "sg:classifiers":[
        {
            "category":"Transit Center",
            "subcategory":"Freight",
            "type":"Transportation"
        }
    ],
    "sg:phone":"+61 1300 363 025",
    "sg:postcode":"3025",
    "sg:province":"VIC",
    "sg:tags":[
        "forklift",
        "truck"
    ],
    "wof:name":"Prolift Toyota",
    "wof:placetype":"venue"
},
  "geometry": {"coordinates":[144.83758499999999,-37.819733],"type":"Point"}
}