{
  "type": "Feature",
  "properties": {
    "addr:full":"7 Chams St Marsden QLD 4132",
    "addr:housenumber":"7",
    "addr:postcode":"4132",
    "addr:street":"Chams St",
    "iso:country":"AU",
    "sg:address":"7 Chams St",
    "sg:city":"Marsden",
    "sg:classifiers":[
        {
            "category":"Building & Trades",
            "subcategory":"Construction",
            "type":"Services"
        }
    ],
    "sg:phone":"+61 7 3803 4387",
    "sg:postcode":"4132",
    "sg:province":"QLD",
    "sg:tags":[
        "ceiling"
    ],
    "wof:name":"Lets Get Plastered",
    "wof:placetype":"venue"
},
  "geometry": {"coordinates":[153.08311462399999,-27.6704463959],"type":"Point"}
}