{
  "type": "Feature",
  "properties": {
    "addr:full":"41 Crescent Ave Taree NSW 2430",
    "addr:housenumber":"41",
    "addr:postcode":"2430",
    "addr:street":"Crescent Ave",
    "iso:country":"AU",
    "sg:address":"41 Crescent Ave",
    "sg:city":"Taree",
    "sg:classifiers":[
        {
            "category":"Banks & Credit Unions",
            "subcategory":"Financial Services",
            "type":"Services"
        }
    ],
    "sg:phone":"+61 2 6551 0511",
    "sg:postcode":"2430",
    "sg:province":"NSW",
    "sg:tags":[
        "annuity",
        "rollover",
        "superannuation",
        "consultant"
    ],
    "wof:name":"Forum Financial Services",
    "wof:placetype":"venue"
},
  "geometry": {"coordinates":[152.47203099999999,-31.906246],"type":"Point"}
}