{
  "type": "Feature",
  "properties": {
    "addr:full":"Shp 3/ 79 Glenfern Rd Ferntree Gully VIC 3156",
    "addr:housenumber":"/ 79",
    "addr:postcode":"3156",
    "addr:street":"Glenfern Rd",
    "iso:country":"AU",
    "sg:address":"Shp 3/ 79 Glenfern Rd",
    "sg:city":"Ferntree Gully",
    "sg:classifiers":[
        {
            "category":"Personal",
            "subcategory":"Beauty Salon",
            "type":"Services"
        }
    ],
    "sg:phone":"+61 3 9752 3966",
    "sg:postcode":"3156",
    "sg:province":"VIC",
    "sg:tags":[
        "hairdresser"
    ],
    "wof:name":"Kelly's Reflections",
    "wof:placetype":"venue"
},
  "geometry": {"coordinates":[145.29348754899999,-37.8953514099],"type":"Point"}
}