{
  "type": "Feature",
  "properties": {
    "iso:country":"AU",
    "sg:address":"Level 1 Medici Medical Centre 15 Scott St",
    "sg:city":"Toowoomba",
    "sg:classifiers":[
        {
            "category":"Health Services",
            "subcategory":"Health Practitioner",
            "type":"Services"
        }
    ],
    "sg:phone":"+61 7 4638 8015",
    "sg:postcode":"4350",
    "sg:province":"QLD",
    "sg:tags":[
        "audiologists"
    ],
    "wof:name":"Neurosensory Unit",
    "wof:placetype":"venue"
},
  "geometry": {"coordinates":[151.973206,-27.563314],"type":"Point"}
}