{
  "type": "Feature",
  "properties": {
    "addr:full":"Unit 1 24 Glover St Landsdale WA 6065",
    "addr:housenumber":"24",
    "addr:postcode":"6065",
    "addr:street":"Glover St",
    "iso:country":"AU",
    "sg:address":"Unit 1 24 Glover St",
    "sg:city":"Landsdale",
    "sg:classifiers":[
        {
            "category":"Home & Garden",
            "subcategory":"Building Materials",
            "type":"Retail Goods"
        }
    ],
    "sg:phone":"+61 8 9302 1742",
    "sg:postcode":"6065",
    "sg:province":"WA",
    "sg:tags":[
        "insulation"
    ],
    "wof:name":"Total Comfort Industries Pty Ltd",
    "wof:placetype":"venue"
},
  "geometry": {"coordinates":[115.849060059,-31.8023796082],"type":"Point"}
}