{
  "type": "Feature",
  "properties": {
    "addr:full":"3 Poulton Ave Beverley Park NSW 2217",
    "addr:housenumber":"3",
    "addr:postcode":"2217",
    "addr:street":"Poulton Ave Beverley",
    "iso:country":"AU",
    "sg:address":"3 Poulton Ave",
    "sg:city":"Beverley Park",
    "sg:classifiers":[
        {
            "category":"Food & Beverages",
            "subcategory":"Specialty",
            "type":"Retail Goods"
        }
    ],
    "sg:phone":"+61 2 9587 2736",
    "sg:postcode":"2217",
    "sg:province":"NSW",
    "sg:tags":[
        "product",
        "health"
    ],
    "wof:name":"Juice Plus - Sutherland Shire",
    "wof:placetype":"venue"
},
  "geometry": {"coordinates":[151.12689209000001,-33.9766807556],"type":"Point"}
}