{
  "type": "Feature",
  "properties": {
    "iso:country":"AU",
    "sg:address":"80 Princes Hwy",
    "sg:city":"Narooma",
    "sg:classifiers":[
        {
            "category":"Health Services",
            "subcategory":"Doctor",
            "type":"Services"
        }
    ],
    "sg:phone":"+61 2 4476 2999",
    "sg:postcode":"2546",
    "sg:province":"NSW",
    "sg:tags":[
        "medical",
        "practitioner"
    ],
    "wof:name":"Wray Jennifer",
    "wof:placetype":"venue"
},
  "geometry": {"coordinates":[150.128005981,-36.2170028687],"type":"Point"}
}