{
  "type": "Feature",
  "properties": {
    "addr:full":"98 Dennis Rd Springwood QLD 4127",
    "addr:housenumber":"98",
    "addr:postcode":"4127",
    "addr:street":"Dennis Rd",
    "iso:country":"AU",
    "sg:address":"98 Dennis Rd",
    "sg:city":"Springwood",
    "sg:classifiers":[
        {
            "category":"Building & Trades",
            "subcategory":"Locksmith",
            "type":"Services"
        }
    ],
    "sg:phone":"+61 7 3208 2288",
    "sg:postcode":"4127",
    "sg:province":"QLD",
    "sg:tags":[
        "equipment",
        "operating",
        "door",
        "gate"
    ],
    "wof:name":"Automatic Gates & Doors Pty Ltd",
    "wof:placetype":"venue"
},
  "geometry": {"coordinates":[153.13246154800001,-27.6172084808],"type":"Point"}
}