{
  "type": "Feature",
  "properties": {
    "iso:country":"AU",
    "sg:address":"1 Waterloo Rd",
    "sg:city":"Macquarie Park",
    "sg:classifiers":[
        {
            "category":"Real Estate",
            "subcategory":"Surveying",
            "type":"Services"
        }
    ],
    "sg:phone":"+61 2 9857 3700",
    "sg:postcode":"2113",
    "sg:province":"NSW",
    "sg:tags":[
        "map",
        "mapping"
    ],
    "wof:name":"Universal Publishers Pty Ltd",
    "wof:placetype":"venue"
},
  "geometry": {"coordinates":[151.13044738799999,-33.7863388062],"type":"Point"}
}