{
  "type": "Feature",
  "properties": {
    "addr:full":"9 Narrane St Tugun QLD 4224",
    "addr:housenumber":"9",
    "addr:postcode":"4224",
    "addr:street":"Narrane St",
    "iso:country":"AU",
    "sg:address":"9 Narrane St",
    "sg:city":"Tugun",
    "sg:classifiers":[
        {
            "category":"Health Services",
            "subcategory":"Doctor",
            "type":"Services"
        }
    ],
    "sg:phone":"+61 7 5534 4453",
    "sg:postcode":"4224",
    "sg:province":"QLD",
    "sg:tags":[
        "medical",
        "practitioner"
    ],
    "wof:name":"Bellhouse C Paul",
    "wof:placetype":"venue"
},
  "geometry": {"coordinates":[153.49269104000001,-28.1455116272],"type":"Point"}
}