{
  "type": "Feature",
  "properties": {
    "addr:full":"173 Spence St Cairns QLD 4870",
    "addr:housenumber":"173",
    "addr:postcode":"4870",
    "addr:street":"Spence St",
    "iso:country":"AU",
    "sg:address":"173 Spence St",
    "sg:city":"Cairns",
    "sg:classifiers":[
        {
            "category":"Transit Center",
            "subcategory":"Freight",
            "type":"Transportation"
        }
    ],
    "sg:phone":"+61 7 4035 3005",
    "sg:postcode":"4870",
    "sg:province":"QLD",
    "sg:tags":[
        "forklift",
        "truck"
    ],
    "wof:name":"Cairns Cargo Distributors Pty Ltd",
    "wof:placetype":"venue"
},
  "geometry": {"coordinates":[145.76679992699999,-16.9316520691],"type":"Point"}
}