{
  "type": "Feature",
  "properties": {
    "addr:full":"41 Garden Drv Tullamarine VIC 3043",
    "addr:housenumber":"41",
    "addr:postcode":"3043",
    "addr:street":"Garden Drv",
    "iso:country":"AU",
    "sg:address":"41 Garden Drv",
    "sg:city":"Tullamarine",
    "sg:classifiers":[
        {
            "category":"Wholesale",
            "subcategory":"Painting Supplies",
            "type":"Manufacturing & Wholesale Goods"
        }
    ],
    "sg:phone":"+61 3 9335 3933",
    "sg:postcode":"3043",
    "sg:province":"VIC",
    "sg:tags":[
        "product",
        "cleaning"
    ],
    "sg:website":"http://www.plasnet.com.au/revcocleaning",
    "wof:name":"Revco Australia Pty Ltd",
    "wof:placetype":"venue"
},
  "geometry": {"coordinates":[144.87794494600001,-37.6909675598],"type":"Point"}
}