{
  "type": "Feature",
  "properties": {
    "addr:full":"205 Boulder Rd Kalgoorlie WA 6430",
    "addr:housenumber":"205",
    "addr:postcode":"6430",
    "addr:street":"Boulder Rd",
    "iso:country":"AU",
    "sg:address":"205 Boulder Rd",
    "sg:city":"Kalgoorlie",
    "sg:classifiers":[
        {
            "category":"Retail",
            "subcategory":"Auto Repair",
            "type":"Services"
        }
    ],
    "sg:phone":"+61 8 9022 7709",
    "sg:postcode":"6430",
    "sg:province":"WA",
    "sg:tags":[
        "repairer",
        "motor",
        "engineer"
    ],
    "wof:name":"UltraTune",
    "wof:placetype":"venue"
},
  "geometry": {"coordinates":[121.476287842,-30.7481174469],"type":"Point"}
}