{
  "type": "Feature",
  "properties": {
    "addr:full":"Shop 5, 53- 57 King St Warrawong NSW 2502",
    "addr:housenumber":"shop;53 57",
    "addr:postcode":"2502",
    "addr:street":"King St",
    "iso:country":"AU",
    "sg:address":"Shop 5, 53- 57 King St",
    "sg:city":"Warrawong",
    "sg:classifiers":[
        {
            "category":"Military Area",
            "subcategory":"Air Force Base",
            "type":"Public Place"
        }
    ],
    "sg:phone":"+61 2 4274 7102",
    "sg:postcode":"2502",
    "sg:province":"NSW",
    "sg:tags":[
        "men's",
        "tailor"
    ],
    "wof:name":"Alex Alterations",
    "wof:placetype":"venue"
},
  "geometry": {"coordinates":[150.887756,-34.485043],"type":"Point"}
}