{
  "type": "Feature",
  "properties": {
    "addr:full":"PO Box 25 Cockatoo Valley SA 5351",
    "addr:postcode":"5351",
    "iso:country":"AU",
    "sg:address":"PO Box 25",
    "sg:city":"Cockatoo Valley",
    "sg:classifiers":[
        {
            "category":"Building & Trades",
            "subcategory":"Landscaping Services",
            "type":"Services"
        }
    ],
    "sg:phone":"+61 8 8523 4222",
    "sg:postcode":"5351",
    "sg:province":"SA",
    "sg:tags":[
        "stump",
        "tree",
        "felling",
        "removal"
    ],
    "wof:name":"Arbortech Tree Services",
    "wof:placetype":"venue"
},
  "geometry": {"coordinates":[138.83270263700001,-34.6112518311],"type":"Point"}
}