{
  "type": "Feature",
  "properties": {
    "addr:full":"38 Munibung Rd Cardiff NSW 2285",
    "addr:housenumber":"38",
    "addr:postcode":"2285",
    "addr:street":"Munibung Rd",
    "iso:country":"AU",
    "sg:address":"38 Munibung Rd",
    "sg:city":"Cardiff",
    "sg:classifiers":[
        {
            "category":"Building & Trades",
            "subcategory":"Plumbing",
            "type":"Services"
        }
    ],
    "sg:phone":"+61 2 4953 6444",
    "sg:postcode":"2285",
    "sg:province":"NSW",
    "sg:tags":[
        "fitting",
        "hose",
        "supply"
    ],
    "wof:name":"Total Rubber Newcastle",
    "wof:placetype":"venue"
},
  "geometry": {"coordinates":[151.646575928,-32.9427490234],"type":"Point"}
}