{
  "type": "Feature",
  "properties": {
    "addr:full":"10 Gifford St South Plympton SA 5038",
    "addr:housenumber":"10",
    "addr:postcode":"5038",
    "addr:street":"Gifford St",
    "iso:country":"AU",
    "sg:address":"10 Gifford St",
    "sg:city":"South Plympton",
    "sg:classifiers":[
        {
            "category":"Education",
            "subcategory":"Music School",
            "type":"Public Place"
        }
    ],
    "sg:phone":"+61 401 080 659",
    "sg:postcode":"5038",
    "sg:province":"SA",
    "sg:tags":[
        "teacher"
    ],
    "wof:name":"Don't Fret Guitar Tuition C.P.M",
    "wof:placetype":"venue"
},
  "geometry": {"coordinates":[138.55911254899999,-34.9780158997],"type":"Point"}
}