{
  "type": "Feature",
  "properties": {
    "iso:country":"AU",
    "sg:address":"40 Storrington Crs",
    "sg:city":"Balga",
    "sg:classifiers":[
        {
            "category":"Building & Trades",
            "subcategory":"Cleaning & Sanitation",
            "type":"Services"
        }
    ],
    "sg:phone":"+61 439 989 565",
    "sg:postcode":"6061",
    "sg:province":"WA",
    "sg:tags":[
        "industrial",
        "commercial",
        "contractor"
    ],
    "wof:name":"Fine Line Commercial Cleaning Service",
    "wof:placetype":"venue"
},
  "geometry": {"coordinates":[115.83769989,-31.8557090759],"type":"Point"}
}