{
  "type": "Feature",
  "properties": {
    "addr:full":"Cnr North Fort Road & Head Scenic Drive Manly NSW 2095",
    "addr:postcode":"2095",
    "addr:street":"Cnr North Fort Road &;Scenic Drive",
    "iso:country":"AU",
    "sg:address":"Cnr North Fort Road & Head Scenic Drive",
    "sg:city":"Manly",
    "sg:classifiers":[
        {
            "category":"Cafe",
            "type":"Food & Drink"
        }
    ],
    "sg:phone":"+61 2 9976 0169",
    "sg:postcode":"2095",
    "sg:province":"NSW",
    "wof:name":"North Fort Caf\ufffd",
    "wof:placetype":"venue"
},
  "geometry": {"coordinates":[151.29580688499999,-33.8063354492],"type":"Point"}
}