{
  "type": "Feature",
  "properties": {
    "addr:full":"444 Sheridan St Cairns North QLD 4870",
    "addr:housenumber":"444",
    "addr:postcode":"4870",
    "addr:street":"Sheridan St",
    "iso:country":"AU",
    "sg:address":"444 Sheridan St",
    "sg:city":"Cairns North",
    "sg:classifiers":[
        {
            "category":"Autos & Motor Vehicles",
            "subcategory":"Auto Supplies",
            "type":"Retail Goods"
        }
    ],
    "sg:phone":"+61 7 4032 0700",
    "sg:postcode":"4870",
    "sg:province":"QLD",
    "sg:tags":[
        "part",
        "cycles",
        "accessory"
    ],
    "wof:name":"Kawasaki FNQ",
    "wof:placetype":"venue"
},
  "geometry": {"coordinates":[145.754074097,-16.8945331573],"type":"Point"}
}