{
  "type": "Feature",
  "properties": {
    "iso:country":"AU",
    "sg:address":"12-14 Wollumbin St",
    "sg:city":"Murwillumbah",
    "sg:classifiers":[
        {
            "category":"Autos & Motor Vehicles",
            "subcategory":"Auto Supplies",
            "type":"Retail Goods"
        }
    ],
    "sg:phone":"+61 2 6672 8444",
    "sg:postcode":"2484",
    "sg:province":"NSW",
    "sg:tags":[
        "part",
        "cycles",
        "accessory"
    ],
    "wof:name":"Wollumbin Motor Cycle Accessories",
    "wof:placetype":"venue"
},
  "geometry": {"coordinates":[153.39544677699999,-28.3273658752],"type":"Point"}
}