{
  "type": "Feature",
  "properties": {
    "addr:full":"Community Centre Forest St Woodend VIC 3442",
    "addr:postcode":"3442",
    "addr:street":"Forest St",
    "iso:country":"AU",
    "sg:address":"Community Centre Forest St",
    "sg:city":"Woodend",
    "sg:classifiers":[
        {
            "category":"Social Services",
            "subcategory":"Child Care",
            "type":"Services"
        }
    ],
    "sg:phone":"+61 3 5427 8255",
    "sg:postcode":"3442",
    "sg:province":"VIC",
    "sg:tags":[
        "support",
        "health"
    ],
    "wof:name":"Maternal & Child Health Centres",
    "wof:placetype":"venue"
},
  "geometry": {"coordinates":[144.52993774399999,-37.3549995422],"type":"Point"}
}