{
  "type": "Feature",
  "properties": {
    "addr:full":"27 Hickory Drv Thornlie WA 6108",
    "addr:housenumber":"27",
    "addr:postcode":"6108",
    "addr:street":"Hickory Drv",
    "iso:country":"AU",
    "sg:address":"27 Hickory Drv",
    "sg:city":"Thornlie",
    "sg:classifiers":[
        {
            "category":"Professional",
            "subcategory":"Accounting & Tax Preparation",
            "type":"Services"
        }
    ],
    "sg:phone":"+61 8 9452 0817",
    "sg:postcode":"6108",
    "sg:province":"WA",
    "sg:tags":[
        "bookkeeping"
    ],
    "wof:name":"Applied Business Assistants",
    "wof:placetype":"venue"
},
  "geometry": {"coordinates":[115.947898865,-32.0760688782],"type":"Point"}
}