{
  "type": "Feature",
  "properties": {
    "iso:country":"AU",
    "sg:address":"208 Mary St",
    "sg:city":"Gympie",
    "sg:classifiers":[
        {
            "category":"Health Services",
            "subcategory":"Dentist",
            "type":"Services"
        }
    ],
    "sg:phone":"+61 7 5482 2688",
    "sg:postcode":"4570",
    "sg:province":"QLD",
    "wof:name":"Dixon Paul J",
    "wof:placetype":"venue"
},
  "geometry": {"coordinates":[152.65957641599999,-26.1891651154],"type":"Point"}
}