{
  "type": "Feature",
  "properties": {
    "iso:country":"AU",
    "sg:address":"3 Grafton St",
    "sg:city":"Blacktown",
    "sg:classifiers":[
        {
            "category":"Health Services",
            "subcategory":"Doctor",
            "type":"Services"
        }
    ],
    "sg:phone":"+61 2 9621 7644",
    "sg:postcode":"2148",
    "sg:province":"NSW",
    "sg:tags":[
        "medical",
        "practitioner"
    ],
    "wof:name":"Zelas Peter",
    "wof:placetype":"venue"
},
  "geometry": {"coordinates":[150.913696289,-33.7735595703],"type":"Point"}
}