{
  "type": "Feature",
  "properties": {
    "iso:country":"AU",
    "sg:address":"Cnr United & Currumburra Rds",
    "sg:city":"Ashmore",
    "sg:classifiers":[
        {
            "category":"Home & Garden",
            "subcategory":"Hardware",
            "type":"Retail Goods"
        }
    ],
    "sg:phone":"+61 7 5539 1522",
    "sg:postcode":"4214",
    "sg:province":"QLD",
    "sg:tags":[
        "supply",
        "maker",
        "cabinet"
    ],
    "wof:name":"Cut To Size Ashmore (Aust) Pty Ltd",
    "wof:placetype":"venue"
},
  "geometry": {"coordinates":[153.382415772,-27.9846992493],"type":"Point"}
}