{
  "type": "Feature",
  "properties": {
    "addr:full":"Cnr Bruce Hwy & & Lauriston St Bowen QLD 4805",
    "addr:postcode":"4805",
    "addr:street":"Cnr Bruce Hwy;St",
    "iso:country":"AU",
    "sg:address":"Cnr Bruce Hwy & & Lauriston St",
    "sg:city":"Bowen",
    "sg:classifiers":[
        {
            "category":"Farming",
            "subcategory":"Farm & Veterinary Services",
            "type":"Manufacturing & Wholesale Goods"
        }
    ],
    "sg:phone":"+61 7 4785 2322",
    "sg:postcode":"4805",
    "sg:province":"QLD",
    "sg:tags":[
        "irrigation",
        "reticulation",
        "system"
    ],
    "wof:name":"Bartec Rural Services Pty Ltd",
    "wof:placetype":"venue"
},
  "geometry": {"coordinates":[148.220870972,-20.0146656036],"type":"Point"}
}