{
  "type": "Feature",
  "properties": {
    "addr:full":"22 Butler St Tully QLD 4854",
    "addr:housenumber":"22",
    "addr:postcode":"4854",
    "addr:street":"Butler St",
    "iso:country":"AU",
    "sg:address":"22 Butler St",
    "sg:city":"Tully",
    "sg:classifiers":[
        {
            "category":"Building & Trades",
            "subcategory":"Landscaping Services",
            "type":"Services"
        }
    ],
    "sg:phone":"+61 7 4068 2255",
    "sg:postcode":"4854",
    "sg:province":"QLD",
    "sg:tags":[
        "horticultural",
        "consultant"
    ],
    "wof:name":"Growcom",
    "wof:placetype":"venue"
},
  "geometry": {"coordinates":[145.92442321799999,-17.9339046478],"type":"Point"}
}