{
  "type": "Feature",
  "properties": {
    "addr:full":"31 Giles St Kingston ACT 2604",
    "addr:housenumber":"31",
    "addr:postcode":"2604",
    "addr:street":"Giles St",
    "iso:country":"AU",
    "sg:address":"31 Giles St",
    "sg:city":"Kingston",
    "sg:classifiers":[
        {
            "category":"Travel",
            "subcategory":"Hotels & Motels",
            "type":"Entertainment"
        }
    ],
    "sg:phone":"+61 2 6295 2333",
    "sg:postcode":"2604",
    "sg:province":"ACT",
    "wof:name":"The York Canberra",
    "wof:placetype":"venue"
},
  "geometry": {"coordinates":[149.140380859,-35.3152160645],"type":"Point"}
}