{
  "type": "Feature",
  "properties": {
    "addr:full":"48 Palmerin St Warwick QLD 4370",
    "addr:housenumber":"48",
    "addr:postcode":"4370",
    "addr:street":"Palmerin St",
    "iso:country":"AU",
    "sg:address":"48 Palmerin St",
    "sg:city":"Warwick",
    "sg:classifiers":[
        {
            "category":"Organizations",
            "subcategory":"Community Association",
            "type":"Services"
        }
    ],
    "sg:phone":"+61 7 4661 1918",
    "sg:postcode":"4370",
    "sg:province":"QLD",
    "sg:tags":[
        "organisation",
        "family",
        "welfare"
    ],
    "wof:name":"St Vincent De Paul Society",
    "wof:placetype":"venue"
},
  "geometry": {"coordinates":[152.033203125,-28.2137641907],"type":"Point"}
}