{
  "type": "Feature",
  "properties": {
    "iso:country":"AU",
    "sg:address":"16 Handford Rd",
    "sg:city":"Zillmere",
    "sg:classifiers":[
        {
            "category":"Banks & Credit Unions",
            "subcategory":"Bank",
            "type":"Services"
        }
    ],
    "sg:phone":"+61 1300 554 872",
    "sg:postcode":"4034",
    "sg:province":"QLD",
    "sg:tags":[
        "broker",
        "mortgage"
    ],
    "wof:name":"Lloyds Finance",
    "wof:placetype":"venue"
},
  "geometry": {"coordinates":[153.03804,-27.359358],"type":"Point"}
}