{
  "type": "Feature",
  "properties": {
    "iso:country":"AU",
    "sg:address":"Anzac Ave",
    "sg:city":"Marian",
    "sg:classifiers":[
        {
            "category":"Autos & Motor Vehicles",
            "subcategory":"Fuel & Gas Station",
            "type":"Retail Goods"
        }
    ],
    "sg:phone":"+61 7 4954 3207",
    "sg:postcode":"4753",
    "sg:province":"QLD",
    "wof:name":"Daly Pty Ltd",
    "wof:placetype":"venue"
},
  "geometry": {"coordinates":[148.945923,-21.144951],"type":"Point"}
}