{
  "type": "Feature",
  "properties": {
    "addr:full":"Suite 102, Lvl 1/ 3 Smail St Ultimo NSW 2007",
    "addr:housenumber":"/ 3",
    "addr:postcode":"2007",
    "addr:street":"Smail St",
    "iso:country":"AU",
    "sg:address":"Suite 102, Lvl 1/ 3 Smail St",
    "sg:city":"Ultimo",
    "sg:classifiers":[
        {
            "category":"Shopping",
            "subcategory":"Computers & Home Electronics",
            "type":"Retail Goods"
        }
    ],
    "sg:phone":"+61 1800 833 883",
    "sg:postcode":"2007",
    "sg:province":"NSW",
    "sg:tags":[
        "hardware",
        "equipment"
    ],
    "wof:name":"I-Tech Group Pty Ltd",
    "wof:placetype":"venue"
},
  "geometry": {"coordinates":[151.19566345199999,-33.8829650879],"type":"Point"}
}