{
  "type": "Feature",
  "properties": {
    "addr:full":"760 Cygnet Coast Rd Petcheys Bay TAS 7112",
    "addr:housenumber":"760",
    "addr:postcode":"7112",
    "addr:street":"Cygnet Coast Rd Petcheys",
    "iso:country":"AU",
    "sg:address":"760 Cygnet Coast Rd",
    "sg:city":"Petcheys Bay",
    "sg:classifiers":[
        {
            "category":"Professional",
            "subcategory":"Printing & Photocopies",
            "type":"Services"
        }
    ],
    "sg:phone":"+61 3 6295 0257",
    "sg:postcode":"7112",
    "sg:province":"TAS",
    "sg:tags":[
        "textile",
        "clothing"
    ],
    "wof:name":"VanDiemonium",
    "wof:placetype":"venue"
},
  "geometry": {"coordinates":[147.07502746599999,-43.1975212097],"type":"Point"}
}