{
  "type": "Feature",
  "properties": {
    "addr:full":"97 Tamar St Ballina NSW 2478",
    "addr:housenumber":"97",
    "addr:postcode":"2478",
    "addr:street":"Tamar St",
    "iso:country":"AU",
    "sg:address":"97 Tamar St",
    "sg:city":"Ballina",
    "sg:classifiers":[
        {
            "category":"Health Services",
            "subcategory":"Doctor",
            "type":"Services"
        }
    ],
    "sg:phone":"+61 2 6681 5411",
    "sg:postcode":"2478",
    "sg:province":"NSW",
    "sg:tags":[
        "medical",
        "practitioner"
    ],
    "wof:name":"Carrol Brian Dr",
    "wof:placetype":"venue"
},
  "geometry": {"coordinates":[153.55857849099999,-28.8681259155],"type":"Point"}
}