{
  "type": "Feature",
  "properties": {
    "addr:full":"Calder Park Raceway Pk Keilor VIC 3036",
    "addr:postcode":"3036",
    "iso:country":"AU",
    "sg:address":"Calder Park Raceway Pk",
    "sg:city":"Keilor",
    "sg:classifiers":[
        {
            "category":"Retail",
            "subcategory":"Driving School",
            "type":"Services"
        }
    ],
    "sg:phone":"+61 3 9217 8825",
    "sg:postcode":"3036",
    "sg:province":"VIC",
    "sg:website":"http://www.riderbros.com.au",
    "wof:name":"Rider Brothers Motorcycle Training",
    "wof:placetype":"venue"
},
  "geometry": {"coordinates":[144.83750900000001,-37.717476],"type":"Point"}
}