{
  "type": "Feature",
  "properties": {
    "addr:full":"14 Horne St Sunbury VIC 3429",
    "addr:housenumber":"14",
    "addr:postcode":"3429",
    "addr:street":"Horne St",
    "iso:country":"AU",
    "sg:address":"14 Horne St",
    "sg:city":"Sunbury",
    "sg:classifiers":[
        {
            "category":"Insurance",
            "subcategory":"Hazard Insurance",
            "type":"Services"
        }
    ],
    "sg:phone":"+61 3 9740 7199",
    "sg:postcode":"3429",
    "sg:province":"VIC",
    "sg:tags":[
        "fire",
        "accident",
        "marine"
    ],
    "wof:name":"Pr Insurance Specialists",
    "wof:placetype":"venue"
},
  "geometry": {"coordinates":[144.72760009800001,-37.5769844055],"type":"Point"}
}