{
  "type": "Feature",
  "properties": {
    "addr:full":"Unit 6, 92a Mona Vale Rd Mona Vale NSW 2103",
    "addr:housenumber":"92a",
    "addr:postcode":"2103",
    "addr:street":"Mona Vale Rd",
    "iso:country":"AU",
    "sg:address":"Unit 6, 92a Mona Vale Rd",
    "sg:city":"Mona Vale",
    "sg:classifiers":[
        {
            "category":"Autos & Motor Vehicles",
            "subcategory":"Auto Supplies",
            "type":"Retail Goods"
        }
    ],
    "sg:phone":"+61 2 9979 8555",
    "sg:postcode":"2103",
    "sg:province":"NSW",
    "sg:tags":[
        "battery",
        "automotive"
    ],
    "wof:name":"Rycom Instruments",
    "wof:placetype":"venue"
},
  "geometry": {"coordinates":[151.28919982900001,-33.676109314],"type":"Point"}
}