{
  "type": "Feature",
  "properties": {
    "iso:country":"AU",
    "sg:address":"18 Church St",
    "sg:city":"Penola",
    "sg:classifiers":[
        {
            "category":"Health Services",
            "subcategory":"Health Practitioner",
            "type":"Services"
        }
    ],
    "sg:phone":"+61 8 8737 2218",
    "sg:postcode":"5277",
    "sg:province":"SA",
    "sg:tags":[
        "physiotherapist"
    ],
    "wof:name":"McArthur Physiotherapy",
    "wof:placetype":"venue"
},
  "geometry": {"coordinates":[140.83749399999999,-37.382141],"type":"Point"}
}