{
  "type": "Feature",
  "properties": {
    "addr:full":"245 Keenan St Wungong WA 6112",
    "addr:housenumber":"245",
    "addr:postcode":"6112",
    "addr:street":"Keenan St",
    "iso:country":"AU",
    "sg:address":"245 Keenan St",
    "sg:city":"Wungong",
    "sg:classifiers":[
        {
            "category":"Farming",
            "subcategory":"Livestock Farm",
            "type":"Manufacturing & Wholesale Goods"
        }
    ],
    "sg:phone":"+61 8 9399 3564",
    "sg:postcode":"6112",
    "sg:province":"WA",
    "sg:tags":[
        "agistment"
    ],
    "wof:name":"Twinbrooks",
    "wof:placetype":"venue"
},
  "geometry": {"coordinates":[116.00389099100001,-32.1865310669],"type":"Point"}
}