{
  "type": "Feature",
  "properties": {
    "iso:country":"AU",
    "sg:address":"48 Royal Ave",
    "sg:city":"Pooraka",
    "sg:classifiers":[
        {
            "category":"Health Services",
            "subcategory":"Health Practitioner",
            "type":"Services"
        }
    ],
    "sg:phone":"+61 8 8262 4865",
    "sg:postcode":"5095",
    "sg:province":"SA",
    "sg:tags":[
        "alternative"
    ],
    "wof:name":"South Australian Spiritual Healers Association Incorporated",
    "wof:placetype":"venue"
},
  "geometry": {"coordinates":[138.61825561500001,-34.8328018188],"type":"Point"}
}