{
  "type": "Feature",
  "properties": {
    "iso:country":"AU",
    "sg:address":"5 Bent St",
    "sg:city":"The Entrance",
    "sg:classifiers":[
        {
            "category":"Travel",
            "subcategory":"Hotels & Motels",
            "type":"Entertainment"
        }
    ],
    "sg:phone":"+61 2 4333 5669",
    "sg:postcode":"2261",
    "sg:province":"NSW",
    "wof:name":"Annabell's Bed & Breakfast The Entrance",
    "wof:placetype":"venue"
},
  "geometry": {"coordinates":[151.49685700000001,-33.339512],"type":"Point"}
}