{
  "type": "Feature",
  "properties": {
    "addr:full":"203 Englefield Rd Oxley QLD 4075",
    "addr:housenumber":"203",
    "addr:postcode":"4075",
    "addr:street":"Englefield Rd",
    "iso:country":"AU",
    "sg:address":"203 Englefield Rd",
    "sg:city":"Oxley",
    "sg:classifiers":[
        {
            "category":"Professional",
            "subcategory":"Computer Services",
            "type":"Services"
        }
    ],
    "sg:phone":"+61 7 3375 5396",
    "sg:postcode":"4075",
    "sg:province":"QLD",
    "sg:tags":[
        "repairs",
        "upgrade",
        "equipment"
    ],
    "wof:name":"Truform Data",
    "wof:placetype":"venue"
},
  "geometry": {"coordinates":[152.96661376899999,-27.5592327118],"type":"Point"}
}