{
  "type": "Feature",
  "properties": {
    "addr:full":"5 Coldstream St Ulmarra NSW 2462",
    "addr:housenumber":"5",
    "addr:postcode":"2462",
    "addr:street":"Coldstream St",
    "iso:country":"AU",
    "sg:address":"5 Coldstream St",
    "sg:city":"Ulmarra",
    "sg:classifiers":[
        {
            "category":"Manufacturing",
            "subcategory":"Pottery",
            "type":"Manufacturing & Wholesale Goods"
        }
    ],
    "sg:phone":"+61 2 6644 5757",
    "sg:postcode":"2462",
    "sg:province":"NSW",
    "wof:name":"Coldstream Gallery",
    "wof:placetype":"venue"
},
  "geometry": {"coordinates":[153.02796935999999,-29.6312160492],"type":"Point"}
}