{
  "type": "Feature",
  "properties": {
    "addr:full":"41 Cameron St Wauchope NSW 2446",
    "addr:housenumber":"41",
    "addr:postcode":"2446",
    "addr:street":"Cameron St",
    "iso:country":"AU",
    "sg:address":"41 Cameron St",
    "sg:city":"Wauchope",
    "sg:classifiers":[
        {
            "category":"Shopping",
            "subcategory":"Mobile Phones",
            "type":"Retail Goods"
        }
    ],
    "sg:phone":"+61 2 6586 4671",
    "sg:postcode":"2446",
    "sg:province":"NSW",
    "sg:tags":[
        "battery",
        "equipment",
        "charging"
    ],
    "wof:name":"Hastings Technologies",
    "wof:placetype":"venue"
},
  "geometry": {"coordinates":[152.73413099999999,-31.457111],"type":"Point"}
}