{
  "type": "Feature",
  "properties": {
    "addr:full":"Unit 14/ 500 Seventeen Mile Rocks Rd Seventeen Mile Rocks QLD 4073",
    "addr:housenumber":"/ 500",
    "addr:postcode":"4073",
    "addr:street":"Seventeen Mile Rocks Rd",
    "iso:country":"AU",
    "sg:address":"Unit 14/ 500 Seventeen Mile Rocks Rd",
    "sg:city":"Seventeen Mile Rocks",
    "sg:classifiers":[
        {
            "category":"Communications",
            "subcategory":"Film & Video Production",
            "type":"Services"
        }
    ],
    "sg:phone":"+61 7 3279 0898",
    "sg:postcode":"4073",
    "sg:province":"QLD",
    "sg:tags":[
        "mirror"
    ],
    "wof:name":"Mirrorworks (Australia)",
    "wof:placetype":"venue"
},
  "geometry": {"coordinates":[152.95591735799999,-27.5418167114],"type":"Point"}
}