{
  "type": "Feature",
  "properties": {
    "addr:full":"Shop 4/ 6 Hill St Camden NSW 2570",
    "addr:housenumber":"shop 4 / 6",
    "addr:postcode":"2570",
    "addr:street":"Hill St",
    "iso:country":"AU",
    "sg:address":"Shop 4/ 6 Hill St",
    "sg:city":"Camden",
    "sg:classifiers":[
        {
            "category":"Restaurant",
            "type":"Food & Drink"
        }
    ],
    "sg:phone":"+61 2 4655 2771",
    "sg:postcode":"2570",
    "sg:province":"NSW",
    "wof:name":"Camden Jumbo Chinese Restaurant",
    "wof:placetype":"venue"
},
  "geometry": {"coordinates":[150.697265625,-34.0541725159],"type":"Point"}
}