{
  "type": "Feature",
  "properties": {
    "addr:full":"1st Flr 259 Lygon St Carlton VIC 3053",
    "addr:housenumber":"259",
    "addr:postcode":"3053",
    "addr:street":"Lygon St",
    "iso:country":"AU",
    "sg:address":"1st Flr 259 Lygon St",
    "sg:city":"Carlton",
    "sg:classifiers":[
        {
            "category":"Banks & Credit Unions",
            "subcategory":"Investment Brokerage",
            "type":"Services"
        }
    ],
    "sg:phone":"+61 1800 653 061",
    "sg:postcode":"3053",
    "sg:province":"VIC",
    "wof:name":"Commonwealth Financial Planning",
    "wof:placetype":"venue"
},
  "geometry": {"coordinates":[144.96697998100001,-37.7994346619],"type":"Point"}
}