{
  "type": "Feature",
  "properties": {
    "addr:full":"14 Vine St Stones Corner QLD 4120",
    "addr:housenumber":"14",
    "addr:postcode":"4120",
    "addr:street":"Vine St",
    "iso:country":"AU",
    "sg:address":"14 Vine St",
    "sg:city":"Stones Corner",
    "sg:classifiers":[
        {
            "category":"Professional",
            "subcategory":"Art Services",
            "type":"Services"
        }
    ],
    "sg:phone":"+61 7 3394 8555",
    "sg:postcode":"4120",
    "sg:province":"QLD",
    "sg:tags":[
        "graphic",
        "designer"
    ],
    "wof:name":"Kingsbury Design",
    "wof:placetype":"venue"
},
  "geometry": {"coordinates":[153.04765319800001,-27.5023288727],"type":"Point"}
}