{
  "type": "Feature",
  "properties": {
    "iso:country":"AU",
    "sg:address":"47 Nicholls St",
    "sg:city":"Broken Hill",
    "sg:classifiers":[
        {
            "category":"Personal",
            "subcategory":"Beauty Salon",
            "type":"Services"
        }
    ],
    "sg:phone":"+61 8 8088 2671",
    "sg:postcode":"2880",
    "sg:province":"NSW",
    "sg:tags":[
        "hairdresser"
    ],
    "wof:name":"Karen's Hair Spa Salon",
    "wof:placetype":"venue"
},
  "geometry": {"coordinates":[141.445114136,-31.9716186523],"type":"Point"}
}