{
  "type": "Feature",
  "properties": {
    "addr:full":"1st Floor London Crt, Hay St (Mall End) Perth WA 6000",
    "addr:postcode":"6000",
    "addr:street":"Hay St Mall End",
    "iso:country":"AU",
    "sg:address":"1st Floor London Crt, Hay St",
    "sg:city":"(Mall End) Perth",
    "sg:classifiers":[
        {
            "category":"Personal",
            "type":"Services"
        }
    ],
    "sg:phone":"+61 8 9221 1992",
    "sg:postcode":"6000",
    "sg:province":"WA",
    "sg:tags":[
        "dressmaker"
    ],
    "wof:name":"Up Front Clothing",
    "wof:placetype":"venue"
},
  "geometry": {"coordinates":[115.853813171,-31.9525032043],"type":"Point"}
}