{
  "type": "Feature",
  "properties": {
    "iso:country":"AU",
    "sg:address":"PO Box 6167",
    "sg:city":"Croydon North",
    "sg:classifiers":[
        {
            "category":"Professional",
            "subcategory":"Accounting & Tax Preparation",
            "type":"Services"
        }
    ],
    "sg:phone":"+61 409 906 026",
    "sg:postcode":"3136",
    "sg:province":"VIC",
    "sg:tags":[
        "bookkeeping"
    ],
    "wof:name":"Admin Troubleshooters",
    "wof:placetype":"venue"
},
  "geometry": {"coordinates":[145.279754639,-37.7989196777],"type":"Point"}
}