{
  "type": "Feature",
  "properties": {
    "iso:country":"AU",
    "sg:address":"90 Days Rd",
    "sg:city":"Croydon Park",
    "sg:classifiers":[
        {
            "category":"Retail",
            "subcategory":"Auto Repair",
            "type":"Services"
        }
    ],
    "sg:phone":"+61 8 8346 2876",
    "sg:postcode":"5008",
    "sg:province":"SA",
    "sg:tags":[
        "repairer",
        "motor",
        "engineer"
    ],
    "wof:name":"B & P Mechanical Repairs",
    "wof:placetype":"venue"
},
  "geometry": {"coordinates":[138.56634500000001,-34.878376],"type":"Point"}
}