{
  "type": "Feature",
  "properties": {
    "iso:country":"AU",
    "sg:address":"84 Briggs St",
    "sg:city":"Carlisle",
    "sg:classifiers":[
        {
            "category":"Building & Trades",
            "subcategory":"Construction",
            "type":"Services"
        }
    ],
    "sg:phone":"+61 8 9355 4000",
    "sg:postcode":"6101",
    "sg:province":"WA",
    "sg:tags":[
        "home",
        "air conditioning"
    ],
    "wof:name":"Living Comfort Air Conditioning",
    "wof:placetype":"venue"
},
  "geometry": {"coordinates":[115.926368713,-31.9844379425],"type":"Point"}
}