{
  "type": "Feature",
  "properties": {
    "addr:full":"55 Seventh St Weston NSW 2326",
    "addr:housenumber":"55",
    "addr:postcode":"2326",
    "addr:street":"Seventh St",
    "iso:country":"AU",
    "sg:address":"55 Seventh St",
    "sg:city":"Weston",
    "sg:classifiers":[
        {
            "category":"Retail",
            "subcategory":"Repair Shop",
            "type":"Services"
        }
    ],
    "sg:phone":"+61 2 4937 3167",
    "sg:postcode":"2326",
    "sg:province":"NSW",
    "sg:tags":[
        "upholsterer"
    ],
    "wof:name":"Kays Upholstery",
    "wof:placetype":"venue"
},
  "geometry": {"coordinates":[151.456756592,-32.8067893982],"type":"Point"}
}