{
  "type": "Feature",
  "properties": {
    "iso:country":"AU",
    "sg:address":"Shop 3, 40 Playne St",
    "sg:city":"Frankston",
    "sg:classifiers":[
        {
            "category":"Fast Food",
            "type":"Food & Drink"
        }
    ],
    "sg:phone":"+61 3 9781 5644",
    "sg:postcode":"3199",
    "sg:province":"VIC",
    "sg:tags":[
        "away",
        "take"
    ],
    "wof:name":"Frankston Charcoal Chicken",
    "wof:placetype":"venue"
},
  "geometry": {"coordinates":[145.122512817,-38.1451225281],"type":"Point"}
}