{
  "type": "Feature",
  "properties": {
    "iso:country":"AU",
    "sg:address":"129 View St",
    "sg:city":"Bendigo",
    "sg:classifiers":[
        {
            "category":"Recreation",
            "subcategory":"Fishing",
            "type":"Entertainment"
        }
    ],
    "sg:phone":"+61 3 5443 8625",
    "sg:postcode":"3550",
    "sg:province":"VIC",
    "sg:tags":[
        "tackle"
    ],
    "wof:name":"Nelson Kingsley Fishing Tackle Pty Ltd",
    "wof:placetype":"venue"
},
  "geometry": {"coordinates":[144.27572631800001,-36.7573661804],"type":"Point"}
}