{
  "type": "Feature",
  "properties": {
    "addr:full":"87 Tukara Rd Penrith NSW 2750",
    "addr:housenumber":"87",
    "addr:postcode":"2750",
    "addr:street":"Tukara Rd",
    "iso:country":"AU",
    "sg:address":"87 Tukara Rd",
    "sg:city":"Penrith",
    "sg:classifiers":[
        {
            "category":"Communications",
            "type":"Services"
        }
    ],
    "sg:phone":"+61 2 4736 1529",
    "sg:postcode":"2750",
    "sg:province":"NSW",
    "sg:tags":[
        "antenna"
    ],
    "wof:name":"Aerial Installations",
    "wof:placetype":"venue"
},
  "geometry": {"coordinates":[150.69752502399999,-33.780216217],"type":"Point"}
}