{
  "type": "Feature",
  "properties": {
    "addr:full":"1 Meredith St Mt Waverley VIC 3149",
    "addr:housenumber":"1",
    "addr:postcode":"3149",
    "addr:street":"Meredith St Mt",
    "iso:country":"AU",
    "sg:address":"1 Meredith St",
    "sg:city":"Mt Waverley",
    "sg:classifiers":[
        {
            "category":"Banks & Credit Unions",
            "subcategory":"Financial Services",
            "type":"Services"
        }
    ],
    "sg:phone":"+61 3 9807 9388",
    "sg:postcode":"3149",
    "sg:province":"VIC",
    "sg:tags":[
        "planning"
    ],
    "wof:name":"Valveet Consulting",
    "wof:placetype":"venue"
},
  "geometry": {"coordinates":[145.11854553200001,-37.8826637268],"type":"Point"}
}