{
  "type": "Feature",
  "properties": {
    "addr:full":"Shop 14 Lake Haven Shopping Cntr Lake Haven Drv Lake Haven NSW 2263",
    "addr:housenumber":"shop 14",
    "addr:postcode":"2263",
    "addr:street":"Lake Haven;Lake Haven Drv Lake",
    "iso:country":"AU",
    "sg:address":"Shop 14 Lake Haven Shopping Cntr Lake Haven Drv",
    "sg:city":"Lake Haven",
    "sg:classifiers":[
        {
            "category":"Shopping",
            "subcategory":"Clothing, Apparel, & Fashions",
            "type":"Retail Goods"
        }
    ],
    "sg:phone":"+61 2 4392 7610",
    "sg:postcode":"2263",
    "sg:province":"NSW",
    "sg:tags":[
        "menswear"
    ],
    "wof:name":"Lowes",
    "wof:placetype":"venue"
},
  "geometry": {"coordinates":[151.500137,-33.243942],"type":"Point"}
}