{
  "type": "Feature",
  "properties": {
    "addr:full":"54 Bayford St Oxley QLD 4075",
    "addr:housenumber":"54",
    "addr:postcode":"4075",
    "addr:street":"Bayford St",
    "iso:country":"AU",
    "sg:address":"54 Bayford St",
    "sg:city":"Oxley",
    "sg:classifiers":[
        {
            "category":"Building & Trades",
            "subcategory":"Construction",
            "type":"Services"
        }
    ],
    "sg:phone":"+61 410 596 977",
    "sg:postcode":"4075",
    "sg:province":"QLD",
    "sg:tags":[
        "management"
    ],
    "wof:name":"Archer Projects - Construction, Project Management",
    "wof:placetype":"venue"
},
  "geometry": {"coordinates":[152.98272705100001,-27.5594539642],"type":"Point"}
}