{
  "type": "Feature",
  "properties": {
    "addr:full":"464 Forestry Rd Bluewater QLD 4818",
    "addr:housenumber":"464",
    "addr:postcode":"4818",
    "addr:street":"Forestry Rd",
    "iso:country":"AU",
    "sg:address":"464 Forestry Rd",
    "sg:city":"Bluewater",
    "sg:classifiers":[
        {
            "category":"Professional",
            "subcategory":"Engineering",
            "type":"Services"
        }
    ],
    "sg:phone":"+61 7 4788 6066",
    "sg:postcode":"4818",
    "sg:province":"QLD",
    "sg:tags":[
        "engineer"
    ],
    "wof:name":"Larfarge Refractory Engineering Pty Ltd",
    "wof:placetype":"venue"
},
  "geometry": {"coordinates":[146.50247200000001,-19.217192],"type":"Point"}
}