{
  "type": "Feature",
  "properties": {
    "iso:country":"AU",
    "sg:address":"11 Birch Ave",
    "sg:city":"Newstead",
    "sg:classifiers":[
        {
            "category":"Government",
            "subcategory":"City Hall",
            "type":"Public Place"
        }
    ],
    "sg:phone":"+61 3 6331 2640",
    "sg:postcode":"7250",
    "sg:province":"TAS",
    "wof:name":"R.A.O.B., G.A.B. Hall",
    "wof:placetype":"venue"
},
  "geometry": {"coordinates":[147.162841797,-41.4398231506],"type":"Point"}
}