{
  "type": "Feature",
  "properties": {
    "addr:full":"31 Dinwoodie Ave Clarence Gardens SA 5039",
    "addr:housenumber":"31",
    "addr:postcode":"5039",
    "addr:street":"Dinwoodie Ave",
    "iso:country":"AU",
    "sg:address":"31 Dinwoodie Ave",
    "sg:city":"Clarence Gardens",
    "sg:classifiers":[
        {
            "category":"Shopping",
            "subcategory":"Computers & Home Electronics",
            "type":"Retail Goods"
        }
    ],
    "sg:phone":"+61 8 8293 8222",
    "sg:postcode":"5039",
    "sg:province":"SA",
    "sg:tags":[
        "wholesaler",
        "equipment",
        "electronic",
        "mfrs"
    ],
    "wof:name":"A.H. Distributors Pty Ltd",
    "wof:placetype":"venue"
},
  "geometry": {"coordinates":[138.576339722,-34.9702339172],"type":"Point"}
}