{
  "type": "Feature",
  "properties": {
    "addr:full":"61- 63 Williams Rd Coburg North VIC 3058",
    "addr:housenumber":"63",
    "addr:postcode":"3058",
    "addr:street":"Williams Rd",
    "iso:country":"AU",
    "sg:address":"61- 63 Williams Rd",
    "sg:city":"Coburg North",
    "sg:classifiers":[
        {
            "category":"Shopping",
            "subcategory":"Pets & Pet Supplies",
            "type":"Retail Goods"
        }
    ],
    "sg:phone":"+61 3 9350 6600",
    "sg:postcode":"3058",
    "sg:province":"VIC",
    "sg:tags":[
        "monumental",
        "mason"
    ],
    "wof:name":"APVS Marble & Granite",
    "wof:placetype":"venue"
},
  "geometry": {"coordinates":[144.96099853499999,-37.7272911072],"type":"Point"}
}