{
  "type": "Feature",
  "properties": {
    "iso:country":"AU",
    "sg:address":"13-15 Sunderland St",
    "sg:city":"Moonah",
    "sg:classifiers":[
        {
            "category":"Home & Garden",
            "subcategory":"Household Appliances",
            "type":"Retail Goods"
        }
    ],
    "sg:phone":"+61 3 6272 9819",
    "sg:postcode":"7009",
    "sg:province":"TAS",
    "sg:tags":[
        "heating",
        "system"
    ],
    "wof:name":"Fourtec",
    "wof:placetype":"venue"
},
  "geometry": {"coordinates":[147.29507446299999,-42.8417243958],"type":"Point"}
}