{
  "type": "Feature",
  "properties": {
    "addr:full":"Ashgrove West Shopping Centre 486 Waterworks Rd Ashgrove QLD 4060",
    "addr:housenumber":"486",
    "addr:postcode":"4060",
    "addr:street":"Waterworks Rd",
    "iso:country":"AU",
    "sg:address":"Ashgrove West Shopping Centre 486 Waterworks Rd",
    "sg:city":"Ashgrove",
    "sg:classifiers":[
        {
            "category":"Shopping",
            "subcategory":"Gifts & Souvenirs",
            "type":"Retail Goods"
        }
    ],
    "sg:phone":"+61 7 3366 7858",
    "sg:postcode":"4060",
    "sg:province":"QLD",
    "sg:tags":[
        "print",
        "poster",
        "pictures"
    ],
    "wof:name":"Ashgrove Picture Framers",
    "wof:placetype":"venue"
},
  "geometry": {"coordinates":[152.97793579099999,-27.4492511749],"type":"Point"}
}