{
  "type": "Feature",
  "properties": {
    "addr:full":"Young St Deepwater NSW 2371",
    "addr:postcode":"2371",
    "addr:street":"Young St",
    "iso:country":"AU",
    "sg:address":"Young St",
    "sg:city":"Deepwater",
    "sg:classifiers":[
        {
            "category":"Education",
            "subcategory":"School",
            "type":"Public Place"
        }
    ],
    "sg:phone":"+61 2 6734 5395",
    "sg:postcode":"2371",
    "sg:province":"NSW",
    "sg:tags":[
        "state",
        "-",
        "nsw"
    ],
    "wof:name":"Deepwater Public School",
    "wof:placetype":"venue"
},
  "geometry": {"coordinates":[151.84681701700001,-29.4422016144],"type":"Point"}
}