{
  "type": "Feature",
  "properties": {
    "addr:full":"Bruxner Hwy Lismore NSW 2480",
    "addr:postcode":"2480",
    "addr:street":"Bruxner Hwy",
    "iso:country":"AU",
    "sg:address":"Bruxner Hwy",
    "sg:city":"Lismore",
    "sg:classifiers":[
        {
            "category":"Professional",
            "subcategory":"Engineering",
            "type":"Services"
        }
    ],
    "sg:phone":"+61 2 6622 1222",
    "sg:postcode":"2480",
    "sg:province":"NSW",
    "sg:tags":[
        "engineer"
    ],
    "wof:name":"Gilmore Don Engineering",
    "wof:placetype":"venue"
},
  "geometry": {"coordinates":[153.26512145999999,-28.8239688873],"type":"Point"}
}