{
  "type": "Feature",
  "properties": {
    "addr:full":"Norris Rd Bracken Ridge QLD 4017",
    "addr:postcode":"4017",
    "addr:street":"Norris Rd",
    "iso:country":"AU",
    "sg:address":"Norris Rd",
    "sg:city":"Bracken Ridge",
    "sg:classifiers":[
        {
            "category":"Retail",
            "subcategory":"Auto Repair",
            "type":"Services"
        }
    ],
    "sg:phone":"+61 7 3261 5699",
    "sg:postcode":"4017",
    "sg:province":"QLD",
    "sg:tags":[
        "repairer",
        "motor",
        "engineer"
    ],
    "wof:name":"Auto Easy Mobile Mechanic's",
    "wof:placetype":"venue"
},
  "geometry": {"coordinates":[153.025314331,-27.3308849335],"type":"Point"}
}