{
  "type": "Feature",
  "properties": {
    "addr:full":"Morton Rd Christie Downs SA 5164",
    "addr:postcode":"5164",
    "addr:street":"Morton Rd",
    "iso:country":"AU",
    "sg:address":"Morton Rd",
    "sg:city":"Christie Downs",
    "sg:classifiers":[
        {
            "category":"Education",
            "subcategory":"School",
            "type":"Public Place"
        }
    ],
    "sg:phone":"+61 8 8329 9777",
    "sg:postcode":"5164",
    "sg:province":"SA",
    "sg:tags":[
        "state",
        "except",
        "nsw"
    ],
    "wof:name":"Christies Beach High & Southern Vocational College",
    "wof:placetype":"venue"
},
  "geometry": {"coordinates":[138.498291016,-35.1286239624],"type":"Point"}
}