{
  "type": "Feature",
  "properties": {
    "iso:country":"AU",
    "sg:address":"11 Hilldale Drv",
    "sg:city":"Cameron Park",
    "sg:classifiers":[
        {
            "category":"Professional",
            "subcategory":"Accounting & Tax Preparation",
            "type":"Services"
        }
    ],
    "sg:phone":"+61 2 4958 8683",
    "sg:postcode":"2285",
    "sg:province":"NSW",
    "sg:tags":[
        "consultant",
        "taxation"
    ],
    "wof:name":"Jason Hammond",
    "wof:placetype":"venue"
},
  "geometry": {"coordinates":[151.61509704599999,-32.9193305969],"type":"Point"}
}