{
  "type": "Feature",
  "properties": {
    "iso:country":"AU",
    "sg:address":"6 Boisdale Ave",
    "sg:city":"Sunshine North",
    "sg:classifiers":[
        {
            "category":"Professional",
            "subcategory":"Computer Services",
            "type":"Services"
        }
    ],
    "sg:phone":"+61 3 9364 8947",
    "sg:postcode":"3020",
    "sg:province":"VIC",
    "sg:tags":[
        "consultant",
        "system"
    ],
    "wof:name":"Microwise Solutions",
    "wof:placetype":"venue"
},
  "geometry": {"coordinates":[144.823181,-37.767197],"type":"Point"}
}