{
  "type": "Feature",
  "properties": {
    "addr:full":"17 Clyde Rd Berwick VIC 3806",
    "addr:housenumber":"17",
    "addr:postcode":"3806",
    "addr:street":"Clyde Rd",
    "iso:country":"AU",
    "sg:address":"17 Clyde Rd",
    "sg:city":"Berwick",
    "sg:classifiers":[
        {
            "category":"Health Services",
            "subcategory":"Doctor",
            "type":"Services"
        }
    ],
    "sg:phone":"+61 3 9707 1444",
    "sg:postcode":"3806",
    "sg:province":"VIC",
    "sg:tags":[
        "medical",
        "practitioner"
    ],
    "wof:name":"Ineson C",
    "wof:placetype":"venue"
},
  "geometry": {"coordinates":[145.34359741200001,-38.0330352783],"type":"Point"}
}