{
  "type": "Feature",
  "properties": {
    "addr:full":"8 / 35 Colin Jamieson Drv Welshpool WA 6106",
    "addr:housenumber":"/ 35",
    "addr:postcode":"6106",
    "addr:street":"Colin Jamieson Drv",
    "iso:country":"AU",
    "sg:address":"8 / 35 Colin Jamieson Drv",
    "sg:city":"Welshpool",
    "sg:classifiers":[
        {
            "category":"Communications",
            "type":"Services"
        }
    ],
    "sg:phone":"+61 1800 664 197",
    "sg:postcode":"6106",
    "sg:province":"WA",
    "sg:tags":[
        "equipment",
        "radio"
    ],
    "wof:name":"Sentricom",
    "wof:placetype":"venue"
},
  "geometry": {"coordinates":[115.936698914,-31.9936733246],"type":"Point"}
}