{
  "type": "Feature",
  "properties": {
    "addr:full":"437 Alderley St Toowoomba QLD 4350",
    "addr:housenumber":"437",
    "addr:postcode":"4350",
    "addr:street":"Alderley St",
    "iso:country":"AU",
    "sg:address":"437 Alderley St",
    "sg:city":"Toowoomba",
    "sg:classifiers":[
        {
            "category":"Building & Trades",
            "subcategory":"Construction",
            "type":"Services"
        }
    ],
    "sg:phone":"+61 7 4635 0799",
    "sg:postcode":"4350",
    "sg:province":"QLD",
    "sg:tags":[
        "contractor"
    ],
    "wof:name":"Craftsman Homes",
    "wof:placetype":"venue"
},
  "geometry": {"coordinates":[151.92248499999999,-27.580956],"type":"Point"}
}