{
  "type": "Feature",
  "properties": {
    "addr:full":"10 Gnoorong St Warneet VIC 3980",
    "addr:housenumber":"10",
    "addr:postcode":"3980",
    "addr:street":"Gnoorong St",
    "iso:country":"AU",
    "sg:address":"10 Gnoorong St",
    "sg:city":"Warneet",
    "sg:classifiers":[
        {
            "category":"Building & Trades",
            "subcategory":"Cleaning & Sanitation",
            "type":"Services"
        }
    ],
    "sg:phone":"+61 411 459 000",
    "sg:postcode":"3980",
    "sg:province":"VIC",
    "sg:tags":[
        "cleaner",
        "repairer",
        "roof"
    ],
    "wof:name":"Top Notch Roof Restorations",
    "wof:placetype":"venue"
},
  "geometry": {"coordinates":[145.309692383,-38.2238006592],"type":"Point"}
}