{
  "type": "Feature",
  "properties": {
    "iso:country":"AU",
    "sg:address":"19 Uduc Rd",
    "sg:city":"Harvey",
    "sg:classifiers":[
        {
            "category":"Autos & Motor Vehicles",
            "subcategory":"Fuel & Gas Station",
            "type":"Retail Goods"
        }
    ],
    "sg:phone":"+61 8 9729 1464",
    "sg:postcode":"6220",
    "sg:province":"WA",
    "wof:name":"Shell Co Of Australia Ltd The",
    "wof:placetype":"venue"
},
  "geometry": {"coordinates":[115.894058,-33.079948],"type":"Point"}
}