{
  "type": "Feature",
  "properties": {
    "iso:country":"AU",
    "sg:address":"1 North St",
    "sg:city":"Batemans Bay",
    "sg:classifiers":[
        {
            "category":"Real Estate",
            "subcategory":"Architect",
            "type":"Services"
        }
    ],
    "sg:phone":"+61 2 4472 7388",
    "sg:postcode":"2536",
    "sg:province":"NSW",
    "wof:name":"Architects Edmiston Jones",
    "wof:placetype":"venue"
},
  "geometry": {"coordinates":[150.17771911599999,-35.7060203552],"type":"Point"}
}