{
  "type": "Feature",
  "properties": {
    "addr:full":"Ste5/ 621 Wynnum Rd Morningside QLD 4170",
    "addr:housenumber":"621",
    "addr:postcode":"4170",
    "addr:street":"Wynnum Rd",
    "iso:country":"AU",
    "sg:address":"Ste5/ 621 Wynnum Rd",
    "sg:city":"Morningside",
    "sg:classifiers":[
        {
            "category":"Banks & Credit Unions",
            "subcategory":"Financial Services",
            "type":"Services"
        }
    ],
    "sg:phone":"+61 7 3902 2400",
    "sg:postcode":"4170",
    "sg:province":"QLD",
    "sg:tags":[
        "franchising"
    ],
    "wof:name":"Franchise Sales Australia",
    "wof:placetype":"venue"
},
  "geometry": {"coordinates":[153.071777344,-27.4680747986],"type":"Point"}
}