{
  "type": "Feature",
  "properties": {
    "addr:full":"1 Colchester St Somerville VIC 3912",
    "addr:housenumber":"1",
    "addr:postcode":"3912",
    "addr:street":"Colchester St",
    "iso:country":"AU",
    "sg:address":"1 Colchester St",
    "sg:city":"Somerville",
    "sg:classifiers":[
        {
            "category":"Shopping",
            "subcategory":"Clothing, Apparel, & Fashions",
            "type":"Retail Goods"
        }
    ],
    "sg:phone":"+61 3 5977 6725",
    "sg:postcode":"3912",
    "sg:province":"VIC",
    "sg:tags":[
        "wholesaler",
        "children's",
        "mfrs",
        "wear"
    ],
    "wof:name":"Our Child",
    "wof:placetype":"venue"
},
  "geometry": {"coordinates":[145.16545105,-38.2241897583],"type":"Point"}
}