{
  "type": "Feature",
  "properties": {
    "addr:full":"Cnr Wellington & Alfred Sts Mackay QLD 4740",
    "addr:postcode":"4740",
    "addr:street":"Cnr Wellington & Alfred Sts",
    "iso:country":"AU",
    "sg:address":"Cnr Wellington & Alfred Sts",
    "sg:city":"Mackay",
    "sg:classifiers":[
        {
            "category":"Professional",
            "subcategory":"Business Services",
            "type":"Services"
        }
    ],
    "sg:phone":"+61 7 4951 1722",
    "sg:postcode":"4740",
    "sg:province":"QLD",
    "sg:tags":[
        "consultant",
        "leasing"
    ],
    "sg:website":"http://www.alliedleasing.com.au",
    "wof:name":"Allied Leasing Corporation Pty Ltd",
    "wof:placetype":"venue"
},
  "geometry": {"coordinates":[149.179733,-21.148054],"type":"Point"}
}