{
  "type": "Feature",
  "properties": {
    "iso:country":"AU",
    "sg:address":"Blakefield Rd",
    "sg:city":"Muswellbrook",
    "sg:classifiers":[
        {
            "category":"Shopping",
            "subcategory":"Pets & Pet Supplies",
            "type":"Retail Goods"
        }
    ],
    "sg:phone":"+61 2 6541 3566",
    "sg:postcode":"2333",
    "sg:province":"NSW",
    "sg:tags":[
        "boring",
        "drilling",
        "equipment"
    ],
    "wof:name":"Team Manufacturing Australia Pty Ltd",
    "wof:placetype":"venue"
},
  "geometry": {"coordinates":[150.881134033,-32.3033790588],"type":"Point"}
}