{
  "type": "Feature",
  "properties": {
    "iso:country":"AU",
    "sg:address":"Cnr Darling & Dandenong Rds",
    "sg:city":"Malvern East",
    "sg:classifiers":[
        {
            "category":"Retail",
            "subcategory":"Auto Repair",
            "type":"Services"
        }
    ],
    "sg:phone":"+61 3 9571 2888",
    "sg:postcode":"3145",
    "sg:province":"VIC",
    "sg:tags":[
        "wheel",
        "balancing",
        "alignment"
    ],
    "wof:name":"Delarue Tyres Pty Ltd",
    "wof:placetype":"venue"
},
  "geometry": {"coordinates":[145.059448242,-37.8764343262],"type":"Point"}
}