{
  "type": "Feature",
  "properties": {
    "iso:country":"AU",
    "sg:address":"17 Matthew Flinders Drv",
    "sg:city":"Port Macquarie",
    "sg:classifiers":[
        {
            "category":"Building & Trades",
            "subcategory":"Landscaping Services",
            "type":"Services"
        }
    ],
    "sg:phone":"+61 2 6582 0950",
    "sg:postcode":"2444",
    "sg:province":"NSW",
    "sg:tags":[
        "consultant"
    ],
    "wof:name":"Mann Environmental Consultancy",
    "wof:placetype":"venue"
},
  "geometry": {"coordinates":[152.93362400000001,-31.472296],"type":"Point"}
}