{
  "type": "Feature",
  "properties": {
    "addr:full":"176 Weatherall Rd Cheltenham VIC 3192",
    "addr:housenumber":"176",
    "addr:postcode":"3192",
    "addr:street":"Weatherall Rd",
    "iso:country":"AU",
    "sg:address":"176 Weatherall Rd",
    "sg:city":"Cheltenham",
    "sg:classifiers":[
        {
            "category":"Building & Trades",
            "subcategory":"Locksmith",
            "type":"Services"
        }
    ],
    "sg:phone":"+61 3 9584 8188",
    "sg:postcode":"3192",
    "sg:province":"VIC",
    "sg:tags":[
        "lock"
    ],
    "wof:name":"Executive Locksmiths",
    "wof:placetype":"venue"
},
  "geometry": {"coordinates":[145.050979614,-37.9721374512],"type":"Point"}
}