{
  "type": "Feature",
  "properties": {
    "iso:country":"AU",
    "sg:address":"Metaira Rd",
    "sg:city":"Burnie",
    "sg:classifiers":[
        {
            "category":"Communications",
            "subcategory":"News Services",
            "type":"Services"
        }
    ],
    "sg:phone":"+61 3 6435 7229",
    "sg:postcode":"7320",
    "sg:province":"TAS",
    "sg:tags":[
        "information",
        "tourist",
        "attractions"
    ],
    "wof:name":"Annsleigh Gardens & Tea Rooms",
    "wof:placetype":"venue"
},
  "geometry": {"coordinates":[145.898254,-41.075859],"type":"Point"}
}