{
  "type": "Feature",
  "properties": {
    "addr:full":"308 Chapel St Prahran VIC 3181",
    "addr:housenumber":"308",
    "addr:postcode":"3181",
    "addr:street":"Chapel St",
    "iso:country":"AU",
    "sg:address":"308 Chapel St",
    "sg:city":"Prahran",
    "sg:classifiers":[
        {
            "category":"Shopping",
            "subcategory":"Music",
            "type":"Retail Goods"
        }
    ],
    "sg:phone":"+61 3 9530 2000",
    "sg:postcode":"3181",
    "sg:province":"VIC",
    "sg:tags":[
        "store"
    ],
    "wof:name":"Dixon Recycled Records",
    "wof:placetype":"venue"
},
  "geometry": {"coordinates":[144.99409484899999,-37.8480606079],"type":"Point"}
}