{
  "type": "Feature",
  "properties": {
    "iso:country":"AU",
    "sg:address":"Shp1/ 208 Beardy St",
    "sg:city":"Armidale",
    "sg:classifiers":[
        {
            "category":"Personal",
            "subcategory":"Shoe Repair & Shine",
            "type":"Services"
        }
    ],
    "sg:phone":"+61 2 6772 6618",
    "sg:postcode":"2350",
    "sg:province":"NSW",
    "sg:tags":[
        "footwear"
    ],
    "wof:name":"Armidale Shoe Repairs",
    "wof:placetype":"venue"
},
  "geometry": {"coordinates":[151.66510009800001,-30.5131778717],"type":"Point"}
}