{
  "type": "Feature",
  "properties": {
    "iso:country":"AU",
    "sg:address":"1/ 172 Cowper St",
    "sg:city":"Warrawong",
    "sg:classifiers":[
        {
            "category":"Personal",
            "subcategory":"Beauty Salon",
            "type":"Services"
        }
    ],
    "sg:phone":"+61 2 4274 0422",
    "sg:postcode":"2502",
    "sg:province":"NSW",
    "sg:tags":[
        "hairdresser"
    ],
    "wof:name":"JC Unique Hair Studio",
    "wof:placetype":"venue"
},
  "geometry": {"coordinates":[150.888992,-34.485126],"type":"Point"}
}