{
  "type": "Feature",
  "properties": {
    "iso:country":"AU",
    "sg:address":"PO Box 3010",
    "sg:city":"Yokine",
    "sg:classifiers":[
        {
            "category":"Real Estate",
            "subcategory":"Architect",
            "type":"Services"
        }
    ],
    "sg:phone":"+61 409 345 411",
    "sg:postcode":"6060",
    "sg:province":"WA",
    "sg:tags":[
        "building",
        "designer"
    ],
    "wof:name":"Kirkovski Design",
    "wof:placetype":"venue"
},
  "geometry": {"coordinates":[115.850013733,-31.9015102386],"type":"Point"}
}