{
  "type": "Feature",
  "properties": {
    "iso:country":"AU",
    "sg:address":"81- 83 Fairbank Rd",
    "sg:city":"Clayton South",
    "sg:classifiers":[
        {
            "category":"Food & Beverages",
            "subcategory":"Bakery",
            "type":"Retail Goods"
        }
    ],
    "sg:phone":"+61 1300 225 464",
    "sg:postcode":"3169",
    "sg:province":"VIC",
    "sg:tags":[
        "baker"
    ],
    "wof:name":"Goodman Fielder",
    "wof:placetype":"venue"
},
  "geometry": {"coordinates":[145.13052368199999,-37.9418182373],"type":"Point"}
}