{
  "type": "Feature",
  "properties": {
    "iso:country":"AU",
    "sg:address":"18a Blandford St",
    "sg:city":"Grange",
    "sg:classifiers":[
        {
            "category":"Professional",
            "subcategory":"Engineering",
            "type":"Services"
        }
    ],
    "sg:phone":"+61 7 3352 5359",
    "sg:postcode":"4051",
    "sg:province":"QLD",
    "sg:tags":[
        "civil",
        "engineer"
    ],
    "wof:name":"J & G Civil Drainage Contracting",
    "wof:placetype":"venue"
},
  "geometry": {"coordinates":[153.00865173299999,-27.4210910797],"type":"Point"}
}