{
  "type": "Feature",
  "properties": {
    "addr:full":"Court House Cornmeal Pde Maroochydore QLD 4558",
    "addr:postcode":"4558",
    "addr:street":"Cornmeal",
    "iso:country":"AU",
    "sg:address":"Court House Cornmeal Pde",
    "sg:city":"Maroochydore",
    "sg:classifiers":[
        {
            "category":"Organizations",
            "subcategory":"Community Association",
            "type":"Services"
        }
    ],
    "sg:phone":"+61 7 5443 7439",
    "sg:postcode":"4558",
    "sg:province":"QLD",
    "sg:tags":[
        "organisation",
        "family",
        "welfare"
    ],
    "wof:name":"Friends At Court",
    "wof:placetype":"venue"
},
  "geometry": {"coordinates":[153.08999633799999,-26.6540470123],"type":"Point"}
}