{
  "type": "Feature",
  "properties": {
    "addr:full":"Shed 2/ 6 Travers St Coconut Grove NT 0810",
    "addr:housenumber":"2 / 6",
    "addr:postcode":"0810",
    "addr:street":"Travers St",
    "iso:country":"AU",
    "sg:address":"Shed 2/ 6 Travers St",
    "sg:city":"Coconut Grove",
    "sg:classifiers":[
        {
            "category":"Home & Garden",
            "subcategory":"Hardware",
            "type":"Retail Goods"
        }
    ],
    "sg:phone":"+61 8 8948 4122",
    "sg:postcode":"0810",
    "sg:province":"NT",
    "sg:tags":[
        "tarpaulin"
    ],
    "wof:name":"Shadeworks Hire",
    "wof:placetype":"venue"
},
  "geometry": {"coordinates":[130.85319519000001,-12.4012441635],"type":"Point"}
}