{
  "type": "Feature",
  "properties": {
    "addr:full":"Tucka Tucka St Quambone NSW 2831",
    "addr:postcode":"2831",
    "addr:street":"St",
    "iso:country":"AU",
    "sg:address":"Tucka Tucka St",
    "sg:city":"Quambone",
    "sg:classifiers":[
        {
            "category":"Government",
            "subcategory":"Post Office",
            "type":"Public Place"
        }
    ],
    "sg:phone":"+61 2 6824 2077",
    "sg:postcode":"2831",
    "sg:province":"NSW",
    "sg:tags":[
        "postal"
    ],
    "wof:name":"Australia Post",
    "wof:placetype":"venue"
},
  "geometry": {"coordinates":[147.87013244600001,-30.9283695221],"type":"Point"}
}