{
  "type": "Feature",
  "properties": {
    "iso:country":"AU",
    "sg:address":"32 Merton St",
    "sg:city":"Altona Meadows",
    "sg:classifiers":[
        {
            "category":"Building & Trades",
            "subcategory":"Cleaning & Sanitation",
            "type":"Services"
        }
    ],
    "sg:phone":"+61 3 9931 1427",
    "sg:postcode":"3028",
    "sg:province":"VIC",
    "sg:tags":[
        "industrial",
        "commercial",
        "contractor"
    ],
    "wof:name":"White Seal Contract Cleaning Services Pty ltd",
    "wof:placetype":"venue"
},
  "geometry": {"coordinates":[144.778244,-37.865067],"type":"Point"}
}