{
  "type": "Feature",
  "properties": {
    "addr:full":"52A Ballina St Lennox Head NSW 2478",
    "addr:housenumber":"52a",
    "addr:postcode":"2478",
    "addr:street":"Ballina St",
    "iso:country":"AU",
    "sg:address":"52A Ballina St",
    "sg:city":"Lennox Head",
    "sg:classifiers":[
        {
            "category":"Shopping",
            "subcategory":"Computers & Home Electronics",
            "type":"Retail Goods"
        }
    ],
    "sg:phone":"+61 2 6687 7735",
    "sg:postcode":"2478",
    "sg:province":"NSW",
    "sg:tags":[
        "hardware",
        "equipment"
    ],
    "wof:name":"Lennox Head Computer Services",
    "wof:placetype":"venue"
},
  "geometry": {"coordinates":[153.59378051799999,-28.7946224213],"type":"Point"}
}