{
  "type": "Feature",
  "properties": {
    "addr:full":"80 Woodville Rd Granville NSW 2142",
    "addr:housenumber":"80",
    "addr:postcode":"2142",
    "addr:street":"Woodville Rd",
    "iso:country":"AU",
    "sg:address":"80 Woodville Rd",
    "sg:city":"Granville",
    "sg:classifiers":[
        {
            "category":"Retail",
            "subcategory":"Auto Repair",
            "type":"Services"
        }
    ],
    "sg:phone":"+61 2 9637 5474",
    "sg:postcode":"2142",
    "sg:province":"NSW",
    "sg:tags":[
        "repairer",
        "motor",
        "engineer"
    ],
    "wof:name":"P Auto Repair",
    "wof:placetype":"venue"
},
  "geometry": {"coordinates":[151.00227355999999,-33.8335990906],"type":"Point"}
}