{
  "type": "Feature",
  "properties": {
    "addr:full":"79 Jersey Rd Woollahra NSW 2025",
    "addr:housenumber":"79",
    "addr:postcode":"2025",
    "addr:street":"Jersey Rd",
    "iso:country":"AU",
    "sg:address":"79 Jersey Rd",
    "sg:city":"Woollahra",
    "sg:classifiers":[
        {
            "category":"Wholesale",
            "subcategory":"Furniture",
            "type":"Manufacturing & Wholesale Goods"
        }
    ],
    "sg:phone":"+61 2 9328 3352",
    "sg:postcode":"2025",
    "sg:province":"NSW",
    "sg:tags":[
        "wholesaler",
        "mfrs"
    ],
    "wof:name":"Christophe Living",
    "wof:placetype":"venue"
},
  "geometry": {"coordinates":[151.235794067,-33.8874588013],"type":"Point"}
}