{
  "type": "Feature",
  "properties": {
    "addr:full":"122 High St Avoca VIC 3467",
    "addr:housenumber":"122",
    "addr:postcode":"3467",
    "addr:street":"High St",
    "iso:country":"AU",
    "sg:address":"122 High St",
    "sg:city":"Avoca",
    "sg:classifiers":[
        {
            "category":"Communications",
            "subcategory":"News Services",
            "type":"Services"
        }
    ],
    "sg:phone":"+61 1800 206 622",
    "sg:postcode":"3467",
    "sg:province":"VIC",
    "sg:tags":[
        "information",
        "tourist",
        "attractions"
    ],
    "wof:name":"Avoca Information & Community Resource Centre",
    "wof:placetype":"venue"
},
  "geometry": {"coordinates":[143.47445678700001,-37.0887298584],"type":"Point"}
}