{
  "type": "Feature",
  "properties": {
    "iso:country":"AU",
    "sg:address":"Shop 2/ 5 Fannie Bay Pl",
    "sg:city":"Fannie Bay",
    "sg:classifiers":[
        {
            "category":"Arena",
            "subcategory":"Horse Racetrack",
            "type":"Entertainment"
        }
    ],
    "sg:phone":"+61 8 8981 6220",
    "sg:postcode":"0820",
    "sg:province":"NT",
    "sg:tags":[
        "retail",
        "swimwear"
    ],
    "wof:name":"Beach Bums",
    "wof:placetype":"venue"
},
  "geometry": {"coordinates":[130.83648681599999,-12.4239044189],"type":"Point"}
}