{
  "type": "Feature",
  "properties": {
    "addr:full":"22 Glenlivet Crt Greenwith SA 5125",
    "addr:housenumber":"22",
    "addr:postcode":"5125",
    "addr:street":"Glenlivet Crt",
    "iso:country":"AU",
    "sg:address":"22 Glenlivet Crt",
    "sg:city":"Greenwith",
    "sg:classifiers":[
        {
            "category":"Building & Trades",
            "subcategory":"Construction",
            "type":"Services"
        }
    ],
    "sg:phone":"+61 8 8289 7553",
    "sg:postcode":"5125",
    "sg:province":"SA",
    "sg:tags":[
        "fencing",
        "contractor"
    ],
    "wof:name":"Ace Fencing",
    "wof:placetype":"venue"
},
  "geometry": {"coordinates":[138.709656,-34.767735],"type":"Point"}
}