{
  "type": "Feature",
  "properties": {
    "addr:full":"(Sales) Unit 14/ 8 Campbell St Artarmon NSW 2064",
    "addr:housenumber":"14 / 8",
    "addr:postcode":"2064",
    "addr:street":"Campbell St",
    "iso:country":"AU",
    "sg:address":"(Sales) Unit 14/ 8 Campbell St",
    "sg:city":"Artarmon",
    "sg:classifiers":[
        {
            "category":"Shopping",
            "subcategory":"Computers & Home Electronics",
            "type":"Retail Goods"
        }
    ],
    "sg:phone":"+61 2 9438 3977",
    "sg:postcode":"2064",
    "sg:province":"NSW",
    "sg:tags":[
        "hardware",
        "equipment"
    ],
    "wof:name":"Time-Link Pty Ltd",
    "wof:placetype":"venue"
},
  "geometry": {"coordinates":[151.18661499000001,-33.8174438477],"type":"Point"}
}