{
  "type": "Feature",
  "properties": {
    "iso:country":"AU",
    "sg:address":"Percy St",
    "sg:city":"Wellington",
    "sg:classifiers":[
        {
            "category":"Education",
            "subcategory":"School",
            "type":"Public Place"
        }
    ],
    "sg:phone":"+61 2 6845 4080",
    "sg:postcode":"2820",
    "sg:province":"NSW",
    "sg:tags":[
        "state",
        "-",
        "nsw"
    ],
    "wof:name":"Wellington Primary School",
    "wof:placetype":"venue"
},
  "geometry": {"coordinates":[148.94215393100001,-32.5565872192],"type":"Point"}
}