{
  "type": "Feature",
  "properties": {
    "addr:full":"180 Sunnyholt Rd Blacktown NSW 2148",
    "addr:housenumber":"180",
    "addr:postcode":"2148",
    "addr:street":"Sunnyholt Rd",
    "iso:country":"AU",
    "sg:address":"180 Sunnyholt Rd",
    "sg:city":"Blacktown",
    "sg:classifiers":[
        {
            "category":"Retail",
            "subcategory":"Auto Repair",
            "type":"Services"
        }
    ],
    "sg:phone":"+61 2 9671 6100",
    "sg:postcode":"2148",
    "sg:province":"NSW",
    "sg:tags":[
        "repairer",
        "motor",
        "engineer"
    ],
    "wof:name":"Fletcher's Automotive Services Pty Ltd",
    "wof:placetype":"venue"
},
  "geometry": {"coordinates":[150.91569519000001,-33.7500495911],"type":"Point"}
}