{
  "type": "Feature",
  "properties": {
    "iso:country":"AU",
    "sg:address":"11 Matthew Jones Drv",
    "sg:city":"Warwick",
    "sg:classifiers":[
        {
            "category":"Building & Trades",
            "subcategory":"Construction",
            "type":"Services"
        }
    ],
    "sg:phone":"+61 7 4661 8613",
    "sg:postcode":"4370",
    "sg:province":"QLD",
    "sg:tags":[
        "industrial",
        "commercial",
        "air conditioning"
    ],
    "wof:name":"Ezychill Pty Ltd",
    "wof:placetype":"venue"
},
  "geometry": {"coordinates":[152.00126648,-28.2206554413],"type":"Point"}
}