{
  "type": "Feature",
  "properties": {
    "addr:full":"9 Heather St Collaroy Plateau NSW 2097",
    "addr:housenumber":"9",
    "addr:postcode":"2097",
    "addr:street":"Heather St",
    "iso:country":"AU",
    "sg:address":"9 Heather St",
    "sg:city":"Collaroy Plateau",
    "sg:classifiers":[
        {
            "category":"Building & Trades",
            "subcategory":"Construction",
            "type":"Services"
        }
    ],
    "sg:phone":"+61 409 242 380",
    "sg:postcode":"2097",
    "sg:province":"NSW",
    "sg:tags":[
        "contractor"
    ],
    "wof:name":"Shallis Building Pty Ltd",
    "wof:placetype":"venue"
},
  "geometry": {"coordinates":[151.28477477999999,-33.7313423157],"type":"Point"}
}