{
  "type": "Feature",
  "properties": {
    "iso:country":"AU",
    "sg:address":"Factory 1, 26 Keon Pde",
    "sg:city":"Thomastown",
    "sg:classifiers":[
        {
            "category":"Retail",
            "subcategory":"Auto Repair",
            "type":"Services"
        }
    ],
    "sg:phone":"+61 3 9460 9122",
    "sg:postcode":"3074",
    "sg:province":"VIC",
    "sg:tags":[
        "repairer",
        "motor",
        "engineer"
    ],
    "wof:name":"Auto Volante Automotive Repair Specialists",
    "wof:placetype":"venue"
},
  "geometry": {"coordinates":[145.015548706,-37.6949691772],"type":"Point"}
}