{
  "type": "Feature",
  "properties": {
    "addr:full":"19 Summer Hill Crt Wynn Vale SA 5127",
    "addr:housenumber":"19",
    "addr:postcode":"5127",
    "addr:street":"Summer Hill Crt",
    "iso:country":"AU",
    "sg:address":"19 Summer Hill Crt",
    "sg:city":"Wynn Vale",
    "sg:classifiers":[
        {
            "category":"Personal",
            "type":"Services"
        }
    ],
    "sg:phone":"+61 8 8263 6089",
    "sg:postcode":"5127",
    "sg:province":"SA",
    "sg:tags":[
        "reducing",
        "treatment",
        "weight"
    ],
    "wof:name":"Herbalife Australasia Pty Ltd",
    "wof:placetype":"venue"
},
  "geometry": {"coordinates":[138.67657470699999,-34.8041191101],"type":"Point"}
}