{
  "type": "Feature",
  "properties": {
    "addr:full":"1140 South Rd Clovelly Park SA 5042",
    "addr:housenumber":"1140",
    "addr:postcode":"5042",
    "addr:street":"South Rd",
    "iso:country":"AU",
    "sg:address":"1140 South Rd",
    "sg:city":"Clovelly Park",
    "sg:classifiers":[
        {
            "category":"Health Services",
            "subcategory":"Doctor",
            "type":"Services"
        }
    ],
    "sg:phone":"+61 8 8276 9855",
    "sg:postcode":"5042",
    "sg:province":"SA",
    "sg:tags":[
        "medical",
        "practitioner"
    ],
    "wof:name":"Taylor Susan E",
    "wof:placetype":"venue"
},
  "geometry": {"coordinates":[138.574783,-34.994579],"type":"Point"}
}