{
  "type": "Feature",
  "properties": {
    "iso:country":"AU",
    "sg:address":"1 Tudor Rd",
    "sg:city":"Sunshine",
    "sg:classifiers":[
        {
            "category":"Professional",
            "subcategory":"Detective & Security Services",
            "type":"Services"
        }
    ],
    "sg:phone":"+61 433 852 928",
    "sg:postcode":"3020",
    "sg:province":"VIC",
    "sg:tags":[
        "domestic",
        "alarm",
        "commercial",
        "burglar"
    ],
    "wof:name":"TFT Pty Ltd",
    "wof:placetype":"venue"
},
  "geometry": {"coordinates":[144.831238,-37.767899],"type":"Point"}
}