{
  "type": "Feature",
  "properties": {
    "addr:full":"67 Koornang Rd Carnegie VIC 3163",
    "addr:housenumber":"67",
    "addr:postcode":"3163",
    "addr:street":"Koornang Rd",
    "iso:country":"AU",
    "sg:address":"67 Koornang Rd",
    "sg:city":"Carnegie",
    "sg:classifiers":[
        {
            "category":"Health Services",
            "subcategory":"Health Practitioner",
            "type":"Services"
        }
    ],
    "sg:phone":"+61 3 8500 2343",
    "sg:postcode":"3163",
    "sg:province":"VIC",
    "sg:tags":[
        "naturopath"
    ],
    "wof:name":"Michelle Maddern",
    "wof:placetype":"venue"
},
  "geometry": {"coordinates":[145.05735778799999,-37.8867835999],"type":"Point"}
}