{
  "type": "Feature",
  "properties": {
    "addr:full":"3c May St Scarborough WA 6019",
    "addr:housenumber":"3c",
    "addr:postcode":"6019",
    "addr:street":"May St",
    "iso:country":"AU",
    "sg:address":"3c May St",
    "sg:city":"Scarborough",
    "sg:classifiers":[
        {
            "category":"Banks & Credit Unions",
            "subcategory":"Bank",
            "type":"Services"
        }
    ],
    "sg:phone":"+61 413 151 596",
    "sg:postcode":"6019",
    "sg:province":"WA",
    "sg:tags":[
        "broker",
        "mortgage"
    ],
    "wof:name":"Mortgage Angels",
    "wof:placetype":"venue"
},
  "geometry": {"coordinates":[115.761428833,-31.8903656006],"type":"Point"}
}