{
  "type": "Feature",
  "properties": {
    "addr:full":"Cnr Enoggera Rd & Ashgrove Ave Newmarket QLD 4051",
    "addr:postcode":"4051",
    "addr:street":"Cnr Enoggera Rd & Ashgrove Ave",
    "iso:country":"AU",
    "sg:address":"Cnr Enoggera Rd & Ashgrove Ave",
    "sg:city":"Newmarket",
    "sg:classifiers":[
        {
            "category":"Health Services",
            "subcategory":"Doctor",
            "type":"Services"
        }
    ],
    "sg:phone":"+61 7 3356 8940",
    "sg:postcode":"4051",
    "sg:province":"QLD",
    "sg:tags":[
        "medical",
        "practitioner"
    ],
    "wof:name":"Newmarket 7 Day Medical Centre",
    "wof:placetype":"venue"
},
  "geometry": {"coordinates":[153.00544738799999,-27.4302997589],"type":"Point"}
}