{
  "type": "Feature",
  "properties": {
    "addr:full":"103 Canterbury Rd Bayswater North VIC 3153",
    "addr:housenumber":"103",
    "addr:postcode":"3153",
    "addr:street":"Canterbury Rd",
    "iso:country":"AU",
    "sg:address":"103 Canterbury Rd",
    "sg:city":"Bayswater North",
    "sg:classifiers":[
        {
            "category":"Building & Trades",
            "subcategory":"Plumbing",
            "type":"Services"
        }
    ],
    "sg:phone":"+61 3 9720 5222",
    "sg:postcode":"3153",
    "sg:province":"VIC",
    "sg:tags":[
        "plumber",
        "gasfitters"
    ],
    "wof:name":"R & S Plumbing",
    "wof:placetype":"venue"
},
  "geometry": {"coordinates":[145.29335022000001,-37.8248252869],"type":"Point"}
}