{
  "type": "Feature",
  "properties": {
    "addr:full":"63 Milburn St Chermside West QLD 4032",
    "addr:housenumber":"63",
    "addr:postcode":"4032",
    "addr:street":"Milburn St",
    "iso:country":"AU",
    "sg:address":"63 Milburn St",
    "sg:city":"Chermside West",
    "sg:classifiers":[
        {
            "category":"Government",
            "subcategory":"Post Office",
            "type":"Public Place"
        }
    ],
    "sg:phone":"+61 7 3359 7550",
    "sg:postcode":"4032",
    "sg:province":"QLD",
    "sg:tags":[
        "postal"
    ],
    "wof:name":"Chermside West Post Office",
    "wof:placetype":"venue"
},
  "geometry": {"coordinates":[153.018753,-27.378542],"type":"Point"}
}