{
  "type": "Feature",
  "properties": {
    "addr:full":"6 Jackson Pde Coburg VIC 3058",
    "addr:housenumber":"6",
    "addr:postcode":"3058",
    "addr:street":"Jackson Pde",
    "iso:country":"AU",
    "sg:address":"6 Jackson Pde",
    "sg:city":"Coburg",
    "sg:classifiers":[
        {
            "category":"Retail",
            "subcategory":"Auto Repair",
            "type":"Services"
        }
    ],
    "sg:phone":"+61 3 9354 1165",
    "sg:postcode":"3058",
    "sg:province":"VIC",
    "sg:tags":[
        "body",
        "motor",
        "trimmer"
    ],
    "wof:name":"Cleary & Son Motor Trimmers",
    "wof:placetype":"venue"
},
  "geometry": {"coordinates":[144.980392456,-37.7351303101],"type":"Point"}
}