{
  "type": "Feature",
  "properties": {
    "addr:full":"Unit 11/ 323 Newcastle St Northbridge WA 6003",
    "addr:housenumber":"/ 323",
    "addr:postcode":"6003",
    "addr:street":"Newcastle St",
    "iso:country":"AU",
    "sg:address":"Unit 11/ 323 Newcastle St",
    "sg:city":"Northbridge",
    "sg:classifiers":[
        {
            "category":"Professional",
            "subcategory":"Art Services",
            "type":"Services"
        }
    ],
    "sg:phone":"+61 8 9328 4060",
    "sg:postcode":"6003",
    "sg:province":"WA",
    "sg:tags":[
        "interior",
        "designer"
    ],
    "wof:name":"B Z Design",
    "wof:placetype":"venue"
},
  "geometry": {"coordinates":[115.85456085200001,-31.9431152344],"type":"Point"}
}