{
  "type": "Feature",
  "properties": {
    "addr:full":"PO Box 68 Aireys Inlet VIC 3231",
    "addr:postcode":"3231",
    "iso:country":"AU",
    "sg:address":"PO Box 68",
    "sg:city":"Aireys Inlet",
    "sg:classifiers":[
        {
            "category":"Social Services",
            "subcategory":"Retirement Home",
            "type":"Services"
        }
    ],
    "sg:phone":"+61 419 512 151",
    "sg:postcode":"3231",
    "sg:province":"VIC",
    "sg:tags":[
        "environmental",
        "consultant",
        "pollution"
    ],
    "wof:name":"Greene Environmental System",
    "wof:placetype":"venue"
},
  "geometry": {"coordinates":[144.10638427699999,-38.4604187012],"type":"Point"}
}