{
  "type": "Feature",
  "properties": {
    "iso:country":"AU",
    "sg:address":"5 Heath Crt",
    "sg:city":"Dales Creek",
    "sg:classifiers":[
        {
            "category":"Building & Trades",
            "subcategory":"Construction",
            "type":"Services"
        }
    ],
    "sg:phone":"+61 3 5368 6777",
    "sg:postcode":"3341",
    "sg:province":"VIC",
    "sg:tags":[
        "earth",
        "excavating",
        "moving",
        "contractor"
    ],
    "wof:name":"On Trac Mini Digger",
    "wof:placetype":"venue"
},
  "geometry": {"coordinates":[144.30165100100001,-37.5176734924],"type":"Point"}
}