{
  "type": "Feature",
  "properties": {
    "addr:full":"1/ 271 Esplanade Lakes Entrance VIC 3909",
    "addr:housenumber":"/ 271",
    "addr:postcode":"3909",
    "addr:street":"Esplanade",
    "iso:country":"AU",
    "sg:address":"1/ 271 Esplanade",
    "sg:city":"Lakes Entrance",
    "sg:classifiers":[
        {
            "category":"Professional",
            "subcategory":"Accounting & Tax Preparation",
            "type":"Services"
        }
    ],
    "sg:phone":"+61 3 5155 3700",
    "sg:postcode":"3909",
    "sg:province":"VIC",
    "sg:tags":[
        "accountant",
        "auditor"
    ],
    "wof:name":"Eager & Partners",
    "wof:placetype":"venue"
},
  "geometry": {"coordinates":[148.00227355999999,-37.8771514893],"type":"Point"}
}