{
  "type": "Feature",
  "properties": {
    "iso:country":"AU",
    "sg:address":"17 Boronia St",
    "sg:city":"Ermington",
    "sg:classifiers":[
        {
            "category":"Professional",
            "subcategory":"Detective & Security Services",
            "type":"Services"
        }
    ],
    "sg:phone":"+61 2 9638 5533",
    "sg:postcode":"2115",
    "sg:province":"NSW",
    "sg:tags":[
        "domestic",
        "alarm",
        "commercial",
        "burglar"
    ],
    "wof:name":"B H F-Affordable Alarms",
    "wof:placetype":"venue"
},
  "geometry": {"coordinates":[151.06031799300001,-33.817817688],"type":"Point"}
}