{
  "type": "Feature",
  "properties": {
    "addr:full":"1 Edgecliff Rd Bondi Junction NSW 2022",
    "addr:housenumber":"1",
    "addr:postcode":"2022",
    "addr:street":"Edgecliff Rd",
    "iso:country":"AU",
    "sg:address":"1 Edgecliff Rd",
    "sg:city":"Bondi Junction",
    "sg:classifiers":[
        {
            "category":"Building & Trades",
            "subcategory":"Construction",
            "type":"Services"
        }
    ],
    "sg:phone":"+61 2 9387 4111",
    "sg:postcode":"2022",
    "sg:province":"NSW",
    "sg:tags":[
        "contractor"
    ],
    "wof:name":"Spinners Team Of Tradesmen",
    "wof:placetype":"venue"
},
  "geometry": {"coordinates":[151.25607299800001,-33.889251709],"type":"Point"}
}