{
  "type": "Feature",
  "properties": {
    "iso:country":"AU",
    "sg:address":"3392 Warburton Hwy",
    "sg:city":"Warburton",
    "sg:classifiers":[
        {
            "category":"Health Services",
            "subcategory":"Health Practitioner",
            "type":"Services"
        }
    ],
    "sg:phone":"+61 3 5966 9922",
    "sg:postcode":"3799",
    "sg:province":"VIC",
    "sg:tags":[
        "alternative"
    ],
    "wof:name":"Warburton Wellbeing",
    "wof:placetype":"venue"
},
  "geometry": {"coordinates":[145.69866943400001,-37.7531318665],"type":"Point"}
}