{
  "type": "Feature",
  "properties": {
    "iso:country":"AU",
    "sg:address":"PO Box 270",
    "sg:city":"Hamilton",
    "sg:classifiers":[
        {
            "category":"Professional",
            "subcategory":"Detective & Security Services",
            "type":"Services"
        }
    ],
    "sg:phone":"+61 7 3257 4701",
    "sg:postcode":"4007",
    "sg:province":"QLD",
    "sg:tags":[
        "investigator"
    ],
    "wof:name":"GCI Group Pty Ltd",
    "wof:placetype":"venue"
},
  "geometry": {"coordinates":[153.064606,-27.4375],"type":"Point"}
}