{
  "type": "Feature",
  "properties": {
    "addr:full":"PO Box 441 Mermaid Beach QLD 4218",
    "addr:postcode":"4218",
    "iso:country":"AU",
    "sg:address":"PO Box 441",
    "sg:city":"Mermaid Beach",
    "sg:classifiers":[
        {
            "category":"Train Station",
            "subcategory":"Light Rail",
            "type":"Transportation"
        }
    ],
    "sg:phone":"+61 7 5527 7333",
    "sg:postcode":"4218",
    "sg:province":"QLD",
    "sg:tags":[
        "survey",
        "traffic"
    ],
    "wof:name":"Skild Traffic",
    "wof:placetype":"venue"
},
  "geometry": {"coordinates":[153.433761597,-28.0389785767],"type":"Point"}
}