{
  "type": "Feature",
  "properties": {
    "addr:full":"Shop 14, Birkdale Fair, Cnr Birkdale Rd & Mary Ple Birkdale QLD 4159",
    "addr:housenumber":"shop 14",
    "addr:postcode":"4159",
    "addr:street":"Birkdale Fair Cnr Birkdale Rd & Mary Ple",
    "iso:country":"AU",
    "sg:address":"Shop 14, Birkdale Fair, Cnr Birkdale Rd & Mary Ple",
    "sg:city":"Birkdale",
    "sg:classifiers":[
        {
            "category":"Food & Beverages",
            "subcategory":"Bakery",
            "type":"Retail Goods"
        }
    ],
    "sg:phone":"+61 7 3822 4211",
    "sg:postcode":"4159",
    "sg:province":"QLD",
    "sg:tags":[
        "baker"
    ],
    "wof:name":"Brumbys Bakeries",
    "wof:placetype":"venue"
},
  "geometry": {"coordinates":[153.208618164,-27.5049152374],"type":"Point"}
}