{
  "type": "Feature",
  "properties": {
    "addr:full":"22- 26 Osborne Ave Cowes VIC 3922",
    "addr:housenumber":"26",
    "addr:postcode":"3922",
    "addr:street":"Osborne Ave",
    "iso:country":"AU",
    "sg:address":"22- 26 Osborne Ave",
    "sg:city":"Cowes",
    "sg:classifiers":[
        {
            "category":"Travel",
            "subcategory":"Hotels & Motels",
            "type":"Entertainment"
        }
    ],
    "sg:phone":"+61 3 5952 1874",
    "sg:postcode":"3922",
    "sg:province":"VIC",
    "wof:name":"Tropicana Motor Inn",
    "wof:placetype":"venue"
},
  "geometry": {"coordinates":[145.23431396500001,-38.4514541626],"type":"Point"}
}