{
  "type": "Feature",
  "properties": {
    "addr:full":"11 Queensferry Pl Greenvale VIC 3059",
    "addr:housenumber":"11",
    "addr:postcode":"3059",
    "addr:street":"Queensferry Pl",
    "iso:country":"AU",
    "sg:address":"11 Queensferry Pl",
    "sg:city":"Greenvale",
    "sg:classifiers":[
        {
            "category":"Building & Trades",
            "subcategory":"Construction",
            "type":"Services"
        }
    ],
    "sg:phone":"+61 3 9333 1454",
    "sg:postcode":"3059",
    "sg:province":"VIC",
    "sg:tags":[
        "roof"
    ],
    "wof:name":"Zemlic Roofing",
    "wof:placetype":"venue"
},
  "geometry": {"coordinates":[144.884765625,-37.6498985291],"type":"Point"}
}