{
  "type": "Feature",
  "properties": {
    "addr:full":"PO Box 67 Park Orchards VIC 3114",
    "addr:postcode":"3114",
    "iso:country":"AU",
    "sg:address":"PO Box 67",
    "sg:city":"Park Orchards",
    "sg:classifiers":[
        {
            "category":"Shopping",
            "subcategory":"Stationery & Office Supplies",
            "type":"Retail Goods"
        }
    ],
    "sg:phone":"+61 3 9876 5997",
    "sg:postcode":"3114",
    "sg:province":"VIC",
    "sg:tags":[
        "packaging",
        "material"
    ],
    "wof:name":"Warehouse Wrappings Supplies Pty Ltd",
    "wof:placetype":"venue"
},
  "geometry": {"coordinates":[145.21330261200001,-37.7759590149],"type":"Point"}
}