{
  "type": "Feature",
  "properties": {
    "iso:country":"AU",
    "sg:address":"42 Bowman Crs",
    "sg:city":"Enfield",
    "sg:classifiers":[
        {
            "category":"Building & Trades",
            "subcategory":"Construction",
            "type":"Services"
        }
    ],
    "sg:phone":"+61 8 8262 2693",
    "sg:postcode":"5085",
    "sg:province":"SA",
    "sg:tags":[
        "mural"
    ],
    "wof:name":"Catherine M Bourn",
    "wof:placetype":"venue"
},
  "geometry": {"coordinates":[138.60745239299999,-34.8621940613],"type":"Point"}
}