{
  "type": "Feature",
  "properties": {
    "iso:country":"AU",
    "sg:address":"24 Grove St",
    "sg:city":"Dulwich Hill",
    "sg:classifiers":[
        {
            "category":"Building & Trades",
            "subcategory":"Construction",
            "type":"Services"
        }
    ],
    "sg:phone":"+61 2 9560 6199",
    "sg:postcode":"2203",
    "sg:province":"NSW",
    "sg:tags":[
        "concrete",
        "contractor"
    ],
    "wof:name":"Royal Hire",
    "wof:placetype":"venue"
},
  "geometry": {"coordinates":[151.138718,-33.902081],"type":"Point"}
}