{
  "type": "Feature",
  "properties": {
    "addr:full":"135 Stirling Hwy Nedlands WA 6009",
    "addr:housenumber":"135",
    "addr:postcode":"6009",
    "addr:street":"Stirling Hwy",
    "iso:country":"AU",
    "sg:address":"135 Stirling Hwy",
    "sg:city":"Nedlands",
    "sg:classifiers":[
        {
            "category":"Fast Food",
            "type":"Food & Drink"
        }
    ],
    "sg:phone":"+61 8 9389 6432",
    "sg:postcode":"6009",
    "sg:province":"WA",
    "sg:tags":[
        "away",
        "take"
    ],
    "wof:name":"Nando's Australia",
    "wof:placetype":"venue"
},
  "geometry": {"coordinates":[115.797371,-31.980074],"type":"Point"}
}