{
  "type": "Feature",
  "properties": {
    "iso:country":"AU",
    "sg:address":"37 Kingsley Drv",
    "sg:city":"Kingsley",
    "sg:classifiers":[
        {
            "category":"Health Services",
            "subcategory":"Doctor",
            "type":"Services"
        }
    ],
    "sg:phone":"+61 8 9409 7700",
    "sg:postcode":"6026",
    "sg:province":"WA",
    "sg:tags":[
        "medical",
        "practitioner"
    ],
    "wof:name":"Slusarczyk Carl",
    "wof:placetype":"venue"
},
  "geometry": {"coordinates":[115.787513733,-31.8026866913],"type":"Point"}
}