{
  "type": "Feature",
  "properties": {
    "iso:country":"AU",
    "sg:address":"Airport Rd",
    "sg:city":"Wendouree",
    "sg:classifiers":[
        {
            "category":"Retail",
            "subcategory":"Driving School",
            "type":"Services"
        }
    ],
    "sg:phone":"+61 1300 366 640",
    "sg:postcode":"3355",
    "sg:province":"VIC",
    "wof:name":"Stay Upright Motor Cycle Techniques",
    "wof:placetype":"venue"
},
  "geometry": {"coordinates":[143.803299,-37.517445],"type":"Point"}
}