{
  "type": "Feature",
  "properties": {
    "iso:country":"AU",
    "sg:address":"3/ 271 Harbord Rd",
    "sg:city":"Brookvale",
    "sg:classifiers":[
        {
            "category":"Building & Trades",
            "subcategory":"Construction",
            "type":"Services"
        }
    ],
    "sg:phone":"+61 13 63 60",
    "sg:postcode":"2100",
    "sg:province":"NSW",
    "sg:tags":[
        "window",
        "tinting"
    ],
    "sg:website":"http://www.sol-ace.com.au",
    "wof:name":"Sol Ace",
    "wof:placetype":"venue"
},
  "geometry": {"coordinates":[151.28070068400001,-33.7596511841],"type":"Point"}
}