{
  "type": "Feature",
  "properties": {
    "iso:country":"AU",
    "sg:address":"27 Veronica Ave",
    "sg:city":"Cardiff",
    "sg:classifiers":[
        {
            "category":"Education",
            "subcategory":"Special Training",
            "type":"Public Place"
        }
    ],
    "sg:phone":"+61 2 4956 5680",
    "sg:postcode":"2285",
    "sg:province":"NSW",
    "sg:tags":[
        "tuition-educational"
    ],
    "wof:name":"Clever Kids Education Centres",
    "wof:placetype":"venue"
},
  "geometry": {"coordinates":[151.65931701700001,-32.9391098022],"type":"Point"}
}