{
  "type": "Feature",
  "properties": {
    "addr:full":"57 Kay Ave Lalor VIC 3075",
    "addr:housenumber":"57",
    "addr:postcode":"3075",
    "addr:street":"Kay Ave",
    "iso:country":"AU",
    "sg:address":"57 Kay Ave",
    "sg:city":"Lalor",
    "sg:classifiers":[
        {
            "category":"Retail",
            "subcategory":"Auto Rental",
            "type":"Services"
        }
    ],
    "sg:phone":"+61 3 9402 6232",
    "sg:postcode":"3075",
    "sg:province":"VIC",
    "sg:tags":[
        "chauffeur",
        "car",
        "hire",
        "driven",
        "limousine"
    ],
    "wof:name":"A1 Lavish Limousines",
    "wof:placetype":"venue"
},
  "geometry": {"coordinates":[145.000442505,-37.6592292786],"type":"Point"}
}