{
  "type": "Feature",
  "properties": {
    "iso:country":"AU",
    "sg:address":"50 Aurelian St",
    "sg:city":"Palmyra",
    "sg:classifiers":[
        {
            "category":"Building & Trades",
            "subcategory":"Construction",
            "type":"Services"
        }
    ],
    "sg:phone":"+61 418 906 735",
    "sg:postcode":"6157",
    "sg:province":"WA",
    "sg:tags":[
        "brick",
        "paving"
    ],
    "wof:name":"B & M's Innovative Brickpaving",
    "wof:placetype":"venue"
},
  "geometry": {"coordinates":[115.782242,-32.045727],"type":"Point"}
}