{
  "type": "Feature",
  "properties": {
    "addr:full":"162 Derby St Penrith NSW 2740",
    "addr:housenumber":"162",
    "addr:postcode":"2740",
    "addr:street":"Derby St",
    "iso:country":"AU",
    "sg:address":"162 Derby St",
    "sg:city":"Penrith",
    "sg:classifiers":[
        {
            "category":"Banks & Credit Unions",
            "subcategory":"Financial Services",
            "type":"Services"
        }
    ],
    "sg:phone":"+61 2 4732 3699",
    "sg:postcode":"2740",
    "sg:province":"NSW",
    "sg:tags":[
        "advisory",
        "planning",
        "retirement"
    ],
    "wof:name":"RetireInvest",
    "wof:placetype":"venue"
},
  "geometry": {"coordinates":[150.702652,-33.758865],"type":"Point"}
}