{
  "type": "Feature",
  "properties": {
    "addr:full":"11 Hercules St Tullamarine VIC 3043",
    "addr:housenumber":"11",
    "addr:postcode":"3043",
    "addr:street":"Hercules St",
    "iso:country":"AU",
    "sg:address":"11 Hercules St",
    "sg:city":"Tullamarine",
    "sg:classifiers":[
        {
            "category":"Manufacturing",
            "subcategory":"Tools & Machinery",
            "type":"Manufacturing & Wholesale Goods"
        }
    ],
    "sg:phone":"+61 3 9330 2050",
    "sg:postcode":"3043",
    "sg:province":"VIC",
    "sg:tags":[
        "toolmaker"
    ],
    "wof:name":"CH Tooling & Engineering",
    "wof:placetype":"venue"
},
  "geometry": {"coordinates":[144.87875366200001,-37.6901702881],"type":"Point"}
}