{
  "type": "Feature",
  "properties": {
    "addr:full":"36- 40 Harp St Belmore NSW 2192",
    "addr:housenumber":"40",
    "addr:postcode":"2192",
    "addr:street":"Harp St",
    "iso:country":"AU",
    "sg:address":"36- 40 Harp St",
    "sg:city":"Belmore",
    "sg:classifiers":[
        {
            "category":"Professional",
            "type":"Services"
        }
    ],
    "sg:phone":"+61 2 9704 6666",
    "sg:postcode":"2192",
    "sg:province":"NSW",
    "sg:tags":[
        "valuer"
    ],
    "wof:name":"Pickles Auctions Pty Ltd",
    "wof:placetype":"venue"
},
  "geometry": {"coordinates":[151.09918200000001,-33.925121],"type":"Point"}
}