{
  "type": "Feature",
  "properties": {
    "iso:country":"AU",
    "sg:address":"127 Nott St",
    "sg:city":"Port Melbourne",
    "sg:classifiers":[
        {
            "category":"Education",
            "subcategory":"School",
            "type":"Public Place"
        }
    ],
    "sg:phone":"+61 3 9646 0855",
    "sg:postcode":"3207",
    "sg:province":"VIC",
    "wof:name":"Port Phillip Specialist School",
    "wof:placetype":"venue"
},
  "geometry": {"coordinates":[144.940887,-37.83849],"type":"Point"}
}