{
  "type": "Feature",
  "properties": {
    "iso:country":"AU",
    "sg:address":"1/ 472 Mulgrave Rd",
    "sg:city":"Cairns",
    "sg:classifiers":[
        {
            "category":"Banks & Credit Unions",
            "subcategory":"Investment Brokerage",
            "type":"Services"
        }
    ],
    "sg:phone":"+61 7 4033 6944",
    "sg:postcode":"4870",
    "sg:province":"QLD",
    "sg:tags":[
        "broker"
    ],
    "wof:name":"Bizbrokers (Aust) Pty Ltd",
    "wof:placetype":"venue"
},
  "geometry": {"coordinates":[145.74110412600001,-16.9409656525],"type":"Point"}
}