{
  "type": "Feature",
  "properties": {
    "addr:full":"255a Springvale Rd Glen Waverley VIC 3150",
    "addr:housenumber":"255a",
    "addr:postcode":"3150",
    "addr:street":"Springvale Rd",
    "iso:country":"AU",
    "sg:address":"255a Springvale Rd",
    "sg:city":"Glen Waverley",
    "sg:classifiers":[
        {
            "category":"Wholesale",
            "subcategory":"Medical Equipment & Supplies",
            "type":"Manufacturing & Wholesale Goods"
        }
    ],
    "sg:phone":"+61 3 9886 8799",
    "sg:postcode":"3150",
    "sg:province":"VIC",
    "sg:tags":[
        "aids",
        "hearing"
    ],
    "wof:name":"AudioClinic",
    "wof:placetype":"venue"
},
  "geometry": {"coordinates":[145.165725708,-37.8789520264],"type":"Point"}
}