{
  "type": "Feature",
  "properties": {
    "addr:full":"107 Tangerine St Villawood NSW 2163",
    "addr:housenumber":"107",
    "addr:postcode":"2163",
    "addr:street":"Tangerine St",
    "iso:country":"AU",
    "sg:address":"107 Tangerine St",
    "sg:city":"Villawood",
    "sg:classifiers":[
        {
            "category":"Food & Beverages",
            "subcategory":"Supermarket",
            "type":"Retail Goods"
        }
    ],
    "sg:phone":"+61 2 9724 2161",
    "sg:postcode":"2163",
    "sg:province":"NSW",
    "sg:tags":[
        "grocery",
        "store"
    ],
    "wof:name":"Food Stop",
    "wof:placetype":"venue"
},
  "geometry": {"coordinates":[150.968017578,-33.8764648438],"type":"Point"}
}