{
  "type": "Feature",
  "properties": {
    "addr:full":"8/ 36 Trout St Ashgrove QLD 4060",
    "addr:housenumber":"/ 36",
    "addr:postcode":"4060",
    "addr:street":"Trout St",
    "iso:country":"AU",
    "sg:address":"8/ 36 Trout St",
    "sg:city":"Ashgrove",
    "sg:classifiers":[
        {
            "category":"Government",
            "subcategory":"Post Office",
            "type":"Public Place"
        }
    ],
    "sg:phone":"+61 7 3366 3033",
    "sg:postcode":"4060",
    "sg:province":"QLD",
    "sg:tags":[
        "yoga"
    ],
    "wof:name":"Satyananda Yoga",
    "wof:placetype":"venue"
},
  "geometry": {"coordinates":[152.992095947,-27.4473819733],"type":"Point"}
}