{
  "type": "Feature",
  "properties": {
    "iso:country":"AU",
    "sg:address":"Queen St",
    "sg:city":"Brisbane",
    "sg:classifiers":[
        {
            "category":"Retail",
            "subcategory":"Event Space",
            "type":"Services"
        }
    ],
    "sg:phone":"+61 7 3306 8888",
    "sg:postcode":"4000",
    "sg:province":"QLD",
    "sg:tags":[
        "venue",
        "reception",
        "wedding"
    ],
    "sg:website":"http://www.conradtreasury.com.au",
    "wof:name":"Conrad Treasury",
    "wof:placetype":"venue"
},
  "geometry": {"coordinates":[153.02607727,-27.4689922333],"type":"Point"}
}