{
  "type": "Feature",
  "properties": {
    "iso:country":"AU",
    "sg:address":"17 Tumbare St",
    "sg:city":"Atherton",
    "sg:classifiers":[
        {
            "category":"Building & Trades",
            "subcategory":"Construction",
            "type":"Services"
        }
    ],
    "sg:phone":"+61 7 4091 1892",
    "sg:postcode":"4883",
    "sg:province":"QLD",
    "sg:tags":[
        "contractor"
    ],
    "wof:name":"Feeney C T & M J",
    "wof:placetype":"venue"
},
  "geometry": {"coordinates":[145.475067139,-17.2752590179],"type":"Point"}
}