{
  "type": "Feature",
  "properties": {
    "addr:full":"32 Henty St Casterton VIC 3311",
    "addr:housenumber":"32",
    "addr:postcode":"3311",
    "addr:street":"Henty St",
    "iso:country":"AU",
    "sg:address":"32 Henty St",
    "sg:city":"Casterton",
    "sg:classifiers":[
        {
            "category":"Health Services",
            "subcategory":"Doctor",
            "type":"Services"
        }
    ],
    "sg:phone":"+61 3 5581 1611",
    "sg:postcode":"3311",
    "sg:province":"VIC",
    "sg:tags":[
        "medical",
        "practitioner"
    ],
    "wof:name":"MacGibbon P.A. Dr",
    "wof:placetype":"venue"
},
  "geometry": {"coordinates":[141.40672302199999,-37.5836524963],"type":"Point"}
}