{
  "type": "Feature",
  "properties": {
    "addr:full":"255 Maroubra Rd Maroubra NSW 2035",
    "addr:housenumber":"255",
    "addr:postcode":"2035",
    "addr:street":"Maroubra Rd",
    "iso:country":"AU",
    "sg:address":"255 Maroubra Rd",
    "sg:city":"Maroubra",
    "sg:classifiers":[
        {
            "category":"Health Services",
            "subcategory":"Doctor",
            "type":"Services"
        }
    ],
    "sg:phone":"+61 2 9349 4756",
    "sg:postcode":"2035",
    "sg:province":"NSW",
    "sg:tags":[
        "medical",
        "practitioner"
    ],
    "wof:name":"Berdoukas G A",
    "wof:placetype":"venue"
},
  "geometry": {"coordinates":[151.24200439399999,-33.9420471191],"type":"Point"}
}