{
  "type": "Feature",
  "properties": {
    "addr:full":"PO Box 922 Ulladulla NSW 2539",
    "addr:postcode":"2539",
    "iso:country":"AU",
    "sg:address":"PO Box 922",
    "sg:city":"Ulladulla",
    "sg:classifiers":[
        {
            "category":"Shopping",
            "subcategory":"Clothing, Apparel, & Fashions",
            "type":"Retail Goods"
        }
    ],
    "sg:phone":"+61 2 4454 4870",
    "sg:postcode":"2539",
    "sg:province":"NSW",
    "sg:tags":[
        "accessory"
    ],
    "wof:name":"Pink Parties",
    "wof:placetype":"venue"
},
  "geometry": {"coordinates":[150.475631714,-35.3509788513],"type":"Point"}
}