{
  "type": "Feature",
  "properties": {
    "iso:country":"AU",
    "sg:address":"Sundown Rd",
    "sg:city":"Sundown",
    "sg:classifiers":[
        {
            "category":"Farming",
            "subcategory":"Farm",
            "type":"Manufacturing & Wholesale Goods"
        }
    ],
    "sg:phone":"+61 7 4061 2030",
    "sg:postcode":"4872",
    "sg:province":"QLD",
    "sg:tags":[
        "farmer"
    ],
    "wof:name":"Austin E A",
    "wof:placetype":"venue"
},
  "geometry": {"coordinates":[144.947097778,-17.7964038849],"type":"Point"}
}