{
  "type": "Feature",
  "properties": {
    "iso:country":"AU",
    "sg:address":"3 Angas St",
    "sg:city":"Port Lincoln",
    "sg:classifiers":[
        {
            "category":"Real Estate",
            "subcategory":"Surveying",
            "type":"Services"
        }
    ],
    "sg:phone":"+61 8 8682 6632",
    "sg:postcode":"5606",
    "sg:province":"SA",
    "sg:tags":[
        "surveyor",
        "land"
    ],
    "wof:name":"Dansie P A & Associates Pty Ltd",
    "wof:placetype":"venue"
},
  "geometry": {"coordinates":[135.850159,-34.709625],"type":"Point"}
}