{
  "type": "Feature",
  "properties": {
    "addr:full":"9 Mitchell Rd Lilydale VIC 3140",
    "addr:housenumber":"9",
    "addr:postcode":"3140",
    "addr:street":"Mitchell Rd",
    "iso:country":"AU",
    "sg:address":"9 Mitchell Rd",
    "sg:city":"Lilydale",
    "sg:classifiers":[
        {
            "category":"Utilities",
            "type":"Services"
        }
    ],
    "sg:phone":"+61 412 531 821",
    "sg:postcode":"3140",
    "sg:province":"VIC",
    "sg:tags":[
        "refrigeration",
        "industrial",
        "commercial",
        "retail"
    ],
    "wof:name":"John's Refrigeration & Air Conditioning",
    "wof:placetype":"venue"
},
  "geometry": {"coordinates":[145.37135314899999,-37.7693557739],"type":"Point"}
}