{
  "type": "Feature",
  "properties": {
    "addr:full":"Shop 12/ 106 Sydney Rd Brunswick VIC 3056",
    "addr:housenumber":"shop 12 / 106",
    "addr:postcode":"3056",
    "addr:street":"Sydney Rd",
    "iso:country":"AU",
    "sg:address":"Shop 12/ 106 Sydney Rd",
    "sg:city":"Brunswick",
    "sg:classifiers":[
        {
            "category":"Shopping",
            "subcategory":"Jewelry",
            "type":"Retail Goods"
        }
    ],
    "sg:phone":"+61 3 9388 1329",
    "sg:postcode":"3056",
    "sg:province":"VIC",
    "sg:tags":[
        "jeweller"
    ],
    "wof:name":"Ritzy Fine Jewellery",
    "wof:placetype":"venue"
},
  "geometry": {"coordinates":[144.96087646500001,-37.7754707336],"type":"Point"}
}