{
  "type": "Feature",
  "properties": {
    "addr:full":"86 Albert St Preston VIC 3072",
    "addr:housenumber":"86",
    "addr:postcode":"3072",
    "addr:street":"Albert St",
    "iso:country":"AU",
    "sg:address":"86 Albert St",
    "sg:city":"Preston",
    "sg:classifiers":[
        {
            "category":"Farming",
            "subcategory":"Orchard",
            "type":"Manufacturing & Wholesale Goods"
        }
    ],
    "sg:phone":"+61 3 9470 6084",
    "sg:postcode":"3072",
    "sg:province":"VIC",
    "sg:tags":[
        "wholesaler",
        "jean",
        "mfrs"
    ],
    "wof:name":"Jeanworks",
    "wof:placetype":"venue"
},
  "geometry": {"coordinates":[145.022705078,-37.7429733276],"type":"Point"}
}