{
  "type": "Feature",
  "properties": {
    "iso:country":"AU",
    "sg:address":"67 Doonside Crs",
    "sg:city":"Blacktown",
    "sg:classifiers":[
        {
            "category":"Professional",
            "type":"Services"
        }
    ],
    "sg:phone":"+61 2 9621 5565",
    "sg:postcode":"2148",
    "sg:province":"NSW",
    "sg:tags":[
        "transport"
    ],
    "wof:name":"Francrane",
    "wof:placetype":"venue"
},
  "geometry": {"coordinates":[150.87283325199999,-33.7815666199],"type":"Point"}
}