{
  "type": "Feature",
  "properties": {
    "iso:country":"AU",
    "sg:address":"Unit C9, 15",
    "sg:city":"Narabang Way Belrose",
    "sg:classifiers":[
        {
            "category":"Wholesale",
            "subcategory":"Medical Equipment & Supplies",
            "type":"Manufacturing & Wholesale Goods"
        }
    ],
    "sg:phone":"+61 2 9986 1001",
    "sg:postcode":"2085",
    "sg:province":"NSW",
    "sg:tags":[
        "dental"
    ],
    "wof:name":"Medical Imaging Technologies Pty Ltd",
    "wof:placetype":"venue"
},
  "geometry": {"coordinates":[151.212432861,-33.7053451538],"type":"Point"}
}