{
  "type": "Feature",
  "properties": {
    "iso:country":"AU",
    "sg:address":"53 Huon Creek Rd",
    "sg:city":"Wodonga",
    "sg:classifiers":[
        {
            "category":"Farming",
            "subcategory":"Farm & Veterinary Services",
            "type":"Manufacturing & Wholesale Goods"
        }
    ],
    "sg:phone":"+61 419 125 449",
    "sg:postcode":"3690",
    "sg:province":"VIC",
    "sg:tags":[
        "irrigation",
        "reticulation",
        "system"
    ],
    "wof:name":"Heritage Irrigation",
    "wof:placetype":"venue"
},
  "geometry": {"coordinates":[146.89125060999999,-36.1147155762],"type":"Point"}
}