{
  "type": "Feature",
  "properties": {
    "iso:country":"AU",
    "sg:address":"Cnr Brunswick & Merthyr Rds",
    "sg:city":"New Farm",
    "sg:classifiers":[
        {
            "category":"Health Services",
            "subcategory":"Optometrist",
            "type":"Services"
        }
    ],
    "sg:phone":"+61 7 3358 6566",
    "sg:postcode":"4005",
    "sg:province":"QLD",
    "wof:name":"Brunswick Optical",
    "wof:placetype":"venue"
},
  "geometry": {"coordinates":[153.04612731899999,-27.4671821594],"type":"Point"}
}