{
  "type": "Feature",
  "properties": {
    "addr:full":"Cnr High & Cooper St Epping VIC 3076",
    "addr:postcode":"3076",
    "addr:street":"St",
    "iso:country":"AU",
    "sg:address":"Cnr High & Cooper St",
    "sg:city":"Epping",
    "sg:classifiers":[
        {
            "category":"Health Services",
            "subcategory":"Health Practitioner",
            "type":"Services"
        }
    ],
    "sg:phone":"+61 3 9401 1999",
    "sg:postcode":"3076",
    "sg:province":"VIC",
    "sg:tags":[
        "physiotherapist"
    ],
    "wof:name":"Backfocus Physiotherapy",
    "wof:placetype":"venue"
},
  "geometry": {"coordinates":[145.009490967,-37.6383590698],"type":"Point"}
}