{
  "type": "Feature",
  "properties": {
    "addr:full":"28 Traline Rd Glass House Mountains QLD 4518",
    "addr:housenumber":"28",
    "addr:postcode":"4518",
    "addr:street":"Traline Rd",
    "iso:country":"AU",
    "sg:address":"28 Traline Rd",
    "sg:city":"Glass House Mountains",
    "sg:classifiers":[
        {
            "category":"Social Services",
            "subcategory":"Job Training",
            "type":"Services"
        }
    ],
    "sg:phone":"+61 7 5496 9597",
    "sg:postcode":"4518",
    "sg:province":"QLD",
    "sg:tags":[
        "goldsmith",
        "silversmith"
    ],
    "wof:name":"C.W. Bannan Gold & Silversmith",
    "wof:placetype":"venue"
},
  "geometry": {"coordinates":[152.96531677199999,-26.907907486],"type":"Point"}
}