{
  "type": "Feature",
  "properties": {
    "addr:full":"61 Lang St Padstow NSW 2211",
    "addr:housenumber":"61",
    "addr:postcode":"2211",
    "addr:street":"Lang St",
    "iso:country":"AU",
    "sg:address":"61 Lang St",
    "sg:city":"Padstow",
    "sg:classifiers":[
        {
            "category":"Home & Garden",
            "subcategory":"Carpets & Floor Coverings",
            "type":"Retail Goods"
        }
    ],
    "sg:phone":"+61 1300 887 349",
    "sg:postcode":"2211",
    "sg:province":"NSW",
    "sg:tags":[
        "material",
        "waterproofing"
    ],
    "sg:website":"http://www.waterproofingstuff.com",
    "wof:name":"Waterproofing Stuff",
    "wof:placetype":"venue"
},
  "geometry": {"coordinates":[151.02522300000001,-33.962662],"type":"Point"}
}