{
  "type": "Feature",
  "properties": {
    "iso:country":"AU",
    "sg:address":"98 C Muller Rd",
    "sg:city":"Hampstead Gardens",
    "sg:classifiers":[
        {
            "category":"Retail",
            "subcategory":"Auto Repair",
            "type":"Services"
        }
    ],
    "sg:phone":"+61 8 8261 1888",
    "sg:postcode":"5086",
    "sg:province":"SA",
    "sg:tags":[
        "bus",
        "truck"
    ],
    "wof:name":"Fisher Performance",
    "wof:placetype":"venue"
},
  "geometry": {"coordinates":[138.6300354,-34.8714866638],"type":"Point"}
}