{
  "type": "Feature",
  "properties": {
    "addr:full":"McCallum St Swan Hill VIC 3585",
    "addr:postcode":"3585",
    "addr:street":"Mccallum St",
    "iso:country":"AU",
    "sg:address":"McCallum St",
    "sg:city":"Swan Hill",
    "sg:classifiers":[
        {
            "category":"Organizations",
            "subcategory":"Professional Association",
            "type":"Services"
        }
    ],
    "sg:phone":"+61 3 5032 4314",
    "sg:postcode":"3585",
    "sg:province":"VIC",
    "sg:tags":[
        "rural",
        "organisation",
        "production",
        "primary"
    ],
    "wof:name":"Swan Hill Show Society",
    "wof:placetype":"venue"
},
  "geometry": {"coordinates":[143.56024199999999,-35.338577],"type":"Point"}
}