{
  "type": "Feature",
  "properties": {
    "iso:country":"AU",
    "sg:address":"Meath Ave",
    "sg:city":"Taroona",
    "sg:classifiers":[
        {
            "category":"Education",
            "subcategory":"School",
            "type":"Public Place"
        }
    ],
    "sg:phone":"+61 3 6227 7700",
    "sg:postcode":"7053",
    "sg:province":"TAS",
    "sg:tags":[
        "state",
        "except",
        "nsw"
    ],
    "wof:name":"Taroona High School",
    "wof:placetype":"venue"
},
  "geometry": {"coordinates":[147.352936,-42.94458],"type":"Point"}
}