{
  "type": "Feature",
  "properties": {
    "addr:full":"74 Erskine Rd Macleod VIC 3085",
    "addr:housenumber":"74",
    "addr:postcode":"3085",
    "addr:street":"Erskine Rd",
    "iso:country":"AU",
    "sg:address":"74 Erskine Rd",
    "sg:city":"Macleod",
    "sg:classifiers":[
        {
            "category":"Real Estate",
            "subcategory":"Architect",
            "type":"Services"
        }
    ],
    "sg:phone":"+61 438 170 187",
    "sg:postcode":"3085",
    "sg:province":"VIC",
    "sg:tags":[
        "building",
        "designer"
    ],
    "wof:name":"AR Constructions Pty Ltd",
    "wof:placetype":"venue"
},
  "geometry": {"coordinates":[145.07244873100001,-37.7281570435],"type":"Point"}
}