{
  "type": "Feature",
  "properties": {
    "addr:full":"83 Cowper St Granville NSW 2142",
    "addr:housenumber":"83",
    "addr:postcode":"2142",
    "addr:street":"Cowper St",
    "iso:country":"AU",
    "sg:address":"83 Cowper St",
    "sg:city":"Granville",
    "sg:classifiers":[
        {
            "category":"Food & Beverages",
            "subcategory":"Bakery",
            "type":"Retail Goods"
        }
    ],
    "sg:phone":"+61 2 9682 3763",
    "sg:postcode":"2142",
    "sg:province":"NSW",
    "sg:tags":[
        "baker"
    ],
    "wof:name":"Granville Lebanese Bread",
    "wof:placetype":"venue"
},
  "geometry": {"coordinates":[151.00979614299999,-33.8304138184],"type":"Point"}
}