{
  "type": "Feature",
  "properties": {
    "addr:full":"26 Argyle Ave Anna Bay NSW 2316",
    "addr:housenumber":"26",
    "addr:postcode":"2316",
    "addr:street":"Argyle Ave Anna Bay",
    "iso:country":"AU",
    "sg:address":"26 Argyle Ave",
    "sg:city":"Anna Bay",
    "sg:classifiers":[
        {
            "category":"Utilities",
            "subcategory":"Electric",
            "type":"Services"
        }
    ],
    "sg:phone":"+61 2 4982 1838",
    "sg:postcode":"2316",
    "sg:province":"NSW",
    "sg:tags":[
        "electrical",
        "contractor"
    ],
    "wof:name":"Marlen Electrics",
    "wof:placetype":"venue"
},
  "geometry": {"coordinates":[152.08380099999999,-32.78442],"type":"Point"}
}