{
  "type": "Feature",
  "properties": {
    "addr:full":"Shop 11 Woodcroft Drv Woodcroft NSW 2767",
    "addr:housenumber":"shop 11",
    "addr:postcode":"2767",
    "addr:street":"Woodcroft Drv",
    "iso:country":"AU",
    "sg:address":"Shop 11 Woodcroft Drv",
    "sg:city":"Woodcroft",
    "sg:classifiers":[
        {
            "category":"Health Services",
            "subcategory":"Dentist",
            "type":"Services"
        }
    ],
    "sg:phone":"+61 2 9621 3088",
    "sg:postcode":"2767",
    "sg:province":"NSW",
    "wof:name":"Woodcroft Dental Centre",
    "wof:placetype":"venue"
},
  "geometry": {"coordinates":[150.87864685100001,-33.7499656677],"type":"Point"}
}