{
  "type": "Feature",
  "properties": {
    "addr:full":"323 Blackburn Rd Burwood East VIC 3151",
    "addr:housenumber":"323",
    "addr:postcode":"3151",
    "addr:street":"Blackburn Rd",
    "iso:country":"AU",
    "sg:address":"323 Blackburn Rd",
    "sg:city":"Burwood East",
    "sg:classifiers":[
        {
            "category":"Health Services",
            "subcategory":"Health Practitioner",
            "type":"Services"
        }
    ],
    "sg:phone":"+61 3 9803 6323",
    "sg:postcode":"3151",
    "sg:province":"VIC",
    "sg:tags":[
        "psychologist"
    ],
    "wof:name":"Psychrespect",
    "wof:placetype":"venue"
},
  "geometry": {"coordinates":[145.15284729000001,-37.8494377136],"type":"Point"}
}