{
  "type": "Feature",
  "properties": {
    "iso:country":"AU",
    "sg:address":"11 Nandewar Drv",
    "sg:city":"Buderim",
    "sg:classifiers":[
        {
            "category":"Utilities",
            "subcategory":"Electric",
            "type":"Services"
        }
    ],
    "sg:phone":"+61 411 347 572",
    "sg:postcode":"4556",
    "sg:province":"QLD",
    "sg:tags":[
        "electrical",
        "contractor"
    ],
    "wof:name":"Allcoast Electrical & Antenna Services",
    "wof:placetype":"venue"
},
  "geometry": {"coordinates":[153.070587158,-26.697681427],"type":"Point"}
}