{
  "type": "Feature",
  "properties": {
    "addr:full":"41 Rene St Noosaville QLD 4566",
    "addr:housenumber":"41",
    "addr:postcode":"4566",
    "addr:street":"Rene St",
    "iso:country":"AU",
    "sg:address":"41 Rene St",
    "sg:city":"Noosaville",
    "sg:classifiers":[
        {
            "category":"Manufacturing",
            "subcategory":"Metals",
            "type":"Manufacturing & Wholesale Goods"
        }
    ],
    "sg:phone":"+61 7 5449 7277",
    "sg:postcode":"4566",
    "sg:province":"QLD",
    "sg:tags":[
        "steel",
        "fabricator",
        "mfrs"
    ],
    "wof:name":"Haines Engineering",
    "wof:placetype":"venue"
},
  "geometry": {"coordinates":[153.04225158700001,-26.4153499603],"type":"Point"}
}