{
  "type": "Feature",
  "properties": {
    "iso:country":"AU",
    "sg:address":"Wilson Pde",
    "sg:city":"Heathcote",
    "sg:classifiers":[
        {
            "category":"Education",
            "subcategory":"School",
            "type":"Public Place"
        }
    ],
    "sg:phone":"+61 2 9520 9488",
    "sg:postcode":"2233",
    "sg:province":"NSW",
    "sg:tags":[
        "state",
        "-",
        "nsw"
    ],
    "wof:name":"Heathcote High School",
    "wof:placetype":"venue"
},
  "geometry": {"coordinates":[151.01187133799999,-34.0832252502],"type":"Point"}
}