{
  "type": "Feature",
  "properties": {
    "addr:full":"Unit 2, 26-28 Loganlea Rd Waterford QLD 4133",
    "addr:housenumber":"26-28",
    "addr:postcode":"4133",
    "addr:street":"Loganlea Rd",
    "iso:country":"AU",
    "sg:address":"Unit 2, 26-28 Loganlea Rd",
    "sg:city":"Waterford",
    "sg:classifiers":[
        {
            "category":"Shopping",
            "subcategory":"Crafts & Fabrics",
            "type":"Retail Goods"
        }
    ],
    "sg:phone":"+61 7 3805 7355",
    "sg:postcode":"4133",
    "sg:province":"QLD",
    "sg:tags":[
        "supply"
    ],
    "wof:name":"Stampers And Scapbookers Wonderland",
    "wof:placetype":"venue"
},
  "geometry": {"coordinates":[153.13612365700001,-27.6915569305],"type":"Point"}
}