{
  "type": "Feature",
  "properties": {
    "addr:full":"5 Dyer Crs Gosford West NSW 2250",
    "addr:housenumber":"5",
    "addr:postcode":"2250",
    "addr:street":"Dyer Crs",
    "iso:country":"AU",
    "sg:address":"5 Dyer Crs",
    "sg:city":"Gosford West",
    "sg:classifiers":[
        {
            "category":"Home & Garden",
            "subcategory":"Building Materials",
            "type":"Retail Goods"
        }
    ],
    "sg:phone":"+61 2 4323 1411",
    "sg:postcode":"2250",
    "sg:province":"NSW",
    "sg:tags":[
        "fencing"
    ],
    "wof:name":"Log Factory The",
    "wof:placetype":"venue"
},
  "geometry": {"coordinates":[151.32734680199999,-33.4264717102],"type":"Point"}
}