{
  "type": "Feature",
  "properties": {
    "iso:country":"AU",
    "sg:address":"41 Wyong St",
    "sg:city":"Keilor East",
    "sg:classifiers":[
        {
            "category":"Fast Food",
            "type":"Food & Drink"
        }
    ],
    "sg:phone":"+61 3 9331 5337",
    "sg:postcode":"3033",
    "sg:province":"VIC",
    "sg:tags":[
        "away",
        "take"
    ],
    "wof:name":"Centre Way BBQ Chicken",
    "wof:placetype":"venue"
},
  "geometry": {"coordinates":[144.866013,-37.732956],"type":"Point"}
}