{
  "type": "Feature",
  "properties": {
    "iso:country":"AU",
    "sg:address":"6/ 331 Hope Island Rd",
    "sg:city":"Hope Island",
    "sg:classifiers":[
        {
            "category":"Restaurant",
            "type":"Food & Drink"
        }
    ],
    "sg:phone":"+61 7 5514 0455",
    "sg:postcode":"4212",
    "sg:province":"QLD",
    "wof:name":"Department Dining",
    "wof:placetype":"venue"
},
  "geometry": {"coordinates":[153.33981323200001,-27.8768596649],"type":"Point"}
}