{
  "type": "Feature",
  "properties": {
    "iso:country":"AU",
    "sg:address":"20 Valley Rd",
    "sg:city":"Devonport",
    "sg:classifiers":[
        {
            "category":"Restaurant",
            "type":"Food & Drink"
        }
    ],
    "sg:phone":"+61 3 6421 5557",
    "sg:postcode":"7310",
    "sg:province":"TAS",
    "wof:name":"Drysdale Restaurant",
    "wof:placetype":"venue"
},
  "geometry": {"coordinates":[146.344406128,-41.1865119934],"type":"Point"}
}