{
  "type": "Feature",
  "properties": {
    "addr:full":"14 Hilly St Mortlake NSW 2137",
    "addr:housenumber":"14",
    "addr:postcode":"2137",
    "addr:street":"Hilly St",
    "iso:country":"AU",
    "sg:address":"14 Hilly St",
    "sg:city":"Mortlake",
    "sg:classifiers":[
        {
            "category":"Wholesale",
            "subcategory":"Machinery & Supplies",
            "type":"Manufacturing & Wholesale Goods"
        }
    ],
    "sg:phone":"+61 2 9736 1320",
    "sg:postcode":"2137",
    "sg:province":"NSW",
    "sg:tags":[
        "instrument",
        "scientific"
    ],
    "wof:name":"Corbett Research",
    "wof:placetype":"venue"
},
  "geometry": {"coordinates":[151.10580444300001,-33.8394470215],"type":"Point"}
}