{
  "type": "Feature",
  "properties": {
    "iso:country":"AU",
    "sg:address":"Greenwood La",
    "sg:city":"Singleton",
    "sg:classifiers":[
        {
            "category":"Farming",
            "subcategory":"Farm",
            "type":"Manufacturing & Wholesale Goods"
        }
    ],
    "sg:phone":"+61 2 6572 1180",
    "sg:postcode":"2330",
    "sg:province":"NSW",
    "sg:tags":[
        "farmer"
    ],
    "wof:name":"Stacey R R & Son Pty Ltd",
    "wof:placetype":"venue"
},
  "geometry": {"coordinates":[151.18206799999999,-32.571552],"type":"Point"}
}