{
  "type": "Feature",
  "properties": {
    "addr:full":"33 King William St Adelaide SA 5000",
    "addr:housenumber":"33",
    "addr:postcode":"5000",
    "addr:street":"King William St",
    "iso:country":"AU",
    "sg:address":"33 King William St",
    "sg:city":"Adelaide",
    "sg:classifiers":[
        {
            "category":"Professional",
            "subcategory":"Engineering",
            "type":"Services"
        }
    ],
    "sg:phone":"+61 8 8424 3800",
    "sg:postcode":"5000",
    "sg:province":"SA",
    "sg:tags":[
        "consulting",
        "engineer"
    ],
    "wof:name":"SKM",
    "wof:placetype":"venue"
},
  "geometry": {"coordinates":[138.59922790499999,-34.9228057861],"type":"Point"}
}