{
  "type": "Feature",
  "properties": {
    "iso:country":"AU",
    "sg:address":"3/19- 21",
    "sg:city":"Swift Way Dandenong",
    "sg:classifiers":[
        {
            "category":"Landmark",
            "subcategory":"City Walls",
            "type":"Public Place"
        }
    ],
    "sg:phone":"+61 3 9706 4079",
    "sg:postcode":"3175",
    "sg:province":"VIC",
    "sg:tags":[
        "facing",
        "hard"
    ],
    "wof:name":"Tungsten Hardfacing Pty Ltd",
    "wof:placetype":"venue"
},
  "geometry": {"coordinates":[145.206542969,-38.0341033936],"type":"Point"}
}