{
  "type": "Feature",
  "properties": {
    "iso:country":"AU",
    "sg:address":"17 Lemnos St",
    "sg:city":"Shenton Park",
    "sg:classifiers":[
        {
            "category":"Health Services",
            "subcategory":"Health Practitioner",
            "type":"Services"
        }
    ],
    "sg:phone":"+61 8 9382 2663",
    "sg:postcode":"6008",
    "sg:province":"WA",
    "sg:tags":[
        "physiotherapist"
    ],
    "wof:name":"On The Go Physio",
    "wof:placetype":"venue"
},
  "geometry": {"coordinates":[115.799156189,-31.9570541382],"type":"Point"}
}