{
  "type": "Feature",
  "properties": {
    "addr:full":"28 Stanfield Drv null QLD 4210",
    "addr:housenumber":"28",
    "addr:postcode":"4210",
    "addr:street":"Stanfield Drv",
    "iso:country":"AU",
    "sg:address":"28 Stanfield Drv",
    "sg:city":"null",
    "sg:classifiers":[
        {
            "category":"Professional",
            "subcategory":"Employment Agencies",
            "type":"Services"
        }
    ],
    "sg:phone":"+61 408 283 305",
    "sg:postcode":"4210",
    "sg:province":"QLD",
    "sg:tags":[
        "entertainer",
        "agent"
    ],
    "wof:name":"Danielle Goullet",
    "wof:placetype":"venue"
},
  "geometry": {"coordinates":[153.28135681099999,-27.8986759186],"type":"Point"}
}