{
  "type": "Feature",
  "properties": {
    "iso:country":"AU",
    "sg:address":"470 Goodwood Rd",
    "sg:city":"Cumberland Park",
    "sg:classifiers":[
        {
            "category":"Health Services",
            "subcategory":"Doctor",
            "type":"Services"
        }
    ],
    "sg:phone":"+61 8 8272 6666",
    "sg:postcode":"5041",
    "sg:province":"SA",
    "sg:tags":[
        "medical",
        "practitioner"
    ],
    "wof:name":"Hand Injury Clinic The",
    "wof:placetype":"venue"
},
  "geometry": {"coordinates":[138.591293,-34.974895],"type":"Point"}
}