{
  "type": "Feature",
  "properties": {
    "addr:full":"Ellen St Penola SA 5277",
    "addr:postcode":"5277",
    "addr:street":"Ellen St",
    "iso:country":"AU",
    "sg:address":"Ellen St",
    "sg:city":"Penola",
    "sg:classifiers":[
        {
            "category":"Professional",
            "subcategory":"Engineering",
            "type":"Services"
        }
    ],
    "sg:phone":"+61 8 8737 3470",
    "sg:postcode":"5277",
    "sg:province":"SA",
    "sg:tags":[
        "engineer"
    ],
    "wof:name":"L T & J M Wilson",
    "wof:placetype":"venue"
},
  "geometry": {"coordinates":[140.83114599999999,-37.373791],"type":"Point"}
}