{
  "type": "Feature",
  "properties": {
    "iso:country":"AU",
    "sg:address":"35 Crows Rd",
    "sg:city":"Belmont",
    "sg:classifiers":[
        {
            "category":"Manufacturing",
            "subcategory":"Tools & Machinery",
            "type":"Manufacturing & Wholesale Goods"
        }
    ],
    "sg:phone":"+61 3 5244 0008",
    "sg:postcode":"3216",
    "sg:province":"VIC",
    "sg:tags":[
        "earth",
        "excavating",
        "moving",
        "equipment"
    ],
    "wof:name":"Brad Drew Trucks Pty Ltd",
    "wof:placetype":"venue"
},
  "geometry": {"coordinates":[144.35403442399999,-38.1844825745],"type":"Point"}
}