{
  "type": "Feature",
  "properties": {
    "addr:full":"39 High St Oatlands TAS 7120",
    "addr:housenumber":"39",
    "addr:postcode":"7120",
    "addr:street":"High St",
    "iso:country":"AU",
    "sg:address":"39 High St",
    "sg:city":"Oatlands",
    "sg:classifiers":[
        {
            "category":"Retail",
            "subcategory":"Veterinary Services",
            "type":"Services"
        }
    ],
    "sg:phone":"+61 3 6254 0006",
    "sg:postcode":"7120",
    "sg:province":"TAS",
    "sg:tags":[
        "surgeon"
    ],
    "wof:name":"Oatlands Veterinary Clinic",
    "wof:placetype":"venue"
},
  "geometry": {"coordinates":[147.36799621599999,-42.3023948669],"type":"Point"}
}