{
  "type": "Feature",
  "properties": {
    "addr:full":"111 Avoca Drv Kincumber NSW 2251",
    "addr:housenumber":"111",
    "addr:postcode":"2251",
    "addr:street":"Avoca Drv",
    "iso:country":"AU",
    "sg:address":"111 Avoca Drv",
    "sg:city":"Kincumber",
    "sg:classifiers":[
        {
            "category":"Personal",
            "subcategory":"Barber",
            "type":"Services"
        }
    ],
    "sg:phone":"+61 2 4369 6135",
    "sg:postcode":"2251",
    "sg:province":"NSW",
    "wof:name":"Barber & Brew",
    "wof:placetype":"venue"
},
  "geometry": {"coordinates":[151.388595581,-33.4686546326],"type":"Point"}
}