{
  "type": "Feature",
  "properties": {
    "addr:full":"20 Park Rd Garden Suburb NSW 2289",
    "addr:housenumber":"20",
    "addr:postcode":"2289",
    "addr:street":"Park Rd",
    "iso:country":"AU",
    "sg:address":"20 Park Rd",
    "sg:city":"Garden Suburb",
    "sg:classifiers":[
        {
            "category":"Real Estate",
            "subcategory":"Architect",
            "type":"Services"
        }
    ],
    "sg:phone":"+61 2 4920 6624",
    "sg:postcode":"2289",
    "sg:province":"NSW",
    "sg:tags":[
        "building",
        "designer"
    ],
    "wof:name":"Garman Design",
    "wof:placetype":"venue"
},
  "geometry": {"coordinates":[151.67965698200001,-32.9423217773],"type":"Point"}
}