{
  "type": "Feature",
  "properties": {
    "iso:country":"AU",
    "sg:address":"85 Commercial St",
    "sg:city":"Walla Walla",
    "sg:classifiers":[
        {
            "category":"Fast Food",
            "type":"Food & Drink"
        }
    ],
    "sg:phone":"+61 2 6029 2259",
    "sg:postcode":"2659",
    "sg:province":"NSW",
    "sg:tags":[
        "away",
        "take"
    ],
    "wof:name":"Billabong Cafe",
    "wof:placetype":"venue"
},
  "geometry": {"coordinates":[146.90061950699999,-35.7679786682],"type":"Point"}
}