{
  "type": "Feature",
  "properties": {
    "iso:country":"AU",
    "sg:address":"Suite 7, 45 Ringwood St",
    "sg:city":"Ringwood",
    "sg:classifiers":[
        {
            "category":"Health Services",
            "subcategory":"Doctor",
            "type":"Services"
        }
    ],
    "sg:phone":"+61 1300 799 543",
    "sg:postcode":"3134",
    "sg:province":"VIC",
    "sg:tags":[
        "medical",
        "practitioner"
    ],
    "wof:name":"Avana Cosmetic & Laser Clinics",
    "wof:placetype":"venue"
},
  "geometry": {"coordinates":[145.227172852,-37.8116035461],"type":"Point"}
}