{
  "type": "Feature",
  "properties": {
    "addr:full":"Level 2 and 12, 37 Bligh St Sydney NSW 2000",
    "addr:housenumber":"37",
    "addr:postcode":"2000",
    "addr:street":"Bligh St",
    "iso:country":"AU",
    "sg:address":"Level 2 and 12, 37 Bligh St",
    "sg:city":"Sydney",
    "sg:classifiers":[
        {
            "category":"Structure",
            "subcategory":"Office Building",
            "type":"Public Place"
        }
    ],
    "sg:phone":"+61 2 8233 6100",
    "sg:postcode":"2000",
    "sg:province":"NSW",
    "sg:tags":[
        "serviced"
    ],
    "sg:website":"http://www.uos.com.au",
    "wof:name":"Ultimate Office Solutions",
    "wof:placetype":"venue"
},
  "geometry": {"coordinates":[151.209884644,-33.8660888672],"type":"Point"}
}