{
  "type": "Feature",
  "properties": {
    "iso:country":"AU",
    "sg:address":"Charles St",
    "sg:city":"Euroa",
    "sg:classifiers":[
        {
            "category":"Shopping",
            "subcategory":"Crafts & Fabrics",
            "type":"Retail Goods"
        }
    ],
    "sg:phone":"+61 3 5795 3578",
    "sg:postcode":"3666",
    "sg:province":"VIC",
    "sg:tags":[
        "supply"
    ],
    "wof:name":"First Edition Fibres & Yarns",
    "wof:placetype":"venue"
},
  "geometry": {"coordinates":[145.57325744600001,-36.7450370789],"type":"Point"}
}