{
  "type": "Feature",
  "properties": {
    "iso:country":"AU",
    "sg:address":"PO Box 3024",
    "sg:city":"Willoughby North",
    "sg:classifiers":[
        {
            "category":"Wholesale",
            "subcategory":"Auto Parts",
            "type":"Manufacturing & Wholesale Goods"
        }
    ],
    "sg:phone":"+61 412 301 419",
    "sg:postcode":"2068",
    "sg:province":"NSW",
    "sg:tags":[
        "watch"
    ],
    "wof:name":"Global Watches",
    "wof:placetype":"venue"
},
  "geometry": {"coordinates":[151.19578552199999,-33.7930908203],"type":"Point"}
}