{
  "type": "Feature",
  "properties": {
    "addr:full":"7 Fairfax Rd Glenorchy TAS 7010",
    "addr:housenumber":"7",
    "addr:postcode":"7010",
    "addr:street":"Fairfax Rd",
    "iso:country":"AU",
    "sg:address":"7 Fairfax Rd",
    "sg:city":"Glenorchy",
    "sg:classifiers":[
        {
            "category":"Utilities",
            "subcategory":"Electric",
            "type":"Services"
        }
    ],
    "sg:phone":"+61 419 364 727",
    "sg:postcode":"7010",
    "sg:province":"TAS",
    "sg:tags":[
        "electrical",
        "contractor"
    ],
    "wof:name":"Wiggins David",
    "wof:placetype":"venue"
},
  "geometry": {"coordinates":[147.27734375,-42.8383255005],"type":"Point"}
}