{
  "type": "Feature",
  "properties": {
    "addr:full":"6/10 Gladstone Rd Castle Hill NSW 2154",
    "addr:housenumber":"/ 10",
    "addr:postcode":"2154",
    "addr:street":"Gladstone Rd",
    "iso:country":"AU",
    "sg:address":"6/10 Gladstone Rd",
    "sg:city":"Castle Hill",
    "sg:classifiers":[
        {
            "category":"Health Services",
            "subcategory":"Doctor",
            "type":"Services"
        }
    ],
    "sg:phone":"+61 2 9634 3399",
    "sg:postcode":"2154",
    "sg:province":"NSW",
    "sg:tags":[
        "nurse",
        "nursing"
    ],
    "wof:name":"Just Better Care",
    "wof:placetype":"venue"
},
  "geometry": {"coordinates":[150.975906372,-33.7336883545],"type":"Point"}
}