{
  "type": "Feature",
  "properties": {
    "iso:country":"AU",
    "sg:address":"39 Edgar St",
    "sg:city":"Werribee",
    "sg:classifiers":[
        {
            "category":"Building & Trades",
            "subcategory":"Equipment Rental",
            "type":"Services"
        }
    ],
    "sg:phone":"+61 3 9741 3072",
    "sg:postcode":"3030",
    "sg:province":"VIC",
    "sg:tags":[
        "crane",
        "hire"
    ],
    "wof:name":"Werribee Structural Steel & Crane Hire Pty Ltd",
    "wof:placetype":"venue"
},
  "geometry": {"coordinates":[144.64613299999999,-37.898914],"type":"Point"}
}