{
  "type": "Feature",
  "properties": {
    "iso:country":"AU",
    "sg:address":"19 Queen St",
    "sg:city":"Grafton",
    "sg:classifiers":[
        {
            "category":"Wholesale",
            "subcategory":"Farm Supplies",
            "type":"Manufacturing & Wholesale Goods"
        }
    ],
    "sg:phone":"+61 2 6641 4100",
    "sg:postcode":"2460",
    "sg:province":"NSW",
    "sg:tags":[
        "equipment"
    ],
    "wof:name":"Norco Rural Stores",
    "wof:placetype":"venue"
},
  "geometry": {"coordinates":[152.930587769,-29.6900310516],"type":"Point"}
}