{
  "type": "Feature",
  "properties": {
    "addr:full":"55 Grevillea St Biloela QLD 4715",
    "addr:housenumber":"55",
    "addr:postcode":"4715",
    "addr:street":"Grevillea St",
    "iso:country":"AU",
    "sg:address":"55 Grevillea St",
    "sg:city":"Biloela",
    "sg:classifiers":[
        {
            "category":"Food & Beverages",
            "subcategory":"Bakery",
            "type":"Retail Goods"
        }
    ],
    "sg:phone":"+61 7 4992 1485",
    "sg:postcode":"4715",
    "sg:province":"QLD",
    "sg:tags":[
        "cake",
        "shop",
        "pastry"
    ],
    "wof:name":"Simmons Bakery",
    "wof:placetype":"venue"
},
  "geometry": {"coordinates":[150.513549805,-24.4008293152],"type":"Point"}
}