{
  "type": "Feature",
  "properties": {
    "iso:country":"AU",
    "sg:address":"35 Ervin Rd",
    "sg:city":"Kilsyth",
    "sg:classifiers":[
        {
            "category":"Professional",
            "subcategory":"Computer Services",
            "type":"Services"
        }
    ],
    "sg:phone":"+61 408 204 047",
    "sg:postcode":"3137",
    "sg:province":"VIC",
    "sg:tags":[
        "repairs",
        "upgrade",
        "equipment"
    ],
    "wof:name":"Vivid Technologies",
    "wof:placetype":"venue"
},
  "geometry": {"coordinates":[145.308105469,-37.7968902588],"type":"Point"}
}