{
  "type": "Feature",
  "properties": {
    "addr:full":"Level 8, 303 Coronation Drv Milton QLD 4064",
    "addr:housenumber":"303",
    "addr:postcode":"4064",
    "addr:street":"Coronation Drv",
    "iso:country":"AU",
    "sg:address":"Level 8, 303 Coronation Drv",
    "sg:city":"Milton",
    "sg:classifiers":[
        {
            "category":"Professional",
            "subcategory":"Business Services",
            "type":"Services"
        }
    ],
    "sg:phone":"+61 1300 666 001",
    "sg:postcode":"4064",
    "sg:province":"QLD",
    "sg:tags":[
        "consultant",
        "leasing"
    ],
    "wof:name":"Fleetpartners",
    "wof:placetype":"venue"
},
  "geometry": {"coordinates":[153.00378418,-27.4741706848],"type":"Point"}
}