{
  "type": "Feature",
  "properties": {
    "addr:full":"Cnr Baker & Moore Sts East Botany NSW 2019",
    "addr:postcode":"2019",
    "addr:street":"Cnr;East",
    "iso:country":"AU",
    "sg:address":"Cnr Baker & Moore Sts",
    "sg:city":"East Botany",
    "sg:classifiers":[
        {
            "category":"Utilities",
            "subcategory":"Recycling",
            "type":"Services"
        }
    ],
    "sg:phone":"+61 2 9316 4343",
    "sg:postcode":"2019",
    "sg:province":"NSW",
    "wof:name":"Visy Recycling",
    "wof:placetype":"venue"
},
  "geometry": {"coordinates":[151.20448303200001,-33.9544372559],"type":"Point"}
}