{
  "type": "Feature",
  "properties": {
    "addr:full":"100 Philip Hwy Elizabeth South SA 5112",
    "addr:housenumber":"100",
    "addr:postcode":"5112",
    "addr:street":"Philip Hwy",
    "iso:country":"AU",
    "sg:address":"100 Philip Hwy",
    "sg:city":"Elizabeth South",
    "sg:classifiers":[
        {
            "category":"Food & Beverages",
            "subcategory":"Meat & Fish",
            "type":"Retail Goods"
        }
    ],
    "sg:phone":"+61 8 8252 3342",
    "sg:postcode":"5112",
    "sg:province":"SA",
    "sg:tags":[
        "seafood"
    ],
    "wof:name":"Samsons Seafoods",
    "wof:placetype":"venue"
},
  "geometry": {"coordinates":[138.665405273,-34.7274742126],"type":"Point"}
}