{
  "type": "Feature",
  "properties": {
    "addr:full":"Mort St Braddon ACT 2612",
    "addr:postcode":"2612",
    "addr:street":"Mort St",
    "iso:country":"AU",
    "sg:address":"Mort St",
    "sg:city":"Braddon",
    "sg:classifiers":[
        {
            "category":"Education",
            "subcategory":"Special Training",
            "type":"Public Place"
        }
    ],
    "sg:phone":"+61 2 6247 5770",
    "sg:postcode":"2612",
    "sg:province":"ACT",
    "sg:tags":[
        "feldenkrais"
    ],
    "wof:name":"Eva Culek",
    "wof:placetype":"venue"
},
  "geometry": {"coordinates":[149.131256103,-35.2745895386],"type":"Point"}
}