{
  "type": "Feature",
  "properties": {
    "addr:full":"Shop 15b Brandon Park Shopng Cntr Brandon Park VIC 3170",
    "addr:housenumber":"15b",
    "addr:postcode":"3170",
    "addr:street":"Shop;Brandon Park Shopng Cntr Brandon Park",
    "iso:country":"AU",
    "sg:address":"Shop 15b Brandon Park Shopng Cntr",
    "sg:city":"Brandon Park",
    "sg:classifiers":[
        {
            "category":"Shopping",
            "subcategory":"Optical Goods",
            "type":"Retail Goods"
        }
    ],
    "sg:phone":"+61 3 9562 5311",
    "sg:postcode":"3170",
    "sg:province":"VIC",
    "sg:tags":[
        "dispenser",
        "prescription"
    ],
    "wof:name":"The Optical Shop",
    "wof:placetype":"venue"
},
  "geometry": {"coordinates":[145.17161560100001,-37.9170379639],"type":"Point"}
}