{
  "type": "Feature",
  "properties": {
    "addr:full":"Shop 3 53 Carrier St Benalla VIC 3672",
    "addr:housenumber":"shop;53",
    "addr:postcode":"3672",
    "addr:street":"Carrier St",
    "iso:country":"AU",
    "sg:address":"Shop 3 53 Carrier St",
    "sg:city":"Benalla",
    "sg:classifiers":[
        {
            "category":"Professional",
            "subcategory":"Computer Services",
            "type":"Services"
        }
    ],
    "sg:phone":"+61 3 5762 6661",
    "sg:postcode":"3672",
    "sg:province":"VIC",
    "sg:tags":[
        "equipment",
        "networking",
        "installation"
    ],
    "wof:name":"Cross Country Computers",
    "wof:placetype":"venue"
},
  "geometry": {"coordinates":[145.98571799999999,-36.550285],"type":"Point"}
}