{
  "type": "Feature",
  "properties": {
    "addr:full":"58 Riverside Rd Chipping Norton NSW 2170",
    "addr:housenumber":"58",
    "addr:postcode":"2170",
    "addr:street":"Riverside Rd",
    "iso:country":"AU",
    "sg:address":"58 Riverside Rd",
    "sg:city":"Chipping Norton",
    "sg:classifiers":[
        {
            "category":"Wholesale",
            "subcategory":"Auto Parts",
            "type":"Manufacturing & Wholesale Goods"
        }
    ],
    "sg:phone":"+61 2 9755 2202",
    "sg:postcode":"2170",
    "sg:province":"NSW",
    "sg:tags":[
        "recyclers"
    ],
    "wof:name":"Landmark Auto Wreckers",
    "wof:placetype":"venue"
},
  "geometry": {"coordinates":[150.968460083,-33.9203033447],"type":"Point"}
}