{
  "type": "Feature",
  "properties": {
    "addr:full":"Ross House Level 4, 247 Flinders Lane Melbourne VIC 3000",
    "addr:housenumber":"247",
    "addr:postcode":"3000",
    "addr:street":"Flinders Lane",
    "iso:country":"AU",
    "sg:address":"Ross House Level 4, 247 Flinders Lane",
    "sg:city":"Melbourne",
    "sg:classifiers":[
        {
            "category":"Recreation",
            "type":"Entertainment"
        }
    ],
    "sg:phone":"+61 3 9650 8241",
    "sg:postcode":"3000",
    "sg:province":"VIC",
    "sg:tags":[
        "supply",
        "outdoor",
        "adventure",
        "activity"
    ],
    "wof:name":"Wild About Adventures Pty Ltd",
    "wof:placetype":"venue"
},
  "geometry": {"coordinates":[144.96611023,-37.8168678284],"type":"Point"}
}