{
  "type": "Feature",
  "properties": {
    "addr:full":"90 Parramatta Rd Granville NSW 2142",
    "addr:housenumber":"90",
    "addr:postcode":"2142",
    "addr:street":"Parramatta Rd",
    "iso:country":"AU",
    "sg:address":"90 Parramatta Rd",
    "sg:city":"Granville",
    "sg:classifiers":[
        {
            "category":"Retail",
            "subcategory":"Auto Repair",
            "type":"Services"
        }
    ],
    "sg:phone":"+61 2 9897 2892",
    "sg:postcode":"2142",
    "sg:province":"NSW",
    "sg:tags":[
        "repairer",
        "motor",
        "engineer"
    ],
    "wof:name":"Sari Motor Repairs",
    "wof:placetype":"venue"
},
  "geometry": {"coordinates":[151.014602661,-33.8317642212],"type":"Point"}
}