{
  "type": "Feature",
  "properties": {
    "addr:full":"5 Through Rd Ringwood VIC 3134",
    "addr:housenumber":"5",
    "addr:postcode":"3134",
    "addr:street":"Through Rd",
    "iso:country":"AU",
    "sg:address":"5 Through Rd",
    "sg:city":"Ringwood",
    "sg:classifiers":[
        {
            "category":"Manufacturing",
            "subcategory":"Tools & Machinery",
            "type":"Manufacturing & Wholesale Goods"
        }
    ],
    "sg:phone":"+61 3 9870 0249",
    "sg:postcode":"3134",
    "sg:province":"VIC",
    "sg:tags":[
        "earth",
        "excavating",
        "moving",
        "equipment"
    ],
    "wof:name":"Roe D F",
    "wof:placetype":"venue"
},
  "geometry": {"coordinates":[145.229446411,-37.8014984131],"type":"Point"}
}