{
  "type": "Feature",
  "properties": {
    "addr:full":"Suite 1, Ground Floor 131 - 135 George St Liverpool NSW 2170",
    "addr:housenumber":"131 135",
    "addr:postcode":"2170",
    "addr:street":"George St",
    "iso:country":"AU",
    "sg:address":"Suite 1, Ground Floor 131 - 135 George St",
    "sg:city":"Liverpool",
    "sg:classifiers":[
        {
            "category":"Health Services",
            "subcategory":"Doctor",
            "type":"Services"
        }
    ],
    "sg:phone":"+61 1300 558 505",
    "sg:postcode":"2170",
    "sg:province":"NSW",
    "sg:tags":[
        "occupational",
        "safety"
    ],
    "sg:website":"http://www.activeohs.com.au",
    "wof:name":"Active Occupational Health Services",
    "wof:placetype":"venue"
},
  "geometry": {"coordinates":[150.92457580600001,-33.9236106873],"type":"Point"}
}