{
  "type": "Feature",
  "properties": {
    "addr:full":"PO Box 6341 Silverwater NSW 1811",
    "addr:postcode":"1811",
    "iso:country":"AU",
    "sg:address":"PO Box 6341",
    "sg:city":"Silverwater",
    "sg:classifiers":[
        {
            "category":"Utilities",
            "type":"Services"
        }
    ],
    "sg:phone":"+61 1300 766 772",
    "sg:postcode":"1811",
    "sg:province":"NSW",
    "sg:tags":[
        "refrigeration",
        "industrial",
        "commercial",
        "retail"
    ],
    "wof:name":"Coldchain Australia P/L",
    "wof:placetype":"venue"
},
  "geometry": {"coordinates":[151.04791299999999,-33.834999],"type":"Point"}
}