{
  "type": "Feature",
  "properties": {
    "addr:full":"3/784 Corner Of Pacific Highway & Moree St Gordon NSW 2072",
    "addr:housenumber":"/ 784",
    "addr:postcode":"2072",
    "addr:street":"Corner Of Pacific Highway & Moree St",
    "iso:country":"AU",
    "sg:address":"3/784 Corner Of Pacific Highway & Moree St",
    "sg:city":"Gordon",
    "sg:classifiers":[
        {
            "category":"Shopping",
            "subcategory":"Jewelry",
            "type":"Retail Goods"
        }
    ],
    "sg:phone":"+61 2 9499 3899",
    "sg:postcode":"2072",
    "sg:province":"NSW",
    "sg:tags":[
        "jeweller"
    ],
    "wof:name":"D'bron Fine Jewellery",
    "wof:placetype":"venue"
},
  "geometry": {"coordinates":[151.15333557100001,-33.7575912476],"type":"Point"}
}