{
  "type": "Feature",
  "properties": {
    "addr:full":"145 Wellington St Launceston TAS 7250",
    "addr:housenumber":"145",
    "addr:postcode":"7250",
    "addr:street":"Wellington St",
    "iso:country":"AU",
    "sg:address":"145 Wellington St",
    "sg:city":"Launceston",
    "sg:classifiers":[
        {
            "category":"Utilities",
            "type":"Services"
        }
    ],
    "sg:phone":"+61 3 6331 6711",
    "sg:postcode":"7250",
    "sg:province":"TAS",
    "sg:tags":[
        "equipment",
        "towing"
    ],
    "wof:name":"Nuts & Bolts Tasmania",
    "wof:placetype":"venue"
},
  "geometry": {"coordinates":[147.138839722,-41.443813324],"type":"Point"}
}