{
  "type": "Feature",
  "properties": {
    "addr:full":"105- 109 High St Mansfield VIC 3722",
    "addr:housenumber":"105 109",
    "addr:postcode":"3722",
    "addr:street":"High St",
    "iso:country":"AU",
    "sg:address":"105- 109 High St",
    "sg:city":"Mansfield",
    "sg:classifiers":[
        {
            "category":"Professional",
            "subcategory":"Accounting & Tax Preparation",
            "type":"Services"
        }
    ],
    "sg:phone":"+61 3 5775 3170",
    "sg:postcode":"3722",
    "sg:province":"VIC",
    "sg:tags":[
        "consultant",
        "taxation"
    ],
    "wof:name":"Henry Partners Pty Ltd",
    "wof:placetype":"venue"
},
  "geometry": {"coordinates":[146.08720398,-37.0518341064],"type":"Point"}
}