{
  "type": "Feature",
  "properties": {
    "addr:full":"17 Palomino Drv Mudgeeraba QLD 4213",
    "addr:housenumber":"17",
    "addr:postcode":"4213",
    "addr:street":"Palomino Drv",
    "iso:country":"AU",
    "sg:address":"17 Palomino Drv",
    "sg:city":"Mudgeeraba",
    "sg:classifiers":[
        {
            "category":"Building & Trades",
            "subcategory":"Construction",
            "type":"Services"
        }
    ],
    "sg:phone":"+61 439 033 748",
    "sg:postcode":"4213",
    "sg:province":"QLD",
    "sg:tags":[
        "contractor"
    ],
    "wof:name":"Tron Systems Pty Ltd",
    "wof:placetype":"venue"
},
  "geometry": {"coordinates":[153.365524292,-28.1079559326],"type":"Point"}
}