{
  "type": "Feature",
  "properties": {
    "iso:country":"AU",
    "sg:address":"PO Box 761",
    "sg:city":"Cowra",
    "sg:classifiers":[
        {
            "category":"Building & Trades",
            "subcategory":"Construction",
            "type":"Services"
        }
    ],
    "sg:phone":"+61 428 161 028",
    "sg:postcode":"2794",
    "sg:province":"NSW",
    "sg:tags":[
        "plasterboard",
        "plasterer",
        "fixer"
    ],
    "wof:name":"Richards Plastering Service",
    "wof:placetype":"venue"
},
  "geometry": {"coordinates":[148.69056701700001,-33.8345909119],"type":"Point"}
}