{
  "type": "Feature",
  "properties": {
    "iso:country":"AU",
    "sg:address":"40b Knight St",
    "sg:city":"North Rockhampton",
    "sg:classifiers":[
        {
            "category":"Retail",
            "subcategory":"Auto Repair",
            "type":"Services"
        }
    ],
    "sg:phone":"+61 7 4926 5122",
    "sg:postcode":"4701",
    "sg:province":"QLD",
    "sg:tags":[
        "repairer",
        "motor",
        "engineer"
    ],
    "wof:name":"Millennium Power Steering & Automotive",
    "wof:placetype":"venue"
},
  "geometry": {"coordinates":[150.51431274399999,-23.3610134125],"type":"Point"}
}