{
  "type": "Feature",
  "properties": {
    "addr:full":"231 Camboon Rd Malaga WA 6090",
    "addr:housenumber":"231",
    "addr:postcode":"6090",
    "addr:street":"Camboon Rd",
    "iso:country":"AU",
    "sg:address":"231 Camboon Rd",
    "sg:city":"Malaga",
    "sg:classifiers":[
        {
            "category":"Home & Garden",
            "subcategory":"Furniture",
            "type":"Retail Goods"
        }
    ],
    "sg:phone":"+61 8 9248 7055",
    "sg:postcode":"6090",
    "sg:province":"WA",
    "sg:tags":[
        "business"
    ],
    "wof:name":"Astra Metal Products",
    "wof:placetype":"venue"
},
  "geometry": {"coordinates":[115.887290955,-31.8573741913],"type":"Point"}
}