{
  "type": "Feature",
  "properties": {
    "addr:full":"8A/ 233 Berrigan Drv Glen Iris WA 6230",
    "addr:housenumber":"8a / 233",
    "addr:postcode":"6230",
    "addr:street":"Berrigan Drv",
    "iso:country":"AU",
    "sg:address":"8A/ 233 Berrigan Drv",
    "sg:city":"Glen Iris",
    "sg:classifiers":[
        {
            "category":"Shopping",
            "subcategory":"Bridal",
            "type":"Retail Goods"
        }
    ],
    "sg:phone":"+61 8 9417 7100",
    "sg:postcode":"6230",
    "sg:province":"WA",
    "sg:tags":[
        "hire",
        "wear"
    ],
    "wof:name":"Angels Bridal & Formal Wear",
    "wof:placetype":"venue"
},
  "geometry": {"coordinates":[115.67952,-33.33675],"type":"Point"}
}