{
  "type": "Feature",
  "properties": {
    "addr:full":"29 May St St Peters NSW 2044",
    "addr:housenumber":"29",
    "addr:postcode":"2044",
    "addr:street":"May St",
    "iso:country":"AU",
    "sg:address":"29 May St",
    "sg:city":"St Peters",
    "sg:classifiers":[
        {
            "category":"Fast Food",
            "type":"Food & Drink"
        }
    ],
    "sg:phone":"+61 2 9516 2687",
    "sg:postcode":"2044",
    "sg:province":"NSW",
    "sg:tags":[
        "away",
        "take"
    ],
    "wof:name":"Connie Sandwich Shop",
    "wof:placetype":"venue"
},
  "geometry": {"coordinates":[151.179855,-33.908871],"type":"Point"}
}