{
  "type": "Feature",
  "properties": {
    "iso:country":"AU",
    "sg:address":"129 Queens Pde",
    "sg:city":"Clifton Hill",
    "sg:classifiers":[
        {
            "category":"Government",
            "subcategory":"Post Office",
            "type":"Public Place"
        }
    ],
    "sg:phone":"+61 3 9486 8044",
    "sg:postcode":"3068",
    "sg:province":"VIC",
    "sg:tags":[
        "yoga"
    ],
    "wof:name":"Clifton Hill Yoga Studio",
    "wof:placetype":"venue"
},
  "geometry": {"coordinates":[144.99046325699999,-37.7891693115],"type":"Point"}
}