{
  "type": "Feature",
  "properties": {
    "addr:full":"107 Thirroul Rd Kanahooka NSW 2530",
    "addr:housenumber":"107",
    "addr:postcode":"2530",
    "addr:street":"Thirroul Rd",
    "iso:country":"AU",
    "sg:address":"107 Thirroul Rd",
    "sg:city":"Kanahooka",
    "sg:classifiers":[
        {
            "category":"Professional",
            "subcategory":"Business Services",
            "type":"Services"
        }
    ],
    "sg:phone":"+61 2 4261 7808",
    "sg:postcode":"2530",
    "sg:province":"NSW",
    "sg:tags":[
        "drafting"
    ],
    "wof:name":"Rika Drafting Pty Ltd",
    "wof:placetype":"venue"
},
  "geometry": {"coordinates":[150.807693481,-34.49401474],"type":"Point"}
}