{
  "type": "Feature",
  "properties": {
    "addr:full":"Shop 2 & 3 / 17 Geddes St Mulgrave VIC 3170",
    "addr:housenumber":"shop 2 & 3 / 17",
    "addr:postcode":"3170",
    "addr:street":"Geddes St",
    "iso:country":"AU",
    "sg:address":"Shop 2 & 3 / 17 Geddes St",
    "sg:city":"Mulgrave",
    "sg:classifiers":[
        {
            "category":"Building & Trades",
            "subcategory":"Construction",
            "type":"Services"
        }
    ],
    "sg:phone":"+61 3 9545 1223",
    "sg:postcode":"3170",
    "sg:province":"VIC",
    "sg:tags":[
        "renovation",
        "alterations",
        "extension",
        "contractor"
    ],
    "wof:name":"Waverley Bathrooms",
    "wof:placetype":"venue"
},
  "geometry": {"coordinates":[145.154907227,-37.9060668945],"type":"Point"}
}