{
  "type": "Feature",
  "properties": {
    "addr:full":"55 Rushdale St Knoxfield VIC 3180",
    "addr:housenumber":"55",
    "addr:postcode":"3180",
    "addr:street":"Rushdale St",
    "iso:country":"AU",
    "sg:address":"55 Rushdale St",
    "sg:city":"Knoxfield",
    "sg:classifiers":[
        {
            "category":"Manufacturing",
            "subcategory":"Metals",
            "type":"Manufacturing & Wholesale Goods"
        }
    ],
    "sg:phone":"+61 3 9753 3011",
    "sg:postcode":"3180",
    "sg:province":"VIC",
    "sg:tags":[
        "steel",
        "fabricator",
        "mfrs"
    ],
    "sg:website":"http://www.barrasteel.com.au",
    "wof:name":"Barra Steel",
    "wof:placetype":"venue"
},
  "geometry": {"coordinates":[145.25553894000001,-37.8946151733],"type":"Point"}
}