{
  "type": "Feature",
  "properties": {
    "addr:full":"26 Argyle Ave Ryde NSW 2112",
    "addr:housenumber":"26",
    "addr:postcode":"2112",
    "addr:street":"Argyle Ave",
    "iso:country":"AU",
    "sg:address":"26 Argyle Ave",
    "sg:city":"Ryde",
    "sg:classifiers":[
        {
            "category":"Social Services",
            "subcategory":"Child Care",
            "type":"Services"
        }
    ],
    "sg:phone":"+61 2 9809 2632",
    "sg:postcode":"2112",
    "sg:province":"NSW",
    "sg:tags":[
        "support",
        "health"
    ],
    "wof:name":"Early Childhood Health Centres",
    "wof:placetype":"venue"
},
  "geometry": {"coordinates":[151.107696533,-33.8142585754],"type":"Point"}
}