{
  "type": "Feature",
  "properties": {
    "iso:country":"AU",
    "sg:address":"10 Barbour St",
    "sg:city":"Esk",
    "sg:classifiers":[
        {
            "category":"Building & Trades",
            "subcategory":"Landscaping Services",
            "type":"Services"
        }
    ],
    "sg:phone":"+61 7 5424 1242",
    "sg:postcode":"4312",
    "sg:province":"QLD",
    "sg:tags":[
        "grazier"
    ],
    "wof:name":"Conroy M P",
    "wof:placetype":"venue"
},
  "geometry": {"coordinates":[152.416915894,-27.2347316742],"type":"Point"}
}