{
  "type": "Feature",
  "properties": {
    "iso:country":"AU",
    "sg:address":"7 Sinclair Ave",
    "sg:city":"Lower Templestowe",
    "sg:classifiers":[
        {
            "category":"Arena",
            "subcategory":"Sports Club",
            "type":"Entertainment"
        }
    ],
    "sg:phone":"+61 3 9852 1027",
    "sg:postcode":"3107",
    "sg:province":"VIC",
    "sg:tags":[
        "defence",
        "supply",
        "self",
        "instruction",
        "martial art"
    ],
    "wof:name":"Added Health Services",
    "wof:placetype":"venue"
},
  "geometry": {"coordinates":[145.12217712399999,-37.7626724243],"type":"Point"}
}