{
  "type": "Feature",
  "properties": {
    "addr:full":"132A Alma Rd St Kilda VIC 3182",
    "addr:housenumber":"132a",
    "addr:postcode":"3182",
    "addr:street":"Alma Rd",
    "iso:country":"AU",
    "sg:address":"132A Alma Rd St",
    "sg:city":"Kilda",
    "sg:classifiers":[
        {
            "category":"Home & Garden",
            "subcategory":"Hardware",
            "type":"Retail Goods"
        }
    ],
    "sg:phone":"+61 3 9527 8338",
    "sg:postcode":"3182",
    "sg:province":"VIC",
    "sg:tags":[
        "product",
        "treatment",
        "floor"
    ],
    "wof:name":"Best Non-Slip Solutions",
    "wof:placetype":"venue"
},
  "geometry": {"coordinates":[144.98387145999999,-37.8604125977],"type":"Point"}
}