{
  "type": "Feature",
  "properties": {
    "addr:full":"Charles Rd Mt Pleasant Dayboro QLD 4521",
    "addr:postcode":"4521",
    "addr:street":"Charles Rd",
    "iso:country":"AU",
    "sg:address":"Charles Rd Mt Pleasant",
    "sg:city":"Dayboro",
    "sg:classifiers":[
        {
            "category":"Farming",
            "subcategory":"Farm",
            "type":"Manufacturing & Wholesale Goods"
        }
    ],
    "sg:phone":"+61 7 3425 1229",
    "sg:postcode":"4521",
    "sg:province":"QLD",
    "sg:tags":[
        "farmer"
    ],
    "wof:name":"Williams A V",
    "wof:placetype":"venue"
},
  "geometry": {"coordinates":[152.779877,-27.170656],"type":"Point"}
}