{
  "type": "Feature",
  "properties": {
    "addr:full":"3 Orana Ave Boyne Island QLD 4680",
    "addr:housenumber":"3",
    "addr:postcode":"4680",
    "addr:street":"Orana Ave",
    "iso:country":"AU",
    "sg:address":"3 Orana Ave",
    "sg:city":"Boyne Island",
    "sg:classifiers":[
        {
            "category":"Travel",
            "subcategory":"Hotels & Motels",
            "type":"Entertainment"
        }
    ],
    "sg:phone":"+61 7 4973 7444",
    "sg:postcode":"4680",
    "sg:province":"QLD",
    "wof:name":"Boyne Island Motel & Villa's",
    "wof:placetype":"venue"
},
  "geometry": {"coordinates":[151.35247802699999,-23.9388885498],"type":"Point"}
}