{
  "type": "Feature",
  "properties": {
    "addr:full":"365 High St Northcote VIC 3070",
    "addr:housenumber":"365",
    "addr:postcode":"3070",
    "addr:street":"High St",
    "iso:country":"AU",
    "sg:address":"365 High St",
    "sg:city":"Northcote",
    "sg:classifiers":[
        {
            "category":"Building & Trades",
            "subcategory":"Locksmith",
            "type":"Services"
        }
    ],
    "sg:phone":"+61 3 9482 1531",
    "sg:postcode":"3070",
    "sg:province":"VIC",
    "sg:tags":[
        "lock"
    ],
    "sg:website":"http://www.metrolock.com.au",
    "wof:name":"Metrolock Security",
    "wof:placetype":"venue"
},
  "geometry": {"coordinates":[144.99876399999999,-37.769871],"type":"Point"}
}