{
  "type": "Feature",
  "properties": {
    "addr:full":"12 Glyde St Port Augusta SA 5700",
    "addr:housenumber":"12",
    "addr:postcode":"5700",
    "addr:street":"Glyde St",
    "iso:country":"AU",
    "sg:address":"12 Glyde St",
    "sg:city":"Port Augusta",
    "sg:classifiers":[
        {
            "category":"Insurance",
            "subcategory":"Hazard Insurance",
            "type":"Services"
        }
    ],
    "sg:phone":"+61 8 8642 4008",
    "sg:postcode":"5700",
    "sg:province":"SA",
    "sg:tags":[
        "fire",
        "accident",
        "marine"
    ],
    "wof:name":"Ray Thompson",
    "wof:placetype":"venue"
},
  "geometry": {"coordinates":[137.77488708499999,-32.4968566895],"type":"Point"}
}