{
  "type": "Feature",
  "properties": {
    "iso:country":"AU",
    "sg:address":"3/ 13",
    "sg:city":"Mudjimba Esp North Shore",
    "sg:classifiers":[
        {
            "category":"Real Estate",
            "subcategory":"Real Estate Agent",
            "type":"Services"
        }
    ],
    "sg:phone":"+61 7 5448 8111",
    "sg:postcode":"4565",
    "sg:province":"QLD",
    "wof:name":"Real Way Property Consultants",
    "wof:placetype":"venue"
},
  "geometry": {"coordinates":[153.04284668,-26.3514900208],"type":"Point"}
}