{
  "type": "Feature",
  "properties": {
    "iso:country":"AU",
    "sg:address":"755 High St",
    "sg:city":"Thornbury",
    "sg:classifiers":[
        {
            "category":"Utilities",
            "subcategory":"Telephone",
            "type":"Services"
        }
    ],
    "sg:phone":"+61 3 9458 6400",
    "sg:postcode":"3071",
    "sg:province":"VIC",
    "sg:tags":[
        "equipment",
        "system"
    ],
    "wof:name":"National Telecom Group",
    "wof:placetype":"venue"
},
  "geometry": {"coordinates":[145.00057983400001,-37.7578811646],"type":"Point"}
}