{
  "type": "Feature",
  "properties": {
    "addr:full":"68 Telopea St Redfern NSW 2016",
    "addr:housenumber":"68",
    "addr:postcode":"2016",
    "addr:street":"Telopea St",
    "iso:country":"AU",
    "sg:address":"68 Telopea St",
    "sg:city":"Redfern",
    "sg:classifiers":[
        {
            "category":"Professional",
            "subcategory":"Computer Services",
            "type":"Services"
        }
    ],
    "sg:phone":"+61 2 9310 7500",
    "sg:postcode":"2016",
    "sg:province":"NSW",
    "sg:tags":[
        "package",
        "software"
    ],
    "wof:name":"HR3 Pty Ltd",
    "wof:placetype":"venue"
},
  "geometry": {"coordinates":[151.21131897000001,-33.8941497803],"type":"Point"}
}