{
  "type": "Feature",
  "properties": {
    "iso:country":"AU",
    "sg:address":"34 Pleasant St",
    "sg:city":"North Ballarat",
    "sg:classifiers":[
        {
            "category":"Travel",
            "subcategory":"Hostel",
            "type":"Entertainment"
        }
    ],
    "sg:phone":"+61 3 5332 1841",
    "sg:postcode":"3350",
    "sg:province":"VIC",
    "sg:tags":[
        "home"
    ],
    "wof:name":"Pleasant Homes",
    "wof:placetype":"venue"
},
  "geometry": {"coordinates":[143.83827199999999,-37.562855],"type":"Point"}
}