{
  "type": "Feature",
  "properties": {
    "iso:country":"AU",
    "sg:address":"19 Chuter St",
    "sg:city":"McMahons Point",
    "sg:classifiers":[
        {
            "category":"Professional",
            "subcategory":"Art Services",
            "type":"Services"
        }
    ],
    "sg:phone":"+61 2 9929 6629",
    "sg:postcode":"2060",
    "sg:province":"NSW",
    "sg:tags":[
        "arranger",
        "music",
        "composer"
    ],
    "wof:name":"Beamo Music",
    "wof:placetype":"venue"
},
  "geometry": {"coordinates":[151.20317077600001,-33.8423309326],"type":"Point"}
}