{
  "type": "Feature",
  "properties": {
    "addr:full":"Cnr Bald Hill Rd & Bormar Drv Pakenham VIC 3810",
    "addr:postcode":"3810",
    "addr:street":"Bald Hill Rd & Bormar Drv",
    "iso:country":"AU",
    "sg:address":"Cnr Bald Hill Rd & Bormar Drv",
    "sg:city":"Pakenham",
    "sg:classifiers":[
        {
            "category":"Wholesale",
            "subcategory":"Farm Supplies",
            "type":"Manufacturing & Wholesale Goods"
        }
    ],
    "sg:phone":"+61 3 5941 1844",
    "sg:postcode":"3810",
    "sg:province":"VIC",
    "sg:tags":[
        "equipment"
    ],
    "wof:name":"Pakenham Produce & Saddlery",
    "wof:placetype":"venue"
},
  "geometry": {"coordinates":[145.486313,-38.079475],"type":"Point"}
}