{
  "type": "Feature",
  "properties": {
    "addr:full":"Stratton Park Shopping Centre 3 Jecks Pl Stratton WA 6056",
    "addr:housenumber":"3",
    "addr:postcode":"6056",
    "addr:street":"Jecks Pl",
    "iso:country":"AU",
    "sg:address":"Stratton Park Shopping Centre 3 Jecks Pl",
    "sg:city":"Stratton",
    "sg:classifiers":[
        {
            "category":"Health Services",
            "subcategory":"Doctor",
            "type":"Services"
        }
    ],
    "sg:phone":"+61 8 9250 7700",
    "sg:postcode":"6056",
    "sg:province":"WA",
    "sg:tags":[
        "medical",
        "practitioner"
    ],
    "wof:name":"Stratton Park Medical Centre",
    "wof:placetype":"venue"
},
  "geometry": {"coordinates":[116.035263062,-31.869392395],"type":"Point"}
}