{
  "type": "Feature",
  "properties": {
    "addr:full":"5/ 1 Donaldson St Wyong North NSW 2259",
    "addr:housenumber":"/ 1",
    "addr:postcode":"2259",
    "addr:street":"Donaldson St",
    "iso:country":"AU",
    "sg:address":"5/ 1 Donaldson St",
    "sg:city":"Wyong North",
    "sg:classifiers":[
        {
            "category":"Shopping",
            "subcategory":"Discount & Variety Stores",
            "type":"Retail Goods"
        }
    ],
    "sg:phone":"+61 2 4353 9493",
    "sg:postcode":"2259",
    "sg:province":"NSW",
    "sg:tags":[
        "shop",
        "adult"
    ],
    "wof:name":"Nauti & Nice Adult Megastores",
    "wof:placetype":"venue"
},
  "geometry": {"coordinates":[151.442169189,-33.2665748596],"type":"Point"}
}