{
  "type": "Feature",
  "properties": {
    "addr:full":"Suite 7 Cnr Denison & King St Deakin ACT 2600",
    "addr:housenumber":"cnr",
    "addr:postcode":"2600",
    "addr:street":"St",
    "iso:country":"AU",
    "sg:address":"Suite 7 Cnr Denison & King St",
    "sg:city":"Deakin",
    "sg:classifiers":[
        {
            "category":"Personal",
            "subcategory":"Massage",
            "type":"Services"
        }
    ],
    "sg:phone":"+61 439 883 776",
    "sg:postcode":"2600",
    "sg:province":"ACT",
    "sg:tags":[
        "therapy"
    ],
    "wof:name":"Allison, Lauren",
    "wof:placetype":"venue"
},
  "geometry": {"coordinates":[149.09771728499999,-35.3149108887],"type":"Point"}
}