{
  "type": "Feature",
  "properties": {
    "addr:full":"17- 35 Parramatta Rd Homebush NSW 2140",
    "addr:housenumber":"35",
    "addr:postcode":"2140",
    "addr:street":"Parramatta Rd",
    "iso:country":"AU",
    "sg:address":"17- 35 Parramatta Rd",
    "sg:city":"Homebush",
    "sg:classifiers":[
        {
            "category":"Autos & Motor Vehicles",
            "subcategory":"Auto Supplies",
            "type":"Retail Goods"
        }
    ],
    "sg:phone":"+61 2 8741 3000",
    "sg:postcode":"2140",
    "sg:province":"NSW",
    "sg:tags":[
        "part",
        "cycles",
        "accessory"
    ],
    "wof:name":"Fraser Motorcycles",
    "wof:placetype":"venue"
},
  "geometry": {"coordinates":[151.08869934099999,-33.8652267456],"type":"Point"}
}