{
  "type": "Feature",
  "properties": {
    "iso:country":"AU",
    "sg:address":"Shop T143 Bay City Plaza, Malop St",
    "sg:city":"Geelong",
    "sg:classifiers":[
        {
            "category":"Shopping",
            "subcategory":"Clothing, Apparel, & Fashions",
            "type":"Retail Goods"
        }
    ],
    "sg:phone":"+61 3 5229 3576",
    "sg:postcode":"3220",
    "sg:province":"VIC",
    "sg:tags":[
        "jean"
    ],
    "wof:name":"Giordano (Australia) Pty Ltd",
    "wof:placetype":"venue"
},
  "geometry": {"coordinates":[144.35878,-38.146667],"type":"Point"}
}