{
  "type": "Feature",
  "properties": {
    "addr:full":"D157 Perth GPO Boxes 6840 Alfred Cove WA 6154",
    "addr:housenumber":"d157;6840",
    "addr:postcode":"6154",
    "addr:street":"Perth;Boxes",
    "iso:country":"AU",
    "sg:address":"D157 Perth GPO Boxes 6840",
    "sg:city":"Alfred Cove",
    "sg:classifiers":[
        {
            "category":"Professional",
            "subcategory":"Employment Agencies",
            "type":"Services"
        }
    ],
    "sg:phone":"+61 8 9330 4157",
    "sg:postcode":"6154",
    "sg:province":"WA",
    "sg:tags":[
        "provider",
        "internet"
    ],
    "wof:name":"Candela",
    "wof:placetype":"venue"
},
  "geometry": {"coordinates":[115.815659,-32.031559],"type":"Point"}
}