{
  "type": "Feature",
  "properties": {
    "iso:country":"AU",
    "sg:address":"Colonial Centre Warrimoo Ave",
    "sg:city":"St Ives Chase",
    "sg:classifiers":[
        {
            "category":"Deli",
            "type":"Food & Drink"
        }
    ],
    "sg:phone":"+61 2 9449 5137",
    "sg:postcode":"2075",
    "sg:province":"NSW",
    "sg:tags":[
        "delicatessen"
    ],
    "wof:name":"4 Square Deli",
    "wof:placetype":"venue"
},
  "geometry": {"coordinates":[151.16062927199999,-33.710231781],"type":"Point"}
}