{
  "type": "Feature",
  "properties": {
    "iso:country":"AU",
    "sg:address":"150 Koornang Rd",
    "sg:city":"Carnegie",
    "sg:classifiers":[
        {
            "category":"Personal",
            "subcategory":"Beauty Salon",
            "type":"Services"
        }
    ],
    "sg:phone":"+61 3 9569 5073",
    "sg:postcode":"3163",
    "sg:province":"VIC",
    "sg:tags":[
        "hairdresser"
    ],
    "wof:name":"Orlando Joseph For Hair",
    "wof:placetype":"venue"
},
  "geometry": {"coordinates":[145.05718994099999,-37.8894577026],"type":"Point"}
}