{
  "type": "Feature",
  "properties": {
    "addr:full":"115-117 North West Coastal Hwy Wonthella WA 6530",
    "addr:housenumber":"115-117",
    "addr:postcode":"6530",
    "addr:street":"North West Coastal Hwy",
    "iso:country":"AU",
    "sg:address":"115-117 North West Coastal Hwy",
    "sg:city":"Wonthella",
    "sg:classifiers":[
        {
            "category":"Autos & Motor Vehicles",
            "subcategory":"Fuel & Gas Station",
            "type":"Retail Goods"
        }
    ],
    "sg:phone":"+61 8 9964 5445",
    "sg:postcode":"6530",
    "sg:province":"WA",
    "wof:name":"Smart Mart Pure Convenience",
    "wof:placetype":"venue"
},
  "geometry": {"coordinates":[114.62448883099999,-28.7687721252],"type":"Point"}
}