{
  "type": "Feature",
  "properties": {
    "addr:full":"57 Mulgrave St Gin Gin QLD 4671",
    "addr:housenumber":"57",
    "addr:postcode":"4671",
    "addr:street":"Mulgrave St",
    "iso:country":"AU",
    "sg:address":"57 Mulgrave St",
    "sg:city":"Gin Gin",
    "sg:classifiers":[
        {
            "category":"Autos & Motor Vehicles",
            "subcategory":"Auto Supplies",
            "type":"Retail Goods"
        }
    ],
    "sg:phone":"+61 7 4157 2888",
    "sg:postcode":"4671",
    "sg:province":"QLD",
    "sg:tags":[
        "part",
        "cycles",
        "accessory"
    ],
    "wof:name":"Gin Gin Motorcycles",
    "wof:placetype":"venue"
},
  "geometry": {"coordinates":[151.962784,-24.99382],"type":"Point"}
}