{
  "type": "Feature",
  "properties": {
    "addr:full":"143/ 313 Harris St Pyrmont NSW 2009",
    "addr:housenumber":"143 / 313",
    "addr:postcode":"2009",
    "addr:street":"Harris St",
    "iso:country":"AU",
    "sg:address":"143/ 313 Harris St",
    "sg:city":"Pyrmont",
    "sg:classifiers":[
        {
            "category":"Health Services",
            "subcategory":"Dentist",
            "type":"Services"
        }
    ],
    "sg:phone":"+61 2 9660 3322",
    "sg:postcode":"2009",
    "sg:province":"NSW",
    "wof:name":"Pyrmont Dental Centre.",
    "wof:placetype":"venue"
},
  "geometry": {"coordinates":[151.19639587399999,-33.8741912842],"type":"Point"}
}