{
  "type": "Feature",
  "properties": {
    "addr:full":"346 Military Rd Vaucluse NSW 2030",
    "addr:housenumber":"346",
    "addr:postcode":"2030",
    "addr:street":"Military Rd",
    "iso:country":"AU",
    "sg:address":"346 Military Rd",
    "sg:city":"Vaucluse",
    "sg:classifiers":[
        {
            "category":"Professional",
            "subcategory":"Accounting & Tax Preparation",
            "type":"Services"
        }
    ],
    "sg:phone":"+61 2 9337 5160",
    "sg:postcode":"2030",
    "sg:province":"NSW",
    "sg:tags":[
        "accountant",
        "auditor"
    ],
    "wof:name":"S N S Accounting",
    "wof:placetype":"venue"
},
  "geometry": {"coordinates":[151.28099060100001,-33.8633308411],"type":"Point"}
}