{
  "type": "Feature",
  "properties": {
    "iso:country":"AU",
    "sg:address":"43 Prime Drv",
    "sg:city":"Seven Hills",
    "sg:classifiers":[
        {
            "category":"Home & Garden",
            "subcategory":"Furniture",
            "type":"Retail Goods"
        }
    ],
    "sg:phone":"+61 2 9624 1133",
    "sg:postcode":"2147",
    "sg:province":"NSW",
    "sg:tags":[
        "repair",
        "restoration"
    ],
    "wof:name":"Parker Furniture Refurbishment",
    "wof:placetype":"venue"
},
  "geometry": {"coordinates":[150.952835083,-33.772441864],"type":"Point"}
}