{
  "type": "Feature",
  "properties": {
    "addr:full":"Castletown Shoppingworld, Kings Rd Hyde Park QLD 4812",
    "addr:postcode":"4812",
    "addr:street":"Kings Rd",
    "iso:country":"AU",
    "sg:address":"Castletown Shoppingworld, Kings Rd",
    "sg:city":"Hyde Park",
    "sg:classifiers":[
        {
            "category":"Banks & Credit Unions",
            "subcategory":"Financial Services",
            "type":"Services"
        }
    ],
    "sg:phone":"+61 7 4772 1666",
    "sg:postcode":"4812",
    "sg:province":"QLD",
    "sg:tags":[
        "building",
        "society"
    ],
    "wof:name":"Bendigo Bank",
    "wof:placetype":"venue"
},
  "geometry": {"coordinates":[146.79182399999999,-19.278521],"type":"Point"}
}