{
  "type": "Feature",
  "properties": {
    "addr:full":"4 John La Salisbury SA 5108",
    "addr:housenumber":"4",
    "addr:postcode":"5108",
    "addr:street":"John La",
    "iso:country":"AU",
    "sg:address":"4 John La",
    "sg:city":"Salisbury",
    "sg:classifiers":[
        {
            "category":"Personal",
            "subcategory":"Tattoo Parlor",
            "type":"Services"
        }
    ],
    "sg:phone":"+61 8 8281 3330",
    "sg:postcode":"5108",
    "sg:province":"SA",
    "sg:tags":[
        "tattooing"
    ],
    "wof:name":"Tattoo Cave",
    "wof:placetype":"venue"
},
  "geometry": {"coordinates":[138.64369201700001,-34.7632789612],"type":"Point"}
}