{
  "type": "Feature",
  "properties": {
    "addr:full":"24 Cadell St Wondai QLD 4606",
    "addr:housenumber":"24",
    "addr:postcode":"4606",
    "addr:street":"Cadell St",
    "iso:country":"AU",
    "sg:address":"24 Cadell St",
    "sg:city":"Wondai",
    "sg:classifiers":[
        {
            "category":"Arena",
            "subcategory":"Sports Club",
            "type":"Entertainment"
        }
    ],
    "sg:phone":"+61 7 4168 5530",
    "sg:postcode":"4606",
    "sg:province":"QLD",
    "sg:tags":[
        "hunt",
        "racing"
    ],
    "wof:name":"South Burnett Race Club",
    "wof:placetype":"venue"
},
  "geometry": {"coordinates":[151.87434400000001,-26.322392],"type":"Point"}
}