{
  "type": "Feature",
  "properties": {
    "iso:country":"AU",
    "sg:address":"Shop 3, The Mall, Dunmore St",
    "sg:city":"Wentworthville",
    "sg:classifiers":[
        {
            "category":"Shopping",
            "subcategory":"Clothing, Apparel, & Fashions",
            "type":"Retail Goods"
        }
    ],
    "sg:phone":"+61 2 9896 5789",
    "sg:postcode":"2145",
    "sg:province":"NSW",
    "sg:tags":[
        "lady",
        "wear"
    ],
    "wof:name":"Noni- B-Fashions",
    "wof:placetype":"venue"
},
  "geometry": {"coordinates":[150.97108459500001,-33.8076248169],"type":"Point"}
}