{
  "type": "Feature",
  "properties": {
    "addr:full":"35 Smith St Charlestown NSW 2290",
    "addr:housenumber":"35",
    "addr:postcode":"2290",
    "addr:street":"Smith St",
    "iso:country":"AU",
    "sg:address":"35 Smith St",
    "sg:city":"Charlestown",
    "sg:classifiers":[
        {
            "category":"Real Estate",
            "subcategory":"Architect",
            "type":"Services"
        }
    ],
    "sg:phone":"+61 2 4942 5222",
    "sg:postcode":"2290",
    "sg:province":"NSW",
    "wof:name":"Seymour Rod",
    "wof:placetype":"venue"
},
  "geometry": {"coordinates":[151.69729614299999,-32.9638824463],"type":"Point"}
}