{
  "type": "Feature",
  "properties": {
    "iso:country":"AU",
    "sg:address":"Pudman St",
    "sg:city":"Boorowa",
    "sg:classifiers":[
        {
            "category":"Education",
            "subcategory":"School",
            "type":"Public Place"
        }
    ],
    "sg:phone":"+61 2 6385 3009",
    "sg:postcode":"2586",
    "sg:province":"NSW",
    "sg:tags":[
        "state",
        "-",
        "nsw"
    ],
    "wof:name":"Boorowa Central School",
    "wof:placetype":"venue"
},
  "geometry": {"coordinates":[148.72807312,-34.4379005432],"type":"Point"}
}