{
  "type": "Feature",
  "properties": {
    "addr:full":"155 Newbridge Rd Moorebank NSW 2170",
    "addr:housenumber":"155",
    "addr:postcode":"2170",
    "addr:street":"Newbridge Rd",
    "iso:country":"AU",
    "sg:address":"155 Newbridge Rd",
    "sg:city":"Moorebank",
    "sg:classifiers":[
        {
            "category":"Manufacturing",
            "subcategory":"Metals",
            "type":"Manufacturing & Wholesale Goods"
        }
    ],
    "sg:phone":"+61 2 9601 1475",
    "sg:postcode":"2170",
    "sg:province":"NSW",
    "sg:tags":[
        "sheet",
        "worker"
    ],
    "wof:name":"Moorebank Sheet Metal Pty Ltd",
    "wof:placetype":"venue"
},
  "geometry": {"coordinates":[150.93980407699999,-33.9297409058],"type":"Point"}
}