{
  "type": "Feature",
  "properties": {
    "iso:country":"AU",
    "sg:address":"26 Cyprus St",
    "sg:city":"Townsend",
    "sg:classifiers":[
        {
            "category":"Banks & Credit Unions",
            "subcategory":"Investment Brokerage",
            "type":"Services"
        }
    ],
    "sg:phone":"+61 1800 173 257",
    "sg:postcode":"2463",
    "sg:province":"NSW",
    "sg:tags":[
        "mechanical",
        "oil",
        "seal"
    ],
    "wof:name":"Paulmen Seals Australia Pty Ltd",
    "wof:placetype":"venue"
},
  "geometry": {"coordinates":[153.22201538100001,-29.4684486389],"type":"Point"}
}