{
  "type": "Feature",
  "properties": {
    "addr:full":"90 Wallendoon St Cootamundra NSW 2590",
    "addr:housenumber":"90",
    "addr:postcode":"2590",
    "addr:street":"Wallendoon St",
    "iso:country":"AU",
    "sg:address":"90 Wallendoon St",
    "sg:city":"Cootamundra",
    "sg:classifiers":[
        {
            "category":"Real Estate",
            "subcategory":"Surveying",
            "type":"Services"
        }
    ],
    "sg:phone":"+61 2 6942 3395",
    "sg:postcode":"2590",
    "sg:province":"NSW",
    "sg:tags":[
        "surveyor",
        "land"
    ],
    "wof:name":"Pengelly Ian",
    "wof:placetype":"venue"
},
  "geometry": {"coordinates":[148.02804565400001,-34.6411743164],"type":"Point"}
}