{
  "type": "Feature",
  "properties": {
    "addr:full":"Unit 14 & 15 1904 Beach Rd Malaga WA 6090",
    "addr:housenumber":"&;1904",
    "addr:postcode":"6090",
    "addr:street":"15;Beach Rd",
    "iso:country":"AU",
    "sg:address":"Unit 14 & 15 1904 Beach Rd",
    "sg:city":"Malaga",
    "sg:classifiers":[
        {
            "category":"Building & Trades",
            "subcategory":"Cleaning & Sanitation",
            "type":"Services"
        }
    ],
    "sg:phone":"+61 8 9209 2855",
    "sg:postcode":"6090",
    "sg:province":"WA",
    "sg:tags":[
        "cleaner",
        "repairer",
        "roof"
    ],
    "wof:name":"Centurion Roof Coatings",
    "wof:placetype":"venue"
},
  "geometry": {"coordinates":[115.887252808,-31.8555831909],"type":"Point"}
}