{
  "type": "Feature",
  "properties": {
    "iso:country":"AU",
    "sg:address":"Old Gympie Rd",
    "sg:city":"Mooloolah",
    "sg:classifiers":[
        {
            "category":"Autos & Motor Vehicles",
            "subcategory":"Auto Supplies",
            "type":"Retail Goods"
        }
    ],
    "sg:phone":"+61 7 5494 7402",
    "sg:postcode":"4553",
    "sg:province":"QLD",
    "sg:tags":[
        "camper-trailers",
        "caravan",
        "equipment"
    ],
    "wof:name":"The Wandera Trailers & Campers",
    "wof:placetype":"venue"
},
  "geometry": {"coordinates":[152.97392300000001,-26.754074],"type":"Point"}
}