{
  "type": "Feature",
  "properties": {
    "iso:country":"AU",
    "sg:address":"Nelson Bay Rd",
    "sg:city":"Salt Ash",
    "sg:classifiers":[
        {
            "category":"Education",
            "subcategory":"School",
            "type":"Public Place"
        }
    ],
    "sg:phone":"+61 2 4982 6251",
    "sg:postcode":"2318",
    "sg:province":"NSW",
    "sg:tags":[
        "state",
        "-",
        "nsw"
    ],
    "wof:name":"Salt Ash Public",
    "wof:placetype":"venue"
},
  "geometry": {"coordinates":[151.899124,-32.791637],"type":"Point"}
}