{
  "type": "Feature",
  "properties": {
    "iso:country":"AU",
    "sg:address":"2 Mathew St",
    "sg:city":"Cessnock",
    "sg:classifiers":[
        {
            "category":"Building & Trades",
            "subcategory":"Plumbing",
            "type":"Services"
        }
    ],
    "sg:phone":"+61 2 4991 1290",
    "sg:postcode":"2325",
    "sg:province":"NSW",
    "sg:tags":[
        "plumber",
        "gasfitters"
    ],
    "wof:name":"Nightingale Brian",
    "wof:placetype":"venue"
},
  "geometry": {"coordinates":[151.35426330600001,-32.8309898376],"type":"Point"}
}