{
  "type": "Feature",
  "properties": {
    "addr:full":"41 Belford Ave Bateau Bay NSW 2261",
    "addr:housenumber":"41",
    "addr:postcode":"2261",
    "addr:street":"Belford Ave",
    "iso:country":"AU",
    "sg:address":"41 Belford Ave",
    "sg:city":"Bateau Bay",
    "sg:classifiers":[
        {
            "category":"Building & Trades",
            "subcategory":"Construction",
            "type":"Services"
        }
    ],
    "sg:phone":"+61 2 4333 6477",
    "sg:postcode":"2261",
    "sg:province":"NSW",
    "sg:tags":[
        "roof"
    ],
    "wof:name":"Pullin Hadley F",
    "wof:placetype":"venue"
},
  "geometry": {"coordinates":[151.46383700000001,-33.383865],"type":"Point"}
}