{
  "type": "Feature",
  "properties": {
    "addr:full":"8 Mccartney St Liverpool NSW 2170",
    "addr:housenumber":"8",
    "addr:postcode":"2170",
    "addr:street":"Mccartney St",
    "iso:country":"AU",
    "sg:address":"8 Mccartney St",
    "sg:city":"Liverpool",
    "sg:classifiers":[
        {
            "category":"Professional",
            "subcategory":"Art Services",
            "type":"Services"
        }
    ],
    "sg:phone":"+61 402 960 862",
    "sg:postcode":"2170",
    "sg:province":"NSW",
    "sg:tags":[
        "decorator",
        "painter"
    ],
    "wof:name":"A1 Soltani Painting & Decorating",
    "wof:placetype":"venue"
},
  "geometry": {"coordinates":[150.92628479000001,-33.9105796814],"type":"Point"}
}