{
  "type": "Feature",
  "properties": {
    "iso:country":"AU",
    "sg:address":"39 Jardine St",
    "sg:city":"Kingston",
    "sg:classifiers":[
        {
            "category":"Banks & Credit Unions",
            "subcategory":"Investment Brokerage",
            "type":"Services"
        }
    ],
    "sg:phone":"+61 2 6124 4888",
    "sg:postcode":"2604",
    "sg:province":"ACT",
    "sg:tags":[
        "management",
        "property"
    ],
    "wof:name":"Elders Real Estate",
    "wof:placetype":"venue"
},
  "geometry": {"coordinates":[149.14227294899999,-35.3156242371],"type":"Point"}
}