{
  "type": "Feature",
  "properties": {
    "iso:country":"AU",
    "sg:address":"12 Talbot St",
    "sg:city":"Fingal",
    "sg:classifiers":[
        {
            "category":"Fast Food",
            "type":"Food & Drink"
        }
    ],
    "sg:phone":"+61 3 6374 2151",
    "sg:postcode":"7214",
    "sg:province":"TAS",
    "sg:tags":[
        "away",
        "take"
    ],
    "wof:name":"Fingal Takeaways",
    "wof:placetype":"venue"
},
  "geometry": {"coordinates":[147.96910099999999,-41.6385],"type":"Point"}
}