{
  "type": "Feature",
  "properties": {
    "addr:full":"32 Coachwood Drv Unanderra NSW 2526",
    "addr:housenumber":"32",
    "addr:postcode":"2526",
    "addr:street":"Coachwood Drv",
    "iso:country":"AU",
    "sg:address":"32 Coachwood Drv",
    "sg:city":"Unanderra",
    "sg:classifiers":[
        {
            "category":"Professional",
            "type":"Services"
        }
    ],
    "sg:phone":"+61 2 4271 5677",
    "sg:postcode":"2526",
    "sg:province":"NSW",
    "sg:tags":[
        "overlocking",
        "rug",
        "carpet"
    ],
    "wof:name":"Unanderra Carpet Overlockers",
    "wof:placetype":"venue"
},
  "geometry": {"coordinates":[150.83065795900001,-34.4505691528],"type":"Point"}
}