{
  "type": "Feature",
  "properties": {
    "addr:full":"690 Rowella Rd Rowella TAS 7270",
    "addr:housenumber":"690",
    "addr:postcode":"7270",
    "addr:street":"Rowella Rd",
    "iso:country":"AU",
    "sg:address":"690 Rowella Rd",
    "sg:city":"Rowella",
    "sg:classifiers":[
        {
            "category":"Wholesale",
            "subcategory":"Non-durable Goods",
            "type":"Manufacturing & Wholesale Goods"
        }
    ],
    "sg:phone":"+61 3 6394 7559",
    "sg:postcode":"7270",
    "sg:province":"TAS",
    "sg:tags":[
        "wholesaler",
        "mfrs",
        "cosmetic"
    ],
    "wof:name":"Lavender House",
    "wof:placetype":"venue"
},
  "geometry": {"coordinates":[146.91380310100001,-41.177570343],"type":"Point"}
}