{
  "type": "Feature",
  "properties": {
    "iso:country":"AU",
    "sg:address":"Suite 1, 200 Maroubra Rd",
    "sg:city":"Maroubra",
    "sg:classifiers":[
        {
            "category":"Professional",
            "subcategory":"Employment Agencies",
            "type":"Services"
        }
    ],
    "sg:phone":"+61 2 9314 2165",
    "sg:postcode":"2035",
    "sg:province":"NSW",
    "wof:name":"Jobfind Centre",
    "wof:placetype":"venue"
},
  "geometry": {"coordinates":[151.24101257300001,-33.9416656494],"type":"Point"}
}