{
  "type": "Feature",
  "properties": {
    "addr:full":"27 Harbour St Mosman NSW 2088",
    "addr:housenumber":"27",
    "addr:postcode":"2088",
    "addr:street":"Harbour St",
    "iso:country":"AU",
    "sg:address":"27 Harbour St",
    "sg:city":"Mosman",
    "sg:classifiers":[
        {
            "category":"Utilities",
            "subcategory":"Electric",
            "type":"Services"
        }
    ],
    "sg:phone":"+61 2 9953 9595",
    "sg:postcode":"2088",
    "sg:province":"NSW",
    "sg:tags":[
        "electrical",
        "contractor"
    ],
    "wof:name":"Mosman Electrical",
    "wof:placetype":"venue"
},
  "geometry": {"coordinates":[151.23919677699999,-33.8267631531],"type":"Point"}
}