{
  "type": "Feature",
  "properties": {
    "iso:country":"AU",
    "sg:address":"U6/ 89 Jedda Rd",
    "sg:city":"Prestons",
    "sg:classifiers":[
        {
            "category":"Building & Trades",
            "subcategory":"Construction",
            "type":"Services"
        }
    ],
    "sg:phone":"+61 2 9608 6922",
    "sg:postcode":"2170",
    "sg:province":"NSW",
    "sg:tags":[
        "contractor"
    ],
    "wof:name":"Elamond Homes",
    "wof:placetype":"venue"
},
  "geometry": {"coordinates":[150.87721252399999,-33.9331359863],"type":"Point"}
}