{
  "type": "Feature",
  "properties": {
    "addr:full":"17 Lucas St North Rockhampton QLD 4701",
    "addr:housenumber":"17",
    "addr:postcode":"4701",
    "addr:street":"Lucas St North",
    "iso:country":"AU",
    "sg:address":"17 Lucas St",
    "sg:city":"North Rockhampton",
    "sg:classifiers":[
        {
            "category":"Arts & Performance",
            "subcategory":"Music",
            "type":"Entertainment"
        }
    ],
    "sg:phone":"+61 437 068 518",
    "sg:postcode":"4701",
    "sg:province":"QLD",
    "sg:tags":[
        "mobile",
        "jockey",
        "disc"
    ],
    "wof:name":"John Kift",
    "wof:placetype":"venue"
},
  "geometry": {"coordinates":[150.51983642600001,-23.3641548157],"type":"Point"}
}