{
  "type": "Feature",
  "properties": {
    "iso:country":"AU",
    "sg:address":"Suite 6, 2- 4 Henley Beach Rd",
    "sg:city":"Mile End",
    "sg:classifiers":[
        {
            "category":"Education",
            "subcategory":"School",
            "type":"Public Place"
        }
    ],
    "sg:phone":"+61 8 8351 9322",
    "sg:postcode":"5031",
    "sg:province":"SA",
    "sg:tags":[
        "co-educational"
    ],
    "wof:name":"Sunrise Christian School Inc.",
    "wof:placetype":"venue"
},
  "geometry": {"coordinates":[138.57899475100001,-34.9231109619],"type":"Point"}
}