{
  "type": "Feature",
  "properties": {
    "iso:country":"AU",
    "sg:address":"54 MacAlister St",
    "sg:city":"Murgon",
    "sg:classifiers":[
        {
            "category":"Retail",
            "subcategory":"Auto Rental",
            "type":"Services"
        }
    ],
    "sg:phone":"+61 1300 300 907",
    "sg:postcode":"4605",
    "sg:province":"QLD",
    "sg:tags":[
        "car",
        "hire",
        "minibus"
    ],
    "wof:name":"Thrifty",
    "wof:placetype":"venue"
},
  "geometry": {"coordinates":[151.941147,-26.244234],"type":"Point"}
}