{
  "type": "Feature",
  "properties": {
    "addr:full":"7 Harris St Wallsend NSW 2287",
    "addr:housenumber":"7",
    "addr:postcode":"2287",
    "addr:street":"Harris St",
    "iso:country":"AU",
    "sg:address":"7 Harris St",
    "sg:city":"Wallsend",
    "sg:classifiers":[
        {
            "category":"Professional",
            "subcategory":"Accounting & Tax Preparation",
            "type":"Services"
        }
    ],
    "sg:phone":"+61 2 4950 2533",
    "sg:postcode":"2287",
    "sg:province":"NSW",
    "sg:tags":[
        "consultant",
        "taxation"
    ],
    "wof:name":"Hunter Tax Services",
    "wof:placetype":"venue"
},
  "geometry": {"coordinates":[151.61776733400001,-32.9207305908],"type":"Point"}
}