{
  "type": "Feature",
  "properties": {
    "addr:full":"304 Alice St Maryborough QLD 4650",
    "addr:housenumber":"304",
    "addr:postcode":"4650",
    "addr:street":"Alice St",
    "iso:country":"AU",
    "sg:address":"304 Alice St",
    "sg:city":"Maryborough",
    "sg:classifiers":[
        {
            "category":"Retail",
            "subcategory":"Auto Rental",
            "type":"Services"
        }
    ],
    "sg:phone":"+61 7 4122 1211",
    "sg:postcode":"4650",
    "sg:province":"QLD",
    "sg:tags":[
        "car",
        "hire",
        "minibus"
    ],
    "wof:name":"Thrifty",
    "wof:placetype":"venue"
},
  "geometry": {"coordinates":[152.697723,-25.53953],"type":"Point"}
}