{
  "type": "Feature",
  "properties": {
    "addr:full":"Unit 2 28 Hutchinson St Burleigh Heads QLD 4220",
    "addr:housenumber":"28",
    "addr:postcode":"4220",
    "addr:street":"Hutchinson St",
    "iso:country":"AU",
    "sg:address":"Unit 2 28 Hutchinson St",
    "sg:city":"Burleigh Heads",
    "sg:classifiers":[
        {
            "category":"Home & Garden",
            "subcategory":"Building Materials",
            "type":"Retail Goods"
        }
    ],
    "sg:phone":"+61 7 5593 7467",
    "sg:postcode":"4220",
    "sg:province":"QLD",
    "sg:tags":[
        "insect",
        "screen"
    ],
    "wof:name":"Freedom Retractable Screens",
    "wof:placetype":"venue"
},
  "geometry": {"coordinates":[153.42283630399999,-28.1075363159],"type":"Point"}
}