{
  "type": "Feature",
  "properties": {
    "iso:country":"AU",
    "sg:address":"31 Elizabeth St",
    "sg:city":"Bayswater",
    "sg:classifiers":[
        {
            "category":"Health Services",
            "subcategory":"Nursing And Care Facility",
            "type":"Services"
        }
    ],
    "sg:phone":"+61 3 9720 3711",
    "sg:postcode":"3153",
    "sg:province":"VIC",
    "sg:tags":[
        "home"
    ],
    "wof:name":"Tabulam Nursing Home",
    "wof:placetype":"venue"
},
  "geometry": {"coordinates":[145.264404297,-37.8546447754],"type":"Point"}
}