{
  "type": "Feature",
  "properties": {
    "addr:full":"Shop 3/116- 120 Glenferrie Rd Malvern VIC 3144",
    "addr:housenumber":"shop 3 / 116 120",
    "addr:postcode":"3144",
    "addr:street":"Glenferrie Rd",
    "iso:country":"AU",
    "sg:address":"Shop 3/116- 120 Glenferrie Rd",
    "sg:city":"Malvern",
    "sg:classifiers":[
        {
            "category":"Shopping",
            "subcategory":"Clothing, Apparel, & Fashions",
            "type":"Retail Goods"
        }
    ],
    "sg:phone":"+61 3 9500 2147",
    "sg:postcode":"3144",
    "sg:province":"VIC",
    "sg:tags":[
        "lady",
        "wear"
    ],
    "wof:name":"Esse",
    "wof:placetype":"venue"
},
  "geometry": {"coordinates":[145.02862548799999,-37.8616828918],"type":"Point"}
}