{
  "type": "Feature",
  "properties": {
    "iso:country":"AU",
    "sg:address":"1 Farrer House, Swift St",
    "sg:city":"Albury",
    "sg:classifiers":[
        {
            "category":"Banks & Credit Unions",
            "subcategory":"Investment Brokerage",
            "type":"Services"
        }
    ],
    "sg:phone":"+61 2 6041 2635",
    "sg:postcode":"2640",
    "sg:province":"NSW",
    "sg:tags":[
        "finance",
        "broker"
    ],
    "wof:name":"Aldonga Finance Brokers Pty Ltd",
    "wof:placetype":"venue"
},
  "geometry": {"coordinates":[146.916381836,-36.0786628723],"type":"Point"}
}