{
  "type": "Feature",
  "properties": {
    "iso:country":"AU",
    "sg:address":"42 Maryland St",
    "sg:city":"Stanthorpe",
    "sg:classifiers":[
        {
            "category":"Autos & Motor Vehicles",
            "subcategory":"Automobile Sales",
            "type":"Retail Goods"
        }
    ],
    "sg:phone":"+61 7 4681 2200",
    "sg:postcode":"4380",
    "sg:province":"QLD",
    "sg:tags":[
        "car",
        "new"
    ],
    "wof:name":"Central Motors",
    "wof:placetype":"venue"
},
  "geometry": {"coordinates":[151.933685,-28.656113],"type":"Point"}
}