{
  "type": "Feature",
  "properties": {
    "addr:full":"378 Newell Hwy Moree NSW 2400",
    "addr:housenumber":"378",
    "addr:postcode":"2400",
    "addr:street":"Newell Hwy",
    "iso:country":"AU",
    "sg:address":"378 Newell Hwy",
    "sg:city":"Moree",
    "sg:classifiers":[
        {
            "category":"Travel",
            "subcategory":"Hotels & Motels",
            "type":"Entertainment"
        }
    ],
    "sg:phone":"+61 2 6752 3233",
    "sg:postcode":"2400",
    "sg:province":"NSW",
    "wof:name":"Jackaroo Motor Inn",
    "wof:placetype":"venue"
},
  "geometry": {"coordinates":[149.842697144,-29.4699363708],"type":"Point"}
}