{
  "type": "Feature",
  "properties": {
    "addr:full":"1 Belmore St Yarrawonga VIC 3730",
    "addr:housenumber":"1",
    "addr:postcode":"3730",
    "addr:street":"Belmore St",
    "iso:country":"AU",
    "sg:address":"1 Belmore St",
    "sg:city":"Yarrawonga",
    "sg:classifiers":[
        {
            "category":"Travel",
            "subcategory":"Hotels & Motels",
            "type":"Entertainment"
        }
    ],
    "sg:phone":"+61 3 5744 3839",
    "sg:postcode":"3730",
    "sg:province":"VIC",
    "sg:tags":[
        "accommodation"
    ],
    "wof:name":"Criterion Hotel",
    "wof:placetype":"venue"
},
  "geometry": {"coordinates":[146.00416564899999,-36.008895874],"type":"Point"}
}