{
  "type": "Feature",
  "properties": {
    "addr:full":"92 Gibson St Jindera NSW 2642",
    "addr:housenumber":"92",
    "addr:postcode":"2642",
    "addr:street":"Gibson St",
    "iso:country":"AU",
    "sg:address":"92 Gibson St",
    "sg:city":"Jindera",
    "sg:classifiers":[
        {
            "category":"Building & Trades",
            "subcategory":"Construction",
            "type":"Services"
        }
    ],
    "sg:phone":"+61 2 6026 3435",
    "sg:postcode":"2642",
    "sg:province":"NSW",
    "sg:tags":[
        "plasterboard",
        "plasterer",
        "fixer"
    ],
    "wof:name":"R & J Plasterers Pty Ltd",
    "wof:placetype":"venue"
},
  "geometry": {"coordinates":[146.890823364,-35.9528427124],"type":"Point"}
}