{
  "type": "Feature",
  "properties": {
    "iso:country":"AU",
    "sg:address":"14 Vale Rd",
    "sg:city":"Bathurst",
    "sg:classifiers":[
        {
            "category":"Commercial Area",
            "type":"Public Place"
        }
    ],
    "sg:phone":"+61 2 6331 1570",
    "sg:postcode":"2795",
    "sg:province":"NSW",
    "sg:tags":[
        "heavy",
        "carrier"
    ],
    "wof:name":"Greg Bayliss Brick Supplies",
    "wof:placetype":"venue"
},
  "geometry": {"coordinates":[149.56956481899999,-33.4663887024],"type":"Point"}
}