{
  "type": "Feature",
  "properties": {
    "addr:full":"81 Cairns Rd Camira QLD 4300",
    "addr:housenumber":"81",
    "addr:postcode":"4300",
    "addr:street":"Cairns Rd",
    "iso:country":"AU",
    "sg:address":"81 Cairns Rd",
    "sg:city":"Camira",
    "sg:classifiers":[
        {
            "category":"Building & Trades",
            "subcategory":"Cleaning & Sanitation",
            "type":"Services"
        }
    ],
    "sg:phone":"+61 7 3288 2752",
    "sg:postcode":"4300",
    "sg:province":"QLD",
    "sg:tags":[
        "industrial",
        "commercial",
        "contractor"
    ],
    "wof:name":"Hunter Felstead Enterprises Pty Ltd",
    "wof:placetype":"venue"
},
  "geometry": {"coordinates":[152.91018676799999,-27.6302776337],"type":"Point"}
}