{
  "type": "Feature",
  "properties": {
    "addr:full":"32 Wells Rd Frankston VIC 3199",
    "addr:housenumber":"32",
    "addr:postcode":"3199",
    "addr:street":"Wells Rd",
    "iso:country":"AU",
    "sg:address":"32 Wells Rd",
    "sg:city":"Frankston",
    "sg:classifiers":[
        {
            "category":"Home & Garden",
            "subcategory":"Hardware",
            "type":"Retail Goods"
        }
    ],
    "sg:phone":"+61 3 9786 6666",
    "sg:postcode":"3199",
    "sg:province":"VIC",
    "sg:tags":[
        "plumber",
        "supply"
    ],
    "wof:name":"Tradelink Plumbing Centres",
    "wof:placetype":"venue"
},
  "geometry": {"coordinates":[145.13438415499999,-38.1229248047],"type":"Point"}
}