{
  "type": "Feature",
  "properties": {
    "iso:country":"AU",
    "sg:address":"9/ 10 Clarice Rd",
    "sg:city":"Box Hill South",
    "sg:classifiers":[
        {
            "category":"Communications",
            "type":"Services"
        }
    ],
    "sg:phone":"+61 3 9898 7064",
    "sg:postcode":"3128",
    "sg:province":"VIC",
    "sg:tags":[
        "public",
        "system",
        "address"
    ],
    "wof:name":"Lighting Lab",
    "wof:placetype":"venue"
},
  "geometry": {"coordinates":[145.133636475,-37.8356895447],"type":"Point"}
}