{
  "type": "Feature",
  "properties": {
    "iso:country":"AU",
    "sg:address":"29 Camelot St",
    "sg:city":"Carine",
    "sg:classifiers":[
        {
            "category":"Professional",
            "subcategory":"Detective & Security Services",
            "type":"Services"
        }
    ],
    "sg:phone":"+61 8 9448 9145",
    "sg:postcode":"6020",
    "sg:province":"WA",
    "sg:tags":[
        "consultant",
        "system"
    ],
    "wof:name":"Corcoran Steve Security Electronic Surveillance",
    "wof:placetype":"venue"
},
  "geometry": {"coordinates":[115.796737671,-31.8540630341],"type":"Point"}
}