{
  "type": "Feature",
  "properties": {
    "addr:full":"75 Fairy Dell Rd Monbulk VIC 3793",
    "addr:housenumber":"75",
    "addr:postcode":"3793",
    "addr:street":"Fairy Dell Rd",
    "iso:country":"AU",
    "sg:address":"75 Fairy Dell Rd",
    "sg:city":"Monbulk",
    "sg:classifiers":[
        {
            "category":"Farming",
            "subcategory":"Nursery",
            "type":"Manufacturing & Wholesale Goods"
        }
    ],
    "sg:phone":"+61 3 9756 6530",
    "sg:postcode":"3793",
    "sg:province":"VIC",
    "wof:name":"Monbulk Rose Farm",
    "wof:placetype":"venue"
},
  "geometry": {"coordinates":[145.42137145999999,-37.8973999023],"type":"Point"}
}