{
  "type": "Feature",
  "properties": {
    "addr:full":"102 West St Glenroy VIC 3046",
    "addr:housenumber":"102",
    "addr:postcode":"3046",
    "addr:street":"West St",
    "iso:country":"AU",
    "sg:address":"102 West St",
    "sg:city":"Glenroy",
    "sg:classifiers":[
        {
            "category":"Fast Food",
            "type":"Food & Drink"
        }
    ],
    "sg:phone":"+61 3 9306 7580",
    "sg:postcode":"3046",
    "sg:province":"VIC",
    "sg:tags":[
        "away",
        "take"
    ],
    "wof:name":"West Street Seafoods",
    "wof:placetype":"venue"
},
  "geometry": {"coordinates":[144.93824768100001,-37.7088775635],"type":"Point"}
}