{
  "type": "Feature",
  "properties": {
    "iso:country":"AU",
    "sg:address":"121 Errol St",
    "sg:city":"North Melbourne",
    "sg:classifiers":[
        {
            "category":"Autos & Motor Vehicles",
            "subcategory":"Automobile Sales",
            "type":"Retail Goods"
        }
    ],
    "sg:phone":"+61 3 9328 2351",
    "sg:postcode":"3051",
    "sg:province":"VIC",
    "sg:tags":[
        "car",
        "used"
    ],
    "wof:name":"Monte Carlo Motors",
    "wof:placetype":"venue"
},
  "geometry": {"coordinates":[144.94964599599999,-37.8019523621],"type":"Point"}
}