{
  "type": "Feature",
  "properties": {
    "addr:full":"108a Elimatta Rd Mona Vale NSW 2103",
    "addr:housenumber":"108a",
    "addr:postcode":"2103",
    "addr:street":"Elimatta Rd",
    "iso:country":"AU",
    "sg:address":"108a Elimatta Rd",
    "sg:city":"Mona Vale",
    "sg:classifiers":[
        {
            "category":"Building & Trades",
            "subcategory":"Plumbing",
            "type":"Services"
        }
    ],
    "sg:phone":"+61 418 211 634",
    "sg:postcode":"2103",
    "sg:province":"NSW",
    "sg:tags":[
        "plumber",
        "gasfitters"
    ],
    "wof:name":"Mulligan & Collett Plumbing",
    "wof:placetype":"venue"
},
  "geometry": {"coordinates":[151.29896545400001,-33.6819343567],"type":"Point"}
}