{
  "type": "Feature",
  "properties": {
    "addr:full":"4a Palings Crt Nerang QLD 4211",
    "addr:housenumber":"4a",
    "addr:postcode":"4211",
    "addr:street":"Palings Crt",
    "iso:country":"AU",
    "sg:address":"4a Palings Crt",
    "sg:city":"Nerang",
    "sg:classifiers":[
        {
            "category":"Retail",
            "subcategory":"Storage",
            "type":"Services"
        }
    ],
    "sg:phone":"+61 7 5596 0787",
    "sg:postcode":"4211",
    "sg:province":"QLD",
    "sg:tags":[
        "removal",
        "furniture"
    ],
    "wof:name":"Nerang Removals",
    "wof:placetype":"venue"
},
  "geometry": {"coordinates":[153.34022522000001,-27.9804210663],"type":"Point"}
}