{
  "type": "Feature",
  "properties": {
    "addr:full":"84 Daws Rd Edwardstown SA 5039",
    "addr:housenumber":"84",
    "addr:postcode":"5039",
    "addr:street":"Daws Rd",
    "iso:country":"AU",
    "sg:address":"84 Daws Rd",
    "sg:city":"Edwardstown",
    "sg:classifiers":[
        {
            "category":"Home & Garden",
            "subcategory":"Carpets & Floor Coverings",
            "type":"Retail Goods"
        }
    ],
    "sg:phone":"+61 8 8276 7566",
    "sg:postcode":"5039",
    "sg:province":"SA",
    "sg:tags":[
        "tile",
        "wall"
    ],
    "wof:name":"South Pacific Ceramic Tiles",
    "wof:placetype":"venue"
},
  "geometry": {"coordinates":[138.57241821299999,-34.9927368164],"type":"Point"}
}