{
  "type": "Feature",
  "properties": {
    "addr:full":"10 Melrose St Homebush NSW 2140",
    "addr:housenumber":"10",
    "addr:postcode":"2140",
    "addr:street":"Melrose St",
    "iso:country":"AU",
    "sg:address":"10 Melrose St",
    "sg:city":"Homebush",
    "sg:classifiers":[
        {
            "category":"Professional",
            "subcategory":"Detective & Security Services",
            "type":"Services"
        }
    ],
    "sg:phone":"+61 2 9763 1800",
    "sg:postcode":"2140",
    "sg:province":"NSW",
    "sg:tags":[
        "consultant",
        "system"
    ],
    "wof:name":"Sydney Building Technology Brokers",
    "wof:placetype":"venue"
},
  "geometry": {"coordinates":[151.08555602999999,-33.8697280884],"type":"Point"}
}