{
  "type": "Feature",
  "properties": {
    "addr:full":"6 Wattle Pl Sandy Beach NSW 2456",
    "addr:housenumber":"6",
    "addr:postcode":"2456",
    "addr:street":"Wattle Pl",
    "iso:country":"AU",
    "sg:address":"6 Wattle Pl",
    "sg:city":"Sandy Beach",
    "sg:classifiers":[
        {
            "category":"Manufacturing",
            "subcategory":"Wood Products",
            "type":"Manufacturing & Wholesale Goods"
        }
    ],
    "sg:phone":"+61 2 6656 1404",
    "sg:postcode":"2456",
    "sg:province":"NSW",
    "sg:tags":[
        "polisher",
        "french"
    ],
    "wof:name":"Burgess Greg",
    "wof:placetype":"venue"
},
  "geometry": {"coordinates":[153.19035299999999,-30.146345],"type":"Point"}
}