{
  "type": "Feature",
  "properties": {
    "addr:full":"27 Hincksman St Queanbeyan NSW 2620",
    "addr:housenumber":"27",
    "addr:postcode":"2620",
    "addr:street":"Hincksman St",
    "iso:country":"AU",
    "sg:address":"27 Hincksman St",
    "sg:city":"Queanbeyan",
    "sg:classifiers":[
        {
            "category":"Wholesale",
            "subcategory":"Drugs",
            "type":"Manufacturing & Wholesale Goods"
        }
    ],
    "sg:phone":"+61 2 6297 5622",
    "sg:postcode":"2620",
    "sg:province":"NSW",
    "sg:tags":[
        "wholesaler",
        "pharmaceutical",
        "product",
        "mfrs"
    ],
    "wof:name":"API (Canberra) Pty Ltd",
    "wof:placetype":"venue"
},
  "geometry": {"coordinates":[149.241531372,-35.3410224915],"type":"Point"}
}