{
  "type": "Feature",
  "properties": {
    "addr:full":"Shop 8/ 82 Marina Blv Ocean Reef WA 6027",
    "addr:housenumber":"shop 8 / 82",
    "addr:postcode":"6027",
    "addr:street":"Marina Blv",
    "iso:country":"AU",
    "sg:address":"Shop 8/ 82 Marina Blv",
    "sg:city":"Ocean Reef",
    "sg:classifiers":[
        {
            "category":"Fast Food",
            "type":"Food & Drink"
        }
    ],
    "sg:phone":"+61 8 9402 4333",
    "sg:postcode":"6027",
    "sg:province":"WA",
    "sg:tags":[
        "away",
        "take"
    ],
    "wof:name":"Ocean Reef Fish & Chips",
    "wof:placetype":"venue"
},
  "geometry": {"coordinates":[115.740829468,-31.7661933899],"type":"Point"}
}