{
  "type": "Feature",
  "properties": {
    "addr:full":"26 Alkoomie St Wynnum QLD 4178",
    "addr:housenumber":"26",
    "addr:postcode":"4178",
    "addr:street":"Alkoomie St",
    "iso:country":"AU",
    "sg:address":"26 Alkoomie St",
    "sg:city":"Wynnum",
    "sg:classifiers":[
        {
            "category":"Building & Trades",
            "subcategory":"Plumbing",
            "type":"Services"
        }
    ],
    "sg:phone":"+61 7 3396 2804",
    "sg:postcode":"4178",
    "sg:province":"QLD",
    "sg:tags":[
        "plumber",
        "gasfitters"
    ],
    "wof:name":"Chris Beaver Plumbing",
    "wof:placetype":"venue"
},
  "geometry": {"coordinates":[153.171798706,-27.4348278046],"type":"Point"}
}