{
  "type": "Feature",
  "properties": {
    "addr:full":"52 The Straight Rd Mulgoa NSW 2745",
    "addr:housenumber":"52",
    "addr:postcode":"2745",
    "addr:street":"The Straight Rd",
    "iso:country":"AU",
    "sg:address":"52 The Straight Rd",
    "sg:city":"Mulgoa",
    "sg:classifiers":[
        {
            "category":"Professional",
            "type":"Services"
        }
    ],
    "sg:phone":"+61 2 4773 8841",
    "sg:postcode":"2745",
    "sg:province":"NSW",
    "sg:tags":[
        "transport"
    ],
    "wof:name":"Azz-Tran Haulage Contractors",
    "wof:placetype":"venue"
},
  "geometry": {"coordinates":[150.65057373100001,-33.840461731],"type":"Point"}
}