{
  "type": "Feature",
  "properties": {
    "iso:country":"AU",
    "sg:address":"8 Garrick Rd",
    "sg:city":"St Ives",
    "sg:classifiers":[
        {
            "category":"Real Estate",
            "subcategory":"Real Estate Services",
            "type":"Services"
        }
    ],
    "sg:phone":"+61 2 9144 6199",
    "sg:postcode":"2075",
    "sg:province":"NSW",
    "sg:tags":[
        "consultant",
        "property"
    ],
    "wof:name":"Tyler Retail Services Pty Ltd",
    "wof:placetype":"venue"
},
  "geometry": {"coordinates":[151.167068481,-33.7253379822],"type":"Point"}
}