{
  "type": "Feature",
  "properties": {
    "addr:full":"41 Lonsdale St Dandenong VIC 3175",
    "addr:housenumber":"41",
    "addr:postcode":"3175",
    "addr:street":"Lonsdale St",
    "iso:country":"AU",
    "sg:address":"41 Lonsdale St",
    "sg:city":"Dandenong",
    "sg:classifiers":[
        {
            "category":"Autos & Motor Vehicles",
            "subcategory":"Automobile Sales",
            "type":"Retail Goods"
        }
    ],
    "sg:phone":"+61 3 9771 9400",
    "sg:postcode":"3175",
    "sg:province":"VIC",
    "sg:tags":[
        "car",
        "new"
    ],
    "wof:name":"Dandenong Proton",
    "wof:placetype":"venue"
},
  "geometry": {"coordinates":[145.21449279800001,-37.9907417297],"type":"Point"}
}