{
  "type": "Feature",
  "properties": {
    "addr:full":"77 Yalwal Rd Nowra NSW 2541",
    "addr:housenumber":"77",
    "addr:postcode":"2541",
    "addr:street":"Yalwal Rd",
    "iso:country":"AU",
    "sg:address":"77 Yalwal Rd",
    "sg:city":"Nowra",
    "sg:classifiers":[
        {
            "category":"Professional",
            "subcategory":"Art Services",
            "type":"Services"
        }
    ],
    "sg:phone":"+61 2 4423 3160",
    "sg:postcode":"2541",
    "sg:province":"NSW",
    "sg:tags":[
        "decorator",
        "painter"
    ],
    "wof:name":"George C M & K A",
    "wof:placetype":"venue"
},
  "geometry": {"coordinates":[150.58741760300001,-34.8919525146],"type":"Point"}
}