{
  "type": "Feature",
  "properties": {
    "addr:full":"Coniston St Diamond Creek VIC 3089",
    "addr:postcode":"3089",
    "addr:street":"Coniston St",
    "iso:country":"AU",
    "sg:address":"Coniston St",
    "sg:city":"Diamond Creek",
    "sg:classifiers":[
        {
            "category":"Education",
            "subcategory":"Kindergarten",
            "type":"Public Place"
        }
    ],
    "sg:phone":"+61 3 9438 2663",
    "sg:postcode":"3089",
    "sg:province":"VIC",
    "sg:tags":[
        "pre-schools"
    ],
    "wof:name":"Diamond Creek East Pre-school",
    "wof:placetype":"venue"
},
  "geometry": {"coordinates":[145.160797,-37.677128],"type":"Point"}
}