{
  "type": "Feature",
  "properties": {
    "addr:full":"2 Warrego Hwy Dulacca QLD 4425",
    "addr:housenumber":"2",
    "addr:postcode":"4425",
    "addr:street":"Warrego Hwy",
    "iso:country":"AU",
    "sg:address":"2 Warrego Hwy",
    "sg:city":"Dulacca",
    "sg:classifiers":[
        {
            "category":"Retail",
            "subcategory":"Repair Shop",
            "type":"Services"
        }
    ],
    "sg:phone":"+61 7 4627 6081",
    "sg:postcode":"4425",
    "sg:province":"QLD",
    "sg:tags":[
        "upholsterer"
    ],
    "wof:name":"P.H. Francisco Upholsterer",
    "wof:placetype":"venue"
},
  "geometry": {"coordinates":[149.74412536599999,-26.6431789398],"type":"Point"}
}