{
  "type": "Feature",
  "properties": {
    "iso:country":"AU",
    "sg:address":"14 Frost Rd",
    "sg:city":"Campbelltown",
    "sg:classifiers":[
        {
            "category":"Retail",
            "subcategory":"Auto Repair",
            "type":"Services"
        }
    ],
    "sg:phone":"+61 2 4620 0526",
    "sg:postcode":"2560",
    "sg:province":"NSW",
    "sg:tags":[
        "body",
        "builder",
        "motor"
    ],
    "wof:name":"Unique Truck Bodies",
    "wof:placetype":"venue"
},
  "geometry": {"coordinates":[150.80873107900001,-34.0592308044],"type":"Point"}
}