{
  "type": "Feature",
  "properties": {
    "iso:country":"AU",
    "sg:address":"85 Crane St",
    "sg:city":"Longreach",
    "sg:classifiers":[
        {
            "category":"Taxi",
            "type":"Transportation"
        }
    ],
    "sg:phone":"+61 7 4658 3600",
    "sg:postcode":"4730",
    "sg:province":"QLD",
    "sg:tags":[
        "cab"
    ],
    "wof:name":"Tanks Cabs Longreach",
    "wof:placetype":"venue"
},
  "geometry": {"coordinates":[144.253204,-23.441719],"type":"Point"}
}