{
  "type": "Feature",
  "properties": {
    "iso:country":"AU",
    "sg:address":"4 Malton Pl",
    "sg:city":"City Beach",
    "sg:classifiers":[
        {
            "category":"Health Services",
            "subcategory":"Doctor",
            "type":"Services"
        }
    ],
    "sg:phone":"+61 401 283 241",
    "sg:postcode":"6015",
    "sg:province":"WA",
    "sg:tags":[
        "occupational",
        "safety"
    ],
    "wof:name":"Injury Claims Management Pty Ltd",
    "wof:placetype":"venue"
},
  "geometry": {"coordinates":[115.77143859900001,-31.923286438],"type":"Point"}
}