{
  "type": "Feature",
  "properties": {
    "iso:country":"AU",
    "sg:address":"74 Railway St",
    "sg:city":"Altona",
    "sg:classifiers":[
        {
            "category":"Communications",
            "subcategory":"Film & Video Production",
            "type":"Services"
        }
    ],
    "sg:phone":"+61 3 9398 1112",
    "sg:postcode":"3018",
    "sg:province":"VIC",
    "sg:tags":[
        "dvd",
        "library"
    ],
    "wof:name":"Station Sound & Video",
    "wof:placetype":"venue"
},
  "geometry": {"coordinates":[144.830276489,-37.8674850464],"type":"Point"}
}