{
  "type": "Feature",
  "properties": {
    "iso:country":"AU",
    "sg:address":"550 Elcho Rd",
    "sg:city":"Lovely Banks",
    "sg:classifiers":[
        {
            "category":"Shopping",
            "subcategory":"Party Supplies",
            "type":"Retail Goods"
        }
    ],
    "sg:phone":"+61 3 5282 5824",
    "sg:postcode":"3221",
    "sg:province":"VIC",
    "sg:tags":[
        "children's"
    ],
    "wof:name":"Saddle On",
    "wof:placetype":"venue"
},
  "geometry": {"coordinates":[144.31831399999999,-38.025314],"type":"Point"}
}