{
  "type": "Feature",
  "properties": {
    "addr:full":"22 Bobbin Head Rd Pymble NSW 2073",
    "addr:housenumber":"22",
    "addr:postcode":"2073",
    "addr:street":"Bobbin Head Rd",
    "iso:country":"AU",
    "sg:address":"22 Bobbin Head Rd",
    "sg:city":"Pymble",
    "sg:classifiers":[
        {
            "category":"Building & Trades",
            "subcategory":"Plumbing",
            "type":"Services"
        }
    ],
    "sg:phone":"+61 2 9449 7942",
    "sg:postcode":"2073",
    "sg:province":"NSW",
    "sg:tags":[
        "plumber",
        "gasfitters"
    ],
    "wof:name":"Patteson J",
    "wof:placetype":"venue"
},
  "geometry": {"coordinates":[151.136962891,-33.737033844],"type":"Point"}
}