{
  "type": "Feature",
  "properties": {
    "addr:full":"87 Frobisher Rd Osborne Park WA 6017",
    "addr:housenumber":"87",
    "addr:postcode":"6017",
    "addr:street":"Frobisher Rd",
    "iso:country":"AU",
    "sg:address":"87 Frobisher Rd",
    "sg:city":"Osborne Park",
    "sg:classifiers":[
        {
            "category":"Home & Garden",
            "subcategory":"Furniture",
            "type":"Retail Goods"
        }
    ],
    "sg:phone":"+61 8 9444 0488",
    "sg:postcode":"6017",
    "sg:province":"WA",
    "sg:tags":[
        "business"
    ],
    "wof:name":"Furniture Spot",
    "wof:placetype":"venue"
},
  "geometry": {"coordinates":[115.819587708,-31.9064693451],"type":"Point"}
}