{
  "type": "Feature",
  "properties": {
    "addr:full":"Chalkhill Rd McLaren Vale SA 5171",
    "addr:postcode":"5171",
    "addr:street":"Chalkhill Rd",
    "iso:country":"AU",
    "sg:address":"Chalkhill Rd",
    "sg:city":"McLaren Vale",
    "sg:classifiers":[
        {
            "category":"Wholesale",
            "subcategory":"Farm Supplies",
            "type":"Manufacturing & Wholesale Goods"
        }
    ],
    "sg:phone":"+61 8 8323 8795",
    "sg:postcode":"5171",
    "sg:province":"SA",
    "sg:tags":[
        "equipment"
    ],
    "wof:name":"Wrights Tractor Sales, Service & Wrecking",
    "wof:placetype":"venue"
},
  "geometry": {"coordinates":[138.53590393100001,-35.2095489502],"type":"Point"}
}