{
  "type": "Feature",
  "properties": {
    "addr:full":"7 Iris St Frenchs Forest NSW 2086",
    "addr:housenumber":"7",
    "addr:postcode":"2086",
    "addr:street":"Iris St",
    "iso:country":"AU",
    "sg:address":"7 Iris St",
    "sg:city":"Frenchs Forest",
    "sg:classifiers":[
        {
            "category":"Building & Trades",
            "subcategory":"Construction",
            "type":"Services"
        }
    ],
    "sg:phone":"+61 2 9451 6004",
    "sg:postcode":"2086",
    "sg:province":"NSW",
    "sg:tags":[
        "earth",
        "excavating",
        "moving",
        "contractor"
    ],
    "wof:name":"Aardvark Earthworks",
    "wof:placetype":"venue"
},
  "geometry": {"coordinates":[151.24079895,-33.7485237122],"type":"Point"}
}