{
  "type": "Feature",
  "properties": {
    "iso:country":"AU",
    "sg:address":"22 Grace Crs",
    "sg:city":"Lamberts Beach",
    "sg:classifiers":[
        {
            "category":"Professional",
            "subcategory":"Business Services",
            "type":"Services"
        }
    ],
    "sg:phone":"+61 7 4955 1475",
    "sg:postcode":"4740",
    "sg:province":"QLD",
    "sg:tags":[
        "drafting"
    ],
    "wof:name":"Design Solutions Mackay Pty Ltd",
    "wof:placetype":"venue"
},
  "geometry": {"coordinates":[149.111847,-21.15519],"type":"Point"}
}