{
  "type": "Feature",
  "properties": {
    "iso:country":"AU",
    "sg:address":"30 Hobson St",
    "sg:city":"Sandringham",
    "sg:classifiers":[
        {
            "category":"Real Estate",
            "subcategory":"Architect",
            "type":"Services"
        }
    ],
    "sg:phone":"+61 3 9521 0630",
    "sg:postcode":"3191",
    "sg:province":"VIC",
    "sg:tags":[
        "magnet",
        "magnetic",
        "material"
    ],
    "wof:name":"Cre8ive Promotional Products",
    "wof:placetype":"venue"
},
  "geometry": {"coordinates":[145.015167236,-37.9488258362],"type":"Point"}
}