{
  "type": "Feature",
  "properties": {
    "addr:full":"26 Circuit Drv Hendon SA 5014",
    "addr:housenumber":"26",
    "addr:postcode":"5014",
    "addr:street":"Circuit Drv",
    "iso:country":"AU",
    "sg:address":"26 Circuit Drv",
    "sg:city":"Hendon",
    "sg:classifiers":[
        {
            "category":"Farming",
            "subcategory":"Crops",
            "type":"Manufacturing & Wholesale Goods"
        }
    ],
    "sg:phone":"+61 8 8244 6255",
    "sg:postcode":"5014",
    "sg:province":"SA",
    "sg:tags":[
        "warehousing"
    ],
    "wof:name":"Adelaides Wine Storage & Logistics Pty Ltd",
    "wof:placetype":"venue"
},
  "geometry": {"coordinates":[138.51756286599999,-34.8799819946],"type":"Point"}
}