{
  "type": "Feature",
  "properties": {
    "addr:full":"Suite 7/ 201 Mann St Gosford NSW 2250",
    "addr:housenumber":"/ 201",
    "addr:postcode":"2250",
    "addr:street":"Mann St",
    "iso:country":"AU",
    "sg:address":"Suite 7/ 201 Mann St",
    "sg:city":"Gosford",
    "sg:classifiers":[
        {
            "category":"Health Services",
            "subcategory":"Health Practitioner",
            "type":"Services"
        }
    ],
    "sg:phone":"+61 2 4323 1455",
    "sg:postcode":"2250",
    "sg:province":"NSW",
    "sg:tags":[
        "naturopath"
    ],
    "wof:name":"Wholastic Balance Naturopathic Centre",
    "wof:placetype":"venue"
},
  "geometry": {"coordinates":[151.34254455600001,-33.4243431091],"type":"Point"}
}