{
  "type": "Feature",
  "properties": {
    "addr:full":"6 McLeod Crt Cavan SA 5094",
    "addr:housenumber":"6",
    "addr:postcode":"5094",
    "addr:street":"Mcleod Crt",
    "iso:country":"AU",
    "sg:address":"6 McLeod Crt",
    "sg:city":"Cavan",
    "sg:classifiers":[
        {
            "category":"Wholesale",
            "subcategory":"Auto Parts",
            "type":"Manufacturing & Wholesale Goods"
        }
    ],
    "sg:phone":"+61 8 8260 6544",
    "sg:postcode":"5094",
    "sg:province":"SA",
    "sg:tags":[
        "tyre"
    ],
    "wof:name":"Bridgestone Earthmover Tyres Pty Ltd",
    "wof:placetype":"venue"
},
  "geometry": {"coordinates":[138.60031127900001,-34.8239097595],"type":"Point"}
}