{
  "type": "Feature",
  "properties": {
    "addr:full":"23 Hindley St Adelaide SA 5000",
    "addr:housenumber":"23",
    "addr:postcode":"5000",
    "addr:street":"Hindley St",
    "iso:country":"AU",
    "sg:address":"23 Hindley St",
    "sg:city":"Adelaide",
    "sg:classifiers":[
        {
            "category":"Travel",
            "subcategory":"Hotels & Motels",
            "type":"Entertainment"
        }
    ],
    "sg:phone":"+61 8 8231 4049",
    "sg:postcode":"5000",
    "sg:province":"SA",
    "wof:name":"City Central Motel",
    "wof:placetype":"venue"
},
  "geometry": {"coordinates":[138.59823608400001,-34.9231834412],"type":"Point"}
}