{
  "type": "Feature",
  "properties": {
    "addr:full":"66 Flinders St Wollongong NSW 2500",
    "addr:housenumber":"66",
    "addr:postcode":"2500",
    "addr:street":"Flinders St",
    "iso:country":"AU",
    "sg:address":"66 Flinders St",
    "sg:city":"Wollongong",
    "sg:classifiers":[
        {
            "category":"Professional",
            "type":"Services"
        }
    ],
    "sg:phone":"+61 2 4229 4994",
    "sg:postcode":"2500",
    "sg:province":"NSW",
    "sg:tags":[
        "spray",
        "painting"
    ],
    "wof:name":"Wollongong City Smash Repairs",
    "wof:placetype":"venue"
},
  "geometry": {"coordinates":[150.89213599999999,-34.418015],"type":"Point"}
}