{
  "type": "Feature",
  "properties": {
    "iso:country":"AU",
    "sg:address":"134 Queen St",
    "sg:city":"Ayr",
    "sg:classifiers":[
        {
            "category":"Fast Food",
            "type":"Food & Drink"
        }
    ],
    "sg:phone":"+61 7 4783 3300",
    "sg:postcode":"4807",
    "sg:province":"QLD",
    "sg:tags":[
        "away",
        "take"
    ],
    "wof:name":"Eagle Boys Pizza Ayr",
    "wof:placetype":"venue"
},
  "geometry": {"coordinates":[147.405960083,-19.5754566193],"type":"Point"}
}