{
  "type": "Feature",
  "properties": {
    "iso:country":"AU",
    "sg:address":"1 Maple Ave",
    "sg:city":"Forestville",
    "sg:classifiers":[
        {
            "category":"Building & Trades",
            "subcategory":"Construction",
            "type":"Services"
        }
    ],
    "sg:phone":"+61 8 8297 6666",
    "sg:postcode":"5035",
    "sg:province":"SA",
    "sg:tags":[
        "window",
        "tinting"
    ],
    "wof:name":"Solchek Pty Ltd",
    "wof:placetype":"venue"
},
  "geometry": {"coordinates":[138.58366394000001,-34.9481315613],"type":"Point"}
}