{
  "type": "Feature",
  "properties": {
    "addr:full":"3 Gleeson Pl Abbotsbury NSW 2176",
    "addr:housenumber":"3",
    "addr:postcode":"2176",
    "addr:street":"Gleeson Pl",
    "iso:country":"AU",
    "sg:address":"3 Gleeson Pl",
    "sg:city":"Abbotsbury",
    "sg:classifiers":[
        {
            "category":"Utilities",
            "subcategory":"Electric",
            "type":"Services"
        }
    ],
    "sg:phone":"+61 412 655 008",
    "sg:postcode":"2176",
    "sg:province":"NSW",
    "sg:tags":[
        "electrical",
        "contractor"
    ],
    "wof:name":"PCP Electric",
    "wof:placetype":"venue"
},
  "geometry": {"coordinates":[150.867645264,-33.8694801331],"type":"Point"}
}