{
  "type": "Feature",
  "properties": {
    "addr:full":"Suite 1, 20 Gibberd Rd Balcatta WA 6021",
    "addr:housenumber":"20",
    "addr:postcode":"6021",
    "addr:street":"Gibberd Rd",
    "iso:country":"AU",
    "sg:address":"Suite 1, 20 Gibberd Rd",
    "sg:city":"Balcatta",
    "sg:classifiers":[
        {
            "category":"Manufacturing",
            "subcategory":"Furniture",
            "type":"Manufacturing & Wholesale Goods"
        }
    ],
    "sg:phone":"+61 8 9240 1488",
    "sg:postcode":"6021",
    "sg:province":"WA",
    "sg:tags":[
        "builder",
        "designer",
        "custom"
    ],
    "wof:name":"Silvestri Cabinet Designs",
    "wof:placetype":"venue"
},
  "geometry": {"coordinates":[115.812232971,-31.8647708893],"type":"Point"}
}