{
  "type": "Feature",
  "properties": {
    "iso:country":"AU",
    "sg:address":"863 Great Western Hwy",
    "sg:city":"Minchinbury",
    "sg:classifiers":[
        {
            "category":"Travel",
            "subcategory":"Hotels & Motels",
            "type":"Entertainment"
        }
    ],
    "sg:phone":"+61 2 9625 9902",
    "sg:postcode":"2770",
    "sg:province":"NSW",
    "wof:name":"Motel Voyager",
    "wof:placetype":"venue"
},
  "geometry": {"coordinates":[150.81324768100001,-33.7791404724],"type":"Point"}
}