{
  "type": "Feature",
  "properties": {
    "addr:full":"140 Fitzgerald St Northam WA 6401",
    "addr:housenumber":"140",
    "addr:postcode":"6401",
    "addr:street":"Fitzgerald St",
    "iso:country":"AU",
    "sg:address":"140 Fitzgerald St",
    "sg:city":"Northam",
    "sg:classifiers":[
        {
            "category":"Shopping",
            "subcategory":"Clothing, Apparel, & Fashions",
            "type":"Retail Goods"
        }
    ],
    "sg:phone":"+61 8 9622 3047",
    "sg:postcode":"6401",
    "sg:province":"WA",
    "sg:tags":[
        "recycled",
        "clothing"
    ],
    "wof:name":"Good Sammy Northam",
    "wof:placetype":"venue"
},
  "geometry": {"coordinates":[116.672340393,-31.6526851654],"type":"Point"}
}