{
  "type": "Feature",
  "properties": {
    "iso:country":"AU",
    "sg:address":"3/16 Sussex Crt",
    "sg:city":"Sunbury",
    "sg:classifiers":[
        {
            "category":"Professional",
            "subcategory":"Engineering",
            "type":"Services"
        }
    ],
    "sg:phone":"+61 3 9746 3633",
    "sg:postcode":"3429",
    "sg:province":"VIC",
    "sg:tags":[
        "diesel",
        "engineer"
    ],
    "wof:name":"M W Diesel Maintenance",
    "wof:placetype":"venue"
},
  "geometry": {"coordinates":[144.719650269,-37.5873298645],"type":"Point"}
}