{
  "type": "Feature",
  "properties": {
    "iso:country":"AU",
    "sg:address":"401 Maroondah Hwy",
    "sg:city":"Ringwood",
    "sg:classifiers":[
        {
            "category":"Building & Trades",
            "subcategory":"Construction",
            "type":"Services"
        }
    ],
    "sg:phone":"+61 3 9870 6800",
    "sg:postcode":"3134",
    "sg:province":"VIC",
    "sg:tags":[
        "window",
        "tinting"
    ],
    "wof:name":"Australian Auto Tint Pty Ltd",
    "wof:placetype":"venue"
},
  "geometry": {"coordinates":[145.24703979500001,-37.8029022217],"type":"Point"}
}