{
  "type": "Feature",
  "properties": {
    "iso:country":"AU",
    "sg:address":"U8/ 106 Joynton Ave",
    "sg:city":"Zetland",
    "sg:classifiers":[
        {
            "category":"Personal",
            "type":"Services"
        }
    ],
    "sg:phone":"+61 2 9697 2488",
    "sg:postcode":"2017",
    "sg:province":"NSW",
    "sg:tags":[
        "introduction",
        "social"
    ],
    "wof:name":"Dates With Mates",
    "wof:placetype":"venue"
},
  "geometry": {"coordinates":[151.20843505900001,-33.9062271118],"type":"Point"}
}