{
  "type": "Feature",
  "properties": {
    "addr:full":"216 Pakington St Geelong West VIC 3218",
    "addr:housenumber":"216",
    "addr:postcode":"3218",
    "addr:street":"Pakington St",
    "iso:country":"AU",
    "sg:address":"216 Pakington St",
    "sg:city":"Geelong West",
    "sg:classifiers":[
        {
            "category":"Real Estate",
            "subcategory":"Real Estate Agent",
            "type":"Services"
        }
    ],
    "sg:phone":"+61 3 5222 1333",
    "sg:postcode":"3218",
    "sg:province":"VIC",
    "wof:name":"Jens Gaunt Real Estate Geelong Pty Ltd",
    "wof:placetype":"venue"
},
  "geometry": {"coordinates":[144.348114014,-38.1426200867],"type":"Point"}
}