{
  "type": "Feature",
  "properties": {
    "addr:full":"21 Spray Ave Mordialloc VIC 3195",
    "addr:housenumber":"21",
    "addr:postcode":"3195",
    "addr:street":"Spray Ave",
    "iso:country":"AU",
    "sg:address":"21 Spray Ave",
    "sg:city":"Mordialloc",
    "sg:classifiers":[
        {
            "category":"Commercial Area",
            "type":"Public Place"
        }
    ],
    "sg:phone":"+61 3 9587 7120",
    "sg:postcode":"3195",
    "sg:province":"VIC",
    "sg:tags":[
        "heavy",
        "carrier"
    ],
    "wof:name":"Crains Machinery Transport Pty Ltd",
    "wof:placetype":"venue"
},
  "geometry": {"coordinates":[145.102386475,-38.0094833374],"type":"Point"}
}