{
  "type": "Feature",
  "properties": {
    "iso:country":"AU",
    "sg:address":"55 Thornley St",
    "sg:city":"Leichhardt",
    "sg:classifiers":[
        {
            "category":"Health Services",
            "subcategory":"Health Practitioner",
            "type":"Services"
        }
    ],
    "sg:phone":"+61 2 9560 3011",
    "sg:postcode":"2040",
    "sg:province":"NSW",
    "sg:tags":[
        "acupuncture"
    ],
    "wof:name":"Hoad Annette",
    "wof:placetype":"venue"
},
  "geometry": {"coordinates":[151.155716,-33.885387],"type":"Point"}
}