{
  "type": "Feature",
  "properties": {
    "iso:country":"AU",
    "sg:address":"Unit B4/11- 15 Moxon Rd",
    "sg:city":"Punchbowl",
    "sg:classifiers":[
        {
            "category":"Wholesale",
            "subcategory":"Toys & Hobbies",
            "type":"Manufacturing & Wholesale Goods"
        }
    ],
    "sg:phone":"+61 2 9709 8666",
    "sg:postcode":"2196",
    "sg:province":"NSW",
    "wof:name":"Weirdo (Imports) Pty Ltd",
    "wof:placetype":"venue"
},
  "geometry": {"coordinates":[151.042694,-33.934391],"type":"Point"}
}