{
  "type": "Feature",
  "properties": {
    "addr:full":"14 Thomas St Hornsby NSW 2077",
    "addr:housenumber":"14",
    "addr:postcode":"2077",
    "addr:street":"Thomas St",
    "iso:country":"AU",
    "sg:address":"14 Thomas St",
    "sg:city":"Hornsby",
    "sg:classifiers":[
        {
            "category":"Health Services",
            "subcategory":"Health Practitioner",
            "type":"Services"
        }
    ],
    "sg:phone":"+61 401 698 588",
    "sg:postcode":"2077",
    "sg:province":"NSW",
    "sg:tags":[
        "reiki"
    ],
    "wof:name":"Debra A Mccormick",
    "wof:placetype":"venue"
},
  "geometry": {"coordinates":[151.102462769,-33.7067947388],"type":"Point"}
}