{
  "type": "Feature",
  "properties": {
    "addr:full":"46 Young St Carrington NSW 2294",
    "addr:housenumber":"46",
    "addr:postcode":"2294",
    "addr:street":"Young St",
    "iso:country":"AU",
    "sg:address":"46 Young St",
    "sg:city":"Carrington",
    "sg:classifiers":[
        {
            "category":"Health Services",
            "subcategory":"Health Practitioner",
            "type":"Services"
        }
    ],
    "sg:phone":"+61 2 4961 4989",
    "sg:postcode":"2294",
    "sg:province":"NSW",
    "sg:tags":[
        "psychologist"
    ],
    "wof:name":"Mortlock Therese",
    "wof:placetype":"venue"
},
  "geometry": {"coordinates":[151.767944336,-32.9118881226],"type":"Point"}
}