{
  "type": "Feature",
  "properties": {
    "addr:full":"Depot, U2/ 246 Evans Rd Salisbury QLD 4107",
    "addr:housenumber":"246",
    "addr:postcode":"4107",
    "addr:street":"U2 /;Evans Rd",
    "iso:country":"AU",
    "sg:address":"Depot, U2/ 246 Evans Rd",
    "sg:city":"Salisbury",
    "sg:classifiers":[
        {
            "category":"Retail",
            "subcategory":"Storage",
            "type":"Services"
        }
    ],
    "sg:phone":"+61 7 3219 5144",
    "sg:postcode":"4107",
    "sg:province":"QLD",
    "sg:tags":[
        "removal",
        "furniture"
    ],
    "wof:name":"Hughes W.E.",
    "wof:placetype":"venue"
},
  "geometry": {"coordinates":[153.03367614699999,-27.5452823639],"type":"Point"}
}