{
  "type": "Feature",
  "properties": {
    "iso:country":"AU",
    "sg:address":"1470 Logan Rd",
    "sg:city":"Mt Gravatt",
    "sg:classifiers":[
        {
            "category":"Sports & Exercise",
            "subcategory":"Gym",
            "type":"Entertainment"
        }
    ],
    "sg:phone":"+61 7 3420 0255",
    "sg:postcode":"4122",
    "sg:province":"QLD",
    "sg:tags":[
        "health",
        "fitness"
    ],
    "wof:name":"Curves Mt Gravatt",
    "wof:placetype":"venue"
},
  "geometry": {"coordinates":[153.07940673799999,-27.5380210876],"type":"Point"}
}