{
  "type": "Feature",
  "properties": {
    "addr:full":"123 Island View Drv Clayton SA 5256",
    "addr:housenumber":"123",
    "addr:postcode":"5256",
    "addr:street":"Island View Drv",
    "iso:country":"AU",
    "sg:address":"123 Island View Drv",
    "sg:city":"Clayton",
    "sg:classifiers":[
        {
            "category":"Recreation",
            "subcategory":"Boat Charter",
            "type":"Entertainment"
        }
    ],
    "sg:phone":"+61 8 8537 0372",
    "sg:postcode":"5256",
    "sg:province":"SA",
    "sg:tags":[
        "hire",
        "drive"
    ],
    "wof:name":"Backwater Boats",
    "wof:placetype":"venue"
},
  "geometry": {"coordinates":[138.928344727,-35.4929161072],"type":"Point"}
}