{
  "type": "Feature",
  "properties": {
    "iso:country":"AU",
    "sg:address":"142 Highclere Ave",
    "sg:city":"Punchbowl",
    "sg:classifiers":[
        {
            "category":"Education",
            "subcategory":"School",
            "type":"Public Place"
        }
    ],
    "sg:phone":"+61 2 9750 8455",
    "sg:postcode":"2196",
    "sg:province":"NSW",
    "wof:name":"St Charbel's College",
    "wof:placetype":"venue"
},
  "geometry": {"coordinates":[151.056656,-33.917202],"type":"Point"}
}