{
  "type": "Feature",
  "properties": {
    "addr:full":"128 Beerburrum St Caloundra QLD 4551",
    "addr:housenumber":"128",
    "addr:postcode":"4551",
    "addr:street":"Beerburrum St",
    "iso:country":"AU",
    "sg:address":"128 Beerburrum St",
    "sg:city":"Caloundra",
    "sg:classifiers":[
        {
            "category":"Building & Trades",
            "subcategory":"Construction",
            "type":"Services"
        }
    ],
    "sg:phone":"+61 7 5438 1188",
    "sg:postcode":"4551",
    "sg:province":"QLD",
    "sg:tags":[
        "contractor"
    ],
    "wof:name":"Lyrebird Homes",
    "wof:placetype":"venue"
},
  "geometry": {"coordinates":[153.12506103499999,-26.7801971436],"type":"Point"}
}