{
  "type": "Feature",
  "properties": {
    "addr:full":"806 Beaudesert Rd Coopers Plains QLD 4108",
    "addr:housenumber":"806",
    "addr:postcode":"4108",
    "addr:street":"Beaudesert Rd",
    "iso:country":"AU",
    "sg:address":"806 Beaudesert Rd",
    "sg:city":"Coopers Plains",
    "sg:classifiers":[
        {
            "category":"Wholesale",
            "subcategory":"Metals & Minerals",
            "type":"Manufacturing & Wholesale Goods"
        }
    ],
    "sg:phone":"+61 7 3277 2088",
    "sg:postcode":"4108",
    "sg:province":"QLD",
    "sg:tags":[
        "steel",
        "merchant"
    ],
    "wof:name":"Simsmetal Limited",
    "wof:placetype":"venue"
},
  "geometry": {"coordinates":[153.021286011,-27.5590076447],"type":"Point"}
}