{
  "type": "Feature",
  "properties": {
    "iso:country":"AU",
    "sg:address":"17 Anglo Rd",
    "sg:city":"Campsie",
    "sg:classifiers":[
        {
            "category":"Health Services",
            "subcategory":"Doctor",
            "type":"Services"
        }
    ],
    "sg:phone":"+61 2 9787 7724",
    "sg:postcode":"2194",
    "sg:province":"NSW",
    "sg:tags":[
        "medical",
        "practitioner"
    ],
    "wof:name":"Lawendy Rafat",
    "wof:placetype":"venue"
},
  "geometry": {"coordinates":[151.10273699999999,-33.911201],"type":"Point"}
}