{
  "type": "Feature",
  "properties": {
    "addr:full":"Level 1, 4 Burbank Pl Baulkham Hills NSW 2153",
    "addr:housenumber":"4",
    "addr:postcode":"2153",
    "addr:street":"Burbank Pl",
    "iso:country":"AU",
    "sg:address":"Level 1, 4 Burbank Pl",
    "sg:city":"Baulkham Hills",
    "sg:classifiers":[
        {
            "category":"Retail",
            "subcategory":"Driving School",
            "type":"Services"
        }
    ],
    "sg:phone":"+61 2 8866 1100",
    "sg:postcode":"2153",
    "sg:province":"NSW",
    "sg:tags":[
        "equipment",
        "pile",
        "contractor"
    ],
    "wof:name":"Frankipile Aust. Pty. Ltd.",
    "wof:placetype":"venue"
},
  "geometry": {"coordinates":[150.959259033,-33.7330093384],"type":"Point"}
}