{
  "type": "Feature",
  "properties": {
    "iso:country":"AU",
    "sg:address":"74 Sunscape Drv",
    "sg:city":"Beenleigh",
    "sg:classifiers":[
        {
            "category":"Building & Trades",
            "subcategory":"Landscaping Services",
            "type":"Services"
        }
    ],
    "sg:phone":"+61 402 332 793",
    "sg:postcode":"4207",
    "sg:province":"QLD",
    "sg:tags":[
        "stump",
        "tree",
        "felling",
        "removal"
    ],
    "wof:name":"Avalon Tree Service",
    "wof:placetype":"venue"
},
  "geometry": {"coordinates":[153.21685790999999,-27.6963920593],"type":"Point"}
}