{
  "type": "Feature",
  "properties": {
    "addr:full":"Shop 28 Dog Swamp Shopping Centre Yokine WA 6060",
    "addr:housenumber":"shop 28",
    "addr:postcode":"6060",
    "addr:street":"Dog",
    "iso:country":"AU",
    "sg:address":"Shop 28 Dog Swamp Shopping Centre",
    "sg:city":"Yokine",
    "sg:classifiers":[
        {
            "category":"Government",
            "subcategory":"Post Office",
            "type":"Public Place"
        }
    ],
    "sg:phone":"+61 13 13 18",
    "sg:postcode":"6060",
    "sg:province":"WA",
    "sg:tags":[
        "postal"
    ],
    "wof:name":"Australia Post",
    "wof:placetype":"venue"
},
  "geometry": {"coordinates":[115.850013733,-31.9015102386],"type":"Point"}
}