{
  "type": "Feature",
  "properties": {
    "iso:country":"AU",
    "sg:address":"128 Gerler St",
    "sg:city":"Hendra",
    "sg:classifiers":[
        {
            "category":"Building & Trades",
            "subcategory":"Plumbing",
            "type":"Services"
        }
    ],
    "sg:phone":"+61 7 3633 4236",
    "sg:postcode":"4011",
    "sg:province":"QLD",
    "sg:tags":[
        "equipment",
        "valves"
    ],
    "wof:name":"Drivetech",
    "wof:placetype":"venue"
},
  "geometry": {"coordinates":[153.071671,-27.418825],"type":"Point"}
}