{
  "type": "Feature",
  "properties": {
    "iso:country":"AU",
    "sg:address":"1/ 83 Beryl St",
    "sg:city":"Balcatta",
    "sg:classifiers":[
        {
            "category":"Retail",
            "subcategory":"Auto Rental",
            "type":"Services"
        }
    ],
    "sg:phone":"+61 8 9344 8949",
    "sg:postcode":"6021",
    "sg:province":"WA",
    "sg:tags":[
        "chauffeur",
        "car",
        "hire",
        "driven",
        "limousine"
    ],
    "wof:name":"Jessica Livingston",
    "wof:placetype":"venue"
},
  "geometry": {"coordinates":[115.832427978,-31.8773937225],"type":"Point"}
}