{
  "type": "Feature",
  "properties": {
    "iso:country":"AU",
    "sg:address":"6 Enderley Ave",
    "sg:city":"Clayfield",
    "sg:classifiers":[
        {
            "category":"Health Services",
            "subcategory":"Doctor",
            "type":"Services"
        }
    ],
    "sg:phone":"+61 7 3256 9943",
    "sg:postcode":"4011",
    "sg:province":"QLD",
    "sg:tags":[
        "medical",
        "practitioner"
    ],
    "wof:name":"Dr. Kenneth Elms Pty Ltd",
    "wof:placetype":"venue"
},
  "geometry": {"coordinates":[153.05453499999999,-27.424109],"type":"Point"}
}