{
  "type": "Feature",
  "properties": {
    "iso:country":"AU",
    "sg:address":"306 Ferry Rd",
    "sg:city":"Southport",
    "sg:classifiers":[
        {
            "category":"Building & Trades",
            "subcategory":"Pest Control",
            "type":"Services"
        }
    ],
    "sg:phone":"+61 413 940 722",
    "sg:postcode":"4215",
    "sg:province":"QLD",
    "wof:name":"Pigeon.com.au",
    "wof:placetype":"venue"
},
  "geometry": {"coordinates":[153.41404724099999,-27.9952697754],"type":"Point"}
}