{
  "type": "Feature",
  "properties": {
    "addr:full":"Buckle St Balcatta WA 6021",
    "addr:postcode":"6021",
    "addr:street":"Buckle St",
    "iso:country":"AU",
    "sg:address":"Buckle St",
    "sg:city":"Balcatta",
    "sg:classifiers":[
        {
            "category":"Building & Trades",
            "subcategory":"Construction",
            "type":"Services"
        }
    ],
    "sg:phone":"+61 413 013 416",
    "sg:postcode":"6021",
    "sg:province":"WA",
    "sg:tags":[
        "contractor"
    ],
    "wof:name":"Timber Dimensions",
    "wof:placetype":"venue"
},
  "geometry": {"coordinates":[115.815391541,-31.8723087311],"type":"Point"}
}