{
  "type": "Feature",
  "properties": {
    "addr:full":"7 Winifred St Frankston VIC 3199",
    "addr:housenumber":"7",
    "addr:postcode":"3199",
    "addr:street":"Winifred St",
    "iso:country":"AU",
    "sg:address":"7 Winifred St",
    "sg:city":"Frankston",
    "sg:classifiers":[
        {
            "category":"Health Services",
            "subcategory":"Doctor",
            "type":"Services"
        }
    ],
    "sg:phone":"+61 3 9781 2510",
    "sg:postcode":"3199",
    "sg:province":"VIC",
    "sg:tags":[
        "medical",
        "practitioner"
    ],
    "wof:name":"Trivedi Amar Associate Professor",
    "wof:placetype":"venue"
},
  "geometry": {"coordinates":[145.10206604000001,-37.8952598572],"type":"Point"}
}