{
  "type": "Feature",
  "properties": {
    "addr:full":"7 Rosberg Rd Wingfield SA 5013",
    "addr:housenumber":"7",
    "addr:postcode":"5013",
    "addr:street":"Rosberg Rd",
    "iso:country":"AU",
    "sg:address":"7 Rosberg Rd",
    "sg:city":"Wingfield",
    "sg:classifiers":[
        {
            "category":"Manufacturing",
            "subcategory":"Metals",
            "type":"Manufacturing & Wholesale Goods"
        }
    ],
    "sg:phone":"+61 8 8349 2700",
    "sg:postcode":"5013",
    "sg:province":"SA",
    "sg:tags":[
        "cutting"
    ],
    "wof:name":"Medo Fabrication Pty Ltd",
    "wof:placetype":"venue"
},
  "geometry": {"coordinates":[138.56610107399999,-34.846912384],"type":"Point"}
}