{
  "type": "Feature",
  "properties": {
    "addr:full":"14 Todd St Shorncliffe QLD 4017",
    "addr:housenumber":"14",
    "addr:postcode":"4017",
    "addr:street":"Todd St",
    "iso:country":"AU",
    "sg:address":"14 Todd St",
    "sg:city":"Shorncliffe",
    "sg:classifiers":[
        {
            "category":"Utilities",
            "subcategory":"Electric",
            "type":"Services"
        }
    ],
    "sg:phone":"+61 7 3869 1485",
    "sg:postcode":"4017",
    "sg:province":"QLD",
    "sg:tags":[
        "electrical",
        "contractor"
    ],
    "wof:name":"R & F Electrical",
    "wof:placetype":"venue"
},
  "geometry": {"coordinates":[153.08334350600001,-27.325838089],"type":"Point"}
}