{
  "type": "Feature",
  "properties": {
    "iso:country":"AU",
    "sg:address":"53 Curtin Ave",
    "sg:city":"Cottesloe",
    "sg:classifiers":[
        {
            "category":"Education",
            "subcategory":"School",
            "type":"Public Place"
        }
    ],
    "sg:phone":"+61 8 9384 6344",
    "sg:postcode":"6011",
    "sg:province":"WA",
    "sg:tags":[
        "state",
        "except",
        "nsw"
    ],
    "wof:name":"Schools Government (Public)",
    "wof:placetype":"venue"
},
  "geometry": {"coordinates":[115.755470276,-32.0094337463],"type":"Point"}
}