{
  "type": "Feature",
  "properties": {
    "addr:full":"Unit 3/ 73 Beauchamp Rd Matraville NSW 2036",
    "addr:housenumber":"73",
    "addr:postcode":"2036",
    "addr:street":"Beauchamp Rd",
    "iso:country":"AU",
    "sg:address":"Unit 3/ 73 Beauchamp Rd",
    "sg:city":"Matraville",
    "sg:classifiers":[
        {
            "category":"Professional",
            "subcategory":"Employment Agencies",
            "type":"Services"
        }
    ],
    "sg:phone":"+61 2 9316 4577",
    "sg:postcode":"2036",
    "sg:province":"NSW",
    "sg:tags":[
        "broker",
        "custom"
    ],
    "sg:website":"http://www.harveyint.com.au",
    "wof:name":"Harvey International Services",
    "wof:placetype":"venue"
},
  "geometry": {"coordinates":[151.22363281200001,-33.9497070312],"type":"Point"}
}