{
  "type": "Feature",
  "properties": {
    "iso:country":"AU",
    "sg:address":"330- 332 Wyndham St",
    "sg:city":"Shepparton",
    "sg:classifiers":[
        {
            "category":"Shopping",
            "subcategory":"Mobile Phones",
            "type":"Retail Goods"
        }
    ],
    "sg:phone":"+61 3 5831 5066",
    "sg:postcode":"3630",
    "sg:province":"VIC",
    "sg:tags":[
        "telephone",
        "accessory"
    ],
    "wof:name":"Optus World",
    "wof:placetype":"venue"
},
  "geometry": {"coordinates":[145.39923095699999,-36.3806686401],"type":"Point"}
}