{
  "type": "Feature",
  "properties": {
    "addr:full":"12 Delaware St Epping NSW 2121",
    "addr:housenumber":"12",
    "addr:postcode":"2121",
    "addr:street":"Delaware St",
    "iso:country":"AU",
    "sg:address":"12 Delaware St",
    "sg:city":"Epping",
    "sg:classifiers":[
        {
            "category":"Building & Trades",
            "subcategory":"Construction",
            "type":"Services"
        }
    ],
    "sg:phone":"+61 411 773 975",
    "sg:postcode":"2121",
    "sg:province":"NSW",
    "sg:tags":[
        "roof"
    ],
    "wof:name":"Anco Roofing Service",
    "wof:placetype":"venue"
},
  "geometry": {"coordinates":[151.071609497,-33.7705345154],"type":"Point"}
}