{
  "type": "Feature",
  "properties": {
    "iso:country":"AU",
    "sg:address":"Cnr Beaudesert Road & Kameruka St",
    "sg:city":"Calamvale",
    "sg:classifiers":[
        {
            "category":"Health Services",
            "subcategory":"Health Practitioner",
            "type":"Services"
        }
    ],
    "sg:phone":"+61 7 3272 5230",
    "sg:postcode":"4116",
    "sg:province":"QLD",
    "sg:tags":[
        "physiotherapist"
    ],
    "wof:name":"Calamvale Physiotherapy Centre",
    "wof:placetype":"venue"
},
  "geometry": {"coordinates":[153.049438477,-27.6217956543],"type":"Point"}
}