{
  "type": "Feature",
  "properties": {
    "addr:full":"18 Neasham Drv Dandenong VIC 3175",
    "addr:housenumber":"18",
    "addr:postcode":"3175",
    "addr:street":"Neasham Drv",
    "iso:country":"AU",
    "sg:address":"18 Neasham Drv",
    "sg:city":"Dandenong",
    "sg:classifiers":[
        {
            "category":"Home & Garden",
            "subcategory":"Carpets & Floor Coverings",
            "type":"Retail Goods"
        }
    ],
    "sg:phone":"+61 1300 785 963",
    "sg:postcode":"3175",
    "sg:province":"VIC",
    "sg:tags":[
        "tile",
        "wall",
        "layer"
    ],
    "sg:website":"http://www.contemporaryfinishes.com.au",
    "wof:name":"Contemporary Finishes",
    "wof:placetype":"venue"
},
  "geometry": {"coordinates":[145.200317383,-37.9435691833],"type":"Point"}
}