{
  "type": "Feature",
  "properties": {
    "addr:full":"6 Racecourse Rd Pakenham VIC 3810",
    "addr:housenumber":"6",
    "addr:postcode":"3810",
    "addr:street":"Racecourse Rd",
    "iso:country":"AU",
    "sg:address":"6 Racecourse Rd",
    "sg:city":"Pakenham",
    "sg:classifiers":[
        {
            "category":"Retail",
            "subcategory":"Auto Repair",
            "type":"Services"
        }
    ],
    "sg:phone":"+61 3 5941 7055",
    "sg:postcode":"3810",
    "sg:province":"VIC",
    "sg:tags":[
        "repairer",
        "motor",
        "engineer"
    ],
    "wof:name":"Hold Serv",
    "wof:placetype":"venue"
},
  "geometry": {"coordinates":[145.49229399999999,-38.083214],"type":"Point"}
}