{
  "type": "Feature",
  "properties": {
    "iso:country":"AU",
    "sg:address":"Level 10, 200 Mary St",
    "sg:city":"Brisbane",
    "sg:classifiers":[
        {
            "category":"Professional",
            "subcategory":"Engineering",
            "type":"Services"
        }
    ],
    "sg:phone":"+61 7 3295 1400",
    "sg:postcode":"4000",
    "sg:province":"QLD",
    "sg:tags":[
        "consulting",
        "engineer"
    ],
    "wof:name":"Bechtel Services (Australia) Pty Ltd",
    "wof:placetype":"venue"
},
  "geometry": {"coordinates":[153.029418945,-27.4702377319],"type":"Point"}
}