{
  "type": "Feature",
  "properties": {
    "iso:country":"AU",
    "sg:address":"67 Ilmenite Crs",
    "sg:city":"Capel",
    "sg:classifiers":[
        {
            "category":"Manufacturing",
            "subcategory":"Rubber & Plastics",
            "type":"Manufacturing & Wholesale Goods"
        }
    ],
    "sg:phone":"+61 8 9727 3120",
    "sg:postcode":"6271",
    "sg:province":"WA",
    "sg:tags":[
        "fabricator"
    ],
    "wof:name":"South West Industrial Plastics",
    "wof:placetype":"venue"
},
  "geometry": {"coordinates":[115.55467224100001,-33.5524711609],"type":"Point"}
}