{
  "type": "Feature",
  "properties": {
    "addr:full":"50 Nevin Drv Thomastown VIC 3074",
    "addr:housenumber":"50",
    "addr:postcode":"3074",
    "addr:street":"Nevin Drv",
    "iso:country":"AU",
    "sg:address":"50 Nevin Drv",
    "sg:city":"Thomastown",
    "sg:classifiers":[
        {
            "category":"Manufacturing",
            "subcategory":"Rubber & Plastics",
            "type":"Manufacturing & Wholesale Goods"
        }
    ],
    "sg:phone":"+61 3 9466 4422",
    "sg:postcode":"3074",
    "sg:province":"VIC",
    "sg:tags":[
        "fabricator"
    ],
    "wof:name":"Ausfab Plastics Australia Pty Ltd",
    "wof:placetype":"venue"
},
  "geometry": {"coordinates":[145.03352355999999,-37.6965103149],"type":"Point"}
}