{
  "type": "Feature",
  "properties": {
    "addr:full":"Paterson St Mundijong WA 6123",
    "addr:postcode":"6123",
    "addr:street":"Paterson St",
    "iso:country":"AU",
    "sg:address":"Paterson St",
    "sg:city":"Mundijong",
    "sg:classifiers":[
        {
            "category":"Government",
            "subcategory":"Post Office",
            "type":"Public Place"
        }
    ],
    "sg:phone":"+61 8 9525 5757",
    "sg:postcode":"6123",
    "sg:province":"WA",
    "sg:tags":[
        "postal"
    ],
    "wof:name":"Australia Post",
    "wof:placetype":"venue"
},
  "geometry": {"coordinates":[115.990379334,-32.2828330994],"type":"Point"}
}