{
  "type": "Feature",
  "properties": {
    "addr:full":"RMB 257 Barham NSW 2732",
    "addr:postcode":"2732",
    "iso:country":"AU",
    "sg:address":"RMB 257",
    "sg:city":"Barham",
    "sg:classifiers":[
        {
            "category":"Building & Trades",
            "subcategory":"Equipment Rental",
            "type":"Services"
        }
    ],
    "sg:phone":"+61 1800 644 369",
    "sg:postcode":"2732",
    "sg:province":"NSW",
    "sg:tags":[
        "supply",
        "catering"
    ],
    "wof:name":"A Osterley Catering Equipment Sales & Service",
    "wof:placetype":"venue"
},
  "geometry": {"coordinates":[144.127914,-35.624241],"type":"Point"}
}