{
  "type": "Feature",
  "properties": {
    "addr:full":"Shp 209/ 2 Hooker Blv Broadbeach Waters QLD 4218",
    "addr:housenumber":"209 / 2",
    "addr:postcode":"4218",
    "addr:street":"Hooker Blv Broadbeach",
    "iso:country":"AU",
    "sg:address":"Shp 209/ 2 Hooker Blv",
    "sg:city":"Broadbeach Waters",
    "sg:classifiers":[
        {
            "category":"Shopping",
            "subcategory":"Crafts & Fabrics",
            "type":"Retail Goods"
        }
    ],
    "sg:phone":"+61 7 5592 6303",
    "sg:postcode":"4218",
    "sg:province":"QLD",
    "sg:tags":[
        "supply"
    ],
    "wof:name":"Riot Art And Craft Kurc",
    "wof:placetype":"venue"
},
  "geometry": {"coordinates":[153.42514038100001,-28.0352897644],"type":"Point"}
}