{
  "type": "Feature",
  "properties": {
    "addr:full":"72 Mission Hill Rd Penguin TAS 7316",
    "addr:housenumber":"72",
    "addr:postcode":"7316",
    "addr:street":"Mission Hill Rd",
    "iso:country":"AU",
    "sg:address":"72 Mission Hill Rd",
    "sg:city":"Penguin",
    "sg:classifiers":[
        {
            "category":"Utilities",
            "subcategory":"Electric",
            "type":"Services"
        }
    ],
    "sg:phone":"+61 3 6437 1510",
    "sg:postcode":"7316",
    "sg:province":"TAS",
    "sg:tags":[
        "electrical",
        "contractor"
    ],
    "wof:name":"Brian Targett",
    "wof:placetype":"venue"
},
  "geometry": {"coordinates":[146.057830811,-41.1145172119],"type":"Point"}
}