{
  "type": "Feature",
  "properties": {
    "addr:full":"1188 Pacific Hwy Pymble NSW 2073",
    "addr:housenumber":"1188",
    "addr:postcode":"2073",
    "addr:street":"Pacific Hwy",
    "iso:country":"AU",
    "sg:address":"1188 Pacific Hwy",
    "sg:city":"Pymble",
    "sg:classifiers":[
        {
            "category":"Education",
            "subcategory":"Music School",
            "type":"Public Place"
        }
    ],
    "sg:phone":"+61 2 9488 8260",
    "sg:postcode":"2073",
    "sg:province":"NSW",
    "sg:tags":[
        "teacher"
    ],
    "wof:name":"Suzuki Talent Education Association of Aust (NSW) Inc",
    "wof:placetype":"venue"
},
  "geometry": {"coordinates":[151.13911438,-33.7420463562],"type":"Point"}
}