{
  "type": "Feature",
  "properties": {
    "addr:full":"118 Centre Dandenong Rd Dingley Village VIC 3172",
    "addr:housenumber":"118",
    "addr:postcode":"3172",
    "addr:street":"Centre Dandenong Rd",
    "iso:country":"AU",
    "sg:address":"118 Centre Dandenong Rd",
    "sg:city":"Dingley Village",
    "sg:classifiers":[
        {
            "category":"Health Services",
            "subcategory":"Chiropractor",
            "type":"Services"
        }
    ],
    "sg:phone":"+61 3 9558 1436",
    "sg:postcode":"3172",
    "sg:province":"VIC",
    "wof:name":"Novytarger Jonathan Dr",
    "wof:placetype":"venue"
},
  "geometry": {"coordinates":[145.13323974599999,-37.9843101501],"type":"Point"}
}