{
  "type": "Feature",
  "properties": {
    "addr:full":"Gatton Shopng Cntr 29 William St Gatton QLD 4343",
    "addr:housenumber":"29",
    "addr:postcode":"4343",
    "addr:street":"William St",
    "iso:country":"AU",
    "sg:address":"Gatton Shopng Cntr 29 William St",
    "sg:city":"Gatton",
    "sg:classifiers":[
        {
            "category":"Communications",
            "subcategory":"Film & Video Production",
            "type":"Services"
        }
    ],
    "sg:phone":"+61 7 5462 2888",
    "sg:postcode":"4343",
    "sg:province":"QLD",
    "sg:tags":[
        "dvd",
        "library"
    ],
    "wof:name":"Video Ezy",
    "wof:placetype":"venue"
},
  "geometry": {"coordinates":[152.278106689,-27.5599384308],"type":"Point"}
}