{
  "type": "Feature",
  "properties": {
    "addr:full":"PO Box 751 Kiama NSW 2533",
    "addr:postcode":"2533",
    "iso:country":"AU",
    "sg:address":"PO Box 751",
    "sg:city":"Kiama",
    "sg:classifiers":[
        {
            "category":"Professional",
            "subcategory":"Computer Services",
            "type":"Services"
        }
    ],
    "sg:phone":"+61 438 335 849",
    "sg:postcode":"2533",
    "sg:province":"NSW",
    "sg:tags":[
        "consultant",
        "system"
    ],
    "wof:name":"Binary Star Software",
    "wof:placetype":"venue"
},
  "geometry": {"coordinates":[150.851806641,-34.6771583557],"type":"Point"}
}