{
  "type": "Feature",
  "properties": {
    "addr:full":"314 Wattle St Ultimo NSW 2007",
    "addr:housenumber":"314",
    "addr:postcode":"2007",
    "addr:street":"Wattle St",
    "iso:country":"AU",
    "sg:address":"314 Wattle St",
    "sg:city":"Ultimo",
    "sg:classifiers":[
        {
            "category":"Shopping",
            "subcategory":"Computers & Home Electronics",
            "type":"Retail Goods"
        }
    ],
    "sg:phone":"+61 2 9571 1333",
    "sg:postcode":"2007",
    "sg:province":"NSW",
    "sg:tags":[
        "hire",
        "video",
        "game"
    ],
    "wof:name":"Reds Notebook World",
    "wof:placetype":"venue"
},
  "geometry": {"coordinates":[151.19508361800001,-33.8776092529],"type":"Point"}
}