{
  "type": "Feature",
  "properties": {
    "iso:country":"AU",
    "sg:address":"5/ 42 Junction Rd",
    "sg:city":"Burleigh",
    "sg:classifiers":[
        {
            "category":"Professional",
            "subcategory":"Business Services",
            "type":"Services"
        }
    ],
    "sg:phone":"+61 7 5593 5944",
    "sg:postcode":"4220",
    "sg:province":"QLD",
    "sg:tags":[
        "consultant",
        "promoter",
        "entertainment"
    ],
    "wof:name":"JVE Promotions",
    "wof:placetype":"venue"
},
  "geometry": {"coordinates":[153.42471313499999,-28.1072940826],"type":"Point"}
}