{
  "type": "Feature",
  "properties": {
    "addr:full":"29 Clancy St Boulder WA 6432",
    "addr:housenumber":"29",
    "addr:postcode":"6432",
    "addr:street":"Clancy St",
    "iso:country":"AU",
    "sg:address":"29 Clancy St",
    "sg:city":"Boulder",
    "sg:classifiers":[
        {
            "category":"Mining & Drilling",
            "type":"Manufacturing & Wholesale Goods"
        }
    ],
    "sg:phone":"+61 8 9093 4893",
    "sg:postcode":"6432",
    "sg:province":"WA",
    "sg:tags":[
        "equipment",
        "quarrying",
        "supply"
    ],
    "wof:name":"A T S Mining Maintenance",
    "wof:placetype":"venue"
},
  "geometry": {"coordinates":[121.490440369,-30.7768154144],"type":"Point"}
}