{
  "type": "Feature",
  "properties": {
    "iso:country":"AU",
    "sg:address":"22 Woodview Rd",
    "sg:city":"Springfield",
    "sg:classifiers":[
        {
            "category":"Health Services",
            "subcategory":"Health Practitioner",
            "type":"Services"
        }
    ],
    "sg:phone":"+61 412 540 237",
    "sg:postcode":"2250",
    "sg:province":"NSW",
    "sg:tags":[
        "pathologist",
        "speech"
    ],
    "wof:name":"Cheeky Monkeys Speech Pathology (Mobile Service)",
    "wof:placetype":"venue"
},
  "geometry": {"coordinates":[151.36541748100001,-33.4243621826],"type":"Point"}
}