{
  "type": "Feature",
  "properties": {
    "addr:full":"6 Barwell Ave Barmera SA 5345",
    "addr:housenumber":"6",
    "addr:postcode":"5345",
    "addr:street":"Barwell Ave",
    "iso:country":"AU",
    "sg:address":"6 Barwell Ave",
    "sg:city":"Barmera",
    "sg:classifiers":[
        {
            "category":"Food & Beverages",
            "subcategory":"Bakery",
            "type":"Retail Goods"
        }
    ],
    "sg:phone":"+61 8 8588 2138",
    "sg:postcode":"5345",
    "sg:province":"SA",
    "sg:tags":[
        "baker"
    ],
    "wof:name":"Barmera Bakery",
    "wof:placetype":"venue"
},
  "geometry": {"coordinates":[140.46409606899999,-34.2519683838],"type":"Point"}
}