{
  "type": "Feature",
  "properties": {
    "addr:full":"U 5/ 7 St Andrews Pl Cronulla NSW 2230",
    "addr:postcode":"2230",
    "addr:street":"Pl",
    "iso:country":"AU",
    "sg:address":"U 5/ 7 St Andrews Pl",
    "sg:city":"Cronulla",
    "sg:classifiers":[
        {
            "category":"Retail",
            "subcategory":"Auto Repair",
            "type":"Services"
        }
    ],
    "sg:phone":"+61 2 9527 4391",
    "sg:postcode":"2230",
    "sg:province":"NSW",
    "sg:tags":[
        "body",
        "motor",
        "trimmer"
    ],
    "wof:name":"Bright Carpet Cleaner Services",
    "wof:placetype":"venue"
},
  "geometry": {"coordinates":[151.14955139200001,-34.0516548157],"type":"Point"}
}