{
  "type": "Feature",
  "properties": {
    "addr:full":"16- 18 Grosvenor St Sydney NSW 2000",
    "addr:housenumber":"18",
    "addr:postcode":"2000",
    "addr:street":"Grosvenor St",
    "iso:country":"AU",
    "sg:address":"16- 18 Grosvenor St",
    "sg:city":"Sydney",
    "sg:classifiers":[
        {
            "category":"Communications",
            "type":"Services"
        }
    ],
    "sg:phone":"+61 1800 199 184",
    "sg:postcode":"2000",
    "sg:province":"NSW",
    "sg:tags":[
        "translation"
    ],
    "wof:name":"Paen Communications Ltd",
    "wof:placetype":"venue"
},
  "geometry": {"coordinates":[151.20576477,-33.8633155823],"type":"Point"}
}