{
  "type": "Feature",
  "properties": {
    "addr:full":"3-5 Awun Crt Springvale VIC 3171",
    "addr:housenumber":"3-5",
    "addr:postcode":"3171",
    "addr:street":"Awun Crt",
    "iso:country":"AU",
    "sg:address":"3-5 Awun Crt",
    "sg:city":"Springvale",
    "sg:classifiers":[
        {
            "category":"Shopping",
            "subcategory":"Gifts & Souvenirs",
            "type":"Retail Goods"
        }
    ],
    "sg:phone":"+61 3 9549 4700",
    "sg:postcode":"3171",
    "sg:province":"VIC",
    "sg:tags":[
        "wrapping"
    ],
    "wof:name":"All Australian Greetings",
    "wof:placetype":"venue"
},
  "geometry": {"coordinates":[145.143112183,-37.9456367493],"type":"Point"}
}