{
  "type": "Feature",
  "properties": {
    "addr:full":"265 Bourke St Melbourne VIC 3000",
    "addr:housenumber":"265",
    "addr:postcode":"3000",
    "addr:street":"Bourke St",
    "iso:country":"AU",
    "sg:address":"265 Bourke St",
    "sg:city":"Melbourne",
    "sg:classifiers":[
        {
            "category":"Shopping",
            "subcategory":"Mobile Phones",
            "type":"Retail Goods"
        }
    ],
    "sg:phone":"+61 3 8645 6110",
    "sg:postcode":"3000",
    "sg:province":"VIC",
    "sg:tags":[
        "telephone",
        "accessory"
    ],
    "wof:name":"Vodafone",
    "wof:placetype":"venue"
},
  "geometry": {"coordinates":[144.96582031200001,-37.8135948181],"type":"Point"}
}