{
  "type": "Feature",
  "properties": {
    "addr:full":"Tradelink Rd Browns Plains QLD 4118",
    "addr:postcode":"4118",
    "addr:street":"Tradelink Rd",
    "iso:country":"AU",
    "sg:address":"Tradelink Rd",
    "sg:city":"Browns Plains",
    "sg:classifiers":[
        {
            "category":"Retail",
            "subcategory":"Storage",
            "type":"Services"
        }
    ],
    "sg:phone":"+61 1800 806 840",
    "sg:postcode":"4118",
    "sg:province":"QLD",
    "wof:name":"Browns Plains Self Storage",
    "wof:placetype":"venue"
},
  "geometry": {"coordinates":[153.03315734899999,-27.6645565033],"type":"Point"}
}