{
  "type": "Feature",
  "properties": {
    "addr:full":"54 Manila St Beenleigh QLD 4207",
    "addr:housenumber":"54",
    "addr:postcode":"4207",
    "addr:street":"Manila St",
    "iso:country":"AU",
    "sg:address":"54 Manila St",
    "sg:city":"Beenleigh",
    "sg:classifiers":[
        {
            "category":"Personal",
            "subcategory":"Massage",
            "type":"Services"
        }
    ],
    "sg:phone":"+61 7 3807 1290",
    "sg:postcode":"4207",
    "sg:province":"QLD",
    "sg:tags":[
        "therapy"
    ],
    "wof:name":"Collard June",
    "wof:placetype":"venue"
},
  "geometry": {"coordinates":[153.199707031,-27.7145633698],"type":"Point"}
}