{
  "type": "Feature",
  "properties": {
    "addr:full":"Shop 1/ 208 Canterbury Rd Bayswater VIC 3153",
    "addr:housenumber":"shop 1 / 208",
    "addr:postcode":"3153",
    "addr:street":"Canterbury Rd",
    "iso:country":"AU",
    "sg:address":"Shop 1/ 208 Canterbury Rd",
    "sg:city":"Bayswater",
    "sg:phone":"+61 3 8727 7400",
    "sg:postcode":"3153",
    "sg:province":"VIC",
    "wof:name":"McCracken's Water Services",
    "wof:placetype":"venue"
},
  "geometry": {"coordinates":[145.281448364,-37.8278770447],"type":"Point"}
}