{
  "type": "Feature",
  "properties": {
    "iso:country":"AU",
    "sg:address":"2 Burrows Ave",
    "sg:city":"Kanahooka",
    "sg:classifiers":[
        {
            "category":"Building & Trades",
            "subcategory":"Cleaning & Sanitation",
            "type":"Services"
        }
    ],
    "sg:phone":"+61 411 733 303",
    "sg:postcode":"2530",
    "sg:province":"NSW",
    "sg:tags":[
        "industrial",
        "commercial",
        "contractor"
    ],
    "wof:name":"Wollongong ACS Pty Ltd",
    "wof:placetype":"venue"
},
  "geometry": {"coordinates":[150.817962647,-34.4956741333],"type":"Point"}
}