{
  "type": "Feature",
  "properties": {
    "addr:full":"Unit 1/ 16 Skinner St Hastings VIC 3915",
    "addr:housenumber":"16",
    "addr:postcode":"3915",
    "addr:street":"Skinner St",
    "iso:country":"AU",
    "sg:address":"Unit 1/ 16 Skinner St",
    "sg:city":"Hastings",
    "sg:classifiers":[
        {
            "category":"Building & Trades",
            "subcategory":"Construction",
            "type":"Services"
        }
    ],
    "sg:phone":"+61 439 435 008",
    "sg:postcode":"3915",
    "sg:province":"VIC",
    "sg:tags":[
        "fencing",
        "contractor"
    ],
    "wof:name":"Brett Hardman Pty Ltd",
    "wof:placetype":"venue"
},
  "geometry": {"coordinates":[145.194946289,-38.3114051819],"type":"Point"}
}