{
  "type": "Feature",
  "properties": {
    "addr:full":"66 Gordon St Brighton-le-Sands NSW 2216",
    "addr:housenumber":"66",
    "addr:postcode":"2216",
    "addr:street":"Gordon St",
    "iso:country":"AU",
    "sg:address":"66 Gordon St",
    "sg:city":"Brighton-le-Sands",
    "sg:classifiers":[
        {
            "category":"Professional",
            "subcategory":"Accounting & Tax Preparation",
            "type":"Services"
        }
    ],
    "sg:phone":"+61 2 9556 1913",
    "sg:postcode":"2216",
    "sg:province":"NSW",
    "sg:tags":[
        "accountant",
        "auditor"
    ],
    "wof:name":"Elias,Bastas & Associates",
    "wof:placetype":"venue"
},
  "geometry": {"coordinates":[151.152466,-33.957607],"type":"Point"}
}