{
  "type": "Feature",
  "properties": {
    "addr:full":"236 Coventry St South Melbourne VIC 3205",
    "addr:housenumber":"236",
    "addr:postcode":"3205",
    "addr:street":"Coventry St",
    "iso:country":"AU",
    "sg:address":"236 Coventry St",
    "sg:city":"South Melbourne",
    "sg:classifiers":[
        {
            "category":"Manufacturing",
            "subcategory":"Building Materials",
            "type":"Manufacturing & Wholesale Goods"
        }
    ],
    "sg:phone":"+61 3 9690 9292",
    "sg:postcode":"3205",
    "sg:province":"VIC",
    "sg:tags":[
        "stone",
        "product",
        "supply"
    ],
    "wof:name":"Country Floors",
    "wof:placetype":"venue"
},
  "geometry": {"coordinates":[144.96107499999999,-37.831463],"type":"Point"}
}