{
  "type": "Feature",
  "properties": {
    "addr:full":"174 Main St Croydon VIC 3136",
    "addr:housenumber":"174",
    "addr:postcode":"3136",
    "addr:street":"Main St",
    "iso:country":"AU",
    "sg:address":"174 Main St",
    "sg:city":"Croydon",
    "sg:classifiers":[
        {
            "category":"Internet Cafe",
            "subcategory":"None",
            "type":"Food & Drink"
        }
    ],
    "sg:phone":"+61 3 9725 2666",
    "sg:postcode":"3136",
    "sg:province":"VIC",
    "wof:name":"Network Nirvana",
    "wof:placetype":"venue"
},
  "geometry": {"coordinates":[145.28083801299999,-37.7979888916],"type":"Point"}
}