{
  "type": "Feature",
  "properties": {
    "iso:country":"AU",
    "sg:address":"PO Box 5089",
    "sg:city":"Falcon",
    "sg:classifiers":[
        {
            "category":"Building & Trades",
            "subcategory":"Plumbing",
            "type":"Services"
        }
    ],
    "sg:phone":"+61 8 9534 2692",
    "sg:postcode":"6210",
    "sg:province":"WA",
    "sg:tags":[
        "plumber",
        "gasfitters"
    ],
    "wof:name":"Rod Finlay Plumbing",
    "wof:placetype":"venue"
},
  "geometry": {"coordinates":[115.662193,-32.581299],"type":"Point"}
}