{
  "type": "Feature",
  "properties": {
    "addr:full":"18 Robinson St Thorpdale VIC 3835",
    "addr:housenumber":"18",
    "addr:postcode":"3835",
    "addr:street":"Robinson St",
    "iso:country":"AU",
    "sg:address":"18 Robinson St",
    "sg:city":"Thorpdale",
    "sg:classifiers":[
        {
            "category":"Manufacturing",
            "subcategory":"Soap",
            "type":"Manufacturing & Wholesale Goods"
        }
    ],
    "sg:phone":"+61 3 5634 6261",
    "sg:postcode":"3835",
    "sg:province":"VIC",
    "sg:tags":[
        "detergent"
    ],
    "wof:name":"Gippsland Soap Distributors",
    "wof:placetype":"venue"
},
  "geometry": {"coordinates":[146.17465200000001,-38.305519],"type":"Point"}
}