{
  "type": "Feature",
  "properties": {
    "iso:country":"AU",
    "sg:address":"1107 Bannockburn-Shelford Rd",
    "sg:city":"Teesdale",
    "sg:classifiers":[
        {
            "category":"Education",
            "subcategory":"Kindergarten",
            "type":"Public Place"
        }
    ],
    "sg:phone":"+61 3 5281 5488",
    "sg:postcode":"3328",
    "sg:province":"VIC",
    "sg:tags":[
        "pre-schools"
    ],
    "wof:name":"Teesdale Pre-School",
    "wof:placetype":"venue"
},
  "geometry": {"coordinates":[144.062622,-38.022308],"type":"Point"}
}