{
  "type": "Feature",
  "properties": {
    "iso:country":"AU",
    "sg:address":"31- 33 King George St",
    "sg:city":"Cohuna",
    "sg:classifiers":[
        {
            "category":"Shopping",
            "subcategory":"Shoes",
            "type":"Retail Goods"
        }
    ],
    "sg:phone":"+61 3 5456 2164",
    "sg:postcode":"3568",
    "sg:province":"VIC",
    "sg:tags":[
        "footwear"
    ],
    "wof:name":"Halls Footwear",
    "wof:placetype":"venue"
},
  "geometry": {"coordinates":[144.221099853,-35.8085784912],"type":"Point"}
}