{
  "type": "Feature",
  "properties": {
    "addr:full":"373 Gosport St Moree NSW 2400",
    "addr:housenumber":"373",
    "addr:postcode":"2400",
    "addr:street":"Gosport St",
    "iso:country":"AU",
    "sg:address":"373 Gosport St",
    "sg:city":"Moree",
    "sg:classifiers":[
        {
            "category":"Professional",
            "subcategory":"Detective & Security Services",
            "type":"Services"
        }
    ],
    "sg:phone":"+61 2 6752 1666",
    "sg:postcode":"2400",
    "sg:province":"NSW",
    "sg:tags":[
        "equipment",
        "window",
        "doors"
    ],
    "wof:name":"Moree Aluminium & Glass",
    "wof:placetype":"venue"
},
  "geometry": {"coordinates":[149.84718322800001,-29.4759540558],"type":"Point"}
}