{
  "type": "Feature",
  "properties": {
    "addr:full":"133 Victoria Ave Chatswood NSW 2067",
    "addr:housenumber":"133",
    "addr:postcode":"2067",
    "addr:street":"Victoria Ave",
    "iso:country":"AU",
    "sg:address":"133 Victoria Ave",
    "sg:city":"Chatswood",
    "sg:classifiers":[
        {
            "category":"Health Services",
            "subcategory":"Medical Lab",
            "type":"Services"
        }
    ],
    "sg:phone":"+61 2 9417 1940",
    "sg:postcode":"2067",
    "sg:province":"NSW",
    "sg:tags":[
        "laboratory",
        "pathology"
    ],
    "wof:name":"Sydney Skin Pathology",
    "wof:placetype":"venue"
},
  "geometry": {"coordinates":[151.19578552199999,-33.7922019958],"type":"Point"}
}