{
  "type": "Feature",
  "properties": {
    "addr:full":"106 Childs Rd Epping VIC 3076",
    "addr:housenumber":"106",
    "addr:postcode":"3076",
    "addr:street":"Childs Rd",
    "iso:country":"AU",
    "sg:address":"106 Childs Rd",
    "sg:city":"Epping",
    "sg:classifiers":[
        {
            "category":"Professional",
            "subcategory":"Art Services",
            "type":"Services"
        }
    ],
    "sg:phone":"+61 3 9408 4846",
    "sg:postcode":"3076",
    "sg:province":"VIC",
    "sg:tags":[
        "graphic",
        "designer"
    ],
    "wof:name":"Createnz Designz",
    "wof:placetype":"venue"
},
  "geometry": {"coordinates":[145.01512145999999,-37.6591758728],"type":"Point"}
}