{
  "type": "Feature",
  "properties": {
    "addr:full":"68 Salerno St Surfers Paradise QLD 4217",
    "addr:housenumber":"68",
    "addr:postcode":"4217",
    "addr:street":"Salerno St",
    "iso:country":"AU",
    "sg:address":"68 Salerno St",
    "sg:city":"Surfers Paradise",
    "sg:classifiers":[
        {
            "category":"Real Estate",
            "subcategory":"Developer",
            "type":"Services"
        }
    ],
    "sg:phone":"+61 7 5538 6009",
    "sg:postcode":"4217",
    "sg:province":"QLD",
    "sg:tags":[
        "development"
    ],
    "wof:name":"Clubb Group Of Companies",
    "wof:placetype":"venue"
},
  "geometry": {"coordinates":[153.418655395,-28.013376236],"type":"Point"}
}