{
  "type": "Feature",
  "properties": {
    "iso:country":"AU",
    "sg:address":"Ingall St",
    "sg:city":"Mayfield",
    "sg:classifiers":[
        {
            "category":"Professional",
            "type":"Services"
        }
    ],
    "sg:phone":"+61 2 4935 4328",
    "sg:postcode":"2304",
    "sg:province":"NSW",
    "sg:tags":[
        "transport"
    ],
    "wof:name":"Mannway Logistics",
    "wof:placetype":"venue"
},
  "geometry": {"coordinates":[151.74693298299999,-32.9000205994],"type":"Point"}
}