{
  "type": "Feature",
  "properties": {
    "iso:country":"AU",
    "sg:address":"17 Archimedes Pl",
    "sg:city":"Murarrie",
    "sg:classifiers":[
        {
            "category":"Wholesale",
            "subcategory":"Machinery & Supplies",
            "type":"Manufacturing & Wholesale Goods"
        }
    ],
    "sg:phone":"+61 7 3902 5444",
    "sg:postcode":"4172",
    "sg:province":"QLD",
    "sg:tags":[
        "engine",
        "petrol"
    ],
    "wof:name":"QL Accessories",
    "wof:placetype":"venue"
},
  "geometry": {"coordinates":[153.10304260300001,-27.4524745941],"type":"Point"}
}