{
  "type": "Feature",
  "properties": {
    "addr:full":"PO Box 114 Punchbowl NSW 2196",
    "addr:postcode":"2196",
    "iso:country":"AU",
    "sg:address":"PO Box 114",
    "sg:city":"Punchbowl",
    "sg:classifiers":[
        {
            "category":"Building & Trades",
            "subcategory":"Construction",
            "type":"Services"
        }
    ],
    "sg:phone":"+61 2 9592 3795",
    "sg:postcode":"2196",
    "sg:province":"NSW",
    "sg:tags":[
        "contractor"
    ],
    "wof:name":"Allan Top Roofing Pty LTd",
    "wof:placetype":"venue"
},
  "geometry": {"coordinates":[151.053741,-33.92585],"type":"Point"}
}