{
  "type": "Feature",
  "properties": {
    "addr:full":"U 3/ 2908 Logan Rd Underwood QLD 4119",
    "addr:housenumber":"/ 2908",
    "addr:postcode":"4119",
    "addr:street":"Logan Rd",
    "iso:country":"AU",
    "sg:address":"U 3/ 2908 Logan Rd",
    "sg:city":"Underwood",
    "sg:classifiers":[
        {
            "category":"Banks & Credit Unions",
            "subcategory":"Investment Brokerage",
            "type":"Services"
        }
    ],
    "sg:phone":"+61 7 3423 3877",
    "sg:postcode":"4119",
    "sg:province":"QLD",
    "sg:tags":[
        "finance",
        "broker"
    ],
    "wof:name":"Gold Seal Finance",
    "wof:placetype":"venue"
},
  "geometry": {"coordinates":[153.11134338400001,-27.6070709229],"type":"Point"}
}