{
  "type": "Feature",
  "properties": {
    "addr:full":"173 River St Maclean NSW 2463",
    "addr:housenumber":"173",
    "addr:postcode":"2463",
    "addr:street":"River St",
    "iso:country":"AU",
    "sg:address":"173 River St",
    "sg:city":"Maclean",
    "sg:classifiers":[
        {
            "category":"Travel",
            "subcategory":"Hotels & Motels",
            "type":"Entertainment"
        }
    ],
    "sg:phone":"+61 2 6645 2088",
    "sg:postcode":"2463",
    "sg:province":"NSW",
    "sg:tags":[
        "accommodation"
    ],
    "wof:name":"Clarence Hotel",
    "wof:placetype":"venue"
},
  "geometry": {"coordinates":[153.19700622600001,-29.4548664093],"type":"Point"}
}