{
  "type": "Feature",
  "properties": {
    "iso:country":"AU",
    "sg:address":"PO Box 667",
    "sg:city":"Emerald",
    "sg:classifiers":[
        {
            "category":"Retail",
            "subcategory":"Driving School",
            "type":"Services"
        }
    ],
    "sg:phone":"+61 1300 782 119",
    "sg:postcode":"3782",
    "sg:province":"VIC",
    "wof:name":"K & M Driving School",
    "wof:placetype":"venue"
},
  "geometry": {"coordinates":[145.441025,-37.932072],"type":"Point"}
}