{
  "type": "Feature",
  "properties": {
    "iso:country":"AU",
    "sg:address":"12 Arvenis Crs",
    "sg:city":"Balgownie",
    "sg:classifiers":[
        {
            "category":"Building & Trades",
            "subcategory":"Construction",
            "type":"Services"
        }
    ],
    "sg:phone":"+61 2 4283 7580",
    "sg:postcode":"2519",
    "sg:province":"NSW",
    "sg:tags":[
        "waterproofing",
        "contractor"
    ],
    "wof:name":"Coachwood Plans & Engineering Services",
    "wof:placetype":"venue"
},
  "geometry": {"coordinates":[150.878143,-34.388649],"type":"Point"}
}