{
  "type": "Feature",
  "properties": {
    "addr:full":"Cnr Bennett Rd & Autumnleaf Pde 165 Bennett Rd St Clair NSW 2759",
    "addr:housenumber":"165",
    "addr:postcode":"2759",
    "addr:street":"Cnr Bennett Rd & Autumnleaf Pde;Bennett Rd",
    "iso:country":"AU",
    "sg:address":"Cnr Bennett Rd & Autumnleaf Pde 165 Bennett Rd",
    "sg:city":"St Clair",
    "sg:classifiers":[
        {
            "category":"Social Services",
            "subcategory":"Child Care",
            "type":"Services"
        }
    ],
    "sg:phone":"+61 2 9834 1636",
    "sg:postcode":"2759",
    "sg:province":"NSW",
    "wof:name":"Harold Wheen Pre School",
    "wof:placetype":"venue"
},
  "geometry": {"coordinates":[150.79022216800001,-33.7957687378],"type":"Point"}
}