{
  "type": "Feature",
  "properties": {
    "iso:country":"AU",
    "sg:address":"2 Henty St",
    "sg:city":"Dandenong",
    "sg:classifiers":[
        {
            "category":"Personal",
            "subcategory":"Massage",
            "type":"Services"
        }
    ],
    "sg:phone":"+61 3 9791 8757",
    "sg:postcode":"3175",
    "sg:province":"VIC",
    "sg:tags":[
        "therapy"
    ],
    "wof:name":"Robinson M.D.",
    "wof:placetype":"venue"
},
  "geometry": {"coordinates":[145.21171569800001,-37.9818878174],"type":"Point"}
}