{
  "type": "Feature",
  "properties": {
    "addr:full":"Lot238/ Brookman Rd Meadows SA 5201",
    "addr:postcode":"5201",
    "addr:street":"Brookman Rd",
    "iso:country":"AU",
    "sg:address":"Lot238/ Brookman Rd",
    "sg:city":"Meadows",
    "sg:classifiers":[
        {
            "category":"Organizations",
            "subcategory":"Membership Organization",
            "type":"Services"
        }
    ],
    "sg:phone":"+61 8 8388 3936",
    "sg:postcode":"5201",
    "sg:province":"SA",
    "sg:tags":[
        "support",
        "health",
        "organisation"
    ],
    "wof:name":"Recovery Support Incorporated",
    "wof:placetype":"venue"
},
  "geometry": {"coordinates":[138.73806762699999,-35.1834983826],"type":"Point"}
}