{
  "type": "Feature",
  "properties": {
    "addr:full":"12/ 6 Chaplin Drv Lane Cove NSW 2066",
    "addr:housenumber":"12 / 6",
    "addr:postcode":"2066",
    "addr:street":"Chaplin Drv",
    "iso:country":"AU",
    "sg:address":"12/ 6 Chaplin Drv",
    "sg:city":"Lane Cove",
    "sg:classifiers":[
        {
            "category":"Shopping",
            "subcategory":"Stationery & Office Supplies",
            "type":"Retail Goods"
        }
    ],
    "sg:phone":"+61 2 9427 7433",
    "sg:postcode":"2066",
    "sg:province":"NSW",
    "sg:tags":[
        "partition"
    ],
    "wof:name":"Neech + Szoko",
    "wof:placetype":"venue"
},
  "geometry": {"coordinates":[151.147949219,-33.809803009],"type":"Point"}
}