{
  "type": "Feature",
  "properties": {
    "addr:full":"13/ 180 South Creek Rd Wheeler Heights NSW 2097",
    "addr:housenumber":"13 / 180",
    "addr:postcode":"2097",
    "addr:street":"South Creek Rd",
    "iso:country":"AU",
    "sg:address":"13/ 180 South Creek Rd",
    "sg:city":"Wheeler Heights",
    "sg:classifiers":[
        {
            "category":"Health Services",
            "subcategory":"Dentist",
            "type":"Services"
        }
    ],
    "sg:phone":"+61 2 9981 3055",
    "sg:postcode":"2097",
    "sg:province":"NSW",
    "wof:name":"Chow M Dr",
    "wof:placetype":"venue"
},
  "geometry": {"coordinates":[151.278533936,-33.7326774597],"type":"Point"}
}