{
  "type": "Feature",
  "properties": {
    "addr:full":"Gangemi Rd Cowley QLD 4871",
    "addr:postcode":"4871",
    "addr:street":"Gangemi Rd",
    "iso:country":"AU",
    "sg:address":"Gangemi Rd",
    "sg:city":"Cowley",
    "sg:classifiers":[
        {
            "category":"Building & Trades",
            "subcategory":"Construction",
            "type":"Services"
        }
    ],
    "sg:phone":"+61 429 654 811",
    "sg:postcode":"4871",
    "sg:province":"QLD",
    "sg:tags":[
        "earth",
        "excavating",
        "moving",
        "contractor"
    ],
    "wof:name":"A &L Puccini Excavations",
    "wof:placetype":"venue"
},
  "geometry": {"coordinates":[146.078201294,-17.6901245117],"type":"Point"}
}