{
  "type": "Feature",
  "properties": {
    "addr:full":"35 Roberts St Kingsville VIC 3012",
    "addr:housenumber":"35",
    "addr:postcode":"3012",
    "addr:street":"Roberts St",
    "iso:country":"AU",
    "sg:address":"35 Roberts St",
    "sg:city":"Kingsville",
    "sg:classifiers":[
        {
            "category":"Social Services",
            "subcategory":"Child Care",
            "type":"Services"
        }
    ],
    "sg:phone":"+61 3 9315 2012",
    "sg:postcode":"3012",
    "sg:province":"VIC",
    "sg:tags":[
        "support",
        "health"
    ],
    "wof:name":"Maternal & Child Health Centres",
    "wof:placetype":"venue"
},
  "geometry": {"coordinates":[144.87098693900001,-37.8051757812],"type":"Point"}
}