{
  "type": "Feature",
  "properties": {
    "addr:full":"4/ 32 Craftsman Ave Berkeley Vale NSW 2261",
    "addr:housenumber":"/ 32",
    "addr:postcode":"2261",
    "addr:street":"Craftsman Ave",
    "iso:country":"AU",
    "sg:address":"4/ 32 Craftsman Ave",
    "sg:city":"Berkeley Vale",
    "sg:classifiers":[
        {
            "category":"Wholesale",
            "subcategory":"Metals & Minerals",
            "type":"Manufacturing & Wholesale Goods"
        }
    ],
    "sg:phone":"+61 2 4388 2896",
    "sg:postcode":"2261",
    "sg:province":"NSW",
    "sg:tags":[
        "steel",
        "stainless",
        "product",
        "equipment"
    ],
    "wof:name":"Master Stainless",
    "wof:placetype":"venue"
},
  "geometry": {"coordinates":[151.42291299999999,-33.327122],"type":"Point"}
}