{
  "type": "Feature",
  "properties": {
    "iso:country":"AU",
    "sg:address":"Eungella Rd",
    "sg:city":"Gargett",
    "sg:classifiers":[
        {
            "category":"Food & Beverages",
            "subcategory":"Groceries & Convenience Stores",
            "type":"Retail Goods"
        }
    ],
    "sg:phone":"+61 7 4958 5175",
    "sg:postcode":"4741",
    "sg:province":"QLD",
    "wof:name":"Gargett Store",
    "wof:placetype":"venue"
},
  "geometry": {"coordinates":[148.746246,-21.156059],"type":"Point"}
}