{
  "type": "Feature",
  "properties": {
    "iso:country":"AU",
    "sg:address":"1 Moselle Crt",
    "sg:city":"Morayfield",
    "sg:classifiers":[
        {
            "category":"Building & Trades",
            "subcategory":"Construction",
            "type":"Services"
        }
    ],
    "sg:phone":"+61 7 5497 9992",
    "sg:postcode":"4506",
    "sg:province":"QLD",
    "sg:tags":[
        "contractor"
    ],
    "wof:name":"Buckett Peter",
    "wof:placetype":"venue"
},
  "geometry": {"coordinates":[152.91268920900001,-27.1319446564],"type":"Point"}
}