{
  "type": "Feature",
  "properties": {
    "iso:country":"AU",
    "sg:address":"4/ 229 Hampton Rd",
    "sg:city":"South Fremantle",
    "sg:classifiers":[
        {
            "category":"Home & Garden",
            "subcategory":"Building Materials",
            "type":"Retail Goods"
        }
    ],
    "sg:phone":"+61 8 9336 2569",
    "sg:postcode":"6162",
    "sg:province":"WA",
    "sg:tags":[
        "secondhand"
    ],
    "wof:name":"Cottage Demolition",
    "wof:placetype":"venue"
},
  "geometry": {"coordinates":[115.760178,-32.074512],"type":"Point"}
}