{
  "type": "Feature",
  "properties": {
    "addr:full":"25 Liguria St Coogee NSW 2034",
    "addr:housenumber":"25",
    "addr:postcode":"2034",
    "addr:street":"Liguria St",
    "iso:country":"AU",
    "sg:address":"25 Liguria St",
    "sg:city":"Coogee",
    "sg:classifiers":[
        {
            "category":"Professional",
            "subcategory":"Art Services",
            "type":"Services"
        }
    ],
    "sg:phone":"+61 2 9349 4231",
    "sg:postcode":"2034",
    "sg:province":"NSW",
    "sg:tags":[
        "interior",
        "decorator"
    ],
    "wof:name":"Accent Interiors",
    "wof:placetype":"venue"
},
  "geometry": {"coordinates":[151.25955200199999,-33.9361228943],"type":"Point"}
}