{
  "type": "Feature",
  "properties": {
    "iso:country":"AU",
    "sg:address":"178 Churchill Ave",
    "sg:city":"Braybrook",
    "sg:classifiers":[
        {
            "category":"Food & Beverages",
            "subcategory":"Bakery",
            "type":"Retail Goods"
        }
    ],
    "sg:phone":"+61 3 9311 1096",
    "sg:postcode":"3019",
    "sg:province":"VIC",
    "sg:tags":[
        "baker"
    ],
    "wof:name":"Masarap Bakery",
    "wof:placetype":"venue"
},
  "geometry": {"coordinates":[144.85252380399999,-37.7863807678],"type":"Point"}
}