{
  "type": "Feature",
  "properties": {
    "addr:full":"385 Little Lonsdale St Melbourne VIC 3000",
    "addr:housenumber":"385",
    "addr:postcode":"3000",
    "addr:street":"Little Lonsdale St",
    "iso:country":"AU",
    "sg:address":"385 Little Lonsdale St",
    "sg:city":"Melbourne",
    "sg:classifiers":[
        {
            "category":"Professional",
            "subcategory":"Accounting & Tax Preparation",
            "type":"Services"
        }
    ],
    "sg:phone":"+61 3 9670 2110",
    "sg:postcode":"3000",
    "sg:province":"VIC",
    "sg:tags":[
        "accountant",
        "auditor"
    ],
    "wof:name":"James B Sidak & Associates Pty Ltd",
    "wof:placetype":"venue"
},
  "geometry": {"coordinates":[144.95967102,-37.8123397827],"type":"Point"}
}