{
  "type": "Feature",
  "properties": {
    "iso:country":"AU",
    "sg:address":"7 Robinia Drv",
    "sg:city":"Bowral",
    "sg:classifiers":[
        {
            "category":"Building & Trades",
            "subcategory":"Construction",
            "type":"Services"
        }
    ],
    "sg:phone":"+61 407 917 649",
    "sg:postcode":"2576",
    "sg:province":"NSW",
    "sg:tags":[
        "repair",
        "maintenance",
        "contractor"
    ],
    "wof:name":"Darren Meyers Carpentry",
    "wof:placetype":"venue"
},
  "geometry": {"coordinates":[150.440216064,-34.4985771179],"type":"Point"}
}