{
  "type": "Feature",
  "properties": {
    "addr:full":"33 Bunya Lake Crt Bunya QLD 4055",
    "addr:housenumber":"33",
    "addr:postcode":"4055",
    "addr:street":"Bunya Lake Crt",
    "iso:country":"AU",
    "sg:address":"33 Bunya Lake Crt",
    "sg:city":"Bunya",
    "sg:classifiers":[
        {
            "category":"Building & Trades",
            "subcategory":"Construction",
            "type":"Services"
        }
    ],
    "sg:phone":"+61 1800 466 388",
    "sg:postcode":"4055",
    "sg:province":"QLD",
    "sg:tags":[
        "contractor"
    ],
    "sg:website":"http://www.homedesign.net.au",
    "wof:name":"Home Design Building Group",
    "wof:placetype":"venue"
},
  "geometry": {"coordinates":[152.94105529800001,-27.3609485626],"type":"Point"}
}