{
  "type": "Feature",
  "properties": {
    "addr:full":"16 Sanford Rd Albany WA 6330",
    "addr:housenumber":"16",
    "addr:postcode":"6330",
    "addr:street":"Sanford Rd",
    "iso:country":"AU",
    "sg:address":"16 Sanford Rd",
    "sg:city":"Albany",
    "sg:classifiers":[
        {
            "category":"Retail",
            "subcategory":"Auto Repair",
            "type":"Services"
        }
    ],
    "sg:phone":"+61 8 9841 8777",
    "sg:postcode":"6330",
    "sg:province":"WA",
    "sg:tags":[
        "repairer",
        "motor",
        "engineer"
    ],
    "wof:name":"Dowsetts Automotive Service",
    "wof:placetype":"venue"
},
  "geometry": {"coordinates":[117.879966736,-35.0163192749],"type":"Point"}
}