{
  "type": "Feature",
  "properties": {
    "addr:full":"3- 9 Greg St Hazelbrook NSW 2779",
    "addr:housenumber":"9",
    "addr:postcode":"2779",
    "addr:street":"Greg St",
    "iso:country":"AU",
    "sg:address":"3- 9 Greg St",
    "sg:city":"Hazelbrook",
    "sg:classifiers":[
        {
            "category":"Utilities",
            "subcategory":"Water",
            "type":"Services"
        }
    ],
    "sg:phone":"+61 2 4759 1514",
    "sg:postcode":"2779",
    "sg:province":"NSW",
    "sg:tags":[
        "hot",
        "system"
    ],
    "wof:name":"Ciosmak P J",
    "wof:placetype":"venue"
},
  "geometry": {"coordinates":[150.446243286,-33.7221221924],"type":"Point"}
}