{
  "type": "Feature",
  "properties": {
    "addr:full":"3 Kelso Crs Moorebank NSW 2170",
    "addr:housenumber":"3",
    "addr:postcode":"2170",
    "addr:street":"Kelso Crs",
    "iso:country":"AU",
    "sg:address":"3 Kelso Crs",
    "sg:city":"Moorebank",
    "sg:classifiers":[
        {
            "category":"Shopping",
            "subcategory":"Stationery & Office Supplies",
            "type":"Retail Goods"
        }
    ],
    "sg:phone":"+61 2 9602 3565",
    "sg:postcode":"2170",
    "sg:province":"NSW",
    "sg:tags":[
        "equipment",
        "display",
        "exhibition"
    ],
    "wof:name":"Display Resources Pty Ltd",
    "wof:placetype":"venue"
},
  "geometry": {"coordinates":[150.922927856,-33.9513893127],"type":"Point"}
}