{
  "type": "Feature",
  "properties": {
    "addr:full":"58 Stirling Rd Port Augusta SA 5700",
    "addr:housenumber":"58",
    "addr:postcode":"5700",
    "addr:street":"Stirling Rd",
    "iso:country":"AU",
    "sg:address":"58 Stirling Rd",
    "sg:city":"Port Augusta",
    "sg:classifiers":[
        {
            "category":"Health Services",
            "subcategory":"Chiropractor",
            "type":"Services"
        }
    ],
    "sg:phone":"+61 8 8642 6111",
    "sg:postcode":"5700",
    "sg:province":"SA",
    "wof:name":"Hunter Andrew",
    "wof:placetype":"venue"
},
  "geometry": {"coordinates":[137.77281189000001,-32.4998588562],"type":"Point"}
}