{
  "type": "Feature",
  "properties": {
    "iso:country":"AU",
    "sg:address":"3 Macauleys Headland Drv",
    "sg:city":"Coffs Harbour",
    "sg:classifiers":[
        {
            "category":"Social Services",
            "subcategory":"Retirement Home",
            "type":"Services"
        }
    ],
    "sg:phone":"+61 2 6652 3606",
    "sg:postcode":"2450",
    "sg:province":"NSW",
    "sg:tags":[
        "environmental",
        "consultant",
        "pollution"
    ],
    "wof:name":"Clarke H K & Associates Pty Ltd - NOISE CONSULTANTS",
    "wof:placetype":"venue"
},
  "geometry": {"coordinates":[153.136887,-30.276739],"type":"Point"}
}