{
  "type": "Feature",
  "properties": {
    "addr:full":"118 Manning River Drv Taree South NSW 2430",
    "addr:housenumber":"118",
    "addr:postcode":"2430",
    "addr:street":"Manning River Drv",
    "iso:country":"AU",
    "sg:address":"118 Manning River Drv",
    "sg:city":"Taree South",
    "sg:classifiers":[
        {
            "category":"Home & Garden",
            "subcategory":"Building Materials",
            "type":"Retail Goods"
        }
    ],
    "sg:phone":"+61 2 6557 8100",
    "sg:postcode":"2430",
    "sg:province":"NSW",
    "sg:tags":[
        "fitting",
        "door"
    ],
    "wof:name":"Taree Recycled Building Materials",
    "wof:placetype":"venue"
},
  "geometry": {"coordinates":[152.48904400000001,-31.899965],"type":"Point"}
}