{
  "type": "Feature",
  "properties": {
    "addr:full":"U7/ 337 Aroo Rd Ulladulla NSW 2539",
    "addr:housenumber":"337",
    "addr:postcode":"2539",
    "addr:street":"U7 /;Aroo Rd",
    "iso:country":"AU",
    "sg:address":"U7/ 337 Aroo Rd",
    "sg:city":"Ulladulla",
    "sg:classifiers":[
        {
            "category":"Retail",
            "subcategory":"Auto Repair",
            "type":"Services"
        }
    ],
    "sg:phone":"+61 2 4454 1600",
    "sg:postcode":"2539",
    "sg:province":"NSW",
    "sg:tags":[
        "beater",
        "painter",
        "panel"
    ],
    "wof:name":"Coast Auto Body Restorations",
    "wof:placetype":"venue"
},
  "geometry": {"coordinates":[150.461013794,-35.3701972961],"type":"Point"}
}