{
  "type": "Feature",
  "properties": {
    "addr:full":"Ste204/ 86 Murray St Hobart TAS 7000",
    "addr:housenumber":"86",
    "addr:postcode":"7000",
    "addr:street":"Murray St",
    "iso:country":"AU",
    "sg:address":"Ste204/ 86 Murray St",
    "sg:city":"Hobart",
    "sg:classifiers":[
        {
            "category":"Education",
            "subcategory":"Music School",
            "type":"Public Place"
        }
    ],
    "sg:phone":"+61 3 6224 8778",
    "sg:postcode":"7000",
    "sg:province":"TAS",
    "sg:tags":[
        "therapy",
        "relaxation"
    ],
    "wof:name":"Stress Resolution",
    "wof:placetype":"venue"
},
  "geometry": {"coordinates":[147.32612609899999,-42.8829994202],"type":"Point"}
}