{
  "type": "Feature",
  "properties": {
    "addr:full":"237 Boorowa St Young NSW 2594",
    "addr:housenumber":"237",
    "addr:postcode":"2594",
    "addr:street":"Boorowa St",
    "iso:country":"AU",
    "sg:address":"237 Boorowa St",
    "sg:city":"Young",
    "sg:classifiers":[
        {
            "category":"Communications",
            "subcategory":"Film & Video Production",
            "type":"Services"
        }
    ],
    "sg:phone":"+61 2 6382 3716",
    "sg:postcode":"2594",
    "sg:province":"NSW",
    "sg:tags":[
        "dvd",
        "library"
    ],
    "wof:name":"Video Ezy (Young)",
    "wof:placetype":"venue"
},
  "geometry": {"coordinates":[148.293212891,-34.3122787476],"type":"Point"}
}