{
  "type": "Feature",
  "properties": {
    "addr:full":"57 Pilkington St Garbutt QLD 4814",
    "addr:housenumber":"57",
    "addr:postcode":"4814",
    "addr:street":"Pilkington St",
    "iso:country":"AU",
    "sg:address":"57 Pilkington St",
    "sg:city":"Garbutt",
    "sg:classifiers":[
        {
            "category":"Retail",
            "subcategory":"Auto Repair",
            "type":"Services"
        }
    ],
    "sg:phone":"+61 7 4779 9570",
    "sg:postcode":"4814",
    "sg:province":"QLD",
    "sg:tags":[
        "repairer",
        "motor",
        "engineer"
    ],
    "wof:name":"Kirby's Automotive Centre",
    "wof:placetype":"venue"
},
  "geometry": {"coordinates":[146.766876,-19.271261],"type":"Point"}
}