{
  "type": "Feature",
  "properties": {
    "addr:full":"10 Pope St Beverley SA 5009",
    "addr:housenumber":"10",
    "addr:postcode":"5009",
    "addr:street":"Pope St",
    "iso:country":"AU",
    "sg:address":"10 Pope St",
    "sg:city":"Beverley",
    "sg:classifiers":[
        {
            "category":"Professional",
            "type":"Services"
        }
    ],
    "sg:phone":"+61 8 8345 0546",
    "sg:postcode":"5009",
    "sg:province":"SA",
    "sg:tags":[
        "shop",
        "fitting"
    ],
    "wof:name":"Image Shopfitting & Constructions",
    "wof:placetype":"venue"
},
  "geometry": {"coordinates":[138.54412841800001,-34.8898582458],"type":"Point"}
}