{
  "type": "Feature",
  "properties": {
    "iso:country":"AU",
    "sg:address":"23 - 29 Factory St",
    "sg:city":"Granville",
    "sg:classifiers":[
        {
            "category":"Communications",
            "type":"Services"
        }
    ],
    "sg:phone":"+61 1300 765 657",
    "sg:postcode":"2142",
    "sg:province":"NSW",
    "sg:tags":[
        "equipment",
        "radio"
    ],
    "wof:name":"Dataryte Technology",
    "wof:placetype":"venue"
},
  "geometry": {"coordinates":[151.01559448200001,-33.8404121399],"type":"Point"}
}