{
  "type": "Feature",
  "properties": {
    "addr:full":"17 Cranbourne Pl Cranbourne VIC 3977",
    "addr:housenumber":"17",
    "addr:postcode":"3977",
    "addr:street":"Cranbourne Pl",
    "iso:country":"AU",
    "sg:address":"17 Cranbourne Pl",
    "sg:city":"Cranbourne",
    "sg:classifiers":[
        {
            "category":"Health Services",
            "subcategory":"Chiropractor",
            "type":"Services"
        }
    ],
    "sg:phone":"+61 3 5996 8222",
    "sg:postcode":"3977",
    "sg:province":"VIC",
    "wof:name":"Hamod Carol Dr",
    "wof:placetype":"venue"
},
  "geometry": {"coordinates":[145.28160095199999,-38.0966758728],"type":"Point"}
}