{
  "type": "Feature",
  "properties": {
    "addr:full":"5 Alcock Rd Elimbah QLD 4516",
    "addr:housenumber":"5",
    "addr:postcode":"4516",
    "addr:street":"Alcock Rd",
    "iso:country":"AU",
    "sg:address":"5 Alcock Rd",
    "sg:city":"Elimbah",
    "sg:classifiers":[
        {
            "category":"Manufacturing",
            "subcategory":"Buildings",
            "type":"Manufacturing & Wholesale Goods"
        }
    ],
    "sg:phone":"+61 2 9546 7044",
    "sg:postcode":"4516",
    "sg:province":"QLD",
    "sg:tags":[
        "house",
        "gazebo",
        "shade"
    ],
    "wof:name":"Leisure Time Greenhouses",
    "wof:placetype":"venue"
},
  "geometry": {"coordinates":[152.922653,-27.024826],"type":"Point"}
}