{
  "type": "Feature",
  "properties": {
    "iso:country":"AU",
    "sg:address":"PO Box 598",
    "sg:city":"Albany Creek",
    "sg:classifiers":[
        {
            "category":"Home & Garden",
            "subcategory":"Building Materials",
            "type":"Retail Goods"
        }
    ],
    "sg:phone":"+61 412 032 325",
    "sg:postcode":"4035",
    "sg:province":"QLD",
    "sg:tags":[
        "lawn",
        "cutting",
        "maintenance"
    ],
    "wof:name":"Senko Vegitation Services Australia",
    "wof:placetype":"venue"
},
  "geometry": {"coordinates":[152.96537799999999,-27.34589],"type":"Point"}
}