{
  "type": "Feature",
  "properties": {
    "addr:full":"64 Nemira St Carseldine QLD 4034",
    "addr:housenumber":"64",
    "addr:postcode":"4034",
    "addr:street":"Nemira St",
    "iso:country":"AU",
    "sg:address":"64 Nemira St",
    "sg:city":"Carseldine",
    "sg:classifiers":[
        {
            "category":"Education",
            "subcategory":"Special Training",
            "type":"Public Place"
        }
    ],
    "sg:phone":"+61 7 3863 1053",
    "sg:postcode":"4034",
    "sg:province":"QLD",
    "sg:tags":[
        "tuition-educational"
    ],
    "wof:name":"KeyTutors",
    "wof:placetype":"venue"
},
  "geometry": {"coordinates":[153.011154,-27.358414],"type":"Point"}
}