{
  "type": "Feature",
  "properties": {
    "iso:country":"AU",
    "sg:address":"39 Dover Drv",
    "sg:city":"Burleigh Heads",
    "sg:classifiers":[
        {
            "category":"Home & Garden",
            "subcategory":"Building Materials",
            "type":"Retail Goods"
        }
    ],
    "sg:phone":"+61 7 5535 2266",
    "sg:postcode":"4220",
    "sg:province":"QLD",
    "sg:tags":[
        "laminate",
        "laminated",
        "panel"
    ],
    "wof:name":"Burleigh Heads Postforming",
    "wof:placetype":"venue"
},
  "geometry": {"coordinates":[153.42665100100001,-28.1046791077],"type":"Point"}
}