{
  "type": "Feature",
  "properties": {
    "addr:full":"20 Nixon St Rosebud VIC 3939",
    "addr:housenumber":"20",
    "addr:postcode":"3939",
    "addr:street":"Nixon St",
    "iso:country":"AU",
    "sg:address":"20 Nixon St",
    "sg:city":"Rosebud",
    "sg:classifiers":[
        {
            "category":"Home & Garden",
            "subcategory":"Carpets & Floor Coverings",
            "type":"Retail Goods"
        }
    ],
    "sg:phone":"+61 404 495 024",
    "sg:postcode":"3939",
    "sg:province":"VIC",
    "sg:tags":[
        "tile",
        "wall"
    ],
    "wof:name":"Precision Tiling",
    "wof:placetype":"venue"
},
  "geometry": {"coordinates":[144.91603088400001,-38.3690071106],"type":"Point"}
}