{
  "type": "Feature",
  "properties": {
    "addr:full":"174 Morayfield Rd Morayfield QLD 4506",
    "addr:housenumber":"174",
    "addr:postcode":"4506",
    "addr:street":"Morayfield Rd",
    "iso:country":"AU",
    "sg:address":"174 Morayfield Rd",
    "sg:city":"Morayfield",
    "sg:classifiers":[
        {
            "category":"Real Estate",
            "subcategory":"Real Estate Agent",
            "type":"Services"
        }
    ],
    "sg:phone":"+61 7 5495 7777",
    "sg:postcode":"4506",
    "sg:province":"QLD",
    "wof:name":"Marsellos Pike Real Estate",
    "wof:placetype":"venue"
},
  "geometry": {"coordinates":[152.950775147,-27.111366272],"type":"Point"}
}