{
  "type": "Feature",
  "properties": {
    "addr:full":"Manningham Medical Centre 200 High St Doncaster VIC 3108",
    "addr:housenumber":"200",
    "addr:postcode":"3108",
    "addr:street":"High St",
    "iso:country":"AU",
    "sg:address":"Manningham Medical Centre 200 High St",
    "sg:city":"Doncaster",
    "sg:classifiers":[
        {
            "category":"Health Services",
            "subcategory":"Doctor",
            "type":"Services"
        }
    ],
    "sg:phone":"+61 3 8850 0456",
    "sg:postcode":"3108",
    "sg:province":"VIC",
    "sg:tags":[
        "medical",
        "practitioner"
    ],
    "wof:name":"Ashton Peter Winter",
    "wof:placetype":"venue"
},
  "geometry": {"coordinates":[145.1224823,-37.7792434692],"type":"Point"}
}