{
  "type": "Feature",
  "properties": {
    "addr:full":"12 Commercial Rd Mentone VIC 3194",
    "addr:housenumber":"12",
    "addr:postcode":"3194",
    "addr:street":"Commercial Rd",
    "iso:country":"AU",
    "sg:address":"12 Commercial Rd",
    "sg:city":"Mentone",
    "sg:classifiers":[
        {
            "category":"Professional",
            "subcategory":"Management & Consulting",
            "type":"Services"
        }
    ],
    "sg:phone":"+61 3 9584 8900",
    "sg:postcode":"3194",
    "sg:province":"VIC",
    "sg:tags":[
        "consultant",
        "migration"
    ],
    "wof:name":"ABK Group Pty Ltd",
    "wof:placetype":"venue"
},
  "geometry": {"coordinates":[145.066040039,-37.985458374],"type":"Point"}
}