{
  "type": "Feature",
  "properties": {
    "addr:full":"30A Lawler St Subiaco WA 6008",
    "addr:housenumber":"30a",
    "addr:postcode":"6008",
    "addr:street":"Lawler St",
    "iso:country":"AU",
    "sg:address":"30A Lawler St",
    "sg:city":"Subiaco",
    "sg:classifiers":[
        {
            "category":"Government",
            "subcategory":"Court House",
            "type":"Public Place"
        }
    ],
    "sg:phone":"+61 8 9381 8442",
    "sg:postcode":"6008",
    "sg:province":"WA",
    "sg:tags":[
        "personal",
        "marriage",
        "family",
        "counselling"
    ],
    "wof:name":"Judy Morris",
    "wof:placetype":"venue"
},
  "geometry": {"coordinates":[115.818557739,-31.9513092041],"type":"Point"}
}