{
  "type": "Feature",
  "properties": {
    "addr:full":"4 Grange Drv Cooloongup WA 6168",
    "addr:housenumber":"4",
    "addr:postcode":"6168",
    "addr:street":"Grange Drv",
    "iso:country":"AU",
    "sg:address":"4 Grange Drv",
    "sg:city":"Cooloongup",
    "sg:classifiers":[
        {
            "category":"Professional",
            "type":"Services"
        }
    ],
    "sg:phone":"+61 8 9592 1372",
    "sg:postcode":"6168",
    "sg:province":"WA",
    "sg:tags":[
        "transport"
    ],
    "wof:name":"Patmic Pilot",
    "wof:placetype":"venue"
},
  "geometry": {"coordinates":[115.76277899999999,-32.294704],"type":"Point"}
}