{
  "type": "Feature",
  "properties": {
    "iso:country":"AU",
    "sg:address":"15 Gallop St",
    "sg:city":"Colac",
    "sg:classifiers":[
        {
            "category":"Utilities",
            "subcategory":"Water",
            "type":"Services"
        }
    ],
    "sg:phone":"+61 3 5231 5366",
    "sg:postcode":"3250",
    "sg:province":"VIC",
    "sg:tags":[
        "hot",
        "system"
    ],
    "wof:name":"Borwicks Trading",
    "wof:placetype":"venue"
},
  "geometry": {"coordinates":[143.60936000000001,-38.334721],"type":"Point"}
}