{
  "type": "Feature",
  "properties": {
    "addr:full":"Kiosk 316 Westfield Shopngtwn 1 Anderson Chatswood NSW 2067",
    "addr:housenumber":"316;1",
    "addr:postcode":"2067",
    "addr:street":"Westfield Shopngtwn",
    "iso:country":"AU",
    "sg:address":"Kiosk 316 Westfield Shopngtwn 1 Anderson",
    "sg:city":"Chatswood",
    "sg:classifiers":[
        {
            "category":"Banks & Credit Unions",
            "subcategory":"Bank",
            "type":"Services"
        }
    ],
    "sg:phone":"+61 2 9411 3430",
    "sg:postcode":"2067",
    "sg:province":"NSW",
    "wof:name":"Colonial",
    "wof:placetype":"venue"
},
  "geometry": {"coordinates":[151.183227539,-33.7960777283],"type":"Point"}
}