{
  "type": "Feature",
  "properties": {
    "iso:country":"AU",
    "sg:address":"Fact 3/ 11 Douglas St",
    "sg:city":"Sunshine North",
    "sg:classifiers":[
        {
            "category":"Wholesale",
            "subcategory":"Apparel",
            "type":"Manufacturing & Wholesale Goods"
        }
    ],
    "sg:phone":"+61 3 9364 8595",
    "sg:postcode":"3020",
    "sg:province":"VIC",
    "sg:tags":[
        "wholesaler",
        "mfrs",
        "dress"
    ],
    "wof:name":"F W of Australia",
    "wof:placetype":"venue"
},
  "geometry": {"coordinates":[144.844437,-37.764793],"type":"Point"}
}