{
  "type": "Feature",
  "properties": {
    "addr:full":"PO Box 243 Maclean NSW 2463",
    "addr:postcode":"2463",
    "iso:country":"AU",
    "sg:address":"PO Box 243",
    "sg:city":"Maclean",
    "sg:classifiers":[
        {
            "category":"Taxi",
            "type":"Transportation"
        }
    ],
    "sg:phone":"+61 2 6645 2122",
    "sg:postcode":"2463",
    "sg:province":"NSW",
    "sg:tags":[
        "cab"
    ],
    "wof:name":"Maclean Taxis",
    "wof:placetype":"venue"
},
  "geometry": {"coordinates":[153.21983337399999,-29.4524097443],"type":"Point"}
}