{
  "type": "Feature",
  "properties": {
    "iso:country":"AU",
    "sg:address":"1620 Ipswich Rd",
    "sg:city":"Rocklea",
    "sg:classifiers":[
        {
            "category":"Food & Beverages",
            "subcategory":"Bakery",
            "type":"Retail Goods"
        }
    ],
    "sg:phone":"+61 7 3274 6158",
    "sg:postcode":"4106",
    "sg:province":"QLD",
    "sg:tags":[
        "baker"
    ],
    "wof:name":"Austral Croissants Pty Ltd",
    "wof:placetype":"venue"
},
  "geometry": {"coordinates":[153.00978088400001,-27.5520248413],"type":"Point"}
}