{
  "type": "Feature",
  "properties": {
    "addr:full":"Factory 2/ 10 Nicole Cl Bayswater North VIC 3153",
    "addr:housenumber":"/ 10",
    "addr:postcode":"3153",
    "addr:street":"Nicole Cl",
    "iso:country":"AU",
    "sg:address":"Factory 2/ 10 Nicole Cl",
    "sg:city":"Bayswater North",
    "sg:classifiers":[
        {
            "category":"Landmark",
            "subcategory":"Fountain",
            "type":"Public Place"
        }
    ],
    "sg:phone":"+61 3 9720 6015",
    "sg:postcode":"3153",
    "sg:province":"VIC",
    "sg:tags":[
        "wholesaler",
        "spring",
        "mfrs"
    ],
    "wof:name":"Multiclip Pty Ltd",
    "wof:placetype":"venue"
},
  "geometry": {"coordinates":[145.29005432100001,-37.8253211975],"type":"Point"}
}