{
  "type": "Feature",
  "properties": {
    "iso:country":"AU",
    "sg:address":"215 Charters Towers Rd",
    "sg:city":"Hermit Park",
    "sg:classifiers":[
        {
            "category":"Education",
            "subcategory":"Vocational School",
            "type":"Public Place"
        }
    ],
    "sg:phone":"+61 7 4775 2124",
    "sg:postcode":"4812",
    "sg:province":"QLD",
    "sg:tags":[
        "beauty"
    ],
    "wof:name":"Townsville Nail & Beauty Training School",
    "wof:placetype":"venue"
},
  "geometry": {"coordinates":[146.796997,-19.285383],"type":"Point"}
}