{
  "type": "Feature",
  "properties": {
    "iso:country":"AU",
    "sg:address":"178 Main St",
    "sg:city":"Croydon",
    "sg:classifiers":[
        {
            "category":"Personal",
            "subcategory":"Tanning Parlor",
            "type":"Services"
        }
    ],
    "sg:phone":"+61 3 9725 0725",
    "sg:postcode":"3136",
    "sg:province":"VIC",
    "sg:tags":[
        "solarium"
    ],
    "wof:name":"Body Bronze",
    "wof:placetype":"venue"
},
  "geometry": {"coordinates":[145.28083801299999,-37.7979812622],"type":"Point"}
}