{
  "type": "Feature",
  "properties": {
    "iso:country":"AU",
    "sg:address":"21/1 Reliance Drv Tuggerah Business Park",
    "sg:city":"Tuggerah",
    "sg:classifiers":[
        {
            "category":"Real Estate",
            "subcategory":"Real Estate Agent",
            "type":"Services"
        }
    ],
    "sg:phone":"+61 2 4353 7700",
    "sg:postcode":"2259",
    "sg:province":"NSW",
    "wof:name":"LJ Hooker Commercial",
    "wof:placetype":"venue"
},
  "geometry": {"coordinates":[151.42123413100001,-33.3134422302],"type":"Point"}
}