{
  "type": "Feature",
  "properties": {
    "addr:full":"Victoria St Ballarat VIC 3350",
    "addr:postcode":"3350",
    "addr:street":"Victoria St",
    "iso:country":"AU",
    "sg:address":"Victoria St",
    "sg:city":"Ballarat",
    "sg:classifiers":[
        {
            "category":"Education",
            "subcategory":"School",
            "type":"Public Place"
        }
    ],
    "sg:phone":"+61 3 5331 1816",
    "sg:postcode":"3350",
    "sg:province":"VIC",
    "sg:tags":[
        "co-educational"
    ],
    "wof:name":"St Alipius School",
    "wof:placetype":"venue"
},
  "geometry": {"coordinates":[143.86483799999999,-37.562798],"type":"Point"}
}