{
  "type": "Feature",
  "properties": {
    "iso:country":"AU",
    "sg:address":"37 Culwell Ave",
    "sg:city":"Mitcham",
    "sg:classifiers":[
        {
            "category":"Professional",
            "subcategory":"Detective & Security Services",
            "type":"Services"
        }
    ],
    "sg:phone":"+61 3 9874 5693",
    "sg:postcode":"3132",
    "sg:province":"VIC",
    "sg:tags":[
        "consultant",
        "system"
    ],
    "wof:name":"Proton Security",
    "wof:placetype":"venue"
},
  "geometry": {"coordinates":[145.213058472,-37.8228874207],"type":"Point"}
}