{
  "type": "Feature",
  "properties": {
    "addr:full":"Sandler Ave North Rocks NSW 2151",
    "addr:postcode":"2151",
    "addr:street":"Sandler Ave",
    "iso:country":"AU",
    "sg:address":"Sandler Ave",
    "sg:city":"North Rocks",
    "sg:classifiers":[
        {
            "category":"Health Services",
            "subcategory":"Health Practitioner",
            "type":"Services"
        }
    ],
    "sg:phone":"+61 2 9873 3837",
    "sg:postcode":"2151",
    "sg:province":"NSW",
    "sg:tags":[
        "hypnotherapy"
    ],
    "wof:name":"Megan Davenport",
    "wof:placetype":"venue"
},
  "geometry": {"coordinates":[151.026901245,-33.7756271362],"type":"Point"}
}