{
  "type": "Feature",
  "properties": {
    "addr:full":"14 Darling St Tamworth NSW 2340",
    "addr:housenumber":"14",
    "addr:postcode":"2340",
    "addr:street":"Darling St",
    "iso:country":"AU",
    "sg:address":"14 Darling St",
    "sg:city":"Tamworth",
    "sg:classifiers":[
        {
            "category":"Health Services",
            "subcategory":"Chiropractor",
            "type":"Services"
        }
    ],
    "sg:phone":"+61 2 6766 5690",
    "sg:postcode":"2340",
    "sg:province":"NSW",
    "wof:name":"J T Chiropractic Clinic",
    "wof:placetype":"venue"
},
  "geometry": {"coordinates":[150.92750549300001,-31.0858840942],"type":"Point"}
}