{
  "type": "Feature",
  "properties": {
    "iso:country":"AU",
    "sg:address":"24 Redden St",
    "sg:city":"Portsmith",
    "sg:classifiers":[
        {
            "category":"Home & Garden",
            "subcategory":"Furniture",
            "type":"Retail Goods"
        }
    ],
    "sg:phone":"+61 7 4035 8900",
    "sg:postcode":"4870",
    "sg:province":"QLD",
    "sg:tags":[
        "business"
    ],
    "wof:name":"Abcon Office Furniture",
    "wof:placetype":"venue"
},
  "geometry": {"coordinates":[145.76971435600001,-16.9431114197],"type":"Point"}
}