{
  "type": "Feature",
  "properties": {
    "iso:country":"AU",
    "sg:address":"11 Edgecliff Mews",
    "sg:city":"Edgecliff",
    "sg:classifiers":[
        {
            "category":"Health Services",
            "subcategory":"Doctor",
            "type":"Services"
        }
    ],
    "sg:phone":"+61 2 9327 4817",
    "sg:postcode":"2027",
    "sg:province":"NSW",
    "sg:tags":[
        "medical",
        "practitioner"
    ],
    "wof:name":"Woodforth IJ",
    "wof:placetype":"venue"
},
  "geometry": {"coordinates":[151.24180602999999,-33.8816566467],"type":"Point"}
}