{
  "type": "Feature",
  "properties": {
    "addr:full":"16 Freeman St Kingston TAS 7050",
    "addr:housenumber":"16",
    "addr:postcode":"7050",
    "addr:street":"Freeman St",
    "iso:country":"AU",
    "sg:address":"16 Freeman St",
    "sg:city":"Kingston",
    "sg:classifiers":[
        {
            "category":"Professional",
            "subcategory":"Employment Agencies",
            "type":"Services"
        }
    ],
    "sg:phone":"+61 3 6229 1140",
    "sg:postcode":"7050",
    "sg:province":"TAS",
    "wof:name":"STEPS Employment & Training Solutions",
    "wof:placetype":"venue"
},
  "geometry": {"coordinates":[147.323914,-42.981434],"type":"Point"}
}