{
  "type": "Feature",
  "properties": {
    "addr:full":"Cnr Beach & Erindale Rds Warwick WA 6024",
    "addr:postcode":"6024",
    "addr:street":"Cnr",
    "iso:country":"AU",
    "sg:address":"Cnr Beach & Erindale Rds",
    "sg:city":"Warwick",
    "sg:classifiers":[
        {
            "category":"Wholesale",
            "subcategory":"Medical Equipment & Supplies",
            "type":"Manufacturing & Wholesale Goods"
        }
    ],
    "sg:phone":"+61 8 9246 2244",
    "sg:postcode":"6024",
    "sg:province":"WA",
    "sg:tags":[
        "aids",
        "hearing"
    ],
    "wof:name":"Laubman & Pank Hearing Centres",
    "wof:placetype":"venue"
},
  "geometry": {"coordinates":[115.813056946,-31.8445892334],"type":"Point"}
}