{
  "type": "Feature",
  "properties": {
    "addr:full":"66 Creaney Drv Kingsley WA 6026",
    "addr:housenumber":"66",
    "addr:postcode":"6026",
    "addr:street":"Creaney Drv",
    "iso:country":"AU",
    "sg:address":"66 Creaney Drv",
    "sg:city":"Kingsley",
    "sg:classifiers":[
        {
            "category":"Retail",
            "subcategory":"Veterinary Services",
            "type":"Services"
        }
    ],
    "sg:phone":"+61 8 9409 6855",
    "sg:postcode":"6026",
    "sg:province":"WA",
    "sg:tags":[
        "surgeon"
    ],
    "wof:name":"Kingsley Veterinary Hospital",
    "wof:placetype":"venue"
},
  "geometry": {"coordinates":[115.78981781,-31.8089141846],"type":"Point"}
}