{
  "type": "Feature",
  "properties": {
    "addr:full":"9/ 30 Morton St Wollstonecraft NSW 2065",
    "addr:housenumber":"/ 30",
    "addr:postcode":"2065",
    "addr:street":"Morton St",
    "iso:country":"AU",
    "sg:address":"9/ 30 Morton St",
    "sg:city":"Wollstonecraft",
    "sg:classifiers":[
        {
            "category":"Building & Trades",
            "subcategory":"Construction",
            "type":"Services"
        }
    ],
    "sg:phone":"+61 418 243 143",
    "sg:postcode":"2065",
    "sg:province":"NSW",
    "sg:tags":[
        "contractor"
    ],
    "wof:name":"McCarthy D J",
    "wof:placetype":"venue"
},
  "geometry": {"coordinates":[151.19973754899999,-33.8325538635],"type":"Point"}
}