{
  "type": "Feature",
  "properties": {
    "addr:full":"16 Euroka Drv Taree NSW 2430",
    "addr:housenumber":"16",
    "addr:postcode":"2430",
    "addr:street":"Euroka Drv",
    "iso:country":"AU",
    "sg:address":"16 Euroka Drv",
    "sg:city":"Taree",
    "sg:classifiers":[
        {
            "category":"Building & Trades",
            "subcategory":"Construction",
            "type":"Services"
        }
    ],
    "sg:phone":"+61 418 471 356",
    "sg:postcode":"2430",
    "sg:province":"NSW",
    "sg:tags":[
        "contractor"
    ],
    "wof:name":"Hopkins John",
    "wof:placetype":"venue"
},
  "geometry": {"coordinates":[152.438873,-31.877977],"type":"Point"}
}