{
  "type": "Feature",
  "properties": {
    "iso:country":"AU",
    "sg:address":"Unit 11 13- 15 Burrows Rd South",
    "sg:city":"St Peters",
    "sg:classifiers":[
        {
            "category":"Shopping",
            "subcategory":"Optical Goods",
            "type":"Retail Goods"
        }
    ],
    "sg:phone":"+61 2 9516 5017",
    "sg:postcode":"2044",
    "sg:province":"NSW",
    "sg:tags":[
        "supply"
    ],
    "wof:name":"Spectacular Specs-For Your Eyes Only",
    "wof:placetype":"venue"
},
  "geometry": {"coordinates":[151.176025391,-33.921787262],"type":"Point"}
}