{
  "type": "Feature",
  "properties": {
    "addr:full":"Cnr Kedron Brook & Days Rds Grange QLD 4051",
    "addr:postcode":"4051",
    "addr:street":"Cnr Kedron",
    "iso:country":"AU",
    "sg:address":"Cnr Kedron Brook & Days Rds",
    "sg:city":"Grange",
    "sg:classifiers":[
        {
            "category":"Health Services",
            "subcategory":"Optometrist",
            "type":"Services"
        }
    ],
    "sg:phone":"+61 7 3356 4703",
    "sg:postcode":"4051",
    "sg:province":"QLD",
    "wof:name":"Grange Optical Premium Outlet",
    "wof:placetype":"venue"
},
  "geometry": {"coordinates":[153.01895141599999,-27.4270706177],"type":"Point"}
}