{
  "type": "Feature",
  "properties": {
    "iso:country":"AU",
    "sg:address":"2/ 21 View St",
    "sg:city":"Camden",
    "sg:classifiers":[
        {
            "category":"Donuts",
            "subcategory":"None",
            "type":"Food & Drink"
        }
    ],
    "sg:phone":"+61 2 4655 4609",
    "sg:postcode":"2570",
    "sg:province":"NSW",
    "sg:tags":[
        "die",
        "engraver",
        "sinker"
    ],
    "wof:name":"Maranatha Engraving",
    "wof:placetype":"venue"
},
  "geometry": {"coordinates":[150.69859314000001,-34.0550041199],"type":"Point"}
}