{
  "type": "Feature",
  "properties": {
    "addr:full":"Browns Rd Devon Meadows VIC 3977",
    "addr:postcode":"3977",
    "addr:street":"Browns Rd",
    "iso:country":"AU",
    "sg:address":"Browns Rd",
    "sg:city":"Devon Meadows",
    "sg:classifiers":[
        {
            "category":"Farming",
            "subcategory":"Livestock Farm",
            "type":"Manufacturing & Wholesale Goods"
        }
    ],
    "sg:phone":"+61 3 5998 2654",
    "sg:postcode":"3977",
    "sg:province":"VIC",
    "sg:tags":[
        "agistment"
    ],
    "wof:name":"Mulyan Pty Ltd",
    "wof:placetype":"venue"
},
  "geometry": {"coordinates":[145.31727600100001,-38.1566314697],"type":"Point"}
}