{
  "type": "Feature",
  "properties": {
    "addr:full":"1A Quirk Rd Manly Vale NSW 2093",
    "addr:housenumber":"1a",
    "addr:postcode":"2093",
    "addr:street":"Quirk Rd",
    "iso:country":"AU",
    "sg:address":"1A Quirk Rd",
    "sg:city":"Manly Vale",
    "sg:classifiers":[
        {
            "category":"Wholesale",
            "subcategory":"Metals & Minerals",
            "type":"Manufacturing & Wholesale Goods"
        }
    ],
    "sg:phone":"+61 2 9948 0933",
    "sg:postcode":"2093",
    "sg:province":"NSW",
    "sg:tags":[
        "steel",
        "stainless",
        "product",
        "equipment"
    ],
    "wof:name":"Maph Engineering Pty Ltd",
    "wof:placetype":"venue"
},
  "geometry": {"coordinates":[151.269973755,-33.7868499756],"type":"Point"}
}