{
  "type": "Feature",
  "properties": {
    "addr:full":"Suite 8/ 67 Howe St Osborne Park WA 6017",
    "addr:housenumber":"67",
    "addr:postcode":"6017",
    "addr:street":"Howe St",
    "iso:country":"AU",
    "sg:address":"Suite 8/ 67 Howe St",
    "sg:city":"Osborne Park",
    "sg:classifiers":[
        {
            "category":"Professional",
            "subcategory":"Employment Agencies",
            "type":"Services"
        }
    ],
    "sg:phone":"+61 8 9244 8988",
    "sg:postcode":"6017",
    "sg:province":"WA",
    "sg:tags":[
        "provider",
        "internet"
    ],
    "wof:name":"CityNEX",
    "wof:placetype":"venue"
},
  "geometry": {"coordinates":[115.813796997,-31.9071598053],"type":"Point"}
}