{
  "type": "Feature",
  "properties": {
    "addr:full":"264 Halifax St Adelaide SA 5000",
    "addr:housenumber":"264",
    "addr:postcode":"5000",
    "addr:street":"Halifax St",
    "iso:country":"AU",
    "sg:address":"264 Halifax St",
    "sg:city":"Adelaide",
    "sg:classifiers":[
        {
            "category":"Professional",
            "subcategory":"Art Services",
            "type":"Services"
        }
    ],
    "sg:phone":"+61 8 8232 6550",
    "sg:postcode":"5000",
    "sg:province":"SA",
    "sg:tags":[
        "graphic",
        "designer"
    ],
    "wof:name":"Pasquale Portaro",
    "wof:placetype":"venue"
},
  "geometry": {"coordinates":[138.61143493599999,-34.932220459],"type":"Point"}
}