{
  "type": "Feature",
  "properties": {
    "addr:full":"PO Box 1668 Bairnsdale VIC 3875",
    "addr:postcode":"3875",
    "iso:country":"AU",
    "sg:address":"PO Box 1668",
    "sg:city":"Bairnsdale",
    "sg:classifiers":[
        {
            "category":"Industrial Area",
            "type":"Public Place"
        }
    ],
    "sg:phone":"+61 428 531 249",
    "sg:postcode":"3875",
    "sg:province":"VIC",
    "sg:tags":[
        "rural",
        "shed"
    ],
    "wof:name":"D & S Fabrications",
    "wof:placetype":"venue"
},
  "geometry": {"coordinates":[147.61129760700001,-37.8314208984],"type":"Point"}
}