{
  "type": "Feature",
  "properties": {
    "addr:full":"146 Somerton Rd Somerton VIC 3062",
    "addr:housenumber":"146",
    "addr:postcode":"3062",
    "addr:street":"Somerton Rd",
    "iso:country":"AU",
    "sg:address":"146 Somerton Rd",
    "sg:city":"Somerton",
    "sg:classifiers":[
        {
            "category":"Home & Garden",
            "subcategory":"Garden Supply",
            "type":"Retail Goods"
        }
    ],
    "sg:phone":"+61 3 9305 3557",
    "sg:postcode":"3062",
    "sg:province":"VIC",
    "sg:tags":[
        "equipment"
    ],
    "wof:name":"Somerton Road Garden Supplies",
    "wof:placetype":"venue"
},
  "geometry": {"coordinates":[144.93714904800001,-37.6415290833],"type":"Point"}
}