{
  "type": "Feature",
  "properties": {
    "addr:full":"91 Glennie St Wyoming NSW 2250",
    "addr:housenumber":"91",
    "addr:postcode":"2250",
    "addr:street":"Glennie St",
    "iso:country":"AU",
    "sg:address":"91 Glennie St",
    "sg:city":"Wyoming",
    "sg:classifiers":[
        {
            "category":"Fast Food",
            "type":"Food & Drink"
        }
    ],
    "sg:phone":"+61 2 4325 2983",
    "sg:postcode":"2250",
    "sg:province":"NSW",
    "sg:tags":[
        "away",
        "take"
    ],
    "wof:name":"Robyn's Corner Store",
    "wof:placetype":"venue"
},
  "geometry": {"coordinates":[151.34815979000001,-33.4129371643],"type":"Point"}
}