{
  "type": "Feature",
  "properties": {
    "iso:country":"AU",
    "sg:address":"687- 691 Chambers Flat Rd",
    "sg:city":"Chambers Flat",
    "sg:classifiers":[
        {
            "category":"Building & Trades",
            "subcategory":"Construction",
            "type":"Services"
        }
    ],
    "sg:phone":"+61 407 145 341",
    "sg:postcode":"4133",
    "sg:province":"QLD",
    "sg:tags":[
        "contractor"
    ],
    "wof:name":"R W Gills House Builder",
    "wof:placetype":"venue"
},
  "geometry": {"coordinates":[153.08889770499999,-27.7449092865],"type":"Point"}
}