{
  "type": "Feature",
  "properties": {
    "iso:country":"AU",
    "sg:address":"Notting Rd",
    "sg:city":"Kondinin",
    "sg:classifiers":[
        {
            "category":"Farming",
            "subcategory":"Farm",
            "type":"Manufacturing & Wholesale Goods"
        }
    ],
    "sg:phone":"+61 8 9889 1021",
    "sg:postcode":"6367",
    "sg:province":"WA",
    "sg:tags":[
        "farmer"
    ],
    "wof:name":"Wilkins B W",
    "wof:placetype":"venue"
},
  "geometry": {"coordinates":[118.266357,-32.498798],"type":"Point"}
}