{
  "type": "Feature",
  "properties": {
    "addr:full":"12 Rayson St Murray Bridge SA 5253",
    "addr:housenumber":"12",
    "addr:postcode":"5253",
    "addr:street":"Rayson St",
    "iso:country":"AU",
    "sg:address":"12 Rayson St",
    "sg:city":"Murray Bridge",
    "sg:classifiers":[
        {
            "category":"Retail",
            "subcategory":"Auto Repair",
            "type":"Services"
        }
    ],
    "sg:phone":"+61 8 8531 2400",
    "sg:postcode":"5253",
    "sg:province":"SA",
    "sg:tags":[
        "beater",
        "painter",
        "panel"
    ],
    "wof:name":"Bridge Paint & Panel",
    "wof:placetype":"venue"
},
  "geometry": {"coordinates":[139.25424194300001,-35.1267242432],"type":"Point"}
}