{
  "type": "Feature",
  "properties": {
    "addr:full":"563 Glebe Rd Adamstown NSW 2289",
    "addr:housenumber":"563",
    "addr:postcode":"2289",
    "addr:street":"Glebe Rd",
    "iso:country":"AU",
    "sg:address":"563 Glebe Rd",
    "sg:city":"Adamstown",
    "sg:classifiers":[
        {
            "category":"Health Services",
            "subcategory":"Health Practitioner",
            "type":"Services"
        }
    ],
    "sg:phone":"+61 2 4957 3747",
    "sg:postcode":"2289",
    "sg:province":"NSW",
    "sg:tags":[
        "physiotherapist"
    ],
    "wof:name":"Catchpole Chris",
    "wof:placetype":"venue"
},
  "geometry": {"coordinates":[151.72807312,-32.9346923828],"type":"Point"}
}