{
  "type": "Feature",
  "properties": {
    "iso:country":"AU",
    "sg:address":"22 Luisa Ave",
    "sg:city":"Dandenong",
    "sg:classifiers":[
        {
            "category":"Professional",
            "subcategory":"Engineering",
            "type":"Services"
        }
    ],
    "sg:phone":"+61 3 9768 2601",
    "sg:postcode":"3175",
    "sg:province":"VIC",
    "sg:tags":[
        "building",
        "prefabricated",
        "transportable",
        "industrial",
        "commercial"
    ],
    "wof:name":"Mobile Systems Australia Pty Ltd",
    "wof:placetype":"venue"
},
  "geometry": {"coordinates":[145.203033447,-38.0363235474],"type":"Point"}
}