{
  "type": "Feature",
  "properties": {
    "addr:full":"11 Roxburgh St Lorn NSW 2320",
    "addr:housenumber":"11",
    "addr:postcode":"2320",
    "addr:street":"Roxburgh St",
    "iso:country":"AU",
    "sg:address":"11 Roxburgh St",
    "sg:city":"Lorn",
    "sg:classifiers":[
        {
            "category":"Education",
            "subcategory":"Music School",
            "type":"Public Place"
        }
    ],
    "sg:phone":"+61 2 4934 2541",
    "sg:postcode":"2320",
    "sg:province":"NSW",
    "sg:tags":[
        "choir",
        "bands",
        "orchestra"
    ],
    "wof:name":"Fulcher B & R",
    "wof:placetype":"venue"
},
  "geometry": {"coordinates":[151.55738830600001,-32.7273902893],"type":"Point"}
}