{
  "type": "Feature",
  "properties": {
    "addr:full":"430 Francis St Brooklyn VIC 3012",
    "addr:housenumber":"430",
    "addr:postcode":"3012",
    "addr:street":"Francis St",
    "iso:country":"AU",
    "sg:address":"430 Francis St",
    "sg:city":"Brooklyn",
    "sg:classifiers":[
        {
            "category":"Building & Trades",
            "subcategory":"Construction",
            "type":"Services"
        }
    ],
    "sg:phone":"+61 3 9314 7769",
    "sg:postcode":"3012",
    "sg:province":"VIC",
    "sg:tags":[
        "contractor"
    ],
    "wof:name":"Modscape-Modular Sustainable Housing",
    "wof:placetype":"venue"
},
  "geometry": {"coordinates":[144.854125977,-37.8169288635],"type":"Point"}
}