{
  "type": "Feature",
  "properties": {
    "addr:full":"61 George St Bathurst NSW 2795",
    "addr:housenumber":"61",
    "addr:postcode":"2795",
    "addr:street":"George St",
    "iso:country":"AU",
    "sg:address":"61 George St",
    "sg:city":"Bathurst",
    "sg:classifiers":[
        {
            "category":"Home & Garden",
            "subcategory":"Carpets & Floor Coverings",
            "type":"Retail Goods"
        }
    ],
    "sg:phone":"+61 2 6331 4866",
    "sg:postcode":"2795",
    "sg:province":"NSW",
    "sg:tags":[
        "wood"
    ],
    "wof:name":"Carpet Choice",
    "wof:placetype":"venue"
},
  "geometry": {"coordinates":[149.57850647000001,-33.4166526794],"type":"Point"}
}