{
  "type": "Feature",
  "properties": {
    "addr:full":"PO Box 692 Ocean Grove VIC 3226",
    "addr:postcode":"3226",
    "iso:country":"AU",
    "sg:address":"PO Box 692",
    "sg:city":"Ocean Grove",
    "sg:classifiers":[
        {
            "category":"Education",
            "subcategory":"Special Training",
            "type":"Public Place"
        }
    ],
    "sg:phone":"+61 3 5255 1611",
    "sg:postcode":"3226",
    "sg:province":"VIC",
    "sg:tags":[
        "development"
    ],
    "wof:name":"Telephone Power Pty Ltd",
    "wof:placetype":"venue"
},
  "geometry": {"coordinates":[144.53810100000001,-38.265339],"type":"Point"}
}