{
  "type": "Feature",
  "properties": {
    "addr:full":"1 Roper Pl East Killara NSW 2071",
    "addr:housenumber":"1",
    "addr:postcode":"2071",
    "addr:street":"Roper Pl",
    "iso:country":"AU",
    "sg:address":"1 Roper Pl",
    "sg:city":"East Killara",
    "sg:classifiers":[
        {
            "category":"Communications",
            "subcategory":"News Services",
            "type":"Services"
        }
    ],
    "sg:phone":"+61 411 870 777",
    "sg:postcode":"2071",
    "sg:province":"NSW",
    "sg:tags":[
        "information",
        "tourist",
        "attractions"
    ],
    "wof:name":"Sydney Specialists Tourism Marketing",
    "wof:placetype":"venue"
},
  "geometry": {"coordinates":[151.17982482900001,-33.7628707886],"type":"Point"}
}