{
  "type": "Feature",
  "properties": {
    "addr:full":"3 Clay La Kuranda QLD 4872",
    "addr:housenumber":"3",
    "addr:postcode":"4872",
    "addr:street":"Clay La Kuranda",
    "iso:country":"AU",
    "sg:address":"3 Clay La",
    "sg:city":"Kuranda",
    "sg:classifiers":[
        {
            "category":"Utilities",
            "subcategory":"Electric",
            "type":"Services"
        }
    ],
    "sg:phone":"+61 7 4093 7105",
    "sg:postcode":"4872",
    "sg:province":"QLD",
    "sg:tags":[
        "electrical",
        "contractor"
    ],
    "wof:name":"Hughes T D",
    "wof:placetype":"venue"
},
  "geometry": {"coordinates":[145.627685547,-16.8129177094],"type":"Point"}
}