{
  "type": "Feature",
  "properties": {
    "iso:country":"AU",
    "sg:address":"27 Nariel St",
    "sg:city":"Albion",
    "sg:classifiers":[
        {
            "category":"Retail",
            "subcategory":"Auto Repair",
            "type":"Services"
        }
    ],
    "sg:phone":"+61 7 3262 9303",
    "sg:postcode":"4010",
    "sg:province":"QLD",
    "sg:tags":[
        "beater",
        "painter",
        "panel"
    ],
    "wof:name":"Albion Bodyworks",
    "wof:placetype":"venue"
},
  "geometry": {"coordinates":[153.043823242,-27.439081192],"type":"Point"}
}