{
  "type": "Feature",
  "properties": {
    "addr:full":"47 David St Yokine WA 6060",
    "addr:housenumber":"47",
    "addr:postcode":"6060",
    "addr:street":"David St",
    "iso:country":"AU",
    "sg:address":"47 David St",
    "sg:city":"Yokine",
    "sg:classifiers":[
        {
            "category":"Building & Trades",
            "subcategory":"Plumbing",
            "type":"Services"
        }
    ],
    "sg:phone":"+61 8 9349 5827",
    "sg:postcode":"6060",
    "sg:province":"WA",
    "sg:tags":[
        "plumber",
        "gasfitters"
    ],
    "wof:name":"Denny's Gas Fitting",
    "wof:placetype":"venue"
},
  "geometry": {"coordinates":[115.84555053699999,-31.8897647858],"type":"Point"}
}