{
  "type": "Feature",
  "properties": {
    "addr:full":"PO Box 194 Bairnsdale VIC 3875",
    "addr:postcode":"3875",
    "iso:country":"AU",
    "sg:address":"PO Box 194",
    "sg:city":"Bairnsdale",
    "sg:classifiers":[
        {
            "category":"Farming",
            "subcategory":"Farm & Veterinary Services",
            "type":"Manufacturing & Wholesale Goods"
        }
    ],
    "sg:phone":"+61 3 5156 8073",
    "sg:postcode":"3875",
    "sg:province":"VIC",
    "sg:tags":[
        "irrigation",
        "reticulation",
        "system"
    ],
    "wof:name":"Rho-tec Electronic Services",
    "wof:placetype":"venue"
},
  "geometry": {"coordinates":[147.61129760700001,-37.8314208984],"type":"Point"}
}