{
  "type": "Feature",
  "properties": {
    "iso:country":"AU",
    "sg:address":"Gympie Rd",
    "sg:city":"Chermside",
    "sg:classifiers":[
        {
            "category":"Food & Beverages",
            "subcategory":"Fruits & Vegetables",
            "type":"Retail Goods"
        }
    ],
    "sg:phone":"+61 7 3359 1157",
    "sg:postcode":"4032",
    "sg:province":"QLD",
    "sg:tags":[
        "greengrocer",
        "fruiterer"
    ],
    "wof:name":"Garden Of Eden Fruits",
    "wof:placetype":"venue"
},
  "geometry": {"coordinates":[153.031113,-27.386387],"type":"Point"}
}