{
  "type": "Feature",
  "properties": {
    "iso:country":"AU",
    "sg:address":"Production St",
    "sg:city":"Bundaberg",
    "sg:classifiers":[
        {
            "category":"Home & Garden",
            "subcategory":"Building Materials",
            "type":"Retail Goods"
        }
    ],
    "sg:phone":"+61 7 4152 5233",
    "sg:postcode":"4670",
    "sg:province":"QLD",
    "sg:tags":[
        "pre-mixed",
        "concrete"
    ],
    "wof:name":"Readymix",
    "wof:placetype":"venue"
},
  "geometry": {"coordinates":[152.329681397,-24.8893260956],"type":"Point"}
}