{
  "type": "Feature",
  "properties": {
    "iso:country":"AU",
    "sg:address":"85 Barwon Tce",
    "sg:city":"South Geelong",
    "sg:classifiers":[
        {
            "category":"Home & Garden",
            "subcategory":"Building Materials",
            "type":"Retail Goods"
        }
    ],
    "sg:phone":"+61 3 5222 3161",
    "sg:postcode":"3220",
    "sg:province":"VIC",
    "sg:tags":[
        "supply"
    ],
    "wof:name":"Barry Medew Building Supplies",
    "wof:placetype":"venue"
},
  "geometry": {"coordinates":[144.366364,-38.170025],"type":"Point"}
}