{
  "type": "Feature",
  "properties": {
    "addr:full":"1168 Glenhuntly Rd Glen Huntly VIC 3163",
    "addr:housenumber":"1168",
    "addr:postcode":"3163",
    "addr:street":"Glenhuntly Rd",
    "iso:country":"AU",
    "sg:address":"1168 Glenhuntly Rd",
    "sg:city":"Glen Huntly",
    "sg:classifiers":[
        {
            "category":"Personal",
            "subcategory":"Beauty Salon",
            "type":"Services"
        }
    ],
    "sg:phone":"+61 3 9571 6661",
    "sg:postcode":"3163",
    "sg:province":"VIC",
    "sg:tags":[
        "hairdresser"
    ],
    "wof:name":"Cliffs Eco Hair Centre",
    "wof:placetype":"venue"
},
  "geometry": {"coordinates":[145.042892456,-37.8896217346],"type":"Point"}
}