{
  "type": "Feature",
  "properties": {
    "addr:full":"405 Bridge Rd Para Hills SA 5096",
    "addr:housenumber":"405",
    "addr:postcode":"5096",
    "addr:street":"Bridge Rd",
    "iso:country":"AU",
    "sg:address":"405 Bridge Rd",
    "sg:city":"Para Hills",
    "sg:classifiers":[
        {
            "category":"Food & Beverages",
            "subcategory":"Liquor & Beverages",
            "type":"Retail Goods"
        }
    ],
    "sg:phone":"+61 8 8264 3067",
    "sg:postcode":"5096",
    "sg:province":"SA",
    "sg:tags":[
        "store"
    ],
    "wof:name":"Liquorland",
    "wof:placetype":"venue"
},
  "geometry": {"coordinates":[138.648880005,-34.8074874878],"type":"Point"}
}