{
  "type": "Feature",
  "properties": {
    "addr:full":"1 Parramatta Rd (Cnr Loftus St) Concord NSW 2137",
    "addr:housenumber":"1",
    "addr:postcode":"2137",
    "addr:street":"Parramatta Rd Cnr Loftus St",
    "iso:country":"AU",
    "sg:address":"1 Parramatta Rd (Cnr Loftus St)",
    "sg:city":"Concord",
    "sg:classifiers":[
        {
            "category":"Retail",
            "subcategory":"Auto Repair",
            "type":"Services"
        }
    ],
    "sg:phone":"+61 2 9745 3588",
    "sg:postcode":"2137",
    "sg:province":"NSW",
    "sg:tags":[
        "repairer",
        "motor",
        "engineer"
    ],
    "wof:name":"Midas",
    "wof:placetype":"venue"
},
  "geometry": {"coordinates":[151.107421875,-33.8689689636],"type":"Point"}
}