{
  "type": "Feature",
  "properties": {
    "addr:full":"655 Macarthur Ave Pinkenba QLD 4008",
    "addr:housenumber":"655",
    "addr:postcode":"4008",
    "addr:street":"Macarthur Ave",
    "iso:country":"AU",
    "sg:address":"655 Macarthur Ave",
    "sg:city":"Pinkenba",
    "sg:classifiers":[
        {
            "category":"Professional",
            "type":"Services"
        }
    ],
    "sg:phone":"+61 7 3633 4100",
    "sg:postcode":"4008",
    "sg:province":"QLD",
    "sg:tags":[
        "marine",
        "contractor"
    ],
    "wof:name":"Australian Maritime Systems",
    "wof:placetype":"venue"
},
  "geometry": {"coordinates":[153.11068725600001,-27.4354476929],"type":"Point"}
}