{
  "type": "Feature",
  "properties": {
    "addr:full":"12 Elizabeth Ave Taree NSW 2430",
    "addr:housenumber":"12",
    "addr:postcode":"2430",
    "addr:street":"Elizabeth Ave",
    "iso:country":"AU",
    "sg:address":"12 Elizabeth Ave",
    "sg:city":"Taree",
    "sg:classifiers":[
        {
            "category":"Professional",
            "subcategory":"Computer Services",
            "type":"Services"
        }
    ],
    "sg:phone":"+61 2 6552 6411",
    "sg:postcode":"2430",
    "sg:province":"NSW",
    "sg:tags":[
        "equipment",
        "networking",
        "installation"
    ],
    "wof:name":"Stowe Communications",
    "wof:placetype":"venue"
},
  "geometry": {"coordinates":[152.45349100000001,-31.902302],"type":"Point"}
}