{
  "type": "Feature",
  "properties": {
    "iso:country":"AU",
    "sg:address":"25 Bunnett St",
    "sg:city":"Sunshine North",
    "sg:classifiers":[
        {
            "category":"Manufacturing",
            "subcategory":"Glass & Minerals",
            "type":"Manufacturing & Wholesale Goods"
        }
    ],
    "sg:phone":"+61 3 9311 3136",
    "sg:postcode":"3020",
    "sg:province":"VIC",
    "sg:tags":[
        "merchant",
        "granite",
        "marble"
    ],
    "wof:name":"VP Kay Marble & Granite",
    "wof:placetype":"venue"
},
  "geometry": {"coordinates":[144.840164,-37.764355],"type":"Point"}
}