{
  "type": "Feature",
  "properties": {
    "addr:full":"PO Box 3797 Palmerston NT 0831",
    "addr:postcode":"nt 0831",
    "iso:country":"AU",
    "sg:address":"PO Box 3797",
    "sg:city":"Palmerston",
    "sg:classifiers":[
        {
            "category":"Building & Trades",
            "subcategory":"Construction",
            "type":"Services"
        }
    ],
    "sg:phone":"+61 408 954 877",
    "sg:postcode":"0831",
    "sg:province":"NT",
    "sg:tags":[
        "industrial",
        "commercial",
        "air conditioning"
    ],
    "wof:name":"Hannas Comfort Cooling",
    "wof:placetype":"venue"
},
  "geometry": {"coordinates":[130.983215,-12.48065],"type":"Point"}
}