{
  "type": "Feature",
  "properties": {
    "addr:full":"P O Box 6171 Waikiki WA 6169",
    "addr:postcode":"6169",
    "iso:country":"AU",
    "sg:address":"P O Box 6171",
    "sg:city":"Waikiki",
    "sg:classifiers":[
        {
            "category":"Building & Trades",
            "subcategory":"Locksmith",
            "type":"Services"
        }
    ],
    "sg:phone":"+61 8 9592 8093",
    "sg:postcode":"6169",
    "sg:province":"WA",
    "sg:tags":[
        "lock"
    ],
    "wof:name":"Total Lock Service",
    "wof:placetype":"venue"
},
  "geometry": {"coordinates":[115.753502,-32.31778],"type":"Point"}
}