{
  "type": "Feature",
  "properties": {
    "iso:country":"AU",
    "sg:address":"363 Portrush Rd",
    "sg:city":"Toorak Gardens",
    "sg:classifiers":[
        {
            "category":"Arts & Performance",
            "subcategory":"Art Gallery",
            "type":"Entertainment"
        }
    ],
    "sg:phone":"+61 8 8331 1577",
    "sg:postcode":"5065",
    "sg:province":"SA",
    "sg:tags":[
        "aboriginal",
        "craft"
    ],
    "wof:name":"Aust. Dreamtime Creations",
    "wof:placetype":"venue"
},
  "geometry": {"coordinates":[138.64183044399999,-34.9334983826],"type":"Point"}
}