{
  "type": "Feature",
  "properties": {
    "addr:full":"1 Kunjin St Corrigin WA 6375",
    "addr:housenumber":"1",
    "addr:postcode":"6375",
    "addr:street":"Kunjin St",
    "iso:country":"AU",
    "sg:address":"1 Kunjin St",
    "sg:city":"Corrigin",
    "sg:classifiers":[
        {
            "category":"Wholesale",
            "subcategory":"Machinery & Supplies",
            "type":"Manufacturing & Wholesale Goods"
        }
    ],
    "sg:phone":"+61 8 9063 2149",
    "sg:postcode":"6375",
    "sg:province":"WA",
    "sg:tags":[
        "bearing",
        "bushing"
    ],
    "wof:name":"Corrigin Bearing Service",
    "wof:placetype":"venue"
},
  "geometry": {"coordinates":[117.867401,-32.333748],"type":"Point"}
}