{
  "type": "Feature",
  "properties": {
    "iso:country":"AU",
    "sg:address":"Malaga Markets 7 Bonner Drv",
    "sg:city":"Malaga",
    "sg:classifiers":[
        {
            "category":"Deli",
            "type":"Food & Drink"
        }
    ],
    "sg:phone":"+61 8 9249 4405",
    "sg:postcode":"6090",
    "sg:province":"WA",
    "sg:tags":[
        "delicatessen"
    ],
    "wof:name":"Festivo Continental Foods",
    "wof:placetype":"venue"
},
  "geometry": {"coordinates":[115.880470276,-31.8507328033],"type":"Point"}
}