{
  "type": "Feature",
  "properties": {
    "iso:country":"AU",
    "sg:address":"Burchmann Rd",
    "sg:city":"Lockrose",
    "sg:classifiers":[
        {
            "category":"Farming",
            "subcategory":"Farm",
            "type":"Manufacturing & Wholesale Goods"
        }
    ],
    "sg:phone":"+61 7 5465 8208",
    "sg:postcode":"4342",
    "sg:province":"QLD",
    "sg:tags":[
        "farmer"
    ],
    "wof:name":"Boughen R H & E J",
    "wof:placetype":"venue"
},
  "geometry": {"coordinates":[152.44602966299999,-27.5048847198],"type":"Point"}
}