{
  "type": "Feature",
  "properties": {
    "addr:full":"31/6 Station Rd Margaret River WA 6285",
    "addr:housenumber":"31 / 6",
    "addr:postcode":"6285",
    "addr:street":"Station Rd",
    "iso:country":"AU",
    "sg:address":"31/6 Station Rd",
    "sg:city":"Margaret River",
    "sg:classifiers":[
        {
            "category":"Health Services",
            "subcategory":"Chiropractor",
            "type":"Services"
        }
    ],
    "sg:phone":"+61 8 9755 5273",
    "sg:postcode":"6285",
    "sg:province":"WA",
    "wof:name":"Station Road Chiropractic",
    "wof:placetype":"venue"
},
  "geometry": {"coordinates":[115.071296692,-33.9541511536],"type":"Point"}
}