{
  "type": "Feature",
  "properties": {
    "iso:country":"AU",
    "sg:address":"331 Sandgate Rd",
    "sg:city":"Albion",
    "sg:classifiers":[
        {
            "category":"Restaurant",
            "type":"Food & Drink"
        }
    ],
    "sg:phone":"+61 7 3862 2400",
    "sg:postcode":"4010",
    "sg:province":"QLD",
    "sg:website":"http://www.sitar.com.au",
    "wof:name":"Sitar Indian Restaurant",
    "wof:placetype":"venue"
},
  "geometry": {"coordinates":[153.042205811,-27.4294929504],"type":"Point"}
}