{
  "type": "Feature",
  "properties": {
    "iso:country":"AU",
    "sg:address":"193 Mclennan St",
    "sg:city":"Mooroopna",
    "sg:classifiers":[
        {
            "category":"Fast Food",
            "type":"Food & Drink"
        }
    ],
    "sg:phone":"+61 3 5825 1877",
    "sg:postcode":"3629",
    "sg:province":"VIC",
    "sg:tags":[
        "away",
        "take"
    ],
    "wof:name":"Kelly's Place",
    "wof:placetype":"venue"
},
  "geometry": {"coordinates":[145.34779357900001,-36.3966560364],"type":"Point"}
}