{
  "type": "Feature",
  "properties": {
    "addr:full":"135 Lovell St Young NSW 2594",
    "addr:housenumber":"135",
    "addr:postcode":"2594",
    "addr:street":"Lovell St",
    "iso:country":"AU",
    "sg:address":"135 Lovell St",
    "sg:city":"Young",
    "sg:classifiers":[
        {
            "category":"Wholesale",
            "subcategory":"Farm Supplies",
            "type":"Manufacturing & Wholesale Goods"
        }
    ],
    "sg:phone":"+61 2 6382 1666",
    "sg:postcode":"2594",
    "sg:province":"NSW",
    "sg:tags":[
        "feed",
        "supplement",
        "stock"
    ],
    "wof:name":"Young Stock Feeds Pty Ltd",
    "wof:placetype":"venue"
},
  "geometry": {"coordinates":[148.291183472,-34.310585022],"type":"Point"}
}