{
  "type": "Feature",
  "properties": {
    "addr:full":"42 Meares Rd McGraths Hill NSW 2756",
    "addr:housenumber":"42",
    "addr:postcode":"2756",
    "addr:street":"Meares Rd",
    "iso:country":"AU",
    "sg:address":"42 Meares Rd",
    "sg:city":"McGraths Hill",
    "sg:classifiers":[
        {
            "category":"Building & Trades",
            "subcategory":"Construction",
            "type":"Services"
        }
    ],
    "sg:phone":"+61 2 4587 8940",
    "sg:postcode":"2756",
    "sg:province":"NSW",
    "sg:tags":[
        "earth",
        "excavating",
        "moving",
        "contractor"
    ],
    "wof:name":"Andrew's Bobcat Services",
    "wof:placetype":"venue"
},
  "geometry": {"coordinates":[150.84107971200001,-33.6183776855],"type":"Point"}
}