{
  "type": "Feature",
  "properties": {
    "iso:country":"AU",
    "sg:address":"24 Gloucester Crs",
    "sg:city":"Bray Park",
    "sg:classifiers":[
        {
            "category":"Building & Trades",
            "subcategory":"Construction",
            "type":"Services"
        }
    ],
    "sg:phone":"+61 419 710 443",
    "sg:postcode":"4500",
    "sg:province":"QLD",
    "sg:tags":[
        "contractor"
    ],
    "wof:name":"Kevvia Contracting Pty Ltd",
    "wof:placetype":"venue"
},
  "geometry": {"coordinates":[153.04934692399999,-27.2995433807],"type":"Point"}
}