{
  "type": "Feature",
  "properties": {
    "addr:full":"Coal Rd Loy Yang VIC 3844",
    "addr:postcode":"3844",
    "addr:street":"Coal Rd",
    "iso:country":"AU",
    "sg:address":"Coal Rd",
    "sg:city":"Loy Yang",
    "sg:classifiers":[
        {
            "category":"Building & Trades",
            "subcategory":"Cleaning & Sanitation",
            "type":"Services"
        }
    ],
    "sg:phone":"+61 3 5173 3540",
    "sg:postcode":"3844",
    "sg:province":"VIC",
    "sg:tags":[
        "asbestos",
        "treatment",
        "removal"
    ],
    "wof:name":"Vac-Tech Group Pty Ltd",
    "wof:placetype":"venue"
},
  "geometry": {"coordinates":[146.571136475,-38.2154388428],"type":"Point"}
}