{
  "type": "Feature",
  "properties": {
    "addr:full":"438 Elizabeth St North Hobart TAS 7000",
    "addr:housenumber":"438",
    "addr:postcode":"7000",
    "addr:street":"Elizabeth St",
    "iso:country":"AU",
    "sg:address":"438 Elizabeth St",
    "sg:city":"North Hobart",
    "sg:classifiers":[
        {
            "category":"Health Services",
            "subcategory":"Doctor",
            "type":"Services"
        }
    ],
    "sg:phone":"+61 3 6234 5377",
    "sg:postcode":"7000",
    "sg:province":"TAS",
    "sg:tags":[
        "medical",
        "practitioner"
    ],
    "wof:name":"Nuwayhid Fadi",
    "wof:placetype":"venue"
},
  "geometry": {"coordinates":[147.312866211,-42.8711051941],"type":"Point"}
}