{
  "type": "Feature",
  "properties": {
    "addr:full":"24 Price St Nambour QLD 4560",
    "addr:housenumber":"24",
    "addr:postcode":"4560",
    "addr:street":"Price St",
    "iso:country":"AU",
    "sg:address":"24 Price St",
    "sg:city":"Nambour",
    "sg:classifiers":[
        {
            "category":"Retail",
            "subcategory":"Auto Repair",
            "type":"Services"
        }
    ],
    "sg:phone":"+61 7 5441 4955",
    "sg:postcode":"4560",
    "sg:province":"QLD",
    "sg:tags":[
        "beater",
        "painter",
        "panel"
    ],
    "wof:name":"Terry Nangle Smash Repairs",
    "wof:placetype":"venue"
},
  "geometry": {"coordinates":[152.95797729500001,-26.6241912842],"type":"Point"}
}