{
  "type": "Feature",
  "properties": {
    "iso:country":"AU",
    "sg:address":"10 Sturt St",
    "sg:city":"Smithfield",
    "sg:classifiers":[
        {
            "category":"Manufacturing",
            "subcategory":"Metals",
            "type":"Manufacturing & Wholesale Goods"
        }
    ],
    "sg:phone":"+61 2 9892 4353",
    "sg:postcode":"2164",
    "sg:province":"NSW",
    "sg:tags":[
        "steel",
        "fabricator",
        "mfrs"
    ],
    "wof:name":"Miles Special Builders & Services",
    "wof:placetype":"venue"
},
  "geometry": {"coordinates":[150.95472717300001,-33.848285675],"type":"Point"}
}