{
  "type": "Feature",
  "properties": {
    "addr:full":"10 Banyule Rd Rosanna VIC 3084",
    "addr:housenumber":"10",
    "addr:postcode":"3084",
    "addr:street":"Banyule Rd",
    "iso:country":"AU",
    "sg:address":"10 Banyule Rd",
    "sg:city":"Rosanna",
    "sg:classifiers":[
        {
            "category":"Education",
            "subcategory":"Special Training",
            "type":"Public Place"
        }
    ],
    "sg:phone":"+61 431 362 238",
    "sg:postcode":"3084",
    "sg:province":"VIC",
    "sg:tags":[
        "drama",
        "tuition"
    ],
    "wof:name":"Primarily Performers",
    "wof:placetype":"venue"
},
  "geometry": {"coordinates":[145.07330322300001,-37.7430648804],"type":"Point"}
}