{
  "type": "Feature",
  "properties": {
    "addr:full":"2 Nina St The Gap QLD 4061",
    "addr:housenumber":"2",
    "addr:postcode":"4061",
    "addr:street":"Nina St",
    "iso:country":"AU",
    "sg:address":"2 Nina St",
    "sg:city":"The Gap",
    "sg:classifiers":[
        {
            "category":"Personal",
            "type":"Services"
        }
    ],
    "sg:phone":"+61 7 3300 9501",
    "sg:postcode":"4061",
    "sg:province":"QLD",
    "sg:tags":[
        "wallpapering",
        "wallcovering"
    ],
    "wof:name":"Costanzo Sergio",
    "wof:placetype":"venue"
},
  "geometry": {"coordinates":[152.947555542,-27.4396915436],"type":"Point"}
}