{
  "type": "Feature",
  "properties": {
    "addr:full":"Shop 3,350 Bong Bong St (enter Boolwey St) Bowral NSW 2576",
    "addr:housenumber":"3,350 bong",
    "addr:postcode":"2576",
    "addr:street":"Bong St;Boolwey St",
    "iso:country":"AU",
    "sg:address":"Shop 3,350 Bong Bong St (enter Boolwey St)",
    "sg:city":"Bowral",
    "sg:classifiers":[
        {
            "category":"Health Services",
            "subcategory":"Optometrist",
            "type":"Services"
        }
    ],
    "sg:phone":"+61 2 4862 1190",
    "sg:postcode":"2576",
    "sg:province":"NSW",
    "sg:website":"http://www.bowraleyecarecentre.com.au",
    "wof:name":"Bowral Eye Care Centre Trevor Matley",
    "wof:placetype":"venue"
},
  "geometry": {"coordinates":[150.417694092,-34.4804267883],"type":"Point"}
}