{
  "type": "Feature",
  "properties": {
    "addr:full":"186- 202 York St South Melbourne VIC 3205",
    "addr:housenumber":"202",
    "addr:postcode":"3205",
    "addr:street":"York St",
    "iso:country":"AU",
    "sg:address":"186- 202 York St",
    "sg:city":"South Melbourne",
    "sg:classifiers":[
        {
            "category":"Wholesale",
            "subcategory":"Furniture",
            "type":"Manufacturing & Wholesale Goods"
        }
    ],
    "sg:phone":"+61 3 9686 3525",
    "sg:postcode":"3205",
    "sg:province":"VIC",
    "sg:tags":[
        "wholesaler",
        "mfrs"
    ],
    "wof:name":"Boss Furniture",
    "wof:placetype":"venue"
},
  "geometry": {"coordinates":[144.95529199999999,-37.831867],"type":"Point"}
}