{
  "type": "Feature",
  "properties": {
    "addr:full":"48 Dawson Hwy Biloela QLD 4715",
    "addr:housenumber":"48",
    "addr:postcode":"4715",
    "addr:street":"Dawson Hwy",
    "iso:country":"AU",
    "sg:address":"48 Dawson Hwy",
    "sg:city":"Biloela",
    "sg:classifiers":[
        {
            "category":"Manufacturing",
            "subcategory":"Tools & Machinery",
            "type":"Manufacturing & Wholesale Goods"
        }
    ],
    "sg:phone":"+61 7 4992 2133",
    "sg:postcode":"4715",
    "sg:province":"QLD",
    "wof:name":"Biloela Tools & Bearing Supplies Pty Ltd",
    "wof:placetype":"venue"
},
  "geometry": {"coordinates":[150.504302978,-24.4055309296],"type":"Point"}
}