{
  "type": "Feature",
  "properties": {
    "addr:full":"125 Barnier Drv Quakers Hill NSW 2763",
    "addr:housenumber":"125",
    "addr:postcode":"2763",
    "addr:street":"Barnier Drv",
    "iso:country":"AU",
    "sg:address":"125 Barnier Drv",
    "sg:city":"Quakers Hill",
    "sg:classifiers":[
        {
            "category":"Education",
            "subcategory":"School",
            "type":"Public Place"
        }
    ],
    "sg:phone":"+61 2 9626 3999",
    "sg:postcode":"2763",
    "sg:province":"NSW",
    "wof:name":"Mary Immaculate Primary School",
    "wof:placetype":"venue"
},
  "geometry": {"coordinates":[150.90301513700001,-33.7197532654],"type":"Point"}
}