{
  "type": "Feature",
  "properties": {
    "addr:full":"Innovation Drv Dowsing Point TAS 7010",
    "addr:postcode":"7010",
    "addr:street":"Innovation Drv",
    "iso:country":"AU",
    "sg:address":"Innovation Drv",
    "sg:city":"Dowsing Point",
    "sg:classifiers":[
        {
            "category":"Real Estate",
            "subcategory":"Architect",
            "type":"Services"
        }
    ],
    "sg:phone":"+61 3 6278 7113",
    "sg:postcode":"7010",
    "sg:province":"TAS",
    "sg:tags":[
        "building",
        "designer"
    ],
    "wof:name":"View Build Pty Ltd",
    "wof:placetype":"venue"
},
  "geometry": {"coordinates":[147.29690551799999,-42.8240814209],"type":"Point"}
}