{
  "type": "Feature",
  "properties": {
    "addr:full":"12- 14 Sydal St Caloundra QLD 4551",
    "addr:housenumber":"14",
    "addr:postcode":"4551",
    "addr:street":"Sydal St",
    "iso:country":"AU",
    "sg:address":"12- 14 Sydal St",
    "sg:city":"Caloundra",
    "sg:classifiers":[
        {
            "category":"Retail",
            "subcategory":"Storage",
            "type":"Services"
        }
    ],
    "sg:phone":"+61 7 5499 7011",
    "sg:postcode":"4551",
    "sg:province":"QLD",
    "sg:tags":[
        "removal",
        "furniture"
    ],
    "wof:name":"Fort Knox Storage Group",
    "wof:placetype":"venue"
},
  "geometry": {"coordinates":[153.103912353,-26.7949466705],"type":"Point"}
}