{
  "type": "Feature",
  "properties": {
    "addr:full":"Pickernell Rd Varley WA 6355",
    "addr:postcode":"6355",
    "addr:street":"Pickernell Rd",
    "iso:country":"AU",
    "sg:address":"Pickernell Rd",
    "sg:city":"Varley",
    "sg:classifiers":[
        {
            "category":"Farming",
            "subcategory":"Farm",
            "type":"Manufacturing & Wholesale Goods"
        }
    ],
    "sg:phone":"+61 8 9875 1045",
    "sg:postcode":"6355",
    "sg:province":"WA",
    "sg:tags":[
        "farmer"
    ],
    "wof:name":"Metcalf S T & T G",
    "wof:placetype":"venue"
},
  "geometry": {"coordinates":[119.62563299999999,-32.841736],"type":"Point"}
}