{
  "type": "Feature",
  "properties": {
    "addr:full":"2 Wellington St Kerang VIC 3579",
    "addr:housenumber":"2",
    "addr:postcode":"3579",
    "addr:street":"Wellington St",
    "iso:country":"AU",
    "sg:address":"2 Wellington St",
    "sg:city":"Kerang",
    "sg:classifiers":[
        {
            "category":"Wholesale",
            "subcategory":"Machinery & Supplies",
            "type":"Manufacturing & Wholesale Goods"
        }
    ],
    "sg:phone":"+61 3 5452 2697",
    "sg:postcode":"3579",
    "sg:province":"VIC",
    "sg:tags":[
        "agricultural"
    ],
    "wof:name":"Frieling H T & W J Pty. Ltd",
    "wof:placetype":"venue"
},
  "geometry": {"coordinates":[143.91792297399999,-35.7366409302],"type":"Point"}
}