{
  "type": "Feature",
  "properties": {
    "addr:full":"10 Lambert Ave Sandy Bay TAS 7005",
    "addr:housenumber":"10",
    "addr:postcode":"7005",
    "addr:street":"Lambert Ave",
    "iso:country":"AU",
    "sg:address":"10 Lambert Ave",
    "sg:city":"Sandy Bay",
    "sg:classifiers":[
        {
            "category":"Building & Trades",
            "subcategory":"Plumbing",
            "type":"Services"
        }
    ],
    "sg:phone":"+61 1800 888 766",
    "sg:postcode":"7005",
    "sg:province":"TAS",
    "sg:tags":[
        "plumber",
        "gasfitters"
    ],
    "wof:name":"Underground Asset Services",
    "wof:placetype":"venue"
},
  "geometry": {"coordinates":[147.334472656,-42.9037017822],"type":"Point"}
}