{
  "type": "Feature",
  "properties": {
    "iso:country":"AU",
    "sg:address":"Ste14/ 235 Spit Rd",
    "sg:city":"Mosman",
    "sg:classifiers":[
        {
            "category":"Education",
            "subcategory":"Dance Studio",
            "type":"Public Place"
        }
    ],
    "sg:phone":"+61 1300 735 581",
    "sg:postcode":"2088",
    "sg:province":"NSW",
    "sg:tags":[
        "venue",
        "tuition"
    ],
    "wof:name":"Pole Stars Australia",
    "wof:placetype":"venue"
},
  "geometry": {"coordinates":[151.246994019,-33.8066635132],"type":"Point"}
}