{
  "type": "Feature",
  "properties": {
    "iso:country":"AU",
    "sg:address":"2a Russell Ave",
    "sg:city":"Sans Souci",
    "sg:classifiers":[
        {
            "category":"Manufacturing",
            "subcategory":"Printing",
            "type":"Manufacturing & Wholesale Goods"
        }
    ],
    "sg:phone":"+61 2 9529 5077",
    "sg:postcode":"2219",
    "sg:province":"NSW",
    "sg:tags":[
        "wholesaler",
        "mfrs",
        "greeting",
        "card"
    ],
    "wof:name":"LPO Services Pty Ltd",
    "wof:placetype":"venue"
},
  "geometry": {"coordinates":[151.13220200000001,-33.992641],"type":"Point"}
}