{
  "type": "Feature",
  "properties": {
    "addr:full":"401 Mountain View Rd Maleny QLD 4552",
    "addr:housenumber":"401",
    "addr:postcode":"4552",
    "addr:street":"Mountain View Rd",
    "iso:country":"AU",
    "sg:address":"401 Mountain View Rd",
    "sg:city":"Maleny",
    "sg:classifiers":[
        {
            "category":"Restaurant",
            "type":"Food & Drink"
        }
    ],
    "sg:phone":"+61 7 5499 9377",
    "sg:postcode":"4552",
    "sg:province":"QLD",
    "wof:name":"King Ludwigs German Restaurant",
    "wof:placetype":"venue"
},
  "geometry": {"coordinates":[152.856033325,-26.7799968719],"type":"Point"}
}