{
  "type": "Feature",
  "properties": {
    "addr:full":"57 Greenslade St Tingalpa QLD 4173",
    "addr:housenumber":"57",
    "addr:postcode":"4173",
    "addr:street":"Greenslade St",
    "iso:country":"AU",
    "sg:address":"57 Greenslade St",
    "sg:city":"Tingalpa",
    "sg:classifiers":[
        {
            "category":"Building & Trades",
            "subcategory":"Plumbing",
            "type":"Services"
        }
    ],
    "sg:phone":"+61 7 3901 2339",
    "sg:postcode":"4173",
    "sg:province":"QLD",
    "sg:tags":[
        "plumber",
        "gasfitters"
    ],
    "wof:name":"Solve All Plumbing & Property Maintenance Pty Ltd",
    "wof:placetype":"venue"
},
  "geometry": {"coordinates":[153.12625122099999,-27.4704360962],"type":"Point"}
}