{
  "type": "Feature",
  "properties": {
    "addr:full":"11 Leake St Essendon VIC 3040",
    "addr:housenumber":"11",
    "addr:postcode":"3040",
    "addr:street":"Leake St",
    "iso:country":"AU",
    "sg:address":"11 Leake St",
    "sg:city":"Essendon",
    "sg:classifiers":[
        {
            "category":"Health Services",
            "subcategory":"Doctor",
            "type":"Services"
        }
    ],
    "sg:phone":"+61 3 9379 2042",
    "sg:postcode":"3040",
    "sg:province":"VIC",
    "sg:tags":[
        "medical",
        "practitioner"
    ],
    "wof:name":"Leake St Clinic",
    "wof:placetype":"venue"
},
  "geometry": {"coordinates":[144.91053772000001,-37.7466278076],"type":"Point"}
}