{
  "type": "Feature",
  "properties": {
    "addr:full":"31 Stirling Hwy Nedlands WA 6009",
    "addr:housenumber":"31",
    "addr:postcode":"6009",
    "addr:street":"Stirling Hwy",
    "iso:country":"AU",
    "sg:address":"31 Stirling Hwy",
    "sg:city":"Nedlands",
    "sg:classifiers":[
        {
            "category":"Health Services",
            "subcategory":"Dentist",
            "type":"Services"
        }
    ],
    "sg:phone":"+61 8 9386 6598",
    "sg:postcode":"6009",
    "sg:province":"WA",
    "wof:name":"Harris Peter M",
    "wof:placetype":"venue"
},
  "geometry": {"coordinates":[115.810913,-31.97773],"type":"Point"}
}