{
  "type": "Feature",
  "properties": {
    "addr:full":"182 Broome St Cottesloe WA 6011",
    "addr:housenumber":"182",
    "addr:postcode":"6011",
    "addr:street":"Broome St",
    "iso:country":"AU",
    "sg:address":"182 Broome St",
    "sg:city":"Cottesloe",
    "sg:classifiers":[
        {
            "category":"Professional",
            "subcategory":"Research",
            "type":"Services"
        }
    ],
    "sg:phone":"+61 8 9385 1938",
    "sg:postcode":"6011",
    "sg:province":"WA",
    "sg:tags":[
        "historical"
    ],
    "wof:name":"Art Deco Society Of WA (Inc)",
    "wof:placetype":"venue"
},
  "geometry": {"coordinates":[115.756317139,-31.9869766235],"type":"Point"}
}