{
  "type": "Feature",
  "properties": {
    "addr:full":"Unit 6, 39 Mather Drv Neerabup WA 6031",
    "addr:housenumber":"39",
    "addr:postcode":"6031",
    "addr:street":"Mather Drv",
    "iso:country":"AU",
    "sg:address":"Unit 6, 39 Mather Drv",
    "sg:city":"Neerabup",
    "sg:classifiers":[
        {
            "category":"Manufacturing",
            "subcategory":"Glass & Minerals",
            "type":"Manufacturing & Wholesale Goods"
        }
    ],
    "sg:phone":"+61 421 967 672",
    "sg:postcode":"6031",
    "sg:province":"WA",
    "sg:tags":[
        "repair",
        "fibreglass",
        "product"
    ],
    "wof:name":"JS Fibreglass",
    "wof:placetype":"venue"
},
  "geometry": {"coordinates":[115.788803101,-31.6845989227],"type":"Point"}
}