{
  "type": "Feature",
  "properties": {
    "addr:full":"36 Union St Armadale VIC 3143",
    "addr:housenumber":"36",
    "addr:postcode":"3143",
    "addr:street":"Union St",
    "iso:country":"AU",
    "sg:address":"36 Union St",
    "sg:city":"Armadale",
    "sg:classifiers":[
        {
            "category":"Professional",
            "subcategory":"Accounting & Tax Preparation",
            "type":"Services"
        }
    ],
    "sg:phone":"+61 3 9576 1859",
    "sg:postcode":"3143",
    "sg:province":"VIC",
    "sg:tags":[
        "accountant",
        "auditor"
    ],
    "wof:name":"Wellingtons Accounting Services",
    "wof:placetype":"venue"
},
  "geometry": {"coordinates":[145.02484130900001,-37.8591880798],"type":"Point"}
}