{
  "type": "Feature",
  "properties": {
    "iso:country":"AU",
    "sg:address":"Unit 1/ 4 Jamieson Pl",
    "sg:city":"Glendenning",
    "sg:classifiers":[
        {
            "category":"Food & Beverages",
            "subcategory":"Supermarket",
            "type":"Retail Goods"
        }
    ],
    "sg:phone":"+61 2 9625 4118",
    "sg:postcode":"2761",
    "sg:province":"NSW",
    "sg:tags":[
        "grocery",
        "store"
    ],
    "wof:name":"Pacific Green Groceries",
    "wof:placetype":"venue"
},
  "geometry": {"coordinates":[150.852966,-33.757526],"type":"Point"}
}