{
  "type": "Feature",
  "properties": {
    "addr:full":"96 Neil St Toowoomba QLD 4350",
    "addr:housenumber":"96",
    "addr:postcode":"4350",
    "addr:street":"Neil St",
    "iso:country":"AU",
    "sg:address":"96 Neil St",
    "sg:city":"Toowoomba",
    "sg:classifiers":[
        {
            "category":"Health Services",
            "subcategory":"Dentist",
            "type":"Services"
        }
    ],
    "sg:phone":"+61 7 4632 5622",
    "sg:postcode":"4350",
    "sg:province":"QLD",
    "wof:name":"Milne Kerry Dr",
    "wof:placetype":"venue"
},
  "geometry": {"coordinates":[151.95451399999999,-27.567986],"type":"Point"}
}