{
  "type": "Feature",
  "properties": {
    "addr:full":"271- 273 Rex Rd (Corner of Northbourne Rd) Campbellfield VIC 3061",
    "addr:housenumber":"271 273",
    "addr:postcode":"3061",
    "addr:street":"Rex Rd Corner Of Northbourne Rd",
    "iso:country":"AU",
    "sg:address":"271- 273 Rex Rd (Corner of Northbourne Rd)",
    "sg:city":"Campbellfield",
    "sg:classifiers":[
        {
            "category":"Manufacturing",
            "subcategory":"Building Materials",
            "type":"Manufacturing & Wholesale Goods"
        }
    ],
    "sg:phone":"+61 1300 732 494",
    "sg:postcode":"3061",
    "sg:province":"VIC",
    "sg:tags":[
        "equipment",
        "handling"
    ],
    "sg:website":"http://www.alpharacking.com.au",
    "wof:name":"Alpha Racking",
    "wof:placetype":"venue"
},
  "geometry": {"coordinates":[144.963134766,-37.6480636597],"type":"Point"}
}