{
  "type": "Feature",
  "properties": {
    "addr:full":"813 Fifteenth Ave West Hoxton NSW 2171",
    "addr:housenumber":"813",
    "addr:postcode":"2171",
    "addr:street":"Fifteenth Ave West",
    "iso:country":"AU",
    "sg:address":"813 Fifteenth Ave",
    "sg:city":"West Hoxton",
    "sg:classifiers":[
        {
            "category":"Retail",
            "subcategory":"Auto Repair",
            "type":"Services"
        }
    ],
    "sg:phone":"+61 2 9606 0308",
    "sg:postcode":"2171",
    "sg:province":"NSW",
    "sg:tags":[
        "repairer",
        "motor",
        "engineer"
    ],
    "wof:name":"Advance Automotive Repairs",
    "wof:placetype":"venue"
},
  "geometry": {"coordinates":[150.829620361,-33.9208221436],"type":"Point"}
}