{
  "type": "Feature",
  "properties": {
    "iso:country":"AU",
    "sg:address":"54 Middle St",
    "sg:city":"Chinchilla",
    "sg:classifiers":[
        {
            "category":"Health Services",
            "subcategory":"Doctor",
            "type":"Services"
        }
    ],
    "sg:phone":"+61 7 4662 7094",
    "sg:postcode":"4413",
    "sg:province":"QLD",
    "sg:tags":[
        "nurse",
        "nursing"
    ],
    "wof:name":"Spiritus Care Services",
    "wof:placetype":"venue"
},
  "geometry": {"coordinates":[150.62713623100001,-26.7432575226],"type":"Point"}
}