{
  "type": "Feature",
  "properties": {
    "iso:country":"AU",
    "sg:address":"16 Winston Pl",
    "sg:city":"Devonport",
    "sg:classifiers":[
        {
            "category":"Health Services",
            "subcategory":"Health Practitioner",
            "type":"Services"
        }
    ],
    "sg:phone":"+61 3 6423 6059",
    "sg:postcode":"7310",
    "sg:province":"TAS",
    "sg:tags":[
        "pathologist",
        "speech"
    ],
    "wof:name":"Brooke Lynn M",
    "wof:placetype":"venue"
},
  "geometry": {"coordinates":[146.348709106,-41.1699028015],"type":"Point"}
}