{
  "type": "Feature",
  "properties": {
    "iso:country":"AU",
    "sg:address":"Eulo St",
    "sg:city":"Baralaba",
    "sg:classifiers":[
        {
            "category":"Farming",
            "subcategory":"Farm",
            "type":"Manufacturing & Wholesale Goods"
        }
    ],
    "sg:phone":"+61 7 4998 1218",
    "sg:postcode":"4702",
    "sg:province":"QLD",
    "sg:tags":[
        "farmer"
    ],
    "wof:name":"Johnston E R",
    "wof:placetype":"venue"
},
  "geometry": {"coordinates":[147.65101623499999,-23.455619812],"type":"Point"}
}