{
  "type": "Feature",
  "properties": {
    "addr:full":"82 William St Norwood SA 5067",
    "addr:housenumber":"82",
    "addr:postcode":"5067",
    "addr:street":"William St",
    "iso:country":"AU",
    "sg:address":"82 William St",
    "sg:city":"Norwood",
    "sg:classifiers":[
        {
            "category":"Farming",
            "subcategory":"Farm & Veterinary Services",
            "type":"Manufacturing & Wholesale Goods"
        }
    ],
    "sg:phone":"+61 417 925 824",
    "sg:postcode":"5067",
    "sg:province":"SA",
    "sg:tags":[
        "agricultural",
        "advisory"
    ],
    "wof:name":"Pro-Ag Consulting",
    "wof:placetype":"venue"
},
  "geometry": {"coordinates":[138.630935669,-34.9246025085],"type":"Point"}
}