{
  "type": "Feature",
  "properties": {
    "addr:full":"3 Round Hay Crt Berwick VIC 3806",
    "addr:housenumber":"3",
    "addr:postcode":"3806",
    "addr:street":"Round Hay Crt",
    "iso:country":"AU",
    "sg:address":"3 Round Hay Crt",
    "sg:city":"Berwick",
    "sg:classifiers":[
        {
            "category":"Manufacturing",
            "subcategory":"Metals",
            "type":"Manufacturing & Wholesale Goods"
        }
    ],
    "sg:phone":"+61 412 091 811",
    "sg:postcode":"3806",
    "sg:province":"VIC",
    "sg:tags":[
        "steel",
        "fabricator",
        "mfrs"
    ],
    "wof:name":"Berwick Fabrications",
    "wof:placetype":"venue"
},
  "geometry": {"coordinates":[145.349853516,-38.0267944336],"type":"Point"}
}