{
  "type": "Feature",
  "properties": {
    "iso:country":"AU",
    "sg:address":"Lot 1 Princes Hwy",
    "sg:city":"Winchelsea",
    "sg:classifiers":[
        {
            "category":"Retail",
            "subcategory":"Auto Repair",
            "type":"Services"
        }
    ],
    "sg:phone":"+61 3 5267 2421",
    "sg:postcode":"3241",
    "sg:province":"VIC",
    "sg:tags":[
        "repairer",
        "motor",
        "engineer"
    ],
    "wof:name":"Johnson Brothers",
    "wof:placetype":"venue"
},
  "geometry": {"coordinates":[143.99371337900001,-38.2388267517],"type":"Point"}
}