{
  "type": "Feature",
  "properties": {
    "addr:full":"23- 33 Ogilvie Ave Echuca VIC 3564",
    "addr:housenumber":"33",
    "addr:postcode":"3564",
    "addr:street":"Ogilvie Ave",
    "iso:country":"AU",
    "sg:address":"23- 33 Ogilvie Ave",
    "sg:city":"Echuca",
    "sg:classifiers":[
        {
            "category":"Communications",
            "subcategory":"News Services",
            "type":"Services"
        }
    ],
    "sg:phone":"+61 3 5482 2730",
    "sg:postcode":"3564",
    "sg:province":"VIC",
    "sg:tags":[
        "information",
        "tourist",
        "attractions"
    ],
    "wof:name":"Raverty's Motor Museum",
    "wof:placetype":"venue"
},
  "geometry": {"coordinates":[144.74827575699999,-36.1404953003],"type":"Point"}
}