{
  "type": "Feature",
  "properties": {
    "iso:country":"AU",
    "sg:address":"4 Mc Ewans Beach Rd",
    "sg:city":"Mackay",
    "sg:classifiers":[
        {
            "category":"Manufacturing",
            "subcategory":"Tools & Machinery",
            "type":"Manufacturing & Wholesale Goods"
        }
    ],
    "sg:phone":"+61 7 4944 1778",
    "sg:postcode":"4740",
    "sg:province":"QLD",
    "sg:tags":[
        "equipment",
        "scale",
        "weighing"
    ],
    "wof:name":"Australasia Scales",
    "wof:placetype":"venue"
},
  "geometry": {"coordinates":[149.169693,-21.236025],"type":"Point"}
}