{
  "type": "Feature",
  "properties": {
    "iso:country":"AU",
    "sg:address":"33 Manmanning Rd",
    "sg:city":"Wongan Hills",
    "sg:classifiers":[
        {
            "category":"Insurance",
            "subcategory":"Insurance Agent",
            "type":"Services"
        }
    ],
    "sg:phone":"+61 8 9671 1269",
    "sg:postcode":"6603",
    "sg:province":"WA",
    "sg:tags":[
        "wool",
        "broker"
    ],
    "wof:name":"GH Michell & Sons (Aust) Pty Ltd",
    "wof:placetype":"venue"
},
  "geometry": {"coordinates":[116.725692749,-30.8986244202],"type":"Point"}
}