{
  "type": "Feature",
  "properties": {
    "addr:full":"37 Bates St Merredin WA 6415",
    "addr:housenumber":"37",
    "addr:postcode":"6415",
    "addr:street":"Bates St",
    "iso:country":"AU",
    "sg:address":"37 Bates St",
    "sg:city":"Merredin",
    "sg:classifiers":[
        {
            "category":"Home & Garden",
            "subcategory":"Household Appliances",
            "type":"Retail Goods"
        }
    ],
    "sg:phone":"+61 8 9041 1391",
    "sg:postcode":"6415",
    "sg:province":"WA",
    "sg:tags":[
        "equipment",
        "gas"
    ],
    "wof:name":"Merredin Refrigeration & Gas",
    "wof:placetype":"venue"
},
  "geometry": {"coordinates":[118.278800964,-31.4796161652],"type":"Point"}
}