{
  "type": "Feature",
  "properties": {
    "iso:country":"AU",
    "sg:address":"1st Floor, 54 Kitchener Pde",
    "sg:city":"Bankstown",
    "sg:classifiers":[
        {
            "category":"Health Services",
            "subcategory":"Doctor",
            "type":"Services"
        }
    ],
    "sg:phone":"+61 2 9709 6314",
    "sg:postcode":"2200",
    "sg:province":"NSW",
    "sg:tags":[
        "medical",
        "practitioner"
    ],
    "wof:name":"Davies Campbell de Lambert Pathology",
    "wof:placetype":"venue"
},
  "geometry": {"coordinates":[151.03273,-33.916874],"type":"Point"}
}