{
  "type": "Feature",
  "properties": {
    "iso:country":"AU",
    "sg:address":"16 Boulder Rd",
    "sg:city":"Malaga",
    "sg:classifiers":[
        {
            "category":"Mining & Drilling",
            "type":"Manufacturing & Wholesale Goods"
        }
    ],
    "sg:phone":"+61 8 9209 2126",
    "sg:postcode":"6090",
    "sg:province":"WA",
    "sg:tags":[
        "boring",
        "contractor"
    ],
    "wof:name":"Austral Drilling Services Pty Ltd",
    "wof:placetype":"venue"
},
  "geometry": {"coordinates":[115.901481628,-31.8649635315],"type":"Point"}
}