{
  "type": "Feature",
  "properties": {
    "iso:country":"AU",
    "sg:address":"3 Hayes St",
    "sg:city":"Bentleigh",
    "sg:classifiers":[
        {
            "category":"Education",
            "subcategory":"Special Training",
            "type":"Public Place"
        }
    ],
    "sg:phone":"+61 3 9576 5919",
    "sg:postcode":"3204",
    "sg:province":"VIC",
    "sg:tags":[
        "development"
    ],
    "wof:name":"VoTech Training Services",
    "wof:placetype":"venue"
},
  "geometry": {"coordinates":[145.04068,-37.916706],"type":"Point"}
}