{
  "type": "Feature",
  "properties": {
    "addr:full":"4 Durham Rd Armidale NSW 2350",
    "addr:housenumber":"4",
    "addr:postcode":"2350",
    "addr:street":"Durham Rd",
    "iso:country":"AU",
    "sg:address":"4 Durham Rd",
    "sg:city":"Armidale",
    "sg:classifiers":[
        {
            "category":"Professional",
            "subcategory":"Art Services",
            "type":"Services"
        }
    ],
    "sg:phone":"+61 2 6771 1799",
    "sg:postcode":"2350",
    "sg:province":"NSW",
    "sg:tags":[
        "decorator",
        "painter"
    ],
    "wof:name":"O&#039;Hara B & E",
    "wof:placetype":"venue"
},
  "geometry": {"coordinates":[151.67103576700001,-30.5553035736],"type":"Point"}
}