{
  "type": "Feature",
  "properties": {
    "iso:country":"AU",
    "sg:address":"Shop 2 / 17 Julie St,",
    "sg:city":"Crestmead",
    "sg:classifiers":[
        {
            "category":"Personal",
            "subcategory":"Beauty Salon",
            "type":"Services"
        }
    ],
    "sg:phone":"+61 7 3803 3940",
    "sg:postcode":"4132",
    "sg:province":"QLD",
    "sg:tags":[
        "hairdresser"
    ],
    "wof:name":"Honeycombs Hair & Beauty Salon",
    "wof:placetype":"venue"
},
  "geometry": {"coordinates":[153.08201599099999,-27.6973304749],"type":"Point"}
}