{
  "type": "Feature",
  "properties": {
    "addr:full":"187 Elizabeth Drv Liverpool NSW 2170",
    "addr:housenumber":"187",
    "addr:postcode":"2170",
    "addr:street":"Elizabeth Drv",
    "iso:country":"AU",
    "sg:address":"187 Elizabeth Drv",
    "sg:city":"Liverpool",
    "sg:classifiers":[
        {
            "category":"Fast Food",
            "type":"Food & Drink"
        }
    ],
    "sg:phone":"+61 2 9734 6528",
    "sg:postcode":"2170",
    "sg:province":"NSW",
    "sg:tags":[
        "away",
        "take"
    ],
    "wof:name":"D & P Takeaway",
    "wof:placetype":"venue"
},
  "geometry": {"coordinates":[150.89857482900001,-33.9069900513],"type":"Point"}
}