{
  "type": "Feature",
  "properties": {
    "addr:full":"Suite 1, 113 Dawson St Lismore NSW 2480",
    "addr:housenumber":"113",
    "addr:postcode":"2480",
    "addr:street":"Dawson St",
    "iso:country":"AU",
    "sg:address":"Suite 1, 113 Dawson St",
    "sg:city":"Lismore",
    "sg:classifiers":[
        {
            "category":"Organizations",
            "subcategory":"Professional Association",
            "type":"Services"
        }
    ],
    "sg:phone":"+61 2 6622 4933",
    "sg:postcode":"2480",
    "sg:province":"NSW",
    "sg:tags":[
        "rural",
        "organisation",
        "production",
        "primary"
    ],
    "wof:name":"Australian Macadamia Society Ltd",
    "wof:placetype":"venue"
},
  "geometry": {"coordinates":[153.27944946299999,-28.811422348],"type":"Point"}
}