{
  "type": "Feature",
  "properties": {
    "iso:country":"AU",
    "sg:address":"Lvl 1/ 65 Mary St",
    "sg:city":"Brisbane",
    "sg:classifiers":[
        {
            "category":"Professional",
            "subcategory":"Detective & Security Services",
            "type":"Services"
        }
    ],
    "sg:phone":"+61 411 427 637",
    "sg:postcode":"4000",
    "sg:province":"QLD",
    "sg:tags":[
        "guard",
        "patrol"
    ],
    "wof:name":"Corporate Security And Training",
    "wof:placetype":"venue"
},
  "geometry": {"coordinates":[153.02728271500001,-27.4722423553],"type":"Point"}
}