{
  "type": "Feature",
  "properties": {
    "addr:full":"248 Huntingdale Rd Huntingdale VIC 3166",
    "addr:housenumber":"248",
    "addr:postcode":"3166",
    "addr:street":"Huntingdale Rd",
    "iso:country":"AU",
    "sg:address":"248 Huntingdale Rd",
    "sg:city":"Huntingdale",
    "sg:classifiers":[
        {
            "category":"Home & Garden",
            "subcategory":"Hardware",
            "type":"Retail Goods"
        }
    ],
    "sg:phone":"+61 3 9543 3973",
    "sg:postcode":"3166",
    "sg:province":"VIC",
    "sg:tags":[
        "repair",
        "tool",
        "power"
    ],
    "wof:name":"Huntingdale Power Tools",
    "wof:placetype":"venue"
},
  "geometry": {"coordinates":[145.10472106899999,-37.9056167603],"type":"Point"}
}