{
  "type": "Feature",
  "properties": {
    "addr:full":"6 Lawson Ave Beresfield NSW 2322",
    "addr:housenumber":"6",
    "addr:postcode":"2322",
    "addr:street":"Lawson Ave",
    "iso:country":"AU",
    "sg:address":"6 Lawson Ave",
    "sg:city":"Beresfield",
    "sg:classifiers":[
        {
            "category":"Communications",
            "subcategory":"Film & Video Production",
            "type":"Services"
        }
    ],
    "sg:phone":"+61 2 4964 1044",
    "sg:postcode":"2322",
    "sg:province":"NSW",
    "sg:tags":[
        "dvd",
        "library"
    ],
    "wof:name":"Movie Shack Pty Ltd",
    "wof:placetype":"venue"
},
  "geometry": {"coordinates":[151.65835571299999,-32.800945282],"type":"Point"}
}