{
  "type": "Feature",
  "properties": {
    "addr:full":"PO Box 192 Lancefield VIC 3435",
    "addr:postcode":"3435",
    "iso:country":"AU",
    "sg:address":"PO Box 192",
    "sg:city":"Lancefield",
    "sg:classifiers":[
        {
            "category":"Home & Garden",
            "subcategory":"Home Furnishings",
            "type":"Retail Goods"
        }
    ],
    "sg:phone":"+61 3 5429 2526",
    "sg:postcode":"3435",
    "sg:province":"VIC",
    "sg:tags":[
        "storage",
        "rack",
        "wine"
    ],
    "wof:name":"D&L Gates & Home Furnishings",
    "wof:placetype":"venue"
},
  "geometry": {"coordinates":[144.736816406,-37.2784500122],"type":"Point"}
}