{
  "type": "Feature",
  "properties": {
    "iso:country":"AU",
    "sg:address":"1 Mann St",
    "sg:city":"Gosford",
    "sg:classifiers":[
        {
            "category":"Building & Trades",
            "subcategory":"Construction",
            "type":"Services"
        }
    ],
    "sg:phone":"+61 2 4323 7900",
    "sg:postcode":"2250",
    "sg:province":"NSW",
    "sg:tags":[
        "roof"
    ],
    "wof:name":"Riviera Developments Pty Ltd",
    "wof:placetype":"venue"
},
  "geometry": {"coordinates":[151.34124755900001,-33.4317207336],"type":"Point"}
}