{
  "type": "Feature",
  "properties": {
    "iso:country":"AU",
    "sg:address":"201/104- 112 Maroubra Rd",
    "sg:city":"Maroubra",
    "sg:classifiers":[
        {
            "category":"Personal",
            "type":"Services"
        }
    ],
    "sg:phone":"+61 2 9344 8762",
    "sg:postcode":"2035",
    "sg:province":"NSW",
    "sg:tags":[
        "reducing",
        "treatment",
        "weight"
    ],
    "wof:name":"Herbalife Maroubra",
    "wof:placetype":"venue"
},
  "geometry": {"coordinates":[151.23570251500001,-33.9408950806],"type":"Point"}
}