{
  "type": "Feature",
  "properties": {
    "addr:full":"Cnr Mulgrave Rd & Draper St Cairns QLD 4870",
    "addr:postcode":"4870",
    "addr:street":"Cnr Mulgrave Rd & Draper St",
    "iso:country":"AU",
    "sg:address":"Cnr Mulgrave Rd & Draper St",
    "sg:city":"Cairns",
    "sg:classifiers":[
        {
            "category":"Real Estate",
            "subcategory":"Developer",
            "type":"Services"
        }
    ],
    "sg:phone":"+61 7 4030 0100",
    "sg:postcode":"4870",
    "sg:province":"QLD",
    "sg:tags":[
        "chartering",
        "ship",
        "broker"
    ],
    "wof:name":"Markwell Marine",
    "wof:placetype":"venue"
},
  "geometry": {"coordinates":[145.76617431599999,-16.9237804413],"type":"Point"}
}