{
  "type": "Feature",
  "properties": {
    "addr:full":"507 Dean St Albury NSW 2640",
    "addr:housenumber":"507",
    "addr:postcode":"2640",
    "addr:street":"Dean St",
    "iso:country":"AU",
    "sg:address":"507 Dean St",
    "sg:city":"Albury",
    "sg:classifiers":[
        {
            "category":"Personal",
            "subcategory":"Beauty Salon",
            "type":"Services"
        }
    ],
    "sg:phone":"+61 2 6022 4099",
    "sg:postcode":"2640",
    "sg:province":"NSW",
    "wof:name":"Beauty for life",
    "wof:placetype":"venue"
},
  "geometry": {"coordinates":[146.912185669,-36.0803794861],"type":"Point"}
}