{
  "type": "Feature",
  "properties": {
    "iso:country":"AU",
    "sg:address":"40 Guernsey Ave",
    "sg:city":"Minto",
    "sg:classifiers":[
        {
            "category":"Social Services",
            "subcategory":"Child Care",
            "type":"Services"
        }
    ],
    "sg:phone":"+61 2 9603 6747",
    "sg:postcode":"2566",
    "sg:province":"NSW",
    "wof:name":"Kabbarli Early Learning Centre",
    "wof:placetype":"venue"
},
  "geometry": {"coordinates":[150.854171753,-34.0232887268],"type":"Point"}
}