{
  "type": "Feature",
  "properties": {
    "iso:country":"AU",
    "sg:address":"10 Bellbird Crs",
    "sg:city":"Vermont",
    "sg:classifiers":[
        {
            "category":"Professional",
            "subcategory":"Employment Agencies",
            "type":"Services"
        }
    ],
    "sg:phone":"+61 3 9872 3807",
    "sg:postcode":"3133",
    "sg:province":"VIC",
    "sg:tags":[
        "provider",
        "internet"
    ],
    "wof:name":"Melbourne Remote Systems",
    "wof:placetype":"venue"
},
  "geometry": {"coordinates":[145.226318359,-37.8419532776],"type":"Point"}
}