{
  "type": "Feature",
  "properties": {
    "iso:country":"AU",
    "sg:address":"110 Teven Rd",
    "sg:city":"Ballina",
    "sg:classifiers":[
        {
            "category":"Home & Garden",
            "subcategory":"Building Materials",
            "type":"Retail Goods"
        }
    ],
    "sg:phone":"+61 2 6686 7911",
    "sg:postcode":"2478",
    "sg:province":"NSW",
    "sg:tags":[
        "fencing"
    ],
    "wof:name":"Great Australian Fencing Company (The)",
    "wof:placetype":"venue"
},
  "geometry": {"coordinates":[153.521560669,-28.8527889252],"type":"Point"}
}