{
  "type": "Feature",
  "properties": {
    "addr:full":"Blanchards Rd Brogo NSW 2550",
    "addr:postcode":"2550",
    "addr:street":"Blanchards Rd",
    "iso:country":"AU",
    "sg:address":"Blanchards Rd",
    "sg:city":"Brogo",
    "sg:classifiers":[
        {
            "category":"Retail",
            "subcategory":"Repair Shop",
            "type":"Services"
        }
    ],
    "sg:phone":"+61 2 6492 7319",
    "sg:postcode":"2550",
    "sg:province":"NSW",
    "sg:tags":[
        "stove",
        "part",
        "range"
    ],
    "wof:name":"Tony Gray Wood Stove Repairs",
    "wof:placetype":"venue"
},
  "geometry": {"coordinates":[149.81939697300001,-36.5334854126],"type":"Point"}
}