{
  "type": "Feature",
  "properties": {
    "iso:country":"AU",
    "sg:address":"203 Charles St",
    "sg:city":"Launceston",
    "sg:classifiers":[
        {
            "category":"Restaurant",
            "type":"Food & Drink"
        }
    ],
    "sg:phone":"+61 3 6331 9448",
    "sg:postcode":"7250",
    "sg:province":"TAS",
    "wof:name":"Canton Restaurant",
    "wof:placetype":"venue"
},
  "geometry": {"coordinates":[147.13937377900001,-41.4400062561],"type":"Point"}
}