{
  "type": "Feature",
  "properties": {
    "addr:full":"Woodland Ave St Marys NSW 2760",
    "addr:postcode":"2760",
    "addr:street":"Woodland Ave",
    "iso:country":"AU",
    "sg:address":"Woodland Ave",
    "sg:city":"St Marys",
    "sg:classifiers":[
        {
            "category":"Arts & Performance",
            "subcategory":"Dance",
            "type":"Entertainment"
        }
    ],
    "sg:phone":"+61 2 4727 7319",
    "sg:postcode":"2760",
    "sg:province":"NSW",
    "sg:tags":[
        "theatrical",
        "ballet",
        "tuition"
    ],
    "wof:name":"St Marys Dance Centre",
    "wof:placetype":"venue"
},
  "geometry": {"coordinates":[150.79351806599999,-33.7718734741],"type":"Point"}
}