{
  "type": "Feature",
  "properties": {
    "addr:full":"13 Smith St Alice Springs NT 0870",
    "addr:housenumber":"13",
    "addr:postcode":"nt 0870",
    "addr:street":"Smith St",
    "iso:country":"AU",
    "sg:address":"13 Smith St",
    "sg:city":"Alice Springs",
    "sg:classifiers":[
        {
            "category":"Autos & Motor Vehicles",
            "subcategory":"Automobile Sales",
            "type":"Retail Goods"
        }
    ],
    "sg:phone":"+61 8 8952 1334",
    "sg:postcode":"0870",
    "sg:province":"NT",
    "sg:tags":[
        "car",
        "new"
    ],
    "wof:name":"Subaru",
    "wof:placetype":"venue"
},
  "geometry": {"coordinates":[133.874633789,-23.693277359],"type":"Point"}
}