{
  "type": "Feature",
  "properties": {
    "addr:full":"23 Griffiths St Bacchus Marsh VIC 3340",
    "addr:housenumber":"23",
    "addr:postcode":"3340",
    "addr:street":"Griffiths St",
    "iso:country":"AU",
    "sg:address":"23 Griffiths St",
    "sg:city":"Bacchus Marsh",
    "sg:classifiers":[
        {
            "category":"Retail",
            "subcategory":"Auto Repair",
            "type":"Services"
        }
    ],
    "sg:phone":"+61 3 5367 2041",
    "sg:postcode":"3340",
    "sg:province":"VIC",
    "sg:tags":[
        "repairer",
        "motor",
        "engineer"
    ],
    "wof:name":"Autowell",
    "wof:placetype":"venue"
},
  "geometry": {"coordinates":[144.42529300000001,-37.686302],"type":"Point"}
}