{
  "type": "Feature",
  "properties": {
    "addr:full":"10 Lamrock Ave Bondi Beach NSW 2026",
    "addr:housenumber":"10",
    "addr:postcode":"2026",
    "addr:street":"Lamrock Ave",
    "iso:country":"AU",
    "sg:address":"10 Lamrock Ave",
    "sg:city":"Bondi Beach",
    "sg:classifiers":[
        {
            "category":"Cafe",
            "type":"Food & Drink"
        }
    ],
    "sg:phone":"+61 2 9300 0149",
    "sg:postcode":"2026",
    "sg:province":"NSW",
    "wof:name":"Baristas Coffee",
    "wof:placetype":"venue"
},
  "geometry": {"coordinates":[151.27273559599999,-33.8925247192],"type":"Point"}
}