{
  "type": "Feature",
  "properties": {
    "addr:full":"Marine Pde Hastings VIC 3915",
    "addr:postcode":"3915",
    "addr:street":"Marine",
    "iso:country":"AU",
    "sg:address":"Marine Pde",
    "sg:city":"Hastings",
    "sg:classifiers":[
        {
            "category":"Sports & Exercise",
            "subcategory":"Gym",
            "type":"Entertainment"
        }
    ],
    "sg:phone":"+61 1300 850 197",
    "sg:postcode":"3915",
    "sg:province":"VIC",
    "sg:tags":[
        "health",
        "fitness"
    ],
    "wof:name":"Pelican Park Recreation Centre",
    "wof:placetype":"venue"
},
  "geometry": {"coordinates":[145.19418335,-38.3070297241],"type":"Point"}
}