{
  "type": "Feature",
  "properties": {
    "addr:full":"8 Bogan Rd Hillbank SA 5112",
    "addr:housenumber":"8",
    "addr:postcode":"5112",
    "addr:street":"Bogan Rd",
    "iso:country":"AU",
    "sg:address":"8 Bogan Rd",
    "sg:city":"Hillbank",
    "sg:classifiers":[
        {
            "category":"Food & Beverages",
            "subcategory":"Liquor & Beverages",
            "type":"Retail Goods"
        }
    ],
    "sg:phone":"+61 8 8252 3726",
    "sg:postcode":"5112",
    "sg:province":"SA",
    "sg:tags":[
        "store"
    ],
    "wof:name":"Hillbank Liquor",
    "wof:placetype":"venue"
},
  "geometry": {"coordinates":[138.67971801799999,-34.7393836975],"type":"Point"}
}