{
  "type": "Feature",
  "properties": {
    "addr:full":"Unit 1/ 6 Kirke St Balcatta WA 6021",
    "addr:housenumber":"6",
    "addr:postcode":"6021",
    "addr:street":"Kirke St",
    "iso:country":"AU",
    "sg:address":"Unit 1/ 6 Kirke St",
    "sg:city":"Balcatta",
    "sg:classifiers":[
        {
            "category":"Wholesale",
            "subcategory":"Home Furnishings",
            "type":"Manufacturing & Wholesale Goods"
        }
    ],
    "sg:phone":"+61 8 9240 5966",
    "sg:postcode":"6021",
    "sg:province":"WA",
    "sg:tags":[
        "wholesaler",
        "curtain",
        "mfrs"
    ],
    "wof:name":"Window Witchery",
    "wof:placetype":"venue"
},
  "geometry": {"coordinates":[115.82305145300001,-31.8601913452],"type":"Point"}
}