{
  "type": "Feature",
  "properties": {
    "addr:full":"Old Pacific Hwy Mullaway NSW 2456",
    "addr:postcode":"2456",
    "addr:street":"Pacific Hwy",
    "iso:country":"AU",
    "sg:address":"Old Pacific Hwy",
    "sg:city":"Mullaway",
    "sg:classifiers":[
        {
            "category":"Education",
            "subcategory":"School",
            "type":"Public Place"
        }
    ],
    "sg:phone":"+61 2 6654 0377",
    "sg:postcode":"2456",
    "sg:province":"NSW",
    "sg:tags":[
        "state",
        "-",
        "nsw"
    ],
    "wof:name":"Mullaway Public School",
    "wof:placetype":"venue"
},
  "geometry": {"coordinates":[153.187927,-30.088493],"type":"Point"}
}