{
  "type": "Feature",
  "properties": {
    "iso:country":"AU",
    "sg:address":"Shop 6 / 102 Eighth St",
    "sg:city":"Mildura",
    "sg:classifiers":[
        {
            "category":"Professional",
            "subcategory":"Accounting & Tax Preparation",
            "type":"Services"
        }
    ],
    "sg:phone":"+61 3 5022 0488",
    "sg:postcode":"3500",
    "sg:province":"VIC",
    "sg:tags":[
        "bookkeeping"
    ],
    "wof:name":"ABC Training & Business Services",
    "wof:placetype":"venue"
},
  "geometry": {"coordinates":[142.16485595699999,-34.1886901855],"type":"Point"}
}