{
  "type": "Feature",
  "properties": {
    "iso:country":"AU",
    "sg:address":"22 Pearce St",
    "sg:city":"Warragul",
    "sg:classifiers":[
        {
            "category":"Transit Center",
            "subcategory":"Passenger",
            "type":"Transportation"
        }
    ],
    "sg:phone":"+61 3 5622 2441",
    "sg:postcode":"3820",
    "sg:province":"VIC",
    "sg:tags":[
        "wood",
        "moulding",
        "plastic"
    ],
    "wof:name":"Nyora Tool & Dye Pty Ltd",
    "wof:placetype":"venue"
},
  "geometry": {"coordinates":[145.93757600000001,-38.163418],"type":"Point"}
}