{
  "type": "Feature",
  "properties": {
    "iso:country":"AU",
    "sg:address":"Unit 3/ 121 Kurrajong Rd",
    "sg:city":"St Marys",
    "sg:classifiers":[
        {
            "category":"Retail",
            "subcategory":"Auto Repair",
            "type":"Services"
        }
    ],
    "sg:phone":"+61 2 9833 2646",
    "sg:postcode":"2760",
    "sg:province":"NSW",
    "sg:tags":[
        "repairer",
        "motor",
        "engineer"
    ],
    "wof:name":"West Star Autos",
    "wof:placetype":"venue"
},
  "geometry": {"coordinates":[150.80305480999999,-33.7630348206],"type":"Point"}
}