{
  "type": "Feature",
  "properties": {
    "addr:full":"Albany Hwy Tenterden WA 6322",
    "addr:postcode":"6322",
    "addr:street":"Albany Hwy",
    "iso:country":"AU",
    "sg:address":"Albany Hwy",
    "sg:city":"Tenterden",
    "sg:classifiers":[
        {
            "category":"Home & Garden",
            "subcategory":"Garden Supply",
            "type":"Retail Goods"
        }
    ],
    "sg:phone":"+61 8 9851 7218",
    "sg:postcode":"6322",
    "sg:province":"WA",
    "sg:tags":[
        "fertilizer"
    ],
    "wof:name":"Stirling Bulk Distributors",
    "wof:placetype":"venue"
},
  "geometry": {"coordinates":[117.5520401,-34.382598877],"type":"Point"}
}