{
  "type": "Feature",
  "properties": {
    "addr:full":"Pacific Hwy Bangalow NSW 2479",
    "addr:postcode":"2479",
    "addr:street":"Pacific Hwy",
    "iso:country":"AU",
    "sg:address":"Pacific Hwy",
    "sg:city":"Bangalow",
    "sg:classifiers":[
        {
            "category":"Autos & Motor Vehicles",
            "subcategory":"Fuel & Gas Station",
            "type":"Retail Goods"
        }
    ],
    "sg:phone":"+61 2 6687 1022",
    "sg:postcode":"2479",
    "sg:province":"NSW",
    "wof:name":"BP Australia Limited",
    "wof:placetype":"venue"
},
  "geometry": {"coordinates":[153.53009033199999,-28.6789588928],"type":"Point"}
}