{
  "type": "Feature",
  "properties": {
    "addr:full":"397 Bong Bong St Bowral NSW 2576",
    "addr:housenumber":"397",
    "addr:postcode":"2576",
    "addr:street":"Bong Bong St",
    "iso:country":"AU",
    "sg:address":"397 Bong Bong St",
    "sg:city":"Bowral",
    "sg:classifiers":[
        {
            "category":"Shopping",
            "subcategory":"Optical Goods",
            "type":"Retail Goods"
        }
    ],
    "sg:phone":"+61 2 4862 2177",
    "sg:postcode":"2576",
    "sg:province":"NSW",
    "sg:tags":[
        "dispenser",
        "prescription"
    ],
    "wof:name":"Highlands Optical Services Pty Ltd",
    "wof:placetype":"venue"
},
  "geometry": {"coordinates":[150.417068481,-34.4819374084],"type":"Point"}
}