{
  "type": "Feature",
  "properties": {
    "addr:full":"PO Box 200 Wingham NSW 2429",
    "addr:postcode":"2429",
    "iso:country":"AU",
    "sg:address":"PO Box 200",
    "sg:city":"Wingham",
    "sg:classifiers":[
        {
            "category":"Commercial Area",
            "type":"Public Place"
        }
    ],
    "sg:phone":"+61 418 401 939",
    "sg:postcode":"2429",
    "sg:province":"NSW",
    "sg:tags":[
        "heavy",
        "carrier"
    ],
    "wof:name":"Manning Valley Transport",
    "wof:placetype":"venue"
},
  "geometry": {"coordinates":[152.36668399999999,-31.869881],"type":"Point"}
}