{
  "type": "Feature",
  "properties": {
    "addr:full":"Unit 5, 352 Macaulay Rd Kensington VIC 3031",
    "addr:housenumber":"352",
    "addr:postcode":"3031",
    "addr:street":"Macaulay Rd",
    "iso:country":"AU",
    "sg:address":"Unit 5, 352 Macaulay Rd",
    "sg:city":"Kensington",
    "sg:classifiers":[
        {
            "category":"Professional",
            "subcategory":"Research",
            "type":"Services"
        }
    ],
    "sg:phone":"+61 3 8371 7600",
    "sg:postcode":"3031",
    "sg:province":"VIC",
    "sg:tags":[
        "analyst"
    ],
    "wof:name":"Dairy Technical Services Limited",
    "wof:placetype":"venue"
},
  "geometry": {"coordinates":[144.933426,-37.794636],"type":"Point"}
}