{
  "type": "Feature",
  "properties": {
    "addr:full":"1/1- 7 Lagoon St Narrabeen NSW 2101",
    "addr:housenumber":"/ 1 7",
    "addr:postcode":"2101",
    "addr:street":"Lagoon St",
    "iso:country":"AU",
    "sg:address":"1/1- 7 Lagoon St",
    "sg:city":"Narrabeen",
    "sg:classifiers":[
        {
            "category":"Real Estate",
            "subcategory":"Real Estate Agent",
            "type":"Services"
        }
    ],
    "sg:phone":"+61 2 9913 3300",
    "sg:postcode":"2101",
    "sg:province":"NSW",
    "wof:name":"LJ Hooker Narrabeen",
    "wof:placetype":"venue"
},
  "geometry": {"coordinates":[151.29826399999999,-33.713741],"type":"Point"}
}