{
  "type": "Feature",
  "properties": {
    "addr:full":"20 Nelson St Fairfield NSW 2165",
    "addr:housenumber":"20",
    "addr:postcode":"2165",
    "addr:street":"Nelson St",
    "iso:country":"AU",
    "sg:address":"20 Nelson St",
    "sg:city":"Fairfield",
    "sg:classifiers":[
        {
            "category":"Professional",
            "subcategory":"Business Services",
            "type":"Services"
        }
    ],
    "sg:phone":"+61 2 9823 7787",
    "sg:postcode":"2165",
    "sg:province":"NSW",
    "sg:tags":[
        "drafting"
    ],
    "wof:name":"Fairfield Arc Draft",
    "wof:placetype":"venue"
},
  "geometry": {"coordinates":[150.95512390100001,-33.8685760498],"type":"Point"}
}