{
  "type": "Feature",
  "properties": {
    "addr:full":"Shop 1 The Town Centre Cnr Main Western Rd & Griffith St North Tamborine QLD 4272",
    "addr:housenumber":"shop 1",
    "addr:postcode":"4272",
    "addr:street":"The Town;Cnr Main Western Rd & Griffith St North",
    "iso:country":"AU",
    "sg:address":"Shop 1 The Town Centre Cnr Main Western Rd & Griffith St",
    "sg:city":"North Tamborine",
    "sg:classifiers":[
        {
            "category":"Real Estate",
            "subcategory":"Real Estate Agent",
            "type":"Services"
        }
    ],
    "sg:phone":"+61 7 5545 0623",
    "sg:postcode":"4272",
    "sg:province":"QLD",
    "wof:name":"Professionals Tamborine Mountain Realty",
    "wof:placetype":"venue"
},
  "geometry": {"coordinates":[153.184417725,-27.9288063049],"type":"Point"}
}