{
  "type": "Feature",
  "properties": {
    "iso:country":"AU",
    "sg:address":"12 Wiggs Rd",
    "sg:city":"Riverwood",
    "sg:classifiers":[
        {
            "category":"Home & Garden",
            "subcategory":"Garden Supply",
            "type":"Retail Goods"
        }
    ],
    "sg:phone":"+61 2 9534 3344",
    "sg:postcode":"2210",
    "sg:province":"NSW",
    "sg:tags":[
        "equipment"
    ],
    "wof:name":"Kelso",
    "wof:placetype":"venue"
},
  "geometry": {"coordinates":[151.051407,-33.938854],"type":"Point"}
}