{
  "type": "Feature",
  "properties": {
    "addr:full":"Whitfords Ave Woodvale WA 6026",
    "addr:postcode":"6026",
    "addr:street":"Whitfords Ave",
    "iso:country":"AU",
    "sg:address":"Whitfords Ave",
    "sg:city":"Woodvale",
    "sg:classifiers":[
        {
            "category":"Health Services",
            "subcategory":"Doctor",
            "type":"Services"
        }
    ],
    "sg:phone":"+61 8 9309 4211",
    "sg:postcode":"6026",
    "sg:province":"WA",
    "sg:tags":[
        "medical",
        "practitioner"
    ],
    "wof:name":"Kelly Andreav Dr",
    "wof:placetype":"venue"
},
  "geometry": {"coordinates":[115.796607971,-31.8001594543],"type":"Point"}
}