{
  "type": "Feature",
  "properties": {
    "iso:country":"AU",
    "sg:address":"47 East Market St",
    "sg:city":"Richmond",
    "sg:classifiers":[
        {
            "category":"Health Services",
            "subcategory":"Doctor",
            "type":"Services"
        }
    ],
    "sg:phone":"+61 2 4588 5636",
    "sg:postcode":"2753",
    "sg:province":"NSW",
    "sg:tags":[
        "medical",
        "practitioner"
    ],
    "wof:name":"Raj Thandavan",
    "wof:placetype":"venue"
},
  "geometry": {"coordinates":[150.751052856,-33.6002693176],"type":"Point"}
}