{
  "type": "Feature",
  "properties": {
    "addr:full":"91 Ballantrae Drv St Andrews NSW 2566",
    "addr:housenumber":"91",
    "addr:postcode":"2566",
    "addr:street":"Ballantrae Drv",
    "iso:country":"AU",
    "sg:address":"91 Ballantrae Drv",
    "sg:city":"St Andrews",
    "sg:classifiers":[
        {
            "category":"Cafe",
            "type":"Food & Drink"
        }
    ],
    "sg:phone":"+61 2 9603 2697",
    "sg:postcode":"2566",
    "sg:province":"NSW",
    "wof:name":"St Andrews Cafe Bar",
    "wof:placetype":"venue"
},
  "geometry": {"coordinates":[150.832107544,-34.021396637],"type":"Point"}
}