{
  "type": "Feature",
  "properties": {
    "addr:full":"1 The Kingsway Cronulla NSW 2230",
    "addr:housenumber":"1",
    "addr:postcode":"2230",
    "addr:street":"The Kingsway",
    "iso:country":"AU",
    "sg:address":"1 The Kingsway",
    "sg:city":"Cronulla",
    "sg:classifiers":[
        {
            "category":"Travel",
            "subcategory":"Hotels & Motels",
            "type":"Entertainment"
        }
    ],
    "sg:phone":"+61 2 8536 3600",
    "sg:postcode":"2230",
    "sg:province":"NSW",
    "sg:tags":[
        "accommodation"
    ],
    "sg:website":"http://www.questapartments.com.au",
    "wof:name":"Quest Cronulla Beach",
    "wof:placetype":"venue"
},
  "geometry": {"coordinates":[151.15419006400001,-34.051410675],"type":"Point"}
}