{
  "type": "Feature",
  "properties": {
    "iso:country":"AU",
    "sg:address":"Cnr Nerang Rd & Bailey Crs",
    "sg:city":"Southport",
    "sg:classifiers":[
        {
            "category":"Retail",
            "subcategory":"Auto Repair",
            "type":"Services"
        }
    ],
    "sg:phone":"+61 7 5532 3555",
    "sg:postcode":"4215",
    "sg:province":"QLD",
    "sg:tags":[
        "clutch",
        "brake"
    ],
    "wof:name":"Gold Coast Brakes",
    "wof:placetype":"venue"
},
  "geometry": {"coordinates":[153.383270264,-27.9764709473],"type":"Point"}
}