{
  "type": "Feature",
  "properties": {
    "addr:full":"Cnr Caloundra & Trevally Crs Manly West QLD 4179",
    "addr:postcode":"4179",
    "addr:street":"Cnr;Crs",
    "iso:country":"AU",
    "sg:address":"Cnr Caloundra & Trevally Crs",
    "sg:city":"Manly West",
    "sg:classifiers":[
        {
            "category":"Food & Beverages",
            "subcategory":"Groceries & Convenience Stores",
            "type":"Retail Goods"
        }
    ],
    "sg:phone":"+61 7 3348 7166",
    "sg:postcode":"4179",
    "sg:province":"QLD",
    "wof:name":"Manly Heights Convenience Store",
    "wof:placetype":"venue"
},
  "geometry": {"coordinates":[153.170455933,-27.469461441],"type":"Point"}
}