{
  "type": "Feature",
  "properties": {
    "iso:country":"AU",
    "sg:address":"159- 163 Caulfield Ave",
    "sg:city":"Clarence Gardens",
    "sg:classifiers":[
        {
            "category":"Professional",
            "subcategory":"Engineering",
            "type":"Services"
        }
    ],
    "sg:phone":"+61 8 8293 1099",
    "sg:postcode":"5039",
    "sg:province":"SA",
    "sg:tags":[
        "engineer"
    ],
    "wof:name":"Contract Engineering SA Pty Ltd",
    "wof:placetype":"venue"
},
  "geometry": {"coordinates":[138.57395935100001,-34.9768333435],"type":"Point"}
}