{
  "type": "Feature",
  "properties": {
    "iso:country":"AU",
    "sg:address":"106 Dryandra Crt",
    "sg:city":"Thurgoona",
    "sg:classifiers":[
        {
            "category":"Personal",
            "type":"Services"
        }
    ],
    "sg:phone":"+61 2 6043 3301",
    "sg:postcode":"2640",
    "sg:province":"NSW",
    "sg:tags":[
        "reducing",
        "treatment",
        "weight"
    ],
    "wof:name":"Herbalife Australasia Pty Ltd",
    "wof:placetype":"venue"
},
  "geometry": {"coordinates":[146.97747802699999,-36.0531730652],"type":"Point"}
}