{
  "type": "Feature",
  "properties": {
    "iso:country":"AU",
    "sg:address":"50 Redland Bay Rd",
    "sg:city":"Capalaba",
    "sg:classifiers":[
        {
            "category":"Home & Garden",
            "subcategory":"Carpets & Floor Coverings",
            "type":"Retail Goods"
        }
    ],
    "sg:phone":"+61 7 3823 4111",
    "sg:postcode":"4157",
    "sg:province":"QLD",
    "sg:tags":[
        "tile",
        "wall"
    ],
    "wof:name":"Tile Wizards",
    "wof:placetype":"venue"
},
  "geometry": {"coordinates":[153.19500732399999,-27.5279693604],"type":"Point"}
}