{
  "type": "Feature",
  "properties": {
    "addr:full":"107 Ordish Rd Dandenong VIC 3175",
    "addr:housenumber":"107",
    "addr:postcode":"3175",
    "addr:street":"Ordish Rd",
    "iso:country":"AU",
    "sg:address":"107 Ordish Rd",
    "sg:city":"Dandenong",
    "sg:classifiers":[
        {
            "category":"Mining & Drilling",
            "type":"Manufacturing & Wholesale Goods"
        }
    ],
    "sg:phone":"+61 3 9706 5017",
    "sg:postcode":"3175",
    "sg:province":"VIC",
    "sg:tags":[
        "boring",
        "contractor"
    ],
    "wof:name":"Pile Driving Services",
    "wof:placetype":"venue"
},
  "geometry": {"coordinates":[145.19284057600001,-38.026424408],"type":"Point"}
}