{
  "type": "Feature",
  "properties": {
    "addr:full":"274 Bunnerong Rd Hillsdale NSW 2036",
    "addr:housenumber":"274",
    "addr:postcode":"2036",
    "addr:street":"Bunnerong Rd",
    "iso:country":"AU",
    "sg:address":"274 Bunnerong Rd",
    "sg:city":"Hillsdale",
    "sg:classifiers":[
        {
            "category":"Social Services",
            "subcategory":"Adult Care",
            "type":"Services"
        }
    ],
    "sg:phone":"+61 419 700 024",
    "sg:postcode":"2036",
    "sg:province":"NSW",
    "sg:tags":[
        "towing"
    ],
    "wof:name":"Wilson Towing",
    "wof:placetype":"venue"
},
  "geometry": {"coordinates":[151.230194092,-33.9538154602],"type":"Point"}
}