{
  "type": "Feature",
  "properties": {
    "iso:country":"AU",
    "sg:address":"29 / 37 Wilkins Rd",
    "sg:city":"Gillman",
    "sg:classifiers":[
        {
            "category":"Real Estate",
            "subcategory":"Real Estate Agent",
            "type":"Services"
        }
    ],
    "sg:phone":"+61 8 8341 0013",
    "sg:postcode":"5013",
    "sg:province":"SA",
    "sg:tags":[
        "steel",
        "foundry",
        "iron"
    ],
    "wof:name":"Wheatley & Williams Pty Ltd",
    "wof:placetype":"venue"
},
  "geometry": {"coordinates":[138.533691406,-34.836555481],"type":"Point"}
}