{
  "type": "Feature",
  "properties": {
    "addr:full":"15 Anzac Crs Loxton SA 5333",
    "addr:housenumber":"15",
    "addr:postcode":"5333",
    "addr:street":"Anzac Crs",
    "iso:country":"AU",
    "sg:address":"15 Anzac Crs",
    "sg:city":"Loxton",
    "sg:classifiers":[
        {
            "category":"Deli",
            "type":"Food & Drink"
        }
    ],
    "sg:phone":"+61 8 8584 7748",
    "sg:postcode":"5333",
    "sg:province":"SA",
    "sg:tags":[
        "delicatessen"
    ],
    "wof:name":"Loxton Mini Mart",
    "wof:placetype":"venue"
},
  "geometry": {"coordinates":[140.57780456500001,-34.4486694336],"type":"Point"}
}