{
  "type": "Feature",
  "properties": {
    "addr:full":"Discovery Ave Willmot NSW 2770",
    "addr:postcode":"2770",
    "addr:street":"Discovery Ave",
    "iso:country":"AU",
    "sg:address":"Discovery Ave",
    "sg:city":"Willmot",
    "sg:classifiers":[
        {
            "category":"Social Services",
            "subcategory":"Child Care",
            "type":"Services"
        }
    ],
    "sg:phone":"+61 2 9626 0798",
    "sg:postcode":"2770",
    "sg:province":"NSW",
    "sg:tags":[
        "support",
        "health"
    ],
    "wof:name":"Early Childhood Health Centres",
    "wof:placetype":"venue"
},
  "geometry": {"coordinates":[150.79066467300001,-33.7244682312],"type":"Point"}
}