{
  "type": "Feature",
  "properties": {
    "addr:full":"54 Pendlebury Rd Cardiff NSW 2285",
    "addr:housenumber":"54",
    "addr:postcode":"2285",
    "addr:street":"Pendlebury Rd",
    "iso:country":"AU",
    "sg:address":"54 Pendlebury Rd",
    "sg:city":"Cardiff",
    "sg:classifiers":[
        {
            "category":"Home & Garden",
            "subcategory":"Building Materials",
            "type":"Retail Goods"
        }
    ],
    "sg:phone":"+61 1800 666 437",
    "sg:postcode":"2285",
    "sg:province":"NSW",
    "sg:tags":[
        "tile",
        "roofing"
    ],
    "wof:name":"Monier Wunderlich",
    "wof:placetype":"venue"
},
  "geometry": {"coordinates":[151.65293884299999,-32.9403190613],"type":"Point"}
}