{
  "type": "Feature",
  "properties": {
    "iso:country":"AU",
    "sg:address":"2/ 11 Denninup Way",
    "sg:city":"Malaga",
    "sg:classifiers":[
        {
            "category":"Home & Garden",
            "subcategory":"Hardware",
            "type":"Retail Goods"
        }
    ],
    "sg:phone":"+61 1800 558 258",
    "sg:postcode":"6090",
    "sg:province":"WA",
    "sg:tags":[
        "woodworking",
        "machinery"
    ],
    "wof:name":"Altendorf Australia",
    "wof:placetype":"venue"
},
  "geometry": {"coordinates":[115.887840271,-31.8522586823],"type":"Point"}
}