{
  "type": "Feature",
  "properties": {
    "addr:full":"198 Coogee Bay Rd Coogee NSW 2034",
    "addr:housenumber":"198",
    "addr:postcode":"2034",
    "addr:street":"Coogee Bay Rd",
    "iso:country":"AU",
    "sg:address":"198 Coogee Bay Rd",
    "sg:city":"Coogee",
    "sg:classifiers":[
        {
            "category":"Health Services",
            "subcategory":"Health Practitioner",
            "type":"Services"
        }
    ],
    "sg:phone":"+61 2 9664 9998",
    "sg:postcode":"2034",
    "sg:province":"NSW",
    "sg:tags":[
        "acupuncture"
    ],
    "wof:name":"Coogee Medical & Acupuncture Practice",
    "wof:placetype":"venue"
},
  "geometry": {"coordinates":[151.25457763700001,-33.9203262329],"type":"Point"}
}