{
  "type": "Feature",
  "properties": {
    "addr:full":"Tara Hills Rd Mossman QLD 4873",
    "addr:postcode":"4873",
    "addr:street":"Hills Rd",
    "iso:country":"AU",
    "sg:address":"Tara Hills Rd",
    "sg:city":"Mossman",
    "sg:classifiers":[
        {
            "category":"Farming",
            "subcategory":"Farm",
            "type":"Manufacturing & Wholesale Goods"
        }
    ],
    "sg:phone":"+61 7 4098 1285",
    "sg:postcode":"4873",
    "sg:province":"QLD",
    "sg:tags":[
        "farmer"
    ],
    "wof:name":"Brie Brie Estates Pty Ltd",
    "wof:placetype":"venue"
},
  "geometry": {"coordinates":[145.35218810999999,-16.4784240723],"type":"Point"}
}