{
  "type": "Feature",
  "properties": {
    "addr:full":"Shop 1, 71 Edgeworth David Ave Hornsby NSW 2077",
    "addr:housenumber":"shop;71",
    "addr:postcode":"2077",
    "addr:street":"Edgeworth David Ave",
    "iso:country":"AU",
    "sg:address":"Shop 1, 71 Edgeworth David Ave",
    "sg:city":"Hornsby",
    "sg:classifiers":[
        {
            "category":"Building & Trades",
            "subcategory":"Landscaping Services",
            "type":"Services"
        }
    ],
    "sg:phone":"+61 2 9487 7770",
    "sg:postcode":"2077",
    "sg:province":"NSW",
    "sg:tags":[
        "designer",
        "landscape",
        "contractor"
    ],
    "wof:name":"Acclaimed Landscape Lighting",
    "wof:placetype":"venue"
},
  "geometry": {"coordinates":[151.10406494099999,-33.7061920166],"type":"Point"}
}