{
  "type": "Feature",
  "properties": {
    "addr:full":"Cnr Michael & Bulwer Sts Maitland NSW 2320",
    "addr:postcode":"2320",
    "addr:street":"Sts",
    "iso:country":"AU",
    "sg:address":"Cnr Michael & Bulwer Sts",
    "sg:city":"Maitland",
    "sg:classifiers":[
        {
            "category":"Food & Beverages",
            "subcategory":"Supermarket",
            "type":"Retail Goods"
        }
    ],
    "sg:phone":"+61 2 4934 7344",
    "sg:postcode":"2320",
    "sg:province":"NSW",
    "sg:tags":[
        "grocery",
        "store"
    ],
    "wof:name":"Bi-Lo Pty Limited",
    "wof:placetype":"venue"
},
  "geometry": {"coordinates":[151.570114136,-32.7078857422],"type":"Point"}
}