{
  "type": "Feature",
  "properties": {
    "addr:full":"Unit 10 B/ 354 Brisbane Rd Arundel QLD 4214",
    "addr:housenumber":"/ 354",
    "addr:postcode":"4214",
    "addr:street":"B;Brisbane Rd",
    "iso:country":"AU",
    "sg:address":"Unit 10 B/ 354 Brisbane Rd",
    "sg:city":"Arundel",
    "sg:classifiers":[
        {
            "category":"Recreation",
            "subcategory":"Boat Charter",
            "type":"Entertainment"
        }
    ],
    "sg:phone":"+61 7 5594 9444",
    "sg:postcode":"4214",
    "sg:province":"QLD",
    "sg:tags":[
        "canopy",
        "motor"
    ],
    "wof:name":"Bayline Marine Covers",
    "wof:placetype":"venue"
},
  "geometry": {"coordinates":[153.37307739299999,-27.9311580658],"type":"Point"}
}