{
  "type": "Feature",
  "properties": {
    "iso:country":"AU",
    "sg:address":"134 Federation Ave",
    "sg:city":"Corowa",
    "sg:classifiers":[
        {
            "category":"Building & Trades",
            "subcategory":"Construction",
            "type":"Services"
        }
    ],
    "sg:phone":"+61 2 6033 1844",
    "sg:postcode":"2646",
    "sg:province":"NSW",
    "sg:tags":[
        "earth",
        "excavating",
        "moving",
        "contractor"
    ],
    "wof:name":"Upton Engineering Pty Ltd",
    "wof:placetype":"venue"
},
  "geometry": {"coordinates":[146.381149292,-36.0054168701],"type":"Point"}
}