{
  "type": "Feature",
  "properties": {
    "iso:country":"AU",
    "sg:address":"53 / 2 Railway Pde",
    "sg:city":"Lidcombe",
    "sg:classifiers":[
        {
            "category":"Professional",
            "type":"Services"
        }
    ],
    "sg:phone":"+61 2 9643 1155",
    "sg:postcode":"2141",
    "sg:province":"NSW",
    "sg:tags":[
        "shop",
        "fitting"
    ],
    "sg:website":"http://www.alantek.com.au",
    "wof:name":"Alantek",
    "wof:placetype":"venue"
},
  "geometry": {"coordinates":[151.03871154800001,-33.8579216003],"type":"Point"}
}