{
  "type": "Feature",
  "properties": {
    "addr:full":"34 Weston St Naval Base WA 6165",
    "addr:housenumber":"34",
    "addr:postcode":"6165",
    "addr:street":"Weston St",
    "iso:country":"AU",
    "sg:address":"34 Weston St",
    "sg:city":"Naval Base",
    "sg:classifiers":[
        {
            "category":"Professional",
            "subcategory":"Engineering",
            "type":"Services"
        }
    ],
    "sg:phone":"+61 418 913 363",
    "sg:postcode":"6165",
    "sg:province":"WA",
    "sg:tags":[
        "engineer"
    ],
    "wof:name":"Regal Engineering",
    "wof:placetype":"venue"
},
  "geometry": {"coordinates":[115.783562,-32.203373],"type":"Point"}
}