{
  "type": "Feature",
  "properties": {
    "addr:full":"13a King William St Bayswater WA 6053",
    "addr:housenumber":"13a",
    "addr:postcode":"6053",
    "addr:street":"King William St",
    "iso:country":"AU",
    "sg:address":"13a King William St",
    "sg:city":"Bayswater",
    "sg:classifiers":[
        {
            "category":"Real Estate",
            "subcategory":"Real Estate Agent",
            "type":"Services"
        }
    ],
    "sg:phone":"+61 8 9271 6900",
    "sg:postcode":"6053",
    "sg:province":"WA",
    "wof:name":"Bob Biggs Real Estate",
    "wof:placetype":"venue"
},
  "geometry": {"coordinates":[115.912696838,-31.9192943573],"type":"Point"}
}