{
  "type": "Feature",
  "properties": {
    "addr:full":"206 Ables Bay Rd Cygnet TAS 7112",
    "addr:housenumber":"206",
    "addr:postcode":"7112",
    "addr:street":"Ables Bay Rd",
    "iso:country":"AU",
    "sg:address":"206 Ables Bay Rd",
    "sg:city":"Cygnet",
    "sg:classifiers":[
        {
            "category":"Government",
            "subcategory":"Post Office",
            "type":"Public Place"
        }
    ],
    "sg:phone":"+61 400 993 024",
    "sg:postcode":"7112",
    "sg:province":"TAS",
    "sg:tags":[
        "yoga"
    ],
    "wof:name":"Niche-Southern Tasmanian Yoga Retreat Centre",
    "wof:placetype":"venue"
},
  "geometry": {"coordinates":[147.098709106,-43.2158126831],"type":"Point"}
}