{
  "type": "Feature",
  "properties": {
    "iso:country":"AU",
    "sg:address":"Shop 3 Wonthella Shopping Complex, Fifth St, Wonthella",
    "sg:city":"Geraldton",
    "sg:classifiers":[
        {
            "category":"Personal",
            "subcategory":"Beauty Salon",
            "type":"Services"
        }
    ],
    "sg:phone":"+61 8 9921 5544",
    "sg:postcode":"6530",
    "sg:province":"WA",
    "sg:tags":[
        "hairdresser"
    ],
    "wof:name":"Total Edge 4 Hair",
    "wof:placetype":"venue"
},
  "geometry": {"coordinates":[114.626289368,-28.7649402618],"type":"Point"}
}