{
  "type": "Feature",
  "properties": {
    "addr:full":"Shp 1/ 2 Cunningham St Moorebank NSW 2170",
    "addr:housenumber":"/ 2",
    "addr:postcode":"2170",
    "addr:street":"Cunningham St",
    "iso:country":"AU",
    "sg:address":"Shp 1/ 2 Cunningham St",
    "sg:city":"Moorebank",
    "sg:classifiers":[
        {
            "category":"Cafe",
            "type":"Food & Drink"
        }
    ],
    "sg:phone":"+61 2 9822 8831",
    "sg:postcode":"2170",
    "sg:province":"NSW",
    "wof:name":"Cosmos Moorebank Cafe",
    "wof:placetype":"venue"
},
  "geometry": {"coordinates":[150.93861389200001,-33.9346199036],"type":"Point"}
}