{
  "type": "Feature",
  "properties": {
    "addr:full":"Shop 4/ 967 Point Nepean Rd Rosebud VIC 3939",
    "addr:housenumber":"shop 4 / 967",
    "addr:postcode":"3939",
    "addr:street":"Nepean Rd",
    "iso:country":"AU",
    "sg:address":"Shop 4/ 967 Point Nepean Rd",
    "sg:city":"Rosebud",
    "sg:classifiers":[
        {
            "category":"Fast Food",
            "type":"Food & Drink"
        }
    ],
    "sg:phone":"+61 3 5982 2575",
    "sg:postcode":"3939",
    "sg:province":"VIC",
    "sg:tags":[
        "away",
        "take"
    ],
    "wof:name":"Rosebud Seafoods",
    "wof:placetype":"venue"
},
  "geometry": {"coordinates":[144.908035278,-38.3550224304],"type":"Point"}
}