{
  "type": "Feature",
  "properties": {
    "addr:full":"Level 3, 88 Jephson St Toowong QLD 4066",
    "addr:housenumber":"88",
    "addr:postcode":"4066",
    "addr:street":"Jephson St",
    "iso:country":"AU",
    "sg:address":"Level 3, 88 Jephson St",
    "sg:city":"Toowong",
    "sg:classifiers":[
        {
            "category":"Government",
            "subcategory":"Customs House",
            "type":"Public Place"
        }
    ],
    "sg:phone":"+61 7 3721 7000",
    "sg:postcode":"4066",
    "sg:province":"QLD",
    "sg:tags":[
        "title",
        "management",
        "stratum"
    ],
    "sg:website":"http://www.bcssm.com.au",
    "wof:name":"BCS",
    "wof:placetype":"venue"
},
  "geometry": {"coordinates":[152.990356445,-27.4869384766],"type":"Point"}
}