{
  "type": "Feature",
  "properties": {
    "iso:country":"AU",
    "sg:address":"427 Princes Hwy",
    "sg:city":"Noble Park",
    "sg:classifiers":[
        {
            "category":"Fast Food",
            "type":"Food & Drink"
        }
    ],
    "sg:phone":"+61 3 9546 4108",
    "sg:postcode":"3174",
    "sg:province":"VIC",
    "sg:tags":[
        "away",
        "take"
    ],
    "wof:name":"Nancy's Place",
    "wof:placetype":"venue"
},
  "geometry": {"coordinates":[145.18482971200001,-37.9588432312],"type":"Point"}
}