{
  "type": "Feature",
  "properties": {
    "iso:country":"AU",
    "sg:address":"49 Towong St",
    "sg:city":"Tallangatta",
    "sg:classifiers":[
        {
            "category":"Personal",
            "subcategory":"Beauty Salon",
            "type":"Services"
        }
    ],
    "sg:phone":"+61 2 6071 2670",
    "sg:postcode":"3700",
    "sg:province":"VIC",
    "sg:tags":[
        "hairdresser"
    ],
    "wof:name":"Tallangatta Family Hair Care",
    "wof:placetype":"venue"
},
  "geometry": {"coordinates":[147.17805480999999,-36.21692276],"type":"Point"}
}