{
  "type": "Feature",
  "properties": {
    "addr:full":"54 Great Eastern Hwy West Kalgoorlie WA 6430",
    "addr:housenumber":"54",
    "addr:postcode":"6430",
    "addr:street":"Great Eastern Hwy West",
    "iso:country":"AU",
    "sg:address":"54 Great Eastern Hwy West",
    "sg:city":"Kalgoorlie",
    "sg:classifiers":[
        {
            "category":"Home & Garden",
            "subcategory":"Hardware",
            "type":"Retail Goods"
        }
    ],
    "sg:phone":"+61 8 9091 1887",
    "sg:postcode":"6430",
    "sg:province":"WA",
    "sg:tags":[
        "pumping",
        "contractor"
    ],
    "wof:name":"Powerwest",
    "wof:placetype":"venue"
},
  "geometry": {"coordinates":[121.438362122,-30.7766132355],"type":"Point"}
}