{
  "type": "Feature",
  "properties": {
    "addr:full":"Unit 1/ 14 Duffy Ave Thornleigh NSW 2120",
    "addr:housenumber":"14",
    "addr:postcode":"2120",
    "addr:street":"Duffy Ave",
    "iso:country":"AU",
    "sg:address":"Unit 1/ 14 Duffy Ave",
    "sg:city":"Thornleigh",
    "sg:classifiers":[
        {
            "category":"Retail",
            "subcategory":"Auto Repair",
            "type":"Services"
        }
    ],
    "sg:phone":"+61 2 9875 4953",
    "sg:postcode":"2120",
    "sg:province":"NSW",
    "sg:tags":[
        "repairer",
        "motor",
        "engineer"
    ],
    "wof:name":"N.A.S. Automotives",
    "wof:placetype":"venue"
},
  "geometry": {"coordinates":[151.08261108400001,-33.7251701355],"type":"Point"}
}