{
  "type": "Feature",
  "properties": {
    "addr:full":"43 Landsborough Ave Scarborough QLD 4020",
    "addr:housenumber":"43",
    "addr:postcode":"4020",
    "addr:street":"Landsborough Ave",
    "iso:country":"AU",
    "sg:address":"43 Landsborough Ave",
    "sg:city":"Scarborough",
    "sg:classifiers":[
        {
            "category":"Building & Trades",
            "subcategory":"Construction",
            "type":"Services"
        }
    ],
    "sg:phone":"+61 7 3880 1581",
    "sg:postcode":"4020",
    "sg:province":"QLD",
    "sg:tags":[
        "management"
    ],
    "wof:name":"Conomos D & A Dacon Project Management",
    "wof:placetype":"venue"
},
  "geometry": {"coordinates":[153.114349,-27.20438],"type":"Point"}
}