{
  "type": "Feature",
  "properties": {
    "iso:country":"AU",
    "sg:address":"Suite 4, 504 Lutwyche Rd",
    "sg:city":"Lutwyche",
    "sg:classifiers":[
        {
            "category":"Banks & Credit Unions",
            "subcategory":"Financial Services",
            "type":"Services"
        }
    ],
    "sg:phone":"+61 7 3857 8584",
    "sg:postcode":"4030",
    "sg:province":"QLD",
    "sg:tags":[
        "advisory",
        "planning",
        "retirement"
    ],
    "wof:name":"Allied Planning & Financial Services",
    "wof:placetype":"venue"
},
  "geometry": {"coordinates":[153.03349299999999,-27.422937],"type":"Point"}
}