{
  "type": "Feature",
  "properties": {
    "addr:full":"21 Norman St Port Pirie SA 5540",
    "addr:housenumber":"21",
    "addr:postcode":"5540",
    "addr:street":"Norman St",
    "iso:country":"AU",
    "sg:address":"21 Norman St",
    "sg:city":"Port Pirie",
    "sg:classifiers":[
        {
            "category":"Health Services",
            "subcategory":"Dentist",
            "type":"Services"
        }
    ],
    "sg:phone":"+61 8 8632 6499",
    "sg:postcode":"5540",
    "sg:province":"SA",
    "wof:name":"Salmon Richard",
    "wof:placetype":"venue"
},
  "geometry": {"coordinates":[138.00892639200001,-33.1795043945],"type":"Point"}
}