{
  "type": "Feature",
  "properties": {
    "addr:full":"43- 51 Cowper Wharf Rd Woolloomooloo NSW 2011",
    "addr:housenumber":"51",
    "addr:postcode":"2011",
    "addr:street":"Cowper Wharf Rd",
    "iso:country":"AU",
    "sg:address":"43- 51 Cowper Wharf Rd",
    "sg:city":"Woolloomooloo",
    "sg:classifiers":[
        {
            "category":"Arts & Performance",
            "subcategory":"Art Gallery",
            "type":"Entertainment"
        }
    ],
    "sg:phone":"+61 2 9368 1411",
    "sg:postcode":"2011",
    "sg:province":"NSW",
    "wof:name":"Biennale Of Sydney The",
    "wof:placetype":"venue"
},
  "geometry": {"coordinates":[151.22047424300001,-33.8694076538],"type":"Point"}
}