{
  "type": "Feature",
  "properties": {
    "addr:full":"624- 630 Dorset Rd Bayswater VIC 3153",
    "addr:housenumber":"630",
    "addr:postcode":"3153",
    "addr:street":"Dorset Rd",
    "iso:country":"AU",
    "sg:address":"624- 630 Dorset Rd",
    "sg:city":"Bayswater",
    "sg:classifiers":[
        {
            "category":"Autos & Motor Vehicles",
            "subcategory":"Automobile Sales",
            "type":"Retail Goods"
        }
    ],
    "sg:phone":"+61 3 9729 9670",
    "sg:postcode":"3153",
    "sg:province":"VIC",
    "sg:tags":[
        "car",
        "used"
    ],
    "wof:name":"Front City Car Sales",
    "wof:placetype":"venue"
},
  "geometry": {"coordinates":[145.28749084500001,-37.823764801],"type":"Point"}
}