{
  "type": "Feature",
  "properties": {
    "addr:full":"85 Chapman Ave Glenroy VIC 3046",
    "addr:housenumber":"85",
    "addr:postcode":"3046",
    "addr:street":"Chapman Ave",
    "iso:country":"AU",
    "sg:address":"85 Chapman Ave",
    "sg:city":"Glenroy",
    "sg:classifiers":[
        {
            "category":"Health Services",
            "subcategory":"Nursing And Care Facility",
            "type":"Services"
        }
    ],
    "sg:phone":"+61 3 9306 7766",
    "sg:postcode":"3046",
    "sg:province":"VIC",
    "sg:tags":[
        "home"
    ],
    "wof:name":"Glenroy Private Nursing Home",
    "wof:placetype":"venue"
},
  "geometry": {"coordinates":[144.9115448,-37.7058143616],"type":"Point"}
}