{
  "type": "Feature",
  "properties": {
    "addr:full":"Andrew House 1 Wickham Tce Brisbane QLD 4000",
    "addr:housenumber":"1",
    "addr:postcode":"4000",
    "addr:street":"Wickham Tce",
    "iso:country":"AU",
    "sg:address":"Andrew House 1 Wickham Tce",
    "sg:city":"Brisbane",
    "sg:classifiers":[
        {
            "category":"Banks & Credit Unions",
            "subcategory":"Financial Services",
            "type":"Services"
        }
    ],
    "sg:phone":"+61 7 3832 7011",
    "sg:postcode":"4000",
    "sg:province":"QLD",
    "sg:tags":[
        "planning"
    ],
    "wof:name":"Stockwell Michael",
    "wof:placetype":"venue"
},
  "geometry": {"coordinates":[153.02079773,-27.4644050598],"type":"Point"}
}