{
  "type": "Feature",
  "properties": {
    "iso:country":"AU",
    "sg:address":"Shop 3, Mortimer Centre",
    "sg:city":"Mudgee",
    "sg:classifiers":[
        {
            "category":"Building & Trades",
            "subcategory":"Pest Control",
            "type":"Services"
        }
    ],
    "sg:phone":"+61 2 6372 6423",
    "sg:postcode":"2850",
    "sg:province":"NSW",
    "wof:name":"Insectra Pest Management",
    "wof:placetype":"venue"
},
  "geometry": {"coordinates":[149.585617,-32.592827],"type":"Point"}
}