{
  "type": "Feature",
  "properties": {
    "iso:country":"AU",
    "sg:address":"93 Bass Hwy",
    "sg:city":"Somerset",
    "sg:classifiers":[
        {
            "category":"Autos & Motor Vehicles",
            "subcategory":"Fuel & Gas Station",
            "type":"Retail Goods"
        }
    ],
    "sg:phone":"+61 3 6435 1413",
    "sg:postcode":"7322",
    "sg:province":"TAS",
    "wof:name":"BP Australia Limited",
    "wof:placetype":"venue"
},
  "geometry": {"coordinates":[145.825684,-41.03614],"type":"Point"}
}