{
  "type": "Feature",
  "properties": {
    "iso:country":"AU",
    "sg:address":"Cnr Blackburn & Ferntree Gully Rds",
    "sg:city":"Mt Waverley",
    "sg:classifiers":[
        {
            "category":"Autos & Motor Vehicles",
            "subcategory":"Fuel & Gas Station",
            "type":"Retail Goods"
        }
    ],
    "sg:phone":"+61 3 9562 5070",
    "sg:postcode":"3149",
    "sg:province":"VIC",
    "wof:name":"Ampol Shop Stop Mt Waverley",
    "wof:placetype":"venue"
},
  "geometry": {"coordinates":[145.14268493599999,-37.9009208679],"type":"Point"}
}