{
  "type": "Feature",
  "properties": {
    "addr:full":"10 Newton St Broadmeadow NSW 2292",
    "addr:housenumber":"10",
    "addr:postcode":"2292",
    "addr:street":"Newton St",
    "iso:country":"AU",
    "sg:address":"10 Newton St",
    "sg:city":"Broadmeadow",
    "sg:classifiers":[
        {
            "category":"Manufacturing",
            "subcategory":"Electronics",
            "type":"Manufacturing & Wholesale Goods"
        }
    ],
    "sg:phone":"+61 2 4957 2480",
    "sg:postcode":"2292",
    "sg:province":"NSW",
    "sg:tags":[
        "wholesaler",
        "equipment",
        "part",
        "mfrs",
        "refrigeration"
    ],
    "wof:name":"Waterman Refrigeration",
    "wof:placetype":"venue"
},
  "geometry": {"coordinates":[151.724975586,-32.9246368408],"type":"Point"}
}