{
  "type": "Feature",
  "properties": {
    "addr:full":"70 Magellan St Lismore NSW 2480",
    "addr:housenumber":"70",
    "addr:postcode":"2480",
    "addr:street":"Magellan St",
    "iso:country":"AU",
    "sg:address":"70 Magellan St",
    "sg:city":"Lismore",
    "sg:classifiers":[
        {
            "category":"Shopping",
            "subcategory":"Computers & Home Electronics",
            "type":"Retail Goods"
        }
    ],
    "sg:phone":"+61 2 6621 9350",
    "sg:postcode":"2480",
    "sg:province":"NSW",
    "sg:tags":[
        "equipment",
        "part",
        "electronic"
    ],
    "wof:name":"Tandy",
    "wof:placetype":"venue"
},
  "geometry": {"coordinates":[153.27700805699999,-28.8092422485],"type":"Point"}
}