{
  "type": "Feature",
  "properties": {
    "iso:country":"AU",
    "sg:address":"12 Industrial Drv",
    "sg:city":"Coffs Harbour",
    "sg:classifiers":[
        {
            "category":"Building & Trades",
            "subcategory":"Construction",
            "type":"Services"
        }
    ],
    "sg:phone":"+61 2 6651 7223",
    "sg:postcode":"2450",
    "sg:province":"NSW",
    "sg:tags":[
        "contractor"
    ],
    "wof:name":"The Williams River Steel",
    "wof:placetype":"venue"
},
  "geometry": {"coordinates":[153.08764600000001,-30.313799],"type":"Point"}
}