{
  "type": "Feature",
  "properties": {
    "addr:full":"4 Queen St Burnie TAS 7320",
    "addr:housenumber":"4",
    "addr:postcode":"7320",
    "addr:street":"Queen St",
    "iso:country":"AU",
    "sg:address":"4 Queen St",
    "sg:city":"Burnie",
    "sg:classifiers":[
        {
            "category":"Health Services",
            "subcategory":"Chiropractor",
            "type":"Services"
        }
    ],
    "sg:phone":"+61 3 6431 9388",
    "sg:postcode":"7320",
    "sg:province":"TAS",
    "wof:name":"Springer Scott",
    "wof:placetype":"venue"
},
  "geometry": {"coordinates":[145.904785,-41.054146],"type":"Point"}
}