{
  "type": "Feature",
  "properties": {
    "addr:full":"Cnr Tuckers Rd & Burleigh Drv Templestowe VIC 3106",
    "addr:postcode":"3106",
    "addr:street":"Cnr Tuckers Rd & Burleigh Drv",
    "iso:country":"AU",
    "sg:address":"Cnr Tuckers Rd & Burleigh Drv",
    "sg:city":"Templestowe",
    "sg:classifiers":[
        {
            "category":"Health Services",
            "subcategory":"Dentist",
            "type":"Services"
        }
    ],
    "sg:phone":"+61 3 9841 0068",
    "sg:postcode":"3106",
    "sg:province":"VIC",
    "wof:name":"Singh Harpal",
    "wof:placetype":"venue"
},
  "geometry": {"coordinates":[145.156051636,-37.7684593201],"type":"Point"}
}