{
  "type": "Feature",
  "properties": {
    "iso:country":"AU",
    "sg:address":"53 East St",
    "sg:city":"Rockhampton City",
    "sg:classifiers":[
        {
            "category":"Personal",
            "subcategory":"Beauty Salon",
            "type":"Services"
        }
    ],
    "sg:phone":"+61 7 4927 5522",
    "sg:postcode":"4700",
    "sg:province":"QLD",
    "sg:tags":[
        "hairdresser"
    ],
    "wof:name":"Kerry's Barber Shop",
    "wof:placetype":"venue"
},
  "geometry": {"coordinates":[150.52114868199999,-23.3889350891],"type":"Point"}
}