{
  "type": "Feature",
  "properties": {
    "addr:full":"134 Mills St Altona North VIC 3025",
    "addr:housenumber":"134",
    "addr:postcode":"3025",
    "addr:street":"Mills St",
    "iso:country":"AU",
    "sg:address":"134 Mills St",
    "sg:city":"Altona North",
    "sg:classifiers":[
        {
            "category":"Home & Garden",
            "subcategory":"Carpets & Floor Coverings",
            "type":"Retail Goods"
        }
    ],
    "sg:phone":"+61 3 9327 2304",
    "sg:postcode":"3025",
    "sg:province":"VIC",
    "sg:tags":[
        "tile",
        "wall",
        "layer"
    ],
    "wof:name":"A & N Imperial Tiling Pty Ltd",
    "wof:placetype":"venue"
},
  "geometry": {"coordinates":[144.85549900000001,-37.835808],"type":"Point"}
}