{
  "type": "Feature",
  "properties": {
    "iso:country":"AU",
    "sg:address":"Hamilton St",
    "sg:city":"Finley",
    "sg:classifiers":[
        {
            "category":"Travel",
            "subcategory":"Hostel",
            "type":"Entertainment"
        }
    ],
    "sg:phone":"+61 3 5883 9623",
    "sg:postcode":"2713",
    "sg:province":"NSW",
    "sg:tags":[
        "home"
    ],
    "wof:name":"Ulupna Lodge Hostel",
    "wof:placetype":"venue"
},
  "geometry": {"coordinates":[145.56980895999999,-35.6345443726],"type":"Point"}
}