{
  "type": "Feature",
  "properties": {
    "addr:full":"Goonyella Rd Moranbah QLD 4744",
    "addr:postcode":"4744",
    "addr:street":"Goonyella Rd",
    "iso:country":"AU",
    "sg:address":"Goonyella Rd",
    "sg:city":"Moranbah",
    "sg:classifiers":[
        {
            "category":"Home & Garden",
            "subcategory":"Building Materials",
            "type":"Retail Goods"
        }
    ],
    "sg:phone":"+61 7 4941 7492",
    "sg:postcode":"4744",
    "sg:province":"QLD",
    "sg:tags":[
        "pre-mixed",
        "concrete"
    ],
    "wof:name":"Pioneer Construction Materials",
    "wof:placetype":"venue"
},
  "geometry": {"coordinates":[148.04006957999999,-22.0065631866],"type":"Point"}
}