{
  "type": "Feature",
  "properties": {
    "addr:full":"50 Morley St Coorparoo QLD 4151",
    "addr:housenumber":"50",
    "addr:postcode":"4151",
    "addr:street":"Morley St",
    "iso:country":"AU",
    "sg:address":"50 Morley St",
    "sg:city":"Coorparoo",
    "sg:classifiers":[
        {
            "category":"Mining & Drilling",
            "type":"Manufacturing & Wholesale Goods"
        }
    ],
    "sg:phone":"+61 7 3394 2724",
    "sg:postcode":"4151",
    "sg:province":"QLD",
    "sg:tags":[
        "concrete",
        "breaking",
        "grinding",
        "sawing"
    ],
    "wof:name":"Archquip",
    "wof:placetype":"venue"
},
  "geometry": {"coordinates":[153.052368164,-27.4918727875],"type":"Point"}
}