{
  "type": "Feature",
  "properties": {
    "addr:full":"24 Norton St Leichhardt NSW 2040",
    "addr:housenumber":"24",
    "addr:postcode":"2040",
    "addr:street":"Norton St",
    "iso:country":"AU",
    "sg:address":"24 Norton St",
    "sg:city":"Leichhardt",
    "sg:classifiers":[
        {
            "category":"Personal",
            "subcategory":"Massage",
            "type":"Services"
        }
    ],
    "sg:phone":"+61 2 9560 7624",
    "sg:postcode":"2040",
    "sg:province":"NSW",
    "sg:tags":[
        "therapy"
    ],
    "sg:website":"http://www.skintherapeia.com.au",
    "wof:name":"Skin Therapeia",
    "wof:placetype":"venue"
},
  "geometry": {"coordinates":[151.157364,-33.887112],"type":"Point"}
}