{
  "type": "Feature",
  "properties": {
    "addr:full":"4 School St Rushworth VIC 3612",
    "addr:housenumber":"4",
    "addr:postcode":"3612",
    "addr:street":"School St",
    "iso:country":"AU",
    "sg:address":"4 School St",
    "sg:city":"Rushworth",
    "sg:classifiers":[
        {
            "category":"Travel",
            "subcategory":"Hotels & Motels",
            "type":"Entertainment"
        }
    ],
    "sg:phone":"+61 3 5856 1090",
    "sg:postcode":"3612",
    "sg:province":"VIC",
    "wof:name":"Rushworth Motel",
    "wof:placetype":"venue"
},
  "geometry": {"coordinates":[145.01536560100001,-36.5848846436],"type":"Point"}
}