{
  "type": "Feature",
  "properties": {
    "iso:country":"AU",
    "sg:address":"110 Bayswater Rd",
    "sg:city":"(Cnr French St) Pimlico",
    "sg:phone":"+61 7 4725 6988",
    "sg:postcode":"4812",
    "sg:province":"QLD",
    "wof:name":"About Town Windscreen Repairs & Replacements",
    "wof:placetype":"venue"
},
  "geometry": {"coordinates":[146.790527,-19.276548],"type":"Point"}
}