{
  "type": "Feature",
  "properties": {
    "iso:country":"AU",
    "sg:address":"PO Box 2405",
    "sg:city":"North Parramatta",
    "sg:classifiers":[
        {
            "category":"Real Estate",
            "subcategory":"Real Estate Agent",
            "type":"Services"
        }
    ],
    "sg:phone":"+61 2 9630 1310",
    "sg:postcode":"1750",
    "sg:province":"NSW",
    "wof:name":"Griffin Developments Australia",
    "wof:placetype":"venue"
},
  "geometry": {"coordinates":[151.010712,-33.798038],"type":"Point"}
}