{
  "type": "Feature",
  "properties": {
    "addr:full":"64 Hampden Rd Battery Point TAS 7004",
    "addr:housenumber":"64",
    "addr:postcode":"7004",
    "addr:street":"Hampden Rd",
    "iso:country":"AU",
    "sg:address":"64 Hampden Rd",
    "sg:city":"Battery Point",
    "sg:classifiers":[
        {
            "category":"Real Estate",
            "subcategory":"Real Estate Agent",
            "type":"Services"
        }
    ],
    "sg:phone":"+61 408 125 422",
    "sg:postcode":"7004",
    "sg:province":"TAS",
    "wof:name":"Soundy John",
    "wof:placetype":"venue"
},
  "geometry": {"coordinates":[147.33375549300001,-42.8898429871],"type":"Point"}
}