{
  "type": "Feature",
  "properties": {
    "iso:country":"AU",
    "sg:address":"Shop 11, Centenary Marketplace McLaughlin Rd",
    "sg:city":"Edmonton",
    "sg:classifiers":[
        {
            "category":"Health Services",
            "subcategory":"Dentist",
            "type":"Services"
        }
    ],
    "sg:phone":"+61 7 4045 3845",
    "sg:postcode":"4869",
    "sg:province":"QLD",
    "wof:name":"Daly Simon",
    "wof:placetype":"venue"
},
  "geometry": {"coordinates":[145.736938477,-17.0120258331],"type":"Point"}
}