{
  "type": "Feature",
  "properties": {
    "addr:full":"65 Victoria St Nhill VIC 3418",
    "addr:housenumber":"65",
    "addr:postcode":"3418",
    "addr:street":"Victoria St",
    "iso:country":"AU",
    "sg:address":"65 Victoria St",
    "sg:city":"Nhill",
    "sg:classifiers":[
        {
            "category":"Retail",
            "subcategory":"Auto Repair",
            "type":"Services"
        }
    ],
    "sg:phone":"+61 3 5391 1515",
    "sg:postcode":"3418",
    "sg:province":"VIC",
    "sg:tags":[
        "repairer",
        "motor",
        "engineer"
    ],
    "wof:name":"G E MacKenzie Motors",
    "wof:placetype":"venue"
},
  "geometry": {"coordinates":[141.64747619600001,-36.3358192444],"type":"Point"}
}