{
  "type": "Feature",
  "properties": {
    "iso:country":"AU",
    "sg:address":"Shop 30",
    "sg:city":"-32 Nerang River Plaza Nerang",
    "sg:classifiers":[
        {
            "category":"Shopping",
            "subcategory":"Pawn Shop",
            "type":"Retail Goods"
        }
    ],
    "sg:phone":"+61 1300 302 274",
    "sg:postcode":"4211",
    "sg:province":"QLD",
    "sg:tags":[
        "pawnbroker"
    ],
    "wof:name":"Hinterland Cash Express",
    "wof:placetype":"venue"
},
  "geometry": {"coordinates":[153.33245849599999,-27.9961948395],"type":"Point"}
}