{
  "type": "Feature",
  "properties": {
    "iso:country":"AU",
    "sg:address":"\"Lyndhurst\" MS 335",
    "sg:city":"Jimbour",
    "sg:classifiers":[
        {
            "category":"Farming",
            "subcategory":"Farm",
            "type":"Manufacturing & Wholesale Goods"
        }
    ],
    "sg:phone":"+61 7 4663 5195",
    "sg:postcode":"4352",
    "sg:province":"QLD",
    "sg:tags":[
        "farmer"
    ],
    "wof:name":"Pallathorpe Enterprises Pty Ltd",
    "wof:placetype":"venue"
},
  "geometry": {"coordinates":[151.916946,-27.558603],"type":"Point"}
}