{
  "type": "Feature",
  "properties": {
    "addr:full":"41 Oswald St Kyabram VIC 3620",
    "addr:housenumber":"41",
    "addr:postcode":"3620",
    "addr:street":"Oswald St",
    "iso:country":"AU",
    "sg:address":"41 Oswald St",
    "sg:city":"Kyabram",
    "sg:classifiers":[
        {
            "category":"Health Services",
            "subcategory":"Dentist",
            "type":"Services"
        }
    ],
    "sg:phone":"+61 3 5852 2670",
    "sg:postcode":"3620",
    "sg:province":"VIC",
    "sg:tags":[
        "dental",
        "prosthetist"
    ],
    "wof:name":"Roger S. Gilbert",
    "wof:placetype":"venue"
},
  "geometry": {"coordinates":[145.05357360799999,-36.3122520447],"type":"Point"}
}