{
  "type": "Feature",
  "properties": {
    "iso:country":"AU",
    "sg:address":"36 Dickson Ave",
    "sg:city":"Artarmon",
    "sg:classifiers":[
        {
            "category":"Shopping",
            "subcategory":"Computers & Home Electronics",
            "type":"Retail Goods"
        }
    ],
    "sg:phone":"+61 2 9436 1995",
    "sg:postcode":"2064",
    "sg:province":"NSW",
    "sg:tags":[
        "global",
        "positioning",
        "system"
    ],
    "wof:name":"Metrosound",
    "wof:placetype":"venue"
},
  "geometry": {"coordinates":[151.18446350100001,-33.8159332275],"type":"Point"}
}