{
  "type": "Feature",
  "properties": {
    "addr:full":"48 Norwood Rd Caulfield North VIC 3161",
    "addr:housenumber":"48",
    "addr:postcode":"3161",
    "addr:street":"Norwood Rd",
    "iso:country":"AU",
    "sg:address":"48 Norwood Rd",
    "sg:city":"Caulfield North",
    "sg:classifiers":[
        {
            "category":"Professional",
            "subcategory":"Testing Lab",
            "type":"Services"
        }
    ],
    "sg:phone":"+61 3 9527 7748",
    "sg:postcode":"3161",
    "sg:province":"VIC",
    "sg:tags":[
        "inspection"
    ],
    "wof:name":"All Tagged",
    "wof:placetype":"venue"
},
  "geometry": {"coordinates":[145.01435852,-37.8619422913],"type":"Point"}
}