{
  "type": "Feature",
  "properties": {
    "addr:full":"18 Elizabeth St Malvern VIC 3144",
    "addr:housenumber":"18",
    "addr:postcode":"3144",
    "addr:street":"Elizabeth St",
    "iso:country":"AU",
    "sg:address":"18 Elizabeth St",
    "sg:city":"Malvern",
    "sg:classifiers":[
        {
            "category":"Personal",
            "subcategory":"Beauty Salon",
            "type":"Services"
        }
    ],
    "sg:phone":"+61 3 9822 6203",
    "sg:postcode":"3144",
    "sg:province":"VIC",
    "wof:name":"Femelle Beauty",
    "wof:placetype":"venue"
},
  "geometry": {"coordinates":[145.03616332999999,-37.8510856628],"type":"Point"}
}