{
  "type": "Feature",
  "properties": {
    "addr:full":"Southlands Shopping Centre Cnr Mawson Pl & Heard S Mawson ACT 2607",
    "addr:postcode":"2607",
    "addr:street":"Cnr Mawson Pl &;S",
    "iso:country":"AU",
    "sg:address":"Southlands Shopping Centre Cnr Mawson Pl & Heard S",
    "sg:city":"Mawson",
    "sg:classifiers":[
        {
            "category":"Health Services",
            "subcategory":"Doctor",
            "type":"Services"
        }
    ],
    "sg:phone":"+61 2 6290 0900",
    "sg:postcode":"2607",
    "sg:province":"ACT",
    "sg:tags":[
        "medical",
        "practitioner"
    ],
    "wof:name":"McDonald Brenda",
    "wof:placetype":"venue"
},
  "geometry": {"coordinates":[149.093826294,-35.3642425537],"type":"Point"}
}