{
  "type": "Feature",
  "properties": {
    "addr:full":"33 Gladstone St East Perth WA 6004",
    "addr:housenumber":"33",
    "addr:postcode":"6004",
    "addr:street":"Gladstone St East",
    "iso:country":"AU",
    "sg:address":"33 Gladstone St",
    "sg:city":"East Perth",
    "sg:classifiers":[
        {
            "category":"Professional",
            "subcategory":"Printing & Photocopies",
            "type":"Services"
        }
    ],
    "sg:phone":"+61 8 9227 6661",
    "sg:postcode":"6004",
    "sg:province":"WA",
    "sg:tags":[
        "rubber",
        "stamp",
        "metal"
    ],
    "wof:name":"WA Shoe Care Products",
    "wof:placetype":"venue"
},
  "geometry": {"coordinates":[115.871780395,-31.9473495483],"type":"Point"}
}