{
  "type": "Feature",
  "properties": {
    "iso:country":"AU",
    "sg:address":"65 Pendlebury Rd",
    "sg:city":"Cardiff",
    "sg:classifiers":[
        {
            "category":"Home & Garden",
            "subcategory":"Building Materials",
            "type":"Retail Goods"
        }
    ],
    "sg:phone":"+61 2 4940 3444",
    "sg:postcode":"2285",
    "sg:province":"NSW",
    "sg:tags":[
        "merchant",
        "glass",
        "glazier"
    ],
    "wof:name":"G. James Glass & Aluminium",
    "wof:placetype":"venue"
},
  "geometry": {"coordinates":[151.651855469,-32.9469299316],"type":"Point"}
}