{
  "type": "Feature",
  "properties": {
    "addr:full":"17 Lake Ave Ocean Grove VIC 3226",
    "addr:housenumber":"17",
    "addr:postcode":"3226",
    "addr:street":"Lake Ave",
    "iso:country":"AU",
    "sg:address":"17 Lake Ave",
    "sg:city":"Ocean Grove",
    "sg:classifiers":[
        {
            "category":"Travel",
            "subcategory":"Hotels & Motels",
            "type":"Entertainment"
        }
    ],
    "sg:phone":"+61 3 5256 1199",
    "sg:postcode":"3226",
    "sg:province":"VIC",
    "wof:name":"Ocean Grove Gardens Motel",
    "wof:placetype":"venue"
},
  "geometry": {"coordinates":[144.51033000000001,-38.258659],"type":"Point"}
}