{
  "type": "Feature",
  "properties": {
    "iso:country":"AU",
    "sg:address":"Shed 2 Corner of Nash & Kempster St",
    "sg:city":"Sandgate",
    "sg:classifiers":[
        {
            "category":"Professional",
            "subcategory":"Detective & Security Services",
            "type":"Services"
        }
    ],
    "sg:phone":"+61 7 3869 2522",
    "sg:postcode":"4017",
    "sg:province":"QLD",
    "sg:tags":[
        "equipment",
        "window",
        "doors"
    ],
    "wof:name":"L A Security",
    "wof:placetype":"venue"
},
  "geometry": {"coordinates":[153.06109619099999,-27.3202095032],"type":"Point"}
}