{
  "type": "Feature",
  "properties": {
    "addr:full":"27 Charles St Norwood SA 5067",
    "addr:housenumber":"27",
    "addr:postcode":"5067",
    "addr:street":"Charles St",
    "iso:country":"AU",
    "sg:address":"27 Charles St",
    "sg:city":"Norwood",
    "sg:classifiers":[
        {
            "category":"Health Services",
            "subcategory":"Chiropractor",
            "type":"Services"
        }
    ],
    "sg:phone":"+61 8 8364 0508",
    "sg:postcode":"5067",
    "sg:province":"SA",
    "wof:name":"Logan William Dr",
    "wof:placetype":"venue"
},
  "geometry": {"coordinates":[138.625534058,-34.9255714417],"type":"Point"}
}