{
  "type": "Feature",
  "properties": {
    "addr:full":"65 Beach Rd Coobowie SA 5583",
    "addr:housenumber":"65",
    "addr:postcode":"5583",
    "addr:street":"Beach Rd",
    "iso:country":"AU",
    "sg:address":"65 Beach Rd",
    "sg:city":"Coobowie",
    "sg:classifiers":[
        {
            "category":"Government",
            "subcategory":"Post Office",
            "type":"Public Place"
        }
    ],
    "sg:phone":"+61 8 8852 8090",
    "sg:postcode":"5583",
    "sg:province":"SA",
    "sg:tags":[
        "postal"
    ],
    "wof:name":"Australia Post",
    "wof:placetype":"venue"
},
  "geometry": {"coordinates":[137.73277282699999,-35.0438041687],"type":"Point"}
}