{
  "type": "Feature",
  "properties": {
    "addr:full":"4 Takalvan St Bundaberg QLD 4670",
    "addr:housenumber":"4",
    "addr:postcode":"4670",
    "addr:street":"Takalvan St",
    "iso:country":"AU",
    "sg:address":"4 Takalvan St",
    "sg:city":"Bundaberg",
    "sg:classifiers":[
        {
            "category":"Autos & Motor Vehicles",
            "subcategory":"Automobile Sales",
            "type":"Retail Goods"
        }
    ],
    "sg:phone":"+61 7 4150 7800",
    "sg:postcode":"4670",
    "sg:province":"QLD",
    "sg:tags":[
        "car",
        "used"
    ],
    "wof:name":"Bundaberg Toyota",
    "wof:placetype":"venue"
},
  "geometry": {"coordinates":[152.33709716800001,-24.8695602417],"type":"Point"}
}