{
  "type": "Feature",
  "properties": {
    "addr:full":"Shop 6, Ocean Crt, Cnr Ocean St & Beach Rd Maroochydore QLD 4558",
    "addr:housenumber":"shop 6",
    "addr:postcode":"4558",
    "addr:street":"Ocean Crt Cnr Ocean St & Beach Rd",
    "iso:country":"AU",
    "sg:address":"Shop 6, Ocean Crt, Cnr Ocean St & Beach Rd",
    "sg:city":"Maroochydore",
    "sg:classifiers":[
        {
            "category":"Retail",
            "subcategory":"Auto Rental",
            "type":"Services"
        }
    ],
    "sg:phone":"+61 7 5453 1999",
    "sg:postcode":"4558",
    "sg:province":"QLD",
    "sg:tags":[
        "car",
        "hire",
        "minibus"
    ],
    "wof:name":"Avis",
    "wof:placetype":"venue"
},
  "geometry": {"coordinates":[153.089477539,-26.6520080566],"type":"Point"}
}