{
  "type": "Feature",
  "properties": {
    "iso:country":"AU",
    "sg:address":"Level 5, 22 King William St",
    "sg:city":"Adelaide",
    "sg:classifiers":[
        {
            "category":"Health Services",
            "subcategory":"Dentist",
            "type":"Services"
        }
    ],
    "sg:phone":"+61 8 8212 3499",
    "sg:postcode":"5000",
    "sg:province":"SA",
    "sg:website":"http://www.rikendental.com.au",
    "wof:name":"Riken Dental Group",
    "wof:placetype":"venue"
},
  "geometry": {"coordinates":[138.59971618599999,-34.9223823547],"type":"Point"}
}