{
  "type": "Feature",
  "properties": {
    "addr:full":"5 Tubbo Pl Wagga Wagga NSW 2650",
    "addr:housenumber":"5",
    "addr:postcode":"2650",
    "addr:street":"Tubbo Pl",
    "iso:country":"AU",
    "sg:address":"5 Tubbo Pl",
    "sg:city":"Wagga Wagga",
    "sg:classifiers":[
        {
            "category":"Home & Garden",
            "subcategory":"Building Materials",
            "type":"Retail Goods"
        }
    ],
    "sg:phone":"+61 407 667 149",
    "sg:postcode":"2650",
    "sg:province":"NSW",
    "sg:tags":[
        "lawn",
        "cutting",
        "maintenance"
    ],
    "wof:name":"Riverina Grasshoppers",
    "wof:placetype":"venue"
},
  "geometry": {"coordinates":[147.35398864699999,-35.1512374878],"type":"Point"}
}