{
  "type": "Feature",
  "properties": {
    "iso:country":"AU",
    "sg:address":"Cnr Archer & West Sts",
    "sg:city":"Rockhampton",
    "sg:classifiers":[
        {
            "category":"Food & Beverages",
            "subcategory":"Liquor & Beverages",
            "type":"Retail Goods"
        }
    ],
    "sg:phone":"+61 7 4922 1389",
    "sg:postcode":"4700",
    "sg:province":"QLD",
    "sg:tags":[
        "store"
    ],
    "wof:name":"Brunswick Hotel",
    "wof:placetype":"venue"
},
  "geometry": {"coordinates":[150.49371337900001,-23.3854751587],"type":"Point"}
}