{
  "type": "Feature",
  "properties": {
    "iso:country":"AU",
    "sg:address":"99 Beach Rd",
    "sg:city":"Pialba",
    "sg:classifiers":[
        {
            "category":"Social Services",
            "subcategory":"Adult Care",
            "type":"Services"
        }
    ],
    "sg:phone":"+61 7 4124 5999",
    "sg:postcode":"4655",
    "sg:province":"QLD",
    "sg:tags":[
        "towing"
    ],
    "wof:name":"Pialba Smash Repairs",
    "wof:placetype":"venue"
},
  "geometry": {"coordinates":[152.831223,-25.28677],"type":"Point"}
}