{
  "type": "Feature",
  "properties": {
    "iso:country":"AU",
    "sg:address":"23 Rosebank Ave",
    "sg:city":"Dural",
    "sg:classifiers":[
        {
            "category":"Utilities",
            "subcategory":"Electric",
            "type":"Services"
        }
    ],
    "sg:phone":"+61 2 8004 2606",
    "sg:postcode":"2158",
    "sg:province":"NSW",
    "sg:tags":[
        "electrical",
        "contractor"
    ],
    "wof:name":"M G B Electrical",
    "wof:placetype":"venue"
},
  "geometry": {"coordinates":[151.01649475100001,-33.6914215088],"type":"Point"}
}