{
  "type": "Feature",
  "properties": {
    "iso:country":"AU",
    "sg:address":"Gardiner St",
    "sg:city":"Goolwa",
    "sg:classifiers":[
        {
            "category":"Professional",
            "subcategory":"Engineering",
            "type":"Services"
        }
    ],
    "sg:phone":"+61 8 8555 5257",
    "sg:postcode":"5214",
    "sg:province":"SA",
    "sg:tags":[
        "steam",
        "engineer"
    ],
    "wof:name":"Strath Steam",
    "wof:placetype":"venue"
},
  "geometry": {"coordinates":[138.775512695,-35.5013046265],"type":"Point"}
}