{
  "type": "Feature",
  "properties": {
    "iso:country":"AU",
    "sg:address":"Gooding Drv",
    "sg:city":"Merrimac",
    "sg:classifiers":[
        {
            "category":"Retail",
            "subcategory":"Event Space",
            "type":"Services"
        }
    ],
    "sg:phone":"+61 7 5579 8700",
    "sg:postcode":"4226",
    "sg:province":"QLD",
    "sg:tags":[
        "venue",
        "reception",
        "wedding"
    ],
    "wof:name":"Lakelands Golf Club",
    "wof:placetype":"venue"
},
  "geometry": {"coordinates":[153.38404846200001,-28.0330791473],"type":"Point"}
}