{
  "type": "Feature",
  "properties": {
    "addr:full":"125 Great North Rd Five Dock NSW 2046",
    "addr:housenumber":"125",
    "addr:postcode":"2046",
    "addr:street":"Great North Rd",
    "iso:country":"AU",
    "sg:address":"125 Great North Rd",
    "sg:city":"Five Dock",
    "sg:classifiers":[
        {
            "category":"Fast Food",
            "type":"Food & Drink"
        }
    ],
    "sg:phone":"+61 2 9713 4853",
    "sg:postcode":"2046",
    "sg:province":"NSW",
    "sg:tags":[
        "away",
        "take"
    ],
    "wof:name":"Texas Charcoal Chicken",
    "wof:placetype":"venue"
},
  "geometry": {"coordinates":[151.129456,-33.868664],"type":"Point"}
}