{
  "type": "Feature",
  "properties": {
    "iso:country":"AU",
    "sg:address":"Unit 1/ 32 Boulder Rd",
    "sg:city":"Malaga",
    "sg:classifiers":[
        {
            "category":"Education",
            "subcategory":"Dance Studio",
            "type":"Public Place"
        }
    ],
    "sg:phone":"+61 8 9276 3737",
    "sg:postcode":"6090",
    "sg:province":"WA",
    "sg:tags":[
        "venue",
        "tuition"
    ],
    "wof:name":"Irish Dancing Academy Of W.A.",
    "wof:placetype":"venue"
},
  "geometry": {"coordinates":[115.904006958,-31.8649291992],"type":"Point"}
}