{
  "type": "Feature",
  "properties": {
    "addr:full":"77 Erindale Rd Balcatta WA 6021",
    "addr:housenumber":"77",
    "addr:postcode":"6021",
    "addr:street":"Erindale Rd",
    "iso:country":"AU",
    "sg:address":"77 Erindale Rd",
    "sg:city":"Balcatta",
    "sg:classifiers":[
        {
            "category":"Banks & Credit Unions",
            "subcategory":"Investment Brokerage",
            "type":"Services"
        }
    ],
    "sg:phone":"+61 8 9344 1111",
    "sg:postcode":"6021",
    "sg:province":"WA",
    "sg:tags":[
        "water",
        "reticulation",
        "contractor"
    ],
    "wof:name":"Custom Irrigation",
    "wof:placetype":"venue"
},
  "geometry": {"coordinates":[115.806602478,-31.8662853241],"type":"Point"}
}