{
  "type": "Feature",
  "properties": {
    "addr:full":"Nambour Central Mall Lowe St Nambour QLD 4560",
    "addr:postcode":"4560",
    "addr:street":"Lowe St",
    "iso:country":"AU",
    "sg:address":"Nambour Central Mall Lowe St",
    "sg:city":"Nambour",
    "sg:classifiers":[
        {
            "category":"Banks & Credit Unions",
            "subcategory":"Financial Services",
            "type":"Services"
        }
    ],
    "sg:phone":"+61 1300 138 832",
    "sg:postcode":"4560",
    "sg:province":"QLD",
    "sg:tags":[
        "planning"
    ],
    "wof:name":"WEALTHPATH WEALTH GENERATION",
    "wof:placetype":"venue"
},
  "geometry": {"coordinates":[152.960403442,-26.6258125305],"type":"Point"}
}