{
  "type": "Feature",
  "properties": {
    "iso:country":"AU",
    "sg:address":"Suite 2/ 73 Ford St",
    "sg:city":"Beechworth",
    "sg:classifiers":[
        {
            "category":"Health Services",
            "subcategory":"Chiropractor",
            "type":"Services"
        }
    ],
    "sg:phone":"+61 3 5728 3317",
    "sg:postcode":"3747",
    "sg:province":"VIC",
    "wof:name":"Maguire Chiropractic Centres",
    "wof:placetype":"venue"
},
  "geometry": {"coordinates":[146.68626399999999,-36.359741],"type":"Point"}
}