{
  "type": "Feature",
  "properties": {
    "iso:country":"AU",
    "sg:address":"Cnr Eastern & Caprice Rds",
    "sg:city":"Geraldton",
    "sg:classifiers":[
        {
            "category":"Arts & Performance",
            "subcategory":"Dance",
            "type":"Entertainment"
        }
    ],
    "sg:phone":"+61 8 9964 1942",
    "sg:postcode":"6530",
    "sg:province":"WA",
    "sg:tags":[
        "theatrical",
        "ballet",
        "tuition"
    ],
    "wof:name":"Kerry's Batavia Coast Dance Centre",
    "wof:placetype":"venue"
},
  "geometry": {"coordinates":[114.61965942400001,-28.7751331329],"type":"Point"}
}