{
  "type": "Feature",
  "properties": {
    "addr:full":"5 Malua St Reservoir VIC 3073",
    "addr:housenumber":"5",
    "addr:postcode":"3073",
    "addr:street":"Malua St",
    "iso:country":"AU",
    "sg:address":"5 Malua St",
    "sg:city":"Reservoir",
    "sg:classifiers":[
        {
            "category":"Manufacturing",
            "subcategory":"Electronics",
            "type":"Manufacturing & Wholesale Goods"
        }
    ],
    "sg:phone":"+61 3 8336 1266",
    "sg:postcode":"3073",
    "sg:province":"VIC",
    "sg:tags":[
        "wholesaler",
        "equipment",
        "part",
        "mfrs",
        "refrigeration"
    ],
    "wof:name":"Gordon John A. Refrigeration Pty Ltd",
    "wof:placetype":"venue"
},
  "geometry": {"coordinates":[144.98178100600001,-37.719039917],"type":"Point"}
}