{
  "type": "Feature",
  "properties": {
    "addr:full":"881 Ruthven St South Toowoomba QLD 4350",
    "addr:housenumber":"881",
    "addr:postcode":"4350",
    "addr:street":"Ruthven St",
    "iso:country":"AU",
    "sg:address":"881 Ruthven St South",
    "sg:city":"Toowoomba",
    "sg:classifiers":[
        {
            "category":"Home & Garden",
            "subcategory":"Garden Supply",
            "type":"Retail Goods"
        }
    ],
    "sg:phone":"+61 7 4636 1077",
    "sg:postcode":"4350",
    "sg:province":"QLD",
    "sg:tags":[
        "equipment",
        "hydroponics"
    ],
    "wof:name":"Walshs Seeds Garden Centre",
    "wof:placetype":"venue"
},
  "geometry": {"coordinates":[151.94717399999999,-27.596014],"type":"Point"}
}