{
  "type": "Feature",
  "properties": {
    "addr:full":"Level 1, 56- 58 Burwood Rd Hawthorn VIC 3122",
    "addr:housenumber":"56 58",
    "addr:postcode":"3122",
    "addr:street":"Burwood Rd",
    "iso:country":"AU",
    "sg:address":"Level 1, 56- 58 Burwood Rd",
    "sg:city":"Hawthorn",
    "sg:classifiers":[
        {
            "category":"Professional",
            "subcategory":"Accounting & Tax Preparation",
            "type":"Services"
        }
    ],
    "sg:phone":"+61 3 9818 6000",
    "sg:postcode":"3122",
    "sg:province":"VIC",
    "sg:tags":[
        "consultant",
        "taxation"
    ],
    "wof:name":"Stantins",
    "wof:placetype":"venue"
},
  "geometry": {"coordinates":[145.024291992,-37.8214492798],"type":"Point"}
}