{
  "type": "Feature",
  "properties": {
    "addr:full":"Suite 9a, 83a Main St Greensborough VIC 3088",
    "addr:postcode":"3088",
    "addr:street":"83A Main St",
    "iso:country":"AU",
    "sg:address":"Suite 9a, 83a Main St",
    "sg:city":"Greensborough",
    "sg:classifiers":[
        {
            "category":"Banks & Credit Unions",
            "subcategory":"Investment Brokerage",
            "type":"Services"
        }
    ],
    "sg:phone":"+61 3 9435 9718",
    "sg:postcode":"3088",
    "sg:province":"VIC",
    "wof:name":"Bowen M Financial Services",
    "wof:placetype":"venue"
},
  "geometry": {"coordinates":[145.104934692,-37.7033081055],"type":"Point"}
}