{
  "type": "Feature",
  "properties": {
    "addr:full":"9 Moongalba St Boondall QLD 4034",
    "addr:housenumber":"9",
    "addr:postcode":"4034",
    "addr:street":"Moongalba St",
    "iso:country":"AU",
    "sg:address":"9 Moongalba St",
    "sg:city":"Boondall",
    "sg:classifiers":[
        {
            "category":"Sports & Exercise",
            "subcategory":"Gym",
            "type":"Entertainment"
        }
    ],
    "sg:phone":"+61 410 597 600",
    "sg:postcode":"4034",
    "sg:province":"QLD",
    "sg:tags":[
        "personal",
        "trainer",
        "fitness"
    ],
    "wof:name":"On Course Personal Training",
    "wof:placetype":"venue"
},
  "geometry": {"coordinates":[153.05908199999999,-27.362638],"type":"Point"}
}