{
  "type": "Feature",
  "properties": {
    "iso:country":"AU",
    "sg:address":"2/ 20 Christine Ave",
    "sg:city":"Miami",
    "sg:classifiers":[
        {
            "category":"Autos & Motor Vehicles",
            "subcategory":"Auto Supplies",
            "type":"Retail Goods"
        }
    ],
    "sg:phone":"+61 7 5508 2080",
    "sg:postcode":"4220",
    "sg:province":"QLD",
    "sg:tags":[
        "battery",
        "automotive"
    ],
    "wof:name":"A E S Auto Electrical Services",
    "wof:placetype":"venue"
},
  "geometry": {"coordinates":[153.443115234,-28.0772476196],"type":"Point"}
}