{
  "type": "Feature",
  "properties": {
    "iso:country":"AU",
    "sg:address":"Shop 1b/ 45a Bay St",
    "sg:city":"Double Bay",
    "sg:classifiers":[
        {
            "category":"Shopping",
            "subcategory":"Clothing, Apparel, & Fashions",
            "type":"Retail Goods"
        }
    ],
    "sg:phone":"+61 2 9363 3232",
    "sg:postcode":"2028",
    "sg:province":"NSW",
    "sg:tags":[
        "lady",
        "wear"
    ],
    "wof:name":"Bare Pty Ltd",
    "wof:placetype":"venue"
},
  "geometry": {"coordinates":[151.241943359,-33.8764457703],"type":"Point"}
}