{
  "type": "Feature",
  "properties": {
    "addr:full":"8 Canal Rd St Peters NSW 2044",
    "addr:housenumber":"8",
    "addr:postcode":"2044",
    "addr:street":"Canal Rd",
    "iso:country":"AU",
    "sg:address":"8 Canal Rd",
    "sg:city":"St Peters",
    "sg:classifiers":[
        {
            "category":"Manufacturing",
            "subcategory":"Apparel",
            "type":"Manufacturing & Wholesale Goods"
        }
    ],
    "sg:phone":"+61 2 9519 2433",
    "sg:postcode":"2044",
    "sg:province":"NSW",
    "sg:tags":[
        "wholesaler",
        "mfrs",
        "footwear"
    ],
    "wof:name":"Bally",
    "wof:placetype":"venue"
},
  "geometry": {"coordinates":[151.17581200000001,-33.917042],"type":"Point"}
}