{
  "type": "Feature",
  "properties": {
    "addr:full":"9 Mott St Heatley QLD 4814",
    "addr:housenumber":"9",
    "addr:postcode":"4814",
    "addr:street":"Mott St",
    "iso:country":"AU",
    "sg:address":"9 Mott St",
    "sg:city":"Heatley",
    "sg:classifiers":[
        {
            "category":"Retail",
            "subcategory":"Driving School",
            "type":"Services"
        }
    ],
    "sg:phone":"+61 7 4775 1533",
    "sg:postcode":"4814",
    "sg:province":"QLD",
    "wof:name":"Bettys Driving School",
    "wof:placetype":"venue"
},
  "geometry": {"coordinates":[146.75071700000001,-19.291471],"type":"Point"}
}