{
  "type": "Feature",
  "properties": {
    "iso:country":"AU",
    "sg:address":"26 Henry St",
    "sg:city":"Penrith",
    "sg:classifiers":[
        {
            "category":"Manufacturing",
            "subcategory":"Motor Vehicles & Parts",
            "type":"Manufacturing & Wholesale Goods"
        }
    ],
    "sg:phone":"+61 2 4731 4200",
    "sg:postcode":"2750",
    "sg:province":"NSW",
    "sg:tags":[
        "replacement"
    ],
    "wof:name":"Henry St. Spare Parts Pty. Ltd.",
    "wof:placetype":"venue"
},
  "geometry": {"coordinates":[150.85386657699999,-33.8924179077],"type":"Point"}
}