{
  "type": "Feature",
  "properties": {
    "iso:country":"AU",
    "sg:address":"59 Corypha Crs",
    "sg:city":"Calamvale",
    "sg:classifiers":[
        {
            "category":"Personal",
            "subcategory":"Beauty Salon",
            "type":"Services"
        }
    ],
    "sg:phone":"+61 7 3273 1779",
    "sg:postcode":"4116",
    "sg:province":"QLD",
    "wof:name":"Calamvale Skin & Beauty",
    "wof:placetype":"venue"
},
  "geometry": {"coordinates":[153.04942321799999,-27.6217803955],"type":"Point"}
}