{
  "type": "Feature",
  "properties": {
    "addr:full":"PO Box 1393 Cooma NSW 2630",
    "addr:postcode":"2630",
    "iso:country":"AU",
    "sg:address":"PO Box 1393",
    "sg:city":"Cooma",
    "sg:classifiers":[
        {
            "category":"Real Estate",
            "subcategory":"Architect",
            "type":"Services"
        }
    ],
    "sg:phone":"+61 2 6453 3372",
    "sg:postcode":"2630",
    "sg:province":"NSW",
    "sg:tags":[
        "building",
        "designer"
    ],
    "wof:name":"DMW Design & Drafting",
    "wof:placetype":"venue"
},
  "geometry": {"coordinates":[149.13154602,-36.2323493958],"type":"Point"}
}