{
  "type": "Feature",
  "properties": {
    "iso:country":"AU",
    "sg:address":"232A Dorset Rd",
    "sg:city":"Boronia",
    "sg:classifiers":[
        {
            "category":"Home & Garden",
            "subcategory":"Building Materials",
            "type":"Retail Goods"
        }
    ],
    "sg:phone":"+61 3 9779 4987",
    "sg:postcode":"3155",
    "sg:province":"VIC",
    "sg:tags":[
        "merchant",
        "glass",
        "glazier"
    ],
    "wof:name":"Eastern Glass",
    "wof:placetype":"venue"
},
  "geometry": {"coordinates":[145.285842895,-37.8612861633],"type":"Point"}
}