{
  "type": "Feature",
  "properties": {
    "addr:full":"PO Box 1053 Central Park VIC 3145",
    "addr:postcode":"3145",
    "addr:street":"Park",
    "iso:country":"AU",
    "sg:address":"PO Box 1053",
    "sg:city":"Central Park",
    "sg:classifiers":[
        {
            "category":"Professional",
            "subcategory":"Testing Lab",
            "type":"Services"
        }
    ],
    "sg:phone":"+61 413 179 316",
    "sg:postcode":"3145",
    "sg:province":"VIC",
    "sg:tags":[
        "inspection"
    ],
    "wof:name":"Data Link Verification Pty Ltd",
    "wof:placetype":"venue"
},
  "geometry": {"coordinates":[145.04893493599999,-37.867641449],"type":"Point"}
}