{
  "type": "Feature",
  "properties": {
    "iso:country":"AU",
    "sg:address":"PO Box 120",
    "sg:city":"Atherton",
    "sg:classifiers":[
        {
            "category":"Utilities",
            "subcategory":"Refuse",
            "type":"Services"
        }
    ],
    "sg:phone":"+61 7 4095 4498",
    "sg:postcode":"4883",
    "sg:province":"QLD",
    "sg:tags":[
        "remover",
        "rubbish"
    ],
    "wof:name":"Tableland Trade Waste",
    "wof:placetype":"venue"
},
  "geometry": {"coordinates":[145.474975586,-17.2683391571],"type":"Point"}
}