{
  "type": "Feature",
  "properties": {
    "iso:country":"AU",
    "sg:address":"163 Auckland St",
    "sg:city":"Bega",
    "sg:classifiers":[
        {
            "category":"Professional",
            "subcategory":"Computer Services",
            "type":"Services"
        }
    ],
    "sg:phone":"+61 2 6492 3652",
    "sg:postcode":"2550",
    "sg:province":"NSW",
    "sg:tags":[
        "training"
    ],
    "wof:name":"Bega Valley Telecottage",
    "wof:placetype":"venue"
},
  "geometry": {"coordinates":[149.83793640100001,-36.6883468628],"type":"Point"}
}