{
  "type": "Feature",
  "properties": {
    "addr:full":"46 Simmat Ave Condell Park NSW 2200",
    "addr:housenumber":"46",
    "addr:postcode":"2200",
    "addr:street":"Simmat Ave",
    "iso:country":"AU",
    "sg:address":"46 Simmat Ave",
    "sg:city":"Condell Park",
    "sg:classifiers":[
        {
            "category":"Health Services",
            "subcategory":"Doctor",
            "type":"Services"
        }
    ],
    "sg:phone":"+61 2 9790 6192",
    "sg:postcode":"2200",
    "sg:province":"NSW",
    "sg:tags":[
        "medical",
        "practitioner"
    ],
    "wof:name":"Harnett Sue",
    "wof:placetype":"venue"
},
  "geometry": {"coordinates":[151.011414,-33.922302],"type":"Point"}
}