{
  "type": "Feature",
  "properties": {
    "addr:full":"Andrews Crt Chambers Flat QLD 4133",
    "addr:postcode":"4133",
    "addr:street":"Andrews Crt",
    "iso:country":"AU",
    "sg:address":"Andrews Crt",
    "sg:city":"Chambers Flat",
    "sg:classifiers":[
        {
            "category":"Building & Trades",
            "subcategory":"Construction",
            "type":"Services"
        }
    ],
    "sg:phone":"+61 419 703 648",
    "sg:postcode":"4133",
    "sg:province":"QLD",
    "sg:tags":[
        "earth",
        "excavating",
        "moving",
        "contractor"
    ],
    "wof:name":"Andrews Court Plant Hire",
    "wof:placetype":"venue"
},
  "geometry": {"coordinates":[153.08294677699999,-27.7309494019],"type":"Point"}
}