{
  "type": "Feature",
  "properties": {
    "iso:country":"AU",
    "sg:address":"4/ 237 Unley Rd",
    "sg:city":"Malvern",
    "sg:classifiers":[
        {
            "category":"Health Services",
            "subcategory":"Chiropractor",
            "type":"Services"
        }
    ],
    "sg:phone":"+61 8 8357 8211",
    "sg:postcode":"5061",
    "sg:province":"SA",
    "wof:name":"Essential Chiropractic",
    "wof:placetype":"venue"
},
  "geometry": {"coordinates":[138.608154297,-34.9566268921],"type":"Point"}
}