{
  "type": "Feature",
  "properties": {
    "addr:full":"8 Contingent St Trafalgar VIC 3824",
    "addr:housenumber":"8",
    "addr:postcode":"3824",
    "addr:street":"Contingent St",
    "iso:country":"AU",
    "sg:address":"8 Contingent St",
    "sg:city":"Trafalgar",
    "sg:classifiers":[
        {
            "category":"Shopping",
            "subcategory":"Clothing, Apparel, & Fashions",
            "type":"Retail Goods"
        }
    ],
    "sg:phone":"+61 3 5633 2788",
    "sg:postcode":"3824",
    "sg:province":"VIC",
    "sg:tags":[
        "recycled",
        "clothing"
    ],
    "wof:name":"Trafalgar & District Community Op Shop",
    "wof:placetype":"venue"
},
  "geometry": {"coordinates":[146.15519699999999,-38.208179],"type":"Point"}
}