{
  "type": "Feature",
  "properties": {
    "addr:full":"20 Guernsey St Guildford NSW 2161",
    "addr:housenumber":"20",
    "addr:postcode":"2161",
    "addr:street":"Guernsey St",
    "iso:country":"AU",
    "sg:address":"20 Guernsey St",
    "sg:city":"Guildford",
    "sg:classifiers":[
        {
            "category":"Shopping",
            "subcategory":"Gifts & Souvenirs",
            "type":"Retail Goods"
        }
    ],
    "sg:phone":"+61 2 9632 8500",
    "sg:postcode":"2161",
    "sg:province":"NSW",
    "sg:tags":[
        "shop",
        "supply"
    ],
    "wof:name":"Donghua Trading Co",
    "wof:placetype":"venue"
},
  "geometry": {"coordinates":[150.97808837900001,-33.8600959778],"type":"Point"}
}