{
  "type": "Feature",
  "properties": {
    "addr:full":"Shop 17 The Plaza Alstonville NSW 2477",
    "addr:housenumber":"shop 17",
    "addr:postcode":"2477",
    "addr:street":"The",
    "iso:country":"AU",
    "sg:address":"Shop 17 The Plaza",
    "sg:city":"Alstonville",
    "sg:classifiers":[
        {
            "category":"Professional",
            "subcategory":"Advertising",
            "type":"Services"
        }
    ],
    "sg:phone":"+61 2 6628 5529",
    "sg:postcode":"2477",
    "sg:province":"NSW",
    "sg:tags":[
        "balloon",
        "novelty"
    ],
    "wof:name":"Alstonville Florist",
    "wof:placetype":"venue"
},
  "geometry": {"coordinates":[153.43785095199999,-28.8404541016],"type":"Point"}
}