{
  "type": "Feature",
  "properties": {
    "addr:full":"Suite 1/30-38 Victoria St Paddington NSW 2021",
    "addr:housenumber":"/ 30-38",
    "addr:postcode":"2021",
    "addr:street":"Victoria St",
    "iso:country":"AU",
    "sg:address":"Suite 1/30-38 Victoria St",
    "sg:city":"Paddington",
    "sg:classifiers":[
        {
            "category":"Shopping",
            "subcategory":"Clothing, Apparel, & Fashions",
            "type":"Retail Goods"
        }
    ],
    "sg:phone":"+61 2 9380 4880",
    "sg:postcode":"2021",
    "sg:province":"NSW",
    "sg:tags":[
        "accessory"
    ],
    "wof:name":"Paris Mode",
    "wof:placetype":"venue"
},
  "geometry": {"coordinates":[151.230194092,-33.8862876892],"type":"Point"}
}