{
  "type": "Feature",
  "properties": {
    "addr:full":"Ochertyre Rd Deniliquin VIC 2710",
    "addr:postcode":"2710",
    "addr:street":"Ochertyre Rd",
    "iso:country":"AU",
    "sg:address":"Ochertyre Rd",
    "sg:city":"Deniliquin",
    "sg:classifiers":[
        {
            "category":"Sports & Exercise",
            "subcategory":"Sports Center",
            "type":"Entertainment"
        }
    ],
    "sg:phone":"+61 3 5881 4100",
    "sg:postcode":"2710",
    "sg:province":"VIC",
    "sg:tags":[
        "ground"
    ],
    "wof:name":"Deniliquin Sports Park Inc.",
    "wof:placetype":"venue"
},
  "geometry": {"coordinates":[144.957397461,-35.529499054],"type":"Point"}
}