{
  "type": "Feature",
  "properties": {
    "addr:full":"10 Jellicoe St Brassall QLD 4305",
    "addr:housenumber":"10",
    "addr:postcode":"4305",
    "addr:street":"Jellicoe St",
    "iso:country":"AU",
    "sg:address":"10 Jellicoe St",
    "sg:city":"Brassall",
    "sg:classifiers":[
        {
            "category":"Building & Trades",
            "subcategory":"Plumbing",
            "type":"Services"
        }
    ],
    "sg:phone":"+61 408 192 668",
    "sg:postcode":"4305",
    "sg:province":"QLD",
    "sg:tags":[
        "plumber",
        "gasfitters"
    ],
    "wof:name":"GL & LS Harris",
    "wof:placetype":"venue"
},
  "geometry": {"coordinates":[152.73980712900001,-27.5943431854],"type":"Point"}
}