{
  "type": "Feature",
  "properties": {
    "addr:full":"146 Argyle St Hobart TAS 7000",
    "addr:housenumber":"146",
    "addr:postcode":"7000",
    "addr:street":"Argyle St",
    "iso:country":"AU",
    "sg:address":"146 Argyle St",
    "sg:city":"Hobart",
    "sg:classifiers":[
        {
            "category":"Autos & Motor Vehicles",
            "subcategory":"Automobile Sales",
            "type":"Retail Goods"
        }
    ],
    "sg:phone":"+61 3 6231 6161",
    "sg:postcode":"7000",
    "sg:province":"TAS",
    "sg:tags":[
        "car",
        "used"
    ],
    "wof:name":"Hobart City Commercials",
    "wof:placetype":"venue"
},
  "geometry": {"coordinates":[147.32324218799999,-42.8762435913],"type":"Point"}
}