{
  "type": "Feature",
  "properties": {
    "iso:country":"AU",
    "sg:address":"Suite 17,79- 83 High St",
    "sg:city":"Kew",
    "sg:classifiers":[
        {
            "category":"Banks & Credit Unions",
            "subcategory":"Financial Services",
            "type":"Services"
        }
    ],
    "sg:phone":"+61 3 9862 0111",
    "sg:postcode":"3101",
    "sg:province":"VIC",
    "sg:tags":[
        "loan",
        "finance",
        "mortgage"
    ],
    "wof:name":"Mortgage Access Group",
    "wof:placetype":"venue"
},
  "geometry": {"coordinates":[145.027786255,-37.8083724976],"type":"Point"}
}