{
  "type": "Feature",
  "properties": {
    "addr:full":"61 Dunn Rd Rocklea QLD 4106",
    "addr:housenumber":"61",
    "addr:postcode":"4106",
    "addr:street":"Dunn Rd",
    "iso:country":"AU",
    "sg:address":"61 Dunn Rd",
    "sg:city":"Rocklea",
    "sg:classifiers":[
        {
            "category":"Transit Center",
            "subcategory":"Freight",
            "type":"Transportation"
        }
    ],
    "sg:phone":"+61 7 3274 2797",
    "sg:postcode":"4106",
    "sg:province":"QLD",
    "sg:tags":[
        "forklift",
        "truck"
    ],
    "wof:name":"Rocklea Paint & Panel",
    "wof:placetype":"venue"
},
  "geometry": {"coordinates":[152.997314453,-27.5548324585],"type":"Point"}
}