{
  "type": "Feature",
  "properties": {
    "addr:full":"164 Magill Rd Norwood SA 5067",
    "addr:housenumber":"164",
    "addr:postcode":"5067",
    "addr:street":"Magill Rd",
    "iso:country":"AU",
    "sg:address":"164 Magill Rd",
    "sg:city":"Norwood",
    "sg:classifiers":[
        {
            "category":"Shopping",
            "subcategory":"Antiques",
            "type":"Retail Goods"
        }
    ],
    "sg:phone":"+61 8 8363 5300",
    "sg:postcode":"5067",
    "sg:province":"SA",
    "wof:name":"Abbey Antiques",
    "wof:placetype":"venue"
},
  "geometry": {"coordinates":[138.63534545900001,-34.9151725769],"type":"Point"}
}