{
  "type": "Feature",
  "properties": {
    "addr:full":"561 Larkhill Boundary Rd Lark Hill QLD 4306",
    "addr:housenumber":"561",
    "addr:postcode":"4306",
    "addr:street":"Larkhill Boundary Rd",
    "iso:country":"AU",
    "sg:address":"561 Larkhill Boundary Rd",
    "sg:city":"Lark Hill",
    "sg:classifiers":[
        {
            "category":"Building & Trades",
            "subcategory":"Construction",
            "type":"Services"
        }
    ],
    "sg:phone":"+61 7 5426 6333",
    "sg:postcode":"4306",
    "sg:province":"QLD",
    "sg:tags":[
        "earth",
        "excavating",
        "moving",
        "contractor"
    ],
    "wof:name":"N.J. & S.K. Hutchinson",
    "wof:placetype":"venue"
},
  "geometry": {"coordinates":[152.591796875,-27.5209197998],"type":"Point"}
}