{
  "type": "Feature",
  "properties": {
    "iso:country":"AU",
    "sg:address":"1 Port Rd",
    "sg:city":"Thebarton",
    "sg:classifiers":[
        {
            "category":"Manufacturing",
            "subcategory":"Motor Vehicles & Parts",
            "type":"Manufacturing & Wholesale Goods"
        }
    ],
    "sg:phone":"+61 8 8354 9522",
    "sg:postcode":"5031",
    "sg:province":"SA",
    "sg:tags":[
        "replacement"
    ],
    "wof:name":"Metro Holden Parts",
    "wof:placetype":"venue"
},
  "geometry": {"coordinates":[138.578292847,-34.9181213379],"type":"Point"}
}