{
  "type": "Feature",
  "properties": {
    "addr:full":"3 Homer Crt Ferntree Gully VIC 3156",
    "addr:housenumber":"3",
    "addr:postcode":"3156",
    "addr:street":"Homer Crt",
    "iso:country":"AU",
    "sg:address":"3 Homer Crt",
    "sg:city":"Ferntree Gully",
    "sg:classifiers":[
        {
            "category":"Professional",
            "subcategory":"Art Services",
            "type":"Services"
        }
    ],
    "sg:phone":"+61 3 9764 0023",
    "sg:postcode":"3156",
    "sg:province":"VIC",
    "sg:tags":[
        "decorator",
        "painter"
    ],
    "wof:name":"Dazzle Brush Master Painters",
    "wof:placetype":"venue"
},
  "geometry": {"coordinates":[145.260696411,-37.8971748352],"type":"Point"}
}