{
  "type": "Feature",
  "properties": {
    "iso:country":"AU",
    "sg:address":"28 Clarice Rd",
    "sg:city":"Box Hill",
    "sg:classifiers":[
        {
            "category":"Retail",
            "subcategory":"Auto Repair",
            "type":"Services"
        }
    ],
    "sg:phone":"+61 3 9898 5913",
    "sg:postcode":"3128",
    "sg:province":"VIC",
    "sg:tags":[
        "beater",
        "painter",
        "panel"
    ],
    "wof:name":"Clarice Body Group Pty Ltd",
    "wof:placetype":"venue"
},
  "geometry": {"coordinates":[145.133636475,-37.8343772888],"type":"Point"}
}