{
  "type": "Feature",
  "properties": {
    "iso:country":"AU",
    "sg:address":"41 Parkland Drv",
    "sg:city":"Hamlyn Heights",
    "sg:classifiers":[
        {
            "category":"Professional",
            "subcategory":"Engineering",
            "type":"Services"
        }
    ],
    "sg:phone":"+61 437 198 895",
    "sg:postcode":"3215",
    "sg:province":"VIC",
    "sg:tags":[
        "engineer"
    ],
    "wof:name":"Engineering Procurement Service",
    "wof:placetype":"venue"
},
  "geometry": {"coordinates":[144.32322692899999,-38.1095695496],"type":"Point"}
}