{
  "type": "Feature",
  "properties": {
    "iso:country":"AU",
    "sg:address":"8 Pansywood Crt",
    "sg:city":"Mt Pleasant",
    "sg:classifiers":[
        {
            "category":"Building & Trades",
            "subcategory":"Cleaning & Sanitation",
            "type":"Services"
        }
    ],
    "sg:phone":"+61 7 4942 7744",
    "sg:postcode":"4740",
    "sg:province":"QLD",
    "sg:tags":[
        "cleaner",
        "repairer",
        "roof"
    ],
    "wof:name":"Knapman S & I Plumbing",
    "wof:placetype":"venue"
},
  "geometry": {"coordinates":[149.16598500000001,-21.119366],"type":"Point"}
}