{
  "type": "Feature",
  "properties": {
    "iso:country":"AU",
    "sg:address":"6 Kansas Rd",
    "sg:city":"Toongabbie",
    "sg:classifiers":[
        {
            "category":"Home & Garden",
            "subcategory":"Building Materials",
            "type":"Retail Goods"
        }
    ],
    "sg:phone":"+61 410 508 952",
    "sg:postcode":"2146",
    "sg:province":"NSW",
    "sg:tags":[
        "lawn",
        "cutting",
        "maintenance"
    ],
    "wof:name":"Brads Backyard Professional Lawn & Garden Care",
    "wof:placetype":"venue"
},
  "geometry": {"coordinates":[150.935836792,-33.7982444763],"type":"Point"}
}