{
  "type": "Feature",
  "properties": {
    "addr:full":"12- 14 Tobias St Forbes NSW 2871",
    "addr:housenumber":"14",
    "addr:postcode":"2871",
    "addr:street":"Tobias St",
    "iso:country":"AU",
    "sg:address":"12- 14 Tobias St",
    "sg:city":"Forbes",
    "sg:classifiers":[
        {
            "category":"Home & Garden",
            "subcategory":"Hardware",
            "type":"Retail Goods"
        }
    ],
    "sg:phone":"+61 2 6852 3466",
    "sg:postcode":"2871",
    "sg:province":"NSW",
    "sg:tags":[
        "repair",
        "tool",
        "power"
    ],
    "wof:name":"Haley's Steel & Hardware Pty Ltd",
    "wof:placetype":"venue"
},
  "geometry": {"coordinates":[148.023697,-33.362339],"type":"Point"}
}