{
  "type": "Feature",
  "properties": {
    "iso:country":"AU",
    "sg:address":"26 Curtis Rd",
    "sg:city":"Mulgrave",
    "sg:classifiers":[
        {
            "category":"Retail",
            "subcategory":"Auto Repair",
            "type":"Services"
        }
    ],
    "sg:phone":"+61 2 4577 8744",
    "sg:postcode":"2756",
    "sg:province":"NSW",
    "sg:tags":[
        "repairer",
        "motor",
        "engineer"
    ],
    "wof:name":"Aussie 4x4 & Commercial",
    "wof:placetype":"venue"
},
  "geometry": {"coordinates":[150.83612060600001,-33.6268882751],"type":"Point"}
}