{
  "type": "Feature",
  "properties": {
    "iso:country":"AU",
    "sg:address":"8 Forrest St",
    "sg:city":"Fremantle",
    "sg:classifiers":[
        {
            "category":"Education",
            "subcategory":"School",
            "type":"Public Place"
        }
    ],
    "sg:phone":"+61 8 9335 6136",
    "sg:postcode":"6160",
    "sg:province":"WA",
    "sg:tags":[
        "state",
        "except",
        "nsw"
    ],
    "wof:name":"Schools Government (Public)",
    "wof:placetype":"venue"
},
  "geometry": {"coordinates":[115.75971199999999,-32.048386],"type":"Point"}
}