{
  "type": "Feature",
  "properties": {
    "addr:full":"Shop 5, Wheelers Hill Shopping Centre, 200 Jells Rd Wheelers Hill VIC 3150",
    "addr:housenumber":"shop 5;200",
    "addr:postcode":"3150",
    "addr:street":"Jells Rd",
    "iso:country":"AU",
    "sg:address":"Shop 5, Wheelers Hill Shopping Centre, 200 Jells Rd",
    "sg:city":"Wheelers Hill",
    "sg:classifiers":[
        {
            "category":"Food & Beverages",
            "subcategory":"Bakery",
            "type":"Retail Goods"
        }
    ],
    "sg:phone":"+61 3 9562 0461",
    "sg:postcode":"3150",
    "sg:province":"VIC",
    "sg:tags":[
        "baker"
    ],
    "wof:name":"Bakers Delight Ltd",
    "wof:placetype":"venue"
},
  "geometry": {"coordinates":[145.18856811500001,-37.9102706909],"type":"Point"}
}