{
  "type": "Feature",
  "properties": {
    "addr:full":"6 Patrick St Ulverstone TAS 7315",
    "addr:housenumber":"6",
    "addr:postcode":"7315",
    "addr:street":"Patrick St",
    "iso:country":"AU",
    "sg:address":"6 Patrick St",
    "sg:city":"Ulverstone",
    "sg:classifiers":[
        {
            "category":"Health Services",
            "subcategory":"Doctor",
            "type":"Services"
        }
    ],
    "sg:phone":"+61 3 6425 1611",
    "sg:postcode":"7315",
    "sg:province":"TAS",
    "sg:tags":[
        "medical",
        "practitioner"
    ],
    "wof:name":"Cann: N",
    "wof:placetype":"venue"
},
  "geometry": {"coordinates":[146.17120361299999,-41.1553459167],"type":"Point"}
}