{
  "type": "Feature",
  "properties": {
    "addr:full":"9 Swan St Hinton NSW 2321",
    "addr:housenumber":"9",
    "addr:postcode":"2321",
    "addr:street":"Swan St",
    "iso:country":"AU",
    "sg:address":"9 Swan St",
    "sg:city":"Hinton",
    "sg:classifiers":[
        {
            "category":"Professional",
            "subcategory":"Management & Consulting",
            "type":"Services"
        }
    ],
    "sg:phone":"+61 2 4930 5400",
    "sg:postcode":"2321",
    "sg:province":"NSW",
    "sg:tags":[
        "consultant"
    ],
    "wof:name":"Cannington Business Services",
    "wof:placetype":"venue"
},
  "geometry": {"coordinates":[151.65461730999999,-32.7190704346],"type":"Point"}
}