{
  "type": "Feature",
  "properties": {
    "addr:full":"Shop 1- 322 Windang Rd Windang NSW 2528",
    "addr:housenumber":"shop 1",
    "addr:postcode":"322;2528",
    "addr:street":"Windang Rd",
    "iso:country":"AU",
    "sg:address":"Shop 1- 322 Windang Rd",
    "sg:city":"Windang",
    "sg:classifiers":[
        {
            "category":"Wholesale",
            "subcategory":"Medical Equipment & Supplies",
            "type":"Manufacturing & Wholesale Goods"
        }
    ],
    "sg:phone":"+61 2 4295 3166",
    "sg:postcode":"2528",
    "sg:province":"NSW",
    "sg:tags":[
        "aid",
        "care",
        "health",
        "home"
    ],
    "wof:name":"Margs Little Cars for Little Kids",
    "wof:placetype":"venue"
},
  "geometry": {"coordinates":[150.86856079099999,-34.5320281982],"type":"Point"}
}