{
  "type": "Feature",
  "properties": {
    "iso:country":"AU",
    "sg:address":"662 Anzac Ave",
    "sg:city":"Toowoomba",
    "sg:classifiers":[
        {
            "category":"Building & Trades",
            "subcategory":"Cleaning & Sanitation",
            "type":"Services"
        }
    ],
    "sg:phone":"+61 412 664 360",
    "sg:postcode":"4350",
    "sg:province":"QLD",
    "sg:tags":[
        "industrial",
        "commercial",
        "contractor"
    ],
    "wof:name":"Petes Cleaning Service",
    "wof:placetype":"venue"
},
  "geometry": {"coordinates":[151.928955,-27.56695],"type":"Point"}
}