{
  "type": "Feature",
  "properties": {
    "addr:full":"2 Hughes St Kununoppin WA 6489",
    "addr:housenumber":"2",
    "addr:postcode":"6489",
    "addr:street":"Hughes St",
    "iso:country":"AU",
    "sg:address":"2 Hughes St",
    "sg:city":"Kununoppin",
    "sg:classifiers":[
        {
            "category":"Health Services",
            "subcategory":"Doctor",
            "type":"Services"
        }
    ],
    "sg:phone":"+61 8 9683 2032",
    "sg:postcode":"6489",
    "sg:province":"WA",
    "sg:tags":[
        "medical",
        "practitioner"
    ],
    "wof:name":"Radunovich John G Dr",
    "wof:placetype":"venue"
},
  "geometry": {"coordinates":[117.925170898,-31.1105995178],"type":"Point"}
}