{
  "type": "Feature",
  "properties": {
    "addr:full":"PO Box 13 Engadine NSW 2233",
    "addr:postcode":"2233",
    "iso:country":"AU",
    "sg:address":"PO Box 13",
    "sg:city":"Engadine",
    "sg:classifiers":[
        {
            "category":"Recreation",
            "subcategory":"Water Park",
            "type":"Entertainment"
        }
    ],
    "sg:phone":"+61 419 813 275",
    "sg:postcode":"2233",
    "sg:province":"NSW",
    "sg:tags":[
        "resort",
        "skiing"
    ],
    "wof:name":"Australian Powersports",
    "wof:placetype":"venue"
},
  "geometry": {"coordinates":[151.01315307600001,-34.065158844],"type":"Point"}
}