{
  "type": "Feature",
  "properties": {
    "iso:country":"AU",
    "sg:address":"145 Sydney St",
    "sg:city":"New Farm",
    "sg:classifiers":[
        {
            "category":"Building & Trades",
            "subcategory":"Landscaping Services",
            "type":"Services"
        }
    ],
    "sg:phone":"+61 7 3403 0157",
    "sg:postcode":"4005",
    "sg:province":"QLD",
    "sg:tags":[
        "control",
        "weed"
    ],
    "wof:name":"Vegetation Treatment Services",
    "wof:placetype":"venue"
},
  "geometry": {"coordinates":[153.04963684099999,-27.4666538239],"type":"Point"}
}