{
  "type": "Feature",
  "properties": {
    "addr:full":"128 Grand Junction Rd Rosewater SA 5013",
    "addr:housenumber":"128",
    "addr:postcode":"5013",
    "addr:street":"Grand Junction Rd",
    "iso:country":"AU",
    "sg:address":"128 Grand Junction Rd",
    "sg:city":"Rosewater",
    "sg:classifiers":[
        {
            "category":"Autos & Motor Vehicles",
            "subcategory":"Fuel & Gas Station",
            "type":"Retail Goods"
        }
    ],
    "sg:phone":"+61 8 8447 7661",
    "sg:postcode":"5013",
    "sg:province":"SA",
    "wof:name":"Caltex Rosewater",
    "wof:placetype":"venue"
},
  "geometry": {"coordinates":[138.52479553200001,-34.8518028259],"type":"Point"}
}