{
  "type": "Feature",
  "properties": {
    "iso:country":"AU",
    "sg:address":"263 Brisbane St",
    "sg:city":"Dubbo",
    "sg:classifiers":[
        {
            "category":"Shopping",
            "subcategory":"Computers & Home Electronics",
            "type":"Retail Goods"
        }
    ],
    "sg:phone":"+61 409 811 673",
    "sg:postcode":"2830",
    "sg:province":"NSW",
    "sg:tags":[
        "detector",
        "electronic"
    ],
    "wof:name":"Lyntet",
    "wof:placetype":"venue"
},
  "geometry": {"coordinates":[148.602325439,-32.2572860718],"type":"Point"}
}