{
  "type": "Feature",
  "properties": {
    "addr:full":"Shop 4 Taylors Arcade, Butler St Tully QLD 4854",
    "addr:housenumber":"shop 4",
    "addr:postcode":"4854",
    "addr:street":"Taylors Arcade Butler St",
    "iso:country":"AU",
    "sg:address":"Shop 4 Taylors Arcade, Butler St",
    "sg:city":"Tully",
    "sg:classifiers":[
        {
            "category":"Shopping",
            "subcategory":"Music",
            "type":"Retail Goods"
        }
    ],
    "sg:phone":"+61 7 4068 3166",
    "sg:postcode":"4854",
    "sg:province":"QLD",
    "sg:tags":[
        "store"
    ],
    "wof:name":"Good Vibrations",
    "wof:placetype":"venue"
},
  "geometry": {"coordinates":[145.93232727,-17.93409729],"type":"Point"}
}