{
  "type": "Feature",
  "properties": {
    "iso:country":"AU",
    "sg:address":"560 Mengha Rd",
    "sg:city":"Forest",
    "sg:classifiers":[
        {
            "category":"Building & Trades",
            "subcategory":"Cleaning & Sanitation",
            "type":"Services"
        }
    ],
    "sg:phone":"+61 417 556 280",
    "sg:postcode":"7330",
    "sg:province":"TAS",
    "sg:tags":[
        "grease",
        "trap"
    ],
    "wof:name":"Allan Lord Contracting",
    "wof:placetype":"venue"
},
  "geometry": {"coordinates":[145.247803,-40.860973],"type":"Point"}
}