{
  "type": "Feature",
  "properties": {
    "addr:full":"263 Durham St Bathurst NSW 2795",
    "addr:housenumber":"263",
    "addr:postcode":"2795",
    "addr:street":"Durham St",
    "iso:country":"AU",
    "sg:address":"263 Durham St",
    "sg:city":"Bathurst",
    "sg:classifiers":[
        {
            "category":"Cafe",
            "type":"Food & Drink"
        }
    ],
    "sg:phone":"+61 2 6332 9222",
    "sg:postcode":"2795",
    "sg:province":"NSW",
    "wof:name":"The Tree House Cafe & Restaurant",
    "wof:placetype":"venue"
},
  "geometry": {"coordinates":[149.57278442399999,-33.4047927856],"type":"Point"}
}