{
  "type": "Feature",
  "properties": {
    "iso:country":"AU",
    "sg:address":"Cumminin Rd",
    "sg:city":"Narembeen",
    "sg:classifiers":[
        {
            "category":"Farming",
            "subcategory":"Farm",
            "type":"Manufacturing & Wholesale Goods"
        }
    ],
    "sg:phone":"+61 8 9064 7362",
    "sg:postcode":"6369",
    "sg:province":"WA",
    "sg:tags":[
        "farmer"
    ],
    "wof:name":"Yandle A & S",
    "wof:placetype":"venue"
},
  "geometry": {"coordinates":[118.239571,-32.061016],"type":"Point"}
}