{
  "type": "Feature",
  "properties": {
    "addr:full":"137 Catherine Fields Rd Catherine Field NSW 2171",
    "addr:housenumber":"137",
    "addr:postcode":"2171",
    "addr:street":"Catherine Fields Rd",
    "iso:country":"AU",
    "sg:address":"137 Catherine Fields Rd",
    "sg:city":"Catherine Field",
    "sg:classifiers":[
        {
            "category":"Building & Trades",
            "subcategory":"Construction",
            "type":"Services"
        }
    ],
    "sg:phone":"+61 419 909 888",
    "sg:postcode":"2171",
    "sg:province":"NSW",
    "sg:tags":[
        "earth",
        "excavating",
        "moving",
        "contractor"
    ],
    "wof:name":"F C Concrete & Excavations",
    "wof:placetype":"venue"
},
  "geometry": {"coordinates":[150.760864258,-33.9888763428],"type":"Point"}
}