{
  "type": "Feature",
  "properties": {
    "addr:full":"PO Box 151 Oyster Bay NSW 2225",
    "addr:postcode":"2225",
    "iso:country":"AU",
    "sg:address":"PO Box 151",
    "sg:city":"Oyster Bay",
    "sg:classifiers":[
        {
            "category":"Utilities",
            "subcategory":"Electric",
            "type":"Services"
        }
    ],
    "sg:phone":"+61 418 114 576",
    "sg:postcode":"2225",
    "sg:province":"NSW",
    "sg:tags":[
        "electrical",
        "contractor"
    ],
    "wof:name":"Kaytech Electrical",
    "wof:placetype":"venue"
},
  "geometry": {"coordinates":[151.078323364,-34.0092391968],"type":"Point"}
}