{
  "type": "Feature",
  "properties": {
    "addr:full":"66 Kings St Perth WA 6000",
    "addr:housenumber":"66",
    "addr:postcode":"6000",
    "addr:street":"Kings St",
    "iso:country":"AU",
    "sg:address":"66 Kings St",
    "sg:city":"Perth",
    "sg:classifiers":[
        {
            "category":"Shopping",
            "subcategory":"Party Supplies",
            "type":"Retail Goods"
        }
    ],
    "sg:phone":"+61 8 9486 8366",
    "sg:postcode":"6000",
    "sg:province":"WA",
    "sg:tags":[
        "hire",
        "costume"
    ],
    "wof:name":"Aladdin's Cave Costume Hire",
    "wof:placetype":"venue"
},
  "geometry": {"coordinates":[115.85546875,-31.9515857697],"type":"Point"}
}