{
  "type": "Feature",
  "properties": {
    "addr:full":"25 Linlithgow St Mitcham VIC 3132",
    "addr:housenumber":"25",
    "addr:postcode":"3132",
    "addr:street":"Linlithgow St",
    "iso:country":"AU",
    "sg:address":"25 Linlithgow St",
    "sg:city":"Mitcham",
    "sg:classifiers":[
        {
            "category":"Building & Trades",
            "subcategory":"Landscaping Services",
            "type":"Services"
        }
    ],
    "sg:phone":"+61 3 9874 4126",
    "sg:postcode":"3132",
    "sg:province":"VIC",
    "sg:tags":[
        "designer",
        "landscape",
        "contractor"
    ],
    "wof:name":"Armadillo Excavations",
    "wof:placetype":"venue"
},
  "geometry": {"coordinates":[145.20509338400001,-37.8217048645],"type":"Point"}
}