{
  "type": "Feature",
  "properties": {
    "addr:full":"10 Elwin Drv Orange NSW 2800",
    "addr:housenumber":"10",
    "addr:postcode":"2800",
    "addr:street":"Elwin Drv",
    "iso:country":"AU",
    "sg:address":"10 Elwin Drv",
    "sg:city":"Orange",
    "sg:classifiers":[
        {
            "category":"Home & Garden",
            "subcategory":"Furniture",
            "type":"Retail Goods"
        }
    ],
    "sg:phone":"+61 2 6362 3530",
    "sg:postcode":"2800",
    "sg:province":"NSW",
    "sg:tags":[
        "business"
    ],
    "wof:name":"Q OFFICE FURNITURE",
    "wof:placetype":"venue"
},
  "geometry": {"coordinates":[149.105712891,-33.2853164673],"type":"Point"}
}