{
  "type": "Feature",
  "properties": {
    "addr:full":"1 Rex Crt Noble Park VIC 3174",
    "addr:housenumber":"1",
    "addr:postcode":"3174",
    "addr:street":"Rex Crt",
    "iso:country":"AU",
    "sg:address":"1 Rex Crt",
    "sg:city":"Noble Park",
    "sg:classifiers":[
        {
            "category":"Utilities",
            "subcategory":"Electric",
            "type":"Services"
        }
    ],
    "sg:phone":"+61 3 9558 5276",
    "sg:postcode":"3174",
    "sg:province":"VIC",
    "sg:tags":[
        "electrical",
        "contractor"
    ],
    "wof:name":"Noble Park Electrical Services",
    "wof:placetype":"venue"
},
  "geometry": {"coordinates":[145.175384522,-37.9755096436],"type":"Point"}
}