{
  "type": "Feature",
  "properties": {
    "addr:full":"185 Herston Rd Herston QLD 4006",
    "addr:housenumber":"185",
    "addr:postcode":"4006",
    "addr:street":"Herston Rd",
    "iso:country":"AU",
    "sg:address":"185 Herston Rd",
    "sg:city":"Herston",
    "sg:classifiers":[
        {
            "category":"Social Services",
            "subcategory":"Child Care",
            "type":"Services"
        }
    ],
    "sg:phone":"+61 7 3252 5059",
    "sg:postcode":"4006",
    "sg:province":"QLD",
    "wof:name":"Kelvin Grove Community Childcare Centre",
    "wof:placetype":"venue"
},
  "geometry": {"coordinates":[153.02702331500001,-27.4498157501],"type":"Point"}
}