{
  "type": "Feature",
  "properties": {
    "iso:country":"AU",
    "sg:address":"PO Box 7148, St",
    "sg:city":"Kilda Rd, Melbourne, 8004 Melbourne",
    "sg:classifiers":[
        {
            "category":"Shopping",
            "subcategory":"Jewelry",
            "type":"Retail Goods"
        }
    ],
    "sg:phone":"+61 411 518 140",
    "sg:postcode":"8004",
    "sg:province":"VIC",
    "sg:tags":[
        "merchant",
        "gem"
    ],
    "wof:name":"The Emerald Mine",
    "wof:placetype":"venue"
},
  "geometry": {"coordinates":[144.96751403799999,-37.8176269531],"type":"Point"}
}