{
  "type": "Feature",
  "properties": {
    "addr:full":"8 Stewart St South Brighton SA 5048",
    "addr:housenumber":"8",
    "addr:postcode":"5048",
    "addr:street":"Stewart St South",
    "iso:country":"AU",
    "sg:address":"8 Stewart St",
    "sg:city":"South Brighton",
    "sg:classifiers":[
        {
            "category":"Building & Trades",
            "subcategory":"Construction",
            "type":"Services"
        }
    ],
    "sg:phone":"+61 8 8298 1871",
    "sg:postcode":"5048",
    "sg:province":"SA",
    "sg:tags":[
        "roof"
    ],
    "wof:name":"B C Bax Roofing",
    "wof:placetype":"venue"
},
  "geometry": {"coordinates":[138.52844200000001,-35.027142],"type":"Point"}
}