{
  "type": "Feature",
  "properties": {
    "addr:full":"9 Hynes Crt Mildura VIC 3500",
    "addr:housenumber":"9",
    "addr:postcode":"3500",
    "addr:street":"Hynes Crt",
    "iso:country":"AU",
    "sg:address":"9 Hynes Crt",
    "sg:city":"Mildura",
    "sg:classifiers":[
        {
            "category":"Home & Garden",
            "subcategory":"Furniture",
            "type":"Retail Goods"
        }
    ],
    "sg:phone":"+61 3 5023 6461",
    "sg:postcode":"3500",
    "sg:province":"VIC",
    "sg:tags":[
        "business"
    ],
    "wof:name":"Balcombes Joinery",
    "wof:placetype":"venue"
},
  "geometry": {"coordinates":[142.17379760700001,-34.1936264038],"type":"Point"}
}