{
  "type": "Feature",
  "properties": {
    "addr:full":"Unit 4 21 Windorah St Stafford QLD 4053",
    "addr:housenumber":"21",
    "addr:postcode":"4053",
    "addr:street":"Windorah St",
    "iso:country":"AU",
    "sg:address":"Unit 4 21 Windorah St",
    "sg:city":"Stafford",
    "sg:classifiers":[
        {
            "category":"Communications",
            "type":"Services"
        }
    ],
    "sg:phone":"+61 7 3856 4188",
    "sg:postcode":"4053",
    "sg:province":"QLD",
    "sg:tags":[
        "data"
    ],
    "wof:name":"Allied Systems Pty Ltd",
    "wof:placetype":"venue"
},
  "geometry": {"coordinates":[153.010955811,-27.4109363556],"type":"Point"}
}