{
  "type": "Feature",
  "properties": {
    "addr:full":"Simpson St Mt Isa QLD 4825",
    "addr:postcode":"4825",
    "addr:street":"Simpson St",
    "iso:country":"AU",
    "sg:address":"Simpson St",
    "sg:city":"Mt Isa",
    "sg:classifiers":[
        {
            "category":"Food & Beverages",
            "subcategory":"Supermarket",
            "type":"Retail Goods"
        }
    ],
    "sg:phone":"+61 7 4743 6033",
    "sg:postcode":"4825",
    "sg:province":"QLD",
    "sg:tags":[
        "grocery",
        "store"
    ],
    "wof:name":"K Mart Australia Ltd",
    "wof:placetype":"venue"
},
  "geometry": {"coordinates":[139.493988,-20.729208],"type":"Point"}
}