{
  "type": "Feature",
  "properties": {
    "iso:country":"AU",
    "sg:address":"35 Glenferrie Rd",
    "sg:city":"Malvern",
    "sg:classifiers":[
        {
            "category":"Health Services",
            "subcategory":"Health Practitioner",
            "type":"Services"
        }
    ],
    "sg:phone":"+61 401 161 376",
    "sg:postcode":"3144",
    "sg:province":"VIC",
    "sg:tags":[
        "osteopath"
    ],
    "wof:name":"Body Of Osteopathy",
    "wof:placetype":"venue"
},
  "geometry": {"coordinates":[145.02789306599999,-37.8641014099],"type":"Point"}
}