{
  "type": "Feature",
  "properties": {
    "addr:full":"3 Glenbrae Crt Bannockburn VIC 3331",
    "addr:housenumber":"3",
    "addr:postcode":"3331",
    "addr:street":"Glenbrae Crt",
    "iso:country":"AU",
    "sg:address":"3 Glenbrae Crt",
    "sg:city":"Bannockburn",
    "sg:classifiers":[
        {
            "category":"Utilities",
            "type":"Services"
        }
    ],
    "sg:phone":"+61 3 5281 1866",
    "sg:postcode":"3331",
    "sg:province":"VIC",
    "sg:tags":[
        "refrigeration",
        "industrial",
        "commercial",
        "retail"
    ],
    "wof:name":"Sureseal",
    "wof:placetype":"venue"
},
  "geometry": {"coordinates":[144.16435200000001,-38.056149],"type":"Point"}
}