{
  "type": "Feature",
  "properties": {
    "addr:full":"84 Ring Rd Townsville QLD 4810",
    "addr:housenumber":"84",
    "addr:postcode":"4810",
    "addr:street":"Ring Rd",
    "iso:country":"AU",
    "sg:address":"84 Ring Rd",
    "sg:city":"Townsville",
    "sg:classifiers":[
        {
            "category":"Building & Trades",
            "subcategory":"Equipment Rental",
            "type":"Services"
        }
    ],
    "sg:phone":"+61 7 4788 8249",
    "sg:postcode":"4810",
    "sg:province":"QLD",
    "sg:tags":[
        "hire",
        "catering"
    ],
    "wof:name":"Robinson Catering Services",
    "wof:placetype":"venue"
},
  "geometry": {"coordinates":[146.762024,-19.317938],"type":"Point"}
}