{
  "type": "Feature",
  "properties": {
    "addr:full":"160 Ruddle Drv Maleny QLD 4552",
    "addr:housenumber":"160",
    "addr:postcode":"4552",
    "addr:street":"Ruddle Drv",
    "iso:country":"AU",
    "sg:address":"160 Ruddle Drv",
    "sg:city":"Maleny",
    "sg:classifiers":[
        {
            "category":"Professional",
            "subcategory":"Secretarial Services",
            "type":"Services"
        }
    ],
    "sg:phone":"+61 7 5494 3677",
    "sg:postcode":"4552",
    "sg:province":"QLD",
    "sg:tags":[
        "typing"
    ],
    "wof:name":"Top Notch Business Services",
    "wof:placetype":"venue"
},
  "geometry": {"coordinates":[152.84872436500001,-26.7579441071],"type":"Point"}
}