{
  "type": "Feature",
  "properties": {
    "addr:full":"Shop 151 Ground Level Westfield Shopping Ctr Burwood NSW 2134",
    "addr:postcode":"2134",
    "addr:street":"Shopping Ctr",
    "iso:country":"AU",
    "sg:address":"Shop 151 Ground Level Westfield Shopping Ctr",
    "sg:city":"Burwood",
    "sg:classifiers":[
        {
            "category":"Shopping",
            "subcategory":"Mobile Phones",
            "type":"Retail Goods"
        }
    ],
    "sg:phone":"+61 2 8753 3303",
    "sg:postcode":"2134",
    "sg:province":"NSW",
    "sg:tags":[
        "telephone",
        "accessory"
    ],
    "wof:name":"Vodafone Burwood",
    "wof:placetype":"venue"
},
  "geometry": {"coordinates":[151.103515625,-33.8781585693],"type":"Point"}
}