{
  "type": "Feature",
  "properties": {
    "iso:country":"AU",
    "sg:address":"8 Wollong St",
    "sg:city":"Gosford North",
    "sg:classifiers":[
        {
            "category":"Professional",
            "subcategory":"Engineering",
            "type":"Services"
        }
    ],
    "sg:phone":"+61 2 4323 4051",
    "sg:postcode":"2250",
    "sg:province":"NSW",
    "sg:tags":[
        "engineer"
    ],
    "wof:name":"Taylor Made Fibreglass Products",
    "wof:placetype":"venue"
},
  "geometry": {"coordinates":[151.342453003,-33.411315918],"type":"Point"}
}