{
  "type": "Feature",
  "properties": {
    "addr:full":"Level 12, 15 London Cct Canberra ACT 2600",
    "addr:housenumber":"15",
    "addr:postcode":"2600",
    "addr:street":"London Cct",
    "iso:country":"AU",
    "sg:address":"Level 12, 15",
    "sg:city":"London Cct Canberra",
    "sg:classifiers":[
        {
            "category":"Professional",
            "subcategory":"Employment Agencies",
            "type":"Services"
        }
    ],
    "sg:phone":"+61 2 6245 2985",
    "sg:postcode":"2600",
    "sg:province":"ACT",
    "wof:name":"Tanner Menzies",
    "wof:placetype":"venue"
},
  "geometry": {"coordinates":[149.12611389200001,-35.2809181213],"type":"Point"}
}