{
  "type": "Feature",
  "properties": {
    "addr:full":"170 Cambridge St West Leederville WA 6007",
    "addr:housenumber":"170",
    "addr:postcode":"6007",
    "addr:street":"Cambridge St West",
    "iso:country":"AU",
    "sg:address":"170 Cambridge St",
    "sg:city":"West Leederville",
    "sg:classifiers":[
        {
            "category":"Health Services",
            "subcategory":"Chiropractor",
            "type":"Services"
        }
    ],
    "sg:phone":"+61 8 9388 0823",
    "sg:postcode":"6007",
    "sg:province":"WA",
    "wof:name":"Bramley Lance",
    "wof:placetype":"venue"
},
  "geometry": {"coordinates":[115.82579803500001,-31.9405860901],"type":"Point"}
}