{
  "type": "Feature",
  "properties": {
    "addr:full":"22 Willaura Drv Coominya QLD 4311",
    "addr:housenumber":"22",
    "addr:postcode":"4311",
    "addr:street":"Willaura Drv",
    "iso:country":"AU",
    "sg:address":"22 Willaura Drv",
    "sg:city":"Coominya",
    "sg:classifiers":[
        {
            "category":"Military Area",
            "subcategory":"Air Force Base",
            "type":"Public Place"
        }
    ],
    "sg:phone":"+61 7 5426 4676",
    "sg:postcode":"4311",
    "sg:province":"QLD",
    "sg:tags":[
        "conditioner",
        "treatment",
        "soil"
    ],
    "wof:name":"Way To Go Fertilisers",
    "wof:placetype":"venue"
},
  "geometry": {"coordinates":[152.42416381800001,-27.3407611847],"type":"Point"}
}