{
  "type": "Feature",
  "properties": {
    "addr:full":"106 Bolwarra Park Drv Bolwarra Heights NSW 2320",
    "addr:housenumber":"106",
    "addr:postcode":"2320",
    "addr:street":"Bolwarra Park Drv",
    "iso:country":"AU",
    "sg:address":"106 Bolwarra Park Drv",
    "sg:city":"Bolwarra Heights",
    "sg:classifiers":[
        {
            "category":"Real Estate",
            "subcategory":"Developer",
            "type":"Services"
        }
    ],
    "sg:phone":"+61 2 4930 6876",
    "sg:postcode":"2320",
    "sg:province":"NSW",
    "sg:tags":[
        "development"
    ],
    "wof:name":"Forest Ridge Estate",
    "wof:placetype":"venue"
},
  "geometry": {"coordinates":[151.57675170900001,-32.6916007996],"type":"Point"}
}