{
  "type": "Feature",
  "properties": {
    "addr:full":"157 Sailors Bay Rd Northbridge NSW 2063",
    "addr:housenumber":"157",
    "addr:postcode":"2063",
    "addr:street":"Sailors Bay Rd",
    "iso:country":"AU",
    "sg:address":"157 Sailors Bay Rd",
    "sg:city":"Northbridge",
    "sg:classifiers":[
        {
            "category":"Arts & Performance",
            "subcategory":"Art Gallery",
            "type":"Entertainment"
        }
    ],
    "sg:phone":"+61 2 9967 9040",
    "sg:postcode":"2063",
    "sg:province":"NSW",
    "wof:name":"Bridge Gallery The",
    "wof:placetype":"venue"
},
  "geometry": {"coordinates":[151.211669922,-33.8108291626],"type":"Point"}
}