{
  "type": "Feature",
  "properties": {
    "addr:full":"2/ 277 Mann St Gosford NSW 2250",
    "addr:housenumber":"/ 277",
    "addr:postcode":"2250",
    "addr:street":"Mann St",
    "iso:country":"AU",
    "sg:address":"2/ 277 Mann St",
    "sg:city":"Gosford",
    "sg:classifiers":[
        {
            "category":"Professional",
            "subcategory":"Employment Agencies",
            "type":"Services"
        }
    ],
    "sg:phone":"+61 2 4322 4155",
    "sg:postcode":"2250",
    "sg:province":"NSW",
    "wof:name":"Centre Staffing",
    "wof:placetype":"venue"
},
  "geometry": {"coordinates":[151.342987061,-33.4220962524],"type":"Point"}
}