{
  "type": "Feature",
  "properties": {
    "addr:full":"12 Talbot Rd Hazelbrook NSW 2779",
    "addr:housenumber":"12",
    "addr:postcode":"2779",
    "addr:street":"Talbot Rd",
    "iso:country":"AU",
    "sg:address":"12 Talbot Rd",
    "sg:city":"Hazelbrook",
    "sg:classifiers":[
        {
            "category":"Shopping",
            "type":"Retail Goods"
        }
    ],
    "sg:phone":"+61 2 4758 7327",
    "sg:postcode":"2779",
    "sg:province":"NSW",
    "sg:tags":[
        "equipment",
        "safety",
        "accessory"
    ],
    "wof:name":"Mid Mountains Optical Service",
    "wof:placetype":"venue"
},
  "geometry": {"coordinates":[150.45863342300001,-33.7227249146],"type":"Point"}
}