{
  "type": "Feature",
  "properties": {
    "iso:country":"AU",
    "sg:address":"17a Albert St",
    "sg:city":"Harbord",
    "sg:classifiers":[
        {
            "category":"Shopping",
            "subcategory":"Computers & Home Electronics",
            "type":"Retail Goods"
        }
    ],
    "sg:phone":"+61 2 9905 6437",
    "sg:postcode":"2096",
    "sg:province":"NSW",
    "sg:tags":[
        "equipment",
        "supply"
    ],
    "wof:name":"Lazarus Imaging",
    "wof:placetype":"venue"
},
  "geometry": {"coordinates":[151.28619384800001,-33.7784957886],"type":"Point"}
}