{
  "type": "Feature",
  "properties": {
    "addr:full":"33 Gertz Ave Reservoir VIC 3073",
    "addr:housenumber":"33",
    "addr:postcode":"3073",
    "addr:street":"Gertz Ave",
    "iso:country":"AU",
    "sg:address":"33 Gertz Ave",
    "sg:city":"Reservoir",
    "sg:classifiers":[
        {
            "category":"Home & Garden",
            "subcategory":"Carpets & Floor Coverings",
            "type":"Retail Goods"
        }
    ],
    "sg:phone":"+61 418 344 125",
    "sg:postcode":"3073",
    "sg:province":"VIC",
    "sg:tags":[
        "tile",
        "wall",
        "layer"
    ],
    "wof:name":"A & J Gabriele Tiling Co",
    "wof:placetype":"venue"
},
  "geometry": {"coordinates":[145.03364563,-37.6994476318],"type":"Point"}
}