{
  "type": "Feature",
  "properties": {
    "iso:country":"AU",
    "sg:address":"80 Harvester Rd",
    "sg:city":"Sunshine",
    "sg:classifiers":[
        {
            "category":"Personal",
            "subcategory":"Beauty Salon",
            "type":"Services"
        }
    ],
    "sg:phone":"+61 3 9364 8988",
    "sg:postcode":"3020",
    "sg:province":"VIC",
    "sg:tags":[
        "hairdresser"
    ],
    "wof:name":"Lindy Hair & Beauty",
    "wof:placetype":"venue"
},
  "geometry": {"coordinates":[144.82917800000001,-37.782871],"type":"Point"}
}