{
  "type": "Feature",
  "properties": {
    "iso:country":"AU",
    "sg:address":"38 Paten Rd",
    "sg:city":"The Gap",
    "sg:classifiers":[
        {
            "category":"Building & Trades",
            "subcategory":"Plumbing",
            "type":"Services"
        }
    ],
    "sg:phone":"+61 411 330 394",
    "sg:postcode":"4061",
    "sg:province":"QLD",
    "sg:tags":[
        "plumber",
        "gasfitters"
    ],
    "wof:name":"Cains Plumbing Service",
    "wof:placetype":"venue"
},
  "geometry": {"coordinates":[152.94114685100001,-27.4476032257],"type":"Point"}
}