{
  "type": "Feature",
  "properties": {
    "iso:country":"AU",
    "sg:address":"18 Green St",
    "sg:city":"Brookvale",
    "sg:classifiers":[
        {
            "category":"Retail",
            "subcategory":"Auto Rental",
            "type":"Services"
        }
    ],
    "sg:phone":"+61 1800 352 516",
    "sg:postcode":"2100",
    "sg:province":"NSW",
    "sg:tags":[
        "car",
        "hire",
        "minibus"
    ],
    "wof:name":"Auto Car & Campervan Rental Centre",
    "wof:placetype":"venue"
},
  "geometry": {"coordinates":[151.267410278,-33.7641181946],"type":"Point"}
}