{
  "type": "Feature",
  "properties": {
    "addr:full":"27 William St Earlwood NSW 2206",
    "addr:housenumber":"27",
    "addr:postcode":"2206",
    "addr:street":"William St",
    "iso:country":"AU",
    "sg:address":"27 William St",
    "sg:city":"Earlwood",
    "sg:classifiers":[
        {
            "category":"Fast Food",
            "type":"Food & Drink"
        }
    ],
    "sg:phone":"+61 2 9789 4144",
    "sg:postcode":"2206",
    "sg:province":"NSW",
    "sg:tags":[
        "away",
        "take"
    ],
    "wof:name":"KFC",
    "wof:placetype":"venue"
},
  "geometry": {"coordinates":[151.12335200000001,-33.927105],"type":"Point"}
}