{
  "type": "Feature",
  "properties": {
    "iso:country":"AU",
    "sg:address":"41 Manor Hill Cl",
    "sg:city":"Holgate",
    "sg:classifiers":[
        {
            "category":"Building & Trades",
            "subcategory":"Construction",
            "type":"Services"
        }
    ],
    "sg:phone":"+61 2 4367 6753",
    "sg:postcode":"2250",
    "sg:province":"NSW",
    "sg:tags":[
        "joiner",
        "carpenter"
    ],
    "wof:name":"Board M D & P J",
    "wof:placetype":"venue"
},
  "geometry": {"coordinates":[151.406524658,-33.4019012451],"type":"Point"}
}