{
  "type": "Feature",
  "properties": {
    "iso:country":"AU",
    "sg:address":"2 Faraday Rd",
    "sg:city":"Padstow",
    "sg:classifiers":[
        {
            "category":"Real Estate",
            "subcategory":"Real Estate Agent",
            "type":"Services"
        }
    ],
    "sg:phone":"+61 2 9771 4555",
    "sg:postcode":"2211",
    "sg:province":"NSW",
    "wof:name":"Professionals Chambers Flemming",
    "wof:placetype":"venue"
},
  "geometry": {"coordinates":[151.03401199999999,-33.953575],"type":"Point"}
}