{
  "type": "Feature",
  "properties": {
    "addr:full":"18 Main Rd Moonah TAS 7009",
    "addr:housenumber":"18",
    "addr:postcode":"7009",
    "addr:street":"Main Rd",
    "iso:country":"AU",
    "sg:address":"18 Main Rd",
    "sg:city":"Moonah",
    "sg:classifiers":[
        {
            "category":"Wholesale",
            "subcategory":"Medical Equipment & Supplies",
            "type":"Manufacturing & Wholesale Goods"
        }
    ],
    "sg:phone":"+61 3 6278 2189",
    "sg:postcode":"7009",
    "sg:province":"TAS",
    "sg:tags":[
        "aids",
        "hearing"
    ],
    "wof:name":"Helping Hearing",
    "wof:placetype":"venue"
},
  "geometry": {"coordinates":[147.29734802199999,-42.8500938416],"type":"Point"}
}