{
  "type": "Feature",
  "properties": {
    "addr:full":"Grd Flr, 50 Cleveland St Stones Corner QLD 4120",
    "addr:postcode":"4120",
    "addr:street":"Grd;Cleveland St",
    "iso:country":"AU",
    "sg:address":"Grd Flr, 50 Cleveland St",
    "sg:city":"Stones Corner",
    "sg:classifiers":[
        {
            "category":"Banks & Credit Unions",
            "subcategory":"Financial Services",
            "type":"Services"
        }
    ],
    "sg:phone":"+61 7 3847 3044",
    "sg:postcode":"4120",
    "sg:province":"QLD",
    "sg:tags":[
        "planning"
    ],
    "wof:name":"Genesys Wealth Advisers",
    "wof:placetype":"venue"
},
  "geometry": {"coordinates":[153.04403686500001,-27.4993877411],"type":"Point"}
}