{
  "type": "Feature",
  "properties": {
    "addr:full":"7 Grant Ave Toorak VIC 3142",
    "addr:housenumber":"7",
    "addr:postcode":"3142",
    "addr:street":"Grant Ave",
    "iso:country":"AU",
    "sg:address":"7 Grant Ave",
    "sg:city":"Toorak",
    "sg:classifiers":[
        {
            "category":"Professional",
            "subcategory":"Computer Services",
            "type":"Services"
        }
    ],
    "sg:phone":"+61 500 554 432",
    "sg:postcode":"3142",
    "sg:province":"VIC",
    "sg:tags":[
        "package",
        "software"
    ],
    "wof:name":"Peak Systems Solutions",
    "wof:placetype":"venue"
},
  "geometry": {"coordinates":[145.017669678,-37.8464584351],"type":"Point"}
}