{
  "type": "Feature",
  "properties": {
    "addr:full":"14 Burwood Rd Burwood NSW 2134",
    "addr:housenumber":"14",
    "addr:postcode":"2134",
    "addr:street":"Burwood Rd",
    "iso:country":"AU",
    "sg:address":"14 Burwood Rd",
    "sg:city":"Burwood",
    "sg:classifiers":[
        {
            "category":"Health Services",
            "subcategory":"Dentist",
            "type":"Services"
        }
    ],
    "sg:phone":"+61 2 9747 1988",
    "sg:postcode":"2134",
    "sg:province":"NSW",
    "wof:name":"Kwan Leonard",
    "wof:placetype":"venue"
},
  "geometry": {"coordinates":[151.10531616200001,-33.8698883057],"type":"Point"}
}