{
  "type": "Feature",
  "properties": {
    "addr:full":"630 Murray St Perth WA 6000",
    "addr:housenumber":"630",
    "addr:postcode":"6000",
    "addr:street":"Murray St",
    "iso:country":"AU",
    "sg:address":"630 Murray St",
    "sg:city":"Perth",
    "sg:classifiers":[
        {
            "category":"Shopping",
            "subcategory":"Mobile Phones",
            "type":"Retail Goods"
        }
    ],
    "sg:phone":"+61 1300 138 030",
    "sg:postcode":"6000",
    "sg:province":"WA",
    "sg:tags":[
        "telephone",
        "accessory"
    ],
    "sg:website":"http://www.mpia.com.au",
    "wof:name":"Mobile Phone Installations Australia",
    "wof:placetype":"venue"
},
  "geometry": {"coordinates":[115.85925293,-31.9531364441],"type":"Point"}
}