{
  "type": "Feature",
  "properties": {
    "iso:country":"AU",
    "sg:address":"139 Woolooware Rd",
    "sg:city":"Cronulla",
    "sg:classifiers":[
        {
            "category":"Food & Beverages",
            "subcategory":"Fruits & Vegetables",
            "type":"Retail Goods"
        }
    ],
    "sg:phone":"+61 2 9523 8008",
    "sg:postcode":"2230",
    "sg:province":"NSW",
    "sg:tags":[
        "greengrocer",
        "fruiterer"
    ],
    "wof:name":"Burraneer Fruit Market",
    "wof:placetype":"venue"
},
  "geometry": {"coordinates":[151.13995361299999,-34.0543708801],"type":"Point"}
}