{
  "type": "Feature",
  "properties": {
    "addr:full":"116 Newcastle Rd Wallsend NSW 2287",
    "addr:housenumber":"116",
    "addr:postcode":"2287",
    "addr:street":"Newcastle Rd",
    "iso:country":"AU",
    "sg:address":"116 Newcastle Rd",
    "sg:city":"Wallsend",
    "sg:classifiers":[
        {
            "category":"Wholesale",
            "subcategory":"Scrap",
            "type":"Manufacturing & Wholesale Goods"
        }
    ],
    "sg:phone":"+61 2 4955 8712",
    "sg:postcode":"2287",
    "sg:province":"NSW",
    "sg:tags":[
        "merchant",
        "metal"
    ],
    "wof:name":"Nonferral (NSW) Pty Ltd",
    "wof:placetype":"venue"
},
  "geometry": {"coordinates":[151.684204102,-32.9036903381],"type":"Point"}
}