{
  "type": "Feature",
  "properties": {
    "iso:country":"AU",
    "sg:address":"20 Low St",
    "sg:city":"Yandina",
    "sg:classifiers":[
        {
            "category":"Education",
            "subcategory":"Kindergarten",
            "type":"Public Place"
        }
    ],
    "sg:phone":"+61 7 5472 7000",
    "sg:postcode":"4561",
    "sg:province":"QLD",
    "sg:tags":[
        "pre-schools"
    ],
    "wof:name":"Coolabah Early ChildHood Development Centres",
    "wof:placetype":"venue"
},
  "geometry": {"coordinates":[152.955276489,-26.5596427917],"type":"Point"}
}