{
  "type": "Feature",
  "properties": {
    "iso:country":"AU",
    "sg:address":"Doncaster East Rd",
    "sg:city":"Mitcham",
    "sg:classifiers":[
        {
            "category":"Health Services",
            "subcategory":"Doctor",
            "type":"Services"
        }
    ],
    "sg:phone":"+61 3 9210 3146",
    "sg:postcode":"3132",
    "sg:province":"VIC",
    "sg:tags":[
        "medical",
        "practitioner"
    ],
    "wof:name":"Stelmach Wanda.S.",
    "wof:placetype":"venue"
},
  "geometry": {"coordinates":[145.196334839,-37.8156242371],"type":"Point"}
}