{
  "type": "Feature",
  "properties": {
    "iso:country":"AU",
    "sg:address":"50 Sutherland St",
    "sg:city":"Mascot",
    "sg:classifiers":[
        {
            "category":"Professional",
            "subcategory":"Detective & Security Services",
            "type":"Services"
        }
    ],
    "sg:phone":"+61 2 9667 1144",
    "sg:postcode":"2020",
    "sg:province":"NSW",
    "sg:tags":[
        "investigator"
    ],
    "wof:name":"A.B.L.E. Investigations Pty Ltd",
    "wof:placetype":"venue"
},
  "geometry": {"coordinates":[151.200897217,-33.9253196716],"type":"Point"}
}