{
  "type": "Feature",
  "properties": {
    "addr:full":"795 Canning Hwy Applecross WA 6153",
    "addr:housenumber":"795",
    "addr:postcode":"6153",
    "addr:street":"Canning Hwy",
    "iso:country":"AU",
    "sg:address":"795 Canning Hwy",
    "sg:city":"Applecross",
    "sg:classifiers":[
        {
            "category":"Restaurant",
            "type":"Food & Drink"
        }
    ],
    "sg:phone":"+61 8 9316 2111",
    "sg:postcode":"6153",
    "sg:province":"WA",
    "wof:name":"Bridge Cafe The",
    "wof:placetype":"venue"
},
  "geometry": {"coordinates":[115.835999,-32.019398],"type":"Point"}
}