{
  "type": "Feature",
  "properties": {
    "iso:country":"AU",
    "sg:address":"Lot 2 Hazelwood Crt",
    "sg:city":"Cannonvale",
    "sg:classifiers":[
        {
            "category":"Social Services",
            "subcategory":"Child Care",
            "type":"Services"
        }
    ],
    "sg:phone":"+61 7 4946 5609",
    "sg:postcode":"4802",
    "sg:province":"QLD",
    "wof:name":"Scallywags Limited Hours Child Care",
    "wof:placetype":"venue"
},
  "geometry": {"coordinates":[148.69757080100001,-20.2800254822],"type":"Point"}
}