{
  "type": "Feature",
  "properties": {
    "addr:full":"530 Ghazeepore Rd Freshwater Creek VIC 3216",
    "addr:housenumber":"530",
    "addr:postcode":"3216",
    "addr:street":"Ghazeepore Rd",
    "iso:country":"AU",
    "sg:address":"530 Ghazeepore Rd",
    "sg:city":"Freshwater Creek",
    "sg:classifiers":[
        {
            "category":"Utilities",
            "subcategory":"Water",
            "type":"Services"
        }
    ],
    "sg:phone":"+61 3 5264 5131",
    "sg:postcode":"3216",
    "sg:province":"VIC",
    "sg:tags":[
        "cartage"
    ],
    "wof:name":"W. Larcombe & Sons",
    "wof:placetype":"venue"
},
  "geometry": {"coordinates":[144.29437255900001,-38.2524757385],"type":"Point"}
}