{
  "type": "Feature",
  "properties": {
    "addr:full":"109 Goodwood Rd Goodwood SA 5034",
    "addr:housenumber":"109",
    "addr:postcode":"5034",
    "addr:street":"Goodwood Rd",
    "iso:country":"AU",
    "sg:address":"109 Goodwood Rd",
    "sg:city":"Goodwood",
    "sg:classifiers":[
        {
            "category":"Shopping",
            "subcategory":"Shoes",
            "type":"Retail Goods"
        }
    ],
    "sg:phone":"+61 8 8272 9092",
    "sg:postcode":"5034",
    "sg:province":"SA",
    "sg:tags":[
        "footwear"
    ],
    "wof:name":"Goodwood Shoes",
    "wof:placetype":"venue"
},
  "geometry": {"coordinates":[138.58978271500001,-34.9511260986],"type":"Point"}
}