{
  "type": "Feature",
  "properties": {
    "iso:country":"AU",
    "sg:address":"2/ 2 Acacia St",
    "sg:city":"Yarrawonga",
    "sg:classifiers":[
        {
            "category":"Social Services",
            "subcategory":"Adult Care",
            "type":"Services"
        }
    ],
    "sg:phone":"+61 3 5743 1844",
    "sg:postcode":"3730",
    "sg:province":"VIC",
    "sg:tags":[
        "towing"
    ],
    "wof:name":"Ultimate Towing",
    "wof:placetype":"venue"
},
  "geometry": {"coordinates":[145.99874877900001,-36.0263900757],"type":"Point"}
}