{
  "type": "Feature",
  "properties": {
    "addr:full":"25 Earl St Kingaroy QLD 4610",
    "addr:housenumber":"25",
    "addr:postcode":"4610",
    "addr:street":"Earl St",
    "iso:country":"AU",
    "sg:address":"25 Earl St",
    "sg:city":"Kingaroy",
    "sg:classifiers":[
        {
            "category":"Utilities",
            "subcategory":"Refuse",
            "type":"Services"
        }
    ],
    "sg:phone":"+61 7 4162 3948",
    "sg:postcode":"4610",
    "sg:province":"QLD",
    "sg:tags":[
        "remover",
        "rubbish"
    ],
    "wof:name":"Dial A Home Maintenance",
    "wof:placetype":"venue"
},
  "geometry": {"coordinates":[151.84260559099999,-26.5522956848],"type":"Point"}
}