{
  "type": "Feature",
  "properties": {
    "iso:country":"AU",
    "sg:address":"10 Allandale Rd",
    "sg:city":"Cessnock",
    "sg:classifiers":[
        {
            "category":"Communications",
            "subcategory":"Film & Video Production",
            "type":"Services"
        }
    ],
    "sg:phone":"+61 2 4991 1537",
    "sg:postcode":"2325",
    "sg:province":"NSW",
    "sg:tags":[
        "dvd",
        "library"
    ],
    "wof:name":"Video Ezy",
    "wof:placetype":"venue"
},
  "geometry": {"coordinates":[151.35562133799999,-32.8308258057],"type":"Point"}
}