{
  "type": "Feature",
  "properties": {
    "iso:country":"AU",
    "sg:address":"22 Dimboola Rd",
    "sg:city":"Horsham",
    "sg:classifiers":[
        {
            "category":"Travel",
            "subcategory":"Hotels & Motels",
            "type":"Entertainment"
        }
    ],
    "sg:phone":"+61 3 5382 5944",
    "sg:postcode":"3400",
    "sg:province":"VIC",
    "wof:name":"Motel Ploughmans Motor Inn",
    "wof:placetype":"venue"
},
  "geometry": {"coordinates":[142.19583129899999,-36.7099685669],"type":"Point"}
}