{
  "type": "Feature",
  "properties": {
    "addr:full":"74 High St Heathcote VIC 3523",
    "addr:housenumber":"74",
    "addr:postcode":"3523",
    "addr:street":"High St",
    "iso:country":"AU",
    "sg:address":"74 High St",
    "sg:city":"Heathcote",
    "sg:classifiers":[
        {
            "category":"Manufacturing",
            "subcategory":"Motor Vehicles & Parts",
            "type":"Manufacturing & Wholesale Goods"
        }
    ],
    "sg:phone":"+61 3 5433 2559",
    "sg:postcode":"3523",
    "sg:province":"VIC",
    "sg:tags":[
        "wholesaler",
        "cycle",
        "mfrs",
        "accessory"
    ],
    "wof:name":"Holeshot Sports Pty Ltd",
    "wof:placetype":"venue"
},
  "geometry": {"coordinates":[144.711884,-36.926697],"type":"Point"}
}