{
  "type": "Feature",
  "properties": {
    "addr:full":"1015 Manks Rd Dalmore VIC 3981",
    "addr:housenumber":"1015",
    "addr:postcode":"3981",
    "addr:street":"Manks Rd",
    "iso:country":"AU",
    "sg:address":"1015 Manks Rd",
    "sg:city":"Dalmore",
    "sg:classifiers":[
        {
            "category":"Retail",
            "subcategory":"Storage",
            "type":"Services"
        }
    ],
    "sg:phone":"+61 3 5998 8411",
    "sg:postcode":"3981",
    "sg:province":"VIC",
    "sg:tags":[
        "cold"
    ],
    "wof:name":"Dalmore Cold Stores",
    "wof:placetype":"venue"
},
  "geometry": {"coordinates":[145.43258667000001,-38.176902771],"type":"Point"}
}