{
  "type": "Feature",
  "properties": {
    "addr:full":"Shop 17, Terrace Shopping Centre, Brice Ave Mooroolbark VIC 3138",
    "addr:housenumber":"shop 17",
    "addr:postcode":"3138",
    "addr:street":"Terrace Shopping;Brice Ave",
    "iso:country":"AU",
    "sg:address":"Shop 17, Terrace Shopping Centre, Brice Ave",
    "sg:city":"Mooroolbark",
    "sg:classifiers":[
        {
            "category":"Shopping",
            "subcategory":"Jewelry",
            "type":"Retail Goods"
        }
    ],
    "sg:phone":"+61 3 9727 1171",
    "sg:postcode":"3138",
    "sg:province":"VIC",
    "sg:tags":[
        "jeweller"
    ],
    "wof:name":"Terrace Jewellers",
    "wof:placetype":"venue"
},
  "geometry": {"coordinates":[145.317626953,-37.7860603333],"type":"Point"}
}