{
  "type": "Feature",
  "properties": {
    "addr:full":"2 Homebush Drv Woodberry NSW 2322",
    "addr:housenumber":"2",
    "addr:postcode":"2322",
    "addr:street":"Homebush Drv",
    "iso:country":"AU",
    "sg:address":"2 Homebush Drv",
    "sg:city":"Woodberry",
    "sg:classifiers":[
        {
            "category":"Home & Garden",
            "subcategory":"Building Materials",
            "type":"Retail Goods"
        }
    ],
    "sg:phone":"+61 2 4964 1566",
    "sg:postcode":"2322",
    "sg:province":"NSW",
    "sg:tags":[
        "insulation"
    ],
    "wof:name":"A & C Classic Window Tinting",
    "wof:placetype":"venue"
},
  "geometry": {"coordinates":[151.678390503,-32.7910919189],"type":"Point"}
}