{
  "type": "Feature",
  "properties": {
    "iso:country":"AU",
    "sg:address":"17 Grevillea St",
    "sg:city":"Mt Gravatt East",
    "sg:classifiers":[
        {
            "category":"Professional",
            "subcategory":"Computer Services",
            "type":"Services"
        }
    ],
    "sg:phone":"+61 414 781 058",
    "sg:postcode":"4122",
    "sg:province":"QLD",
    "sg:tags":[
        "consultant",
        "system"
    ],
    "wof:name":"Informatix Pty Ltd",
    "wof:placetype":"venue"
},
  "geometry": {"coordinates":[153.09310913100001,-27.5214881897],"type":"Point"}
}