{
  "type": "Feature",
  "properties": {
    "addr:full":"29 Brisbane St Launceston TAS 7250",
    "addr:housenumber":"29",
    "addr:postcode":"7250",
    "addr:street":"Brisbane St",
    "iso:country":"AU",
    "sg:address":"29 Brisbane St",
    "sg:city":"Launceston",
    "sg:classifiers":[
        {
            "category":"Banks & Credit Unions",
            "subcategory":"Investment Brokerage",
            "type":"Services"
        }
    ],
    "sg:phone":"+61 3 6334 4900",
    "sg:postcode":"7250",
    "sg:province":"TAS",
    "sg:tags":[
        "share",
        "broker",
        "stock"
    ],
    "wof:name":"Bridges Personal Investment Services",
    "wof:placetype":"venue"
},
  "geometry": {"coordinates":[147.14295959500001,-41.4342727661],"type":"Point"}
}