{
  "type": "Feature",
  "properties": {
    "iso:country":"AU",
    "sg:address":"273 Bridge Rd",
    "sg:city":"Richmond",
    "sg:classifiers":[
        {
            "category":"Arena",
            "subcategory":"Sports Club",
            "type":"Entertainment"
        }
    ],
    "sg:phone":"+61 3 9427 0270",
    "sg:postcode":"3121",
    "sg:province":"VIC",
    "sg:tags":[
        "defence",
        "supply",
        "self",
        "instruction",
        "martial art"
    ],
    "sg:website":"http://www.dominance.com.au",
    "wof:name":"Dominance Mixed Martial Arts",
    "wof:placetype":"venue"
},
  "geometry": {"coordinates":[144.99871826200001,-37.8184013367],"type":"Point"}
}