{
  "type": "Feature",
  "properties": {
    "iso:country":"AU",
    "sg:address":"6 Easton Ave",
    "sg:city":"Seaford",
    "sg:classifiers":[
        {
            "category":"Retail",
            "subcategory":"Storage",
            "type":"Services"
        }
    ],
    "sg:phone":"+61 1800 507 501",
    "sg:postcode":"3198",
    "sg:province":"VIC",
    "sg:tags":[
        "removal",
        "furniture"
    ],
    "wof:name":"Regal Removals",
    "wof:placetype":"venue"
},
  "geometry": {"coordinates":[145.13389587399999,-38.1212310791],"type":"Point"}
}