{
  "type": "Feature",
  "properties": {
    "addr:full":"108 Drummond St North Ballarat VIC 3350",
    "addr:housenumber":"108",
    "addr:postcode":"3350",
    "addr:street":"Drummond St North",
    "iso:country":"AU",
    "sg:address":"108 Drummond St",
    "sg:city":"North Ballarat",
    "sg:classifiers":[
        {
            "category":"Professional",
            "subcategory":"Management & Consulting",
            "type":"Services"
        }
    ],
    "sg:phone":"+61 3 5331 1666",
    "sg:postcode":"3350",
    "sg:province":"VIC",
    "sg:tags":[
        "consultant",
        "educational"
    ],
    "wof:name":"Attention Reading & Learning Issues",
    "wof:placetype":"venue"
},
  "geometry": {"coordinates":[143.848206,-37.557533],"type":"Point"}
}