{
  "type": "Feature",
  "properties": {
    "addr:full":"Shp 2/ 1155 Canterbury Rd Punchbowl NSW 2196",
    "addr:housenumber":"/ 1155",
    "addr:postcode":"2196",
    "addr:street":"Canterbury Rd",
    "iso:country":"AU",
    "sg:address":"Shp 2/ 1155 Canterbury Rd",
    "sg:city":"Punchbowl",
    "sg:classifiers":[
        {
            "category":"Home & Garden",
            "subcategory":"Furniture",
            "type":"Retail Goods"
        }
    ],
    "sg:phone":"+61 2 9759 1738",
    "sg:postcode":"2196",
    "sg:province":"NSW",
    "sg:tags":[
        "business"
    ],
    "wof:name":"Minicost Office Furnitures",
    "wof:placetype":"venue"
},
  "geometry": {"coordinates":[151.053833,-33.931793],"type":"Point"}
}