{
  "type": "Feature",
  "properties": {
    "iso:country":"AU",
    "sg:address":"3 Douglas St",
    "sg:city":"Narrandera",
    "sg:classifiers":[
        {
            "category":"Autos & Motor Vehicles",
            "subcategory":"Auto Supplies",
            "type":"Retail Goods"
        }
    ],
    "sg:phone":"+61 2 6959 1887",
    "sg:postcode":"2700",
    "sg:province":"NSW",
    "sg:tags":[
        "battery",
        "automotive"
    ],
    "wof:name":"Beaurepaires",
    "wof:placetype":"venue"
},
  "geometry": {"coordinates":[146.55317688,-34.7445602417],"type":"Point"}
}