{
  "type": "Feature",
  "properties": {
    "iso:country":"AU",
    "sg:address":"Suite 202, 30 Fisher Rd",
    "sg:city":"Dee Why",
    "sg:classifiers":[
        {
            "category":"Professional",
            "subcategory":"Engineering",
            "type":"Services"
        }
    ],
    "sg:phone":"+61 2 9972 9578",
    "sg:postcode":"2099",
    "sg:province":"NSW",
    "sg:tags":[
        "consultant",
        "geotechnical",
        "engineer"
    ],
    "wof:name":"Crozier Geotechnical Consultants",
    "wof:placetype":"venue"
},
  "geometry": {"coordinates":[151.28480529800001,-33.7525482178],"type":"Point"}
}