{
  "type": "Feature",
  "properties": {
    "addr:full":"Shop6/ 51 Bulcock St Caloundra QLD 4551",
    "addr:postcode":"4551",
    "addr:street":"Bulcock St",
    "iso:country":"AU",
    "sg:address":"Shop6/ 51 Bulcock St",
    "sg:city":"Caloundra",
    "sg:classifiers":[
        {
            "category":"Shopping",
            "subcategory":"Clothing, Apparel, & Fashions",
            "type":"Retail Goods"
        }
    ],
    "sg:phone":"+61 7 5438 0544",
    "sg:postcode":"4551",
    "sg:province":"QLD",
    "sg:tags":[
        "boutique"
    ],
    "wof:name":"Champagne Charlie",
    "wof:placetype":"venue"
},
  "geometry": {"coordinates":[153.12933349599999,-26.8046474457],"type":"Point"}
}