{
  "type": "Feature",
  "properties": {
    "iso:country":"AU",
    "sg:address":"21- 23 Aerodrome Rd",
    "sg:city":"Caboolture",
    "sg:classifiers":[
        {
            "category":"Shopping",
            "subcategory":"Crafts & Fabrics",
            "type":"Retail Goods"
        }
    ],
    "sg:phone":"+61 7 5498 3588",
    "sg:postcode":"4510",
    "sg:province":"QLD",
    "sg:tags":[
        "florist",
        "supply"
    ],
    "wof:name":"Greenlea Concepts",
    "wof:placetype":"venue"
},
  "geometry": {"coordinates":[152.980957,-27.08386],"type":"Point"}
}