{
  "type": "Feature",
  "properties": {
    "iso:country":"AU",
    "sg:address":"275 Botany St",
    "sg:city":"Kingsford",
    "sg:classifiers":[
        {
            "category":"Education",
            "subcategory":"Special Training",
            "type":"Public Place"
        }
    ],
    "sg:phone":"+61 419 233 831",
    "sg:postcode":"2032",
    "sg:province":"NSW",
    "sg:tags":[
        "development"
    ],
    "wof:name":"Berger Training & Consulting",
    "wof:placetype":"venue"
},
  "geometry": {"coordinates":[151.23207092300001,-33.9303207397],"type":"Point"}
}