{
  "type": "Feature",
  "properties": {
    "addr:full":"8 Weller Pl Rydalmere NSW 2116",
    "addr:housenumber":"8",
    "addr:postcode":"2116",
    "addr:street":"Weller Pl",
    "iso:country":"AU",
    "sg:address":"8 Weller Pl",
    "sg:city":"Rydalmere",
    "sg:classifiers":[
        {
            "category":"Utilities",
            "subcategory":"Electric",
            "type":"Services"
        }
    ],
    "sg:phone":"+61 2 9898 0567",
    "sg:postcode":"2116",
    "sg:province":"NSW",
    "sg:tags":[
        "electrical",
        "contractor"
    ],
    "wof:name":"Johnson Electrical Services Pty Ltd",
    "wof:placetype":"venue"
},
  "geometry": {"coordinates":[151.03874206500001,-33.8072166443],"type":"Point"}
}