{
  "type": "Feature",
  "properties": {
    "addr:full":"118 Woodriff St Penrith NSW 2750",
    "addr:housenumber":"118",
    "addr:postcode":"2750",
    "addr:street":"Woodriff St",
    "iso:country":"AU",
    "sg:address":"118 Woodriff St",
    "sg:city":"Penrith",
    "sg:classifiers":[
        {
            "category":"Education",
            "subcategory":"Kindergarten",
            "type":"Public Place"
        }
    ],
    "sg:phone":"+61 2 4721 7168",
    "sg:postcode":"2750",
    "sg:province":"NSW",
    "sg:tags":[
        "pre-schools"
    ],
    "wof:name":"Nepean Tiny Tots",
    "wof:placetype":"venue"
},
  "geometry": {"coordinates":[150.69053649899999,-33.7605247498],"type":"Point"}
}