{
  "type": "Feature",
  "properties": {
    "addr:full":"New England Hwy Scone NSW 2337",
    "addr:postcode":"2337",
    "addr:street":"England Hwy",
    "iso:country":"AU",
    "sg:address":"New England Hwy",
    "sg:city":"Scone",
    "sg:classifiers":[
        {
            "category":"Farming",
            "subcategory":"Livestock Farm",
            "type":"Manufacturing & Wholesale Goods"
        }
    ],
    "sg:phone":"+61 2 6545 2808",
    "sg:postcode":"2337",
    "sg:province":"NSW",
    "sg:tags":[
        "breeder",
        "horse",
        "stud"
    ],
    "wof:name":"Flame Tree Stud Pty Ltd",
    "wof:placetype":"venue"
},
  "geometry": {"coordinates":[150.86781310999999,-32.0457267761],"type":"Point"}
}