{
  "type": "Feature",
  "properties": {
    "addr:full":"2 Monomeeth Drv Mitcham VIC 3132",
    "addr:housenumber":"2",
    "addr:postcode":"3132",
    "addr:street":"Monomeeth Drv",
    "iso:country":"AU",
    "sg:address":"2 Monomeeth Drv",
    "sg:city":"Mitcham",
    "sg:classifiers":[
        {
            "category":"Shopping",
            "subcategory":"Computers & Home Electronics",
            "type":"Retail Goods"
        }
    ],
    "sg:phone":"+61 3 9837 1510",
    "sg:postcode":"3132",
    "sg:province":"VIC",
    "sg:tags":[
        "hardware",
        "equipment"
    ],
    "wof:name":"Axon Computers",
    "wof:placetype":"venue"
},
  "geometry": {"coordinates":[145.20317077600001,-37.8166503906],"type":"Point"}
}