{
  "type": "Feature",
  "properties": {
    "iso:country":"AU",
    "sg:address":"1045 Doncaster Rd",
    "sg:city":"Doncaster East",
    "sg:classifiers":[
        {
            "category":"Health Services",
            "subcategory":"Optometrist",
            "type":"Services"
        }
    ],
    "sg:phone":"+61 3 9841 8422",
    "sg:postcode":"3109",
    "sg:province":"VIC",
    "wof:name":"Kays Eyecare Melbourne Pty Ltd",
    "wof:placetype":"venue"
},
  "geometry": {"coordinates":[145.16307067899999,-37.7891044617],"type":"Point"}
}