{
  "type": "Feature",
  "properties": {
    "addr:full":"16 Manningham Rd Bulleen VIC 3105",
    "addr:housenumber":"16",
    "addr:postcode":"3105",
    "addr:street":"Manningham Rd",
    "iso:country":"AU",
    "sg:address":"16 Manningham Rd",
    "sg:city":"Bulleen",
    "sg:classifiers":[
        {
            "category":"Autos & Motor Vehicles",
            "subcategory":"Automobile Sales",
            "type":"Retail Goods"
        }
    ],
    "sg:phone":"+61 3 9850 6733",
    "sg:postcode":"3105",
    "sg:province":"VIC",
    "sg:tags":[
        "car",
        "used"
    ],
    "wof:name":"Motorfield & Co Bulleen",
    "wof:placetype":"venue"
},
  "geometry": {"coordinates":[145.08221435600001,-37.7615318298],"type":"Point"}
}