{
  "type": "Feature",
  "properties": {
    "addr:full":"160 Churchill Ave Braybrook VIC 3019",
    "addr:housenumber":"160",
    "addr:postcode":"3019",
    "addr:street":"Churchill Ave",
    "iso:country":"AU",
    "sg:address":"160 Churchill Ave",
    "sg:city":"Braybrook",
    "sg:classifiers":[
        {
            "category":"Food & Beverages",
            "subcategory":"Liquor & Beverages",
            "type":"Retail Goods"
        }
    ],
    "sg:phone":"+61 3 9311 1495",
    "sg:postcode":"3019",
    "sg:province":"VIC",
    "sg:tags":[
        "store"
    ],
    "wof:name":"Western Cellars",
    "wof:placetype":"venue"
},
  "geometry": {"coordinates":[144.85263061500001,-37.7863197327],"type":"Point"}
}