{
  "type": "Feature",
  "properties": {
    "addr:full":"Cnr Lugard St & Castlereagh Rd Penrith NSW 2750",
    "addr:postcode":"2750",
    "addr:street":"Cnr Lugard St & Castlereagh Rd",
    "iso:country":"AU",
    "sg:address":"Cnr Lugard St & Castlereagh Rd",
    "sg:city":"Penrith",
    "sg:classifiers":[
        {
            "category":"Shopping",
            "subcategory":"Party Supplies",
            "type":"Retail Goods"
        }
    ],
    "sg:phone":"+61 2 4731 5500",
    "sg:postcode":"2750",
    "sg:province":"NSW",
    "sg:tags":[
        "toilet",
        "portable"
    ],
    "wof:name":"Kennards Washroom Hire",
    "wof:placetype":"venue"
},
  "geometry": {"coordinates":[150.690109253,-33.7471084595],"type":"Point"}
}