{
  "type": "Feature",
  "properties": {
    "iso:country":"AU",
    "sg:address":"36 Kirribilli Ave",
    "sg:city":"Keysborough",
    "sg:classifiers":[
        {
            "category":"Building & Trades",
            "subcategory":"Plumbing",
            "type":"Services"
        }
    ],
    "sg:phone":"+61 3 9798 1843",
    "sg:postcode":"3173",
    "sg:province":"VIC",
    "sg:tags":[
        "plumber",
        "gasfitters"
    ],
    "wof:name":"Bee's Plumbing Service",
    "wof:placetype":"venue"
},
  "geometry": {"coordinates":[145.16619873100001,-37.9851989746],"type":"Point"}
}