{
  "type": "Feature",
  "properties": {
    "addr:full":"68- 80 George St Parramatta NSW 2150",
    "addr:housenumber":"80",
    "addr:postcode":"2150",
    "addr:street":"George St",
    "iso:country":"AU",
    "sg:address":"68- 80 George St",
    "sg:city":"Parramatta",
    "sg:classifiers":[
        {
            "category":"Professional",
            "subcategory":"Accounting & Tax Preparation",
            "type":"Services"
        }
    ],
    "sg:phone":"+61 2 9891 1155",
    "sg:postcode":"2150",
    "sg:province":"NSW",
    "sg:tags":[
        "accountant",
        "auditor"
    ],
    "wof:name":"Casey Bates Pty Ltd",
    "wof:placetype":"venue"
},
  "geometry": {"coordinates":[150.97653198200001,-33.8503913879],"type":"Point"}
}