{
  "type": "Feature",
  "properties": {
    "addr:full":"418a Elizabeth St Surry Hills NSW 2010",
    "addr:housenumber":"418a",
    "addr:postcode":"2010",
    "addr:street":"Elizabeth St",
    "iso:country":"AU",
    "sg:address":"418a Elizabeth St",
    "sg:city":"Surry Hills",
    "sg:classifiers":[
        {
            "category":"Organizations",
            "subcategory":"Professional Association",
            "type":"Services"
        }
    ],
    "sg:phone":"+61 2 9212 6922",
    "sg:postcode":"2010",
    "sg:province":"NSW",
    "sg:tags":[
        "organisation",
        "business"
    ],
    "wof:name":"Extended Care Industry Industrial Secretariat",
    "wof:placetype":"venue"
},
  "geometry": {"coordinates":[151.20840454099999,-33.8863525391],"type":"Point"}
}