{
  "type": "Feature",
  "properties": {
    "iso:country":"AU",
    "sg:address":"5 Broadsound Rd",
    "sg:city":"Mackay",
    "sg:classifiers":[
        {
            "category":"Manufacturing",
            "subcategory":"Leather Goods",
            "type":"Manufacturing & Wholesale Goods"
        }
    ],
    "sg:phone":"+61 7 4952 4969",
    "sg:postcode":"4740",
    "sg:province":"QLD",
    "sg:tags":[
        "wholesaler",
        "mfrs",
        "clothing"
    ],
    "wof:name":"LittleBit Country",
    "wof:placetype":"venue"
},
  "geometry": {"coordinates":[149.15344200000001,-21.167418],"type":"Point"}
}