{
  "type": "Feature",
  "properties": {
    "addr:full":"5/ 51 Collingwood St Osborne Park WA 6017",
    "addr:housenumber":"/ 51",
    "addr:postcode":"6017",
    "addr:street":"Collingwood St",
    "iso:country":"AU",
    "sg:address":"5/ 51 Collingwood St",
    "sg:city":"Osborne Park",
    "sg:classifiers":[
        {
            "category":"Home & Garden",
            "subcategory":"Furniture",
            "type":"Retail Goods"
        }
    ],
    "sg:phone":"+61 8 9244 4443",
    "sg:postcode":"6017",
    "sg:province":"WA",
    "sg:tags":[
        "repair",
        "restoration"
    ],
    "wof:name":"A1 Furniture Restorations",
    "wof:placetype":"venue"
},
  "geometry": {"coordinates":[115.815063477,-31.9027442932],"type":"Point"}
}