{
  "type": "Feature",
  "properties": {
    "iso:country":"AU",
    "sg:address":"146 Carrington St",
    "sg:city":"O&#039;Connor",
    "sg:classifiers":[
        {
            "category":"Banks & Credit Unions",
            "subcategory":"Financial Services",
            "type":"Services"
        }
    ],
    "sg:phone":"+61 8 9331 1166",
    "sg:postcode":"6163",
    "sg:province":"WA",
    "sg:tags":[
        "settlement",
        "nt",
        "agent",
        "wa"
    ],
    "wof:name":"Concorde Settlements",
    "wof:placetype":"venue"
},
  "geometry": {"coordinates":[115.777252,-32.08432],"type":"Point"}
}