{
  "type": "Feature",
  "properties": {
    "addr:full":"Weaber Plains Rd Kununurra WA 6743",
    "addr:postcode":"6743",
    "addr:street":"Weaber Plains Rd",
    "iso:country":"AU",
    "sg:address":"Weaber Plains Rd",
    "sg:city":"Kununurra",
    "sg:classifiers":[
        {
            "category":"Farming",
            "subcategory":"Crops",
            "type":"Manufacturing & Wholesale Goods"
        }
    ],
    "sg:phone":"+61 8 9166 4600",
    "sg:postcode":"6743",
    "sg:province":"WA",
    "sg:tags":[
        "sugarcane",
        "mill",
        "grower"
    ],
    "wof:name":"CSR Ord Sugar",
    "wof:placetype":"venue"
},
  "geometry": {"coordinates":[128.73936462399999,-15.7726697922],"type":"Point"}
}