{
  "type": "Feature",
  "properties": {
    "addr:full":"Cnr Fogarty & Wilkinson Sts Alice Springs NT 0870",
    "addr:postcode":"nt 0870",
    "addr:street":"Cnr",
    "iso:country":"AU",
    "sg:address":"Cnr Fogarty & Wilkinson Sts",
    "sg:city":"Alice Springs",
    "sg:classifiers":[
        {
            "category":"Autos & Motor Vehicles",
            "subcategory":"Auto Supplies",
            "type":"Retail Goods"
        }
    ],
    "sg:phone":"+61 8 8952 1051",
    "sg:postcode":"0870",
    "sg:province":"NT",
    "sg:tags":[
        "battery",
        "automotive"
    ],
    "wof:name":"Don Grant Auto Electrics",
    "wof:placetype":"venue"
},
  "geometry": {"coordinates":[133.87220764200001,-23.7003803253],"type":"Point"}
}