{
  "type": "Feature",
  "properties": {
    "addr:full":"1 Merrivale Drv Warrnambool VIC 3280",
    "addr:housenumber":"1",
    "addr:postcode":"3280",
    "addr:street":"Merrivale Drv",
    "iso:country":"AU",
    "sg:address":"1 Merrivale Drv",
    "sg:city":"Warrnambool",
    "sg:classifiers":[
        {
            "category":"Autos & Motor Vehicles",
            "subcategory":"Automobile Sales",
            "type":"Retail Goods"
        }
    ],
    "sg:phone":"+61 3 5561 4285",
    "sg:postcode":"3280",
    "sg:province":"VIC",
    "sg:tags":[
        "car",
        "used"
    ],
    "wof:name":"Star Auto Sales",
    "wof:placetype":"venue"
},
  "geometry": {"coordinates":[142.469512939,-38.3842430115],"type":"Point"}
}