{
  "type": "Feature",
  "properties": {
    "addr:full":"583 Chapel St South Yarra VIC 3141",
    "addr:housenumber":"583",
    "addr:postcode":"3141",
    "addr:street":"Chapel St",
    "iso:country":"AU",
    "sg:address":"583 Chapel St",
    "sg:city":"South Yarra",
    "sg:classifiers":[
        {
            "category":"Manufacturing",
            "subcategory":"Food",
            "type":"Manufacturing & Wholesale Goods"
        }
    ],
    "sg:phone":"+61 3 9827 3734",
    "sg:postcode":"3141",
    "sg:province":"VIC",
    "sg:tags":[
        "function",
        "catering"
    ],
    "wof:name":"Greek Deli & Taverna",
    "wof:placetype":"venue"
},
  "geometry": {"coordinates":[144.995330811,-37.8400764465],"type":"Point"}
}