{
  "type": "Feature",
  "properties": {
    "addr:full":"Penrice Rd Light Pass SA 5355",
    "addr:postcode":"5355",
    "addr:street":"Penrice Rd",
    "iso:country":"AU",
    "sg:address":"Penrice Rd",
    "sg:city":"Light Pass",
    "sg:classifiers":[
        {
            "category":"Professional",
            "type":"Services"
        }
    ],
    "sg:phone":"+61 8 8562 1644",
    "sg:postcode":"5355",
    "sg:province":"SA",
    "sg:tags":[
        "transport"
    ],
    "wof:name":"Hahn's Haulage",
    "wof:placetype":"venue"
},
  "geometry": {"coordinates":[139.03033447300001,-34.477897644],"type":"Point"}
}