{
  "type": "Feature",
  "properties": {
    "addr:full":"Ainslie Shopping Centre, 3 Edgar St Ainslie ACT 2602",
    "addr:housenumber":"3",
    "addr:postcode":"2602",
    "addr:street":"Edgar St",
    "iso:country":"AU",
    "sg:address":"Ainslie Shopping Centre, 3 Edgar St",
    "sg:city":"Ainslie",
    "sg:classifiers":[
        {
            "category":"Retail",
            "subcategory":"Self-service Laundry",
            "type":"Services"
        }
    ],
    "sg:phone":"+61 2 6248 0039",
    "sg:postcode":"2602",
    "sg:province":"ACT",
    "wof:name":"Ainslie Laundrette",
    "wof:placetype":"venue"
},
  "geometry": {"coordinates":[149.14515685999999,-35.262462616],"type":"Point"}
}