{
  "type": "Feature",
  "properties": {
    "iso:country":"AU",
    "sg:address":"Tarcombe Rd",
    "sg:city":"Avenel",
    "sg:classifiers":[
        {
            "category":"Professional",
            "subcategory":"Employment Agencies",
            "type":"Services"
        }
    ],
    "sg:phone":"+61 3 5796 2479",
    "sg:postcode":"3664",
    "sg:province":"VIC",
    "sg:tags":[
        "entertainer",
        "agent"
    ],
    "wof:name":"Graydon Johnston - Niteshift",
    "wof:placetype":"venue"
},
  "geometry": {"coordinates":[145.240768433,-36.9085235596],"type":"Point"}
}