{
  "type": "Feature",
  "properties": {
    "iso:country":"AU",
    "sg:address":"9 Park St",
    "sg:city":"Bright",
    "sg:classifiers":[
        {
            "category":"Professional",
            "subcategory":"Art Services",
            "type":"Services"
        }
    ],
    "sg:phone":"+61 3 5755 1987",
    "sg:postcode":"3741",
    "sg:province":"VIC",
    "sg:tags":[
        "graphic",
        "designer"
    ],
    "wof:name":"Shell Design",
    "wof:placetype":"venue"
},
  "geometry": {"coordinates":[146.962006,-36.731812],"type":"Point"}
}