{
  "type": "Feature",
  "properties": {
    "addr:full":"6 Marcel Crs Blacktown NSW 2148",
    "addr:housenumber":"6",
    "addr:postcode":"2148",
    "addr:street":"Marcel Crs",
    "iso:country":"AU",
    "sg:address":"6 Marcel Crs",
    "sg:city":"Blacktown",
    "sg:classifiers":[
        {
            "category":"Health Services",
            "subcategory":"Doctor",
            "type":"Services"
        }
    ],
    "sg:phone":"+61 2 9387 6518",
    "sg:postcode":"2148",
    "sg:province":"NSW",
    "sg:tags":[
        "medical",
        "practitioner"
    ],
    "wof:name":"Malouf G Mark Dr",
    "wof:placetype":"venue"
},
  "geometry": {"coordinates":[150.998046875,-33.7510871887],"type":"Point"}
}