{
  "type": "Feature",
  "properties": {
    "addr:full":"PO Box 276 St Helens TAS 7216",
    "addr:postcode":"7216",
    "iso:country":"AU",
    "sg:address":"PO Box 276 St",
    "sg:city":"Helens",
    "sg:classifiers":[
        {
            "category":"Professional",
            "subcategory":"Business Services",
            "type":"Services"
        }
    ],
    "sg:phone":"+61 1800 242 611",
    "sg:postcode":"7216",
    "sg:province":"TAS",
    "sg:tags":[
        "record",
        "management",
        "storage"
    ],
    "wof:name":"Records Management Association of Australasia",
    "wof:placetype":"venue"
},
  "geometry": {"coordinates":[148.23994400000001,-41.316879],"type":"Point"}
}