{
  "type": "Feature",
  "properties": {
    "addr:full":"25 Telegraph Rd Bundaberg QLD 4670",
    "addr:housenumber":"25",
    "addr:postcode":"4670",
    "addr:street":"Telegraph Rd",
    "iso:country":"AU",
    "sg:address":"25 Telegraph Rd",
    "sg:city":"Bundaberg",
    "sg:classifiers":[
        {
            "category":"Building & Trades",
            "subcategory":"Pest Control",
            "type":"Services"
        }
    ],
    "sg:phone":"+61 423 041 955",
    "sg:postcode":"4670",
    "sg:province":"QLD",
    "wof:name":"Termisafe",
    "wof:placetype":"venue"
},
  "geometry": {"coordinates":[152.382125855,-24.8612251282],"type":"Point"}
}