{
  "type": "Feature",
  "properties": {
    "addr:full":"122 Berrys Heads Rd Narara NSW 2250",
    "addr:housenumber":"122",
    "addr:postcode":"2250",
    "addr:street":"Berrys Heads Rd",
    "iso:country":"AU",
    "sg:address":"122 Berrys Heads Rd",
    "sg:city":"Narara",
    "sg:classifiers":[
        {
            "category":"Landmark",
            "subcategory":"Scenic View",
            "type":"Public Place"
        }
    ],
    "sg:phone":"+61 414 458 720",
    "sg:postcode":"2250",
    "sg:province":"NSW",
    "sg:tags":[
        "staircase",
        "handrail"
    ],
    "wof:name":"Staircase Systems",
    "wof:placetype":"venue"
},
  "geometry": {"coordinates":[151.35682678200001,-33.3931121826],"type":"Point"}
}