{
  "type": "Feature",
  "properties": {
    "iso:country":"AU",
    "sg:address":"131 Mortimer St",
    "sg:city":"Mudgee",
    "sg:classifiers":[
        {
            "category":"Shopping",
            "subcategory":"Antiques",
            "type":"Retail Goods"
        }
    ],
    "sg:phone":"+61 2 6372 3612",
    "sg:postcode":"2850",
    "sg:province":"NSW",
    "wof:name":"Settlers Store Antiques",
    "wof:placetype":"venue"
},
  "geometry": {"coordinates":[149.580658,-32.592216],"type":"Point"}
}