{
  "type": "Feature",
  "properties": {
    "addr:full":"104 Cutler Rd Jandakot WA 6164",
    "addr:housenumber":"104",
    "addr:postcode":"6164",
    "addr:street":"Cutler Rd",
    "iso:country":"AU",
    "sg:address":"104 Cutler Rd",
    "sg:city":"Jandakot",
    "sg:classifiers":[
        {
            "category":"Utilities",
            "type":"Services"
        }
    ],
    "sg:phone":"+61 8 9414 1500",
    "sg:postcode":"6164",
    "sg:province":"WA",
    "sg:tags":[
        "refrigeration",
        "industrial",
        "commercial",
        "retail"
    ],
    "wof:name":"Electro-Cool WA",
    "wof:placetype":"venue"
},
  "geometry": {"coordinates":[115.866592,-32.120075],"type":"Point"}
}