{
  "type": "Feature",
  "properties": {
    "addr:full":"19/ 4-14 Watson St Neutral Bay NSW 2089",
    "addr:housenumber":"19 / 4-14",
    "addr:postcode":"2089",
    "addr:street":"Watson St",
    "iso:country":"AU",
    "sg:address":"19/ 4-14 Watson St",
    "sg:city":"Neutral Bay",
    "sg:classifiers":[
        {
            "category":"Professional",
            "subcategory":"Computer Services",
            "type":"Services"
        }
    ],
    "sg:phone":"+61 430 033 042",
    "sg:postcode":"2089",
    "sg:province":"NSW",
    "sg:tags":[
        "information"
    ],
    "wof:name":"Sigma Online Technologies",
    "wof:placetype":"venue"
},
  "geometry": {"coordinates":[151.21812439000001,-33.831489563],"type":"Point"}
}