{
  "type": "Feature",
  "properties": {
    "iso:country":"AU",
    "sg:address":"Shp 20/ 495 Burwood Hwy",
    "sg:city":"Vermont South",
    "sg:classifiers":[
        {
            "category":"Banks & Credit Unions",
            "subcategory":"Bank",
            "type":"Services"
        }
    ],
    "sg:phone":"+61 13 25 75",
    "sg:postcode":"3133",
    "sg:province":"VIC",
    "wof:name":"Bank Of Melbourne",
    "wof:placetype":"venue"
},
  "geometry": {"coordinates":[145.180541992,-37.8559684753],"type":"Point"}
}