{
  "type": "Feature",
  "properties": {
    "iso:country":"AU",
    "sg:address":"2/ 68",
    "sg:city":"The Terrace Ocean Grove",
    "sg:classifiers":[
        {
            "category":"Personal",
            "subcategory":"Hair Removal",
            "type":"Services"
        }
    ],
    "sg:phone":"+61 3 5255 1652",
    "sg:postcode":"3226",
    "sg:province":"VIC",
    "wof:name":"Rachels Beauty Spot",
    "wof:placetype":"venue"
},
  "geometry": {"coordinates":[144.522629,-38.267994],"type":"Point"}
}