{
  "type": "Feature",
  "properties": {
    "iso:country":"AU",
    "sg:address":"13 Bellairs Ave",
    "sg:city":"Seddon",
    "sg:classifiers":[
        {
            "category":"Personal",
            "subcategory":"Beauty Salon",
            "type":"Services"
        }
    ],
    "sg:phone":"+61 3 9689 1212",
    "sg:postcode":"3011",
    "sg:province":"VIC",
    "wof:name":"Nurture Skin & Body Care",
    "wof:placetype":"venue"
},
  "geometry": {"coordinates":[144.895217895,-37.8099594116],"type":"Point"}
}