{
  "type": "Feature",
  "properties": {
    "iso:country":"AU",
    "sg:address":"379 Camberwell Rd",
    "sg:city":"Camberwell",
    "sg:classifiers":[
        {
            "category":"Home & Garden",
            "subcategory":"Carpets & Floor Coverings",
            "type":"Retail Goods"
        }
    ],
    "sg:phone":"+61 3 9882 0019",
    "sg:postcode":"3124",
    "sg:province":"VIC",
    "wof:name":"Floorworld",
    "wof:placetype":"venue"
},
  "geometry": {"coordinates":[145.06092834500001,-37.8347206116],"type":"Point"}
}