{
  "type": "Feature",
  "properties": {
    "addr:full":"966 Burwood Hwy Ferntree Gully VIC 3156",
    "addr:housenumber":"966",
    "addr:postcode":"3156",
    "addr:street":"Burwood Hwy",
    "iso:country":"AU",
    "sg:address":"966 Burwood Hwy",
    "sg:city":"Ferntree Gully",
    "sg:classifiers":[
        {
            "category":"Banks & Credit Unions",
            "subcategory":"Investment Brokerage",
            "type":"Services"
        }
    ],
    "sg:phone":"+61 3 9758 7333",
    "sg:postcode":"3156",
    "sg:province":"VIC",
    "sg:tags":[
        "radiator",
        "motor"
    ],
    "wof:name":"Gully Radiator Centre",
    "wof:placetype":"venue"
},
  "geometry": {"coordinates":[145.28514099099999,-37.8869628906],"type":"Point"}
}