{
  "type": "Feature",
  "properties": {
    "addr:full":"284 Victoria St Abbotsford VIC 3067",
    "addr:housenumber":"284",
    "addr:postcode":"3067",
    "addr:street":"Victoria St",
    "iso:country":"AU",
    "sg:address":"284 Victoria St",
    "sg:city":"Abbotsford",
    "sg:classifiers":[
        {
            "category":"Building & Trades",
            "subcategory":"Locksmith",
            "type":"Services"
        }
    ],
    "sg:phone":"+61 3 9425 9955",
    "sg:postcode":"3067",
    "sg:province":"VIC",
    "sg:tags":[
        "lock"
    ],
    "wof:name":"Telecommunications Locksmiths",
    "wof:placetype":"venue"
},
  "geometry": {"coordinates":[145.00086975100001,-37.8106613159],"type":"Point"}
}