{
  "type": "Feature",
  "properties": {
    "addr:full":"Nelson Pl Williamstown VIC 3016",
    "addr:postcode":"3016",
    "addr:street":"Nelson Pl",
    "iso:country":"AU",
    "sg:address":"Nelson Pl",
    "sg:city":"Williamstown",
    "sg:classifiers":[
        {
            "category":"Travel",
            "subcategory":"Hotels & Motels",
            "type":"Entertainment"
        }
    ],
    "sg:phone":"+61 3 9397 4147",
    "sg:postcode":"3016",
    "sg:province":"VIC",
    "wof:name":"Amawind Williamstown Serviced Apartments",
    "wof:placetype":"venue"
},
  "geometry": {"coordinates":[144.902633667,-37.8615036011],"type":"Point"}
}