{
  "type": "Feature",
  "properties": {
    "addr:full":"Whitford City Shopng Cntr Hillarys WA 6025",
    "addr:postcode":"6025",
    "iso:country":"AU",
    "sg:address":"Whitford City Shopng Cntr",
    "sg:city":"Hillarys",
    "sg:classifiers":[
        {
            "category":"Wholesale",
            "subcategory":"Medical Equipment & Supplies",
            "type":"Manufacturing & Wholesale Goods"
        }
    ],
    "sg:phone":"+61 8 9401 0077",
    "sg:postcode":"6025",
    "sg:province":"WA",
    "sg:tags":[
        "aids",
        "hearing"
    ],
    "wof:name":"Laubman & Pank Hearing Centres",
    "wof:placetype":"venue"
},
  "geometry": {"coordinates":[115.738388062,-31.8148555756],"type":"Point"}
}