{
  "type": "Feature",
  "properties": {
    "iso:country":"AU",
    "sg:address":"136 Wairoa Ave",
    "sg:city":"Bondi",
    "sg:classifiers":[
        {
            "category":"Retail",
            "subcategory":"Self-service Laundry",
            "type":"Services"
        }
    ],
    "sg:phone":"+61 2 9130 3161",
    "sg:postcode":"2026",
    "sg:province":"NSW",
    "wof:name":"Johns Laundrette",
    "wof:placetype":"venue"
},
  "geometry": {"coordinates":[151.27822875999999,-33.8884811401],"type":"Point"}
}