{
  "type": "Feature",
  "properties": {
    "addr:full":"Level9/ 123 Epping Rd North Ryde NSW 2113",
    "addr:housenumber":"/ 123",
    "addr:postcode":"2113",
    "addr:street":"Epping Rd",
    "iso:country":"AU",
    "sg:address":"Level9/ 123 Epping Rd",
    "sg:city":"North Ryde",
    "sg:classifiers":[
        {
            "category":"Shopping",
            "subcategory":"Computers & Home Electronics",
            "type":"Retail Goods"
        }
    ],
    "sg:phone":"+61 2 8877 7222",
    "sg:postcode":"2113",
    "sg:province":"NSW",
    "sg:tags":[
        "hardware",
        "equipment"
    ],
    "wof:name":"AMD Far East Limited - Aust & NZ Branch",
    "wof:placetype":"venue"
},
  "geometry": {"coordinates":[151.12954711899999,-33.7811164856],"type":"Point"}
}