{
  "type": "Feature",
  "properties": {
    "iso:country":"AU",
    "sg:address":"Shop 30",
    "sg:city":"Upper Level, Kippa-Ring Shopping Centre Redcl",
    "sg:classifiers":[
        {
            "category":"Shopping",
            "subcategory":"Jewelry",
            "type":"Retail Goods"
        }
    ],
    "sg:phone":"+61 7 3284 5423",
    "sg:postcode":"4020",
    "sg:province":"QLD",
    "sg:tags":[
        "jeweller"
    ],
    "wof:name":"Doug Morris Jewellers of Redcliffe",
    "wof:placetype":"venue"
},
  "geometry": {"coordinates":[153.107224,-27.22217],"type":"Point"}
}