{
  "type": "Feature",
  "properties": {
    "addr:full":"Alpine Pl Forest Lake QLD 4078",
    "addr:postcode":"4078",
    "addr:street":"Alpine Pl",
    "iso:country":"AU",
    "sg:address":"Alpine Pl",
    "sg:city":"Forest Lake",
    "sg:classifiers":[
        {
            "category":"Education",
            "subcategory":"School",
            "type":"Public Place"
        }
    ],
    "sg:phone":"+61 7 3372 0111",
    "sg:postcode":"4078",
    "sg:province":"QLD",
    "sg:tags":[
        "co-educational"
    ],
    "wof:name":"Forest Lake College",
    "wof:placetype":"venue"
},
  "geometry": {"coordinates":[152.973266602,-27.6137218475],"type":"Point"}
}