{
  "type": "Feature",
  "properties": {
    "addr:full":"1/ 54 Bronte Rd Bondi Junction NSW 2022",
    "addr:housenumber":"/ 54",
    "addr:postcode":"2022",
    "addr:street":"Bronte Rd",
    "iso:country":"AU",
    "sg:address":"1/ 54 Bronte Rd",
    "sg:city":"Bondi Junction",
    "sg:classifiers":[
        {
            "category":"Government",
            "subcategory":"Court House",
            "type":"Public Place"
        }
    ],
    "sg:phone":"+61 2 9369 1258",
    "sg:postcode":"2022",
    "sg:province":"NSW",
    "sg:tags":[
        "personal",
        "marriage",
        "family",
        "counselling"
    ],
    "wof:name":"Margaret Tonko BA (Psych)",
    "wof:placetype":"venue"
},
  "geometry": {"coordinates":[151.25018310600001,-33.8944091797],"type":"Point"}
}