{
  "type": "Feature",
  "properties": {
    "addr:full":"14 Military Rd Merrylands NSW 2160",
    "addr:housenumber":"14",
    "addr:postcode":"2160",
    "addr:street":"Military Rd",
    "iso:country":"AU",
    "sg:address":"14 Military Rd",
    "sg:city":"Merrylands",
    "sg:classifiers":[
        {
            "category":"Food & Beverages",
            "subcategory":"Liquor & Beverages",
            "type":"Retail Goods"
        }
    ],
    "sg:phone":"+61 2 8868 7777",
    "sg:postcode":"2160",
    "sg:province":"NSW",
    "sg:tags":[
        "store"
    ],
    "wof:name":"Merrylands RSL Club",
    "wof:placetype":"venue"
},
  "geometry": {"coordinates":[150.990631103,-33.8382148743],"type":"Point"}
}