{
  "type": "Feature",
  "properties": {
    "iso:country":"AU",
    "sg:address":"Unit 2, 124 Ham St",
    "sg:city":"Windsor",
    "sg:classifiers":[
        {
            "category":"Retail",
            "subcategory":"Auto Repair",
            "type":"Services"
        }
    ],
    "sg:phone":"+61 2 4577 3823",
    "sg:postcode":"2756",
    "sg:province":"NSW",
    "sg:tags":[
        "repairer",
        "motor",
        "engineer"
    ],
    "wof:name":"Ross Stafford Brake & Clutch Repairs",
    "wof:placetype":"venue"
},
  "geometry": {"coordinates":[150.81256103499999,-33.6264190674],"type":"Point"}
}