{
  "type": "Feature",
  "properties": {
    "addr:full":"U5/ 383 Victoria Rd Malaga WA 6090",
    "addr:housenumber":"383",
    "addr:postcode":"6090",
    "addr:street":"U5 /;Victoria Rd",
    "iso:country":"AU",
    "sg:address":"U5/ 383 Victoria Rd",
    "sg:city":"Malaga",
    "sg:classifiers":[
        {
            "category":"Retail",
            "subcategory":"Auto Repair",
            "type":"Services"
        }
    ],
    "sg:phone":"+61 8 9249 9504",
    "sg:postcode":"6090",
    "sg:province":"WA",
    "sg:tags":[
        "repairer",
        "motor",
        "engineer"
    ],
    "wof:name":"Byrne Race Cars",
    "wof:placetype":"venue"
},
  "geometry": {"coordinates":[115.89679717999999,-31.8614063263],"type":"Point"}
}