{
  "type": "Feature",
  "properties": {
    "addr:full":"325 Chapel St Prahran VIC 3181",
    "addr:housenumber":"325",
    "addr:postcode":"3181",
    "addr:street":"Chapel St",
    "iso:country":"AU",
    "sg:address":"325 Chapel St",
    "sg:city":"Prahran",
    "sg:classifiers":[
        {
            "category":"Retail",
            "subcategory":"Repair Shop",
            "type":"Services"
        }
    ],
    "sg:phone":"+61 3 9533 6622",
    "sg:postcode":"3181",
    "sg:province":"VIC",
    "sg:tags":[
        "mending",
        "clothing",
        "alteration"
    ],
    "wof:name":"Sew Right Tailoring",
    "wof:placetype":"venue"
},
  "geometry": {"coordinates":[144.993850708,-37.8475456238],"type":"Point"}
}