{
  "type": "Feature",
  "properties": {
    "iso:country":"AU",
    "sg:address":"Cnr Grendon & Palmer Sts",
    "sg:city":"North Mackay",
    "sg:classifiers":[
        {
            "category":"Health Services",
            "subcategory":"Doctor",
            "type":"Services"
        }
    ],
    "sg:phone":"+61 7 4953 2566",
    "sg:postcode":"4740",
    "sg:province":"QLD",
    "sg:tags":[
        "medical",
        "practitioner"
    ],
    "wof:name":"Fenner Family Medicine",
    "wof:placetype":"venue"
},
  "geometry": {"coordinates":[149.189011,-21.12335],"type":"Point"}
}