{
  "type": "Feature",
  "properties": {
    "addr:full":"Essendon Airport 120 Bulla Road Essendon Essendon VIC 3040",
    "addr:housenumber":"120",
    "addr:postcode":"3040",
    "addr:street":"Bulla Road",
    "iso:country":"AU",
    "sg:address":"Essendon Airport 120 Bulla Road",
    "sg:city":"Essendon Essendon",
    "sg:classifiers":[
        {
            "category":"Home & Garden",
            "subcategory":"Furniture",
            "type":"Retail Goods"
        }
    ],
    "sg:phone":"+61 3 9351 0669",
    "sg:postcode":"3040",
    "sg:province":"VIC",
    "sg:tags":[
        "repair",
        "restoration"
    ],
    "wof:name":"Adriatic Furniture",
    "wof:placetype":"venue"
},
  "geometry": {"coordinates":[144.910400391,-37.7444496155],"type":"Point"}
}