{
  "type": "Feature",
  "properties": {
    "iso:country":"AU",
    "sg:address":"161 Military Rd",
    "sg:city":"Dover Heights",
    "sg:classifiers":[
        {
            "category":"Building & Trades",
            "subcategory":"Construction",
            "type":"Services"
        }
    ],
    "sg:phone":"+61 2 9371 0649",
    "sg:postcode":"2030",
    "sg:province":"NSW",
    "sg:tags":[
        "contractor"
    ],
    "wof:name":"Designbank Fine Architecture Pty Ltd",
    "wof:placetype":"venue"
},
  "geometry": {"coordinates":[151.28094482399999,-33.8724441528],"type":"Point"}
}