{
  "type": "Feature",
  "properties": {
    "addr:full":"PO Box 98 Branxton NSW 2335",
    "addr:postcode":"2335",
    "iso:country":"AU",
    "sg:address":"PO Box 98",
    "sg:city":"Branxton",
    "sg:classifiers":[
        {
            "category":"Building & Trades",
            "subcategory":"Construction",
            "type":"Services"
        }
    ],
    "sg:phone":"+61 417 678 306",
    "sg:postcode":"2335",
    "sg:province":"NSW",
    "sg:tags":[
        "earth",
        "excavating",
        "moving",
        "contractor"
    ],
    "wof:name":"Fenech Rural & Building Excavations",
    "wof:placetype":"venue"
},
  "geometry": {"coordinates":[151.3515625,-32.655960083],"type":"Point"}
}