{
  "type": "Feature",
  "properties": {
    "iso:country":"AU",
    "sg:address":"541 Raglan Pde",
    "sg:city":"Warrnambool",
    "sg:classifiers":[
        {
            "category":"Home & Garden",
            "subcategory":"Household Appliances",
            "type":"Retail Goods"
        }
    ],
    "sg:phone":"+61 3 5562 2155",
    "sg:postcode":"3280",
    "sg:province":"VIC",
    "sg:tags":[
        "heating",
        "system"
    ],
    "wof:name":"Turland Bros Pty Ltd",
    "wof:placetype":"venue"
},
  "geometry": {"coordinates":[142.486404419,-38.3813247681],"type":"Point"}
}