{
  "type": "Feature",
  "properties": {
    "iso:country":"AU",
    "sg:address":"16 Oceano St",
    "sg:city":"Copacabana",
    "sg:classifiers":[
        {
            "category":"Train Station",
            "subcategory":"Rail",
            "type":"Transportation"
        }
    ],
    "sg:phone":"+61 428 100 011",
    "sg:postcode":"2251",
    "sg:province":"NSW",
    "sg:tags":[
        "wallboard"
    ],
    "wof:name":"Copacabana Interior Linings Pty Ltd",
    "wof:placetype":"venue"
},
  "geometry": {"coordinates":[151.43898010300001,-33.490196228],"type":"Point"}
}