{
  "type": "Feature",
  "properties": {
    "iso:country":"AU",
    "sg:address":"33 Brookes St",
    "sg:city":"Bowen Hills",
    "sg:classifiers":[
        {
            "category":"Professional",
            "subcategory":"Computer Services",
            "type":"Services"
        }
    ],
    "sg:phone":"+61 7 3257 3777",
    "sg:postcode":"4006",
    "sg:province":"QLD",
    "sg:tags":[
        "package",
        "software"
    ],
    "wof:name":"Locomotive International Pty Ltd",
    "wof:placetype":"venue"
},
  "geometry": {"coordinates":[153.03526306099999,-27.4501094818],"type":"Point"}
}