{
  "type": "Feature",
  "properties": {
    "addr:full":"28 Hartwell St Coolbinia WA 6050",
    "addr:housenumber":"28",
    "addr:postcode":"6050",
    "addr:street":"Hartwell St",
    "iso:country":"AU",
    "sg:address":"28 Hartwell St",
    "sg:city":"Coolbinia",
    "sg:classifiers":[
        {
            "category":"Professional",
            "subcategory":"Art Services",
            "type":"Services"
        }
    ],
    "sg:phone":"+61 412 918 740",
    "sg:postcode":"6050",
    "sg:province":"WA",
    "sg:tags":[
        "interior",
        "designer"
    ],
    "wof:name":"BGA Interiors",
    "wof:placetype":"venue"
},
  "geometry": {"coordinates":[115.85446167000001,-31.9120578766],"type":"Point"}
}