{
  "type": "Feature",
  "properties": {
    "addr:full":"Shop 2/ 220 King St Mascot NSW 2020",
    "addr:housenumber":"shop 2 / 220",
    "addr:postcode":"2020",
    "addr:street":"King St",
    "iso:country":"AU",
    "sg:address":"Shop 2/ 220 King St",
    "sg:city":"Mascot",
    "sg:classifiers":[
        {
            "category":"Retail",
            "subcategory":"Veterinary Services",
            "type":"Services"
        }
    ],
    "sg:phone":"+61 2 9667 0022",
    "sg:postcode":"2020",
    "sg:province":"NSW",
    "sg:tags":[
        "surgeon"
    ],
    "wof:name":"James The Vet",
    "wof:placetype":"venue"
},
  "geometry": {"coordinates":[151.19447326700001,-33.9297142029],"type":"Point"}
}