{
  "type": "Feature",
  "properties": {
    "addr:full":"21 Hurlstone Ave Hurlstone Park NSW 2193",
    "addr:housenumber":"21",
    "addr:postcode":"2193",
    "addr:street":"Hurlstone Ave",
    "iso:country":"AU",
    "sg:address":"21 Hurlstone Ave",
    "sg:city":"Hurlstone Park",
    "sg:classifiers":[
        {
            "category":"Real Estate",
            "subcategory":"Architect",
            "type":"Services"
        }
    ],
    "sg:phone":"+61 2 9559 5608",
    "sg:postcode":"2193",
    "sg:province":"NSW",
    "sg:tags":[
        "building",
        "designer"
    ],
    "wof:name":"Hurlestone Design",
    "wof:placetype":"venue"
},
  "geometry": {"coordinates":[151.12550400000001,-33.913612],"type":"Point"}
}