{
  "type": "Feature",
  "properties": {
    "addr:full":"Alison Crs Russell Island QLD 4184",
    "addr:postcode":"4184",
    "addr:street":"Alison Crs",
    "iso:country":"AU",
    "sg:address":"Alison Crs",
    "sg:city":"Russell Island",
    "sg:classifiers":[
        {
            "category":"Health Services",
            "subcategory":"Doctor",
            "type":"Services"
        }
    ],
    "sg:phone":"+61 7 3409 1151",
    "sg:postcode":"4184",
    "sg:province":"QLD",
    "sg:tags":[
        "medical",
        "practitioner"
    ],
    "wof:name":"de Wytt Laurinda",
    "wof:placetype":"venue"
},
  "geometry": {"coordinates":[153.38339233400001,-27.6893100739],"type":"Point"}
}