{
  "type": "Feature",
  "properties": {
    "addr:full":"2 / 129 Goulburn Rd Echuca VIC 3564",
    "addr:housenumber":"/ 129",
    "addr:postcode":"3564",
    "addr:street":"Goulburn Rd",
    "iso:country":"AU",
    "sg:address":"2 / 129 Goulburn Rd",
    "sg:city":"Echuca",
    "sg:classifiers":[
        {
            "category":"Farming",
            "subcategory":"Farm & Veterinary Services",
            "type":"Manufacturing & Wholesale Goods"
        }
    ],
    "sg:phone":"+61 3 5482 5774",
    "sg:postcode":"3564",
    "sg:province":"VIC",
    "sg:tags":[
        "agricultural",
        "advisory"
    ],
    "wof:name":"Farmanco Pty Ltd",
    "wof:placetype":"venue"
},
  "geometry": {"coordinates":[144.76234435999999,-36.1282501221],"type":"Point"}
}