{
  "type": "Feature",
  "properties": {
    "iso:country":"AU",
    "sg:address":"Shop 1061 Westfield Shoppingtown",
    "sg:city":"Tuggerah",
    "sg:classifiers":[
        {
            "category":"Shopping",
            "subcategory":"Jewelry",
            "type":"Retail Goods"
        }
    ],
    "sg:phone":"+61 2 4353 5226",
    "sg:postcode":"2259",
    "sg:province":"NSW",
    "sg:tags":[
        "fashion",
        "jewellery"
    ],
    "wof:name":"Kleins Jewellery Of Tuggerah",
    "wof:placetype":"venue"
},
  "geometry": {"coordinates":[151.415557861,-33.306930542],"type":"Point"}
}