{
  "type": "Feature",
  "properties": {
    "iso:country":"AU",
    "sg:address":"23 Old Lansdowne Rd",
    "sg:city":"Cundletown",
    "sg:classifiers":[
        {
            "category":"Building & Trades",
            "subcategory":"Landscaping Services",
            "type":"Services"
        }
    ],
    "sg:phone":"+61 2 6553 9107",
    "sg:postcode":"2430",
    "sg:province":"NSW",
    "sg:tags":[
        "fertilizer",
        "spreading",
        "insecticide"
    ],
    "wof:name":"Burnard D L",
    "wof:placetype":"venue"
},
  "geometry": {"coordinates":[152.50959800000001,-31.875666],"type":"Point"}
}