{
  "type": "Feature",
  "properties": {
    "iso:country":"AU",
    "sg:address":"Shop 19, Rapid Creek Business Village Trower Rd",
    "sg:city":"Rapid Creek",
    "sg:classifiers":[
        {
            "category":"Organizations",
            "subcategory":"Community Association",
            "type":"Services"
        }
    ],
    "sg:phone":"+61 8 8948 5311",
    "sg:postcode":"0810",
    "sg:province":"NT",
    "sg:tags":[
        "organisation",
        "family",
        "welfare"
    ],
    "wof:name":"SIDSandKids",
    "wof:placetype":"venue"
},
  "geometry": {"coordinates":[130.86032104500001,-12.3868494034],"type":"Point"}
}