{
  "type": "Feature",
  "properties": {
    "addr:full":"31 Old Farm Rd Helensburgh NSW 2508",
    "addr:housenumber":"31",
    "addr:postcode":"2508",
    "addr:street":"Old Farm Rd",
    "iso:country":"AU",
    "sg:address":"31 Old Farm Rd",
    "sg:city":"Helensburgh",
    "sg:classifiers":[
        {
            "category":"Social Services",
            "subcategory":"Adult Care",
            "type":"Services"
        }
    ],
    "sg:phone":"+61 2 4294 2227",
    "sg:postcode":"2508",
    "sg:province":"NSW",
    "sg:tags":[
        "aged"
    ],
    "wof:name":"Robin Wirth Aged Care Pty Ltd",
    "wof:placetype":"venue"
},
  "geometry": {"coordinates":[150.997818,-34.181419],"type":"Point"}
}