{
  "type": "Feature",
  "properties": {
    "addr:full":"Shop 2/ 71 Billington Pl Emu Plains NSW 2750",
    "addr:housenumber":"shop 2 / 71",
    "addr:postcode":"2750",
    "addr:street":"Pl",
    "iso:country":"AU",
    "sg:address":"Shop 2/ 71 Billington Pl",
    "sg:city":"Emu Plains",
    "sg:classifiers":[
        {
            "category":"Personal",
            "subcategory":"Massage",
            "type":"Services"
        }
    ],
    "sg:phone":"+61 2 4735 3114",
    "sg:postcode":"2750",
    "sg:province":"NSW",
    "sg:tags":[
        "therapy"
    ],
    "wof:name":"Tranquility Skin & Body Care",
    "wof:placetype":"venue"
},
  "geometry": {"coordinates":[150.674591064,-33.7465286255],"type":"Point"}
}