{
  "type": "Feature",
  "properties": {
    "iso:country":"AU",
    "sg:address":"360 Dudley St",
    "sg:city":"Docklands",
    "sg:classifiers":[
        {
            "category":"Manufacturing",
            "subcategory":"Tools & Machinery",
            "type":"Manufacturing & Wholesale Goods"
        }
    ],
    "sg:phone":"+61 3 9329 9077",
    "sg:postcode":"3008",
    "sg:province":"VIC",
    "sg:tags":[
        "earth",
        "excavating",
        "moving",
        "equipment"
    ],
    "wof:name":"CAT Rental Store",
    "wof:placetype":"venue"
},
  "geometry": {"coordinates":[144.945587158,-37.8115539551],"type":"Point"}
}