{
  "type": "Feature",
  "properties": {
    "iso:country":"AU",
    "sg:address":"29 Fullerton Cove Rd",
    "sg:city":"Fullerton Cove",
    "sg:classifiers":[
        {
            "category":"Retail",
            "subcategory":"Auto Rental",
            "type":"Services"
        }
    ],
    "sg:phone":"+61 2 4965 0454",
    "sg:postcode":"2318",
    "sg:province":"NSW",
    "sg:tags":[
        "car",
        "wedding"
    ],
    "wof:name":"Silhouette Bridal Cars.",
    "wof:placetype":"venue"
},
  "geometry": {"coordinates":[151.831436,-32.837311],"type":"Point"}
}