{
  "type": "Feature",
  "properties": {
    "iso:country":"AU",
    "sg:address":"18 Maude St",
    "sg:city":"Anula",
    "sg:classifiers":[
        {
            "category":"Recreation",
            "subcategory":"Fishing",
            "type":"Entertainment"
        }
    ],
    "sg:phone":"+61 8 8927 5215",
    "sg:postcode":"0812",
    "sg:province":"NT",
    "sg:tags":[
        "trip"
    ],
    "wof:name":"Mark Wests Hooked On Fishing Safaris",
    "wof:placetype":"venue"
},
  "geometry": {"coordinates":[130.88627600000001,-12.390459],"type":"Point"}
}