{
  "type": "Feature",
  "properties": {
    "iso:country":"AU",
    "sg:address":"226 Victoria St",
    "sg:city":"Cardwell",
    "sg:classifiers":[
        {
            "category":"Health Services",
            "subcategory":"Doctor",
            "type":"Services"
        }
    ],
    "sg:phone":"+61 7 4066 8533",
    "sg:postcode":"4849",
    "sg:province":"QLD",
    "sg:tags":[
        "medical",
        "practitioner"
    ],
    "wof:name":"Cardwell Family Practice",
    "wof:placetype":"venue"
},
  "geometry": {"coordinates":[146.017883,-18.257044],"type":"Point"}
}