{
  "type": "Feature",
  "properties": {
    "addr:full":"71 Leslie St Mandurah WA 6210",
    "addr:housenumber":"71",
    "addr:postcode":"6210",
    "addr:street":"Leslie St",
    "iso:country":"AU",
    "sg:address":"71 Leslie St",
    "sg:city":"Mandurah",
    "sg:classifiers":[
        {
            "category":"Shopping",
            "subcategory":"Computers & Home Electronics",
            "type":"Retail Goods"
        }
    ],
    "sg:phone":"+61 8 9581 3129",
    "sg:postcode":"6210",
    "sg:province":"WA",
    "sg:tags":[
        "small",
        "equipment",
        "business"
    ],
    "wof:name":"Contract A Tech",
    "wof:placetype":"venue"
},
  "geometry": {"coordinates":[115.726288,-32.541843],"type":"Point"}
}