{
  "type": "Feature",
  "properties": {
    "addr:full":"14 / 600 Bruce Hwy Woree QLD 4868",
    "addr:housenumber":"14 / 600",
    "addr:postcode":"4868",
    "addr:street":"Bruce Hwy",
    "iso:country":"AU",
    "sg:address":"14 / 600 Bruce Hwy",
    "sg:city":"Woree",
    "sg:classifiers":[
        {
            "category":"Health Services",
            "subcategory":"Doctor",
            "type":"Services"
        }
    ],
    "sg:phone":"+61 7 4054 3744",
    "sg:postcode":"4868",
    "sg:province":"QLD",
    "sg:tags":[
        "medical",
        "practitioner"
    ],
    "wof:name":"Walker Colin H",
    "wof:placetype":"venue"
},
  "geometry": {"coordinates":[145.74595642099999,-16.9533500671],"type":"Point"}
}