{
  "type": "Feature",
  "properties": {
    "addr:full":"Lot 50 , Forrington Hts Waroona WA 6215",
    "addr:postcode":"6215",
    "iso:country":"AU",
    "sg:address":"Lot 50",
    "sg:city":", Forrington Hts Waroona",
    "sg:classifiers":[
        {
            "category":"Building & Trades",
            "subcategory":"Construction",
            "type":"Services"
        }
    ],
    "sg:phone":"+61 8 9733 2064",
    "sg:postcode":"6215",
    "sg:province":"WA",
    "sg:tags":[
        "earth",
        "excavating",
        "moving",
        "contractor"
    ],
    "wof:name":"Butlers Earthmoving",
    "wof:placetype":"venue"
},
  "geometry": {"coordinates":[115.942879,-32.834942],"type":"Point"}
}