{
  "type": "Feature",
  "properties": {
    "addr:full":"2/ 1 Boden Rd Seven Hills NSW 2147",
    "addr:housenumber":"/ 1",
    "addr:postcode":"2147",
    "addr:street":"Boden Rd",
    "iso:country":"AU",
    "sg:address":"2/ 1 Boden Rd",
    "sg:city":"Seven Hills",
    "sg:classifiers":[
        {
            "category":"Retail",
            "subcategory":"Funeral Services",
            "type":"Services"
        }
    ],
    "sg:phone":"+61 2 9624 1385",
    "sg:postcode":"2147",
    "sg:province":"NSW",
    "sg:tags":[
        "cremation"
    ],
    "wof:name":"T J Andrews Funeral Services",
    "wof:placetype":"venue"
},
  "geometry": {"coordinates":[150.95954895,-33.7744789124],"type":"Point"}
}