{
  "type": "Feature",
  "properties": {
    "addr:full":"7 Rhys Crt Torquay QLD 4655",
    "addr:housenumber":"7",
    "addr:postcode":"4655",
    "addr:street":"Rhys Crt",
    "iso:country":"AU",
    "sg:address":"7 Rhys Crt",
    "sg:city":"Torquay",
    "sg:classifiers":[
        {
            "category":"Personal",
            "subcategory":"Massage",
            "type":"Services"
        }
    ],
    "sg:phone":"+61 7 4128 9046",
    "sg:postcode":"4655",
    "sg:province":"QLD",
    "sg:tags":[
        "therapy"
    ],
    "wof:name":"Feronica Beauty Room",
    "wof:placetype":"venue"
},
  "geometry": {"coordinates":[152.867615,-25.29472],"type":"Point"}
}