{
  "type": "Feature",
  "properties": {
    "iso:country":"AU",
    "sg:address":"1-3 Havilah St",
    "sg:city":"Chatswood",
    "sg:classifiers":[
        {
            "category":"Real Estate",
            "subcategory":"Real Estate Agent",
            "type":"Services"
        }
    ],
    "sg:phone":"+61 2 9412 2177",
    "sg:postcode":"2067",
    "sg:province":"NSW",
    "wof:name":"Lorimer Real Estate Pty Ltd",
    "wof:placetype":"venue"
},
  "geometry": {"coordinates":[151.18736267099999,-33.7945175171],"type":"Point"}
}