{
  "type": "Feature",
  "properties": {
    "iso:country":"AU",
    "sg:address":"PO Box 6019",
    "sg:city":"Riverview",
    "sg:classifiers":[
        {
            "category":"Wholesale",
            "subcategory":"Farm Supplies",
            "type":"Manufacturing & Wholesale Goods"
        }
    ],
    "sg:phone":"+61 7 3282 6122",
    "sg:postcode":"4303",
    "sg:province":"QLD",
    "sg:tags":[
        "feed",
        "supplement",
        "stock"
    ],
    "wof:name":"By Products Management",
    "wof:placetype":"venue"
},
  "geometry": {"coordinates":[152.85081481899999,-27.5960998535],"type":"Point"}
}