{
  "type": "Feature",
  "properties": {
    "addr:full":"PO Box 901 Crows Nest NSW 2065",
    "addr:postcode":"2065",
    "iso:country":"AU",
    "sg:address":"PO Box 901",
    "sg:city":"Crows Nest",
    "sg:classifiers":[
        {
            "category":"Restaurant",
            "type":"Food & Drink"
        }
    ],
    "sg:phone":"+61 1300 368 446",
    "sg:postcode":"2065",
    "sg:province":"NSW",
    "wof:name":"Australian Menus Pty Ltd",
    "wof:placetype":"venue"
},
  "geometry": {"coordinates":[151.200881958,-33.8251609802],"type":"Point"}
}