{
  "type": "Feature",
  "properties": {
    "addr:full":"58 West St Busselton WA 6280",
    "addr:housenumber":"58",
    "addr:postcode":"6280",
    "addr:street":"West St",
    "iso:country":"AU",
    "sg:address":"58 West St",
    "sg:city":"Busselton",
    "sg:classifiers":[
        {
            "category":"Health Services",
            "subcategory":"Doctor",
            "type":"Services"
        }
    ],
    "sg:phone":"+61 8 9754 2880",
    "sg:postcode":"6280",
    "sg:province":"WA",
    "sg:tags":[
        "nurse",
        "nursing"
    ],
    "wof:name":"Silver Chain",
    "wof:placetype":"venue"
},
  "geometry": {"coordinates":[115.341430664,-33.6519088745],"type":"Point"}
}