{
  "type": "Feature",
  "properties": {
    "addr:full":"11 Arthur Drv Wyong NSW 2259",
    "addr:housenumber":"11",
    "addr:postcode":"2259",
    "addr:street":"Arthur Drv",
    "iso:country":"AU",
    "sg:address":"11 Arthur Drv",
    "sg:city":"Wyong",
    "sg:classifiers":[
        {
            "category":"Travel",
            "subcategory":"Travel Agent",
            "type":"Entertainment"
        }
    ],
    "sg:phone":"+61 2 4351 1573",
    "sg:postcode":"2259",
    "sg:province":"NSW",
    "sg:tags":[
        "tour",
        "holiday",
        "adventure"
    ],
    "wof:name":"Camp Easy Tours",
    "wof:placetype":"venue"
},
  "geometry": {"coordinates":[151.422607422,-33.2782287598],"type":"Point"}
}