{
  "type": "Feature",
  "properties": {
    "addr:full":"Suite 14 495 Princes Hwy Rockdale NSW 2216",
    "addr:housenumber":"495",
    "addr:postcode":"2216",
    "addr:street":"Princes Hwy",
    "iso:country":"AU",
    "sg:address":"Suite 14 495 Princes Hwy",
    "sg:city":"Rockdale",
    "sg:classifiers":[
        {
            "category":"Health Services",
            "subcategory":"Dentist",
            "type":"Services"
        }
    ],
    "sg:phone":"+61 2 9567 1729",
    "sg:postcode":"2216",
    "sg:province":"NSW",
    "wof:name":"Ayar Robert Dr",
    "wof:placetype":"venue"
},
  "geometry": {"coordinates":[151.13772599999999,-33.95216],"type":"Point"}
}