{
  "type": "Feature",
  "properties": {
    "addr:full":"35 Victoria Ave Chelmer QLD 4068",
    "addr:housenumber":"35",
    "addr:postcode":"4068",
    "addr:street":"Victoria Ave",
    "iso:country":"AU",
    "sg:address":"35 Victoria Ave",
    "sg:city":"Chelmer",
    "sg:classifiers":[
        {
            "category":"Health Services",
            "subcategory":"Nursing And Care Facility",
            "type":"Services"
        }
    ],
    "sg:phone":"+61 7 3379 9800",
    "sg:postcode":"4068",
    "sg:province":"QLD",
    "sg:tags":[
        "home"
    ],
    "wof:name":"Salvation Army Warrina Village Nursing Home",
    "wof:placetype":"venue"
},
  "geometry": {"coordinates":[152.971466064,-27.5090694427],"type":"Point"}
}