{
  "type": "Feature",
  "properties": {
    "iso:country":"AU",
    "sg:address":"33 MacDonald St",
    "sg:city":"Lakemba",
    "sg:classifiers":[
        {
            "category":"Building & Trades",
            "subcategory":"Construction",
            "type":"Services"
        }
    ],
    "sg:phone":"+61 2 9740 3479",
    "sg:postcode":"2195",
    "sg:province":"NSW",
    "sg:tags":[
        "joiner",
        "carpenter"
    ],
    "wof:name":"B.N.A. Joinery",
    "wof:placetype":"venue"
},
  "geometry": {"coordinates":[151.072571,-33.916855],"type":"Point"}
}