{
  "type": "Feature",
  "properties": {
    "iso:country":"AU",
    "sg:address":"PO Box 789",
    "sg:city":"Kew",
    "sg:classifiers":[
        {
            "category":"Real Estate",
            "subcategory":"Architect",
            "type":"Services"
        }
    ],
    "sg:phone":"+61 3 9625 2299",
    "sg:postcode":"3101",
    "sg:province":"VIC",
    "wof:name":"Welst Walter & Associates Architects",
    "wof:placetype":"venue"
},
  "geometry": {"coordinates":[145.030883789,-37.8014717102],"type":"Point"}
}