{
  "type": "Feature",
  "properties": {
    "addr:full":"378 Balwyn Rd Balwyn North VIC 3104",
    "addr:housenumber":"378",
    "addr:postcode":"3104",
    "addr:street":"Balwyn Rd",
    "iso:country":"AU",
    "sg:address":"378 Balwyn Rd",
    "sg:city":"Balwyn North",
    "sg:classifiers":[
        {
            "category":"Arena",
            "subcategory":"Sports Club",
            "type":"Entertainment"
        }
    ],
    "sg:phone":"+61 3 9857 6718",
    "sg:postcode":"3104",
    "sg:province":"VIC",
    "sg:tags":[
        "defence",
        "supply",
        "self",
        "instruction",
        "martial art"
    ],
    "wof:name":"International Goju Karatedo Balwyn Dojo",
    "wof:placetype":"venue"
},
  "geometry": {"coordinates":[145.086395264,-37.7876319885],"type":"Point"}
}