{
  "type": "Feature",
  "properties": {
    "addr:full":"4 Federation St Bungalow QLD 4870",
    "addr:housenumber":"4",
    "addr:postcode":"4870",
    "addr:street":"Federation St",
    "iso:country":"AU",
    "sg:address":"4 Federation St",
    "sg:city":"Bungalow",
    "sg:classifiers":[
        {
            "category":"Building & Trades",
            "subcategory":"Construction",
            "type":"Services"
        }
    ],
    "sg:phone":"+61 7 4031 3273",
    "sg:postcode":"4870",
    "sg:province":"QLD",
    "sg:tags":[
        "welding"
    ],
    "wof:name":"Economy Engineering",
    "wof:placetype":"venue"
},
  "geometry": {"coordinates":[145.75479125999999,-16.9408836365],"type":"Point"}
}