{
  "type": "Feature",
  "properties": {
    "addr:full":"Blair Drv St Lucia QLD 4067",
    "addr:postcode":"4067",
    "addr:street":"Blair Drv",
    "iso:country":"AU",
    "sg:address":"Blair Drv",
    "sg:city":"St Lucia",
    "sg:classifiers":[
        {
            "category":"Sports & Exercise",
            "subcategory":"Sports Center",
            "type":"Entertainment"
        }
    ],
    "sg:phone":"+61 7 3371 7906",
    "sg:postcode":"4067",
    "sg:province":"QLD",
    "sg:tags":[
        "coach",
        "tennis"
    ],
    "wof:name":"The University Of Queensland Tennis Centre St Lucia",
    "wof:placetype":"venue"
},
  "geometry": {"coordinates":[153.014602661,-27.494468689],"type":"Point"}
}