{
  "type": "Feature",
  "properties": {
    "iso:country":"AU",
    "sg:address":"Shp 310G Warringah Mall",
    "sg:city":"Brookvale",
    "sg:classifiers":[
        {
            "category":"Shopping",
            "subcategory":"Clothing, Apparel, & Fashions",
            "type":"Retail Goods"
        }
    ],
    "sg:phone":"+61 2 9905 6503",
    "sg:postcode":"2100",
    "sg:province":"NSW",
    "sg:tags":[
        "lady",
        "wear"
    ],
    "wof:name":"Jacqui E",
    "wof:placetype":"venue"
},
  "geometry": {"coordinates":[151.24801635700001,-33.7516098022],"type":"Point"}
}