{
  "type": "Feature",
  "properties": {
    "addr:full":"Lvl 3, 74- 78 Wentworth Ave Sydney NSW 2000",
    "addr:housenumber":"74 78",
    "addr:postcode":"2000",
    "addr:street":"Wentworth Ave",
    "iso:country":"AU",
    "sg:address":"Lvl 3, 74- 78 Wentworth Ave",
    "sg:city":"Sydney",
    "sg:classifiers":[
        {
            "category":"Education",
            "subcategory":"University",
            "type":"Public Place"
        }
    ],
    "sg:phone":"+61 1300 136 933",
    "sg:postcode":"2000",
    "sg:province":"NSW",
    "sg:tags":[
        "college",
        "tertiary"
    ],
    "wof:name":"QANTM College",
    "wof:placetype":"venue"
},
  "geometry": {"coordinates":[151.20979309099999,-33.8794670105],"type":"Point"}
}