{
  "type": "Feature",
  "properties": {
    "addr:full":"Shop 5 112-114 Bains Rd Morphett Vale SA 5162",
    "addr:housenumber":"shop 5",
    "addr:postcode":"112-114;5162",
    "addr:street":"Bains Rd",
    "iso:country":"AU",
    "sg:address":"Shop 5 112-114 Bains Rd",
    "sg:city":"Morphett Vale",
    "sg:classifiers":[
        {
            "category":"Fast Food",
            "type":"Food & Drink"
        }
    ],
    "sg:phone":"+61 8 8325 2793",
    "sg:postcode":"5162",
    "sg:province":"SA",
    "sg:tags":[
        "away",
        "take"
    ],
    "wof:name":"Pizza Blue",
    "wof:placetype":"venue"
},
  "geometry": {"coordinates":[138.54344177199999,-35.1145896912],"type":"Point"}
}