{
  "type": "Feature",
  "properties": {
    "addr:full":"U1/ 1 Villanova St Wanneroo WA 6065",
    "addr:housenumber":"1",
    "addr:postcode":"6065",
    "addr:street":"U1 /;Villanova St",
    "iso:country":"AU",
    "sg:address":"U1/ 1 Villanova St",
    "sg:city":"Wanneroo",
    "sg:classifiers":[
        {
            "category":"Food & Beverages",
            "subcategory":"Bakery",
            "type":"Retail Goods"
        }
    ],
    "sg:phone":"+61 8 9405 9670",
    "sg:postcode":"6065",
    "sg:province":"WA",
    "sg:tags":[
        "baker"
    ],
    "wof:name":"Le Moulin Lebonese Bakery",
    "wof:placetype":"venue"
},
  "geometry": {"coordinates":[115.80783081,-31.7806282043],"type":"Point"}
}