{
  "type": "Feature",
  "properties": {
    "addr:full":"77 Nellie St Nundah QLD 4012",
    "addr:housenumber":"77",
    "addr:postcode":"4012",
    "addr:street":"Nellie St",
    "iso:country":"AU",
    "sg:address":"77 Nellie St",
    "sg:city":"Nundah",
    "sg:classifiers":[
        {
            "category":"Home & Garden",
            "subcategory":"Hardware",
            "type":"Retail Goods"
        }
    ],
    "sg:phone":"+61 7 3266 9419",
    "sg:postcode":"4012",
    "sg:province":"QLD",
    "sg:tags":[
        "manufacturer"
    ],
    "wof:name":"Roca Australia",
    "wof:placetype":"venue"
},
  "geometry": {"coordinates":[153.0677948,-27.4000988007],"type":"Point"}
}