{
  "type": "Feature",
  "properties": {
    "addr:full":"Main St Currie TAS 7256",
    "addr:postcode":"7256",
    "addr:street":"Main St",
    "iso:country":"AU",
    "sg:address":"Main St",
    "sg:city":"Currie",
    "sg:classifiers":[
        {
            "category":"Shopping",
            "subcategory":"Clothing, Apparel, & Fashions",
            "type":"Retail Goods"
        }
    ],
    "sg:phone":"+61 3 6462 1711",
    "sg:postcode":"7256",
    "sg:province":"TAS",
    "sg:tags":[
        "menswear"
    ],
    "wof:name":"Philbey's Mens & Boyswear",
    "wof:placetype":"venue"
},
  "geometry": {"coordinates":[143.85075378400001,-39.930896759],"type":"Point"}
}