{
  "type": "Feature",
  "properties": {
    "addr:full":"184 Marshall Rd Rocklea QLD 4106",
    "addr:housenumber":"184",
    "addr:postcode":"4106",
    "addr:street":"Marshall Rd",
    "iso:country":"AU",
    "sg:address":"184 Marshall Rd",
    "sg:city":"Rocklea",
    "sg:classifiers":[
        {
            "category":"Home & Garden",
            "subcategory":"Hardware",
            "type":"Retail Goods"
        }
    ],
    "sg:phone":"+61 7 3277 6655",
    "sg:postcode":"4106",
    "sg:province":"QLD",
    "sg:tags":[
        "plumber",
        "supply"
    ],
    "wof:name":"Gatic",
    "wof:placetype":"venue"
},
  "geometry": {"coordinates":[153.01019287099999,-27.5537567139],"type":"Point"}
}