{
  "type": "Feature",
  "properties": {
    "addr:full":"136a Eighth St Mildura VIC 3500",
    "addr:housenumber":"136a",
    "addr:postcode":"3500",
    "addr:street":"Eighth St",
    "iso:country":"AU",
    "sg:address":"136a Eighth St",
    "sg:city":"Mildura",
    "sg:classifiers":[
        {
            "category":"Cafe",
            "type":"Food & Drink"
        }
    ],
    "sg:phone":"+61 3 5023 5655",
    "sg:postcode":"3500",
    "sg:province":"VIC",
    "wof:name":"Folkways Cafe",
    "wof:placetype":"venue"
},
  "geometry": {"coordinates":[142.16192626899999,-34.1842193604],"type":"Point"}
}