{
  "type": "Feature",
  "properties": {
    "addr:full":"307 Forest Rd Hurstville NSW 2220",
    "addr:housenumber":"307",
    "addr:postcode":"2220",
    "addr:street":"Forest Rd",
    "iso:country":"AU",
    "sg:address":"307 Forest Rd",
    "sg:city":"Hurstville",
    "sg:classifiers":[
        {
            "category":"Health Services",
            "subcategory":"Optometrist",
            "type":"Services"
        }
    ],
    "sg:phone":"+61 2 9570 9861",
    "sg:postcode":"2220",
    "sg:province":"NSW",
    "wof:name":"Eye2see",
    "wof:placetype":"venue"
},
  "geometry": {"coordinates":[151.100372314,-33.9653015137],"type":"Point"}
}