{
  "type": "Feature",
  "properties": {
    "addr:full":"269 South Western Hwy Armadale WA 6112",
    "addr:housenumber":"269",
    "addr:postcode":"6112",
    "addr:street":"South Western Hwy",
    "iso:country":"AU",
    "sg:address":"269 South Western Hwy",
    "sg:city":"Armadale",
    "sg:classifiers":[
        {
            "category":"Retail",
            "subcategory":"Auto Repair",
            "type":"Services"
        }
    ],
    "sg:phone":"+61 8 9399 9773",
    "sg:postcode":"6112",
    "sg:province":"WA",
    "sg:tags":[
        "repairer",
        "motor",
        "engineer"
    ],
    "wof:name":"Nick Palumbo Auto Repairs",
    "wof:placetype":"venue"
},
  "geometry": {"coordinates":[116.014968872,-32.1717033386],"type":"Point"}
}