{
  "type": "Feature",
  "properties": {
    "addr:full":"Rocky Ponds Rd Galong NSW 2585",
    "addr:postcode":"2585",
    "addr:street":"Ponds Rd",
    "iso:country":"AU",
    "sg:address":"Rocky Ponds Rd",
    "sg:city":"Galong",
    "sg:classifiers":[
        {
            "category":"Education",
            "subcategory":"School",
            "type":"Public Place"
        }
    ],
    "sg:phone":"+61 2 6386 7264",
    "sg:postcode":"2585",
    "sg:province":"NSW",
    "sg:tags":[
        "state",
        "-",
        "nsw"
    ],
    "wof:name":"Galong Public School",
    "wof:placetype":"venue"
},
  "geometry": {"coordinates":[148.55763244600001,-34.5987625122],"type":"Point"}
}