{
  "type": "Feature",
  "properties": {
    "addr:full":"11 Nolan St Bendigo VIC 3550",
    "addr:housenumber":"11",
    "addr:postcode":"3550",
    "addr:street":"Nolan St",
    "iso:country":"AU",
    "sg:address":"11 Nolan St",
    "sg:city":"Bendigo",
    "sg:classifiers":[
        {
            "category":"Home & Garden",
            "subcategory":"Household Appliances",
            "type":"Retail Goods"
        }
    ],
    "sg:phone":"+61 3 5442 5188",
    "sg:postcode":"3550",
    "sg:province":"VIC",
    "sg:tags":[
        "equipment",
        "gas"
    ],
    "wof:name":"Inland Heating & Cooling",
    "wof:placetype":"venue"
},
  "geometry": {"coordinates":[144.27528381400001,-36.7709465027],"type":"Point"}
}