{
  "type": "Feature",
  "properties": {
    "addr:full":"238 Shellharbour Rd Warilla NSW 2528",
    "addr:housenumber":"238",
    "addr:postcode":"2528",
    "addr:street":"Shellharbour Rd",
    "iso:country":"AU",
    "sg:address":"238 Shellharbour Rd",
    "sg:city":"Warilla",
    "sg:classifiers":[
        {
            "category":"Shopping",
            "subcategory":"Clothing, Apparel, & Fashions",
            "type":"Retail Goods"
        }
    ],
    "sg:phone":"+61 2 4296 1798",
    "sg:postcode":"2528",
    "sg:province":"NSW",
    "sg:tags":[
        "recycled",
        "clothing"
    ],
    "wof:name":"Salvos Stores",
    "wof:placetype":"venue"
},
  "geometry": {"coordinates":[150.859664917,-34.5594291687],"type":"Point"}
}