{
  "type": "Feature",
  "properties": {
    "iso:country":"AU",
    "sg:address":"School Rd",
    "sg:city":"Gunbower",
    "sg:classifiers":[
        {
            "category":"Education",
            "subcategory":"School",
            "type":"Public Place"
        }
    ],
    "sg:phone":"+61 3 5487 1323",
    "sg:postcode":"3566",
    "sg:province":"VIC",
    "sg:tags":[
        "state",
        "except",
        "nsw"
    ],
    "wof:name":"Gunbower Primary School",
    "wof:placetype":"venue"
},
  "geometry": {"coordinates":[144.363281,-35.95607],"type":"Point"}
}