{
  "type": "Feature",
  "properties": {
    "addr:full":"95 Bonds Rd Punchbowl NSW 2196",
    "addr:housenumber":"95",
    "addr:postcode":"2196",
    "addr:street":"Bonds Rd",
    "iso:country":"AU",
    "sg:address":"95 Bonds Rd",
    "sg:city":"Punchbowl",
    "sg:classifiers":[
        {
            "category":"Professional",
            "subcategory":"Detective & Security Services",
            "type":"Services"
        }
    ],
    "sg:phone":"+61 2 9534 5777",
    "sg:postcode":"2196",
    "sg:province":"NSW",
    "sg:tags":[
        "identification",
        "system"
    ],
    "wof:name":"Pegasus Printing",
    "wof:placetype":"venue"
},
  "geometry": {"coordinates":[151.06141700000001,-33.937592],"type":"Point"}
}