{
  "type": "Feature",
  "properties": {
    "iso:country":"AU",
    "sg:address":"95 Bonds Rd",
    "sg:city":"Punchbowl",
    "sg:classifiers":[
        {
            "category":"Professional",
            "subcategory":"Detective & Security Services",
            "type":"Services"
        }
    ],
    "sg:phone":"+61 2 9534 5777",
    "sg:postcode":"2196",
    "sg:province":"NSW",
    "sg:tags":[
        "identification",
        "system"
    ],
    "wof:name":"Pegasus Printing",
    "wof:placetype":"venue"
},
  "geometry": {"coordinates":[151.061417,-33.937592],"type":"Point"}
}