{
  "type": "Feature",
  "properties": {
    "iso:country":"AU",
    "sg:address":"210 Bannister Rd",
    "sg:city":"Canning Vale",
    "sg:classifiers":[
        {
            "category":"Food & Beverages",
            "subcategory":"Liquor & Beverages",
            "type":"Retail Goods"
        }
    ],
    "sg:phone":"+61 8 9256 2077",
    "sg:postcode":"6155",
    "sg:province":"WA",
    "sg:tags":[
        "store"
    ],
    "wof:name":"Cellarbrations",
    "wof:placetype":"venue"
},
  "geometry": {"coordinates":[115.90406,-32.062347],"type":"Point"}
}