{
  "type": "Feature",
  "properties": {
    "addr:full":"Lot 11 Cessnock St Cessnock NSW 2325",
    "addr:postcode":"2325",
    "addr:street":"St",
    "iso:country":"AU",
    "sg:address":"Lot 11 Cessnock St",
    "sg:city":"Cessnock",
    "sg:classifiers":[
        {
            "category":"Retail",
            "subcategory":"Auto Repair",
            "type":"Services"
        }
    ],
    "sg:phone":"+61 1300 764 111",
    "sg:postcode":"2325",
    "sg:province":"NSW",
    "sg:tags":[
        "repairer",
        "motor",
        "engineer"
    ],
    "wof:name":"Ray Prescott Automotive Services",
    "wof:placetype":"venue"
},
  "geometry": {"coordinates":[151.356323242,-32.8414115906],"type":"Point"}
}