{
  "type": "Feature",
  "properties": {
    "addr:full":"PO Box 56 Toukley NSW 2263",
    "addr:postcode":"2263",
    "iso:country":"AU",
    "sg:address":"PO Box 56",
    "sg:city":"Toukley",
    "sg:classifiers":[
        {
            "category":"Building & Trades",
            "subcategory":"Plumbing",
            "type":"Services"
        }
    ],
    "sg:phone":"+61 407 972 909",
    "sg:postcode":"2263",
    "sg:province":"NSW",
    "sg:tags":[
        "plumber",
        "gasfitters"
    ],
    "wof:name":"Doug Nelson Plumbing",
    "wof:placetype":"venue"
},
  "geometry": {"coordinates":[151.542877,-33.26408],"type":"Point"}
}