{
  "type": "Feature",
  "properties": {
    "addr:full":"9 Karoonda Rd Rainbow Beach QLD 4581",
    "addr:housenumber":"9",
    "addr:postcode":"4581",
    "addr:street":"Karoonda Rd",
    "iso:country":"AU",
    "sg:address":"9 Karoonda Rd",
    "sg:city":"Rainbow Beach",
    "sg:classifiers":[
        {
            "category":"Retail",
            "subcategory":"Auto Repair",
            "type":"Services"
        }
    ],
    "sg:phone":"+61 7 5486 3144",
    "sg:postcode":"4581",
    "sg:province":"QLD",
    "sg:tags":[
        "repairer",
        "motor",
        "engineer"
    ],
    "wof:name":"Rainbow Beach Tyre & Mechanical Service",
    "wof:placetype":"venue"
},
  "geometry": {"coordinates":[153.08045959500001,-25.8969841003],"type":"Point"}
}