{
  "type": "Feature",
  "properties": {
    "addr:full":"4 Grafton St Blacktown NSW 2148",
    "addr:housenumber":"4",
    "addr:postcode":"2148",
    "addr:street":"Grafton St",
    "iso:country":"AU",
    "sg:address":"4 Grafton St",
    "sg:city":"Blacktown",
    "sg:classifiers":[
        {
            "category":"Health Services",
            "subcategory":"Health Practitioner",
            "type":"Services"
        }
    ],
    "sg:phone":"+61 2 9621 8799",
    "sg:postcode":"2148",
    "sg:province":"NSW",
    "sg:tags":[
        "physiotherapist"
    ],
    "wof:name":"O&#039;Connell Steven",
    "wof:placetype":"venue"
},
  "geometry": {"coordinates":[150.91395568900001,-33.7738456726],"type":"Point"}
}