{
  "type": "Feature",
  "properties": {
    "addr:full":"32 Punch St Artarmon NSW 2064",
    "addr:housenumber":"32",
    "addr:postcode":"2064",
    "addr:street":"Punch St",
    "iso:country":"AU",
    "sg:address":"32 Punch St",
    "sg:city":"Artarmon",
    "sg:classifiers":[
        {
            "category":"Utilities",
            "subcategory":"Sewage",
            "type":"Services"
        }
    ],
    "sg:phone":"+61 2 9438 4900",
    "sg:postcode":"2064",
    "sg:province":"NSW",
    "sg:tags":[
        "water",
        "waste",
        "treatment"
    ],
    "wof:name":"Flovac Vacuum Sewerage systems",
    "wof:placetype":"venue"
},
  "geometry": {"coordinates":[151.19017028799999,-33.8143730164],"type":"Point"}
}