{
  "type": "Feature",
  "properties": {
    "addr:full":"Shop 31, HIllarys Shopping Centre, 110 Flinders Av Hillarys WA 6025",
    "addr:housenumber":"shop 31;110",
    "addr:postcode":"6025",
    "addr:street":"Flinders Av",
    "iso:country":"AU",
    "sg:address":"Shop 31, HIllarys Shopping Centre, 110 Flinders Av",
    "sg:city":"Hillarys",
    "sg:classifiers":[
        {
            "category":"Health Services",
            "subcategory":"Dentist",
            "type":"Services"
        }
    ],
    "sg:phone":"+61 8 9403 6400",
    "sg:postcode":"6025",
    "sg:province":"WA",
    "wof:name":"Draper Michael Dr",
    "wof:placetype":"venue"
},
  "geometry": {"coordinates":[115.747802734,-31.8074951172],"type":"Point"}
}