{
  "type": "Feature",
  "properties": {
    "iso:country":"AU",
    "sg:address":"Shop 10, 220 Target Hill Rd",
    "sg:city":"Greenwith",
    "sg:classifiers":[
        {
            "category":"Personal",
            "subcategory":"Beauty Salon",
            "type":"Services"
        }
    ],
    "sg:phone":"+61 8 8289 8155",
    "sg:postcode":"5125",
    "sg:province":"SA",
    "sg:tags":[
        "hairdresser"
    ],
    "wof:name":"Golden Grove Hair & Beauty Centre",
    "wof:placetype":"venue"
},
  "geometry": {"coordinates":[138.71286,-34.772034],"type":"Point"}
}