{
  "type": "Feature",
  "properties": {
    "addr:full":"48 Maitland St Bingara NSW 2404",
    "addr:housenumber":"48",
    "addr:postcode":"2404",
    "addr:street":"Maitland St",
    "iso:country":"AU",
    "sg:address":"48 Maitland St",
    "sg:city":"Bingara",
    "sg:classifiers":[
        {
            "category":"Shopping",
            "subcategory":"Clothing, Apparel, & Fashions",
            "type":"Retail Goods"
        }
    ],
    "sg:phone":"+61 2 6724 1745",
    "sg:postcode":"2404",
    "sg:province":"NSW",
    "sg:tags":[
        "lady",
        "wear"
    ],
    "wof:name":"Boutique Capri",
    "wof:placetype":"venue"
},
  "geometry": {"coordinates":[150.571365356,-29.8678321838],"type":"Point"}
}