{
  "type": "Feature",
  "properties": {
    "iso:country":"AU",
    "sg:address":"15 Webber Pde",
    "sg:city":"Keilor East",
    "sg:classifiers":[
        {
            "category":"Wholesale",
            "subcategory":"Furniture",
            "type":"Manufacturing & Wholesale Goods"
        }
    ],
    "sg:phone":"+61 3 9331 5288",
    "sg:postcode":"3033",
    "sg:province":"VIC",
    "sg:tags":[
        "wholesaler",
        "mfrs"
    ],
    "wof:name":"Brava Aust Pty Ltd",
    "wof:placetype":"venue"
},
  "geometry": {"coordinates":[144.855087,-37.736259],"type":"Point"}
}