{
  "type": "Feature",
  "properties": {
    "addr:full":"852 Sydney Rd Brunswick VIC 3056",
    "addr:housenumber":"852",
    "addr:postcode":"3056",
    "addr:street":"Sydney Rd",
    "iso:country":"AU",
    "sg:address":"852 Sydney Rd",
    "sg:city":"Brunswick",
    "sg:classifiers":[
        {
            "category":"Food & Beverages",
            "subcategory":"Groceries & Convenience Stores",
            "type":"Retail Goods"
        }
    ],
    "sg:phone":"+61 3 9386 7790",
    "sg:postcode":"3056",
    "sg:province":"VIC",
    "wof:name":"Bismini Mart",
    "wof:placetype":"venue"
},
  "geometry": {"coordinates":[144.96406555199999,-37.7566947937],"type":"Point"}
}