{
  "type": "Feature",
  "properties": {
    "iso:country":"AU",
    "sg:address":"164 Kilaben Rd",
    "sg:city":"Kilaben Bay",
    "sg:classifiers":[
        {
            "category":"Professional",
            "subcategory":"Business Services",
            "type":"Services"
        }
    ],
    "sg:phone":"+61 409 152 746",
    "sg:postcode":"2283",
    "sg:province":"NSW",
    "sg:tags":[
        "drafting"
    ],
    "wof:name":"MLG Drafting Service Pty Ltd",
    "wof:placetype":"venue"
},
  "geometry": {"coordinates":[151.55111694300001,-33.0066833496],"type":"Point"}
}