{
  "type": "Feature",
  "properties": {
    "iso:country":"AU",
    "sg:address":"9/ 1468 Anzac Ave",
    "sg:city":"Kallangur",
    "sg:classifiers":[
        {
            "category":"Real Estate",
            "subcategory":"Real Estate Agent",
            "type":"Services"
        }
    ],
    "sg:phone":"+61 7 3204 4546",
    "sg:postcode":"4503",
    "sg:province":"QLD",
    "wof:name":"PRD Nationwide Realty",
    "wof:placetype":"venue"
},
  "geometry": {"coordinates":[152.99774169899999,-27.2495212555],"type":"Point"}
}