{
  "type": "Feature",
  "properties": {
    "iso:country":"AU",
    "sg:address":"Suite 1/ 11",
    "sg:city":"Karp Ct Bundall",
    "sg:classifiers":[
        {
            "category":"Banks & Credit Unions",
            "subcategory":"Bank",
            "type":"Services"
        }
    ],
    "sg:phone":"+61 1800 697 526",
    "sg:postcode":"4217",
    "sg:province":"QLD",
    "sg:tags":[
        "broker",
        "mortgage"
    ],
    "wof:name":"My Mortgage Planner",
    "wof:placetype":"venue"
},
  "geometry": {"coordinates":[153.41308593799999,-28.0008411407],"type":"Point"}
}