{
  "type": "Feature",
  "properties": {
    "addr:full":"Shop 19 Maddington Shopping Centre Maddington WA 6109",
    "addr:housenumber":"shop 19",
    "addr:postcode":"6109",
    "iso:country":"AU",
    "sg:address":"Shop 19",
    "sg:city":"Maddington Shopping Centre Maddington",
    "sg:classifiers":[
        {
            "category":"Shopping",
            "subcategory":"Clothing, Apparel, & Fashions",
            "type":"Retail Goods"
        }
    ],
    "sg:phone":"+61 8 9493 5332",
    "sg:postcode":"6109",
    "sg:province":"WA",
    "sg:tags":[
        "lingerie",
        "hosiery",
        "sleepwear"
    ],
    "wof:name":"Bras &#039;N&#039; Things",
    "wof:placetype":"venue"
},
  "geometry": {"coordinates":[116.01087188699999,-32.0391387939],"type":"Point"}
}