{
  "type": "Feature",
  "properties": {
    "addr:full":"Cnr Illawarra St & Sixth Ave Port Kembla NSW 2505",
    "addr:postcode":"2505",
    "addr:street":"Cnr Illawarra St & Sixth Ave",
    "iso:country":"AU",
    "sg:address":"Cnr Illawarra St & Sixth Ave",
    "sg:city":"Port Kembla",
    "sg:classifiers":[
        {
            "category":"Retail",
            "subcategory":"Auto Repair",
            "type":"Services"
        }
    ],
    "sg:phone":"+61 2 4274 2782",
    "sg:postcode":"2505",
    "sg:province":"NSW",
    "sg:tags":[
        "electrical"
    ],
    "wof:name":"Magnetic Auto Electrics",
    "wof:placetype":"venue"
},
  "geometry": {"coordinates":[150.90145899999999,-34.486462],"type":"Point"}
}