{
  "type": "Feature",
  "properties": {
    "addr:full":"4 Terminus St Castle Hill NSW 2154",
    "addr:housenumber":"4",
    "addr:postcode":"2154",
    "addr:street":"Terminus St",
    "iso:country":"AU",
    "sg:address":"4 Terminus St",
    "sg:city":"Castle Hill",
    "sg:classifiers":[
        {
            "category":"Food & Beverages",
            "subcategory":"Supermarket",
            "type":"Retail Goods"
        }
    ],
    "sg:phone":"+61 2 9634 3043",
    "sg:postcode":"2154",
    "sg:province":"NSW",
    "sg:tags":[
        "grocery",
        "store"
    ],
    "wof:name":"Franklins Limited",
    "wof:placetype":"venue"
},
  "geometry": {"coordinates":[151.00640869099999,-33.7334098816],"type":"Point"}
}