{
  "type": "Feature",
  "properties": {
    "iso:country":"AU",
    "sg:address":"75 Wood St",
    "sg:city":"White Gum Valley",
    "sg:classifiers":[
        {
            "category":"Building & Trades",
            "subcategory":"Cleaning & Sanitation",
            "type":"Services"
        }
    ],
    "sg:phone":"+61 413 059 799",
    "sg:postcode":"6162",
    "sg:province":"WA",
    "sg:tags":[
        "window"
    ],
    "wof:name":"Kenkleen Canning Vale",
    "wof:placetype":"venue"
},
  "geometry": {"coordinates":[115.76367999999999,-32.061836],"type":"Point"}
}