{
  "type": "Feature",
  "properties": {
    "addr:full":"382 Raymond St Sale VIC 3850",
    "addr:housenumber":"382",
    "addr:postcode":"3850",
    "addr:street":"Raymond St",
    "iso:country":"AU",
    "sg:address":"382 Raymond St",
    "sg:city":"Sale",
    "sg:classifiers":[
        {
            "category":"Professional",
            "subcategory":"Accounting & Tax Preparation",
            "type":"Services"
        }
    ],
    "sg:phone":"+61 3 5144 5063",
    "sg:postcode":"3850",
    "sg:province":"VIC",
    "sg:tags":[
        "accountant",
        "auditor"
    ],
    "wof:name":"Chirnside & Associates",
    "wof:placetype":"venue"
},
  "geometry": {"coordinates":[147.065643311,-38.1046676636],"type":"Point"}
}