{
  "type": "Feature",
  "properties": {
    "addr:full":"4 George St Murrumbeena VIC 3163",
    "addr:housenumber":"4",
    "addr:postcode":"3163",
    "addr:street":"George St",
    "iso:country":"AU",
    "sg:address":"4 George St",
    "sg:city":"Murrumbeena",
    "sg:classifiers":[
        {
            "category":"Shopping",
            "subcategory":"Computers & Home Electronics",
            "type":"Retail Goods"
        }
    ],
    "sg:phone":"+61 3 9563 8133",
    "sg:postcode":"3163",
    "sg:province":"VIC",
    "sg:tags":[
        "equipment",
        "part",
        "electronic"
    ],
    "wof:name":"Streamline Electrics",
    "wof:placetype":"venue"
},
  "geometry": {"coordinates":[145.074127197,-37.9051513672],"type":"Point"}
}