{
  "type": "Feature",
  "properties": {
    "iso:country":"AU",
    "sg:address":"40 Bombala St",
    "sg:city":"Nimmitabel",
    "sg:classifiers":[
        {
            "category":"Food & Beverages",
            "subcategory":"Bakery",
            "type":"Retail Goods"
        }
    ],
    "sg:phone":"+61 2 6454 6436",
    "sg:postcode":"2631",
    "sg:province":"NSW",
    "sg:tags":[
        "baker"
    ],
    "wof:name":"Nimmitabel Bakery",
    "wof:placetype":"venue"
},
  "geometry": {"coordinates":[149.280319214,-36.5188179016],"type":"Point"}
}