{
  "type": "Feature",
  "properties": {
    "addr:full":"5 West End St Katoomba NSW 2780",
    "addr:housenumber":"5",
    "addr:postcode":"2780",
    "addr:street":"West;St",
    "iso:country":"AU",
    "sg:address":"5 West End St",
    "sg:city":"Katoomba",
    "sg:classifiers":[
        {
            "category":"Education",
            "subcategory":"Kindergarten",
            "type":"Public Place"
        }
    ],
    "sg:phone":"+61 2 4782 2156",
    "sg:postcode":"2780",
    "sg:province":"NSW",
    "sg:tags":[
        "pre-schools"
    ],
    "wof:name":"Katoomba Children's Cottage Inc",
    "wof:placetype":"venue"
},
  "geometry": {"coordinates":[150.309783936,-33.7188644409],"type":"Point"}
}