{
  "type": "Feature",
  "properties": {
    "addr:full":"Shop 121 289 Sussex St Sydney NSW 2000",
    "addr:housenumber":"121 289",
    "addr:postcode":"2000",
    "addr:street":"Sussex St",
    "iso:country":"AU",
    "sg:address":"Shop 121 289 Sussex St",
    "sg:city":"Sydney",
    "sg:classifiers":[
        {
            "category":"Retail",
            "subcategory":"Laundry & Dry Cleaning",
            "type":"Services"
        }
    ],
    "sg:phone":"+61 2 9264 6661",
    "sg:postcode":"2000",
    "sg:province":"NSW",
    "wof:name":"City Laundry & Dry Cleaning",
    "wof:placetype":"venue"
},
  "geometry": {"coordinates":[151.20411682100001,-33.8742675781],"type":"Point"}
}