{
  "type": "Feature",
  "properties": {
    "addr:full":"158 Sloane St Goulburn NSW 2580",
    "addr:housenumber":"158",
    "addr:postcode":"2580",
    "addr:street":"Sloane St",
    "iso:country":"AU",
    "sg:address":"158 Sloane St",
    "sg:city":"Goulburn",
    "sg:classifiers":[
        {
            "category":"Wholesale",
            "subcategory":"Painting Supplies",
            "type":"Manufacturing & Wholesale Goods"
        }
    ],
    "sg:phone":"+61 2 4821 5550",
    "sg:postcode":"2580",
    "sg:province":"NSW",
    "sg:tags":[
        "painter"
    ],
    "wof:name":"Goulburn Paint Solutions",
    "wof:placetype":"venue"
},
  "geometry": {"coordinates":[149.71827697800001,-34.7587394714],"type":"Point"}
}