{
  "type": "Feature",
  "properties": {
    "addr:full":"114 Douro St North Geelong VIC 3215",
    "addr:housenumber":"114",
    "addr:postcode":"3215",
    "addr:street":"Douro St",
    "iso:country":"AU",
    "sg:address":"114 Douro St",
    "sg:city":"North Geelong",
    "sg:classifiers":[
        {
            "category":"Manufacturing",
            "subcategory":"Motor Vehicles & Parts",
            "type":"Manufacturing & Wholesale Goods"
        }
    ],
    "sg:phone":"+61 3 5277 2288",
    "sg:postcode":"3215",
    "sg:province":"VIC",
    "sg:tags":[
        "replacement"
    ],
    "wof:name":"Friends Holden Wreckers",
    "wof:placetype":"venue"
},
  "geometry": {"coordinates":[144.34947204599999,-38.1140365601],"type":"Point"}
}