{
  "type": "Feature",
  "properties": {
    "addr:full":"40- 42 Grosvenor St Woollahra NSW 2025",
    "addr:housenumber":"42",
    "addr:postcode":"2025",
    "addr:street":"Grosvenor St",
    "iso:country":"AU",
    "sg:address":"40- 42 Grosvenor St",
    "sg:city":"Woollahra",
    "sg:classifiers":[
        {
            "category":"Government",
            "subcategory":"Court House",
            "type":"Public Place"
        }
    ],
    "sg:phone":"+61 2 9387 6966",
    "sg:postcode":"2025",
    "sg:province":"NSW",
    "sg:tags":[
        "personal",
        "marriage",
        "family",
        "counselling"
    ],
    "wof:name":"Haines Dr. Amelia",
    "wof:placetype":"venue"
},
  "geometry": {"coordinates":[151.24945068400001,-33.8905067444],"type":"Point"}
}