{
  "type": "Feature",
  "properties": {
    "addr:full":"Shop 7A, Kmart Plaza, Cnr Blackburn Rd & Burwood Hwy Burwood East VIC 3151",
    "addr:housenumber":"shop 7a",
    "addr:postcode":"3151",
    "addr:street":"Plaza Cnr Blackburn Rd & Burwood Hwy",
    "iso:country":"AU",
    "sg:address":"Shop 7A, Kmart Plaza, Cnr Blackburn Rd & Burwood Hwy",
    "sg:city":"Burwood East",
    "sg:classifiers":[
        {
            "category":"Food & Beverages",
            "subcategory":"Bakery",
            "type":"Retail Goods"
        }
    ],
    "sg:phone":"+61 3 9886 6855",
    "sg:postcode":"3151",
    "sg:province":"VIC",
    "sg:tags":[
        "cake",
        "shop",
        "pastry"
    ],
    "wof:name":"Ferguson Plarre Bakehouses Pty Ltd",
    "wof:placetype":"venue"
},
  "geometry": {"coordinates":[145.151687622,-37.85364151],"type":"Point"}
}