{
  "type": "Feature",
  "properties": {
    "addr:full":"40 Cobran Rd Cheltenham NSW 2119",
    "addr:housenumber":"40",
    "addr:postcode":"2119",
    "addr:street":"Cobran Rd",
    "iso:country":"AU",
    "sg:address":"40 Cobran Rd",
    "sg:city":"Cheltenham",
    "sg:classifiers":[
        {
            "category":"Home & Garden",
            "subcategory":"Furniture",
            "type":"Retail Goods"
        }
    ],
    "sg:phone":"+61 2 9868 1515",
    "sg:postcode":"2119",
    "sg:province":"NSW",
    "sg:tags":[
        "business"
    ],
    "wof:name":"The Fundamentals Footrests",
    "wof:placetype":"venue"
},
  "geometry": {"coordinates":[151.084182739,-33.7557525635],"type":"Point"}
}