{
  "type": "Feature",
  "properties": {
    "addr:full":"PO Box 57 Riverton WA 6148",
    "addr:postcode":"6148",
    "iso:country":"AU",
    "sg:address":"PO Box 57",
    "sg:city":"Riverton",
    "sg:classifiers":[
        {
            "category":"Insurance",
            "subcategory":"Hazard Insurance",
            "type":"Services"
        }
    ],
    "sg:phone":"+61 8 9457 0235",
    "sg:postcode":"6148",
    "sg:province":"WA",
    "sg:tags":[
        "loss",
        "adjuster",
        "assessor"
    ],
    "wof:name":"Ace Assessing Services",
    "wof:placetype":"venue"
},
  "geometry": {"coordinates":[115.893822,-32.030602],"type":"Point"}
}