{
  "type": "Feature",
  "properties": {
    "addr:full":"228 Military Rd Dover Heights NSW 2030",
    "addr:housenumber":"228",
    "addr:postcode":"2030",
    "addr:street":"Military Rd",
    "iso:country":"AU",
    "sg:address":"228 Military Rd",
    "sg:city":"Dover Heights",
    "sg:classifiers":[
        {
            "category":"Real Estate",
            "subcategory":"Developer",
            "type":"Services"
        }
    ],
    "sg:phone":"+61 2 9371 6892",
    "sg:postcode":"2030",
    "sg:province":"NSW",
    "sg:tags":[
        "development"
    ],
    "wof:name":"Hitter Group",
    "wof:placetype":"venue"
},
  "geometry": {"coordinates":[151.28073120100001,-33.8719596863],"type":"Point"}
}