{
  "type": "Feature",
  "properties": {
    "iso:country":"AU",
    "sg:address":"64-66 Boat Harbour Drv",
    "sg:city":"Pialba",
    "sg:classifiers":[
        {
            "category":"Home & Garden",
            "subcategory":"Carpets & Floor Coverings",
            "type":"Retail Goods"
        }
    ],
    "sg:phone":"+61 7 4124 2413",
    "sg:postcode":"4655",
    "sg:province":"QLD",
    "sg:tags":[
        "tile",
        "wall"
    ],
    "sg:website":"http://www.galaxytiles.com.au",
    "wof:name":"Galaxy Tile Imports and Floor Coverings",
    "wof:placetype":"venue"
},
  "geometry": {"coordinates":[152.841324,-25.288754],"type":"Point"}
}