{
  "type": "Feature",
  "properties": {
    "addr:full":"8 Munro St Coburg VIC 3058",
    "addr:housenumber":"8",
    "addr:postcode":"3058",
    "addr:street":"Munro St",
    "iso:country":"AU",
    "sg:address":"8 Munro St",
    "sg:city":"Coburg",
    "sg:classifiers":[
        {
            "category":"Personal",
            "subcategory":"Hair Removal",
            "type":"Services"
        }
    ],
    "sg:phone":"+61 3 9354 2728",
    "sg:postcode":"3058",
    "sg:province":"VIC",
    "wof:name":"Lets Face It Beauty Studio",
    "wof:placetype":"venue"
},
  "geometry": {"coordinates":[144.96499633799999,-37.744682312],"type":"Point"}
}