{
  "type": "Feature",
  "properties": {
    "iso:country":"AU",
    "sg:address":"PO Box 338",
    "sg:city":"Beecroft",
    "sg:classifiers":[
        {
            "category":"Professional",
            "subcategory":"Management & Consulting",
            "type":"Services"
        }
    ],
    "sg:phone":"+61 2 9634 5458",
    "sg:postcode":"2119",
    "sg:province":"NSW",
    "sg:tags":[
        "consultant"
    ],
    "wof:name":"MindAct",
    "wof:placetype":"venue"
},
  "geometry": {"coordinates":[151.06483459500001,-33.7503204346],"type":"Point"}
}