{
  "type": "Feature",
  "properties": {
    "addr:full":"4 Frazer St Lakemba NSW 2195",
    "addr:housenumber":"4",
    "addr:postcode":"2195",
    "addr:street":"Frazer St",
    "iso:country":"AU",
    "sg:address":"4 Frazer St",
    "sg:city":"Lakemba",
    "sg:classifiers":[
        {
            "category":"Real Estate",
            "subcategory":"Architect",
            "type":"Services"
        }
    ],
    "sg:phone":"+61 2 9759 5598",
    "sg:postcode":"2195",
    "sg:province":"NSW",
    "sg:tags":[
        "fuel",
        "equipment",
        "pump",
        "carburettor"
    ],
    "wof:name":"Midel Pty Ltd",
    "wof:placetype":"venue"
},
  "geometry": {"coordinates":[151.076019,-33.911289],"type":"Point"}
}