{
  "type": "Feature",
  "properties": {
    "iso:country":"AU",
    "sg:address":"82 Gibson St",
    "sg:city":"Bowden",
    "sg:classifiers":[
        {
            "category":"Utilities",
            "subcategory":"Electric",
            "type":"Services"
        }
    ],
    "sg:phone":"+61 8 8340 0900",
    "sg:postcode":"5007",
    "sg:province":"SA",
    "sg:tags":[
        "electrical",
        "contractor"
    ],
    "wof:name":"Quality Electrical Services (Sa) Pty Ltd",
    "wof:placetype":"venue"
},
  "geometry": {"coordinates":[138.57972717300001,-34.9030456543],"type":"Point"}
}