{
  "type": "Feature",
  "properties": {
    "iso:country":"AU",
    "sg:address":"65 Wellington St",
    "sg:city":"Longford",
    "sg:classifiers":[
        {
            "category":"Wholesale",
            "subcategory":"Medical Equipment & Supplies",
            "type":"Manufacturing & Wholesale Goods"
        }
    ],
    "sg:phone":"+61 3 6391 1327",
    "sg:postcode":"7301",
    "sg:province":"TAS",
    "sg:tags":[
        "aid",
        "care",
        "health",
        "home"
    ],
    "wof:name":"Armstrong Pharmacy",
    "wof:placetype":"venue"
},
  "geometry": {"coordinates":[147.12231399999999,-41.594341],"type":"Point"}
}