{
  "type": "Feature",
  "properties": {
    "addr:full":"25 Mandible St Alexandria NSW 2015",
    "addr:housenumber":"25",
    "addr:postcode":"2015",
    "addr:street":"Mandible St",
    "iso:country":"AU",
    "sg:address":"25 Mandible St",
    "sg:city":"Alexandria",
    "sg:classifiers":[
        {
            "category":"Home & Garden",
            "subcategory":"Building Materials",
            "type":"Retail Goods"
        }
    ],
    "sg:phone":"+61 2 9318 0022",
    "sg:postcode":"2015",
    "sg:province":"NSW",
    "sg:tags":[
        "pre-mixed",
        "concrete"
    ],
    "wof:name":"Concrite",
    "wof:placetype":"venue"
},
  "geometry": {"coordinates":[151.19891357399999,-33.9050331116],"type":"Point"}
}