{
  "type": "Feature",
  "properties": {
    "addr:full":"59 Wyrallah Rd Lismore NSW 2480",
    "addr:housenumber":"59",
    "addr:postcode":"2480",
    "addr:street":"Wyrallah Rd",
    "iso:country":"AU",
    "sg:address":"59 Wyrallah Rd",
    "sg:city":"Lismore",
    "sg:classifiers":[
        {
            "category":"Home & Garden",
            "subcategory":"Furniture",
            "type":"Retail Goods"
        }
    ],
    "sg:phone":"+61 2 6622 3533",
    "sg:postcode":"2480",
    "sg:province":"NSW",
    "sg:tags":[
        "business"
    ],
    "wof:name":"Lizzy's Furniture",
    "wof:placetype":"venue"
},
  "geometry": {"coordinates":[153.285354614,-28.8200721741],"type":"Point"}
}