{
  "type": "Feature",
  "properties": {
    "addr:full":"5- 15 Labilliere St Bacchus Marsh VIC 3340",
    "addr:housenumber":"15",
    "addr:postcode":"3340",
    "addr:street":"5;St",
    "iso:country":"AU",
    "sg:address":"5- 15 Labilliere St",
    "sg:city":"Bacchus Marsh",
    "sg:classifiers":[
        {
            "category":"Sports & Exercise",
            "subcategory":"Gym",
            "type":"Entertainment"
        }
    ],
    "sg:phone":"+61 3 5367 6650",
    "sg:postcode":"3340",
    "sg:province":"VIC",
    "sg:tags":[
        "health",
        "fitness"
    ],
    "wof:name":"Bacchus Marsh Leisure Centre",
    "wof:placetype":"venue"
},
  "geometry": {"coordinates":[144.43182400000001,-37.683903],"type":"Point"}
}