{
  "type": "Feature",
  "properties": {
    "iso:country":"AU",
    "sg:address":"85 Farrants Rd",
    "sg:city":"Werribee South",
    "sg:classifiers":[
        {
            "category":"Food & Beverages",
            "subcategory":"Fruits & Vegetables",
            "type":"Retail Goods"
        }
    ],
    "sg:phone":"+61 3 9742 1320",
    "sg:postcode":"3030",
    "sg:province":"VIC",
    "sg:tags":[
        "grower"
    ],
    "wof:name":"R & A Baggio & Sons",
    "wof:placetype":"venue"
},
  "geometry": {"coordinates":[144.68095400000001,-37.959656],"type":"Point"}
}