{
  "type": "Feature",
  "properties": {
    "iso:country":"AU",
    "sg:address":"1/ 41 Charters Towers Rd",
    "sg:city":"Townsville",
    "sg:classifiers":[
        {
            "category":"Building & Trades",
            "subcategory":"Construction",
            "type":"Services"
        }
    ],
    "sg:phone":"+61 7 4721 5922",
    "sg:postcode":"4810",
    "sg:province":"QLD",
    "sg:tags":[
        "fencing",
        "contractor"
    ],
    "wof:name":"Superior Screens",
    "wof:placetype":"venue"
},
  "geometry": {"coordinates":[146.80358899999999,-19.272734],"type":"Point"}
}