{
  "type": "Feature",
  "properties": {
    "addr:full":"13 Phillip St St George QLD 4487",
    "addr:housenumber":"13",
    "addr:postcode":"4487",
    "addr:street":"Phillip St",
    "iso:country":"AU",
    "sg:address":"13 Phillip St",
    "sg:city":"St George",
    "sg:classifiers":[
        {
            "category":"Farming",
            "subcategory":"Farm & Veterinary Services",
            "type":"Manufacturing & Wholesale Goods"
        }
    ],
    "sg:phone":"+61 7 4625 4367",
    "sg:postcode":"4487",
    "sg:province":"QLD",
    "sg:tags":[
        "contracting"
    ],
    "wof:name":"Ron's Row Weeding",
    "wof:placetype":"venue"
},
  "geometry": {"coordinates":[148.58096313499999,-28.0376491547],"type":"Point"}
}