{
  "type": "Feature",
  "properties": {
    "iso:country":"AU",
    "sg:address":"U22/ 2-8 Campbell St",
    "sg:city":"Artarmon",
    "sg:classifiers":[
        {
            "category":"Wholesale",
            "subcategory":"Vending Machines",
            "type":"Manufacturing & Wholesale Goods"
        }
    ],
    "sg:phone":"+61 2 9901 3399",
    "sg:postcode":"2064",
    "sg:province":"NSW",
    "sg:tags":[
        "equipment",
        "mailing"
    ],
    "wof:name":"Mail Tech Pty Ltd",
    "wof:placetype":"venue"
},
  "geometry": {"coordinates":[151.18661499000001,-33.8174438477],"type":"Point"}
}