{
  "type": "Feature",
  "properties": {
    "addr:full":"11 Durward Ave Glen Waverley VIC 3150",
    "addr:housenumber":"11",
    "addr:postcode":"3150",
    "addr:street":"Durward Ave",
    "iso:country":"AU",
    "sg:address":"11 Durward Ave",
    "sg:city":"Glen Waverley",
    "sg:classifiers":[
        {
            "category":"Utilities",
            "subcategory":"Electric",
            "type":"Services"
        }
    ],
    "sg:phone":"+61 3 9802 8638",
    "sg:postcode":"3150",
    "sg:province":"VIC",
    "sg:tags":[
        "electrical",
        "contractor"
    ],
    "wof:name":"P.S.T. Electrical Services",
    "wof:placetype":"venue"
},
  "geometry": {"coordinates":[145.15133667000001,-37.8901939392],"type":"Point"}
}