{
  "type": "Feature",
  "properties": {
    "addr:full":"Shop 2 153 Prince Edward Ave Culburra NSW 2540",
    "addr:housenumber":"shop 2 153",
    "addr:postcode":"2540",
    "addr:street":"Prince Edward Ave",
    "iso:country":"AU",
    "sg:address":"Shop 2 153 Prince Edward Ave",
    "sg:city":"Culburra",
    "sg:classifiers":[
        {
            "category":"Fast Food",
            "type":"Food & Drink"
        }
    ],
    "sg:phone":"+61 2 4447 3633",
    "sg:postcode":"2540",
    "sg:province":"NSW",
    "sg:tags":[
        "away",
        "take"
    ],
    "wof:name":"Culburra-Bamboleo Pizzeria Cafe",
    "wof:placetype":"venue"
},
  "geometry": {"coordinates":[150.75944519000001,-34.9295501709],"type":"Point"}
}