{
  "type": "Feature",
  "properties": {
    "addr:full":"2a Victoria St Hall ACT 2618",
    "addr:housenumber":"2a",
    "addr:postcode":"2618",
    "addr:street":"Victoria St",
    "iso:country":"AU",
    "sg:address":"2a Victoria St",
    "sg:city":"Hall",
    "sg:classifiers":[
        {
            "category":"Manufacturing",
            "subcategory":"Metals",
            "type":"Manufacturing & Wholesale Goods"
        }
    ],
    "sg:phone":"+61 2 6230 2600",
    "sg:postcode":"2618",
    "sg:province":"ACT",
    "sg:tags":[
        "fabricator",
        "aluminium"
    ],
    "wof:name":"Hall Metal Fabrications",
    "wof:placetype":"venue"
},
  "geometry": {"coordinates":[149.07057189899999,-35.1708831787],"type":"Point"}
}