{
  "type": "Feature",
  "properties": {
    "addr:full":"17 Century Drv Braeside VIC 3195",
    "addr:housenumber":"17",
    "addr:postcode":"3195",
    "addr:street":"Century Drv",
    "iso:country":"AU",
    "sg:address":"17 Century Drv",
    "sg:city":"Braeside",
    "sg:classifiers":[
        {
            "category":"Professional",
            "type":"Services"
        }
    ],
    "sg:phone":"+61 3 9580 8166",
    "sg:postcode":"3195",
    "sg:province":"VIC",
    "sg:tags":[
        "packaging",
        "filling",
        "assembling"
    ],
    "wof:name":"Beau-Pack (Vic) Pty Ltd",
    "wof:placetype":"venue"
},
  "geometry": {"coordinates":[145.10786438,-38.002696991],"type":"Point"}
}