{
  "type": "Feature",
  "properties": {
    "iso:country":"AU",
    "sg:address":"Unit 12/ 398 Marion St",
    "sg:city":"Condell Park",
    "sg:classifiers":[
        {
            "category":"Military Area",
            "subcategory":"Air Force Base",
            "type":"Public Place"
        }
    ],
    "sg:phone":"+61 2 9796 3125",
    "sg:postcode":"2200",
    "sg:province":"NSW",
    "sg:tags":[
        "box",
        "case",
        "wood"
    ],
    "wof:name":"Gray N E",
    "wof:placetype":"venue"
},
  "geometry": {"coordinates":[151.00176999999999,-33.916405],"type":"Point"}
}