{
  "type": "Feature",
  "properties": {
    "iso:country":"AU",
    "sg:address":"12 Denham Crs",
    "sg:city":"Rural View",
    "sg:classifiers":[
        {
            "category":"Professional",
            "type":"Services"
        }
    ],
    "sg:phone":"+61 7 4969 6100",
    "sg:postcode":"4740",
    "sg:province":"QLD",
    "sg:tags":[
        "shop",
        "fitting"
    ],
    "wof:name":"SJ Taylor Constructions Pty Ltd",
    "wof:placetype":"venue"
},
  "geometry": {"coordinates":[149.160294,-21.057791],"type":"Point"}
}