{
  "type": "Feature",
  "properties": {
    "addr:full":"26 Angle St Balgowlah NSW 2093",
    "addr:housenumber":"26",
    "addr:postcode":"2093",
    "addr:street":"Angle St",
    "iso:country":"AU",
    "sg:address":"26 Angle St",
    "sg:city":"Balgowlah",
    "sg:classifiers":[
        {
            "category":"Shopping",
            "subcategory":"News",
            "type":"Retail Goods"
        }
    ],
    "sg:phone":"+61 2 9949 4255",
    "sg:postcode":"2093",
    "sg:province":"NSW",
    "sg:tags":[
        "magazine",
        "periodical"
    ],
    "wof:name":"Sydney Concierge Map",
    "wof:placetype":"venue"
},
  "geometry": {"coordinates":[151.262374878,-33.7931785583],"type":"Point"}
}