{
  "type": "Feature",
  "properties": {
    "addr:full":"182 Fairy St Warrnambool VIC 3280",
    "addr:housenumber":"182",
    "addr:postcode":"3280",
    "addr:street":"Fairy St",
    "iso:country":"AU",
    "sg:address":"182 Fairy St",
    "sg:city":"Warrnambool",
    "sg:classifiers":[
        {
            "category":"Real Estate",
            "subcategory":"Real Estate Agent",
            "type":"Services"
        }
    ],
    "sg:phone":"+61 3 5560 5508",
    "sg:postcode":"3280",
    "sg:province":"VIC",
    "wof:name":"McNally Property Management P/L",
    "wof:placetype":"venue"
},
  "geometry": {"coordinates":[142.48127746599999,-38.3788414001],"type":"Point"}
}