{
  "type": "Feature",
  "properties": {
    "iso:country":"AU",
    "sg:address":"24 William St",
    "sg:city":"Cobram",
    "sg:classifiers":[
        {
            "category":"Personal",
            "subcategory":"Shoe Repair & Shine",
            "type":"Services"
        }
    ],
    "sg:phone":"+61 3 5872 2611",
    "sg:postcode":"3644",
    "sg:province":"VIC",
    "sg:tags":[
        "footwear"
    ],
    "wof:name":"Mantovani Shoe & Leather Repairs",
    "wof:placetype":"venue"
},
  "geometry": {"coordinates":[145.65089416500001,-35.9197349548],"type":"Point"}
}