{
  "type": "Feature",
  "properties": {
    "addr:full":"52 Adelong Rd Tumut NSW 2720",
    "addr:housenumber":"52",
    "addr:postcode":"2720",
    "addr:street":"Adelong Rd",
    "iso:country":"AU",
    "sg:address":"52 Adelong Rd",
    "sg:city":"Tumut",
    "sg:classifiers":[
        {
            "category":"Retail",
            "subcategory":"Auto Repair",
            "type":"Services"
        }
    ],
    "sg:phone":"+61 2 6947 6374",
    "sg:postcode":"2720",
    "sg:province":"NSW",
    "sg:tags":[
        "repairer",
        "motor",
        "engineer"
    ],
    "wof:name":"Tumut Holden Service Centre",
    "wof:placetype":"venue"
},
  "geometry": {"coordinates":[148.21286000000001,-35.295727],"type":"Point"}
}