{
  "type": "Feature",
  "properties": {
    "addr:full":"544 Whitehorse Rd Balwyn VIC 3103",
    "addr:housenumber":"544",
    "addr:postcode":"3103",
    "addr:street":"Whitehorse Rd",
    "iso:country":"AU",
    "sg:address":"544 Whitehorse Rd",
    "sg:city":"Balwyn",
    "sg:classifiers":[
        {
            "category":"Real Estate",
            "subcategory":"Real Estate Agent",
            "type":"Services"
        }
    ],
    "sg:phone":"+61 3 9830 7000",
    "sg:postcode":"3103",
    "sg:province":"VIC",
    "wof:name":"Hocking Stuart",
    "wof:placetype":"venue"
},
  "geometry": {"coordinates":[145.099212647,-37.8150978088],"type":"Point"}
}