{
  "type": "Feature",
  "properties": {
    "addr:full":"St Matthews Parish Cntr Queen Elizabeth Sq Dean St Albury NSW 2640",
    "addr:postcode":"2640",
    "addr:street":"Elizabeth Sq Dean St",
    "iso:country":"AU",
    "sg:address":"St Matthews Parish Cntr Queen Elizabeth Sq Dean St",
    "sg:city":"Albury",
    "sg:classifiers":[
        {
            "category":"Social Services",
            "subcategory":"Child Care",
            "type":"Services"
        }
    ],
    "sg:phone":"+61 2 6021 6545",
    "sg:postcode":"2640",
    "sg:province":"NSW",
    "wof:name":"Central Albury Occasional Childcare Centre",
    "wof:placetype":"venue"
},
  "geometry": {"coordinates":[146.905197144,-36.0793991089],"type":"Point"}
}