{
  "type": "Feature",
  "properties": {
    "addr:full":"56 Rae St Colac VIC 3250",
    "addr:housenumber":"56",
    "addr:postcode":"3250",
    "addr:street":"Rae St",
    "iso:country":"AU",
    "sg:address":"56 Rae St",
    "sg:city":"Colac",
    "sg:classifiers":[
        {
            "category":"Freight",
            "type":"Transportation"
        }
    ],
    "sg:phone":"+61 3 5232 1000",
    "sg:postcode":"3250",
    "sg:province":"VIC",
    "sg:tags":[
        "light",
        "carrier"
    ],
    "wof:name":"Fraser's Transport",
    "wof:placetype":"venue"
},
  "geometry": {"coordinates":[143.59208699999999,-38.342018],"type":"Point"}
}