{
  "type": "Feature",
  "properties": {
    "iso:country":"AU",
    "sg:address":"40 Renae St",
    "sg:city":"Andergrove",
    "sg:classifiers":[
        {
            "category":"Professional",
            "subcategory":"Secretarial Services",
            "type":"Services"
        }
    ],
    "sg:phone":"+61 7 4955 7800",
    "sg:postcode":"4740",
    "sg:province":"QLD",
    "sg:tags":[
        "typing"
    ],
    "wof:name":"SSS Secretarial Services",
    "wof:placetype":"venue"
},
  "geometry": {"coordinates":[149.193939,-21.086029],"type":"Point"}
}