{
  "type": "Feature",
  "properties": {
    "addr:full":"41- 79 Crystal St Broken Hill NSW 2880",
    "addr:housenumber":"79",
    "addr:postcode":"2880",
    "addr:street":"Crystal St",
    "iso:country":"AU",
    "sg:address":"41- 79 Crystal St",
    "sg:city":"Broken Hill",
    "sg:classifiers":[
        {
            "category":"Professional",
            "subcategory":"Business Services",
            "type":"Services"
        }
    ],
    "sg:phone":"+61 1300 650 058",
    "sg:postcode":"2880",
    "sg:province":"NSW",
    "sg:tags":[
        "small",
        "advisory"
    ],
    "wof:name":"Far Western Business Advisory Service",
    "wof:placetype":"venue"
},
  "geometry": {"coordinates":[141.46051025400001,-31.9630451202],"type":"Point"}
}