{
  "type": "Feature",
  "properties": {
    "iso:country":"AU",
    "sg:address":"7 Pembury Pl",
    "sg:city":"Rocherlea",
    "sg:classifiers":[
        {
            "category":"Building & Trades",
            "subcategory":"Equipment Rental",
            "type":"Services"
        }
    ],
    "sg:phone":"+61 407 268 700",
    "sg:postcode":"7248",
    "sg:province":"TAS",
    "sg:tags":[
        "platform",
        "hire",
        "work",
        "elevating"
    ],
    "wof:name":"Pro Access Hire Pty Ltd",
    "wof:placetype":"venue"
},
  "geometry": {"coordinates":[147.115524292,-41.3737754822],"type":"Point"}
}