{
  "type": "Feature",
  "properties": {
    "addr:full":"250 Main North Rd Clare SA 5453",
    "addr:housenumber":"250",
    "addr:postcode":"5453",
    "addr:street":"Main North Rd",
    "iso:country":"AU",
    "sg:address":"250 Main North Rd",
    "sg:city":"Clare",
    "sg:classifiers":[
        {
            "category":"Food & Beverages",
            "subcategory":"Supermarket",
            "type":"Retail Goods"
        }
    ],
    "sg:phone":"+61 8 8842 2133",
    "sg:postcode":"5453",
    "sg:province":"SA",
    "sg:tags":[
        "grocery",
        "store"
    ],
    "wof:name":"IGA Everyday",
    "wof:placetype":"venue"
},
  "geometry": {"coordinates":[138.61134300000001,-33.832726],"type":"Point"}
}