{
  "type": "Feature",
  "properties": {
    "addr:full":"63 Old College Rd Gatton QLD 4343",
    "addr:housenumber":"63",
    "addr:postcode":"4343",
    "addr:street":"Old College Rd",
    "iso:country":"AU",
    "sg:address":"63 Old College Rd",
    "sg:city":"Gatton",
    "sg:classifiers":[
        {
            "category":"Building & Trades",
            "subcategory":"Construction",
            "type":"Services"
        }
    ],
    "sg:phone":"+61 7 5462 1150",
    "sg:postcode":"4343",
    "sg:province":"QLD",
    "sg:tags":[
        "joiner",
        "carpenter"
    ],
    "wof:name":"Pine Back In Time",
    "wof:placetype":"venue"
},
  "geometry": {"coordinates":[152.28407287600001,-27.5536441803],"type":"Point"}
}