{
  "type": "Feature",
  "properties": {
    "addr:full":"49 Mitchell Ave Molendinar QLD 4214",
    "addr:housenumber":"49",
    "addr:postcode":"4214",
    "addr:street":"Mitchell Ave",
    "iso:country":"AU",
    "sg:address":"49 Mitchell Ave",
    "sg:city":"Molendinar",
    "sg:classifiers":[
        {
            "category":"Real Estate",
            "subcategory":"Real Estate Operator",
            "type":"Services"
        }
    ],
    "sg:phone":"+61 438 188 109",
    "sg:postcode":"4214",
    "sg:province":"QLD",
    "sg:tags":[
        "concrete",
        "pumping"
    ],
    "wof:name":"Allcrete Pumping Services",
    "wof:placetype":"venue"
},
  "geometry": {"coordinates":[153.36843872099999,-27.9788188934],"type":"Point"}
}