{
  "type": "Feature",
  "properties": {
    "addr:full":"913 Rathdowne St Carlton North VIC 3054",
    "addr:housenumber":"913",
    "addr:postcode":"3054",
    "addr:street":"Rathdowne St",
    "iso:country":"AU",
    "sg:address":"913 Rathdowne St",
    "sg:city":"Carlton North",
    "sg:classifiers":[
        {
            "category":"Health Services",
            "subcategory":"Health Practitioner",
            "type":"Services"
        }
    ],
    "sg:phone":"+61 3 9380 2499",
    "sg:postcode":"3054",
    "sg:province":"VIC",
    "sg:tags":[
        "naturopath"
    ],
    "wof:name":"Naturopathic Healthcare",
    "wof:placetype":"venue"
},
  "geometry": {"coordinates":[144.972732544,-37.7828025818],"type":"Point"}
}