{
  "type": "Feature",
  "properties": {
    "addr:full":"52 Midland Rd Mingenew WA 6522",
    "addr:housenumber":"52",
    "addr:postcode":"6522",
    "addr:street":"Midland Rd",
    "iso:country":"AU",
    "sg:address":"52 Midland Rd",
    "sg:city":"Mingenew",
    "sg:classifiers":[
        {
            "category":"Food & Beverages",
            "subcategory":"Supermarket",
            "type":"Retail Goods"
        }
    ],
    "sg:phone":"+61 8 9928 1003",
    "sg:postcode":"6522",
    "sg:province":"WA",
    "sg:tags":[
        "grocery",
        "store"
    ],
    "wof:name":"IGA Supermarkets",
    "wof:placetype":"venue"
},
  "geometry": {"coordinates":[115.442497253,-29.1900424957],"type":"Point"}
}