{
  "type": "Feature",
  "properties": {
    "iso:country":"AU",
    "sg:address":"202 Terrigal Drv (Cnr Terrigal Drv",
    "sg:city":"& Junction Rd) Terrigal",
    "sg:classifiers":[
        {
            "category":"Health Services",
            "subcategory":"Chiropractor",
            "type":"Services"
        }
    ],
    "sg:phone":"+61 2 4385 3253",
    "sg:postcode":"2260",
    "sg:province":"NSW",
    "wof:name":"Seisun John & Stutterd Nicola",
    "wof:placetype":"venue"
},
  "geometry": {"coordinates":[151.437866,-33.44009],"type":"Point"}
}