{
  "type": "Feature",
  "properties": {
    "addr:full":"PO Box 85 Happy Valley SA 5159",
    "addr:postcode":"5159",
    "iso:country":"AU",
    "sg:address":"PO Box 85",
    "sg:city":"Happy Valley",
    "sg:classifiers":[
        {
            "category":"Professional",
            "subcategory":"Printing & Photocopies",
            "type":"Services"
        }
    ],
    "sg:phone":"+61 8 8387 1090",
    "sg:postcode":"5159",
    "sg:province":"SA",
    "sg:tags":[
        "embroidery"
    ],
    "wof:name":"Jakal Enterprises",
    "wof:placetype":"venue"
},
  "geometry": {"coordinates":[138.57586669899999,-35.0831108093],"type":"Point"}
}