{
  "type": "Feature",
  "properties": {
    "iso:country":"AU",
    "sg:address":"9 Loddon St",
    "sg:city":"Kaleen",
    "sg:classifiers":[
        {
            "category":"Personal",
            "subcategory":"Massage",
            "type":"Services"
        }
    ],
    "sg:phone":"+61 2 6241 6716",
    "sg:postcode":"2617",
    "sg:province":"ACT",
    "sg:tags":[
        "therapy"
    ],
    "wof:name":"Nurturing Hands-Joan Fisher",
    "wof:placetype":"venue"
},
  "geometry": {"coordinates":[149.09889221200001,-35.2291679382],"type":"Point"}
}