{
  "type": "Feature",
  "properties": {
    "iso:country":"AU",
    "sg:address":"140 Kathleen Drv",
    "sg:city":"Old Beach",
    "sg:classifiers":[
        {
            "category":"Building & Trades",
            "subcategory":"Construction",
            "type":"Services"
        }
    ],
    "sg:phone":"+61 418 129 366",
    "sg:postcode":"7017",
    "sg:province":"TAS",
    "sg:tags":[
        "contractor"
    ],
    "wof:name":"Budd A J",
    "wof:placetype":"venue"
},
  "geometry": {"coordinates":[147.31559753400001,-42.7478027344],"type":"Point"}
}