{
  "type": "Feature",
  "properties": {
    "addr:full":"31/ 10 Gladstone Rd Castle Hill NSW 2154",
    "addr:housenumber":"31 / 10",
    "addr:postcode":"2154",
    "addr:street":"Gladstone Rd",
    "iso:country":"AU",
    "sg:address":"31/ 10 Gladstone Rd",
    "sg:city":"Castle Hill",
    "sg:classifiers":[
        {
            "category":"Real Estate",
            "subcategory":"Real Estate Agent",
            "type":"Services"
        }
    ],
    "sg:phone":"+61 2 9634 3888",
    "sg:postcode":"2154",
    "sg:province":"NSW",
    "wof:name":"Coutts Industrial Real Estate",
    "wof:placetype":"venue"
},
  "geometry": {"coordinates":[150.975906372,-33.7336883545],"type":"Point"}
}