{
  "type": "Feature",
  "properties": {
    "addr:full":"103-110 Princes Hwy Beaconsfield VIC 3807",
    "addr:housenumber":"103-110",
    "addr:postcode":"3807",
    "addr:street":"Princes Hwy",
    "iso:country":"AU",
    "sg:address":"103-110 Princes Hwy",
    "sg:city":"Beaconsfield",
    "sg:classifiers":[
        {
            "category":"Retail",
            "subcategory":"Storage",
            "type":"Services"
        }
    ],
    "sg:phone":"+61 3 9707 5700",
    "sg:postcode":"3807",
    "sg:province":"VIC",
    "sg:tags":[
        "removal",
        "furniture"
    ],
    "wof:name":"Berwick Moving & Storage",
    "wof:placetype":"venue"
},
  "geometry": {"coordinates":[145.373046875,-38.0503845215],"type":"Point"}
}