{
  "type": "Feature",
  "properties": {
    "addr:full":"22 Charles St Maffra VIC 3860",
    "addr:housenumber":"22",
    "addr:postcode":"3860",
    "addr:street":"Charles St",
    "iso:country":"AU",
    "sg:address":"22 Charles St",
    "sg:city":"Maffra",
    "sg:classifiers":[
        {
            "category":"Building & Trades",
            "subcategory":"Construction",
            "type":"Services"
        }
    ],
    "sg:phone":"+61 3 5147 1473",
    "sg:postcode":"3860",
    "sg:province":"VIC",
    "sg:tags":[
        "contractor"
    ],
    "wof:name":"Lemchens & Skulte Pty Ltd",
    "wof:placetype":"venue"
},
  "geometry": {"coordinates":[146.97923278799999,-37.9580917358],"type":"Point"}
}