{
  "type": "Feature",
  "properties": {
    "addr:full":"331 Lennox St Richmond VIC 3121",
    "addr:housenumber":"331",
    "addr:postcode":"3121",
    "addr:street":"Lennox St",
    "iso:country":"AU",
    "sg:address":"331 Lennox St",
    "sg:city":"Richmond",
    "sg:classifiers":[
        {
            "category":"Personal",
            "subcategory":"Beauty Salon",
            "type":"Services"
        }
    ],
    "sg:phone":"+61 3 9428 4666",
    "sg:postcode":"3121",
    "sg:province":"VIC",
    "sg:tags":[
        "hairdresser"
    ],
    "wof:name":"Scissors For Hair",
    "wof:placetype":"venue"
},
  "geometry": {"coordinates":[144.993606567,-37.8247795105],"type":"Point"}
}