{
  "type": "Feature",
  "properties": {
    "addr:full":"Unit 13, 211 Dunmore St Wentworthville NSW 2145",
    "addr:housenumber":"211",
    "addr:postcode":"2145",
    "addr:street":"Dunmore St",
    "iso:country":"AU",
    "sg:address":"Unit 13, 211 Dunmore St",
    "sg:city":"Wentworthville",
    "sg:classifiers":[
        {
            "category":"Real Estate",
            "subcategory":"Real Estate Operator",
            "type":"Services"
        }
    ],
    "sg:phone":"+61 413 551 096",
    "sg:postcode":"2145",
    "sg:province":"NSW",
    "sg:tags":[
        "building",
        "consultant",
        "management"
    ],
    "wof:name":"Seenohe Painting & Decorations.",
    "wof:placetype":"venue"
},
  "geometry": {"coordinates":[150.96014404300001,-33.8049201965],"type":"Point"}
}