{
  "type": "Feature",
  "properties": {
    "addr:full":"15- 17 Hope St South Brisbane QLD 4101",
    "addr:housenumber":"17",
    "addr:postcode":"4101",
    "addr:street":"Hope St",
    "iso:country":"AU",
    "sg:address":"15- 17 Hope St",
    "sg:city":"South Brisbane",
    "sg:classifiers":[
        {
            "category":"Food & Beverages",
            "subcategory":"Meat & Fish",
            "type":"Retail Goods"
        }
    ],
    "sg:phone":"+61 7 3844 2247",
    "sg:postcode":"4101",
    "sg:province":"QLD",
    "sg:tags":[
        "seafood"
    ],
    "wof:name":"Gambaro's Seafoods Retail",
    "wof:placetype":"venue"
},
  "geometry": {"coordinates":[153.01585388199999,-27.4719276428],"type":"Point"}
}