{
  "type": "Feature",
  "properties": {
    "addr:full":"29 Caroline Crs Blackburn North VIC 3130",
    "addr:housenumber":"29",
    "addr:postcode":"3130",
    "addr:street":"Caroline Crs",
    "iso:country":"AU",
    "sg:address":"29 Caroline Crs",
    "sg:city":"Blackburn North",
    "sg:classifiers":[
        {
            "category":"Building & Trades",
            "subcategory":"Plumbing",
            "type":"Services"
        }
    ],
    "sg:phone":"+61 413 212 276",
    "sg:postcode":"3130",
    "sg:province":"VIC",
    "sg:tags":[
        "plumber",
        "gasfitters"
    ],
    "wof:name":"YahPoo Plumbing",
    "wof:placetype":"venue"
},
  "geometry": {"coordinates":[145.137329102,-37.8092041016],"type":"Point"}
}