{
  "type": "Feature",
  "properties": {
    "iso:country":"AU",
    "sg:address":"7 Beddi Rd",
    "sg:city":"Duncraig",
    "sg:classifiers":[
        {
            "category":"Travel",
            "subcategory":"Hostel",
            "type":"Entertainment"
        }
    ],
    "sg:phone":"+61 8 9246 2050",
    "sg:postcode":"6023",
    "sg:province":"WA",
    "sg:tags":[
        "home"
    ],
    "wof:name":"Trinity Village",
    "wof:placetype":"venue"
},
  "geometry": {"coordinates":[115.76474761999999,-31.8401756287],"type":"Point"}
}