{
  "type": "Feature",
  "properties": {
    "addr:full":"PO Box 1792 Sunnybank Hills QLD 4109",
    "addr:postcode":"4109",
    "iso:country":"AU",
    "sg:address":"PO Box 1792",
    "sg:city":"Sunnybank Hills",
    "sg:classifiers":[
        {
            "category":"Utilities",
            "subcategory":"Natural Gas",
            "type":"Services"
        }
    ],
    "sg:phone":"+61 414 355 817",
    "sg:postcode":"4109",
    "sg:province":"QLD",
    "sg:tags":[
        "solid",
        "plasterer"
    ],
    "wof:name":"Allrender Solid Plasterers",
    "wof:placetype":"venue"
},
  "geometry": {"coordinates":[153.05857849099999,-27.598690033],"type":"Point"}
}