{
  "type": "Feature",
  "properties": {
    "addr:full":"Cnr Alexandra Pde & Reeves St Clifton Hill VIC 3068",
    "addr:postcode":"3068",
    "addr:street":"Alexandra;St",
    "iso:country":"AU",
    "sg:address":"Cnr Alexandra Pde & Reeves St",
    "sg:city":"Clifton Hill",
    "sg:classifiers":[
        {
            "category":"Farming",
            "subcategory":"Orchard",
            "type":"Manufacturing & Wholesale Goods"
        }
    ],
    "sg:phone":"+61 3 9486 2644",
    "sg:postcode":"3068",
    "sg:province":"VIC",
    "sg:tags":[
        "wholesaler",
        "jean",
        "mfrs"
    ],
    "wof:name":"Nif Naf",
    "wof:placetype":"venue"
},
  "geometry": {"coordinates":[144.99273681599999,-37.794418335],"type":"Point"}
}