{
  "type": "Feature",
  "properties": {
    "iso:country":"AU",
    "sg:address":"285 Flinders St",
    "sg:city":"Adelaide",
    "sg:classifiers":[
        {
            "category":"Health Services",
            "subcategory":"Doctor",
            "type":"Services"
        }
    ],
    "sg:phone":"+61 8 8232 4200",
    "sg:postcode":"5000",
    "sg:province":"SA",
    "sg:tags":[
        "medical",
        "practitioner"
    ],
    "wof:name":"Scroop Andrew",
    "wof:placetype":"venue"
},
  "geometry": {"coordinates":[138.610717773,-34.9267425537],"type":"Point"}
}