{
  "type": "Feature",
  "properties": {
    "addr:full":"17 Paine Ave Moorebank NSW 2170",
    "addr:housenumber":"17",
    "addr:postcode":"2170",
    "addr:street":"Paine Ave",
    "iso:country":"AU",
    "sg:address":"17 Paine Ave",
    "sg:city":"Moorebank",
    "sg:classifiers":[
        {
            "category":"Building & Trades",
            "subcategory":"Construction",
            "type":"Services"
        }
    ],
    "sg:phone":"+61 411 773 870",
    "sg:postcode":"2170",
    "sg:province":"NSW",
    "sg:tags":[
        "concrete",
        "contractor"
    ],
    "wof:name":"Nick's Concrete Resurfacing",
    "wof:placetype":"venue"
},
  "geometry": {"coordinates":[150.94847106899999,-33.9412002563],"type":"Point"}
}