{
  "type": "Feature",
  "properties": {
    "addr:full":"22 Stenhouse Ave Brooklyn VIC 3012",
    "addr:housenumber":"22",
    "addr:postcode":"3012",
    "addr:street":"Stenhouse Ave",
    "iso:country":"AU",
    "sg:address":"22 Stenhouse Ave",
    "sg:city":"Brooklyn",
    "sg:classifiers":[
        {
            "category":"Manufacturing",
            "subcategory":"Food",
            "type":"Manufacturing & Wholesale Goods"
        }
    ],
    "sg:phone":"+61 424 568 177",
    "sg:postcode":"3012",
    "sg:province":"VIC",
    "sg:tags":[
        "function",
        "catering"
    ],
    "wof:name":"Wheel Wine & Dine You",
    "wof:placetype":"venue"
},
  "geometry": {"coordinates":[144.847259522,-37.8194198608],"type":"Point"}
}