{
  "type": "Feature",
  "properties": {
    "addr:full":"3 Straphmont Drv Strathalbyn SA 5255",
    "addr:housenumber":"3",
    "addr:postcode":"5255",
    "addr:street":"Straphmont Drv",
    "iso:country":"AU",
    "sg:address":"3 Straphmont Drv",
    "sg:city":"Strathalbyn",
    "sg:classifiers":[
        {
            "category":"Manufacturing",
            "subcategory":"Tools & Machinery",
            "type":"Manufacturing & Wholesale Goods"
        }
    ],
    "sg:phone":"+61 8 8536 3219",
    "sg:postcode":"5255",
    "sg:province":"SA",
    "wof:name":"Statewide Tools",
    "wof:placetype":"venue"
},
  "geometry": {"coordinates":[138.90072631800001,-35.2642326355],"type":"Point"}
}