{
  "type": "Feature",
  "properties": {
    "addr:full":"25 Marlborough St Adelaide SA 5000",
    "addr:housenumber":"25",
    "addr:postcode":"5000",
    "addr:street":"Marlborough St",
    "iso:country":"AU",
    "sg:address":"25 Marlborough St",
    "sg:city":"Adelaide",
    "sg:classifiers":[
        {
            "category":"Professional",
            "subcategory":"Computer Services",
            "type":"Services"
        }
    ],
    "sg:phone":"+61 8 8410 6066",
    "sg:postcode":"5000",
    "sg:province":"SA",
    "sg:tags":[
        "scanning",
        "document"
    ],
    "wof:name":"Unique Image",
    "wof:placetype":"venue"
},
  "geometry": {"coordinates":[138.59127807600001,-34.930355072],"type":"Point"}
}