{
  "type": "Feature",
  "properties": {
    "iso:country":"AU",
    "sg:address":"6 Girraween Crt",
    "sg:city":"Sunshine Beach",
    "sg:classifiers":[
        {
            "category":"Health Services",
            "subcategory":"Health Practitioner",
            "type":"Services"
        }
    ],
    "sg:phone":"+61 7 5455 3882",
    "sg:postcode":"4567",
    "sg:province":"QLD",
    "sg:tags":[
        "osteopath"
    ],
    "wof:name":"McLeish Skye Noosa Osteopathy",
    "wof:placetype":"venue"
},
  "geometry": {"coordinates":[153.10041809099999,-26.4074077606],"type":"Point"}
}