{
  "type": "Feature",
  "properties": {
    "addr:full":"459 Main Nth Rd Enfield SA 5085",
    "addr:housenumber":"459",
    "addr:postcode":"5085",
    "addr:street":"Main Nth Rd",
    "iso:country":"AU",
    "sg:address":"459 Main Nth Rd",
    "sg:city":"Enfield",
    "sg:classifiers":[
        {
            "category":"Autos & Motor Vehicles",
            "subcategory":"Automobile Sales",
            "type":"Retail Goods"
        }
    ],
    "sg:phone":"+61 8 8262 4447",
    "sg:postcode":"5085",
    "sg:province":"SA",
    "sg:tags":[
        "car",
        "used"
    ],
    "wof:name":"Adelaide Vehicle Centre",
    "wof:placetype":"venue"
},
  "geometry": {"coordinates":[138.60086059599999,-34.8543395996],"type":"Point"}
}