{
  "type": "Feature",
  "properties": {
    "addr:full":"1A / 42 Stanbel Rd Salisbury Plain SA 5109",
    "addr:housenumber":"1a / 42",
    "addr:postcode":"5109",
    "addr:street":"Stanbel Rd",
    "iso:country":"AU",
    "sg:address":"1A / 42 Stanbel Rd",
    "sg:city":"Salisbury Plain",
    "sg:classifiers":[
        {
            "category":"Manufacturing",
            "subcategory":"Furniture",
            "type":"Manufacturing & Wholesale Goods"
        }
    ],
    "sg:phone":"+61 8 8281 7581",
    "sg:postcode":"5109",
    "sg:province":"SA",
    "sg:tags":[
        "builder",
        "designer",
        "custom"
    ],
    "wof:name":"Burton Originals Cabinet Maker",
    "wof:placetype":"venue"
},
  "geometry": {"coordinates":[138.65640258799999,-34.7674026489],"type":"Point"}
}