{
  "type": "Feature",
  "properties": {
    "iso:country":"AU",
    "sg:address":"38- 40 Young St",
    "sg:city":"Wollongong",
    "sg:classifiers":[
        {
            "category":"Real Estate",
            "subcategory":"Real Estate Agent",
            "type":"Services"
        }
    ],
    "sg:phone":"+61 2 4228 7822",
    "sg:postcode":"2500",
    "sg:province":"NSW",
    "wof:name":"Bevans Real Estate Group - Illawarra",
    "wof:placetype":"venue"
},
  "geometry": {"coordinates":[150.890366,-34.423126],"type":"Point"}
}