{
  "type": "Feature",
  "properties": {
    "iso:country":"AU",
    "sg:address":"PO Box 36385",
    "sg:city":"Winnellie",
    "sg:classifiers":[
        {
            "category":"Shopping",
            "subcategory":"Party Supplies",
            "type":"Retail Goods"
        }
    ],
    "sg:phone":"+61 407 615 097",
    "sg:postcode":"0821",
    "sg:province":"NT",
    "sg:tags":[
        "children's"
    ],
    "wof:name":"Kid&#039;z Fun Biz",
    "wof:placetype":"venue"
},
  "geometry": {"coordinates":[130.87991332999999,-12.4266233444],"type":"Point"}
}