{
  "type": "Feature",
  "properties": {
    "iso:country":"AU",
    "sg:address":"24 Brook St",
    "sg:city":"Toowoomba",
    "sg:classifiers":[
        {
            "category":"Shopping",
            "subcategory":"Antiques",
            "type":"Retail Goods"
        }
    ],
    "sg:phone":"+61 7 4638 2258",
    "sg:postcode":"4350",
    "sg:province":"QLD",
    "sg:tags":[
        "restoration",
        "reproduction"
    ],
    "wof:name":"Trost Upholstery",
    "wof:placetype":"venue"
},
  "geometry": {"coordinates":[151.94593800000001,-27.543674],"type":"Point"}
}