{
  "type": "Feature",
  "properties": {
    "iso:country":"AU",
    "sg:address":"265 Swan St",
    "sg:city":"Richmond",
    "sg:classifiers":[
        {
            "category":"Professional",
            "subcategory":"Computer Services",
            "type":"Services"
        }
    ],
    "sg:phone":"+61 3 9429 4033",
    "sg:postcode":"3121",
    "sg:province":"VIC",
    "sg:tags":[
        "consultant",
        "system"
    ],
    "wof:name":"So-Rite Data Systems",
    "wof:placetype":"venue"
},
  "geometry": {"coordinates":[145.00143432600001,-37.8259239197],"type":"Point"}
}