{
  "type": "Feature",
  "properties": {
    "iso:country":"AU",
    "sg:address":"101 Bell St",
    "sg:city":"Heidelberg West",
    "sg:classifiers":[
        {
            "category":"Autos & Motor Vehicles",
            "subcategory":"Auto Supplies",
            "type":"Retail Goods"
        }
    ],
    "sg:phone":"+61 3 9459 7516",
    "sg:postcode":"3081",
    "sg:province":"VIC",
    "sg:tags":[
        "camper-trailers",
        "caravan",
        "equipment"
    ],
    "wof:name":"Evernew Caravans Pty Ltd",
    "wof:placetype":"venue"
},
  "geometry": {"coordinates":[145.05232238799999,-37.7536315918],"type":"Point"}
}