{
  "type": "Feature",
  "properties": {
    "iso:country":"AU",
    "sg:address":"330 Hobart Rd",
    "sg:city":"Kings Meadows",
    "sg:classifiers":[
        {
            "category":"Fast Food",
            "type":"Food & Drink"
        }
    ],
    "sg:phone":"+61 3 6344 6646",
    "sg:postcode":"7249",
    "sg:province":"TAS",
    "sg:tags":[
        "away",
        "take"
    ],
    "wof:name":"Spiders Diner",
    "wof:placetype":"venue"
},
  "geometry": {"coordinates":[147.167312622,-41.4824104309],"type":"Point"}
}