{
  "type": "Feature",
  "properties": {
    "addr:full":"1/ 67 Pakington St Geelong West VIC 3218",
    "addr:housenumber":"/ 67",
    "addr:postcode":"3218",
    "addr:street":"Pakington St",
    "iso:country":"AU",
    "sg:address":"1/ 67 Pakington St",
    "sg:city":"Geelong West",
    "sg:classifiers":[
        {
            "category":"Building & Trades",
            "subcategory":"Construction",
            "type":"Services"
        }
    ],
    "sg:phone":"+61 3 5229 1372",
    "sg:postcode":"3218",
    "sg:province":"VIC",
    "sg:tags":[
        "window",
        "aluminium"
    ],
    "wof:name":"Grange Windows",
    "wof:placetype":"venue"
},
  "geometry": {"coordinates":[144.34901428200001,-38.1359939575],"type":"Point"}
}