{
  "type": "Feature",
  "properties": {
    "addr:full":"Unit C1, Capital Business Park 3 Rodborough Rd Frenchs Forest NSW 2086",
    "addr:housenumber":"3",
    "addr:postcode":"2086",
    "addr:street":"Park;Rodborough Rd",
    "iso:country":"AU",
    "sg:address":"Unit C1, Capital Business Park 3 Rodborough Rd",
    "sg:city":"Frenchs Forest",
    "sg:classifiers":[
        {
            "category":"Shopping",
            "subcategory":"Antiques",
            "type":"Retail Goods"
        }
    ],
    "sg:phone":"+61 2 9898 1070",
    "sg:postcode":"2086",
    "sg:province":"NSW",
    "sg:tags":[
        "collectable",
        "memorabilia"
    ],
    "wof:name":"Magic Moments Memorabilia.",
    "wof:placetype":"venue"
},
  "geometry": {"coordinates":[151.243774414,-33.753742218],"type":"Point"}
}