{
  "type": "Feature",
  "properties": {
    "iso:country":"AU",
    "sg:address":"3 Junction Rd",
    "sg:city":"Mossman",
    "sg:classifiers":[
        {
            "category":"Retail",
            "subcategory":"Storage",
            "type":"Services"
        }
    ],
    "sg:phone":"+61 409 266 389",
    "sg:postcode":"4873",
    "sg:province":"QLD",
    "sg:tags":[
        "removal",
        "furniture"
    ],
    "wof:name":"Mossman Self Storage",
    "wof:placetype":"venue"
},
  "geometry": {"coordinates":[145.37503051799999,-16.456785202],"type":"Point"}
}