{
  "type": "Feature",
  "properties": {
    "addr:full":"3 Grosvenor Pl Sydney NSW 2000",
    "addr:housenumber":"3",
    "addr:postcode":"2000",
    "addr:street":"Grosvenor Pl",
    "iso:country":"AU",
    "sg:address":"3 Grosvenor Pl",
    "sg:city":"Sydney",
    "sg:classifiers":[
        {
            "category":"Fast Food",
            "type":"Food & Drink"
        }
    ],
    "sg:phone":"+61 2 9252 2744",
    "sg:postcode":"2000",
    "sg:province":"NSW",
    "sg:tags":[
        "away",
        "take"
    ],
    "wof:name":"Fancy Fillings",
    "wof:placetype":"venue"
},
  "geometry": {"coordinates":[151.20576477,-33.8633155823],"type":"Point"}
}