{
  "type": "Feature",
  "properties": {
    "addr:full":"44 Tennyson St Williamstown North VIC 3016",
    "addr:housenumber":"44",
    "addr:postcode":"3016",
    "addr:street":"Tennyson St",
    "iso:country":"AU",
    "sg:address":"44 Tennyson St",
    "sg:city":"Williamstown North",
    "sg:classifiers":[
        {
            "category":"Manufacturing",
            "subcategory":"Metals",
            "type":"Manufacturing & Wholesale Goods"
        }
    ],
    "sg:phone":"+61 3 9397 8385",
    "sg:postcode":"3016",
    "sg:province":"VIC",
    "sg:tags":[
        "wholesaler",
        "aluminium",
        "mfrs"
    ],
    "wof:name":"Adelist Aluminium",
    "wof:placetype":"venue"
},
  "geometry": {"coordinates":[144.86091613799999,-37.8526420593],"type":"Point"}
}