{
  "type": "Feature",
  "properties": {
    "addr:full":"Suite 1 Lvl 5 295- 301 Pitt St Sydney NSW 2000",
    "addr:housenumber":"295 301",
    "addr:postcode":"2000",
    "addr:street":"Pitt St",
    "iso:country":"AU",
    "sg:address":"Suite 1 Lvl 5 295- 301 Pitt St",
    "sg:city":"Sydney",
    "sg:classifiers":[
        {
            "category":"Retail",
            "subcategory":"Repair Shop",
            "type":"Services"
        }
    ],
    "sg:phone":"+61 2 9262 9006",
    "sg:postcode":"2000",
    "sg:province":"NSW",
    "sg:tags":[
        "mending",
        "clothing",
        "alteration"
    ],
    "wof:name":"MK Clothing Alterations",
    "wof:placetype":"venue"
},
  "geometry": {"coordinates":[151.20791625999999,-33.8734474182],"type":"Point"}
}