{
  "type": "Feature",
  "properties": {
    "addr:full":"35 Norval St Auburn NSW 2144",
    "addr:housenumber":"35",
    "addr:postcode":"2144",
    "addr:street":"Norval St",
    "iso:country":"AU",
    "sg:address":"35 Norval St",
    "sg:city":"Auburn",
    "sg:classifiers":[
        {
            "category":"Health Services",
            "subcategory":"Doctor",
            "type":"Services"
        }
    ],
    "sg:phone":"+61 2 9649 8742",
    "sg:postcode":"2144",
    "sg:province":"NSW",
    "sg:tags":[
        "medical",
        "practitioner"
    ],
    "wof:name":"Wegman Eric Dr",
    "wof:placetype":"venue"
},
  "geometry": {"coordinates":[151.03335571299999,-33.8592758179],"type":"Point"}
}