{
  "type": "Feature",
  "properties": {
    "addr:full":"3 Graham St Nowra NSW 2541",
    "addr:housenumber":"3",
    "addr:postcode":"2541",
    "addr:street":"Graham St",
    "iso:country":"AU",
    "sg:address":"3 Graham St",
    "sg:city":"Nowra",
    "sg:classifiers":[
        {
            "category":"Food & Beverages",
            "subcategory":"Fruits & Vegetables",
            "type":"Retail Goods"
        }
    ],
    "sg:phone":"+61 2 4421 0202",
    "sg:postcode":"2541",
    "sg:province":"NSW",
    "sg:tags":[
        "wholesale"
    ],
    "wof:name":"Shoalhaven Fruit Market",
    "wof:placetype":"venue"
},
  "geometry": {"coordinates":[150.60168457,-34.8697776794],"type":"Point"}
}