{
  "type": "Feature",
  "properties": {
    "addr:full":"6- 8 Albert La Taree NSW 2430",
    "addr:housenumber":"8",
    "addr:postcode":"2430",
    "addr:street":"Albert La",
    "iso:country":"AU",
    "sg:address":"6- 8 Albert La",
    "sg:city":"Taree",
    "sg:classifiers":[
        {
            "category":"Professional",
            "subcategory":"Detective & Security Services",
            "type":"Services"
        }
    ],
    "sg:phone":"+61 2 6552 3377",
    "sg:postcode":"2430",
    "sg:province":"NSW",
    "sg:tags":[
        "equipment",
        "window",
        "doors"
    ],
    "wof:name":"Excelsior Glass & Hardware",
    "wof:placetype":"venue"
},
  "geometry": {"coordinates":[152.459045,-31.913364],"type":"Point"}
}