{
  "type": "Feature",
  "properties": {
    "addr:full":"PO Box 395 Kingsford NSW 2032",
    "addr:postcode":"2032",
    "iso:country":"AU",
    "sg:address":"PO Box 395",
    "sg:city":"Kingsford",
    "sg:classifiers":[
        {
            "category":"Health Services",
            "subcategory":"Doctor",
            "type":"Services"
        }
    ],
    "sg:phone":"+61 413 015 191",
    "sg:postcode":"2032",
    "sg:province":"NSW",
    "sg:tags":[
        "occupational",
        "safety"
    ],
    "wof:name":"Envirohs",
    "wof:placetype":"venue"
},
  "geometry": {"coordinates":[151.227493286,-33.9234886169],"type":"Point"}
}