{
  "type": "Feature",
  "properties": {
    "iso:country":"AU",
    "sg:address":"7 Panorama Drv",
    "sg:city":"Bundaberg",
    "sg:classifiers":[
        {
            "category":"Retail",
            "subcategory":"Repair Shop",
            "type":"Services"
        }
    ],
    "sg:phone":"+61 429 194 193",
    "sg:postcode":"4670",
    "sg:province":"QLD",
    "sg:tags":[
        "maintenance",
        "pool",
        "swimming"
    ],
    "wof:name":"MPR Mobile Pump Repairs",
    "wof:placetype":"venue"
},
  "geometry": {"coordinates":[152.424102783,-24.8414173126],"type":"Point"}
}