{
  "type": "Feature",
  "properties": {
    "addr:full":"89 Single Ridge Rd Kurrajong NSW 2758",
    "addr:housenumber":"89",
    "addr:postcode":"2758",
    "addr:street":"Single Ridge Rd",
    "iso:country":"AU",
    "sg:address":"89 Single Ridge Rd",
    "sg:city":"Kurrajong",
    "sg:classifiers":[
        {
            "category":"Manufacturing",
            "subcategory":"Retail Goods",
            "type":"Manufacturing & Wholesale Goods"
        }
    ],
    "sg:phone":"+61 2 4573 1311",
    "sg:postcode":"2758",
    "sg:province":"NSW",
    "sg:tags":[
        "merchant",
        "pump",
        "mfrs"
    ],
    "wof:name":"Ultradrilling Pty Ltd",
    "wof:placetype":"venue"
},
  "geometry": {"coordinates":[150.69917297399999,-33.5325279236],"type":"Point"}
}