{
  "type": "Feature",
  "properties": {
    "iso:country":"AU",
    "sg:address":"24 Station St",
    "sg:city":"Marrickville",
    "sg:classifiers":[
        {
            "category":"Education",
            "subcategory":"Junior College",
            "type":"Public Place"
        }
    ],
    "sg:phone":"+61 2 9558 9788",
    "sg:postcode":"2204",
    "sg:province":"NSW",
    "sg:tags":[
        "business"
    ],
    "wof:name":"Ozi-Land",
    "wof:placetype":"venue"
},
  "geometry": {"coordinates":[151.160568,-33.926563],"type":"Point"}
}