{
  "type": "Feature",
  "properties": {
    "addr:full":"24 Station St Marrickville NSW 2204",
    "addr:housenumber":"24",
    "addr:postcode":"2204",
    "addr:street":"Station St",
    "iso:country":"AU",
    "sg:address":"24 Station St",
    "sg:city":"Marrickville",
    "sg:classifiers":[
        {
            "category":"Education",
            "subcategory":"Junior College",
            "type":"Public Place"
        }
    ],
    "sg:phone":"+61 2 9558 9788",
    "sg:postcode":"2204",
    "sg:province":"NSW",
    "sg:tags":[
        "business"
    ],
    "wof:name":"Ozi-Land",
    "wof:placetype":"venue"
},
  "geometry": {"coordinates":[151.16056800000001,-33.926563],"type":"Point"}
}