{
  "type": "Feature",
  "properties": {
    "addr:full":"Unit 2, 10 McCourt Rd Moss Vale NSW 2577",
    "addr:housenumber":"10",
    "addr:postcode":"2577",
    "addr:street":"Mccourt Rd",
    "iso:country":"AU",
    "sg:address":"Unit 2, 10 McCourt Rd",
    "sg:city":"Moss Vale",
    "sg:classifiers":[
        {
            "category":"Retail",
            "subcategory":"Auto Repair",
            "type":"Services"
        }
    ],
    "sg:phone":"+61 2 4869 1145",
    "sg:postcode":"2577",
    "sg:province":"NSW",
    "sg:tags":[
        "repairer",
        "motor",
        "engineer"
    ],
    "wof:name":"Graham Burns Automotive Pty Ltd",
    "wof:placetype":"venue"
},
  "geometry": {"coordinates":[150.37905883799999,-34.534198761],"type":"Point"}
}