{
  "type": "Feature",
  "properties": {
    "addr:full":"1076 Moggill Rd Kenmore QLD 4069",
    "addr:housenumber":"1076",
    "addr:postcode":"4069",
    "addr:street":"Moggill Rd",
    "iso:country":"AU",
    "sg:address":"1076 Moggill Rd",
    "sg:city":"Kenmore",
    "sg:classifiers":[
        {
            "category":"Education",
            "subcategory":"Kindergarten",
            "type":"Public Place"
        }
    ],
    "sg:phone":"+61 7 3378 2068",
    "sg:postcode":"4069",
    "sg:province":"QLD",
    "sg:tags":[
        "pre-schools"
    ],
    "wof:name":"Kenmore District Kindergarten & Pre-School",
    "wof:placetype":"venue"
},
  "geometry": {"coordinates":[152.940750122,-27.508026123],"type":"Point"}
}