{
  "type": "Feature",
  "properties": {
    "addr:full":"7 Westridge Rd Penguin TAS 7316",
    "addr:housenumber":"7",
    "addr:postcode":"7316",
    "addr:street":"Westridge Rd",
    "iso:country":"AU",
    "sg:address":"7 Westridge Rd",
    "sg:city":"Penguin",
    "sg:classifiers":[
        {
            "category":"Professional",
            "subcategory":"Computer Services",
            "type":"Services"
        }
    ],
    "sg:phone":"+61 3 6437 2355",
    "sg:postcode":"7316",
    "sg:province":"TAS",
    "sg:tags":[
        "repairs",
        "upgrade",
        "equipment"
    ],
    "wof:name":"Mink Systems",
    "wof:placetype":"venue"
},
  "geometry": {"coordinates":[146.06263732900001,-41.1067008972],"type":"Point"}
}