{
  "type": "Feature",
  "properties": {
    "addr:full":"49 Perversi Ave Diamond Creek VIC 3089",
    "addr:housenumber":"49",
    "addr:postcode":"3089",
    "addr:street":"Perversi Ave",
    "iso:country":"AU",
    "sg:address":"49 Perversi Ave",
    "sg:city":"Diamond Creek",
    "sg:classifiers":[
        {
            "category":"Home & Garden",
            "subcategory":"Building Materials",
            "type":"Retail Goods"
        }
    ],
    "sg:phone":"+61 418 354 939",
    "sg:postcode":"3089",
    "sg:province":"VIC",
    "sg:tags":[
        "gate"
    ],
    "wof:name":"Diamond Valley Gates",
    "wof:placetype":"venue"
},
  "geometry": {"coordinates":[145.173508,-37.673431],"type":"Point"}
}