{
  "type": "Feature",
  "properties": {
    "addr:full":"2 Knights Bridge Crs Mullaloo WA 6027",
    "addr:housenumber":"2",
    "addr:postcode":"6027",
    "addr:street":"Knights Bridge Crs",
    "iso:country":"AU",
    "sg:address":"2 Knights Bridge Crs",
    "sg:city":"Mullaloo",
    "sg:classifiers":[
        {
            "category":"Shopping",
            "subcategory":"Computers & Home Electronics",
            "type":"Retail Goods"
        }
    ],
    "sg:phone":"+61 8 9307 2236",
    "sg:postcode":"6027",
    "sg:province":"WA",
    "sg:tags":[
        "equipment",
        "supply"
    ],
    "wof:name":"Dereglen Agencies",
    "wof:placetype":"venue"
},
  "geometry": {"coordinates":[115.74329376199999,-31.7780704498],"type":"Point"}
}