{
  "type": "Feature",
  "properties": {
    "addr:full":"Ward St Salisbury Heights SA 5109",
    "addr:postcode":"5109",
    "addr:street":"Ward St",
    "iso:country":"AU",
    "sg:address":"Ward St",
    "sg:city":"Salisbury Heights",
    "sg:classifiers":[
        {
            "category":"Education",
            "subcategory":"School",
            "type":"Public Place"
        }
    ],
    "sg:phone":"+61 8 8258 7299",
    "sg:postcode":"5109",
    "sg:province":"SA",
    "sg:tags":[
        "state",
        "except",
        "nsw"
    ],
    "wof:name":"Salisbury Heights Primary Schools",
    "wof:placetype":"venue"
},
  "geometry": {"coordinates":[138.67770385700001,-34.7594566345],"type":"Point"}
}