{
  "type": "Feature",
  "properties": {
    "iso:country":"AU",
    "sg:address":"25 Dixon St",
    "sg:city":"Sunnybank",
    "sg:classifiers":[
        {
            "category":"Mining & Drilling",
            "type":"Manufacturing & Wholesale Goods"
        }
    ],
    "sg:phone":"+61 7 3345 5744",
    "sg:postcode":"4109",
    "sg:province":"QLD",
    "sg:tags":[
        "concrete",
        "breaking",
        "grinding",
        "sawing"
    ],
    "wof:name":"Fyfe & Elliott",
    "wof:placetype":"venue"
},
  "geometry": {"coordinates":[153.05563354500001,-27.5801353455],"type":"Point"}
}