{
  "type": "Feature",
  "properties": {
    "addr:full":"1/227 Ewing Rd Woodridge QLD 4114",
    "addr:housenumber":"/ 227",
    "addr:postcode":"4114",
    "addr:street":"Ewing Rd",
    "iso:country":"AU",
    "sg:address":"1/227 Ewing Rd",
    "sg:city":"Woodridge",
    "sg:classifiers":[
        {
            "category":"Manufacturing",
            "subcategory":"Furniture",
            "type":"Manufacturing & Wholesale Goods"
        }
    ],
    "sg:phone":"+61 7 3290 6383",
    "sg:postcode":"4114",
    "sg:province":"QLD",
    "sg:tags":[
        "builder",
        "designer",
        "custom"
    ],
    "wof:name":"Spacemaster Wardrobe",
    "wof:placetype":"venue"
},
  "geometry": {"coordinates":[153.11032104500001,-27.6552505493],"type":"Point"}
}