{
  "type": "Feature",
  "properties": {
    "iso:country":"AU",
    "sg:address":"27 John St",
    "sg:city":"The Oaks",
    "sg:classifiers":[
        {
            "category":"Retail",
            "subcategory":"Auto Repair",
            "type":"Services"
        }
    ],
    "sg:phone":"+61 2 4657 1123",
    "sg:postcode":"2570",
    "sg:province":"NSW",
    "sg:tags":[
        "repairer",
        "motor",
        "engineer"
    ],
    "wof:name":"S R Noakes & Sons Pty Ltd",
    "wof:placetype":"venue"
},
  "geometry": {"coordinates":[150.57127380399999,-34.0753479004],"type":"Point"}
}