{
  "type": "Feature",
  "properties": {
    "addr:full":"36 Market St Bankstown NSW 2200",
    "addr:housenumber":"36",
    "addr:postcode":"2200",
    "addr:street":"Market St",
    "iso:country":"AU",
    "sg:address":"36 Market St",
    "sg:city":"Bankstown",
    "sg:classifiers":[
        {
            "category":"Professional",
            "subcategory":"Computer Services",
            "type":"Services"
        }
    ],
    "sg:phone":"+61 2 9708 0601",
    "sg:postcode":"2200",
    "sg:province":"NSW",
    "sg:tags":[
        "equipment",
        "networking",
        "installation"
    ],
    "wof:name":"PC-Bug Fixer",
    "wof:placetype":"venue"
},
  "geometry": {"coordinates":[151.02148399999999,-33.91785],"type":"Point"}
}