{
  "type": "Feature",
  "properties": {
    "iso:country":"AU",
    "sg:address":"8 Cross St",
    "sg:city":"Wagga Wagga",
    "sg:classifiers":[
        {
            "category":"Arts & Performance",
            "subcategory":"Theater",
            "type":"Entertainment"
        }
    ],
    "sg:phone":"+61 2 6921 6861",
    "sg:postcode":"2650",
    "sg:province":"NSW",
    "sg:tags":[
        "theatre"
    ],
    "wof:name":"Riverina Playhouse Theatre",
    "wof:placetype":"venue"
},
  "geometry": {"coordinates":[147.37367248499999,-35.1079711914],"type":"Point"}
}