{
  "type": "Feature",
  "properties": {
    "iso:country":"AU",
    "sg:address":"338 South Rd",
    "sg:city":"Croydon Park",
    "sg:classifiers":[
        {
            "category":"Autos & Motor Vehicles",
            "subcategory":"Auto Supplies",
            "type":"Retail Goods"
        }
    ],
    "sg:phone":"+61 8 8241 7888",
    "sg:postcode":"5008",
    "sg:province":"SA",
    "sg:tags":[
        "camper-trailers",
        "caravan",
        "equipment"
    ],
    "sg:website":"http://www.trakshak.com.au",
    "wof:name":"Trak Shak Pty Ltd",
    "wof:placetype":"venue"
},
  "geometry": {"coordinates":[138.571136,-34.876743],"type":"Point"}
}