{
  "type": "Feature",
  "properties": {
    "addr:full":"11 Pobje Ave Birrong NSW 2143",
    "addr:housenumber":"11",
    "addr:postcode":"2143",
    "addr:street":"Pobje Ave",
    "iso:country":"AU",
    "sg:address":"11 Pobje Ave",
    "sg:city":"Birrong",
    "sg:classifiers":[
        {
            "category":"Building & Trades",
            "subcategory":"Cleaning & Sanitation",
            "type":"Services"
        }
    ],
    "sg:phone":"+61 2 9644 9873",
    "sg:postcode":"2143",
    "sg:province":"NSW",
    "sg:tags":[
        "chemical",
        "pressure",
        "steam",
        "contractor"
    ],
    "wof:name":"Fitzroy Cleaning Service",
    "wof:placetype":"venue"
},
  "geometry": {"coordinates":[151.02229309099999,-33.8948097229],"type":"Point"}
}