{
  "type": "Feature",
  "properties": {
    "addr:full":"504 Elizabeth St Melbourne VIC 3000",
    "addr:housenumber":"504",
    "addr:postcode":"3000",
    "addr:street":"Elizabeth St",
    "iso:country":"AU",
    "sg:address":"504 Elizabeth St",
    "sg:city":"Melbourne",
    "sg:classifiers":[
        {
            "category":"Travel",
            "subcategory":"Hotels & Motels",
            "type":"Entertainment"
        }
    ],
    "sg:phone":"+61 3 9663 6237",
    "sg:postcode":"3000",
    "sg:province":"VIC",
    "sg:tags":[
        "accommodation"
    ],
    "wof:name":"Stork Hotel",
    "wof:placetype":"venue"
},
  "geometry": {"coordinates":[144.960113525,-37.8072471619],"type":"Point"}
}