{
  "type": "Feature",
  "properties": {
    "addr:full":"262 High St Preston VIC 3072",
    "addr:housenumber":"262",
    "addr:postcode":"3072",
    "addr:street":"High St",
    "iso:country":"AU",
    "sg:address":"262 High St",
    "sg:city":"Preston",
    "sg:classifiers":[
        {
            "category":"Sports & Exercise",
            "subcategory":"Ski Resort",
            "type":"Entertainment"
        }
    ],
    "sg:phone":"+61 3 9484 9258",
    "sg:postcode":"3072",
    "sg:province":"VIC",
    "sg:tags":[
        "propelled",
        "jet"
    ],
    "wof:name":"Melbourne Seadoo",
    "wof:placetype":"venue"
},
  "geometry": {"coordinates":[145.003372192,-37.7429389954],"type":"Point"}
}