{
  "type": "Feature",
  "properties": {
    "iso:country":"AU",
    "sg:address":"5 Kew Pl",
    "sg:city":"Heritage Park",
    "sg:classifiers":[
        {
            "category":"Personal",
            "subcategory":"Massage",
            "type":"Services"
        }
    ],
    "sg:phone":"+61 7 3803 1648",
    "sg:postcode":"4118",
    "sg:province":"QLD",
    "sg:tags":[
        "therapy"
    ],
    "wof:name":"A Wholistic Approach",
    "wof:placetype":"venue"
},
  "geometry": {"coordinates":[153.05685424800001,-27.6781692505],"type":"Point"}
}