{
  "type": "Feature",
  "properties": {
    "iso:country":"AU",
    "sg:address":"265 Whitehall St",
    "sg:city":"Yarraville",
    "sg:classifiers":[
        {
            "category":"Farming",
            "subcategory":"Fish & Marine Products",
            "type":"Manufacturing & Wholesale Goods"
        }
    ],
    "sg:phone":"+61 3 9283 4500",
    "sg:postcode":"3013",
    "sg:province":"VIC",
    "sg:tags":[
        "chemical",
        "supplier"
    ],
    "wof:name":"CSR Distilleries",
    "wof:placetype":"venue"
},
  "geometry": {"coordinates":[144.89891052199999,-37.8180160522],"type":"Point"}
}