{
  "type": "Feature",
  "properties": {
    "addr:full":"21 Karoola Crs Lindisfarne TAS 7015",
    "addr:housenumber":"21",
    "addr:postcode":"7015",
    "addr:street":"Karoola Crs",
    "iso:country":"AU",
    "sg:address":"21 Karoola Crs",
    "sg:city":"Lindisfarne",
    "sg:classifiers":[
        {
            "category":"Building & Trades",
            "subcategory":"Construction",
            "type":"Services"
        }
    ],
    "sg:phone":"+61 418 146 115",
    "sg:postcode":"7015",
    "sg:province":"TAS",
    "sg:tags":[
        "contractor"
    ],
    "wof:name":"Andrew Hapka Building Contractors",
    "wof:placetype":"venue"
},
  "geometry": {"coordinates":[147.35678100600001,-42.8416519165],"type":"Point"}
}