{
  "type": "Feature",
  "properties": {
    "iso:country":"AU",
    "sg:address":"Upton Plaza 9, 21 Upton St",
    "sg:city":"Bundall",
    "sg:classifiers":[
        {
            "category":"Professional",
            "subcategory":"Testing Lab",
            "type":"Services"
        }
    ],
    "sg:phone":"+61 7 5531 5800",
    "sg:postcode":"4217",
    "sg:province":"QLD",
    "sg:tags":[
        "soil",
        "investigation"
    ],
    "wof:name":"The International Institute Of Soil Technologies Pty Ltd",
    "wof:placetype":"venue"
},
  "geometry": {"coordinates":[153.41026306099999,-28.009223938],"type":"Point"}
}