{
  "type": "Feature",
  "properties": {
    "addr:full":"Cnr Brierley & Liardet Sts Weston ACT 2611",
    "addr:postcode":"2611",
    "addr:street":"Cnr;Sts",
    "iso:country":"AU",
    "sg:address":"Cnr Brierley & Liardet Sts",
    "sg:city":"Weston",
    "sg:classifiers":[
        {
            "category":"Communications",
            "subcategory":"Film & Video Production",
            "type":"Services"
        }
    ],
    "sg:phone":"+61 2 6288 1077",
    "sg:postcode":"2611",
    "sg:province":"ACT",
    "sg:tags":[
        "dvd",
        "library"
    ],
    "wof:name":"Video 2000",
    "wof:placetype":"venue"
},
  "geometry": {"coordinates":[149.05337524399999,-35.3398933411],"type":"Point"}
}