{
  "type": "Feature",
  "properties": {
    "addr:full":"Shop 7 50 Australis Ave Wattle Grove NSW 2173",
    "addr:housenumber":"shop;50",
    "addr:postcode":"2173",
    "addr:street":"Australis Ave",
    "iso:country":"AU",
    "sg:address":"Shop 7 50 Australis Ave",
    "sg:city":"Wattle Grove",
    "sg:classifiers":[
        {
            "category":"Fast Food",
            "type":"Food & Drink"
        }
    ],
    "sg:phone":"+61 2 9731 1333",
    "sg:postcode":"2173",
    "sg:province":"NSW",
    "sg:tags":[
        "away",
        "take"
    ],
    "wof:name":"Piccola Pizzeria",
    "wof:placetype":"venue"
},
  "geometry": {"coordinates":[150.94264221200001,-33.9551010132],"type":"Point"}
}