{
  "type": "Feature",
  "properties": {
    "addr:full":"Shop B6 Stockland, Mc Farlane St Merrylands NSW 2160",
    "addr:housenumber":"b6 stockland",
    "addr:postcode":"2160",
    "addr:street":"Mc Farlane St",
    "iso:country":"AU",
    "sg:address":"Shop B6 Stockland, Mc Farlane St",
    "sg:city":"Merrylands",
    "sg:classifiers":[
        {
            "category":"Deli",
            "type":"Food & Drink"
        }
    ],
    "sg:phone":"+61 2 9682 1146",
    "sg:postcode":"2160",
    "sg:province":"NSW",
    "sg:tags":[
        "delicatessen"
    ],
    "wof:name":"Deli Select",
    "wof:placetype":"venue"
},
  "geometry": {"coordinates":[150.98817443900001,-33.83618927],"type":"Point"}
}