{
  "type": "Feature",
  "properties": {
    "addr:full":"8 Pambula St Pambula NSW 2549",
    "addr:housenumber":"8",
    "addr:postcode":"2549",
    "addr:street":"Pambula St",
    "iso:country":"AU",
    "sg:address":"8 Pambula St",
    "sg:city":"Pambula",
    "sg:classifiers":[
        {
            "category":"Utilities",
            "subcategory":"Electric",
            "type":"Services"
        }
    ],
    "sg:phone":"+61 2 6495 6162",
    "sg:postcode":"2549",
    "sg:province":"NSW",
    "sg:tags":[
        "electrical",
        "contractor"
    ],
    "wof:name":"Savage R J",
    "wof:placetype":"venue"
},
  "geometry": {"coordinates":[149.87188720699999,-36.9241790771],"type":"Point"}
}