{
  "type": "Feature",
  "properties": {
    "iso:country":"AU",
    "sg:address":"200 Doghole Rd",
    "sg:city":"Stockrington",
    "sg:classifiers":[
        {
            "category":"Building & Trades",
            "subcategory":"Plumbing",
            "type":"Services"
        }
    ],
    "sg:phone":"+61 417 288 494",
    "sg:postcode":"2322",
    "sg:province":"NSW",
    "sg:tags":[
        "plumber",
        "gasfitters"
    ],
    "wof:name":"Watts G R & R L",
    "wof:placetype":"venue"
},
  "geometry": {"coordinates":[151.598587036,-32.8585205078],"type":"Point"}
}