{
  "type": "Feature",
  "properties": {
    "addr:full":"68 Commercial St Korumburra VIC 3950",
    "addr:housenumber":"68",
    "addr:postcode":"3950",
    "addr:street":"Commercial St",
    "iso:country":"AU",
    "sg:address":"68 Commercial St",
    "sg:city":"Korumburra",
    "sg:classifiers":[
        {
            "category":"Banks & Credit Unions",
            "subcategory":"Financial Services",
            "type":"Services"
        }
    ],
    "sg:phone":"+61 3 5658 1020",
    "sg:postcode":"3950",
    "sg:province":"VIC",
    "sg:tags":[
        "advisory",
        "planning",
        "retirement"
    ],
    "wof:name":"Retire & Wealth Planners Pty Ltd",
    "wof:placetype":"venue"
},
  "geometry": {"coordinates":[145.82281494099999,-38.4323501587],"type":"Point"}
}