{
  "type": "Feature",
  "properties": {
    "addr:full":"28 Butler St Tewantin QLD 4565",
    "addr:housenumber":"28",
    "addr:postcode":"4565",
    "addr:street":"Butler St",
    "iso:country":"AU",
    "sg:address":"28 Butler St",
    "sg:city":"Tewantin",
    "sg:classifiers":[
        {
            "category":"Building & Trades",
            "subcategory":"Plumbing",
            "type":"Services"
        }
    ],
    "sg:phone":"+61 7 5455 6442",
    "sg:postcode":"4565",
    "sg:province":"QLD",
    "sg:tags":[
        "plumber",
        "gasfitters"
    ],
    "wof:name":"Paul D. Gill Plumber & Drainer",
    "wof:placetype":"venue"
},
  "geometry": {"coordinates":[153.02767944300001,-26.3932056427],"type":"Point"}
}