{
  "type": "Feature",
  "properties": {
    "addr:full":"Unit 5/ 65 Stephens Ave Torrensville SA 5031",
    "addr:housenumber":"65",
    "addr:postcode":"5031",
    "addr:street":"Stephens Ave",
    "iso:country":"AU",
    "sg:address":"Unit 5/ 65 Stephens Ave",
    "sg:city":"Torrensville",
    "sg:classifiers":[
        {
            "category":"Shopping",
            "subcategory":"Stationery & Office Supplies",
            "type":"Retail Goods"
        }
    ],
    "sg:phone":"+61 1300 650 504",
    "sg:postcode":"5031",
    "sg:province":"SA",
    "sg:tags":[
        "screen",
        "printing"
    ],
    "wof:name":"Sericol Australia Pty Ltd",
    "wof:placetype":"venue"
},
  "geometry": {"coordinates":[138.555175781,-34.9161491394],"type":"Point"}
}