{
  "type": "Feature",
  "properties": {
    "addr:full":"137 Curtis St Oberon NSW 2787",
    "addr:housenumber":"137",
    "addr:postcode":"2787",
    "addr:street":"Curtis St",
    "iso:country":"AU",
    "sg:address":"137 Curtis St",
    "sg:city":"Oberon",
    "sg:classifiers":[
        {
            "category":"Education",
            "subcategory":"School",
            "type":"Public Place"
        }
    ],
    "sg:phone":"+61 2 6336 1226",
    "sg:postcode":"2787",
    "sg:province":"NSW",
    "wof:name":"St Joseph's Central - Primary Dept",
    "wof:placetype":"venue"
},
  "geometry": {"coordinates":[149.85394287099999,-33.7063026428],"type":"Point"}
}