{
  "type": "Feature",
  "properties": {
    "addr:full":"2 Indra Crs Karana Downs QLD 4306",
    "addr:housenumber":"2",
    "addr:postcode":"4306",
    "addr:street":"Indra Crs",
    "iso:country":"AU",
    "sg:address":"2 Indra Crs",
    "sg:city":"Karana Downs",
    "sg:classifiers":[
        {
            "category":"Health Services",
            "subcategory":"Health Practitioner",
            "type":"Services"
        }
    ],
    "sg:phone":"+61 7 3201 1959",
    "sg:postcode":"4306",
    "sg:province":"QLD",
    "sg:tags":[
        "bowen",
        "therapy"
    ],
    "wof:name":"Bowen Therapy at Karana Downs",
    "wof:placetype":"venue"
},
  "geometry": {"coordinates":[152.82296752900001,-27.5472202301],"type":"Point"}
}