{
  "type": "Feature",
  "properties": {
    "addr:full":"127 New Town Rd New Town TAS 7008",
    "addr:housenumber":"127",
    "addr:postcode":"7008",
    "addr:street":"New Town Rd",
    "iso:country":"AU",
    "sg:address":"127 New Town Rd",
    "sg:city":"New Town",
    "sg:classifiers":[
        {
            "category":"Health Services",
            "subcategory":"Doctor",
            "type":"Services"
        }
    ],
    "sg:phone":"+61 3 6228 7285",
    "sg:postcode":"7008",
    "sg:province":"TAS",
    "sg:tags":[
        "medical",
        "practitioner"
    ],
    "wof:name":"Braithwaite J",
    "wof:placetype":"venue"
},
  "geometry": {"coordinates":[147.306838989,-42.8598709106],"type":"Point"}
}