{
  "type": "Feature",
  "properties": {
    "addr:full":"2 Glen Crt Paradise SA 5075",
    "addr:housenumber":"2",
    "addr:postcode":"5075",
    "addr:street":"Glen Crt",
    "iso:country":"AU",
    "sg:address":"2 Glen Crt",
    "sg:city":"Paradise",
    "sg:classifiers":[
        {
            "category":"Building & Trades",
            "subcategory":"Cleaning & Sanitation",
            "type":"Services"
        }
    ],
    "sg:phone":"+61 8 8337 9102",
    "sg:postcode":"5075",
    "sg:province":"SA",
    "sg:tags":[
        "industrial",
        "commercial",
        "contractor"
    ],
    "wof:name":"Allkleen Property Services",
    "wof:placetype":"venue"
},
  "geometry": {"coordinates":[138.666381836,-34.8756904602],"type":"Point"}
}