{
  "type": "Feature",
  "properties": {
    "iso:country":"AU",
    "sg:address":"Old Railway Station Building Boddington St",
    "sg:city":"Mackay",
    "sg:classifiers":[
        {
            "category":"Personal",
            "subcategory":"Massage",
            "type":"Services"
        }
    ],
    "sg:phone":"+61 409 563 237",
    "sg:postcode":"4740",
    "sg:province":"QLD",
    "sg:tags":[
        "therapy"
    ],
    "wof:name":"Janelle De Silva",
    "wof:placetype":"venue"
},
  "geometry": {"coordinates":[149.181519,-21.148394],"type":"Point"}
}