{
  "type": "Feature",
  "properties": {
    "iso:country":"AU",
    "sg:address":"PO Box 1473",
    "sg:city":"Palmerston",
    "sg:phone":"+61 8 8947 5227",
    "sg:postcode":"0830",
    "sg:province":"NT",
    "wof:name":"Northern Water Solutions",
    "wof:placetype":"venue"
},
  "geometry": {"coordinates":[131.15321399999999,-12.28659],"type":"Point"}
}