{
  "type": "Feature",
  "properties": {
    "addr:full":"85 Burwood Rd Burwood NSW 2134",
    "addr:housenumber":"85",
    "addr:postcode":"2134",
    "addr:street":"Burwood Rd",
    "iso:country":"AU",
    "sg:address":"85 Burwood Rd",
    "sg:city":"Burwood",
    "sg:classifiers":[
        {
            "category":"Health Services",
            "subcategory":"Dentist",
            "type":"Services"
        }
    ],
    "sg:phone":"+61 2 9747 1515",
    "sg:postcode":"2134",
    "sg:province":"NSW",
    "wof:name":"Bechara E",
    "wof:placetype":"venue"
},
  "geometry": {"coordinates":[151.10386657699999,-33.8757247925],"type":"Point"}
}