{
  "type": "Feature",
  "properties": {
    "addr:full":"331A Berry St Rosebery NSW 2018",
    "addr:housenumber":"331a",
    "addr:postcode":"2018",
    "addr:street":"Berry St",
    "iso:country":"AU",
    "sg:address":"331A Berry St",
    "sg:city":"Rosebery",
    "sg:classifiers":[
        {
            "category":"Food & Beverages",
            "subcategory":"Fruits & Vegetables",
            "type":"Retail Goods"
        }
    ],
    "sg:phone":"+61 2 8338 0150",
    "sg:postcode":"2018",
    "sg:province":"NSW",
    "sg:tags":[
        "consultant",
        "catering"
    ],
    "wof:name":"Flavours Kosher Catering",
    "wof:placetype":"venue"
},
  "geometry": {"coordinates":[151.205245972,-33.9237365723],"type":"Point"}
}