{
  "type": "Feature",
  "properties": {
    "addr:full":"33 Boundary Rd Mordialloc VIC 3195",
    "addr:housenumber":"33",
    "addr:postcode":"3195",
    "addr:street":"Boundary Rd",
    "iso:country":"AU",
    "sg:address":"33 Boundary Rd",
    "sg:city":"Mordialloc",
    "sg:classifiers":[
        {
            "category":"Retail",
            "subcategory":"Auto Repair",
            "type":"Services"
        }
    ],
    "sg:phone":"+61 3 9580 9045",
    "sg:postcode":"3195",
    "sg:province":"VIC",
    "sg:tags":[
        "repairer",
        "motor",
        "engineer"
    ],
    "wof:name":"Repco Auto Repair",
    "wof:placetype":"venue"
},
  "geometry": {"coordinates":[145.10350036599999,-38.0081253052],"type":"Point"}
}