{
  "type": "Feature",
  "properties": {
    "addr:full":"Lot 560 Sparks Rd Henderson WA 6166",
    "addr:housenumber":"560",
    "addr:postcode":"6166",
    "addr:street":"Sparks Rd",
    "iso:country":"AU",
    "sg:address":"Lot 560 Sparks Rd",
    "sg:city":"Henderson",
    "sg:classifiers":[
        {
            "category":"Marine",
            "type":"Transportation"
        }
    ],
    "sg:phone":"+61 8 9437 3055",
    "sg:postcode":"6166",
    "sg:province":"WA",
    "sg:tags":[
        "industrial",
        "tanker",
        "cleaning"
    ],
    "wof:name":"AlphaBlast",
    "wof:placetype":"venue"
},
  "geometry": {"coordinates":[115.77652,-32.162781],"type":"Point"}
}