{
  "type": "Feature",
  "properties": {
    "iso:country":"AU",
    "sg:address":"1c Birch St",
    "sg:city":"Caulfield South",
    "sg:classifiers":[
        {
            "category":"Education",
            "subcategory":"Kindergarten",
            "type":"Public Place"
        }
    ],
    "sg:phone":"+61 3 9528 4131",
    "sg:postcode":"3162",
    "sg:province":"VIC",
    "sg:tags":[
        "pre-schools"
    ],
    "wof:name":"Caulfield South Pre-School",
    "wof:placetype":"venue"
},
  "geometry": {"coordinates":[145.02107238799999,-37.892665863],"type":"Point"}
}