{
  "type": "Feature",
  "properties": {
    "iso:country":"AU",
    "sg:address":"182 Cowper St",
    "sg:city":"Warrawong",
    "sg:classifiers":[
        {
            "category":"Organizations",
            "subcategory":"Non-profit Organization",
            "type":"Services"
        }
    ],
    "sg:phone":"+61 2 4274 9155",
    "sg:postcode":"2502",
    "sg:province":"NSW",
    "sg:tags":[
        "support",
        "disability",
        "organisation"
    ],
    "wof:name":"Workskills Illawarra",
    "wof:placetype":"venue"
},
  "geometry": {"coordinates":[150.88853499999999,-34.485161],"type":"Point"}
}