{
  "type": "Feature",
  "properties": {
    "iso:country":"AU",
    "sg:address":"60 Newark Ave",
    "sg:city":"Newborough",
    "sg:classifiers":[
        {
            "category":"Food & Beverages",
            "subcategory":"Groceries & Convenience Stores",
            "type":"Retail Goods"
        }
    ],
    "sg:phone":"+61 3 5126 3208",
    "sg:postcode":"3825",
    "sg:province":"VIC",
    "wof:name":"Newark Ave Milk Bar",
    "wof:placetype":"venue"
},
  "geometry": {"coordinates":[146.288696,-38.175789],"type":"Point"}
}