{
  "type": "Feature",
  "properties": {
    "iso:country":"AU",
    "sg:address":"Cnr Nicholson Rd & Lansdowne Entrance",
    "sg:city":"Canning Vale",
    "sg:classifiers":[
        {
            "category":"Farming",
            "subcategory":"Nursery",
            "type":"Manufacturing & Wholesale Goods"
        }
    ],
    "sg:phone":"+61 8 9455 1660",
    "sg:postcode":"6155",
    "sg:province":"WA",
    "wof:name":"Pioneer Gardens Nursery",
    "wof:placetype":"venue"
},
  "geometry": {"coordinates":[115.920441,-32.080193],"type":"Point"}
}