{
  "type": "Feature",
  "properties": {
    "addr:full":"96a Hobart Rd Kings Meadows TAS 7249",
    "addr:housenumber":"96a",
    "addr:postcode":"7249",
    "addr:street":"Hobart Rd",
    "iso:country":"AU",
    "sg:address":"96a Hobart Rd",
    "sg:city":"Kings Meadows",
    "sg:classifiers":[
        {
            "category":"Banks & Credit Unions",
            "subcategory":"Bank",
            "type":"Services"
        }
    ],
    "sg:phone":"+61 13 20 32",
    "sg:postcode":"7249",
    "sg:province":"TAS",
    "wof:name":"Westpac",
    "wof:placetype":"venue"
},
  "geometry": {"coordinates":[147.159423828,-41.4660606384],"type":"Point"}
}