{
  "type": "Feature",
  "properties": {
    "addr:full":"42 Bank St Port Fairy VIC 3284",
    "addr:housenumber":"42",
    "addr:postcode":"3284",
    "addr:street":"Bank St",
    "iso:country":"AU",
    "sg:address":"42 Bank St",
    "sg:city":"Port Fairy",
    "sg:classifiers":[
        {
            "category":"Travel",
            "subcategory":"Hotels & Motels",
            "type":"Entertainment"
        }
    ],
    "sg:phone":"+61 3 5568 2891",
    "sg:postcode":"3284",
    "sg:province":"VIC",
    "sg:tags":[
        "accommodation"
    ],
    "wof:name":"The Victoria Hotel",
    "wof:placetype":"venue"
},
  "geometry": {"coordinates":[142.23422241200001,-38.383014679],"type":"Point"}
}