{
  "type": "Feature",
  "properties": {
    "iso:country":"AU",
    "sg:address":"7 Main St",
    "sg:city":"Hahndorf",
    "sg:classifiers":[
        {
            "category":"Health Services",
            "subcategory":"Chiropractor",
            "type":"Services"
        }
    ],
    "sg:phone":"+61 8 8388 1511",
    "sg:postcode":"5245",
    "sg:province":"SA",
    "wof:name":"Hahndorf Chiropractic",
    "wof:placetype":"venue"
},
  "geometry": {"coordinates":[138.80992126500001,-35.029296875],"type":"Point"}
}