{
  "type": "Feature",
  "properties": {
    "addr:full":"Suite 1, Level 36 2 Bell St Pascoe Vale South VIC 3044",
    "addr:housenumber":"2",
    "addr:postcode":"3044",
    "addr:street":"Bell St",
    "iso:country":"AU",
    "sg:address":"Suite 1, Level 36 2 Bell St",
    "sg:city":"Pascoe Vale South",
    "sg:classifiers":[
        {
            "category":"Building & Trades",
            "subcategory":"Landscaping Services",
            "type":"Services"
        }
    ],
    "sg:phone":"+61 3 9355 7177",
    "sg:postcode":"3044",
    "sg:province":"VIC",
    "sg:tags":[
        "consultant"
    ],
    "wof:name":"Greater Melbourne Homes",
    "wof:placetype":"venue"
},
  "geometry": {"coordinates":[144.94049072300001,-37.7385520935],"type":"Point"}
}