{
  "type": "Feature",
  "properties": {
    "addr:full":"12 Montrose Ave Apollo Bay VIC 3233",
    "addr:housenumber":"12",
    "addr:postcode":"3233",
    "addr:street":"Montrose Ave",
    "iso:country":"AU",
    "sg:address":"12 Montrose Ave",
    "sg:city":"Apollo Bay",
    "sg:classifiers":[
        {
            "category":"Professional",
            "subcategory":"Art Services",
            "type":"Services"
        }
    ],
    "sg:phone":"+61 3 5237 6578",
    "sg:postcode":"3233",
    "sg:province":"VIC",
    "sg:tags":[
        "artist"
    ],
    "wof:name":"Shannon Pat",
    "wof:placetype":"venue"
},
  "geometry": {"coordinates":[143.66645813,-38.7556266785],"type":"Point"}
}