{
  "type": "Feature",
  "properties": {
    "iso:country":"AU",
    "sg:address":"Swift St",
    "sg:city":"Ballina",
    "sg:classifiers":[
        {
            "category":"Food & Beverages",
            "subcategory":"Groceries & Convenience Stores",
            "type":"Retail Goods"
        }
    ],
    "sg:phone":"+61 2 6686 2565",
    "sg:postcode":"2478",
    "sg:province":"NSW",
    "wof:name":"High School Tuck Shop",
    "wof:placetype":"venue"
},
  "geometry": {"coordinates":[153.55775451700001,-28.8651256561],"type":"Point"}
}