{
  "type": "Feature",
  "properties": {
    "addr:full":"Shop 142 Whiford City Shopng Cntr Whitfords Ave Hillarys WA 6025",
    "addr:housenumber":"142",
    "addr:postcode":"6025",
    "addr:street":"Whiford City Shopng Cntr Whitfords Ave",
    "iso:country":"AU",
    "sg:address":"Shop 142 Whiford City Shopng Cntr Whitfords Ave",
    "sg:city":"Hillarys",
    "sg:classifiers":[
        {
            "category":"Professional",
            "subcategory":"Art Services",
            "type":"Services"
        }
    ],
    "sg:phone":"+61 8 9401 0442",
    "sg:postcode":"6025",
    "sg:province":"WA",
    "sg:tags":[
        "picture",
        "frame",
        "framing"
    ],
    "wof:name":"Rabbit Photo",
    "wof:placetype":"venue"
},
  "geometry": {"coordinates":[115.755699158,-31.8075447083],"type":"Point"}
}