{
  "type": "Feature",
  "properties": {
    "addr:full":"53 Holloway Drv Bayswater VIC 3153",
    "addr:housenumber":"53",
    "addr:postcode":"3153",
    "addr:street":"Holloway Drv",
    "iso:country":"AU",
    "sg:address":"53 Holloway Drv",
    "sg:city":"Bayswater",
    "sg:classifiers":[
        {
            "category":"Shopping",
            "subcategory":"Mobile Phones",
            "type":"Retail Goods"
        }
    ],
    "sg:phone":"+61 3 9762 9599",
    "sg:postcode":"3153",
    "sg:province":"VIC",
    "sg:tags":[
        "wholesaler",
        "mfrs",
        "electrical",
        "switchboard"
    ],
    "wof:name":"ASM Sheetmetal Pty Ltd",
    "wof:placetype":"venue"
},
  "geometry": {"coordinates":[145.27961730999999,-37.8480644226],"type":"Point"}
}