{
  "type": "Feature",
  "properties": {
    "addr:full":"Unit 1 434 Cambridge St Floreat WA 6014",
    "addr:housenumber":"434",
    "addr:postcode":"6014",
    "addr:street":"Cambridge St",
    "iso:country":"AU",
    "sg:address":"Unit 1 434 Cambridge St",
    "sg:city":"Floreat",
    "sg:classifiers":[
        {
            "category":"Health Services",
            "subcategory":"Dentist",
            "type":"Services"
        }
    ],
    "sg:phone":"+61 8 9387 4192",
    "sg:postcode":"6014",
    "sg:province":"WA",
    "wof:name":"Birch J D",
    "wof:placetype":"venue"
},
  "geometry": {"coordinates":[115.80219268800001,-31.9406452179],"type":"Point"}
}