{
  "type": "Feature",
  "properties": {
    "iso:country":"AU",
    "sg:address":"5 Bradley St",
    "sg:city":"Goulburn",
    "sg:classifiers":[
        {
            "category":"Health Services",
            "subcategory":"Chiropractor",
            "type":"Services"
        }
    ],
    "sg:phone":"+61 2 4821 5796",
    "sg:postcode":"2580",
    "sg:province":"NSW",
    "wof:name":"Hampton Craig",
    "wof:placetype":"venue"
},
  "geometry": {"coordinates":[149.72505188,-34.7508087158],"type":"Point"}
}