{
  "type": "Feature",
  "properties": {
    "addr:full":"253 Rundle St Adelaide SA 5000",
    "addr:housenumber":"253",
    "addr:postcode":"5000",
    "addr:street":"Rundle St",
    "iso:country":"AU",
    "sg:address":"253 Rundle St",
    "sg:city":"Adelaide",
    "sg:classifiers":[
        {
            "category":"Personal",
            "subcategory":"Day Spa",
            "type":"Services"
        }
    ],
    "sg:phone":"+61 8 8359 3304",
    "sg:postcode":"5000",
    "sg:province":"SA",
    "wof:name":"Endota Spa",
    "wof:placetype":"venue"
},
  "geometry": {"coordinates":[138.608718872,-34.9226493835],"type":"Point"}
}