{
  "type": "Feature",
  "properties": {
    "addr:full":"260 Moreland Rd Brunswick VIC 3056",
    "addr:housenumber":"260",
    "addr:postcode":"3056",
    "addr:street":"Moreland Rd",
    "iso:country":"AU",
    "sg:address":"260 Moreland Rd",
    "sg:city":"Brunswick",
    "sg:classifiers":[
        {
            "category":"Health Services",
            "subcategory":"Doctor",
            "type":"Services"
        }
    ],
    "sg:phone":"+61 3 9383 2377",
    "sg:postcode":"3056",
    "sg:province":"VIC",
    "sg:tags":[
        "medical",
        "practitioner"
    ],
    "wof:name":"Haw Chris S",
    "wof:placetype":"venue"
},
  "geometry": {"coordinates":[144.95790100100001,-37.7548217773],"type":"Point"}
}