{
  "type": "Feature",
  "properties": {
    "addr:full":"7 David Muir St Slade Point QLD 4740",
    "addr:housenumber":"7",
    "addr:postcode":"4740",
    "addr:street":"David Muir St",
    "iso:country":"AU",
    "sg:address":"7 David Muir St",
    "sg:city":"Slade Point",
    "sg:classifiers":[
        {
            "category":"Banks & Credit Unions",
            "subcategory":"Bank",
            "type":"Services"
        }
    ],
    "sg:phone":"+61 7 4955 1922",
    "sg:postcode":"4740",
    "sg:province":"QLD",
    "sg:tags":[
        "concrete",
        "reinforcement"
    ],
    "wof:name":"Onesteel Reinforcing",
    "wof:placetype":"venue"
},
  "geometry": {"coordinates":[149.21253999999999,-21.090883],"type":"Point"}
}