{
  "type": "Feature",
  "properties": {
    "addr:full":"8025 Great Eastern Hwy Mundaring WA 6073",
    "addr:housenumber":"8025",
    "addr:postcode":"6073",
    "addr:street":"Great Eastern Hwy",
    "iso:country":"AU",
    "sg:address":"8025 Great Eastern Hwy",
    "sg:city":"Mundaring",
    "sg:classifiers":[
        {
            "category":"Education",
            "subcategory":"Special Training",
            "type":"Public Place"
        }
    ],
    "sg:phone":"+61 8 9295 2492",
    "sg:postcode":"6073",
    "sg:province":"WA",
    "sg:tags":[
        "development"
    ],
    "wof:name":"Australian Training Management Pty Ltd",
    "wof:placetype":"venue"
},
  "geometry": {"coordinates":[116.17430877699999,-31.9024944305],"type":"Point"}
}