{
  "type": "Feature",
  "properties": {
    "iso:country":"AU",
    "sg:address":"3 Chesney Crt",
    "sg:city":"Gladstone Park",
    "sg:classifiers":[
        {
            "category":"Utilities",
            "subcategory":"Mobile Phone",
            "type":"Services"
        }
    ],
    "sg:phone":"+61 3 9338 7817",
    "sg:postcode":"3043",
    "sg:province":"VIC",
    "sg:tags":[
        "aviation",
        "consultant"
    ],
    "wof:name":"Das Aviation Consultants",
    "wof:placetype":"venue"
},
  "geometry": {"coordinates":[144.89476013199999,-37.6957435608],"type":"Point"}
}