{
  "type": "Feature",
  "properties": {
    "addr:full":"23 Gawler St Portland VIC 3305",
    "addr:housenumber":"23",
    "addr:postcode":"3305",
    "addr:street":"Gawler St",
    "iso:country":"AU",
    "sg:address":"23 Gawler St",
    "sg:city":"Portland",
    "sg:classifiers":[
        {
            "category":"Building & Trades",
            "subcategory":"Construction",
            "type":"Services"
        }
    ],
    "sg:phone":"+61 3 5523 5017",
    "sg:postcode":"3305",
    "sg:province":"VIC",
    "sg:tags":[
        "fencing",
        "contractor"
    ],
    "wof:name":"Morton Philip",
    "wof:placetype":"venue"
},
  "geometry": {"coordinates":[141.60401916500001,-38.3506164551],"type":"Point"}
}