{
  "type": "Feature",
  "properties": {
    "addr:full":"Apperley St Banyo QLD 4014",
    "addr:postcode":"4014",
    "addr:street":"Apperley St",
    "iso:country":"AU",
    "sg:address":"Apperley St",
    "sg:city":"Banyo",
    "sg:classifiers":[
        {
            "category":"Arena",
            "subcategory":"Sports Club",
            "type":"Entertainment"
        }
    ],
    "sg:phone":"+61 418 745 801",
    "sg:postcode":"4014",
    "sg:province":"QLD",
    "sg:tags":[
        "defence",
        "supply",
        "self",
        "instruction",
        "martial art"
    ],
    "wof:name":"Black Crane Kung Fu Schools",
    "wof:placetype":"venue"
},
  "geometry": {"coordinates":[153.08070373499999,-27.3716697693],"type":"Point"}
}