{
  "type": "Feature",
  "properties": {
    "iso:country":"AU",
    "sg:address":"252 Main Rd",
    "sg:city":"Toukley",
    "sg:classifiers":[
        {
            "category":"Fast Food",
            "type":"Food & Drink"
        }
    ],
    "sg:phone":"+61 2 4396 1622",
    "sg:postcode":"2263",
    "sg:province":"NSW",
    "sg:tags":[
        "away",
        "take"
    ],
    "wof:name":"Jothi Indian Restaurant",
    "wof:placetype":"venue"
},
  "geometry": {"coordinates":[151.548325,-33.266087],"type":"Point"}
}