{
  "type": "Feature",
  "properties": {
    "addr:full":"92 Merriwa St Boggabilla NSW 2409",
    "addr:housenumber":"92",
    "addr:postcode":"2409",
    "addr:street":"Merriwa St",
    "iso:country":"AU",
    "sg:address":"92 Merriwa St",
    "sg:city":"Boggabilla",
    "sg:classifiers":[
        {
            "category":"Travel",
            "subcategory":"Hotels & Motels",
            "type":"Entertainment"
        }
    ],
    "sg:phone":"+61 7 4676 2217",
    "sg:postcode":"2409",
    "sg:province":"NSW",
    "sg:tags":[
        "accommodation"
    ],
    "wof:name":"Wobbly Boot Hotel",
    "wof:placetype":"venue"
},
  "geometry": {"coordinates":[150.35995483400001,-28.6024303436],"type":"Point"}
}