{
  "type": "Feature",
  "properties": {
    "addr:full":"10 Laurio Pl Mayfield West NSW 2304",
    "addr:housenumber":"10",
    "addr:postcode":"2304",
    "addr:street":"Laurio Pl",
    "iso:country":"AU",
    "sg:address":"10 Laurio Pl",
    "sg:city":"Mayfield West",
    "sg:classifiers":[
        {
            "category":"Education",
            "subcategory":"Special Training",
            "type":"Public Place"
        }
    ],
    "sg:phone":"+61 2 4960 9322",
    "sg:postcode":"2304",
    "sg:province":"NSW",
    "sg:tags":[
        "school",
        "flying"
    ],
    "wof:name":"Aerologistics Pty Ltd",
    "wof:placetype":"venue"
},
  "geometry": {"coordinates":[151.72819519000001,-32.880191803],"type":"Point"}
}