{
  "type": "Feature",
  "properties": {
    "addr:full":"Shop 4 Centrepiont Civic ACT 2601",
    "addr:housenumber":"shop 4",
    "addr:postcode":"2601",
    "addr:street":"Centrepiont Civic",
    "iso:country":"AU",
    "sg:address":"Shop 4 Centrepiont",
    "sg:city":"Civic",
    "sg:classifiers":[
        {
            "category":"Shopping",
            "subcategory":"Clothing, Apparel, & Fashions",
            "type":"Retail Goods"
        }
    ],
    "sg:phone":"+61 2 6248 9104",
    "sg:postcode":"2601",
    "sg:province":"ACT",
    "sg:tags":[
        "lady",
        "wear"
    ],
    "wof:name":"Zafari",
    "wof:placetype":"venue"
},
  "geometry": {"coordinates":[149.111816406,-35.2768592834],"type":"Point"}
}