{
  "type": "Feature",
  "properties": {
    "addr:full":"6 Attunga Crt Highton VIC 3216",
    "addr:housenumber":"6",
    "addr:postcode":"3216",
    "addr:street":"Attunga Crt",
    "iso:country":"AU",
    "sg:address":"6 Attunga Crt",
    "sg:city":"Highton",
    "sg:classifiers":[
        {
            "category":"Shopping",
            "subcategory":"Computers & Home Electronics",
            "type":"Retail Goods"
        }
    ],
    "sg:phone":"+61 400 990 346",
    "sg:postcode":"3216",
    "sg:province":"VIC",
    "sg:tags":[
        "hardware",
        "equipment"
    ],
    "wof:name":"B.A. Kent Business Solutions",
    "wof:placetype":"venue"
},
  "geometry": {"coordinates":[144.310302734,-38.1722297668],"type":"Point"}
}