{
  "type": "Feature",
  "properties": {
    "addr:full":"24 Carl Crt Hallam VIC 3803",
    "addr:housenumber":"24",
    "addr:postcode":"3803",
    "addr:street":"Carl Crt",
    "iso:country":"AU",
    "sg:address":"24 Carl Crt",
    "sg:city":"Hallam",
    "sg:classifiers":[
        {
            "category":"Shopping",
            "subcategory":"Stationery & Office Supplies",
            "type":"Retail Goods"
        }
    ],
    "sg:phone":"+61 3 9796 4454",
    "sg:postcode":"3803",
    "sg:province":"VIC",
    "sg:tags":[
        "packaging",
        "material"
    ],
    "wof:name":"Strapco Australia",
    "wof:placetype":"venue"
},
  "geometry": {"coordinates":[145.267974853,-38.0093574524],"type":"Point"}
}