{
  "type": "Feature",
  "properties": {
    "addr:full":"40 Roger St Brookvale NSW 2100",
    "addr:housenumber":"40",
    "addr:postcode":"2100",
    "addr:street":"Roger St",
    "iso:country":"AU",
    "sg:address":"40 Roger St",
    "sg:city":"Brookvale",
    "sg:classifiers":[
        {
            "category":"Autos & Motor Vehicles",
            "subcategory":"Auto Supplies",
            "type":"Retail Goods"
        }
    ],
    "sg:phone":"+61 2 9938 4777",
    "sg:postcode":"2100",
    "sg:province":"NSW",
    "sg:tags":[
        "part",
        "cycles",
        "accessory"
    ],
    "sg:website":"http://www.freedommotorcycles.com.au",
    "wof:name":"Freedom Motorcycles",
    "wof:placetype":"venue"
},
  "geometry": {"coordinates":[151.26965332,-33.7645568848],"type":"Point"}
}