{
  "type": "Feature",
  "properties": {
    "iso:country":"AU",
    "sg:address":"PO Box 117",
    "sg:city":"Camp Hill",
    "sg:classifiers":[
        {
            "category":"Utilities",
            "subcategory":"Electric",
            "type":"Services"
        }
    ],
    "sg:phone":"+61 412 833 107",
    "sg:postcode":"4152",
    "sg:province":"QLD",
    "sg:tags":[
        "electrical",
        "contractor"
    ],
    "wof:name":"A.N.W Electrical",
    "wof:placetype":"venue"
},
  "geometry": {"coordinates":[153.07696533199999,-27.50041008],"type":"Point"}
}