{
  "type": "Feature",
  "properties": {
    "iso:country":"AU",
    "sg:address":"Shop 4/ 33 Ellendon St",
    "sg:city":"Bungendore",
    "sg:classifiers":[
        {
            "category":"Personal",
            "type":"Services"
        }
    ],
    "sg:phone":"+61 2 6238 1288",
    "sg:postcode":"2621",
    "sg:province":"NSW",
    "sg:tags":[
        "dressmaker"
    ],
    "wof:name":"Sue Symons Dressmaking & Design",
    "wof:placetype":"venue"
},
  "geometry": {"coordinates":[149.440475464,-35.255153656],"type":"Point"}
}