{
  "type": "Feature",
  "properties": {
    "iso:country":"AU",
    "sg:address":"10/18 Banfield St",
    "sg:city":"Chermside",
    "sg:classifiers":[
        {
            "category":"Health Services",
            "subcategory":"Health Practitioner",
            "type":"Services"
        }
    ],
    "sg:phone":"+61 7 3861 4455",
    "sg:postcode":"4032",
    "sg:province":"QLD",
    "sg:tags":[
        "naturopath"
    ],
    "wof:name":"Catherine Irving",
    "wof:placetype":"venue"
},
  "geometry": {"coordinates":[153.03161600000001,-27.3818],"type":"Point"}
}