{
  "type": "Feature",
  "properties": {
    "addr:full":"130 Fussell St Ballarat VIC 3350",
    "addr:housenumber":"130",
    "addr:postcode":"3350",
    "addr:street":"Fussell St",
    "iso:country":"AU",
    "sg:address":"130 Fussell St",
    "sg:city":"Ballarat",
    "sg:classifiers":[
        {
            "category":"Wholesale",
            "subcategory":"Chemicals & Plastics",
            "type":"Manufacturing & Wholesale Goods"
        }
    ],
    "sg:phone":"+61 415 860 508",
    "sg:postcode":"3350",
    "sg:province":"VIC",
    "sg:tags":[
        "repair"
    ],
    "wof:name":"Pro Plastic Repairs",
    "wof:placetype":"venue"
},
  "geometry": {"coordinates":[143.89418000000001,-37.565434],"type":"Point"}
}