{
  "type": "Feature",
  "properties": {
    "addr:full":"Unit 5/ 68 Lambeck Drv Tullamarine VIC 3043",
    "addr:housenumber":"68",
    "addr:postcode":"3043",
    "addr:street":"Lambeck Drv",
    "iso:country":"AU",
    "sg:address":"Unit 5/ 68 Lambeck Drv",
    "sg:city":"Tullamarine",
    "sg:classifiers":[
        {
            "category":"Wholesale",
            "subcategory":"Office Equipment",
            "type":"Manufacturing & Wholesale Goods"
        }
    ],
    "sg:phone":"+61 3 9338 8566",
    "sg:postcode":"3043",
    "sg:province":"VIC",
    "sg:tags":[
        "packaging",
        "consultant"
    ],
    "wof:name":"Lakewood Corporation Pty Ltd The",
    "wof:placetype":"venue"
},
  "geometry": {"coordinates":[144.853591919,-37.7091445923],"type":"Point"}
}