{
  "type": "Feature",
  "properties": {
    "addr:full":"PO Box 120 Denham WA 6537",
    "addr:postcode":"6537",
    "iso:country":"AU",
    "sg:address":"PO Box 120",
    "sg:city":"Denham",
    "sg:classifiers":[
        {
            "category":"Recreation",
            "subcategory":"Boat Charter",
            "type":"Entertainment"
        }
    ],
    "sg:phone":"+61 8 9948 1113",
    "sg:postcode":"6537",
    "sg:province":"WA",
    "wof:name":"Shark Bay Charter Service",
    "wof:placetype":"venue"
},
  "geometry": {"coordinates":[113.539360046,-25.9285697937],"type":"Point"}
}