{
  "type": "Feature",
  "properties": {
    "addr:full":"Aero Building, Suite 3, Ground Level 247 Coward St Mascot NSW 2020",
    "addr:housenumber":"247",
    "addr:postcode":"2020",
    "addr:street":"Coward St",
    "iso:country":"AU",
    "sg:address":"Aero Building, Suite 3, Ground Level 247 Coward St",
    "sg:city":"Mascot",
    "sg:classifiers":[
        {
            "category":"Home & Garden",
            "subcategory":"Furniture",
            "type":"Retail Goods"
        }
    ],
    "sg:phone":"+61 2 9669 4699",
    "sg:postcode":"2020",
    "sg:province":"NSW",
    "sg:tags":[
        "business"
    ],
    "sg:website":"http://www.moduflex.com.au",
    "wof:name":"Moduflex Office Solutions",
    "wof:placetype":"venue"
},
  "geometry": {"coordinates":[151.184646606,-33.923992157],"type":"Point"}
}