{
  "type": "Feature",
  "properties": {
    "addr:full":"Unit 1/ 348 South Pine Rd Brendale QLD 4500",
    "addr:housenumber":"/ 348",
    "addr:postcode":"4500",
    "addr:street":"South Pine Rd",
    "iso:country":"AU",
    "sg:address":"Unit 1/ 348 South Pine Rd",
    "sg:city":"Brendale",
    "sg:classifiers":[
        {
            "category":"Autos & Motor Vehicles",
            "subcategory":"Auto Supplies",
            "type":"Retail Goods"
        }
    ],
    "sg:phone":"+61 7 3881 1011",
    "sg:postcode":"4500",
    "sg:province":"QLD",
    "sg:tags":[
        "garage",
        "equipment"
    ],
    "wof:name":"Eagle S.M.F. Distributors Pty Ltd",
    "wof:placetype":"venue"
},
  "geometry": {"coordinates":[152.98733520499999,-27.32447052],"type":"Point"}
}