{
  "type": "Feature",
  "properties": {
    "iso:country":"AU",
    "sg:address":"44 Park Beach Rd",
    "sg:city":"Coffs Harbour",
    "sg:classifiers":[
        {
            "category":"Real Estate",
            "subcategory":"Architect",
            "type":"Services"
        }
    ],
    "sg:phone":"+61 2 6651 4905",
    "sg:postcode":"2450",
    "sg:province":"NSW",
    "sg:tags":[
        "building",
        "designer"
    ],
    "wof:name":"DRA Architects Pty Ltd",
    "wof:placetype":"venue"
},
  "geometry": {"coordinates":[153.13000500000001,-30.285116],"type":"Point"}
}