{
  "type": "Feature",
  "properties": {
    "iso:country":"AU",
    "sg:address":"107 John St",
    "sg:city":"Cabramatta",
    "sg:classifiers":[
        {
            "category":"Health Services",
            "subcategory":"Doctor",
            "type":"Services"
        }
    ],
    "sg:phone":"+61 2 9726 2931",
    "sg:postcode":"2166",
    "sg:province":"NSW",
    "sg:tags":[
        "medical",
        "practitioner"
    ],
    "wof:name":"La Thien P",
    "wof:placetype":"venue"
},
  "geometry": {"coordinates":[150.934494019,-33.8947296143],"type":"Point"}
}