{
  "type": "Feature",
  "properties": {
    "addr:full":"15 Derwent Park Rd Derwent Park TAS 7009",
    "addr:housenumber":"15",
    "addr:postcode":"7009",
    "addr:street":"Derwent Park Rd",
    "iso:country":"AU",
    "sg:address":"15 Derwent Park Rd",
    "sg:city":"Derwent Park",
    "sg:classifiers":[
        {
            "category":"Shopping",
            "subcategory":"Bicycles & Sporting Goods",
            "type":"Retail Goods"
        }
    ],
    "sg:phone":"+61 1800 656 667",
    "sg:postcode":"7009",
    "sg:province":"TAS",
    "sg:tags":[
        "chemical",
        "equipment",
        "pool",
        "swimming"
    ],
    "wof:name":"Tankworld Summertime Pools",
    "wof:placetype":"venue"
},
  "geometry": {"coordinates":[147.292526245,-42.8393211365],"type":"Point"}
}