{
  "type": "Feature",
  "properties": {
    "iso:country":"AU",
    "sg:address":"107 Targo St",
    "sg:city":"Bundaberg South",
    "sg:classifiers":[
        {
            "category":"Shopping",
            "subcategory":"Gifts & Souvenirs",
            "type":"Retail Goods"
        }
    ],
    "sg:phone":"+61 7 4152 8535",
    "sg:postcode":"4670",
    "sg:province":"QLD",
    "sg:tags":[
        "print",
        "poster",
        "pictures"
    ],
    "wof:name":"Classic Framing",
    "wof:placetype":"venue"
},
  "geometry": {"coordinates":[152.36012268100001,-24.8769626617],"type":"Point"}
}