{
  "type": "Feature",
  "properties": {
    "addr:full":"197 Gover St North Adelaide SA 5006",
    "addr:housenumber":"197",
    "addr:postcode":"5006",
    "addr:street":"Gover St",
    "iso:country":"AU",
    "sg:address":"197 Gover St",
    "sg:city":"North Adelaide",
    "sg:classifiers":[
        {
            "category":"Personal",
            "subcategory":"Beauty Salon",
            "type":"Services"
        }
    ],
    "sg:phone":"+61 419 038 884",
    "sg:postcode":"5006",
    "sg:province":"SA",
    "sg:tags":[
        "hairdresser"
    ],
    "wof:name":"Darlene Lingo",
    "wof:placetype":"venue"
},
  "geometry": {"coordinates":[138.59260559099999,-34.9054069519],"type":"Point"}
}