{
  "type": "Feature",
  "properties": {
    "iso:country":"AU",
    "sg:address":"20 Main St",
    "sg:city":"Croydon",
    "sg:classifiers":[
        {
            "category":"Shopping",
            "subcategory":"Crafts & Fabrics",
            "type":"Retail Goods"
        }
    ],
    "sg:phone":"+61 3 9725 0065",
    "sg:postcode":"3136",
    "sg:province":"VIC",
    "sg:tags":[
        "supply"
    ],
    "wof:name":"Missy Moo Cottage Crafts",
    "wof:placetype":"venue"
},
  "geometry": {"coordinates":[145.28268432600001,-37.7945098877],"type":"Point"}
}