{
  "type": "Feature",
  "properties": {
    "iso:country":"AU",
    "sg:address":"Unit 3, 14 Bon Mace Cl",
    "sg:city":"Berkeley Vale",
    "sg:classifiers":[
        {
            "category":"Retail",
            "subcategory":"Auto Repair",
            "type":"Services"
        }
    ],
    "sg:phone":"+61 2 4388 2550",
    "sg:postcode":"2261",
    "sg:province":"NSW",
    "sg:tags":[
        "clutch",
        "brake"
    ],
    "wof:name":"Boydys Mechanical Pty Ltd",
    "wof:placetype":"venue"
},
  "geometry": {"coordinates":[151.438583,-33.344639],"type":"Point"}
}