{
  "type": "Feature",
  "properties": {
    "addr:full":"Unit 10/ 9 Ladbroke St Milperra NSW 2214",
    "addr:housenumber":"/ 9",
    "addr:postcode":"2214",
    "addr:street":"Ladbroke St",
    "iso:country":"AU",
    "sg:address":"Unit 10/ 9 Ladbroke St",
    "sg:city":"Milperra",
    "sg:classifiers":[
        {
            "category":"Home & Garden",
            "subcategory":"Carpets & Floor Coverings",
            "type":"Retail Goods"
        }
    ],
    "sg:phone":"+61 2 9773 4963",
    "sg:postcode":"2214",
    "sg:province":"NSW",
    "sg:tags":[
        "material",
        "waterproofing"
    ],
    "wof:name":"Penetron Australia",
    "wof:placetype":"venue"
},
  "geometry": {"coordinates":[150.99505600000001,-33.932735],"type":"Point"}
}