{
  "type": "Feature",
  "properties": {
    "addr:full":"Shp1/ 126 Adelaide St Brisbane QLD 4000",
    "addr:housenumber":"126",
    "addr:postcode":"4000",
    "addr:street":"Adelaide St",
    "iso:country":"AU",
    "sg:address":"Shp1/ 126 Adelaide St",
    "sg:city":"Brisbane",
    "sg:classifiers":[
        {
            "category":"Shopping",
            "subcategory":"Clothing, Apparel, & Fashions",
            "type":"Retail Goods"
        }
    ],
    "sg:phone":"+61 7 3221 2332",
    "sg:postcode":"4000",
    "sg:province":"QLD",
    "sg:tags":[
        "lady",
        "wear"
    ],
    "wof:name":"Latin Clothing Company",
    "wof:placetype":"venue"
},
  "geometry": {"coordinates":[153.02516174300001,-27.4681587219],"type":"Point"}
}