{
  "type": "Feature",
  "properties": {
    "addr:full":"Suite 4/ 200 Rokeby Rd Subiaco WA 6008",
    "addr:housenumber":"/ 200",
    "addr:postcode":"6008",
    "addr:street":"Rokeby Rd",
    "iso:country":"AU",
    "sg:address":"Suite 4/ 200 Rokeby Rd",
    "sg:city":"Subiaco",
    "sg:classifiers":[
        {
            "category":"Health Services",
            "subcategory":"Doctor",
            "type":"Services"
        }
    ],
    "sg:phone":"+61 8 9388 3305",
    "sg:postcode":"6008",
    "sg:province":"WA",
    "sg:tags":[
        "medical",
        "practitioner"
    ],
    "wof:name":"Smith Peter A Dr",
    "wof:placetype":"venue"
},
  "geometry": {"coordinates":[115.82409668,-31.950876236],"type":"Point"}
}