{
  "type": "Feature",
  "properties": {
    "addr:full":"34 Mahara St Bardon QLD 4065",
    "addr:housenumber":"34",
    "addr:postcode":"4065",
    "addr:street":"Mahara St",
    "iso:country":"AU",
    "sg:address":"34 Mahara St",
    "sg:city":"Bardon",
    "sg:classifiers":[
        {
            "category":"Home & Garden",
            "subcategory":"Building Materials",
            "type":"Retail Goods"
        }
    ],
    "sg:phone":"+61 419 770 205",
    "sg:postcode":"4065",
    "sg:province":"QLD",
    "sg:tags":[
        "lawn",
        "cutting",
        "maintenance"
    ],
    "wof:name":"Elementree Landscapes",
    "wof:placetype":"venue"
},
  "geometry": {"coordinates":[152.98524475100001,-27.4639186859],"type":"Point"}
}