{
  "type": "Feature",
  "properties": {
    "iso:country":"AU",
    "sg:address":"Shop 45/ 61- 89 Buckingham St",
    "sg:city":"Surry Hills",
    "sg:classifiers":[
        {
            "category":"Wholesale",
            "subcategory":"Chemicals & Plastics",
            "type":"Manufacturing & Wholesale Goods"
        }
    ],
    "sg:phone":"+61 2 9310 2000",
    "sg:postcode":"2010",
    "sg:province":"NSW",
    "sg:tags":[
        "bag"
    ],
    "wof:name":"Carrybags Co",
    "wof:placetype":"venue"
},
  "geometry": {"coordinates":[151.206863403,-33.8894042969],"type":"Point"}
}