{
  "type": "Feature",
  "properties": {
    "addr:full":"Level 2 492 St Kilda Rd Melbourne VIC 3004",
    "addr:housenumber":"492",
    "addr:postcode":"3004",
    "addr:street":"St Kilda Rd",
    "iso:country":"AU",
    "sg:address":"Level 2 492 St Kilda Rd",
    "sg:city":"Melbourne",
    "sg:classifiers":[
        {
            "category":"Banks & Credit Unions",
            "subcategory":"Investment Brokerage",
            "type":"Services"
        }
    ],
    "sg:phone":"+61 3 9866 5811",
    "sg:postcode":"3004",
    "sg:province":"VIC",
    "sg:tags":[
        "finance",
        "broker"
    ],
    "wof:name":"Payton Finance Pty Ltd",
    "wof:placetype":"venue"
},
  "geometry": {"coordinates":[144.977981567,-37.8439331055],"type":"Point"}
}