{
  "type": "Feature",
  "properties": {
    "addr:full":"PO Box 378 Mooroolbark VIC 3138",
    "addr:postcode":"3138",
    "iso:country":"AU",
    "sg:address":"PO Box 378",
    "sg:city":"Mooroolbark",
    "sg:classifiers":[
        {
            "category":"Social Services",
            "subcategory":"Adult Care",
            "type":"Services"
        }
    ],
    "sg:phone":"+61 3 9727 2744",
    "sg:postcode":"3138",
    "sg:province":"VIC",
    "sg:tags":[
        "aged"
    ],
    "wof:name":"Dementia Care Australia Pty Ltd",
    "wof:placetype":"venue"
},
  "geometry": {"coordinates":[145.3175354,-37.7861785889],"type":"Point"}
}