{
  "type": "Feature",
  "properties": {
    "iso:country":"AU",
    "sg:address":"54a Stradbroke Drv",
    "sg:city":"St Albans",
    "sg:classifiers":[
        {
            "category":"Food & Beverages",
            "subcategory":"Specialty",
            "type":"Retail Goods"
        }
    ],
    "sg:phone":"+61 3 9310 8844",
    "sg:postcode":"3021",
    "sg:province":"VIC",
    "sg:tags":[
        "product",
        "health"
    ],
    "wof:name":"Diet Magic Naturally",
    "wof:placetype":"venue"
},
  "geometry": {"coordinates":[144.809341,-37.747593],"type":"Point"}
}