{
  "type": "Feature",
  "properties": {
    "iso:country":"AU",
    "sg:address":"15 Collins St",
    "sg:city":"Melbourne",
    "sg:classifiers":[
        {
            "category":"Personal",
            "subcategory":"Beauty Salon",
            "type":"Services"
        }
    ],
    "sg:phone":"+61 3 9662 4222",
    "sg:postcode":"3000",
    "sg:province":"VIC",
    "sg:tags":[
        "hair",
        "treatment",
        "replacement"
    ],
    "wof:name":"John Of Melbourne",
    "wof:placetype":"venue"
},
  "geometry": {"coordinates":[144.97349548299999,-37.8135795593],"type":"Point"}
}