{
  "type": "Feature",
  "properties": {
    "iso:country":"AU",
    "sg:address":"PO Box 503",
    "sg:city":"Mildura",
    "sg:classifiers":[
        {
            "category":"Home & Garden",
            "subcategory":"Carpets & Floor Coverings",
            "type":"Retail Goods"
        }
    ],
    "sg:phone":"+61 419 529 961",
    "sg:postcode":"3502",
    "sg:province":"VIC",
    "sg:tags":[
        "tile",
        "wall",
        "layer"
    ],
    "wof:name":"Mildura Tiling Service",
    "wof:placetype":"venue"
},
  "geometry": {"coordinates":[142.165557861,-34.184551239],"type":"Point"}
}