{
  "type": "Feature",
  "properties": {
    "addr:full":"217 Musgrave St Rockhampton QLD 4700",
    "addr:housenumber":"217",
    "addr:postcode":"4700",
    "addr:street":"Musgrave St",
    "iso:country":"AU",
    "sg:address":"217 Musgrave St",
    "sg:city":"Rockhampton",
    "sg:classifiers":[
        {
            "category":"Landmark",
            "subcategory":"Fountain",
            "type":"Public Place"
        }
    ],
    "sg:phone":"+61 7 4922 6844",
    "sg:postcode":"4700",
    "sg:province":"QLD",
    "sg:tags":[
        "wholesaler",
        "spring",
        "mfrs"
    ],
    "wof:name":"Pedders Suspension",
    "wof:placetype":"venue"
},
  "geometry": {"coordinates":[150.522903442,-23.3600559235],"type":"Point"}
}