{
  "type": "Feature",
  "properties": {
    "addr:full":"29 Rudloc Rd Morley WA 6062",
    "addr:housenumber":"29",
    "addr:postcode":"6062",
    "addr:street":"Rudloc Rd",
    "iso:country":"AU",
    "sg:address":"29 Rudloc Rd",
    "sg:city":"Morley",
    "sg:classifiers":[
        {
            "category":"Professional",
            "subcategory":"Printing & Photocopies",
            "type":"Services"
        }
    ],
    "sg:phone":"+61 8 9276 5477",
    "sg:postcode":"6062",
    "sg:province":"WA",
    "sg:tags":[
        "trophy"
    ],
    "wof:name":"Trophy Warehouse",
    "wof:placetype":"venue"
},
  "geometry": {"coordinates":[115.897743225,-31.9007415771],"type":"Point"}
}