{
  "type": "Feature",
  "properties": {
    "addr:full":"Shop 17 The Park Centre 789 Albany Hwy East Victoria Park WA 6101",
    "addr:housenumber":"shop 17;789",
    "addr:postcode":"6101",
    "addr:street":"The Park;Albany Hwy",
    "iso:country":"AU",
    "sg:address":"Shop 17 The Park Centre 789 Albany Hwy",
    "sg:city":"East Victoria Park",
    "sg:classifiers":[
        {
            "category":"Fast Food",
            "type":"Food & Drink"
        }
    ],
    "sg:phone":"+61 8 9362 2488",
    "sg:postcode":"6101",
    "sg:province":"WA",
    "sg:tags":[
        "away",
        "take"
    ],
    "wof:name":"Wokinabox",
    "wof:placetype":"venue"
},
  "geometry": {"coordinates":[115.90199279799999,-31.9831447601],"type":"Point"}
}