{
  "type": "Feature",
  "properties": {
    "addr:full":"Unit C34 240 Wyndham St Alexandria NSW 2015",
    "addr:housenumber":"240",
    "addr:postcode":"2015",
    "addr:street":"Wyndham St",
    "iso:country":"AU",
    "sg:address":"Unit C34 240 Wyndham St",
    "sg:city":"Alexandria",
    "sg:classifiers":[
        {
            "category":"Sports & Exercise",
            "subcategory":"Gym",
            "type":"Entertainment"
        }
    ],
    "sg:phone":"+61 414 423 060",
    "sg:postcode":"2015",
    "sg:province":"NSW",
    "sg:tags":[
        "personal",
        "trainer",
        "fitness"
    ],
    "wof:name":"Eye On Fitness",
    "wof:placetype":"venue"
},
  "geometry": {"coordinates":[151.20039367699999,-33.9019050598],"type":"Point"}
}