{
  "type": "Feature",
  "properties": {
    "iso:country":"AU",
    "sg:address":"Shop 7 78 The Mall",
    "sg:city":"Seymour",
    "sg:classifiers":[
        {
            "category":"Shopping",
            "subcategory":"Clothing, Apparel, & Fashions",
            "type":"Retail Goods"
        }
    ],
    "sg:phone":"+61 3 5792 3105",
    "sg:postcode":"3660",
    "sg:province":"VIC",
    "sg:tags":[
        "jean"
    ],
    "wof:name":"Cactus Jeans",
    "wof:placetype":"venue"
},
  "geometry": {"coordinates":[145.132522583,-37.0272445679],"type":"Point"}
}