{
  "type": "Feature",
  "properties": {
    "iso:country":"AU",
    "sg:address":"101 Tamar St",
    "sg:city":"Ballina",
    "sg:classifiers":[
        {
            "category":"Health Services",
            "subcategory":"Dentist",
            "type":"Services"
        }
    ],
    "sg:phone":"+61 2 6686 9922",
    "sg:postcode":"2478",
    "sg:province":"NSW",
    "sg:tags":[
        "dental",
        "prosthetist"
    ],
    "wof:name":"North Coast Denture Services",
    "wof:placetype":"venue"
},
  "geometry": {"coordinates":[153.558227539,-28.867975235],"type":"Point"}
}