{
  "type": "Feature",
  "properties": {
    "iso:country":"AU",
    "sg:address":"277 Mitchells La",
    "sg:city":"Sunbury",
    "sg:classifiers":[
        {
            "category":"Transit Center",
            "subcategory":"Freight",
            "type":"Transportation"
        }
    ],
    "sg:phone":"+61 3 9744 7056",
    "sg:postcode":"3429",
    "sg:province":"VIC",
    "sg:tags":[
        "forklift",
        "truck"
    ],
    "wof:name":"Mita Forklift Services",
    "wof:placetype":"venue"
},
  "geometry": {"coordinates":[144.691970825,-37.5830459595],"type":"Point"}
}