{
  "type": "Feature",
  "properties": {
    "addr:full":"21/ 37 Mortimer Rd Archerfield QLD 4108",
    "addr:housenumber":"21 / 37",
    "addr:postcode":"4108",
    "addr:street":"Mortimer Rd",
    "iso:country":"AU",
    "sg:address":"21/ 37 Mortimer Rd",
    "sg:city":"Archerfield",
    "sg:classifiers":[
        {
            "category":"Banks & Credit Unions",
            "subcategory":"Atm",
            "type":"Services"
        }
    ],
    "sg:phone":"+61 1300 856 415",
    "sg:postcode":"4108",
    "sg:province":"QLD",
    "sg:tags":[
        "box",
        "case",
        "metal"
    ],
    "wof:name":"Just Imports",
    "wof:placetype":"venue"
},
  "geometry": {"coordinates":[153.010040283,-27.5775852203],"type":"Point"}
}