{
  "type": "Feature",
  "properties": {
    "iso:country":"AU",
    "sg:address":"26 Pembroke St",
    "sg:city":"Surrey Hills",
    "sg:classifiers":[
        {
            "category":"Professional",
            "subcategory":"Art Services",
            "type":"Services"
        }
    ],
    "sg:phone":"+61 419 994 969",
    "sg:postcode":"3127",
    "sg:province":"VIC",
    "sg:tags":[
        "decorator",
        "painter"
    ],
    "wof:name":"Triple &#039;R&#039; Painting Services",
    "wof:placetype":"venue"
},
  "geometry": {"coordinates":[145.10763549800001,-37.8297653198],"type":"Point"}
}