{
  "type": "Feature",
  "properties": {
    "addr:full":"16- 18 Wood St Beaconsfield VIC 3807",
    "addr:housenumber":"18",
    "addr:postcode":"3807",
    "addr:street":"Wood St",
    "iso:country":"AU",
    "sg:address":"16- 18 Wood St",
    "sg:city":"Beaconsfield",
    "sg:classifiers":[
        {
            "category":"Health Services",
            "subcategory":"Chiropractor",
            "type":"Services"
        }
    ],
    "sg:phone":"+61 3 9796 1110",
    "sg:postcode":"3807",
    "sg:province":"VIC",
    "wof:name":"Carter Craig Dr",
    "wof:placetype":"venue"
},
  "geometry": {"coordinates":[145.367752075,-38.0463447571],"type":"Point"}
}