{
  "type": "Feature",
  "properties": {
    "addr:full":"3A Bassett Pl Menai NSW 2234",
    "addr:housenumber":"3a",
    "addr:postcode":"2234",
    "addr:street":"Bassett Pl",
    "iso:country":"AU",
    "sg:address":"3A Bassett Pl",
    "sg:city":"Menai",
    "sg:classifiers":[
        {
            "category":"Home & Garden",
            "subcategory":"Building Materials",
            "type":"Retail Goods"
        }
    ],
    "sg:phone":"+61 418 458 783",
    "sg:postcode":"2234",
    "sg:province":"NSW",
    "sg:tags":[
        "lawn",
        "cutting",
        "maintenance"
    ],
    "wof:name":"Danbre Services",
    "wof:placetype":"venue"
},
  "geometry": {"coordinates":[151.01150512699999,-34.0193557739],"type":"Point"}
}