{
  "type": "Feature",
  "properties": {
    "addr:full":"21 Torrens St Braddon ACT 2612",
    "addr:housenumber":"21",
    "addr:postcode":"2612",
    "addr:street":"Torrens St",
    "iso:country":"AU",
    "sg:address":"21 Torrens St",
    "sg:city":"Braddon",
    "sg:classifiers":[
        {
            "category":"Insurance",
            "subcategory":"Hazard Insurance",
            "type":"Services"
        }
    ],
    "sg:phone":"+61 2 6240 4670",
    "sg:postcode":"2612",
    "sg:province":"ACT",
    "sg:tags":[
        "motor",
        "vehicle"
    ],
    "wof:name":"CGU",
    "wof:placetype":"venue"
},
  "geometry": {"coordinates":[149.133865356,-35.2737693787],"type":"Point"}
}