{
  "type": "Feature",
  "properties": {
    "addr:full":"42 Parkland Rd Carlingford NSW 2118",
    "addr:housenumber":"42",
    "addr:postcode":"2118",
    "addr:street":"Parkland Rd",
    "iso:country":"AU",
    "sg:address":"42 Parkland Rd",
    "sg:city":"Carlingford",
    "sg:classifiers":[
        {
            "category":"Personal",
            "subcategory":"Massage",
            "type":"Services"
        }
    ],
    "sg:phone":"+61 2 9872 2373",
    "sg:postcode":"2118",
    "sg:province":"NSW",
    "sg:tags":[
        "therapy"
    ],
    "wof:name":"Carlingford Therapeutic Massage",
    "wof:placetype":"venue"
},
  "geometry": {"coordinates":[151.04168701200001,-33.7733306885],"type":"Point"}
}