{
  "type": "Feature",
  "properties": {
    "addr:full":"1/ 73 remington Drv Dandenong South VIC 3175",
    "addr:housenumber":"/ 73",
    "addr:postcode":"3175",
    "addr:street":"Remington Drv",
    "iso:country":"AU",
    "sg:address":"1/ 73 remington Drv",
    "sg:city":"Dandenong South",
    "sg:classifiers":[
        {
            "category":"Retail",
            "subcategory":"Auto Repair",
            "type":"Services"
        }
    ],
    "sg:phone":"+61 3 9799 3250",
    "sg:postcode":"3175",
    "sg:province":"VIC",
    "sg:tags":[
        "wheel",
        "balancing",
        "alignment"
    ],
    "wof:name":"Hardy Spicer Driveshaft Services",
    "wof:placetype":"venue"
},
  "geometry": {"coordinates":[145.23042297399999,-38.0295715332],"type":"Point"}
}