{
  "type": "Feature",
  "properties": {
    "iso:country":"AU",
    "sg:address":"U1/ 96 Ocean St",
    "sg:city":"Narrabeen",
    "sg:classifiers":[
        {
            "category":"Professional",
            "subcategory":"Art Services",
            "type":"Services"
        }
    ],
    "sg:phone":"+61 2 9913 7876",
    "sg:postcode":"2101",
    "sg:province":"NSW",
    "sg:tags":[
        "graphic",
        "designer"
    ],
    "wof:name":"Mark Reynolds Designs",
    "wof:placetype":"venue"
},
  "geometry": {"coordinates":[151.299606,-33.714596],"type":"Point"}
}