{
  "type": "Feature",
  "properties": {
    "iso:country":"AU",
    "sg:address":"Shp 1/ 67 Skylark St",
    "sg:city":"Inala",
    "sg:classifiers":[
        {
            "category":"Personal",
            "subcategory":"Beauty Salon",
            "type":"Services"
        }
    ],
    "sg:phone":"+61 7 3278 9388",
    "sg:postcode":"4077",
    "sg:province":"QLD",
    "sg:tags":[
        "hairdresser"
    ],
    "wof:name":"Ngoc Van Hair Design",
    "wof:placetype":"venue"
},
  "geometry": {"coordinates":[152.97291564899999,-27.5969982147],"type":"Point"}
}