{
  "type": "Feature",
  "properties": {
    "addr:full":"22 Jennings St Colac VIC 3250",
    "addr:housenumber":"22",
    "addr:postcode":"3250",
    "addr:street":"Jennings St",
    "iso:country":"AU",
    "sg:address":"22 Jennings St",
    "sg:city":"Colac",
    "sg:classifiers":[
        {
            "category":"Professional",
            "subcategory":"Art Services",
            "type":"Services"
        }
    ],
    "sg:phone":"+61 3 5231 2758",
    "sg:postcode":"3250",
    "sg:province":"VIC",
    "sg:tags":[
        "decorator",
        "painter"
    ],
    "wof:name":"Tevelein G N & E A",
    "wof:placetype":"venue"
},
  "geometry": {"coordinates":[143.57827800000001,-38.340473],"type":"Point"}
}