{
  "type": "Feature",
  "properties": {
    "addr:full":"18 Westbank Ave Emu Plains NSW 2750",
    "addr:housenumber":"18",
    "addr:postcode":"2750",
    "addr:street":"Westbank Ave",
    "iso:country":"AU",
    "sg:address":"18 Westbank Ave",
    "sg:city":"Emu Plains",
    "sg:classifiers":[
        {
            "category":"Health Services",
            "subcategory":"Health Practitioner",
            "type":"Services"
        }
    ],
    "sg:phone":"+61 2 4735 5178",
    "sg:postcode":"2750",
    "sg:province":"NSW",
    "sg:tags":[
        "osteopath"
    ],
    "wof:name":"Hubbard Paul C",
    "wof:placetype":"venue"
},
  "geometry": {"coordinates":[150.67416381800001,-33.7501907349],"type":"Point"}
}