{
  "type": "Feature",
  "properties": {
    "addr:full":"101 Eumundi Rd Noosaville QLD 4566",
    "addr:housenumber":"101",
    "addr:postcode":"4566",
    "addr:street":"Eumundi Rd",
    "iso:country":"AU",
    "sg:address":"101 Eumundi Rd",
    "sg:city":"Noosaville",
    "sg:classifiers":[
        {
            "category":"Train Station",
            "subcategory":"Light Rail",
            "type":"Transportation"
        }
    ],
    "sg:phone":"+61 7 5449 7199",
    "sg:postcode":"4566",
    "sg:province":"QLD",
    "sg:tags":[
        "equipment",
        "energy",
        "solar"
    ],
    "wof:name":"Noosa Pool Care",
    "wof:placetype":"venue"
},
  "geometry": {"coordinates":[153.05046081500001,-26.4043960571],"type":"Point"}
}