{
  "type": "Feature",
  "properties": {
    "addr:full":"1 Fraser Pl Shalvey NSW 2770",
    "addr:housenumber":"1",
    "addr:postcode":"2770",
    "addr:street":"Fraser Pl",
    "iso:country":"AU",
    "sg:address":"1 Fraser Pl",
    "sg:city":"Shalvey",
    "sg:classifiers":[
        {
            "category":"Professional",
            "subcategory":"Detective & Security Services",
            "type":"Services"
        }
    ],
    "sg:phone":"+61 2 9628 8712",
    "sg:postcode":"2770",
    "sg:province":"NSW",
    "sg:tags":[
        "consultant",
        "system"
    ],
    "wof:name":"B K General Protection Services",
    "wof:placetype":"venue"
},
  "geometry": {"coordinates":[150.80763244600001,-33.724899292],"type":"Point"}
}