{
  "type": "Feature",
  "properties": {
    "iso:country":"AU",
    "sg:address":"4 Tova Drv",
    "sg:city":"Carrum Downs",
    "sg:classifiers":[
        {
            "category":"Manufacturing",
            "subcategory":"Rubber & Plastics",
            "type":"Manufacturing & Wholesale Goods"
        }
    ],
    "sg:phone":"+61 3 9775 1773",
    "sg:postcode":"3201",
    "sg:province":"VIC",
    "sg:tags":[
        "wholesaler",
        "product",
        "mfrs"
    ],
    "wof:name":"Matrix Lattice Works",
    "wof:placetype":"venue"
},
  "geometry": {"coordinates":[145.163483,-38.098915],"type":"Point"}
}