{
  "type": "Feature",
  "properties": {
    "iso:country":"AU",
    "sg:address":"87 Mons Rd",
    "sg:city":"Carina",
    "sg:classifiers":[
        {
            "category":"Professional",
            "subcategory":"Business Services",
            "type":"Services"
        }
    ],
    "sg:phone":"+61 411 423 777",
    "sg:postcode":"4152",
    "sg:province":"QLD",
    "sg:tags":[
        "drafting"
    ],
    "wof:name":"R & B Technical Services Pty Ltd",
    "wof:placetype":"venue"
},
  "geometry": {"coordinates":[153.091674805,-27.5030918121],"type":"Point"}
}