{
  "type": "Feature",
  "properties": {
    "addr:full":"132 Keira St Wollongong NSW 2500",
    "addr:housenumber":"132",
    "addr:postcode":"2500",
    "addr:street":"Keira St",
    "iso:country":"AU",
    "sg:address":"132 Keira St",
    "sg:city":"Wollongong",
    "sg:classifiers":[
        {
            "category":"Sports & Exercise",
            "subcategory":"Gym",
            "type":"Entertainment"
        }
    ],
    "sg:phone":"+61 2 4227 5622",
    "sg:postcode":"2500",
    "sg:province":"NSW",
    "sg:tags":[
        "health",
        "fitness"
    ],
    "wof:name":"movementMedicine",
    "wof:placetype":"venue"
},
  "geometry": {"coordinates":[150.89352400000001,-34.422302],"type":"Point"}
}