{
  "type": "Feature",
  "properties": {
    "iso:country":"AU",
    "sg:address":"Ground Floor,Stanley Place 235a Wills St",
    "sg:city":"Townsville",
    "sg:classifiers":[
        {
            "category":"Health Services",
            "subcategory":"Health Practitioner",
            "type":"Services"
        }
    ],
    "sg:phone":"+61 407 035 848",
    "sg:postcode":"4810",
    "sg:province":"QLD",
    "sg:tags":[
        "psychologist"
    ],
    "wof:name":"Bernadette Edwards Consultant Psychologist",
    "wof:placetype":"venue"
},
  "geometry": {"coordinates":[146.808426,-19.263569],"type":"Point"}
}