{
  "type": "Feature",
  "properties": {
    "addr:full":"8/ 134a Pt Cartwright Drv Buddina QLD 4575",
    "addr:housenumber":"/ 134a",
    "addr:postcode":"4575",
    "addr:street":"Pt Cartwright Drv",
    "iso:country":"AU",
    "sg:address":"8/ 134a Pt Cartwright Drv",
    "sg:city":"Buddina",
    "sg:classifiers":[
        {
            "category":"Health Services",
            "subcategory":"Health Practitioner",
            "type":"Services"
        }
    ],
    "sg:phone":"+61 7 5444 2844",
    "sg:postcode":"4575",
    "sg:province":"QLD",
    "sg:tags":[
        "naturopath"
    ],
    "wof:name":"Joan Goldsmith",
    "wof:placetype":"venue"
},
  "geometry": {"coordinates":[153.13002,-26.701191],"type":"Point"}
}