{
  "type": "Feature",
  "properties": {
    "iso:country":"AU",
    "sg:address":"Shop 29 Wanneroo Markets",
    "sg:city":"Wanneroo",
    "sg:classifiers":[
        {
            "category":"Shopping",
            "subcategory":"Bridal",
            "type":"Retail Goods"
        }
    ],
    "sg:phone":"+61 402 474 652",
    "sg:postcode":"6065",
    "sg:province":"WA",
    "sg:tags":[
        "hire",
        "wear"
    ],
    "wof:name":"Little Princess Boutique",
    "wof:placetype":"venue"
},
  "geometry": {"coordinates":[115.785728455,-31.7232913971],"type":"Point"}
}