{
  "type": "Feature",
  "properties": {
    "addr:full":"1 Linden Crt Taylors Lakes VIC 3038",
    "addr:housenumber":"1",
    "addr:postcode":"3038",
    "addr:street":"Linden Crt",
    "iso:country":"AU",
    "sg:address":"1 Linden Crt",
    "sg:city":"Taylors Lakes",
    "sg:classifiers":[
        {
            "category":"Personal",
            "subcategory":"Beauty Salon",
            "type":"Services"
        }
    ],
    "sg:phone":"+61 411 888 756",
    "sg:postcode":"3038",
    "sg:province":"VIC",
    "sg:tags":[
        "supply",
        "artist",
        "make-up"
    ],
    "wof:name":"Beauty and More",
    "wof:placetype":"venue"
},
  "geometry": {"coordinates":[144.78523300000001,-37.692715],"type":"Point"}
}