{
  "type": "Feature",
  "properties": {
    "addr:full":"124a Hawksview St Guildford NSW 2161",
    "addr:housenumber":"124a",
    "addr:postcode":"2161",
    "addr:street":"Hawksview St",
    "iso:country":"AU",
    "sg:address":"124a Hawksview St",
    "sg:city":"Guildford",
    "sg:classifiers":[
        {
            "category":"Food & Beverages",
            "subcategory":"Groceries & Convenience Stores",
            "type":"Retail Goods"
        }
    ],
    "sg:phone":"+61 2 9681 1154",
    "sg:postcode":"2161",
    "sg:province":"NSW",
    "wof:name":"Four Square Food Store",
    "wof:placetype":"venue"
},
  "geometry": {"coordinates":[150.98023986800001,-33.8459014893],"type":"Point"}
}