{
  "type": "Feature",
  "properties": {
    "addr:full":"42 Owen St Huskisson NSW 2540",
    "addr:housenumber":"42",
    "addr:postcode":"2540",
    "addr:street":"Owen St",
    "iso:country":"AU",
    "sg:address":"42 Owen St",
    "sg:city":"Huskisson",
    "sg:classifiers":[
        {
            "category":"Food & Beverages",
            "subcategory":"Liquor & Beverages",
            "type":"Retail Goods"
        }
    ],
    "sg:phone":"+61 2 4441 5341",
    "sg:postcode":"2540",
    "sg:province":"NSW",
    "sg:tags":[
        "store"
    ],
    "wof:name":"Husky Drive-In Bottle Shop",
    "wof:placetype":"venue"
},
  "geometry": {"coordinates":[150.66947937,-35.0387306213],"type":"Point"}
}