{
  "type": "Feature",
  "properties": {
    "addr:full":"Unit 51/ 11 - 21 Underwood Rd Homebush NSW 2140",
    "addr:housenumber":"/;21",
    "addr:postcode":"2140",
    "addr:street":"Underwood Rd",
    "iso:country":"AU",
    "sg:address":"Unit 51/ 11 - 21 Underwood Rd",
    "sg:city":"Homebush",
    "sg:classifiers":[
        {
            "category":"Building & Trades",
            "subcategory":"Construction",
            "type":"Services"
        }
    ],
    "sg:phone":"+61 2 9025 0700",
    "sg:postcode":"2140",
    "sg:province":"NSW",
    "sg:tags":[
        "industrial",
        "commercial",
        "air conditioning"
    ],
    "wof:name":"M+W Zander",
    "wof:placetype":"venue"
},
  "geometry": {"coordinates":[151.08128356899999,-33.8585929871],"type":"Point"}
}