{
  "type": "Feature",
  "properties": {
    "addr:full":"172 Ring Rd Ballarat VIC 3350",
    "addr:housenumber":"172",
    "addr:postcode":"3350",
    "addr:street":"Ring Rd",
    "iso:country":"AU",
    "sg:address":"172 Ring Rd",
    "sg:city":"Ballarat",
    "sg:classifiers":[
        {
            "category":"Home & Garden",
            "subcategory":"Hardware",
            "type":"Retail Goods"
        }
    ],
    "sg:phone":"+61 1800 639 966",
    "sg:postcode":"3350",
    "sg:province":"VIC",
    "sg:tags":[
        "tarpaulin"
    ],
    "wof:name":"C.E. Bartlett Pty Ltd",
    "wof:placetype":"venue"
},
  "geometry": {"coordinates":[143.802933,-37.53334],"type":"Point"}
}