{
  "type": "Feature",
  "properties": {
    "iso:country":"AU",
    "sg:address":"Ste 5/ 1 Leicester Ave",
    "sg:city":"Glen Waverley",
    "sg:classifiers":[
        {
            "category":"Real Estate",
            "subcategory":"Surveying",
            "type":"Services"
        }
    ],
    "sg:phone":"+61 3 9547 5017",
    "sg:postcode":"3150",
    "sg:province":"VIC",
    "sg:tags":[
        "building",
        "surveyor"
    ],
    "wof:name":"Wilsmore Nelson Group",
    "wof:placetype":"venue"
},
  "geometry": {"coordinates":[145.145721436,-37.8875350952],"type":"Point"}
}