{
  "type": "Feature",
  "properties": {
    "iso:country":"AU",
    "sg:address":"27 Laurence Rd",
    "sg:city":"Kalamunda",
    "sg:classifiers":[
        {
            "category":"Wholesale",
            "subcategory":"Machinery & Supplies",
            "type":"Manufacturing & Wholesale Goods"
        }
    ],
    "sg:phone":"+61 8 9451 1249",
    "sg:postcode":"6076",
    "sg:province":"WA",
    "sg:tags":[
        "equipment",
        "system",
        "elevating",
        "conveying"
    ],
    "wof:name":"Abalink Belt, Screw & Elevator Co",
    "wof:placetype":"venue"
},
  "geometry": {"coordinates":[116.07311248800001,-31.9908275604],"type":"Point"}
}