{
  "type": "Feature",
  "properties": {
    "iso:country":"AU",
    "sg:address":"9-17 Bellambi Street",
    "sg:city":"Tarrawanna",
    "sg:classifiers":[
        {
            "category":"Social Services",
            "subcategory":"Adult Care",
            "type":"Services"
        }
    ],
    "sg:phone":"+61 2 4283 6677",
    "sg:postcode":"2518",
    "sg:province":"NSW",
    "sg:tags":[
        "towing"
    ],
    "wof:name":"Tarrawanna Towing",
    "wof:placetype":"venue"
},
  "geometry": {"coordinates":[150.888077,-34.373699],"type":"Point"}
}