{
  "type": "Feature",
  "properties": {
    "addr:full":"75 Wyanna St Berowra Heights NSW 2082",
    "addr:housenumber":"75",
    "addr:postcode":"2082",
    "addr:street":"Wyanna St",
    "iso:country":"AU",
    "sg:address":"75 Wyanna St",
    "sg:city":"Berowra Heights",
    "sg:classifiers":[
        {
            "category":"Professional",
            "subcategory":"Computer Services",
            "type":"Services"
        }
    ],
    "sg:phone":"+61 2 9456 3027",
    "sg:postcode":"2082",
    "sg:province":"NSW",
    "sg:tags":[
        "tele-communications",
        "consultant"
    ],
    "wof:name":"G K Connections Pty Ltd",
    "wof:placetype":"venue"
},
  "geometry": {"coordinates":[151.12991332999999,-33.6174926758],"type":"Point"}
}