{
  "type": "Feature",
  "properties": {
    "addr:full":"8 Featherwood Drv Wagga Wagga NSW 2650",
    "addr:housenumber":"8",
    "addr:postcode":"2650",
    "addr:street":"Featherwood Drv",
    "iso:country":"AU",
    "sg:address":"8 Featherwood Drv",
    "sg:city":"Wagga Wagga",
    "sg:classifiers":[
        {
            "category":"Home & Garden",
            "subcategory":"Building Materials",
            "type":"Retail Goods"
        }
    ],
    "sg:phone":"+61 2 6926 2966",
    "sg:postcode":"2650",
    "sg:province":"NSW",
    "sg:tags":[
        "fencing"
    ],
    "wof:name":"Sharrock Mark Fencing",
    "wof:placetype":"venue"
},
  "geometry": {"coordinates":[147.34959411599999,-35.169002533],"type":"Point"}
}