{
  "type": "Feature",
  "properties": {
    "addr:full":"163 Magnesium Drv Crestmead QLD 4132",
    "addr:housenumber":"163",
    "addr:postcode":"4132",
    "addr:street":"Magnesium Drv",
    "iso:country":"AU",
    "sg:address":"163 Magnesium Drv",
    "sg:city":"Crestmead",
    "sg:classifiers":[
        {
            "category":"Wholesale",
            "subcategory":"Machinery & Supplies",
            "type":"Manufacturing & Wholesale Goods"
        }
    ],
    "sg:phone":"+61 7 3803 6100",
    "sg:postcode":"4132",
    "sg:province":"QLD",
    "sg:tags":[
        "equipment",
        "system",
        "elevating",
        "conveying"
    ],
    "wof:name":"G & B Stainless Pty Ltd",
    "wof:placetype":"venue"
},
  "geometry": {"coordinates":[153.078292847,-27.6833438873],"type":"Point"}
}