{
  "type": "Feature",
  "properties": {
    "iso:country":"AU",
    "sg:address":"19A Queen St",
    "sg:city":"Bentley",
    "sg:classifiers":[
        {
            "category":"Building & Trades",
            "subcategory":"Cleaning & Sanitation",
            "type":"Services"
        }
    ],
    "sg:phone":"+61 430 352 323",
    "sg:postcode":"6102",
    "sg:province":"WA",
    "sg:tags":[
        "industrial",
        "commercial",
        "contractor"
    ],
    "wof:name":"Nick & Nick The Cleaning Specialists",
    "wof:placetype":"venue"
},
  "geometry": {"coordinates":[115.91871643099999,-32.0032958984],"type":"Point"}
}