{
  "type": "Feature",
  "properties": {
    "addr:full":"Cnr Pound St & turf St Grafton NSW 2460",
    "addr:postcode":"2460",
    "addr:street":"Pound St & Turf St",
    "iso:country":"AU",
    "sg:address":"Cnr Pound St & turf St",
    "sg:city":"Grafton",
    "sg:classifiers":[
        {
            "category":"Food & Beverages",
            "subcategory":"Liquor & Beverages",
            "type":"Retail Goods"
        }
    ],
    "sg:phone":"+61 2 6642 2095",
    "sg:postcode":"2460",
    "sg:province":"NSW",
    "sg:tags":[
        "store"
    ],
    "wof:name":"Liquor Legends",
    "wof:placetype":"venue"
},
  "geometry": {"coordinates":[152.93728637699999,-29.6911125183],"type":"Point"}
}