{
  "type": "Feature",
  "properties": {
    "addr:full":"11/ 15 Deniliquin St Tocumwal NSW 2714",
    "addr:housenumber":"11 / 15",
    "addr:postcode":"2714",
    "addr:street":"Deniliquin St",
    "iso:country":"AU",
    "sg:address":"11/ 15 Deniliquin St",
    "sg:city":"Tocumwal",
    "sg:classifiers":[
        {
            "category":"Fast Food",
            "type":"Food & Drink"
        }
    ],
    "sg:phone":"+61 3 5874 2929",
    "sg:postcode":"2714",
    "sg:province":"NSW",
    "sg:tags":[
        "away",
        "take"
    ],
    "wof:name":"Tocumwal Cod Cafe",
    "wof:placetype":"venue"
},
  "geometry": {"coordinates":[145.55955505399999,-35.8089904785],"type":"Point"}
}