{
  "type": "Feature",
  "properties": {
    "addr:full":"Room 1, 141 High St Stanthorpe QLD 4380",
    "addr:housenumber":"141",
    "addr:postcode":"4380",
    "addr:street":"High St",
    "iso:country":"AU",
    "sg:address":"Room 1, 141 High St",
    "sg:city":"Stanthorpe",
    "sg:classifiers":[
        {
            "category":"Health Services",
            "subcategory":"Health Practitioner",
            "type":"Services"
        }
    ],
    "sg:phone":"+61 7 4681 4290",
    "sg:postcode":"4380",
    "sg:province":"QLD",
    "sg:tags":[
        "naturopath"
    ],
    "wof:name":"Christine Watt",
    "wof:placetype":"venue"
},
  "geometry": {"coordinates":[151.934967,-28.654881],"type":"Point"}
}