{
  "type": "Feature",
  "properties": {
    "addr:full":"Edwin Russell Building Brettoneaux St Seymour VIC 3660",
    "addr:postcode":"3660",
    "addr:street":"St",
    "iso:country":"AU",
    "sg:address":"Edwin Russell Building Brettoneaux St",
    "sg:city":"Seymour",
    "sg:classifiers":[
        {
            "category":"Health Services",
            "subcategory":"Doctor",
            "type":"Services"
        }
    ],
    "sg:phone":"+61 3 5792 3933",
    "sg:postcode":"3660",
    "sg:province":"VIC",
    "sg:tags":[
        "medical",
        "practitioner"
    ],
    "wof:name":"Gribbles Pathology (Vic) Pty Ltd",
    "wof:placetype":"venue"
},
  "geometry": {"coordinates":[145.13865661599999,-37.0188674927],"type":"Point"}
}