{
  "type": "Feature",
  "properties": {
    "addr:full":"255 Queens Rd Wandin VIC 3139",
    "addr:housenumber":"255",
    "addr:postcode":"3139",
    "addr:street":"Queens Rd",
    "iso:country":"AU",
    "sg:address":"255 Queens Rd",
    "sg:city":"Wandin",
    "sg:classifiers":[
        {
            "category":"Manufacturing",
            "subcategory":"Paper Products",
            "type":"Manufacturing & Wholesale Goods"
        }
    ],
    "sg:phone":"+61 3 5964 2486",
    "sg:postcode":"3139",
    "sg:province":"VIC",
    "sg:tags":[
        "sawdust",
        "supplier",
        "shaving"
    ],
    "wof:name":"Wandin Valley Mulch Pty Ltd",
    "wof:placetype":"venue"
},
  "geometry": {"coordinates":[145.45474243199999,-37.7961845398],"type":"Point"}
}