{
  "type": "Feature",
  "properties": {
    "addr:full":"206 Fulham Rd Aitkenvale QLD 4814",
    "addr:housenumber":"206",
    "addr:postcode":"4814",
    "addr:street":"Fulham Rd",
    "iso:country":"AU",
    "sg:address":"206 Fulham Rd",
    "sg:city":"Aitkenvale",
    "sg:classifiers":[
        {
            "category":"Health Services",
            "subcategory":"Dentist",
            "type":"Services"
        }
    ],
    "sg:phone":"+61 7 4779 2979",
    "sg:postcode":"4814",
    "sg:province":"QLD",
    "wof:name":"Dental 206",
    "wof:placetype":"venue"
},
  "geometry": {"coordinates":[146.76731899999999,-19.289511],"type":"Point"}
}