{
  "type": "Feature",
  "properties": {
    "iso:country":"AU",
    "sg:address":"Lochner St",
    "sg:city":"Latrobe",
    "sg:classifiers":[
        {
            "category":"Building & Trades",
            "subcategory":"Construction",
            "type":"Services"
        }
    ],
    "sg:phone":"+61 3 6426 1892",
    "sg:postcode":"7307",
    "sg:province":"TAS",
    "sg:tags":[
        "contractor"
    ],
    "wof:name":"Rand P & E",
    "wof:placetype":"venue"
},
  "geometry": {"coordinates":[146.40623500000001,-41.226673],"type":"Point"}
}