{
  "type": "Feature",
  "properties": {
    "addr:full":"390 Simpsons Rd Bardon QLD 4065",
    "addr:housenumber":"390",
    "addr:postcode":"4065",
    "addr:street":"Simpsons Rd",
    "iso:country":"AU",
    "sg:address":"390 Simpsons Rd",
    "sg:city":"Bardon",
    "sg:classifiers":[
        {
            "category":"Education",
            "subcategory":"Special Training",
            "type":"Public Place"
        }
    ],
    "sg:phone":"+61 7 3368 7755",
    "sg:postcode":"4065",
    "sg:province":"QLD",
    "sg:tags":[
        "development"
    ],
    "wof:name":"J Curve",
    "wof:placetype":"venue"
},
  "geometry": {"coordinates":[152.97012329099999,-27.4631748199],"type":"Point"}
}