{
  "type": "Feature",
  "properties": {
    "addr:full":"41 Brady St South Melbourne VIC 3205",
    "addr:housenumber":"41",
    "addr:postcode":"3205",
    "addr:street":"Brady St",
    "iso:country":"AU",
    "sg:address":"41 Brady St",
    "sg:city":"South Melbourne",
    "sg:classifiers":[
        {
            "category":"Social Services",
            "subcategory":"Job Training",
            "type":"Services"
        }
    ],
    "sg:phone":"+61 1300 888 637",
    "sg:postcode":"3205",
    "sg:province":"VIC",
    "sg:tags":[
        "hire",
        "computer",
        "leasing"
    ],
    "sg:website":"http://www.nes.com.au",
    "wof:name":"NES Electronic Hire",
    "wof:placetype":"venue"
},
  "geometry": {"coordinates":[144.94426000000001,-37.826462],"type":"Point"}
}