{
  "type": "Feature",
  "properties": {
    "addr:full":"225 Clarence St Howrah TAS 7018",
    "addr:housenumber":"225",
    "addr:postcode":"7018",
    "addr:street":"Clarence St",
    "iso:country":"AU",
    "sg:address":"225 Clarence St",
    "sg:city":"Howrah",
    "sg:classifiers":[
        {
            "category":"Fast Food",
            "type":"Food & Drink"
        }
    ],
    "sg:phone":"+61 3 6247 8446",
    "sg:postcode":"7018",
    "sg:province":"TAS",
    "sg:tags":[
        "away",
        "take"
    ],
    "wof:name":"Pizza Hut",
    "wof:placetype":"venue"
},
  "geometry": {"coordinates":[147.40116882300001,-42.87890625],"type":"Point"}
}