{
  "type": "Feature",
  "properties": {
    "addr:full":"Beach Rd Palm Island QLD 4816",
    "addr:postcode":"4816",
    "addr:street":"Beach Rd",
    "iso:country":"AU",
    "sg:address":"Beach Rd",
    "sg:city":"Palm Island",
    "sg:classifiers":[
        {
            "category":"Shopping",
            "subcategory":"Clothing, Apparel, & Fashions",
            "type":"Retail Goods"
        }
    ],
    "sg:phone":"+61 7 4770 1133",
    "sg:postcode":"4816",
    "sg:province":"QLD",
    "sg:tags":[
        "menswear"
    ],
    "wof:name":"Island Life Clothing",
    "wof:placetype":"venue"
},
  "geometry": {"coordinates":[146.58291600000001,-18.75477],"type":"Point"}
}