{
  "type": "Feature",
  "properties": {
    "addr:full":"Cnr Dewhurst & Barwan Sts Narrabri NSW 2390",
    "addr:postcode":"2390",
    "addr:street":"Cnr",
    "iso:country":"AU",
    "sg:address":"Cnr Dewhurst & Barwan Sts",
    "sg:city":"Narrabri",
    "sg:classifiers":[
        {
            "category":"Shopping",
            "type":"Retail Goods"
        }
    ],
    "sg:phone":"+61 2 6792 2122",
    "sg:postcode":"2390",
    "sg:province":"NSW",
    "sg:tags":[
        "agent",
        "stock"
    ],
    "wof:name":"Elders Limited",
    "wof:placetype":"venue"
},
  "geometry": {"coordinates":[149.78515625,-30.3261871338],"type":"Point"}
}