{
  "type": "Feature",
  "properties": {
    "addr:full":"26 James St Fortitude Valley QLD 4006",
    "addr:housenumber":"26",
    "addr:postcode":"4006",
    "addr:street":"James St",
    "iso:country":"AU",
    "sg:address":"26 James St",
    "sg:city":"Fortitude Valley",
    "sg:classifiers":[
        {
            "category":"Home & Garden",
            "subcategory":"Carpets & Floor Coverings",
            "type":"Retail Goods"
        }
    ],
    "sg:phone":"+61 7 3852 5322",
    "sg:postcode":"4006",
    "sg:province":"QLD",
    "sg:tags":[
        "wood"
    ],
    "sg:website":"http://www.boral.com.au",
    "wof:name":"Boral &#034;Walk On Wood&#034;",
    "wof:placetype":"venue"
},
  "geometry": {"coordinates":[153.03921508799999,-27.4560031891],"type":"Point"}
}