{
  "type": "Feature",
  "properties": {
    "addr:full":"PO Box 3692 Loganholme QLD 4129",
    "addr:postcode":"4129",
    "iso:country":"AU",
    "sg:address":"PO Box 3692",
    "sg:city":"Loganholme",
    "sg:classifiers":[
        {
            "category":"Banks & Credit Unions",
            "subcategory":"Financial Services",
            "type":"Services"
        }
    ],
    "sg:phone":"+61 7 3209 7092",
    "sg:postcode":"4129",
    "sg:province":"QLD",
    "sg:tags":[
        "planning"
    ],
    "wof:name":"Infocus Money Management",
    "wof:placetype":"venue"
},
  "geometry": {"coordinates":[153.185791016,-27.6725502014],"type":"Point"}
}