{
  "type": "Feature",
  "properties": {
    "iso:country":"AU",
    "sg:address":"1/ 12 Endeavour Drv",
    "sg:city":"Port Kennedy",
    "sg:classifiers":[
        {
            "category":"Health Services",
            "subcategory":"Doctor",
            "type":"Services"
        }
    ],
    "sg:phone":"+61 8 9524 6611",
    "sg:postcode":"6172",
    "sg:province":"WA",
    "sg:tags":[
        "podiatrist"
    ],
    "wof:name":"Chia David",
    "wof:placetype":"venue"
},
  "geometry": {"coordinates":[115.75221999999999,-32.370308],"type":"Point"}
}