{
  "type": "Feature",
  "properties": {
    "addr:full":"PO Box 189 Robina QLD 4226",
    "addr:postcode":"4226",
    "iso:country":"AU",
    "sg:address":"PO Box 189",
    "sg:city":"Robina",
    "sg:classifiers":[
        {
            "category":"Retail",
            "subcategory":"Event Space",
            "type":"Services"
        }
    ],
    "sg:phone":"+61 7 5593 2600",
    "sg:postcode":"4226",
    "sg:province":"QLD",
    "sg:tags":[
        "function",
        "organiser"
    ],
    "wof:name":"Logan City Tavern And Function Room",
    "wof:placetype":"venue"
},
  "geometry": {"coordinates":[153.390380859,-28.0680007935],"type":"Point"}
}