{
  "type": "Feature",
  "properties": {
    "addr:full":"2 Vialls Ave Parkdale VIC 3195",
    "addr:housenumber":"2",
    "addr:postcode":"3195",
    "addr:street":"Vialls Ave",
    "iso:country":"AU",
    "sg:address":"2 Vialls Ave",
    "sg:city":"Parkdale",
    "sg:classifiers":[
        {
            "category":"Home & Garden",
            "subcategory":"Building Materials",
            "type":"Retail Goods"
        }
    ],
    "sg:phone":"+61 419 568 151",
    "sg:postcode":"3195",
    "sg:province":"VIC",
    "sg:tags":[
        "lawn",
        "cutting",
        "maintenance"
    ],
    "wof:name":"Mordi Mowing",
    "wof:placetype":"venue"
},
  "geometry": {"coordinates":[145.085281372,-37.9931678772],"type":"Point"}
}