{
  "type": "Feature",
  "properties": {
    "addr:full":"PO Box 2246 Marmion WA 6020",
    "addr:postcode":"6020",
    "iso:country":"AU",
    "sg:address":"PO Box 2246",
    "sg:city":"Marmion",
    "sg:classifiers":[
        {
            "category":"Banks & Credit Unions",
            "subcategory":"Financial Services",
            "type":"Services"
        }
    ],
    "sg:phone":"+61 8 9448 8077",
    "sg:postcode":"6020",
    "sg:province":"WA",
    "sg:tags":[
        "settlement",
        "nt",
        "agent",
        "wa"
    ],
    "wof:name":"Concept Settlements",
    "wof:placetype":"venue"
},
  "geometry": {"coordinates":[115.758827209,-31.8460502625],"type":"Point"}
}