{
  "type": "Feature",
  "properties": {
    "iso:country":"AU",
    "sg:address":"138 Hair St",
    "sg:city":"Echuca",
    "sg:classifiers":[
        {
            "category":"Shopping",
            "subcategory":"Computers & Home Electronics",
            "type":"Retail Goods"
        }
    ],
    "sg:phone":"+61 3 5480 2003",
    "sg:postcode":"3564",
    "sg:province":"VIC",
    "sg:tags":[
        "equipment",
        "supply"
    ],
    "wof:name":"M.R. Computer Supplies",
    "wof:placetype":"venue"
},
  "geometry": {"coordinates":[144.75001525900001,-36.1291503906],"type":"Point"}
}