{
  "type": "Feature",
  "properties": {
    "addr:full":"Level 1/ 77b Matthews Ave Airport West VIC 3042",
    "addr:housenumber":"/ 77b",
    "addr:postcode":"3042",
    "addr:street":"Matthews Ave",
    "iso:country":"AU",
    "sg:address":"Level 1/ 77b Matthews Ave",
    "sg:city":"Airport West",
    "sg:classifiers":[
        {
            "category":"Shopping",
            "subcategory":"Computers & Home Electronics",
            "type":"Retail Goods"
        }
    ],
    "sg:phone":"+61 3 9330 4566",
    "sg:postcode":"3042",
    "sg:province":"VIC",
    "sg:tags":[
        "small",
        "equipment",
        "business"
    ],
    "wof:name":"Centastaff IT",
    "wof:placetype":"venue"
},
  "geometry": {"coordinates":[144.89173889200001,-37.7183952332],"type":"Point"}
}