{
  "type": "Feature",
  "properties": {
    "iso:country":"AU",
    "sg:address":"178 Wcker Rd",
    "sg:city":"Mansfield",
    "sg:classifiers":[
        {
            "category":"Retail",
            "subcategory":"Auto Rental",
            "type":"Services"
        }
    ],
    "sg:phone":"+61 7 3347 8000",
    "sg:postcode":"4122",
    "sg:province":"QLD",
    "sg:tags":[
        "car",
        "armoured"
    ],
    "wof:name":"Armaguard",
    "wof:placetype":"venue"
},
  "geometry": {"coordinates":[153.103439331,-27.5337657928],"type":"Point"}
}