{
  "type": "Feature",
  "properties": {
    "addr:full":"1129 Great Western Hwy Lithgow NSW 2790",
    "addr:housenumber":"1129",
    "addr:postcode":"2790",
    "addr:street":"Great Western Hwy",
    "iso:country":"AU",
    "sg:address":"1129 Great Western Hwy",
    "sg:city":"Lithgow",
    "sg:classifiers":[
        {
            "category":"Autos & Motor Vehicles",
            "subcategory":"Automobile Sales",
            "type":"Retail Goods"
        }
    ],
    "sg:phone":"+61 2 6351 3333",
    "sg:postcode":"2790",
    "sg:province":"NSW",
    "sg:tags":[
        "car",
        "new"
    ],
    "wof:name":"Lithgow Valley Kia",
    "wof:placetype":"venue"
},
  "geometry": {"coordinates":[150.12278747600001,-33.511138916],"type":"Point"}
}