{
  "type": "Feature",
  "properties": {
    "addr:full":"18 Lancaster St Ingleburn NSW 2565",
    "addr:housenumber":"18",
    "addr:postcode":"2565",
    "addr:street":"Lancaster St",
    "iso:country":"AU",
    "sg:address":"18 Lancaster St",
    "sg:city":"Ingleburn",
    "sg:classifiers":[
        {
            "category":"Wholesale",
            "subcategory":"Drugs",
            "type":"Manufacturing & Wholesale Goods"
        }
    ],
    "sg:phone":"+61 2 9829 2111",
    "sg:postcode":"2565",
    "sg:province":"NSW",
    "sg:tags":[
        "wholesaler",
        "pharmaceutical",
        "product",
        "mfrs"
    ],
    "wof:name":"Chemists Own Pty Ltd",
    "wof:placetype":"venue"
},
  "geometry": {"coordinates":[150.86349487300001,-33.9921722412],"type":"Point"}
}