{
  "type": "Feature",
  "properties": {
    "iso:country":"AU",
    "sg:address":"Shop 6, 200 Scott St",
    "sg:city":"Cairns",
    "sg:classifiers":[
        {
            "category":"Building & Trades",
            "subcategory":"Construction",
            "type":"Services"
        }
    ],
    "sg:phone":"+61 7 4045 1436",
    "sg:postcode":"4870",
    "sg:province":"QLD",
    "sg:tags":[
        "insulation",
        "contractor"
    ],
    "wof:name":"Alsafe Cairns",
    "wof:placetype":"venue"
},
  "geometry": {"coordinates":[145.75100707999999,-16.9410247803],"type":"Point"}
}