{
  "type": "Feature",
  "properties": {
    "addr:full":"430 Waverley Rd Malvern East VIC 3145",
    "addr:housenumber":"430",
    "addr:postcode":"3145",
    "addr:street":"Waverley Rd",
    "iso:country":"AU",
    "sg:address":"430 Waverley Rd",
    "sg:city":"Malvern East",
    "sg:classifiers":[
        {
            "category":"Personal",
            "subcategory":"Beauty Salon",
            "type":"Services"
        }
    ],
    "sg:phone":"+61 3 9571 3843",
    "sg:postcode":"3145",
    "sg:province":"VIC",
    "sg:tags":[
        "hairdresser"
    ],
    "wof:name":"Absolute Hair Salon",
    "wof:placetype":"venue"
},
  "geometry": {"coordinates":[145.06646728499999,-37.8782615662],"type":"Point"}
}