{
  "type": "Feature",
  "properties": {
    "addr:full":"35 Excelsior Rd Gympie QLD 4570",
    "addr:housenumber":"35",
    "addr:postcode":"4570",
    "addr:street":"Excelsior Rd",
    "iso:country":"AU",
    "sg:address":"35 Excelsior Rd",
    "sg:city":"Gympie",
    "sg:classifiers":[
        {
            "category":"Health Services",
            "subcategory":"Doctor",
            "type":"Services"
        }
    ],
    "sg:phone":"+61 7 5482 5899",
    "sg:postcode":"4570",
    "sg:province":"QLD",
    "sg:tags":[
        "medical",
        "practitioner"
    ],
    "wof:name":"Excelsior Road Medical Centre",
    "wof:placetype":"venue"
},
  "geometry": {"coordinates":[152.666259766,-26.1981182098],"type":"Point"}
}