{
  "type": "Feature",
  "properties": {
    "iso:country":"AU",
    "sg:address":"Newbriatan Rd",
    "sg:city":"Robinvale",
    "sg:classifiers":[
        {
            "category":"Farming",
            "subcategory":"Berry Farm",
            "type":"Manufacturing & Wholesale Goods"
        }
    ],
    "sg:phone":"+61 3 5026 3129",
    "sg:postcode":"3549",
    "sg:province":"VIC",
    "sg:tags":[
        "fruit",
        "grower"
    ],
    "wof:name":"Zappia R",
    "wof:placetype":"venue"
},
  "geometry": {"coordinates":[142.75906372099999,-34.603603363],"type":"Point"}
}