{
  "type": "Feature",
  "properties": {
    "iso:country":"AU",
    "sg:address":"101 St Johns Rd",
    "sg:city":"Campbelltown",
    "sg:classifiers":[
        {
            "category":"Real Estate",
            "subcategory":"Surveying",
            "type":"Services"
        }
    ],
    "sg:phone":"+61 2 4626 8875",
    "sg:postcode":"2560",
    "sg:province":"NSW",
    "sg:tags":[
        "surveyor",
        "land"
    ],
    "wof:name":"Basile M W",
    "wof:placetype":"venue"
},
  "geometry": {"coordinates":[150.821411133,-34.0867614746],"type":"Point"}
}