{
  "type": "Feature",
  "properties": {
    "iso:country":"AU",
    "sg:address":"Unit 3, 218 Leitchs Rd",
    "sg:city":"Brendale",
    "sg:classifiers":[
        {
            "category":"Manufacturing",
            "subcategory":"Leather Goods",
            "type":"Manufacturing & Wholesale Goods"
        }
    ],
    "sg:phone":"+61 7 3881 2488",
    "sg:postcode":"4500",
    "sg:province":"QLD",
    "sg:tags":[
        "wholesaler",
        "mfrs"
    ],
    "wof:name":"Syd Hill & Sons Pty Ltd",
    "wof:placetype":"venue"
},
  "geometry": {"coordinates":[152.979644775,-27.325258255],"type":"Point"}
}