{
  "type": "Feature",
  "properties": {
    "addr:full":"35 Welshpool Rd Welshpool WA 6106",
    "addr:housenumber":"35",
    "addr:postcode":"6106",
    "addr:street":"Welshpool Rd",
    "iso:country":"AU",
    "sg:address":"35 Welshpool Rd",
    "sg:city":"Welshpool",
    "sg:classifiers":[
        {
            "category":"Autos & Motor Vehicles",
            "subcategory":"Auto Supplies",
            "type":"Retail Goods"
        }
    ],
    "sg:phone":"+61 8 9362 1744",
    "sg:postcode":"6106",
    "sg:province":"WA",
    "sg:tags":[
        "wheel",
        "four",
        "equipment",
        "drive",
        "accessory"
    ],
    "wof:name":"Front Runner 4 x 4 Technology",
    "wof:placetype":"venue"
},
  "geometry": {"coordinates":[115.918312073,-31.994052887],"type":"Point"}
}