{
  "type": "Feature",
  "properties": {
    "addr:full":"126c Canterbury Rd Blackburn South VIC 3130",
    "addr:housenumber":"126c",
    "addr:postcode":"3130",
    "addr:street":"Canterbury Rd",
    "iso:country":"AU",
    "sg:address":"126c Canterbury Rd",
    "sg:city":"Blackburn South",
    "sg:classifiers":[
        {
            "category":"Health Services",
            "subcategory":"Health Practitioner",
            "type":"Services"
        }
    ],
    "sg:phone":"+61 3 9878 0890",
    "sg:postcode":"3130",
    "sg:province":"VIC",
    "sg:tags":[
        "reiki"
    ],
    "wof:name":"Renee Burton Natural Therapies",
    "wof:placetype":"venue"
},
  "geometry": {"coordinates":[145.14755249000001,-37.8319549561],"type":"Point"}
}