{
  "type": "Feature",
  "properties": {
    "addr:full":"53 Taylor St Armidale NSW 2350",
    "addr:housenumber":"53",
    "addr:postcode":"2350",
    "addr:street":"Taylor St",
    "iso:country":"AU",
    "sg:address":"53 Taylor St",
    "sg:city":"Armidale",
    "sg:classifiers":[
        {
            "category":"Health Services",
            "subcategory":"Health Practitioner",
            "type":"Services"
        }
    ],
    "sg:phone":"+61 2 6772 7528",
    "sg:postcode":"2350",
    "sg:province":"NSW",
    "sg:tags":[
        "alternative"
    ],
    "wof:name":"Julie Hicks - Geomancer",
    "wof:placetype":"venue"
},
  "geometry": {"coordinates":[151.67494201700001,-30.5061302185],"type":"Point"}
}