{
  "type": "Feature",
  "properties": {
    "addr:full":"Level 19, 140 St Georges Tce Perth WA 6000",
    "addr:housenumber":"140",
    "addr:postcode":"6000",
    "addr:street":"St Georges Tce",
    "iso:country":"AU",
    "sg:address":"Level 19, 140 St Georges Tce",
    "sg:city":"Perth",
    "sg:classifiers":[
        {
            "category":"Real Estate",
            "subcategory":"Real Estate Services",
            "type":"Services"
        }
    ],
    "sg:phone":"+61 8 9261 6666",
    "sg:postcode":"6000",
    "sg:province":"WA",
    "sg:tags":[
        "valuer"
    ],
    "wof:name":"Colliers International",
    "wof:placetype":"venue"
},
  "geometry": {"coordinates":[115.856391907,-31.954492569],"type":"Point"}
}