{
  "type": "Feature",
  "properties": {
    "addr:full":"111 McMillian Ave Parkhurst QLD 4702",
    "addr:housenumber":"111",
    "addr:postcode":"4702",
    "addr:street":"Mcmillian Ave",
    "iso:country":"AU",
    "sg:address":"111 McMillian Ave",
    "sg:city":"Parkhurst",
    "sg:classifiers":[
        {
            "category":"Building & Trades",
            "subcategory":"Construction",
            "type":"Services"
        }
    ],
    "sg:phone":"+61 7 4936 3630",
    "sg:postcode":"4702",
    "sg:province":"QLD",
    "sg:tags":[
        "contractor"
    ],
    "wof:name":"Medlin RL & HF Building Contractors",
    "wof:placetype":"venue"
},
  "geometry": {"coordinates":[150.514434814,-23.304889679],"type":"Point"}
}