{
  "type": "Feature",
  "properties": {
    "addr:full":"3, 571 Military Rd Mosman NSW 2088",
    "addr:housenumber":"3 571",
    "addr:postcode":"2088",
    "addr:street":"Military Rd",
    "iso:country":"AU",
    "sg:address":"3, 571 Military Rd",
    "sg:city":"Mosman",
    "sg:classifiers":[
        {
            "category":"Personal",
            "subcategory":"Beauty Salon",
            "type":"Services"
        }
    ],
    "sg:phone":"+61 2 9969 7818",
    "sg:postcode":"2088",
    "sg:province":"NSW",
    "sg:tags":[
        "hair",
        "wedding"
    ],
    "wof:name":"Bromptons Hair & Bromptons Bride Hair & Make-up Specialists",
    "wof:placetype":"venue"
},
  "geometry": {"coordinates":[151.24090576200001,-33.8246421814],"type":"Point"}
}