{
  "type": "Feature",
  "properties": {
    "addr:full":"227 Adelaide St Maryborough QLD 4650",
    "addr:housenumber":"227",
    "addr:postcode":"4650",
    "addr:street":"Adelaide St",
    "iso:country":"AU",
    "sg:address":"227 Adelaide St",
    "sg:city":"Maryborough",
    "sg:classifiers":[
        {
            "category":"Wholesale",
            "subcategory":"Medical Equipment & Supplies",
            "type":"Manufacturing & Wholesale Goods"
        }
    ],
    "sg:phone":"+61 7 4121 3184",
    "sg:postcode":"4650",
    "sg:province":"QLD",
    "sg:tags":[
        "aid",
        "care",
        "health",
        "home"
    ],
    "wof:name":"Costigans Good Price Pharmacy Warehouse",
    "wof:placetype":"venue"
},
  "geometry": {"coordinates":[152.70210299999999,-25.538345],"type":"Point"}
}