{
  "type": "Feature",
  "properties": {
    "iso:country":"AU",
    "sg:address":"75 Dunloe Ave",
    "sg:city":"Mont Albert North",
    "sg:classifiers":[
        {
            "category":"Personal",
            "subcategory":"Beauty Salon",
            "type":"Services"
        }
    ],
    "sg:phone":"+61 3 9890 9427",
    "sg:postcode":"3129",
    "sg:province":"VIC",
    "sg:tags":[
        "hairdresser"
    ],
    "wof:name":"Kristoff's Hair Salon",
    "wof:placetype":"venue"
},
  "geometry": {"coordinates":[145.10922241200001,-37.8084411621],"type":"Point"}
}