{
  "type": "Feature",
  "properties": {
    "addr:full":"90 Teviot Rd Carbrook QLD 4130",
    "addr:housenumber":"90",
    "addr:postcode":"4130",
    "addr:street":"Teviot Rd",
    "iso:country":"AU",
    "sg:address":"90 Teviot Rd",
    "sg:city":"Carbrook",
    "sg:classifiers":[
        {
            "category":"Building & Trades",
            "subcategory":"Construction",
            "type":"Services"
        }
    ],
    "sg:phone":"+61 7 3206 8674",
    "sg:postcode":"4130",
    "sg:province":"QLD",
    "sg:tags":[
        "contractor"
    ],
    "wof:name":"Lechner F & L J",
    "wof:placetype":"venue"
},
  "geometry": {"coordinates":[153.27536010700001,-27.6786212921],"type":"Point"}
}