{
  "type": "Feature",
  "properties": {
    "addr:full":"Shop 24, Shopping World Cnr Oxley Hwy & Denne St Tamworth NSW 2340",
    "addr:housenumber":"shop 24;cnr",
    "addr:postcode":"2340",
    "addr:street":"Oxley Hwy & Denne St",
    "iso:country":"AU",
    "sg:address":"Shop 24, Shopping World Cnr Oxley Hwy & Denne St",
    "sg:city":"Tamworth",
    "sg:classifiers":[
        {
            "category":"Personal",
            "subcategory":"Beauty Salon",
            "type":"Services"
        }
    ],
    "sg:phone":"+61 2 6762 7222",
    "sg:postcode":"2340",
    "sg:province":"NSW",
    "sg:tags":[
        "hairdresser"
    ],
    "wof:name":"Just Cuts",
    "wof:placetype":"venue"
},
  "geometry": {"coordinates":[150.92852783199999,-31.0906391144],"type":"Point"}
}