{
  "type": "Feature",
  "properties": {
    "iso:country":"AU",
    "sg:address":"6 Fogarty St",
    "sg:city":"Alice Springs",
    "sg:classifiers":[
        {
            "category":"Professional",
            "subcategory":"Printing & Photocopies",
            "type":"Services"
        }
    ],
    "sg:phone":"+61 8 8953 1903",
    "sg:postcode":"0870",
    "sg:province":"NT",
    "sg:tags":[
        "photocopier"
    ],
    "wof:name":"Comspec (N.T.) Pty Ltd",
    "wof:placetype":"venue"
},
  "geometry": {"coordinates":[133.872283936,-23.700553894],"type":"Point"}
}