{
  "type": "Feature",
  "properties": {
    "addr:full":"1 Benalla Rd Shepparton VIC 3630",
    "addr:housenumber":"1",
    "addr:postcode":"3630",
    "addr:street":"Benalla Rd",
    "iso:country":"AU",
    "sg:address":"1 Benalla Rd",
    "sg:city":"Shepparton",
    "sg:classifiers":[
        {
            "category":"Autos & Motor Vehicles",
            "subcategory":"Automobile Sales",
            "type":"Retail Goods"
        }
    ],
    "sg:phone":"+61 3 5821 9411",
    "sg:postcode":"3630",
    "sg:province":"VIC",
    "sg:tags":[
        "car",
        "new"
    ],
    "wof:name":"Kia Thompson",
    "wof:placetype":"venue"
},
  "geometry": {"coordinates":[145.41311645499999,-36.3827934265],"type":"Point"}
}