{
  "type": "Feature",
  "properties": {
    "addr:full":"Level 4, AMP Place, 10 Eagle St, Brisbane QLD 4000",
    "addr:housenumber":"10",
    "addr:postcode":"4000",
    "addr:street":"Amp;Eagle St",
    "iso:country":"AU",
    "sg:address":"Level 4, AMP Place, 10",
    "sg:city":"Eagle St, Brisbane",
    "sg:classifiers":[
        {
            "category":"Professional",
            "subcategory":"Employment Agencies",
            "type":"Services"
        }
    ],
    "sg:phone":"+61 7 3279 9789",
    "sg:postcode":"4000",
    "sg:province":"QLD",
    "wof:name":"Fresh Soul Recruitment Services",
    "wof:placetype":"venue"
},
  "geometry": {"coordinates":[153.03001403799999,-27.4687213898],"type":"Point"}
}