{
  "type": "Feature",
  "properties": {
    "iso:country":"AU",
    "sg:address":"Unit 2/ 19 Pineview Drv",
    "sg:city":"Goonellabah",
    "sg:classifiers":[
        {
            "category":"Personal",
            "subcategory":"Massage",
            "type":"Services"
        }
    ],
    "sg:phone":"+61 414 790 488",
    "sg:postcode":"2480",
    "sg:province":"NSW",
    "sg:tags":[
        "therapy"
    ],
    "wof:name":"Healing Hands Massage Therapy",
    "wof:placetype":"venue"
},
  "geometry": {"coordinates":[153.3384552,-28.8195877075],"type":"Point"}
}