{
  "type": "Feature",
  "properties": {
    "iso:country":"AU",
    "sg:address":"2 Kendall St",
    "sg:city":"Canterbury",
    "sg:classifiers":[
        {
            "category":"Social Services",
            "subcategory":"Child Care",
            "type":"Services"
        }
    ],
    "sg:phone":"+61 3 9836 2106",
    "sg:postcode":"3126",
    "sg:province":"VIC",
    "sg:tags":[
        "support",
        "health"
    ],
    "wof:name":"Maternal & Child Health Centres",
    "wof:placetype":"venue"
},
  "geometry": {"coordinates":[145.077926636,-37.8257675171],"type":"Point"}
}