{
  "type": "Feature",
  "properties": {
    "addr:full":"76 Cawarra Rd Caringbah NSW 2229",
    "addr:housenumber":"76",
    "addr:postcode":"2229",
    "addr:street":"Cawarra Rd",
    "iso:country":"AU",
    "sg:address":"76 Cawarra Rd",
    "sg:city":"Caringbah",
    "sg:classifiers":[
        {
            "category":"Banks & Credit Unions",
            "subcategory":"Investment Brokerage",
            "type":"Services"
        }
    ],
    "sg:phone":"+61 408 296 773",
    "sg:postcode":"2229",
    "sg:province":"NSW",
    "sg:tags":[
        "finance",
        "broker"
    ],
    "wof:name":"Robert Moylan & Associates P/L",
    "wof:placetype":"venue"
},
  "geometry": {"coordinates":[151.125274658,-34.0347290039],"type":"Point"}
}