{
  "type": "Feature",
  "properties": {
    "iso:country":"AU",
    "sg:address":"26 Kendall North Av",
    "sg:city":"Queanbeyan",
    "sg:classifiers":[
        {
            "category":"Wholesale",
            "subcategory":"Home Furnishings",
            "type":"Manufacturing & Wholesale Goods"
        }
    ],
    "sg:phone":"+61 2 6297 4443",
    "sg:postcode":"2620",
    "sg:province":"ACT",
    "sg:tags":[
        "terrazzo"
    ],
    "wof:name":"PDA Marble & Granite",
    "wof:placetype":"venue"
},
  "geometry": {"coordinates":[149.20379638700001,-35.3496246338],"type":"Point"}
}