{
  "type": "Feature",
  "properties": {
    "addr:full":"1st Floor 47 Kishorn Rd Applecross WA 6153",
    "addr:housenumber":"47",
    "addr:postcode":"6153",
    "addr:street":"Kishorn Rd",
    "iso:country":"AU",
    "sg:address":"1st Floor 47 Kishorn Rd",
    "sg:city":"Applecross",
    "sg:classifiers":[
        {
            "category":"Professional",
            "subcategory":"Research",
            "type":"Services"
        }
    ],
    "sg:phone":"+61 8 9316 2322",
    "sg:postcode":"6153",
    "sg:province":"WA",
    "sg:tags":[
        "market"
    ],
    "sg:website":"http://www.marketresearch.com.au",
    "wof:name":"Patterson Market Research",
    "wof:placetype":"venue"
},
  "geometry": {"coordinates":[115.848068,-32.012657],"type":"Point"}
}