{
  "type": "Feature",
  "properties": {
    "addr:full":"QTV House, 1 Aquatic Place North Rockhampton QLD 4701",
    "addr:housenumber":"1",
    "addr:postcode":"4701",
    "addr:street":"Aquatic Place North",
    "iso:country":"AU",
    "sg:address":"QTV House, 1 Aquatic Place",
    "sg:city":"North Rockhampton",
    "sg:classifiers":[
        {
            "category":"Professional",
            "subcategory":"Engineering",
            "type":"Services"
        }
    ],
    "sg:phone":"+61 7 4924 7500",
    "sg:postcode":"4701",
    "sg:province":"QLD",
    "sg:tags":[
        "consulting",
        "engineer"
    ],
    "wof:name":"Cardno",
    "wof:placetype":"venue"
},
  "geometry": {"coordinates":[150.51939392099999,-23.356306076],"type":"Point"}
}