{
  "type": "Feature",
  "properties": {
    "addr:full":"40 New Grove Rd Healesville VIC 3777",
    "addr:housenumber":"40",
    "addr:postcode":"3777",
    "addr:street":"New Grove Rd",
    "iso:country":"AU",
    "sg:address":"40 New Grove Rd",
    "sg:city":"Healesville",
    "sg:classifiers":[
        {
            "category":"Building & Trades",
            "subcategory":"Construction",
            "type":"Services"
        }
    ],
    "sg:phone":"+61 3 5962 4231",
    "sg:postcode":"3777",
    "sg:province":"VIC",
    "sg:tags":[
        "contractor"
    ],
    "wof:name":"Peck R A",
    "wof:placetype":"venue"
},
  "geometry": {"coordinates":[145.523956,-37.661518],"type":"Point"}
}