{
  "type": "Feature",
  "properties": {
    "addr:full":"981 North East Rd Modbury SA 5092",
    "addr:housenumber":"981",
    "addr:postcode":"5092",
    "addr:street":"North East Rd",
    "iso:country":"AU",
    "sg:address":"981 North East Rd",
    "sg:city":"Modbury",
    "sg:classifiers":[
        {
            "category":"Home & Garden",
            "subcategory":"Carpets & Floor Coverings",
            "type":"Retail Goods"
        }
    ],
    "sg:phone":"+61 8 8265 4902",
    "sg:postcode":"5092",
    "sg:province":"SA",
    "sg:tags":[
        "tile",
        "wall"
    ],
    "wof:name":"Beaumont Tiles",
    "wof:placetype":"venue"
},
  "geometry": {"coordinates":[138.686843872,-34.8313484192],"type":"Point"}
}