{
  "type": "Feature",
  "properties": {
    "addr:full":"1198 Great Northern Hwy Upper Swan WA 6069",
    "addr:housenumber":"1198",
    "addr:postcode":"6069",
    "addr:street":"Great Northern Hwy Upper",
    "iso:country":"AU",
    "sg:address":"1198 Great Northern Hwy",
    "sg:city":"Upper Swan",
    "sg:classifiers":[
        {
            "category":"Utilities",
            "subcategory":"Electric",
            "type":"Services"
        }
    ],
    "sg:phone":"+61 8 9296 4490",
    "sg:postcode":"6069",
    "sg:province":"WA",
    "sg:tags":[
        "electrical",
        "contractor"
    ],
    "wof:name":"Fardell K R",
    "wof:placetype":"venue"
},
  "geometry": {"coordinates":[116.02986908,-31.7698078156],"type":"Point"}
}