{
  "type": "Feature",
  "properties": {
    "addr:full":"PO Box 584 Kotara NSW 2289",
    "addr:postcode":"2289",
    "iso:country":"AU",
    "sg:address":"PO Box 584",
    "sg:city":"Kotara",
    "sg:classifiers":[
        {
            "category":"Utilities",
            "subcategory":"Mobile Phone",
            "type":"Services"
        }
    ],
    "sg:phone":"+61 1800 022 248",
    "sg:postcode":"2289",
    "sg:province":"NSW",
    "sg:tags":[
        "repair",
        "telephone"
    ],
    "wof:name":"Commtek Pty Ltd",
    "wof:placetype":"venue"
},
  "geometry": {"coordinates":[151.710693359,-32.9406318665],"type":"Point"}
}