{
  "type": "Feature",
  "properties": {
    "iso:country":"AU",
    "sg:address":"455 Wyndham St",
    "sg:city":"Shepparton",
    "sg:classifiers":[
        {
            "category":"Retail",
            "subcategory":"Event Space",
            "type":"Services"
        }
    ],
    "sg:phone":"+61 3 5831 4488",
    "sg:postcode":"3630",
    "sg:province":"VIC",
    "sg:tags":[
        "venue",
        "reception",
        "wedding"
    ],
    "wof:name":"Shepparton Club Inc.",
    "wof:placetype":"venue"
},
  "geometry": {"coordinates":[145.39874267600001,-36.3846282959],"type":"Point"}
}