{
  "type": "Feature",
  "properties": {
    "iso:country":"AU",
    "sg:address":"Unit 2/ 54 Rene St",
    "sg:city":"Noosaville",
    "sg:classifiers":[
        {
            "category":"Manufacturing",
            "subcategory":"Metals",
            "type":"Manufacturing & Wholesale Goods"
        }
    ],
    "sg:phone":"+61 7 5449 9555",
    "sg:postcode":"4566",
    "sg:province":"QLD",
    "sg:tags":[
        "polisher"
    ],
    "wof:name":"Mike's Custom Shop",
    "wof:placetype":"venue"
},
  "geometry": {"coordinates":[153.04217529300001,-26.4157867432],"type":"Point"}
}