{
  "type": "Feature",
  "properties": {
    "addr:full":"Lvl 3/ 7 Bridge St Sydney NSW 2000",
    "addr:housenumber":"/ 7",
    "addr:postcode":"2000",
    "addr:street":"Bridge St",
    "iso:country":"AU",
    "sg:address":"Lvl 3/ 7 Bridge St",
    "sg:city":"Sydney",
    "sg:classifiers":[
        {
            "category":"Banks & Credit Unions",
            "subcategory":"Investment Brokerage",
            "type":"Services"
        }
    ],
    "sg:phone":"+61 2 9241 5885",
    "sg:postcode":"2000",
    "sg:province":"NSW",
    "sg:tags":[
        "share",
        "broker",
        "stock"
    ],
    "wof:name":"VBM Capital Pty Ltd",
    "wof:placetype":"venue"
},
  "geometry": {"coordinates":[151.20817565900001,-33.8637924194],"type":"Point"}
}