{
  "type": "Feature",
  "properties": {
    "addr:full":"385 Fisher St Cloverdale WA 6105",
    "addr:housenumber":"385",
    "addr:postcode":"6105",
    "addr:street":"Fisher St",
    "iso:country":"AU",
    "sg:address":"385 Fisher St",
    "sg:city":"Cloverdale",
    "sg:classifiers":[
        {
            "category":"Professional",
            "type":"Services"
        }
    ],
    "sg:phone":"+61 8 9478 4914",
    "sg:postcode":"6105",
    "sg:province":"WA",
    "sg:tags":[
        "transport"
    ],
    "wof:name":"Hun Transport",
    "wof:placetype":"venue"
},
  "geometry": {"coordinates":[115.95075988799999,-31.9707374573],"type":"Point"}
}