{
  "type": "Feature",
  "properties": {
    "iso:country":"AU",
    "sg:address":"Old Cleveland Rd East",
    "sg:city":"Birkdale",
    "sg:classifiers":[
        {
            "category":"Arena",
            "subcategory":"Sports Club",
            "type":"Entertainment"
        }
    ],
    "sg:phone":"+61 7 3822 1431",
    "sg:postcode":"4159",
    "sg:province":"QLD",
    "sg:tags":[
        "union",
        "rugby"
    ],
    "wof:name":"Redlands Rugby Union Club",
    "wof:placetype":"venue"
},
  "geometry": {"coordinates":[153.210037231,-27.5053482056],"type":"Point"}
}