{
  "type": "Feature",
  "properties": {
    "iso:country":"AU",
    "sg:address":"29 Smith St",
    "sg:city":"Kempsey",
    "sg:classifiers":[
        {
            "category":"Banks & Credit Unions",
            "subcategory":"Investment Brokerage",
            "type":"Services"
        }
    ],
    "sg:phone":"+61 2 6562 6800",
    "sg:postcode":"2440",
    "sg:province":"NSW",
    "sg:tags":[
        "management",
        "property"
    ],
    "wof:name":"Nationwide Realty Kempsey",
    "wof:placetype":"venue"
},
  "geometry": {"coordinates":[152.84210200000001,-31.079664],"type":"Point"}
}