{
  "type": "Feature",
  "properties": {
    "addr:full":"112 Tongarra Rd Albion Park NSW 2527",
    "addr:housenumber":"112",
    "addr:postcode":"2527",
    "addr:street":"Tongarra Rd",
    "iso:country":"AU",
    "sg:address":"112 Tongarra Rd",
    "sg:city":"Albion Park",
    "sg:classifiers":[
        {
            "category":"Autos & Motor Vehicles",
            "subcategory":"Fuel & Gas Station",
            "type":"Retail Goods"
        }
    ],
    "sg:phone":"+61 2 4256 2046",
    "sg:postcode":"2527",
    "sg:province":"NSW",
    "wof:name":"Harris W G & Sons Pty Ltd",
    "wof:placetype":"venue"
},
  "geometry": {"coordinates":[150.821975708,-34.5708122253],"type":"Point"}
}