{
  "type": "Feature",
  "properties": {
    "iso:country":"AU",
    "sg:address":"145 Archerfield Rd",
    "sg:city":"Richlands",
    "sg:classifiers":[
        {
            "category":"Farming",
            "subcategory":"Farm & Veterinary Services",
            "type":"Manufacturing & Wholesale Goods"
        }
    ],
    "sg:phone":"+61 7 3723 9000",
    "sg:postcode":"4077",
    "sg:province":"QLD",
    "sg:tags":[
        "irrigation",
        "reticulation",
        "system"
    ],
    "wof:name":"RPG-Australia Pipe Division",
    "wof:placetype":"venue"
},
  "geometry": {"coordinates":[152.95622253400001,-27.5796070099],"type":"Point"}
}