{
  "type": "Feature",
  "properties": {
    "addr:full":"115 Hume St Wodonga VIC 3690",
    "addr:housenumber":"115",
    "addr:postcode":"3690",
    "addr:street":"Hume St",
    "iso:country":"AU",
    "sg:address":"115 Hume St",
    "sg:city":"Wodonga",
    "sg:classifiers":[
        {
            "category":"Professional",
            "subcategory":"Employment Agencies",
            "type":"Services"
        }
    ],
    "sg:phone":"+61 1800 631 196",
    "sg:postcode":"3690",
    "sg:province":"VIC",
    "wof:name":"Workways Association Inc. Employment Services",
    "wof:placetype":"venue"
},
  "geometry": {"coordinates":[146.8855896,-36.1239776611],"type":"Point"}
}