{
  "type": "Feature",
  "properties": {
    "addr:full":"6 Island Crs Cowes VIC 3922",
    "addr:housenumber":"6",
    "addr:postcode":"3922",
    "addr:street":"Island Crs",
    "iso:country":"AU",
    "sg:address":"6 Island Crs",
    "sg:city":"Cowes",
    "sg:classifiers":[
        {
            "category":"Food & Beverages",
            "subcategory":"Farmers Market",
            "type":"Retail Goods"
        }
    ],
    "sg:phone":"+61 407 351 247",
    "sg:postcode":"3922",
    "sg:province":"VIC",
    "sg:tags":[
        "beekeeper"
    ],
    "wof:name":"Bass Coast Beekeeping",
    "wof:placetype":"venue"
},
  "geometry": {"coordinates":[145.23898315400001,-38.4565200806],"type":"Point"}
}