{
  "type": "Feature",
  "properties": {
    "iso:country":"AU",
    "sg:address":"3 Jarvis St",
    "sg:city":"O'Connor",
    "sg:classifiers":[
        {
            "category":"Autos & Motor Vehicles",
            "subcategory":"Boat Sales",
            "type":"Retail Goods"
        }
    ],
    "sg:phone":"+61 8 9331 5031",
    "sg:postcode":"6163",
    "sg:province":"WA",
    "sg:tags":[
        "builder",
        "yacht",
        "repairer"
    ],
    "wof:name":"EDON Industries",
    "wof:placetype":"venue"
},
  "geometry": {"coordinates":[115.789543,-32.060387],"type":"Point"}
}