{
  "type": "Feature",
  "properties": {
    "iso:country":"AU",
    "sg:address":"324 Collier Rd",
    "sg:city":"Bassendean",
    "sg:classifiers":[
        {
            "category":"Retail",
            "subcategory":"Auto Rental",
            "type":"Services"
        }
    ],
    "sg:phone":"+61 13 61 39",
    "sg:postcode":"6054",
    "sg:province":"WA",
    "sg:tags":[
        "car",
        "hire",
        "minibus"
    ],
    "sg:website":"http://www.thrifty.com.au/wa",
    "wof:name":"Thrifty 4WD Hire",
    "wof:placetype":"venue"
},
  "geometry": {"coordinates":[115.93296051,-31.9055576324],"type":"Point"}
}