{
  "type": "Feature",
  "properties": {
    "addr:full":"Dacre St Mitchell NSW 2795",
    "addr:postcode":"2795",
    "addr:street":"Dacre St",
    "iso:country":"AU",
    "sg:address":"Dacre St",
    "sg:city":"Mitchell",
    "sg:classifiers":[
        {
            "category":"Retail",
            "subcategory":"Storage",
            "type":"Services"
        }
    ],
    "sg:phone":"+61 2 6242 0092",
    "sg:postcode":"2795",
    "sg:province":"NSW",
    "wof:name":"Capital Self Storage",
    "wof:placetype":"venue"
},
  "geometry": {"coordinates":[149.55674743599999,-33.4224586487],"type":"Point"}
}