{
  "type": "Feature",
  "properties": {
    "addr:full":"30 Fisher St Salisbury SA 5108",
    "addr:housenumber":"30",
    "addr:postcode":"5108",
    "addr:street":"Fisher St",
    "iso:country":"AU",
    "sg:address":"30 Fisher St",
    "sg:city":"Salisbury",
    "sg:classifiers":[
        {
            "category":"Social Services",
            "subcategory":"Adult Care",
            "type":"Services"
        }
    ],
    "sg:phone":"+61 8 8258 2100",
    "sg:postcode":"5108",
    "sg:province":"SA",
    "sg:tags":[
        "towing"
    ],
    "wof:name":"Penfield Auto Wreckers",
    "wof:placetype":"venue"
},
  "geometry": {"coordinates":[138.64610290499999,-34.7524757385],"type":"Point"}
}