{
  "type": "Feature",
  "properties": {
    "addr:full":"4 Taylor Crt South Plympton SA 5038",
    "addr:housenumber":"4",
    "addr:postcode":"5038",
    "addr:street":"Taylor Crt",
    "iso:country":"AU",
    "sg:address":"4 Taylor Crt",
    "sg:city":"South Plympton",
    "sg:classifiers":[
        {
            "category":"Retail",
            "subcategory":"Auto Repair",
            "type":"Services"
        }
    ],
    "sg:phone":"+61 8 8297 1405",
    "sg:postcode":"5038",
    "sg:province":"SA",
    "sg:tags":[
        "sport",
        "motor"
    ],
    "wof:name":"Zip BDH Pty Ltd",
    "wof:placetype":"venue"
},
  "geometry": {"coordinates":[138.56301879899999,-34.9774246216],"type":"Point"}
}