{
  "type": "Feature",
  "properties": {
    "iso:country":"AU",
    "sg:address":"40 Woolshed St",
    "sg:city":"Bordertown",
    "sg:classifiers":[
        {
            "category":"Professional",
            "subcategory":"Accounting & Tax Preparation",
            "type":"Services"
        }
    ],
    "sg:phone":"+61 8 8752 2561",
    "sg:postcode":"5268",
    "sg:province":"SA",
    "sg:tags":[
        "accountant",
        "auditor"
    ],
    "wof:name":"mhm - A Personal Approach To Business",
    "wof:placetype":"venue"
},
  "geometry": {"coordinates":[140.77371199999999,-36.311157],"type":"Point"}
}