{
  "type": "Feature",
  "properties": {
    "addr:full":"160 Strickland Rd Bendigo VIC 3550",
    "addr:housenumber":"160",
    "addr:postcode":"3550",
    "addr:street":"Strickland Rd",
    "iso:country":"AU",
    "sg:address":"160 Strickland Rd",
    "sg:city":"Bendigo",
    "sg:classifiers":[
        {
            "category":"Utilities",
            "type":"Services"
        }
    ],
    "sg:phone":"+61 3 5444 0511",
    "sg:postcode":"3550",
    "sg:province":"VIC",
    "sg:tags":[
        "refrigeration",
        "industrial",
        "commercial",
        "retail"
    ],
    "wof:name":"DPK Mechanical Services",
    "wof:placetype":"venue"
},
  "geometry": {"coordinates":[144.26632690400001,-36.7560119629],"type":"Point"}
}