{
  "type": "Feature",
  "properties": {
    "iso:country":"AU",
    "sg:address":"91 Larnoo Drv",
    "sg:city":"Doncaster East",
    "sg:classifiers":[
        {
            "category":"Building & Trades",
            "subcategory":"Construction",
            "type":"Services"
        }
    ],
    "sg:phone":"+61 3 9842 6636",
    "sg:postcode":"3109",
    "sg:province":"VIC",
    "sg:tags":[
        "contractor"
    ],
    "wof:name":"Newnham L. B. & C. L. Pty Ltd",
    "wof:placetype":"venue"
},
  "geometry": {"coordinates":[145.17460632300001,-37.7587509155],"type":"Point"}
}