{
  "type": "Feature",
  "properties": {
    "iso:country":"AU",
    "sg:address":"44 Newton St",
    "sg:city":"Surrey Hills",
    "sg:classifiers":[
        {
            "category":"Health Services",
            "subcategory":"Health Practitioner",
            "type":"Services"
        }
    ],
    "sg:phone":"+61 3 9899 7908",
    "sg:postcode":"3127",
    "sg:province":"VIC",
    "sg:tags":[
        "physiotherapist"
    ],
    "wof:name":"Jensen Jette",
    "wof:placetype":"venue"
},
  "geometry": {"coordinates":[145.10839843799999,-37.832118988],"type":"Point"}
}