{
  "type": "Feature",
  "properties": {
    "addr:full":"Suite 3, Level 6 93 George St Parramatta NSW 2150",
    "addr:housenumber":"93",
    "addr:postcode":"2150",
    "addr:street":"George St",
    "iso:country":"AU",
    "sg:address":"Suite 3, Level 6 93 George St",
    "sg:city":"Parramatta",
    "sg:classifiers":[
        {
            "category":"Banks & Credit Unions",
            "subcategory":"Financial Services",
            "type":"Services"
        }
    ],
    "sg:phone":"+61 2 9687 0311",
    "sg:postcode":"2150",
    "sg:province":"NSW",
    "sg:tags":[
        "planning"
    ],
    "wof:name":"Tron Financial Planning",
    "wof:placetype":"venue"
},
  "geometry": {"coordinates":[150.9765625,-33.8502388],"type":"Point"}
}