{
  "type": "Feature",
  "properties": {
    "addr:full":"Westfield Shopngtwn Aird St Parramatta NSW 2150",
    "addr:postcode":"2150",
    "addr:street":"Aird St",
    "iso:country":"AU",
    "sg:address":"Westfield Shopngtwn Aird St",
    "sg:city":"Parramatta",
    "sg:classifiers":[
        {
            "category":"Food & Beverages",
            "subcategory":"Supermarket",
            "type":"Retail Goods"
        }
    ],
    "sg:phone":"+61 2 9635 4179",
    "sg:postcode":"2150",
    "sg:province":"NSW",
    "sg:tags":[
        "grocery",
        "store"
    ],
    "wof:name":"Franklins Limited",
    "wof:placetype":"venue"
},
  "geometry": {"coordinates":[151.003509522,-33.8180236816],"type":"Point"}
}