{
  "type": "Feature",
  "properties": {
    "addr:full":"57 Macquarie St Parramatta NSW 2150",
    "addr:housenumber":"57",
    "addr:postcode":"2150",
    "addr:street":"Macquarie St",
    "iso:country":"AU",
    "sg:address":"57 Macquarie St",
    "sg:city":"Parramatta",
    "sg:classifiers":[
        {
            "category":"Personal",
            "subcategory":"Massage",
            "type":"Services"
        }
    ],
    "sg:phone":"+61 2 9635 0909",
    "sg:postcode":"2150",
    "sg:province":"NSW",
    "sg:tags":[
        "therapy"
    ],
    "wof:name":"Dynamic Healing",
    "wof:placetype":"venue"
},
  "geometry": {"coordinates":[150.94125366200001,-33.8706283569],"type":"Point"}
}