{
  "type": "Feature",
  "properties": {
    "addr:full":"3 Walker St Wickliffe VIC 3379",
    "addr:housenumber":"3",
    "addr:postcode":"3379",
    "addr:street":"Walker St",
    "iso:country":"AU",
    "sg:address":"3 Walker St",
    "sg:city":"Wickliffe",
    "sg:classifiers":[
        {
            "category":"Travel",
            "subcategory":"Hotels & Motels",
            "type":"Entertainment"
        }
    ],
    "sg:phone":"+61 3 5350 3209",
    "sg:postcode":"3379",
    "sg:province":"VIC",
    "sg:tags":[
        "accommodation"
    ],
    "wof:name":"Wickliffe Hotel",
    "wof:placetype":"venue"
},
  "geometry": {"coordinates":[142.724884033,-37.6928939819],"type":"Point"}
}