{
  "type": "Feature",
  "properties": {
    "iso:country":"AU",
    "sg:address":"195c The Boulevarde",
    "sg:city":"Fairfield Heights",
    "sg:classifiers":[
        {
            "category":"Real Estate",
            "subcategory":"Real Estate Agent",
            "type":"Services"
        }
    ],
    "sg:phone":"+61 2 9727 6022",
    "sg:postcode":"2165",
    "sg:province":"NSW",
    "sg:website":"http://www.prettirealestate.com.au",
    "wof:name":"Pretti Real Estate",
    "wof:placetype":"venue"
},
  "geometry": {"coordinates":[150.938262939,-33.8647041321],"type":"Point"}
}