{
  "type": "Feature",
  "properties": {
    "addr:full":"Unit 1, 72- 74 Gibbes Ave Chatswood NSW 2057",
    "addr:housenumber":"72 74",
    "addr:postcode":"2057",
    "addr:street":"Gibbes Ave",
    "iso:country":"AU",
    "sg:address":"Unit 1, 72- 74 Gibbes Ave",
    "sg:city":"Chatswood",
    "sg:classifiers":[
        {
            "category":"Home & Garden",
            "subcategory":"Home Furnishings",
            "type":"Retail Goods"
        }
    ],
    "sg:phone":"+61 1800 111 275",
    "sg:postcode":"2057",
    "sg:province":"NSW",
    "sg:tags":[
        "storage",
        "rack",
        "wine"
    ],
    "sg:website":"http://www.wine-ark.com",
    "wof:name":"Wine-Ark",
    "wof:placetype":"venue"
},
  "geometry": {"coordinates":[151.19851700000001,-33.786358],"type":"Point"}
}