{
  "type": "Feature",
  "properties": {
    "iso:country":"AU",
    "sg:address":"173 Woodlands Drv",
    "sg:city":"Wamuran",
    "sg:classifiers":[
        {
            "category":"Professional",
            "subcategory":"Printing & Photocopies",
            "type":"Services"
        }
    ],
    "sg:phone":"+61 7 5496 6747",
    "sg:postcode":"4512",
    "sg:province":"QLD",
    "sg:tags":[
        "screen",
        "printer"
    ],
    "wof:name":"Cowabunga Screenprint",
    "wof:placetype":"venue"
},
  "geometry": {"coordinates":[152.86082500000001,-27.0401],"type":"Point"}
}