{
  "type": "Feature",
  "properties": {
    "iso:country":"AU",
    "sg:address":"Shop 1/ 4 Treelands Drv",
    "sg:city":"Yamba",
    "sg:classifiers":[
        {
            "category":"Communications",
            "subcategory":"Film & Video Production",
            "type":"Services"
        }
    ],
    "sg:phone":"+61 2 6646 2227",
    "sg:postcode":"2464",
    "sg:province":"NSW",
    "sg:tags":[
        "dvd",
        "library"
    ],
    "wof:name":"Civic Video",
    "wof:placetype":"venue"
},
  "geometry": {"coordinates":[153.32720947300001,-29.4283771515],"type":"Point"}
}