{
  "type": "Feature",
  "properties": {
    "iso:country":"AU",
    "sg:address":"1 Mavis St",
    "sg:city":"Revesby",
    "sg:classifiers":[
        {
            "category":"Autos & Motor Vehicles",
            "subcategory":"Auto Supplies",
            "type":"Retail Goods"
        }
    ],
    "sg:phone":"+61 2 9792 1767",
    "sg:postcode":"2212",
    "sg:province":"NSW",
    "sg:tags":[
        "accessory"
    ],
    "wof:name":"Mavis Spares",
    "wof:placetype":"venue"
},
  "geometry": {"coordinates":[151.02087399999999,-33.93716],"type":"Point"}
}