{
  "type": "Feature",
  "properties": {
    "addr:full":"13- 78 Toorak Rd Burwood VIC 3125",
    "addr:housenumber":"78",
    "addr:postcode":"3125",
    "addr:street":"Toorak Rd",
    "iso:country":"AU",
    "sg:address":"13- 78 Toorak Rd",
    "sg:city":"Burwood",
    "sg:classifiers":[
        {
            "category":"Professional",
            "subcategory":"Detective & Security Services",
            "type":"Services"
        }
    ],
    "sg:phone":"+61 417 310 828",
    "sg:postcode":"3125",
    "sg:province":"VIC",
    "sg:tags":[
        "consultant",
        "system"
    ],
    "wof:name":"Joel Sheehan",
    "wof:placetype":"venue"
},
  "geometry": {"coordinates":[145.07374572800001,-37.8480224609],"type":"Point"}
}