{
  "type": "Feature",
  "properties": {
    "addr:full":"50 Mt Dandenong Rd Ringwood East VIC 3135",
    "addr:housenumber":"50",
    "addr:postcode":"3135",
    "addr:street":"Mt Dandenong Rd",
    "iso:country":"AU",
    "sg:address":"50 Mt Dandenong Rd",
    "sg:city":"Ringwood East",
    "sg:classifiers":[
        {
            "category":"Structure",
            "subcategory":"Office Building",
            "type":"Public Place"
        }
    ],
    "sg:phone":"+61 3 9870 1592",
    "sg:postcode":"3135",
    "sg:province":"VIC",
    "sg:tags":[
        "slater",
        "tiler",
        "roof"
    ],
    "wof:name":"Colourtone Roof Restoration",
    "wof:placetype":"venue"
},
  "geometry": {"coordinates":[145.249435425,-37.8089485168],"type":"Point"}
}