{
  "type": "Feature",
  "properties": {
    "addr:full":"16 Horseshoe Crs Epping VIC 3076",
    "addr:housenumber":"16",
    "addr:postcode":"3076",
    "addr:street":"Horseshoe Crs",
    "iso:country":"AU",
    "sg:address":"16 Horseshoe Crs",
    "sg:city":"Epping",
    "sg:classifiers":[
        {
            "category":"Professional",
            "type":"Services"
        }
    ],
    "sg:phone":"+61 419 874 045",
    "sg:postcode":"3076",
    "sg:province":"VIC",
    "sg:tags":[
        "transport"
    ],
    "wof:name":"Tieri Transport Services",
    "wof:placetype":"venue"
},
  "geometry": {"coordinates":[144.837234497,-37.7257575989],"type":"Point"}
}