{
  "type": "Feature",
  "properties": {
    "iso:country":"AU",
    "sg:address":"23 Tiver Rd",
    "sg:city":"Evanston South",
    "sg:classifiers":[
        {
            "category":"Professional",
            "subcategory":"Art Services",
            "type":"Services"
        }
    ],
    "sg:phone":"+61 8 8522 2329",
    "sg:postcode":"5116",
    "sg:province":"SA",
    "sg:tags":[
        "decorator",
        "painter"
    ],
    "wof:name":"Gillard H T",
    "wof:placetype":"venue"
},
  "geometry": {"coordinates":[138.730865478,-34.6430282593],"type":"Point"}
}