{
  "type": "Feature",
  "properties": {
    "iso:country":"AU",
    "sg:address":"PO Box 457",
    "sg:city":"Oxenford",
    "sg:classifiers":[
        {
            "category":"Education",
            "subcategory":"School",
            "type":"Public Place"
        }
    ],
    "sg:phone":"+61 7 5585 9900",
    "sg:postcode":"4210",
    "sg:province":"QLD",
    "sg:tags":[
        "co-educational"
    ],
    "wof:name":"Coomera Anglican College",
    "wof:placetype":"venue"
},
  "geometry": {"coordinates":[153.31413269000001,-27.9020309448],"type":"Point"}
}