{
  "type": "Feature",
  "properties": {
    "iso:country":"AU",
    "sg:address":"161 Musgrave St",
    "sg:city":"Rockhampton",
    "sg:classifiers":[
        {
            "category":"Travel",
            "subcategory":"Hotels & Motels",
            "type":"Entertainment"
        }
    ],
    "sg:phone":"+61 7 4927 3899",
    "sg:postcode":"4700",
    "sg:province":"QLD",
    "wof:name":"Post Office Hotel Motel",
    "wof:placetype":"venue"
},
  "geometry": {"coordinates":[150.52178955100001,-23.3666763306],"type":"Point"}
}