{
  "type": "Feature",
  "properties": {
    "iso:country":"AU",
    "sg:address":"17 Buckley St",
    "sg:city":"Carnegie",
    "sg:classifiers":[
        {
            "category":"Health Services",
            "subcategory":"Health Practitioner",
            "type":"Services"
        }
    ],
    "sg:phone":"+61 3 9572 1358",
    "sg:postcode":"3163",
    "sg:province":"VIC",
    "sg:tags":[
        "psychologist"
    ],
    "wof:name":"Walker Lyndon",
    "wof:placetype":"venue"
},
  "geometry": {"coordinates":[145.052078247,-37.8863601685],"type":"Point"}
}