{
  "type": "Feature",
  "properties": {
    "iso:country":"AU",
    "sg:address":"Maroubra St",
    "sg:city":"Maroochydore",
    "sg:classifiers":[
        {
            "category":"Health Services",
            "subcategory":"Health Practitioner",
            "type":"Services"
        }
    ],
    "sg:phone":"+61 7 5443 2219",
    "sg:postcode":"4558",
    "sg:province":"QLD",
    "sg:tags":[
        "acupuncture"
    ],
    "wof:name":"Diane Cheal Acupuncture",
    "wof:placetype":"venue"
},
  "geometry": {"coordinates":[153.10122680699999,-26.6629314423],"type":"Point"}
}