{
  "type": "Feature",
  "properties": {
    "addr:full":"36 Don St Bowen QLD 4805",
    "addr:housenumber":"36",
    "addr:postcode":"4805",
    "addr:street":"Don St",
    "iso:country":"AU",
    "sg:address":"36 Don St",
    "sg:city":"Bowen",
    "sg:classifiers":[
        {
            "category":"Retail",
            "subcategory":"Veterinary Services",
            "type":"Services"
        }
    ],
    "sg:phone":"+61 7 4786 3166",
    "sg:postcode":"4805",
    "sg:province":"QLD",
    "sg:tags":[
        "surgeon"
    ],
    "wof:name":"Brolgas Rest Vet Clinic",
    "wof:placetype":"venue"
},
  "geometry": {"coordinates":[148.23060607900001,-20.0093727112],"type":"Point"}
}