{
  "type": "Feature",
  "properties": {
    "addr:full":"17a Wheeler St Belmont WA 6104",
    "addr:housenumber":"17a",
    "addr:postcode":"6104",
    "addr:street":"Wheeler St",
    "iso:country":"AU",
    "sg:address":"17a Wheeler St",
    "sg:city":"Belmont",
    "sg:classifiers":[
        {
            "category":"Wholesale",
            "subcategory":"Medical Equipment & Supplies",
            "type":"Manufacturing & Wholesale Goods"
        }
    ],
    "sg:phone":"+61 8 9479 3244",
    "sg:postcode":"6104",
    "sg:province":"WA",
    "sg:tags":[
        "dental"
    ],
    "wof:name":"West Coast Dental Depot",
    "wof:placetype":"venue"
},
  "geometry": {"coordinates":[115.92401886,-31.9498386383],"type":"Point"}
}