{
  "type": "Feature",
  "properties": {
    "iso:country":"AU",
    "sg:address":"252 Marri Park Drv",
    "sg:city":"Casuarina",
    "sg:classifiers":[
        {
            "category":"Health Services",
            "subcategory":"Doctor",
            "type":"Services"
        }
    ],
    "sg:phone":"+61 419 937 201",
    "sg:postcode":"6167",
    "sg:province":"WA",
    "sg:tags":[
        "occupational",
        "safety"
    ],
    "wof:name":"JSA Programs",
    "wof:placetype":"venue"
},
  "geometry": {"coordinates":[115.877167,-32.230507],"type":"Point"}
}