{
  "type": "Feature",
  "properties": {
    "addr:full":"22 Homestead Rd Wonga Park VIC 3115",
    "addr:housenumber":"22",
    "addr:postcode":"3115",
    "addr:street":"Homestead Rd",
    "iso:country":"AU",
    "sg:address":"22 Homestead Rd",
    "sg:city":"Wonga Park",
    "sg:classifiers":[
        {
            "category":"Building & Trades",
            "subcategory":"Construction",
            "type":"Services"
        }
    ],
    "sg:phone":"+61 3 9722 2172",
    "sg:postcode":"3115",
    "sg:province":"VIC",
    "sg:tags":[
        "contractor"
    ],
    "wof:name":"Hartley Building Services",
    "wof:placetype":"venue"
},
  "geometry": {"coordinates":[145.277877808,-37.7425422668],"type":"Point"}
}