{
  "type": "Feature",
  "properties": {
    "addr:full":"Glover St Strath Creek VIC 3658",
    "addr:postcode":"3658",
    "addr:street":"Glover St",
    "iso:country":"AU",
    "sg:address":"Glover St",
    "sg:city":"Strath Creek",
    "sg:classifiers":[
        {
            "category":"Government",
            "subcategory":"Post Office",
            "type":"Public Place"
        }
    ],
    "sg:phone":"+61 3 5784 9220",
    "sg:postcode":"3658",
    "sg:province":"VIC",
    "sg:tags":[
        "postal"
    ],
    "wof:name":"Australia Post",
    "wof:placetype":"venue"
},
  "geometry": {"coordinates":[145.21817016599999,-37.2373390198],"type":"Point"}
}