{
  "type": "Feature",
  "properties": {
    "addr:full":"Townsville Rd Bambaroo QLD 4850",
    "addr:postcode":"4850",
    "addr:street":"Townsville Rd",
    "iso:country":"AU",
    "sg:address":"Townsville Rd",
    "sg:city":"Bambaroo",
    "sg:classifiers":[
        {
            "category":"Farming",
            "subcategory":"Farm",
            "type":"Manufacturing & Wholesale Goods"
        }
    ],
    "sg:phone":"+61 7 4777 3133",
    "sg:postcode":"4850",
    "sg:province":"QLD",
    "sg:tags":[
        "farmer"
    ],
    "wof:name":"Barbagallo S & G",
    "wof:placetype":"venue"
},
  "geometry": {"coordinates":[146.14891052199999,-18.7068977356],"type":"Point"}
}