{
  "type": "Feature",
  "properties": {
    "addr:full":"Victorian Police 28 Ivanhoe Pde Ivanhoe VIC 3079",
    "addr:housenumber":"28",
    "addr:postcode":"3079",
    "addr:street":"Ivanhoe Pde",
    "iso:country":"AU",
    "sg:address":"Victorian Police 28 Ivanhoe Pde",
    "sg:city":"Ivanhoe",
    "sg:classifiers":[
        {
            "category":"Professional",
            "subcategory":"Detective & Security Services",
            "type":"Services"
        }
    ],
    "sg:phone":"+61 3 9499 8965",
    "sg:postcode":"3079",
    "sg:province":"VIC",
    "sg:tags":[
        "consultant",
        "system"
    ],
    "wof:name":"Crime Prevention Office",
    "wof:placetype":"venue"
},
  "geometry": {"coordinates":[145.04432678200001,-37.7655601501],"type":"Point"}
}