{
  "type": "Feature",
  "properties": {
    "addr:full":"181 River St Maclean NSW 2463",
    "addr:housenumber":"181",
    "addr:postcode":"2463",
    "addr:street":"River St",
    "iso:country":"AU",
    "sg:address":"181 River St",
    "sg:city":"Maclean",
    "sg:classifiers":[
        {
            "category":"Home & Garden",
            "subcategory":"Carpets & Floor Coverings",
            "type":"Retail Goods"
        }
    ],
    "sg:phone":"+61 2 6645 2671",
    "sg:postcode":"2463",
    "sg:province":"NSW",
    "wof:name":"Coulters Carpet Court",
    "wof:placetype":"venue"
},
  "geometry": {"coordinates":[153.19741821299999,-29.4541873932],"type":"Point"}
}