{
  "type": "Feature",
  "properties": {
    "iso:country":"AU",
    "sg:address":"Masons Pde",
    "sg:city":"Gosford",
    "sg:classifiers":[
        {
            "category":"Retail",
            "subcategory":"Event Space",
            "type":"Services"
        }
    ],
    "sg:phone":"+61 2 4325 0644",
    "sg:postcode":"2250",
    "sg:province":"NSW",
    "sg:tags":[
        "function",
        "organiser"
    ],
    "wof:name":"Gosford Shoreline Restaurant",
    "wof:placetype":"venue"
},
  "geometry": {"coordinates":[151.34277343799999,-33.4331550598],"type":"Point"}
}