{
  "type": "Feature",
  "properties": {
    "addr:full":"Black Hill Rd Black Hill NSW 2322",
    "addr:postcode":"2322",
    "addr:street":"Black Hill Rd",
    "iso:country":"AU",
    "sg:address":"Black Hill Rd",
    "sg:city":"Black Hill",
    "sg:classifiers":[
        {
            "category":"Education",
            "subcategory":"School",
            "type":"Public Place"
        }
    ],
    "sg:phone":"+61 2 4930 3137",
    "sg:postcode":"2322",
    "sg:province":"NSW",
    "sg:tags":[
        "state",
        "-",
        "nsw"
    ],
    "wof:name":"Black Hill Public School",
    "wof:placetype":"venue"
},
  "geometry": {"coordinates":[151.58943176299999,-32.833770752],"type":"Point"}
}