{
  "type": "Feature",
  "properties": {
    "iso:country":"AU",
    "sg:address":"51 Trade Pl",
    "sg:city":"Coburg",
    "sg:classifiers":[
        {
            "category":"Manufacturing",
            "subcategory":"Glass & Minerals",
            "type":"Manufacturing & Wholesale Goods"
        }
    ],
    "sg:phone":"+61 3 9350 5074",
    "sg:postcode":"3058",
    "sg:province":"VIC",
    "sg:tags":[
        "merchant",
        "granite",
        "marble"
    ],
    "wof:name":"Australia Marble House",
    "wof:placetype":"venue"
},
  "geometry": {"coordinates":[144.96995544399999,-37.7243041992],"type":"Point"}
}