{
  "type": "Feature",
  "properties": {
    "addr:full":"10 Anthony Drv Rowville VIC 3178",
    "addr:housenumber":"10",
    "addr:postcode":"3178",
    "addr:street":"Anthony Drv",
    "iso:country":"AU",
    "sg:address":"10 Anthony Drv",
    "sg:city":"Rowville",
    "sg:classifiers":[
        {
            "category":"Building & Trades",
            "subcategory":"Landscaping Services",
            "type":"Services"
        }
    ],
    "sg:phone":"+61 412 798 752",
    "sg:postcode":"3178",
    "sg:province":"VIC",
    "sg:tags":[
        "designer",
        "landscape",
        "contractor"
    ],
    "wof:name":"Mark Robertson Landscaping",
    "wof:placetype":"venue"
},
  "geometry": {"coordinates":[145.27227783199999,-37.9202308655],"type":"Point"}
}