{
  "type": "Feature",
  "properties": {
    "iso:country":"AU",
    "sg:address":"PO Box 616",
    "sg:city":"Duncraig",
    "sg:classifiers":[
        {
            "category":"Shopping",
            "subcategory":"Party Supplies",
            "type":"Retail Goods"
        }
    ],
    "sg:phone":"+61 8 9246 1704",
    "sg:postcode":"6023",
    "sg:province":"WA",
    "wof:name":"Chocolate Attraction",
    "wof:placetype":"venue"
},
  "geometry": {"coordinates":[115.778648377,-31.8311500549],"type":"Point"}
}