{
  "type": "Feature",
  "properties": {
    "addr:full":"10- 12 Robert St Wickham NSW 2293",
    "addr:housenumber":"12",
    "addr:postcode":"2293",
    "addr:street":"Robert St",
    "iso:country":"AU",
    "sg:address":"10- 12 Robert St",
    "sg:city":"Wickham",
    "sg:classifiers":[
        {
            "category":"Home & Garden",
            "subcategory":"Household Appliances",
            "type":"Retail Goods"
        }
    ],
    "sg:phone":"+61 2 4962 3622",
    "sg:postcode":"2293",
    "sg:province":"NSW",
    "sg:tags":[
        "chemical",
        "equipment",
        "steam",
        "cleaning",
        "pressure"
    ],
    "sg:website":"http://www.assetcleaning.com",
    "wof:name":"Asset Cleaning Supplies",
    "wof:placetype":"venue"
},
  "geometry": {"coordinates":[151.75770568900001,-32.9174880981],"type":"Point"}
}