{
  "type": "Feature",
  "properties": {
    "addr:full":"17 Esmond St Emerald QLD 4720",
    "addr:housenumber":"17",
    "addr:postcode":"4720",
    "addr:street":"Esmond St",
    "iso:country":"AU",
    "sg:address":"17 Esmond St",
    "sg:city":"Emerald",
    "sg:classifiers":[
        {
            "category":"Restaurant",
            "type":"Food & Drink"
        }
    ],
    "sg:phone":"+61 7 4982 1113",
    "sg:postcode":"4720",
    "sg:province":"QLD",
    "wof:name":"Capricornian Restaurant",
    "wof:placetype":"venue"
},
  "geometry": {"coordinates":[148.15815699999999,-23.517183],"type":"Point"}
}