{
  "type": "Feature",
  "properties": {
    "iso:country":"AU",
    "sg:address":"9 Catamaran Rd",
    "sg:city":"Berkeley Vale",
    "sg:classifiers":[
        {
            "category":"Fast Food",
            "type":"Food & Drink"
        }
    ],
    "sg:phone":"+61 2 4389 2333",
    "sg:postcode":"2261",
    "sg:province":"NSW",
    "sg:tags":[
        "away",
        "take"
    ],
    "wof:name":"Food Factory",
    "wof:placetype":"venue"
},
  "geometry": {"coordinates":[151.40438800000001,-33.334587],"type":"Point"}
}