{
  "type": "Feature",
  "properties": {
    "addr:full":"72 Ferrier St Lockhart NSW 2656",
    "addr:housenumber":"72",
    "addr:postcode":"2656",
    "addr:street":"Ferrier St",
    "iso:country":"AU",
    "sg:address":"72 Ferrier St",
    "sg:city":"Lockhart",
    "sg:classifiers":[
        {
            "category":"Building & Trades",
            "subcategory":"Plumbing",
            "type":"Services"
        }
    ],
    "sg:phone":"+61 427 205 496",
    "sg:postcode":"2656",
    "sg:province":"NSW",
    "sg:tags":[
        "repair",
        "appliance",
        "system",
        "heating"
    ],
    "wof:name":"Graham Cox",
    "wof:placetype":"venue"
},
  "geometry": {"coordinates":[146.717453003,-35.2200698853],"type":"Point"}
}