{
  "type": "Feature",
  "properties": {
    "iso:country":"AU",
    "sg:address":"9 Vincent St (Nth)",
    "sg:city":"Daylesford",
    "sg:classifiers":[
        {
            "category":"Mining & Drilling",
            "type":"Manufacturing & Wholesale Goods"
        }
    ],
    "sg:phone":"+61 3 5348 2639",
    "sg:postcode":"3460",
    "sg:province":"VIC",
    "sg:tags":[
        "boring",
        "contractor"
    ],
    "wof:name":"G & S Rixon",
    "wof:placetype":"venue"
},
  "geometry": {"coordinates":[144.14299011200001,-37.340877533],"type":"Point"}
}