{
  "type": "Feature",
  "properties": {
    "iso:country":"AU",
    "sg:address":"U5/ 13 Larkin St",
    "sg:city":"Riverwood",
    "sg:classifiers":[
        {
            "category":"Professional",
            "subcategory":"Engineering",
            "type":"Services"
        }
    ],
    "sg:phone":"+61 2 9534 8997",
    "sg:postcode":"2210",
    "sg:province":"NSW",
    "sg:tags":[
        "engineer"
    ],
    "wof:name":"Innorael Pty Ltd",
    "wof:placetype":"venue"
},
  "geometry": {"coordinates":[151.061066,-33.941319],"type":"Point"}
}