{
  "type": "Feature",
  "properties": {
    "iso:country":"AU",
    "sg:address":"836 Boundary Rd",
    "sg:city":"Coopers Plains",
    "sg:classifiers":[
        {
            "category":"Wholesale",
            "subcategory":"Auto Parts",
            "type":"Manufacturing & Wholesale Goods"
        }
    ],
    "sg:phone":"+61 7 3722 0111",
    "sg:postcode":"4108",
    "sg:province":"QLD",
    "sg:tags":[
        "tyre"
    ],
    "wof:name":"Kumho Tyre Aust Pty Ltd",
    "wof:placetype":"venue"
},
  "geometry": {"coordinates":[153.03007507300001,-27.569103241],"type":"Point"}
}