{
  "type": "Feature",
  "properties": {
    "iso:country":"AU",
    "sg:address":"57 Breese St",
    "sg:city":"Brunswick",
    "sg:classifiers":[
        {
            "category":"Retail",
            "subcategory":"Auto Repair",
            "type":"Services"
        }
    ],
    "sg:phone":"+61 3 9386 6884",
    "sg:postcode":"3056",
    "sg:province":"VIC",
    "sg:tags":[
        "repairer",
        "motor",
        "engineer"
    ],
    "wof:name":"Australian's L.P.G. Service Centres",
    "wof:placetype":"venue"
},
  "geometry": {"coordinates":[144.961624145,-37.7609825134],"type":"Point"}
}