{
  "type": "Feature",
  "properties": {
    "addr:full":"Pyrenees Hwy Avoca VIC 3467",
    "addr:postcode":"3467",
    "addr:street":"Pyrenees Hwy",
    "iso:country":"AU",
    "sg:address":"Pyrenees Hwy",
    "sg:city":"Avoca",
    "sg:classifiers":[
        {
            "category":"Utilities",
            "subcategory":"Electric",
            "type":"Services"
        }
    ],
    "sg:phone":"+61 3 5465 3755",
    "sg:postcode":"3467",
    "sg:province":"VIC",
    "sg:tags":[
        "electrical",
        "contractor"
    ],
    "wof:name":"Bernie Turner",
    "wof:placetype":"venue"
},
  "geometry": {"coordinates":[143.472091675,-37.0901603699],"type":"Point"}
}