{
  "type": "Feature",
  "properties": {
    "addr:full":"31 Endeavour Drv Avoca Beach NSW 2251",
    "addr:housenumber":"31",
    "addr:postcode":"2251",
    "addr:street":"Endeavour Drv",
    "iso:country":"AU",
    "sg:address":"31 Endeavour Drv",
    "sg:city":"Avoca Beach",
    "sg:classifiers":[
        {
            "category":"Building & Trades",
            "subcategory":"Construction",
            "type":"Services"
        }
    ],
    "sg:phone":"+61 2 4382 1731",
    "sg:postcode":"2251",
    "sg:province":"NSW",
    "sg:tags":[
        "contractor"
    ],
    "wof:name":"Avoca Beach Building Pty Ltd",
    "wof:placetype":"venue"
},
  "geometry": {"coordinates":[151.43942260700001,-33.4759635925],"type":"Point"}
}