{
  "type": "Feature",
  "properties": {
    "addr:full":"16 Irving Rd Aldinga Beach SA 5173",
    "addr:housenumber":"16",
    "addr:postcode":"5173",
    "addr:street":"Irving Rd",
    "iso:country":"AU",
    "sg:address":"16 Irving Rd",
    "sg:city":"Aldinga Beach",
    "sg:classifiers":[
        {
            "category":"Building & Trades",
            "subcategory":"Equipment Rental",
            "type":"Services"
        }
    ],
    "sg:phone":"+61 8 8557 7348",
    "sg:postcode":"5173",
    "sg:province":"SA",
    "sg:tags":[
        "saw"
    ],
    "wof:name":"Statewide Saw Sharpening Service",
    "wof:placetype":"venue"
},
  "geometry": {"coordinates":[138.452835083,-35.2753143311],"type":"Point"}
}