{
  "type": "Feature",
  "properties": {
    "iso:country":"AU",
    "sg:address":"Albermarle Ave",
    "sg:city":"Rose Bay",
    "sg:classifiers":[
        {
            "category":"Social Services",
            "subcategory":"Child Care",
            "type":"Services"
        }
    ],
    "sg:phone":"+61 2 9371 5892",
    "sg:postcode":"2029",
    "sg:province":"NSW",
    "wof:name":"Rose Bay Out Of School Care Centre",
    "wof:placetype":"venue"
},
  "geometry": {"coordinates":[151.27037048299999,-33.8731040955],"type":"Point"}
}