{
  "type": "Feature",
  "properties": {
    "addr:full":"37 Carr St Waverton NSW 2060",
    "addr:housenumber":"37",
    "addr:postcode":"2060",
    "addr:street":"Carr St",
    "iso:country":"AU",
    "sg:address":"37 Carr St",
    "sg:city":"Waverton",
    "sg:classifiers":[
        {
            "category":"Professional",
            "subcategory":"Art Services",
            "type":"Services"
        }
    ],
    "sg:phone":"+61 2 9460 2727",
    "sg:postcode":"2060",
    "sg:province":"NSW",
    "sg:tags":[
        "graphic",
        "designer"
    ],
    "wof:name":"RBD",
    "wof:placetype":"venue"
},
  "geometry": {"coordinates":[151.19918823200001,-33.8371200562],"type":"Point"}
}