{
  "type": "Feature",
  "properties": {
    "addr:full":"427 Peel St Tamworth NSW 2340",
    "addr:housenumber":"427",
    "addr:postcode":"2340",
    "addr:street":"Peel St",
    "iso:country":"AU",
    "sg:address":"427 Peel St",
    "sg:city":"Tamworth",
    "sg:classifiers":[
        {
            "category":"Banks & Credit Unions",
            "subcategory":"Financial Services",
            "type":"Services"
        }
    ],
    "sg:phone":"+61 2 6766 6550",
    "sg:postcode":"2340",
    "sg:province":"NSW",
    "sg:tags":[
        "planning"
    ],
    "wof:name":"Winchcombe Carson Financial Planning Pty Ltd",
    "wof:placetype":"venue"
},
  "geometry": {"coordinates":[150.931243897,-31.0923290253],"type":"Point"}
}