{
  "type": "Feature",
  "properties": {
    "addr:full":"Shop 4 243- 254 Anzac Pde Kingsford NSW 2032",
    "addr:housenumber":"shop 4;254",
    "addr:postcode":"243;2032",
    "addr:street":"Anzac Pde",
    "iso:country":"AU",
    "sg:address":"Shop 4 243- 254 Anzac Pde",
    "sg:city":"Kingsford",
    "sg:classifiers":[
        {
            "category":"Shopping",
            "subcategory":"Computers & Home Electronics",
            "type":"Retail Goods"
        }
    ],
    "sg:phone":"+61 2 9663 5911",
    "sg:postcode":"2032",
    "sg:province":"NSW",
    "sg:tags":[
        "hardware",
        "equipment"
    ],
    "wof:name":"Electronic Warehouse Kingsford Pty Ltd",
    "wof:placetype":"venue"
},
  "geometry": {"coordinates":[151.226364136,-33.9199104309],"type":"Point"}
}