{
  "type": "Feature",
  "properties": {
    "addr:full":"222 Hartley St Cairns QLD 4870",
    "addr:housenumber":"222",
    "addr:postcode":"4870",
    "addr:street":"Hartley St",
    "iso:country":"AU",
    "sg:address":"222 Hartley St",
    "sg:city":"Cairns",
    "sg:classifiers":[
        {
            "category":"Shopping",
            "subcategory":"Stationery & Office Supplies",
            "type":"Retail Goods"
        }
    ],
    "sg:phone":"+61 7 4035 5100",
    "sg:postcode":"4870",
    "sg:province":"QLD",
    "sg:tags":[
        "equipment",
        "badge",
        "making"
    ],
    "wof:name":"Kehoes Trophies",
    "wof:placetype":"venue"
},
  "geometry": {"coordinates":[145.753982544,-16.9452896118],"type":"Point"}
}