{
  "type": "Feature",
  "properties": {
    "iso:country":"AU",
    "sg:address":"504b LWR Nth East Rd",
    "sg:city":"Campbelltown",
    "sg:classifiers":[
        {
            "category":"Home & Garden",
            "subcategory":"Hardware",
            "type":"Retail Goods"
        }
    ],
    "sg:phone":"+61 8 8337 4590",
    "sg:postcode":"5074",
    "sg:province":"SA",
    "sg:tags":[
        "repair",
        "tool",
        "power"
    ],
    "wof:name":"Battery Co. The",
    "wof:placetype":"venue"
},
  "geometry": {"coordinates":[138.661712647,-34.8808822632],"type":"Point"}
}