{
  "type": "Feature",
  "properties": {
    "iso:country":"AU",
    "sg:address":"15 Clare St",
    "sg:city":"Bayswater",
    "sg:classifiers":[
        {
            "category":"Manufacturing",
            "subcategory":"Tools & Machinery",
            "type":"Manufacturing & Wholesale Goods"
        }
    ],
    "sg:phone":"+61 3 9720 3399",
    "sg:postcode":"3153",
    "sg:province":"VIC",
    "sg:tags":[
        "equipment",
        "scale",
        "weighing"
    ],
    "wof:name":"Detection Systems",
    "wof:placetype":"venue"
},
  "geometry": {"coordinates":[145.28175354000001,-37.8439064026],"type":"Point"}
}