{
  "type": "Feature",
  "properties": {
    "addr:full":"138 Stradbroke Rd Rostrevor SA 5073",
    "addr:housenumber":"138",
    "addr:postcode":"5073",
    "addr:street":"Stradbroke Rd",
    "iso:country":"AU",
    "sg:address":"138 Stradbroke Rd",
    "sg:city":"Rostrevor",
    "sg:classifiers":[
        {
            "category":"Building & Trades",
            "subcategory":"Cleaning & Sanitation",
            "type":"Services"
        }
    ],
    "sg:phone":"+61 8 8365 5026",
    "sg:postcode":"5073",
    "sg:province":"SA",
    "sg:tags":[
        "industrial",
        "commercial",
        "contractor"
    ],
    "wof:name":"Quattro 4 Property Services SA Pty Ltd",
    "wof:placetype":"venue"
},
  "geometry": {"coordinates":[138.69215393100001,-34.8910560608],"type":"Point"}
}