{
  "type": "Feature",
  "properties": {
    "addr:full":"86 Hopkins St Footscray VIC 3011",
    "addr:housenumber":"86",
    "addr:postcode":"3011",
    "addr:street":"Hopkins St",
    "iso:country":"AU",
    "sg:address":"86 Hopkins St",
    "sg:city":"Footscray",
    "sg:classifiers":[
        {
            "category":"Food & Beverages",
            "subcategory":"Supermarket",
            "type":"Retail Goods"
        }
    ],
    "sg:phone":"+61 3 9687 7277",
    "sg:postcode":"3011",
    "sg:province":"VIC",
    "sg:tags":[
        "grocery",
        "store"
    ],
    "wof:name":"Thanh Phat Supermarket",
    "wof:placetype":"venue"
},
  "geometry": {"coordinates":[144.90252685600001,-37.7999534607],"type":"Point"}
}