{
  "type": "Feature",
  "properties": {
    "addr:full":"5/ 29 Logan River Rd Beenleigh QLD 4207",
    "addr:housenumber":"/ 29",
    "addr:postcode":"4207",
    "addr:street":"Logan River Rd",
    "iso:country":"AU",
    "sg:address":"5/ 29 Logan River Rd",
    "sg:city":"Beenleigh",
    "sg:classifiers":[
        {
            "category":"Organizations",
            "subcategory":"Non-profit Organization",
            "type":"Services"
        }
    ],
    "sg:phone":"+61 7 3807 8333",
    "sg:postcode":"4207",
    "sg:province":"QLD",
    "sg:tags":[
        "support",
        "disability",
        "organisation"
    ],
    "wof:name":"Job Placement Limited",
    "wof:placetype":"venue"
},
  "geometry": {"coordinates":[153.190063477,-27.7141971588],"type":"Point"}
}