{
  "type": "Feature",
  "properties": {
    "iso:country":"AU",
    "sg:address":"6 Production Rd",
    "sg:city":"Melton",
    "sg:classifiers":[
        {
            "category":"Retail",
            "subcategory":"Storage",
            "type":"Services"
        }
    ],
    "sg:phone":"+61 3 9746 7350",
    "sg:postcode":"3337",
    "sg:province":"VIC",
    "wof:name":"Melton Mini Storage",
    "wof:placetype":"venue"
},
  "geometry": {"coordinates":[144.598907,-37.6912],"type":"Point"}
}