{
  "type": "Feature",
  "properties": {
    "addr:full":"5- 7 King William Rd Unley SA 5061",
    "addr:housenumber":"7",
    "addr:postcode":"5061",
    "addr:street":"King William Rd",
    "iso:country":"AU",
    "sg:address":"5- 7 King William Rd",
    "sg:city":"Unley",
    "sg:classifiers":[
        {
            "category":"Farming",
            "subcategory":"Vineyard",
            "type":"Manufacturing & Wholesale Goods"
        }
    ],
    "sg:phone":"+61 8 8208 4000",
    "sg:postcode":"5061",
    "sg:province":"SA",
    "sg:tags":[
        "winery"
    ],
    "wof:name":"Food & Beverage Australia Limited",
    "wof:placetype":"venue"
},
  "geometry": {"coordinates":[138.600372314,-34.9422073364],"type":"Point"}
}