{
  "type": "Feature",
  "properties": {
    "iso:country":"AU",
    "sg:address":"12 Barina St",
    "sg:city":"Cannon Hill",
    "sg:classifiers":[
        {
            "category":"Wholesale",
            "subcategory":"Machinery & Supplies",
            "type":"Manufacturing & Wholesale Goods"
        }
    ],
    "sg:phone":"+61 7 3899 4323",
    "sg:postcode":"4170",
    "sg:province":"QLD",
    "sg:tags":[
        "equipment",
        "hydraulic"
    ],
    "wof:name":"Hydraulic Diesel Marine",
    "wof:placetype":"venue"
},
  "geometry": {"coordinates":[153.08506774899999,-27.4668865204],"type":"Point"}
}