{
  "type": "Feature",
  "properties": {
    "addr:full":"113 Coonawarra Rd Winnellie NT 0820",
    "addr:housenumber":"113",
    "addr:postcode":"nt 0820",
    "addr:street":"Coonawarra Rd",
    "iso:country":"AU",
    "sg:address":"113 Coonawarra Rd",
    "sg:city":"Winnellie",
    "sg:classifiers":[
        {
            "category":"Manufacturing",
            "subcategory":"Motor Vehicles & Parts",
            "type":"Manufacturing & Wholesale Goods"
        }
    ],
    "sg:phone":"+61 8 8947 0623",
    "sg:postcode":"0820",
    "sg:province":"NT",
    "sg:tags":[
        "replacement"
    ],
    "wof:name":"Japanese Auto Mart (N.T.)",
    "wof:placetype":"venue"
},
  "geometry": {"coordinates":[130.88633727999999,-12.4302988052],"type":"Point"}
}