{
  "type": "Feature",
  "properties": {
    "iso:country":"AU",
    "sg:address":"116 Terrace Rd",
    "sg:city":"Guildford",
    "sg:classifiers":[
        {
            "category":"Shopping",
            "subcategory":"Antiques",
            "type":"Retail Goods"
        }
    ],
    "sg:phone":"+61 8 9379 1234",
    "sg:postcode":"6055",
    "sg:province":"WA",
    "sg:tags":[
        "restoration",
        "reproduction"
    ],
    "wof:name":"Classic Yesterdays",
    "wof:placetype":"venue"
},
  "geometry": {"coordinates":[115.974052,-31.8969],"type":"Point"}
}