{
  "type": "Feature",
  "properties": {
    "addr:full":"43 Campbell Ave Anna Bay NSW 2316",
    "addr:housenumber":"43",
    "addr:postcode":"2316",
    "addr:street":"Campbell Ave Anna Bay",
    "iso:country":"AU",
    "sg:address":"43 Campbell Ave",
    "sg:city":"Anna Bay",
    "sg:classifiers":[
        {
            "category":"Personal",
            "subcategory":"Massage",
            "type":"Services"
        }
    ],
    "sg:phone":"+61 2 4982 1033",
    "sg:postcode":"2316",
    "sg:province":"NSW",
    "sg:tags":[
        "therapy"
    ],
    "wof:name":"Squires Amanda",
    "wof:placetype":"venue"
},
  "geometry": {"coordinates":[152.08296200000001,-32.780811],"type":"Point"}
}