{
  "type": "Feature",
  "properties": {
    "iso:country":"AU",
    "sg:address":"8 Coates Pl",
    "sg:city":"Wetherill Park",
    "sg:classifiers":[
        {
            "category":"Shopping",
            "subcategory":"Crafts & Fabrics",
            "type":"Retail Goods"
        }
    ],
    "sg:phone":"+61 2 9757 2222",
    "sg:postcode":"2164",
    "sg:province":"NSW",
    "sg:tags":[
        "merchant",
        "cork"
    ],
    "wof:name":"Australian Glass & Cork Products Pty Ltd",
    "wof:placetype":"venue"
},
  "geometry": {"coordinates":[150.88511657699999,-33.84034729],"type":"Point"}
}