{
  "type": "Feature",
  "properties": {
    "iso:country":"AU",
    "sg:address":"7 Northumberland Ave",
    "sg:city":"Stanmore",
    "sg:classifiers":[
        {
            "category":"Health Services",
            "subcategory":"Health Practitioner",
            "type":"Services"
        }
    ],
    "sg:phone":"+61 2 9565 2291",
    "sg:postcode":"2048",
    "sg:province":"NSW",
    "sg:tags":[
        "osteopath"
    ],
    "wof:name":"Newtown Osteopathic Medicine Centre",
    "wof:placetype":"venue"
},
  "geometry": {"coordinates":[151.167908,-33.888599],"type":"Point"}
}