{
  "type": "Feature",
  "properties": {
    "addr:full":"139 Oxford St Leederville WA 6007",
    "addr:housenumber":"139",
    "addr:postcode":"6007",
    "addr:street":"Oxford St",
    "iso:country":"AU",
    "sg:address":"139 Oxford St",
    "sg:city":"Leederville",
    "sg:classifiers":[
        {
            "category":"Farming",
            "subcategory":"Farm & Veterinary Services",
            "type":"Manufacturing & Wholesale Goods"
        }
    ],
    "sg:phone":"+61 412 602 583",
    "sg:postcode":"6007",
    "sg:province":"WA",
    "sg:tags":[
        "poultry",
        "processing",
        "supply"
    ],
    "wof:name":"Farmgate Poultry & Meats",
    "wof:placetype":"venue"
},
  "geometry": {"coordinates":[115.841072083,-31.9368057251],"type":"Point"}
}