{
  "type": "Feature",
  "properties": {
    "addr:full":"181 Military Rd Neutral Bay NSW 2089",
    "addr:housenumber":"181",
    "addr:postcode":"2089",
    "addr:street":"Military Rd",
    "iso:country":"AU",
    "sg:address":"181 Military Rd",
    "sg:city":"Neutral Bay",
    "sg:classifiers":[
        {
            "category":"Shopping",
            "subcategory":"Shoes",
            "type":"Retail Goods"
        }
    ],
    "sg:phone":"+61 2 9904 2868",
    "sg:postcode":"2089",
    "sg:province":"NSW",
    "sg:tags":[
        "footwear"
    ],
    "wof:name":"Enrico Santi",
    "wof:placetype":"venue"
},
  "geometry": {"coordinates":[151.22271728499999,-33.8316802979],"type":"Point"}
}