{
  "type": "Feature",
  "properties": {
    "addr:full":"114 Victoria St Victor Harbor SA 5211",
    "addr:housenumber":"114",
    "addr:postcode":"5211",
    "addr:street":"Victoria St",
    "iso:country":"AU",
    "sg:address":"114 Victoria St",
    "sg:city":"Victor Harbor",
    "sg:classifiers":[
        {
            "category":"Communications",
            "subcategory":"News Services",
            "type":"Services"
        }
    ],
    "sg:phone":"+61 8 8552 1111",
    "sg:postcode":"5211",
    "sg:province":"SA",
    "sg:tags":[
        "information",
        "tourist",
        "attractions"
    ],
    "wof:name":"Victor Harbor Beach Front Holiday Park",
    "wof:placetype":"venue"
},
  "geometry": {"coordinates":[138.61378479000001,-35.5581207275],"type":"Point"}
}