{
  "type": "Feature",
  "properties": {
    "addr:full":"106 Glebe Point Rd Glebe NSW 2037",
    "addr:housenumber":"106",
    "addr:postcode":"2037",
    "addr:street":"Glebe Point Rd",
    "iso:country":"AU",
    "sg:address":"106 Glebe Point Rd",
    "sg:city":"Glebe",
    "sg:classifiers":[
        {
            "category":"Education",
            "subcategory":"Kindergarten",
            "type":"Public Place"
        }
    ],
    "sg:phone":"+61 2 9660 8157",
    "sg:postcode":"2037",
    "sg:province":"NSW",
    "sg:tags":[
        "pre-schools"
    ],
    "wof:name":"Amigoss Pre-School & Long Day Care Centre",
    "wof:placetype":"venue"
},
  "geometry": {"coordinates":[151.18913269000001,-33.8818702698],"type":"Point"}
}