{
  "type": "Feature",
  "properties": {
    "iso:country":"AU",
    "sg:address":"1/ 239 Beaconsfield St",
    "sg:city":"Milperra",
    "sg:classifiers":[
        {
            "category":"Manufacturing",
            "subcategory":"Glass & Minerals",
            "type":"Manufacturing & Wholesale Goods"
        }
    ],
    "sg:phone":"+61 2 9792 7200",
    "sg:postcode":"2214",
    "sg:province":"NSW",
    "sg:tags":[
        "mfrg",
        "processing"
    ],
    "wof:name":"Moondani Glass Design Pty Ltd",
    "wof:placetype":"venue"
},
  "geometry": {"coordinates":[150.994583,-33.942043],"type":"Point"}
}