{
  "type": "Feature",
  "properties": {
    "iso:country":"AU",
    "sg:address":"189 Alfred St",
    "sg:city":"Mackay",
    "sg:classifiers":[
        {
            "category":"Retail",
            "subcategory":"Funeral Services",
            "type":"Services"
        }
    ],
    "sg:phone":"+61 7 4957 3248",
    "sg:postcode":"4740",
    "sg:province":"QLD",
    "sg:tags":[
        "cremation"
    ],
    "wof:name":"Mackay Funerals",
    "wof:placetype":"venue"
},
  "geometry": {"coordinates":[149.18414300000001,-21.145273],"type":"Point"}
}