{
  "type": "Feature",
  "properties": {
    "addr:full":"Shop 2 & 4 Uriarra Rd Queanbeyan NSW 2620",
    "addr:housenumber":"shop 2 & 4",
    "addr:postcode":"2620",
    "addr:street":"Uriarra Rd",
    "iso:country":"AU",
    "sg:address":"Shop 2 & 4 Uriarra Rd",
    "sg:city":"Queanbeyan",
    "sg:classifiers":[
        {
            "category":"Professional",
            "subcategory":"Art Services",
            "type":"Services"
        }
    ],
    "sg:phone":"+61 2 6299 0448",
    "sg:postcode":"2620",
    "sg:province":"NSW",
    "sg:tags":[
        "picture",
        "frame",
        "framing"
    ],
    "wof:name":"Framing Doctor",
    "wof:placetype":"venue"
},
  "geometry": {"coordinates":[149.21461486800001,-35.3442687988],"type":"Point"}
}