{
  "type": "Feature",
  "properties": {
    "addr:full":"80- 82 Goondoon St Gladstone QLD 4680",
    "addr:housenumber":"82",
    "addr:postcode":"4680",
    "addr:street":"Goondoon St",
    "iso:country":"AU",
    "sg:address":"80- 82 Goondoon St",
    "sg:city":"Gladstone",
    "sg:classifiers":[
        {
            "category":"Banks & Credit Unions",
            "subcategory":"Bank",
            "type":"Services"
        }
    ],
    "sg:phone":"+61 13 20 32",
    "sg:postcode":"4680",
    "sg:province":"QLD",
    "wof:name":"Westpac Banking Corporation",
    "wof:placetype":"venue"
},
  "geometry": {"coordinates":[151.36604309099999,-23.9486846924],"type":"Point"}
}