{
  "type": "Feature",
  "properties": {
    "addr:full":"2474 Gold Coast Hwy Mermaid Beach QLD 4218",
    "addr:housenumber":"2474",
    "addr:postcode":"4218",
    "addr:street":"Gold Coast Hwy",
    "iso:country":"AU",
    "sg:address":"2474 Gold Coast Hwy",
    "sg:city":"Mermaid Beach",
    "sg:classifiers":[
        {
            "category":"Fast Food",
            "type":"Food & Drink"
        }
    ],
    "sg:phone":"+61 7 5575 1166",
    "sg:postcode":"4218",
    "sg:province":"QLD",
    "sg:tags":[
        "away",
        "take"
    ],
    "wof:name":"Eagle Boys Pizza - Mermaid Beach",
    "wof:placetype":"venue"
},
  "geometry": {"coordinates":[153.43458557100001,-28.0443725586],"type":"Point"}
}