{
  "type": "Feature",
  "properties": {
    "iso:country":"AU",
    "sg:address":"311 North East Rd",
    "sg:city":"Hampstead Gardens",
    "sg:classifiers":[
        {
            "category":"Wholesale",
            "subcategory":"Furniture",
            "type":"Manufacturing & Wholesale Goods"
        }
    ],
    "sg:phone":"+61 8 8266 5766",
    "sg:postcode":"5086",
    "sg:province":"SA",
    "sg:tags":[
        "wholesaler",
        "mfrs"
    ],
    "sg:website":"http://www.saloungesuites.com.au",
    "wof:name":"SA Lounge Suites",
    "wof:placetype":"venue"
},
  "geometry": {"coordinates":[138.63543701200001,-34.8722343445],"type":"Point"}
}