{
  "type": "Feature",
  "properties": {
    "addr:full":"67B Katrina St Blackburn VIC 3130",
    "addr:housenumber":"67b",
    "addr:postcode":"3130",
    "addr:street":"Katrina St",
    "iso:country":"AU",
    "sg:address":"67B Katrina St",
    "sg:city":"Blackburn",
    "sg:classifiers":[
        {
            "category":"Shopping",
            "subcategory":"Computers & Home Electronics",
            "type":"Retail Goods"
        }
    ],
    "sg:phone":"+61 3 9877 4711",
    "sg:postcode":"3130",
    "sg:province":"VIC",
    "sg:tags":[
        "cleaning"
    ],
    "wof:name":"Computer Cleaning Company Pty Ltd",
    "wof:placetype":"venue"
},
  "geometry": {"coordinates":[145.14805602999999,-37.8037834167],"type":"Point"}
}