{
  "type": "Feature",
  "properties": {
    "addr:full":"46 Stachon St Gosford North NSW 2250",
    "addr:housenumber":"46",
    "addr:postcode":"2250",
    "addr:street":"Stachon St",
    "iso:country":"AU",
    "sg:address":"46 Stachon St",
    "sg:city":"Gosford North",
    "sg:classifiers":[
        {
            "category":"Building & Trades",
            "subcategory":"Cleaning & Sanitation",
            "type":"Services"
        }
    ],
    "sg:phone":"+61 2 4325 7270",
    "sg:postcode":"2250",
    "sg:province":"NSW",
    "sg:tags":[
        "wall",
        "brick"
    ],
    "wof:name":"Central Coast Brick Cleaning",
    "wof:placetype":"venue"
},
  "geometry": {"coordinates":[151.35401916500001,-33.4184188843],"type":"Point"}
}