{
  "type": "Feature",
  "properties": {
    "addr:full":"Shop 5, 431 St Kilda Rd Melbourne VIC 3004",
    "addr:housenumber":"shop 5 431",
    "addr:postcode":"3004",
    "addr:street":"St Kilda Rd",
    "iso:country":"AU",
    "sg:address":"Shop 5, 431 St Kilda Rd",
    "sg:city":"Melbourne",
    "sg:classifiers":[
        {
            "category":"Wholesale",
            "subcategory":"Music Publishers",
            "type":"Manufacturing & Wholesale Goods"
        }
    ],
    "sg:phone":"+61 3 9821 5255",
    "sg:postcode":"3004",
    "sg:province":"VIC",
    "sg:tags":[
        "wholesaler",
        "dvd",
        "mfrs",
        "cd"
    ],
    "wof:name":"Xtreem Technology",
    "wof:placetype":"venue"
},
  "geometry": {"coordinates":[144.97547912600001,-37.8371276855],"type":"Point"}
}