{
  "type": "Feature",
  "properties": {
    "iso:country":"AU",
    "sg:address":"16 Bridge St",
    "sg:city":"Picton",
    "sg:classifiers":[
        {
            "category":"Education",
            "subcategory":"Kindergarten",
            "type":"Public Place"
        }
    ],
    "sg:phone":"+61 2 4677 2122",
    "sg:postcode":"2571",
    "sg:province":"NSW",
    "sg:tags":[
        "pre-schools"
    ],
    "wof:name":"Busy Bees Preschool & Long Day Care Centre",
    "wof:placetype":"venue"
},
  "geometry": {"coordinates":[150.60426330600001,-34.189201355],"type":"Point"}
}