{
  "type": "Feature",
  "properties": {
    "addr:full":"PO Box 1376 Mt Barker SA 5251",
    "addr:postcode":"5251",
    "iso:country":"AU",
    "sg:address":"PO Box 1376",
    "sg:city":"Mt Barker",
    "sg:classifiers":[
        {
            "category":"Wholesale",
            "subcategory":"Scrap",
            "type":"Manufacturing & Wholesale Goods"
        }
    ],
    "sg:phone":"+61 439 915 105",
    "sg:postcode":"5251",
    "sg:province":"SA",
    "sg:tags":[
        "merchant",
        "metal"
    ],
    "wof:name":"Adelaide Hills Towing & Salvage",
    "wof:placetype":"venue"
},
  "geometry": {"coordinates":[138.85289001500001,-35.0617103577],"type":"Point"}
}