{
  "type": "Feature",
  "properties": {
    "addr:full":"Shp1/ 93 Pacific Hwy North Sydney NSW 2060",
    "addr:postcode":"2060",
    "addr:street":"Pacific Hwy",
    "iso:country":"AU",
    "sg:address":"Shp1/ 93 Pacific Hwy",
    "sg:city":"North Sydney",
    "sg:classifiers":[
        {
            "category":"Personal",
            "subcategory":"Beauty Salon",
            "type":"Services"
        }
    ],
    "sg:phone":"+61 2 9955 9613",
    "sg:postcode":"2060",
    "sg:province":"NSW",
    "sg:tags":[
        "hairdresser"
    ],
    "wof:name":"Dimples Hairdressing",
    "wof:placetype":"venue"
},
  "geometry": {"coordinates":[151.20892334000001,-33.8408889771],"type":"Point"}
}