{
  "type": "Feature",
  "properties": {
    "iso:country":"AU",
    "sg:address":"43 Riversdale Rd",
    "sg:city":"Oxenford",
    "sg:classifiers":[
        {
            "category":"Professional",
            "type":"Services"
        }
    ],
    "sg:phone":"+61 7 5561 7677",
    "sg:postcode":"4210",
    "sg:province":"QLD",
    "sg:tags":[
        "transport"
    ],
    "wof:name":"Bateman's Transport",
    "wof:placetype":"venue"
},
  "geometry": {"coordinates":[153.30668640100001,-27.8990116119],"type":"Point"}
}