{
  "type": "Feature",
  "properties": {
    "addr:full":"PO Box 688 Jimboomba QLD 4280",
    "addr:postcode":"4280",
    "iso:country":"AU",
    "sg:address":"PO Box 688",
    "sg:city":"Jimboomba",
    "sg:classifiers":[
        {
            "category":"Home & Garden",
            "subcategory":"Building Materials",
            "type":"Retail Goods"
        }
    ],
    "sg:phone":"+61 7 5543 1455",
    "sg:postcode":"4280",
    "sg:province":"QLD",
    "sg:tags":[
        "merchant",
        "glass",
        "glazier"
    ],
    "wof:name":"Topline Glazing",
    "wof:placetype":"venue"
},
  "geometry": {"coordinates":[153.02887000000001,-27.813459],"type":"Point"}
}