{
  "type": "Feature",
  "properties": {
    "addr:full":"66 Paintland Pde Yarraville VIC 3013",
    "addr:housenumber":"66",
    "addr:postcode":"3013",
    "addr:street":"Paintland Pde",
    "iso:country":"AU",
    "sg:address":"66 Paintland Pde",
    "sg:city":"Yarraville",
    "sg:classifiers":[
        {
            "category":"Professional",
            "subcategory":"Art Services",
            "type":"Services"
        }
    ],
    "sg:phone":"+61 404 177 120",
    "sg:postcode":"3013",
    "sg:province":"VIC",
    "sg:tags":[
        "decorator",
        "painter"
    ],
    "wof:name":"A & R Affordable Painter",
    "wof:placetype":"venue"
},
  "geometry": {"coordinates":[144.89321899399999,-37.8111534119],"type":"Point"}
}