{
  "type": "Feature",
  "properties": {
    "addr:full":"Shp2/ 120 Rawson Rd Greenacre NSW 2190",
    "addr:housenumber":"120",
    "addr:postcode":"2190",
    "addr:street":"Rawson Rd",
    "iso:country":"AU",
    "sg:address":"Shp2/ 120 Rawson Rd",
    "sg:city":"Greenacre",
    "sg:classifiers":[
        {
            "category":"Food & Beverages",
            "subcategory":"Fruits & Vegetables",
            "type":"Retail Goods"
        }
    ],
    "sg:phone":"+61 2 9790 2607",
    "sg:postcode":"2190",
    "sg:province":"NSW",
    "sg:tags":[
        "greengrocer",
        "fruiterer"
    ],
    "wof:name":"Rawson Rd Fruit Market",
    "wof:placetype":"venue"
},
  "geometry": {"coordinates":[151.052673,-33.901901],"type":"Point"}
}