{
  "type": "Feature",
  "properties": {
    "addr:full":"24 Tovan Akas Ave Bentleigh VIC 3204",
    "addr:housenumber":"24",
    "addr:postcode":"3204",
    "addr:street":"Tovan Akas Ave",
    "iso:country":"AU",
    "sg:address":"24 Tovan Akas Ave",
    "sg:city":"Bentleigh",
    "sg:classifiers":[
        {
            "category":"Utilities",
            "subcategory":"Electric",
            "type":"Services"
        }
    ],
    "sg:phone":"+61 3 9557 8019",
    "sg:postcode":"3204",
    "sg:province":"VIC",
    "sg:tags":[
        "electrical",
        "contractor"
    ],
    "wof:name":"Coutts S & J Electrics",
    "wof:placetype":"venue"
},
  "geometry": {"coordinates":[145.027557,-37.922981],"type":"Point"}
}