{
  "type": "Feature",
  "properties": {
    "addr:full":"85 Takalvan St West Bundaberg QLD 4670",
    "addr:housenumber":"85",
    "addr:postcode":"4670",
    "addr:street":"Takalvan St West",
    "iso:country":"AU",
    "sg:address":"85 Takalvan St",
    "sg:city":"West Bundaberg",
    "sg:classifiers":[
        {
            "category":"Transit Center",
            "subcategory":"Freight",
            "type":"Transportation"
        }
    ],
    "sg:phone":"+61 7 4152 2133",
    "sg:postcode":"4670",
    "sg:province":"QLD",
    "sg:tags":[
        "forklift",
        "truck"
    ],
    "wof:name":"Craft Rental & Hardware",
    "wof:placetype":"venue"
},
  "geometry": {"coordinates":[152.326004028,-24.8815956116],"type":"Point"}
}