{
  "type": "Feature",
  "properties": {
    "addr:full":"63 Ellis La Camden NSW 2570",
    "addr:housenumber":"63",
    "addr:postcode":"2570",
    "addr:street":"Ellis La",
    "iso:country":"AU",
    "sg:address":"63 Ellis La",
    "sg:city":"Camden",
    "sg:classifiers":[
        {
            "category":"Building & Trades",
            "subcategory":"Construction",
            "type":"Services"
        }
    ],
    "sg:phone":"+61 412 468 007",
    "sg:postcode":"2570",
    "sg:province":"NSW",
    "sg:tags":[
        "stonework",
        "stone",
        "mason"
    ],
    "wof:name":"Douglas Mihajlovic",
    "wof:placetype":"venue"
},
  "geometry": {"coordinates":[150.67201232900001,-34.0393066406],"type":"Point"}
}