{
  "type": "Feature",
  "properties": {
    "iso:country":"AU",
    "sg:address":"256 Albany Hwy",
    "sg:city":"Albany",
    "sg:classifiers":[
        {
            "category":"Retail",
            "subcategory":"Auto Repair",
            "type":"Services"
        }
    ],
    "sg:phone":"+61 8 9841 7955",
    "sg:postcode":"6330",
    "sg:province":"WA",
    "sg:tags":[
        "clutch",
        "brake"
    ],
    "wof:name":"Great Southern Brake & Clutch",
    "wof:placetype":"venue"
},
  "geometry": {"coordinates":[117.870483398,-35.0100364685],"type":"Point"}
}