{
  "type": "Feature",
  "properties": {
    "addr:full":"41 Evans St Hobart TAS 7000",
    "addr:housenumber":"41",
    "addr:postcode":"7000",
    "addr:street":"Evans St",
    "iso:country":"AU",
    "sg:address":"41 Evans St",
    "sg:city":"Hobart",
    "sg:classifiers":[
        {
            "category":"Commercial Area",
            "type":"Public Place"
        }
    ],
    "sg:phone":"+61 1300 668 105",
    "sg:postcode":"7000",
    "sg:province":"TAS",
    "sg:tags":[
        "heavy",
        "carrier"
    ],
    "wof:name":"Toll Autologistics",
    "wof:placetype":"venue"
},
  "geometry": {"coordinates":[147.33401489299999,-42.8799171448],"type":"Point"}
}