{
  "type": "Feature",
  "properties": {
    "addr:full":"Ste51/ 229 Westbury Rd Prospect TAS 7250",
    "addr:housenumber":"229",
    "addr:postcode":"7250",
    "addr:street":"Westbury Rd",
    "iso:country":"AU",
    "sg:address":"Ste51/ 229 Westbury Rd",
    "sg:city":"Prospect",
    "sg:classifiers":[
        {
            "category":"Travel",
            "subcategory":"Hotels & Motels",
            "type":"Entertainment"
        }
    ],
    "sg:phone":"+61 3 6344 3688",
    "sg:postcode":"7250",
    "sg:province":"TAS",
    "sg:tags":[
        "accommodation"
    ],
    "wof:name":"EBC Leisure Limited",
    "wof:placetype":"venue"
},
  "geometry": {"coordinates":[147.13424682600001,-41.4706268311],"type":"Point"}
}