{
  "type": "Feature",
  "properties": {
    "addr:full":"Cnr Dandenong & Huntingdale Rds Oakleigh VIC 3166",
    "addr:postcode":"3166",
    "addr:street":"Cnr",
    "iso:country":"AU",
    "sg:address":"Cnr Dandenong & Huntingdale Rds",
    "sg:city":"Oakleigh",
    "sg:classifiers":[
        {
            "category":"Retail",
            "subcategory":"Auto Repair",
            "type":"Services"
        }
    ],
    "sg:phone":"+61 3 9252 5000",
    "sg:postcode":"3166",
    "sg:province":"VIC",
    "sg:tags":[
        "repairer",
        "motor",
        "engineer"
    ],
    "wof:name":"Nissan",
    "wof:placetype":"venue"
},
  "geometry": {"coordinates":[145.09591674800001,-37.8951530457],"type":"Point"}
}