{
  "type": "Feature",
  "properties": {
    "iso:country":"AU",
    "sg:address":"Big Bear Shopping Centre, Shop 16 116 Military Rd",
    "sg:city":"Neutral Bay",
    "sg:classifiers":[
        {
            "category":"Food & Beverages",
            "subcategory":"Bakery",
            "type":"Retail Goods"
        }
    ],
    "sg:phone":"+61 2 9904 3599",
    "sg:postcode":"2089",
    "sg:province":"NSW",
    "sg:tags":[
        "baker"
    ],
    "wof:name":"Bakers Delight Ltd",
    "wof:placetype":"venue"
},
  "geometry": {"coordinates":[151.219314575,-33.830242157],"type":"Point"}
}