{
  "type": "Feature",
  "properties": {
    "addr:full":"PO Box 285 Mermaid Beach QLD 4218",
    "addr:postcode":"4218",
    "iso:country":"AU",
    "sg:address":"PO Box 285",
    "sg:city":"Mermaid Beach",
    "sg:classifiers":[
        {
            "category":"Home & Garden",
            "subcategory":"Building Materials",
            "type":"Retail Goods"
        }
    ],
    "sg:phone":"+61 7 5573 3408",
    "sg:postcode":"4218",
    "sg:province":"QLD",
    "sg:tags":[
        "merchant",
        "glass",
        "glazier"
    ],
    "wof:name":"Gold Coast Glass",
    "wof:placetype":"venue"
},
  "geometry": {"coordinates":[153.432037353,-28.0367908478],"type":"Point"}
}