{
  "type": "Feature",
  "properties": {
    "iso:country":"AU",
    "sg:address":"8 Pikki St",
    "sg:city":"Maroochydore",
    "sg:classifiers":[
        {
            "category":"Communications",
            "subcategory":"Film & Video Production",
            "type":"Services"
        }
    ],
    "sg:phone":"+61 7 5452 9808",
    "sg:postcode":"4558",
    "sg:province":"QLD",
    "sg:tags":[
        "television",
        "system",
        "circuit",
        "closed"
    ],
    "wof:name":"Aerosignals VISION",
    "wof:placetype":"venue"
},
  "geometry": {"coordinates":[153.086425781,-26.6535758972],"type":"Point"}
}