{
  "type": "Feature",
  "properties": {
    "iso:country":"AU",
    "sg:address":"82 Bridge St",
    "sg:city":"Muswellbrook",
    "sg:classifiers":[
        {
            "category":"Shopping",
            "subcategory":"Clothing, Apparel, & Fashions",
            "type":"Retail Goods"
        }
    ],
    "sg:phone":"+61 2 6543 1230",
    "sg:postcode":"2333",
    "sg:province":"NSW",
    "sg:tags":[
        "lady",
        "wear"
    ],
    "wof:name":"Fine & Dandy Boutique",
    "wof:placetype":"venue"
},
  "geometry": {"coordinates":[150.88836669899999,-32.2646598816],"type":"Point"}
}