{
  "type": "Feature",
  "properties": {
    "iso:country":"AU",
    "sg:address":"101 Lochinvar Rd",
    "sg:city":"Upper Kedron",
    "sg:classifiers":[
        {
            "category":"Banks & Credit Unions",
            "subcategory":"Financial Services",
            "type":"Services"
        }
    ],
    "sg:phone":"+61 7 3851 1066",
    "sg:postcode":"4055",
    "sg:province":"QLD",
    "sg:tags":[
        "equipment",
        "chain"
    ],
    "wof:name":"Loadsafe Australia Pty Ltd",
    "wof:placetype":"venue"
},
  "geometry": {"coordinates":[152.91029357900001,-27.4099617004],"type":"Point"}
}