{
  "type": "Feature",
  "properties": {
    "addr:full":"Shop B, 249 Bourbong St Bundaberg QLD 4670",
    "addr:housenumber":"249",
    "addr:postcode":"4670",
    "addr:street":"Bourbong St",
    "iso:country":"AU",
    "sg:address":"Shop B, 249 Bourbong St",
    "sg:city":"Bundaberg",
    "sg:classifiers":[
        {
            "category":"Food & Beverages",
            "subcategory":"Bakery",
            "type":"Retail Goods"
        }
    ],
    "sg:phone":"+61 7 4151 2122",
    "sg:postcode":"4670",
    "sg:province":"QLD",
    "sg:tags":[
        "cake",
        "shop",
        "pastry"
    ],
    "wof:name":"Cheesecake Shop The",
    "wof:placetype":"venue"
},
  "geometry": {"coordinates":[152.3409729,-24.8680362701],"type":"Point"}
}