{
  "type": "Feature",
  "properties": {
    "addr:full":"Albert St Albany WA 6330",
    "addr:postcode":"6330",
    "addr:street":"Albert St",
    "iso:country":"AU",
    "sg:address":"Albert St",
    "sg:city":"Albany",
    "sg:classifiers":[
        {
            "category":"Food & Beverages",
            "subcategory":"Supermarket",
            "type":"Retail Goods"
        }
    ],
    "sg:phone":"+61 8 9841 8566",
    "sg:postcode":"6330",
    "sg:province":"WA",
    "sg:tags":[
        "grocery",
        "store"
    ],
    "wof:name":"Albany Community Food Service",
    "wof:placetype":"venue"
},
  "geometry": {"coordinates":[117.88388824499999,-35.0140800476],"type":"Point"}
}