{
  "type": "Feature",
  "properties": {
    "addr:full":"145 Waverley St Bucasia QLD 4750",
    "addr:housenumber":"145",
    "addr:postcode":"4750",
    "addr:street":"Waverley St",
    "iso:country":"AU",
    "sg:address":"145 Waverley St",
    "sg:city":"Bucasia",
    "sg:classifiers":[
        {
            "category":"Building & Trades",
            "subcategory":"Construction",
            "type":"Services"
        }
    ],
    "sg:phone":"+61 7 4954 6138",
    "sg:postcode":"4750",
    "sg:province":"QLD",
    "sg:tags":[
        "polishing",
        "sanding",
        "floor"
    ],
    "wof:name":"Cullen K J & G N",
    "wof:placetype":"venue"
},
  "geometry": {"coordinates":[149.157883,-21.027308],"type":"Point"}
}