{
  "type": "Feature",
  "properties": {
    "iso:country":"AU",
    "sg:address":"Suite 8, Pegasus Ctr, 42 Bundall Rd",
    "sg:city":"Bundall",
    "sg:classifiers":[
        {
            "category":"Professional",
            "subcategory":"Business Services",
            "type":"Services"
        }
    ],
    "sg:phone":"+61 7 5592 3399",
    "sg:postcode":"4217",
    "sg:province":"QLD",
    "sg:tags":[
        "broker"
    ],
    "sg:website":"http://www.nbs.net.au",
    "wof:name":"National Business Sales",
    "wof:placetype":"venue"
},
  "geometry": {"coordinates":[153.41184997600001,-28.0108375549],"type":"Point"}
}