{
  "type": "Feature",
  "properties": {
    "addr:full":"194 Clarinda St Parkes NSW 2870",
    "addr:housenumber":"194",
    "addr:postcode":"2870",
    "addr:street":"Clarinda St",
    "iso:country":"AU",
    "sg:address":"194 Clarinda St",
    "sg:city":"Parkes",
    "sg:classifiers":[
        {
            "category":"Arena",
            "subcategory":"Sports Club",
            "type":"Entertainment"
        }
    ],
    "sg:phone":"+61 2 6862 1499",
    "sg:postcode":"2870",
    "sg:province":"NSW",
    "sg:tags":[
        "league",
        "rugby"
    ],
    "wof:name":"Parkes Leagues Club Co-Op Pty Ltd",
    "wof:placetype":"venue"
},
  "geometry": {"coordinates":[148.17506399999999,-33.138821],"type":"Point"}
}