{
  "type": "Feature",
  "properties": {
    "addr:full":"11 Roseberry Ave Rosebery NSW 2018",
    "addr:housenumber":"11",
    "addr:postcode":"2018",
    "addr:street":"Roseberry Ave",
    "iso:country":"AU",
    "sg:address":"11 Roseberry Ave",
    "sg:city":"Rosebery",
    "sg:classifiers":[
        {
            "category":"Food & Beverages",
            "subcategory":"Liquor & Beverages",
            "type":"Retail Goods"
        }
    ],
    "sg:phone":"+61 2 9666 0000",
    "sg:postcode":"2018",
    "sg:province":"NSW",
    "sg:tags":[
        "merchant",
        "spirit",
        "wine"
    ],
    "wof:name":"Bollinger Champagne",
    "wof:placetype":"venue"
},
  "geometry": {"coordinates":[151.207763672,-33.9135246277],"type":"Point"}
}