{
  "type": "Feature",
  "properties": {
    "addr:full":"Lot 1 Hipathites Rd Samsonvale QLD 4520",
    "addr:postcode":"4520",
    "addr:street":"Hipathites Rd",
    "iso:country":"AU",
    "sg:address":"Lot 1 Hipathites Rd",
    "sg:city":"Samsonvale",
    "sg:classifiers":[
        {
            "category":"Building & Trades",
            "subcategory":"Landscaping Services",
            "type":"Services"
        }
    ],
    "sg:phone":"+61 7 3289 9136",
    "sg:postcode":"4520",
    "sg:province":"QLD",
    "sg:tags":[
        "inspection"
    ],
    "wof:name":"Enchelmaier Ron",
    "wof:placetype":"venue"
},
  "geometry": {"coordinates":[152.835938,-27.269165],"type":"Point"}
}