{
  "type": "Feature",
  "properties": {
    "addr:full":"11 Hossack Ave Coburg North VIC 3058",
    "addr:housenumber":"11",
    "addr:postcode":"3058",
    "addr:street":"Hossack Ave",
    "iso:country":"AU",
    "sg:address":"11 Hossack Ave",
    "sg:city":"Coburg North",
    "sg:classifiers":[
        {
            "category":"Home & Garden",
            "subcategory":"Hardware",
            "type":"Retail Goods"
        }
    ],
    "sg:phone":"+61 3 9350 7333",
    "sg:postcode":"3058",
    "sg:province":"VIC",
    "sg:tags":[
        "rope",
        "twine"
    ],
    "sg:website":"http://www.braidcore.com.au",
    "wof:name":"Braidcore Industries",
    "wof:placetype":"venue"
},
  "geometry": {"coordinates":[144.956542969,-37.7321968079],"type":"Point"}
}