{
  "type": "Feature",
  "properties": {
    "addr:full":"Horsham Plz Horsham VIC 3400",
    "addr:postcode":"3400",
    "addr:street":"Horsham Plz",
    "iso:country":"AU",
    "sg:address":"Horsham Plz",
    "sg:city":"Horsham",
    "sg:classifiers":[
        {
            "category":"Autos & Motor Vehicles",
            "subcategory":"Auto Supplies",
            "type":"Retail Goods"
        }
    ],
    "sg:phone":"+61 3 5382 5977",
    "sg:postcode":"3400",
    "sg:province":"VIC",
    "sg:tags":[
        "tyre"
    ],
    "wof:name":"Kmart Tyre & Auto Service",
    "wof:placetype":"venue"
},
  "geometry": {"coordinates":[142.19712829599999,-36.714630127],"type":"Point"}
}