{
  "type": "Feature",
  "properties": {
    "addr:full":"269 Appleby Rd Stafford Heights QLD 4053",
    "addr:housenumber":"269",
    "addr:postcode":"4053",
    "addr:street":"Appleby Rd",
    "iso:country":"AU",
    "sg:address":"269 Appleby Rd",
    "sg:city":"Stafford Heights",
    "sg:classifiers":[
        {
            "category":"Health Services",
            "subcategory":"Doctor",
            "type":"Services"
        }
    ],
    "sg:phone":"+61 7 3861 4555",
    "sg:postcode":"4053",
    "sg:province":"QLD",
    "sg:tags":[
        "podiatrist"
    ],
    "sg:website":"http://www.thefootspot.com",
    "wof:name":"The Foot Spot",
    "wof:placetype":"venue"
},
  "geometry": {"coordinates":[153.01121520999999,-27.3931179047],"type":"Point"}
}