{
  "type": "Feature",
  "properties": {
    "iso:country":"AU",
    "sg:address":"7 Warrabungle St",
    "sg:city":"Gunnedah",
    "sg:classifiers":[
        {
            "category":"Structure",
            "subcategory":"Bridge",
            "type":"Public Place"
        }
    ],
    "sg:phone":"+61 2 6742 6662",
    "sg:postcode":"2380",
    "sg:province":"NSW",
    "sg:tags":[
        "chainsaw",
        "brushcutters"
    ],
    "wof:name":"Gunnedah Hire Service Pty Ltd",
    "wof:placetype":"venue"
},
  "geometry": {"coordinates":[150.24464416500001,-30.9740123749],"type":"Point"}
}