{
  "type": "Feature",
  "properties": {
    "iso:country":"AU",
    "sg:address":"100 Angus Smith Drv",
    "sg:city":"Douglas",
    "sg:classifiers":[
        {
            "category":"Health Services",
            "subcategory":"Dentist",
            "type":"Services"
        }
    ],
    "sg:phone":"+61 7 4725 5800",
    "sg:postcode":"4814",
    "sg:province":"QLD",
    "wof:name":"Pryde Brian Dr",
    "wof:placetype":"venue"
},
  "geometry": {"coordinates":[146.734695,-19.330072],"type":"Point"}
}