{
  "type": "Feature",
  "properties": {
    "iso:country":"AU",
    "sg:address":"15 Northern Rd",
    "sg:city":"Heidelberg West",
    "sg:classifiers":[
        {
            "category":"Manufacturing",
            "subcategory":"Metals",
            "type":"Manufacturing & Wholesale Goods"
        }
    ],
    "sg:phone":"+61 3 9459 2838",
    "sg:postcode":"3081",
    "sg:province":"VIC",
    "sg:tags":[
        "steel",
        "fabricator",
        "mfrs"
    ],
    "wof:name":"B & B Steel Pty Ltd",
    "wof:placetype":"venue"
},
  "geometry": {"coordinates":[145.04461669899999,-37.7288513184],"type":"Point"}
}