{
  "type": "Feature",
  "properties": {
    "iso:country":"AU",
    "sg:address":"Cnr Schiller & Say Sts",
    "sg:city":"Wagga Wagga",
    "sg:classifiers":[
        {
            "category":"Banks & Credit Unions",
            "subcategory":"Bank",
            "type":"Services"
        }
    ],
    "sg:phone":"+61 2 6921 4178",
    "sg:postcode":"2650",
    "sg:province":"NSW",
    "sg:tags":[
        "concrete",
        "reinforcement"
    ],
    "wof:name":"OneSteel Reinforcing",
    "wof:placetype":"venue"
},
  "geometry": {"coordinates":[147.41798400900001,-35.1290054321],"type":"Point"}
}