{
  "type": "Feature",
  "properties": {
    "iso:country":"AU",
    "sg:address":"34 Kepler St",
    "sg:city":"Warrnambool",
    "sg:classifiers":[
        {
            "category":"Real Estate",
            "subcategory":"Surveying",
            "type":"Services"
        }
    ],
    "sg:phone":"+61 3 5562 3752",
    "sg:postcode":"3280",
    "sg:province":"VIC",
    "sg:tags":[
        "surveyor",
        "land"
    ],
    "wof:name":"Forster Land Surveying",
    "wof:placetype":"venue"
},
  "geometry": {"coordinates":[142.48043823200001,-38.3841552734],"type":"Point"}
}