{
  "type": "Feature",
  "properties": {
    "addr:full":"Fourth St Alford SA 5555",
    "addr:postcode":"5555",
    "addr:street":"Fourth St",
    "iso:country":"AU",
    "sg:address":"Fourth St",
    "sg:city":"Alford",
    "sg:classifiers":[
        {
            "category":"Travel",
            "subcategory":"Hotels & Motels",
            "type":"Entertainment"
        }
    ],
    "sg:phone":"+61 8 8824 2202",
    "sg:postcode":"5555",
    "sg:province":"SA",
    "sg:tags":[
        "accommodation"
    ],
    "wof:name":"Alford Hotel",
    "wof:placetype":"venue"
},
  "geometry": {"coordinates":[137.81979370100001,-33.8156280518],"type":"Point"}
}