{
  "type": "Feature",
  "properties": {
    "addr:full":"Level 8/ 120 Sussex St Sydney NSW 2000",
    "addr:housenumber":"/ 120",
    "addr:postcode":"2000",
    "addr:street":"Sussex St",
    "iso:country":"AU",
    "sg:address":"Level 8/ 120 Sussex St",
    "sg:city":"Sydney",
    "sg:classifiers":[
        {
            "category":"Transit Center",
            "subcategory":"Freight",
            "type":"Transportation"
        }
    ],
    "sg:phone":"+61 2 9364 8960",
    "sg:postcode":"2000",
    "sg:province":"NSW",
    "sg:tags":[
        "agent",
        "shipping"
    ],
    "wof:name":"Beaufort Shipping Agency Co",
    "wof:placetype":"venue"
},
  "geometry": {"coordinates":[151.203735352,-33.8682365417],"type":"Point"}
}