{
  "type": "Feature",
  "properties": {
    "iso:country":"AU",
    "sg:address":"Factory 2, 6 Strezlecki Gr",
    "sg:city":"Laverton",
    "sg:classifiers":[
        {
            "category":"Manufacturing",
            "subcategory":"Metals",
            "type":"Manufacturing & Wholesale Goods"
        }
    ],
    "sg:phone":"+61 3 9369 1190",
    "sg:postcode":"3028",
    "sg:province":"VIC",
    "sg:tags":[
        "steel",
        "fabricator",
        "mfrs"
    ],
    "wof:name":"Wyndham Fabrications",
    "wof:placetype":"venue"
},
  "geometry": {"coordinates":[144.758072,-37.868622],"type":"Point"}
}