{
  "type": "Feature",
  "properties": {
    "iso:country":"AU",
    "sg:address":"241 Dugan St",
    "sg:city":"Kalgoorlie",
    "sg:classifiers":[
        {
            "category":"Professional",
            "type":"Services"
        }
    ],
    "sg:phone":"+61 8 9091 2788",
    "sg:postcode":"6430",
    "sg:province":"WA",
    "sg:tags":[
        "shop",
        "fitting"
    ],
    "wof:name":"Somerville Cabinets",
    "wof:placetype":"venue"
},
  "geometry": {"coordinates":[121.459121704,-30.7560310364],"type":"Point"}
}