{
  "type": "Feature",
  "properties": {
    "addr:full":"Shp1/ 9 Patrick St Campbelltown NSW 2560",
    "addr:housenumber":"9",
    "addr:postcode":"2560",
    "addr:street":"Patrick St",
    "iso:country":"AU",
    "sg:address":"Shp1/ 9 Patrick St",
    "sg:city":"Campbelltown",
    "sg:classifiers":[
        {
            "category":"Retail",
            "subcategory":"Laundry & Dry Cleaning",
            "type":"Services"
        }
    ],
    "sg:phone":"+61 2 4620 5249",
    "sg:postcode":"2560",
    "sg:province":"NSW",
    "wof:name":"Lovely Laundry",
    "wof:placetype":"venue"
},
  "geometry": {"coordinates":[150.81361389200001,-34.0654144287],"type":"Point"}
}