{
  "type": "Feature",
  "properties": {
    "iso:country":"AU",
    "sg:address":"PO Box 167",
    "sg:city":"Leppington",
    "sg:classifiers":[
        {
            "category":"Farming",
            "subcategory":"Farm & Veterinary Services",
            "type":"Manufacturing & Wholesale Goods"
        }
    ],
    "sg:phone":"+61 2 9606 5555",
    "sg:postcode":"2171",
    "sg:province":"NSW",
    "sg:tags":[
        "seedsman"
    ],
    "wof:name":"Leppington Speedy Seedlings",
    "wof:placetype":"venue"
},
  "geometry": {"coordinates":[150.846237183,-33.9284286499],"type":"Point"}
}