{
  "type": "Feature",
  "properties": {
    "iso:country":"AU",
    "sg:address":"179 Martyn St",
    "sg:city":"Cairns",
    "sg:classifiers":[
        {
            "category":"Sports & Exercise",
            "subcategory":"Gym",
            "type":"Entertainment"
        }
    ],
    "sg:phone":"+61 412 508 191",
    "sg:postcode":"4870",
    "sg:province":"QLD",
    "sg:tags":[
        "personal",
        "trainer",
        "fitness"
    ],
    "wof:name":"Christina Monds",
    "wof:placetype":"venue"
},
  "geometry": {"coordinates":[145.75718689000001,-16.9142627716],"type":"Point"}
}