{
  "type": "Feature",
  "properties": {
    "addr:full":"15 Rhodes Drv Glen Waverley VIC 3150",
    "addr:housenumber":"15",
    "addr:postcode":"3150",
    "addr:street":"Rhodes Drv",
    "iso:country":"AU",
    "sg:address":"15 Rhodes Drv",
    "sg:city":"Glen Waverley",
    "sg:classifiers":[
        {
            "category":"Wholesale",
            "subcategory":"Home Furnishings",
            "type":"Manufacturing & Wholesale Goods"
        }
    ],
    "sg:phone":"+61 419 343 579",
    "sg:postcode":"3150",
    "sg:province":"VIC",
    "sg:tags":[
        "wholesaler",
        "mfrs",
        "manchester"
    ],
    "wof:name":"Textile Group The",
    "wof:placetype":"venue"
},
  "geometry": {"coordinates":[145.17582702600001,-37.8848495483],"type":"Point"}
}