{
  "type": "Feature",
  "properties": {
    "addr:full":"27 Edward St Biggenden QLD 4621",
    "addr:housenumber":"27",
    "addr:postcode":"4621",
    "addr:street":"Edward St",
    "iso:country":"AU",
    "sg:address":"27 Edward St",
    "sg:city":"Biggenden",
    "sg:classifiers":[
        {
            "category":"Travel",
            "subcategory":"Hotels & Motels",
            "type":"Entertainment"
        }
    ],
    "sg:phone":"+61 7 4127 1252",
    "sg:postcode":"4621",
    "sg:province":"QLD",
    "sg:tags":[
        "accommodation"
    ],
    "wof:name":"Grand Hotel",
    "wof:placetype":"venue"
},
  "geometry": {"coordinates":[152.042542,-25.509924],"type":"Point"}
}