{
  "type": "Feature",
  "properties": {
    "iso:country":"AU",
    "sg:address":"36 Colebard East St",
    "sg:city":"Acacia Ridge",
    "sg:classifiers":[
        {
            "category":"Manufacturing",
            "subcategory":"Tools & Machinery",
            "type":"Manufacturing & Wholesale Goods"
        }
    ],
    "sg:phone":"+61 7 3276 8919",
    "sg:postcode":"4110",
    "sg:province":"QLD",
    "sg:tags":[
        "earth",
        "excavating",
        "moving",
        "equipment"
    ],
    "wof:name":"CJD Equipment Pty Ltd",
    "wof:placetype":"venue"
},
  "geometry": {"coordinates":[153.00544738799999,-27.5813293457],"type":"Point"}
}