{
  "type": "Feature",
  "properties": {
    "addr:full":"24 Ainsworth St Salisbury QLD 4107",
    "addr:housenumber":"24",
    "addr:postcode":"4107",
    "addr:street":"Ainsworth St",
    "iso:country":"AU",
    "sg:address":"24 Ainsworth St",
    "sg:city":"Salisbury",
    "sg:classifiers":[
        {
            "category":"Personal",
            "subcategory":"Barber",
            "type":"Services"
        }
    ],
    "sg:phone":"+61 419 637 237",
    "sg:postcode":"4107",
    "sg:province":"QLD",
    "wof:name":"Jack's Barber Shop",
    "wof:placetype":"venue"
},
  "geometry": {"coordinates":[153.036819458,-27.5508041382],"type":"Point"}
}