{
  "type": "Feature",
  "properties": {
    "iso:country":"AU",
    "sg:address":"5/ 445 Oxley Drv",
    "sg:city":"Runaway Bay",
    "sg:classifiers":[
        {
            "category":"Communications",
            "subcategory":"Film & Video Production",
            "type":"Services"
        }
    ],
    "sg:phone":"+61 7 5563 9211",
    "sg:postcode":"4216",
    "sg:province":"QLD",
    "sg:tags":[
        "dvd",
        "library"
    ],
    "wof:name":"Blockbuster",
    "wof:placetype":"venue"
},
  "geometry": {"coordinates":[153.38772582999999,-27.9208831787],"type":"Point"}
}