{
  "type": "Feature",
  "properties": {
    "addr:full":"Cnr Cowpasture & North Liverpool Rds Green Valley NSW 2168",
    "addr:postcode":"2168",
    "addr:street":"Cnr Cowpasture & North",
    "iso:country":"AU",
    "sg:address":"Cnr Cowpasture & North Liverpool Rds",
    "sg:city":"Green Valley",
    "sg:classifiers":[
        {
            "category":"Building & Trades",
            "subcategory":"Construction",
            "type":"Services"
        }
    ],
    "sg:phone":"+61 2 9608 3333",
    "sg:postcode":"2168",
    "sg:province":"NSW",
    "sg:tags":[
        "contractor"
    ],
    "wof:name":"CSB Homes",
    "wof:placetype":"venue"
},
  "geometry": {"coordinates":[150.85719299300001,-33.8944206238],"type":"Point"}
}