{
  "type": "Feature",
  "properties": {
    "addr:full":"390 Payneham Rd Payneham SA 5070",
    "addr:housenumber":"390",
    "addr:postcode":"5070",
    "addr:street":"Payneham Rd",
    "iso:country":"AU",
    "sg:address":"390 Payneham Rd",
    "sg:city":"Payneham",
    "sg:classifiers":[
        {
            "category":"Insurance",
            "subcategory":"Hazard Insurance",
            "type":"Services"
        }
    ],
    "sg:phone":"+61 8 8337 7733",
    "sg:postcode":"5070",
    "sg:province":"SA",
    "sg:tags":[
        "motor",
        "vehicle"
    ],
    "wof:name":"DeConno & Blanco Insurance Brokers",
    "wof:placetype":"venue"
},
  "geometry": {"coordinates":[138.64468383799999,-34.894329071],"type":"Point"}
}