{
  "type": "Feature",
  "properties": {
    "addr:full":"114 Gilba Rd Girraween NSW 2145",
    "addr:housenumber":"114",
    "addr:postcode":"2145",
    "addr:street":"Gilba Rd",
    "iso:country":"AU",
    "sg:address":"114 Gilba Rd",
    "sg:city":"Girraween",
    "sg:classifiers":[
        {
            "category":"Building & Trades",
            "subcategory":"Equipment Rental",
            "type":"Services"
        }
    ],
    "sg:phone":"+61 411 250 052",
    "sg:postcode":"2145",
    "sg:province":"NSW",
    "sg:tags":[
        "crane",
        "hire"
    ],
    "wof:name":"Outdoor Fabrications Pty Ltd",
    "wof:placetype":"venue"
},
  "geometry": {"coordinates":[150.943725586,-33.798210144],"type":"Point"}
}