{
  "type": "Feature",
  "properties": {
    "addr:full":"Ste 13B/ 23 James St Fortitude Valley QLD 4006",
    "addr:housenumber":"/ 23",
    "addr:postcode":"4006",
    "addr:street":"James St",
    "iso:country":"AU",
    "sg:address":"Ste 13B/ 23 James St",
    "sg:city":"Fortitude Valley",
    "sg:classifiers":[
        {
            "category":"Banks & Credit Unions",
            "subcategory":"Financial Services",
            "type":"Services"
        }
    ],
    "sg:phone":"+61 7 3363 5000",
    "sg:postcode":"4006",
    "sg:province":"QLD",
    "sg:tags":[
        "planning"
    ],
    "wof:name":"Aspiri Financial Services Pty Ltd",
    "wof:placetype":"venue"
},
  "geometry": {"coordinates":[153.03939819300001,-27.4564990997],"type":"Point"}
}