{
  "type": "Feature",
  "properties": {
    "addr:full":"John&#039;s Hair Studio Yandilla St Pittsworth QLD 4356",
    "addr:postcode":"4356",
    "addr:street":"St",
    "iso:country":"AU",
    "sg:address":"John&#039;s Hair Studio Yandilla St",
    "sg:city":"Pittsworth",
    "sg:classifiers":[
        {
            "category":"Personal",
            "subcategory":"Beauty Salon",
            "type":"Services"
        }
    ],
    "sg:phone":"+61 7 4693 1067",
    "sg:postcode":"4356",
    "sg:province":"QLD",
    "wof:name":"Bous For Beauty",
    "wof:placetype":"venue"
},
  "geometry": {"coordinates":[151.63580300000001,-27.71553],"type":"Point"}
}