{
  "type": "Feature",
  "properties": {
    "addr:full":"35 Tower Rd New Town TAS 7008",
    "addr:housenumber":"35",
    "addr:postcode":"7008",
    "addr:street":"Tower Rd",
    "iso:country":"AU",
    "sg:address":"35 Tower Rd",
    "sg:city":"New Town",
    "sg:classifiers":[
        {
            "category":"Education",
            "subcategory":"Special Training",
            "type":"Public Place"
        }
    ],
    "sg:phone":"+61 3 6208 6000",
    "sg:postcode":"7008",
    "sg:province":"TAS",
    "sg:tags":[
        "development"
    ],
    "wof:name":"Willson Training Centre",
    "wof:placetype":"venue"
},
  "geometry": {"coordinates":[147.305984497,-42.8513717651],"type":"Point"}
}