{
  "type": "Feature",
  "properties": {
    "addr:full":"57 Elanda St Sunshine Beach QLD 4567",
    "addr:housenumber":"57",
    "addr:postcode":"4567",
    "addr:street":"Elanda St",
    "iso:country":"AU",
    "sg:address":"57 Elanda St",
    "sg:city":"Sunshine Beach",
    "sg:classifiers":[
        {
            "category":"Airline",
            "type":"Transportation"
        }
    ],
    "sg:phone":"+61 7 5474 5811",
    "sg:postcode":"4567",
    "sg:province":"QLD",
    "sg:tags":[
        "aircraft",
        "rental",
        "charter"
    ],
    "wof:name":"Southern Cross Air Pty Ltd",
    "wof:placetype":"venue"
},
  "geometry": {"coordinates":[153.10873413100001,-26.4078655243],"type":"Point"}
}