{
  "type": "Feature",
  "properties": {
    "addr:full":"12 Forster Ave Malvern East VIC 3145",
    "addr:housenumber":"12",
    "addr:postcode":"3145",
    "addr:street":"Forster Ave",
    "iso:country":"AU",
    "sg:address":"12 Forster Ave",
    "sg:city":"Malvern East",
    "sg:classifiers":[
        {
            "category":"Building & Trades",
            "subcategory":"Construction",
            "type":"Services"
        }
    ],
    "sg:phone":"+61 3 9569 3899",
    "sg:postcode":"3145",
    "sg:province":"VIC",
    "sg:tags":[
        "contractor"
    ],
    "wof:name":"Tasha Construction",
    "wof:placetype":"venue"
},
  "geometry": {"coordinates":[145.062896728,-37.8751945496],"type":"Point"}
}