{
  "type": "Feature",
  "properties": {
    "addr:full":"Room A17, Tok Corporate Centre 1st Floor, Toorak Rd Toorak VIC 3142",
    "addr:postcode":"3142",
    "addr:street":"Toorak Rd",
    "iso:country":"AU",
    "sg:address":"Room A17, Tok Corporate Centre 1st Floor, Toorak Rd",
    "sg:city":"Toorak",
    "sg:classifiers":[
        {
            "category":"Health Services",
            "subcategory":"Doctor",
            "type":"Services"
        }
    ],
    "sg:phone":"+61 408 477 307",
    "sg:postcode":"3142",
    "sg:province":"VIC",
    "sg:tags":[
        "medical",
        "practitioner"
    ],
    "wof:name":"Churchman Guy Dr",
    "wof:placetype":"venue"
},
  "geometry": {"coordinates":[145.017974853,-37.842124939],"type":"Point"}
}