{
  "type": "Feature",
  "properties": {
    "iso:country":"AU",
    "sg:address":"Factory 6, 93 Abbott Rd",
    "sg:city":"Hallam",
    "sg:classifiers":[
        {
            "category":"Wholesale",
            "subcategory":"Apparel",
            "type":"Manufacturing & Wholesale Goods"
        }
    ],
    "sg:phone":"+61 3 9796 5316",
    "sg:postcode":"3803",
    "sg:province":"VIC",
    "sg:tags":[
        "wholesaler",
        "men's",
        "mfrs",
        "sportswear"
    ],
    "wof:name":"Nguyen V",
    "wof:placetype":"venue"
},
  "geometry": {"coordinates":[145.261444092,-38.0082206726],"type":"Point"}
}