{
  "type": "Feature",
  "properties": {
    "iso:country":"AU",
    "sg:address":"47 Patrea St",
    "sg:city":"Banyo",
    "sg:classifiers":[
        {
            "category":"Professional",
            "subcategory":"Art Services",
            "type":"Services"
        }
    ],
    "sg:phone":"+61 7 3267 7168",
    "sg:postcode":"4014",
    "sg:province":"QLD",
    "sg:tags":[
        "decorator",
        "painter"
    ],
    "wof:name":"Masters Painting Service",
    "wof:placetype":"venue"
},
  "geometry": {"coordinates":[153.08599853499999,-27.3840274811],"type":"Point"}
}