{
  "type": "Feature",
  "properties": {
    "iso:country":"AU",
    "sg:address":"Port Beach Rd",
    "sg:city":"North Fremantle",
    "sg:classifiers":[
        {
            "category":"Transit Center",
            "subcategory":"Freight",
            "type":"Transportation"
        }
    ],
    "sg:phone":"+61 8 9432 0300",
    "sg:postcode":"6159",
    "sg:province":"WA",
    "sg:tags":[
        "stevedore"
    ],
    "wof:name":"Patrick The Australian Stevedore",
    "wof:placetype":"venue"
},
  "geometry": {"coordinates":[115.745819,-32.035393],"type":"Point"}
}