{
  "type": "Feature",
  "properties": {
    "iso:country":"AU",
    "sg:address":"Shp3/ 26 Ulong St",
    "sg:city":"Griffith",
    "sg:classifiers":[
        {
            "category":"Deli",
            "type":"Food & Drink"
        }
    ],
    "sg:phone":"+61 2 6964 5559",
    "sg:postcode":"2680",
    "sg:province":"NSW",
    "sg:tags":[
        "delicatessen"
    ],
    "wof:name":"Cafe Deli",
    "wof:placetype":"venue"
},
  "geometry": {"coordinates":[146.041595,-34.293228],"type":"Point"}
}