{
  "type": "Feature",
  "properties": {
    "iso:country":"AU",
    "sg:address":"Level 1/ 23 King St",
    "sg:city":"Perth",
    "sg:classifiers":[
        {
            "category":"Health Services",
            "subcategory":"Dentist",
            "type":"Services"
        }
    ],
    "sg:phone":"+61 8 9321 7484",
    "sg:postcode":"6000",
    "sg:province":"WA",
    "wof:name":"Metropolitan Dental Surgeries",
    "wof:placetype":"venue"
},
  "geometry": {"coordinates":[115.85508728000001,-31.952419281],"type":"Point"}
}