{
  "type": "Feature",
  "properties": {
    "addr:full":"75 Nicholson St Footscray VIC 3011",
    "addr:housenumber":"75",
    "addr:postcode":"3011",
    "addr:street":"Nicholson St",
    "iso:country":"AU",
    "sg:address":"75 Nicholson St",
    "sg:city":"Footscray",
    "sg:classifiers":[
        {
            "category":"Education",
            "subcategory":"Special Training",
            "type":"Public Place"
        }
    ],
    "sg:phone":"+61 3 9689 0555",
    "sg:postcode":"3011",
    "sg:province":"VIC",
    "sg:tags":[
        "college",
        "hairdressing"
    ],
    "wof:name":"L & G Australia Hair & Beauty College Pty Ltd",
    "wof:placetype":"venue"
},
  "geometry": {"coordinates":[144.899780273,-37.7993888855],"type":"Point"}
}