{
  "type": "Feature",
  "properties": {
    "addr:full":"15 Dew St Aberfoyle Park SA 5159",
    "addr:housenumber":"15",
    "addr:postcode":"5159",
    "addr:street":"Dew St",
    "iso:country":"AU",
    "sg:address":"15 Dew St",
    "sg:city":"Aberfoyle Park",
    "sg:classifiers":[
        {
            "category":"Structure",
            "subcategory":"Office Building",
            "type":"Public Place"
        }
    ],
    "sg:phone":"+61 8 8270 7217",
    "sg:postcode":"5159",
    "sg:province":"SA",
    "sg:tags":[
        "slater",
        "tiler",
        "roof"
    ],
    "wof:name":"Acquired Roofing",
    "wof:placetype":"venue"
},
  "geometry": {"coordinates":[138.598587036,-35.0616798401],"type":"Point"}
}