{
  "type": "Feature",
  "properties": {
    "addr:full":"581 Ballina Rd Goonellabah NSW 2480",
    "addr:housenumber":"581",
    "addr:postcode":"2480",
    "addr:street":"Ballina Rd",
    "iso:country":"AU",
    "sg:address":"581 Ballina Rd",
    "sg:city":"Goonellabah",
    "sg:classifiers":[
        {
            "category":"Health Services",
            "subcategory":"Health Practitioner",
            "type":"Services"
        }
    ],
    "sg:phone":"+61 2 6625 2888",
    "sg:postcode":"2480",
    "sg:province":"NSW",
    "sg:tags":[
        "physiotherapist"
    ],
    "wof:name":"Boyce Gabrielle",
    "wof:placetype":"venue"
},
  "geometry": {"coordinates":[153.36677551299999,-28.8111686707],"type":"Point"}
}