{
  "type": "Feature",
  "properties": {
    "iso:country":"AU",
    "sg:address":"100 River Ave",
    "sg:city":"Innisfail",
    "sg:classifiers":[
        {
            "category":"Organizations",
            "subcategory":"Labor Organization",
            "type":"Services"
        }
    ],
    "sg:phone":"+61 7 4061 3942",
    "sg:postcode":"4860",
    "sg:province":"QLD",
    "sg:tags":[
        "union"
    ],
    "wof:name":"Australian Manufacturing Workers' Union",
    "wof:placetype":"venue"
},
  "geometry": {"coordinates":[146.02952575699999,-17.5320396423],"type":"Point"}
}