{
  "type": "Feature",
  "properties": {
    "addr:full":"Unit 1, 8 Copernicus Way Keilor Downs VIC 3038",
    "addr:housenumber":"8",
    "addr:postcode":"3038",
    "addr:street":"Copernicus Way",
    "iso:country":"AU",
    "sg:address":"Unit 1, 8 Copernicus Way",
    "sg:city":"Keilor Downs",
    "sg:classifiers":[
        {
            "category":"Health Services",
            "subcategory":"Doctor",
            "type":"Services"
        }
    ],
    "sg:phone":"+61 3 9366 7977",
    "sg:postcode":"3038",
    "sg:province":"VIC",
    "sg:tags":[
        "medical",
        "practitioner"
    ],
    "wof:name":"Knowles John",
    "wof:placetype":"venue"
},
  "geometry": {"coordinates":[144.806229,-37.723812],"type":"Point"}
}