{
  "type": "Feature",
  "properties": {
    "addr:full":"Warrego Hwy Chinchilla QLD 4413",
    "addr:postcode":"4413",
    "addr:street":"Warrego Hwy",
    "iso:country":"AU",
    "sg:address":"Warrego Hwy",
    "sg:city":"Chinchilla",
    "sg:classifiers":[
        {
            "category":"Manufacturing",
            "subcategory":"Motor Vehicles & Parts",
            "type":"Manufacturing & Wholesale Goods"
        }
    ],
    "sg:phone":"+61 7 4669 1244",
    "sg:postcode":"4413",
    "sg:province":"QLD",
    "sg:tags":[
        "replacement"
    ],
    "wof:name":"Jackson's Parts N Industrial Supplies",
    "wof:placetype":"venue"
},
  "geometry": {"coordinates":[150.644134522,-26.748872757],"type":"Point"}
}