{
  "type": "Feature",
  "properties": {
    "iso:country":"AU",
    "sg:address":"42 Preston St",
    "sg:city":"Coburg",
    "sg:classifiers":[
        {
            "category":"Farming",
            "subcategory":"Fish & Marine Products",
            "type":"Manufacturing & Wholesale Goods"
        }
    ],
    "sg:phone":"+61 3 9386 1578",
    "sg:postcode":"3058",
    "sg:province":"VIC",
    "sg:tags":[
        "organic"
    ],
    "wof:name":"Cocoa Rhapsody",
    "wof:placetype":"venue"
},
  "geometry": {"coordinates":[144.954055786,-37.7440681458],"type":"Point"}
}