{
  "type": "Feature",
  "properties": {
    "addr:full":"15 High St Dry Creek SA 5094",
    "addr:housenumber":"15",
    "addr:postcode":"5094",
    "addr:street":"High St Dry",
    "iso:country":"AU",
    "sg:address":"15 High St",
    "sg:city":"Dry Creek",
    "sg:classifiers":[
        {
            "category":"Building & Trades",
            "subcategory":"Construction",
            "type":"Services"
        }
    ],
    "sg:phone":"+61 418 823 700",
    "sg:postcode":"5094",
    "sg:province":"SA",
    "sg:tags":[
        "tennis court",
        "repair"
    ],
    "wof:name":"R.J. Gilbert",
    "wof:placetype":"venue"
},
  "geometry": {"coordinates":[138.58807373100001,-34.8355102539],"type":"Point"}
}