{
  "type": "Feature",
  "properties": {
    "addr:full":"41a Kirwan St Floreat WA 6014",
    "addr:housenumber":"41a",
    "addr:postcode":"6014",
    "addr:street":"Kirwan St",
    "iso:country":"AU",
    "sg:address":"41a Kirwan St",
    "sg:city":"Floreat",
    "sg:classifiers":[
        {
            "category":"Professional",
            "subcategory":"Management & Consulting",
            "type":"Services"
        }
    ],
    "sg:phone":"+61 8 9284 9044",
    "sg:postcode":"6014",
    "sg:province":"WA",
    "sg:tags":[
        "consultant",
        "relocation"
    ],
    "wof:name":"Relocation Resources Pty Ltd",
    "wof:placetype":"venue"
},
  "geometry": {"coordinates":[115.798789978,-31.945432663],"type":"Point"}
}