{
  "type": "Feature",
  "properties": {
    "addr:full":"139 George St Quirindi NSW 2343",
    "addr:housenumber":"139",
    "addr:postcode":"2343",
    "addr:street":"George St",
    "iso:country":"AU",
    "sg:address":"139 George St",
    "sg:city":"Quirindi",
    "sg:classifiers":[
        {
            "category":"Health Services",
            "subcategory":"Doctor",
            "type":"Services"
        }
    ],
    "sg:phone":"+61 2 6746 1454",
    "sg:postcode":"2343",
    "sg:province":"NSW",
    "sg:tags":[
        "medical",
        "practitioner"
    ],
    "wof:name":"Redmayne W",
    "wof:placetype":"venue"
},
  "geometry": {"coordinates":[150.67918395999999,-31.5113048553],"type":"Point"}
}