{
  "type": "Feature",
  "properties": {
    "iso:country":"AU",
    "sg:address":"85 Mt Pleasant Rd",
    "sg:city":"Nunawading",
    "sg:classifiers":[
        {
            "category":"Education",
            "subcategory":"Music School",
            "type":"Public Place"
        }
    ],
    "sg:phone":"+61 3 9935 9479",
    "sg:postcode":"3131",
    "sg:province":"VIC",
    "sg:tags":[
        "singing",
        "teacher"
    ],
    "wof:name":"BTP Talent Development",
    "wof:placetype":"venue"
},
  "geometry": {"coordinates":[145.18011474599999,-37.8266067505],"type":"Point"}
}