{
  "type": "Feature",
  "properties": {
    "iso:country":"AU",
    "sg:address":"5 Desire Pl",
    "sg:city":"Hoppers Crossing",
    "sg:classifiers":[
        {
            "category":"Wholesale",
            "subcategory":"Furniture",
            "type":"Manufacturing & Wholesale Goods"
        }
    ],
    "sg:phone":"+61 3 9748 0222",
    "sg:postcode":"3029",
    "sg:province":"VIC",
    "sg:tags":[
        "wholesaler",
        "mfrs"
    ],
    "wof:name":"Casans Lounge Suites",
    "wof:placetype":"venue"
},
  "geometry": {"coordinates":[144.719055,-37.875446],"type":"Point"}
}