{
  "type": "Feature",
  "properties": {
    "iso:country":"AU",
    "sg:address":"Shop 8 Windsor Town Centre Kable St",
    "sg:city":"Windsor",
    "sg:classifiers":[
        {
            "category":"Personal",
            "subcategory":"Beauty Salon",
            "type":"Services"
        }
    ],
    "sg:phone":"+61 2 4577 3749",
    "sg:postcode":"2756",
    "sg:province":"NSW",
    "sg:tags":[
        "hairdresser"
    ],
    "wof:name":"Pure Indulgence",
    "wof:placetype":"venue"
},
  "geometry": {"coordinates":[150.821868897,-33.6063919067],"type":"Point"}
}