{
  "type": "Feature",
  "properties": {
    "addr:full":"700 Milpera St Tom Price WA 6751",
    "addr:housenumber":"700",
    "addr:postcode":"6751",
    "addr:street":"Milpera St",
    "iso:country":"AU",
    "sg:address":"700 Milpera St",
    "sg:city":"Tom Price",
    "sg:classifiers":[
        {
            "category":"Shopping",
            "subcategory":"Bicycles & Sporting Goods",
            "type":"Retail Goods"
        }
    ],
    "sg:phone":"+61 8 9189 2194",
    "sg:postcode":"6751",
    "sg:province":"WA",
    "sg:tags":[
        "chemical",
        "equipment",
        "pool",
        "swimming"
    ],
    "wof:name":"R & K Pool Supplies",
    "wof:placetype":"venue"
},
  "geometry": {"coordinates":[117.794692993,-22.6864547729],"type":"Point"}
}