{
  "type": "Feature",
  "properties": {
    "iso:country":"AU",
    "sg:address":"Unit 1/ 60 Fairford Rd",
    "sg:city":"Padstow",
    "sg:classifiers":[
        {
            "category":"Shopping",
            "subcategory":"Optical Goods",
            "type":"Retail Goods"
        }
    ],
    "sg:phone":"+61 2 9790 3119",
    "sg:postcode":"2211",
    "sg:province":"NSW",
    "sg:tags":[
        "supply"
    ],
    "wof:name":"Pro-laser Australia",
    "wof:placetype":"venue"
},
  "geometry": {"coordinates":[151.03627,-33.938194],"type":"Point"}
}