{
  "type": "Feature",
  "properties": {
    "iso:country":"AU",
    "sg:address":"10/ 53 Penkivil St",
    "sg:city":"Bondi",
    "sg:classifiers":[
        {
            "category":"Health Services",
            "subcategory":"Health Practitioner",
            "type":"Services"
        }
    ],
    "sg:phone":"+61 2 9389 0630",
    "sg:postcode":"2026",
    "sg:province":"NSW",
    "sg:tags":[
        "psychologist"
    ],
    "wof:name":"Withers Judith",
    "wof:placetype":"venue"
},
  "geometry": {"coordinates":[151.26124572800001,-33.8918190002],"type":"Point"}
}