{
  "type": "Feature",
  "properties": {
    "addr:full":"14 Brunker Rd Broadmeadow NSW 2292",
    "addr:housenumber":"14",
    "addr:postcode":"2292",
    "addr:street":"Brunker Rd",
    "iso:country":"AU",
    "sg:address":"14 Brunker Rd",
    "sg:city":"Broadmeadow",
    "sg:classifiers":[
        {
            "category":"Organizations",
            "subcategory":"Community Association",
            "type":"Services"
        }
    ],
    "sg:phone":"+61 2 4961 2423",
    "sg:postcode":"2292",
    "sg:province":"NSW",
    "sg:tags":[
        "organisation",
        "family",
        "welfare"
    ],
    "wof:name":"Hunter Aboriginal Childrens Service",
    "wof:placetype":"venue"
},
  "geometry": {"coordinates":[151.73628234899999,-32.9253234863],"type":"Point"}
}