{
  "type": "Feature",
  "properties": {
    "iso:country":"AU",
    "sg:address":"212 Aqueduct Rd St",
    "sg:city":"Helena",
    "sg:classifiers":[
        {
            "category":"Health Services",
            "subcategory":"Doctor",
            "type":"Services"
        }
    ],
    "sg:phone":"+61 3 9438 5666",
    "sg:postcode":"3088",
    "sg:province":"VIC",
    "sg:tags":[
        "medical",
        "practitioner"
    ],
    "wof:name":"Rose Gary",
    "wof:placetype":"venue"
},
  "geometry": {"coordinates":[145.13607788100001,-37.6846542358],"type":"Point"}
}