{
  "type": "Feature",
  "properties": {
    "addr:full":"345 King William St Adelaide SA 5000",
    "addr:housenumber":"345",
    "addr:postcode":"5000",
    "addr:street":"King William St",
    "iso:country":"AU",
    "sg:address":"345 King William St",
    "sg:city":"Adelaide",
    "sg:classifiers":[
        {
            "category":"Professional",
            "subcategory":"Management & Consulting",
            "type":"Services"
        }
    ],
    "sg:phone":"+61 8 8233 9050",
    "sg:postcode":"5000",
    "sg:province":"SA",
    "sg:tags":[
        "consultant"
    ],
    "wof:name":"NCML (Holdings) Limited",
    "wof:placetype":"venue"
},
  "geometry": {"coordinates":[138.59999084500001,-34.9325065613],"type":"Point"}
}