{
  "type": "Feature",
  "properties": {
    "iso:country":"AU",
    "sg:address":"216 South Pine Rd",
    "sg:city":"Enoggera",
    "sg:classifiers":[
        {
            "category":"Manufacturing",
            "subcategory":"Printing",
            "type":"Manufacturing & Wholesale Goods"
        }
    ],
    "sg:phone":"+61 7 3355 1173",
    "sg:postcode":"4051",
    "sg:province":"QLD",
    "sg:tags":[
        "wholesaler",
        "mfrs",
        "greeting",
        "card"
    ],
    "wof:name":"John Sands",
    "wof:placetype":"venue"
},
  "geometry": {"coordinates":[152.996185303,-27.4179229736],"type":"Point"}
}