{
  "type": "Feature",
  "properties": {
    "iso:country":"AU",
    "sg:address":"New South Head Rd",
    "sg:city":"Edgecliff",
    "sg:classifiers":[
        {
            "category":"Government",
            "subcategory":"Court House",
            "type":"Public Place"
        }
    ],
    "sg:phone":"+61 2 9363 4211",
    "sg:postcode":"2027",
    "sg:province":"NSW",
    "sg:tags":[
        "personal",
        "marriage",
        "family",
        "counselling"
    ],
    "wof:name":"Amex Drugstop",
    "wof:placetype":"venue"
},
  "geometry": {"coordinates":[151.23907470699999,-33.8790206909],"type":"Point"}
}