{
  "type": "Feature",
  "properties": {
    "addr:full":"941 Port Rd Cheltenham SA 5014",
    "addr:housenumber":"941",
    "addr:postcode":"5014",
    "addr:street":"Port Rd",
    "iso:country":"AU",
    "sg:address":"941 Port Rd",
    "sg:city":"Cheltenham",
    "sg:classifiers":[
        {
            "category":"Building & Trades",
            "subcategory":"Plumbing",
            "type":"Services"
        }
    ],
    "sg:phone":"+61 8 8444 7321",
    "sg:postcode":"5014",
    "sg:province":"SA",
    "sg:tags":[
        "plumber",
        "gasfitters"
    ],
    "wof:name":"SA Hot Water & Plumbing",
    "wof:placetype":"venue"
},
  "geometry": {"coordinates":[138.522872925,-34.8721466064],"type":"Point"}
}