{
  "type": "Feature",
  "properties": {
    "addr:full":"481 Milton Rd Auchenflower QLD 4066",
    "addr:housenumber":"481",
    "addr:postcode":"4066",
    "addr:street":"Milton Rd",
    "iso:country":"AU",
    "sg:address":"481 Milton Rd",
    "sg:city":"Auchenflower",
    "sg:classifiers":[
        {
            "category":"Professional",
            "subcategory":"Employment Agencies",
            "type":"Services"
        }
    ],
    "sg:phone":"+61 7 3870 4330",
    "sg:postcode":"4066",
    "sg:province":"QLD",
    "wof:name":"Specialist Project Staff Recruitment Pty Ltd",
    "wof:placetype":"venue"
},
  "geometry": {"coordinates":[152.99772644000001,-27.4720363617],"type":"Point"}
}