{
  "type": "Feature",
  "properties": {
    "addr:full":"18 Cavendish Ave Blacktown NSW 2148",
    "addr:housenumber":"18",
    "addr:postcode":"2148",
    "addr:street":"Cavendish Ave",
    "iso:country":"AU",
    "sg:address":"18 Cavendish Ave",
    "sg:city":"Blacktown",
    "sg:classifiers":[
        {
            "category":"Retail",
            "subcategory":"Auto Repair",
            "type":"Services"
        }
    ],
    "sg:phone":"+61 418 868 381",
    "sg:postcode":"2148",
    "sg:province":"NSW",
    "sg:tags":[
        "electrical"
    ],
    "wof:name":"Langford Auto Electrics Pty Ltd",
    "wof:placetype":"venue"
},
  "geometry": {"coordinates":[150.91827392600001,-33.7849578857],"type":"Point"}
}