{
  "type": "Feature",
  "properties": {
    "addr:full":"15 Bennett Pde Kew East VIC 3102",
    "addr:housenumber":"15",
    "addr:postcode":"3102",
    "addr:street":"Bennett Pde",
    "iso:country":"AU",
    "sg:address":"15 Bennett Pde",
    "sg:city":"Kew East",
    "sg:classifiers":[
        {
            "category":"Professional",
            "subcategory":"Accounting & Tax Preparation",
            "type":"Services"
        }
    ],
    "sg:phone":"+61 3 9859 5758",
    "sg:postcode":"3102",
    "sg:province":"VIC",
    "sg:tags":[
        "accountant",
        "auditor"
    ],
    "wof:name":"McLoughlin J J",
    "wof:placetype":"venue"
},
  "geometry": {"coordinates":[145.05976867699999,-37.7991600037],"type":"Point"}
}