{
  "type": "Feature",
  "properties": {
    "addr:full":"Unit 1/ 1 Cavendish St Mittagong NSW 2575",
    "addr:housenumber":"1",
    "addr:postcode":"2575",
    "addr:street":"Cavendish St",
    "iso:country":"AU",
    "sg:address":"Unit 1/ 1 Cavendish St",
    "sg:city":"Mittagong",
    "sg:classifiers":[
        {
            "category":"Professional",
            "subcategory":"Art Services",
            "type":"Services"
        }
    ],
    "sg:phone":"+61 2 4871 2121",
    "sg:postcode":"2575",
    "sg:province":"NSW",
    "sg:tags":[
        "picture",
        "frame",
        "framing"
    ],
    "wof:name":"Art & Picture Works Gallery",
    "wof:placetype":"venue"
},
  "geometry": {"coordinates":[150.43423461899999,-34.4474525452],"type":"Point"}
}