{
  "type": "Feature",
  "properties": {
    "addr:full":"Rear 66 Euston Rd Alexandria NSW 2015",
    "addr:housenumber":"66",
    "addr:postcode":"2015",
    "addr:street":"Euston Rd",
    "iso:country":"AU",
    "sg:address":"Rear 66 Euston Rd",
    "sg:city":"Alexandria",
    "sg:classifiers":[
        {
            "category":"Arts & Performance",
            "subcategory":"Theater",
            "type":"Entertainment"
        }
    ],
    "sg:phone":"+61 2 9550 6922",
    "sg:postcode":"2015",
    "sg:province":"NSW",
    "sg:tags":[
        "theatrical",
        "supply"
    ],
    "wof:name":"Opera Australia Props Hire",
    "wof:placetype":"venue"
},
  "geometry": {"coordinates":[151.19125366200001,-33.9069824219],"type":"Point"}
}