{
  "type": "Feature",
  "properties": {
    "addr:full":"36 Donald St South Hurstville NSW 2221",
    "addr:housenumber":"36",
    "addr:postcode":"2221",
    "addr:street":"Donald St",
    "iso:country":"AU",
    "sg:address":"36 Donald St",
    "sg:city":"South Hurstville",
    "sg:classifiers":[
        {
            "category":"Retail",
            "subcategory":"Storage",
            "type":"Services"
        }
    ],
    "sg:phone":"+61 2 9554 8651",
    "sg:postcode":"2221",
    "sg:province":"NSW",
    "sg:tags":[
        "removal",
        "furniture"
    ],
    "wof:name":"Miller Removals",
    "wof:placetype":"venue"
},
  "geometry": {"coordinates":[151.09852600100001,-33.9572563171],"type":"Point"}
}