{
  "type": "Feature",
  "properties": {
    "addr:full":"15 Springfield Ave Potts Point NSW 2011",
    "addr:housenumber":"15",
    "addr:postcode":"2011",
    "addr:street":"Springfield Ave",
    "iso:country":"AU",
    "sg:address":"15 Springfield Ave",
    "sg:city":"Potts Point",
    "sg:classifiers":[
        {
            "category":"Travel",
            "subcategory":"Hotels & Motels",
            "type":"Entertainment"
        }
    ],
    "sg:phone":"+61 2 9358 3122",
    "sg:postcode":"2011",
    "sg:province":"NSW",
    "sg:tags":[
        "accommodation"
    ],
    "wof:name":"Bernly Private Hotel",
    "wof:placetype":"venue"
},
  "geometry": {"coordinates":[151.223953247,-33.8725891113],"type":"Point"}
}