{
  "type": "Feature",
  "properties": {
    "addr:full":"Suite 1/ 9 The Ave Midland WA 6056",
    "addr:housenumber":"9",
    "addr:postcode":"6056",
    "addr:street":"The Ave",
    "iso:country":"AU",
    "sg:address":"Suite 1/ 9 The Ave",
    "sg:city":"Midland",
    "sg:classifiers":[
        {
            "category":"Health Services",
            "subcategory":"Dentist",
            "type":"Services"
        }
    ],
    "sg:phone":"+61 8 9250 1988",
    "sg:postcode":"6056",
    "sg:province":"WA",
    "wof:name":"Gorczynska Monika I Dr",
    "wof:placetype":"venue"
},
  "geometry": {"coordinates":[116.00498199499999,-31.8876914978],"type":"Point"}
}