{
  "type": "Feature",
  "properties": {
    "iso:country":"AU",
    "sg:address":"19 Ocean View Drv",
    "sg:city":"Alstonville",
    "sg:classifiers":[
        {
            "category":"Autos & Motor Vehicles",
            "subcategory":"Fuel & Gas Station",
            "type":"Retail Goods"
        }
    ],
    "sg:phone":"+61 2 6628 6199",
    "sg:postcode":"2477",
    "sg:province":"NSW",
    "sg:tags":[
        "injection",
        "diesel"
    ],
    "wof:name":"Anticoke Northern Rivers",
    "wof:placetype":"venue"
},
  "geometry": {"coordinates":[153.45384216299999,-28.8473358154],"type":"Point"}
}