{
  "type": "Feature",
  "properties": {
    "addr:full":"29 Broad St Croydon Park NSW 2133",
    "addr:housenumber":"29",
    "addr:postcode":"2133",
    "addr:street":"Broad St",
    "iso:country":"AU",
    "sg:address":"29 Broad St",
    "sg:city":"Croydon Park",
    "sg:classifiers":[
        {
            "category":"Social Services",
            "subcategory":"Child Care",
            "type":"Services"
        }
    ],
    "sg:phone":"+61 2 9744 1697",
    "sg:postcode":"2133",
    "sg:province":"NSW",
    "wof:name":"Croydon Park Cottage",
    "wof:placetype":"venue"
},
  "geometry": {"coordinates":[151.10191345199999,-33.8996543884],"type":"Point"}
}