{
  "type": "Feature",
  "properties": {
    "addr:full":"102- 104 Beaconsfield St Silverwater NSW 2128",
    "addr:housenumber":"104",
    "addr:postcode":"2128",
    "addr:street":"Beaconsfield St",
    "iso:country":"AU",
    "sg:address":"102- 104 Beaconsfield St",
    "sg:city":"Silverwater",
    "sg:classifiers":[
        {
            "category":"Shopping",
            "subcategory":"Computers & Home Electronics",
            "type":"Retail Goods"
        }
    ],
    "sg:phone":"+61 1300 130 336",
    "sg:postcode":"2128",
    "sg:province":"NSW",
    "sg:tags":[
        "hardware",
        "equipment"
    ],
    "wof:name":"BenQ Australia Pty Ltd",
    "wof:placetype":"venue"
},
  "geometry": {"coordinates":[151.03669738799999,-33.8374176025],"type":"Point"}
}