{
  "type": "Feature",
  "properties": {
    "addr:full":"36 Hayward Rd Ferntree Gully VIC 3156",
    "addr:housenumber":"36",
    "addr:postcode":"3156",
    "addr:street":"Hayward Rd",
    "iso:country":"AU",
    "sg:address":"36 Hayward Rd",
    "sg:city":"Ferntree Gully",
    "sg:classifiers":[
        {
            "category":"Autos & Motor Vehicles",
            "subcategory":"Auto Supplies",
            "type":"Retail Goods"
        }
    ],
    "sg:phone":"+61 3 9758 3886",
    "sg:postcode":"3156",
    "sg:province":"VIC",
    "sg:tags":[
        "part",
        "cycles",
        "accessory"
    ],
    "wof:name":"CityMotorbikes Motovert Pitracer Thumper MotoX Specialists",
    "wof:placetype":"venue"
},
  "geometry": {"coordinates":[145.265182495,-37.8792190552],"type":"Point"}
}