{
  "type": "Feature",
  "properties": {
    "addr:full":"Fact 10 /14- 26 Audsley St Clayton VIC 3168",
    "addr:housenumber":"10 / 14 26",
    "addr:postcode":"3168",
    "addr:street":"Fact;Audsley St",
    "iso:country":"AU",
    "sg:address":"Fact 10 /14- 26 Audsley St",
    "sg:city":"Clayton",
    "sg:classifiers":[
        {
            "category":"Building & Trades",
            "subcategory":"Cleaning & Sanitation",
            "type":"Services"
        }
    ],
    "sg:phone":"+61 3 9562 6113",
    "sg:postcode":"3168",
    "sg:province":"VIC",
    "sg:tags":[
        "asbestos",
        "treatment",
        "removal"
    ],
    "sg:website":"http://www.atstech.com.au",
    "wof:name":"ATS Australasian Technical Services Pty Ltd",
    "wof:placetype":"venue"
},
  "geometry": {"coordinates":[145.13021850600001,-37.9152908325],"type":"Point"}
}