{
  "type": "Feature",
  "properties": {
    "addr:full":"114 Lunga St Carina QLD 4152",
    "addr:housenumber":"114",
    "addr:postcode":"4152",
    "addr:street":"Lunga St",
    "iso:country":"AU",
    "sg:address":"114 Lunga St",
    "sg:city":"Carina",
    "sg:classifiers":[
        {
            "category":"Professional",
            "subcategory":"Accounting & Tax Preparation",
            "type":"Services"
        }
    ],
    "sg:phone":"+61 7 3395 3493",
    "sg:postcode":"4152",
    "sg:province":"QLD",
    "sg:tags":[
        "accountant",
        "auditor"
    ],
    "wof:name":"Colette Craig",
    "wof:placetype":"venue"
},
  "geometry": {"coordinates":[153.08860778799999,-27.4824256897],"type":"Point"}
}