{
  "type": "Feature",
  "properties": {
    "addr:full":"105 Soldiers Rd Harbord NSW 2096",
    "addr:housenumber":"105",
    "addr:postcode":"2096",
    "addr:street":"Soldiers Rd",
    "iso:country":"AU",
    "sg:address":"105 Soldiers Rd",
    "sg:city":"Harbord",
    "sg:classifiers":[
        {
            "category":"Building & Trades",
            "subcategory":"Construction",
            "type":"Services"
        }
    ],
    "sg:phone":"+61 2 9907 3307",
    "sg:postcode":"2096",
    "sg:province":"NSW",
    "sg:tags":[
        "contractor"
    ],
    "wof:name":"Metbuild Pty Ltd",
    "wof:placetype":"venue"
},
  "geometry": {"coordinates":[151.27882385300001,-33.7759056091],"type":"Point"}
}