{
  "type": "Feature",
  "properties": {
    "addr:full":"Kosciusko Rd Jindabyne NSW 2627",
    "addr:postcode":"2627",
    "addr:street":"Kosciusko Rd",
    "iso:country":"AU",
    "sg:address":"Kosciusko Rd",
    "sg:city":"Jindabyne",
    "sg:classifiers":[
        {
            "category":"Autos & Motor Vehicles",
            "subcategory":"Fuel & Gas Station",
            "type":"Retail Goods"
        }
    ],
    "sg:phone":"+61 2 6456 2127",
    "sg:postcode":"2627",
    "sg:province":"NSW",
    "wof:name":"BP Australia Limited",
    "wof:placetype":"venue"
},
  "geometry": {"coordinates":[148.62123107900001,-36.4253387451],"type":"Point"}
}