{
  "type": "Feature",
  "properties": {
    "addr:full":"Unit 1 8 Ives St Murarrie QLD 4172",
    "addr:housenumber":"8",
    "addr:postcode":"4172",
    "addr:street":"Ives St",
    "iso:country":"AU",
    "sg:address":"Unit 1 8 Ives St",
    "sg:city":"Murarrie",
    "sg:classifiers":[
        {
            "category":"Professional",
            "subcategory":"Employment Agencies",
            "type":"Services"
        }
    ],
    "sg:phone":"+61 7 3348 9899",
    "sg:postcode":"4172",
    "sg:province":"QLD",
    "sg:tags":[
        "broker",
        "custom"
    ],
    "wof:name":"International Trade Management Pty Ltd",
    "wof:placetype":"venue"
},
  "geometry": {"coordinates":[153.098144531,-27.4606018066],"type":"Point"}
}