{
  "type": "Feature",
  "properties": {
    "iso:country":"AU",
    "sg:address":"Portside Business Park 4",
    "sg:city":"Central Blv Port Melbourne",
    "sg:classifiers":[
        {
            "category":"Shopping",
            "subcategory":"Clothing, Apparel, & Fashions",
            "type":"Retail Goods"
        }
    ],
    "sg:phone":"+61 3 9644 2160",
    "sg:postcode":"3207",
    "sg:province":"VIC",
    "sg:tags":[
        "menswear"
    ],
    "wof:name":"Working For The Weekend",
    "wof:placetype":"venue"
},
  "geometry": {"coordinates":[144.918915,-37.822208],"type":"Point"}
}