{
  "type": "Feature",
  "properties": {
    "addr:full":"Newbridge-Laanecoorie Rd Newbridge VIC 3551",
    "addr:postcode":"3551",
    "addr:street":"Newbridge-Laanecoorie Rd",
    "iso:country":"AU",
    "sg:address":"Newbridge-Laanecoorie Rd",
    "sg:city":"Newbridge",
    "sg:classifiers":[
        {
            "category":"Retail",
            "subcategory":"Animal Services",
            "type":"Services"
        }
    ],
    "sg:phone":"+61 3 5438 7473",
    "sg:postcode":"3551",
    "sg:province":"VIC",
    "sg:tags":[
        "breeder",
        "sheep",
        "stud",
        "cattle"
    ],
    "wof:name":"Harris c Gloroy Poll Dorset Sheep Stud",
    "wof:placetype":"venue"
},
  "geometry": {"coordinates":[143.91339111299999,-36.7456665039],"type":"Point"}
}