{
  "type": "Feature",
  "properties": {
    "iso:country":"AU",
    "sg:address":"411 Burke Rd",
    "sg:city":"Glen Iris",
    "sg:classifiers":[
        {
            "category":"Professional",
            "subcategory":"Accounting & Tax Preparation",
            "type":"Services"
        }
    ],
    "sg:phone":"+61 3 9822 2862",
    "sg:postcode":"3146",
    "sg:province":"VIC",
    "sg:tags":[
        "accountant",
        "auditor"
    ],
    "wof:name":"Alan Coughlan",
    "wof:placetype":"venue"
},
  "geometry": {"coordinates":[145.05337524399999,-37.8477973938],"type":"Point"}
}