{
  "type": "Feature",
  "properties": {
    "addr:full":"14 Bannerman St Cremorne NSW 2090",
    "addr:housenumber":"14",
    "addr:postcode":"2090",
    "addr:street":"Bannerman St",
    "iso:country":"AU",
    "sg:address":"14 Bannerman St",
    "sg:city":"Cremorne",
    "sg:classifiers":[
        {
            "category":"Professional",
            "subcategory":"Art Services",
            "type":"Services"
        }
    ],
    "sg:phone":"+61 411 331 303",
    "sg:postcode":"2090",
    "sg:province":"NSW",
    "sg:tags":[
        "graphic",
        "designer"
    ],
    "wof:name":"ID Graphic Design",
    "wof:placetype":"venue"
},
  "geometry": {"coordinates":[151.22503662099999,-33.8368873596],"type":"Point"}
}