{
  "type": "Feature",
  "properties": {
    "iso:country":"AU",
    "sg:address":"21 Blackwood Crt",
    "sg:city":"Frankston South",
    "sg:classifiers":[
        {
            "category":"Retail",
            "subcategory":"Auto Repair",
            "type":"Services"
        }
    ],
    "sg:phone":"+61 3 5971 5068",
    "sg:postcode":"3199",
    "sg:province":"VIC",
    "sg:tags":[
        "repairer",
        "motor",
        "engineer"
    ],
    "wof:name":"Car Doctor",
    "wof:placetype":"venue"
},
  "geometry": {"coordinates":[145.14202880900001,-38.178062439],"type":"Point"}
}