{
  "type": "Feature",
  "properties": {
    "iso:country":"AU",
    "sg:address":"22 Dalton Pl",
    "sg:city":"Wilson",
    "sg:classifiers":[
        {
            "category":"Education",
            "subcategory":"School",
            "type":"Public Place"
        }
    ],
    "sg:phone":"+61 8 9458 3637",
    "sg:postcode":"6107",
    "sg:province":"WA",
    "wof:name":"Rehoboth Christian Primary School",
    "wof:placetype":"venue"
},
  "geometry": {"coordinates":[115.913619995,-32.0139045715],"type":"Point"}
}