{
  "type": "Feature",
  "properties": {
    "addr:full":"4 Norman St Peakhurst NSW 2210",
    "addr:housenumber":"4",
    "addr:postcode":"2210",
    "addr:street":"Norman St",
    "iso:country":"AU",
    "sg:address":"4 Norman St",
    "sg:city":"Peakhurst",
    "sg:classifiers":[
        {
            "category":"Wholesale",
            "subcategory":"Machinery & Supplies",
            "type":"Manufacturing & Wholesale Goods"
        }
    ],
    "sg:phone":"+61 2 9534 5033",
    "sg:postcode":"2210",
    "sg:province":"NSW",
    "sg:tags":[
        "equipment",
        "system",
        "elevating",
        "conveying"
    ],
    "wof:name":"Leon K Engineering Co Pty Ltd",
    "wof:placetype":"venue"
},
  "geometry": {"coordinates":[151.066956,-33.963196],"type":"Point"}
}