{
  "type": "Feature",
  "properties": {
    "addr:full":"693 Station St Box Hill VIC 3128",
    "addr:housenumber":"693",
    "addr:postcode":"3128",
    "addr:street":"Station St",
    "iso:country":"AU",
    "sg:address":"693 Station St",
    "sg:city":"Box Hill",
    "sg:classifiers":[
        {
            "category":"Sports & Exercise",
            "subcategory":"Ski Slope",
            "type":"Entertainment"
        }
    ],
    "sg:phone":"+61 3 9897 4200",
    "sg:postcode":"3128",
    "sg:province":"VIC",
    "sg:tags":[
        "equipment",
        "hire",
        "retail",
        "snow"
    ],
    "wof:name":"Box Hill Skate Ski & Surf",
    "wof:placetype":"venue"
},
  "geometry": {"coordinates":[145.12384033199999,-37.8176460266],"type":"Point"}
}