{
  "type": "Feature",
  "properties": {
    "addr:full":"46 Fitzgerald Rd Morley WA 6062",
    "addr:housenumber":"46",
    "addr:postcode":"6062",
    "addr:street":"Fitzgerald Rd",
    "iso:country":"AU",
    "sg:address":"46 Fitzgerald Rd",
    "sg:city":"Morley",
    "sg:classifiers":[
        {
            "category":"Shopping",
            "subcategory":"Clothing, Apparel, & Fashions",
            "type":"Retail Goods"
        }
    ],
    "sg:phone":"+61 411 727 664",
    "sg:postcode":"6062",
    "sg:province":"WA",
    "sg:tags":[
        "lingerie",
        "hosiery",
        "sleepwear"
    ],
    "wof:name":"Lovett Lingerie",
    "wof:placetype":"venue"
},
  "geometry": {"coordinates":[115.909538269,-31.8889503479],"type":"Point"}
}