{
  "type": "Feature",
  "properties": {
    "iso:country":"AU",
    "sg:address":"85 Station St",
    "sg:city":"Aspendale",
    "sg:classifiers":[
        {
            "category":"Building & Trades",
            "subcategory":"Construction",
            "type":"Services"
        }
    ],
    "sg:phone":"+61 416 083 711",
    "sg:postcode":"3195",
    "sg:province":"VIC",
    "sg:tags":[
        "contractor"
    ],
    "wof:name":"Hogan K",
    "wof:placetype":"venue"
},
  "geometry": {"coordinates":[145.09927368199999,-38.0220336914],"type":"Point"}
}