{
  "type": "Feature",
  "properties": {
    "iso:country":"AU",
    "sg:address":"324a Military Rd",
    "sg:city":"Cremorne",
    "sg:classifiers":[
        {
            "category":"Shopping",
            "subcategory":"Clothing, Apparel, & Fashions",
            "type":"Retail Goods"
        }
    ],
    "sg:phone":"+61 2 9953 9519",
    "sg:postcode":"2090",
    "sg:province":"NSW",
    "sg:tags":[
        "recycled",
        "clothing"
    ],
    "wof:name":"St Vincent De Paul Society",
    "wof:placetype":"venue"
},
  "geometry": {"coordinates":[151.22764587399999,-33.8294525146],"type":"Point"}
}