{
  "type": "Feature",
  "properties": {
    "addr:full":"365 Racecourse Rd Sunbury VIC 3429",
    "addr:housenumber":"365",
    "addr:postcode":"3429",
    "addr:street":"Racecourse Rd",
    "iso:country":"AU",
    "sg:address":"365 Racecourse Rd",
    "sg:city":"Sunbury",
    "sg:classifiers":[
        {
            "category":"Utilities",
            "subcategory":"Electric",
            "type":"Services"
        }
    ],
    "sg:phone":"+61 408 565 842",
    "sg:postcode":"3429",
    "sg:province":"VIC",
    "sg:tags":[
        "electrical",
        "contractor"
    ],
    "wof:name":"Telfer Electrical & Communications Pty Ltd",
    "wof:placetype":"venue"
},
  "geometry": {"coordinates":[144.73471069300001,-37.5488548279],"type":"Point"}
}