{
  "type": "Feature",
  "properties": {
    "iso:country":"AU",
    "sg:address":"PO Box 218",
    "sg:city":"Stanthorpe",
    "sg:classifiers":[
        {
            "category":"Farming",
            "subcategory":"Farm & Veterinary Services",
            "type":"Manufacturing & Wholesale Goods"
        }
    ],
    "sg:phone":"+61 7 4683 5240",
    "sg:postcode":"4380",
    "sg:province":"QLD",
    "sg:tags":[
        "irrigation",
        "reticulation",
        "system"
    ],
    "wof:name":"IRI-Master",
    "wof:placetype":"venue"
},
  "geometry": {"coordinates":[151.940201,-28.65159],"type":"Point"}
}