{
  "type": "Feature",
  "properties": {
    "addr:full":"190 Argyle St Hobart TAS 7000",
    "addr:housenumber":"190",
    "addr:postcode":"7000",
    "addr:street":"Argyle St",
    "iso:country":"AU",
    "sg:address":"190 Argyle St",
    "sg:city":"Hobart",
    "sg:classifiers":[
        {
            "category":"Utilities",
            "subcategory":"Electric",
            "type":"Services"
        }
    ],
    "sg:phone":"+61 1800 429 423",
    "sg:postcode":"7000",
    "sg:province":"TAS",
    "sg:tags":[
        "element"
    ],
    "wof:name":"Stokes Synertec",
    "wof:placetype":"venue"
},
  "geometry": {"coordinates":[147.31785583499999,-42.8740272522],"type":"Point"}
}