{
  "type": "Feature",
  "properties": {
    "iso:country":"AU",
    "sg:address":"Day Ave",
    "sg:city":"Omeo",
    "sg:classifiers":[
        {
            "category":"Fast Food",
            "type":"Food & Drink"
        }
    ],
    "sg:phone":"+61 3 5159 1272",
    "sg:postcode":"3898",
    "sg:province":"VIC",
    "sg:tags":[
        "away",
        "take"
    ],
    "wof:name":"The Olde Country Kitchen",
    "wof:placetype":"venue"
},
  "geometry": {"coordinates":[147.595306397,-37.0964851379],"type":"Point"}
}