{
  "type": "Feature",
  "properties": {
    "iso:country":"AU",
    "sg:address":"PO Box 238",
    "sg:city":"Budgewoi",
    "sg:classifiers":[
        {
            "category":"Building & Trades",
            "subcategory":"Construction",
            "type":"Services"
        }
    ],
    "sg:phone":"+61 2 4390 8545",
    "sg:postcode":"2262",
    "sg:province":"NSW",
    "sg:tags":[
        "scaffolding"
    ],
    "wof:name":"AJ Highrise Scaffolding Pty Ltd",
    "wof:placetype":"venue"
},
  "geometry": {"coordinates":[151.548935,-33.232632],"type":"Point"}
}