{
  "type": "Feature",
  "properties": {
    "addr:full":"Shop 5 1 Grice Ave Paradise Point QLD 4216",
    "addr:housenumber":"shop;1",
    "addr:postcode":"4216",
    "addr:street":"Grice Ave",
    "iso:country":"AU",
    "sg:address":"Shop 5 1 Grice Ave",
    "sg:city":"Paradise Point",
    "sg:classifiers":[
        {
            "category":"Cafe",
            "type":"Food & Drink"
        }
    ],
    "sg:phone":"+61 7 5577 2573",
    "sg:postcode":"4216",
    "sg:province":"QLD",
    "wof:name":"Caffe Kamocha",
    "wof:placetype":"venue"
},
  "geometry": {"coordinates":[153.394454956,-27.8866157532],"type":"Point"}
}