{
  "type": "Feature",
  "properties": {
    "addr:full":"4 Bergen Way Mindarie WA 6030",
    "addr:housenumber":"4",
    "addr:postcode":"6030",
    "addr:street":"Bergen Way",
    "iso:country":"AU",
    "sg:address":"4 Bergen Way",
    "sg:city":"Mindarie",
    "sg:classifiers":[
        {
            "category":"Shopping",
            "subcategory":"Clothing, Apparel, & Fashions",
            "type":"Retail Goods"
        }
    ],
    "sg:phone":"+61 8 9304 4114",
    "sg:postcode":"6030",
    "sg:province":"WA",
    "sg:tags":[
        "sportswear"
    ],
    "wof:name":"Northern Surf",
    "wof:placetype":"venue"
},
  "geometry": {"coordinates":[115.713516235,-31.6758747101],"type":"Point"}
}