{
  "type": "Feature",
  "properties": {
    "addr:full":"18 Anthony Drv Rosemeadow NSW 2560",
    "addr:housenumber":"18",
    "addr:postcode":"2560",
    "addr:street":"Anthony Drv",
    "iso:country":"AU",
    "sg:address":"18 Anthony Drv",
    "sg:city":"Rosemeadow",
    "sg:classifiers":[
        {
            "category":"Professional",
            "subcategory":"Art Services",
            "type":"Services"
        }
    ],
    "sg:phone":"+61 2 4628 7391",
    "sg:postcode":"2560",
    "sg:province":"NSW",
    "sg:tags":[
        "graphic",
        "designer"
    ],
    "wof:name":"R.J.S Graphics",
    "wof:placetype":"venue"
},
  "geometry": {"coordinates":[150.79156494099999,-34.0990447998],"type":"Point"}
}