{
  "type": "Feature",
  "properties": {
    "addr:full":"32 Argyle St Breakfast Creek QLD 4010",
    "addr:housenumber":"32",
    "addr:postcode":"4010",
    "addr:street":"Argyle St",
    "iso:country":"AU",
    "sg:address":"32 Argyle St",
    "sg:city":"Breakfast Creek",
    "sg:classifiers":[
        {
            "category":"Manufacturing",
            "subcategory":"Glass & Minerals",
            "type":"Manufacturing & Wholesale Goods"
        }
    ],
    "sg:phone":"+61 7 3262 7875",
    "sg:postcode":"4010",
    "sg:province":"QLD",
    "sg:tags":[
        "repair",
        "fibreglass",
        "product"
    ],
    "wof:name":"Breakfast Creek Slipways",
    "wof:placetype":"venue"
},
  "geometry": {"coordinates":[153.04226684599999,-27.441116333],"type":"Point"}
}