{
  "type": "Feature",
  "properties": {
    "addr:full":"Unit 1/ 30 Piper Drv Ballina NSW 2478",
    "addr:housenumber":"30",
    "addr:postcode":"2478",
    "addr:street":"Piper Drv",
    "iso:country":"AU",
    "sg:address":"Unit 1/ 30 Piper Drv",
    "sg:city":"Ballina",
    "sg:classifiers":[
        {
            "category":"Food & Beverages",
            "subcategory":"Fruits & Vegetables",
            "type":"Retail Goods"
        }
    ],
    "sg:phone":"+61 2 6681 6461",
    "sg:postcode":"2478",
    "sg:province":"NSW",
    "sg:tags":[
        "consultant",
        "catering"
    ],
    "wof:name":"Pipers Catering",
    "wof:placetype":"venue"
},
  "geometry": {"coordinates":[153.55714416500001,-28.8477230072],"type":"Point"}
}