{
  "type": "Feature",
  "properties": {
    "addr:full":"11 Beverley Rd McCrae VIC 3938",
    "addr:housenumber":"11",
    "addr:postcode":"3938",
    "addr:street":"Beverley Rd",
    "iso:country":"AU",
    "sg:address":"11 Beverley Rd",
    "sg:city":"McCrae",
    "sg:classifiers":[
        {
            "category":"Communications",
            "subcategory":"News Services",
            "type":"Services"
        }
    ],
    "sg:phone":"+61 3 5981 2866",
    "sg:postcode":"3938",
    "sg:province":"VIC",
    "sg:tags":[
        "information",
        "tourist",
        "attractions"
    ],
    "wof:name":"National Trust Of Australia (Victoria)",
    "wof:placetype":"venue"
},
  "geometry": {"coordinates":[144.93084716800001,-38.3496398926],"type":"Point"}
}