{
  "type": "Feature",
  "properties": {
    "iso:country":"AU",
    "sg:address":"Corner Daly St",
    "sg:city":"& Dashwood Place Darwin",
    "sg:classifiers":[
        {
            "category":"Retail",
            "subcategory":"Auto Repair",
            "type":"Services"
        }
    ],
    "sg:phone":"+61 8 8981 5249",
    "sg:postcode":"0800",
    "sg:province":"NT",
    "sg:tags":[
        "electrical"
    ],
    "wof:name":"City Autos",
    "wof:placetype":"venue"
},
  "geometry": {"coordinates":[130.83786010700001,-12.4560604095],"type":"Point"}
}