{
  "type": "Feature",
  "properties": {
    "addr:full":"23 Mildura St Fyshwick ACT 2609",
    "addr:housenumber":"23",
    "addr:postcode":"2609",
    "addr:street":"Mildura St",
    "iso:country":"AU",
    "sg:address":"23 Mildura St",
    "sg:city":"Fyshwick",
    "sg:classifiers":[
        {
            "category":"Professional",
            "type":"Services"
        }
    ],
    "sg:phone":"+61 1300 366 684",
    "sg:postcode":"2609",
    "sg:province":"ACT",
    "sg:tags":[
        "transport"
    ],
    "wof:name":"Toll IPEC",
    "wof:placetype":"venue"
},
  "geometry": {"coordinates":[149.15570068400001,-35.3229866028],"type":"Point"}
}