{
  "type": "Feature",
  "properties": {
    "iso:country":"AU",
    "sg:address":"28 George Mason Drv",
    "sg:city":"Wellington",
    "sg:classifiers":[
        {
            "category":"Professional",
            "type":"Services"
        }
    ],
    "sg:phone":"+61 8 8572 7110",
    "sg:postcode":"5259",
    "sg:province":"SA",
    "sg:tags":[
        "transport"
    ],
    "wof:name":"Lower Murray Haulage",
    "wof:placetype":"venue"
},
  "geometry": {"coordinates":[139.394165039,-35.3226203918],"type":"Point"}
}