{
  "type": "Feature",
  "properties": {
    "iso:country":"AU",
    "sg:address":"52 Herries St",
    "sg:city":"Toowoomba",
    "sg:classifiers":[
        {
            "category":"Retail",
            "subcategory":"Funeral Services",
            "type":"Services"
        }
    ],
    "sg:phone":"+61 7 4632 4211",
    "sg:postcode":"4350",
    "sg:province":"QLD",
    "sg:tags":[
        "cremation"
    ],
    "wof:name":"Hiram Philp Funerals",
    "wof:placetype":"venue"
},
  "geometry": {"coordinates":[151.938751,-27.562353],"type":"Point"}
}