{
  "type": "Feature",
  "properties": {
    "iso:country":"AU",
    "sg:address":"56 Kennington Rd",
    "sg:city":"Camp Hill",
    "sg:classifiers":[
        {
            "category":"Utilities",
            "subcategory":"Water",
            "type":"Services"
        }
    ],
    "sg:phone":"+61 7 3398 4455",
    "sg:postcode":"4152",
    "sg:province":"QLD",
    "sg:tags":[
        "cartage"
    ],
    "wof:name":"Craigs Carrying",
    "wof:placetype":"venue"
},
  "geometry": {"coordinates":[153.08599853499999,-27.4910373688],"type":"Point"}
}