{
  "type": "Feature",
  "properties": {
    "addr:full":"Level 1, Garden Medical Centre 612 Wodonga Pl Albury NSW 2640",
    "addr:housenumber":"612",
    "addr:postcode":"2640",
    "addr:street":"Pl",
    "iso:country":"AU",
    "sg:address":"Level 1, Garden Medical Centre 612 Wodonga Pl",
    "sg:city":"Albury",
    "sg:classifiers":[
        {
            "category":"Health Services",
            "subcategory":"Optometrist",
            "type":"Services"
        }
    ],
    "sg:phone":"+61 2 6041 6111",
    "sg:postcode":"2640",
    "sg:province":"NSW",
    "wof:name":"Eyecare Plus Optometrists",
    "wof:placetype":"venue"
},
  "geometry": {"coordinates":[146.91526794399999,-36.0804824829],"type":"Point"}
}