{
  "type": "Feature",
  "properties": {
    "iso:country":"AU",
    "sg:address":"156- 158 Maurice Rd",
    "sg:city":"Murray Bridge",
    "sg:classifiers":[
        {
            "category":"Social Services",
            "subcategory":"Adult Care",
            "type":"Services"
        }
    ],
    "sg:phone":"+61 417 882 049",
    "sg:postcode":"5253",
    "sg:province":"SA",
    "sg:tags":[
        "towing"
    ],
    "wof:name":"Bridge Towing Service",
    "wof:placetype":"venue"
},
  "geometry": {"coordinates":[139.249923706,-35.1191444397],"type":"Point"}
}