{
  "type": "Feature",
  "properties": {
    "addr:full":"Shp 45/ 200 Mirrabooka Ave Alexander Heights WA 6064",
    "addr:housenumber":"45 / 200",
    "addr:postcode":"6064",
    "addr:street":"Mirrabooka Ave",
    "iso:country":"AU",
    "sg:address":"Shp 45/ 200 Mirrabooka Ave",
    "sg:city":"Alexander Heights",
    "sg:classifiers":[
        {
            "category":"Personal",
            "subcategory":"Hair Removal",
            "type":"Services"
        }
    ],
    "sg:phone":"+61 8 9343 7319",
    "sg:postcode":"6064",
    "sg:province":"WA",
    "wof:name":"D&#039;Luxxe Beauty",
    "wof:placetype":"venue"
},
  "geometry": {"coordinates":[115.852577209,-31.8299236298],"type":"Point"}
}