{
  "type": "Feature",
  "properties": {
    "addr:full":"636 King St Newtown NSW 2042",
    "addr:housenumber":"636",
    "addr:postcode":"2042",
    "addr:street":"King St",
    "iso:country":"AU",
    "sg:address":"636 King St",
    "sg:city":"Newtown",
    "sg:classifiers":[
        {
            "category":"Real Estate",
            "subcategory":"Real Estate Agent",
            "type":"Services"
        }
    ],
    "sg:phone":"+61 2 9565 2188",
    "sg:postcode":"2042",
    "sg:province":"NSW",
    "wof:name":"Catania Medrano Real Estate Pty Ltd",
    "wof:placetype":"venue"
},
  "geometry": {"coordinates":[151.18092300000001,-33.905285],"type":"Point"}
}