{
  "type": "Feature",
  "properties": {
    "addr:full":"41 Loco St Seymour VIC 3660",
    "addr:housenumber":"41",
    "addr:postcode":"3660",
    "addr:street":"Loco St",
    "iso:country":"AU",
    "sg:address":"41 Loco St",
    "sg:city":"Seymour",
    "sg:classifiers":[
        {
            "category":"Cafe",
            "type":"Food & Drink"
        }
    ],
    "sg:phone":"+61 3 5792 1436",
    "sg:postcode":"3660",
    "sg:province":"VIC",
    "wof:name":"Caravan Cafe",
    "wof:placetype":"venue"
},
  "geometry": {"coordinates":[145.14308166500001,-37.0297164917],"type":"Point"}
}