{
  "type": "Feature",
  "properties": {
    "iso:country":"AU",
    "sg:address":"3 King William St",
    "sg:city":"Bayswater",
    "sg:classifiers":[
        {
            "category":"Real Estate",
            "subcategory":"Real Estate Agent",
            "type":"Services"
        }
    ],
    "sg:phone":"+61 8 9272 8411",
    "sg:postcode":"6053",
    "sg:province":"WA",
    "wof:name":"Carters Real Estate (Bayswater)",
    "wof:placetype":"venue"
},
  "geometry": {"coordinates":[115.912109375,-31.9188137054],"type":"Point"}
}