{
  "type": "Feature",
  "properties": {
    "addr:full":"569 Magill Rd Magill SA 5072",
    "addr:housenumber":"569",
    "addr:postcode":"5072",
    "addr:street":"Magill Rd",
    "iso:country":"AU",
    "sg:address":"569 Magill Rd",
    "sg:city":"Magill",
    "sg:classifiers":[
        {
            "category":"Professional",
            "subcategory":"Business Services",
            "type":"Services"
        }
    ],
    "sg:phone":"+61 8 8332 1166",
    "sg:postcode":"5072",
    "sg:province":"SA",
    "sg:tags":[
        "broker"
    ],
    "wof:name":"Business Interests",
    "wof:placetype":"venue"
},
  "geometry": {"coordinates":[138.67135620100001,-34.9131317139],"type":"Point"}
}