{
  "type": "Feature",
  "properties": {
    "iso:country":"AU",
    "sg:address":"4 bridge St",
    "sg:city":"Pymble",
    "sg:classifiers":[
        {
            "category":"Professional",
            "subcategory":"Lawyer & Legal Services",
            "type":"Services"
        }
    ],
    "sg:phone":"+61 2 9440 1202",
    "sg:postcode":"2073",
    "sg:province":"NSW",
    "sg:tags":[
        "wills",
        "probate",
        "estate"
    ],
    "wof:name":"Fox & Staniland Lawyers",
    "wof:placetype":"venue"
},
  "geometry": {"coordinates":[151.14578247099999,-33.7495536804],"type":"Point"}
}