{
  "type": "Feature",
  "properties": {
    "addr:full":"Lvl 1/ 302 Waverley Rd Malvern East VIC 3145",
    "addr:housenumber":"/ 302",
    "addr:postcode":"3145",
    "addr:street":"Waverley Rd",
    "iso:country":"AU",
    "sg:address":"Lvl 1/ 302 Waverley Rd",
    "sg:city":"Malvern East",
    "sg:classifiers":[
        {
            "category":"Professional",
            "subcategory":"Engineering",
            "type":"Services"
        }
    ],
    "sg:phone":"+61 3 9571 0244",
    "sg:postcode":"3145",
    "sg:province":"VIC",
    "sg:tags":[
        "consulting",
        "engineer"
    ],
    "wof:name":"Ecological Engineering Pty Ltd",
    "wof:placetype":"venue"
},
  "geometry": {"coordinates":[145.05824279800001,-37.8773155212],"type":"Point"}
}