{
  "type": "Feature",
  "properties": {
    "addr:full":"420- 426 Mt Cotton Rd Capalaba QLD 4157",
    "addr:housenumber":"420 426",
    "addr:postcode":"4157",
    "addr:street":"Mt Cotton Rd",
    "iso:country":"AU",
    "sg:address":"420- 426 Mt Cotton Rd",
    "sg:city":"Capalaba",
    "sg:classifiers":[
        {
            "category":"Autos & Motor Vehicles",
            "subcategory":"Fuel & Gas Station",
            "type":"Retail Goods"
        }
    ],
    "sg:phone":"+61 7 3823 5638",
    "sg:postcode":"4157",
    "sg:province":"QLD",
    "wof:name":"Plus Petrol",
    "wof:placetype":"venue"
},
  "geometry": {"coordinates":[153.206665039,-27.5636425018],"type":"Point"}
}