{
  "type": "Feature",
  "properties": {
    "addr:full":"261 Hume St Toowoomba QLD 4350",
    "addr:housenumber":"261",
    "addr:postcode":"4350",
    "addr:street":"Hume St",
    "iso:country":"AU",
    "sg:address":"261 Hume St",
    "sg:city":"Toowoomba",
    "sg:classifiers":[
        {
            "category":"Personal",
            "subcategory":"Beauty Salon",
            "type":"Services"
        }
    ],
    "sg:phone":"+61 7 4638 3623",
    "sg:postcode":"4350",
    "sg:province":"QLD",
    "sg:tags":[
        "hairdresser"
    ],
    "wof:name":"Zigbi's Hair Stylists",
    "wof:placetype":"venue"
},
  "geometry": {"coordinates":[151.95524599999999,-27.575266],"type":"Point"}
}