{
  "type": "Feature",
  "properties": {
    "iso:country":"AU",
    "sg:address":"56 Thurlow St",
    "sg:city":"Riverwood",
    "sg:classifiers":[
        {
            "category":"Food & Beverages",
            "subcategory":"Fruits & Vegetables",
            "type":"Retail Goods"
        }
    ],
    "sg:phone":"+61 2 9153 8329",
    "sg:postcode":"2210",
    "sg:province":"NSW",
    "sg:tags":[
        "consultant",
        "catering"
    ],
    "wof:name":"Nassif Holdings",
    "wof:placetype":"venue"
},
  "geometry": {"coordinates":[151.054413,-33.951336],"type":"Point"}
}