{
  "type": "Feature",
  "properties": {
    "addr:full":"6/ 19-23 Marlo Rd Cronulla NSW 2230",
    "addr:housenumber":"/ 19-23",
    "addr:postcode":"2230",
    "addr:street":"Marlo Rd",
    "iso:country":"AU",
    "sg:address":"6/ 19-23 Marlo Rd",
    "sg:city":"Cronulla",
    "sg:classifiers":[
        {
            "category":"Government",
            "subcategory":"Court House",
            "type":"Public Place"
        }
    ],
    "sg:phone":"+61 2 9527 5550",
    "sg:postcode":"2230",
    "sg:province":"NSW",
    "sg:tags":[
        "personal",
        "marriage",
        "family",
        "counselling"
    ],
    "wof:name":"Cronulla Professional Counselling Services",
    "wof:placetype":"venue"
},
  "geometry": {"coordinates":[151.154006958,-34.0475082397],"type":"Point"}
}