{
  "type": "Feature",
  "properties": {
    "iso:country":"AU",
    "sg:address":"16 Gatenby St",
    "sg:city":"Cressy",
    "sg:classifiers":[
        {
            "category":"Building & Trades",
            "subcategory":"Construction",
            "type":"Services"
        }
    ],
    "sg:phone":"+61 3 6397 6361",
    "sg:postcode":"7302",
    "sg:province":"TAS",
    "sg:tags":[
        "contractor"
    ],
    "wof:name":"Thompson G N",
    "wof:placetype":"venue"
},
  "geometry": {"coordinates":[147.081832886,-41.6847229004],"type":"Point"}
}