{
  "type": "Feature",
  "properties": {
    "addr:full":"40 Washington St Essendon VIC 3040",
    "addr:housenumber":"40",
    "addr:postcode":"3040",
    "addr:street":"Washington St",
    "iso:country":"AU",
    "sg:address":"40 Washington St",
    "sg:city":"Essendon",
    "sg:classifiers":[
        {
            "category":"Building & Trades",
            "subcategory":"Plumbing",
            "type":"Services"
        }
    ],
    "sg:phone":"+61 418 384 614",
    "sg:postcode":"3040",
    "sg:province":"VIC",
    "sg:tags":[
        "plumber",
        "gasfitters"
    ],
    "wof:name":"BV's Plumbing",
    "wof:placetype":"venue"
},
  "geometry": {"coordinates":[144.91017150900001,-37.7526245117],"type":"Point"}
}