{
  "type": "Feature",
  "properties": {
    "iso:country":"AU",
    "sg:address":"7- 19 Tikalara St",
    "sg:city":"Regency Park",
    "sg:classifiers":[
        {
            "category":"Wholesale",
            "subcategory":"Machinery & Supplies",
            "type":"Manufacturing & Wholesale Goods"
        }
    ],
    "sg:phone":"+61 8 8340 1066",
    "sg:postcode":"5010",
    "sg:province":"SA",
    "sg:tags":[
        "engineer"
    ],
    "wof:name":"Blackwood J & Son Ltd",
    "wof:placetype":"venue"
},
  "geometry": {"coordinates":[138.57304382300001,-34.8681793213],"type":"Point"}
}