{
  "type": "Feature",
  "properties": {
    "addr:full":"93 Cimitiere St Launceston TAS 7250",
    "addr:housenumber":"93",
    "addr:postcode":"7250",
    "addr:street":"Cimitiere St",
    "iso:country":"AU",
    "sg:address":"93 Cimitiere St",
    "sg:city":"Launceston",
    "sg:classifiers":[
        {
            "category":"Home & Garden",
            "subcategory":"Furniture",
            "type":"Retail Goods"
        }
    ],
    "sg:phone":"+61 3 6334 2264",
    "sg:postcode":"7250",
    "sg:province":"TAS",
    "sg:tags":[
        "business"
    ],
    "wof:name":"Launceston Salvage Co",
    "wof:placetype":"venue"
},
  "geometry": {"coordinates":[147.13902282699999,-41.4338188171],"type":"Point"}
}