{
  "type": "Feature",
  "properties": {
    "addr:full":"Suite, 3 199 Gympie Tce Noosaville QLD 4566",
    "addr:housenumber":"199",
    "addr:postcode":"4566",
    "addr:street":"Gympie Tce",
    "iso:country":"AU",
    "sg:address":"Suite, 3 199",
    "sg:city":"Gympie Tce Noosaville",
    "sg:classifiers":[
        {
            "category":"Personal",
            "subcategory":"Massage",
            "type":"Services"
        }
    ],
    "sg:phone":"+61 7 5474 4311",
    "sg:postcode":"4566",
    "sg:province":"QLD",
    "sg:tags":[
        "therapy"
    ],
    "wof:name":"Pure Health Lifestyle & Balance",
    "wof:placetype":"venue"
},
  "geometry": {"coordinates":[153.061935425,-26.3983459473],"type":"Point"}
}