{
  "type": "Feature",
  "properties": {
    "addr:full":"13 Tathra St Gosford West NSW 2250",
    "addr:housenumber":"13",
    "addr:postcode":"2250",
    "addr:street":"Tathra St",
    "iso:country":"AU",
    "sg:address":"13 Tathra St",
    "sg:city":"Gosford West",
    "sg:classifiers":[
        {
            "category":"Wholesale",
            "subcategory":"Metals & Minerals",
            "type":"Manufacturing & Wholesale Goods"
        }
    ],
    "sg:phone":"+61 2 4324 5449",
    "sg:postcode":"2250",
    "sg:province":"NSW",
    "sg:tags":[
        "steel",
        "stainless",
        "product",
        "equipment"
    ],
    "wof:name":"J. C. Design Pty Ltd.",
    "wof:placetype":"venue"
},
  "geometry": {"coordinates":[151.318069458,-33.4178733826],"type":"Point"}
}