{
  "type": "Feature",
  "properties": {
    "addr:full":"Cnr Havelock & Bugg Sts Smithton TAS 7330",
    "addr:postcode":"7330",
    "iso:country":"AU",
    "sg:address":"Cnr Havelock & Bugg Sts",
    "sg:city":"Smithton",
    "sg:classifiers":[
        {
            "category":"Sports & Exercise",
            "subcategory":"Sports Center",
            "type":"Entertainment"
        }
    ],
    "sg:phone":"+61 3 6452 3033",
    "sg:postcode":"7330",
    "sg:province":"TAS",
    "sg:tags":[
        "ground"
    ],
    "wof:name":"Band-Room Sports Complex",
    "wof:placetype":"venue"
},
  "geometry": {"coordinates":[145.12150600000001,-40.845318],"type":"Point"}
}