{
  "type": "Feature",
  "properties": {
    "addr:full":"72 Main Rd Woodside SA 5244",
    "addr:housenumber":"72",
    "addr:postcode":"5244",
    "addr:street":"Main Rd",
    "iso:country":"AU",
    "sg:address":"72 Main Rd",
    "sg:city":"Woodside",
    "sg:classifiers":[
        {
            "category":"Autos & Motor Vehicles",
            "subcategory":"Fuel & Gas Station",
            "type":"Retail Goods"
        }
    ],
    "sg:phone":"+61 8 8389 7268",
    "sg:postcode":"5244",
    "sg:province":"SA",
    "wof:name":"Mobil Oil Australia Pty Ltd",
    "wof:placetype":"venue"
},
  "geometry": {"coordinates":[138.91192626899999,-35.0358200073],"type":"Point"}
}