{
  "type": "Feature",
  "properties": {
    "addr:full":"Level 1/ 8 First Ave Blacktown NSW 2148",
    "addr:housenumber":"/ 8",
    "addr:postcode":"2148",
    "addr:street":"First Ave",
    "iso:country":"AU",
    "sg:address":"Level 1/ 8 First Ave",
    "sg:city":"Blacktown",
    "sg:classifiers":[
        {
            "category":"Arena",
            "subcategory":"Sports Club",
            "type":"Entertainment"
        }
    ],
    "sg:phone":"+61 2 9831 7549",
    "sg:postcode":"2148",
    "sg:province":"NSW",
    "sg:tags":[
        "defence",
        "supply",
        "self",
        "instruction",
        "martial art"
    ],
    "wof:name":"Home Of Champions-Gym & Fight Centre",
    "wof:placetype":"venue"
},
  "geometry": {"coordinates":[150.91178894000001,-33.7684020996],"type":"Point"}
}