{
  "type": "Feature",
  "properties": {
    "iso:country":"AU",
    "sg:address":"8 Ritchie Drv",
    "sg:city":"Rockingham",
    "sg:classifiers":[
        {
            "category":"Utilities",
            "subcategory":"Electric",
            "type":"Services"
        }
    ],
    "sg:phone":"+61 409 071 901",
    "sg:postcode":"6168",
    "sg:province":"WA",
    "sg:tags":[
        "electrical",
        "contractor"
    ],
    "wof:name":"The Vital Spark",
    "wof:placetype":"venue"
},
  "geometry": {"coordinates":[115.725319,-32.283195],"type":"Point"}
}