{
  "type": "Feature",
  "properties": {
    "addr:full":"709 Glenferrie Rd Hawthorn VIC 3122",
    "addr:housenumber":"709",
    "addr:postcode":"3122",
    "addr:street":"Glenferrie Rd",
    "iso:country":"AU",
    "sg:address":"709 Glenferrie Rd",
    "sg:city":"Hawthorn",
    "sg:classifiers":[
        {
            "category":"Shopping",
            "subcategory":"Clothing, Apparel, & Fashions",
            "type":"Retail Goods"
        }
    ],
    "sg:phone":"+61 3 9815 3222",
    "sg:postcode":"3122",
    "sg:province":"VIC",
    "sg:tags":[
        "lady",
        "wear"
    ],
    "wof:name":"Scarlett & Sly",
    "wof:placetype":"venue"
},
  "geometry": {"coordinates":[145.035766602,-37.8194541931],"type":"Point"}
}