{
  "type": "Feature",
  "properties": {
    "addr:full":"8- 10 Wade St Inverell NSW 2360",
    "addr:housenumber":"10",
    "addr:postcode":"2360",
    "addr:street":"8;Wade St",
    "iso:country":"AU",
    "sg:address":"8- 10 Wade St",
    "sg:city":"Inverell",
    "sg:classifiers":[
        {
            "category":"Education",
            "subcategory":"Kindergarten",
            "type":"Public Place"
        }
    ],
    "sg:phone":"+61 2 6721 0333",
    "sg:postcode":"2360",
    "sg:province":"NSW",
    "sg:tags":[
        "pre-schools"
    ],
    "wof:name":"Platypus Club The",
    "wof:placetype":"venue"
},
  "geometry": {"coordinates":[151.105377197,-29.7683334351],"type":"Point"}
}