{
  "type": "Feature",
  "properties": {
    "addr:full":"476 Bay St Port Melbourne VIC 3207",
    "addr:housenumber":"476",
    "addr:postcode":"3207",
    "addr:street":"Bay St",
    "iso:country":"AU",
    "sg:address":"476 Bay St",
    "sg:city":"Port Melbourne",
    "sg:classifiers":[
        {
            "category":"Deli",
            "type":"Food & Drink"
        }
    ],
    "sg:phone":"+61 3 9676 2444",
    "sg:postcode":"3207",
    "sg:province":"VIC",
    "sg:tags":[
        "delicatessen"
    ],
    "wof:name":"La Bottega on Bay",
    "wof:placetype":"venue"
},
  "geometry": {"coordinates":[144.946854,-37.833874],"type":"Point"}
}