{
  "type": "Feature",
  "properties": {
    "iso:country":"AU",
    "sg:address":"130 Marri Park Drv",
    "sg:city":"Casuarina",
    "sg:classifiers":[
        {
            "category":"Professional",
            "type":"Services"
        }
    ],
    "sg:phone":"+61 8 9419 2591",
    "sg:postcode":"6167",
    "sg:province":"WA",
    "sg:tags":[
        "transport"
    ],
    "wof:name":"Spiders Pilot & Tilt Tray Services",
    "wof:placetype":"venue"
},
  "geometry": {"coordinates":[115.877663,-32.236607],"type":"Point"}
}