{
  "type": "Feature",
  "properties": {
    "iso:country":"AU",
    "sg:address":"33 Carrathool Ave",
    "sg:city":"Rosebud",
    "sg:classifiers":[
        {
            "category":"Building & Trades",
            "subcategory":"Equipment Rental",
            "type":"Services"
        }
    ],
    "sg:phone":"+61 3 5982 1098",
    "sg:postcode":"3939",
    "sg:province":"VIC",
    "sg:tags":[
        "party",
        "hire"
    ],
    "wof:name":"Arneys Jumping Castle Hire",
    "wof:placetype":"venue"
},
  "geometry": {"coordinates":[144.931564331,-38.3836631775],"type":"Point"}
}