{
  "type": "Feature",
  "properties": {
    "iso:country":"AU",
    "sg:address":"15 George St",
    "sg:city":"Scottsdale",
    "sg:classifiers":[
        {
            "category":"Health Services",
            "subcategory":"Doctor",
            "type":"Services"
        }
    ],
    "sg:phone":"+61 3 6352 2555",
    "sg:postcode":"7260",
    "sg:province":"TAS",
    "sg:tags":[
        "medical",
        "practitioner"
    ],
    "wof:name":"Scottsdale Medical Centre",
    "wof:placetype":"venue"
},
  "geometry": {"coordinates":[147.51754800000001,-41.158501],"type":"Point"}
}