{
  "type": "Feature",
  "properties": {
    "iso:country":"AU",
    "sg:address":"39 Hammond Crt",
    "sg:city":"Baulkham Hills",
    "sg:classifiers":[
        {
            "category":"Utilities",
            "subcategory":"Electric",
            "type":"Services"
        }
    ],
    "sg:phone":"+61 419 986 947",
    "sg:postcode":"2153",
    "sg:province":"NSW",
    "sg:tags":[
        "electrical",
        "contractor"
    ],
    "wof:name":"Q.A.L. Electrical Services",
    "wof:placetype":"venue"
},
  "geometry": {"coordinates":[150.97708129899999,-33.7661895752],"type":"Point"}
}