{
  "type": "Feature",
  "properties": {
    "addr:full":"3 James St Bassendean WA 6054",
    "addr:housenumber":"3",
    "addr:postcode":"6054",
    "addr:street":"James St",
    "iso:country":"AU",
    "sg:address":"3 James St",
    "sg:city":"Bassendean",
    "sg:classifiers":[
        {
            "category":"Education",
            "subcategory":"Kindergarten",
            "type":"Public Place"
        }
    ],
    "sg:phone":"+61 8 9279 5505",
    "sg:postcode":"6054",
    "sg:province":"WA",
    "sg:tags":[
        "pre-schools"
    ],
    "wof:name":"Catholic Church",
    "wof:placetype":"venue"
},
  "geometry": {"coordinates":[115.95043182400001,-31.9043941498],"type":"Point"}
}