{
  "type": "Feature",
  "properties": {
    "addr:full":"PO Box 1173 Spring Hill QLD 4004",
    "addr:postcode":"4004",
    "iso:country":"AU",
    "sg:address":"PO Box 1173",
    "sg:city":"Spring Hill",
    "sg:classifiers":[
        {
            "category":"Education",
            "subcategory":"Special Training",
            "type":"Public Place"
        }
    ],
    "sg:phone":"+61 7 3902 0005",
    "sg:postcode":"4004",
    "sg:province":"QLD",
    "sg:tags":[
        "development"
    ],
    "wof:name":"Tap Into Image",
    "wof:placetype":"venue"
},
  "geometry": {"coordinates":[153.02444457999999,-27.4608707428],"type":"Point"}
}