{
  "type": "Feature",
  "properties": {
    "iso:country":"AU",
    "sg:address":"18 Nestle Crt",
    "sg:city":"Arthurs Seat",
    "sg:classifiers":[
        {
            "category":"Health Services",
            "subcategory":"Health Practitioner",
            "type":"Services"
        }
    ],
    "sg:phone":"+61 3 5981 8712",
    "sg:postcode":"3936",
    "sg:province":"VIC",
    "sg:tags":[
        "naturopath"
    ],
    "wof:name":"Carpmael Andrew",
    "wof:placetype":"venue"
},
  "geometry": {"coordinates":[144.953887939,-38.3527145386],"type":"Point"}
}