{
  "type": "Feature",
  "properties": {
    "iso:country":"AU",
    "sg:address":"12 Lincoln St",
    "sg:city":"Strathpine",
    "sg:classifiers":[
        {
            "category":"Food & Beverages",
            "subcategory":"Supermarket",
            "type":"Retail Goods"
        }
    ],
    "sg:phone":"+61 7 3889 6219",
    "sg:postcode":"4500",
    "sg:province":"QLD",
    "sg:tags":[
        "grocery",
        "store"
    ],
    "wof:name":"Everyday Express Foodmart",
    "wof:placetype":"venue"
},
  "geometry": {"coordinates":[152.99156189000001,-27.2956085205],"type":"Point"}
}