{
  "type": "Feature",
  "properties": {
    "addr:full":"Sawmill Rd Capella QLD 4702",
    "addr:postcode":"4702",
    "addr:street":"Sawmill Rd",
    "iso:country":"AU",
    "sg:address":"Sawmill Rd",
    "sg:city":"Capella",
    "sg:classifiers":[
        {
            "category":"Manufacturing",
            "subcategory":"Lumber",
            "type":"Manufacturing & Wholesale Goods"
        }
    ],
    "sg:phone":"+61 7 4984 9355",
    "sg:postcode":"4702",
    "sg:province":"QLD",
    "sg:tags":[
        "sawmillers"
    ],
    "wof:name":"Franettovich Sawmill",
    "wof:placetype":"venue"
},
  "geometry": {"coordinates":[147.698364258,-23.417673111],"type":"Point"}
}