{
  "type": "Feature",
  "properties": {
    "addr:full":"29 Helena St Randwick NSW 2031",
    "addr:housenumber":"29",
    "addr:postcode":"2031",
    "addr:street":"Helena St",
    "iso:country":"AU",
    "sg:address":"29 Helena St",
    "sg:city":"Randwick",
    "sg:classifiers":[
        {
            "category":"Professional",
            "subcategory":"Art Services",
            "type":"Services"
        }
    ],
    "sg:phone":"+61 2 9314 6220",
    "sg:postcode":"2031",
    "sg:province":"NSW",
    "sg:tags":[
        "graphic",
        "designer"
    ],
    "wof:name":"Fat Cat Designs.",
    "wof:placetype":"venue"
},
  "geometry": {"coordinates":[151.24151611299999,-33.9250793457],"type":"Point"}
}