{
  "type": "Feature",
  "properties": {
    "addr:full":"19 Ormerod St Naracoorte SA 5271",
    "addr:housenumber":"19",
    "addr:postcode":"5271",
    "addr:street":"Ormerod St",
    "iso:country":"AU",
    "sg:address":"19 Ormerod St",
    "sg:city":"Naracoorte",
    "sg:classifiers":[
        {
            "category":"Shopping",
            "subcategory":"Computers & Home Electronics",
            "type":"Retail Goods"
        }
    ],
    "sg:phone":"+61 8 8762 1867",
    "sg:postcode":"5271",
    "sg:province":"SA",
    "sg:tags":[
        "small",
        "equipment",
        "business"
    ],
    "wof:name":"Jasons Ultra-Tek",
    "wof:placetype":"venue"
},
  "geometry": {"coordinates":[140.73994400000001,-36.955837],"type":"Point"}
}