{
  "type": "Feature",
  "properties": {
    "addr:full":"14 Binney St Euroa VIC 3666",
    "addr:housenumber":"14",
    "addr:postcode":"3666",
    "addr:street":"Binney St",
    "iso:country":"AU",
    "sg:address":"14 Binney St",
    "sg:city":"Euroa",
    "sg:classifiers":[
        {
            "category":"Insurance",
            "subcategory":"Hazard Insurance",
            "type":"Services"
        }
    ],
    "sg:phone":"+61 3 5822 2233",
    "sg:postcode":"3666",
    "sg:province":"VIC",
    "sg:tags":[
        "loss",
        "adjuster",
        "assessor"
    ],
    "wof:name":"Freemans Australia Pty Ltd",
    "wof:placetype":"venue"
},
  "geometry": {"coordinates":[145.56930542000001,-36.7492599487],"type":"Point"}
}