{
  "type": "Feature",
  "properties": {
    "addr:full":"165 Military Rd Avondale Heights VIC 3034",
    "addr:housenumber":"165",
    "addr:postcode":"3034",
    "addr:street":"Military Rd",
    "iso:country":"AU",
    "sg:address":"165 Military Rd",
    "sg:city":"Avondale Heights",
    "sg:classifiers":[
        {
            "category":"Deli",
            "type":"Food & Drink"
        }
    ],
    "sg:phone":"+61 3 9337 1321",
    "sg:postcode":"3034",
    "sg:province":"VIC",
    "sg:tags":[
        "delicatessen"
    ],
    "wof:name":"Conidi Deli",
    "wof:placetype":"venue"
},
  "geometry": {"coordinates":[144.860626,-37.759331],"type":"Point"}
}