{
  "type": "Feature",
  "properties": {
    "addr:full":"774 Pacific Hwy Gordon NSW 2072",
    "addr:housenumber":"774",
    "addr:postcode":"2072",
    "addr:street":"Pacific Hwy",
    "iso:country":"AU",
    "sg:address":"774 Pacific Hwy",
    "sg:city":"Gordon",
    "sg:classifiers":[
        {
            "category":"Personal",
            "subcategory":"Massage",
            "type":"Services"
        }
    ],
    "sg:phone":"+61 2 9499 5108",
    "sg:postcode":"2072",
    "sg:province":"NSW",
    "sg:tags":[
        "therapy"
    ],
    "wof:name":"Wang J",
    "wof:placetype":"venue"
},
  "geometry": {"coordinates":[151.152786255,-33.7559356689],"type":"Point"}
}