{
  "type": "Feature",
  "properties": {
    "addr:full":"74 Railway Pde Canley Vale NSW 2166",
    "addr:housenumber":"74",
    "addr:postcode":"2166",
    "addr:street":"Railway Pde",
    "iso:country":"AU",
    "sg:address":"74 Railway Pde",
    "sg:city":"Canley Vale",
    "sg:classifiers":[
        {
            "category":"Retail",
            "subcategory":"Auto Repair",
            "type":"Services"
        }
    ],
    "sg:phone":"+61 2 9724 4770",
    "sg:postcode":"2166",
    "sg:province":"NSW",
    "sg:tags":[
        "repairer",
        "motor",
        "engineer"
    ],
    "wof:name":"Ninh 1-Go Auto Repairs",
    "wof:placetype":"venue"
},
  "geometry": {"coordinates":[150.943603516,-33.8866691589],"type":"Point"}
}