{
  "type": "Feature",
  "properties": {
    "iso:country":"AU",
    "sg:address":"River St",
    "sg:city":"Cowra",
    "sg:classifiers":[
        {
            "category":"Home & Garden",
            "subcategory":"Building Materials",
            "type":"Retail Goods"
        }
    ],
    "sg:phone":"+61 2 6341 1288",
    "sg:postcode":"2794",
    "sg:province":"NSW",
    "sg:tags":[
        "pre-mixed",
        "concrete"
    ],
    "wof:name":"Bryants Concrete Pty Ltd",
    "wof:placetype":"venue"
},
  "geometry": {"coordinates":[148.682662964,-33.8287391663],"type":"Point"}
}