{
  "type": "Feature",
  "properties": {
    "addr:full":"CPC Medical Centre 14 Lake Rd Port Macquarie NSW 2444",
    "addr:housenumber":"14",
    "addr:postcode":"2444",
    "addr:street":"Lake Rd",
    "iso:country":"AU",
    "sg:address":"CPC Medical Centre 14 Lake Rd",
    "sg:city":"Port Macquarie",
    "sg:classifiers":[
        {
            "category":"Health Services",
            "subcategory":"Health Practitioner",
            "type":"Services"
        }
    ],
    "sg:phone":"+61 2 6583 2008",
    "sg:postcode":"2444",
    "sg:province":"NSW",
    "sg:tags":[
        "psychologist"
    ],
    "wof:name":"Gary Grant",
    "wof:placetype":"venue"
},
  "geometry": {"coordinates":[152.91142300000001,-31.435587],"type":"Point"}
}