{
  "type": "Feature",
  "properties": {
    "addr:full":"5/ 290 Whitehall St Yarraville VIC 3013",
    "addr:housenumber":"/ 290",
    "addr:postcode":"3013",
    "addr:street":"Whitehall St",
    "iso:country":"AU",
    "sg:address":"5/ 290 Whitehall St",
    "sg:city":"Yarraville",
    "sg:classifiers":[
        {
            "category":"Personal",
            "type":"Services"
        }
    ],
    "sg:phone":"+61 3 9687 2966",
    "sg:postcode":"3013",
    "sg:province":"VIC",
    "sg:tags":[
        "reducing",
        "treatment",
        "weight"
    ],
    "wof:name":"Fernwood Slimplicity",
    "wof:placetype":"venue"
},
  "geometry": {"coordinates":[144.898635864,-37.8212852478],"type":"Point"}
}