{
  "type": "Feature",
  "properties": {
    "iso:country":"AU",
    "sg:address":"604 Burwood Rd",
    "sg:city":"Hawthorn East",
    "sg:classifiers":[
        {
            "category":"Retail",
            "subcategory":"Repair Shop",
            "type":"Services"
        }
    ],
    "sg:phone":"+61 3 9882 5824",
    "sg:postcode":"3123",
    "sg:province":"VIC",
    "sg:tags":[
        "upholsterer"
    ],
    "wof:name":"Nouveau- Bisgrove Furnishings",
    "wof:placetype":"venue"
},
  "geometry": {"coordinates":[145.04518127399999,-37.8238563538],"type":"Point"}
}