{
  "type": "Feature",
  "properties": {
    "iso:country":"AU",
    "sg:address":"77 Elanora Rd",
    "sg:city":"Elanora Heights",
    "sg:classifiers":[
        {
            "category":"Health Services",
            "subcategory":"Health Practitioner",
            "type":"Services"
        }
    ],
    "sg:phone":"+61 2 9944 7241",
    "sg:postcode":"2101",
    "sg:province":"NSW",
    "sg:tags":[
        "psychologist"
    ],
    "wof:name":"Thirkell Beverley Dr",
    "wof:placetype":"venue"
},
  "geometry": {"coordinates":[151.277435,-33.70002],"type":"Point"}
}