{
  "type": "Feature",
  "properties": {
    "iso:country":"AU",
    "sg:address":"18 De Havilland Rd",
    "sg:city":"Mordialloc",
    "sg:classifiers":[
        {
            "category":"Professional",
            "subcategory":"Engineering",
            "type":"Services"
        }
    ],
    "sg:phone":"+61 3 9587 3299",
    "sg:postcode":"3195",
    "sg:province":"VIC",
    "sg:tags":[
        "engineer"
    ],
    "wof:name":"Plaspares",
    "wof:placetype":"venue"
},
  "geometry": {"coordinates":[145.10076904300001,-37.9866065979],"type":"Point"}
}