{
  "type": "Feature",
  "properties": {
    "addr:full":"2 / 68 Paringa Ave Somerton Park SA 5044",
    "addr:housenumber":"/ 68",
    "addr:postcode":"5044",
    "addr:street":"Paringa Ave Somerton",
    "iso:country":"AU",
    "sg:address":"2 / 68 Paringa Ave",
    "sg:city":"Somerton Park",
    "sg:phone":"+61 8 8350 9722",
    "sg:postcode":"5044",
    "sg:province":"SA",
    "wof:name":"Sun-Gard SuperStore Marion",
    "wof:placetype":"venue"
},
  "geometry": {"coordinates":[138.52922100000001,-34.998627],"type":"Point"}
}