{
  "type": "Feature",
  "properties": {
    "addr:full":"Unit 20, 257 Colchester Rd Kilsyth VIC 3137",
    "addr:housenumber":"257",
    "addr:postcode":"3137",
    "addr:street":"Colchester Rd",
    "iso:country":"AU",
    "sg:address":"Unit 20, 257 Colchester Rd",
    "sg:city":"Kilsyth",
    "sg:classifiers":[
        {
            "category":"Train Station",
            "subcategory":"Light Rail",
            "type":"Transportation"
        }
    ],
    "sg:phone":"+61 1300 000 734",
    "sg:postcode":"3137",
    "sg:province":"VIC",
    "sg:tags":[
        "equipment",
        "energy",
        "solar"
    ],
    "wof:name":"RF Industries Pty Ltd",
    "wof:placetype":"venue"
},
  "geometry": {"coordinates":[145.30398559599999,-37.8238716125],"type":"Point"}
}