{
  "type": "Feature",
  "properties": {
    "iso:country":"AU",
    "sg:address":"6 Peasant St",
    "sg:city":"Holland Park West",
    "sg:classifiers":[
        {
            "category":"Professional",
            "subcategory":"Art Services",
            "type":"Services"
        }
    ],
    "sg:phone":"+61 7 3847 8377",
    "sg:postcode":"4121",
    "sg:province":"QLD",
    "sg:tags":[
        "decorator",
        "painter"
    ],
    "wof:name":"Wright & Joy Painters",
    "wof:placetype":"venue"
},
  "geometry": {"coordinates":[153.05642700199999,-27.5164470673],"type":"Point"}
}