{
  "type": "Feature",
  "properties": {
    "addr:full":"Shop 11G 107 Latrobe Tce Paddington QLD 4064",
    "addr:housenumber":"11g 107",
    "addr:postcode":"4064",
    "addr:street":"Shop;Latrobe Tce",
    "iso:country":"AU",
    "sg:address":"Shop 11G 107",
    "sg:city":"Latrobe Tce Paddington",
    "sg:classifiers":[
        {
            "category":"Cafe",
            "type":"Food & Drink"
        }
    ],
    "sg:phone":"+61 7 3368 3411",
    "sg:postcode":"4064",
    "sg:province":"QLD",
    "wof:name":"Cafe Del-Mar",
    "wof:placetype":"venue"
},
  "geometry": {"coordinates":[152.997756958,-27.4589214325],"type":"Point"}
}