{
  "type": "Feature",
  "properties": {
    "addr:full":"15 Monash St Clermont QLD 4721",
    "addr:housenumber":"15",
    "addr:postcode":"4721",
    "addr:street":"Monash St",
    "iso:country":"AU",
    "sg:address":"15 Monash St",
    "sg:city":"Clermont",
    "sg:classifiers":[
        {
            "category":"Social Services",
            "subcategory":"Adult Care",
            "type":"Services"
        }
    ],
    "sg:phone":"+61 7 4983 3200",
    "sg:postcode":"4721",
    "sg:province":"QLD",
    "sg:tags":[
        "aged"
    ],
    "wof:name":"Monash Lodge",
    "wof:placetype":"venue"
},
  "geometry": {"coordinates":[147.631027222,-22.8298797607],"type":"Point"}
}