{
  "type": "Feature",
  "properties": {
    "addr:full":"Shop 1, 494 Old South Head Rd Rose Bay NSW 2029",
    "addr:housenumber":"shop 1 494",
    "addr:postcode":"2029",
    "addr:street":"Old South Head Rd",
    "iso:country":"AU",
    "sg:address":"Shop 1, 494 Old South Head Rd",
    "sg:city":"Rose Bay",
    "sg:classifiers":[
        {
            "category":"Real Estate",
            "subcategory":"Real Estate Agent",
            "type":"Services"
        }
    ],
    "sg:phone":"+61 2 9388 3133",
    "sg:postcode":"2029",
    "sg:province":"NSW",
    "wof:name":"Julie Feller Real Estate",
    "wof:placetype":"venue"
},
  "geometry": {"coordinates":[151.272613525,-33.8746948242],"type":"Point"}
}