{
  "type": "Feature",
  "properties": {
    "addr:full":"Suite 2/ 1343 Malvern Rd Malvern VIC 3144",
    "addr:housenumber":"/ 1343",
    "addr:postcode":"3144",
    "addr:street":"Malvern Rd",
    "iso:country":"AU",
    "sg:address":"Suite 2/ 1343 Malvern Rd",
    "sg:city":"Malvern",
    "sg:classifiers":[
        {
            "category":"Professional",
            "subcategory":"Accounting & Tax Preparation",
            "type":"Services"
        }
    ],
    "sg:phone":"+61 3 9821 0133",
    "sg:postcode":"3144",
    "sg:province":"VIC",
    "sg:tags":[
        "accountant",
        "auditor"
    ],
    "wof:name":"Taylors Accountants & Advisors",
    "wof:placetype":"venue"
},
  "geometry": {"coordinates":[145.03887939399999,-37.8526611328],"type":"Point"}
}