{
  "type": "Feature",
  "properties": {
    "iso:country":"AU",
    "sg:address":"15 Barolin St",
    "sg:city":"Bundaberg",
    "sg:classifiers":[
        {
            "category":"Health Services",
            "subcategory":"Doctor",
            "type":"Services"
        }
    ],
    "sg:phone":"+61 7 4151 2608",
    "sg:postcode":"4670",
    "sg:province":"QLD",
    "sg:tags":[
        "medical",
        "practitioner"
    ],
    "wof:name":"Chapman J",
    "wof:placetype":"venue"
},
  "geometry": {"coordinates":[152.34922790499999,-24.8678684235],"type":"Point"}
}