{
  "type": "Feature",
  "properties": {
    "addr:full":"Master Builders House Traders Pl Maroochydore QLD 4558",
    "addr:postcode":"4558",
    "addr:street":"Pl",
    "iso:country":"AU",
    "sg:address":"Master Builders House Traders Pl",
    "sg:city":"Maroochydore",
    "sg:classifiers":[
        {
            "category":"Real Estate",
            "subcategory":"Architect",
            "type":"Services"
        }
    ],
    "sg:phone":"+61 7 5479 6868",
    "sg:postcode":"4558",
    "sg:province":"QLD",
    "wof:name":"Young Architects",
    "wof:placetype":"venue"
},
  "geometry": {"coordinates":[153.06834411599999,-26.6442928314],"type":"Point"}
}