{
  "type": "Feature",
  "properties": {
    "addr:full":"83 Wonthaggi Rd Inverloch VIC 3996",
    "addr:housenumber":"83",
    "addr:postcode":"3996",
    "addr:street":"Wonthaggi Rd",
    "iso:country":"AU",
    "sg:address":"83 Wonthaggi Rd",
    "sg:city":"Inverloch",
    "sg:classifiers":[
        {
            "category":"Wholesale",
            "subcategory":"Metals & Minerals",
            "type":"Manufacturing & Wholesale Goods"
        }
    ],
    "sg:phone":"+61 408 242 210",
    "sg:postcode":"3996",
    "sg:province":"VIC",
    "sg:tags":[
        "steel",
        "stainless",
        "product",
        "equipment"
    ],
    "wof:name":"Gippsland Sheetmetal Industries Pty Ltd",
    "wof:placetype":"venue"
},
  "geometry": {"coordinates":[145.72427400000001,-38.62656],"type":"Point"}
}