{
  "type": "Feature",
  "properties": {
    "iso:country":"AU",
    "sg:address":"168 Princes Hwy",
    "sg:city":"Beverley Park",
    "sg:classifiers":[
        {
            "category":"Building & Trades",
            "subcategory":"Construction",
            "type":"Services"
        }
    ],
    "sg:phone":"+61 419 216 009",
    "sg:postcode":"2217",
    "sg:province":"NSW",
    "sg:tags":[
        "rendering",
        "cement"
    ],
    "wof:name":"Tsigolis Rendering Pty Ltd",
    "wof:placetype":"venue"
},
  "geometry": {"coordinates":[151.125885,-33.976345],"type":"Point"}
}