{
  "type": "Feature",
  "properties": {
    "addr:full":"Suite 14, 1- 13 Rokeby Rd Subiaco WA 6008",
    "addr:housenumber":"1 13",
    "addr:postcode":"6008",
    "addr:street":"Rokeby Rd",
    "iso:country":"AU",
    "sg:address":"Suite 14, 1- 13 Rokeby Rd",
    "sg:city":"Subiaco",
    "sg:classifiers":[
        {
            "category":"Health Services",
            "subcategory":"Health Practitioner",
            "type":"Services"
        }
    ],
    "sg:phone":"+61 8 9388 7871",
    "sg:postcode":"6008",
    "sg:province":"WA",
    "sg:tags":[
        "naturopath"
    ],
    "wof:name":"Sommerhalder, Sabine",
    "wof:placetype":"venue"
},
  "geometry": {"coordinates":[115.823860169,-31.9459209442],"type":"Point"}
}