{
  "type": "Feature",
  "properties": {
    "addr:full":"Glen Forrest Hall, Cnr Statham St & Marnie Rd Glen Forrest WA 6071",
    "addr:postcode":"6071",
    "addr:street":"Glen;Cnr Statham St & Marnie Rd",
    "iso:country":"AU",
    "sg:address":"Glen Forrest Hall, Cnr Statham St & Marnie Rd",
    "sg:city":"Glen Forrest",
    "sg:classifiers":[
        {
            "category":"Arena",
            "subcategory":"Sports Club",
            "type":"Entertainment"
        }
    ],
    "sg:phone":"+61 8 9295 6607",
    "sg:postcode":"6071",
    "sg:province":"WA",
    "sg:tags":[
        "defence",
        "supply",
        "self",
        "instruction",
        "martial art"
    ],
    "wof:name":"West Australian Goju Ryu Karate Do",
    "wof:placetype":"venue"
},
  "geometry": {"coordinates":[116.101966858,-31.9034328461],"type":"Point"}
}