{
  "type": "Feature",
  "properties": {
    "addr:full":"272 Inkerman St St Kilda East VIC 3183",
    "addr:housenumber":"272",
    "addr:postcode":"3183",
    "addr:street":"Inkerman St",
    "iso:country":"AU",
    "sg:address":"272 Inkerman St St",
    "sg:city":"Kilda East",
    "sg:classifiers":[
        {
            "category":"Personal",
            "subcategory":"Beauty Salon",
            "type":"Services"
        }
    ],
    "sg:phone":"+61 3 9527 9878",
    "sg:postcode":"3183",
    "sg:province":"VIC",
    "sg:tags":[
        "hairdresser"
    ],
    "wof:name":"Ys Way Hairdressing",
    "wof:placetype":"venue"
},
  "geometry": {"coordinates":[144.99305725100001,-37.865688324],"type":"Point"}
}