{
  "type": "Feature",
  "properties": {
    "addr:full":"35 Outlook Drv Ninderry QLD 4561",
    "addr:housenumber":"35",
    "addr:postcode":"4561",
    "addr:street":"Outlook Drv",
    "iso:country":"AU",
    "sg:address":"35 Outlook Drv",
    "sg:city":"Ninderry",
    "sg:classifiers":[
        {
            "category":"Coffee & Tea",
            "type":"Food & Drink"
        }
    ],
    "sg:phone":"+61 7 5446 7528",
    "sg:postcode":"4561",
    "sg:province":"QLD",
    "sg:tags":[
        "kayak",
        "canoe"
    ],
    "sg:website":"http://www.natureline.com.au",
    "wof:name":"Natureline Australia",
    "wof:placetype":"venue"
},
  "geometry": {"coordinates":[152.973846436,-26.5398464203],"type":"Point"}
}