{
  "type": "Feature",
  "properties": {
    "addr:full":"105 Webster St Ballarat VIC 3350",
    "addr:housenumber":"105",
    "addr:postcode":"3350",
    "addr:street":"Webster St",
    "iso:country":"AU",
    "sg:address":"105 Webster St",
    "sg:city":"Ballarat",
    "sg:classifiers":[
        {
            "category":"Health Services",
            "subcategory":"Doctor",
            "type":"Services"
        }
    ],
    "sg:phone":"+61 3 5320 2144",
    "sg:postcode":"3350",
    "sg:province":"VIC",
    "sg:tags":[
        "nurse",
        "nursing"
    ],
    "wof:name":"St John of God Home Nursing Service",
    "wof:placetype":"venue"
},
  "geometry": {"coordinates":[143.84730500000001,-37.556465],"type":"Point"}
}