{
  "type": "Feature",
  "properties": {
    "addr:full":"375 Grossmans Rd Torquay VIC 3228",
    "addr:housenumber":"375",
    "addr:postcode":"3228",
    "addr:street":"Grossmans Rd",
    "iso:country":"AU",
    "sg:address":"375 Grossmans Rd",
    "sg:city":"Torquay",
    "sg:classifiers":[
        {
            "category":"Utilities",
            "subcategory":"Refuse",
            "type":"Services"
        }
    ],
    "sg:phone":"+61 412 752 964",
    "sg:postcode":"3228",
    "sg:province":"VIC",
    "sg:tags":[
        "remover",
        "rubbish"
    ],
    "wof:name":"Torquay Bobcat & Truck Hire",
    "wof:placetype":"venue"
},
  "geometry": {"coordinates":[144.279526,-38.317669],"type":"Point"}
}