{
  "type": "Feature",
  "properties": {
    "addr:full":"2 Warbroon Crt Bella Vista NSW 2153",
    "addr:housenumber":"2",
    "addr:postcode":"2153",
    "addr:street":"Warbroon Crt",
    "iso:country":"AU",
    "sg:address":"2 Warbroon Crt",
    "sg:city":"Bella Vista",
    "sg:classifiers":[
        {
            "category":"Building & Trades",
            "subcategory":"Cleaning & Sanitation",
            "type":"Services"
        }
    ],
    "sg:phone":"+61 414 894 093",
    "sg:postcode":"2153",
    "sg:province":"NSW",
    "sg:tags":[
        "chemical",
        "pressure",
        "steam",
        "contractor"
    ],
    "wof:name":"Escalator Cleaning Services Australia",
    "wof:placetype":"venue"
},
  "geometry": {"coordinates":[150.96539306599999,-33.7396583557],"type":"Point"}
}