{
  "type": "Feature",
  "properties": {
    "addr:full":"3 Bute St Seddon VIC 3011",
    "addr:housenumber":"3",
    "addr:postcode":"3011",
    "addr:street":"Bute St",
    "iso:country":"AU",
    "sg:address":"3 Bute St",
    "sg:city":"Seddon",
    "sg:classifiers":[
        {
            "category":"Professional",
            "subcategory":"Management & Consulting",
            "type":"Services"
        }
    ],
    "sg:phone":"+61 3 8307 0513",
    "sg:postcode":"3011",
    "sg:province":"VIC",
    "sg:tags":[
        "consultant",
        "educational"
    ],
    "wof:name":"ANZUK Education Services",
    "wof:placetype":"venue"
},
  "geometry": {"coordinates":[144.89520263700001,-37.8039054871],"type":"Point"}
}