{
  "type": "Feature",
  "properties": {
    "addr:full":"48 Webster Rd Stafford QLD 4053",
    "addr:housenumber":"48",
    "addr:postcode":"4053",
    "addr:street":"Webster Rd",
    "iso:country":"AU",
    "sg:address":"48 Webster Rd",
    "sg:city":"Stafford",
    "sg:classifiers":[
        {
            "category":"Social Services",
            "subcategory":"Child Care",
            "type":"Services"
        }
    ],
    "sg:phone":"+61 7 3356 8787",
    "sg:postcode":"4053",
    "sg:province":"QLD",
    "wof:name":"YMCA Outside School Hours Care",
    "wof:placetype":"venue"
},
  "geometry": {"coordinates":[153.015914917,-27.4163551331],"type":"Point"}
}