{
  "type": "Feature",
  "properties": {
    "iso:country":"AU",
    "sg:address":"46 Tobruk Ave",
    "sg:city":"Heidelberg West",
    "sg:classifiers":[
        {
            "category":"Home & Garden",
            "subcategory":"Building Materials",
            "type":"Retail Goods"
        }
    ],
    "sg:phone":"+61 3 9455 2446",
    "sg:postcode":"3081",
    "sg:province":"VIC",
    "sg:tags":[
        "merchant",
        "glass",
        "glazier"
    ],
    "wof:name":"A Allbrite Glass Supply & Replacement",
    "wof:placetype":"venue"
},
  "geometry": {"coordinates":[145.040283203,-37.7475242615],"type":"Point"}
}