{
  "type": "Feature",
  "properties": {
    "iso:country":"AU",
    "sg:address":"12 Herbert St",
    "sg:city":"Invermay",
    "sg:classifiers":[
        {
            "category":"Home & Garden",
            "subcategory":"Building Materials",
            "type":"Retail Goods"
        }
    ],
    "sg:phone":"+61 3 6334 5384",
    "sg:postcode":"7248",
    "sg:province":"TAS",
    "sg:tags":[
        "shutter",
        "roller",
        "grille"
    ],
    "wof:name":"Bottom Line Blinds & Awnings",
    "wof:placetype":"venue"
},
  "geometry": {"coordinates":[147.14140319800001,-41.4205780029],"type":"Point"}
}