{
  "type": "Feature",
  "properties": {
    "iso:country":"AU",
    "sg:address":"155 High St",
    "sg:city":"Maryborough",
    "sg:classifiers":[
        {
            "category":"Travel",
            "subcategory":"Hotels & Motels",
            "type":"Entertainment"
        }
    ],
    "sg:phone":"+61 3 5460 5500",
    "sg:postcode":"3465",
    "sg:province":"VIC",
    "sg:tags":[
        "pub"
    ],
    "wof:name":"Flagstaff Hotel Maryborough",
    "wof:placetype":"venue"
},
  "geometry": {"coordinates":[143.73858642600001,-37.0460395813],"type":"Point"}
}