{
  "type": "Feature",
  "properties": {
    "addr:full":"Shed 4 Export Drv Berrimah NT 0828",
    "addr:postcode":"nt 0828",
    "addr:street":"Export Drv",
    "iso:country":"AU",
    "sg:address":"Shed 4 Export Drv",
    "sg:city":"Berrimah",
    "sg:classifiers":[
        {
            "category":"Mining & Drilling",
            "type":"Manufacturing & Wholesale Goods"
        }
    ],
    "sg:phone":"+61 8 9316 1301",
    "sg:postcode":"0828",
    "sg:province":"NT",
    "sg:tags":[
        "equipment",
        "quarrying",
        "supply"
    ],
    "wof:name":"Mintech Chemical Industries",
    "wof:placetype":"venue"
},
  "geometry": {"coordinates":[130.925247192,-12.471124649],"type":"Point"}
}