{
  "type": "Feature",
  "properties": {
    "addr:full":"20 Wentworth St Wagga Wagga NSW 2650",
    "addr:housenumber":"20",
    "addr:postcode":"2650",
    "addr:street":"Wentworth St",
    "iso:country":"AU",
    "sg:address":"20 Wentworth St",
    "sg:city":"Wagga Wagga",
    "sg:classifiers":[
        {
            "category":"Building & Trades",
            "subcategory":"Construction",
            "type":"Services"
        }
    ],
    "sg:phone":"+61 2 6921 5568",
    "sg:postcode":"2650",
    "sg:province":"NSW",
    "sg:tags":[
        "welding"
    ],
    "wof:name":"Bidgee Welding Pty Ltd",
    "wof:placetype":"venue"
},
  "geometry": {"coordinates":[147.40740966800001,-35.1275863647],"type":"Point"}
}