{
  "type": "Feature",
  "properties": {
    "addr:full":"59 Hunter St Newcastle NSW 2300",
    "addr:housenumber":"59",
    "addr:postcode":"2300",
    "addr:street":"Hunter St",
    "iso:country":"AU",
    "sg:address":"59 Hunter St",
    "sg:city":"Newcastle",
    "sg:classifiers":[
        {
            "category":"Professional",
            "subcategory":"Engineering",
            "type":"Services"
        }
    ],
    "sg:phone":"+61 2 4927 1800",
    "sg:postcode":"2300",
    "sg:province":"NSW",
    "sg:tags":[
        "consulting",
        "engineer"
    ],
    "wof:name":"Hughes Trueman Reinhold",
    "wof:placetype":"venue"
},
  "geometry": {"coordinates":[151.78381300000001,-32.927807],"type":"Point"}
}