{
  "type": "Feature",
  "properties": {
    "addr:full":"3 Obi Obi Rd Mapleton QLD 4560",
    "addr:housenumber":"3",
    "addr:postcode":"4560",
    "addr:street":"Obi Obi Rd",
    "iso:country":"AU",
    "sg:address":"3 Obi Obi Rd",
    "sg:city":"Mapleton",
    "sg:classifiers":[
        {
            "category":"Cafe",
            "type":"Food & Drink"
        }
    ],
    "sg:phone":"+61 7 5445 7677",
    "sg:postcode":"4560",
    "sg:province":"QLD",
    "wof:name":"Mapleton Daily Grind",
    "wof:placetype":"venue"
},
  "geometry": {"coordinates":[152.86602783199999,-26.6239032745],"type":"Point"}
}