{
  "type": "Feature",
  "properties": {
    "addr:full":"27 Marine Ave Port Lincoln SA 5606",
    "addr:housenumber":"27",
    "addr:postcode":"5606",
    "addr:street":"Marine Ave",
    "iso:country":"AU",
    "sg:address":"27 Marine Ave",
    "sg:city":"Port Lincoln",
    "sg:classifiers":[
        {
            "category":"Social Services",
            "subcategory":"Retirement Home",
            "type":"Services"
        }
    ],
    "sg:phone":"+61 8 8682 8200",
    "sg:postcode":"5606",
    "sg:province":"SA",
    "sg:tags":[
        "village"
    ],
    "wof:name":"Lincoln Grove Estate",
    "wof:placetype":"venue"
},
  "geometry": {"coordinates":[135.84655799999999,-34.726887],"type":"Point"}
}