{
  "type": "Feature",
  "properties": {
    "iso:country":"AU",
    "sg:address":"273 Spring St",
    "sg:city":"Reservoir",
    "sg:classifiers":[
        {
            "category":"Fast Food",
            "type":"Food & Drink"
        }
    ],
    "sg:phone":"+61 3 9460 5525",
    "sg:postcode":"3073",
    "sg:province":"VIC",
    "sg:tags":[
        "away",
        "take"
    ],
    "wof:name":"La Porchetta Pizza Restaurant",
    "wof:placetype":"venue"
},
  "geometry": {"coordinates":[145.00740051299999,-37.714630127],"type":"Point"}
}