{
  "type": "Feature",
  "properties": {
    "iso:country":"AU",
    "sg:address":"14 Bosworth Rd",
    "sg:city":"Woolgoolga",
    "sg:classifiers":[
        {
            "category":"Building & Trades",
            "subcategory":"Construction",
            "type":"Services"
        }
    ],
    "sg:phone":"+61 2 6654 2188",
    "sg:postcode":"2456",
    "sg:province":"NSW",
    "sg:tags":[
        "welding"
    ],
    "wof:name":"ARC Attack Engineering",
    "wof:placetype":"venue"
},
  "geometry": {"coordinates":[153.193954,-30.125261],"type":"Point"}
}