{
  "type": "Feature",
  "properties": {
    "addr:full":"PO Box 81 Hallam VIC 3803",
    "addr:postcode":"3803",
    "iso:country":"AU",
    "sg:address":"PO Box 81",
    "sg:city":"Hallam",
    "sg:classifiers":[
        {
            "category":"Education",
            "subcategory":"Music School",
            "type":"Public Place"
        }
    ],
    "sg:phone":"+61 500 555 201",
    "sg:postcode":"3803",
    "sg:province":"VIC",
    "sg:tags":[
        "choir",
        "bands",
        "orchestra"
    ],
    "wof:name":"City Of Casey Pipe Band",
    "wof:placetype":"venue"
},
  "geometry": {"coordinates":[145.269256592,-38.0042991638],"type":"Point"}
}