{
  "type": "Feature",
  "properties": {
    "addr:full":"Port Drv Broome WA 6725",
    "addr:postcode":"6725",
    "addr:street":"Port Drv",
    "iso:country":"AU",
    "sg:address":"Port Drv",
    "sg:city":"Broome",
    "sg:classifiers":[
        {
            "category":"Communications",
            "subcategory":"News Services",
            "type":"Services"
        }
    ],
    "sg:phone":"+61 8 9193 5025",
    "sg:postcode":"6725",
    "sg:province":"WA",
    "sg:tags":[
        "information",
        "tourist",
        "attractions"
    ],
    "wof:name":"Broome Hovercraft",
    "wof:placetype":"venue"
},
  "geometry": {"coordinates":[122.677589416,-18.2141704559],"type":"Point"}
}