{
  "type": "Feature",
  "properties": {
    "addr:full":"13 George St Mt Evelyn VIC 3796",
    "addr:housenumber":"13",
    "addr:postcode":"3796",
    "addr:street":"George St",
    "iso:country":"AU",
    "sg:address":"13 George St",
    "sg:city":"Mt Evelyn",
    "sg:classifiers":[
        {
            "category":"Building & Trades",
            "subcategory":"Landscaping Services",
            "type":"Services"
        }
    ],
    "sg:phone":"+61 3 9736 2939",
    "sg:postcode":"3796",
    "sg:province":"VIC",
    "sg:tags":[
        "designer",
        "landscape",
        "contractor"
    ],
    "wof:name":"Adam Edwards Garden Improvements & Design",
    "wof:placetype":"venue"
},
  "geometry": {"coordinates":[145.37028503400001,-37.7855758667],"type":"Point"}
}