{
  "type": "Feature",
  "properties": {
    "iso:country":"AU",
    "sg:address":"57 Service St",
    "sg:city":"Bairnsdale",
    "sg:classifiers":[
        {
            "category":"Retail",
            "subcategory":"Auto Repair",
            "type":"Services"
        }
    ],
    "sg:phone":"+61 3 5152 1767",
    "sg:postcode":"3875",
    "sg:province":"VIC",
    "sg:tags":[
        "muffler",
        "exhaust",
        "system"
    ],
    "wof:name":"Riviera Exhausts",
    "wof:placetype":"venue"
},
  "geometry": {"coordinates":[147.63006591800001,-37.8278007507],"type":"Point"}
}