{
  "type": "Feature",
  "properties": {
    "addr:full":"4 Gladstone St Moorooka QLD 4105",
    "addr:housenumber":"4",
    "addr:postcode":"4105",
    "addr:street":"Gladstone St",
    "iso:country":"AU",
    "sg:address":"4 Gladstone St",
    "sg:city":"Moorooka",
    "sg:classifiers":[
        {
            "category":"Home & Garden",
            "subcategory":"Carpets & Floor Coverings",
            "type":"Retail Goods"
        }
    ],
    "sg:phone":"+61 7 3277 2630",
    "sg:postcode":"4105",
    "sg:province":"QLD",
    "sg:tags":[
        "mat",
        "matting"
    ],
    "wof:name":"Cleantex Services Pty Ltd",
    "wof:placetype":"venue"
},
  "geometry": {"coordinates":[153.019363403,-27.5440158844],"type":"Point"}
}