{
  "type": "Feature",
  "properties": {
    "addr:full":"314 Childs Rd Mill Park VIC 3082",
    "addr:housenumber":"314",
    "addr:postcode":"3082",
    "addr:street":"Childs Rd",
    "iso:country":"AU",
    "sg:address":"314 Childs Rd",
    "sg:city":"Mill Park",
    "sg:classifiers":[
        {
            "category":"Health Services",
            "subcategory":"Health Practitioner",
            "type":"Services"
        }
    ],
    "sg:phone":"+61 3 9807 8996",
    "sg:postcode":"3082",
    "sg:province":"VIC",
    "sg:tags":[
        "acupuncture"
    ],
    "wof:name":"Ann Zhu Chinese Med. Dr.",
    "wof:placetype":"venue"
},
  "geometry": {"coordinates":[145.061813355,-37.6672286987],"type":"Point"}
}