{
  "type": "Feature",
  "properties": {
    "addr:full":"Mitchell Centre 59 Mitchell St Darwin NT 0800",
    "addr:housenumber":"59",
    "addr:postcode":"nt 0800",
    "addr:street":"Mitchell St",
    "iso:country":"AU",
    "sg:address":"Mitchell Centre 59 Mitchell St",
    "sg:city":"Darwin",
    "sg:classifiers":[
        {
            "category":"Banks & Credit Unions",
            "subcategory":"Bank",
            "type":"Services"
        }
    ],
    "sg:phone":"+61 13 11 82",
    "sg:postcode":"0800",
    "sg:province":"NT",
    "sg:tags":[
        "society"
    ],
    "wof:name":"Savings & Loans Credit Union",
    "wof:placetype":"venue"
},
  "geometry": {"coordinates":[130.83978271500001,-12.4631958008],"type":"Point"}
}