{
  "type": "Feature",
  "properties": {
    "iso:country":"AU",
    "sg:address":"Cnr Albert & Railway Sts",
    "sg:city":"Wickham",
    "sg:classifiers":[
        {
            "category":"Manufacturing",
            "subcategory":"Motor Vehicles & Parts",
            "type":"Manufacturing & Wholesale Goods"
        }
    ],
    "sg:phone":"+61 2 4922 0550",
    "sg:postcode":"2293",
    "sg:province":"NSW",
    "sg:tags":[
        "replacement"
    ],
    "wof:name":"Kloster Ford Newcastle",
    "wof:placetype":"venue"
},
  "geometry": {"coordinates":[151.75677490199999,-32.9197235107],"type":"Point"}
}