{
  "type": "Feature",
  "properties": {
    "addr:full":"Meehan St Yass NSW 2582",
    "addr:postcode":"2582",
    "addr:street":"Meehan St",
    "iso:country":"AU",
    "sg:address":"Meehan St",
    "sg:city":"Yass",
    "sg:classifiers":[
        {
            "category":"Shopping",
            "subcategory":"Clothing, Apparel, & Fashions",
            "type":"Retail Goods"
        }
    ],
    "sg:phone":"+61 2 6226 1371",
    "sg:postcode":"2582",
    "sg:province":"NSW",
    "sg:tags":[
        "recycled",
        "clothing"
    ],
    "wof:name":"St Vincent De Paul Socy",
    "wof:placetype":"venue"
},
  "geometry": {"coordinates":[148.91021728499999,-34.8427696228],"type":"Point"}
}