{
  "type": "Feature",
  "properties": {
    "addr:full":"131-137 Wright St East Devonport TAS 7310",
    "addr:housenumber":"131-137",
    "addr:postcode":"7310",
    "addr:street":"Wright St East",
    "iso:country":"AU",
    "sg:address":"131-137 Wright St",
    "sg:city":"East Devonport",
    "sg:classifiers":[
        {
            "category":"Professional",
            "type":"Services"
        }
    ],
    "sg:phone":"+61 3 6498 6300",
    "sg:postcode":"7310",
    "sg:province":"TAS",
    "sg:tags":[
        "transport"
    ],
    "wof:name":"Chas Kelly Transport",
    "wof:placetype":"venue"
},
  "geometry": {"coordinates":[146.36929321299999,-41.1861343384],"type":"Point"}
}