{
  "type": "Feature",
  "properties": {
    "iso:country":"AU",
    "sg:address":"11 Ninth St",
    "sg:city":"Home Hill",
    "sg:classifiers":[
        {
            "category":"Building & Trades",
            "subcategory":"Pest Control",
            "type":"Services"
        }
    ],
    "sg:phone":"+61 412 660 160",
    "sg:postcode":"4806",
    "sg:province":"QLD",
    "wof:name":"Flag Pest Control",
    "wof:placetype":"venue"
},
  "geometry": {"coordinates":[147.41180419899999,-19.6638698578],"type":"Point"}
}