{
  "type": "Feature",
  "properties": {
    "addr:full":"Lambhill Crs Highton VIC 3216",
    "addr:postcode":"3216",
    "addr:street":"Lambhill Crs",
    "iso:country":"AU",
    "sg:address":"Lambhill Crs",
    "sg:city":"Highton",
    "sg:classifiers":[
        {
            "category":"Education",
            "subcategory":"School",
            "type":"Public Place"
        }
    ],
    "sg:phone":"+61 3 5243 2521",
    "sg:postcode":"3216",
    "sg:province":"VIC",
    "sg:tags":[
        "state",
        "except",
        "nsw"
    ],
    "wof:name":"Montpelliar Primary School",
    "wof:placetype":"venue"
},
  "geometry": {"coordinates":[144.318756103,-38.1721496582],"type":"Point"}
}