{
  "type": "Feature",
  "properties": {
    "addr:full":"475 Wanna Wanna Rd Queanbeyan ACT 2620",
    "addr:housenumber":"475",
    "addr:postcode":"2620",
    "addr:street":"Wanna Rd",
    "iso:country":"AU",
    "sg:address":"475 Wanna Wanna Rd",
    "sg:city":"Queanbeyan",
    "sg:classifiers":[
        {
            "category":"Professional",
            "subcategory":"Management & Consulting",
            "type":"Services"
        }
    ],
    "sg:phone":"+61 2 6298 1890",
    "sg:postcode":"2620",
    "sg:province":"ACT",
    "sg:tags":[
        "consultant",
        "energy"
    ],
    "wof:name":"Keith Woodward",
    "wof:placetype":"venue"
},
  "geometry": {"coordinates":[149.304779053,-35.395565033],"type":"Point"}
}