{
  "type": "Feature",
  "properties": {
    "addr:full":"103A Lockyer St Adamstown NSW 2289",
    "addr:housenumber":"103a",
    "addr:postcode":"2289",
    "addr:street":"Lockyer St",
    "iso:country":"AU",
    "sg:address":"103A Lockyer St",
    "sg:city":"Adamstown",
    "sg:classifiers":[
        {
            "category":"Building & Trades",
            "subcategory":"Pest Control",
            "type":"Services"
        }
    ],
    "sg:phone":"+61 2 4963 6863",
    "sg:postcode":"2289",
    "sg:province":"NSW",
    "wof:name":"Adamstown Pest Control",
    "wof:placetype":"venue"
},
  "geometry": {"coordinates":[151.730926514,-32.9376068115],"type":"Point"}
}