{
  "type": "Feature",
  "properties": {
    "addr:full":"21 Okano St Moura QLD 4718",
    "addr:housenumber":"21",
    "addr:postcode":"4718",
    "addr:street":"Okano St",
    "iso:country":"AU",
    "sg:address":"21 Okano St",
    "sg:city":"Moura",
    "sg:classifiers":[
        {
            "category":"Utilities",
            "subcategory":"Water",
            "type":"Services"
        }
    ],
    "sg:phone":"+61 7 4997 3095",
    "sg:postcode":"4718",
    "sg:province":"QLD",
    "sg:tags":[
        "cartage"
    ],
    "wof:name":"Moura Sand & Gravel Pty Ltd",
    "wof:placetype":"venue"
},
  "geometry": {"coordinates":[149.97718810999999,-24.5631885529],"type":"Point"}
}