{
  "type": "Feature",
  "properties": {
    "iso:country":"AU",
    "sg:address":"29 Lorraine Ave",
    "sg:city":"Marcoola Beach",
    "sg:classifiers":[
        {
            "category":"Building & Trades",
            "subcategory":"Construction",
            "type":"Services"
        }
    ],
    "sg:phone":"+61 1300 362 084",
    "sg:postcode":"4564",
    "sg:province":"QLD",
    "sg:tags":[
        "contractor"
    ],
    "wof:name":"Dall Designer Homes",
    "wof:placetype":"venue"
},
  "geometry": {"coordinates":[153.09327697800001,-26.5844745636],"type":"Point"}
}