{
  "type": "Feature",
  "properties": {
    "addr:full":"330 Ballarat Rd Braybrook VIC 3019",
    "addr:housenumber":"330",
    "addr:postcode":"3019",
    "addr:street":"Ballarat Rd",
    "iso:country":"AU",
    "sg:address":"330 Ballarat Rd",
    "sg:city":"Braybrook",
    "sg:classifiers":[
        {
            "category":"Manufacturing",
            "subcategory":"Textiles",
            "type":"Manufacturing & Wholesale Goods"
        }
    ],
    "sg:phone":"+61 3 9300 5800",
    "sg:postcode":"3019",
    "sg:province":"VIC",
    "sg:tags":[
        "knitted",
        "woven",
        "fabric"
    ],
    "wof:name":"Auzcotex Pty Ltd",
    "wof:placetype":"venue"
},
  "geometry": {"coordinates":[144.85078430199999,-37.7792625427],"type":"Point"}
}