{
  "type": "Feature",
  "properties": {
    "iso:country":"AU",
    "sg:address":"3/ 41 Sherwood Rd",
    "sg:city":"Toowong",
    "sg:classifiers":[
        {
            "category":"Health Services",
            "subcategory":"Health Practitioner",
            "type":"Services"
        }
    ],
    "sg:phone":"+61 7 3870 0955",
    "sg:postcode":"4066",
    "sg:province":"QLD",
    "sg:tags":[
        "psychologist"
    ],
    "wof:name":"Toowong Counselling Centre",
    "wof:placetype":"venue"
},
  "geometry": {"coordinates":[152.99101257300001,-27.4852256775],"type":"Point"}
}