{
  "type": "Feature",
  "properties": {
    "iso:country":"AU",
    "sg:address":"538 Kooringal Rd",
    "sg:city":"Wagga Wagga",
    "sg:classifiers":[
        {
            "category":"Building & Trades",
            "subcategory":"Construction",
            "type":"Services"
        }
    ],
    "sg:phone":"+61 2 6922 6092",
    "sg:postcode":"2650",
    "sg:province":"NSW",
    "sg:tags":[
        "fencing",
        "contractor"
    ],
    "wof:name":"Cochrane Nelder",
    "wof:placetype":"venue"
},
  "geometry": {"coordinates":[147.375167847,-35.1526870728],"type":"Point"}
}