{
  "type": "Feature",
  "properties": {
    "iso:country":"AU",
    "sg:address":"159 Wheatsheaf Rd",
    "sg:city":"Glenroy",
    "sg:classifiers":[
        {
            "category":"Communications",
            "type":"Services"
        }
    ],
    "sg:phone":"+61 3 9306 4675",
    "sg:postcode":"3046",
    "sg:province":"VIC",
    "sg:tags":[
        "public",
        "system",
        "address"
    ],
    "wof:name":"All Sound Systems",
    "wof:placetype":"venue"
},
  "geometry": {"coordinates":[144.91880798299999,-37.7062911987],"type":"Point"}
}