{
  "type": "Feature",
  "properties": {
    "iso:country":"AU",
    "sg:address":"Unit 3, 2- 4 Woolworths Ave",
    "sg:city":"Warilla",
    "sg:classifiers":[
        {
            "category":"Professional",
            "subcategory":"Printing & Photocopies",
            "type":"Services"
        }
    ],
    "sg:phone":"+61 2 4297 3883",
    "sg:postcode":"2528",
    "sg:province":"NSW",
    "sg:tags":[
        "trophy"
    ],
    "wof:name":"M M Sports Warehouse",
    "wof:placetype":"venue"
},
  "geometry": {"coordinates":[150.864105225,-34.5474624634],"type":"Point"}
}