{
  "type": "Feature",
  "properties": {
    "iso:country":"AU",
    "sg:address":"39 Bridge St",
    "sg:city":"Richmond",
    "sg:classifiers":[
        {
            "category":"Food & Beverages",
            "subcategory":"Groceries & Convenience Stores",
            "type":"Retail Goods"
        }
    ],
    "sg:phone":"+61 3 6260 2187",
    "sg:postcode":"7025",
    "sg:province":"TAS",
    "wof:name":"Richmond Friendly Grocer",
    "wof:placetype":"venue"
},
  "geometry": {"coordinates":[147.43829345699999,-42.7349319458],"type":"Point"}
}