{
  "type": "Feature",
  "properties": {
    "addr:full":"6 Cherbourg Ave Beaumaris VIC 3193",
    "addr:housenumber":"6",
    "addr:postcode":"3193",
    "addr:street":"Cherbourg Ave",
    "iso:country":"AU",
    "sg:address":"6 Cherbourg Ave",
    "sg:city":"Beaumaris",
    "sg:classifiers":[
        {
            "category":"Building & Trades",
            "subcategory":"Construction",
            "type":"Services"
        }
    ],
    "sg:phone":"+61 3 9584 6144",
    "sg:postcode":"3193",
    "sg:province":"VIC",
    "sg:tags":[
        "contractor"
    ],
    "wof:name":"Commercial & Office Modifications Pty Ltd",
    "wof:placetype":"venue"
},
  "geometry": {"coordinates":[145.04675293,-37.9739532471],"type":"Point"}
}