{
  "type": "Feature",
  "properties": {
    "iso:country":"AU",
    "sg:address":"273 Camberwell Rd",
    "sg:city":"Camberwell",
    "sg:classifiers":[
        {
            "category":"Health Services",
            "subcategory":"Doctor",
            "type":"Services"
        }
    ],
    "sg:phone":"+61 3 9882 5151",
    "sg:postcode":"3124",
    "sg:province":"VIC",
    "sg:tags":[
        "medical",
        "practitioner"
    ],
    "wof:name":"Woolhouse, Michelle Dr",
    "wof:placetype":"venue"
},
  "geometry": {"coordinates":[145.05778503400001,-37.8320274353],"type":"Point"}
}