{
  "type": "Feature",
  "properties": {
    "addr:full":"Unit 2, 10 Victoria St Bunbury WA 6230",
    "addr:housenumber":"10",
    "addr:postcode":"6230",
    "addr:street":"Victoria St",
    "iso:country":"AU",
    "sg:address":"Unit 2, 10 Victoria St",
    "sg:city":"Bunbury",
    "sg:classifiers":[
        {
            "category":"Banks & Credit Unions",
            "subcategory":"Financial Services",
            "type":"Services"
        }
    ],
    "sg:phone":"+61 8 9791 1116",
    "sg:postcode":"6230",
    "sg:province":"WA",
    "sg:tags":[
        "planning"
    ],
    "wof:name":"Count Wealth Accountants",
    "wof:placetype":"venue"
},
  "geometry": {"coordinates":[115.637039,-33.319649],"type":"Point"}
}