{
  "type": "Feature",
  "properties": {
    "iso:country":"AU",
    "sg:address":"PO Box 254",
    "sg:city":"Gawler",
    "sg:classifiers":[
        {
            "category":"Building & Trades",
            "subcategory":"Construction",
            "type":"Services"
        }
    ],
    "sg:phone":"+61 8 8523 4898",
    "sg:postcode":"5118",
    "sg:province":"SA",
    "sg:tags":[
        "concrete",
        "treatment",
        "repair"
    ],
    "wof:name":"Spray Pave Gawler",
    "wof:placetype":"venue"
},
  "geometry": {"coordinates":[138.72822600000001,-34.596329],"type":"Point"}
}