{
  "type": "Feature",
  "properties": {
    "iso:country":"AU",
    "sg:address":"16 Prince Of Wales Pde",
    "sg:city":"Alexandra Hills",
    "sg:classifiers":[
        {
            "category":"Building & Trades",
            "subcategory":"Plumbing",
            "type":"Services"
        }
    ],
    "sg:phone":"+61 7 3820 2955",
    "sg:postcode":"4161",
    "sg:province":"QLD",
    "sg:tags":[
        "plumber",
        "gasfitters"
    ],
    "wof:name":"Jakarta Plumbing & Drainage Services",
    "wof:placetype":"venue"
},
  "geometry": {"coordinates":[153.22259521500001,-27.5212612152],"type":"Point"}
}