{
  "type": "Feature",
  "properties": {
    "addr:full":"Suite 2 52 Gordon St Mackay QLD 4740",
    "addr:housenumber":"52",
    "addr:postcode":"4740",
    "addr:street":"Gordon St",
    "iso:country":"AU",
    "sg:address":"Suite 2 52 Gordon St",
    "sg:city":"Mackay",
    "sg:classifiers":[
        {
            "category":"Health Services",
            "subcategory":"Dentist",
            "type":"Services"
        }
    ],
    "sg:phone":"+61 7 4953 5804",
    "sg:postcode":"4740",
    "sg:province":"QLD",
    "wof:name":"Rosemarie Kirkland Pty Ltd",
    "wof:placetype":"venue"
},
  "geometry": {"coordinates":[149.181625,-21.142565],"type":"Point"}
}