{
  "type": "Feature",
  "properties": {
    "addr:full":"PO Box 203 Exmouth WA 6707",
    "addr:postcode":"6707",
    "iso:country":"AU",
    "sg:address":"PO Box 203",
    "sg:city":"Exmouth",
    "sg:classifiers":[
        {
            "category":"Travel",
            "subcategory":"Travel Agent",
            "type":"Entertainment"
        }
    ],
    "sg:phone":"+61 8 9949 1550",
    "sg:postcode":"6707",
    "sg:province":"WA",
    "sg:tags":[
        "tour",
        "holiday",
        "adventure"
    ],
    "wof:name":"Ningaloo Safari Tours",
    "wof:placetype":"venue"
},
  "geometry": {"coordinates":[114.133277893,-21.9462604523],"type":"Point"}
}