{
  "type": "Feature",
  "properties": {
    "addr:full":"Lilliput St Broadmeadows VIC 3047",
    "addr:postcode":"3047",
    "addr:street":"Lilliput St",
    "iso:country":"AU",
    "sg:address":"Lilliput St",
    "sg:city":"Broadmeadows",
    "sg:classifiers":[
        {
            "category":"Social Services",
            "subcategory":"Child Care",
            "type":"Services"
        }
    ],
    "sg:phone":"+61 3 9309 7979",
    "sg:postcode":"3047",
    "sg:province":"VIC",
    "sg:tags":[
        "support",
        "health"
    ],
    "wof:name":"Maternal & Child Health Centres",
    "wof:placetype":"venue"
},
  "geometry": {"coordinates":[144.92239379899999,-37.6712150574],"type":"Point"}
}