{
  "type": "Feature",
  "properties": {
    "addr:full":"262 Grubb St North Rockhampton QLD 4701",
    "addr:housenumber":"262",
    "addr:postcode":"4701",
    "addr:street":"Grubb St North",
    "iso:country":"AU",
    "sg:address":"262 Grubb St",
    "sg:city":"North Rockhampton",
    "sg:classifiers":[
        {
            "category":"Building & Trades",
            "subcategory":"Construction",
            "type":"Services"
        }
    ],
    "sg:phone":"+61 7 4926 2787",
    "sg:postcode":"4701",
    "sg:province":"QLD",
    "sg:tags":[
        "renovation",
        "alterations",
        "extension",
        "contractor"
    ],
    "wof:name":"Boswood T G & J Pty Ltd",
    "wof:placetype":"venue"
},
  "geometry": {"coordinates":[150.54124450699999,-23.3704071045],"type":"Point"}
}