{
  "type": "Feature",
  "properties": {
    "addr:full":"Shop 12, Gallery Level, Brisbane Arcade Queen Street Mall Brisbane QLD 4000",
    "addr:housenumber":"shop 12;brisbane",
    "addr:postcode":"4000",
    "addr:street":"Queen Street Mall",
    "iso:country":"AU",
    "sg:address":"Shop 12, Gallery Level, Brisbane Arcade Queen Street Mall",
    "sg:city":"Brisbane",
    "sg:classifiers":[
        {
            "category":"Personal",
            "subcategory":"Beauty Salon",
            "type":"Services"
        }
    ],
    "sg:phone":"+61 7 3229 6923",
    "sg:postcode":"4000",
    "sg:province":"QLD",
    "wof:name":"Unique Nails",
    "wof:placetype":"venue"
},
  "geometry": {"coordinates":[153.02276611299999,-27.4651203156],"type":"Point"}
}