{
  "type": "Feature",
  "properties": {
    "addr:full":"368 Settlement Rd Thomastown VIC 3074",
    "addr:housenumber":"368",
    "addr:postcode":"3074",
    "addr:street":"Settlement Rd",
    "iso:country":"AU",
    "sg:address":"368 Settlement Rd",
    "sg:city":"Thomastown",
    "sg:classifiers":[
        {
            "category":"Professional",
            "type":"Services"
        }
    ],
    "sg:phone":"+61 3 9464 6456",
    "sg:postcode":"3074",
    "sg:province":"VIC",
    "sg:tags":[
        "transport"
    ],
    "wof:name":"Region Peak Transport",
    "wof:placetype":"venue"
},
  "geometry": {"coordinates":[145.017089844,-37.6881599426],"type":"Point"}
}