{
  "type": "Feature",
  "properties": {
    "iso:country":"AU",
    "sg:address":"Shop 8",
    "sg:city":"Rivergum Village Mill Park",
    "sg:classifiers":[
        {
            "category":"Health Services",
            "subcategory":"Optometrist",
            "type":"Services"
        }
    ],
    "sg:phone":"+61 3 9436 9644",
    "sg:postcode":"3082",
    "sg:province":"VIC",
    "wof:name":"Campanella Giorgio & Scalora Daniela",
    "wof:placetype":"venue"
},
  "geometry": {"coordinates":[145.06466674800001,-37.671169281],"type":"Point"}
}