{
  "type": "Feature",
  "properties": {
    "iso:country":"AU",
    "sg:address":"15/ 1 Hawkesbury Rd",
    "sg:city":"Springwood",
    "sg:classifiers":[
        {
            "category":"Building & Trades",
            "subcategory":"Construction",
            "type":"Services"
        }
    ],
    "sg:phone":"+61 2 4751 6383",
    "sg:postcode":"2777",
    "sg:province":"NSW",
    "sg:tags":[
        "management"
    ],
    "wof:name":"Haddock Constructions Pty Ltd",
    "wof:placetype":"venue"
},
  "geometry": {"coordinates":[150.57164001500001,-33.6975364685],"type":"Point"}
}