{
  "type": "Feature",
  "properties": {
    "iso:country":"AU",
    "sg:address":"5 Prospect Rd",
    "sg:city":"Bendigo East",
    "sg:classifiers":[
        {
            "category":"Home & Garden",
            "subcategory":"Hardware",
            "type":"Retail Goods"
        }
    ],
    "sg:phone":"+61 3 5444 4594",
    "sg:postcode":"3550",
    "sg:province":"VIC",
    "sg:tags":[
        "supply",
        "maker",
        "cabinet"
    ],
    "wof:name":"Lincoln Sentry",
    "wof:placetype":"venue"
},
  "geometry": {"coordinates":[144.31427001899999,-36.7438926697],"type":"Point"}
}