{
  "type": "Feature",
  "properties": {
    "iso:country":"AU",
    "sg:address":"1 Keane St",
    "sg:city":"Wanneroo",
    "sg:classifiers":[
        {
            "category":"Arts & Performance",
            "subcategory":"Music",
            "type":"Entertainment"
        }
    ],
    "sg:phone":"+61 8 9405 6450",
    "sg:postcode":"6065",
    "sg:province":"WA",
    "sg:tags":[
        "mobile",
        "jockey",
        "disc"
    ],
    "sg:website":"http://www.showco.com.au",
    "wof:name":"Showco",
    "wof:placetype":"venue"
},
  "geometry": {"coordinates":[115.801338196,-31.7529335022],"type":"Point"}
}