{
  "type": "Feature",
  "properties": {
    "iso:country":"AU",
    "sg:address":"10 Edinburgh Rd",
    "sg:city":"Albany",
    "sg:classifiers":[
        {
            "category":"Farming",
            "subcategory":"Farm & Veterinary Services",
            "type":"Manufacturing & Wholesale Goods"
        }
    ],
    "sg:phone":"+61 8 9841 4275",
    "sg:postcode":"6330",
    "sg:province":"WA",
    "sg:tags":[
        "contracting"
    ],
    "wof:name":"Webb L G",
    "wof:placetype":"venue"
},
  "geometry": {"coordinates":[117.853660584,-34.9879646301],"type":"Point"}
}