{
  "type": "Feature",
  "properties": {
    "iso:country":"AU",
    "sg:address":"132 Ryhill Rd",
    "sg:city":"Sunnybank Hills",
    "sg:classifiers":[
        {
            "category":"Personal",
            "subcategory":"Massage",
            "type":"Services"
        }
    ],
    "sg:phone":"+61 7 3344 1401",
    "sg:postcode":"4109",
    "sg:province":"QLD",
    "sg:tags":[
        "therapy"
    ],
    "wof:name":"Daley Lee",
    "wof:placetype":"venue"
},
  "geometry": {"coordinates":[153.04066467300001,-27.583442688],"type":"Point"}
}