{
  "type": "Feature",
  "properties": {
    "addr:full":"1/ 65 Logan River Rd Beenleigh QLD 4207",
    "addr:housenumber":"/ 65",
    "addr:postcode":"4207",
    "addr:street":"Logan River Rd",
    "iso:country":"AU",
    "sg:address":"1/ 65 Logan River Rd",
    "sg:city":"Beenleigh",
    "sg:classifiers":[
        {
            "category":"Manufacturing",
            "subcategory":"Metals",
            "type":"Manufacturing & Wholesale Goods"
        }
    ],
    "sg:phone":"+61 7 3804 7444",
    "sg:postcode":"4207",
    "sg:province":"QLD",
    "sg:tags":[
        "wholesaler",
        "aluminium",
        "mfrs"
    ],
    "wof:name":"Direct Aluminium",
    "wof:placetype":"venue"
},
  "geometry": {"coordinates":[153.186447144,-27.7136726379],"type":"Point"}
}