{
  "type": "Feature",
  "properties": {
    "addr:full":"15 Hampshire Rd Glen Waverley VIC 3150",
    "addr:housenumber":"15",
    "addr:postcode":"3150",
    "addr:street":"Hampshire Rd",
    "iso:country":"AU",
    "sg:address":"15 Hampshire Rd",
    "sg:city":"Glen Waverley",
    "sg:classifiers":[
        {
            "category":"Professional",
            "subcategory":"Printing & Photocopies",
            "type":"Services"
        }
    ],
    "sg:phone":"+61 3 9560 7888",
    "sg:postcode":"3150",
    "sg:province":"VIC",
    "sg:tags":[
        "photocopying"
    ],
    "wof:name":"Minuteman Press",
    "wof:placetype":"venue"
},
  "geometry": {"coordinates":[145.14393615700001,-37.9006195068],"type":"Point"}
}