{
  "type": "Feature",
  "properties": {
    "addr:full":"45 Ravendale Rd Port Lincoln SA 5606",
    "addr:housenumber":"45",
    "addr:postcode":"5606",
    "addr:street":"Ravendale Rd",
    "iso:country":"AU",
    "sg:address":"45 Ravendale Rd",
    "sg:city":"Port Lincoln",
    "sg:classifiers":[
        {
            "category":"Retail",
            "subcategory":"Auto Repair",
            "type":"Services"
        }
    ],
    "sg:phone":"+61 8 8683 1400",
    "sg:postcode":"5606",
    "sg:province":"SA",
    "sg:tags":[
        "repairer",
        "motor",
        "engineer"
    ],
    "wof:name":"Q Mechanical Services",
    "wof:placetype":"venue"
},
  "geometry": {"coordinates":[135.86454800000001,-34.736778],"type":"Point"}
}