{
  "type": "Feature",
  "properties": {
    "iso:country":"AU",
    "sg:address":"45 Ravendale Rd",
    "sg:city":"Port Lincoln",
    "sg:classifiers":[
        {
            "category":"Retail",
            "subcategory":"Auto Repair",
            "type":"Services"
        }
    ],
    "sg:phone":"+61 8 8683 1400",
    "sg:postcode":"5606",
    "sg:province":"SA",
    "sg:tags":[
        "repairer",
        "motor",
        "engineer"
    ],
    "wof:name":"Q Mechanical Services",
    "wof:placetype":"venue"
},
  "geometry": {"coordinates":[135.864548,-34.736778],"type":"Point"}
}