{
  "type": "Feature",
  "properties": {
    "iso:country":"AU",
    "sg:address":"Wallarah Rd",
    "sg:city":"Gorokan",
    "sg:classifiers":[
        {
            "category":"Wholesale",
            "subcategory":"Seafood",
            "type":"Manufacturing & Wholesale Goods"
        }
    ],
    "sg:phone":"+61 2 4392 1603",
    "sg:postcode":"2263",
    "sg:province":"NSW",
    "sg:tags":[
        "fish"
    ],
    "wof:name":"Commercial Fishermen's Co-operative Limited",
    "wof:placetype":"venue"
},
  "geometry": {"coordinates":[151.50357099999999,-33.254795],"type":"Point"}
}