{
  "type": "Feature",
  "properties": {
    "iso:country":"AU",
    "sg:address":"287 Albert St",
    "sg:city":"Brunswick",
    "sg:classifiers":[
        {
            "category":"Retail",
            "subcategory":"Auto Repair",
            "type":"Services"
        }
    ],
    "sg:phone":"+61 3 9387 7266",
    "sg:postcode":"3056",
    "sg:province":"VIC",
    "sg:tags":[
        "beater",
        "painter",
        "panel"
    ],
    "wof:name":"Galda Smash Repairs",
    "wof:placetype":"venue"
},
  "geometry": {"coordinates":[144.96034240700001,-37.7685317993],"type":"Point"}
}