{
  "type": "Feature",
  "properties": {
    "iso:country":"AU",
    "sg:address":"Unit 1, 14-16 Stanhope Gardens",
    "sg:city":"Midvale",
    "sg:classifiers":[
        {
            "category":"Professional",
            "type":"Services"
        }
    ],
    "sg:phone":"+61 8 9274 2399",
    "sg:postcode":"6056",
    "sg:province":"WA",
    "sg:tags":[
        "spray",
        "painting"
    ],
    "wof:name":"Auto Accident Repair Centre",
    "wof:placetype":"venue"
},
  "geometry": {"coordinates":[116.029197693,-31.8927593231],"type":"Point"}
}