{
  "type": "Feature",
  "properties": {
    "addr:full":"U34/ 1-3 Beresford Rd Strathfield NSW 2135",
    "addr:housenumber":"1-3",
    "addr:postcode":"2135",
    "addr:street":"/;Beresford Rd",
    "iso:country":"AU",
    "sg:address":"U34/ 1-3 Beresford Rd",
    "sg:city":"Strathfield",
    "sg:classifiers":[
        {
            "category":"Professional",
            "subcategory":"Accounting & Tax Preparation",
            "type":"Services"
        }
    ],
    "sg:phone":"+61 2 9763 2086",
    "sg:postcode":"2135",
    "sg:province":"NSW",
    "sg:tags":[
        "accountant",
        "auditor"
    ],
    "wof:name":"R K Accounting Pty Ltd",
    "wof:placetype":"venue"
},
  "geometry": {"coordinates":[151.090301514,-33.8695526123],"type":"Point"}
}