{
  "type": "Feature",
  "properties": {
    "iso:country":"AU",
    "sg:address":"24- 26 Pearl St",
    "sg:city":"Kingscliff",
    "sg:classifiers":[
        {
            "category":"Restaurant",
            "type":"Food & Drink"
        }
    ],
    "sg:phone":"+61 2 6674 0600",
    "sg:postcode":"2487",
    "sg:province":"NSW",
    "sg:tags":[
        "pizza"
    ],
    "wof:name":"Eagle Boys Pizza",
    "wof:placetype":"venue"
},
  "geometry": {"coordinates":[153.57562255900001,-28.2557945251],"type":"Point"}
}