{
  "type": "Feature",
  "properties": {
    "iso:country":"AU",
    "sg:address":"2 Byron St",
    "sg:city":"Glenelg",
    "sg:classifiers":[
        {
            "category":"Retail",
            "subcategory":"Repair Shop",
            "type":"Services"
        }
    ],
    "sg:phone":"+61 8 8294 7441",
    "sg:postcode":"5045",
    "sg:province":"SA",
    "sg:tags":[
        "machine",
        "sewing"
    ],
    "wof:name":"Barbs Sew & Knits",
    "wof:placetype":"venue"
},
  "geometry": {"coordinates":[138.51698300000001,-34.980022],"type":"Point"}
}