{
  "type": "Feature",
  "properties": {
    "addr:full":"78 Murray Rd Corrimal East NSW 2518",
    "addr:housenumber":"78",
    "addr:postcode":"2518",
    "addr:street":"Murray Rd",
    "iso:country":"AU",
    "sg:address":"78 Murray Rd",
    "sg:city":"Corrimal East",
    "sg:classifiers":[
        {
            "category":"Social Services",
            "subcategory":"Child Care",
            "type":"Services"
        }
    ],
    "sg:phone":"+61 2 4283 6233",
    "sg:postcode":"2518",
    "sg:province":"NSW",
    "wof:name":"KU Corrimal East Preschool",
    "wof:placetype":"venue"
},
  "geometry": {"coordinates":[150.91322299999999,-34.376488],"type":"Point"}
}