{
  "type": "Feature",
  "properties": {
    "addr:full":"65 Main St Mittagong NSW 2575",
    "addr:housenumber":"65",
    "addr:postcode":"2575",
    "addr:street":"Main St",
    "iso:country":"AU",
    "sg:address":"65 Main St",
    "sg:city":"Mittagong",
    "sg:classifiers":[
        {
            "category":"Real Estate",
            "subcategory":"Real Estate Agent",
            "type":"Services"
        }
    ],
    "sg:phone":"+61 2 4871 2400",
    "sg:postcode":"2575",
    "sg:province":"NSW",
    "wof:name":"Mittagong Real Estate",
    "wof:placetype":"venue"
},
  "geometry": {"coordinates":[150.44767761200001,-34.4511146545],"type":"Point"}
}