{
  "type": "Feature",
  "properties": {
    "iso:country":"AU",
    "sg:address":"12 Mulwala Drv",
    "sg:city":"Wyee Point",
    "sg:classifiers":[
        {
            "category":"Retail",
            "subcategory":"Driving School",
            "type":"Services"
        }
    ],
    "sg:phone":"+61 414 434 178",
    "sg:postcode":"2259",
    "sg:province":"NSW",
    "wof:name":"Alpha Driving School",
    "wof:placetype":"venue"
},
  "geometry": {"coordinates":[151.523513794,-33.1437568665],"type":"Point"}
}