{
  "type": "Feature",
  "properties": {
    "iso:country":"AU",
    "sg:address":"23a Railway Pde",
    "sg:city":"Kogarah",
    "sg:classifiers":[
        {
            "category":"Shopping",
            "subcategory":"Shoes",
            "type":"Retail Goods"
        }
    ],
    "sg:phone":"+61 2 9588 4097",
    "sg:postcode":"2217",
    "sg:province":"NSW",
    "sg:tags":[
        "footwear"
    ],
    "wof:name":"Kogarah Shoes",
    "wof:placetype":"venue"
},
  "geometry": {"coordinates":[151.132507,-33.963207],"type":"Point"}
}