{
  "type": "Feature",
  "properties": {
    "iso:country":"AU",
    "sg:address":"PO Box 140",
    "sg:city":"Lower Plenty",
    "sg:classifiers":[
        {
            "category":"Professional",
            "subcategory":"Art Services",
            "type":"Services"
        }
    ],
    "sg:phone":"+61 422 131 972",
    "sg:postcode":"3093",
    "sg:province":"VIC",
    "sg:tags":[
        "graphic",
        "designer"
    ],
    "wof:name":"Sarbee Design",
    "wof:placetype":"venue"
},
  "geometry": {"coordinates":[145.11796569800001,-37.7384605408],"type":"Point"}
}