{
  "type": "Feature",
  "properties": {
    "iso:country":"AU",
    "sg:address":"Unit 15-16, 28 Rudloc Rd",
    "sg:city":"Morley",
    "sg:classifiers":[
        {
            "category":"Shopping",
            "subcategory":"Gifts & Souvenirs",
            "type":"Retail Goods"
        }
    ],
    "sg:phone":"+61 8 6424 8552",
    "sg:postcode":"6062",
    "sg:province":"WA",
    "sg:tags":[
        "shop",
        "supply"
    ],
    "wof:name":"Trendtastic",
    "wof:placetype":"venue"
},
  "geometry": {"coordinates":[115.89791870099999,-31.900970459],"type":"Point"}
}