{
  "type": "Feature",
  "properties": {
    "addr:full":"8 Higlett St Scarborough QLD 4020",
    "addr:housenumber":"8",
    "addr:postcode":"4020",
    "addr:street":"Higlett St",
    "iso:country":"AU",
    "sg:address":"8 Higlett St",
    "sg:city":"Scarborough",
    "sg:classifiers":[
        {
            "category":"Health Services",
            "subcategory":"Medical Lab",
            "type":"Services"
        }
    ],
    "sg:phone":"+61 7 3203 6439",
    "sg:postcode":"4020",
    "sg:province":"QLD",
    "sg:tags":[
        "laboratory",
        "dental"
    ],
    "wof:name":"Gibbon Mike",
    "wof:placetype":"venue"
},
  "geometry": {"coordinates":[153.11225899999999,-27.211641],"type":"Point"}
}