{
  "type": "Feature",
  "properties": {
    "addr:full":"1 Gleeson Rd Burpengary QLD 4505",
    "addr:housenumber":"1",
    "addr:postcode":"4505",
    "addr:street":"Gleeson Rd",
    "iso:country":"AU",
    "sg:address":"1 Gleeson Rd",
    "sg:city":"Burpengary",
    "sg:classifiers":[
        {
            "category":"Commercial Area",
            "type":"Public Place"
        }
    ],
    "sg:phone":"+61 7 3888 1441",
    "sg:postcode":"4505",
    "sg:province":"QLD",
    "sg:tags":[
        "heavy",
        "carrier"
    ],
    "wof:name":"Pine Rivers 24 Hour Towing",
    "wof:placetype":"venue"
},
  "geometry": {"coordinates":[152.96690368599999,-27.1378631592],"type":"Point"}
}