{
  "type": "Feature",
  "properties": {
    "iso:country":"AU",
    "sg:address":"Beilby Pl",
    "sg:city":"Kambah",
    "sg:classifiers":[
        {
            "category":"Retail",
            "subcategory":"Driving School",
            "type":"Services"
        }
    ],
    "sg:phone":"+61 2 6231 3685",
    "sg:postcode":"2902",
    "sg:province":"ACT",
    "wof:name":"D.R.I.V.E",
    "wof:placetype":"venue"
},
  "geometry": {"coordinates":[149.06007385300001,-35.3710289001],"type":"Point"}
}