{
  "type": "Feature",
  "properties": {
    "addr:full":"Suite 25, 809 Pacific Hwy Chatswood NSW 2067",
    "addr:housenumber":"809",
    "addr:postcode":"2067",
    "addr:street":"Pacific Hwy",
    "iso:country":"AU",
    "sg:address":"Suite 25, 809 Pacific Hwy",
    "sg:city":"Chatswood",
    "sg:classifiers":[
        {
            "category":"Professional",
            "subcategory":"Research",
            "type":"Services"
        }
    ],
    "sg:phone":"+61 1800 816 575",
    "sg:postcode":"2067",
    "sg:province":"NSW",
    "sg:tags":[
        "actuary"
    ],
    "wof:name":"SMA Consultants Pty Ltd",
    "wof:placetype":"venue"
},
  "geometry": {"coordinates":[151.17814636200001,-33.7961883545],"type":"Point"}
}