{
  "type": "Feature",
  "properties": {
    "addr:full":"83A Alfred St North Melbourne VIC 3051",
    "addr:housenumber":"83a",
    "addr:postcode":"3051",
    "addr:street":"Alfred St",
    "iso:country":"AU",
    "sg:address":"83A Alfred St",
    "sg:city":"North Melbourne",
    "sg:classifiers":[
        {
            "category":"Professional",
            "subcategory":"Detective & Security Services",
            "type":"Services"
        }
    ],
    "sg:phone":"+61 408 314 315",
    "sg:postcode":"3051",
    "sg:province":"VIC",
    "sg:tags":[
        "guard",
        "patrol"
    ],
    "wof:name":"Ammo Security Services Pty Ltd",
    "wof:placetype":"venue"
},
  "geometry": {"coordinates":[144.93858337399999,-37.7906913757],"type":"Point"}
}