{
  "type": "Feature",
  "properties": {
    "iso:country":"AU",
    "sg:address":"PO Box 149",
    "sg:city":"Two Wells",
    "sg:classifiers":[
        {
            "category":"Banks & Credit Unions",
            "subcategory":"Investment Brokerage",
            "type":"Services"
        }
    ],
    "sg:phone":"+61 401 600 833",
    "sg:postcode":"5501",
    "sg:province":"SA",
    "sg:tags":[
        "pulverising",
        "machinery",
        "grinding"
    ],
    "wof:name":"Roller Grain Rollers",
    "wof:placetype":"venue"
},
  "geometry": {"coordinates":[138.51475500000001,-34.594002],"type":"Point"}
}