{
  "type": "Feature",
  "properties": {
    "addr:full":"87a Cripps St Salisbury QLD 4107",
    "addr:housenumber":"87a",
    "addr:postcode":"4107",
    "addr:street":"Cripps St",
    "iso:country":"AU",
    "sg:address":"87a Cripps St",
    "sg:city":"Salisbury",
    "sg:classifiers":[
        {
            "category":"Organizations",
            "subcategory":"Community Association",
            "type":"Services"
        }
    ],
    "sg:phone":"+61 7 3275 3218",
    "sg:postcode":"4107",
    "sg:province":"QLD",
    "sg:tags":[
        "club",
        "senior",
        "citizen"
    ],
    "wof:name":"Salisbury & District Senior Citizens Centre",
    "wof:placetype":"venue"
},
  "geometry": {"coordinates":[153.03260803200001,-27.5512371063],"type":"Point"}
}