{
  "type": "Feature",
  "properties": {
    "iso:country":"AU",
    "sg:address":"25 Norman St",
    "sg:city":"Port Pirie",
    "sg:classifiers":[
        {
            "category":"Insurance",
            "subcategory":"Insurance Agent",
            "type":"Services"
        }
    ],
    "sg:phone":"+61 8 8632 5588",
    "sg:postcode":"5540",
    "sg:province":"SA",
    "sg:tags":[
        "broker"
    ],
    "wof:name":"Pirie Insurance Brokers",
    "wof:placetype":"venue"
},
  "geometry": {"coordinates":[138.00840759299999,-33.1797027588],"type":"Point"}
}