{
  "type": "Feature",
  "properties": {
    "addr:full":"5/ 13 Waine St Harbord NSW 2096",
    "addr:housenumber":"/ 13",
    "addr:postcode":"2096",
    "addr:street":"Waine St",
    "iso:country":"AU",
    "sg:address":"5/ 13 Waine St",
    "sg:city":"Harbord",
    "sg:classifiers":[
        {
            "category":"Health Services",
            "subcategory":"Health Practitioner",
            "type":"Services"
        }
    ],
    "sg:phone":"+61 2 9440 4992",
    "sg:postcode":"2096",
    "sg:province":"NSW",
    "sg:tags":[
        "acupuncture"
    ],
    "wof:name":"Rose Michael",
    "wof:placetype":"venue"
},
  "geometry": {"coordinates":[151.27804565400001,-33.7797393799],"type":"Point"}
}