{
  "type": "Feature",
  "properties": {
    "iso:country":"AU",
    "sg:address":"Shp 1/ 106 High St",
    "sg:city":"Greta",
    "sg:classifiers":[
        {
            "category":"Health Services",
            "subcategory":"Clinic",
            "type":"Services"
        }
    ],
    "sg:phone":"+61 2 4938 7988",
    "sg:postcode":"2334",
    "sg:province":"NSW",
    "sg:tags":[
        "aromatherapy"
    ],
    "wof:name":"The Natural Wellness Of Greta",
    "wof:placetype":"venue"
},
  "geometry": {"coordinates":[151.38833618199999,-32.6769828796],"type":"Point"}
}