{
  "type": "Feature",
  "properties": {
    "addr:full":"Unit C2/ 77 Munibung Rd Cardiff NSW 2285",
    "addr:postcode":"2285",
    "addr:street":"Munibung Rd",
    "iso:country":"AU",
    "sg:address":"Unit C2/ 77 Munibung Rd",
    "sg:city":"Cardiff",
    "sg:classifiers":[
        {
            "category":"Building & Trades",
            "subcategory":"Construction",
            "type":"Services"
        }
    ],
    "sg:phone":"+61 2 4954 3363",
    "sg:postcode":"2285",
    "sg:province":"NSW",
    "sg:tags":[
        "scaffolding"
    ],
    "wof:name":"Direct Scaffolds Newcastle",
    "wof:placetype":"venue"
},
  "geometry": {"coordinates":[151.64002990700001,-32.9426994324],"type":"Point"}
}