{
  "type": "Feature",
  "properties": {
    "addr:full":"Clarendon St Derby WA 6728",
    "addr:postcode":"6728",
    "addr:street":"Clarendon St",
    "iso:country":"AU",
    "sg:address":"Clarendon St",
    "sg:city":"Derby",
    "sg:classifiers":[
        {
            "category":"Food & Beverages",
            "subcategory":"Supermarket",
            "type":"Retail Goods"
        }
    ],
    "sg:phone":"+61 8 9191 1210",
    "sg:postcode":"6728",
    "sg:province":"WA",
    "sg:tags":[
        "grocery",
        "store"
    ],
    "wof:name":"Rustys Foodland & Liquor Store",
    "wof:placetype":"venue"
},
  "geometry": {"coordinates":[123.636901855,-17.3077468872],"type":"Point"}
}