{
  "type": "Feature",
  "properties": {
    "iso:country":"AU",
    "sg:address":"95 Main St",
    "sg:city":"Katoomba",
    "sg:classifiers":[
        {
            "category":"Personal",
            "subcategory":"Beauty Salon",
            "type":"Services"
        }
    ],
    "sg:phone":"+61 2 4782 1247",
    "sg:postcode":"2780",
    "sg:province":"NSW",
    "sg:tags":[
        "hairdresser"
    ],
    "wof:name":"Shed Hairdressing",
    "wof:placetype":"venue"
},
  "geometry": {"coordinates":[150.311035156,-33.7122764587],"type":"Point"}
}