{
  "type": "Feature",
  "properties": {
    "addr:full":"94/ Fermont St Underwood QLD 4119",
    "addr:housenumber":"94 / fermont",
    "addr:postcode":"4119",
    "addr:street":"St",
    "iso:country":"AU",
    "sg:address":"94/ Fermont St",
    "sg:city":"Underwood",
    "sg:classifiers":[
        {
            "category":"Professional",
            "subcategory":"Art Services",
            "type":"Services"
        }
    ],
    "sg:phone":"+61 7 3841 4271",
    "sg:postcode":"4119",
    "sg:province":"QLD",
    "sg:tags":[
        "decorator",
        "painter"
    ],
    "wof:name":"Twina Isaac",
    "wof:placetype":"venue"
},
  "geometry": {"coordinates":[153.110137939,-27.5966567993],"type":"Point"}
}