{
  "type": "Feature",
  "properties": {
    "addr:full":"PO Box 11 Kangaroo Ground VIC 3097",
    "addr:postcode":"3097",
    "addr:street":"Kangaroo",
    "iso:country":"AU",
    "sg:address":"PO Box 11",
    "sg:city":"Kangaroo Ground",
    "sg:classifiers":[
        {
            "category":"Professional",
            "subcategory":"Art Services",
            "type":"Services"
        }
    ],
    "sg:phone":"+61 419 354 933",
    "sg:postcode":"3097",
    "sg:province":"VIC",
    "sg:tags":[
        "graphic",
        "designer"
    ],
    "wof:name":"Organyx Design",
    "wof:placetype":"venue"
},
  "geometry": {"coordinates":[145.215667725,-37.6913490295],"type":"Point"}
}