{
  "type": "Feature",
  "properties": {
    "iso:country":"AU",
    "sg:address":"Room 37/ 54 Brisbane St",
    "sg:city":"Launceston",
    "sg:classifiers":[
        {
            "category":"Professional",
            "subcategory":"Management & Consulting",
            "type":"Services"
        }
    ],
    "sg:phone":"+61 3 6334 0047",
    "sg:postcode":"7250",
    "sg:province":"TAS",
    "sg:tags":[
        "consultant",
        "educational"
    ],
    "wof:name":"Beverage Stuart",
    "wof:placetype":"venue"
},
  "geometry": {"coordinates":[147.14068603499999,-41.4360542297],"type":"Point"}
}