{
  "type": "Feature",
  "properties": {
    "addr:full":"Shop 180 , Smithfield S/C, Cnr Captain Cook & Kennedy QLD 4350",
    "addr:housenumber":"180;s / c",
    "addr:postcode":"4350",
    "addr:street":"Smithfield;Cnr Captain",
    "iso:country":"AU",
    "sg:address":"Shop 180",
    "sg:city":", Smithfield S/C, Cnr Captain Cook & Kennedy",
    "sg:classifiers":[
        {
            "category":"Personal",
            "subcategory":"Piercing",
            "type":"Services"
        }
    ],
    "sg:phone":"+61 7 4038 2399",
    "sg:postcode":"4350",
    "sg:province":"QLD",
    "sg:tags":[
        "body",
        "ear"
    ],
    "wof:name":"Hairhouse Warehouse",
    "wof:placetype":"venue"
},
  "geometry": {"coordinates":[151.928223,-27.589245],"type":"Point"}
}