{
  "type": "Feature",
  "properties": {
    "addr:full":"80 Chin Chen St Islington NSW 2296",
    "addr:housenumber":"80",
    "addr:postcode":"2296",
    "addr:street":"Chin Chen St",
    "iso:country":"AU",
    "sg:address":"80 Chin Chen St",
    "sg:city":"Islington",
    "sg:classifiers":[
        {
            "category":"Professional",
            "subcategory":"Engineering",
            "type":"Services"
        }
    ],
    "sg:phone":"+61 2 4940 0133",
    "sg:postcode":"2296",
    "sg:province":"NSW",
    "sg:tags":[
        "electrical",
        "engineer"
    ],
    "wof:name":"Excalibur Engineering",
    "wof:placetype":"venue"
},
  "geometry": {"coordinates":[151.74362182600001,-32.9118804932],"type":"Point"}
}