{
  "type": "Feature",
  "properties": {
    "addr:full":"16 Stanhope St Broadmeadows VIC 3047",
    "addr:housenumber":"16",
    "addr:postcode":"3047",
    "addr:street":"Stanhope St",
    "iso:country":"AU",
    "sg:address":"16 Stanhope St",
    "sg:city":"Broadmeadows",
    "sg:classifiers":[
        {
            "category":"Building & Trades",
            "subcategory":"Plumbing",
            "type":"Services"
        }
    ],
    "sg:phone":"+61 423 643 789",
    "sg:postcode":"3047",
    "sg:province":"VIC",
    "sg:tags":[
        "plumber",
        "gasfitters"
    ],
    "wof:name":"Efficient Plumbing Services",
    "wof:placetype":"venue"
},
  "geometry": {"coordinates":[144.93402099599999,-37.6858291626],"type":"Point"}
}