{
  "type": "Feature",
  "properties": {
    "addr:full":"55a Chandler Rd Noble Park VIC 3174",
    "addr:housenumber":"55a",
    "addr:postcode":"3174",
    "addr:street":"Chandler Rd",
    "iso:country":"AU",
    "sg:address":"55a Chandler Rd",
    "sg:city":"Noble Park",
    "sg:classifiers":[
        {
            "category":"Shopping",
            "subcategory":"Mobile Phones",
            "type":"Retail Goods"
        }
    ],
    "sg:phone":"+61 418 380 636",
    "sg:postcode":"3174",
    "sg:province":"VIC",
    "sg:tags":[
        "telephone",
        "accessory"
    ],
    "wof:name":"Abacom Pty Ltd",
    "wof:placetype":"venue"
},
  "geometry": {"coordinates":[145.186813355,-37.9693870544],"type":"Point"}
}