{
  "type": "Feature",
  "properties": {
    "addr:full":"Level 9, 12 Moore St Canberra ACT Canberra ACT 2601",
    "addr:housenumber":"12",
    "addr:postcode":"2601",
    "addr:street":"Moore St",
    "iso:country":"AU",
    "sg:address":"Level 9, 12 Moore St",
    "sg:city":"Canberra ACT Canberra",
    "sg:classifiers":[
        {
            "category":"Banks & Credit Unions",
            "subcategory":"Financial Services",
            "type":"Services"
        }
    ],
    "sg:phone":"+61 13 16 55",
    "sg:postcode":"2601",
    "sg:province":"ACT",
    "sg:tags":[
        "annuity",
        "rollover",
        "superannuation",
        "consultant"
    ],
    "wof:name":"Commonwealth Funds Management Ltd",
    "wof:placetype":"venue"
},
  "geometry": {"coordinates":[149.12815856899999,-35.2773895264],"type":"Point"}
}