{
  "type": "Feature",
  "properties": {
    "addr:full":"40 Banksia Drv Byron Bay NSW 2481",
    "addr:housenumber":"40",
    "addr:postcode":"2481",
    "addr:street":"Banksia Drv",
    "iso:country":"AU",
    "sg:address":"40 Banksia Drv",
    "sg:city":"Byron Bay",
    "sg:classifiers":[
        {
            "category":"Retail",
            "subcategory":"Auto Repair",
            "type":"Services"
        }
    ],
    "sg:phone":"+61 2 6685 8865",
    "sg:postcode":"2481",
    "sg:province":"NSW",
    "sg:tags":[
        "repairer",
        "motor",
        "engineer"
    ],
    "wof:name":"Prestige Motors",
    "wof:placetype":"venue"
},
  "geometry": {"coordinates":[153.58590698200001,-28.6372108459],"type":"Point"}
}