{
  "type": "Feature",
  "properties": {
    "addr:full":"Palmerston St Maryborough VIC 3465",
    "addr:postcode":"3465",
    "addr:street":"Palmerston St",
    "iso:country":"AU",
    "sg:address":"Palmerston St",
    "sg:city":"Maryborough",
    "sg:classifiers":[
        {
            "category":"Education",
            "subcategory":"School",
            "type":"Public Place"
        }
    ],
    "sg:phone":"+61 3 5461 1411",
    "sg:postcode":"3465",
    "sg:province":"VIC",
    "sg:tags":[
        "state",
        "except",
        "nsw"
    ],
    "wof:name":"Maryborough High School",
    "wof:placetype":"venue"
},
  "geometry": {"coordinates":[143.73405456500001,-37.0458488464],"type":"Point"}
}