{
  "type": "Feature",
  "properties": {
    "iso:country":"AU",
    "sg:address":"Factory 9 Western Ave",
    "sg:city":"Sunshine",
    "sg:classifiers":[
        {
            "category":"Home & Garden",
            "subcategory":"Building Materials",
            "type":"Retail Goods"
        }
    ],
    "sg:phone":"+61 3 9311 3553",
    "sg:postcode":"3020",
    "sg:province":"VIC",
    "sg:tags":[
        "merchant",
        "glass",
        "glazier"
    ],
    "wof:name":"Sunshine Glass Pty Ltd",
    "wof:placetype":"venue"
},
  "geometry": {"coordinates":[144.83326700000001,-37.800678],"type":"Point"}
}