{
  "type": "Feature",
  "properties": {
    "iso:country":"AU",
    "sg:address":"45-55 South Centre Rd",
    "sg:city":"Melbourne Airport",
    "sg:classifiers":[
        {
            "category":"Home & Garden",
            "subcategory":"Hardware",
            "type":"Retail Goods"
        }
    ],
    "sg:phone":"+61 3 8346 1100",
    "sg:postcode":"3045",
    "sg:province":"VIC",
    "sg:tags":[
        "woodworking",
        "machinery"
    ],
    "wof:name":"Triton Manufacturing & Design Co Pty Ltd",
    "wof:placetype":"venue"
},
  "geometry": {"coordinates":[144.85505676299999,-37.6874694824],"type":"Point"}
}