{
  "type": "Feature",
  "properties": {
    "addr:full":"4 Mount Barker Rd Stirling SA 5152",
    "addr:housenumber":"4",
    "addr:postcode":"5152",
    "addr:street":"Mount Barker Rd",
    "iso:country":"AU",
    "sg:address":"4 Mount Barker Rd",
    "sg:city":"Stirling",
    "sg:classifiers":[
        {
            "category":"Real Estate",
            "subcategory":"Real Estate Agent",
            "type":"Services"
        }
    ],
    "sg:phone":"+61 8 8339 6855",
    "sg:postcode":"5152",
    "sg:province":"SA",
    "wof:name":"Ray White South Australia",
    "wof:placetype":"venue"
},
  "geometry": {"coordinates":[138.72323608400001,-35.0081558228],"type":"Point"}
}