{
  "type": "Feature",
  "properties": {
    "addr:full":"454 Sydney Rd Brunswick VIC 3056",
    "addr:housenumber":"454",
    "addr:postcode":"3056",
    "addr:street":"Sydney Rd",
    "iso:country":"AU",
    "sg:address":"454 Sydney Rd",
    "sg:city":"Brunswick",
    "sg:classifiers":[
        {
            "category":"Shopping",
            "subcategory":"Clothing, Apparel, & Fashions",
            "type":"Retail Goods"
        }
    ],
    "sg:phone":"+61 3 9380 9774",
    "sg:postcode":"3056",
    "sg:province":"VIC",
    "sg:tags":[
        "accessory"
    ],
    "wof:name":"Kattina Fashion Accessories",
    "wof:placetype":"venue"
},
  "geometry": {"coordinates":[144.96217346200001,-37.7675437927],"type":"Point"}
}