{
  "type": "Feature",
  "properties": {
    "iso:country":"AU",
    "sg:address":"8 Vine St",
    "sg:city":"Albany",
    "sg:classifiers":[
        {
            "category":"Retail",
            "subcategory":"Car Wash",
            "type":"Services"
        }
    ],
    "sg:phone":"+61 8 9841 2802",
    "sg:postcode":"6330",
    "sg:province":"WA",
    "sg:tags":[
        "truck",
        "cleaning"
    ],
    "wof:name":"Fat Cats Car Wash",
    "wof:placetype":"venue"
},
  "geometry": {"coordinates":[117.88835907000001,-35.0166931152],"type":"Point"}
}