{
  "type": "Feature",
  "properties": {
    "addr:full":"McVicar Pl Mt Helena WA 6082",
    "addr:postcode":"6082",
    "addr:street":"Mcvicar Pl",
    "iso:country":"AU",
    "sg:address":"McVicar Pl",
    "sg:city":"Mt Helena",
    "sg:classifiers":[
        {
            "category":"Food & Beverages",
            "subcategory":"Supermarket",
            "type":"Retail Goods"
        }
    ],
    "sg:phone":"+61 8 9572 1023",
    "sg:postcode":"6082",
    "sg:province":"WA",
    "sg:tags":[
        "grocery",
        "store"
    ],
    "wof:name":"IGA Supermarkets",
    "wof:placetype":"venue"
},
  "geometry": {"coordinates":[116.21012878400001,-31.8781929016],"type":"Point"}
}