{
  "type": "Feature",
  "properties": {
    "addr:full":"Unit 9, 202 Sunnyholt Rd Blacktown NSW 2148",
    "addr:housenumber":"202",
    "addr:postcode":"2148",
    "addr:street":"Sunnyholt Rd",
    "iso:country":"AU",
    "sg:address":"Unit 9, 202 Sunnyholt Rd",
    "sg:city":"Blacktown",
    "sg:classifiers":[
        {
            "category":"Professional",
            "subcategory":"Detective & Security Services",
            "type":"Services"
        }
    ],
    "sg:phone":"+61 2 9621 1755",
    "sg:postcode":"2148",
    "sg:province":"NSW",
    "sg:tags":[
        "equipment",
        "window",
        "doors"
    ],
    "wof:name":"Delta Blinds (Aust) Pty Ltd",
    "wof:placetype":"venue"
},
  "geometry": {"coordinates":[150.91615295400001,-33.7478294373],"type":"Point"}
}