{
  "type": "Feature",
  "properties": {
    "addr:full":"17 Toombul Rd Northgate QLD 4013",
    "addr:housenumber":"17",
    "addr:postcode":"4013",
    "addr:street":"Toombul Rd",
    "iso:country":"AU",
    "sg:address":"17 Toombul Rd",
    "sg:city":"Northgate",
    "sg:classifiers":[
        {
            "category":"Autos & Motor Vehicles",
            "subcategory":"Fuel & Gas Station",
            "type":"Retail Goods"
        }
    ],
    "sg:phone":"+61 7 3260 7069",
    "sg:postcode":"4013",
    "sg:province":"QLD",
    "wof:name":"Liberty Service Stations",
    "wof:placetype":"venue"
},
  "geometry": {"coordinates":[153.06814575199999,-27.3921909332],"type":"Point"}
}