{
  "type": "Feature",
  "properties": {
    "addr:full":"2 Halyard St Wurtulla QLD 4575",
    "addr:housenumber":"2",
    "addr:postcode":"4575",
    "addr:street":"Halyard St",
    "iso:country":"AU",
    "sg:address":"2 Halyard St",
    "sg:city":"Wurtulla",
    "sg:classifiers":[
        {
            "category":"Home & Garden",
            "subcategory":"Carpets & Floor Coverings",
            "type":"Retail Goods"
        }
    ],
    "sg:phone":"+61 418 986 484",
    "sg:postcode":"4575",
    "sg:province":"QLD",
    "sg:tags":[
        "tile",
        "wall",
        "layer"
    ],
    "wof:name":"J & S Ceramic Tiling",
    "wof:placetype":"venue"
},
  "geometry": {"coordinates":[153.12735000000001,-26.750055],"type":"Point"}
}