{
  "type": "Feature",
  "properties": {
    "addr:full":"455 Scarborough Beach Rd Osborne Park WA 6017",
    "addr:housenumber":"455",
    "addr:postcode":"6017",
    "addr:street":"Scarborough Beach Rd",
    "iso:country":"AU",
    "sg:address":"455 Scarborough Beach Rd",
    "sg:city":"Osborne Park",
    "sg:classifiers":[
        {
            "category":"Wholesale",
            "subcategory":"Home Furnishings",
            "type":"Manufacturing & Wholesale Goods"
        }
    ],
    "sg:phone":"+61 8 9242 3078",
    "sg:postcode":"6017",
    "sg:province":"WA",
    "sg:tags":[
        "wholesaler",
        "bedding",
        "mfrs",
        "bed"
    ],
    "wof:name":"Bretts Beds & Futons",
    "wof:placetype":"venue"
},
  "geometry": {"coordinates":[115.809310913,-31.9061660767],"type":"Point"}
}