{
  "type": "Feature",
  "properties": {
    "iso:country":"AU",
    "sg:address":"500 Flinders St",
    "sg:city":"Townsville",
    "sg:classifiers":[
        {
            "category":"Travel",
            "subcategory":"Hotels & Motels",
            "type":"Entertainment"
        }
    ],
    "sg:phone":"+61 7 4771 6191",
    "sg:postcode":"4810",
    "sg:province":"QLD",
    "wof:name":"Great Northern Hotel",
    "wof:placetype":"venue"
},
  "geometry": {"coordinates":[146.80940200000001,-19.266878],"type":"Point"}
}