{
  "type": "Feature",
  "properties": {
    "addr:full":"200 Kensington Rd West Melbourne VIC 3003",
    "addr:housenumber":"200",
    "addr:postcode":"3003",
    "addr:street":"Kensington Rd",
    "iso:country":"AU",
    "sg:address":"200 Kensington Rd",
    "sg:city":"West Melbourne",
    "sg:classifiers":[
        {
            "category":"Home & Garden",
            "subcategory":"Garden Supply",
            "type":"Retail Goods"
        }
    ],
    "sg:phone":"+61 3 9687 2338",
    "sg:postcode":"3003",
    "sg:province":"VIC",
    "sg:tags":[
        "landscape"
    ],
    "wof:name":"Paddy's Bricks",
    "wof:placetype":"venue"
},
  "geometry": {"coordinates":[144.91734314000001,-37.7999343872],"type":"Point"}
}