{
  "type": "Feature",
  "properties": {
    "addr:full":"S2, 72 Prince Edward Drv Dapto NSW 2530",
    "addr:housenumber":"72",
    "addr:postcode":"2530",
    "addr:street":"S2;Prince Edward Drv",
    "iso:country":"AU",
    "sg:address":"S2, 72 Prince Edward Drv",
    "sg:city":"Dapto",
    "sg:classifiers":[
        {
            "category":"Personal",
            "subcategory":"Beauty Salon",
            "type":"Services"
        }
    ],
    "sg:phone":"+61 2 4261 7086",
    "sg:postcode":"2530",
    "sg:province":"NSW",
    "sg:tags":[
        "hairdresser"
    ],
    "wof:name":"Kapooka Hair Room",
    "wof:placetype":"venue"
},
  "geometry": {"coordinates":[150.79771423299999,-34.4894638062],"type":"Point"}
}