{
  "type": "Feature",
  "properties": {
    "addr:full":"53 - 57 Magazine Rd Dry Creek SA 5094",
    "addr:housenumber":"57",
    "addr:postcode":"5094",
    "addr:street":"Magazine Rd Dry",
    "iso:country":"AU",
    "sg:address":"53 - 57 Magazine Rd",
    "sg:city":"Dry Creek",
    "sg:classifiers":[
        {
            "category":"Retail",
            "subcategory":"Driving School",
            "type":"Services"
        }
    ],
    "sg:phone":"+61 8 8359 0099",
    "sg:postcode":"5094",
    "sg:province":"SA",
    "sg:tags":[
        "defensive",
        "advanced"
    ],
    "wof:name":"Heavy Vehicle Driving Training",
    "wof:placetype":"venue"
},
  "geometry": {"coordinates":[138.581787109,-34.8364677429],"type":"Point"}
}