{
  "type": "Feature",
  "properties": {
    "addr:full":"223 Lakes Creek Rd North Rockhampton QLD 4701",
    "addr:housenumber":"223",
    "addr:postcode":"4701",
    "addr:street":"Lakes Creek Rd North",
    "iso:country":"AU",
    "sg:address":"223 Lakes Creek Rd",
    "sg:city":"North Rockhampton",
    "sg:classifiers":[
        {
            "category":"Recreation",
            "subcategory":"Fishing",
            "type":"Entertainment"
        }
    ],
    "sg:phone":"+61 7 4928 9157",
    "sg:postcode":"4701",
    "sg:province":"QLD",
    "sg:tags":[
        "bait"
    ],
    "wof:name":"Kalka Bait & Tackle",
    "wof:placetype":"venue"
},
  "geometry": {"coordinates":[150.55311584500001,-23.3742771149],"type":"Point"}
}