{
  "type": "Feature",
  "properties": {
    "addr:full":"Illawarra Community Centre 265 Pakington St Geelong VIC 3220",
    "addr:housenumber":"265",
    "addr:postcode":"3220",
    "addr:street":"Pakington St",
    "iso:country":"AU",
    "sg:address":"Illawarra Community Centre 265 Pakington St",
    "sg:city":"Geelong",
    "sg:classifiers":[
        {
            "category":"Health Services",
            "subcategory":"Doctor",
            "type":"Services"
        }
    ],
    "sg:phone":"+61 3 5221 4100",
    "sg:postcode":"3220",
    "sg:province":"VIC",
    "sg:tags":[
        "medical",
        "practitioner"
    ],
    "wof:name":"International Diabetes Institute",
    "wof:placetype":"venue"
},
  "geometry": {"coordinates":[144.346405,-38.149738],"type":"Point"}
}