{
  "type": "Feature",
  "properties": {
    "addr:full":"Poplar Rd Wagga Wagga NSW 2650",
    "addr:postcode":"2650",
    "addr:street":"Poplar Rd",
    "iso:country":"AU",
    "sg:address":"Poplar Rd",
    "sg:city":"Wagga Wagga",
    "sg:classifiers":[
        {
            "category":"Building & Trades",
            "subcategory":"Construction",
            "type":"Services"
        }
    ],
    "sg:phone":"+61 2 6922 5559",
    "sg:postcode":"2650",
    "sg:province":"NSW",
    "sg:tags":[
        "contractor"
    ],
    "wof:name":"Cahalan P J",
    "wof:placetype":"venue"
},
  "geometry": {"coordinates":[147.39494323700001,-35.1790161133],"type":"Point"}
}