{
  "type": "Feature",
  "properties": {
    "iso:country":"AU",
    "sg:address":"162 Princes Hwy",
    "sg:city":"Milton",
    "sg:classifiers":[
        {
            "category":"Professional",
            "subcategory":"Art Services",
            "type":"Services"
        }
    ],
    "sg:phone":"+61 2 4455 5499",
    "sg:postcode":"2538",
    "sg:province":"NSW",
    "sg:tags":[
        "artist"
    ],
    "wof:name":"Lane Patricia",
    "wof:placetype":"venue"
},
  "geometry": {"coordinates":[150.44329834000001,-35.3198432922],"type":"Point"}
}