{
  "type": "Feature",
  "properties": {
    "addr:full":"Telemon St St Helens TAS 7216",
    "addr:postcode":"7216",
    "addr:street":"St",
    "iso:country":"AU",
    "sg:address":"Telemon St St",
    "sg:city":"Helens",
    "sg:classifiers":[
        {
            "category":"Farming",
            "subcategory":"Fish & Marine Products",
            "type":"Manufacturing & Wholesale Goods"
        }
    ],
    "sg:phone":"+61 3 6376 1758",
    "sg:postcode":"7216",
    "sg:province":"TAS",
    "sg:tags":[
        "fisherman"
    ],
    "wof:name":"Wisby R G",
    "wof:placetype":"venue"
},
  "geometry": {"coordinates":[148.248199,-41.333382],"type":"Point"}
}