{
  "type": "Feature",
  "properties": {
    "addr:full":"Church St Maffra VIC 3860",
    "addr:postcode":"3860",
    "addr:street":"Church St",
    "iso:country":"AU",
    "sg:address":"Church St",
    "sg:city":"Maffra",
    "sg:classifiers":[
        {
            "category":"Education",
            "subcategory":"School",
            "type":"Public Place"
        }
    ],
    "sg:phone":"+61 3 5147 1236",
    "sg:postcode":"3860",
    "sg:province":"VIC",
    "sg:tags":[
        "state",
        "except",
        "nsw"
    ],
    "wof:name":"Maffra Primary School",
    "wof:placetype":"venue"
},
  "geometry": {"coordinates":[146.979125977,-37.9654846191],"type":"Point"}
}