{
  "type": "Feature",
  "properties": {
    "iso:country":"AU",
    "sg:address":"173 Brisbane St",
    "sg:city":"Ipswich",
    "sg:classifiers":[
        {
            "category":"Cafe",
            "type":"Food & Drink"
        }
    ],
    "sg:phone":"+61 7 3282 8299",
    "sg:postcode":"4305",
    "sg:province":"QLD",
    "wof:name":"Cactus Espresso Bar",
    "wof:placetype":"venue"
},
  "geometry": {"coordinates":[152.75714111299999,-27.6139431],"type":"Point"}
}