{
  "type": "Feature",
  "properties": {
    "addr:full":"PO Box 1051 Cronulla NSW 2230",
    "addr:postcode":"2230",
    "iso:country":"AU",
    "sg:address":"PO Box 1051",
    "sg:city":"Cronulla",
    "sg:classifiers":[
        {
            "category":"Building & Trades",
            "subcategory":"Construction",
            "type":"Services"
        }
    ],
    "sg:phone":"+61 419 234 287",
    "sg:postcode":"2230",
    "sg:province":"NSW",
    "sg:tags":[
        "renovation",
        "alterations",
        "extension",
        "contractor"
    ],
    "wof:name":"Livingspace Building",
    "wof:placetype":"venue"
},
  "geometry": {"coordinates":[151.153366089,-34.055229187],"type":"Point"}
}