{
  "type": "Feature",
  "properties": {
    "iso:country":"AU",
    "sg:address":"303 George St",
    "sg:city":"Windsor",
    "sg:classifiers":[
        {
            "category":"Health Services",
            "subcategory":"Doctor",
            "type":"Services"
        }
    ],
    "sg:phone":"+61 2 4577 7058",
    "sg:postcode":"2756",
    "sg:province":"NSW",
    "sg:tags":[
        "medical",
        "practitioner"
    ],
    "wof:name":"Sydney Cardiology Group",
    "wof:placetype":"venue"
},
  "geometry": {"coordinates":[150.817092895,-33.6089057922],"type":"Point"}
}