{
  "type": "Feature",
  "properties": {
    "iso:country":"AU",
    "sg:address":"50 Scheurles Rd",
    "sg:city":"Kulpi",
    "sg:classifiers":[
        {
            "category":"Building & Trades",
            "subcategory":"Plumbing",
            "type":"Services"
        }
    ],
    "sg:phone":"+61 7 4692 8018",
    "sg:postcode":"4352",
    "sg:province":"QLD",
    "sg:tags":[
        "plumber",
        "gasfitters"
    ],
    "wof:name":"Jenkinson B F & P",
    "wof:placetype":"venue"
},
  "geometry": {"coordinates":[151.700363,-27.187889],"type":"Point"}
}