{
  "type": "Feature",
  "properties": {
    "addr:full":"50 Scheurles Rd Kulpi QLD 4352",
    "addr:housenumber":"50",
    "addr:postcode":"4352",
    "addr:street":"Scheurles Rd",
    "iso:country":"AU",
    "sg:address":"50 Scheurles Rd",
    "sg:city":"Kulpi",
    "sg:classifiers":[
        {
            "category":"Building & Trades",
            "subcategory":"Plumbing",
            "type":"Services"
        }
    ],
    "sg:phone":"+61 7 4692 8018",
    "sg:postcode":"4352",
    "sg:province":"QLD",
    "sg:tags":[
        "plumber",
        "gasfitters"
    ],
    "wof:name":"Jenkinson B F & P",
    "wof:placetype":"venue"
},
  "geometry": {"coordinates":[151.70036300000001,-27.187889],"type":"Point"}
}