{
  "type": "Feature",
  "properties": {
    "iso:country":"AU",
    "sg:address":"19 Alexandra Rd",
    "sg:city":"Hoppers Crossing",
    "sg:classifiers":[
        {
            "category":"Professional",
            "type":"Services"
        }
    ],
    "sg:phone":"+61 3 9974 6774",
    "sg:postcode":"3029",
    "sg:province":"VIC",
    "sg:tags":[
        "transport"
    ],
    "wof:name":"Cotham Dale Pty Ltd",
    "wof:placetype":"venue"
},
  "geometry": {"coordinates":[144.708282,-37.852009],"type":"Point"}
}