{
  "type": "Feature",
  "properties": {
    "addr:full":"Unit 17 / 55 Mitchell Rd Brookvale NSW 2100",
    "addr:housenumber":"/ 55",
    "addr:postcode":"2100",
    "addr:street":"Mitchell Rd",
    "iso:country":"AU",
    "sg:address":"Unit 17 / 55 Mitchell Rd",
    "sg:city":"Brookvale",
    "sg:classifiers":[
        {
            "category":"Professional",
            "subcategory":"Art Services",
            "type":"Services"
        }
    ],
    "sg:phone":"+61 2 9905 4042",
    "sg:postcode":"2100",
    "sg:province":"NSW",
    "sg:tags":[
        "graphic",
        "designer"
    ],
    "wof:name":"Minuteman Press - Brookvale",
    "wof:placetype":"venue"
},
  "geometry": {"coordinates":[151.27503967300001,-33.7614326477],"type":"Point"}
}