{
  "type": "Feature",
  "properties": {
    "addr:full":"3rd floor 55 Currie St Adelaide SA 5000",
    "addr:housenumber":"55",
    "addr:postcode":"5000",
    "addr:street":"Currie St",
    "iso:country":"AU",
    "sg:address":"3rd floor 55 Currie St",
    "sg:city":"Adelaide",
    "sg:classifiers":[
        {
            "category":"Wholesale",
            "subcategory":"Medical Equipment & Supplies",
            "type":"Manufacturing & Wholesale Goods"
        }
    ],
    "sg:phone":"+61 8 8237 6145",
    "sg:postcode":"5000",
    "sg:province":"SA",
    "sg:tags":[
        "aids",
        "hearing"
    ],
    "wof:name":"Australian Hearing",
    "wof:placetype":"venue"
},
  "geometry": {"coordinates":[138.59678649899999,-34.9247207642],"type":"Point"}
}