{
  "type": "Feature",
  "properties": {
    "iso:country":"AU",
    "sg:address":"Lot 107 Henry Rd",
    "sg:city":"Blakiston",
    "sg:classifiers":[
        {
            "category":"Building & Trades",
            "subcategory":"Construction",
            "type":"Services"
        }
    ],
    "sg:phone":"+61 419 844 055",
    "sg:postcode":"5250",
    "sg:province":"SA",
    "sg:tags":[
        "earth",
        "excavating",
        "moving",
        "contractor"
    ],
    "wof:name":"DingoMaster",
    "wof:placetype":"venue"
},
  "geometry": {"coordinates":[138.88311767600001,-35.051738739],"type":"Point"}
}