{
  "type": "Feature",
  "properties": {
    "addr:full":"102 Daffodil Rd Boronia VIC 3155",
    "addr:housenumber":"102",
    "addr:postcode":"3155",
    "addr:street":"Daffodil Rd",
    "iso:country":"AU",
    "sg:address":"102 Daffodil Rd",
    "sg:city":"Boronia",
    "sg:classifiers":[
        {
            "category":"Real Estate",
            "subcategory":"Real Estate Services",
            "type":"Services"
        }
    ],
    "sg:phone":"+61 3 9761 0954",
    "sg:postcode":"3155",
    "sg:province":"VIC",
    "sg:tags":[
        "consultant",
        "property"
    ],
    "wof:name":"C J Mason Consulting",
    "wof:placetype":"venue"
},
  "geometry": {"coordinates":[145.29739379899999,-37.8645782471],"type":"Point"}
}