{
  "type": "Feature",
  "properties": {
    "addr:full":"22 Orient Point Rd Culburra NSW 2540",
    "addr:housenumber":"22",
    "addr:postcode":"2540",
    "addr:street":"Orient Point Rd",
    "iso:country":"AU",
    "sg:address":"22 Orient Point Rd",
    "sg:city":"Culburra",
    "sg:classifiers":[
        {
            "category":"Building & Trades",
            "subcategory":"Plumbing",
            "type":"Services"
        }
    ],
    "sg:phone":"+61 2 4447 3067",
    "sg:postcode":"2540",
    "sg:province":"NSW",
    "sg:tags":[
        "drainers"
    ],
    "wof:name":"Culburra Plumbing Services",
    "wof:placetype":"venue"
},
  "geometry": {"coordinates":[150.75541687,-34.9127349854],"type":"Point"}
}