{
  "type": "Feature",
  "properties": {
    "iso:country":"AU",
    "sg:address":"23 Cecilia St St",
    "sg:city":"Helens",
    "sg:classifiers":[
        {
            "category":"Food & Beverages",
            "subcategory":"Supermarket",
            "type":"Retail Goods"
        }
    ],
    "sg:phone":"+61 3 6376 1161",
    "sg:postcode":"7216",
    "sg:province":"TAS",
    "sg:tags":[
        "grocery",
        "store"
    ],
    "wof:name":"Value Plus IGA Stores",
    "wof:placetype":"venue"
},
  "geometry": {"coordinates":[148.24913000000001,-41.323898],"type":"Point"}
}