{
  "type": "Feature",
  "properties": {
    "addr:full":"Jugiong Rd Cootamundra NSW 2590",
    "addr:postcode":"2590",
    "addr:street":"Jugiong Rd",
    "iso:country":"AU",
    "sg:address":"Jugiong Rd",
    "sg:city":"Cootamundra",
    "sg:classifiers":[
        {
            "category":"Building & Trades",
            "subcategory":"Construction",
            "type":"Services"
        }
    ],
    "sg:phone":"+61 422 542 040",
    "sg:postcode":"2590",
    "sg:province":"NSW",
    "sg:tags":[
        "earth",
        "excavating",
        "moving",
        "contractor"
    ],
    "wof:name":"Coota Bobcat Services",
    "wof:placetype":"venue"
},
  "geometry": {"coordinates":[148.054977417,-34.6712493896],"type":"Point"}
}