{
  "type": "Feature",
  "properties": {
    "iso:country":"AU",
    "sg:address":"109 Ryans La",
    "sg:city":"Pyree",
    "sg:classifiers":[
        {
            "category":"Farming",
            "subcategory":"Farm",
            "type":"Manufacturing & Wholesale Goods"
        }
    ],
    "sg:phone":"+61 2 4447 1209",
    "sg:postcode":"2540",
    "sg:province":"NSW",
    "sg:tags":[
        "farmer"
    ],
    "wof:name":"Watts B J",
    "wof:placetype":"venue"
},
  "geometry": {"coordinates":[150.69586181599999,-34.8991394043],"type":"Point"}
}