{
  "type": "Feature",
  "properties": {
    "addr:full":"66- 68 High St Northcote VIC 3070",
    "addr:housenumber":"68",
    "addr:postcode":"3070",
    "addr:street":"High St",
    "iso:country":"AU",
    "sg:address":"66- 68 High St",
    "sg:city":"Northcote",
    "sg:classifiers":[
        {
            "category":"Personal",
            "subcategory":"Beauty Salon",
            "type":"Services"
        }
    ],
    "sg:phone":"+61 3 9481 0870",
    "sg:postcode":"3070",
    "sg:province":"VIC",
    "wof:name":"Mademoiselle Beauty Parlour",
    "wof:placetype":"venue"
},
  "geometry": {"coordinates":[144.99696399999999,-37.780624],"type":"Point"}
}