{
  "type": "Feature",
  "properties": {
    "iso:country":"AU",
    "sg:address":"403 Charles St",
    "sg:city":"North Perth",
    "sg:classifiers":[
        {
            "category":"Health Services",
            "subcategory":"Health Practitioner",
            "type":"Services"
        }
    ],
    "sg:phone":"+61 8 9444 7822",
    "sg:postcode":"6006",
    "sg:province":"WA",
    "sg:tags":[
        "osteopath"
    ],
    "wof:name":"Benjamin Rowland",
    "wof:placetype":"venue"
},
  "geometry": {"coordinates":[115.85104370099999,-31.9238319397],"type":"Point"}
}