{
  "type": "Feature",
  "properties": {
    "addr:full":"Willows Shopping Centre Herveys Range Rd Kirwan QLD 4817",
    "addr:postcode":"4817",
    "addr:street":"Range Rd",
    "iso:country":"AU",
    "sg:address":"Willows Shopping Centre Herveys Range Rd",
    "sg:city":"Kirwan",
    "sg:classifiers":[
        {
            "category":"Fast Food",
            "type":"Food & Drink"
        }
    ],
    "sg:phone":"+61 7 4723 0422",
    "sg:postcode":"4817",
    "sg:province":"QLD",
    "sg:tags":[
        "away",
        "take"
    ],
    "wof:name":"Super Sandwich and Burger Bar",
    "wof:placetype":"venue"
},
  "geometry": {"coordinates":[146.73516799999999,-19.30369],"type":"Point"}
}