{
  "type": "Feature",
  "properties": {
    "addr:full":"48 Station St Parramatta NSW 2150",
    "addr:housenumber":"48",
    "addr:postcode":"2150",
    "addr:street":"Station St",
    "iso:country":"AU",
    "sg:address":"48 Station St",
    "sg:city":"Parramatta",
    "sg:classifiers":[
        {
            "category":"Restaurant",
            "type":"Food & Drink"
        }
    ],
    "sg:phone":"+61 2 9633 2889",
    "sg:postcode":"2150",
    "sg:province":"NSW",
    "sg:website":"http://www.peronisrestaurant.com.au",
    "wof:name":"Peronis Restaurant",
    "wof:placetype":"venue"
},
  "geometry": {"coordinates":[151.00793457,-33.820098877],"type":"Point"}
}