{
  "type": "Feature",
  "properties": {
    "addr:full":"PO Box 1397 Green Valley NSW 2168",
    "addr:postcode":"2168",
    "iso:country":"AU",
    "sg:address":"PO Box 1397",
    "sg:city":"Green Valley",
    "sg:classifiers":[
        {
            "category":"Professional",
            "type":"Services"
        }
    ],
    "sg:phone":"+61 2 8784 4000",
    "sg:postcode":"2168",
    "sg:province":"NSW",
    "sg:tags":[
        "message",
        "answering",
        "telephone"
    ],
    "wof:name":"Able Telephone Answering Service",
    "wof:placetype":"venue"
},
  "geometry": {"coordinates":[150.86651611299999,-33.9027404785],"type":"Point"}
}