{
  "type": "Feature",
  "properties": {
    "addr:full":"7 East Row St Canberra City ACT 2601",
    "addr:housenumber":"7",
    "addr:postcode":"2601",
    "addr:street":"East Row St",
    "iso:country":"AU",
    "sg:address":"7 East Row St",
    "sg:city":"Canberra City",
    "sg:classifiers":[
        {
            "category":"Food & Beverages",
            "subcategory":"Liquor & Beverages",
            "type":"Retail Goods"
        }
    ],
    "sg:phone":"+61 2 6248 6955",
    "sg:postcode":"2601",
    "sg:province":"ACT",
    "sg:tags":[
        "store"
    ],
    "wof:name":"Dina's Liquor",
    "wof:placetype":"venue"
},
  "geometry": {"coordinates":[149.13034057600001,-35.2795333862],"type":"Point"}
}