{
  "type": "Feature",
  "properties": {
    "addr:full":"105 Ocean Beach Rd Sorrento VIC 3943",
    "addr:housenumber":"105",
    "addr:postcode":"3943",
    "addr:street":"Ocean Beach Rd",
    "iso:country":"AU",
    "sg:address":"105 Ocean Beach Rd",
    "sg:city":"Sorrento",
    "sg:classifiers":[
        {
            "category":"Shopping",
            "subcategory":"Clothing, Apparel, & Fashions",
            "type":"Retail Goods"
        }
    ],
    "sg:phone":"+61 3 5984 4953",
    "sg:postcode":"3943",
    "sg:province":"VIC",
    "sg:tags":[
        "lady",
        "wear"
    ],
    "wof:name":"Promenade At Sorrento",
    "wof:placetype":"venue"
},
  "geometry": {"coordinates":[144.73840332,-38.3397598267],"type":"Point"}
}