{
  "type": "Feature",
  "properties": {
    "addr:full":"PO Box 54 Quirindi NSW 2343",
    "addr:postcode":"2343",
    "iso:country":"AU",
    "sg:address":"PO Box 54",
    "sg:city":"Quirindi",
    "sg:classifiers":[
        {
            "category":"Industrial Area",
            "type":"Public Place"
        }
    ],
    "sg:phone":"+61 1800 672 766",
    "sg:postcode":"2343",
    "sg:province":"NSW",
    "sg:tags":[
        "rural",
        "shed"
    ],
    "wof:name":"Ezyframe Sheds & Garages",
    "wof:placetype":"venue"
},
  "geometry": {"coordinates":[150.67579650900001,-31.5191898346],"type":"Point"}
}