{
  "type": "Feature",
  "properties": {
    "addr:full":"210 Urana St Wagga Wagga NSW 2650",
    "addr:housenumber":"210",
    "addr:postcode":"2650",
    "addr:street":"Urana St",
    "iso:country":"AU",
    "sg:address":"210 Urana St",
    "sg:city":"Wagga Wagga",
    "sg:classifiers":[
        {
            "category":"Manufacturing",
            "subcategory":"Petroleum Products",
            "type":"Manufacturing & Wholesale Goods"
        }
    ],
    "sg:phone":"+61 1800 656 580",
    "sg:postcode":"2650",
    "sg:province":"NSW",
    "sg:tags":[
        "lubricant"
    ],
    "wof:name":"Core Oil",
    "wof:placetype":"venue"
},
  "geometry": {"coordinates":[147.34286499000001,-35.1250762939],"type":"Point"}
}