{
  "type": "Feature",
  "properties": {
    "iso:country":"AU",
    "sg:address":"89 Punt Rd",
    "sg:city":"Cobram",
    "sg:classifiers":[
        {
            "category":"Professional",
            "subcategory":"Computer Services",
            "type":"Services"
        }
    ],
    "sg:phone":"+61 3 5871 2199",
    "sg:postcode":"3643",
    "sg:province":"VIC",
    "sg:tags":[
        "equipment",
        "networking",
        "installation"
    ],
    "wof:name":"Cobram My Computer",
    "wof:placetype":"venue"
},
  "geometry": {"coordinates":[145.646972656,-35.920425415],"type":"Point"}
}