{
  "type": "Feature",
  "properties": {
    "iso:country":"AU",
    "sg:address":"Kamerunga Villas Kamerunga Rd",
    "sg:city":"Kamerunga",
    "sg:classifiers":[
        {
            "category":"Retail",
            "subcategory":"Laundry & Dry Cleaning",
            "type":"Services"
        }
    ],
    "sg:phone":"+61 7 4039 9860",
    "sg:postcode":"4870",
    "sg:province":"QLD",
    "sg:tags":[
        "manicurist"
    ],
    "wof:name":"Therese O'Loughlin",
    "wof:placetype":"venue"
},
  "geometry": {"coordinates":[145.70472717300001,-16.8852386475],"type":"Point"}
}