{
  "type": "Feature",
  "properties": {
    "addr:full":"Lot 83 Larsen Rd Byford WA 6122",
    "addr:postcode":"6122",
    "addr:street":"Larsen Rd",
    "iso:country":"AU",
    "sg:address":"Lot 83 Larsen Rd",
    "sg:city":"Byford",
    "sg:classifiers":[
        {
            "category":"Building & Trades",
            "subcategory":"Construction",
            "type":"Services"
        }
    ],
    "sg:phone":"+61 418 908 773",
    "sg:postcode":"6122",
    "sg:province":"WA",
    "sg:tags":[
        "earth",
        "excavating",
        "moving",
        "contractor"
    ],
    "wof:name":"Blue Heeler Contracting",
    "wof:placetype":"venue"
},
  "geometry": {"coordinates":[115.99736023,-32.2113952637],"type":"Point"}
}