{
  "type": "Feature",
  "properties": {
    "addr:full":"381 Phoenix Rd Bibra Lake WA 6163",
    "addr:housenumber":"381",
    "addr:postcode":"6163",
    "addr:street":"Phoenix Rd",
    "iso:country":"AU",
    "sg:address":"381 Phoenix Rd",
    "sg:city":"Bibra Lake",
    "sg:classifiers":[
        {
            "category":"Manufacturing",
            "subcategory":"Paper Products",
            "type":"Manufacturing & Wholesale Goods"
        }
    ],
    "sg:phone":"+61 8 9434 0434",
    "sg:postcode":"6163",
    "sg:province":"WA",
    "sg:tags":[
        "box",
        "fibre",
        "carton",
        "cardboard"
    ],
    "wof:name":"Amcor Fibre Packaging",
    "wof:placetype":"venue"
},
  "geometry": {"coordinates":[115.810852,-32.093307],"type":"Point"}
}