{
  "type": "Feature",
  "properties": {
    "addr:full":"Unit 1/ 1 Egan Rd Dandenong VIC 3175",
    "addr:housenumber":"1",
    "addr:postcode":"3175",
    "addr:street":"Egan Rd",
    "iso:country":"AU",
    "sg:address":"Unit 1/ 1 Egan Rd",
    "sg:city":"Dandenong",
    "sg:classifiers":[
        {
            "category":"Wholesale",
            "subcategory":"Toys & Hobbies",
            "type":"Manufacturing & Wholesale Goods"
        }
    ],
    "sg:phone":"+61 3 9791 9149",
    "sg:postcode":"3175",
    "sg:province":"VIC",
    "wof:name":"T & P Pre-School Equipment",
    "wof:placetype":"venue"
},
  "geometry": {"coordinates":[145.19424438499999,-37.9958267212],"type":"Point"}
}