{
  "type": "Feature",
  "properties": {
    "iso:country":"AU",
    "sg:address":"3 Colombo St",
    "sg:city":"Victoria Park",
    "sg:classifiers":[
        {
            "category":"Mining & Drilling",
            "type":"Manufacturing & Wholesale Goods"
        }
    ],
    "sg:phone":"+61 412 927 000",
    "sg:postcode":"6100",
    "sg:province":"WA",
    "sg:tags":[
        "boring",
        "contractor"
    ],
    "wof:name":"AGF Charter Group",
    "wof:placetype":"venue"
},
  "geometry": {"coordinates":[115.89073944099999,-31.9699878693],"type":"Point"}
}