{
  "type": "Feature",
  "properties": {
    "iso:country":"AU",
    "sg:address":"20 Alice St",
    "sg:city":"Seven Hills",
    "sg:classifiers":[
        {
            "category":"Professional",
            "subcategory":"Accounting & Tax Preparation",
            "type":"Services"
        }
    ],
    "sg:phone":"+61 2 9831 1940",
    "sg:postcode":"2147",
    "sg:province":"NSW",
    "sg:tags":[
        "accountant",
        "auditor"
    ],
    "wof:name":"Butchart Rodney J & Associates",
    "wof:placetype":"venue"
},
  "geometry": {"coordinates":[150.93429565400001,-33.7768516541],"type":"Point"}
}