{
  "type": "Feature",
  "properties": {
    "addr:full":"51 Alacrity Pl Henderson WA 6166",
    "addr:housenumber":"51",
    "addr:postcode":"6166",
    "addr:street":"Alacrity Pl",
    "iso:country":"AU",
    "sg:address":"51 Alacrity Pl",
    "sg:city":"Henderson",
    "sg:classifiers":[
        {
            "category":"Mining & Drilling",
            "type":"Manufacturing & Wholesale Goods"
        }
    ],
    "sg:phone":"+61 8 9437 8600",
    "sg:postcode":"6166",
    "sg:province":"WA",
    "sg:tags":[
        "equipment",
        "quarrying",
        "supply"
    ],
    "wof:name":"Nomad Modular Building Pty Ltd",
    "wof:placetype":"venue"
},
  "geometry": {"coordinates":[115.77903000000001,-32.166206],"type":"Point"}
}