{
  "type": "Feature",
  "properties": {
    "addr:full":"286A Settlement Rd Thomastown VIC 3074",
    "addr:housenumber":"286a",
    "addr:postcode":"3074",
    "addr:street":"Settlement Rd",
    "iso:country":"AU",
    "sg:address":"286A Settlement Rd",
    "sg:city":"Thomastown",
    "sg:classifiers":[
        {
            "category":"Wholesale",
            "subcategory":"Electrical",
            "type":"Manufacturing & Wholesale Goods"
        }
    ],
    "sg:phone":"+61 3 9466 2333",
    "sg:postcode":"3074",
    "sg:province":"VIC",
    "sg:tags":[
        "wholesaler"
    ],
    "wof:name":"Rexel Electrical Supplies",
    "wof:placetype":"venue"
},
  "geometry": {"coordinates":[145.029006958,-37.6905784607],"type":"Point"}
}