{
  "type": "Feature",
  "properties": {
    "iso:country":"AU",
    "sg:address":"14 Lake Rd",
    "sg:city":"Port Macquarie",
    "sg:classifiers":[
        {
            "category":"Health Services",
            "subcategory":"Doctor",
            "type":"Services"
        }
    ],
    "sg:phone":"+61 2 6583 2008",
    "sg:postcode":"2444",
    "sg:province":"NSW",
    "sg:tags":[
        "medical",
        "practitioner"
    ],
    "wof:name":"Gregory David",
    "wof:placetype":"venue"
},
  "geometry": {"coordinates":[152.911423,-31.435587],"type":"Point"}
}