{
  "type": "Feature",
  "properties": {
    "iso:country":"AU",
    "sg:address":"281 Centre Rd",
    "sg:city":"Bentleigh",
    "sg:classifiers":[
        {
            "category":"Shopping",
            "subcategory":"Clothing, Apparel, & Fashions",
            "type":"Retail Goods"
        }
    ],
    "sg:phone":"+61 3 9557 8551",
    "sg:postcode":"3204",
    "sg:province":"VIC",
    "sg:tags":[
        "boutique"
    ],
    "wof:name":"Amiti\ufffd Textiles",
    "wof:placetype":"venue"
},
  "geometry": {"coordinates":[145.033356,-37.91766],"type":"Point"}
}