{
  "type": "Feature",
  "properties": {
    "addr:full":"16 Heathersay Ave Aldinga Beach SA 5173",
    "addr:housenumber":"16",
    "addr:postcode":"5173",
    "addr:street":"Heathersay Ave",
    "iso:country":"AU",
    "sg:address":"16 Heathersay Ave",
    "sg:city":"Aldinga Beach",
    "sg:classifiers":[
        {
            "category":"Retail",
            "subcategory":"Veterinary Services",
            "type":"Services"
        }
    ],
    "sg:phone":"+61 8 8556 5498",
    "sg:postcode":"5173",
    "sg:province":"SA",
    "sg:tags":[
        "surgeon"
    ],
    "wof:name":"Blackwell R G",
    "wof:placetype":"venue"
},
  "geometry": {"coordinates":[138.45904540999999,-35.2734642029],"type":"Point"}
}