{
  "type": "Feature",
  "properties": {
    "iso:country":"AU",
    "sg:address":"23 Brierty St",
    "sg:city":"Wynnum West",
    "sg:classifiers":[
        {
            "category":"Shopping",
            "subcategory":"Computers & Home Electronics",
            "type":"Retail Goods"
        }
    ],
    "sg:phone":"+61 7 3893 2820",
    "sg:postcode":"4178",
    "sg:province":"QLD",
    "sg:tags":[
        "small",
        "equipment",
        "business"
    ],
    "wof:name":"Computer Allied Services",
    "wof:placetype":"venue"
},
  "geometry": {"coordinates":[153.15640258799999,-27.4464435577],"type":"Point"}
}