{
  "type": "Feature",
  "properties": {
    "iso:country":"AU",
    "sg:address":"10 Lakelands Drv",
    "sg:city":"Wangara",
    "sg:classifiers":[
        {
            "category":"Arts & Performance",
            "subcategory":"Comedy Club",
            "type":"Entertainment"
        }
    ],
    "sg:phone":"+61 8 9306 4020",
    "sg:postcode":"6065",
    "sg:province":"WA",
    "sg:tags":[
        "piano",
        "removal"
    ],
    "wof:name":"Bonds Removalists",
    "wof:placetype":"venue"
},
  "geometry": {"coordinates":[115.84644317599999,-31.7834358215],"type":"Point"}
}