{
  "type": "Feature",
  "properties": {
    "iso:country":"AU",
    "sg:address":"Brentnall Rd",
    "sg:city":"Croydon",
    "sg:classifiers":[
        {
            "category":"Education",
            "subcategory":"School",
            "type":"Public Place"
        }
    ],
    "sg:phone":"+61 3 9870 4551",
    "sg:postcode":"3136",
    "sg:province":"VIC",
    "sg:tags":[
        "state",
        "except",
        "nsw"
    ],
    "wof:name":"Maroondah Secondary College",
    "wof:placetype":"venue"
},
  "geometry": {"coordinates":[145.26213073700001,-37.7942390442],"type":"Point"}
}