{
  "type": "Feature",
  "properties": {
    "iso:country":"AU",
    "sg:address":"Cnr Adelaide & William Sts",
    "sg:city":"Fremantle",
    "sg:classifiers":[
        {
            "category":"Banks & Credit Unions",
            "subcategory":"Bureau De Change",
            "type":"Services"
        }
    ],
    "sg:phone":"+61 8 9431 7022",
    "sg:postcode":"6160",
    "sg:province":"WA",
    "sg:tags":[
        "currency",
        "exchange",
        "foreign"
    ],
    "wof:name":"Interforex Pty Ltd",
    "wof:placetype":"venue"
},
  "geometry": {"coordinates":[115.749512,-32.050991],"type":"Point"}
}