{
  "type": "Feature",
  "properties": {
    "addr:full":"1964 Anderson Rd Karratha WA 6714",
    "addr:housenumber":"1964",
    "addr:postcode":"6714",
    "addr:street":"Anderson Rd",
    "iso:country":"AU",
    "sg:address":"1964 Anderson Rd",
    "sg:city":"Karratha",
    "sg:classifiers":[
        {
            "category":"Home & Garden",
            "subcategory":"Hardware",
            "type":"Retail Goods"
        }
    ],
    "sg:phone":"+61 8 9144 4646",
    "sg:postcode":"6714",
    "sg:province":"WA",
    "sg:tags":[
        "generating",
        "set",
        "generator"
    ],
    "wof:name":"Cummins",
    "wof:placetype":"venue"
},
  "geometry": {"coordinates":[116.870727539,-20.7680187225],"type":"Point"}
}