{
  "type": "Feature",
  "properties": {
    "addr:full":"18 Chaleyer St Glen Iris VIC 3146",
    "addr:housenumber":"18",
    "addr:postcode":"3146",
    "addr:street":"Chaleyer St",
    "iso:country":"AU",
    "sg:address":"18 Chaleyer St",
    "sg:city":"Glen Iris",
    "sg:classifiers":[
        {
            "category":"Utilities",
            "subcategory":"Water",
            "type":"Services"
        }
    ],
    "sg:phone":"+61 3 9885 5392",
    "sg:postcode":"3146",
    "sg:province":"VIC",
    "sg:tags":[
        "equipment",
        "treatment"
    ],
    "sg:website":"http://www.allpure.com.au",
    "wof:name":"Allpure Water Systems.",
    "wof:placetype":"venue"
},
  "geometry": {"coordinates":[145.085205078,-37.8589706421],"type":"Point"}
}