{
  "type": "Feature",
  "properties": {
    "addr:full":"Ste 8/ 860 Nepean Hwy Hampton East VIC 3188",
    "addr:housenumber":"/ 860",
    "addr:postcode":"3188",
    "addr:street":"Nepean Hwy",
    "iso:country":"AU",
    "sg:address":"Ste 8/ 860 Nepean Hwy",
    "sg:city":"Hampton East",
    "sg:classifiers":[
        {
            "category":"Professional",
            "subcategory":"Computer Services",
            "type":"Services"
        }
    ],
    "sg:phone":"+61 3 9555 1159",
    "sg:postcode":"3188",
    "sg:province":"VIC",
    "sg:tags":[
        "package",
        "software"
    ],
    "wof:name":"Compros Australia Pty Ltd",
    "wof:placetype":"venue"
},
  "geometry": {"coordinates":[145.03503418,-37.9340820312],"type":"Point"}
}