{
  "type": "Feature",
  "properties": {
    "addr:full":"43 Gilchrist St Shepparton VIC 3630",
    "addr:housenumber":"43",
    "addr:postcode":"3630",
    "addr:street":"Gilchrist St",
    "iso:country":"AU",
    "sg:address":"43 Gilchrist St",
    "sg:city":"Shepparton",
    "sg:classifiers":[
        {
            "category":"Building & Trades",
            "subcategory":"Construction",
            "type":"Services"
        }
    ],
    "sg:phone":"+61 3 5822 0266",
    "sg:postcode":"3630",
    "sg:province":"VIC",
    "sg:tags":[
        "pool",
        "swimming"
    ],
    "wof:name":"Aquazone Pools & Spas",
    "wof:placetype":"venue"
},
  "geometry": {"coordinates":[145.41818237300001,-36.3880882263],"type":"Point"}
}