{
  "type": "Feature",
  "properties": {
    "addr:full":"1454 Gowings Hill Rd Sherwood NSW 2440",
    "addr:housenumber":"1454",
    "addr:postcode":"2440",
    "addr:street":"Gowings Hill Rd",
    "iso:country":"AU",
    "sg:address":"1454 Gowings Hill Rd",
    "sg:city":"Sherwood",
    "sg:classifiers":[
        {
            "category":"Building & Trades",
            "subcategory":"Plumbing",
            "type":"Services"
        }
    ],
    "sg:phone":"+61 2 6566 9205",
    "sg:postcode":"2440",
    "sg:province":"NSW",
    "sg:tags":[
        "plumber",
        "gasfitters"
    ],
    "wof:name":"Packwood Plumbing",
    "wof:placetype":"venue"
},
  "geometry": {"coordinates":[152.724716,-31.061453],"type":"Point"}
}