{
  "type": "Feature",
  "properties": {
    "addr:full":"Lvl 4, 66 Berry St North Sydney NSW 2060",
    "addr:housenumber":"66",
    "addr:postcode":"2060",
    "addr:street":"Berry St",
    "iso:country":"AU",
    "sg:address":"Lvl 4, 66 Berry St",
    "sg:city":"North Sydney",
    "sg:classifiers":[
        {
            "category":"Professional",
            "subcategory":"Management & Consulting",
            "type":"Services"
        }
    ],
    "sg:phone":"+61 2 9957 6521",
    "sg:postcode":"2060",
    "sg:province":"NSW",
    "sg:tags":[
        "consultant"
    ],
    "wof:name":"Decision Support Centres Of Australia",
    "wof:placetype":"venue"
},
  "geometry": {"coordinates":[151.20831298799999,-33.8368377686],"type":"Point"}
}