{
  "type": "Feature",
  "properties": {
    "addr:full":"383 Albert St East Melbourne VIC 3002",
    "addr:housenumber":"383",
    "addr:postcode":"3002",
    "addr:street":"Albert St",
    "iso:country":"AU",
    "sg:address":"383 Albert St",
    "sg:city":"East Melbourne",
    "sg:classifiers":[
        {
            "category":"Government",
            "subcategory":"Court House",
            "type":"Public Place"
        }
    ],
    "sg:phone":"+61 3 9287 5505",
    "sg:postcode":"3002",
    "sg:province":"VIC",
    "sg:tags":[
        "personal",
        "marriage",
        "family",
        "counselling"
    ],
    "wof:name":"Seasons Loss & Grief Program",
    "wof:placetype":"venue"
},
  "geometry": {"coordinates":[144.977416992,-37.8098754883],"type":"Point"}
}