{
  "type": "Feature",
  "properties": {
    "iso:country":"AU",
    "sg:address":"21 Coromandel Pde",
    "sg:city":"Blackwood",
    "sg:classifiers":[
        {
            "category":"Arts & Performance",
            "subcategory":"Theater",
            "type":"Entertainment"
        }
    ],
    "sg:phone":"+61 1300 658 522",
    "sg:postcode":"5051",
    "sg:province":"SA",
    "sg:tags":[
        "theatre"
    ],
    "wof:name":"Blackwood Players Incorporated",
    "wof:placetype":"venue"
},
  "geometry": {"coordinates":[138.617996,-35.023666],"type":"Point"}
}