{
  "type": "Feature",
  "properties": {
    "addr:full":"151 Old Northern Rd Baulkham Hills NSW 2153",
    "addr:housenumber":"151",
    "addr:postcode":"2153",
    "addr:street":"Old Northern Rd",
    "iso:country":"AU",
    "sg:address":"151 Old Northern Rd",
    "sg:city":"Baulkham Hills",
    "sg:classifiers":[
        {
            "category":"Professional",
            "subcategory":"Business Services",
            "type":"Services"
        }
    ],
    "sg:phone":"+61 2 9686 2032",
    "sg:postcode":"2153",
    "sg:province":"NSW",
    "sg:tags":[
        "drafting"
    ],
    "wof:name":"Recaf Design",
    "wof:placetype":"venue"
},
  "geometry": {"coordinates":[151.00982665999999,-33.7314987183],"type":"Point"}
}