{
  "type": "Feature",
  "properties": {
    "addr:full":"143 Boorowa St Young NSW 2594",
    "addr:housenumber":"143",
    "addr:postcode":"2594",
    "addr:street":"Boorowa St",
    "iso:country":"AU",
    "sg:address":"143 Boorowa St",
    "sg:city":"Young",
    "sg:classifiers":[
        {
            "category":"Restaurant",
            "type":"Food & Drink"
        }
    ],
    "sg:phone":"+61 2 6382 7255",
    "sg:postcode":"2594",
    "sg:province":"NSW",
    "wof:name":"Cherrywood Licenced Cafe/Rest",
    "wof:placetype":"venue"
},
  "geometry": {"coordinates":[148.294021606,-34.3124351501],"type":"Point"}
}