{
  "type": "Feature",
  "properties": {
    "addr:full":"Shop 31 Riverton Forum Shopng Cntr Riverton WA 6148",
    "addr:housenumber":"shop 31",
    "addr:postcode":"6148",
    "iso:country":"AU",
    "sg:address":"Shop 31 Riverton Forum Shopng Cntr",
    "sg:city":"Riverton",
    "sg:classifiers":[
        {
            "category":"Ice Cream",
            "type":"Food & Drink"
        }
    ],
    "sg:phone":"+61 8 9457 4776",
    "sg:postcode":"6148",
    "sg:province":"WA",
    "sg:tags":[
        "retail"
    ],
    "wof:name":"Wendy's Supa Sundaes",
    "wof:placetype":"venue"
},
  "geometry": {"coordinates":[115.861969,-32.040756],"type":"Point"}
}