{
  "type": "Feature",
  "properties": {
    "addr:full":"17 Allambie Crs Kiama NSW 2533",
    "addr:housenumber":"17",
    "addr:postcode":"2533",
    "addr:street":"Allambie Crs",
    "iso:country":"AU",
    "sg:address":"17 Allambie Crs",
    "sg:city":"Kiama",
    "sg:classifiers":[
        {
            "category":"Building & Trades",
            "subcategory":"Plumbing",
            "type":"Services"
        }
    ],
    "sg:phone":"+61 414 611 418",
    "sg:postcode":"2533",
    "sg:province":"NSW",
    "sg:tags":[
        "plumber",
        "gasfitters"
    ],
    "wof:name":"Alements Plumbing",
    "wof:placetype":"venue"
},
  "geometry": {"coordinates":[150.851806641,-34.6771583557],"type":"Point"}
}