{
  "type": "Feature",
  "properties": {
    "iso:country":"AU",
    "sg:address":"9 Marong Crt",
    "sg:city":"Boronia",
    "sg:classifiers":[
        {
            "category":"Shopping",
            "subcategory":"Crafts & Fabrics",
            "type":"Retail Goods"
        }
    ],
    "sg:phone":"+61 3 9778 9066",
    "sg:postcode":"3155",
    "sg:province":"VIC",
    "sg:tags":[
        "florist",
        "supply"
    ],
    "wof:name":"Jobar Imports",
    "wof:placetype":"venue"
},
  "geometry": {"coordinates":[145.306884766,-37.8426551819],"type":"Point"}
}