{
  "type": "Feature",
  "properties": {
    "addr:full":"15 Holyrood Ave Newtown VIC 3220",
    "addr:housenumber":"15",
    "addr:postcode":"3220",
    "addr:street":"Holyrood Ave",
    "iso:country":"AU",
    "sg:address":"15 Holyrood Ave",
    "sg:city":"Newtown",
    "sg:classifiers":[
        {
            "category":"Retail",
            "subcategory":"Repair Shop",
            "type":"Services"
        }
    ],
    "sg:phone":"+61 3 5221 0408",
    "sg:postcode":"3220",
    "sg:province":"VIC",
    "sg:tags":[
        "machine",
        "repairs",
        "part",
        "dryer",
        "washing"
    ],
    "wof:name":"Walden's Appliance Service",
    "wof:placetype":"venue"
},
  "geometry": {"coordinates":[144.32690400000001,-38.157944],"type":"Point"}
}