{
  "type": "Feature",
  "properties": {
    "addr:full":"1 Freestone Rd Warwick QLD 4370",
    "addr:housenumber":"1",
    "addr:postcode":"4370",
    "addr:street":"Freestone Rd",
    "iso:country":"AU",
    "sg:address":"1 Freestone Rd",
    "sg:city":"Warwick",
    "sg:classifiers":[
        {
            "category":"Autos & Motor Vehicles",
            "subcategory":"Auto Supplies",
            "type":"Retail Goods"
        }
    ],
    "sg:phone":"+61 7 4661 1255",
    "sg:postcode":"4370",
    "sg:province":"QLD",
    "sg:tags":[
        "equipment",
        "part",
        "truck"
    ],
    "wof:name":"Bellingham & Co - Warwick",
    "wof:placetype":"venue"
},
  "geometry": {"coordinates":[152.03474426299999,-28.2141857147],"type":"Point"}
}