{
  "type": "Feature",
  "properties": {
    "addr:full":"19 Hopetoun St Bendigo VIC 3539",
    "addr:housenumber":"19",
    "addr:postcode":"3539",
    "addr:street":"Hopetoun St",
    "iso:country":"AU",
    "sg:address":"19 Hopetoun St",
    "sg:city":"Bendigo",
    "sg:classifiers":[
        {
            "category":"Real Estate",
            "subcategory":"Architect",
            "type":"Services"
        }
    ],
    "sg:phone":"+61 3 5444 3315",
    "sg:postcode":"3539",
    "sg:province":"VIC",
    "sg:tags":[
        "building",
        "designer"
    ],
    "wof:name":"Penno Drafting and Design",
    "wof:placetype":"venue"
},
  "geometry": {"coordinates":[144.284851,-36.757843],"type":"Point"}
}