{
  "type": "Feature",
  "properties": {
    "iso:country":"AU",
    "sg:address":"Gibbons Rd",
    "sg:city":"Hamilton",
    "sg:classifiers":[
        {
            "category":"Home & Garden",
            "subcategory":"Building Materials",
            "type":"Retail Goods"
        }
    ],
    "sg:phone":"+61 423 781 996",
    "sg:postcode":"3300",
    "sg:province":"VIC",
    "sg:tags":[
        "lawn",
        "cutting",
        "maintenance"
    ],
    "wof:name":"Ian Overall Mowing",
    "wof:placetype":"venue"
},
  "geometry": {"coordinates":[142.03558349599999,-37.7160377502],"type":"Point"}
}