{
  "type": "Feature",
  "properties": {
    "iso:country":"AU",
    "sg:address":"110 Wigram Rd",
    "sg:city":"Harris Park",
    "sg:classifiers":[
        {
            "category":"Government",
            "subcategory":"Fire Station",
            "type":"Public Place"
        }
    ],
    "sg:phone":"+61 2 9895 4620",
    "sg:postcode":"2150",
    "sg:province":"NSW",
    "sg:tags":[
        "brigade"
    ],
    "wof:name":"Fire Brigades-NSW",
    "wof:placetype":"venue"
},
  "geometry": {"coordinates":[151.009277344,-33.819316864],"type":"Point"}
}