{
  "type": "Feature",
  "properties": {
    "addr:full":"43 Cressbrook St Toogoolawah QLD 4313",
    "addr:housenumber":"43",
    "addr:postcode":"4313",
    "addr:street":"Cressbrook St",
    "iso:country":"AU",
    "sg:address":"43 Cressbrook St",
    "sg:city":"Toogoolawah",
    "sg:classifiers":[
        {
            "category":"Banks & Credit Unions",
            "subcategory":"Financial Services",
            "type":"Services"
        }
    ],
    "sg:phone":"+61 7 5423 0900",
    "sg:postcode":"4313",
    "sg:province":"QLD",
    "sg:tags":[
        "building",
        "society"
    ],
    "wof:name":"Heritage Building Society",
    "wof:placetype":"venue"
},
  "geometry": {"coordinates":[152.37887573200001,-27.0925273895],"type":"Point"}
}