{
  "type": "Feature",
  "properties": {
    "addr:full":"Shp 5 Oakleigh Central Shopng Cntr Oakleigh VIC 3166",
    "addr:housenumber":"5",
    "addr:postcode":"3166",
    "addr:street":"Oakleigh Central Shopng",
    "iso:country":"AU",
    "sg:address":"Shp 5",
    "sg:city":"Oakleigh Central Shopng Cntr Oakleigh",
    "sg:classifiers":[
        {
            "category":"Food & Beverages",
            "subcategory":"Liquor & Beverages",
            "type":"Retail Goods"
        }
    ],
    "sg:phone":"+61 3 9568 1444",
    "sg:postcode":"3166",
    "sg:province":"VIC",
    "sg:tags":[
        "store"
    ],
    "wof:name":"Liquorland",
    "wof:placetype":"venue"
},
  "geometry": {"coordinates":[145.10638427699999,-37.8989562988],"type":"Point"}
}