{
  "type": "Feature",
  "properties": {
    "addr:full":"8 Station Rd Wesburn VIC 3799",
    "addr:housenumber":"8",
    "addr:postcode":"3799",
    "addr:street":"Station Rd",
    "iso:country":"AU",
    "sg:address":"8 Station Rd",
    "sg:city":"Wesburn",
    "sg:classifiers":[
        {
            "category":"Building & Trades",
            "subcategory":"Construction",
            "type":"Services"
        }
    ],
    "sg:phone":"+61 413 085 139",
    "sg:postcode":"3799",
    "sg:province":"VIC",
    "sg:tags":[
        "roof"
    ],
    "wof:name":"IJV Roof Plumbing",
    "wof:placetype":"venue"
},
  "geometry": {"coordinates":[145.64326477,-37.7662200928],"type":"Point"}
}