{
  "type": "Feature",
  "properties": {
    "addr:full":"137 Barton St Oak Flats NSW 2529",
    "addr:housenumber":"137",
    "addr:postcode":"2529",
    "addr:street":"Barton St Oak Flats",
    "iso:country":"AU",
    "sg:address":"137 Barton St",
    "sg:city":"Oak Flats",
    "sg:classifiers":[
        {
            "category":"Building & Trades",
            "subcategory":"Construction",
            "type":"Services"
        }
    ],
    "sg:phone":"+61 2 4256 4597",
    "sg:postcode":"2529",
    "sg:province":"NSW",
    "sg:tags":[
        "contractor"
    ],
    "wof:name":"Coleman Terry",
    "wof:placetype":"venue"
},
  "geometry": {"coordinates":[150.81065368599999,-34.5611076355],"type":"Point"}
}