{
  "type": "Feature",
  "properties": {
    "addr:full":"Spanos Rd Silkwood East QLD 4857",
    "addr:postcode":"4857",
    "addr:street":"Spanos Rd",
    "iso:country":"AU",
    "sg:address":"Spanos Rd",
    "sg:city":"Silkwood East",
    "sg:classifiers":[
        {
            "category":"Freight",
            "type":"Transportation"
        }
    ],
    "sg:phone":"+61 7 4065 2224",
    "sg:postcode":"4857",
    "sg:province":"QLD",
    "sg:tags":[
        "light",
        "carrier"
    ],
    "wof:name":"Azzopardi Frank & John",
    "wof:placetype":"venue"
},
  "geometry": {"coordinates":[146.04440307600001,-17.7360687256],"type":"Point"}
}