{
  "type": "Feature",
  "properties": {
    "iso:country":"AU",
    "sg:address":"Greaves Rd",
    "sg:city":"Narre Warren",
    "sg:classifiers":[
        {
            "category":"Social Services",
            "subcategory":"Child Care",
            "type":"Services"
        }
    ],
    "sg:phone":"+61 425 846 106",
    "sg:postcode":"3805",
    "sg:province":"VIC",
    "wof:name":"Happy Days Child Care",
    "wof:placetype":"venue"
},
  "geometry": {"coordinates":[145.301132,-38.054882],"type":"Point"}
}