{
  "type": "Feature",
  "properties": {
    "addr:full":"Albany Hwy Mt Barker WA 6324",
    "addr:postcode":"6324",
    "addr:street":"Albany Hwy Mt",
    "iso:country":"AU",
    "sg:address":"Albany Hwy",
    "sg:city":"Mt Barker",
    "sg:classifiers":[
        {
            "category":"Farming",
            "subcategory":"Nursery",
            "type":"Manufacturing & Wholesale Goods"
        }
    ],
    "sg:phone":"+61 8 9851 1802",
    "sg:postcode":"6324",
    "sg:province":"WA",
    "wof:name":"Bandicoot Nursery",
    "wof:placetype":"venue"
},
  "geometry": {"coordinates":[117.664550781,-34.6286582947],"type":"Point"}
}