{
  "type": "Feature",
  "properties": {
    "addr:full":"332 Lygon St Carlton VIC 3053",
    "addr:housenumber":"332",
    "addr:postcode":"3053",
    "addr:street":"Lygon St",
    "iso:country":"AU",
    "sg:address":"332 Lygon St",
    "sg:city":"Carlton",
    "sg:classifiers":[
        {
            "category":"Shopping",
            "subcategory":"Clothing, Apparel, & Fashions",
            "type":"Retail Goods"
        }
    ],
    "sg:phone":"+61 3 9347 3648",
    "sg:postcode":"3053",
    "sg:province":"VIC",
    "sg:tags":[
        "menswear"
    ],
    "wof:name":"Rpm",
    "wof:placetype":"venue"
},
  "geometry": {"coordinates":[144.96737670900001,-37.7991447449],"type":"Point"}
}