{
  "type": "Feature",
  "properties": {
    "iso:country":"AU",
    "sg:address":"28 Wood St",
    "sg:city":"Geelong South",
    "sg:classifiers":[
        {
            "category":"Autos & Motor Vehicles",
            "subcategory":"Auto Supplies",
            "type":"Retail Goods"
        }
    ],
    "sg:phone":"+61 3 5222 1816",
    "sg:postcode":"3220",
    "sg:province":"VIC",
    "sg:tags":[
        "camper-trailers",
        "caravan",
        "equipment"
    ],
    "wof:name":"Driftaway Caravans Geelong",
    "wof:placetype":"venue"
},
  "geometry": {"coordinates":[144.367874,-38.170128],"type":"Point"}
}