{
  "type": "Feature",
  "properties": {
    "iso:country":"AU",
    "sg:address":"645 Burwood Road",
    "sg:city":"Hawthorn East",
    "sg:classifiers":[
        {
            "category":"Professional",
            "subcategory":"Art Services",
            "type":"Services"
        }
    ],
    "sg:phone":"+61 3 8800 3889",
    "sg:postcode":"3123",
    "sg:province":"VIC",
    "sg:tags":[
        "graphic",
        "designer"
    ],
    "wof:name":"Blackfeather Graphics",
    "wof:placetype":"venue"
},
  "geometry": {"coordinates":[145.04556274399999,-37.8236427307],"type":"Point"}
}