{
  "type": "Feature",
  "properties": {
    "addr:full":"18a Miowera Rd North Turramurra NSW 2074",
    "addr:housenumber":"18a",
    "addr:postcode":"2074",
    "addr:street":"Miowera Rd",
    "iso:country":"AU",
    "sg:address":"18a Miowera Rd",
    "sg:city":"North Turramurra",
    "sg:classifiers":[
        {
            "category":"Professional",
            "subcategory":"Computer Services",
            "type":"Services"
        }
    ],
    "sg:phone":"+61 2 9988 3587",
    "sg:postcode":"2074",
    "sg:province":"NSW",
    "sg:tags":[
        "tele-communications",
        "consultant"
    ],
    "wof:name":"Delaney Communications Pty Ltd",
    "wof:placetype":"venue"
},
  "geometry": {"coordinates":[151.15034484899999,-33.7144165039],"type":"Point"}
}