{
  "type": "Feature",
  "properties": {
    "addr:full":"118 Lockyer Ave Albany WA 6330",
    "addr:housenumber":"118",
    "addr:postcode":"6330",
    "addr:street":"Lockyer Ave",
    "iso:country":"AU",
    "sg:address":"118 Lockyer Ave",
    "sg:city":"Albany",
    "sg:classifiers":[
        {
            "category":"Home & Garden",
            "subcategory":"Carpets & Floor Coverings",
            "type":"Retail Goods"
        }
    ],
    "sg:phone":"+61 8 9842 2000",
    "sg:postcode":"6330",
    "sg:province":"WA",
    "sg:tags":[
        "mattress"
    ],
    "wof:name":"Albany Furniture World",
    "wof:placetype":"venue"
},
  "geometry": {"coordinates":[117.88530731199999,-35.0152282715],"type":"Point"}
}