{
  "type": "Feature",
  "properties": {
    "iso:country":"AU",
    "sg:address":"42- 44 Fowler St",
    "sg:city":"Moe",
    "sg:classifiers":[
        {
            "category":"Organizations",
            "subcategory":"Membership Organization",
            "type":"Services"
        }
    ],
    "sg:phone":"+61 3 5127 9100",
    "sg:postcode":"3825",
    "sg:province":"VIC",
    "sg:tags":[
        "support",
        "health",
        "organisation"
    ],
    "wof:name":"Alzheimer's Australia Vic",
    "wof:placetype":"venue"
},
  "geometry": {"coordinates":[146.26135300000001,-38.180294],"type":"Point"}
}