{
  "type": "Feature",
  "properties": {
    "addr:full":"21 Maisie Pl Eight Mile Plains QLD 4113",
    "addr:housenumber":"21",
    "addr:postcode":"4113",
    "addr:street":"Maisie Pl",
    "iso:country":"AU",
    "sg:address":"21 Maisie Pl",
    "sg:city":"Eight Mile Plains",
    "sg:classifiers":[
        {
            "category":"Personal",
            "subcategory":"Hair Removal",
            "type":"Services"
        }
    ],
    "sg:phone":"+61 7 3341 1562",
    "sg:postcode":"4113",
    "sg:province":"QLD",
    "wof:name":"Strip & Wax Beauty Salon",
    "wof:placetype":"venue"
},
  "geometry": {"coordinates":[153.099853516,-27.5726966858],"type":"Point"}
}