{
  "type": "Feature",
  "properties": {
    "iso:country":"AU",
    "sg:address":"52- 54 Russell St",
    "sg:city":"Tumut",
    "sg:classifiers":[
        {
            "category":"Banks & Credit Unions",
            "subcategory":"Bank",
            "type":"Services"
        }
    ],
    "sg:phone":"+61 2 6947 3311",
    "sg:postcode":"2720",
    "sg:province":"NSW",
    "sg:tags":[
        "society"
    ],
    "wof:name":"Service One Members Banking",
    "wof:placetype":"venue"
},
  "geometry": {"coordinates":[148.223526,-35.302616],"type":"Point"}
}