{
  "type": "Feature",
  "properties": {
    "iso:country":"AU",
    "sg:address":"296 Main Rd",
    "sg:city":"Glenorchy",
    "sg:classifiers":[
        {
            "category":"Fast Food",
            "type":"Food & Drink"
        }
    ],
    "sg:phone":"+61 3 6272 6558",
    "sg:postcode":"7010",
    "sg:province":"TAS",
    "sg:tags":[
        "away",
        "take"
    ],
    "wof:name":"Atlantis Take Away",
    "wof:placetype":"venue"
},
  "geometry": {"coordinates":[147.283477783,-42.8346862793],"type":"Point"}
}