{
  "type": "Feature",
  "properties": {
    "addr:full":"10 Prinsep St Bunbury WA 6230",
    "addr:housenumber":"10",
    "addr:postcode":"6230",
    "addr:street":"Prinsep St",
    "iso:country":"AU",
    "sg:address":"10 Prinsep St",
    "sg:city":"Bunbury",
    "sg:classifiers":[
        {
            "category":"Personal",
            "subcategory":"Skin Care",
            "type":"Services"
        }
    ],
    "sg:phone":"+61 8 9791 4491",
    "sg:postcode":"6230",
    "sg:province":"WA",
    "sg:tags":[
        "treatment"
    ],
    "wof:name":"Grand Central Skin & Body",
    "wof:placetype":"venue"
},
  "geometry": {"coordinates":[115.645348,-33.380112],"type":"Point"}
}