{
  "type": "Feature",
  "properties": {
    "iso:country":"AU",
    "sg:address":"41 Kathleen St",
    "sg:city":"Tamworth",
    "sg:classifiers":[
        {
            "category":"Professional",
            "subcategory":"Art Services",
            "type":"Services"
        }
    ],
    "sg:phone":"+61 2 6765 7672",
    "sg:postcode":"2340",
    "sg:province":"NSW",
    "sg:tags":[
        "decorator",
        "painter"
    ],
    "wof:name":"Daniel Philp",
    "wof:placetype":"venue"
},
  "geometry": {"coordinates":[150.918533325,-31.1107692719],"type":"Point"}
}