{
  "type": "Feature",
  "properties": {
    "addr:full":"38 kalman Drv Boronia VIC 3155",
    "addr:housenumber":"38",
    "addr:postcode":"3155",
    "addr:street":"Kalman Drv",
    "iso:country":"AU",
    "sg:address":"38 kalman Drv",
    "sg:city":"Boronia",
    "sg:classifiers":[
        {
            "category":"Retail",
            "subcategory":"Storage",
            "type":"Services"
        }
    ],
    "sg:phone":"+61 3 9738 0799",
    "sg:postcode":"3155",
    "sg:province":"VIC",
    "sg:tags":[
        "removal",
        "furniture"
    ],
    "wof:name":"Southern Trading Furniture Transport Pty Ltd",
    "wof:placetype":"venue"
},
  "geometry": {"coordinates":[145.29629516599999,-37.8362045288],"type":"Point"}
}