{
  "type": "Feature",
  "properties": {
    "addr:full":"741 Victoria Rd Ryde NSW 2112",
    "addr:housenumber":"741",
    "addr:postcode":"2112",
    "addr:street":"Victoria Rd",
    "iso:country":"AU",
    "sg:address":"741 Victoria Rd",
    "sg:city":"Ryde",
    "sg:classifiers":[
        {
            "category":"Shopping",
            "subcategory":"Mobile Phones",
            "type":"Retail Goods"
        }
    ],
    "sg:phone":"+61 13 17 60",
    "sg:postcode":"2112",
    "sg:province":"NSW",
    "sg:tags":[
        "telephone",
        "accessory"
    ],
    "wof:name":"Battery World",
    "wof:placetype":"venue"
},
  "geometry": {"coordinates":[151.10452270499999,-33.8151397705],"type":"Point"}
}