{
  "type": "Feature",
  "properties": {
    "iso:country":"AU",
    "sg:address":"Cnr Jersey & Hyatts Rds",
    "sg:city":"Plumpton",
    "sg:classifiers":[
        {
            "category":"Health Services",
            "subcategory":"Doctor",
            "type":"Services"
        }
    ],
    "sg:phone":"+61 2 9677 0037",
    "sg:postcode":"2761",
    "sg:province":"NSW",
    "sg:tags":[
        "medical",
        "practitioner"
    ],
    "wof:name":"Hampson Sugerman Macquarie Pathology",
    "wof:placetype":"venue"
},
  "geometry": {"coordinates":[150.83595299999999,-33.744141],"type":"Point"}
}