{
  "type": "Feature",
  "properties": {
    "addr:full":"52 Old Laidley Foest Hill Rd Forest Hill QLD 4342",
    "addr:housenumber":"52",
    "addr:postcode":"4342",
    "addr:street":"Old Laidley Foest Hill Rd",
    "iso:country":"AU",
    "sg:address":"52 Old Laidley Foest Hill Rd",
    "sg:city":"Forest Hill",
    "sg:classifiers":[
        {
            "category":"Shopping",
            "subcategory":"Computers & Home Electronics",
            "type":"Retail Goods"
        }
    ],
    "sg:phone":"+61 7 5465 4976",
    "sg:postcode":"4342",
    "sg:province":"QLD",
    "sg:tags":[
        "equipment",
        "supply"
    ],
    "wof:name":"G Holder Computer Service",
    "wof:placetype":"venue"
},
  "geometry": {"coordinates":[152.36929321299999,-27.581735611],"type":"Point"}
}