{
  "type": "Feature",
  "properties": {
    "iso:country":"AU",
    "sg:address":"18 Bardwell Rd",
    "sg:city":"Mosman",
    "sg:classifiers":[
        {
            "category":"Health Services",
            "subcategory":"Nursing And Care Facility",
            "type":"Services"
        }
    ],
    "sg:phone":"+61 2 9969 2500",
    "sg:postcode":"2088",
    "sg:province":"NSW",
    "sg:tags":[
        "home"
    ],
    "wof:name":"Amity at Mosman",
    "wof:placetype":"venue"
},
  "geometry": {"coordinates":[151.23558044399999,-33.8238983154],"type":"Point"}
}