{
  "type": "Feature",
  "properties": {
    "iso:country":"AU",
    "sg:address":"2/41 Wises Rd",
    "sg:city":"Maroochydore",
    "sg:classifiers":[
        {
            "category":"Retail",
            "subcategory":"Repair Shop",
            "type":"Services"
        }
    ],
    "sg:phone":"+61 7 5443 4570",
    "sg:postcode":"4558",
    "sg:province":"QLD",
    "sg:tags":[
        "upholsterer"
    ],
    "wof:name":"Glens Upholstery",
    "wof:placetype":"venue"
},
  "geometry": {"coordinates":[153.086227417,-26.6714420319],"type":"Point"}
}