{
  "type": "Feature",
  "properties": {
    "iso:country":"AU",
    "sg:address":"Unit 1, 14- 16 Brewers St",
    "sg:city":"Burpengary",
    "sg:classifiers":[
        {
            "category":"Home & Garden",
            "subcategory":"Building Materials",
            "type":"Retail Goods"
        }
    ],
    "sg:phone":"+61 1800 652 267",
    "sg:postcode":"4505",
    "sg:province":"QLD",
    "sg:tags":[
        "plaster",
        "plasterboard",
        "supply"
    ],
    "wof:name":"Pro Plaster Products",
    "wof:placetype":"venue"
},
  "geometry": {"coordinates":[152.95494079599999,-27.208026886],"type":"Point"}
}