{
  "type": "Feature",
  "properties": {
    "addr:full":"89 Rushdale St Scoresby VIC 3179",
    "addr:housenumber":"89",
    "addr:postcode":"3179",
    "addr:street":"Rushdale St",
    "iso:country":"AU",
    "sg:address":"89 Rushdale St",
    "sg:city":"Scoresby",
    "sg:classifiers":[
        {
            "category":"Structure",
            "subcategory":"Bridge",
            "type":"Public Place"
        }
    ],
    "sg:phone":"+61 3 9764 8055",
    "sg:postcode":"3179",
    "sg:province":"VIC",
    "sg:tags":[
        "chainsaw",
        "brushcutters"
    ],
    "wof:name":"Dolmar",
    "wof:placetype":"venue"
},
  "geometry": {"coordinates":[145.249435425,-37.9025039673],"type":"Point"}
}