{
  "type": "Feature",
  "properties": {
    "addr:full":"Shop 45B Old Perth Rd Bassendean WA 6054",
    "addr:housenumber":"45b",
    "addr:postcode":"6054",
    "addr:street":"Shop;Old Perth Rd",
    "iso:country":"AU",
    "sg:address":"Shop 45B Old Perth Rd",
    "sg:city":"Bassendean",
    "sg:classifiers":[
        {
            "category":"Education",
            "subcategory":"Special Training",
            "type":"Public Place"
        }
    ],
    "sg:phone":"+61 8 9377 2113",
    "sg:postcode":"6054",
    "sg:province":"WA",
    "sg:tags":[
        "college",
        "hairdressing"
    ],
    "wof:name":"Blackberries",
    "wof:placetype":"venue"
},
  "geometry": {"coordinates":[115.94972229,-31.9043540955],"type":"Point"}
}