{
  "type": "Feature",
  "properties": {
    "addr:full":"4 Curdie St Cobden VIC 3266",
    "addr:housenumber":"4",
    "addr:postcode":"3266",
    "addr:street":"Curdie St",
    "iso:country":"AU",
    "sg:address":"4 Curdie St",
    "sg:city":"Cobden",
    "sg:classifiers":[
        {
            "category":"Retail",
            "subcategory":"Veterinary Services",
            "type":"Services"
        }
    ],
    "sg:phone":"+61 3 5595 1534",
    "sg:postcode":"3266",
    "sg:province":"VIC",
    "sg:tags":[
        "surgeon"
    ],
    "wof:name":"Darcy G M",
    "wof:placetype":"venue"
},
  "geometry": {"coordinates":[143.07951355,-38.3286209106],"type":"Point"}
}