{
  "type": "Feature",
  "properties": {
    "addr:full":"Unit 3 1 Stockwell Pl Archerfield QLD 4108",
    "addr:housenumber":"1",
    "addr:postcode":"4108",
    "addr:street":"Stockwell Pl",
    "iso:country":"AU",
    "sg:address":"Unit 3 1 Stockwell Pl",
    "sg:city":"Archerfield",
    "sg:classifiers":[
        {
            "category":"Shopping",
            "subcategory":"Optical Goods",
            "type":"Retail Goods"
        }
    ],
    "sg:phone":"+61 7 3276 7428",
    "sg:postcode":"4108",
    "sg:province":"QLD",
    "sg:tags":[
        "supply"
    ],
    "wof:name":"CMC Ultramold Pty Ltd",
    "wof:placetype":"venue"
},
  "geometry": {"coordinates":[153.01661682100001,-27.5673274994],"type":"Point"}
}