{
  "type": "Feature",
  "properties": {
    "addr:full":"Westfield Carindale Shopping Cntr Carindale QLD 4152",
    "addr:postcode":"4152",
    "iso:country":"AU",
    "sg:address":"Westfield Carindale Shopping Cntr",
    "sg:city":"Carindale",
    "sg:classifiers":[
        {
            "category":"Banks & Credit Unions",
            "subcategory":"Bank",
            "type":"Services"
        }
    ],
    "sg:phone":"+61 7 3398 8044",
    "sg:postcode":"4152",
    "sg:province":"QLD",
    "sg:tags":[
        "broker",
        "mortgage"
    ],
    "wof:name":"Mortgage Choice",
    "wof:placetype":"venue"
},
  "geometry": {"coordinates":[153.10316467300001,-27.5040683746],"type":"Point"}
}