{
  "type": "Feature",
  "properties": {
    "iso:country":"AU",
    "sg:address":"27 Lathams Rd",
    "sg:city":"Carrum Downs",
    "sg:classifiers":[
        {
            "category":"Retail",
            "subcategory":"Auto Repair",
            "type":"Services"
        }
    ],
    "sg:phone":"+61 3 9775 1314",
    "sg:postcode":"3201",
    "sg:province":"VIC",
    "sg:tags":[
        "repairer",
        "motor",
        "engineer"
    ],
    "wof:name":"M.A.C Automotive",
    "wof:placetype":"venue"
},
  "geometry": {"coordinates":[145.16789199999999,-38.098896],"type":"Point"}
}