{
  "type": "Feature",
  "properties": {
    "addr:full":"1 Wilkinson St Reservoir VIC 3073",
    "addr:housenumber":"1",
    "addr:postcode":"3073",
    "addr:street":"Wilkinson St",
    "iso:country":"AU",
    "sg:address":"1 Wilkinson St",
    "sg:city":"Reservoir",
    "sg:classifiers":[
        {
            "category":"Building & Trades",
            "subcategory":"Cleaning & Sanitation",
            "type":"Services"
        }
    ],
    "sg:phone":"+61 3 9478 3683",
    "sg:postcode":"3073",
    "sg:province":"VIC",
    "sg:tags":[
        "cleaner",
        "repairer",
        "roof"
    ],
    "wof:name":"Melbourne Roof Restoration",
    "wof:placetype":"venue"
},
  "geometry": {"coordinates":[145.01927185100001,-37.7275733948],"type":"Point"}
}