{
  "type": "Feature",
  "properties": {
    "iso:country":"AU",
    "sg:address":"Harker St",
    "sg:city":"Sunbury",
    "sg:classifiers":[
        {
            "category":"Retail",
            "subcategory":"Auto Repair",
            "type":"Services"
        }
    ],
    "sg:phone":"+61 3 9740 6222",
    "sg:postcode":"3429",
    "sg:province":"VIC",
    "sg:tags":[
        "transmission",
        "automotive",
        "car"
    ],
    "wof:name":"P.C. Automatics",
    "wof:placetype":"venue"
},
  "geometry": {"coordinates":[144.72735595699999,-37.5836181641],"type":"Point"}
}