{
  "type": "Feature",
  "properties": {
    "addr:full":"40 Gregory St Batemans Bay NSW 2536",
    "addr:housenumber":"40",
    "addr:postcode":"2536",
    "addr:street":"Gregory St",
    "iso:country":"AU",
    "sg:address":"40 Gregory St",
    "sg:city":"Batemans Bay",
    "sg:classifiers":[
        {
            "category":"Retail",
            "subcategory":"Auto Repair",
            "type":"Services"
        }
    ],
    "sg:phone":"+61 2 4472 5829",
    "sg:postcode":"2536",
    "sg:province":"NSW",
    "sg:tags":[
        "repairer",
        "motor",
        "engineer"
    ],
    "wof:name":"B & S Automatics",
    "wof:placetype":"venue"
},
  "geometry": {"coordinates":[150.178955078,-35.7183227539],"type":"Point"}
}