{
  "type": "Feature",
  "properties": {
    "iso:country":"AU",
    "sg:address":"51 Ross Crs",
    "sg:city":"Blaxland",
    "sg:classifiers":[
        {
            "category":"Building & Trades",
            "subcategory":"Landscaping Services",
            "type":"Services"
        }
    ],
    "sg:phone":"+61 411 024 075",
    "sg:postcode":"2774",
    "sg:province":"NSW",
    "sg:tags":[
        "designer",
        "landscape",
        "contractor"
    ],
    "wof:name":"GO enviro Landscapes",
    "wof:placetype":"venue"
},
  "geometry": {"coordinates":[150.60708618199999,-33.7418785095],"type":"Point"}
}