{
  "type": "Feature",
  "properties": {
    "iso:country":"AU",
    "sg:address":"PO Box 1011",
    "sg:city":"Bathurst",
    "sg:classifiers":[
        {
            "category":"Farming",
            "subcategory":"Nursery",
            "type":"Manufacturing & Wholesale Goods"
        }
    ],
    "sg:phone":"+61 2 6332 6960",
    "sg:postcode":"2795",
    "sg:province":"NSW",
    "wof:name":"Australian Nurserymen's Fruit Improve Co Ltd",
    "wof:placetype":"venue"
},
  "geometry": {"coordinates":[149.57583618199999,-33.4188270569],"type":"Point"}
}