{
  "type": "Feature",
  "properties": {
    "addr:full":"338 Mowbray Rd Chatswood NSW 2067",
    "addr:housenumber":"338",
    "addr:postcode":"2067",
    "addr:street":"Mowbray Rd",
    "iso:country":"AU",
    "sg:address":"338 Mowbray Rd",
    "sg:city":"Chatswood",
    "sg:classifiers":[
        {
            "category":"Health Services",
            "subcategory":"Health Practitioner",
            "type":"Services"
        }
    ],
    "sg:phone":"+61 2 9413 4674",
    "sg:postcode":"2067",
    "sg:province":"NSW",
    "sg:tags":[
        "osteopath"
    ],
    "wof:name":"Garland William",
    "wof:placetype":"venue"
},
  "geometry": {"coordinates":[151.18325805699999,-33.803237915],"type":"Point"}
}