{
  "type": "Feature",
  "properties": {
    "iso:country":"AU",
    "sg:address":"1 Mcgeehan Crs",
    "sg:city":"Myrtleford",
    "sg:classifiers":[
        {
            "category":"Utilities",
            "subcategory":"Electric",
            "type":"Services"
        }
    ],
    "sg:phone":"+61 3 5752 1717",
    "sg:postcode":"3737",
    "sg:province":"VIC",
    "sg:tags":[
        "electrical",
        "contractor"
    ],
    "wof:name":"CBE Electrical & Air Conditioning P/L",
    "wof:placetype":"venue"
},
  "geometry": {"coordinates":[146.723876953,-36.5606575012],"type":"Point"}
}