{
  "type": "Feature",
  "properties": {
    "iso:country":"AU",
    "sg:address":"Lvl1/ 429 High St",
    "sg:city":"Penrith",
    "sg:classifiers":[
        {
            "category":"Banks & Credit Unions",
            "subcategory":"Financial Services",
            "type":"Services"
        }
    ],
    "sg:phone":"+61 2 4722 6971",
    "sg:postcode":"2750",
    "sg:province":"NSW",
    "sg:tags":[
        "planning"
    ],
    "wof:name":"Fusion Financial Solutions (Sydney) Pty Ltd",
    "wof:placetype":"venue"
},
  "geometry": {"coordinates":[150.91557312,-33.894908905],"type":"Point"}
}