{
  "type": "Feature",
  "properties": {
    "addr:full":"140 Redfern St Redfern NSW 2016",
    "addr:housenumber":"140",
    "addr:postcode":"2016",
    "addr:street":"Redfern St",
    "iso:country":"AU",
    "sg:address":"140 Redfern St",
    "sg:city":"Redfern",
    "sg:classifiers":[
        {
            "category":"Shopping",
            "subcategory":"Clothing, Apparel, & Fashions",
            "type":"Retail Goods"
        }
    ],
    "sg:phone":"+61 2 9319 1461",
    "sg:postcode":"2016",
    "sg:province":"NSW",
    "sg:tags":[
        "lady",
        "wear"
    ],
    "wof:name":"Second To None",
    "wof:placetype":"venue"
},
  "geometry": {"coordinates":[151.20237731899999,-33.89245224],"type":"Point"}
}