{
  "type": "Feature",
  "properties": {
    "iso:country":"AU",
    "sg:address":"Grevillea Drv",
    "sg:city":"Alice Springs",
    "sg:classifiers":[
        {
            "category":"Education",
            "subcategory":"University",
            "type":"Public Place"
        }
    ],
    "sg:phone":"+61 1800 654 865",
    "sg:postcode":"0871",
    "sg:province":"NT",
    "sg:tags":[
        "college",
        "tertiary"
    ],
    "wof:name":"Charles Darwin University",
    "wof:placetype":"venue"
},
  "geometry": {"coordinates":[133.89614868199999,-23.6970424652],"type":"Point"}
}