{
  "type": "Feature",
  "properties": {
    "addr:full":"Shop 96, Lake Haven Shopping Centre, Lakr Haven Drv Lake Haven NSW 2263",
    "addr:housenumber":"shop 96",
    "addr:postcode":"2263",
    "addr:street":"Lake Haven;Haven Drv Lake",
    "iso:country":"AU",
    "sg:address":"Shop 96, Lake Haven Shopping Centre, Lakr Haven Drv",
    "sg:city":"Lake Haven",
    "sg:classifiers":[
        {
            "category":"Shopping",
            "subcategory":"Clothing, Apparel, & Fashions",
            "type":"Retail Goods"
        }
    ],
    "sg:phone":"+61 2 4392 7785",
    "sg:postcode":"2263",
    "sg:province":"NSW",
    "sg:tags":[
        "lady",
        "wear"
    ],
    "wof:name":"Noni- B-Fashions",
    "wof:placetype":"venue"
},
  "geometry": {"coordinates":[151.49774199999999,-33.24651],"type":"Point"}
}