{
  "type": "Feature",
  "properties": {
    "addr:full":"Ste 6/ 167 Queen St Campbelltown NSW 2560",
    "addr:housenumber":"/ 167",
    "addr:postcode":"2560",
    "addr:street":"Queen St",
    "iso:country":"AU",
    "sg:address":"Ste 6/ 167 Queen St",
    "sg:city":"Campbelltown",
    "sg:classifiers":[
        {
            "category":"Professional",
            "subcategory":"Detective & Security Services",
            "type":"Services"
        }
    ],
    "sg:phone":"+61 2 4628 1195",
    "sg:postcode":"2560",
    "sg:province":"NSW",
    "sg:tags":[
        "consultant",
        "system"
    ],
    "wof:name":"B D S Assoc Security",
    "wof:placetype":"venue"
},
  "geometry": {"coordinates":[150.81404113799999,-34.0666999817],"type":"Point"}
}