{
  "type": "Feature",
  "properties": {
    "iso:country":"AU",
    "sg:address":"1a Windsor Ave",
    "sg:city":"Springvale",
    "sg:classifiers":[
        {
            "category":"Shopping",
            "subcategory":"Jewelry",
            "type":"Retail Goods"
        }
    ],
    "sg:phone":"+61 3 9546 1151",
    "sg:postcode":"3171",
    "sg:province":"VIC",
    "sg:tags":[
        "jeweller"
    ],
    "wof:name":"Kim Mai Jewellery",
    "wof:placetype":"venue"
},
  "geometry": {"coordinates":[145.151947022,-37.9517288208],"type":"Point"}
}