{
  "type": "Feature",
  "properties": {
    "addr:full":"356 Church St Parramatta NSW 2150",
    "addr:housenumber":"356",
    "addr:postcode":"2150",
    "addr:street":"Church St",
    "iso:country":"AU",
    "sg:address":"356 Church St",
    "sg:city":"Parramatta",
    "sg:classifiers":[
        {
            "category":"Shopping",
            "subcategory":"Department Store",
            "type":"Retail Goods"
        }
    ],
    "sg:phone":"+61 2 9890 1274",
    "sg:postcode":"2150",
    "sg:province":"NSW",
    "wof:name":"Lee A & J Trading Co",
    "wof:placetype":"venue"
},
  "geometry": {"coordinates":[151.00535583499999,-33.8093948364],"type":"Point"}
}