{
  "type": "Feature",
  "properties": {
    "addr:full":"1522 Ipswich Rd Rocklea QLD 4106",
    "addr:housenumber":"1522",
    "addr:postcode":"4106",
    "addr:street":"Ipswich Rd",
    "iso:country":"AU",
    "sg:address":"1522 Ipswich Rd",
    "sg:city":"Rocklea",
    "sg:classifiers":[
        {
            "category":"Autos & Motor Vehicles",
            "subcategory":"Automobile Sales",
            "type":"Retail Goods"
        }
    ],
    "sg:phone":"+61 7 3277 5200",
    "sg:postcode":"4106",
    "sg:province":"QLD",
    "sg:tags":[
        "bus",
        "used",
        "truck"
    ],
    "wof:name":"Boss Truck Sales",
    "wof:placetype":"venue"
},
  "geometry": {"coordinates":[153.009841919,-27.5507488251],"type":"Point"}
}