{
  "type": "Feature",
  "properties": {
    "addr:full":"20a Armstrong St Middle Park VIC 3206",
    "addr:housenumber":"20a",
    "addr:postcode":"3206",
    "addr:street":"Armstrong St",
    "iso:country":"AU",
    "sg:address":"20a Armstrong St",
    "sg:city":"Middle Park",
    "sg:classifiers":[
        {
            "category":"Travel",
            "subcategory":"Hotels & Motels",
            "type":"Entertainment"
        }
    ],
    "sg:phone":"+61 3 9686 3511",
    "sg:postcode":"3206",
    "sg:province":"VIC",
    "sg:tags":[
        "accommodation"
    ],
    "wof:name":"Ashley Hotel Group Pty Ltd",
    "wof:placetype":"venue"
},
  "geometry": {"coordinates":[144.964294,-37.850204],"type":"Point"}
}