{
  "type": "Feature",
  "properties": {
    "iso:country":"AU",
    "sg:address":"70 Tobruk Rd",
    "sg:city":"Narellan Vale",
    "sg:classifiers":[
        {
            "category":"Food & Beverages",
            "subcategory":"Specialty",
            "type":"Retail Goods"
        }
    ],
    "sg:phone":"+61 2 4647 8979",
    "sg:postcode":"2567",
    "sg:province":"NSW",
    "sg:tags":[
        "product",
        "health"
    ],
    "wof:name":"Herbalife Australasia Pty Ltd",
    "wof:placetype":"venue"
},
  "geometry": {"coordinates":[150.749603272,-34.0438690186],"type":"Point"}
}