{
  "type": "Feature",
  "properties": {
    "addr:full":"984 Main North East Rd Modbury SA 5092",
    "addr:housenumber":"984",
    "addr:postcode":"5092",
    "addr:street":"Main North East Rd",
    "iso:country":"AU",
    "sg:address":"984 Main North East Rd",
    "sg:city":"Modbury",
    "sg:classifiers":[
        {
            "category":"Shopping",
            "subcategory":"Clothing, Apparel, & Fashions",
            "type":"Retail Goods"
        }
    ],
    "sg:phone":"+61 8 8396 5022",
    "sg:postcode":"5092",
    "sg:province":"SA",
    "sg:tags":[
        "lady",
        "wear"
    ],
    "wof:name":"Sussan Corporation Australia Ltd",
    "wof:placetype":"venue"
},
  "geometry": {"coordinates":[138.68934631400001,-34.8309783936],"type":"Point"}
}