{
  "type": "Feature",
  "properties": {
    "addr:full":"74 Newcastle St Fyshwick ACT 2609",
    "addr:housenumber":"74",
    "addr:postcode":"2609",
    "addr:street":"Newcastle St",
    "iso:country":"AU",
    "sg:address":"74 Newcastle St",
    "sg:city":"Fyshwick",
    "sg:classifiers":[
        {
            "category":"Building & Trades",
            "subcategory":"Construction",
            "type":"Services"
        }
    ],
    "sg:phone":"+61 2 6228 1193",
    "sg:postcode":"2609",
    "sg:province":"ACT",
    "sg:tags":[
        "home",
        "air conditioning"
    ],
    "wof:name":"AAA Air Conditioning",
    "wof:placetype":"venue"
},
  "geometry": {"coordinates":[149.178390503,-35.3299446106],"type":"Point"}
}