{
  "type": "Feature",
  "properties": {
    "addr:full":"5 Heath St Sandringham VIC 3191",
    "addr:housenumber":"5",
    "addr:postcode":"3191",
    "addr:street":"Heath St",
    "iso:country":"AU",
    "sg:address":"5 Heath St",
    "sg:city":"Sandringham",
    "sg:classifiers":[
        {
            "category":"Health Services",
            "subcategory":"Nursing And Care Facility",
            "type":"Services"
        }
    ],
    "sg:phone":"+61 3 9521 0896",
    "sg:postcode":"3191",
    "sg:province":"VIC",
    "sg:tags":[
        "home"
    ],
    "wof:name":"St Benedicts Aged Care Facility",
    "wof:placetype":"venue"
},
  "geometry": {"coordinates":[145.013427734,-37.9539108276],"type":"Point"}
}