{
  "type": "Feature",
  "properties": {
    "addr:full":"Lismore Rd Camperdown VIC 3260",
    "addr:postcode":"3260",
    "addr:street":"Lismore Rd",
    "iso:country":"AU",
    "sg:address":"Lismore Rd",
    "sg:city":"Camperdown",
    "sg:classifiers":[
        {
            "category":"Arena",
            "subcategory":"Sports Club",
            "type":"Entertainment"
        }
    ],
    "sg:phone":"+61 3 5593 2151",
    "sg:postcode":"3260",
    "sg:province":"VIC",
    "sg:tags":[
        "hunt",
        "racing"
    ],
    "wof:name":"Camperdown Turf Club",
    "wof:placetype":"venue"
},
  "geometry": {"coordinates":[143.14210510300001,-38.2296600342],"type":"Point"}
}