{
  "type": "Feature",
  "properties": {
    "addr:full":"478 Goodwood Rd Cumberland Park SA 5041",
    "addr:housenumber":"478",
    "addr:postcode":"5041",
    "addr:street":"Goodwood Rd",
    "iso:country":"AU",
    "sg:address":"478 Goodwood Rd",
    "sg:city":"Cumberland Park",
    "sg:classifiers":[
        {
            "category":"Health Services",
            "subcategory":"Health Practitioner",
            "type":"Services"
        }
    ],
    "sg:phone":"+61 8 8272 1820",
    "sg:postcode":"5041",
    "sg:province":"SA",
    "sg:tags":[
        "naturopath"
    ],
    "wof:name":"Om Ayush Holistic Health Centre",
    "wof:placetype":"venue"
},
  "geometry": {"coordinates":[138.591354,-34.975384],"type":"Point"}
}