{
  "type": "Feature",
  "properties": {
    "iso:country":"AU",
    "sg:address":"3/31- 33 Argyle St",
    "sg:city":"Camden",
    "sg:classifiers":[
        {
            "category":"Real Estate",
            "subcategory":"Real Estate Agent",
            "type":"Services"
        }
    ],
    "sg:phone":"+61 2 4655 3000",
    "sg:postcode":"2570",
    "sg:province":"NSW",
    "wof:name":"Elders Real Estate",
    "wof:placetype":"venue"
},
  "geometry": {"coordinates":[150.69813537600001,-34.0533981323],"type":"Point"}
}