{
  "type": "Feature",
  "properties": {
    "addr:full":"7, 35 High St Caringbah NSW 2229",
    "addr:housenumber":"35",
    "addr:postcode":"2229",
    "addr:street":"7;High St",
    "iso:country":"AU",
    "sg:address":"7, 35 High St",
    "sg:city":"Caringbah",
    "sg:classifiers":[
        {
            "category":"Home & Garden",
            "subcategory":"Building Materials",
            "type":"Retail Goods"
        }
    ],
    "sg:phone":"+61 423 300 208",
    "sg:postcode":"2229",
    "sg:province":"NSW",
    "sg:tags":[
        "tile",
        "roofing"
    ],
    "wof:name":"Racell Roof Tiling",
    "wof:placetype":"venue"
},
  "geometry": {"coordinates":[151.116912842,-34.0453987122],"type":"Point"}
}