{
  "type": "Feature",
  "properties": {
    "addr:full":"2/ 12 Harvey St North Eagle Farm QLD 4009",
    "addr:housenumber":"/ 12",
    "addr:postcode":"4009",
    "addr:street":"Harvey St North",
    "iso:country":"AU",
    "sg:address":"2/ 12 Harvey St North",
    "sg:city":"Eagle Farm",
    "sg:classifiers":[
        {
            "category":"Manufacturing",
            "subcategory":"Metals",
            "type":"Manufacturing & Wholesale Goods"
        }
    ],
    "sg:phone":"+61 7 3216 4377",
    "sg:postcode":"4009",
    "sg:province":"QLD",
    "sg:tags":[
        "fabricator",
        "aluminium"
    ],
    "wof:name":"Abra-Ca-Dabra Products",
    "wof:placetype":"venue"
},
  "geometry": {"coordinates":[153.09135437,-27.4309844971],"type":"Point"}
}