{
  "type": "Feature",
  "properties": {
    "iso:country":"AU",
    "sg:address":"80 Rusden St",
    "sg:city":"Armidale",
    "sg:classifiers":[
        {
            "category":"Food & Beverages",
            "subcategory":"Groceries & Convenience Stores",
            "type":"Retail Goods"
        }
    ],
    "sg:phone":"+61 2 6772 4224",
    "sg:postcode":"2350",
    "sg:province":"NSW",
    "wof:name":"B B's Corner Store",
    "wof:placetype":"venue"
},
  "geometry": {"coordinates":[151.67129516599999,-30.5163459778],"type":"Point"}
}