{
  "type": "Feature",
  "properties": {
    "addr:full":"Unit 11, 33 Nyrang St Lidcombe NSW 2141",
    "addr:housenumber":"33",
    "addr:postcode":"2141",
    "addr:street":"Nyrang St",
    "iso:country":"AU",
    "sg:address":"Unit 11, 33 Nyrang St",
    "sg:city":"Lidcombe",
    "sg:classifiers":[
        {
            "category":"Wholesale",
            "subcategory":"Painting Supplies",
            "type":"Manufacturing & Wholesale Goods"
        }
    ],
    "sg:phone":"+61 2 9648 6955",
    "sg:postcode":"2141",
    "sg:province":"NSW",
    "sg:tags":[
        "equipment",
        "spraying"
    ],
    "wof:name":"Dearie R.L. Pty Ltd",
    "wof:placetype":"venue"
},
  "geometry": {"coordinates":[151.04768371599999,-33.8484725952],"type":"Point"}
}