{
  "type": "Feature",
  "properties": {
    "addr:full":"9 Balaclava St Woolloongabba QLD 4102",
    "addr:housenumber":"9",
    "addr:postcode":"4102",
    "addr:street":"Balaclava St",
    "iso:country":"AU",
    "sg:address":"9 Balaclava St",
    "sg:city":"Woolloongabba",
    "sg:classifiers":[
        {
            "category":"Retail",
            "subcategory":"Auto Repair",
            "type":"Services"
        }
    ],
    "sg:phone":"+61 7 3391 1447",
    "sg:postcode":"4102",
    "sg:province":"QLD",
    "sg:tags":[
        "repairer",
        "motor",
        "engineer"
    ],
    "wof:name":"Action Transmissions",
    "wof:placetype":"venue"
},
  "geometry": {"coordinates":[153.03660583499999,-27.4901790619],"type":"Point"}
}