{
  "type": "Feature",
  "properties": {
    "addr:full":"74 Shirley Pl Kings Meadows TAS 7249",
    "addr:housenumber":"74",
    "addr:postcode":"7249",
    "addr:street":"Shirley Pl",
    "iso:country":"AU",
    "sg:address":"74 Shirley Pl",
    "sg:city":"Kings Meadows",
    "sg:classifiers":[
        {
            "category":"Building & Trades",
            "subcategory":"Construction",
            "type":"Services"
        }
    ],
    "sg:phone":"+61 3 6343 4477",
    "sg:postcode":"7249",
    "sg:province":"TAS",
    "sg:tags":[
        "home",
        "air conditioning"
    ],
    "wof:name":"Quon & Co Pty Ltd",
    "wof:placetype":"venue"
},
  "geometry": {"coordinates":[147.160247803,-41.4681968689],"type":"Point"}
}