{
  "type": "Feature",
  "properties": {
    "addr:full":"185 Bridge Rd Richmond VIC 3121",
    "addr:housenumber":"185",
    "addr:postcode":"3121",
    "addr:street":"Bridge Rd",
    "iso:country":"AU",
    "sg:address":"185 Bridge Rd",
    "sg:city":"Richmond",
    "sg:classifiers":[
        {
            "category":"Shopping",
            "subcategory":"Clothing, Apparel, & Fashions",
            "type":"Retail Goods"
        }
    ],
    "sg:phone":"+61 3 9427 1674",
    "sg:postcode":"3121",
    "sg:province":"VIC",
    "sg:tags":[
        "menswear"
    ],
    "wof:name":"Broadway Design",
    "wof:placetype":"venue"
},
  "geometry": {"coordinates":[144.99595642099999,-37.8180809021],"type":"Point"}
}