{
  "type": "Feature",
  "properties": {
    "addr:full":"Cnr Maryborough & George Sts Bundaberg QLD 4670",
    "addr:postcode":"4670",
    "addr:street":"Cnr",
    "iso:country":"AU",
    "sg:address":"Cnr Maryborough & George Sts",
    "sg:city":"Bundaberg",
    "sg:classifiers":[
        {
            "category":"Food & Beverages",
            "subcategory":"Supermarket",
            "type":"Retail Goods"
        }
    ],
    "sg:phone":"+61 7 4153 1055",
    "sg:postcode":"4670",
    "sg:province":"QLD",
    "sg:tags":[
        "grocery",
        "store"
    ],
    "wof:name":"Woolworths Limited",
    "wof:placetype":"venue"
},
  "geometry": {"coordinates":[152.34671020499999,-24.8670425415],"type":"Point"}
}