{
  "type": "Feature",
  "properties": {
    "addr:full":"60 Newlands Rd Coburg North VIC 3058",
    "addr:housenumber":"60",
    "addr:postcode":"3058",
    "addr:street":"Newlands Rd",
    "iso:country":"AU",
    "sg:address":"60 Newlands Rd",
    "sg:city":"Coburg North",
    "sg:classifiers":[
        {
            "category":"Personal",
            "subcategory":"Beauty Salon",
            "type":"Services"
        }
    ],
    "sg:phone":"+61 3 9355 7759",
    "sg:postcode":"3058",
    "sg:province":"VIC",
    "sg:tags":[
        "hairdresser"
    ],
    "wof:name":"Hair Smart Studio",
    "wof:placetype":"venue"
},
  "geometry": {"coordinates":[144.978027344,-37.7205200195],"type":"Point"}
}