{
  "type": "Feature",
  "properties": {
    "addr:full":"Shop 2 8th Ave Palm Beach QLD 4221",
    "addr:housenumber":"shop 2",
    "addr:postcode":"4221",
    "addr:street":"8Th Ave",
    "iso:country":"AU",
    "sg:address":"Shop 2 8th Ave",
    "sg:city":"Palm Beach",
    "sg:classifiers":[
        {
            "category":"Professional",
            "subcategory":"Accounting & Tax Preparation",
            "type":"Services"
        }
    ],
    "sg:phone":"+61 7 5598 1118",
    "sg:postcode":"4221",
    "sg:province":"QLD",
    "sg:tags":[
        "accountant",
        "auditor"
    ],
    "sg:website":"http://www.byrneandmiller.com.au",
    "wof:name":"Byrne & Miller",
    "wof:placetype":"venue"
},
  "geometry": {"coordinates":[153.47093200699999,-28.1186466217],"type":"Point"}
}