{
  "type": "Feature",
  "properties": {
    "iso:country":"AU",
    "sg:address":"63 Wilga St",
    "sg:city":"Coonamble",
    "sg:classifiers":[
        {
            "category":"Home & Garden",
            "subcategory":"Building Materials",
            "type":"Retail Goods"
        }
    ],
    "sg:phone":"+61 2 6822 2206",
    "sg:postcode":"2829",
    "sg:province":"NSW",
    "sg:tags":[
        "pre-mixed",
        "concrete"
    ],
    "wof:name":"Coonamble Concrete",
    "wof:placetype":"venue"
},
  "geometry": {"coordinates":[148.38200378400001,-30.9620990753],"type":"Point"}
}