{
  "type": "Feature",
  "properties": {
    "addr:full":"1 Bruce St Glendale NSW 2285",
    "addr:housenumber":"1",
    "addr:postcode":"2285",
    "addr:street":"Bruce St",
    "iso:country":"AU",
    "sg:address":"1 Bruce St",
    "sg:city":"Glendale",
    "sg:classifiers":[
        {
            "category":"Professional",
            "subcategory":"Business Services",
            "type":"Services"
        }
    ],
    "sg:phone":"+61 2 4956 5444",
    "sg:postcode":"2285",
    "sg:province":"NSW",
    "sg:tags":[
        "drafting"
    ],
    "wof:name":"Glendale Building Designers",
    "wof:placetype":"venue"
},
  "geometry": {"coordinates":[151.652053833,-32.9289131165],"type":"Point"}
}