{
  "type": "Feature",
  "properties": {
    "addr:full":"221 Crowther Drv Kundabung NSW 2441",
    "addr:housenumber":"221",
    "addr:postcode":"2441",
    "addr:street":"Crowther Drv",
    "iso:country":"AU",
    "sg:address":"221 Crowther Drv",
    "sg:city":"Kundabung",
    "sg:classifiers":[
        {
            "category":"Education",
            "subcategory":"Dance Studio",
            "type":"Public Place"
        }
    ],
    "sg:phone":"+61 427 117 176",
    "sg:postcode":"2441",
    "sg:province":"NSW",
    "sg:tags":[
        "venue",
        "tuition"
    ],
    "wof:name":"Rosyln West Ballroom Dance Studio",
    "wof:placetype":"venue"
},
  "geometry": {"coordinates":[152.802246,-31.210457],"type":"Point"}
}