{
  "type": "Feature",
  "properties": {
    "addr:full":"135 Byrnes Rd Wagga Wagga NSW 2650",
    "addr:housenumber":"135",
    "addr:postcode":"2650",
    "addr:street":"Byrnes Rd",
    "iso:country":"AU",
    "sg:address":"135 Byrnes Rd",
    "sg:city":"Wagga Wagga",
    "sg:classifiers":[
        {
            "category":"Building & Trades",
            "subcategory":"Plumbing",
            "type":"Services"
        }
    ],
    "sg:phone":"+61 418 693 146",
    "sg:postcode":"2650",
    "sg:province":"NSW",
    "sg:tags":[
        "plumber",
        "gasfitters"
    ],
    "wof:name":"Sydenham Plumbing",
    "wof:placetype":"venue"
},
  "geometry": {"coordinates":[147.405197144,-35.0866241455],"type":"Point"}
}