{
  "type": "Feature",
  "properties": {
    "addr:full":"442 Nicholson St Fitzroy North VIC 3068",
    "addr:housenumber":"442",
    "addr:postcode":"3068",
    "addr:street":"Nicholson St",
    "iso:country":"AU",
    "sg:address":"442 Nicholson St",
    "sg:city":"Fitzroy North",
    "sg:classifiers":[
        {
            "category":"Travel",
            "subcategory":"Hotels & Motels",
            "type":"Entertainment"
        }
    ],
    "sg:phone":"+61 3 9481 4693",
    "sg:postcode":"3068",
    "sg:province":"VIC",
    "sg:tags":[
        "accommodation"
    ],
    "wof:name":"Royal Oak Hotel",
    "wof:placetype":"venue"
},
  "geometry": {"coordinates":[144.976654053,-37.7894592285],"type":"Point"}
}