{
  "type": "Feature",
  "properties": {
    "addr:full":"Fact 2 27 Melverton Drv Hallam VIC 3803",
    "addr:housenumber":"2 27",
    "addr:postcode":"3803",
    "addr:street":"Fact;Melverton Drv",
    "iso:country":"AU",
    "sg:address":"Fact 2 27 Melverton Drv",
    "sg:city":"Hallam",
    "sg:classifiers":[
        {
            "category":"Manufacturing",
            "subcategory":"Metals",
            "type":"Manufacturing & Wholesale Goods"
        }
    ],
    "sg:phone":"+61 3 9796 4690",
    "sg:postcode":"3803",
    "sg:province":"VIC",
    "sg:tags":[
        "sheet",
        "worker"
    ],
    "wof:name":"McKenzie Thompson",
    "wof:placetype":"venue"
},
  "geometry": {"coordinates":[145.27508544899999,-38.010055542],"type":"Point"}
}