{
  "type": "Feature",
  "properties": {
    "addr:full":"540 Brighton Rd Brighton SA 5048",
    "addr:housenumber":"540",
    "addr:postcode":"5048",
    "addr:street":"Brighton Rd",
    "iso:country":"AU",
    "sg:address":"540 Brighton Rd",
    "sg:city":"Brighton",
    "sg:classifiers":[
        {
            "category":"Health Services",
            "subcategory":"Doctor",
            "type":"Services"
        }
    ],
    "sg:phone":"+61 8 8296 5844",
    "sg:postcode":"5048",
    "sg:province":"SA",
    "sg:tags":[
        "medical",
        "practitioner"
    ],
    "wof:name":"Johns Richard L",
    "wof:placetype":"venue"
},
  "geometry": {"coordinates":[138.52330000000001,-35.023079],"type":"Point"}
}