{
  "type": "Feature",
  "properties": {
    "iso:country":"AU",
    "sg:address":"540 Brighton Rd",
    "sg:city":"Brighton",
    "sg:classifiers":[
        {
            "category":"Health Services",
            "subcategory":"Doctor",
            "type":"Services"
        }
    ],
    "sg:phone":"+61 8 8296 5844",
    "sg:postcode":"5048",
    "sg:province":"SA",
    "sg:tags":[
        "medical",
        "practitioner"
    ],
    "wof:name":"Johns Richard L",
    "wof:placetype":"venue"
},
  "geometry": {"coordinates":[138.5233,-35.023079],"type":"Point"}
}