{
  "type": "Feature",
  "properties": {
    "addr:full":"40 Johnston St Newport VIC 3015",
    "addr:housenumber":"40",
    "addr:postcode":"3015",
    "addr:street":"Johnston St",
    "iso:country":"AU",
    "sg:address":"40 Johnston St",
    "sg:city":"Newport",
    "sg:classifiers":[
        {
            "category":"Retail",
            "subcategory":"Repair Shop",
            "type":"Services"
        }
    ],
    "sg:phone":"+61 3 9391 7798",
    "sg:postcode":"3015",
    "sg:province":"VIC",
    "sg:tags":[
        "upholsterer"
    ],
    "wof:name":"Suite Comfort Furniture Upholstery",
    "wof:placetype":"venue"
},
  "geometry": {"coordinates":[144.87535095199999,-37.8390274048],"type":"Point"}
}