{
  "type": "Feature",
  "properties": {
    "iso:country":"AU",
    "sg:address":"206 Phillip St",
    "sg:city":"(East) Mt Pleasant",
    "sg:classifiers":[
        {
            "category":"Social Services",
            "subcategory":"Retirement Home",
            "type":"Services"
        }
    ],
    "sg:phone":"+61 7 4942 2522",
    "sg:postcode":"4740",
    "sg:province":"QLD",
    "sg:tags":[
        "village"
    ],
    "sg:website":"http://www.gfe.net.au",
    "wof:name":"Carlyle Gardens",
    "wof:placetype":"venue"
},
  "geometry": {"coordinates":[149.157928,-21.117462],"type":"Point"}
}