{
  "type": "Feature",
  "properties": {
    "iso:country":"AU",
    "sg:address":"4 Guilfoyle Ave",
    "sg:city":"Double Bay",
    "sg:classifiers":[
        {
            "category":"Personal",
            "type":"Services"
        }
    ],
    "sg:phone":"+61 2 9362 4737",
    "sg:postcode":"2028",
    "sg:province":"NSW",
    "sg:tags":[
        "dressmaker"
    ],
    "wof:name":"Angelina Dressmaker",
    "wof:placetype":"venue"
},
  "geometry": {"coordinates":[151.241333008,-33.8766784668],"type":"Point"}
}