{
  "type": "Feature",
  "properties": {
    "addr:full":"3/ 10 West Pde West Ryde NSW 2114",
    "addr:housenumber":"/ 10",
    "addr:postcode":"2114",
    "addr:street":"West Pde",
    "iso:country":"AU",
    "sg:address":"3/ 10 West Pde",
    "sg:city":"West Ryde",
    "sg:classifiers":[
        {
            "category":"Home & Garden",
            "subcategory":"Garden Supply",
            "type":"Retail Goods"
        }
    ],
    "sg:phone":"+61 2 4578 6622",
    "sg:postcode":"2114",
    "sg:province":"NSW",
    "sg:tags":[
        "turf",
        "lawn"
    ],
    "wof:name":"Qualturf Pty. Ltd.",
    "wof:placetype":"venue"
},
  "geometry": {"coordinates":[151.08883667000001,-33.8073577881],"type":"Point"}
}