{
  "type": "Feature",
  "properties": {
    "addr:full":"Level 28 / 303 Collins St Melbourne VIC 3000",
    "addr:housenumber":"/ 303",
    "addr:postcode":"3000",
    "addr:street":"Collins St",
    "iso:country":"AU",
    "sg:address":"Level 28 / 303 Collins St",
    "sg:city":"Melbourne",
    "sg:classifiers":[
        {
            "category":"Education",
            "subcategory":"Special Training",
            "type":"Public Place"
        }
    ],
    "sg:phone":"+61 3 9678 9068",
    "sg:postcode":"3000",
    "sg:province":"VIC",
    "sg:tags":[
        "development",
        "computer/it"
    ],
    "wof:name":"SE101 Pty Ltd",
    "wof:placetype":"venue"
},
  "geometry": {"coordinates":[144.963989258,-37.816368103],"type":"Point"}
}