{
  "type": "Feature",
  "properties": {
    "addr:full":"Hinkler Place Shopping Centre Maryborough St Bundaberg QLD 4670",
    "addr:postcode":"4670",
    "addr:street":"Hinkler;St",
    "iso:country":"AU",
    "sg:address":"Hinkler Place Shopping Centre Maryborough St",
    "sg:city":"Bundaberg",
    "sg:classifiers":[
        {
            "category":"Health Services",
            "subcategory":"Doctor",
            "type":"Services"
        }
    ],
    "sg:phone":"+61 7 4153 2927",
    "sg:postcode":"4670",
    "sg:province":"QLD",
    "sg:tags":[
        "medical",
        "practitioner"
    ],
    "wof:name":"The Family Practice At Hinkler Place",
    "wof:placetype":"venue"
},
  "geometry": {"coordinates":[152.34671020499999,-24.8670425415],"type":"Point"}
}