{
  "type": "Feature",
  "properties": {
    "addr:full":"U3, Sinnott Crs Camperdown VIC 3260",
    "addr:postcode":"3260",
    "addr:street":"Sinnott Crs",
    "iso:country":"AU",
    "sg:address":"U3, Sinnott Crs",
    "sg:city":"Camperdown",
    "sg:classifiers":[
        {
            "category":"Retail",
            "subcategory":"Auto Repair",
            "type":"Services"
        }
    ],
    "sg:phone":"+61 3 5593 2922",
    "sg:postcode":"3260",
    "sg:province":"VIC",
    "sg:tags":[
        "beater",
        "painter",
        "panel"
    ],
    "wof:name":"Sinclair Panels",
    "wof:placetype":"venue"
},
  "geometry": {"coordinates":[143.14210510300001,-38.2296600342],"type":"Point"}
}