{
  "type": "Feature",
  "properties": {
    "addr:full":"583 Robinson Rd Borroloola NT 0854",
    "addr:housenumber":"583",
    "addr:postcode":"nt 0854",
    "addr:street":"Robinson Rd",
    "iso:country":"AU",
    "sg:address":"583 Robinson Rd",
    "sg:city":"Borroloola",
    "sg:classifiers":[
        {
            "category":"Home & Garden",
            "subcategory":"Building Materials",
            "type":"Retail Goods"
        }
    ],
    "sg:phone":"+61 8 8975 8774",
    "sg:postcode":"0854",
    "sg:province":"NT",
    "sg:tags":[
        "supply"
    ],
    "wof:name":"Gulf Industrial & Building Supplies",
    "wof:placetype":"venue"
},
  "geometry": {"coordinates":[136.30676299999999,-16.063631],"type":"Point"}
}