{
  "type": "Feature",
  "properties": {
    "addr:full":"1 Bogan St Breakfast Creek QLD 4010",
    "addr:housenumber":"1",
    "addr:postcode":"4010",
    "addr:street":"Bogan St",
    "iso:country":"AU",
    "sg:address":"1 Bogan St",
    "sg:city":"Breakfast Creek",
    "sg:classifiers":[
        {
            "category":"Retail",
            "subcategory":"Event Space",
            "type":"Services"
        }
    ],
    "sg:phone":"+61 7 3292 3155",
    "sg:postcode":"4010",
    "sg:province":"QLD",
    "sg:tags":[
        "venue",
        "reception",
        "wedding"
    ],
    "wof:name":"The Pavilion Function & Conference Centre",
    "wof:placetype":"venue"
},
  "geometry": {"coordinates":[153.044754028,-27.4358177185],"type":"Point"}
}