{
  "type": "Feature",
  "properties": {
    "addr:full":"Eyre St Chifley NSW 2036",
    "addr:postcode":"2036",
    "addr:street":"Eyre St",
    "iso:country":"AU",
    "sg:address":"Eyre St",
    "sg:city":"Chifley",
    "sg:classifiers":[
        {
            "category":"Building & Trades",
            "subcategory":"Construction",
            "type":"Services"
        }
    ],
    "sg:phone":"+61 2 9661 9666",
    "sg:postcode":"2036",
    "sg:province":"NSW",
    "sg:tags":[
        "concrete",
        "contractor"
    ],
    "wof:name":"J.B. Concreting",
    "wof:placetype":"venue"
},
  "geometry": {"coordinates":[151.24114990199999,-33.9661216736],"type":"Point"}
}