{
  "type": "Feature",
  "properties": {
    "iso:country":"AU",
    "sg:address":"Sunshine Ave",
    "sg:city":"Kealba",
    "sg:classifiers":[
        {
            "category":"Fast Food",
            "type":"Food & Drink"
        }
    ],
    "sg:phone":"+61 3 9364 3000",
    "sg:postcode":"3021",
    "sg:province":"VIC",
    "sg:tags":[
        "away",
        "take"
    ],
    "wof:name":"My Mate's Pizza & Pasta",
    "wof:placetype":"venue"
},
  "geometry": {"coordinates":[144.81572,-37.730064],"type":"Point"}
}