{
  "type": "Feature",
  "properties": {
    "addr:full":"1c Barker Ave Como WA 6152",
    "addr:housenumber":"1c",
    "addr:postcode":"6152",
    "addr:street":"Barker Ave",
    "iso:country":"AU",
    "sg:address":"1c Barker Ave",
    "sg:city":"Como",
    "sg:classifiers":[
        {
            "category":"Fast Food",
            "type":"Food & Drink"
        }
    ],
    "sg:phone":"+61 8 9450 2058",
    "sg:postcode":"6152",
    "sg:province":"WA",
    "sg:tags":[
        "away",
        "take"
    ],
    "wof:name":"Johnny's Quality Fish Bar",
    "wof:placetype":"venue"
},
  "geometry": {"coordinates":[115.864662,-31.996878],"type":"Point"}
}