{
  "type": "Feature",
  "properties": {
    "iso:country":"AU",
    "sg:address":"27 Cocoparra Crs",
    "sg:city":"Taylors Lakes",
    "sg:classifiers":[
        {
            "category":"Personal",
            "subcategory":"Beauty Salon",
            "type":"Services"
        }
    ],
    "sg:phone":"+61 412 098 251",
    "sg:postcode":"3038",
    "sg:province":"VIC",
    "sg:tags":[
        "hairdresser"
    ],
    "wof:name":"Keen Cutters",
    "wof:placetype":"venue"
},
  "geometry": {"coordinates":[144.781326,-37.696911],"type":"Point"}
}