{
  "type": "Feature",
  "properties": {
    "addr:full":"19 Emu Bay Rd Deloraine TAS 7304",
    "addr:housenumber":"19",
    "addr:postcode":"7304",
    "addr:street":"Emu Bay Rd",
    "iso:country":"AU",
    "sg:address":"19 Emu Bay Rd",
    "sg:city":"Deloraine",
    "sg:classifiers":[
        {
            "category":"Travel",
            "subcategory":"Hotels & Motels",
            "type":"Entertainment"
        }
    ],
    "sg:phone":"+61 3 6362 2075",
    "sg:postcode":"7304",
    "sg:province":"TAS",
    "sg:tags":[
        "accommodation"
    ],
    "wof:name":"Empire Hotel And Brasserie",
    "wof:placetype":"venue"
},
  "geometry": {"coordinates":[146.65623500000001,-41.524937],"type":"Point"}
}