{
  "type": "Feature",
  "properties": {
    "addr:full":"75 Boyd St Bathurst NSW 2795",
    "addr:housenumber":"75",
    "addr:postcode":"2795",
    "addr:street":"Boyd St",
    "iso:country":"AU",
    "sg:address":"75 Boyd St",
    "sg:city":"Bathurst",
    "sg:classifiers":[
        {
            "category":"Professional",
            "subcategory":"Accounting & Tax Preparation",
            "type":"Services"
        }
    ],
    "sg:phone":"+61 2 6331 3798",
    "sg:postcode":"2795",
    "sg:province":"NSW",
    "sg:tags":[
        "deduction",
        "payroll"
    ],
    "wof:name":"Payroll Preparations Central West",
    "wof:placetype":"venue"
},
  "geometry": {"coordinates":[149.61346435600001,-33.4131698608],"type":"Point"}
}