{
  "type": "Feature",
  "properties": {
    "addr:full":"76 Junction Rd Schofields NSW 2762",
    "addr:housenumber":"76",
    "addr:postcode":"2762",
    "addr:street":"Junction Rd",
    "iso:country":"AU",
    "sg:address":"76 Junction Rd",
    "sg:city":"Schofields",
    "sg:classifiers":[
        {
            "category":"Building & Trades",
            "subcategory":"Construction",
            "type":"Services"
        }
    ],
    "sg:phone":"+61 2 9627 2432",
    "sg:postcode":"2762",
    "sg:province":"NSW",
    "sg:tags":[
        "joinery"
    ],
    "wof:name":"M J A Kitchen Doors",
    "wof:placetype":"venue"
},
  "geometry": {"coordinates":[150.879394531,-33.6983337402],"type":"Point"}
}