{
  "type": "Feature",
  "properties": {
    "iso:country":"AU",
    "sg:address":"PO Box 859",
    "sg:city":"Rozelle",
    "sg:classifiers":[
        {
            "category":"Professional",
            "subcategory":"Art Services",
            "type":"Services"
        }
    ],
    "sg:phone":"+61 411 052 522",
    "sg:postcode":"2039",
    "sg:province":"NSW",
    "sg:tags":[
        "graphic",
        "designer"
    ],
    "wof:name":"Quiddity Creative",
    "wof:placetype":"venue"
},
  "geometry": {"coordinates":[151.17036438,-33.8634414673],"type":"Point"}
}