{
  "type": "Feature",
  "properties": {
    "iso:country":"AU",
    "sg:address":"PO Box 177",
    "sg:city":"Collaroy Beach",
    "sg:classifiers":[
        {
            "category":"Utilities",
            "subcategory":"Sewage",
            "type":"Services"
        }
    ],
    "sg:phone":"+61 409 320 840",
    "sg:postcode":"2097",
    "sg:province":"NSW",
    "sg:tags":[
        "arboriculturist"
    ],
    "wof:name":"Intensive Tree Care Service",
    "wof:placetype":"venue"
},
  "geometry": {"coordinates":[151.301223755,-33.7321205139],"type":"Point"}
}