{
  "type": "Feature",
  "properties": {
    "addr:full":"Shop 4, 132 Beerburrum St Aroona QLD 4551",
    "addr:housenumber":"shop 4",
    "addr:postcode":"132;4551",
    "addr:street":"Beerburrum St",
    "iso:country":"AU",
    "sg:address":"Shop 4, 132 Beerburrum St",
    "sg:city":"Aroona",
    "sg:classifiers":[
        {
            "category":"Personal",
            "subcategory":"Tanning Parlor",
            "type":"Services"
        }
    ],
    "sg:phone":"+61 7 5492 6633",
    "sg:postcode":"4551",
    "sg:province":"QLD",
    "sg:tags":[
        "solarium"
    ],
    "wof:name":"Allure Body Lounge",
    "wof:placetype":"venue"
},
  "geometry": {"coordinates":[153.12010192899999,-26.7798137665],"type":"Point"}
}