{
  "type": "Feature",
  "properties": {
    "iso:country":"AU",
    "sg:address":"7 Yuille St",
    "sg:city":"Melton",
    "sg:classifiers":[
        {
            "category":"Retail",
            "subcategory":"Auto Rental",
            "type":"Services"
        }
    ],
    "sg:phone":"+61 3 9743 0477",
    "sg:postcode":"3337",
    "sg:province":"VIC",
    "sg:tags":[
        "chauffeur",
        "car",
        "hire",
        "driven",
        "limousine"
    ],
    "wof:name":"Retro Classic Rides",
    "wof:placetype":"venue"
},
  "geometry": {"coordinates":[144.59065200000001,-37.679676],"type":"Point"}
}