{
  "type": "Feature",
  "properties": {
    "addr:full":"Cnr Glenelg Hwy & Parker St Dunkeld VIC 3294",
    "addr:postcode":"3294",
    "addr:street":"Cnr Glenelg Hwy &;St",
    "iso:country":"AU",
    "sg:address":"Cnr Glenelg Hwy & Parker St",
    "sg:city":"Dunkeld",
    "sg:classifiers":[
        {
            "category":"Autos & Motor Vehicles",
            "subcategory":"Fuel & Gas Station",
            "type":"Retail Goods"
        }
    ],
    "sg:phone":"+61 3 5577 2444",
    "sg:postcode":"3294",
    "sg:province":"VIC",
    "wof:name":"Robco Petroleum Distributors",
    "wof:placetype":"venue"
},
  "geometry": {"coordinates":[142.33839416500001,-37.6490249634],"type":"Point"}
}