{
  "type": "Feature",
  "properties": {
    "addr:full":"24 Railway Rd Meadowbank NSW 2114",
    "addr:housenumber":"24",
    "addr:postcode":"2114",
    "addr:street":"Railway Rd",
    "iso:country":"AU",
    "sg:address":"24 Railway Rd",
    "sg:city":"Meadowbank",
    "sg:classifiers":[
        {
            "category":"Professional",
            "subcategory":"Printing & Photocopies",
            "type":"Services"
        }
    ],
    "sg:phone":"+61 2 9808 3340",
    "sg:postcode":"2114",
    "sg:province":"NSW",
    "sg:tags":[
        "trophy"
    ],
    "wof:name":"O'Brien Engineering Pty Ltd",
    "wof:placetype":"venue"
},
  "geometry": {"coordinates":[151.08996582,-33.8175735474],"type":"Point"}
}