{
  "type": "Feature",
  "properties": {
    "addr:full":"49- 51 Richard Rd Rutherford NSW 2320",
    "addr:housenumber":"51",
    "addr:postcode":"2320",
    "addr:street":"Richard Rd",
    "iso:country":"AU",
    "sg:address":"49- 51 Richard Rd",
    "sg:city":"Rutherford",
    "sg:classifiers":[
        {
            "category":"Education",
            "subcategory":"Kindergarten",
            "type":"Public Place"
        }
    ],
    "sg:phone":"+61 2 4932 9022",
    "sg:postcode":"2320",
    "sg:province":"NSW",
    "sg:tags":[
        "pre-schools"
    ],
    "wof:name":"Little Legends Child Care Centre",
    "wof:placetype":"venue"
},
  "geometry": {"coordinates":[151.51710510300001,-32.7060585022],"type":"Point"}
}