{
  "type": "Feature",
  "properties": {
    "addr:full":"Pacific Hwy Tweed Heads NSW 2485",
    "addr:postcode":"2485",
    "addr:street":"Pacific Hwy",
    "iso:country":"AU",
    "sg:address":"Pacific Hwy",
    "sg:city":"Tweed Heads",
    "sg:classifiers":[
        {
            "category":"Farming",
            "subcategory":"Crops",
            "type":"Manufacturing & Wholesale Goods"
        }
    ],
    "sg:phone":"+61 7 5524 3561",
    "sg:postcode":"2485",
    "sg:province":"NSW",
    "sg:tags":[
        "club",
        "rowing"
    ],
    "wof:name":"Tweed Heads Rowing & Aquatic Club Ltd",
    "wof:placetype":"venue"
},
  "geometry": {"coordinates":[153.51756286599999,-28.1832504272],"type":"Point"}
}