{
  "type": "Feature",
  "properties": {
    "addr:full":"42 Oakbank Rd Otago TAS 7017",
    "addr:housenumber":"42",
    "addr:postcode":"7017",
    "addr:street":"Oakbank Rd",
    "iso:country":"AU",
    "sg:address":"42 Oakbank Rd",
    "sg:city":"Otago",
    "sg:classifiers":[
        {
            "category":"Arena",
            "subcategory":"Bull Ring",
            "type":"Entertainment"
        }
    ],
    "sg:phone":"+61 3 6272 9976",
    "sg:postcode":"7017",
    "sg:province":"TAS",
    "sg:tags":[
        "club",
        "bushwalking"
    ],
    "wof:name":"PANDANI BUSHWALKING CLUB",
    "wof:placetype":"venue"
},
  "geometry": {"coordinates":[147.26148986800001,-42.8287353516],"type":"Point"}
}