{
  "type": "Feature",
  "properties": {
    "addr:full":"Suite 2/ 40-42 John St Lidcombe NSW 2141",
    "addr:housenumber":"/ 40-42",
    "addr:postcode":"2141",
    "addr:street":"John St",
    "iso:country":"AU",
    "sg:address":"Suite 2/ 40-42 John St",
    "sg:city":"Lidcombe",
    "sg:classifiers":[
        {
            "category":"Travel",
            "subcategory":"Travel Agent",
            "type":"Entertainment"
        }
    ],
    "sg:phone":"+61 2 9749 4722",
    "sg:postcode":"2141",
    "sg:province":"NSW",
    "sg:tags":[
        "consultant"
    ],
    "wof:name":"A Universe Travel",
    "wof:placetype":"venue"
},
  "geometry": {"coordinates":[151.04478454599999,-33.8612518311],"type":"Point"}
}