{
  "type": "Feature",
  "properties": {
    "iso:country":"AU",
    "sg:address":"Level 3, Suite 303, 270 Pacific Hwy",
    "sg:city":"Crows Nest",
    "sg:classifiers":[
        {
            "category":"Banks & Credit Unions",
            "subcategory":"Investment Brokerage",
            "type":"Services"
        }
    ],
    "sg:phone":"+61 2 9438 4511",
    "sg:postcode":"2065",
    "sg:province":"NSW",
    "sg:tags":[
        "management",
        "property"
    ],
    "wof:name":"Laing + Simmons Residential Investment Services",
    "wof:placetype":"venue"
},
  "geometry": {"coordinates":[151.198852539,-33.8254547119],"type":"Point"}
}