{
  "type": "Feature",
  "properties": {
    "addr:full":"406 Bluff Rd Hampton VIC 3188",
    "addr:housenumber":"406",
    "addr:postcode":"3188",
    "addr:street":"Bluff Rd",
    "iso:country":"AU",
    "sg:address":"406 Bluff Rd",
    "sg:city":"Hampton",
    "sg:classifiers":[
        {
            "category":"Fast Food",
            "type":"Food & Drink"
        }
    ],
    "sg:phone":"+61 3 9553 3491",
    "sg:postcode":"3188",
    "sg:province":"VIC",
    "sg:tags":[
        "away",
        "take"
    ],
    "wof:name":"Hos Kitchen",
    "wof:placetype":"venue"
},
  "geometry": {"coordinates":[145.022384644,-37.9462165833],"type":"Point"}
}