{
  "type": "Feature",
  "properties": {
    "addr:full":"32 West Ave Cessnock NSW 2325",
    "addr:housenumber":"32",
    "addr:postcode":"2325",
    "addr:street":"West Ave",
    "iso:country":"AU",
    "sg:address":"32 West Ave",
    "sg:city":"Cessnock",
    "sg:classifiers":[
        {
            "category":"Health Services",
            "subcategory":"Doctor",
            "type":"Services"
        }
    ],
    "sg:phone":"+61 2 4990 1104",
    "sg:postcode":"2325",
    "sg:province":"NSW",
    "sg:tags":[
        "medical",
        "practitioner"
    ],
    "wof:name":"McQueen D A",
    "wof:placetype":"venue"
},
  "geometry": {"coordinates":[151.34962463400001,-32.8368377686],"type":"Point"}
}