{
  "type": "Feature",
  "properties": {
    "addr:full":"Shop 9 / 45 Francis St Northbridge WA 6003",
    "addr:housenumber":"shop 9 / 45",
    "addr:postcode":"6003",
    "addr:street":"Francis St",
    "iso:country":"AU",
    "sg:address":"Shop 9 / 45 Francis St",
    "sg:city":"Northbridge",
    "sg:classifiers":[
        {
            "category":"Professional",
            "subcategory":"Printing & Photocopies",
            "type":"Services"
        }
    ],
    "sg:phone":"+61 8 9228 1188",
    "sg:postcode":"6003",
    "sg:province":"WA",
    "sg:tags":[
        "rubber",
        "stamp",
        "metal"
    ],
    "sg:website":"http://www.whkcarricks.com.au",
    "wof:name":"Danny's Shoe Repairs",
    "wof:placetype":"venue"
},
  "geometry": {"coordinates":[115.859733581,-31.9480648041],"type":"Point"}
}