{
  "type": "Feature",
  "properties": {
    "iso:country":"AU",
    "sg:address":"Karalee Shopping Village Shop 3 Junction Rd",
    "sg:city":"Karalee",
    "sg:classifiers":[
        {
            "category":"Personal",
            "subcategory":"Beauty Salon",
            "type":"Services"
        }
    ],
    "sg:phone":"+61 7 3812 2928",
    "sg:postcode":"4306",
    "sg:province":"QLD",
    "sg:tags":[
        "hairdresser"
    ],
    "wof:name":"Karalee Hair Designs",
    "wof:placetype":"venue"
},
  "geometry": {"coordinates":[152.81101989699999,-27.5730686188],"type":"Point"}
}