{
  "type": "Feature",
  "properties": {
    "iso:country":"AU",
    "sg:address":"Suite 3, 1st Floor 13 Pulteney St",
    "sg:city":"Taree",
    "sg:classifiers":[
        {
            "category":"Manufacturing",
            "subcategory":"Jewelry",
            "type":"Manufacturing & Wholesale Goods"
        }
    ],
    "sg:phone":"+61 2 6551 2775",
    "sg:postcode":"2430",
    "sg:province":"NSW",
    "sg:tags":[
        "mfrg",
        "jeweller"
    ],
    "wof:name":"Rob Green Manufacturing Jeweller",
    "wof:placetype":"venue"
},
  "geometry": {"coordinates":[152.45933500000001,-31.91371],"type":"Point"}
}