{
  "type": "Feature",
  "properties": {
    "addr:full":"Shop8 Midway Arcade 974 Main Rd Eltham VIC 3095",
    "addr:housenumber":"974",
    "addr:postcode":"3095",
    "addr:street":"Main Rd",
    "iso:country":"AU",
    "sg:address":"Shop8 Midway Arcade 974 Main Rd",
    "sg:city":"Eltham",
    "sg:classifiers":[
        {
            "category":"Personal",
            "subcategory":"Beauty Salon",
            "type":"Services"
        }
    ],
    "sg:phone":"+61 3 9431 0744",
    "sg:postcode":"3095",
    "sg:province":"VIC",
    "wof:name":"Beauty Profile",
    "wof:placetype":"venue"
},
  "geometry": {"coordinates":[145.148803711,-37.7137260437],"type":"Point"}
}