{
  "type": "Feature",
  "properties": {
    "addr:full":"Yorketown Rd Craigmore SA 5114",
    "addr:postcode":"5114",
    "addr:street":"Yorketown Rd",
    "iso:country":"AU",
    "sg:address":"Yorketown Rd",
    "sg:city":"Craigmore",
    "sg:classifiers":[
        {
            "category":"Food & Beverages",
            "subcategory":"Liquor & Beverages",
            "type":"Retail Goods"
        }
    ],
    "sg:phone":"+61 8 8252 2959",
    "sg:postcode":"5114",
    "sg:province":"SA",
    "sg:tags":[
        "store"
    ],
    "wof:name":"Craigmore Cellars",
    "wof:placetype":"venue"
},
  "geometry": {"coordinates":[138.69366455100001,-34.7072143555],"type":"Point"}
}