{
  "type": "Feature",
  "properties": {
    "addr:full":"133 Scarborough Beach Rd Mt Hawthorn WA 6016",
    "addr:housenumber":"133",
    "addr:postcode":"6016",
    "addr:street":"Scarborough Beach Rd",
    "iso:country":"AU",
    "sg:address":"133 Scarborough Beach Rd",
    "sg:city":"Mt Hawthorn",
    "sg:classifiers":[
        {
            "category":"Airline",
            "type":"Transportation"
        }
    ],
    "sg:phone":"+61 8 9443 1511",
    "sg:postcode":"6016",
    "sg:province":"WA",
    "sg:tags":[
        "surveyor",
        "aerial"
    ],
    "sg:website":"http://www.whelans.com.au",
    "wof:name":"Whelans (WA) Pty Ltd",
    "wof:placetype":"venue"
},
  "geometry": {"coordinates":[115.840179443,-31.9221553802],"type":"Point"}
}