{
  "type": "Feature",
  "properties": {
    "addr:full":"31 Hesse St Queenscliff VIC 3225",
    "addr:housenumber":"31",
    "addr:postcode":"3225",
    "addr:street":"Hesse St",
    "iso:country":"AU",
    "sg:address":"31 Hesse St",
    "sg:city":"Queenscliff",
    "sg:classifiers":[
        {
            "category":"Organizations",
            "subcategory":"Community Association",
            "type":"Services"
        }
    ],
    "sg:phone":"+61 3 5258 2273",
    "sg:postcode":"3225",
    "sg:province":"VIC",
    "sg:tags":[
        "organisation",
        "family",
        "welfare"
    ],
    "wof:name":"St Vincent De Paul Society",
    "wof:placetype":"venue"
},
  "geometry": {"coordinates":[144.661957,-38.266239],"type":"Point"}
}