{
  "type": "Feature",
  "properties": {
    "iso:country":"AU",
    "sg:address":"3 Prescott Crs",
    "sg:city":"Industrial Park Gawler Belt",
    "sg:classifiers":[
        {
            "category":"Manufacturing",
            "subcategory":"Motor Vehicles & Parts",
            "type":"Manufacturing & Wholesale Goods"
        }
    ],
    "sg:phone":"+61 8 8522 5677",
    "sg:postcode":"5118",
    "sg:province":"SA",
    "sg:tags":[
        "replacement"
    ],
    "wof:name":"Gawler Auto Dismantlers",
    "wof:placetype":"venue"
},
  "geometry": {"coordinates":[138.735474,-34.574772],"type":"Point"}
}