{
  "type": "Feature",
  "properties": {
    "addr:full":"72 White St Tamworth NSW 2340",
    "addr:housenumber":"72",
    "addr:postcode":"2340",
    "addr:street":"White St",
    "iso:country":"AU",
    "sg:address":"72 White St",
    "sg:city":"Tamworth",
    "sg:classifiers":[
        {
            "category":"Building & Trades",
            "subcategory":"Construction",
            "type":"Services"
        }
    ],
    "sg:phone":"+61 2 6766 1189",
    "sg:postcode":"2340",
    "sg:province":"NSW",
    "sg:tags":[
        "concrete",
        "contractor"
    ],
    "wof:name":"Tufreys Concreting & Plastering",
    "wof:placetype":"venue"
},
  "geometry": {"coordinates":[150.94134521500001,-31.0870819092],"type":"Point"}
}