{
  "type": "Feature",
  "properties": {
    "addr:full":"277 Waterworks Rd Ashgrove QLD 4060",
    "addr:housenumber":"277",
    "addr:postcode":"4060",
    "addr:street":"Waterworks Rd",
    "iso:country":"AU",
    "sg:address":"277 Waterworks Rd",
    "sg:city":"Ashgrove",
    "sg:classifiers":[
        {
            "category":"Home & Garden",
            "subcategory":"Hardware",
            "type":"Retail Goods"
        }
    ],
    "sg:phone":"+61 7 3366 1677",
    "sg:postcode":"4060",
    "sg:province":"QLD",
    "sg:tags":[
        "plumber",
        "supply"
    ],
    "wof:name":"Bowman Water Solutions",
    "wof:placetype":"venue"
},
  "geometry": {"coordinates":[152.990356445,-27.4457511902],"type":"Point"}
}