{
  "type": "Feature",
  "properties": {
    "iso:country":"AU",
    "sg:address":"13 Heatherdale Rd",
    "sg:city":"Ringwood",
    "sg:classifiers":[
        {
            "category":"Shopping",
            "subcategory":"Stationery & Office Supplies",
            "type":"Retail Goods"
        }
    ],
    "sg:phone":"+61 3 9874 6828",
    "sg:postcode":"3134",
    "sg:province":"VIC",
    "sg:tags":[
        "equipment",
        "facsimile"
    ],
    "wof:name":"A Business World Communications",
    "wof:placetype":"venue"
},
  "geometry": {"coordinates":[145.21353149399999,-37.8191833496],"type":"Point"}
}