{
  "type": "Feature",
  "properties": {
    "addr:full":"Suite 3, Level 5, North Shore Private Hospital Wes Leonards NSW 2065",
    "addr:postcode":"2065",
    "addr:street":"Shore",
    "iso:country":"AU",
    "sg:address":"Suite 3, Level 5, North Shore Private Hospital Wes",
    "sg:city":"Leonards",
    "sg:classifiers":[
        {
            "category":"Health Services",
            "subcategory":"Doctor",
            "type":"Services"
        }
    ],
    "sg:phone":"+61 2 9966 4431",
    "sg:postcode":"2065",
    "sg:province":"NSW",
    "sg:tags":[
        "medical",
        "practitioner"
    ],
    "wof:name":"Marshman David",
    "wof:placetype":"venue"
},
  "geometry": {"coordinates":[151.189208984,-33.821231842],"type":"Point"}
}