{
  "type": "Feature",
  "properties": {
    "addr:full":"9 Waterfall Ave Forestville NSW 2087",
    "addr:housenumber":"9",
    "addr:postcode":"2087",
    "addr:street":"Waterfall Ave",
    "iso:country":"AU",
    "sg:address":"9 Waterfall Ave",
    "sg:city":"Forestville",
    "sg:classifiers":[
        {
            "category":"Professional",
            "subcategory":"Research",
            "type":"Services"
        }
    ],
    "sg:phone":"+61 2 9975 7011",
    "sg:postcode":"2087",
    "sg:province":"NSW",
    "sg:tags":[
        "market"
    ],
    "wof:name":"Le Grice Research",
    "wof:placetype":"venue"
},
  "geometry": {"coordinates":[151.21554565400001,-33.7679672241],"type":"Point"}
}