{
  "type": "Feature",
  "properties": {
    "addr:full":"U4/ 48 Thuringowa Drv Thuringowa Central QLD 4817",
    "addr:postcode":"4817",
    "addr:street":"U4 / 48 Thuringowa Drv",
    "iso:country":"AU",
    "sg:address":"U4/ 48 Thuringowa Drv",
    "sg:city":"Thuringowa Central",
    "sg:classifiers":[
        {
            "category":"Professional",
            "subcategory":"Employment Agencies",
            "type":"Services"
        }
    ],
    "sg:phone":"+61 7 4723 6533",
    "sg:postcode":"4817",
    "sg:province":"QLD",
    "wof:name":"ATS Workforce",
    "wof:placetype":"venue"
},
  "geometry": {"coordinates":[146.72950700000001,-19.312632],"type":"Point"}
}