{
  "type": "Feature",
  "properties": {
    "addr:full":"102 Exmoor Drv Margaret River WA 6285",
    "addr:housenumber":"102",
    "addr:postcode":"6285",
    "addr:street":"Exmoor Drv",
    "iso:country":"AU",
    "sg:address":"102 Exmoor Drv",
    "sg:city":"Margaret River",
    "sg:classifiers":[
        {
            "category":"Social Services",
            "subcategory":"Retirement Home",
            "type":"Services"
        }
    ],
    "sg:phone":"+61 8 9757 3394",
    "sg:postcode":"6285",
    "sg:province":"WA",
    "sg:tags":[
        "environmental",
        "consultant",
        "pollution"
    ],
    "wof:name":"Leeuwin Hydrogeological Services",
    "wof:placetype":"venue"
},
  "geometry": {"coordinates":[115.049423218,-33.9847679138],"type":"Point"}
}