{
  "type": "Feature",
  "properties": {
    "addr:full":"67 Buchanan Rd Berwick VIC 3806",
    "addr:housenumber":"67",
    "addr:postcode":"3806",
    "addr:street":"Buchanan Rd",
    "iso:country":"AU",
    "sg:address":"67 Buchanan Rd",
    "sg:city":"Berwick",
    "sg:classifiers":[
        {
            "category":"Building & Trades",
            "subcategory":"Plumbing",
            "type":"Services"
        }
    ],
    "sg:phone":"+61 3 9769 5299",
    "sg:postcode":"3806",
    "sg:province":"VIC",
    "sg:tags":[
        "plumber",
        "gasfitters"
    ],
    "wof:name":"Das Services Pty Ltd",
    "wof:placetype":"venue"
},
  "geometry": {"coordinates":[145.35707092300001,-38.0228652954],"type":"Point"}
}