{
  "type": "Feature",
  "properties": {
    "iso:country":"AU",
    "sg:address":"Unit 4/ 26 Dobra Rd",
    "sg:city":"Yangebup",
    "sg:classifiers":[
        {
            "category":"Manufacturing",
            "subcategory":"Glass & Minerals",
            "type":"Manufacturing & Wholesale Goods"
        }
    ],
    "sg:phone":"+61 8 9418 1100",
    "sg:postcode":"6164",
    "sg:province":"WA",
    "sg:tags":[
        "fabricator",
        "foam",
        "processor"
    ],
    "wof:name":"Specialty Foams Pty Ltd",
    "wof:placetype":"venue"
},
  "geometry": {"coordinates":[115.796288,-32.117458],"type":"Point"}
}