{
  "type": "Feature",
  "properties": {
    "iso:country":"AU",
    "sg:address":"Cnr Kooyong Rd & Great Eastern Hwy",
    "sg:city":"Rivervale",
    "sg:classifiers":[
        {
            "category":"Personal",
            "subcategory":"Tanning Parlor",
            "type":"Services"
        }
    ],
    "sg:phone":"+61 8 9355 5722",
    "sg:postcode":"6103",
    "sg:province":"WA",
    "sg:tags":[
        "solarium"
    ],
    "wof:name":"Zanzi Beach Tanning Studio",
    "wof:placetype":"venue"
},
  "geometry": {"coordinates":[115.912780762,-31.9606971741],"type":"Point"}
}