{
  "type": "Feature",
  "properties": {
    "addr:full":"255 Kensington Rd Kensington Park SA 5068",
    "addr:housenumber":"255",
    "addr:postcode":"5068",
    "addr:street":"Kensington Rd",
    "iso:country":"AU",
    "sg:address":"255 Kensington Rd",
    "sg:city":"Kensington Park",
    "sg:classifiers":[
        {
            "category":"Deli",
            "type":"Food & Drink"
        }
    ],
    "sg:phone":"+61 8 8431 4330",
    "sg:postcode":"5068",
    "sg:province":"SA",
    "sg:tags":[
        "delicatessen"
    ],
    "wof:name":"Top Shop Convenience Stores",
    "wof:placetype":"venue"
},
  "geometry": {"coordinates":[138.65545654300001,-34.9260864258],"type":"Point"}
}