{
  "type": "Feature",
  "properties": {
    "addr:full":"323 Chapel St Prahran VIC 3181",
    "addr:housenumber":"323",
    "addr:postcode":"3181",
    "addr:street":"Chapel St",
    "iso:country":"AU",
    "sg:address":"323 Chapel St",
    "sg:city":"Prahran",
    "sg:classifiers":[
        {
            "category":"Shopping",
            "subcategory":"Clothing, Apparel, & Fashions",
            "type":"Retail Goods"
        }
    ],
    "sg:phone":"+61 3 9533 8513",
    "sg:postcode":"3181",
    "sg:province":"VIC",
    "sg:tags":[
        "lady",
        "wear"
    ],
    "wof:name":"Devious Pty Ltd",
    "wof:placetype":"venue"
},
  "geometry": {"coordinates":[144.99383544899999,-37.8476066589],"type":"Point"}
}