{
  "type": "Feature",
  "properties": {
    "addr:full":"Suite 718A, 401 Sussex St Sydney NSW 2000",
    "addr:housenumber":"401",
    "addr:postcode":"2000",
    "addr:street":"Sussex St",
    "iso:country":"AU",
    "sg:address":"Suite 718A, 401 Sussex St",
    "sg:city":"Sydney",
    "sg:classifiers":[
        {
            "category":"Professional",
            "subcategory":"Employment Agencies",
            "type":"Services"
        }
    ],
    "sg:phone":"+61 2 9281 6529",
    "sg:postcode":"2000",
    "sg:province":"NSW",
    "wof:name":"Aust China International Service Centre",
    "wof:placetype":"venue"
},
  "geometry": {"coordinates":[151.20463562,-33.8782501221],"type":"Point"}
}