{
  "type": "Feature",
  "properties": {
    "addr:full":"79-85 Oxford St Bondi Junction NSW 2022",
    "addr:housenumber":"79-85",
    "addr:postcode":"2022",
    "addr:street":"Oxford St",
    "iso:country":"AU",
    "sg:address":"79-85 Oxford St",
    "sg:city":"Bondi Junction",
    "sg:classifiers":[
        {
            "category":"Banks & Credit Unions",
            "subcategory":"Financial Services",
            "type":"Services"
        }
    ],
    "sg:phone":"+61 2 9369 2443",
    "sg:postcode":"2022",
    "sg:province":"NSW",
    "sg:tags":[
        "annuity",
        "rollover",
        "superannuation",
        "consultant"
    ],
    "wof:name":"Forman Financial Services",
    "wof:placetype":"venue"
},
  "geometry": {"coordinates":[151.24615478499999,-33.8915214539],"type":"Point"}
}