{
  "type": "Feature",
  "properties": {
    "addr:full":"Shop 46 The Park Centre East Victoria Park WA 6101",
    "addr:housenumber":"shop 46",
    "addr:postcode":"6101",
    "addr:street":"The Park",
    "iso:country":"AU",
    "sg:address":"Shop 46",
    "sg:city":"The Park Centre East Victoria Park",
    "sg:classifiers":[
        {
            "category":"Personal",
            "subcategory":"Shoe Repair & Shine",
            "type":"Services"
        }
    ],
    "sg:phone":"+61 8 9362 5747",
    "sg:postcode":"6101",
    "sg:province":"WA",
    "sg:tags":[
        "footwear"
    ],
    "wof:name":"The Shoeman Multi-Service",
    "wof:placetype":"venue"
},
  "geometry": {"coordinates":[115.90348053,-31.9852199554],"type":"Point"}
}