{
  "type": "Feature",
  "properties": {
    "addr:full":"10 Knowles Pl Bossley Park NSW 2176",
    "addr:housenumber":"10",
    "addr:postcode":"2176",
    "addr:street":"Knowles Pl",
    "iso:country":"AU",
    "sg:address":"10 Knowles Pl",
    "sg:city":"Bossley Park",
    "sg:classifiers":[
        {
            "category":"Professional",
            "type":"Services"
        }
    ],
    "sg:phone":"+61 2 9729 0319",
    "sg:postcode":"2176",
    "sg:province":"NSW",
    "sg:tags":[
        "transport"
    ],
    "wof:name":"Lazar Fast Delivery",
    "wof:placetype":"venue"
},
  "geometry": {"coordinates":[150.895462036,-33.8622131348],"type":"Point"}
}