{
  "type": "Feature",
  "properties": {
    "addr:full":"131 Fairfield Rd Guildford NSW 2161",
    "addr:housenumber":"131",
    "addr:postcode":"2161",
    "addr:street":"Fairfield Rd",
    "iso:country":"AU",
    "sg:address":"131 Fairfield Rd",
    "sg:city":"Guildford",
    "sg:classifiers":[
        {
            "category":"Personal",
            "subcategory":"Beauty Salon",
            "type":"Services"
        }
    ],
    "sg:phone":"+61 2 9632 6722",
    "sg:postcode":"2161",
    "sg:province":"NSW",
    "sg:tags":[
        "hairdresser"
    ],
    "wof:name":"Kim's Cut N Style",
    "wof:placetype":"venue"
},
  "geometry": {"coordinates":[150.96112060600001,-33.8501434326],"type":"Point"}
}