{
  "type": "Feature",
  "properties": {
    "addr:full":"25 Javez Drv Quinns Rocks WA 6030",
    "addr:housenumber":"25",
    "addr:postcode":"6030",
    "addr:street":"Javez Drv",
    "iso:country":"AU",
    "sg:address":"25 Javez Drv",
    "sg:city":"Quinns Rocks",
    "sg:classifiers":[
        {
            "category":"Health Services",
            "subcategory":"Doctor",
            "type":"Services"
        }
    ],
    "sg:phone":"+61 8 9305 1975",
    "sg:postcode":"6030",
    "sg:province":"WA",
    "sg:tags":[
        "reflexology"
    ],
    "wof:name":"Washer Vera",
    "wof:placetype":"venue"
},
  "geometry": {"coordinates":[115.695610046,-31.6719379425],"type":"Point"}
}