{
  "type": "Feature",
  "properties": {
    "iso:country":"AU",
    "sg:address":"Main Rd",
    "sg:city":"Mt George",
    "sg:classifiers":[
        {
            "category":"Farming",
            "subcategory":"Orchard",
            "type":"Manufacturing & Wholesale Goods"
        }
    ],
    "sg:phone":"+61 2 6550 6541",
    "sg:postcode":"2424",
    "sg:province":"NSW",
    "sg:tags":[
        "citrus",
        "fruit",
        "grower"
    ],
    "wof:name":"Temple M C & J A",
    "wof:placetype":"venue"
},
  "geometry": {"coordinates":[152.178955,-31.881889],"type":"Point"}
}