{
  "type": "Feature",
  "properties": {
    "iso:country":"AU",
    "sg:address":"95 McGahan St",
    "sg:city":"Carina Heights",
    "sg:classifiers":[
        {
            "category":"Education",
            "subcategory":"Dance Studio",
            "type":"Public Place"
        }
    ],
    "sg:phone":"+61 7 3395 4222",
    "sg:postcode":"4152",
    "sg:province":"QLD",
    "sg:tags":[
        "training",
        "video",
        "film"
    ],
    "wof:name":"Vision Presentations",
    "wof:placetype":"venue"
},
  "geometry": {"coordinates":[153.089477539,-27.5071659088],"type":"Point"}
}