{
  "type": "Feature",
  "properties": {
    "iso:country":"AU",
    "sg:address":"184 Bass Hwy",
    "sg:city":"Wonthaggi",
    "sg:classifiers":[
        {
            "category":"Food & Beverages",
            "subcategory":"Groceries & Convenience Stores",
            "type":"Retail Goods"
        }
    ],
    "sg:phone":"+61 3 5672 1402",
    "sg:postcode":"3995",
    "sg:province":"VIC",
    "wof:name":"Hicksborough General Store",
    "wof:placetype":"venue"
},
  "geometry": {"coordinates":[145.601685,-38.605267],"type":"Point"}
}