{
  "type": "Feature",
  "properties": {
    "iso:country":"AU",
    "sg:address":"21 Whyalla St",
    "sg:city":"Fyshwick",
    "sg:classifiers":[
        {
            "category":"Manufacturing",
            "subcategory":"Building Materials",
            "type":"Manufacturing & Wholesale Goods"
        }
    ],
    "sg:phone":"+61 2 6280 4010",
    "sg:postcode":"2609",
    "sg:province":"ACT",
    "sg:tags":[
        "concrete",
        "product"
    ],
    "wof:name":"Hebel",
    "wof:placetype":"venue"
},
  "geometry": {"coordinates":[149.17417907699999,-35.3334617615],"type":"Point"}
}