{
  "type": "Feature",
  "properties": {
    "iso:country":"AU",
    "sg:address":"1/ 54 Boulder Rd",
    "sg:city":"Malaga",
    "sg:classifiers":[
        {
            "category":"Bars & Pubs",
            "subcategory":"Champagne Bar",
            "type":"Food & Drink"
        }
    ],
    "sg:phone":"+61 8 9248 1077",
    "sg:postcode":"6090",
    "sg:province":"WA",
    "sg:tags":[
        "lintel",
        "arch"
    ],
    "wof:name":"Calab Steel",
    "wof:placetype":"venue"
},
  "geometry": {"coordinates":[115.90701294,-31.8649082184],"type":"Point"}
}