{
  "type": "Feature",
  "properties": {
    "addr:full":"25 Ainsworth St Geraldton WA 6530",
    "addr:housenumber":"25",
    "addr:postcode":"6530",
    "addr:street":"Ainsworth St",
    "iso:country":"AU",
    "sg:address":"25 Ainsworth St",
    "sg:city":"Geraldton",
    "sg:classifiers":[
        {
            "category":"Health Services",
            "subcategory":"Health Practitioner",
            "type":"Services"
        }
    ],
    "sg:phone":"+61 8 9921 1001",
    "sg:postcode":"6530",
    "sg:province":"WA",
    "sg:tags":[
        "naturopath"
    ],
    "wof:name":"Health Waves",
    "wof:placetype":"venue"
},
  "geometry": {"coordinates":[114.622879028,-28.7657375336],"type":"Point"}
}