{
  "type": "Feature",
  "properties": {
    "addr:full":"3460 Pacific Hwy Springwood QLD 4127",
    "addr:housenumber":"3460",
    "addr:postcode":"4127",
    "addr:street":"Pacific Hwy",
    "iso:country":"AU",
    "sg:address":"3460 Pacific Hwy",
    "sg:city":"Springwood",
    "sg:classifiers":[
        {
            "category":"Banks & Credit Unions",
            "subcategory":"Financial Services",
            "type":"Services"
        }
    ],
    "sg:phone":"+61 7 3808 7133",
    "sg:postcode":"4127",
    "sg:province":"QLD",
    "sg:tags":[
        "planning"
    ],
    "wof:name":"Boothman P & M Financial Planning Services",
    "wof:placetype":"venue"
},
  "geometry": {"coordinates":[153.129806519,-27.6288204193],"type":"Point"}
}