{
  "type": "Feature",
  "properties": {
    "addr:full":"Shop 8a Module Shopping Centre Hannah St Beecroft NSW 2119",
    "addr:housenumber":"shop 8a",
    "addr:postcode":"2119",
    "addr:street":"Hannah St",
    "iso:country":"AU",
    "sg:address":"Shop 8a Module Shopping Centre Hannah St",
    "sg:city":"Beecroft",
    "sg:classifiers":[
        {
            "category":"Shopping",
            "subcategory":"Crafts & Fabrics",
            "type":"Retail Goods"
        }
    ],
    "sg:phone":"+61 2 9875 5844",
    "sg:postcode":"2119",
    "sg:province":"NSW",
    "sg:tags":[
        "wool",
        "knitting",
        "accessory"
    ],
    "wof:name":"Knit It",
    "wof:placetype":"venue"
},
  "geometry": {"coordinates":[151.06532287600001,-33.7493896484],"type":"Point"}
}