{
  "type": "Feature",
  "properties": {
    "iso:country":"AU",
    "sg:address":"Unit 205/ 188 Chalmers St",
    "sg:city":"Sydney",
    "sg:classifiers":[
        {
            "category":"Shopping",
            "subcategory":"Stationery & Office Supplies",
            "type":"Retail Goods"
        }
    ],
    "sg:phone":"+61 2 9698 2390",
    "sg:postcode":"2000",
    "sg:province":"NSW",
    "sg:tags":[
        "equipment",
        "facsimile"
    ],
    "wof:name":"Accurate Office Technologies",
    "wof:placetype":"venue"
},
  "geometry": {"coordinates":[151.20640564000001,-33.8888702393],"type":"Point"}
}