{
  "type": "Feature",
  "properties": {
    "addr:full":"4/ 26 Expo Crt Southport QLD 4215",
    "addr:housenumber":"/ 26",
    "addr:postcode":"4215",
    "addr:street":"Expo Crt",
    "iso:country":"AU",
    "sg:address":"4/ 26 Expo Crt",
    "sg:city":"Southport",
    "sg:classifiers":[
        {
            "category":"Building & Trades",
            "subcategory":"Construction",
            "type":"Services"
        }
    ],
    "sg:phone":"+61 7 5571 2770",
    "sg:postcode":"4215",
    "sg:province":"QLD",
    "sg:tags":[
        "contractor"
    ],
    "wof:name":"The Caprice Group",
    "wof:placetype":"venue"
},
  "geometry": {"coordinates":[153.385894775,-27.9806594849],"type":"Point"}
}