{
  "type": "Feature",
  "properties": {
    "addr:full":"63A Premier Dr Campbellfield VIC 3061",
    "addr:housenumber":"63a",
    "addr:postcode":"3061",
    "addr:street":"Premier Dr",
    "iso:country":"AU",
    "sg:address":"63A Premier Dr",
    "sg:city":"Campbellfield",
    "sg:classifiers":[
        {
            "category":"Wholesale",
            "subcategory":"Machinery & Supplies",
            "type":"Manufacturing & Wholesale Goods"
        }
    ],
    "sg:phone":"+61 3 9358 0900",
    "sg:postcode":"3061",
    "sg:province":"VIC",
    "sg:tags":[
        "equipment",
        "welding"
    ],
    "wof:name":"Procus Welding & Industrial Supplies Pty Ltd",
    "wof:placetype":"venue"
},
  "geometry": {"coordinates":[144.966033936,-37.659198761],"type":"Point"}
}