{
  "type": "Feature",
  "properties": {
    "addr:full":"68 Sprent St Narrabundah ACT 2604",
    "addr:housenumber":"68",
    "addr:postcode":"2604",
    "addr:street":"Sprent St",
    "iso:country":"AU",
    "sg:address":"68 Sprent St",
    "sg:city":"Narrabundah",
    "sg:classifiers":[
        {
            "category":"Building & Trades",
            "subcategory":"Construction",
            "type":"Services"
        }
    ],
    "sg:phone":"+61 2 6295 9695",
    "sg:postcode":"2604",
    "sg:province":"ACT",
    "sg:tags":[
        "contractor"
    ],
    "wof:name":"Munns K W",
    "wof:placetype":"venue"
},
  "geometry": {"coordinates":[149.14309692399999,-35.3374938965],"type":"Point"}
}