{
  "type": "Feature",
  "properties": {
    "addr:full":"Cnr Pacific Hwy & Burns Rd Ourimbah NSW 2258",
    "addr:postcode":"2258",
    "addr:street":"Cnr Pacific Hwy & Burns Rd",
    "iso:country":"AU",
    "sg:address":"Cnr Pacific Hwy & Burns Rd",
    "sg:city":"Ourimbah",
    "sg:classifiers":[
        {
            "category":"Manufacturing",
            "subcategory":"Pottery",
            "type":"Manufacturing & Wholesale Goods"
        }
    ],
    "sg:phone":"+61 2 4362 2236",
    "sg:postcode":"2258",
    "sg:province":"NSW",
    "wof:name":"Home & Garden Centre Ourimbah",
    "wof:placetype":"venue"
},
  "geometry": {"coordinates":[151.36978149399999,-33.3519020081],"type":"Point"}
}