{
  "type": "Feature",
  "properties": {
    "iso:country":"AU",
    "sg:address":"Factory A, 20 Early St",
    "sg:city":"Mansfield",
    "sg:classifiers":[
        {
            "category":"Professional",
            "subcategory":"Detective & Security Services",
            "type":"Services"
        }
    ],
    "sg:phone":"+61 438 509 737",
    "sg:postcode":"3722",
    "sg:province":"VIC",
    "sg:tags":[
        "equipment",
        "window",
        "doors"
    ],
    "wof:name":"Robbo's Glass",
    "wof:placetype":"venue"
},
  "geometry": {"coordinates":[146.085845947,-37.0506973267],"type":"Point"}
}