{
  "type": "Feature",
  "properties": {
    "addr:full":"Cnr Francis Blv & Sunbury Rd Sunbury VIC 3429",
    "addr:postcode":"3429",
    "addr:street":"Cnr Francis Blv & Sunbury Rd",
    "iso:country":"AU",
    "sg:address":"Cnr Francis Blv & Sunbury Rd",
    "sg:city":"Sunbury",
    "sg:classifiers":[
        {
            "category":"Sports & Exercise",
            "subcategory":"Golf",
            "type":"Entertainment"
        }
    ],
    "sg:phone":"+61 3 9744 4344",
    "sg:postcode":"3429",
    "sg:province":"VIC",
    "sg:tags":[
        "club"
    ],
    "wof:name":"Goonawarra Golf Club Ltd",
    "wof:placetype":"venue"
},
  "geometry": {"coordinates":[144.740768433,-37.5834121704],"type":"Point"}
}