{
  "type": "Feature",
  "properties": {
    "addr:full":"Unit 18 46-48 Abel St Penrith NSW 2750",
    "addr:housenumber":"46-48",
    "addr:postcode":"2750",
    "addr:street":"Abel St",
    "iso:country":"AU",
    "sg:address":"Unit 18 46-48 Abel St",
    "sg:city":"Penrith",
    "sg:classifiers":[
        {
            "category":"Professional",
            "subcategory":"Accounting & Tax Preparation",
            "type":"Services"
        }
    ],
    "sg:phone":"+61 2 4721 1054",
    "sg:postcode":"2750",
    "sg:province":"NSW",
    "sg:tags":[
        "accountant",
        "auditor"
    ],
    "wof:name":"Kevin F Craven & Assoc. Pty Ltd",
    "wof:placetype":"venue"
},
  "geometry": {"coordinates":[150.67103576700001,-33.7432174683],"type":"Point"}
}