{
  "type": "Feature",
  "properties": {
    "iso:country":"AU",
    "sg:address":"249 Ormond Rd",
    "sg:city":"Narre Warren South",
    "sg:classifiers":[
        {
            "category":"Health Services",
            "subcategory":"Doctor",
            "type":"Services"
        }
    ],
    "sg:phone":"+61 3 8794 9700",
    "sg:postcode":"3805",
    "sg:province":"VIC",
    "sg:tags":[
        "medical",
        "practitioner"
    ],
    "wof:name":"Morley, D. Dr",
    "wof:placetype":"venue"
},
  "geometry": {"coordinates":[145.287613,-38.053677],"type":"Point"}
}