{
  "type": "Feature",
  "properties": {
    "addr:full":"1 Colwyn Rd Bayswater WA 6053",
    "addr:housenumber":"1",
    "addr:postcode":"6053",
    "addr:street":"Colwyn Rd",
    "iso:country":"AU",
    "sg:address":"1 Colwyn Rd",
    "sg:city":"Bayswater",
    "sg:classifiers":[
        {
            "category":"Building & Trades",
            "subcategory":"Construction",
            "type":"Services"
        }
    ],
    "sg:phone":"+61 411 860 457",
    "sg:postcode":"6053",
    "sg:province":"WA",
    "sg:tags":[
        "contractor"
    ],
    "wof:name":"Cosy Homes Constructions Pty Ltd",
    "wof:placetype":"venue"
},
  "geometry": {"coordinates":[115.930908203,-31.9230613708],"type":"Point"}
}