{
  "type": "Feature",
  "properties": {
    "addr:full":"25 Napier St Mendooran NSW 2842",
    "addr:housenumber":"25",
    "addr:postcode":"2842",
    "addr:street":"Napier St",
    "iso:country":"AU",
    "sg:address":"25 Napier St",
    "sg:city":"Mendooran",
    "sg:classifiers":[
        {
            "category":"Home & Garden",
            "subcategory":"Hardware",
            "type":"Retail Goods"
        }
    ],
    "sg:phone":"+61 428 637 072",
    "sg:postcode":"2842",
    "sg:province":"NSW",
    "sg:tags":[
        "pumping",
        "contractor"
    ],
    "wof:name":"M.T. McKechnie Drilling Services",
    "wof:placetype":"venue"
},
  "geometry": {"coordinates":[149.125336,-31.822119],"type":"Point"}
}