{
  "type": "Feature",
  "properties": {
    "addr:full":"Shp7/ 99 Kendal St Cowra NSW 2794",
    "addr:housenumber":"99",
    "addr:postcode":"2794",
    "addr:street":"Kendal St",
    "iso:country":"AU",
    "sg:address":"Shp7/ 99 Kendal St",
    "sg:city":"Cowra",
    "sg:classifiers":[
        {
            "category":"Shopping",
            "subcategory":"Clothing, Apparel, & Fashions",
            "type":"Retail Goods"
        }
    ],
    "sg:phone":"+61 2 6342 6646",
    "sg:postcode":"2794",
    "sg:province":"NSW",
    "sg:tags":[
        "lingerie",
        "hosiery",
        "sleepwear"
    ],
    "wof:name":"Lace Of Hearts Lingerie Boutique",
    "wof:placetype":"venue"
},
  "geometry": {"coordinates":[148.69776916500001,-33.8355636597],"type":"Point"}
}