{
  "type": "Feature",
  "properties": {
    "addr:full":"Old Geelong Rd Ararat VIC 3377",
    "addr:postcode":"3377",
    "addr:street":"Geelong Rd",
    "iso:country":"AU",
    "sg:address":"Old Geelong Rd",
    "sg:city":"Ararat",
    "sg:classifiers":[
        {
            "category":"Building & Trades",
            "subcategory":"Construction",
            "type":"Services"
        }
    ],
    "sg:phone":"+61 3 5352 1013",
    "sg:postcode":"3377",
    "sg:province":"VIC",
    "sg:tags":[
        "earth",
        "excavating",
        "moving",
        "contractor"
    ],
    "wof:name":"Max A Wohlers",
    "wof:placetype":"venue"
},
  "geometry": {"coordinates":[142.93130493199999,-37.2824211121],"type":"Point"}
}