{
  "type": "Feature",
  "properties": {
    "iso:country":"AU",
    "sg:address":"Cnr Farm & Alexandra Sts",
    "sg:city":"North Rockhampton",
    "sg:classifiers":[
        {
            "category":"Retail",
            "subcategory":"Auto Repair",
            "type":"Services"
        }
    ],
    "sg:phone":"+61 7 4927 4700",
    "sg:postcode":"4701",
    "sg:province":"QLD",
    "sg:tags":[
        "bus",
        "truck"
    ],
    "wof:name":"Mack Trucks Australia Pty Ltd",
    "wof:placetype":"venue"
},
  "geometry": {"coordinates":[150.517776489,-23.3561992645],"type":"Point"}
}