{
  "type": "Feature",
  "properties": {
    "iso:country":"AU",
    "sg:address":"LG 43",
    "sg:city":"Campbelltown Mall Campbelltown",
    "sg:classifiers":[
        {
            "category":"Shopping",
            "subcategory":"Jewelry",
            "type":"Retail Goods"
        }
    ],
    "sg:phone":"+61 2 4620 0496",
    "sg:postcode":"2560",
    "sg:province":"NSW",
    "sg:tags":[
        "jeweller"
    ],
    "wof:name":"Kleins",
    "wof:placetype":"venue"
},
  "geometry": {"coordinates":[150.83729553200001,-34.0107879639],"type":"Point"}
}