{
  "type": "Feature",
  "properties": {
    "iso:country":"AU",
    "sg:address":"13 Gilling Pl",
    "sg:city":"Orelia",
    "sg:classifiers":[
        {
            "category":"Retail",
            "subcategory":"Auto Rental",
            "type":"Services"
        }
    ],
    "sg:phone":"+61 8 9439 1667",
    "sg:postcode":"6167",
    "sg:province":"WA",
    "sg:tags":[
        "chauffeur",
        "car",
        "hire",
        "driven",
        "limousine"
    ],
    "wof:name":"All Type Limousines",
    "wof:placetype":"venue"
},
  "geometry": {"coordinates":[115.832291,-32.23093],"type":"Point"}
}