{
  "type": "Feature",
  "properties": {
    "addr:full":"8- 10 Northumberland Rd Auburn NSW 2144",
    "addr:housenumber":"10",
    "addr:postcode":"2144",
    "addr:street":"8;Northumberland Rd",
    "iso:country":"AU",
    "sg:address":"8- 10 Northumberland Rd",
    "sg:city":"Auburn",
    "sg:classifiers":[
        {
            "category":"Home & Garden",
            "subcategory":"Building Materials",
            "type":"Retail Goods"
        }
    ],
    "sg:phone":"+61 417 022 900",
    "sg:postcode":"2144",
    "sg:province":"NSW",
    "sg:tags":[
        "shutter",
        "roller",
        "grille"
    ],
    "wof:name":"Ceevee Roller Shutters Pty Ltd",
    "wof:placetype":"venue"
},
  "geometry": {"coordinates":[151.03364563,-33.8486404419],"type":"Point"}
}