{
  "type": "Feature",
  "properties": {
    "iso:country":"AU",
    "sg:address":"1 / 10",
    "sg:city":"Bon Mace Close, Tumbi Umbi",
    "sg:classifiers":[
        {
            "category":"Building & Trades",
            "subcategory":"Construction",
            "type":"Services"
        }
    ],
    "sg:phone":"+61 2 4388 3100",
    "sg:postcode":"2261",
    "sg:province":"NSW",
    "sg:tags":[
        "home",
        "air conditioning"
    ],
    "wof:name":"All Systems Air Conditioning",
    "wof:placetype":"venue"
},
  "geometry": {"coordinates":[151.44245900000001,-33.358597],"type":"Point"}
}