{
  "type": "Feature",
  "properties": {
    "addr:full":"127 Pangee St Nyngan NSW 2825",
    "addr:housenumber":"127",
    "addr:postcode":"2825",
    "addr:street":"Pangee St",
    "iso:country":"AU",
    "sg:address":"127 Pangee St",
    "sg:city":"Nyngan",
    "sg:classifiers":[
        {
            "category":"Food & Beverages",
            "subcategory":"Fruits & Vegetables",
            "type":"Retail Goods"
        }
    ],
    "sg:phone":"+61 2 6832 1564",
    "sg:postcode":"2825",
    "sg:province":"NSW",
    "sg:tags":[
        "greengrocer",
        "fruiterer"
    ],
    "wof:name":"Nyngan Fresh Foods",
    "wof:placetype":"venue"
},
  "geometry": {"coordinates":[147.19647216800001,-31.563325882],"type":"Point"}
}