{
  "type": "Feature",
  "properties": {
    "addr:full":"17 Alfreda Ave Rosanna VIC 3084",
    "addr:housenumber":"17",
    "addr:postcode":"3084",
    "addr:street":"Alfreda Ave",
    "iso:country":"AU",
    "sg:address":"17 Alfreda Ave",
    "sg:city":"Rosanna",
    "sg:classifiers":[
        {
            "category":"Recreation",
            "subcategory":"Fishing",
            "type":"Entertainment"
        }
    ],
    "sg:phone":"+61 3 9459 5220",
    "sg:postcode":"3084",
    "sg:province":"VIC",
    "sg:tags":[
        "tackle"
    ],
    "wof:name":"Magnum Fishing Products",
    "wof:placetype":"venue"
},
  "geometry": {"coordinates":[145.07095336899999,-37.7421722412],"type":"Point"}
}