{
  "type": "Feature",
  "properties": {
    "addr:full":"Shop 22 Caringbah Shopping Village Caringbah NSW 2229",
    "addr:housenumber":"shop 22",
    "addr:postcode":"2229",
    "iso:country":"AU",
    "sg:address":"Shop 22",
    "sg:city":"Caringbah Shopping Village Caringbah",
    "sg:classifiers":[
        {
            "category":"Personal",
            "subcategory":"Beauty Salon",
            "type":"Services"
        }
    ],
    "sg:phone":"+61 2 9540 3199",
    "sg:postcode":"2229",
    "sg:province":"NSW",
    "sg:tags":[
        "hairdresser"
    ],
    "wof:name":"Vizual Hair Studio",
    "wof:placetype":"venue"
},
  "geometry": {"coordinates":[151.13473510700001,-34.0485458374],"type":"Point"}
}