{
  "type": "Feature",
  "properties": {
    "iso:country":"AU",
    "sg:address":"1 / 14 Crocker Drv",
    "sg:city":"Malaga",
    "sg:classifiers":[
        {
            "category":"Manufacturing",
            "subcategory":"Retail Goods",
            "type":"Manufacturing & Wholesale Goods"
        }
    ],
    "sg:phone":"+61 8 9248 3500",
    "sg:postcode":"6090",
    "sg:province":"WA",
    "sg:tags":[
        "merchant",
        "pump",
        "mfrs"
    ],
    "wof:name":"Kelair Pumps",
    "wof:placetype":"venue"
},
  "geometry": {"coordinates":[115.88176727299999,-31.8602581024],"type":"Point"}
}