{
  "type": "Feature",
  "properties": {
    "iso:country":"AU",
    "sg:address":"160 Collins St",
    "sg:city":"Hobart",
    "sg:classifiers":[
        {
            "category":"Shopping",
            "subcategory":"Optical Goods",
            "type":"Retail Goods"
        }
    ],
    "sg:phone":"+61 3 6224 3988",
    "sg:postcode":"7000",
    "sg:province":"TAS",
    "sg:tags":[
        "dispenser",
        "prescription"
    ],
    "wof:name":"Look Of Australia",
    "wof:placetype":"venue"
},
  "geometry": {"coordinates":[147.32650756800001,-42.8841667175],"type":"Point"}
}