{
  "type": "Feature",
  "properties": {
    "addr:full":"36 Lacebark St North Lakes QLD 4509",
    "addr:housenumber":"36",
    "addr:postcode":"4509",
    "addr:street":"Lacebark St",
    "iso:country":"AU",
    "sg:address":"36 Lacebark St",
    "sg:city":"North Lakes",
    "sg:classifiers":[
        {
            "category":"Banks & Credit Unions",
            "subcategory":"Financial Services",
            "type":"Services"
        }
    ],
    "sg:phone":"+61 7 3139 1460",
    "sg:postcode":"4509",
    "sg:province":"QLD",
    "sg:tags":[
        "loan",
        "finance",
        "mortgage"
    ],
    "wof:name":"Bluezone Loans Pty Ltd",
    "wof:placetype":"venue"
},
  "geometry": {"coordinates":[153.01353454599999,-27.2243404388],"type":"Point"}
}