{
  "type": "Feature",
  "properties": {
    "iso:country":"AU",
    "sg:address":"125 Baxter Rd",
    "sg:city":"Mascot",
    "sg:classifiers":[
        {
            "category":"Retail",
            "subcategory":"Auto Repair",
            "type":"Services"
        }
    ],
    "sg:phone":"+61 2 9667 4860",
    "sg:postcode":"2020",
    "sg:province":"NSW",
    "sg:tags":[
        "beater",
        "painter",
        "panel"
    ],
    "wof:name":"K R Geary Auto Repairs",
    "wof:placetype":"venue"
},
  "geometry": {"coordinates":[151.187103272,-33.9312744141],"type":"Point"}
}