{
  "type": "Feature",
  "properties": {
    "addr:full":"2318 Frankston-Flinders Rd Bittern VIC 3918",
    "addr:housenumber":"2318",
    "addr:postcode":"3918",
    "addr:street":"Frankston-Flinders Rd",
    "iso:country":"AU",
    "sg:address":"2318 Frankston-Flinders Rd",
    "sg:city":"Bittern",
    "sg:classifiers":[
        {
            "category":"Building & Trades",
            "subcategory":"Landscaping Services",
            "type":"Services"
        }
    ],
    "sg:phone":"+61 412 833 852",
    "sg:postcode":"3918",
    "sg:province":"VIC",
    "sg:tags":[
        "designer",
        "landscape",
        "contractor"
    ],
    "wof:name":"Indigenous Garden Restoration Company Pty Ltd",
    "wof:placetype":"venue"
},
  "geometry": {"coordinates":[145.182769775,-38.3287734985],"type":"Point"}
}