{
  "type": "Feature",
  "properties": {
    "addr:full":"41 Export Drv Brooklyn VIC 3025",
    "addr:housenumber":"41",
    "addr:postcode":"3025",
    "addr:street":"Export Drv",
    "iso:country":"AU",
    "sg:address":"41 Export Drv",
    "sg:city":"Brooklyn",
    "sg:classifiers":[
        {
            "category":"Home & Garden",
            "subcategory":"Carpets & Floor Coverings",
            "type":"Retail Goods"
        }
    ],
    "sg:phone":"+61 3 9315 1399",
    "sg:postcode":"3025",
    "sg:province":"VIC",
    "wof:name":"Cork & Seals Pty Ltd",
    "wof:placetype":"venue"
},
  "geometry": {"coordinates":[144.854996,-37.821907],"type":"Point"}
}