{
  "type": "Feature",
  "properties": {
    "addr:full":"Shop 3 William Crt 12- 18 William St Gosford NSW 2250",
    "addr:housenumber":"shop 3;12 18",
    "addr:postcode":"2250",
    "addr:street":"William Crt;William St",
    "iso:country":"AU",
    "sg:address":"Shop 3 William Crt 12- 18 William St",
    "sg:city":"Gosford",
    "sg:classifiers":[
        {
            "category":"Shopping",
            "subcategory":"Optical Goods",
            "type":"Retail Goods"
        }
    ],
    "sg:phone":"+61 2 4325 1087",
    "sg:postcode":"2250",
    "sg:province":"NSW",
    "sg:tags":[
        "dispenser",
        "prescription"
    ],
    "wof:name":"OPSM Pty Ltd",
    "wof:placetype":"venue"
},
  "geometry": {"coordinates":[151.34315490700001,-33.4260520935],"type":"Point"}
}