{
  "type": "Feature",
  "properties": {
    "iso:country":"AU",
    "sg:address":"4 Alma St",
    "sg:city":"Hectorville",
    "sg:classifiers":[
        {
            "category":"Building & Trades",
            "subcategory":"Plumbing",
            "type":"Services"
        }
    ],
    "sg:phone":"+61 8 8337 3285",
    "sg:postcode":"5073",
    "sg:province":"SA",
    "sg:tags":[
        "plumber",
        "gasfitters"
    ],
    "wof:name":"Smith R J & H",
    "wof:placetype":"venue"
},
  "geometry": {"coordinates":[138.65982055699999,-34.8944320679],"type":"Point"}
}