{
  "type": "Feature",
  "properties": {
    "addr:full":"Queen Elizabeth II Hospital Cnr Kessels & Troughto Coopers Plains QLD 4108",
    "addr:postcode":"4108",
    "addr:street":"Cnr",
    "iso:country":"AU",
    "sg:address":"Queen Elizabeth II Hospital Cnr Kessels & Troughto",
    "sg:city":"Coopers Plains",
    "sg:classifiers":[
        {
            "category":"Health Services",
            "subcategory":"Doctor",
            "type":"Services"
        }
    ],
    "sg:phone":"+61 7 3275 6454",
    "sg:postcode":"4108",
    "sg:province":"QLD",
    "sg:tags":[
        "medical",
        "practitioner"
    ],
    "wof:name":"Mactaggart Peter",
    "wof:placetype":"venue"
},
  "geometry": {"coordinates":[153.04299926799999,-27.557800293],"type":"Point"}
}