{
  "type": "Feature",
  "properties": {
    "addr:full":"15 Cowper Rd Umina Beach NSW 2257",
    "addr:housenumber":"15",
    "addr:postcode":"2257",
    "addr:street":"Cowper Rd",
    "iso:country":"AU",
    "sg:address":"15 Cowper Rd",
    "sg:city":"Umina Beach",
    "sg:classifiers":[
        {
            "category":"Education",
            "subcategory":"Music School",
            "type":"Public Place"
        }
    ],
    "sg:phone":"+61 2 4344 7312",
    "sg:postcode":"2257",
    "sg:province":"NSW",
    "sg:tags":[
        "singing",
        "teacher"
    ],
    "wof:name":"Bonita Surenne",
    "wof:placetype":"venue"
},
  "geometry": {"coordinates":[151.30398559599999,-33.5316886902],"type":"Point"}
}