{
  "type": "Feature",
  "properties": {
    "addr:full":"Carnarvon Hwy St George QLD 4487",
    "addr:postcode":"4487",
    "addr:street":"Carnarvon Hwy",
    "iso:country":"AU",
    "sg:address":"Carnarvon Hwy St",
    "sg:city":"George",
    "sg:classifiers":[
        {
            "category":"Autos & Motor Vehicles",
            "subcategory":"Auto Supplies",
            "type":"Retail Goods"
        }
    ],
    "sg:phone":"+61 7 4625 5799",
    "sg:postcode":"4487",
    "sg:province":"QLD",
    "sg:tags":[
        "tyre"
    ],
    "wof:name":"Tyre Power St George",
    "wof:placetype":"venue"
},
  "geometry": {"coordinates":[148.58958435100001,-28.0445137024],"type":"Point"}
}