{
  "type": "Feature",
  "properties": {
    "addr:full":"1 Dayboro Rd Petrie QLD 4502",
    "addr:housenumber":"1",
    "addr:postcode":"4502",
    "addr:street":"Dayboro Rd",
    "iso:country":"AU",
    "sg:address":"1 Dayboro Rd",
    "sg:city":"Petrie",
    "sg:classifiers":[
        {
            "category":"Real Estate",
            "subcategory":"Real Estate Agent",
            "type":"Services"
        }
    ],
    "sg:phone":"+61 7 3285 1710",
    "sg:postcode":"4502",
    "sg:province":"QLD",
    "wof:name":"Harcourts Queensland Pty Ltd",
    "wof:placetype":"venue"
},
  "geometry": {"coordinates":[152.97462463400001,-27.2682609558],"type":"Point"}
}