{
  "type": "Feature",
  "properties": {
    "addr:full":"Suite 1b, Level 1, 98 Woodlark St Lismore NSW 2480",
    "addr:housenumber":"suite 1b level;98",
    "addr:postcode":"2480",
    "addr:street":"Woodlark St",
    "iso:country":"AU",
    "sg:address":"Suite 1b, Level 1, 98 Woodlark St",
    "sg:city":"Lismore",
    "sg:classifiers":[
        {
            "category":"Banks & Credit Unions",
            "subcategory":"Bank",
            "type":"Services"
        }
    ],
    "sg:phone":"+61 2 6619 1800",
    "sg:postcode":"2480",
    "sg:province":"NSW",
    "sg:tags":[
        "broker",
        "mortgage"
    ],
    "wof:name":"Living Loans",
    "wof:placetype":"venue"
},
  "geometry": {"coordinates":[153.27897644000001,-28.8073635101],"type":"Point"}
}