{
  "type": "Feature",
  "properties": {
    "addr:full":"Argyle Stores, Lv 1/ 12 Argyle St The Rocks NSW 2000",
    "addr:housenumber":"12",
    "addr:postcode":"2000",
    "addr:street":"Argyle St",
    "iso:country":"AU",
    "sg:address":"Argyle Stores, Lv 1/ 12 Argyle St",
    "sg:city":"The Rocks",
    "sg:classifiers":[
        {
            "category":"Professional",
            "subcategory":"Management & Consulting",
            "type":"Services"
        }
    ],
    "sg:phone":"+61 2 9247 7233",
    "sg:postcode":"2000",
    "sg:province":"NSW",
    "sg:tags":[
        "consultant",
        "relocation"
    ],
    "wof:name":"MoveCorp Australia Pty Ltd",
    "wof:placetype":"venue"
},
  "geometry": {"coordinates":[151.20765685999999,-33.8588943481],"type":"Point"}
}