{
  "type": "Feature",
  "properties": {
    "iso:country":"AU",
    "sg:address":"250 Manns St",
    "sg:city":"Gosford",
    "sg:classifiers":[
        {
            "category":"Professional",
            "subcategory":"Accounting & Tax Preparation",
            "type":"Services"
        }
    ],
    "sg:phone":"+61 2 4323 9755",
    "sg:postcode":"2250",
    "sg:province":"NSW",
    "sg:tags":[
        "consultant",
        "taxation"
    ],
    "wof:name":"Brown M F R & Co",
    "wof:placetype":"venue"
},
  "geometry": {"coordinates":[151.326705933,-33.4168701172],"type":"Point"}
}