{
  "type": "Feature",
  "properties": {
    "iso:country":"AU",
    "sg:address":"U1504/ 230 Marine Pde",
    "sg:city":"Labrador",
    "sg:classifiers":[
        {
            "category":"Professional",
            "subcategory":"Art Services",
            "type":"Services"
        }
    ],
    "sg:phone":"+61 7 5532 3477",
    "sg:postcode":"4215",
    "sg:province":"QLD",
    "sg:tags":[
        "interior",
        "designer"
    ],
    "wof:name":"Life By Design Gold Coast",
    "wof:placetype":"venue"
},
  "geometry": {"coordinates":[153.40916442899999,-27.950592041],"type":"Point"}
}