{
  "type": "Feature",
  "properties": {
    "iso:country":"AU",
    "sg:address":"17A Evans Ave",
    "sg:city":"North Mackay",
    "sg:classifiers":[
        {
            "category":"Wholesale",
            "subcategory":"Apparel",
            "type":"Manufacturing & Wholesale Goods"
        }
    ],
    "sg:phone":"+61 7 4951 4892",
    "sg:postcode":"4740",
    "sg:province":"QLD",
    "sg:tags":[
        "wholesaler",
        "mfrs",
        "uniform"
    ],
    "wof:name":"Mackay Clothing Factory",
    "wof:placetype":"venue"
},
  "geometry": {"coordinates":[149.187393,-21.124069],"type":"Point"}
}