{
  "type": "Feature",
  "properties": {
    "addr:full":"Industrial Products Division, 17-25 Templestowe Rd Bulleen VIC 3105",
    "addr:housenumber":"17-25",
    "addr:postcode":"3105",
    "addr:street":"Templestowe Rd",
    "iso:country":"AU",
    "sg:address":"Industrial Products Division, 17-25 Templestowe Rd",
    "sg:city":"Bulleen",
    "sg:classifiers":[
        {
            "category":"Manufacturing",
            "subcategory":"Paper Products",
            "type":"Manufacturing & Wholesale Goods"
        }
    ],
    "sg:phone":"+61 3 9851 2200",
    "sg:postcode":"3105",
    "sg:province":"VIC",
    "sg:tags":[
        "tube",
        "cardboard"
    ],
    "wof:name":"Sonoco Australia Pty Ltd",
    "wof:placetype":"venue"
},
  "geometry": {"coordinates":[145.08738708499999,-37.7574577332],"type":"Point"}
}