{
  "type": "Feature",
  "properties": {
    "addr:full":"Shop 45,Castletown Shopping World Hyde Park QLD 4812",
    "addr:housenumber":"shop 45",
    "addr:postcode":"4812",
    "addr:street":"Castletown Shopping",
    "iso:country":"AU",
    "sg:address":"Shop 45,Castletown Shopping World",
    "sg:city":"Hyde Park",
    "sg:classifiers":[
        {
            "category":"Health Services",
            "subcategory":"Optometrist",
            "type":"Services"
        }
    ],
    "sg:phone":"+61 7 4721 6834",
    "sg:postcode":"4812",
    "sg:province":"QLD",
    "wof:name":"Johnson Elizabeth",
    "wof:placetype":"venue"
},
  "geometry": {"coordinates":[146.79513499999999,-19.27693],"type":"Point"}
}