{
  "type": "Feature",
  "properties": {
    "addr:full":"154 Formosa Rd Gumdale QLD 4154",
    "addr:housenumber":"154",
    "addr:postcode":"4154",
    "addr:street":"Formosa Rd",
    "iso:country":"AU",
    "sg:address":"154 Formosa Rd",
    "sg:city":"Gumdale",
    "sg:classifiers":[
        {
            "category":"Travel",
            "subcategory":"Travel Agent",
            "type":"Entertainment"
        }
    ],
    "sg:phone":"+61 7 3390 6040",
    "sg:postcode":"4154",
    "sg:province":"QLD",
    "sg:tags":[
        "consultant"
    ],
    "wof:name":"Traveltrends",
    "wof:placetype":"venue"
},
  "geometry": {"coordinates":[153.14048767099999,-27.4923763275],"type":"Point"}
}