{
  "type": "Feature",
  "properties": {
    "addr:full":"130 Glengarrie Rd Tomewin NSW 2484",
    "addr:housenumber":"130",
    "addr:postcode":"2484",
    "addr:street":"Glengarrie Rd",
    "iso:country":"AU",
    "sg:address":"130 Glengarrie Rd",
    "sg:city":"Tomewin",
    "sg:classifiers":[
        {
            "category":"Manufacturing",
            "subcategory":"Pottery",
            "type":"Manufacturing & Wholesale Goods"
        }
    ],
    "sg:phone":"+61 7 5533 0298",
    "sg:postcode":"2484",
    "sg:province":"NSW",
    "wof:name":"Tomewin Pottery",
    "wof:placetype":"venue"
},
  "geometry": {"coordinates":[153.397674561,-28.2371406555],"type":"Point"}
}