{
  "type": "Feature",
  "properties": {
    "addr:full":"23 Park Rd Maryborough VIC 3465",
    "addr:housenumber":"23",
    "addr:postcode":"3465",
    "addr:street":"Park Rd",
    "iso:country":"AU",
    "sg:address":"23 Park Rd",
    "sg:city":"Maryborough",
    "sg:classifiers":[
        {
            "category":"Farming",
            "subcategory":"Farm & Veterinary Services",
            "type":"Manufacturing & Wholesale Goods"
        }
    ],
    "sg:phone":"+61 418 571 819",
    "sg:postcode":"3465",
    "sg:province":"VIC",
    "sg:tags":[
        "contracting"
    ],
    "wof:name":"Fenton D A & N J",
    "wof:placetype":"venue"
},
  "geometry": {"coordinates":[143.74020385700001,-37.0419273376],"type":"Point"}
}