{
  "type": "Feature",
  "properties": {
    "iso:country":"AU",
    "sg:address":"PO Box 2837",
    "sg:city":"Carlingford Court",
    "sg:classifiers":[
        {
            "category":"Shopping",
            "subcategory":"Beauty & Cosmetics",
            "type":"Retail Goods"
        }
    ],
    "sg:phone":"+61 415 787 944",
    "sg:postcode":"2118",
    "sg:province":"NSW",
    "wof:name":"Angel Face Make Up Artistry",
    "wof:placetype":"venue"
},
  "geometry": {"coordinates":[151.05239868199999,-33.7761688232],"type":"Point"}
}