{
  "type": "Feature",
  "properties": {
    "addr:full":"10 Von Nida Crt Dingley Village VIC 3172",
    "addr:housenumber":"10",
    "addr:postcode":"3172",
    "addr:street":"Von Nida Crt",
    "iso:country":"AU",
    "sg:address":"10 Von Nida Crt",
    "sg:city":"Dingley Village",
    "sg:classifiers":[
        {
            "category":"Shopping",
            "subcategory":"Computers & Home Electronics",
            "type":"Retail Goods"
        }
    ],
    "sg:phone":"+61 3 9511 8502",
    "sg:postcode":"3172",
    "sg:province":"VIC",
    "sg:tags":[
        "small",
        "equipment",
        "business"
    ],
    "wof:name":"Antec Computer Solutions",
    "wof:placetype":"venue"
},
  "geometry": {"coordinates":[145.125457764,-37.9796943665],"type":"Point"}
}