{
  "type": "Feature",
  "properties": {
    "addr:full":"Next to 85 Lake Entrance Rd Oak Flats NSW 2529",
    "addr:postcode":"2529",
    "addr:street":"Lake Entrance Rd",
    "iso:country":"AU",
    "sg:address":"Next to 85 Lake Entrance Rd",
    "sg:city":"Oak Flats",
    "sg:classifiers":[
        {
            "category":"Shopping",
            "subcategory":"Crafts & Fabrics",
            "type":"Retail Goods"
        }
    ],
    "sg:phone":"+61 2 4256 8054",
    "sg:postcode":"2529",
    "sg:province":"NSW",
    "sg:tags":[
        "supply"
    ],
    "wof:name":"Scrapaholix",
    "wof:placetype":"venue"
},
  "geometry": {"coordinates":[150.825317383,-34.5650291443],"type":"Point"}
}