{
  "type": "Feature",
  "properties": {
    "addr:full":"Depot Lot 2 Railway St Coonamble NSW 2829",
    "addr:housenumber":"2",
    "addr:postcode":"2829",
    "addr:street":"Railway St",
    "iso:country":"AU",
    "sg:address":"Depot Lot 2 Railway St",
    "sg:city":"Coonamble",
    "sg:classifiers":[
        {
            "category":"Building & Trades",
            "subcategory":"Construction",
            "type":"Services"
        }
    ],
    "sg:phone":"+61 2 6822 2121",
    "sg:postcode":"2829",
    "sg:province":"NSW",
    "sg:tags":[
        "earth",
        "excavating",
        "moving",
        "contractor"
    ],
    "wof:name":"Chris Newbold Bulk Haulage Pty Ltd",
    "wof:placetype":"venue"
},
  "geometry": {"coordinates":[148.38090515100001,-30.9546718597],"type":"Point"}
}