{
  "type": "Feature",
  "properties": {
    "addr:full":"28 Tolverne St Rochedale South QLD 4123",
    "addr:housenumber":"28",
    "addr:postcode":"4123",
    "addr:street":"Tolverne St",
    "iso:country":"AU",
    "sg:address":"28 Tolverne St",
    "sg:city":"Rochedale South",
    "sg:classifiers":[
        {
            "category":"Education",
            "subcategory":"Music School",
            "type":"Public Place"
        }
    ],
    "sg:phone":"+61 7 3342 5011",
    "sg:postcode":"4123",
    "sg:province":"QLD",
    "sg:tags":[
        "teacher"
    ],
    "wof:name":"Brita Denton",
    "wof:placetype":"venue"
},
  "geometry": {"coordinates":[153.11819457999999,-27.6005516052],"type":"Point"}
}