{
  "type": "Feature",
  "properties": {
    "addr:full":"Shop 22 Lynbrook Village Shopping Centre, Cnr Lynbrook Blv & South Gippsland Hwy Lynbrook VIC 3975",
    "addr:housenumber":"shop 22",
    "addr:postcode":"3975",
    "addr:street":"Village;Cnr Lynbrook Blv & South Gippsland Hwy",
    "iso:country":"AU",
    "sg:address":"Shop 22 Lynbrook Village Shopping Centre, Cnr Lynbrook Blv & South Gippsland Hwy",
    "sg:city":"Lynbrook",
    "sg:classifiers":[
        {
            "category":"Travel",
            "subcategory":"Travel Agent",
            "type":"Entertainment"
        }
    ],
    "sg:phone":"+61 13 18 66",
    "sg:postcode":"3975",
    "sg:province":"VIC",
    "sg:tags":[
        "consultant"
    ],
    "wof:name":"Flight Centre",
    "wof:placetype":"venue"
},
  "geometry": {"coordinates":[145.25318908700001,-38.0530395508],"type":"Point"}
}