{
  "type": "Feature",
  "properties": {
    "addr:full":"67 Channon St Gympie QLD 4570",
    "addr:housenumber":"67",
    "addr:postcode":"4570",
    "addr:street":"Channon St",
    "iso:country":"AU",
    "sg:address":"67 Channon St",
    "sg:city":"Gympie",
    "sg:classifiers":[
        {
            "category":"Health Services",
            "subcategory":"Health Practitioner",
            "type":"Services"
        }
    ],
    "sg:phone":"+61 7 5483 7688",
    "sg:postcode":"4570",
    "sg:province":"QLD",
    "sg:tags":[
        "naturopath"
    ],
    "wof:name":"Cameron Stirling",
    "wof:placetype":"venue"
},
  "geometry": {"coordinates":[152.65711975100001,-26.1858673096],"type":"Point"}
}