{
  "type": "Feature",
  "properties": {
    "iso:country":"AU",
    "sg:address":"6 Williams Ave",
    "sg:city":"Glenelg East",
    "sg:classifiers":[
        {
            "category":"Professional",
            "subcategory":"Management & Consulting",
            "type":"Services"
        }
    ],
    "sg:phone":"+61 8 8294 1583",
    "sg:postcode":"5045",
    "sg:province":"SA",
    "sg:tags":[
        "consultant"
    ],
    "wof:name":"Curkpatrick Management Pty Ltd",
    "wof:placetype":"venue"
},
  "geometry": {"coordinates":[138.52328499999999,-34.98299],"type":"Point"}
}