{
  "type": "Feature",
  "properties": {
    "iso:country":"AU",
    "sg:address":"350 Mt Jack Rd",
    "sg:city":"Brookhill",
    "sg:classifiers":[
        {
            "category":"Building & Trades",
            "subcategory":"Construction",
            "type":"Services"
        }
    ],
    "sg:phone":"+61 417 190 495",
    "sg:postcode":"4816",
    "sg:province":"QLD",
    "sg:tags":[
        "earth",
        "excavating",
        "moving",
        "contractor"
    ],
    "wof:name":"A & S Taylor Excavator Hire",
    "wof:placetype":"venue"
},
  "geometry": {"coordinates":[146.861435,-19.415209],"type":"Point"}
}