{
  "type": "Feature",
  "properties": {
    "addr:full":"Sanders St Korumburra VIC 3950",
    "addr:postcode":"3950",
    "addr:street":"Sanders St",
    "iso:country":"AU",
    "sg:address":"Sanders St",
    "sg:city":"Korumburra",
    "sg:classifiers":[
        {
            "category":"Professional",
            "type":"Services"
        }
    ],
    "sg:phone":"+61 3 5655 1432",
    "sg:postcode":"3950",
    "sg:province":"VIC",
    "sg:tags":[
        "transport"
    ],
    "wof:name":"Moriarty Transport",
    "wof:placetype":"venue"
},
  "geometry": {"coordinates":[145.814163208,-38.4263534546],"type":"Point"}
}