{
  "type": "Feature",
  "properties": {
    "iso:country":"AU",
    "sg:address":"12- 20 Miller St",
    "sg:city":"Brunswick East",
    "sg:classifiers":[
        {
            "category":"Autos & Motor Vehicles",
            "subcategory":"Auto Supplies",
            "type":"Retail Goods"
        }
    ],
    "sg:phone":"+61 3 9387 4133",
    "sg:postcode":"3057",
    "sg:province":"VIC",
    "sg:tags":[
        "transmission",
        "equipment",
        "power"
    ],
    "wof:name":"David Brown John Welsh Custombuild Pty Ltd",
    "wof:placetype":"venue"
},
  "geometry": {"coordinates":[144.97731018100001,-37.7761726379],"type":"Point"}
}