{
  "type": "Feature",
  "properties": {
    "addr:full":"1060 Wellington Rd Narre Warren East VIC 3804",
    "addr:housenumber":"1060",
    "addr:postcode":"3804",
    "addr:street":"Wellington Rd",
    "iso:country":"AU",
    "sg:address":"1060 Wellington Rd",
    "sg:city":"Narre Warren East",
    "sg:classifiers":[
        {
            "category":"Farming",
            "subcategory":"Nursery",
            "type":"Manufacturing & Wholesale Goods"
        }
    ],
    "sg:phone":"+61 3 9796 8308",
    "sg:postcode":"3804",
    "sg:province":"VIC",
    "wof:name":"Speciality Trees",
    "wof:placetype":"venue"
},
  "geometry": {"coordinates":[145.3409729,-37.9519081116],"type":"Point"}
}