{
  "type": "Feature",
  "properties": {
    "iso:country":"AU",
    "sg:address":"604 Kings Georges Rd",
    "sg:city":"Penshurst",
    "sg:classifiers":[
        {
            "category":"Home & Garden",
            "subcategory":"Household Appliances",
            "type":"Retail Goods"
        }
    ],
    "sg:phone":"+61 2 9580 9449",
    "sg:postcode":"2222",
    "sg:province":"NSW",
    "sg:tags":[
        "heating",
        "system"
    ],
    "wof:name":"Bexley Hot Water Repairs",
    "wof:placetype":"venue"
},
  "geometry": {"coordinates":[151.087402344,-33.9569969177],"type":"Point"}
}