{
  "type": "Feature",
  "properties": {
    "addr:full":"195 Corio St Shepparton VIC 3630",
    "addr:housenumber":"195",
    "addr:postcode":"3630",
    "addr:street":"Corio St",
    "iso:country":"AU",
    "sg:address":"195 Corio St",
    "sg:city":"Shepparton",
    "sg:classifiers":[
        {
            "category":"Building & Trades",
            "subcategory":"Locksmith",
            "type":"Services"
        }
    ],
    "sg:phone":"+61 3 5831 7766",
    "sg:postcode":"3630",
    "sg:province":"VIC",
    "sg:tags":[
        "lock"
    ],
    "wof:name":"Shepparton Locksmith Service",
    "wof:placetype":"venue"
},
  "geometry": {"coordinates":[145.40333557100001,-36.3825645447],"type":"Point"}
}