{
  "type": "Feature",
  "properties": {
    "iso:country":"AU",
    "sg:address":"256 Glen Eira Rd",
    "sg:city":"Elsternwick",
    "sg:classifiers":[
        {
            "category":"Restaurant",
            "type":"Food & Drink"
        }
    ],
    "sg:phone":"+61 3 9528 4192",
    "sg:postcode":"3185",
    "sg:province":"VIC",
    "wof:name":"Elsternwick Casual Dining",
    "wof:placetype":"venue"
},
  "geometry": {"coordinates":[145.00785827600001,-37.8782234192],"type":"Point"}
}