{
  "type": "Feature",
  "properties": {
    "addr:full":"7 Victoria St Inglewood QLD 4387",
    "addr:housenumber":"7",
    "addr:postcode":"4387",
    "addr:street":"Victoria St",
    "iso:country":"AU",
    "sg:address":"7 Victoria St",
    "sg:city":"Inglewood",
    "sg:classifiers":[
        {
            "category":"Building & Trades",
            "subcategory":"Construction",
            "type":"Services"
        }
    ],
    "sg:phone":"+61 7 4652 1050",
    "sg:postcode":"4387",
    "sg:province":"QLD",
    "sg:tags":[
        "welding"
    ],
    "wof:name":"BLASK Engineering",
    "wof:placetype":"venue"
},
  "geometry": {"coordinates":[151.082077,-28.411161],"type":"Point"}
}