{
  "type": "Feature",
  "properties": {
    "addr:full":"61 Rushdale St Knoxfield VIC 3180",
    "addr:housenumber":"61",
    "addr:postcode":"3180",
    "addr:street":"Rushdale St",
    "iso:country":"AU",
    "sg:address":"61 Rushdale St",
    "sg:city":"Knoxfield",
    "sg:classifiers":[
        {
            "category":"Health Services",
            "subcategory":"Health Practitioner",
            "type":"Services"
        }
    ],
    "sg:phone":"+61 3 9763 3988",
    "sg:postcode":"3180",
    "sg:province":"VIC",
    "sg:tags":[
        "alternative"
    ],
    "wof:name":"Herli Pacific Pty Ltd",
    "wof:placetype":"venue"
},
  "geometry": {"coordinates":[145.25555419899999,-37.8947677612],"type":"Point"}
}