{
  "type": "Feature",
  "properties": {
    "addr:full":"3 Hymes St Kanimbla QLD 4870",
    "addr:housenumber":"3",
    "addr:postcode":"4870",
    "addr:street":"Hymes St",
    "iso:country":"AU",
    "sg:address":"3 Hymes St",
    "sg:city":"Kanimbla",
    "sg:classifiers":[
        {
            "category":"Home & Garden",
            "subcategory":"Carpets & Floor Coverings",
            "type":"Retail Goods"
        }
    ],
    "sg:phone":"+61 7 4034 2224",
    "sg:postcode":"4870",
    "sg:province":"QLD",
    "sg:tags":[
        "tile",
        "wall",
        "layer"
    ],
    "wof:name":"Bradley JW",
    "wof:placetype":"venue"
},
  "geometry": {"coordinates":[145.72767639200001,-16.9272708893],"type":"Point"}
}