{
  "type": "Feature",
  "properties": {
    "addr:full":"PO Box 316 Gungahlin ACT 2912",
    "addr:postcode":"2912",
    "iso:country":"AU",
    "sg:address":"PO Box 316",
    "sg:city":"Gungahlin",
    "sg:classifiers":[
        {
            "category":"Professional",
            "subcategory":"Art Services",
            "type":"Services"
        }
    ],
    "sg:phone":"+61 419 466 148",
    "sg:postcode":"2912",
    "sg:province":"ACT",
    "sg:tags":[
        "decorator",
        "painter"
    ],
    "wof:name":"Wallys Executive Home",
    "wof:placetype":"venue"
},
  "geometry": {"coordinates":[149.137405395,-35.1838493347],"type":"Point"}
}