{
  "type": "Feature",
  "properties": {
    "iso:country":"AU",
    "sg:address":"1 Surrey Rd",
    "sg:city":"South Yarra",
    "sg:classifiers":[
        {
            "category":"Food & Beverages",
            "subcategory":"Groceries & Convenience Stores",
            "type":"Retail Goods"
        }
    ],
    "sg:phone":"+61 3 9827 8012",
    "sg:postcode":"3141",
    "sg:province":"VIC",
    "wof:name":"Lay T",
    "wof:placetype":"venue"
},
  "geometry": {"coordinates":[144.997924805,-37.8465957642],"type":"Point"}
}