{
  "type": "Feature",
  "properties": {
    "iso:country":"AU",
    "sg:address":"2980 Old Cleveland Rd",
    "sg:city":"Capalaba",
    "sg:classifiers":[
        {
            "category":"Shopping",
            "subcategory":"Bicycles & Sporting Goods",
            "type":"Retail Goods"
        }
    ],
    "sg:phone":"+61 7 3245 7555",
    "sg:postcode":"4157",
    "sg:province":"QLD",
    "sg:tags":[
        "chemical",
        "equipment",
        "pool",
        "swimming"
    ],
    "wof:name":"Swimart Pool & Spa Services",
    "wof:placetype":"venue"
},
  "geometry": {"coordinates":[153.18280029300001,-27.5162200928],"type":"Point"}
}