{
  "type": "Feature",
  "properties": {
    "addr:full":"52 Bultje St Dubbo NSW 2830",
    "addr:housenumber":"52",
    "addr:postcode":"2830",
    "addr:street":"Bultje St",
    "iso:country":"AU",
    "sg:address":"52 Bultje St",
    "sg:city":"Dubbo",
    "sg:classifiers":[
        {
            "category":"Health Services",
            "subcategory":"Doctor",
            "type":"Services"
        }
    ],
    "sg:phone":"+61 2 6882 9900",
    "sg:postcode":"2830",
    "sg:province":"NSW",
    "sg:tags":[
        "medical",
        "practitioner"
    ],
    "wof:name":"Tooth A J Dr",
    "wof:placetype":"venue"
},
  "geometry": {"coordinates":[148.60365295400001,-32.2513160706],"type":"Point"}
}