{
  "type": "Feature",
  "properties": {
    "addr:full":"7 Thalaba Rd New Lambton NSW 2305",
    "addr:housenumber":"7",
    "addr:postcode":"2305",
    "addr:street":"Thalaba Rd",
    "iso:country":"AU",
    "sg:address":"7 Thalaba Rd",
    "sg:city":"New Lambton",
    "sg:classifiers":[
        {
            "category":"Retail",
            "subcategory":"Auto Rental",
            "type":"Services"
        }
    ],
    "sg:phone":"+61 2 4956 1829",
    "sg:postcode":"2305",
    "sg:province":"NSW",
    "sg:tags":[
        "car",
        "wedding"
    ],
    "wof:name":"Classic 56-57 Chevrolet Wedding Cars",
    "wof:placetype":"venue"
},
  "geometry": {"coordinates":[151.71972700000001,-32.921947],"type":"Point"}
}