{
  "type": "Feature",
  "properties": {
    "addr:full":"15 Princes Rd Auburn NSW 2144",
    "addr:housenumber":"15",
    "addr:postcode":"2144",
    "addr:street":"Princes Rd",
    "iso:country":"AU",
    "sg:address":"15 Princes Rd",
    "sg:city":"Auburn",
    "sg:classifiers":[
        {
            "category":"Autos & Motor Vehicles",
            "subcategory":"Auto Supplies",
            "type":"Retail Goods"
        }
    ],
    "sg:phone":"+61 2 9644 4675",
    "sg:postcode":"2144",
    "sg:province":"NSW",
    "sg:tags":[
        "accessory"
    ],
    "wof:name":"Bebco Trading Pty Ltd",
    "wof:placetype":"venue"
},
  "geometry": {"coordinates":[151.023345947,-33.8761558533],"type":"Point"}
}