{
  "type": "Feature",
  "properties": {
    "addr:full":"152 Main Rd Cardiff NSW 2285",
    "addr:housenumber":"152",
    "addr:postcode":"2285",
    "addr:street":"Main Rd",
    "iso:country":"AU",
    "sg:address":"152 Main Rd",
    "sg:city":"Cardiff",
    "sg:classifiers":[
        {
            "category":"Education",
            "subcategory":"Kindergarten",
            "type":"Public Place"
        }
    ],
    "sg:phone":"+61 2 4954 8954",
    "sg:postcode":"2285",
    "sg:province":"NSW",
    "sg:tags":[
        "pre-schools"
    ],
    "wof:name":"Cardiff Community Pre-School",
    "wof:placetype":"venue"
},
  "geometry": {"coordinates":[151.67115783700001,-32.9388198853],"type":"Point"}
}