{
  "type": "Feature",
  "properties": {
    "addr:full":"9/ 6 Macquarie Drv Thomastown VIC 3074",
    "addr:housenumber":"/ 6",
    "addr:postcode":"3074",
    "addr:street":"Macquarie Drv",
    "iso:country":"AU",
    "sg:address":"9/ 6 Macquarie Drv",
    "sg:city":"Thomastown",
    "sg:classifiers":[
        {
            "category":"Retail",
            "subcategory":"Auto Repair",
            "type":"Services"
        }
    ],
    "sg:phone":"+61 3 9465 9344",
    "sg:postcode":"3074",
    "sg:province":"VIC",
    "sg:tags":[
        "clutch",
        "brake"
    ],
    "wof:name":"Bundoora Brake & Clutch Service",
    "wof:placetype":"venue"
},
  "geometry": {"coordinates":[145.033081055,-37.6917877197],"type":"Point"}
}