{
  "type": "Feature",
  "properties": {
    "addr:full":"79 Mary St Gympie QLD 4570",
    "addr:housenumber":"79",
    "addr:postcode":"4570",
    "addr:street":"Mary St",
    "iso:country":"AU",
    "sg:address":"79 Mary St",
    "sg:city":"Gympie",
    "sg:classifiers":[
        {
            "category":"Cafe",
            "type":"Food & Drink"
        }
    ],
    "sg:phone":"+61 7 5482 1368",
    "sg:postcode":"4570",
    "sg:province":"QLD",
    "wof:name":"Brown Jug Cafe The",
    "wof:placetype":"venue"
},
  "geometry": {"coordinates":[152.66331481899999,-26.1900367737],"type":"Point"}
}