{
  "type": "Feature",
  "properties": {
    "addr:full":"52 Spalding Ave Sunshine North VIC 3020",
    "addr:housenumber":"52",
    "addr:postcode":"3020",
    "addr:street":"Spalding Ave",
    "iso:country":"AU",
    "sg:address":"52 Spalding Ave",
    "sg:city":"Sunshine North",
    "sg:classifiers":[
        {
            "category":"Building & Trades",
            "subcategory":"Construction",
            "type":"Services"
        }
    ],
    "sg:phone":"+61 3 9364 3221",
    "sg:postcode":"3020",
    "sg:province":"VIC",
    "sg:tags":[
        "welding"
    ],
    "wof:name":"Perfect Welding",
    "wof:placetype":"venue"
},
  "geometry": {"coordinates":[144.83970600000001,-37.752274],"type":"Point"}
}