{
  "type": "Feature",
  "properties": {
    "iso:country":"AU",
    "sg:address":"168 Avoca Drv",
    "sg:city":"Avoca Beach",
    "sg:classifiers":[
        {
            "category":"Health Services",
            "subcategory":"Health Practitioner",
            "type":"Services"
        }
    ],
    "sg:phone":"+61 2 4382 4567",
    "sg:postcode":"2251",
    "sg:province":"NSW",
    "sg:tags":[
        "physiotherapist"
    ],
    "wof:name":"Avoca Beach Physiotherapy And Sports Injury Clinic",
    "wof:placetype":"venue"
},
  "geometry": {"coordinates":[151.43363952600001,-33.4660644531],"type":"Point"}
}