{
  "type": "Feature",
  "properties": {
    "iso:country":"AU",
    "sg:address":"461 Ocean Drv",
    "sg:city":"Laurieton",
    "sg:classifiers":[
        {
            "category":"Autos & Motor Vehicles",
            "subcategory":"Fuel & Gas Station",
            "type":"Retail Goods"
        }
    ],
    "sg:phone":"+61 2 6559 5888",
    "sg:postcode":"2443",
    "sg:province":"NSW",
    "wof:name":"Caltex Service Station",
    "wof:placetype":"venue"
},
  "geometry": {"coordinates":[152.797913,-31.643763],"type":"Point"}
}