{
  "type": "Feature",
  "properties": {
    "addr:full":"3 Lorikeet Crt Tingira Heights NSW 2290",
    "addr:housenumber":"3",
    "addr:postcode":"2290",
    "addr:street":"Lorikeet Crt",
    "iso:country":"AU",
    "sg:address":"3 Lorikeet Crt",
    "sg:city":"Tingira Heights",
    "sg:classifiers":[
        {
            "category":"Personal",
            "subcategory":"Beauty Salon",
            "type":"Services"
        }
    ],
    "sg:phone":"+61 2 4948 8188",
    "sg:postcode":"2290",
    "sg:province":"NSW",
    "sg:tags":[
        "hairdresser"
    ],
    "wof:name":"Jackies Hair Studio",
    "wof:placetype":"venue"
},
  "geometry": {"coordinates":[151.67155456500001,-32.9907150269],"type":"Point"}
}