{
  "type": "Feature",
  "properties": {
    "iso:country":"AU",
    "sg:address":"PO Box 1296",
    "sg:city":"Gosford",
    "sg:classifiers":[
        {
            "category":"Education",
            "subcategory":"Special Training",
            "type":"Public Place"
        }
    ],
    "sg:phone":"+61 2 4322 3376",
    "sg:postcode":"2250",
    "sg:province":"NSW",
    "sg:tags":[
        "development"
    ],
    "wof:name":"BWAC",
    "wof:placetype":"venue"
},
  "geometry": {"coordinates":[151.34249877900001,-33.4237213135],"type":"Point"}
}