{
  "type": "Feature",
  "properties": {
    "iso:country":"AU",
    "sg:address":"Beaury St",
    "sg:city":"Urbenville",
    "sg:classifiers":[
        {
            "category":"Health Services",
            "subcategory":"Doctor",
            "type":"Services"
        }
    ],
    "sg:phone":"+61 2 6634 1330",
    "sg:postcode":"2475",
    "sg:province":"NSW",
    "sg:tags":[
        "nurse",
        "nursing"
    ],
    "wof:name":"Urbenville & District Hospital Nurses' Home",
    "wof:placetype":"venue"
},
  "geometry": {"coordinates":[152.547073364,-28.472612381],"type":"Point"}
}