{
  "type": "Feature",
  "properties": {
    "iso:country":"AU",
    "sg:address":"Dalton Ave",
    "sg:city":"Aldgate",
    "sg:classifiers":[
        {
            "category":"Sports & Exercise",
            "subcategory":"Sports Center",
            "type":"Entertainment"
        }
    ],
    "sg:phone":"+61 8 8339 5216",
    "sg:postcode":"5154",
    "sg:province":"SA",
    "sg:tags":[
        "coach",
        "tennis"
    ],
    "wof:name":"Kerr G S",
    "wof:placetype":"venue"
},
  "geometry": {"coordinates":[138.74606323200001,-35.0257377625],"type":"Point"}
}