{
  "type": "Feature",
  "properties": {
    "addr:full":"Shp7/ 5 Tallebudgera Creek Rd Burleigh Heads QLD 4220",
    "addr:postcode":"4220",
    "addr:street":"Tallebudgera Creek Rd",
    "iso:country":"AU",
    "sg:address":"Shp7/ 5 Tallebudgera Creek Rd",
    "sg:city":"Burleigh Heads",
    "sg:classifiers":[
        {
            "category":"Education",
            "subcategory":"Music School",
            "type":"Public Place"
        }
    ],
    "sg:phone":"+61 7 5520 0369",
    "sg:postcode":"4220",
    "sg:province":"QLD",
    "sg:tags":[
        "teacher"
    ],
    "wof:name":"Jump In 2 Musik",
    "wof:placetype":"venue"
},
  "geometry": {"coordinates":[153.441116333,-28.1097259521],"type":"Point"}
}