{
  "type": "Feature",
  "properties": {
    "addr:full":"Shop 4A 63 The Crescent Fairfield NSW 2165",
    "addr:housenumber":"shop 4a 63",
    "addr:postcode":"2165",
    "addr:street":"The Crescent",
    "iso:country":"AU",
    "sg:address":"Shop 4A 63 The Crescent",
    "sg:city":"Fairfield",
    "sg:classifiers":[
        {
            "category":"Health Services",
            "subcategory":"Optometrist",
            "type":"Services"
        }
    ],
    "sg:phone":"+61 2 9724 5632",
    "sg:postcode":"2165",
    "sg:province":"NSW",
    "wof:name":"Amaro George, Savidis Anastasios",
    "wof:placetype":"venue"
},
  "geometry": {"coordinates":[150.95631408700001,-33.872127533],"type":"Point"}
}