{
  "type": "Feature",
  "properties": {
    "iso:country":"AU",
    "sg:address":"28 Read St",
    "sg:city":"Blakehurst",
    "sg:classifiers":[
        {
            "category":"Professional",
            "subcategory":"Art Services",
            "type":"Services"
        }
    ],
    "sg:phone":"+61 2 9546 8888",
    "sg:postcode":"2221",
    "sg:province":"NSW",
    "sg:tags":[
        "interior",
        "decorator"
    ],
    "wof:name":"Design Code",
    "wof:placetype":"venue"
},
  "geometry": {"coordinates":[151.10820007300001,-33.9924201965],"type":"Point"}
}