{
  "type": "Feature",
  "properties": {
    "addr:full":"474 A High St Northcote VIC 3070",
    "addr:housenumber":"474 a",
    "addr:postcode":"3070",
    "addr:street":"High St",
    "iso:country":"AU",
    "sg:address":"474 A High St",
    "sg:city":"Northcote",
    "sg:classifiers":[
        {
            "category":"Real Estate",
            "subcategory":"Real Estate Agent",
            "type":"Services"
        }
    ],
    "sg:phone":"+61 3 9486 2000",
    "sg:postcode":"3070",
    "sg:province":"VIC",
    "wof:name":"Collings Real Estate Pty Ltd",
    "wof:placetype":"venue"
},
  "geometry": {"coordinates":[144.998276,-37.772957],"type":"Point"}
}