{
  "type": "Feature",
  "properties": {
    "addr:full":"250 Rae St Fitzroy North VIC 3068",
    "addr:housenumber":"250",
    "addr:postcode":"3068",
    "addr:street":"Rae St",
    "iso:country":"AU",
    "sg:address":"250 Rae St",
    "sg:city":"Fitzroy North",
    "sg:classifiers":[
        {
            "category":"Real Estate",
            "subcategory":"Architect",
            "type":"Services"
        }
    ],
    "sg:phone":"+61 425 726 131",
    "sg:postcode":"3068",
    "sg:province":"VIC",
    "wof:name":"Andrew Maynard Architect",
    "wof:placetype":"venue"
},
  "geometry": {"coordinates":[144.979736328,-37.7864494324],"type":"Point"}
}