{
  "type": "Feature",
  "properties": {
    "addr:full":"5 Palm Beach Ave Palm Beach QLD 4221",
    "addr:housenumber":"5",
    "addr:postcode":"4221",
    "addr:street":"Palm Beach Ave",
    "iso:country":"AU",
    "sg:address":"5 Palm Beach Ave",
    "sg:city":"Palm Beach",
    "sg:classifiers":[
        {
            "category":"Real Estate",
            "subcategory":"Real Estate Agent",
            "type":"Services"
        }
    ],
    "sg:phone":"+61 7 5534 6100",
    "sg:postcode":"4221",
    "sg:province":"QLD",
    "wof:name":"Elders Real Estate Palm Beach",
    "wof:placetype":"venue"
},
  "geometry": {"coordinates":[153.473022461,-28.1207942963],"type":"Point"}
}