{
  "type": "Feature",
  "properties": {
    "addr:full":"207 Narangba Rd Kurwongbah QLD 4503",
    "addr:housenumber":"207",
    "addr:postcode":"4503",
    "addr:street":"Narangba Rd",
    "iso:country":"AU",
    "sg:address":"207 Narangba Rd",
    "sg:city":"Kurwongbah",
    "sg:classifiers":[
        {
            "category":"Building & Trades",
            "subcategory":"Landscaping Services",
            "type":"Services"
        }
    ],
    "sg:phone":"+61 1800 100 223",
    "sg:postcode":"4503",
    "sg:province":"QLD",
    "sg:tags":[
        "stump",
        "tree",
        "felling",
        "removal"
    ],
    "wof:name":"A A-Local Tree Services",
    "wof:placetype":"venue"
},
  "geometry": {"coordinates":[152.97206115700001,-27.2481536865],"type":"Point"}
}