{
  "type": "Feature",
  "properties": {
    "iso:country":"AU",
    "sg:address":"Unit 1/ 36 Jijaws St",
    "sg:city":"Sumner",
    "sg:classifiers":[
        {
            "category":"Manufacturing",
            "subcategory":"Furniture",
            "type":"Manufacturing & Wholesale Goods"
        }
    ],
    "sg:phone":"+61 7 3712 0061",
    "sg:postcode":"4074",
    "sg:province":"QLD",
    "sg:tags":[
        "builder",
        "designer",
        "custom"
    ],
    "wof:name":"Beinke Upholstery Services Repair Restore Recover",
    "wof:placetype":"venue"
},
  "geometry": {"coordinates":[152.939453125,-27.5635147095],"type":"Point"}
}