{
  "type": "Feature",
  "properties": {
    "addr:full":"6 Production St Noosaville QLD 4566",
    "addr:housenumber":"6",
    "addr:postcode":"4566",
    "addr:street":"Production St",
    "iso:country":"AU",
    "sg:address":"6 Production St",
    "sg:city":"Noosaville",
    "sg:classifiers":[
        {
            "category":"Autos & Motor Vehicles",
            "subcategory":"Boat Sales",
            "type":"Retail Goods"
        }
    ],
    "sg:phone":"+61 7 5449 8888",
    "sg:postcode":"4566",
    "sg:province":"QLD",
    "sg:tags":[
        "yacht"
    ],
    "wof:name":"Noosa Cat Australia Pty Ltd",
    "wof:placetype":"venue"
},
  "geometry": {"coordinates":[153.04513549800001,-26.4151878357],"type":"Point"}
}