{
  "type": "Feature",
  "properties": {
    "addr:full":"42 Fullwood St Sunbury VIC 3429",
    "addr:housenumber":"42",
    "addr:postcode":"3429",
    "addr:street":"Fullwood St",
    "iso:country":"AU",
    "sg:address":"42 Fullwood St",
    "sg:city":"Sunbury",
    "sg:classifiers":[
        {
            "category":"Utilities",
            "type":"Services"
        }
    ],
    "sg:phone":"+61 3 9379 7769",
    "sg:postcode":"3429",
    "sg:province":"VIC",
    "sg:tags":[
        "refrigeration",
        "industrial",
        "commercial",
        "retail"
    ],
    "wof:name":"M.P. Angus Refrigeration Pty Ltd",
    "wof:placetype":"venue"
},
  "geometry": {"coordinates":[144.70066833499999,-37.5668258667],"type":"Point"}
}