{
  "type": "Feature",
  "properties": {
    "iso:country":"AU",
    "sg:address":"10 Whalley Crt",
    "sg:city":"Doncaster East",
    "sg:classifiers":[
        {
            "category":"Building & Trades",
            "subcategory":"Plumbing",
            "type":"Services"
        }
    ],
    "sg:phone":"+61 3 9722 2244",
    "sg:postcode":"3109",
    "sg:province":"VIC",
    "sg:tags":[
        "plumber",
        "gasfitters"
    ],
    "wof:name":"Lower Templestowe Plumbing",
    "wof:placetype":"venue"
},
  "geometry": {"coordinates":[145.14422607399999,-37.795124054],"type":"Point"}
}