{
  "type": "Feature",
  "properties": {
    "iso:country":"AU",
    "sg:address":"234 Toorak Rd",
    "sg:city":"South Yarra",
    "sg:classifiers":[
        {
            "category":"Fast Food",
            "type":"Food & Drink"
        }
    ],
    "sg:phone":"+61 3 9826 9155",
    "sg:postcode":"3141",
    "sg:province":"VIC",
    "sg:tags":[
        "away",
        "take"
    ],
    "wof:name":"Wok 234",
    "wof:placetype":"venue"
},
  "geometry": {"coordinates":[144.99493408199999,-37.8395080566],"type":"Point"}
}