{
  "type": "Feature",
  "properties": {
    "iso:country":"AU",
    "sg:address":"389 Newman Rd",
    "sg:city":"Geebung",
    "sg:classifiers":[
        {
            "category":"Manufacturing",
            "subcategory":"Printing",
            "type":"Manufacturing & Wholesale Goods"
        }
    ],
    "sg:phone":"+61 7 3865 1555",
    "sg:postcode":"4034",
    "sg:province":"QLD",
    "sg:tags":[
        "wholesaler",
        "mfrs",
        "greeting",
        "card"
    ],
    "wof:name":"Fred Hosking Pty Ltd",
    "wof:placetype":"venue"
},
  "geometry": {"coordinates":[153.048325,-27.367449],"type":"Point"}
}