{
  "type": "Feature",
  "properties": {
    "addr:full":"389 Newman Rd Geebung QLD 4034",
    "addr:housenumber":"389",
    "addr:postcode":"4034",
    "addr:street":"Newman Rd",
    "iso:country":"AU",
    "sg:address":"389 Newman Rd",
    "sg:city":"Geebung",
    "sg:classifiers":[
        {
            "category":"Manufacturing",
            "subcategory":"Printing",
            "type":"Manufacturing & Wholesale Goods"
        }
    ],
    "sg:phone":"+61 7 3865 1555",
    "sg:postcode":"4034",
    "sg:province":"QLD",
    "sg:tags":[
        "wholesaler",
        "mfrs",
        "greeting",
        "card"
    ],
    "wof:name":"Fred Hosking Pty Ltd",
    "wof:placetype":"venue"
},
  "geometry": {"coordinates":[153.04832500000001,-27.367449],"type":"Point"}
}