{
  "type": "Feature",
  "properties": {
    "addr:full":"12 Antill St Yennora NSW 2161",
    "addr:housenumber":"12",
    "addr:postcode":"2161",
    "addr:street":"Antill St",
    "iso:country":"AU",
    "sg:address":"12 Antill St",
    "sg:city":"Yennora",
    "sg:classifiers":[
        {
            "category":"Autos & Motor Vehicles",
            "subcategory":"Auto Supplies",
            "type":"Retail Goods"
        }
    ],
    "sg:phone":"+61 2 9892 4666",
    "sg:postcode":"2161",
    "sg:province":"NSW",
    "sg:tags":[
        "accessory"
    ],
    "wof:name":"A1 Roof Racks",
    "wof:placetype":"venue"
},
  "geometry": {"coordinates":[150.977615356,-33.8635673523],"type":"Point"}
}