{
  "type": "Feature",
  "properties": {
    "addr:full":"122 Kinabalu Drv Eagle Heights QLD 4271",
    "addr:housenumber":"122",
    "addr:postcode":"4271",
    "addr:street":"Kinabalu Drv Eagle Heights",
    "iso:country":"AU",
    "sg:address":"122 Kinabalu Drv",
    "sg:city":"Eagle Heights",
    "sg:classifiers":[
        {
            "category":"Military Area",
            "subcategory":"Air Force Base",
            "type":"Public Place"
        }
    ],
    "sg:phone":"+61 7 5545 1320",
    "sg:postcode":"4271",
    "sg:province":"QLD",
    "sg:tags":[
        "pole",
        "lighting",
        "power"
    ],
    "wof:name":"Underground Mains & Property Poles",
    "wof:placetype":"venue"
},
  "geometry": {"coordinates":[153.20401000999999,-27.904592514],"type":"Point"}
}