{
  "type": "Feature",
  "properties": {
    "addr:full":"42 Havelock St Mayfield NSW 2304",
    "addr:housenumber":"42",
    "addr:postcode":"2304",
    "addr:street":"Havelock St",
    "iso:country":"AU",
    "sg:address":"42 Havelock St",
    "sg:city":"Mayfield",
    "sg:classifiers":[
        {
            "category":"Health Services",
            "subcategory":"Health Practitioner",
            "type":"Services"
        }
    ],
    "sg:phone":"+61 2 4960 8049",
    "sg:postcode":"2304",
    "sg:province":"NSW",
    "sg:tags":[
        "psychotherapist"
    ],
    "wof:name":"A Absolutely Confidential Counselling Consultants",
    "wof:placetype":"venue"
},
  "geometry": {"coordinates":[151.74346923799999,-32.8986244202],"type":"Point"}
}