{
  "type": "Feature",
  "properties": {
    "addr:full":"134 Gladstone St Fyshwick ACT 2609",
    "addr:housenumber":"134",
    "addr:postcode":"2609",
    "addr:street":"Gladstone St",
    "iso:country":"AU",
    "sg:address":"134 Gladstone St",
    "sg:city":"Fyshwick",
    "sg:classifiers":[
        {
            "category":"Manufacturing",
            "subcategory":"Furniture",
            "type":"Manufacturing & Wholesale Goods"
        }
    ],
    "sg:phone":"+61 2 6280 7798",
    "sg:postcode":"2609",
    "sg:province":"ACT",
    "sg:tags":[
        "builder",
        "designer",
        "custom"
    ],
    "wof:name":"Decor Living",
    "wof:placetype":"venue"
},
  "geometry": {"coordinates":[149.182907105,-35.3248023987],"type":"Point"}
}