{
  "type": "Feature",
  "properties": {
    "addr:full":"24 Badgery Ave Strathfield NSW 2135",
    "addr:housenumber":"24",
    "addr:postcode":"2135",
    "addr:street":"Badgery Ave",
    "iso:country":"AU",
    "sg:address":"24 Badgery Ave",
    "sg:city":"Strathfield",
    "sg:classifiers":[
        {
            "category":"Professional",
            "subcategory":"Business Services",
            "type":"Services"
        }
    ],
    "sg:phone":"+61 409 042 625",
    "sg:postcode":"2135",
    "sg:province":"NSW",
    "sg:tags":[
        "exporter"
    ],
    "wof:name":"Ultra Suppliers Pty Ltd",
    "wof:placetype":"venue"
},
  "geometry": {"coordinates":[151.07499694800001,-33.8692817688],"type":"Point"}
}