{
  "type": "Feature",
  "properties": {
    "addr:full":"52 Blenheim St Croydon Park NSW 2133",
    "addr:housenumber":"52",
    "addr:postcode":"2133",
    "addr:street":"Blenheim St",
    "iso:country":"AU",
    "sg:address":"52 Blenheim St",
    "sg:city":"Croydon Park",
    "sg:classifiers":[
        {
            "category":"Professional",
            "subcategory":"Business Services",
            "type":"Services"
        }
    ],
    "sg:phone":"+61 2 9642 4910",
    "sg:postcode":"2133",
    "sg:province":"NSW",
    "sg:tags":[
        "drafting"
    ],
    "wof:name":"A.F.D.",
    "wof:placetype":"venue"
},
  "geometry": {"coordinates":[151.09185790999999,-33.8989715576],"type":"Point"}
}