{
  "type": "Feature",
  "properties": {
    "addr:full":"15 Edgecliff Rd Bondi Junction NSW 2022",
    "addr:housenumber":"15",
    "addr:postcode":"2022",
    "addr:street":"Edgecliff Rd",
    "iso:country":"AU",
    "sg:address":"15 Edgecliff Rd",
    "sg:city":"Bondi Junction",
    "sg:classifiers":[
        {
            "category":"Health Services",
            "subcategory":"Dentist",
            "type":"Services"
        }
    ],
    "sg:phone":"+61 2 9387 7821",
    "sg:postcode":"2022",
    "sg:province":"NSW",
    "wof:name":"Deverall William R",
    "wof:placetype":"venue"
},
  "geometry": {"coordinates":[151.25531005900001,-33.8892555237],"type":"Point"}
}