{
  "type": "Feature",
  "properties": {
    "addr:full":"Kubbine Rd Kubbine WA 6308",
    "addr:postcode":"6308",
    "addr:street":"Kubbine Rd",
    "iso:country":"AU",
    "sg:address":"Kubbine Rd",
    "sg:city":"Kubbine",
    "sg:classifiers":[
        {
            "category":"Farming",
            "subcategory":"Farm",
            "type":"Manufacturing & Wholesale Goods"
        }
    ],
    "sg:phone":"+61 8 9887 6021",
    "sg:postcode":"6308",
    "sg:province":"WA",
    "sg:tags":[
        "farmer"
    ],
    "wof:name":"Salau A F & V",
    "wof:placetype":"venue"
},
  "geometry": {"coordinates":[116.818687439,-32.5420875549],"type":"Point"}
}