{
  "type": "Feature",
  "properties": {
    "iso:country":"AU",
    "sg:address":"12 Budgeree Rd",
    "sg:city":"Toongabbie",
    "sg:classifiers":[
        {
            "category":"Professional",
            "subcategory":"Computer Services",
            "type":"Services"
        }
    ],
    "sg:phone":"+61 2 9631 2323",
    "sg:postcode":"2146",
    "sg:province":"NSW",
    "sg:tags":[
        "repairs",
        "upgrade",
        "equipment"
    ],
    "wof:name":"Computers Today",
    "wof:placetype":"venue"
},
  "geometry": {"coordinates":[150.953048706,-33.7921104431],"type":"Point"}
}