{
  "type": "Feature",
  "properties": {
    "addr:full":"Shop 1, 50 Wrights Rd Kellyville NSW 2153",
    "addr:housenumber":"shop;50",
    "addr:postcode":"2153",
    "addr:street":"Wrights Rd",
    "iso:country":"AU",
    "sg:address":"Shop 1, 50 Wrights Rd",
    "sg:city":"Kellyville",
    "sg:classifiers":[
        {
            "category":"Real Estate",
            "subcategory":"Real Estate Agent",
            "type":"Services"
        }
    ],
    "sg:phone":"+61 2 9899 3311",
    "sg:postcode":"2153",
    "sg:province":"NSW",
    "wof:name":"Elders Gilmour",
    "wof:placetype":"venue"
},
  "geometry": {"coordinates":[150.97543335,-33.7134094238],"type":"Point"}
}