{
  "type": "Feature",
  "properties": {
    "iso:country":"AU",
    "sg:address":"Unit 5/ 81 Stephen Rd",
    "sg:city":"Botany",
    "sg:classifiers":[
        {
            "category":"Building & Trades",
            "subcategory":"Construction",
            "type":"Services"
        }
    ],
    "sg:phone":"+61 2 9316 9713",
    "sg:postcode":"2019",
    "sg:province":"NSW",
    "sg:tags":[
        "contractor"
    ],
    "wof:name":"KHP Constructions",
    "wof:placetype":"venue"
},
  "geometry": {"coordinates":[151.208450317,-33.9536781311],"type":"Point"}
}