{
  "type": "Feature",
  "properties": {
    "iso:country":"AU",
    "sg:address":"Fawthrop St",
    "sg:city":"Portland",
    "sg:classifiers":[
        {
            "category":"Education",
            "subcategory":"Kindergarten",
            "type":"Public Place"
        }
    ],
    "sg:phone":"+61 3 5523 1084",
    "sg:postcode":"3305",
    "sg:province":"VIC",
    "sg:tags":[
        "pre-schools"
    ],
    "wof:name":"Portland Pre-School",
    "wof:placetype":"venue"
},
  "geometry": {"coordinates":[141.594406128,-38.3543968201],"type":"Point"}
}