{
  "type": "Feature",
  "properties": {
    "iso:country":"AU",
    "sg:address":"31 Staple St",
    "sg:city":"Seventeen Mile Rocks",
    "sg:classifiers":[
        {
            "category":"Building & Trades",
            "subcategory":"Construction",
            "type":"Services"
        }
    ],
    "sg:phone":"+61 7 3376 4044",
    "sg:postcode":"4073",
    "sg:province":"QLD",
    "sg:tags":[
        "contractor"
    ],
    "wof:name":"Hutchinson Builders",
    "wof:placetype":"venue"
},
  "geometry": {"coordinates":[152.95433044399999,-27.5427742004],"type":"Point"}
}