{
  "type": "Feature",
  "properties": {
    "addr:full":"50 Bennet St Dandenong VIC 3175",
    "addr:housenumber":"50",
    "addr:postcode":"3175",
    "addr:street":"Bennet St",
    "iso:country":"AU",
    "sg:address":"50 Bennet St",
    "sg:city":"Dandenong",
    "sg:classifiers":[
        {
            "category":"Wholesale",
            "subcategory":"Auto Parts",
            "type":"Manufacturing & Wholesale Goods"
        }
    ],
    "sg:phone":"+61 3 9794 6565",
    "sg:postcode":"3175",
    "sg:province":"VIC",
    "sg:tags":[
        "recyclers"
    ],
    "wof:name":"Dandy Spares & Repairs",
    "wof:placetype":"venue"
},
  "geometry": {"coordinates":[145.19906616200001,-37.9884910583],"type":"Point"}
}