{
  "type": "Feature",
  "properties": {
    "iso:country":"AU",
    "sg:address":"167a High St",
    "sg:city":"Belmont",
    "sg:classifiers":[
        {
            "category":"Professional",
            "subcategory":"Employment Agencies",
            "type":"Services"
        }
    ],
    "sg:phone":"+61 3 5241 6188",
    "sg:postcode":"3216",
    "sg:province":"VIC",
    "sg:tags":[
        "provider",
        "internet"
    ],
    "wof:name":"Sunet Internet",
    "wof:placetype":"venue"
},
  "geometry": {"coordinates":[144.343185425,-38.1748313904],"type":"Point"}
}