{
  "type": "Feature",
  "properties": {
    "iso:country":"AU",
    "sg:address":"70 Barkers Rd",
    "sg:city":"Hawthorn",
    "sg:classifiers":[
        {
            "category":"Fast Food",
            "type":"Food & Drink"
        }
    ],
    "sg:phone":"+61 3 9853 2222",
    "sg:postcode":"3122",
    "sg:province":"VIC",
    "sg:tags":[
        "away",
        "take"
    ],
    "wof:name":"Lina's Pizza",
    "wof:placetype":"venue"
},
  "geometry": {"coordinates":[145.02264404300001,-37.813129425],"type":"Point"}
}