{
  "type": "Feature",
  "properties": {
    "addr:full":"162 Commercial Rd Koroit VIC 3282",
    "addr:housenumber":"162",
    "addr:postcode":"3282",
    "addr:street":"Commercial Rd",
    "iso:country":"AU",
    "sg:address":"162 Commercial Rd",
    "sg:city":"Koroit",
    "sg:classifiers":[
        {
            "category":"Shopping",
            "subcategory":"Antiques",
            "type":"Retail Goods"
        }
    ],
    "sg:phone":"+61 3 5565 8078",
    "sg:postcode":"3282",
    "sg:province":"VIC",
    "sg:tags":[
        "restoration",
        "reproduction"
    ],
    "wof:name":"Southern Cross Relics",
    "wof:placetype":"venue"
},
  "geometry": {"coordinates":[142.362884522,-38.2914848328],"type":"Point"}
}