{
  "type": "Feature",
  "properties": {
    "iso:country":"AU",
    "sg:address":"471 Little Bourke St",
    "sg:city":"Melbourne",
    "sg:classifiers":[
        {
            "category":"Conference Center",
            "type":"Public Place"
        }
    ],
    "sg:phone":"+61 3 9607 3000",
    "sg:postcode":"3000",
    "sg:province":"VIC",
    "sg:tags":[
        "venue",
        "convention"
    ],
    "wof:name":"Pacific International Suites Melbourne",
    "wof:placetype":"venue"
},
  "geometry": {"coordinates":[144.95903015100001,-37.8144607544],"type":"Point"}
}