{
  "type": "Feature",
  "properties": {
    "addr:full":"Medical Centre Sparkes Rd Bray Park QLD 4500",
    "addr:postcode":"4500",
    "addr:street":"Sparkes Rd",
    "iso:country":"AU",
    "sg:address":"Medical Centre Sparkes Rd",
    "sg:city":"Bray Park",
    "sg:classifiers":[
        {
            "category":"Health Services",
            "subcategory":"Health Practitioner",
            "type":"Services"
        }
    ],
    "sg:phone":"+61 7 3889 6233",
    "sg:postcode":"4500",
    "sg:province":"QLD",
    "sg:tags":[
        "physiotherapist"
    ],
    "wof:name":"Arrow Leanne",
    "wof:placetype":"venue"
},
  "geometry": {"coordinates":[152.968063355,-27.2966804504],"type":"Point"}
}