{
  "type": "Feature",
  "properties": {
    "addr:full":"25 Dural Rd Dural NSW 2158",
    "addr:housenumber":"25",
    "addr:postcode":"2158",
    "addr:street":"Dural Rd",
    "iso:country":"AU",
    "sg:address":"25 Dural Rd",
    "sg:city":"Dural",
    "sg:classifiers":[
        {
            "category":"Autos & Motor Vehicles",
            "subcategory":"Automobile Sales",
            "type":"Retail Goods"
        }
    ],
    "sg:phone":"+61 2 8215 0516",
    "sg:postcode":"2158",
    "sg:province":"NSW",
    "sg:tags":[
        "car",
        "new"
    ],
    "wof:name":"A 1 Car Brokers",
    "wof:placetype":"venue"
},
  "geometry": {"coordinates":[151.09393310600001,-33.7023277283],"type":"Point"}
}