{
  "type": "Feature",
  "properties": {
    "iso:country":"AU",
    "sg:address":"61 Lomas La",
    "sg:city":"Lovedale",
    "sg:classifiers":[
        {
            "category":"Real Estate",
            "subcategory":"Architect",
            "type":"Services"
        }
    ],
    "sg:phone":"+61 412 690 790",
    "sg:postcode":"2325",
    "sg:province":"NSW",
    "sg:tags":[
        "building",
        "designer"
    ],
    "wof:name":"G.J Gilmour Pty Ltd",
    "wof:placetype":"venue"
},
  "geometry": {"coordinates":[151.35716247600001,-32.7943344116],"type":"Point"}
}