{
  "type": "Feature",
  "properties": {
    "addr:full":"748 High St Epping VIC 3076",
    "addr:housenumber":"748",
    "addr:postcode":"3076",
    "addr:street":"High St",
    "iso:country":"AU",
    "sg:address":"748 High St",
    "sg:city":"Epping",
    "sg:classifiers":[
        {
            "category":"Professional",
            "subcategory":"Employment Agencies",
            "type":"Services"
        }
    ],
    "sg:phone":"+61 3 9401 2455",
    "sg:postcode":"3076",
    "sg:province":"VIC",
    "wof:name":"Job Futures",
    "wof:placetype":"venue"
},
  "geometry": {"coordinates":[145.01344299300001,-37.854675293],"type":"Point"}
}