{
  "type": "Feature",
  "properties": {
    "iso:country":"AU",
    "sg:address":"19 Dibar Drv",
    "sg:city":"Tamworth",
    "sg:classifiers":[
        {
            "category":"Utilities",
            "subcategory":"Electric",
            "type":"Services"
        }
    ],
    "sg:phone":"+61 427 754 397",
    "sg:postcode":"2340",
    "sg:province":"NSW",
    "sg:tags":[
        "electrical",
        "contractor"
    ],
    "wof:name":"Kevin Mackey Electrical",
    "wof:placetype":"venue"
},
  "geometry": {"coordinates":[150.90606689399999,-31.1190433502],"type":"Point"}
}