{
  "type": "Feature",
  "properties": {
    "iso:country":"AU",
    "sg:address":"The F.K.I Campus 1 Feodore St",
    "sg:city":"Caulfield South",
    "sg:classifiers":[
        {
            "category":"Education",
            "subcategory":"School",
            "type":"Public Place"
        }
    ],
    "sg:phone":"+61 3 9834 0090",
    "sg:postcode":"3162",
    "sg:province":"VIC",
    "sg:tags":[
        "co-educational"
    ],
    "wof:name":"Mount Scopus Memorial College",
    "wof:placetype":"venue"
},
  "geometry": {"coordinates":[145.034225464,-37.8994789124],"type":"Point"}
}