{
  "type": "Feature",
  "properties": {
    "addr:full":"Rear Of 630 Bourke Rd Camberwell VIC 3124",
    "addr:housenumber":"rear;630",
    "addr:postcode":"3124",
    "addr:street":"Bourke Rd",
    "iso:country":"AU",
    "sg:address":"Rear Of 630 Bourke Rd",
    "sg:city":"Camberwell",
    "sg:classifiers":[
        {
            "category":"Shopping",
            "subcategory":"Baby Store",
            "type":"Retail Goods"
        }
    ],
    "sg:phone":"+61 3 9882 3299",
    "sg:postcode":"3124",
    "sg:province":"VIC",
    "sg:tags":[
        "children's",
        "wear"
    ],
    "wof:name":"Kids Stop",
    "wof:placetype":"venue"
},
  "geometry": {"coordinates":[145.057250977,-37.8292694092],"type":"Point"}
}