{
  "type": "Feature",
  "properties": {
    "iso:country":"AU",
    "sg:address":"32 Arnold St",
    "sg:city":"Box Hill",
    "sg:classifiers":[
        {
            "category":"Health Services",
            "subcategory":"Health Practitioner",
            "type":"Services"
        }
    ],
    "sg:phone":"+61 409 552 665",
    "sg:postcode":"3128",
    "sg:province":"VIC",
    "sg:tags":[
        "psychotherapist"
    ],
    "wof:name":"Jenny Carver",
    "wof:placetype":"venue"
},
  "geometry": {"coordinates":[145.115844727,-37.8138275146],"type":"Point"}
}