{
  "type": "Feature",
  "properties": {
    "addr:full":"Challis Rd Cairlocup WA 6343",
    "addr:postcode":"6343",
    "addr:street":"Challis Rd",
    "iso:country":"AU",
    "sg:address":"Challis Rd",
    "sg:city":"Cairlocup",
    "sg:classifiers":[
        {
            "category":"Farming",
            "subcategory":"Farm",
            "type":"Manufacturing & Wholesale Goods"
        }
    ],
    "sg:phone":"+61 8 9820 4042",
    "sg:postcode":"6343",
    "sg:province":"WA",
    "sg:tags":[
        "farmer"
    ],
    "wof:name":"O&#039;Halloran W S & K A",
    "wof:placetype":"venue"
},
  "geometry": {"coordinates":[118.77298,-33.580647],"type":"Point"}
}