{
  "type": "Feature",
  "properties": {
    "addr:full":"Suite 2, 74 Willoughby Rd Crows Nest NSW 2065",
    "addr:housenumber":"74",
    "addr:postcode":"2065",
    "addr:street":"Willoughby Rd",
    "iso:country":"AU",
    "sg:address":"Suite 2, 74 Willoughby Rd",
    "sg:city":"Crows Nest",
    "sg:classifiers":[
        {
            "category":"Health Services",
            "subcategory":"Health Practitioner",
            "type":"Services"
        }
    ],
    "sg:phone":"+61 2 9460 7091",
    "sg:postcode":"2065",
    "sg:province":"NSW",
    "sg:tags":[
        "psychotherapist"
    ],
    "wof:name":"Centre Of Therapy, Bodywork & Yoga",
    "wof:placetype":"venue"
},
  "geometry": {"coordinates":[151.200714111,-33.8253326416],"type":"Point"}
}