{
  "type": "Feature",
  "properties": {
    "iso:country":"AU",
    "sg:address":"5 Hill St",
    "sg:city":"Corrigin",
    "sg:classifiers":[
        {
            "category":"Utilities",
            "subcategory":"Cable",
            "type":"Services"
        }
    ],
    "sg:phone":"+61 8 9063 2242",
    "sg:postcode":"6375",
    "sg:province":"WA",
    "sg:tags":[
        "agricultural",
        "aerial"
    ],
    "wof:name":"Mallee Aviation",
    "wof:placetype":"venue"
},
  "geometry": {"coordinates":[117.877487,-32.325718],"type":"Point"}
}