{
  "type": "Feature",
  "properties": {
    "addr:full":"\"Bimdadeen\" Homestead Rd Pittsworth QLD 4356",
    "addr:postcode":"4356",
    "addr:street":"Homestead Rd",
    "iso:country":"AU",
    "sg:address":"\"Bimdadeen\" Homestead Rd",
    "sg:city":"Pittsworth",
    "sg:classifiers":[
        {
            "category":"Farming",
            "subcategory":"Farm",
            "type":"Manufacturing & Wholesale Goods"
        }
    ],
    "sg:phone":"+61 7 4693 1530",
    "sg:postcode":"4356",
    "sg:province":"QLD",
    "sg:tags":[
        "farmer"
    ],
    "wof:name":"Postle G H & P J",
    "wof:placetype":"venue"
},
  "geometry": {"coordinates":[151.67335499999999,-27.781351],"type":"Point"}
}