{
  "type": "Feature",
  "properties": {
    "iso:country":"AU",
    "sg:address":"2 Driftwood Ave",
    "sg:city":"Byron Bay",
    "sg:classifiers":[
        {
            "category":"Building & Trades",
            "subcategory":"Construction",
            "type":"Services"
        }
    ],
    "sg:phone":"+61 2 6685 8422",
    "sg:postcode":"2481",
    "sg:province":"NSW",
    "sg:tags":[
        "contractor"
    ],
    "wof:name":"Mazzer F H",
    "wof:placetype":"venue"
},
  "geometry": {"coordinates":[153.620162964,-28.6592006683],"type":"Point"}
}