{
  "type": "Feature",
  "properties": {
    "addr:full":"1/ 107 Stirling Hwy North Fremantle WA 6159",
    "addr:housenumber":"/ 107",
    "addr:postcode":"6159",
    "addr:street":"Stirling Hwy",
    "iso:country":"AU",
    "sg:address":"1/ 107 Stirling Hwy",
    "sg:city":"North Fremantle",
    "sg:classifiers":[
        {
            "category":"Real Estate",
            "subcategory":"Architect",
            "type":"Services"
        }
    ],
    "sg:phone":"+61 8 9336 2856",
    "sg:postcode":"6159",
    "sg:province":"WA",
    "wof:name":"McCann Gerard",
    "wof:placetype":"venue"
},
  "geometry": {"coordinates":[115.752731,-32.031208],"type":"Point"}
}