{
  "type": "Feature",
  "properties": {
    "addr:full":"2 In St Tamworth NSW 2340",
    "addr:postcode":"2340",
    "addr:street":"St",
    "iso:country":"AU",
    "sg:address":"2 In St",
    "sg:city":"Tamworth",
    "sg:classifiers":[
        {
            "category":"Farming",
            "subcategory":"Farm & Veterinary Services",
            "type":"Manufacturing & Wholesale Goods"
        }
    ],
    "sg:phone":"+61 2 6762 7720",
    "sg:postcode":"2340",
    "sg:province":"NSW",
    "sg:tags":[
        "poultry",
        "processing",
        "supply"
    ],
    "wof:name":"Elmsleigh Poultry Transport",
    "wof:placetype":"venue"
},
  "geometry": {"coordinates":[150.91365051299999,-31.0934638977],"type":"Point"}
}