{
  "type": "Feature",
  "properties": {
    "addr:full":"113 Fletcher St Adamstown NSW 2289",
    "addr:housenumber":"113",
    "addr:postcode":"2289",
    "addr:street":"Fletcher St",
    "iso:country":"AU",
    "sg:address":"113 Fletcher St",
    "sg:city":"Adamstown",
    "sg:classifiers":[
        {
            "category":"Social Services",
            "subcategory":"Adult Care",
            "type":"Services"
        }
    ],
    "sg:phone":"+61 2 4941 4000",
    "sg:postcode":"2289",
    "sg:province":"NSW",
    "sg:tags":[
        "towing"
    ],
    "wof:name":"Hayes Peter",
    "wof:placetype":"venue"
},
  "geometry": {"coordinates":[151.714309692,-32.938457489],"type":"Point"}
}