{
  "type": "Feature",
  "properties": {
    "iso:country":"AU",
    "sg:address":"49b Central Rd",
    "sg:city":"Rossmoyne",
    "sg:classifiers":[
        {
            "category":"Government",
            "subcategory":"Post Office",
            "type":"Public Place"
        }
    ],
    "sg:phone":"+61 8 9457 2391",
    "sg:postcode":"6148",
    "sg:province":"WA",
    "sg:tags":[
        "postal"
    ],
    "wof:name":"Australia Post",
    "wof:placetype":"venue"
},
  "geometry": {"coordinates":[115.867439,-32.038452],"type":"Point"}
}