{
  "type": "Feature",
  "properties": {
    "iso:country":"AU",
    "sg:address":"2/ 90 Central Ave",
    "sg:city":"Derwent Park",
    "sg:classifiers":[
        {
            "category":"Building & Trades",
            "subcategory":"Cleaning & Sanitation",
            "type":"Services"
        }
    ],
    "sg:phone":"+61 438 130 060",
    "sg:postcode":"7009",
    "sg:province":"TAS",
    "sg:tags":[
        "window"
    ],
    "wof:name":"A & R Northern Cleaners (Tasmania) Pty Ltd",
    "wof:placetype":"venue"
},
  "geometry": {"coordinates":[147.301681519,-42.8381118774],"type":"Point"}
}