{
  "type": "Feature",
  "properties": {
    "addr:full":"24 Mckenzie St Mowbray TAS 7248",
    "addr:housenumber":"24",
    "addr:postcode":"7248",
    "addr:street":"Mckenzie St",
    "iso:country":"AU",
    "sg:address":"24 Mckenzie St",
    "sg:city":"Mowbray",
    "sg:classifiers":[
        {
            "category":"Retail",
            "subcategory":"Auto Repair",
            "type":"Services"
        }
    ],
    "sg:phone":"+61 3 6326 9980",
    "sg:postcode":"7248",
    "sg:province":"TAS",
    "sg:tags":[
        "electrical"
    ],
    "wof:name":"Sparkys Auto Electrical",
    "wof:placetype":"venue"
},
  "geometry": {"coordinates":[147.13352966299999,-41.4098167419],"type":"Point"}
}