{
  "type": "Feature",
  "properties": {
    "iso:country":"AU",
    "sg:address":"Shop 5 20-22 Ranelagh Drv",
    "sg:city":"Mt Eliza",
    "sg:classifiers":[
        {
            "category":"Professional",
            "subcategory":"Computer Services",
            "type":"Services"
        }
    ],
    "sg:phone":"+61 3 9787 6711",
    "sg:postcode":"3930",
    "sg:province":"VIC",
    "sg:tags":[
        "repairs",
        "upgrade",
        "equipment"
    ],
    "wof:name":"Village PC",
    "wof:placetype":"venue"
},
  "geometry": {"coordinates":[145.088012695,-38.1843338013],"type":"Point"}
}