{
  "type": "Feature",
  "properties": {
    "addr:full":"58- 60 Burke St Wangaratta VIC 3677",
    "addr:housenumber":"60",
    "addr:postcode":"3677",
    "addr:street":"Burke St",
    "iso:country":"AU",
    "sg:address":"58- 60 Burke St",
    "sg:city":"Wangaratta",
    "sg:classifiers":[
        {
            "category":"Education",
            "subcategory":"Kindergarten",
            "type":"Public Place"
        }
    ],
    "sg:phone":"+61 3 5721 2319",
    "sg:postcode":"3677",
    "sg:province":"VIC",
    "sg:tags":[
        "pre-schools"
    ],
    "wof:name":"James Tilson Kindergarten",
    "wof:placetype":"venue"
},
  "geometry": {"coordinates":[146.316772461,-36.3722267151],"type":"Point"}
}