{
  "type": "Feature",
  "properties": {
    "addr:full":"501 Prospect Hwy Prospect NSW 2148",
    "addr:housenumber":"501",
    "addr:postcode":"2148",
    "addr:street":"Prospect Hwy",
    "iso:country":"AU",
    "sg:address":"501 Prospect Hwy",
    "sg:city":"Prospect",
    "sg:classifiers":[
        {
            "category":"Building & Trades",
            "subcategory":"Cleaning & Sanitation",
            "type":"Services"
        }
    ],
    "sg:phone":"+61 2 9621 3425",
    "sg:postcode":"2148",
    "sg:province":"NSW",
    "sg:tags":[
        "industrial",
        "commercial",
        "contractor"
    ],
    "wof:name":"Prospect Cleaning Services Pty Ltd",
    "wof:placetype":"venue"
},
  "geometry": {"coordinates":[150.91839599599999,-33.7969741821],"type":"Point"}
}