{
  "type": "Feature",
  "properties": {
    "addr:full":"246 Purnell Rd Corio VIC 3214",
    "addr:housenumber":"246",
    "addr:postcode":"3214",
    "addr:street":"Purnell Rd",
    "iso:country":"AU",
    "sg:address":"246 Purnell Rd",
    "sg:city":"Corio",
    "sg:classifiers":[
        {
            "category":"Building & Trades",
            "subcategory":"Construction",
            "type":"Services"
        }
    ],
    "sg:phone":"+61 417 332 860",
    "sg:postcode":"3214",
    "sg:province":"VIC",
    "sg:tags":[
        "insulation",
        "contractor"
    ],
    "wof:name":"Hart G.E. & L.M.",
    "wof:placetype":"venue"
},
  "geometry": {"coordinates":[144.33937072800001,-38.0716247559],"type":"Point"}
}