{
  "type": "Feature",
  "properties": {
    "addr:full":"6/ 75 Elizabeth St Sydney NSW 2000",
    "addr:housenumber":"/ 75",
    "addr:postcode":"2000",
    "addr:street":"Elizabeth St",
    "iso:country":"AU",
    "sg:address":"6/ 75 Elizabeth St",
    "sg:city":"Sydney",
    "sg:classifiers":[
        {
            "category":"Wholesale",
            "subcategory":"Electrical",
            "type":"Manufacturing & Wholesale Goods"
        }
    ],
    "sg:phone":"+61 1300 765 800",
    "sg:postcode":"2000",
    "sg:province":"NSW",
    "sg:tags":[
        "wholesaler",
        "mfrs",
        "accessory"
    ],
    "wof:name":"Ideal Industries",
    "wof:placetype":"venue"
},
  "geometry": {"coordinates":[151.21029663100001,-33.8686218262],"type":"Point"}
}