{
  "type": "Feature",
  "properties": {
    "addr:full":"24 Erith St Bundanoon NSW 2578",
    "addr:housenumber":"24",
    "addr:postcode":"2578",
    "addr:street":"Erith St",
    "iso:country":"AU",
    "sg:address":"24 Erith St",
    "sg:city":"Bundanoon",
    "sg:classifiers":[
        {
            "category":"Professional",
            "subcategory":"Engineering",
            "type":"Services"
        }
    ],
    "sg:phone":"+61 2 4883 6406",
    "sg:postcode":"2578",
    "sg:province":"NSW",
    "sg:tags":[
        "consulting",
        "engineer"
    ],
    "wof:name":"Ellsmore & Associates",
    "wof:placetype":"venue"
},
  "geometry": {"coordinates":[150.300506592,-34.6554222107],"type":"Point"}
}