{
  "type": "Feature",
  "properties": {
    "addr:full":"263 Homer St Earlwood NSW 2206",
    "addr:housenumber":"263",
    "addr:postcode":"2206",
    "addr:street":"Homer St",
    "iso:country":"AU",
    "sg:address":"263 Homer St",
    "sg:city":"Earlwood",
    "sg:classifiers":[
        {
            "category":"Health Services",
            "subcategory":"Doctor",
            "type":"Services"
        }
    ],
    "sg:phone":"+61 2 9559 4952",
    "sg:postcode":"2206",
    "sg:province":"NSW",
    "sg:tags":[
        "medical",
        "practitioner"
    ],
    "wof:name":"Macarounas Dr John",
    "wof:placetype":"venue"
},
  "geometry": {"coordinates":[151.12359599999999,-33.927956],"type":"Point"}
}