{
  "type": "Feature",
  "properties": {
    "addr:full":"PO Box 154 Albion Park NSW 2527",
    "addr:postcode":"2527",
    "iso:country":"AU",
    "sg:address":"PO Box 154",
    "sg:city":"Albion Park",
    "sg:classifiers":[
        {
            "category":"Building & Trades",
            "subcategory":"Pest Control",
            "type":"Services"
        }
    ],
    "sg:phone":"+61 2 4257 2675",
    "sg:postcode":"2527",
    "sg:province":"NSW",
    "wof:name":"Colin R Levy & Associates",
    "wof:placetype":"venue"
},
  "geometry": {"coordinates":[150.777511597,-34.5793991089],"type":"Point"}
}