{
  "type": "Feature",
  "properties": {
    "addr:full":"d'Albora Marina New Beach Rd Rushcutters Bay NSW 2011",
    "addr:postcode":"2011",
    "addr:street":"Beach Rd",
    "iso:country":"AU",
    "sg:address":"d'Albora Marina New Beach Rd",
    "sg:city":"Rushcutters Bay",
    "sg:classifiers":[
        {
            "category":"Recreation",
            "subcategory":"Boat Charter",
            "type":"Entertainment"
        }
    ],
    "sg:phone":"+61 2 9363 5998",
    "sg:postcode":"2011",
    "sg:province":"NSW",
    "sg:tags":[
        "canopy",
        "motor"
    ],
    "wof:name":"Premier Boat Trimming",
    "wof:placetype":"venue"
},
  "geometry": {"coordinates":[151.232147217,-33.8758811951],"type":"Point"}
}