{
  "type": "Feature",
  "properties": {
    "addr:full":"7 Allison Rd Wyong NSW 2259",
    "addr:housenumber":"7",
    "addr:postcode":"2259",
    "addr:street":"Allison Rd",
    "iso:country":"AU",
    "sg:address":"7 Allison Rd",
    "sg:city":"Wyong",
    "sg:classifiers":[
        {
            "category":"Health Services",
            "subcategory":"Dentist",
            "type":"Services"
        }
    ],
    "sg:phone":"+61 2 4353 2525",
    "sg:postcode":"2259",
    "sg:province":"NSW",
    "sg:tags":[
        "technician",
        "dental"
    ],
    "wof:name":"Eager K R",
    "wof:placetype":"venue"
},
  "geometry": {"coordinates":[151.424224853,-33.2841720581],"type":"Point"}
}