{
  "type": "Feature",
  "properties": {
    "addr:full":"226- 228 Albany Hwy Albany WA 6330",
    "addr:housenumber":"228",
    "addr:postcode":"6330",
    "addr:street":"Albany Hwy",
    "iso:country":"AU",
    "sg:address":"226- 228 Albany Hwy",
    "sg:city":"Albany",
    "sg:classifiers":[
        {
            "category":"Home & Garden",
            "subcategory":"Carpets & Floor Coverings",
            "type":"Retail Goods"
        }
    ],
    "sg:phone":"+61 8 9842 9909",
    "sg:postcode":"6330",
    "sg:province":"WA",
    "sg:tags":[
        "tile",
        "wall"
    ],
    "wof:name":"Metro Ceramic Tiles",
    "wof:placetype":"venue"
},
  "geometry": {"coordinates":[117.871688843,-35.0118408203],"type":"Point"}
}