{
  "type": "Feature",
  "properties": {
    "addr:full":"Cold Store Rd, Lenswood 5240, SA Australia Lenswood SA 5240",
    "addr:postcode":"5240;lenswood sa 5240",
    "addr:street":"Rd",
    "iso:country":"AU",
    "sg:address":"Cold Store Rd, Lenswood 5240, SA Australia",
    "sg:city":"Lenswood",
    "sg:classifiers":[
        {
            "category":"Retail",
            "subcategory":"Storage",
            "type":"Services"
        }
    ],
    "sg:phone":"+61 8 8389 8300",
    "sg:postcode":"5240",
    "sg:province":"SA",
    "sg:tags":[
        "cold"
    ],
    "wof:name":"Lenswood Cold Stores",
    "wof:placetype":"venue"
},
  "geometry": {"coordinates":[138.83224487300001,-34.9168510437],"type":"Point"}
}