{
  "type": "Feature",
  "properties": {
    "addr:full":"Level 8/ 32 Bridge St Sydney NSW 2000",
    "addr:housenumber":"/ 32",
    "addr:postcode":"2000",
    "addr:street":"Bridge St",
    "iso:country":"AU",
    "sg:address":"Level 8/ 32 Bridge St",
    "sg:city":"Sydney",
    "sg:classifiers":[
        {
            "category":"Professional",
            "subcategory":"Employment Agencies",
            "type":"Services"
        }
    ],
    "sg:phone":"+61 2 9241 5558",
    "sg:postcode":"2000",
    "sg:province":"NSW",
    "sg:tags":[
        "provider",
        "internet"
    ],
    "wof:name":"New Logic Pty Ltd",
    "wof:placetype":"venue"
},
  "geometry": {"coordinates":[151.20884704599999,-33.863483429],"type":"Point"}
}