{
  "type": "Feature",
  "properties": {
    "iso:country":"AU",
    "sg:address":"Shop 6 Cnr Mildura & Ridgevale Drvs",
    "sg:city":"Helensvale",
    "sg:classifiers":[
        {
            "category":"Personal",
            "subcategory":"Beauty Salon",
            "type":"Services"
        }
    ],
    "sg:phone":"+61 7 5529 8522",
    "sg:postcode":"4212",
    "sg:province":"QLD",
    "sg:tags":[
        "hairdresser"
    ],
    "wof:name":"Helensvale Hair International",
    "wof:placetype":"venue"
},
  "geometry": {"coordinates":[153.33578491200001,-27.9171791077],"type":"Point"}
}