{
  "type": "Feature",
  "properties": {
    "addr:full":"Shop 11, 217 Pt Nepean Rd Dromana VIC 3936",
    "addr:housenumber":"shop 11",
    "addr:postcode":"217;3936",
    "addr:street":"Pt Nepean Rd",
    "iso:country":"AU",
    "sg:address":"Shop 11, 217 Pt Nepean Rd",
    "sg:city":"Dromana",
    "sg:classifiers":[
        {
            "category":"Fast Food",
            "type":"Food & Drink"
        }
    ],
    "sg:phone":"+61 3 5987 3124",
    "sg:postcode":"3936",
    "sg:province":"VIC",
    "sg:tags":[
        "away",
        "take"
    ],
    "wof:name":"The Lucky Catch - Dromana Hub",
    "wof:placetype":"venue"
},
  "geometry": {"coordinates":[144.965286255,-38.3326034546],"type":"Point"}
}