{
  "type": "Feature",
  "properties": {
    "addr:full":"Harvest Pl Wongan Hills WA 6603",
    "addr:postcode":"6603",
    "addr:street":"Harvest Pl Wongan",
    "iso:country":"AU",
    "sg:address":"Harvest Pl",
    "sg:city":"Wongan Hills",
    "sg:classifiers":[
        {
            "category":"Shopping",
            "subcategory":"Computers & Home Electronics",
            "type":"Retail Goods"
        }
    ],
    "sg:phone":"+61 8 9671 1500",
    "sg:postcode":"6603",
    "sg:province":"WA",
    "sg:tags":[
        "hardware",
        "equipment"
    ],
    "wof:name":"Rural Wise",
    "wof:placetype":"venue"
},
  "geometry": {"coordinates":[116.71727752699999,-30.892244339],"type":"Point"}
}