{
  "type": "Feature",
  "properties": {
    "addr:full":"70 Ellen St Port Pirie SA 5540",
    "addr:housenumber":"70",
    "addr:postcode":"5540",
    "addr:street":"Ellen St",
    "iso:country":"AU",
    "sg:address":"70 Ellen St",
    "sg:city":"Port Pirie",
    "sg:classifiers":[
        {
            "category":"Health Services",
            "subcategory":"Dentist",
            "type":"Services"
        }
    ],
    "sg:phone":"+61 8 8633 3900",
    "sg:postcode":"5540",
    "sg:province":"SA",
    "sg:tags":[
        "dental",
        "prosthetist"
    ],
    "wof:name":"Port Pirie Denture Clinic",
    "wof:placetype":"venue"
},
  "geometry": {"coordinates":[138.00990295400001,-33.1762046814],"type":"Point"}
}