{
  "type": "Feature",
  "properties": {
    "addr:full":"Hume Hwy Longwood VIC 3665",
    "addr:postcode":"3665",
    "addr:street":"Hume Hwy",
    "iso:country":"AU",
    "sg:address":"Hume Hwy",
    "sg:city":"Longwood",
    "sg:classifiers":[
        {
            "category":"Building & Trades",
            "subcategory":"Landscaping Services",
            "type":"Services"
        }
    ],
    "sg:phone":"+61 3 5796 2386",
    "sg:postcode":"3665",
    "sg:province":"VIC",
    "sg:tags":[
        "grazier"
    ],
    "wof:name":"McCracken J A",
    "wof:placetype":"venue"
},
  "geometry": {"coordinates":[145.398925781,-36.8306999207],"type":"Point"}
}