{
  "type": "Feature",
  "properties": {
    "iso:country":"AU",
    "sg:address":"30 Field St",
    "sg:city":"Adelaide",
    "sg:classifiers":[
        {
            "category":"Wholesale",
            "subcategory":"Seafood",
            "type":"Manufacturing & Wholesale Goods"
        }
    ],
    "sg:phone":"+61 8 8400 1300",
    "sg:postcode":"5000",
    "sg:province":"SA",
    "sg:tags":[
        "fish"
    ],
    "sg:website":"http://www.angelakis.com.au",
    "wof:name":"Angelakis Bros",
    "wof:placetype":"venue"
},
  "geometry": {"coordinates":[138.59614563,-34.9306106567],"type":"Point"}
}