{
  "type": "Feature",
  "properties": {
    "addr:full":"2 Dudley St Pagewood NSW 2035",
    "addr:housenumber":"2",
    "addr:postcode":"2035",
    "addr:street":"Dudley St",
    "iso:country":"AU",
    "sg:address":"2 Dudley St",
    "sg:city":"Pagewood",
    "sg:classifiers":[
        {
            "category":"Manufacturing",
            "subcategory":"Glass & Minerals",
            "type":"Manufacturing & Wholesale Goods"
        }
    ],
    "sg:phone":"+61 2 9695 1085",
    "sg:postcode":"2035",
    "sg:province":"NSW",
    "sg:tags":[
        "repair",
        "fibreglass",
        "product"
    ],
    "wof:name":"Pump Maintenance Services",
    "wof:placetype":"venue"
},
  "geometry": {"coordinates":[151.21018981899999,-33.9451026917],"type":"Point"}
}