{
  "type": "Feature",
  "properties": {
    "iso:country":"AU",
    "sg:address":"37 Kullaroo Rd",
    "sg:city":"Kahibah",
    "sg:classifiers":[
        {
            "category":"Personal",
            "subcategory":"Massage",
            "type":"Services"
        }
    ],
    "sg:phone":"+61 2 4943 4754",
    "sg:postcode":"2290",
    "sg:province":"NSW",
    "sg:tags":[
        "therapy"
    ],
    "wof:name":"Musclecare",
    "wof:placetype":"venue"
},
  "geometry": {"coordinates":[151.70579528799999,-32.9584884644],"type":"Point"}
}