{
  "type": "Feature",
  "properties": {
    "iso:country":"AU",
    "sg:address":"365 Bambra Rd",
    "sg:city":"Caulfield South",
    "sg:classifiers":[
        {
            "category":"Health Services",
            "subcategory":"Health Practitioner",
            "type":"Services"
        }
    ],
    "sg:phone":"+61 3 9597 9440",
    "sg:postcode":"3162",
    "sg:province":"VIC",
    "sg:tags":[
        "hypnotherapy"
    ],
    "wof:name":"Quality Of Life Therapy",
    "wof:placetype":"venue"
},
  "geometry": {"coordinates":[145.02610778799999,-37.9007377625],"type":"Point"}
}