{
  "type": "Feature",
  "properties": {
    "addr:full":"24 Park Royal Drv Floraville NSW 2280",
    "addr:housenumber":"24",
    "addr:postcode":"2280",
    "addr:street":"Park Royal Drv",
    "iso:country":"AU",
    "sg:address":"24 Park Royal Drv",
    "sg:city":"Floraville",
    "sg:classifiers":[
        {
            "category":"Building & Trades",
            "subcategory":"Plumbing",
            "type":"Services"
        }
    ],
    "sg:phone":"+61 2 4945 5049",
    "sg:postcode":"2280",
    "sg:province":"NSW",
    "sg:tags":[
        "plumber",
        "gasfitters"
    ],
    "wof:name":"Brewster David Plumbing",
    "wof:placetype":"venue"
},
  "geometry": {"coordinates":[151.66249084500001,-33.016998291],"type":"Point"}
}