{
  "type": "Feature",
  "properties": {
    "addr:full":"631 Tyringham Rd Dorrigo North NSW 2453",
    "addr:housenumber":"631",
    "addr:postcode":"2453",
    "addr:street":"Tyringham Rd",
    "iso:country":"AU",
    "sg:address":"631 Tyringham Rd",
    "sg:city":"Dorrigo North",
    "sg:classifiers":[
        {
            "category":"Retail",
            "subcategory":"Veterinary Services",
            "type":"Services"
        }
    ],
    "sg:phone":"+61 427 256 818",
    "sg:postcode":"2453",
    "sg:province":"NSW",
    "sg:tags":[
        "surgeon"
    ],
    "wof:name":"Dorrigo Plateau Veterinary Clinic",
    "wof:placetype":"venue"
},
  "geometry": {"coordinates":[152.679596,-30.290945],"type":"Point"}
}