{
  "type": "Feature",
  "properties": {
    "iso:country":"AU",
    "sg:address":"53 Jones Rd",
    "sg:city":"Highgate",
    "sg:classifiers":[
        {
            "category":"Real Estate",
            "subcategory":"Architect",
            "type":"Services"
        }
    ],
    "sg:phone":"+61 402 731 418",
    "sg:postcode":"5063",
    "sg:province":"SA",
    "sg:tags":[
        "building",
        "designer"
    ],
    "wof:name":"Kim Franklin",
    "wof:placetype":"venue"
},
  "geometry": {"coordinates":[138.62623596200001,-34.9617004395],"type":"Point"}
}