{
  "type": "Feature",
  "properties": {
    "addr:full":"11 Church St Paddington NSW 2021",
    "addr:housenumber":"11",
    "addr:postcode":"2021",
    "addr:street":"Church St",
    "iso:country":"AU",
    "sg:address":"11 Church St",
    "sg:city":"Paddington",
    "sg:classifiers":[
        {
            "category":"Manufacturing",
            "subcategory":"Jewelry",
            "type":"Manufacturing & Wholesale Goods"
        }
    ],
    "sg:phone":"+61 2 9356 4141",
    "sg:postcode":"2021",
    "sg:province":"NSW",
    "sg:tags":[
        "designer",
        "jewellery"
    ],
    "wof:name":"R.Q. Design",
    "wof:placetype":"venue"
},
  "geometry": {"coordinates":[151.21917724599999,-33.8849449158],"type":"Point"}
}