{
  "type": "Feature",
  "properties": {
    "addr:full":"14 Eildon Rd Ashburton VIC 3147",
    "addr:housenumber":"14",
    "addr:postcode":"3147",
    "addr:street":"Eildon Rd",
    "iso:country":"AU",
    "sg:address":"14 Eildon Rd",
    "sg:city":"Ashburton",
    "sg:classifiers":[
        {
            "category":"Professional",
            "subcategory":"Art Services",
            "type":"Services"
        }
    ],
    "sg:phone":"+61 411 117 934",
    "sg:postcode":"3147",
    "sg:province":"VIC",
    "sg:tags":[
        "decorator",
        "painter"
    ],
    "wof:name":"Perfect Painting Pty Ltd",
    "wof:placetype":"venue"
},
  "geometry": {"coordinates":[145.10969543499999,-37.8622550964],"type":"Point"}
}