{
  "type": "Feature",
  "properties": {
    "addr:full":"52 Oxford Tce Unley SA 5061",
    "addr:housenumber":"52",
    "addr:postcode":"5061",
    "addr:street":"Oxford Tce",
    "iso:country":"AU",
    "sg:address":"52 Oxford Tce",
    "sg:city":"Unley",
    "sg:classifiers":[
        {
            "category":"Education",
            "subcategory":"School",
            "type":"Public Place"
        }
    ],
    "sg:phone":"+61 8 8272 1655",
    "sg:postcode":"5061",
    "sg:province":"SA",
    "sg:tags":[
        "co-educational"
    ],
    "sg:website":"http://www.saintspyridon.com",
    "wof:name":"Saint Spyridon College R-7",
    "wof:placetype":"venue"
},
  "geometry": {"coordinates":[138.60833740199999,-34.9503440857],"type":"Point"}
}