{
  "type": "Feature",
  "properties": {
    "addr:full":"98 Wedgewood Rd Hallam VIC 3803",
    "addr:housenumber":"98",
    "addr:postcode":"3803",
    "addr:street":"Wedgewood Rd",
    "iso:country":"AU",
    "sg:address":"98 Wedgewood Rd",
    "sg:city":"Hallam",
    "sg:classifiers":[
        {
            "category":"Wholesale",
            "subcategory":"Machinery & Supplies",
            "type":"Manufacturing & Wholesale Goods"
        }
    ],
    "sg:phone":"+61 3 9798 3544",
    "sg:postcode":"3803",
    "sg:province":"VIC",
    "sg:tags":[
        "equipment",
        "hydraulic"
    ],
    "wof:name":"Dolphin Hydraulics Pty Ltd",
    "wof:placetype":"venue"
},
  "geometry": {"coordinates":[145.257415772,-38.0052604675],"type":"Point"}
}