{
  "type": "Feature",
  "properties": {
    "iso:country":"AU",
    "sg:address":"31 Powers Rd",
    "sg:city":"Seven Hills",
    "sg:classifiers":[
        {
            "category":"Manufacturing",
            "subcategory":"Retail Goods",
            "type":"Manufacturing & Wholesale Goods"
        }
    ],
    "sg:phone":"+61 2 9830 2200",
    "sg:postcode":"2147",
    "sg:province":"NSW",
    "sg:tags":[
        "merchant",
        "pump",
        "mfrs"
    ],
    "sg:website":"http://www.epg.com.au",
    "wof:name":"Engineered Products Group",
    "wof:placetype":"venue"
},
  "geometry": {"coordinates":[150.945678711,-33.7738609314],"type":"Point"}
}