{
  "type": "Feature",
  "properties": {
    "iso:country":"AU",
    "sg:address":"265 Richmond Rd",
    "sg:city":"Richmond",
    "sg:classifiers":[
        {
            "category":"Parking",
            "type":"Transportation"
        }
    ],
    "sg:phone":"+61 8 8351 7033",
    "sg:postcode":"5033",
    "sg:province":"SA",
    "wof:name":"Airport Security Parking",
    "wof:placetype":"venue"
},
  "geometry": {"coordinates":[138.55523681599999,-34.9427566528],"type":"Point"}
}