{
  "type": "Feature",
  "properties": {
    "addr:full":"5 Seahorse Pl Caves Beach NSW 2281",
    "addr:housenumber":"5",
    "addr:postcode":"2281",
    "addr:street":"Seahorse Pl",
    "iso:country":"AU",
    "sg:address":"5 Seahorse Pl",
    "sg:city":"Caves Beach",
    "sg:classifiers":[
        {
            "category":"Professional",
            "subcategory":"Accounting & Tax Preparation",
            "type":"Services"
        }
    ],
    "sg:phone":"+61 2 4972 1338",
    "sg:postcode":"2281",
    "sg:province":"NSW",
    "sg:tags":[
        "bookkeeping"
    ],
    "wof:name":"Express Bookkeeping-Lake Macquarie East",
    "wof:placetype":"venue"
},
  "geometry": {"coordinates":[151.647338867,-33.0999336243],"type":"Point"}
}