{
  "type": "Feature",
  "properties": {
    "addr:full":"70 Charlotte Rd Gumdale QLD 4154",
    "addr:housenumber":"70",
    "addr:postcode":"4154",
    "addr:street":"Charlotte Rd",
    "iso:country":"AU",
    "sg:address":"70 Charlotte Rd",
    "sg:city":"Gumdale",
    "sg:classifiers":[
        {
            "category":"Education",
            "subcategory":"School",
            "type":"Public Place"
        }
    ],
    "sg:phone":"+61 7 3906 9111",
    "sg:postcode":"4154",
    "sg:province":"QLD",
    "sg:tags":[
        "state",
        "except",
        "nsw"
    ],
    "wof:name":"Moreton Bay Environmental Education Centre",
    "wof:placetype":"venue"
},
  "geometry": {"coordinates":[153.17291259800001,-27.4431056976],"type":"Point"}
}