{
  "type": "Feature",
  "properties": {
    "addr:full":"610 Queensberry St North Melbourne VIC 3051",
    "addr:housenumber":"610",
    "addr:postcode":"3051",
    "addr:street":"Queensberry St",
    "iso:country":"AU",
    "sg:address":"610 Queensberry St",
    "sg:city":"North Melbourne",
    "sg:classifiers":[
        {
            "category":"Cafe",
            "type":"Food & Drink"
        }
    ],
    "sg:phone":"+61 3 9326 8648",
    "sg:postcode":"3051",
    "sg:province":"VIC",
    "wof:name":"Roma Coffee Bar",
    "wof:placetype":"venue"
},
  "geometry": {"coordinates":[144.94712829599999,-37.8026046753],"type":"Point"}
}