{
  "type": "Feature",
  "properties": {
    "addr:full":"17 Station St Hornsby NSW 2077",
    "addr:housenumber":"17",
    "addr:postcode":"2077",
    "addr:street":"Station St",
    "iso:country":"AU",
    "sg:address":"17 Station St",
    "sg:city":"Hornsby",
    "sg:classifiers":[
        {
            "category":"Banks & Credit Unions",
            "subcategory":"Financial Services",
            "type":"Services"
        }
    ],
    "sg:phone":"+61 2 9477 2077",
    "sg:postcode":"2077",
    "sg:province":"NSW",
    "sg:tags":[
        "loan",
        "finance",
        "mortgage"
    ],
    "wof:name":"RAMS Home Loans",
    "wof:placetype":"venue"
},
  "geometry": {"coordinates":[151.097824097,-33.7028923035],"type":"Point"}
}