{
  "type": "Feature",
  "properties": {
    "iso:country":"AU",
    "sg:address":"PO Box 3025",
    "sg:city":"Norman Park",
    "sg:classifiers":[
        {
            "category":"Arena",
            "subcategory":"Sports Club",
            "type":"Entertainment"
        }
    ],
    "sg:phone":"+61 417 724 021",
    "sg:postcode":"4170",
    "sg:province":"QLD",
    "sg:tags":[
        "defence",
        "supply",
        "self",
        "instruction",
        "martial art"
    ],
    "wof:name":"BJJ Australia",
    "wof:placetype":"venue"
},
  "geometry": {"coordinates":[153.05592346200001,-27.4741001129],"type":"Point"}
}