{
  "type": "Feature",
  "properties": {
    "addr:full":"2 Short St Forster NSW 2428",
    "addr:housenumber":"2",
    "addr:postcode":"2428",
    "addr:street":"Short St",
    "iso:country":"AU",
    "sg:address":"2 Short St",
    "sg:city":"Forster",
    "sg:classifiers":[
        {
            "category":"Farming",
            "subcategory":"Fish & Marine Products",
            "type":"Manufacturing & Wholesale Goods"
        }
    ],
    "sg:phone":"+61 2 6554 6786",
    "sg:postcode":"2428",
    "sg:province":"NSW",
    "sg:tags":[
        "supplier",
        "oyster",
        "farmer"
    ],
    "wof:name":"Worboys S F & B M",
    "wof:placetype":"venue"
},
  "geometry": {"coordinates":[152.51298499999999,-32.188686],"type":"Point"}
}