{
  "type": "Feature",
  "properties": {
    "iso:country":"AU",
    "sg:address":"B18/ 3 Zamia St",
    "sg:city":"Sunnybank",
    "sg:classifiers":[
        {
            "category":"Professional",
            "subcategory":"Engineering",
            "type":"Services"
        }
    ],
    "sg:phone":"+61 7 3216 9366",
    "sg:postcode":"4109",
    "sg:province":"QLD",
    "sg:tags":[
        "consulting",
        "engineer"
    ],
    "wof:name":"Engwell Pty Ltd",
    "wof:placetype":"venue"
},
  "geometry": {"coordinates":[153.06076049800001,-27.5708618164],"type":"Point"}
}