{
  "type": "Feature",
  "properties": {
    "addr:full":"Rondelay Drv Castle Hill NSW 2154",
    "addr:postcode":"2154",
    "addr:street":"Rondelay Drv",
    "iso:country":"AU",
    "sg:address":"Rondelay Drv",
    "sg:city":"Castle Hill",
    "sg:classifiers":[
        {
            "category":"Education",
            "subcategory":"School",
            "type":"Public Place"
        }
    ],
    "sg:phone":"+61 2 9634 3774",
    "sg:postcode":"2154",
    "sg:province":"NSW",
    "sg:tags":[
        "state",
        "-",
        "nsw"
    ],
    "wof:name":"Excelsior Public School",
    "wof:placetype":"venue"
},
  "geometry": {"coordinates":[150.993286133,-33.7413787842],"type":"Point"}
}