{
  "type": "Feature",
  "properties": {
    "addr:full":"13 Burnett Crs Reservoir VIC 3073",
    "addr:housenumber":"13",
    "addr:postcode":"3073",
    "addr:street":"Burnett Crs",
    "iso:country":"AU",
    "sg:address":"13 Burnett Crs",
    "sg:city":"Reservoir",
    "sg:classifiers":[
        {
            "category":"Building & Trades",
            "subcategory":"Cleaning & Sanitation",
            "type":"Services"
        }
    ],
    "sg:phone":"+61 403 013 319",
    "sg:postcode":"3073",
    "sg:province":"VIC",
    "sg:tags":[
        "window"
    ],
    "wof:name":"Roberts Window Cleaning",
    "wof:placetype":"venue"
},
  "geometry": {"coordinates":[145.061569214,-37.6605262756],"type":"Point"}
}