{
  "type": "Feature",
  "properties": {
    "addr:full":"Unit 2 56 Export Drv Ernest QLD 4214",
    "addr:housenumber":"56",
    "addr:postcode":"4214",
    "addr:street":"Export Drv Ernest",
    "iso:country":"AU",
    "sg:address":"Unit 2 56 Export Drv",
    "sg:city":"Ernest",
    "sg:classifiers":[
        {
            "category":"Building & Trades",
            "subcategory":"Construction",
            "type":"Services"
        }
    ],
    "sg:phone":"+61 7 5594 7199",
    "sg:postcode":"4214",
    "sg:province":"QLD",
    "sg:tags":[
        "course",
        "golf",
        "equipment"
    ],
    "wof:name":"True Turf Equipment",
    "wof:placetype":"venue"
},
  "geometry": {"coordinates":[153.36036682100001,-27.9671287537],"type":"Point"}
}