{
  "type": "Feature",
  "properties": {
    "iso:country":"AU",
    "sg:address":"646 Wyndham St",
    "sg:city":"Shepparton",
    "sg:classifiers":[
        {
            "category":"Fast Food",
            "type":"Food & Drink"
        }
    ],
    "sg:phone":"+61 3 5822 0501",
    "sg:postcode":"3630",
    "sg:province":"VIC",
    "sg:tags":[
        "away",
        "take"
    ],
    "wof:name":"Subway Sandwiches & Salads",
    "wof:placetype":"venue"
},
  "geometry": {"coordinates":[145.394805908,-36.4007949829],"type":"Point"}
}