{
  "type": "Feature",
  "properties": {
    "addr:full":"4 Wilson St Toowoomba QLD 4350",
    "addr:housenumber":"4",
    "addr:postcode":"4350",
    "addr:street":"Wilson St",
    "iso:country":"AU",
    "sg:address":"4 Wilson St",
    "sg:city":"Toowoomba",
    "sg:classifiers":[
        {
            "category":"Train Station",
            "subcategory":"Light Rail",
            "type":"Transportation"
        }
    ],
    "sg:phone":"+61 418 795 728",
    "sg:postcode":"4350",
    "sg:province":"QLD",
    "sg:tags":[
        "equipment",
        "energy",
        "solar"
    ],
    "wof:name":"Brian Jones Solar Energy",
    "wof:placetype":"venue"
},
  "geometry": {"coordinates":[151.989044189,-27.5848026276],"type":"Point"}
}