{
  "type": "Feature",
  "properties": {
    "addr:full":"Wellington St Northam WA 6401",
    "addr:postcode":"6401",
    "addr:street":"Wellington St",
    "iso:country":"AU",
    "sg:address":"Wellington St",
    "sg:city":"Northam",
    "sg:classifiers":[
        {
            "category":"Arena",
            "subcategory":"Sports Club",
            "type":"Entertainment"
        }
    ],
    "sg:phone":"+61 8 9622 5314",
    "sg:postcode":"6401",
    "sg:province":"WA",
    "sg:tags":[
        "hunt",
        "racing"
    ],
    "wof:name":"Northam Race Promotions",
    "wof:placetype":"venue"
},
  "geometry": {"coordinates":[116.665908813,-31.6605815887],"type":"Point"}
}