{
  "type": "Feature",
  "properties": {
    "addr:full":"L1 64 Talbragar St Dubbo NSW 2830",
    "addr:housenumber":"64",
    "addr:postcode":"2830",
    "addr:street":"L1;Talbragar St",
    "iso:country":"AU",
    "sg:address":"L1 64 Talbragar St",
    "sg:city":"Dubbo",
    "sg:classifiers":[
        {
            "category":"Professional",
            "subcategory":"Management & Consulting",
            "type":"Services"
        }
    ],
    "sg:phone":"+61 2 6884 5888",
    "sg:postcode":"2830",
    "sg:province":"NSW",
    "sg:tags":[
        "consultant"
    ],
    "wof:name":"Mindshop",
    "wof:placetype":"venue"
},
  "geometry": {"coordinates":[148.603607178,-32.2449111938],"type":"Point"}
}