{
  "type": "Feature",
  "properties": {
    "addr:full":"Shop 16 Mariners Cove Seaworld Drv Main Beach QLD 4217",
    "addr:housenumber":"shop 16",
    "addr:postcode":"4217",
    "addr:street":"Mariners Cove Seaworld Drv",
    "iso:country":"AU",
    "sg:address":"Shop 16 Mariners Cove Seaworld Drv",
    "sg:city":"Main Beach",
    "sg:classifiers":[
        {
            "category":"Autos & Motor Vehicles",
            "subcategory":"Boat Sales",
            "type":"Retail Goods"
        }
    ],
    "sg:phone":"+61 7 5528 5333",
    "sg:postcode":"4217",
    "sg:province":"QLD",
    "sg:tags":[
        "yacht"
    ],
    "wof:name":"Bayliner",
    "wof:placetype":"venue"
},
  "geometry": {"coordinates":[153.428131103,-27.9717655182],"type":"Point"}
}