{
  "type": "Feature",
  "properties": {
    "addr:full":"Cnr Riddell Rd & Elizabeth Drv Sunbury VIC 3429",
    "addr:postcode":"3429",
    "addr:street":"Riddell Rd & Elizabeth Drv",
    "iso:country":"AU",
    "sg:address":"Cnr Riddell Rd & Elizabeth Drv",
    "sg:city":"Sunbury",
    "sg:classifiers":[
        {
            "category":"Retail",
            "subcategory":"Veterinary Services",
            "type":"Services"
        }
    ],
    "sg:phone":"+61 3 9744 1644",
    "sg:postcode":"3429",
    "sg:province":"VIC",
    "sg:tags":[
        "surgeon"
    ],
    "wof:name":"Sunbury All Creatures Veterinary Clinic",
    "wof:placetype":"venue"
},
  "geometry": {"coordinates":[144.728118897,-37.5753097534],"type":"Point"}
}