{
  "type": "Feature",
  "properties": {
    "iso:country":"AU",
    "sg:address":"87-89 Portrush Rd",
    "sg:city":"Evandale",
    "sg:classifiers":[
        {
            "category":"Fast Food",
            "type":"Food & Drink"
        }
    ],
    "sg:phone":"+61 8 8132 1698",
    "sg:postcode":"5069",
    "sg:province":"SA",
    "sg:tags":[
        "away",
        "take"
    ],
    "wof:name":"Subway",
    "wof:placetype":"venue"
},
  "geometry": {"coordinates":[138.63949585,-34.9040756226],"type":"Point"}
}