{
  "type": "Feature",
  "properties": {
    "iso:country":"AU",
    "sg:address":"135 Lake St",
    "sg:city":"Northbridge",
    "sg:classifiers":[
        {
            "category":"Education",
            "subcategory":"Special Training",
            "type":"Public Place"
        }
    ],
    "sg:phone":"+61 8 9328 7675",
    "sg:postcode":"6003",
    "sg:province":"WA",
    "sg:tags":[
        "development"
    ],
    "wof:name":"Western Australian Barista Academy",
    "wof:placetype":"venue"
},
  "geometry": {"coordinates":[115.858978272,-31.9441375732],"type":"Point"}
}