{
  "type": "Feature",
  "properties": {
    "iso:country":"AU",
    "sg:address":"203 Victoria Rd",
    "sg:city":"Northcote",
    "sg:classifiers":[
        {
            "category":"Health Services",
            "subcategory":"Health Practitioner",
            "type":"Services"
        }
    ],
    "sg:phone":"+61 3 9482 6737",
    "sg:postcode":"3070",
    "sg:province":"VIC",
    "sg:tags":[
        "technique",
        "alexander"
    ],
    "wof:name":"Northcote Alexander Technique",
    "wof:placetype":"venue"
},
  "geometry": {"coordinates":[145.01153600000001,-37.767982],"type":"Point"}
}