{
  "type": "Feature",
  "properties": {
    "iso:country":"AU",
    "sg:address":"108 Spencer Rd",
    "sg:city":"Langford",
    "sg:classifiers":[
        {
            "category":"Health Services",
            "subcategory":"Doctor",
            "type":"Services"
        }
    ],
    "sg:phone":"+61 8 9451 4915",
    "sg:postcode":"6147",
    "sg:province":"WA",
    "sg:tags":[
        "medical",
        "practitioner"
    ],
    "wof:name":"Yeap C T",
    "wof:placetype":"venue"
},
  "geometry": {"coordinates":[115.947006,-32.037689],"type":"Point"}
}