{
  "type": "Feature",
  "properties": {
    "addr:full":"Suite 18 , Woodbury Court Business Centre Bendigo VIC 3550",
    "addr:postcode":"3550",
    "addr:street":"Woodbury",
    "iso:country":"AU",
    "sg:address":"Suite 18",
    "sg:city":", Woodbury Court Business Centre Bendigo",
    "sg:classifiers":[
        {
            "category":"Shopping",
            "subcategory":"Computers & Home Electronics",
            "type":"Retail Goods"
        }
    ],
    "sg:phone":"+61 3 5444 9500",
    "sg:postcode":"3550",
    "sg:province":"VIC",
    "sg:tags":[
        "hardware",
        "equipment"
    ],
    "wof:name":"Bendigo IT",
    "wof:placetype":"venue"
},
  "geometry": {"coordinates":[144.311035156,-36.7602996826],"type":"Point"}
}