{
  "type": "Feature",
  "properties": {
    "addr:full":"Rocky Crossing Rd Agnes Water QLD 4677",
    "addr:postcode":"4677",
    "addr:street":"Rocky Crossing Rd",
    "iso:country":"AU",
    "sg:address":"Rocky Crossing Rd",
    "sg:city":"Agnes Water",
    "sg:classifiers":[
        {
            "category":"Home & Garden",
            "subcategory":"Building Materials",
            "type":"Retail Goods"
        }
    ],
    "sg:phone":"+61 7 4974 9246",
    "sg:postcode":"4677",
    "sg:province":"QLD",
    "sg:tags":[
        "pre-mixed",
        "concrete"
    ],
    "wof:name":"Boral",
    "wof:placetype":"venue"
},
  "geometry": {"coordinates":[151.86257900000001,-24.248684],"type":"Point"}
}