{
  "type": "Feature",
  "properties": {
    "iso:country":"AU",
    "sg:address":"Unit 2 38 Terrence Rd",
    "sg:city":"Brendale",
    "sg:classifiers":[
        {
            "category":"Retail",
            "subcategory":"Auto Repair",
            "type":"Services"
        }
    ],
    "sg:phone":"+61 7 3889 7757",
    "sg:postcode":"4500",
    "sg:province":"QLD",
    "sg:tags":[
        "transmission",
        "automotive",
        "car"
    ],
    "wof:name":"Johnson Transmissions Pty Ltd",
    "wof:placetype":"venue"
},
  "geometry": {"coordinates":[152.98127746599999,-27.3200492859],"type":"Point"}
}