{
  "type": "Feature",
  "properties": {
    "addr:full":"1 - 7 West St Petersham NSW 2049",
    "addr:housenumber":"7",
    "addr:postcode":"2049",
    "addr:street":"West St",
    "iso:country":"AU",
    "sg:address":"1 - 7 West St",
    "sg:city":"Petersham",
    "sg:classifiers":[
        {
            "category":"Government",
            "subcategory":"Post Office",
            "type":"Public Place"
        }
    ],
    "sg:phone":"+61 414 339 300",
    "sg:postcode":"2049",
    "sg:province":"NSW",
    "sg:tags":[
        "yoga"
    ],
    "wof:name":"Awakened Heart",
    "wof:placetype":"venue"
},
  "geometry": {"coordinates":[151.15022300000001,-33.892666],"type":"Point"}
}