{
  "type": "Feature",
  "properties": {
    "addr:full":"15 Hoey St Toowoomba QLD 4350",
    "addr:housenumber":"15",
    "addr:postcode":"4350",
    "addr:street":"Hoey St",
    "iso:country":"AU",
    "sg:address":"15 Hoey St",
    "sg:city":"Toowoomba",
    "sg:classifiers":[
        {
            "category":"Manufacturing",
            "subcategory":"Chemicals & Compounds",
            "type":"Manufacturing & Wholesale Goods"
        }
    ],
    "sg:phone":"+61 7 4636 1612",
    "sg:postcode":"4350",
    "sg:province":"QLD",
    "sg:tags":[
        "agricultural"
    ],
    "wof:name":"Trygon Agri-Solutions Pty Ltd",
    "wof:placetype":"venue"
},
  "geometry": {"coordinates":[151.94006300000001,-27.585085],"type":"Point"}
}