{
  "type": "Feature",
  "properties": {
    "iso:country":"AU",
    "sg:address":"16 Morven Rd",
    "sg:city":"Niagara Park",
    "sg:classifiers":[
        {
            "category":"Home & Garden",
            "subcategory":"Furniture",
            "type":"Retail Goods"
        }
    ],
    "sg:phone":"+61 2 4328 1138",
    "sg:postcode":"2250",
    "sg:province":"NSW",
    "sg:tags":[
        "repair",
        "restoration"
    ],
    "wof:name":"Jeff Wells Upholsterer",
    "wof:placetype":"venue"
},
  "geometry": {"coordinates":[151.35647582999999,-33.3885002136],"type":"Point"}
}