{
  "type": "Feature",
  "properties": {
    "iso:country":"AU",
    "sg:address":"Level 6 14 Mt Gravatt Capalaba Rd",
    "sg:city":"Mt Gravatt",
    "sg:classifiers":[
        {
            "category":"Professional",
            "subcategory":"Accounting & Tax Preparation",
            "type":"Services"
        }
    ],
    "sg:phone":"+61 7 3349 1121",
    "sg:postcode":"4122",
    "sg:province":"QLD",
    "sg:tags":[
        "accountant",
        "auditor"
    ],
    "wof:name":"Griffin Jones",
    "wof:placetype":"venue"
},
  "geometry": {"coordinates":[153.081787109,-27.5594844818],"type":"Point"}
}