{
  "type": "Feature",
  "properties": {
    "addr:full":"Ste 2/ 35 Ellingworth Pde Box Hill VIC 3128",
    "addr:postcode":"3128",
    "addr:street":"35 Ellingworth Pde",
    "iso:country":"AU",
    "sg:address":"Ste 2/ 35 Ellingworth Pde",
    "sg:city":"Box Hill",
    "sg:classifiers":[
        {
            "category":"Professional",
            "subcategory":"Engineering",
            "type":"Services"
        }
    ],
    "sg:phone":"+61 3 9898 2200",
    "sg:postcode":"3128",
    "sg:province":"VIC",
    "sg:tags":[
        "consulting",
        "engineer"
    ],
    "wof:name":"Fenton Partners",
    "wof:placetype":"venue"
},
  "geometry": {"coordinates":[145.12692260700001,-37.820690155],"type":"Point"}
}