{
  "type": "Feature",
  "properties": {
    "addr:full":"42 Marie St Castle Hill NSW 2154",
    "addr:housenumber":"42",
    "addr:postcode":"2154",
    "addr:street":"Marie St",
    "iso:country":"AU",
    "sg:address":"42 Marie St",
    "sg:city":"Castle Hill",
    "sg:classifiers":[
        {
            "category":"Building & Trades",
            "subcategory":"Cleaning & Sanitation",
            "type":"Services"
        }
    ],
    "sg:phone":"+61 412 064 015",
    "sg:postcode":"2154",
    "sg:province":"NSW",
    "sg:tags":[
        "industrial",
        "commercial",
        "contractor"
    ],
    "wof:name":"Castle Hill Cleaning & Maintenance Services",
    "wof:placetype":"venue"
},
  "geometry": {"coordinates":[150.995239258,-33.7399597168],"type":"Point"}
}