{
  "type": "Feature",
  "properties": {
    "iso:country":"AU",
    "sg:address":"4 Pinnaroo Crs",
    "sg:city":"Burnside",
    "sg:classifiers":[
        {
            "category":"Shopping",
            "subcategory":"Antiques",
            "type":"Retail Goods"
        }
    ],
    "sg:phone":"+61 3 8361 7920",
    "sg:postcode":"3023",
    "sg:province":"VIC",
    "sg:tags":[
        "restoration",
        "reproduction"
    ],
    "wof:name":"Top Stitch Upholstery",
    "wof:placetype":"venue"
},
  "geometry": {"coordinates":[144.75462300000001,-37.761559],"type":"Point"}
}