{
  "type": "Feature",
  "properties": {
    "addr:full":"Herveys Range Rd Townsville QLD 4810",
    "addr:postcode":"4810",
    "addr:street":"Range Rd",
    "iso:country":"AU",
    "sg:address":"Herveys Range Rd",
    "sg:city":"Townsville",
    "sg:classifiers":[
        {
            "category":"Retail",
            "subcategory":"Event Space",
            "type":"Services"
        }
    ],
    "sg:phone":"+61 7 4773 6699",
    "sg:postcode":"4810",
    "sg:province":"QLD",
    "sg:tags":[
        "venue",
        "reception",
        "wedding"
    ],
    "wof:name":"Brothers Leagues Club",
    "wof:placetype":"venue"
},
  "geometry": {"coordinates":[146.72744800000001,-19.317715],"type":"Point"}
}