{
  "type": "Feature",
  "properties": {
    "iso:country":"AU",
    "sg:address":"144 St Kilda Rd St",
    "sg:city":"Kilda",
    "sg:classifiers":[
        {
            "category":"Banks & Credit Unions",
            "subcategory":"Investment Brokerage",
            "type":"Services"
        }
    ],
    "sg:phone":"+61 3 9525 4728",
    "sg:postcode":"3182",
    "sg:province":"VIC",
    "sg:tags":[
        "electricity",
        "supplier"
    ],
    "wof:name":"Diamond Energy Pty Ltd",
    "wof:placetype":"venue"
},
  "geometry": {"coordinates":[144.98460388199999,-37.8603477478],"type":"Point"}
}