{
  "type": "Feature",
  "properties": {
    "addr:full":"27 Gem St Lightning Ridge NSW 2834",
    "addr:housenumber":"27",
    "addr:postcode":"2834",
    "addr:street":"Gem St",
    "iso:country":"AU",
    "sg:address":"27 Gem St",
    "sg:city":"Lightning Ridge",
    "sg:classifiers":[
        {
            "category":"Retail",
            "subcategory":"Veterinary Services",
            "type":"Services"
        }
    ],
    "sg:phone":"+61 2 6829 2199",
    "sg:postcode":"2834",
    "sg:province":"NSW",
    "sg:tags":[
        "surgeon"
    ],
    "wof:name":"Lightning Ridge Veterinary Clinic",
    "wof:placetype":"venue"
},
  "geometry": {"coordinates":[147.98361199999999,-29.426788],"type":"Point"}
}