{
  "type": "Feature",
  "properties": {
    "addr:full":"303 High St Melton VIC 3337",
    "addr:housenumber":"303",
    "addr:postcode":"3337",
    "addr:street":"High St",
    "iso:country":"AU",
    "sg:address":"303 High St",
    "sg:city":"Melton",
    "sg:classifiers":[
        {
            "category":"Shopping",
            "subcategory":"Pawn Shop",
            "type":"Retail Goods"
        }
    ],
    "sg:phone":"+61 3 9746 7854",
    "sg:postcode":"3337",
    "sg:province":"VIC",
    "sg:tags":[
        "pawnbroker"
    ],
    "wof:name":"Greater Trader Pawnbroker",
    "wof:placetype":"venue"
},
  "geometry": {"coordinates":[144.58390800000001,-37.683285],"type":"Point"}
}