{
  "type": "Feature",
  "properties": {
    "addr:full":"24 Taroona Ave Burnie TAS 7320",
    "addr:housenumber":"24",
    "addr:postcode":"7320",
    "addr:street":"Taroona Ave",
    "iso:country":"AU",
    "sg:address":"24 Taroona Ave",
    "sg:city":"Burnie",
    "sg:classifiers":[
        {
            "category":"Personal",
            "subcategory":"Massage",
            "type":"Services"
        }
    ],
    "sg:phone":"+61 3 6433 4545",
    "sg:postcode":"7320",
    "sg:province":"TAS",
    "sg:tags":[
        "therapy"
    ],
    "wof:name":"Lamont's Rejuvenating Massage Therapy",
    "wof:placetype":"venue"
},
  "geometry": {"coordinates":[145.88331600000001,-41.065403],"type":"Point"}
}