{
  "type": "Feature",
  "properties": {
    "iso:country":"AU",
    "sg:address":"Level 9/ 34 Queens Rd",
    "sg:city":"Melbourne",
    "sg:classifiers":[
        {
            "category":"Professional",
            "subcategory":"Art Services",
            "type":"Services"
        }
    ],
    "sg:phone":"+61 3 9529 2411",
    "sg:postcode":"3004",
    "sg:province":"VIC",
    "sg:tags":[
        "graphic",
        "designer"
    ],
    "wof:name":"Harry Simon & Associates Pty Ltd",
    "wof:placetype":"venue"
},
  "geometry": {"coordinates":[144.97622680699999,-37.8440322876],"type":"Point"}
}