{
  "type": "Feature",
  "properties": {
    "iso:country":"AU",
    "sg:address":"88 Main South Rd",
    "sg:city":"Reynella",
    "sg:classifiers":[
        {
            "category":"Autos & Motor Vehicles",
            "subcategory":"Auto Supplies",
            "type":"Retail Goods"
        }
    ],
    "sg:phone":"+61 8 8381 8300",
    "sg:postcode":"5161",
    "sg:province":"SA",
    "sg:tags":[
        "wheel",
        "four",
        "equipment",
        "drive",
        "accessory"
    ],
    "wof:name":"Southern Vales 4WD",
    "wof:placetype":"venue"
},
  "geometry": {"coordinates":[138.53242492699999,-35.0993881226],"type":"Point"}
}