{
  "type": "Feature",
  "properties": {
    "addr:full":"104 Seagull Ave Mermaid Beach QLD 4218",
    "addr:housenumber":"104",
    "addr:postcode":"4218",
    "addr:street":"Seagull Ave",
    "iso:country":"AU",
    "sg:address":"104 Seagull Ave",
    "sg:city":"Mermaid Beach",
    "sg:classifiers":[
        {
            "category":"Professional",
            "subcategory":"Accounting & Tax Preparation",
            "type":"Services"
        }
    ],
    "sg:phone":"+61 7 5578 5274",
    "sg:postcode":"4218",
    "sg:province":"QLD",
    "sg:tags":[
        "jukebox"
    ],
    "wof:name":"All Occasions Juke Box Hire",
    "wof:placetype":"venue"
},
  "geometry": {"coordinates":[153.438964844,-28.053560257],"type":"Point"}
}