{
  "type": "Feature",
  "properties": {
    "iso:country":"AU",
    "sg:address":"56 Scott St",
    "sg:city":"Kersbrook",
    "sg:classifiers":[
        {
            "category":"Travel",
            "subcategory":"Hotels & Motels",
            "type":"Entertainment"
        }
    ],
    "sg:phone":"+61 8 8389 3144",
    "sg:postcode":"5231",
    "sg:province":"SA",
    "sg:tags":[
        "pub"
    ],
    "wof:name":"Kersbrook Tavern",
    "wof:placetype":"venue"
},
  "geometry": {"coordinates":[138.85166931099999,-34.7825622559],"type":"Point"}
}