{
  "type": "Feature",
  "properties": {
    "iso:country":"AU",
    "sg:address":"171 Lake Rd",
    "sg:city":"Port Macquarie",
    "sg:classifiers":[
        {
            "category":"Home & Garden",
            "subcategory":"Carpets & Floor Coverings",
            "type":"Retail Goods"
        }
    ],
    "sg:phone":"+61 2 6581 0777",
    "sg:postcode":"2444",
    "sg:province":"NSW",
    "wof:name":"Design Carpets",
    "wof:placetype":"venue"
},
  "geometry": {"coordinates":[152.894836,-31.447926],"type":"Point"}
}