{
  "type": "Feature",
  "properties": {
    "addr:full":"23 Swan Rd Morwell VIC 3840",
    "addr:housenumber":"23",
    "addr:postcode":"3840",
    "addr:street":"Swan Rd",
    "iso:country":"AU",
    "sg:address":"23 Swan Rd",
    "sg:city":"Morwell",
    "sg:classifiers":[
        {
            "category":"Professional",
            "type":"Services"
        }
    ],
    "sg:phone":"+61 3 5134 5377",
    "sg:postcode":"3840",
    "sg:province":"VIC",
    "sg:tags":[
        "transport"
    ],
    "wof:name":"Dyers Gippsland Transport",
    "wof:placetype":"venue"
},
  "geometry": {"coordinates":[146.44358825699999,-38.2382965088],"type":"Point"}
}