{
  "type": "Feature",
  "properties": {
    "iso:country":"AU",
    "sg:address":"1st Floor, 2 Centreway",
    "sg:city":"Mt Waverley",
    "sg:classifiers":[
        {
            "category":"Building & Trades",
            "subcategory":"Construction",
            "type":"Services"
        }
    ],
    "sg:phone":"+61 3 9887 8984",
    "sg:postcode":"3149",
    "sg:province":"VIC",
    "sg:tags":[
        "contractor"
    ],
    "wof:name":"Bellemore Homes",
    "wof:placetype":"venue"
},
  "geometry": {"coordinates":[145.14335632300001,-37.891494751],"type":"Point"}
}