{
  "type": "Feature",
  "properties": {
    "iso:country":"AU",
    "sg:address":"1 Britt Pl",
    "sg:city":"Burnie",
    "sg:classifiers":[
        {
            "category":"Building & Trades",
            "subcategory":"Construction",
            "type":"Services"
        }
    ],
    "sg:phone":"+61 438 226 620",
    "sg:postcode":"7320",
    "sg:province":"TAS",
    "sg:tags":[
        "roof"
    ],
    "wof:name":"Complete Maintenance Services",
    "wof:placetype":"venue"
},
  "geometry": {"coordinates":[145.902542,-41.090172],"type":"Point"}
}