{
  "type": "Feature",
  "properties": {
    "addr:full":"PO Box 8118 Kooringal NSW 2650",
    "addr:postcode":"2650",
    "iso:country":"AU",
    "sg:address":"PO Box 8118",
    "sg:city":"Kooringal",
    "sg:classifiers":[
        {
            "category":"Building & Trades",
            "subcategory":"Construction",
            "type":"Services"
        }
    ],
    "sg:phone":"+61 2 6922 5650",
    "sg:postcode":"2650",
    "sg:province":"NSW",
    "sg:tags":[
        "plasterboard",
        "plasterer",
        "fixer"
    ],
    "wof:name":"Wagga Interior Linings",
    "wof:placetype":"venue"
},
  "geometry": {"coordinates":[147.37730407699999,-35.1417884827],"type":"Point"}
}