{
  "type": "Feature",
  "properties": {
    "addr:full":"U6/ 2 Carole Rd Maddington WA 6109",
    "addr:housenumber":"2",
    "addr:postcode":"6109",
    "addr:street":"U6 /;Carole Rd",
    "iso:country":"AU",
    "sg:address":"U6/ 2 Carole Rd",
    "sg:city":"Maddington",
    "sg:classifiers":[
        {
            "category":"Building & Trades",
            "subcategory":"Construction",
            "type":"Services"
        }
    ],
    "sg:phone":"+61 8 9493 6544",
    "sg:postcode":"6109",
    "sg:province":"WA",
    "sg:tags":[
        "fencing",
        "contractor"
    ],
    "wof:name":"BDD Services",
    "wof:placetype":"venue"
},
  "geometry": {"coordinates":[115.98210907000001,-32.0465393066],"type":"Point"}
}