{
  "type": "Feature",
  "properties": {
    "addr:full":"16 Wolverhampton St Stafford QLD 4053",
    "addr:housenumber":"16",
    "addr:postcode":"4053",
    "addr:street":"Wolverhampton St",
    "iso:country":"AU",
    "sg:address":"16 Wolverhampton St",
    "sg:city":"Stafford",
    "sg:classifiers":[
        {
            "category":"Home & Garden",
            "subcategory":"Building Materials",
            "type":"Retail Goods"
        }
    ],
    "sg:phone":"+61 7 3856 5500",
    "sg:postcode":"4053",
    "sg:province":"QLD",
    "sg:tags":[
        "balustrading"
    ],
    "wof:name":"A Lui's Woodturning",
    "wof:placetype":"venue"
},
  "geometry": {"coordinates":[153.01481628400001,-27.4174594879],"type":"Point"}
}