{
  "type": "Feature",
  "properties": {
    "iso:country":"AU",
    "sg:address":"122 Kings Rd",
    "sg:city":"New Lambton",
    "sg:classifiers":[
        {
            "category":"Structure",
            "subcategory":"Office Building",
            "type":"Public Place"
        }
    ],
    "sg:phone":"+61 2 4957 4798",
    "sg:postcode":"2305",
    "sg:province":"NSW",
    "sg:tags":[
        "slater",
        "tiler",
        "roof"
    ],
    "wof:name":"G & NC Watson Roof Tiling Service",
    "wof:placetype":"venue"
},
  "geometry": {"coordinates":[151.721283,-32.93148],"type":"Point"}
}