{
  "type": "Feature",
  "properties": {
    "iso:country":"AU",
    "sg:address":"217 Anzac Ave",
    "sg:city":"Toowoomba",
    "sg:classifiers":[
        {
            "category":"Wholesale",
            "subcategory":"Farm Supplies",
            "type":"Manufacturing & Wholesale Goods"
        }
    ],
    "sg:phone":"+61 7 4634 1377",
    "sg:postcode":"4350",
    "sg:province":"QLD",
    "sg:tags":[
        "feed",
        "supplement",
        "stock"
    ],
    "wof:name":"D H A Rural Sales",
    "wof:placetype":"venue"
},
  "geometry": {"coordinates":[151.92366,-27.573286],"type":"Point"}
}