{
  "type": "Feature",
  "properties": {
    "addr:full":"18 Mount St Perth WA 6000",
    "addr:housenumber":"18",
    "addr:postcode":"6000",
    "addr:street":"Mount St",
    "iso:country":"AU",
    "sg:address":"18 Mount St",
    "sg:city":"Perth",
    "sg:classifiers":[
        {
            "category":"Real Estate",
            "subcategory":"Architect",
            "type":"Services"
        }
    ],
    "sg:phone":"+61 8 9261 1800",
    "sg:postcode":"6000",
    "sg:province":"WA",
    "wof:name":"Buckeridge L W & Associates (1966) Architects",
    "wof:placetype":"venue"
},
  "geometry": {"coordinates":[115.849899292,-31.9532566071],"type":"Point"}
}