{
  "type": "Feature",
  "properties": {
    "addr:full":"366 Anzac Hwy Plympton SA 5038",
    "addr:housenumber":"366",
    "addr:postcode":"5038",
    "addr:street":"Anzac Hwy",
    "iso:country":"AU",
    "sg:address":"366 Anzac Hwy",
    "sg:city":"Plympton",
    "sg:classifiers":[
        {
            "category":"Fast Food",
            "type":"Food & Drink"
        }
    ],
    "sg:phone":"+61 8 8297 4688",
    "sg:postcode":"5038",
    "sg:province":"SA",
    "sg:tags":[
        "away",
        "take"
    ],
    "wof:name":"Marcellina Pizza Bar Restaurant",
    "wof:placetype":"venue"
},
  "geometry": {"coordinates":[138.54867553700001,-34.9681968689],"type":"Point"}
}