{
  "type": "Feature",
  "properties": {
    "iso:country":"AU",
    "sg:address":"158 Princes Hwy",
    "sg:city":"St Peters",
    "sg:classifiers":[
        {
            "category":"Home & Garden",
            "subcategory":"Garden Supply",
            "type":"Retail Goods"
        }
    ],
    "sg:phone":"+61 2 9517 2675",
    "sg:postcode":"2044",
    "sg:province":"NSW",
    "sg:tags":[
        "equipment"
    ],
    "wof:name":"Pottery Shack The",
    "wof:placetype":"venue"
},
  "geometry": {"coordinates":[151.178375,-33.913731],"type":"Point"}
}