{
  "type": "Feature",
  "properties": {
    "addr:full":"92 Gaskill St Canowindra NSW 2804",
    "addr:housenumber":"92",
    "addr:postcode":"2804",
    "addr:street":"Gaskill St",
    "iso:country":"AU",
    "sg:address":"92 Gaskill St",
    "sg:city":"Canowindra",
    "sg:classifiers":[
        {
            "category":"Farming",
            "subcategory":"Livestock Farm",
            "type":"Manufacturing & Wholesale Goods"
        }
    ],
    "sg:phone":"+61 2 6344 1749",
    "sg:postcode":"2804",
    "sg:province":"NSW",
    "sg:tags":[
        "school",
        "theological"
    ],
    "wof:name":"Cornerstone Community Team",
    "wof:placetype":"venue"
},
  "geometry": {"coordinates":[148.660354614,-33.5633354187],"type":"Point"}
}