{
  "type": "Feature",
  "properties": {
    "iso:country":"AU",
    "sg:address":"320 Redbank Plains Rd",
    "sg:city":"Redbank Plains",
    "sg:classifiers":[
        {
            "category":"Professional",
            "subcategory":"Detective & Security Services",
            "type":"Services"
        }
    ],
    "sg:phone":"+61 7 3814 3733",
    "sg:postcode":"4301",
    "sg:province":"QLD",
    "sg:tags":[
        "equipment",
        "window",
        "doors"
    ],
    "wof:name":"Goodna Glass Replacement",
    "wof:placetype":"venue"
},
  "geometry": {"coordinates":[152.87274169899999,-27.6389122009],"type":"Point"}
}