{
  "type": "Feature",
  "properties": {
    "addr:full":"Cnr Albany St & Pacific Hwy Coffs Harbour NSW 2450",
    "addr:postcode":"2450",
    "addr:street":"Cnr Albany St & Pacific Hwy",
    "iso:country":"AU",
    "sg:address":"Cnr Albany St & Pacific Hwy",
    "sg:city":"Coffs Harbour",
    "sg:classifiers":[
        {
            "category":"Travel",
            "subcategory":"Hotels & Motels",
            "type":"Entertainment"
        }
    ],
    "sg:phone":"+61 2 6652 3166",
    "sg:postcode":"2450",
    "sg:province":"NSW",
    "wof:name":"Matador Motor Inn",
    "wof:placetype":"venue"
},
  "geometry": {"coordinates":[153.11087000000001,-30.300819],"type":"Point"}
}