{
  "type": "Feature",
  "properties": {
    "addr:full":"Shop 3042 Westfield Shoppingtown Indooroopilly Mog Indooroopilly QLD 4068",
    "addr:housenumber":"3042",
    "addr:postcode":"4068",
    "addr:street":"Westfield Shoppingtown",
    "iso:country":"AU",
    "sg:address":"Shop 3042 Westfield Shoppingtown Indooroopilly Mog",
    "sg:city":"Indooroopilly",
    "sg:classifiers":[
        {
            "category":"Personal",
            "subcategory":"Shoe Repair & Shine",
            "type":"Services"
        }
    ],
    "sg:phone":"+61 7 3878 6673",
    "sg:postcode":"4068",
    "sg:province":"QLD",
    "sg:tags":[
        "footwear"
    ],
    "wof:name":"Cavallo Nero Quality Shoe Repairs",
    "wof:placetype":"venue"
},
  "geometry": {"coordinates":[152.974487305,-27.4973583221],"type":"Point"}
}