{
  "type": "Feature",
  "properties": {
    "addr:full":"6/ 1300 Samford Rd Ferny Grove QLD 4055",
    "addr:housenumber":"/ 1300",
    "addr:postcode":"4055",
    "addr:street":"Samford Rd",
    "iso:country":"AU",
    "sg:address":"6/ 1300 Samford Rd",
    "sg:city":"Ferny Grove",
    "sg:classifiers":[
        {
            "category":"Health Services",
            "subcategory":"Health Practitioner",
            "type":"Services"
        }
    ],
    "sg:phone":"+61 7 3351 4388",
    "sg:postcode":"4055",
    "sg:province":"QLD",
    "sg:tags":[
        "physiotherapist"
    ],
    "wof:name":"Ferny Grove Physiotherapy",
    "wof:placetype":"venue"
},
  "geometry": {"coordinates":[152.937744141,-27.4027233124],"type":"Point"}
}