{
  "type": "Feature",
  "properties": {
    "addr:full":"Tresco West Rd Tresco VIC 3583",
    "addr:postcode":"3583",
    "addr:street":"West Rd",
    "iso:country":"AU",
    "sg:address":"Tresco West Rd",
    "sg:city":"Tresco",
    "sg:classifiers":[
        {
            "category":"Farming",
            "subcategory":"Berry Farm",
            "type":"Manufacturing & Wholesale Goods"
        }
    ],
    "sg:phone":"+61 3 5037 2495",
    "sg:postcode":"3583",
    "sg:province":"VIC",
    "sg:tags":[
        "fruit",
        "grower"
    ],
    "wof:name":"Frees Fresh Fruit",
    "wof:placetype":"venue"
},
  "geometry": {"coordinates":[143.66859400000001,-35.501816],"type":"Point"}
}