{
  "type": "Feature",
  "properties": {
    "addr:full":"Shop 46, Campbelltown Mall, 271 Queen St Campbelltown NSW 2560",
    "addr:housenumber":"shop 46;271",
    "addr:postcode":"2560",
    "addr:street":"Campbelltown Mall;Queen St",
    "iso:country":"AU",
    "sg:address":"Shop 46, Campbelltown Mall, 271 Queen St",
    "sg:city":"Campbelltown",
    "sg:classifiers":[
        {
            "category":"Shopping",
            "subcategory":"Clothing, Apparel, & Fashions",
            "type":"Retail Goods"
        }
    ],
    "sg:phone":"+61 2 4620 0766",
    "sg:postcode":"2560",
    "sg:province":"NSW",
    "sg:tags":[
        "lady",
        "wear"
    ],
    "wof:name":"Noni- B-Fashions",
    "wof:placetype":"venue"
},
  "geometry": {"coordinates":[150.81254577600001,-34.0688095093],"type":"Point"}
}