{
  "type": "Feature",
  "properties": {
    "addr:full":"41 Princes Hwy Dapto NSW 2530",
    "addr:housenumber":"41",
    "addr:postcode":"2530",
    "addr:street":"Princes Hwy",
    "iso:country":"AU",
    "sg:address":"41 Princes Hwy",
    "sg:city":"Dapto",
    "sg:classifiers":[
        {
            "category":"Real Estate",
            "subcategory":"Real Estate Agent",
            "type":"Services"
        }
    ],
    "sg:phone":"+61 2 4261 3333",
    "sg:postcode":"2530",
    "sg:province":"NSW",
    "sg:website":"http://www.prdnationwide.com.au",
    "wof:name":"PRDnationwide Dapto",
    "wof:placetype":"venue"
},
  "geometry": {"coordinates":[150.795578003,-34.4925384521],"type":"Point"}
}