{
  "type": "Feature",
  "properties": {
    "iso:country":"AU",
    "sg:address":"24 Balcombe Park La",
    "sg:city":"Beaumaris",
    "sg:classifiers":[
        {
            "category":"Professional",
            "subcategory":"Management & Consulting",
            "type":"Services"
        }
    ],
    "sg:phone":"+61 3 9589 0606",
    "sg:postcode":"3193",
    "sg:province":"VIC",
    "sg:tags":[
        "consultant"
    ],
    "wof:name":"Evolution Matrix Pty Ltd",
    "wof:placetype":"venue"
},
  "geometry": {"coordinates":[145.03102111800001,-37.9762573242],"type":"Point"}
}