{
  "type": "Feature",
  "properties": {
    "addr:full":"PO Box 734 Forbes NSW 2871",
    "addr:postcode":"2871",
    "iso:country":"AU",
    "sg:address":"PO Box 734",
    "sg:city":"Forbes",
    "sg:classifiers":[
        {
            "category":"Personal",
            "type":"Services"
        }
    ],
    "sg:phone":"+61 2 6851 4434",
    "sg:postcode":"2871",
    "sg:province":"NSW",
    "sg:tags":[
        "wallpapering",
        "wallcovering"
    ],
    "wof:name":"Masterstroke Painters",
    "wof:placetype":"venue"
},
  "geometry": {"coordinates":[148.01153600000001,-33.38052],"type":"Point"}
}