{
  "type": "Feature",
  "properties": {
    "iso:country":"AU",
    "sg:address":"1st Floor, 86 Gawler Pl",
    "sg:city":"Adelaide",
    "sg:classifiers":[
        {
            "category":"Personal",
            "subcategory":"Beauty Salon",
            "type":"Services"
        }
    ],
    "sg:phone":"+61 8 8223 2400",
    "sg:postcode":"5000",
    "sg:province":"SA",
    "sg:tags":[
        "hairdresser"
    ],
    "sg:website":"http://www.clipjoint.com.au",
    "wof:name":"Clip Joint Salons",
    "wof:placetype":"venue"
},
  "geometry": {"coordinates":[138.60214233400001,-34.924446106],"type":"Point"}
}