{
  "type": "Feature",
  "properties": {
    "addr:full":"6 Ann St Salisbury SA 5108",
    "addr:housenumber":"6",
    "addr:postcode":"5108",
    "addr:street":"Ann St",
    "iso:country":"AU",
    "sg:address":"6 Ann St",
    "sg:city":"Salisbury",
    "sg:classifiers":[
        {
            "category":"Insurance",
            "subcategory":"Hazard Insurance",
            "type":"Services"
        }
    ],
    "sg:phone":"+61 13 25 85",
    "sg:postcode":"5108",
    "sg:province":"SA",
    "sg:tags":[
        "fire",
        "accident",
        "marine"
    ],
    "wof:name":"CPS Credit Union (SA) Ltd",
    "wof:placetype":"venue"
},
  "geometry": {"coordinates":[138.64857482900001,-34.7630119324],"type":"Point"}
}