{
  "type": "Feature",
  "properties": {
    "addr:full":"256 Huntingdale Rd Oakleigh VIC 3166",
    "addr:housenumber":"256",
    "addr:postcode":"3166",
    "addr:street":"Huntingdale Rd",
    "iso:country":"AU",
    "sg:address":"256 Huntingdale Rd",
    "sg:city":"Oakleigh",
    "sg:classifiers":[
        {
            "category":"Retail",
            "subcategory":"Auto Repair",
            "type":"Services"
        }
    ],
    "sg:phone":"+61 3 9252 5050",
    "sg:postcode":"3166",
    "sg:province":"VIC",
    "sg:tags":[
        "repairer",
        "motor",
        "engineer"
    ],
    "wof:name":"Tony White Daihtsu",
    "wof:placetype":"venue"
},
  "geometry": {"coordinates":[145.104446411,-37.9070549011],"type":"Point"}
}