{
  "type": "Feature",
  "properties": {
    "addr:full":"17 Macrossan St Toowoomba QLD 4350",
    "addr:housenumber":"17",
    "addr:postcode":"4350",
    "addr:street":"Macrossan St",
    "iso:country":"AU",
    "sg:address":"17 Macrossan St",
    "sg:city":"Toowoomba",
    "sg:classifiers":[
        {
            "category":"Building & Trades",
            "subcategory":"Construction",
            "type":"Services"
        }
    ],
    "sg:phone":"+61 417 748 535",
    "sg:postcode":"4350",
    "sg:province":"QLD",
    "sg:tags":[
        "contractor"
    ],
    "wof:name":"Merv Smith Homes",
    "wof:placetype":"venue"
},
  "geometry": {"coordinates":[151.918747,-27.530394],"type":"Point"}
}