{
  "type": "Feature",
  "properties": {
    "addr:full":"8 Euston St Malvern VIC 3144",
    "addr:housenumber":"8",
    "addr:postcode":"3144",
    "addr:street":"Euston St",
    "iso:country":"AU",
    "sg:address":"8 Euston St",
    "sg:city":"Malvern",
    "sg:classifiers":[
        {
            "category":"Structure",
            "subcategory":"Office Building",
            "type":"Public Place"
        }
    ],
    "sg:phone":"+61 3 9822 4500",
    "sg:postcode":"3144",
    "sg:province":"VIC",
    "sg:tags":[
        "slater",
        "tiler",
        "roof"
    ],
    "wof:name":"Roofline Roof Restoration Pty Ltd",
    "wof:placetype":"venue"
},
  "geometry": {"coordinates":[145.03894043,-37.8566665649],"type":"Point"}
}