{
  "type": "Feature",
  "properties": {
    "addr:full":"485 Chapel St South Yarra VIC 3141",
    "addr:housenumber":"485",
    "addr:postcode":"3141",
    "addr:street":"Chapel St",
    "iso:country":"AU",
    "sg:address":"485 Chapel St",
    "sg:city":"South Yarra",
    "sg:classifiers":[
        {
            "category":"Food & Beverages",
            "subcategory":"Fruits & Vegetables",
            "type":"Retail Goods"
        }
    ],
    "sg:phone":"+61 3 9827 4934",
    "sg:postcode":"3141",
    "sg:province":"VIC",
    "sg:tags":[
        "greengrocer",
        "fruiterer"
    ],
    "wof:name":"Rocky's Fruit & Vegies",
    "wof:placetype":"venue"
},
  "geometry": {"coordinates":[144.99472045900001,-37.8431282043],"type":"Point"}
}