{
  "type": "Feature",
  "properties": {
    "iso:country":"AU",
    "sg:address":"Bldg 309 Shiers Ave",
    "sg:city":"Mascot",
    "sg:classifiers":[
        {
            "category":"Wholesale",
            "subcategory":"Machinery & Supplies",
            "type":"Manufacturing & Wholesale Goods"
        }
    ],
    "sg:phone":"+61 2 9669 1917",
    "sg:postcode":"2020",
    "sg:province":"NSW",
    "sg:tags":[
        "equipment",
        "system",
        "elevating",
        "conveying"
    ],
    "wof:name":"Glidepath O & M Pty Ltd",
    "wof:placetype":"venue"
},
  "geometry": {"coordinates":[151.18539428700001,-33.9337234497],"type":"Point"}
}