{
  "type": "Feature",
  "properties": {
    "iso:country":"AU",
    "sg:address":"10 Benson St",
    "sg:city":"Toowong",
    "sg:classifiers":[
        {
            "category":"Health Services",
            "subcategory":"Doctor",
            "type":"Services"
        }
    ],
    "sg:phone":"+61 7 3870 5700",
    "sg:postcode":"4066",
    "sg:province":"QLD",
    "sg:tags":[
        "medical",
        "practitioner"
    ],
    "wof:name":"Balkin Anthony Dr",
    "wof:placetype":"venue"
},
  "geometry": {"coordinates":[152.99359130900001,-27.4855175018],"type":"Point"}
}