{
  "type": "Feature",
  "properties": {
    "iso:country":"AU",
    "sg:address":"13 Cash Fues Pl",
    "sg:city":"Wantirna",
    "sg:classifiers":[
        {
            "category":"Building & Trades",
            "subcategory":"Plumbing",
            "type":"Services"
        }
    ],
    "sg:phone":"+61 3 9887 4203",
    "sg:postcode":"3152",
    "sg:province":"VIC",
    "sg:tags":[
        "plumber",
        "gasfitters"
    ],
    "wof:name":"Lennox Plumbing & Heating",
    "wof:placetype":"venue"
},
  "geometry": {"coordinates":[145.219573975,-37.8398094177],"type":"Point"}
}