{
  "type": "Feature",
  "properties": {
    "addr:full":"Old Farm Strawberry Hill Middleton Rd Albany WA 6330",
    "addr:postcode":"6330",
    "addr:street":"Middleton Rd",
    "iso:country":"AU",
    "sg:address":"Old Farm Strawberry Hill Middleton Rd",
    "sg:city":"Albany",
    "sg:classifiers":[
        {
            "category":"Organizations",
            "subcategory":"Non-profit Organization",
            "type":"Services"
        }
    ],
    "sg:phone":"+61 8 9841 3735",
    "sg:postcode":"6330",
    "sg:province":"WA",
    "sg:tags":[
        "environmental",
        "organisation",
        "conservation"
    ],
    "wof:name":"National Trust Of Australia (WA) The",
    "wof:placetype":"venue"
},
  "geometry": {"coordinates":[117.898536682,-35.017906189],"type":"Point"}
}