{
  "type": "Feature",
  "properties": {
    "iso:country":"AU",
    "sg:address":"1102 Toorak Rd",
    "sg:city":"Camberwell",
    "sg:classifiers":[
        {
            "category":"Professional",
            "subcategory":"Computer Services",
            "type":"Services"
        }
    ],
    "sg:phone":"+61 3 9805 3400",
    "sg:postcode":"3124",
    "sg:province":"VIC",
    "sg:tags":[
        "package",
        "software"
    ],
    "wof:name":"Space-Time Research Pty Ltd",
    "wof:placetype":"venue"
},
  "geometry": {"coordinates":[145.07550048799999,-37.8481483459],"type":"Point"}
}