{
  "type": "Feature",
  "properties": {
    "iso:country":"AU",
    "sg:address":"16 White Swan Ave",
    "sg:city":"Blue Haven",
    "sg:classifiers":[
        {
            "category":"Home & Garden",
            "subcategory":"Building Materials",
            "type":"Retail Goods"
        }
    ],
    "sg:phone":"+61 414 884 872",
    "sg:postcode":"2262",
    "sg:province":"NSW",
    "sg:tags":[
        "lawn",
        "cutting",
        "maintenance"
    ],
    "wof:name":"Peter Walsh Garden Maintenance",
    "wof:placetype":"venue"
},
  "geometry": {"coordinates":[151.497894,-33.21006],"type":"Point"}
}