{
  "type": "Feature",
  "properties": {
    "addr:full":"16 Hamill St Garbutt QLD 4814",
    "addr:housenumber":"16",
    "addr:postcode":"4814",
    "addr:street":"Hamill St",
    "iso:country":"AU",
    "sg:address":"16 Hamill St",
    "sg:city":"Garbutt",
    "sg:classifiers":[
        {
            "category":"Autos & Motor Vehicles",
            "subcategory":"Automobile Sales",
            "type":"Retail Goods"
        }
    ],
    "sg:phone":"+61 7 4775 1255",
    "sg:postcode":"4814",
    "sg:province":"QLD",
    "sg:tags":[
        "equipment",
        "trailer"
    ],
    "wof:name":"Budget Trailers",
    "wof:placetype":"venue"
},
  "geometry": {"coordinates":[146.75872799999999,-19.26597],"type":"Point"}
}