{
  "type": "Feature",
  "properties": {
    "iso:country":"AU",
    "sg:address":"9 Ian Ave",
    "sg:city":"North Curl Curl",
    "sg:classifiers":[
        {
            "category":"Retail",
            "subcategory":"Driving School",
            "type":"Services"
        }
    ],
    "sg:phone":"+61 2 9905 1816",
    "sg:postcode":"2099",
    "sg:province":"NSW",
    "wof:name":"Coll-Roy Driving School",
    "wof:placetype":"venue"
},
  "geometry": {"coordinates":[151.300415039,-33.762046814],"type":"Point"}
}