{
  "type": "Feature",
  "properties": {
    "addr:full":"Level 6/ 13 Spring St Chatswood NSW 2067",
    "addr:housenumber":"/ 13",
    "addr:postcode":"2067",
    "addr:street":"Spring St",
    "iso:country":"AU",
    "sg:address":"Level 6/ 13 Spring St",
    "sg:city":"Chatswood",
    "sg:classifiers":[
        {
            "category":"Health Services",
            "subcategory":"Dentist",
            "type":"Services"
        }
    ],
    "sg:phone":"+61 2 8448 0144",
    "sg:postcode":"2067",
    "sg:province":"NSW",
    "wof:name":"HCF Dental Centres",
    "wof:placetype":"venue"
},
  "geometry": {"coordinates":[151.184814453,-33.7964248657],"type":"Point"}
}