{
  "type": "Feature",
  "properties": {
    "addr:full":"205 Military Rd Henley Beach South SA 5022",
    "addr:housenumber":"205",
    "addr:postcode":"5022",
    "addr:street":"Military Rd",
    "iso:country":"AU",
    "sg:address":"205 Military Rd",
    "sg:city":"Henley Beach South",
    "sg:classifiers":[
        {
            "category":"Real Estate",
            "subcategory":"Architect",
            "type":"Services"
        }
    ],
    "sg:phone":"+61 8 8235 2123",
    "sg:postcode":"5022",
    "sg:province":"SA",
    "sg:tags":[
        "building",
        "designer"
    ],
    "wof:name":"Threesixtydegrees",
    "wof:placetype":"venue"
},
  "geometry": {"coordinates":[138.497970581,-34.9271202087],"type":"Point"}
}