{
  "type": "Feature",
  "properties": {
    "addr:full":"6 Henderson St Turrella NSW 2205",
    "addr:housenumber":"6",
    "addr:postcode":"2205",
    "addr:street":"Henderson St",
    "iso:country":"AU",
    "sg:address":"6 Henderson St",
    "sg:city":"Turrella",
    "sg:classifiers":[
        {
            "category":"Home & Garden",
            "subcategory":"Building Materials",
            "type":"Retail Goods"
        }
    ],
    "sg:phone":"+61 2 9567 0488",
    "sg:postcode":"2205",
    "sg:province":"NSW",
    "sg:tags":[
        "shutter",
        "roller",
        "grille"
    ],
    "wof:name":"A. Thompsons Roller Shutters Pty Ltd",
    "wof:placetype":"venue"
},
  "geometry": {"coordinates":[151.140884,-33.929104],"type":"Point"}
}