{
  "type": "Feature",
  "properties": {
    "addr:full":"783 Fig Tree Pocket Rd Fig Tree Pocket QLD 4069",
    "addr:housenumber":"783",
    "addr:postcode":"4069",
    "addr:street":"Fig;Pocket Rd",
    "iso:country":"AU",
    "sg:address":"783 Fig Tree Pocket Rd",
    "sg:city":"Fig Tree Pocket",
    "sg:classifiers":[
        {
            "category":"Home & Garden",
            "subcategory":"Building Materials",
            "type":"Retail Goods"
        }
    ],
    "sg:phone":"+61 7 3878 5667",
    "sg:postcode":"4069",
    "sg:province":"QLD",
    "sg:tags":[
        "retaining",
        "wall"
    ],
    "wof:name":"Logan Landscapes Pty Ltd",
    "wof:placetype":"venue"
},
  "geometry": {"coordinates":[152.96636962900001,-27.5394268036],"type":"Point"}
}