{
  "type": "Feature",
  "properties": {
    "iso:country":"AU",
    "sg:address":"70 Arcadi St",
    "sg:city":"Arcadia Vale",
    "sg:classifiers":[
        {
            "category":"Education",
            "subcategory":"Special Training",
            "type":"Public Place"
        }
    ],
    "sg:phone":"+61 2 4975 4584",
    "sg:postcode":"2283",
    "sg:province":"NSW",
    "sg:tags":[
        "development"
    ],
    "wof:name":"Puller David Training & Development",
    "wof:placetype":"venue"
},
  "geometry": {"coordinates":[151.579315186,-33.061756134],"type":"Point"}
}