{
  "type": "Feature",
  "properties": {
    "addr:full":"317 Timor St Warrnambool VIC 3280",
    "addr:housenumber":"317",
    "addr:postcode":"3280",
    "addr:street":"Timor St",
    "iso:country":"AU",
    "sg:address":"317 Timor St",
    "sg:city":"Warrnambool",
    "sg:classifiers":[
        {
            "category":"Health Services",
            "subcategory":"Health Practitioner",
            "type":"Services"
        }
    ],
    "sg:phone":"+61 3 5562 0298",
    "sg:postcode":"3280",
    "sg:province":"VIC",
    "sg:tags":[
        "physiotherapist"
    ],
    "wof:name":"Cavalieri F",
    "wof:placetype":"venue"
},
  "geometry": {"coordinates":[142.472900391,-38.3813171387],"type":"Point"}
}