{
  "type": "Feature",
  "properties": {
    "addr:full":"21 Station St Dandenong VIC 3175",
    "addr:housenumber":"21",
    "addr:postcode":"3175",
    "addr:street":"Station St",
    "iso:country":"AU",
    "sg:address":"21 Station St",
    "sg:city":"Dandenong",
    "sg:classifiers":[
        {
            "category":"Building & Trades",
            "subcategory":"Construction",
            "type":"Services"
        }
    ],
    "sg:phone":"+61 3 9794 6230",
    "sg:postcode":"3175",
    "sg:province":"VIC",
    "sg:tags":[
        "contractor"
    ],
    "wof:name":"Statewide Contracting Pty Ltd",
    "wof:placetype":"venue"
},
  "geometry": {"coordinates":[145.20893859899999,-37.9925537109],"type":"Point"}
}