{
  "type": "Feature",
  "properties": {
    "addr:full":"34 Stevens St Queenscliff VIC 3225",
    "addr:housenumber":"34",
    "addr:postcode":"3225",
    "addr:street":"Stevens St",
    "iso:country":"AU",
    "sg:address":"34 Stevens St",
    "sg:city":"Queenscliff",
    "sg:classifiers":[
        {
            "category":"Education",
            "subcategory":"School",
            "type":"Public Place"
        }
    ],
    "sg:phone":"+61 3 5258 1736",
    "sg:postcode":"3225",
    "sg:province":"VIC",
    "sg:tags":[
        "co-educational"
    ],
    "wof:name":"St Aloysius' School",
    "wof:placetype":"venue"
},
  "geometry": {"coordinates":[144.65522799999999,-38.268879],"type":"Point"}
}