{
  "type": "Feature",
  "properties": {
    "addr:full":"Shp3/ 18 Railway Tce Rockingham WA 6168",
    "addr:housenumber":"18",
    "addr:postcode":"6168",
    "addr:street":"Railway Tce",
    "iso:country":"AU",
    "sg:address":"Shp3/ 18 Railway Tce",
    "sg:city":"Rockingham",
    "sg:classifiers":[
        {
            "category":"Fast Food",
            "type":"Food & Drink"
        }
    ],
    "sg:phone":"+61 8 9527 1315",
    "sg:postcode":"6168",
    "sg:province":"WA",
    "sg:tags":[
        "away",
        "take"
    ],
    "wof:name":"Arcade Fish & Chips",
    "wof:placetype":"venue"
},
  "geometry": {"coordinates":[115.72962200000001,-32.276295],"type":"Point"}
}