{
  "type": "Feature",
  "properties": {
    "addr:full":"Unit 5/ 31 The Esplanade Cotton Tree QLD 4558",
    "addr:housenumber":"31",
    "addr:postcode":"4558",
    "addr:street":"The Esplanade Cotton",
    "iso:country":"AU",
    "sg:address":"Unit 5/ 31 The Esplanade",
    "sg:city":"Cotton Tree",
    "sg:classifiers":[
        {
            "category":"Cafe",
            "type":"Food & Drink"
        }
    ],
    "sg:phone":"+61 7 5443 8494",
    "sg:postcode":"4558",
    "sg:province":"QLD",
    "wof:name":"Cafe Envy",
    "wof:placetype":"venue"
},
  "geometry": {"coordinates":[153.09808349599999,-26.655216217],"type":"Point"}
}