{
  "type": "Feature",
  "properties": {
    "iso:country":"AU",
    "sg:address":"Lewis Ave",
    "sg:city":"Mt Gambier",
    "sg:classifiers":[
        {
            "category":"Freight",
            "type":"Transportation"
        }
    ],
    "sg:phone":"+61 8 8725 1384",
    "sg:postcode":"5290",
    "sg:province":"SA",
    "sg:tags":[
        "light",
        "carrier"
    ],
    "wof:name":"Potter R G",
    "wof:placetype":"venue"
},
  "geometry": {"coordinates":[140.808685,-37.845524],"type":"Point"}
}