{
  "type": "Feature",
  "properties": {
    "addr:full":"Cnr Compton & North Rds Woodridge QLD 4114",
    "addr:postcode":"4114",
    "addr:street":"Cnr Compton & North Rds",
    "iso:country":"AU",
    "sg:address":"Cnr Compton & North Rds",
    "sg:city":"Woodridge",
    "sg:classifiers":[
        {
            "category":"Autos & Motor Vehicles",
            "subcategory":"Fuel & Gas Station",
            "type":"Retail Goods"
        }
    ],
    "sg:phone":"+61 7 3808 7154",
    "sg:postcode":"4114",
    "sg:province":"QLD",
    "wof:name":"BP",
    "wof:placetype":"venue"
},
  "geometry": {"coordinates":[153.10972595199999,-27.6193904877],"type":"Point"}
}