{
  "type": "Feature",
  "properties": {
    "addr:full":"509 Willarong Rd Caringbah NSW 2229",
    "addr:housenumber":"509",
    "addr:postcode":"2229",
    "addr:street":"Willarong Rd",
    "iso:country":"AU",
    "sg:address":"509 Willarong Rd",
    "sg:city":"Caringbah",
    "sg:classifiers":[
        {
            "category":"Utilities",
            "subcategory":"Electric",
            "type":"Services"
        }
    ],
    "sg:phone":"+61 2 9524 5803",
    "sg:postcode":"2229",
    "sg:province":"NSW",
    "sg:tags":[
        "electrical",
        "contractor"
    ],
    "wof:name":"Flynn C & S Pty Ltd",
    "wof:placetype":"venue"
},
  "geometry": {"coordinates":[151.10797119099999,-34.0597877502],"type":"Point"}
}