{
  "type": "Feature",
  "properties": {
    "addr:full":"95 Gaffney St Coburg North VIC 3058",
    "addr:housenumber":"95",
    "addr:postcode":"3058",
    "addr:street":"Gaffney St",
    "iso:country":"AU",
    "sg:address":"95 Gaffney St",
    "sg:city":"Coburg North",
    "sg:classifiers":[
        {
            "category":"Personal",
            "subcategory":"Beauty Salon",
            "type":"Services"
        }
    ],
    "sg:phone":"+61 3 9350 4724",
    "sg:postcode":"3058",
    "sg:province":"VIC",
    "sg:tags":[
        "hairdresser"
    ],
    "wof:name":"Guy Unisex Salon",
    "wof:placetype":"venue"
},
  "geometry": {"coordinates":[144.959152222,-37.7335166931],"type":"Point"}
}