{
  "type": "Feature",
  "properties": {
    "iso:country":"AU",
    "sg:address":"25 Burwood Hwy",
    "sg:city":"Burwood",
    "sg:classifiers":[
        {
            "category":"Military Area",
            "subcategory":"Armory",
            "type":"Public Place"
        }
    ],
    "sg:phone":"+61 3 9888 8987",
    "sg:postcode":"3125",
    "sg:province":"VIC",
    "sg:tags":[
        "teleconferencing"
    ],
    "wof:name":"IBS Audio Visual",
    "wof:placetype":"venue"
},
  "geometry": {"coordinates":[145.09684753400001,-37.8503684998],"type":"Point"}
}