{
  "type": "Feature",
  "properties": {
    "addr:full":"Unit 1 18 Devlan St Mansfield QLD 4122",
    "addr:housenumber":"18",
    "addr:postcode":"4122",
    "addr:street":"Devlan St",
    "iso:country":"AU",
    "sg:address":"Unit 1 18 Devlan St",
    "sg:city":"Mansfield",
    "sg:classifiers":[
        {
            "category":"Banks & Credit Unions",
            "subcategory":"Financial Services",
            "type":"Services"
        }
    ],
    "sg:phone":"+61 7 3349 4377",
    "sg:postcode":"4122",
    "sg:province":"QLD",
    "sg:tags":[
        "equipment",
        "chain"
    ],
    "wof:name":"Allsling & Bolt",
    "wof:placetype":"venue"
},
  "geometry": {"coordinates":[153.09710693400001,-27.5301036835],"type":"Point"}
}