{
  "type": "Feature",
  "properties": {
    "iso:country":"AU",
    "sg:address":"162 Auburn St",
    "sg:city":"Goulburn",
    "sg:classifiers":[
        {
            "category":"Personal",
            "type":"Services"
        }
    ],
    "sg:phone":"+61 2 4822 1234",
    "sg:postcode":"2580",
    "sg:province":"NSW",
    "sg:tags":[
        "gift"
    ],
    "wof:name":"Lyn's Floral Studio",
    "wof:placetype":"venue"
},
  "geometry": {"coordinates":[149.717819214,-34.7551040649],"type":"Point"}
}