{
  "type": "Feature",
  "properties": {
    "iso:country":"AU",
    "sg:address":"62 Grafton St",
    "sg:city":"Warwick",
    "sg:classifiers":[
        {
            "category":"Building & Trades",
            "subcategory":"Construction",
            "type":"Services"
        }
    ],
    "sg:phone":"+61 7 4661 7712",
    "sg:postcode":"4370",
    "sg:province":"QLD",
    "sg:tags":[
        "welding"
    ],
    "wof:name":"Matsons Engineering & Springworks",
    "wof:placetype":"venue"
},
  "geometry": {"coordinates":[152.03590393100001,-28.2167549133],"type":"Point"}
}