{
  "type": "Feature",
  "properties": {
    "addr:full":"17 Morlyn Drv Mt Martha VIC 3934",
    "addr:housenumber":"17",
    "addr:postcode":"3934",
    "addr:street":"Morlyn Drv Mt Martha",
    "iso:country":"AU",
    "sg:address":"17 Morlyn Drv",
    "sg:city":"Mt Martha",
    "sg:classifiers":[
        {
            "category":"Building & Trades",
            "subcategory":"Landscaping Services",
            "type":"Services"
        }
    ],
    "sg:phone":"+61 415 767 865",
    "sg:postcode":"3934",
    "sg:province":"VIC",
    "sg:tags":[
        "stump",
        "tree",
        "felling",
        "removal"
    ],
    "wof:name":"Bayside Loptops Tree Lopping",
    "wof:placetype":"venue"
},
  "geometry": {"coordinates":[145.03407287600001,-38.2539482117],"type":"Point"}
}