{
  "type": "Feature",
  "properties": {
    "addr:full":"Nicholson Pl Albury NSW 2640",
    "addr:postcode":"2640",
    "addr:street":"Pl",
    "iso:country":"AU",
    "sg:address":"Nicholson Pl",
    "sg:city":"Albury",
    "sg:classifiers":[
        {
            "category":"Social Services",
            "subcategory":"Retirement Home",
            "type":"Services"
        }
    ],
    "sg:phone":"+61 2 6042 1100",
    "sg:postcode":"2640",
    "sg:province":"NSW",
    "sg:tags":[
        "village"
    ],
    "wof:name":"Lutheran Aged Care - \"Pemberton View\"",
    "wof:placetype":"venue"
},
  "geometry": {"coordinates":[146.89210510300001,-36.0748977661],"type":"Point"}
}