{
  "type": "Feature",
  "properties": {
    "addr:full":"111 Poinciana Ave Tewantin QLD 4565",
    "addr:housenumber":"111",
    "addr:postcode":"4565",
    "addr:street":"Poinciana Ave",
    "iso:country":"AU",
    "sg:address":"111 Poinciana Ave",
    "sg:city":"Tewantin",
    "sg:classifiers":[
        {
            "category":"Real Estate",
            "subcategory":"Real Estate Agent",
            "type":"Services"
        }
    ],
    "sg:phone":"+61 7 5449 8077",
    "sg:postcode":"4565",
    "sg:province":"QLD",
    "wof:name":"Warren Evans Real Estate",
    "wof:placetype":"venue"
},
  "geometry": {"coordinates":[153.03890991200001,-26.391872406],"type":"Point"}
}