{
  "type": "Feature",
  "properties": {
    "addr:full":"Level 1, 163 Halifax St Adelaide SA 5000",
    "addr:housenumber":"163",
    "addr:postcode":"5000",
    "addr:street":"Halifax St",
    "iso:country":"AU",
    "sg:address":"Level 1, 163 Halifax St",
    "sg:city":"Adelaide",
    "sg:classifiers":[
        {
            "category":"Bars & Pubs",
            "subcategory":"Lounge",
            "type":"Food & Drink"
        }
    ],
    "sg:phone":"+61 8 8227 1800",
    "sg:postcode":"5000",
    "sg:province":"SA",
    "sg:tags":[
        "water",
        "filter",
        "drinking"
    ],
    "sg:website":"http://www.adelaidewatersmart.com.au",
    "wof:name":"AA Adelaide Watersmart",
    "wof:placetype":"venue"
},
  "geometry": {"coordinates":[138.60800170900001,-34.9326477051],"type":"Point"}
}