{
  "type": "Feature",
  "properties": {
    "addr:full":"21 Kilkenny Rd Woodville SA 5011",
    "addr:housenumber":"21",
    "addr:postcode":"5011",
    "addr:street":"Kilkenny Rd",
    "iso:country":"AU",
    "sg:address":"21 Kilkenny Rd",
    "sg:city":"Woodville",
    "sg:classifiers":[
        {
            "category":"Building & Trades",
            "subcategory":"Electrical",
            "type":"Services"
        }
    ],
    "sg:phone":"+61 8 8445 7388",
    "sg:postcode":"5011",
    "sg:province":"SA",
    "sg:tags":[
        "testing",
        "tagging"
    ],
    "wof:name":"CJ Electrical",
    "wof:placetype":"venue"
},
  "geometry": {"coordinates":[138.548995972,-34.886516571],"type":"Point"}
}