{
  "type": "Feature",
  "properties": {
    "addr:full":"35 Broadwater Rd Upper Mt Gravatt QLD 4122",
    "addr:housenumber":"35",
    "addr:postcode":"4122",
    "addr:street":"Broadwater Rd Upper",
    "iso:country":"AU",
    "sg:address":"35 Broadwater Rd",
    "sg:city":"Upper Mt Gravatt",
    "sg:classifiers":[
        {
            "category":"Professional",
            "subcategory":"Employment Agencies",
            "type":"Services"
        }
    ],
    "sg:phone":"+61 7 3399 8028",
    "sg:postcode":"4122",
    "sg:province":"QLD",
    "sg:tags":[
        "occupational",
        "therapist"
    ],
    "wof:name":"Tyquin Group",
    "wof:placetype":"venue"
},
  "geometry": {"coordinates":[153.083786011,-27.5423698425],"type":"Point"}
}