{
  "type": "Feature",
  "properties": {
    "addr:full":"2 Epson Pl Bateau Bay NSW 2261",
    "addr:housenumber":"2",
    "addr:postcode":"2261",
    "addr:street":"Epson Pl",
    "iso:country":"AU",
    "sg:address":"2 Epson Pl",
    "sg:city":"Bateau Bay",
    "sg:classifiers":[
        {
            "category":"Professional",
            "subcategory":"Computer Services",
            "type":"Services"
        }
    ],
    "sg:phone":"+61 1300 650 099",
    "sg:postcode":"2261",
    "sg:province":"NSW",
    "sg:tags":[
        "package",
        "software"
    ],
    "wof:name":"Checkbox Solutions",
    "wof:placetype":"venue"
},
  "geometry": {"coordinates":[151.46942100000001,-33.389194],"type":"Point"}
}