{
  "type": "Feature",
  "properties": {
    "addr:full":"32 Alfrieda St St Albans VIC 3021",
    "addr:housenumber":"32",
    "addr:postcode":"3021",
    "addr:street":"Alfrieda St",
    "iso:country":"AU",
    "sg:address":"32 Alfrieda St",
    "sg:city":"St Albans",
    "sg:classifiers":[
        {
            "category":"Food & Beverages",
            "subcategory":"Supermarket",
            "type":"Retail Goods"
        }
    ],
    "sg:phone":"+61 3 9366 6518",
    "sg:postcode":"3021",
    "sg:province":"VIC",
    "sg:tags":[
        "grocery",
        "store"
    ],
    "wof:name":"Kim Minh Asian Grocery",
    "wof:placetype":"venue"
},
  "geometry": {"coordinates":[144.80088799999999,-37.743214],"type":"Point"}
}