{
  "type": "Feature",
  "properties": {
    "addr:full":"David Muir St Mackay QLD 4740",
    "addr:postcode":"4740",
    "addr:street":"Muir St",
    "iso:country":"AU",
    "sg:address":"David Muir St",
    "sg:city":"Mackay",
    "sg:classifiers":[
        {
            "category":"Building & Trades",
            "subcategory":"Construction",
            "type":"Services"
        }
    ],
    "sg:phone":"+61 7 4955 4860",
    "sg:postcode":"4740",
    "sg:province":"QLD",
    "sg:tags":[
        "window",
        "aluminium"
    ],
    "wof:name":"G. James Glass & Aluminium",
    "wof:placetype":"venue"
},
  "geometry": {"coordinates":[149.21534700000001,-21.089565],"type":"Point"}
}