{
  "type": "Feature",
  "properties": {
    "addr:full":"232 Young St Unley SA 5061",
    "addr:housenumber":"232",
    "addr:postcode":"5061",
    "addr:street":"Young St",
    "iso:country":"AU",
    "sg:address":"232 Young St",
    "sg:city":"Unley",
    "sg:classifiers":[
        {
            "category":"Home & Garden",
            "subcategory":"Carpets & Floor Coverings",
            "type":"Retail Goods"
        }
    ],
    "sg:phone":"+61 8 8272 3885",
    "sg:postcode":"5061",
    "sg:province":"SA",
    "sg:tags":[
        "tile",
        "wall",
        "layer"
    ],
    "wof:name":"Cappello Damien",
    "wof:placetype":"venue"
},
  "geometry": {"coordinates":[138.602294922,-34.9447288513],"type":"Point"}
}