{
  "type": "Feature",
  "properties": {
    "iso:country":"AU",
    "sg:address":"229 River St",
    "sg:city":"Maclean",
    "sg:classifiers":[
        {
            "category":"Real Estate",
            "subcategory":"Real Estate Agent",
            "type":"Services"
        }
    ],
    "sg:phone":"+61 2 6645 2222",
    "sg:postcode":"2463",
    "sg:province":"NSW",
    "wof:name":"L J Hooker Maclean",
    "wof:placetype":"venue"
},
  "geometry": {"coordinates":[153.19694519000001,-29.4568004608],"type":"Point"}
}