{
  "type": "Feature",
  "properties": {
    "addr:full":"115 Armstrong St (North) Ballarat VIC 3350",
    "addr:housenumber":"115",
    "addr:postcode":"3350",
    "addr:street":"Armstrong St North",
    "iso:country":"AU",
    "sg:address":"115 Armstrong St (North)",
    "sg:city":"Ballarat",
    "sg:classifiers":[
        {
            "category":"Retail",
            "subcategory":"Repair Shop",
            "type":"Services"
        }
    ],
    "sg:phone":"+61 3 5332 9919",
    "sg:postcode":"3350",
    "sg:province":"VIC",
    "sg:tags":[
        "machine",
        "repairs",
        "part",
        "dryer",
        "washing"
    ],
    "wof:name":"Ballarat Associated Appliance Service",
    "wof:placetype":"venue"
},
  "geometry": {"coordinates":[143.85569799999999,-37.565762],"type":"Point"}
}