{
  "type": "Feature",
  "properties": {
    "iso:country":"AU",
    "sg:address":"12 Tuscan Crt",
    "sg:city":"Thomastown",
    "sg:classifiers":[
        {
            "category":"Building & Trades",
            "subcategory":"Pest Control",
            "type":"Services"
        }
    ],
    "sg:phone":"+61 3 9462 5599",
    "sg:postcode":"3074",
    "sg:province":"VIC",
    "sg:tags":[
        "robot"
    ],
    "wof:name":"Mechanimation",
    "wof:placetype":"venue"
},
  "geometry": {"coordinates":[145.005126953,-37.6875991821],"type":"Point"}
}