{
  "type": "Feature",
  "properties": {
    "addr:full":"Factory 2- 17 Gantry Pl Braemar NSW 2575",
    "addr:housenumber":"17",
    "addr:postcode":"2575",
    "addr:street":"Gantry Pl",
    "iso:country":"AU",
    "sg:address":"Factory 2- 17 Gantry Pl",
    "sg:city":"Braemar",
    "sg:classifiers":[
        {
            "category":"Home & Garden",
            "subcategory":"Carpets & Floor Coverings",
            "type":"Retail Goods"
        }
    ],
    "sg:phone":"+61 2 4872 2999",
    "sg:postcode":"2575",
    "sg:province":"NSW",
    "sg:tags":[
        "double",
        "window",
        "glazed"
    ],
    "wof:name":"Platinum Windows & Doors",
    "wof:placetype":"venue"
},
  "geometry": {"coordinates":[150.478424072,-34.4244117737],"type":"Point"}
}