{
  "type": "Feature",
  "properties": {
    "addr:full":"Shp 4 Lvl 3 Ashfield Mall Liverpool Rd Ashfield NSW 2131",
    "addr:housenumber":"3",
    "addr:postcode":"2131",
    "addr:street":"Ashfield Mall Liverpool Rd",
    "iso:country":"AU",
    "sg:address":"Shp 4 Lvl 3 Ashfield Mall Liverpool Rd",
    "sg:city":"Ashfield",
    "sg:classifiers":[
        {
            "category":"Health Services",
            "subcategory":"Optometrist",
            "type":"Services"
        }
    ],
    "sg:phone":"+61 2 9716 4807",
    "sg:postcode":"2131",
    "sg:province":"NSW",
    "wof:name":"Papatheodorou Chris",
    "wof:placetype":"venue"
},
  "geometry": {"coordinates":[151.12663269000001,-33.8897666931],"type":"Point"}
}