{
  "type": "Feature",
  "properties": {
    "addr:full":"U 15/ 8 Gladstone Rd Castle Hill NSW 2154",
    "addr:housenumber":"15 / 8",
    "addr:postcode":"2154",
    "addr:street":"Gladstone Rd",
    "iso:country":"AU",
    "sg:address":"U 15/ 8 Gladstone Rd",
    "sg:city":"Castle Hill",
    "sg:classifiers":[
        {
            "category":"Professional",
            "subcategory":"Art Services",
            "type":"Services"
        }
    ],
    "sg:phone":"+61 2 9894 5036",
    "sg:postcode":"2154",
    "sg:province":"NSW",
    "sg:tags":[
        "picture",
        "frame",
        "framing"
    ],
    "wof:name":"Cotswold Picture Framing",
    "wof:placetype":"venue"
},
  "geometry": {"coordinates":[150.976837158,-33.7334098816],"type":"Point"}
}