{
  "type": "Feature",
  "properties": {
    "iso:country":"AU",
    "sg:address":"11 Maitland St",
    "sg:city":"Muswellbrook",
    "sg:classifiers":[
        {
            "category":"Utilities",
            "type":"Services"
        }
    ],
    "sg:phone":"+61 2 6543 3333",
    "sg:postcode":"2333",
    "sg:province":"NSW",
    "sg:tags":[
        "equipment",
        "towing"
    ],
    "wof:name":"Auto One Muswellbrook",
    "wof:placetype":"venue"
},
  "geometry": {"coordinates":[150.88706970199999,-32.2686080933],"type":"Point"}
}