{
  "type": "Feature",
  "properties": {
    "addr:full":"L1 318 Forest Rd Hurstville NSW 2220",
    "addr:housenumber":"318",
    "addr:postcode":"2220",
    "addr:street":"Forest Rd",
    "iso:country":"AU",
    "sg:address":"L1 318 Forest Rd",
    "sg:city":"Hurstville",
    "sg:classifiers":[
        {
            "category":"Professional",
            "subcategory":"Accounting & Tax Preparation",
            "type":"Services"
        }
    ],
    "sg:phone":"+61 2 9586 3022",
    "sg:postcode":"2220",
    "sg:province":"NSW",
    "sg:tags":[
        "consultant",
        "taxation"
    ],
    "wof:name":"Raymond Huang & Co. CPA",
    "wof:placetype":"venue"
},
  "geometry": {"coordinates":[151.102218628,-33.96641922],"type":"Point"}
}