{
  "type": "Feature",
  "properties": {
    "addr:full":"Shp 7/ 76 Beach Rd Christies Beach SA 5165",
    "addr:housenumber":"/ 76",
    "addr:postcode":"5165",
    "addr:street":"Beach Rd",
    "iso:country":"AU",
    "sg:address":"Shp 7/ 76 Beach Rd",
    "sg:city":"Christies Beach",
    "sg:classifiers":[
        {
            "category":"Professional",
            "subcategory":"Accounting & Tax Preparation",
            "type":"Services"
        }
    ],
    "sg:phone":"+61 8 8326 6850",
    "sg:postcode":"5165",
    "sg:province":"SA",
    "sg:tags":[
        "consultant",
        "taxation"
    ],
    "wof:name":"H&R Block",
    "wof:placetype":"venue"
},
  "geometry": {"coordinates":[138.483840942,-35.1389083862],"type":"Point"}
}