{
  "type": "Feature",
  "properties": {
    "addr:full":"24 Coghlans Rd Warrnambool VIC 3280",
    "addr:housenumber":"24",
    "addr:postcode":"3280",
    "addr:street":"Coghlans Rd",
    "iso:country":"AU",
    "sg:address":"24 Coghlans Rd",
    "sg:city":"Warrnambool",
    "sg:classifiers":[
        {
            "category":"Retail",
            "subcategory":"Auto Repair",
            "type":"Services"
        }
    ],
    "sg:phone":"+61 3 5561 3919",
    "sg:postcode":"3280",
    "sg:province":"VIC",
    "sg:tags":[
        "recapping",
        "repairing",
        "retreading",
        "tyre"
    ],
    "wof:name":"Richardson Bros Retreading Pty Ltd",
    "wof:placetype":"venue"
},
  "geometry": {"coordinates":[142.461959839,-38.3519935608],"type":"Point"}
}