{
  "type": "Feature",
  "properties": {
    "iso:country":"AU",
    "sg:address":"Forrester Rd St",
    "sg:city":"Marys",
    "sg:classifiers":[
        {
            "category":"Community Center",
            "type":"Public Place"
        }
    ],
    "sg:phone":"+61 1300 135 309",
    "sg:postcode":"2760",
    "sg:province":"NSW",
    "sg:tags":[
        "interference",
        "frequency",
        "radio",
        "screening"
    ],
    "wof:name":"ADI EMC Test Services",
    "wof:placetype":"venue"
},
  "geometry": {"coordinates":[150.776977539,-33.7487945557],"type":"Point"}
}