{
  "type": "Feature",
  "properties": {
    "addr:full":"63 Boomerang Rd Edensor Park NSW 2176",
    "addr:housenumber":"63",
    "addr:postcode":"2176",
    "addr:street":"Boomerang Rd",
    "iso:country":"AU",
    "sg:address":"63 Boomerang Rd",
    "sg:city":"Edensor Park",
    "sg:classifiers":[
        {
            "category":"Utilities",
            "subcategory":"Electric",
            "type":"Services"
        }
    ],
    "sg:phone":"+61 2 9610 6263",
    "sg:postcode":"2176",
    "sg:province":"NSW",
    "sg:tags":[
        "electrical",
        "contractor"
    ],
    "wof:name":"Oliveri Electrical Contractors Pty Ltd",
    "wof:placetype":"venue"
},
  "geometry": {"coordinates":[150.883865356,-33.8822212219],"type":"Point"}
}