{
  "type": "Feature",
  "properties": {
    "iso:country":"AU",
    "sg:address":"34 Howard St",
    "sg:city":"Nambour",
    "sg:classifiers":[
        {
            "category":"Organizations",
            "subcategory":"Non-profit Organization",
            "type":"Services"
        }
    ],
    "sg:phone":"+61 7 5441 7278",
    "sg:postcode":"4560",
    "sg:province":"QLD",
    "sg:tags":[
        "support",
        "disability",
        "organisation"
    ],
    "wof:name":"Sunshine Coast Independent Living Service",
    "wof:placetype":"venue"
},
  "geometry": {"coordinates":[152.95860290499999,-26.6298427582],"type":"Point"}
}