{
  "type": "Feature",
  "properties": {
    "addr:full":"43- 47 Simpson St Northcote VIC 3070",
    "addr:housenumber":"47",
    "addr:postcode":"3070",
    "addr:street":"Simpson St",
    "iso:country":"AU",
    "sg:address":"43- 47 Simpson St",
    "sg:city":"Northcote",
    "sg:classifiers":[
        {
            "category":"Food & Beverages",
            "subcategory":"Bakery",
            "type":"Retail Goods"
        }
    ],
    "sg:phone":"+61 3 9489 0433",
    "sg:postcode":"3070",
    "sg:province":"VIC",
    "sg:tags":[
        "baker"
    ],
    "wof:name":"Telstar Bakery Pty Ltd",
    "wof:placetype":"venue"
},
  "geometry": {"coordinates":[145.006699,-37.778355],"type":"Point"}
}