{
  "type": "Feature",
  "properties": {
    "addr:full":"1543 Ipswich Rd Rocklea QLD 4106",
    "addr:housenumber":"1543",
    "addr:postcode":"4106",
    "addr:street":"Ipswich Rd",
    "iso:country":"AU",
    "sg:address":"1543 Ipswich Rd",
    "sg:city":"Rocklea",
    "sg:classifiers":[
        {
            "category":"Manufacturing",
            "subcategory":"Motor Vehicles & Parts",
            "type":"Manufacturing & Wholesale Goods"
        }
    ],
    "sg:phone":"+61 7 3277 0588",
    "sg:postcode":"4106",
    "sg:province":"QLD",
    "sg:tags":[
        "engine",
        "equipment",
        "diesel"
    ],
    "wof:name":"Rocklea Wrecking",
    "wof:placetype":"venue"
},
  "geometry": {"coordinates":[153.008834839,-27.5516910553],"type":"Point"}
}