{
  "type": "Feature",
  "properties": {
    "iso:country":"AU",
    "sg:address":"500 Station St",
    "sg:city":"Carrum",
    "sg:classifiers":[
        {
            "category":"Professional",
            "subcategory":"Accounting & Tax Preparation",
            "type":"Services"
        }
    ],
    "sg:phone":"+61 3 9772 2988",
    "sg:postcode":"3197",
    "sg:province":"VIC",
    "sg:tags":[
        "accountant",
        "auditor"
    ],
    "wof:name":"Murnane B P & Associates",
    "wof:placetype":"venue"
},
  "geometry": {"coordinates":[145.122802734,-38.0749282837],"type":"Point"}
}