{
  "type": "Feature",
  "properties": {
    "iso:country":"AU",
    "sg:address":"27 Cotswold Rd",
    "sg:city":"Strathfield",
    "sg:classifiers":[
        {
            "category":"Health Services",
            "subcategory":"Doctor",
            "type":"Services"
        }
    ],
    "sg:phone":"+61 2 9642 7484",
    "sg:postcode":"2135",
    "sg:province":"NSW",
    "sg:tags":[
        "medical",
        "practitioner"
    ],
    "wof:name":"Zagreb Medical Centre Pty Ltd",
    "wof:placetype":"venue"
},
  "geometry": {"coordinates":[151.08648681599999,-33.8815193176],"type":"Point"}
}