{
  "type": "Feature",
  "properties": {
    "addr:full":"76 Watton St Werribee VIC 3030",
    "addr:housenumber":"76",
    "addr:postcode":"3030",
    "addr:street":"Watton St",
    "iso:country":"AU",
    "sg:address":"76 Watton St",
    "sg:city":"Werribee",
    "sg:classifiers":[
        {
            "category":"Shopping",
            "subcategory":"Clothing, Apparel, & Fashions",
            "type":"Retail Goods"
        }
    ],
    "sg:phone":"+61 3 9974 0411",
    "sg:postcode":"3030",
    "sg:province":"VIC",
    "sg:tags":[
        "menswear"
    ],
    "wof:name":"Sires Suits & Menswear",
    "wof:placetype":"venue"
},
  "geometry": {"coordinates":[144.658401,-37.902748],"type":"Point"}
}