{
  "type": "Feature",
  "properties": {
    "addr:full":"11 Goyder Rd Parap NT 0820",
    "addr:housenumber":"11",
    "addr:postcode":"nt 0820",
    "addr:street":"Goyder Rd",
    "iso:country":"AU",
    "sg:address":"11 Goyder Rd",
    "sg:city":"Parap",
    "sg:classifiers":[
        {
            "category":"Professional",
            "subcategory":"Management & Consulting",
            "type":"Services"
        }
    ],
    "sg:phone":"+61 8 8923 4888",
    "sg:postcode":"0820",
    "sg:province":"NT",
    "sg:tags":[
        "consultant",
        "energy"
    ],
    "wof:name":"All Energy Consultants",
    "wof:placetype":"venue"
},
  "geometry": {"coordinates":[130.83958435100001,-12.4382152557],"type":"Point"}
}