{
  "type": "Feature",
  "properties": {
    "addr:full":"68a Stanbell Rd Salisbury Plain SA 5109",
    "addr:housenumber":"68a",
    "addr:postcode":"5109",
    "addr:street":"Stanbell Rd",
    "iso:country":"AU",
    "sg:address":"68a Stanbell Rd",
    "sg:city":"Salisbury Plain",
    "sg:classifiers":[
        {
            "category":"Retail",
            "subcategory":"Storage",
            "type":"Services"
        }
    ],
    "sg:phone":"+61 1800 357 676",
    "sg:postcode":"5109",
    "sg:province":"SA",
    "sg:tags":[
        "removal",
        "furniture"
    ],
    "sg:website":"http://www.acrossaus.com.au",
    "wof:name":"Across Australia Removals",
    "wof:placetype":"venue"
},
  "geometry": {"coordinates":[138.65914917000001,-34.7691459656],"type":"Point"}
}