{
  "type": "Feature",
  "properties": {
    "addr:full":"69 Railway Ave Railway Estate QLD 4810",
    "addr:housenumber":"69",
    "addr:postcode":"4810",
    "addr:street":"Railway Ave Railway",
    "iso:country":"AU",
    "sg:address":"69 Railway Ave",
    "sg:city":"Railway Estate",
    "sg:classifiers":[
        {
            "category":"Food & Beverages",
            "subcategory":"Liquor & Beverages",
            "type":"Retail Goods"
        }
    ],
    "sg:phone":"+61 7 4724 2177",
    "sg:postcode":"4810",
    "sg:province":"QLD",
    "sg:tags":[
        "store"
    ],
    "wof:name":"Railway Estate Bottleshop",
    "wof:placetype":"venue"
},
  "geometry": {"coordinates":[146.815933,-19.278175],"type":"Point"}
}