{
  "type": "Feature",
  "properties": {
    "addr:full":"25 Prowse St West Perth WA 6005",
    "addr:housenumber":"25",
    "addr:postcode":"6005",
    "addr:street":"Prowse St",
    "iso:country":"AU",
    "sg:address":"25 Prowse St",
    "sg:city":"West Perth",
    "sg:classifiers":[
        {
            "category":"Health Services",
            "subcategory":"Doctor",
            "type":"Services"
        }
    ],
    "sg:phone":"+61 8 9321 0007",
    "sg:postcode":"6005",
    "sg:province":"WA",
    "sg:tags":[
        "medical",
        "practitioner"
    ],
    "wof:name":"Kierath Tony Mr",
    "wof:placetype":"venue"
},
  "geometry": {"coordinates":[115.841003418,-31.9447479248],"type":"Point"}
}