{
  "type": "Feature",
  "properties": {
    "iso:country":"AU",
    "sg:address":"47 Warner St",
    "sg:city":"Fortitude Valley",
    "sg:classifiers":[
        {
            "category":"Shopping",
            "subcategory":"Computers & Home Electronics",
            "type":"Retail Goods"
        }
    ],
    "sg:phone":"+61 7 3308 2060",
    "sg:postcode":"4006",
    "sg:province":"QLD",
    "sg:tags":[
        "equipment",
        "multimedia"
    ],
    "wof:name":"BCM Digital",
    "wof:placetype":"venue"
},
  "geometry": {"coordinates":[153.03456115700001,-27.4568080902],"type":"Point"}
}