{
  "type": "Feature",
  "properties": {
    "addr:full":"Fitzroy St North Dubbo NSW 2830",
    "addr:postcode":"2830",
    "addr:street":"Fitzroy St North",
    "iso:country":"AU",
    "sg:address":"Fitzroy St",
    "sg:city":"North Dubbo",
    "sg:classifiers":[
        {
            "category":"Building & Trades",
            "subcategory":"Construction",
            "type":"Services"
        }
    ],
    "sg:phone":"+61 2 6882 1000",
    "sg:postcode":"2830",
    "sg:province":"NSW",
    "sg:tags":[
        "contractor"
    ],
    "wof:name":"Dubbo Terrazzo & Concrete Industries",
    "wof:placetype":"venue"
},
  "geometry": {"coordinates":[148.61529540999999,-32.2392272949],"type":"Point"}
}