{
  "type": "Feature",
  "properties": {
    "addr:full":"Shop 403 , Robina Town Centre Shopping Centre Robina QLD 4226",
    "addr:housenumber":"403",
    "addr:postcode":"4226",
    "addr:street":"Robina",
    "iso:country":"AU",
    "sg:address":"Shop 403",
    "sg:city":", Robina Town Centre Shopping Centre Robina",
    "sg:classifiers":[
        {
            "category":"Banks & Credit Unions",
            "subcategory":"Financial Services",
            "type":"Services"
        }
    ],
    "sg:phone":"+61 7 5593 2839",
    "sg:postcode":"4226",
    "sg:province":"QLD",
    "sg:tags":[
        "building",
        "society"
    ],
    "wof:name":"Wide Bay Australia Ltd",
    "wof:placetype":"venue"
},
  "geometry": {"coordinates":[153.38783264200001,-28.0696353912],"type":"Point"}
}