{
  "type": "Feature",
  "properties": {
    "iso:country":"AU",
    "sg:address":"15 Dendy St",
    "sg:city":"Brighton",
    "sg:classifiers":[
        {
            "category":"Metro Station",
            "type":"Transportation"
        }
    ],
    "sg:phone":"+61 3 9592 9760",
    "sg:postcode":"3186",
    "sg:province":"VIC",
    "sg:tags":[
        "consultant",
        "marine"
    ],
    "wof:name":"Andersson Kjell",
    "wof:placetype":"venue"
},
  "geometry": {"coordinates":[144.991165161,-37.9191055298],"type":"Point"}
}