{
  "type": "Feature",
  "properties": {
    "iso:country":"AU",
    "sg:address":"3 Oban Rd",
    "sg:city":"Ringwood",
    "sg:classifiers":[
        {
            "category":"Autos & Motor Vehicles",
            "subcategory":"Auto Supplies",
            "type":"Retail Goods"
        }
    ],
    "sg:phone":"+61 3 9870 1939",
    "sg:postcode":"3134",
    "sg:province":"VIC",
    "sg:tags":[
        "automotive",
        "stereo",
        "radio"
    ],
    "wof:name":"Insane Audio",
    "wof:placetype":"venue"
},
  "geometry": {"coordinates":[145.253616333,-37.7977790833],"type":"Point"}
}