{
  "type": "Feature",
  "properties": {
    "addr:full":"33-35 Ringwood St Ringwood VIC 3134",
    "addr:housenumber":"33-35",
    "addr:postcode":"3134",
    "addr:street":"Ringwood St",
    "iso:country":"AU",
    "sg:address":"33-35 Ringwood St",
    "sg:city":"Ringwood",
    "sg:classifiers":[
        {
            "category":"Cafe",
            "type":"Food & Drink"
        }
    ],
    "sg:phone":"+61 3 9870 7633",
    "sg:postcode":"3134",
    "sg:province":"VIC",
    "wof:name":"Cafe 35",
    "wof:placetype":"venue"
},
  "geometry": {"coordinates":[145.22718810999999,-37.8147850037],"type":"Point"}
}