{
  "type": "Feature",
  "properties": {
    "addr:full":"282 St Georges Rd Northcote VIC 3070",
    "addr:housenumber":"282",
    "addr:postcode":"3070",
    "addr:street":"St Georges Rd",
    "iso:country":"AU",
    "sg:address":"282 St Georges Rd",
    "sg:city":"Northcote",
    "sg:classifiers":[
        {
            "category":"Shopping",
            "subcategory":"Computers & Home Electronics",
            "type":"Retail Goods"
        }
    ],
    "sg:phone":"+61 3 9484 6162",
    "sg:postcode":"3070",
    "sg:province":"VIC",
    "sg:tags":[
        "hardware",
        "equipment"
    ],
    "wof:name":"Max Computer Engineering",
    "wof:placetype":"venue"
},
  "geometry": {"coordinates":[144.99307300000001,-37.761951],"type":"Point"}
}