{
  "type": "Feature",
  "properties": {
    "iso:country":"AU",
    "sg:address":"77 Boundary Rd",
    "sg:city":"Mortdale",
    "sg:classifiers":[
        {
            "category":"Shopping",
            "subcategory":"Beauty & Cosmetics",
            "type":"Retail Goods"
        }
    ],
    "sg:phone":"+61 2 9584 2678",
    "sg:postcode":"2223",
    "sg:province":"NSW",
    "sg:tags":[
        "equipment",
        "salon",
        "supply"
    ],
    "wof:name":"Beauty Warehouse",
    "wof:placetype":"venue"
},
  "geometry": {"coordinates":[151.06930542000001,-33.9653663635],"type":"Point"}
}