{
  "type": "Feature",
  "properties": {
    "iso:country":"AU",
    "sg:address":"4 George Ave",
    "sg:city":"Valley View",
    "sg:classifiers":[
        {
            "category":"Education",
            "subcategory":"Special Training",
            "type":"Public Place"
        }
    ],
    "sg:phone":"+61 8 8264 3857",
    "sg:postcode":"5093",
    "sg:province":"SA",
    "sg:tags":[
        "tuition-educational"
    ],
    "wof:name":"Reading For Sure",
    "wof:placetype":"venue"
},
  "geometry": {"coordinates":[138.66560363799999,-34.8372306824],"type":"Point"}
}