{
  "type": "Feature",
  "properties": {
    "addr:full":"Unit 7, 17- 23 Oatley Crt Belconnen ACT 2617",
    "addr:housenumber":"17 23",
    "addr:postcode":"2617",
    "addr:street":"Oatley Crt",
    "iso:country":"AU",
    "sg:address":"Unit 7, 17- 23 Oatley Crt",
    "sg:city":"Belconnen",
    "sg:classifiers":[
        {
            "category":"Professional",
            "subcategory":"Management & Consulting",
            "type":"Services"
        }
    ],
    "sg:phone":"+61 2 6251 5133",
    "sg:postcode":"2617",
    "sg:province":"ACT",
    "sg:tags":[
        "information"
    ],
    "wof:name":"Commercial Computer Centre Pty Ltd",
    "wof:placetype":"venue"
},
  "geometry": {"coordinates":[149.060012817,-35.2412605286],"type":"Point"}
}