{
  "type": "Feature",
  "properties": {
    "addr:full":"20 Raleigh Ave Flinders Park SA 5025",
    "addr:housenumber":"20",
    "addr:postcode":"5025",
    "addr:street":"Raleigh Ave Flinders",
    "iso:country":"AU",
    "sg:address":"20 Raleigh Ave",
    "sg:city":"Flinders Park",
    "sg:classifiers":[
        {
            "category":"Home & Garden",
            "subcategory":"Building Materials",
            "type":"Retail Goods"
        }
    ],
    "sg:phone":"+61 8 8352 2657",
    "sg:postcode":"5025",
    "sg:province":"SA",
    "sg:tags":[
        "lawn",
        "cutting",
        "maintenance"
    ],
    "wof:name":"M & MR Frisby-Smith",
    "wof:placetype":"venue"
},
  "geometry": {"coordinates":[138.544998169,-34.9065856934],"type":"Point"}
}