{
  "type": "Feature",
  "properties": {
    "addr:full":"197 Murarrie Rd Murarrie QLD 4172",
    "addr:housenumber":"197",
    "addr:postcode":"4172",
    "addr:street":"Murarrie Rd",
    "iso:country":"AU",
    "sg:address":"197 Murarrie Rd",
    "sg:city":"Murarrie",
    "sg:classifiers":[
        {
            "category":"Autos & Motor Vehicles",
            "subcategory":"Auto Supplies",
            "type":"Retail Goods"
        }
    ],
    "sg:phone":"+61 7 3390 4148",
    "sg:postcode":"4172",
    "sg:province":"QLD",
    "sg:tags":[
        "tyre"
    ],
    "wof:name":"Ace Tyres & Auto Care",
    "wof:placetype":"venue"
},
  "geometry": {"coordinates":[153.10041809099999,-27.4660282135],"type":"Point"}
}