{
  "type": "Feature",
  "properties": {
    "addr:full":"33- 37 Craig St Long Gully VIC 3550",
    "addr:housenumber":"37",
    "addr:postcode":"3550",
    "addr:street":"Craig St Long",
    "iso:country":"AU",
    "sg:address":"33- 37 Craig St",
    "sg:city":"Long Gully",
    "sg:classifiers":[
        {
            "category":"Wholesale",
            "subcategory":"Painting Supplies",
            "type":"Manufacturing & Wholesale Goods"
        }
    ],
    "sg:phone":"+61 3 5441 2510",
    "sg:postcode":"3550",
    "sg:province":"VIC",
    "sg:tags":[
        "product",
        "cleaning"
    ],
    "wof:name":"Qualchem",
    "wof:placetype":"venue"
},
  "geometry": {"coordinates":[144.262542725,-36.7413444519],"type":"Point"}
}