{
  "type": "Feature",
  "properties": {
    "iso:country":"AU",
    "sg:address":"1362 North Rd",
    "sg:city":"Oakleigh South",
    "sg:classifiers":[
        {
            "category":"Industrial Area",
            "type":"Public Place"
        }
    ],
    "sg:phone":"+61 3 9543 7888",
    "sg:postcode":"3167",
    "sg:province":"VIC",
    "sg:tags":[
        "protective",
        "clothing"
    ],
    "wof:name":"Absolute Safety",
    "wof:placetype":"venue"
},
  "geometry": {"coordinates":[145.11062622099999,-37.9127235413],"type":"Point"}
}