{
  "type": "Feature",
  "properties": {
    "addr:full":"83 Victoria St Prospect SA 5082",
    "addr:housenumber":"83",
    "addr:postcode":"5082",
    "addr:street":"Victoria St",
    "iso:country":"AU",
    "sg:address":"83 Victoria St",
    "sg:city":"Prospect",
    "sg:classifiers":[
        {
            "category":"Bars & Pubs",
            "subcategory":"Lounge",
            "type":"Food & Drink"
        }
    ],
    "sg:phone":"+61 411 106 216",
    "sg:postcode":"5082",
    "sg:province":"SA",
    "sg:tags":[
        "water",
        "filter",
        "drinking"
    ],
    "wof:name":"Filtertap",
    "wof:placetype":"venue"
},
  "geometry": {"coordinates":[138.58578491200001,-34.8807525635],"type":"Point"}
}