{
  "type": "Feature",
  "properties": {
    "iso:country":"AU",
    "sg:address":"200 Smith La",
    "sg:city":"Broadford",
    "sg:classifiers":[
        {
            "category":"Building & Trades",
            "subcategory":"Construction",
            "type":"Services"
        }
    ],
    "sg:phone":"+61 403 635 899",
    "sg:postcode":"3658",
    "sg:province":"VIC",
    "sg:tags":[
        "concrete",
        "contractor"
    ],
    "wof:name":"CRD Concreting",
    "wof:placetype":"venue"
},
  "geometry": {"coordinates":[145.06198120100001,-37.2066802979],"type":"Point"}
}