{
  "type": "Feature",
  "properties": {
    "addr:full":"2 Peter St Doncaster East VIC 3109",
    "addr:housenumber":"2",
    "addr:postcode":"3109",
    "addr:street":"Peter St",
    "iso:country":"AU",
    "sg:address":"2 Peter St",
    "sg:city":"Doncaster East",
    "sg:classifiers":[
        {
            "category":"Professional",
            "subcategory":"Secretarial Services",
            "type":"Services"
        }
    ],
    "sg:phone":"+61 3 9848 1022",
    "sg:postcode":"3109",
    "sg:province":"VIC",
    "sg:tags":[
        "typing"
    ],
    "wof:name":"Daily Words",
    "wof:placetype":"venue"
},
  "geometry": {"coordinates":[145.146972656,-37.7945823669],"type":"Point"}
}