{
  "type": "Feature",
  "properties": {
    "addr:full":"Unit 4/ 19 Gatwick Rd Bayswater VIC 3153",
    "addr:housenumber":"19",
    "addr:postcode":"3153",
    "addr:street":"Gatwick Rd",
    "iso:country":"AU",
    "sg:address":"Unit 4/ 19 Gatwick Rd",
    "sg:city":"Bayswater",
    "sg:classifiers":[
        {
            "category":"Shopping",
            "subcategory":"Stationery & Office Supplies",
            "type":"Retail Goods"
        }
    ],
    "sg:phone":"+61 3 9761 6022",
    "sg:postcode":"3153",
    "sg:province":"VIC",
    "sg:tags":[
        "merchant",
        "paper"
    ],
    "wof:name":"Conservation Paper Pty Ltd",
    "wof:placetype":"venue"
},
  "geometry": {"coordinates":[145.296585083,-37.8220481873],"type":"Point"}
}