{
  "type": "Feature",
  "properties": {
    "addr:full":"40 Talbot St Colac VIC 3250",
    "addr:housenumber":"40",
    "addr:postcode":"3250",
    "addr:street":"Talbot St",
    "iso:country":"AU",
    "sg:address":"40 Talbot St",
    "sg:city":"Colac",
    "sg:classifiers":[
        {
            "category":"Shopping",
            "subcategory":"Stationery & Office Supplies",
            "type":"Retail Goods"
        }
    ],
    "sg:phone":"+61 3 5231 2763",
    "sg:postcode":"3250",
    "sg:province":"VIC",
    "sg:tags":[
        "equipment",
        "dairy"
    ],
    "wof:name":"B.C.S. Engineering",
    "wof:placetype":"venue"
},
  "geometry": {"coordinates":[143.59641999999999,-38.348167],"type":"Point"}
}