{
  "type": "Feature",
  "properties": {
    "iso:country":"AU",
    "sg:address":"9 Pinecone Crt",
    "sg:city":"Bunya",
    "sg:classifiers":[
        {
            "category":"Professional",
            "subcategory":"Engineering",
            "type":"Services"
        }
    ],
    "sg:phone":"+61 7 3351 3714",
    "sg:postcode":"4055",
    "sg:province":"QLD",
    "sg:tags":[
        "consulting",
        "engineer"
    ],
    "wof:name":"Joreath Consulting Engineering Services",
    "wof:placetype":"venue"
},
  "geometry": {"coordinates":[152.92262268100001,-27.3799514771],"type":"Point"}
}