{
  "type": "Feature",
  "properties": {
    "addr:full":"13 Dudley St Melbourne VIC 3000",
    "addr:housenumber":"13",
    "addr:postcode":"3000",
    "addr:street":"Dudley St",
    "iso:country":"AU",
    "sg:address":"13 Dudley St",
    "sg:city":"Melbourne",
    "sg:classifiers":[
        {
            "category":"Professional",
            "subcategory":"Accounting & Tax Preparation",
            "type":"Services"
        }
    ],
    "sg:phone":"+61 3 9326 4688",
    "sg:postcode":"3000",
    "sg:province":"VIC",
    "sg:tags":[
        "accountant",
        "auditor"
    ],
    "wof:name":"Action Accounting & Financial Services",
    "wof:placetype":"venue"
},
  "geometry": {"coordinates":[144.95181274399999,-37.8095664978],"type":"Point"}
}