{
  "type": "Feature",
  "properties": {
    "iso:country":"AU",
    "sg:address":"9 Dorachus Drv",
    "sg:city":"Regents Park",
    "sg:classifiers":[
        {
            "category":"Retail",
            "subcategory":"Repair Shop",
            "type":"Services"
        }
    ],
    "sg:phone":"+61 7 3809 0652",
    "sg:postcode":"4118",
    "sg:province":"QLD",
    "sg:tags":[
        "repairing",
        "piano",
        "tuning"
    ],
    "wof:name":"Brisbane Piano Centre",
    "wof:placetype":"venue"
},
  "geometry": {"coordinates":[153.04188537600001,-27.6686820984],"type":"Point"}
}