{
  "type": "Feature",
  "properties": {
    "addr:full":"221 Johnston St Abbotsford VIC 3067",
    "addr:housenumber":"221",
    "addr:postcode":"3067",
    "addr:street":"Johnston St",
    "iso:country":"AU",
    "sg:address":"221 Johnston St",
    "sg:city":"Abbotsford",
    "sg:classifiers":[
        {
            "category":"Building & Trades",
            "subcategory":"Construction",
            "type":"Services"
        }
    ],
    "sg:phone":"+61 3 9419 3838",
    "sg:postcode":"3067",
    "sg:province":"VIC",
    "sg:tags":[
        "contractor"
    ],
    "wof:name":"Matherson Construction Pty Ltd",
    "wof:placetype":"venue"
},
  "geometry": {"coordinates":[144.99339294399999,-37.7999992371],"type":"Point"}
}