{
  "type": "Feature",
  "properties": {
    "addr:full":"11 Murphy St Invermay TAS 7248",
    "addr:housenumber":"11",
    "addr:postcode":"7248",
    "addr:street":"Murphy St",
    "iso:country":"AU",
    "sg:address":"11 Murphy St",
    "sg:city":"Invermay",
    "sg:classifiers":[
        {
            "category":"Autos & Motor Vehicles",
            "subcategory":"Automobile Sales",
            "type":"Retail Goods"
        }
    ],
    "sg:phone":"+61 3 6334 4588",
    "sg:postcode":"7248",
    "sg:province":"TAS",
    "sg:tags":[
        "car",
        "used"
    ],
    "wof:name":"Murphy Street Motors",
    "wof:placetype":"venue"
},
  "geometry": {"coordinates":[147.12550354000001,-41.4259109497],"type":"Point"}
}