{
  "type": "Feature",
  "properties": {
    "iso:country":"AU",
    "sg:address":"269 Bondi Rd",
    "sg:city":"Bondi",
    "sg:classifiers":[
        {
            "category":"Food & Beverages",
            "subcategory":"Supermarket",
            "type":"Retail Goods"
        }
    ],
    "sg:phone":"+61 2 9130 5421",
    "sg:postcode":"2026",
    "sg:province":"NSW",
    "sg:tags":[
        "grocery",
        "store"
    ],
    "wof:name":"Khan's Supermarket",
    "wof:placetype":"venue"
},
  "geometry": {"coordinates":[151.268066406,-33.8946876526],"type":"Point"}
}