{
  "type": "Feature",
  "properties": {
    "addr:full":"Cnr Cathedral & Farbes Sts Woolloomooloo NSW 2011",
    "addr:postcode":"2011",
    "iso:country":"AU",
    "sg:address":"Cnr Cathedral & Farbes Sts",
    "sg:city":"Woolloomooloo",
    "sg:classifiers":[
        {
            "category":"Health Services",
            "subcategory":"Doctor",
            "type":"Services"
        }
    ],
    "sg:phone":"+61 2 9357 2694",
    "sg:postcode":"2011",
    "sg:province":"NSW",
    "sg:tags":[
        "medical",
        "practitioner"
    ],
    "wof:name":"Huang Don N H",
    "wof:placetype":"venue"
},
  "geometry": {"coordinates":[151.21905517600001,-33.8727340698],"type":"Point"}
}