{
  "type": "Feature",
  "properties": {
    "iso:country":"AU",
    "sg:address":"374 Hargreaves St",
    "sg:city":"Bendigo",
    "sg:classifiers":[
        {
            "category":"Shopping",
            "subcategory":"Computers & Home Electronics",
            "type":"Retail Goods"
        }
    ],
    "sg:phone":"+61 3 5442 6411",
    "sg:postcode":"3539",
    "sg:province":"VIC",
    "sg:tags":[
        "small",
        "equipment",
        "business"
    ],
    "wof:name":"Bendigo Web Central",
    "wof:placetype":"venue"
},
  "geometry": {"coordinates":[144.27858000000001,-36.761066],"type":"Point"}
}