{
  "type": "Feature",
  "properties": {
    "iso:country":"AU",
    "sg:address":"77 Hudson Rd",
    "sg:city":"Albion",
    "sg:classifiers":[
        {
            "category":"Retail",
            "subcategory":"Auto Repair",
            "type":"Services"
        }
    ],
    "sg:phone":"+61 7 3262 4160",
    "sg:postcode":"4010",
    "sg:province":"QLD",
    "sg:tags":[
        "repairer",
        "motor",
        "engineer"
    ],
    "wof:name":"Kratzmann Motors Pty Ltd",
    "wof:placetype":"venue"
},
  "geometry": {"coordinates":[153.04153442399999,-27.4287338257],"type":"Point"}
}