{
  "type": "Feature",
  "properties": {
    "iso:country":"AU",
    "sg:address":"34/ 1 Ricketts Rd",
    "sg:city":"Mt Waverley",
    "sg:classifiers":[
        {
            "category":"Professional",
            "subcategory":"Accounting & Tax Preparation",
            "type":"Services"
        }
    ],
    "sg:phone":"+61 3 9548 7422",
    "sg:postcode":"3149",
    "sg:province":"VIC",
    "sg:tags":[
        "consultant",
        "taxation"
    ],
    "wof:name":"Peter Delis & Co",
    "wof:placetype":"venue"
},
  "geometry": {"coordinates":[145.13706970199999,-37.89478302],"type":"Point"}
}