{
  "type": "Feature",
  "properties": {
    "addr:full":"Manningtree Rd Hawthorn VIC 3122",
    "addr:postcode":"3122",
    "addr:street":"Manningtree Rd",
    "iso:country":"AU",
    "sg:address":"Manningtree Rd",
    "sg:city":"Hawthorn",
    "sg:classifiers":[
        {
            "category":"Education",
            "subcategory":"School",
            "type":"Public Place"
        }
    ],
    "sg:phone":"+61 3 9818 4338",
    "sg:postcode":"3122",
    "sg:province":"VIC",
    "sg:tags":[
        "state",
        "except",
        "nsw"
    ],
    "wof:name":"Glenferrie Primary School",
    "wof:placetype":"venue"
},
  "geometry": {"coordinates":[145.031494141,-37.823600769],"type":"Point"}
}