{
  "type": "Feature",
  "properties": {
    "iso:country":"AU",
    "sg:address":"2/ 77 Myall St",
    "sg:city":"Dubbo",
    "sg:classifiers":[
        {
            "category":"Health Services",
            "subcategory":"Doctor",
            "type":"Services"
        }
    ],
    "sg:phone":"+61 2 6884 1049",
    "sg:postcode":"2830",
    "sg:province":"NSW",
    "sg:tags":[
        "occupational",
        "safety"
    ],
    "wof:name":"Occupational Services Pty Ltd",
    "wof:placetype":"venue"
},
  "geometry": {"coordinates":[148.612457275,-32.2398109436],"type":"Point"}
}