{
  "type": "Feature",
  "properties": {
    "iso:country":"AU",
    "sg:address":"271 Charman Rd",
    "sg:city":"Cheltenham",
    "sg:classifiers":[
        {
            "category":"Food & Beverages",
            "subcategory":"Liquor & Beverages",
            "type":"Retail Goods"
        }
    ],
    "sg:phone":"+61 3 9583 6953",
    "sg:postcode":"3192",
    "sg:province":"VIC",
    "sg:tags":[
        "store"
    ],
    "wof:name":"BWS Liquor Stores",
    "wof:placetype":"venue"
},
  "geometry": {"coordinates":[145.05532836899999,-37.9665412903],"type":"Point"}
}