{
  "type": "Feature",
  "properties": {
    "addr:full":"28 Meredith St Queanbeyan ACT 2620",
    "addr:housenumber":"28",
    "addr:postcode":"2620",
    "addr:street":"Meredith St",
    "iso:country":"AU",
    "sg:address":"28 Meredith St",
    "sg:city":"Queanbeyan",
    "sg:classifiers":[
        {
            "category":"Banks & Credit Unions",
            "subcategory":"Bank",
            "type":"Services"
        }
    ],
    "sg:phone":"+61 2 6299 3166",
    "sg:postcode":"2620",
    "sg:province":"ACT",
    "sg:tags":[
        "broker",
        "mortgage"
    ],
    "wof:name":"Avibe Finance Pty Ltd",
    "wof:placetype":"venue"
},
  "geometry": {"coordinates":[149.226470947,-35.3517417908],"type":"Point"}
}