{
  "type": "Feature",
  "properties": {
    "iso:country":"AU",
    "sg:address":"Zolfair Centre Shop 8 14 Sunnyholt Rd",
    "sg:city":"Blacktown",
    "sg:classifiers":[
        {
            "category":"Fast Food",
            "type":"Food & Drink"
        }
    ],
    "sg:phone":"+61 2 9831 1878",
    "sg:postcode":"2148",
    "sg:province":"NSW",
    "sg:tags":[
        "away",
        "take"
    ],
    "wof:name":"Chinese Kitchen Take Away",
    "wof:placetype":"venue"
},
  "geometry": {"coordinates":[150.91197204599999,-33.7698440552],"type":"Point"}
}