{
  "type": "Feature",
  "properties": {
    "iso:country":"AU",
    "sg:address":"50 Silvester St",
    "sg:city":"Cobden",
    "sg:classifiers":[
        {
            "category":"Professional",
            "subcategory":"Art Services",
            "type":"Services"
        }
    ],
    "sg:phone":"+61 3 5595 2123",
    "sg:postcode":"3266",
    "sg:province":"VIC",
    "sg:tags":[
        "picture",
        "frame",
        "framing"
    ],
    "wof:name":"Kim O&#039;Connor Picture Framer",
    "wof:placetype":"venue"
},
  "geometry": {"coordinates":[143.07362365700001,-38.3268013],"type":"Point"}
}