{
  "type": "Feature",
  "properties": {
    "addr:full":"329 Taylor St Toowoomba QLD 4350",
    "addr:housenumber":"329",
    "addr:postcode":"4350",
    "addr:street":"Taylor St",
    "iso:country":"AU",
    "sg:address":"329 Taylor St",
    "sg:city":"Toowoomba",
    "sg:classifiers":[
        {
            "category":"Wholesale",
            "subcategory":"Machinery & Supplies",
            "type":"Manufacturing & Wholesale Goods"
        }
    ],
    "sg:phone":"+61 7 4634 1566",
    "sg:postcode":"4350",
    "sg:province":"QLD",
    "sg:tags":[
        "equipment",
        "hydraulic"
    ],
    "wof:name":"Pirtek Fluid Systems",
    "wof:placetype":"venue"
},
  "geometry": {"coordinates":[151.91166699999999,-27.551142],"type":"Point"}
}