{
  "type": "Feature",
  "properties": {
    "iso:country":"AU",
    "sg:address":"10 Eva St",
    "sg:city":"Maddington",
    "sg:classifiers":[
        {
            "category":"Retail",
            "subcategory":"Auto Repair",
            "type":"Services"
        }
    ],
    "sg:phone":"+61 8 9459 9110",
    "sg:postcode":"6109",
    "sg:province":"WA",
    "sg:tags":[
        "bus",
        "truck"
    ],
    "wof:name":"DGR Diesel Services",
    "wof:placetype":"venue"
},
  "geometry": {"coordinates":[115.998802185,-32.0365219116],"type":"Point"}
}