{
  "type": "Feature",
  "properties": {
    "iso:country":"AU",
    "sg:address":"44 Granite St",
    "sg:city":"Geebung",
    "sg:classifiers":[
        {
            "category":"Professional",
            "subcategory":"Employment Agencies",
            "type":"Services"
        }
    ],
    "sg:phone":"+61 7 3633 0922",
    "sg:postcode":"4034",
    "sg:province":"QLD",
    "sg:tags":[
        "broker",
        "custom"
    ],
    "wof:name":"International Customs & Logistics",
    "wof:placetype":"venue"
},
  "geometry": {"coordinates":[153.04963699999999,-27.364447],"type":"Point"}
}