{
  "type": "Feature",
  "properties": {
    "addr:full":"Main Rd Mt Compass SA 5210",
    "addr:postcode":"5210",
    "addr:street":"Main Rd",
    "iso:country":"AU",
    "sg:address":"Main Rd",
    "sg:city":"Mt Compass",
    "sg:classifiers":[
        {
            "category":"Food & Beverages",
            "subcategory":"Fruits & Vegetables",
            "type":"Retail Goods"
        }
    ],
    "sg:phone":"+61 8 8556 8428",
    "sg:postcode":"5210",
    "sg:province":"SA",
    "sg:tags":[
        "wholesale"
    ],
    "wof:name":"Agon Berry Farm",
    "wof:placetype":"venue"
},
  "geometry": {"coordinates":[138.62506103499999,-35.355140686],"type":"Point"}
}