{
  "type": "Feature",
  "properties": {
    "addr:full":"93-95 Murrindal Drv Rowville VIC 3178",
    "addr:housenumber":"93-95",
    "addr:postcode":"3178",
    "addr:street":"Murrindal Drv",
    "iso:country":"AU",
    "sg:address":"93-95 Murrindal Drv",
    "sg:city":"Rowville",
    "sg:classifiers":[
        {
            "category":"Social Services",
            "subcategory":"Child Care",
            "type":"Services"
        }
    ],
    "sg:phone":"+61 3 9759 6777",
    "sg:postcode":"3178",
    "sg:province":"VIC",
    "wof:name":"ABC Developmental Learning Centres Pty Ltd",
    "wof:placetype":"venue"
},
  "geometry": {"coordinates":[145.272216797,-37.9108352661],"type":"Point"}
}