{
  "type": "Feature",
  "properties": {
    "iso:country":"AU",
    "sg:address":"Shop 5/ 16 Trouts Rd",
    "sg:city":"Everton Park",
    "sg:classifiers":[
        {
            "category":"Personal",
            "subcategory":"Beauty Salon",
            "type":"Services"
        }
    ],
    "sg:phone":"+61 7 3855 5355",
    "sg:postcode":"4053",
    "sg:province":"QLD",
    "wof:name":"Bliss Therapy",
    "wof:placetype":"venue"
},
  "geometry": {"coordinates":[152.99818420400001,-27.4063854218],"type":"Point"}
}