{
  "type": "Feature",
  "properties": {
    "addr:full":"Lvl 10/ 179 Queen St Melbourne VIC 3000",
    "addr:housenumber":"/ 179",
    "addr:postcode":"3000",
    "addr:street":"Queen St",
    "iso:country":"AU",
    "sg:address":"Lvl 10/ 179 Queen St",
    "sg:city":"Melbourne",
    "sg:classifiers":[
        {
            "category":"Professional",
            "subcategory":"Computer Services",
            "type":"Services"
        }
    ],
    "sg:phone":"+61 3 8601 6100",
    "sg:postcode":"3000",
    "sg:province":"VIC",
    "sg:tags":[
        "consultant",
        "system"
    ],
    "wof:name":"Fulcrum Consulting Group Pty Ltd The",
    "wof:placetype":"venue"
},
  "geometry": {"coordinates":[144.96026611299999,-37.8143386841],"type":"Point"}
}