{
  "type": "Feature",
  "properties": {
    "iso:country":"AU",
    "sg:address":"16a Kent St",
    "sg:city":"Tamworth",
    "sg:classifiers":[
        {
            "category":"Travel",
            "subcategory":"Hotels & Motels",
            "type":"Entertainment"
        }
    ],
    "sg:phone":"+61 2 6765 7999",
    "sg:postcode":"2340",
    "sg:province":"NSW",
    "wof:name":"Southgate Inn Hotel/Motel",
    "wof:placetype":"venue"
},
  "geometry": {"coordinates":[150.91934204099999,-31.1034107208],"type":"Point"}
}