{
  "type": "Feature",
  "properties": {
    "iso:country":"AU",
    "sg:address":"695 Anzac Pde",
    "sg:city":"Maroubra Junction",
    "sg:classifiers":[
        {
            "category":"Health Services",
            "subcategory":"Doctor",
            "type":"Services"
        }
    ],
    "sg:phone":"+61 2 9344 9606",
    "sg:postcode":"2035",
    "sg:province":"NSW",
    "sg:tags":[
        "medical",
        "practitioner"
    ],
    "wof:name":"Moloney Shane",
    "wof:placetype":"venue"
},
  "geometry": {"coordinates":[151.23846435600001,-33.9394416809],"type":"Point"}
}