{
  "type": "Feature",
  "properties": {
    "addr:full":"Shop 90 Waverley Gardens Shopping Centre Mulgrave VIC 3170",
    "addr:housenumber":"shop 90",
    "addr:postcode":"3170",
    "addr:street":"Waverley Gardens",
    "iso:country":"AU",
    "sg:address":"Shop 90 Waverley Gardens Shopping Centre",
    "sg:city":"Mulgrave",
    "sg:classifiers":[
        {
            "category":"Shopping",
            "subcategory":"Clothing, Apparel, & Fashions",
            "type":"Retail Goods"
        }
    ],
    "sg:phone":"+61 3 9547 4609",
    "sg:postcode":"3170",
    "sg:province":"VIC",
    "sg:tags":[
        "lady",
        "wear"
    ],
    "wof:name":"Katies Fashions (Aust) Pty Ltd",
    "wof:placetype":"venue"
},
  "geometry": {"coordinates":[145.124099731,-37.8844299316],"type":"Point"}
}