{
  "type": "Feature",
  "properties": {
    "addr:full":"Coffs Promenade 321 Harbour Drv Coffs Harbour NSW 2450",
    "addr:housenumber":"321",
    "addr:postcode":"2450",
    "addr:street":"Coffs Promenade;Harbour Drv",
    "iso:country":"AU",
    "sg:address":"Coffs Promenade 321 Harbour Drv",
    "sg:city":"Coffs Harbour",
    "sg:classifiers":[
        {
            "category":"Personal",
            "subcategory":"Massage",
            "type":"Services"
        }
    ],
    "sg:phone":"+61 2 6658 0950",
    "sg:postcode":"2450",
    "sg:province":"NSW",
    "sg:tags":[
        "therapy"
    ],
    "wof:name":"Beauty On The Promenade",
    "wof:placetype":"venue"
},
  "geometry": {"coordinates":[153.130371,-30.30526],"type":"Point"}
}