{
  "type": "Feature",
  "properties": {
    "addr:full":"5a Mianga Ave Engadine NSW 2233",
    "addr:housenumber":"5a",
    "addr:postcode":"2233",
    "addr:street":"Mianga Ave",
    "iso:country":"AU",
    "sg:address":"5a Mianga Ave",
    "sg:city":"Engadine",
    "sg:classifiers":[
        {
            "category":"Retail",
            "subcategory":"Auto Repair",
            "type":"Services"
        }
    ],
    "sg:phone":"+61 2 9520 6666",
    "sg:postcode":"2233",
    "sg:province":"NSW",
    "sg:tags":[
        "automotive",
        "air conditioning"
    ],
    "sg:website":"http://www.superiorradiators.com.au",
    "wof:name":"Engadine Radiator Service P/L",
    "wof:placetype":"venue"
},
  "geometry": {"coordinates":[151.01544189399999,-34.0662345886],"type":"Point"}
}