{
  "type": "Feature",
  "properties": {
    "addr:full":"5 Sampson St Maddington WA 6109",
    "addr:housenumber":"5",
    "addr:postcode":"6109",
    "addr:street":"Sampson St",
    "iso:country":"AU",
    "sg:address":"5 Sampson St",
    "sg:city":"Maddington",
    "sg:classifiers":[
        {
            "category":"Autos & Motor Vehicles",
            "subcategory":"Automobile Sales",
            "type":"Retail Goods"
        }
    ],
    "sg:phone":"+61 8 9452 7711",
    "sg:postcode":"6109",
    "sg:province":"WA",
    "sg:tags":[
        "car",
        "used"
    ],
    "wof:name":"Auto Link",
    "wof:placetype":"venue"
},
  "geometry": {"coordinates":[115.981056213,-32.0492706299],"type":"Point"}
}