{
  "type": "Feature",
  "properties": {
    "addr:full":"11 Sylvan Ave Medowie NSW 2318",
    "addr:housenumber":"11",
    "addr:postcode":"2318",
    "addr:street":"Sylvan Ave",
    "iso:country":"AU",
    "sg:address":"11 Sylvan Ave",
    "sg:city":"Medowie",
    "sg:classifiers":[
        {
            "category":"Personal",
            "subcategory":"Beauty Salon",
            "type":"Services"
        }
    ],
    "sg:phone":"+61 2 4982 8591",
    "sg:postcode":"2318",
    "sg:province":"NSW",
    "sg:tags":[
        "hairdresser"
    ],
    "wof:name":"Sylvan Hair Boutique",
    "wof:placetype":"venue"
},
  "geometry": {"coordinates":[151.86663799999999,-32.761559],"type":"Point"}
}