{
  "type": "Feature",
  "properties": {
    "addr:full":"23 Cheviot St North Lakes QLD 4509",
    "addr:housenumber":"23",
    "addr:postcode":"4509",
    "addr:street":"Cheviot St",
    "iso:country":"AU",
    "sg:address":"23 Cheviot St",
    "sg:city":"North Lakes",
    "sg:classifiers":[
        {
            "category":"Professional",
            "subcategory":"Art Services",
            "type":"Services"
        }
    ],
    "sg:phone":"+61 400 056 079",
    "sg:postcode":"4509",
    "sg:province":"QLD",
    "sg:tags":[
        "decorator",
        "painter"
    ],
    "wof:name":"Tyson W Lette Painter & Decorator",
    "wof:placetype":"venue"
},
  "geometry": {"coordinates":[153.02067565900001,-27.2265625],"type":"Point"}
}