{
  "type": "Feature",
  "properties": {
    "addr:full":"159 Westgarth St Fitzroy VIC 3065",
    "addr:housenumber":"159",
    "addr:postcode":"3065",
    "addr:street":"Westgarth St",
    "iso:country":"AU",
    "sg:address":"159 Westgarth St",
    "sg:city":"Fitzroy",
    "sg:classifiers":[
        {
            "category":"Professional",
            "subcategory":"Printing & Photocopies",
            "type":"Services"
        }
    ],
    "sg:phone":"+61 3 9417 3535",
    "sg:postcode":"3065",
    "sg:province":"VIC",
    "sg:tags":[
        "embroidery"
    ],
    "wof:name":"Bravura Embroidery",
    "wof:placetype":"venue"
},
  "geometry": {"coordinates":[144.98468017600001,-37.7951545715],"type":"Point"}
}