{
  "type": "Feature",
  "properties": {
    "addr:full":"30 Were St Montmorency VIC 3094",
    "addr:housenumber":"30",
    "addr:postcode":"3094",
    "addr:street":"Were St",
    "iso:country":"AU",
    "sg:address":"30 Were St",
    "sg:city":"Montmorency",
    "sg:classifiers":[
        {
            "category":"Cafe",
            "type":"Food & Drink"
        }
    ],
    "sg:phone":"+61 3 9435 1542",
    "sg:postcode":"3094",
    "sg:province":"VIC",
    "wof:name":"Were Street Food Store The",
    "wof:placetype":"venue"
},
  "geometry": {"coordinates":[145.12130737300001,-37.7166748047],"type":"Point"}
}