{
  "type": "Feature",
  "properties": {
    "iso:country":"AU",
    "sg:address":"2 Wilson Ave",
    "sg:city":"Elanora Heights",
    "sg:classifiers":[
        {
            "category":"Retail",
            "subcategory":"Storage",
            "type":"Services"
        }
    ],
    "sg:phone":"+61 1300 854 285",
    "sg:postcode":"2101",
    "sg:province":"NSW",
    "wof:name":"Cheapa Self Storage Pty Ltd",
    "wof:placetype":"venue"
},
  "geometry": {"coordinates":[151.27179000000001,-33.69006],"type":"Point"}
}