{
  "type": "Feature",
  "properties": {
    "iso:country":"AU",
    "sg:address":"15 Strickland Rd",
    "sg:city":"Bendigo East",
    "sg:classifiers":[
        {
            "category":"Shopping",
            "subcategory":"Crafts & Fabrics",
            "type":"Retail Goods"
        }
    ],
    "sg:phone":"+61 3 5444 0341",
    "sg:postcode":"3550",
    "sg:province":"VIC",
    "sg:tags":[
        "supply"
    ],
    "wof:name":"Earth Goods",
    "wof:placetype":"venue"
},
  "geometry": {"coordinates":[144.29681396500001,-36.7506256104],"type":"Point"}
}