{
  "type": "Feature",
  "properties": {
    "addr:full":"6/ 559 Box Rd Jannali NSW 2226",
    "addr:housenumber":"/ 559",
    "addr:postcode":"2226",
    "addr:street":"Box Rd",
    "iso:country":"AU",
    "sg:address":"6/ 559 Box Rd",
    "sg:city":"Jannali",
    "sg:classifiers":[
        {
            "category":"Health Services",
            "subcategory":"Doctor",
            "type":"Services"
        }
    ],
    "sg:phone":"+61 2 4294 8415",
    "sg:postcode":"2226",
    "sg:province":"NSW",
    "sg:tags":[
        "podiatrist"
    ],
    "wof:name":"Jannali Podiatry",
    "wof:placetype":"venue"
},
  "geometry": {"coordinates":[151.065505981,-34.0160675049],"type":"Point"}
}