{
  "type": "Feature",
  "properties": {
    "addr:full":"18 Corbett Pl Barden Ridge NSW 2234",
    "addr:housenumber":"18",
    "addr:postcode":"2234",
    "addr:street":"Pl",
    "iso:country":"AU",
    "sg:address":"18 Corbett Pl",
    "sg:city":"Barden Ridge",
    "sg:classifiers":[
        {
            "category":"Building & Trades",
            "subcategory":"Construction",
            "type":"Services"
        }
    ],
    "sg:phone":"+61 2 9543 8452",
    "sg:postcode":"2234",
    "sg:province":"NSW",
    "sg:tags":[
        "joiner",
        "carpenter"
    ],
    "wof:name":"Michaels Carpentry & Joinery",
    "wof:placetype":"venue"
},
  "geometry": {"coordinates":[151.00796508799999,-34.0374641418],"type":"Point"}
}