{
  "type": "Feature",
  "properties": {
    "addr:full":"10 Ferguson St Abbotsford VIC 3067",
    "addr:housenumber":"10",
    "addr:postcode":"3067",
    "addr:street":"Ferguson St",
    "iso:country":"AU",
    "sg:address":"10 Ferguson St",
    "sg:city":"Abbotsford",
    "sg:classifiers":[
        {
            "category":"Shopping",
            "subcategory":"Clothing, Apparel, & Fashions",
            "type":"Retail Goods"
        }
    ],
    "sg:phone":"+61 3 9419 0066",
    "sg:postcode":"3067",
    "sg:province":"VIC",
    "sg:tags":[
        "menswear"
    ],
    "wof:name":"Travisty",
    "wof:placetype":"venue"
},
  "geometry": {"coordinates":[144.992675781,-37.8087234497],"type":"Point"}
}