{
  "type": "Feature",
  "properties": {
    "addr:full":"26 Wellington Rd East Brisbane QLD 4169",
    "addr:housenumber":"26",
    "addr:postcode":"4169",
    "addr:street":"Wellington Rd",
    "iso:country":"AU",
    "sg:address":"26 Wellington Rd",
    "sg:city":"East Brisbane",
    "sg:classifiers":[
        {
            "category":"Retail",
            "subcategory":"Auto Rental",
            "type":"Services"
        }
    ],
    "sg:phone":"+61 7 3391 0831",
    "sg:postcode":"4169",
    "sg:province":"QLD",
    "sg:tags":[
        "car",
        "hire",
        "minibus"
    ],
    "wof:name":"Marque 1",
    "wof:placetype":"venue"
},
  "geometry": {"coordinates":[153.039337158,-27.488822937],"type":"Point"}
}