{
  "type": "Feature",
  "properties": {
    "iso:country":"AU",
    "sg:address":"4 Hewer St",
    "sg:city":"Hampstead Gardens",
    "sg:classifiers":[
        {
            "category":"Manufacturing",
            "subcategory":"Motor Vehicles & Parts",
            "type":"Manufacturing & Wholesale Goods"
        }
    ],
    "sg:phone":"+61 8 8261 5844",
    "sg:postcode":"5086",
    "sg:province":"SA",
    "sg:tags":[
        "replacement"
    ],
    "wof:name":"Klemzig Auto Wreckers",
    "wof:placetype":"venue"
},
  "geometry": {"coordinates":[138.63461303700001,-34.8723640442],"type":"Point"}
}