{
  "type": "Feature",
  "properties": {
    "addr:full":"Turton St Sunnybank QLD 4109",
    "addr:postcode":"4109",
    "addr:street":"Turton St",
    "iso:country":"AU",
    "sg:address":"Turton St",
    "sg:city":"Sunnybank",
    "sg:classifiers":[
        {
            "category":"Personal",
            "subcategory":"Beauty Salon",
            "type":"Services"
        }
    ],
    "sg:phone":"+61 7 3345 2923",
    "sg:postcode":"4109",
    "sg:province":"QLD",
    "sg:tags":[
        "hairdresser"
    ],
    "wof:name":"Nastarzi Hair Dressing Australia",
    "wof:placetype":"venue"
},
  "geometry": {"coordinates":[153.062408447,-27.5755138397],"type":"Point"}
}