{
  "type": "Feature",
  "properties": {
    "iso:country":"AU",
    "sg:address":"111 Gouger St",
    "sg:city":"Adelaide",
    "sg:classifiers":[
        {
            "category":"Communications",
            "subcategory":"Film & Video Production",
            "type":"Services"
        }
    ],
    "sg:phone":"+61 8 8231 6869",
    "sg:postcode":"5000",
    "sg:province":"SA",
    "sg:tags":[
        "buyer",
        "refiner",
        "gold"
    ],
    "wof:name":"Con's Pawnbroker & Secondhand Dealer",
    "wof:placetype":"venue"
},
  "geometry": {"coordinates":[138.59538269000001,-34.9304924011],"type":"Point"}
}