{
  "type": "Feature",
  "properties": {
    "iso:country":"AU",
    "sg:address":"Kinghorne St",
    "sg:city":"Nowra",
    "sg:classifiers":[
        {
            "category":"Deli",
            "type":"Food & Drink"
        }
    ],
    "sg:phone":"+61 2 4423 1344",
    "sg:postcode":"2540",
    "sg:province":"NSW",
    "sg:tags":[
        "delicatessen"
    ],
    "wof:name":"River Deli",
    "wof:placetype":"venue"
},
  "geometry": {"coordinates":[150.60260009800001,-34.8946990967],"type":"Point"}
}