{
  "type": "Feature",
  "properties": {
    "addr:full":"209 Fullarton Rd Eastwood SA 5063",
    "addr:housenumber":"209",
    "addr:postcode":"5063",
    "addr:street":"Fullarton Rd",
    "iso:country":"AU",
    "sg:address":"209 Fullarton Rd",
    "sg:city":"Eastwood",
    "sg:classifiers":[
        {
            "category":"Ice Cream",
            "type":"Food & Drink"
        }
    ],
    "sg:phone":"+61 8 8291 5555",
    "sg:postcode":"5063",
    "sg:province":"SA",
    "sg:tags":[
        "retail"
    ],
    "wof:name":"Wendys",
    "wof:placetype":"venue"
},
  "geometry": {"coordinates":[138.624557495,-34.9426803589],"type":"Point"}
}