{
  "type": "Feature",
  "properties": {
    "addr:full":"25 Hamilton St Gisborne VIC 3437",
    "addr:housenumber":"25",
    "addr:postcode":"3437",
    "addr:street":"Hamilton St",
    "iso:country":"AU",
    "sg:address":"25 Hamilton St",
    "sg:city":"Gisborne",
    "sg:classifiers":[
        {
            "category":"Fast Food",
            "type":"Food & Drink"
        }
    ],
    "sg:phone":"+61 3 5428 4812",
    "sg:postcode":"3437",
    "sg:province":"VIC",
    "sg:tags":[
        "away",
        "take"
    ],
    "wof:name":"The Hot Spot",
    "wof:placetype":"venue"
},
  "geometry": {"coordinates":[144.59019470199999,-37.4879379272],"type":"Point"}
}