{
  "type": "Feature",
  "properties": {
    "iso:country":"AU",
    "sg:address":"257 Grey St",
    "sg:city":"Glen Innes",
    "sg:classifiers":[
        {
            "category":"Food & Beverages",
            "subcategory":"Supermarket",
            "type":"Retail Goods"
        }
    ],
    "sg:phone":"+61 2 6732 2067",
    "sg:postcode":"2370",
    "sg:province":"NSW",
    "sg:tags":[
        "grocery",
        "store"
    ],
    "wof:name":"Bi-Lo Pty Ltd",
    "wof:placetype":"venue"
},
  "geometry": {"coordinates":[151.73614501899999,-29.7360115051],"type":"Point"}
}