{
  "type": "Feature",
  "properties": {
    "addr:full":"PO Box 1260 Joondalup DC WA 6919",
    "addr:postcode":"6919",
    "iso:country":"AU",
    "sg:address":"PO Box 1260",
    "sg:city":"Joondalup DC",
    "sg:classifiers":[
        {
            "category":"Building & Trades",
            "subcategory":"Pest Control",
            "type":"Services"
        }
    ],
    "sg:phone":"+61 409 473 787",
    "sg:postcode":"6919",
    "sg:province":"WA",
    "wof:name":"Aarest That Pest",
    "wof:placetype":"venue"
},
  "geometry": {"coordinates":[115.769889831,-31.7465190887],"type":"Point"}
}