{
  "type": "Feature",
  "properties": {
    "iso:country":"AU",
    "sg:address":"5 Cadesby Crt",
    "sg:city":"Boronia",
    "sg:classifiers":[
        {
            "category":"Professional",
            "subcategory":"Art Services",
            "type":"Services"
        }
    ],
    "sg:phone":"+61 3 9720 9607",
    "sg:postcode":"3155",
    "sg:province":"VIC",
    "sg:tags":[
        "decorator",
        "painter"
    ],
    "wof:name":"Cida Painting Restoring",
    "wof:placetype":"venue"
},
  "geometry": {"coordinates":[145.27122497600001,-37.8564796448],"type":"Point"}
}