{
  "type": "Feature",
  "properties": {
    "iso:country":"AU",
    "sg:address":"Higgins Shopng Cntr Higgins Pl",
    "sg:city":"Higgins",
    "sg:classifiers":[
        {
            "category":"Personal",
            "subcategory":"Beauty Salon",
            "type":"Services"
        }
    ],
    "sg:phone":"+61 2 6254 2418",
    "sg:postcode":"2615",
    "sg:province":"ACT",
    "sg:tags":[
        "hairdresser"
    ],
    "wof:name":"Higgins Hair Design",
    "wof:placetype":"venue"
},
  "geometry": {"coordinates":[149.02708435100001,-35.2317085266],"type":"Point"}
}