{
  "type": "Feature",
  "properties": {
    "addr:full":"2 Leadenham Pl Chipping Norton NSW 2170",
    "addr:housenumber":"2",
    "addr:postcode":"2170",
    "addr:street":"Leadenham Pl",
    "iso:country":"AU",
    "sg:address":"2 Leadenham Pl",
    "sg:city":"Chipping Norton",
    "sg:classifiers":[
        {
            "category":"Professional",
            "subcategory":"Engineering",
            "type":"Services"
        }
    ],
    "sg:phone":"+61 2 9755 1852",
    "sg:postcode":"2170",
    "sg:province":"NSW",
    "sg:tags":[
        "electrical",
        "engineer"
    ],
    "wof:name":"D.J.V. Electrical ( & Services )",
    "wof:placetype":"venue"
},
  "geometry": {"coordinates":[150.95957946799999,-33.914894104],"type":"Point"}
}