{
  "type": "Feature",
  "properties": {
    "iso:country":"AU",
    "sg:address":"768 Canning Hwy",
    "sg:city":"Applecross",
    "sg:classifiers":[
        {
            "category":"Autos & Motor Vehicles",
            "subcategory":"Boat Sales",
            "type":"Retail Goods"
        }
    ],
    "sg:phone":"+61 8 9315 3511",
    "sg:postcode":"6153",
    "sg:province":"WA",
    "sg:tags":[
        "yacht"
    ],
    "wof:name":"Mobilarm Ltd",
    "wof:placetype":"venue"
},
  "geometry": {"coordinates":[115.84446699999999,-32.014683],"type":"Point"}
}