{
  "type": "Feature",
  "properties": {
    "iso:country":"AU",
    "sg:address":"2 Kealman Rd",
    "sg:city":"Queanbeyan",
    "sg:classifiers":[
        {
            "category":"Building & Trades",
            "subcategory":"Construction",
            "type":"Services"
        }
    ],
    "sg:phone":"+61 2 6299 2806",
    "sg:postcode":"2620",
    "sg:province":"NSW",
    "sg:tags":[
        "industrial",
        "commercial",
        "air conditioning"
    ],
    "wof:name":"Electaire Pty Ltd",
    "wof:placetype":"venue"
},
  "geometry": {"coordinates":[149.207855225,-35.3518714905],"type":"Point"}
}