{
  "type": "Feature",
  "properties": {
    "addr:full":"PO Box 531 Moranbah QLD 4744",
    "addr:postcode":"4744",
    "iso:country":"AU",
    "sg:address":"PO Box 531",
    "sg:city":"Moranbah",
    "sg:classifiers":[
        {
            "category":"Building & Trades",
            "subcategory":"Construction",
            "type":"Services"
        }
    ],
    "sg:phone":"+61 403 368 127",
    "sg:postcode":"4744",
    "sg:province":"QLD",
    "sg:tags":[
        "welding"
    ],
    "wof:name":"Corsetti Industries Pty Ltd",
    "wof:placetype":"venue"
},
  "geometry": {"coordinates":[148.09439086899999,-22.1004600525],"type":"Point"}
}