{
  "type": "Feature",
  "properties": {
    "iso:country":"AU",
    "sg:address":"591 Boundary Rd",
    "sg:city":"Darra",
    "sg:classifiers":[
        {
            "category":"Manufacturing",
            "subcategory":"Tools & Machinery",
            "type":"Manufacturing & Wholesale Goods"
        }
    ],
    "sg:phone":"+61 1800 331 660",
    "sg:postcode":"4076",
    "sg:province":"QLD",
    "sg:tags":[
        "earth",
        "excavating",
        "moving",
        "equipment"
    ],
    "sg:website":"http://www.terex.com",
    "wof:name":"Terex",
    "wof:placetype":"venue"
},
  "geometry": {"coordinates":[152.95817565900001,-27.5770988464],"type":"Point"}
}