{
  "type": "Feature",
  "properties": {
    "addr:full":"Unit 5/ 18 Rene St Noosaville QLD 4566",
    "addr:housenumber":"18",
    "addr:postcode":"4566",
    "addr:street":"Rene St",
    "iso:country":"AU",
    "sg:address":"Unit 5/ 18 Rene St",
    "sg:city":"Noosaville",
    "sg:classifiers":[
        {
            "category":"Manufacturing",
            "subcategory":"Furniture",
            "type":"Manufacturing & Wholesale Goods"
        }
    ],
    "sg:phone":"+61 7 5449 9664",
    "sg:postcode":"4566",
    "sg:province":"QLD",
    "sg:tags":[
        "builder",
        "designer",
        "custom"
    ],
    "wof:name":"Master Jack Cabinetry & Maintenance",
    "wof:placetype":"venue"
},
  "geometry": {"coordinates":[153.04246520999999,-26.4140205383],"type":"Point"}
}