{
  "type": "Feature",
  "properties": {
    "addr:full":"2206 Pacific Hwy Heatherbrae NSW 2324",
    "addr:housenumber":"2206",
    "addr:postcode":"2324",
    "addr:street":"Pacific Hwy",
    "iso:country":"AU",
    "sg:address":"2206 Pacific Hwy",
    "sg:city":"Heatherbrae",
    "sg:classifiers":[
        {
            "category":"School Buses",
            "type":"Transportation"
        }
    ],
    "sg:phone":"+61 2 4987 4400",
    "sg:postcode":"2324",
    "sg:province":"NSW",
    "sg:tags":[
        "brick"
    ],
    "wof:name":"Timbercrete - Bricks / Blocks",
    "wof:placetype":"venue"
},
  "geometry": {"coordinates":[151.71737670900001,-32.7988777161],"type":"Point"}
}