{
  "type": "Feature",
  "properties": {
    "addr:full":"18 Powderham Rd Caulfield North VIC 3161",
    "addr:housenumber":"18",
    "addr:postcode":"3161",
    "addr:street":"Powderham Rd",
    "iso:country":"AU",
    "sg:address":"18 Powderham Rd",
    "sg:city":"Caulfield North",
    "sg:classifiers":[
        {
            "category":"Health Services",
            "subcategory":"Medical Lab",
            "type":"Services"
        }
    ],
    "sg:phone":"+61 3 9532 8976",
    "sg:postcode":"3161",
    "sg:province":"VIC",
    "sg:tags":[
        "laboratory",
        "dental"
    ],
    "wof:name":"Prestige Dental",
    "wof:placetype":"venue"
},
  "geometry": {"coordinates":[145.022094727,-37.8748588562],"type":"Point"}
}