{
  "type": "Feature",
  "properties": {
    "iso:country":"AU",
    "sg:address":"9 Booreea St",
    "sg:city":"Blacktown",
    "sg:classifiers":[
        {
            "category":"Professional",
            "subcategory":"Computer Services",
            "type":"Services"
        }
    ],
    "sg:phone":"+61 2 8807 4359",
    "sg:postcode":"2148",
    "sg:province":"NSW",
    "sg:tags":[
        "repairs",
        "upgrade",
        "equipment"
    ],
    "wof:name":"Mobile Computer Administration",
    "wof:placetype":"venue"
},
  "geometry": {"coordinates":[150.90391540499999,-33.7738494873],"type":"Point"}
}