{
  "type": "Feature",
  "properties": {
    "addr:full":"8 Orchid Ave Hervey Bay QLD 4655",
    "addr:housenumber":"8",
    "addr:postcode":"4655",
    "addr:street":"Orchid Ave",
    "iso:country":"AU",
    "sg:address":"8 Orchid Ave",
    "sg:city":"Hervey Bay",
    "sg:classifiers":[
        {
            "category":"Organizations",
            "subcategory":"Professional Association",
            "type":"Services"
        }
    ],
    "sg:phone":"+61 7 4125 6020",
    "sg:postcode":"4655",
    "sg:province":"QLD",
    "sg:tags":[
        "web",
        "internet"
    ],
    "wof:name":"Webline",
    "wof:placetype":"venue"
},
  "geometry": {"coordinates":[152.882248,-25.295269],"type":"Point"}
}