{
  "type": "Feature",
  "properties": {
    "addr:full":"Level 1 11-15 Dowe St Tamworth NSW 2340",
    "addr:housenumber":"11-15",
    "addr:postcode":"2340",
    "addr:street":"Dowe St",
    "iso:country":"AU",
    "sg:address":"Level 1 11-15 Dowe St",
    "sg:city":"Tamworth",
    "sg:classifiers":[
        {
            "category":"Banks & Credit Unions",
            "subcategory":"Bank",
            "type":"Services"
        }
    ],
    "sg:phone":"+61 2 6766 6180",
    "sg:postcode":"2340",
    "sg:province":"NSW",
    "sg:tags":[
        "broker",
        "mortgage"
    ],
    "wof:name":"Tamcity Finance",
    "wof:placetype":"venue"
},
  "geometry": {"coordinates":[150.93199157699999,-31.089630127],"type":"Point"}
}