{
  "type": "Feature",
  "properties": {
    "addr:full":"66 Katoomba St Katoomba NSW 2780",
    "addr:housenumber":"66",
    "addr:postcode":"2780",
    "addr:street":"Katoomba St",
    "iso:country":"AU",
    "sg:address":"66 Katoomba St",
    "sg:city":"Katoomba",
    "sg:classifiers":[
        {
            "category":"Real Estate",
            "subcategory":"Real Estate Agent",
            "type":"Services"
        }
    ],
    "sg:phone":"+61 2 4782 2822",
    "sg:postcode":"2780",
    "sg:province":"NSW",
    "wof:name":"Raine & Horne Katoomba",
    "wof:placetype":"venue"
},
  "geometry": {"coordinates":[150.311813355,-33.7136650085],"type":"Point"}
}