{
  "type": "Feature",
  "properties": {
    "addr:full":"Freemantle Drv Stirling ACT 2611",
    "addr:postcode":"2611",
    "addr:street":"Freemantle Drv",
    "iso:country":"AU",
    "sg:address":"Freemantle Drv",
    "sg:city":"Stirling",
    "sg:classifiers":[
        {
            "category":"Arena",
            "subcategory":"Sports Club",
            "type":"Entertainment"
        }
    ],
    "sg:phone":"+61 2 6288 5047",
    "sg:postcode":"2611",
    "sg:province":"ACT",
    "sg:tags":[
        "australian",
        "football",
        "rule"
    ],
    "wof:name":"Weston Creek Football Club & Sport Centre Inc",
    "wof:placetype":"venue"
},
  "geometry": {"coordinates":[149.04951477,-35.3489837646],"type":"Point"}
}