{
  "type": "Feature",
  "properties": {
    "iso:country":"AU",
    "sg:address":"106 Williams St",
    "sg:city":"Earlwood",
    "sg:classifiers":[
        {
            "category":"Building & Trades",
            "subcategory":"Construction",
            "type":"Services"
        }
    ],
    "sg:phone":"+61 2 9787 7879",
    "sg:postcode":"2206",
    "sg:province":"NSW",
    "sg:tags":[
        "rendering",
        "cement"
    ],
    "wof:name":"Maximum Plastering Services Pty Ltd",
    "wof:placetype":"venue"
},
  "geometry": {"coordinates":[151.116409,-33.926659],"type":"Point"}
}