{
  "type": "Feature",
  "properties": {
    "addr:full":"1-5 Sussex St East Victoria Park WA 6101",
    "addr:housenumber":"1-5",
    "addr:postcode":"6101",
    "addr:street":"Sussex St",
    "iso:country":"AU",
    "sg:address":"1-5 Sussex St",
    "sg:city":"East Victoria Park",
    "sg:classifiers":[
        {
            "category":"Social Services",
            "subcategory":"Child Care",
            "type":"Services"
        }
    ],
    "sg:phone":"+61 8 9470 1149",
    "sg:postcode":"6101",
    "sg:province":"WA",
    "wof:name":"Billabong Community Child Care Centre",
    "wof:placetype":"venue"
},
  "geometry": {"coordinates":[115.90019989,-31.9842586517],"type":"Point"}
}