{
  "type": "Feature",
  "properties": {
    "addr:full":"10 Martin Rd Morphett Vale SA 5162",
    "addr:housenumber":"10",
    "addr:postcode":"5162",
    "addr:street":"Martin Rd",
    "iso:country":"AU",
    "sg:address":"10 Martin Rd",
    "sg:city":"Morphett Vale",
    "sg:classifiers":[
        {
            "category":"Building & Trades",
            "subcategory":"Landscaping Services",
            "type":"Services"
        }
    ],
    "sg:phone":"+61 414 803 100",
    "sg:postcode":"5162",
    "sg:province":"SA",
    "sg:tags":[
        "gardener"
    ],
    "wof:name":"Den's Gardening",
    "wof:placetype":"venue"
},
  "geometry": {"coordinates":[138.514968872,-35.1205940247],"type":"Point"}
}