{
  "type": "Feature",
  "properties": {
    "addr:full":"59 Waratah Ave Belgrave VIC 3160",
    "addr:housenumber":"59",
    "addr:postcode":"3160",
    "addr:street":"Waratah Ave",
    "iso:country":"AU",
    "sg:address":"59 Waratah Ave",
    "sg:city":"Belgrave",
    "sg:classifiers":[
        {
            "category":"Professional",
            "subcategory":"Computer Services",
            "type":"Services"
        }
    ],
    "sg:phone":"+61 3 9754 7970",
    "sg:postcode":"3160",
    "sg:province":"VIC",
    "sg:tags":[
        "consultant",
        "system"
    ],
    "wof:name":"BPOS Systems Pty Ltd",
    "wof:placetype":"venue"
},
  "geometry": {"coordinates":[145.35856628400001,-37.9175872803],"type":"Point"}
}