{
  "type": "Feature",
  "properties": {
    "addr:full":"Unit 1, 1 Stirling Rd Blackwood SA 5051",
    "addr:housenumber":"1",
    "addr:postcode":"5051",
    "addr:street":"Stirling Rd",
    "iso:country":"AU",
    "sg:address":"Unit 1, 1 Stirling Rd",
    "sg:city":"Blackwood",
    "sg:classifiers":[
        {
            "category":"Retail",
            "subcategory":"Auto Repair",
            "type":"Services"
        }
    ],
    "sg:phone":"+61 8 8370 0288",
    "sg:postcode":"5051",
    "sg:province":"SA",
    "sg:tags":[
        "automotive",
        "air conditioning"
    ],
    "wof:name":"Elite Auto Electronics",
    "wof:placetype":"venue"
},
  "geometry": {"coordinates":[138.62037699999999,-35.014198],"type":"Point"}
}