{
  "type": "Feature",
  "properties": {
    "iso:country":"AU",
    "sg:address":"Endeavour Valley Rd",
    "sg:city":"Cooktown",
    "sg:classifiers":[
        {
            "category":"Retail",
            "subcategory":"Auto Repair",
            "type":"Services"
        }
    ],
    "sg:phone":"+61 7 4069 6090",
    "sg:postcode":"4895",
    "sg:province":"QLD",
    "sg:tags":[
        "repairer",
        "motor",
        "engineer"
    ],
    "wof:name":"Marton Mechanical Services",
    "wof:placetype":"venue"
},
  "geometry": {"coordinates":[145.237915039,-15.4790372849],"type":"Point"}
}