{
  "type": "Feature",
  "properties": {
    "addr:full":"127 Mount Rankin Rd Bathurst NSW 2795",
    "addr:housenumber":"127",
    "addr:postcode":"2795",
    "addr:street":"Mount Rankin Rd",
    "iso:country":"AU",
    "sg:address":"127 Mount Rankin Rd",
    "sg:city":"Bathurst",
    "sg:classifiers":[
        {
            "category":"Building & Trades",
            "subcategory":"Landscaping Services",
            "type":"Services"
        }
    ],
    "sg:phone":"+61 2 6337 1545",
    "sg:postcode":"2795",
    "sg:province":"NSW",
    "sg:tags":[
        "stump",
        "tree",
        "felling",
        "removal"
    ],
    "wof:name":"Accurate Tree Service",
    "wof:placetype":"venue"
},
  "geometry": {"coordinates":[149.51643371599999,-33.3535003662],"type":"Point"}
}