{
  "type": "Feature",
  "properties": {
    "iso:country":"AU",
    "sg:address":"Chapman Rd",
    "sg:city":"Geraldton",
    "sg:classifiers":[
        {
            "category":"Professional",
            "type":"Services"
        }
    ],
    "sg:phone":"+61 8 9938 3815",
    "sg:postcode":"6530",
    "sg:province":"WA",
    "sg:tags":[
        "transport"
    ],
    "wof:name":"Whitehurst Transport",
    "wof:placetype":"venue"
},
  "geometry": {"coordinates":[114.62223815900001,-28.7424926758],"type":"Point"}
}