{
  "type": "Feature",
  "properties": {
    "addr:full":"24 Queensborough Pde Karalee QLD 4306",
    "addr:housenumber":"24",
    "addr:postcode":"4306",
    "addr:street":"Queensborough Pde",
    "iso:country":"AU",
    "sg:address":"24 Queensborough Pde",
    "sg:city":"Karalee",
    "sg:classifiers":[
        {
            "category":"Professional",
            "subcategory":"Accounting & Tax Preparation",
            "type":"Services"
        }
    ],
    "sg:phone":"+61 7 3294 7045",
    "sg:postcode":"4306",
    "sg:province":"QLD",
    "sg:tags":[
        "bookkeeping"
    ],
    "wof:name":"BBK Bookkeeping",
    "wof:placetype":"venue"
},
  "geometry": {"coordinates":[152.81028747600001,-27.5766563416],"type":"Point"}
}