{
  "type": "Feature",
  "properties": {
    "addr:full":"7 Sarah Crescent Ferny Grove QLD 4055",
    "addr:housenumber":"7",
    "addr:postcode":"4055",
    "addr:street":"Sarah Crescent",
    "iso:country":"AU",
    "sg:address":"7 Sarah Crescent",
    "sg:city":"Ferny Grove",
    "sg:classifiers":[
        {
            "category":"Building & Trades",
            "subcategory":"Construction",
            "type":"Services"
        }
    ],
    "sg:phone":"+61 410 558 685",
    "sg:postcode":"4055",
    "sg:province":"QLD",
    "sg:tags":[
        "earth",
        "excavating",
        "moving",
        "contractor"
    ],
    "wof:name":"Good As Dunn Earthmoving",
    "wof:placetype":"venue"
},
  "geometry": {"coordinates":[152.936737061,-27.4015197754],"type":"Point"}
}