{
  "type": "Feature",
  "properties": {
    "iso:country":"AU",
    "sg:address":"Cnr Gordon & Peel Sts",
    "sg:city":"Mackay",
    "sg:classifiers":[
        {
            "category":"Banks & Credit Unions",
            "subcategory":"Financial Services",
            "type":"Services"
        }
    ],
    "sg:phone":"+61 7 4951 5200",
    "sg:postcode":"4740",
    "sg:province":"QLD",
    "sg:tags":[
        "finance",
        "motor",
        "vehicle"
    ],
    "wof:name":"Capitalcorp Financial Services",
    "wof:placetype":"venue"
},
  "geometry": {"coordinates":[149.17887899999999,-21.145544],"type":"Point"}
}