{
  "type": "Feature",
  "properties": {
    "addr:full":"32 Spencer St Bunbury WA 6230",
    "addr:housenumber":"32",
    "addr:postcode":"6230",
    "addr:street":"Spencer St",
    "iso:country":"AU",
    "sg:address":"32 Spencer St",
    "sg:city":"Bunbury",
    "sg:classifiers":[
        {
            "category":"Autos & Motor Vehicles",
            "subcategory":"Automobile Sales",
            "type":"Retail Goods"
        }
    ],
    "sg:phone":"+61 8 9721 8999",
    "sg:postcode":"6230",
    "sg:province":"WA",
    "sg:tags":[
        "car",
        "used"
    ],
    "wof:name":"Bunbury Hyundai",
    "wof:placetype":"venue"
},
  "geometry": {"coordinates":[115.641541,-33.346947],"type":"Point"}
}