{
  "type": "Feature",
  "properties": {
    "iso:country":"AU",
    "sg:address":"24 Windermere Ave",
    "sg:city":"Northmead",
    "sg:classifiers":[
        {
            "category":"Building & Trades",
            "subcategory":"Plumbing",
            "type":"Services"
        }
    ],
    "sg:phone":"+61 2 9639 1700",
    "sg:postcode":"2152",
    "sg:province":"NSW",
    "sg:tags":[
        "plumber",
        "gasfitters"
    ],
    "wof:name":"Aquaheat Installations",
    "wof:placetype":"venue"
},
  "geometry": {"coordinates":[151.00239563,-33.778213501],"type":"Point"}
}