{
  "type": "Feature",
  "properties": {
    "addr:full":"PO Box 469 Kellyville NSW 2153",
    "addr:postcode":"2153",
    "iso:country":"AU",
    "sg:address":"PO Box 469",
    "sg:city":"Kellyville",
    "sg:classifiers":[
        {
            "category":"Building & Trades",
            "subcategory":"Construction",
            "type":"Services"
        }
    ],
    "sg:phone":"+61 2 9629 3970",
    "sg:postcode":"2153",
    "sg:province":"NSW",
    "sg:tags":[
        "earth",
        "excavating",
        "moving",
        "contractor"
    ],
    "wof:name":"Raygal Pty Ltd",
    "wof:placetype":"venue"
},
  "geometry": {"coordinates":[150.97642517099999,-33.7541503906],"type":"Point"}
}