{
  "type": "Feature",
  "properties": {
    "addr:full":"10 Barrack St Sydney NSW 2000",
    "addr:housenumber":"10",
    "addr:postcode":"2000",
    "addr:street":"Barrack St",
    "iso:country":"AU",
    "sg:address":"10 Barrack St",
    "sg:city":"Sydney",
    "sg:classifiers":[
        {
            "category":"Banks & Credit Unions",
            "subcategory":"Financial Services",
            "type":"Services"
        }
    ],
    "sg:phone":"+61 2 8272 2999",
    "sg:postcode":"2000",
    "sg:province":"NSW",
    "sg:tags":[
        "planning"
    ],
    "wof:name":"Partnership Planning Ltd",
    "wof:placetype":"venue"
},
  "geometry": {"coordinates":[151.20614624000001,-33.8675498962],"type":"Point"}
}