{
  "type": "Feature",
  "properties": {
    "iso:country":"AU",
    "sg:address":"PO Box 496",
    "sg:city":"Wonthaggi",
    "sg:classifiers":[
        {
            "category":"Professional",
            "subcategory":"Art Services",
            "type":"Services"
        }
    ],
    "sg:phone":"+61 415 856 063",
    "sg:postcode":"3995",
    "sg:province":"VIC",
    "sg:tags":[
        "graphic",
        "designer"
    ],
    "wof:name":"Quirky Graphics",
    "wof:placetype":"venue"
},
  "geometry": {"coordinates":[145.594467,-38.605721],"type":"Point"}
}