{
  "type": "Feature",
  "properties": {
    "iso:country":"AU",
    "sg:address":"PO Box 386",
    "sg:city":"Hahndorf",
    "sg:classifiers":[
        {
            "category":"Manufacturing",
            "subcategory":"Buildings",
            "type":"Manufacturing & Wholesale Goods"
        }
    ],
    "sg:phone":"+61 8 8388 1828",
    "sg:postcode":"5245",
    "sg:province":"SA",
    "sg:tags":[
        "house",
        "gazebo",
        "shade"
    ],
    "wof:name":"Shade-SA-&#039;Shade-Scape&#039;",
    "wof:placetype":"venue"
},
  "geometry": {"coordinates":[138.809890747,-35.0293006897],"type":"Point"}
}