{
  "type": "Feature",
  "properties": {
    "addr:full":"27 Bingara Crs Bella Vista NSW 2153",
    "addr:housenumber":"27",
    "addr:postcode":"2153",
    "addr:street":"Bingara Crs",
    "iso:country":"AU",
    "sg:address":"27 Bingara Crs",
    "sg:city":"Bella Vista",
    "sg:classifiers":[
        {
            "category":"Autos & Motor Vehicles",
            "subcategory":"Automobile Sales",
            "type":"Retail Goods"
        }
    ],
    "sg:phone":"+61 1800 333 008",
    "sg:postcode":"2153",
    "sg:province":"NSW",
    "sg:tags":[
        "car",
        "new"
    ],
    "wof:name":"Auswide Motor Search Pty Ltd",
    "wof:placetype":"venue"
},
  "geometry": {"coordinates":[150.95550537099999,-33.7379684448],"type":"Point"}
}