{
  "type": "Feature",
  "properties": {
    "iso:country":"AU",
    "sg:address":"61 O'Donnell St",
    "sg:city":"North Bondi",
    "sg:classifiers":[
        {
            "category":"Real Estate",
            "subcategory":"Architect",
            "type":"Services"
        }
    ],
    "sg:phone":"+61 2 9300 0847",
    "sg:postcode":"2026",
    "sg:province":"NSW",
    "wof:name":"Yvonne P. Haber Architect",
    "wof:placetype":"venue"
},
  "geometry": {"coordinates":[151.281692505,-33.8846549988],"type":"Point"}
}