{
  "type": "Feature",
  "properties": {
    "iso:country":"AU",
    "sg:address":"127 Sheridan St",
    "sg:city":"Cairns",
    "sg:classifiers":[
        {
            "category":"Banks & Credit Unions",
            "subcategory":"Financial Services",
            "type":"Services"
        }
    ],
    "sg:phone":"+61 7 4031 8288",
    "sg:postcode":"4870",
    "sg:province":"QLD",
    "sg:tags":[
        "loan",
        "finance",
        "mortgage"
    ],
    "wof:name":"Choice Home Loans",
    "wof:placetype":"venue"
},
  "geometry": {"coordinates":[145.76948547399999,-16.919008255],"type":"Point"}
}