{
  "type": "Feature",
  "properties": {
    "addr:full":"9 Channon St Gympie QLD 4570",
    "addr:housenumber":"9",
    "addr:postcode":"4570",
    "addr:street":"Channon St",
    "iso:country":"AU",
    "sg:address":"9 Channon St",
    "sg:city":"Gympie",
    "sg:classifiers":[
        {
            "category":"Retail",
            "subcategory":"Veterinary Services",
            "type":"Services"
        }
    ],
    "sg:phone":"+61 7 5482 4226",
    "sg:postcode":"4570",
    "sg:province":"QLD",
    "sg:tags":[
        "surgeon"
    ],
    "wof:name":"Freney L M",
    "wof:placetype":"venue"
},
  "geometry": {"coordinates":[152.65692138700001,-26.1899776459],"type":"Point"}
}