{
  "type": "Feature",
  "properties": {
    "addr:full":"38 Denman Pde Normanhurst NSW 2076",
    "addr:housenumber":"38",
    "addr:postcode":"2076",
    "addr:street":"Denman Pde",
    "iso:country":"AU",
    "sg:address":"38 Denman Pde",
    "sg:city":"Normanhurst",
    "sg:classifiers":[
        {
            "category":"Manufacturing",
            "subcategory":"Food",
            "type":"Manufacturing & Wholesale Goods"
        }
    ],
    "sg:phone":"+61 2 9489 7133",
    "sg:postcode":"2076",
    "sg:province":"NSW",
    "sg:tags":[
        "function",
        "catering"
    ],
    "wof:name":"Upper Crust Catering",
    "wof:placetype":"venue"
},
  "geometry": {"coordinates":[151.096557617,-33.7215690613],"type":"Point"}
}