{
  "type": "Feature",
  "properties": {
    "addr:full":"30 Alfred St Southern Cross Terminal Chipping Norton NSW 2170",
    "addr:housenumber":"30",
    "addr:postcode":"2170",
    "addr:street":"Alfred St",
    "iso:country":"AU",
    "sg:address":"30 Alfred St Southern Cross Terminal",
    "sg:city":"Chipping Norton",
    "sg:classifiers":[
        {
            "category":"Professional",
            "type":"Services"
        }
    ],
    "sg:phone":"+61 2 9755 1395",
    "sg:postcode":"2170",
    "sg:province":"NSW",
    "sg:tags":[
        "transport"
    ],
    "wof:name":"Leeton Road Freighters Pty Ltd",
    "wof:placetype":"venue"
},
  "geometry": {"coordinates":[150.964767456,-33.9232330322],"type":"Point"}
}