{
  "type": "Feature",
  "properties": {
    "iso:country":"AU",
    "sg:address":"274 Barkly St",
    "sg:city":"Brunswick",
    "sg:classifiers":[
        {
            "category":"Manufacturing",
            "subcategory":"Leather Goods",
            "type":"Manufacturing & Wholesale Goods"
        }
    ],
    "sg:phone":"+61 3 9387 2822",
    "sg:postcode":"3056",
    "sg:province":"VIC",
    "sg:tags":[
        "wholesaler",
        "mfrs",
        "clothing"
    ],
    "wof:name":"Palermo John Pty Ltd",
    "wof:placetype":"venue"
},
  "geometry": {"coordinates":[144.961227417,-37.7762832642],"type":"Point"}
}