{
  "type": "Feature",
  "properties": {
    "iso:country":"AU",
    "sg:address":"PO Box 3050",
    "sg:city":"Narellan Delivery Cntr",
    "sg:classifiers":[
        {
            "category":"Building & Trades",
            "subcategory":"Cleaning & Sanitation",
            "type":"Services"
        }
    ],
    "sg:phone":"+61 2 9711 3454",
    "sg:postcode":"2567",
    "sg:province":"NSW",
    "sg:tags":[
        "industrial",
        "commercial",
        "contractor"
    ],
    "wof:name":"Star Cleaning",
    "wof:placetype":"venue"
},
  "geometry": {"coordinates":[150.75428772000001,-34.0431098938],"type":"Point"}
}