{
  "type": "Feature",
  "properties": {
    "iso:country":"AU",
    "sg:address":"Level 4/ 303 Collins St",
    "sg:city":"Melbourne",
    "sg:classifiers":[
        {
            "category":"Organizations",
            "subcategory":"Professional Association",
            "type":"Services"
        }
    ],
    "sg:phone":"+61 3 9620 7077",
    "sg:postcode":"3000",
    "sg:province":"VIC",
    "sg:tags":[
        "web",
        "internet"
    ],
    "wof:name":"MMpowered Communications",
    "wof:placetype":"venue"
},
  "geometry": {"coordinates":[144.963989258,-37.816368103],"type":"Point"}
}