{
  "type": "Feature",
  "properties": {
    "addr:full":"53 Lampton Ave Derwent Park TAS 7009",
    "addr:housenumber":"53",
    "addr:postcode":"7009",
    "addr:street":"Lampton Ave",
    "iso:country":"AU",
    "sg:address":"53 Lampton Ave",
    "sg:city":"Derwent Park",
    "sg:classifiers":[
        {
            "category":"Professional",
            "type":"Services"
        }
    ],
    "sg:phone":"+61 3 6272 8566",
    "sg:postcode":"7009",
    "sg:province":"TAS",
    "sg:tags":[
        "transport"
    ],
    "wof:name":"Star Track Express",
    "wof:placetype":"venue"
},
  "geometry": {"coordinates":[147.29411315900001,-42.8345146179],"type":"Point"}
}