{
  "type": "Feature",
  "properties": {
    "addr:full":"Unit 3/ 236 Campbell Pde Bondi Beach NSW 2026",
    "addr:housenumber":"/ 236",
    "addr:postcode":"2026",
    "addr:street":"Campbell Pde",
    "iso:country":"AU",
    "sg:address":"Unit 3/ 236 Campbell Pde",
    "sg:city":"Bondi Beach",
    "sg:classifiers":[
        {
            "category":"Professional",
            "subcategory":"Secretarial Services",
            "type":"Services"
        }
    ],
    "sg:phone":"+61 2 9130 7088",
    "sg:postcode":"2026",
    "sg:province":"NSW",
    "sg:tags":[
        "typing"
    ],
    "wof:name":"Perdriau On Campbell",
    "wof:placetype":"venue"
},
  "geometry": {"coordinates":[151.27984619099999,-33.8893890381],"type":"Point"}
}