{
  "type": "Feature",
  "properties": {
    "addr:full":"131- 135 Thomas St Dandenong VIC 3175",
    "addr:housenumber":"135",
    "addr:postcode":"3175",
    "addr:street":"Thomas St",
    "iso:country":"AU",
    "sg:address":"131- 135 Thomas St",
    "sg:city":"Dandenong",
    "sg:classifiers":[
        {
            "category":"Ice Cream",
            "type":"Food & Drink"
        }
    ],
    "sg:phone":"+61 3 9792 2229",
    "sg:postcode":"3175",
    "sg:province":"VIC",
    "sg:tags":[
        "specialised",
        "fitting",
        "lady",
        "wear"
    ],
    "wof:name":"Big In Black",
    "wof:placetype":"venue"
},
  "geometry": {"coordinates":[145.212646484,-37.9893074036],"type":"Point"}
}