{
  "type": "Feature",
  "properties": {
    "addr:full":"10 Brendan Drv Nerang QLD 4211",
    "addr:housenumber":"10",
    "addr:postcode":"4211",
    "addr:street":"Brendan Drv",
    "iso:country":"AU",
    "sg:address":"10 Brendan Drv",
    "sg:city":"Nerang",
    "sg:classifiers":[
        {
            "category":"Professional",
            "subcategory":"Detective & Security Services",
            "type":"Services"
        }
    ],
    "sg:phone":"+61 7 5578 3700",
    "sg:postcode":"4211",
    "sg:province":"QLD",
    "sg:tags":[
        "equipment",
        "window",
        "doors"
    ],
    "wof:name":"C.K.A. Windows & Doors",
    "wof:placetype":"venue"
},
  "geometry": {"coordinates":[153.34100341800001,-27.9981746674],"type":"Point"}
}