{
  "type": "Feature",
  "properties": {
    "addr:full":"PO Box 343 Merewether NSW 2291",
    "addr:postcode":"2291",
    "iso:country":"AU",
    "sg:address":"PO Box 343",
    "sg:city":"Merewether",
    "sg:classifiers":[
        {
            "category":"Real Estate",
            "subcategory":"Surveying",
            "type":"Services"
        }
    ],
    "sg:phone":"+61 2 4969 7253",
    "sg:postcode":"2291",
    "sg:province":"NSW",
    "sg:tags":[
        "surveyor",
        "land"
    ],
    "wof:name":"Graeme Ellerton",
    "wof:placetype":"venue"
},
  "geometry": {"coordinates":[151.74896240199999,-32.943359375],"type":"Point"}
}