{
  "type": "Feature",
  "properties": {
    "addr:full":"32 Weyba St Sunshine Beach QLD 4567",
    "addr:housenumber":"32",
    "addr:postcode":"4567",
    "addr:street":"Weyba St",
    "iso:country":"AU",
    "sg:address":"32 Weyba St",
    "sg:city":"Sunshine Beach",
    "sg:classifiers":[
        {
            "category":"Building & Trades",
            "subcategory":"Construction",
            "type":"Services"
        }
    ],
    "sg:phone":"+61 7 5447 5346",
    "sg:postcode":"4567",
    "sg:province":"QLD",
    "sg:tags":[
        "brick",
        "paving"
    ],
    "wof:name":"North Coast Paving",
    "wof:placetype":"venue"
},
  "geometry": {"coordinates":[153.07920837399999,-26.4087352753],"type":"Point"}
}