{
  "type": "Feature",
  "properties": {
    "addr:full":"2401 Warrego Hwy Yamanto QLD 4305",
    "addr:housenumber":"2401",
    "addr:postcode":"4305",
    "addr:street":"Warrego Hwy",
    "iso:country":"AU",
    "sg:address":"2401 Warrego Hwy",
    "sg:city":"Yamanto",
    "sg:classifiers":[
        {
            "category":"Building & Trades",
            "subcategory":"Construction",
            "type":"Services"
        }
    ],
    "sg:phone":"+61 412 564 368",
    "sg:postcode":"4305",
    "sg:province":"QLD",
    "sg:tags":[
        "contractor"
    ],
    "wof:name":"Crosby W H",
    "wof:placetype":"venue"
},
  "geometry": {"coordinates":[152.75328064000001,-27.5807304382],"type":"Point"}
}