{
  "type": "Feature",
  "properties": {
    "addr:full":"11 Hamilton St Bassendean WA 6054",
    "addr:housenumber":"11",
    "addr:postcode":"6054",
    "addr:street":"Hamilton St",
    "iso:country":"AU",
    "sg:address":"11 Hamilton St",
    "sg:city":"Bassendean",
    "sg:classifiers":[
        {
            "category":"Education",
            "subcategory":"School",
            "type":"Public Place"
        }
    ],
    "sg:phone":"+61 8 9279 2209",
    "sg:postcode":"6054",
    "sg:province":"WA",
    "wof:name":"Montessori Schools",
    "wof:placetype":"venue"
},
  "geometry": {"coordinates":[115.95169067400001,-31.903263092],"type":"Point"}
}