{
  "type": "Feature",
  "properties": {
    "iso:country":"AU",
    "sg:address":"Unit 1/ 93- 103 Dalrymple Rd",
    "sg:city":"Garbutt",
    "sg:classifiers":[
        {
            "category":"Communications",
            "subcategory":"Television Station",
            "type":"Services"
        }
    ],
    "sg:phone":"+61 7 4725 8992",
    "sg:postcode":"4814",
    "sg:province":"QLD",
    "sg:tags":[
        "equipment",
        "laser"
    ],
    "wof:name":"ABC Lasers",
    "wof:placetype":"venue"
},
  "geometry": {"coordinates":[146.773224,-19.270519],"type":"Point"}
}