{
  "type": "Feature",
  "properties": {
    "addr:full":"Lvl 3 53 Walker St Sydney NSW 2000",
    "addr:housenumber":"53",
    "addr:postcode":"2000",
    "addr:street":"Walker St",
    "iso:country":"AU",
    "sg:address":"Lvl 3 53 Walker St",
    "sg:city":"Sydney",
    "sg:classifiers":[
        {
            "category":"Real Estate",
            "subcategory":"Surveying",
            "type":"Services"
        }
    ],
    "sg:phone":"+61 2 9956 7322",
    "sg:postcode":"2000",
    "sg:province":"NSW",
    "sg:tags":[
        "surveyor",
        "marine",
        "cargo"
    ],
    "wof:name":"ABS Pacific",
    "wof:placetype":"venue"
},
  "geometry": {"coordinates":[151.207427978,-33.8970756531],"type":"Point"}
}