{
  "type": "Feature",
  "properties": {
    "iso:country":"AU",
    "sg:address":"Lakewood Drv",
    "sg:city":"Burpengary",
    "sg:classifiers":[
        {
            "category":"Professional",
            "type":"Services"
        }
    ],
    "sg:phone":"+61 7 3888 2222",
    "sg:postcode":"4505",
    "sg:province":"QLD",
    "sg:tags":[
        "transport"
    ],
    "wof:name":"Drewerys Transport Pty Ltd",
    "wof:placetype":"venue"
},
  "geometry": {"coordinates":[153.002487183,-27.1609191895],"type":"Point"}
}