{
  "type": "Feature",
  "properties": {
    "iso:country":"AU",
    "sg:address":"189- 191 Balaclava Rd",
    "sg:city":"Caulfield North",
    "sg:classifiers":[
        {
            "category":"Professional",
            "subcategory":"Accounting & Tax Preparation",
            "type":"Services"
        }
    ],
    "sg:phone":"+61 3 9526 0009",
    "sg:postcode":"3161",
    "sg:province":"VIC",
    "sg:tags":[
        "accountant",
        "auditor"
    ],
    "wof:name":"Prudentia Private Clients",
    "wof:placetype":"venue"
},
  "geometry": {"coordinates":[145.022827148,-37.8725395203],"type":"Point"}
}