{
  "type": "Feature",
  "properties": {
    "iso:country":"AU",
    "sg:address":"Shoalhaven Bridge Rd",
    "sg:city":"Nowra",
    "sg:classifiers":[
        {
            "category":"Building & Trades",
            "subcategory":"Landscaping Services",
            "type":"Services"
        }
    ],
    "sg:phone":"+61 2 4429 3453",
    "sg:postcode":"2541",
    "sg:province":"NSW",
    "sg:tags":[
        "stump",
        "tree",
        "felling",
        "removal"
    ],
    "wof:name":"Shoalhaven City & Eurobodalla Shire Councils",
    "wof:placetype":"venue"
},
  "geometry": {"coordinates":[150.60064697300001,-34.8719749451],"type":"Point"}
}