{
  "type": "Feature",
  "properties": {
    "iso:country":"AU",
    "sg:address":"TradePark Drv",
    "sg:city":"Tullamarine",
    "sg:classifiers":[
        {
            "category":"Manufacturing",
            "subcategory":"Aerospace",
            "type":"Manufacturing & Wholesale Goods"
        }
    ],
    "sg:phone":"+61 3 9334 5542",
    "sg:postcode":"3043",
    "sg:province":"VIC",
    "sg:tags":[
        "equipment",
        "aircraft",
        "maintenance"
    ],
    "wof:name":"Honeywell- Aircraft Landing Systems",
    "wof:placetype":"venue"
},
  "geometry": {"coordinates":[144.870330811,-37.6947174072],"type":"Point"}
}