{
  "type": "Feature",
  "properties": {
    "addr:full":"1/ 77 Devonshire Rd Watsonia VIC 3087",
    "addr:housenumber":"/ 77",
    "addr:postcode":"3087",
    "addr:street":"Devonshire Rd",
    "iso:country":"AU",
    "sg:address":"1/ 77 Devonshire Rd",
    "sg:city":"Watsonia",
    "sg:classifiers":[
        {
            "category":"Health Services",
            "subcategory":"Health Practitioner",
            "type":"Services"
        }
    ],
    "sg:phone":"+61 3 9432 5011",
    "sg:postcode":"3087",
    "sg:province":"VIC",
    "sg:tags":[
        "osteopath"
    ],
    "wof:name":"Henderson Matthew",
    "wof:placetype":"venue"
},
  "geometry": {"coordinates":[145.081939697,-37.7124328613],"type":"Point"}
}