{
  "type": "Feature",
  "properties": {
    "addr:full":"478- 484 Penshurst St Roseville NSW 2069",
    "addr:housenumber":"478 484",
    "addr:postcode":"2069",
    "addr:street":"Penshurst St",
    "iso:country":"AU",
    "sg:address":"478- 484 Penshurst St",
    "sg:city":"Roseville",
    "sg:classifiers":[
        {
            "category":"Autos & Motor Vehicles",
            "subcategory":"Boat Sales",
            "type":"Retail Goods"
        }
    ],
    "sg:phone":"+61 13 13 08",
    "sg:postcode":"2069",
    "sg:province":"NSW",
    "sg:tags":[
        "machine",
        "dishwashing"
    ],
    "wof:name":"Kleenmaid",
    "wof:placetype":"venue"
},
  "geometry": {"coordinates":[151.19166564899999,-33.7842102051],"type":"Point"}
}