{
  "type": "Feature",
  "properties": {
    "iso:country":"AU",
    "sg:address":"Level 6, 49 York St",
    "sg:city":"Sydney",
    "sg:classifiers":[
        {
            "category":"Professional",
            "subcategory":"Art Services",
            "type":"Services"
        }
    ],
    "sg:phone":"+61 2 9279 2444",
    "sg:postcode":"2000",
    "sg:province":"NSW",
    "sg:tags":[
        "graphic",
        "designer"
    ],
    "wof:name":"H2O Creative Communications",
    "wof:placetype":"venue"
},
  "geometry": {"coordinates":[151.20570373499999,-33.8668937683],"type":"Point"}
}