{
  "type": "Feature",
  "properties": {
    "addr:full":"52 Mahogany Ave Frankston VIC 3199",
    "addr:housenumber":"52",
    "addr:postcode":"3199",
    "addr:street":"Mahogany Ave",
    "iso:country":"AU",
    "sg:address":"52 Mahogany Ave",
    "sg:city":"Frankston",
    "sg:classifiers":[
        {
            "category":"Manufacturing",
            "subcategory":"Food",
            "type":"Manufacturing & Wholesale Goods"
        }
    ],
    "sg:phone":"+61 1300 557 417",
    "sg:postcode":"3199",
    "sg:province":"VIC",
    "sg:tags":[
        "function",
        "catering"
    ],
    "wof:name":"Irresistible Roasts and Fingerfoods",
    "wof:placetype":"venue"
},
  "geometry": {"coordinates":[145.14808654800001,-38.1235618591],"type":"Point"}
}