{
  "type": "Feature",
  "properties": {
    "iso:country":"AU",
    "sg:address":"130 Swan St",
    "sg:city":"Richmond",
    "sg:classifiers":[
        {
            "category":"Shopping",
            "subcategory":"Clothing, Apparel, & Fashions",
            "type":"Retail Goods"
        }
    ],
    "sg:phone":"+61 3 9425 9399",
    "sg:postcode":"3121",
    "sg:province":"VIC",
    "sg:tags":[
        "wholesaler",
        "children's",
        "mfrs",
        "wear"
    ],
    "wof:name":"Kidsdesign Pty Ltd",
    "wof:placetype":"venue"
},
  "geometry": {"coordinates":[144.99424743599999,-37.8253936768],"type":"Point"}
}