{
  "type": "Feature",
  "properties": {
    "iso:country":"AU",
    "sg:address":"8/ 29 Spenser St St",
    "sg:city":"Kilda",
    "sg:classifiers":[
        {
            "category":"Shopping",
            "subcategory":"Computers & Home Electronics",
            "type":"Retail Goods"
        }
    ],
    "sg:phone":"+61 402 164 544",
    "sg:postcode":"3182",
    "sg:province":"VIC",
    "sg:tags":[
        "equipment",
        "multimedia"
    ],
    "wof:name":"New Media Lab",
    "wof:placetype":"venue"
},
  "geometry": {"coordinates":[144.977493286,-37.8702392578],"type":"Point"}
}