{
  "type": "Feature",
  "properties": {
    "addr:full":"Shop 29A, Shellharbour Square Shopping Centre, Lake Entrance Rd Blackbutt NSW 2529",
    "addr:housenumber":"29a",
    "addr:postcode":"2529",
    "addr:street":"Shellharbour Square Shopping;Lake Entrance Rd",
    "iso:country":"AU",
    "sg:address":"Shop 29A, Shellharbour Square Shopping Centre, Lake Entrance Rd",
    "sg:city":"Blackbutt",
    "sg:classifiers":[
        {
            "category":"Shopping",
            "subcategory":"Mobile Phones",
            "type":"Retail Goods"
        }
    ],
    "sg:phone":"+61 2 4296 4745",
    "sg:postcode":"2529",
    "sg:province":"NSW",
    "sg:tags":[
        "telephone",
        "accessory"
    ],
    "wof:name":"Vodafone",
    "wof:placetype":"venue"
},
  "geometry": {"coordinates":[150.82241821299999,-34.5697593689],"type":"Point"}
}