{
  "type": "Feature",
  "properties": {
    "addr:full":"Unit 8, 15 Childs Rd Chipping Norton NSW 2170",
    "addr:housenumber":"15",
    "addr:postcode":"2170",
    "addr:street":"Childs Rd",
    "iso:country":"AU",
    "sg:address":"Unit 8, 15 Childs Rd",
    "sg:city":"Chipping Norton",
    "sg:classifiers":[
        {
            "category":"Utilities",
            "type":"Services"
        }
    ],
    "sg:phone":"+61 2 9755 2366",
    "sg:postcode":"2170",
    "sg:province":"NSW",
    "sg:tags":[
        "refrigeration",
        "industrial",
        "commercial",
        "retail"
    ],
    "wof:name":"Brightline",
    "wof:placetype":"venue"
},
  "geometry": {"coordinates":[150.96488952600001,-33.9187088013],"type":"Point"}
}