{
  "type": "Feature",
  "properties": {
    "addr:full":"935 South Rd Edwardstown SA 5039",
    "addr:housenumber":"935",
    "addr:postcode":"5039",
    "addr:street":"South Rd",
    "iso:country":"AU",
    "sg:address":"935 South Rd",
    "sg:city":"Edwardstown",
    "sg:classifiers":[
        {
            "category":"Manufacturing",
            "subcategory":"Motor Vehicles & Parts",
            "type":"Manufacturing & Wholesale Goods"
        }
    ],
    "sg:phone":"+61 8 8371 4944",
    "sg:postcode":"5039",
    "sg:province":"SA",
    "sg:tags":[
        "replacement"
    ],
    "wof:name":"Sprint Auto Parts Pty Ltd",
    "wof:placetype":"venue"
},
  "geometry": {"coordinates":[138.57391357399999,-34.9776382446],"type":"Point"}
}