{
  "type": "Feature",
  "properties": {
    "addr:full":"7 Moutrie Pl Castle Hill NSW 2154",
    "addr:housenumber":"7",
    "addr:postcode":"2154",
    "addr:street":"Moutrie Pl",
    "iso:country":"AU",
    "sg:address":"7 Moutrie Pl",
    "sg:city":"Castle Hill",
    "sg:classifiers":[
        {
            "category":"Wholesale",
            "subcategory":"Machinery & Supplies",
            "type":"Manufacturing & Wholesale Goods"
        }
    ],
    "sg:phone":"+61 2 9634 2492",
    "sg:postcode":"2154",
    "sg:province":"NSW",
    "sg:tags":[
        "equipment",
        "welding"
    ],
    "wof:name":"Ulacourt Pty Ltd",
    "wof:placetype":"venue"
},
  "geometry": {"coordinates":[151.011276245,-33.7283859253],"type":"Point"}
}