{
  "type": "Feature",
  "properties": {
    "addr:full":"Unit 29, 274- 276 Hoxton Park Rd Liverpool NSW 2170",
    "addr:housenumber":"274 276",
    "addr:postcode":"2170",
    "addr:street":"Hoxton Park Rd",
    "iso:country":"AU",
    "sg:address":"Unit 29, 274- 276 Hoxton Park Rd",
    "sg:city":"Liverpool",
    "sg:classifiers":[
        {
            "category":"Government",
            "subcategory":"Department Of Motor Vehicles",
            "type":"Public Place"
        }
    ],
    "sg:phone":"+61 2 9608 2871",
    "sg:postcode":"2170",
    "sg:province":"NSW",
    "sg:tags":[
        "wholesaler",
        "mfrs",
        "accessory"
    ],
    "wof:name":"Marity P/L",
    "wof:placetype":"venue"
},
  "geometry": {"coordinates":[150.90496826200001,-33.9273376465],"type":"Point"}
}