{
  "type": "Feature",
  "properties": {
    "iso:country":"AU",
    "sg:address":"5 Neal St",
    "sg:city":"Gisborne",
    "sg:classifiers":[
        {
            "category":"Health Services",
            "subcategory":"Health Practitioner",
            "type":"Services"
        }
    ],
    "sg:phone":"+61 3 5428 0300",
    "sg:postcode":"3437",
    "sg:province":"VIC",
    "sg:tags":[
        "physiotherapist"
    ],
    "wof:name":"Neal St Physiotherapy & Sports Medicine Clinic",
    "wof:placetype":"venue"
},
  "geometry": {"coordinates":[144.584472656,-37.4856185913],"type":"Point"}
}