{
  "type": "Feature",
  "properties": {
    "iso:country":"AU",
    "sg:address":"22 Sussex St",
    "sg:city":"Maylands",
    "sg:classifiers":[
        {
            "category":"Communications",
            "subcategory":"Film & Video Production",
            "type":"Services"
        }
    ],
    "sg:phone":"+61 8 9471 9200",
    "sg:postcode":"6051",
    "sg:province":"WA",
    "sg:tags":[
        "equipment",
        "amplification",
        "music"
    ],
    "wof:name":"Audex Sound",
    "wof:placetype":"venue"
},
  "geometry": {"coordinates":[115.89660600000001,-31.922535],"type":"Point"}
}