{
  "type": "Feature",
  "properties": {
    "addr:full":"Shop 9A Caldarra Ave Engadine NSW 2233",
    "addr:housenumber":"shop 9a",
    "addr:postcode":"2233",
    "addr:street":"Caldarra Ave",
    "iso:country":"AU",
    "sg:address":"Shop 9A Caldarra Ave",
    "sg:city":"Engadine",
    "sg:classifiers":[
        {
            "category":"Ice Cream",
            "type":"Food & Drink"
        }
    ],
    "sg:phone":"+61 2 9548 1705",
    "sg:postcode":"2233",
    "sg:province":"NSW",
    "sg:tags":[
        "cone",
        "wafer"
    ],
    "wof:name":"Engadine Court Icecreamery",
    "wof:placetype":"venue"
},
  "geometry": {"coordinates":[151.01968383799999,-34.0571784973],"type":"Point"}
}