{
  "type": "Feature",
  "properties": {
    "iso:country":"AU",
    "sg:address":"32 Bancroft St",
    "sg:city":"Kelvin Grove",
    "sg:classifiers":[
        {
            "category":"Shopping",
            "subcategory":"Pets & Pet Supplies",
            "type":"Retail Goods"
        }
    ],
    "sg:phone":"+61 433 237 574",
    "sg:postcode":"4059",
    "sg:province":"QLD",
    "sg:tags":[
        "shop",
        "supplier"
    ],
    "wof:name":"My Animal Pty Ltd",
    "wof:placetype":"venue"
},
  "geometry": {"coordinates":[153.00721740700001,-27.4443092346],"type":"Point"}
}