{
  "type": "Feature",
  "properties": {
    "addr:full":"Unit A10 Adamco Business Park, Cnr Westall & Centr Clayton VIC 3168",
    "addr:postcode":"3168",
    "addr:street":"Cnr",
    "iso:country":"AU",
    "sg:address":"Unit A10 Adamco Business Park, Cnr Westall & Centr",
    "sg:city":"Clayton",
    "sg:classifiers":[
        {
            "category":"Autos & Motor Vehicles",
            "subcategory":"Auto Supplies",
            "type":"Retail Goods"
        }
    ],
    "sg:phone":"+61 1300 731 137",
    "sg:postcode":"3168",
    "sg:province":"VIC",
    "sg:tags":[
        "wheel",
        "four",
        "equipment",
        "drive",
        "accessory"
    ],
    "wof:name":"Ironman 4 x 4 Suspension",
    "wof:placetype":"venue"
},
  "geometry": {"coordinates":[145.12937927199999,-37.9023933411],"type":"Point"}
}