{
  "type": "Feature",
  "properties": {
    "iso:country":"AU",
    "sg:address":"139 Keon Pde",
    "sg:city":"Keon Park",
    "sg:classifiers":[
        {
            "category":"Retail",
            "subcategory":"Driving School",
            "type":"Services"
        }
    ],
    "sg:phone":"+61 3 9460 4611",
    "sg:postcode":"3073",
    "sg:province":"VIC",
    "wof:name":"Coolaroo Driving School",
    "wof:placetype":"venue"
},
  "geometry": {"coordinates":[145.01300048799999,-37.6950416565],"type":"Point"}
}