{
  "type": "Feature",
  "properties": {
    "iso:country":"AU",
    "sg:address":"Shop 1/ 18 Mountain View Ave",
    "sg:city":"Miami",
    "sg:classifiers":[
        {
            "category":"Shopping",
            "subcategory":"Bicycles & Sporting Goods",
            "type":"Retail Goods"
        }
    ],
    "sg:phone":"+61 7 5576 1111",
    "sg:postcode":"4220",
    "sg:province":"QLD",
    "sg:tags":[
        "chemical",
        "equipment",
        "pool",
        "swimming"
    ],
    "wof:name":"Discount Pool Chemicals Burleigh Heads",
    "wof:placetype":"venue"
},
  "geometry": {"coordinates":[153.443359375,-28.0756034851],"type":"Point"}
}