{
  "type": "Feature",
  "properties": {
    "addr:full":"19 Karella St Mordialloc VIC 3195",
    "addr:housenumber":"19",
    "addr:postcode":"3195",
    "addr:street":"Karella St",
    "iso:country":"AU",
    "sg:address":"19 Karella St",
    "sg:city":"Mordialloc",
    "sg:classifiers":[
        {
            "category":"Home & Garden",
            "subcategory":"Carpets & Floor Coverings",
            "type":"Retail Goods"
        }
    ],
    "sg:phone":"+61 418 622 516",
    "sg:postcode":"3195",
    "sg:province":"VIC",
    "wof:name":"Living Hardwood Flooring",
    "wof:placetype":"venue"
},
  "geometry": {"coordinates":[145.09753418,-38.007774353],"type":"Point"}
}