{
  "type": "Feature",
  "properties": {
    "iso:country":"AU",
    "sg:address":"47 Pinjarra Rd",
    "sg:city":"Mandurah",
    "sg:classifiers":[
        {
            "category":"Insurance",
            "subcategory":"Insurance Agent",
            "type":"Services"
        }
    ],
    "sg:phone":"+61 8 9581 5858",
    "sg:postcode":"6210",
    "sg:province":"WA",
    "wof:name":"Axion Insurance",
    "wof:placetype":"venue"
},
  "geometry": {"coordinates":[115.772713,-32.546894],"type":"Point"}
}