{
  "type": "Feature",
  "properties": {
    "iso:country":"AU",
    "sg:address":"8th Flr/4- 6 Bligh St",
    "sg:city":"Sydney",
    "sg:classifiers":[
        {
            "category":"Professional",
            "subcategory":"Management & Consulting",
            "type":"Services"
        }
    ],
    "sg:phone":"+61 2 9232 2789",
    "sg:postcode":"2000",
    "sg:province":"NSW",
    "sg:tags":[
        "consultant",
        "energy"
    ],
    "wof:name":"Next Generation Energy Solution (NGeS)",
    "wof:placetype":"venue"
},
  "geometry": {"coordinates":[151.211013794,-33.8650894165],"type":"Point"}
}