{
  "type": "Feature",
  "properties": {
    "iso:country":"AU",
    "sg:address":"10 Ruthven St",
    "sg:city":"Harlaxton",
    "sg:classifiers":[
        {
            "category":"Government",
            "subcategory":"Post Office",
            "type":"Public Place"
        }
    ],
    "sg:phone":"+61 7 4638 1129",
    "sg:postcode":"4350",
    "sg:province":"QLD",
    "sg:tags":[
        "postal"
    ],
    "wof:name":"Australia Post",
    "wof:placetype":"venue"
},
  "geometry": {"coordinates":[151.957245,-27.530094],"type":"Point"}
}