{
  "type": "Feature",
  "properties": {
    "addr:full":"16 Fairdale Crt Eltham VIC 3095",
    "addr:housenumber":"16",
    "addr:postcode":"3095",
    "addr:street":"Fairdale Crt",
    "iso:country":"AU",
    "sg:address":"16 Fairdale Crt",
    "sg:city":"Eltham",
    "sg:classifiers":[
        {
            "category":"Arts & Performance",
            "subcategory":"Theater",
            "type":"Entertainment"
        }
    ],
    "sg:phone":"+61 3 9431 2725",
    "sg:postcode":"3095",
    "sg:province":"VIC",
    "sg:tags":[
        "theatrical",
        "supply"
    ],
    "wof:name":"Destructive Slide Show Co",
    "wof:placetype":"venue"
},
  "geometry": {"coordinates":[145.15852355999999,-37.7118721008],"type":"Point"}
}