{
  "type": "Feature",
  "properties": {
    "addr:full":"Unit 2, 37- 39 Lexton Rd Box Hill VIC 3128",
    "addr:housenumber":"37 39",
    "addr:postcode":"3128",
    "addr:street":"Lexton Rd",
    "iso:country":"AU",
    "sg:address":"Unit 2, 37- 39 Lexton Rd",
    "sg:city":"Box Hill",
    "sg:classifiers":[
        {
            "category":"Wholesale",
            "subcategory":"Machinery & Supplies",
            "type":"Manufacturing & Wholesale Goods"
        }
    ],
    "sg:phone":"+61 3 9899 7390",
    "sg:postcode":"3128",
    "sg:province":"VIC",
    "sg:tags":[
        "belting",
        "mfrs"
    ],
    "wof:name":"Paterson Belting",
    "wof:placetype":"venue"
},
  "geometry": {"coordinates":[145.13583374000001,-37.8119049072],"type":"Point"}
}