{
  "type": "Feature",
  "properties": {
    "iso:country":"AU",
    "sg:address":"166-168 Melville Rd",
    "sg:city":"Brunswick West",
    "sg:classifiers":[
        {
            "category":"Food & Beverages",
            "subcategory":"Supermarket",
            "type":"Retail Goods"
        }
    ],
    "sg:phone":"+61 3 9386 0977",
    "sg:postcode":"3055",
    "sg:province":"VIC",
    "sg:tags":[
        "grocery",
        "store"
    ],
    "wof:name":"Albion Budget Supermarket",
    "wof:placetype":"venue"
},
  "geometry": {"coordinates":[144.945068359,-37.7583732605],"type":"Point"}
}