{
  "type": "Feature",
  "properties": {
    "addr:full":"Pinehill Rd Wolseley SA 5269",
    "addr:postcode":"5269",
    "addr:street":"Pinehill Rd",
    "iso:country":"AU",
    "sg:address":"Pinehill Rd",
    "sg:city":"Wolseley",
    "sg:classifiers":[
        {
            "category":"Farming",
            "subcategory":"Farm",
            "type":"Manufacturing & Wholesale Goods"
        }
    ],
    "sg:phone":"+61 8 8753 2312",
    "sg:postcode":"5269",
    "sg:province":"SA",
    "sg:tags":[
        "farmer"
    ],
    "wof:name":"Tink B A & J A",
    "wof:placetype":"venue"
},
  "geometry": {"coordinates":[140.91220100000001,-36.312874],"type":"Point"}
}