{
  "type": "Feature",
  "properties": {
    "addr:full":"81 Colebard St West Acacia Ridge QLD 4110",
    "addr:housenumber":"81",
    "addr:postcode":"4110",
    "addr:street":"Colebard St West",
    "iso:country":"AU",
    "sg:address":"81 Colebard St West",
    "sg:city":"Acacia Ridge",
    "sg:classifiers":[
        {
            "category":"Shopping",
            "type":"Retail Goods"
        }
    ],
    "sg:phone":"+61 7 3277 9855",
    "sg:postcode":"4110",
    "sg:province":"QLD",
    "sg:tags":[
        "equipment",
        "safety",
        "accessory"
    ],
    "wof:name":"Spanset Australia Ltd",
    "wof:placetype":"venue"
},
  "geometry": {"coordinates":[153.00318908700001,-27.5792503357],"type":"Point"}
}