{
  "type": "Feature",
  "properties": {
    "addr:full":"79 Queen St Ayr QLD 4807",
    "addr:housenumber":"79",
    "addr:postcode":"4807",
    "addr:street":"Queen St",
    "iso:country":"AU",
    "sg:address":"79 Queen St",
    "sg:city":"Ayr",
    "sg:classifiers":[
        {
            "category":"Shopping",
            "subcategory":"Music",
            "type":"Retail Goods"
        }
    ],
    "sg:phone":"+61 7 4783 1304",
    "sg:postcode":"4807",
    "sg:province":"QLD",
    "sg:tags":[
        "instrument",
        "musical"
    ],
    "wof:name":"Delta Music (Leading Edge)",
    "wof:placetype":"venue"
},
  "geometry": {"coordinates":[147.40731811500001,-19.5734462738],"type":"Point"}
}