{
  "type": "Feature",
  "properties": {
    "iso:country":"AU",
    "sg:address":"33 Unley Rd",
    "sg:city":"Parkside",
    "sg:classifiers":[
        {
            "category":"Health Services",
            "subcategory":"Optometrist",
            "type":"Services"
        }
    ],
    "sg:phone":"+61 8 8373 2210",
    "sg:postcode":"5063",
    "sg:province":"SA",
    "wof:name":"Griffiths Andrew",
    "wof:placetype":"venue"
},
  "geometry": {"coordinates":[138.60716247600001,-34.943572998],"type":"Point"}
}