{
  "type": "Feature",
  "properties": {
    "addr:full":"Aroona St Coomba Park NSW 2428",
    "addr:postcode":"2428",
    "addr:street":"Aroona St",
    "iso:country":"AU",
    "sg:address":"Aroona St",
    "sg:city":"Coomba Park",
    "sg:classifiers":[
        {
            "category":"Shopping",
            "subcategory":"Computers & Home Electronics",
            "type":"Retail Goods"
        }
    ],
    "sg:phone":"+61 2 6554 2062",
    "sg:postcode":"2428",
    "sg:province":"NSW",
    "sg:tags":[
        "equipment",
        "supply"
    ],
    "wof:name":"Independent Quickfill",
    "wof:placetype":"venue"
},
  "geometry": {"coordinates":[152.45477299999999,-32.239315],"type":"Point"}
}