{
  "type": "Feature",
  "properties": {
    "iso:country":"AU",
    "sg:address":"48 John St",
    "sg:city":"Salisbury",
    "sg:classifiers":[
        {
            "category":"Shopping",
            "subcategory":"Clothing, Apparel, & Fashions",
            "type":"Retail Goods"
        }
    ],
    "sg:phone":"+61 8 8258 2050",
    "sg:postcode":"5108",
    "sg:province":"SA",
    "sg:tags":[
        "menswear"
    ],
    "wof:name":"Mensland",
    "wof:placetype":"venue"
},
  "geometry": {"coordinates":[138.64479064899999,-34.7624015808],"type":"Point"}
}