{
  "type": "Feature",
  "properties": {
    "addr:full":"80 Amalfi Drv Hillarys WA 6025",
    "addr:housenumber":"80",
    "addr:postcode":"6025",
    "addr:street":"Amalfi Drv",
    "iso:country":"AU",
    "sg:address":"80 Amalfi Drv",
    "sg:city":"Hillarys",
    "sg:classifiers":[
        {
            "category":"Retail",
            "subcategory":"Repair Shop",
            "type":"Services"
        }
    ],
    "sg:phone":"+61 8 9307 5877",
    "sg:postcode":"6025",
    "sg:province":"WA",
    "sg:tags":[
        "stove",
        "part",
        "range"
    ],
    "wof:name":"Modern Appliance Repairs",
    "wof:placetype":"venue"
},
  "geometry": {"coordinates":[115.742492676,-31.8156604767],"type":"Point"}
}