{
  "type": "Feature",
  "properties": {
    "addr:full":"49 Great Eastern Hwy Rivervale WA 6103",
    "addr:housenumber":"49",
    "addr:postcode":"6103",
    "addr:street":"Great Eastern Hwy",
    "iso:country":"AU",
    "sg:address":"49 Great Eastern Hwy",
    "sg:city":"Rivervale",
    "sg:classifiers":[
        {
            "category":"Fast Food",
            "type":"Food & Drink"
        }
    ],
    "sg:phone":"+61 8 9472 7486",
    "sg:postcode":"6103",
    "sg:province":"WA",
    "sg:tags":[
        "away",
        "take"
    ],
    "wof:name":"Red Rooster",
    "wof:placetype":"venue"
},
  "geometry": {"coordinates":[115.907318115,-31.955909729],"type":"Point"}
}