{
  "type": "Feature",
  "properties": {
    "addr:full":"48 Bailey St Bairnsdale VIC 3875",
    "addr:housenumber":"48",
    "addr:postcode":"3875",
    "addr:street":"Bailey St",
    "iso:country":"AU",
    "sg:address":"48 Bailey St",
    "sg:city":"Bairnsdale",
    "sg:classifiers":[
        {
            "category":"Professional",
            "subcategory":"Engineering",
            "type":"Services"
        }
    ],
    "sg:phone":"+61 3 5152 1600",
    "sg:postcode":"3875",
    "sg:province":"VIC",
    "sg:tags":[
        "consulting",
        "engineer"
    ],
    "wof:name":"Earth Tech Engineering Pty Ltd",
    "wof:placetype":"venue"
},
  "geometry": {"coordinates":[147.63206481899999,-37.8267631531],"type":"Point"}
}