{
  "type": "Feature",
  "properties": {
    "addr:full":"906- 910 Glenhuntly Rd Caulfield VIC 3162",
    "addr:housenumber":"910",
    "addr:postcode":"3162",
    "addr:street":"Glenhuntly Rd",
    "iso:country":"AU",
    "sg:address":"906- 910 Glenhuntly Rd",
    "sg:city":"Caulfield",
    "sg:classifiers":[
        {
            "category":"Building & Trades",
            "subcategory":"Equipment Rental",
            "type":"Services"
        }
    ],
    "sg:phone":"+61 3 9532 8833",
    "sg:postcode":"3162",
    "sg:province":"VIC",
    "sg:tags":[
        "party",
        "hire"
    ],
    "wof:name":"Dann Event Hire",
    "wof:placetype":"venue"
},
  "geometry": {"coordinates":[145.02832031200001,-37.8877944946],"type":"Point"}
}