{
  "type": "Feature",
  "properties": {
    "addr:full":"283 Eardley's Rd Bundaberg QLD 4670",
    "addr:housenumber":"283",
    "addr:postcode":"4670",
    "addr:street":"Eardley'S Rd",
    "iso:country":"AU",
    "sg:address":"283 Eardley's Rd",
    "sg:city":"Bundaberg",
    "sg:classifiers":[
        {
            "category":"Building & Trades",
            "subcategory":"Construction",
            "type":"Services"
        }
    ],
    "sg:phone":"+61 7 4159 8489",
    "sg:postcode":"4670",
    "sg:province":"QLD",
    "sg:tags":[
        "earth",
        "excavating",
        "moving",
        "contractor"
    ],
    "wof:name":"B.D.N. Earthmovers",
    "wof:placetype":"venue"
},
  "geometry": {"coordinates":[152.34669494600001,-24.8670501709],"type":"Point"}
}