{
  "type": "Feature",
  "properties": {
    "addr:full":"PO Box 91 Cardiff NSW 2285",
    "addr:postcode":"2285",
    "iso:country":"AU",
    "sg:address":"PO Box 91",
    "sg:city":"Cardiff",
    "sg:classifiers":[
        {
            "category":"Home & Garden",
            "subcategory":"Hardware",
            "type":"Retail Goods"
        }
    ],
    "sg:phone":"+61 2 4954 0000",
    "sg:postcode":"2285",
    "sg:province":"NSW",
    "sg:tags":[
        "part",
        "air conditioning"
    ],
    "wof:name":"Marin Industries Pty Ltd",
    "wof:placetype":"venue"
},
  "geometry": {"coordinates":[151.664596558,-32.9420509338],"type":"Point"}
}