{
  "type": "Feature",
  "properties": {
    "addr:full":"79 Kremzow Rd Brendale QLD 4500",
    "addr:housenumber":"79",
    "addr:postcode":"4500",
    "addr:street":"Kremzow Rd",
    "iso:country":"AU",
    "sg:address":"79 Kremzow Rd",
    "sg:city":"Brendale",
    "sg:classifiers":[
        {
            "category":"Shopping",
            "subcategory":"Bicycles & Sporting Goods",
            "type":"Retail Goods"
        }
    ],
    "sg:phone":"+61 7 3889 6722",
    "sg:postcode":"4500",
    "sg:province":"QLD",
    "sg:tags":[
        "chemical",
        "equipment",
        "pool",
        "swimming"
    ],
    "wof:name":"Swimsafe Pool Products",
    "wof:placetype":"venue"
},
  "geometry": {"coordinates":[152.97555542000001,-27.3164901733],"type":"Point"}
}