{
  "type": "Feature",
  "properties": {
    "addr:full":"134 Fussell St Ballarat VIC 3350",
    "addr:housenumber":"134",
    "addr:postcode":"3350",
    "addr:street":"Fussell St",
    "iso:country":"AU",
    "sg:address":"134 Fussell St",
    "sg:city":"Ballarat",
    "sg:classifiers":[
        {
            "category":"Building & Trades",
            "subcategory":"Construction",
            "type":"Services"
        }
    ],
    "sg:phone":"+61 3 5332 7040",
    "sg:postcode":"3350",
    "sg:province":"VIC",
    "sg:tags":[
        "joinery"
    ],
    "wof:name":"Advanced Cabinetry",
    "wof:placetype":"venue"
},
  "geometry": {"coordinates":[143.89421100000001,-37.565861],"type":"Point"}
}