{
  "type": "Feature",
  "properties": {
    "addr:full":"15 Pacific Hwy Kariong NSW 2250",
    "addr:housenumber":"15",
    "addr:postcode":"2250",
    "addr:street":"Pacific Hwy",
    "iso:country":"AU",
    "sg:address":"15 Pacific Hwy",
    "sg:city":"Kariong",
    "sg:classifiers":[
        {
            "category":"Building & Trades",
            "subcategory":"Pest Control",
            "type":"Services"
        }
    ],
    "sg:phone":"+61 2 4340 1270",
    "sg:postcode":"2250",
    "sg:province":"NSW",
    "wof:name":"A-Bill Pest Services",
    "wof:placetype":"venue"
},
  "geometry": {"coordinates":[151.29782104500001,-33.4357185364],"type":"Point"}
}