{
  "type": "Feature",
  "properties": {
    "addr:full":"Shop 2, Narangba Valley Shop Cntr Narangba QLD 4504",
    "addr:housenumber":"shop 2",
    "addr:postcode":"4504",
    "iso:country":"AU",
    "sg:address":"Shop 2, Narangba Valley Shop Cntr",
    "sg:city":"Narangba",
    "sg:classifiers":[
        {
            "category":"Fast Food",
            "type":"Food & Drink"
        }
    ],
    "sg:phone":"+61 7 3385 5588",
    "sg:postcode":"4504",
    "sg:province":"QLD",
    "sg:tags":[
        "away",
        "take"
    ],
    "wof:name":"Eagle Boys Pizza - Narangba",
    "wof:placetype":"venue"
},
  "geometry": {"coordinates":[152.97222900400001,-27.2442073822],"type":"Point"}
}