{
  "type": "Feature",
  "properties": {
    "iso:country":"AU",
    "sg:address":"Deep Creek Rd",
    "sg:city":"Wiseleigh",
    "sg:classifiers":[
        {
            "category":"Building & Trades",
            "subcategory":"Construction",
            "type":"Services"
        }
    ],
    "sg:phone":"+61 3 5157 5643",
    "sg:postcode":"3885",
    "sg:province":"VIC",
    "sg:tags":[
        "bridge",
        "contractor"
    ],
    "wof:name":"East Gippsland Bridges Pty Ltd",
    "wof:placetype":"venue"
},
  "geometry": {"coordinates":[147.80741882300001,-37.7123565674],"type":"Point"}
}