{
  "type": "Feature",
  "properties": {
    "iso:country":"AU",
    "sg:address":"26 Railway St",
    "sg:city":"Liverpool",
    "sg:classifiers":[
        {
            "category":"Food & Beverages",
            "subcategory":"Bakery",
            "type":"Retail Goods"
        }
    ],
    "sg:phone":"+61 2 9602 2529",
    "sg:postcode":"2170",
    "sg:province":"NSW",
    "sg:tags":[
        "cake",
        "shop",
        "pastry"
    ],
    "wof:name":"Parthenon Continental Cakes",
    "wof:placetype":"venue"
},
  "geometry": {"coordinates":[150.925506592,-33.924369812],"type":"Point"}
}