{
  "type": "Feature",
  "properties": {
    "addr:full":"8 Wood St Ballarat VIC 3350",
    "addr:housenumber":"8",
    "addr:postcode":"3350",
    "addr:street":"Wood St",
    "iso:country":"AU",
    "sg:address":"8 Wood St",
    "sg:city":"Ballarat",
    "sg:classifiers":[
        {
            "category":"Building & Trades",
            "subcategory":"Construction",
            "type":"Services"
        }
    ],
    "sg:phone":"+61 3 5332 2358",
    "sg:postcode":"3350",
    "sg:province":"VIC",
    "sg:tags":[
        "worker",
        "metal"
    ],
    "wof:name":"Duka B",
    "wof:placetype":"venue"
},
  "geometry": {"coordinates":[143.852295,-37.54369],"type":"Point"}
}