{
  "type": "Feature",
  "properties": {
    "iso:country":"AU",
    "sg:address":"21 Wheeler Ave",
    "sg:city":"Lurnea",
    "sg:classifiers":[
        {
            "category":"Home & Garden",
            "subcategory":"Building Materials",
            "type":"Retail Goods"
        }
    ],
    "sg:phone":"+61 419 427 964",
    "sg:postcode":"2170",
    "sg:province":"NSW",
    "sg:tags":[
        "merchant",
        "glass",
        "glazier"
    ],
    "wof:name":"Westside Glass",
    "wof:placetype":"venue"
},
  "geometry": {"coordinates":[150.89224243199999,-33.9383087158],"type":"Point"}
}