{
  "type": "Feature",
  "properties": {
    "addr:full":"Devon La Tarneit VIC 3029",
    "addr:postcode":"3029",
    "iso:country":"AU",
    "sg:address":"Devon La",
    "sg:city":"Tarneit",
    "sg:classifiers":[
        {
            "category":"Building & Trades",
            "subcategory":"Construction",
            "type":"Services"
        }
    ],
    "sg:phone":"+61 411 120 956",
    "sg:postcode":"3029",
    "sg:province":"VIC",
    "sg:tags":[
        "joiner",
        "carpenter"
    ],
    "wof:name":"NJO Carpentry",
    "wof:placetype":"venue"
},
  "geometry": {"coordinates":[144.70494099999999,-37.842617],"type":"Point"}
}