{
  "type": "Feature",
  "properties": {
    "addr:full":"127 Creek St Brisbane QLD 4000",
    "addr:housenumber":"127",
    "addr:postcode":"4000",
    "addr:street":"Creek St",
    "iso:country":"AU",
    "sg:address":"127 Creek St",
    "sg:city":"Brisbane",
    "sg:classifiers":[
        {
            "category":"Utilities",
            "subcategory":"Telephone",
            "type":"Services"
        }
    ],
    "sg:phone":"+61 7 3337 9999",
    "sg:postcode":"4000",
    "sg:province":"QLD",
    "sg:tags":[
        "equipment",
        "system"
    ],
    "wof:name":"Host Tel Voip Specialists",
    "wof:placetype":"venue"
},
  "geometry": {"coordinates":[153.027709961,-27.4658489227],"type":"Point"}
}