{
  "type": "Feature",
  "properties": {
    "addr:full":"501 South Rd Bentleigh VIC 3204",
    "addr:housenumber":"501",
    "addr:postcode":"3204",
    "addr:street":"South Rd",
    "iso:country":"AU",
    "sg:address":"501 South Rd",
    "sg:city":"Bentleigh",
    "sg:classifiers":[
        {
            "category":"Health Services",
            "subcategory":"Health Practitioner",
            "type":"Services"
        }
    ],
    "sg:phone":"+61 1300 366 284",
    "sg:postcode":"3204",
    "sg:province":"VIC",
    "sg:tags":[
        "physiotherapist"
    ],
    "wof:name":"Jennifer Vardy",
    "wof:placetype":"venue"
},
  "geometry": {"coordinates":[145.040131,-37.933456],"type":"Point"}
}