{
  "type": "Feature",
  "properties": {
    "addr:full":"20 Papagni Ave Newton SA 5074",
    "addr:housenumber":"20",
    "addr:postcode":"5074",
    "addr:street":"Papagni Ave",
    "iso:country":"AU",
    "sg:address":"20 Papagni Ave",
    "sg:city":"Newton",
    "sg:classifiers":[
        {
            "category":"Home & Garden",
            "subcategory":"Building Materials",
            "type":"Retail Goods"
        }
    ],
    "sg:phone":"+61 8 8165 2495",
    "sg:postcode":"5074",
    "sg:province":"SA",
    "sg:tags":[
        "merchant",
        "glass",
        "glazier"
    ],
    "wof:name":"G S Glass",
    "wof:placetype":"venue"
},
  "geometry": {"coordinates":[138.68255615199999,-34.879234314],"type":"Point"}
}