{
  "type": "Feature",
  "properties": {
    "addr:full":"23 Prindiville Drv Wangara WA 6065",
    "addr:housenumber":"23",
    "addr:postcode":"6065",
    "addr:street":"Prindiville Drv",
    "iso:country":"AU",
    "sg:address":"23 Prindiville Drv",
    "sg:city":"Wangara",
    "sg:classifiers":[
        {
            "category":"Shopping",
            "subcategory":"Bicycles & Sporting Goods",
            "type":"Retail Goods"
        }
    ],
    "sg:phone":"+61 8 9309 4800",
    "sg:postcode":"6065",
    "sg:province":"WA",
    "sg:tags":[
        "chemical",
        "equipment",
        "pool",
        "swimming"
    ],
    "wof:name":"Klen International",
    "wof:placetype":"venue"
},
  "geometry": {"coordinates":[115.818466187,-31.7908382416],"type":"Point"}
}