{
  "type": "Feature",
  "properties": {
    "addr:full":"Bridge St Trentham VIC 3458",
    "addr:postcode":"3458",
    "addr:street":"Bridge St",
    "iso:country":"AU",
    "sg:address":"Bridge St",
    "sg:city":"Trentham",
    "sg:classifiers":[
        {
            "category":"Education",
            "subcategory":"Kindergarten",
            "type":"Public Place"
        }
    ],
    "sg:phone":"+61 3 5424 1543",
    "sg:postcode":"3458",
    "sg:province":"VIC",
    "sg:tags":[
        "pre-schools"
    ],
    "wof:name":"Trentham Kindergarten Association",
    "wof:placetype":"venue"
},
  "geometry": {"coordinates":[144.32838439899999,-37.3884353638],"type":"Point"}
}