{
  "type": "Feature",
  "properties": {
    "iso:country":"AU",
    "sg:address":"16 Commerce Ave",
    "sg:city":"Warana",
    "sg:classifiers":[
        {
            "category":"Retail",
            "subcategory":"Auto Repair",
            "type":"Services"
        }
    ],
    "sg:phone":"+61 7 5493 3911",
    "sg:postcode":"4575",
    "sg:province":"QLD",
    "sg:tags":[
        "engine",
        "reconditioning"
    ],
    "wof:name":"Northern Volks Pty Ltd",
    "wof:placetype":"venue"
},
  "geometry": {"coordinates":[153.12793,-26.728329],"type":"Point"}
}