{
  "type": "Feature",
  "properties": {
    "iso:country":"AU",
    "sg:address":"Shop 4- 6",
    "sg:city":"Elgin Blv Wodonga",
    "sg:classifiers":[
        {
            "category":"Autos & Motor Vehicles",
            "subcategory":"Auto Supplies",
            "type":"Retail Goods"
        }
    ],
    "sg:phone":"+61 2 6024 1257",
    "sg:postcode":"3690",
    "sg:province":"VIC",
    "sg:tags":[
        "part",
        "cycles",
        "accessory"
    ],
    "wof:name":"Matthews Cycles",
    "wof:placetype":"venue"
},
  "geometry": {"coordinates":[146.892501831,-36.1128997803],"type":"Point"}
}