{
  "type": "Feature",
  "properties": {
    "addr:full":"173 Durlacher St Geraldton WA 6530",
    "addr:housenumber":"173",
    "addr:postcode":"6530",
    "addr:street":"Durlacher St",
    "iso:country":"AU",
    "sg:address":"173 Durlacher St",
    "sg:city":"Geraldton",
    "sg:classifiers":[
        {
            "category":"Fast Food",
            "type":"Food & Drink"
        }
    ],
    "sg:phone":"+61 8 9921 5310",
    "sg:postcode":"6530",
    "sg:province":"WA",
    "sg:tags":[
        "away",
        "take"
    ],
    "wof:name":"Hooks Sea & Salad Bar",
    "wof:placetype":"venue"
},
  "geometry": {"coordinates":[114.61743927000001,-28.7809143066],"type":"Point"}
}