{
  "type": "Feature",
  "properties": {
    "addr:full":"330 Cliveden Ave Corinda QLD 4075",
    "addr:housenumber":"330",
    "addr:postcode":"4075",
    "addr:street":"Cliveden Ave",
    "iso:country":"AU",
    "sg:address":"330 Cliveden Ave",
    "sg:city":"Corinda",
    "sg:classifiers":[
        {
            "category":"Education",
            "subcategory":"School",
            "type":"Public Place"
        }
    ],
    "sg:phone":"+61 7 3716 2335",
    "sg:postcode":"4075",
    "sg:province":"QLD",
    "sg:tags":[
        "state",
        "except",
        "nsw"
    ],
    "wof:name":"Corinda Preschool",
    "wof:placetype":"venue"
},
  "geometry": {"coordinates":[152.98147582999999,-27.5492553711],"type":"Point"}
}