{
  "type": "Feature",
  "properties": {
    "iso:country":"AU",
    "sg:address":"3/ 22 Nagle St",
    "sg:city":"Wagga Wagga",
    "sg:classifiers":[
        {
            "category":"Professional",
            "subcategory":"Printing & Photocopies",
            "type":"Services"
        }
    ],
    "sg:phone":"+61 2 6921 1565",
    "sg:postcode":"2650",
    "sg:province":"NSW",
    "sg:tags":[
        "screen",
        "printer"
    ],
    "wof:name":"Darrens T-Shirts & Screen Printing",
    "wof:placetype":"venue"
},
  "geometry": {"coordinates":[147.38226318400001,-35.1236419678],"type":"Point"}
}