{
  "type": "Feature",
  "properties": {
    "addr:full":"40 Lemon Ave Mildura VIC 3500",
    "addr:housenumber":"40",
    "addr:postcode":"3500",
    "addr:street":"Lemon Ave",
    "iso:country":"AU",
    "sg:address":"40 Lemon Ave",
    "sg:city":"Mildura",
    "sg:classifiers":[
        {
            "category":"Professional",
            "subcategory":"Detective & Security Services",
            "type":"Services"
        }
    ],
    "sg:phone":"+61 3 5022 7855",
    "sg:postcode":"3500",
    "sg:province":"VIC",
    "sg:tags":[
        "guard",
        "patrol"
    ],
    "wof:name":"Marshall Security Service Pty Ltd",
    "wof:placetype":"venue"
},
  "geometry": {"coordinates":[142.166213989,-34.1875457764],"type":"Point"}
}