{
  "type": "Feature",
  "properties": {
    "addr:full":"145 Graham Rd Marom Creek NSW 2480",
    "addr:housenumber":"145",
    "addr:postcode":"2480",
    "addr:street":"Graham Rd",
    "iso:country":"AU",
    "sg:address":"145 Graham Rd",
    "sg:city":"Marom Creek",
    "sg:classifiers":[
        {
            "category":"Ice Cream",
            "type":"Food & Drink"
        }
    ],
    "sg:phone":"+61 427 782 674",
    "sg:postcode":"2480",
    "sg:province":"NSW",
    "sg:tags":[
        "retail"
    ],
    "wof:name":"Debbie and Robert Cregan",
    "wof:placetype":"venue"
},
  "geometry": {"coordinates":[153.361724853,-28.880153656],"type":"Point"}
}