{
  "type": "Feature",
  "properties": {
    "addr:full":"52 De Burgh Rd Caversham WA 6055",
    "addr:postcode":"6055",
    "addr:street":"52 De Burgh Rd",
    "iso:country":"AU",
    "sg:address":"52 De Burgh Rd",
    "sg:city":"Caversham",
    "sg:classifiers":[
        {
            "category":"Farming",
            "subcategory":"Vineyard",
            "type":"Manufacturing & Wholesale Goods"
        }
    ],
    "sg:phone":"+61 8 9279 6060",
    "sg:postcode":"6055",
    "sg:province":"WA",
    "sg:tags":[
        "winery"
    ],
    "wof:name":"Lovreta & Sons",
    "wof:placetype":"venue"
},
  "geometry": {"coordinates":[115.980469,-31.875017],"type":"Point"}
}