{
  "type": "Feature",
  "properties": {
    "iso:country":"AU",
    "sg:address":"331 Morpeth Rd",
    "sg:city":"Raworth",
    "sg:classifiers":[
        {
            "category":"Building & Trades",
            "subcategory":"Landscaping Services",
            "type":"Services"
        }
    ],
    "sg:phone":"+61 2 4936 6377",
    "sg:postcode":"2321",
    "sg:province":"NSW",
    "sg:tags":[
        "gardener"
    ],
    "wof:name":"Garden Angel",
    "wof:placetype":"venue"
},
  "geometry": {"coordinates":[151.61408996599999,-32.7266693115],"type":"Point"}
}