{
  "type": "Feature",
  "properties": {
    "iso:country":"AU",
    "sg:address":"69 Boundary Rd",
    "sg:city":"Newcomb",
    "sg:classifiers":[
        {
            "category":"Building & Trades",
            "subcategory":"Cleaning & Sanitation",
            "type":"Services"
        }
    ],
    "sg:phone":"+61 419 556 773",
    "sg:postcode":"3219",
    "sg:province":"VIC",
    "sg:tags":[
        "abrasive",
        "blasting"
    ],
    "wof:name":"Hardiman Steel Protection Pty Ltd",
    "wof:placetype":"venue"
},
  "geometry": {"coordinates":[144.38575744600001,-38.163028717],"type":"Point"}
}