{
  "type": "Feature",
  "properties": {
    "addr:full":"644 David Low Way Pacific Paradise QLD 4564",
    "addr:housenumber":"644",
    "addr:postcode":"4564",
    "addr:street":"David Low Way",
    "iso:country":"AU",
    "sg:address":"644 David Low Way",
    "sg:city":"Pacific Paradise",
    "sg:classifiers":[
        {
            "category":"Real Estate",
            "subcategory":"Real Estate Agent",
            "type":"Services"
        }
    ],
    "sg:phone":"+61 7 5448 7700",
    "sg:postcode":"4564",
    "sg:province":"QLD",
    "sg:website":"http://www.maroochynorthshorerealty.com",
    "wof:name":"Maroochy North Shore Realty",
    "wof:placetype":"venue"
},
  "geometry": {"coordinates":[153.07745361299999,-26.618894577],"type":"Point"}
}