{
  "type": "Feature",
  "properties": {
    "iso:country":"AU",
    "sg:address":"Shop 3 2 Raymond McMahon Blv",
    "sg:city":"Endeavour Hills",
    "sg:classifiers":[
        {
            "category":"Fast Food",
            "type":"Food & Drink"
        }
    ],
    "sg:phone":"+61 3 9700 6888",
    "sg:postcode":"3802",
    "sg:province":"VIC",
    "sg:tags":[
        "away",
        "take"
    ],
    "wof:name":"Gold Dish Chinese Takeaway",
    "wof:placetype":"venue"
},
  "geometry": {"coordinates":[145.26141357399999,-37.9785919189],"type":"Point"}
}