{
  "type": "Feature",
  "properties": {
    "iso:country":"AU",
    "sg:address":"T095A, Erina Fair, Terrigal Drv",
    "sg:city":"Erina",
    "sg:classifiers":[
        {
            "category":"Health Services",
            "subcategory":"Optometrist",
            "type":"Services"
        }
    ],
    "sg:phone":"+61 2 4365 2638",
    "sg:postcode":"2250",
    "sg:province":"NSW",
    "wof:name":"Icontact",
    "wof:placetype":"venue"
},
  "geometry": {"coordinates":[151.39523315400001,-33.4345855713],"type":"Point"}
}