{
  "type": "Feature",
  "properties": {
    "iso:country":"AU",
    "sg:address":"28 Walters Drv",
    "sg:city":"Osborne Park",
    "sg:classifiers":[
        {
            "category":"Professional",
            "subcategory":"Employment Agencies",
            "type":"Services"
        }
    ],
    "sg:phone":"+61 8 9244 2404",
    "sg:postcode":"6017",
    "sg:province":"WA",
    "wof:name":"Supply Solutions",
    "wof:placetype":"venue"
},
  "geometry": {"coordinates":[115.809089661,-31.909576416],"type":"Point"}
}