{
  "type": "Feature",
  "properties": {
    "iso:country":"AU",
    "sg:address":"11 Mackie Rd",
    "sg:city":"Narangba",
    "sg:classifiers":[
        {
            "category":"Professional",
            "type":"Services"
        }
    ],
    "sg:phone":"+61 419 655 698",
    "sg:postcode":"4504",
    "sg:province":"QLD",
    "sg:tags":[
        "transport"
    ],
    "wof:name":"Paul McCahon Transport",
    "wof:placetype":"venue"
},
  "geometry": {"coordinates":[152.98301696799999,-27.1969108582],"type":"Point"}
}