{
  "type": "Feature",
  "properties": {
    "addr:full":"PO Box 189 Carina QLD 4152",
    "addr:postcode":"4152",
    "iso:country":"AU",
    "sg:address":"PO Box 189",
    "sg:city":"Carina",
    "sg:classifiers":[
        {
            "category":"Professional",
            "subcategory":"Computer Services",
            "type":"Services"
        }
    ],
    "sg:phone":"+61 7 3843 2335",
    "sg:postcode":"4152",
    "sg:province":"QLD",
    "sg:tags":[
        "consultant",
        "system"
    ],
    "wof:name":"Support Technology+",
    "wof:placetype":"venue"
},
  "geometry": {"coordinates":[153.100006103,-27.4898204803],"type":"Point"}
}