{
  "type": "Feature",
  "properties": {
    "addr:full":"Stilton Rd Picton NSW 2571",
    "addr:postcode":"2571",
    "addr:street":"Stilton Rd",
    "iso:country":"AU",
    "sg:address":"Stilton Rd",
    "sg:city":"Picton",
    "sg:classifiers":[
        {
            "category":"Manufacturing",
            "subcategory":"Tools & Machinery",
            "type":"Manufacturing & Wholesale Goods"
        }
    ],
    "sg:phone":"+61 2 4677 1367",
    "sg:postcode":"2571",
    "sg:province":"NSW",
    "sg:tags":[
        "toolmaker"
    ],
    "wof:name":"Visser J G",
    "wof:placetype":"venue"
},
  "geometry": {"coordinates":[150.60401916500001,-34.2038383484],"type":"Point"}
}