{
  "type": "Feature",
  "properties": {
    "addr:full":"37 Vine St Magill SA 5072",
    "addr:housenumber":"37",
    "addr:postcode":"5072",
    "addr:street":"Vine St",
    "iso:country":"AU",
    "sg:address":"37 Vine St",
    "sg:city":"Magill",
    "sg:classifiers":[
        {
            "category":"Retail",
            "subcategory":"Auto Repair",
            "type":"Services"
        }
    ],
    "sg:phone":"+61 8 8364 4077",
    "sg:postcode":"5072",
    "sg:province":"SA",
    "sg:tags":[
        "repairer",
        "motor",
        "engineer"
    ],
    "wof:name":"Pacetech Automotive",
    "wof:placetype":"venue"
},
  "geometry": {"coordinates":[138.68043518100001,-34.9083900452],"type":"Point"}
}