{
  "type": "Feature",
  "properties": {
    "iso:country":"AU",
    "sg:address":"Emu Flat Rd",
    "sg:city":"Keith",
    "sg:classifiers":[
        {
            "category":"Sports & Exercise",
            "subcategory":"Golf",
            "type":"Entertainment"
        }
    ],
    "sg:phone":"+61 8 8755 1272",
    "sg:postcode":"5267",
    "sg:province":"SA",
    "sg:tags":[
        "club"
    ],
    "wof:name":"Keith Golf Club Incorporated",
    "wof:placetype":"venue"
},
  "geometry": {"coordinates":[140.353424,-36.093048],"type":"Point"}
}