{
  "type": "Feature",
  "properties": {
    "iso:country":"AU",
    "sg:address":"Cnr Harp Rd & High St",
    "sg:city":"Kew East",
    "sg:classifiers":[
        {
            "category":"Utilities",
            "subcategory":"Fuel Oil & Lpg",
            "type":"Services"
        }
    ],
    "sg:phone":"+61 3 9859 2615",
    "sg:postcode":"3102",
    "sg:province":"VIC",
    "sg:tags":[
        "merchant"
    ],
    "wof:name":"Dunning & Sons",
    "wof:placetype":"venue"
},
  "geometry": {"coordinates":[145.05079650900001,-37.7993583679],"type":"Point"}
}