{
  "type": "Feature",
  "properties": {
    "addr:full":"Unit 16, 7 Anella Ave Castle Hill NSW 2154",
    "addr:housenumber":"7",
    "addr:postcode":"2154",
    "addr:street":"Anella Ave",
    "iso:country":"AU",
    "sg:address":"Unit 16, 7 Anella Ave",
    "sg:city":"Castle Hill",
    "sg:classifiers":[
        {
            "category":"Insurance",
            "subcategory":"Life Insurance",
            "type":"Services"
        }
    ],
    "sg:phone":"+61 2 9899 9644",
    "sg:postcode":"2154",
    "sg:province":"NSW",
    "wof:name":"InsureInvest Financial Centre Pty Ltd",
    "wof:placetype":"venue"
},
  "geometry": {"coordinates":[150.97848510700001,-33.7265663147],"type":"Point"}
}