{
  "type": "Feature",
  "properties": {
    "iso:country":"AU",
    "sg:address":"31 Wilson St",
    "sg:city":"Horsham",
    "sg:classifiers":[
        {
            "category":"Shopping",
            "type":"Retail Goods"
        }
    ],
    "sg:phone":"+61 3 5382 0330",
    "sg:postcode":"3400",
    "sg:province":"VIC",
    "sg:tags":[
        "clearance",
        "factory",
        "outlet"
    ],
    "wof:name":"Leading Labels Factory Outlet",
    "wof:placetype":"venue"
},
  "geometry": {"coordinates":[142.20112609899999,-36.7167396545],"type":"Point"}
}