{
  "type": "Feature",
  "properties": {
    "addr:full":"Unit 22 Thew Pde Dee Why NSW 2099",
    "addr:postcode":"2099",
    "iso:country":"AU",
    "sg:address":"Unit 22 Thew Pde",
    "sg:city":"Dee Why",
    "sg:classifiers":[
        {
            "category":"Retail",
            "subcategory":"Auto Repair",
            "type":"Services"
        }
    ],
    "sg:phone":"+61 2 9982 5288",
    "sg:postcode":"2099",
    "sg:province":"NSW",
    "sg:tags":[
        "engine",
        "reconditioning"
    ],
    "wof:name":"MIA Engine Service Pty Ltd",
    "wof:placetype":"venue"
},
  "geometry": {"coordinates":[151.28305053700001,-33.7365493774],"type":"Point"}
}