{
  "type": "Feature",
  "properties": {
    "addr:full":"328- 330 North East Rd Greenacres SA 5086",
    "addr:housenumber":"330",
    "addr:postcode":"5086",
    "addr:street":"North East Rd",
    "iso:country":"AU",
    "sg:address":"328- 330 North East Rd",
    "sg:city":"Greenacres",
    "sg:classifiers":[
        {
            "category":"Home & Garden",
            "subcategory":"Hardware",
            "type":"Retail Goods"
        }
    ],
    "sg:phone":"+61 1800 032 566",
    "sg:postcode":"5086",
    "sg:province":"SA",
    "sg:tags":[
        "plumber",
        "supply"
    ],
    "wof:name":"Reece Pty Ltd",
    "wof:placetype":"venue"
},
  "geometry": {"coordinates":[138.638183594,-34.8706626892],"type":"Point"}
}