{
  "type": "Feature",
  "properties": {
    "iso:country":"AU",
    "sg:address":"62- 72 High St",
    "sg:city":"Southport",
    "sg:classifiers":[
        {
            "category":"Autos & Motor Vehicles",
            "subcategory":"Automobile Sales",
            "type":"Retail Goods"
        }
    ],
    "sg:phone":"+61 7 5583 8888",
    "sg:postcode":"4215",
    "sg:province":"QLD",
    "sg:tags":[
        "car",
        "used"
    ],
    "wof:name":"James Frizelles Automotive Group",
    "wof:placetype":"venue"
},
  "geometry": {"coordinates":[153.40921020499999,-27.9673442841],"type":"Point"}
}