{
  "type": "Feature",
  "properties": {
    "addr:full":"101 Nelson St Wallsend NSW 2287",
    "addr:housenumber":"101",
    "addr:postcode":"2287",
    "addr:street":"Nelson St",
    "iso:country":"AU",
    "sg:address":"101 Nelson St",
    "sg:city":"Wallsend",
    "sg:classifiers":[
        {
            "category":"Personal",
            "subcategory":"Beauty Salon",
            "type":"Services"
        }
    ],
    "sg:phone":"+61 2 4955 5800",
    "sg:postcode":"2287",
    "sg:province":"NSW",
    "wof:name":"Sienna Rae Beauty Therapy",
    "wof:placetype":"venue"
},
  "geometry": {"coordinates":[151.66917419399999,-32.9011001587],"type":"Point"}
}