{
  "type": "Feature",
  "properties": {
    "iso:country":"AU",
    "sg:address":"Shop 10",
    "sg:city":", Clifton Village Shopping Centre Clifton Bea",
    "sg:classifiers":[
        {
            "category":"Personal",
            "subcategory":"Massage",
            "type":"Services"
        }
    ],
    "sg:phone":"+61 7 4059 2759",
    "sg:postcode":"4879",
    "sg:province":"QLD",
    "sg:tags":[
        "therapy"
    ],
    "wof:name":"beauty@clifton#",
    "wof:placetype":"venue"
},
  "geometry": {"coordinates":[145.675292969,-16.7689056396],"type":"Point"}
}