{
  "type": "Feature",
  "properties": {
    "iso:country":"AU",
    "sg:address":"35 Law St",
    "sg:city":"Bundamba",
    "sg:classifiers":[
        {
            "category":"Building & Trades",
            "subcategory":"Plumbing",
            "type":"Services"
        }
    ],
    "sg:phone":"+61 7 3816 0195",
    "sg:postcode":"4304",
    "sg:province":"QLD",
    "sg:tags":[
        "plumber",
        "gasfitters"
    ],
    "wof:name":"Bundamba Plumbing",
    "wof:placetype":"venue"
},
  "geometry": {"coordinates":[152.813598633,-27.6039829254],"type":"Point"}
}