{
  "type": "Feature",
  "properties": {
    "addr:full":"Talea Mayne Drv Tamworth NSW 2340",
    "addr:postcode":"2340",
    "addr:street":"Mayne Drv",
    "iso:country":"AU",
    "sg:address":"Talea Mayne Drv",
    "sg:city":"Tamworth",
    "sg:classifiers":[
        {
            "category":"Building & Trades",
            "subcategory":"Construction",
            "type":"Services"
        }
    ],
    "sg:phone":"+61 2 6760 7334",
    "sg:postcode":"2340",
    "sg:province":"NSW",
    "sg:tags":[
        "concrete",
        "contractor"
    ],
    "wof:name":"Sinclair Ross Concrete",
    "wof:placetype":"venue"
},
  "geometry": {"coordinates":[150.87986755399999,-31.0963954926],"type":"Point"}
}