{
  "type": "Feature",
  "properties": {
    "addr:full":"109 Springacre Rd Thornlands QLD 4164",
    "addr:housenumber":"109",
    "addr:postcode":"4164",
    "addr:street":"Springacre Rd",
    "iso:country":"AU",
    "sg:address":"109 Springacre Rd",
    "sg:city":"Thornlands",
    "sg:classifiers":[
        {
            "category":"Professional",
            "subcategory":"Management & Consulting",
            "type":"Services"
        }
    ],
    "sg:phone":"+61 7 3206 4316",
    "sg:postcode":"4164",
    "sg:province":"QLD",
    "sg:tags":[
        "consultant"
    ],
    "wof:name":"Mobandilla Pty Ltd",
    "wof:placetype":"venue"
},
  "geometry": {"coordinates":[153.256256103,-27.5806026459],"type":"Point"}
}