{
  "type": "Feature",
  "properties": {
    "addr:full":"1 / 45 Edward St Osborne Park WA 6017",
    "addr:housenumber":"/ 45",
    "addr:postcode":"6017",
    "addr:street":"Edward St",
    "iso:country":"AU",
    "sg:address":"1 / 45 Edward St",
    "sg:city":"Osborne Park",
    "sg:classifiers":[
        {
            "category":"Manufacturing",
            "subcategory":"Metals",
            "type":"Manufacturing & Wholesale Goods"
        }
    ],
    "sg:phone":"+61 8 9444 2611",
    "sg:postcode":"6017",
    "sg:province":"WA",
    "sg:tags":[
        "metallurgist"
    ],
    "wof:name":"LionOre Technology Pty Ltd",
    "wof:placetype":"venue"
},
  "geometry": {"coordinates":[115.82673645,-31.9017925262],"type":"Point"}
}