{
  "type": "Feature",
  "properties": {
    "iso:country":"AU",
    "sg:address":"PO Box 69",
    "sg:city":"Richmond",
    "sg:classifiers":[
        {
            "category":"Shopping",
            "subcategory":"Jewelry",
            "type":"Retail Goods"
        }
    ],
    "sg:phone":"+61 419 652 488",
    "sg:postcode":"7025",
    "sg:province":"TAS",
    "sg:tags":[
        "jeweller"
    ],
    "wof:name":"Sotear",
    "wof:placetype":"venue"
},
  "geometry": {"coordinates":[147.436843872,-42.7359695435],"type":"Point"}
}