{
  "type": "Feature",
  "properties": {
    "addr:full":"41 Mountford Rd New Farm QLD 4005",
    "addr:housenumber":"41",
    "addr:postcode":"4005",
    "addr:street":"Mountford Rd",
    "iso:country":"AU",
    "sg:address":"41 Mountford Rd",
    "sg:city":"New Farm",
    "sg:classifiers":[
        {
            "category":"Travel",
            "subcategory":"Travel Agent",
            "type":"Entertainment"
        }
    ],
    "sg:phone":"+61 7 3358 3299",
    "sg:postcode":"4005",
    "sg:province":"QLD",
    "sg:tags":[
        "consultant"
    ],
    "wof:name":"Advanced Travel Service",
    "wof:placetype":"venue"
},
  "geometry": {"coordinates":[153.04576110799999,-27.4728736877],"type":"Point"}
}