{
  "type": "Feature",
  "properties": {
    "addr:full":"6 Oak St Glenden QLD 4743",
    "addr:housenumber":"6",
    "addr:postcode":"4743",
    "addr:street":"Oak St",
    "iso:country":"AU",
    "sg:address":"6 Oak St",
    "sg:city":"Glenden",
    "sg:classifiers":[
        {
            "category":"Wholesale",
            "subcategory":"Farm Supplies",
            "type":"Manufacturing & Wholesale Goods"
        }
    ],
    "sg:phone":"+61 7 4958 9080",
    "sg:postcode":"4743",
    "sg:province":"QLD",
    "sg:tags":[
        "feed",
        "supplement",
        "stock"
    ],
    "wof:name":"Glenden Hardware & Rural",
    "wof:placetype":"venue"
},
  "geometry": {"coordinates":[148.10656700000001,-21.34597],"type":"Point"}
}