{
  "type": "Feature",
  "properties": {
    "iso:country":"AU",
    "sg:address":"Shop 12",
    "sg:city":"Girraween Shopping Cntr Armidale",
    "sg:classifiers":[
        {
            "category":"Building & Trades",
            "subcategory":"Equipment Rental",
            "type":"Services"
        }
    ],
    "sg:phone":"+61 1800 859 621",
    "sg:postcode":"2350",
    "sg:province":"NSW",
    "sg:tags":[
        "supply",
        "catering"
    ],
    "wof:name":"O.C.C.E.",
    "wof:placetype":"venue"
},
  "geometry": {"coordinates":[151.74203491200001,-30.6037902832],"type":"Point"}
}