{
  "type": "Feature",
  "properties": {
    "addr:full":"Suite 2/ 8 Lingard St Merewether NSW 2291",
    "addr:housenumber":"8",
    "addr:postcode":"2291",
    "addr:street":"Lingard St",
    "iso:country":"AU",
    "sg:address":"Suite 2/ 8 Lingard St",
    "sg:city":"Merewether",
    "sg:classifiers":[
        {
            "category":"Real Estate",
            "subcategory":"Surveying",
            "type":"Services"
        }
    ],
    "sg:phone":"+61 2 4963 5520",
    "sg:postcode":"2291",
    "sg:province":"NSW",
    "sg:tags":[
        "surveyor",
        "land"
    ],
    "wof:name":"Blight Brian",
    "wof:placetype":"venue"
},
  "geometry": {"coordinates":[151.755783081,-32.9415206909],"type":"Point"}
}