{
  "type": "Feature",
  "properties": {
    "addr:full":"23 Hurtle Ave Bonython ACT 2905",
    "addr:housenumber":"23",
    "addr:postcode":"2905",
    "addr:street":"Hurtle Ave",
    "iso:country":"AU",
    "sg:address":"23 Hurtle Ave",
    "sg:city":"Bonython",
    "sg:classifiers":[
        {
            "category":"Building & Trades",
            "subcategory":"Construction",
            "type":"Services"
        }
    ],
    "sg:phone":"+61 414 626 890",
    "sg:postcode":"2905",
    "sg:province":"ACT",
    "sg:tags":[
        "contractor"
    ],
    "wof:name":"Kyriacou S",
    "wof:placetype":"venue"
},
  "geometry": {"coordinates":[149.08467102,-35.4349632263],"type":"Point"}
}