{
  "type": "Feature",
  "properties": {
    "addr:full":"17/ 19 Lady Penrhyn Drv Unanderra NSW 2526",
    "addr:housenumber":"17 / 19",
    "addr:postcode":"2526",
    "addr:street":"Lady Penrhyn Drv",
    "iso:country":"AU",
    "sg:address":"17/ 19 Lady Penrhyn Drv",
    "sg:city":"Unanderra",
    "sg:classifiers":[
        {
            "category":"Building & Trades",
            "subcategory":"Construction",
            "type":"Services"
        }
    ],
    "sg:phone":"+61 2 4272 4044",
    "sg:postcode":"2526",
    "sg:province":"NSW",
    "sg:tags":[
        "industrial",
        "commercial",
        "air conditioning"
    ],
    "wof:name":"Thomas & Coffey",
    "wof:placetype":"venue"
},
  "geometry": {"coordinates":[150.84863281200001,-34.4621315002],"type":"Point"}
}