{
  "type": "Feature",
  "properties": {
    "addr:full":"24 Thomas St Chatswood NSW 2067",
    "addr:housenumber":"24",
    "addr:postcode":"2067",
    "addr:street":"Thomas St",
    "iso:country":"AU",
    "sg:address":"24 Thomas St",
    "sg:city":"Chatswood",
    "sg:classifiers":[
        {
            "category":"Health Services",
            "subcategory":"Doctor",
            "type":"Services"
        }
    ],
    "sg:phone":"+61 2 9411 1585",
    "sg:postcode":"2067",
    "sg:province":"NSW",
    "sg:tags":[
        "medical",
        "practitioner"
    ],
    "wof:name":"Figtree B R Scamps P A Grattan-Smith A P",
    "wof:placetype":"venue"
},
  "geometry": {"coordinates":[151.17956543,-33.7983627319],"type":"Point"}
}