{
  "type": "Feature",
  "properties": {
    "iso:country":"AU",
    "sg:address":"PO Box 25",
    "sg:city":"Maryborough",
    "sg:classifiers":[
        {
            "category":"Building & Trades",
            "subcategory":"Construction",
            "type":"Services"
        }
    ],
    "sg:phone":"+61 417 520 721",
    "sg:postcode":"3465",
    "sg:province":"VIC",
    "sg:tags":[
        "plasterboard",
        "plasterer",
        "fixer"
    ],
    "wof:name":"Taylor Brian",
    "wof:placetype":"venue"
},
  "geometry": {"coordinates":[143.73561096200001,-37.0486412048],"type":"Point"}
}