{
  "type": "Feature",
  "properties": {
    "iso:country":"AU",
    "sg:address":"41 Yule Rd",
    "sg:city":"Merewether",
    "sg:classifiers":[
        {
            "category":"Professional",
            "subcategory":"Computer Services",
            "type":"Services"
        }
    ],
    "sg:phone":"+61 2 4963 3633",
    "sg:postcode":"2291",
    "sg:province":"NSW",
    "sg:tags":[
        "consultant",
        "system"
    ],
    "wof:name":"Novatex Research Pty Ltd",
    "wof:placetype":"venue"
},
  "geometry": {"coordinates":[151.74316406200001,-32.9452514648],"type":"Point"}
}