{
  "type": "Feature",
  "properties": {
    "iso:country":"AU",
    "sg:address":"18 Chatsbury St",
    "sg:city":"Goulburn",
    "sg:classifiers":[
        {
            "category":"Transit Center",
            "subcategory":"Freight",
            "type":"Transportation"
        }
    ],
    "sg:phone":"+61 2 4821 3699",
    "sg:postcode":"2580",
    "sg:province":"NSW",
    "sg:tags":[
        "equipment",
        "transport",
        "road",
        "vehicle"
    ],
    "wof:name":"Goulburn Truck Towing",
    "wof:placetype":"venue"
},
  "geometry": {"coordinates":[149.73535156200001,-34.7437057495],"type":"Point"}
}