{
  "type": "Feature",
  "properties": {
    "addr:full":"63 Riechardt Rd Winnellie NT 0821",
    "addr:housenumber":"63",
    "addr:postcode":"nt 0821",
    "addr:street":"Riechardt Rd",
    "iso:country":"AU",
    "sg:address":"63 Riechardt Rd",
    "sg:city":"Winnellie",
    "sg:classifiers":[
        {
            "category":"Retail",
            "subcategory":"Storage",
            "type":"Services"
        }
    ],
    "sg:phone":"+61 8 8985 5474",
    "sg:postcode":"0821",
    "sg:province":"NT",
    "wof:name":"Winnellie-Central u-Storage",
    "wof:placetype":"venue"
},
  "geometry": {"coordinates":[130.87991332999999,-12.4266233444],"type":"Point"}
}