{
  "type": "Feature",
  "properties": {
    "iso:country":"AU",
    "sg:address":"22 Red Poll Crt",
    "sg:city":"Chittering",
    "sg:classifiers":[
        {
            "category":"Building & Trades",
            "subcategory":"Cleaning & Sanitation",
            "type":"Services"
        }
    ],
    "sg:phone":"+61 8 9571 8167",
    "sg:postcode":"6084",
    "sg:province":"WA",
    "sg:tags":[
        "tank",
        "septic"
    ],
    "wof:name":"Chittering Septic Service",
    "wof:placetype":"venue"
},
  "geometry": {"coordinates":[116.071731567,-31.5641498566],"type":"Point"}
}