{
  "type": "Feature",
  "properties": {
    "addr:full":"6 Headlands Crt Caloundra QLD 4551",
    "addr:housenumber":"6",
    "addr:postcode":"4551",
    "addr:street":"Headlands Crt",
    "iso:country":"AU",
    "sg:address":"6 Headlands Crt",
    "sg:city":"Caloundra",
    "sg:classifiers":[
        {
            "category":"Professional",
            "subcategory":"Management & Consulting",
            "type":"Services"
        }
    ],
    "sg:phone":"+61 422 159 830",
    "sg:postcode":"4551",
    "sg:province":"QLD",
    "sg:tags":[
        "consultant",
        "educational"
    ],
    "wof:name":"Successful Kids!",
    "wof:placetype":"venue"
},
  "geometry": {"coordinates":[153.14210510300001,-26.7954883575],"type":"Point"}
}