{
  "type": "Feature",
  "properties": {
    "addr:full":"89 Hardgrave Rd West End (Brisbane) QLD 4101",
    "addr:housenumber":"89",
    "addr:postcode":"4101",
    "addr:street":"Hardgrave Rd",
    "iso:country":"AU",
    "sg:address":"89 Hardgrave Rd",
    "sg:city":"West End (Brisbane)",
    "sg:classifiers":[
        {
            "category":"Shopping",
            "subcategory":"Clothing, Apparel, & Fashions",
            "type":"Retail Goods"
        }
    ],
    "sg:phone":"+61 7 3844 7423",
    "sg:postcode":"4101",
    "sg:province":"QLD",
    "sg:tags":[
        "recycled",
        "clothing"
    ],
    "wof:name":"St Veronica Thrift Shop",
    "wof:placetype":"venue"
},
  "geometry": {"coordinates":[153.00672912600001,-27.4828472137],"type":"Point"}
}