{
  "type": "Feature",
  "properties": {
    "iso:country":"AU",
    "sg:address":"185 Sir Fred Schonell Drv",
    "sg:city":"St Lucia",
    "sg:classifiers":[
        {
            "category":"Fast Food",
            "type":"Food & Drink"
        }
    ],
    "sg:phone":"+61 7 3870 7757",
    "sg:postcode":"4067",
    "sg:province":"QLD",
    "sg:tags":[
        "away",
        "take"
    ],
    "wof:name":"Chai's Takeaway & Convenience Store",
    "wof:placetype":"venue"
},
  "geometry": {"coordinates":[153.0027771,-27.4944896698],"type":"Point"}
}