{
  "type": "Feature",
  "properties": {
    "addr:full":"103 Grandview St Pymble NSW 2073",
    "addr:housenumber":"103",
    "addr:postcode":"2073",
    "addr:street":"Grandview St",
    "iso:country":"AU",
    "sg:address":"103 Grandview St",
    "sg:city":"Pymble",
    "sg:classifiers":[
        {
            "category":"Food & Beverages",
            "subcategory":"Liquor & Beverages",
            "type":"Retail Goods"
        }
    ],
    "sg:phone":"+61 2 9449 9511",
    "sg:postcode":"2073",
    "sg:province":"NSW",
    "sg:tags":[
        "store"
    ],
    "wof:name":"Pymble Cellars",
    "wof:placetype":"venue"
},
  "geometry": {"coordinates":[151.14146423299999,-33.7441482544],"type":"Point"}
}