{
  "type": "Feature",
  "properties": {
    "addr:full":"Factory 3 85-91 Highstreet Melton VIC 3337",
    "addr:housenumber":"3 85-91",
    "addr:postcode":"3337",
    "addr:street":"Highstreet",
    "iso:country":"AU",
    "sg:address":"Factory 3 85-91 Highstreet",
    "sg:city":"Melton",
    "sg:classifiers":[
        {
            "category":"Utilities",
            "subcategory":"Electric",
            "type":"Services"
        }
    ],
    "sg:phone":"+61 404 306 061",
    "sg:postcode":"3337",
    "sg:province":"VIC",
    "sg:tags":[
        "electrical",
        "contractor"
    ],
    "wof:name":"Local Home Electrical Services P/L",
    "wof:placetype":"venue"
},
  "geometry": {"coordinates":[144.58189400000001,-37.683289],"type":"Point"}
}