{
  "type": "Feature",
  "properties": {
    "addr:full":"70 St Kilda Rd St Kilda VIC 3182",
    "addr:housenumber":"70",
    "addr:postcode":"3182",
    "addr:street":"St Kilda Rd",
    "iso:country":"AU",
    "sg:address":"70 St Kilda Rd St",
    "sg:city":"Kilda",
    "sg:classifiers":[
        {
            "category":"Building & Trades",
            "subcategory":"Locksmith",
            "type":"Services"
        }
    ],
    "sg:phone":"+61 1800 628 110",
    "sg:postcode":"3182",
    "sg:province":"VIC",
    "sg:tags":[
        "lock"
    ],
    "wof:name":"A AAABA Shomer Locksmiths",
    "wof:placetype":"venue"
},
  "geometry": {"coordinates":[144.98396301299999,-37.8585014343],"type":"Point"}
}