{
  "type": "Feature",
  "properties": {
    "addr:full":"2 Magnolia Pl Port Macquarie NSW 2444",
    "addr:housenumber":"2",
    "addr:postcode":"2444",
    "addr:street":"Magnolia Pl",
    "iso:country":"AU",
    "sg:address":"2 Magnolia Pl",
    "sg:city":"Port Macquarie",
    "sg:classifiers":[
        {
            "category":"Building & Trades",
            "subcategory":"Construction",
            "type":"Services"
        }
    ],
    "sg:phone":"+61 2 6582 3148",
    "sg:postcode":"2444",
    "sg:province":"NSW",
    "sg:tags":[
        "ceiling"
    ],
    "wof:name":"Fred Middleton",
    "wof:placetype":"venue"
},
  "geometry": {"coordinates":[152.91999799999999,-31.46043],"type":"Point"}
}