{
  "type": "Feature",
  "properties": {
    "addr:full":"Level 12, 20 Bridge St Sydney NSW 2000",
    "addr:housenumber":"20",
    "addr:postcode":"2000",
    "addr:street":"Bridge St",
    "iso:country":"AU",
    "sg:address":"Level 12, 20 Bridge St",
    "sg:city":"Sydney",
    "sg:classifiers":[
        {
            "category":"Banks & Credit Unions",
            "subcategory":"Investment Brokerage",
            "type":"Services"
        }
    ],
    "sg:phone":"+61 2 9251 1877",
    "sg:postcode":"2000",
    "sg:province":"NSW",
    "wof:name":"Vertex Capital Management Ltd",
    "wof:placetype":"venue"
},
  "geometry": {"coordinates":[151.208816528,-33.863483429],"type":"Point"}
}