{
  "type": "Feature",
  "properties": {
    "addr:full":"86 Bunnerong Rd Maroubra NSW 2035",
    "addr:housenumber":"86",
    "addr:postcode":"2035",
    "addr:street":"Bunnerong Rd",
    "iso:country":"AU",
    "sg:address":"86 Bunnerong Rd",
    "sg:city":"Maroubra",
    "sg:classifiers":[
        {
            "category":"Health Services",
            "subcategory":"Health Practitioner",
            "type":"Services"
        }
    ],
    "sg:phone":"+61 402 249 358",
    "sg:postcode":"2035",
    "sg:province":"NSW",
    "sg:tags":[
        "pathologist",
        "speech"
    ],
    "wof:name":"Adelaide Pendlebury",
    "wof:placetype":"venue"
},
  "geometry": {"coordinates":[151.229446411,-33.9374275208],"type":"Point"}
}