{
  "type": "Feature",
  "properties": {
    "addr:full":"169 Spencer St Bunbury WA 6230",
    "addr:housenumber":"169",
    "addr:postcode":"6230",
    "addr:street":"Spencer St",
    "iso:country":"AU",
    "sg:address":"169 Spencer St",
    "sg:city":"Bunbury",
    "sg:classifiers":[
        {
            "category":"Health Services",
            "subcategory":"Health Practitioner",
            "type":"Services"
        }
    ],
    "sg:phone":"+61 8 9792 5775",
    "sg:postcode":"6230",
    "sg:province":"WA",
    "sg:tags":[
        "herbalist"
    ],
    "wof:name":"Change Centre",
    "wof:placetype":"venue"
},
  "geometry": {"coordinates":[115.641502,-33.346245],"type":"Point"}
}