{
  "type": "Feature",
  "properties": {
    "addr:full":"Shp 128 Tea Tree Plaza Modbury SA 5092",
    "addr:housenumber":"128",
    "addr:postcode":"5092",
    "addr:street":"Tea Tree Plaza",
    "iso:country":"AU",
    "sg:address":"Shp 128 Tea Tree Plaza",
    "sg:city":"Modbury",
    "sg:classifiers":[
        {
            "category":"Shopping",
            "subcategory":"Mobile Phones",
            "type":"Retail Goods"
        }
    ],
    "sg:phone":"+61 8 8418 0302",
    "sg:postcode":"5092",
    "sg:province":"SA",
    "sg:tags":[
        "telephone",
        "accessory"
    ],
    "wof:name":"Vodafone",
    "wof:placetype":"venue"
},
  "geometry": {"coordinates":[138.69236755399999,-34.8331794739],"type":"Point"}
}