{
  "type": "Feature",
  "properties": {
    "iso:country":"AU",
    "sg:address":"152 Baroona Rd",
    "sg:city":"Rosalie",
    "sg:classifiers":[
        {
            "category":"Retail",
            "subcategory":"Repair Shop",
            "type":"Services"
        }
    ],
    "sg:phone":"+61 7 3367 0479",
    "sg:postcode":"4064",
    "sg:province":"QLD",
    "sg:tags":[
        "mending",
        "clothing",
        "alteration"
    ],
    "wof:name":"See Drycleaners",
    "wof:placetype":"venue"
},
  "geometry": {"coordinates":[152.99757385300001,-27.4663257599],"type":"Point"}
}