{
  "type": "Feature",
  "properties": {
    "iso:country":"AU",
    "sg:address":"Ste3/ 4 Newlyn St",
    "sg:city":"Caulfield",
    "sg:classifiers":[
        {
            "category":"Social Services",
            "subcategory":"Job Training",
            "type":"Services"
        }
    ],
    "sg:phone":"+61 424 073 983",
    "sg:postcode":"3162",
    "sg:province":"VIC",
    "sg:tags":[
        "sport"
    ],
    "wof:name":"Optimum Performance",
    "wof:placetype":"venue"
},
  "geometry": {"coordinates":[145.02919006400001,-37.8829040527],"type":"Point"}
}