{
  "type": "Feature",
  "properties": {
    "addr:full":"Shop 15/ 564 Esplanade Urangan QLD 4655",
    "addr:housenumber":"shop 15 / 564",
    "addr:postcode":"4655",
    "addr:street":"Esplanade",
    "iso:country":"AU",
    "sg:address":"Shop 15/ 564",
    "sg:city":"Esplanade Urangan",
    "sg:classifiers":[
        {
            "category":"Personal",
            "subcategory":"Beauty Salon",
            "type":"Services"
        }
    ],
    "sg:phone":"+61 7 4128 9144",
    "sg:postcode":"4655",
    "sg:province":"QLD",
    "sg:tags":[
        "hairdresser"
    ],
    "wof:name":"Hervey Bay HairWaves",
    "wof:placetype":"venue"
},
  "geometry": {"coordinates":[152.80862400000001,-25.259825],"type":"Point"}
}