{
  "type": "Feature",
  "properties": {
    "addr:full":"37 Twelfth Ave Gawler South SA 5118",
    "addr:housenumber":"37",
    "addr:postcode":"5118",
    "addr:street":"Twelfth Ave",
    "iso:country":"AU",
    "sg:address":"37 Twelfth Ave",
    "sg:city":"Gawler South",
    "sg:classifiers":[
        {
            "category":"Social Services",
            "subcategory":"Child Care",
            "type":"Services"
        }
    ],
    "sg:phone":"+61 8 8523 1488",
    "sg:postcode":"5118",
    "sg:province":"SA",
    "sg:website":"http://www.childcare.com.au",
    "wof:name":"ABC Gawler South",
    "wof:placetype":"venue"
},
  "geometry": {"coordinates":[138.74305699999999,-34.605801],"type":"Point"}
}