{
  "type": "Feature",
  "properties": {
    "addr:full":"46 Cook St Flinders VIC 3929",
    "addr:housenumber":"46",
    "addr:postcode":"3929",
    "addr:street":"Cook St",
    "iso:country":"AU",
    "sg:address":"46 Cook St",
    "sg:city":"Flinders",
    "sg:classifiers":[
        {
            "category":"Home & Garden",
            "subcategory":"Garden Supply",
            "type":"Retail Goods"
        }
    ],
    "sg:phone":"+61 3 5989 0110",
    "sg:postcode":"3929",
    "sg:province":"VIC",
    "sg:tags":[
        "equipment"
    ],
    "wof:name":"Bloomings Of Flinders",
    "wof:placetype":"venue"
},
  "geometry": {"coordinates":[145.01724243199999,-38.4736976624],"type":"Point"}
}