{
  "type": "Feature",
  "properties": {
    "iso:country":"AU",
    "sg:address":"Unit 6, 3 Collingwood St",
    "sg:city":"Osborne Park",
    "sg:classifiers":[
        {
            "category":"Manufacturing",
            "subcategory":"Paper Products",
            "type":"Manufacturing & Wholesale Goods"
        }
    ],
    "sg:phone":"+61 8 9242 7271",
    "sg:postcode":"6017",
    "sg:province":"WA",
    "sg:tags":[
        "box",
        "fibre",
        "carton",
        "cardboard"
    ],
    "wof:name":"Pak Wholesalers",
    "wof:placetype":"venue"
},
  "geometry": {"coordinates":[115.816680908,-31.9042854309],"type":"Point"}
}