{
  "type": "Feature",
  "properties": {
    "addr:full":"774 Glenhuntly Rd Caulfield VIC 3162",
    "addr:housenumber":"774",
    "addr:postcode":"3162",
    "addr:street":"Glenhuntly Rd",
    "iso:country":"AU",
    "sg:address":"774 Glenhuntly Rd",
    "sg:city":"Caulfield",
    "sg:classifiers":[
        {
            "category":"Communications",
            "subcategory":"Film & Video Production",
            "type":"Services"
        }
    ],
    "sg:phone":"+61 3 9532 8501",
    "sg:postcode":"3162",
    "sg:province":"VIC",
    "sg:tags":[
        "dvd",
        "library"
    ],
    "wof:name":"Video Busters",
    "wof:placetype":"venue"
},
  "geometry": {"coordinates":[145.021408081,-37.8869361877],"type":"Point"}
}