{
  "type": "Feature",
  "properties": {
    "addr:full":"15 Brandl St Eight Mile Plains QLD 4113",
    "addr:housenumber":"15",
    "addr:postcode":"4113",
    "addr:street":"Brandl St",
    "iso:country":"AU",
    "sg:address":"15 Brandl St",
    "sg:city":"Eight Mile Plains",
    "sg:classifiers":[
        {
            "category":"Communications",
            "type":"Services"
        }
    ],
    "sg:phone":"+61 7 3279 3212",
    "sg:postcode":"4113",
    "sg:province":"QLD",
    "sg:tags":[
        "equipment",
        "radio"
    ],
    "wof:name":"A E M S Queensland",
    "wof:placetype":"venue"
},
  "geometry": {"coordinates":[153.097946167,-27.5813045502],"type":"Point"}
}