{
  "type": "Feature",
  "properties": {
    "addr:full":"43 Mont Victor Rd Kew VIC 3101",
    "addr:housenumber":"43",
    "addr:postcode":"3101",
    "addr:street":"Mont Victor Rd",
    "iso:country":"AU",
    "sg:address":"43 Mont Victor Rd",
    "sg:city":"Kew",
    "sg:classifiers":[
        {
            "category":"Education",
            "subcategory":"Music School",
            "type":"Public Place"
        }
    ],
    "sg:phone":"+61 3 9817 4221",
    "sg:postcode":"3101",
    "sg:province":"VIC",
    "sg:tags":[
        "choir",
        "bands",
        "orchestra"
    ],
    "wof:name":"Melbourne Musicians",
    "wof:placetype":"venue"
},
  "geometry": {"coordinates":[145.05792236299999,-37.8064041138],"type":"Point"}
}