{
  "type": "Feature",
  "properties": {
    "iso:country":"AU",
    "sg:address":"3 Evelyn St",
    "sg:city":"Toowoomba",
    "sg:classifiers":[
        {
            "category":"Social Services",
            "subcategory":"Adult Care",
            "type":"Services"
        }
    ],
    "sg:phone":"+61 407 790 703",
    "sg:postcode":"4350",
    "sg:province":"QLD",
    "sg:tags":[
        "towing"
    ],
    "wof:name":"Russell Day Towing",
    "wof:placetype":"venue"
},
  "geometry": {"coordinates":[151.95564300000001,-27.553099],"type":"Point"}
}