{
  "type": "Feature",
  "properties": {
    "iso:country":"AU",
    "sg:address":"36 Allen St",
    "sg:city":"South Townsville",
    "sg:classifiers":[
        {
            "category":"Retail",
            "subcategory":"Auto Repair",
            "type":"Services"
        }
    ],
    "sg:phone":"+61 7 4771 3630",
    "sg:postcode":"4810",
    "sg:province":"QLD",
    "sg:tags":[
        "repairer",
        "motor",
        "engineer"
    ],
    "wof:name":"Maz Serv",
    "wof:placetype":"venue"
},
  "geometry": {"coordinates":[146.826523,-19.264133],"type":"Point"}
}