{
  "type": "Feature",
  "properties": {
    "addr:full":"280 Crown St Darlinghurst NSW 2010",
    "addr:housenumber":"280",
    "addr:postcode":"2010",
    "addr:street":"Crown St",
    "iso:country":"AU",
    "sg:address":"280 Crown St",
    "sg:city":"Darlinghurst",
    "sg:classifiers":[
        {
            "category":"Real Estate",
            "subcategory":"Real Estate Agent",
            "type":"Services"
        }
    ],
    "sg:phone":"+61 2 9331 2991",
    "sg:postcode":"2010",
    "sg:province":"NSW",
    "wof:name":"Oxford Real Estate Pty Ltd",
    "wof:placetype":"venue"
},
  "geometry": {"coordinates":[151.215240478,-33.8798866272],"type":"Point"}
}