{
  "type": "Feature",
  "properties": {
    "iso:country":"AU",
    "sg:address":"City Physiotherapy 123 Chruch St",
    "sg:city":"Wollongong",
    "sg:classifiers":[
        {
            "category":"Health Services",
            "subcategory":"Health Practitioner",
            "type":"Services"
        }
    ],
    "sg:phone":"+61 2 4226 1015",
    "sg:postcode":"2500",
    "sg:province":"NSW",
    "sg:tags":[
        "physiotherapist"
    ],
    "wof:name":"Parle Phillip",
    "wof:placetype":"venue"
},
  "geometry": {"coordinates":[150.894699,-34.428822],"type":"Point"}
}