{
  "type": "Feature",
  "properties": {
    "addr:full":"160 McKinnon Rd McKinnon VIC 3204",
    "addr:housenumber":"160",
    "addr:postcode":"3204",
    "addr:street":"Mckinnon Rd",
    "iso:country":"AU",
    "sg:address":"160 McKinnon Rd",
    "sg:city":"McKinnon",
    "sg:classifiers":[
        {
            "category":"Health Services",
            "subcategory":"Dentist",
            "type":"Services"
        }
    ],
    "sg:phone":"+61 3 9576 7588",
    "sg:postcode":"3204",
    "sg:province":"VIC",
    "wof:name":"Rose Adam Dr.",
    "wof:placetype":"venue"
},
  "geometry": {"coordinates":[145.038422,-37.91119],"type":"Point"}
}