{
  "type": "Feature",
  "properties": {
    "addr:full":"PO Box 1005 Shepparton VIC 3632",
    "addr:postcode":"3632",
    "iso:country":"AU",
    "sg:address":"PO Box 1005",
    "sg:city":"Shepparton",
    "sg:classifiers":[
        {
            "category":"Industrial Area",
            "type":"Public Place"
        }
    ],
    "sg:phone":"+61 412 746 771",
    "sg:postcode":"3632",
    "sg:province":"VIC",
    "sg:tags":[
        "rural",
        "shed"
    ],
    "wof:name":"Sheds & Shade",
    "wof:placetype":"venue"
},
  "geometry": {"coordinates":[145.399291992,-36.3811683655],"type":"Point"}
}