{
  "type": "Feature",
  "properties": {
    "addr:full":"221a Bay St Port Melbourne VIC 3207",
    "addr:housenumber":"221a",
    "addr:postcode":"3207",
    "addr:street":"Bay St",
    "iso:country":"AU",
    "sg:address":"221a Bay St",
    "sg:city":"Port Melbourne",
    "sg:classifiers":[
        {
            "category":"Banks & Credit Unions",
            "subcategory":"Financial Services",
            "type":"Services"
        }
    ],
    "sg:phone":"+61 3 9646 8399",
    "sg:postcode":"3207",
    "sg:province":"VIC",
    "sg:tags":[
        "financier"
    ],
    "wof:name":"Film Finance Corporation Australia Limited",
    "wof:placetype":"venue"
},
  "geometry": {"coordinates":[144.94229100000001,-37.838432],"type":"Point"}
}