{
  "type": "Feature",
  "properties": {
    "addr:full":"220 Waterdale Rd Ivanhoe VIC 3079",
    "addr:housenumber":"220",
    "addr:postcode":"3079",
    "addr:street":"Waterdale Rd",
    "iso:country":"AU",
    "sg:address":"220 Waterdale Rd",
    "sg:city":"Ivanhoe",
    "sg:classifiers":[
        {
            "category":"Food & Beverages",
            "subcategory":"Liquor & Beverages",
            "type":"Retail Goods"
        }
    ],
    "sg:phone":"+61 3 9499 1003",
    "sg:postcode":"3079",
    "sg:province":"VIC",
    "sg:tags":[
        "store"
    ],
    "wof:name":"Swansons Fine Wines & Gourmet Foods",
    "wof:placetype":"venue"
},
  "geometry": {"coordinates":[145.04434204099999,-37.7594909668],"type":"Point"}
}