{
  "type": "Feature",
  "properties": {
    "addr:full":"18 High St Gawler SA 5118",
    "addr:housenumber":"18",
    "addr:postcode":"5118",
    "addr:street":"High St",
    "iso:country":"AU",
    "sg:address":"18 High St",
    "sg:city":"Gawler",
    "sg:classifiers":[
        {
            "category":"Retail",
            "subcategory":"Auto Repair",
            "type":"Services"
        }
    ],
    "sg:phone":"+61 8 8522 4922",
    "sg:postcode":"5118",
    "sg:province":"SA",
    "sg:tags":[
        "repairer",
        "motor",
        "engineer"
    ],
    "wof:name":"Paul Stevens Motor Repairs",
    "wof:placetype":"venue"
},
  "geometry": {"coordinates":[138.75007600000001,-34.597534],"type":"Point"}
}