{
  "type": "Feature",
  "properties": {
    "addr:full":"17 Lawrence St Beaufort VIC 3373",
    "addr:housenumber":"17",
    "addr:postcode":"3373",
    "addr:street":"Lawrence St",
    "iso:country":"AU",
    "sg:address":"17 Lawrence St",
    "sg:city":"Beaufort",
    "sg:classifiers":[
        {
            "category":"Banks & Credit Unions",
            "subcategory":"Bank",
            "type":"Services"
        }
    ],
    "sg:phone":"+61 3 5349 2322",
    "sg:postcode":"3373",
    "sg:province":"VIC",
    "wof:name":"Bendigo Community Bank",
    "wof:placetype":"venue"
},
  "geometry": {"coordinates":[143.383468628,-37.4333152771],"type":"Point"}
}