{
  "type": "Feature",
  "properties": {
    "addr:full":"35 Assembly Drv Tullamarine VIC 3043",
    "addr:housenumber":"35",
    "addr:postcode":"3043",
    "addr:street":"Assembly Drv",
    "iso:country":"AU",
    "sg:address":"35 Assembly Drv",
    "sg:city":"Tullamarine",
    "sg:classifiers":[
        {
            "category":"Recreation",
            "type":"Entertainment"
        }
    ],
    "sg:phone":"+61 3 9338 1664",
    "sg:postcode":"3043",
    "sg:province":"VIC",
    "sg:tags":[
        "hire",
        "tour",
        "motor",
        "cycle"
    ],
    "wof:name":"Imported Tyre Wholesalers",
    "wof:placetype":"venue"
},
  "geometry": {"coordinates":[144.863082886,-37.7100524902],"type":"Point"}
}