{
  "type": "Feature",
  "properties": {
    "addr:full":"265 Avoca St Haberfield NSW 2045",
    "addr:housenumber":"265",
    "addr:postcode":"2045",
    "addr:street":"Avoca St",
    "iso:country":"AU",
    "sg:address":"265 Avoca St",
    "sg:city":"Haberfield",
    "sg:classifiers":[
        {
            "category":"Autos & Motor Vehicles",
            "subcategory":"Automobile Sales",
            "type":"Retail Goods"
        }
    ],
    "sg:phone":"+61 2 9797 7311",
    "sg:postcode":"2045",
    "sg:province":"NSW",
    "sg:tags":[
        "car",
        "new"
    ],
    "wof:name":"Rick Damelian Suzuki",
    "wof:placetype":"venue"
},
  "geometry": {"coordinates":[151.13926699999999,-33.881031],"type":"Point"}
}