{
  "type": "Feature",
  "properties": {
    "addr:full":"5/ 214 Waterworks Rd Ashgrove QLD 4060",
    "addr:housenumber":"/ 214",
    "addr:postcode":"4060",
    "addr:street":"Waterworks Rd",
    "iso:country":"AU",
    "sg:address":"5/ 214 Waterworks Rd",
    "sg:city":"Ashgrove",
    "sg:classifiers":[
        {
            "category":"Professional",
            "subcategory":"Accounting & Tax Preparation",
            "type":"Services"
        }
    ],
    "sg:phone":"+61 7 3366 5008",
    "sg:postcode":"4060",
    "sg:province":"QLD",
    "sg:tags":[
        "consultant",
        "taxation"
    ],
    "wof:name":"Colin A. Edwards & Associates",
    "wof:placetype":"venue"
},
  "geometry": {"coordinates":[152.99375915499999,-27.4455604553],"type":"Point"}
}