{
  "type": "Feature",
  "properties": {
    "iso:country":"AU",
    "sg:address":"88 Roslyn St",
    "sg:city":"Ashbury",
    "sg:classifiers":[
        {
            "category":"Real Estate",
            "subcategory":"Architect",
            "type":"Services"
        }
    ],
    "sg:phone":"+61 412 555 935",
    "sg:postcode":"2193",
    "sg:province":"NSW",
    "wof:name":"Doyle John Hamilton",
    "wof:placetype":"venue"
},
  "geometry": {"coordinates":[151.111923,-33.899101],"type":"Point"}
}