{
  "type": "Feature",
  "properties": {
    "iso:country":"AU",
    "sg:address":"Frome Rd",
    "sg:city":"Adelaide",
    "sg:classifiers":[
        {
            "category":"Education",
            "subcategory":"University",
            "type":"Public Place"
        }
    ],
    "sg:phone":"+61 8 8303 4299",
    "sg:postcode":"5000",
    "sg:province":"SA",
    "sg:tags":[
        "college",
        "tertiary"
    ],
    "wof:name":"National Centre For Petroleum Geology & Geophysics",
    "wof:placetype":"venue"
},
  "geometry": {"coordinates":[138.60780334500001,-34.9211273193],"type":"Point"}
}