{
  "type": "Feature",
  "properties": {
    "addr:full":"29 Cadell St Wentworth VIC 2648",
    "addr:housenumber":"29",
    "addr:postcode":"2648",
    "addr:street":"Cadell St",
    "iso:country":"AU",
    "sg:address":"29 Cadell St",
    "sg:city":"Wentworth",
    "sg:classifiers":[
        {
            "category":"Real Estate",
            "subcategory":"Real Estate Agent",
            "type":"Services"
        }
    ],
    "sg:phone":"+61 428 257 470",
    "sg:postcode":"2648",
    "sg:province":"VIC",
    "sg:tags":[
        "handyman's",
        "equipment",
        "hire",
        "builders",
        "contractor"
    ],
    "wof:name":"Murray Darling Digger Hire",
    "wof:placetype":"venue"
},
  "geometry": {"coordinates":[141.91645800000001,-34.110638],"type":"Point"}
}