{
  "type": "Feature",
  "properties": {
    "addr:full":"Unit 2, 47 Pinjarra Rd Mandurah WA 6210",
    "addr:housenumber":"47",
    "addr:postcode":"6210",
    "addr:street":"Pinjarra Rd",
    "iso:country":"AU",
    "sg:address":"Unit 2, 47 Pinjarra Rd",
    "sg:city":"Mandurah",
    "sg:classifiers":[
        {
            "category":"Shopping",
            "subcategory":"Computers & Home Electronics",
            "type":"Retail Goods"
        }
    ],
    "sg:phone":"+61 8 9581 5057",
    "sg:postcode":"6210",
    "sg:province":"WA",
    "sg:tags":[
        "small",
        "equipment",
        "business"
    ],
    "wof:name":"Baycom Technologies",
    "wof:placetype":"venue"
},
  "geometry": {"coordinates":[115.772713,-32.546894],"type":"Point"}
}