{
  "type": "Feature",
  "properties": {
    "addr:full":"Kingfisher Ave Coleambally NSW 2707",
    "addr:postcode":"2707",
    "addr:street":"Kingfisher Ave",
    "iso:country":"AU",
    "sg:address":"Kingfisher Ave",
    "sg:city":"Coleambally",
    "sg:classifiers":[
        {
            "category":"Health Services",
            "subcategory":"Hospital",
            "type":"Services"
        }
    ],
    "sg:phone":"+61 13 12 33",
    "sg:postcode":"2707",
    "sg:province":"NSW",
    "sg:tags":[
        "ambulance"
    ],
    "wof:name":"Ambulance Service Of NSW",
    "wof:placetype":"venue"
},
  "geometry": {"coordinates":[145.887481689,-34.804889679],"type":"Point"}
}