{
  "type": "Feature",
  "properties": {
    "addr:full":"Pitt Town Bottoms Rd Pitt Town NSW 2756",
    "addr:postcode":"2756",
    "addr:street":"Bottoms Rd",
    "iso:country":"AU",
    "sg:address":"Pitt Town Bottoms Rd",
    "sg:city":"Pitt Town",
    "sg:classifiers":[
        {
            "category":"Manufacturing",
            "subcategory":"Tools & Machinery",
            "type":"Manufacturing & Wholesale Goods"
        }
    ],
    "sg:phone":"+61 408 242 595",
    "sg:postcode":"2756",
    "sg:province":"NSW",
    "sg:tags":[
        "earth",
        "excavating",
        "moving",
        "equipment"
    ],
    "wof:name":"Rod Hanckel Earth Drilling",
    "wof:placetype":"venue"
},
  "geometry": {"coordinates":[150.85627746599999,-33.5735816956],"type":"Point"}
}