{
  "type": "Feature",
  "properties": {
    "addr:full":"4 Princess St Warrnambool VIC 3280",
    "addr:housenumber":"4",
    "addr:postcode":"3280",
    "addr:street":"Princess St",
    "iso:country":"AU",
    "sg:address":"4 Princess St",
    "sg:city":"Warrnambool",
    "sg:classifiers":[
        {
            "category":"Health Services",
            "subcategory":"Doctor",
            "type":"Services"
        }
    ],
    "sg:phone":"+61 3 5561 0700",
    "sg:postcode":"3280",
    "sg:province":"VIC",
    "sg:tags":[
        "medical",
        "practitioner"
    ],
    "wof:name":"Grave Murray Dr",
    "wof:placetype":"venue"
},
  "geometry": {"coordinates":[142.4896698,-38.3791160583],"type":"Point"}
}