{
  "type": "Feature",
  "properties": {
    "addr:full":"1 Redbank Rd Wagga Wagga NSW 2650",
    "addr:housenumber":"1",
    "addr:postcode":"2650",
    "addr:street":"Redbank Rd",
    "iso:country":"AU",
    "sg:address":"1 Redbank Rd",
    "sg:city":"Wagga Wagga",
    "sg:classifiers":[
        {
            "category":"Professional",
            "subcategory":"Business Services",
            "type":"Services"
        }
    ],
    "sg:phone":"+61 2 6971 1680",
    "sg:postcode":"2650",
    "sg:province":"NSW",
    "sg:tags":[
        "livestock",
        "transport"
    ],
    "wof:name":"MLT Equine Transport",
    "wof:placetype":"venue"
},
  "geometry": {"coordinates":[147.337722778,-35.143371582],"type":"Point"}
}