{
  "type": "Feature",
  "properties": {
    "iso:country":"AU",
    "sg:address":"Kilcunda Rd",
    "sg:city":"Bena",
    "sg:classifiers":[
        {
            "category":"Farming",
            "subcategory":"Farm",
            "type":"Manufacturing & Wholesale Goods"
        }
    ],
    "sg:phone":"+61 3 5657 2241",
    "sg:postcode":"3946",
    "sg:province":"VIC",
    "sg:tags":[
        "farmer"
    ],
    "wof:name":"Pratt Joan",
    "wof:placetype":"venue"
},
  "geometry": {"coordinates":[145.714752197,-38.4233207703],"type":"Point"}
}