{
  "type": "Feature",
  "properties": {
    "addr:full":"2/ 97 Belair Rd Torrens Park SA 5062",
    "addr:housenumber":"/ 97",
    "addr:postcode":"5062",
    "addr:street":"Belair Rd",
    "iso:country":"AU",
    "sg:address":"2/ 97 Belair Rd",
    "sg:city":"Torrens Park",
    "sg:classifiers":[
        {
            "category":"Professional",
            "subcategory":"Accounting & Tax Preparation",
            "type":"Services"
        }
    ],
    "sg:phone":"+61 8 8373 1032",
    "sg:postcode":"5062",
    "sg:province":"SA",
    "sg:tags":[
        "consultant",
        "taxation"
    ],
    "wof:name":"Cunningham Yap & Hardman",
    "wof:placetype":"venue"
},
  "geometry": {"coordinates":[138.61029052699999,-34.9943733215],"type":"Point"}
}