{
  "type": "Feature",
  "properties": {
    "addr:full":"Shop 8B, 4 Nicholson St Abbotsford VIC 3067",
    "addr:housenumber":"shop 8b 4",
    "addr:postcode":"3067",
    "addr:street":"Nicholson St",
    "iso:country":"AU",
    "sg:address":"Shop 8B, 4 Nicholson St",
    "sg:city":"Abbotsford",
    "sg:classifiers":[
        {
            "category":"Banks & Credit Unions",
            "subcategory":"Investment Brokerage",
            "type":"Services"
        }
    ],
    "sg:phone":"+61 3 9427 9744",
    "sg:postcode":"3067",
    "sg:province":"VIC",
    "sg:tags":[
        "debt",
        "collection"
    ],
    "wof:name":"Elwyn Delves & Associates",
    "wof:placetype":"venue"
},
  "geometry": {"coordinates":[144.99621582,-37.8095016479],"type":"Point"}
}