{
  "type": "Feature",
  "properties": {
    "iso:country":"AU",
    "sg:address":"73 Pickering St",
    "sg:city":"Enoggera",
    "sg:classifiers":[
        {
            "category":"Retail",
            "subcategory":"Auto Repair",
            "type":"Services"
        }
    ],
    "sg:phone":"+61 7 3354 3899",
    "sg:postcode":"4051",
    "sg:province":"QLD",
    "sg:tags":[
        "clutch",
        "brake"
    ],
    "wof:name":"Northside Clutch & Brake Supplies",
    "wof:placetype":"venue"
},
  "geometry": {"coordinates":[152.99472045900001,-27.4194412231],"type":"Point"}
}