{
  "type": "Feature",
  "properties": {
    "addr:full":"Elanora Drv Rockingham WA 6168",
    "addr:postcode":"6168",
    "addr:street":"Elanora Drv",
    "iso:country":"AU",
    "sg:address":"Elanora Drv",
    "sg:city":"Rockingham",
    "sg:classifiers":[
        {
            "category":"Health Services",
            "subcategory":"Doctor",
            "type":"Services"
        }
    ],
    "sg:phone":"+61 8 9527 6622",
    "sg:postcode":"6168",
    "sg:province":"WA",
    "sg:tags":[
        "medical",
        "practitioner"
    ],
    "wof:name":"Rockingham Medical Imaging",
    "wof:placetype":"venue"
},
  "geometry": {"coordinates":[115.762878,-32.294498],"type":"Point"}
}