{
  "type": "Feature",
  "properties": {
    "addr:full":"Princes Hwy Narooma NSW 2546",
    "addr:postcode":"2546",
    "addr:street":"Princes Hwy",
    "iso:country":"AU",
    "sg:address":"Princes Hwy",
    "sg:city":"Narooma",
    "sg:classifiers":[
        {
            "category":"Manufacturing",
            "subcategory":"Lumber",
            "type":"Manufacturing & Wholesale Goods"
        }
    ],
    "sg:phone":"+61 2 4476 7908",
    "sg:postcode":"2546",
    "sg:province":"NSW",
    "sg:tags":[
        "sawmillers"
    ],
    "wof:name":"Davis & Herbert",
    "wof:placetype":"venue"
},
  "geometry": {"coordinates":[150.132354736,-36.2188682556],"type":"Point"}
}