{
  "type": "Feature",
  "properties": {
    "addr:full":"1/2- 6 Yannis Crt Springvale VIC 3171",
    "addr:housenumber":"/ 2 6",
    "addr:postcode":"3171",
    "addr:street":"Yannis Crt",
    "iso:country":"AU",
    "sg:address":"1/2- 6 Yannis Crt",
    "sg:city":"Springvale",
    "sg:classifiers":[
        {
            "category":"Home & Garden",
            "subcategory":"Carpets & Floor Coverings",
            "type":"Retail Goods"
        }
    ],
    "sg:phone":"+61 3 9558 5783",
    "sg:postcode":"3171",
    "sg:province":"VIC",
    "sg:tags":[
        "tile",
        "wall"
    ],
    "wof:name":"Superb Tiles",
    "wof:placetype":"venue"
},
  "geometry": {"coordinates":[145.141677856,-37.9442977905],"type":"Point"}
}