{
  "type": "Feature",
  "properties": {
    "addr:full":"Richardson Pl Roxby Downs SA 5725",
    "addr:postcode":"5725",
    "addr:street":"Pl",
    "iso:country":"AU",
    "sg:address":"Richardson Pl",
    "sg:city":"Roxby Downs",
    "sg:classifiers":[
        {
            "category":"Government",
            "subcategory":"Post Office",
            "type":"Public Place"
        }
    ],
    "sg:phone":"+61 8 8671 0130",
    "sg:postcode":"5725",
    "sg:province":"SA",
    "sg:tags":[
        "postal"
    ],
    "wof:name":"Australia Post",
    "wof:placetype":"venue"
},
  "geometry": {"coordinates":[136.89532470699999,-30.5621833801],"type":"Point"}
}