{
  "type": "Feature",
  "properties": {
    "addr:full":"18 Elder St Alice Springs NT 0870",
    "addr:housenumber":"18",
    "addr:postcode":"nt 0870",
    "addr:street":"Elder St",
    "iso:country":"AU",
    "sg:address":"18 Elder St",
    "sg:city":"Alice Springs",
    "sg:classifiers":[
        {
            "category":"Professional",
            "subcategory":"Printing & Photocopies",
            "type":"Services"
        }
    ],
    "sg:phone":"+61 8 8952 7400",
    "sg:postcode":"0870",
    "sg:province":"NT",
    "sg:tags":[
        "photocopier"
    ],
    "wof:name":"Red Centre Office Technology",
    "wof:placetype":"venue"
},
  "geometry": {"coordinates":[133.87031555199999,-23.6980895996],"type":"Point"}
}