{
  "type": "Feature",
  "properties": {
    "addr:full":"Shop 10/ 61 Northborne Ave Canberra ACT 2600",
    "addr:housenumber":"shop 10 / 61",
    "addr:postcode":"2600",
    "addr:street":"Northborne Ave",
    "iso:country":"AU",
    "sg:address":"Shop 10/ 61 Northborne Ave",
    "sg:city":"Canberra",
    "sg:classifiers":[
        {
            "category":"Retail",
            "subcategory":"Auto Rental",
            "type":"Services"
        }
    ],
    "sg:phone":"+61 411 460 993",
    "sg:postcode":"2600",
    "sg:province":"ACT",
    "sg:tags":[
        "chauffeur",
        "car",
        "hire",
        "driven",
        "limousine"
    ],
    "wof:name":"Xavier Winston Exotic Car Hire",
    "wof:placetype":"venue"
},
  "geometry": {"coordinates":[149.128814697,-35.2785491943],"type":"Point"}
}