{
  "type": "Feature",
  "properties": {
    "addr:full":"Lot 1000 Orkney Rd Karratha WA 6714",
    "addr:housenumber":"1000",
    "addr:postcode":"6714",
    "addr:street":"Orkney Rd",
    "iso:country":"AU",
    "sg:address":"Lot 1000 Orkney Rd",
    "sg:city":"Karratha",
    "sg:classifiers":[
        {
            "category":"Social Services",
            "subcategory":"Child Care",
            "type":"Services"
        }
    ],
    "sg:phone":"+61 8 9185 5966",
    "sg:postcode":"6714",
    "sg:province":"WA",
    "sg:tags":[
        "fleet",
        "management"
    ],
    "wof:name":"Corefleet",
    "wof:placetype":"venue"
},
  "geometry": {"coordinates":[116.859718323,-20.7730007172],"type":"Point"}
}