{
  "type": "Feature",
  "properties": {
    "addr:full":"12 Davidson Pde Cremorne NSW 2090",
    "addr:housenumber":"12",
    "addr:postcode":"2090",
    "addr:street":"Davidson Pde",
    "iso:country":"AU",
    "sg:address":"12 Davidson Pde",
    "sg:city":"Cremorne",
    "sg:classifiers":[
        {
            "category":"Professional",
            "subcategory":"Employment Agencies",
            "type":"Services"
        }
    ],
    "sg:phone":"+61 2 9908 7711",
    "sg:postcode":"2090",
    "sg:province":"NSW",
    "sg:tags":[
        "occupational",
        "therapist"
    ],
    "wof:name":"Evaluate",
    "wof:placetype":"venue"
},
  "geometry": {"coordinates":[151.23150634800001,-33.8217582703],"type":"Point"}
}