{
  "type": "Feature",
  "properties": {
    "iso:country":"AU",
    "sg:address":"50 Gulfview Rd",
    "sg:city":"Christies Beach",
    "sg:classifiers":[
        {
            "category":"Health Services",
            "subcategory":"Nursing And Care Facility",
            "type":"Services"
        }
    ],
    "sg:phone":"+61 8 8384 3133",
    "sg:postcode":"5165",
    "sg:province":"SA",
    "sg:tags":[
        "home"
    ],
    "wof:name":"Christies Beach Residential Care Services",
    "wof:placetype":"venue"
},
  "geometry": {"coordinates":[138.47654724099999,-35.131023407],"type":"Point"}
}