{
  "type": "Feature",
  "properties": {
    "addr:full":"517 Alderley St Toowoomba QLD 4350",
    "addr:housenumber":"517",
    "addr:postcode":"4350",
    "addr:street":"Alderley St",
    "iso:country":"AU",
    "sg:address":"517 Alderley St",
    "sg:city":"Toowoomba",
    "sg:classifiers":[
        {
            "category":"Retail",
            "subcategory":"Storage",
            "type":"Services"
        }
    ],
    "sg:phone":"+61 7 4638 7333",
    "sg:postcode":"4350",
    "sg:province":"QLD",
    "sg:tags":[
        "removal",
        "furniture"
    ],
    "wof:name":"Economy Self Storage Sheds",
    "wof:placetype":"venue"
},
  "geometry": {"coordinates":[151.92219499999999,-27.580919],"type":"Point"}
}