{
  "type": "Feature",
  "properties": {
    "addr:full":"80 Hanson Rd Gladstone QLD 4680",
    "addr:housenumber":"80",
    "addr:postcode":"4680",
    "addr:street":"Hanson Rd",
    "iso:country":"AU",
    "sg:address":"80 Hanson Rd",
    "sg:city":"Gladstone",
    "sg:classifiers":[
        {
            "category":"Home & Garden",
            "subcategory":"Hardware",
            "type":"Retail Goods"
        }
    ],
    "sg:phone":"+61 7 4972 6999",
    "sg:postcode":"4680",
    "sg:province":"QLD",
    "sg:tags":[
        "plumber",
        "supply"
    ],
    "wof:name":"Tradelink Plumbing Centres",
    "wof:placetype":"venue"
},
  "geometry": {"coordinates":[151.244216919,-23.8401489258],"type":"Point"}
}