{
  "type": "Feature",
  "properties": {
    "iso:country":"AU",
    "sg:address":"38 Oke St",
    "sg:city":"Ouyen",
    "sg:classifiers":[
        {
            "category":"Shopping",
            "subcategory":"Clothing, Apparel, & Fashions",
            "type":"Retail Goods"
        }
    ],
    "sg:phone":"+61 3 5092 1372",
    "sg:postcode":"3490",
    "sg:province":"VIC",
    "sg:tags":[
        "menswear"
    ],
    "wof:name":"Country Clothing & Furniture",
    "wof:placetype":"venue"
},
  "geometry": {"coordinates":[142.31500244099999,-35.0710868835],"type":"Point"}
}