{
  "type": "Feature",
  "properties": {
    "addr:full":"18 Creswood Pl Warners Bay NSW 2282",
    "addr:housenumber":"18",
    "addr:postcode":"2282",
    "addr:street":"Creswood Pl",
    "iso:country":"AU",
    "sg:address":"18 Creswood Pl",
    "sg:city":"Warners Bay",
    "sg:classifiers":[
        {
            "category":"Building & Trades",
            "subcategory":"Construction",
            "type":"Services"
        }
    ],
    "sg:phone":"+61 2 4947 1391",
    "sg:postcode":"2282",
    "sg:province":"NSW",
    "sg:tags":[
        "concrete",
        "paving"
    ],
    "wof:name":"Cessnock Concrete Specialist Pty Ltd",
    "wof:placetype":"venue"
},
  "geometry": {"coordinates":[151.65917968799999,-32.9766426086],"type":"Point"}
}