{
  "type": "Feature",
  "properties": {
    "iso:country":"AU",
    "sg:address":"18 Macpherson St",
    "sg:city":"Warriewood",
    "sg:classifiers":[
        {
            "category":"Cafe",
            "type":"Food & Drink"
        }
    ],
    "sg:phone":"+61 2 9997 8097",
    "sg:postcode":"2102",
    "sg:province":"NSW",
    "wof:name":"Cafe Belle Fleur",
    "wof:placetype":"venue"
},
  "geometry": {"coordinates":[151.297775,-33.689648],"type":"Point"}
}