{
  "type": "Feature",
  "properties": {
    "addr:full":"1 Johnson Rd Wyong NSW 2259",
    "addr:housenumber":"1",
    "addr:postcode":"2259",
    "addr:street":"Johnson Rd",
    "iso:country":"AU",
    "sg:address":"1 Johnson Rd",
    "sg:city":"Wyong",
    "sg:phone":"+61 2 4353 1287",
    "sg:postcode":"2259",
    "sg:province":"NSW",
    "sg:website":"http://www.formit.com.au",
    "wof:name":"Formit Services",
    "wof:placetype":"venue"
},
  "geometry": {"coordinates":[151.422363281,-33.2946357727],"type":"Point"}
}