{
  "type": "Feature",
  "properties": {
    "addr:full":"25 Trent St Glen Iris VIC 3146",
    "addr:housenumber":"25",
    "addr:postcode":"3146",
    "addr:street":"Trent St",
    "iso:country":"AU",
    "sg:address":"25 Trent St",
    "sg:city":"Glen Iris",
    "sg:classifiers":[
        {
            "category":"Wholesale",
            "subcategory":"Home Furnishings",
            "type":"Manufacturing & Wholesale Goods"
        }
    ],
    "sg:phone":"+61 3 9805 2811",
    "sg:postcode":"3146",
    "sg:province":"VIC",
    "wof:name":"Hoad Fabrics",
    "wof:placetype":"venue"
},
  "geometry": {"coordinates":[145.081176758,-37.8515472412],"type":"Point"}
}