{
  "type": "Feature",
  "properties": {
    "addr:full":"12 Bridge St Lidcombe NSW 2141",
    "addr:housenumber":"12",
    "addr:postcode":"2141",
    "addr:street":"Bridge St",
    "iso:country":"AU",
    "sg:address":"12 Bridge St",
    "sg:city":"Lidcombe",
    "sg:classifiers":[
        {
            "category":"Retail",
            "subcategory":"Event Space",
            "type":"Services"
        }
    ],
    "sg:phone":"+61 2 9649 9222",
    "sg:postcode":"2141",
    "sg:province":"NSW",
    "sg:tags":[
        "venue",
        "reception",
        "wedding"
    ],
    "wof:name":"Grand Westella",
    "wof:placetype":"venue"
},
  "geometry": {"coordinates":[151.04298400900001,-33.8639526367],"type":"Point"}
}