{
  "type": "Feature",
  "properties": {
    "addr:full":"1519 San Mateo Ave Mildura VIC 3500",
    "addr:housenumber":"1519",
    "addr:postcode":"3500",
    "addr:street":"San Mateo Ave",
    "iso:country":"AU",
    "sg:address":"1519 San Mateo Ave",
    "sg:city":"Mildura",
    "sg:classifiers":[
        {
            "category":"Building & Trades",
            "subcategory":"Construction",
            "type":"Services"
        }
    ],
    "sg:phone":"+61 3 5023 5821",
    "sg:postcode":"3500",
    "sg:province":"VIC",
    "sg:tags":[
        "contractor"
    ],
    "wof:name":"P DE T Constructions",
    "wof:placetype":"venue"
},
  "geometry": {"coordinates":[142.13922119099999,-34.2125740051],"type":"Point"}
}