{
  "type": "Feature",
  "properties": {
    "addr:full":"182 Belmore Rd Balwyn VIC 3103",
    "addr:housenumber":"182",
    "addr:postcode":"3103",
    "addr:street":"Belmore Rd",
    "iso:country":"AU",
    "sg:address":"182 Belmore Rd",
    "sg:city":"Balwyn",
    "sg:classifiers":[
        {
            "category":"Professional",
            "subcategory":"Accounting & Tax Preparation",
            "type":"Services"
        }
    ],
    "sg:phone":"+61 3 9857 6261",
    "sg:postcode":"3103",
    "sg:province":"VIC",
    "sg:tags":[
        "consultant",
        "taxation"
    ],
    "wof:name":"Moylan Group",
    "wof:placetype":"venue"
},
  "geometry": {"coordinates":[145.083816528,-37.8036613464],"type":"Point"}
}