{
  "type": "Feature",
  "properties": {
    "addr:full":"69 Fullarton Rd Kent Town SA 5067",
    "addr:housenumber":"69",
    "addr:postcode":"5067",
    "addr:street":"Fullarton Rd",
    "iso:country":"AU",
    "sg:address":"69 Fullarton Rd",
    "sg:city":"Kent Town",
    "sg:classifiers":[
        {
            "category":"Banks & Credit Unions",
            "subcategory":"Investment Brokerage",
            "type":"Services"
        }
    ],
    "sg:phone":"+61 8 8334 2100",
    "sg:postcode":"5067",
    "sg:province":"SA",
    "sg:tags":[
        "finance",
        "broker"
    ],
    "wof:name":"Access Capital",
    "wof:placetype":"venue"
},
  "geometry": {"coordinates":[138.623336792,-34.9256744385],"type":"Point"}
}