{
  "type": "Feature",
  "properties": {
    "iso:country":"AU",
    "sg:address":"55 Church St",
    "sg:city":"Brighton",
    "sg:classifiers":[
        {
            "category":"Travel",
            "subcategory":"Travel Agent",
            "type":"Entertainment"
        }
    ],
    "sg:phone":"+61 3 9553 8722",
    "sg:postcode":"3186",
    "sg:province":"VIC",
    "sg:tags":[
        "consultant"
    ],
    "wof:name":"STA Travel",
    "wof:placetype":"venue"
},
  "geometry": {"coordinates":[144.994384766,-37.913646698],"type":"Point"}
}