{
  "type": "Feature",
  "properties": {
    "addr:full":"13-17 Searl Road Cronulla NSW 2230",
    "addr:housenumber":"13-17",
    "addr:postcode":"2230",
    "addr:street":"Searl Road",
    "iso:country":"AU",
    "sg:address":"13-17 Searl Road",
    "sg:city":"Cronulla",
    "sg:classifiers":[
        {
            "category":"Utilities",
            "subcategory":"Electric",
            "type":"Services"
        }
    ],
    "sg:phone":"+61 2 9523 2369",
    "sg:postcode":"2230",
    "sg:province":"NSW",
    "sg:tags":[
        "electrical",
        "contractor"
    ],
    "wof:name":"Ampelect Electrical Pty Ltd",
    "wof:placetype":"venue"
},
  "geometry": {"coordinates":[151.148895264,-34.05235672],"type":"Point"}
}