{
  "type": "Feature",
  "properties": {
    "addr:full":"47 Jervis Drv Illawong NSW 2234",
    "addr:housenumber":"47",
    "addr:postcode":"2234",
    "addr:street":"Jervis Drv",
    "iso:country":"AU",
    "sg:address":"47 Jervis Drv",
    "sg:city":"Illawong",
    "sg:classifiers":[
        {
            "category":"Building & Trades",
            "subcategory":"Construction",
            "type":"Services"
        }
    ],
    "sg:phone":"+61 2 9543 8701",
    "sg:postcode":"2234",
    "sg:province":"NSW",
    "sg:tags":[
        "concrete",
        "contractor"
    ],
    "wof:name":"All Class Home Improvements",
    "wof:placetype":"venue"
},
  "geometry": {"coordinates":[151.01649475100001,-34.0050125122],"type":"Point"}
}