{
  "type": "Feature",
  "properties": {
    "addr:full":"411 Railway Pde Henty NSW 2658",
    "addr:housenumber":"411",
    "addr:postcode":"2658",
    "addr:street":"Railway Pde",
    "iso:country":"AU",
    "sg:address":"411 Railway Pde",
    "sg:city":"Henty",
    "sg:classifiers":[
        {
            "category":"Professional",
            "type":"Services"
        }
    ],
    "sg:phone":"+61 2 6929 3500",
    "sg:postcode":"2658",
    "sg:province":"NSW",
    "sg:tags":[
        "transport"
    ],
    "wof:name":"Tantershel Transport Pty Ltd",
    "wof:placetype":"venue"
},
  "geometry": {"coordinates":[147.03590393100001,-35.5173416138],"type":"Point"}
}