{
  "type": "Feature",
  "properties": {
    "iso:country":"AU",
    "sg:address":"6 Jarvie Ave",
    "sg:city":"Petersham",
    "sg:classifiers":[
        {
            "category":"Home & Garden",
            "subcategory":"Carpets & Floor Coverings",
            "type":"Retail Goods"
        }
    ],
    "sg:phone":"+61 2 9560 1335",
    "sg:postcode":"2049",
    "sg:province":"NSW",
    "sg:tags":[
        "tile",
        "wall",
        "layer"
    ],
    "wof:name":"Massa Masonry",
    "wof:placetype":"venue"
},
  "geometry": {"coordinates":[151.15007,-33.899178],"type":"Point"}
}