{
  "type": "Feature",
  "properties": {
    "addr:full":"PO Box 6011 Fairfield Gardens QLD 4103",
    "addr:postcode":"4103",
    "addr:street":"Fairfield Gardens",
    "iso:country":"AU",
    "sg:address":"PO Box 6011",
    "sg:city":"Fairfield Gardens",
    "sg:classifiers":[
        {
            "category":"Manufacturing",
            "subcategory":"Building Materials",
            "type":"Manufacturing & Wholesale Goods"
        }
    ],
    "sg:phone":"+61 7 3844 6001",
    "sg:postcode":"4103",
    "sg:province":"QLD",
    "sg:tags":[
        "stone",
        "product",
        "supply"
    ],
    "wof:name":"Stonehouse Creations Pty Ltd",
    "wof:placetype":"venue"
},
  "geometry": {"coordinates":[153.02435302699999,-27.5094795227],"type":"Point"}
}