{
  "type": "Feature",
  "properties": {
    "addr:full":"Suite 5 667 Oxley Rd Corinda QLD 4075",
    "addr:housenumber":"667",
    "addr:postcode":"4075",
    "addr:street":"Oxley Rd",
    "iso:country":"AU",
    "sg:address":"Suite 5 667 Oxley Rd",
    "sg:city":"Corinda",
    "sg:classifiers":[
        {
            "category":"Health Services",
            "subcategory":"Doctor",
            "type":"Services"
        }
    ],
    "sg:phone":"+61 7 3379 1303",
    "sg:postcode":"4075",
    "sg:province":"QLD",
    "sg:tags":[
        "medical",
        "practitioner"
    ],
    "wof:name":"Turnbull J T",
    "wof:placetype":"venue"
},
  "geometry": {"coordinates":[152.98144531200001,-27.5398826599],"type":"Point"}
}