{
  "type": "Feature",
  "properties": {
    "iso:country":"AU",
    "sg:address":"20 Biffin St",
    "sg:city":"Cook",
    "sg:classifiers":[
        {
            "category":"Building & Trades",
            "subcategory":"Construction",
            "type":"Services"
        }
    ],
    "sg:phone":"+61 2 6251 2515",
    "sg:postcode":"2614",
    "sg:province":"ACT",
    "sg:tags":[
        "waterproofing",
        "contractor"
    ],
    "wof:name":"Superior Waterproofing Systems",
    "wof:placetype":"venue"
},
  "geometry": {"coordinates":[149.05996704099999,-35.2566108704],"type":"Point"}
}