{
  "type": "Feature",
  "properties": {
    "addr:full":"86 Genrich Rd Maryborough QLD 4650",
    "addr:housenumber":"86",
    "addr:postcode":"4650",
    "addr:street":"Genrich Rd",
    "iso:country":"AU",
    "sg:address":"86 Genrich Rd",
    "sg:city":"Maryborough",
    "sg:classifiers":[
        {
            "category":"Professional",
            "subcategory":"Art Services",
            "type":"Services"
        }
    ],
    "sg:phone":"+61 7 4123 1870",
    "sg:postcode":"4650",
    "sg:province":"QLD",
    "sg:tags":[
        "decorator",
        "painter"
    ],
    "wof:name":"Chris Welsh",
    "wof:placetype":"venue"
},
  "geometry": {"coordinates":[152.67872600000001,-25.516375],"type":"Point"}
}