{
  "type": "Feature",
  "properties": {
    "addr:full":"Unit 1/ 1 Adina Crt Tullamarine VIC 3043",
    "addr:housenumber":"1",
    "addr:postcode":"3043",
    "addr:street":"Adina Crt",
    "iso:country":"AU",
    "sg:address":"Unit 1/ 1 Adina Crt",
    "sg:city":"Tullamarine",
    "sg:classifiers":[
        {
            "category":"Retail",
            "subcategory":"Repair Shop",
            "type":"Services"
        }
    ],
    "sg:phone":"+61 3 9335 2250",
    "sg:postcode":"3043",
    "sg:province":"VIC",
    "sg:tags":[
        "machine",
        "repairs",
        "part",
        "dryer",
        "washing"
    ],
    "wof:name":"Miele Appliance",
    "wof:placetype":"venue"
},
  "geometry": {"coordinates":[144.876861572,-37.7113571167],"type":"Point"}
}