{
  "type": "Feature",
  "properties": {
    "iso:country":"AU",
    "sg:address":"16 Comet Ave",
    "sg:city":"Atherton",
    "sg:classifiers":[
        {
            "category":"Autos & Motor Vehicles",
            "subcategory":"Automobile Sales",
            "type":"Retail Goods"
        }
    ],
    "sg:phone":"+61 7 4091 4777",
    "sg:postcode":"4883",
    "sg:province":"QLD",
    "sg:tags":[
        "car",
        "new"
    ],
    "wof:name":"Hiland Ford Pty Ltd",
    "wof:placetype":"venue"
},
  "geometry": {"coordinates":[145.47532653799999,-17.2552471161],"type":"Point"}
}