{
  "type": "Feature",
  "properties": {
    "addr:full":"9th Floor 50 Appel St Surfers Paradise QLD 4217",
    "addr:housenumber":"50",
    "addr:postcode":"4217",
    "addr:street":"Appel St",
    "iso:country":"AU",
    "sg:address":"9th Floor 50 Appel St",
    "sg:city":"Surfers Paradise",
    "sg:classifiers":[
        {
            "category":"Building & Trades",
            "subcategory":"Construction",
            "type":"Services"
        }
    ],
    "sg:phone":"+61 7 5538 4133",
    "sg:postcode":"4217",
    "sg:province":"QLD",
    "sg:tags":[
        "contractor"
    ],
    "wof:name":"Ingles Group (Qld) Pty Ltd",
    "wof:placetype":"venue"
},
  "geometry": {"coordinates":[153.42825317399999,-28.0054473877],"type":"Point"}
}