{
  "type": "Feature",
  "properties": {
    "iso:country":"AU",
    "sg:address":"342 Nepean Hwy",
    "sg:city":"Frankston",
    "sg:classifiers":[
        {
            "category":"Health Services",
            "subcategory":"Health Practitioner",
            "type":"Services"
        }
    ],
    "sg:phone":"+61 3 9770 2343",
    "sg:postcode":"3199",
    "sg:province":"VIC",
    "sg:tags":[
        "physiotherapist"
    ],
    "wof:name":"LifeCare Frankston Physiotherapy",
    "wof:placetype":"venue"
},
  "geometry": {"coordinates":[145.08071899399999,-37.9903373718],"type":"Point"}
}