{
  "type": "Feature",
  "properties": {
    "iso:country":"AU",
    "sg:address":"774 Chesterpass Rd",
    "sg:city":"King River",
    "sg:classifiers":[
        {
            "category":"Building & Trades",
            "subcategory":"Landscaping Services",
            "type":"Services"
        }
    ],
    "sg:phone":"+61 418 688 101",
    "sg:postcode":"6330",
    "sg:province":"WA",
    "sg:tags":[
        "designer",
        "landscape",
        "contractor"
    ],
    "wof:name":"Colorview Landscaping",
    "wof:placetype":"venue"
},
  "geometry": {"coordinates":[117.90255737299999,-34.9413070679],"type":"Point"}
}