{
  "type": "Feature",
  "properties": {
    "addr:full":"Level 6 343 Lt Collins St Melbourne VIC 3000",
    "addr:housenumber":"343",
    "addr:postcode":"3000",
    "addr:street":"Lt Collins St",
    "iso:country":"AU",
    "sg:address":"Level 6 343 Lt Collins St",
    "sg:city":"Melbourne",
    "sg:classifiers":[
        {
            "category":"Wholesale",
            "subcategory":"Medical Equipment & Supplies",
            "type":"Manufacturing & Wholesale Goods"
        }
    ],
    "sg:phone":"+61 3 9602 1707",
    "sg:postcode":"3000",
    "sg:province":"VIC",
    "sg:tags":[
        "aids",
        "hearing"
    ],
    "wof:name":"Widex Hearing Aids",
    "wof:placetype":"venue"
},
  "geometry": {"coordinates":[144.970611572,-37.8142967224],"type":"Point"}
}