{
  "type": "Feature",
  "properties": {
    "addr:full":"17 Edinburgh St Port Lincoln SA 5606",
    "addr:housenumber":"17",
    "addr:postcode":"5606",
    "addr:street":"Edinburgh St",
    "iso:country":"AU",
    "sg:address":"17 Edinburgh St",
    "sg:city":"Port Lincoln",
    "sg:classifiers":[
        {
            "category":"Farming",
            "subcategory":"Fish & Marine Products",
            "type":"Manufacturing & Wholesale Goods"
        }
    ],
    "sg:phone":"+61 8 8682 6561",
    "sg:postcode":"5606",
    "sg:province":"SA",
    "sg:tags":[
        "organic"
    ],
    "wof:name":"Fresh Eyre Foods",
    "wof:placetype":"venue"
},
  "geometry": {"coordinates":[135.86038199999999,-34.724365],"type":"Point"}
}