{
  "type": "Feature",
  "properties": {
    "addr:full":"C/-Kyabram Hospital Fenaughty St Kyabram VIC 3620",
    "addr:postcode":"3620",
    "addr:street":"C /;St",
    "iso:country":"AU",
    "sg:address":"C/-Kyabram Hospital Fenaughty St",
    "sg:city":"Kyabram",
    "sg:classifiers":[
        {
            "category":"Health Services",
            "subcategory":"Doctor",
            "type":"Services"
        }
    ],
    "sg:phone":"+61 3 5857 0204",
    "sg:postcode":"3620",
    "sg:province":"VIC",
    "sg:tags":[
        "medical",
        "practitioner"
    ],
    "wof:name":"Bell Imaging Group",
    "wof:placetype":"venue"
},
  "geometry": {"coordinates":[145.041870117,-36.3146209717],"type":"Point"}
}