{
  "type": "Feature",
  "properties": {
    "iso:country":"AU",
    "sg:address":"33 Kent St",
    "sg:city":"Millers Point",
    "sg:classifiers":[
        {
            "category":"Travel",
            "subcategory":"Hotels & Motels",
            "type":"Entertainment"
        }
    ],
    "sg:phone":"+61 2 9247 3786",
    "sg:postcode":"2000",
    "sg:province":"NSW",
    "sg:tags":[
        "accommodation"
    ],
    "wof:name":"Captain Cook Hotel",
    "wof:placetype":"venue"
},
  "geometry": {"coordinates":[151.203399658,-33.8588905334],"type":"Point"}
}