{
  "type": "Feature",
  "properties": {
    "addr:full":"29 Noorong St Barham NSW 2732",
    "addr:housenumber":"29",
    "addr:postcode":"2732",
    "addr:street":"Noorong St",
    "iso:country":"AU",
    "sg:address":"29 Noorong St",
    "sg:city":"Barham",
    "sg:classifiers":[
        {
            "category":"Health Services",
            "subcategory":"Doctor",
            "type":"Services"
        }
    ],
    "sg:phone":"+61 3 5453 3500",
    "sg:postcode":"2732",
    "sg:province":"NSW",
    "sg:tags":[
        "medical",
        "practitioner"
    ],
    "wof:name":"Barham-Koondrook Medical Centre",
    "wof:placetype":"venue"
},
  "geometry": {"coordinates":[144.12841800000001,-35.629658],"type":"Point"}
}