{
  "type": "Feature",
  "properties": {
    "addr:full":"Shop 3/ 275 Stafford Rd Stafford QLD 4053",
    "addr:housenumber":"shop 3 / 275",
    "addr:postcode":"4053",
    "addr:street":"Stafford Rd",
    "iso:country":"AU",
    "sg:address":"Shop 3/ 275 Stafford Rd",
    "sg:city":"Stafford",
    "sg:classifiers":[
        {
            "category":"Professional",
            "type":"Services"
        }
    ],
    "sg:phone":"+61 7 3113 4700",
    "sg:postcode":"4053",
    "sg:province":"QLD",
    "sg:tags":[
        "message",
        "answering",
        "telephone"
    ],
    "wof:name":"Your Brisbane Office",
    "wof:placetype":"venue"
},
  "geometry": {"coordinates":[153.019454956,-27.4106369019],"type":"Point"}
}