{
  "type": "Feature",
  "properties": {
    "addr:full":"Unit 6, 188 Manns Rd Gosford West NSW 2250",
    "addr:housenumber":"188",
    "addr:postcode":"2250",
    "addr:street":"Manns Rd",
    "iso:country":"AU",
    "sg:address":"Unit 6, 188 Manns Rd",
    "sg:city":"Gosford West",
    "sg:classifiers":[
        {
            "category":"Manufacturing",
            "subcategory":"Metals",
            "type":"Manufacturing & Wholesale Goods"
        }
    ],
    "sg:phone":"+61 2 4325 1113",
    "sg:postcode":"2250",
    "sg:province":"NSW",
    "sg:tags":[
        "steel",
        "fabricator",
        "mfrs"
    ],
    "wof:name":"King Steel",
    "wof:placetype":"venue"
},
  "geometry": {"coordinates":[151.319488525,-33.4242324829],"type":"Point"}
}