{
  "type": "Feature",
  "properties": {
    "iso:country":"AU",
    "sg:address":"Whistler Drv",
    "sg:city":"Burleigh Waters",
    "sg:classifiers":[
        {
            "category":"Education",
            "subcategory":"School",
            "type":"Public Place"
        }
    ],
    "sg:phone":"+61 7 5568 6333",
    "sg:postcode":"4220",
    "sg:province":"QLD",
    "sg:tags":[
        "state",
        "except",
        "nsw"
    ],
    "wof:name":"Caningeraba Primary School",
    "wof:placetype":"venue"
},
  "geometry": {"coordinates":[153.43133544899999,-28.0855865479],"type":"Point"}
}