{
  "type": "Feature",
  "properties": {
    "addr:full":"4 Chrysostom St North Beach WA 6020",
    "addr:housenumber":"4",
    "addr:postcode":"6020",
    "addr:street":"Chrysostom St",
    "iso:country":"AU",
    "sg:address":"4 Chrysostom St",
    "sg:city":"North Beach",
    "sg:classifiers":[
        {
            "category":"Utilities",
            "subcategory":"Electric",
            "type":"Services"
        }
    ],
    "sg:phone":"+61 418 934 880",
    "sg:postcode":"6020",
    "sg:province":"WA",
    "sg:tags":[
        "electrical",
        "contractor"
    ],
    "wof:name":"L.J. Electrical",
    "wof:placetype":"venue"
},
  "geometry": {"coordinates":[115.75676727299999,-31.8656082153],"type":"Point"}
}