{
  "type": "Feature",
  "properties": {
    "addr:full":"881 Main North Rd Pooraka SA 5095",
    "addr:housenumber":"881",
    "addr:postcode":"5095",
    "addr:street":"Main North Rd",
    "iso:country":"AU",
    "sg:address":"881 Main North Rd",
    "sg:city":"Pooraka",
    "sg:classifiers":[
        {
            "category":"Manufacturing",
            "subcategory":"Tools & Machinery",
            "type":"Manufacturing & Wholesale Goods"
        }
    ],
    "sg:phone":"+61 8 8262 5322",
    "sg:postcode":"5095",
    "sg:province":"SA",
    "sg:tags":[
        "earth",
        "excavating",
        "moving",
        "equipment"
    ],
    "wof:name":"Warrin Equipment",
    "wof:placetype":"venue"
},
  "geometry": {"coordinates":[138.61929321299999,-34.8222694397],"type":"Point"}
}