{
  "type": "Feature",
  "properties": {
    "iso:country":"AU",
    "sg:address":"218 Derby St",
    "sg:city":"Penrith",
    "sg:classifiers":[
        {
            "category":"Health Services",
            "subcategory":"Doctor",
            "type":"Services"
        }
    ],
    "sg:phone":"+61 2 4732 1166",
    "sg:postcode":"2750",
    "sg:province":"NSW",
    "sg:tags":[
        "medical",
        "practitioner"
    ],
    "wof:name":"Southlands Medical Clinic",
    "wof:placetype":"venue"
},
  "geometry": {"coordinates":[150.68772888199999,-33.7720794678],"type":"Point"}
}