{
  "type": "Feature",
  "properties": {
    "addr:full":"Schuss St Falls Creek VIC 3699",
    "addr:postcode":"3699",
    "addr:street":"Schuss St Falls Creek",
    "iso:country":"AU",
    "sg:address":"Schuss St",
    "sg:city":"Falls Creek",
    "sg:classifiers":[
        {
            "category":"Sports & Exercise",
            "subcategory":"Ski Resort",
            "type":"Entertainment"
        }
    ],
    "sg:phone":"+61 3 5758 3499",
    "sg:postcode":"3699",
    "sg:province":"VIC",
    "sg:tags":[
        "tour",
        "centres"
    ],
    "wof:name":"Mountain Multiservice",
    "wof:placetype":"venue"
},
  "geometry": {"coordinates":[147.27421569800001,-36.8659210205],"type":"Point"}
}