{
  "type": "Feature",
  "properties": {
    "addr:full":"371 Longplains Rd Bridgenorth TAS 7277",
    "addr:housenumber":"371",
    "addr:postcode":"7277",
    "addr:street":"Longplains Rd",
    "iso:country":"AU",
    "sg:address":"371 Longplains Rd",
    "sg:city":"Bridgenorth",
    "sg:classifiers":[
        {
            "category":"Wholesale",
            "subcategory":"Construction Materials",
            "type":"Manufacturing & Wholesale Goods"
        }
    ],
    "sg:phone":"+61 408 121 854",
    "sg:postcode":"7277",
    "sg:province":"TAS",
    "sg:tags":[
        "wholesaler",
        "lighting",
        "mfrs",
        "accessory"
    ],
    "wof:name":"Jingle Bulbs Christmas & Party Lights",
    "wof:placetype":"venue"
},
  "geometry": {"coordinates":[146.95208740199999,-41.3433265686],"type":"Point"}
}