{
  "type": "Feature",
  "properties": {
    "addr:full":"Unit 4 1457 Albany Hwy Cannington WA 6107",
    "addr:housenumber":"1457",
    "addr:postcode":"6107",
    "addr:street":"Albany Hwy",
    "iso:country":"AU",
    "sg:address":"Unit 4 1457 Albany Hwy",
    "sg:city":"Cannington",
    "sg:classifiers":[
        {
            "category":"Shopping",
            "subcategory":"Crafts & Fabrics",
            "type":"Retail Goods"
        }
    ],
    "sg:phone":"+61 8 9350 5655",
    "sg:postcode":"6107",
    "sg:province":"WA",
    "sg:tags":[
        "merchant",
        "cork"
    ],
    "wof:name":"Planet Timbers WA Pty Ltd",
    "wof:placetype":"venue"
},
  "geometry": {"coordinates":[115.926513672,-32.0118675232],"type":"Point"}
}