{
  "type": "Feature",
  "properties": {
    "addr:full":"24 Liebelt Rd Mt Barker SA 5251",
    "addr:housenumber":"24",
    "addr:postcode":"5251",
    "addr:street":"Liebelt Rd",
    "iso:country":"AU",
    "sg:address":"24 Liebelt Rd",
    "sg:city":"Mt Barker",
    "sg:classifiers":[
        {
            "category":"Building & Trades",
            "subcategory":"Plumbing",
            "type":"Services"
        }
    ],
    "sg:phone":"+61 421 523 891",
    "sg:postcode":"5251",
    "sg:province":"SA",
    "sg:tags":[
        "plumber",
        "gasfitters"
    ],
    "wof:name":"JRK Plumbing Services",
    "wof:placetype":"venue"
},
  "geometry": {"coordinates":[138.86854553200001,-35.0824928284],"type":"Point"}
}