{
  "type": "Feature",
  "properties": {
    "addr:full":"128 Bowen St Spring Hill QLD 4004",
    "addr:housenumber":"128",
    "addr:postcode":"4004",
    "addr:street":"Bowen St",
    "iso:country":"AU",
    "sg:address":"128 Bowen St",
    "sg:city":"Spring Hill",
    "sg:classifiers":[
        {
            "category":"Professional",
            "subcategory":"Employment Agencies",
            "type":"Services"
        }
    ],
    "sg:phone":"+61 7 3236 9366",
    "sg:postcode":"4004",
    "sg:province":"QLD",
    "sg:tags":[
        "provider",
        "internet"
    ],
    "wof:name":"TereDonn Computer Engineering",
    "wof:placetype":"venue"
},
  "geometry": {"coordinates":[153.02841186500001,-27.4627170563],"type":"Point"}
}