{
  "type": "Feature",
  "properties": {
    "iso:country":"AU",
    "sg:address":"22 Whaddon Ave",
    "sg:city":"Dee Why",
    "sg:classifiers":[
        {
            "category":"Building & Trades",
            "subcategory":"Plumbing",
            "type":"Services"
        }
    ],
    "sg:phone":"+61 411 695 860",
    "sg:postcode":"2099",
    "sg:province":"NSW",
    "sg:tags":[
        "plumber",
        "gasfitters"
    ],
    "wof:name":"Aweena Plumbing",
    "wof:placetype":"venue"
},
  "geometry": {"coordinates":[151.27934265100001,-33.7534332275],"type":"Point"}
}