{
  "type": "Feature",
  "properties": {
    "addr:full":"32 West Thebarton Rd Thebarton SA 5031",
    "addr:housenumber":"32",
    "addr:postcode":"5031",
    "addr:street":"West Thebarton Rd",
    "iso:country":"AU",
    "sg:address":"32 West Thebarton Rd",
    "sg:city":"Thebarton",
    "sg:classifiers":[
        {
            "category":"Manufacturing",
            "subcategory":"Tools & Machinery",
            "type":"Manufacturing & Wholesale Goods"
        }
    ],
    "sg:phone":"+61 8 8238 3500",
    "sg:postcode":"5031",
    "sg:province":"SA",
    "sg:tags":[
        "equipment",
        "scale",
        "weighing"
    ],
    "wof:name":"Robway Crane Safety Systems Pty Ltd",
    "wof:placetype":"venue"
},
  "geometry": {"coordinates":[138.56893920900001,-34.9140052795],"type":"Point"}
}