{
  "type": "Feature",
  "properties": {
    "iso:country":"AU",
    "sg:address":"3 Gillingham St",
    "sg:city":"Watsonia North",
    "sg:classifiers":[
        {
            "category":"Building & Trades",
            "subcategory":"Construction",
            "type":"Services"
        }
    ],
    "sg:phone":"+61 3 9432 6534",
    "sg:postcode":"3087",
    "sg:province":"VIC",
    "sg:tags":[
        "renovation",
        "alterations",
        "extension",
        "contractor"
    ],
    "wof:name":"Iken Building & Maintenance Services",
    "wof:placetype":"venue"
},
  "geometry": {"coordinates":[145.08619689899999,-37.6924171448],"type":"Point"}
}