{
  "type": "Feature",
  "properties": {
    "iso:country":"AU",
    "sg:address":"Suite 3/ 85 Foster St",
    "sg:city":"Dandenong",
    "sg:classifiers":[
        {
            "category":"Home & Garden",
            "subcategory":"Building Materials",
            "type":"Retail Goods"
        }
    ],
    "sg:phone":"+61 3 9794 8433",
    "sg:postcode":"3175",
    "sg:province":"VIC",
    "sg:tags":[
        "supply"
    ],
    "wof:name":"National Building Suppliers",
    "wof:placetype":"venue"
},
  "geometry": {"coordinates":[145.21220398,-37.9897766113],"type":"Point"}
}