{
  "type": "Feature",
  "properties": {
    "iso:country":"AU",
    "sg:address":"23 Sutherland St",
    "sg:city":"Port Hedland",
    "sg:classifiers":[
        {
            "category":"Autos & Motor Vehicles",
            "subcategory":"Fuel & Gas Station",
            "type":"Retail Goods"
        }
    ],
    "sg:phone":"+61 417 955 027",
    "sg:postcode":"6721",
    "sg:province":"WA",
    "sg:tags":[
        "petrol",
        "marketing",
        "pump",
        "equipment"
    ],
    "wof:name":"Kimbara Fitting Service",
    "wof:placetype":"venue"
},
  "geometry": {"coordinates":[118.59765625,-20.3093357086],"type":"Point"}
}