{
  "type": "Feature",
  "properties": {
    "addr:full":"88 Gray St Hamilton VIC 3300",
    "addr:housenumber":"88",
    "addr:postcode":"3300",
    "addr:street":"Gray St",
    "iso:country":"AU",
    "sg:address":"88 Gray St",
    "sg:city":"Hamilton",
    "sg:classifiers":[
        {
            "category":"Real Estate",
            "subcategory":"Real Estate Agent",
            "type":"Services"
        }
    ],
    "sg:phone":"+61 3 5572 2018",
    "sg:postcode":"3300",
    "sg:province":"VIC",
    "wof:name":"Keith P. Lanyon Pty Ltd",
    "wof:placetype":"venue"
},
  "geometry": {"coordinates":[142.022979736,-37.7440261841],"type":"Point"}
}