{
  "type": "Feature",
  "properties": {
    "iso:country":"AU",
    "sg:address":"140 Alexander Drv",
    "sg:city":"Highland Park",
    "sg:classifiers":[
        {
            "category":"Social Services",
            "subcategory":"Child Care",
            "type":"Services"
        }
    ],
    "sg:phone":"+61 7 5596 4299",
    "sg:postcode":"4211",
    "sg:province":"QLD",
    "wof:name":"Highland Park Super Kids",
    "wof:placetype":"venue"
},
  "geometry": {"coordinates":[153.33306884800001,-28.0118122101],"type":"Point"}
}