{
  "type": "Feature",
  "properties": {
    "addr:full":"23 Kissing Point Rd Dundas NSW 2117",
    "addr:housenumber":"23",
    "addr:postcode":"2117",
    "addr:street":"Kissing Point Rd",
    "iso:country":"AU",
    "sg:address":"23 Kissing Point Rd",
    "sg:city":"Dundas",
    "sg:classifiers":[
        {
            "category":"Landmark",
            "subcategory":"Scenic View",
            "type":"Public Place"
        }
    ],
    "sg:phone":"+61 2 9636 7325",
    "sg:postcode":"2117",
    "sg:province":"NSW",
    "sg:tags":[
        "staircase",
        "handrail"
    ],
    "wof:name":"Metro Stairs",
    "wof:placetype":"venue"
},
  "geometry": {"coordinates":[151.04219055199999,-33.7997550964],"type":"Point"}
}