{
  "type": "Feature",
  "properties": {
    "addr:full":"10th Flr AMP Building, 1 Hobart Pl Canberra City ACT 2601",
    "addr:postcode":"2601",
    "addr:street":"Pl",
    "iso:country":"AU",
    "sg:address":"10th Flr AMP Building, 1 Hobart Pl",
    "sg:city":"Canberra City",
    "sg:classifiers":[
        {
            "category":"Health Services",
            "subcategory":"Health Practitioner",
            "type":"Services"
        }
    ],
    "sg:phone":"+61 434 240 163",
    "sg:postcode":"2601",
    "sg:province":"ACT",
    "sg:tags":[
        "psychologist"
    ],
    "wof:name":"Dawson Steven Dr",
    "wof:placetype":"venue"
},
  "geometry": {"coordinates":[149.126342773,-35.2795257568],"type":"Point"}
}