{
  "type": "Feature",
  "properties": {
    "addr:full":"Suite 4, 15 Pakington St St Kilda VIC 3182",
    "addr:housenumber":"15",
    "addr:postcode":"3182",
    "addr:street":"Pakington St",
    "iso:country":"AU",
    "sg:address":"Suite 4, 15 Pakington St",
    "sg:city":"St Kilda",
    "sg:classifiers":[
        {
            "category":"Banks & Credit Unions",
            "subcategory":"Atm",
            "type":"Services"
        }
    ],
    "sg:phone":"+61 1300 668 609",
    "sg:postcode":"3182",
    "sg:province":"VIC",
    "sg:tags":[
        "shelf"
    ],
    "wof:name":"Quick Companies Pty Ltd",
    "wof:placetype":"venue"
},
  "geometry": {"coordinates":[144.98707580600001,-37.8659477234],"type":"Point"}
}