{
  "type": "Feature",
  "properties": {
    "addr:full":"240 Star St Welshpool WA 6106",
    "addr:housenumber":"240",
    "addr:postcode":"6106",
    "addr:street":"Star St",
    "iso:country":"AU",
    "sg:address":"240 Star St",
    "sg:city":"Welshpool",
    "sg:classifiers":[
        {
            "category":"Fast Food",
            "type":"Food & Drink"
        }
    ],
    "sg:phone":"+61 8 9361 6636",
    "sg:postcode":"6106",
    "sg:province":"WA",
    "sg:tags":[
        "away",
        "take"
    ],
    "wof:name":"Star Lunch-Bar",
    "wof:placetype":"venue"
},
  "geometry": {"coordinates":[115.929100037,-31.987071991],"type":"Point"}
}