{
  "type": "Feature",
  "properties": {
    "addr:full":"Shop 36, Bunbury Forum Shopping Centre, Sandridge Bunbury WA 6230",
    "addr:housenumber":"shop 36",
    "addr:postcode":"6230",
    "iso:country":"AU",
    "sg:address":"Shop 36, Bunbury Forum Shopping Centre, Sandridge",
    "sg:city":"Bunbury",
    "sg:classifiers":[
        {
            "category":"Personal",
            "subcategory":"Beauty Salon",
            "type":"Services"
        }
    ],
    "sg:phone":"+61 8 9721 1911",
    "sg:postcode":"6230",
    "sg:province":"WA",
    "sg:tags":[
        "hairdresser"
    ],
    "wof:name":"Forum Hair & Beauty",
    "wof:placetype":"venue"
},
  "geometry": {"coordinates":[115.65014600000001,-33.341118],"type":"Point"}
}