{
  "type": "Feature",
  "properties": {
    "addr:full":"12 Alban St Lidcombe NSW 2141",
    "addr:housenumber":"12",
    "addr:postcode":"2141",
    "addr:street":"St",
    "iso:country":"AU",
    "sg:address":"12 Alban St",
    "sg:city":"Lidcombe",
    "sg:classifiers":[
        {
            "category":"Building & Trades",
            "subcategory":"Construction",
            "type":"Services"
        }
    ],
    "sg:phone":"+61 2 9647 2111",
    "sg:postcode":"2141",
    "sg:province":"NSW",
    "sg:tags":[
        "window",
        "tinting"
    ],
    "wof:name":"Premier Window Tinting",
    "wof:placetype":"venue"
},
  "geometry": {"coordinates":[151.04606628400001,-33.8452262878],"type":"Point"}
}