{
  "type": "Feature",
  "properties": {
    "addr:full":"85 Main St Normanville SA 5204",
    "addr:housenumber":"85",
    "addr:postcode":"5204",
    "addr:street":"Main St",
    "iso:country":"AU",
    "sg:address":"85 Main St",
    "sg:city":"Normanville",
    "sg:classifiers":[
        {
            "category":"Government",
            "subcategory":"Post Office",
            "type":"Public Place"
        }
    ],
    "sg:phone":"+61 8 8558 3446",
    "sg:postcode":"5204",
    "sg:province":"SA",
    "sg:tags":[
        "postal"
    ],
    "wof:name":"Australia Post",
    "wof:placetype":"venue"
},
  "geometry": {"coordinates":[138.35121154800001,-35.4582138062],"type":"Point"}
}