{
  "type": "Feature",
  "properties": {
    "iso:country":"AU",
    "sg:address":"115 Denison St",
    "sg:city":"Hamilton",
    "sg:classifiers":[
        {
            "category":"Home & Garden",
            "subcategory":"Hardware",
            "type":"Retail Goods"
        }
    ],
    "sg:phone":"+61 2 4953 9922",
    "sg:postcode":"2303",
    "sg:province":"NSW",
    "sg:tags":[
        "product",
        "treatment",
        "floor"
    ],
    "wof:name":"Pretoria Flooring Co",
    "wof:placetype":"venue"
},
  "geometry": {"coordinates":[151.747543,-32.925419],"type":"Point"}
}