{
  "type": "Feature",
  "properties": {
    "addr:full":"19 Elma Rd Cheltenham North VIC 3192",
    "addr:housenumber":"19",
    "addr:postcode":"3192",
    "addr:street":"Elma Rd",
    "iso:country":"AU",
    "sg:address":"19 Elma Rd",
    "sg:city":"Cheltenham North",
    "sg:classifiers":[
        {
            "category":"Real Estate",
            "subcategory":"Real Estate Agent",
            "type":"Services"
        }
    ],
    "sg:phone":"+61 3 9553 1515",
    "sg:postcode":"3192",
    "sg:province":"VIC",
    "sg:tags":[
        "handyman's",
        "equipment",
        "hire",
        "builders",
        "contractor"
    ],
    "wof:name":"Ditchwitch Trenching & Excavations",
    "wof:placetype":"venue"
},
  "geometry": {"coordinates":[145.07270813,-37.9503974915],"type":"Point"}
}