{
  "type": "Feature",
  "properties": {
    "iso:country":"AU",
    "sg:address":"125 Kenny St",
    "sg:city":"Westmeadows",
    "sg:classifiers":[
        {
            "category":"Social Services",
            "subcategory":"Adult Care",
            "type":"Services"
        }
    ],
    "sg:phone":"+61 3 9333 3022",
    "sg:postcode":"3049",
    "sg:province":"VIC",
    "sg:tags":[
        "aged"
    ],
    "wof:name":"St Annes Hostel For The Aged",
    "wof:placetype":"venue"
},
  "geometry": {"coordinates":[144.889633,-37.674541],"type":"Point"}
}