{
  "type": "Feature",
  "properties": {
    "iso:country":"AU",
    "sg:address":"9 Grose St",
    "sg:city":"Leura",
    "sg:classifiers":[
        {
            "category":"Health Services",
            "subcategory":"Doctor",
            "type":"Services"
        }
    ],
    "sg:phone":"+61 2 4784 2205",
    "sg:postcode":"2780",
    "sg:province":"NSW",
    "sg:tags":[
        "medical",
        "practitioner"
    ],
    "wof:name":"Rassaby Dr L S",
    "wof:placetype":"venue"
},
  "geometry": {"coordinates":[150.33297729500001,-33.7129592896],"type":"Point"}
}