{
  "type": "Feature",
  "properties": {
    "addr:full":"213- 215 Northbourne Rd Campbellfield VIC 3061",
    "addr:housenumber":"215",
    "addr:postcode":"3061",
    "addr:street":"Northbourne Rd",
    "iso:country":"AU",
    "sg:address":"213- 215 Northbourne Rd",
    "sg:city":"Campbellfield",
    "sg:classifiers":[
        {
            "category":"Juice Bar",
            "subcategory":"None",
            "type":"Food & Drink"
        }
    ],
    "sg:phone":"+61 3 9303 7211",
    "sg:postcode":"3061",
    "sg:province":"VIC",
    "sg:tags":[
        "merchant",
        "fruit",
        "processor"
    ],
    "wof:name":"Crusta Fruit Juices Pty Ltd",
    "wof:placetype":"venue"
},
  "geometry": {"coordinates":[144.956787109,-37.6480903625],"type":"Point"}
}