{
  "type": "Feature",
  "properties": {
    "addr:full":"220/ 222 Sunnyholt Rd Kings Park NSW 2148",
    "addr:housenumber":"220 / 222",
    "addr:postcode":"2148",
    "addr:street":"Sunnyholt Rd",
    "iso:country":"AU",
    "sg:address":"220/ 222 Sunnyholt Rd",
    "sg:city":"Kings Park",
    "sg:classifiers":[
        {
            "category":"Fast Food",
            "type":"Food & Drink"
        }
    ],
    "sg:phone":"+61 2 9621 0021",
    "sg:postcode":"2148",
    "sg:province":"NSW",
    "sg:tags":[
        "away",
        "take"
    ],
    "wof:name":"KFC",
    "wof:placetype":"venue"
},
  "geometry": {"coordinates":[150.916213989,-33.7447242737],"type":"Point"}
}