{
  "type": "Feature",
  "properties": {
    "addr:full":"80- 82 Chesterville Rd Cheltenham VIC 3192",
    "addr:housenumber":"82",
    "addr:postcode":"3192",
    "addr:street":"Chesterville Rd",
    "iso:country":"AU",
    "sg:address":"80- 82 Chesterville Rd",
    "sg:city":"Cheltenham",
    "sg:classifiers":[
        {
            "category":"Food & Beverages",
            "subcategory":"Liquor & Beverages",
            "type":"Retail Goods"
        }
    ],
    "sg:phone":"+61 3 9583 8525",
    "sg:postcode":"3192",
    "sg:province":"VIC",
    "sg:tags":[
        "store"
    ],
    "wof:name":"Cellarbrations",
    "wof:placetype":"venue"
},
  "geometry": {"coordinates":[145.057540894,-37.9565353394],"type":"Point"}
}