{
  "type": "Feature",
  "properties": {
    "addr:full":"Tom Collins Drv Shepparton VIC 3630",
    "addr:postcode":"3630",
    "addr:street":"Collins Drv",
    "iso:country":"AU",
    "sg:address":"Tom Collins Drv",
    "sg:city":"Shepparton",
    "sg:classifiers":[
        {
            "category":"Social Services",
            "subcategory":"Job Training",
            "type":"Services"
        }
    ],
    "sg:phone":"+61 3 5832 9400",
    "sg:postcode":"3630",
    "sg:province":"VIC",
    "sg:tags":[
        "sport"
    ],
    "wof:name":"Aquamoves",
    "wof:placetype":"venue"
},
  "geometry": {"coordinates":[145.39596557600001,-36.3855133057],"type":"Point"}
}