{
  "type": "Feature",
  "properties": {
    "iso:country":"AU",
    "sg:address":"4/ 355 Brighton Rd",
    "sg:city":"Hove",
    "sg:classifiers":[
        {
            "category":"Education",
            "subcategory":"Special Training",
            "type":"Public Place"
        }
    ],
    "sg:phone":"+61 8 8296 0577",
    "sg:postcode":"5048",
    "sg:province":"SA",
    "sg:tags":[
        "diving",
        "school",
        "scuba"
    ],
    "wof:name":"Adelaide Scuba",
    "wof:placetype":"venue"
},
  "geometry": {"coordinates":[138.522186,-35.009029],"type":"Point"}
}