{
  "type": "Feature",
  "properties": {
    "iso:country":"AU",
    "sg:address":"16 Harrison Ave",
    "sg:city":"Concord West",
    "sg:classifiers":[
        {
            "category":"Building & Trades",
            "subcategory":"Construction",
            "type":"Services"
        }
    ],
    "sg:phone":"+61 2 9736 3121",
    "sg:postcode":"2138",
    "sg:province":"NSW",
    "sg:tags":[
        "earth",
        "excavating",
        "moving",
        "contractor"
    ],
    "wof:name":"Hickey's Earthmoving Pty Ltd",
    "wof:placetype":"venue"
},
  "geometry": {"coordinates":[151.086837769,-33.836933136],"type":"Point"}
}