{
  "type": "Feature",
  "properties": {
    "iso:country":"AU",
    "sg:address":"121 Cranbourne Rd",
    "sg:city":"Langwarrin",
    "sg:classifiers":[
        {
            "category":"Personal",
            "subcategory":"Beauty Salon",
            "type":"Services"
        }
    ],
    "sg:phone":"+61 3 9785 6711",
    "sg:postcode":"3910",
    "sg:province":"VIC",
    "wof:name":"Get Gorgeous By Leanne",
    "wof:placetype":"venue"
},
  "geometry": {"coordinates":[145.185424805,-38.1535720825],"type":"Point"}
}