{
  "type": "Feature",
  "properties": {
    "iso:country":"AU",
    "sg:address":"Lot 97",
    "sg:city":"Emanuel Way Fitzroy Crossing",
    "sg:classifiers":[
        {
            "category":"Utilities",
            "subcategory":"Electric",
            "type":"Services"
        }
    ],
    "sg:phone":"+61 8 9191 5150",
    "sg:postcode":"6765",
    "sg:province":"WA",
    "sg:tags":[
        "electrical",
        "contractor"
    ],
    "wof:name":"Johnson G J & Co",
    "wof:placetype":"venue"
},
  "geometry": {"coordinates":[125.56900024399999,-18.1978054047],"type":"Point"}
}