{
  "type": "Feature",
  "properties": {
    "iso:country":"AU",
    "sg:address":"9 River St",
    "sg:city":"Bassendean",
    "sg:classifiers":[
        {
            "category":"Building & Trades",
            "subcategory":"Construction",
            "type":"Services"
        }
    ],
    "sg:phone":"+61 419 938 513",
    "sg:postcode":"6054",
    "sg:province":"WA",
    "sg:tags":[
        "contractor"
    ],
    "wof:name":"Couples Contracting",
    "wof:placetype":"venue"
},
  "geometry": {"coordinates":[115.956886291,-31.8979663849],"type":"Point"}
}