{
  "type": "Feature",
  "properties": {
    "addr:full":"122 Elder St Lambton NSW 2299",
    "addr:housenumber":"122",
    "addr:postcode":"2299",
    "addr:street":"Elder St",
    "iso:country":"AU",
    "sg:address":"122 Elder St",
    "sg:city":"Lambton",
    "sg:classifiers":[
        {
            "category":"Retail",
            "subcategory":"Funeral Services",
            "type":"Services"
        }
    ],
    "sg:phone":"+61 2 4956 4221",
    "sg:postcode":"2299",
    "sg:province":"NSW",
    "sg:tags":[
        "director"
    ],
    "wof:name":"Funeral Assistance Services",
    "wof:placetype":"venue"
},
  "geometry": {"coordinates":[151.70706176799999,-32.9112243652],"type":"Point"}
}