{
  "type": "Feature",
  "properties": {
    "addr:full":"Queen Street Specialist Centre 119 Queen St Cleveland QLD 4163",
    "addr:housenumber":"119",
    "addr:postcode":"4163",
    "addr:street":"Queen St",
    "iso:country":"AU",
    "sg:address":"Queen Street Specialist Centre 119 Queen St",
    "sg:city":"Cleveland",
    "sg:classifiers":[
        {
            "category":"Health Services",
            "subcategory":"Doctor",
            "type":"Services"
        }
    ],
    "sg:phone":"+61 7 3345 7408",
    "sg:postcode":"4163",
    "sg:province":"QLD",
    "sg:tags":[
        "medical",
        "practitioner"
    ],
    "wof:name":"Millican Paul",
    "wof:placetype":"venue"
},
  "geometry": {"coordinates":[153.26788330100001,-27.5281410217],"type":"Point"}
}