{
  "type": "Feature",
  "properties": {
    "addr:full":"91 Haldon St Lakemba NSW 2195",
    "addr:housenumber":"91",
    "addr:postcode":"2195",
    "addr:street":"Haldon St",
    "iso:country":"AU",
    "sg:address":"91 Haldon St",
    "sg:city":"Lakemba",
    "sg:classifiers":[
        {
            "category":"Shopping",
            "subcategory":"Baby Store",
            "type":"Retail Goods"
        }
    ],
    "sg:phone":"+61 2 9740 5801",
    "sg:postcode":"2195",
    "sg:province":"NSW",
    "sg:tags":[
        "children's",
        "wear"
    ],
    "wof:name":"Lakemba Empire Children's Wear",
    "wof:placetype":"venue"
},
  "geometry": {"coordinates":[151.077698,-33.92065],"type":"Point"}
}