{
  "type": "Feature",
  "properties": {
    "addr:full":"45 Hackney Rd Hackney SA 5069",
    "addr:housenumber":"45",
    "addr:postcode":"5069",
    "addr:street":"Hackney Rd",
    "iso:country":"AU",
    "sg:address":"45 Hackney Rd",
    "sg:city":"Hackney",
    "sg:classifiers":[
        {
            "category":"Real Estate",
            "subcategory":"Architect",
            "type":"Services"
        }
    ],
    "sg:phone":"+61 8 8363 2155",
    "sg:postcode":"5069",
    "sg:province":"SA",
    "wof:name":"Hames Sharley",
    "wof:placetype":"venue"
},
  "geometry": {"coordinates":[138.61456298799999,-34.9161186218],"type":"Point"}
}