{
  "type": "Feature",
  "properties": {
    "iso:country":"AU",
    "sg:address":"56 & 20 Greg Chappell Drv",
    "sg:city":"Burleigh Heads",
    "sg:classifiers":[
        {
            "category":"Retail",
            "subcategory":"Storage",
            "type":"Services"
        }
    ],
    "sg:phone":"+61 7 5593 4424",
    "sg:postcode":"4220",
    "sg:province":"QLD",
    "wof:name":"Fort Knox Storage Group",
    "wof:placetype":"venue"
},
  "geometry": {"coordinates":[153.41522216800001,-28.1041431427],"type":"Point"}
}