{
  "type": "Feature",
  "properties": {
    "iso:country":"AU",
    "sg:address":"5a Willis Rd",
    "sg:city":"Woolgoolga",
    "sg:classifiers":[
        {
            "category":"Retail",
            "subcategory":"Storage",
            "type":"Services"
        }
    ],
    "sg:phone":"+61 2 6654 9009",
    "sg:postcode":"2456",
    "sg:province":"NSW",
    "wof:name":"Woolgoolga Self Storage",
    "wof:placetype":"venue"
},
  "geometry": {"coordinates":[153.19607500000001,-30.125988],"type":"Point"}
}