{
  "type": "Feature",
  "properties": {
    "addr:full":"Cnr Pine Rd & Franklin St Canungra QLD 4275",
    "addr:postcode":"4275",
    "addr:street":"Cnr Pine Rd & Franklin St",
    "iso:country":"AU",
    "sg:address":"Cnr Pine Rd & Franklin St",
    "sg:city":"Canungra",
    "sg:classifiers":[
        {
            "category":"Retail",
            "subcategory":"Veterinary Services",
            "type":"Services"
        }
    ],
    "sg:phone":"+61 7 5543 5622",
    "sg:postcode":"4275",
    "sg:province":"QLD",
    "sg:tags":[
        "surgeon"
    ],
    "wof:name":"Canungra Veterinary Surgery",
    "wof:placetype":"venue"
},
  "geometry": {"coordinates":[153.16676330600001,-28.0185165405],"type":"Point"}
}