{
  "type": "Feature",
  "properties": {
    "iso:country":"AU",
    "sg:address":"Gladstone Pde",
    "sg:city":"Elsternwick",
    "sg:classifiers":[
        {
            "category":"Health Services",
            "subcategory":"Doctor",
            "type":"Services"
        }
    ],
    "sg:phone":"+61 3 9523 6457",
    "sg:postcode":"3185",
    "sg:province":"VIC",
    "sg:tags":[
        "medical",
        "practitioner"
    ],
    "wof:name":"Len F. Dr",
    "wof:placetype":"venue"
},
  "geometry": {"coordinates":[145.00904846200001,-37.8895568848],"type":"Point"}
}