{
  "type": "Feature",
  "properties": {
    "addr:full":"Shop 7 Cnr Parkway & Annois Rds Bibra Lake WA 6163",
    "addr:housenumber":"shop 7",
    "addr:postcode":"6163",
    "addr:street":"Cnr Parkway & Annois Rds",
    "iso:country":"AU",
    "sg:address":"Shop 7 Cnr Parkway & Annois Rds",
    "sg:city":"Bibra Lake",
    "sg:classifiers":[
        {
            "category":"Food & Beverages",
            "subcategory":"Supermarket",
            "type":"Retail Goods"
        }
    ],
    "sg:phone":"+61 8 9417 2433",
    "sg:postcode":"6163",
    "sg:province":"WA",
    "sg:tags":[
        "grocery",
        "store"
    ],
    "wof:name":"Eziway Food Stores",
    "wof:placetype":"venue"
},
  "geometry": {"coordinates":[115.84030199999999,-32.090641],"type":"Point"}
}