{
  "type": "Feature",
  "properties": {
    "addr:full":"Kings Langley Child Care Centre, 113 James Cook Drv, Kings Langley NSW 2147",
    "addr:housenumber":"113",
    "addr:postcode":"2147",
    "addr:street":"James Cook Drv",
    "iso:country":"AU",
    "sg:address":"Kings Langley Child Care Centre, 113",
    "sg:city":"James Cook Drv, Kings Langley",
    "sg:classifiers":[
        {
            "category":"Social Services",
            "subcategory":"Child Care",
            "type":"Services"
        }
    ],
    "sg:phone":"+61 2 9624 3328",
    "sg:postcode":"2147",
    "sg:province":"NSW",
    "wof:name":"Blacktown City Council",
    "wof:placetype":"venue"
},
  "geometry": {"coordinates":[150.924957275,-33.7433052063],"type":"Point"}
}