{
  "type": "Feature",
  "properties": {
    "addr:full":"Shop 2, Morphett Vale Village, 162 South Rd Morphett Vale SA 5162",
    "addr:housenumber":"shop 2;162",
    "addr:postcode":"5162",
    "addr:street":"Morphett Vale Village;South Rd",
    "iso:country":"AU",
    "sg:address":"Shop 2, Morphett Vale Village, 162 South Rd",
    "sg:city":"Morphett Vale",
    "sg:classifiers":[
        {
            "category":"Food & Beverages",
            "subcategory":"Bakery",
            "type":"Retail Goods"
        }
    ],
    "sg:phone":"+61 8 8384 4688",
    "sg:postcode":"5162",
    "sg:province":"SA",
    "sg:tags":[
        "baker"
    ],
    "wof:name":"Bakers Delight(SA)Pty Ltd",
    "wof:placetype":"venue"
},
  "geometry": {"coordinates":[138.51751709000001,-35.1183166504],"type":"Point"}
}