{
  "type": "Feature",
  "properties": {
    "iso:country":"AU",
    "sg:address":"93 Garsed St",
    "sg:city":"Bendigo",
    "sg:classifiers":[
        {
            "category":"Autos & Motor Vehicles",
            "subcategory":"Auto Supplies",
            "type":"Retail Goods"
        }
    ],
    "sg:phone":"+61 3 5444 4669",
    "sg:postcode":"3550",
    "sg:province":"VIC",
    "sg:tags":[
        "wheel",
        "automotive",
        "rim"
    ],
    "wof:name":"Marketplace Car Sales",
    "wof:placetype":"venue"
},
  "geometry": {"coordinates":[144.27809143100001,-36.7661857605],"type":"Point"}
}