{
  "type": "Feature",
  "properties": {
    "addr:full":"183 Main Rd Huonville TAS 7109",
    "addr:housenumber":"183",
    "addr:postcode":"7109",
    "addr:street":"Main Rd",
    "iso:country":"AU",
    "sg:address":"183 Main Rd",
    "sg:city":"Huonville",
    "sg:classifiers":[
        {
            "category":"Autos & Motor Vehicles",
            "subcategory":"Fuel & Gas Station",
            "type":"Retail Goods"
        }
    ],
    "sg:phone":"+61 3 6264 1419",
    "sg:postcode":"7109",
    "sg:province":"TAS",
    "wof:name":"Shell Huonville",
    "wof:placetype":"venue"
},
  "geometry": {"coordinates":[147.058883667,-43.0176887512],"type":"Point"}
}