{
  "type": "Feature",
  "properties": {
    "addr:full":"61 Market St Wollongong NSW 2500",
    "addr:housenumber":"61",
    "addr:postcode":"2500",
    "addr:street":"Market St",
    "iso:country":"AU",
    "sg:address":"61 Market St",
    "sg:city":"Wollongong",
    "sg:classifiers":[
        {
            "category":"Health Services",
            "subcategory":"Health Practitioner",
            "type":"Services"
        }
    ],
    "sg:phone":"+61 2 4226 3371",
    "sg:postcode":"2500",
    "sg:province":"NSW",
    "sg:tags":[
        "psychologist"
    ],
    "sg:website":"http://www.cgpservices.com.au",
    "wof:name":"Dr Christine Gillies",
    "wof:placetype":"venue"
},
  "geometry": {"coordinates":[150.89483642600001,-34.4241790771],"type":"Point"}
}