{
  "type": "Feature",
  "properties": {
    "iso:country":"AU",
    "sg:address":"30 Inkerman St St",
    "sg:city":"Kilda",
    "sg:classifiers":[
        {
            "category":"Real Estate",
            "subcategory":"Architect",
            "type":"Services"
        }
    ],
    "sg:phone":"+61 3 9525 3588",
    "sg:postcode":"3182",
    "sg:province":"VIC",
    "wof:name":"McDonald Colman Pty Ltd",
    "wof:placetype":"venue"
},
  "geometry": {"coordinates":[144.982879639,-37.864112854],"type":"Point"}
}