{
  "type": "Feature",
  "properties": {
    "addr:full":"91 Ashford Ave Milperra NSW 2214",
    "addr:housenumber":"91",
    "addr:postcode":"2214",
    "addr:street":"Ashford Ave",
    "iso:country":"AU",
    "sg:address":"91 Ashford Ave",
    "sg:city":"Milperra",
    "sg:classifiers":[
        {
            "category":"Shopping",
            "subcategory":"Computers & Home Electronics",
            "type":"Retail Goods"
        }
    ],
    "sg:phone":"+61 2 9774 1707",
    "sg:postcode":"2214",
    "sg:province":"NSW",
    "sg:tags":[
        "equipment",
        "multimedia"
    ],
    "wof:name":"Columbia Pelikan Pty Ltd",
    "wof:placetype":"venue"
},
  "geometry": {"coordinates":[150.989532,-33.937187],"type":"Point"}
}