{
  "type": "Feature",
  "properties": {
    "iso:country":"AU",
    "sg:address":"171 Kendall St",
    "sg:city":"Cowra",
    "sg:classifiers":[
        {
            "category":"Health Services",
            "subcategory":"Medical Lab",
            "type":"Services"
        }
    ],
    "sg:phone":"+61 2 6342 4366",
    "sg:postcode":"2794",
    "sg:province":"NSW",
    "sg:tags":[
        "laboratory",
        "pathology"
    ],
    "wof:name":"Macquarie Pathology Services Pty Ltd",
    "wof:placetype":"venue"
},
  "geometry": {"coordinates":[148.69776916500001,-33.8355636597],"type":"Point"}
}