{
  "type": "Feature",
  "properties": {
    "addr:full":"Level 2, 15 - 17 William St Perth WA 6000",
    "addr:housenumber":"15 17",
    "addr:postcode":"6000",
    "addr:street":"William St",
    "iso:country":"AU",
    "sg:address":"Level 2, 15 - 17 William St",
    "sg:city":"Perth",
    "sg:classifiers":[
        {
            "category":"Banks & Credit Unions",
            "subcategory":"Financial Services",
            "type":"Services"
        }
    ],
    "sg:phone":"+61 8 9211 4077",
    "sg:postcode":"6000",
    "sg:province":"WA",
    "sg:tags":[
        "annuity",
        "rollover",
        "superannuation",
        "consultant"
    ],
    "wof:name":"Asteron Limited",
    "wof:placetype":"venue"
},
  "geometry": {"coordinates":[115.86382293699999,-31.94099617],"type":"Point"}
}