{
  "type": "Feature",
  "properties": {
    "addr:full":"Ste 1/ 292 Maitland Rd Mayfield NSW 2304",
    "addr:housenumber":"/ 292",
    "addr:postcode":"2304",
    "addr:street":"Maitland Rd",
    "iso:country":"AU",
    "sg:address":"Ste 1/ 292 Maitland Rd",
    "sg:city":"Mayfield",
    "sg:classifiers":[
        {
            "category":"Real Estate",
            "subcategory":"Surveying",
            "type":"Services"
        }
    ],
    "sg:phone":"+61 1300 305 072",
    "sg:postcode":"2304",
    "sg:province":"NSW",
    "sg:tags":[
        "surveyor",
        "land"
    ],
    "wof:name":"Pegasus Technical",
    "wof:placetype":"venue"
},
  "geometry": {"coordinates":[151.73570251500001,-32.8968009949],"type":"Point"}
}