{
  "type": "Feature",
  "properties": {
    "iso:country":"AU",
    "sg:address":"1148 North Rd",
    "sg:city":"Oakleigh South",
    "sg:classifiers":[
        {
            "category":"Food & Beverages",
            "subcategory":"Liquor & Beverages",
            "type":"Retail Goods"
        }
    ],
    "sg:phone":"+61 3 9570 3750",
    "sg:postcode":"3167",
    "sg:province":"VIC",
    "sg:tags":[
        "store"
    ],
    "wof:name":"Cheeers Liquor Group",
    "wof:placetype":"venue"
},
  "geometry": {"coordinates":[145.08627319300001,-37.9097518921],"type":"Point"}
}