{
  "type": "Feature",
  "properties": {
    "iso:country":"AU",
    "sg:address":"Ste 603, San Clinic 185 Fox Valley Rd",
    "sg:city":"Wahroonga",
    "sg:classifiers":[
        {
            "category":"Health Services",
            "subcategory":"Doctor",
            "type":"Services"
        }
    ],
    "sg:phone":"+61 2 9473 8633",
    "sg:postcode":"2076",
    "sg:province":"NSW",
    "sg:tags":[
        "medical",
        "practitioner"
    ],
    "wof:name":"Washington Harvey G",
    "wof:placetype":"venue"
},
  "geometry": {"coordinates":[151.1015625,-33.73229599],"type":"Point"}
}