{
  "type": "Feature",
  "properties": {
    "addr:full":"295 Sandy Bay Rd Sandy Bay TAS 7005",
    "addr:housenumber":"295",
    "addr:postcode":"7005",
    "addr:street":"Sandy Bay Rd",
    "iso:country":"AU",
    "sg:address":"295 Sandy Bay Rd",
    "sg:city":"Sandy Bay",
    "sg:classifiers":[
        {
            "category":"Personal",
            "subcategory":"Massage",
            "type":"Services"
        }
    ],
    "sg:phone":"+61 3 6224 0228",
    "sg:postcode":"7005",
    "sg:province":"TAS",
    "sg:tags":[
        "therapy"
    ],
    "wof:name":"Blaikie Tessa",
    "wof:placetype":"venue"
},
  "geometry": {"coordinates":[147.32945251500001,-42.8986206055],"type":"Point"}
}