{
  "type": "Feature",
  "properties": {
    "iso:country":"AU",
    "sg:address":"43A Bendigo Ave",
    "sg:city":"Bentleigh",
    "sg:classifiers":[
        {
            "category":"Home & Garden",
            "subcategory":"Hardware",
            "type":"Retail Goods"
        }
    ],
    "sg:phone":"+61 3 9557 5731",
    "sg:postcode":"3204",
    "sg:province":"VIC",
    "sg:tags":[
        "supply",
        "maker",
        "cabinet"
    ],
    "wof:name":"Radok Distributors Pty Ltd",
    "wof:placetype":"venue"
},
  "geometry": {"coordinates":[145.03656000000001,-37.922256],"type":"Point"}
}