{
  "type": "Feature",
  "properties": {
    "addr:full":"90 Anderson St Webberton WA 6530",
    "addr:housenumber":"90",
    "addr:postcode":"6530",
    "addr:street":"Anderson St",
    "iso:country":"AU",
    "sg:address":"90 Anderson St",
    "sg:city":"Webberton",
    "sg:classifiers":[
        {
            "category":"Retail",
            "subcategory":"Auto Repair",
            "type":"Services"
        }
    ],
    "sg:phone":"+61 8 9965 4333",
    "sg:postcode":"6530",
    "sg:province":"WA",
    "sg:tags":[
        "repairer",
        "motor",
        "engineer"
    ],
    "wof:name":"Whyatt's Automotive",
    "wof:placetype":"venue"
},
  "geometry": {"coordinates":[114.635063171,-28.7528953552],"type":"Point"}
}