{
  "type": "Feature",
  "properties": {
    "iso:country":"AU",
    "sg:address":"176 Crittenden Rd",
    "sg:city":"Findon",
    "sg:classifiers":[
        {
            "category":"Education",
            "subcategory":"School",
            "type":"Public Place"
        }
    ],
    "sg:phone":"+61 8 8445 9666",
    "sg:postcode":"5023",
    "sg:province":"SA",
    "sg:tags":[
        "girl"
    ],
    "wof:name":"Siena College",
    "wof:placetype":"venue"
},
  "geometry": {"coordinates":[138.53224182100001,-34.8952102661],"type":"Point"}
}