{
  "type": "Feature",
  "properties": {
    "iso:country":"AU",
    "sg:address":"2/ 62 Collins St",
    "sg:city":"Mentone",
    "sg:classifiers":[
        {
            "category":"Real Estate",
            "subcategory":"Architect",
            "type":"Services"
        }
    ],
    "sg:phone":"+61 3 9583 0026",
    "sg:postcode":"3194",
    "sg:province":"VIC",
    "wof:name":"Alvis Svikers",
    "wof:placetype":"venue"
},
  "geometry": {"coordinates":[145.06097412099999,-37.979763031],"type":"Point"}
}