{
  "type": "Feature",
  "properties": {
    "addr:full":"7a Kemp St The Junction NSW 2291",
    "addr:housenumber":"7a",
    "addr:postcode":"2291",
    "addr:street":"Kemp St",
    "iso:country":"AU",
    "sg:address":"7a Kemp St",
    "sg:city":"The Junction",
    "sg:classifiers":[
        {
            "category":"Professional",
            "subcategory":"Engineering",
            "type":"Services"
        }
    ],
    "sg:phone":"+61 2 4950 6066",
    "sg:postcode":"2291",
    "sg:province":"NSW",
    "sg:tags":[
        "electrical",
        "engineer"
    ],
    "wof:name":"RLP Electric Pty Ltd",
    "wof:placetype":"venue"
},
  "geometry": {"coordinates":[151.762084961,-32.9371604919],"type":"Point"}
}