{
  "type": "Feature",
  "properties": {
    "iso:country":"AU",
    "sg:address":"615 Warrigul Rd",
    "sg:city":"Ashburton",
    "sg:classifiers":[
        {
            "category":"Wholesale",
            "subcategory":"Machinery & Supplies",
            "type":"Manufacturing & Wholesale Goods"
        }
    ],
    "sg:phone":"+61 3 9764 1101",
    "sg:postcode":"3147",
    "sg:province":"VIC",
    "sg:tags":[
        "equipment",
        "system",
        "elevating",
        "conveying"
    ],
    "wof:name":"Metys Pty Ltd",
    "wof:placetype":"venue"
},
  "geometry": {"coordinates":[145.09231567399999,-37.8729324341],"type":"Point"}
}