{
  "type": "Feature",
  "properties": {
    "addr:full":"30 Wendron St Cloverdale WA 6105",
    "addr:housenumber":"30",
    "addr:postcode":"6105",
    "addr:street":"Wendron St",
    "iso:country":"AU",
    "sg:address":"30 Wendron St",
    "sg:city":"Cloverdale",
    "sg:classifiers":[
        {
            "category":"Social Services",
            "subcategory":"Adult Care",
            "type":"Services"
        }
    ],
    "sg:phone":"+61 439 090 804",
    "sg:postcode":"6105",
    "sg:province":"WA",
    "sg:tags":[
        "towing"
    ],
    "wof:name":"A & I Towing",
    "wof:placetype":"venue"
},
  "geometry": {"coordinates":[115.94847869900001,-31.9696846008],"type":"Point"}
}