{
  "type": "Feature",
  "properties": {
    "addr:full":"823 High St Epping VIC 3076",
    "addr:housenumber":"823",
    "addr:postcode":"3076",
    "addr:street":"High St",
    "iso:country":"AU",
    "sg:address":"823 High St",
    "sg:city":"Epping",
    "sg:classifiers":[
        {
            "category":"Arena",
            "subcategory":"Horse Racetrack",
            "type":"Entertainment"
        }
    ],
    "sg:phone":"+61 3 8405 3208",
    "sg:postcode":"3076",
    "sg:province":"VIC",
    "sg:tags":[
        "retail",
        "swimwear"
    ],
    "wof:name":"Indigo Swimwear and Activewear",
    "wof:placetype":"venue"
},
  "geometry": {"coordinates":[145.01521301299999,-37.8546485901],"type":"Point"}
}