{
  "type": "Feature",
  "properties": {
    "iso:country":"AU",
    "sg:address":"95 Wrigley St",
    "sg:city":"Gilgandra",
    "sg:classifiers":[
        {
            "category":"Arts & Performance",
            "subcategory":"Music",
            "type":"Entertainment"
        }
    ],
    "sg:phone":"+61 437 849 817",
    "sg:postcode":"2827",
    "sg:province":"NSW",
    "sg:tags":[
        "mobile",
        "jockey",
        "disc"
    ],
    "wof:name":"DJ Schmak",
    "wof:placetype":"venue"
},
  "geometry": {"coordinates":[148.66015625,-31.7083034515],"type":"Point"}
}