{
  "type": "Feature",
  "properties": {
    "addr:full":"1/ 26 Wentworth Ave Mascot NSW 2020",
    "addr:housenumber":"/ 26",
    "addr:postcode":"2020",
    "addr:street":"Wentworth Ave",
    "iso:country":"AU",
    "sg:address":"1/ 26 Wentworth Ave",
    "sg:city":"Mascot",
    "sg:classifiers":[
        {
            "category":"Real Estate",
            "subcategory":"Architect",
            "type":"Services"
        }
    ],
    "sg:phone":"+61 1800 685 485",
    "sg:postcode":"2020",
    "sg:province":"NSW",
    "sg:tags":[
        "magnet",
        "magnetic",
        "material"
    ],
    "wof:name":"AMF Magnetics",
    "wof:placetype":"venue"
},
  "geometry": {"coordinates":[151.19529724099999,-33.9346008301],"type":"Point"}
}