{
  "type": "Feature",
  "properties": {
    "iso:country":"AU",
    "sg:address":"21 Slatey Creek Rd",
    "sg:city":"Ballarat",
    "sg:classifiers":[
        {
            "category":"Health Services",
            "subcategory":"Doctor",
            "type":"Services"
        }
    ],
    "sg:phone":"+61 3 5332 2450",
    "sg:postcode":"3352",
    "sg:province":"VIC",
    "sg:tags":[
        "reflexology"
    ],
    "wof:name":"Margaret Stewart",
    "wof:placetype":"venue"
},
  "geometry": {"coordinates":[143.91153,-37.480942],"type":"Point"}
}