{
  "type": "Feature",
  "properties": {
    "addr:full":"69 Dragon St Warwick QLD 4370",
    "addr:housenumber":"69",
    "addr:postcode":"4370",
    "addr:street":"Dragon St",
    "iso:country":"AU",
    "sg:address":"69 Dragon St",
    "sg:city":"Warwick",
    "sg:classifiers":[
        {
            "category":"Food & Beverages",
            "subcategory":"Groceries & Convenience Stores",
            "type":"Retail Goods"
        }
    ],
    "sg:phone":"+61 7 4661 1478",
    "sg:postcode":"4370",
    "sg:province":"QLD",
    "wof:name":"Dragon Street Convenience Store",
    "wof:placetype":"venue"
},
  "geometry": {"coordinates":[152.027175903,-28.2187385559],"type":"Point"}
}