{
  "type": "Feature",
  "properties": {
    "addr:full":"162 Norwell Rd Norwell QLD 4208",
    "addr:housenumber":"162",
    "addr:postcode":"4208",
    "addr:street":"Norwell Rd",
    "iso:country":"AU",
    "sg:address":"162 Norwell Rd",
    "sg:city":"Norwell",
    "sg:classifiers":[
        {
            "category":"Home & Garden",
            "subcategory":"Garden Supply",
            "type":"Retail Goods"
        }
    ],
    "sg:phone":"+61 412 075 626",
    "sg:postcode":"4208",
    "sg:province":"QLD",
    "sg:tags":[
        "landscape"
    ],
    "wof:name":"Willmanns Sugarcane Hay",
    "wof:placetype":"venue"
},
  "geometry": {"coordinates":[153.288818359,-27.7651062012],"type":"Point"}
}