{
  "type": "Feature",
  "properties": {
    "iso:country":"AU",
    "sg:address":"Shp 7/ 10b Charles St",
    "sg:city":"Canterbury",
    "sg:classifiers":[
        {
            "category":"Professional",
            "subcategory":"Art Services",
            "type":"Services"
        }
    ],
    "sg:phone":"+61 2 9787 8099",
    "sg:postcode":"2193",
    "sg:province":"NSW",
    "sg:tags":[
        "graphic",
        "designer"
    ],
    "wof:name":"J-Grow Graphic Design & Printing",
    "wof:placetype":"venue"
},
  "geometry": {"coordinates":[151.116348,-33.911182],"type":"Point"}
}