{
  "type": "Feature",
  "properties": {
    "iso:country":"AU",
    "sg:address":"55 Frome St",
    "sg:city":"Adelaide",
    "sg:classifiers":[
        {
            "category":"Restaurant",
            "type":"Food & Drink"
        }
    ],
    "sg:phone":"+61 8 8100 4495",
    "sg:postcode":"5000",
    "sg:province":"SA",
    "sg:website":"http://www.majestichotels.com.au",
    "wof:name":"Culshaws Grill",
    "wof:placetype":"venue"
},
  "geometry": {"coordinates":[138.60812377900001,-34.9230194092],"type":"Point"}
}