{
  "type": "Feature",
  "properties": {
    "addr:full":"783 Windsor Rd Box Hill NSW 2765",
    "addr:housenumber":"783",
    "addr:postcode":"2765",
    "addr:street":"Windsor Rd",
    "iso:country":"AU",
    "sg:address":"783 Windsor Rd",
    "sg:city":"Box Hill",
    "sg:classifiers":[
        {
            "category":"Transit Center",
            "subcategory":"Freight",
            "type":"Transportation"
        }
    ],
    "sg:phone":"+61 2 9627 5094",
    "sg:postcode":"2765",
    "sg:province":"NSW",
    "sg:tags":[
        "weighbridge"
    ],
    "wof:name":"Windsor Road Public Weighbridge",
    "wof:placetype":"venue"
},
  "geometry": {"coordinates":[150.91392517099999,-33.6802711487],"type":"Point"}
}