{
  "type": "Feature",
  "properties": {
    "addr:full":"1 Heppe Valley Rd Robinvale South VIC 3549",
    "addr:housenumber":"1",
    "addr:postcode":"3549",
    "addr:street":"Heppe Valley Rd",
    "iso:country":"AU",
    "sg:address":"1 Heppe Valley Rd",
    "sg:city":"Robinvale South",
    "sg:classifiers":[
        {
            "category":"Farming",
            "subcategory":"Berry Farm",
            "type":"Manufacturing & Wholesale Goods"
        }
    ],
    "sg:phone":"+61 3 5026 3998",
    "sg:postcode":"3549",
    "sg:province":"VIC",
    "sg:tags":[
        "fruit",
        "grower"
    ],
    "wof:name":"Bitsounis H",
    "wof:placetype":"venue"
},
  "geometry": {"coordinates":[142.767669678,-34.6226081848],"type":"Point"}
}