{
  "type": "Feature",
  "properties": {
    "iso:country":"AU",
    "sg:address":"187 Ruthven St",
    "sg:city":"Toowoomba",
    "sg:classifiers":[
        {
            "category":"Personal",
            "subcategory":"Nail Salon",
            "type":"Services"
        }
    ],
    "sg:phone":"+61 7 4632 6168",
    "sg:postcode":"4350",
    "sg:province":"QLD",
    "sg:tags":[
        "artificial"
    ],
    "wof:name":"Leesa's His & Hers Hairdresser",
    "wof:placetype":"venue"
},
  "geometry": {"coordinates":[151.952255,-27.568483],"type":"Point"}
}