{
  "type": "Feature",
  "properties": {
    "addr:full":"187 Ruthven St Toowoomba QLD 4350",
    "addr:housenumber":"187",
    "addr:postcode":"4350",
    "addr:street":"Ruthven St",
    "iso:country":"AU",
    "sg:address":"187 Ruthven St",
    "sg:city":"Toowoomba",
    "sg:classifiers":[
        {
            "category":"Personal",
            "subcategory":"Nail Salon",
            "type":"Services"
        }
    ],
    "sg:phone":"+61 7 4632 6168",
    "sg:postcode":"4350",
    "sg:province":"QLD",
    "sg:tags":[
        "artificial"
    ],
    "wof:name":"Leesa's His & Hers Hairdresser",
    "wof:placetype":"venue"
},
  "geometry": {"coordinates":[151.95225500000001,-27.568483],"type":"Point"}
}