{
  "type": "Feature",
  "properties": {
    "addr:full":"1463 Pittwater Rd Narrabeen NSW 2101",
    "addr:housenumber":"1463",
    "addr:postcode":"2101",
    "addr:street":"Pittwater Rd",
    "iso:country":"AU",
    "sg:address":"1463 Pittwater Rd",
    "sg:city":"Narrabeen",
    "sg:classifiers":[
        {
            "category":"Shopping",
            "subcategory":"Party Supplies",
            "type":"Retail Goods"
        }
    ],
    "sg:phone":"+61 2 9970 7999",
    "sg:postcode":"2101",
    "sg:province":"NSW",
    "wof:name":"Balloons Balloons",
    "wof:placetype":"venue"
},
  "geometry": {"coordinates":[151.30181899999999,-33.695705],"type":"Point"}
}