{
  "type": "Feature",
  "properties": {
    "addr:full":"21 Buddina St Stafford QLD 4053",
    "addr:housenumber":"21",
    "addr:postcode":"4053",
    "addr:street":"Buddina St",
    "iso:country":"AU",
    "sg:address":"21 Buddina St",
    "sg:city":"Stafford",
    "sg:classifiers":[
        {
            "category":"Education",
            "subcategory":"School",
            "type":"Public Place"
        }
    ],
    "sg:phone":"+61 7 3357 9403",
    "sg:postcode":"4053",
    "sg:province":"QLD",
    "sg:tags":[
        "supply"
    ],
    "wof:name":"Cole & Cole",
    "wof:placetype":"venue"
},
  "geometry": {"coordinates":[153.022247314,-27.4098052979],"type":"Point"}
}