{
  "type": "Feature",
  "properties": {
    "addr:full":"6 Mcdonald Crs Charlestown NSW 2290",
    "addr:housenumber":"6",
    "addr:postcode":"2290",
    "addr:street":"Mcdonald Crs",
    "iso:country":"AU",
    "sg:address":"6 Mcdonald Crs",
    "sg:city":"Charlestown",
    "sg:classifiers":[
        {
            "category":"Retail",
            "subcategory":"Storage",
            "type":"Services"
        }
    ],
    "sg:phone":"+61 2 4942 3995",
    "sg:postcode":"2290",
    "sg:province":"NSW",
    "sg:tags":[
        "removal",
        "furniture"
    ],
    "wof:name":"Ken Smit Removals",
    "wof:placetype":"venue"
},
  "geometry": {"coordinates":[151.68455505399999,-32.9597244263],"type":"Point"}
}