{
  "type": "Feature",
  "properties": {
    "iso:country":"AU",
    "sg:address":"Lot 4 Bulahdelah Rd",
    "sg:city":"Booral",
    "sg:classifiers":[
        {
            "category":"Shopping",
            "type":"Retail Goods"
        }
    ],
    "sg:phone":"+61 2 4994 9172",
    "sg:postcode":"2425",
    "sg:province":"NSW",
    "sg:tags":[
        "produce",
        "grain"
    ],
    "wof:name":"Booral Produce",
    "wof:placetype":"venue"
},
  "geometry": {"coordinates":[151.98744201700001,-32.4728813171],"type":"Point"}
}