{
  "type": "Feature",
  "properties": {
    "addr:full":"343 Uhlmann Rd Burpengary QLD 4505",
    "addr:housenumber":"343",
    "addr:postcode":"4505",
    "addr:street":"Uhlmann Rd",
    "iso:country":"AU",
    "sg:address":"343 Uhlmann Rd",
    "sg:city":"Burpengary",
    "sg:classifiers":[
        {
            "category":"Manufacturing",
            "subcategory":"Building Materials",
            "type":"Manufacturing & Wholesale Goods"
        }
    ],
    "sg:phone":"+61 7 5497 8897",
    "sg:postcode":"4505",
    "sg:province":"QLD",
    "sg:tags":[
        "concrete",
        "product"
    ],
    "wof:name":"Dunlop Panels Pty Ltd",
    "wof:placetype":"venue"
},
  "geometry": {"coordinates":[153.00355529800001,-27.1414985657],"type":"Point"}
}