{
  "type": "Feature",
  "properties": {
    "iso:country":"AU",
    "sg:address":"28 Coolawin Crs",
    "sg:city":"Shellharbour",
    "sg:classifiers":[
        {
            "category":"Professional",
            "subcategory":"Detective & Security Services",
            "type":"Services"
        }
    ],
    "sg:phone":"+61 2 4296 1147",
    "sg:postcode":"2529",
    "sg:province":"NSW",
    "sg:tags":[
        "equipment",
        "window",
        "doors"
    ],
    "wof:name":"Freelite Glass Aluminium Windows & Doors",
    "wof:placetype":"venue"
},
  "geometry": {"coordinates":[150.86412048299999,-34.5756912231],"type":"Point"}
}