{
  "type": "Feature",
  "properties": {
    "addr:full":"PO Box 2069 Greenvale VIC 3059",
    "addr:postcode":"3059",
    "iso:country":"AU",
    "sg:address":"PO Box 2069",
    "sg:city":"Greenvale",
    "sg:classifiers":[
        {
            "category":"Professional",
            "subcategory":"Detective & Security Services",
            "type":"Services"
        }
    ],
    "sg:phone":"+61 419 885 670",
    "sg:postcode":"3059",
    "sg:province":"VIC",
    "sg:tags":[
        "consultant",
        "system"
    ],
    "wof:name":"Advanced Security & Electrical Services Pty Ltd",
    "wof:placetype":"venue"
},
  "geometry": {"coordinates":[144.87501525900001,-37.6348800659],"type":"Point"}
}