{
  "type": "Feature",
  "properties": {
    "addr:full":"7 West St Brookvale NSW 2100",
    "addr:housenumber":"7",
    "addr:postcode":"2100",
    "addr:street":"West St",
    "iso:country":"AU",
    "sg:address":"7 West St",
    "sg:city":"Brookvale",
    "sg:classifiers":[
        {
            "category":"Manufacturing",
            "subcategory":"Motor Vehicles & Parts",
            "type":"Manufacturing & Wholesale Goods"
        }
    ],
    "sg:phone":"+61 2 9905 9733",
    "sg:postcode":"2100",
    "sg:province":"NSW",
    "sg:tags":[
        "replacement"
    ],
    "wof:name":"Cv Xpress",
    "wof:placetype":"venue"
},
  "geometry": {"coordinates":[151.27699279800001,-33.7615394592],"type":"Point"}
}