{
  "type": "Feature",
  "properties": {
    "iso:country":"AU",
    "sg:address":"132 Tweed Coast Rd",
    "sg:city":"Chinderah",
    "sg:classifiers":[
        {
            "category":"Building & Trades",
            "subcategory":"Construction",
            "type":"Services"
        }
    ],
    "sg:phone":"+61 410 656 897",
    "sg:postcode":"2487",
    "sg:province":"NSW",
    "sg:tags":[
        "fencing",
        "contractor"
    ],
    "wof:name":"Cage Temporary Fence Hire",
    "wof:placetype":"venue"
},
  "geometry": {"coordinates":[153.564620972,-28.2904262543],"type":"Point"}
}