{
  "type": "Feature",
  "properties": {
    "addr:full":"Reserve Rd Muchea WA 6501",
    "addr:postcode":"6501",
    "addr:street":"Reserve Rd",
    "iso:country":"AU",
    "sg:address":"Reserve Rd",
    "sg:city":"Muchea",
    "sg:classifiers":[
        {
            "category":"Manufacturing",
            "subcategory":"Tools & Machinery",
            "type":"Manufacturing & Wholesale Goods"
        }
    ],
    "sg:phone":"+61 8 9571 0069",
    "sg:postcode":"6501",
    "sg:province":"WA",
    "sg:tags":[
        "earth",
        "excavating",
        "moving",
        "equipment"
    ],
    "wof:name":"Muchea Grading Contractors",
    "wof:placetype":"venue"
},
  "geometry": {"coordinates":[116.00232699999999,-31.542881],"type":"Point"}
}