{
  "type": "Feature",
  "properties": {
    "addr:full":"Shop 240 Ipswich City Mall, Nicholas St Ipswich QLD 4305",
    "addr:housenumber":"240",
    "addr:postcode":"4305",
    "addr:street":"Nicholas St",
    "iso:country":"AU",
    "sg:address":"Shop 240 Ipswich City Mall, Nicholas St",
    "sg:city":"Ipswich",
    "sg:classifiers":[
        {
            "category":"Shopping",
            "subcategory":"Mobile Phones",
            "type":"Retail Goods"
        }
    ],
    "sg:phone":"+61 7 3282 7222",
    "sg:postcode":"4305",
    "sg:province":"QLD",
    "sg:tags":[
        "telephone",
        "accessory"
    ],
    "wof:name":"Optus World",
    "wof:placetype":"venue"
},
  "geometry": {"coordinates":[152.76527404800001,-27.6164894104],"type":"Point"}
}