{
  "type": "Feature",
  "properties": {
    "iso:country":"AU",
    "sg:address":"39 Albert St St",
    "sg:city":"Peters",
    "sg:classifiers":[
        {
            "category":"Farming",
            "subcategory":"Fish & Marine Products",
            "type":"Manufacturing & Wholesale Goods"
        }
    ],
    "sg:phone":"+61 2 9519 5199",
    "sg:postcode":"2044",
    "sg:province":"NSW",
    "sg:tags":[
        "chemical",
        "supplier"
    ],
    "wof:name":"Dye &#034;M&#034; All Pty Ltd",
    "wof:placetype":"venue"
},
  "geometry": {"coordinates":[151.179535,-33.91291],"type":"Point"}
}