{
  "type": "Feature",
  "properties": {
    "iso:country":"AU",
    "sg:address":"High St",
    "sg:city":"Cobram",
    "sg:classifiers":[
        {
            "category":"Retail",
            "subcategory":"Funeral Services",
            "type":"Services"
        }
    ],
    "sg:phone":"+61 1800 622 482",
    "sg:postcode":"3643",
    "sg:province":"VIC",
    "sg:tags":[
        "director"
    ],
    "wof:name":"Hoban, Hutson & Tuttle",
    "wof:placetype":"venue"
},
  "geometry": {"coordinates":[145.64918518100001,-35.9171905518],"type":"Point"}
}