{
  "type": "Feature",
  "properties": {
    "iso:country":"AU",
    "sg:address":"13 Canberra St",
    "sg:city":"Patterson Lakes",
    "sg:classifiers":[
        {
            "category":"Building & Trades",
            "subcategory":"Construction",
            "type":"Services"
        }
    ],
    "sg:phone":"+61 412 044 009",
    "sg:postcode":"3197",
    "sg:province":"VIC",
    "sg:tags":[
        "concrete",
        "contractor"
    ],
    "wof:name":"F & J Torcasio",
    "wof:placetype":"venue"
},
  "geometry": {"coordinates":[145.13508605999999,-38.0730285645],"type":"Point"}
}