{
  "type": "Feature",
  "properties": {
    "addr:full":"470 Pacific Hwy Wyoming NSW 2250",
    "addr:housenumber":"470",
    "addr:postcode":"2250",
    "addr:street":"Pacific Hwy",
    "iso:country":"AU",
    "sg:address":"470 Pacific Hwy",
    "sg:city":"Wyoming",
    "sg:classifiers":[
        {
            "category":"Sports & Exercise",
            "subcategory":"Gym",
            "type":"Entertainment"
        }
    ],
    "sg:phone":"+61 2 4322 8100",
    "sg:postcode":"2250",
    "sg:province":"NSW",
    "sg:tags":[
        "health",
        "fitness"
    ],
    "wof:name":"Healthy Inspirations",
    "wof:placetype":"venue"
},
  "geometry": {"coordinates":[151.34861755399999,-33.409576416],"type":"Point"}
}