{
  "type": "Feature",
  "properties": {
    "addr:full":"Bapayme Rd Moorebank NSW 2170",
    "addr:postcode":"2170",
    "addr:street":"Bapayme Rd",
    "iso:country":"AU",
    "sg:address":"Bapayme Rd",
    "sg:city":"Moorebank",
    "sg:classifiers":[
        {
            "category":"Professional",
            "type":"Services"
        }
    ],
    "sg:phone":"+61 2 9821 1181",
    "sg:postcode":"2170",
    "sg:province":"NSW",
    "sg:tags":[
        "transport"
    ],
    "wof:name":"Lance Smith Heavy Haulage",
    "wof:placetype":"venue"
},
  "geometry": {"coordinates":[150.92433166500001,-33.942779541],"type":"Point"}
}