{
  "type": "Feature",
  "properties": {
    "addr:full":"Blind Creek Rd Windermere VIC 3352",
    "addr:postcode":"3352",
    "addr:street":"Blind Creek Rd",
    "iso:country":"AU",
    "sg:address":"Blind Creek Rd",
    "sg:city":"Windermere",
    "sg:classifiers":[
        {
            "category":"Shopping",
            "type":"Retail Goods"
        }
    ],
    "sg:phone":"+61 3 5344 8217",
    "sg:postcode":"3352",
    "sg:province":"VIC",
    "sg:tags":[
        "produce",
        "grain"
    ],
    "wof:name":"Alexander D S & D M Pty Ltd",
    "wof:placetype":"venue"
},
  "geometry": {"coordinates":[143.71850599999999,-37.488182],"type":"Point"}
}