{
  "type": "Feature",
  "properties": {
    "iso:country":"AU",
    "sg:address":"Sunrise Shopping Centre Ben Lexcen Drv",
    "sg:city":"Sunrise Beach",
    "sg:classifiers":[
        {
            "category":"Food & Beverages",
            "subcategory":"Bakery",
            "type":"Retail Goods"
        }
    ],
    "sg:phone":"+61 7 5447 5733",
    "sg:postcode":"4567",
    "sg:province":"QLD",
    "sg:tags":[
        "cake",
        "shop",
        "pastry"
    ],
    "wof:name":"Breadlovers",
    "wof:placetype":"venue"
},
  "geometry": {"coordinates":[153.10293579099999,-26.4147224426],"type":"Point"}
}