{
  "type": "Feature",
  "properties": {
    "addr:full":"9 Geonic St Springwood QLD 4127",
    "addr:housenumber":"9",
    "addr:postcode":"4127",
    "addr:street":"Geonic St",
    "iso:country":"AU",
    "sg:address":"9 Geonic St",
    "sg:city":"Springwood",
    "sg:classifiers":[
        {
            "category":"Retail",
            "subcategory":"Auto Repair",
            "type":"Services"
        }
    ],
    "sg:phone":"+61 7 3808 6668",
    "sg:postcode":"4127",
    "sg:province":"QLD",
    "sg:tags":[
        "beater",
        "painter",
        "panel"
    ],
    "wof:name":"Mick Edwards Bodyworks",
    "wof:placetype":"venue"
},
  "geometry": {"coordinates":[153.107955933,-27.6201515198],"type":"Point"}
}