{
  "type": "Feature",
  "properties": {
    "addr:full":"6 Nelson Pl Curtin ACT 2605",
    "addr:housenumber":"6",
    "addr:postcode":"2605",
    "addr:street":"Nelson Pl Curtin",
    "iso:country":"AU",
    "sg:address":"6 Nelson Pl",
    "sg:city":"Curtin",
    "sg:classifiers":[
        {
            "category":"Social Services",
            "type":"Services"
        }
    ],
    "sg:phone":"+61 2 6282 4030",
    "sg:postcode":"2605",
    "sg:province":"ACT",
    "sg:tags":[
        "kinesiology"
    ],
    "wof:name":"Lesley Lee",
    "wof:placetype":"venue"
},
  "geometry": {"coordinates":[149.07618713400001,-35.3273468018],"type":"Point"}
}