{
  "type": "Feature",
  "properties": {
    "iso:country":"AU",
    "sg:address":"Cnr Union & Bull Sts",
    "sg:city":"Newcastle West",
    "sg:classifiers":[
        {
            "category":"Manufacturing",
            "subcategory":"Motor Vehicles & Parts",
            "type":"Manufacturing & Wholesale Goods"
        }
    ],
    "sg:phone":"+61 13 17 23",
    "sg:postcode":"2302",
    "sg:province":"NSW",
    "sg:tags":[
        "replacement"
    ],
    "wof:name":"Natrad",
    "wof:placetype":"venue"
},
  "geometry": {"coordinates":[151.760254,-32.92836],"type":"Point"}
}