{
  "type": "Feature",
  "properties": {
    "iso:country":"AU",
    "sg:address":"310- 314 Lorimer St",
    "sg:city":"Port Melbourne",
    "sg:classifiers":[
        {
            "category":"Retail",
            "subcategory":"Storage",
            "type":"Services"
        }
    ],
    "sg:phone":"+61 3 9645 3349",
    "sg:postcode":"3207",
    "sg:province":"VIC",
    "wof:name":"Port Melbourne Storage Pty Ltd",
    "wof:placetype":"venue"
},
  "geometry": {"coordinates":[144.906586,-37.824718],"type":"Point"}
}