{
  "type": "Feature",
  "properties": {
    "iso:country":"AU",
    "sg:address":"64 Arnisdale Rd",
    "sg:city":"Duncraig",
    "sg:classifiers":[
        {
            "category":"Health Services",
            "subcategory":"Health Practitioner",
            "type":"Services"
        }
    ],
    "sg:phone":"+61 8 9246 4066",
    "sg:postcode":"6023",
    "sg:province":"WA",
    "sg:tags":[
        "physiotherapist"
    ],
    "wof:name":"MTM (Made to Move) Physiotherapy Group",
    "wof:placetype":"venue"
},
  "geometry": {"coordinates":[115.783538818,-31.8349342346],"type":"Point"}
}