{
  "type": "Feature",
  "properties": {
    "iso:country":"AU",
    "sg:address":"39- 41 Minchinton St",
    "sg:city":"Caloundra",
    "sg:classifiers":[
        {
            "category":"Health Services",
            "subcategory":"Doctor",
            "type":"Services"
        }
    ],
    "sg:phone":"+61 7 5491 3987",
    "sg:postcode":"4551",
    "sg:province":"QLD",
    "sg:tags":[
        "podiatrist"
    ],
    "wof:name":"Barry Hawes",
    "wof:placetype":"venue"
},
  "geometry": {"coordinates":[153.13192749000001,-26.8033504486],"type":"Point"}
}