{
  "type": "Feature",
  "properties": {
    "addr:full":"Unit 5/ 339 Liverpool St Darlinghurst NSW 2010",
    "addr:housenumber":"/ 339",
    "addr:postcode":"2010",
    "addr:street":"Liverpool St",
    "iso:country":"AU",
    "sg:address":"Unit 5/ 339 Liverpool St",
    "sg:city":"Darlinghurst",
    "sg:classifiers":[
        {
            "category":"Professional",
            "subcategory":"Art Services",
            "type":"Services"
        }
    ],
    "sg:phone":"+61 2 9361 6525",
    "sg:postcode":"2010",
    "sg:province":"NSW",
    "sg:tags":[
        "graphic",
        "designer"
    ],
    "wof:name":"Young Alexander Design",
    "wof:placetype":"venue"
},
  "geometry": {"coordinates":[151.21873474099999,-33.877986908],"type":"Point"}
}