{
  "type": "Feature",
  "properties": {
    "addr:full":"312 Manns Rd Gosford West NSW 2250",
    "addr:housenumber":"312",
    "addr:postcode":"2250",
    "addr:street":"Manns Rd",
    "iso:country":"AU",
    "sg:address":"312 Manns Rd",
    "sg:city":"Gosford West",
    "sg:classifiers":[
        {
            "category":"Autos & Motor Vehicles",
            "subcategory":"Automobile Sales",
            "type":"Retail Goods"
        }
    ],
    "sg:phone":"+61 2 4336 2244",
    "sg:postcode":"2250",
    "sg:province":"NSW",
    "sg:tags":[
        "car",
        "used"
    ],
    "wof:name":"Auto Group Limited",
    "wof:placetype":"venue"
},
  "geometry": {"coordinates":[151.319381714,-33.4245910645],"type":"Point"}
}