{
  "type": "Feature",
  "properties": {
    "addr:full":"21 Harris St Summerhill TAS 7250",
    "addr:housenumber":"21",
    "addr:postcode":"7250",
    "addr:street":"Harris St",
    "iso:country":"AU",
    "sg:address":"21 Harris St",
    "sg:city":"Summerhill",
    "sg:classifiers":[
        {
            "category":"Education",
            "subcategory":"Dance Studio",
            "type":"Public Place"
        }
    ],
    "sg:phone":"+61 3 6344 6522",
    "sg:postcode":"7250",
    "sg:province":"TAS",
    "sg:tags":[
        "square",
        "caller",
        "dancing"
    ],
    "wof:name":"Launceston Square Dance Club",
    "wof:placetype":"venue"
},
  "geometry": {"coordinates":[147.13229370100001,-41.4632492065],"type":"Point"}
}