{
  "type": "Feature",
  "properties": {
    "addr:full":"Unit 19, 65 Marigold St Revesby NSW 2212",
    "addr:housenumber":"65",
    "addr:postcode":"2212",
    "addr:street":"Marigold St",
    "iso:country":"AU",
    "sg:address":"Unit 19, 65 Marigold St",
    "sg:city":"Revesby",
    "sg:classifiers":[
        {
            "category":"Shopping",
            "subcategory":"Stationery & Office Supplies",
            "type":"Retail Goods"
        }
    ],
    "sg:phone":"+61 2 9792 4475",
    "sg:postcode":"2212",
    "sg:province":"NSW",
    "sg:tags":[
        "packaging",
        "equipment",
        "sealing",
        "filling"
    ],
    "wof:name":"Actionpac",
    "wof:placetype":"venue"
},
  "geometry": {"coordinates":[150.99951200000001,-33.94054],"type":"Point"}
}