{
  "type": "Feature",
  "properties": {
    "addr:full":"Lot 13 Husband Rd Mandurah WA 6210",
    "addr:postcode":"6210",
    "addr:street":"Husband Rd",
    "iso:country":"AU",
    "sg:address":"Lot 13 Husband Rd",
    "sg:city":"Mandurah",
    "sg:classifiers":[
        {
            "category":"Utilities",
            "subcategory":"Electric",
            "type":"Services"
        }
    ],
    "sg:phone":"+61 8 9581 1271",
    "sg:postcode":"6210",
    "sg:province":"WA",
    "sg:tags":[
        "electrical",
        "contractor"
    ],
    "wof:name":"Mandurah Electrical Services Pty Ltd",
    "wof:placetype":"venue"
},
  "geometry": {"coordinates":[115.775993,-32.548286],"type":"Point"}
}