{
  "type": "Feature",
  "properties": {
    "addr:full":"Lot 208 Midwestern Hwy Hay NSW 2711",
    "addr:postcode":"2711",
    "addr:street":"Midwestern Hwy",
    "iso:country":"AU",
    "sg:address":"Lot 208 Midwestern Hwy",
    "sg:city":"Hay",
    "sg:classifiers":[
        {
            "category":"Shopping",
            "type":"Retail Goods"
        }
    ],
    "sg:phone":"+61 2 6993 1007",
    "sg:postcode":"2711",
    "sg:province":"NSW",
    "sg:tags":[
        "agent",
        "stock"
    ],
    "wof:name":"Elders Ltd",
    "wof:placetype":"venue"
},
  "geometry": {"coordinates":[144.843948364,-34.5069885254],"type":"Point"}
}