{
  "type": "Feature",
  "properties": {
    "iso:country":"AU",
    "sg:address":"192 Armstrong St",
    "sg:city":"Colac",
    "sg:classifiers":[
        {
            "category":"Building & Trades",
            "subcategory":"Construction",
            "type":"Services"
        }
    ],
    "sg:phone":"+61 3 5231 4081",
    "sg:postcode":"3250",
    "sg:province":"VIC",
    "sg:tags":[
        "joiner",
        "carpenter"
    ],
    "wof:name":"Neale S M & M L",
    "wof:placetype":"venue"
},
  "geometry": {"coordinates":[143.576874,-38.337788],"type":"Point"}
}