{
  "type": "Feature",
  "properties": {
    "addr:full":"2/ 32 Bentley St Williamstown VIC 3016",
    "addr:housenumber":"/ 32",
    "addr:postcode":"3016",
    "addr:street":"Bentley St",
    "iso:country":"AU",
    "sg:address":"2/ 32 Bentley St",
    "sg:city":"Williamstown",
    "sg:classifiers":[
        {
            "category":"Building & Trades",
            "subcategory":"Construction",
            "type":"Services"
        }
    ],
    "sg:phone":"+61 3 8742 7781",
    "sg:postcode":"3016",
    "sg:province":"VIC",
    "sg:tags":[
        "window",
        "aluminium"
    ],
    "wof:name":"Australian Aluminium Windows",
    "wof:placetype":"venue"
},
  "geometry": {"coordinates":[144.86041259800001,-37.8509559631],"type":"Point"}
}