{
  "type": "Feature",
  "properties": {
    "iso:country":"AU",
    "sg:address":"118 Main Rd",
    "sg:city":"Lower Plenty",
    "sg:classifiers":[
        {
            "category":"Health Services",
            "subcategory":"Health Practitioner",
            "type":"Services"
        }
    ],
    "sg:phone":"+61 3 9434 3742",
    "sg:postcode":"3093",
    "sg:province":"VIC",
    "sg:tags":[
        "physiotherapist"
    ],
    "wof:name":"Kirsten Woods",
    "wof:placetype":"venue"
},
  "geometry": {"coordinates":[145.11424255399999,-37.726726532],"type":"Point"}
}