{
  "type": "Feature",
  "properties": {
    "addr:full":"186 Musgrave St North Rockhampton QLD 4701",
    "addr:housenumber":"186",
    "addr:postcode":"4701",
    "addr:street":"Musgrave St North",
    "iso:country":"AU",
    "sg:address":"186 Musgrave St",
    "sg:city":"North Rockhampton",
    "sg:classifiers":[
        {
            "category":"Professional",
            "subcategory":"Employment Agencies",
            "type":"Services"
        }
    ],
    "sg:phone":"+61 7 4922 5400",
    "sg:postcode":"4701",
    "sg:province":"QLD",
    "wof:name":"Minniecon & Burke Pty Ltd",
    "wof:placetype":"venue"
},
  "geometry": {"coordinates":[150.523193359,-23.3618450165],"type":"Point"}
}