{
  "type": "Feature",
  "properties": {
    "addr:full":"236 Gertrude St Fitzroy VIC 3065",
    "addr:housenumber":"236",
    "addr:postcode":"3065",
    "addr:street":"Gertrude St",
    "iso:country":"AU",
    "sg:address":"236 Gertrude St",
    "sg:city":"Fitzroy",
    "sg:classifiers":[
        {
            "category":"Shopping",
            "subcategory":"Music",
            "type":"Retail Goods"
        }
    ],
    "sg:phone":"+61 3 9417 7557",
    "sg:postcode":"3065",
    "sg:province":"VIC",
    "sg:tags":[
        "store"
    ],
    "wof:name":"Northside Records",
    "wof:placetype":"venue"
},
  "geometry": {"coordinates":[144.982620239,-37.806438446],"type":"Point"}
}