{
  "type": "Feature",
  "properties": {
    "addr:full":"531 Macauley St Albury NSW 2640",
    "addr:housenumber":"531",
    "addr:postcode":"2640",
    "addr:street":"Macauley St",
    "iso:country":"AU",
    "sg:address":"531 Macauley St",
    "sg:city":"Albury",
    "sg:classifiers":[
        {
            "category":"Banks & Credit Unions",
            "subcategory":"Financial Services",
            "type":"Services"
        }
    ],
    "sg:phone":"+61 2 6021 7000",
    "sg:postcode":"2640",
    "sg:province":"NSW",
    "sg:tags":[
        "advisory",
        "planning",
        "retirement"
    ],
    "wof:name":"PY Financial Services",
    "wof:placetype":"venue"
},
  "geometry": {"coordinates":[146.92222595199999,-36.0798797607],"type":"Point"}
}