{
  "type": "Feature",
  "properties": {
    "iso:country":"AU",
    "sg:address":"43 Hay St",
    "sg:city":"Cootamundra",
    "sg:classifiers":[
        {
            "category":"Personal",
            "subcategory":"Massage",
            "type":"Services"
        }
    ],
    "sg:phone":"+61 2 6942 1447",
    "sg:postcode":"2590",
    "sg:province":"NSW",
    "sg:tags":[
        "therapy"
    ],
    "wof:name":"Stephen Dunsmore Massage Therapy",
    "wof:placetype":"venue"
},
  "geometry": {"coordinates":[148.026885986,-34.631893158],"type":"Point"}
}