{
  "type": "Feature",
  "properties": {
    "addr:full":"4 Desert Ash Pl Helena Valley WA 6056",
    "addr:housenumber":"4",
    "addr:postcode":"6056",
    "addr:street":"Desert Ash Pl Helena",
    "iso:country":"AU",
    "sg:address":"4 Desert Ash Pl",
    "sg:city":"Helena Valley",
    "sg:classifiers":[
        {
            "category":"Shopping",
            "subcategory":"Party Supplies",
            "type":"Retail Goods"
        }
    ],
    "sg:phone":"+61 419 831 597",
    "sg:postcode":"6056",
    "sg:province":"WA",
    "sg:tags":[
        "hire",
        "costume"
    ],
    "wof:name":"A Wackyshak Fancy Dress",
    "wof:placetype":"venue"
},
  "geometry": {"coordinates":[116.03517150899999,-31.9130516052],"type":"Point"}
}