{
  "type": "Feature",
  "properties": {
    "addr:full":"46 Peppertree St Kirwan QLD 4817",
    "addr:housenumber":"46",
    "addr:postcode":"4817",
    "addr:street":"Peppertree St",
    "iso:country":"AU",
    "sg:address":"46 Peppertree St",
    "sg:city":"Kirwan",
    "sg:classifiers":[
        {
            "category":"Building & Trades",
            "subcategory":"Equipment Rental",
            "type":"Services"
        }
    ],
    "sg:phone":"+61 7 4723 5080",
    "sg:postcode":"4817",
    "sg:province":"QLD",
    "sg:tags":[
        "party",
        "hire"
    ],
    "wof:name":"O&#039;grady Michael",
    "wof:placetype":"venue"
},
  "geometry": {"coordinates":[146.72283899999999,-19.302906],"type":"Point"}
}