{
  "type": "Feature",
  "properties": {
    "iso:country":"AU",
    "sg:address":"15 Quarry St",
    "sg:city":"Fremantle",
    "sg:classifiers":[
        {
            "category":"Shopping",
            "subcategory":"Party Supplies",
            "type":"Retail Goods"
        }
    ],
    "sg:phone":"+61 8 9432 9500",
    "sg:postcode":"6160",
    "sg:province":"WA",
    "sg:tags":[
        "children's"
    ],
    "wof:name":"Buster The Fun Bus",
    "wof:placetype":"venue"
},
  "geometry": {"coordinates":[115.750938,-32.049431],"type":"Point"}
}