{
  "type": "Feature",
  "properties": {
    "addr:full":"137 Cathedral Ave Geraldton WA 6530",
    "addr:housenumber":"137",
    "addr:postcode":"6530",
    "addr:street":"Cathedral Ave",
    "iso:country":"AU",
    "sg:address":"137 Cathedral Ave",
    "sg:city":"Geraldton",
    "sg:classifiers":[
        {
            "category":"Travel",
            "subcategory":"Hotels & Motels",
            "type":"Entertainment"
        }
    ],
    "sg:phone":"+61 8 9921 6111",
    "sg:postcode":"6530",
    "sg:province":"WA",
    "wof:name":"Sun City Accommodation",
    "wof:placetype":"venue"
},
  "geometry": {"coordinates":[114.615097046,-28.7822914124],"type":"Point"}
}