{
  "type": "Feature",
  "properties": {
    "addr:full":"202 Baylis St Wagga Wagga NSW 2650",
    "addr:housenumber":"202",
    "addr:postcode":"2650",
    "addr:street":"Baylis St",
    "iso:country":"AU",
    "sg:address":"202 Baylis St",
    "sg:city":"Wagga Wagga",
    "sg:classifiers":[
        {
            "category":"Shopping",
            "subcategory":"Clothing, Apparel, & Fashions",
            "type":"Retail Goods"
        }
    ],
    "sg:phone":"+61 2 6921 8053",
    "sg:postcode":"2650",
    "sg:province":"NSW",
    "sg:tags":[
        "boutique"
    ],
    "wof:name":"Risky Business Fashion Boutique",
    "wof:placetype":"venue"
},
  "geometry": {"coordinates":[147.37008667000001,-35.1113357544],"type":"Point"}
}