{
  "type": "Feature",
  "properties": {
    "iso:country":"AU",
    "sg:address":"Ryan Rd",
    "sg:city":"Lake Magenta",
    "sg:classifiers":[
        {
            "category":"Farming",
            "subcategory":"Farm",
            "type":"Manufacturing & Wholesale Goods"
        }
    ],
    "sg:phone":"+61 8 9872 0057",
    "sg:postcode":"6355",
    "sg:province":"WA",
    "sg:tags":[
        "farmer"
    ],
    "wof:name":"Hams K J & H D",
    "wof:placetype":"venue"
},
  "geometry": {"coordinates":[119.27346799999999,-33.491444],"type":"Point"}
}