{
  "type": "Feature",
  "properties": {
    "addr:full":"278 Charters Towers Rd Hermit Park QLD 4812",
    "addr:housenumber":"278",
    "addr:postcode":"4812",
    "addr:street":"Charters Towers Rd",
    "iso:country":"AU",
    "sg:address":"278 Charters Towers Rd",
    "sg:city":"Hermit Park",
    "sg:classifiers":[
        {
            "category":"Personal",
            "subcategory":"Beauty Salon",
            "type":"Services"
        }
    ],
    "sg:phone":"+61 7 4775 2443",
    "sg:postcode":"4812",
    "sg:province":"QLD",
    "wof:name":"Mandys Beautylicious",
    "wof:placetype":"venue"
},
  "geometry": {"coordinates":[146.79631000000001,-19.29047],"type":"Point"}
}