{
  "type": "Feature",
  "properties": {
    "addr:full":"5 Shirley St Padstow NSW 2211",
    "addr:housenumber":"5",
    "addr:postcode":"2211",
    "addr:street":"Shirley St",
    "iso:country":"AU",
    "sg:address":"5 Shirley St",
    "sg:city":"Padstow",
    "sg:classifiers":[
        {
            "category":"Building & Trades",
            "subcategory":"Construction",
            "type":"Services"
        }
    ],
    "sg:phone":"+61 2 9774 2838",
    "sg:postcode":"2211",
    "sg:province":"NSW",
    "sg:tags":[
        "contractor"
    ],
    "wof:name":"Neale R",
    "wof:placetype":"venue"
},
  "geometry": {"coordinates":[151.02264400000001,-33.95565],"type":"Point"}
}