{
  "type": "Feature",
  "properties": {
    "addr:full":"3/ 9 Ohea St Coburg VIC 3058",
    "addr:housenumber":"/ 9",
    "addr:postcode":"3058",
    "addr:street":"Ohea St",
    "iso:country":"AU",
    "sg:address":"3/ 9 Ohea St",
    "sg:city":"Coburg",
    "sg:classifiers":[
        {
            "category":"Manufacturing",
            "subcategory":"Textiles",
            "type":"Manufacturing & Wholesale Goods"
        }
    ],
    "sg:phone":"+61 3 9318 2000",
    "sg:postcode":"3058",
    "sg:province":"VIC",
    "sg:tags":[
        "agent"
    ],
    "wof:name":"Texlinc Pty Ltd",
    "wof:placetype":"venue"
},
  "geometry": {"coordinates":[144.965576172,-37.7377204895],"type":"Point"}
}