{
  "type": "Feature",
  "properties": {
    "addr:full":"The Dome Suite 1 & 2, 134 Victoria St Mackay QLD 4740",
    "addr:housenumber":"&;134",
    "addr:postcode":"4740",
    "addr:street":"Victoria St",
    "iso:country":"AU",
    "sg:address":"The Dome Suite 1 & 2, 134 Victoria St",
    "sg:city":"Mackay",
    "sg:classifiers":[
        {
            "category":"Government",
            "subcategory":"Customs House",
            "type":"Public Place"
        }
    ],
    "sg:phone":"+61 7 4957 9544",
    "sg:postcode":"4740",
    "sg:province":"QLD",
    "sg:tags":[
        "title",
        "management",
        "stratum"
    ],
    "wof:name":"Body Corporate Services",
    "wof:placetype":"venue"
},
  "geometry": {"coordinates":[149.185226,-21.140928],"type":"Point"}
}