{
  "type": "Feature",
  "properties": {
    "addr:full":"7 Butler Ave Swanbourne WA 6010",
    "addr:housenumber":"7",
    "addr:postcode":"6010",
    "addr:street":"Butler Ave",
    "iso:country":"AU",
    "sg:address":"7 Butler Ave",
    "sg:city":"Swanbourne",
    "sg:classifiers":[
        {
            "category":"Real Estate",
            "subcategory":"Architect",
            "type":"Services"
        }
    ],
    "sg:phone":"+61 8 9384 1085",
    "sg:postcode":"6010",
    "sg:province":"WA",
    "wof:name":"Mellor Architects",
    "wof:placetype":"venue"
},
  "geometry": {"coordinates":[115.77262878400001,-31.9709224701],"type":"Point"}
}