{
  "type": "Feature",
  "properties": {
    "iso:country":"AU",
    "sg:address":"443 Auburn Rd",
    "sg:city":"Hawthorn",
    "sg:classifiers":[
        {
            "category":"Travel",
            "subcategory":"Resort",
            "type":"Entertainment"
        }
    ],
    "sg:phone":"+61 3 8831 8833",
    "sg:postcode":"3122",
    "sg:province":"VIC",
    "sg:tags":[
        "consultant",
        "timesharing"
    ],
    "wof:name":"Trendwest South Pacific Pty Ltd",
    "wof:placetype":"venue"
},
  "geometry": {"coordinates":[145.04179382300001,-37.8392219543],"type":"Point"}
}