{
  "type": "Feature",
  "properties": {
    "iso:country":"AU",
    "sg:address":"288 Oxford St",
    "sg:city":"Paddington",
    "sg:classifiers":[
        {
            "category":"Restaurant",
            "type":"Food & Drink"
        }
    ],
    "sg:phone":"+61 2 9331 7886",
    "sg:postcode":"2021",
    "sg:province":"NSW",
    "wof:name":"Anastasia's Restaurant",
    "wof:placetype":"venue"
},
  "geometry": {"coordinates":[151.22810363799999,-33.8852844238],"type":"Point"}
}