{
  "type": "Feature",
  "properties": {
    "iso:country":"AU",
    "sg:address":"Corner Wharf & Sheridan Sts",
    "sg:city":"Cairns",
    "sg:classifiers":[
        {
            "category":"Conference Center",
            "type":"Public Place"
        }
    ],
    "sg:phone":"+61 7 4042 4200",
    "sg:postcode":"4870",
    "sg:province":"QLD",
    "sg:tags":[
        "venue",
        "convention"
    ],
    "sg:website":"http://www.cairnsconvention.com.au",
    "wof:name":"Cairns Convention Centre",
    "wof:placetype":"venue"
},
  "geometry": {"coordinates":[145.77784729000001,-16.929069519],"type":"Point"}
}