{
  "type": "Feature",
  "properties": {
    "addr:full":"356 Hunter St Newcastle NSW 2300",
    "addr:housenumber":"356",
    "addr:postcode":"2300",
    "addr:street":"Hunter St",
    "iso:country":"AU",
    "sg:address":"356 Hunter St",
    "sg:city":"Newcastle",
    "sg:classifiers":[
        {
            "category":"Sports & Exercise",
            "subcategory":"Ski Slope",
            "type":"Entertainment"
        }
    ],
    "sg:phone":"+61 2 4969 5100",
    "sg:postcode":"2300",
    "sg:province":"NSW",
    "sg:tags":[
        "equipment",
        "hire",
        "retail",
        "snow"
    ],
    "wof:name":"ESS Boardstore",
    "wof:placetype":"venue"
},
  "geometry": {"coordinates":[151.77470400000001,-32.926575],"type":"Point"}
}