{
  "type": "Feature",
  "properties": {
    "addr:full":"Harris Rd Ventnor VIC 3922",
    "addr:postcode":"3922",
    "addr:street":"Harris Rd",
    "iso:country":"AU",
    "sg:address":"Harris Rd",
    "sg:city":"Ventnor",
    "sg:classifiers":[
        {
            "category":"Building & Trades",
            "subcategory":"Construction",
            "type":"Services"
        }
    ],
    "sg:phone":"+61 3 5956 8219",
    "sg:postcode":"3922",
    "sg:province":"VIC",
    "sg:tags":[
        "joiner",
        "carpenter"
    ],
    "wof:name":"Garforth R J",
    "wof:placetype":"venue"
},
  "geometry": {"coordinates":[145.17768859899999,-38.4646034241],"type":"Point"}
}