{
  "type": "Feature",
  "properties": {
    "iso:country":"AU",
    "sg:address":"349 Boston Rd",
    "sg:city":"Belmont",
    "sg:classifiers":[
        {
            "category":"Utilities",
            "subcategory":"Electric",
            "type":"Services"
        }
    ],
    "sg:phone":"+61 7 3348 9860",
    "sg:postcode":"4153",
    "sg:province":"QLD",
    "sg:tags":[
        "electrical",
        "contractor"
    ],
    "wof:name":"Reliant Data & Electrical Solutions",
    "wof:placetype":"venue"
},
  "geometry": {"coordinates":[153.14549255399999,-27.5050582886],"type":"Point"}
}