{
  "type": "Feature",
  "properties": {
    "addr:full":"Cnr Antill St & Federal Hwy Watson ACT 2602",
    "addr:postcode":"2602",
    "addr:street":"Cnr Antill St & Federal Hwy",
    "iso:country":"AU",
    "sg:address":"Cnr Antill St & Federal Hwy",
    "sg:city":"Watson",
    "sg:classifiers":[
        {
            "category":"Autos & Motor Vehicles",
            "subcategory":"Fuel & Gas Station",
            "type":"Retail Goods"
        }
    ],
    "sg:phone":"+61 2 6242 7624",
    "sg:postcode":"2602",
    "sg:province":"ACT",
    "wof:name":"Ampol Limited",
    "wof:placetype":"venue"
},
  "geometry": {"coordinates":[149.161651611,-35.2425994873],"type":"Point"}
}