{
  "type": "Feature",
  "properties": {
    "addr:full":"57 Young Rd Baldivis WA 6171",
    "addr:housenumber":"57",
    "addr:postcode":"6171",
    "addr:street":"Young Rd",
    "iso:country":"AU",
    "sg:address":"57 Young Rd",
    "sg:city":"Baldivis",
    "sg:classifiers":[
        {
            "category":"Building & Trades",
            "subcategory":"Plumbing",
            "type":"Services"
        }
    ],
    "sg:phone":"+61 8 9524 3000",
    "sg:postcode":"6171",
    "sg:province":"WA",
    "sg:tags":[
        "drainers"
    ],
    "wof:name":"G & O Drainage Pty Ltd",
    "wof:placetype":"venue"
},
  "geometry": {"coordinates":[115.83998099999999,-32.338005],"type":"Point"}
}