{
  "type": "Feature",
  "properties": {
    "iso:country":"AU",
    "sg:address":"146 Evans St",
    "sg:city":"Port Melbourne",
    "sg:classifiers":[
        {
            "category":"Travel",
            "subcategory":"Hotels & Motels",
            "type":"Entertainment"
        }
    ],
    "sg:phone":"+61 3 9646 1991",
    "sg:postcode":"3207",
    "sg:province":"VIC",
    "sg:tags":[
        "accommodation"
    ],
    "wof:name":"Albion Hotel Port Melbourne",
    "wof:placetype":"venue"
},
  "geometry": {"coordinates":[144.943344,-37.832588],"type":"Point"}
}