{
  "type": "Feature",
  "properties": {
    "addr:full":"Units 3 & 4/ 124 Winton Rd Joondalup WA 6027",
    "addr:housenumber":"units 3 & 4 / 124",
    "addr:postcode":"6027",
    "addr:street":"Winton Rd",
    "iso:country":"AU",
    "sg:address":"Units 3 & 4/ 124 Winton Rd",
    "sg:city":"Joondalup",
    "sg:classifiers":[
        {
            "category":"Home & Garden",
            "subcategory":"Furniture",
            "type":"Retail Goods"
        }
    ],
    "sg:phone":"+61 8 9300 1717",
    "sg:postcode":"6027",
    "sg:province":"WA",
    "sg:tags":[
        "business"
    ],
    "wof:name":"Joondalup Stationery & Office Supplies",
    "wof:placetype":"venue"
},
  "geometry": {"coordinates":[115.75971984900001,-31.7410583496],"type":"Point"}
}