{
  "type": "Feature",
  "properties": {
    "addr:full":"1st Floor 186a Pulteney St Adelaide SA 5000",
    "addr:housenumber":"186a",
    "addr:postcode":"5000",
    "addr:street":"Pulteney St",
    "iso:country":"AU",
    "sg:address":"1st Floor 186a Pulteney St",
    "sg:city":"Adelaide",
    "sg:classifiers":[
        {
            "category":"Education",
            "subcategory":"Junior College",
            "type":"Public Place"
        }
    ],
    "sg:phone":"+61 8 8223 3233",
    "sg:postcode":"5000",
    "sg:province":"SA",
    "sg:tags":[
        "make-up"
    ],
    "wof:name":"Media Makeup Academy",
    "wof:placetype":"venue"
},
  "geometry": {"coordinates":[138.606002808,-34.9260139465],"type":"Point"}
}