{
  "type": "Feature",
  "properties": {
    "iso:country":"AU",
    "sg:address":"190 Rileys Hill Rd",
    "sg:city":"Broadwater",
    "sg:classifiers":[
        {
            "category":"Food & Beverages",
            "subcategory":"Groceries & Convenience Stores",
            "type":"Retail Goods"
        }
    ],
    "sg:phone":"+61 2 6682 8125",
    "sg:postcode":"2472",
    "sg:province":"NSW",
    "sg:tags":[
        "merchant",
        "egg"
    ],
    "wof:name":"Rugged Beginnings",
    "wof:placetype":"venue"
},
  "geometry": {"coordinates":[153.42523193400001,-29.0190868378],"type":"Point"}
}