{
  "type": "Feature",
  "properties": {
    "addr:full":"10 Moonbi St Brendale QLD 4500",
    "addr:housenumber":"10",
    "addr:postcode":"4500",
    "addr:street":"Moonbi St",
    "iso:country":"AU",
    "sg:address":"10 Moonbi St",
    "sg:city":"Brendale",
    "sg:classifiers":[
        {
            "category":"Building & Trades",
            "subcategory":"Cleaning & Sanitation",
            "type":"Services"
        }
    ],
    "sg:phone":"+61 7 3480 6000",
    "sg:postcode":"4500",
    "sg:province":"QLD",
    "sg:tags":[
        "sweeping",
        "machine"
    ],
    "wof:name":"MacDonald Johnston Engineering Co. Pty Ltd",
    "wof:placetype":"venue"
},
  "geometry": {"coordinates":[152.989303589,-27.3226852417],"type":"Point"}
}