{
  "type": "Feature",
  "properties": {
    "iso:country":"AU",
    "sg:address":"Shop 3/ 1a Thabeban St",
    "sg:city":"Bundaberg",
    "sg:classifiers":[
        {
            "category":"Food & Beverages",
            "subcategory":"Bakery",
            "type":"Retail Goods"
        }
    ],
    "sg:phone":"+61 7 4153 1266",
    "sg:postcode":"4670",
    "sg:province":"QLD",
    "sg:tags":[
        "cake",
        "shop",
        "pastry"
    ],
    "wof:name":"Fresh Fields Bakery",
    "wof:placetype":"venue"
},
  "geometry": {"coordinates":[152.35969543499999,-24.8918914795],"type":"Point"}
}