{
  "type": "Feature",
  "properties": {
    "addr:full":"6 King St Claremont WA 6010",
    "addr:housenumber":"6",
    "addr:postcode":"6010",
    "addr:street":"King St",
    "iso:country":"AU",
    "sg:address":"6 King St",
    "sg:city":"Claremont",
    "sg:classifiers":[
        {
            "category":"Manufacturing",
            "subcategory":"Jewelry",
            "type":"Manufacturing & Wholesale Goods"
        }
    ],
    "sg:phone":"+61 8 9384 1570",
    "sg:postcode":"6010",
    "sg:province":"WA",
    "sg:tags":[
        "mfrg",
        "jeweller"
    ],
    "wof:name":"Robertson Andrew",
    "wof:placetype":"venue"
},
  "geometry": {"coordinates":[115.788719177,-31.9854946136],"type":"Point"}
}