{
  "type": "Feature",
  "properties": {
    "addr:full":"161 Railway Crs Lisarow NSW 2250",
    "addr:housenumber":"161",
    "addr:postcode":"2250",
    "addr:street":"Railway Crs",
    "iso:country":"AU",
    "sg:address":"161 Railway Crs",
    "sg:city":"Lisarow",
    "sg:classifiers":[
        {
            "category":"Shopping",
            "subcategory":"Gifts & Souvenirs",
            "type":"Retail Goods"
        }
    ],
    "sg:phone":"+61 2 4329 3944",
    "sg:postcode":"2250",
    "sg:province":"NSW",
    "sg:tags":[
        "print",
        "poster",
        "pictures"
    ],
    "wof:name":"Koala Posters Publishing Pty Ltd",
    "wof:placetype":"venue"
},
  "geometry": {"coordinates":[151.306030273,-33.4976272583],"type":"Point"}
}