{
  "type": "Feature",
  "properties": {
    "iso:country":"AU",
    "sg:address":"16 Keys Rd",
    "sg:city":"Lower Mitcham",
    "sg:classifiers":[
        {
            "category":"Health Services",
            "subcategory":"Chiropractor",
            "type":"Services"
        }
    ],
    "sg:phone":"+61 8 8357 3829",
    "sg:postcode":"5062",
    "sg:province":"SA",
    "wof:name":"Yvan V. Tooth Dr",
    "wof:placetype":"venue"
},
  "geometry": {"coordinates":[138.60467529300001,-34.9782752991],"type":"Point"}
}