{
  "type": "Feature",
  "properties": {
    "addr:full":"Lot 2, MacPeak Crs Smithfield(Cairns) QLD 4878",
    "addr:postcode":"4878",
    "addr:street":"Crs",
    "iso:country":"AU",
    "sg:address":"Lot 2, MacPeak Crs",
    "sg:city":"Smithfield(Cairns)",
    "sg:classifiers":[
        {
            "category":"Banks & Credit Unions",
            "subcategory":"Bureau De Change",
            "type":"Services"
        }
    ],
    "sg:phone":"+61 7 4055 6981",
    "sg:postcode":"4878",
    "sg:province":"QLD",
    "sg:tags":[
        "repairs",
        "part",
        "appliance",
        "electrical"
    ],
    "wof:name":"Affordable Electrics",
    "wof:placetype":"venue"
},
  "geometry": {"coordinates":[145.73231506400001,-16.9370746613],"type":"Point"}
}