{
  "type": "Feature",
  "properties": {
    "addr:full":"PO Box 9219 Brighton VIC 3186",
    "addr:postcode":"3186",
    "iso:country":"AU",
    "sg:address":"PO Box 9219",
    "sg:city":"Brighton",
    "sg:classifiers":[
        {
            "category":"Military Area",
            "subcategory":"Army Base",
            "type":"Public Place"
        }
    ],
    "sg:phone":"+61 3 9580 1412",
    "sg:postcode":"3186",
    "sg:province":"VIC",
    "sg:tags":[
        "concrete",
        "slab",
        "floor"
    ],
    "wof:name":"A & J Concreting",
    "wof:placetype":"venue"
},
  "geometry": {"coordinates":[144.99830627399999,-37.9100990295],"type":"Point"}
}