{
  "type": "Feature",
  "properties": {
    "iso:country":"AU",
    "sg:address":"22 Earl St",
    "sg:city":"Coffs Harbour",
    "sg:classifiers":[
        {
            "category":"Social Services",
            "subcategory":"Adult Care",
            "type":"Services"
        }
    ],
    "sg:phone":"+61 2 6652 8725",
    "sg:postcode":"2450",
    "sg:province":"NSW",
    "sg:tags":[
        "aged"
    ],
    "wof:name":"Coffs Harbour Home Modification",
    "wof:placetype":"venue"
},
  "geometry": {"coordinates":[153.11747700000001,-30.299807],"type":"Point"}
}