{
  "type": "Feature",
  "properties": {
    "iso:country":"AU",
    "sg:address":"Unit 9/ 10-14 Lilian Fowler Pl",
    "sg:city":"Marrickville",
    "sg:classifiers":[
        {
            "category":"Professional",
            "subcategory":"Business Services",
            "type":"Services"
        }
    ],
    "sg:phone":"+61 2 9516 2744",
    "sg:postcode":"2204",
    "sg:province":"NSW",
    "sg:tags":[
        "exporter"
    ],
    "wof:name":"JD's Seafood Export Contractors Pty Limited",
    "wof:placetype":"venue"
},
  "geometry": {"coordinates":[151.168747,-33.909847],"type":"Point"}
}