{
  "type": "Feature",
  "properties": {
    "addr:full":"77 Wirraglen Rd Highfields QLD 4352",
    "addr:housenumber":"77",
    "addr:postcode":"4352",
    "addr:street":"Wirraglen Rd",
    "iso:country":"AU",
    "sg:address":"77 Wirraglen Rd",
    "sg:city":"Highfields",
    "sg:classifiers":[
        {
            "category":"Communications",
            "subcategory":"News Services",
            "type":"Services"
        }
    ],
    "sg:phone":"+61 7 4696 6309",
    "sg:postcode":"4352",
    "sg:province":"QLD",
    "sg:tags":[
        "information",
        "tourist",
        "attractions"
    ],
    "wof:name":"Highfields Pioneer Village",
    "wof:placetype":"venue"
},
  "geometry": {"coordinates":[151.954926,-27.442541],"type":"Point"}
}