{
  "type": "Feature",
  "properties": {
    "addr:full":"PO Box 37 Bute SA 5560",
    "addr:postcode":"5560",
    "iso:country":"AU",
    "sg:address":"PO Box 37",
    "sg:city":"Bute",
    "sg:classifiers":[
        {
            "category":"Farming",
            "subcategory":"Farm",
            "type":"Manufacturing & Wholesale Goods"
        }
    ],
    "sg:phone":"+61 8 8826 2093",
    "sg:postcode":"5560",
    "sg:province":"SA",
    "sg:tags":[
        "farmer"
    ],
    "wof:name":"Axford John & A L",
    "wof:placetype":"venue"
},
  "geometry": {"coordinates":[138.00987243599999,-33.8648796082],"type":"Point"}
}