{
  "type": "Feature",
  "properties": {
    "addr:full":"16 French St Netherby SA 5062",
    "addr:housenumber":"16",
    "addr:postcode":"5062",
    "addr:street":"French St",
    "iso:country":"AU",
    "sg:address":"16 French St",
    "sg:city":"Netherby",
    "sg:classifiers":[
        {
            "category":"Building & Trades",
            "subcategory":"Cleaning & Sanitation",
            "type":"Services"
        }
    ],
    "sg:phone":"+61 8 8272 3172",
    "sg:postcode":"5062",
    "sg:province":"SA",
    "sg:tags":[
        "window"
    ],
    "wof:name":"Higham R J & L A",
    "wof:placetype":"venue"
},
  "geometry": {"coordinates":[138.62518310600001,-34.9719429016],"type":"Point"}
}