{
  "type": "Feature",
  "properties": {
    "addr:full":"1 Caprella St Heathridge WA 6027",
    "addr:housenumber":"1",
    "addr:postcode":"6027",
    "addr:street":"Caprella St",
    "iso:country":"AU",
    "sg:address":"1 Caprella St",
    "sg:city":"Heathridge",
    "sg:classifiers":[
        {
            "category":"Utilities",
            "type":"Services"
        }
    ],
    "sg:phone":"+61 409 297 147",
    "sg:postcode":"6027",
    "sg:province":"WA",
    "sg:tags":[
        "refrigeration",
        "industrial",
        "commercial",
        "retail"
    ],
    "wof:name":"Tad's Refrigeration & Airconditioning Service",
    "wof:placetype":"venue"
},
  "geometry": {"coordinates":[115.77127075200001,-31.7661476135],"type":"Point"}
}