{
  "type": "Feature",
  "properties": {
    "addr:full":"215 Whitehorse Rd Blackburn VIC 3130",
    "addr:housenumber":"215",
    "addr:postcode":"3130",
    "addr:street":"Whitehorse Rd",
    "iso:country":"AU",
    "sg:address":"215 Whitehorse Rd",
    "sg:city":"Blackburn",
    "sg:classifiers":[
        {
            "category":"Health Services",
            "subcategory":"Dentist",
            "type":"Services"
        }
    ],
    "sg:phone":"+61 3 9878 9227",
    "sg:postcode":"3130",
    "sg:province":"VIC",
    "wof:name":"Brown Maxwell",
    "wof:placetype":"venue"
},
  "geometry": {"coordinates":[145.16012573200001,-37.8177680969],"type":"Point"}
}