{
  "type": "Feature",
  "properties": {
    "addr:full":"104, 68 Alexander St Crows Nest NSW 2065",
    "addr:housenumber":"68",
    "addr:postcode":"104;2065",
    "addr:street":"Alexander St",
    "iso:country":"AU",
    "sg:address":"104, 68 Alexander St",
    "sg:city":"Crows Nest",
    "sg:classifiers":[
        {
            "category":"Shopping",
            "subcategory":"Computers & Home Electronics",
            "type":"Retail Goods"
        }
    ],
    "sg:phone":"+61 2 9966 5266",
    "sg:postcode":"2065",
    "sg:province":"NSW",
    "sg:tags":[
        "hardware",
        "equipment"
    ],
    "wof:name":"Memory Masters",
    "wof:placetype":"venue"
},
  "geometry": {"coordinates":[151.202102661,-33.8262290955],"type":"Point"}
}