{
  "type": "Feature",
  "properties": {
    "addr:full":"Shp8/ 39 Truman Ave Cromer NSW 2099",
    "addr:housenumber":"39",
    "addr:postcode":"2099",
    "addr:street":"Truman Ave",
    "iso:country":"AU",
    "sg:address":"Shp8/ 39 Truman Ave",
    "sg:city":"Cromer",
    "sg:classifiers":[
        {
            "category":"Fast Food",
            "type":"Food & Drink"
        }
    ],
    "sg:phone":"+61 2 9982 4149",
    "sg:postcode":"2099",
    "sg:province":"NSW",
    "sg:tags":[
        "away",
        "take"
    ],
    "wof:name":"Cromer Pizza",
    "wof:placetype":"venue"
},
  "geometry": {"coordinates":[151.26445007300001,-33.7347106934],"type":"Point"}
}