{
  "type": "Feature",
  "properties": {
    "addr:full":"U107/ 45 Gilby St Mt Waverley VIC 3149",
    "addr:housenumber":"u107 / 45",
    "addr:postcode":"3149",
    "addr:street":"Gilby St Mt",
    "iso:country":"AU",
    "sg:address":"U107/ 45 Gilby St",
    "sg:city":"Mt Waverley",
    "sg:classifiers":[
        {
            "category":"Home & Garden",
            "subcategory":"Building Materials",
            "type":"Retail Goods"
        }
    ],
    "sg:phone":"+61 3 9544 0001",
    "sg:postcode":"3149",
    "sg:province":"VIC",
    "sg:tags":[
        "plaster",
        "plasterboard",
        "supply"
    ],
    "wof:name":"South East Plasterboard Supplies (VIC) Pty Ltd",
    "wof:placetype":"venue"
},
  "geometry": {"coordinates":[145.13731384299999,-37.8984413147],"type":"Point"}
}