{
  "type": "Feature",
  "properties": {
    "addr:full":"190 Merrivale Drv Warrnambool VIC 3280",
    "addr:housenumber":"190",
    "addr:postcode":"3280",
    "addr:street":"Merrivale Drv",
    "iso:country":"AU",
    "sg:address":"190 Merrivale Drv",
    "sg:city":"Warrnambool",
    "sg:classifiers":[
        {
            "category":"Building & Trades",
            "subcategory":"Construction",
            "type":"Services"
        }
    ],
    "sg:phone":"+61 3 5562 0783",
    "sg:postcode":"3280",
    "sg:province":"VIC",
    "sg:tags":[
        "excavation",
        "foundation"
    ],
    "wof:name":"Gladman D J & G A",
    "wof:placetype":"venue"
},
  "geometry": {"coordinates":[142.45428466800001,-38.3769035339],"type":"Point"}
}