{
  "type": "Feature",
  "properties": {
    "addr:full":"73 Belgravia St Belmont WA 6104",
    "addr:housenumber":"73",
    "addr:postcode":"6104",
    "addr:street":"Belgravia St",
    "iso:country":"AU",
    "sg:address":"73 Belgravia St",
    "sg:city":"Belmont",
    "sg:classifiers":[
        {
            "category":"Autos & Motor Vehicles",
            "subcategory":"Auto Supplies",
            "type":"Retail Goods"
        }
    ],
    "sg:phone":"+61 8 9479 4997",
    "sg:postcode":"6104",
    "sg:province":"WA",
    "sg:tags":[
        "automotive",
        "stereo",
        "radio"
    ],
    "wof:name":"Allcom Audio",
    "wof:placetype":"venue"
},
  "geometry": {"coordinates":[115.928230286,-31.9481639862],"type":"Point"}
}