{
  "type": "Feature",
  "properties": {
    "addr:full":"910 Barrenjoey Rd Palm Beach NSW 2108",
    "addr:housenumber":"910",
    "addr:postcode":"2108",
    "addr:street":"Barrenjoey Rd",
    "iso:country":"AU",
    "sg:address":"910 Barrenjoey Rd",
    "sg:city":"Palm Beach",
    "sg:classifiers":[
        {
            "category":"Professional",
            "subcategory":"Art Services",
            "type":"Services"
        }
    ],
    "sg:phone":"+61 2 9974 4849",
    "sg:postcode":"2108",
    "sg:province":"NSW",
    "sg:tags":[
        "decorator",
        "painter"
    ],
    "wof:name":"Conduit Michael",
    "wof:placetype":"venue"
},
  "geometry": {"coordinates":[151.32008361800001,-33.5976524353],"type":"Point"}
}