{
  "type": "Feature",
  "properties": {
    "addr:full":"2/ 92 Gladstone St Fyshwick ACT 2609",
    "addr:housenumber":"/ 92",
    "addr:postcode":"2609",
    "addr:street":"Gladstone St",
    "iso:country":"AU",
    "sg:address":"2/ 92 Gladstone St",
    "sg:city":"Fyshwick",
    "sg:classifiers":[
        {
            "category":"Manufacturing",
            "subcategory":"Paper Products",
            "type":"Manufacturing & Wholesale Goods"
        }
    ],
    "sg:phone":"+61 2 6280 6599",
    "sg:postcode":"2609",
    "sg:province":"ACT",
    "sg:tags":[
        "wholesaler",
        "toilet",
        "mfrs"
    ],
    "wof:name":"Dowlings Canberra Pty Ltd",
    "wof:placetype":"venue"
},
  "geometry": {"coordinates":[149.17901611299999,-35.3219947815],"type":"Point"}
}