{
  "type": "Feature",
  "properties": {
    "addr:full":"340 Stanmore Rd Petersham NSW 2049",
    "addr:housenumber":"340",
    "addr:postcode":"2049",
    "addr:street":"Stanmore Rd",
    "iso:country":"AU",
    "sg:address":"340 Stanmore Rd",
    "sg:city":"Petersham",
    "sg:classifiers":[
        {
            "category":"Shopping",
            "subcategory":"Party Supplies",
            "type":"Retail Goods"
        }
    ],
    "sg:phone":"+61 2 9569 1050",
    "sg:postcode":"2049",
    "sg:province":"NSW",
    "sg:tags":[
        "hire",
        "costume"
    ],
    "sg:website":"http://www.acecostumehire.com",
    "wof:name":"Ace Costume Hire",
    "wof:placetype":"venue"
},
  "geometry": {"coordinates":[151.15725699999999,-33.895908],"type":"Point"}
}