{
  "type": "Feature",
  "properties": {
    "iso:country":"AU",
    "sg:address":"28 Bertram St",
    "sg:city":"Mortlake",
    "sg:classifiers":[
        {
            "category":"Building & Trades",
            "subcategory":"Cleaning & Sanitation",
            "type":"Services"
        }
    ],
    "sg:phone":"+61 2 9743 1278",
    "sg:postcode":"2137",
    "sg:province":"NSW",
    "sg:tags":[
        "commercial",
        "maintenance"
    ],
    "wof:name":"John The Pom Industrial Maintenance",
    "wof:placetype":"venue"
},
  "geometry": {"coordinates":[151.10618591299999,-33.84324646],"type":"Point"}
}