{
  "type": "Feature",
  "properties": {
    "addr:full":"72 Railway St Yennora NSW 2161",
    "addr:housenumber":"72",
    "addr:postcode":"2161",
    "addr:street":"Railway St",
    "iso:country":"AU",
    "sg:address":"72 Railway St",
    "sg:city":"Yennora",
    "sg:classifiers":[
        {
            "category":"Wholesale",
            "subcategory":"Auto Parts",
            "type":"Manufacturing & Wholesale Goods"
        }
    ],
    "sg:phone":"+61 2 9892 1010",
    "sg:postcode":"2161",
    "sg:province":"NSW",
    "sg:tags":[
        "recyclers"
    ],
    "wof:name":"Ace Auto Spares",
    "wof:placetype":"venue"
},
  "geometry": {"coordinates":[150.97224426299999,-33.8644752502],"type":"Point"}
}