{
  "type": "Feature",
  "properties": {
    "iso:country":"AU",
    "sg:address":"30 Cotterill Ave",
    "sg:city":"Bribie Island",
    "sg:classifiers":[
        {
            "category":"Education",
            "subcategory":"Kindergarten",
            "type":"Public Place"
        }
    ],
    "sg:phone":"+61 7 3408 1788",
    "sg:postcode":"4507",
    "sg:province":"QLD",
    "sg:tags":[
        "pre-schools"
    ],
    "wof:name":"Bribie Island Kindergarten & Preschool",
    "wof:placetype":"venue"
},
  "geometry": {"coordinates":[153.160919189,-27.0774211884],"type":"Point"}
}