{
  "type": "Feature",
  "properties": {
    "iso:country":"AU",
    "sg:address":"32A Rose Ave",
    "sg:city":"Norlane",
    "sg:classifiers":[
        {
            "category":"Shopping",
            "subcategory":"Beauty & Cosmetics",
            "type":"Retail Goods"
        }
    ],
    "sg:phone":"+61 3 5275 6255",
    "sg:postcode":"3214",
    "sg:province":"VIC",
    "sg:tags":[
        "equipment",
        "salon",
        "supply"
    ],
    "wof:name":"Spirit Body & Skin Care Pty Ltd",
    "wof:placetype":"venue"
},
  "geometry": {"coordinates":[144.36051940900001,-38.0877456665],"type":"Point"}
}