{
  "type": "Feature",
  "properties": {
    "addr:full":"20 Enterprise St Kunda Park QLD 4556",
    "addr:housenumber":"20",
    "addr:postcode":"4556",
    "addr:street":"Enterprise St",
    "iso:country":"AU",
    "sg:address":"20 Enterprise St",
    "sg:city":"Kunda Park",
    "sg:classifiers":[
        {
            "category":"Home & Garden",
            "subcategory":"Garden Supply",
            "type":"Retail Goods"
        }
    ],
    "sg:phone":"+61 1800 732 933",
    "sg:postcode":"4556",
    "sg:province":"QLD",
    "sg:tags":[
        "fertilizer"
    ],
    "wof:name":"Natrakelp Fertilizers",
    "wof:placetype":"venue"
},
  "geometry": {"coordinates":[153.03001403799999,-26.666135788],"type":"Point"}
}