{
  "type": "Feature",
  "properties": {
    "iso:country":"AU",
    "sg:address":"138 Witton Rd",
    "sg:city":"Indooroopilly",
    "sg:classifiers":[
        {
            "category":"Sports & Exercise",
            "subcategory":"Gym",
            "type":"Entertainment"
        }
    ],
    "sg:phone":"+61 7 3378 8950",
    "sg:postcode":"4068",
    "sg:province":"QLD",
    "sg:tags":[
        "health",
        "fitness"
    ],
    "sg:website":"http://www.workout.net.au",
    "wof:name":"Workout Indooroopilly",
    "wof:placetype":"venue"
},
  "geometry": {"coordinates":[152.96554565400001,-27.5067234039],"type":"Point"}
}