{
  "type": "Feature",
  "properties": {
    "addr:full":"4 Roycroft Ave Highton VIC 3216",
    "addr:housenumber":"4",
    "addr:postcode":"3216",
    "addr:street":"Roycroft Ave",
    "iso:country":"AU",
    "sg:address":"4 Roycroft Ave",
    "sg:city":"Highton",
    "sg:classifiers":[
        {
            "category":"Professional",
            "subcategory":"Accounting & Tax Preparation",
            "type":"Services"
        }
    ],
    "sg:phone":"+61 3 5244 2311",
    "sg:postcode":"3216",
    "sg:province":"VIC",
    "sg:tags":[
        "bookkeeping"
    ],
    "wof:name":"Active Business Consultants Pty Ltd",
    "wof:placetype":"venue"
},
  "geometry": {"coordinates":[144.32168579099999,-38.1833610535],"type":"Point"}
}