{
  "type": "Feature",
  "properties": {
    "addr:full":"14 Costello Rd Cawarral QLD 4702",
    "addr:housenumber":"14",
    "addr:postcode":"4702",
    "addr:street":"Costello Rd",
    "iso:country":"AU",
    "sg:address":"14 Costello Rd",
    "sg:city":"Cawarral",
    "sg:classifiers":[
        {
            "category":"Utilities",
            "subcategory":"Water",
            "type":"Services"
        }
    ],
    "sg:phone":"+61 427 344 102",
    "sg:postcode":"4702",
    "sg:province":"QLD",
    "sg:tags":[
        "cartage"
    ],
    "wof:name":"Allan Van Lathum",
    "wof:placetype":"venue"
},
  "geometry": {"coordinates":[150.695144653,-23.2926559448],"type":"Point"}
}