{
  "type": "Feature",
  "properties": {
    "iso:country":"AU",
    "sg:address":"256 Mill Point Rd",
    "sg:city":"South Perth",
    "sg:classifiers":[
        {
            "category":"Manufacturing",
            "subcategory":"Jewelry",
            "type":"Manufacturing & Wholesale Goods"
        }
    ],
    "sg:phone":"+61 8 9368 5255",
    "sg:postcode":"6151",
    "sg:province":"WA",
    "sg:tags":[
        "designer",
        "jewellery"
    ],
    "sg:website":"http://www.kiandesign.com.au",
    "wof:name":"Kian Design",
    "wof:placetype":"venue"
},
  "geometry": {"coordinates":[115.856041,-31.975454],"type":"Point"}
}