{
  "type": "Feature",
  "properties": {
    "addr:full":"\"Rossgole\" Rossgoll Rd Robertson NSW 2577",
    "addr:postcode":"2577",
    "addr:street":"Rossgoll Rd",
    "iso:country":"AU",
    "sg:address":"\"Rossgole\" Rossgoll Rd",
    "sg:city":"Robertson",
    "sg:classifiers":[
        {
            "category":"Train Station",
            "subcategory":"Rail",
            "type":"Transportation"
        }
    ],
    "sg:phone":"+61 2 4885 1405",
    "sg:postcode":"2577",
    "sg:province":"NSW",
    "sg:tags":[
        "goat",
        "farmer"
    ],
    "wof:name":"Prand Cashmeres",
    "wof:placetype":"venue"
},
  "geometry": {"coordinates":[150.57882690400001,-34.5910224915],"type":"Point"}
}