{
  "type": "Feature",
  "properties": {
    "addr:full":"22 Rosshire Rd Newport West VIC 3015",
    "addr:housenumber":"22",
    "addr:postcode":"3015",
    "addr:street":"Rosshire Rd",
    "iso:country":"AU",
    "sg:address":"22 Rosshire Rd",
    "sg:city":"Newport West",
    "sg:classifiers":[
        {
            "category":"Home & Garden",
            "subcategory":"Carpets & Floor Coverings",
            "type":"Retail Goods"
        }
    ],
    "sg:phone":"+61 410 949 221",
    "sg:postcode":"3015",
    "sg:province":"VIC",
    "sg:tags":[
        "tile",
        "wall",
        "layer"
    ],
    "wof:name":"Pinnacle Tiling",
    "wof:placetype":"venue"
},
  "geometry": {"coordinates":[144.865432739,-37.8475914001],"type":"Point"}
}