{
  "type": "Feature",
  "properties": {
    "addr:full":"46 Limestone St Ipswich QLD 4305",
    "addr:housenumber":"46",
    "addr:postcode":"4305",
    "addr:street":"Limestone St",
    "iso:country":"AU",
    "sg:address":"46 Limestone St",
    "sg:city":"Ipswich",
    "sg:classifiers":[
        {
            "category":"Health Services",
            "subcategory":"Dentist",
            "type":"Services"
        }
    ],
    "sg:phone":"+61 7 3281 5899",
    "sg:postcode":"4305",
    "sg:province":"QLD",
    "wof:name":"Rutley Edward",
    "wof:placetype":"venue"
},
  "geometry": {"coordinates":[152.761444092,-27.615776062],"type":"Point"}
}