{
  "type": "Feature",
  "properties": {
    "addr:full":"333 Gillies St Ballarat VIC 3350",
    "addr:housenumber":"333",
    "addr:postcode":"3350",
    "addr:street":"Gillies St",
    "iso:country":"AU",
    "sg:address":"333 Gillies St",
    "sg:city":"Ballarat",
    "sg:classifiers":[
        {
            "category":"Autos & Motor Vehicles",
            "subcategory":"Auto Supplies",
            "type":"Retail Goods"
        }
    ],
    "sg:phone":"+61 3 5339 9455",
    "sg:postcode":"3350",
    "sg:province":"VIC",
    "sg:tags":[
        "accessory"
    ],
    "wof:name":"Super Cheap Auto",
    "wof:placetype":"venue"
},
  "geometry": {"coordinates":[143.822495,-37.536388],"type":"Point"}
}