{
  "type": "Feature",
  "properties": {
    "addr:full":"Wellington Rd Wistow SA 5251",
    "addr:postcode":"5251",
    "addr:street":"Wellington Rd",
    "iso:country":"AU",
    "sg:address":"Wellington Rd",
    "sg:city":"Wistow",
    "sg:classifiers":[
        {
            "category":"Food & Beverages",
            "subcategory":"Groceries & Convenience Stores",
            "type":"Retail Goods"
        }
    ],
    "sg:phone":"+61 8 8391 1535",
    "sg:postcode":"5251",
    "sg:province":"SA",
    "wof:name":"Wistow General Store",
    "wof:placetype":"venue"
},
  "geometry": {"coordinates":[138.888671875,-35.1123657227],"type":"Point"}
}