{
  "type": "Feature",
  "properties": {
    "addr:full":"Level 1/ 23 Oxford Rd Ingleburn NSW 2565",
    "addr:housenumber":"/ 23",
    "addr:postcode":"2565",
    "addr:street":"Oxford Rd",
    "iso:country":"AU",
    "sg:address":"Level 1/ 23 Oxford Rd",
    "sg:city":"Ingleburn",
    "sg:classifiers":[
        {
            "category":"Banks & Credit Unions",
            "subcategory":"Financial Services",
            "type":"Services"
        }
    ],
    "sg:phone":"+61 2 9829 4188",
    "sg:postcode":"2565",
    "sg:province":"NSW",
    "sg:tags":[
        "planning"
    ],
    "wof:name":"Starman Financial Services Pty Ltd",
    "wof:placetype":"venue"
},
  "geometry": {"coordinates":[150.865997314,-33.9986419678],"type":"Point"}
}