{
  "type": "Feature",
  "properties": {
    "addr:full":"Suite 315, 71-73 Archer Street Chatswood 2067 Chatswood NSW 2067",
    "addr:housenumber":"71-73",
    "addr:postcode":"2067;2067",
    "addr:street":"Archer Street",
    "iso:country":"AU",
    "sg:address":"Suite 315, 71-73 Archer Street Chatswood 2067",
    "sg:city":"Chatswood",
    "sg:classifiers":[
        {
            "category":"Banks & Credit Unions",
            "subcategory":"Bank",
            "type":"Services"
        }
    ],
    "sg:phone":"+61 2 9411 6122",
    "sg:postcode":"2067",
    "sg:province":"NSW",
    "sg:tags":[
        "broker",
        "mortgage"
    ],
    "wof:name":"Summit 21",
    "wof:placetype":"venue"
},
  "geometry": {"coordinates":[151.18263244600001,-33.7962188721],"type":"Point"}
}