{
  "type": "Feature",
  "properties": {
    "addr:full":"Bridge Rd Homebush NSW 2140",
    "addr:postcode":"2140",
    "addr:street":"Bridge Rd",
    "iso:country":"AU",
    "sg:address":"Bridge Rd",
    "sg:city":"Homebush",
    "sg:classifiers":[
        {
            "category":"Education",
            "subcategory":"School",
            "type":"Public Place"
        }
    ],
    "sg:phone":"+61 2 9764 3611",
    "sg:postcode":"2140",
    "sg:province":"NSW",
    "sg:tags":[
        "boy"
    ],
    "wof:name":"Homebush Boys' High School",
    "wof:placetype":"venue"
},
  "geometry": {"coordinates":[151.07911682100001,-33.8636665344],"type":"Point"}
}