{
  "type": "Feature",
  "properties": {
    "addr:full":"9 Tourello Rd Mt Eliza VIC 3930",
    "addr:housenumber":"9",
    "addr:postcode":"3930",
    "addr:street":"Tourello Rd",
    "iso:country":"AU",
    "sg:address":"9 Tourello Rd",
    "sg:city":"Mt Eliza",
    "sg:classifiers":[
        {
            "category":"Professional",
            "subcategory":"Engineering",
            "type":"Services"
        }
    ],
    "sg:phone":"+61 3 9787 0226",
    "sg:postcode":"3930",
    "sg:province":"VIC",
    "sg:tags":[
        "electronic",
        "engineer"
    ],
    "wof:name":"Semaphore Logic (Aust) Pty Ltd",
    "wof:placetype":"venue"
},
  "geometry": {"coordinates":[145.07632446299999,-38.1846885681],"type":"Point"}
}