{
  "type": "Feature",
  "properties": {
    "addr:full":"4 / 470 Sydney Rd Balgowlah NSW 2093",
    "addr:housenumber":"/ 470",
    "addr:postcode":"2093",
    "addr:street":"Sydney Rd",
    "iso:country":"AU",
    "sg:address":"4 / 470 Sydney Rd",
    "sg:city":"Balgowlah",
    "sg:classifiers":[
        {
            "category":"Building & Trades",
            "subcategory":"Landscaping Services",
            "type":"Services"
        }
    ],
    "sg:phone":"+61 2 9400 2335",
    "sg:postcode":"2093",
    "sg:province":"NSW",
    "sg:tags":[
        "consultant"
    ],
    "wof:name":"DK Building Certifiers Pty Ltd",
    "wof:placetype":"venue"
},
  "geometry": {"coordinates":[151.25709533700001,-33.7946510315],"type":"Point"}
}