{
  "type": "Feature",
  "properties": {
    "addr:full":"138 Scarborough Beach Rd Scarborough WA 6019",
    "addr:housenumber":"138",
    "addr:postcode":"6019",
    "addr:street":"Scarborough Beach Rd",
    "iso:country":"AU",
    "sg:address":"138 Scarborough Beach Rd",
    "sg:city":"Scarborough",
    "sg:classifiers":[
        {
            "category":"Organizations",
            "subcategory":"Professional Association",
            "type":"Services"
        }
    ],
    "sg:phone":"+61 8 9245 8888",
    "sg:postcode":"6019",
    "sg:province":"WA",
    "sg:tags":[
        "web",
        "internet"
    ],
    "wof:name":"Perth Website Design",
    "wof:placetype":"venue"
},
  "geometry": {"coordinates":[115.77130127,-31.8937835693],"type":"Point"}
}