{
  "type": "Feature",
  "properties": {
    "iso:country":"AU",
    "sg:address":"2 Lancaster St",
    "sg:city":"Spearwood",
    "sg:classifiers":[
        {
            "category":"Banks & Credit Unions",
            "subcategory":"Bank",
            "type":"Services"
        }
    ],
    "sg:phone":"+61 13 20 32",
    "sg:postcode":"6163",
    "sg:province":"WA",
    "wof:name":"Westpac",
    "wof:placetype":"venue"
},
  "geometry": {"coordinates":[115.783272,-32.095585],"type":"Point"}
}