{
  "type": "Feature",
  "properties": {
    "addr:full":"23 Wotton St Bayswater WA 6053",
    "addr:housenumber":"23",
    "addr:postcode":"6053",
    "addr:street":"Wotton St",
    "iso:country":"AU",
    "sg:address":"23 Wotton St",
    "sg:city":"Bayswater",
    "sg:classifiers":[
        {
            "category":"Utilities",
            "subcategory":"Refuse",
            "type":"Services"
        }
    ],
    "sg:phone":"+61 8 9471 7077",
    "sg:postcode":"6053",
    "sg:province":"WA",
    "sg:tags":[
        "disposal",
        "reduction",
        "waste"
    ],
    "wof:name":"Tyre Recyclers W.A.",
    "wof:placetype":"venue"
},
  "geometry": {"coordinates":[115.920150757,-31.8997821808],"type":"Point"}
}