{
  "type": "Feature",
  "properties": {
    "iso:country":"AU",
    "sg:address":"13 Roper St",
    "sg:city":"Moorabbin",
    "sg:classifiers":[
        {
            "category":"Utilities",
            "subcategory":"Electric",
            "type":"Services"
        }
    ],
    "sg:phone":"+61 3 9553 3422",
    "sg:postcode":"3189",
    "sg:province":"VIC",
    "sg:tags":[
        "electrical",
        "contractor"
    ],
    "wof:name":"Prolec Contracting Pty Ltd",
    "wof:placetype":"venue"
},
  "geometry": {"coordinates":[145.05520629899999,-37.9452705383],"type":"Point"}
}