{
  "type": "Feature",
  "properties": {
    "addr:full":"299c Pacific Hwy Coffs Harbour NSW 2450",
    "addr:housenumber":"299c",
    "addr:postcode":"2450",
    "addr:street":"Pacific Hwy",
    "iso:country":"AU",
    "sg:address":"299c Pacific Hwy",
    "sg:city":"Coffs Harbour",
    "sg:classifiers":[
        {
            "category":"Home & Garden",
            "subcategory":"Garden Supply",
            "type":"Retail Goods"
        }
    ],
    "sg:phone":"+61 2 6652 8933",
    "sg:postcode":"2450",
    "sg:province":"NSW",
    "sg:tags":[
        "equipment"
    ],
    "wof:name":"Fibreglass King",
    "wof:placetype":"venue"
},
  "geometry": {"coordinates":[153.091431,-30.317007],"type":"Point"}
}