{
  "type": "Feature",
  "properties": {
    "addr:full":"92 Maitland St Narrabri NSW 2390",
    "addr:housenumber":"92",
    "addr:postcode":"2390",
    "addr:street":"Maitland St",
    "iso:country":"AU",
    "sg:address":"92 Maitland St",
    "sg:city":"Narrabri",
    "sg:classifiers":[
        {
            "category":"Building & Trades",
            "subcategory":"Construction",
            "type":"Services"
        }
    ],
    "sg:phone":"+61 2 6799 1310",
    "sg:postcode":"2390",
    "sg:province":"NSW",
    "sg:tags":[
        "home",
        "air conditioning"
    ],
    "wof:name":"Narrabri Retravision",
    "wof:placetype":"venue"
},
  "geometry": {"coordinates":[149.784255981,-30.3269920349],"type":"Point"}
}