{
  "type": "Feature",
  "properties": {
    "iso:country":"AU",
    "sg:address":"26 Wells Rd",
    "sg:city":"Mirboo North",
    "sg:classifiers":[
        {
            "category":"Retail",
            "subcategory":"Auto Repair",
            "type":"Services"
        }
    ],
    "sg:phone":"+61 3 5668 1383",
    "sg:postcode":"3871",
    "sg:province":"VIC",
    "sg:tags":[
        "repairer",
        "motor",
        "engineer"
    ],
    "wof:name":"Ridgway Motors",
    "wof:placetype":"venue"
},
  "geometry": {"coordinates":[146.15228271500001,-38.3929977417],"type":"Point"}
}