{
  "type": "Feature",
  "properties": {
    "addr:full":"35 Blackwood Rd Salisbury QLD 4107",
    "addr:housenumber":"35",
    "addr:postcode":"4107",
    "addr:street":"Blackwood Rd",
    "iso:country":"AU",
    "sg:address":"35 Blackwood Rd",
    "sg:city":"Salisbury",
    "sg:classifiers":[
        {
            "category":"Retail",
            "subcategory":"Repair Shop",
            "type":"Services"
        }
    ],
    "sg:phone":"+61 7 3277 8559",
    "sg:postcode":"4107",
    "sg:province":"QLD",
    "sg:tags":[
        "upholsterer"
    ],
    "wof:name":"Darren Luther Upholstery",
    "wof:placetype":"venue"
},
  "geometry": {"coordinates":[153.02410888700001,-27.5525836945],"type":"Point"}
}