{
  "type": "Feature",
  "properties": {
    "iso:country":"AU",
    "sg:address":"Suite 203, 443 Victoria Ave",
    "sg:city":"Chatswood",
    "sg:classifiers":[
        {
            "category":"Health Services",
            "subcategory":"Health Practitioner",
            "type":"Services"
        }
    ],
    "sg:phone":"+61 2 9413 4674",
    "sg:postcode":"2067",
    "sg:province":"NSW",
    "sg:tags":[
        "osteopath"
    ],
    "wof:name":"Artarmon Osteopaths",
    "wof:placetype":"venue"
},
  "geometry": {"coordinates":[151.18260192899999,-33.7962303162],"type":"Point"}
}