{
  "type": "Feature",
  "properties": {
    "addr:full":"737 Main Rd Edgeworth NSW 2285",
    "addr:housenumber":"737",
    "addr:postcode":"2285",
    "addr:street":"Main Rd",
    "iso:country":"AU",
    "sg:address":"737 Main Rd",
    "sg:city":"Edgeworth",
    "sg:classifiers":[
        {
            "category":"Professional",
            "subcategory":"Business Services",
            "type":"Services"
        }
    ],
    "sg:phone":"+61 2 4958 4988",
    "sg:postcode":"2285",
    "sg:province":"NSW",
    "sg:tags":[
        "broker"
    ],
    "wof:name":"McFarlane Noel First National",
    "wof:placetype":"venue"
},
  "geometry": {"coordinates":[151.61024475100001,-32.9230422974],"type":"Point"}
}