{
  "type": "Feature",
  "properties": {
    "iso:country":"AU",
    "sg:address":"116 Grindle Rd",
    "sg:city":"Rocklea",
    "sg:classifiers":[
        {
            "category":"Home & Garden",
            "subcategory":"Building Materials",
            "type":"Retail Goods"
        }
    ],
    "sg:phone":"+61 7 3277 0169",
    "sg:postcode":"4106",
    "sg:province":"QLD",
    "sg:tags":[
        "supply"
    ],
    "wof:name":"Tasbeam Pty Ltd",
    "wof:placetype":"venue"
},
  "geometry": {"coordinates":[153.00033569300001,-27.5537452698],"type":"Point"}
}