{
  "type": "Feature",
  "properties": {
    "iso:country":"AU",
    "sg:address":"8 Sir John Young Crs",
    "sg:city":"Woolloomooloo",
    "sg:classifiers":[
        {
            "category":"Professional",
            "subcategory":"Management & Consulting",
            "type":"Services"
        }
    ],
    "sg:phone":"+61 411 131 307",
    "sg:postcode":"2011",
    "sg:province":"NSW",
    "sg:tags":[
        "consultant"
    ],
    "wof:name":"Harte Management",
    "wof:placetype":"venue"
},
  "geometry": {"coordinates":[151.21978759800001,-33.8690681458],"type":"Point"}
}