{
  "type": "Feature",
  "properties": {
    "addr:full":"Lot 27 McDaniel Rd Broome WA 6725",
    "addr:postcode":"6725",
    "addr:street":"Mcdaniel Rd",
    "iso:country":"AU",
    "sg:address":"Lot 27 McDaniel Rd",
    "sg:city":"Broome",
    "sg:classifiers":[
        {
            "category":"Communications",
            "subcategory":"Television Station",
            "type":"Services"
        }
    ],
    "sg:phone":"+61 8 9193 5440",
    "sg:postcode":"6725",
    "sg:province":"WA",
    "sg:tags":[
        "mfrs",
        "tank",
        "installation",
        "septic"
    ],
    "wof:name":"Kimberley Septics & Concrete Products",
    "wof:placetype":"venue"
},
  "geometry": {"coordinates":[122.203712463,-17.986125946],"type":"Point"}
}