{
  "type": "Feature",
  "properties": {
    "iso:country":"AU",
    "sg:address":"Shop 7, 1- 9 Manning St",
    "sg:city":"Tuncurry",
    "sg:classifiers":[
        {
            "category":"Professional",
            "subcategory":"Computer Services",
            "type":"Services"
        }
    ],
    "sg:phone":"+61 438 424 144",
    "sg:postcode":"2428",
    "sg:province":"NSW",
    "sg:tags":[
        "repairs",
        "upgrade",
        "equipment"
    ],
    "wof:name":"Bits an Bytes",
    "wof:placetype":"venue"
},
  "geometry": {"coordinates":[152.50039699999999,-32.176521],"type":"Point"}
}