{
  "type": "Feature",
  "properties": {
    "addr:full":"Shop 2 Hilditch Shopping Cntr Hilditch Ave Newman WA 6753",
    "addr:housenumber":"shop 2",
    "addr:postcode":"6753",
    "addr:street":"Hilditch Shopping Cntr Hilditch Ave",
    "iso:country":"AU",
    "sg:address":"Shop 2 Hilditch Shopping Cntr Hilditch Ave",
    "sg:city":"Newman",
    "sg:classifiers":[
        {
            "category":"Fast Food",
            "type":"Food & Drink"
        }
    ],
    "sg:phone":"+61 8 9177 8668",
    "sg:postcode":"6753",
    "sg:province":"WA",
    "sg:tags":[
        "away",
        "take"
    ],
    "wof:name":"Newman Thai Restaurant",
    "wof:placetype":"venue"
},
  "geometry": {"coordinates":[119.731498718,-23.3537464142],"type":"Point"}
}