{
  "type": "Feature",
  "properties": {
    "addr:full":"286 Ann St Maryborough QLD 4650",
    "addr:housenumber":"286",
    "addr:postcode":"4650",
    "addr:street":"Ann St",
    "iso:country":"AU",
    "sg:address":"286 Ann St",
    "sg:city":"Maryborough",
    "sg:classifiers":[
        {
            "category":"Professional",
            "subcategory":"Art Services",
            "type":"Services"
        }
    ],
    "sg:phone":"+61 7 4123 5244",
    "sg:postcode":"4650",
    "sg:province":"QLD",
    "sg:tags":[
        "decorator",
        "painter"
    ],
    "wof:name":"H & L Wemmerslager",
    "wof:placetype":"venue"
},
  "geometry": {"coordinates":[152.69871499999999,-25.548096],"type":"Point"}
}