{
  "type": "Feature",
  "properties": {
    "addr:full":"Pier 8/ 23 Hickson Rd Millers Point NSW 2000",
    "addr:housenumber":"23",
    "addr:postcode":"2000",
    "addr:street":"Hickson Rd",
    "iso:country":"AU",
    "sg:address":"Pier 8/ 23 Hickson Rd",
    "sg:city":"Millers Point",
    "sg:classifiers":[
        {
            "category":"Professional",
            "subcategory":"Research",
            "type":"Services"
        }
    ],
    "sg:phone":"+61 2 9258 4444",
    "sg:postcode":"2000",
    "sg:province":"NSW",
    "sg:tags":[
        "market"
    ],
    "wof:name":"The Leading Edge Market Reaserch Consultants Pty Ltd",
    "wof:placetype":"venue"
},
  "geometry": {"coordinates":[151.20245361299999,-33.8588867188],"type":"Point"}
}