{
  "type": "Feature",
  "properties": {
    "iso:country":"AU",
    "sg:address":"PO Box 1062",
    "sg:city":"Howard Springs",
    "sg:classifiers":[
        {
            "category":"Building & Trades",
            "subcategory":"Landscaping Services",
            "type":"Services"
        }
    ],
    "sg:phone":"+61 417 823 845",
    "sg:postcode":"0835",
    "sg:province":"NT",
    "sg:tags":[
        "slashing",
        "contractor"
    ],
    "wof:name":"Rural Bobcat Hire",
    "wof:placetype":"venue"
},
  "geometry": {"coordinates":[131.04579200000001,-12.49626],"type":"Point"}
}