{
  "type": "Feature",
  "properties": {
    "iso:country":"AU",
    "sg:address":"8 Marsh St",
    "sg:city":"Cannon Hill",
    "sg:classifiers":[
        {
            "category":"Building & Trades",
            "subcategory":"Construction",
            "type":"Services"
        }
    ],
    "sg:phone":"+61 417 615 702",
    "sg:postcode":"4170",
    "sg:province":"QLD",
    "sg:tags":[
        "brick",
        "paving"
    ],
    "wof:name":"John's Paving",
    "wof:placetype":"venue"
},
  "geometry": {"coordinates":[153.08973693900001,-27.4690570831],"type":"Point"}
}