{
  "type": "Feature",
  "properties": {
    "addr:full":"39 Carnegie St Kalgoorlie WA 6430",
    "addr:housenumber":"39",
    "addr:postcode":"6430",
    "addr:street":"Carnegie St",
    "iso:country":"AU",
    "sg:address":"39 Carnegie St",
    "sg:city":"Kalgoorlie",
    "sg:classifiers":[
        {
            "category":"Building & Trades",
            "subcategory":"Construction",
            "type":"Services"
        }
    ],
    "sg:phone":"+61 409 912 986",
    "sg:postcode":"6430",
    "sg:province":"WA",
    "sg:tags":[
        "concrete",
        "contractor"
    ],
    "wof:name":"Kalgoorlie Precast Concrete",
    "wof:placetype":"venue"
},
  "geometry": {"coordinates":[121.443229675,-30.7866382599],"type":"Point"}
}