{
  "type": "Feature",
  "properties": {
    "addr:full":"Hampton St Bridgetown WA 6255",
    "addr:postcode":"6255",
    "addr:street":"Hampton St",
    "iso:country":"AU",
    "sg:address":"Hampton St",
    "sg:city":"Bridgetown",
    "sg:classifiers":[
        {
            "category":"Food & Beverages",
            "subcategory":"Supermarket",
            "type":"Retail Goods"
        }
    ],
    "sg:phone":"+61 8 9761 1611",
    "sg:postcode":"6255",
    "sg:province":"WA",
    "sg:tags":[
        "grocery",
        "store"
    ],
    "wof:name":"IGA Supermarkets",
    "wof:placetype":"venue"
},
  "geometry": {"coordinates":[116.136817932,-33.9559059143],"type":"Point"}
}