{
  "type": "Feature",
  "properties": {
    "addr:full":"48 Jones Rd Bellbird Park QLD 4300",
    "addr:housenumber":"48",
    "addr:postcode":"4300",
    "addr:street":"Jones Rd",
    "iso:country":"AU",
    "sg:address":"48 Jones Rd",
    "sg:city":"Bellbird Park",
    "sg:classifiers":[
        {
            "category":"Building & Trades",
            "subcategory":"Pest Control",
            "type":"Services"
        }
    ],
    "sg:phone":"+61 7 3814 3539",
    "sg:postcode":"4300",
    "sg:province":"QLD",
    "wof:name":"PGM Pest Control Home & Garden Maintenance",
    "wof:placetype":"venue"
},
  "geometry": {"coordinates":[152.877227783,-27.6468086243],"type":"Point"}
}