{
  "type": "Feature",
  "properties": {
    "iso:country":"AU",
    "sg:address":"3 Melton Valley Drv",
    "sg:city":"Melton",
    "sg:classifiers":[
        {
            "category":"Wholesale",
            "subcategory":"Scrap",
            "type":"Manufacturing & Wholesale Goods"
        }
    ],
    "sg:phone":"+61 3 9743 7165",
    "sg:postcode":"3337",
    "sg:province":"VIC",
    "sg:tags":[
        "merchant",
        "metal"
    ],
    "wof:name":"Monark Metals",
    "wof:placetype":"venue"
},
  "geometry": {"coordinates":[144.597946,-37.682808],"type":"Point"}
}