{
  "type": "Feature",
  "properties": {
    "addr:full":"29 Alma Ave Woy Woy NSW 2256",
    "addr:housenumber":"29",
    "addr:postcode":"2256",
    "addr:street":"Alma Ave",
    "iso:country":"AU",
    "sg:address":"29 Alma Ave",
    "sg:city":"Woy Woy",
    "sg:classifiers":[
        {
            "category":"Retail",
            "subcategory":"Auto Repair",
            "type":"Services"
        }
    ],
    "sg:phone":"+61 2 4341 1838",
    "sg:postcode":"2256",
    "sg:province":"NSW",
    "sg:tags":[
        "repairer",
        "motor",
        "engineer"
    ],
    "wof:name":"Wilkinson Auto Service",
    "wof:placetype":"venue"
},
  "geometry": {"coordinates":[151.324295044,-33.5037727356],"type":"Point"}
}