{
  "type": "Feature",
  "properties": {
    "iso:country":"AU",
    "sg:address":"Maple St",
    "sg:city":"Cooroy",
    "sg:classifiers":[
        {
            "category":"Food & Beverages",
            "subcategory":"Liquor & Beverages",
            "type":"Retail Goods"
        }
    ],
    "sg:phone":"+61 7 5442 6688",
    "sg:postcode":"4563",
    "sg:province":"QLD",
    "sg:tags":[
        "store"
    ],
    "wof:name":"Cooroy Cellars",
    "wof:placetype":"venue"
},
  "geometry": {"coordinates":[152.90887451200001,-26.4205932617],"type":"Point"}
}