{
  "type": "Feature",
  "properties": {
    "addr:full":"76 Eastview Ave North Ryde NSW 2113",
    "addr:housenumber":"76",
    "addr:postcode":"2113",
    "addr:street":"Eastview Ave",
    "iso:country":"AU",
    "sg:address":"76 Eastview Ave",
    "sg:city":"North Ryde",
    "sg:phone":"+61 2 9888 3913",
    "sg:postcode":"2113",
    "sg:province":"NSW",
    "wof:name":"Air-Rate",
    "wof:placetype":"venue"
},
  "geometry": {"coordinates":[151.116165161,-33.7923927307],"type":"Point"}
}