{
  "type": "Feature",
  "properties": {
    "addr:full":"72 Flinders St Melbourne VIC 3000",
    "addr:housenumber":"72",
    "addr:postcode":"3000",
    "addr:street":"Flinders St",
    "iso:country":"AU",
    "sg:address":"72 Flinders St",
    "sg:city":"Melbourne",
    "sg:classifiers":[
        {
            "category":"Restaurant",
            "type":"Food & Drink"
        }
    ],
    "sg:phone":"+61 3 9677 9677",
    "sg:postcode":"3000",
    "sg:province":"VIC",
    "wof:name":"The Press Club Restaurant & Bar",
    "wof:placetype":"venue"
},
  "geometry": {"coordinates":[144.97247314399999,-37.8158302307],"type":"Point"}
}