{
  "type": "Feature",
  "properties": {
    "iso:country":"AU",
    "sg:address":"Lot 91 Montclaire Crt",
    "sg:city":"Cashmere",
    "sg:classifiers":[
        {
            "category":"Personal",
            "subcategory":"Beauty Salon",
            "type":"Services"
        }
    ],
    "sg:phone":"+61 407 788 410",
    "sg:postcode":"4500",
    "sg:province":"QLD",
    "sg:tags":[
        "supply",
        "artist",
        "make-up"
    ],
    "wof:name":"Alisa McGregor-Greene",
    "wof:placetype":"venue"
},
  "geometry": {"coordinates":[152.93359375,-27.2953662872],"type":"Point"}
}