{
  "type": "Feature",
  "properties": {
    "iso:country":"AU",
    "sg:address":"Unit 2/ 291 Ross River Rd",
    "sg:city":"Aitkenvale",
    "sg:classifiers":[
        {
            "category":"Professional",
            "subcategory":"Management & Consulting",
            "type":"Services"
        }
    ],
    "sg:phone":"+61 1800 819 167",
    "sg:postcode":"4814",
    "sg:province":"QLD",
    "sg:tags":[
        "consultant",
        "relocation"
    ],
    "wof:name":"Toll Transitions",
    "wof:placetype":"venue"
},
  "geometry": {"coordinates":[146.766296,-19.297026],"type":"Point"}
}