{
  "type": "Feature",
  "properties": {
    "iso:country":"AU",
    "sg:address":"122 Crescent Rd",
    "sg:city":"Newport",
    "sg:classifiers":[
        {
            "category":"Autos & Motor Vehicles",
            "subcategory":"Boat Sales",
            "type":"Retail Goods"
        }
    ],
    "sg:phone":"+61 2 9999 4188",
    "sg:postcode":"2106",
    "sg:province":"NSW",
    "sg:tags":[
        "yacht"
    ],
    "wof:name":"Angler Charters",
    "wof:placetype":"venue"
},
  "geometry": {"coordinates":[151.31112670900001,-33.6647644043],"type":"Point"}
}