{
  "type": "Feature",
  "properties": {
    "addr:full":"66 Lytton Rd Bulimba QLD 4171",
    "addr:housenumber":"66",
    "addr:postcode":"4171",
    "addr:street":"Lytton Rd",
    "iso:country":"AU",
    "sg:address":"66 Lytton Rd",
    "sg:city":"Bulimba",
    "sg:classifiers":[
        {
            "category":"Manufacturing",
            "subcategory":"Watercraft",
            "type":"Manufacturing & Wholesale Goods"
        }
    ],
    "sg:phone":"+61 7 3399 9266",
    "sg:postcode":"4171",
    "sg:province":"QLD",
    "sg:tags":[
        "sail",
        "marine",
        "maker"
    ],
    "wof:name":"Mortensen Sails",
    "wof:placetype":"venue"
},
  "geometry": {"coordinates":[153.06492614699999,-27.4497509003],"type":"Point"}
}