{
  "type": "Feature",
  "properties": {
    "iso:country":"AU",
    "sg:address":"P.O BOX 87 KATANNING",
    "sg:city":"Katanning",
    "sg:classifiers":[
        {
            "category":"Professional",
            "subcategory":"Accounting & Tax Preparation",
            "type":"Services"
        }
    ],
    "sg:phone":"+61 8 9821 1311",
    "sg:postcode":"6317",
    "sg:province":"WA",
    "sg:tags":[
        "consultant",
        "taxation"
    ],
    "wof:name":"Marsden Business Solutions",
    "wof:placetype":"venue"
},
  "geometry": {"coordinates":[117.553451538,-33.6880989075],"type":"Point"}
}