{
  "type": "Feature",
  "properties": {
    "addr:full":"112 Synott St Werribee VIC 3030",
    "addr:housenumber":"112",
    "addr:postcode":"3030",
    "addr:street":"Synott St",
    "iso:country":"AU",
    "sg:address":"112 Synott St",
    "sg:city":"Werribee",
    "sg:classifiers":[
        {
            "category":"Health Services",
            "subcategory":"Doctor",
            "type":"Services"
        }
    ],
    "sg:phone":"+61 3 9741 1222",
    "sg:postcode":"3030",
    "sg:province":"VIC",
    "sg:tags":[
        "medical",
        "practitioner"
    ],
    "wof:name":"Chelmer Imaging Group",
    "wof:placetype":"venue"
},
  "geometry": {"coordinates":[144.65463299999999,-37.906361],"type":"Point"}
}