{
  "type": "Feature",
  "properties": {
    "addr:full":"Unit 2/ 9 Nesbitt St Wagga Wagga NSW 2650",
    "addr:housenumber":"9",
    "addr:postcode":"2650",
    "addr:street":"Nesbitt St",
    "iso:country":"AU",
    "sg:address":"Unit 2/ 9 Nesbitt St",
    "sg:city":"Wagga Wagga",
    "sg:classifiers":[
        {
            "category":"Utilities",
            "subcategory":"Electric",
            "type":"Services"
        }
    ],
    "sg:phone":"+61 2 6931 7200",
    "sg:postcode":"2650",
    "sg:province":"NSW",
    "sg:tags":[
        "electrical",
        "contractor"
    ],
    "wof:name":"South West Catering Pty Ltd",
    "wof:placetype":"venue"
},
  "geometry": {"coordinates":[147.384277344,-35.1213150024],"type":"Point"}
}