{
  "type": "Feature",
  "properties": {
    "iso:country":"AU",
    "sg:address":"94 Anderson Ave",
    "sg:city":"Panania",
    "sg:classifiers":[
        {
            "category":"Food & Beverages",
            "subcategory":"Fruits & Vegetables",
            "type":"Retail Goods"
        }
    ],
    "sg:phone":"+61 2 9792 4522",
    "sg:postcode":"2213",
    "sg:province":"NSW",
    "sg:tags":[
        "greengrocer",
        "fruiterer"
    ],
    "wof:name":"Bonanza Fresh",
    "wof:placetype":"venue"
},
  "geometry": {"coordinates":[150.998611,-33.953815],"type":"Point"}
}