{
  "type": "Feature",
  "properties": {
    "iso:country":"AU",
    "sg:address":"Shp1a/ 87 Jonson St",
    "sg:city":"Byron Bay",
    "sg:classifiers":[
        {
            "category":"Shopping",
            "subcategory":"Crafts & Fabrics",
            "type":"Retail Goods"
        }
    ],
    "sg:phone":"+61 2 6685 5692",
    "sg:postcode":"2481",
    "sg:province":"NSW",
    "sg:tags":[
        "supply"
    ],
    "wof:name":"The Bead Shop",
    "wof:placetype":"venue"
},
  "geometry": {"coordinates":[153.612884522,-28.6483860016],"type":"Point"}
}