{
  "type": "Feature",
  "properties": {
    "addr:full":"2 Arizonica St Clontarf QLD 4019",
    "addr:housenumber":"2",
    "addr:postcode":"4019",
    "addr:street":"Arizonica St",
    "iso:country":"AU",
    "sg:address":"2 Arizonica St",
    "sg:city":"Clontarf",
    "sg:classifiers":[
        {
            "category":"Building & Trades",
            "subcategory":"Construction",
            "type":"Services"
        }
    ],
    "sg:phone":"+61 7 3283 3854",
    "sg:postcode":"4019",
    "sg:province":"QLD",
    "sg:tags":[
        "plasterboard",
        "plasterer",
        "fixer"
    ],
    "wof:name":"Fiorello G & C",
    "wof:placetype":"venue"
},
  "geometry": {"coordinates":[153.087356567,-27.2398834229],"type":"Point"}
}