{
  "type": "Feature",
  "properties": {
    "addr:full":"10 Jannali Rd Dubbo NSW 2830",
    "addr:housenumber":"10",
    "addr:postcode":"2830",
    "addr:street":"Jannali Rd",
    "iso:country":"AU",
    "sg:address":"10 Jannali Rd",
    "sg:city":"Dubbo",
    "sg:classifiers":[
        {
            "category":"Autos & Motor Vehicles",
            "subcategory":"Auto Supplies",
            "type":"Retail Goods"
        }
    ],
    "sg:phone":"+61 438 350 305",
    "sg:postcode":"2830",
    "sg:province":"NSW",
    "sg:tags":[
        "battery",
        "automotive"
    ],
    "wof:name":"Big Micks Auto Electrical & Air Conditioning",
    "wof:placetype":"venue"
},
  "geometry": {"coordinates":[148.583221436,-32.241065979],"type":"Point"}
}