{
  "type": "Feature",
  "properties": {
    "iso:country":"AU",
    "sg:address":"Suite 2, 35 Fourth Ave",
    "sg:city":"Eastwood",
    "sg:classifiers":[
        {
            "category":"Health Services",
            "subcategory":"Health Practitioner",
            "type":"Services"
        }
    ],
    "sg:phone":"+61 2 9874 9000",
    "sg:postcode":"2122",
    "sg:province":"NSW",
    "sg:tags":[
        "consultant",
        "conservation",
        "hearing"
    ],
    "wof:name":"M.A.C. Audiology Service",
    "wof:placetype":"venue"
},
  "geometry": {"coordinates":[151.087966919,-33.7947311401],"type":"Point"}
}