{
  "type": "Feature",
  "properties": {
    "addr:full":"1 Scott St Point Clare NSW 2250",
    "addr:housenumber":"1",
    "addr:postcode":"2250",
    "addr:street":"Scott St",
    "iso:country":"AU",
    "sg:address":"1 Scott St",
    "sg:city":"Point Clare",
    "sg:classifiers":[
        {
            "category":"Personal",
            "subcategory":"Tattoo Parlor",
            "type":"Services"
        }
    ],
    "sg:phone":"+61 2 4322 6597",
    "sg:postcode":"2250",
    "sg:province":"NSW",
    "sg:tags":[
        "resume"
    ],
    "wof:name":"Amazing Resumes",
    "wof:placetype":"venue"
},
  "geometry": {"coordinates":[151.328216553,-33.4423294067],"type":"Point"}
}