{
  "type": "Feature",
  "properties": {
    "addr:full":"Shop 116 Greensborough Plaza S 20 Main St Greensborough VIC 3088",
    "addr:housenumber":"116;20",
    "addr:postcode":"3088",
    "addr:street":"Greensborough Plaza S;Main St",
    "iso:country":"AU",
    "sg:address":"Shop 116 Greensborough Plaza S 20 Main St",
    "sg:city":"Greensborough",
    "sg:classifiers":[
        {
            "category":"Fast Food",
            "type":"Food & Drink"
        }
    ],
    "sg:phone":"+61 3 9434 6419",
    "sg:postcode":"3088",
    "sg:province":"VIC",
    "sg:tags":[
        "away",
        "take"
    ],
    "wof:name":"Jesters",
    "wof:placetype":"venue"
},
  "geometry": {"coordinates":[145.10276794399999,-37.7044143677],"type":"Point"}
}