{
  "type": "Feature",
  "properties": {
    "iso:country":"AU",
    "sg:address":"19 Sunninghill Rd",
    "sg:city":"Stoneville",
    "sg:classifiers":[
        {
            "category":"Utilities",
            "subcategory":"Electric",
            "type":"Services"
        }
    ],
    "sg:phone":"+61 8 9295 1801",
    "sg:postcode":"6081",
    "sg:province":"WA",
    "sg:tags":[
        "electrical",
        "contractor"
    ],
    "wof:name":"Mundaring Electrical Contracting Service",
    "wof:placetype":"venue"
},
  "geometry": {"coordinates":[116.16464233400001,-31.8829135895],"type":"Point"}
}