{
  "type": "Feature",
  "properties": {
    "addr:full":"128 Stanley St West Melbourne VIC 3003",
    "addr:housenumber":"128",
    "addr:postcode":"3003",
    "addr:street":"Stanley St",
    "iso:country":"AU",
    "sg:address":"128 Stanley St",
    "sg:city":"West Melbourne",
    "sg:classifiers":[
        {
            "category":"Manufacturing",
            "subcategory":"Textiles",
            "type":"Manufacturing & Wholesale Goods"
        }
    ],
    "sg:phone":"+61 3 9326 6944",
    "sg:postcode":"3003",
    "sg:province":"VIC",
    "sg:tags":[
        "wholesaler",
        "mfrs",
        "handkerchief"
    ],
    "wof:name":"Barry Healey Agencies Pty Ltd",
    "wof:placetype":"venue"
},
  "geometry": {"coordinates":[144.94801330600001,-37.8086967468],"type":"Point"}
}