{
  "type": "Feature",
  "properties": {
    "addr:full":"2nd Floor, 520 Swift St Albury NSW 2640",
    "addr:housenumber":"520",
    "addr:postcode":"2640",
    "addr:street":"Swift St",
    "iso:country":"AU",
    "sg:address":"2nd Floor, 520 Swift St",
    "sg:city":"Albury",
    "sg:classifiers":[
        {
            "category":"Professional",
            "subcategory":"Accounting & Tax Preparation",
            "type":"Services"
        }
    ],
    "sg:phone":"+61 2 6023 9100",
    "sg:postcode":"2640",
    "sg:province":"NSW",
    "sg:tags":[
        "consultant",
        "taxation"
    ],
    "wof:name":"Goonan Paul",
    "wof:placetype":"venue"
},
  "geometry": {"coordinates":[146.91612243599999,-36.0787696838],"type":"Point"}
}