{
  "type": "Feature",
  "properties": {
    "addr:full":"Shop 1 21 Ballarat St Brunswick VIC 3056",
    "addr:housenumber":"shop;21",
    "addr:postcode":"3056",
    "addr:street":"Ballarat St",
    "iso:country":"AU",
    "sg:address":"Shop 1 21 Ballarat St",
    "sg:city":"Brunswick",
    "sg:classifiers":[
        {
            "category":"Shopping",
            "subcategory":"Clothing, Apparel, & Fashions",
            "type":"Retail Goods"
        }
    ],
    "sg:phone":"+61 3 9388 1618",
    "sg:postcode":"3056",
    "sg:province":"VIC",
    "sg:tags":[
        "menswear"
    ],
    "wof:name":"Menz Mode",
    "wof:placetype":"venue"
},
  "geometry": {"coordinates":[144.96072387699999,-37.766002655],"type":"Point"}
}