{
  "type": "Feature",
  "properties": {
    "addr:full":"149 Ramsay St Haberfield NSW 2045",
    "addr:housenumber":"149",
    "addr:postcode":"2045",
    "addr:street":"Ramsay St",
    "iso:country":"AU",
    "sg:address":"149 Ramsay St",
    "sg:city":"Haberfield",
    "sg:classifiers":[
        {
            "category":"Travel",
            "subcategory":"Travel Agent",
            "type":"Entertainment"
        }
    ],
    "sg:phone":"+61 2 9716 6922",
    "sg:postcode":"2045",
    "sg:province":"NSW",
    "sg:tags":[
        "consultant"
    ],
    "wof:name":"Forza Travel",
    "wof:placetype":"venue"
},
  "geometry": {"coordinates":[151.138824,-33.880226],"type":"Point"}
}