{
  "type": "Feature",
  "properties": {
    "iso:country":"AU",
    "sg:address":"Shop 5/ 477 Riverton Drv East",
    "sg:city":"Riverton",
    "sg:classifiers":[
        {
            "category":"Personal",
            "subcategory":"Beauty Salon",
            "type":"Services"
        }
    ],
    "sg:phone":"+61 8 9457 9126",
    "sg:postcode":"6148",
    "sg:province":"WA",
    "sg:tags":[
        "hairdresser"
    ],
    "wof:name":"Kurious Hair Design",
    "wof:placetype":"venue"
},
  "geometry": {"coordinates":[115.9021,-32.031624],"type":"Point"}
}