{
  "type": "Feature",
  "properties": {
    "addr:full":"Shp 1/ 93 Grimshaw St Greensborough VIC 3088",
    "addr:housenumber":"/ 93",
    "addr:postcode":"3088",
    "addr:street":"Grimshaw St",
    "iso:country":"AU",
    "sg:address":"Shp 1/ 93 Grimshaw St",
    "sg:city":"Greensborough",
    "sg:classifiers":[
        {
            "category":"Personal",
            "subcategory":"Beauty Salon",
            "type":"Services"
        }
    ],
    "sg:phone":"+61 3 9434 4801",
    "sg:postcode":"3088",
    "sg:province":"VIC",
    "sg:tags":[
        "hairdresser"
    ],
    "wof:name":"Lishous",
    "wof:placetype":"venue"
},
  "geometry": {"coordinates":[145.10162353499999,-37.7045326233],"type":"Point"}
}