{
  "type": "Feature",
  "properties": {
    "addr:full":"338 Middleton Rd Albany WA 6330",
    "addr:housenumber":"338",
    "addr:postcode":"6330",
    "addr:street":"Middleton Rd",
    "iso:country":"AU",
    "sg:address":"338 Middleton Rd",
    "sg:city":"Albany",
    "sg:classifiers":[
        {
            "category":"Personal",
            "subcategory":"Beauty Salon",
            "type":"Services"
        }
    ],
    "sg:phone":"+61 8 9842 8444",
    "sg:postcode":"6330",
    "sg:province":"WA",
    "sg:tags":[
        "hairdresser"
    ],
    "wof:name":"Amanda's Hair Boutique",
    "wof:placetype":"venue"
},
  "geometry": {"coordinates":[117.88475036600001,-35.0199050903],"type":"Point"}
}