{
  "type": "Feature",
  "properties": {
    "addr:full":"1 Osborne Rd North Haven SA 5018",
    "addr:housenumber":"1",
    "addr:postcode":"5018",
    "addr:street":"Osborne Rd",
    "iso:country":"AU",
    "sg:address":"1 Osborne Rd",
    "sg:city":"North Haven",
    "sg:classifiers":[
        {
            "category":"Health Services",
            "subcategory":"Doctor",
            "type":"Services"
        }
    ],
    "sg:phone":"+61 8 8341 8433",
    "sg:postcode":"5018",
    "sg:province":"SA",
    "sg:tags":[
        "medical",
        "practitioner"
    ],
    "wof:name":"Macris H",
    "wof:placetype":"venue"
},
  "geometry": {"coordinates":[138.491500855,-34.7926216125],"type":"Point"}
}