{
  "type": "Feature",
  "properties": {
    "iso:country":"AU",
    "sg:address":"58 Park Ave",
    "sg:city":"Avalon",
    "sg:classifiers":[
        {
            "category":"Professional",
            "subcategory":"Art Services",
            "type":"Services"
        }
    ],
    "sg:phone":"+61 412 610 430",
    "sg:postcode":"2107",
    "sg:province":"NSW",
    "sg:tags":[
        "interior",
        "designer"
    ],
    "wof:name":"Peppertree Designs",
    "wof:placetype":"venue"
},
  "geometry": {"coordinates":[151.32591247600001,-33.628780365],"type":"Point"}
}