{
  "type": "Feature",
  "properties": {
    "iso:country":"AU",
    "sg:address":"McCallums Rd",
    "sg:city":"Colo Vale",
    "sg:classifiers":[
        {
            "category":"Home & Garden",
            "subcategory":"Household Appliances",
            "type":"Retail Goods"
        }
    ],
    "sg:phone":"+61 409 908 726",
    "sg:postcode":"2575",
    "sg:province":"NSW",
    "sg:tags":[
        "equipment",
        "gas"
    ],
    "wof:name":"Highlands Energy",
    "wof:placetype":"venue"
},
  "geometry": {"coordinates":[150.46343994099999,-34.4085273743],"type":"Point"}
}