{
  "type": "Feature",
  "properties": {
    "iso:country":"AU",
    "sg:address":"77 Darlinghurst Rd",
    "sg:city":"Kings Cross",
    "sg:classifiers":[
        {
            "category":"Bars & Pubs",
            "subcategory":"Nightclub",
            "type":"Food & Drink"
        }
    ],
    "sg:phone":"+61 2 9357 1180",
    "sg:postcode":"2011",
    "sg:province":"NSW",
    "sg:tags":[
        "discotheque"
    ],
    "wof:name":"Porkys Nite Spot",
    "wof:placetype":"venue"
},
  "geometry": {"coordinates":[151.224517822,-33.8731040955],"type":"Point"}
}