{
  "type": "Feature",
  "properties": {
    "iso:country":"AU",
    "sg:address":"51 Hollingworth St",
    "sg:city":"Port Macquarie",
    "sg:classifiers":[
        {
            "category":"Building & Trades",
            "subcategory":"Construction",
            "type":"Services"
        }
    ],
    "sg:phone":"+61 2 6584 6600",
    "sg:postcode":"2444",
    "sg:province":"NSW",
    "sg:tags":[
        "renovation",
        "alterations",
        "extension",
        "contractor"
    ],
    "wof:name":"Allen & Newton Pty Ltd",
    "wof:placetype":"venue"
},
  "geometry": {"coordinates":[152.90507500000001,-31.437132],"type":"Point"}
}