{
  "type": "Feature",
  "properties": {
    "iso:country":"AU",
    "sg:address":"8 Baruna Crt",
    "sg:city":"Mandurah",
    "sg:classifiers":[
        {
            "category":"Building & Trades",
            "subcategory":"Construction",
            "type":"Services"
        }
    ],
    "sg:phone":"+61 8 9534 7918",
    "sg:postcode":"6210",
    "sg:province":"WA",
    "sg:tags":[
        "management"
    ],
    "wof:name":"Harvey M J & Co",
    "wof:placetype":"venue"
},
  "geometry": {"coordinates":[115.706947,-32.531719],"type":"Point"}
}