{
  "type": "Feature",
  "properties": {
    "addr:full":"Shop 11, Taylors Lakes Shppng Cntr Taylors Lakes VIC 3038",
    "addr:housenumber":"shop 11",
    "addr:postcode":"3038",
    "iso:country":"AU",
    "sg:address":"Shop 11, Taylors Lakes Shppng Cntr",
    "sg:city":"Taylors Lakes",
    "sg:classifiers":[
        {
            "category":"Real Estate",
            "subcategory":"Real Estate Agent",
            "type":"Services"
        }
    ],
    "sg:phone":"+61 3 9390 9022",
    "sg:postcode":"3038",
    "sg:province":"VIC",
    "wof:name":"Lakes Real Estate",
    "wof:placetype":"venue"
},
  "geometry": {"coordinates":[144.813446,-37.729622],"type":"Point"}
}