{
  "type": "Feature",
  "properties": {
    "addr:full":"PO Box 741 Torquay VIC 3228",
    "addr:postcode":"3228",
    "iso:country":"AU",
    "sg:address":"PO Box 741",
    "sg:city":"Torquay",
    "sg:classifiers":[
        {
            "category":"Building & Trades",
            "subcategory":"Landscaping Services",
            "type":"Services"
        }
    ],
    "sg:phone":"+61 424 065 525",
    "sg:postcode":"3228",
    "sg:province":"VIC",
    "sg:tags":[
        "gardener"
    ],
    "wof:name":"All Nature Care",
    "wof:placetype":"venue"
},
  "geometry": {"coordinates":[144.33218400000001,-38.314346],"type":"Point"}
}