{
  "type": "Feature",
  "properties": {
    "addr:full":"12 Cocus Crs Palm Cove QLD 4879",
    "addr:housenumber":"12",
    "addr:postcode":"4879",
    "addr:street":"Cocus Crs",
    "iso:country":"AU",
    "sg:address":"12 Cocus Crs",
    "sg:city":"Palm Cove",
    "sg:classifiers":[
        {
            "category":"Professional",
            "subcategory":"Art Services",
            "type":"Services"
        }
    ],
    "sg:phone":"+61 419 997 691",
    "sg:postcode":"4879",
    "sg:province":"QLD",
    "sg:tags":[
        "decorator",
        "painter"
    ],
    "wof:name":"Moran Prestige",
    "wof:placetype":"venue"
},
  "geometry": {"coordinates":[145.67100524899999,-16.7458992004],"type":"Point"}
}