{
  "type": "Feature",
  "properties": {
    "addr:full":"42 Xanadu Drv Caboolture QLD 4510",
    "addr:housenumber":"42",
    "addr:postcode":"4510",
    "addr:street":"Xanadu Drv",
    "iso:country":"AU",
    "sg:address":"42 Xanadu Drv",
    "sg:city":"Caboolture",
    "sg:classifiers":[
        {
            "category":"Building & Trades",
            "subcategory":"Construction",
            "type":"Services"
        }
    ],
    "sg:phone":"+61 433 688 135",
    "sg:postcode":"4510",
    "sg:province":"QLD",
    "sg:tags":[
        "spouting",
        "guttering"
    ],
    "wof:name":"Gutter Guard International",
    "wof:placetype":"venue"
},
  "geometry": {"coordinates":[152.93383800000001,-27.086567],"type":"Point"}
}