{
  "type": "Feature",
  "properties": {
    "addr:full":"34- 50 Nathan Rd Dandenong South VIC 3175",
    "addr:housenumber":"50",
    "addr:postcode":"3175",
    "addr:street":"Nathan Rd",
    "iso:country":"AU",
    "sg:address":"34- 50 Nathan Rd",
    "sg:city":"Dandenong South",
    "sg:classifiers":[
        {
            "category":"Building & Trades",
            "subcategory":"Construction",
            "type":"Services"
        }
    ],
    "sg:phone":"+61 3 9706 7779",
    "sg:postcode":"3175",
    "sg:province":"VIC",
    "sg:tags":[
        "contractor"
    ],
    "wof:name":"Hartcon Australia Pty Ltd",
    "wof:placetype":"venue"
},
  "geometry": {"coordinates":[145.23814392099999,-38.0095214844],"type":"Point"}
}