{
  "type": "Feature",
  "properties": {
    "iso:country":"AU",
    "sg:address":"414 Stirling Hwy",
    "sg:city":"Cottesloe",
    "sg:classifiers":[
        {
            "category":"Banks & Credit Unions",
            "subcategory":"Financial Services",
            "type":"Services"
        }
    ],
    "sg:phone":"+61 8 9384 0600",
    "sg:postcode":"6011",
    "sg:province":"WA",
    "sg:tags":[
        "settlement",
        "nt",
        "agent",
        "wa"
    ],
    "sg:website":"http://www.seaviewsettlements.com.au",
    "wof:name":"Seaview Settlements",
    "wof:placetype":"venue"
},
  "geometry": {"coordinates":[115.7604599,-32.0027313232],"type":"Point"}
}