{
  "type": "Feature",
  "properties": {
    "addr:full":"18 Albion Rse Australind WA 6233",
    "addr:housenumber":"18",
    "addr:postcode":"6233",
    "addr:street":"Albion Rse",
    "iso:country":"AU",
    "sg:address":"18 Albion Rse",
    "sg:city":"Australind",
    "sg:classifiers":[
        {
            "category":"Utilities",
            "subcategory":"Electric",
            "type":"Services"
        }
    ],
    "sg:phone":"+61 8 9725 8075",
    "sg:postcode":"6233",
    "sg:province":"WA",
    "sg:tags":[
        "electrical",
        "contractor"
    ],
    "wof:name":"P.R. & M.J. Butcher Electrical Contractors",
    "wof:placetype":"venue"
},
  "geometry": {"coordinates":[115.733177,-33.242596],"type":"Point"}
}