{
  "type": "Feature",
  "properties": {
    "addr:full":"51 Bondi Rd Bondi NSW 2026",
    "addr:housenumber":"51",
    "addr:postcode":"2026",
    "addr:street":"Bondi Rd",
    "iso:country":"AU",
    "sg:address":"51 Bondi Rd",
    "sg:city":"Bondi",
    "sg:classifiers":[
        {
            "category":"Food & Beverages",
            "subcategory":"Supermarket",
            "type":"Retail Goods"
        }
    ],
    "sg:phone":"+61 2 9387 8750",
    "sg:postcode":"2026",
    "sg:province":"NSW",
    "sg:tags":[
        "grocery",
        "store"
    ],
    "wof:name":"Star Supermarket IGA Bondi",
    "wof:placetype":"venue"
},
  "geometry": {"coordinates":[151.259841919,-33.8934593201],"type":"Point"}
}