{
  "type": "Feature",
  "properties": {
    "iso:country":"AU",
    "sg:address":"52 Cambridge Rd",
    "sg:city":"Bellerive",
    "sg:classifiers":[
        {
            "category":"Health Services",
            "subcategory":"Dentist",
            "type":"Services"
        }
    ],
    "sg:phone":"+61 3 6244 4871",
    "sg:postcode":"7018",
    "sg:province":"TAS",
    "wof:name":"Humphrey N P Dr",
    "wof:placetype":"venue"
},
  "geometry": {"coordinates":[147.36790466299999,-42.8745727539],"type":"Point"}
}