{
  "type": "Feature",
  "properties": {
    "addr:full":"Shed 3,Cnr Birdwood Ave & The Boulevard Geelong North VIC 3215",
    "addr:housenumber":"3",
    "addr:postcode":"3215",
    "addr:street":"Cnr Birdwood Ave & The Boulevard",
    "iso:country":"AU",
    "sg:address":"Shed 3,Cnr Birdwood Ave & The Boulevard",
    "sg:city":"Geelong North",
    "sg:classifiers":[
        {
            "category":"Retail",
            "subcategory":"Car Wash",
            "type":"Services"
        }
    ],
    "sg:phone":"+61 3 5277 1677",
    "sg:postcode":"3215",
    "sg:province":"VIC",
    "sg:tags":[
        "truck",
        "cleaning"
    ],
    "wof:name":"Bay City Car Groomers",
    "wof:placetype":"venue"
},
  "geometry": {"coordinates":[144.35296630900001,-38.0985794067],"type":"Point"}
}