{
  "type": "Feature",
  "properties": {
    "addr:full":"117 Philip Hwy Elizabeth South SA 5112",
    "addr:housenumber":"117",
    "addr:postcode":"5112",
    "addr:street":"Philip Hwy",
    "iso:country":"AU",
    "sg:address":"117 Philip Hwy",
    "sg:city":"Elizabeth South",
    "sg:classifiers":[
        {
            "category":"Autos & Motor Vehicles",
            "subcategory":"Automobile Sales",
            "type":"Retail Goods"
        }
    ],
    "sg:phone":"+61 8 8287 3799",
    "sg:postcode":"5112",
    "sg:province":"SA",
    "sg:tags":[
        "car",
        "used"
    ],
    "wof:name":"Elizabeth Cheaper Car Centre",
    "wof:placetype":"venue"
},
  "geometry": {"coordinates":[138.662963867,-34.7318267822],"type":"Point"}
}