{
  "type": "Feature",
  "properties": {
    "iso:country":"AU",
    "sg:address":"Shop 29",
    "sg:city":"Waverley Gardens Shopping Centre Mulgrave",
    "sg:classifiers":[
        {
            "category":"Health Services",
            "subcategory":"Optometrist",
            "type":"Services"
        }
    ],
    "sg:phone":"+61 3 9547 7182",
    "sg:postcode":"3170",
    "sg:province":"VIC",
    "wof:name":"Optical World",
    "wof:placetype":"venue"
},
  "geometry": {"coordinates":[145.12216186500001,-37.8839416504],"type":"Point"}
}