{
  "type": "Feature",
  "properties": {
    "addr:full":"Unit 7 20 Malcolm Rd Maddington WA 6109",
    "addr:housenumber":"20",
    "addr:postcode":"6109",
    "addr:street":"Malcolm Rd",
    "iso:country":"AU",
    "sg:address":"Unit 7 20 Malcolm Rd",
    "sg:city":"Maddington",
    "sg:classifiers":[
        {
            "category":"Manufacturing",
            "subcategory":"Metals",
            "type":"Manufacturing & Wholesale Goods"
        }
    ],
    "sg:phone":"+61 8 9452 2131",
    "sg:postcode":"6109",
    "sg:province":"WA",
    "sg:tags":[
        "steel",
        "fabricator",
        "mfrs"
    ],
    "wof:name":"Willetton Steel Fabricators",
    "wof:placetype":"venue"
},
  "geometry": {"coordinates":[115.985069275,-32.0418128967],"type":"Point"}
}