{
  "type": "Feature",
  "properties": {
    "iso:country":"AU",
    "sg:address":"42 Moore Ave",
    "sg:city":"Montrose",
    "sg:classifiers":[
        {
            "category":"Education",
            "subcategory":"Special Training",
            "type":"Public Place"
        }
    ],
    "sg:phone":"+61 3 9761 9611",
    "sg:postcode":"3765",
    "sg:province":"VIC",
    "sg:tags":[
        "development"
    ],
    "wof:name":"Pacific Link Training Consultancy",
    "wof:placetype":"venue"
},
  "geometry": {"coordinates":[145.36378479000001,-37.8021583557],"type":"Point"}
}