{
  "type": "Feature",
  "properties": {
    "addr:full":"941 Wellington St West Perth WA 6005",
    "addr:housenumber":"941",
    "addr:postcode":"6005",
    "addr:street":"Wellington St",
    "iso:country":"AU",
    "sg:address":"941 Wellington St",
    "sg:city":"West Perth",
    "sg:classifiers":[
        {
            "category":"Building & Trades",
            "subcategory":"Construction",
            "type":"Services"
        }
    ],
    "sg:phone":"+61 8 9322 1488",
    "sg:postcode":"6005",
    "sg:province":"WA",
    "sg:tags":[
        "management"
    ],
    "wof:name":"Kilcullen And Clark",
    "wof:placetype":"venue"
},
  "geometry": {"coordinates":[115.843299866,-31.9465255737],"type":"Point"}
}