{
  "type": "Feature",
  "properties": {
    "addr:full":"6 Blanch St Oatley NSW 2223",
    "addr:housenumber":"6",
    "addr:postcode":"2223",
    "addr:street":"Blanch St",
    "iso:country":"AU",
    "sg:address":"6 Blanch St",
    "sg:city":"Oatley",
    "sg:classifiers":[
        {
            "category":"Professional",
            "subcategory":"Computer Services",
            "type":"Services"
        }
    ],
    "sg:phone":"+61 2 9570 9097",
    "sg:postcode":"2223",
    "sg:province":"NSW",
    "sg:tags":[
        "consultant",
        "system"
    ],
    "wof:name":"Progmatics Pty Ltd",
    "wof:placetype":"venue"
},
  "geometry": {"coordinates":[151.087127686,-33.9777107239],"type":"Point"}
}