{
  "type": "Feature",
  "properties": {
    "iso:country":"AU",
    "sg:address":"29 Tyalgum Ave",
    "sg:city":"Panania",
    "sg:classifiers":[
        {
            "category":"Personal",
            "subcategory":"Beauty Salon",
            "type":"Services"
        }
    ],
    "sg:phone":"+61 418 169 814",
    "sg:postcode":"2213",
    "sg:province":"NSW",
    "sg:tags":[
        "supply",
        "artist",
        "make-up"
    ],
    "wof:name":"Professional Bridal Makeup",
    "wof:placetype":"venue"
},
  "geometry": {"coordinates":[151.01005599999999,-33.95676],"type":"Point"}
}