{
  "type": "Feature",
  "properties": {
    "addr:full":"Unit 1 Flinders St Port Kembla NSW 2505",
    "addr:postcode":"2505",
    "addr:street":"Flinders St",
    "iso:country":"AU",
    "sg:address":"Unit 1 Flinders St",
    "sg:city":"Port Kembla",
    "sg:classifiers":[
        {
            "category":"Manufacturing",
            "subcategory":"Metals",
            "type":"Manufacturing & Wholesale Goods"
        }
    ],
    "sg:phone":"+61 2 4274 4300",
    "sg:postcode":"2505",
    "sg:province":"NSW",
    "sg:tags":[
        "steel",
        "fabricator",
        "mfrs"
    ],
    "wof:name":"Unifab Signs",
    "wof:placetype":"venue"
},
  "geometry": {"coordinates":[150.88832099999999,-34.473213],"type":"Point"}
}