{
  "type": "Feature",
  "properties": {
    "addr:full":"250 Glenroy Rd Glenroy VIC 3046",
    "addr:housenumber":"250",
    "addr:postcode":"3046",
    "addr:street":"Glenroy Rd",
    "iso:country":"AU",
    "sg:address":"250 Glenroy Rd",
    "sg:city":"Glenroy",
    "sg:classifiers":[
        {
            "category":"Food & Beverages",
            "subcategory":"Liquor & Beverages",
            "type":"Retail Goods"
        }
    ],
    "sg:phone":"+61 3 9300 3864",
    "sg:postcode":"3046",
    "sg:province":"VIC",
    "sg:tags":[
        "store"
    ],
    "wof:name":"Liquorland",
    "wof:placetype":"venue"
},
  "geometry": {"coordinates":[144.91635131800001,-37.7060928345],"type":"Point"}
}