{
  "type": "Feature",
  "properties": {
    "addr:full":"Shd1/Office 2 5 Tulagi Rd Palmerston NT 0830",
    "addr:housenumber":"5",
    "addr:postcode":"nt 0830",
    "addr:street":"Tulagi Rd",
    "iso:country":"AU",
    "sg:address":"Shd1/Office 2 5 Tulagi Rd",
    "sg:city":"Palmerston",
    "sg:classifiers":[
        {
            "category":"Professional",
            "subcategory":"Business Services",
            "type":"Services"
        }
    ],
    "sg:phone":"+61 8 8983 4422",
    "sg:postcode":"0830",
    "sg:province":"NT",
    "sg:tags":[
        "drafting"
    ],
    "wof:name":"Northern Building Designs",
    "wof:placetype":"venue"
},
  "geometry": {"coordinates":[130.99002100000001,-12.469336],"type":"Point"}
}