{
  "type": "Feature",
  "properties": {
    "addr:full":"32 Douglas St Blackburn VIC 3130",
    "addr:housenumber":"32",
    "addr:postcode":"3130",
    "addr:street":"Douglas St",
    "iso:country":"AU",
    "sg:address":"32 Douglas St",
    "sg:city":"Blackburn",
    "sg:classifiers":[
        {
            "category":"Building & Trades",
            "subcategory":"Plumbing",
            "type":"Services"
        }
    ],
    "sg:phone":"+61 408 057 025",
    "sg:postcode":"3130",
    "sg:province":"VIC",
    "sg:tags":[
        "plumber",
        "gasfitters"
    ],
    "wof:name":"Neville G Sprague Plumbing",
    "wof:placetype":"venue"
},
  "geometry": {"coordinates":[145.154174805,-37.8016738892],"type":"Point"}
}