{
  "type": "Feature",
  "properties": {
    "addr:full":"Commercial Rd Mildura VIC 3500",
    "addr:postcode":"3500",
    "addr:street":"Commercial Rd",
    "iso:country":"AU",
    "sg:address":"Commercial Rd",
    "sg:city":"Mildura",
    "sg:classifiers":[
        {
            "category":"Farming",
            "subcategory":"Berry Farm",
            "type":"Manufacturing & Wholesale Goods"
        }
    ],
    "sg:phone":"+61 3 5021 0488",
    "sg:postcode":"3500",
    "sg:province":"VIC",
    "sg:tags":[
        "fruit",
        "grower"
    ],
    "wof:name":"Mighty Melon Company",
    "wof:placetype":"venue"
},
  "geometry": {"coordinates":[142.07870483400001,-34.1685371399],"type":"Point"}
}