{
  "type": "Feature",
  "properties": {
    "iso:country":"AU",
    "sg:address":"7 Kananook Ave",
    "sg:city":"Seaford",
    "sg:classifiers":[
        {
            "category":"Building & Trades",
            "subcategory":"Pest Control",
            "type":"Services"
        }
    ],
    "sg:phone":"+61 3 9785 3853",
    "sg:postcode":"3198",
    "sg:province":"VIC",
    "sg:tags":[
        "equipment",
        "insect"
    ],
    "wof:name":"Ultra Violet Insect Exterminators, Germicidal Fixtures & Sterilizers",
    "wof:placetype":"venue"
},
  "geometry": {"coordinates":[145.128616333,-38.1137962341],"type":"Point"}
}