{
  "type": "Feature",
  "properties": {
    "iso:country":"AU",
    "sg:address":"261 Joseph St",
    "sg:city":"Ballarat",
    "sg:classifiers":[
        {
            "category":"Food & Beverages",
            "subcategory":"Groceries & Convenience Stores",
            "type":"Retail Goods"
        }
    ],
    "sg:phone":"+61 3 5332 7878",
    "sg:postcode":"3350",
    "sg:province":"VIC",
    "wof:name":"Te Sue & Ty",
    "wof:placetype":"venue"
},
  "geometry": {"coordinates":[143.87768600000001,-37.575943],"type":"Point"}
}