{
  "type": "Feature",
  "properties": {
    "addr:full":"85 Watsonia Rd Watsonia VIC 3087",
    "addr:housenumber":"85",
    "addr:postcode":"3087",
    "addr:street":"Watsonia Rd",
    "iso:country":"AU",
    "sg:address":"85 Watsonia Rd",
    "sg:city":"Watsonia",
    "sg:classifiers":[
        {
            "category":"Food & Beverages",
            "subcategory":"Bakery",
            "type":"Retail Goods"
        }
    ],
    "sg:phone":"+61 3 9435 2560",
    "sg:postcode":"3087",
    "sg:province":"VIC",
    "sg:tags":[
        "cake",
        "shop",
        "pastry"
    ],
    "wof:name":"Bakers Choice",
    "wof:placetype":"venue"
},
  "geometry": {"coordinates":[145.082794189,-37.7092552185],"type":"Point"}
}