{
  "type": "Feature",
  "properties": {
    "addr:full":"25/ 937 Marion Rd Mitchell Park SA 5043",
    "addr:housenumber":"25 / 937",
    "addr:postcode":"5043",
    "addr:street":"Marion Rd",
    "iso:country":"AU",
    "sg:address":"25/ 937 Marion Rd",
    "sg:city":"Mitchell Park",
    "sg:classifiers":[
        {
            "category":"Autos & Motor Vehicles",
            "subcategory":"Auto Supplies",
            "type":"Retail Goods"
        }
    ],
    "sg:phone":"+61 8 8296 6012",
    "sg:postcode":"5043",
    "sg:province":"SA",
    "sg:tags":[
        "accessory"
    ],
    "wof:name":"ISC Performance",
    "wof:placetype":"venue"
},
  "geometry": {"coordinates":[138.55873099999999,-35.013737],"type":"Point"}
}