{
  "type": "Feature",
  "properties": {
    "iso:country":"AU",
    "sg:address":"32 Gleadow St",
    "sg:city":"Evatt",
    "sg:classifiers":[
        {
            "category":"Building & Trades",
            "subcategory":"Construction",
            "type":"Services"
        }
    ],
    "sg:phone":"+61 413 606 611",
    "sg:postcode":"2617",
    "sg:province":"ACT",
    "sg:tags":[
        "window",
        "tinting"
    ],
    "wof:name":"Marks Mobile Window Tint",
    "wof:placetype":"venue"
},
  "geometry": {"coordinates":[149.07278442399999,-35.2110595703],"type":"Point"}
}