{
  "type": "Feature",
  "properties": {
    "iso:country":"AU",
    "sg:address":"14 Blackall St",
    "sg:city":"Woombye",
    "sg:classifiers":[
        {
            "category":"Wholesale",
            "subcategory":"Construction Materials",
            "type":"Manufacturing & Wholesale Goods"
        }
    ],
    "sg:phone":"+61 7 5442 1744",
    "sg:postcode":"4559",
    "sg:province":"QLD",
    "sg:tags":[
        "protective",
        "coating"
    ],
    "wof:name":"Acculine",
    "wof:placetype":"venue"
},
  "geometry": {"coordinates":[152.96507263199999,-26.660654068],"type":"Point"}
}