{
  "type": "Feature",
  "properties": {
    "iso:country":"AU",
    "sg:address":"115 Dixon Rd",
    "sg:city":"Rockingham",
    "sg:classifiers":[
        {
            "category":"Retail",
            "subcategory":"Auto Repair",
            "type":"Services"
        }
    ],
    "sg:phone":"+61 8 9527 8999",
    "sg:postcode":"6168",
    "sg:province":"WA",
    "sg:tags":[
        "fuel",
        "petrol",
        "injection"
    ],
    "wof:name":"Rockingham Electronic Fuel Injection",
    "wof:placetype":"venue"
},
  "geometry": {"coordinates":[115.773376,-32.276772],"type":"Point"}
}