{
  "type": "Feature",
  "properties": {
    "addr:full":"104 Church St Wollongong NSW 2500",
    "addr:housenumber":"104",
    "addr:postcode":"2500",
    "addr:street":"Church St",
    "iso:country":"AU",
    "sg:address":"104 Church St",
    "sg:city":"Wollongong",
    "sg:classifiers":[
        {
            "category":"Health Services",
            "subcategory":"Health Practitioner",
            "type":"Services"
        }
    ],
    "sg:phone":"+61 2 4225 7860",
    "sg:postcode":"2500",
    "sg:province":"NSW",
    "sg:tags":[
        "psychologist"
    ],
    "wof:name":"Grainger Jessica Dr Clinical Psychologist",
    "wof:placetype":"venue"
},
  "geometry": {"coordinates":[150.89372299999999,-34.431316],"type":"Point"}
}