{
  "type": "Feature",
  "properties": {
    "addr:full":"PO Box 61 Miners Rest VIC 3352",
    "addr:postcode":"3352",
    "iso:country":"AU",
    "sg:address":"PO Box 61",
    "sg:city":"Miners Rest",
    "sg:classifiers":[
        {
            "category":"Building & Trades",
            "subcategory":"Cleaning & Sanitation",
            "type":"Services"
        }
    ],
    "sg:phone":"+61 3 5334 6126",
    "sg:postcode":"3352",
    "sg:province":"VIC",
    "sg:tags":[
        "window"
    ],
    "wof:name":"Redline Cleaning",
    "wof:placetype":"venue"
},
  "geometry": {"coordinates":[143.79997299999999,-37.480789],"type":"Point"}
}