{
  "type": "Feature",
  "properties": {
    "addr:full":"5 Channel Hwy Kingston TAS 7050",
    "addr:housenumber":"5",
    "addr:postcode":"7050",
    "addr:street":"Channel Hwy",
    "iso:country":"AU",
    "sg:address":"5 Channel Hwy",
    "sg:city":"Kingston",
    "sg:classifiers":[
        {
            "category":"Structure",
            "subcategory":"Bridge",
            "type":"Public Place"
        }
    ],
    "sg:phone":"+61 3 6229 7799",
    "sg:postcode":"7050",
    "sg:province":"TAS",
    "sg:tags":[
        "chainsaw",
        "brushcutters"
    ],
    "wof:name":"Kingston Mowers & Saws",
    "wof:placetype":"venue"
},
  "geometry": {"coordinates":[147.31516999999999,-42.973919],"type":"Point"}
}