{
  "type": "Feature",
  "properties": {
    "iso:country":"AU",
    "sg:address":"15 Bugden Ave",
    "sg:city":"Alstonville",
    "sg:classifiers":[
        {
            "category":"Health Services",
            "subcategory":"Doctor",
            "type":"Services"
        }
    ],
    "sg:phone":"+61 2 6628 3101",
    "sg:postcode":"2477",
    "sg:province":"NSW",
    "sg:tags":[
        "medical",
        "practitioner"
    ],
    "wof:name":"Traise Ian L Dr",
    "wof:placetype":"venue"
},
  "geometry": {"coordinates":[153.43971252399999,-28.8411884308],"type":"Point"}
}