{
  "type": "Feature",
  "properties": {
    "addr:full":"17 Delatite Crt Warrandyte South VIC 3134",
    "addr:housenumber":"17",
    "addr:postcode":"3134",
    "addr:street":"Delatite Crt",
    "iso:country":"AU",
    "sg:address":"17 Delatite Crt",
    "sg:city":"Warrandyte South",
    "sg:classifiers":[
        {
            "category":"Building & Trades",
            "subcategory":"Cleaning & Sanitation",
            "type":"Services"
        }
    ],
    "sg:phone":"+61 417 536 690",
    "sg:postcode":"3134",
    "sg:province":"VIC",
    "sg:tags":[
        "chemical",
        "pressure",
        "steam",
        "contractor"
    ],
    "wof:name":"Aquapower High Pressure Cleaning",
    "wof:placetype":"venue"
},
  "geometry": {"coordinates":[145.23870849599999,-37.7747573853],"type":"Point"}
}