{
  "type": "Feature",
  "properties": {
    "addr:full":"85 Edith St Innisfail QLD 4860",
    "addr:housenumber":"85",
    "addr:postcode":"4860",
    "addr:street":"Edith St",
    "iso:country":"AU",
    "sg:address":"85 Edith St",
    "sg:city":"Innisfail",
    "sg:classifiers":[
        {
            "category":"Recreation",
            "subcategory":"Fishing",
            "type":"Entertainment"
        }
    ],
    "sg:phone":"+61 7 4061 1416",
    "sg:postcode":"4860",
    "sg:province":"QLD",
    "sg:tags":[
        "tackle"
    ],
    "wof:name":"Innisfail Tackle & Sports",
    "wof:placetype":"venue"
},
  "geometry": {"coordinates":[146.02842712399999,-17.5244235992],"type":"Point"}
}