{
  "type": "Feature",
  "properties": {
    "iso:country":"AU",
    "sg:address":"553 Rear Albany Hwy",
    "sg:city":"Victoria Park",
    "sg:classifiers":[
        {
            "category":"Health Services",
            "subcategory":"Doctor",
            "type":"Services"
        }
    ],
    "sg:phone":"+61 8 9355 4549",
    "sg:postcode":"6100",
    "sg:province":"WA",
    "sg:tags":[
        "medical",
        "practitioner"
    ],
    "wof:name":"Aviles Ma-Sarah Dr",
    "wof:placetype":"venue"
},
  "geometry": {"coordinates":[115.889968872,-31.9690055847],"type":"Point"}
}