{
  "type": "Feature",
  "properties": {
    "iso:country":"AU",
    "sg:address":"Hilltop Plaza Shopping Centre Cnr Hopetoun & Charl",
    "sg:city":"Charlestown",
    "sg:classifiers":[
        {
            "category":"Sports & Exercise",
            "subcategory":"Ski Slope",
            "type":"Entertainment"
        }
    ],
    "sg:phone":"+61 2 4942 5066",
    "sg:postcode":"2290",
    "sg:province":"NSW",
    "sg:tags":[
        "equipment",
        "hire",
        "retail",
        "snow"
    ],
    "wof:name":"Rebel Sport",
    "wof:placetype":"venue"
},
  "geometry": {"coordinates":[151.69488525400001,-32.9614562988],"type":"Point"}
}