{
  "type": "Feature",
  "properties": {
    "iso:country":"AU",
    "sg:address":"13 Exford Rd",
    "sg:city":"Melton South",
    "sg:classifiers":[
        {
            "category":"Fast Food",
            "type":"Food & Drink"
        }
    ],
    "sg:phone":"+61 3 9743 7404",
    "sg:postcode":"3338",
    "sg:province":"VIC",
    "sg:tags":[
        "away",
        "take"
    ],
    "wof:name":"T.J's Blue Sea Fish Shop",
    "wof:placetype":"venue"
},
  "geometry": {"coordinates":[144.574554,-37.704773],"type":"Point"}
}