{
  "type": "Feature",
  "properties": {
    "addr:full":"109 Lava St Warrnambool VIC 3280",
    "addr:housenumber":"109",
    "addr:postcode":"3280",
    "addr:street":"Lava St",
    "iso:country":"AU",
    "sg:address":"109 Lava St",
    "sg:city":"Warrnambool",
    "sg:classifiers":[
        {
            "category":"Organizations",
            "subcategory":"Non-profit Organization",
            "type":"Services"
        }
    ],
    "sg:phone":"+61 3 5561 9444",
    "sg:postcode":"3280",
    "sg:province":"VIC",
    "sg:tags":[
        "support",
        "disability",
        "organisation"
    ],
    "wof:name":"Glenelg Community Residential Services",
    "wof:placetype":"venue"
},
  "geometry": {"coordinates":[142.48570251500001,-38.3822479248],"type":"Point"}
}