{
  "type": "Feature",
  "properties": {
    "addr:full":"461 Lutwyche Rd Lutwyche QLD 4030",
    "addr:housenumber":"461",
    "addr:postcode":"4030",
    "addr:street":"Lutwyche Rd",
    "iso:country":"AU",
    "sg:address":"461 Lutwyche Rd",
    "sg:city":"Lutwyche",
    "sg:classifiers":[
        {
            "category":"Travel",
            "subcategory":"Resort",
            "type":"Entertainment"
        }
    ],
    "sg:phone":"+61 7 3632 8899",
    "sg:postcode":"4030",
    "sg:province":"QLD",
    "sg:tags":[
        "consultant",
        "timesharing"
    ],
    "wof:name":"Trendwest South Pacific Pty Ltd",
    "wof:placetype":"venue"
},
  "geometry": {"coordinates":[153.03370699999999,-27.424234],"type":"Point"}
}