{
  "type": "Feature",
  "properties": {
    "iso:country":"AU",
    "sg:address":"6 Freeman St",
    "sg:city":"Kingston",
    "sg:classifiers":[
        {
            "category":"Professional",
            "subcategory":"Engineering",
            "type":"Services"
        }
    ],
    "sg:phone":"+61 3 6229 2131",
    "sg:postcode":"7050",
    "sg:province":"TAS",
    "sg:tags":[
        "consulting",
        "engineer"
    ],
    "wof:name":"Panton D",
    "wof:placetype":"venue"
},
  "geometry": {"coordinates":[147.309662,-42.977528],"type":"Point"}
}