{
  "type": "Feature",
  "properties": {
    "addr:full":"44 Hiles St Alexandria NSW 2015",
    "addr:housenumber":"44",
    "addr:postcode":"2015",
    "addr:street":"Hiles St",
    "iso:country":"AU",
    "sg:address":"44 Hiles St",
    "sg:city":"Alexandria",
    "sg:classifiers":[
        {
            "category":"Manufacturing",
            "subcategory":"Rubber & Plastics",
            "type":"Manufacturing & Wholesale Goods"
        }
    ],
    "sg:phone":"+61 2 9319 4926",
    "sg:postcode":"2015",
    "sg:province":"NSW",
    "sg:tags":[
        "moulders"
    ],
    "wof:name":"Roko Packaging Co. Pty. Ltd.",
    "wof:placetype":"venue"
},
  "geometry": {"coordinates":[151.19943237300001,-33.9027900696],"type":"Point"}
}