{
  "type": "Feature",
  "properties": {
    "addr:full":"24 Cross St Brookvale NSW 2100",
    "addr:housenumber":"24",
    "addr:postcode":"2100",
    "addr:street":"Cross St",
    "iso:country":"AU",
    "sg:address":"24 Cross St",
    "sg:city":"Brookvale",
    "sg:classifiers":[
        {
            "category":"Building & Trades",
            "subcategory":"Locksmith",
            "type":"Services"
        }
    ],
    "sg:phone":"+61 2 8845 0777",
    "sg:postcode":"2100",
    "sg:province":"NSW",
    "sg:tags":[
        "lock"
    ],
    "wof:name":"Security Hardware Pty Ltd",
    "wof:placetype":"venue"
},
  "geometry": {"coordinates":[151.26550293,-33.764919281],"type":"Point"}
}