{
  "type": "Feature",
  "properties": {
    "addr:full":"Shop 9, CQU Commercial Centre, Yamba Rd Rockhampton QLD 4700",
    "addr:housenumber":"shop 9",
    "addr:postcode":"4700",
    "addr:street":"Cqu;Yamba Rd",
    "iso:country":"AU",
    "sg:address":"Shop 9, CQU Commercial Centre, Yamba Rd",
    "sg:city":"Rockhampton",
    "sg:classifiers":[
        {
            "category":"Fast Food",
            "type":"Food & Drink"
        }
    ],
    "sg:phone":"+61 7 4936 2711",
    "sg:postcode":"4700",
    "sg:province":"QLD",
    "sg:tags":[
        "away",
        "take"
    ],
    "wof:name":"Susys Asian Delight",
    "wof:placetype":"venue"
},
  "geometry": {"coordinates":[150.50942993199999,-23.4106502533],"type":"Point"}
}