{
  "type": "Feature",
  "properties": {
    "addr:full":"47 Redfern St Redfern NSW 2016",
    "addr:housenumber":"47",
    "addr:postcode":"2016",
    "addr:street":"Redfern St",
    "iso:country":"AU",
    "sg:address":"47 Redfern St",
    "sg:city":"Redfern",
    "sg:classifiers":[
        {
            "category":"Travel",
            "subcategory":"Hostel",
            "type":"Entertainment"
        }
    ],
    "sg:phone":"+61 2 9319 6304",
    "sg:postcode":"2016",
    "sg:province":"NSW",
    "sg:tags":[
        "home"
    ],
    "wof:name":"Missionholme",
    "wof:placetype":"venue"
},
  "geometry": {"coordinates":[151.20809936500001,-33.8934402466],"type":"Point"}
}