{
  "type": "Feature",
  "properties": {
    "iso:country":"AU",
    "sg:address":"50 George St",
    "sg:city":"Bathurst",
    "sg:classifiers":[
        {
            "category":"Building & Trades",
            "subcategory":"Construction",
            "type":"Services"
        }
    ],
    "sg:phone":"+61 412 739 663",
    "sg:postcode":"2795",
    "sg:province":"NSW",
    "sg:tags":[
        "contractor"
    ],
    "wof:name":"Asco Homes & Building Pty Ltd",
    "wof:placetype":"venue"
},
  "geometry": {"coordinates":[149.57850647000001,-33.41664505],"type":"Point"}
}