{
  "type": "Feature",
  "properties": {
    "addr:full":"Unit 1 10 Helium St Narangba QLD 4504",
    "addr:housenumber":"10",
    "addr:postcode":"4504",
    "addr:street":"Helium St",
    "iso:country":"AU",
    "sg:address":"Unit 1 10 Helium St",
    "sg:city":"Narangba",
    "sg:classifiers":[
        {
            "category":"Health Services",
            "subcategory":"Health Practitioner",
            "type":"Services"
        }
    ],
    "sg:phone":"+61 7 3888 3289",
    "sg:postcode":"4504",
    "sg:province":"QLD",
    "sg:tags":[
        "naturopath"
    ],
    "wof:name":"Glutenfree Bakery",
    "wof:placetype":"venue"
},
  "geometry": {"coordinates":[152.98495483400001,-27.1891422272],"type":"Point"}
}