{
  "type": "Feature",
  "properties": {
    "addr:full":"26 Arthur St Baulkham Hills NSW 2153",
    "addr:housenumber":"26",
    "addr:postcode":"2153",
    "addr:street":"Arthur St",
    "iso:country":"AU",
    "sg:address":"26 Arthur St",
    "sg:city":"Baulkham Hills",
    "sg:classifiers":[
        {
            "category":"Home & Garden",
            "subcategory":"Carpets & Floor Coverings",
            "type":"Retail Goods"
        }
    ],
    "sg:phone":"+61 2 9639 3601",
    "sg:postcode":"2153",
    "sg:province":"NSW",
    "sg:tags":[
        "tile",
        "wall"
    ],
    "wof:name":"Action Tiles",
    "wof:placetype":"venue"
},
  "geometry": {"coordinates":[150.97117614699999,-33.833782196],"type":"Point"}
}