{
  "type": "Feature",
  "properties": {
    "iso:country":"AU",
    "sg:address":"446 Collins St",
    "sg:city":"Melbourne",
    "sg:classifiers":[
        {
            "category":"Professional",
            "subcategory":"Management & Consulting",
            "type":"Services"
        }
    ],
    "sg:phone":"+61 3 9222 8900",
    "sg:postcode":"3000",
    "sg:province":"VIC",
    "sg:tags":[
        "consultant",
        "energy"
    ],
    "wof:name":"Edgecap",
    "wof:placetype":"venue"
},
  "geometry": {"coordinates":[144.959518433,-37.8173866272],"type":"Point"}
}