{
  "type": "Feature",
  "properties": {
    "addr:full":"87 Eatonvale Rd Tinana QLD 4650",
    "addr:housenumber":"87",
    "addr:postcode":"4650",
    "addr:street":"Eatonvale Rd",
    "iso:country":"AU",
    "sg:address":"87 Eatonvale Rd",
    "sg:city":"Tinana",
    "sg:classifiers":[
        {
            "category":"Building & Trades",
            "subcategory":"Construction",
            "type":"Services"
        }
    ],
    "sg:phone":"+61 7 4121 5353",
    "sg:postcode":"4650",
    "sg:province":"QLD",
    "sg:tags":[
        "earth",
        "excavating",
        "moving",
        "contractor"
    ],
    "wof:name":"Dirt Diggas",
    "wof:placetype":"venue"
},
  "geometry": {"coordinates":[152.657715,-25.523497],"type":"Point"}
}