{
  "type": "Feature",
  "properties": {
    "addr:full":"PO Box 689 Sylvania Waters NSW 2224",
    "addr:postcode":"2224",
    "iso:country":"AU",
    "sg:address":"PO Box 689",
    "sg:city":"Sylvania Waters",
    "sg:classifiers":[
        {
            "category":"Utilities",
            "subcategory":"Electric",
            "type":"Services"
        }
    ],
    "sg:phone":"+61 402 641 774",
    "sg:postcode":"2224",
    "sg:province":"NSW",
    "sg:tags":[
        "electrical",
        "contractor"
    ],
    "wof:name":"Sparkies Electrical",
    "wof:placetype":"venue"
},
  "geometry": {"coordinates":[151.10899352999999,-34.0229415894],"type":"Point"}
}