{
  "type": "Feature",
  "properties": {
    "iso:country":"AU",
    "sg:address":"U6/ 17 Keppel Drv",
    "sg:city":"Hallam",
    "sg:classifiers":[
        {
            "category":"Military Area",
            "subcategory":"Naval Base",
            "type":"Public Place"
        }
    ],
    "sg:phone":"+61 3 9796 5077",
    "sg:postcode":"3803",
    "sg:province":"VIC",
    "sg:tags":[
        "stand",
        "rack"
    ],
    "wof:name":"Erect a Rack",
    "wof:placetype":"venue"
},
  "geometry": {"coordinates":[145.27320861800001,-38.0157737732],"type":"Point"}
}