{
  "type": "Feature",
  "properties": {
    "addr:full":"14 Trevally St Tin Can Bay QLD 4580",
    "addr:housenumber":"14",
    "addr:postcode":"4580",
    "addr:street":"Trevally St",
    "iso:country":"AU",
    "sg:address":"14 Trevally St",
    "sg:city":"Tin Can Bay",
    "sg:classifiers":[
        {
            "category":"Building & Trades",
            "subcategory":"Pest Control",
            "type":"Services"
        }
    ],
    "sg:phone":"+61 407 765 866",
    "sg:postcode":"4580",
    "sg:province":"QLD",
    "wof:name":"Cooloola Pest Control",
    "wof:placetype":"venue"
},
  "geometry": {"coordinates":[153.00193786599999,-25.921289444],"type":"Point"}
}