{
  "type": "Feature",
  "properties": {
    "addr:full":"871 Centre Rd Bentleigh East VIC 3165",
    "addr:housenumber":"871",
    "addr:postcode":"3165",
    "addr:street":"Centre Rd",
    "iso:country":"AU",
    "sg:address":"871 Centre Rd",
    "sg:city":"Bentleigh East",
    "sg:classifiers":[
        {
            "category":"Industrial Area",
            "type":"Public Place"
        }
    ],
    "sg:phone":"+61 3 9579 6144",
    "sg:postcode":"3165",
    "sg:province":"VIC",
    "sg:tags":[
        "consulting",
        "chemist"
    ],
    "wof:name":"Hart Analytical Pty Ltd",
    "wof:placetype":"venue"
},
  "geometry": {"coordinates":[145.06483459500001,-37.9216995239],"type":"Point"}
}