{
  "type": "Feature",
  "properties": {
    "iso:country":"AU",
    "sg:address":"108 Perouse Rd",
    "sg:city":"Randwick",
    "sg:classifiers":[
        {
            "category":"Professional",
            "subcategory":"Business Services",
            "type":"Services"
        }
    ],
    "sg:phone":"+61 2 9314 6265",
    "sg:postcode":"2031",
    "sg:province":"NSW",
    "sg:tags":[
        "fashion",
        "agent"
    ],
    "wof:name":"Frantik Agencies Pty Ltd",
    "wof:placetype":"venue"
},
  "geometry": {"coordinates":[151.24354553200001,-33.9226951599],"type":"Point"}
}