{
  "type": "Feature",
  "properties": {
    "addr:full":"15 Devon St Bray Park QLD 4500",
    "addr:housenumber":"15",
    "addr:postcode":"4500",
    "addr:street":"Devon St Bray Park",
    "iso:country":"AU",
    "sg:address":"15 Devon St",
    "sg:city":"Bray Park",
    "sg:classifiers":[
        {
            "category":"Home & Garden",
            "subcategory":"Building Materials",
            "type":"Retail Goods"
        }
    ],
    "sg:phone":"+61 421 743 204",
    "sg:postcode":"4500",
    "sg:province":"QLD",
    "sg:tags":[
        "retaining",
        "wall"
    ],
    "wof:name":"Retaining Solutions",
    "wof:placetype":"venue"
},
  "geometry": {"coordinates":[152.95567321799999,-27.2892990112],"type":"Point"}
}