{
  "type": "Feature",
  "properties": {
    "iso:country":"AU",
    "sg:address":"25 Redgum Drv",
    "sg:city":"Burpengary",
    "sg:classifiers":[
        {
            "category":"Building & Trades",
            "subcategory":"Cleaning & Sanitation",
            "type":"Services"
        }
    ],
    "sg:phone":"+61 7 3886 6733",
    "sg:postcode":"4505",
    "sg:province":"QLD",
    "sg:tags":[
        "cleaner",
        "repairer",
        "roof"
    ],
    "wof:name":"Paragon Roof & Guttering",
    "wof:placetype":"venue"
},
  "geometry": {"coordinates":[152.925247192,-27.1681175232],"type":"Point"}
}