{
  "type": "Feature",
  "properties": {
    "iso:country":"AU",
    "sg:address":"Level 2, 28 President Ave",
    "sg:city":"Caringbah",
    "sg:classifiers":[
        {
            "category":"Health Services",
            "subcategory":"Doctor",
            "type":"Services"
        }
    ],
    "sg:phone":"+61 2 9525 9966",
    "sg:postcode":"2229",
    "sg:province":"NSW",
    "sg:tags":[
        "medical",
        "practitioner"
    ],
    "wof:name":"Parle Julie Dr",
    "wof:placetype":"venue"
},
  "geometry": {"coordinates":[151.12164306599999,-34.0430526733],"type":"Point"}
}