{
  "type": "Feature",
  "properties": {
    "iso:country":"AU",
    "sg:address":"97 Hume Hwy",
    "sg:city":"Chullora",
    "sg:classifiers":[
        {
            "category":"Travel",
            "subcategory":"Hotels & Motels",
            "type":"Entertainment"
        }
    ],
    "sg:phone":"+61 2 9758 7999",
    "sg:postcode":"2190",
    "sg:province":"NSW",
    "wof:name":"Sleep Express",
    "wof:placetype":"venue"
},
  "geometry": {"coordinates":[151.05642700000001,-33.892387],"type":"Point"}
}