{
  "type": "Feature",
  "properties": {
    "addr:full":"97 Sophia Rd Worrigee NSW 2540",
    "addr:housenumber":"97",
    "addr:postcode":"2540",
    "addr:street":"Sophia Rd",
    "iso:country":"AU",
    "sg:address":"97 Sophia Rd",
    "sg:city":"Worrigee",
    "sg:classifiers":[
        {
            "category":"Organizations",
            "subcategory":"Professional Association",
            "type":"Services"
        }
    ],
    "sg:phone":"+61 2 4423 0644",
    "sg:postcode":"2540",
    "sg:province":"NSW",
    "sg:tags":[
        "web",
        "internet"
    ],
    "wof:name":"Ozewebhost Pty Ltd",
    "wof:placetype":"venue"
},
  "geometry": {"coordinates":[150.62571716299999,-34.8983726501],"type":"Point"}
}