{
  "type": "Feature",
  "properties": {
    "addr:full":"Chivell St Elizabeth South SA 5112",
    "addr:postcode":"5112",
    "iso:country":"AU",
    "sg:address":"Chivell St",
    "sg:city":"Elizabeth South",
    "sg:classifiers":[
        {
            "category":"Education",
            "subcategory":"School",
            "type":"Public Place"
        }
    ],
    "sg:phone":"+61 8 8255 2219",
    "sg:postcode":"5112",
    "sg:province":"SA",
    "sg:tags":[
        "state",
        "except",
        "nsw"
    ],
    "wof:name":"Elizabeth South School",
    "wof:placetype":"venue"
},
  "geometry": {"coordinates":[138.66244506800001,-34.7318077087],"type":"Point"}
}