{
  "type": "Feature",
  "properties": {
    "iso:country":"AU",
    "sg:address":"10 Lilydale Ave",
    "sg:city":"Peakhurst",
    "sg:classifiers":[
        {
            "category":"Personal",
            "subcategory":"Beauty Salon",
            "type":"Services"
        }
    ],
    "sg:phone":"+61 2 9596 2621",
    "sg:postcode":"2210",
    "sg:province":"NSW",
    "sg:tags":[
        "supply",
        "artist",
        "make-up"
    ],
    "wof:name":"Devine Makeup Artistry",
    "wof:placetype":"venue"
},
  "geometry": {"coordinates":[151.059662,-33.964039],"type":"Point"}
}