{
  "type": "Feature",
  "properties": {
    "addr:full":"1010 Skyline Rd Yarra Glen VIC 3775",
    "addr:housenumber":"1010",
    "addr:postcode":"3775",
    "addr:street":"Skyline Rd",
    "iso:country":"AU",
    "sg:address":"1010 Skyline Rd",
    "sg:city":"Yarra Glen",
    "sg:classifiers":[
        {
            "category":"Travel",
            "subcategory":"Travel Agent",
            "type":"Entertainment"
        }
    ],
    "sg:phone":"+61 3 9730 2455",
    "sg:postcode":"3775",
    "sg:province":"VIC",
    "sg:tags":[
        "consultant"
    ],
    "wof:name":"Harvard Executive Travel",
    "wof:placetype":"venue"
},
  "geometry": {"coordinates":[145.350784,-37.64653],"type":"Point"}
}