{
  "type": "Feature",
  "properties": {
    "iso:country":"AU",
    "sg:address":"6 First Ave",
    "sg:city":"Caloundra",
    "sg:classifiers":[
        {
            "category":"Airline",
            "type":"Transportation"
        }
    ],
    "sg:phone":"+61 7 5491 8311",
    "sg:postcode":"4551",
    "sg:province":"QLD",
    "sg:tags":[
        "agent"
    ],
    "wof:name":"Suncity Travel Caloundra",
    "wof:placetype":"venue"
},
  "geometry": {"coordinates":[153.123657227,-26.8034286499],"type":"Point"}
}