{
  "type": "Feature",
  "properties": {
    "addr:full":"Lvl 1/ 462 Parramatta Rd Petersham NSW 2049",
    "addr:housenumber":"/ 462",
    "addr:postcode":"2049",
    "addr:street":"Parramatta Rd",
    "iso:country":"AU",
    "sg:address":"Lvl 1/ 462 Parramatta Rd",
    "sg:city":"Petersham",
    "sg:classifiers":[
        {
            "category":"Professional",
            "subcategory":"Art Services",
            "type":"Services"
        }
    ],
    "sg:phone":"+61 2 9560 0081",
    "sg:postcode":"2049",
    "sg:province":"NSW",
    "sg:tags":[
        "interior",
        "designer"
    ],
    "wof:name":"Aldo Virtich Pty Ltd",
    "wof:placetype":"venue"
},
  "geometry": {"coordinates":[151.15872200000001,-33.888184],"type":"Point"}
}