{
  "type": "Feature",
  "properties": {
    "iso:country":"AU",
    "sg:address":"42 Station St",
    "sg:city":"Waratah",
    "sg:classifiers":[
        {
            "category":"Arena",
            "subcategory":"Sports Club",
            "type":"Entertainment"
        }
    ],
    "sg:phone":"+61 2 4960 1866",
    "sg:postcode":"2298",
    "sg:province":"NSW",
    "sg:tags":[
        "union",
        "rugby"
    ],
    "wof:name":"Waratahs Rugby Club The",
    "wof:placetype":"venue"
},
  "geometry": {"coordinates":[151.72772216800001,-32.9030265808],"type":"Point"}
}