{
  "type": "Feature",
  "properties": {
    "addr:full":"10 King St Raymond Terrace NSW 2324",
    "addr:housenumber":"10",
    "addr:postcode":"2324",
    "addr:street":"King St",
    "iso:country":"AU",
    "sg:address":"10 King St",
    "sg:city":"Raymond Terrace",
    "sg:classifiers":[
        {
            "category":"Health Services",
            "subcategory":"Health Practitioner",
            "type":"Services"
        }
    ],
    "sg:phone":"+61 2 4983 1393",
    "sg:postcode":"2324",
    "sg:province":"NSW",
    "sg:tags":[
        "osteopath"
    ],
    "wof:name":"Chris Derkenne",
    "wof:placetype":"venue"
},
  "geometry": {"coordinates":[151.74334716800001,-32.7595558167],"type":"Point"}
}