{
  "type": "Feature",
  "properties": {
    "iso:country":"AU",
    "sg:address":"1050 Afterlee Rd",
    "sg:city":"Eden Creek",
    "sg:classifiers":[
        {
            "category":"Building & Trades",
            "subcategory":"Pest Control",
            "type":"Services"
        }
    ],
    "sg:phone":"+61 2 6633 3109",
    "sg:postcode":"2474",
    "sg:province":"NSW",
    "sg:tags":[
        "horse",
        "transport"
    ],
    "wof:name":"Kyogle Horse Transport",
    "wof:placetype":"venue"
},
  "geometry": {"coordinates":[152.90890502900001,-28.579120636],"type":"Point"}
}