{
  "type": "Feature",
  "properties": {
    "addr:full":"21 Duke St West Launceston TAS 7250",
    "addr:housenumber":"21",
    "addr:postcode":"7250",
    "addr:street":"Duke St West",
    "iso:country":"AU",
    "sg:address":"21 Duke St",
    "sg:city":"West Launceston",
    "sg:classifiers":[
        {
            "category":"Professional",
            "subcategory":"Management & Consulting",
            "type":"Services"
        }
    ],
    "sg:phone":"+61 3 6331 1671",
    "sg:postcode":"7250",
    "sg:province":"TAS",
    "sg:tags":[
        "consultant",
        "business"
    ],
    "wof:name":"Eio Pty Ltd",
    "wof:placetype":"venue"
},
  "geometry": {"coordinates":[147.13412475600001,-41.4531211853],"type":"Point"}
}