{
  "type": "Feature",
  "properties": {
    "addr:full":"19 Unwins Bridge Rd Sydenham NSW 2044",
    "addr:housenumber":"19",
    "addr:postcode":"2044",
    "addr:street":"Unwins Bridge Rd",
    "iso:country":"AU",
    "sg:address":"19 Unwins Bridge Rd",
    "sg:city":"Sydenham",
    "sg:classifiers":[
        {
            "category":"Banks & Credit Unions",
            "subcategory":"Bureau De Change",
            "type":"Services"
        }
    ],
    "sg:phone":"+61 2 9519 5416",
    "sg:postcode":"2044",
    "sg:province":"NSW",
    "sg:tags":[
        "repairs",
        "part",
        "appliance",
        "electrical"
    ],
    "wof:name":"Dyna Service",
    "wof:placetype":"venue"
},
  "geometry": {"coordinates":[151.16905199999999,-33.914471],"type":"Point"}
}