{
  "type": "Feature",
  "properties": {
    "iso:country":"AU",
    "sg:address":"102 Railway St",
    "sg:city":"Corrimal",
    "sg:classifiers":[
        {
            "category":"Personal",
            "subcategory":"Beauty Salon",
            "type":"Services"
        }
    ],
    "sg:phone":"+61 2 4285 5022",
    "sg:postcode":"2518",
    "sg:province":"NSW",
    "sg:tags":[
        "hairdresser"
    ],
    "wof:name":"Fionas Art of Hair",
    "wof:placetype":"venue"
},
  "geometry": {"coordinates":[150.89799500000001,-34.373138],"type":"Point"}
}