{
  "type": "Feature",
  "properties": {
    "iso:country":"AU",
    "sg:address":"St",
    "sg:city":"Marks on the Hill, 2 - 6 Hobart Rd, South Lau",
    "sg:classifiers":[
        {
            "category":"Education",
            "subcategory":"Dance Studio",
            "type":"Public Place"
        }
    ],
    "sg:phone":"+61 411 708 007",
    "sg:postcode":"7249",
    "sg:province":"TAS",
    "sg:tags":[
        "venue",
        "tuition"
    ],
    "wof:name":"Palmers Dance Studio",
    "wof:placetype":"venue"
},
  "geometry": {"coordinates":[147.15553283700001,-41.4599990845],"type":"Point"}
}