{
  "type": "Feature",
  "properties": {
    "iso:country":"AU",
    "sg:address":"89 York St",
    "sg:city":"Sydney",
    "sg:classifiers":[
        {
            "category":"Professional",
            "subcategory":"Engineering",
            "type":"Services"
        }
    ],
    "sg:phone":"+61 2 9299 9978",
    "sg:postcode":"2001",
    "sg:province":"NSW",
    "sg:tags":[
        "consulting",
        "engineer"
    ],
    "wof:name":"Hinds Blunden",
    "wof:placetype":"venue"
},
  "geometry": {"coordinates":[151.20599365199999,-33.8694534302],"type":"Point"}
}