{
  "type": "Feature",
  "properties": {
    "iso:country":"AU",
    "sg:address":"PO Box 3172",
    "sg:city":"Mt Druitt Village",
    "sg:classifiers":[
        {
            "category":"Health Services",
            "subcategory":"Doctor",
            "type":"Services"
        }
    ],
    "sg:phone":"+61 2 9832 7985",
    "sg:postcode":"2770",
    "sg:province":"NSW",
    "sg:tags":[
        "occupational",
        "safety"
    ],
    "wof:name":"Advocating Workplace Safety",
    "wof:placetype":"venue"
},
  "geometry": {"coordinates":[150.81158447300001,-33.7720489502],"type":"Point"}
}