{
  "type": "Feature",
  "properties": {
    "addr:full":"8 Glassford Ave Upper Ferntree Gully VIC 3156",
    "addr:housenumber":"8",
    "addr:postcode":"3156",
    "addr:street":"Glassford Ave",
    "iso:country":"AU",
    "sg:address":"8 Glassford Ave",
    "sg:city":"Upper Ferntree Gully",
    "sg:classifiers":[
        {
            "category":"Wholesale",
            "subcategory":"Machinery & Supplies",
            "type":"Manufacturing & Wholesale Goods"
        }
    ],
    "sg:phone":"+61 3 9758 0664",
    "sg:postcode":"3156",
    "sg:province":"VIC",
    "sg:tags":[
        "instrument",
        "scientific"
    ],
    "wof:name":"Petersen Glass Technologies",
    "wof:placetype":"venue"
},
  "geometry": {"coordinates":[145.32473754899999,-37.8936767578],"type":"Point"}
}