{
  "type": "Feature",
  "properties": {
    "addr:full":"4 Aral Crt Iluka WA 6028",
    "addr:housenumber":"4",
    "addr:postcode":"6028",
    "addr:street":"Aral Crt",
    "iso:country":"AU",
    "sg:address":"4 Aral Crt",
    "sg:city":"Iluka",
    "sg:classifiers":[
        {
            "category":"Shopping",
            "subcategory":"Stationery & Office Supplies",
            "type":"Retail Goods"
        }
    ],
    "sg:phone":"+61 8 9305 4335",
    "sg:postcode":"6028",
    "sg:province":"WA",
    "sg:tags":[
        "partition"
    ],
    "wof:name":"Padbury Ceilings & Partitions",
    "wof:placetype":"venue"
},
  "geometry": {"coordinates":[115.73124694800001,-31.7427654266],"type":"Point"}
}