{
  "type": "Feature",
  "properties": {
    "iso:country":"AU",
    "sg:address":"Unit 4/ 14 Halley Rd",
    "sg:city":"Balcatta",
    "sg:classifiers":[
        {
            "category":"Manufacturing",
            "subcategory":"Glass & Minerals",
            "type":"Manufacturing & Wholesale Goods"
        }
    ],
    "sg:phone":"+61 413 305 339",
    "sg:postcode":"6021",
    "sg:province":"WA",
    "sg:tags":[
        "etching"
    ],
    "wof:name":"Leadlight Abstractions",
    "wof:placetype":"venue"
},
  "geometry": {"coordinates":[115.825950623,-31.8616733551],"type":"Point"}
}