{
  "type": "Feature",
  "properties": {
    "addr:full":"Unit 6/ 10 Warton Rd Huntingdale WA 6110",
    "addr:housenumber":"10",
    "addr:postcode":"6110",
    "addr:street":"Warton Rd",
    "iso:country":"AU",
    "sg:address":"Unit 6/ 10 Warton Rd",
    "sg:city":"Huntingdale",
    "sg:classifiers":[
        {
            "category":"Real Estate",
            "subcategory":"Real Estate Agent",
            "type":"Services"
        }
    ],
    "sg:phone":"+61 8 9251 6688",
    "sg:postcode":"6110",
    "sg:province":"WA",
    "wof:name":"Brown Murray",
    "wof:placetype":"venue"
},
  "geometry": {"coordinates":[115.953460693,-32.0815849304],"type":"Point"}
}