{
  "type": "Feature",
  "properties": {
    "addr:full":"Cnr Tait & Britton Sts Smithfield NSW 2164",
    "addr:postcode":"2164",
    "addr:street":"Cnr",
    "iso:country":"AU",
    "sg:address":"Cnr Tait & Britton Sts",
    "sg:city":"Smithfield",
    "sg:classifiers":[
        {
            "category":"Banks & Credit Unions",
            "subcategory":"Bank",
            "type":"Services"
        }
    ],
    "sg:phone":"+61 2 9604 0022",
    "sg:postcode":"2164",
    "sg:province":"NSW",
    "sg:tags":[
        "leather",
        "cutting",
        "fabric",
        "plastic"
    ],
    "wof:name":"A Sew-Sure Product",
    "wof:placetype":"venue"
},
  "geometry": {"coordinates":[150.94415283199999,-33.8457565308],"type":"Point"}
}