{
  "type": "Feature",
  "properties": {
    "addr:full":"60 Garden Rd Clayton VIC 3168",
    "addr:housenumber":"60",
    "addr:postcode":"3168",
    "addr:street":"Garden Rd",
    "iso:country":"AU",
    "sg:address":"60 Garden Rd",
    "sg:city":"Clayton",
    "sg:classifiers":[
        {
            "category":"Building & Trades",
            "subcategory":"Equipment Rental",
            "type":"Services"
        }
    ],
    "sg:phone":"+61 3 9822 8222",
    "sg:postcode":"3168",
    "sg:province":"VIC",
    "sg:tags":[
        "demolition",
        "contractor"
    ],
    "wof:name":"eco recyclers Pty Ltd",
    "wof:placetype":"venue"
},
  "geometry": {"coordinates":[145.145996094,-37.9237709045],"type":"Point"}
}