{
  "type": "Feature",
  "properties": {
    "addr:full":"4 Sturt St Ballarat VIC 3350",
    "addr:housenumber":"4",
    "addr:postcode":"3350",
    "addr:street":"Sturt St",
    "iso:country":"AU",
    "sg:address":"4 Sturt St",
    "sg:city":"Ballarat",
    "sg:classifiers":[
        {
            "category":"Shopping",
            "subcategory":"Jewelry",
            "type":"Retail Goods"
        }
    ],
    "sg:phone":"+61 3 5333 7408",
    "sg:postcode":"3350",
    "sg:province":"VIC",
    "sg:tags":[
        "jeweller"
    ],
    "wof:name":"Sturt Street Gifts",
    "wof:placetype":"venue"
},
  "geometry": {"coordinates":[143.86042800000001,-37.561916],"type":"Point"}
}