{
  "type": "Feature",
  "properties": {
    "addr:full":"Cnr Manning & Suttie Rds Woollahra NSW 2025",
    "addr:postcode":"2025",
    "addr:street":"Cnr",
    "iso:country":"AU",
    "sg:address":"Cnr Manning & Suttie Rds",
    "sg:city":"Woollahra",
    "sg:classifiers":[
        {
            "category":"Professional",
            "subcategory":"Engineering",
            "type":"Services"
        }
    ],
    "sg:phone":"+61 2 9327 3774",
    "sg:postcode":"2025",
    "sg:province":"NSW",
    "sg:tags":[
        "engineer",
        "mechanical"
    ],
    "wof:name":"Cooper Park Garage",
    "wof:placetype":"venue"
},
  "geometry": {"coordinates":[151.24746704099999,-33.8860664368],"type":"Point"}
}