{
  "type": "Feature",
  "properties": {
    "iso:country":"AU",
    "sg:address":"1119 Cnr Great Western Hwy & Main Rd",
    "sg:city":"Lithgow",
    "sg:classifiers":[
        {
            "category":"Fast Food",
            "type":"Food & Drink"
        }
    ],
    "sg:phone":"+61 2 6353 1952",
    "sg:postcode":"2790",
    "sg:province":"NSW",
    "sg:tags":[
        "away",
        "take"
    ],
    "wof:name":"Red Rooster",
    "wof:placetype":"venue"
},
  "geometry": {"coordinates":[150.136184692,-33.483039856],"type":"Point"}
}