{
  "type": "Feature",
  "properties": {
    "addr:full":"65 Crooke St Bairnsdale VIC 3875",
    "addr:housenumber":"65",
    "addr:postcode":"3875",
    "addr:street":"Crooke St",
    "iso:country":"AU",
    "sg:address":"65 Crooke St",
    "sg:city":"Bairnsdale",
    "sg:classifiers":[
        {
            "category":"Home & Garden",
            "subcategory":"Carpets & Floor Coverings",
            "type":"Retail Goods"
        }
    ],
    "sg:phone":"+61 407 842 560",
    "sg:postcode":"3875",
    "sg:province":"VIC",
    "sg:tags":[
        "tile",
        "wall",
        "layer"
    ],
    "wof:name":"Stevens B D",
    "wof:placetype":"venue"
},
  "geometry": {"coordinates":[147.65159606899999,-37.8293037415],"type":"Point"}
}