{
  "type": "Feature",
  "properties": {
    "iso:country":"AU",
    "sg:address":"84 Maitland St",
    "sg:city":"Bingara",
    "sg:classifiers":[
        {
            "category":"Food & Beverages",
            "subcategory":"Bakery",
            "type":"Retail Goods"
        }
    ],
    "sg:phone":"+61 2 6724 1901",
    "sg:postcode":"2404",
    "sg:province":"NSW",
    "sg:tags":[
        "baker"
    ],
    "wof:name":"Bingara Bake House",
    "wof:placetype":"venue"
},
  "geometry": {"coordinates":[150.57205200199999,-29.8696708679],"type":"Point"}
}