{
  "type": "Feature",
  "properties": {
    "addr:full":"Suite 5,2nd Floor City Arcade Office Towers 207 Mu Perth WA 6000",
    "addr:housenumber":"5,2;207",
    "addr:postcode":"6000",
    "addr:street":"Nd Floor City",
    "iso:country":"AU",
    "sg:address":"Suite 5,2nd Floor City Arcade Office Towers 207 Mu",
    "sg:city":"Perth",
    "sg:classifiers":[
        {
            "category":"Manufacturing",
            "subcategory":"Jewelry",
            "type":"Manufacturing & Wholesale Goods"
        }
    ],
    "sg:phone":"+61 8 9322 5766",
    "sg:postcode":"6000",
    "sg:province":"WA",
    "sg:tags":[
        "designer",
        "jewellery"
    ],
    "wof:name":"Dieckmann Bros",
    "wof:placetype":"venue"
},
  "geometry": {"coordinates":[115.8543396,-31.9515380859],"type":"Point"}
}