{
  "type": "Feature",
  "properties": {
    "iso:country":"AU",
    "sg:address":"6934 Midland Hwy",
    "sg:city":"Scotsburn",
    "sg:classifiers":[
        {
            "category":"Manufacturing",
            "subcategory":"Musical Instruments",
            "type":"Manufacturing & Wholesale Goods"
        }
    ],
    "sg:phone":"+61 418 347 781",
    "sg:postcode":"3352",
    "sg:province":"VIC",
    "sg:tags":[
        "logging",
        "timber"
    ],
    "wof:name":"Timboon Logging Pty Ltd",
    "wof:placetype":"venue"
},
  "geometry": {"coordinates":[143.93052700000001,-37.670109],"type":"Point"}
}