{
  "type": "Feature",
  "properties": {
    "addr:full":"814 Caramut Rd Mailors Flat VIC 3275",
    "addr:housenumber":"814",
    "addr:postcode":"3275",
    "addr:street":"Caramut Rd",
    "iso:country":"AU",
    "sg:address":"814 Caramut Rd",
    "sg:city":"Mailors Flat",
    "sg:classifiers":[
        {
            "category":"Building & Trades",
            "subcategory":"Equipment Rental",
            "type":"Services"
        }
    ],
    "sg:phone":"+61 3 5565 9444",
    "sg:postcode":"3275",
    "sg:province":"VIC",
    "sg:tags":[
        "demolition",
        "contractor"
    ],
    "wof:name":"Mailors Flat Demolition and Antiques",
    "wof:placetype":"venue"
},
  "geometry": {"coordinates":[142.46191406200001,-38.3044013977],"type":"Point"}
}