{
  "type": "Feature",
  "properties": {
    "iso:country":"AU",
    "sg:address":"31 Preston Peak La",
    "sg:city":"Preston",
    "sg:classifiers":[
        {
            "category":"Farming",
            "subcategory":"Vineyard",
            "type":"Manufacturing & Wholesale Goods"
        }
    ],
    "sg:phone":"+61 7 4630 9499",
    "sg:postcode":"4352",
    "sg:province":"QLD",
    "sg:tags":[
        "winery"
    ],
    "wof:name":"Preston Peak Wines",
    "wof:placetype":"venue"
},
  "geometry": {"coordinates":[151.96623199999999,-27.651325],"type":"Point"}
}