{
  "type": "Feature",
  "properties": {
    "iso:country":"AU",
    "sg:address":"Unit 6, 32 Liney Ave",
    "sg:city":"Campsie",
    "sg:classifiers":[
        {
            "category":"Home & Garden",
            "subcategory":"Furniture",
            "type":"Retail Goods"
        }
    ],
    "sg:phone":"+61 2 9787 7013",
    "sg:postcode":"2194",
    "sg:province":"NSW",
    "sg:tags":[
        "business"
    ],
    "wof:name":"Ireka Office Furniture",
    "wof:placetype":"venue"
},
  "geometry": {"coordinates":[151.101578,-33.926163],"type":"Point"}
}