{
  "type": "Feature",
  "properties": {
    "iso:country":"AU",
    "sg:address":"193 - 195 Main Rd",
    "sg:city":"Huonville",
    "sg:classifiers":[
        {
            "category":"Professional",
            "subcategory":"Detective & Security Services",
            "type":"Services"
        }
    ],
    "sg:phone":"+61 3 6264 2511",
    "sg:postcode":"7109",
    "sg:province":"TAS",
    "sg:tags":[
        "equipment",
        "window",
        "doors"
    ],
    "wof:name":"Cliffords Glass & Glazing",
    "wof:placetype":"venue"
},
  "geometry": {"coordinates":[147.04730224599999,-43.0326461792],"type":"Point"}
}