{
  "type": "Feature",
  "properties": {
    "iso:country":"AU",
    "sg:address":"46 Longmorn Crs",
    "sg:city":"Carrara",
    "sg:classifiers":[
        {
            "category":"Building & Trades",
            "subcategory":"Construction",
            "type":"Services"
        }
    ],
    "sg:phone":"+61 416 252 704",
    "sg:postcode":"4211",
    "sg:province":"QLD",
    "sg:tags":[
        "fencing",
        "contractor"
    ],
    "wof:name":"Simon Oldham Bricklaying",
    "wof:placetype":"venue"
},
  "geometry": {"coordinates":[153.36398315400001,-28.0106391907],"type":"Point"}
}