{
  "type": "Feature",
  "properties": {
    "iso:country":"AU",
    "sg:address":"118 Kingsway Drv",
    "sg:city":"Lalor",
    "sg:classifiers":[
        {
            "category":"Education",
            "subcategory":"Kindergarten",
            "type":"Public Place"
        }
    ],
    "sg:phone":"+61 3 9465 1993",
    "sg:postcode":"3075",
    "sg:province":"VIC",
    "sg:tags":[
        "pre-schools"
    ],
    "wof:name":"Jacaranda Preschool",
    "wof:placetype":"venue"
},
  "geometry": {"coordinates":[145.00488281200001,-37.6641044617],"type":"Point"}
}