{
  "type": "Feature",
  "properties": {
    "addr:full":"6 Burne Crt Kew VIC 3101",
    "addr:housenumber":"6",
    "addr:postcode":"3101",
    "addr:street":"Burne Crt",
    "iso:country":"AU",
    "sg:address":"6 Burne Crt",
    "sg:city":"Kew",
    "sg:classifiers":[
        {
            "category":"Government",
            "subcategory":"Court House",
            "type":"Public Place"
        }
    ],
    "sg:phone":"+61 3 9818 2755",
    "sg:postcode":"3101",
    "sg:province":"VIC",
    "sg:tags":[
        "personal",
        "marriage",
        "family",
        "counselling"
    ],
    "wof:name":"Walter Glaser",
    "wof:placetype":"venue"
},
  "geometry": {"coordinates":[145.03460693400001,-37.8136787415],"type":"Point"}
}