{
  "type": "Feature",
  "properties": {
    "iso:country":"AU",
    "sg:address":"148 Curlewis St",
    "sg:city":"Bondi",
    "sg:classifiers":[
        {
            "category":"Cafe",
            "type":"Food & Drink"
        }
    ],
    "sg:phone":"+61 2 9365 4834",
    "sg:postcode":"2026",
    "sg:province":"NSW",
    "wof:name":"Potugalia",
    "wof:placetype":"venue"
},
  "geometry": {"coordinates":[151.27549743599999,-33.8895454407],"type":"Point"}
}