{
  "type": "Feature",
  "properties": {
    "addr:full":"45 Welshpool Rd Welshpool WA 6106",
    "addr:housenumber":"45",
    "addr:postcode":"6106",
    "addr:street":"Welshpool Rd",
    "iso:country":"AU",
    "sg:address":"45 Welshpool Rd",
    "sg:city":"Welshpool",
    "sg:classifiers":[
        {
            "category":"Retail",
            "subcategory":"Auto Repair",
            "type":"Services"
        }
    ],
    "sg:phone":"+61 8 9470 1117",
    "sg:postcode":"6106",
    "sg:province":"WA",
    "sg:tags":[
        "car",
        "restoration",
        "supply"
    ],
    "wof:name":"Restorers Hotline",
    "wof:placetype":"venue"
},
  "geometry": {"coordinates":[115.919891357,-31.9940910339],"type":"Point"}
}