{
  "type": "Feature",
  "properties": {
    "iso:country":"AU",
    "sg:address":"26 Firebrace St",
    "sg:city":"Horsham",
    "sg:classifiers":[
        {
            "category":"Education",
            "subcategory":"Music School",
            "type":"Public Place"
        }
    ],
    "sg:phone":"+61 3 5381 2202",
    "sg:postcode":"3400",
    "sg:province":"VIC",
    "sg:tags":[
        "teacher"
    ],
    "wof:name":"Rockstuff",
    "wof:placetype":"venue"
},
  "geometry": {"coordinates":[142.199905395,-36.7135467529],"type":"Point"}
}