{
  "type": "Feature",
  "properties": {
    "addr:full":"Shop 3 Fraser St Torquay QLD 4655",
    "addr:housenumber":"shop 3",
    "addr:postcode":"4655",
    "addr:street":"Fraser St",
    "iso:country":"AU",
    "sg:address":"Shop 3 Fraser St",
    "sg:city":"Torquay",
    "sg:classifiers":[
        {
            "category":"Personal",
            "subcategory":"Massage",
            "type":"Services"
        }
    ],
    "sg:phone":"+61 7 4125 6299",
    "sg:postcode":"4655",
    "sg:province":"QLD",
    "sg:tags":[
        "therapy"
    ],
    "wof:name":"Relax Wave Body & Beauty Shop",
    "wof:placetype":"venue"
},
  "geometry": {"coordinates":[152.87295499999999,-25.284441],"type":"Point"}
}