{
  "type": "Feature",
  "properties": {
    "addr:full":"Level 5 45 William St Melbourne VIC 3000",
    "addr:housenumber":"45",
    "addr:postcode":"3000",
    "addr:street":"William St",
    "iso:country":"AU",
    "sg:address":"Level 5 45 William St",
    "sg:city":"Melbourne",
    "sg:classifiers":[
        {
            "category":"Insurance",
            "subcategory":"Insurance Agent",
            "type":"Services"
        }
    ],
    "sg:phone":"+61 3 9629 4233",
    "sg:postcode":"3000",
    "sg:province":"VIC",
    "sg:tags":[
        "future",
        "broker"
    ],
    "wof:name":"Peter G Moloney & Associates Pty Ltd",
    "wof:placetype":"venue"
},
  "geometry": {"coordinates":[144.95936584500001,-37.8185272217],"type":"Point"}
}