{
  "type": "Feature",
  "properties": {
    "addr:full":"107- 109 Sackville St Collingwood VIC 3066",
    "addr:housenumber":"109",
    "addr:postcode":"3066",
    "addr:street":"Sackville St",
    "iso:country":"AU",
    "sg:address":"107- 109 Sackville St",
    "sg:city":"Collingwood",
    "sg:classifiers":[
        {
            "category":"Personal",
            "subcategory":"Skin Care",
            "type":"Services"
        }
    ],
    "sg:phone":"+61 3 9417 3466",
    "sg:postcode":"3066",
    "sg:province":"VIC",
    "sg:tags":[
        "merchant",
        "hide"
    ],
    "wof:name":"N.S.W. Leather Co Pty Ltd",
    "wof:placetype":"venue"
},
  "geometry": {"coordinates":[144.99029540999999,-37.7989768982],"type":"Point"}
}