{
  "type": "Feature",
  "properties": {
    "addr:full":"65 Franklin St Traralgon VIC 3844",
    "addr:housenumber":"65",
    "addr:postcode":"3844",
    "addr:street":"Franklin St",
    "iso:country":"AU",
    "sg:address":"65 Franklin St",
    "sg:city":"Traralgon",
    "sg:classifiers":[
        {
            "category":"Organizations",
            "subcategory":"Community Association",
            "type":"Services"
        }
    ],
    "sg:phone":"+61 428 884 443",
    "sg:postcode":"3844",
    "sg:province":"VIC",
    "sg:tags":[
        "shiatsu",
        "therapy"
    ],
    "wof:name":"Shiatsu & Complementry Therapy",
    "wof:placetype":"venue"
},
  "geometry": {"coordinates":[146.53807067899999,-38.1968612671],"type":"Point"}
}