{
  "type": "Feature",
  "properties": {
    "iso:country":"AU",
    "sg:address":"59 Pell Rd",
    "sg:city":"Wyuna",
    "sg:classifiers":[
        {
            "category":"Building & Trades",
            "subcategory":"Construction",
            "type":"Services"
        }
    ],
    "sg:phone":"+61 3 5859 4380",
    "sg:postcode":"3620",
    "sg:province":"VIC",
    "sg:tags":[
        "earth",
        "excavating",
        "moving",
        "contractor"
    ],
    "wof:name":"DJ & NT Foley Laser Grading",
    "wof:placetype":"venue"
},
  "geometry": {"coordinates":[145.04856872600001,-36.3059997559],"type":"Point"}
}