{
  "type": "Feature",
  "properties": {
    "addr:full":"8 Acacia Ave Albion Park NSW 2527",
    "addr:housenumber":"8",
    "addr:postcode":"2527",
    "addr:street":"Acacia Ave Albion Park",
    "iso:country":"AU",
    "sg:address":"8 Acacia Ave",
    "sg:city":"Albion Park",
    "sg:classifiers":[
        {
            "category":"Professional",
            "subcategory":"Printing & Photocopies",
            "type":"Services"
        }
    ],
    "sg:phone":"+61 2 4257 4201",
    "sg:postcode":"2527",
    "sg:province":"NSW",
    "sg:tags":[
        "screen",
        "printer"
    ],
    "wof:name":"Damon Bishop Graphics",
    "wof:placetype":"venue"
},
  "geometry": {"coordinates":[150.79583740199999,-34.5703620911],"type":"Point"}
}