{
  "type": "Feature",
  "properties": {
    "iso:country":"AU",
    "sg:address":"448 Canterbury Rd",
    "sg:city":"Forest Hill",
    "sg:classifiers":[
        {
            "category":"Education",
            "subcategory":"Music School",
            "type":"Public Place"
        }
    ],
    "sg:phone":"+61 3 9878 2586",
    "sg:postcode":"3131",
    "sg:province":"VIC",
    "sg:tags":[
        "teacher"
    ],
    "wof:name":"Dimpsey Sally",
    "wof:placetype":"venue"
},
  "geometry": {"coordinates":[145.17880249000001,-37.8356208801],"type":"Point"}
}