{
  "type": "Feature",
  "properties": {
    "iso:country":"AU",
    "sg:address":"1/ 21 Ocean Ave",
    "sg:city":"Double Bay",
    "sg:classifiers":[
        {
            "category":"Health Services",
            "subcategory":"Health Practitioner",
            "type":"Services"
        }
    ],
    "sg:phone":"+61 2 9362 0114",
    "sg:postcode":"2028",
    "sg:province":"NSW",
    "sg:tags":[
        "homoeopath"
    ],
    "wof:name":"Margaret Cawood",
    "wof:placetype":"venue"
},
  "geometry": {"coordinates":[151.23834228499999,-33.8774986267],"type":"Point"}
}