{
  "type": "Feature",
  "properties": {
    "addr:full":"8 Capel Ave Rosebud West VIC 3940",
    "addr:housenumber":"8",
    "addr:postcode":"3940",
    "addr:street":"Capel Ave",
    "iso:country":"AU",
    "sg:address":"8 Capel Ave",
    "sg:city":"Rosebud West",
    "sg:classifiers":[
        {
            "category":"Health Services",
            "subcategory":"Nursing And Care Facility",
            "type":"Services"
        }
    ],
    "sg:phone":"+61 3 5982 1811",
    "sg:postcode":"3940",
    "sg:province":"VIC",
    "sg:tags":[
        "home"
    ],
    "wof:name":"Rosebud Private Nursing Home",
    "wof:placetype":"venue"
},
  "geometry": {"coordinates":[144.87669372600001,-38.364238739],"type":"Point"}
}