{
  "type": "Feature",
  "properties": {
    "iso:country":"AU",
    "sg:address":"Shop 1, Cnr Murray & Carroll Rds",
    "sg:city":"Corrimal",
    "sg:classifiers":[
        {
            "category":"Retail",
            "subcategory":"Self-service Laundry",
            "type":"Services"
        }
    ],
    "sg:phone":"+61 2 4284 0280",
    "sg:postcode":"2518",
    "sg:province":"NSW",
    "wof:name":"East Corrimal Laundry",
    "wof:placetype":"venue"
},
  "geometry": {"coordinates":[150.88652,-34.375858],"type":"Point"}
}