{
  "type": "Feature",
  "properties": {
    "addr:full":"Level 3, 2 Martin Pl Sydney NSW 2000",
    "addr:housenumber":"2",
    "addr:postcode":"2000",
    "addr:street":"Martin Pl",
    "iso:country":"AU",
    "sg:address":"Level 3, 2 Martin Pl",
    "sg:city":"Sydney",
    "sg:classifiers":[
        {
            "category":"Banks & Credit Unions",
            "subcategory":"Financial Services",
            "type":"Services"
        }
    ],
    "sg:phone":"+61 2 9879 6643",
    "sg:postcode":"2000",
    "sg:province":"NSW",
    "sg:tags":[
        "annuity",
        "rollover",
        "superannuation",
        "consultant"
    ],
    "wof:name":"Actuaries in Super",
    "wof:placetype":"venue"
},
  "geometry": {"coordinates":[151.207275391,-33.8673057556],"type":"Point"}
}