{
  "type": "Feature",
  "properties": {
    "addr:full":"31 Substation Rd Image Flat QLD 4560",
    "addr:postcode":"4560",
    "addr:street":"Substation Rd",
    "iso:country":"AU",
    "sg:address":"31 Substation Rd",
    "sg:city":"Image Flat",
    "sg:classifiers":[
        {
            "category":"Education",
            "subcategory":"Music School",
            "type":"Public Place"
        }
    ],
    "sg:phone":"+61 7 5441 2386",
    "sg:postcode":"4560",
    "sg:province":"QLD",
    "sg:tags":[
        "teacher"
    ],
    "wof:name":"Allison Caterer",
    "wof:placetype":"venue"
},
  "geometry": {"coordinates":[152.94737243599999,-26.6092014313],"type":"Point"}
}