{
  "type": "Feature",
  "properties": {
    "iso:country":"AU",
    "sg:address":"Suite 5 54 Angove St",
    "sg:city":"North Perth",
    "sg:classifiers":[
        {
            "category":"Building & Trades",
            "subcategory":"Construction",
            "type":"Services"
        }
    ],
    "sg:phone":"+61 8 9228 4315",
    "sg:postcode":"6006",
    "sg:province":"WA",
    "sg:tags":[
        "contractor"
    ],
    "wof:name":"Starwest Constructions Pty Ltd",
    "wof:placetype":"venue"
},
  "geometry": {"coordinates":[115.857147217,-31.9295864105],"type":"Point"}
}