{
  "type": "Feature",
  "properties": {
    "addr:full":"23 Diamond Drv Ocean Reef WA 6027",
    "addr:housenumber":"23",
    "addr:postcode":"6027",
    "addr:street":"Diamond Drv",
    "iso:country":"AU",
    "sg:address":"23 Diamond Drv",
    "sg:city":"Ocean Reef",
    "sg:classifiers":[
        {
            "category":"Manufacturing",
            "subcategory":"Tools & Machinery",
            "type":"Manufacturing & Wholesale Goods"
        }
    ],
    "sg:phone":"+61 8 9403 2787",
    "sg:postcode":"6027",
    "sg:province":"WA",
    "sg:tags":[
        "earth",
        "excavating",
        "moving",
        "equipment"
    ],
    "wof:name":"All Weather Bobcats",
    "wof:placetype":"venue"
},
  "geometry": {"coordinates":[115.73750305199999,-31.7680435181],"type":"Point"}
}