{
  "type": "Feature",
  "properties": {
    "addr:full":"6 Jacqueline Crt Coolum Beach QLD 4573",
    "addr:housenumber":"6",
    "addr:postcode":"4573",
    "addr:street":"Jacqueline Crt",
    "iso:country":"AU",
    "sg:address":"6 Jacqueline Crt",
    "sg:city":"Coolum Beach",
    "sg:classifiers":[
        {
            "category":"Utilities",
            "type":"Services"
        }
    ],
    "sg:phone":"+61 1300 661 478",
    "sg:postcode":"4573",
    "sg:province":"QLD",
    "sg:tags":[
        "refrigeration",
        "industrial",
        "commercial",
        "retail"
    ],
    "wof:name":"Sunstate Climate Control Pty Ltd",
    "wof:placetype":"venue"
},
  "geometry": {"coordinates":[153.08543395999999,-26.5547027588],"type":"Point"}
}