{
  "type": "Feature",
  "properties": {
    "iso:country":"AU",
    "sg:address":"183c Main Rd",
    "sg:city":"Blackwood",
    "sg:classifiers":[
        {
            "category":"Personal",
            "type":"Services"
        }
    ],
    "sg:phone":"+61 8 8178 0233",
    "sg:postcode":"5051",
    "sg:province":"SA",
    "sg:tags":[
        "gift"
    ],
    "wof:name":"Blackwood Flowers & Gift Baskets",
    "wof:placetype":"venue"
},
  "geometry": {"coordinates":[138.623978,-35.025158],"type":"Point"}
}