{
  "type": "Feature",
  "properties": {
    "addr:full":"32- 34 Pendlebury Rd Cardiff NSW 2285",
    "addr:housenumber":"34",
    "addr:postcode":"2285",
    "addr:street":"Pendlebury Rd",
    "iso:country":"AU",
    "sg:address":"32- 34 Pendlebury Rd",
    "sg:city":"Cardiff",
    "sg:classifiers":[
        {
            "category":"Mining & Drilling",
            "type":"Manufacturing & Wholesale Goods"
        }
    ],
    "sg:phone":"+61 2 4954 0100",
    "sg:postcode":"2285",
    "sg:province":"NSW",
    "sg:tags":[
        "equipment",
        "quarrying",
        "supply"
    ],
    "wof:name":"Boart Longyear Pty Ltd",
    "wof:placetype":"venue"
},
  "geometry": {"coordinates":[151.65371704099999,-32.9449043274],"type":"Point"}
}