{
  "type": "Feature",
  "properties": {
    "addr:full":"19 Mahonga St Jerilderie NSW 2716",
    "addr:housenumber":"19",
    "addr:postcode":"2716",
    "addr:street":"Mahonga St",
    "iso:country":"AU",
    "sg:address":"19 Mahonga St",
    "sg:city":"Jerilderie",
    "sg:classifiers":[
        {
            "category":"Autos & Motor Vehicles",
            "subcategory":"Auto Supplies",
            "type":"Retail Goods"
        }
    ],
    "sg:phone":"+61 3 5886 1863",
    "sg:postcode":"2716",
    "sg:province":"NSW",
    "sg:tags":[
        "tyre"
    ],
    "wof:name":"Jerilderie Tyre Service",
    "wof:placetype":"venue"
},
  "geometry": {"coordinates":[145.72482299800001,-35.3567771912],"type":"Point"}
}