{
  "type": "Feature",
  "properties": {
    "iso:country":"AU",
    "sg:address":"96 Oxford St",
    "sg:city":"Paddington",
    "sg:classifiers":[
        {
            "category":"Food & Beverages",
            "subcategory":"Bakery",
            "type":"Retail Goods"
        }
    ],
    "sg:phone":"+61 2 9361 6617",
    "sg:postcode":"2021",
    "sg:province":"NSW",
    "sg:tags":[
        "cake",
        "shop",
        "pastry"
    ],
    "wof:name":"Sweet Art",
    "wof:placetype":"venue"
},
  "geometry": {"coordinates":[151.22134399399999,-33.8834686279],"type":"Point"}
}