{
  "type": "Feature",
  "properties": {
    "addr:full":"Home Building Centre 85 Leghorn St Rockingham WA 6168",
    "addr:housenumber":"85",
    "addr:postcode":"6168",
    "addr:street":"Leghorn St",
    "iso:country":"AU",
    "sg:address":"Home Building Centre 85 Leghorn St",
    "sg:city":"Rockingham",
    "sg:classifiers":[
        {
            "category":"Building & Trades",
            "subcategory":"Plumbing",
            "type":"Services"
        }
    ],
    "sg:phone":"+61 8 9592 9055",
    "sg:postcode":"6168",
    "sg:province":"WA",
    "sg:tags":[
        "plumber",
        "gasfitters"
    ],
    "wof:name":"Ballantyne Plumbing, Gas & Electrical (WA)",
    "wof:placetype":"venue"
},
  "geometry": {"coordinates":[115.73944899999999,-32.284576],"type":"Point"}
}