{
  "type": "Feature",
  "properties": {
    "addr:full":"Hepworth St Kenmore QLD 4069",
    "addr:postcode":"4069",
    "addr:street":"Hepworth St",
    "iso:country":"AU",
    "sg:address":"Hepworth St",
    "sg:city":"Kenmore",
    "sg:classifiers":[
        {
            "category":"Arena",
            "subcategory":"Sports Club",
            "type":"Entertainment"
        }
    ],
    "sg:phone":"+61 7 3378 9520",
    "sg:postcode":"4069",
    "sg:province":"QLD",
    "sg:tags":[
        "australian",
        "football",
        "rule"
    ],
    "wof:name":"Kenmore Junior Australian Football Club",
    "wof:placetype":"venue"
},
  "geometry": {"coordinates":[152.95184326200001,-27.5141105652],"type":"Point"}
}