{
  "type": "Feature",
  "properties": {
    "iso:country":"AU",
    "sg:address":"1 Armstrong St",
    "sg:city":"Charlton",
    "sg:classifiers":[
        {
            "category":"Education",
            "subcategory":"Kindergarten",
            "type":"Public Place"
        }
    ],
    "sg:phone":"+61 3 5491 1775",
    "sg:postcode":"3525",
    "sg:province":"VIC",
    "sg:tags":[
        "pre-schools"
    ],
    "wof:name":"Charlton & District Pre School Centre",
    "wof:placetype":"venue"
},
  "geometry": {"coordinates":[143.349976,-36.269058],"type":"Point"}
}