{
  "type": "Feature",
  "properties": {
    "iso:country":"AU",
    "sg:address":"8-12 Pace Rd",
    "sg:city":"Medina",
    "sg:classifiers":[
        {
            "category":"Health Services",
            "subcategory":"Doctor",
            "type":"Services"
        }
    ],
    "sg:phone":"+61 8 9419 2044",
    "sg:postcode":"6167",
    "sg:province":"WA",
    "sg:tags":[
        "medical",
        "practitioner"
    ],
    "wof:name":"Bhasin R Dr",
    "wof:placetype":"venue"
},
  "geometry": {"coordinates":[115.80645,-32.235954],"type":"Point"}
}