{
  "type": "Feature",
  "properties": {
    "addr:full":"Shp 1, 465 High St Mt Hutton NSW 2290",
    "addr:housenumber":"465",
    "addr:postcode":"2290",
    "addr:street":"High St",
    "iso:country":"AU",
    "sg:address":"Shp 1, 465 High St",
    "sg:city":"Mt Hutton",
    "sg:classifiers":[
        {
            "category":"Professional",
            "subcategory":"Accounting & Tax Preparation",
            "type":"Services"
        }
    ],
    "sg:phone":"+61 2 4934 3298",
    "sg:postcode":"2290",
    "sg:province":"NSW",
    "sg:tags":[
        "consultant",
        "taxation"
    ],
    "wof:name":"H & R Block",
    "wof:placetype":"venue"
},
  "geometry": {"coordinates":[151.72105407699999,-33.0113563538],"type":"Point"}
}