{
  "type": "Feature",
  "properties": {
    "addr:full":"57 Duthy St Malvern SA 5061",
    "addr:housenumber":"57",
    "addr:postcode":"5061",
    "addr:street":"Duthy St",
    "iso:country":"AU",
    "sg:address":"57 Duthy St",
    "sg:city":"Malvern",
    "sg:classifiers":[
        {
            "category":"Wholesale",
            "subcategory":"Seafood",
            "type":"Manufacturing & Wholesale Goods"
        }
    ],
    "sg:phone":"+61 8 8271 4225",
    "sg:postcode":"5061",
    "sg:province":"SA",
    "sg:tags":[
        "fish"
    ],
    "wof:name":"Gulf Seafoods Pty Ltd",
    "wof:placetype":"venue"
},
  "geometry": {"coordinates":[138.61512756400001,-34.9589996338],"type":"Point"}
}