{
  "type": "Feature",
  "properties": {
    "addr:full":"PO Box 1598 Preston South VIC 3072",
    "addr:postcode":"3072",
    "iso:country":"AU",
    "sg:address":"PO Box 1598",
    "sg:city":"Preston South",
    "sg:classifiers":[
        {
            "category":"Home & Garden",
            "subcategory":"Carpets & Floor Coverings",
            "type":"Retail Goods"
        }
    ],
    "sg:phone":"+61 401 575 103",
    "sg:postcode":"3072",
    "sg:province":"VIC",
    "sg:tags":[
        "tile",
        "wall",
        "layer"
    ],
    "wof:name":"Tiles By The Miles",
    "wof:placetype":"venue"
},
  "geometry": {"coordinates":[145.00909423799999,-37.7416496277],"type":"Point"}
}