{
  "type": "Feature",
  "properties": {
    "iso:country":"AU",
    "sg:address":"Factory 7, 25 Glenelg St",
    "sg:city":"Coolaroo",
    "sg:classifiers":[
        {
            "category":"Manufacturing",
            "subcategory":"Tools & Machinery",
            "type":"Manufacturing & Wholesale Goods"
        }
    ],
    "sg:phone":"+61 3 9302 1942",
    "sg:postcode":"3048",
    "sg:province":"VIC",
    "sg:tags":[
        "toolmaker"
    ],
    "wof:name":"C & B Tooling Pty Ltd",
    "wof:placetype":"venue"
},
  "geometry": {"coordinates":[144.938065,-37.654308],"type":"Point"}
}