{
  "type": "Feature",
  "properties": {
    "addr:full":"77 Union St Armadale VIC 3143",
    "addr:housenumber":"77",
    "addr:postcode":"3143",
    "addr:street":"Union St",
    "iso:country":"AU",
    "sg:address":"77 Union St",
    "sg:city":"Armadale",
    "sg:classifiers":[
        {
            "category":"Personal",
            "subcategory":"Beauty Salon",
            "type":"Services"
        }
    ],
    "sg:phone":"+61 3 9576 0997",
    "sg:postcode":"3143",
    "sg:province":"VIC",
    "sg:tags":[
        "hairdresser"
    ],
    "wof:name":"Regala Hair",
    "wof:placetype":"venue"
},
  "geometry": {"coordinates":[145.02801513700001,-37.859588623],"type":"Point"}
}