{
  "type": "Feature",
  "properties": {
    "addr:full":"263 Maroondah Hwy Ringwood VIC 3134",
    "addr:housenumber":"263",
    "addr:postcode":"3134",
    "addr:street":"Maroondah Hwy",
    "iso:country":"AU",
    "sg:address":"263 Maroondah Hwy",
    "sg:city":"Ringwood",
    "sg:classifiers":[
        {
            "category":"Shopping",
            "subcategory":"Computers & Home Electronics",
            "type":"Retail Goods"
        }
    ],
    "sg:phone":"+61 3 9870 2033",
    "sg:postcode":"3134",
    "sg:province":"VIC",
    "sg:tags":[
        "small",
        "equipment",
        "business"
    ],
    "wof:name":"AMT Electronics",
    "wof:placetype":"venue"
},
  "geometry": {"coordinates":[145.233642578,-37.8131866455],"type":"Point"}
}