{
  "type": "Feature",
  "properties": {
    "iso:country":"AU",
    "sg:address":"1715 Princes Hwy",
    "sg:city":"Oakleigh",
    "sg:classifiers":[
        {
            "category":"Banks & Credit Unions",
            "subcategory":"Investment Brokerage",
            "type":"Services"
        }
    ],
    "sg:phone":"+61 3 9543 2892",
    "sg:postcode":"3166",
    "sg:province":"VIC",
    "sg:tags":[
        "broker"
    ],
    "wof:name":"Carfinder",
    "wof:placetype":"venue"
},
  "geometry": {"coordinates":[145.105712891,-37.9005317688],"type":"Point"}
}