{
  "type": "Feature",
  "properties": {
    "iso:country":"AU",
    "sg:address":"13 Zircon St",
    "sg:city":"Bayview Heights",
    "sg:classifiers":[
        {
            "category":"Travel",
            "subcategory":"Travel Agent",
            "type":"Entertainment"
        }
    ],
    "sg:phone":"+61 7 4033 0242",
    "sg:postcode":"4868",
    "sg:province":"QLD",
    "sg:tags":[
        "tour",
        "holiday",
        "adventure"
    ],
    "wof:name":"Peachs Off The Beaten Track",
    "wof:placetype":"venue"
},
  "geometry": {"coordinates":[145.732879639,-16.9611644745],"type":"Point"}
}