{
  "type": "Feature",
  "properties": {
    "iso:country":"AU",
    "sg:address":"53/21 Norton St",
    "sg:city":"Leichhardt",
    "sg:classifiers":[
        {
            "category":"Education",
            "subcategory":"Special Training",
            "type":"Public Place"
        }
    ],
    "sg:phone":"+61 2 9568 1783",
    "sg:postcode":"2040",
    "sg:province":"NSW",
    "sg:tags":[
        "development"
    ],
    "wof:name":"Morgan Griffith",
    "wof:placetype":"venue"
},
  "geometry": {"coordinates":[151.157669,-33.887093],"type":"Point"}
}