{
  "type": "Feature",
  "properties": {
    "iso:country":"AU",
    "sg:address":"184a Church St",
    "sg:city":"Mudgee",
    "sg:classifiers":[
        {
            "category":"Personal",
            "subcategory":"Beauty Salon",
            "type":"Services"
        }
    ],
    "sg:phone":"+61 2 6372 2600",
    "sg:postcode":"2850",
    "sg:province":"NSW",
    "sg:tags":[
        "hairdresser"
    ],
    "wof:name":"Studio 184",
    "wof:placetype":"venue"
},
  "geometry": {"coordinates":[149.586014,-32.603931],"type":"Point"}
}