{
  "type": "Feature",
  "properties": {
    "addr:full":"4 Rowley St North Haven NSW 2443",
    "addr:housenumber":"4",
    "addr:postcode":"2443",
    "addr:street":"Rowley St",
    "iso:country":"AU",
    "sg:address":"4 Rowley St",
    "sg:city":"North Haven",
    "sg:classifiers":[
        {
            "category":"Retail",
            "subcategory":"Repair Shop",
            "type":"Services"
        }
    ],
    "sg:phone":"+61 2 6559 7276",
    "sg:postcode":"2443",
    "sg:province":"NSW",
    "sg:tags":[
        "machine",
        "repairs",
        "part",
        "dryer",
        "washing"
    ],
    "wof:name":"Bowler A T & J W",
    "wof:placetype":"venue"
},
  "geometry": {"coordinates":[152.820404,-31.638008],"type":"Point"}
}