{
  "type": "Feature",
  "properties": {
    "iso:country":"AU",
    "sg:address":"Apt 211",
    "sg:city":"Stant&#039; Elia The Esplanade Docklands",
    "sg:classifiers":[
        {
            "category":"Wholesale",
            "subcategory":"Painting Supplies",
            "type":"Manufacturing & Wholesale Goods"
        }
    ],
    "sg:phone":"+61 417 367 569",
    "sg:postcode":"3008",
    "sg:province":"VIC",
    "sg:tags":[
        "painter"
    ],
    "wof:name":"Globak Paints & Chemicals",
    "wof:placetype":"venue"
},
  "geometry": {"coordinates":[144.93801879899999,-37.8173408508],"type":"Point"}
}