{
  "type": "Feature",
  "properties": {
    "iso:country":"AU",
    "sg:address":"401 New South Head Rd",
    "sg:city":"Double Bay",
    "sg:classifiers":[
        {
            "category":"Real Estate",
            "subcategory":"Real Estate Agent",
            "type":"Services"
        }
    ],
    "sg:phone":"+61 2 9328 6404",
    "sg:postcode":"2028",
    "sg:province":"NSW",
    "wof:name":"Hudson Realty",
    "wof:placetype":"venue"
},
  "geometry": {"coordinates":[151.24302673299999,-33.877822876],"type":"Point"}
}