{
  "type": "Feature",
  "properties": {
    "addr:full":"Cnr Lyons & Hartley Sts Cairns QLD 4870",
    "addr:postcode":"4870",
    "addr:street":"Cnr",
    "iso:country":"AU",
    "sg:address":"Cnr Lyons & Hartley Sts",
    "sg:city":"Cairns",
    "sg:classifiers":[
        {
            "category":"Building & Trades",
            "subcategory":"Construction",
            "type":"Services"
        }
    ],
    "sg:phone":"+61 7 4052 4488",
    "sg:postcode":"4870",
    "sg:province":"QLD",
    "sg:tags":[
        "scaffolding"
    ],
    "wof:name":"Paramount Hire",
    "wof:placetype":"venue"
},
  "geometry": {"coordinates":[145.761062622,-16.9455051422],"type":"Point"}
}