{
  "type": "Feature",
  "properties": {
    "addr:full":"\"Bookamerrie\" St George QLD 4487",
    "addr:postcode":"4487",
    "iso:country":"AU",
    "sg:address":"\"Bookamerrie\"",
    "sg:city":"St George",
    "sg:classifiers":[
        {
            "category":"Farming",
            "subcategory":"Farm",
            "type":"Manufacturing & Wholesale Goods"
        }
    ],
    "sg:phone":"+61 7 4625 2188",
    "sg:postcode":"4487",
    "sg:province":"QLD",
    "sg:tags":[
        "farmer"
    ],
    "wof:name":"Rogan Pastoral Co.",
    "wof:placetype":"venue"
},
  "geometry": {"coordinates":[148.58096313499999,-28.0376491547],"type":"Point"}
}