{
  "type": "Feature",
  "properties": {
    "addr:full":"PO Box 97 Greenwith SA 5125",
    "addr:postcode":"5125",
    "iso:country":"AU",
    "sg:address":"PO Box 97",
    "sg:city":"Greenwith",
    "sg:classifiers":[
        {
            "category":"Arts & Performance",
            "subcategory":"Music",
            "type":"Entertainment"
        }
    ],
    "sg:phone":"+61 8 8289 7465",
    "sg:postcode":"5125",
    "sg:province":"SA",
    "sg:tags":[
        "mobile",
        "jockey",
        "disc"
    ],
    "wof:name":"Supreme Sound Mobile DJ",
    "wof:placetype":"venue"
},
  "geometry": {"coordinates":[138.718918,-34.769691],"type":"Point"}
}