{
  "type": "Feature",
  "properties": {
    "addr:full":"Shop 1, 18 Karalta Rd Erina NSW 2250",
    "addr:housenumber":"shop;18",
    "addr:postcode":"2250",
    "addr:street":"Karalta Rd",
    "iso:country":"AU",
    "sg:address":"Shop 1, 18 Karalta Rd",
    "sg:city":"Erina",
    "sg:classifiers":[
        {
            "category":"Banks & Credit Unions",
            "subcategory":"Bank",
            "type":"Services"
        }
    ],
    "sg:phone":"+61 2 4365 0900",
    "sg:postcode":"2250",
    "sg:province":"NSW",
    "sg:tags":[
        "broker",
        "mortgage"
    ],
    "wof:name":"Mortgage Choice",
    "wof:placetype":"venue"
},
  "geometry": {"coordinates":[151.33888244600001,-33.3975830078],"type":"Point"}
}