{
  "type": "Feature",
  "properties": {
    "addr:full":"6a St Andrews Shopng Cntr St Andrews NSW 2566",
    "addr:housenumber":"6a",
    "addr:postcode":"2566",
    "addr:street":"St",
    "iso:country":"AU",
    "sg:address":"6a St Andrews Shopng Cntr",
    "sg:city":"St Andrews",
    "sg:classifiers":[
        {
            "category":"Food & Beverages",
            "subcategory":"Bakery",
            "type":"Retail Goods"
        }
    ],
    "sg:phone":"+61 2 9603 7302",
    "sg:postcode":"2566",
    "sg:province":"NSW",
    "sg:tags":[
        "baker"
    ],
    "wof:name":"St Andrews Bakery",
    "wof:placetype":"venue"
},
  "geometry": {"coordinates":[150.82818603499999,-34.013633728],"type":"Point"}
}