{
  "type": "Feature",
  "properties": {
    "iso:country":"AU",
    "sg:address":"Unit 1, 8 Leda Drv",
    "sg:city":"Andrews",
    "sg:classifiers":[
        {
            "category":"Professional",
            "subcategory":"Printing & Photocopies",
            "type":"Services"
        }
    ],
    "sg:phone":"+61 7 5576 2341",
    "sg:postcode":"4220",
    "sg:province":"QLD",
    "sg:tags":[
        "photocopying"
    ],
    "wof:name":"Worldwide Online Printing",
    "wof:placetype":"venue"
},
  "geometry": {"coordinates":[153.44325256400001,-28.0932178497],"type":"Point"}
}