{
  "type": "Feature",
  "properties": {
    "addr:full":"Unit 2, 71 Bushmead Rd Hazelmere WA 6055",
    "addr:housenumber":"71",
    "addr:postcode":"6055",
    "addr:street":"Bushmead Rd",
    "iso:country":"AU",
    "sg:address":"Unit 2, 71 Bushmead Rd",
    "sg:city":"Hazelmere",
    "sg:classifiers":[
        {
            "category":"Real Estate",
            "subcategory":"Real Estate Agent",
            "type":"Services"
        }
    ],
    "sg:phone":"+61 8 9274 0056",
    "sg:postcode":"6055",
    "sg:province":"WA",
    "sg:tags":[
        "handyman's",
        "equipment",
        "hire",
        "builders",
        "contractor"
    ],
    "wof:name":"Kenco Hire",
    "wof:placetype":"venue"
},
  "geometry": {"coordinates":[116.010094,-31.91049],"type":"Point"}
}