{
  "type": "Feature",
  "properties": {
    "iso:country":"AU",
    "sg:address":"6 Paramount Pl",
    "sg:city":"Glenning Valley",
    "sg:classifiers":[
        {
            "category":"Building & Trades",
            "subcategory":"Pest Control",
            "type":"Services"
        }
    ],
    "sg:phone":"+61 2 4388 6411",
    "sg:postcode":"2261",
    "sg:province":"NSW",
    "wof:name":"Erina Pest Control",
    "wof:placetype":"venue"
},
  "geometry": {"coordinates":[151.42749,-33.335827],"type":"Point"}
}