{
  "type": "Feature",
  "properties": {
    "addr:full":"20 Colong Pl Wagga Wagga NSW 2650",
    "addr:housenumber":"20",
    "addr:postcode":"2650",
    "addr:street":"Colong Pl",
    "iso:country":"AU",
    "sg:address":"20 Colong Pl",
    "sg:city":"Wagga Wagga",
    "sg:classifiers":[
        {
            "category":"Real Estate",
            "subcategory":"Architect",
            "type":"Services"
        }
    ],
    "sg:phone":"+61 2 6921 1118",
    "sg:postcode":"2650",
    "sg:province":"NSW",
    "sg:tags":[
        "building",
        "designer"
    ],
    "wof:name":"Kerry Smith Designs Pty Ltd",
    "wof:placetype":"venue"
},
  "geometry": {"coordinates":[147.378829956,-35.1295394897],"type":"Point"}
}