{
  "type": "Feature",
  "properties": {
    "iso:country":"AU",
    "sg:address":"42 Lyons St",
    "sg:city":"Warwick",
    "sg:classifiers":[
        {
            "category":"Retail",
            "subcategory":"Auto Repair",
            "type":"Services"
        }
    ],
    "sg:phone":"+61 7 4661 3548",
    "sg:postcode":"4370",
    "sg:province":"QLD",
    "sg:tags":[
        "repairer",
        "motor",
        "engineer"
    ],
    "wof:name":"Mal Wood Automotive",
    "wof:placetype":"venue"
},
  "geometry": {"coordinates":[152.03909301799999,-28.221988678],"type":"Point"}
}