{
  "type": "Feature",
  "properties": {
    "iso:country":"AU",
    "sg:address":"68 Herbert St",
    "sg:city":"Ingham",
    "sg:classifiers":[
        {
            "category":"Food & Beverages",
            "subcategory":"Liquor & Beverages",
            "type":"Retail Goods"
        }
    ],
    "sg:phone":"+61 7 4776 1166",
    "sg:postcode":"4850",
    "sg:province":"QLD",
    "sg:tags":[
        "store"
    ],
    "wof:name":"Victoria Hotel",
    "wof:placetype":"venue"
},
  "geometry": {"coordinates":[146.159866333,-18.6485958099],"type":"Point"}
}