{
  "type": "Feature",
  "properties": {
    "addr:full":"Fcty2/ 10 Rutherford Rd Seaford VIC 3198",
    "addr:housenumber":"10",
    "addr:postcode":"3198",
    "addr:street":"Rutherford Rd",
    "iso:country":"AU",
    "sg:address":"Fcty2/ 10 Rutherford Rd",
    "sg:city":"Seaford",
    "sg:classifiers":[
        {
            "category":"Retail",
            "subcategory":"Auto Repair",
            "type":"Services"
        }
    ],
    "sg:phone":"+61 3 9775 1038",
    "sg:postcode":"3198",
    "sg:province":"VIC",
    "sg:tags":[
        "repairer",
        "motor",
        "engineer"
    ],
    "wof:name":"Prestige Performance Automotive",
    "wof:placetype":"venue"
},
  "geometry": {"coordinates":[145.15077209500001,-38.0987472534],"type":"Point"}
}