{
  "type": "Feature",
  "properties": {
    "addr:full":"Level 9, 39- 41 York St Sydney NSW 2000",
    "addr:housenumber":"39 41",
    "addr:postcode":"2000",
    "addr:street":"York St",
    "iso:country":"AU",
    "sg:address":"Level 9, 39- 41 York St",
    "sg:city":"Sydney",
    "sg:classifiers":[
        {
            "category":"Airline",
            "type":"Transportation"
        }
    ],
    "sg:phone":"+61 2 9290 1148",
    "sg:postcode":"2000",
    "sg:province":"NSW",
    "sg:tags":[
        "agent"
    ],
    "wof:name":"China Eastern Airlines",
    "wof:placetype":"venue"
},
  "geometry": {"coordinates":[151.205688477,-33.8668022156],"type":"Point"}
}