{
  "type": "Feature",
  "properties": {
    "addr:full":"1/ 16 Belgrave St Kempsey NSW 2440",
    "addr:housenumber":"/ 16",
    "addr:postcode":"2440",
    "addr:street":"Belgrave St",
    "iso:country":"AU",
    "sg:address":"1/ 16 Belgrave St",
    "sg:city":"Kempsey",
    "sg:classifiers":[
        {
            "category":"Banks & Credit Unions",
            "subcategory":"Financial Services",
            "type":"Services"
        }
    ],
    "sg:phone":"+61 2 6562 8277",
    "sg:postcode":"2440",
    "sg:province":"NSW",
    "sg:tags":[
        "loan",
        "finance",
        "mortgage"
    ],
    "wof:name":"Westlawn Finance Limited",
    "wof:placetype":"venue"
},
  "geometry": {"coordinates":[152.84161399999999,-31.080713],"type":"Point"}
}