{
  "type": "Feature",
  "properties": {
    "addr:full":"7 Beaver St Webberton WA 6530",
    "addr:housenumber":"7",
    "addr:postcode":"6530",
    "addr:street":"Beaver St",
    "iso:country":"AU",
    "sg:address":"7 Beaver St",
    "sg:city":"Webberton",
    "sg:classifiers":[
        {
            "category":"Commercial Area",
            "type":"Public Place"
        }
    ],
    "sg:phone":"+61 8 9964 2880",
    "sg:postcode":"6530",
    "sg:province":"WA",
    "sg:tags":[
        "heavy",
        "carrier"
    ],
    "wof:name":"Boss Transport & Services",
    "wof:placetype":"venue"
},
  "geometry": {"coordinates":[114.633262634,-28.7571315765],"type":"Point"}
}