{
  "type": "Feature",
  "properties": {
    "addr:full":"263 Oxford St Darlinghurst NSW 2010",
    "addr:housenumber":"263",
    "addr:postcode":"2010",
    "addr:street":"Oxford St",
    "iso:country":"AU",
    "sg:address":"263 Oxford St",
    "sg:city":"Darlinghurst",
    "sg:classifiers":[
        {
            "category":"Cafe",
            "type":"Food & Drink"
        }
    ],
    "sg:phone":"+61 2 9360 3947",
    "sg:postcode":"2010",
    "sg:province":"NSW",
    "wof:name":"Oddy's Cafe",
    "wof:placetype":"venue"
},
  "geometry": {"coordinates":[151.21900939899999,-33.8817176819],"type":"Point"}
}