{
  "type": "Feature",
  "properties": {
    "addr:full":"100 Village Ave Taylors Lakes VIC 3038",
    "addr:housenumber":"100",
    "addr:postcode":"3038",
    "addr:street":"Village Ave",
    "iso:country":"AU",
    "sg:address":"100 Village Ave",
    "sg:city":"Taylors Lakes",
    "sg:classifiers":[
        {
            "category":"Recreation",
            "subcategory":"Amusement Park",
            "type":"Entertainment"
        }
    ],
    "sg:phone":"+61 3 9449 8822",
    "sg:postcode":"3038",
    "sg:province":"VIC",
    "wof:name":"Junglemania",
    "wof:placetype":"venue"
},
  "geometry": {"coordinates":[144.797211,-37.701775],"type":"Point"}
}