{
  "type": "Feature",
  "properties": {
    "iso:country":"AU",
    "sg:address":"1018 Canley Vale Rd",
    "sg:city":"Wetherill Park",
    "sg:classifiers":[
        {
            "category":"Government",
            "subcategory":"Fire Station",
            "type":"Public Place"
        }
    ],
    "sg:phone":"+61 1300 134 651",
    "sg:postcode":"2164",
    "sg:province":"NSW",
    "sg:tags":[
        "equipment",
        "protection",
        "consultant"
    ],
    "wof:name":"Dixon (Asia Pacific)",
    "wof:placetype":"venue"
},
  "geometry": {"coordinates":[150.89585876500001,-33.8504333496],"type":"Point"}
}