{
  "type": "Feature",
  "properties": {
    "iso:country":"AU",
    "sg:address":"11/ 125 Bull St",
    "sg:city":"Newcastle West",
    "sg:classifiers":[
        {
            "category":"Professional",
            "subcategory":"Employment Agencies",
            "type":"Services"
        }
    ],
    "sg:phone":"+61 2 4929 2288",
    "sg:postcode":"2302",
    "sg:province":"NSW",
    "wof:name":"Engineers and Managers Australia Pty Ltd",
    "wof:placetype":"venue"
},
  "geometry": {"coordinates":[151.764893,-32.928764],"type":"Point"}
}