{
  "type": "Feature",
  "properties": {
    "iso:country":"AU",
    "sg:address":"2 Watt St",
    "sg:city":"Windermere Park",
    "sg:classifiers":[
        {
            "category":"Home & Garden",
            "subcategory":"Carpets & Floor Coverings",
            "type":"Retail Goods"
        }
    ],
    "sg:phone":"+61 2 4973 2740",
    "sg:postcode":"2264",
    "sg:province":"NSW",
    "sg:tags":[
        "tile",
        "wall"
    ],
    "wof:name":"Bullock Ross",
    "wof:placetype":"venue"
},
  "geometry": {"coordinates":[151.528763,-33.113316],"type":"Point"}
}