{
  "type": "Feature",
  "properties": {
    "addr:full":"Shop 6 a Belconnen Fresh Food Markets Belconnen ACT 2617",
    "addr:housenumber":"shop 6 a",
    "addr:postcode":"2617",
    "iso:country":"AU",
    "sg:address":"Shop 6",
    "sg:city":"a Belconnen Fresh Food Markets Belconnen",
    "sg:classifiers":[
        {
            "category":"Wholesale",
            "subcategory":"Painting Supplies",
            "type":"Manufacturing & Wholesale Goods"
        }
    ],
    "sg:phone":"+61 2 6251 6552",
    "sg:postcode":"2617",
    "sg:province":"ACT",
    "sg:tags":[
        "product",
        "cleaning"
    ],
    "wof:name":"Soapbox Belconnen",
    "wof:placetype":"venue"
},
  "geometry": {"coordinates":[149.06353759800001,-35.239730835],"type":"Point"}
}