{
  "type": "Feature",
  "properties": {
    "addr:full":"58 Pitt St Sydney NSW 2000",
    "addr:housenumber":"58",
    "addr:postcode":"2000",
    "addr:street":"Pitt St",
    "iso:country":"AU",
    "sg:address":"58 Pitt St",
    "sg:city":"Sydney",
    "sg:classifiers":[
        {
            "category":"Professional",
            "subcategory":"Printing & Photocopies",
            "type":"Services"
        }
    ],
    "sg:phone":"+61 2 9252 2243",
    "sg:postcode":"2000",
    "sg:province":"NSW",
    "sg:tags":[
        "photocopying"
    ],
    "wof:name":"Fedex Kinkos",
    "wof:placetype":"venue"
},
  "geometry": {"coordinates":[151.20903015100001,-33.864025116],"type":"Point"}
}