{
  "type": "Feature",
  "properties": {
    "iso:country":"AU",
    "sg:address":"333 Stanmore Rd",
    "sg:city":"Petersham",
    "sg:classifiers":[
        {
            "category":"Retail",
            "subcategory":"Self-service Laundry",
            "type":"Services"
        }
    ],
    "sg:phone":"+61 2 9564 2453",
    "sg:postcode":"2049",
    "sg:province":"NSW",
    "wof:name":"Blue Balloon Laundrette",
    "wof:placetype":"venue"
},
  "geometry": {"coordinates":[151.157227,-33.895634],"type":"Point"}
}