{
  "type": "Feature",
  "properties": {
    "addr:full":"24 Adelaide Rd Mt Barker SA 5251",
    "addr:housenumber":"24",
    "addr:postcode":"5251",
    "addr:street":"Adelaide Rd",
    "iso:country":"AU",
    "sg:address":"24 Adelaide Rd",
    "sg:city":"Mt Barker",
    "sg:classifiers":[
        {
            "category":"Autos & Motor Vehicles",
            "subcategory":"Fuel & Gas Station",
            "type":"Retail Goods"
        }
    ],
    "sg:phone":"+61 8 8398 2882",
    "sg:postcode":"5251",
    "sg:province":"SA",
    "wof:name":"BP Mt Barker",
    "wof:placetype":"venue"
},
  "geometry": {"coordinates":[138.85630798299999,-35.0664710999],"type":"Point"}
}