{
  "type": "Feature",
  "properties": {
    "addr:full":"U9/ 24 Clyde St Rydalmere NSW 2116",
    "addr:housenumber":"24",
    "addr:postcode":"2116",
    "addr:street":"U9 /;Clyde St",
    "iso:country":"AU",
    "sg:address":"U9/ 24 Clyde St",
    "sg:city":"Rydalmere",
    "sg:classifiers":[
        {
            "category":"Professional",
            "subcategory":"Computer Services",
            "type":"Services"
        }
    ],
    "sg:phone":"+61 1300 487 877",
    "sg:postcode":"2116",
    "sg:province":"NSW",
    "sg:tags":[
        "consultant",
        "system"
    ],
    "wof:name":"Entirity Business Services Pty Ltd",
    "wof:placetype":"venue"
},
  "geometry": {"coordinates":[151.05015564000001,-33.8265037537],"type":"Point"}
}