{
  "type": "Feature",
  "properties": {
    "iso:country":"AU",
    "sg:address":"214 Willoughby Rd",
    "sg:city":"Naremburn",
    "sg:classifiers":[
        {
            "category":"Building & Trades",
            "subcategory":"Construction",
            "type":"Services"
        }
    ],
    "sg:phone":"+61 2 9902 4700",
    "sg:postcode":"2065",
    "sg:province":"NSW",
    "sg:tags":[
        "management"
    ],
    "wof:name":"Richard Crookes Constructions Pty Ltd",
    "wof:placetype":"venue"
},
  "geometry": {"coordinates":[151.200775147,-33.8203048706],"type":"Point"}
}