{
  "type": "Feature",
  "properties": {
    "iso:country":"AU",
    "sg:address":"6 Brunker Rd",
    "sg:city":"Chullora",
    "sg:classifiers":[
        {
            "category":"Home & Garden",
            "subcategory":"Building Materials",
            "type":"Retail Goods"
        }
    ],
    "sg:phone":"+61 1300 309 038",
    "sg:postcode":"2190",
    "sg:province":"NSW",
    "sg:tags":[
        "supply"
    ],
    "wof:name":"BHP Steel Lysaght",
    "wof:placetype":"venue"
},
  "geometry": {"coordinates":[151.044037,-33.900009],"type":"Point"}
}