{
  "type": "Feature",
  "properties": {
    "addr:full":"95 Stanley Rd Ingleburn NSW 2565",
    "addr:housenumber":"95",
    "addr:postcode":"2565",
    "addr:street":"Stanley Rd",
    "iso:country":"AU",
    "sg:address":"95 Stanley Rd",
    "sg:city":"Ingleburn",
    "sg:classifiers":[
        {
            "category":"Building & Trades",
            "subcategory":"Construction",
            "type":"Services"
        }
    ],
    "sg:phone":"+61 2 9605 4022",
    "sg:postcode":"2565",
    "sg:province":"NSW",
    "sg:tags":[
        "scaffolding"
    ],
    "wof:name":"Speedy Gantry Hire",
    "wof:placetype":"venue"
},
  "geometry": {"coordinates":[150.86277770999999,-33.9884414673],"type":"Point"}
}