{
  "type": "Feature",
  "properties": {
    "addr:full":"20 Wyong St Oatley NSW 2223",
    "addr:housenumber":"20",
    "addr:postcode":"2223",
    "addr:street":"Wyong St",
    "iso:country":"AU",
    "sg:address":"20 Wyong St",
    "sg:city":"Oatley",
    "sg:classifiers":[
        {
            "category":"Professional",
            "subcategory":"Art Services",
            "type":"Services"
        }
    ],
    "sg:phone":"+61 2 9580 1532",
    "sg:postcode":"2223",
    "sg:province":"NSW",
    "sg:tags":[
        "decorator",
        "painter"
    ],
    "wof:name":"DJ & RJ Henniker",
    "wof:placetype":"venue"
},
  "geometry": {"coordinates":[151.07713317899999,-33.9889335632],"type":"Point"}
}