{
  "type": "Feature",
  "properties": {
    "addr:full":"Shop 7/ 163 Commercial Rd Prahran VIC 3181",
    "addr:housenumber":"shop 7 / 163",
    "addr:postcode":"3181",
    "addr:street":"Commercial Rd",
    "iso:country":"AU",
    "sg:address":"Shop 7/ 163 Commercial Rd",
    "sg:city":"Prahran",
    "sg:classifiers":[
        {
            "category":"Food & Beverages",
            "subcategory":"Fruits & Vegetables",
            "type":"Retail Goods"
        }
    ],
    "sg:phone":"+61 3 9804 8606",
    "sg:postcode":"3181",
    "sg:province":"VIC",
    "sg:tags":[
        "greengrocer",
        "fruiterer"
    ],
    "wof:name":"Ripe The Organic Grocer",
    "wof:placetype":"venue"
},
  "geometry": {"coordinates":[144.99183654800001,-37.846408844],"type":"Point"}
}