{
  "type": "Feature",
  "properties": {
    "addr:full":"36 Owen Rd Kelmscott WA 6111",
    "addr:housenumber":"36",
    "addr:postcode":"6111",
    "addr:street":"Owen Rd",
    "iso:country":"AU",
    "sg:address":"36 Owen Rd",
    "sg:city":"Kelmscott",
    "sg:classifiers":[
        {
            "category":"Building & Trades",
            "subcategory":"Construction",
            "type":"Services"
        }
    ],
    "sg:phone":"+61 8 9497 2519",
    "sg:postcode":"6111",
    "sg:province":"WA",
    "sg:tags":[
        "fencing",
        "contractor"
    ],
    "wof:name":"R & R Fencing & Gates",
    "wof:placetype":"venue"
},
  "geometry": {"coordinates":[116.005096435,-32.1321372986],"type":"Point"}
}