{
  "type": "Feature",
  "properties": {
    "addr:full":"10 Timms Crt Woodridge QLD 4114",
    "addr:housenumber":"10",
    "addr:postcode":"4114",
    "addr:street":"Timms Crt",
    "iso:country":"AU",
    "sg:address":"10 Timms Crt",
    "sg:city":"Woodridge",
    "sg:classifiers":[
        {
            "category":"Retail",
            "subcategory":"Auto Repair",
            "type":"Services"
        }
    ],
    "sg:phone":"+61 7 3208 6274",
    "sg:postcode":"4114",
    "sg:province":"QLD",
    "sg:tags":[
        "sport",
        "motor"
    ],
    "wof:name":"JHH Performance Engineering",
    "wof:placetype":"venue"
},
  "geometry": {"coordinates":[153.10700988799999,-27.620349884],"type":"Point"}
}