{
  "type": "Feature",
  "properties": {
    "addr:full":"83 Segenhoe St Aberdeen NSW 2336",
    "addr:housenumber":"83",
    "addr:postcode":"2336",
    "addr:street":"Segenhoe St",
    "iso:country":"AU",
    "sg:address":"83 Segenhoe St",
    "sg:city":"Aberdeen",
    "sg:classifiers":[
        {
            "category":"Farming",
            "subcategory":"Livestock Farm",
            "type":"Manufacturing & Wholesale Goods"
        }
    ],
    "sg:phone":"+61 2 6543 7144",
    "sg:postcode":"2336",
    "sg:province":"NSW",
    "sg:tags":[
        "buyer"
    ],
    "wof:name":"Clifford Tony",
    "wof:placetype":"venue"
},
  "geometry": {"coordinates":[150.88844299300001,-32.1700210571],"type":"Point"}
}