{
  "type": "Feature",
  "properties": {
    "iso:country":"AU",
    "sg:address":"60 Victor Crs",
    "sg:city":"Narre Warren",
    "sg:classifiers":[
        {
            "category":"Health Services",
            "subcategory":"Dentist",
            "type":"Services"
        }
    ],
    "sg:phone":"+61 3 9771 2030",
    "sg:postcode":"3805",
    "sg:province":"VIC",
    "wof:name":"Primary Dental Narre Warren",
    "wof:placetype":"venue"
},
  "geometry": {"coordinates":[145.305588,-38.02042],"type":"Point"}
}