{
  "type": "Feature",
  "properties": {
    "iso:country":"AU",
    "sg:address":"159 Beechboro Rd",
    "sg:city":"Bayswater",
    "sg:classifiers":[
        {
            "category":"Manufacturing",
            "subcategory":"Buildings",
            "type":"Manufacturing & Wholesale Goods"
        }
    ],
    "sg:phone":"+61 8 9471 7088",
    "sg:postcode":"6053",
    "sg:province":"WA",
    "sg:tags":[
        "transportable",
        "domestic",
        "relocatable"
    ],
    "wof:name":"Aussie Portables",
    "wof:placetype":"venue"
},
  "geometry": {"coordinates":[115.91914367699999,-31.9007797241],"type":"Point"}
}