{
  "type": "Feature",
  "properties": {
    "addr:full":"5 Gundara St The Gap QLD 4061",
    "addr:housenumber":"5",
    "addr:postcode":"4061",
    "addr:street":"Gundara St",
    "iso:country":"AU",
    "sg:address":"5 Gundara St",
    "sg:city":"The Gap",
    "sg:classifiers":[
        {
            "category":"Autos & Motor Vehicles",
            "subcategory":"Auto Supplies",
            "type":"Retail Goods"
        }
    ],
    "sg:phone":"+61 421 228 772",
    "sg:postcode":"4061",
    "sg:province":"QLD",
    "sg:tags":[
        "turbochargers"
    ],
    "wof:name":"Boosted Xtremes",
    "wof:placetype":"venue"
},
  "geometry": {"coordinates":[152.94764709500001,-27.437877655],"type":"Point"}
}