{
  "type": "Feature",
  "properties": {
    "addr:full":"420 Victoria St Brunswick VIC 3056",
    "addr:housenumber":"420",
    "addr:postcode":"3056",
    "addr:street":"Victoria St",
    "iso:country":"AU",
    "sg:address":"420 Victoria St",
    "sg:city":"Brunswick",
    "sg:classifiers":[
        {
            "category":"Real Estate",
            "subcategory":"Architect",
            "type":"Services"
        }
    ],
    "sg:phone":"+61 3 9940 1407",
    "sg:postcode":"3056",
    "sg:province":"VIC",
    "sg:website":"http://www.archameleon.com.au",
    "wof:name":"Justin Moore Pty Ltd Architects",
    "wof:placetype":"venue"
},
  "geometry": {"coordinates":[144.956573486,-37.7664718628],"type":"Point"}
}