{
  "type": "Feature",
  "properties": {
    "iso:country":"AU",
    "sg:address":"15 Caloola St",
    "sg:city":"Tamworth",
    "sg:classifiers":[
        {
            "category":"Retail",
            "subcategory":"Auto Repair",
            "type":"Services"
        }
    ],
    "sg:phone":"+61 408 658 765",
    "sg:postcode":"2340",
    "sg:province":"NSW",
    "sg:tags":[
        "fuel",
        "petrol",
        "injection"
    ],
    "wof:name":"E F I Masterblaster",
    "wof:placetype":"venue"
},
  "geometry": {"coordinates":[150.907958984,-31.1195068359],"type":"Point"}
}