{
  "type": "Feature",
  "properties": {
    "iso:country":"AU",
    "sg:address":"28 Dapville St",
    "sg:city":"Cobar",
    "sg:classifiers":[
        {
            "category":"Mining & Drilling",
            "type":"Manufacturing & Wholesale Goods"
        }
    ],
    "sg:phone":"+61 2 6836 4892",
    "sg:postcode":"2835",
    "sg:province":"NSW",
    "sg:tags":[
        "equipment",
        "quarrying",
        "supply"
    ],
    "wof:name":"Atlas Copco Construction & Mining Australia",
    "wof:placetype":"venue"
},
  "geometry": {"coordinates":[145.852798,-31.499289],"type":"Point"}
}