{
  "type": "Feature",
  "properties": {
    "addr:full":"2/ 8 William St South Rockhampton QLD 4700",
    "addr:housenumber":"/ 8",
    "addr:postcode":"4700",
    "addr:street":"William St South",
    "iso:country":"AU",
    "sg:address":"2/ 8 William St",
    "sg:city":"South Rockhampton",
    "sg:classifiers":[
        {
            "category":"Banks & Credit Unions",
            "subcategory":"Bank",
            "type":"Services"
        }
    ],
    "sg:phone":"+61 7 4922 6677",
    "sg:postcode":"4700",
    "sg:province":"QLD",
    "sg:tags":[
        "broker",
        "mortgage"
    ],
    "wof:name":"All Finanz Solutions (Qld) Pty Ltd",
    "wof:placetype":"venue"
},
  "geometry": {"coordinates":[150.50897216800001,-23.3833866119],"type":"Point"}
}