{
  "type": "Feature",
  "properties": {
    "addr:full":"104 Lyons Rd Drummoyne NSW 2047",
    "addr:housenumber":"104",
    "addr:postcode":"2047",
    "addr:street":"Lyons Rd",
    "iso:country":"AU",
    "sg:address":"104 Lyons Rd",
    "sg:city":"Drummoyne",
    "sg:classifiers":[
        {
            "category":"Recreation",
            "subcategory":"Fishing",
            "type":"Entertainment"
        }
    ],
    "sg:phone":"+61 2 9819 6278",
    "sg:postcode":"2047",
    "sg:province":"NSW",
    "sg:tags":[
        "bait"
    ],
    "wof:name":"Drummoyne Bait & Tackle",
    "wof:placetype":"venue"
},
  "geometry": {"coordinates":[151.14967300000001,-33.85408],"type":"Point"}
}