{
  "type": "Feature",
  "properties": {
    "addr:full":"Cusack La Jimboomba QLD 4280",
    "addr:postcode":"4280",
    "addr:street":"Cusack",
    "iso:country":"AU",
    "sg:address":"Cusack La",
    "sg:city":"Jimboomba",
    "sg:classifiers":[
        {
            "category":"Health Services",
            "subcategory":"Doctor",
            "type":"Services"
        }
    ],
    "sg:phone":"+61 7 5547 7733",
    "sg:postcode":"4280",
    "sg:province":"QLD",
    "sg:tags":[
        "medical",
        "practitioner"
    ],
    "wof:name":"Jimboomba Junction Family Practice (QLD)",
    "wof:placetype":"venue"
},
  "geometry": {"coordinates":[153.02641299999999,-27.831095],"type":"Point"}
}