{
  "type": "Feature",
  "properties": {
    "addr:full":"8 Kirkland Ave Euroa VIC 3666",
    "addr:housenumber":"8",
    "addr:postcode":"3666",
    "addr:street":"Kirkland Ave",
    "iso:country":"AU",
    "sg:address":"8 Kirkland Ave",
    "sg:city":"Euroa",
    "sg:classifiers":[
        {
            "category":"Retail",
            "subcategory":"Veterinary Services",
            "type":"Services"
        }
    ],
    "sg:phone":"+61 3 5795 2888",
    "sg:postcode":"3666",
    "sg:province":"VIC",
    "sg:tags":[
        "surgeon"
    ],
    "wof:name":"Worotniuk B",
    "wof:placetype":"venue"
},
  "geometry": {"coordinates":[145.57057189899999,-36.7486724854],"type":"Point"}
}