{
  "type": "Feature",
  "properties": {
    "addr:full":"PO Box 253 Box Hill North VIC 3129",
    "addr:postcode":"3129",
    "iso:country":"AU",
    "sg:address":"PO Box 253",
    "sg:city":"Box Hill North",
    "sg:classifiers":[
        {
            "category":"Home & Garden",
            "subcategory":"Carpets & Floor Coverings",
            "type":"Retail Goods"
        }
    ],
    "sg:phone":"+61 3 9899 0477",
    "sg:postcode":"3129",
    "sg:province":"VIC",
    "sg:tags":[
        "layer",
        "planner"
    ],
    "wof:name":"Carpet Installations Service",
    "wof:placetype":"venue"
},
  "geometry": {"coordinates":[145.126861572,-37.7974510193],"type":"Point"}
}