{
  "type": "Feature",
  "properties": {
    "addr:full":"105 Union St McMahons Point NSW 2060",
    "addr:housenumber":"105",
    "addr:postcode":"2060",
    "addr:street":"Union St",
    "iso:country":"AU",
    "sg:address":"105 Union St",
    "sg:city":"McMahons Point",
    "sg:classifiers":[
        {
            "category":"Professional",
            "subcategory":"Accounting & Tax Preparation",
            "type":"Services"
        }
    ],
    "sg:phone":"+61 2 9954 7933",
    "sg:postcode":"2060",
    "sg:province":"NSW",
    "sg:tags":[
        "accountant",
        "auditor"
    ],
    "wof:name":"Willcox & Levee",
    "wof:placetype":"venue"
},
  "geometry": {"coordinates":[151.20408630399999,-33.8422698975],"type":"Point"}
}