{
  "type": "Feature",
  "properties": {
    "addr:full":"Shp7/ 32 Macrossan St Port Douglas QLD 4877",
    "addr:postcode":"4877",
    "addr:street":"Macrossan St",
    "iso:country":"AU",
    "sg:address":"Shp7/ 32 Macrossan St",
    "sg:city":"Port Douglas",
    "sg:classifiers":[
        {
            "category":"Personal",
            "subcategory":"Day Spa",
            "type":"Services"
        }
    ],
    "sg:phone":"+61 7 4099 5099",
    "sg:postcode":"4877",
    "sg:province":"QLD",
    "wof:name":"Wellness@port",
    "wof:placetype":"venue"
},
  "geometry": {"coordinates":[145.46568298299999,-16.4839820862],"type":"Point"}
}