{
  "type": "Feature",
  "properties": {
    "iso:country":"AU",
    "sg:address":"445 Woodberry Rd",
    "sg:city":"Woodberry",
    "sg:classifiers":[
        {
            "category":"Building & Trades",
            "subcategory":"Construction",
            "type":"Services"
        }
    ],
    "sg:phone":"+61 2 4964 1207",
    "sg:postcode":"2322",
    "sg:province":"NSW",
    "sg:tags":[
        "concrete",
        "contractor"
    ],
    "wof:name":"Glen Maybury",
    "wof:placetype":"venue"
},
  "geometry": {"coordinates":[151.67500305199999,-32.7905158997],"type":"Point"}
}