{
  "type": "Feature",
  "properties": {
    "iso:country":"AU",
    "sg:address":"Shop 10 433 Nepean Hwy",
    "sg:city":"Frankston",
    "sg:classifiers":[
        {
            "category":"Wholesale",
            "subcategory":"Medical Equipment & Supplies",
            "type":"Manufacturing & Wholesale Goods"
        }
    ],
    "sg:phone":"+61 1800 069 997",
    "sg:postcode":"3199",
    "sg:province":"VIC",
    "sg:tags":[
        "dental"
    ],
    "wof:name":"Dental Computing Services",
    "wof:placetype":"venue"
},
  "geometry": {"coordinates":[145.00950622600001,-37.9068870544],"type":"Point"}
}