{
  "type": "Feature",
  "properties": {
    "addr:full":"32 Nandewar St Narrabri NSW 2390",
    "addr:housenumber":"32",
    "addr:postcode":"2390",
    "addr:street":"Nandewar St",
    "iso:country":"AU",
    "sg:address":"32 Nandewar St",
    "sg:city":"Narrabri",
    "sg:classifiers":[
        {
            "category":"Education",
            "subcategory":"School",
            "type":"Public Place"
        }
    ],
    "sg:phone":"+61 2 6792 1796",
    "sg:postcode":"2390",
    "sg:province":"NSW",
    "sg:tags":[
        "co-educational"
    ],
    "wof:name":"St Francis Xaviers School",
    "wof:placetype":"venue"
},
  "geometry": {"coordinates":[149.78797912600001,-30.3257141113],"type":"Point"}
}