{
  "type": "Feature",
  "properties": {
    "addr:full":"Level 3, 255 William St Melbourne VIC 3000",
    "addr:housenumber":"255",
    "addr:postcode":"3000",
    "addr:street":"William St",
    "iso:country":"AU",
    "sg:address":"Level 3, 255 William St",
    "sg:city":"Melbourne",
    "sg:classifiers":[
        {
            "category":"Education",
            "subcategory":"Dance Studio",
            "type":"Public Place"
        }
    ],
    "sg:phone":"+61 3 9926 4717",
    "sg:postcode":"3000",
    "sg:province":"VIC",
    "sg:tags":[
        "instruction",
        "language"
    ],
    "wof:name":"AMES Education",
    "wof:placetype":"venue"
},
  "geometry": {"coordinates":[144.956863403,-37.8130493164],"type":"Point"}
}