{
  "type": "Feature",
  "properties": {
    "addr:full":"83 Roseneath Pde Wynnum North QLD 4178",
    "addr:housenumber":"83",
    "addr:postcode":"4178",
    "addr:street":"Roseneath Pde",
    "iso:country":"AU",
    "sg:address":"83 Roseneath Pde",
    "sg:city":"Wynnum North",
    "sg:classifiers":[
        {
            "category":"Building & Trades",
            "subcategory":"Construction",
            "type":"Services"
        }
    ],
    "sg:phone":"+61 402 032 775",
    "sg:postcode":"4178",
    "sg:province":"QLD",
    "sg:tags":[
        "ceiling"
    ],
    "wof:name":"Herman P Plastering",
    "wof:placetype":"venue"
},
  "geometry": {"coordinates":[153.1509552,-27.4429702759],"type":"Point"}
}