{
  "type": "Feature",
  "properties": {
    "addr:full":"33 Boundary St Roseville NSW 2069",
    "addr:housenumber":"33",
    "addr:postcode":"2069",
    "addr:street":"Boundary St",
    "iso:country":"AU",
    "sg:address":"33 Boundary St",
    "sg:city":"Roseville",
    "sg:classifiers":[
        {
            "category":"Professional",
            "subcategory":"Computer Services",
            "type":"Services"
        }
    ],
    "sg:phone":"+61 2 9924 2620",
    "sg:postcode":"2069",
    "sg:province":"NSW",
    "sg:tags":[
        "consultant",
        "system"
    ],
    "wof:name":"Wilson Consulting Pty Ltd",
    "wof:placetype":"venue"
},
  "geometry": {"coordinates":[151.183425903,-33.786026001],"type":"Point"}
}