{
  "type": "Feature",
  "properties": {
    "addr:full":"3 Dunluce Crt Keperra QLD 4054",
    "addr:housenumber":"3",
    "addr:postcode":"4054",
    "addr:street":"Dunluce Crt",
    "iso:country":"AU",
    "sg:address":"3 Dunluce Crt",
    "sg:city":"Keperra",
    "sg:classifiers":[
        {
            "category":"Retail",
            "subcategory":"Driving School",
            "type":"Services"
        }
    ],
    "sg:phone":"+61 421 127 107",
    "sg:postcode":"4054",
    "sg:province":"QLD",
    "wof:name":"ESJ Driving School",
    "wof:placetype":"venue"
},
  "geometry": {"coordinates":[152.9402771,-27.4165744781],"type":"Point"}
}