{
  "type": "Feature",
  "properties": {
    "iso:country":"AU",
    "sg:address":"PO Box 439",
    "sg:city":"Park Holme",
    "sg:classifiers":[
        {
            "category":"Education",
            "subcategory":"Junior College",
            "type":"Public Place"
        }
    ],
    "sg:phone":"+61 409 868 171",
    "sg:postcode":"5043",
    "sg:province":"SA",
    "sg:tags":[
        "wholesaler",
        "school",
        "mfrs",
        "uniform"
    ],
    "wof:name":"James Kelly Agencies",
    "wof:placetype":"venue"
},
  "geometry": {"coordinates":[138.556793,-34.990849],"type":"Point"}
}