{
  "type": "Feature",
  "properties": {
    "addr:full":"4 Russell St (Cnr Breen St) Bendigo VIC 3550",
    "addr:housenumber":"4",
    "addr:postcode":"3550",
    "addr:street":"Russell St Cnr Breen St",
    "iso:country":"AU",
    "sg:address":"4 Russell St (Cnr Breen St)",
    "sg:city":"Bendigo",
    "sg:classifiers":[
        {
            "category":"Industrial Area",
            "type":"Public Place"
        }
    ],
    "sg:phone":"+61 3 5444 0523",
    "sg:postcode":"3550",
    "sg:province":"VIC",
    "sg:tags":[
        "rural",
        "shed"
    ],
    "wof:name":"Bendigo Garages",
    "wof:placetype":"venue"
},
  "geometry": {"coordinates":[144.277435303,-36.7690544128],"type":"Point"}
}