{
  "type": "Feature",
  "properties": {
    "addr:full":"790 Glenferrie Rd Hawthorn VIC 3122",
    "addr:housenumber":"790",
    "addr:postcode":"3122",
    "addr:street":"Glenferrie Rd",
    "iso:country":"AU",
    "sg:address":"790 Glenferrie Rd",
    "sg:city":"Hawthorn",
    "sg:classifiers":[
        {
            "category":"Shopping",
            "subcategory":"Gifts & Souvenirs",
            "type":"Retail Goods"
        }
    ],
    "sg:phone":"+61 3 9819 9790",
    "sg:postcode":"3122",
    "sg:province":"VIC",
    "sg:tags":[
        "print",
        "poster",
        "pictures"
    ],
    "wof:name":"Picture Framing Classes",
    "wof:placetype":"venue"
},
  "geometry": {"coordinates":[145.03639221200001,-37.8179397583],"type":"Point"}
}