{
  "type": "Feature",
  "properties": {
    "addr:full":"5 Elsie Pl Sinnamon Park QLD 4073",
    "addr:housenumber":"5",
    "addr:postcode":"4073",
    "addr:street":"Elsie Pl",
    "iso:country":"AU",
    "sg:address":"5 Elsie Pl",
    "sg:city":"Sinnamon Park",
    "sg:classifiers":[
        {
            "category":"Professional",
            "subcategory":"Engineering",
            "type":"Services"
        }
    ],
    "sg:phone":"+61 7 3279 2645",
    "sg:postcode":"4073",
    "sg:province":"QLD",
    "sg:tags":[
        "consulting",
        "engineer"
    ],
    "wof:name":"Bagheri J & H Pty Ltd",
    "wof:placetype":"venue"
},
  "geometry": {"coordinates":[152.94752502399999,-27.5501174927],"type":"Point"}
}