{
  "type": "Feature",
  "properties": {
    "iso:country":"AU",
    "sg:address":"Howard Rd",
    "sg:city":"Marchagee",
    "sg:classifiers":[
        {
            "category":"Farming",
            "subcategory":"Farm",
            "type":"Manufacturing & Wholesale Goods"
        }
    ],
    "sg:phone":"+61 8 9951 8236",
    "sg:postcode":"6515",
    "sg:province":"WA",
    "sg:tags":[
        "farmer"
    ],
    "wof:name":"Maley C R M & B G",
    "wof:placetype":"venue"
},
  "geometry": {"coordinates":[116.075912,-30.09721],"type":"Point"}
}