{
  "type": "Feature",
  "properties": {
    "addr:full":"78 Maple St Greystanes NSW 2145",
    "addr:housenumber":"78",
    "addr:postcode":"2145",
    "addr:street":"Maple St",
    "iso:country":"AU",
    "sg:address":"78 Maple St",
    "sg:city":"Greystanes",
    "sg:classifiers":[
        {
            "category":"Real Estate",
            "subcategory":"Developer",
            "type":"Services"
        }
    ],
    "sg:phone":"+61 2 9688 4266",
    "sg:postcode":"2145",
    "sg:province":"NSW",
    "sg:tags":[
        "development"
    ],
    "wof:name":"McDowell Enterprises (NSW) Pty Ltd",
    "wof:placetype":"venue"
},
  "geometry": {"coordinates":[150.95382690400001,-33.8175888062],"type":"Point"}
}