{
  "type": "Feature",
  "properties": {
    "addr:full":"6 Old Castle Hill Rd Castle Hill NSW 2154",
    "addr:housenumber":"6",
    "addr:postcode":"2154",
    "addr:street":"Old Castle Hill Rd",
    "iso:country":"AU",
    "sg:address":"6 Old Castle Hill Rd",
    "sg:city":"Castle Hill",
    "sg:classifiers":[
        {
            "category":"Health Services",
            "subcategory":"Dentist",
            "type":"Services"
        }
    ],
    "sg:phone":"+61 2 9899 3030",
    "sg:postcode":"2154",
    "sg:province":"NSW",
    "wof:name":"Middleton Alain G Dr & Associates",
    "wof:placetype":"venue"
},
  "geometry": {"coordinates":[151.00816345199999,-33.7308273315],"type":"Point"}
}