{
  "type": "Feature",
  "properties": {
    "iso:country":"AU",
    "sg:address":"327 Dalton Rd",
    "sg:city":"Epping",
    "sg:classifiers":[
        {
            "category":"Retail",
            "subcategory":"Driving School",
            "type":"Services"
        }
    ],
    "sg:phone":"+61 3 9408 7509",
    "sg:postcode":"3076",
    "sg:province":"VIC",
    "wof:name":"Olympia Driving School",
    "wof:placetype":"venue"
},
  "geometry": {"coordinates":[145.03094482399999,-37.6618461609],"type":"Point"}
}