{
  "type": "Feature",
  "properties": {
    "iso:country":"AU",
    "sg:address":"115 Auburn Rd",
    "sg:city":"Auburn",
    "sg:classifiers":[
        {
            "category":"Fast Food",
            "type":"Food & Drink"
        }
    ],
    "sg:phone":"+61 2 9481 1111",
    "sg:postcode":"2144",
    "sg:province":"NSW",
    "sg:tags":[
        "away",
        "take"
    ],
    "wof:name":"Pizza Hut",
    "wof:placetype":"venue"
},
  "geometry": {"coordinates":[151.03211975100001,-33.8539619446],"type":"Point"}
}