{
  "type": "Feature",
  "properties": {
    "iso:country":"AU",
    "sg:address":"Shed 5 Bovril St",
    "sg:city":"Katherine",
    "sg:classifiers":[
        {
            "category":"Utilities",
            "subcategory":"Refuse",
            "type":"Services"
        }
    ],
    "sg:phone":"+61 8 8971 0577",
    "sg:postcode":"0850",
    "sg:province":"NT",
    "sg:tags":[
        "remover",
        "rubbish"
    ],
    "wof:name":"M.T. Bins",
    "wof:placetype":"venue"
},
  "geometry": {"coordinates":[132.25886499999999,-14.484819],"type":"Point"}
}