{
  "type": "Feature",
  "properties": {
    "addr:full":"4/ 80 Regentville Rd Penrith NSW 2750",
    "addr:housenumber":"/ 80",
    "addr:postcode":"2750",
    "addr:street":"Regentville Rd",
    "iso:country":"AU",
    "sg:address":"4/ 80 Regentville Rd",
    "sg:city":"Penrith",
    "sg:classifiers":[
        {
            "category":"Building & Trades",
            "subcategory":"Construction",
            "type":"Services"
        }
    ],
    "sg:phone":"+61 2 4732 6300",
    "sg:postcode":"2750",
    "sg:province":"NSW",
    "sg:tags":[
        "contractor"
    ],
    "wof:name":"Eastcoast Building Services Pty Ltd",
    "wof:placetype":"venue"
},
  "geometry": {"coordinates":[150.68238830600001,-33.7661552429],"type":"Point"}
}