{
  "type": "Feature",
  "properties": {
    "addr:full":"10 Bombala St Cooma NSW 2630",
    "addr:housenumber":"10",
    "addr:postcode":"2630",
    "addr:street":"Bombala St",
    "iso:country":"AU",
    "sg:address":"10 Bombala St",
    "sg:city":"Cooma",
    "sg:classifiers":[
        {
            "category":"Travel",
            "subcategory":"Hotels & Motels",
            "type":"Entertainment"
        }
    ],
    "sg:phone":"+61 2 6452 1688",
    "sg:postcode":"2630",
    "sg:province":"NSW",
    "wof:name":"Cooma China Town",
    "wof:placetype":"venue"
},
  "geometry": {"coordinates":[149.12692260700001,-36.2341918945],"type":"Point"}
}