{
  "type": "Feature",
  "properties": {
    "addr:full":"20 Adelaide Rd Victor Harbor SA 5211",
    "addr:housenumber":"20",
    "addr:postcode":"5211",
    "addr:street":"Adelaide Rd",
    "iso:country":"AU",
    "sg:address":"20 Adelaide Rd",
    "sg:city":"Victor Harbor",
    "sg:classifiers":[
        {
            "category":"Wholesale",
            "subcategory":"Farm Supplies",
            "type":"Manufacturing & Wholesale Goods"
        }
    ],
    "sg:phone":"+61 8 8552 1788",
    "sg:postcode":"5211",
    "sg:province":"SA",
    "sg:tags":[
        "equipment"
    ],
    "wof:name":"Rosetta Rural Agencies",
    "wof:placetype":"venue"
},
  "geometry": {"coordinates":[138.63888549800001,-35.535369873],"type":"Point"}
}