{
  "type": "Feature",
  "properties": {
    "addr:full":"PO Box 5020 Launceston TAS 7250",
    "addr:postcode":"7250",
    "iso:country":"AU",
    "sg:address":"PO Box 5020",
    "sg:city":"Launceston",
    "sg:classifiers":[
        {
            "category":"Building & Trades",
            "subcategory":"Construction",
            "type":"Services"
        }
    ],
    "sg:phone":"+61 418 134 133",
    "sg:postcode":"7250",
    "sg:province":"TAS",
    "sg:tags":[
        "concrete",
        "contractor"
    ],
    "wof:name":"Island Concrete Pumps",
    "wof:placetype":"venue"
},
  "geometry": {"coordinates":[147.138504028,-41.4452018738],"type":"Point"}
}