{
  "type": "Feature",
  "properties": {
    "iso:country":"AU",
    "sg:address":"159 Ryrie St",
    "sg:city":"Geelong",
    "sg:classifiers":[
        {
            "category":"Shopping",
            "subcategory":"Clothing, Apparel, & Fashions",
            "type":"Retail Goods"
        }
    ],
    "sg:phone":"+61 3 5224 1455",
    "sg:postcode":"3220",
    "sg:province":"VIC",
    "sg:tags":[
        "accessory"
    ],
    "wof:name":"Venus Flytrap",
    "wof:placetype":"venue"
},
  "geometry": {"coordinates":[144.360291,-38.14925],"type":"Point"}
}