{
  "type": "Feature",
  "properties": {
    "addr:full":"Unit 5/ 7 Commercial Crt Tullamarine VIC 3043",
    "addr:housenumber":"7",
    "addr:postcode":"3043",
    "addr:street":"Commercial Crt",
    "iso:country":"AU",
    "sg:address":"Unit 5/ 7 Commercial Crt",
    "sg:city":"Tullamarine",
    "sg:classifiers":[
        {
            "category":"Professional",
            "type":"Services"
        }
    ],
    "sg:phone":"+61 3 9310 5353",
    "sg:postcode":"3043",
    "sg:province":"VIC",
    "sg:tags":[
        "forwarding",
        "agent",
        "transport"
    ],
    "wof:name":"AquaAir Freight Services",
    "wof:placetype":"venue"
},
  "geometry": {"coordinates":[144.857254028,-37.7083625793],"type":"Point"}
}