{
  "type": "Feature",
  "properties": {
    "addr:full":"Shop 13 734 Rode Rd Stafford Heights QLD 4053",
    "addr:housenumber":"shop 13",
    "addr:postcode":"734;4053",
    "addr:street":"Rode Rd",
    "iso:country":"AU",
    "sg:address":"Shop 13 734 Rode Rd",
    "sg:city":"Stafford Heights",
    "sg:classifiers":[
        {
            "category":"Shopping",
            "subcategory":"Clothing, Apparel, & Fashions",
            "type":"Retail Goods"
        }
    ],
    "sg:phone":"+61 7 3359 1588",
    "sg:postcode":"4053",
    "sg:province":"QLD",
    "sg:tags":[
        "lady",
        "wear"
    ],
    "wof:name":"Zag Clothing",
    "wof:placetype":"venue"
},
  "geometry": {"coordinates":[153.01014709500001,-27.3910732269],"type":"Point"}
}