{
  "type": "Feature",
  "properties": {
    "addr:full":"157 Powell St Joondanna WA 6060",
    "addr:housenumber":"157",
    "addr:postcode":"6060",
    "addr:street":"Powell St",
    "iso:country":"AU",
    "sg:address":"157 Powell St",
    "sg:city":"Joondanna",
    "sg:classifiers":[
        {
            "category":"Education",
            "subcategory":"Kindergarten",
            "type":"Public Place"
        }
    ],
    "sg:phone":"+61 8 9242 3422",
    "sg:postcode":"6060",
    "sg:province":"WA",
    "sg:tags":[
        "pre-schools"
    ],
    "wof:name":"Catholic Church",
    "wof:placetype":"venue"
},
  "geometry": {"coordinates":[115.84410095200001,-31.9105300903],"type":"Point"}
}