{
  "type": "Feature",
  "properties": {
    "iso:country":"AU",
    "sg:address":"33 Lake St",
    "sg:city":"Windale",
    "sg:classifiers":[
        {
            "category":"Health Services",
            "subcategory":"Doctor",
            "type":"Services"
        }
    ],
    "sg:phone":"+61 2 4948 5611",
    "sg:postcode":"2306",
    "sg:province":"NSW",
    "sg:tags":[
        "medical",
        "practitioner"
    ],
    "wof:name":"Marsh Lindsay",
    "wof:placetype":"venue"
},
  "geometry": {"coordinates":[151.682343,-32.992462],"type":"Point"}
}