{
  "type": "Feature",
  "properties": {
    "iso:country":"AU",
    "sg:address":"96 Fawkner Ave",
    "sg:city":"Blairgowrie",
    "sg:classifiers":[
        {
            "category":"Retail",
            "subcategory":"Auto Rental",
            "type":"Services"
        }
    ],
    "sg:phone":"+61 419 307 352",
    "sg:postcode":"3942",
    "sg:province":"VIC",
    "sg:tags":[
        "chauffeur",
        "car",
        "hire",
        "driven",
        "limousine"
    ],
    "wof:name":"Mornington Peninsula Limousines",
    "wof:placetype":"venue"
},
  "geometry": {"coordinates":[144.76205444300001,-38.3552856445],"type":"Point"}
}