{
  "type": "Feature",
  "properties": {
    "addr:full":"U2/ 19 Beale St Southport QLD 4215",
    "addr:housenumber":"19",
    "addr:postcode":"4215",
    "addr:street":"U2 /;Beale St",
    "iso:country":"AU",
    "sg:address":"U2/ 19 Beale St",
    "sg:city":"Southport",
    "sg:classifiers":[
        {
            "category":"Real Estate",
            "subcategory":"Real Estate Agent",
            "type":"Services"
        }
    ],
    "sg:phone":"+61 416 226 166",
    "sg:postcode":"4215",
    "sg:province":"QLD",
    "wof:name":"Get Realty",
    "wof:placetype":"venue"
},
  "geometry": {"coordinates":[153.400314331,-27.9657688141],"type":"Point"}
}