{
  "type": "Feature",
  "properties": {
    "addr:full":"Galway Bay Drv Ashtonfield NSW 2323",
    "addr:postcode":"2323",
    "addr:street":"Bay Drv",
    "iso:country":"AU",
    "sg:address":"Galway Bay Drv",
    "sg:city":"Ashtonfield",
    "sg:classifiers":[
        {
            "category":"Health Services",
            "subcategory":"Health Practitioner",
            "type":"Services"
        }
    ],
    "sg:phone":"+61 406 535 034",
    "sg:postcode":"2323",
    "sg:province":"NSW",
    "sg:tags":[
        "alternative"
    ],
    "wof:name":"Enchanted Indigo Moon",
    "wof:placetype":"venue"
},
  "geometry": {"coordinates":[151.594848633,-32.7710075378],"type":"Point"}
}