{
  "type": "Feature",
  "properties": {
    "addr:full":"32 Spalding St Flynn ACT 2615",
    "addr:housenumber":"32",
    "addr:postcode":"2615",
    "addr:street":"Spalding St",
    "iso:country":"AU",
    "sg:address":"32 Spalding St",
    "sg:city":"Flynn",
    "sg:classifiers":[
        {
            "category":"Retail",
            "subcategory":"Animal Services",
            "type":"Services"
        }
    ],
    "sg:phone":"+61 2 6258 8542",
    "sg:postcode":"2615",
    "sg:province":"ACT",
    "sg:tags":[
        "breeder",
        "sheep",
        "stud",
        "cattle"
    ],
    "wof:name":"Patterson Park Border Liercester & Hampshire Down Stud",
    "wof:placetype":"venue"
},
  "geometry": {"coordinates":[149.04884338400001,-35.1996688843],"type":"Point"}
}