{
  "type": "Feature",
  "properties": {
    "addr:full":"9 Foundry St Maylands WA 6051",
    "addr:housenumber":"9",
    "addr:postcode":"6051",
    "addr:street":"Foundry St",
    "iso:country":"AU",
    "sg:address":"9 Foundry St",
    "sg:city":"Maylands",
    "sg:classifiers":[
        {
            "category":"Sports & Exercise",
            "subcategory":"Gym",
            "type":"Entertainment"
        }
    ],
    "sg:phone":"+61 8 9272 9200",
    "sg:postcode":"6051",
    "sg:province":"WA",
    "sg:tags":[
        "health",
        "fitness"
    ],
    "wof:name":"Flex Fitness",
    "wof:placetype":"venue"
},
  "geometry": {"coordinates":[115.898033,-31.927399],"type":"Point"}
}