{
  "type": "Feature",
  "properties": {
    "addr:full":"151 Hopkins St Footscray VIC 3011",
    "addr:housenumber":"151",
    "addr:postcode":"3011",
    "addr:street":"Hopkins St",
    "iso:country":"AU",
    "sg:address":"151 Hopkins St",
    "sg:city":"Footscray",
    "sg:classifiers":[
        {
            "category":"Travel",
            "subcategory":"Travel Agent",
            "type":"Entertainment"
        }
    ],
    "sg:phone":"+61 3 9687 1057",
    "sg:postcode":"3011",
    "sg:province":"VIC",
    "sg:tags":[
        "consultant"
    ],
    "wof:name":"Vien Dong Tourist Services",
    "wof:placetype":"venue"
},
  "geometry": {"coordinates":[144.89976501500001,-37.7996711731],"type":"Point"}
}