{
  "type": "Feature",
  "properties": {
    "addr:full":"9 Lansdowne Pde Oatley NSW 2223",
    "addr:housenumber":"9",
    "addr:postcode":"2223",
    "addr:street":"Lansdowne Pde",
    "iso:country":"AU",
    "sg:address":"9 Lansdowne Pde",
    "sg:city":"Oatley",
    "sg:classifiers":[
        {
            "category":"Professional",
            "subcategory":"Art Services",
            "type":"Services"
        }
    ],
    "sg:phone":"+61 2 9580 0859",
    "sg:postcode":"2223",
    "sg:province":"NSW",
    "sg:tags":[
        "interior",
        "decorator"
    ],
    "wof:name":"Decorate.com.au",
    "wof:placetype":"venue"
},
  "geometry": {"coordinates":[151.06903076200001,-33.9838066101],"type":"Point"}
}