{
  "type": "Feature",
  "properties": {
    "addr:full":"111 Sussex St Sydney NSW 2001",
    "addr:housenumber":"111",
    "addr:postcode":"2001",
    "addr:street":"Sussex St",
    "iso:country":"AU",
    "sg:address":"111 Sussex St",
    "sg:city":"Sydney",
    "sg:classifiers":[
        {
            "category":"Travel",
            "subcategory":"Hotels & Motels",
            "type":"Entertainment"
        }
    ],
    "sg:phone":"+61 2 8297 7000",
    "sg:postcode":"2001",
    "sg:province":"NSW",
    "sg:tags":[
        "pub"
    ],
    "wof:name":"Slip Inn",
    "wof:placetype":"venue"
},
  "geometry": {"coordinates":[151.203369141,-33.8678436279],"type":"Point"}
}