{
  "type": "Feature",
  "properties": {
    "addr:full":"44 High St Bendigo VIC 3550",
    "addr:housenumber":"44",
    "addr:postcode":"3550",
    "addr:street":"High St",
    "iso:country":"AU",
    "sg:address":"44 High St",
    "sg:city":"Bendigo",
    "sg:classifiers":[
        {
            "category":"Personal",
            "subcategory":"Barber",
            "type":"Services"
        }
    ],
    "sg:phone":"+61 3 5441 3399",
    "sg:postcode":"3550",
    "sg:province":"VIC",
    "wof:name":"Hair C&#039;Hi",
    "wof:placetype":"venue"
},
  "geometry": {"coordinates":[144.27804565400001,-36.7598876953],"type":"Point"}
}