{
  "type": "Feature",
  "properties": {
    "addr:full":"Hamilton Hill Shopping Centre Shop 8, 10 Simms Rd Hamilton Hill WA 6163",
    "addr:housenumber":"shop 8 10",
    "addr:postcode":"6163",
    "addr:street":"Simms Rd",
    "iso:country":"AU",
    "sg:address":"Hamilton Hill Shopping Centre Shop 8, 10 Simms Rd",
    "sg:city":"Hamilton Hill",
    "sg:classifiers":[
        {
            "category":"Communications",
            "subcategory":"Film & Video Production",
            "type":"Services"
        }
    ],
    "sg:phone":"+61 8 9314 1156",
    "sg:postcode":"6163",
    "sg:province":"WA",
    "sg:tags":[
        "dvd",
        "library"
    ],
    "wof:name":"Video Ezy",
    "wof:placetype":"venue"
},
  "geometry": {"coordinates":[115.781761,-32.075333],"type":"Point"}
}