{
  "type": "Feature",
  "properties": {
    "addr:full":"11 Maria St Kurrimine Beach QLD 4871",
    "addr:housenumber":"11",
    "addr:postcode":"4871",
    "addr:street":"Maria St",
    "iso:country":"AU",
    "sg:address":"11 Maria St",
    "sg:city":"Kurrimine Beach",
    "sg:classifiers":[
        {
            "category":"Professional",
            "subcategory":"Printing & Photocopies",
            "type":"Services"
        }
    ],
    "sg:phone":"+61 7 4065 6288",
    "sg:postcode":"4871",
    "sg:province":"QLD",
    "sg:tags":[
        "trophy"
    ],
    "wof:name":"Deluxe Trophies",
    "wof:placetype":"venue"
},
  "geometry": {"coordinates":[146.10572814899999,-17.7762184143],"type":"Point"}
}