{
  "type": "Feature",
  "properties": {
    "addr:full":"16 Home Rd Nar Nar Goon VIC 3812",
    "addr:housenumber":"16",
    "addr:postcode":"3812",
    "addr:street":"Home Rd",
    "iso:country":"AU",
    "sg:address":"16 Home Rd",
    "sg:city":"Nar Nar Goon",
    "sg:classifiers":[
        {
            "category":"Building & Trades",
            "subcategory":"Construction",
            "type":"Services"
        }
    ],
    "sg:phone":"+61 3 5942 5508",
    "sg:postcode":"3812",
    "sg:province":"VIC",
    "sg:tags":[
        "earth",
        "excavating",
        "moving",
        "contractor"
    ],
    "wof:name":"Independent Excavations Pty Ltd",
    "wof:placetype":"venue"
},
  "geometry": {"coordinates":[145.566284,-38.08511],"type":"Point"}
}