{
  "type": "Feature",
  "properties": {
    "addr:full":"52 South St Bellerive TAS 7018",
    "addr:housenumber":"52",
    "addr:postcode":"7018",
    "addr:street":"South St",
    "iso:country":"AU",
    "sg:address":"52 South St",
    "sg:city":"Bellerive",
    "sg:classifiers":[
        {
            "category":"Professional",
            "subcategory":"Art Services",
            "type":"Services"
        }
    ],
    "sg:phone":"+61 417 580 981",
    "sg:postcode":"7018",
    "sg:province":"TAS",
    "sg:tags":[
        "decorator",
        "painter"
    ],
    "wof:name":"Dyson Painters",
    "wof:placetype":"venue"
},
  "geometry": {"coordinates":[147.38453674300001,-42.8770446777],"type":"Point"}
}