{
  "type": "Feature",
  "properties": {
    "iso:country":"AU",
    "sg:address":"10- 12 Grey St",
    "sg:city":"St George",
    "sg:classifiers":[
        {
            "category":"Autos & Motor Vehicles",
            "subcategory":"Auto Supplies",
            "type":"Retail Goods"
        }
    ],
    "sg:phone":"+61 7 4625 3187",
    "sg:postcode":"4487",
    "sg:province":"QLD",
    "sg:tags":[
        "tyre"
    ],
    "wof:name":"St George Tyre Service",
    "wof:placetype":"venue"
},
  "geometry": {"coordinates":[148.579177856,-28.0358753204],"type":"Point"}
}