{
  "type": "Feature",
  "properties": {
    "iso:country":"AU",
    "sg:address":"8 Francis St",
    "sg:city":"Narrabri",
    "sg:classifiers":[
        {
            "category":"Manufacturing",
            "subcategory":"Textiles",
            "type":"Manufacturing & Wholesale Goods"
        }
    ],
    "sg:phone":"+61 2 6792 4533",
    "sg:postcode":"2390",
    "sg:province":"NSW",
    "sg:tags":[
        "cotton"
    ],
    "wof:name":"Continental Eagle Pty Ltd",
    "wof:placetype":"venue"
},
  "geometry": {"coordinates":[149.778106689,-30.3128814697],"type":"Point"}
}