{
  "type": "Feature",
  "properties": {
    "addr:full":"237 Hutt St Adelaide SA 5000",
    "addr:housenumber":"237",
    "addr:postcode":"5000",
    "addr:street":"Hutt St",
    "iso:country":"AU",
    "sg:address":"237 Hutt St",
    "sg:city":"Adelaide",
    "sg:classifiers":[
        {
            "category":"Health Services",
            "subcategory":"Chiropractor",
            "type":"Services"
        }
    ],
    "sg:phone":"+61 8 8223 2822",
    "sg:postcode":"5000",
    "sg:province":"SA",
    "wof:name":"Watherston Graham J",
    "wof:placetype":"venue"
},
  "geometry": {"coordinates":[138.61216735799999,-34.9335861206],"type":"Point"}
}