{
  "type": "Feature",
  "properties": {
    "addr:full":"Unit 3/ 10 Pavilion Pl Cardiff NSW 2285",
    "addr:housenumber":"10",
    "addr:postcode":"2285",
    "addr:street":"Pavilion Pl",
    "iso:country":"AU",
    "sg:address":"Unit 3/ 10 Pavilion Pl",
    "sg:city":"Cardiff",
    "sg:classifiers":[
        {
            "category":"Building & Trades",
            "subcategory":"Construction",
            "type":"Services"
        }
    ],
    "sg:phone":"+61 2 4954 3471",
    "sg:postcode":"2285",
    "sg:province":"NSW",
    "sg:tags":[
        "fencing",
        "contractor"
    ],
    "wof:name":"Decorative Aluminium Works",
    "wof:placetype":"venue"
},
  "geometry": {"coordinates":[151.645263672,-32.9404640198],"type":"Point"}
}