{
  "type": "Feature",
  "properties": {
    "iso:country":"AU",
    "sg:address":"1B 1 Canal Rd",
    "sg:city":"Leichhardt",
    "sg:classifiers":[
        {
            "category":"Utilities",
            "subcategory":"Water",
            "type":"Services"
        }
    ],
    "sg:phone":"+61 2 9560 1451",
    "sg:postcode":"2040",
    "sg:province":"NSW",
    "sg:tags":[
        "cartage"
    ],
    "wof:name":"Dtfx Pty Ltd",
    "wof:placetype":"venue"
},
  "geometry": {"coordinates":[151.151443,-33.87257],"type":"Point"}
}