{
  "type": "Feature",
  "properties": {
    "addr:full":"Cnr Murray Valley Hwy & Gooramadda Rds Rutherglen VIC 3685",
    "addr:postcode":"3685",
    "addr:street":"Cnr Murray Valley Hwy & Gooramadda Rds",
    "iso:country":"AU",
    "sg:address":"Cnr Murray Valley Hwy & Gooramadda Rds",
    "sg:city":"Rutherglen",
    "sg:classifiers":[
        {
            "category":"Wholesale",
            "subcategory":"Farm Supplies",
            "type":"Manufacturing & Wholesale Goods"
        }
    ],
    "sg:phone":"+61 2 6032 9533",
    "sg:postcode":"3685",
    "sg:province":"VIC",
    "sg:tags":[
        "equipment"
    ],
    "wof:name":"McNamara's Country Store",
    "wof:placetype":"venue"
},
  "geometry": {"coordinates":[146.47578430199999,-36.0532684326],"type":"Point"}
}