{
  "type": "Feature",
  "properties": {
    "addr:full":"14 Langley St Rockingham WA 6168",
    "addr:housenumber":"14",
    "addr:postcode":"6168",
    "addr:street":"Langley St",
    "iso:country":"AU",
    "sg:address":"14 Langley St",
    "sg:city":"Rockingham",
    "sg:classifiers":[
        {
            "category":"Social Services",
            "subcategory":"Retirement Home",
            "type":"Services"
        }
    ],
    "sg:phone":"+61 8 9527 1757",
    "sg:postcode":"6168",
    "sg:province":"WA",
    "sg:tags":[
        "accommodation",
        "special"
    ],
    "wof:name":"Rockingham Nursing Home",
    "wof:placetype":"venue"
},
  "geometry": {"coordinates":[115.72695899999999,-32.281471],"type":"Point"}
}