{
  "type": "Feature",
  "properties": {
    "addr:full":"346 Albany Hwy Albany WA 6330",
    "addr:housenumber":"346",
    "addr:postcode":"6330",
    "addr:street":"Albany Hwy",
    "iso:country":"AU",
    "sg:address":"346 Albany Hwy",
    "sg:city":"Albany",
    "sg:classifiers":[
        {
            "category":"Autos & Motor Vehicles",
            "subcategory":"Automobile Sales",
            "type":"Retail Goods"
        }
    ],
    "sg:phone":"+61 8 9841 4555",
    "sg:postcode":"6330",
    "sg:province":"WA",
    "sg:tags":[
        "car",
        "new"
    ],
    "wof:name":"Albany Subaru",
    "wof:placetype":"venue"
},
  "geometry": {"coordinates":[117.864898682,-35.0023612976],"type":"Point"}
}