{
  "type": "Feature",
  "properties": {
    "addr:full":"15 Leawood Crs Boya WA 6056",
    "addr:housenumber":"15",
    "addr:postcode":"6056",
    "addr:street":"Leawood Crs",
    "iso:country":"AU",
    "sg:address":"15 Leawood Crs",
    "sg:city":"Boya",
    "sg:classifiers":[
        {
            "category":"Professional",
            "subcategory":"Engineering",
            "type":"Services"
        }
    ],
    "sg:phone":"+61 417 929 380",
    "sg:postcode":"6056",
    "sg:province":"WA",
    "sg:tags":[
        "engineer",
        "mechanical"
    ],
    "wof:name":"Russell's Mechanical & Gas Pty Ltd",
    "wof:placetype":"venue"
},
  "geometry": {"coordinates":[116.049026489,-31.9188899994],"type":"Point"}
}