{
  "type": "Feature",
  "properties": {
    "addr:full":"472 High St Northcote VIC 3070",
    "addr:housenumber":"472",
    "addr:postcode":"3070",
    "addr:street":"High St",
    "iso:country":"AU",
    "sg:address":"472 High St",
    "sg:city":"Northcote",
    "sg:classifiers":[
        {
            "category":"Utilities",
            "subcategory":"Telephone",
            "type":"Services"
        }
    ],
    "sg:phone":"+61 3 9486 4666",
    "sg:postcode":"3070",
    "sg:province":"VIC",
    "sg:tags":[
        "equipment",
        "system"
    ],
    "wof:name":"Techphone Communications",
    "wof:placetype":"venue"
},
  "geometry": {"coordinates":[145.011414,-37.773701],"type":"Point"}
}