{
  "type": "Feature",
  "properties": {
    "addr:full":"Lot 1 Purvis La Dubbo NSW 2830",
    "addr:postcode":"2830",
    "addr:street":"La",
    "iso:country":"AU",
    "sg:address":"Lot 1 Purvis La",
    "sg:city":"Dubbo",
    "sg:classifiers":[
        {
            "category":"Autos & Motor Vehicles",
            "subcategory":"Automobile Sales",
            "type":"Retail Goods"
        }
    ],
    "sg:phone":"+61 2 6884 2023",
    "sg:postcode":"2830",
    "sg:province":"NSW",
    "sg:tags":[
        "bus",
        "truck",
        "new"
    ],
    "wof:name":"Tracserv Trucks",
    "wof:placetype":"venue"
},
  "geometry": {"coordinates":[148.62271118199999,-32.2216567993],"type":"Point"}
}