{
  "type": "Feature",
  "properties": {
    "addr:full":"Shp 65 Showcase On The Mall Coolangatta QLD 4225",
    "addr:housenumber":"65",
    "addr:postcode":"4225",
    "addr:street":"Showcase On The Mall",
    "iso:country":"AU",
    "sg:address":"Shp 65 Showcase On The Mall",
    "sg:city":"Coolangatta",
    "sg:classifiers":[
        {
            "category":"Shopping",
            "subcategory":"Clothing, Apparel, & Fashions",
            "type":"Retail Goods"
        }
    ],
    "sg:phone":"+61 7 5536 2171",
    "sg:postcode":"4225",
    "sg:province":"QLD",
    "sg:tags":[
        "jean"
    ],
    "wof:name":"Jay Jay's Trademark",
    "wof:placetype":"venue"
},
  "geometry": {"coordinates":[153.537841797,-28.1684398651],"type":"Point"}
}