{
  "type": "Feature",
  "properties": {
    "addr:full":"Great Western Super Centre Settlement Rd Keperra QLD 4054",
    "addr:postcode":"4054",
    "addr:street":"Settlement Rd",
    "iso:country":"AU",
    "sg:address":"Great Western Super Centre Settlement Rd",
    "sg:city":"Keperra",
    "sg:classifiers":[
        {
            "category":"Autos & Motor Vehicles",
            "subcategory":"Auto Supplies",
            "type":"Retail Goods"
        }
    ],
    "sg:phone":"+61 7 3851 3611",
    "sg:postcode":"4054",
    "sg:province":"QLD",
    "sg:tags":[
        "accessory"
    ],
    "wof:name":"Super Cheap Auto",
    "wof:placetype":"venue"
},
  "geometry": {"coordinates":[152.94903564399999,-27.4145431519],"type":"Point"}
}