{
  "type": "Feature",
  "properties": {
    "addr:full":"175 Butterfield St Herston QLD 4006",
    "addr:housenumber":"175",
    "addr:postcode":"4006",
    "addr:street":"Butterfield St",
    "iso:country":"AU",
    "sg:address":"175 Butterfield St",
    "sg:city":"Herston",
    "sg:classifiers":[
        {
            "category":"Building & Trades",
            "subcategory":"Plumbing",
            "type":"Services"
        }
    ],
    "sg:phone":"+61 7 3257 4660",
    "sg:postcode":"4006",
    "sg:province":"QLD",
    "sg:tags":[
        "plumber",
        "gasfitters"
    ],
    "wof:name":"Ken Clarke Plumbing",
    "wof:placetype":"venue"
},
  "geometry": {"coordinates":[153.01919555699999,-27.4444904327],"type":"Point"}
}