{
  "type": "Feature",
  "properties": {
    "addr:full":"459 Toorak Rd Toorak VIC 3142",
    "addr:housenumber":"459",
    "addr:postcode":"3142",
    "addr:street":"Toorak Rd",
    "iso:country":"AU",
    "sg:address":"459 Toorak Rd",
    "sg:city":"Toorak",
    "sg:classifiers":[
        {
            "category":"Banks & Credit Unions",
            "subcategory":"Financial Services",
            "type":"Services"
        }
    ],
    "sg:phone":"+61 3 9296 2100",
    "sg:postcode":"3142",
    "sg:province":"VIC",
    "sg:tags":[
        "planning"
    ],
    "wof:name":"Kildair Pty Ltd",
    "wof:placetype":"venue"
},
  "geometry": {"coordinates":[145.008102417,-37.8408470154],"type":"Point"}
}