{
  "type": "Feature",
  "properties": {
    "addr:full":"10 Smith St Charlestown NSW 2290",
    "addr:housenumber":"10",
    "addr:postcode":"2290",
    "addr:street":"Smith St",
    "iso:country":"AU",
    "sg:address":"10 Smith St",
    "sg:city":"Charlestown",
    "sg:classifiers":[
        {
            "category":"Health Services",
            "subcategory":"Health Practitioner",
            "type":"Services"
        }
    ],
    "sg:phone":"+61 2 4943 7899",
    "sg:postcode":"2290",
    "sg:province":"NSW",
    "sg:tags":[
        "physiotherapist"
    ],
    "wof:name":"Buchanan A & Marosszeky Z",
    "wof:placetype":"venue"
},
  "geometry": {"coordinates":[151.69758605999999,-32.9621124268],"type":"Point"}
}