{
  "type": "Feature",
  "properties": {
    "addr:full":"35 Victoria St Nhill VIC 3418",
    "addr:housenumber":"35",
    "addr:postcode":"3418",
    "addr:street":"Victoria St",
    "iso:country":"AU",
    "sg:address":"35 Victoria St",
    "sg:city":"Nhill",
    "sg:classifiers":[
        {
            "category":"Shopping",
            "subcategory":"Clothing, Apparel, & Fashions",
            "type":"Retail Goods"
        }
    ],
    "sg:phone":"+61 3 5391 1334",
    "sg:postcode":"3418",
    "sg:province":"VIC",
    "sg:tags":[
        "menswear"
    ],
    "wof:name":"Mensland",
    "wof:placetype":"venue"
},
  "geometry": {"coordinates":[141.64938354500001,-36.3342323303],"type":"Point"}
}