{
  "type": "Feature",
  "properties": {
    "addr:full":"Cnr Iluka Rd & Hickey St Iluka NSW 2466",
    "addr:postcode":"2466",
    "addr:street":"Cnr Iluka Rd & Hickey St",
    "iso:country":"AU",
    "sg:address":"Cnr Iluka Rd & Hickey St",
    "sg:city":"Iluka",
    "sg:classifiers":[
        {
            "category":"Sports & Exercise",
            "subcategory":"Golf",
            "type":"Entertainment"
        }
    ],
    "sg:phone":"+61 2 6646 6408",
    "sg:postcode":"2466",
    "sg:province":"NSW",
    "sg:tags":[
        "club"
    ],
    "wof:name":"Iluka Golf Club Ltd",
    "wof:placetype":"venue"
},
  "geometry": {"coordinates":[153.35568237300001,-29.4032649994],"type":"Point"}
}