{
  "type": "Feature",
  "properties": {
    "addr:full":"87 Evanita Drv Gilston QLD 4211",
    "addr:housenumber":"87",
    "addr:postcode":"4211",
    "addr:street":"Evanita Drv",
    "iso:country":"AU",
    "sg:address":"87 Evanita Drv",
    "sg:city":"Gilston",
    "sg:classifiers":[
        {
            "category":"Building & Trades",
            "subcategory":"Construction",
            "type":"Services"
        }
    ],
    "sg:phone":"+61 7 5533 2389",
    "sg:postcode":"4211",
    "sg:province":"QLD",
    "sg:tags":[
        "concrete",
        "contractor"
    ],
    "wof:name":"Pro-Renovations & Concrete Cosmetics",
    "wof:placetype":"venue"
},
  "geometry": {"coordinates":[153.31509399399999,-28.0328330994],"type":"Point"}
}