{
  "type": "Feature",
  "properties": {
    "addr:full":"246 Nepean Hwy Edithvale VIC 3196",
    "addr:housenumber":"246",
    "addr:postcode":"3196",
    "addr:street":"Nepean Hwy",
    "iso:country":"AU",
    "sg:address":"246 Nepean Hwy",
    "sg:city":"Edithvale",
    "sg:classifiers":[
        {
            "category":"Home & Garden",
            "subcategory":"Hardware",
            "type":"Retail Goods"
        }
    ],
    "sg:phone":"+61 3 9772 1141",
    "sg:postcode":"3196",
    "sg:province":"VIC",
    "sg:tags":[
        "repair",
        "tool",
        "power"
    ],
    "wof:name":"S & S Tools New And Used",
    "wof:placetype":"venue"
},
  "geometry": {"coordinates":[145.107543945,-38.0371818542],"type":"Point"}
}