{
  "type": "Feature",
  "properties": {
    "iso:country":"AU",
    "sg:address":"35 Scott St",
    "sg:city":"Pooraka",
    "sg:classifiers":[
        {
            "category":"Professional",
            "subcategory":"Computer Services",
            "type":"Services"
        }
    ],
    "sg:phone":"+61 8 8359 1180",
    "sg:postcode":"5095",
    "sg:province":"SA",
    "sg:tags":[
        "repairs",
        "upgrade",
        "equipment"
    ],
    "wof:name":"Pooraka Computers",
    "wof:placetype":"venue"
},
  "geometry": {"coordinates":[138.613555908,-34.8318023682],"type":"Point"}
}