{
  "type": "Feature",
  "properties": {
    "addr:full":"60 Botany Rd Alexandria NSW 2015",
    "addr:housenumber":"60",
    "addr:postcode":"2015",
    "addr:street":"Botany Rd",
    "iso:country":"AU",
    "sg:address":"60 Botany Rd",
    "sg:city":"Alexandria",
    "sg:classifiers":[
        {
            "category":"Fast Food",
            "type":"Food & Drink"
        }
    ],
    "sg:phone":"+61 2 9698 1888",
    "sg:postcode":"2015",
    "sg:province":"NSW",
    "sg:tags":[
        "away",
        "take"
    ],
    "wof:name":"Chicken Express Systems Pty Ltd",
    "wof:placetype":"venue"
},
  "geometry": {"coordinates":[151.19908142099999,-33.8966178894],"type":"Point"}
}