{
  "type": "Feature",
  "properties": {
    "addr:full":"1186 Gold Coast Hwy Palm Beach QLD 4221",
    "addr:housenumber":"1186",
    "addr:postcode":"4221",
    "addr:street":"Gold Coast Hwy",
    "iso:country":"AU",
    "sg:address":"1186 Gold Coast Hwy",
    "sg:city":"Palm Beach",
    "sg:classifiers":[
        {
            "category":"Retail",
            "subcategory":"Auto Repair",
            "type":"Services"
        }
    ],
    "sg:phone":"+61 7 5534 2999",
    "sg:postcode":"4221",
    "sg:province":"QLD",
    "sg:tags":[
        "repairer",
        "motor",
        "engineer"
    ],
    "wof:name":"Mobil Car Care",
    "wof:placetype":"venue"
},
  "geometry": {"coordinates":[153.470794678,-28.1183757782],"type":"Point"}
}