{
  "type": "Feature",
  "properties": {
    "addr:full":"151-153 Brunswick St Fitzroy VIC 3065",
    "addr:housenumber":"151-153",
    "addr:postcode":"3065",
    "addr:street":"Brunswick St",
    "iso:country":"AU",
    "sg:address":"151-153 Brunswick St",
    "sg:city":"Fitzroy",
    "sg:classifiers":[
        {
            "category":"Retail",
            "subcategory":"Self-service Laundry",
            "type":"Services"
        }
    ],
    "sg:phone":"+61 3 9415 6944",
    "sg:postcode":"3065",
    "sg:province":"VIC",
    "wof:name":"My Beautiful Laundrette",
    "wof:placetype":"venue"
},
  "geometry": {"coordinates":[144.977493286,-37.8029022217],"type":"Point"}
}