{
  "type": "Feature",
  "properties": {
    "addr:full":"Unit 9 / 7 - 11 Rocco Drv Scoresby VIC 3179",
    "addr:housenumber":"11",
    "addr:postcode":"3179",
    "addr:street":"Rocco Drv",
    "iso:country":"AU",
    "sg:address":"Unit 9 / 7 - 11 Rocco Drv",
    "sg:city":"Scoresby",
    "sg:classifiers":[
        {
            "category":"Banks & Credit Unions",
            "subcategory":"Financial Services",
            "type":"Services"
        }
    ],
    "sg:phone":"+61 3 9764 9300",
    "sg:postcode":"3179",
    "sg:province":"VIC",
    "sg:tags":[
        "equipment",
        "chain"
    ],
    "wof:name":"Chain & Wire Rope Sales",
    "wof:placetype":"venue"
},
  "geometry": {"coordinates":[145.216995239,-37.899394989],"type":"Point"}
}