{
  "type": "Feature",
  "properties": {
    "addr:full":"40 Sailors Bay Rd Northbridge NSW 2063",
    "addr:housenumber":"40",
    "addr:postcode":"2063",
    "addr:street":"Sailors Bay Rd",
    "iso:country":"AU",
    "sg:address":"40 Sailors Bay Rd",
    "sg:city":"Northbridge",
    "sg:classifiers":[
        {
            "category":"Home & Garden",
            "subcategory":"Building Materials",
            "type":"Retail Goods"
        }
    ],
    "sg:phone":"+61 2 9958 5907",
    "sg:postcode":"2063",
    "sg:province":"NSW",
    "sg:tags":[
        "lawn",
        "cutting",
        "maintenance"
    ],
    "wof:name":"R & R Property Maintenance",
    "wof:placetype":"venue"
},
  "geometry": {"coordinates":[151.20576477,-33.8101921082],"type":"Point"}
}