{
  "type": "Feature",
  "properties": {
    "addr:full":"55 Powell St Bowen QLD 4805",
    "addr:housenumber":"55",
    "addr:postcode":"4805",
    "addr:street":"Powell St",
    "iso:country":"AU",
    "sg:address":"55 Powell St",
    "sg:city":"Bowen",
    "sg:classifiers":[
        {
            "category":"Travel",
            "subcategory":"Hotels & Motels",
            "type":"Entertainment"
        }
    ],
    "sg:phone":"+61 7 4786 1533",
    "sg:postcode":"4805",
    "sg:province":"QLD",
    "sg:tags":[
        "accommodation"
    ],
    "wof:name":"Denison Hotel",
    "wof:placetype":"venue"
},
  "geometry": {"coordinates":[148.24104309099999,-20.0149288177],"type":"Point"}
}