{
  "type": "Feature",
  "properties": {
    "iso:country":"AU",
    "sg:address":"15 Cummins St",
    "sg:city":"Unanderra",
    "sg:classifiers":[
        {
            "category":"Professional",
            "subcategory":"Printing & Photocopies",
            "type":"Services"
        }
    ],
    "sg:phone":"+61 2 4272 3948",
    "sg:postcode":"2526",
    "sg:province":"NSW",
    "sg:tags":[
        "publishing",
        "desktop"
    ],
    "wof:name":"Bold Impressions Desktop Publishing",
    "wof:placetype":"venue"
},
  "geometry": {"coordinates":[150.84022522000001,-34.4520759583],"type":"Point"}
}