{
  "type": "Feature",
  "properties": {
    "addr:full":"1/ 95 Anita Ave Lake Munmorah NSW 2259",
    "addr:housenumber":"/ 95",
    "addr:postcode":"2259",
    "addr:street":"Anita Ave",
    "iso:country":"AU",
    "sg:address":"1/ 95 Anita Ave",
    "sg:city":"Lake Munmorah",
    "sg:classifiers":[
        {
            "category":"Personal",
            "subcategory":"Beauty Salon",
            "type":"Services"
        }
    ],
    "sg:phone":"+61 2 4358 1233",
    "sg:postcode":"2259",
    "sg:province":"NSW",
    "sg:tags":[
        "hairdresser"
    ],
    "wof:name":"Stylish Impacts",
    "wof:placetype":"venue"
},
  "geometry": {"coordinates":[151.577026367,-33.1956253052],"type":"Point"}
}