{
  "type": "Feature",
  "properties": {
    "iso:country":"AU",
    "sg:address":"Cnr Gympie & Hamilton Rds",
    "sg:city":"Chermside",
    "sg:classifiers":[
        {
            "category":"Health Services",
            "subcategory":"Health Practitioner",
            "type":"Services"
        }
    ],
    "sg:phone":"+61 7 3359 6883",
    "sg:postcode":"4032",
    "sg:province":"QLD",
    "sg:tags":[
        "acupuncture"
    ],
    "wof:name":"Chi Link Nationwide Natural Therapy Health Centre",
    "wof:placetype":"venue"
},
  "geometry": {"coordinates":[153.03393600000001,-27.38636],"type":"Point"}
}