{
  "type": "Feature",
  "properties": {
    "iso:country":"AU",
    "sg:address":"19 Queen St",
    "sg:city":"Campbelltown",
    "sg:classifiers":[
        {
            "category":"Shopping",
            "subcategory":"Bicycles & Sporting Goods",
            "type":"Retail Goods"
        }
    ],
    "sg:phone":"+61 2 4626 7199",
    "sg:postcode":"2560",
    "sg:province":"NSW",
    "sg:tags":[
        "chemical",
        "equipment",
        "pool",
        "swimming"
    ],
    "wof:name":"Blue Lagoon Pools & Spas Pty. Ltd.",
    "wof:placetype":"venue"
},
  "geometry": {"coordinates":[150.82009887699999,-34.0599327087],"type":"Point"}
}