{
  "type": "Feature",
  "properties": {
    "addr:full":"192 Reserve Creek Rd Murwillumbah NSW 2484",
    "addr:housenumber":"192",
    "addr:postcode":"2484",
    "addr:street":"Reserve Creek Rd",
    "iso:country":"AU",
    "sg:address":"192 Reserve Creek Rd",
    "sg:city":"Murwillumbah",
    "sg:classifiers":[
        {
            "category":"Retail",
            "subcategory":"Auto Repair",
            "type":"Services"
        }
    ],
    "sg:phone":"+61 2 6672 3573",
    "sg:postcode":"2484",
    "sg:province":"NSW",
    "sg:tags":[
        "repairer",
        "motor",
        "engineer"
    ],
    "wof:name":"Cross S A Autos",
    "wof:placetype":"venue"
},
  "geometry": {"coordinates":[153.4271698,-28.3327064514],"type":"Point"}
}