{
  "type": "Feature",
  "properties": {
    "addr:full":"217a Forrest St Palmyra WA 6157",
    "addr:housenumber":"217a",
    "addr:postcode":"6157",
    "addr:street":"Forrest St",
    "iso:country":"AU",
    "sg:address":"217a Forrest St",
    "sg:city":"Palmyra",
    "sg:classifiers":[
        {
            "category":"Professional",
            "subcategory":"Art Services",
            "type":"Services"
        }
    ],
    "sg:phone":"+61 8 9339 7661",
    "sg:postcode":"6157",
    "sg:province":"WA",
    "sg:tags":[
        "interior",
        "designer"
    ],
    "wof:name":"Crane Irene & Associates",
    "wof:placetype":"venue"
},
  "geometry": {"coordinates":[115.786018,-32.04826],"type":"Point"}
}