{
  "type": "Feature",
  "properties": {
    "addr:full":"536 Princes St Rockdale NSW 2216",
    "addr:housenumber":"536",
    "addr:postcode":"2216",
    "addr:street":"Princes St",
    "iso:country":"AU",
    "sg:address":"536 Princes St",
    "sg:city":"Rockdale",
    "sg:classifiers":[
        {
            "category":"Shopping",
            "subcategory":"Pawn Shop",
            "type":"Retail Goods"
        }
    ],
    "sg:phone":"+61 2 9567 3944",
    "sg:postcode":"2216",
    "sg:province":"NSW",
    "sg:tags":[
        "pawnbroker"
    ],
    "wof:name":"Cash Brokers",
    "wof:placetype":"venue"
},
  "geometry": {"coordinates":[151.15643299999999,-33.959923],"type":"Point"}
}