{
  "type": "Feature",
  "properties": {
    "addr:full":"21 Pearl St Torquay VIC 3228",
    "addr:housenumber":"21",
    "addr:postcode":"3228",
    "addr:street":"Pearl St",
    "iso:country":"AU",
    "sg:address":"21 Pearl St",
    "sg:city":"Torquay",
    "sg:classifiers":[
        {
            "category":"Real Estate",
            "subcategory":"Real Estate Agent",
            "type":"Services"
        }
    ],
    "sg:phone":"+61 3 5261 2101",
    "sg:postcode":"3228",
    "sg:province":"VIC",
    "wof:name":"Hayden Real Estate",
    "wof:placetype":"venue"
},
  "geometry": {"coordinates":[144.323227,-38.332188],"type":"Point"}
}