{
  "type": "Feature",
  "properties": {
    "addr:full":"Sinnott St Burwood VIC 3125",
    "addr:postcode":"3125",
    "addr:street":"Sinnott St",
    "iso:country":"AU",
    "sg:address":"Sinnott St",
    "sg:city":"Burwood",
    "sg:classifiers":[
        {
            "category":"Utilities",
            "subcategory":"Water",
            "type":"Services"
        }
    ],
    "sg:phone":"+61 412 839 122",
    "sg:postcode":"3125",
    "sg:province":"VIC",
    "sg:tags":[
        "hot",
        "system"
    ],
    "wof:name":"O&#039;Shea Plumbing",
    "wof:placetype":"venue"
},
  "geometry": {"coordinates":[145.111160278,-37.8524360657],"type":"Point"}
}