{
  "type": "Feature",
  "properties": {
    "addr:full":"185 Fairbairn Rd Sunshine VIC 3020",
    "addr:housenumber":"185",
    "addr:postcode":"3020",
    "addr:street":"Fairbairn Rd",
    "iso:country":"AU",
    "sg:address":"185 Fairbairn Rd",
    "sg:city":"Sunshine",
    "sg:classifiers":[
        {
            "category":"Real Estate",
            "subcategory":"Real Estate Agent",
            "type":"Services"
        }
    ],
    "sg:phone":"+61 3 9312 5444",
    "sg:postcode":"3020",
    "sg:province":"VIC",
    "sg:tags":[
        "handyman's",
        "equipment",
        "hire",
        "builders",
        "contractor"
    ],
    "wof:name":"Complete Hire Equipment",
    "wof:placetype":"venue"
},
  "geometry": {"coordinates":[144.817184,-37.812996],"type":"Point"}
}