{
  "type": "Feature",
  "properties": {
    "addr:full":"108 Brisbane St Beaudesert QLD 4285",
    "addr:housenumber":"108",
    "addr:postcode":"4285",
    "addr:street":"Brisbane St",
    "iso:country":"AU",
    "sg:address":"108 Brisbane St",
    "sg:city":"Beaudesert",
    "sg:classifiers":[
        {
            "category":"Autos & Motor Vehicles",
            "subcategory":"Fuel & Gas Station",
            "type":"Retail Goods"
        }
    ],
    "sg:phone":"+61 7 5541 1948",
    "sg:postcode":"4285",
    "sg:province":"QLD",
    "wof:name":"Road Runner Service Station",
    "wof:placetype":"venue"
},
  "geometry": {"coordinates":[152.99525499999999,-27.984051],"type":"Point"}
}