{
  "type": "Feature",
  "properties": {
    "addr:full":"321 Greenwattle St Toowoomba QLD 4350",
    "addr:housenumber":"321",
    "addr:postcode":"4350",
    "addr:street":"Greenwattle St",
    "iso:country":"AU",
    "sg:address":"321 Greenwattle St",
    "sg:city":"Toowoomba",
    "sg:classifiers":[
        {
            "category":"Building & Trades",
            "subcategory":"Construction",
            "type":"Services"
        }
    ],
    "sg:phone":"+61 408 602 470",
    "sg:postcode":"4350",
    "sg:province":"QLD",
    "sg:tags":[
        "plasterboard",
        "plasterer",
        "fixer"
    ],
    "wof:name":"Just Fix Plaster",
    "wof:placetype":"venue"
},
  "geometry": {"coordinates":[151.91456600000001,-27.568087],"type":"Point"}
}