{
  "type": "Feature",
  "properties": {
    "addr:full":"Shop 15 The Mall Wantirna VIC 3152",
    "addr:housenumber":"shop 15",
    "addr:postcode":"3152",
    "addr:street":"The Mall",
    "iso:country":"AU",
    "sg:address":"Shop 15",
    "sg:city":"The Mall Wantirna",
    "sg:classifiers":[
        {
            "category":"Education",
            "subcategory":"Music School",
            "type":"Public Place"
        }
    ],
    "sg:phone":"+61 3 9720 3620",
    "sg:postcode":"3152",
    "sg:province":"VIC",
    "sg:tags":[
        "teacher"
    ],
    "wof:name":"Hosking Music",
    "wof:placetype":"venue"
},
  "geometry": {"coordinates":[145.232177734,-37.8477668762],"type":"Point"}
}