{
  "type": "Feature",
  "properties": {
    "addr:full":"Level 3/ 128 Exhibition St Melbourne VIC 3000",
    "addr:housenumber":"/ 128",
    "addr:postcode":"3000",
    "addr:street":"Exhibition St",
    "iso:country":"AU",
    "sg:address":"Level 3/ 128 Exhibition St",
    "sg:city":"Melbourne",
    "sg:classifiers":[
        {
            "category":"Professional",
            "subcategory":"Employment Agencies",
            "type":"Services"
        }
    ],
    "sg:phone":"+61 3 9659 3444",
    "sg:postcode":"3000",
    "sg:province":"VIC",
    "wof:name":"Job Futures",
    "wof:placetype":"venue"
},
  "geometry": {"coordinates":[144.97105407699999,-37.8127479553],"type":"Point"}
}