{
  "type": "Feature",
  "properties": {
    "iso:country":"AU",
    "sg:address":"8680 Murray River Rd",
    "sg:city":"Walwa",
    "sg:classifiers":[
        {
            "category":"Farming",
            "subcategory":"Vineyard",
            "type":"Manufacturing & Wholesale Goods"
        }
    ],
    "sg:phone":"+61 2 6037 1577",
    "sg:postcode":"3709",
    "sg:province":"NSW",
    "sg:tags":[
        "winery"
    ],
    "wof:name":"Lankeys Creek Wines Pty Ltd",
    "wof:placetype":"venue"
},
  "geometry": {"coordinates":[147.70616149899999,-35.9317321777],"type":"Point"}
}