{
  "type": "Feature",
  "properties": {
    "iso:country":"AU",
    "sg:address":"Maple St",
    "sg:city":"Cooroy",
    "sg:classifiers":[
        {
            "category":"Health Services",
            "subcategory":"Doctor",
            "type":"Services"
        }
    ],
    "sg:phone":"+61 7 5447 6196",
    "sg:postcode":"4563",
    "sg:province":"QLD",
    "sg:tags":[
        "medical",
        "practitioner"
    ],
    "wof:name":"Southern X-Ray Clinics",
    "wof:placetype":"venue"
},
  "geometry": {"coordinates":[152.90887451200001,-26.4205932617],"type":"Point"}
}