{
  "type": "Feature",
  "properties": {
    "addr:full":"4 Centenary Crs Maroochydore QLD 4558",
    "addr:housenumber":"4",
    "addr:postcode":"4558",
    "addr:street":"Centenary Crs",
    "iso:country":"AU",
    "sg:address":"4 Centenary Crs",
    "sg:city":"Maroochydore",
    "sg:classifiers":[
        {
            "category":"Personal",
            "subcategory":"Beauty Salon",
            "type":"Services"
        }
    ],
    "sg:phone":"+61 414 958 273",
    "sg:postcode":"4558",
    "sg:province":"QLD",
    "sg:tags":[
        "hairdresser"
    ],
    "wof:name":"Emily Glasson - Mobile Stylist",
    "wof:placetype":"venue"
},
  "geometry": {"coordinates":[153.06553649899999,-26.6553192139],"type":"Point"}
}