{
  "type": "Feature",
  "properties": {
    "iso:country":"AU",
    "sg:address":"8 Lynch Rd",
    "sg:city":"Narara",
    "sg:classifiers":[
        {
            "category":"Shopping",
            "subcategory":"Computers & Home Electronics",
            "type":"Retail Goods"
        }
    ],
    "sg:phone":"+61 2 4322 6555",
    "sg:postcode":"2250",
    "sg:province":"NSW",
    "sg:tags":[
        "hardware",
        "equipment"
    ],
    "wof:name":"Kevyn Allen Computers",
    "wof:placetype":"venue"
},
  "geometry": {"coordinates":[151.340499878,-33.4067649841],"type":"Point"}
}