{
  "type": "Feature",
  "properties": {
    "iso:country":"AU",
    "sg:address":"985 North East Rd",
    "sg:city":"Modbury",
    "sg:classifiers":[
        {
            "category":"Shopping",
            "subcategory":"Computers & Home Electronics",
            "type":"Retail Goods"
        }
    ],
    "sg:phone":"+61 8 8395 7777",
    "sg:postcode":"5092",
    "sg:province":"SA",
    "sg:tags":[
        "equipment",
        "part",
        "electronic"
    ],
    "wof:name":"Dick Smith Electronics",
    "wof:placetype":"venue"
},
  "geometry": {"coordinates":[138.68739318900001,-34.8312835693],"type":"Point"}
}