{
  "type": "Feature",
  "properties": {
    "addr:full":"Shp5/ 24 Main St Blacktown NSW 2148",
    "addr:housenumber":"24",
    "addr:postcode":"2148",
    "addr:street":"Main St",
    "iso:country":"AU",
    "sg:address":"Shp5/ 24 Main St",
    "sg:city":"Blacktown",
    "sg:classifiers":[
        {
            "category":"Professional",
            "subcategory":"Accounting & Tax Preparation",
            "type":"Services"
        }
    ],
    "sg:phone":"+61 2 9621 1429",
    "sg:postcode":"2148",
    "sg:province":"NSW",
    "sg:tags":[
        "accountant",
        "auditor"
    ],
    "wof:name":"Tower Accountants",
    "wof:placetype":"venue"
},
  "geometry": {"coordinates":[150.907913208,-33.7691078186],"type":"Point"}
}