{
  "type": "Feature",
  "properties": {
    "addr:full":"479 Cummins St Broken Hill NSW 2880",
    "addr:housenumber":"479",
    "addr:postcode":"2880",
    "addr:street":"Cummins St",
    "iso:country":"AU",
    "sg:address":"479 Cummins St",
    "sg:city":"Broken Hill",
    "sg:classifiers":[
        {
            "category":"Building & Trades",
            "subcategory":"Construction",
            "type":"Services"
        }
    ],
    "sg:phone":"+61 418 858 482",
    "sg:postcode":"2880",
    "sg:province":"NSW",
    "sg:tags":[
        "contractor"
    ],
    "wof:name":"Winders Dean",
    "wof:placetype":"venue"
},
  "geometry": {"coordinates":[141.459716797,-31.9404411316],"type":"Point"}
}