{
  "type": "Feature",
  "properties": {
    "addr:full":"1551 Waterford Tamborine Rd Logan Village QLD 4207",
    "addr:housenumber":"1551",
    "addr:postcode":"4207",
    "addr:street":"Waterford Tamborine Rd",
    "iso:country":"AU",
    "sg:address":"1551 Waterford Tamborine Rd",
    "sg:city":"Logan Village",
    "sg:classifiers":[
        {
            "category":"Retail",
            "subcategory":"Event Space",
            "type":"Services"
        }
    ],
    "sg:phone":"+61 7 5546 8182",
    "sg:postcode":"4207",
    "sg:province":"QLD",
    "sg:tags":[
        "function",
        "organiser"
    ],
    "wof:name":"Garden Paradise Cafe & Functions Venue",
    "wof:placetype":"venue"
},
  "geometry": {"coordinates":[153.09991455100001,-27.7994174957],"type":"Point"}
}