{
  "type": "Feature",
  "properties": {
    "iso:country":"AU",
    "sg:address":"21 Short St",
    "sg:city":"Bendigo",
    "sg:classifiers":[
        {
            "category":"Organizations",
            "subcategory":"Professional Association",
            "type":"Services"
        }
    ],
    "sg:phone":"+61 3 5443 4478",
    "sg:postcode":"3550",
    "sg:province":"VIC",
    "sg:tags":[
        "organisation",
        "business"
    ],
    "wof:name":"Victorian Employers&#039; Chamber of Commerce & Industry",
    "wof:placetype":"venue"
},
  "geometry": {"coordinates":[144.276123047,-36.7625541687],"type":"Point"}
}