{
  "type": "Feature",
  "properties": {
    "addr:full":"17 Telegraph Rd Kingscote SA 5223",
    "addr:housenumber":"17",
    "addr:postcode":"5223",
    "addr:street":"Telegraph Rd",
    "iso:country":"AU",
    "sg:address":"17 Telegraph Rd",
    "sg:city":"Kingscote",
    "sg:classifiers":[
        {
            "category":"Real Estate",
            "subcategory":"Real Estate Agent",
            "type":"Services"
        }
    ],
    "sg:phone":"+61 8 8553 2102",
    "sg:postcode":"5223",
    "sg:province":"SA",
    "wof:name":"Elders Real Estate",
    "wof:placetype":"venue"
},
  "geometry": {"coordinates":[137.634674072,-35.6530075073],"type":"Point"}
}