{
  "type": "Feature",
  "properties": {
    "addr:full":"231 Oxford St Leederville WA 6007",
    "addr:housenumber":"231",
    "addr:postcode":"6007",
    "addr:street":"Oxford St",
    "iso:country":"AU",
    "sg:address":"231 Oxford St",
    "sg:city":"Leederville",
    "sg:classifiers":[
        {
            "category":"Food & Beverages",
            "subcategory":"Groceries & Convenience Stores",
            "type":"Retail Goods"
        }
    ],
    "sg:phone":"+61 8 9444 9644",
    "sg:postcode":"6007",
    "sg:province":"WA",
    "wof:name":"Re Store",
    "wof:placetype":"venue"
},
  "geometry": {"coordinates":[115.841072083,-31.9332332611],"type":"Point"}
}