{
  "type": "Feature",
  "properties": {
    "iso:country":"AU",
    "sg:address":"13 Kennedy St",
    "sg:city":"Gorokan",
    "sg:classifiers":[
        {
            "category":"Professional",
            "subcategory":"Business Services",
            "type":"Services"
        }
    ],
    "sg:phone":"+61 2 4392 2826",
    "sg:postcode":"2263",
    "sg:province":"NSW",
    "sg:tags":[
        "drafting"
    ],
    "wof:name":"Jan & John Rutty Drafting Pty Ltd",
    "wof:placetype":"venue"
},
  "geometry": {"coordinates":[151.506989,-33.258942],"type":"Point"}
}