{
  "type": "Feature",
  "properties": {
    "addr:full":"Ground Floor, 55 Victoria Pde Collingwood VIC 3066",
    "addr:housenumber":"55",
    "addr:postcode":"3066",
    "addr:street":"Victoria Pde",
    "iso:country":"AU",
    "sg:address":"Ground Floor, 55 Victoria Pde",
    "sg:city":"Collingwood",
    "sg:classifiers":[
        {
            "category":"Banks & Credit Unions",
            "subcategory":"Financial Services",
            "type":"Services"
        }
    ],
    "sg:phone":"+61 1300 139 736",
    "sg:postcode":"3066",
    "sg:province":"VIC",
    "sg:tags":[
        "planning"
    ],
    "wof:name":"Wren Investment Advisers",
    "wof:placetype":"venue"
},
  "geometry": {"coordinates":[144.98452758799999,-37.8087654114],"type":"Point"}
}