{
  "type": "Feature",
  "properties": {
    "addr:full":"516 Mulgrave Rd Earlville QLD 4870",
    "addr:housenumber":"516",
    "addr:postcode":"4870",
    "addr:street":"Mulgrave Rd",
    "iso:country":"AU",
    "sg:address":"516 Mulgrave Rd",
    "sg:city":"Earlville",
    "sg:classifiers":[
        {
            "category":"Autos & Motor Vehicles",
            "subcategory":"Automobile Sales",
            "type":"Retail Goods"
        }
    ],
    "sg:phone":"+61 7 4033 0111",
    "sg:postcode":"4870",
    "sg:province":"QLD",
    "sg:tags":[
        "car",
        "used"
    ],
    "wof:name":"Drivers Mart",
    "wof:placetype":"venue"
},
  "geometry": {"coordinates":[145.73829650900001,-16.9437980652],"type":"Point"}
}