{
  "type": "Feature",
  "properties": {
    "iso:country":"AU",
    "sg:address":"Shop 7 Regent Arcade Rundle Mall",
    "sg:city":"Adelaide",
    "sg:classifiers":[
        {
            "category":"Retail",
            "subcategory":"Repair Shop",
            "type":"Services"
        }
    ],
    "sg:phone":"+61 8 8232 0707",
    "sg:postcode":"5000",
    "sg:province":"SA",
    "sg:tags":[
        "mending",
        "clothing",
        "alteration"
    ],
    "wof:name":"5 Star Alterations",
    "wof:placetype":"venue"
},
  "geometry": {"coordinates":[138.60609435999999,-34.9274520874],"type":"Point"}
}