{
  "type": "Feature",
  "properties": {
    "addr:full":"97 Gascoigne St Kingswood NSW 2747",
    "addr:housenumber":"97",
    "addr:postcode":"2747",
    "addr:street":"Gascoigne St",
    "iso:country":"AU",
    "sg:address":"97 Gascoigne St",
    "sg:city":"Kingswood",
    "sg:classifiers":[
        {
            "category":"Manufacturing",
            "subcategory":"Retail Goods",
            "type":"Manufacturing & Wholesale Goods"
        }
    ],
    "sg:phone":"+61 2 4731 3940",
    "sg:postcode":"2747",
    "sg:province":"NSW",
    "sg:tags":[
        "merchant",
        "pump",
        "mfrs"
    ],
    "wof:name":"General Pump Company",
    "wof:placetype":"venue"
},
  "geometry": {"coordinates":[150.71870422399999,-33.7534828186],"type":"Point"}
}