{
  "type": "Feature",
  "properties": {
    "iso:country":"AU",
    "sg:address":"127 Wharf St",
    "sg:city":"Forster",
    "sg:classifiers":[
        {
            "category":"Professional",
            "subcategory":"Accounting & Tax Preparation",
            "type":"Services"
        }
    ],
    "sg:phone":"+61 2 6555 2020",
    "sg:postcode":"2428",
    "sg:province":"NSW",
    "sg:tags":[
        "consultant",
        "taxation"
    ],
    "wof:name":"Domina John",
    "wof:placetype":"venue"
},
  "geometry": {"coordinates":[152.50810200000001,-32.179981],"type":"Point"}
}