{
  "type": "Feature",
  "properties": {
    "iso:country":"AU",
    "sg:address":"41 Avelia St",
    "sg:city":"Alexandra Hills",
    "sg:classifiers":[
        {
            "category":"Retail",
            "subcategory":"Driving School",
            "type":"Services"
        }
    ],
    "sg:phone":"+61 417 280 340",
    "sg:postcode":"4161",
    "sg:province":"QLD",
    "wof:name":"Southern Cross Training Services",
    "wof:placetype":"venue"
},
  "geometry": {"coordinates":[153.21180725100001,-27.517747879],"type":"Point"}
}