{
  "type": "Feature",
  "properties": {
    "iso:country":"AU",
    "sg:address":"10 Hillcrest Ave",
    "sg:city":"Eltham",
    "sg:classifiers":[
        {
            "category":"Wholesale",
            "subcategory":"Painting Supplies",
            "type":"Manufacturing & Wholesale Goods"
        }
    ],
    "sg:phone":"+61 3 9439 6468",
    "sg:postcode":"3095",
    "sg:province":"VIC",
    "sg:tags":[
        "product",
        "cleaning"
    ],
    "wof:name":"Grace Peter & Beth",
    "wof:placetype":"venue"
},
  "geometry": {"coordinates":[145.15388488799999,-37.7288970947],"type":"Point"}
}