{
  "type": "Feature",
  "properties": {
    "addr:full":"324- 328 Windang Rd Windang NSW 2528",
    "addr:housenumber":"328",
    "addr:postcode":"2528",
    "addr:street":"Windang Rd",
    "iso:country":"AU",
    "sg:address":"324- 328 Windang Rd",
    "sg:city":"Windang",
    "sg:classifiers":[
        {
            "category":"Train Station",
            "subcategory":"Light Rail",
            "type":"Transportation"
        }
    ],
    "sg:phone":"+61 2 4297 8666",
    "sg:postcode":"2528",
    "sg:province":"NSW",
    "sg:tags":[
        "equipment",
        "energy",
        "solar"
    ],
    "wof:name":"Pool & Spa Central",
    "wof:placetype":"venue"
},
  "geometry": {"coordinates":[150.86854553200001,-34.5321350098],"type":"Point"}
}