{
  "type": "Feature",
  "properties": {
    "iso:country":"AU",
    "sg:address":"246 Old Northern Rd",
    "sg:city":"Castle Hill",
    "sg:classifiers":[
        {
            "category":"Personal",
            "subcategory":"Beauty Salon",
            "type":"Services"
        }
    ],
    "sg:phone":"+61 2 8850 5033",
    "sg:postcode":"2154",
    "sg:province":"NSW",
    "sg:tags":[
        "hairdresser"
    ],
    "wof:name":"Redzz Curl-Up & Dye",
    "wof:placetype":"venue"
},
  "geometry": {"coordinates":[151.002853394,-33.7351531982],"type":"Point"}
}