{
  "type": "Feature",
  "properties": {
    "addr:full":"PO Box 140 Vaucluse NSW 2030",
    "addr:postcode":"2030",
    "iso:country":"AU",
    "sg:address":"PO Box 140",
    "sg:city":"Vaucluse",
    "sg:classifiers":[
        {
            "category":"Personal",
            "subcategory":"Massage",
            "type":"Services"
        }
    ],
    "sg:phone":"+61 416 279 439",
    "sg:postcode":"2030",
    "sg:province":"NSW",
    "sg:tags":[
        "therapy"
    ],
    "wof:name":"BalanSD",
    "wof:placetype":"venue"
},
  "geometry": {"coordinates":[151.28192138700001,-33.8597106934],"type":"Point"}
}