{
  "type": "Feature",
  "properties": {
    "addr:full":"27 Matthews St Parkes NSW 2870",
    "addr:housenumber":"27",
    "addr:postcode":"2870",
    "addr:street":"Matthews St",
    "iso:country":"AU",
    "sg:address":"27 Matthews St",
    "sg:city":"Parkes",
    "sg:classifiers":[
        {
            "category":"Retail",
            "subcategory":"Auto Repair",
            "type":"Services"
        }
    ],
    "sg:phone":"+61 2 6862 4180",
    "sg:postcode":"2870",
    "sg:province":"NSW",
    "sg:tags":[
        "repairer",
        "motor",
        "engineer"
    ],
    "wof:name":"Jeff Page Automotive Services",
    "wof:placetype":"venue"
},
  "geometry": {"coordinates":[148.16244499999999,-33.148979],"type":"Point"}
}