{
  "type": "Feature",
  "properties": {
    "iso:country":"AU",
    "sg:address":"33 Liverpool St",
    "sg:city":"Ingleburn",
    "sg:classifiers":[
        {
            "category":"Manufacturing",
            "subcategory":"Metals",
            "type":"Manufacturing & Wholesale Goods"
        }
    ],
    "sg:phone":"+61 2 9829 2711",
    "sg:postcode":"2565",
    "sg:province":"NSW",
    "sg:tags":[
        "steel",
        "fabricator",
        "mfrs"
    ],
    "wof:name":"Ficogi Engineering Pty Ltd",
    "wof:placetype":"venue"
},
  "geometry": {"coordinates":[150.85853576700001,-33.9997177124],"type":"Point"}
}