{
  "type": "Feature",
  "properties": {
    "iso:country":"AU",
    "sg:address":"Hook Rd",
    "sg:city":"Winnellie",
    "sg:classifiers":[
        {
            "category":"Arena",
            "subcategory":"Sports Club",
            "type":"Entertainment"
        }
    ],
    "sg:phone":"+61 8 8984 3167",
    "sg:postcode":"0820",
    "sg:province":"NT",
    "sg:tags":[
        "hunt",
        "racing"
    ],
    "wof:name":"Darwin Greyhound Association Of The N.T.",
    "wof:placetype":"venue"
},
  "geometry": {"coordinates":[130.89439392099999,-12.4263429642],"type":"Point"}
}