{
  "type": "Feature",
  "properties": {
    "addr:full":"Newry Rd Boisdale VIC 3860",
    "addr:postcode":"3860",
    "addr:street":"Newry Rd",
    "iso:country":"AU",
    "sg:address":"Newry Rd",
    "sg:city":"Boisdale",
    "sg:classifiers":[
        {
            "category":"Education",
            "subcategory":"School",
            "type":"Public Place"
        }
    ],
    "sg:phone":"+61 3 5145 4391",
    "sg:postcode":"3860",
    "sg:province":"VIC",
    "sg:tags":[
        "state",
        "except",
        "nsw"
    ],
    "wof:name":"Boisdale Primary School",
    "wof:placetype":"venue"
},
  "geometry": {"coordinates":[146.955932617,-37.9315681458],"type":"Point"}
}