{
  "type": "Feature",
  "properties": {
    "addr:full":"636 North Rd Ormond VIC 3204",
    "addr:housenumber":"636",
    "addr:postcode":"3204",
    "addr:street":"North Rd",
    "iso:country":"AU",
    "sg:address":"636 North Rd",
    "sg:city":"Ormond",
    "sg:classifiers":[
        {
            "category":"Fast Food",
            "type":"Food & Drink"
        }
    ],
    "sg:phone":"+61 3 9576 9300",
    "sg:postcode":"3204",
    "sg:province":"VIC",
    "sg:tags":[
        "away",
        "take"
    ],
    "wof:name":"Pizza Haven",
    "wof:placetype":"venue"
},
  "geometry": {"coordinates":[145.04347200000001,-37.904491],"type":"Point"}
}