{
  "type": "Feature",
  "properties": {
    "iso:country":"AU",
    "sg:address":"Level 1/ 723 Hunter St",
    "sg:city":"Newcastle",
    "sg:classifiers":[
        {
            "category":"Health Services",
            "subcategory":"Health Practitioner",
            "type":"Services"
        }
    ],
    "sg:phone":"+61 2 4961 5800",
    "sg:postcode":"2300",
    "sg:province":"NSW",
    "sg:tags":[
        "herbalist"
    ],
    "wof:name":"Hunter College Of Massage",
    "wof:placetype":"venue"
},
  "geometry": {"coordinates":[151.760178,-32.925678],"type":"Point"}
}