{
  "type": "Feature",
  "properties": {
    "iso:country":"AU",
    "sg:address":"679 Heidelberg Rd",
    "sg:city":"Alphington",
    "sg:classifiers":[
        {
            "category":"Autos & Motor Vehicles",
            "subcategory":"Automobile Sales",
            "type":"Retail Goods"
        }
    ],
    "sg:phone":"+61 3 9497 2378",
    "sg:postcode":"3078",
    "sg:province":"VIC",
    "sg:tags":[
        "car",
        "used"
    ],
    "wof:name":"Harmil Motors",
    "wof:placetype":"venue"
},
  "geometry": {"coordinates":[145.02850341800001,-37.7811317444],"type":"Point"}
}