{
  "type": "Feature",
  "properties": {
    "addr:full":"32 Anzac Pde Yeppoon QLD 4703",
    "addr:housenumber":"32",
    "addr:postcode":"4703",
    "addr:street":"Anzac Pde",
    "iso:country":"AU",
    "sg:address":"32 Anzac Pde",
    "sg:city":"Yeppoon",
    "sg:classifiers":[
        {
            "category":"Travel",
            "subcategory":"Hotels & Motels",
            "type":"Entertainment"
        }
    ],
    "sg:phone":"+61 7 4939 1594",
    "sg:postcode":"4703",
    "sg:province":"QLD",
    "wof:name":"Como Beachfront Units",
    "wof:placetype":"venue"
},
  "geometry": {"coordinates":[150.74940490700001,-23.1321239471],"type":"Point"}
}