{
  "type": "Feature",
  "properties": {
    "iso:country":"AU",
    "sg:address":"14 Ash Pl",
    "sg:city":"Narellan",
    "sg:classifiers":[
        {
            "category":"Utilities",
            "subcategory":"Electric",
            "type":"Services"
        }
    ],
    "sg:phone":"+61 2 4647 8036",
    "sg:postcode":"2567",
    "sg:province":"NSW",
    "sg:tags":[
        "electrical",
        "contractor"
    ],
    "wof:name":"North Point Electrical Services Pty Ltd",
    "wof:placetype":"venue"
},
  "geometry": {"coordinates":[150.74159240700001,-34.0508613586],"type":"Point"}
}