{
  "type": "Feature",
  "properties": {
    "iso:country":"AU",
    "sg:address":"225 Buckley St",
    "sg:city":"Footscray",
    "sg:classifiers":[
        {
            "category":"Professional",
            "subcategory":"Detective & Security Services",
            "type":"Services"
        }
    ],
    "sg:phone":"+61 3 9687 8282",
    "sg:postcode":"3011",
    "sg:province":"VIC",
    "sg:tags":[
        "equipment",
        "window",
        "doors"
    ],
    "wof:name":"Royal Screens Pty Ltd",
    "wof:placetype":"venue"
},
  "geometry": {"coordinates":[144.88682556099999,-37.8023529053],"type":"Point"}
}