{
  "type": "Feature",
  "properties": {
    "iso:country":"AU",
    "sg:address":"14 Challenor St",
    "sg:city":"Toowoomba",
    "sg:classifiers":[
        {
            "category":"Building & Trades",
            "subcategory":"Construction",
            "type":"Services"
        }
    ],
    "sg:phone":"+61 418 716 424",
    "sg:postcode":"4350",
    "sg:province":"QLD",
    "sg:tags":[
        "contractor"
    ],
    "wof:name":"Gooderham Robert J",
    "wof:placetype":"venue"
},
  "geometry": {"coordinates":[151.932007,-27.543652],"type":"Point"}
}