{
  "type": "Feature",
  "properties": {
    "iso:country":"AU",
    "sg:address":"280 Church St",
    "sg:city":"Newtown",
    "sg:classifiers":[
        {
            "category":"Health Services",
            "subcategory":"Health Practitioner",
            "type":"Services"
        }
    ],
    "sg:phone":"+61 2 9519 9960",
    "sg:postcode":"2042",
    "sg:province":"NSW",
    "sg:tags":[
        "alternative"
    ],
    "wof:name":"Kaye Margaret",
    "wof:placetype":"venue"
},
  "geometry": {"coordinates":[151.180984,-33.894886],"type":"Point"}
}