{
  "type": "Feature",
  "properties": {
    "addr:full":"19A Frederick St Putney NSW 2112",
    "addr:housenumber":"19a",
    "addr:postcode":"2112",
    "addr:street":"Frederick St",
    "iso:country":"AU",
    "sg:address":"19A Frederick St",
    "sg:city":"Putney",
    "sg:classifiers":[
        {
            "category":"Health Services",
            "subcategory":"Doctor",
            "type":"Services"
        }
    ],
    "sg:phone":"+61 414 182 424",
    "sg:postcode":"2112",
    "sg:province":"NSW",
    "sg:tags":[
        "reflexology"
    ],
    "wof:name":"Christine Humphreys",
    "wof:placetype":"venue"
},
  "geometry": {"coordinates":[151.112823486,-33.8209877014],"type":"Point"}
}