{
  "type": "Feature",
  "properties": {
    "addr:full":"Unit 11, 16-22 Bremner Rd Rothwell QLD 4022",
    "addr:housenumber":"16-22",
    "addr:postcode":"4022",
    "addr:street":"Bremner Rd",
    "iso:country":"AU",
    "sg:address":"Unit 11, 16-22 Bremner Rd",
    "sg:city":"Rothwell",
    "sg:classifiers":[
        {
            "category":"Recreation",
            "subcategory":"Boat Charter",
            "type":"Entertainment"
        }
    ],
    "sg:phone":"+61 7 3204 0726",
    "sg:postcode":"4022",
    "sg:province":"QLD",
    "sg:tags":[
        "hire",
        "drive"
    ],
    "wof:name":"Deception Bay Bait & Tackle",
    "wof:placetype":"venue"
},
  "geometry": {"coordinates":[153.06274400000001,-27.219032],"type":"Point"}
}