{
  "type": "Feature",
  "properties": {
    "addr:full":"2 Davey St Mandurah WA 6210",
    "addr:housenumber":"2",
    "addr:postcode":"6210",
    "addr:street":"Davey St",
    "iso:country":"AU",
    "sg:address":"2 Davey St",
    "sg:city":"Mandurah",
    "sg:classifiers":[
        {
            "category":"Real Estate",
            "subcategory":"Real Estate Agent",
            "type":"Services"
        }
    ],
    "sg:phone":"+61 8 9581 4555",
    "sg:postcode":"6210",
    "sg:province":"WA",
    "wof:name":"Ray White Mandurah",
    "wof:placetype":"venue"
},
  "geometry": {"coordinates":[115.722672,-32.533596],"type":"Point"}
}