{
  "type": "Feature",
  "properties": {
    "addr:full":"Shop 3 20 Taylors Ave Morphett Vale SA 5162",
    "addr:housenumber":"shop;20",
    "addr:postcode":"5162",
    "addr:street":"Taylors Ave",
    "iso:country":"AU",
    "sg:address":"Shop 3 20 Taylors Ave",
    "sg:city":"Morphett Vale",
    "sg:classifiers":[
        {
            "category":"Personal",
            "subcategory":"Beauty Salon",
            "type":"Services"
        }
    ],
    "sg:phone":"+61 8 8325 1269",
    "sg:postcode":"5162",
    "sg:province":"SA",
    "sg:tags":[
        "hairdresser"
    ],
    "wof:name":"Immaculate Hair Concept",
    "wof:placetype":"venue"
},
  "geometry": {"coordinates":[138.54307556099999,-35.1263122559],"type":"Point"}
}