{
  "type": "Feature",
  "properties": {
    "iso:country":"AU",
    "sg:address":"1- 3 Morgan Crt",
    "sg:city":"Glenroy",
    "sg:classifiers":[
        {
            "category":"Health Services",
            "subcategory":"Optometrist",
            "type":"Services"
        }
    ],
    "sg:phone":"+61 3 9306 9941",
    "sg:postcode":"3046",
    "sg:province":"VIC",
    "wof:name":"Di Falco Sam Mr",
    "wof:placetype":"venue"
},
  "geometry": {"coordinates":[144.916473389,-37.7060165405],"type":"Point"}
}