{
  "type": "Feature",
  "properties": {
    "addr:full":"889 Burwood Hwy Ferntree Gully VIC 3156",
    "addr:housenumber":"889",
    "addr:postcode":"3156",
    "addr:street":"Burwood Hwy",
    "iso:country":"AU",
    "sg:address":"889 Burwood Hwy",
    "sg:city":"Ferntree Gully",
    "sg:classifiers":[
        {
            "category":"Autos & Motor Vehicles",
            "subcategory":"Auto Supplies",
            "type":"Retail Goods"
        }
    ],
    "sg:phone":"+61 3 9753 6556",
    "sg:postcode":"3156",
    "sg:province":"VIC",
    "sg:tags":[
        "battery",
        "automotive"
    ],
    "wof:name":"Beaurepaires",
    "wof:placetype":"venue"
},
  "geometry": {"coordinates":[145.28128051799999,-37.8836364746],"type":"Point"}
}