{
  "type": "Feature",
  "properties": {
    "iso:country":"AU",
    "sg:address":"9-11 Downie Ave",
    "sg:city":"Bucasia",
    "sg:classifiers":[
        {
            "category":"Health Services",
            "subcategory":"Doctor",
            "type":"Services"
        }
    ],
    "sg:phone":"+61 7 4954 7755",
    "sg:postcode":"4750",
    "sg:province":"QLD",
    "sg:tags":[
        "medical",
        "practitioner"
    ],
    "wof:name":"Northern Beaches Family Practice",
    "wof:placetype":"venue"
},
  "geometry": {"coordinates":[149.157974,-21.0368],"type":"Point"}
}