{
  "type": "Feature",
  "properties": {
    "iso:country":"AU",
    "sg:address":"40 Peregrine Ave",
    "sg:city":"Tamworth",
    "sg:classifiers":[
        {
            "category":"Professional",
            "subcategory":"Accounting & Tax Preparation",
            "type":"Services"
        }
    ],
    "sg:phone":"+61 2 6765 8900",
    "sg:postcode":"2340",
    "sg:province":"NSW",
    "sg:tags":[
        "bookkeeping"
    ],
    "wof:name":"Pamela Joys Bookkeeping Service",
    "wof:placetype":"venue"
},
  "geometry": {"coordinates":[150.948394775,-31.1291007996],"type":"Point"}
}