{
  "type": "Feature",
  "properties": {
    "addr:full":"169 Brisbane Rd Mooloolaba QLD 4557",
    "addr:housenumber":"169",
    "addr:postcode":"4557",
    "addr:street":"Brisbane Rd",
    "iso:country":"AU",
    "sg:address":"169 Brisbane Rd",
    "sg:city":"Mooloolaba",
    "sg:classifiers":[
        {
            "category":"Personal",
            "subcategory":"Beauty Salon",
            "type":"Services"
        }
    ],
    "sg:phone":"+61 7 5444 0017",
    "sg:postcode":"4557",
    "sg:province":"QLD",
    "sg:tags":[
        "hairdresser"
    ],
    "wof:name":"Blush Hair & Beauty",
    "wof:placetype":"venue"
},
  "geometry": {"coordinates":[153.11526489299999,-26.6915054321],"type":"Point"}
}