{
  "type": "Feature",
  "properties": {
    "addr:full":"Level 1 260 Crown St Wollongong NSW 2520",
    "addr:housenumber":"260",
    "addr:postcode":"2520",
    "addr:street":"Crown St",
    "iso:country":"AU",
    "sg:address":"Level 1 260 Crown St",
    "sg:city":"Wollongong",
    "sg:classifiers":[
        {
            "category":"Shopping",
            "subcategory":"Discount & Variety Stores",
            "type":"Retail Goods"
        }
    ],
    "sg:phone":"+61 2 4227 1071",
    "sg:postcode":"2520",
    "sg:province":"NSW",
    "sg:tags":[
        "shop",
        "adult"
    ],
    "wof:name":"Adult Temptations",
    "wof:placetype":"venue"
},
  "geometry": {"coordinates":[150.89141845699999,-34.4251403809],"type":"Point"}
}