{
  "type": "Feature",
  "properties": {
    "addr:full":"Hicks St Russell Vale NSW 2517",
    "addr:postcode":"2517",
    "addr:street":"Hicks St",
    "iso:country":"AU",
    "sg:address":"Hicks St",
    "sg:city":"Russell Vale",
    "sg:classifiers":[
        {
            "category":"Sports & Exercise",
            "subcategory":"Golf",
            "type":"Entertainment"
        }
    ],
    "sg:phone":"+61 2 4285 1286",
    "sg:postcode":"2517",
    "sg:province":"NSW",
    "sg:tags":[
        "club"
    ],
    "wof:name":"Russell Vale Golf Club",
    "wof:placetype":"venue"
},
  "geometry": {"coordinates":[150.90025329599999,-34.3569412231],"type":"Point"}
}