{
  "type": "Feature",
  "properties": {
    "iso:country":"AU",
    "sg:address":"PO Box 7058",
    "sg:city":"Noble Park East",
    "sg:classifiers":[
        {
            "category":"Recreation",
            "type":"Entertainment"
        }
    ],
    "sg:phone":"+61 3 9546 9939",
    "sg:postcode":"3174",
    "sg:province":"VIC",
    "sg:tags":[
        "club",
        "card"
    ],
    "wof:name":"Dandenong Bridge Club Inc",
    "wof:placetype":"venue"
},
  "geometry": {"coordinates":[145.180145264,-37.9604682922],"type":"Point"}
}