{
  "type": "Feature",
  "properties": {
    "iso:country":"AU",
    "sg:address":"1st Floor 82 Waymouth St",
    "sg:city":"Adelaide",
    "sg:classifiers":[
        {
            "category":"Professional",
            "subcategory":"Management & Consulting",
            "type":"Services"
        }
    ],
    "sg:phone":"+61 8 8221 6665",
    "sg:postcode":"5000",
    "sg:province":"SA",
    "sg:tags":[
        "consultant",
        "industrial",
        "relation"
    ],
    "wof:name":"EMA Consulting Pty Ltd",
    "wof:placetype":"venue"
},
  "geometry": {"coordinates":[138.598999023,-34.9259376526],"type":"Point"}
}