{
  "type": "Feature",
  "properties": {
    "iso:country":"AU",
    "sg:address":"154 Goondoon St",
    "sg:city":"Gladstone",
    "sg:classifiers":[
        {
            "category":"Retail",
            "subcategory":"Car Wash",
            "type":"Services"
        }
    ],
    "sg:phone":"+61 7 4972 9202",
    "sg:postcode":"4680",
    "sg:province":"QLD",
    "sg:tags":[
        "truck",
        "cleaning"
    ],
    "wof:name":"Superwash Gladstone",
    "wof:placetype":"venue"
},
  "geometry": {"coordinates":[151.257568359,-23.8456630707],"type":"Point"}
}