{
  "type": "Feature",
  "properties": {
    "addr:full":"19 Kirrawee Drv Redwood Park SA 5097",
    "addr:housenumber":"19",
    "addr:postcode":"5097",
    "addr:street":"Kirrawee Drv",
    "iso:country":"AU",
    "sg:address":"19 Kirrawee Drv",
    "sg:city":"Redwood Park",
    "sg:classifiers":[
        {
            "category":"Education",
            "subcategory":"Music School",
            "type":"Public Place"
        }
    ],
    "sg:phone":"+61 8 8251 4765",
    "sg:postcode":"5097",
    "sg:province":"SA",
    "sg:tags":[
        "teacher"
    ],
    "wof:name":"Baer Yvette- Piano",
    "wof:placetype":"venue"
},
  "geometry": {"coordinates":[138.715744019,-34.8106384277],"type":"Point"}
}