{
  "type": "Feature",
  "properties": {
    "iso:country":"AU",
    "sg:address":"12 Davy St",
    "sg:city":"Tatura",
    "sg:classifiers":[
        {
            "category":"Professional",
            "subcategory":"Art Services",
            "type":"Services"
        }
    ],
    "sg:phone":"+61 423 497 327",
    "sg:postcode":"3616",
    "sg:province":"VIC",
    "sg:tags":[
        "decorator",
        "painter"
    ],
    "wof:name":"B .J. Dalby",
    "wof:placetype":"venue"
},
  "geometry": {"coordinates":[145.23175048799999,-36.4458351135],"type":"Point"}
}