{
  "type": "Feature",
  "properties": {
    "addr:full":"PO Box 277 Wandin North VIC 3139",
    "addr:postcode":"3139",
    "iso:country":"AU",
    "sg:address":"PO Box 277",
    "sg:city":"Wandin North",
    "sg:classifiers":[
        {
            "category":"Building & Trades",
            "subcategory":"Construction",
            "type":"Services"
        }
    ],
    "sg:phone":"+61 409 236 113",
    "sg:postcode":"3139",
    "sg:province":"VIC",
    "sg:tags":[
        "plasterboard",
        "plasterer",
        "fixer"
    ],
    "wof:name":"Legg Jeff",
    "wof:placetype":"venue"
},
  "geometry": {"coordinates":[145.427246094,-37.7789306641],"type":"Point"}
}