{
  "type": "Feature",
  "properties": {
    "iso:country":"AU",
    "sg:address":"47 Waymouth St",
    "sg:city":"Adelaide",
    "sg:classifiers":[
        {
            "category":"Organizations",
            "subcategory":"Non-profit Organization",
            "type":"Services"
        }
    ],
    "sg:phone":"+61 8 8232 4644",
    "sg:postcode":"5000",
    "sg:province":"SA",
    "sg:tags":[
        "support",
        "disability",
        "organisation"
    ],
    "wof:name":"Blind Sporting Council Inc",
    "wof:placetype":"venue"
},
  "geometry": {"coordinates":[138.59902954099999,-34.9259376526],"type":"Point"}
}