{
  "type": "Feature",
  "properties": {
    "addr:full":"PO Box 890 C.P Mildura VIC 3501",
    "addr:postcode":"c.p;3501",
    "iso:country":"AU",
    "sg:address":"PO Box 890",
    "sg:city":"C.P Mildura",
    "sg:classifiers":[
        {
            "category":"Farming",
            "subcategory":"Farm & Veterinary Services",
            "type":"Manufacturing & Wholesale Goods"
        }
    ],
    "sg:phone":"+61 409 177 114",
    "sg:postcode":"3501",
    "sg:province":"VIC",
    "sg:tags":[
        "irrigation",
        "reticulation",
        "system"
    ],
    "wof:name":"Sunraysia Irrigation & Garden Edging",
    "wof:placetype":"venue"
},
  "geometry": {"coordinates":[142.161712647,-34.186050415],"type":"Point"}
}