{
  "type": "Feature",
  "properties": {
    "addr:full":"77 Bannigan Ave Success WA 6164",
    "addr:housenumber":"77",
    "addr:postcode":"6164",
    "addr:street":"Bannigan Ave",
    "iso:country":"AU",
    "sg:address":"77 Bannigan Ave",
    "sg:city":"Success",
    "sg:classifiers":[
        {
            "category":"Building & Trades",
            "subcategory":"Construction",
            "type":"Services"
        }
    ],
    "sg:phone":"+61 419 194 861",
    "sg:postcode":"6164",
    "sg:province":"WA",
    "sg:tags":[
        "welding"
    ],
    "wof:name":"Ferret Boilermaking",
    "wof:placetype":"venue"
},
  "geometry": {"coordinates":[115.849518,-32.140762],"type":"Point"}
}