{
  "type": "Feature",
  "properties": {
    "addr:full":"336 St Kilda Rd St Kilda VIC 3182",
    "addr:housenumber":"336",
    "addr:postcode":"3182",
    "addr:street":"St Kilda Rd",
    "iso:country":"AU",
    "sg:address":"336 St Kilda Rd",
    "sg:city":"St Kilda",
    "sg:classifiers":[
        {
            "category":"Professional",
            "subcategory":"Business Services",
            "type":"Services"
        }
    ],
    "sg:phone":"+61 3 9593 9240",
    "sg:postcode":"3182",
    "sg:province":"VIC",
    "sg:tags":[
        "fashion",
        "agent"
    ],
    "wof:name":"YUG Corp Pty Ltd",
    "wof:placetype":"venue"
},
  "geometry": {"coordinates":[144.98638915999999,-37.8654975891],"type":"Point"}
}