{
  "type": "Feature",
  "properties": {
    "iso:country":"AU",
    "sg:address":"Killarney Rd",
    "sg:city":"Tumut",
    "sg:classifiers":[
        {
            "category":"Home & Garden",
            "subcategory":"Garden Supply",
            "type":"Retail Goods"
        }
    ],
    "sg:phone":"+61 2 6947 4704",
    "sg:postcode":"2720",
    "sg:province":"NSW",
    "sg:tags":[
        "landscape"
    ],
    "wof:name":"Australian Native Landscapes Pty Ltd",
    "wof:placetype":"venue"
},
  "geometry": {"coordinates":[148.182709,-35.324753],"type":"Point"}
}