{
  "type": "Feature",
  "properties": {
    "addr:full":"Shop 39 Albert St Taree NSW 2430",
    "addr:housenumber":"shop 39",
    "addr:postcode":"2430",
    "addr:street":"Albert St",
    "iso:country":"AU",
    "sg:address":"Shop 39 Albert St",
    "sg:city":"Taree",
    "sg:classifiers":[
        {
            "category":"Shopping",
            "subcategory":"Bridal",
            "type":"Retail Goods"
        }
    ],
    "sg:phone":"+61 2 6551 7128",
    "sg:postcode":"2430",
    "sg:province":"NSW",
    "sg:tags":[
        "hire",
        "wear"
    ],
    "wof:name":"Wedding Wotnots",
    "wof:placetype":"venue"
},
  "geometry": {"coordinates":[152.46113600000001,-31.910984],"type":"Point"}
}