{
  "type": "Feature",
  "properties": {
    "iso:country":"AU",
    "sg:address":"2/ 115 Military Rd",
    "sg:city":"Neutral Bay",
    "sg:classifiers":[
        {
            "category":"Arts & Performance",
            "subcategory":"Art Gallery",
            "type":"Entertainment"
        }
    ],
    "sg:phone":"+61 2 9953 3531",
    "sg:postcode":"2089",
    "sg:province":"NSW",
    "wof:name":"Hilton Hordern",
    "wof:placetype":"venue"
},
  "geometry": {"coordinates":[151.22035217300001,-33.8309173584],"type":"Point"}
}