{
  "type": "Feature",
  "properties": {
    "addr:full":"Albert St Beaudesert QLD 4285",
    "addr:postcode":"4285",
    "addr:street":"Albert St",
    "iso:country":"AU",
    "sg:address":"Albert St",
    "sg:city":"Beaudesert",
    "sg:classifiers":[
        {
            "category":"Organizations",
            "subcategory":"Community Association",
            "type":"Services"
        }
    ],
    "sg:phone":"+61 7 5541 2643",
    "sg:postcode":"4285",
    "sg:province":"QLD",
    "sg:tags":[
        "organisation",
        "family",
        "welfare"
    ],
    "wof:name":"Meals On Wheels",
    "wof:placetype":"venue"
},
  "geometry": {"coordinates":[152.99655200000001,-27.990602],"type":"Point"}
}