{
  "type": "Feature",
  "properties": {
    "iso:country":"AU",
    "sg:address":"22 High St",
    "sg:city":"Fremantle",
    "sg:classifiers":[
        {
            "category":"Real Estate",
            "subcategory":"Developer",
            "type":"Services"
        }
    ],
    "sg:phone":"+61 8 9336 3996",
    "sg:postcode":"6160",
    "sg:province":"WA",
    "sg:tags":[
        "chartering",
        "ship",
        "broker"
    ],
    "wof:name":"Western Offshore Technology Pty Ltd",
    "wof:placetype":"venue"
},
  "geometry": {"coordinates":[115.745216,-32.054749],"type":"Point"}
}