{
  "type": "Feature",
  "properties": {
    "addr:full":"101 Hyde Rd Yeronga QLD 4104",
    "addr:housenumber":"101",
    "addr:postcode":"4104",
    "addr:street":"Hyde Rd",
    "iso:country":"AU",
    "sg:address":"101 Hyde Rd",
    "sg:city":"Yeronga",
    "sg:classifiers":[
        {
            "category":"Communications",
            "type":"Services"
        }
    ],
    "sg:phone":"+61 7 3392 7600",
    "sg:postcode":"4104",
    "sg:province":"QLD",
    "sg:tags":[
        "equipment",
        "microwave"
    ],
    "wof:name":"EM Solutions Pty Ltd",
    "wof:placetype":"venue"
},
  "geometry": {"coordinates":[153.014404297,-27.5114784241],"type":"Point"}
}