{
  "type": "Feature",
  "properties": {
    "iso:country":"AU",
    "sg:address":"124 Grigor St West",
    "sg:city":"Caloundra",
    "sg:classifiers":[
        {
            "category":"Manufacturing",
            "subcategory":"Metals",
            "type":"Manufacturing & Wholesale Goods"
        }
    ],
    "sg:phone":"+61 7 5491 7233",
    "sg:postcode":"4551",
    "sg:province":"QLD",
    "sg:tags":[
        "equipment",
        "cutting"
    ],
    "wof:name":"McGrath Machinery Pty Ltd",
    "wof:placetype":"venue"
},
  "geometry": {"coordinates":[153.13682556099999,-26.791721344],"type":"Point"}
}