{
  "type": "Feature",
  "properties": {
    "addr:full":"130 Hogan St Tatura VIC 3616",
    "addr:housenumber":"130",
    "addr:postcode":"3616",
    "addr:street":"Hogan St",
    "iso:country":"AU",
    "sg:address":"130 Hogan St",
    "sg:city":"Tatura",
    "sg:classifiers":[
        {
            "category":"Food & Beverages",
            "subcategory":"Bakery",
            "type":"Retail Goods"
        }
    ],
    "sg:phone":"+61 3 5824 1267",
    "sg:postcode":"3616",
    "sg:province":"VIC",
    "sg:tags":[
        "baker"
    ],
    "wof:name":"Tatura Hot Bread",
    "wof:placetype":"venue"
},
  "geometry": {"coordinates":[145.22723388700001,-36.4402427673],"type":"Point"}
}