{
  "type": "Feature",
  "properties": {
    "addr:full":"27 Commercial St West Mt Gambier SA 5290",
    "addr:housenumber":"27",
    "addr:postcode":"5290",
    "addr:street":"Commercial St West",
    "iso:country":"AU",
    "sg:address":"27 Commercial St West",
    "sg:city":"Mt Gambier",
    "sg:classifiers":[
        {
            "category":"Shopping",
            "subcategory":"Optical Goods",
            "type":"Retail Goods"
        }
    ],
    "sg:phone":"+61 8 8725 7088",
    "sg:postcode":"5290",
    "sg:province":"SA",
    "sg:tags":[
        "dispenser",
        "prescription"
    ],
    "wof:name":"Kevin Paisley Fashion Eyewear",
    "wof:placetype":"venue"
},
  "geometry": {"coordinates":[140.77926600000001,-37.828091],"type":"Point"}
}