{
  "type": "Feature",
  "properties": {
    "addr:full":"9- 11 India St Capalaba QLD 4157",
    "addr:housenumber":"11",
    "addr:postcode":"4157",
    "addr:street":"9;India St",
    "iso:country":"AU",
    "sg:address":"9- 11 India St",
    "sg:city":"Capalaba",
    "sg:classifiers":[
        {
            "category":"Manufacturing",
            "subcategory":"Metals",
            "type":"Manufacturing & Wholesale Goods"
        }
    ],
    "sg:phone":"+61 7 3245 2772",
    "sg:postcode":"4157",
    "sg:province":"QLD",
    "sg:tags":[
        "steel",
        "fabricator",
        "mfrs"
    ],
    "wof:name":"Custom Shades & Fabrication",
    "wof:placetype":"venue"
},
  "geometry": {"coordinates":[153.20208740199999,-27.5303535461],"type":"Point"}
}