{
  "type": "Feature",
  "properties": {
    "iso:country":"AU",
    "sg:address":"36 Berkshire Rd",
    "sg:city":"Sunshine North",
    "sg:classifiers":[
        {
            "category":"Retail",
            "subcategory":"Auto Repair",
            "type":"Services"
        }
    ],
    "sg:phone":"+61 3 9311 3506",
    "sg:postcode":"3020",
    "sg:province":"VIC",
    "sg:tags":[
        "beater",
        "painter",
        "panel"
    ],
    "wof:name":"C & D Panels",
    "wof:placetype":"venue"
},
  "geometry": {"coordinates":[144.842575,-37.765488],"type":"Point"}
}