{
  "type": "Feature",
  "properties": {
    "iso:country":"AU",
    "sg:address":"Shp 37 Neutral Bay Vlge 1-7 Rangers Rd",
    "sg:city":"Neutral Bay",
    "sg:classifiers":[
        {
            "category":"Health Services",
            "subcategory":"Optometrist",
            "type":"Services"
        }
    ],
    "sg:phone":"+61 2 9953 7778",
    "sg:postcode":"2089",
    "sg:province":"NSW",
    "wof:name":"Bergstein Geri, Kotow Michael",
    "wof:placetype":"venue"
},
  "geometry": {"coordinates":[151.22369384800001,-33.8319320679],"type":"Point"}
}