{
  "type": "Feature",
  "properties": {
    "addr:full":"29 Camfield Drv Heatherbrae NSW 2324",
    "addr:housenumber":"29",
    "addr:postcode":"2324",
    "addr:street":"Camfield Drv",
    "iso:country":"AU",
    "sg:address":"29 Camfield Drv",
    "sg:city":"Heatherbrae",
    "sg:classifiers":[
        {
            "category":"Building & Trades",
            "subcategory":"Construction",
            "type":"Services"
        }
    ],
    "sg:phone":"+61 2 4987 3666",
    "sg:postcode":"2324",
    "sg:province":"NSW",
    "sg:tags":[
        "pool",
        "swimming"
    ],
    "wof:name":"Ross Parker",
    "wof:placetype":"venue"
},
  "geometry": {"coordinates":[151.74221801799999,-32.7821807861],"type":"Point"}
}