{
  "type": "Feature",
  "properties": {
    "addr:full":"5 Kropp St Biggera Waters QLD 4216",
    "addr:housenumber":"5",
    "addr:postcode":"4216",
    "addr:street":"Kropp St",
    "iso:country":"AU",
    "sg:address":"5 Kropp St",
    "sg:city":"Biggera Waters",
    "sg:classifiers":[
        {
            "category":"Building & Trades",
            "subcategory":"Plumbing",
            "type":"Services"
        }
    ],
    "sg:phone":"+61 7 5537 3738",
    "sg:postcode":"4216",
    "sg:province":"QLD",
    "sg:tags":[
        "repair",
        "appliance",
        "system",
        "heating"
    ],
    "wof:name":"Gold Coast Heating Installations",
    "wof:placetype":"venue"
},
  "geometry": {"coordinates":[153.398635864,-27.9272212982],"type":"Point"}
}