{
  "type": "Feature",
  "properties": {
    "addr:full":"Level 1, 182 Beamish St Campsie NSW 2194",
    "addr:housenumber":"182",
    "addr:postcode":"2194",
    "addr:street":"Beamish St",
    "iso:country":"AU",
    "sg:address":"Level 1, 182 Beamish St",
    "sg:city":"Campsie",
    "sg:classifiers":[
        {
            "category":"Building & Trades",
            "subcategory":"Construction",
            "type":"Services"
        }
    ],
    "sg:phone":"+61 2 9787 6899",
    "sg:postcode":"2194",
    "sg:province":"NSW",
    "sg:tags":[
        "polishing",
        "sanding",
        "floor"
    ],
    "wof:name":"100% Floor Sanding",
    "wof:placetype":"venue"
},
  "geometry": {"coordinates":[151.10363799999999,-33.909538],"type":"Point"}
}