{
  "type": "Feature",
  "properties": {
    "iso:country":"AU",
    "sg:address":"6 Easterby St",
    "sg:city":"Gladstone",
    "sg:classifiers":[
        {
            "category":"Autos & Motor Vehicles",
            "subcategory":"Auto Supplies",
            "type":"Retail Goods"
        }
    ],
    "sg:phone":"+61 7 4972 7857",
    "sg:postcode":"4680",
    "sg:province":"QLD",
    "sg:tags":[
        "accessory"
    ],
    "wof:name":"Opticool P/L",
    "wof:placetype":"venue"
},
  "geometry": {"coordinates":[151.24957275400001,-23.8435268402],"type":"Point"}
}