{
  "type": "Feature",
  "properties": {
    "addr:full":"510 Macaulay Rd Kensington VIC 3031",
    "addr:housenumber":"510",
    "addr:postcode":"3031",
    "addr:street":"Macaulay Rd",
    "iso:country":"AU",
    "sg:address":"510 Macaulay Rd",
    "sg:city":"Kensington",
    "sg:classifiers":[
        {
            "category":"Health Services",
            "subcategory":"Chiropractor",
            "type":"Services"
        }
    ],
    "sg:phone":"+61 3 9372 5588",
    "sg:postcode":"3031",
    "sg:province":"VIC",
    "wof:name":"Gason Sandra Dr",
    "wof:placetype":"venue"
},
  "geometry": {"coordinates":[144.929047,-37.794167],"type":"Point"}
}