{
  "type": "Feature",
  "properties": {
    "iso:country":"AU",
    "sg:address":"75 Perkins St",
    "sg:city":"South Townsville",
    "sg:classifiers":[
        {
            "category":"Food & Beverages",
            "subcategory":"Supermarket",
            "type":"Retail Goods"
        }
    ],
    "sg:phone":"+61 7 4771 4225",
    "sg:postcode":"4810",
    "sg:province":"QLD",
    "sg:tags":[
        "grocery",
        "store"
    ],
    "wof:name":"Goon Chew D & B C",
    "wof:placetype":"venue"
},
  "geometry": {"coordinates":[146.820694,-19.269415],"type":"Point"}
}