{
  "type": "Feature",
  "properties": {
    "addr:full":"95 Heywood St Bendigo East VIC 3550",
    "addr:housenumber":"95",
    "addr:postcode":"3550",
    "addr:street":"Heywood St",
    "iso:country":"AU",
    "sg:address":"95 Heywood St",
    "sg:city":"Bendigo East",
    "sg:classifiers":[
        {
            "category":"Retail",
            "subcategory":"Repair Shop",
            "type":"Services"
        }
    ],
    "sg:phone":"+61 3 5448 3655",
    "sg:postcode":"3550",
    "sg:province":"VIC",
    "sg:tags":[
        "machine",
        "repairs",
        "part",
        "dryer",
        "washing"
    ],
    "wof:name":"Bendigo Appliance Repairs",
    "wof:placetype":"venue"
},
  "geometry": {"coordinates":[144.300857544,-36.7222557068],"type":"Point"}
}