{
  "type": "Feature",
  "properties": {
    "iso:country":"AU",
    "sg:address":"72 High St",
    "sg:city":"Boonah",
    "sg:classifiers":[
        {
            "category":"Banks & Credit Unions",
            "subcategory":"Investment Brokerage",
            "type":"Services"
        }
    ],
    "sg:phone":"+61 1300 551 998",
    "sg:postcode":"4310",
    "sg:province":"QLD",
    "sg:tags":[
        "finance",
        "broker"
    ],
    "wof:name":"Concept Pro Pty Ltd",
    "wof:placetype":"venue"
},
  "geometry": {"coordinates":[152.68251037600001,-27.9966583252],"type":"Point"}
}