{
  "type": "Feature",
  "properties": {
    "addr:full":"Shop 3 & 4, Mantra Resort Buccaneer Ave Urangan QLD 4655",
    "addr:housenumber":"shop 3 & 4",
    "addr:postcode":"4655",
    "addr:street":"Buccaneer Ave",
    "iso:country":"AU",
    "sg:address":"Shop 3 & 4, Mantra Resort Buccaneer Ave",
    "sg:city":"Urangan",
    "sg:classifiers":[
        {
            "category":"Personal",
            "subcategory":"Day Spa",
            "type":"Services"
        }
    ],
    "sg:phone":"+61 7 4125 3888",
    "sg:postcode":"4655",
    "sg:province":"QLD",
    "wof:name":"Serendipity Spa Retreat",
    "wof:placetype":"venue"
},
  "geometry": {"coordinates":[152.908646,-25.293362],"type":"Point"}
}