{
  "type": "Feature",
  "properties": {
    "iso:country":"AU",
    "sg:address":"2/ 347 Cressy St",
    "sg:city":"Deniliquin",
    "sg:classifiers":[
        {
            "category":"Banks & Credit Unions",
            "subcategory":"Financial Services",
            "type":"Services"
        }
    ],
    "sg:phone":"+61 3 5881 3062",
    "sg:postcode":"2710",
    "sg:province":"NSW",
    "sg:tags":[
        "financier"
    ],
    "wof:name":"Darryl Redden Business & Finance Services",
    "wof:placetype":"venue"
},
  "geometry": {"coordinates":[144.96151733400001,-35.52759552],"type":"Point"}
}