{
  "type": "Feature",
  "properties": {
    "addr:full":"Northern Festival Centre 106 Gertrude St Port Pirie SA 5540",
    "addr:housenumber":"106",
    "addr:postcode":"5540",
    "addr:street":"Gertrude St",
    "iso:country":"AU",
    "sg:address":"Northern Festival Centre 106 Gertrude St",
    "sg:city":"Port Pirie",
    "sg:classifiers":[
        {
            "category":"Cinema",
            "subcategory":"Movie Theater",
            "type":"Entertainment"
        }
    ],
    "sg:phone":"+61 8 8632 4122",
    "sg:postcode":"5540",
    "sg:province":"SA",
    "wof:name":"Keith Michell Theatre",
    "wof:placetype":"venue"
},
  "geometry": {"coordinates":[138.007278442,-33.1786231995],"type":"Point"}
}