{
  "type": "Feature",
  "properties": {
    "iso:country":"AU",
    "sg:address":"66 Roe St",
    "sg:city":"Northbridge",
    "sg:classifiers":[
        {
            "category":"Restaurant",
            "type":"Food & Drink"
        }
    ],
    "sg:phone":"+61 8 9328 9668",
    "sg:postcode":"6003",
    "sg:province":"WA",
    "wof:name":"Chin Chin Eating House",
    "wof:placetype":"venue"
},
  "geometry": {"coordinates":[115.856460571,-31.9487895966],"type":"Point"}
}