{
  "type": "Feature",
  "properties": {
    "addr:full":"6 O&#039;keefe Drv Coffs Harbour NSW 2450",
    "addr:housenumber":"6",
    "addr:postcode":"2450",
    "addr:street":"Keefe Drv",
    "iso:country":"AU",
    "sg:address":"6 O&#039;keefe Drv",
    "sg:city":"Coffs Harbour",
    "sg:classifiers":[
        {
            "category":"Shopping",
            "subcategory":"Bicycles & Sporting Goods",
            "type":"Retail Goods"
        }
    ],
    "sg:phone":"+61 2 6658 0007",
    "sg:postcode":"2450",
    "sg:province":"NSW",
    "sg:tags":[
        "trampoline"
    ],
    "wof:name":"AA Gymnastic & Trampoline Equipment (Wavebay Pty Ltd)",
    "wof:placetype":"venue"
},
  "geometry": {"coordinates":[153.097656,-30.316151],"type":"Point"}
}