{
  "type": "Feature",
  "properties": {
    "addr:full":"Bartram St Dumbleyung WA 6350",
    "addr:postcode":"6350",
    "addr:street":"Bartram St",
    "iso:country":"AU",
    "sg:address":"Bartram St",
    "sg:city":"Dumbleyung",
    "sg:classifiers":[
        {
            "category":"Travel",
            "subcategory":"Hotels & Motels",
            "type":"Entertainment"
        }
    ],
    "sg:phone":"+61 8 9863 4028",
    "sg:postcode":"6350",
    "sg:province":"WA",
    "sg:tags":[
        "accommodation"
    ],
    "wof:name":"Dumbleyung Tavern",
    "wof:placetype":"venue"
},
  "geometry": {"coordinates":[117.73825100000001,-33.315739],"type":"Point"}
}