{
  "type": "Feature",
  "properties": {
    "addr:full":"Shop 8/ 195 Oxford St Bondi Junction NSW 2022",
    "addr:housenumber":"shop 8 / 195",
    "addr:postcode":"2022",
    "addr:street":"Oxford St",
    "iso:country":"AU",
    "sg:address":"Shop 8/ 195 Oxford St",
    "sg:city":"Bondi Junction",
    "sg:classifiers":[
        {
            "category":"Restaurant",
            "type":"Food & Drink"
        }
    ],
    "sg:phone":"+61 2 9387 7041",
    "sg:postcode":"2022",
    "sg:province":"NSW",
    "wof:name":"Copacabana Bondi Bar & Grill",
    "wof:placetype":"venue"
},
  "geometry": {"coordinates":[151.24935913100001,-33.8921470642],"type":"Point"}
}