{
  "type": "Feature",
  "properties": {
    "iso:country":"AU",
    "sg:address":"Shp3/ 236 Port Elliot Rd",
    "sg:city":"Victor Harbor",
    "sg:classifiers":[
        {
            "category":"Deli",
            "type":"Food & Drink"
        }
    ],
    "sg:phone":"+61 8 8552 3334",
    "sg:postcode":"5211",
    "sg:province":"SA",
    "sg:tags":[
        "delicatessen"
    ],
    "wof:name":"Harbourview Deli",
    "wof:placetype":"venue"
},
  "geometry": {"coordinates":[138.64747619600001,-35.5354385376],"type":"Point"}
}