{
  "type": "Feature",
  "properties": {
    "addr:full":"3/ 14 Hinkler Crt Brendale QLD 4500",
    "addr:housenumber":"/ 14",
    "addr:postcode":"4500",
    "addr:street":"Hinkler Crt",
    "iso:country":"AU",
    "sg:address":"3/ 14 Hinkler Crt",
    "sg:city":"Brendale",
    "sg:classifiers":[
        {
            "category":"Utilities",
            "subcategory":"Sewage",
            "type":"Services"
        }
    ],
    "sg:phone":"+61 7 3889 6144",
    "sg:postcode":"4500",
    "sg:province":"QLD",
    "sg:tags":[
        "water",
        "waste",
        "treatment"
    ],
    "wof:name":"Clivus Multrum Pty Ltd",
    "wof:placetype":"venue"
},
  "geometry": {"coordinates":[152.98797607399999,-27.3043212891],"type":"Point"}
}