{
  "type": "Feature",
  "properties": {
    "iso:country":"AU",
    "sg:address":"Lvl2/ 7 Merriwa St",
    "sg:city":"Gordon",
    "sg:classifiers":[
        {
            "category":"Personal",
            "subcategory":"Beauty Salon",
            "type":"Services"
        }
    ],
    "sg:phone":"+61 2 9418 4988",
    "sg:postcode":"2072",
    "sg:province":"NSW",
    "wof:name":"Pink Hibiscus",
    "wof:placetype":"venue"
},
  "geometry": {"coordinates":[151.14828491200001,-33.7527427673],"type":"Point"}
}