{
  "type": "Feature",
  "properties": {
    "addr:full":"537a Barkly St Footscray West VIC 3012",
    "addr:housenumber":"537a",
    "addr:postcode":"3012",
    "addr:street":"Barkly St",
    "iso:country":"AU",
    "sg:address":"537a Barkly St",
    "sg:city":"Footscray West",
    "sg:classifiers":[
        {
            "category":"Professional",
            "subcategory":"Accounting & Tax Preparation",
            "type":"Services"
        }
    ],
    "sg:phone":"+61 3 9689 3308",
    "sg:postcode":"3012",
    "sg:province":"VIC",
    "sg:tags":[
        "consultant",
        "taxation"
    ],
    "wof:name":"Dukovski & Co CPAs",
    "wof:placetype":"venue"
},
  "geometry": {"coordinates":[144.87847900400001,-37.7976417542],"type":"Point"}
}