{
  "type": "Feature",
  "properties": {
    "iso:country":"AU",
    "sg:address":"Level 2, Reserve Bank Building 45 St Georges St",
    "sg:city":"Perth",
    "sg:classifiers":[
        {
            "category":"Banks & Credit Unions",
            "subcategory":"Financial Services",
            "type":"Services"
        }
    ],
    "sg:phone":"+61 8 9323 2000",
    "sg:postcode":"6000",
    "sg:province":"WA",
    "sg:tags":[
        "registrar",
        "share"
    ],
    "wof:name":"BT Registry (WA) Pty Ltd",
    "wof:placetype":"venue"
},
  "geometry": {"coordinates":[115.858970642,-31.9556350708],"type":"Point"}
}