{
  "type": "Feature",
  "properties": {
    "addr:full":"Shed 2 Unit 14 218 Macquarie Rd Warners Bay NSW 2282",
    "addr:housenumber":"218",
    "addr:postcode":"2282",
    "addr:street":"Macquarie Rd",
    "iso:country":"AU",
    "sg:address":"Shed 2 Unit 14 218 Macquarie Rd",
    "sg:city":"Warners Bay",
    "sg:classifiers":[
        {
            "category":"Professional",
            "type":"Services"
        }
    ],
    "sg:phone":"+61 2 4956 7377",
    "sg:postcode":"2282",
    "sg:province":"NSW",
    "sg:tags":[
        "spray",
        "painting"
    ],
    "wof:name":"Allyance Panel Beating",
    "wof:placetype":"venue"
},
  "geometry": {"coordinates":[151.65281677199999,-32.9658470154],"type":"Point"}
}