{
  "type": "Feature",
  "properties": {
    "iso:country":"AU",
    "sg:address":"PO Box 366",
    "sg:city":"Berowra",
    "sg:classifiers":[
        {
            "category":"Building & Trades",
            "subcategory":"Construction",
            "type":"Services"
        }
    ],
    "sg:phone":"+61 418 600 216",
    "sg:postcode":"2081",
    "sg:province":"NSW",
    "sg:tags":[
        "scaffolding"
    ],
    "wof:name":"Marmin Scaffold Hire",
    "wof:placetype":"venue"
},
  "geometry": {"coordinates":[151.150390625,-33.6227493286],"type":"Point"}
}