{
  "type": "Feature",
  "properties": {
    "iso:country":"AU",
    "sg:address":"Suite 12 1st Floor Randwick Centre, Cnr High St &",
    "sg:city":"Randwick",
    "sg:classifiers":[
        {
            "category":"Health Services",
            "subcategory":"Dentist",
            "type":"Services"
        }
    ],
    "sg:phone":"+61 2 9314 5226",
    "sg:postcode":"2031",
    "sg:province":"NSW",
    "wof:name":"Randwick Dental Clinic",
    "wof:placetype":"venue"
},
  "geometry": {"coordinates":[151.24122619600001,-33.9171638489],"type":"Point"}
}