{
  "type": "Feature",
  "properties": {
    "addr:full":"195 Springvale Rd Nunawading VIC 3131",
    "addr:housenumber":"195",
    "addr:postcode":"3131",
    "addr:street":"Springvale Rd",
    "iso:country":"AU",
    "sg:address":"195 Springvale Rd",
    "sg:city":"Nunawading",
    "sg:classifiers":[
        {
            "category":"Retail",
            "subcategory":"Car Wash",
            "type":"Services"
        }
    ],
    "sg:phone":"+61 3 9894 8377",
    "sg:postcode":"3131",
    "sg:province":"VIC",
    "sg:tags":[
        "truck",
        "cleaning"
    ],
    "wof:name":"Fine Hand Car Wash",
    "wof:placetype":"venue"
},
  "geometry": {"coordinates":[145.17573547399999,-37.8214111328],"type":"Point"}
}