{
  "type": "Feature",
  "properties": {
    "addr:full":"Shop 76 1 West Pde West Ryde NSW 2114",
    "addr:housenumber":"shop 76 1",
    "addr:postcode":"2114",
    "addr:street":"West Pde",
    "iso:country":"AU",
    "sg:address":"Shop 76 1 West Pde",
    "sg:city":"West Ryde",
    "sg:classifiers":[
        {
            "category":"Professional",
            "subcategory":"Computer Services",
            "type":"Services"
        }
    ],
    "sg:phone":"+61 2 9807 9588",
    "sg:postcode":"2114",
    "sg:province":"NSW",
    "sg:tags":[
        "repairs",
        "upgrade",
        "equipment"
    ],
    "wof:name":"JX Technology Pty Ltd",
    "wof:placetype":"venue"
},
  "geometry": {"coordinates":[151.088912964,-33.8076972961],"type":"Point"}
}