{
  "type": "Feature",
  "properties": {
    "addr:full":"30 Oakmont Crs Albany Creek QLD 4035",
    "addr:housenumber":"30",
    "addr:postcode":"4035",
    "addr:street":"Oakmont Crs",
    "iso:country":"AU",
    "sg:address":"30 Oakmont Crs",
    "sg:city":"Albany Creek",
    "sg:classifiers":[
        {
            "category":"Professional",
            "subcategory":"Accounting & Tax Preparation",
            "type":"Services"
        }
    ],
    "sg:phone":"+61 7 3264 4055",
    "sg:postcode":"4035",
    "sg:province":"QLD",
    "sg:tags":[
        "accountant",
        "auditor"
    ],
    "wof:name":"Hirn Consulting",
    "wof:placetype":"venue"
},
  "geometry": {"coordinates":[152.96537799999999,-27.34589],"type":"Point"}
}