{
  "type": "Feature",
  "properties": {
    "addr:full":"Mc Millan St Anglesea VIC 3230",
    "addr:postcode":"3230",
    "addr:street":"Mc Millan St",
    "iso:country":"AU",
    "sg:address":"Mc Millan St",
    "sg:city":"Anglesea",
    "sg:classifiers":[
        {
            "category":"Education",
            "subcategory":"Kindergarten",
            "type":"Public Place"
        }
    ],
    "sg:phone":"+61 3 5263 1376",
    "sg:postcode":"3230",
    "sg:province":"VIC",
    "sg:tags":[
        "pre-schools"
    ],
    "wof:name":"Anglesea Pre-School",
    "wof:placetype":"venue"
},
  "geometry": {"coordinates":[144.186172,-38.4095],"type":"Point"}
}