{
  "type": "Feature",
  "properties": {
    "addr:full":"42 Banyule Crt Wattle Grove NSW 2173",
    "addr:housenumber":"42",
    "addr:postcode":"2173",
    "addr:street":"Banyule Crt",
    "iso:country":"AU",
    "sg:address":"42 Banyule Crt",
    "sg:city":"Wattle Grove",
    "sg:classifiers":[
        {
            "category":"Banks & Credit Unions",
            "subcategory":"Financial Services",
            "type":"Services"
        }
    ],
    "sg:phone":"+61 2 9825 2200",
    "sg:postcode":"2173",
    "sg:province":"NSW",
    "sg:tags":[
        "loan",
        "finance",
        "mortgage"
    ],
    "wof:name":"Kesuma Home Loans",
    "wof:placetype":"venue"
},
  "geometry": {"coordinates":[150.938064575,-33.9532279968],"type":"Point"}
}