{
  "type": "Feature",
  "properties": {
    "iso:country":"AU",
    "sg:address":"481 Old Cleveland Rd",
    "sg:city":"Camp Hill",
    "sg:classifiers":[
        {
            "category":"Personal",
            "subcategory":"Massage",
            "type":"Services"
        }
    ],
    "sg:phone":"+61 7 3843 1722",
    "sg:postcode":"4152",
    "sg:province":"QLD",
    "sg:tags":[
        "therapy"
    ],
    "wof:name":"Positive Life Store",
    "wof:placetype":"venue"
},
  "geometry": {"coordinates":[153.067306519,-27.4918079376],"type":"Point"}
}