{
  "type": "Feature",
  "properties": {
    "addr:full":"18 Loch Carron Ave Farmborough Heights NSW 2526",
    "addr:housenumber":"18",
    "addr:postcode":"2526",
    "addr:street":"Loch Carron Ave",
    "iso:country":"AU",
    "sg:address":"18 Loch Carron Ave",
    "sg:city":"Farmborough Heights",
    "sg:classifiers":[
        {
            "category":"Personal",
            "subcategory":"Beauty Salon",
            "type":"Services"
        }
    ],
    "sg:phone":"+61 2 4272 3707",
    "sg:postcode":"2526",
    "sg:province":"NSW",
    "wof:name":"Beauty By Alison",
    "wof:placetype":"venue"
},
  "geometry": {"coordinates":[150.813995361,-34.458694458],"type":"Point"}
}