{
  "type": "Feature",
  "properties": {
    "addr:full":"67 Anzac Hwy Ashford SA 5035",
    "addr:housenumber":"67",
    "addr:postcode":"5035",
    "addr:street":"Anzac Hwy",
    "iso:country":"AU",
    "sg:address":"67 Anzac Hwy",
    "sg:city":"Ashford",
    "sg:classifiers":[
        {
            "category":"Health Services",
            "subcategory":"Doctor",
            "type":"Services"
        }
    ],
    "sg:phone":"+61 8 8292 3111",
    "sg:postcode":"5035",
    "sg:province":"SA",
    "sg:tags":[
        "podiatrist"
    ],
    "wof:name":"Advanced Podiatry",
    "wof:placetype":"venue"
},
  "geometry": {"coordinates":[138.576629639,-34.9491462708],"type":"Point"}
}