{
  "type": "Feature",
  "properties": {
    "addr:full":"58 Ernest St Innisfail QLD 4860",
    "addr:housenumber":"58",
    "addr:postcode":"4860",
    "addr:street":"Ernest St",
    "iso:country":"AU",
    "sg:address":"58 Ernest St",
    "sg:city":"Innisfail",
    "sg:classifiers":[
        {
            "category":"Food & Beverages",
            "subcategory":"Groceries & Convenience Stores",
            "type":"Retail Goods"
        }
    ],
    "sg:phone":"+61 7 4061 1676",
    "sg:postcode":"4860",
    "sg:province":"QLD",
    "wof:name":"Ernest St News",
    "wof:placetype":"venue"
},
  "geometry": {"coordinates":[146.02809143100001,-17.5244216919],"type":"Point"}
}