{
  "type": "Feature",
  "properties": {
    "addr:full":"16 Slessor Ave Lynbrook VIC 3975",
    "addr:housenumber":"16",
    "addr:postcode":"3975",
    "addr:street":"Slessor Ave",
    "iso:country":"AU",
    "sg:address":"16 Slessor Ave",
    "sg:city":"Lynbrook",
    "sg:classifiers":[
        {
            "category":"Building & Trades",
            "subcategory":"Plumbing",
            "type":"Services"
        }
    ],
    "sg:phone":"+61 3 9799 6770",
    "sg:postcode":"3975",
    "sg:province":"VIC",
    "sg:tags":[
        "plumber",
        "gasfitters"
    ],
    "wof:name":"Damien Gardiner Plumbing",
    "wof:placetype":"venue"
},
  "geometry": {"coordinates":[145.25245666500001,-38.0496368408],"type":"Point"}
}