{
  "type": "Feature",
  "properties": {
    "iso:country":"AU",
    "sg:address":"1181 Wynnum Rd",
    "sg:city":"Cannon Hill",
    "sg:classifiers":[
        {
            "category":"Fast Food",
            "type":"Food & Drink"
        }
    ],
    "sg:phone":"+61 7 3131 8733",
    "sg:postcode":"4170",
    "sg:province":"QLD",
    "sg:tags":[
        "away",
        "take"
    ],
    "wof:name":"Domino's Pizza",
    "wof:placetype":"venue"
},
  "geometry": {"coordinates":[153.112182617,-27.4727287292],"type":"Point"}
}