{
  "type": "Feature",
  "properties": {
    "addr:full":"36 Bartlett Rd Giru QLD 4809",
    "addr:housenumber":"36",
    "addr:postcode":"4809",
    "addr:street":"Bartlett Rd",
    "iso:country":"AU",
    "sg:address":"36 Bartlett Rd",
    "sg:city":"Giru",
    "sg:classifiers":[
        {
            "category":"Commercial Area",
            "type":"Public Place"
        }
    ],
    "sg:phone":"+61 7 3278 6425",
    "sg:postcode":"4809",
    "sg:province":"QLD",
    "sg:tags":[
        "heavy",
        "carrier"
    ],
    "wof:name":"Coral Coast Produce Logistics",
    "wof:placetype":"venue"
},
  "geometry": {"coordinates":[147.13734435999999,-19.5633716583],"type":"Point"}
}