{
  "type": "Feature",
  "properties": {
    "addr:full":"109 Golda Ave Salisbury QLD 4107",
    "addr:housenumber":"109",
    "addr:postcode":"4107",
    "addr:street":"Golda Ave",
    "iso:country":"AU",
    "sg:address":"109 Golda Ave",
    "sg:city":"Salisbury",
    "sg:classifiers":[
        {
            "category":"Education",
            "subcategory":"Kindergarten",
            "type":"Public Place"
        }
    ],
    "sg:phone":"+61 7 3719 3177",
    "sg:postcode":"4107",
    "sg:province":"QLD",
    "sg:tags":[
        "pre-schools"
    ],
    "wof:name":"Southside Christian Centre",
    "wof:placetype":"venue"
},
  "geometry": {"coordinates":[153.040252686,-27.5579109192],"type":"Point"}
}