{
  "type": "Feature",
  "properties": {
    "iso:country":"AU",
    "sg:address":"9b Monaco St",
    "sg:city":"Parkdale",
    "sg:classifiers":[
        {
            "category":"Wholesale",
            "subcategory":"Painting Supplies",
            "type":"Manufacturing & Wholesale Goods"
        }
    ],
    "sg:phone":"+61 417 744 244",
    "sg:postcode":"3194",
    "sg:province":"VIC",
    "sg:tags":[
        "equipment",
        "spraying"
    ],
    "wof:name":"KB Mobile Spray Centre",
    "wof:placetype":"venue"
},
  "geometry": {"coordinates":[145.07351684599999,-37.996547699],"type":"Point"}
}