{
  "type": "Feature",
  "properties": {
    "addr:full":"126 Barry Rd Campbellfield VIC 3061",
    "addr:housenumber":"126",
    "addr:postcode":"3061",
    "addr:street":"Barry Rd",
    "iso:country":"AU",
    "sg:address":"126 Barry Rd",
    "sg:city":"Campbellfield",
    "sg:classifiers":[
        {
            "category":"Utilities",
            "subcategory":"Refuse",
            "type":"Services"
        }
    ],
    "sg:phone":"+61 3 9357 8900",
    "sg:postcode":"3061",
    "sg:province":"VIC",
    "sg:tags":[
        "remover",
        "rubbish"
    ],
    "wof:name":"Melbourne Waste",
    "wof:placetype":"venue"
},
  "geometry": {"coordinates":[144.96473693900001,-37.6678314209],"type":"Point"}
}