{
  "type": "Feature",
  "properties": {
    "addr:full":"63 Eaglesfield St Beaudesert QLD 4285",
    "addr:housenumber":"63",
    "addr:postcode":"4285",
    "addr:street":"Eaglesfield St",
    "iso:country":"AU",
    "sg:address":"63 Eaglesfield St",
    "sg:city":"Beaudesert",
    "sg:classifiers":[
        {
            "category":"Building & Trades",
            "subcategory":"Landscaping Services",
            "type":"Services"
        }
    ],
    "sg:phone":"+61 7 5541 3458",
    "sg:postcode":"4285",
    "sg:province":"QLD",
    "sg:tags":[
        "designer",
        "landscape",
        "contractor"
    ],
    "wof:name":"Antcliff C J & V M",
    "wof:placetype":"venue"
},
  "geometry": {"coordinates":[153.00706500000001,-27.988234],"type":"Point"}
}