{
  "type": "Feature",
  "properties": {
    "addr:full":"Unit 2/ 66 Hassall St Wetherill Park NSW 2164",
    "addr:housenumber":"66",
    "addr:postcode":"2164",
    "addr:street":"Hassall St",
    "iso:country":"AU",
    "sg:address":"Unit 2/ 66 Hassall St",
    "sg:city":"Wetherill Park",
    "sg:classifiers":[
        {
            "category":"Building & Trades",
            "subcategory":"Construction",
            "type":"Services"
        }
    ],
    "sg:phone":"+61 2 9725 3666",
    "sg:postcode":"2164",
    "sg:province":"NSW",
    "sg:tags":[
        "repairing",
        "window"
    ],
    "wof:name":"Economy Glass",
    "wof:placetype":"venue"
},
  "geometry": {"coordinates":[150.912277222,-33.8399429321],"type":"Point"}
}