{
  "type": "Feature",
  "properties": {
    "addr:full":"328 Carlisle St Balaclava VIC 3183",
    "addr:housenumber":"328",
    "addr:postcode":"3183",
    "addr:street":"Carlisle St",
    "iso:country":"AU",
    "sg:address":"328 Carlisle St",
    "sg:city":"Balaclava",
    "sg:classifiers":[
        {
            "category":"Fast Food",
            "type":"Food & Drink"
        }
    ],
    "sg:phone":"+61 3 9527 8733",
    "sg:postcode":"3183",
    "sg:province":"VIC",
    "sg:tags":[
        "away",
        "take"
    ],
    "wof:name":"Glicks II",
    "wof:placetype":"venue"
},
  "geometry": {"coordinates":[144.99598693900001,-37.8689079285],"type":"Point"}
}