{
  "type": "Feature",
  "properties": {
    "iso:country":"AU",
    "sg:address":"590 Anzac Pde",
    "sg:city":"Kingsford",
    "sg:classifiers":[
        {
            "category":"Fast Food",
            "type":"Food & Drink"
        }
    ],
    "sg:phone":"+61 2 9314 1440",
    "sg:postcode":"2032",
    "sg:province":"NSW",
    "sg:tags":[
        "away",
        "take"
    ],
    "wof:name":"Lino's Pizzeria",
    "wof:placetype":"venue"
},
  "geometry": {"coordinates":[151.231201172,-33.9260215759],"type":"Point"}
}