{
  "type": "Feature",
  "properties": {
    "addr:full":"23 Mt Pleasant Rd Belmont VIC 3216",
    "addr:housenumber":"23",
    "addr:postcode":"3216",
    "addr:street":"Mt Pleasant Rd",
    "iso:country":"AU",
    "sg:address":"23 Mt Pleasant Rd",
    "sg:city":"Belmont",
    "sg:classifiers":[
        {
            "category":"Arts & Performance",
            "subcategory":"Art Gallery",
            "type":"Entertainment"
        }
    ],
    "sg:phone":"+61 3 5244 2850",
    "sg:postcode":"3216",
    "sg:province":"VIC",
    "wof:name":"Creative Insprations Gallery",
    "wof:placetype":"venue"
},
  "geometry": {"coordinates":[144.34669494600001,-38.1709594727],"type":"Point"}
}