{
  "type": "Feature",
  "properties": {
    "iso:country":"AU",
    "sg:address":"22A William St",
    "sg:city":"Beaudesert",
    "sg:classifiers":[
        {
            "category":"Fast Food",
            "type":"Food & Drink"
        }
    ],
    "sg:phone":"+61 7 5541 2044",
    "sg:postcode":"4285",
    "sg:province":"QLD",
    "sg:tags":[
        "away",
        "take"
    ],
    "wof:name":"Happy Valley Chinese Family Restaurant",
    "wof:placetype":"venue"
},
  "geometry": {"coordinates":[152.995865,-27.986572],"type":"Point"}
}