{
  "type": "Feature",
  "properties": {
    "addr:full":"3/ 18 Beta Ave Kingston QLD 4114",
    "addr:housenumber":"/ 18",
    "addr:postcode":"4114",
    "addr:street":"Beta Ave",
    "iso:country":"AU",
    "sg:address":"3/ 18 Beta Ave",
    "sg:city":"Kingston",
    "sg:classifiers":[
        {
            "category":"Building & Trades",
            "subcategory":"Landscaping Services",
            "type":"Services"
        }
    ],
    "sg:phone":"+61 421 112 077",
    "sg:postcode":"4114",
    "sg:province":"QLD",
    "sg:tags":[
        "gardener"
    ],
    "wof:name":"A 1 Green Thumb Garden Solutions",
    "wof:placetype":"venue"
},
  "geometry": {"coordinates":[153.10551452600001,-27.6562156677],"type":"Point"}
}