{
  "type": "Feature",
  "properties": {
    "addr:full":"Bramwell Rd Noranda WA 6062",
    "addr:postcode":"6062",
    "addr:street":"Bramwell Rd",
    "iso:country":"AU",
    "sg:address":"Bramwell Rd",
    "sg:city":"Noranda",
    "sg:classifiers":[
        {
            "category":"Education",
            "subcategory":"School",
            "type":"Public Place"
        }
    ],
    "sg:phone":"+61 8 9376 5555",
    "sg:postcode":"6062",
    "sg:province":"WA",
    "sg:tags":[
        "state",
        "except",
        "nsw"
    ],
    "wof:name":"Morley Senior High School",
    "wof:placetype":"venue"
},
  "geometry": {"coordinates":[115.888366699,-31.8740882874],"type":"Point"}
}