{
  "type": "Feature",
  "properties": {
    "iso:country":"AU",
    "sg:address":"20 Rawson Ave",
    "sg:city":"Queens Park",
    "sg:classifiers":[
        {
            "category":"Organizations",
            "subcategory":"Professional Association",
            "type":"Services"
        }
    ],
    "sg:phone":"+61 2 9386 5054",
    "sg:postcode":"2022",
    "sg:province":"NSW",
    "sg:tags":[
        "web",
        "internet"
    ],
    "wof:name":"Golf Site Pty Ltd",
    "wof:placetype":"venue"
},
  "geometry": {"coordinates":[151.243484497,-33.8956985474],"type":"Point"}
}