{
  "type": "Feature",
  "properties": {
    "iso:country":"AU",
    "sg:address":"Lot 8 Hatchs Rd",
    "sg:city":"Nyora",
    "sg:classifiers":[
        {
            "category":"Building & Trades",
            "subcategory":"Plumbing",
            "type":"Services"
        }
    ],
    "sg:phone":"+61 3 5659 6522",
    "sg:postcode":"3987",
    "sg:province":"VIC",
    "sg:tags":[
        "plumber",
        "gasfitters"
    ],
    "wof:name":"Brian Nelson Plumbing",
    "wof:placetype":"venue"
},
  "geometry": {"coordinates":[145.676605225,-38.3323745728],"type":"Point"}
}