{
  "type": "Feature",
  "properties": {
    "iso:country":"AU",
    "sg:address":"25 Old Barrenjoey Rd",
    "sg:city":"Avalon",
    "sg:classifiers":[
        {
            "category":"Health Services",
            "subcategory":"Optometrist",
            "type":"Services"
        }
    ],
    "sg:phone":"+61 2 9918 0616",
    "sg:postcode":"2107",
    "sg:province":"NSW",
    "wof:name":"Norman Valerie Optometrist",
    "wof:placetype":"venue"
},
  "geometry": {"coordinates":[151.328323364,-33.6377868652],"type":"Point"}
}