{
  "type": "Feature",
  "properties": {
    "addr:full":"2/ 24 High St Wauchope NSW 2446",
    "addr:housenumber":"/ 24",
    "addr:postcode":"2446",
    "addr:street":"High St",
    "iso:country":"AU",
    "sg:address":"2/ 24 High St",
    "sg:city":"Wauchope",
    "sg:classifiers":[
        {
            "category":"Health Services",
            "subcategory":"Health Practitioner",
            "type":"Services"
        }
    ],
    "sg:phone":"+61 2 6586 1044",
    "sg:postcode":"2446",
    "sg:province":"NSW",
    "sg:tags":[
        "acupuncture"
    ],
    "wof:name":"Acupuncture Chinese Herbs Vicki Burrows",
    "wof:placetype":"venue"
},
  "geometry": {"coordinates":[152.733643,-31.457497],"type":"Point"}
}