{
  "type": "Feature",
  "properties": {
    "addr:full":"14 Mary St Granville NSW 2142",
    "addr:housenumber":"14",
    "addr:postcode":"2142",
    "addr:street":"Mary St",
    "iso:country":"AU",
    "sg:address":"14 Mary St",
    "sg:city":"Granville",
    "sg:classifiers":[
        {
            "category":"Education",
            "subcategory":"School",
            "type":"Public Place"
        }
    ],
    "sg:phone":"+61 2 9637 0489",
    "sg:postcode":"2142",
    "sg:province":"NSW",
    "sg:tags":[
        "state",
        "-",
        "nsw"
    ],
    "wof:name":"Granville Boys' High School",
    "wof:placetype":"venue"
},
  "geometry": {"coordinates":[151.01017761200001,-33.8339271545],"type":"Point"}
}