{
  "type": "Feature",
  "properties": {
    "iso:country":"AU",
    "sg:address":"18 John St",
    "sg:city":"Lidcombe",
    "sg:classifiers":[
        {
            "category":"Retail",
            "subcategory":"Laundry & Dry Cleaning",
            "type":"Services"
        }
    ],
    "sg:phone":"+61 2 9649 9369",
    "sg:postcode":"2141",
    "sg:province":"NSW",
    "wof:name":"Lidcombe Laundry Services",
    "wof:placetype":"venue"
},
  "geometry": {"coordinates":[151.044525147,-33.8623275757],"type":"Point"}
}