{
  "type": "Feature",
  "properties": {
    "addr:full":"45 Brighton Rd St Kilda VIC 3182",
    "addr:housenumber":"45",
    "addr:postcode":"3182",
    "addr:street":"Brighton Rd",
    "iso:country":"AU",
    "sg:address":"45 Brighton Rd",
    "sg:city":"St Kilda",
    "sg:classifiers":[
        {
            "category":"Education",
            "subcategory":"Kindergarten",
            "type":"Public Place"
        }
    ],
    "sg:phone":"+61 3 9525 5151",
    "sg:postcode":"3182",
    "sg:province":"VIC",
    "sg:tags":[
        "pre-schools"
    ],
    "wof:name":"Tree House Child Care",
    "wof:placetype":"venue"
},
  "geometry": {"coordinates":[144.988372803,-37.8707199097],"type":"Point"}
}