{
  "type": "Feature",
  "properties": {
    "iso:country":"AU",
    "sg:address":"PO Box 1040",
    "sg:city":"Hampton North",
    "sg:classifiers":[
        {
            "category":"Building & Trades",
            "subcategory":"Construction",
            "type":"Services"
        }
    ],
    "sg:phone":"+61 3 9533 1188",
    "sg:postcode":"3188",
    "sg:province":"VIC",
    "sg:tags":[
        "contractor"
    ],
    "wof:name":"Fairley Constructions Pty Ltd",
    "wof:placetype":"venue"
},
  "geometry": {"coordinates":[144.998123169,-37.9300117493],"type":"Point"}
}