{
  "type": "Feature",
  "properties": {
    "addr:full":"Level 5, 146 Marsden St Parramatta NSW 2150",
    "addr:housenumber":"146",
    "addr:postcode":"2150",
    "addr:street":"Marsden St",
    "iso:country":"AU",
    "sg:address":"Level 5, 146 Marsden St",
    "sg:city":"Parramatta",
    "sg:classifiers":[
        {
            "category":"Professional",
            "subcategory":"Business Services",
            "type":"Services"
        }
    ],
    "sg:phone":"+61 2 8833 2000",
    "sg:postcode":"2150",
    "sg:province":"NSW",
    "sg:tags":[
        "small",
        "advisory"
    ],
    "wof:name":"Malouf Solicitors",
    "wof:placetype":"venue"
},
  "geometry": {"coordinates":[151.00173950199999,-33.8142662048],"type":"Point"}
}