{
  "type": "Feature",
  "properties": {
    "addr:full":"62 Belmore Rd Punchbowl NSW 2196",
    "addr:housenumber":"62",
    "addr:postcode":"2196",
    "addr:street":"Belmore Rd",
    "iso:country":"AU",
    "sg:address":"62 Belmore Rd",
    "sg:city":"Punchbowl",
    "sg:classifiers":[
        {
            "category":"School Buses",
            "type":"Transportation"
        }
    ],
    "sg:phone":"+61 2 9915 9100",
    "sg:postcode":"2196",
    "sg:province":"NSW",
    "sg:tags":[
        "brick"
    ],
    "wof:name":"Austral Bricks",
    "wof:placetype":"venue"
},
  "geometry": {"coordinates":[151.05577099999999,-33.93462],"type":"Point"}
}