{
  "type": "Feature",
  "properties": {
    "addr:full":"Level 7 815 Pacific Hwy Chatswood NSW 2067",
    "addr:housenumber":"815",
    "addr:postcode":"2067",
    "addr:street":"Pacific Hwy",
    "iso:country":"AU",
    "sg:address":"Level 7 815 Pacific Hwy",
    "sg:city":"Chatswood",
    "sg:classifiers":[
        {
            "category":"Professional",
            "subcategory":"Employment Agencies",
            "type":"Services"
        }
    ],
    "sg:phone":"+61 2 8448 0612",
    "sg:postcode":"2067",
    "sg:province":"NSW",
    "sg:tags":[
        "provider",
        "internet"
    ],
    "wof:name":"Tel Pacific",
    "wof:placetype":"venue"
},
  "geometry": {"coordinates":[151.17829895,-33.7957878113],"type":"Point"}
}