{
  "type": "Feature",
  "properties": {
    "addr:full":"323 Park St South Melbourne VIC 3205",
    "addr:housenumber":"323",
    "addr:postcode":"3205",
    "addr:street":"Park St",
    "iso:country":"AU",
    "sg:address":"323 Park St",
    "sg:city":"South Melbourne",
    "sg:classifiers":[
        {
            "category":"Education",
            "subcategory":"Music School",
            "type":"Public Place"
        }
    ],
    "sg:phone":"+61 3 9690 4141",
    "sg:postcode":"3205",
    "sg:province":"VIC",
    "sg:tags":[
        "teacher"
    ],
    "wof:name":"Ford Peter",
    "wof:placetype":"venue"
},
  "geometry": {"coordinates":[144.95549,-37.837124],"type":"Point"}
}