{
  "type": "Feature",
  "properties": {
    "addr:full":"Cnr Morayfield & Oakeyflat Rds Morayfield QLD 4506",
    "addr:postcode":"4506",
    "addr:street":"Cnr Morayfield & Oakeyflat Rds",
    "iso:country":"AU",
    "sg:address":"Cnr Morayfield & Oakeyflat Rds",
    "sg:city":"Morayfield",
    "sg:classifiers":[
        {
            "category":"Health Services",
            "subcategory":"Doctor",
            "type":"Services"
        }
    ],
    "sg:phone":"+61 7 5497 8888",
    "sg:postcode":"4506",
    "sg:province":"QLD",
    "sg:tags":[
        "medical",
        "practitioner"
    ],
    "wof:name":"Zeeman Sandra",
    "wof:placetype":"venue"
},
  "geometry": {"coordinates":[152.949417114,-27.1096820831],"type":"Point"}
}