{
  "type": "Feature",
  "properties": {
    "iso:country":"AU",
    "sg:address":"56 Holloway Drv",
    "sg:city":"Bayswater",
    "sg:classifiers":[
        {
            "category":"Wholesale",
            "subcategory":"Auto Parts",
            "type":"Manufacturing & Wholesale Goods"
        }
    ],
    "sg:phone":"+61 3 9762 7233",
    "sg:postcode":"3153",
    "sg:province":"VIC",
    "sg:tags":[
        "recyclers"
    ],
    "wof:name":"Kiarparts",
    "wof:placetype":"venue"
},
  "geometry": {"coordinates":[145.27992248499999,-37.8480987549],"type":"Point"}
}