{
  "type": "Feature",
  "properties": {
    "addr:full":"499 Formosa Rd Gumdale QLD 4154",
    "addr:housenumber":"499",
    "addr:postcode":"4154",
    "addr:street":"Formosa Rd",
    "iso:country":"AU",
    "sg:address":"499 Formosa Rd",
    "sg:city":"Gumdale",
    "sg:classifiers":[
        {
            "category":"Retail",
            "subcategory":"Auto Rental",
            "type":"Services"
        }
    ],
    "sg:phone":"+61 400 166 232",
    "sg:postcode":"4154",
    "sg:province":"QLD",
    "sg:tags":[
        "camper-trailers",
        "caravan",
        "hire"
    ],
    "wof:name":"Aussie Campworks Hire",
    "wof:placetype":"venue"
},
  "geometry": {"coordinates":[153.16200256400001,-27.4960651398],"type":"Point"}
}