{
  "type": "Feature",
  "properties": {
    "addr:full":"21 Robbie Drv Reynella East SA 5161",
    "addr:housenumber":"21",
    "addr:postcode":"5161",
    "addr:street":"Robbie Drv",
    "iso:country":"AU",
    "sg:address":"21 Robbie Drv",
    "sg:city":"Reynella East",
    "sg:classifiers":[
        {
            "category":"Professional",
            "subcategory":"Art Services",
            "type":"Services"
        }
    ],
    "sg:phone":"+61 8 8322 5244",
    "sg:postcode":"5161",
    "sg:province":"SA",
    "sg:tags":[
        "graphic",
        "designer"
    ],
    "wof:name":"Hamilton Steel",
    "wof:placetype":"venue"
},
  "geometry": {"coordinates":[138.55569457999999,-35.0852508545],"type":"Point"}
}