{
  "type": "Feature",
  "properties": {
    "addr:full":"420A Coramba Rd Coffs Harbour NSW 2450",
    "addr:housenumber":"420a",
    "addr:postcode":"2450",
    "addr:street":"Coramba Rd",
    "iso:country":"AU",
    "sg:address":"420A Coramba Rd",
    "sg:city":"Coffs Harbour",
    "sg:classifiers":[
        {
            "category":"Personal",
            "subcategory":"Massage",
            "type":"Services"
        }
    ],
    "sg:phone":"+61 2 6652 3368",
    "sg:postcode":"2450",
    "sg:province":"NSW",
    "sg:tags":[
        "therapy"
    ],
    "wof:name":"Academy of Rosemond Muscle Neurology, Therapy & Clinic",
    "wof:placetype":"venue"
},
  "geometry": {"coordinates":[153.082626,-30.28747],"type":"Point"}
}