{
  "type": "Feature",
  "properties": {
    "addr:full":"22 Craigie Ave Kanwal NSW 2259",
    "addr:housenumber":"22",
    "addr:postcode":"2259",
    "addr:street":"Craigie Ave Kanwal",
    "iso:country":"AU",
    "sg:address":"22 Craigie Ave",
    "sg:city":"Kanwal",
    "sg:classifiers":[
        {
            "category":"Health Services",
            "subcategory":"Health Practitioner",
            "type":"Services"
        }
    ],
    "sg:phone":"+61 2 4393 5046",
    "sg:postcode":"2259",
    "sg:province":"NSW",
    "sg:tags":[
        "naturopath"
    ],
    "wof:name":"Hielman Jane",
    "wof:placetype":"venue"
},
  "geometry": {"coordinates":[151.487426758,-33.2635498047],"type":"Point"}
}