{
  "type": "Feature",
  "properties": {
    "addr:full":"Unit 1/ 53- 57 Glen Osmond Rd Eastwood SA 5063",
    "addr:housenumber":"57",
    "addr:postcode":"5063",
    "addr:street":"Glen Osmond Rd",
    "iso:country":"AU",
    "sg:address":"Unit 1/ 53- 57 Glen Osmond Rd",
    "sg:city":"Eastwood",
    "sg:classifiers":[
        {
            "category":"Insurance",
            "subcategory":"Hazard Insurance",
            "type":"Services"
        }
    ],
    "sg:phone":"+61 8 8271 1166",
    "sg:postcode":"5063",
    "sg:province":"SA",
    "sg:tags":[
        "motor",
        "vehicle"
    ],
    "wof:name":"National Transport Insurance",
    "wof:placetype":"venue"
},
  "geometry": {"coordinates":[138.62039184599999,-34.9432601929],"type":"Point"}
}