{
  "type": "Feature",
  "properties": {
    "addr:full":"Jugiong St Boorowa NSW 2586",
    "addr:postcode":"2586",
    "addr:street":"Jugiong St",
    "iso:country":"AU",
    "sg:address":"Jugiong St",
    "sg:city":"Boorowa",
    "sg:classifiers":[
        {
            "category":"Health Services",
            "subcategory":"Doctor",
            "type":"Services"
        }
    ],
    "sg:phone":"+61 2 6385 3004",
    "sg:postcode":"2586",
    "sg:province":"NSW",
    "sg:tags":[
        "medical",
        "practitioner"
    ],
    "wof:name":"Boorowa Medical Centre",
    "wof:placetype":"venue"
},
  "geometry": {"coordinates":[148.72727966299999,-34.442035675],"type":"Point"}
}