{
  "type": "Feature",
  "properties": {
    "iso:country":"AU",
    "sg:address":"117 High St",
    "sg:city":"Kew",
    "sg:classifiers":[
        {
            "category":"Fast Food",
            "type":"Food & Drink"
        }
    ],
    "sg:phone":"+61 3 9853 0223",
    "sg:postcode":"3101",
    "sg:province":"VIC",
    "sg:tags":[
        "away",
        "take"
    ],
    "wof:name":"Bivio Pizza Bistro",
    "wof:placetype":"venue"
},
  "geometry": {"coordinates":[145.02934265100001,-37.8071861267],"type":"Point"}
}