{
  "type": "Feature",
  "properties": {
    "addr:full":"Gartrell St Roseworthy SA 5371",
    "addr:postcode":"5371",
    "addr:street":"Gartrell St",
    "iso:country":"AU",
    "sg:address":"Gartrell St",
    "sg:city":"Roseworthy",
    "sg:classifiers":[
        {
            "category":"Education",
            "subcategory":"School",
            "type":"Public Place"
        }
    ],
    "sg:phone":"+61 8 8524 8032",
    "sg:postcode":"5371",
    "sg:province":"SA",
    "sg:tags":[
        "state",
        "except",
        "nsw"
    ],
    "wof:name":"Roseworthy Primary School",
    "wof:placetype":"venue"
},
  "geometry": {"coordinates":[138.749557495,-34.5343399048],"type":"Point"}
}