{
  "type": "Feature",
  "properties": {
    "iso:country":"AU",
    "sg:address":"4 Dalmeny Ave",
    "sg:city":"Rosebery",
    "sg:classifiers":[
        {
            "category":"Retail",
            "subcategory":"Storage",
            "type":"Services"
        }
    ],
    "sg:phone":"+61 2 9662 7746",
    "sg:postcode":"2018",
    "sg:province":"NSW",
    "sg:tags":[
        "removal",
        "furniture"
    ],
    "wof:name":"A Kings Removals & Storage",
    "wof:placetype":"venue"
},
  "geometry": {"coordinates":[151.206832886,-33.9224281311],"type":"Point"}
}