{
  "type": "Feature",
  "properties": {
    "addr:full":"King Rd Mooloolah Valley QLD 4553",
    "addr:postcode":"4553",
    "addr:street":"King Rd",
    "iso:country":"AU",
    "sg:address":"King Rd",
    "sg:city":"Mooloolah Valley",
    "sg:classifiers":[
        {
            "category":"Education",
            "subcategory":"School",
            "type":"Public Place"
        }
    ],
    "sg:phone":"+61 7 5413 6333",
    "sg:postcode":"4553",
    "sg:province":"QLD",
    "sg:tags":[
        "state",
        "except",
        "nsw"
    ],
    "wof:name":"Mooloolah Primary School",
    "wof:placetype":"venue"
},
  "geometry": {"coordinates":[152.95907600000001,-26.765169],"type":"Point"}
}