{
  "type": "Feature",
  "properties": {
    "addr:full":"1 Wordell Crt Melton VIC 3337",
    "addr:housenumber":"1",
    "addr:postcode":"3337",
    "addr:street":"Wordell Crt",
    "iso:country":"AU",
    "sg:address":"1 Wordell Crt",
    "sg:city":"Melton",
    "sg:classifiers":[
        {
            "category":"Professional",
            "subcategory":"Computer Services",
            "type":"Services"
        }
    ],
    "sg:phone":"+61 411 154 805",
    "sg:postcode":"3337",
    "sg:province":"VIC",
    "sg:tags":[
        "repairs",
        "upgrade",
        "equipment"
    ],
    "wof:name":"Click Here 4 Help Computer Services",
    "wof:placetype":"venue"
},
  "geometry": {"coordinates":[144.58575400000001,-37.669643],"type":"Point"}
}