{
  "type": "Feature",
  "properties": {
    "addr:full":"2 Neutron Pl Rowville VIC 3178",
    "addr:housenumber":"2",
    "addr:postcode":"3178",
    "addr:street":"Neutron Pl",
    "iso:country":"AU",
    "sg:address":"2 Neutron Pl",
    "sg:city":"Rowville",
    "sg:classifiers":[
        {
            "category":"Manufacturing",
            "subcategory":"Tools & Machinery",
            "type":"Manufacturing & Wholesale Goods"
        }
    ],
    "sg:phone":"+61 3 9763 9002",
    "sg:postcode":"3178",
    "sg:province":"VIC",
    "sg:tags":[
        "toolmaker"
    ],
    "wof:name":"Formula Tooling",
    "wof:placetype":"venue"
},
  "geometry": {"coordinates":[145.24705505399999,-37.9059066772],"type":"Point"}
}