{
  "type": "Feature",
  "properties": {
    "iso:country":"AU",
    "sg:address":"17 Challenger Pl",
    "sg:city":"Melville",
    "sg:classifiers":[
        {
            "category":"Professional",
            "subcategory":"Accounting & Tax Preparation",
            "type":"Services"
        }
    ],
    "sg:phone":"+61 412 000 126",
    "sg:postcode":"6156",
    "sg:province":"WA",
    "sg:tags":[
        "bookkeeping"
    ],
    "wof:name":"Melville Bookkeeping & Secretarial Services",
    "wof:placetype":"venue"
},
  "geometry": {"coordinates":[115.801361,-32.044018],"type":"Point"}
}