{
  "type": "Feature",
  "properties": {
    "iso:country":"AU",
    "sg:address":"170 Wedel Rd",
    "sg:city":"Alton Downs",
    "sg:classifiers":[
        {
            "category":"Home & Garden",
            "subcategory":"Garden Supply",
            "type":"Retail Goods"
        }
    ],
    "sg:phone":"+61 7 4934 1154",
    "sg:postcode":"4702",
    "sg:province":"QLD",
    "sg:tags":[
        "equipment"
    ],
    "wof:name":"Des & Sue Dunne",
    "wof:placetype":"venue"
},
  "geometry": {"coordinates":[150.422973633,-23.2778949738],"type":"Point"}
}