{
  "type": "Feature",
  "properties": {
    "iso:country":"AU",
    "sg:address":"218 Whitehall St",
    "sg:city":"Yarraville",
    "sg:classifiers":[
        {
            "category":"Home & Garden",
            "subcategory":"Building Materials",
            "type":"Retail Goods"
        }
    ],
    "sg:phone":"+61 3 9687 8000",
    "sg:postcode":"3013",
    "sg:province":"VIC",
    "sg:tags":[
        "shutter",
        "roller",
        "grille"
    ],
    "wof:name":"Overhead Doors Australia",
    "wof:placetype":"venue"
},
  "geometry": {"coordinates":[144.89939880399999,-37.8152732849],"type":"Point"}
}