{
  "type": "Feature",
  "properties": {
    "iso:country":"AU",
    "sg:address":"Shop K 105 Fountain Gate Shopng Cntr Magid Drv",
    "sg:city":"Narre Warren",
    "sg:classifiers":[
        {
            "category":"Shopping",
            "subcategory":"Mobile Phones",
            "type":"Retail Goods"
        }
    ],
    "sg:phone":"+61 3 9704 5841",
    "sg:postcode":"3805",
    "sg:province":"VIC",
    "sg:tags":[
        "telephone",
        "accessory"
    ],
    "wof:name":"Austalk Business Centres Pty Ltd",
    "wof:placetype":"venue"
},
  "geometry": {"coordinates":[145.30139199999999,-38.016815],"type":"Point"}
}