{
  "type": "Feature",
  "properties": {
    "addr:full":"20a Anembo Rd Berowra NSW 2081",
    "addr:housenumber":"20a",
    "addr:postcode":"2081",
    "addr:street":"Anembo Rd",
    "iso:country":"AU",
    "sg:address":"20a Anembo Rd",
    "sg:city":"Berowra",
    "sg:classifiers":[
        {
            "category":"Home & Garden",
            "subcategory":"Building Materials",
            "type":"Retail Goods"
        }
    ],
    "sg:phone":"+61 2 9456 3951",
    "sg:postcode":"2081",
    "sg:province":"NSW",
    "sg:tags":[
        "restoration",
        "supply"
    ],
    "wof:name":"SGF Tuckpointing",
    "wof:placetype":"venue"
},
  "geometry": {"coordinates":[151.145187378,-33.6291885376],"type":"Point"}
}