{
  "type": "Feature",
  "properties": {
    "iso:country":"AU",
    "sg:address":"10 Kendall St",
    "sg:city":"Charlestown",
    "sg:classifiers":[
        {
            "category":"Building & Trades",
            "subcategory":"Construction",
            "type":"Services"
        }
    ],
    "sg:phone":"+61 2 4942 5471",
    "sg:postcode":"2290",
    "sg:province":"NSW",
    "sg:tags":[
        "home",
        "air conditioning"
    ],
    "wof:name":"England Darren Air Cond.",
    "wof:placetype":"venue"
},
  "geometry": {"coordinates":[151.687255859,-32.9592323303],"type":"Point"}
}