{
  "type": "Feature",
  "properties": {
    "iso:country":"AU",
    "sg:address":"4 Bedford St",
    "sg:city":"North Perth",
    "sg:classifiers":[
        {
            "category":"Professional",
            "subcategory":"Art Services",
            "type":"Services"
        }
    ],
    "sg:phone":"+61 8 9201 9980",
    "sg:postcode":"6006",
    "sg:province":"WA",
    "sg:tags":[
        "artist"
    ],
    "wof:name":"Brendon Darby",
    "wof:placetype":"venue"
},
  "geometry": {"coordinates":[115.851287842,-31.9184188843],"type":"Point"}
}