{
  "type": "Feature",
  "properties": {
    "addr:full":"Main North Rd Auburn SA 5451",
    "addr:postcode":"5451",
    "addr:street":"Main North Rd",
    "iso:country":"AU",
    "sg:address":"Main North Rd",
    "sg:city":"Auburn",
    "sg:classifiers":[
        {
            "category":"Restaurant",
            "type":"Food & Drink"
        }
    ],
    "sg:phone":"+61 8 8849 2130",
    "sg:postcode":"5451",
    "sg:province":"SA",
    "sg:tags":[
        "roadhouse"
    ],
    "wof:name":"Auburn Roadhouse",
    "wof:placetype":"venue"
},
  "geometry": {"coordinates":[138.685654,-34.026669],"type":"Point"}
}