{
  "type": "Feature",
  "properties": {
    "addr:full":"14 Peppercorn St Sunnybank Hills QLD 4109",
    "addr:housenumber":"14",
    "addr:postcode":"4109",
    "addr:street":"Peppercorn St",
    "iso:country":"AU",
    "sg:address":"14 Peppercorn St",
    "sg:city":"Sunnybank Hills",
    "sg:classifiers":[
        {
            "category":"Building & Trades",
            "subcategory":"Pest Control",
            "type":"Services"
        }
    ],
    "sg:phone":"+61 7 3222 7190",
    "sg:postcode":"4109",
    "sg:province":"QLD",
    "wof:name":"Pest Terminator",
    "wof:placetype":"venue"
},
  "geometry": {"coordinates":[153.05973815900001,-27.6012592316],"type":"Point"}
}