{
  "type": "Feature",
  "properties": {
    "iso:country":"AU",
    "sg:address":"136 Byrne St",
    "sg:city":"Fitzroy North",
    "sg:classifiers":[
        {
            "category":"Professional",
            "subcategory":"Computer Services",
            "type":"Services"
        }
    ],
    "sg:phone":"+61 3 9489 4033",
    "sg:postcode":"3068",
    "sg:province":"VIC",
    "sg:tags":[
        "package",
        "software"
    ],
    "wof:name":"Australian Systems Engineering Pty Ltd",
    "wof:placetype":"venue"
},
  "geometry": {"coordinates":[144.98535156200001,-37.7804603577],"type":"Point"}
}