{
  "type": "Feature",
  "properties": {
    "iso:country":"AU",
    "sg:address":"332 Hanson Rd",
    "sg:city":"Wingfield",
    "sg:classifiers":[
        {
            "category":"Manufacturing",
            "subcategory":"Glass & Minerals",
            "type":"Manufacturing & Wholesale Goods"
        }
    ],
    "sg:phone":"+61 428 112 559",
    "sg:postcode":"5013",
    "sg:province":"SA",
    "sg:tags":[
        "fabricator",
        "foam",
        "processor"
    ],
    "wof:name":"Gunspray",
    "wof:placetype":"venue"
},
  "geometry": {"coordinates":[138.54656982399999,-34.8451576233],"type":"Point"}
}