{
  "type": "Feature",
  "properties": {
    "iso:country":"AU",
    "sg:address":"97b Main St",
    "sg:city":"Woodside",
    "sg:classifiers":[
        {
            "category":"Shopping",
            "subcategory":"Crafts & Fabrics",
            "type":"Retail Goods"
        }
    ],
    "sg:phone":"+61 8 8389 9200",
    "sg:postcode":"5244",
    "sg:province":"SA",
    "sg:tags":[
        "quilting"
    ],
    "wof:name":"Patchwork Apple The",
    "wof:placetype":"venue"
},
  "geometry": {"coordinates":[138.87458801299999,-34.9038276672],"type":"Point"}
}