{
  "type": "Feature",
  "properties": {
    "iso:country":"AU",
    "sg:address":"Shp7",
    "sg:city":"/ 7 Harrington Sq Altona",
    "sg:classifiers":[
        {
            "category":"Food & Beverages",
            "subcategory":"Fruits & Vegetables",
            "type":"Retail Goods"
        }
    ],
    "sg:phone":"+61 3 9315 9991",
    "sg:postcode":"3018",
    "sg:province":"VIC",
    "sg:tags":[
        "greengrocer",
        "fruiterer"
    ],
    "wof:name":"Kusums Spice House",
    "wof:placetype":"venue"
},
  "geometry": {"coordinates":[144.81364440900001,-37.8645477295],"type":"Point"}
}