{
  "type": "Feature",
  "properties": {
    "iso:country":"AU",
    "sg:address":"PO Box 178",
    "sg:city":"Daw Park",
    "sg:classifiers":[
        {
            "category":"Retail",
            "subcategory":"Laundry & Dry Cleaning",
            "type":"Services"
        }
    ],
    "sg:phone":"+61 417 866 774",
    "sg:postcode":"5041",
    "sg:province":"SA",
    "sg:tags":[
        "truck",
        "tip",
        "contractor"
    ],
    "wof:name":"Greg Lee Haulage Pty Ltd",
    "wof:placetype":"venue"
},
  "geometry": {"coordinates":[138.590302,-34.981354],"type":"Point"}
}