{
  "type": "Feature",
  "properties": {
    "addr:full":"PO Box 10004 Adelaide SA 5001",
    "addr:postcode":"5001",
    "iso:country":"AU",
    "sg:address":"PO Box 10004",
    "sg:city":"Adelaide",
    "sg:classifiers":[
        {
            "category":"Building & Trades",
            "subcategory":"Construction",
            "type":"Services"
        }
    ],
    "sg:phone":"+61 417 366 537",
    "sg:postcode":"5001",
    "sg:province":"SA",
    "sg:tags":[
        "management"
    ],
    "wof:name":"Blueprint Infrastructure Services",
    "wof:placetype":"venue"
},
  "geometry": {"coordinates":[138.599731445,-34.9257698059],"type":"Point"}
}