{
  "type": "Feature",
  "properties": {
    "addr:full":"Depot Gosport St Moree NSW 2400",
    "addr:postcode":"2400",
    "addr:street":"Gosport St",
    "iso:country":"AU",
    "sg:address":"Depot Gosport St",
    "sg:city":"Moree",
    "sg:classifiers":[
        {
            "category":"Utilities",
            "subcategory":"Fuel Oil & Lpg",
            "type":"Services"
        }
    ],
    "sg:phone":"+61 2 6752 7366",
    "sg:postcode":"2400",
    "sg:province":"NSW",
    "sg:tags":[
        "merchant"
    ],
    "wof:name":"Lowes Petroleum Service Pty Ltd",
    "wof:placetype":"venue"
},
  "geometry": {"coordinates":[149.84724426299999,-29.4700393677],"type":"Point"}
}