{
  "type": "Feature",
  "properties": {
    "addr:full":"PO Box 629 Main Beach QLD 4217",
    "addr:postcode":"4217",
    "iso:country":"AU",
    "sg:address":"PO Box 629",
    "sg:city":"Main Beach",
    "sg:classifiers":[
        {
            "category":"Government",
            "subcategory":"Customs House",
            "type":"Public Place"
        }
    ],
    "sg:phone":"+61 7 5531 2299",
    "sg:postcode":"4217",
    "sg:province":"QLD",
    "sg:tags":[
        "title",
        "management",
        "stratum"
    ],
    "wof:name":"Project King Pty Ltd",
    "wof:placetype":"venue"
},
  "geometry": {"coordinates":[153.429153442,-27.982339859],"type":"Point"}
}