{
  "type": "Feature",
  "properties": {
    "iso:country":"AU",
    "sg:address":"48 Nanworen Crs",
    "sg:city":"Bell Park",
    "sg:classifiers":[
        {
            "category":"Building & Trades",
            "subcategory":"Construction",
            "type":"Services"
        }
    ],
    "sg:phone":"+61 418 522 334",
    "sg:postcode":"3215",
    "sg:province":"VIC",
    "sg:tags":[
        "contractor"
    ],
    "wof:name":"Universal Developments",
    "wof:placetype":"venue"
},
  "geometry": {"coordinates":[144.336105347,-38.1099395752],"type":"Point"}
}