{
  "type": "Feature",
  "properties": {
    "addr:full":"35 Mary St Noosaville QLD 4566",
    "addr:housenumber":"35",
    "addr:postcode":"4566",
    "addr:street":"Mary St",
    "iso:country":"AU",
    "sg:address":"35 Mary St",
    "sg:city":"Noosaville",
    "sg:classifiers":[
        {
            "category":"Health Services",
            "subcategory":"Doctor",
            "type":"Services"
        }
    ],
    "sg:phone":"+61 7 5455 6788",
    "sg:postcode":"4566",
    "sg:province":"QLD",
    "sg:tags":[
        "medical",
        "practitioner"
    ],
    "wof:name":"Richardson Karen",
    "wof:placetype":"venue"
},
  "geometry": {"coordinates":[153.06542968799999,-26.400390625],"type":"Point"}
}