{
  "type": "Feature",
  "properties": {
    "addr:full":"66 Hampden Rd Artarmon NSW 2064",
    "addr:housenumber":"66",
    "addr:postcode":"2064",
    "addr:street":"Hampden Rd",
    "iso:country":"AU",
    "sg:address":"66 Hampden Rd",
    "sg:city":"Artarmon",
    "sg:classifiers":[
        {
            "category":"Shopping",
            "subcategory":"Shoes",
            "type":"Retail Goods"
        }
    ],
    "sg:phone":"+61 2 9411 1198",
    "sg:postcode":"2064",
    "sg:province":"NSW",
    "sg:tags":[
        "footwear"
    ],
    "wof:name":"Comfort & Fit",
    "wof:placetype":"venue"
},
  "geometry": {"coordinates":[151.185089111,-33.8092803955],"type":"Point"}
}