{
  "type": "Feature",
  "properties": {
    "addr:full":"Shop 5 348 Unley Rd Unley Park SA 5061",
    "addr:housenumber":"shop 5",
    "addr:postcode":"348;5061",
    "addr:street":"Unley Rd",
    "iso:country":"AU",
    "sg:address":"Shop 5 348 Unley Rd",
    "sg:city":"Unley Park",
    "sg:classifiers":[
        {
            "category":"Health Services",
            "subcategory":"Chiropractor",
            "type":"Services"
        }
    ],
    "sg:phone":"+61 8 8272 5322",
    "sg:postcode":"5061",
    "sg:province":"SA",
    "wof:name":"Hyde Park Chiropractic Centre",
    "wof:placetype":"venue"
},
  "geometry": {"coordinates":[138.60810852,-34.9599685669],"type":"Point"}
}