{
  "type": "Feature",
  "properties": {
    "addr:full":"153 Hobart Rd Kings Meadows TAS 7249",
    "addr:housenumber":"153",
    "addr:postcode":"7249",
    "addr:street":"Hobart Rd",
    "iso:country":"AU",
    "sg:address":"153 Hobart Rd",
    "sg:city":"Kings Meadows",
    "sg:classifiers":[
        {
            "category":"Professional",
            "subcategory":"Accounting & Tax Preparation",
            "type":"Services"
        }
    ],
    "sg:phone":"+61 3 6344 9433",
    "sg:postcode":"7249",
    "sg:province":"TAS",
    "sg:tags":[
        "accountant",
        "auditor"
    ],
    "wof:name":"Peebles Michelle",
    "wof:placetype":"venue"
},
  "geometry": {"coordinates":[147.161010742,-41.468334198],"type":"Point"}
}