{
  "type": "Feature",
  "properties": {
    "addr:full":"242 Macquarie St Dubbo NSW 2830",
    "addr:housenumber":"242",
    "addr:postcode":"2830",
    "addr:street":"Macquarie St",
    "iso:country":"AU",
    "sg:address":"242 Macquarie St",
    "sg:city":"Dubbo",
    "sg:classifiers":[
        {
            "category":"Shopping",
            "subcategory":"Pawn Shop",
            "type":"Retail Goods"
        }
    ],
    "sg:phone":"+61 2 6884 0133",
    "sg:postcode":"2830",
    "sg:province":"NSW",
    "sg:tags":[
        "pawnbroker"
    ],
    "wof:name":"Country Cash & Trade",
    "wof:placetype":"venue"
},
  "geometry": {"coordinates":[148.60104370100001,-32.2478218079],"type":"Point"}
}