{
  "type": "Feature",
  "properties": {
    "iso:country":"AU",
    "sg:address":"162 Brisbane St",
    "sg:city":"Beaudesert",
    "sg:classifiers":[
        {
            "category":"Utilities",
            "subcategory":"Fuel Oil & Lpg",
            "type":"Services"
        }
    ],
    "sg:phone":"+61 7 5541 2266",
    "sg:postcode":"4285",
    "sg:province":"QLD",
    "sg:tags":[
        "merchant"
    ],
    "wof:name":"Ampol Distributors",
    "wof:placetype":"venue"
},
  "geometry": {"coordinates":[152.994247,-27.975773],"type":"Point"}
}