{
  "type": "Feature",
  "properties": {
    "addr:full":"Shp 19/ 236 Bourke St Melbourne VIC 3000",
    "addr:housenumber":"19 / 236",
    "addr:postcode":"3000",
    "addr:street":"Bourke St",
    "iso:country":"AU",
    "sg:address":"Shp 19/ 236 Bourke St",
    "sg:city":"Melbourne",
    "sg:classifiers":[
        {
            "category":"Building & Trades",
            "subcategory":"Locksmith",
            "type":"Services"
        }
    ],
    "sg:phone":"+61 3 9639 4417",
    "sg:postcode":"3000",
    "sg:province":"VIC",
    "sg:tags":[
        "lock"
    ],
    "wof:name":"Mister Minit",
    "wof:placetype":"venue"
},
  "geometry": {"coordinates":[144.966064453,-37.8132553101],"type":"Point"}
}