{
  "type": "Feature",
  "properties": {
    "addr:full":"59 Cochranes Rd Moorabbin VIC 3189",
    "addr:housenumber":"59",
    "addr:postcode":"3189",
    "addr:street":"Cochranes Rd",
    "iso:country":"AU",
    "sg:address":"59 Cochranes Rd",
    "sg:city":"Moorabbin",
    "sg:classifiers":[
        {
            "category":"Autos & Motor Vehicles",
            "subcategory":"Fuel & Gas Station",
            "type":"Retail Goods"
        }
    ],
    "sg:phone":"+61 3 9553 3164",
    "sg:postcode":"3189",
    "sg:province":"VIC",
    "wof:name":"L G Petroleum",
    "wof:placetype":"venue"
},
  "geometry": {"coordinates":[145.06866455100001,-37.9428672791],"type":"Point"}
}