{
  "type": "Feature",
  "properties": {
    "addr:full":"Shop2/2- 16 Glenmore Rd Paddington NSW 2021",
    "addr:housenumber":"16",
    "addr:postcode":"2021",
    "addr:street":"Glenmore Rd",
    "iso:country":"AU",
    "sg:address":"Shop2/2- 16 Glenmore Rd",
    "sg:city":"Paddington",
    "sg:classifiers":[
        {
            "category":"Shopping",
            "subcategory":"Clothing, Apparel, & Fashions",
            "type":"Retail Goods"
        }
    ],
    "sg:phone":"+61 2 9357 4700",
    "sg:postcode":"2021",
    "sg:province":"NSW",
    "sg:tags":[
        "lady",
        "wear"
    ],
    "wof:name":"Zimmermann Wear Pty Ltd",
    "wof:placetype":"venue"
},
  "geometry": {"coordinates":[151.23042297399999,-33.8872871399],"type":"Point"}
}