{
  "type": "Feature",
  "properties": {
    "addr:full":"1 Aspinall St Watson ACT 2602",
    "addr:housenumber":"1",
    "addr:postcode":"2602",
    "addr:street":"Aspinall St",
    "iso:country":"AU",
    "sg:address":"1 Aspinall St",
    "sg:city":"Watson",
    "sg:classifiers":[
        {
            "category":"Manufacturing",
            "subcategory":"Pottery",
            "type":"Manufacturing & Wholesale Goods"
        }
    ],
    "sg:phone":"+61 2 6241 7800",
    "sg:postcode":"2602",
    "sg:province":"ACT",
    "wof:name":"Canberra Potters' Society Inc",
    "wof:placetype":"venue"
},
  "geometry": {"coordinates":[149.154663086,-35.2312736511],"type":"Point"}
}