{
  "type": "Feature",
  "properties": {
    "addr:full":"130 Spence St Cairns QLD 4870",
    "addr:housenumber":"130",
    "addr:postcode":"4870",
    "addr:street":"Spence St",
    "iso:country":"AU",
    "sg:address":"130 Spence St",
    "sg:city":"Cairns",
    "sg:classifiers":[
        {
            "category":"Home & Garden",
            "subcategory":"Home Furnishings",
            "type":"Retail Goods"
        }
    ],
    "sg:phone":"+61 7 4041 1410",
    "sg:postcode":"4870",
    "sg:province":"QLD",
    "sg:tags":[
        "shower",
        "screen"
    ],
    "wof:name":"Only Bathrooms",
    "wof:placetype":"venue"
},
  "geometry": {"coordinates":[145.75422668499999,-16.9414825439],"type":"Point"}
}