{
  "type": "Feature",
  "properties": {
    "iso:country":"AU",
    "sg:address":"390 Ballarat Rd",
    "sg:city":"Sunshine",
    "sg:classifiers":[
        {
            "category":"Autos & Motor Vehicles",
            "subcategory":"Fuel & Gas Station",
            "type":"Retail Goods"
        }
    ],
    "sg:phone":"+61 3 9311 2663",
    "sg:postcode":"3020",
    "sg:province":"VIC",
    "wof:name":"Shell Western Sun Self Serve",
    "wof:placetype":"venue"
},
  "geometry": {"coordinates":[144.84385700000001,-37.778412],"type":"Point"}
}