{
  "type": "Feature",
  "properties": {
    "addr:full":"Avoca Drv Green Point NSW 2251",
    "addr:postcode":"2251",
    "addr:street":"Avoca Drv",
    "iso:country":"AU",
    "sg:address":"Avoca Drv",
    "sg:city":"Green Point",
    "sg:classifiers":[
        {
            "category":"Professional",
            "subcategory":"Art Services",
            "type":"Services"
        }
    ],
    "sg:phone":"+61 2 4361 9008",
    "sg:postcode":"2251",
    "sg:province":"NSW",
    "sg:tags":[
        "interior",
        "decorator"
    ],
    "wof:name":"La Melia Rose",
    "wof:placetype":"venue"
},
  "geometry": {"coordinates":[151.37176513700001,-33.4466896057],"type":"Point"}
}