{
  "type": "Feature",
  "properties": {
    "addr:full":"85 Wyee Rd Wyee NSW 2259",
    "addr:housenumber":"85",
    "addr:postcode":"2259",
    "addr:street":"Wyee Rd",
    "iso:country":"AU",
    "sg:address":"85 Wyee Rd",
    "sg:city":"Wyee",
    "sg:classifiers":[
        {
            "category":"Travel",
            "subcategory":"Hostel",
            "type":"Entertainment"
        }
    ],
    "sg:phone":"+61 2 4357 1276",
    "sg:postcode":"2259",
    "sg:province":"NSW",
    "sg:tags":[
        "home"
    ],
    "wof:name":"Bethshan Ministries Ltd",
    "wof:placetype":"venue"
},
  "geometry": {"coordinates":[151.49140930199999,-33.1851501465],"type":"Point"}
}