{
  "type": "Feature",
  "properties": {
    "addr:full":"McCormicks Rd Fosterville VIC 3557",
    "addr:postcode":"3557",
    "addr:street":"Mccormicks Rd",
    "iso:country":"AU",
    "sg:address":"McCormicks Rd",
    "sg:city":"Fosterville",
    "sg:classifiers":[
        {
            "category":"Building & Trades",
            "subcategory":"Construction",
            "type":"Services"
        }
    ],
    "sg:phone":"+61 3 5439 7532",
    "sg:postcode":"3557",
    "sg:province":"VIC",
    "sg:tags":[
        "earth",
        "excavating",
        "moving",
        "contractor"
    ],
    "wof:name":"Hoare Bros Pty Ltd",
    "wof:placetype":"venue"
},
  "geometry": {"coordinates":[144.497680664,-36.6980705261],"type":"Point"}
}