{
  "type": "Feature",
  "properties": {
    "iso:country":"AU",
    "sg:address":"12 Bibby Crt",
    "sg:city":"Moorabbin",
    "sg:classifiers":[
        {
            "category":"Wholesale",
            "subcategory":"Painting Supplies",
            "type":"Manufacturing & Wholesale Goods"
        }
    ],
    "sg:phone":"+61 3 9553 1044",
    "sg:postcode":"3189",
    "sg:province":"VIC",
    "sg:tags":[
        "wholesaler",
        "paint",
        "mfrs"
    ],
    "wof:name":"Protec Pty Ltd",
    "wof:placetype":"venue"
},
  "geometry": {"coordinates":[145.0675354,-37.9430618286],"type":"Point"}
}