{
  "type": "Feature",
  "properties": {
    "addr:full":"20 Gloucester St Glenroy VIC 3046",
    "addr:housenumber":"20",
    "addr:postcode":"3046",
    "addr:street":"Gloucester St",
    "iso:country":"AU",
    "sg:address":"20 Gloucester St",
    "sg:city":"Glenroy",
    "sg:classifiers":[
        {
            "category":"Personal",
            "subcategory":"Massage",
            "type":"Services"
        }
    ],
    "sg:phone":"+61 418 367 065",
    "sg:postcode":"3046",
    "sg:province":"VIC",
    "sg:tags":[
        "therapy"
    ],
    "wof:name":"Robert White Mobile Massage Therapy",
    "wof:placetype":"venue"
},
  "geometry": {"coordinates":[144.947357178,-37.7141265869],"type":"Point"}
}