{
  "type": "Feature",
  "properties": {
    "addr:full":"5 Distribution Ave Ashmore QLD 4214",
    "addr:housenumber":"5",
    "addr:postcode":"4214",
    "addr:street":"Distribution Ave",
    "iso:country":"AU",
    "sg:address":"5 Distribution Ave",
    "sg:city":"Ashmore",
    "sg:classifiers":[
        {
            "category":"Food & Beverages",
            "subcategory":"Specialty",
            "type":"Retail Goods"
        }
    ],
    "sg:phone":"+61 7 5564 9499",
    "sg:postcode":"4214",
    "sg:province":"QLD",
    "sg:tags":[
        "product",
        "health"
    ],
    "wof:name":"thexton.com.au",
    "wof:placetype":"venue"
},
  "geometry": {"coordinates":[153.35853576700001,-27.9768123627],"type":"Point"}
}