{
  "type": "Feature",
  "properties": {
    "addr:full":"50 Victoria Rd Pennant Hills NSW 2120",
    "addr:housenumber":"50",
    "addr:postcode":"2120",
    "addr:street":"Victoria Rd",
    "iso:country":"AU",
    "sg:address":"50 Victoria Rd",
    "sg:city":"Pennant Hills",
    "sg:classifiers":[
        {
            "category":"Building & Trades",
            "subcategory":"Landscaping Services",
            "type":"Services"
        }
    ],
    "sg:phone":"+61 2 9875 5120",
    "sg:postcode":"2120",
    "sg:province":"NSW",
    "sg:tags":[
        "designer",
        "landscape",
        "contractor"
    ],
    "wof:name":"Cabbage Tree Landscape",
    "wof:placetype":"venue"
},
  "geometry": {"coordinates":[151.0574646,-33.7381858826],"type":"Point"}
}