{
  "type": "Feature",
  "properties": {
    "iso:country":"AU",
    "sg:address":"8 Goldsmith Rd",
    "sg:city":"Somersby",
    "sg:classifiers":[
        {
            "category":"Professional",
            "subcategory":"Employment Agencies",
            "type":"Services"
        }
    ],
    "sg:phone":"+61 427 272 439",
    "sg:postcode":"2250",
    "sg:province":"NSW",
    "sg:tags":[
        "hire",
        "labour",
        "contractor"
    ],
    "wof:name":"Specialised Labor Hire",
    "wof:placetype":"venue"
},
  "geometry": {"coordinates":[151.304031372,-33.3932800293],"type":"Point"}
}