{
  "type": "Feature",
  "properties": {
    "iso:country":"AU",
    "sg:address":"Wangara Rd",
    "sg:city":"Cheltenham",
    "sg:classifiers":[
        {
            "category":"Arena",
            "subcategory":"Sports Club",
            "type":"Entertainment"
        }
    ],
    "sg:phone":"+61 3 9583 9290",
    "sg:postcode":"3192",
    "sg:province":"VIC",
    "sg:tags":[
        "organisation",
        "sporting"
    ],
    "wof:name":"Australian Institute Of Sport - Golf Program",
    "wof:placetype":"venue"
},
  "geometry": {"coordinates":[145.03501892099999,-37.9582901001],"type":"Point"}
}