{
  "type": "Feature",
  "properties": {
    "iso:country":"AU",
    "sg:address":"Shop 3 68",
    "sg:city":"Jessica Blv Minyama",
    "sg:classifiers":[
        {
            "category":"Personal",
            "subcategory":"Beauty Salon",
            "type":"Services"
        }
    ],
    "sg:phone":"+61 7 5477 6145",
    "sg:postcode":"4575",
    "sg:province":"QLD",
    "sg:tags":[
        "hairdresser"
    ],
    "wof:name":"Luv The Doo!",
    "wof:placetype":"venue"
},
  "geometry": {"coordinates":[153.124054,-26.698994],"type":"Point"}
}