{
  "type": "Feature",
  "properties": {
    "addr:full":"73 Thomas St Parramatta NSW 2150",
    "addr:housenumber":"73",
    "addr:postcode":"2150",
    "addr:street":"Thomas St",
    "iso:country":"AU",
    "sg:address":"73 Thomas St",
    "sg:city":"Parramatta",
    "sg:classifiers":[
        {
            "category":"Building & Trades",
            "subcategory":"Construction",
            "type":"Services"
        }
    ],
    "sg:phone":"+61 418 287 434",
    "sg:postcode":"2150",
    "sg:province":"NSW",
    "sg:tags":[
        "contractor"
    ],
    "wof:name":"Elias RL Pty Ltd",
    "wof:placetype":"venue"
},
  "geometry": {"coordinates":[150.991363525,-33.8273200989],"type":"Point"}
}