{
  "type": "Feature",
  "properties": {
    "addr:full":"330 Warwick Rd Yamanto QLD 4305",
    "addr:housenumber":"330",
    "addr:postcode":"4305",
    "addr:street":"Warwick Rd",
    "iso:country":"AU",
    "sg:address":"330 Warwick Rd",
    "sg:city":"Yamanto",
    "sg:classifiers":[
        {
            "category":"Home & Garden",
            "subcategory":"Building Materials",
            "type":"Retail Goods"
        }
    ],
    "sg:phone":"+61 1300 783 358",
    "sg:postcode":"4305",
    "sg:province":"QLD",
    "sg:tags":[
        "fencing"
    ],
    "wof:name":"Hans Steel Supplies",
    "wof:placetype":"venue"
},
  "geometry": {"coordinates":[152.75042724599999,-27.6488838196],"type":"Point"}
}