{
  "type": "Feature",
  "properties": {
    "addr:full":"139 Marshall St Goondiwindi QLD 4390",
    "addr:housenumber":"139",
    "addr:postcode":"4390",
    "addr:street":"Marshall St",
    "iso:country":"AU",
    "sg:address":"139 Marshall St",
    "sg:city":"Goondiwindi",
    "sg:classifiers":[
        {
            "category":"Manufacturing",
            "subcategory":"Textiles",
            "type":"Manufacturing & Wholesale Goods"
        }
    ],
    "sg:phone":"+61 7 4671 2800",
    "sg:postcode":"4390",
    "sg:province":"QLD",
    "sg:tags":[
        "cotton"
    ],
    "wof:name":"Namoi Cotton Co-Operative Ltd",
    "wof:placetype":"venue"
},
  "geometry": {"coordinates":[150.30975341800001,-28.5471878052],"type":"Point"}
}