{
  "type": "Feature",
  "properties": {
    "addr:full":"73 Kitchener St Tugun QLD 4224",
    "addr:housenumber":"73",
    "addr:postcode":"4224",
    "addr:street":"Kitchener St",
    "iso:country":"AU",
    "sg:address":"73 Kitchener St",
    "sg:city":"Tugun",
    "sg:classifiers":[
        {
            "category":"Building & Trades",
            "subcategory":"Construction",
            "type":"Services"
        }
    ],
    "sg:phone":"+61 7 5534 6250",
    "sg:postcode":"4224",
    "sg:province":"QLD",
    "sg:tags":[
        "renovation",
        "alterations",
        "extension",
        "contractor"
    ],
    "wof:name":"Builder Artu's Constructions",
    "wof:placetype":"venue"
},
  "geometry": {"coordinates":[153.491729736,-28.1507015228],"type":"Point"}
}