{
  "type": "Feature",
  "properties": {
    "iso:country":"AU",
    "sg:address":"127-133 Burwood Rd",
    "sg:city":"Burwood",
    "sg:classifiers":[
        {
            "category":"Shopping",
            "subcategory":"Clothing, Apparel, & Fashions",
            "type":"Retail Goods"
        }
    ],
    "sg:phone":"+61 2 9744 1123",
    "sg:postcode":"2134",
    "sg:province":"NSW",
    "sg:tags":[
        "hire",
        "men's",
        "wear",
        "formal"
    ],
    "wof:name":"Burwood Formal Hire",
    "wof:placetype":"venue"
},
  "geometry": {"coordinates":[151.103713989,-33.8764686584],"type":"Point"}
}