{
  "type": "Feature",
  "properties": {
    "addr:full":"6 East Boundary Rd Bentleigh East VIC 3165",
    "addr:housenumber":"6",
    "addr:postcode":"3165",
    "addr:street":"East Boundary Rd",
    "iso:country":"AU",
    "sg:address":"6 East Boundary Rd",
    "sg:city":"Bentleigh East",
    "sg:classifiers":[
        {
            "category":"Utilities",
            "subcategory":"Electric",
            "type":"Services"
        }
    ],
    "sg:phone":"+61 3 9579 3306",
    "sg:postcode":"3165",
    "sg:province":"VIC",
    "sg:tags":[
        "electrical",
        "contractor"
    ],
    "wof:name":"Scopel S M & E",
    "wof:placetype":"venue"
},
  "geometry": {"coordinates":[145.05657959000001,-37.9349975586],"type":"Point"}
}