{
  "type": "Feature",
  "properties": {
    "addr:full":"35 Great Western Hwy Springwood NSW 2777",
    "addr:housenumber":"35",
    "addr:postcode":"2777",
    "addr:street":"Great Western Hwy",
    "iso:country":"AU",
    "sg:address":"35 Great Western Hwy",
    "sg:city":"Springwood",
    "sg:classifiers":[
        {
            "category":"Professional",
            "subcategory":"Employment Agencies",
            "type":"Services"
        }
    ],
    "sg:phone":"+61 2 4751 6126",
    "sg:postcode":"2777",
    "sg:province":"NSW",
    "sg:tags":[
        "provider",
        "internet"
    ],
    "wof:name":"Eye Cue Communications",
    "wof:placetype":"venue"
},
  "geometry": {"coordinates":[150.581787109,-33.7023544312],"type":"Point"}
}