{
  "type": "Feature",
  "properties": {
    "addr:full":"165 Cameron St Ayr QLD 4807",
    "addr:housenumber":"165",
    "addr:postcode":"4807",
    "addr:street":"Cameron St",
    "iso:country":"AU",
    "sg:address":"165 Cameron St",
    "sg:city":"Ayr",
    "sg:classifiers":[
        {
            "category":"Organizations",
            "subcategory":"Community Association",
            "type":"Services"
        }
    ],
    "sg:phone":"+61 7 4783 5946",
    "sg:postcode":"4807",
    "sg:province":"QLD",
    "sg:tags":[
        "organisation",
        "family",
        "welfare"
    ],
    "wof:name":"Alcoholics Anonymous",
    "wof:placetype":"venue"
},
  "geometry": {"coordinates":[147.395950317,-19.5790500641],"type":"Point"}
}