{
  "type": "Feature",
  "properties": {
    "addr:full":"164 Ferry St Maryborough QLD 4650",
    "addr:housenumber":"164",
    "addr:postcode":"4650",
    "addr:street":"Ferry St",
    "iso:country":"AU",
    "sg:address":"164 Ferry St",
    "sg:city":"Maryborough",
    "sg:classifiers":[
        {
            "category":"Manufacturing",
            "subcategory":"Furniture",
            "type":"Manufacturing & Wholesale Goods"
        }
    ],
    "sg:phone":"+61 7 4122 1499",
    "sg:postcode":"4650",
    "sg:province":"QLD",
    "sg:tags":[
        "builder",
        "designer",
        "custom"
    ],
    "wof:name":"Pitt & Co Cabinets",
    "wof:placetype":"venue"
},
  "geometry": {"coordinates":[152.69961499999999,-25.530762],"type":"Point"}
}