{
  "type": "Feature",
  "properties": {
    "addr:full":"74 Bayfield Rd Bayswater VIC 3153",
    "addr:housenumber":"74",
    "addr:postcode":"3153",
    "addr:street":"Bayfield Rd",
    "iso:country":"AU",
    "sg:address":"74 Bayfield Rd",
    "sg:city":"Bayswater",
    "sg:classifiers":[
        {
            "category":"Communications",
            "subcategory":"Film & Video Production",
            "type":"Services"
        }
    ],
    "sg:phone":"+61 3 9720 7000",
    "sg:postcode":"3153",
    "sg:province":"VIC",
    "sg:tags":[
        "colour",
        "pigment"
    ],
    "wof:name":"Ravenswood Australia",
    "wof:placetype":"venue"
},
  "geometry": {"coordinates":[145.27601623499999,-37.8239860535],"type":"Point"}
}