{
  "type": "Feature",
  "properties": {
    "addr:full":"Cnr Arden & Carr St Coogee NSW 2034",
    "addr:postcode":"2034",
    "addr:street":"Cnr Arden;Carr St",
    "iso:country":"AU",
    "sg:address":"Cnr Arden & Carr St",
    "sg:city":"Coogee",
    "sg:classifiers":[
        {
            "category":"Restaurant",
            "type":"Food & Drink"
        }
    ],
    "sg:phone":"+61 2 9315 9111",
    "sg:postcode":"2034",
    "sg:province":"NSW",
    "wof:name":"Crowne Plaza Promenade Restaurant",
    "wof:placetype":"venue"
},
  "geometry": {"coordinates":[151.25686645499999,-33.9205245972],"type":"Point"}
}