{
  "type": "Feature",
  "properties": {
    "addr:full":"17 Natalia Ave Huntingdale VIC 3166",
    "addr:housenumber":"17",
    "addr:postcode":"3166",
    "addr:street":"Natalia Ave",
    "iso:country":"AU",
    "sg:address":"17 Natalia Ave",
    "sg:city":"Huntingdale",
    "sg:classifiers":[
        {
            "category":"Wholesale",
            "subcategory":"Construction Materials",
            "type":"Manufacturing & Wholesale Goods"
        }
    ],
    "sg:phone":"+61 3 9543 1133",
    "sg:postcode":"3166",
    "sg:province":"VIC",
    "sg:tags":[
        "wholesaler",
        "equipment",
        "bathroom",
        "mfrs",
        "accessory"
    ],
    "wof:name":"Lynteq Australia Pty Ltd",
    "wof:placetype":"venue"
},
  "geometry": {"coordinates":[145.10516357399999,-37.9023399353],"type":"Point"}
}