{
  "type": "Feature",
  "properties": {
    "addr:full":"Dawson Hwy Moura QLD 4718",
    "addr:postcode":"4718",
    "addr:street":"Dawson Hwy",
    "iso:country":"AU",
    "sg:address":"Dawson Hwy",
    "sg:city":"Moura",
    "sg:classifiers":[
        {
            "category":"Professional",
            "subcategory":"Accounting & Tax Preparation",
            "type":"Services"
        }
    ],
    "sg:phone":"+61 7 4997 3855",
    "sg:postcode":"4718",
    "sg:province":"QLD",
    "sg:tags":[
        "accountant",
        "auditor"
    ],
    "wof:name":"Dawson Accounting & Management Services Pty Ltd",
    "wof:placetype":"venue"
},
  "geometry": {"coordinates":[149.97416687,-24.5672588348],"type":"Point"}
}