{
  "type": "Feature",
  "properties": {
    "addr:full":"unit 5 50 Rushdale St Scoresby VIC 3179",
    "addr:housenumber":"50",
    "addr:postcode":"3179",
    "addr:street":"Rushdale St",
    "iso:country":"AU",
    "sg:address":"unit 5 50 Rushdale St",
    "sg:city":"Scoresby",
    "sg:classifiers":[
        {
            "category":"Fast Food",
            "type":"Food & Drink"
        }
    ],
    "sg:phone":"+61 3 9763 0810",
    "sg:postcode":"3179",
    "sg:province":"VIC",
    "sg:tags":[
        "away",
        "take"
    ],
    "wof:name":"Rushdale Snack Bar",
    "wof:placetype":"venue"
},
  "geometry": {"coordinates":[145.25531005900001,-37.8997268677],"type":"Point"}
}