{
  "type": "Feature",
  "properties": {
    "addr:full":"27 Ferguson Drv Devonport TAS 7310",
    "addr:housenumber":"27",
    "addr:postcode":"7310",
    "addr:street":"Ferguson Drv",
    "iso:country":"AU",
    "sg:address":"27 Ferguson Drv",
    "sg:city":"Devonport",
    "sg:classifiers":[
        {
            "category":"Utilities",
            "subcategory":"Sewage",
            "type":"Services"
        }
    ],
    "sg:phone":"+61 3 6424 3059",
    "sg:postcode":"7310",
    "sg:province":"TAS",
    "sg:tags":[
        "water",
        "waste",
        "treatment"
    ],
    "wof:name":"Kwikflo Pollution Services",
    "wof:placetype":"venue"
},
  "geometry": {"coordinates":[146.34176635700001,-41.2071266174],"type":"Point"}
}