{
  "type": "Feature",
  "properties": {
    "iso:country":"AU",
    "sg:address":"218B Anakie Rd",
    "sg:city":"North Geelong",
    "sg:classifiers":[
        {
            "category":"Food & Beverages",
            "subcategory":"Liquor & Beverages",
            "type":"Retail Goods"
        }
    ],
    "sg:phone":"+61 3 5278 2855",
    "sg:postcode":"3215",
    "sg:province":"VIC",
    "sg:tags":[
        "store"
    ],
    "wof:name":"Cellarbrations",
    "wof:placetype":"venue"
},
  "geometry": {"coordinates":[144.334274292,-38.097454071],"type":"Point"}
}