{
  "type": "Feature",
  "properties": {
    "addr:full":"15 Steele St Devonport TAS 7310",
    "addr:housenumber":"15",
    "addr:postcode":"7310",
    "addr:street":"Steele St",
    "iso:country":"AU",
    "sg:address":"15 Steele St",
    "sg:city":"Devonport",
    "sg:classifiers":[
        {
            "category":"Real Estate",
            "subcategory":"Surveying",
            "type":"Services"
        }
    ],
    "sg:phone":"+61 3 6424 6444",
    "sg:postcode":"7310",
    "sg:province":"TAS",
    "sg:tags":[
        "surveyor",
        "land"
    ],
    "wof:name":"Lester Franks Survey And Geographic",
    "wof:placetype":"venue"
},
  "geometry": {"coordinates":[146.354644775,-41.1776428223],"type":"Point"}
}