{
  "type": "Feature",
  "properties": {
    "addr:full":"37 Catalina Drv Tullamarine VIC 3043",
    "addr:housenumber":"37",
    "addr:postcode":"3043",
    "addr:street":"Catalina Drv",
    "iso:country":"AU",
    "sg:address":"37 Catalina Drv",
    "sg:city":"Tullamarine",
    "sg:classifiers":[
        {
            "category":"Professional",
            "subcategory":"Computer Services",
            "type":"Services"
        }
    ],
    "sg:phone":"+61 1300 360 786",
    "sg:postcode":"3043",
    "sg:province":"VIC",
    "sg:tags":[
        "repairs",
        "upgrade",
        "equipment"
    ],
    "wof:name":"Computer Warranty Services Pty Ltd",
    "wof:placetype":"venue"
},
  "geometry": {"coordinates":[144.87924194300001,-37.6889915466],"type":"Point"}
}