{
  "type": "Feature",
  "properties": {
    "addr:full":"Lowrie Rd Boyanup WA 6237",
    "addr:postcode":"6237",
    "addr:street":"Lowrie Rd",
    "iso:country":"AU",
    "sg:address":"Lowrie Rd",
    "sg:city":"Boyanup",
    "sg:classifiers":[
        {
            "category":"Home & Garden",
            "subcategory":"Garden Supply",
            "type":"Retail Goods"
        }
    ],
    "sg:phone":"+61 8 9731 5034",
    "sg:postcode":"6237",
    "sg:province":"WA",
    "sg:tags":[
        "turf",
        "lawn"
    ],
    "wof:name":"South West Lawn",
    "wof:placetype":"venue"
},
  "geometry": {"coordinates":[115.737381,-33.512512],"type":"Point"}
}