{
  "type": "Feature",
  "properties": {
    "addr:full":"203 Martyn St Cairns QLD 4870",
    "addr:housenumber":"203",
    "addr:postcode":"4870",
    "addr:street":"Martyn St",
    "iso:country":"AU",
    "sg:address":"203 Martyn St",
    "sg:city":"Cairns",
    "sg:classifiers":[
        {
            "category":"Recreation",
            "type":"Entertainment"
        }
    ],
    "sg:phone":"+61 7 4031 0540",
    "sg:postcode":"4870",
    "sg:province":"QLD",
    "sg:tags":[
        "hire",
        "tour",
        "motor",
        "cycle"
    ],
    "wof:name":"Fair Dinkum Bike Tours",
    "wof:placetype":"venue"
},
  "geometry": {"coordinates":[145.75517273,-16.9131507874],"type":"Point"}
}