{
  "type": "Feature",
  "properties": {
    "addr:full":"93a St Hilliers Rd Auburn NSW 2144",
    "addr:housenumber":"93a",
    "addr:postcode":"2144",
    "addr:street":"St Hilliers Rd",
    "iso:country":"AU",
    "sg:address":"93a St Hilliers Rd",
    "sg:city":"Auburn",
    "sg:classifiers":[
        {
            "category":"Fast Food",
            "type":"Food & Drink"
        }
    ],
    "sg:phone":"+61 2 9748 2037",
    "sg:postcode":"2144",
    "sg:province":"NSW",
    "sg:tags":[
        "away",
        "take"
    ],
    "wof:name":"Food Expressions Cafe",
    "wof:placetype":"venue"
},
  "geometry": {"coordinates":[151.041473389,-33.8461303711],"type":"Point"}
}