{
  "type": "Feature",
  "properties": {
    "addr:full":"20 Richards Rd Narangba QLD 4504",
    "addr:housenumber":"20",
    "addr:postcode":"4504",
    "addr:street":"Richards Rd",
    "iso:country":"AU",
    "sg:address":"20 Richards Rd",
    "sg:city":"Narangba",
    "sg:classifiers":[
        {
            "category":"Building & Trades",
            "subcategory":"Equipment Rental",
            "type":"Services"
        }
    ],
    "sg:phone":"+61 7 3888 1205",
    "sg:postcode":"4504",
    "sg:province":"QLD",
    "sg:tags":[
        "party",
        "hire"
    ],
    "wof:name":"Dial-A-Chuck Wagon",
    "wof:placetype":"venue"
},
  "geometry": {"coordinates":[152.97874450699999,-27.2039794922],"type":"Point"}
}