{
  "type": "Feature",
  "properties": {
    "addr:full":"8 Illawong St Cannonvale QLD 4802",
    "addr:housenumber":"8",
    "addr:postcode":"4802",
    "addr:street":"Illawong St",
    "iso:country":"AU",
    "sg:address":"8 Illawong St",
    "sg:city":"Cannonvale",
    "sg:classifiers":[
        {
            "category":"Professional",
            "subcategory":"Engineering",
            "type":"Services"
        }
    ],
    "sg:phone":"+61 7 4946 7364",
    "sg:postcode":"4802",
    "sg:province":"QLD",
    "sg:tags":[
        "consulting",
        "engineer"
    ],
    "wof:name":"G.W. Goddard & Associates",
    "wof:placetype":"venue"
},
  "geometry": {"coordinates":[148.69471740700001,-20.2802753448],"type":"Point"}
}