{
  "type": "Feature",
  "properties": {
    "addr:full":"Lot 13, Coyne Rd Cannonvale QLD 4802",
    "addr:postcode":"4802",
    "addr:street":"Coyne Rd",
    "iso:country":"AU",
    "sg:address":"Lot 13, Coyne Rd",
    "sg:city":"Cannonvale",
    "sg:classifiers":[
        {
            "category":"Home & Garden",
            "subcategory":"Hardware",
            "type":"Retail Goods"
        }
    ],
    "sg:phone":"+61 7 4948 2311",
    "sg:postcode":"4802",
    "sg:province":"QLD",
    "sg:tags":[
        "plumber",
        "supply"
    ],
    "wof:name":"Reece Pty Ltd",
    "wof:placetype":"venue"
},
  "geometry": {"coordinates":[148.690383911,-20.2824993134],"type":"Point"}
}