{
  "type": "Feature",
  "properties": {
    "addr:full":"147 Byrnes St Mareeba QLD 4880",
    "addr:housenumber":"147",
    "addr:postcode":"4880",
    "addr:street":"Byrnes St",
    "iso:country":"AU",
    "sg:address":"147 Byrnes St",
    "sg:city":"Mareeba",
    "sg:classifiers":[
        {
            "category":"Travel",
            "subcategory":"Hotels & Motels",
            "type":"Entertainment"
        }
    ],
    "sg:phone":"+61 7 4092 1046",
    "sg:postcode":"4880",
    "sg:province":"QLD",
    "sg:tags":[
        "accommodation"
    ],
    "wof:name":"Royal Hotel Marreba",
    "wof:placetype":"venue"
},
  "geometry": {"coordinates":[145.42015075699999,-16.9857063293],"type":"Point"}
}