{
  "type": "Feature",
  "properties": {
    "addr:full":"11 Onslow St Latham ACT 2615",
    "addr:housenumber":"11",
    "addr:postcode":"2615",
    "addr:street":"Onslow St",
    "iso:country":"AU",
    "sg:address":"11 Onslow St",
    "sg:city":"Latham",
    "sg:classifiers":[
        {
            "category":"Building & Trades",
            "subcategory":"Construction",
            "type":"Services"
        }
    ],
    "sg:phone":"+61 2 6255 1110",
    "sg:postcode":"2615",
    "sg:province":"ACT",
    "sg:tags":[
        "plasterboard",
        "plasterer",
        "fixer"
    ],
    "wof:name":"J F & M O&#039;Hare",
    "wof:placetype":"venue"
},
  "geometry": {"coordinates":[149.033004761,-35.2201271057],"type":"Point"}
}