{
  "type": "Feature",
  "properties": {
    "iso:country":"AU",
    "sg:address":"105 McLaughlin St",
    "sg:city":"North Rockhampton",
    "sg:classifiers":[
        {
            "category":"Retail",
            "subcategory":"Storage",
            "type":"Services"
        }
    ],
    "sg:phone":"+61 7 4936 3770",
    "sg:postcode":"4701",
    "sg:province":"QLD",
    "sg:tags":[
        "removal",
        "furniture"
    ],
    "wof:name":"Cliff Morgan Removals",
    "wof:placetype":"venue"
},
  "geometry": {"coordinates":[150.51167297399999,-23.3342456818],"type":"Point"}
}