{
  "type": "Feature",
  "properties": {
    "addr:full":"168 Fitzroy St Grafton NSW 2460",
    "addr:housenumber":"168",
    "addr:postcode":"2460",
    "addr:street":"Fitzroy St",
    "iso:country":"AU",
    "sg:address":"168 Fitzroy St",
    "sg:city":"Grafton",
    "sg:classifiers":[
        {
            "category":"Education",
            "subcategory":"Music School",
            "type":"Public Place"
        }
    ],
    "sg:phone":"+61 2 6642 6844",
    "sg:postcode":"2460",
    "sg:province":"NSW",
    "sg:tags":[
        "teacher"
    ],
    "wof:name":"Merrick McCallum Drum Teacher",
    "wof:placetype":"venue"
},
  "geometry": {"coordinates":[152.92973327600001,-29.6887588501],"type":"Point"}
}