{
  "type": "Feature",
  "properties": {
    "addr:full":"Shop 22 William St Beaudesert QLD 4285",
    "addr:housenumber":"shop 22",
    "addr:postcode":"4285",
    "addr:street":"William St",
    "iso:country":"AU",
    "sg:address":"Shop 22 William St",
    "sg:city":"Beaudesert",
    "sg:classifiers":[
        {
            "category":"Personal",
            "subcategory":"Nail Salon",
            "type":"Services"
        }
    ],
    "sg:phone":"+61 7 5541 3712",
    "sg:postcode":"4285",
    "sg:province":"QLD",
    "sg:tags":[
        "artificial"
    ],
    "wof:name":"Terri's Nails & Beauty",
    "wof:placetype":"venue"
},
  "geometry": {"coordinates":[152.996475,-27.988392],"type":"Point"}
}