{
  "type": "Feature",
  "properties": {
    "addr:full":"Brownings Rd Gibson WA 6448",
    "addr:postcode":"6448",
    "addr:street":"Brownings Rd",
    "iso:country":"AU",
    "sg:address":"Brownings Rd",
    "sg:city":"Gibson",
    "sg:classifiers":[
        {
            "category":"Farming",
            "subcategory":"Farm",
            "type":"Manufacturing & Wholesale Goods"
        }
    ],
    "sg:phone":"+61 8 9075 3010",
    "sg:postcode":"6448",
    "sg:province":"WA",
    "sg:tags":[
        "farmer"
    ],
    "wof:name":"Meringo Holdings",
    "wof:placetype":"venue"
},
  "geometry": {"coordinates":[121.752990723,-33.6196784973],"type":"Point"}
}