{
  "type": "Feature",
  "properties": {
    "addr:full":"212 Wellington St Launceston TAS 7250",
    "addr:housenumber":"212",
    "addr:postcode":"7250",
    "addr:street":"Wellington St",
    "iso:country":"AU",
    "sg:address":"212 Wellington St",
    "sg:city":"Launceston",
    "sg:classifiers":[
        {
            "category":"Building & Trades",
            "subcategory":"Plumbing",
            "type":"Services"
        }
    ],
    "sg:phone":"+61 3 6343 6181",
    "sg:postcode":"7250",
    "sg:province":"TAS",
    "sg:tags":[
        "repair",
        "appliance",
        "system",
        "heating"
    ],
    "wof:name":"Rainbow Heating Services",
    "wof:placetype":"venue"
},
  "geometry": {"coordinates":[147.14187622099999,-41.4511032104],"type":"Point"}
}