{
  "type": "Feature",
  "properties": {
    "addr:full":"Shop 3, 46 Main St Pialba QLD 4655",
    "addr:housenumber":"shop;46",
    "addr:postcode":"4655",
    "addr:street":"Main St",
    "iso:country":"AU",
    "sg:address":"Shop 3, 46 Main St",
    "sg:city":"Pialba",
    "sg:classifiers":[
        {
            "category":"Cafe",
            "type":"Food & Drink"
        }
    ],
    "sg:phone":"+61 7 4194 2752",
    "sg:postcode":"4655",
    "sg:province":"QLD",
    "wof:name":"Chatters On The Bay Cafe",
    "wof:placetype":"venue"
},
  "geometry": {"coordinates":[152.83891299999999,-25.284487],"type":"Point"}
}