{
  "type": "Feature",
  "properties": {
    "addr:full":"705 Military Rd Mosman NSW 2088",
    "addr:housenumber":"705",
    "addr:postcode":"2088",
    "addr:street":"Military Rd",
    "iso:country":"AU",
    "sg:address":"705 Military Rd",
    "sg:city":"Mosman",
    "sg:classifiers":[
        {
            "category":"Shopping",
            "subcategory":"Clothing, Apparel, & Fashions",
            "type":"Retail Goods"
        }
    ],
    "sg:phone":"+61 2 9969 3031",
    "sg:postcode":"2088",
    "sg:province":"NSW",
    "sg:tags":[
        "menswear"
    ],
    "wof:name":"Rihani H Menswear & Fine Tailoring",
    "wof:placetype":"venue"
},
  "geometry": {"coordinates":[151.24382019000001,-33.8274269104],"type":"Point"}
}