{
  "type": "Feature",
  "properties": {
    "iso:country":"AU",
    "sg:address":"839 Boundary Rd",
    "sg:city":"Coopers Plains",
    "sg:classifiers":[
        {
            "category":"Home & Garden",
            "subcategory":"Mobile Homes",
            "type":"Retail Goods"
        }
    ],
    "sg:phone":"+61 7 3277 4433",
    "sg:postcode":"4108",
    "sg:province":"QLD",
    "sg:tags":[
        "motor",
        "campervans"
    ],
    "wof:name":"Generator Specialists",
    "wof:placetype":"venue"
},
  "geometry": {"coordinates":[153.030151367,-27.5693702698],"type":"Point"}
}