{
  "type": "Feature",
  "properties": {
    "addr:full":"20 Murray Drv Point Leo VIC 3916",
    "addr:housenumber":"20",
    "addr:postcode":"3916",
    "addr:street":"Murray Drv",
    "iso:country":"AU",
    "sg:address":"20 Murray Drv",
    "sg:city":"Point Leo",
    "sg:classifiers":[
        {
            "category":"Building & Trades",
            "subcategory":"Construction",
            "type":"Services"
        }
    ],
    "sg:phone":"+61 3 5989 8171",
    "sg:postcode":"3916",
    "sg:province":"VIC",
    "sg:tags":[
        "contractor"
    ],
    "wof:name":"Staff Building and Contracting",
    "wof:placetype":"venue"
},
  "geometry": {"coordinates":[145.074386597,-38.4168319702],"type":"Point"}
}