{
  "type": "Feature",
  "properties": {
    "addr:full":"90 Wattletree Rd Malvern VIC 3144",
    "addr:housenumber":"90",
    "addr:postcode":"3144",
    "addr:street":"Wattletree Rd",
    "iso:country":"AU",
    "sg:address":"90 Wattletree Rd",
    "sg:city":"Malvern",
    "sg:classifiers":[
        {
            "category":"Retail",
            "subcategory":"Veterinary Services",
            "type":"Services"
        }
    ],
    "sg:phone":"+61 3 9509 9744",
    "sg:postcode":"3144",
    "sg:province":"VIC",
    "sg:tags":[
        "surgeon"
    ],
    "wof:name":"Malvern Central Vet Centre",
    "wof:placetype":"venue"
},
  "geometry": {"coordinates":[145.03526306099999,-37.8632507324],"type":"Point"}
}