{
  "type": "Feature",
  "properties": {
    "iso:country":"AU",
    "sg:address":"57 Terrina St",
    "sg:city":"Lauderdale",
    "sg:classifiers":[
        {
            "category":"Building & Trades",
            "subcategory":"Construction",
            "type":"Services"
        }
    ],
    "sg:phone":"+61 3 6248 7009",
    "sg:postcode":"7021",
    "sg:province":"TAS",
    "sg:tags":[
        "fencing",
        "contractor"
    ],
    "wof:name":"Rick White",
    "wof:placetype":"venue"
},
  "geometry": {"coordinates":[147.494216919,-42.8996658325],"type":"Point"}
}