{
  "type": "Feature",
  "properties": {
    "iso:country":"AU",
    "sg:address":"10 Mallyon St",
    "sg:city":"Emerald",
    "sg:classifiers":[
        {
            "category":"Banks & Credit Unions",
            "subcategory":"Bank",
            "type":"Services"
        }
    ],
    "sg:phone":"+61 7 4982 0392",
    "sg:postcode":"4720",
    "sg:province":"QLD",
    "wof:name":"Rabobank Australia Group",
    "wof:placetype":"venue"
},
  "geometry": {"coordinates":[148.16931199999999,-23.537745],"type":"Point"}
}