{
  "type": "Feature",
  "properties": {
    "iso:country":"AU",
    "sg:address":"7 Meadowland Crt",
    "sg:city":"Worongary",
    "sg:classifiers":[
        {
            "category":"Professional",
            "subcategory":"Computer Services",
            "type":"Services"
        }
    ],
    "sg:phone":"+61 7 5522 7111",
    "sg:postcode":"4213",
    "sg:province":"QLD",
    "sg:tags":[
        "technical",
        "support"
    ],
    "wof:name":"ITXperts Corporate Gold Coast",
    "wof:placetype":"venue"
},
  "geometry": {"coordinates":[153.347854614,-28.033531189],"type":"Point"}
}