{
  "type": "Feature",
  "properties": {
    "addr:full":"428 Toorak Rd Toorak VIC 3142",
    "addr:housenumber":"428",
    "addr:postcode":"3142",
    "addr:street":"Toorak Rd",
    "iso:country":"AU",
    "sg:address":"428 Toorak Rd",
    "sg:city":"Toorak",
    "sg:classifiers":[
        {
            "category":"Real Estate",
            "subcategory":"Real Estate Agent",
            "type":"Services"
        }
    ],
    "sg:phone":"+61 3 9826 0000",
    "sg:postcode":"3142",
    "sg:province":"VIC",
    "wof:name":"TBM Sales Pty Ltd",
    "wof:placetype":"venue"
},
  "geometry": {"coordinates":[145.00836181599999,-37.8411331177],"type":"Point"}
}