{
  "type": "Feature",
  "properties": {
    "addr:full":"Peninsular Development Rd Musgrave QLD 4871",
    "addr:postcode":"4871",
    "addr:street":"Development Rd",
    "iso:country":"AU",
    "sg:address":"Peninsular Development Rd",
    "sg:city":"Musgrave",
    "sg:classifiers":[
        {
            "category":"Restaurant",
            "type":"Food & Drink"
        }
    ],
    "sg:phone":"+61 7 4060 3229",
    "sg:postcode":"4871",
    "sg:province":"QLD",
    "sg:tags":[
        "roadhouse"
    ],
    "wof:name":"Musgrave Cafe",
    "wof:placetype":"venue"
},
  "geometry": {"coordinates":[143.49250793499999,-14.7804002762],"type":"Point"}
}