{
  "type": "Feature",
  "properties": {
    "iso:country":"AU",
    "sg:address":"15 Hawker St",
    "sg:city":"Airport West",
    "sg:classifiers":[
        {
            "category":"Retail",
            "subcategory":"Auto Repair",
            "type":"Services"
        }
    ],
    "sg:phone":"+61 3 9338 4322",
    "sg:postcode":"3042",
    "sg:province":"VIC",
    "sg:tags":[
        "engine",
        "reconditioning"
    ],
    "wof:name":"J & R Cylinder Heads",
    "wof:placetype":"venue"
},
  "geometry": {"coordinates":[144.889892578,-37.7224655151],"type":"Point"}
}