{
  "type": "Feature",
  "properties": {
    "addr:full":"903 Raglan Pde Warrnambool VIC 3280",
    "addr:housenumber":"903",
    "addr:postcode":"3280",
    "addr:street":"Raglan Pde",
    "iso:country":"AU",
    "sg:address":"903 Raglan Pde",
    "sg:city":"Warrnambool",
    "sg:classifiers":[
        {
            "category":"Health Services",
            "subcategory":"Health Practitioner",
            "type":"Services"
        }
    ],
    "sg:phone":"+61 3 5561 2400",
    "sg:postcode":"3280",
    "sg:province":"VIC",
    "sg:tags":[
        "hypnotherapy"
    ],
    "wof:name":"South-West Counselling",
    "wof:placetype":"venue"
},
  "geometry": {"coordinates":[142.474334717,-38.372341156],"type":"Point"}
}