{
  "type": "Feature",
  "properties": {
    "iso:country":"AU",
    "sg:address":"Bathurst St",
    "sg:city":"Sydney",
    "sg:classifiers":[
        {
            "category":"Professional",
            "type":"Services"
        }
    ],
    "sg:phone":"+61 418 995 379",
    "sg:postcode":"2000",
    "sg:province":"NSW",
    "sg:tags":[
        "shop",
        "fitting"
    ],
    "wof:name":"SMA Fitouts",
    "wof:placetype":"venue"
},
  "geometry": {"coordinates":[151.20945739699999,-33.8746070862],"type":"Point"}
}