{
  "type": "Feature",
  "properties": {
    "addr:full":"Hanger 10 Bush Pilots Ave Aeroglen QLD 4870",
    "addr:housenumber":"10",
    "addr:postcode":"4870",
    "addr:street":"Hanger;Pilots Ave",
    "iso:country":"AU",
    "sg:address":"Hanger 10 Bush Pilots Ave",
    "sg:city":"Aeroglen",
    "sg:classifiers":[
        {
            "category":"Airport",
            "subcategory":"General Aviation",
            "type":"Transportation"
        }
    ],
    "sg:phone":"+61 7 4034 9000",
    "sg:postcode":"4870",
    "sg:province":"QLD",
    "sg:tags":[
        "helicopter"
    ],
    "wof:name":"Sunsea Heli",
    "wof:placetype":"venue"
},
  "geometry": {"coordinates":[145.748657227,-16.8833370209],"type":"Point"}
}