{
  "type": "Feature",
  "properties": {
    "iso:country":"AU",
    "sg:address":"121 Holland Rd",
    "sg:city":"Holland Park",
    "sg:classifiers":[
        {
            "category":"Professional",
            "subcategory":"Detective & Security Services",
            "type":"Services"
        }
    ],
    "sg:phone":"+61 7 3397 8836",
    "sg:postcode":"4121",
    "sg:province":"QLD",
    "sg:tags":[
        "equipment",
        "window",
        "doors"
    ],
    "sg:website":"http://www.steelgrilles.com.au",
    "wof:name":"Barmore Security & Welding",
    "wof:placetype":"venue"
},
  "geometry": {"coordinates":[153.070068359,-27.5165500641],"type":"Point"}
}