{
  "type": "Feature",
  "properties": {
    "iso:country":"AU",
    "sg:address":"563 Douglas Rd",
    "sg:city":"Lavington",
    "sg:classifiers":[
        {
            "category":"Education",
            "subcategory":"Music School",
            "type":"Public Place"
        }
    ],
    "sg:phone":"+61 2 6025 8321",
    "sg:postcode":"2641",
    "sg:province":"NSW",
    "sg:tags":[
        "teacher"
    ],
    "wof:name":"Bob Haanstra Guitar Tuition",
    "wof:placetype":"venue"
},
  "geometry": {"coordinates":[146.93038940400001,-36.0380554199],"type":"Point"}
}