{
  "type": "Feature",
  "properties": {
    "addr:full":"95 High St Willoughby NSW 2068",
    "addr:housenumber":"95",
    "addr:postcode":"2068",
    "addr:street":"High St",
    "iso:country":"AU",
    "sg:address":"95 High St",
    "sg:city":"Willoughby",
    "sg:classifiers":[
        {
            "category":"Shopping",
            "subcategory":"Bicycles & Sporting Goods",
            "type":"Retail Goods"
        }
    ],
    "sg:phone":"+61 2 9958 1000",
    "sg:postcode":"2068",
    "sg:province":"NSW",
    "sg:tags":[
        "chemical",
        "equipment",
        "pool",
        "swimming"
    ],
    "wof:name":"Willoughby Pool Shop",
    "wof:placetype":"venue"
},
  "geometry": {"coordinates":[151.203567505,-33.8022956848],"type":"Point"}
}