{
  "type": "Feature",
  "properties": {
    "iso:country":"AU",
    "sg:address":"33 Thornton St",
    "sg:city":"Surfers Paradise",
    "sg:classifiers":[
        {
            "category":"Building & Trades",
            "subcategory":"Landscaping Services",
            "type":"Services"
        }
    ],
    "sg:phone":"+61 7 5526 8796",
    "sg:postcode":"4217",
    "sg:province":"QLD",
    "sg:tags":[
        "gardener"
    ],
    "wof:name":"Alex Turcas",
    "wof:placetype":"venue"
},
  "geometry": {"coordinates":[153.429763794,-28.0104160309],"type":"Point"}
}