{
  "type": "Feature",
  "properties": {
    "addr:full":"1/ 4 Maple St Maleny QLD 4552",
    "addr:housenumber":"/ 4",
    "addr:postcode":"4552",
    "addr:street":"Maple St",
    "iso:country":"AU",
    "sg:address":"1/ 4 Maple St",
    "sg:city":"Maleny",
    "sg:classifiers":[
        {
            "category":"Real Estate",
            "subcategory":"Real Estate Agent",
            "type":"Services"
        }
    ],
    "sg:phone":"+61 7 5494 3022",
    "sg:postcode":"4552",
    "sg:province":"QLD",
    "wof:name":"Maleny & Hinterland Real Estate",
    "wof:placetype":"venue"
},
  "geometry": {"coordinates":[152.85223388700001,-26.7582015991],"type":"Point"}
}