{
  "type": "Feature",
  "properties": {
    "iso:country":"AU",
    "sg:address":"198 Davistown Rd",
    "sg:city":"Yattalunga",
    "sg:classifiers":[
        {
            "category":"Building & Trades",
            "subcategory":"Construction",
            "type":"Services"
        }
    ],
    "sg:phone":"+61 412 415 891",
    "sg:postcode":"2251",
    "sg:province":"NSW",
    "sg:tags":[
        "spouting",
        "guttering"
    ],
    "wof:name":"Chel gutter protection",
    "wof:placetype":"venue"
},
  "geometry": {"coordinates":[151.361129761,-33.4692153931],"type":"Point"}
}