{
  "type": "Feature",
  "properties": {
    "addr:full":"106 Sixth Ave Cotton Tree QLD 4558",
    "addr:housenumber":"106",
    "addr:postcode":"4558",
    "addr:street":"Sixth Ave Cotton",
    "iso:country":"AU",
    "sg:address":"106 Sixth Ave",
    "sg:city":"Cotton Tree",
    "sg:classifiers":[
        {
            "category":"Cafe",
            "type":"Food & Drink"
        }
    ],
    "sg:phone":"+61 7 5443 3843",
    "sg:postcode":"4558",
    "sg:province":"QLD",
    "wof:name":"SeaBah Cafe",
    "wof:placetype":"venue"
},
  "geometry": {"coordinates":[153.102752686,-26.6604557037],"type":"Point"}
}