{
  "type": "Feature",
  "properties": {
    "iso:country":"AU",
    "sg:address":"U3/ 1 Basil St",
    "sg:city":"Newport",
    "sg:classifiers":[
        {
            "category":"Professional",
            "subcategory":"Management & Consulting",
            "type":"Services"
        }
    ],
    "sg:phone":"+61 3 9391 6122",
    "sg:postcode":"3015",
    "sg:province":"VIC",
    "sg:tags":[
        "consultant",
        "educational"
    ],
    "wof:name":"Pyramid Educational Consultants Of Australia",
    "wof:placetype":"venue"
},
  "geometry": {"coordinates":[144.86575317399999,-37.8474006653],"type":"Point"}
}