{
  "type": "Feature",
  "properties": {
    "addr:full":"Suite 4 79- 81 Rowe St Eastwood NSW 2122",
    "addr:housenumber":"79 81",
    "addr:postcode":"2122",
    "addr:street":"Rowe St",
    "iso:country":"AU",
    "sg:address":"Suite 4 79- 81 Rowe St",
    "sg:city":"Eastwood",
    "sg:classifiers":[
        {
            "category":"Health Services",
            "subcategory":"Chiropractor",
            "type":"Services"
        }
    ],
    "sg:phone":"+61 2 9874 1200",
    "sg:postcode":"2122",
    "sg:province":"NSW",
    "wof:name":"Gunther G F",
    "wof:placetype":"venue"
},
  "geometry": {"coordinates":[151.083450317,-33.7909698486],"type":"Point"}
}