{
  "type": "Feature",
  "properties": {
    "addr:full":"5 Lawrence Drv Devonport TAS 7310",
    "addr:housenumber":"5",
    "addr:postcode":"7310",
    "addr:street":"Lawrence Drv",
    "iso:country":"AU",
    "sg:address":"5 Lawrence Drv",
    "sg:city":"Devonport",
    "sg:classifiers":[
        {
            "category":"Education",
            "subcategory":"School",
            "type":"Public Place"
        }
    ],
    "sg:phone":"+61 3 6424 5211",
    "sg:postcode":"7310",
    "sg:province":"TAS",
    "sg:tags":[
        "state",
        "except",
        "nsw"
    ],
    "wof:name":"Hillcrest Primary",
    "wof:placetype":"venue"
},
  "geometry": {"coordinates":[146.33726501500001,-41.1866455078],"type":"Point"}
}