{
  "type": "Feature",
  "properties": {
    "addr:full":"250 Olinda-Monbulk Rd Monbulk VIC 3793",
    "addr:housenumber":"250",
    "addr:postcode":"3793",
    "addr:street":"Olinda-Monbulk Rd",
    "iso:country":"AU",
    "sg:address":"250 Olinda-Monbulk Rd",
    "sg:city":"Monbulk",
    "sg:classifiers":[
        {
            "category":"Restaurant",
            "type":"Food & Drink"
        }
    ],
    "sg:phone":"+61 3 9756 7045",
    "sg:postcode":"3793",
    "sg:province":"VIC",
    "wof:name":"Blarney's Celtic Affair",
    "wof:placetype":"venue"
},
  "geometry": {"coordinates":[145.40126037600001,-37.8734130859],"type":"Point"}
}