{
  "type": "Feature",
  "properties": {
    "addr:full":"16 Sixth Ave Loftus NSW 2232",
    "addr:housenumber":"16",
    "addr:postcode":"2232",
    "addr:street":"Sixth Ave",
    "iso:country":"AU",
    "sg:address":"16 Sixth Ave",
    "sg:city":"Loftus",
    "sg:classifiers":[
        {
            "category":"Building & Trades",
            "subcategory":"Construction",
            "type":"Services"
        }
    ],
    "sg:phone":"+61 418 403 007",
    "sg:postcode":"2232",
    "sg:province":"NSW",
    "sg:tags":[
        "earth",
        "excavating",
        "moving",
        "contractor"
    ],
    "wof:name":"A.L.T. Excavations",
    "wof:placetype":"venue"
},
  "geometry": {"coordinates":[151.04861450199999,-34.0426445007],"type":"Point"}
}