{
  "type": "Feature",
  "properties": {
    "iso:country":"AU",
    "sg:address":"PO Box 2644",
    "sg:city":"Broome",
    "sg:classifiers":[
        {
            "category":"Recreation",
            "subcategory":"Boat Charter",
            "type":"Entertainment"
        }
    ],
    "sg:phone":"+61 8 9192 8668",
    "sg:postcode":"6725",
    "sg:province":"WA",
    "wof:name":"Kimberley Catamaran Cruises",
    "wof:placetype":"venue"
},
  "geometry": {"coordinates":[122.677589416,-18.2141704559],"type":"Point"}
}