{
  "type": "Feature",
  "properties": {
    "addr:full":"Agnes River Rd Hazel Park VIC 3966",
    "addr:postcode":"3966",
    "addr:street":"River Rd",
    "iso:country":"AU",
    "sg:address":"Agnes River Rd",
    "sg:city":"Hazel Park",
    "sg:classifiers":[
        {
            "category":"Farming",
            "subcategory":"Farm & Veterinary Services",
            "type":"Manufacturing & Wholesale Goods"
        }
    ],
    "sg:phone":"+61 3 5688 1248",
    "sg:postcode":"3966",
    "sg:province":"VIC",
    "sg:tags":[
        "contracting"
    ],
    "wof:name":"Jackson K D",
    "wof:placetype":"venue"
},
  "geometry": {"coordinates":[146.38752746599999,-38.6391372681],"type":"Point"}
}