{
  "type": "Feature",
  "properties": {
    "addr:full":"Unit 2/2- 4 Mulvihill St West Ryde NSW 2114",
    "addr:housenumber":"4",
    "addr:postcode":"2114",
    "addr:street":"Mulvihill St",
    "iso:country":"AU",
    "sg:address":"Unit 2/2- 4 Mulvihill St",
    "sg:city":"West Ryde",
    "sg:classifiers":[
        {
            "category":"Retail",
            "subcategory":"Auto Repair",
            "type":"Services"
        }
    ],
    "sg:phone":"+61 2 9809 1934",
    "sg:postcode":"2114",
    "sg:province":"NSW",
    "sg:tags":[
        "repairer",
        "motor",
        "engineer"
    ],
    "wof:name":"J.R. Automotive Services",
    "wof:placetype":"venue"
},
  "geometry": {"coordinates":[151.093505859,-33.8115234375],"type":"Point"}
}