{
  "type": "Feature",
  "properties": {
    "addr:full":"5 Rowell St Granville NSW 2142",
    "addr:housenumber":"5",
    "addr:postcode":"2142",
    "addr:street":"Rowell St",
    "iso:country":"AU",
    "sg:address":"5 Rowell St",
    "sg:city":"Granville",
    "sg:classifiers":[
        {
            "category":"Communications",
            "subcategory":"Film & Video Production",
            "type":"Services"
        }
    ],
    "sg:phone":"+61 2 9682 3883",
    "sg:postcode":"2142",
    "sg:province":"NSW",
    "sg:tags":[
        "linen",
        "good"
    ],
    "wof:name":"Pdb Trading Co Pty Ltd",
    "wof:placetype":"venue"
},
  "geometry": {"coordinates":[151.01324462900001,-33.8313407898],"type":"Point"}
}