{
  "type": "Feature",
  "properties": {
    "addr:full":"2a Chelmsford Rd Asquith NSW 2077",
    "addr:housenumber":"2a",
    "addr:postcode":"2077",
    "addr:street":"Chelmsford Rd",
    "iso:country":"AU",
    "sg:address":"2a Chelmsford Rd",
    "sg:city":"Asquith",
    "sg:classifiers":[
        {
            "category":"Education",
            "subcategory":"Kindergarten",
            "type":"Public Place"
        }
    ],
    "sg:phone":"+61 2 9477 2258",
    "sg:postcode":"2077",
    "sg:province":"NSW",
    "sg:tags":[
        "pre-schools"
    ],
    "wof:name":"Asquith Norwood Community Pre-School Inc",
    "wof:placetype":"venue"
},
  "geometry": {"coordinates":[151.11639404300001,-33.6890678406],"type":"Point"}
}