{
  "type": "Feature",
  "properties": {
    "addr:full":"23 Lascelles St Coburg West VIC 3058",
    "addr:housenumber":"23",
    "addr:postcode":"3058",
    "addr:street":"Lascelles St",
    "iso:country":"AU",
    "sg:address":"23 Lascelles St",
    "sg:city":"Coburg West",
    "sg:classifiers":[
        {
            "category":"Retail",
            "subcategory":"Auto Rental",
            "type":"Services"
        }
    ],
    "sg:phone":"+61 412 328 087",
    "sg:postcode":"3058",
    "sg:province":"VIC",
    "sg:tags":[
        "chauffeur",
        "car",
        "hire",
        "driven",
        "limousine"
    ],
    "wof:name":"Cunningham Limousines",
    "wof:placetype":"venue"
},
  "geometry": {"coordinates":[144.95045471200001,-37.745098114],"type":"Point"}
}