{
  "type": "Feature",
  "properties": {
    "iso:country":"AU",
    "sg:address":"2 Despatch St",
    "sg:city":"Echuca",
    "sg:classifiers":[
        {
            "category":"Wholesale",
            "subcategory":"Fruits & Vegetables",
            "type":"Manufacturing & Wholesale Goods"
        }
    ],
    "sg:phone":"+61 3 5480 7344",
    "sg:postcode":"3564",
    "sg:province":"VIC",
    "sg:tags":[
        "produce",
        "grain"
    ],
    "wof:name":"Eastate Commodities",
    "wof:placetype":"venue"
},
  "geometry": {"coordinates":[144.72926330600001,-36.1385993958],"type":"Point"}
}