{
  "type": "Feature",
  "properties": {
    "addr:full":"Shop 4 Mulwaree Arcade Bradley St Goulburn NSW 2580",
    "addr:housenumber":"shop 4",
    "addr:postcode":"2580",
    "addr:street":"Mulwaree Arcade Bradley St",
    "iso:country":"AU",
    "sg:address":"Shop 4 Mulwaree Arcade Bradley St",
    "sg:city":"Goulburn",
    "sg:classifiers":[
        {
            "category":"Personal",
            "subcategory":"Beauty Salon",
            "type":"Services"
        }
    ],
    "sg:phone":"+61 2 4823 6186",
    "sg:postcode":"2580",
    "sg:province":"NSW",
    "sg:tags":[
        "hairdresser"
    ],
    "wof:name":"Jagged Edge Hair",
    "wof:placetype":"venue"
},
  "geometry": {"coordinates":[149.72297668499999,-34.7497406006],"type":"Point"}
}