{
  "type": "Feature",
  "properties": {
    "iso:country":"AU",
    "sg:address":"13 McInnes St",
    "sg:city":"Ridleyton",
    "sg:classifiers":[
        {
            "category":"Building & Trades",
            "subcategory":"Construction",
            "type":"Services"
        }
    ],
    "sg:phone":"+61 8 8346 5567",
    "sg:postcode":"5008",
    "sg:province":"SA",
    "sg:tags":[
        "fencing",
        "contractor"
    ],
    "wof:name":"Florina Light Constructions",
    "wof:placetype":"venue"
},
  "geometry": {"coordinates":[138.568207,-34.899673],"type":"Point"}
}