{
  "type": "Feature",
  "properties": {
    "addr:full":"10 Elite Way Carrum Downs VIC 3201",
    "addr:housenumber":"10",
    "addr:postcode":"3201",
    "addr:street":"Elite Way",
    "iso:country":"AU",
    "sg:address":"10 Elite Way",
    "sg:city":"Carrum Downs",
    "sg:classifiers":[
        {
            "category":"Wholesale",
            "subcategory":"Hardware",
            "type":"Manufacturing & Wholesale Goods"
        }
    ],
    "sg:phone":"+61 3 8773 4000",
    "sg:postcode":"3201",
    "sg:province":"VIC",
    "wof:name":"Zone Hardware",
    "wof:placetype":"venue"
},
  "geometry": {"coordinates":[145.16673299999999,-38.098774],"type":"Point"}
}