{
  "type": "Feature",
  "properties": {
    "addr:full":"61 Bellevue St Toowoomba QLD 4350",
    "addr:housenumber":"61",
    "addr:postcode":"4350",
    "addr:street":"Bellevue St",
    "iso:country":"AU",
    "sg:address":"61 Bellevue St",
    "sg:city":"Toowoomba",
    "sg:classifiers":[
        {
            "category":"Shopping",
            "subcategory":"Crafts & Fabrics",
            "type":"Retail Goods"
        }
    ],
    "sg:phone":"+61 7 4638 3800",
    "sg:postcode":"4350",
    "sg:province":"QLD",
    "sg:tags":[
        "synthetic",
        "canvas",
        "product"
    ],
    "wof:name":"Bob Power Canvas",
    "wof:placetype":"venue"
},
  "geometry": {"coordinates":[151.95030199999999,-27.554642],"type":"Point"}
}