{
  "type": "Feature",
  "properties": {
    "addr:full":"132a Gwynne St Richmond VIC 3121",
    "addr:housenumber":"132a",
    "addr:postcode":"3121",
    "addr:street":"Gwynne St",
    "iso:country":"AU",
    "sg:address":"132a Gwynne St",
    "sg:city":"Richmond",
    "sg:classifiers":[
        {
            "category":"Professional",
            "subcategory":"Business Services",
            "type":"Services"
        }
    ],
    "sg:phone":"+61 3 9421 5800",
    "sg:postcode":"3121",
    "sg:province":"VIC",
    "sg:tags":[
        "fashion",
        "agent"
    ],
    "wof:name":"Condo Fashion Agency",
    "wof:placetype":"venue"
},
  "geometry": {"coordinates":[145.005401611,-37.8244934082],"type":"Point"}
}