{
  "type": "Feature",
  "properties": {
    "addr:full":"195 Bay St Port Melbourne VIC 3207",
    "addr:housenumber":"195",
    "addr:postcode":"3207",
    "addr:street":"Bay St",
    "iso:country":"AU",
    "sg:address":"195 Bay St",
    "sg:city":"Port Melbourne",
    "sg:classifiers":[
        {
            "category":"Shopping",
            "subcategory":"Clothing, Apparel, & Fashions",
            "type":"Retail Goods"
        }
    ],
    "sg:phone":"+61 3 9646 6151",
    "sg:postcode":"3207",
    "sg:province":"VIC",
    "sg:tags":[
        "lingerie",
        "hosiery",
        "sleepwear"
    ],
    "wof:name":"Happy Bodies",
    "wof:placetype":"venue"
},
  "geometry": {"coordinates":[144.94172699999999,-37.839016],"type":"Point"}
}