{
  "type": "Feature",
  "properties": {
    "addr:full":"84 Woolwich St West Leederville WA 6007",
    "addr:housenumber":"84",
    "addr:postcode":"6007",
    "addr:street":"Woolwich St West",
    "iso:country":"AU",
    "sg:address":"84 Woolwich St",
    "sg:city":"West Leederville",
    "sg:classifiers":[
        {
            "category":"Deli",
            "type":"Food & Drink"
        }
    ],
    "sg:phone":"+61 8 9381 1849",
    "sg:postcode":"6007",
    "sg:province":"WA",
    "sg:tags":[
        "delicatessen"
    ],
    "wof:name":"Woolwich St Deli",
    "wof:placetype":"venue"
},
  "geometry": {"coordinates":[115.83541870099999,-31.9385681152],"type":"Point"}
}