{
  "type": "Feature",
  "properties": {
    "addr:full":"28 Futura Rd Keysborough VIC 3173",
    "addr:housenumber":"28",
    "addr:postcode":"3173",
    "addr:street":"Futura Rd",
    "iso:country":"AU",
    "sg:address":"28 Futura Rd",
    "sg:city":"Keysborough",
    "sg:classifiers":[
        {
            "category":"Wholesale",
            "subcategory":"Scrap",
            "type":"Manufacturing & Wholesale Goods"
        }
    ],
    "sg:phone":"+61 3 9798 3364",
    "sg:postcode":"3173",
    "sg:province":"VIC",
    "sg:tags":[
        "merchant",
        "metal"
    ],
    "wof:name":"Old Cars Removed",
    "wof:placetype":"venue"
},
  "geometry": {"coordinates":[145.18911743199999,-37.9864807129],"type":"Point"}
}