{
  "type": "Feature",
  "properties": {
    "iso:country":"AU",
    "sg:address":"Cnr Albert Rd & Lewis St",
    "sg:city":"Mordialloc",
    "sg:classifiers":[
        {
            "category":"Arena",
            "subcategory":"Sports Club",
            "type":"Entertainment"
        }
    ],
    "sg:phone":"+61 3 9558 6438",
    "sg:postcode":"3195",
    "sg:province":"VIC",
    "sg:tags":[
        "defence",
        "supply",
        "self",
        "instruction",
        "martial art"
    ],
    "wof:name":"Liang-I Lifestyle Kung-Fu",
    "wof:placetype":"venue"
},
  "geometry": {"coordinates":[145.08700561500001,-38.0038032532],"type":"Point"}
}