{
  "type": "Feature",
  "properties": {
    "addr:full":"140 Beaconsfield St Revesby NSW 2212",
    "addr:housenumber":"140",
    "addr:postcode":"2212",
    "addr:street":"Beaconsfield St",
    "iso:country":"AU",
    "sg:address":"140 Beaconsfield St",
    "sg:city":"Revesby",
    "sg:classifiers":[
        {
            "category":"Professional",
            "subcategory":"Engineering",
            "type":"Services"
        }
    ],
    "sg:phone":"+61 2 9820 1900",
    "sg:postcode":"2212",
    "sg:province":"NSW",
    "sg:tags":[
        "manufacturing",
        "engineer"
    ],
    "wof:name":"Precision Automation & Robotics",
    "wof:placetype":"venue"
},
  "geometry": {"coordinates":[150.99992399999999,-33.942303],"type":"Point"}
}