{
  "type": "Feature",
  "properties": {
    "addr:full":"118 McNaught Rd Caboolture QLD 4510",
    "addr:housenumber":"118",
    "addr:postcode":"4510",
    "addr:street":"Mcnaught Rd",
    "iso:country":"AU",
    "sg:address":"118 McNaught Rd",
    "sg:city":"Caboolture",
    "sg:classifiers":[
        {
            "category":"Retail",
            "subcategory":"Auto Rental",
            "type":"Services"
        }
    ],
    "sg:phone":"+61 7 5428 2259",
    "sg:postcode":"4510",
    "sg:province":"QLD",
    "sg:tags":[
        "camper-trailers",
        "caravan",
        "hire"
    ],
    "wof:name":"Dell T & L",
    "wof:placetype":"venue"
},
  "geometry": {"coordinates":[152.98817399999999,-27.079252],"type":"Point"}
}