{
  "type": "Feature",
  "properties": {
    "iso:country":"AU",
    "sg:address":"240 Lavarack Ave",
    "sg:city":"Eagle Farm",
    "sg:classifiers":[
        {
            "category":"Building & Trades",
            "subcategory":"Equipment Rental",
            "type":"Services"
        }
    ],
    "sg:phone":"+61 7 3621 1007",
    "sg:postcode":"4009",
    "sg:province":"QLD",
    "sg:tags":[
        "builder",
        "contractor"
    ],
    "wof:name":"Ancon CCL",
    "wof:placetype":"venue"
},
  "geometry": {"coordinates":[153.10568237300001,-27.4319667816],"type":"Point"}
}