{
  "type": "Feature",
  "properties": {
    "iso:country":"AU",
    "sg:address":"3/ 3 Douglas Pl",
    "sg:city":"Barragup",
    "sg:classifiers":[
        {
            "category":"Building & Trades",
            "subcategory":"Plumbing",
            "type":"Services"
        }
    ],
    "sg:phone":"+61 8 9534 9810",
    "sg:postcode":"6210",
    "sg:province":"WA",
    "sg:tags":[
        "pump",
        "repairer"
    ],
    "wof:name":"Southern Motor Rewinds",
    "wof:placetype":"venue"
},
  "geometry": {"coordinates":[115.77629899999999,-32.548889],"type":"Point"}
}