{
  "type": "Feature",
  "properties": {
    "addr:full":"Shop 157, Forest Hill Chase, 270 Canterbury Rd Forest Hill VIC 3131",
    "addr:housenumber":"157;270",
    "addr:postcode":"3131",
    "addr:street":"Forest Hill Chase;Canterbury Rd",
    "iso:country":"AU",
    "sg:address":"Shop 157, Forest Hill Chase, 270 Canterbury Rd",
    "sg:city":"Forest Hill",
    "sg:classifiers":[
        {
            "category":"Health Services",
            "subcategory":"Optometrist",
            "type":"Services"
        }
    ],
    "sg:phone":"+61 3 9878 1922",
    "sg:postcode":"3131",
    "sg:province":"VIC",
    "wof:name":"Laubman & Pank",
    "wof:placetype":"venue"
},
  "geometry": {"coordinates":[145.173065186,-37.8350105286],"type":"Point"}
}