{
  "type": "Feature",
  "properties": {
    "iso:country":"AU",
    "sg:address":"51 Albert Rd",
    "sg:city":"Middle Swan",
    "sg:classifiers":[
        {
            "category":"Organizations",
            "subcategory":"Membership Organization",
            "type":"Services"
        }
    ],
    "sg:phone":"+61 8 9274 3038",
    "sg:postcode":"6056",
    "sg:province":"WA",
    "sg:tags":[
        "club",
        "car"
    ],
    "wof:name":"WA Omnibus Group Inc",
    "wof:placetype":"venue"
},
  "geometry": {"coordinates":[116.026657105,-31.8612289429],"type":"Point"}
}