{
  "type": "Feature",
  "properties": {
    "iso:country":"AU",
    "sg:address":"277b Lawrence Hargrave Drv",
    "sg:city":"Thirroul",
    "sg:classifiers":[
        {
            "category":"Food & Beverages",
            "subcategory":"Bakery",
            "type":"Retail Goods"
        }
    ],
    "sg:phone":"+61 2 4268 2044",
    "sg:postcode":"2515",
    "sg:province":"NSW",
    "sg:tags":[
        "baker"
    ],
    "wof:name":"Sanhhuy Bakery",
    "wof:placetype":"venue"
},
  "geometry": {"coordinates":[150.92344700000001,-34.314926],"type":"Point"}
}