{
  "type": "Feature",
  "properties": {
    "addr:full":"39 Laura St Lutwyche QLD 4030",
    "addr:housenumber":"39",
    "addr:postcode":"4030",
    "addr:street":"Laura St",
    "iso:country":"AU",
    "sg:address":"39 Laura St",
    "sg:city":"Lutwyche",
    "sg:classifiers":[
        {
            "category":"Sports & Exercise",
            "subcategory":"Sports Center",
            "type":"Entertainment"
        }
    ],
    "sg:phone":"+61 7 3857 2922",
    "sg:postcode":"4030",
    "sg:province":"QLD",
    "sg:tags":[
        "coach",
        "tennis"
    ],
    "wof:name":"Fancutts",
    "wof:placetype":"venue"
},
  "geometry": {"coordinates":[153.036179,-27.423477],"type":"Point"}
}