{
  "type": "Feature",
  "properties": {
    "iso:country":"AU",
    "sg:address":"9 Elder St",
    "sg:city":"Alice Springs",
    "sg:classifiers":[
        {
            "category":"Retail",
            "subcategory":"Storage",
            "type":"Services"
        }
    ],
    "sg:phone":"+61 8 8952 2433",
    "sg:postcode":"0870",
    "sg:province":"NT",
    "sg:tags":[
        "removal",
        "furniture"
    ],
    "wof:name":"Grace Removals Group",
    "wof:placetype":"venue"
},
  "geometry": {"coordinates":[133.87103271500001,-23.698923111],"type":"Point"}
}