{
  "type": "Feature",
  "properties": {
    "iso:country":"AU",
    "sg:address":"8 Anomaly St",
    "sg:city":"Moolap",
    "sg:classifiers":[
        {
            "category":"Professional",
            "subcategory":"Printing & Photocopies",
            "type":"Services"
        }
    ],
    "sg:phone":"+61 3 5248 0403",
    "sg:postcode":"3221",
    "sg:province":"VIC",
    "sg:tags":[
        "screen",
        "printer"
    ],
    "wof:name":"National Signs & Flags",
    "wof:placetype":"venue"
},
  "geometry": {"coordinates":[144.412567,-38.164574],"type":"Point"}
}