{
  "type": "Feature",
  "properties": {
    "iso:country":"AU",
    "sg:address":"50 Point Henry Rd",
    "sg:city":"Moolap",
    "sg:classifiers":[
        {
            "category":"Home & Garden",
            "subcategory":"Garden Supply",
            "type":"Retail Goods"
        }
    ],
    "sg:phone":"+61 3 5248 0324",
    "sg:postcode":"3221",
    "sg:province":"VIC",
    "sg:tags":[
        "equipment"
    ],
    "wof:name":"Mulch 1",
    "wof:placetype":"venue"
},
  "geometry": {"coordinates":[144.426727,-38.163795],"type":"Point"}
}