{
  "type": "Feature",
  "properties": {
    "iso:country":"AU",
    "sg:address":"14 Alice St",
    "sg:city":"Mirani",
    "sg:classifiers":[
        {
            "category":"Freight",
            "type":"Transportation"
        }
    ],
    "sg:phone":"+61 7 4959 1603",
    "sg:postcode":"4754",
    "sg:province":"QLD",
    "sg:tags":[
        "light",
        "carrier"
    ],
    "wof:name":"Pioneer Valley Carriers",
    "wof:placetype":"venue"
},
  "geometry": {"coordinates":[148.86390700000001,-21.157364],"type":"Point"}
}