{
  "type": "Feature",
  "properties": {
    "iso:country":"AU",
    "sg:address":"4 Mooroondu Rd",
    "sg:city":"Thorneside",
    "sg:classifiers":[
        {
            "category":"Building & Trades",
            "subcategory":"Construction",
            "type":"Services"
        }
    ],
    "sg:phone":"+61 418 882 363",
    "sg:postcode":"4158",
    "sg:province":"QLD",
    "sg:tags":[
        "contractor"
    ],
    "wof:name":"Blatchford T G",
    "wof:placetype":"venue"
},
  "geometry": {"coordinates":[153.199462891,-27.4754009247],"type":"Point"}
}