{
  "type": "Feature",
  "properties": {
    "addr:full":"6 Little St Camden NSW 2570",
    "addr:housenumber":"6",
    "addr:postcode":"2570",
    "addr:street":"Little St",
    "iso:country":"AU",
    "sg:address":"6 Little St",
    "sg:city":"Camden",
    "sg:classifiers":[
        {
            "category":"Building & Trades",
            "subcategory":"Construction",
            "type":"Services"
        }
    ],
    "sg:phone":"+61 419 416 089",
    "sg:postcode":"2570",
    "sg:province":"NSW",
    "sg:tags":[
        "welding"
    ],
    "wof:name":"Modis Pty Ltd",
    "wof:placetype":"venue"
},
  "geometry": {"coordinates":[150.692962647,-34.0593414307],"type":"Point"}
}