{
  "type": "Feature",
  "properties": {
    "addr:full":"44 Kathleen St Trigg WA 6029",
    "addr:housenumber":"44",
    "addr:postcode":"6029",
    "addr:street":"Kathleen St",
    "iso:country":"AU",
    "sg:address":"44 Kathleen St",
    "sg:city":"Trigg",
    "sg:classifiers":[
        {
            "category":"Shopping",
            "subcategory":"Antiques",
            "type":"Retail Goods"
        }
    ],
    "sg:phone":"+61 8 9447 3276",
    "sg:postcode":"6029",
    "sg:province":"WA",
    "wof:name":"Wisma Antik",
    "wof:placetype":"venue"
},
  "geometry": {"coordinates":[115.75670623800001,-31.8735752106],"type":"Point"}
}