{
  "type": "Feature",
  "properties": {
    "addr:full":"102 Cooper St Stawell VIC 3380",
    "addr:housenumber":"102",
    "addr:postcode":"3380",
    "addr:street":"Cooper St",
    "iso:country":"AU",
    "sg:address":"102 Cooper St",
    "sg:city":"Stawell",
    "sg:classifiers":[
        {
            "category":"Train Station",
            "subcategory":"Light Rail",
            "type":"Transportation"
        }
    ],
    "sg:phone":"+61 3 5358 1500",
    "sg:postcode":"3380",
    "sg:province":"VIC",
    "sg:tags":[
        "equipment",
        "energy",
        "solar"
    ],
    "wof:name":"Midwest Solar & Automation",
    "wof:placetype":"venue"
},
  "geometry": {"coordinates":[142.77381897000001,-37.0663414001],"type":"Point"}
}