{
  "type": "Feature",
  "properties": {
    "addr:full":"28 Kitchener St North Beach WA 6020",
    "addr:housenumber":"28",
    "addr:postcode":"6020",
    "addr:street":"Kitchener St",
    "iso:country":"AU",
    "sg:address":"28 Kitchener St",
    "sg:city":"North Beach",
    "sg:classifiers":[
        {
            "category":"Social Services",
            "subcategory":"Retirement Home",
            "type":"Services"
        }
    ],
    "sg:phone":"+61 409 004 265",
    "sg:postcode":"6020",
    "sg:province":"WA",
    "sg:tags":[
        "environmental",
        "consultant",
        "pollution"
    ],
    "wof:name":"EcoNord Pty Ltd",
    "wof:placetype":"venue"
},
  "geometry": {"coordinates":[115.757843018,-31.8652935028],"type":"Point"}
}