{
  "type": "Feature",
  "properties": {
    "addr:full":"23 Faulkner Ave Belmont WA 6104",
    "addr:housenumber":"23",
    "addr:postcode":"6104",
    "addr:street":"Faulkner Ave",
    "iso:country":"AU",
    "sg:address":"23 Faulkner Ave",
    "sg:city":"Belmont",
    "sg:classifiers":[
        {
            "category":"Retail",
            "subcategory":"Auto Repair",
            "type":"Services"
        }
    ],
    "sg:phone":"+61 8 9479 1830",
    "sg:postcode":"6104",
    "sg:province":"WA",
    "sg:tags":[
        "wheel",
        "balancing",
        "alignment"
    ],
    "wof:name":"M & D Mechanical & Suspension Repairs",
    "wof:placetype":"venue"
},
  "geometry": {"coordinates":[115.925178528,-31.9539394379],"type":"Point"}
}