{
  "type": "Feature",
  "properties": {
    "addr:full":"413 Golden Four Drv Tugun QLD 4224",
    "addr:housenumber":"413",
    "addr:postcode":"4224",
    "addr:street":"Golden Four Drv",
    "iso:country":"AU",
    "sg:address":"413 Golden Four Drv",
    "sg:city":"Tugun",
    "sg:classifiers":[
        {
            "category":"Professional",
            "subcategory":"Art Services",
            "type":"Services"
        }
    ],
    "sg:phone":"+61 7 5534 7062",
    "sg:postcode":"4224",
    "sg:province":"QLD",
    "sg:tags":[
        "artist"
    ],
    "wof:name":"Gc Magic",
    "wof:placetype":"venue"
},
  "geometry": {"coordinates":[153.49671935999999,-28.1449146271],"type":"Point"}
}