{
  "type": "Feature",
  "properties": {
    "addr:full":"Kinross St Long Gully VIC 3550",
    "addr:postcode":"3550",
    "addr:street":"Kinross St Long",
    "iso:country":"AU",
    "sg:address":"Kinross St",
    "sg:city":"Long Gully",
    "sg:classifiers":[
        {
            "category":"Building & Trades",
            "subcategory":"Equipment Rental",
            "type":"Services"
        }
    ],
    "sg:phone":"+61 3 5441 6322",
    "sg:postcode":"3550",
    "sg:province":"VIC",
    "sg:tags":[
        "crane",
        "hire"
    ],
    "wof:name":"Leech J J & Sons (Aust) Pty Ltd",
    "wof:placetype":"venue"
},
  "geometry": {"coordinates":[144.26271057100001,-36.7398719788],"type":"Point"}
}