{
  "type": "Feature",
  "properties": {
    "iso:country":"AU",
    "sg:address":"Lot 3/ 84 Cocos Drv",
    "sg:city":"Bibra Lake",
    "sg:classifiers":[
        {
            "category":"Building & Trades",
            "subcategory":"Construction",
            "type":"Services"
        }
    ],
    "sg:phone":"+61 408 589 088",
    "sg:postcode":"6163",
    "sg:province":"WA",
    "sg:tags":[
        "insulation",
        "contractor"
    ],
    "wof:name":"I.S.F. Contracting",
    "wof:placetype":"venue"
},
  "geometry": {"coordinates":[115.816307,-32.110069],"type":"Point"}
}