{
  "type": "Feature",
  "properties": {
    "addr:full":"256 Swan St Richmond VIC 3121",
    "addr:housenumber":"256",
    "addr:postcode":"3121",
    "addr:street":"Swan St",
    "iso:country":"AU",
    "sg:address":"256 Swan St",
    "sg:city":"Richmond",
    "sg:classifiers":[
        {
            "category":"Cafe",
            "type":"Food & Drink"
        }
    ],
    "sg:phone":"+61 3 9421 0510",
    "sg:postcode":"3121",
    "sg:province":"VIC",
    "wof:name":"Grandma Funks",
    "wof:placetype":"venue"
},
  "geometry": {"coordinates":[144.99882507300001,-37.8258895874],"type":"Point"}
}