{
  "type": "Feature",
  "properties": {
    "addr:full":"42 Bilkurra St Queanbeyan ACT 2620",
    "addr:housenumber":"42",
    "addr:postcode":"2620",
    "addr:street":"Bilkurra St",
    "iso:country":"AU",
    "sg:address":"42 Bilkurra St",
    "sg:city":"Queanbeyan",
    "sg:classifiers":[
        {
            "category":"Mining & Drilling",
            "type":"Manufacturing & Wholesale Goods"
        }
    ],
    "sg:phone":"+61 2 6298 1209",
    "sg:postcode":"2620",
    "sg:province":"ACT",
    "sg:tags":[
        "concrete",
        "breaking",
        "grinding",
        "sawing"
    ],
    "wof:name":"Twin Cities Sawing & Drilling",
    "wof:placetype":"venue"
},
  "geometry": {"coordinates":[149.20423889200001,-35.3640937805],"type":"Point"}
}