{
  "type": "Feature",
  "properties": {
    "iso:country":"AU",
    "sg:address":"12 Ellen St",
    "sg:city":"Subiaco",
    "sg:classifiers":[
        {
            "category":"Health Services",
            "subcategory":"Doctor",
            "type":"Services"
        }
    ],
    "sg:phone":"+61 8 9381 5677",
    "sg:postcode":"6008",
    "sg:province":"WA",
    "sg:tags":[
        "medical",
        "practitioner"
    ],
    "wof:name":"Henderson Sandra",
    "wof:placetype":"venue"
},
  "geometry": {"coordinates":[115.83009338399999,-31.9464969635],"type":"Point"}
}