{
  "type": "Feature",
  "properties": {
    "addr:full":"66 Gracie St North Melbourne VIC 3051",
    "addr:housenumber":"66",
    "addr:postcode":"3051",
    "addr:street":"Gracie St",
    "iso:country":"AU",
    "sg:address":"66 Gracie St",
    "sg:city":"North Melbourne",
    "sg:classifiers":[
        {
            "category":"Building & Trades",
            "subcategory":"Construction",
            "type":"Services"
        }
    ],
    "sg:phone":"+61 3 9326 5288",
    "sg:postcode":"3051",
    "sg:province":"VIC",
    "sg:tags":[
        "equipment",
        "balancing"
    ],
    "wof:name":"Universal Driveshaft Services Pty Ltd",
    "wof:placetype":"venue"
},
  "geometry": {"coordinates":[144.93875122099999,-37.797252655],"type":"Point"}
}