{
  "type": "Feature",
  "properties": {
    "addr:full":"Mudgee Rd Lidsdale NSW 2790",
    "addr:postcode":"2790",
    "addr:street":"Mudgee Rd",
    "iso:country":"AU",
    "sg:address":"Mudgee Rd",
    "sg:city":"Lidsdale",
    "sg:classifiers":[
        {
            "category":"Mining & Drilling",
            "type":"Manufacturing & Wholesale Goods"
        }
    ],
    "sg:phone":"+61 2 6350 1600",
    "sg:postcode":"2790",
    "sg:province":"NSW",
    "sg:tags":[
        "colliery"
    ],
    "wof:name":"Springvale Colliery",
    "wof:placetype":"venue"
},
  "geometry": {"coordinates":[150.12234497099999,-33.5106124878],"type":"Point"}
}