{
  "type": "Feature",
  "properties": {
    "iso:country":"AU",
    "sg:address":"26 Fourth Ave",
    "sg:city":"Seven Hills",
    "sg:classifiers":[
        {
            "category":"Professional",
            "subcategory":"Detective & Security Services",
            "type":"Services"
        }
    ],
    "sg:phone":"+61 2 9831 8065",
    "sg:postcode":"2147",
    "sg:province":"NSW",
    "sg:tags":[
        "domestic",
        "alarm",
        "commercial",
        "burglar"
    ],
    "wof:name":"Koph Trading Pty Ltd",
    "wof:placetype":"venue"
},
  "geometry": {"coordinates":[150.940917969,-33.7774467468],"type":"Point"}
}