{
  "type": "Feature",
  "properties": {
    "addr:full":"12 Junction St Woollahra NSW 2025",
    "addr:housenumber":"12",
    "addr:postcode":"2025",
    "addr:street":"Junction St",
    "iso:country":"AU",
    "sg:address":"12 Junction St",
    "sg:city":"Woollahra",
    "sg:classifiers":[
        {
            "category":"Health Services",
            "subcategory":"Health Practitioner",
            "type":"Services"
        }
    ],
    "sg:phone":"+61 2 9389 4512",
    "sg:postcode":"2025",
    "sg:province":"NSW",
    "sg:tags":[
        "psychologist"
    ],
    "wof:name":"Luiker Henry Dr",
    "wof:placetype":"venue"
},
  "geometry": {"coordinates":[151.250442505,-33.8903274536],"type":"Point"}
}