{
  "type": "Feature",
  "properties": {
    "addr:full":"5 O&#039;Donnell St Reservoir VIC 3073",
    "addr:housenumber":"5",
    "addr:postcode":"3073",
    "addr:street":"Donnell St",
    "iso:country":"AU",
    "sg:address":"5 O&#039;Donnell St",
    "sg:city":"Reservoir",
    "sg:classifiers":[
        {
            "category":"Building & Trades",
            "subcategory":"Construction",
            "type":"Services"
        }
    ],
    "sg:phone":"+61 3 9460 6869",
    "sg:postcode":"3073",
    "sg:province":"VIC",
    "sg:tags":[
        "joiner",
        "carpenter"
    ],
    "wof:name":"Bressan G",
    "wof:placetype":"venue"
},
  "geometry": {"coordinates":[144.99641418499999,-37.7067070007],"type":"Point"}
}