{
  "type": "Feature",
  "properties": {
    "addr:full":"34 Mileham St Windsor NSW 2756",
    "addr:housenumber":"34",
    "addr:postcode":"2756",
    "addr:street":"Mileham St",
    "iso:country":"AU",
    "sg:address":"34 Mileham St",
    "sg:city":"Windsor",
    "sg:classifiers":[
        {
            "category":"Building & Trades",
            "subcategory":"Construction",
            "type":"Services"
        }
    ],
    "sg:phone":"+61 410 632 001",
    "sg:postcode":"2756",
    "sg:province":"NSW",
    "sg:tags":[
        "fencing",
        "contractor"
    ],
    "wof:name":"Sunline Fence n Sails",
    "wof:placetype":"venue"
},
  "geometry": {"coordinates":[150.81439209000001,-33.6147422791],"type":"Point"}
}