{
  "type": "Feature",
  "properties": {
    "addr:full":"473a Neerim Rd Murrumbeena VIC 3163",
    "addr:housenumber":"473a",
    "addr:postcode":"3163",
    "addr:street":"Neerim Rd",
    "iso:country":"AU",
    "sg:address":"473a Neerim Rd",
    "sg:city":"Murrumbeena",
    "sg:classifiers":[
        {
            "category":"Retail",
            "subcategory":"Auto Repair",
            "type":"Services"
        }
    ],
    "sg:phone":"+61 3 9569 8354",
    "sg:postcode":"3163",
    "sg:province":"VIC",
    "sg:tags":[
        "repairer",
        "motor",
        "engineer"
    ],
    "wof:name":"Billy One Motors",
    "wof:placetype":"venue"
},
  "geometry": {"coordinates":[145.06951904300001,-37.8908691406],"type":"Point"}
}