{
  "type": "Feature",
  "properties": {
    "iso:country":"AU",
    "sg:address":"Carngham Rd",
    "sg:city":"Ballarat",
    "sg:phone":"+61 3 5335 8741",
    "sg:postcode":"3350",
    "sg:province":"VIC",
    "wof:name":"Icon",
    "wof:placetype":"venue"
},
  "geometry": {"coordinates":[143.85737599999999,-37.581841],"type":"Point"}
}