{
  "type": "Feature",
  "properties": {
    "iso:country":"AU",
    "sg:address":"PO Box 3211",
    "sg:city":"South Brisbane BC",
    "sg:classifiers":[
        {
            "category":"Professional",
            "subcategory":"Business Services",
            "type":"Services"
        }
    ],
    "sg:phone":"+61 7 3255 3388",
    "sg:postcode":"4101",
    "sg:province":"QLD",
    "sg:tags":[
        "drafting"
    ],
    "wof:name":"A E C Australia Pty Ltd",
    "wof:placetype":"venue"
},
  "geometry": {"coordinates":[153.01156616200001,-27.4743995667],"type":"Point"}
}