{
  "type": "Feature",
  "properties": {
    "addr:full":"19-21 Nevin Drv Thomastown VIC 3074",
    "addr:housenumber":"19-21",
    "addr:postcode":"3074",
    "addr:street":"Nevin Drv",
    "iso:country":"AU",
    "sg:address":"19-21 Nevin Drv",
    "sg:city":"Thomastown",
    "sg:classifiers":[
        {
            "category":"Manufacturing",
            "subcategory":"Food",
            "type":"Manufacturing & Wholesale Goods"
        }
    ],
    "sg:phone":"+61 3 9465 0065",
    "sg:postcode":"3074",
    "sg:province":"VIC",
    "sg:tags":[
        "product",
        "nut",
        "edible"
    ],
    "wof:name":"Mama Alice Holdings",
    "wof:placetype":"venue"
},
  "geometry": {"coordinates":[145.033447266,-37.6950683594],"type":"Point"}
}