{
  "type": "Feature",
  "properties": {
    "addr:full":"8 Teeton Crt Highett VIC 3190",
    "addr:housenumber":"8",
    "addr:postcode":"3190",
    "addr:street":"Teeton Crt",
    "iso:country":"AU",
    "sg:address":"8 Teeton Crt",
    "sg:city":"Highett",
    "sg:classifiers":[
        {
            "category":"Wholesale",
            "subcategory":"Non-durable Goods",
            "type":"Manufacturing & Wholesale Goods"
        }
    ],
    "sg:phone":"+61 3 9532 2418",
    "sg:postcode":"3190",
    "sg:province":"VIC",
    "sg:tags":[
        "wholesaler",
        "mfrs",
        "cosmetic"
    ],
    "wof:name":"Natural Beauty Care Pty Ltd",
    "wof:placetype":"venue"
},
  "geometry": {"coordinates":[145.05307006800001,-37.9490737915],"type":"Point"}
}