{
  "type": "Feature",
  "properties": {
    "iso:country":"AU",
    "sg:address":"Steps Dance Centre Moris Rd",
    "sg:city":"West Rothwell",
    "sg:classifiers":[
        {
            "category":"Health Services",
            "subcategory":"Health Practitioner",
            "type":"Services"
        }
    ],
    "sg:phone":"+61 7 3204 6388",
    "sg:postcode":"4022",
    "sg:province":"QLD",
    "sg:tags":[
        "physiotherapist"
    ],
    "wof:name":"Turner Mark",
    "wof:placetype":"venue"
},
  "geometry": {"coordinates":[153.053238,-27.21529],"type":"Point"}
}