{
  "type": "Feature",
  "properties": {
    "addr:full":"5 Industrial Park Drv Lilydale VIC 3140",
    "addr:housenumber":"5",
    "addr:postcode":"3140",
    "addr:street":"Industrial Park Drv",
    "iso:country":"AU",
    "sg:address":"5 Industrial Park Drv",
    "sg:city":"Lilydale",
    "sg:classifiers":[
        {
            "category":"Banks & Credit Unions",
            "subcategory":"Bureau De Change",
            "type":"Services"
        }
    ],
    "sg:phone":"+61 1300 307 795",
    "sg:postcode":"3140",
    "sg:province":"VIC",
    "sg:tags":[
        "gas",
        "natural",
        "lp",
        "equipment"
    ],
    "wof:name":"Blue LPG Tanks Kits & Accessories",
    "wof:placetype":"venue"
},
  "geometry": {"coordinates":[145.34883117699999,-37.7509422302],"type":"Point"}
}