{
  "type": "Feature",
  "properties": {
    "addr:full":"157 Park Rd Cheltenham VIC 3192",
    "addr:housenumber":"157",
    "addr:postcode":"3192",
    "addr:street":"Park Rd",
    "iso:country":"AU",
    "sg:address":"157 Park Rd",
    "sg:city":"Cheltenham",
    "sg:classifiers":[
        {
            "category":"Education",
            "subcategory":"Special Training",
            "type":"Public Place"
        }
    ],
    "sg:phone":"+61 3 9585 5188",
    "sg:postcode":"3192",
    "sg:province":"VIC",
    "sg:tags":[
        "development"
    ],
    "wof:name":"Coaching For Results",
    "wof:placetype":"venue"
},
  "geometry": {"coordinates":[145.05548095699999,-37.9652366638],"type":"Point"}
}