{
  "type": "Feature",
  "properties": {
    "iso:country":"AU",
    "sg:address":"suite 8 2B Edward St",
    "sg:city":"Kingsgrove",
    "sg:classifiers":[
        {
            "category":"Professional",
            "subcategory":"Art Services",
            "type":"Services"
        }
    ],
    "sg:phone":"+61 2 9150 9466",
    "sg:postcode":"2208",
    "sg:province":"NSW",
    "sg:tags":[
        "graphic",
        "designer"
    ],
    "sg:website":"http://www.dtgraphics.com.au",
    "wof:name":"DT Graphics",
    "wof:placetype":"venue"
},
  "geometry": {"coordinates":[151.102325,-33.943531],"type":"Point"}
}