{
  "type": "Feature",
  "properties": {
    "addr:full":"2 Norwich Rd Rose Bay NSW 2029",
    "addr:housenumber":"2",
    "addr:postcode":"2029",
    "addr:street":"Norwich Rd",
    "iso:country":"AU",
    "sg:address":"2 Norwich Rd",
    "sg:city":"Rose Bay",
    "sg:classifiers":[
        {
            "category":"Personal",
            "subcategory":"Skin Care",
            "type":"Services"
        }
    ],
    "sg:phone":"+61 2 9371 9968",
    "sg:postcode":"2029",
    "sg:province":"NSW",
    "sg:tags":[
        "information",
        "treatment",
        "smoker"
    ],
    "wof:name":"Yeates Lindsay B & Associates",
    "wof:placetype":"venue"
},
  "geometry": {"coordinates":[151.267868042,-33.8714256287],"type":"Point"}
}