{
  "type": "Feature",
  "properties": {
    "addr:full":"199 Frederick Rd Seaton SA 5023",
    "addr:housenumber":"199",
    "addr:postcode":"5023",
    "addr:street":"Frederick Rd",
    "iso:country":"AU",
    "sg:address":"199 Frederick Rd",
    "sg:city":"Seaton",
    "sg:classifiers":[
        {
            "category":"Travel",
            "subcategory":"Hostel",
            "type":"Entertainment"
        }
    ],
    "sg:phone":"+61 8 8353 6054",
    "sg:postcode":"5023",
    "sg:province":"SA",
    "sg:tags":[
        "home"
    ],
    "wof:name":"Aveo Carisfield",
    "wof:placetype":"venue"
},
  "geometry": {"coordinates":[138.505493164,-34.9026565552],"type":"Point"}
}