{
  "type": "Feature",
  "properties": {
    "addr:full":"8 Newcastle St Rose Bay NSW 2029",
    "addr:housenumber":"8",
    "addr:postcode":"2029",
    "addr:street":"Newcastle St",
    "iso:country":"AU",
    "sg:address":"8 Newcastle St",
    "sg:city":"Rose Bay",
    "sg:classifiers":[
        {
            "category":"Real Estate",
            "subcategory":"Real Estate Agent",
            "type":"Services"
        }
    ],
    "sg:phone":"+61 2 9371 6244",
    "sg:postcode":"2029",
    "sg:province":"NSW",
    "wof:name":"Coventry Hall First National",
    "wof:placetype":"venue"
},
  "geometry": {"coordinates":[151.26937866200001,-33.8703308105],"type":"Point"}
}