{
  "type": "Feature",
  "properties": {
    "iso:country":"AU",
    "sg:address":"Factory 1, 399 Old Geelong Rd",
    "sg:city":"Hoppers Crossing",
    "sg:classifiers":[
        {
            "category":"Wholesale",
            "subcategory":"Machinery & Supplies",
            "type":"Manufacturing & Wholesale Goods"
        }
    ],
    "sg:phone":"+61 3 9369 7766",
    "sg:postcode":"3029",
    "sg:province":"VIC",
    "sg:tags":[
        "distributor",
        "crane",
        "mfrs"
    ],
    "wof:name":"A West Crane Services Pty Ltd",
    "wof:placetype":"venue"
},
  "geometry": {"coordinates":[144.729263,-37.869617],"type":"Point"}
}