{
  "type": "Feature",
  "properties": {
    "iso:country":"AU",
    "sg:address":"23 Delaware St",
    "sg:city":"Geebung",
    "sg:classifiers":[
        {
            "category":"Building & Trades",
            "subcategory":"Landscaping Services",
            "type":"Services"
        }
    ],
    "sg:phone":"+61 416 172 225",
    "sg:postcode":"4034",
    "sg:province":"QLD",
    "sg:tags":[
        "designer",
        "landscape",
        "contractor"
    ],
    "wof:name":"A One Landscaping",
    "wof:placetype":"venue"
},
  "geometry": {"coordinates":[153.04377700000001,-27.377518],"type":"Point"}
}