{
  "type": "Feature",
  "properties": {
    "addr:full":"5 Judd Ave Merrigum VIC 3618",
    "addr:housenumber":"5",
    "addr:postcode":"3618",
    "addr:street":"Judd Ave",
    "iso:country":"AU",
    "sg:address":"5 Judd Ave",
    "sg:city":"Merrigum",
    "sg:classifiers":[
        {
            "category":"Building & Trades",
            "subcategory":"Construction",
            "type":"Services"
        }
    ],
    "sg:phone":"+61 3 5855 2495",
    "sg:postcode":"3618",
    "sg:province":"VIC",
    "sg:tags":[
        "contractor"
    ],
    "wof:name":"Henderson A G & V M",
    "wof:placetype":"venue"
},
  "geometry": {"coordinates":[145.13142395,-36.3690872192],"type":"Point"}
}