{
  "type": "Feature",
  "properties": {
    "iso:country":"AU",
    "sg:address":"19 Primrose St",
    "sg:city":"Violet Town",
    "sg:classifiers":[
        {
            "category":"Farming",
            "subcategory":"Farm",
            "type":"Manufacturing & Wholesale Goods"
        }
    ],
    "sg:phone":"+61 3 5798 1295",
    "sg:postcode":"3669",
    "sg:province":"VIC",
    "sg:tags":[
        "farmer"
    ],
    "wof:name":"Palmer N M",
    "wof:placetype":"venue"
},
  "geometry": {"coordinates":[145.71621704099999,-36.6395111084],"type":"Point"}
}