{
  "type": "Feature",
  "properties": {
    "addr:full":"290 Lennox St Richmond VIC 3121",
    "addr:housenumber":"290",
    "addr:postcode":"3121",
    "addr:street":"Lennox St",
    "iso:country":"AU",
    "sg:address":"290 Lennox St",
    "sg:city":"Richmond",
    "sg:classifiers":[
        {
            "category":"Health Services",
            "subcategory":"Health Practitioner",
            "type":"Services"
        }
    ],
    "sg:phone":"+61 3 9429 5860",
    "sg:postcode":"3121",
    "sg:province":"VIC",
    "sg:tags":[
        "psychologist"
    ],
    "wof:name":"Moore Paul L",
    "wof:placetype":"venue"
},
  "geometry": {"coordinates":[144.99342346200001,-37.823928833],"type":"Point"}
}