{
  "type": "Feature",
  "properties": {
    "addr:full":"466 Swift St Albury NSW 2640",
    "addr:housenumber":"466",
    "addr:postcode":"2640",
    "addr:street":"Swift St",
    "iso:country":"AU",
    "sg:address":"466 Swift St",
    "sg:city":"Albury",
    "sg:classifiers":[
        {
            "category":"Professional",
            "subcategory":"Accounting & Tax Preparation",
            "type":"Services"
        }
    ],
    "sg:phone":"+61 2 6022 0700",
    "sg:postcode":"2640",
    "sg:province":"NSW",
    "sg:tags":[
        "accountant",
        "auditor"
    ],
    "wof:name":"Briese Janissen & Associates",
    "wof:placetype":"venue"
},
  "geometry": {"coordinates":[146.916305542,-36.0787849426],"type":"Point"}
}