{
  "type": "Feature",
  "properties": {
    "addr:full":"9 Gregory St Sandy Bay TAS 7005",
    "addr:housenumber":"9",
    "addr:postcode":"7005",
    "addr:street":"Gregory St",
    "iso:country":"AU",
    "sg:address":"9 Gregory St",
    "sg:city":"Sandy Bay",
    "sg:classifiers":[
        {
            "category":"Health Services",
            "subcategory":"Dentist",
            "type":"Services"
        }
    ],
    "sg:phone":"+61 3 6223 5514",
    "sg:postcode":"7005",
    "sg:province":"TAS",
    "wof:name":"Rushton Jim",
    "wof:placetype":"venue"
},
  "geometry": {"coordinates":[147.32699585,-42.8957901001],"type":"Point"}
}