{
  "type": "Feature",
  "properties": {
    "iso:country":"AU",
    "sg:address":"15 Simms Rd",
    "sg:city":"Greensborough",
    "sg:classifiers":[
        {
            "category":"Home & Garden",
            "subcategory":"Building Materials",
            "type":"Retail Goods"
        }
    ],
    "sg:phone":"+61 3 9434 7060",
    "sg:postcode":"3088",
    "sg:province":"VIC",
    "sg:tags":[
        "balustrading"
    ],
    "wof:name":"Eltham Marine Supplies",
    "wof:placetype":"venue"
},
  "geometry": {"coordinates":[145.11340332,-37.7118911743],"type":"Point"}
}