{
  "type": "Feature",
  "properties": {
    "addr:full":"Shp 7, South Windsor Arc+ George St South Windsor NSW 2756",
    "addr:housenumber":"7",
    "addr:postcode":"2756",
    "addr:street":"George St",
    "iso:country":"AU",
    "sg:address":"Shp 7, South Windsor Arc+ George St",
    "sg:city":"South Windsor",
    "sg:classifiers":[
        {
            "category":"Professional",
            "subcategory":"Accounting & Tax Preparation",
            "type":"Services"
        }
    ],
    "sg:phone":"+61 2 4577 4878",
    "sg:postcode":"2756",
    "sg:province":"NSW",
    "sg:tags":[
        "accountant",
        "auditor"
    ],
    "wof:name":"J & S Taxation & Financial Services",
    "wof:placetype":"venue"
},
  "geometry": {"coordinates":[150.80328369099999,-33.6212310791],"type":"Point"}
}