{
  "type": "Feature",
  "properties": {
    "addr:full":"231 Toodyay Rd Middle Swan WA 6056",
    "addr:housenumber":"231",
    "addr:postcode":"6056",
    "addr:street":"Toodyay Rd",
    "iso:country":"AU",
    "sg:address":"231 Toodyay Rd",
    "sg:city":"Middle Swan",
    "sg:classifiers":[
        {
            "category":"Restaurant",
            "type":"Food & Drink"
        }
    ],
    "sg:phone":"+61 8 9250 4755",
    "sg:postcode":"6056",
    "sg:province":"WA",
    "wof:name":"Chapel Farm",
    "wof:placetype":"venue"
},
  "geometry": {"coordinates":[116.03266143800001,-31.8650016785],"type":"Point"}
}