{
  "type": "Feature",
  "properties": {
    "addr:full":"70 Wyatt Rd Cobram East VIC 3644",
    "addr:housenumber":"70",
    "addr:postcode":"3644",
    "addr:street":"Wyatt Rd",
    "iso:country":"AU",
    "sg:address":"70 Wyatt Rd",
    "sg:city":"Cobram East",
    "sg:classifiers":[
        {
            "category":"Farming",
            "subcategory":"Orchard",
            "type":"Manufacturing & Wholesale Goods"
        }
    ],
    "sg:phone":"+61 429 179 639",
    "sg:postcode":"3644",
    "sg:province":"VIC",
    "sg:tags":[
        "citrus",
        "fruit",
        "grower"
    ],
    "wof:name":"Tranquil Hills Orchards",
    "wof:placetype":"venue"
},
  "geometry": {"coordinates":[145.68261718799999,-35.9429779053],"type":"Point"}
}