{
  "type": "Feature",
  "properties": {
    "addr:full":"Shop 4 373 Kent St Maryborough QLD 4650",
    "addr:housenumber":"shop 4 373",
    "addr:postcode":"4650",
    "addr:street":"Kent St",
    "iso:country":"AU",
    "sg:address":"Shop 4 373 Kent St",
    "sg:city":"Maryborough",
    "sg:classifiers":[
        {
            "category":"Education",
            "subcategory":"University",
            "type":"Public Place"
        }
    ],
    "sg:phone":"+61 7 4123 3566",
    "sg:postcode":"4650",
    "sg:province":"QLD",
    "sg:tags":[
        "educational",
        "organisation",
        "cultural"
    ],
    "wof:name":"Eliza Fraser Arts Association Inc",
    "wof:placetype":"venue"
},
  "geometry": {"coordinates":[152.69929500000001,-25.535549],"type":"Point"}
}