{
  "type": "Feature",
  "properties": {
    "addr:full":"19 Taylors Rd Croydon VIC 3136",
    "addr:housenumber":"19",
    "addr:postcode":"3136",
    "addr:street":"Taylors Rd",
    "iso:country":"AU",
    "sg:address":"19 Taylors Rd",
    "sg:city":"Croydon",
    "sg:classifiers":[
        {
            "category":"Building & Trades",
            "subcategory":"Plumbing",
            "type":"Services"
        }
    ],
    "sg:phone":"+61 3 9723 5070",
    "sg:postcode":"3136",
    "sg:province":"VIC",
    "sg:tags":[
        "plumber",
        "gasfitters"
    ],
    "wof:name":"Degenhardt D F",
    "wof:placetype":"venue"
},
  "geometry": {"coordinates":[145.286010742,-37.8071746826],"type":"Point"}
}