{
  "type": "Feature",
  "properties": {
    "addr:full":"3 Dalton Crt Mulgrave VIC 3170",
    "addr:housenumber":"3",
    "addr:postcode":"3170",
    "addr:street":"Dalton Crt",
    "iso:country":"AU",
    "sg:address":"3 Dalton Crt",
    "sg:city":"Mulgrave",
    "sg:classifiers":[
        {
            "category":"Professional",
            "subcategory":"Accounting & Tax Preparation",
            "type":"Services"
        }
    ],
    "sg:phone":"+61 3 9560 7620",
    "sg:postcode":"3170",
    "sg:province":"VIC",
    "sg:tags":[
        "consultant",
        "taxation"
    ],
    "wof:name":"Hydon B T",
    "wof:placetype":"venue"
},
  "geometry": {"coordinates":[145.17175293,-37.9268112183],"type":"Point"}
}