{
  "type": "Feature",
  "properties": {
    "addr:full":"level 1, 55 Grandview St Pymble NSW 2073",
    "addr:housenumber":"55",
    "addr:postcode":"2073",
    "addr:street":"Grandview St",
    "iso:country":"AU",
    "sg:address":"level 1, 55 Grandview St",
    "sg:city":"Pymble",
    "sg:classifiers":[
        {
            "category":"Professional",
            "subcategory":"Employment Agencies",
            "type":"Services"
        }
    ],
    "sg:phone":"+61 2 9988 3999",
    "sg:postcode":"2073",
    "sg:province":"NSW",
    "wof:name":"Motor Staff",
    "wof:placetype":"venue"
},
  "geometry": {"coordinates":[151.14382934599999,-33.744934082],"type":"Point"}
}