{
  "type": "Feature",
  "properties": {
    "addr:full":"937 Old Northern Rd Dural NSW 2158",
    "addr:housenumber":"937",
    "addr:postcode":"2158",
    "addr:street":"Old Northern Rd",
    "iso:country":"AU",
    "sg:address":"937 Old Northern Rd",
    "sg:city":"Dural",
    "sg:classifiers":[
        {
            "category":"Arts & Performance",
            "subcategory":"Art Gallery",
            "type":"Entertainment"
        }
    ],
    "sg:phone":"+61 2 9651 2196",
    "sg:postcode":"2158",
    "sg:province":"NSW",
    "wof:name":"Dural Galleries",
    "wof:placetype":"venue"
},
  "geometry": {"coordinates":[151.027435303,-33.678188324],"type":"Point"}
}