{
  "type": "Feature",
  "properties": {
    "iso:country":"AU",
    "sg:address":"Princes Hwy",
    "sg:city":"Corio",
    "sg:classifiers":[
        {
            "category":"Arena",
            "subcategory":"Sports Club",
            "type":"Entertainment"
        }
    ],
    "sg:phone":"+61 3 5275 2298",
    "sg:postcode":"3214",
    "sg:province":"VIC",
    "sg:tags":[
        "hunt",
        "racing"
    ],
    "wof:name":"Geelong Greyhound Racing Club",
    "wof:placetype":"venue"
},
  "geometry": {"coordinates":[144.3621521,-38.0805892944],"type":"Point"}
}