{
  "type": "Feature",
  "properties": {
    "addr:full":"PO Box 220 Buderim QLD 4556",
    "addr:postcode":"4556",
    "iso:country":"AU",
    "sg:address":"PO Box 220",
    "sg:city":"Buderim",
    "sg:classifiers":[
        {
            "category":"Airline",
            "type":"Transportation"
        }
    ],
    "sg:phone":"+61 7 5445 4388",
    "sg:postcode":"4556",
    "sg:province":"QLD",
    "sg:tags":[
        "agent"
    ],
    "wof:name":"Carrington Travel & Promotions Pty Ltd",
    "wof:placetype":"venue"
},
  "geometry": {"coordinates":[153.05026245100001,-26.6841888428],"type":"Point"}
}