{
  "type": "Feature",
  "properties": {
    "iso:country":"AU",
    "sg:address":"Northern Hwy",
    "sg:city":"Elmore",
    "sg:classifiers":[
        {
            "category":"Communications",
            "subcategory":"News Services",
            "type":"Services"
        }
    ],
    "sg:phone":"+61 3 5432 6646",
    "sg:postcode":"3558",
    "sg:province":"VIC",
    "sg:tags":[
        "information",
        "tourist",
        "attractions"
    ],
    "wof:name":"Campaspe Run",
    "wof:placetype":"venue"
},
  "geometry": {"coordinates":[144.60949707,-36.4930686951],"type":"Point"}
}