{
  "type": "Feature",
  "properties": {
    "addr:full":"Suite13, 41 Wharf St Forster NSW 2428",
    "addr:housenumber":"41",
    "addr:postcode":"2428",
    "addr:street":"Wharf St",
    "iso:country":"AU",
    "sg:address":"Suite13, 41 Wharf St",
    "sg:city":"Forster",
    "sg:classifiers":[
        {
            "category":"Banks & Credit Unions",
            "subcategory":"Financial Services",
            "type":"Services"
        }
    ],
    "sg:phone":"+61 2 6557 2266",
    "sg:postcode":"2428",
    "sg:province":"NSW",
    "sg:tags":[
        "planning"
    ],
    "wof:name":"Dell Greg",
    "wof:placetype":"venue"
},
  "geometry": {"coordinates":[152.511124,-32.180225],"type":"Point"}
}