{
  "type": "Feature",
  "properties": {
    "addr:full":"1a Ti-Tree La Townsend NSW 2463",
    "addr:housenumber":"1a",
    "addr:postcode":"2463",
    "addr:street":"Ti-Tree La Townsend",
    "iso:country":"AU",
    "sg:address":"1a Ti-Tree La",
    "sg:city":"Townsend",
    "sg:classifiers":[
        {
            "category":"Home & Garden",
            "subcategory":"Carpets & Floor Coverings",
            "type":"Retail Goods"
        }
    ],
    "sg:phone":"+61 2 6645 1565",
    "sg:postcode":"2463",
    "sg:province":"NSW",
    "sg:tags":[
        "tile",
        "wall",
        "layer"
    ],
    "wof:name":"Davidson Michael",
    "wof:placetype":"venue"
},
  "geometry": {"coordinates":[153.20953369099999,-29.4657363892],"type":"Point"}
}