{
  "type": "Feature",
  "properties": {
    "addr:full":"18 Nicol St Highett VIC 3190",
    "addr:housenumber":"18",
    "addr:postcode":"3190",
    "addr:street":"Nicol St",
    "iso:country":"AU",
    "sg:address":"18 Nicol St",
    "sg:city":"Highett",
    "sg:classifiers":[
        {
            "category":"Utilities",
            "subcategory":"Electric",
            "type":"Services"
        }
    ],
    "sg:phone":"+61 1800 650 168",
    "sg:postcode":"3190",
    "sg:province":"VIC",
    "sg:tags":[
        "electrical",
        "contractor"
    ],
    "wof:name":"David's Electrical Service",
    "wof:placetype":"venue"
},
  "geometry": {"coordinates":[145.027877808,-37.9496498108],"type":"Point"}
}