{
  "type": "Feature",
  "properties": {
    "addr:full":"68 Barrie Rd Tullamarine VIC 3043",
    "addr:housenumber":"68",
    "addr:postcode":"3043",
    "addr:street":"Barrie Rd",
    "iso:country":"AU",
    "sg:address":"68 Barrie Rd",
    "sg:city":"Tullamarine",
    "sg:classifiers":[
        {
            "category":"Building & Trades",
            "subcategory":"Construction",
            "type":"Services"
        }
    ],
    "sg:phone":"+61 3 9330 3722",
    "sg:postcode":"3043",
    "sg:province":"VIC",
    "sg:tags":[
        "contractor"
    ],
    "sg:website":"http://www.allmore.com.au",
    "wof:name":"Allmore Constructions Pty Ltd",
    "wof:placetype":"venue"
},
  "geometry": {"coordinates":[144.87411499000001,-37.7144203186],"type":"Point"}
}