{
  "type": "Feature",
  "properties": {
    "addr:full":"205 Doveton St South Ballarat VIC 3350",
    "addr:housenumber":"205",
    "addr:postcode":"3350",
    "addr:street":"Doveton St South",
    "iso:country":"AU",
    "sg:address":"205 Doveton St South",
    "sg:city":"Ballarat",
    "sg:classifiers":[
        {
            "category":"Personal",
            "subcategory":"Massage",
            "type":"Services"
        }
    ],
    "sg:phone":"+61 3 5332 7277",
    "sg:postcode":"3350",
    "sg:province":"VIC",
    "sg:tags":[
        "therapy"
    ],
    "wof:name":"Doveton Street Remedial Massage",
    "wof:placetype":"venue"
},
  "geometry": {"coordinates":[143.85411099999999,-37.56628],"type":"Point"}
}