{
  "type": "Feature",
  "properties": {
    "addr:full":"8 View Rd Glen Waverley VIC 3150",
    "addr:housenumber":"8",
    "addr:postcode":"3150",
    "addr:street":"View Rd",
    "iso:country":"AU",
    "sg:address":"8 View Rd",
    "sg:city":"Glen Waverley",
    "sg:classifiers":[
        {
            "category":"Building & Trades",
            "subcategory":"Plumbing",
            "type":"Services"
        }
    ],
    "sg:phone":"+61 3 8802 8450",
    "sg:postcode":"3150",
    "sg:province":"VIC",
    "sg:tags":[
        "plumber",
        "gasfitters"
    ],
    "wof:name":"Firtek Plumbing",
    "wof:placetype":"venue"
},
  "geometry": {"coordinates":[145.16673278799999,-37.8698539734],"type":"Point"}
}