{
  "type": "Feature",
  "properties": {
    "iso:country":"AU",
    "sg:address":"14 Roycliff Crt",
    "sg:city":"Box Hill",
    "sg:classifiers":[
        {
            "category":"Utilities",
            "subcategory":"Electric",
            "type":"Services"
        }
    ],
    "sg:phone":"+61 3 9890 4077",
    "sg:postcode":"3128",
    "sg:province":"VIC",
    "sg:tags":[
        "electrical",
        "contractor"
    ],
    "wof:name":"Box Hill Electrical Service",
    "wof:placetype":"venue"
},
  "geometry": {"coordinates":[145.11805725100001,-37.8054084778],"type":"Point"}
}