{
  "type": "Feature",
  "properties": {
    "addr:full":"Cnr Luke Ave & Parramatta Rd Burwood NSW 2134",
    "addr:postcode":"2134",
    "addr:street":"Cnr Luke Ave & Parramatta Rd",
    "iso:country":"AU",
    "sg:address":"Cnr Luke Ave & Parramatta Rd",
    "sg:city":"Burwood",
    "sg:classifiers":[
        {
            "category":"Autos & Motor Vehicles",
            "subcategory":"Auto Supplies",
            "type":"Retail Goods"
        }
    ],
    "sg:phone":"+61 2 9744 2032",
    "sg:postcode":"2134",
    "sg:province":"NSW",
    "sg:tags":[
        "battery",
        "automotive"
    ],
    "wof:name":"BP Australia Limited",
    "wof:placetype":"venue"
},
  "geometry": {"coordinates":[151.10963439899999,-33.8721923828],"type":"Point"}
}