{
  "type": "Feature",
  "properties": {
    "addr:full":"25 Trevelyan St Elsternwick VIC 3185",
    "addr:housenumber":"25",
    "addr:postcode":"3185",
    "addr:street":"Trevelyan St",
    "iso:country":"AU",
    "sg:address":"25 Trevelyan St",
    "sg:city":"Elsternwick",
    "sg:classifiers":[
        {
            "category":"Professional",
            "subcategory":"Art Services",
            "type":"Services"
        }
    ],
    "sg:phone":"+61 3 9523 8796",
    "sg:postcode":"3185",
    "sg:province":"VIC",
    "sg:tags":[
        "graphic",
        "designer"
    ],
    "wof:name":"Co-Grafika Pty Ltd",
    "wof:placetype":"venue"
},
  "geometry": {"coordinates":[145.01083374000001,-37.8903579712],"type":"Point"}
}