{
  "type": "Feature",
  "properties": {
    "iso:country":"AU",
    "sg:address":"8 Proffit St",
    "sg:city":"Bunbury",
    "sg:classifiers":[
        {
            "category":"Industrial Area",
            "type":"Public Place"
        }
    ],
    "sg:phone":"+61 8 9721 1217",
    "sg:postcode":"6230",
    "sg:province":"WA",
    "sg:tags":[
        "protective",
        "clothing"
    ],
    "wof:name":"BOC",
    "wof:placetype":"venue"
},
  "geometry": {"coordinates":[115.667618,-33.354427],"type":"Point"}
}