{
  "type": "Feature",
  "properties": {
    "iso:country":"AU",
    "sg:address":"82/ 120 Sturt St",
    "sg:city":"Southbank",
    "sg:classifiers":[
        {
            "category":"Shopping",
            "subcategory":"Musical Instruments",
            "type":"Retail Goods"
        }
    ],
    "sg:phone":"+61 411 103 260",
    "sg:postcode":"3006",
    "sg:province":"VIC",
    "sg:tags":[
        "musician",
        "agent"
    ],
    "wof:name":"Kevin Mahoney",
    "wof:placetype":"venue"
},
  "geometry": {"coordinates":[144.966918945,-37.8244247437],"type":"Point"}
}