{
  "type": "Feature",
  "properties": {
    "addr:full":"260 Railway Pde West Leederville WA 6007",
    "addr:housenumber":"260",
    "addr:postcode":"6007",
    "addr:street":"Railway Pde West",
    "iso:country":"AU",
    "sg:address":"260 Railway Pde",
    "sg:city":"West Leederville",
    "sg:classifiers":[
        {
            "category":"Government",
            "subcategory":"Department Of Motor Vehicles",
            "type":"Public Place"
        }
    ],
    "sg:phone":"+61 1800 686 089",
    "sg:postcode":"6007",
    "sg:province":"WA",
    "sg:tags":[
        "wholesaler",
        "mfrs",
        "accessory"
    ],
    "wof:name":"Thule",
    "wof:placetype":"venue"
},
  "geometry": {"coordinates":[115.83278656,-31.9422569275],"type":"Point"}
}