{
  "type": "Feature",
  "properties": {
    "addr:full":"Lvl 2/ 28 James Pl Adelaide SA 5000",
    "addr:housenumber":"/ 28",
    "addr:postcode":"5000",
    "addr:street":"James Pl",
    "iso:country":"AU",
    "sg:address":"Lvl 2/ 28 James Pl",
    "sg:city":"Adelaide",
    "sg:classifiers":[
        {
            "category":"Professional",
            "subcategory":"Detective & Security Services",
            "type":"Services"
        }
    ],
    "sg:phone":"+61 8 8212 8222",
    "sg:postcode":"5000",
    "sg:province":"SA",
    "sg:tags":[
        "consultant",
        "system"
    ],
    "wof:name":"Central Region Security Systems Pty Ltd",
    "wof:placetype":"venue"
},
  "geometry": {"coordinates":[138.600906372,-34.9239997864],"type":"Point"}
}