{
  "type": "Feature",
  "properties": {
    "addr:full":"185 Watton St Werribee VIC 3030",
    "addr:housenumber":"185",
    "addr:postcode":"3030",
    "addr:street":"Watton St",
    "iso:country":"AU",
    "sg:address":"185 Watton St",
    "sg:city":"Werribee",
    "sg:classifiers":[
        {
            "category":"Manufacturing",
            "subcategory":"Food",
            "type":"Manufacturing & Wholesale Goods"
        }
    ],
    "sg:phone":"+61 411 635 083",
    "sg:postcode":"3030",
    "sg:province":"VIC",
    "sg:tags":[
        "function",
        "catering"
    ],
    "wof:name":"The Max Cafe Bar",
    "wof:placetype":"venue"
},
  "geometry": {"coordinates":[144.65701300000001,-37.903854],"type":"Point"}
}