{
  "type": "Feature",
  "properties": {
    "addr:full":"Level 1/ 120 Birkdale Rd Birkdale QLD 4159",
    "addr:housenumber":"/ 120",
    "addr:postcode":"4159",
    "addr:street":"Birkdale Rd",
    "iso:country":"AU",
    "sg:address":"Level 1/ 120 Birkdale Rd",
    "sg:city":"Birkdale",
    "sg:classifiers":[
        {
            "category":"Organizations",
            "subcategory":"Professional Association",
            "type":"Services"
        }
    ],
    "sg:phone":"+61 7 3488 0983",
    "sg:postcode":"4159",
    "sg:province":"QLD",
    "sg:tags":[
        "web",
        "internet"
    ],
    "wof:name":"Complete Internet Services",
    "wof:placetype":"venue"
},
  "geometry": {"coordinates":[153.21072387699999,-27.5007686615],"type":"Point"}
}