{
  "type": "Feature",
  "properties": {
    "addr:full":"14a Brex Crt Reservoir VIC 3073",
    "addr:housenumber":"14a",
    "addr:postcode":"3073",
    "addr:street":"Brex Crt",
    "iso:country":"AU",
    "sg:address":"14a Brex Crt",
    "sg:city":"Reservoir",
    "sg:classifiers":[
        {
            "category":"Food & Beverages",
            "subcategory":"Bakery",
            "type":"Retail Goods"
        }
    ],
    "sg:phone":"+61 3 9462 4222",
    "sg:postcode":"3073",
    "sg:province":"VIC",
    "sg:tags":[
        "baker"
    ],
    "wof:name":"Cakemen The",
    "wof:placetype":"venue"
},
  "geometry": {"coordinates":[144.98094177199999,-37.7083892822],"type":"Point"}
}