{
  "type": "Feature",
  "properties": {
    "addr:full":"74 Bay St Port Melbourne VIC 3207",
    "addr:housenumber":"74",
    "addr:postcode":"3207",
    "addr:street":"Bay St",
    "iso:country":"AU",
    "sg:address":"74 Bay St",
    "sg:city":"Port Melbourne",
    "sg:classifiers":[
        {
            "category":"Shopping",
            "subcategory":"Clothing, Apparel, & Fashions",
            "type":"Retail Goods"
        }
    ],
    "sg:phone":"+61 3 9646 9983",
    "sg:postcode":"3207",
    "sg:province":"VIC",
    "sg:tags":[
        "lady",
        "wear"
    ],
    "wof:name":"Miishu Fashion Boutique",
    "wof:placetype":"venue"
},
  "geometry": {"coordinates":[144.93942300000001,-37.841946],"type":"Point"}
}