{
  "type": "Feature",
  "properties": {
    "addr:full":"163 Hindmarsh Rd Victor Harbor SA 5211",
    "addr:housenumber":"163",
    "addr:postcode":"5211",
    "addr:street":"Hindmarsh Rd",
    "iso:country":"AU",
    "sg:address":"163 Hindmarsh Rd",
    "sg:city":"Victor Harbor",
    "sg:classifiers":[
        {
            "category":"Professional",
            "subcategory":"Accounting & Tax Preparation",
            "type":"Services"
        }
    ],
    "sg:phone":"+61 8 8552 3711",
    "sg:postcode":"5211",
    "sg:province":"SA",
    "sg:tags":[
        "accountant",
        "auditor"
    ],
    "wof:name":"Perks Chartered Accountants Pty Ltd",
    "wof:placetype":"venue"
},
  "geometry": {"coordinates":[138.623214722,-35.5516090393],"type":"Point"}
}