{
  "type": "Feature",
  "properties": {
    "iso:country":"AU",
    "sg:address":"Cnr Springvale & Centre Rds",
    "sg:city":"Springvale",
    "sg:classifiers":[
        {
            "category":"Autos & Motor Vehicles",
            "subcategory":"Automobile Sales",
            "type":"Retail Goods"
        }
    ],
    "sg:phone":"+61 3 9547 6611",
    "sg:postcode":"3171",
    "sg:province":"VIC",
    "sg:tags":[
        "car",
        "used"
    ],
    "wof:name":"Kwikut Graphics",
    "wof:placetype":"venue"
},
  "geometry": {"coordinates":[145.153930664,-37.9433288574],"type":"Point"}
}