{
  "type": "Feature",
  "properties": {
    "addr:full":"GPO Box 2074 Brisbane QLD 4001",
    "addr:postcode":"4001",
    "iso:country":"AU",
    "sg:address":"GPO Box 2074",
    "sg:city":"Brisbane",
    "sg:classifiers":[
        {
            "category":"Professional",
            "subcategory":"Management & Consulting",
            "type":"Services"
        }
    ],
    "sg:phone":"+61 7 3358 3021",
    "sg:postcode":"4001",
    "sg:province":"QLD",
    "sg:tags":[
        "consultant",
        "industrial",
        "relation"
    ],
    "wof:name":"Turner IR QLD Pty Ltd",
    "wof:placetype":"venue"
},
  "geometry": {"coordinates":[152.88890075699999,-27.5976715088],"type":"Point"}
}