{
  "type": "Feature",
  "properties": {
    "iso:country":"AU",
    "sg:address":"48 Albany St",
    "sg:city":"St Leonards",
    "sg:classifiers":[
        {
            "category":"Professional",
            "type":"Services"
        }
    ],
    "sg:phone":"+61 2 9966 9125",
    "sg:postcode":"2065",
    "sg:province":"NSW",
    "sg:tags":[
        "shop",
        "fitting"
    ],
    "wof:name":"C S Retail & Commercial Design",
    "wof:placetype":"venue"
},
  "geometry": {"coordinates":[151.19764709500001,-33.8236579895],"type":"Point"}
}