{
  "type": "Feature",
  "properties": {
    "addr:full":"8 Corporation Pl Orange NSW 2800",
    "addr:housenumber":"8",
    "addr:postcode":"2800",
    "addr:street":"Corporation Pl",
    "iso:country":"AU",
    "sg:address":"8 Corporation Pl",
    "sg:city":"Orange",
    "sg:classifiers":[
        {
            "category":"Building & Trades",
            "subcategory":"Equipment Rental",
            "type":"Services"
        }
    ],
    "sg:phone":"+61 2 6362 5322",
    "sg:postcode":"2800",
    "sg:province":"NSW",
    "sg:tags":[
        "crane",
        "hire"
    ],
    "wof:name":"Scaffolding Services",
    "wof:placetype":"venue"
},
  "geometry": {"coordinates":[149.10763549800001,-33.3131332397],"type":"Point"}
}