{
  "type": "Feature",
  "properties": {
    "iso:country":"AU",
    "sg:address":"43 Warrigo St",
    "sg:city":"Sadleir",
    "sg:classifiers":[
        {
            "category":"Professional",
            "subcategory":"Art Services",
            "type":"Services"
        }
    ],
    "sg:phone":"+61 2 9608 8840",
    "sg:postcode":"2168",
    "sg:province":"NSW",
    "sg:tags":[
        "decorator",
        "painter"
    ],
    "sg:website":"http://www.anwaarpainting.com.au",
    "wof:name":"Anwaar Painting & Decorating",
    "wof:placetype":"venue"
},
  "geometry": {"coordinates":[150.890182495,-33.9128608704],"type":"Point"}
}