{
  "type": "Feature",
  "properties": {
    "addr:full":"94 Queen St Woollahra NSW 2025",
    "addr:housenumber":"94",
    "addr:postcode":"2025",
    "addr:street":"Queen St",
    "iso:country":"AU",
    "sg:address":"94 Queen St",
    "sg:city":"Woollahra",
    "sg:classifiers":[
        {
            "category":"Shopping",
            "subcategory":"Antiques",
            "type":"Retail Goods"
        }
    ],
    "sg:phone":"+61 2 9362 8628",
    "sg:postcode":"2025",
    "sg:province":"NSW",
    "wof:name":"Hamish Clark Antiques",
    "wof:placetype":"venue"
},
  "geometry": {"coordinates":[151.23611450199999,-33.8884925842],"type":"Point"}
}