{
  "type": "Feature",
  "properties": {
    "addr:full":"1 Mollison St Kyneton VIC 3444",
    "addr:housenumber":"1",
    "addr:postcode":"3444",
    "addr:street":"Mollison St",
    "iso:country":"AU",
    "sg:address":"1 Mollison St",
    "sg:city":"Kyneton",
    "sg:classifiers":[
        {
            "category":"Building & Trades",
            "subcategory":"Equipment Rental",
            "type":"Services"
        }
    ],
    "sg:phone":"+61 421 356 506",
    "sg:postcode":"3444",
    "sg:province":"VIC",
    "sg:tags":[
        "crane",
        "hire"
    ],
    "sg:website":"http://www.users.bigpond.com/sc-ryan",
    "wof:name":"Kyneton Crane Hire",
    "wof:placetype":"venue"
},
  "geometry": {"coordinates":[144.45135498100001,-37.2583312988],"type":"Point"}
}