{
  "type": "Feature",
  "properties": {
    "addr:full":"Shop 15, Ningi Plz, Bribie Island Rd Ningi QLD 4511",
    "addr:housenumber":"shop 15",
    "addr:postcode":"4511",
    "addr:street":"Ningi Plz Bribie Island Rd",
    "iso:country":"AU",
    "sg:address":"Shop 15, Ningi Plz, Bribie Island Rd",
    "sg:city":"Ningi",
    "sg:classifiers":[
        {
            "category":"Real Estate",
            "subcategory":"Real Estate Agent",
            "type":"Services"
        }
    ],
    "sg:phone":"+61 427 071 192",
    "sg:postcode":"4511",
    "sg:province":"QLD",
    "wof:name":"Elders Real Estate Bribie Gateway",
    "wof:placetype":"venue"
},
  "geometry": {"coordinates":[153.09948700000001,-27.065886],"type":"Point"}
}