{
  "type": "Feature",
  "properties": {
    "addr:full":"11 Schubert Crt Burpengary QLD 4505",
    "addr:housenumber":"11",
    "addr:postcode":"4505",
    "addr:street":"Schubert Crt",
    "iso:country":"AU",
    "sg:address":"11 Schubert Crt",
    "sg:city":"Burpengary",
    "sg:classifiers":[
        {
            "category":"Retail",
            "subcategory":"Auto Repair",
            "type":"Services"
        }
    ],
    "sg:phone":"+61 418 198 830",
    "sg:postcode":"4505",
    "sg:province":"QLD",
    "sg:tags":[
        "beater",
        "painter",
        "panel"
    ],
    "wof:name":"Wylie Coyote Motorsport",
    "wof:placetype":"venue"
},
  "geometry": {"coordinates":[152.964355469,-27.1632785797],"type":"Point"}
}