{
  "type": "Feature",
  "properties": {
    "addr:full":"L3 &#034;QVB Market St End&#034; 455 George St Sydney NSW 2000",
    "addr:housenumber":"455",
    "addr:postcode":"2000",
    "addr:street":"Market St;George St",
    "iso:country":"AU",
    "sg:address":"L3 &#034;QVB Market St End&#034; 455 George St",
    "sg:city":"Sydney",
    "sg:classifiers":[
        {
            "category":"Retail",
            "subcategory":"Event Space",
            "type":"Services"
        }
    ],
    "sg:phone":"+61 2 9283 7279",
    "sg:postcode":"2000",
    "sg:province":"NSW",
    "sg:tags":[
        "venue",
        "reception",
        "wedding"
    ],
    "wof:name":"The Tearoom",
    "wof:placetype":"venue"
},
  "geometry": {"coordinates":[151.206863403,-33.8719215393],"type":"Point"}
}