{
  "type": "Feature",
  "properties": {
    "addr:full":"220 Old Kent Rd Greenacre NSW 2190",
    "addr:housenumber":"220",
    "addr:postcode":"2190",
    "addr:street":"Old Kent Rd",
    "iso:country":"AU",
    "sg:address":"220 Old Kent Rd",
    "sg:city":"Greenacre",
    "sg:classifiers":[
        {
            "category":"Education",
            "subcategory":"Special Training",
            "type":"Public Place"
        }
    ],
    "sg:phone":"+61 2 9709 3224",
    "sg:postcode":"2190",
    "sg:province":"NSW",
    "sg:tags":[
        "tuition-educational"
    ],
    "wof:name":"Caresa Education Services",
    "wof:placetype":"venue"
},
  "geometry": {"coordinates":[151.04437300000001,-33.913162],"type":"Point"}
}