{
  "type": "Feature",
  "properties": {
    "addr:full":"10 Davies Pl Picton NSW 2571",
    "addr:housenumber":"10",
    "addr:postcode":"2571",
    "addr:street":"Davies Pl",
    "iso:country":"AU",
    "sg:address":"10 Davies Pl",
    "sg:city":"Picton",
    "sg:classifiers":[
        {
            "category":"Retail",
            "subcategory":"Auto Repair",
            "type":"Services"
        }
    ],
    "sg:phone":"+61 414 181 611",
    "sg:postcode":"2571",
    "sg:province":"NSW",
    "sg:tags":[
        "repairer",
        "motor",
        "engineer"
    ],
    "wof:name":"ABA Mobile Automotive Services",
    "wof:placetype":"venue"
},
  "geometry": {"coordinates":[150.608612061,-34.1644210815],"type":"Point"}
}