{
  "type": "Feature",
  "properties": {
    "iso:country":"AU",
    "sg:address":"PO Box 169",
    "sg:city":"Nelson Bay",
    "sg:classifiers":[
        {
            "category":"Recreation",
            "subcategory":"Fishing",
            "type":"Entertainment"
        }
    ],
    "sg:phone":"+61 2 4981 0305",
    "sg:postcode":"2315",
    "sg:province":"NSW",
    "sg:tags":[
        "tackle"
    ],
    "wof:name":"Pakula Lures Australia Pty Ltd",
    "wof:placetype":"venue"
},
  "geometry": {"coordinates":[152.14331100000001,-32.72279],"type":"Point"}
}