{
  "type": "Feature",
  "properties": {
    "iso:country":"AU",
    "sg:address":"112 Hume St",
    "sg:city":"Wodonga",
    "sg:classifiers":[
        {
            "category":"Health Services",
            "subcategory":"Optometrist",
            "type":"Services"
        }
    ],
    "sg:phone":"+61 2 6024 1177",
    "sg:postcode":"3690",
    "sg:province":"VIC",
    "wof:name":"Peachey Optometry Clinic",
    "wof:placetype":"venue"
},
  "geometry": {"coordinates":[146.885894775,-36.1240081787],"type":"Point"}
}