{
  "type": "Feature",
  "properties": {
    "iso:country":"AU",
    "sg:address":"117 Main St",
    "sg:city":"Cressy",
    "sg:classifiers":[
        {
            "category":"Fast Food",
            "type":"Food & Drink"
        }
    ],
    "sg:phone":"+61 3 6397 6155",
    "sg:postcode":"7302",
    "sg:province":"TAS",
    "sg:tags":[
        "away",
        "take"
    ],
    "wof:name":"Staggs Takeaway & Accommodation",
    "wof:placetype":"venue"
},
  "geometry": {"coordinates":[147.07936096200001,-41.6910667419],"type":"Point"}
}