{
  "type": "Feature",
  "properties": {
    "addr:full":"27 Charles St Springsure QLD 4722",
    "addr:housenumber":"27",
    "addr:postcode":"4722",
    "addr:street":"Charles St",
    "iso:country":"AU",
    "sg:address":"27 Charles St",
    "sg:city":"Springsure",
    "sg:classifiers":[
        {
            "category":"Travel",
            "subcategory":"Hotels & Motels",
            "type":"Entertainment"
        }
    ],
    "sg:phone":"+61 7 4984 1455",
    "sg:postcode":"4722",
    "sg:province":"QLD",
    "wof:name":"Springsure Zamia Motel",
    "wof:placetype":"venue"
},
  "geometry": {"coordinates":[148.087006,-24.116295],"type":"Point"}
}