{
  "type": "Feature",
  "properties": {
    "addr:full":"150 Wharf Rd Newcastle NSW 2300",
    "addr:housenumber":"150",
    "addr:postcode":"2300",
    "addr:street":"Wharf Rd",
    "iso:country":"AU",
    "sg:address":"150 Wharf Rd",
    "sg:city":"Newcastle",
    "sg:classifiers":[
        {
            "category":"Restaurant",
            "type":"Food & Drink"
        }
    ],
    "sg:phone":"+61 2 4929 6333",
    "sg:postcode":"2300",
    "sg:province":"NSW",
    "sg:website":"http://www.qwb.com.au",
    "wof:name":"The Brewery",
    "wof:placetype":"venue"
},
  "geometry": {"coordinates":[151.78308100000001,-32.925945],"type":"Point"}
}