{
  "type": "Feature",
  "properties": {
    "iso:country":"AU",
    "sg:address":"2 Queens Ave",
    "sg:city":"Carnegie",
    "sg:classifiers":[
        {
            "category":"Retail",
            "subcategory":"Auto Repair",
            "type":"Services"
        }
    ],
    "sg:phone":"+61 3 9572 2520",
    "sg:postcode":"3163",
    "sg:province":"VIC",
    "sg:tags":[
        "repairer",
        "motor",
        "engineer"
    ],
    "wof:name":"All 4 W.D. Service & Repairs",
    "wof:placetype":"venue"
},
  "geometry": {"coordinates":[145.04298400900001,-37.8867378235],"type":"Point"}
}