{
  "type": "Feature",
  "properties": {
    "iso:country":"AU",
    "sg:address":"1431 Albany Hwy",
    "sg:city":"Cannington",
    "sg:classifiers":[
        {
            "category":"Professional",
            "subcategory":"Business Services",
            "type":"Services"
        }
    ],
    "sg:phone":"+61 8 9350 5557",
    "sg:postcode":"6107",
    "sg:province":"WA",
    "sg:tags":[
        "exporter"
    ],
    "wof:name":"Austral Asia Supplies",
    "wof:placetype":"venue"
},
  "geometry": {"coordinates":[115.926498413,-32.0118522644],"type":"Point"}
}