{
  "type": "Feature",
  "properties": {
    "addr:full":"5 Malcolm Rd Queanbeyan ACT 2620",
    "addr:housenumber":"5",
    "addr:postcode":"2620",
    "addr:street":"Malcolm Rd",
    "iso:country":"AU",
    "sg:address":"5 Malcolm Rd",
    "sg:city":"Queanbeyan",
    "sg:classifiers":[
        {
            "category":"Autos & Motor Vehicles",
            "subcategory":"Automobile Sales",
            "type":"Retail Goods"
        }
    ],
    "sg:phone":"+61 2 6297 9613",
    "sg:postcode":"2620",
    "sg:province":"ACT",
    "sg:tags":[
        "equipment",
        "trailer"
    ],
    "wof:name":"Haymax Camper Trailers",
    "wof:placetype":"venue"
},
  "geometry": {"coordinates":[149.23495483400001,-35.3654594421],"type":"Point"}
}