{
  "type": "Feature",
  "properties": {
    "addr:full":"10 Amazons Pl Jindalee QLD 4074",
    "addr:housenumber":"10",
    "addr:postcode":"4074",
    "addr:street":"Amazons Pl",
    "iso:country":"AU",
    "sg:address":"10 Amazons Pl",
    "sg:city":"Jindalee",
    "sg:classifiers":[
        {
            "category":"Personal",
            "subcategory":"Beauty Salon",
            "type":"Services"
        }
    ],
    "sg:phone":"+61 7 3715 8900",
    "sg:postcode":"4074",
    "sg:province":"QLD",
    "sg:tags":[
        "hairdresser"
    ],
    "wof:name":"Precision Cuts",
    "wof:placetype":"venue"
},
  "geometry": {"coordinates":[152.94900512699999,-27.5316257477],"type":"Point"}
}