{
  "type": "Feature",
  "properties": {
    "addr:full":"318 Ascot Vale Rd Moonee Ponds VIC 3039",
    "addr:housenumber":"318",
    "addr:postcode":"3039",
    "addr:street":"Ascot Vale Rd",
    "iso:country":"AU",
    "sg:address":"318 Ascot Vale Rd",
    "sg:city":"Moonee Ponds",
    "sg:classifiers":[
        {
            "category":"Health Services",
            "subcategory":"Doctor",
            "type":"Services"
        }
    ],
    "sg:phone":"+61 13 26 60",
    "sg:postcode":"3039",
    "sg:province":"VIC",
    "sg:tags":[
        "medical",
        "practitioner"
    ],
    "wof:name":"Low Jean",
    "wof:placetype":"venue"
},
  "geometry": {"coordinates":[144.924408,-37.770386],"type":"Point"}
}