{
  "type": "Feature",
  "properties": {
    "iso:country":"AU",
    "sg:address":"28 Walsh St",
    "sg:city":"Thebarton",
    "sg:classifiers":[
        {
            "category":"Wholesale",
            "subcategory":"Home Furnishings",
            "type":"Manufacturing & Wholesale Goods"
        }
    ],
    "sg:phone":"+61 8 8443 9363",
    "sg:postcode":"5031",
    "sg:province":"SA",
    "sg:tags":[
        "wholesaler",
        "mfrs",
        "kitchenware"
    ],
    "wof:name":"Thebe International",
    "wof:placetype":"venue"
},
  "geometry": {"coordinates":[138.57685852,-34.9144439697],"type":"Point"}
}