{
  "type": "Feature",
  "properties": {
    "iso:country":"AU",
    "sg:address":"Suite 7/ 80 Main St",
    "sg:city":"Alstonville",
    "sg:classifiers":[
        {
            "category":"Insurance",
            "subcategory":"Insurance Agent",
            "type":"Services"
        }
    ],
    "sg:phone":"+61 2 6628 5161",
    "sg:postcode":"2477",
    "sg:province":"NSW",
    "wof:name":"INGRAM WILES & ASSOCIATES",
    "wof:placetype":"venue"
},
  "geometry": {"coordinates":[153.435913086,-28.8379936218],"type":"Point"}
}