{
  "type": "Feature",
  "properties": {
    "addr:full":"144 Shannon Ave Geelong West VIC 3218",
    "addr:housenumber":"144",
    "addr:postcode":"3218",
    "addr:street":"Shannon Ave",
    "iso:country":"AU",
    "sg:address":"144 Shannon Ave",
    "sg:city":"Geelong West",
    "sg:classifiers":[
        {
            "category":"Fast Food",
            "type":"Food & Drink"
        }
    ],
    "sg:phone":"+61 3 5223 1779",
    "sg:postcode":"3218",
    "sg:province":"VIC",
    "sg:tags":[
        "away",
        "take"
    ],
    "wof:name":"Fishermans Delight",
    "wof:placetype":"venue"
},
  "geometry": {"coordinates":[144.33706665,-38.1379127502],"type":"Point"}
}