{
  "type": "Feature",
  "properties": {
    "iso:country":"AU",
    "sg:address":"9 Mowbray St",
    "sg:city":"Launceston",
    "sg:classifiers":[
        {
            "category":"Home & Garden",
            "subcategory":"Carpets & Floor Coverings",
            "type":"Retail Goods"
        }
    ],
    "sg:phone":"+61 3 6326 3888",
    "sg:postcode":"7250",
    "sg:province":"TAS",
    "wof:name":"Ontera Modular Carpets Pty Ltd",
    "wof:placetype":"venue"
},
  "geometry": {"coordinates":[147.13183593799999,-41.4126358032],"type":"Point"}
}