{
  "type": "Feature",
  "properties": {
    "iso:country":"AU",
    "sg:address":"8 Windsor Ave",
    "sg:city":"Mt Waverley",
    "sg:classifiers":[
        {
            "category":"Professional",
            "subcategory":"Computer Services",
            "type":"Services"
        }
    ],
    "sg:phone":"+61 3 9807 1014",
    "sg:postcode":"3149",
    "sg:province":"VIC",
    "sg:tags":[
        "consultant",
        "system"
    ],
    "wof:name":"Superior Information Systems",
    "wof:placetype":"venue"
},
  "geometry": {"coordinates":[145.11253356899999,-37.8741950989],"type":"Point"}
}