{
  "type": "Feature",
  "properties": {
    "addr:full":"Oak Thee House 256 Hawthorn Rd Caulfield South VIC 3162",
    "addr:housenumber":"256",
    "addr:postcode":"3162",
    "addr:street":"Hawthorn Rd",
    "iso:country":"AU",
    "sg:address":"Oak Thee House 256 Hawthorn Rd",
    "sg:city":"Caulfield South",
    "sg:classifiers":[
        {
            "category":"Health Services",
            "subcategory":"Health Practitioner",
            "type":"Services"
        }
    ],
    "sg:phone":"+61 3 9576 7629",
    "sg:postcode":"3162",
    "sg:province":"VIC",
    "sg:tags":[
        "psychologist"
    ],
    "wof:name":"Vogel Carol E.",
    "wof:placetype":"venue"
},
  "geometry": {"coordinates":[145.02296447800001,-37.8809280396],"type":"Point"}
}