{
  "type": "Feature",
  "properties": {
    "addr:full":"PO Box 6582 Coffs Harbour NSW 2450",
    "addr:postcode":"2450",
    "iso:country":"AU",
    "sg:address":"PO Box 6582",
    "sg:city":"Coffs Harbour",
    "sg:classifiers":[
        {
            "category":"Utilities",
            "subcategory":"Electric",
            "type":"Services"
        }
    ],
    "sg:phone":"+61 427 656 765",
    "sg:postcode":"2450",
    "sg:province":"NSW",
    "sg:tags":[
        "electrical",
        "contractor"
    ],
    "wof:name":"Aliance Design Electrical Pty Ltd",
    "wof:placetype":"venue"
},
  "geometry": {"coordinates":[153.11515800000001,-30.29701],"type":"Point"}
}