{
  "type": "Feature",
  "properties": {
    "iso:country":"AU",
    "sg:address":"1/ 377- 379 Thompson Rd",
    "sg:city":"Geelong North",
    "sg:classifiers":[
        {
            "category":"Home & Garden",
            "subcategory":"Hardware",
            "type":"Retail Goods"
        }
    ],
    "sg:phone":"+61 3 5277 2063",
    "sg:postcode":"3215",
    "sg:province":"VIC",
    "sg:tags":[
        "nut",
        "bolt"
    ],
    "wof:name":"Coventry Fasteners",
    "wof:placetype":"venue"
},
  "geometry": {"coordinates":[144.345626831,-38.098361969],"type":"Point"}
}