{
  "type": "Feature",
  "properties": {
    "iso:country":"AU",
    "sg:address":"77 Chapel St",
    "sg:city":"Colac",
    "sg:classifiers":[
        {
            "category":"Commercial Area",
            "type":"Public Place"
        }
    ],
    "sg:phone":"+61 3 5231 3771",
    "sg:postcode":"3250",
    "sg:province":"VIC",
    "sg:tags":[
        "heavy",
        "carrier"
    ],
    "wof:name":"Baulch C & J",
    "wof:placetype":"venue"
},
  "geometry": {"coordinates":[143.605438,-38.332893],"type":"Point"}
}