{
  "type": "Feature",
  "properties": {
    "addr:full":"Shop 1, 192 Jacobs Drv Sussex Inlet NSW 2540",
    "addr:housenumber":"shop 1 192",
    "addr:postcode":"2540",
    "addr:street":"Jacobs Drv",
    "iso:country":"AU",
    "sg:address":"Shop 1, 192 Jacobs Drv",
    "sg:city":"Sussex Inlet",
    "sg:classifiers":[
        {
            "category":"Manufacturing",
            "subcategory":"Motor Vehicles & Parts",
            "type":"Manufacturing & Wholesale Goods"
        }
    ],
    "sg:phone":"+61 2 4441 2880",
    "sg:postcode":"2540",
    "sg:province":"NSW",
    "sg:tags":[
        "replacement"
    ],
    "wof:name":"Mobys",
    "wof:placetype":"venue"
},
  "geometry": {"coordinates":[150.60188293499999,-35.1568260193],"type":"Point"}
}