{
  "type": "Feature",
  "properties": {
    "iso:country":"AU",
    "sg:address":"42 Barwell Ave",
    "sg:city":"Barmera",
    "sg:classifiers":[
        {
            "category":"Shopping",
            "subcategory":"Clothing, Apparel, & Fashions",
            "type":"Retail Goods"
        }
    ],
    "sg:phone":"+61 8 8588 2219",
    "sg:postcode":"5345",
    "sg:province":"SA",
    "sg:tags":[
        "lady",
        "wear"
    ],
    "wof:name":"B & B Fashions & Fabrics",
    "wof:placetype":"venue"
},
  "geometry": {"coordinates":[140.46470642099999,-34.2516517639],"type":"Point"}
}