{
  "type": "Feature",
  "properties": {
    "iso:country":"AU",
    "sg:address":"67 Coonawarra Rd",
    "sg:city":"Winnellie",
    "sg:classifiers":[
        {
            "category":"Manufacturing",
            "subcategory":"Metals",
            "type":"Manufacturing & Wholesale Goods"
        }
    ],
    "sg:phone":"+61 8 8947 2655",
    "sg:postcode":"0820",
    "sg:province":"NT",
    "sg:tags":[
        "sheet",
        "worker"
    ],
    "wof:name":"Darwin Metal Industries",
    "wof:placetype":"venue"
},
  "geometry": {"coordinates":[130.87840270999999,-12.4303159714],"type":"Point"}
}