{
  "type": "Feature",
  "properties": {
    "addr:full":"Level 1 , The Piazza Surfers Paradise Blv Surfers Par QLD 4217",
    "addr:postcode":"4217",
    "addr:street":"Piazza Surfers Paradise Blv Surfers",
    "iso:country":"AU",
    "sg:address":"Level 1",
    "sg:city":", The Piazza Surfers Paradise Blv Surfers Par",
    "sg:classifiers":[
        {
            "category":"Health Services",
            "subcategory":"Health Practitioner",
            "type":"Services"
        }
    ],
    "sg:phone":"+61 7 5539 0779",
    "sg:postcode":"4217",
    "sg:province":"QLD",
    "sg:tags":[
        "physiotherapist"
    ],
    "wof:name":"My Backs Physio Australia",
    "wof:placetype":"venue"
},
  "geometry": {"coordinates":[153.425018311,-27.9922275543],"type":"Point"}
}