{
  "type": "Feature",
  "properties": {
    "iso:country":"AU",
    "sg:address":"8 Railway St",
    "sg:city":"Boonah",
    "sg:classifiers":[
        {
            "category":"Cafe",
            "type":"Food & Drink"
        }
    ],
    "sg:phone":"+61 7 5463 2699",
    "sg:postcode":"4310",
    "sg:province":"QLD",
    "wof:name":"Flavours Cafe",
    "wof:placetype":"venue"
},
  "geometry": {"coordinates":[152.68190002399999,-27.9956684113],"type":"Point"}
}