{
  "type": "Feature",
  "properties": {
    "addr:full":"Unit 16/ 6 Nuban St Currumbin Waters QLD 4223",
    "addr:housenumber":"/ 6",
    "addr:postcode":"4223",
    "addr:street":"Nuban St",
    "iso:country":"AU",
    "sg:address":"Unit 16/ 6 Nuban St",
    "sg:city":"Currumbin Waters",
    "sg:classifiers":[
        {
            "category":"Building & Trades",
            "subcategory":"Construction",
            "type":"Services"
        }
    ],
    "sg:phone":"+61 7 5534 5788",
    "sg:postcode":"4223",
    "sg:province":"QLD",
    "sg:tags":[
        "contractor"
    ],
    "wof:name":"Quattro Developments Pty Ltd",
    "wof:placetype":"venue"
},
  "geometry": {"coordinates":[153.470504761,-28.1485538483],"type":"Point"}
}