{
  "type": "Feature",
  "properties": {
    "iso:country":"AU",
    "sg:address":"863 Wellington St",
    "sg:city":"West Perth",
    "sg:classifiers":[
        {
            "category":"Professional",
            "subcategory":"Computer Services",
            "type":"Services"
        }
    ],
    "sg:phone":"+61 8 9321 8099",
    "sg:postcode":"6005",
    "sg:province":"WA",
    "sg:tags":[
        "repairs",
        "upgrade",
        "equipment"
    ],
    "wof:name":"Mobile Computer Express",
    "wof:placetype":"venue"
},
  "geometry": {"coordinates":[115.846672058,-31.9476852417],"type":"Point"}
}