{
  "type": "Feature",
  "properties": {
    "iso:country":"AU",
    "sg:address":"Young Rd",
    "sg:city":"Temora",
    "sg:classifiers":[
        {
            "category":"Utilities",
            "subcategory":"Electric",
            "type":"Services"
        }
    ],
    "sg:phone":"+61 2 6977 2818",
    "sg:postcode":"2666",
    "sg:province":"NSW",
    "sg:tags":[
        "electrical",
        "contractor"
    ],
    "wof:name":"Firman T R & J A",
    "wof:placetype":"venue"
},
  "geometry": {"coordinates":[147.54591369600001,-34.4432487488],"type":"Point"}
}