{
  "type": "Feature",
  "properties": {
    "addr:full":"U1/ 8 Belgrave Rd Indooroopilly QLD 4068",
    "addr:housenumber":"8",
    "addr:postcode":"4068",
    "addr:street":"U1 /;Belgrave Rd",
    "iso:country":"AU",
    "sg:address":"U1/ 8 Belgrave Rd",
    "sg:city":"Indooroopilly",
    "sg:classifiers":[
        {
            "category":"Banks & Credit Unions",
            "subcategory":"Investment Brokerage",
            "type":"Services"
        }
    ],
    "sg:phone":"+61 7 3720 0696",
    "sg:postcode":"4068",
    "sg:province":"QLD",
    "sg:tags":[
        "management",
        "property"
    ],
    "wof:name":"Ace Trading",
    "wof:placetype":"venue"
},
  "geometry": {"coordinates":[152.97528076200001,-27.5002822876],"type":"Point"}
}