{
  "type": "Feature",
  "properties": {
    "addr:full":"196 St Johns Rd Glebe NSW 2037",
    "addr:housenumber":"196",
    "addr:postcode":"2037",
    "addr:street":"St Johns Rd",
    "iso:country":"AU",
    "sg:address":"196 St Johns Rd",
    "sg:city":"Glebe",
    "sg:classifiers":[
        {
            "category":"Shopping",
            "subcategory":"Clothing, Apparel, & Fashions",
            "type":"Retail Goods"
        }
    ],
    "sg:phone":"+61 2 9518 4048",
    "sg:postcode":"2037",
    "sg:province":"NSW",
    "sg:tags":[
        "accessory"
    ],
    "wof:name":"Bowerbird",
    "wof:placetype":"venue"
},
  "geometry": {"coordinates":[151.18360900900001,-33.8832244873],"type":"Point"}
}