{
  "type": "Feature",
  "properties": {
    "iso:country":"AU",
    "sg:address":"Silver City Hwy",
    "sg:city":"Mildura",
    "sg:classifiers":[
        {
            "category":"Military Area",
            "subcategory":"Air Force Base",
            "type":"Public Place"
        }
    ],
    "sg:phone":"+61 3 5021 2222",
    "sg:postcode":"3500",
    "sg:province":"VIC",
    "sg:tags":[
        "conditioner",
        "treatment",
        "soil"
    ],
    "wof:name":"Sunraysia Spreading",
    "wof:placetype":"venue"
},
  "geometry": {"coordinates":[142.18075561500001,-34.1708755493],"type":"Point"}
}