{
  "type": "Feature",
  "properties": {
    "addr:full":"16 Granuaille Rd Bangalow NSW 2479",
    "addr:housenumber":"16",
    "addr:postcode":"2479",
    "addr:street":"Granuaille Rd",
    "iso:country":"AU",
    "sg:address":"16 Granuaille Rd",
    "sg:city":"Bangalow",
    "sg:classifiers":[
        {
            "category":"Retail",
            "subcategory":"Auto Repair",
            "type":"Services"
        }
    ],
    "sg:phone":"+61 2 6687 1171",
    "sg:postcode":"2479",
    "sg:province":"NSW",
    "sg:tags":[
        "repairer",
        "motor",
        "engineer"
    ],
    "wof:name":"Bangalow Automotive",
    "wof:placetype":"venue"
},
  "geometry": {"coordinates":[153.52311706500001,-28.6830101013],"type":"Point"}
}