{
  "type": "Feature",
  "properties": {
    "iso:country":"AU",
    "sg:address":"PO Box 162",
    "sg:city":"Buninyong",
    "sg:classifiers":[
        {
            "category":"Farming",
            "subcategory":"Farm & Veterinary Services",
            "type":"Manufacturing & Wholesale Goods"
        }
    ],
    "sg:phone":"+61 417 349 270",
    "sg:postcode":"3357",
    "sg:province":"VIC",
    "sg:tags":[
        "blacksmith",
        "farrier"
    ],
    "wof:name":"Benmor Forge Farrier Service",
    "wof:placetype":"venue"
},
  "geometry": {"coordinates":[143.88627600000001,-37.650761],"type":"Point"}
}