{
  "type": "Feature",
  "properties": {
    "addr:full":"Wentworth St Tewantin QLD 4565",
    "addr:postcode":"4565",
    "addr:street":"Wentworth St",
    "iso:country":"AU",
    "sg:address":"Wentworth St",
    "sg:city":"Tewantin",
    "sg:classifiers":[
        {
            "category":"Real Estate",
            "subcategory":"Real Estate Agent",
            "type":"Services"
        }
    ],
    "sg:phone":"+61 7 5449 0040",
    "sg:postcode":"4565",
    "sg:province":"QLD",
    "wof:name":"Noosa River Heights",
    "wof:placetype":"venue"
},
  "geometry": {"coordinates":[153.015533447,-26.4026012421],"type":"Point"}
}