{
  "type": "Feature",
  "properties": {
    "iso:country":"AU",
    "sg:address":"37 Britten Jones Drv",
    "sg:city":"Holt",
    "sg:classifiers":[
        {
            "category":"Education",
            "subcategory":"Dance Studio",
            "type":"Public Place"
        }
    ],
    "sg:phone":"+61 404 181 862",
    "sg:postcode":"2615",
    "sg:province":"ACT",
    "sg:tags":[
        "venue",
        "tuition"
    ],
    "wof:name":"Salsabor Dance Company",
    "wof:placetype":"venue"
},
  "geometry": {"coordinates":[149.003707886,-35.2217559814],"type":"Point"}
}