{
  "type": "Feature",
  "properties": {
    "addr:full":"5/ 76 Ferry Rd Southport QLD 4215",
    "addr:housenumber":"/ 76",
    "addr:postcode":"4215",
    "addr:street":"Ferry Rd",
    "iso:country":"AU",
    "sg:address":"5/ 76 Ferry Rd",
    "sg:city":"Southport",
    "sg:classifiers":[
        {
            "category":"Government",
            "subcategory":"Post Office",
            "type":"Public Place"
        }
    ],
    "sg:phone":"+61 423 623 783",
    "sg:postcode":"4215",
    "sg:province":"QLD",
    "sg:tags":[
        "yoga"
    ],
    "wof:name":"Shen 9 Shiatsu Yoga",
    "wof:placetype":"venue"
},
  "geometry": {"coordinates":[153.41151428200001,-27.9774608612],"type":"Point"}
}