{
  "type": "Feature",
  "properties": {
    "addr:full":"1/ 380 Clayton Rd Clayton VIC 3168",
    "addr:housenumber":"/ 380",
    "addr:postcode":"3168",
    "addr:street":"Clayton Rd",
    "iso:country":"AU",
    "sg:address":"1/ 380 Clayton Rd",
    "sg:city":"Clayton",
    "sg:classifiers":[
        {
            "category":"Health Services",
            "subcategory":"Optometrist",
            "type":"Services"
        }
    ],
    "sg:phone":"+61 3 9562 8519",
    "sg:postcode":"3168",
    "sg:province":"VIC",
    "wof:name":"ProVision Optometry Clayton",
    "wof:placetype":"venue"
},
  "geometry": {"coordinates":[145.11903381400001,-37.9292449951],"type":"Point"}
}