{
  "type": "Feature",
  "properties": {
    "addr:full":"6 Bay St Port Melbourne VIC 3207",
    "addr:housenumber":"6",
    "addr:postcode":"3207",
    "addr:street":"Bay St",
    "iso:country":"AU",
    "sg:address":"6 Bay St",
    "sg:city":"Port Melbourne",
    "sg:classifiers":[
        {
            "category":"Cinema",
            "subcategory":"Movie Theater",
            "type":"Entertainment"
        }
    ],
    "sg:phone":"+61 3 9644 1900",
    "sg:postcode":"3207",
    "sg:province":"VIC",
    "wof:name":"Reading Cinemas",
    "wof:placetype":"venue"
},
  "geometry": {"coordinates":[144.93859900000001,-37.842854],"type":"Point"}
}