{
  "type": "Feature",
  "properties": {
    "addr:full":"Albury Rd Corowa NSW 2646",
    "addr:postcode":"2646",
    "addr:street":"Albury Rd",
    "iso:country":"AU",
    "sg:address":"Albury Rd",
    "sg:city":"Corowa",
    "sg:classifiers":[
        {
            "category":"Autos & Motor Vehicles",
            "subcategory":"Auto Supplies",
            "type":"Retail Goods"
        }
    ],
    "sg:phone":"+61 2 6033 4288",
    "sg:postcode":"2646",
    "sg:province":"NSW",
    "sg:tags":[
        "tyre"
    ],
    "wof:name":"Yokohama",
    "wof:placetype":"venue"
},
  "geometry": {"coordinates":[146.386154175,-35.9920806885],"type":"Point"}
}