{
  "type": "Feature",
  "properties": {
    "iso:country":"AU",
    "sg:address":"36- 37 Victoria St",
    "sg:city":"Burwood",
    "sg:classifiers":[
        {
            "category":"Banks & Credit Unions",
            "subcategory":"Bank",
            "type":"Services"
        }
    ],
    "sg:phone":"+61 13 21 39",
    "sg:postcode":"2134",
    "sg:province":"NSW",
    "sg:tags":[
        "society"
    ],
    "wof:name":"Metropolitan Credit Union Ltd",
    "wof:placetype":"venue"
},
  "geometry": {"coordinates":[151.10594177199999,-33.8753013611],"type":"Point"}
}