{
  "type": "Feature",
  "properties": {
    "addr:full":"5/ 34 Lani St Wishart QLD 4122",
    "addr:housenumber":"/ 34",
    "addr:postcode":"4122",
    "addr:street":"Lani St",
    "iso:country":"AU",
    "sg:address":"5/ 34 Lani St",
    "sg:city":"Wishart",
    "sg:classifiers":[
        {
            "category":"Communications",
            "type":"Services"
        }
    ],
    "sg:phone":"+61 414 628 389",
    "sg:postcode":"4122",
    "sg:province":"QLD",
    "sg:tags":[
        "translation"
    ],
    "wof:name":"Andric Branislav",
    "wof:placetype":"venue"
},
  "geometry": {"coordinates":[153.09039306599999,-27.5666389465],"type":"Point"}
}