{
  "type": "Feature",
  "properties": {
    "addr:full":"Shop 8 Logan Crt Cowra NSW 2794",
    "addr:housenumber":"shop 8",
    "addr:postcode":"2794",
    "addr:street":"Logan Crt",
    "iso:country":"AU",
    "sg:address":"Shop 8 Logan Crt",
    "sg:city":"Cowra",
    "sg:classifiers":[
        {
            "category":"Personal",
            "subcategory":"Beauty Salon",
            "type":"Services"
        }
    ],
    "sg:phone":"+61 2 6342 1565",
    "sg:postcode":"2794",
    "sg:province":"NSW",
    "sg:tags":[
        "hairdresser"
    ],
    "wof:name":"Tangles Hair Studio",
    "wof:placetype":"venue"
},
  "geometry": {"coordinates":[148.67843627900001,-33.8209571838],"type":"Point"}
}