{
  "type": "Feature",
  "properties": {
    "iso:country":"AU",
    "sg:address":"35-45 Frankston-Dandenong Rd",
    "sg:city":"Dandenong",
    "sg:classifiers":[
        {
            "category":"Railroad",
            "type":"Transportation"
        }
    ],
    "sg:phone":"+61 3 9794 2111",
    "sg:postcode":"3175",
    "sg:province":"VIC",
    "sg:tags":[
        "equipment",
        "railway",
        "construction",
        "material"
    ],
    "wof:name":"Bombardier Transportation",
    "wof:placetype":"venue"
},
  "geometry": {"coordinates":[145.217697144,-38.0011634827],"type":"Point"}
}