{
  "type": "Feature",
  "properties": {
    "iso:country":"AU",
    "sg:address":"Unit 11/ 96",
    "sg:city":"Waratah Blv Canning Vale",
    "sg:classifiers":[
        {
            "category":"Social Services",
            "subcategory":"Child Care",
            "type":"Services"
        }
    ],
    "sg:phone":"+61 8 9455 7836",
    "sg:postcode":"6155",
    "sg:province":"WA",
    "wof:name":"Canning Vale Child Care Centre",
    "wof:placetype":"venue"
},
  "geometry": {"coordinates":[115.911697,-32.074039],"type":"Point"}
}