{
  "type": "Feature",
  "properties": {
    "addr:full":"PO Box 69 Little River VIC 3211",
    "addr:postcode":"3211",
    "iso:country":"AU",
    "sg:address":"PO Box 69",
    "sg:city":"Little River",
    "sg:classifiers":[
        {
            "category":"Farming",
            "subcategory":"Fish & Marine Products",
            "type":"Manufacturing & Wholesale Goods"
        }
    ],
    "sg:phone":"+61 3 5283 1251",
    "sg:postcode":"3211",
    "sg:province":"VIC",
    "sg:tags":[
        "organic"
    ],
    "wof:name":"Pure Earth Geelong",
    "wof:placetype":"venue"
},
  "geometry": {"coordinates":[144.47576904300001,-37.9351882935],"type":"Point"}
}