{
  "type": "Feature",
  "properties": {
    "iso:country":"AU",
    "sg:address":"Unit 14, 11 Donaldson St",
    "sg:city":"Wyong North",
    "sg:classifiers":[
        {
            "category":"Professional",
            "subcategory":"Printing & Photocopies",
            "type":"Services"
        }
    ],
    "sg:phone":"+61 2 4351 1555",
    "sg:postcode":"2259",
    "sg:province":"NSW",
    "sg:tags":[
        "embroidery"
    ],
    "wof:name":"Central Coast Embroidery",
    "wof:placetype":"venue"
},
  "geometry": {"coordinates":[151.442901611,-33.2666816711],"type":"Point"}
}