{
  "type": "Feature",
  "properties": {
    "addr:full":"529 Old South Head Rd Rose Bay NSW 2029",
    "addr:housenumber":"529",
    "addr:postcode":"2029",
    "addr:street":"Old South Head Rd",
    "iso:country":"AU",
    "sg:address":"529 Old South Head Rd",
    "sg:city":"Rose Bay",
    "sg:classifiers":[
        {
            "category":"Professional",
            "subcategory":"Computer Services",
            "type":"Services"
        }
    ],
    "sg:phone":"+61 2 9388 3278",
    "sg:postcode":"2029",
    "sg:province":"NSW",
    "sg:tags":[
        "training"
    ],
    "wof:name":"Computer Tots/ Computer Explorers",
    "wof:placetype":"venue"
},
  "geometry": {"coordinates":[151.27386474599999,-33.8732337952],"type":"Point"}
}