{
  "type": "Feature",
  "properties": {
    "addr:full":"357 Old Kawkesbury Rd Vineyard NSW 2765",
    "addr:housenumber":"357",
    "addr:postcode":"2765",
    "addr:street":"Old Kawkesbury Rd",
    "iso:country":"AU",
    "sg:address":"357 Old Kawkesbury Rd",
    "sg:city":"Vineyard",
    "sg:classifiers":[
        {
            "category":"Building & Trades",
            "subcategory":"Landscaping Services",
            "type":"Services"
        }
    ],
    "sg:phone":"+61 419 614 271",
    "sg:postcode":"2765",
    "sg:province":"NSW",
    "sg:tags":[
        "firebreak",
        "clearing",
        "land",
        "contractor"
    ],
    "wof:name":"Cut & Clear Landcare",
    "wof:placetype":"venue"
},
  "geometry": {"coordinates":[150.859375,-33.6439361572],"type":"Point"}
}