{
  "type": "Feature",
  "properties": {
    "addr:full":"525 Maroondah Hwy Lilydale VIC 3140",
    "addr:housenumber":"525",
    "addr:postcode":"3140",
    "addr:street":"Maroondah Hwy",
    "iso:country":"AU",
    "sg:address":"525 Maroondah Hwy",
    "sg:city":"Lilydale",
    "sg:classifiers":[
        {
            "category":"Professional",
            "subcategory":"Printing & Photocopies",
            "type":"Services"
        }
    ],
    "sg:phone":"+61 3 9739 0770",
    "sg:postcode":"3140",
    "sg:province":"VIC",
    "sg:tags":[
        "screen",
        "printer"
    ],
    "wof:name":"Screen Machine",
    "wof:placetype":"venue"
},
  "geometry": {"coordinates":[145.37327575699999,-37.7425231934],"type":"Point"}
}