{
  "type": "Feature",
  "properties": {
    "iso:country":"AU",
    "sg:address":"18 Miles St",
    "sg:city":"Mulgrave",
    "sg:classifiers":[
        {
            "category":"Professional",
            "subcategory":"Computer Services",
            "type":"Services"
        }
    ],
    "sg:phone":"+61 3 9561 4088",
    "sg:postcode":"3170",
    "sg:province":"VIC",
    "sg:tags":[
        "package",
        "software"
    ],
    "wof:name":"Schlumberger Technologies",
    "wof:placetype":"venue"
},
  "geometry": {"coordinates":[145.15234375,-37.9234046936],"type":"Point"}
}