{
  "type": "Feature",
  "properties": {
    "addr:full":"10 Blake St Mornington VIC 3931",
    "addr:housenumber":"10",
    "addr:postcode":"3931",
    "addr:street":"Blake St",
    "iso:country":"AU",
    "sg:address":"10 Blake St",
    "sg:city":"Mornington",
    "sg:classifiers":[
        {
            "category":"Cafe",
            "type":"Food & Drink"
        }
    ],
    "sg:phone":"+61 3 5976 3818",
    "sg:postcode":"3931",
    "sg:province":"VIC",
    "wof:name":"D'Vine On Blake Bar & Cafe",
    "wof:placetype":"venue"
},
  "geometry": {"coordinates":[145.03819274899999,-38.2186088562],"type":"Point"}
}