{
  "type": "Feature",
  "properties": {
    "iso:country":"AU",
    "sg:address":"Peak Downs Hwy",
    "sg:city":"Eton",
    "sg:classifiers":[
        {
            "category":"Farming",
            "subcategory":"Farm",
            "type":"Manufacturing & Wholesale Goods"
        }
    ],
    "sg:phone":"+61 7 4954 1314",
    "sg:postcode":"4741",
    "sg:province":"QLD",
    "sg:tags":[
        "farmer"
    ],
    "wof:name":"Knuth E R",
    "wof:placetype":"venue"
},
  "geometry": {"coordinates":[148.969864,-21.266634],"type":"Point"}
}