{
  "type": "Feature",
  "properties": {
    "iso:country":"AU",
    "sg:address":"Commercial Suite-1 1 Honeysuckle Drv",
    "sg:city":"Newcastle",
    "sg:classifiers":[
        {
            "category":"Professional",
            "subcategory":"Business Services",
            "type":"Services"
        }
    ],
    "sg:phone":"+61 2 4926 2199",
    "sg:postcode":"2300",
    "sg:province":"NSW",
    "sg:tags":[
        "broker"
    ],
    "wof:name":"Newcastle Hotel Brokers Pty Ltd",
    "wof:placetype":"venue"
},
  "geometry": {"coordinates":[151.770538,-32.925648],"type":"Point"}
}