{
  "type": "Feature",
  "properties": {
    "addr:full":"2a William St Fairfield NSW 2165",
    "addr:housenumber":"2a",
    "addr:postcode":"2165",
    "addr:street":"William St",
    "iso:country":"AU",
    "sg:address":"2a William St",
    "sg:city":"Fairfield",
    "sg:classifiers":[
        {
            "category":"Health Services",
            "subcategory":"Medical Lab",
            "type":"Services"
        }
    ],
    "sg:phone":"+61 2 9728 6023",
    "sg:postcode":"2165",
    "sg:province":"NSW",
    "sg:tags":[
        "laboratory",
        "pathology"
    ],
    "wof:name":"Central Pathology Services Pty Ltd",
    "wof:placetype":"venue"
},
  "geometry": {"coordinates":[150.95451355,-33.8732643127],"type":"Point"}
}