{
  "type": "Feature",
  "properties": {
    "addr:full":"Wandin North Shopping Centre 6 Union Rd Wandin North VIC 3139",
    "addr:housenumber":"6",
    "addr:postcode":"3139",
    "addr:street":"Centre;Union Rd",
    "iso:country":"AU",
    "sg:address":"Wandin North Shopping Centre 6 Union Rd",
    "sg:city":"Wandin North",
    "sg:classifiers":[
        {
            "category":"Personal",
            "subcategory":"Beauty Salon",
            "type":"Services"
        }
    ],
    "sg:phone":"+61 3 5964 4841",
    "sg:postcode":"3139",
    "sg:province":"VIC",
    "sg:tags":[
        "hairdresser"
    ],
    "wof:name":"Kims Kuts & Kolour",
    "wof:placetype":"venue"
},
  "geometry": {"coordinates":[145.42759704599999,-37.7812614441],"type":"Point"}
}