{
  "type": "Feature",
  "properties": {
    "addr:full":"Suite 3 Cnr Quinns Rd & Mindarie Drv Quinns Rocks WA 6030",
    "addr:housenumber":"cnr",
    "addr:postcode":"6030",
    "addr:street":"Quinns Rd & Mindarie Drv",
    "iso:country":"AU",
    "sg:address":"Suite 3 Cnr Quinns Rd & Mindarie Drv",
    "sg:city":"Quinns Rocks",
    "sg:classifiers":[
        {
            "category":"Health Services",
            "subcategory":"Dentist",
            "type":"Services"
        }
    ],
    "sg:phone":"+61 8 9305 9990",
    "sg:postcode":"6030",
    "sg:province":"WA",
    "wof:name":"Mack Gary",
    "wof:placetype":"venue"
},
  "geometry": {"coordinates":[115.70870208700001,-31.6726989746],"type":"Point"}
}