{
  "type": "Feature",
  "properties": {
    "iso:country":"AU",
    "sg:address":"Stafford St",
    "sg:city":"Murwillumbah",
    "sg:classifiers":[
        {
            "category":"Retail",
            "subcategory":"Auto Repair",
            "type":"Services"
        }
    ],
    "sg:phone":"+61 2 6672 4888",
    "sg:postcode":"2484",
    "sg:province":"NSW",
    "sg:tags":[
        "repairer",
        "motor",
        "engineer"
    ],
    "wof:name":"Murwillumbah Motors",
    "wof:placetype":"venue"
},
  "geometry": {"coordinates":[153.399627686,-28.3299427032],"type":"Point"}
}