{
  "type": "Feature",
  "properties": {
    "iso:country":"AU",
    "sg:address":"52 Jetty Rd",
    "sg:city":"Glenelg",
    "sg:classifiers":[
        {
            "category":"Shopping",
            "subcategory":"Clothing, Apparel, & Fashions",
            "type":"Retail Goods"
        }
    ],
    "sg:phone":"+61 8 8295 2000",
    "sg:postcode":"5045",
    "sg:province":"SA",
    "sg:tags":[
        "menswear"
    ],
    "wof:name":"Ed Harry Menswear",
    "wof:placetype":"venue"
},
  "geometry": {"coordinates":[138.513626,-34.980492],"type":"Point"}
}