{
  "type": "Feature",
  "properties": {
    "addr:full":"20-22 Yalgar Rd Kirrawee NSW 2232",
    "addr:housenumber":"20-22",
    "addr:postcode":"2232",
    "addr:street":"Yalgar Rd",
    "iso:country":"AU",
    "sg:address":"20-22 Yalgar Rd",
    "sg:city":"Kirrawee",
    "sg:classifiers":[
        {
            "category":"Professional",
            "type":"Services"
        }
    ],
    "sg:phone":"+61 2 9521 2622",
    "sg:postcode":"2232",
    "sg:province":"NSW",
    "sg:tags":[
        "shop",
        "fitting"
    ],
    "wof:name":"Adlard Joinery Pty Ltd",
    "wof:placetype":"venue"
},
  "geometry": {"coordinates":[151.072433472,-34.0340003967],"type":"Point"}
}