{
  "type": "Feature",
  "properties": {
    "addr:full":"Cnr Cavendish St & Old Hume Hwy Mittagong NSW 2575",
    "addr:postcode":"2575",
    "addr:street":"Cnr Cavendish St & Old Hume Hwy",
    "iso:country":"AU",
    "sg:address":"Cnr Cavendish St & Old Hume Hwy",
    "sg:city":"Mittagong",
    "sg:classifiers":[
        {
            "category":"Wholesale",
            "subcategory":"Machinery & Supplies",
            "type":"Manufacturing & Wholesale Goods"
        }
    ],
    "sg:phone":"+61 2 4872 1771",
    "sg:postcode":"2575",
    "sg:province":"NSW",
    "sg:tags":[
        "agricultural"
    ],
    "wof:name":"Southern Highlands Truck & Tractor",
    "wof:placetype":"venue"
},
  "geometry": {"coordinates":[150.433868408,-34.4485092163],"type":"Point"}
}