{
  "type": "Feature",
  "properties": {
    "addr:full":"14 Mrs Trivett Pl Fremantle WA 6160",
    "addr:housenumber":"14",
    "addr:postcode":"6160",
    "addr:street":"Pl",
    "iso:country":"AU",
    "sg:address":"14 Mrs Trivett Pl",
    "sg:city":"Fremantle",
    "sg:classifiers":[
        {
            "category":"Communications",
            "subcategory":"News Services",
            "type":"Services"
        }
    ],
    "sg:phone":"+61 8 9336 6897",
    "sg:postcode":"6160",
    "sg:province":"WA",
    "sg:tags":[
        "information",
        "tourist",
        "attractions"
    ],
    "wof:name":"Fremantle Volunteer Heritage Guides Association Inc.",
    "wof:placetype":"venue"
},
  "geometry": {"coordinates":[115.74144699999999,-32.054886],"type":"Point"}
}