{
  "type": "Feature",
  "properties": {
    "addr:full":"Unit 3/ 589 Stirling Hwy Cottesloe WA 6011",
    "addr:housenumber":"/ 589",
    "addr:postcode":"6011",
    "addr:street":"Stirling Hwy",
    "iso:country":"AU",
    "sg:address":"Unit 3/ 589 Stirling Hwy",
    "sg:city":"Cottesloe",
    "sg:classifiers":[
        {
            "category":"Real Estate",
            "subcategory":"Surveying",
            "type":"Services"
        }
    ],
    "sg:phone":"+61 1300 728 485",
    "sg:postcode":"6011",
    "sg:province":"WA",
    "sg:tags":[
        "surveyor",
        "land"
    ],
    "sg:website":"http://www.austinsurveys.com.au",
    "wof:name":"Austin Surveys Pty Ltd",
    "wof:placetype":"venue"
},
  "geometry": {"coordinates":[115.761260986,-31.9998416901],"type":"Point"}
}