{
  "type": "Feature",
  "properties": {
    "addr:full":"9 Cullinane St Black Rock VIC 3193",
    "addr:housenumber":"9",
    "addr:postcode":"3193",
    "addr:street":"Cullinane St",
    "iso:country":"AU",
    "sg:address":"9 Cullinane St",
    "sg:city":"Black Rock",
    "sg:classifiers":[
        {
            "category":"Government",
            "subcategory":"Post Office",
            "type":"Public Place"
        }
    ],
    "sg:phone":"+61 3 9589 4940",
    "sg:postcode":"3193",
    "sg:province":"VIC",
    "sg:tags":[
        "yoga"
    ],
    "wof:name":"Sundari Yoga Centre",
    "wof:placetype":"venue"
},
  "geometry": {"coordinates":[145.02149963400001,-37.9747581482],"type":"Point"}
}