{
  "type": "Feature",
  "properties": {
    "iso:country":"AU",
    "sg:address":"27 Central Rd",
    "sg:city":"Unanderra",
    "sg:classifiers":[
        {
            "category":"Travel",
            "subcategory":"Hotels & Motels",
            "type":"Entertainment"
        }
    ],
    "sg:phone":"+61 2 4271 1141",
    "sg:postcode":"2526",
    "sg:province":"NSW",
    "sg:tags":[
        "accommodation"
    ],
    "wof:name":"Unanderra Hotel",
    "wof:placetype":"venue"
},
  "geometry": {"coordinates":[150.84378051799999,-34.4519348145],"type":"Point"}
}