{
  "type": "Feature",
  "properties": {
    "addr:full":"62 Bridge St Bendigo VIC 3550",
    "addr:housenumber":"62",
    "addr:postcode":"3550",
    "addr:street":"Bridge St",
    "iso:country":"AU",
    "sg:address":"62 Bridge St",
    "sg:city":"Bendigo",
    "sg:classifiers":[
        {
            "category":"Personal",
            "subcategory":"Beauty Salon",
            "type":"Services"
        }
    ],
    "sg:phone":"+61 3 5443 3422",
    "sg:postcode":"3550",
    "sg:province":"VIC",
    "sg:tags":[
        "hairdresser"
    ],
    "wof:name":"Bendigo Beauty & Haircare Specialists",
    "wof:placetype":"venue"
},
  "geometry": {"coordinates":[144.28500366200001,-36.7509002686],"type":"Point"}
}