{
  "type": "Feature",
  "properties": {
    "addr:full":"McDonalds Drain Rd Koo Wee Rup VIC 3981",
    "addr:postcode":"3981",
    "addr:street":"Drain Rd",
    "iso:country":"AU",
    "sg:address":"McDonalds Drain Rd",
    "sg:city":"Koo Wee Rup",
    "sg:classifiers":[
        {
            "category":"Professional",
            "subcategory":"Engineering",
            "type":"Services"
        }
    ],
    "sg:phone":"+61 3 5997 2223",
    "sg:postcode":"3981",
    "sg:province":"VIC",
    "sg:tags":[
        "engineer"
    ],
    "wof:name":"A & M Wright Engineering",
    "wof:placetype":"venue"
},
  "geometry": {"coordinates":[145.48200988799999,-38.1921424866],"type":"Point"}
}