{
  "type": "Feature",
  "properties": {
    "addr:full":"22 Rene Rd Launceston TAS 7250",
    "addr:housenumber":"22",
    "addr:postcode":"7250",
    "addr:street":"Rene Rd",
    "iso:country":"AU",
    "sg:address":"22 Rene Rd",
    "sg:city":"Launceston",
    "sg:classifiers":[
        {
            "category":"Building & Trades",
            "subcategory":"Construction",
            "type":"Services"
        }
    ],
    "sg:phone":"+61 3 6343 5770",
    "sg:postcode":"7250",
    "sg:province":"TAS",
    "sg:tags":[
        "renovation",
        "alterations",
        "extension",
        "contractor"
    ],
    "wof:name":"Addon Home Improvements",
    "wof:placetype":"venue"
},
  "geometry": {"coordinates":[147.12367248499999,-41.4668083191],"type":"Point"}
}