{
  "type": "Feature",
  "properties": {
    "addr:full":"Wannaeue Pl Rosebud VIC 3939",
    "addr:postcode":"3939",
    "addr:street":"Wannaeue Pl",
    "iso:country":"AU",
    "sg:address":"Wannaeue Pl",
    "sg:city":"Rosebud",
    "sg:classifiers":[
        {
            "category":"Food & Beverages",
            "subcategory":"Supermarket",
            "type":"Retail Goods"
        }
    ],
    "sg:phone":"+61 3 5981 2066",
    "sg:postcode":"3939",
    "sg:province":"VIC",
    "sg:tags":[
        "grocery",
        "store"
    ],
    "wof:name":"Franklins Fresh Rosebud",
    "wof:placetype":"venue"
},
  "geometry": {"coordinates":[144.90545654300001,-38.3563766479],"type":"Point"}
}