{
  "type": "Feature",
  "properties": {
    "addr:full":"11 Fullarton Rd Kent Town SA 5067",
    "addr:housenumber":"11",
    "addr:postcode":"5067",
    "addr:street":"Fullarton Rd",
    "iso:country":"AU",
    "sg:address":"11 Fullarton Rd",
    "sg:city":"Kent Town",
    "sg:classifiers":[
        {
            "category":"Personal",
            "subcategory":"Adult",
            "type":"Services"
        }
    ],
    "sg:phone":"+61 8 8363 2090",
    "sg:postcode":"5067",
    "sg:province":"SA",
    "sg:tags":[
        "entertainment"
    ],
    "wof:name":"Eden Relaxation Centre",
    "wof:placetype":"venue"
},
  "geometry": {"coordinates":[138.62294006400001,-34.9199295044],"type":"Point"}
}