{
  "type": "Feature",
  "properties": {
    "addr:full":"48 Eastern Ave Dover Heights NSW 2030",
    "addr:housenumber":"48",
    "addr:postcode":"2030",
    "addr:street":"Eastern Ave Dover",
    "iso:country":"AU",
    "sg:address":"48 Eastern Ave",
    "sg:city":"Dover Heights",
    "sg:classifiers":[
        {
            "category":"Professional",
            "subcategory":"Art Services",
            "type":"Services"
        }
    ],
    "sg:phone":"+61 2 9337 4206",
    "sg:postcode":"2030",
    "sg:province":"NSW",
    "sg:tags":[
        "graphic",
        "designer"
    ],
    "wof:name":"Aliferis G",
    "wof:placetype":"venue"
},
  "geometry": {"coordinates":[151.28306579599999,-33.8659667969],"type":"Point"}
}