{
  "type": "Feature",
  "properties": {
    "iso:country":"AU",
    "sg:address":"720 Anzac Hwy",
    "sg:city":"Glenelg",
    "sg:classifiers":[
        {
            "category":"Health Services",
            "subcategory":"Chiropractor",
            "type":"Services"
        }
    ],
    "sg:phone":"+61 8 8294 6754",
    "sg:postcode":"5045",
    "sg:province":"SA",
    "wof:name":"Noonan Bill",
    "wof:placetype":"venue"
},
  "geometry": {"coordinates":[138.51620500000001,-34.976704],"type":"Point"}
}