{
  "type": "Feature",
  "properties": {
    "addr:full":"11 Hilltop Rd Wamberal NSW 2260",
    "addr:housenumber":"11",
    "addr:postcode":"2260",
    "addr:street":"Hilltop Rd",
    "iso:country":"AU",
    "sg:address":"11 Hilltop Rd",
    "sg:city":"Wamberal",
    "sg:classifiers":[
        {
            "category":"Health Services",
            "subcategory":"Doctor",
            "type":"Services"
        }
    ],
    "sg:phone":"+61 416 257 088",
    "sg:postcode":"2260",
    "sg:province":"NSW",
    "sg:tags":[
        "reflexology"
    ],
    "wof:name":"Bocking Martin",
    "wof:placetype":"venue"
},
  "geometry": {"coordinates":[151.44238300000001,-33.427807],"type":"Point"}
}