{
  "type": "Feature",
  "properties": {
    "addr:full":"9 Mitchell St Norah Head NSW 2263",
    "addr:housenumber":"9",
    "addr:postcode":"2263",
    "addr:street":"Mitchell St Norah",
    "iso:country":"AU",
    "sg:address":"9 Mitchell St",
    "sg:city":"Norah Head",
    "sg:classifiers":[
        {
            "category":"Restaurant",
            "type":"Food & Drink"
        }
    ],
    "sg:phone":"+61 2 4396 4507",
    "sg:postcode":"2263",
    "sg:province":"NSW",
    "sg:website":"http://www.shorethymerestaurant.com.au",
    "wof:name":"Shorethyme Restaurant",
    "wof:placetype":"venue"
},
  "geometry": {"coordinates":[151.565506,-33.279083],"type":"Point"}
}