{
  "type": "Feature",
  "properties": {
    "addr:full":"12 Elvys Ave Saratoga NSW 2251",
    "addr:housenumber":"12",
    "addr:postcode":"2251",
    "addr:street":"Elvys Ave",
    "iso:country":"AU",
    "sg:address":"12 Elvys Ave",
    "sg:city":"Saratoga",
    "sg:classifiers":[
        {
            "category":"Building & Trades",
            "subcategory":"Landscaping Services",
            "type":"Services"
        }
    ],
    "sg:phone":"+61 1300 666 577",
    "sg:postcode":"2251",
    "sg:province":"NSW",
    "sg:tags":[
        "stump",
        "tree",
        "felling",
        "removal"
    ],
    "wof:name":"Argonauts Tree & Timber Service",
    "wof:placetype":"venue"
},
  "geometry": {"coordinates":[151.36216735799999,-33.470703125],"type":"Point"}
}