{
  "type": "Feature",
  "properties": {
    "addr:full":"256 Adelaide Tce Perth WA 6000",
    "addr:housenumber":"256",
    "addr:postcode":"6000",
    "addr:street":"Adelaide Tce",
    "iso:country":"AU",
    "sg:address":"256 Adelaide Tce",
    "sg:city":"Perth",
    "sg:classifiers":[
        {
            "category":"Cafe",
            "type":"Food & Drink"
        }
    ],
    "sg:phone":"+61 8 9325 2384",
    "sg:postcode":"6000",
    "sg:province":"WA",
    "wof:name":"Riccardo's Coffee Lounge",
    "wof:placetype":"venue"
},
  "geometry": {"coordinates":[115.864898682,-31.9584579468],"type":"Point"}
}