{
  "type": "Feature",
  "properties": {
    "iso:country":"AU",
    "sg:address":"190 Currie St",
    "sg:city":"Nambour",
    "sg:classifiers":[
        {
            "category":"Retail",
            "subcategory":"Auto Repair",
            "type":"Services"
        }
    ],
    "sg:phone":"+61 7 5476 4477",
    "sg:postcode":"4560",
    "sg:province":"QLD",
    "sg:tags":[
        "repairer",
        "motor",
        "engineer"
    ],
    "wof:name":"Nambour Automatics",
    "wof:placetype":"venue"
},
  "geometry": {"coordinates":[152.96002197300001,-26.630947113],"type":"Point"}
}