{
  "type": "Feature",
  "properties": {
    "addr:full":"7 Leader St Campbellfield VIC 3061",
    "addr:housenumber":"7",
    "addr:postcode":"3061",
    "addr:street":"Leader St",
    "iso:country":"AU",
    "sg:address":"7 Leader St",
    "sg:city":"Campbellfield",
    "sg:classifiers":[
        {
            "category":"Manufacturing",
            "subcategory":"Chemicals & Compounds",
            "type":"Manufacturing & Wholesale Goods"
        }
    ],
    "sg:phone":"+61 3 9308 6888",
    "sg:postcode":"3061",
    "sg:province":"VIC",
    "sg:tags":[
        "industrial"
    ],
    "wof:name":"Global Speciality Chemicals",
    "wof:placetype":"venue"
},
  "geometry": {"coordinates":[144.94424438499999,-37.6434402466],"type":"Point"}
}