{
  "type": "Feature",
  "properties": {
    "addr:full":"2 O'Loughlin St North Mackay QLD 4740",
    "addr:housenumber":"2",
    "addr:postcode":"4740",
    "addr:street":"O'Loughlin St",
    "iso:country":"AU",
    "sg:address":"2 O'Loughlin St",
    "sg:city":"North Mackay",
    "sg:classifiers":[
        {
            "category":"Professional",
            "type":"Services"
        }
    ],
    "sg:phone":"+61 7 4951 2551",
    "sg:postcode":"4740",
    "sg:province":"QLD",
    "sg:tags":[
        "control",
        "equipment",
        "traffic"
    ],
    "wof:name":"East Coast Traffic Control Pty Ltd",
    "wof:placetype":"venue"
},
  "geometry": {"coordinates":[149.19430500000001,-21.118513],"type":"Point"}
}