{
  "type": "Feature",
  "properties": {
    "iso:country":"AU",
    "sg:address":"Ash Rd",
    "sg:city":"Leopold",
    "sg:classifiers":[
        {
            "category":"Arts & Performance",
            "subcategory":"Dance",
            "type":"Entertainment"
        }
    ],
    "sg:phone":"+61 418 404 543",
    "sg:postcode":"3224",
    "sg:province":"VIC",
    "sg:tags":[
        "theatrical",
        "ballet",
        "tuition"
    ],
    "wof:name":"Bellarine Academy of Dance",
    "wof:placetype":"venue"
},
  "geometry": {"coordinates":[144.46740700000001,-38.196823],"type":"Point"}
}