{
  "type": "Feature",
  "properties": {
    "addr:full":"49 Railway St Yennora NSW 2161",
    "addr:housenumber":"49",
    "addr:postcode":"2161",
    "addr:street":"Railway St",
    "iso:country":"AU",
    "sg:address":"49 Railway St",
    "sg:city":"Yennora",
    "sg:classifiers":[
        {
            "category":"Building & Trades",
            "subcategory":"Equipment Rental",
            "type":"Services"
        }
    ],
    "sg:phone":"+61 2 9681 6544",
    "sg:postcode":"2161",
    "sg:province":"NSW",
    "sg:tags":[
        "supply",
        "catering"
    ],
    "wof:name":"Bakery Service",
    "wof:placetype":"venue"
},
  "geometry": {"coordinates":[150.967254639,-33.8671417236],"type":"Point"}
}