{
  "type": "Feature",
  "properties": {
    "addr:full":"68 Kensington Rd Rose Park SA 5067",
    "addr:housenumber":"68",
    "addr:postcode":"5067",
    "addr:street":"Kensington Rd Rose",
    "iso:country":"AU",
    "sg:address":"68 Kensington Rd",
    "sg:city":"Rose Park",
    "sg:classifiers":[
        {
            "category":"Health Services",
            "subcategory":"Doctor",
            "type":"Services"
        }
    ],
    "sg:phone":"+61 8 8431 6955",
    "sg:postcode":"5067",
    "sg:province":"SA",
    "sg:tags":[
        "medical",
        "practitioner"
    ],
    "wof:name":"Della Neil G",
    "wof:placetype":"venue"
},
  "geometry": {"coordinates":[138.628295898,-34.9274902344],"type":"Point"}
}