{
  "type": "Feature",
  "properties": {
    "iso:country":"AU",
    "sg:address":"374 Liverpool Rd",
    "sg:city":"Ashfield",
    "sg:classifiers":[
        {
            "category":"Restaurant",
            "type":"Food & Drink"
        }
    ],
    "sg:phone":"+61 2 9797 8878",
    "sg:postcode":"2131",
    "sg:province":"NSW",
    "wof:name":"Ashfield RSL Club",
    "wof:placetype":"venue"
},
  "geometry": {"coordinates":[151.11721801799999,-33.8886489868],"type":"Point"}
}