{
  "type": "Feature",
  "properties": {
    "iso:country":"AU",
    "sg:address":"Shop 5, Beaumonts Gardens Bowral Rd",
    "sg:city":"Mittagong",
    "sg:classifiers":[
        {
            "category":"Personal",
            "subcategory":"Beauty Salon",
            "type":"Services"
        }
    ],
    "sg:phone":"+61 2 4872 1751",
    "sg:postcode":"2575",
    "sg:province":"NSW",
    "sg:tags":[
        "hairdresser"
    ],
    "wof:name":"Lisa Annes Hair Design",
    "wof:placetype":"venue"
},
  "geometry": {"coordinates":[150.44679260300001,-34.4513473511],"type":"Point"}
}