{
  "type": "Feature",
  "properties": {
    "addr:full":"257 Heaths Rd Hoppers Crossing VIC 3029",
    "addr:housenumber":"257",
    "addr:postcode":"3029",
    "addr:street":"Heaths Rd",
    "iso:country":"AU",
    "sg:address":"257 Heaths Rd",
    "sg:city":"Hoppers Crossing",
    "sg:classifiers":[
        {
            "category":"Professional",
            "subcategory":"Computer Services",
            "type":"Services"
        }
    ],
    "sg:phone":"+61 3 9749 4138",
    "sg:postcode":"3029",
    "sg:province":"VIC",
    "sg:tags":[
        "repairs",
        "upgrade",
        "equipment"
    ],
    "wof:name":"Trinomic Computer Solutions",
    "wof:placetype":"venue"
},
  "geometry": {"coordinates":[144.678314,-37.877171],"type":"Point"}
}