{
  "type": "Feature",
  "properties": {
    "addr:full":"53 Dalton Rd St Ives NSW 2075",
    "addr:housenumber":"53",
    "addr:postcode":"2075",
    "addr:street":"Dalton Rd",
    "iso:country":"AU",
    "sg:address":"53 Dalton Rd St",
    "sg:city":"Ives",
    "sg:classifiers":[
        {
            "category":"Health Services",
            "subcategory":"Health Practitioner",
            "type":"Services"
        }
    ],
    "sg:phone":"+61 2 9144 6176",
    "sg:postcode":"2075",
    "sg:province":"NSW",
    "sg:tags":[
        "pathologist",
        "speech"
    ],
    "wof:name":"Rubinstein Sharon",
    "wof:placetype":"venue"
},
  "geometry": {"coordinates":[151.163696289,-33.710609436],"type":"Point"}
}