{
  "type": "Feature",
  "properties": {
    "addr:full":"603 Jerusalem Creek Rd Eildon VIC 3713",
    "addr:housenumber":"603",
    "addr:postcode":"3713",
    "addr:street":"Jerusalem Creek Rd",
    "iso:country":"AU",
    "sg:address":"603 Jerusalem Creek Rd",
    "sg:city":"Eildon",
    "sg:classifiers":[
        {
            "category":"Recreation",
            "subcategory":"Marina",
            "type":"Entertainment"
        }
    ],
    "sg:phone":"+61 3 5774 2414",
    "sg:postcode":"3713",
    "sg:province":"VIC",
    "wof:name":"Darlingford Waters Marina",
    "wof:placetype":"venue"
},
  "geometry": {"coordinates":[145.959640503,-37.2525024414],"type":"Point"}
}