{
  "type": "Feature",
  "properties": {
    "addr:full":"3374 Pacific Hwy Springwood QLD 4127",
    "addr:housenumber":"3374",
    "addr:postcode":"4127",
    "addr:street":"Pacific Hwy",
    "iso:country":"AU",
    "sg:address":"3374 Pacific Hwy",
    "sg:city":"Springwood",
    "sg:classifiers":[
        {
            "category":"Structure",
            "subcategory":"Office Building",
            "type":"Public Place"
        }
    ],
    "sg:phone":"+61 7 3387 7777",
    "sg:postcode":"4127",
    "sg:province":"QLD",
    "sg:tags":[
        "serviced"
    ],
    "sg:website":"http://www.highpointbc.com.au",
    "wof:name":"Highpoint Business Centre",
    "wof:placetype":"venue"
},
  "geometry": {"coordinates":[153.126754761,-27.6198043823],"type":"Point"}
}