{
  "type": "Feature",
  "properties": {
    "addr:full":"McLean St Coolangatta QLD 4225",
    "addr:postcode":"4225",
    "addr:street":"Mclean St",
    "iso:country":"AU",
    "sg:address":"McLean St",
    "sg:city":"Coolangatta",
    "sg:classifiers":[
        {
            "category":"Fast Food",
            "type":"Food & Drink"
        }
    ],
    "sg:phone":"+61 7 5536 2690",
    "sg:postcode":"4225",
    "sg:province":"QLD",
    "sg:tags":[
        "away",
        "take"
    ],
    "wof:name":"Little Malaya Restaurant Pty Ltd",
    "wof:placetype":"venue"
},
  "geometry": {"coordinates":[153.53810119600001,-28.1672725677],"type":"Point"}
}