{
  "type": "Feature",
  "properties": {
    "addr:full":"37 Wildflower Crs Hoppers Crossing VIC 3029",
    "addr:housenumber":"37",
    "addr:postcode":"3029",
    "addr:street":"Wildflower Crs",
    "iso:country":"AU",
    "sg:address":"37 Wildflower Crs",
    "sg:city":"Hoppers Crossing",
    "sg:classifiers":[
        {
            "category":"Professional",
            "subcategory":"Engineering",
            "type":"Services"
        }
    ],
    "sg:phone":"+61 417 370 743",
    "sg:postcode":"3029",
    "sg:province":"VIC",
    "sg:tags":[
        "engineer"
    ],
    "wof:name":"R & S Machine Maintenance Services",
    "wof:placetype":"venue"
},
  "geometry": {"coordinates":[144.703934,-37.864319],"type":"Point"}
}