{
  "type": "Feature",
  "properties": {
    "addr:full":"83 Turner Rd Berowra Heights NSW 2082",
    "addr:housenumber":"83",
    "addr:postcode":"2082",
    "addr:street":"Turner Rd",
    "iso:country":"AU",
    "sg:address":"83 Turner Rd",
    "sg:city":"Berowra Heights",
    "sg:classifiers":[
        {
            "category":"Professional",
            "type":"Services"
        }
    ],
    "sg:phone":"+61 412 445 757",
    "sg:postcode":"2082",
    "sg:province":"NSW",
    "sg:tags":[
        "courier"
    ],
    "wof:name":"Berowra Couriers",
    "wof:placetype":"venue"
},
  "geometry": {"coordinates":[151.13499450699999,-33.6062355042],"type":"Point"}
}