{
  "type": "Feature",
  "properties": {
    "addr:full":"40 Eurora St Kingston QLD 4114",
    "addr:housenumber":"40",
    "addr:postcode":"4114",
    "addr:street":"Eurora St",
    "iso:country":"AU",
    "sg:address":"40 Eurora St",
    "sg:city":"Kingston",
    "sg:classifiers":[
        {
            "category":"Professional",
            "type":"Services"
        }
    ],
    "sg:phone":"+61 7 3808 5867",
    "sg:postcode":"4114",
    "sg:province":"QLD",
    "sg:tags":[
        "transport"
    ],
    "wof:name":"MacTrans Qld Pty Ltd",
    "wof:placetype":"venue"
},
  "geometry": {"coordinates":[153.11778259299999,-27.6648273468],"type":"Point"}
}