{
  "type": "Feature",
  "properties": {
    "addr:full":"PO Box 110 Woody Point QLD 4019",
    "addr:postcode":"4019",
    "iso:country":"AU",
    "sg:address":"PO Box 110",
    "sg:city":"Woody Point",
    "sg:classifiers":[
        {
            "category":"Airline",
            "type":"Transportation"
        }
    ],
    "sg:phone":"+61 7 3283 1325",
    "sg:postcode":"4019",
    "sg:province":"QLD",
    "sg:tags":[
        "aircraft",
        "rental",
        "charter"
    ],
    "wof:name":"Wallaby Air Tours",
    "wof:placetype":"venue"
},
  "geometry": {"coordinates":[153.10220336899999,-27.2587890625],"type":"Point"}
}