{
  "type": "Feature",
  "properties": {
    "iso:country":"AU",
    "sg:address":"Lot 867 Marmont St",
    "sg:city":"Meekatharra",
    "sg:classifiers":[
        {
            "category":"Professional",
            "type":"Services"
        }
    ],
    "sg:phone":"+61 8 9980 1344",
    "sg:postcode":"6642",
    "sg:province":"WA",
    "sg:tags":[
        "transport"
    ],
    "wof:name":"Centurion",
    "wof:placetype":"venue"
},
  "geometry": {"coordinates":[118.501083374,-26.5977058411],"type":"Point"}
}