{
  "type": "Feature",
  "properties": {
    "addr:full":"PO Box 912 Inverell NSW 2360",
    "addr:postcode":"2360",
    "iso:country":"AU",
    "sg:address":"PO Box 912",
    "sg:city":"Inverell",
    "sg:classifiers":[
        {
            "category":"Building & Trades",
            "subcategory":"Construction",
            "type":"Services"
        }
    ],
    "sg:phone":"+61 2 6721 4000",
    "sg:postcode":"2360",
    "sg:province":"NSW",
    "sg:tags":[
        "contractor"
    ],
    "wof:name":"Bannister Group",
    "wof:placetype":"venue"
},
  "geometry": {"coordinates":[151.113555908,-29.776309967],"type":"Point"}
}