{
  "type": "Feature",
  "properties": {
    "addr:full":"RMB H974 Jubilee Rd Sulky VIC 3364",
    "addr:postcode":"3364",
    "addr:street":"Jubilee Rd",
    "iso:country":"AU",
    "sg:address":"RMB H974 Jubilee Rd",
    "sg:city":"Sulky",
    "sg:classifiers":[
        {
            "category":"Farming",
            "subcategory":"Vineyard",
            "type":"Manufacturing & Wholesale Goods"
        }
    ],
    "sg:phone":"+61 3 5334 6440",
    "sg:postcode":"3364",
    "sg:province":"VIC",
    "sg:tags":[
        "winery"
    ],
    "wof:name":"Dulcinea Vineyard",
    "wof:placetype":"venue"
},
  "geometry": {"coordinates":[143.83877563499999,-37.4609985352],"type":"Point"}
}