{
  "type": "Feature",
  "properties": {
    "iso:country":"AU",
    "sg:address":"213 Coogee Bay Rd",
    "sg:city":"Coogee",
    "sg:classifiers":[
        {
            "category":"Travel",
            "subcategory":"Hotels & Motels",
            "type":"Entertainment"
        }
    ],
    "sg:phone":"+61 2 9664 8526",
    "sg:postcode":"2034",
    "sg:province":"NSW",
    "sg:tags":[
        "accommodation"
    ],
    "wof:name":"Coogee Bayside Private Hotel",
    "wof:placetype":"venue"
},
  "geometry": {"coordinates":[151.25494384800001,-33.9206466675],"type":"Point"}
}