{
  "type": "Feature",
  "properties": {
    "addr:full":"PO Box 75 Bowning ACT 2582",
    "addr:postcode":"2582",
    "iso:country":"AU",
    "sg:address":"PO Box 75",
    "sg:city":"Bowning",
    "sg:classifiers":[
        {
            "category":"Building & Trades",
            "subcategory":"Construction",
            "type":"Services"
        }
    ],
    "sg:phone":"+61 412 288 105",
    "sg:postcode":"2582",
    "sg:province":"ACT",
    "sg:tags":[
        "fencing",
        "contractor"
    ],
    "wof:name":"A Upright Fencing",
    "wof:placetype":"venue"
},
  "geometry": {"coordinates":[148.80133056599999,-34.9616699219],"type":"Point"}
}