{
  "type": "Feature",
  "properties": {
    "addr:full":"11 Grosvenor La Neutral Bay NSW 2089",
    "addr:housenumber":"11",
    "addr:postcode":"2089",
    "addr:street":"Grosvenor La",
    "iso:country":"AU",
    "sg:address":"11 Grosvenor La",
    "sg:city":"Neutral Bay",
    "sg:classifiers":[
        {
            "category":"Professional",
            "subcategory":"Management & Consulting",
            "type":"Services"
        }
    ],
    "sg:phone":"+61 2 9908 8071",
    "sg:postcode":"2089",
    "sg:province":"NSW",
    "sg:tags":[
        "consultant"
    ],
    "wof:name":"Business Crossroad Solutions",
    "wof:placetype":"venue"
},
  "geometry": {"coordinates":[151.222366333,-33.8308944702],"type":"Point"}
}