{
  "type": "Feature",
  "properties": {
    "addr:full":"149-197 Pyrmont St Pyrmont NSW 2009",
    "addr:housenumber":"149-197",
    "addr:postcode":"2009",
    "addr:street":"Pyrmont St",
    "iso:country":"AU",
    "sg:address":"149-197 Pyrmont St",
    "sg:city":"Pyrmont",
    "sg:classifiers":[
        {
            "category":"Real Estate",
            "subcategory":"Real Estate Agent",
            "type":"Services"
        }
    ],
    "sg:phone":"+61 2 9660 9466",
    "sg:postcode":"2009",
    "sg:province":"NSW",
    "wof:name":"Paragon Apartment Management Pty Ltd",
    "wof:placetype":"venue"
},
  "geometry": {"coordinates":[151.195709228,-33.8709793091],"type":"Point"}
}