{
  "type": "Feature",
  "properties": {
    "iso:country":"AU",
    "sg:address":"1264 Heatherton Rd",
    "sg:city":"Noble Park",
    "sg:classifiers":[
        {
            "category":"Food & Beverages",
            "subcategory":"Supermarket",
            "type":"Retail Goods"
        }
    ],
    "sg:phone":"+61 3 9546 7156",
    "sg:postcode":"3174",
    "sg:province":"VIC",
    "sg:tags":[
        "grocery",
        "store"
    ],
    "wof:name":"Heatherton Road Licensed Supermarket",
    "wof:placetype":"venue"
},
  "geometry": {"coordinates":[145.18634033199999,-37.9666061401],"type":"Point"}
}