{
  "type": "Feature",
  "properties": {
    "iso:country":"AU",
    "sg:address":"295 Old Northern Rd",
    "sg:city":"Castle Hill",
    "sg:classifiers":[
        {
            "category":"Fast Food",
            "type":"Food & Drink"
        }
    ],
    "sg:phone":"+61 2 9634 5433",
    "sg:postcode":"2154",
    "sg:province":"NSW",
    "sg:tags":[
        "away",
        "take"
    ],
    "wof:name":"Saltwater Seafoods",
    "wof:placetype":"venue"
},
  "geometry": {"coordinates":[151.00572204599999,-33.7325172424],"type":"Point"}
}