{
  "type": "Feature",
  "properties": {
    "addr:full":"4 Oldham Road Eliz Sth Elizabeth South SA 5112",
    "addr:housenumber":"4",
    "addr:postcode":"5112",
    "addr:street":"Oldham Road Eliz Sth",
    "iso:country":"AU",
    "sg:address":"4 Oldham Road",
    "sg:city":"Eliz Sth Elizabeth South",
    "sg:classifiers":[
        {
            "category":"Landmark",
            "subcategory":"Scenic View",
            "type":"Public Place"
        }
    ],
    "sg:phone":"+61 1300 131 124",
    "sg:postcode":"5112",
    "sg:province":"SA",
    "sg:tags":[
        "staircase",
        "handrail"
    ],
    "wof:name":"Stair Lock International P/L",
    "wof:placetype":"venue"
},
  "geometry": {"coordinates":[138.65907287600001,-34.7456359863],"type":"Point"}
}