{
  "type": "Feature",
  "properties": {
    "iso:country":"AU",
    "sg:address":"33 Mertin St",
    "sg:city":"Bourke",
    "sg:classifiers":[
        {
            "category":"Travel",
            "subcategory":"Hotels & Motels",
            "type":"Entertainment"
        }
    ],
    "sg:phone":"+61 2 6872 2716",
    "sg:postcode":"2840",
    "sg:province":"NSW",
    "wof:name":"Outback Motel The",
    "wof:placetype":"venue"
},
  "geometry": {"coordinates":[145.940842,-30.091764],"type":"Point"}
}