{
  "type": "Feature",
  "properties": {
    "addr:full":"180 Clegg Rd Mt Evelyn VIC 3796",
    "addr:housenumber":"180",
    "addr:postcode":"3796",
    "addr:street":"Clegg Rd",
    "iso:country":"AU",
    "sg:address":"180 Clegg Rd",
    "sg:city":"Mt Evelyn",
    "sg:classifiers":[
        {
            "category":"Utilities",
            "subcategory":"Electric",
            "type":"Services"
        }
    ],
    "sg:phone":"+61 3 9737 1244",
    "sg:postcode":"3796",
    "sg:province":"VIC",
    "sg:tags":[
        "electrical",
        "contractor"
    ],
    "wof:name":"Contech Electrical Pty Ltd",
    "wof:placetype":"venue"
},
  "geometry": {"coordinates":[145.40609741200001,-37.7841072083],"type":"Point"}
}