{
  "type": "Feature",
  "properties": {
    "iso:country":"AU",
    "sg:address":"128 Marion Rd",
    "sg:city":"West Richmond",
    "sg:classifiers":[
        {
            "category":"Autos & Motor Vehicles",
            "subcategory":"Auto Supplies",
            "type":"Retail Goods"
        }
    ],
    "sg:phone":"+61 8 8351 9939",
    "sg:postcode":"5033",
    "sg:province":"SA",
    "sg:tags":[
        "tyre"
    ],
    "wof:name":"Marion Discount Tyres",
    "wof:placetype":"venue"
},
  "geometry": {"coordinates":[138.552658081,-34.9365119934],"type":"Point"}
}