{
  "type": "Feature",
  "properties": {
    "iso:country":"AU",
    "sg:address":"Unit 2/ 29 Storey St",
    "sg:city":"Maroubra",
    "sg:classifiers":[
        {
            "category":"Health Services",
            "subcategory":"Dentist",
            "type":"Services"
        }
    ],
    "sg:phone":"+61 2 9344 4270",
    "sg:postcode":"2035",
    "sg:province":"NSW",
    "sg:tags":[
        "dental",
        "prosthetist"
    ],
    "wof:name":"Krutik Isaak",
    "wof:placetype":"venue"
},
  "geometry": {"coordinates":[151.23646545400001,-33.9364013672],"type":"Point"}
}