{
  "type": "Feature",
  "properties": {
    "addr:full":"PO Box 1395 Charters Towers QLD 4820",
    "addr:postcode":"4820",
    "iso:country":"AU",
    "sg:address":"PO Box 1395",
    "sg:city":"Charters Towers",
    "sg:classifiers":[
        {
            "category":"Building & Trades",
            "subcategory":"Locksmith",
            "type":"Services"
        }
    ],
    "sg:phone":"+61 405 408 958",
    "sg:postcode":"4820",
    "sg:province":"QLD",
    "sg:tags":[
        "lock"
    ],
    "wof:name":"Towers Lock & Key",
    "wof:placetype":"venue"
},
  "geometry": {"coordinates":[146.26315299999999,-20.0774],"type":"Point"}
}