{
  "type": "Feature",
  "properties": {
    "addr:full":"Off Rands Rd Timboon VIC 3268",
    "addr:postcode":"3268",
    "addr:street":"Rands Rd",
    "iso:country":"AU",
    "sg:address":"Off Rands Rd",
    "sg:city":"Timboon",
    "sg:classifiers":[
        {
            "category":"Building & Trades",
            "subcategory":"Construction",
            "type":"Services"
        }
    ],
    "sg:phone":"+61 3 5598 3218",
    "sg:postcode":"3268",
    "sg:province":"VIC",
    "sg:tags":[
        "concrete",
        "contractor"
    ],
    "wof:name":"Togni F L & L F",
    "wof:placetype":"venue"
},
  "geometry": {"coordinates":[142.98219299300001,-38.4841461182],"type":"Point"}
}