{
  "type": "Feature",
  "properties": {
    "iso:country":"AU",
    "sg:address":"126 Raymond St",
    "sg:city":"Sale",
    "sg:classifiers":[
        {
            "category":"Health Services",
            "subcategory":"Dentist",
            "type":"Services"
        }
    ],
    "sg:phone":"+61 3 5144 3588",
    "sg:postcode":"3850",
    "sg:province":"VIC",
    "wof:name":"Kor I Dr",
    "wof:placetype":"venue"
},
  "geometry": {"coordinates":[147.06588745100001,-38.1102752686],"type":"Point"}
}