{
  "type": "Feature",
  "properties": {
    "iso:country":"AU",
    "sg:address":"3230 Old Nothern Rd",
    "sg:city":"Glenorie",
    "sg:classifiers":[
        {
            "category":"Social Services",
            "subcategory":"Retirement Home",
            "type":"Services"
        }
    ],
    "sg:phone":"+61 2 9652 2037",
    "sg:postcode":"2157",
    "sg:province":"NSW",
    "sg:tags":[
        "environmental",
        "consultant",
        "pollution"
    ],
    "wof:name":"Environmental Performance Australia Pty Ltd",
    "wof:placetype":"venue"
},
  "geometry": {"coordinates":[151.01292419399999,-33.5482406616],"type":"Point"}
}