{
  "type": "Feature",
  "properties": {
    "addr:full":"258 Manns Rd Gosford West NSW 2250",
    "addr:housenumber":"258",
    "addr:postcode":"2250",
    "addr:street":"Manns Rd",
    "iso:country":"AU",
    "sg:address":"258 Manns Rd",
    "sg:city":"Gosford West",
    "sg:classifiers":[
        {
            "category":"Utilities",
            "subcategory":"Natural Gas",
            "type":"Services"
        }
    ],
    "sg:phone":"+61 2 4324 5444",
    "sg:postcode":"2250",
    "sg:province":"NSW",
    "sg:tags":[
        "supplier"
    ],
    "wof:name":"BOC Safety",
    "wof:placetype":"venue"
},
  "geometry": {"coordinates":[151.31942749000001,-33.4244346619],"type":"Point"}
}