{
  "type": "Feature",
  "properties": {
    "iso:country":"AU",
    "sg:address":"Blue Eagle Drv",
    "sg:city":"Meadowbrook",
    "sg:classifiers":[
        {
            "category":"Health Services",
            "subcategory":"Nursing And Care Facility",
            "type":"Services"
        }
    ],
    "sg:phone":"+61 7 3299 9090",
    "sg:postcode":"4131",
    "sg:province":"QLD",
    "sg:tags":[
        "treatment",
        "preservation",
        "timber"
    ],
    "wof:name":"Timbertec Treatment Pty Ltd",
    "wof:placetype":"venue"
},
  "geometry": {"coordinates":[153.135620117,-27.6639328003],"type":"Point"}
}