{
  "type": "Feature",
  "properties": {
    "addr:full":"179 Wellington Rd East Brisbane QLD 4169",
    "addr:housenumber":"179",
    "addr:postcode":"4169",
    "addr:street":"Wellington Rd",
    "iso:country":"AU",
    "sg:address":"179 Wellington Rd",
    "sg:city":"East Brisbane",
    "sg:classifiers":[
        {
            "category":"Shopping",
            "subcategory":"Bridal",
            "type":"Retail Goods"
        }
    ],
    "sg:phone":"+61 7 3823 0111",
    "sg:postcode":"4169",
    "sg:province":"QLD",
    "sg:tags":[
        "hire",
        "wear"
    ],
    "wof:name":"Wendy Makin Bridal Designs",
    "wof:placetype":"venue"
},
  "geometry": {"coordinates":[153.04112243599999,-27.4808940887],"type":"Point"}
}