{
  "type": "Feature",
  "properties": {
    "addr:full":"143 Oaky Creek Rd Gheerulla QLD 4574",
    "addr:housenumber":"143",
    "addr:postcode":"4574",
    "addr:street":"Oaky Creek Rd",
    "iso:country":"AU",
    "sg:address":"143 Oaky Creek Rd",
    "sg:city":"Gheerulla",
    "sg:classifiers":[
        {
            "category":"Home & Garden",
            "subcategory":"Kitchen Supply",
            "type":"Retail Goods"
        }
    ],
    "sg:phone":"+61 7 5472 3261",
    "sg:postcode":"4574",
    "sg:province":"QLD",
    "sg:tags":[
        "sharpening"
    ],
    "wof:name":"Corbett Trevor",
    "wof:placetype":"venue"
},
  "geometry": {"coordinates":[152.78942900000001,-26.54715],"type":"Point"}
}