{
  "type": "Feature",
  "properties": {
    "addr:full":"445 Windsor Rd Baulkham Hills NSW 2153",
    "addr:housenumber":"445",
    "addr:postcode":"2153",
    "addr:street":"Windsor Rd",
    "iso:country":"AU",
    "sg:address":"445 Windsor Rd",
    "sg:city":"Baulkham Hills",
    "sg:classifiers":[
        {
            "category":"Health Services",
            "subcategory":"Health Practitioner",
            "type":"Services"
        }
    ],
    "sg:phone":"+61 2 9614 5575",
    "sg:postcode":"2153",
    "sg:province":"NSW",
    "sg:tags":[
        "alternative"
    ],
    "wof:name":"Wholistic Natural Medicine",
    "wof:placetype":"venue"
},
  "geometry": {"coordinates":[150.98591613799999,-33.7497062683],"type":"Point"}
}