{
  "type": "Feature",
  "properties": {
    "addr:full":"U2/ 12 Tasman Way Byron Bay NSW 2481",
    "addr:housenumber":"12",
    "addr:postcode":"2481",
    "addr:street":"U2 /;Tasman Way",
    "iso:country":"AU",
    "sg:address":"U2/ 12 Tasman Way",
    "sg:city":"Byron Bay",
    "sg:classifiers":[
        {
            "category":"Wholesale",
            "subcategory":"Non-durable Goods",
            "type":"Manufacturing & Wholesale Goods"
        }
    ],
    "sg:phone":"+61 2 6685 5023",
    "sg:postcode":"2481",
    "sg:province":"NSW",
    "sg:tags":[
        "wholesaler",
        "mfrs",
        "cosmetic"
    ],
    "wof:name":"Bee Natural",
    "wof:placetype":"venue"
},
  "geometry": {"coordinates":[153.579956055,-28.6355228424],"type":"Point"}
}