{
  "type": "Feature",
  "properties": {
    "addr:full":"30 Bay Rd Claremont WA 6010",
    "addr:housenumber":"30",
    "addr:postcode":"6010",
    "addr:street":"Bay Rd",
    "iso:country":"AU",
    "sg:address":"30 Bay Rd",
    "sg:city":"Claremont",
    "sg:classifiers":[
        {
            "category":"Place Of Worship",
            "subcategory":"Monastery",
            "type":"Public Place"
        }
    ],
    "sg:phone":"+61 8 9384 3722",
    "sg:postcode":"6010",
    "sg:province":"WA",
    "sg:tags":[
        "residential",
        "village"
    ],
    "wof:name":"Silver Chain",
    "wof:placetype":"venue"
},
  "geometry": {"coordinates":[115.790611267,-31.9829864502],"type":"Point"}
}