{
  "type": "Feature",
  "properties": {
    "addr:full":"Sandy Creek Rd Sandy Creek QLD 4570",
    "addr:postcode":"4570",
    "addr:street":"Sandy Creek Rd",
    "iso:country":"AU",
    "sg:address":"Sandy Creek Rd",
    "sg:city":"Sandy Creek",
    "sg:classifiers":[
        {
            "category":"Farming",
            "subcategory":"Farm",
            "type":"Manufacturing & Wholesale Goods"
        }
    ],
    "sg:phone":"+61 7 5485 7198",
    "sg:postcode":"4570",
    "sg:province":"QLD",
    "sg:tags":[
        "farmer"
    ],
    "wof:name":"Benworth Farm",
    "wof:placetype":"venue"
},
  "geometry": {"coordinates":[152.68142700199999,-26.1736927032],"type":"Point"}
}