{
  "type": "Feature",
  "properties": {
    "iso:country":"AU",
    "sg:address":"3/ 1 St",
    "sg:city":"pauls Terrace Spring Hill",
    "sg:classifiers":[
        {
            "category":"Personal",
            "subcategory":"Massage",
            "type":"Services"
        }
    ],
    "sg:phone":"+61 7 3831 9253",
    "sg:postcode":"4000",
    "sg:province":"QLD",
    "sg:tags":[
        "therapy"
    ],
    "wof:name":"The Musculo Skeletal Clinic",
    "wof:placetype":"venue"
},
  "geometry": {"coordinates":[153.026733398,-27.4611682892],"type":"Point"}
}