{
  "type": "Feature",
  "properties": {
    "addr:full":"13 Scott St Liverpool NSW 2170",
    "addr:housenumber":"13",
    "addr:postcode":"2170",
    "addr:street":"Scott St",
    "iso:country":"AU",
    "sg:address":"13 Scott St",
    "sg:city":"Liverpool",
    "sg:classifiers":[
        {
            "category":"Shopping",
            "subcategory":"Discount & Variety Stores",
            "type":"Retail Goods"
        }
    ],
    "sg:phone":"+61 2 9602 1619",
    "sg:postcode":"2170",
    "sg:province":"NSW",
    "sg:tags":[
        "shop",
        "adult"
    ],
    "wof:name":"XXX Adult Shop",
    "wof:placetype":"venue"
},
  "geometry": {"coordinates":[150.926345825,-33.9251441956],"type":"Point"}
}