{
  "type": "Feature",
  "properties": {
    "addr:full":"3 Hillier St Currumbin Waters QLD 4223",
    "addr:housenumber":"3",
    "addr:postcode":"4223",
    "addr:street":"Hillier St",
    "iso:country":"AU",
    "sg:address":"3 Hillier St",
    "sg:city":"Currumbin Waters",
    "sg:classifiers":[
        {
            "category":"Personal",
            "subcategory":"Massage",
            "type":"Services"
        }
    ],
    "sg:phone":"+61 401 397 407",
    "sg:postcode":"4223",
    "sg:province":"QLD",
    "sg:tags":[
        "therapy"
    ],
    "wof:name":"Tracy Zammit",
    "wof:placetype":"venue"
},
  "geometry": {"coordinates":[153.45603942899999,-28.1468887329],"type":"Point"}
}