{
  "type": "Feature",
  "properties": {
    "addr:full":"7/ 5 Rockley St Bondi NSW 2026",
    "addr:housenumber":"/ 5",
    "addr:postcode":"2026",
    "addr:street":"Rockley St",
    "iso:country":"AU",
    "sg:address":"7/ 5 Rockley St",
    "sg:city":"Bondi",
    "sg:classifiers":[
        {
            "category":"Building & Trades",
            "subcategory":"Landscaping Services",
            "type":"Services"
        }
    ],
    "sg:phone":"+61 414 387 665",
    "sg:postcode":"2026",
    "sg:province":"NSW",
    "sg:tags":[
        "designer",
        "landscape",
        "contractor"
    ],
    "wof:name":"Zone Developing Pty Ltd",
    "wof:placetype":"venue"
},
  "geometry": {"coordinates":[151.26596069300001,-33.892250061],"type":"Point"}
}