{
  "type": "Feature",
  "properties": {
    "iso:country":"AU",
    "sg:address":"PO Box 6324",
    "sg:city":"Shepparton",
    "sg:classifiers":[
        {
            "category":"Utilities",
            "subcategory":"Electric",
            "type":"Services"
        }
    ],
    "sg:phone":"+61 412 830 054",
    "sg:postcode":"3632",
    "sg:province":"VIC",
    "sg:tags":[
        "electrical",
        "contractor"
    ],
    "wof:name":"Shane Fitzsimmons Electrical",
    "wof:placetype":"venue"
},
  "geometry": {"coordinates":[145.399291992,-36.3811683655],"type":"Point"}
}