{
  "type": "Feature",
  "properties": {
    "addr:full":"44 Bass St Eden NSW 2551",
    "addr:housenumber":"44",
    "addr:postcode":"2551",
    "addr:street":"Bass St",
    "iso:country":"AU",
    "sg:address":"44 Bass St",
    "sg:city":"Eden",
    "sg:classifiers":[
        {
            "category":"Building & Trades",
            "subcategory":"Construction",
            "type":"Services"
        }
    ],
    "sg:phone":"+61 2 6496 1000",
    "sg:postcode":"2551",
    "sg:province":"NSW",
    "sg:tags":[
        "contractor"
    ],
    "wof:name":"Holman Kevin",
    "wof:placetype":"venue"
},
  "geometry": {"coordinates":[149.90510559099999,-37.0647926331],"type":"Point"}
}