{
  "type": "Feature",
  "properties": {
    "addr:full":"Shop 22, 619 Doncaster Rd Doncaster VIC 3108",
    "addr:housenumber":"shop 22 619",
    "addr:postcode":"3108",
    "addr:street":"Doncaster Rd",
    "iso:country":"AU",
    "sg:address":"Shop 22, 619 Doncaster Rd",
    "sg:city":"Doncaster",
    "sg:classifiers":[
        {
            "category":"Food & Beverages",
            "subcategory":"Liquor & Beverages",
            "type":"Retail Goods"
        }
    ],
    "sg:phone":"+61 3 9848 9660",
    "sg:postcode":"3108",
    "sg:province":"VIC",
    "sg:tags":[
        "store"
    ],
    "wof:name":"Safeway Liquor",
    "wof:placetype":"venue"
},
  "geometry": {"coordinates":[145.125686645,-37.7871360779],"type":"Point"}
}