{
  "type": "Feature",
  "properties": {
    "iso:country":"AU",
    "sg:address":"Shop 3A, 81 High St",
    "sg:city":"Woodend",
    "sg:classifiers":[
        {
            "category":"Real Estate",
            "subcategory":"Real Estate Agent",
            "type":"Services"
        }
    ],
    "sg:phone":"+61 3 5427 3200",
    "sg:postcode":"3442",
    "sg:province":"VIC",
    "wof:name":"Raine & Horne Woodend",
    "wof:placetype":"venue"
},
  "geometry": {"coordinates":[144.52818298299999,-37.3554153442],"type":"Point"}
}