{
  "type": "Feature",
  "properties": {
    "addr:full":"Shp 33, 235 Bourke St Melbourne VIC 3000",
    "addr:housenumber":"235",
    "addr:postcode":"3000",
    "addr:street":"Bourke St",
    "iso:country":"AU",
    "sg:address":"Shp 33, 235 Bourke St",
    "sg:city":"Melbourne",
    "sg:classifiers":[
        {
            "category":"Organizations",
            "subcategory":"Professional Association",
            "type":"Services"
        }
    ],
    "sg:phone":"+61 412 688 689",
    "sg:postcode":"3000",
    "sg:province":"VIC",
    "sg:tags":[
        "web",
        "internet"
    ],
    "wof:name":"Global Frontier",
    "wof:placetype":"venue"
},
  "geometry": {"coordinates":[144.96647644000001,-37.8134002686],"type":"Point"}
}