{
  "type": "Feature",
  "properties": {
    "addr:full":"244 West St Carlton NSW 2218",
    "addr:housenumber":"244",
    "addr:postcode":"2218",
    "addr:street":"West St",
    "iso:country":"AU",
    "sg:address":"244 West St",
    "sg:city":"Carlton",
    "sg:classifiers":[
        {
            "category":"Building & Trades",
            "subcategory":"Locksmith",
            "type":"Services"
        }
    ],
    "sg:phone":"+61 2 9547 1488",
    "sg:postcode":"2218",
    "sg:province":"NSW",
    "sg:tags":[
        "strongroom",
        "safe",
        "door"
    ],
    "sg:website":"http://www.cmisafe.com.au",
    "wof:name":"C.M.I. Safe Co",
    "wof:placetype":"venue"
},
  "geometry": {"coordinates":[151.117966,-33.981171],"type":"Point"}
}