{
  "type": "Feature",
  "properties": {
    "addr:full":"21 Gwynne St Mt Waverley VIC 3149",
    "addr:housenumber":"21",
    "addr:postcode":"3149",
    "addr:street":"Gwynne St Mt",
    "iso:country":"AU",
    "sg:address":"21 Gwynne St",
    "sg:city":"Mt Waverley",
    "sg:classifiers":[
        {
            "category":"Real Estate",
            "subcategory":"Surveying",
            "type":"Services"
        }
    ],
    "sg:phone":"+61 3 9888 2533",
    "sg:postcode":"3149",
    "sg:province":"VIC",
    "sg:tags":[
        "surveyor",
        "quantity"
    ],
    "wof:name":"Fielding Partners Pty Ltd",
    "wof:placetype":"venue"
},
  "geometry": {"coordinates":[145.13265991200001,-37.8711853027],"type":"Point"}
}