{
  "type": "Feature",
  "properties": {
    "addr:full":"1 Main St Boisdale VIC 3860",
    "addr:housenumber":"1",
    "addr:postcode":"3860",
    "addr:street":"Main St",
    "iso:country":"AU",
    "sg:address":"1 Main St",
    "sg:city":"Boisdale",
    "sg:classifiers":[
        {
            "category":"Retail",
            "subcategory":"Auto Repair",
            "type":"Services"
        }
    ],
    "sg:phone":"+61 3 5145 4231",
    "sg:postcode":"3860",
    "sg:province":"VIC",
    "sg:tags":[
        "repairer",
        "motor",
        "engineer"
    ],
    "wof:name":"Boisdale Garage",
    "wof:placetype":"venue"
},
  "geometry": {"coordinates":[146.988739014,-37.8858985901],"type":"Point"}
}