{
  "type": "Feature",
  "properties": {
    "addr:full":"Statewide House, Level 1 99 Gawler Pl Adelaide SA 5000",
    "addr:housenumber":"99",
    "addr:postcode":"5000",
    "addr:street":"Gawler Pl",
    "iso:country":"AU",
    "sg:address":"Statewide House, Level 1 99 Gawler Pl",
    "sg:city":"Adelaide",
    "sg:classifiers":[
        {
            "category":"Banks & Credit Unions",
            "subcategory":"Financial Services",
            "type":"Services"
        }
    ],
    "sg:phone":"+61 1300 885 665",
    "sg:postcode":"5000",
    "sg:province":"SA",
    "sg:tags":[
        "annuity",
        "rollover",
        "superannuation",
        "consultant"
    ],
    "wof:name":"Auswide Master Fund",
    "wof:placetype":"venue"
},
  "geometry": {"coordinates":[138.601852417,-34.9246711731],"type":"Point"}
}