{
  "type": "Feature",
  "properties": {
    "iso:country":"AU",
    "sg:address":"Unit 12 30 Young St",
    "sg:city":"Cremorne",
    "sg:classifiers":[
        {
            "category":"Wholesale",
            "subcategory":"Apparel",
            "type":"Manufacturing & Wholesale Goods"
        }
    ],
    "sg:phone":"+61 414 395 378",
    "sg:postcode":"2090",
    "sg:province":"NSW",
    "sg:tags":[
        "wholesaler",
        "mfrs",
        "menswear"
    ],
    "wof:name":"Sabastien's Fashion",
    "wof:placetype":"venue"
},
  "geometry": {"coordinates":[151.221633911,-33.8293151855],"type":"Point"}
}