{
  "type": "Feature",
  "properties": {
    "addr:full":"68 Gray St Woonona NSW 2517",
    "addr:housenumber":"68",
    "addr:postcode":"2517",
    "addr:street":"Gray St",
    "iso:country":"AU",
    "sg:address":"68 Gray St",
    "sg:city":"Woonona",
    "sg:classifiers":[
        {
            "category":"Professional",
            "subcategory":"Engineering",
            "type":"Services"
        }
    ],
    "sg:phone":"+61 402 443 642",
    "sg:postcode":"2517",
    "sg:province":"NSW",
    "sg:tags":[
        "installation",
        "maintenance",
        "engineer"
    ],
    "wof:name":"All Repairs & Maintenance",
    "wof:placetype":"venue"
},
  "geometry": {"coordinates":[150.910797,-34.347866],"type":"Point"}
}