{
  "type": "Feature",
  "properties": {
    "addr:full":"198 Wilston Rd Grange QLD 4051",
    "addr:housenumber":"198",
    "addr:postcode":"4051",
    "addr:street":"Wilston Rd",
    "iso:country":"AU",
    "sg:address":"198 Wilston Rd",
    "sg:city":"Grange",
    "sg:classifiers":[
        {
            "category":"Wholesale",
            "subcategory":"Painting Supplies",
            "type":"Manufacturing & Wholesale Goods"
        }
    ],
    "sg:phone":"+61 7 3356 3211",
    "sg:postcode":"4051",
    "sg:province":"QLD",
    "sg:tags":[
        "painter"
    ],
    "wof:name":"All Seasons Paints",
    "wof:placetype":"venue"
},
  "geometry": {"coordinates":[153.011062622,-27.4269104004],"type":"Point"}
}