{
  "type": "Feature",
  "properties": {
    "iso:country":"AU",
    "sg:address":"1863 Mt Nebo Rd",
    "sg:city":"Mt Nebo",
    "sg:classifiers":[
        {
            "category":"Personal",
            "subcategory":"Massage",
            "type":"Services"
        }
    ],
    "sg:phone":"+61 7 3289 8111",
    "sg:postcode":"4520",
    "sg:province":"QLD",
    "sg:tags":[
        "therapy"
    ],
    "wof:name":"Michele Hobart Remedial & Sports Massage Centre",
    "wof:placetype":"venue"
},
  "geometry": {"coordinates":[152.7892,-27.398388],"type":"Point"}
}