{
  "type": "Feature",
  "properties": {
    "iso:country":"AU",
    "sg:address":"710 Main North Rd",
    "sg:city":"Gepps Cross",
    "sg:classifiers":[
        {
            "category":"Banks & Credit Unions",
            "subcategory":"Investment Brokerage",
            "type":"Services"
        }
    ],
    "sg:phone":"+61 8 8262 1241",
    "sg:postcode":"5094",
    "sg:province":"SA",
    "sg:tags":[
        "management",
        "property"
    ],
    "wof:name":"MDS Aust Pty Ltd",
    "wof:placetype":"venue"
},
  "geometry": {"coordinates":[138.60549926799999,-34.8404388428],"type":"Point"}
}