{
  "type": "Feature",
  "properties": {
    "addr:full":"7 Airlie Ave Dandenong VIC 3175",
    "addr:housenumber":"7",
    "addr:postcode":"3175",
    "addr:street":"Airlie Ave",
    "iso:country":"AU",
    "sg:address":"7 Airlie Ave",
    "sg:city":"Dandenong",
    "sg:classifiers":[
        {
            "category":"Retail",
            "subcategory":"Auto Repair",
            "type":"Services"
        }
    ],
    "sg:phone":"+61 3 9794 9244",
    "sg:postcode":"3175",
    "sg:province":"VIC",
    "sg:tags":[
        "repairer",
        "motor",
        "engineer"
    ],
    "wof:name":"Classic Motors",
    "wof:placetype":"venue"
},
  "geometry": {"coordinates":[145.20291137699999,-37.973110199],"type":"Point"}
}