{
  "type": "Feature",
  "properties": {
    "iso:country":"AU",
    "sg:address":"11a Parramatta Rd",
    "sg:city":"Keilor",
    "sg:classifiers":[
        {
            "category":"Education",
            "subcategory":"Kindergarten",
            "type":"Public Place"
        }
    ],
    "sg:phone":"+61 3 9336 3270",
    "sg:postcode":"3036",
    "sg:province":"VIC",
    "sg:tags":[
        "pre-schools"
    ],
    "wof:name":"Keilor Gatehouse Pre School",
    "wof:placetype":"venue"
},
  "geometry": {"coordinates":[144.823395,-37.714874],"type":"Point"}
}