{
  "type": "Feature",
  "properties": {
    "iso:country":"AU",
    "sg:address":"U 29/ 506 Botany Rd",
    "sg:city":"Beaconsfield",
    "sg:classifiers":[
        {
            "category":"Professional",
            "subcategory":"Accounting & Tax Preparation",
            "type":"Services"
        }
    ],
    "sg:phone":"+61 2 8399 0572",
    "sg:postcode":"2015",
    "sg:province":"NSW",
    "sg:tags":[
        "accountant",
        "auditor"
    ],
    "wof:name":"Kargas & Co Pty Ltd",
    "wof:placetype":"venue"
},
  "geometry": {"coordinates":[151.20112609899999,-33.9134368896],"type":"Point"}
}