{
  "type": "Feature",
  "properties": {
    "addr:full":"William St Littlehampton SA 5250",
    "addr:postcode":"5250",
    "addr:street":"William St",
    "iso:country":"AU",
    "sg:address":"William St",
    "sg:city":"Littlehampton",
    "sg:classifiers":[
        {
            "category":"Manufacturing",
            "subcategory":"Furniture",
            "type":"Manufacturing & Wholesale Goods"
        }
    ],
    "sg:phone":"+61 410 658 797",
    "sg:postcode":"5250",
    "sg:province":"SA",
    "sg:tags":[
        "builder",
        "designer",
        "custom"
    ],
    "wof:name":"Matthew Greenwood Furniture & Designs",
    "wof:placetype":"venue"
},
  "geometry": {"coordinates":[138.867279053,-35.0504875183],"type":"Point"}
}