{
  "type": "Feature",
  "properties": {
    "iso:country":"AU",
    "sg:address":"36 Aldenham Rd",
    "sg:city":"Warnervale",
    "sg:classifiers":[
        {
            "category":"Retail",
            "subcategory":"Storage",
            "type":"Services"
        }
    ],
    "sg:phone":"+61 2 4393 0503",
    "sg:postcode":"2259",
    "sg:province":"NSW",
    "sg:tags":[
        "removal",
        "furniture"
    ],
    "wof:name":"Ave A Good Weekend Removals",
    "wof:placetype":"venue"
},
  "geometry": {"coordinates":[151.444549561,-33.2484970093],"type":"Point"}
}