{
  "type": "Feature",
  "properties": {
    "addr:full":"107 Bedford Rd Andergrove QLD 4740",
    "addr:housenumber":"107",
    "addr:postcode":"4740",
    "addr:street":"Bedford Rd",
    "iso:country":"AU",
    "sg:address":"107 Bedford Rd",
    "sg:city":"Andergrove",
    "sg:classifiers":[
        {
            "category":"Food & Beverages",
            "subcategory":"Bakery",
            "type":"Retail Goods"
        }
    ],
    "sg:phone":"+61 7 4955 1202",
    "sg:postcode":"4740",
    "sg:province":"QLD",
    "sg:tags":[
        "cake",
        "shop",
        "pastry"
    ],
    "wof:name":"Alcorn's Bakery",
    "wof:placetype":"venue"
},
  "geometry": {"coordinates":[149.181656,-21.106693],"type":"Point"}
}