{
  "type": "Feature",
  "properties": {
    "addr:full":"U2/ 8 Tenth Ave West Moonah TAS 7009",
    "addr:housenumber":"8",
    "addr:postcode":"7009",
    "addr:street":"U2 /;Tenth Ave West",
    "iso:country":"AU",
    "sg:address":"U2/ 8 Tenth Ave",
    "sg:city":"West Moonah",
    "sg:classifiers":[
        {
            "category":"Professional",
            "type":"Services"
        }
    ],
    "sg:phone":"+61 438 067 318",
    "sg:postcode":"7009",
    "sg:province":"TAS",
    "sg:tags":[
        "transport"
    ],
    "wof:name":"Southern Secure Transport",
    "wof:placetype":"venue"
},
  "geometry": {"coordinates":[147.27699279800001,-42.8442192078],"type":"Point"}
}