{
  "type": "Feature",
  "properties": {
    "iso:country":"AU",
    "sg:address":"Weale St",
    "sg:city":"Pittsworth",
    "sg:classifiers":[
        {
            "category":"Health Services",
            "subcategory":"Optometrist",
            "type":"Services"
        }
    ],
    "sg:phone":"+61 7 4693 1028",
    "sg:postcode":"4356",
    "sg:province":"QLD",
    "wof:name":"Felfer, Franz",
    "wof:placetype":"venue"
},
  "geometry": {"coordinates":[151.63765,-27.719427],"type":"Point"}
}