{
  "type": "Feature",
  "properties": {
    "iso:country":"AU",
    "sg:address":"370 Maroubra Rd",
    "sg:city":"Maroubra",
    "sg:classifiers":[
        {
            "category":"Building & Trades",
            "subcategory":"Plumbing",
            "type":"Services"
        }
    ],
    "sg:phone":"+61 412 863 890",
    "sg:postcode":"2035",
    "sg:province":"NSW",
    "sg:tags":[
        "plumber",
        "gasfitters"
    ],
    "wof:name":"B & K Stathis Plumbing",
    "wof:placetype":"venue"
},
  "geometry": {"coordinates":[151.25387573200001,-33.9415664673],"type":"Point"}
}