{
  "type": "Feature",
  "properties": {
    "iso:country":"AU",
    "sg:address":"57 Village Way",
    "sg:city":"Little Mountain",
    "sg:classifiers":[
        {
            "category":"Social Services",
            "subcategory":"Retirement Home",
            "type":"Services"
        }
    ],
    "sg:phone":"+61 1800 898 800",
    "sg:postcode":"4551",
    "sg:province":"QLD",
    "sg:tags":[
        "village"
    ],
    "sg:website":"http://www.sccqld.com.au",
    "wof:name":"Caloundra Rise Retirement Estate",
    "wof:placetype":"venue"
},
  "geometry": {"coordinates":[153.09088134800001,-26.779466629],"type":"Point"}
}