{
  "type": "Feature",
  "properties": {
    "iso:country":"AU",
    "sg:address":"18 Robinson Rd",
    "sg:city":"Bellevue",
    "sg:classifiers":[
        {
            "category":"Autos & Motor Vehicles",
            "subcategory":"Automobile Sales",
            "type":"Retail Goods"
        }
    ],
    "sg:phone":"+61 8 9250 1773",
    "sg:postcode":"6056",
    "sg:province":"WA",
    "sg:tags":[
        "equipment",
        "trailer"
    ],
    "wof:name":"WA Bos Semi Trailer Equipment Pty Ltd",
    "wof:placetype":"venue"
},
  "geometry": {"coordinates":[116.025169373,-31.8973789215],"type":"Point"}
}