{
  "type": "Feature",
  "properties": {
    "addr:full":"158 Union Rd Ascot Vale VIC 3032",
    "addr:housenumber":"158",
    "addr:postcode":"3032",
    "addr:street":"Union Rd",
    "iso:country":"AU",
    "sg:address":"158 Union Rd",
    "sg:city":"Ascot Vale",
    "sg:classifiers":[
        {
            "category":"Health Services",
            "subcategory":"Dentist",
            "type":"Services"
        }
    ],
    "sg:phone":"+61 3 9375 3448",
    "sg:postcode":"3032",
    "sg:province":"VIC",
    "sg:tags":[
        "technician",
        "dental"
    ],
    "wof:name":"King C Kevin Dental Laboratories Pty Ltd",
    "wof:placetype":"venue"
},
  "geometry": {"coordinates":[144.91584800000001,-37.775055],"type":"Point"}
}