{
  "type": "Feature",
  "properties": {
    "iso:country":"AU",
    "sg:address":"439 Burke Rd",
    "sg:city":"Glen Iris",
    "sg:classifiers":[
        {
            "category":"Social Services",
            "type":"Services"
        }
    ],
    "sg:phone":"+61 3 9824 7711",
    "sg:postcode":"3146",
    "sg:province":"VIC",
    "sg:tags":[
        "disabled",
        "person",
        "equipment"
    ],
    "wof:name":"Soundbooks",
    "wof:placetype":"venue"
},
  "geometry": {"coordinates":[145.05368042000001,-37.8463287354],"type":"Point"}
}