{
  "type": "Feature",
  "properties": {
    "addr:full":"14 Bunora Ave Ferny Hills QLD 4055",
    "addr:housenumber":"14",
    "addr:postcode":"4055",
    "addr:street":"Bunora Ave",
    "iso:country":"AU",
    "sg:address":"14 Bunora Ave",
    "sg:city":"Ferny Hills",
    "sg:classifiers":[
        {
            "category":"Banks & Credit Unions",
            "subcategory":"Bank",
            "type":"Services"
        }
    ],
    "sg:phone":"+61 7 3351 1065",
    "sg:postcode":"4055",
    "sg:province":"QLD",
    "sg:tags":[
        "broker",
        "mortgage"
    ],
    "wof:name":"APD Lending Services",
    "wof:placetype":"venue"
},
  "geometry": {"coordinates":[152.94303894000001,-27.396232605],"type":"Point"}
}