{
  "type": "Feature",
  "properties": {
    "iso:country":"AU",
    "sg:address":"Unit 2 14- 16 Byrne St",
    "sg:city":"Auburn",
    "sg:classifiers":[
        {
            "category":"Home & Garden",
            "subcategory":"Building Materials",
            "type":"Retail Goods"
        }
    ],
    "sg:phone":"+61 2 9648 5878",
    "sg:postcode":"2144",
    "sg:province":"NSW",
    "sg:tags":[
        "decorative",
        "coating"
    ],
    "wof:name":"Unitex Granular Marble Pty Ltd",
    "wof:placetype":"venue"
},
  "geometry": {"coordinates":[151.027954102,-33.841796875],"type":"Point"}
}