{
  "type": "Feature",
  "properties": {
    "iso:country":"AU",
    "sg:address":"2 Young St",
    "sg:city":"Frankston",
    "sg:classifiers":[
        {
            "category":"Government",
            "subcategory":"Customs House",
            "type":"Public Place"
        }
    ],
    "sg:phone":"+61 3 9781 4455",
    "sg:postcode":"3199",
    "sg:province":"VIC",
    "sg:tags":[
        "title",
        "management",
        "stratum"
    ],
    "wof:name":"Jones Wal Body Corp Management",
    "wof:placetype":"venue"
},
  "geometry": {"coordinates":[145.155227661,-37.934047699],"type":"Point"}
}