{
  "type": "Feature",
  "properties": {
    "addr:full":"24 Waterford Drv Hillarys WA 6025",
    "addr:housenumber":"24",
    "addr:postcode":"6025",
    "addr:street":"Waterford Drv",
    "iso:country":"AU",
    "sg:address":"24 Waterford Drv",
    "sg:city":"Hillarys",
    "sg:classifiers":[
        {
            "category":"Building & Trades",
            "subcategory":"Cleaning & Sanitation",
            "type":"Services"
        }
    ],
    "sg:phone":"+61 8 9403 2145",
    "sg:postcode":"6025",
    "sg:province":"WA",
    "sg:tags":[
        "cleaner",
        "repairer",
        "roof"
    ],
    "sg:website":"http://www.allroofcare.com.au",
    "wof:name":"All Roofcare",
    "wof:placetype":"venue"
},
  "geometry": {"coordinates":[115.75392150899999,-31.8118114471],"type":"Point"}
}