{
  "type": "Feature",
  "properties": {
    "addr:full":"6 Gregory St Ouyen VIC 3490",
    "addr:housenumber":"6",
    "addr:postcode":"3490",
    "addr:street":"Gregory St",
    "iso:country":"AU",
    "sg:address":"6 Gregory St",
    "sg:city":"Ouyen",
    "sg:classifiers":[
        {
            "category":"Building & Trades",
            "subcategory":"Construction",
            "type":"Services"
        }
    ],
    "sg:phone":"+61 3 5092 1420",
    "sg:postcode":"3490",
    "sg:province":"VIC",
    "sg:tags":[
        "joiner",
        "carpenter"
    ],
    "wof:name":"Smith R & L Builders Pty Ltd",
    "wof:placetype":"venue"
},
  "geometry": {"coordinates":[142.31608581500001,-35.0719261169],"type":"Point"}
}