{
  "type": "Feature",
  "properties": {
    "iso:country":"AU",
    "sg:address":"Shp 2/ 1 Post Office Pl",
    "sg:city":"Traralgon",
    "sg:classifiers":[
        {
            "category":"Shopping",
            "type":"Retail Goods"
        }
    ],
    "sg:phone":"+61 3 5174 7576",
    "sg:postcode":"3844",
    "sg:province":"VIC",
    "sg:tags":[
        "new age",
        "product"
    ],
    "wof:name":"Dyoligy",
    "wof:placetype":"venue"
},
  "geometry": {"coordinates":[146.53828430199999,-38.1952171326],"type":"Point"}
}