{
  "type": "Feature",
  "properties": {
    "iso:country":"AU",
    "sg:address":"13 Harold St",
    "sg:city":"North Parramatta",
    "sg:classifiers":[
        {
            "category":"Organizations",
            "subcategory":"Membership Organization",
            "type":"Services"
        }
    ],
    "sg:phone":"+61 2 9281 1611",
    "sg:postcode":"2151",
    "sg:province":"NSW",
    "sg:tags":[
        "support",
        "health",
        "organisation"
    ],
    "wof:name":"Arthritis Foundation Of NSW",
    "wof:placetype":"venue"
},
  "geometry": {"coordinates":[151.00469970699999,-33.8045654297],"type":"Point"}
}