{
  "type": "Feature",
  "properties": {
    "iso:country":"AU",
    "sg:address":"38-40 Salisbury St",
    "sg:city":"Orbost",
    "sg:classifiers":[
        {
            "category":"Retail",
            "subcategory":"Auto Repair",
            "type":"Services"
        }
    ],
    "sg:phone":"+61 3 5154 2323",
    "sg:postcode":"3888",
    "sg:province":"VIC",
    "sg:tags":[
        "muffler",
        "exhaust",
        "system"
    ],
    "wof:name":"Orbost Exhaust Centre",
    "wof:placetype":"venue"
},
  "geometry": {"coordinates":[148.45721435600001,-37.7048988342],"type":"Point"}
}