{
  "type": "Feature",
  "properties": {
    "iso:country":"AU",
    "sg:address":"2 Harrison Rd",
    "sg:city":"Forrestfield",
    "sg:classifiers":[
        {
            "category":"Communications",
            "type":"Services"
        }
    ],
    "sg:phone":"+61 8 9471 0210",
    "sg:postcode":"6058",
    "sg:province":"WA",
    "sg:tags":[
        "equipment",
        "satellite"
    ],
    "wof:name":"Rawsat Pty Ltd",
    "wof:placetype":"venue"
},
  "geometry": {"coordinates":[115.998123169,-31.9674816132],"type":"Point"}
}