{
  "type": "Feature",
  "properties": {
    "addr:full":"Shop 2/ 99 Pacific Hwy Tweed Heads South NSW 2486",
    "addr:housenumber":"shop 2 / 99",
    "addr:postcode":"2486",
    "addr:street":"Pacific Hwy",
    "iso:country":"AU",
    "sg:address":"Shop 2/ 99 Pacific Hwy",
    "sg:city":"Tweed Heads South",
    "sg:classifiers":[
        {
            "category":"Fast Food",
            "type":"Food & Drink"
        }
    ],
    "sg:phone":"+61 7 5524 4614",
    "sg:postcode":"2486",
    "sg:province":"NSW",
    "sg:tags":[
        "away",
        "take"
    ],
    "wof:name":"Ocean Sky Chinese Restaurant",
    "wof:placetype":"venue"
},
  "geometry": {"coordinates":[153.49188232399999,-28.2130222321],"type":"Point"}
}