{
  "type": "Feature",
  "properties": {
    "addr:full":"6 Old Northern Rd Wisemans Ferry NSW 2775",
    "addr:housenumber":"6",
    "addr:postcode":"2775",
    "addr:street":"Old Northern Rd",
    "iso:country":"AU",
    "sg:address":"6 Old Northern Rd",
    "sg:city":"Wisemans Ferry",
    "sg:classifiers":[
        {
            "category":"Travel",
            "subcategory":"Hotels & Motels",
            "type":"Entertainment"
        }
    ],
    "sg:phone":"+61 2 4566 4301",
    "sg:postcode":"2775",
    "sg:province":"NSW",
    "sg:tags":[
        "accommodation"
    ],
    "wof:name":"Wisemans Ferry Inn Hotel",
    "wof:placetype":"venue"
},
  "geometry": {"coordinates":[150.98747253400001,-33.3803634644],"type":"Point"}
}