{
  "type": "Feature",
  "properties": {
    "addr:full":"72- 74 Broadway St Cobram VIC 3644",
    "addr:housenumber":"74",
    "addr:postcode":"3644",
    "addr:street":"Broadway St",
    "iso:country":"AU",
    "sg:address":"72- 74 Broadway St",
    "sg:city":"Cobram",
    "sg:classifiers":[
        {
            "category":"Professional",
            "type":"Services"
        }
    ],
    "sg:phone":"+61 3 5871 1525",
    "sg:postcode":"3644",
    "sg:province":"VIC",
    "sg:tags":[
        "transport"
    ],
    "wof:name":"Cobram Transport Agency",
    "wof:placetype":"venue"
},
  "geometry": {"coordinates":[145.64585876500001,-35.9165458679],"type":"Point"}
}