{
  "type": "Feature",
  "properties": {
    "iso:country":"AU",
    "sg:address":"21 Newton St",
    "sg:city":"Monto",
    "sg:classifiers":[
        {
            "category":"Shopping",
            "subcategory":"Clothing, Apparel, & Fashions",
            "type":"Retail Goods"
        }
    ],
    "sg:phone":"+61 7 4166 1208",
    "sg:postcode":"4630",
    "sg:province":"QLD",
    "sg:tags":[
        "menswear"
    ],
    "wof:name":"Mensland",
    "wof:placetype":"venue"
},
  "geometry": {"coordinates":[151.122146606,-24.8636131287],"type":"Point"}
}