{
  "type": "Feature",
  "properties": {
    "iso:country":"AU",
    "sg:address":"30 Bass Hwy",
    "sg:city":"Cooee",
    "sg:classifiers":[
        {
            "category":"Structure",
            "subcategory":"Bridge",
            "type":"Public Place"
        }
    ],
    "sg:phone":"+61 3 6432 3788",
    "sg:postcode":"7320",
    "sg:province":"TAS",
    "sg:tags":[
        "chainsaw",
        "brushcutters"
    ],
    "wof:name":"Lingers Motorcycles",
    "wof:placetype":"venue"
},
  "geometry": {"coordinates":[145.879456,-41.042492],"type":"Point"}
}