{
  "type": "Feature",
  "properties": {
    "addr:full":"64 Churchill Ave Kooringal Wagga Wagga NSW 2650",
    "addr:housenumber":"64",
    "addr:postcode":"2650",
    "addr:street":"Churchill Ave",
    "iso:country":"AU",
    "sg:address":"64 Churchill Ave Kooringal",
    "sg:city":"Wagga Wagga",
    "sg:classifiers":[
        {
            "category":"Health Services",
            "subcategory":"Health Practitioner",
            "type":"Services"
        }
    ],
    "sg:phone":"+61 2 6971 8100",
    "sg:postcode":"2650",
    "sg:province":"NSW",
    "sg:tags":[
        "osteopath"
    ],
    "wof:name":"Robert Black DC",
    "wof:placetype":"venue"
},
  "geometry": {"coordinates":[147.38047790499999,-35.1310043335],"type":"Point"}
}