{
  "type": "Feature",
  "properties": {
    "iso:country":"AU",
    "sg:address":"731 Victoria Rd",
    "sg:city":"Ryde",
    "sg:classifiers":[
        {
            "category":"Retail",
            "subcategory":"Auto Repair",
            "type":"Services"
        }
    ],
    "sg:phone":"+61 2 9877 6332",
    "sg:postcode":"2112",
    "sg:province":"NSW",
    "sg:tags":[
        "repairer",
        "motor",
        "engineer"
    ],
    "wof:name":"E K Automotive",
    "wof:placetype":"venue"
},
  "geometry": {"coordinates":[151.10455322300001,-33.8162651062],"type":"Point"}
}