{
  "type": "Feature",
  "properties": {
    "addr:full":"Suite 204, 696 Pittwater Rd Brookvale NSW 2100",
    "addr:housenumber":"696",
    "addr:postcode":"2100",
    "addr:street":"Pittwater Rd",
    "iso:country":"AU",
    "sg:address":"Suite 204, 696 Pittwater Rd",
    "sg:city":"Brookvale",
    "sg:classifiers":[
        {
            "category":"Professional",
            "subcategory":"Employment Agencies",
            "type":"Services"
        }
    ],
    "sg:phone":"+61 2 9905 3566",
    "sg:postcode":"2100",
    "sg:province":"NSW",
    "wof:name":"DCL Recruitment",
    "wof:placetype":"venue"
},
  "geometry": {"coordinates":[151.27191162099999,-33.762134552],"type":"Point"}
}