{
  "type": "Feature",
  "properties": {
    "iso:country":"AU",
    "sg:address":"7 Seymour St",
    "sg:city":"Carrick",
    "sg:classifiers":[
        {
            "category":"Building & Trades",
            "subcategory":"Construction",
            "type":"Services"
        }
    ],
    "sg:phone":"+61 419 300 464",
    "sg:postcode":"7291",
    "sg:province":"TAS",
    "sg:tags":[
        "roof"
    ],
    "wof:name":"Turbo Roofing",
    "wof:placetype":"venue"
},
  "geometry": {"coordinates":[147.01063537600001,-41.5348167419],"type":"Point"}
}