{
  "type": "Feature",
  "properties": {
    "addr:full":"106 Waterloo Rd Trafalgar VIC 3824",
    "addr:housenumber":"106",
    "addr:postcode":"3824",
    "addr:street":"Waterloo Rd",
    "iso:country":"AU",
    "sg:address":"106 Waterloo Rd",
    "sg:city":"Trafalgar",
    "sg:classifiers":[
        {
            "category":"Wholesale",
            "subcategory":"Machinery & Supplies",
            "type":"Manufacturing & Wholesale Goods"
        }
    ],
    "sg:phone":"+61 3 5633 1823",
    "sg:postcode":"3824",
    "sg:province":"VIC",
    "sg:tags":[
        "agricultural"
    ],
    "wof:name":"T.W & H.E Robertson",
    "wof:placetype":"venue"
},
  "geometry": {"coordinates":[146.15905799999999,-38.20615],"type":"Point"}
}