{
  "type": "Feature",
  "properties": {
    "addr:full":"Waterside 61/ 1 Beissel St Belconnen ACT 2617",
    "addr:housenumber":"61 / 1",
    "addr:postcode":"2617",
    "addr:street":"Beissel St",
    "iso:country":"AU",
    "sg:address":"Waterside 61/ 1 Beissel St",
    "sg:city":"Belconnen",
    "sg:classifiers":[
        {
            "category":"Personal",
            "subcategory":"Beauty Salon",
            "type":"Services"
        }
    ],
    "sg:phone":"+61 2 6251 9555",
    "sg:postcode":"2617",
    "sg:province":"ACT",
    "sg:tags":[
        "hairdresser"
    ],
    "wof:name":"La Bimbi Hair",
    "wof:placetype":"venue"
},
  "geometry": {"coordinates":[149.065582275,-35.2360267639],"type":"Point"}
}