{
  "type": "Feature",
  "properties": {
    "addr:full":"1960 Hume Hwy Campbellfield VIC 3061",
    "addr:housenumber":"1960",
    "addr:postcode":"3061",
    "addr:street":"Hume Hwy",
    "iso:country":"AU",
    "sg:address":"1960 Hume Hwy",
    "sg:city":"Campbellfield",
    "sg:classifiers":[
        {
            "category":"Shopping",
            "subcategory":"Stationery & Office Supplies",
            "type":"Retail Goods"
        }
    ],
    "sg:phone":"+61 3 9357 0100",
    "sg:postcode":"3061",
    "sg:province":"VIC",
    "sg:tags":[
        "packaging",
        "material"
    ],
    "wof:name":"Wayne Richardson Sales",
    "wof:placetype":"venue"
},
  "geometry": {"coordinates":[144.95344543499999,-37.6533699036],"type":"Point"}
}