{
  "type": "Feature",
  "properties": {
    "iso:country":"AU",
    "sg:address":"213 Brunswick St",
    "sg:city":"Fitzroy",
    "sg:classifiers":[
        {
            "category":"Personal",
            "subcategory":"Beauty Salon",
            "type":"Services"
        }
    ],
    "sg:phone":"+61 3 9419 1170",
    "sg:postcode":"3065",
    "sg:province":"VIC",
    "sg:tags":[
        "hairdresser"
    ],
    "wof:name":"Enzo & Mena Hair Design",
    "wof:placetype":"venue"
},
  "geometry": {"coordinates":[144.97781372099999,-37.8010292053],"type":"Point"}
}