{
  "type": "Feature",
  "properties": {
    "iso:country":"AU",
    "sg:address":"2 Daly St",
    "sg:city":"Daylesford",
    "sg:classifiers":[
        {
            "category":"Professional",
            "subcategory":"Art Services",
            "type":"Services"
        }
    ],
    "sg:phone":"+61 3 5348 3919",
    "sg:postcode":"3460",
    "sg:province":"VIC",
    "sg:tags":[
        "graphic",
        "designer"
    ],
    "wof:name":"Robertson I A",
    "wof:placetype":"venue"
},
  "geometry": {"coordinates":[144.14831543,-37.3403549194],"type":"Point"}
}