{
  "type": "Feature",
  "properties": {
    "addr:full":"25 Ferndale Rd Glen Iris VIC 3146",
    "addr:housenumber":"25",
    "addr:postcode":"3146",
    "addr:street":"Ferndale Rd",
    "iso:country":"AU",
    "sg:address":"25 Ferndale Rd",
    "sg:city":"Glen Iris",
    "sg:classifiers":[
        {
            "category":"Real Estate",
            "subcategory":"Real Estate Agent",
            "type":"Services"
        }
    ],
    "sg:phone":"+61 3 9885 2010",
    "sg:postcode":"3146",
    "sg:province":"VIC",
    "wof:name":"Ben Sudano Real Estate",
    "wof:placetype":"venue"
},
  "geometry": {"coordinates":[145.07122802699999,-37.8549766541],"type":"Point"}
}