{
  "type": "Feature",
  "properties": {
    "addr:full":"67 Davey St Hobart TAS 7000",
    "addr:housenumber":"67",
    "addr:postcode":"7000",
    "addr:street":"Davey St",
    "iso:country":"AU",
    "sg:address":"67 Davey St",
    "sg:city":"Hobart",
    "sg:classifiers":[
        {
            "category":"Health Services",
            "subcategory":"Doctor",
            "type":"Services"
        }
    ],
    "sg:phone":"+61 3 6223 6500",
    "sg:postcode":"7000",
    "sg:province":"TAS",
    "sg:tags":[
        "medical",
        "practitioner"
    ],
    "wof:name":"Rybak Marzena",
    "wof:placetype":"venue"
},
  "geometry": {"coordinates":[147.326293945,-42.8868713379],"type":"Point"}
}