{
  "type": "Feature",
  "properties": {
    "addr:full":"85 Tallow Wood Pl Mt Gravatt East QLD 4122",
    "addr:housenumber":"85",
    "addr:postcode":"4122",
    "addr:street":"Tallow Wood Pl",
    "iso:country":"AU",
    "sg:address":"85 Tallow Wood Pl",
    "sg:city":"Mt Gravatt East",
    "sg:classifiers":[
        {
            "category":"Professional",
            "subcategory":"Accounting & Tax Preparation",
            "type":"Services"
        }
    ],
    "sg:phone":"+61 7 3219 1134",
    "sg:postcode":"4122",
    "sg:province":"QLD",
    "sg:tags":[
        "bookkeeping"
    ],
    "wof:name":"Malcolm I M",
    "wof:placetype":"venue"
},
  "geometry": {"coordinates":[153.08555602999999,-27.5204257965],"type":"Point"}
}