{
  "type": "Feature",
  "properties": {
    "iso:country":"AU",
    "sg:address":"9 kubis Ave",
    "sg:city":"Aspendale",
    "sg:classifiers":[
        {
            "category":"Building & Trades",
            "subcategory":"Landscaping Services",
            "type":"Services"
        }
    ],
    "sg:phone":"+61 3 9580 6857",
    "sg:postcode":"3195",
    "sg:province":"VIC",
    "sg:tags":[
        "designer",
        "landscape",
        "contractor"
    ],
    "wof:name":"Adina Mering Landscaping",
    "wof:placetype":"venue"
},
  "geometry": {"coordinates":[145.10252380399999,-38.0197677612],"type":"Point"}
}