{
  "type": "Feature",
  "properties": {
    "addr:full":"23 Sale St Orange NSW 2800",
    "addr:housenumber":"23",
    "addr:postcode":"2800",
    "addr:street":"Sale St",
    "iso:country":"AU",
    "sg:address":"23 Sale St",
    "sg:city":"Orange",
    "sg:classifiers":[
        {
            "category":"Real Estate",
            "subcategory":"Real Estate Agent",
            "type":"Services"
        }
    ],
    "sg:phone":"+61 2 6351 2548",
    "sg:postcode":"2800",
    "sg:province":"NSW",
    "wof:name":"L.J. Hooker",
    "wof:placetype":"venue"
},
  "geometry": {"coordinates":[149.09573364299999,-33.284828186],"type":"Point"}
}