{
  "type": "Feature",
  "properties": {
    "addr:full":"2 Doree Pl Dora Creek NSW 2264",
    "addr:housenumber":"2",
    "addr:postcode":"2264",
    "addr:street":"Doree Pl Dora",
    "iso:country":"AU",
    "sg:address":"2 Doree Pl",
    "sg:city":"Dora Creek",
    "sg:classifiers":[
        {
            "category":"Health Services",
            "subcategory":"Dentist",
            "type":"Services"
        }
    ],
    "sg:phone":"+61 2 4973 1938",
    "sg:postcode":"2264",
    "sg:province":"NSW",
    "wof:name":"Sun Ren & Taper Luke",
    "wof:placetype":"venue"
},
  "geometry": {"coordinates":[151.501846,-33.084518],"type":"Point"}
}