{
  "type": "Feature",
  "properties": {
    "addr:full":"Unit 2/ 5 Adina Crt Tullamarine VIC 3043",
    "addr:housenumber":"5",
    "addr:postcode":"3043",
    "addr:street":"Adina Crt",
    "iso:country":"AU",
    "sg:address":"Unit 2/ 5 Adina Crt",
    "sg:city":"Tullamarine",
    "sg:classifiers":[
        {
            "category":"Professional",
            "subcategory":"Employment Agencies",
            "type":"Services"
        }
    ],
    "sg:phone":"+61 3 9335 1844",
    "sg:postcode":"3043",
    "sg:province":"VIC",
    "sg:tags":[
        "broker",
        "custom"
    ],
    "wof:name":"Plane To Sea Logistics Pty Ltd",
    "wof:placetype":"venue"
},
  "geometry": {"coordinates":[144.87597656200001,-37.7112693787],"type":"Point"}
}