{
  "type": "Feature",
  "properties": {
    "addr:full":"19 Elizabeth Ave Taree NSW 2430",
    "addr:housenumber":"19",
    "addr:postcode":"2430",
    "addr:street":"Elizabeth Ave",
    "iso:country":"AU",
    "sg:address":"19 Elizabeth Ave",
    "sg:city":"Taree",
    "sg:classifiers":[
        {
            "category":"Wholesale",
            "subcategory":"Machinery & Supplies",
            "type":"Manufacturing & Wholesale Goods"
        }
    ],
    "sg:phone":"+61 2 6557 7800",
    "sg:postcode":"2430",
    "sg:province":"NSW",
    "sg:tags":[
        "engineer"
    ],
    "wof:name":"Express Agencies Pty Ltd",
    "wof:placetype":"venue"
},
  "geometry": {"coordinates":[152.45292699999999,-31.901237],"type":"Point"}
}