{
  "type": "Feature",
  "properties": {
    "iso:country":"AU",
    "sg:address":"19 First Ave",
    "sg:city":"Maroochydore",
    "sg:classifiers":[
        {
            "category":"Professional",
            "subcategory":"Employment Agencies",
            "type":"Services"
        }
    ],
    "sg:phone":"+61 7 5443 7444",
    "sg:postcode":"4558",
    "sg:province":"QLD",
    "wof:name":"Jobfind Centre",
    "wof:placetype":"venue"
},
  "geometry": {"coordinates":[153.09344482399999,-26.656255722],"type":"Point"}
}