{
  "type": "Feature",
  "properties": {
    "addr:full":"156 Coromandel Pde Blackwood SA 5051",
    "addr:housenumber":"156",
    "addr:postcode":"5051",
    "addr:street":"Coromandel Pde",
    "iso:country":"AU",
    "sg:address":"156 Coromandel Pde",
    "sg:city":"Blackwood",
    "sg:classifiers":[
        {
            "category":"Professional",
            "type":"Services"
        }
    ],
    "sg:phone":"+61 8 8278 8019",
    "sg:postcode":"5051",
    "sg:province":"SA",
    "sg:tags":[
        "packaging",
        "filling",
        "assembling"
    ],
    "wof:name":"Craigburn Industries",
    "wof:placetype":"venue"
},
  "geometry": {"coordinates":[138.618225,-35.043251],"type":"Point"}
}