{
  "type": "Feature",
  "properties": {
    "iso:country":"AU",
    "sg:address":"U1/ 52b St Leonards Rd",
    "sg:city":"Ascot Vale",
    "sg:classifiers":[
        {
            "category":"Shopping",
            "subcategory":"Clothing, Apparel, & Fashions",
            "type":"Retail Goods"
        }
    ],
    "sg:phone":"+61 3 9370 9091",
    "sg:postcode":"3032",
    "sg:province":"VIC",
    "sg:tags":[
        "boutique"
    ],
    "wof:name":"Mishis Boutique",
    "wof:placetype":"venue"
},
  "geometry": {"coordinates":[144.915527,-37.773701],"type":"Point"}
}