{
  "type": "Feature",
  "properties": {
    "iso:country":"AU",
    "sg:address":"28 Hawthorn Rd",
    "sg:city":"Caulfield North",
    "sg:classifiers":[
        {
            "category":"Health Services",
            "subcategory":"Health Practitioner",
            "type":"Services"
        }
    ],
    "sg:phone":"+61 3 9509 1306",
    "sg:postcode":"3161",
    "sg:province":"VIC",
    "sg:tags":[
        "psychotherapist"
    ],
    "wof:name":"Blenkhorn June",
    "wof:placetype":"venue"
},
  "geometry": {"coordinates":[145.02532959000001,-37.8685112],"type":"Point"}
}