{
  "type": "Feature",
  "properties": {
    "addr:full":"11 Bennison Rd Hinchinbrook NSW 2168",
    "addr:housenumber":"11",
    "addr:postcode":"2168",
    "addr:street":"Bennison Rd",
    "iso:country":"AU",
    "sg:address":"11 Bennison Rd",
    "sg:city":"Hinchinbrook",
    "sg:classifiers":[
        {
            "category":"Professional",
            "subcategory":"Art Services",
            "type":"Services"
        }
    ],
    "sg:phone":"+61 407 230 511",
    "sg:postcode":"2168",
    "sg:province":"NSW",
    "sg:tags":[
        "decorator",
        "painter"
    ],
    "wof:name":"Casula Painting Service",
    "wof:placetype":"venue"
},
  "geometry": {"coordinates":[150.85731506400001,-33.9152412415],"type":"Point"}
}