{
  "type": "Feature",
  "properties": {
    "addr:full":"Shop 8 616 Princes Hwy Rockdale NSW 2216",
    "addr:housenumber":"shop 8 616",
    "addr:postcode":"2216",
    "addr:street":"Princes Hwy",
    "iso:country":"AU",
    "sg:address":"Shop 8 616 Princes Hwy",
    "sg:city":"Rockdale",
    "sg:classifiers":[
        {
            "category":"Food & Beverages",
            "subcategory":"Groceries & Convenience Stores",
            "type":"Retail Goods"
        }
    ],
    "sg:phone":"+61 2 9567 5999",
    "sg:postcode":"2216",
    "sg:province":"NSW",
    "wof:name":"Imprez Filipino & Asian Variety Store",
    "wof:placetype":"venue"
},
  "geometry": {"coordinates":[151.13798499999999,-33.957253],"type":"Point"}
}