{
  "type": "Feature",
  "properties": {
    "addr:full":"38 Boronia Ave Cheltenham NSW 2119",
    "addr:housenumber":"38",
    "addr:postcode":"2119",
    "addr:street":"Boronia Ave",
    "iso:country":"AU",
    "sg:address":"38 Boronia Ave",
    "sg:city":"Cheltenham",
    "sg:classifiers":[
        {
            "category":"Health Services",
            "subcategory":"Health Practitioner",
            "type":"Services"
        }
    ],
    "sg:phone":"+61 2 9868 1532",
    "sg:postcode":"2119",
    "sg:province":"NSW",
    "sg:tags":[
        "technique",
        "alexander"
    ],
    "wof:name":"Australian Society of Teachers of the Alexander Technique (AUSTAT)",
    "wof:placetype":"venue"
},
  "geometry": {"coordinates":[151.07191467300001,-33.7590446472],"type":"Point"}
}