{
  "type": "Feature",
  "properties": {
    "addr:full":"203 River St Maclean NSW 2463",
    "addr:housenumber":"203",
    "addr:postcode":"2463",
    "addr:street":"River St",
    "iso:country":"AU",
    "sg:address":"203 River St",
    "sg:city":"Maclean",
    "sg:classifiers":[
        {
            "category":"Organizations",
            "subcategory":"Non-profit Organization",
            "type":"Services"
        }
    ],
    "sg:phone":"+61 2 6645 3200",
    "sg:postcode":"2463",
    "sg:province":"NSW",
    "sg:tags":[
        "support",
        "disability",
        "organisation"
    ],
    "wof:name":"Clarence Community Transport Inc",
    "wof:placetype":"venue"
},
  "geometry": {"coordinates":[153.19676208499999,-29.4551811218],"type":"Point"}
}