{
  "type": "Feature",
  "properties": {
    "addr:full":"Cnr Cambridge & Harborne Sts Wembley WA 6014",
    "addr:postcode":"6014",
    "addr:street":"Cnr",
    "iso:country":"AU",
    "sg:address":"Cnr Cambridge & Harborne Sts",
    "sg:city":"Wembley",
    "sg:classifiers":[
        {
            "category":"Home & Garden",
            "subcategory":"Household Appliances",
            "type":"Retail Goods"
        }
    ],
    "sg:phone":"+61 8 6380 1600",
    "sg:postcode":"6014",
    "sg:province":"WA",
    "sg:tags":[
        "equipment",
        "gas"
    ],
    "wof:name":"Hearth House",
    "wof:placetype":"venue"
},
  "geometry": {"coordinates":[115.813461304,-31.9407501221],"type":"Point"}
}