{
  "type": "Feature",
  "properties": {
    "addr:full":"Albert St Junee NSW 2663",
    "addr:postcode":"2663",
    "addr:street":"Albert St",
    "iso:country":"AU",
    "sg:address":"Albert St",
    "sg:city":"Junee",
    "sg:classifiers":[
        {
            "category":"Farming",
            "subcategory":"Farm & Veterinary Services",
            "type":"Manufacturing & Wholesale Goods"
        }
    ],
    "sg:phone":"+61 2 6924 1337",
    "sg:postcode":"2663",
    "sg:province":"NSW",
    "sg:tags":[
        "shearing",
        "contractor"
    ],
    "wof:name":"Burcher G N",
    "wof:placetype":"venue"
},
  "geometry": {"coordinates":[147.570220947,-34.8746452332],"type":"Point"}
}