{
  "type": "Feature",
  "properties": {
    "iso:country":"AU",
    "sg:address":"18 First Ave",
    "sg:city":"Bickley",
    "sg:classifiers":[
        {
            "category":"Education",
            "subcategory":"School",
            "type":"Public Place"
        }
    ],
    "sg:phone":"+61 8 9291 6399",
    "sg:postcode":"6076",
    "sg:province":"WA",
    "sg:tags":[
        "co-educational"
    ],
    "wof:name":"Carmel Adventist College",
    "wof:placetype":"venue"
},
  "geometry": {"coordinates":[116.09036254900001,-32.006072998],"type":"Point"}
}