{
  "type": "Feature",
  "properties": {
    "addr:full":"393 Burwood Hwy Burwood VIC 3125",
    "addr:housenumber":"393",
    "addr:postcode":"3125",
    "addr:street":"Burwood Hwy",
    "iso:country":"AU",
    "sg:address":"393 Burwood Hwy",
    "sg:city":"Burwood",
    "sg:classifiers":[
        {
            "category":"Sports & Exercise",
            "subcategory":"Gym",
            "type":"Entertainment"
        }
    ],
    "sg:phone":"+61 3 9808 9033",
    "sg:postcode":"3125",
    "sg:province":"VIC",
    "sg:tags":[
        "health",
        "fitness"
    ],
    "wof:name":"Bennettswood Fitness Centre",
    "wof:placetype":"venue"
},
  "geometry": {"coordinates":[145.170196533,-37.8546562195],"type":"Point"}
}