{
  "type": "Feature",
  "properties": {
    "addr:full":"45 Sophie Ave Broadbeach Waters QLD 4218",
    "addr:housenumber":"45",
    "addr:postcode":"4218",
    "addr:street":"Sophie Ave",
    "iso:country":"AU",
    "sg:address":"45 Sophie Ave",
    "sg:city":"Broadbeach Waters",
    "sg:classifiers":[
        {
            "category":"Arena",
            "subcategory":"Sports Club",
            "type":"Entertainment"
        }
    ],
    "sg:phone":"+61 412 359 393",
    "sg:postcode":"4218",
    "sg:province":"QLD",
    "sg:tags":[
        "life",
        "surfing",
        "saving"
    ],
    "wof:name":"Queensland Surf Rowers League",
    "wof:placetype":"venue"
},
  "geometry": {"coordinates":[153.407669067,-28.0264148712],"type":"Point"}
}