{
  "type": "Feature",
  "properties": {
    "addr:full":"PO Box 366 Quirindi NSW 2343",
    "addr:postcode":"2343",
    "iso:country":"AU",
    "sg:address":"PO Box 366",
    "sg:city":"Quirindi",
    "sg:classifiers":[
        {
            "category":"Wholesale",
            "subcategory":"Machinery & Supplies",
            "type":"Manufacturing & Wholesale Goods"
        }
    ],
    "sg:phone":"+61 500 555 355",
    "sg:postcode":"2343",
    "sg:province":"NSW",
    "sg:tags":[
        "agricultural"
    ],
    "wof:name":"DTS Mechanical Design",
    "wof:placetype":"venue"
},
  "geometry": {"coordinates":[150.67579650900001,-31.5191898346],"type":"Point"}
}