{
  "type": "Feature",
  "properties": {
    "iso:country":"AU",
    "sg:address":"Cnr Princes Hwy & Lister Ave",
    "sg:city":"Rockdale",
    "sg:classifiers":[
        {
            "category":"Shopping",
            "subcategory":"Computers & Home Electronics",
            "type":"Retail Goods"
        }
    ],
    "sg:phone":"+61 2 9599 2000",
    "sg:postcode":"2216",
    "sg:province":"NSW",
    "sg:tags":[
        "hi-fi",
        "equipment"
    ],
    "wof:name":"NAPF Electronics",
    "wof:placetype":"venue"
},
  "geometry": {"coordinates":[151.138092,-33.951809],"type":"Point"}
}