{
  "type": "Feature",
  "properties": {
    "addr:full":"4 Waterloo Crt Alexander Heights WA 6064",
    "addr:housenumber":"4",
    "addr:postcode":"6064",
    "addr:street":"Waterloo Crt",
    "iso:country":"AU",
    "sg:address":"4 Waterloo Crt",
    "sg:city":"Alexander Heights",
    "sg:classifiers":[
        {
            "category":"Home & Garden",
            "subcategory":"Building Materials",
            "type":"Retail Goods"
        }
    ],
    "sg:phone":"+61 419 948 592",
    "sg:postcode":"6064",
    "sg:province":"WA",
    "sg:tags":[
        "lawn",
        "cutting",
        "maintenance"
    ],
    "wof:name":"JD's Lawn & Garden Care",
    "wof:placetype":"venue"
},
  "geometry": {"coordinates":[115.87422180199999,-31.8216362],"type":"Point"}
}