{
  "type": "Feature",
  "properties": {
    "iso:country":"AU",
    "sg:address":"5/ 9",
    "sg:city":"Mandurah Tce Mandurah",
    "sg:classifiers":[
        {
            "category":"Restaurant",
            "type":"Food & Drink"
        }
    ],
    "sg:phone":"+61 8 9581 1248",
    "sg:postcode":"6210",
    "sg:province":"WA",
    "wof:name":"Redmanna Waterfront Restaurant",
    "wof:placetype":"venue"
},
  "geometry": {"coordinates":[115.71907,-32.534199],"type":"Point"}
}