{
  "type": "Feature",
  "properties": {
    "addr:full":"PO Box 8022 Rivett ACT 2611",
    "addr:postcode":"2611",
    "iso:country":"AU",
    "sg:address":"PO Box 8022",
    "sg:city":"Rivett",
    "sg:classifiers":[
        {
            "category":"Professional",
            "subcategory":"Detective & Security Services",
            "type":"Services"
        }
    ],
    "sg:phone":"+61 419 693 883",
    "sg:postcode":"2611",
    "sg:province":"ACT",
    "sg:tags":[
        "guard",
        "patrol"
    ],
    "wof:name":"TDK Security",
    "wof:placetype":"venue"
},
  "geometry": {"coordinates":[149.03692626899999,-35.3473396301],"type":"Point"}
}