{
  "type": "Feature",
  "properties": {
    "iso:country":"AU",
    "sg:address":"64 Parramatta Rd",
    "sg:city":"Glebe",
    "sg:classifiers":[
        {
            "category":"Shopping",
            "subcategory":"Computers & Home Electronics",
            "type":"Retail Goods"
        }
    ],
    "sg:phone":"+61 1300 303 240",
    "sg:postcode":"2037",
    "sg:province":"NSW",
    "sg:tags":[
        "equipment",
        "multimedia"
    ],
    "wof:name":"Propertymode.com.au",
    "wof:placetype":"venue"
},
  "geometry": {"coordinates":[151.18234252900001,-33.8853721619],"type":"Point"}
}