{
  "type": "Feature",
  "properties": {
    "iso:country":"AU",
    "sg:address":"PO Box 6140",
    "sg:city":"Baulkham Hills BC",
    "sg:classifiers":[
        {
            "category":"Shopping",
            "subcategory":"Stationery & Office Supplies",
            "type":"Retail Goods"
        }
    ],
    "sg:phone":"+61 2 8845 8600",
    "sg:postcode":"1755",
    "sg:province":"NSW",
    "sg:tags":[
        "partition"
    ],
    "wof:name":"Australian Personal Watercraft Association",
    "wof:placetype":"venue"
},
  "geometry": {"coordinates":[150.975403,-33.761982],"type":"Point"}
}