{
  "type": "Feature",
  "properties": {
    "addr:full":"117 Springfield Rd Blackburn North VIC 3130",
    "addr:housenumber":"117",
    "addr:postcode":"3130",
    "addr:street":"Springfield Rd",
    "iso:country":"AU",
    "sg:address":"117 Springfield Rd",
    "sg:city":"Blackburn North",
    "sg:classifiers":[
        {
            "category":"Health Services",
            "subcategory":"Doctor",
            "type":"Services"
        }
    ],
    "sg:phone":"+61 3 9878 3100",
    "sg:postcode":"3130",
    "sg:province":"VIC",
    "sg:tags":[
        "medical",
        "practitioner"
    ],
    "wof:name":"Blake R O",
    "wof:placetype":"venue"
},
  "geometry": {"coordinates":[145.15298461899999,-37.810333252],"type":"Point"}
}