{
  "type": "Feature",
  "properties": {
    "iso:country":"AU",
    "sg:address":"1 Wilson St",
    "sg:city":"Queanbeyan",
    "sg:classifiers":[
        {
            "category":"Utilities",
            "subcategory":"Electric",
            "type":"Services"
        }
    ],
    "sg:phone":"+61 419 299 583",
    "sg:postcode":"2620",
    "sg:province":"NSW",
    "sg:tags":[
        "electrical",
        "contractor"
    ],
    "wof:name":"Berkeley Electrical Services",
    "wof:placetype":"venue"
},
  "geometry": {"coordinates":[149.211227417,-35.3628120422],"type":"Point"}
}