{
  "type": "Feature",
  "properties": {
    "iso:country":"AU",
    "sg:address":"570 Hendy Main Rd",
    "sg:city":"Mt Moriac",
    "sg:classifiers":[
        {
            "category":"Building & Trades",
            "subcategory":"Equipment Rental",
            "type":"Services"
        }
    ],
    "sg:phone":"+61 417 386 742",
    "sg:postcode":"3240",
    "sg:province":"VIC",
    "sg:tags":[
        "demolition",
        "contractor"
    ],
    "wof:name":"Angus Robert Demolition",
    "wof:placetype":"venue"
},
  "geometry": {"coordinates":[144.17881774899999,-38.2219619751],"type":"Point"}
}