{
  "type": "Feature",
  "properties": {
    "addr:full":"39a Manton St Hindmarsh SA 5007",
    "addr:housenumber":"39a",
    "addr:postcode":"5007",
    "addr:street":"Manton St",
    "iso:country":"AU",
    "sg:address":"39a Manton St",
    "sg:city":"Hindmarsh",
    "sg:classifiers":[
        {
            "category":"Wholesale",
            "subcategory":"Electrical",
            "type":"Manufacturing & Wholesale Goods"
        }
    ],
    "sg:phone":"+61 8 8346 6944",
    "sg:postcode":"5007",
    "sg:province":"SA",
    "sg:tags":[
        "wholesaler"
    ],
    "wof:name":"Ryotech Agencies",
    "wof:placetype":"venue"
},
  "geometry": {"coordinates":[138.569702148,-34.9067077637],"type":"Point"}
}