{
  "type": "Feature",
  "properties": {
    "addr:full":"22a James St Toowoomba QLD 4350",
    "addr:housenumber":"22a",
    "addr:postcode":"4350",
    "addr:street":"James St",
    "iso:country":"AU",
    "sg:address":"22a James St",
    "sg:city":"Toowoomba",
    "sg:classifiers":[
        {
            "category":"Health Services",
            "subcategory":"Dentist",
            "type":"Services"
        }
    ],
    "sg:phone":"+61 7 4632 6553",
    "sg:postcode":"4350",
    "sg:province":"QLD",
    "wof:name":"Quinn Chris Dr",
    "wof:placetype":"venue"
},
  "geometry": {"coordinates":[151.97593699999999,-27.571981],"type":"Point"}
}