{
  "type": "Feature",
  "properties": {
    "iso:country":"AU",
    "sg:address":"Ste 4/ 8 Short St",
    "sg:city":"Nerang",
    "sg:classifiers":[
        {
            "category":"Banks & Credit Unions",
            "subcategory":"Investment Brokerage",
            "type":"Services"
        }
    ],
    "sg:phone":"+61 7 5502 1555",
    "sg:postcode":"4211",
    "sg:province":"QLD",
    "sg:tags":[
        "finance",
        "broker"
    ],
    "wof:name":"Fast Access Finance",
    "wof:placetype":"venue"
},
  "geometry": {"coordinates":[153.33883667000001,-27.9876441956],"type":"Point"}
}