{
  "type": "Feature",
  "properties": {
    "iso:country":"AU",
    "sg:address":"208 Stegmans Rd",
    "sg:city":"Rosedale",
    "sg:classifiers":[
        {
            "category":"Retail",
            "subcategory":"Veterinary Services",
            "type":"Services"
        }
    ],
    "sg:phone":"+61 7 4156 5157",
    "sg:postcode":"4674",
    "sg:province":"QLD",
    "sg:tags":[
        "surgeon"
    ],
    "wof:name":"McDonald A R",
    "wof:placetype":"venue"
},
  "geometry": {"coordinates":[151.904037,-24.574966],"type":"Point"}
}