{
  "type": "Feature",
  "properties": {
    "addr:full":"13 Fletcher Rd Mt Barker SA 5251",
    "addr:housenumber":"13",
    "addr:postcode":"5251",
    "addr:street":"Fletcher Rd",
    "iso:country":"AU",
    "sg:address":"13 Fletcher Rd",
    "sg:city":"Mt Barker",
    "sg:classifiers":[
        {
            "category":"Health Services",
            "subcategory":"Health Practitioner",
            "type":"Services"
        }
    ],
    "sg:phone":"+61 8 8391 0567",
    "sg:postcode":"5251",
    "sg:province":"SA",
    "sg:tags":[
        "naturopath"
    ],
    "wof:name":"Greenwood Holistic Healing Centre",
    "wof:placetype":"venue"
},
  "geometry": {"coordinates":[138.86558532699999,-35.0715484619],"type":"Point"}
}