{
  "type": "Feature",
  "properties": {
    "addr:full":"11 Henry Searle Drv Iluka NSW 2466",
    "addr:housenumber":"11",
    "addr:postcode":"2466",
    "addr:street":"Henry Searle Drv",
    "iso:country":"AU",
    "sg:address":"11 Henry Searle Drv",
    "sg:city":"Iluka",
    "sg:classifiers":[
        {
            "category":"Utilities",
            "subcategory":"Electric",
            "type":"Services"
        }
    ],
    "sg:phone":"+61 2 6646 6244",
    "sg:postcode":"2466",
    "sg:province":"NSW",
    "sg:tags":[
        "electrical",
        "contractor"
    ],
    "wof:name":"Iluka Electrical Services",
    "wof:placetype":"venue"
},
  "geometry": {"coordinates":[153.35162353499999,-29.4068202972],"type":"Point"}
}