{
  "type": "Feature",
  "properties": {
    "addr:full":"Production Ave Warana QLD 4575",
    "addr:postcode":"4575",
    "addr:street":"Production Ave",
    "iso:country":"AU",
    "sg:address":"Production Ave",
    "sg:city":"Warana",
    "sg:classifiers":[
        {
            "category":"School Buses",
            "type":"Transportation"
        }
    ],
    "sg:phone":"+61 13 15 79",
    "sg:postcode":"4575",
    "sg:province":"QLD",
    "sg:tags":[
        "brick"
    ],
    "wof:name":"CSR PGH (Bricks & Pavers)",
    "wof:placetype":"venue"
},
  "geometry": {"coordinates":[153.129211,-26.727793],"type":"Point"}
}