{
  "type": "Feature",
  "properties": {
    "addr:full":"3/ 7 Oakfield Rd Salt Ash NSW 2318",
    "addr:housenumber":"/ 7",
    "addr:postcode":"2318",
    "addr:street":"Oakfield Rd",
    "iso:country":"AU",
    "sg:address":"3/ 7 Oakfield Rd",
    "sg:city":"Salt Ash",
    "sg:classifiers":[
        {
            "category":"Building & Trades",
            "subcategory":"Construction",
            "type":"Services"
        }
    ],
    "sg:phone":"+61 431 489 322",
    "sg:postcode":"2318",
    "sg:province":"NSW",
    "sg:tags":[
        "joinery"
    ],
    "wof:name":"Period Designs",
    "wof:placetype":"venue"
},
  "geometry": {"coordinates":[151.903976,-32.790955],"type":"Point"}
}