{
  "type": "Feature",
  "properties": {
    "iso:country":"AU",
    "sg:address":"6 Cardew St",
    "sg:city":"Melville",
    "sg:classifiers":[
        {
            "category":"Building & Trades",
            "subcategory":"Construction",
            "type":"Services"
        }
    ],
    "sg:phone":"+61 415 956 545",
    "sg:postcode":"6156",
    "sg:province":"WA",
    "sg:tags":[
        "brick",
        "paving"
    ],
    "wof:name":"The Red & The Green",
    "wof:placetype":"venue"
},
  "geometry": {"coordinates":[115.80637400000001,-32.041218],"type":"Point"}
}