{
  "type": "Feature",
  "properties": {
    "addr:full":"75 Belair Rd Kingswood SA 5062",
    "addr:housenumber":"75",
    "addr:postcode":"5062",
    "addr:street":"Belair Rd",
    "iso:country":"AU",
    "sg:address":"75 Belair Rd",
    "sg:city":"Kingswood",
    "sg:classifiers":[
        {
            "category":"Professional",
            "subcategory":"Accounting & Tax Preparation",
            "type":"Services"
        }
    ],
    "sg:phone":"+61 8 8272 5620",
    "sg:postcode":"5062",
    "sg:province":"SA",
    "sg:tags":[
        "accountant",
        "auditor"
    ],
    "wof:name":"dmca",
    "wof:placetype":"venue"
},
  "geometry": {"coordinates":[138.60932922399999,-34.9725761414],"type":"Point"}
}