{
  "type": "Feature",
  "properties": {
    "addr:full":"34 Ballantyne Rd Mortdale NSW 2223",
    "addr:housenumber":"34",
    "addr:postcode":"2223",
    "addr:street":"Ballantyne Rd",
    "iso:country":"AU",
    "sg:address":"34 Ballantyne Rd",
    "sg:city":"Mortdale",
    "sg:classifiers":[
        {
            "category":"Building & Trades",
            "subcategory":"Construction",
            "type":"Services"
        }
    ],
    "sg:phone":"+61 2 9580 7463",
    "sg:postcode":"2223",
    "sg:province":"NSW",
    "sg:tags":[
        "contractor"
    ],
    "wof:name":"Ballantyne I S",
    "wof:placetype":"venue"
},
  "geometry": {"coordinates":[151.064453125,-33.9734153748],"type":"Point"}
}