{
  "type": "Feature",
  "properties": {
    "addr:full":"11 O&#039;Shanesy St Gracemere QLD 4702",
    "addr:housenumber":"11",
    "addr:postcode":"4702",
    "addr:street":"O &;Shanesy St",
    "iso:country":"AU",
    "sg:address":"11 O&#039;Shanesy St",
    "sg:city":"Gracemere",
    "sg:classifiers":[
        {
            "category":"Autos & Motor Vehicles",
            "subcategory":"Auto Supplies",
            "type":"Retail Goods"
        }
    ],
    "sg:phone":"+61 7 4933 1395",
    "sg:postcode":"4702",
    "sg:province":"QLD",
    "sg:tags":[
        "tyre"
    ],
    "wof:name":"Tom Leyden Tyres & Mechanical",
    "wof:placetype":"venue"
},
  "geometry": {"coordinates":[150.452194214,-23.4334201813],"type":"Point"}
}