{
  "type": "Feature",
  "properties": {
    "addr:full":"80 Box St Taren Point NSW 2229",
    "addr:housenumber":"80",
    "addr:postcode":"2229",
    "addr:street":"Box St",
    "iso:country":"AU",
    "sg:address":"80 Box St",
    "sg:city":"Taren Point",
    "sg:classifiers":[
        {
            "category":"Building & Trades",
            "subcategory":"Equipment Rental",
            "type":"Services"
        }
    ],
    "sg:phone":"+61 2 9525 8213",
    "sg:postcode":"2229",
    "sg:province":"NSW",
    "sg:tags":[
        "supply",
        "catering"
    ],
    "wof:name":"Zeus",
    "wof:placetype":"venue"
},
  "geometry": {"coordinates":[151.11814880399999,-34.0239677429],"type":"Point"}
}