{
  "type": "Feature",
  "properties": {
    "addr:full":"Bird St Burnie TAS 7320",
    "addr:postcode":"7320",
    "addr:street":"Bird St",
    "iso:country":"AU",
    "sg:address":"Bird St",
    "sg:city":"Burnie",
    "sg:classifiers":[
        {
            "category":"Education",
            "subcategory":"School",
            "type":"Public Place"
        }
    ],
    "sg:phone":"+61 3 6432 2755",
    "sg:postcode":"7320",
    "sg:province":"TAS",
    "sg:tags":[
        "state",
        "except",
        "nsw"
    ],
    "wof:name":"Montello Primary School",
    "wof:placetype":"venue"
},
  "geometry": {"coordinates":[145.89494300000001,-41.061729],"type":"Point"}
}