{
  "type": "Feature",
  "properties": {
    "iso:country":"AU",
    "sg:address":"126 Main Ave",
    "sg:city":"Windsor",
    "sg:classifiers":[
        {
            "category":"Professional",
            "subcategory":"Employment Agencies",
            "type":"Services"
        }
    ],
    "sg:phone":"+61 413 209 644",
    "sg:postcode":"4030",
    "sg:province":"QLD",
    "sg:tags":[
        "entertainer",
        "agent"
    ],
    "wof:name":"Michael Weston Organisation",
    "wof:placetype":"venue"
},
  "geometry": {"coordinates":[153.026855,-27.432081],"type":"Point"}
}