{
  "type": "Feature",
  "properties": {
    "addr:full":"193 Swallow St Mooroobool QLD 4870",
    "addr:housenumber":"193",
    "addr:postcode":"4870",
    "addr:street":"Swallow St",
    "iso:country":"AU",
    "sg:address":"193 Swallow St",
    "sg:city":"Mooroobool",
    "sg:classifiers":[
        {
            "category":"Food & Beverages",
            "subcategory":"Supermarket",
            "type":"Retail Goods"
        }
    ],
    "sg:phone":"+61 7 4032 3054",
    "sg:postcode":"4870",
    "sg:province":"QLD",
    "sg:tags":[
        "grocery",
        "store"
    ],
    "wof:name":"Campbell's IGA",
    "wof:placetype":"venue"
},
  "geometry": {"coordinates":[145.73431396500001,-16.9272594452],"type":"Point"}
}