{
  "type": "Feature",
  "properties": {
    "addr:full":"23 Dividend St Mansfield QLD 4122",
    "addr:housenumber":"23",
    "addr:postcode":"4122",
    "addr:street":"Dividend St",
    "iso:country":"AU",
    "sg:address":"23 Dividend St",
    "sg:city":"Mansfield",
    "sg:classifiers":[
        {
            "category":"Shopping",
            "subcategory":"Party Supplies",
            "type":"Retail Goods"
        }
    ],
    "sg:phone":"+61 7 3343 4773",
    "sg:postcode":"4122",
    "sg:province":"QLD",
    "wof:name":"Affordable Party Supplies",
    "wof:placetype":"venue"
},
  "geometry": {"coordinates":[153.10415649399999,-27.5317497253],"type":"Point"}
}