{
  "type": "Feature",
  "properties": {
    "addr:full":"34 Mitchell St Bendigo VIC 3550",
    "addr:housenumber":"34",
    "addr:postcode":"3550",
    "addr:street":"Mitchell St",
    "iso:country":"AU",
    "sg:address":"34 Mitchell St",
    "sg:city":"Bendigo",
    "sg:classifiers":[
        {
            "category":"Personal",
            "subcategory":"Beauty Salon",
            "type":"Services"
        }
    ],
    "sg:phone":"+61 3 5444 5075",
    "sg:postcode":"3550",
    "sg:province":"VIC",
    "wof:name":"CNC Nails",
    "wof:placetype":"venue"
},
  "geometry": {"coordinates":[144.279586792,-36.7608261108],"type":"Point"}
}