{
  "type": "Feature",
  "properties": {
    "addr:full":"Level 1/ 68 Grenfell St Adelaide SA 5000",
    "addr:housenumber":"/ 68",
    "addr:postcode":"5000",
    "addr:street":"Grenfell St",
    "iso:country":"AU",
    "sg:address":"Level 1/ 68 Grenfell St",
    "sg:city":"Adelaide",
    "sg:classifiers":[
        {
            "category":"Professional",
            "subcategory":"Engineering",
            "type":"Services"
        }
    ],
    "sg:phone":"+61 8 8235 6694",
    "sg:postcode":"5000",
    "sg:province":"SA",
    "sg:tags":[
        "consulting",
        "engineer"
    ],
    "wof:name":"G.H.D. Pty Ltd",
    "wof:placetype":"venue"
},
  "geometry": {"coordinates":[138.60220336899999,-34.9240455627],"type":"Point"}
}