{
  "type": "Feature",
  "properties": {
    "addr:full":"1155 Malvern Rd Malvern VIC 3144",
    "addr:housenumber":"1155",
    "addr:postcode":"3144",
    "addr:street":"Malvern Rd",
    "iso:country":"AU",
    "sg:address":"1155 Malvern Rd",
    "sg:city":"Malvern",
    "sg:classifiers":[
        {
            "category":"Health Services",
            "subcategory":"Doctor",
            "type":"Services"
        }
    ],
    "sg:phone":"+61 3 9824 7633",
    "sg:postcode":"3144",
    "sg:province":"VIC",
    "sg:tags":[
        "medical",
        "practitioner"
    ],
    "wof:name":"Malvern Diagnostic Imaging",
    "wof:placetype":"venue"
},
  "geometry": {"coordinates":[145.03120422399999,-37.8515930176],"type":"Point"}
}