{
  "type": "Feature",
  "properties": {
    "addr:full":"31 Anglesey Av St Georges SA 5064",
    "addr:housenumber":"31",
    "addr:postcode":"5064",
    "addr:street":"Anglesey Av St",
    "iso:country":"AU",
    "sg:address":"31 Anglesey Av",
    "sg:city":"St Georges",
    "sg:classifiers":[
        {
            "category":"Professional",
            "subcategory":"Art Services",
            "type":"Services"
        }
    ],
    "sg:phone":"+61 414 678 844",
    "sg:postcode":"5064",
    "sg:province":"SA",
    "sg:tags":[
        "graphic",
        "designer"
    ],
    "wof:name":"McConnell Design",
    "wof:placetype":"venue"
},
  "geometry": {"coordinates":[138.64663696299999,-34.9515266418],"type":"Point"}
}