{
  "type": "Feature",
  "properties": {
    "iso:country":"AU",
    "sg:address":"5 Railway St",
    "sg:city":"Kalbar",
    "sg:classifiers":[
        {
            "category":"Farming",
            "subcategory":"Farm",
            "type":"Manufacturing & Wholesale Goods"
        }
    ],
    "sg:phone":"+61 7 5463 7103",
    "sg:postcode":"4309",
    "sg:province":"QLD",
    "sg:tags":[
        "farmer"
    ],
    "wof:name":"Kalbar Grain & Produce",
    "wof:placetype":"venue"
},
  "geometry": {"coordinates":[152.62217712399999,-27.9401473999],"type":"Point"}
}