{
  "type": "Feature",
  "properties": {
    "iso:country":"AU",
    "sg:address":"341 Darling St",
    "sg:city":"Balmain",
    "sg:classifiers":[
        {
            "category":"Fast Food",
            "type":"Food & Drink"
        }
    ],
    "sg:phone":"+61 2 9810 3344",
    "sg:postcode":"2041",
    "sg:province":"NSW",
    "sg:tags":[
        "away",
        "take"
    ],
    "wof:name":"Balmain Trattoria & Pizzeria",
    "wof:placetype":"venue"
},
  "geometry": {"coordinates":[151.17889400000001,-33.856518],"type":"Point"}
}