{
  "type": "Feature",
  "properties": {
    "iso:country":"AU",
    "sg:address":"47 Collins St",
    "sg:city":"Hamilton",
    "sg:classifiers":[
        {
            "category":"Personal",
            "subcategory":"Beauty Salon",
            "type":"Services"
        }
    ],
    "sg:phone":"+61 3 5571 9399",
    "sg:postcode":"3300",
    "sg:province":"VIC",
    "wof:name":"Kylie's Tanning Studio",
    "wof:placetype":"venue"
},
  "geometry": {"coordinates":[142.02069091800001,-37.7476119995],"type":"Point"}
}