{
  "type": "Feature",
  "properties": {
    "addr:full":"182 Beatty Rd Archerfield QLD 4108",
    "addr:housenumber":"182",
    "addr:postcode":"4108",
    "addr:street":"Beatty Rd",
    "iso:country":"AU",
    "sg:address":"182 Beatty Rd",
    "sg:city":"Archerfield",
    "sg:classifiers":[
        {
            "category":"Professional",
            "type":"Services"
        }
    ],
    "sg:phone":"+61 7 3255 5044",
    "sg:postcode":"4108",
    "sg:province":"QLD",
    "sg:tags":[
        "transport"
    ],
    "wof:name":"CBT Logistics",
    "wof:placetype":"venue"
},
  "geometry": {"coordinates":[153.01588439899999,-27.5640830994],"type":"Point"}
}