{
  "type": "Feature",
  "properties": {
    "addr:full":"5 May St Fassifern NSW 2283",
    "addr:housenumber":"5",
    "addr:postcode":"2283",
    "addr:street":"May St",
    "iso:country":"AU",
    "sg:address":"5 May St",
    "sg:city":"Fassifern",
    "sg:classifiers":[
        {
            "category":"Professional",
            "type":"Services"
        }
    ],
    "sg:phone":"+61 2 4959 7073",
    "sg:postcode":"2283",
    "sg:province":"NSW",
    "sg:tags":[
        "courier"
    ],
    "wof:name":"Toronto Limousines",
    "wof:placetype":"venue"
},
  "geometry": {"coordinates":[151.59034729000001,-32.9887962341],"type":"Point"}
}