{
  "type": "Feature",
  "properties": {
    "addr:full":"Martin Pl Sydney NSW 2000",
    "addr:postcode":"2000",
    "addr:street":"Martin Pl",
    "iso:country":"AU",
    "sg:address":"Martin Pl",
    "sg:city":"Sydney",
    "sg:classifiers":[
        {
            "category":"Real Estate",
            "subcategory":"Developer",
            "type":"Services"
        }
    ],
    "sg:phone":"+61 2 9241 1161",
    "sg:postcode":"2000",
    "sg:province":"NSW",
    "sg:tags":[
        "development"
    ],
    "wof:name":"Palmarc Developments",
    "wof:placetype":"venue"
},
  "geometry": {"coordinates":[151.21018981899999,-33.8676948547],"type":"Point"}
}