{
  "type": "Feature",
  "properties": {
    "addr:full":"52 Roy St Jeparit VIC 3423",
    "addr:housenumber":"52",
    "addr:postcode":"3423",
    "addr:street":"Roy St",
    "iso:country":"AU",
    "sg:address":"52 Roy St",
    "sg:city":"Jeparit",
    "sg:classifiers":[
        {
            "category":"Food & Beverages",
            "subcategory":"Supermarket",
            "type":"Retail Goods"
        }
    ],
    "sg:phone":"+61 3 5397 2036",
    "sg:postcode":"3423",
    "sg:province":"VIC",
    "sg:tags":[
        "grocery",
        "store"
    ],
    "wof:name":"Jeparit Supermarket",
    "wof:placetype":"venue"
},
  "geometry": {"coordinates":[141.98838806099999,-36.1417350769],"type":"Point"}
}