{
  "type": "Feature",
  "properties": {
    "addr:full":"2020 Main North Rd Salisbury Park SA 5109",
    "addr:housenumber":"2020",
    "addr:postcode":"5109",
    "addr:street":"Main North Rd",
    "iso:country":"AU",
    "sg:address":"2020 Main North Rd",
    "sg:city":"Salisbury Park",
    "sg:classifiers":[
        {
            "category":"Autos & Motor Vehicles",
            "subcategory":"Automobile Sales",
            "type":"Retail Goods"
        }
    ],
    "sg:phone":"+61 8 8258 9677",
    "sg:postcode":"5109",
    "sg:province":"SA",
    "sg:tags":[
        "car",
        "new"
    ],
    "wof:name":"Kia Motors Australia",
    "wof:placetype":"venue"
},
  "geometry": {"coordinates":[138.67588806099999,-34.7584877014],"type":"Point"}
}