{
  "type": "Feature",
  "properties": {
    "addr:full":"6 Jarrah Crt Greensborough VIC 3088",
    "addr:housenumber":"6",
    "addr:postcode":"3088",
    "addr:street":"Jarrah Crt",
    "iso:country":"AU",
    "sg:address":"6 Jarrah Crt",
    "sg:city":"Greensborough",
    "sg:classifiers":[
        {
            "category":"Professional",
            "subcategory":"Employment Agencies",
            "type":"Services"
        }
    ],
    "sg:phone":"+61 3 9432 1726",
    "sg:postcode":"3088",
    "sg:province":"VIC",
    "sg:tags":[
        "provider",
        "internet"
    ],
    "wof:name":"The Lad Website Services Pty Ltd",
    "wof:placetype":"venue"
},
  "geometry": {"coordinates":[145.09231567399999,-37.6901779175],"type":"Point"}
}