{
  "type": "Feature",
  "properties": {
    "iso:country":"AU",
    "sg:address":"66 Winbourne Rd",
    "sg:city":"Brookvale",
    "sg:classifiers":[
        {
            "category":"Home & Garden",
            "subcategory":"Hardware",
            "type":"Retail Goods"
        }
    ],
    "sg:phone":"+61 2 8456 1117",
    "sg:postcode":"2100",
    "sg:province":"NSW",
    "sg:tags":[
        "plumber",
        "supply"
    ],
    "sg:website":"http://www.hg.com.au",
    "wof:name":"Hardware & General",
    "wof:placetype":"venue"
},
  "geometry": {"coordinates":[151.27403259299999,-33.7620658875],"type":"Point"}
}