{
  "type": "Feature",
  "properties": {
    "addr:full":"Shop 110 Newmarket Rd Windsor QLD 4030",
    "addr:housenumber":"110",
    "addr:postcode":"4030",
    "addr:street":"Newmarket Rd",
    "iso:country":"AU",
    "sg:address":"Shop 110 Newmarket Rd",
    "sg:city":"Windsor",
    "sg:classifiers":[
        {
            "category":"Cafe",
            "type":"Food & Drink"
        }
    ],
    "sg:phone":"+61 7 3864 1107",
    "sg:postcode":"4030",
    "sg:province":"QLD",
    "wof:name":"Gloria Jean's Coffees",
    "wof:placetype":"venue"
},
  "geometry": {"coordinates":[153.02569600000001,-27.437433],"type":"Point"}
}