{
  "type": "Feature",
  "properties": {
    "iso:country":"AU",
    "sg:address":"161-165 Horton Cornmeal Parades",
    "sg:city":"Maroochydore",
    "sg:classifiers":[
        {
            "category":"Shopping",
            "subcategory":"Computers & Home Electronics",
            "type":"Retail Goods"
        }
    ],
    "sg:phone":"+61 7 5479 1800",
    "sg:postcode":"4558",
    "sg:province":"QLD",
    "sg:tags":[
        "equipment",
        "part",
        "electronic"
    ],
    "wof:name":"Dick Smith Electronics",
    "wof:placetype":"venue"
},
  "geometry": {"coordinates":[153.08999633799999,-26.6540470123],"type":"Point"}
}