{
  "type": "Feature",
  "properties": {
    "iso:country":"AU",
    "sg:address":"Unit 30/ 65 Marigold St",
    "sg:city":"Revesby",
    "sg:classifiers":[
        {
            "category":"Utilities",
            "subcategory":"Electric",
            "type":"Services"
        }
    ],
    "sg:phone":"+61 2 9772 4472",
    "sg:postcode":"2212",
    "sg:province":"NSW",
    "sg:tags":[
        "electrical",
        "contractor"
    ],
    "wof:name":"Norfolk Facilities Management",
    "wof:placetype":"venue"
},
  "geometry": {"coordinates":[150.999512,-33.94054],"type":"Point"}
}