{
  "type": "Feature",
  "properties": {
    "addr:full":"14 Archer St Chatswood NSW 2067",
    "addr:housenumber":"14",
    "addr:postcode":"2067",
    "addr:street":"Archer St",
    "iso:country":"AU",
    "sg:address":"14 Archer St",
    "sg:city":"Chatswood",
    "sg:classifiers":[
        {
            "category":"Building & Trades",
            "subcategory":"Construction",
            "type":"Services"
        }
    ],
    "sg:phone":"+61 414 461 131",
    "sg:postcode":"2067",
    "sg:province":"NSW",
    "sg:tags":[
        "contractor"
    ],
    "wof:name":"Ridemi Pty Ltd",
    "wof:placetype":"venue"
},
  "geometry": {"coordinates":[151.187423706,-33.8004493713],"type":"Point"}
}