{
  "type": "Feature",
  "properties": {
    "addr:full":"Mersey Rd Outer Harbor SA 5018",
    "addr:postcode":"5018",
    "addr:street":"Mersey Rd",
    "iso:country":"AU",
    "sg:address":"Mersey Rd",
    "sg:city":"Outer Harbor",
    "sg:classifiers":[
        {
            "category":"Real Estate",
            "subcategory":"Architect",
            "type":"Services"
        }
    ],
    "sg:phone":"+61 8 8348 7000",
    "sg:postcode":"5018",
    "sg:province":"SA",
    "sg:tags":[
        "builder",
        "repairer",
        "ship"
    ],
    "wof:name":"ASC Pty Ltd",
    "wof:placetype":"venue"
},
  "geometry": {"coordinates":[138.508010864,-34.7819213867],"type":"Point"}
}