{
  "type": "Feature",
  "properties": {
    "addr:full":"10B Paterson Rd Springwood NSW 2777",
    "addr:housenumber":"10b",
    "addr:postcode":"2777",
    "addr:street":"Paterson Rd",
    "iso:country":"AU",
    "sg:address":"10B Paterson Rd",
    "sg:city":"Springwood",
    "sg:classifiers":[
        {
            "category":"Professional",
            "subcategory":"Accounting & Tax Preparation",
            "type":"Services"
        }
    ],
    "sg:phone":"+61 2 4751 2269",
    "sg:postcode":"2777",
    "sg:province":"NSW",
    "sg:tags":[
        "accountant",
        "auditor"
    ],
    "wof:name":"Lambert Accounting Services",
    "wof:placetype":"venue"
},
  "geometry": {"coordinates":[150.58392334000001,-33.6911621094],"type":"Point"}
}