{
  "type": "Feature",
  "properties": {
    "addr:full":"1668 Burwood Hwy Belgrave VIC 3160",
    "addr:housenumber":"1668",
    "addr:postcode":"3160",
    "addr:street":"Burwood Hwy",
    "iso:country":"AU",
    "sg:address":"1668 Burwood Hwy",
    "sg:city":"Belgrave",
    "sg:classifiers":[
        {
            "category":"Shopping",
            "subcategory":"Clothing, Apparel, & Fashions",
            "type":"Retail Goods"
        }
    ],
    "sg:phone":"+61 3 9754 7634",
    "sg:postcode":"3160",
    "sg:province":"VIC",
    "sg:tags":[
        "boutique"
    ],
    "wof:name":"Darys Impressive Fashions",
    "wof:placetype":"venue"
},
  "geometry": {"coordinates":[145.35401916500001,-37.9097099304],"type":"Point"}
}