{
  "type": "Feature",
  "properties": {
    "addr:full":"Shop 76, McLeod St Cairns QLD 4870",
    "addr:housenumber":"shop 76",
    "addr:postcode":"4870",
    "addr:street":"Mcleod St",
    "iso:country":"AU",
    "sg:address":"Shop 76, McLeod St",
    "sg:city":"Cairns",
    "sg:classifiers":[
        {
            "category":"Health Services",
            "subcategory":"Optometrist",
            "type":"Services"
        }
    ],
    "sg:phone":"+61 7 4051 7776",
    "sg:postcode":"4870",
    "sg:province":"QLD",
    "wof:name":"Toby Dale",
    "wof:placetype":"venue"
},
  "geometry": {"coordinates":[145.77085876500001,-16.9220676422],"type":"Point"}
}