{
  "type": "Feature",
  "properties": {
    "addr:full":"188 Main St Osborne Park WA 6017",
    "addr:housenumber":"188",
    "addr:postcode":"6017",
    "addr:street":"Main St",
    "iso:country":"AU",
    "sg:address":"188 Main St",
    "sg:city":"Osborne Park",
    "sg:classifiers":[
        {
            "category":"Health Services",
            "subcategory":"Health Practitioner",
            "type":"Services"
        }
    ],
    "sg:phone":"+61 8 9344 6877",
    "sg:postcode":"6017",
    "sg:province":"WA",
    "sg:tags":[
        "physiotherapist"
    ],
    "wof:name":"Northern Districts Physiotherapy Centre",
    "wof:placetype":"venue"
},
  "geometry": {"coordinates":[115.828422546,-31.898853302],"type":"Point"}
}