{
  "type": "Feature",
  "properties": {
    "addr:full":"222 Conadilly St Gunnedah NSW 2380",
    "addr:housenumber":"222",
    "addr:postcode":"2380",
    "addr:street":"Conadilly St",
    "iso:country":"AU",
    "sg:address":"222 Conadilly St",
    "sg:city":"Gunnedah",
    "sg:classifiers":[
        {
            "category":"Shopping",
            "subcategory":"Clothing, Apparel, & Fashions",
            "type":"Retail Goods"
        }
    ],
    "sg:phone":"+61 2 6742 0544",
    "sg:postcode":"2380",
    "sg:province":"NSW",
    "sg:tags":[
        "menswear"
    ],
    "wof:name":"Co-op Department Store",
    "wof:placetype":"venue"
},
  "geometry": {"coordinates":[150.25323486299999,-30.9773483276],"type":"Point"}
}