{
  "type": "Feature",
  "properties": {
    "addr:full":"12 Gough Crs Firle SA 5070",
    "addr:housenumber":"12",
    "addr:postcode":"5070",
    "addr:street":"Gough Crs",
    "iso:country":"AU",
    "sg:address":"12 Gough Crs",
    "sg:city":"Firle",
    "sg:classifiers":[
        {
            "category":"Real Estate",
            "subcategory":"Real Estate Agent",
            "type":"Services"
        }
    ],
    "sg:phone":"+61 8 8331 0054",
    "sg:postcode":"5070",
    "sg:province":"SA",
    "wof:name":"Pavia A",
    "wof:placetype":"venue"
},
  "geometry": {"coordinates":[138.652954102,-34.9039459229],"type":"Point"}
}