{
  "type": "Feature",
  "properties": {
    "addr:full":"PO Box 5473 Chittaway Bay NSW 2261",
    "addr:postcode":"2261",
    "iso:country":"AU",
    "sg:address":"PO Box 5473",
    "sg:city":"Chittaway Bay",
    "sg:classifiers":[
        {
            "category":"Shopping",
            "subcategory":"Clothing, Apparel, & Fashions",
            "type":"Retail Goods"
        }
    ],
    "sg:phone":"+61 404 221 530",
    "sg:postcode":"2261",
    "sg:province":"NSW",
    "sg:tags":[
        "textile",
        "designer"
    ],
    "wof:name":"Juliet In Stilettos",
    "wof:placetype":"venue"
},
  "geometry": {"coordinates":[151.496353,-33.358421],"type":"Point"}
}