{
  "type": "Feature",
  "properties": {
    "addr:full":"111e Midson Rd Epping NSW 2121",
    "addr:housenumber":"111e",
    "addr:postcode":"2121",
    "addr:street":"Midson Rd",
    "iso:country":"AU",
    "sg:address":"111e Midson Rd",
    "sg:city":"Epping",
    "sg:classifiers":[
        {
            "category":"Personal",
            "subcategory":"Massage",
            "type":"Services"
        }
    ],
    "sg:phone":"+61 2 9869 2111",
    "sg:postcode":"2121",
    "sg:province":"NSW",
    "sg:tags":[
        "therapy"
    ],
    "wof:name":"Face Body Wellness",
    "wof:placetype":"venue"
},
  "geometry": {"coordinates":[151.071655273,-33.77576828],"type":"Point"}
}