{
  "type": "Feature",
  "properties": {
    "addr:full":"82 Kintore Ave Adelaide SA 5000",
    "addr:housenumber":"82",
    "addr:postcode":"5000",
    "addr:street":"Kintore Ave",
    "iso:country":"AU",
    "sg:address":"82 Kintore Ave",
    "sg:city":"Adelaide",
    "sg:classifiers":[
        {
            "category":"Museum",
            "type":"Entertainment"
        }
    ],
    "sg:phone":"+61 8 8207 7580",
    "sg:postcode":"5000",
    "sg:province":"SA",
    "wof:name":"Migration Muesum",
    "wof:placetype":"venue"
},
  "geometry": {"coordinates":[138.601837158,-34.9206390381],"type":"Point"}
}