{
  "type": "Feature",
  "properties": {
    "iso:country":"AU",
    "sg:address":"27 Sandgate Rd",
    "sg:city":"Breakfast Creek",
    "sg:classifiers":[
        {
            "category":"Wholesale",
            "subcategory":"Painting Supplies",
            "type":"Manufacturing & Wholesale Goods"
        }
    ],
    "sg:phone":"+61 7 3262 8688",
    "sg:postcode":"4010",
    "sg:province":"QLD",
    "sg:tags":[
        "product",
        "cleaning"
    ],
    "wof:name":"Sheraton Alliance Pty Ltd",
    "wof:placetype":"venue"
},
  "geometry": {"coordinates":[153.04408264200001,-27.4400959015],"type":"Point"}
}