{
  "type": "Feature",
  "properties": {
    "iso:country":"AU",
    "sg:address":"Unit 2/ 34 Stanhope Gardns",
    "sg:city":"Midvale",
    "sg:classifiers":[
        {
            "category":"Landmark",
            "subcategory":"Scenic View",
            "type":"Public Place"
        }
    ],
    "sg:phone":"+61 8 9250 3097",
    "sg:postcode":"6056",
    "sg:province":"WA",
    "sg:tags":[
        "staircase",
        "handrail"
    ],
    "wof:name":"Midvale Joinery",
    "wof:placetype":"venue"
},
  "geometry": {"coordinates":[116.02683258099999,-31.8855209351],"type":"Point"}
}