{
  "type": "Feature",
  "properties": {
    "iso:country":"AU",
    "sg:address":"1/ 424 Balcombe Rd",
    "sg:city":"Beaumaris",
    "sg:classifiers":[
        {
            "category":"Real Estate",
            "subcategory":"Architect",
            "type":"Services"
        }
    ],
    "sg:phone":"+61 3 9589 5354",
    "sg:postcode":"3193",
    "sg:province":"VIC",
    "wof:name":"John H Van Dyk Pty Ltd",
    "wof:placetype":"venue"
},
  "geometry": {"coordinates":[145.03807067899999,-37.9780387878],"type":"Point"}
}