{
  "type": "Feature",
  "properties": {
    "addr:full":"22 Fullarton Rd Kent Town SA 5067",
    "addr:housenumber":"22",
    "addr:postcode":"5067",
    "addr:street":"Fullarton Rd",
    "iso:country":"AU",
    "sg:address":"22 Fullarton Rd",
    "sg:city":"Kent Town",
    "sg:classifiers":[
        {
            "category":"Wholesale",
            "subcategory":"Home Furnishings",
            "type":"Manufacturing & Wholesale Goods"
        }
    ],
    "sg:phone":"+61 1300 076 468",
    "sg:postcode":"5067",
    "sg:province":"SA",
    "sg:tags":[
        "terrazzo"
    ],
    "wof:name":"Best Point",
    "wof:placetype":"venue"
},
  "geometry": {"coordinates":[138.623291016,-34.9204216003],"type":"Point"}
}