{
  "type": "Feature",
  "properties": {
    "addr:full":"PO Box 8535 Mt Pleasant QLD 4740",
    "addr:postcode":"4740",
    "addr:street":"Pleasant",
    "iso:country":"AU",
    "sg:address":"PO Box 8535",
    "sg:city":"Mt Pleasant",
    "sg:classifiers":[
        {
            "category":"Building & Trades",
            "subcategory":"Landscaping Services",
            "type":"Services"
        }
    ],
    "sg:phone":"+61 412 666 375",
    "sg:postcode":"4740",
    "sg:province":"QLD",
    "sg:tags":[
        "gardener"
    ],
    "wof:name":"Brians Garden Care",
    "wof:placetype":"venue"
},
  "geometry": {"coordinates":[149.15718100000001,-21.11883],"type":"Point"}
}