{
  "type": "Feature",
  "properties": {
    "addr:full":"Shop 4/ 78 Glenhaven Rd Glenhaven NSW 2156",
    "addr:housenumber":"shop 4 / 78",
    "addr:postcode":"2156",
    "addr:street":"Glenhaven Rd",
    "iso:country":"AU",
    "sg:address":"Shop 4/ 78 Glenhaven Rd",
    "sg:city":"Glenhaven",
    "sg:classifiers":[
        {
            "category":"Deli",
            "type":"Food & Drink"
        }
    ],
    "sg:phone":"+61 2 9894 2522",
    "sg:postcode":"2156",
    "sg:province":"NSW",
    "sg:tags":[
        "delicatessen"
    ],
    "wof:name":"Olive Hill Gourmet Deli",
    "wof:placetype":"venue"
},
  "geometry": {"coordinates":[151.00140380900001,-33.6980209351],"type":"Point"}
}