{
  "type": "Feature",
  "properties": {
    "addr:full":"1/ 23 Karuah Ave Coffs Harbour NSW 2450",
    "addr:housenumber":"/ 23",
    "addr:postcode":"2450",
    "addr:street":"Karuah Ave",
    "iso:country":"AU",
    "sg:address":"1/ 23 Karuah Ave",
    "sg:city":"Coffs Harbour",
    "sg:classifiers":[
        {
            "category":"Personal",
            "subcategory":"Massage",
            "type":"Services"
        }
    ],
    "sg:phone":"+61 2 6651 9401",
    "sg:postcode":"2450",
    "sg:province":"NSW",
    "sg:tags":[
        "therapy"
    ],
    "wof:name":"Deborah Jones",
    "wof:placetype":"venue"
},
  "geometry": {"coordinates":[153.13494900000001,-30.279413],"type":"Point"}
}