{
  "type": "Feature",
  "properties": {
    "iso:country":"AU",
    "sg:address":"Wattle St",
    "sg:city":"Peakhurst",
    "sg:classifiers":[
        {
            "category":"Retail",
            "subcategory":"Auto Rental",
            "type":"Services"
        }
    ],
    "sg:phone":"+61 2 9534 5017",
    "sg:postcode":"2210",
    "sg:province":"NSW",
    "sg:tags":[
        "car",
        "wedding"
    ],
    "wof:name":"Corkys Hot Rod Hire",
    "wof:placetype":"venue"
},
  "geometry": {"coordinates":[151.070007,-33.962219],"type":"Point"}
}