{
  "type": "Feature",
  "properties": {
    "addr:full":"Unit 3/ 16 Kenworth Pl Brendale QLD 4500",
    "addr:housenumber":"16",
    "addr:postcode":"4500",
    "addr:street":"Kenworth Pl",
    "iso:country":"AU",
    "sg:address":"Unit 3/ 16 Kenworth Pl",
    "sg:city":"Brendale",
    "sg:classifiers":[
        {
            "category":"Autos & Motor Vehicles",
            "subcategory":"Boat Sales",
            "type":"Retail Goods"
        }
    ],
    "sg:phone":"+61 7 3889 9266",
    "sg:postcode":"4500",
    "sg:province":"QLD",
    "sg:tags":[
        "equipment",
        "yacht"
    ],
    "wof:name":"Brisbane Boat Trim",
    "wof:placetype":"venue"
},
  "geometry": {"coordinates":[152.988449097,-27.3249740601],"type":"Point"}
}