{
  "type": "Feature",
  "properties": {
    "addr:full":"11 Regent St Moorebank NSW 2170",
    "addr:housenumber":"11",
    "addr:postcode":"2170",
    "addr:street":"Regent St",
    "iso:country":"AU",
    "sg:address":"11 Regent St",
    "sg:city":"Moorebank",
    "sg:classifiers":[
        {
            "category":"Retail",
            "subcategory":"Auto Repair",
            "type":"Services"
        }
    ],
    "sg:phone":"+61 2 9600 6899",
    "sg:postcode":"2170",
    "sg:province":"NSW",
    "sg:tags":[
        "beater",
        "painter",
        "panel"
    ],
    "wof:name":"Sunshine Smash Repairs",
    "wof:placetype":"venue"
},
  "geometry": {"coordinates":[150.94015502900001,-33.9360198975],"type":"Point"}
}