{
  "type": "Feature",
  "properties": {
    "iso:country":"AU",
    "sg:address":"492 Parramatta Rd",
    "sg:city":"Leichhardt",
    "sg:classifiers":[
        {
            "category":"Manufacturing",
            "subcategory":"Furniture",
            "type":"Manufacturing & Wholesale Goods"
        }
    ],
    "sg:phone":"+61 2 9572 7515",
    "sg:postcode":"2040",
    "sg:province":"NSW",
    "sg:tags":[
        "builder",
        "designer",
        "custom"
    ],
    "wof:name":"Expressions By Design",
    "wof:placetype":"venue"
},
  "geometry": {"coordinates":[151.15748600000001,-33.888428],"type":"Point"}
}