{
  "type": "Feature",
  "properties": {
    "addr:full":"PO Box 704 Castle Hill NSW 2154",
    "addr:postcode":"2154",
    "iso:country":"AU",
    "sg:address":"PO Box 704",
    "sg:city":"Castle Hill",
    "sg:classifiers":[
        {
            "category":"Utilities",
            "subcategory":"Electric",
            "type":"Services"
        }
    ],
    "sg:phone":"+61 418 643 407",
    "sg:postcode":"2154",
    "sg:province":"NSW",
    "sg:tags":[
        "electrical",
        "contractor"
    ],
    "wof:name":"Castle Hill Refrigeration & Electrical Services",
    "wof:placetype":"venue"
},
  "geometry": {"coordinates":[151.003814697,-33.7317695618],"type":"Point"}
}