{
  "type": "Feature",
  "properties": {
    "addr:full":"PO Box 1090 Mt Barker SA 5251",
    "addr:postcode":"5251",
    "iso:country":"AU",
    "sg:address":"PO Box 1090",
    "sg:city":"Mt Barker",
    "sg:classifiers":[
        {
            "category":"Education",
            "subcategory":"School",
            "type":"Public Place"
        }
    ],
    "sg:phone":"+61 1800 061 487",
    "sg:postcode":"5251",
    "sg:province":"SA",
    "sg:tags":[
        "supply"
    ],
    "wof:name":"Spartan School Bags",
    "wof:placetype":"venue"
},
  "geometry": {"coordinates":[138.85289001500001,-35.0617103577],"type":"Point"}
}