{
  "type": "Feature",
  "properties": {
    "addr:full":"27 Seib St Kilcoy QLD 4515",
    "addr:housenumber":"27",
    "addr:postcode":"4515",
    "addr:street":"Seib St",
    "iso:country":"AU",
    "sg:address":"27 Seib St",
    "sg:city":"Kilcoy",
    "sg:classifiers":[
        {
            "category":"Retail",
            "subcategory":"Laundry & Dry Cleaning",
            "type":"Services"
        }
    ],
    "sg:phone":"+61 7 5497 1146",
    "sg:postcode":"4515",
    "sg:province":"QLD",
    "wof:name":"Kilcoy Laundry",
    "wof:placetype":"venue"
},
  "geometry": {"coordinates":[152.567047,-26.943377],"type":"Point"}
}