{
  "type": "Feature",
  "properties": {
    "addr:full":"11 Edward St Kingaroy QLD 4610",
    "addr:housenumber":"11",
    "addr:postcode":"4610",
    "addr:street":"Edward St",
    "iso:country":"AU",
    "sg:address":"11 Edward St",
    "sg:city":"Kingaroy",
    "sg:classifiers":[
        {
            "category":"Health Services",
            "subcategory":"Doctor",
            "type":"Services"
        }
    ],
    "sg:phone":"+61 7 4162 1903",
    "sg:postcode":"4610",
    "sg:province":"QLD",
    "sg:tags":[
        "medical",
        "practitioner"
    ],
    "wof:name":"&#039;Eduardstrete&#039; Family Medical Centre",
    "wof:placetype":"venue"
},
  "geometry": {"coordinates":[151.840530395,-26.5377426147],"type":"Point"}
}