{
  "type": "Feature",
  "properties": {
    "iso:country":"AU",
    "sg:address":"23 Walker St",
    "sg:city":"Baradine",
    "sg:classifiers":[
        {
            "category":"Commercial Area",
            "type":"Public Place"
        }
    ],
    "sg:phone":"+61 2 6843 1211",
    "sg:postcode":"2396",
    "sg:province":"NSW",
    "sg:tags":[
        "heavy",
        "carrier"
    ],
    "wof:name":"Hyde Haulage Pty Ltd",
    "wof:placetype":"venue"
},
  "geometry": {"coordinates":[149.06275939899999,-30.9522800446],"type":"Point"}
}