{
  "type": "Feature",
  "properties": {
    "addr:full":"12 Hancock St Sandgate QLD 4017",
    "addr:housenumber":"12",
    "addr:postcode":"4017",
    "addr:street":"Hancock St",
    "iso:country":"AU",
    "sg:address":"12 Hancock St",
    "sg:city":"Sandgate",
    "sg:classifiers":[
        {
            "category":"Manufacturing",
            "subcategory":"Motor Vehicles & Parts",
            "type":"Manufacturing & Wholesale Goods"
        }
    ],
    "sg:phone":"+61 7 3269 3206",
    "sg:postcode":"4017",
    "sg:province":"QLD",
    "sg:tags":[
        "replacement"
    ],
    "wof:name":"Jeays Aussie Auto",
    "wof:placetype":"venue"
},
  "geometry": {"coordinates":[153.0677948,-27.3203411102],"type":"Point"}
}