{
  "type": "Feature",
  "properties": {
    "addr:full":"20 Walter St Moorabbin VIC 3189",
    "addr:housenumber":"20",
    "addr:postcode":"3189",
    "addr:street":"Walter St",
    "iso:country":"AU",
    "sg:address":"20 Walter St",
    "sg:city":"Moorabbin",
    "sg:classifiers":[
        {
            "category":"Retail",
            "subcategory":"Auto Repair",
            "type":"Services"
        }
    ],
    "sg:phone":"+61 3 9555 4635",
    "sg:postcode":"3189",
    "sg:province":"VIC",
    "sg:tags":[
        "beater",
        "painter",
        "panel"
    ],
    "wof:name":"V R Auto Repairs",
    "wof:placetype":"venue"
},
  "geometry": {"coordinates":[145.06523132300001,-37.9400558472],"type":"Point"}
}