{
  "type": "Feature",
  "properties": {
    "iso:country":"AU",
    "sg:address":"Level 2 101 Edward St",
    "sg:city":"Brisbane",
    "sg:classifiers":[
        {
            "category":"Personal",
            "subcategory":"Beauty Salon",
            "type":"Services"
        }
    ],
    "sg:phone":"+61 7 3229 7794",
    "sg:postcode":"4000",
    "sg:province":"QLD",
    "sg:tags":[
        "hairdresser"
    ],
    "wof:name":"Fadis Hair",
    "wof:placetype":"venue"
},
  "geometry": {"coordinates":[153.02899169899999,-27.470205307],"type":"Point"}
}