{
  "type": "Feature",
  "properties": {
    "addr:full":"Shop 69 Floreat Forum Shopping Centre, Floreat WA 6014",
    "addr:housenumber":"shop 69",
    "addr:postcode":"6014",
    "iso:country":"AU",
    "sg:address":"Shop 69",
    "sg:city":"Floreat Forum Shopping Centre, Floreat",
    "sg:classifiers":[
        {
            "category":"Shopping",
            "subcategory":"Clothing, Apparel, & Fashions",
            "type":"Retail Goods"
        }
    ],
    "sg:phone":"+61 8 9284 1288",
    "sg:postcode":"6014",
    "sg:province":"WA",
    "sg:tags":[
        "lady",
        "wear"
    ],
    "wof:name":"Flower Clothing",
    "wof:placetype":"venue"
},
  "geometry": {"coordinates":[115.792808533,-31.940164566],"type":"Point"}
}