{
  "type": "Feature",
  "properties": {
    "addr:full":"44 Adele Ave Ferntree Gully VIC 3156",
    "addr:housenumber":"44",
    "addr:postcode":"3156",
    "addr:street":"Adele Ave",
    "iso:country":"AU",
    "sg:address":"44 Adele Ave",
    "sg:city":"Ferntree Gully",
    "sg:classifiers":[
        {
            "category":"Industrial Area",
            "type":"Public Place"
        }
    ],
    "sg:phone":"+61 419 535 678",
    "sg:postcode":"3156",
    "sg:province":"VIC",
    "sg:tags":[
        "floor"
    ],
    "wof:name":"T.P.M.M.",
    "wof:placetype":"venue"
},
  "geometry": {"coordinates":[145.26966857900001,-37.8853569031],"type":"Point"}
}