{
  "type": "Feature",
  "properties": {
    "addr:full":"Rocky Point Rd Woongoolba QLD 4207",
    "addr:postcode":"4207",
    "addr:street":"Rocky;Rd",
    "iso:country":"AU",
    "sg:address":"Rocky Point Rd",
    "sg:city":"Woongoolba",
    "sg:classifiers":[
        {
            "category":"Food & Beverages",
            "subcategory":"Meat & Fish",
            "type":"Retail Goods"
        }
    ],
    "sg:phone":"+61 7 5546 2202",
    "sg:postcode":"4207",
    "sg:province":"QLD",
    "sg:tags":[
        "aquaculture"
    ],
    "wof:name":"Rocky Point Hatchery",
    "wof:placetype":"venue"
},
  "geometry": {"coordinates":[153.33943176299999,-27.7231216431],"type":"Point"}
}