{
  "type": "Feature",
  "properties": {
    "addr:full":"132 Simpson Rd Currumbin Waters QLD 4223",
    "addr:housenumber":"132",
    "addr:postcode":"4223",
    "addr:street":"Simpson Rd",
    "iso:country":"AU",
    "sg:address":"132 Simpson Rd",
    "sg:city":"Currumbin Waters",
    "sg:classifiers":[
        {
            "category":"Building & Trades",
            "subcategory":"Pest Control",
            "type":"Services"
        }
    ],
    "sg:phone":"+61 1300 769 369",
    "sg:postcode":"4223",
    "sg:province":"QLD",
    "wof:name":"Watsons Pest And Weed Control",
    "wof:placetype":"venue"
},
  "geometry": {"coordinates":[153.45021057100001,-28.1491317749],"type":"Point"}
}