{
  "type": "Feature",
  "properties": {
    "iso:country":"AU",
    "sg:address":"20 Levey St",
    "sg:city":"Arncliffe",
    "sg:classifiers":[
        {
            "category":"Sports & Exercise",
            "subcategory":"Sports Center",
            "type":"Entertainment"
        }
    ],
    "sg:phone":"+61 2 9556 2355",
    "sg:postcode":"2205",
    "sg:province":"NSW",
    "sg:tags":[
        "coach",
        "tennis"
    ],
    "wof:name":"Racquet Sports International",
    "wof:placetype":"venue"
},
  "geometry": {"coordinates":[151.157196,-33.933746],"type":"Point"}
}