{
  "type": "Feature",
  "properties": {
    "iso:country":"AU",
    "sg:address":"40 Table St",
    "sg:city":"Port Macquarie",
    "sg:classifiers":[
        {
            "category":"Health Services",
            "subcategory":"Health Practitioner",
            "type":"Services"
        }
    ],
    "sg:phone":"+61 2 6584 4554",
    "sg:postcode":"2444",
    "sg:province":"NSW",
    "sg:tags":[
        "pathologist",
        "speech"
    ],
    "wof:name":"Karen Stevens",
    "wof:placetype":"venue"
},
  "geometry": {"coordinates":[152.900284,-31.437346],"type":"Point"}
}