{
  "type": "Feature",
  "properties": {
    "iso:country":"AU",
    "sg:address":"PO Box 659",
    "sg:city":"Kwinana",
    "sg:classifiers":[
        {
            "category":"Home & Garden",
            "subcategory":"Building Materials",
            "type":"Retail Goods"
        }
    ],
    "sg:phone":"+61 407 194 835",
    "sg:postcode":"6966",
    "sg:province":"WA",
    "sg:tags":[
        "lawn",
        "cutting",
        "maintenance"
    ],
    "wof:name":"Belmont Lawns & Gardens",
    "wof:placetype":"venue"
},
  "geometry": {"coordinates":[115.81345399999999,-32.247662],"type":"Point"}
}