{
  "type": "Feature",
  "properties": {
    "iso:country":"AU",
    "sg:address":"31 Bonaparte St",
    "sg:city":"Riverwood",
    "sg:classifiers":[
        {
            "category":"Manufacturing",
            "subcategory":"Paper Products",
            "type":"Manufacturing & Wholesale Goods"
        }
    ],
    "sg:phone":"+61 2 9584 9938",
    "sg:postcode":"2210",
    "sg:province":"NSW",
    "sg:tags":[
        "disposable"
    ],
    "wof:name":"Lets Be Clean",
    "wof:placetype":"venue"
},
  "geometry": {"coordinates":[151.057556,-33.947025],"type":"Point"}
}