{
  "type": "Feature",
  "properties": {
    "iso:country":"AU",
    "sg:address":"5 Karen St",
    "sg:city":"Warrnambool",
    "sg:classifiers":[
        {
            "category":"Social Services",
            "type":"Services"
        }
    ],
    "sg:phone":"+61 3 5561 2020",
    "sg:postcode":"3280",
    "sg:province":"VIC",
    "sg:tags":[
        "disabled",
        "person",
        "equipment"
    ],
    "wof:name":"Access Alterations",
    "wof:placetype":"venue"
},
  "geometry": {"coordinates":[142.51832580600001,-38.3786087036],"type":"Point"}
}