{
  "type": "Feature",
  "properties": {
    "addr:full":"84 Charles St Kew VIC 3101",
    "addr:housenumber":"84",
    "addr:postcode":"3101",
    "addr:street":"Charles St",
    "iso:country":"AU",
    "sg:address":"84 Charles St",
    "sg:city":"Kew",
    "sg:classifiers":[
        {
            "category":"Education",
            "subcategory":"School",
            "type":"Public Place"
        }
    ],
    "sg:phone":"+61 3 9853 3911",
    "sg:postcode":"3101",
    "sg:province":"VIC",
    "sg:tags":[
        "co-educational"
    ],
    "wof:name":"Andale School",
    "wof:placetype":"venue"
},
  "geometry": {"coordinates":[145.03590393100001,-37.8055915833],"type":"Point"}
}