{
  "type": "Feature",
  "properties": {
    "addr:full":"1209 River Way Drv Rasmussen QLD 4815",
    "addr:housenumber":"1209",
    "addr:postcode":"4815",
    "addr:street":"River Way Drv",
    "iso:country":"AU",
    "sg:address":"1209 River Way Drv",
    "sg:city":"Rasmussen",
    "sg:classifiers":[
        {
            "category":"Travel",
            "subcategory":"Hotels & Motels",
            "type":"Entertainment"
        }
    ],
    "sg:phone":"+61 7 4774 0377",
    "sg:postcode":"4815",
    "sg:province":"QLD",
    "sg:tags":[
        "pub"
    ],
    "wof:name":"Upper Ross Hotel",
    "wof:placetype":"venue"
},
  "geometry": {"coordinates":[146.728714,-19.345501],"type":"Point"}
}