{
  "type": "Feature",
  "properties": {
    "addr:full":"47 Yass Rd Queanbeyan ACT 2620",
    "addr:housenumber":"47",
    "addr:postcode":"2620",
    "addr:street":"Yass Rd",
    "iso:country":"AU",
    "sg:address":"47 Yass Rd",
    "sg:city":"Queanbeyan",
    "sg:classifiers":[
        {
            "category":"Manufacturing",
            "subcategory":"Furniture",
            "type":"Manufacturing & Wholesale Goods"
        }
    ],
    "sg:phone":"+61 412 995 446",
    "sg:postcode":"2620",
    "sg:province":"ACT",
    "sg:tags":[
        "builder",
        "designer",
        "custom"
    ],
    "wof:name":"Braithwaite Innovative Joinery",
    "wof:placetype":"venue"
},
  "geometry": {"coordinates":[149.24313354500001,-35.3397903442],"type":"Point"}
}