{
  "type": "Feature",
  "properties": {
    "addr:full":"Henry St Mansfield Park SA 5012",
    "addr:postcode":"5012",
    "addr:street":"Henry St",
    "iso:country":"AU",
    "sg:address":"Henry St",
    "sg:city":"Mansfield Park",
    "sg:classifiers":[
        {
            "category":"Education",
            "subcategory":"School",
            "type":"Public Place"
        }
    ],
    "sg:phone":"+61 8 8445 1594",
    "sg:postcode":"5012",
    "sg:province":"SA",
    "sg:tags":[
        "state",
        "except",
        "nsw"
    ],
    "wof:name":"Mansfield Park Primary",
    "wof:placetype":"venue"
},
  "geometry": {"coordinates":[138.554199219,-34.8534393311],"type":"Point"}
}