{
  "type": "Feature",
  "properties": {
    "addr:full":"94 Hoddle St Abbotsford VIC 3067",
    "addr:housenumber":"94",
    "addr:postcode":"3067",
    "addr:street":"Hoddle St",
    "iso:country":"AU",
    "sg:address":"94 Hoddle St",
    "sg:city":"Abbotsford",
    "sg:classifiers":[
        {
            "category":"Professional",
            "type":"Services"
        }
    ],
    "sg:phone":"+61 3 9419 3333",
    "sg:postcode":"3067",
    "sg:province":"VIC",
    "sg:tags":[
        "shop",
        "fitting"
    ],
    "wof:name":"Restaurant & Bar Solutions",
    "wof:placetype":"venue"
},
  "geometry": {"coordinates":[144.99229431099999,-37.8056373596],"type":"Point"}
}