{
  "type": "Feature",
  "properties": {
    "addr:full":"35 Boundary Rd North Melbourne VIC 3051",
    "addr:housenumber":"35",
    "addr:postcode":"3051",
    "addr:street":"Boundary Rd",
    "iso:country":"AU",
    "sg:address":"35 Boundary Rd",
    "sg:city":"North Melbourne",
    "sg:classifiers":[
        {
            "category":"Manufacturing",
            "subcategory":"Rubber & Plastics",
            "type":"Manufacturing & Wholesale Goods"
        }
    ],
    "sg:phone":"+61 3 9269 6521",
    "sg:postcode":"3051",
    "sg:province":"VIC",
    "sg:tags":[
        "wholesaler",
        "product",
        "mfrs"
    ],
    "wof:name":"Alternative Plastics",
    "wof:placetype":"venue"
},
  "geometry": {"coordinates":[144.93885803200001,-37.7946243286],"type":"Point"}
}