{
  "type": "Feature",
  "properties": {
    "addr:full":"84 Ivy St Kingaroy QLD 4610",
    "addr:housenumber":"84",
    "addr:postcode":"4610",
    "addr:street":"Ivy St",
    "iso:country":"AU",
    "sg:address":"84 Ivy St",
    "sg:city":"Kingaroy",
    "sg:classifiers":[
        {
            "category":"Education",
            "subcategory":"School",
            "type":"Public Place"
        }
    ],
    "sg:phone":"+61 7 4162 3988",
    "sg:postcode":"4610",
    "sg:province":"QLD",
    "sg:tags":[
        "co-educational"
    ],
    "wof:name":"St.John's Lutheran School",
    "wof:placetype":"venue"
},
  "geometry": {"coordinates":[151.85559082,-26.5376529694],"type":"Point"}
}