{
  "type": "Feature",
  "properties": {
    "addr:full":"Community Centre O'Hagan St Gundagai NSW 2722",
    "addr:postcode":"2722",
    "addr:street":"O'Hagan St",
    "iso:country":"AU",
    "sg:address":"Community Centre O'Hagan St",
    "sg:city":"Gundagai",
    "sg:classifiers":[
        {
            "category":"Organizations",
            "subcategory":"Community Association",
            "type":"Services"
        }
    ],
    "sg:phone":"+61 2 6944 3666",
    "sg:postcode":"2722",
    "sg:province":"NSW",
    "sg:tags":[
        "organisation",
        "family",
        "welfare"
    ],
    "wof:name":"Home Care Service Of NSW",
    "wof:placetype":"venue"
},
  "geometry": {"coordinates":[148.104355,-35.051159],"type":"Point"}
}