{
  "type": "Feature",
  "properties": {
    "addr:full":"Proper Bay Rd Port Lincoln SA 5606",
    "addr:postcode":"5606",
    "addr:street":"Proper Bay Rd",
    "iso:country":"AU",
    "sg:address":"Proper Bay Rd",
    "sg:city":"Port Lincoln",
    "sg:classifiers":[
        {
            "category":"Wholesale",
            "subcategory":"Seafood",
            "type":"Manufacturing & Wholesale Goods"
        }
    ],
    "sg:phone":"+61 8 8682 4124",
    "sg:postcode":"5606",
    "sg:province":"SA",
    "sg:tags":[
        "fish"
    ],
    "wof:name":"Valente Trawling",
    "wof:placetype":"venue"
},
  "geometry": {"coordinates":[135.85081500000001,-34.742771],"type":"Point"}
}