{
  "type": "Feature",
  "properties": {
    "iso:country":"AU",
    "sg:address":"123 Cranbourne Rd",
    "sg:city":"Langwarrin",
    "sg:classifiers":[
        {
            "category":"Health Services",
            "subcategory":"Dentist",
            "type":"Services"
        }
    ],
    "sg:phone":"+61 3 9775 5155",
    "sg:postcode":"3910",
    "sg:province":"VIC",
    "wof:name":"Nguyen Cindy Dr",
    "wof:placetype":"venue"
},
  "geometry": {"coordinates":[145.185623169,-38.1535110474],"type":"Point"}
}