{
  "type": "Feature",
  "properties": {
    "iso:country":"AU",
    "sg:address":"357 Clarendon St",
    "sg:city":"South Melbourne",
    "sg:classifiers":[
        {
            "category":"Professional",
            "subcategory":"Accounting & Tax Preparation",
            "type":"Services"
        }
    ],
    "sg:phone":"+61 3 9699 5522",
    "sg:postcode":"3205",
    "sg:province":"VIC",
    "sg:tags":[
        "accountant",
        "auditor"
    ],
    "wof:name":"Sedger S O",
    "wof:placetype":"venue"
},
  "geometry": {"coordinates":[144.961929,-37.835594],"type":"Point"}
}