{
  "type": "Feature",
  "properties": {
    "addr:full":"410 - 412 Goodwood Rd Cumberland Park SA 5041",
    "addr:housenumber":"410 412",
    "addr:postcode":"5041",
    "addr:street":"Goodwood Rd",
    "iso:country":"AU",
    "sg:address":"410 - 412 Goodwood Rd",
    "sg:city":"Cumberland Park",
    "sg:classifiers":[
        {
            "category":"Shopping",
            "subcategory":"Antiques",
            "type":"Retail Goods"
        }
    ],
    "sg:phone":"+61 8 8274 1044",
    "sg:postcode":"5041",
    "sg:province":"SA",
    "sg:tags":[
        "restoration",
        "reproduction"
    ],
    "wof:name":"Con's Upholstery",
    "wof:placetype":"venue"
},
  "geometry": {"coordinates":[138.59097299999999,-34.970852],"type":"Point"}
}