{
  "type": "Feature",
  "properties": {
    "addr:full":"Cooltong Ave Renmark North SA 5341",
    "addr:postcode":"5341",
    "addr:street":"Cooltong Ave",
    "iso:country":"AU",
    "sg:address":"Cooltong Ave",
    "sg:city":"Renmark North",
    "sg:classifiers":[
        {
            "category":"Farming",
            "subcategory":"Berry Farm",
            "type":"Manufacturing & Wholesale Goods"
        }
    ],
    "sg:phone":"+61 8 8595 3066",
    "sg:postcode":"5341",
    "sg:province":"SA",
    "sg:tags":[
        "fruit",
        "grower"
    ],
    "wof:name":"Pope Ian Pty Ltd",
    "wof:placetype":"venue"
},
  "geometry": {"coordinates":[140.696655273,-34.1339111328],"type":"Point"}
}