{
  "type": "Feature",
  "properties": {
    "addr:full":"level 1/ 59 The Esplanade Cotton Tree QLD 4558",
    "addr:housenumber":"/ 59",
    "addr:postcode":"4558",
    "addr:street":"The Esplanade Cotton",
    "iso:country":"AU",
    "sg:address":"level 1/ 59 The Esplanade",
    "sg:city":"Cotton Tree",
    "sg:classifiers":[
        {
            "category":"Professional",
            "subcategory":"Accounting & Tax Preparation",
            "type":"Services"
        }
    ],
    "sg:phone":"+61 7 5443 4988",
    "sg:postcode":"4558",
    "sg:province":"QLD",
    "sg:tags":[
        "accountant",
        "auditor"
    ],
    "wof:name":"Accounting North",
    "wof:placetype":"venue"
},
  "geometry": {"coordinates":[153.09808349599999,-26.655216217],"type":"Point"}
}