{
  "type": "Feature",
  "properties": {
    "addr:full":"373 Terrigal Drv Erina NSW 2250",
    "addr:housenumber":"373",
    "addr:postcode":"2250",
    "addr:street":"Terrigal Drv",
    "iso:country":"AU",
    "sg:address":"373 Terrigal Drv",
    "sg:city":"Erina",
    "sg:classifiers":[
        {
            "category":"Health Services",
            "subcategory":"Chiropractor",
            "type":"Services"
        }
    ],
    "sg:phone":"+61 2 4365 2949",
    "sg:postcode":"2250",
    "sg:province":"NSW",
    "wof:name":"BalancePoint",
    "wof:placetype":"venue"
},
  "geometry": {"coordinates":[151.397384644,-33.4347801208],"type":"Point"}
}