{
  "type": "Feature",
  "properties": {
    "addr:full":"Level 2, 41 Currie St Adelaide SA 5000",
    "addr:housenumber":"41",
    "addr:postcode":"5000",
    "addr:street":"Currie St",
    "iso:country":"AU",
    "sg:address":"Level 2, 41 Currie St",
    "sg:city":"Adelaide",
    "sg:classifiers":[
        {
            "category":"Professional",
            "subcategory":"Employment Agencies",
            "type":"Services"
        }
    ],
    "sg:phone":"+61 1800 806 050",
    "sg:postcode":"5000",
    "sg:province":"SA",
    "sg:tags":[
        "hire",
        "labour",
        "contractor"
    ],
    "wof:name":"Westaff",
    "wof:placetype":"venue"
},
  "geometry": {"coordinates":[138.59779357900001,-34.9246749878],"type":"Point"}
}