{
  "type": "Feature",
  "properties": {
    "addr:full":"54 Pacific Hwy Tweed Heads NSW 2485",
    "addr:housenumber":"54",
    "addr:postcode":"2485",
    "addr:street":"Pacific Hwy",
    "iso:country":"AU",
    "sg:address":"54 Pacific Hwy",
    "sg:city":"Tweed Heads",
    "sg:classifiers":[
        {
            "category":"Shopping",
            "subcategory":"Clothing, Apparel, & Fashions",
            "type":"Retail Goods"
        }
    ],
    "sg:phone":"+61 7 5523 4941",
    "sg:postcode":"2485",
    "sg:province":"NSW",
    "sg:tags":[
        "lady",
        "wear"
    ],
    "wof:name":"Fashionrack",
    "wof:placetype":"venue"
},
  "geometry": {"coordinates":[153.548736572,-28.2218914032],"type":"Point"}
}