{
  "type": "Feature",
  "properties": {
    "addr:full":"Unit 6/91- 93 Old Pittwater Rd Brookvale NSW 2100",
    "addr:housenumber":"93",
    "addr:postcode":"2100",
    "addr:street":"Old Pittwater Rd",
    "iso:country":"AU",
    "sg:address":"Unit 6/91- 93 Old Pittwater Rd",
    "sg:city":"Brookvale",
    "sg:classifiers":[
        {
            "category":"Shopping",
            "subcategory":"Stationery & Office Supplies",
            "type":"Retail Goods"
        }
    ],
    "sg:phone":"+61 2 9907 3143",
    "sg:postcode":"2100",
    "sg:province":"NSW",
    "sg:tags":[
        "packaging",
        "material"
    ],
    "wof:name":"Box Shop",
    "wof:placetype":"venue"
},
  "geometry": {"coordinates":[151.26203918499999,-33.7651863098],"type":"Point"}
}