{
  "type": "Feature",
  "properties": {
    "addr:full":"64- 70 Harper St Molendinar QLD 4214",
    "addr:housenumber":"70",
    "addr:postcode":"4214",
    "addr:street":"Harper St",
    "iso:country":"AU",
    "sg:address":"64- 70 Harper St",
    "sg:city":"Molendinar",
    "sg:classifiers":[
        {
            "category":"Manufacturing",
            "subcategory":"Metals",
            "type":"Manufacturing & Wholesale Goods"
        }
    ],
    "sg:phone":"+61 7 5597 1188",
    "sg:postcode":"4214",
    "sg:province":"QLD",
    "sg:tags":[
        "steel",
        "fabricator",
        "mfrs"
    ],
    "wof:name":"All Plates",
    "wof:placetype":"venue"
},
  "geometry": {"coordinates":[153.358932495,-27.98487854],"type":"Point"}
}