{
  "type": "Feature",
  "properties": {
    "addr:full":"Unit 15/ 55- 57 Newton Rd Wetherill Park NSW 2164",
    "addr:housenumber":"/;57",
    "addr:postcode":"2164",
    "addr:street":"Newton Rd",
    "iso:country":"AU",
    "sg:address":"Unit 15/ 55- 57 Newton Rd",
    "sg:city":"Wetherill Park",
    "sg:classifiers":[
        {
            "category":"Building & Trades",
            "subcategory":"Equipment Rental",
            "type":"Services"
        }
    ],
    "sg:phone":"+61 2 9609 4653",
    "sg:postcode":"2164",
    "sg:province":"NSW",
    "sg:tags":[
        "platform",
        "hire",
        "work",
        "elevating"
    ],
    "wof:name":"Cobra Training Services",
    "wof:placetype":"venue"
},
  "geometry": {"coordinates":[150.89315795900001,-33.8459701538],"type":"Point"}
}