{
  "type": "Feature",
  "properties": {
    "addr:full":"1 Morialta Ave Norwood TAS 7250",
    "addr:housenumber":"1",
    "addr:postcode":"7250",
    "addr:street":"Morialta Ave",
    "iso:country":"AU",
    "sg:address":"1 Morialta Ave",
    "sg:city":"Norwood",
    "sg:classifiers":[
        {
            "category":"Building & Trades",
            "subcategory":"Construction",
            "type":"Services"
        }
    ],
    "sg:phone":"+61 3 6344 6853",
    "sg:postcode":"7250",
    "sg:province":"TAS",
    "sg:tags":[
        "contractor"
    ],
    "wof:name":"West M J & C A",
    "wof:placetype":"venue"
},
  "geometry": {"coordinates":[147.179855347,-41.4670181274],"type":"Point"}
}