{
  "type": "Feature",
  "properties": {
    "addr:full":"62a Walter Rd Bedford WA 6052",
    "addr:housenumber":"62a",
    "addr:postcode":"6052",
    "addr:street":"Walter Rd",
    "iso:country":"AU",
    "sg:address":"62a Walter Rd",
    "sg:city":"Bedford",
    "sg:classifiers":[
        {
            "category":"Retail",
            "subcategory":"Self-service Laundry",
            "type":"Services"
        }
    ],
    "sg:phone":"+61 8 9271 0081",
    "sg:postcode":"6052",
    "sg:province":"WA",
    "wof:name":"The Wash Tub",
    "wof:placetype":"venue"
},
  "geometry": {"coordinates":[115.88156890899999,-31.9076328278],"type":"Point"}
}