{
  "type": "Feature",
  "properties": {
    "addr:full":"32 Selwyn St Paddington NSW 2021",
    "addr:housenumber":"32",
    "addr:postcode":"2021",
    "addr:street":"Selwyn St",
    "iso:country":"AU",
    "sg:address":"32 Selwyn St",
    "sg:city":"Paddington",
    "sg:classifiers":[
        {
            "category":"Organizations",
            "subcategory":"Non-profit Organization",
            "type":"Services"
        }
    ],
    "sg:phone":"+61 2 9332 1361",
    "sg:postcode":"2021",
    "sg:province":"NSW",
    "sg:tags":[
        "support",
        "disability",
        "organisation"
    ],
    "wof:name":"Williams Syndrome (I.H.C.) Association",
    "wof:placetype":"venue"
},
  "geometry": {"coordinates":[151.219573975,-33.885345459],"type":"Point"}
}