{
  "type": "Feature",
  "properties": {
    "iso:country":"AU",
    "sg:address":"265a Sydney Rd",
    "sg:city":"Coburg",
    "sg:classifiers":[
        {
            "category":"Autos & Motor Vehicles",
            "subcategory":"Fuel & Gas Station",
            "type":"Retail Goods"
        }
    ],
    "sg:phone":"+61 3 9383 2022",
    "sg:postcode":"3058",
    "sg:province":"VIC",
    "wof:name":"Alpine Petroleum Pty Ltd",
    "wof:placetype":"venue"
},
  "geometry": {"coordinates":[144.96534729000001,-37.7475318909],"type":"Point"}
}