{
  "type": "Feature",
  "properties": {
    "addr:full":"(Rear) 106 Gray St Hamilton VIC 3300",
    "addr:housenumber":"106",
    "addr:postcode":"3300",
    "addr:street":"Gray St",
    "iso:country":"AU",
    "sg:address":"(Rear) 106 Gray St",
    "sg:city":"Hamilton",
    "sg:classifiers":[
        {
            "category":"Conference Center",
            "type":"Public Place"
        }
    ],
    "sg:phone":"+61 3 5571 9111",
    "sg:postcode":"3300",
    "sg:province":"VIC",
    "sg:tags":[
        "venue",
        "convention"
    ],
    "wof:name":"Gilly's Convention Centre",
    "wof:placetype":"venue"
},
  "geometry": {"coordinates":[142.023605347,-37.7437019348],"type":"Point"}
}