{
  "type": "Feature",
  "properties": {
    "addr:full":"58 Yarragon Rd Leongatha VIC 3953",
    "addr:housenumber":"58",
    "addr:postcode":"3953",
    "addr:street":"Yarragon Rd",
    "iso:country":"AU",
    "sg:address":"58 Yarragon Rd",
    "sg:city":"Leongatha",
    "sg:classifiers":[
        {
            "category":"Wholesale",
            "subcategory":"Farm Supplies",
            "type":"Manufacturing & Wholesale Goods"
        }
    ],
    "sg:phone":"+61 3 5662 3973",
    "sg:postcode":"3953",
    "sg:province":"VIC",
    "sg:tags":[
        "equipment"
    ],
    "wof:name":"Chapman Machinery Service Pty Ltd",
    "wof:placetype":"venue"
},
  "geometry": {"coordinates":[145.950775147,-38.4682388306],"type":"Point"}
}