{
  "type": "Feature",
  "properties": {
    "addr:full":"Unit 1 16 Palings Crt Nerang QLD 4211",
    "addr:housenumber":"16",
    "addr:postcode":"4211",
    "addr:street":"Palings Crt",
    "iso:country":"AU",
    "sg:address":"Unit 1 16 Palings Crt",
    "sg:city":"Nerang",
    "sg:classifiers":[
        {
            "category":"Manufacturing",
            "subcategory":"Tools & Machinery",
            "type":"Manufacturing & Wholesale Goods"
        }
    ],
    "sg:phone":"+61 7 5596 3411",
    "sg:postcode":"4211",
    "sg:province":"QLD",
    "sg:tags":[
        "toolmaker"
    ],
    "wof:name":"Precision Mould Service",
    "wof:placetype":"venue"
},
  "geometry": {"coordinates":[153.340942383,-27.9812717438],"type":"Point"}
}