{
  "type": "Feature",
  "properties": {
    "iso:country":"AU",
    "sg:address":"96 Sutton St",
    "sg:city":"Cootamundra",
    "sg:classifiers":[
        {
            "category":"Travel",
            "subcategory":"Hotels & Motels",
            "type":"Entertainment"
        }
    ],
    "sg:phone":"+61 2 6942 1833",
    "sg:postcode":"2590",
    "sg:province":"NSW",
    "wof:name":"Cootamundra Gardens Motor Inn",
    "wof:placetype":"venue"
},
  "geometry": {"coordinates":[148.02833557100001,-34.640209198],"type":"Point"}
}