{
  "type": "Feature",
  "properties": {
    "iso:country":"AU",
    "sg:address":"Shop 18 Rockingham City Shpng Cntr Read St",
    "sg:city":"Rockingham",
    "sg:classifiers":[
        {
            "category":"Sports & Exercise",
            "subcategory":"Sports Center",
            "type":"Entertainment"
        }
    ],
    "sg:phone":"+61 8 9529 1717",
    "sg:postcode":"6168",
    "sg:province":"WA",
    "sg:tags":[
        "card",
        "memorabilia"
    ],
    "wof:name":"Memorabilia Australia",
    "wof:placetype":"venue"
},
  "geometry": {"coordinates":[115.736557,-32.280621],"type":"Point"}
}