{
  "type": "Feature",
  "properties": {
    "addr:full":"Rise & Shine Rd Wagoora QLD 4798",
    "addr:postcode":"4798",
    "addr:street":"Rd",
    "iso:country":"AU",
    "sg:address":"Rise & Shine Rd",
    "sg:city":"Wagoora",
    "sg:classifiers":[
        {
            "category":"Farming",
            "subcategory":"Farm",
            "type":"Manufacturing & Wholesale Goods"
        }
    ],
    "sg:phone":"+61 7 4958 7706",
    "sg:postcode":"4798",
    "sg:province":"QLD",
    "sg:tags":[
        "farmer"
    ],
    "wof:name":"Wallace I",
    "wof:placetype":"venue"
},
  "geometry": {"coordinates":[148.70353698700001,-20.8507804871],"type":"Point"}
}