{
  "type": "Feature",
  "properties": {
    "iso:country":"AU",
    "sg:address":"Point Vernon Plaza Murphy St",
    "sg:city":"Point Vernon",
    "sg:classifiers":[
        {
            "category":"Personal",
            "subcategory":"Beauty Salon",
            "type":"Services"
        }
    ],
    "sg:phone":"+61 7 4124 1894",
    "sg:postcode":"4655",
    "sg:province":"QLD",
    "sg:tags":[
        "hairdresser"
    ],
    "wof:name":"Graphic Line Hair Design",
    "wof:placetype":"venue"
},
  "geometry": {"coordinates":[152.818405,-25.254396],"type":"Point"}
}