{
  "type": "Feature",
  "properties": {
    "addr:full":"1 Mount Gambier Rd Millicent SA 5280",
    "addr:housenumber":"1",
    "addr:postcode":"5280",
    "addr:street":"Mount Gambier Rd",
    "iso:country":"AU",
    "sg:address":"1 Mount Gambier Rd",
    "sg:city":"Millicent",
    "sg:classifiers":[
        {
            "category":"Communications",
            "subcategory":"News Services",
            "type":"Services"
        }
    ],
    "sg:phone":"+61 8 8733 3205",
    "sg:postcode":"5280",
    "sg:province":"SA",
    "sg:tags":[
        "information",
        "tourist",
        "attractions"
    ],
    "wof:name":"Millicent Visitor Information Centre",
    "wof:placetype":"venue"
},
  "geometry": {"coordinates":[140.371353,-37.612984],"type":"Point"}
}