{
  "type": "Feature",
  "properties": {
    "addr:full":"Shop 14 & 15 East Ballina Shopng Cntr, Links Ave East Ballina NSW 2478",
    "addr:housenumber":"shop 14 & 15",
    "addr:postcode":"2478",
    "addr:street":"Ave",
    "iso:country":"AU",
    "sg:address":"Shop 14 & 15 East Ballina Shopng Cntr, Links Ave",
    "sg:city":"East Ballina",
    "sg:classifiers":[
        {
            "category":"Food & Beverages",
            "subcategory":"Liquor & Beverages",
            "type":"Retail Goods"
        }
    ],
    "sg:phone":"+61 2 6686 9668",
    "sg:postcode":"2478",
    "sg:province":"NSW",
    "sg:tags":[
        "store"
    ],
    "wof:name":"East Ballina Boozatorium",
    "wof:placetype":"venue"
},
  "geometry": {"coordinates":[153.584838867,-28.8580570221],"type":"Point"}
}