{
  "type": "Feature",
  "properties": {
    "addr:full":"371 Hobart Rd Youngtown TAS 7249",
    "addr:housenumber":"371",
    "addr:postcode":"7249",
    "addr:street":"Hobart Rd",
    "iso:country":"AU",
    "sg:address":"371 Hobart Rd",
    "sg:city":"Youngtown",
    "sg:classifiers":[
        {
            "category":"Food & Beverages",
            "subcategory":"Supermarket",
            "type":"Retail Goods"
        }
    ],
    "sg:phone":"+61 3 6344 5202",
    "sg:postcode":"7249",
    "sg:province":"TAS",
    "sg:tags":[
        "grocery",
        "store"
    ],
    "wof:name":"Value Plus IGA Stores",
    "wof:placetype":"venue"
},
  "geometry": {"coordinates":[147.167892456,-41.4861030579],"type":"Point"}
}