{
  "type": "Feature",
  "properties": {
    "addr:full":"38 Jerling St Ulverstone West TAS 7315",
    "addr:housenumber":"38",
    "addr:postcode":"7315",
    "addr:street":"Jerling St",
    "iso:country":"AU",
    "sg:address":"38 Jerling St",
    "sg:city":"Ulverstone West",
    "sg:classifiers":[
        {
            "category":"Building & Trades",
            "subcategory":"Plumbing",
            "type":"Services"
        }
    ],
    "sg:phone":"+61 3 6425 3683",
    "sg:postcode":"7315",
    "sg:province":"TAS",
    "sg:tags":[
        "plumber",
        "gasfitters"
    ],
    "wof:name":"Australian Environmental Plumbing & Drainage",
    "wof:placetype":"venue"
},
  "geometry": {"coordinates":[146.14715576200001,-41.1438598633],"type":"Point"}
}