{
  "type": "Feature",
  "properties": {
    "iso:country":"AU",
    "sg:address":"Shp4/ 1594 Glenrowan-Myrtleford Rd",
    "sg:city":"Milawa",
    "sg:classifiers":[
        {
            "category":"Food & Beverages",
            "subcategory":"Groceries & Convenience Stores",
            "type":"Retail Goods"
        }
    ],
    "sg:phone":"+61 3 5727 3230",
    "sg:postcode":"3678",
    "sg:province":"VIC",
    "wof:name":"Milawa General Store",
    "wof:placetype":"venue"
},
  "geometry": {"coordinates":[146.43107605,-36.4493904114],"type":"Point"}
}