{
  "type": "Feature",
  "properties": {
    "addr:full":"13 Stirling St Thebarton SA 5031",
    "addr:housenumber":"13",
    "addr:postcode":"5031",
    "addr:street":"Stirling St",
    "iso:country":"AU",
    "sg:address":"13 Stirling St",
    "sg:city":"Thebarton",
    "sg:classifiers":[
        {
            "category":"Retail",
            "subcategory":"Auto Repair",
            "type":"Services"
        }
    ],
    "sg:phone":"+61 8 8234 5199",
    "sg:postcode":"5031",
    "sg:province":"SA",
    "sg:tags":[
        "transmission",
        "automotive",
        "car"
    ],
    "wof:name":"Norwood Automatics",
    "wof:placetype":"venue"
},
  "geometry": {"coordinates":[138.572357178,-34.9127311707],"type":"Point"}
}