{
  "type": "Feature",
  "properties": {
    "addr:full":"6 Norfolk La Ballajura WA 6066",
    "addr:housenumber":"6",
    "addr:postcode":"6066",
    "addr:street":"Norfolk La",
    "iso:country":"AU",
    "sg:address":"6 Norfolk La",
    "sg:city":"Ballajura",
    "sg:classifiers":[
        {
            "category":"Building & Trades",
            "subcategory":"Plumbing",
            "type":"Services"
        }
    ],
    "sg:phone":"+61 1300 888 094",
    "sg:postcode":"6066",
    "sg:province":"WA",
    "sg:tags":[
        "plumber",
        "gasfitters"
    ],
    "wof:name":"Plumbing Wizards",
    "wof:placetype":"venue"
},
  "geometry": {"coordinates":[115.81582641599999,-32.0366897583],"type":"Point"}
}