{
  "type": "Feature",
  "properties": {
    "addr:full":"1/ 774 Pacific Hwy Gordon ACT 2906",
    "addr:housenumber":"/ 774",
    "addr:postcode":"2906",
    "addr:street":"Pacific Hwy",
    "iso:country":"AU",
    "sg:address":"1/ 774 Pacific Hwy",
    "sg:city":"Gordon",
    "sg:classifiers":[
        {
            "category":"Health Services",
            "subcategory":"Health Practitioner",
            "type":"Services"
        }
    ],
    "sg:phone":"+61 2 9499 3222",
    "sg:postcode":"2906",
    "sg:province":"ACT",
    "sg:tags":[
        "herbalist"
    ],
    "wof:name":"Peak Achievement Centre Pty Ltd",
    "wof:placetype":"venue"
},
  "geometry": {"coordinates":[149.085449219,-35.4656295776],"type":"Point"}
}