{
  "type": "Feature",
  "properties": {
    "iso:country":"AU",
    "sg:address":"26 Lemana La",
    "sg:city":"Burleigh Heads",
    "sg:classifiers":[
        {
            "category":"Banks & Credit Unions",
            "subcategory":"Bank",
            "type":"Services"
        }
    ],
    "sg:phone":"+61 7 5535 5863",
    "sg:postcode":"4220",
    "sg:province":"QLD",
    "sg:tags":[
        "concrete",
        "reinforcement"
    ],
    "wof:name":"South Coast Steel Fixers Pty Ltd",
    "wof:placetype":"venue"
},
  "geometry": {"coordinates":[153.443634033,-28.0785007477],"type":"Point"}
}