{
  "type": "Feature",
  "properties": {
    "addr:full":"18 Rawlins St Southport QLD 4215",
    "addr:housenumber":"18",
    "addr:postcode":"4215",
    "addr:street":"Rawlins St",
    "iso:country":"AU",
    "sg:address":"18 Rawlins St",
    "sg:city":"Southport",
    "sg:classifiers":[
        {
            "category":"Shopping",
            "subcategory":"Stationery & Office Supplies",
            "type":"Retail Goods"
        }
    ],
    "sg:phone":"+61 1300 788 732",
    "sg:postcode":"4215",
    "sg:province":"QLD",
    "sg:tags":[
        "equipment",
        "facsimile"
    ],
    "wof:name":"Fix IT Fast",
    "wof:placetype":"venue"
},
  "geometry": {"coordinates":[153.41030883799999,-27.9664745331],"type":"Point"}
}