{
  "type": "Feature",
  "properties": {
    "addr:full":"PO Box 610 Armadale WA 6992",
    "addr:postcode":"6992",
    "iso:country":"AU",
    "sg:address":"PO Box 610",
    "sg:city":"Armadale",
    "sg:classifiers":[
        {
            "category":"Shopping",
            "subcategory":"Pets & Pet Supplies",
            "type":"Retail Goods"
        }
    ],
    "sg:phone":"+61 402 664 183",
    "sg:postcode":"6992",
    "sg:province":"WA",
    "sg:tags":[
        "food"
    ],
    "wof:name":"True Friends",
    "wof:placetype":"venue"
},
  "geometry": {"coordinates":[116.00827,-32.15239],"type":"Point"}
}