{
  "type": "Feature",
  "properties": {
    "addr:full":"273 Gower St Preston VIC 3072",
    "addr:housenumber":"273",
    "addr:postcode":"3072",
    "addr:street":"Gower St",
    "iso:country":"AU",
    "sg:address":"273 Gower St",
    "sg:city":"Preston",
    "sg:classifiers":[
        {
            "category":"Personal",
            "subcategory":"Beauty Salon",
            "type":"Services"
        }
    ],
    "sg:phone":"+61 3 9478 2059",
    "sg:postcode":"3072",
    "sg:province":"VIC",
    "sg:tags":[
        "hairdresser"
    ],
    "wof:name":"Rivex Hair Design",
    "wof:placetype":"venue"
},
  "geometry": {"coordinates":[145.00387573200001,-37.7405738831],"type":"Point"}
}