{
  "type": "Feature",
  "properties": {
    "addr:full":"Young Rd Broadmeadow NSW 2292",
    "addr:postcode":"2292",
    "addr:street":"Young Rd",
    "iso:country":"AU",
    "sg:address":"Young Rd",
    "sg:city":"Broadmeadow",
    "sg:classifiers":[
        {
            "category":"Arena",
            "subcategory":"Sports Club",
            "type":"Entertainment"
        }
    ],
    "sg:phone":"+61 2 4961 4493",
    "sg:postcode":"2292",
    "sg:province":"NSW",
    "sg:tags":[
        "defence",
        "supply",
        "self",
        "instruction",
        "martial art"
    ],
    "wof:name":"Aikido Kenkyu Kai Int",
    "wof:placetype":"venue"
},
  "geometry": {"coordinates":[151.732254028,-32.9222259521],"type":"Point"}
}