{
  "type": "Feature",
  "properties": {
    "addr:full":"392 Jones St Ultimo NSW 2007",
    "addr:housenumber":"392",
    "addr:postcode":"2007",
    "addr:street":"Jones St",
    "iso:country":"AU",
    "sg:address":"392 Jones St",
    "sg:city":"Ultimo",
    "sg:classifiers":[
        {
            "category":"Fast Food",
            "type":"Food & Drink"
        }
    ],
    "sg:phone":"+61 2 9518 8866",
    "sg:postcode":"2007",
    "sg:province":"NSW",
    "sg:tags":[
        "away",
        "take"
    ],
    "wof:name":"A Tad Ser Food",
    "wof:placetype":"venue"
},
  "geometry": {"coordinates":[151.196136475,-33.8771972656],"type":"Point"}
}