{
  "type": "Feature",
  "properties": {
    "addr:full":"14 Arnott St Hume ACT 2620",
    "addr:housenumber":"14",
    "addr:postcode":"2620",
    "addr:street":"Arnott St",
    "iso:country":"AU",
    "sg:address":"14 Arnott St",
    "sg:city":"Hume",
    "sg:classifiers":[
        {
            "category":"Home & Garden",
            "subcategory":"Garden Supply",
            "type":"Retail Goods"
        }
    ],
    "sg:phone":"+61 2 6260 1425",
    "sg:postcode":"2620",
    "sg:province":"ACT",
    "sg:tags":[
        "equipment",
        "greenhouses"
    ],
    "wof:name":"Garden World",
    "wof:placetype":"venue"
},
  "geometry": {"coordinates":[149.17454528799999,-35.3882331848],"type":"Point"}
}