{
  "type": "Feature",
  "properties": {
    "addr:full":"Merricks Rd Longford VIC 3851",
    "addr:postcode":"3851",
    "addr:street":"Merricks Rd",
    "iso:country":"AU",
    "sg:address":"Merricks Rd",
    "sg:city":"Longford",
    "sg:classifiers":[
        {
            "category":"Wholesale",
            "subcategory":"Plants",
            "type":"Manufacturing & Wholesale Goods"
        }
    ],
    "sg:phone":"+61 3 5149 7251",
    "sg:postcode":"3851",
    "sg:province":"VIC",
    "sg:tags":[
        "florist"
    ],
    "wof:name":"Australian Wildflower Co Pty Ltd",
    "wof:placetype":"venue"
},
  "geometry": {"coordinates":[147.133712769,-38.1848297119],"type":"Point"}
}