{
  "type": "Feature",
  "properties": {
    "addr:full":"Unit 57 93- 97 Newton Rd Wetherill Park NSW 2164",
    "addr:housenumber":"93 97",
    "addr:postcode":"2164",
    "addr:street":"Newton Rd",
    "iso:country":"AU",
    "sg:address":"Unit 57 93- 97 Newton Rd",
    "sg:city":"Wetherill Park",
    "sg:classifiers":[
        {
            "category":"Autos & Motor Vehicles",
            "subcategory":"Automobile Sales",
            "type":"Retail Goods"
        }
    ],
    "sg:phone":"+61 2 9725 2318",
    "sg:postcode":"2164",
    "sg:province":"NSW",
    "sg:tags":[
        "car",
        "new"
    ],
    "wof:name":"Bas Cars",
    "wof:placetype":"venue"
},
  "geometry": {"coordinates":[150.89210510300001,-33.8474006653],"type":"Point"}
}