{
  "type": "Feature",
  "properties": {
    "addr:full":"113 Canterbury Rd Canterbury NSW 2193",
    "addr:housenumber":"113",
    "addr:postcode":"2193",
    "addr:street":"Canterbury Rd",
    "iso:country":"AU",
    "sg:address":"113 Canterbury Rd",
    "sg:city":"Canterbury",
    "sg:classifiers":[
        {
            "category":"Health Services",
            "subcategory":"Health Practitioner",
            "type":"Services"
        }
    ],
    "sg:phone":"+61 2 9787 3821",
    "sg:postcode":"2193",
    "sg:province":"NSW",
    "sg:tags":[
        "physiotherapist"
    ],
    "wof:name":"Healy Elaine",
    "wof:placetype":"venue"
},
  "geometry": {"coordinates":[151.12136799999999,-33.910522],"type":"Point"}
}