{
  "type": "Feature",
  "properties": {
    "iso:country":"AU",
    "sg:address":"Stoneville Rd",
    "sg:city":"Stoneville",
    "sg:classifiers":[
        {
            "category":"Home & Garden",
            "subcategory":"Garden Supply",
            "type":"Retail Goods"
        }
    ],
    "sg:phone":"+61 8 9295 2010",
    "sg:postcode":"6081",
    "sg:province":"WA",
    "sg:tags":[
        "fertilizer"
    ],
    "wof:name":"Fertilizer King",
    "wof:placetype":"venue"
},
  "geometry": {"coordinates":[116.17056274399999,-31.8774166107],"type":"Point"}
}