{
  "type": "Feature",
  "properties": {
    "addr:full":"40 Zaara St Newcastle NSW 2300",
    "addr:housenumber":"40",
    "addr:postcode":"2300",
    "addr:street":"Zaara St",
    "iso:country":"AU",
    "sg:address":"40 Zaara St",
    "sg:city":"Newcastle",
    "sg:classifiers":[
        {
            "category":"Ice Cream",
            "type":"Food & Drink"
        }
    ],
    "sg:phone":"+61 2 4926 3400",
    "sg:postcode":"2300",
    "sg:province":"NSW",
    "sg:tags":[
        "retail"
    ],
    "wof:name":"Kiwi Waffle 'n Cones",
    "wof:placetype":"venue"
},
  "geometry": {"coordinates":[151.787766,-32.928253],"type":"Point"}
}