{
  "type": "Feature",
  "properties": {
    "addr:full":"Shop 1a/ 73 Gibson Ave Padbury WA 6025",
    "addr:housenumber":"shop 1a / 73",
    "addr:postcode":"6025",
    "addr:street":"Gibson Ave",
    "iso:country":"AU",
    "sg:address":"Shop 1a/ 73 Gibson Ave",
    "sg:city":"Padbury",
    "sg:classifiers":[
        {
            "category":"Personal",
            "subcategory":"Massage",
            "type":"Services"
        }
    ],
    "sg:phone":"+61 8 9402 5226",
    "sg:postcode":"6025",
    "sg:province":"WA",
    "sg:tags":[
        "therapy"
    ],
    "wof:name":"Helena Health & Skin Care Clinic",
    "wof:placetype":"venue"
},
  "geometry": {"coordinates":[115.768447876,-31.8106975555],"type":"Point"}
}