{
  "type": "Feature",
  "properties": {
    "addr:full":"Shop 16 Rapid Creek Shopping Complex Rapid Creek NT 0810",
    "addr:housenumber":"shop 16",
    "addr:postcode":"0810",
    "iso:country":"AU",
    "sg:address":"Shop 16 Rapid Creek Shopping Complex",
    "sg:city":"Rapid Creek",
    "sg:classifiers":[
        {
            "category":"Organizations",
            "subcategory":"Non-profit Organization",
            "type":"Services"
        }
    ],
    "sg:phone":"+61 8 8985 6222",
    "sg:postcode":"0810",
    "sg:province":"NT",
    "sg:tags":[
        "support",
        "disability",
        "organisation"
    ],
    "wof:name":"Down Syndrome Association",
    "wof:placetype":"venue"
},
  "geometry": {"coordinates":[130.86451721200001,-12.3855161667],"type":"Point"}
}