{
  "type": "Feature",
  "properties": {
    "addr:full":"220b Pennant Hills Rd Carlingford NSW 2118",
    "addr:housenumber":"220b",
    "addr:postcode":"2118",
    "addr:street":"Pennant Hills Rd",
    "iso:country":"AU",
    "sg:address":"220b Pennant Hills Rd",
    "sg:city":"Carlingford",
    "sg:classifiers":[
        {
            "category":"Health Services",
            "subcategory":"Chiropractor",
            "type":"Services"
        }
    ],
    "sg:phone":"+61 2 9614 1199",
    "sg:postcode":"2118",
    "sg:province":"NSW",
    "wof:name":"So Vincent C.K.",
    "wof:placetype":"venue"
},
  "geometry": {"coordinates":[151.047439575,-33.7640304565],"type":"Point"}
}