{
  "type": "Feature",
  "properties": {
    "iso:country":"AU",
    "sg:address":"Level 16/ 383 Kent St",
    "sg:city":"Sydney",
    "sg:classifiers":[
        {
            "category":"Insurance",
            "subcategory":"Insurance Agent",
            "type":"Services"
        }
    ],
    "sg:phone":"+61 2 9262 5555",
    "sg:postcode":"2000",
    "sg:province":"NSW",
    "sg:tags":[
        "broker"
    ],
    "wof:name":"Miller & Associates Insurance Broking Pty Ltd",
    "wof:placetype":"venue"
},
  "geometry": {"coordinates":[151.20457458499999,-33.8698959351],"type":"Point"}
}