{
  "type": "Feature",
  "properties": {
    "addr:full":"10 Tullamarine Park Rd Tullamarine VIC 3043",
    "addr:housenumber":"10",
    "addr:postcode":"3043",
    "addr:street":"Tullamarine Park Rd",
    "iso:country":"AU",
    "sg:address":"10 Tullamarine Park Rd",
    "sg:city":"Tullamarine",
    "sg:classifiers":[
        {
            "category":"Retail",
            "subcategory":"Auto Repair",
            "type":"Services"
        }
    ],
    "sg:phone":"+61 3 9338 0389",
    "sg:postcode":"3043",
    "sg:province":"VIC",
    "sg:tags":[
        "beater",
        "painter",
        "panel"
    ],
    "wof:name":"Five Star Panel Repairs",
    "wof:placetype":"venue"
},
  "geometry": {"coordinates":[144.861984253,-37.713558197],"type":"Point"}
}