{
  "type": "Feature",
  "properties": {
    "addr:full":"32 Marshall St Cobar NSW 2835",
    "addr:housenumber":"32",
    "addr:postcode":"2835",
    "addr:street":"Marshall St",
    "iso:country":"AU",
    "sg:address":"32 Marshall St",
    "sg:city":"Cobar",
    "sg:classifiers":[
        {
            "category":"Shopping",
            "subcategory":"Clothing, Apparel, & Fashions",
            "type":"Retail Goods"
        }
    ],
    "sg:phone":"+61 2 6836 2161",
    "sg:postcode":"2835",
    "sg:province":"NSW",
    "sg:tags":[
        "menswear"
    ],
    "wof:name":"Brilliams Menswear",
    "wof:placetype":"venue"
},
  "geometry": {"coordinates":[145.83943199999999,-31.497925],"type":"Point"}
}