{
  "type": "Feature",
  "properties": {
    "addr:full":"103 Buncle St North Melbourne VIC 3051",
    "addr:housenumber":"103",
    "addr:postcode":"3051",
    "addr:street":"Buncle St",
    "iso:country":"AU",
    "sg:address":"103 Buncle St",
    "sg:city":"North Melbourne",
    "sg:classifiers":[
        {
            "category":"Professional",
            "subcategory":"Research",
            "type":"Services"
        }
    ],
    "sg:phone":"+61 3 9326 9326",
    "sg:postcode":"3051",
    "sg:province":"VIC",
    "sg:tags":[
        "analyst"
    ],
    "wof:name":"Artcare Pigment Analysis",
    "wof:placetype":"venue"
},
  "geometry": {"coordinates":[144.94247436500001,-37.7901916504],"type":"Point"}
}