{
  "type": "Feature",
  "properties": {
    "iso:country":"AU",
    "sg:address":"471 Glenferrie Rd",
    "sg:city":"Kooyong",
    "sg:classifiers":[
        {
            "category":"Personal",
            "subcategory":"Beauty Salon",
            "type":"Services"
        }
    ],
    "sg:phone":"+61 3 9822 2723",
    "sg:postcode":"3144",
    "sg:province":"VIC",
    "wof:name":"Callisters Pharmacy",
    "wof:placetype":"venue"
},
  "geometry": {"coordinates":[145.031982422,-37.8403091431],"type":"Point"}
}