{
  "type": "Feature",
  "properties": {
    "iso:country":"AU",
    "sg:address":"PO Box 1041",
    "sg:city":"Kensington Gardens",
    "sg:classifiers":[
        {
            "category":"Shopping",
            "subcategory":"Clothing, Apparel, & Fashions",
            "type":"Retail Goods"
        }
    ],
    "sg:phone":"+61 415 914 020",
    "sg:postcode":"5068",
    "sg:province":"SA",
    "sg:tags":[
        "accessory"
    ],
    "wof:name":"Stellar Handbags",
    "wof:placetype":"venue"
},
  "geometry": {"coordinates":[138.664916992,-34.9197502136],"type":"Point"}
}