{
  "type": "Feature",
  "properties": {
    "iso:country":"AU",
    "sg:address":"16 & 95 Bridge St",
    "sg:city":"Bendigo",
    "sg:classifiers":[
        {
            "category":"Retail",
            "subcategory":"Auto Repair",
            "type":"Services"
        }
    ],
    "sg:phone":"+61 3 5442 6409",
    "sg:postcode":"3550",
    "sg:province":"VIC",
    "sg:tags":[
        "repairer",
        "motor",
        "engineer"
    ],
    "wof:name":"Engine Factory The",
    "wof:placetype":"venue"
},
  "geometry": {"coordinates":[144.28562927199999,-36.7499313354],"type":"Point"}
}