{
  "type": "Feature",
  "properties": {
    "iso:country":"AU",
    "sg:address":"14 Castle Hill Rd",
    "sg:city":"West Pennant Hills",
    "sg:classifiers":[
        {
            "category":"Real Estate",
            "subcategory":"Real Estate Agent",
            "type":"Services"
        }
    ],
    "sg:phone":"+61 2 9980 2555",
    "sg:postcode":"2125",
    "sg:province":"NSW",
    "wof:name":"Professionals West Pennant Hills",
    "wof:placetype":"venue"
},
  "geometry": {"coordinates":[151.026779175,-33.7327842712],"type":"Point"}
}