{
  "type": "Feature",
  "properties": {
    "addr:full":"336 Elizabeth St Surry Hills NSW 2010",
    "addr:housenumber":"336",
    "addr:postcode":"2010",
    "addr:street":"Elizabeth St",
    "iso:country":"AU",
    "sg:address":"336 Elizabeth St",
    "sg:city":"Surry Hills",
    "sg:classifiers":[
        {
            "category":"Health Services",
            "subcategory":"Doctor",
            "type":"Services"
        }
    ],
    "sg:phone":"+61 2 9211 3378",
    "sg:postcode":"2010",
    "sg:province":"NSW",
    "sg:tags":[
        "medical",
        "practitioner"
    ],
    "wof:name":"Khoury Joseph",
    "wof:placetype":"venue"
},
  "geometry": {"coordinates":[151.20831298799999,-33.8845062256],"type":"Point"}
}