{
  "type": "Feature",
  "properties": {
    "addr:full":"15 Delmar Pde Gladesville NSW 2111",
    "addr:housenumber":"15",
    "addr:postcode":"2111",
    "addr:street":"Delmar Pde",
    "iso:country":"AU",
    "sg:address":"15 Delmar Pde",
    "sg:city":"Gladesville",
    "sg:classifiers":[
        {
            "category":"Professional",
            "subcategory":"Computer Services",
            "type":"Services"
        }
    ],
    "sg:phone":"+61 2 9817 0503",
    "sg:postcode":"2111",
    "sg:province":"NSW",
    "sg:tags":[
        "package",
        "software"
    ],
    "wof:name":"A.B.M. Systems",
    "wof:placetype":"venue"
},
  "geometry": {"coordinates":[151.12022399899999,-33.8377761841],"type":"Point"}
}