{
  "type": "Feature",
  "properties": {
    "addr:full":"5 Brougham St Magill SA 5072",
    "addr:housenumber":"5",
    "addr:postcode":"5072",
    "addr:street":"Brougham St",
    "iso:country":"AU",
    "sg:address":"5 Brougham St",
    "sg:city":"Magill",
    "sg:classifiers":[
        {
            "category":"Real Estate",
            "subcategory":"Surveying",
            "type":"Services"
        }
    ],
    "sg:phone":"+61 8 8431 7750",
    "sg:postcode":"5072",
    "sg:province":"SA",
    "sg:tags":[
        "map",
        "mapping"
    ],
    "wof:name":"FLAT EARTH MAPPING",
    "wof:placetype":"venue"
},
  "geometry": {"coordinates":[138.672073364,-34.9119873047],"type":"Point"}
}