{
  "type": "Feature",
  "properties": {
    "addr:full":"Stanley Rd Beechworth VIC 3747",
    "addr:postcode":"3747",
    "addr:street":"Stanley Rd",
    "iso:country":"AU",
    "sg:address":"Stanley Rd",
    "sg:city":"Beechworth",
    "sg:classifiers":[
        {
            "category":"Farming",
            "subcategory":"Orchard",
            "type":"Manufacturing & Wholesale Goods"
        }
    ],
    "sg:phone":"+61 3 5728 6538",
    "sg:postcode":"3747",
    "sg:province":"VIC",
    "sg:tags":[
        "pear",
        "apple",
        "grower"
    ],
    "wof:name":"Fartuszynski P",
    "wof:placetype":"venue"
},
  "geometry": {"coordinates":[146.69903600000001,-36.364353],"type":"Point"}
}