{
  "type": "Feature",
  "properties": {
    "addr:full":"40 Harry Mills Drv Worongary QLD 4213",
    "addr:housenumber":"40",
    "addr:postcode":"4213",
    "addr:street":"Harry Mills Drv",
    "iso:country":"AU",
    "sg:address":"40 Harry Mills Drv",
    "sg:city":"Worongary",
    "sg:classifiers":[
        {
            "category":"Home & Garden",
            "subcategory":"Carpets & Floor Coverings",
            "type":"Retail Goods"
        }
    ],
    "sg:phone":"+61 7 5530 2658",
    "sg:postcode":"4213",
    "sg:province":"QLD",
    "sg:tags":[
        "tile",
        "wall",
        "layer"
    ],
    "wof:name":"Bradshaw Peter J & D",
    "wof:placetype":"venue"
},
  "geometry": {"coordinates":[153.331573486,-28.0464248657],"type":"Point"}
}