{
  "type": "Feature",
  "properties": {
    "iso:country":"AU",
    "sg:address":"23 - 25a Johnston St",
    "sg:city":"Collingwood",
    "sg:classifiers":[
        {
            "category":"Shopping",
            "subcategory":"Computers & Home Electronics",
            "type":"Retail Goods"
        }
    ],
    "sg:phone":"+61 3 9417 7707",
    "sg:postcode":"3066",
    "sg:province":"VIC",
    "sg:tags":[
        "equipment",
        "multimedia"
    ],
    "wof:name":"Studio 52 Recordings",
    "wof:placetype":"venue"
},
  "geometry": {"coordinates":[144.985794067,-37.7992172241],"type":"Point"}
}