{
  "type": "Feature",
  "properties": {
    "addr:full":"Walla Ave Griffith NSW 2680",
    "addr:postcode":"2680",
    "addr:street":"Walla Ave",
    "iso:country":"AU",
    "sg:address":"Walla Ave",
    "sg:city":"Griffith",
    "sg:classifiers":[
        {
            "category":"Farming",
            "subcategory":"Farm",
            "type":"Manufacturing & Wholesale Goods"
        }
    ],
    "sg:phone":"+61 2 6962 3432",
    "sg:postcode":"2680",
    "sg:province":"NSW",
    "sg:tags":[
        "farmer"
    ],
    "wof:name":"Pilosio W T",
    "wof:placetype":"venue"
},
  "geometry": {"coordinates":[146.033737,-34.287777],"type":"Point"}
}