{
  "type": "Feature",
  "properties": {
    "addr:full":"Factory 4/ 262 Wolseley Pl Thomastown VIC 3074",
    "addr:housenumber":"/ 262",
    "addr:postcode":"3074",
    "addr:street":"Wolseley Pl",
    "iso:country":"AU",
    "sg:address":"Factory 4/ 262 Wolseley Pl",
    "sg:city":"Thomastown",
    "sg:classifiers":[
        {
            "category":"Government",
            "subcategory":"Fire Station",
            "type":"Public Place"
        }
    ],
    "sg:phone":"+61 3 9645 5267",
    "sg:postcode":"3074",
    "sg:province":"VIC",
    "sg:tags":[
        "fuel",
        "lamp",
        "burning"
    ],
    "wof:name":"The Oil Lamp Company P/L",
    "wof:placetype":"venue"
},
  "geometry": {"coordinates":[144.999465942,-37.6894798279],"type":"Point"}
}