{
  "type": "Feature",
  "properties": {
    "addr:full":"Piazza Court, Old Northern Rd Castle Hill NSW 2154",
    "addr:postcode":"2154",
    "addr:street":"Piazza Court Old Northern Rd",
    "iso:country":"AU",
    "sg:address":"Piazza Court, Old Northern Rd",
    "sg:city":"Castle Hill",
    "sg:classifiers":[
        {
            "category":"Health Services",
            "subcategory":"Dentist",
            "type":"Services"
        }
    ],
    "sg:phone":"+61 2 9634 6299",
    "sg:postcode":"2154",
    "sg:province":"NSW",
    "wof:name":"A. AAAAAA",
    "wof:placetype":"venue"
},
  "geometry": {"coordinates":[151.005249023,-33.7326927185],"type":"Point"}
}