{
  "type": "Feature",
  "properties": {
    "addr:full":"Cnr North Rd & Lion St Albany WA 6330",
    "addr:postcode":"6330",
    "addr:street":"Cnr North Rd & Lion St",
    "iso:country":"AU",
    "sg:address":"Cnr North Rd & Lion St",
    "sg:city":"Albany",
    "sg:classifiers":[
        {
            "category":"Health Services",
            "subcategory":"Doctor",
            "type":"Services"
        }
    ],
    "sg:phone":"+61 8 9842 2759",
    "sg:postcode":"6330",
    "sg:province":"WA",
    "sg:tags":[
        "podiatrist"
    ],
    "wof:name":"Albany Footcare",
    "wof:placetype":"venue"
},
  "geometry": {"coordinates":[117.884841919,-35.0089416504],"type":"Point"}
}