{
  "type": "Feature",
  "properties": {
    "iso:country":"AU",
    "sg:address":"20 Stubbs St",
    "sg:city":"Kensington",
    "sg:classifiers":[
        {
            "category":"Professional",
            "type":"Services"
        }
    ],
    "sg:phone":"+61 13 11 50",
    "sg:postcode":"3031",
    "sg:province":"VIC",
    "sg:tags":[
        "courier"
    ],
    "wof:name":"TNT",
    "wof:placetype":"venue"
},
  "geometry": {"coordinates":[144.935791,-37.789288],"type":"Point"}
}