{
  "type": "Feature",
  "properties": {
    "iso:country":"AU",
    "sg:address":"9 Central Park Drv",
    "sg:city":"Paget",
    "sg:classifiers":[
        {
            "category":"Manufacturing",
            "subcategory":"Motor Vehicles & Parts",
            "type":"Manufacturing & Wholesale Goods"
        }
    ],
    "sg:phone":"+61 7 4952 4422",
    "sg:postcode":"4740",
    "sg:province":"QLD",
    "sg:tags":[
        "engine",
        "equipment",
        "diesel"
    ],
    "wof:name":"Stiles & Hicks",
    "wof:placetype":"venue"
},
  "geometry": {"coordinates":[149.166077,-21.174229],"type":"Point"}
}