{
  "type": "Feature",
  "properties": {
    "addr:full":"18 Renwick St Wyoming NSW 2250",
    "addr:housenumber":"18",
    "addr:postcode":"2250",
    "addr:street":"Renwick St",
    "iso:country":"AU",
    "sg:address":"18 Renwick St",
    "sg:city":"Wyoming",
    "sg:classifiers":[
        {
            "category":"Health Services",
            "subcategory":"Doctor",
            "type":"Services"
        }
    ],
    "sg:phone":"+61 2 4328 4322",
    "sg:postcode":"2250",
    "sg:province":"NSW",
    "sg:tags":[
        "medical",
        "practitioner"
    ],
    "wof:name":"Kwong A & Meldrum N",
    "wof:placetype":"venue"
},
  "geometry": {"coordinates":[151.35203552199999,-33.4033851624],"type":"Point"}
}