{
  "type": "Feature",
  "properties": {
    "addr:full":"54 Lester St Eaglehawk VIC 3556",
    "addr:housenumber":"54",
    "addr:postcode":"3556",
    "addr:street":"Lester St",
    "iso:country":"AU",
    "sg:address":"54 Lester St",
    "sg:city":"Eaglehawk",
    "sg:classifiers":[
        {
            "category":"Building & Trades",
            "subcategory":"Construction",
            "type":"Services"
        }
    ],
    "sg:phone":"+61 3 5446 1022",
    "sg:postcode":"3556",
    "sg:province":"VIC",
    "sg:tags":[
        "fencing",
        "contractor"
    ],
    "wof:name":"Quality Impressions",
    "wof:placetype":"venue"
},
  "geometry": {"coordinates":[144.24299621599999,-36.708896637],"type":"Point"}
}