{
  "type": "Feature",
  "properties": {
    "addr:full":"PO Box 1566 Osborne Park WA 6017",
    "addr:postcode":"6017",
    "iso:country":"AU",
    "sg:address":"PO Box 1566",
    "sg:city":"Osborne Park",
    "sg:classifiers":[
        {
            "category":"Professional",
            "subcategory":"Art Services",
            "type":"Services"
        }
    ],
    "sg:phone":"+61 8 9445 3644",
    "sg:postcode":"6017",
    "sg:province":"WA",
    "sg:tags":[
        "picture",
        "frame",
        "framing"
    ],
    "wof:name":"Militaria Direct",
    "wof:placetype":"venue"
},
  "geometry": {"coordinates":[115.817710877,-31.9038391113],"type":"Point"}
}