{
  "type": "Feature",
  "properties": {
    "addr:full":"7 West Promenade Manly NSW 2095",
    "addr:housenumber":"7",
    "addr:postcode":"2095",
    "addr:street":"West Promenade",
    "iso:country":"AU",
    "sg:address":"7 West Promenade",
    "sg:city":"Manly",
    "sg:classifiers":[
        {
            "category":"Health Services",
            "subcategory":"Doctor",
            "type":"Services"
        }
    ],
    "sg:phone":"+61 2 9977 2286",
    "sg:postcode":"2095",
    "sg:province":"NSW",
    "sg:tags":[
        "medical",
        "practitioner"
    ],
    "sg:website":"http://www.ppsurgery.com.au",
    "wof:name":"Harper Dr Warwick R",
    "wof:placetype":"venue"
},
  "geometry": {"coordinates":[151.28736877399999,-33.7952384949],"type":"Point"}
}