{
  "type": "Feature",
  "properties": {
    "addr:full":"14 Railway St Liverpool NSW 2170",
    "addr:housenumber":"14",
    "addr:postcode":"2170",
    "addr:street":"Railway St",
    "iso:country":"AU",
    "sg:address":"14 Railway St",
    "sg:city":"Liverpool",
    "sg:classifiers":[
        {
            "category":"Personal",
            "type":"Services"
        }
    ],
    "sg:phone":"+61 2 9601 4100",
    "sg:postcode":"2170",
    "sg:province":"NSW",
    "sg:tags":[
        "gift"
    ],
    "wof:name":"Lilleyman's Floral Studio",
    "wof:placetype":"venue"
},
  "geometry": {"coordinates":[150.92579650900001,-33.9244041443],"type":"Point"}
}