{
  "type": "Feature",
  "properties": {
    "iso:country":"AU",
    "sg:address":"321 White Rd",
    "sg:city":"Wonthaggi",
    "sg:classifiers":[
        {
            "category":"Home & Garden",
            "subcategory":"Carpets & Floor Coverings",
            "type":"Retail Goods"
        }
    ],
    "sg:phone":"+61 3 5672 5590",
    "sg:postcode":"3995",
    "sg:province":"VIC",
    "sg:tags":[
        "tile",
        "wall"
    ],
    "wof:name":"Wonthaggi Floor World",
    "wof:placetype":"venue"
},
  "geometry": {"coordinates":[145.576813,-38.585815],"type":"Point"}
}