{
  "type": "Feature",
  "properties": {
    "iso:country":"AU",
    "sg:address":"Unit 2 21 Baratta St",
    "sg:city":"Blackburn South",
    "sg:classifiers":[
        {
            "category":"Real Estate",
            "subcategory":"Surveying",
            "type":"Services"
        }
    ],
    "sg:phone":"+61 3 9899 4950",
    "sg:postcode":"3130",
    "sg:province":"VIC",
    "sg:tags":[
        "surveyor",
        "land"
    ],
    "wof:name":"Bennett Des & Associates",
    "wof:placetype":"venue"
},
  "geometry": {"coordinates":[145.14122009299999,-37.8377685547],"type":"Point"}
}