{
  "type": "Feature",
  "properties": {
    "iso:country":"AU",
    "sg:address":"199 Clarence St",
    "sg:city":"Sydney",
    "sg:classifiers":[
        {
            "category":"Personal",
            "type":"Services"
        }
    ],
    "sg:phone":"+61 2 9299 9414",
    "sg:postcode":"2000",
    "sg:province":"NSW",
    "sg:tags":[
        "reducing",
        "treatment",
        "weight"
    ],
    "wof:name":"Madame Et Monsieur Weight Loss",
    "wof:placetype":"venue"
},
  "geometry": {"coordinates":[151.20523071299999,-33.8695602417],"type":"Point"}
}