{
  "type": "Feature",
  "properties": {
    "addr:full":"43 Henley Beach Rd Henley Beach South SA 5022",
    "addr:housenumber":"43",
    "addr:postcode":"5022",
    "addr:street":"Henley Beach Rd",
    "iso:country":"AU",
    "sg:address":"43 Henley Beach Rd",
    "sg:city":"Henley Beach South",
    "sg:classifiers":[
        {
            "category":"Personal",
            "type":"Services"
        }
    ],
    "sg:phone":"+61 8 8353 4001",
    "sg:postcode":"5022",
    "sg:province":"SA",
    "sg:tags":[
        "dressmaker"
    ],
    "wof:name":"Koochi Kids",
    "wof:placetype":"venue"
},
  "geometry": {"coordinates":[138.500823975,-34.9255523682],"type":"Point"}
}