{
  "type": "Feature",
  "properties": {
    "iso:country":"AU",
    "sg:address":"25 Richland St",
    "sg:city":"Kingsgrove",
    "sg:classifiers":[
        {
            "category":"Manufacturing",
            "subcategory":"Furniture",
            "type":"Manufacturing & Wholesale Goods"
        }
    ],
    "sg:phone":"+61 2 9502 2161",
    "sg:postcode":"2208",
    "sg:province":"NSW",
    "sg:tags":[
        "builder",
        "designer",
        "custom"
    ],
    "wof:name":"Gerber Trading Co Pty Ltd",
    "wof:placetype":"venue"
},
  "geometry": {"coordinates":[151.09823600000001,-33.934639],"type":"Point"}
}