{
  "type": "Feature",
  "properties": {
    "iso:country":"AU",
    "sg:address":"106 William St",
    "sg:city":"Port Macquarie",
    "sg:classifiers":[
        {
            "category":"Banks & Credit Unions",
            "subcategory":"Bank",
            "type":"Services"
        }
    ],
    "sg:phone":"+61 2 6583 7588",
    "sg:postcode":"2444",
    "sg:province":"NSW",
    "sg:tags":[
        "broker",
        "mortgage"
    ],
    "wof:name":"Direct Advisers&#039; Home Loans",
    "wof:placetype":"venue"
},
  "geometry": {"coordinates":[152.909409,-31.431307],"type":"Point"}
}