{
  "type": "Feature",
  "properties": {
    "addr:full":"PO Box 6121 Mooloolah QLD 4553",
    "addr:postcode":"4553",
    "iso:country":"AU",
    "sg:address":"PO Box 6121",
    "sg:city":"Mooloolah",
    "sg:classifiers":[
        {
            "category":"Building & Trades",
            "subcategory":"Landscaping Services",
            "type":"Services"
        }
    ],
    "sg:phone":"+61 411 424 848",
    "sg:postcode":"4553",
    "sg:province":"QLD",
    "sg:tags":[
        "architect",
        "landscape"
    ],
    "wof:name":"Sight- Design Landscape",
    "wof:placetype":"venue"
},
  "geometry": {"coordinates":[152.96670499999999,-26.766701],"type":"Point"}
}