{
  "type": "Feature",
  "properties": {
    "addr:full":"Unit 2/ 8 Corbusier Pl Balcatta WA 6021",
    "addr:postcode":"6021",
    "addr:street":"Corbusier Pl",
    "iso:country":"AU",
    "sg:address":"Unit 2/ 8 Corbusier Pl",
    "sg:city":"Balcatta",
    "sg:classifiers":[
        {
            "category":"Building & Trades",
            "subcategory":"Construction",
            "type":"Services"
        }
    ],
    "sg:phone":"+61 8 9240 5099",
    "sg:postcode":"6021",
    "sg:province":"WA",
    "sg:tags":[
        "renovation",
        "alterations",
        "extension",
        "contractor"
    ],
    "wof:name":"Trademark Constructions",
    "wof:placetype":"venue"
},
  "geometry": {"coordinates":[115.814208984,-31.8617515564],"type":"Point"}
}