{
  "type": "Feature",
  "properties": {
    "addr:full":"26 Old Perth Rd Bassendean WA 6054",
    "addr:housenumber":"26",
    "addr:postcode":"6054",
    "addr:street":"Old Perth Rd",
    "iso:country":"AU",
    "sg:address":"26 Old Perth Rd",
    "sg:city":"Bassendean",
    "sg:classifiers":[
        {
            "category":"Shopping",
            "subcategory":"Clothing, Apparel, & Fashions",
            "type":"Retail Goods"
        }
    ],
    "sg:phone":"+61 8 9378 3575",
    "sg:postcode":"6054",
    "sg:province":"WA",
    "sg:tags":[
        "lady",
        "wear"
    ],
    "sg:website":"http://juliesvillage.citysearch.com.au",
    "wof:name":"Julies Village Boutique",
    "wof:placetype":"venue"
},
  "geometry": {"coordinates":[115.94837951700001,-31.9039497375],"type":"Point"}
}