{
  "type": "Feature",
  "properties": {
    "addr:full":"19 Swan St Gordonvale QLD 4865",
    "addr:housenumber":"19",
    "addr:postcode":"4865",
    "addr:street":"Swan St",
    "iso:country":"AU",
    "sg:address":"19 Swan St",
    "sg:city":"Gordonvale",
    "sg:classifiers":[
        {
            "category":"Utilities",
            "subcategory":"Electric",
            "type":"Services"
        }
    ],
    "sg:phone":"+61 7 4056 2216",
    "sg:postcode":"4865",
    "sg:province":"QLD",
    "sg:tags":[
        "electrical",
        "contractor"
    ],
    "wof:name":"Barcou Electrics",
    "wof:placetype":"venue"
},
  "geometry": {"coordinates":[145.78465270999999,-17.0986843109],"type":"Point"}
}