{
  "type": "Feature",
  "properties": {
    "addr:full":"PO Box 1472 Wangara WA 6065",
    "addr:postcode":"6065",
    "iso:country":"AU",
    "sg:address":"PO Box 1472",
    "sg:city":"Wangara",
    "sg:classifiers":[
        {
            "category":"Shopping",
            "subcategory":"Stationery & Office Supplies",
            "type":"Retail Goods"
        }
    ],
    "sg:phone":"+61 8 9309 9700",
    "sg:postcode":"6065",
    "sg:province":"WA",
    "sg:tags":[
        "partition"
    ],
    "wof:name":"Interior Building Solutions Pty Ltd",
    "wof:placetype":"venue"
},
  "geometry": {"coordinates":[115.830238342,-31.7956504822],"type":"Point"}
}