{
  "type": "Feature",
  "properties": {
    "addr:full":"9 Sanyo Drv Wodonga VIC 3690",
    "addr:housenumber":"9",
    "addr:postcode":"3690",
    "addr:street":"Sanyo Drv",
    "iso:country":"AU",
    "sg:address":"9 Sanyo Drv",
    "sg:city":"Wodonga",
    "sg:classifiers":[
        {
            "category":"Home & Garden",
            "subcategory":"Building Materials",
            "type":"Retail Goods"
        }
    ],
    "sg:phone":"+61 2 6056 1677",
    "sg:postcode":"3690",
    "sg:province":"VIC",
    "sg:tags":[
        "fitting",
        "door"
    ],
    "wof:name":"Doors &#039;N&#039; Knobs",
    "wof:placetype":"venue"
},
  "geometry": {"coordinates":[146.901657105,-36.124370575],"type":"Point"}
}