{
  "type": "Feature",
  "properties": {
    "addr:full":"187 Queen St Warragul VIC 3820",
    "addr:housenumber":"187",
    "addr:postcode":"3820",
    "addr:street":"Queen St",
    "iso:country":"AU",
    "sg:address":"187 Queen St",
    "sg:city":"Warragul",
    "sg:classifiers":[
        {
            "category":"Manufacturing",
            "subcategory":"Retail Goods",
            "type":"Manufacturing & Wholesale Goods"
        }
    ],
    "sg:phone":"+61 3 5623 1834",
    "sg:postcode":"3820",
    "sg:province":"VIC",
    "sg:tags":[
        "merchant",
        "pump",
        "mfrs"
    ],
    "wof:name":"Daviesway Pty Ltd",
    "wof:placetype":"venue"
},
  "geometry": {"coordinates":[145.938614,-38.143978],"type":"Point"}
}