{
  "type": "Feature",
  "properties": {
    "iso:country":"AU",
    "sg:address":"62 Congdon Ave",
    "sg:city":"Beeliar",
    "sg:classifiers":[
        {
            "category":"Building & Trades",
            "subcategory":"Construction",
            "type":"Services"
        }
    ],
    "sg:phone":"+61 408 429 117",
    "sg:postcode":"6164",
    "sg:province":"WA",
    "sg:tags":[
        "earth",
        "excavating",
        "moving",
        "contractor"
    ],
    "wof:name":"Stirling Concrete Bobcat Hire",
    "wof:placetype":"venue"
},
  "geometry": {"coordinates":[115.797394,-32.131577],"type":"Point"}
}