{
  "type": "Feature",
  "properties": {
    "iso:country":"AU",
    "sg:address":"2 Masodon St",
    "sg:city":"Bossley Park",
    "sg:classifiers":[
        {
            "category":"Wholesale",
            "subcategory":"Painting Supplies",
            "type":"Manufacturing & Wholesale Goods"
        }
    ],
    "sg:phone":"+61 2 9609 2730",
    "sg:postcode":"2176",
    "sg:province":"NSW",
    "sg:tags":[
        "product",
        "cleaning"
    ],
    "wof:name":"Choban Trolley & Cleaning Services",
    "wof:placetype":"venue"
},
  "geometry": {"coordinates":[150.88375854500001,-33.859828949],"type":"Point"}
}