{
  "type": "Feature",
  "properties": {
    "iso:country":"AU",
    "sg:address":"45- 47 Tope St",
    "sg:city":"South Melbourne",
    "sg:classifiers":[
        {
            "category":"Professional",
            "subcategory":"Employment Agencies",
            "type":"Services"
        }
    ],
    "sg:phone":"+61 3 9686 1711",
    "sg:postcode":"3205",
    "sg:province":"VIC",
    "sg:tags":[
        "vic",
        "escort"
    ],
    "wof:name":"Mc Forum",
    "wof:placetype":"venue"
},
  "geometry": {"coordinates":[144.963333,-37.830498],"type":"Point"}
}