{
  "type": "Feature",
  "properties": {
    "addr:full":"Shop 24, Broadway Fair Shopping Centre, 88 Broadway Nedlands WA 6009",
    "addr:housenumber":"shop 24;88",
    "addr:postcode":"6009",
    "addr:street":"Broadway;Broadway",
    "iso:country":"AU",
    "sg:address":"Shop 24, Broadway Fair Shopping Centre, 88",
    "sg:city":"Broadway Nedlands",
    "sg:classifiers":[
        {
            "category":"Shopping",
            "subcategory":"Baby Store",
            "type":"Retail Goods"
        }
    ],
    "sg:phone":"+61 8 9386 3677",
    "sg:postcode":"6009",
    "sg:province":"WA",
    "sg:tags":[
        "wear"
    ],
    "wof:name":"Adorable Affordable",
    "wof:placetype":"venue"
},
  "geometry": {"coordinates":[115.814232,-31.978054],"type":"Point"}
}