{
  "type": "Feature",
  "properties": {
    "iso:country":"AU",
    "sg:address":"Cnr Keen & 110 Woodlark Sts",
    "sg:city":"Lismore",
    "sg:classifiers":[
        {
            "category":"Retail",
            "subcategory":"Event Space",
            "type":"Services"
        }
    ],
    "sg:phone":"+61 2 6622 2924",
    "sg:postcode":"2480",
    "sg:province":"NSW",
    "sg:tags":[
        "function",
        "organiser"
    ],
    "wof:name":"The Commercial Hotel AKA Mary Gilhooleys",
    "wof:placetype":"venue"
},
  "geometry": {"coordinates":[153.27914428700001,-28.8074474335],"type":"Point"}
}