{
  "type": "Feature",
  "properties": {
    "addr:full":"Unit 2/119 Brisbane St, Shops 8-10 Post Office Square Beaudesert QLD 4285",
    "addr:housenumber":"/ 119;8-10",
    "addr:postcode":"4285",
    "addr:street":"Brisbane St;Square",
    "iso:country":"AU",
    "sg:address":"Unit 2/119 Brisbane St, Shops 8-10 Post Office Square",
    "sg:city":"Beaudesert",
    "sg:classifiers":[
        {
            "category":"Professional",
            "subcategory":"Printing & Photocopies",
            "type":"Services"
        }
    ],
    "sg:phone":"+61 7 5541 3050",
    "sg:postcode":"4285",
    "sg:province":"QLD",
    "sg:tags":[
        "trophy"
    ],
    "wof:name":"A Better Copy & Digital Enhancements",
    "wof:placetype":"venue"
},
  "geometry": {"coordinates":[152.99586500000001,-27.986572],"type":"Point"}
}