{
  "type": "Feature",
  "properties": {
    "addr:full":"10 Bennetts Rd, Mornington VIC 3931",
    "addr:housenumber":"10",
    "addr:postcode":"3931",
    "addr:street":"Bennetts Rd",
    "iso:country":"AU",
    "sg:address":"10 Bennetts Rd,",
    "sg:city":"Mornington",
    "sg:classifiers":[
        {
            "category":"Manufacturing",
            "subcategory":"Furniture",
            "type":"Manufacturing & Wholesale Goods"
        }
    ],
    "sg:phone":"+61 3 5975 0344",
    "sg:postcode":"3931",
    "sg:province":"VIC",
    "sg:tags":[
        "builder",
        "designer",
        "custom"
    ],
    "wof:name":"Sorrento Furniture",
    "wof:placetype":"venue"
},
  "geometry": {"coordinates":[145.04801940900001,-38.2310752869],"type":"Point"}
}