{
  "type": "Feature",
  "properties": {
    "addr:full":"Cnr MacPherson & Unumgar Sts Woodenbong NSW 2476",
    "addr:postcode":"2476",
    "addr:street":"Cnr",
    "iso:country":"AU",
    "sg:address":"Cnr MacPherson & Unumgar Sts",
    "sg:city":"Woodenbong",
    "sg:classifiers":[
        {
            "category":"Autos & Motor Vehicles",
            "subcategory":"Fuel & Gas Station",
            "type":"Retail Goods"
        }
    ],
    "sg:phone":"+61 2 6635 1300",
    "sg:postcode":"2476",
    "sg:province":"NSW",
    "wof:name":"Mobil Oil Australia Pty Ltd",
    "wof:placetype":"venue"
},
  "geometry": {"coordinates":[152.61231994600001,-28.3899726868],"type":"Point"}
}