{
  "type": "Feature",
  "properties": {
    "addr:full":"12 Reid St Windsor QLD 4030",
    "addr:housenumber":"12",
    "addr:postcode":"4030",
    "addr:street":"Reid St",
    "iso:country":"AU",
    "sg:address":"12 Reid St",
    "sg:city":"Windsor",
    "sg:classifiers":[
        {
            "category":"Professional",
            "subcategory":"Art Services",
            "type":"Services"
        }
    ],
    "sg:phone":"+61 7 3857 8877",
    "sg:postcode":"4030",
    "sg:province":"QLD",
    "sg:tags":[
        "decorator",
        "painter"
    ],
    "wof:name":"G & S Painters Pty Ltd",
    "wof:placetype":"venue"
},
  "geometry": {"coordinates":[153.026825,-27.427643],"type":"Point"}
}