{
  "type": "Feature",
  "properties": {
    "iso:country":"AU",
    "sg:address":"310 Clayton Rd",
    "sg:city":"Clayton",
    "sg:classifiers":[
        {
            "category":"Personal",
            "subcategory":"Beauty Salon",
            "type":"Services"
        }
    ],
    "sg:phone":"+61 3 9562 7446",
    "sg:postcode":"3168",
    "sg:province":"VIC",
    "sg:tags":[
        "hairdresser"
    ],
    "wof:name":"Hair Panache",
    "wof:placetype":"venue"
},
  "geometry": {"coordinates":[145.119674683,-37.9262123108],"type":"Point"}
}