{
  "type": "Feature",
  "properties": {
    "addr:full":"11 Weenamana Pl Padstow NSW 2211",
    "addr:housenumber":"11",
    "addr:postcode":"2211",
    "addr:street":"Weenamana Pl",
    "iso:country":"AU",
    "sg:address":"11 Weenamana Pl",
    "sg:city":"Padstow",
    "sg:classifiers":[
        {
            "category":"Professional",
            "type":"Services"
        }
    ],
    "sg:phone":"+61 413 318 225",
    "sg:postcode":"2211",
    "sg:province":"NSW",
    "sg:tags":[
        "transport"
    ],
    "wof:name":"Tonlee Pty Ltd",
    "wof:placetype":"venue"
},
  "geometry": {"coordinates":[151.03872699999999,-33.958652],"type":"Point"}
}