{
  "type": "Feature",
  "properties": {
    "iso:country":"AU",
    "sg:address":"322 Canning Hwy",
    "sg:city":"Bicton",
    "sg:classifiers":[
        {
            "category":"Health Services",
            "subcategory":"Health Practitioner",
            "type":"Services"
        }
    ],
    "sg:phone":"+61 438 947 164",
    "sg:postcode":"6157",
    "sg:province":"WA",
    "sg:tags":[
        "psychologist"
    ],
    "wof:name":"Batik Mary",
    "wof:placetype":"venue"
},
  "geometry": {"coordinates":[115.792603,-32.034538],"type":"Point"}
}