{
  "type": "Feature",
  "properties": {
    "addr:full":"Lot1/ Muggletons Rd Garland NSW 2797",
    "addr:postcode":"2797",
    "addr:street":"Muggletons Rd",
    "iso:country":"AU",
    "sg:address":"Lot1/ Muggletons Rd",
    "sg:city":"Garland",
    "sg:classifiers":[
        {
            "category":"Manufacturing",
            "subcategory":"Tools & Machinery",
            "type":"Manufacturing & Wholesale Goods"
        }
    ],
    "sg:phone":"+61 2 6367 5275",
    "sg:postcode":"2797",
    "sg:province":"NSW",
    "sg:tags":[
        "machine",
        "industrial",
        "sewing"
    ],
    "wof:name":"Sewtek Packaging Solutions Pty Ltd",
    "wof:placetype":"venue"
},
  "geometry": {"coordinates":[149.02178955100001,-33.71641922],"type":"Point"}
}