{
  "type": "Feature",
  "properties": {
    "addr:full":"Unit 3/7- 11 Parraweena Rd Taren Point NSW 2229",
    "addr:housenumber":"11",
    "addr:postcode":"2229",
    "addr:street":"Parraweena Rd",
    "iso:country":"AU",
    "sg:address":"Unit 3/7- 11 Parraweena Rd",
    "sg:city":"Taren Point",
    "sg:classifiers":[
        {
            "category":"Parking",
            "subcategory":"Bicycle",
            "type":"Transportation"
        }
    ],
    "sg:phone":"+61 2 9526 8777",
    "sg:postcode":"2229",
    "sg:province":"NSW",
    "sg:tags":[
        "consultant",
        "shipping"
    ],
    "wof:name":"HK Logistics Pty Ltd",
    "wof:placetype":"venue"
},
  "geometry": {"coordinates":[151.12982177699999,-34.0262985229],"type":"Point"}
}