{
  "type": "Feature",
  "properties": {
    "addr:full":"22 Jennings St Bendigo East VIC 3550",
    "addr:housenumber":"22",
    "addr:postcode":"3550",
    "addr:street":"Jennings St",
    "iso:country":"AU",
    "sg:address":"22 Jennings St",
    "sg:city":"Bendigo East",
    "sg:classifiers":[
        {
            "category":"Personal",
            "subcategory":"Massage",
            "type":"Services"
        }
    ],
    "sg:phone":"+61 3 5443 3375",
    "sg:postcode":"3550",
    "sg:province":"VIC",
    "sg:tags":[
        "therapy"
    ],
    "wof:name":"Healing Touch",
    "wof:placetype":"venue"
},
  "geometry": {"coordinates":[144.29887390100001,-36.7514762878],"type":"Point"}
}