{
  "type": "Feature",
  "properties": {
    "addr:full":"45 McLean St Morwell VIC 3840",
    "addr:housenumber":"45",
    "addr:postcode":"3840",
    "addr:street":"Mclean St",
    "iso:country":"AU",
    "sg:address":"45 McLean St",
    "sg:city":"Morwell",
    "sg:classifiers":[
        {
            "category":"Retail",
            "subcategory":"Auto Rental",
            "type":"Services"
        }
    ],
    "sg:phone":"+61 3 5134 6876",
    "sg:postcode":"3840",
    "sg:province":"VIC",
    "sg:tags":[
        "car",
        "hire",
        "minibus"
    ],
    "wof:name":"Mountain-Top Experience 4WD",
    "wof:placetype":"venue"
},
  "geometry": {"coordinates":[146.40162658700001,-38.2415618896],"type":"Point"}
}