{
  "type": "Feature",
  "properties": {
    "addr:full":"PO Box 13003 Melbourne VIC 8010",
    "addr:postcode":"8010",
    "iso:country":"AU",
    "sg:address":"PO Box 13003",
    "sg:city":"Melbourne",
    "sg:classifiers":[
        {
            "category":"Real Estate",
            "subcategory":"Real Estate Agent",
            "type":"Services"
        }
    ],
    "sg:phone":"+61 3 9602 2099",
    "sg:postcode":"8010",
    "sg:province":"VIC",
    "wof:name":"Stockdale Property",
    "wof:placetype":"venue"
},
  "geometry": {"coordinates":[144.963165,-37.814251],"type":"Point"}
}