{
  "type": "Feature",
  "properties": {
    "addr:full":"22 Gladstone Rd, Highgate Hill QLD 4101",
    "addr:housenumber":"22",
    "addr:postcode":"4101",
    "addr:street":"Gladstone Rd",
    "iso:country":"AU",
    "sg:address":"22 Gladstone Rd,",
    "sg:city":"Highgate Hill",
    "sg:classifiers":[
        {
            "category":"Retail",
            "subcategory":"Auto Repair",
            "type":"Services"
        }
    ],
    "sg:phone":"+61 7 3844 2155",
    "sg:postcode":"4101",
    "sg:province":"QLD",
    "sg:tags":[
        "repairer",
        "motor",
        "engineer"
    ],
    "wof:name":"Gladstone Road Garage & Workshop",
    "wof:placetype":"venue"
},
  "geometry": {"coordinates":[153.01979064899999,-27.4833316803],"type":"Point"}
}