{
  "type": "Feature",
  "properties": {
    "addr:full":"Shop 3/ 398 Deception Bay Rd Deception Bay QLD 4508",
    "addr:housenumber":"shop 3 / 398",
    "addr:postcode":"4508",
    "addr:street":"Deception Bay Rd",
    "iso:country":"AU",
    "sg:address":"Shop 3/ 398 Deception Bay Rd",
    "sg:city":"Deception Bay",
    "sg:classifiers":[
        {
            "category":"Fast Food",
            "type":"Food & Drink"
        }
    ],
    "sg:phone":"+61 7 3203 2603",
    "sg:postcode":"4508",
    "sg:province":"QLD",
    "sg:tags":[
        "away",
        "take"
    ],
    "wof:name":"KingsTobacconist Asian And Island Foods",
    "wof:placetype":"venue"
},
  "geometry": {"coordinates":[153.01431274399999,-27.1888828278],"type":"Point"}
}