{
  "type": "Feature",
  "properties": {
    "iso:country":"AU",
    "sg:address":"1a/ 355- 365 South Gipsland Hwy",
    "sg:city":"Dandenong",
    "sg:classifiers":[
        {
            "category":"Professional",
            "subcategory":"Printing & Photocopies",
            "type":"Services"
        }
    ],
    "sg:phone":"+61 3 9798 0466",
    "sg:postcode":"3175",
    "sg:province":"VIC",
    "sg:tags":[
        "embroidery"
    ],
    "wof:name":"Embroidme Dandenong",
    "wof:placetype":"venue"
},
  "geometry": {"coordinates":[145.24473571799999,-38.0289115906],"type":"Point"}
}