{
  "type": "Feature",
  "properties": {
    "iso:country":"AU",
    "sg:address":"18 Peregrine Ave",
    "sg:city":"Tamworth",
    "sg:classifiers":[
        {
            "category":"Utilities",
            "subcategory":"Water",
            "type":"Services"
        }
    ],
    "sg:phone":"+61 2 6765 6959",
    "sg:postcode":"2340",
    "sg:province":"NSW",
    "sg:tags":[
        "hot",
        "system"
    ],
    "wof:name":"Steeps Electrical Services",
    "wof:placetype":"venue"
},
  "geometry": {"coordinates":[150.94581604000001,-31.1280593872],"type":"Point"}
}