{
  "type": "Feature",
  "properties": {
    "addr:full":"2 William St Ermington NSW 2115",
    "addr:housenumber":"2",
    "addr:postcode":"2115",
    "addr:street":"William St",
    "iso:country":"AU",
    "sg:address":"2 William St",
    "sg:city":"Ermington",
    "sg:classifiers":[
        {
            "category":"Professional",
            "subcategory":"Detective & Security Services",
            "type":"Services"
        }
    ],
    "sg:phone":"+61 2 9858 3623",
    "sg:postcode":"2115",
    "sg:province":"NSW",
    "sg:tags":[
        "consultant",
        "system"
    ],
    "wof:name":"Ae Hightech Electronics",
    "wof:placetype":"venue"
},
  "geometry": {"coordinates":[151.06651306099999,-33.8080673218],"type":"Point"}
}