{
  "type": "Feature",
  "properties": {
    "iso:country":"AU",
    "sg:address":"Shop 51, Arbour Ln Robina Town Cntr Robina Drv",
    "sg:city":"Robina",
    "sg:classifiers":[
        {
            "category":"Banks & Credit Unions",
            "subcategory":"Bureau De Change",
            "type":"Services"
        }
    ],
    "sg:phone":"+61 1800 637 642",
    "sg:postcode":"4226",
    "sg:province":"QLD",
    "sg:tags":[
        "currency",
        "exchange",
        "foreign"
    ],
    "wof:name":"Travelex",
    "wof:placetype":"venue"
},
  "geometry": {"coordinates":[153.38783264200001,-28.0696353912],"type":"Point"}
}