{
  "type": "Feature",
  "properties": {
    "addr:full":"Unit 2/ 20 Curtis Rd McGraths Hill NSW 2756",
    "addr:postcode":"2756",
    "addr:street":"Curtis Rd",
    "iso:country":"AU",
    "sg:address":"Unit 2/ 20 Curtis Rd",
    "sg:city":"McGraths Hill",
    "sg:classifiers":[
        {
            "category":"Government",
            "subcategory":"Fire Station",
            "type":"Public Place"
        }
    ],
    "sg:phone":"+61 2 4587 7114",
    "sg:postcode":"2756",
    "sg:province":"NSW",
    "sg:tags":[
        "spring",
        "shock",
        "absorbers",
        "suspension"
    ],
    "wof:name":"Macquarie 4x4",
    "wof:placetype":"venue"
},
  "geometry": {"coordinates":[150.83604431099999,-33.6229972839],"type":"Point"}
}