{
  "type": "Feature",
  "properties": {
    "addr:full":"170a Old Northern Rd Castle Hill NSW 2154",
    "addr:housenumber":"170a",
    "addr:postcode":"2154",
    "addr:street":"Old Northern Rd",
    "iso:country":"AU",
    "sg:address":"170a Old Northern Rd",
    "sg:city":"Castle Hill",
    "sg:classifiers":[
        {
            "category":"Health Services",
            "subcategory":"Doctor",
            "type":"Services"
        }
    ],
    "sg:phone":"+61 2 9688 6678",
    "sg:postcode":"2154",
    "sg:province":"NSW",
    "sg:tags":[
        "medical",
        "practitioner"
    ],
    "wof:name":"Lou Jennifer Dr",
    "wof:placetype":"venue"
},
  "geometry": {"coordinates":[151.01683044399999,-33.730255127],"type":"Point"}
}