{
  "type": "Feature",
  "properties": {
    "addr:full":"49B Hastings Street Scarborough WA 6019",
    "addr:housenumber":"49b",
    "addr:postcode":"6019",
    "addr:street":"Hastings Street",
    "iso:country":"AU",
    "sg:address":"49B Hastings Street",
    "sg:city":"Scarborough",
    "sg:classifiers":[
        {
            "category":"Professional",
            "subcategory":"Employment Agencies",
            "type":"Services"
        }
    ],
    "sg:phone":"+61 8 9245 3644",
    "sg:postcode":"6019",
    "sg:province":"WA",
    "wof:name":"MPM Quality People",
    "wof:placetype":"venue"
},
  "geometry": {"coordinates":[115.759857178,-31.8982791901],"type":"Point"}
}