{
  "type": "Feature",
  "properties": {
    "addr:full":"PO Box 651 Cloverdale Prvte Bxes WA 6985",
    "addr:postcode":"6985",
    "iso:country":"AU",
    "sg:address":"PO Box 651",
    "sg:city":"Cloverdale Prvte Bxes",
    "sg:classifiers":[
        {
            "category":"Retail",
            "subcategory":"Auto Repair",
            "type":"Services"
        }
    ],
    "sg:phone":"+61 1800 655 511",
    "sg:postcode":"6985",
    "sg:province":"WA",
    "sg:tags":[
        "repairer",
        "motor",
        "engineer"
    ],
    "wof:name":"Road Rescue",
    "wof:placetype":"venue"
},
  "geometry": {"coordinates":[115.934341,-31.96364],"type":"Point"}
}