{
  "type": "Feature",
  "properties": {
    "addr:full":"20 Bennetts Rd Mornington VIC 3931",
    "addr:housenumber":"20",
    "addr:postcode":"3931",
    "addr:street":"Bennetts Rd",
    "iso:country":"AU",
    "sg:address":"20 Bennetts Rd",
    "sg:city":"Mornington",
    "sg:classifiers":[
        {
            "category":"Autos & Motor Vehicles",
            "subcategory":"Auto Supplies",
            "type":"Retail Goods"
        }
    ],
    "sg:phone":"+61 3 5975 2642",
    "sg:postcode":"3931",
    "sg:province":"VIC",
    "sg:tags":[
        "wheel",
        "four",
        "equipment",
        "drive",
        "accessory"
    ],
    "wof:name":"PGS 4WD Accessories",
    "wof:placetype":"venue"
},
  "geometry": {"coordinates":[145.048904419,-38.231338501],"type":"Point"}
}