{
  "type": "Feature",
  "properties": {
    "iso:country":"AU",
    "sg:address":"The Esplanade Motor Inn 23",
    "sg:city":"Beach Rd, Batemans Bay",
    "sg:classifiers":[
        {
            "category":"Personal",
            "subcategory":"Beauty Salon",
            "type":"Services"
        }
    ],
    "sg:phone":"+61 2 4472 6391",
    "sg:postcode":"2536",
    "sg:province":"NSW",
    "sg:tags":[
        "supply",
        "artist",
        "make-up"
    ],
    "wof:name":"Sea Crest",
    "wof:placetype":"venue"
},
  "geometry": {"coordinates":[150.17880249000001,-35.7084579468],"type":"Point"}
}