{
  "type": "Feature",
  "properties": {
    "addr:full":"Level 10 45 Clarence St Sydney NSW 2000",
    "addr:housenumber":"45",
    "addr:postcode":"2000",
    "addr:street":"Clarence St",
    "iso:country":"AU",
    "sg:address":"Level 10 45 Clarence St",
    "sg:city":"Sydney",
    "sg:classifiers":[
        {
            "category":"Professional",
            "subcategory":"Management & Consulting",
            "type":"Services"
        }
    ],
    "sg:phone":"+61 2 9262 4000",
    "sg:postcode":"2000",
    "sg:province":"NSW",
    "sg:tags":[
        "consultant"
    ],
    "wof:name":"IT Newcom Pty Ltd",
    "wof:placetype":"venue"
},
  "geometry": {"coordinates":[151.20510864299999,-33.8659744263],"type":"Point"}
}