{
  "type": "Feature",
  "properties": {
    "addr:full":"PO Box 773 Mildura Centre Plaza VIC 3501",
    "addr:postcode":"3501",
    "iso:country":"AU",
    "sg:address":"PO Box 773",
    "sg:city":"Mildura Centre Plaza",
    "sg:classifiers":[
        {
            "category":"Manufacturing",
            "subcategory":"Building Materials",
            "type":"Manufacturing & Wholesale Goods"
        }
    ],
    "sg:phone":"+61 408 234 984",
    "sg:postcode":"3501",
    "sg:province":"VIC",
    "sg:tags":[
        "concrete",
        "product"
    ],
    "wof:name":"Mangan Concreting",
    "wof:placetype":"venue"
},
  "geometry": {"coordinates":[142.13630676299999,-34.2071113586],"type":"Point"}
}