{
  "type": "Feature",
  "properties": {
    "addr:full":"Cnr Waldron Rd & Bent St Chester Hill NSW 2162",
    "addr:postcode":"2162",
    "addr:street":"Waldron Rd & Bent St",
    "iso:country":"AU",
    "sg:address":"Cnr Waldron Rd & Bent St",
    "sg:city":"Chester Hill",
    "sg:classifiers":[
        {
            "category":"Food & Beverages",
            "subcategory":"Liquor & Beverages",
            "type":"Retail Goods"
        }
    ],
    "sg:phone":"+61 2 9644 4435",
    "sg:postcode":"2162",
    "sg:province":"NSW",
    "sg:tags":[
        "store"
    ],
    "wof:name":"Liquorland",
    "wof:placetype":"venue"
},
  "geometry": {"coordinates":[151.00015258799999,-33.8829574585],"type":"Point"}
}