{
  "type": "Feature",
  "properties": {
    "iso:country":"AU",
    "sg:address":"16 Lincoln St",
    "sg:city":"Strathpine",
    "sg:classifiers":[
        {
            "category":"Organizations",
            "subcategory":"Community Association",
            "type":"Services"
        }
    ],
    "sg:phone":"+61 7 3881 2823",
    "sg:postcode":"4500",
    "sg:province":"QLD",
    "sg:tags":[
        "organisation",
        "family",
        "welfare"
    ],
    "wof:name":"Youth Care Pine Rivers Inc",
    "wof:placetype":"venue"
},
  "geometry": {"coordinates":[152.99154663100001,-27.2955989838],"type":"Point"}
}