{
  "type": "Feature",
  "properties": {
    "addr:full":"Shp12/ High St Stanthorpe QLD 4380",
    "addr:postcode":"4380",
    "addr:street":"High St",
    "iso:country":"AU",
    "sg:address":"Shp12/ High St",
    "sg:city":"Stanthorpe",
    "sg:classifiers":[
        {
            "category":"Food & Beverages",
            "subcategory":"Liquor & Beverages",
            "type":"Retail Goods"
        }
    ],
    "sg:phone":"+61 7 4681 4154",
    "sg:postcode":"4380",
    "sg:province":"QLD",
    "sg:tags":[
        "store"
    ],
    "wof:name":"Castle Glen Cellars",
    "wof:placetype":"venue"
},
  "geometry": {"coordinates":[151.940201,-28.651587],"type":"Point"}
}