{
  "type": "Feature",
  "properties": {
    "iso:country":"AU",
    "sg:address":"Queensland Hotel 134 Marshall Rd",
    "sg:city":"Goondiwindi",
    "sg:classifiers":[
        {
            "category":"Food & Beverages",
            "subcategory":"Liquor & Beverages",
            "type":"Retail Goods"
        }
    ],
    "sg:phone":"+61 7 4671 2011",
    "sg:postcode":"4390",
    "sg:province":"QLD",
    "sg:tags":[
        "store"
    ],
    "wof:name":"Liquor King",
    "wof:placetype":"venue"
},
  "geometry": {"coordinates":[150.310012817,-28.5474853516],"type":"Point"}
}