{
  "type": "Feature",
  "properties": {
    "addr:full":"Shop 16, 10- 14 North Ave Cessnock NSW 2325",
    "addr:housenumber":"shop 16 10 14",
    "addr:postcode":"2325",
    "addr:street":"North Ave",
    "iso:country":"AU",
    "sg:address":"Shop 16, 10- 14 North Ave",
    "sg:city":"Cessnock",
    "sg:classifiers":[
        {
            "category":"Health Services",
            "subcategory":"Dentist",
            "type":"Services"
        }
    ],
    "sg:phone":"+61 2 4990 1279",
    "sg:postcode":"2325",
    "sg:province":"NSW",
    "wof:name":"Dr George Patience",
    "wof:placetype":"venue"
},
  "geometry": {"coordinates":[151.356201172,-32.8363189697],"type":"Point"}
}