{
  "type": "Feature",
  "properties": {
    "iso:country":"AU",
    "sg:address":"Cnr 13th St & Deakin Ave (Next To PJ's)",
    "sg:city":"Mildura",
    "sg:classifiers":[
        {
            "category":"Communications",
            "subcategory":"Film & Video Production",
            "type":"Services"
        }
    ],
    "sg:phone":"+61 3 5022 2525",
    "sg:postcode":"3500",
    "sg:province":"VIC",
    "sg:tags":[
        "dvd",
        "library"
    ],
    "wof:name":"Hollywood Express Videos",
    "wof:placetype":"venue"
},
  "geometry": {"coordinates":[142.143112183,-34.2014122009],"type":"Point"}
}