{
  "type": "Feature",
  "properties": {
    "addr:full":"85 McAdams La Bellarine VIC 3221",
    "addr:housenumber":"85",
    "addr:postcode":"3221",
    "addr:street":"Mcadams La Bellarine",
    "iso:country":"AU",
    "sg:address":"85 McAdams La",
    "sg:city":"Bellarine",
    "sg:classifiers":[
        {
            "category":"Farming",
            "subcategory":"Vineyard",
            "type":"Manufacturing & Wholesale Goods"
        }
    ],
    "sg:phone":"+61 3 5251 2223",
    "sg:postcode":"3221",
    "sg:province":"VIC",
    "sg:tags":[
        "winery"
    ],
    "wof:name":"Kilgour Estate Winery",
    "wof:placetype":"venue"
},
  "geometry": {"coordinates":[144.59071399999999,-38.133327],"type":"Point"}
}