{
  "type": "Feature",
  "properties": {
    "iso:country":"AU",
    "sg:address":"35 Walsh Ave",
    "sg:city":"Castle Hill",
    "sg:classifiers":[
        {
            "category":"Education",
            "subcategory":"Kindergarten",
            "type":"Public Place"
        }
    ],
    "sg:phone":"+61 2 9680 1941",
    "sg:postcode":"2154",
    "sg:province":"NSW",
    "sg:tags":[
        "pre-schools"
    ],
    "wof:name":"Aacooloma Pre-School",
    "wof:placetype":"venue"
},
  "geometry": {"coordinates":[151.01084899899999,-33.7416000366],"type":"Point"}
}