{
  "type": "Feature",
  "properties": {
    "addr:full":"10 Hastings Ave Burton SA 5110",
    "addr:housenumber":"10",
    "addr:postcode":"5110",
    "addr:street":"Hastings Ave",
    "iso:country":"AU",
    "sg:address":"10 Hastings Ave",
    "sg:city":"Burton",
    "sg:classifiers":[
        {
            "category":"Retail",
            "subcategory":"Auto Repair",
            "type":"Services"
        }
    ],
    "sg:phone":"+61 400 290 363",
    "sg:postcode":"5110",
    "sg:province":"SA",
    "sg:tags":[
        "beater",
        "painter",
        "panel"
    ],
    "wof:name":"Adelaide Vehicle Refinishing",
    "wof:placetype":"venue"
},
  "geometry": {"coordinates":[138.603683472,-34.7492218018],"type":"Point"}
}