{
  "type": "Feature",
  "properties": {
    "addr:full":"3 Natalie Crt Cranbourne VIC 3977",
    "addr:housenumber":"3",
    "addr:postcode":"3977",
    "addr:street":"Natalie Crt",
    "iso:country":"AU",
    "sg:address":"3 Natalie Crt",
    "sg:city":"Cranbourne",
    "sg:classifiers":[
        {
            "category":"Retail",
            "subcategory":"Driving School",
            "type":"Services"
        }
    ],
    "sg:phone":"+61 1800 447 788",
    "sg:postcode":"3977",
    "sg:province":"VIC",
    "wof:name":"EMECC",
    "wof:placetype":"venue"
},
  "geometry": {"coordinates":[145.257568359,-38.1032562256],"type":"Point"}
}