{
  "type": "Feature",
  "properties": {
    "addr:full":"8 Sutherland Rd Chatswood NSW 2067",
    "addr:housenumber":"8",
    "addr:postcode":"2067",
    "addr:street":"Sutherland Rd",
    "iso:country":"AU",
    "sg:address":"8 Sutherland Rd",
    "sg:city":"Chatswood",
    "sg:classifiers":[
        {
            "category":"Health Services",
            "subcategory":"Doctor",
            "type":"Services"
        }
    ],
    "sg:phone":"+61 2 9419 3659",
    "sg:postcode":"2067",
    "sg:province":"NSW",
    "sg:tags":[
        "medical",
        "practitioner"
    ],
    "wof:name":"Winter E Dr",
    "wof:placetype":"venue"
},
  "geometry": {"coordinates":[151.178787231,-33.8022994995],"type":"Point"}
}