{
  "type": "Feature",
  "properties": {
    "iso:country":"AU",
    "sg:address":"438 South Arm Rd",
    "sg:city":"Lauderdale",
    "sg:classifiers":[
        {
            "category":"Farming",
            "subcategory":"Nursery",
            "type":"Manufacturing & Wholesale Goods"
        }
    ],
    "sg:phone":"+61 3 6248 7748",
    "sg:postcode":"7021",
    "sg:province":"TAS",
    "wof:name":"C.J. Garden Supplies",
    "wof:placetype":"venue"
},
  "geometry": {"coordinates":[147.47994995100001,-42.9063682556],"type":"Point"}
}