{
  "type": "Feature",
  "properties": {
    "addr:full":"28a Florence St Mentone VIC 3194",
    "addr:housenumber":"28a",
    "addr:postcode":"3194",
    "addr:street":"Florence St",
    "iso:country":"AU",
    "sg:address":"28a Florence St",
    "sg:city":"Mentone",
    "sg:classifiers":[
        {
            "category":"Building & Trades",
            "subcategory":"Cleaning & Sanitation",
            "type":"Services"
        }
    ],
    "sg:phone":"+61 3 9585 2888",
    "sg:postcode":"3194",
    "sg:province":"VIC",
    "sg:tags":[
        "chemical",
        "pressure",
        "steam",
        "contractor"
    ],
    "wof:name":"CorpCom Cleaning",
    "wof:placetype":"venue"
},
  "geometry": {"coordinates":[145.062744141,-37.9826927185],"type":"Point"}
}