{
  "type": "Feature",
  "properties": {
    "addr:full":"PO Box 1970 Dee Why NSW 2099",
    "addr:postcode":"2099",
    "iso:country":"AU",
    "sg:address":"PO Box 1970",
    "sg:city":"Dee Why",
    "sg:classifiers":[
        {
            "category":"Education",
            "subcategory":"Special Training",
            "type":"Public Place"
        }
    ],
    "sg:phone":"+61 437 776 348",
    "sg:postcode":"2099",
    "sg:province":"NSW",
    "sg:tags":[
        "development"
    ],
    "wof:name":"Smart Bill Folder",
    "wof:placetype":"venue"
},
  "geometry": {"coordinates":[151.285232544,-33.7537498474],"type":"Point"}
}