{
  "type": "Feature",
  "properties": {
    "iso:country":"AU",
    "sg:address":"159 Taylor St",
    "sg:city":"Toowoomba",
    "sg:classifiers":[
        {
            "category":"Transit Center",
            "subcategory":"Freight",
            "type":"Transportation"
        }
    ],
    "sg:phone":"+61 7 4634 2173",
    "sg:postcode":"4350",
    "sg:province":"QLD",
    "sg:tags":[
        "honey",
        "merchant"
    ],
    "wof:name":"Frank & Jan Flynn",
    "wof:placetype":"venue"
},
  "geometry": {"coordinates":[151.913605,-27.551443],"type":"Point"}
}