{
  "type": "Feature",
  "properties": {
    "addr:full":"90 Third Rd Armadale WA 6112",
    "addr:housenumber":"90",
    "addr:postcode":"6112",
    "addr:street":"Third Rd",
    "iso:country":"AU",
    "sg:address":"90 Third Rd",
    "sg:city":"Armadale",
    "sg:classifiers":[
        {
            "category":"Communications",
            "subcategory":"Film & Video Production",
            "type":"Services"
        }
    ],
    "sg:phone":"+61 8 9399 2704",
    "sg:postcode":"6112",
    "sg:province":"WA",
    "sg:tags":[
        "dvd",
        "library"
    ],
    "wof:name":"Civic Video Pty Ltd",
    "wof:placetype":"venue"
},
  "geometry": {"coordinates":[116.01689148,-32.153881073],"type":"Point"}
}