{
  "type": "Feature",
  "properties": {
    "addr:full":"Shop 2, 30 Main St Ellenbrook WA 6069",
    "addr:housenumber":"shop;30",
    "addr:postcode":"6069",
    "addr:street":"Main St",
    "iso:country":"AU",
    "sg:address":"Shop 2, 30 Main St",
    "sg:city":"Ellenbrook",
    "sg:classifiers":[
        {
            "category":"Banks & Credit Unions",
            "subcategory":"Financial Services",
            "type":"Services"
        }
    ],
    "sg:phone":"+61 8 9296 8717",
    "sg:postcode":"6069",
    "sg:province":"WA",
    "sg:tags":[
        "settlement",
        "nt",
        "agent",
        "wa"
    ],
    "wof:name":"KDD Conveyancing Services",
    "wof:placetype":"venue"
},
  "geometry": {"coordinates":[115.96611023,-31.7852649689],"type":"Point"}
}