{
  "type": "Feature",
  "properties": {
    "addr:full":"Fcty 3, 21-23 Marshall Rd Kirrawee NSW 2232",
    "addr:housenumber":"21-23",
    "addr:postcode":"2232",
    "addr:street":"Marshall Rd",
    "iso:country":"AU",
    "sg:address":"Fcty 3, 21-23 Marshall Rd",
    "sg:city":"Kirrawee",
    "sg:classifiers":[
        {
            "category":"Professional",
            "subcategory":"Engineering",
            "type":"Services"
        }
    ],
    "sg:phone":"+61 2 9545 1073",
    "sg:postcode":"2232",
    "sg:province":"NSW",
    "sg:tags":[
        "manufacturing",
        "engineer"
    ],
    "wof:name":"Bosa Manufacturing Pty Ltd",
    "wof:placetype":"venue"
},
  "geometry": {"coordinates":[151.08108520499999,-34.0254249573],"type":"Point"}
}