{
  "type": "Feature",
  "properties": {
    "addr:full":"292 Hancock St Doubleview WA 6018",
    "addr:housenumber":"292",
    "addr:postcode":"6018",
    "addr:street":"Hancock St",
    "iso:country":"AU",
    "sg:address":"292 Hancock St",
    "sg:city":"Doubleview",
    "sg:classifiers":[
        {
            "category":"Home & Garden",
            "subcategory":"Building Materials",
            "type":"Retail Goods"
        }
    ],
    "sg:phone":"+61 403 052 780",
    "sg:postcode":"6018",
    "sg:province":"WA",
    "sg:tags":[
        "lawn",
        "cutting",
        "maintenance"
    ],
    "wof:name":"Cutting Edge Lawn Mowing",
    "wof:placetype":"venue"
},
  "geometry": {"coordinates":[115.780181885,-31.898979187],"type":"Point"}
}