{
  "type": "Feature",
  "properties": {
    "addr:full":"11 Nugent St Balcatta WA 6021",
    "addr:housenumber":"11",
    "addr:postcode":"6021",
    "addr:street":"Nugent St",
    "iso:country":"AU",
    "sg:address":"11 Nugent St",
    "sg:city":"Balcatta",
    "sg:classifiers":[
        {
            "category":"Travel",
            "subcategory":"Hostel",
            "type":"Entertainment"
        }
    ],
    "sg:phone":"+61 8 9207 4666",
    "sg:postcode":"6021",
    "sg:province":"WA",
    "sg:tags":[
        "home"
    ],
    "wof:name":"MYVISTA",
    "wof:placetype":"venue"
},
  "geometry": {"coordinates":[115.827529907,-31.8664302826],"type":"Point"}
}