{
  "type": "Feature",
  "properties": {
    "addr:full":"19 Beaconsfield St Margate QLD 4019",
    "addr:housenumber":"19",
    "addr:postcode":"4019",
    "addr:street":"Beaconsfield St",
    "iso:country":"AU",
    "sg:address":"19 Beaconsfield St",
    "sg:city":"Margate",
    "sg:classifiers":[
        {
            "category":"Utilities",
            "subcategory":"Electric",
            "type":"Services"
        }
    ],
    "sg:phone":"+61 7 3283 1294",
    "sg:postcode":"4019",
    "sg:province":"QLD",
    "sg:tags":[
        "electrical",
        "contractor"
    ],
    "wof:name":"Natoli Electrical",
    "wof:placetype":"venue"
},
  "geometry": {"coordinates":[153.10824585,-27.242521286],"type":"Point"}
}