{
  "type": "Feature",
  "properties": {
    "iso:country":"AU",
    "sg:address":"PO Box 420",
    "sg:city":"Wollongong",
    "sg:classifiers":[
        {
            "category":"Social Services",
            "subcategory":"Retirement Home",
            "type":"Services"
        }
    ],
    "sg:phone":"+61 2 4228 8668",
    "sg:postcode":"2520",
    "sg:province":"NSW",
    "sg:tags":[
        "environmental",
        "consultant",
        "pollution"
    ],
    "wof:name":"QED Pty Ltd",
    "wof:placetype":"venue"
},
  "geometry": {"coordinates":[150.89982605,-34.4258804321],"type":"Point"}
}