{
  "type": "Feature",
  "properties": {
    "addr:full":"Lot 152 Bakers Rd Grandchester QLD 4340",
    "addr:postcode":"4340",
    "addr:street":"Bakers Rd",
    "iso:country":"AU",
    "sg:address":"Lot 152 Bakers Rd",
    "sg:city":"Grandchester",
    "sg:classifiers":[
        {
            "category":"Train Station",
            "subcategory":"Rail",
            "type":"Transportation"
        }
    ],
    "sg:phone":"+61 7 5465 5267",
    "sg:postcode":"4340",
    "sg:province":"QLD",
    "sg:tags":[
        "goat",
        "farmer"
    ],
    "wof:name":"Brendanvale Goat Stud",
    "wof:placetype":"venue"
},
  "geometry": {"coordinates":[152.45245361299999,-27.6873321533],"type":"Point"}
}