{
  "type": "Feature",
  "properties": {
    "addr:full":"Ste 1 Lvl 10, 16-20 Barrack St Sydney NSW 2000",
    "addr:housenumber":"16-20",
    "addr:postcode":"2000",
    "addr:street":"Barrack St",
    "iso:country":"AU",
    "sg:address":"Ste 1 Lvl 10, 16-20 Barrack St",
    "sg:city":"Sydney",
    "sg:classifiers":[
        {
            "category":"Health Services",
            "subcategory":"Health Practitioner",
            "type":"Services"
        }
    ],
    "sg:phone":"+61 2 9299 1311",
    "sg:postcode":"2000",
    "sg:province":"NSW",
    "sg:tags":[
        "naturopath"
    ],
    "sg:website":"http://www.cbdnaturalhealth.com.au",
    "wof:name":"CBD Health & Medical Centre",
    "wof:placetype":"venue"
},
  "geometry": {"coordinates":[151.20651245100001,-33.8675384521],"type":"Point"}
}