{
  "type": "Feature",
  "properties": {
    "addr:full":"Shop 4 Forrestfield Forum Shopping Centre Forrestfield WA 6058",
    "addr:housenumber":"shop 4",
    "addr:postcode":"6058",
    "iso:country":"AU",
    "sg:address":"Shop 4 Forrestfield Forum Shopping Centre",
    "sg:city":"Forrestfield",
    "sg:classifiers":[
        {
            "category":"Shopping",
            "subcategory":"Clothing, Apparel, & Fashions",
            "type":"Retail Goods"
        }
    ],
    "sg:phone":"+61 8 9453 1550",
    "sg:postcode":"6058",
    "sg:province":"WA",
    "sg:tags":[
        "lady",
        "wear"
    ],
    "wof:name":"Dawns Fashion Boutique",
    "wof:placetype":"venue"
},
  "geometry": {"coordinates":[116.00077819800001,-31.9696292877],"type":"Point"}
}