{
  "type": "Feature",
  "properties": {
    "addr:full":"Unit 5/ 308 Industrial Drv Lemon Tree Passage NSW 2319",
    "addr:housenumber":"/ 308",
    "addr:postcode":"2319",
    "addr:street":"Industrial Drv",
    "iso:country":"AU",
    "sg:address":"Unit 5/ 308 Industrial Drv",
    "sg:city":"Lemon Tree Passage",
    "sg:classifiers":[
        {
            "category":"Building & Trades",
            "subcategory":"Construction",
            "type":"Services"
        }
    ],
    "sg:phone":"+61 2 4982 3788",
    "sg:postcode":"2319",
    "sg:province":"NSW",
    "sg:tags":[
        "contractor"
    ],
    "wof:name":"Kawarren Homes Pty Ltd",
    "wof:placetype":"venue"
},
  "geometry": {"coordinates":[152.03080700000001,-32.732063],"type":"Point"}
}