{
  "type": "Feature",
  "properties": {
    "addr:full":"19 Trigg Rd Chittaway Bay NSW 2261",
    "addr:housenumber":"19",
    "addr:postcode":"2261",
    "addr:street":"Trigg Rd",
    "iso:country":"AU",
    "sg:address":"19 Trigg Rd",
    "sg:city":"Chittaway Bay",
    "sg:classifiers":[
        {
            "category":"Professional",
            "subcategory":"Art Services",
            "type":"Services"
        }
    ],
    "sg:phone":"+61 2 4388 5573",
    "sg:postcode":"2261",
    "sg:province":"NSW",
    "sg:tags":[
        "decorator",
        "painter"
    ],
    "wof:name":"Gwen Butler",
    "wof:placetype":"venue"
},
  "geometry": {"coordinates":[151.43937700000001,-33.3298],"type":"Point"}
}