{
  "type": "Feature",
  "properties": {
    "addr:full":"8 Beverley Ave Warilla NSW 2528",
    "addr:housenumber":"8",
    "addr:postcode":"2528",
    "addr:street":"Beverley Ave",
    "iso:country":"AU",
    "sg:address":"8 Beverley Ave",
    "sg:city":"Warilla",
    "sg:classifiers":[
        {
            "category":"Banks & Credit Unions",
            "subcategory":"Financial Services",
            "type":"Services"
        }
    ],
    "sg:phone":"+61 2 4296 1116",
    "sg:postcode":"2528",
    "sg:province":"NSW",
    "sg:tags":[
        "loan",
        "finance",
        "mortgage"
    ],
    "wof:name":"South Coast Finance",
    "wof:placetype":"venue"
},
  "geometry": {"coordinates":[150.861450195,-34.5516357422],"type":"Point"}
}