{
  "type": "Feature",
  "properties": {
    "addr:full":"Laver St Newman WA 6753",
    "addr:postcode":"6753",
    "addr:street":"Laver St",
    "iso:country":"AU",
    "sg:address":"Laver St",
    "sg:city":"Newman",
    "sg:classifiers":[
        {
            "category":"Professional",
            "type":"Services"
        }
    ],
    "sg:phone":"+61 8 9177 8030",
    "sg:postcode":"6753",
    "sg:province":"WA",
    "sg:tags":[
        "courier"
    ],
    "wof:name":"Overnighters The",
    "wof:placetype":"venue"
},
  "geometry": {"coordinates":[119.733543396,-23.3673820496],"type":"Point"}
}