{
  "type": "Feature",
  "properties": {
    "iso:country":"AU",
    "sg:address":"240 Bloomfield St",
    "sg:city":"Cleveland",
    "sg:classifiers":[
        {
            "category":"Shopping",
            "subcategory":"Computers & Home Electronics",
            "type":"Retail Goods"
        }
    ],
    "sg:phone":"+61 7 3821 3344",
    "sg:postcode":"4163",
    "sg:province":"QLD",
    "sg:tags":[
        "equipment",
        "multimedia"
    ],
    "wof:name":"Mission Studios",
    "wof:placetype":"venue"
},
  "geometry": {"coordinates":[153.26670837399999,-27.535358429],"type":"Point"}
}