{
  "type": "Feature",
  "properties": {
    "addr:full":"32 Collings St Pearce ACT 2607",
    "addr:housenumber":"32",
    "addr:postcode":"2607",
    "addr:street":"Collings St",
    "iso:country":"AU",
    "sg:address":"32 Collings St",
    "sg:city":"Pearce",
    "sg:classifiers":[
        {
            "category":"Retail",
            "subcategory":"Auto Rental",
            "type":"Services"
        }
    ],
    "sg:phone":"+61 2 6295 0796",
    "sg:postcode":"2607",
    "sg:province":"ACT",
    "sg:tags":[
        "car",
        "hire",
        "minibus"
    ],
    "wof:name":"LDI Car Rentals",
    "wof:placetype":"venue"
},
  "geometry": {"coordinates":[149.081130981,-35.3591690063],"type":"Point"}
}