{
  "type": "Feature",
  "properties": {
    "addr:full":"3 Weigand Ave Bankstown NSW 2200",
    "addr:housenumber":"3",
    "addr:postcode":"2200",
    "addr:street":"Weigand Ave",
    "iso:country":"AU",
    "sg:address":"3 Weigand Ave",
    "sg:city":"Bankstown",
    "sg:classifiers":[
        {
            "category":"Health Services",
            "subcategory":"Doctor",
            "type":"Services"
        }
    ],
    "sg:phone":"+61 2 9708 6078",
    "sg:postcode":"2200",
    "sg:province":"NSW",
    "sg:tags":[
        "medical",
        "practitioner"
    ],
    "wof:name":"Voutos P",
    "wof:placetype":"venue"
},
  "geometry": {"coordinates":[151.029404,-33.916832],"type":"Point"}
}