{
  "type": "Feature",
  "properties": {
    "addr:full":"4 Yardley St North Hobart TAS 7000",
    "addr:housenumber":"4",
    "addr:postcode":"7000",
    "addr:street":"Yardley St",
    "iso:country":"AU",
    "sg:address":"4 Yardley St",
    "sg:city":"North Hobart",
    "sg:classifiers":[
        {
            "category":"Home & Garden",
            "subcategory":"Building Materials",
            "type":"Retail Goods"
        }
    ],
    "sg:phone":"+61 3 6234 3797",
    "sg:postcode":"7000",
    "sg:province":"TAS",
    "sg:tags":[
        "lawn",
        "cutting",
        "maintenance"
    ],
    "wof:name":"Gnome Mowing",
    "wof:placetype":"venue"
},
  "geometry": {"coordinates":[147.31568908700001,-42.8700637817],"type":"Point"}
}