{
  "type": "Feature",
  "properties": {
    "addr:full":"8/ 23 Glenaffric St The Gap QLD 4061",
    "addr:housenumber":"/ 23",
    "addr:postcode":"4061",
    "addr:street":"Glenaffric St",
    "iso:country":"AU",
    "sg:address":"8/ 23 Glenaffric St",
    "sg:city":"The Gap",
    "sg:classifiers":[
        {
            "category":"Professional",
            "subcategory":"Accounting & Tax Preparation",
            "type":"Services"
        }
    ],
    "sg:phone":"+61 7 3300 4633",
    "sg:postcode":"4061",
    "sg:province":"QLD",
    "sg:tags":[
        "accountant",
        "auditor"
    ],
    "wof:name":"Irwin & Associates Pty",
    "wof:placetype":"venue"
},
  "geometry": {"coordinates":[152.953613281,-27.4460029602],"type":"Point"}
}