{
  "type": "Feature",
  "properties": {
    "addr:full":"2 Outlook Drv Glass House Mountains QLD 4518",
    "addr:housenumber":"2",
    "addr:postcode":"4518",
    "addr:street":"Outlook Drv",
    "iso:country":"AU",
    "sg:address":"2 Outlook Drv",
    "sg:city":"Glass House Mountains",
    "sg:classifiers":[
        {
            "category":"Utilities",
            "subcategory":"Electric",
            "type":"Services"
        }
    ],
    "sg:phone":"+61 7 5493 0809",
    "sg:postcode":"4518",
    "sg:province":"QLD",
    "sg:tags":[
        "electrical",
        "contractor"
    ],
    "wof:name":"A D K Electrical",
    "wof:placetype":"venue"
},
  "geometry": {"coordinates":[152.94108581500001,-26.9072666168],"type":"Point"}
}