{
  "type": "Feature",
  "properties": {
    "addr:full":"Unit 15, 92 Beechboro Rd Bayswater WA 6053",
    "addr:housenumber":"92",
    "addr:postcode":"6053",
    "addr:street":"Beechboro Rd",
    "iso:country":"AU",
    "sg:address":"Unit 15, 92 Beechboro Rd",
    "sg:city":"Bayswater",
    "sg:classifiers":[
        {
            "category":"Building & Trades",
            "subcategory":"Construction",
            "type":"Services"
        }
    ],
    "sg:phone":"+61 8 9271 6898",
    "sg:postcode":"6053",
    "sg:province":"WA",
    "sg:tags":[
        "welding"
    ],
    "wof:name":"A Endee Metals",
    "wof:placetype":"venue"
},
  "geometry": {"coordinates":[115.91394805900001,-31.908159256],"type":"Point"}
}