{
  "type": "Feature",
  "properties": {
    "addr:full":"91 Merrylands Rd Merrylands NSW 2160",
    "addr:housenumber":"91",
    "addr:postcode":"2160",
    "addr:street":"Merrylands Rd",
    "iso:country":"AU",
    "sg:address":"91 Merrylands Rd",
    "sg:city":"Merrylands",
    "sg:classifiers":[
        {
            "category":"Professional",
            "subcategory":"Computer Services",
            "type":"Services"
        }
    ],
    "sg:phone":"+61 2 9637 6122",
    "sg:postcode":"2160",
    "sg:province":"NSW",
    "sg:tags":[
        "tele-communications",
        "consultant"
    ],
    "wof:name":"Technical Support Equipment Pty Ltd",
    "wof:placetype":"venue"
},
  "geometry": {"coordinates":[150.99288940400001,-33.8369598389],"type":"Point"}
}