{
  "type": "Feature",
  "properties": {
    "iso:country":"AU",
    "sg:address":"123 George St",
    "sg:city":"Hurstville",
    "sg:classifiers":[
        {
            "category":"Utilities",
            "subcategory":"Electric",
            "type":"Services"
        }
    ],
    "sg:phone":"+61 419 620 935",
    "sg:postcode":"2220",
    "sg:province":"NSW",
    "sg:tags":[
        "electrical",
        "contractor"
    ],
    "wof:name":"SBB Electrical",
    "wof:placetype":"venue"
},
  "geometry": {"coordinates":[151.112182617,-33.9776916504],"type":"Point"}
}