{
  "type": "Feature",
  "properties": {
    "addr:full":"Shop 8 Arndale Centre 224 Mt. Dandenong Rd Croydon VIC 3136",
    "addr:housenumber":"shop 8;224",
    "addr:postcode":"3136",
    "addr:street":"Arndale Centre;Mt. Dandenong Rd",
    "iso:country":"AU",
    "sg:address":"Shop 8 Arndale Centre 224 Mt. Dandenong Rd",
    "sg:city":"Croydon",
    "sg:classifiers":[
        {
            "category":"Shopping",
            "subcategory":"Optical Goods",
            "type":"Retail Goods"
        }
    ],
    "sg:phone":"+61 3 9723 0811",
    "sg:postcode":"3136",
    "sg:province":"VIC",
    "sg:tags":[
        "dispenser",
        "prescription"
    ],
    "wof:name":"Australian Eyecare",
    "wof:placetype":"venue"
},
  "geometry": {"coordinates":[145.28520202600001,-37.7992324829],"type":"Point"}
}