{
  "type": "Feature",
  "properties": {
    "iso:country":"AU",
    "sg:address":"15 MacKerras Crs",
    "sg:city":"Theodore",
    "sg:classifiers":[
        {
            "category":"Arena",
            "subcategory":"Sports Club",
            "type":"Entertainment"
        }
    ],
    "sg:phone":"+61 2 6292 7024",
    "sg:postcode":"2905",
    "sg:province":"ACT",
    "sg:tags":[
        "defence",
        "supply",
        "self",
        "instruction",
        "martial art"
    ],
    "wof:name":"Australian Capital Taekwondo",
    "wof:placetype":"venue"
},
  "geometry": {"coordinates":[149.124557495,-35.4470710754],"type":"Point"}
}