{
  "type": "Feature",
  "properties": {
    "iso:country":"AU",
    "sg:address":"Lv 20/ 99 Walker St",
    "sg:city":"North Sydney",
    "sg:classifiers":[
        {
            "category":"Education",
            "subcategory":"Special Training",
            "type":"Public Place"
        }
    ],
    "sg:phone":"+61 2 9657 1060",
    "sg:postcode":"2055",
    "sg:province":"NSW",
    "sg:tags":[
        "development"
    ],
    "wof:name":"Tauri Consulting",
    "wof:placetype":"venue"
},
  "geometry": {"coordinates":[151.208786,-33.839893],"type":"Point"}
}