{
  "type": "Feature",
  "properties": {
    "addr:full":"54 Powell St Bowen QLD 4805",
    "addr:housenumber":"54",
    "addr:postcode":"4805",
    "addr:street":"Powell St",
    "iso:country":"AU",
    "sg:address":"54 Powell St",
    "sg:city":"Bowen",
    "sg:classifiers":[
        {
            "category":"Health Services",
            "subcategory":"Doctor",
            "type":"Services"
        }
    ],
    "sg:phone":"+61 7 4786 1711",
    "sg:postcode":"4805",
    "sg:province":"QLD",
    "sg:tags":[
        "medical",
        "practitioner"
    ],
    "wof:name":"Cairncross D J",
    "wof:placetype":"venue"
},
  "geometry": {"coordinates":[148.24105835,-20.0149173737],"type":"Point"}
}