{
  "type": "Feature",
  "properties": {
    "iso:country":"AU",
    "sg:address":"284 Victoria Rd",
    "sg:city":"Malaga",
    "sg:classifiers":[
        {
            "category":"Shopping",
            "subcategory":"Crafts & Fabrics",
            "type":"Retail Goods"
        }
    ],
    "sg:phone":"+61 8 9249 3755",
    "sg:postcode":"6090",
    "sg:province":"WA",
    "sg:tags":[
        "adhesive"
    ],
    "wof:name":"Henkel Adhesives",
    "wof:placetype":"venue"
},
  "geometry": {"coordinates":[115.889541626,-31.8616752625],"type":"Point"}
}