{
  "type": "Feature",
  "properties": {
    "addr:full":"3 Edmonds Ave Ashwood VIC 3147",
    "addr:housenumber":"3",
    "addr:postcode":"3147",
    "addr:street":"Edmonds Ave",
    "iso:country":"AU",
    "sg:address":"3 Edmonds Ave",
    "sg:city":"Ashwood",
    "sg:classifiers":[
        {
            "category":"Professional",
            "subcategory":"Computer Services",
            "type":"Services"
        }
    ],
    "sg:phone":"+61 3 9886 9327",
    "sg:postcode":"3147",
    "sg:province":"VIC",
    "sg:tags":[
        "consultant",
        "system"
    ],
    "wof:name":"Lan Directions Pty Ltd",
    "wof:placetype":"venue"
},
  "geometry": {"coordinates":[145.09397888199999,-37.8616638184],"type":"Point"}
}