{
  "type": "Feature",
  "properties": {
    "addr:full":"134 Baillie St Horsham VIC 3402",
    "addr:housenumber":"134",
    "addr:postcode":"3402",
    "addr:street":"Baillie St",
    "iso:country":"AU",
    "sg:address":"134 Baillie St",
    "sg:city":"Horsham",
    "sg:classifiers":[
        {
            "category":"Health Services",
            "subcategory":"Health Practitioner",
            "type":"Services"
        }
    ],
    "sg:phone":"+61 407 818 854",
    "sg:postcode":"3402",
    "sg:province":"VIC",
    "sg:tags":[
        "alternative"
    ],
    "wof:name":"Shen Loong Acupuncture",
    "wof:placetype":"venue"
},
  "geometry": {"coordinates":[142.20152282699999,-36.7116012573],"type":"Point"}
}