{
  "type": "Feature",
  "properties": {
    "iso:country":"AU",
    "sg:address":"24 Durrant St",
    "sg:city":"Brighton",
    "sg:classifiers":[
        {
            "category":"Banks & Credit Unions",
            "subcategory":"Investment Brokerage",
            "type":"Services"
        }
    ],
    "sg:phone":"+61 3 9530 5441",
    "sg:postcode":"3186",
    "sg:province":"VIC",
    "sg:tags":[
        "debt",
        "collection"
    ],
    "wof:name":"Victorian Debt Collection Agency",
    "wof:placetype":"venue"
},
  "geometry": {"coordinates":[145.002883911,-37.908821106],"type":"Point"}
}