{
  "type": "Feature",
  "properties": {
    "addr:full":"87 Foleys Rd Woombye QLD 4559",
    "addr:housenumber":"87",
    "addr:postcode":"4559",
    "addr:street":"Foleys Rd",
    "iso:country":"AU",
    "sg:address":"87 Foleys Rd",
    "sg:city":"Woombye",
    "sg:phone":"+61 7 5442 1409",
    "sg:postcode":"4559",
    "sg:province":"QLD",
    "wof:name":"Foleys Tanks",
    "wof:placetype":"venue"
},
  "geometry": {"coordinates":[152.966598511,-26.65275383],"type":"Point"}
}