{
  "type": "Feature",
  "properties": {
    "addr:full":"243 Smith St Fitzroy VIC 3065",
    "addr:housenumber":"243",
    "addr:postcode":"3065",
    "addr:street":"Smith St",
    "iso:country":"AU",
    "sg:address":"243 Smith St",
    "sg:city":"Fitzroy",
    "sg:classifiers":[
        {
            "category":"Food & Beverages",
            "subcategory":"Liquor & Beverages",
            "type":"Retail Goods"
        }
    ],
    "sg:phone":"+61 3 9419 0488",
    "sg:postcode":"3065",
    "sg:province":"VIC",
    "sg:tags":[
        "store"
    ],
    "wof:name":"Safeway Liquor",
    "wof:placetype":"venue"
},
  "geometry": {"coordinates":[144.98365783700001,-37.8015975952],"type":"Point"}
}