{
  "type": "Feature",
  "properties": {
    "iso:country":"AU",
    "sg:address":"Unit 32/ 130 Plateau Crs",
    "sg:city":"Carrara",
    "sg:classifiers":[
        {
            "category":"Utilities",
            "subcategory":"Mobile Phone",
            "type":"Services"
        }
    ],
    "sg:phone":"+61 7 5594 5404",
    "sg:postcode":"4211",
    "sg:province":"QLD",
    "sg:tags":[
        "repair",
        "telephone"
    ],
    "wof:name":"South East Telecommunications",
    "wof:placetype":"venue"
},
  "geometry": {"coordinates":[153.36398315400001,-28.0106391907],"type":"Point"}
}