{
  "type": "Feature",
  "properties": {
    "addr:full":"26 Woongool Rd Maryborough QLD 4650",
    "addr:housenumber":"26",
    "addr:postcode":"4650",
    "addr:street":"Woongool Rd",
    "iso:country":"AU",
    "sg:address":"26 Woongool Rd",
    "sg:city":"Maryborough",
    "sg:classifiers":[
        {
            "category":"Building & Trades",
            "subcategory":"Plumbing",
            "type":"Services"
        }
    ],
    "sg:phone":"+61 7 4122 1905",
    "sg:postcode":"4650",
    "sg:province":"QLD",
    "sg:tags":[
        "plumber",
        "gasfitters"
    ],
    "wof:name":"Murray Barnett Plumbing",
    "wof:placetype":"venue"
},
  "geometry": {"coordinates":[152.706909,-25.568123],"type":"Point"}
}