{
  "type": "Feature",
  "properties": {
    "iso:country":"AU",
    "sg:address":"PO Box 5",
    "sg:city":"Henley Beach",
    "sg:classifiers":[
        {
            "category":"Social Services",
            "type":"Services"
        }
    ],
    "sg:phone":"+61 8 8353 2311",
    "sg:postcode":"5022",
    "sg:province":"SA",
    "sg:tags":[
        "disabled",
        "person",
        "equipment"
    ],
    "wof:name":"Smart Control Systems",
    "wof:placetype":"venue"
},
  "geometry": {"coordinates":[138.49435424800001,-34.9197387695],"type":"Point"}
}