{
  "type": "Feature",
  "properties": {
    "iso:country":"AU",
    "sg:address":"\"Waykup Farm\" Griffiths Rd",
    "sg:city":"Scaddan West",
    "sg:classifiers":[
        {
            "category":"Farming",
            "subcategory":"Farm",
            "type":"Manufacturing & Wholesale Goods"
        }
    ],
    "sg:phone":"+61 8 9078 6026",
    "sg:postcode":"6447",
    "sg:province":"WA",
    "sg:tags":[
        "farmer"
    ],
    "wof:name":"Henderson J J & R M",
    "wof:placetype":"venue"
},
  "geometry": {"coordinates":[121.700088501,-33.4809913635],"type":"Point"}
}