{
  "type": "Feature",
  "properties": {
    "iso:country":"AU",
    "sg:address":"Sports Pde",
    "sg:city":"Mt Isa",
    "sg:classifiers":[
        {
            "category":"Retail",
            "subcategory":"Event Space",
            "type":"Services"
        }
    ],
    "sg:phone":"+61 7 4743 5444",
    "sg:postcode":"4825",
    "sg:province":"QLD",
    "sg:tags":[
        "function",
        "organiser"
    ],
    "wof:name":"Mt Isa Recreation Centre",
    "wof:placetype":"venue"
},
  "geometry": {"coordinates":[139.51020800000001,-20.704535],"type":"Point"}
}