{
  "type": "Feature",
  "properties": {
    "addr:full":"1034 Doncaster Rd Doncaster East VIC 3109",
    "addr:housenumber":"1034",
    "addr:postcode":"3109",
    "addr:street":"Doncaster Rd",
    "iso:country":"AU",
    "sg:address":"1034 Doncaster Rd",
    "sg:city":"Doncaster East",
    "sg:classifiers":[
        {
            "category":"Health Services",
            "subcategory":"Health Practitioner",
            "type":"Services"
        }
    ],
    "sg:phone":"+61 3 9639 1113",
    "sg:postcode":"3109",
    "sg:province":"VIC",
    "sg:tags":[
        "audiologists"
    ],
    "wof:name":"Olayos William",
    "wof:placetype":"venue"
},
  "geometry": {"coordinates":[145.162963867,-37.7894477844],"type":"Point"}
}