{
  "type": "Feature",
  "properties": {
    "addr:full":"4-5/ 51to53 Power Rd Bayswater VIC 3153",
    "addr:housenumber":"4-5 / 51to53",
    "addr:postcode":"3153",
    "addr:street":"Power Rd",
    "iso:country":"AU",
    "sg:address":"4-5/ 51to53 Power Rd",
    "sg:city":"Bayswater",
    "sg:classifiers":[
        {
            "category":"Shopping",
            "subcategory":"Computers & Home Electronics",
            "type":"Retail Goods"
        }
    ],
    "sg:phone":"+61 3 9763 6333",
    "sg:postcode":"3153",
    "sg:province":"VIC",
    "sg:tags":[
        "equipment",
        "part",
        "electronic"
    ],
    "wof:name":"E- Max International Pty ltd",
    "wof:placetype":"venue"
},
  "geometry": {"coordinates":[145.27096557600001,-37.844165802],"type":"Point"}
}