{
  "type": "Feature",
  "properties": {
    "addr:full":"4 Coolibah Crs Ferny Hills QLD 4055",
    "addr:housenumber":"4",
    "addr:postcode":"4055",
    "addr:street":"Coolibah Crs",
    "iso:country":"AU",
    "sg:address":"4 Coolibah Crs",
    "sg:city":"Ferny Hills",
    "sg:classifiers":[
        {
            "category":"Retail",
            "subcategory":"Auto Repair",
            "type":"Services"
        }
    ],
    "sg:phone":"+61 412 192 772",
    "sg:postcode":"4055",
    "sg:province":"QLD",
    "sg:tags":[
        "clutch",
        "brake"
    ],
    "wof:name":"AMBM & Mobile Brake Service",
    "wof:placetype":"venue"
},
  "geometry": {"coordinates":[152.976394653,-27.4546031952],"type":"Point"}
}