{
  "type": "Feature",
  "properties": {
    "iso:country":"AU",
    "sg:address":"4 Freshwater Rd",
    "sg:city":"Jingili",
    "sg:classifiers":[
        {
            "category":"Health Services",
            "subcategory":"Health Practitioner",
            "type":"Services"
        }
    ],
    "sg:phone":"+61 8 8948 3344",
    "sg:postcode":"0810",
    "sg:province":"NT",
    "sg:tags":[
        "alternative"
    ],
    "wof:name":"True Self Natural Healing Centre",
    "wof:placetype":"venue"
},
  "geometry": {"coordinates":[130.87742614699999,-12.3916330338],"type":"Point"}
}