{
  "type": "Feature",
  "properties": {
    "addr:full":"25 Tongarra Drv Ocean Shores NSW 2483",
    "addr:housenumber":"25",
    "addr:postcode":"2483",
    "addr:street":"Tongarra Drv",
    "iso:country":"AU",
    "sg:address":"25 Tongarra Drv",
    "sg:city":"Ocean Shores",
    "sg:classifiers":[
        {
            "category":"Manufacturing",
            "subcategory":"Jewelry",
            "type":"Manufacturing & Wholesale Goods"
        }
    ],
    "sg:phone":"+61 2 6680 4046",
    "sg:postcode":"2483",
    "sg:province":"NSW",
    "sg:tags":[
        "mfrg",
        "jeweller"
    ],
    "wof:name":"Ocean Shores Jewellery Studio",
    "wof:placetype":"venue"
},
  "geometry": {"coordinates":[153.53315734899999,-28.5242443085],"type":"Point"}
}