{
  "type": "Feature",
  "properties": {
    "iso:country":"AU",
    "sg:address":"27 Valetta Rd",
    "sg:city":"Kidman Park",
    "sg:classifiers":[
        {
            "category":"Arena",
            "subcategory":"Sports Club",
            "type":"Entertainment"
        }
    ],
    "sg:phone":"+61 8 8416 6677",
    "sg:postcode":"5025",
    "sg:province":"SA",
    "sg:tags":[
        "organisation",
        "sporting"
    ],
    "wof:name":"Office For Recreation & Sport",
    "wof:placetype":"venue"
},
  "geometry": {"coordinates":[138.529907227,-34.9138374329],"type":"Point"}
}