{
  "type": "Feature",
  "properties": {
    "iso:country":"AU",
    "sg:address":"21 St James Ave",
    "sg:city":"Montrose",
    "sg:classifiers":[
        {
            "category":"Building & Trades",
            "subcategory":"Construction",
            "type":"Services"
        }
    ],
    "sg:phone":"+61 421 195 782",
    "sg:postcode":"3765",
    "sg:province":"VIC",
    "sg:tags":[
        "joiner",
        "carpenter"
    ],
    "wof:name":"J & S Home Renovations",
    "wof:placetype":"venue"
},
  "geometry": {"coordinates":[145.35516357399999,-37.8072662354],"type":"Point"}
}