{
  "type": "Feature",
  "properties": {
    "addr:full":"52 Victoria St Ballarat VIC 3350",
    "addr:housenumber":"52",
    "addr:postcode":"3350",
    "addr:street":"Victoria St",
    "iso:country":"AU",
    "sg:address":"52 Victoria St",
    "sg:city":"Ballarat",
    "sg:classifiers":[
        {
            "category":"Manufacturing",
            "subcategory":"Musical Instruments",
            "type":"Manufacturing & Wholesale Goods"
        }
    ],
    "sg:phone":"+61 3 5331 3122",
    "sg:postcode":"3350",
    "sg:province":"VIC",
    "sg:tags":[
        "repair",
        "maker"
    ],
    "wof:name":"Brenton Fyfield",
    "wof:placetype":"venue"
},
  "geometry": {"coordinates":[143.869034,-37.562511],"type":"Point"}
}