{
  "type": "Feature",
  "properties": {
    "addr:full":"PO Box 71 Crafers SA 5152",
    "addr:postcode":"5152",
    "iso:country":"AU",
    "sg:address":"PO Box 71",
    "sg:city":"Crafers",
    "sg:classifiers":[
        {
            "category":"Government",
            "subcategory":"Court House",
            "type":"Public Place"
        }
    ],
    "sg:phone":"+61 417 876 455",
    "sg:postcode":"5152",
    "sg:province":"SA",
    "sg:tags":[
        "personal",
        "marriage",
        "family",
        "counselling"
    ],
    "wof:name":"Arnaum Walkley Parenting Solutions",
    "wof:placetype":"venue"
},
  "geometry": {"coordinates":[138.70338439899999,-34.9972000122],"type":"Point"}
}