{
  "type": "Feature",
  "properties": {
    "addr:full":"1125 Argyle St Wilton NSW 2571",
    "addr:housenumber":"1125",
    "addr:postcode":"2571",
    "addr:street":"Argyle St",
    "iso:country":"AU",
    "sg:address":"1125 Argyle St",
    "sg:city":"Wilton",
    "sg:classifiers":[
        {
            "category":"Building & Trades",
            "subcategory":"Locksmith",
            "type":"Services"
        }
    ],
    "sg:phone":"+61 1300 136 804",
    "sg:postcode":"2571",
    "sg:province":"NSW",
    "sg:tags":[
        "lock"
    ],
    "wof:name":"Macarthur & Wollondilly Security Locksmiths",
    "wof:placetype":"venue"
},
  "geometry": {"coordinates":[150.70103454599999,-34.2409248352],"type":"Point"}
}