{
  "type": "Feature",
  "properties": {
    "iso:country":"AU",
    "sg:address":"PO Box 6100",
    "sg:city":"Dubbo West",
    "sg:classifiers":[
        {
            "category":"Farming",
            "subcategory":"Farm & Veterinary Services",
            "type":"Manufacturing & Wholesale Goods"
        }
    ],
    "sg:phone":"+61 2 6888 5289",
    "sg:postcode":"2830",
    "sg:province":"NSW",
    "sg:tags":[
        "contracting"
    ],
    "wof:name":"Kick Ass Contracting",
    "wof:placetype":"venue"
},
  "geometry": {"coordinates":[148.593093872,-32.2479705811],"type":"Point"}
}