{
  "type": "Feature",
  "properties": {
    "iso:country":"AU",
    "sg:address":"3 Aboukir St",
    "sg:city":"Dover Heights",
    "sg:classifiers":[
        {
            "category":"Shopping",
            "subcategory":"Stationery & Office Supplies",
            "type":"Retail Goods"
        }
    ],
    "sg:phone":"+61 2 9371 0944",
    "sg:postcode":"2030",
    "sg:province":"NSW",
    "sg:tags":[
        "packaging",
        "equipment",
        "sealing",
        "filling"
    ],
    "wof:name":"Gregorson & Co Pty Ltd",
    "wof:placetype":"venue"
},
  "geometry": {"coordinates":[151.281906128,-33.8750915527],"type":"Point"}
}