{
  "type": "Feature",
  "properties": {
    "iso:country":"AU",
    "sg:address":"92 Brewer Rd",
    "sg:city":"Maida Vale",
    "sg:classifiers":[
        {
            "category":"Retail",
            "subcategory":"Auto Repair",
            "type":"Services"
        }
    ],
    "sg:phone":"+61 8 9454 3694",
    "sg:postcode":"6057",
    "sg:province":"WA",
    "sg:tags":[
        "electrical"
    ],
    "wof:name":"Don's Mobile Auto Electrics",
    "wof:placetype":"venue"
},
  "geometry": {"coordinates":[116.016448975,-31.963054657],"type":"Point"}
}