{
  "type": "Feature",
  "properties": {
    "addr:full":"PO Box 673 Gosnells WA 6110",
    "addr:postcode":"6110",
    "iso:country":"AU",
    "sg:address":"PO Box 673",
    "sg:city":"Gosnells",
    "sg:classifiers":[
        {
            "category":"Building & Trades",
            "subcategory":"Pest Control",
            "type":"Services"
        }
    ],
    "sg:phone":"+61 1300 881 182",
    "sg:postcode":"6110",
    "sg:province":"WA",
    "wof:name":"A AA Western Pest Management",
    "wof:placetype":"venue"
},
  "geometry": {"coordinates":[116.008880615,-32.07862854],"type":"Point"}
}