{
  "type": "Feature",
  "properties": {
    "addr:full":"Cnr Textile St & Machinery Ave Warana QLD 4575",
    "addr:postcode":"4575",
    "addr:street":"Textile St &;Ave",
    "iso:country":"AU",
    "sg:address":"Cnr Textile St & Machinery Ave",
    "sg:city":"Warana",
    "sg:classifiers":[
        {
            "category":"Education",
            "subcategory":"Dance Studio",
            "type":"Public Place"
        }
    ],
    "sg:phone":"+61 402 530 634",
    "sg:postcode":"4575",
    "sg:province":"QLD",
    "sg:tags":[
        "venue",
        "tuition"
    ],
    "wof:name":"Fierce Studios",
    "wof:placetype":"venue"
},
  "geometry": {"coordinates":[153.12278699999999,-26.729773],"type":"Point"}
}