{
  "type": "Feature",
  "properties": {
    "addr:full":"7 Alfred Pl Melbourne VIC 3000",
    "addr:housenumber":"7",
    "addr:postcode":"3000",
    "addr:street":"Alfred Pl",
    "iso:country":"AU",
    "sg:address":"7 Alfred Pl",
    "sg:city":"Melbourne",
    "sg:classifiers":[
        {
            "category":"Restaurant",
            "type":"Food & Drink"
        }
    ],
    "sg:phone":"+61 3 9631 4000",
    "sg:postcode":"3000",
    "sg:province":"VIC",
    "wof:name":"Comme",
    "wof:placetype":"venue"
},
  "geometry": {"coordinates":[144.97000122099999,-37.8142127991],"type":"Point"}
}