{
  "type": "Feature",
  "properties": {
    "addr:full":"Kittyhawk La Parafield Airport SA 5106",
    "addr:postcode":"5106",
    "addr:street":"Kittyhawk La",
    "iso:country":"AU",
    "sg:address":"Kittyhawk La",
    "sg:city":"Parafield Airport",
    "sg:classifiers":[
        {
            "category":"Education",
            "subcategory":"Special Training",
            "type":"Public Place"
        }
    ],
    "sg:phone":"+61 8 8258 9182",
    "sg:postcode":"5106",
    "sg:province":"SA",
    "sg:tags":[
        "school",
        "flying"
    ],
    "wof:name":"TAFE SA Parafield Aviation Campus",
    "wof:placetype":"venue"
},
  "geometry": {"coordinates":[138.635727,-34.789593],"type":"Point"}
}