{
  "type": "Feature",
  "properties": {
    "addr:full":"339 Redbank Plains Rd Redbank Plains QLD 4301",
    "addr:housenumber":"339",
    "addr:postcode":"4301",
    "addr:street":"Redbank Plains Rd",
    "iso:country":"AU",
    "sg:address":"339 Redbank Plains Rd",
    "sg:city":"Redbank Plains",
    "sg:classifiers":[
        {
            "category":"Travel",
            "subcategory":"Hotels & Motels",
            "type":"Entertainment"
        }
    ],
    "sg:phone":"+61 7 3814 3144",
    "sg:postcode":"4301",
    "sg:province":"QLD",
    "sg:tags":[
        "pub"
    ],
    "wof:name":"Redbank Plains Tavern",
    "wof:placetype":"venue"
},
  "geometry": {"coordinates":[152.87272644000001,-27.6389484406],"type":"Point"}
}