{
  "type": "Feature",
  "properties": {
    "addr:full":"60 Ordish Rd Dandenong South VIC 3175",
    "addr:housenumber":"60",
    "addr:postcode":"3175",
    "addr:street":"Ordish Rd",
    "iso:country":"AU",
    "sg:address":"60 Ordish Rd",
    "sg:city":"Dandenong South",
    "sg:classifiers":[
        {
            "category":"Manufacturing",
            "subcategory":"Retail Goods",
            "type":"Manufacturing & Wholesale Goods"
        }
    ],
    "sg:phone":"+61 3 9706 5071",
    "sg:postcode":"3175",
    "sg:province":"VIC",
    "sg:tags":[
        "merchant",
        "tallow"
    ],
    "wof:name":"Argus Tallow Merchants Pty Ltd",
    "wof:placetype":"venue"
},
  "geometry": {"coordinates":[145.19317626899999,-38.0177574158],"type":"Point"}
}