{
  "type": "Feature",
  "properties": {
    "addr:full":"65 Pittwater Rd Gladesville NSW 2111",
    "addr:housenumber":"65",
    "addr:postcode":"2111",
    "addr:street":"Pittwater Rd",
    "iso:country":"AU",
    "sg:address":"65 Pittwater Rd",
    "sg:city":"Gladesville",
    "sg:classifiers":[
        {
            "category":"Professional",
            "subcategory":"Engineering",
            "type":"Services"
        }
    ],
    "sg:phone":"+61 2 9879 0500",
    "sg:postcode":"2111",
    "sg:province":"NSW",
    "sg:tags":[
        "engineer",
        "designing"
    ],
    "wof:name":"Fuzzy Logis",
    "wof:placetype":"venue"
},
  "geometry": {"coordinates":[151.13183593799999,-33.8258323669],"type":"Point"}
}