{
  "type": "Feature",
  "properties": {
    "iso:country":"AU",
    "sg:address":"540 Malvern Rd",
    "sg:city":"Prahran",
    "sg:classifiers":[
        {
            "category":"Building & Trades",
            "subcategory":"Construction",
            "type":"Services"
        }
    ],
    "sg:phone":"+61 3 9573 8393",
    "sg:postcode":"3181",
    "sg:province":"VIC",
    "sg:tags":[
        "contractor"
    ],
    "wof:name":"Glenvill Pty Ltd",
    "wof:placetype":"venue"
},
  "geometry": {"coordinates":[145.004272461,-37.8483505249],"type":"Point"}
}