{
  "type": "Feature",
  "properties": {
    "addr:full":"43 Russell St Werribee VIC 3030",
    "addr:housenumber":"43",
    "addr:postcode":"3030",
    "addr:street":"Russell St",
    "iso:country":"AU",
    "sg:address":"43 Russell St",
    "sg:city":"Werribee",
    "sg:classifiers":[
        {
            "category":"Retail",
            "subcategory":"Auto Repair",
            "type":"Services"
        }
    ],
    "sg:phone":"+61 3 9741 1613",
    "sg:postcode":"3030",
    "sg:province":"VIC",
    "sg:tags":[
        "electrical"
    ],
    "wof:name":"Werribee Auto Electrician Pty Ltd",
    "wof:placetype":"venue"
},
  "geometry": {"coordinates":[144.66154499999999,-37.91069],"type":"Point"}
}