{
  "type": "Feature",
  "properties": {
    "addr:full":"U3/ 19 Seton Rd Moorebank NSW 2170",
    "addr:housenumber":"19",
    "addr:postcode":"2170",
    "addr:street":"U3 /;Seton Rd",
    "iso:country":"AU",
    "sg:address":"U3/ 19 Seton Rd",
    "sg:city":"Moorebank",
    "sg:classifiers":[
        {
            "category":"Wholesale",
            "subcategory":"Auto Parts",
            "type":"Manufacturing & Wholesale Goods"
        }
    ],
    "sg:phone":"+61 2 9600 6089",
    "sg:postcode":"2170",
    "sg:province":"NSW",
    "sg:tags":[
        "tyre"
    ],
    "wof:name":"A.V.A. Tyres Pty Ltd",
    "wof:placetype":"venue"
},
  "geometry": {"coordinates":[150.93890380900001,-33.9364891052],"type":"Point"}
}