{
  "type": "Feature",
  "properties": {
    "iso:country":"AU",
    "sg:address":"29a Miller St",
    "sg:city":"Bendigo",
    "sg:classifiers":[
        {
            "category":"Professional",
            "subcategory":"Employment Agencies",
            "type":"Services"
        }
    ],
    "sg:phone":"+61 3 5443 7200",
    "sg:postcode":"3539",
    "sg:province":"VIC",
    "sg:tags":[
        "hire",
        "labour",
        "contractor"
    ],
    "wof:name":"Workforce Extensions",
    "wof:placetype":"venue"
},
  "geometry": {"coordinates":[144.289276,-36.769516],"type":"Point"}
}