{
  "type": "Feature",
  "properties": {
    "iso:country":"AU",
    "sg:address":"2 Devonshire St",
    "sg:city":"Chatswood",
    "sg:classifiers":[
        {
            "category":"Retail",
            "subcategory":"Auto Repair",
            "type":"Services"
        }
    ],
    "sg:phone":"+61 2 9412 1055",
    "sg:postcode":"2067",
    "sg:province":"NSW",
    "sg:tags":[
        "electrical"
    ],
    "wof:name":"Clearview Brake & Clutch Service",
    "wof:placetype":"venue"
},
  "geometry": {"coordinates":[151.18592834500001,-33.8012390137],"type":"Point"}
}