{
  "type": "Feature",
  "properties": {
    "addr:full":"152 Headland Rd North Curl Curl NSW 2099",
    "addr:housenumber":"152",
    "addr:postcode":"2099",
    "addr:street":"Headland Rd",
    "iso:country":"AU",
    "sg:address":"152 Headland Rd",
    "sg:city":"North Curl Curl",
    "sg:classifiers":[
        {
            "category":"Professional",
            "subcategory":"Management & Consulting",
            "type":"Services"
        }
    ],
    "sg:phone":"+61 2 9939 7887",
    "sg:postcode":"2099",
    "sg:province":"NSW",
    "sg:tags":[
        "consultant"
    ],
    "wof:name":"Quadrant Consulting Pty Ltd",
    "wof:placetype":"venue"
},
  "geometry": {"coordinates":[151.287719727,-33.7597084045],"type":"Point"}
}