{
  "type": "Feature",
  "properties": {
    "iso:country":"AU",
    "sg:address":"281 Wattletree Rd",
    "sg:city":"Malvern East",
    "sg:classifiers":[
        {
            "category":"Building & Trades",
            "subcategory":"Construction",
            "type":"Services"
        }
    ],
    "sg:phone":"+61 3 9509 6433",
    "sg:postcode":"3145",
    "sg:province":"VIC",
    "sg:tags":[
        "home",
        "air conditioning"
    ],
    "wof:name":"Lee W & Sons",
    "wof:placetype":"venue"
},
  "geometry": {"coordinates":[145.040405273,-37.8638000488],"type":"Point"}
}