{
  "type": "Feature",
  "properties": {
    "iso:country":"AU",
    "sg:address":"83 Boundary St",
    "sg:city":"West End (Brisbane)",
    "sg:classifiers":[
        {
            "category":"Fast Food",
            "type":"Food & Drink"
        }
    ],
    "sg:phone":"+61 7 3844 6502",
    "sg:postcode":"4101",
    "sg:province":"QLD",
    "sg:tags":[
        "away",
        "take"
    ],
    "wof:name":"Roundabout Cafe Takeaway",
    "wof:placetype":"venue"
},
  "geometry": {"coordinates":[153.012573242,-27.4773845673],"type":"Point"}
}