{
  "type": "Feature",
  "properties": {
    "addr:full":"Cnr Lang & Alexandra Sts Kurri Kurri NSW 2327",
    "addr:postcode":"2327",
    "iso:country":"AU",
    "sg:address":"Cnr Lang & Alexandra Sts",
    "sg:city":"Kurri Kurri",
    "sg:classifiers":[
        {
            "category":"Travel",
            "subcategory":"Hotels & Motels",
            "type":"Entertainment"
        }
    ],
    "sg:phone":"+61 2 4937 2222",
    "sg:postcode":"2327",
    "sg:province":"NSW",
    "wof:name":"Kurri Motor Inn",
    "wof:placetype":"venue"
},
  "geometry": {"coordinates":[151.481933594,-32.817943573],"type":"Point"}
}