{
  "type": "Feature",
  "properties": {
    "addr:full":"Shop 1,269- 271 Darling St Balmain NSW 2041",
    "addr:housenumber":"1,269 271",
    "addr:postcode":"2041",
    "addr:street":"Darling St",
    "iso:country":"AU",
    "sg:address":"Shop 1,269- 271 Darling St",
    "sg:city":"Balmain",
    "sg:classifiers":[
        {
            "category":"Food & Beverages",
            "subcategory":"Bakery",
            "type":"Retail Goods"
        }
    ],
    "sg:phone":"+61 2 9818 4310",
    "sg:postcode":"2041",
    "sg:province":"NSW",
    "sg:tags":[
        "baker"
    ],
    "wof:name":"Bakers Delight Ltd",
    "wof:placetype":"venue"
},
  "geometry": {"coordinates":[151.18150299999999,-33.857479],"type":"Point"}
}