{
  "type": "Feature",
  "properties": {
    "addr:full":"444 Punchbowl Rd Belmore NSW 2192",
    "addr:housenumber":"444",
    "addr:postcode":"2192",
    "addr:street":"Punchbowl Rd",
    "iso:country":"AU",
    "sg:address":"444 Punchbowl Rd",
    "sg:city":"Belmore",
    "sg:classifiers":[
        {
            "category":"Autos & Motor Vehicles",
            "subcategory":"Fuel & Gas Station",
            "type":"Retail Goods"
        }
    ],
    "sg:phone":"+61 2 9750 5537",
    "sg:postcode":"2192",
    "sg:province":"NSW",
    "wof:name":"Oz-Stop Service Station",
    "wof:placetype":"venue"
},
  "geometry": {"coordinates":[151.076797,-33.907784],"type":"Point"}
}