{
  "type": "Feature",
  "properties": {
    "addr:full":"Vimy House Private Hospital 5 Studley Ave Kew VIC 3101",
    "addr:housenumber":"5",
    "addr:postcode":"3101",
    "addr:street":"Studley Ave",
    "iso:country":"AU",
    "sg:address":"Vimy House Private Hospital 5 Studley Ave",
    "sg:city":"Kew",
    "sg:classifiers":[
        {
            "category":"Health Services",
            "subcategory":"Doctor",
            "type":"Services"
        }
    ],
    "sg:phone":"+61 3 9473 8850",
    "sg:postcode":"3101",
    "sg:province":"VIC",
    "sg:tags":[
        "medical",
        "practitioner"
    ],
    "wof:name":"Feller Julian",
    "wof:placetype":"venue"
},
  "geometry": {"coordinates":[145.02403259299999,-37.8066749573],"type":"Point"}
}