{
  "type": "Feature",
  "properties": {
    "iso:country":"AU",
    "sg:address":"Suite 9 1 Bell Pl",
    "sg:city":"Mudgeeraba",
    "sg:classifiers":[
        {
            "category":"Health Services",
            "subcategory":"Chiropractor",
            "type":"Services"
        }
    ],
    "sg:phone":"+61 7 5576 7633",
    "sg:postcode":"4213",
    "sg:province":"QLD",
    "wof:name":"Vardi Lynne Dr",
    "wof:placetype":"venue"
},
  "geometry": {"coordinates":[153.365768433,-28.0802936554],"type":"Point"}
}