{
  "type": "Feature",
  "properties": {
    "addr:full":"29 Jabiru Ave Condon QLD 4815",
    "addr:housenumber":"29",
    "addr:postcode":"4815",
    "addr:street":"Jabiru Ave",
    "iso:country":"AU",
    "sg:address":"29 Jabiru Ave",
    "sg:city":"Condon",
    "sg:classifiers":[
        {
            "category":"Building & Trades",
            "subcategory":"Construction",
            "type":"Services"
        }
    ],
    "sg:phone":"+61 7 4723 1082",
    "sg:postcode":"4815",
    "sg:province":"QLD",
    "sg:tags":[
        "tennis court",
        "repair"
    ],
    "wof:name":"I & L Asphalt",
    "wof:placetype":"venue"
},
  "geometry": {"coordinates":[146.72018399999999,-19.334217],"type":"Point"}
}