{
  "type": "Feature",
  "properties": {
    "addr:full":"163 Commercial Rd South Yarra VIC 3141",
    "addr:housenumber":"163",
    "addr:postcode":"3141",
    "addr:street":"Commercial Rd",
    "iso:country":"AU",
    "sg:address":"163 Commercial Rd",
    "sg:city":"South Yarra",
    "sg:classifiers":[
        {
            "category":"Food & Beverages",
            "subcategory":"Fruits & Vegetables",
            "type":"Retail Goods"
        }
    ],
    "sg:phone":"+61 3 9827 1550",
    "sg:postcode":"3141",
    "sg:province":"VIC",
    "sg:tags":[
        "greengrocer",
        "fruiterer"
    ],
    "wof:name":"Pino's Fine Produce",
    "wof:placetype":"venue"
},
  "geometry": {"coordinates":[144.99183654800001,-37.846408844],"type":"Point"}
}