{
  "type": "Feature",
  "properties": {
    "addr:full":"Waverley Ave Merrigum VIC 3618",
    "addr:postcode":"3618",
    "addr:street":"Waverley Ave",
    "iso:country":"AU",
    "sg:address":"Waverley Ave",
    "sg:city":"Merrigum",
    "sg:classifiers":[
        {
            "category":"Home & Garden",
            "subcategory":"Building Materials",
            "type":"Retail Goods"
        }
    ],
    "sg:phone":"+61 3 5855 2310",
    "sg:postcode":"3618",
    "sg:province":"VIC",
    "sg:tags":[
        "fencing"
    ],
    "wof:name":"M & T Lawlor Pty Ltd",
    "wof:placetype":"venue"
},
  "geometry": {"coordinates":[145.13201904300001,-36.36876297],"type":"Point"}
}