{
  "type": "Feature",
  "properties": {
    "iso:country":"AU",
    "sg:address":"46 Radley St",
    "sg:city":"Virginia",
    "sg:classifiers":[
        {
            "category":"Manufacturing",
            "subcategory":"Printing",
            "type":"Manufacturing & Wholesale Goods"
        }
    ],
    "sg:phone":"+61 7 5591 5572",
    "sg:postcode":"4014",
    "sg:province":"QLD",
    "sg:tags":[
        "encoding",
        "cheque"
    ],
    "wof:name":"Form Print (Qld) Pty Ltd",
    "wof:placetype":"venue"
},
  "geometry": {"coordinates":[153.064056397,-27.3663215637],"type":"Point"}
}