{
  "type": "Feature",
  "properties": {
    "addr:full":"2- 4 Short St Huonville TAS 7109",
    "addr:housenumber":"4",
    "addr:postcode":"7109",
    "addr:street":"Short St",
    "iso:country":"AU",
    "sg:address":"2- 4 Short St",
    "sg:city":"Huonville",
    "sg:classifiers":[
        {
            "category":"Retail",
            "subcategory":"Event Space",
            "type":"Services"
        }
    ],
    "sg:phone":"+61 3 6264 1311",
    "sg:postcode":"7109",
    "sg:province":"TAS",
    "sg:tags":[
        "venue",
        "reception",
        "wedding"
    ],
    "wof:name":"Huon Manor Restaurant",
    "wof:placetype":"venue"
},
  "geometry": {"coordinates":[147.04664611800001,-43.0324440002],"type":"Point"}
}