{
  "type": "Feature",
  "properties": {
    "addr:full":"15 Raphael Rd Winnellie NT 0820",
    "addr:housenumber":"15",
    "addr:postcode":"nt 0820",
    "addr:street":"Raphael Rd",
    "iso:country":"AU",
    "sg:address":"15 Raphael Rd",
    "sg:city":"Winnellie",
    "sg:classifiers":[
        {
            "category":"Professional",
            "type":"Services"
        }
    ],
    "sg:phone":"+61 8 8984 3446",
    "sg:postcode":"0820",
    "sg:province":"NT",
    "sg:tags":[
        "transport"
    ],
    "wof:name":"Camco Transports",
    "wof:placetype":"venue"
},
  "geometry": {"coordinates":[130.886627197,-12.4302988052],"type":"Point"}
}