{
  "type": "Feature",
  "properties": {
    "iso:country":"AU",
    "sg:address":"23 Kidman St",
    "sg:city":"Alice Springs",
    "sg:classifiers":[
        {
            "category":"Professional",
            "subcategory":"Detective & Security Services",
            "type":"Services"
        }
    ],
    "sg:phone":"+61 8 8952 8009",
    "sg:postcode":"0870",
    "sg:province":"NT",
    "sg:tags":[
        "protective",
        "rustproofing"
    ],
    "wof:name":"Alice Powder Coating N.T. Pty Ltd",
    "wof:placetype":"venue"
},
  "geometry": {"coordinates":[133.869796753,-23.696521759],"type":"Point"}
}