{
  "type": "Feature",
  "properties": {
    "iso:country":"AU",
    "sg:address":"98 Lewin St",
    "sg:city":"Lyneham",
    "sg:classifiers":[
        {
            "category":"Real Estate",
            "subcategory":"Real Estate Agent",
            "type":"Services"
        }
    ],
    "sg:phone":"+61 413 997 034",
    "sg:postcode":"2602",
    "sg:province":"ACT",
    "wof:name":"Building Report Factory",
    "wof:placetype":"venue"
},
  "geometry": {"coordinates":[149.126754761,-35.24766922],"type":"Point"}
}