{
  "type": "Feature",
  "properties": {
    "addr:full":"Shp 6/ 63 Thomson St Belmont VIC 3216",
    "addr:housenumber":"/ 63",
    "addr:postcode":"3216",
    "addr:street":"Thomson St",
    "iso:country":"AU",
    "sg:address":"Shp 6/ 63 Thomson St",
    "sg:city":"Belmont",
    "sg:classifiers":[
        {
            "category":"Shopping",
            "subcategory":"Clothing, Apparel, & Fashions",
            "type":"Retail Goods"
        }
    ],
    "sg:phone":"+61 3 5244 4093",
    "sg:postcode":"3216",
    "sg:province":"VIC",
    "sg:tags":[
        "lady",
        "wear"
    ],
    "wof:name":"Slinky",
    "wof:placetype":"venue"
},
  "geometry": {"coordinates":[144.34169006400001,-38.1749458313],"type":"Point"}
}