{
  "type": "Feature",
  "properties": {
    "addr:full":"340 South Rd Richmond SA 5033",
    "addr:housenumber":"340",
    "addr:postcode":"5033",
    "addr:street":"South Rd",
    "iso:country":"AU",
    "sg:address":"340 South Rd",
    "sg:city":"Richmond",
    "sg:classifiers":[
        {
            "category":"Sports & Exercise",
            "subcategory":"Gym",
            "type":"Entertainment"
        }
    ],
    "sg:phone":"+61 8 8234 1766",
    "sg:postcode":"5033",
    "sg:province":"SA",
    "sg:tags":[
        "health",
        "fitness"
    ],
    "wof:name":"Body Workshop Weight Loss Health & Fitness Centres",
    "wof:placetype":"venue"
},
  "geometry": {"coordinates":[138.570480347,-34.9371185303],"type":"Point"}
}