{
  "type": "Feature",
  "properties": {
    "iso:country":"AU",
    "sg:address":"128 O&#039;Riordan St",
    "sg:city":"Mascot",
    "sg:classifiers":[
        {
            "category":"Real Estate",
            "subcategory":"Real Estate Agent",
            "type":"Services"
        }
    ],
    "sg:phone":"+61 2 9669 5900",
    "sg:postcode":"2020",
    "sg:province":"NSW",
    "wof:name":"L J Hooker",
    "wof:placetype":"venue"
},
  "geometry": {"coordinates":[151.18719482399999,-33.9288215637],"type":"Point"}
}