{
  "type": "Feature",
  "properties": {
    "addr:full":"97 Chisholm Rd Carrara QLD 4211",
    "addr:housenumber":"97",
    "addr:postcode":"4211",
    "addr:street":"Chisholm Rd",
    "iso:country":"AU",
    "sg:address":"97 Chisholm Rd",
    "sg:city":"Carrara",
    "sg:classifiers":[
        {
            "category":"Banks & Credit Unions",
            "subcategory":"Financial Services",
            "type":"Services"
        }
    ],
    "sg:phone":"+61 7 5596 3864",
    "sg:postcode":"4211",
    "sg:province":"QLD",
    "sg:tags":[
        "loan",
        "finance",
        "mortgage"
    ],
    "wof:name":"Fast Easy Loans",
    "wof:placetype":"venue"
},
  "geometry": {"coordinates":[153.356399536,-28.0035133362],"type":"Point"}
}