{
  "type": "Feature",
  "properties": {
    "iso:country":"AU",
    "sg:address":"Flinders Rd",
    "sg:city":"Nowra South",
    "sg:classifiers":[
        {
            "category":"Autos & Motor Vehicles",
            "subcategory":"Auto Supplies",
            "type":"Retail Goods"
        }
    ],
    "sg:phone":"+61 2 4423 3847",
    "sg:postcode":"2541",
    "sg:province":"NSW",
    "sg:tags":[
        "tyre"
    ],
    "wof:name":"Dennis's Tyres",
    "wof:placetype":"venue"
},
  "geometry": {"coordinates":[150.58172607399999,-34.9059867859],"type":"Point"}
}