{
  "type": "Feature",
  "properties": {
    "addr:full":"Shop 29, Gungahlin Market Pl Gungahlin ACT 2912",
    "addr:housenumber":"shop 29",
    "addr:postcode":"2912",
    "addr:street":"Market Pl",
    "iso:country":"AU",
    "sg:address":"Shop 29, Gungahlin Market Pl",
    "sg:city":"Gungahlin",
    "sg:classifiers":[
        {
            "category":"Banks & Credit Unions",
            "subcategory":"Financial Services",
            "type":"Services"
        }
    ],
    "sg:phone":"+61 2 6253 8555",
    "sg:postcode":"2912",
    "sg:province":"ACT",
    "sg:tags":[
        "loan",
        "finance",
        "mortgage"
    ],
    "wof:name":"Choice Home Loans",
    "wof:placetype":"venue"
},
  "geometry": {"coordinates":[149.135665894,-35.183506012],"type":"Point"}
}