{
  "type": "Feature",
  "properties": {
    "iso:country":"AU",
    "sg:address":"5 McArthy Crt",
    "sg:city":"Wallan",
    "sg:classifiers":[
        {
            "category":"Building & Trades",
            "subcategory":"Construction",
            "type":"Services"
        }
    ],
    "sg:phone":"+61 3 5783 1784",
    "sg:postcode":"3756",
    "sg:province":"VIC",
    "sg:tags":[
        "earth",
        "excavating",
        "moving",
        "contractor"
    ],
    "wof:name":"Jacbah Bobcat & Tipper Hire",
    "wof:placetype":"venue"
},
  "geometry": {"coordinates":[144.987595,-37.418583],"type":"Point"}
}