{
  "type": "Feature",
  "properties": {
    "addr:full":"1183 Pt Nepean Rd Rosebud VIC 3939",
    "addr:housenumber":"1183",
    "addr:postcode":"3939",
    "addr:street":"Pt Nepean Rd",
    "iso:country":"AU",
    "sg:address":"1183 Pt Nepean Rd",
    "sg:city":"Rosebud",
    "sg:classifiers":[
        {
            "category":"Fast Food",
            "type":"Food & Drink"
        }
    ],
    "sg:phone":"+61 3 5981 1399",
    "sg:postcode":"3939",
    "sg:province":"VIC",
    "sg:tags":[
        "away",
        "take"
    ],
    "wof:name":"Sharmas All Star Bar & Indian Restaurant",
    "wof:placetype":"venue"
},
  "geometry": {"coordinates":[144.89970398,-38.3573417664],"type":"Point"}
}