{
  "type": "Feature",
  "properties": {
    "addr:full":"947 Wynnum Rd Cannon Hill QLD 4170",
    "addr:housenumber":"947",
    "addr:postcode":"4170",
    "addr:street":"Wynnum Rd",
    "iso:country":"AU",
    "sg:address":"947 Wynnum Rd",
    "sg:city":"Cannon Hill",
    "sg:classifiers":[
        {
            "category":"Wholesale",
            "subcategory":"Machinery & Supplies",
            "type":"Manufacturing & Wholesale Goods"
        }
    ],
    "sg:phone":"+61 7 3399 1326",
    "sg:postcode":"4170",
    "sg:province":"QLD",
    "sg:tags":[
        "engine",
        "petrol"
    ],
    "wof:name":"Aabec Mowers",
    "wof:placetype":"venue"
},
  "geometry": {"coordinates":[153.087890625,-27.468416214],"type":"Point"}
}