{
  "type": "Feature",
  "properties": {
    "iso:country":"AU",
    "sg:address":"263 Dow Ave",
    "sg:city":"Birdwoodton",
    "sg:classifiers":[
        {
            "category":"Social Services",
            "subcategory":"Retirement Home",
            "type":"Services"
        }
    ],
    "sg:phone":"+61 3 5025 6500",
    "sg:postcode":"3505",
    "sg:province":"VIC",
    "sg:tags":[
        "environmental",
        "consultant",
        "pollution"
    ],
    "wof:name":"Ogyris Ecological Research",
    "wof:placetype":"venue"
},
  "geometry": {"coordinates":[142.07267761200001,-34.2083511353],"type":"Point"}
}