{
  "type": "Feature",
  "properties": {
    "iso:country":"AU",
    "sg:address":"211 Vincent St",
    "sg:city":"Cessnock",
    "sg:classifiers":[
        {
            "category":"Manufacturing",
            "subcategory":"Motor Vehicles & Parts",
            "type":"Manufacturing & Wholesale Goods"
        }
    ],
    "sg:phone":"+61 2 4991 1111",
    "sg:postcode":"2325",
    "sg:province":"NSW",
    "sg:tags":[
        "replacement"
    ],
    "wof:name":"Auto One Parts & Accessories",
    "wof:placetype":"venue"
},
  "geometry": {"coordinates":[151.35533142099999,-32.8391151428],"type":"Point"}
}