{
  "type": "Feature",
  "properties": {
    "addr:full":"44 Duke St Gympie QLD 4570",
    "addr:housenumber":"44",
    "addr:postcode":"4570",
    "addr:street":"Duke St",
    "iso:country":"AU",
    "sg:address":"44 Duke St",
    "sg:city":"Gympie",
    "sg:classifiers":[
        {
            "category":"Health Services",
            "subcategory":"Doctor",
            "type":"Services"
        }
    ],
    "sg:phone":"+61 7 5480 4700",
    "sg:postcode":"4570",
    "sg:province":"QLD",
    "sg:tags":[
        "nurse",
        "nursing"
    ],
    "wof:name":"Spiritus Care Services",
    "wof:placetype":"venue"
},
  "geometry": {"coordinates":[152.65679931599999,-26.1859264374],"type":"Point"}
}