{
  "type": "Feature",
  "properties": {
    "iso:country":"AU",
    "sg:address":"Lot 3 Malarkey Rd",
    "sg:city":"Byford",
    "sg:classifiers":[
        {
            "category":"Education",
            "subcategory":"Dance Studio",
            "type":"Public Place"
        }
    ],
    "sg:phone":"+61 8 9495 1425",
    "sg:postcode":"6122",
    "sg:province":"WA",
    "sg:tags":[
        "venue",
        "tuition"
    ],
    "wof:name":"Dance Masters International Association",
    "wof:placetype":"venue"
},
  "geometry": {"coordinates":[115.98667907700001,-32.2156028748],"type":"Point"}
}