{
  "type": "Feature",
  "properties": {
    "iso:country":"AU",
    "sg:address":"U1/ 103 Harburg Drv",
    "sg:city":"Beenleigh",
    "sg:classifiers":[
        {
            "category":"Professional",
            "subcategory":"Art Services",
            "type":"Services"
        }
    ],
    "sg:phone":"+61 7 3804 6530",
    "sg:postcode":"4207",
    "sg:province":"QLD",
    "sg:tags":[
        "decorator",
        "painter"
    ],
    "wof:name":"Go Colour Applicators",
    "wof:placetype":"venue"
},
  "geometry": {"coordinates":[153.182296753,-27.7151050568],"type":"Point"}
}