{
  "type": "Feature",
  "properties": {
    "addr:full":"348 King William St Adelaide SA 5000",
    "addr:housenumber":"348",
    "addr:postcode":"5000",
    "addr:street":"King William St",
    "iso:country":"AU",
    "sg:address":"348 King William St",
    "sg:city":"Adelaide",
    "sg:classifiers":[
        {
            "category":"Fast Food",
            "type":"Food & Drink"
        }
    ],
    "sg:phone":"+61 8 8231 5858",
    "sg:postcode":"5000",
    "sg:province":"SA",
    "sg:tags":[
        "away",
        "take"
    ],
    "wof:name":"La Trattoria Pizza",
    "wof:placetype":"venue"
},
  "geometry": {"coordinates":[138.600509644,-34.9320335388],"type":"Point"}
}