{
  "type": "Feature",
  "properties": {
    "iso:country":"AU",
    "sg:address":"12 Adelaide Rd",
    "sg:city":"Gawler",
    "sg:classifiers":[
        {
            "category":"Health Services",
            "subcategory":"Chiropractor",
            "type":"Services"
        }
    ],
    "sg:phone":"+61 8 8522 4846",
    "sg:postcode":"5118",
    "sg:province":"SA",
    "wof:name":"Thomas Brien Dr",
    "wof:placetype":"venue"
},
  "geometry": {"coordinates":[138.746353,-34.604683],"type":"Point"}
}