{
  "type": "Feature",
  "properties": {
    "addr:full":"Pinelands Plaza, Pinelands Rd (Cnr Beenleigh Rd) Sunnybank Hills QLD 4109",
    "addr:postcode":"4109",
    "addr:street":"Pinelands Rd Cnr Beenleigh Rd",
    "iso:country":"AU",
    "sg:address":"Pinelands Plaza, Pinelands Rd",
    "sg:city":"(Cnr Beenleigh Rd) Sunnybank Hills",
    "sg:classifiers":[
        {
            "category":"Real Estate",
            "subcategory":"Real Estate Agent",
            "type":"Services"
        }
    ],
    "sg:phone":"+61 7 3343 4022",
    "sg:postcode":"4109",
    "sg:province":"QLD",
    "wof:name":"Elders Real Estate",
    "wof:placetype":"venue"
},
  "geometry": {"coordinates":[153.05856323200001,-27.5986919403],"type":"Point"}
}