{
  "type": "Feature",
  "properties": {
    "addr:full":"Casuarinas Rd Mullewa WA 6630",
    "addr:postcode":"6630",
    "addr:street":"Casuarinas Rd",
    "iso:country":"AU",
    "sg:address":"Casuarinas Rd",
    "sg:city":"Mullewa",
    "sg:classifiers":[
        {
            "category":"Arena",
            "subcategory":"Bull Ring",
            "type":"Entertainment"
        }
    ],
    "sg:phone":"+61 8 9927 6042",
    "sg:postcode":"6630",
    "sg:province":"WA",
    "sg:tags":[
        "breeder",
        "pig"
    ],
    "wof:name":"Ella Plains Pastoral Co",
    "wof:placetype":"venue"
},
  "geometry": {"coordinates":[115.182739258,-28.7046642303],"type":"Point"}
}