{
  "type": "Feature",
  "properties": {
    "addr:full":"425 Henley Beach Rd Brooklyn Park SA 5032",
    "addr:housenumber":"425",
    "addr:postcode":"5032",
    "addr:street":"Henley Beach Rd",
    "iso:country":"AU",
    "sg:address":"425 Henley Beach Rd",
    "sg:city":"Brooklyn Park",
    "sg:classifiers":[
        {
            "category":"Professional",
            "subcategory":"Employment Agencies",
            "type":"Services"
        }
    ],
    "sg:phone":"+61 8 8234 9239",
    "sg:postcode":"5032",
    "sg:province":"SA",
    "sg:website":"http://www.maxima.com.au",
    "wof:name":"Maxima Group",
    "wof:placetype":"venue"
},
  "geometry": {"coordinates":[138.53558349599999,-34.9275665283],"type":"Point"}
}