{
  "type": "Feature",
  "properties": {
    "addr:full":"Cnr Cook Hwy & Mc Gregor Rd Smithfield QLD 4350",
    "addr:postcode":"4350",
    "addr:street":"Cnr Cook Hwy & Mc Gregor Rd",
    "iso:country":"AU",
    "sg:address":"Cnr Cook Hwy & Mc Gregor Rd",
    "sg:city":"Smithfield",
    "sg:classifiers":[
        {
            "category":"Health Services",
            "subcategory":"Doctor",
            "type":"Services"
        }
    ],
    "sg:phone":"+61 7 4057 5800",
    "sg:postcode":"4350",
    "sg:province":"QLD",
    "sg:tags":[
        "medical",
        "practitioner"
    ],
    "wof:name":"North Qld X-Ray Services",
    "wof:placetype":"venue"
},
  "geometry": {"coordinates":[151.92860400000001,-27.586323],"type":"Point"}
}