{
  "type": "Feature",
  "properties": {
    "iso:country":"AU",
    "sg:address":"Lot 1 Caffery Rd",
    "sg:city":"Nanango",
    "sg:classifiers":[
        {
            "category":"Building & Trades",
            "subcategory":"Construction",
            "type":"Services"
        }
    ],
    "sg:phone":"+61 7 4163 3344",
    "sg:postcode":"4615",
    "sg:province":"QLD",
    "sg:tags":[
        "fencing",
        "contractor"
    ],
    "wof:name":"South Burnett Fencing",
    "wof:placetype":"venue"
},
  "geometry": {"coordinates":[151.978805542,-26.6609401703],"type":"Point"}
}