{
  "type": "Feature",
  "properties": {
    "iso:country":"AU",
    "sg:address":"271 Greensborough Hwy",
    "sg:city":"Macleod",
    "sg:classifiers":[
        {
            "category":"Health Services",
            "subcategory":"Dentist",
            "type":"Services"
        }
    ],
    "sg:phone":"+61 3 9434 4111",
    "sg:postcode":"3085",
    "sg:province":"VIC",
    "wof:name":"Schwartz Robert E. Dr",
    "wof:placetype":"venue"
},
  "geometry": {"coordinates":[145.081665039,-37.7168540955],"type":"Point"}
}