{
  "type": "Feature",
  "properties": {
    "addr:full":"12 Panton Rd Mandurah WA 6210",
    "addr:housenumber":"12",
    "addr:postcode":"6210",
    "addr:street":"Panton Rd",
    "iso:country":"AU",
    "sg:address":"12 Panton Rd",
    "sg:city":"Mandurah",
    "sg:classifiers":[
        {
            "category":"Autos & Motor Vehicles",
            "subcategory":"Boat Sales",
            "type":"Retail Goods"
        }
    ],
    "sg:phone":"+61 8 9581 8444",
    "sg:postcode":"6210",
    "sg:province":"WA",
    "sg:tags":[
        "yacht"
    ],
    "wof:name":"Estuary Marine Quintrex",
    "wof:placetype":"venue"
},
  "geometry": {"coordinates":[115.74520099999999,-32.512543],"type":"Point"}
}