{
  "type": "Feature",
  "properties": {
    "iso:country":"AU",
    "sg:address":"Lot 39 Waverley St",
    "sg:city":"Nebo",
    "sg:classifiers":[
        {
            "category":"Communications",
            "subcategory":"News Services",
            "type":"Services"
        }
    ],
    "sg:phone":"+61 7 4950 5299",
    "sg:postcode":"4742",
    "sg:province":"QLD",
    "sg:tags":[
        "information",
        "tourist",
        "attractions"
    ],
    "wof:name":"The MAC Culture & Tourism",
    "wof:placetype":"venue"
},
  "geometry": {"coordinates":[148.69523599999999,-21.690592],"type":"Point"}
}