{
  "type": "Feature",
  "properties": {
    "iso:country":"AU",
    "sg:address":"Cedar Ave",
    "sg:city":"Naracoorte",
    "sg:classifiers":[
        {
            "category":"Education",
            "subcategory":"School",
            "type":"Public Place"
        }
    ],
    "sg:phone":"+61 8 8762 2977",
    "sg:postcode":"5271",
    "sg:province":"SA",
    "sg:tags":[
        "state",
        "except",
        "nsw"
    ],
    "wof:name":"Naracoorte South Primary School",
    "wof:placetype":"venue"
},
  "geometry": {"coordinates":[140.74496500000001,-36.962933],"type":"Point"}
}