{
  "type": "Feature",
  "properties": {
    "addr:full":"Cnr Princes Hwy & Garvan Rd Heathcote NSW 2233",
    "addr:postcode":"2233",
    "addr:street":"Cnr Princes Hwy & Garvan Rd",
    "iso:country":"AU",
    "sg:address":"Cnr Princes Hwy & Garvan Rd",
    "sg:city":"Heathcote",
    "sg:classifiers":[
        {
            "category":"Manufacturing",
            "subcategory":"Metals",
            "type":"Manufacturing & Wholesale Goods"
        }
    ],
    "sg:phone":"+61 2 9520 3700",
    "sg:postcode":"2233",
    "sg:province":"NSW",
    "sg:tags":[
        "steel",
        "fabricator",
        "mfrs"
    ],
    "wof:name":"Ken Mitchell Engineering Pty Ltd",
    "wof:placetype":"venue"
},
  "geometry": {"coordinates":[151.011154175,-34.0827903748],"type":"Point"}
}