{
  "type": "Feature",
  "properties": {
    "iso:country":"AU",
    "sg:address":"339 Centre Rd",
    "sg:city":"Bentleigh",
    "sg:classifiers":[
        {
            "category":"Manufacturing",
            "subcategory":"Glass & Minerals",
            "type":"Manufacturing & Wholesale Goods"
        }
    ],
    "sg:phone":"+61 3 9557 1315",
    "sg:postcode":"3204",
    "sg:province":"VIC",
    "sg:tags":[
        "case",
        "counter",
        "show"
    ],
    "wof:name":"Cabinet Displays Pty Ltd",
    "wof:placetype":"venue"
},
  "geometry": {"coordinates":[145.035675,-37.917927],"type":"Point"}
}