{
  "type": "Feature",
  "properties": {
    "addr:full":"1 Fairhills Pde Glen Waverley VIC 3150",
    "addr:housenumber":"1",
    "addr:postcode":"3150",
    "addr:street":"Fairhills Pde",
    "iso:country":"AU",
    "sg:address":"1 Fairhills Pde",
    "sg:city":"Glen Waverley",
    "sg:classifiers":[
        {
            "category":"Health Services",
            "subcategory":"Doctor",
            "type":"Services"
        }
    ],
    "sg:phone":"+61 3 9802 8844",
    "sg:postcode":"3150",
    "sg:province":"VIC",
    "sg:tags":[
        "medical",
        "practitioner"
    ],
    "wof:name":"Francis Dr Janelle",
    "wof:placetype":"venue"
},
  "geometry": {"coordinates":[145.16725158700001,-37.876789093],"type":"Point"}
}