{
  "type": "Feature",
  "properties": {
    "addr:full":"Cnr Newcastle & Wollongong Sts Fyshwick ACT 2609",
    "addr:postcode":"2609",
    "addr:street":"Cnr",
    "iso:country":"AU",
    "sg:address":"Cnr Newcastle & Wollongong Sts",
    "sg:city":"Fyshwick",
    "sg:classifiers":[
        {
            "category":"Manufacturing",
            "subcategory":"Electronics",
            "type":"Manufacturing & Wholesale Goods"
        }
    ],
    "sg:phone":"+61 2 6280 4698",
    "sg:postcode":"2609",
    "sg:province":"ACT",
    "sg:tags":[
        "oven",
        "microwave"
    ],
    "wof:name":"Associated Electronics (A.C.T.) Pty Ltd",
    "wof:placetype":"venue"
},
  "geometry": {"coordinates":[149.17619323700001,-35.3273468018],"type":"Point"}
}