{
  "type": "Feature",
  "properties": {
    "addr:full":"2 Frater Crt Doncaster East VIC 3109",
    "addr:housenumber":"2",
    "addr:postcode":"3109",
    "addr:street":"Frater Crt",
    "iso:country":"AU",
    "sg:address":"2 Frater Crt",
    "sg:city":"Doncaster East",
    "sg:classifiers":[
        {
            "category":"Health Services",
            "subcategory":"Health Practitioner",
            "type":"Services"
        }
    ],
    "sg:phone":"+61 3 9841 7085",
    "sg:postcode":"3109",
    "sg:province":"VIC",
    "sg:tags":[
        "psychologist"
    ],
    "wof:name":"Pearson Trish",
    "wof:placetype":"venue"
},
  "geometry": {"coordinates":[145.17308044399999,-37.7786445618],"type":"Point"}
}