{
  "type": "Feature",
  "properties": {
    "iso:country":"AU",
    "sg:address":"52 Kembla St",
    "sg:city":"Fyshwick",
    "sg:classifiers":[
        {
            "category":"Manufacturing",
            "subcategory":"Buildings",
            "type":"Manufacturing & Wholesale Goods"
        }
    ],
    "sg:phone":"+61 2 6280 9809",
    "sg:postcode":"2609",
    "sg:province":"ACT",
    "sg:tags":[
        "house",
        "gazebo",
        "shade"
    ],
    "wof:name":"Homeplus Vergola",
    "wof:placetype":"venue"
},
  "geometry": {"coordinates":[149.176025391,-35.3239212036],"type":"Point"}
}