{
  "type": "Feature",
  "properties": {
    "iso:country":"AU",
    "sg:address":"2 Station St",
    "sg:city":"Cobden",
    "sg:classifiers":[
        {
            "category":"Utilities",
            "subcategory":"Electric",
            "type":"Services"
        }
    ],
    "sg:phone":"+61 3 5595 1948",
    "sg:postcode":"3266",
    "sg:province":"VIC",
    "sg:tags":[
        "electrical",
        "contractor"
    ],
    "wof:name":"Dickinson Electrical Service Pty Ltd",
    "wof:placetype":"venue"
},
  "geometry": {"coordinates":[143.06483459500001,-38.3263816833],"type":"Point"}
}