{
  "type": "Feature",
  "properties": {
    "iso:country":"AU",
    "sg:address":"38 William St",
    "sg:city":"Dayboro",
    "sg:classifiers":[
        {
            "category":"Real Estate",
            "subcategory":"Real Estate Agent",
            "type":"Services"
        }
    ],
    "sg:phone":"+61 7 3425 1300",
    "sg:postcode":"4521",
    "sg:province":"QLD",
    "wof:name":"Dennis Sharkey Real Estate Pty Ltd",
    "wof:placetype":"venue"
},
  "geometry": {"coordinates":[152.825287,-27.196033],"type":"Point"}
}