{
  "type": "Feature",
  "properties": {
    "addr:full":"103 Sydenham Rd Marrickville NSW 2204",
    "addr:housenumber":"103",
    "addr:postcode":"2204",
    "addr:street":"Sydenham Rd",
    "iso:country":"AU",
    "sg:address":"103 Sydenham Rd",
    "sg:city":"Marrickville",
    "sg:classifiers":[
        {
            "category":"Retail",
            "subcategory":"Auto Repair",
            "type":"Services"
        }
    ],
    "sg:phone":"+61 2 9550 6097",
    "sg:postcode":"2204",
    "sg:province":"NSW",
    "sg:tags":[
        "repairer",
        "motor",
        "engineer"
    ],
    "wof:name":"Steves Auto Repairs Marrickville",
    "wof:placetype":"venue"
},
  "geometry": {"coordinates":[151.16331500000001,-33.910236],"type":"Point"}
}