{
  "type": "Feature",
  "properties": {
    "iso:country":"AU",
    "sg:address":"Capalaba Park Shopng Cntr",
    "sg:city":"Capalaba",
    "sg:classifiers":[
        {
            "category":"Personal",
            "type":"Services"
        }
    ],
    "sg:phone":"+61 7 3245 5174",
    "sg:postcode":"4157",
    "sg:province":"QLD",
    "sg:tags":[
        "gift"
    ],
    "wof:name":"A Capalaba Park Florist",
    "wof:placetype":"venue"
},
  "geometry": {"coordinates":[153.18942260700001,-27.5298175812],"type":"Point"}
}