{
  "type": "Feature",
  "properties": {
    "iso:country":"AU",
    "sg:address":"Hamilton Hwy",
    "sg:city":"Derrinallum",
    "sg:classifiers":[
        {
            "category":"Farming",
            "subcategory":"Farm & Veterinary Services",
            "type":"Manufacturing & Wholesale Goods"
        }
    ],
    "sg:phone":"+61 3 5597 6717",
    "sg:postcode":"3325",
    "sg:province":"VIC",
    "sg:tags":[
        "contracting"
    ],
    "wof:name":"Johndella",
    "wof:placetype":"venue"
},
  "geometry": {"coordinates":[143.22648599999999,-37.947983],"type":"Point"}
}