{
  "type": "Feature",
  "properties": {
    "iso:country":"AU",
    "sg:address":"241 Victoria Rd",
    "sg:city":"Rydalmere",
    "sg:classifiers":[
        {
            "category":"Manufacturing",
            "subcategory":"Motor Vehicles & Parts",
            "type":"Manufacturing & Wholesale Goods"
        }
    ],
    "sg:phone":"+61 2 9684 4066",
    "sg:postcode":"2116",
    "sg:province":"NSW",
    "sg:tags":[
        "replacement"
    ],
    "wof:name":"Justcomm Spares",
    "wof:placetype":"venue"
},
  "geometry": {"coordinates":[151.161346436,-33.9105186462],"type":"Point"}
}