{
  "type": "Feature",
  "properties": {
    "addr:full":"Surrey St Hyde Park QLD 4812",
    "addr:postcode":"4812",
    "addr:street":"Surrey St",
    "iso:country":"AU",
    "sg:address":"Surrey St",
    "sg:city":"Hyde Park",
    "sg:classifiers":[
        {
            "category":"Education",
            "subcategory":"School",
            "type":"Public Place"
        }
    ],
    "sg:phone":"+61 7 4775 4170",
    "sg:postcode":"4812",
    "sg:province":"QLD",
    "sg:tags":[
        "state",
        "except",
        "nsw"
    ],
    "wof:name":"Hermit Park Preschool",
    "wof:placetype":"venue"
},
  "geometry": {"coordinates":[146.79440299999999,-19.279896],"type":"Point"}
}