{
  "type": "Feature",
  "properties": {
    "iso:country":"AU",
    "sg:address":"10/ 14 Rothcote Crt",
    "sg:city":"West Burleigh",
    "sg:classifiers":[
        {
            "category":"Mining & Drilling",
            "type":"Manufacturing & Wholesale Goods"
        }
    ],
    "sg:phone":"+61 7 5522 1366",
    "sg:postcode":"4219",
    "sg:province":"QLD",
    "sg:tags":[
        "steel",
        "window"
    ],
    "wof:name":"Protect A Window Pty Ltd",
    "wof:placetype":"venue"
},
  "geometry": {"coordinates":[153.418334961,-28.1018295288],"type":"Point"}
}