{
  "type": "Feature",
  "properties": {
    "iso:country":"AU",
    "sg:address":"1240 Nepean Hwy",
    "sg:city":"Cheltenham",
    "sg:classifiers":[
        {
            "category":"Autos & Motor Vehicles",
            "subcategory":"Automobile Sales",
            "type":"Retail Goods"
        }
    ],
    "sg:phone":"+61 3 9584 9974",
    "sg:postcode":"3192",
    "sg:province":"VIC",
    "sg:tags":[
        "car",
        "new"
    ],
    "wof:name":"Straightway Suzuki",
    "wof:placetype":"venue"
},
  "geometry": {"coordinates":[145.058425903,-37.9670143127],"type":"Point"}
}