{
  "type": "Feature",
  "properties": {
    "addr:full":"86 Island View Drv Wondunna QLD 4655",
    "addr:housenumber":"86",
    "addr:postcode":"4655",
    "addr:street":"Island View Drv",
    "iso:country":"AU",
    "sg:address":"86 Island View Drv",
    "sg:city":"Wondunna",
    "sg:classifiers":[
        {
            "category":"Military Area",
            "subcategory":"Army Base",
            "type":"Public Place"
        }
    ],
    "sg:phone":"+61 7 4125 4720",
    "sg:postcode":"4655",
    "sg:province":"QLD",
    "sg:tags":[
        "concrete",
        "slab",
        "floor"
    ],
    "wof:name":"Mark Rosier Concreters",
    "wof:placetype":"venue"
},
  "geometry": {"coordinates":[152.89880400000001,-25.321156],"type":"Point"}
}