{
  "type": "Feature",
  "properties": {
    "addr:full":"9 Brewers St Burpengary QLD 4505",
    "addr:housenumber":"9",
    "addr:postcode":"4505",
    "addr:street":"Brewers St",
    "iso:country":"AU",
    "sg:address":"9 Brewers St",
    "sg:city":"Burpengary",
    "sg:classifiers":[
        {
            "category":"Building & Trades",
            "subcategory":"Construction",
            "type":"Services"
        }
    ],
    "sg:phone":"+61 7 3888 8799",
    "sg:postcode":"4505",
    "sg:province":"QLD",
    "sg:tags":[
        "installation",
        "air conditioning"
    ],
    "sg:website":"http://www.snowdonia-aircon.com.au",
    "wof:name":"Snowdonia Airconditioning Services Pty Ltd",
    "wof:placetype":"venue"
},
  "geometry": {"coordinates":[152.98109435999999,-27.1629638672],"type":"Point"}
}