{
  "type": "Feature",
  "properties": {
    "iso:country":"AU",
    "sg:address":"39 Stanley St",
    "sg:city":"Bankstown",
    "sg:classifiers":[
        {
            "category":"Professional",
            "subcategory":"Employment Agencies",
            "type":"Services"
        }
    ],
    "sg:phone":"+61 2 9791 6077",
    "sg:postcode":"2200",
    "sg:province":"NSW",
    "wof:name":"Job Futures",
    "wof:placetype":"venue"
},
  "geometry": {"coordinates":[151.036087,-33.92065],"type":"Point"}
}