{
  "type": "Feature",
  "properties": {
    "iso:country":"AU",
    "sg:address":"16- 18 Jervois St",
    "sg:city":"Port Augusta",
    "sg:classifiers":[
        {
            "category":"Retail",
            "subcategory":"Funeral Services",
            "type":"Services"
        }
    ],
    "sg:phone":"+61 8 8642 2660",
    "sg:postcode":"5700",
    "sg:province":"SA",
    "sg:tags":[
        "director"
    ],
    "wof:name":"Mortlock Funerals",
    "wof:placetype":"venue"
},
  "geometry": {"coordinates":[137.76463317899999,-32.4918479919],"type":"Point"}
}