{
  "type": "Feature",
  "properties": {
    "iso:country":"AU",
    "sg:address":"Suite 6 Ground Floor AHC House 14 Carrara St",
    "sg:city":"Benowa",
    "sg:classifiers":[
        {
            "category":"Health Services",
            "subcategory":"Doctor",
            "type":"Services"
        }
    ],
    "sg:phone":"+61 7 5597 3127",
    "sg:postcode":"4217",
    "sg:province":"QLD",
    "sg:tags":[
        "medical",
        "practitioner"
    ],
    "wof:name":"Dr David Christie",
    "wof:placetype":"venue"
},
  "geometry": {"coordinates":[153.39295959500001,-28.0088024139],"type":"Point"}
}