{
  "type": "Feature",
  "properties": {
    "addr:full":"111 Palmerin St Warwick QLD 4370",
    "addr:housenumber":"111",
    "addr:postcode":"4370",
    "addr:street":"Palmerin St",
    "iso:country":"AU",
    "sg:address":"111 Palmerin St",
    "sg:city":"Warwick",
    "sg:classifiers":[
        {
            "category":"Manufacturing",
            "subcategory":"Jewelry",
            "type":"Manufacturing & Wholesale Goods"
        }
    ],
    "sg:phone":"+61 7 4661 4744",
    "sg:postcode":"4370",
    "sg:province":"QLD",
    "sg:tags":[
        "designer",
        "jewellery"
    ],
    "wof:name":"Bensonhurst Jewellers",
    "wof:placetype":"venue"
},
  "geometry": {"coordinates":[152.03233337399999,-28.2169952393],"type":"Point"}
}