{
  "type": "Feature",
  "properties": {
    "iso:country":"AU",
    "sg:address":"20 Railway Pde",
    "sg:city":"Welshpool",
    "sg:classifiers":[
        {
            "category":"Shopping",
            "subcategory":"Pets & Pet Supplies",
            "type":"Retail Goods"
        }
    ],
    "sg:phone":"+61 8 9350 6587",
    "sg:postcode":"6106",
    "sg:province":"WA",
    "sg:tags":[
        "food"
    ],
    "wof:name":"Valet Beta Group",
    "wof:placetype":"venue"
},
  "geometry": {"coordinates":[115.92407989500001,-31.9951190948],"type":"Point"}
}