{
  "type": "Feature",
  "properties": {
    "addr:full":"74 Jamison St Laverton VIC 3028",
    "addr:housenumber":"74",
    "addr:postcode":"3028",
    "addr:street":"Jamison St",
    "iso:country":"AU",
    "sg:address":"74 Jamison St",
    "sg:city":"Laverton",
    "sg:classifiers":[
        {
            "category":"Home & Garden",
            "subcategory":"Carpets & Floor Coverings",
            "type":"Retail Goods"
        }
    ],
    "sg:phone":"+61 3 9369 9491",
    "sg:postcode":"3028",
    "sg:province":"VIC",
    "sg:tags":[
        "wood"
    ],
    "wof:name":"QAP Timber Floor",
    "wof:placetype":"venue"
},
  "geometry": {"coordinates":[144.774033,-37.870995],"type":"Point"}
}