{
  "type": "Feature",
  "properties": {
    "iso:country":"AU",
    "sg:address":"24 Toomuc Valley Rd",
    "sg:city":"Pakenham",
    "sg:classifiers":[
        {
            "category":"Organizations",
            "subcategory":"Non-profit Organization",
            "type":"Services"
        }
    ],
    "sg:phone":"+61 3 5941 1535",
    "sg:postcode":"3810",
    "sg:province":"VIC",
    "sg:tags":[
        "support",
        "disability",
        "organisation"
    ],
    "wof:name":"Outlook (Vic) Inc",
    "wof:placetype":"venue"
},
  "geometry": {"coordinates":[145.466553,-38.06094],"type":"Point"}
}