{
  "type": "Feature",
  "properties": {
    "addr:full":"PO Box 784 Howard Springs NT 0835",
    "addr:postcode":"nt 0835",
    "iso:country":"AU",
    "sg:address":"PO Box 784",
    "sg:city":"Howard Springs",
    "sg:classifiers":[
        {
            "category":"Building & Trades",
            "subcategory":"Construction",
            "type":"Services"
        }
    ],
    "sg:phone":"+61 417 808 489",
    "sg:postcode":"0835",
    "sg:province":"NT",
    "sg:tags":[
        "concrete",
        "contractor"
    ],
    "wof:name":"Rock Hard Concreting",
    "wof:placetype":"venue"
},
  "geometry": {"coordinates":[131.04579200000001,-12.49626],"type":"Point"}
}