{
  "type": "Feature",
  "properties": {
    "addr:full":"8 Acacia St Katoomba NSW 2780",
    "addr:housenumber":"8",
    "addr:postcode":"2780",
    "addr:street":"Acacia St",
    "iso:country":"AU",
    "sg:address":"8 Acacia St",
    "sg:city":"Katoomba",
    "sg:classifiers":[
        {
            "category":"Utilities",
            "subcategory":"Electric",
            "type":"Services"
        }
    ],
    "sg:phone":"+61 2 4782 1977",
    "sg:postcode":"2780",
    "sg:province":"NSW",
    "sg:tags":[
        "electrical",
        "contractor"
    ],
    "wof:name":"Geoff Hilder",
    "wof:placetype":"venue"
},
  "geometry": {"coordinates":[150.29579162600001,-33.7267036438],"type":"Point"}
}