{
  "type": "Feature",
  "properties": {
    "addr:full":"334 Timor St Warrnambool VIC 3280",
    "addr:housenumber":"334",
    "addr:postcode":"3280",
    "addr:street":"Timor St",
    "iso:country":"AU",
    "sg:address":"334 Timor St",
    "sg:city":"Warrnambool",
    "sg:classifiers":[
        {
            "category":"Health Services",
            "subcategory":"Doctor",
            "type":"Services"
        }
    ],
    "sg:phone":"+61 3 5560 5833",
    "sg:postcode":"3280",
    "sg:province":"VIC",
    "sg:tags":[
        "occupational",
        "safety"
    ],
    "wof:name":"Tim Rayner Audiology",
    "wof:placetype":"venue"
},
  "geometry": {"coordinates":[142.47151184099999,-38.380405426],"type":"Point"}
}