{
  "type": "Feature",
  "properties": {
    "addr:full":"PO Box 76 Red Cliffs VIC 3496",
    "addr:postcode":"3496",
    "iso:country":"AU",
    "sg:address":"PO Box 76",
    "sg:city":"Red Cliffs",
    "sg:classifiers":[
        {
            "category":"Mining & Drilling",
            "type":"Manufacturing & Wholesale Goods"
        }
    ],
    "sg:phone":"+61 427 243 413",
    "sg:postcode":"3496",
    "sg:province":"VIC",
    "sg:tags":[
        "boring",
        "contractor"
    ],
    "wof:name":"Mildura Concrete Cutting And Coring",
    "wof:placetype":"venue"
},
  "geometry": {"coordinates":[142.18652343799999,-34.3077087402],"type":"Point"}
}