{
  "type": "Feature",
  "properties": {
    "addr:full":"10 Darvelle La Mt Eliza VIC 3930",
    "addr:housenumber":"10",
    "addr:postcode":"3930",
    "addr:street":"Darvelle La",
    "iso:country":"AU",
    "sg:address":"10 Darvelle La",
    "sg:city":"Mt Eliza",
    "sg:classifiers":[
        {
            "category":"Home & Garden",
            "subcategory":"Hardware",
            "type":"Retail Goods"
        }
    ],
    "sg:phone":"+61 3 9787 6143",
    "sg:postcode":"3930",
    "sg:province":"VIC",
    "sg:tags":[
        "repair",
        "tool",
        "power"
    ],
    "wof:name":"A.G.M. Power Tools",
    "wof:placetype":"venue"
},
  "geometry": {"coordinates":[145.10989379899999,-38.1786003113],"type":"Point"}
}