{
  "type": "Feature",
  "properties": {
    "addr:full":"2 Glen St Belrose NSW 2085",
    "addr:housenumber":"2",
    "addr:postcode":"2085",
    "addr:street":"Glen St",
    "iso:country":"AU",
    "sg:address":"2 Glen St",
    "sg:city":"Belrose",
    "sg:classifiers":[
        {
            "category":"Health Services",
            "subcategory":"Health Practitioner",
            "type":"Services"
        }
    ],
    "sg:phone":"+61 2 8901 0870",
    "sg:postcode":"2085",
    "sg:province":"NSW",
    "sg:tags":[
        "acupuncture"
    ],
    "wof:name":"Acupuncture Asscn Of Australia Inc",
    "wof:placetype":"venue"
},
  "geometry": {"coordinates":[151.219192505,-33.7389068604],"type":"Point"}
}