{
  "type": "Feature",
  "properties": {
    "iso:country":"AU",
    "sg:address":"60 Smith St",
    "sg:city":"Collingwood",
    "sg:classifiers":[
        {
            "category":"Education",
            "subcategory":"Dance Studio",
            "type":"Public Place"
        }
    ],
    "sg:phone":"+61 425 145 106",
    "sg:postcode":"3066",
    "sg:province":"VIC",
    "sg:tags":[
        "venue",
        "tuition"
    ],
    "wof:name":"Pole Fetish Dance School",
    "wof:placetype":"venue"
},
  "geometry": {"coordinates":[144.98312377900001,-37.8065071106],"type":"Point"}
}