{
  "type": "Feature",
  "properties": {
    "iso:country":"AU",
    "sg:address":"Unit 1, 25 Hallstrom Pl",
    "sg:city":"Wetherill Park",
    "sg:classifiers":[
        {
            "category":"Wholesale",
            "subcategory":"Durable Goods & Equipment",
            "type":"Manufacturing & Wholesale Goods"
        }
    ],
    "sg:phone":"+61 2 9725 1828",
    "sg:postcode":"2164",
    "sg:province":"NSW",
    "sg:tags":[
        "abrasive",
        "blasting"
    ],
    "wof:name":"Abrasive Grit Co",
    "wof:placetype":"venue"
},
  "geometry": {"coordinates":[150.885375977,-33.8448677063],"type":"Point"}
}