{
  "type": "Feature",
  "properties": {
    "addr:full":"10 - 14 Parade St Pingelly WA 6308",
    "addr:housenumber":"14",
    "addr:postcode":"6308",
    "addr:street":"Parade St",
    "iso:country":"AU",
    "sg:address":"10 - 14 Parade St",
    "sg:city":"Pingelly",
    "sg:classifiers":[
        {
            "category":"Banks & Credit Unions",
            "subcategory":"Bank",
            "type":"Services"
        }
    ],
    "sg:phone":"+61 13 20 32",
    "sg:postcode":"6308",
    "sg:province":"WA",
    "wof:name":"Westpac",
    "wof:placetype":"venue"
},
  "geometry": {"coordinates":[117.084289551,-32.5338897705],"type":"Point"}
}