{
  "type": "Feature",
  "properties": {
    "addr:full":"Shop 2 65 Tank St Gladstone QLD 4680",
    "addr:housenumber":"shop;65",
    "addr:postcode":"4680",
    "addr:street":"Tank St",
    "iso:country":"AU",
    "sg:address":"Shop 2 65 Tank St",
    "sg:city":"Gladstone",
    "sg:classifiers":[
        {
            "category":"Personal",
            "subcategory":"Beauty Salon",
            "type":"Services"
        }
    ],
    "sg:phone":"+61 7 4972 4488",
    "sg:postcode":"4680",
    "sg:province":"QLD",
    "sg:tags":[
        "hairdresser"
    ],
    "wof:name":"Crowning Glory Hair Works",
    "wof:placetype":"venue"
},
  "geometry": {"coordinates":[151.25550842300001,-23.8511772156],"type":"Point"}
}