{
  "type": "Feature",
  "properties": {
    "addr:full":"Offices 2/6 Park Rd Jindabyne NSW 2627",
    "addr:housenumber":"2 / 6",
    "addr:postcode":"2627",
    "addr:street":"Park Rd",
    "iso:country":"AU",
    "sg:address":"Offices 2/6 Park Rd",
    "sg:city":"Jindabyne",
    "sg:classifiers":[
        {
            "category":"Health Services",
            "subcategory":"Dentist",
            "type":"Services"
        }
    ],
    "sg:phone":"+61 2 6456 1870",
    "sg:postcode":"2627",
    "sg:province":"NSW",
    "wof:name":"Snowy Mountains Dental",
    "wof:placetype":"venue"
},
  "geometry": {"coordinates":[148.62113952600001,-36.4165153503],"type":"Point"}
}