{
  "type": "Feature",
  "properties": {
    "addr:full":"PO Box 232 Barcaldine QLD 4725",
    "addr:postcode":"4725",
    "iso:country":"AU",
    "sg:address":"PO Box 232",
    "sg:city":"Barcaldine",
    "sg:classifiers":[
        {
            "category":"Communications",
            "subcategory":"News Services",
            "type":"Services"
        }
    ],
    "sg:phone":"+61 7 4651 2211",
    "sg:postcode":"4725",
    "sg:province":"QLD",
    "sg:tags":[
        "information",
        "tourist",
        "attractions"
    ],
    "wof:name":"Artesian Country Tours",
    "wof:placetype":"venue"
},
  "geometry": {"coordinates":[145.28407300000001,-23.55266],"type":"Point"}
}