{
  "type": "Feature",
  "properties": {
    "addr:full":"Block D5 - Shed 5 Horizon Shores Marina Woongoolba QLD 4207",
    "addr:housenumber":"5",
    "addr:postcode":"4207",
    "addr:street":"Horizon Shores Marina",
    "iso:country":"AU",
    "sg:address":"Block D5 - Shed 5 Horizon Shores Marina",
    "sg:city":"Woongoolba",
    "sg:classifiers":[
        {
            "category":"Autos & Motor Vehicles",
            "subcategory":"Boat Sales",
            "type":"Retail Goods"
        }
    ],
    "sg:phone":"+61 7 5546 1599",
    "sg:postcode":"4207",
    "sg:province":"QLD",
    "sg:tags":[
        "builder",
        "yacht",
        "repairer"
    ],
    "wof:name":"Wood On Water",
    "wof:placetype":"venue"
},
  "geometry": {"coordinates":[153.18261718799999,-27.7140674591],"type":"Point"}
}