{
  "type": "Feature",
  "properties": {
    "iso:country":"AU",
    "sg:address":"1373 Gympie Rd",
    "sg:city":"Aspley",
    "sg:classifiers":[
        {
            "category":"Personal",
            "subcategory":"Barber",
            "type":"Services"
        }
    ],
    "sg:phone":"+61 7 3263 5226",
    "sg:postcode":"4034",
    "sg:province":"QLD",
    "wof:name":"John Abbott",
    "wof:placetype":"venue"
},
  "geometry": {"coordinates":[153.017426,-27.362034],"type":"Point"}
}