{
  "type": "Feature",
  "properties": {
    "addr:full":"16 Bridge St Reynella SA 5161",
    "addr:housenumber":"16",
    "addr:postcode":"5161",
    "addr:street":"Bridge St",
    "iso:country":"AU",
    "sg:address":"16 Bridge St",
    "sg:city":"Reynella",
    "sg:classifiers":[
        {
            "category":"Home & Garden",
            "subcategory":"Building Materials",
            "type":"Retail Goods"
        }
    ],
    "sg:phone":"+61 422 479 439",
    "sg:postcode":"5161",
    "sg:province":"SA",
    "sg:tags":[
        "merchant",
        "glass",
        "glazier"
    ],
    "wof:name":"Scratchtech",
    "wof:placetype":"venue"
},
  "geometry": {"coordinates":[138.539230347,-35.0898780823],"type":"Point"}
}