{
  "type": "Feature",
  "properties": {
    "addr:full":"Level 2, 88- 90 Foveaux St Surry Hills NSW 2010",
    "addr:housenumber":"88 90",
    "addr:postcode":"2010",
    "addr:street":"Foveaux St",
    "iso:country":"AU",
    "sg:address":"Level 2, 88- 90 Foveaux St",
    "sg:city":"Surry Hills",
    "sg:classifiers":[
        {
            "category":"Health Services",
            "subcategory":"Dentist",
            "type":"Services"
        }
    ],
    "sg:phone":"+61 2 9211 0388",
    "sg:postcode":"2010",
    "sg:province":"NSW",
    "sg:tags":[
        "technician",
        "dental"
    ],
    "wof:name":"Wagner & King Ceramics Pty Ltd",
    "wof:placetype":"venue"
},
  "geometry": {"coordinates":[151.21214294399999,-33.884677887],"type":"Point"}
}