{
  "type": "Feature",
  "properties": {
    "iso:country":"AU",
    "sg:address":"854 Old Cleveland Rd",
    "sg:city":"Carina",
    "sg:classifiers":[
        {
            "category":"Banks & Credit Unions",
            "subcategory":"Bank",
            "type":"Services"
        }
    ],
    "sg:phone":"+61 7 3324 9555",
    "sg:postcode":"4152",
    "sg:province":"QLD",
    "sg:tags":[
        "broker",
        "mortgage"
    ],
    "wof:name":"City Pacific Finance",
    "wof:placetype":"venue"
},
  "geometry": {"coordinates":[153.093383789,-27.4953994751],"type":"Point"}
}