{
  "type": "Feature",
  "properties": {
    "iso:country":"AU",
    "sg:address":"15 Coorumby Ave",
    "sg:city":"Clifton Springs",
    "sg:classifiers":[
        {
            "category":"Professional",
            "subcategory":"Employment Agencies",
            "type":"Services"
        }
    ],
    "sg:phone":"+61 3 5253 2912",
    "sg:postcode":"3222",
    "sg:province":"VIC",
    "sg:tags":[
        "provider",
        "internet"
    ],
    "wof:name":"Drysdale Computers",
    "wof:placetype":"venue"
},
  "geometry": {"coordinates":[144.57672099999999,-38.151325],"type":"Point"}
}