{
  "type": "Feature",
  "properties": {
    "iso:country":"AU",
    "sg:address":"289 Mona Vale Rd",
    "sg:city":"St Ives",
    "sg:classifiers":[
        {
            "category":"Social Services",
            "type":"Services"
        }
    ],
    "sg:phone":"+61 2 9144 1713",
    "sg:postcode":"2075",
    "sg:province":"NSW",
    "sg:tags":[
        "disabled",
        "person",
        "equipment"
    ],
    "wof:name":"Myco Australia",
    "wof:placetype":"venue"
},
  "geometry": {"coordinates":[151.16900634800001,-33.725189209],"type":"Point"}
}