{
  "type": "Feature",
  "properties": {
    "iso:country":"AU",
    "sg:address":"25- 27 Mackay St",
    "sg:city":"Macksville",
    "sg:classifiers":[
        {
            "category":"Home & Garden",
            "subcategory":"Building Materials",
            "type":"Retail Goods"
        }
    ],
    "sg:phone":"+61 1300 682 980",
    "sg:postcode":"2447",
    "sg:province":"NSW",
    "sg:tags":[
        "pre-mixed",
        "concrete"
    ],
    "wof:name":"Kancon Concrete Group The",
    "wof:placetype":"venue"
},
  "geometry": {"coordinates":[152.916916,-30.706432],"type":"Point"}
}