{
  "type": "Feature",
  "properties": {
    "addr:full":"147 George St Quirindi NSW 2343",
    "addr:housenumber":"147",
    "addr:postcode":"2343",
    "addr:street":"George St",
    "iso:country":"AU",
    "sg:address":"147 George St",
    "sg:city":"Quirindi",
    "sg:classifiers":[
        {
            "category":"Professional",
            "subcategory":"Accounting & Tax Preparation",
            "type":"Services"
        }
    ],
    "sg:phone":"+61 2 6746 1288",
    "sg:postcode":"2343",
    "sg:province":"NSW",
    "sg:tags":[
        "consultant",
        "taxation"
    ],
    "wof:name":"Brackenbury Green & Associates",
    "wof:placetype":"venue"
},
  "geometry": {"coordinates":[150.679153442,-31.5113792419],"type":"Point"}
}