{
  "type": "Feature",
  "properties": {
    "addr:full":"32-36 Victoria St Riverstone NSW 2765",
    "addr:housenumber":"32-36",
    "addr:postcode":"2765",
    "addr:street":"Victoria St",
    "iso:country":"AU",
    "sg:address":"32-36 Victoria St",
    "sg:city":"Riverstone",
    "sg:classifiers":[
        {
            "category":"Transit Center",
            "subcategory":"Freight",
            "type":"Transportation"
        }
    ],
    "sg:phone":"+61 2 9627 4866",
    "sg:postcode":"2765",
    "sg:province":"NSW",
    "sg:tags":[
        "forklift",
        "truck"
    ],
    "wof:name":"Hubtex Australia",
    "wof:placetype":"venue"
},
  "geometry": {"coordinates":[150.857955933,-33.6618080139],"type":"Point"}
}