{
  "type": "Feature",
  "properties": {
    "addr:full":"13- 15 Maple St Cooroy QLD 4563",
    "addr:housenumber":"15",
    "addr:postcode":"4563",
    "addr:street":"Maple St",
    "iso:country":"AU",
    "sg:address":"13- 15 Maple St",
    "sg:city":"Cooroy",
    "sg:classifiers":[
        {
            "category":"Education",
            "subcategory":"Kindergarten",
            "type":"Public Place"
        }
    ],
    "sg:phone":"+61 7 5447 6037",
    "sg:postcode":"4563",
    "sg:province":"QLD",
    "sg:tags":[
        "pre-schools"
    ],
    "wof:name":"C&K Cooroy Community Kindergarten",
    "wof:placetype":"venue"
},
  "geometry": {"coordinates":[152.91058349599999,-26.4166984558],"type":"Point"}
}