{
  "type": "Feature",
  "properties": {
    "iso:country":"AU",
    "sg:address":"8 Smith St",
    "sg:city":"Lennox Head",
    "sg:classifiers":[
        {
            "category":"Building & Trades",
            "subcategory":"Construction",
            "type":"Services"
        }
    ],
    "sg:phone":"+61 2 6687 6769",
    "sg:postcode":"2478",
    "sg:province":"NSW",
    "sg:tags":[
        "joiner",
        "carpenter"
    ],
    "wof:name":"McDarmont Alan",
    "wof:placetype":"venue"
},
  "geometry": {"coordinates":[153.602615356,-28.8297595978],"type":"Point"}
}