{
  "type": "Feature",
  "properties": {
    "addr:full":"16 Cairns Ave Seaton SA 5023",
    "addr:housenumber":"16",
    "addr:postcode":"5023",
    "addr:street":"Cairns Ave",
    "iso:country":"AU",
    "sg:address":"16 Cairns Ave",
    "sg:city":"Seaton",
    "sg:classifiers":[
        {
            "category":"Organizations",
            "subcategory":"Community Association",
            "type":"Services"
        }
    ],
    "sg:phone":"+61 8 8268 7272",
    "sg:postcode":"5023",
    "sg:province":"SA",
    "sg:tags":[
        "club",
        "senior",
        "citizen"
    ],
    "wof:name":"Seaton North Senior Citizens Club",
    "wof:placetype":"venue"
},
  "geometry": {"coordinates":[138.50590515100001,-34.8812904358],"type":"Point"}
}