{
  "type": "Feature",
  "properties": {
    "iso:country":"AU",
    "sg:address":"405 Flemington Rd",
    "sg:city":"North Melbourne",
    "sg:classifiers":[
        {
            "category":"Professional",
            "subcategory":"Computer Services",
            "type":"Services"
        }
    ],
    "sg:phone":"+61 3 9329 3377",
    "sg:postcode":"3051",
    "sg:province":"VIC",
    "sg:tags":[
        "repairs",
        "upgrade",
        "equipment"
    ],
    "wof:name":"Frazer Electronics Pty Ltd",
    "wof:placetype":"venue"
},
  "geometry": {"coordinates":[144.942169189,-37.7897911072],"type":"Point"}
}