{
  "type": "Feature",
  "properties": {
    "addr:full":"136 Church St Balranald NSW 2715",
    "addr:housenumber":"136",
    "addr:postcode":"2715",
    "addr:street":"Church St",
    "iso:country":"AU",
    "sg:address":"136 Church St",
    "sg:city":"Balranald",
    "sg:classifiers":[
        {
            "category":"Farming",
            "subcategory":"Farm & Veterinary Services",
            "type":"Manufacturing & Wholesale Goods"
        }
    ],
    "sg:phone":"+61 3 5020 1543",
    "sg:postcode":"2715",
    "sg:province":"NSW",
    "sg:tags":[
        "shearing",
        "contractor"
    ],
    "wof:name":"Greenham M W & H L",
    "wof:placetype":"venue"
},
  "geometry": {"coordinates":[143.561157227,-34.6353874207],"type":"Point"}
}