{
  "type": "Feature",
  "properties": {
    "addr:full":"14 Bindea St Jannali NSW 2226",
    "addr:housenumber":"14",
    "addr:postcode":"2226",
    "addr:street":"Bindea St",
    "iso:country":"AU",
    "sg:address":"14 Bindea St",
    "sg:city":"Jannali",
    "sg:classifiers":[
        {
            "category":"Building & Trades",
            "subcategory":"Locksmith",
            "type":"Services"
        }
    ],
    "sg:phone":"+61 2 9589 4016",
    "sg:postcode":"2226",
    "sg:province":"NSW",
    "sg:tags":[
        "lock"
    ],
    "wof:name":"Ozzie Locksmiths",
    "wof:placetype":"venue"
},
  "geometry": {"coordinates":[151.065307617,-34.0088310242],"type":"Point"}
}