{
  "type": "Feature",
  "properties": {
    "addr:full":"30 Induna St South Grafton NSW 2460",
    "addr:housenumber":"30",
    "addr:postcode":"2460",
    "addr:street":"Induna St",
    "iso:country":"AU",
    "sg:address":"30 Induna St",
    "sg:city":"South Grafton",
    "sg:classifiers":[
        {
            "category":"Building & Trades",
            "subcategory":"Electrical",
            "type":"Services"
        }
    ],
    "sg:phone":"+61 2 6642 7022",
    "sg:postcode":"2460",
    "sg:province":"NSW",
    "sg:tags":[
        "repair",
        "generator",
        "electric",
        "motor"
    ],
    "wof:name":"Brown Finley Rewinding Service",
    "wof:placetype":"venue"
},
  "geometry": {"coordinates":[152.94517517099999,-29.7223720551],"type":"Point"}
}