{
  "type": "Feature",
  "properties": {
    "addr:full":"100 Darghan St Glebe NSW 2037",
    "addr:housenumber":"100",
    "addr:postcode":"2037",
    "addr:street":"Darghan St",
    "iso:country":"AU",
    "sg:address":"100 Darghan St",
    "sg:city":"Glebe",
    "sg:classifiers":[
        {
            "category":"Real Estate",
            "subcategory":"Real Estate Agent",
            "type":"Services"
        }
    ],
    "sg:phone":"+61 2 9518 4584",
    "sg:postcode":"2037",
    "sg:province":"NSW",
    "sg:tags":[
        "consultant",
        "heritage"
    ],
    "wof:name":"Museum Planning Services Australia",
    "wof:placetype":"venue"
},
  "geometry": {"coordinates":[151.189453125,-33.8770256042],"type":"Point"}
}