{
  "type": "Feature",
  "properties": {
    "addr:full":"81 Main St Mittagong NSW 2575",
    "addr:housenumber":"81",
    "addr:postcode":"2575",
    "addr:street":"Main St",
    "iso:country":"AU",
    "sg:address":"81 Main St",
    "sg:city":"Mittagong",
    "sg:classifiers":[
        {
            "category":"Cafe",
            "type":"Food & Drink"
        }
    ],
    "sg:phone":"+61 2 4872 1724",
    "sg:postcode":"2575",
    "sg:province":"NSW",
    "wof:name":"Toddy's Coffee Shop",
    "wof:placetype":"venue"
},
  "geometry": {"coordinates":[150.447631836,-34.4511184692],"type":"Point"}
}