{
  "type": "Feature",
  "properties": {
    "iso:country":"AU",
    "sg:address":"102 Lyell St",
    "sg:city":"Mittagong",
    "sg:classifiers":[
        {
            "category":"Home & Garden",
            "subcategory":"Building Materials",
            "type":"Retail Goods"
        }
    ],
    "sg:phone":"+61 2 4871 2144",
    "sg:postcode":"2575",
    "sg:province":"NSW",
    "sg:tags":[
        "fitting",
        "door"
    ],
    "wof:name":"Evalock",
    "wof:placetype":"venue"
},
  "geometry": {"coordinates":[150.43145751899999,-34.4489593506],"type":"Point"}
}