{
  "type": "Feature",
  "properties": {
    "iso:country":"AU",
    "sg:address":"85 Carabooda Rd",
    "sg:city":"Carabooda",
    "sg:classifiers":[
        {
            "category":"Farming",
            "subcategory":"Berry Farm",
            "type":"Manufacturing & Wholesale Goods"
        }
    ],
    "sg:phone":"+61 8 9407 5100",
    "sg:postcode":"6033",
    "sg:province":"WA",
    "sg:tags":[
        "fruit",
        "grower"
    ],
    "wof:name":"Avowest Avocados",
    "wof:placetype":"venue"
},
  "geometry": {"coordinates":[115.722427368,-31.6075057983],"type":"Point"}
}