{
  "type": "Feature",
  "properties": {
    "addr:full":"73 Francis St Bondi NSW 2026",
    "addr:housenumber":"73",
    "addr:postcode":"2026",
    "addr:street":"Francis St",
    "iso:country":"AU",
    "sg:address":"73 Francis St",
    "sg:city":"Bondi",
    "sg:classifiers":[
        {
            "category":"Building & Trades",
            "subcategory":"Plumbing",
            "type":"Services"
        }
    ],
    "sg:phone":"+61 2 9365 6410",
    "sg:postcode":"2026",
    "sg:province":"NSW",
    "sg:tags":[
        "plumber",
        "gasfitters"
    ],
    "wof:name":"A.Aaaaaabcan Plumbing",
    "wof:placetype":"venue"
},
  "geometry": {"coordinates":[151.26919555699999,-33.8922767639],"type":"Point"}
}