{
  "type": "Feature",
  "properties": {
    "addr:full":"PO Box 139 Mena Creek QLD 4871",
    "addr:postcode":"4871",
    "iso:country":"AU",
    "sg:address":"PO Box 139",
    "sg:city":"Mena Creek",
    "sg:classifiers":[
        {
            "category":"Building & Trades",
            "subcategory":"Pest Control",
            "type":"Services"
        }
    ],
    "sg:phone":"+61 427 159 266",
    "sg:postcode":"4871",
    "sg:province":"QLD",
    "wof:name":"Lamperd's Pest Control & Carpet Cleaning",
    "wof:placetype":"venue"
},
  "geometry": {"coordinates":[145.960647583,-17.6587905884],"type":"Point"}
}