{
  "type": "Feature",
  "properties": {
    "addr:full":"MTA House, Level 1/ 83 Greenhill Rd Wayville SA 5034",
    "addr:housenumber":"mta;level;/ 83",
    "addr:postcode":"5034",
    "addr:street":"Greenhill Rd",
    "iso:country":"AU",
    "sg:address":"MTA House, Level 1/ 83 Greenhill Rd",
    "sg:city":"Wayville",
    "sg:classifiers":[
        {
            "category":"Education",
            "subcategory":"Special Training",
            "type":"Public Place"
        }
    ],
    "sg:phone":"+61 8 8208 4888",
    "sg:postcode":"5034",
    "sg:province":"SA",
    "sg:tags":[
        "development"
    ],
    "wof:name":"Automotive Business College",
    "wof:placetype":"venue"
},
  "geometry": {"coordinates":[138.59750366200001,-34.9416122437],"type":"Point"}
}