{
  "type": "Feature",
  "properties": {
    "addr:full":"88 Wood St Mackay QLD 4740",
    "addr:housenumber":"88",
    "addr:postcode":"4740",
    "addr:street":"Wood St",
    "iso:country":"AU",
    "sg:address":"88 Wood St",
    "sg:city":"Mackay",
    "sg:classifiers":[
        {
            "category":"Shopping",
            "subcategory":"Clothing, Apparel, & Fashions",
            "type":"Retail Goods"
        }
    ],
    "sg:phone":"+61 7 4951 3817",
    "sg:postcode":"4740",
    "sg:province":"QLD",
    "sg:tags":[
        "lady",
        "wear"
    ],
    "wof:name":"Stockline Clothing",
    "wof:placetype":"venue"
},
  "geometry": {"coordinates":[149.185486,-21.142822],"type":"Point"}
}