{
  "type": "Feature",
  "properties": {
    "iso:country":"AU",
    "sg:address":"Shop 38 Wills Rd",
    "sg:city":"North Woolooware",
    "sg:classifiers":[
        {
            "category":"Shopping",
            "subcategory":"Clothing, Apparel, & Fashions",
            "type":"Retail Goods"
        }
    ],
    "sg:phone":"+61 2 9523 6855",
    "sg:postcode":"2230",
    "sg:province":"NSW",
    "sg:tags":[
        "maternity",
        "wear"
    ],
    "wof:name":"B Js Maternity Boutique",
    "wof:placetype":"venue"
},
  "geometry": {"coordinates":[151.14523315400001,-34.0455589294],"type":"Point"}
}