{
  "type": "Feature",
  "properties": {
    "iso:country":"AU",
    "sg:address":"Foodcourt FC5 Westfield Burwood 158 Burwood Rd",
    "sg:city":"Burwood",
    "sg:classifiers":[
        {
            "category":"Fast Food",
            "type":"Food & Drink"
        }
    ],
    "sg:phone":"+61 2 9744 0110",
    "sg:postcode":"2134",
    "sg:province":"NSW",
    "sg:tags":[
        "away",
        "take"
    ],
    "wof:name":"KFC",
    "wof:placetype":"venue"
},
  "geometry": {"coordinates":[151.104049683,-33.8763847351],"type":"Point"}
}