{
  "type": "Feature",
  "properties": {
    "iso:country":"AU",
    "sg:address":"28 Birt Ave",
    "sg:city":"Budds Beach",
    "sg:classifiers":[
        {
            "category":"Building & Trades",
            "subcategory":"Cleaning & Sanitation",
            "type":"Services"
        }
    ],
    "sg:phone":"+61 402 076 501",
    "sg:postcode":"4218",
    "sg:province":"QLD",
    "sg:tags":[
        "industrial",
        "commercial",
        "contractor"
    ],
    "wof:name":"Bob Johnston Cleaning",
    "wof:placetype":"venue"
},
  "geometry": {"coordinates":[153.42562866200001,-27.9924602509],"type":"Point"}
}