{
  "type": "Feature",
  "properties": {
    "addr:full":"4 Dooley St Warrnambool VIC 3280",
    "addr:housenumber":"4",
    "addr:postcode":"3280",
    "addr:street":"Dooley St",
    "iso:country":"AU",
    "sg:address":"4 Dooley St",
    "sg:city":"Warrnambool",
    "sg:classifiers":[
        {
            "category":"Professional",
            "subcategory":"Accounting & Tax Preparation",
            "type":"Services"
        }
    ],
    "sg:phone":"+61 3 5561 3629",
    "sg:postcode":"3280",
    "sg:province":"VIC",
    "sg:tags":[
        "accountant",
        "auditor"
    ],
    "wof:name":"O'Donnell Darren J",
    "wof:placetype":"venue"
},
  "geometry": {"coordinates":[142.49395751899999,-38.3654632568],"type":"Point"}
}