{
  "type": "Feature",
  "properties": {
    "addr:full":"PO Box 2043 Edithvale VIC 3196",
    "addr:postcode":"3196",
    "iso:country":"AU",
    "sg:address":"PO Box 2043",
    "sg:city":"Edithvale",
    "sg:classifiers":[
        {
            "category":"Building & Trades",
            "subcategory":"Plumbing",
            "type":"Services"
        }
    ],
    "sg:phone":"+61 417 687 711",
    "sg:postcode":"3196",
    "sg:province":"VIC",
    "sg:tags":[
        "plumber",
        "gasfitters"
    ],
    "wof:name":"Jim Spence Plumbing",
    "wof:placetype":"venue"
},
  "geometry": {"coordinates":[145.11370849599999,-38.0369682312],"type":"Point"}
}