{
  "type": "Feature",
  "properties": {
    "addr:full":"6 Malcolm Rd Maddington WA 6109",
    "addr:housenumber":"6",
    "addr:postcode":"6109",
    "addr:street":"Malcolm Rd",
    "iso:country":"AU",
    "sg:address":"6 Malcolm Rd",
    "sg:city":"Maddington",
    "sg:classifiers":[
        {
            "category":"Retail",
            "subcategory":"Auto Repair",
            "type":"Services"
        }
    ],
    "sg:phone":"+61 8 9459 3430",
    "sg:postcode":"6109",
    "sg:province":"WA",
    "sg:tags":[
        "beater",
        "painter",
        "panel"
    ],
    "wof:name":"Maddington Smash Repairs",
    "wof:placetype":"venue"
},
  "geometry": {"coordinates":[115.985092163,-32.0417938232],"type":"Point"}
}