{
  "type": "Feature",
  "properties": {
    "addr:full":"PO Box 20 Alexandra VIC 3714",
    "addr:postcode":"3714",
    "iso:country":"AU",
    "sg:address":"PO Box 20",
    "sg:city":"Alexandra",
    "sg:classifiers":[
        {
            "category":"Organizations",
            "subcategory":"Non-profit Organization",
            "type":"Services"
        }
    ],
    "sg:phone":"+61 3 5772 1888",
    "sg:postcode":"3714",
    "sg:province":"VIC",
    "sg:tags":[
        "support",
        "disability",
        "organisation"
    ],
    "wof:name":"Dame Pattie Menzies Centre Inc",
    "wof:placetype":"venue"
},
  "geometry": {"coordinates":[145.71035766599999,-37.1914596558],"type":"Point"}
}