{
  "type": "Feature",
  "properties": {
    "iso:country":"AU",
    "sg:address":"Brimbank Shopng Cntr Cnr Neale & Station Rds",
    "sg:city":"Deer Park",
    "sg:classifiers":[
        {
            "category":"Personal",
            "subcategory":"Shoe Repair & Shine",
            "type":"Services"
        }
    ],
    "sg:phone":"+61 3 9361 1600",
    "sg:postcode":"3023",
    "sg:province":"VIC",
    "sg:tags":[
        "footwear"
    ],
    "wof:name":"Cobbler Plus Services Pty Ltd",
    "wof:placetype":"venue"
},
  "geometry": {"coordinates":[144.776657,-37.752533],"type":"Point"}
}