{
  "type": "Feature",
  "properties": {
    "addr:full":"35 Edgar St Werribee VIC 3030",
    "addr:housenumber":"35",
    "addr:postcode":"3030",
    "addr:street":"Edgar St",
    "iso:country":"AU",
    "sg:address":"35 Edgar St",
    "sg:city":"Werribee",
    "sg:classifiers":[
        {
            "category":"Professional",
            "subcategory":"Engineering",
            "type":"Services"
        }
    ],
    "sg:phone":"+61 3 9741 3005",
    "sg:postcode":"3030",
    "sg:province":"VIC",
    "sg:tags":[
        "engineer"
    ],
    "wof:name":"G.T.H. Engineering Pty Ltd",
    "wof:placetype":"venue"
},
  "geometry": {"coordinates":[144.646759,-37.898563],"type":"Point"}
}