{
  "type": "Feature",
  "properties": {
    "iso:country":"AU",
    "sg:address":"2/ 38 Klauer St",
    "sg:city":"Seaford",
    "sg:classifiers":[
        {
            "category":"Autos & Motor Vehicles",
            "subcategory":"Auto Supplies",
            "type":"Retail Goods"
        }
    ],
    "sg:phone":"+61 3 9785 7027",
    "sg:postcode":"3198",
    "sg:province":"VIC",
    "sg:tags":[
        "tyre"
    ],
    "wof:name":"AAA The Tyre Factory",
    "wof:placetype":"venue"
},
  "geometry": {"coordinates":[145.14068603499999,-38.1189155579],"type":"Point"}
}