{
  "type": "Feature",
  "properties": {
    "iso:country":"AU",
    "sg:address":"157 Baillie St",
    "sg:city":"Horsham",
    "sg:classifiers":[
        {
            "category":"Personal",
            "subcategory":"Massage",
            "type":"Services"
        }
    ],
    "sg:phone":"+61 419 507 817",
    "sg:postcode":"3400",
    "sg:province":"VIC",
    "sg:tags":[
        "therapy"
    ],
    "wof:name":"Kane Jon Horsham",
    "wof:placetype":"venue"
},
  "geometry": {"coordinates":[142.19984435999999,-36.7118721008],"type":"Point"}
}