{
  "type": "Feature",
  "properties": {
    "iso:country":"AU",
    "sg:address":"329 Barry Rd",
    "sg:city":"Campbellfield",
    "sg:classifiers":[
        {
            "category":"Fast Food",
            "type":"Food & Drink"
        }
    ],
    "sg:phone":"+61 3 9357 9602",
    "sg:postcode":"3061",
    "sg:province":"VIC",
    "sg:tags":[
        "away",
        "take"
    ],
    "wof:name":"Barry Rd Chinese Take Away",
    "wof:placetype":"venue"
},
  "geometry": {"coordinates":[144.94869995100001,-37.6667404175],"type":"Point"}
}