{
  "type": "Feature",
  "properties": {
    "addr:full":"13 Gleadow St Invermay TAS 7248",
    "addr:housenumber":"13",
    "addr:postcode":"7248",
    "addr:street":"Gleadow St",
    "iso:country":"AU",
    "sg:address":"13 Gleadow St",
    "sg:city":"Invermay",
    "sg:classifiers":[
        {
            "category":"Manufacturing",
            "subcategory":"Rubber & Plastics",
            "type":"Manufacturing & Wholesale Goods"
        }
    ],
    "sg:phone":"+61 3 6334 3648",
    "sg:postcode":"7248",
    "sg:province":"TAS",
    "sg:tags":[
        "fabricator"
    ],
    "wof:name":"T & T Plastics",
    "wof:placetype":"venue"
},
  "geometry": {"coordinates":[147.136260986,-41.4267730713],"type":"Point"}
}