{
  "type": "Feature",
  "properties": {
    "addr:full":"29 Bel-Air Drv Port Lincoln SA 5606",
    "addr:housenumber":"29",
    "addr:postcode":"5606",
    "addr:street":"Bel-Air Drv",
    "iso:country":"AU",
    "sg:address":"29 Bel-Air Drv",
    "sg:city":"Port Lincoln",
    "sg:classifiers":[
        {
            "category":"Retail",
            "subcategory":"Storage",
            "type":"Services"
        }
    ],
    "sg:phone":"+61 8 8682 6111",
    "sg:postcode":"5606",
    "sg:province":"SA",
    "wof:name":"Safestore Self Storage",
    "wof:placetype":"venue"
},
  "geometry": {"coordinates":[135.85827599999999,-34.736412],"type":"Point"}
}