{
  "type": "Feature",
  "properties": {
    "addr:full":"2- 8 Edsall St Malvern VIC 3144",
    "addr:housenumber":"8",
    "addr:postcode":"3144",
    "addr:street":"Edsall St",
    "iso:country":"AU",
    "sg:address":"2- 8 Edsall St",
    "sg:city":"Malvern",
    "sg:classifiers":[
        {
            "category":"Food & Beverages",
            "subcategory":"Liquor & Beverages",
            "type":"Retail Goods"
        }
    ],
    "sg:phone":"+61 1300 723 388",
    "sg:postcode":"3144",
    "sg:province":"VIC",
    "sg:tags":[
        "store"
    ],
    "wof:name":"Dan Murphy's",
    "wof:placetype":"venue"
},
  "geometry": {"coordinates":[145.02879333499999,-37.8609771729],"type":"Point"}
}