{
  "type": "Feature",
  "properties": {
    "addr:full":"14 Rose St Chippendale NSW 2008",
    "addr:housenumber":"14",
    "addr:postcode":"2008",
    "addr:street":"Rose St",
    "iso:country":"AU",
    "sg:address":"14 Rose St",
    "sg:city":"Chippendale",
    "sg:classifiers":[
        {
            "category":"Education",
            "subcategory":"University",
            "type":"Public Place"
        }
    ],
    "sg:phone":"+61 2 9212 4440",
    "sg:postcode":"2008",
    "sg:province":"NSW",
    "sg:tags":[
        "educational",
        "organisation",
        "cultural"
    ],
    "wof:name":"Australian South Sea Islanders United Council",
    "wof:placetype":"venue"
},
  "geometry": {"coordinates":[151.195480347,-33.8856811523],"type":"Point"}
}