{
  "type": "Feature",
  "properties": {
    "iso:country":"AU",
    "sg:address":"46 Gapcum Crt",
    "sg:city":"Noble Park",
    "sg:classifiers":[
        {
            "category":"Professional",
            "subcategory":"Computer Services",
            "type":"Services"
        }
    ],
    "sg:phone":"+61 3 9512 3246",
    "sg:postcode":"3174",
    "sg:province":"VIC",
    "sg:tags":[
        "repairs",
        "upgrade",
        "equipment"
    ],
    "wof:name":"Multimedia Microsystems",
    "wof:placetype":"venue"
},
  "geometry": {"coordinates":[145.18382263199999,-37.9638595581],"type":"Point"}
}