{
  "type": "Feature",
  "properties": {
    "addr:full":"74- 76 The Boulevard Toronto NSW 2283",
    "addr:housenumber":"76",
    "addr:postcode":"2283",
    "addr:street":"The Boulevard",
    "iso:country":"AU",
    "sg:address":"74- 76",
    "sg:city":"The Boulevard Toronto",
    "sg:classifiers":[
        {
            "category":"Banks & Credit Unions",
            "subcategory":"Bank",
            "type":"Services"
        }
    ],
    "sg:phone":"+61 13 20 32",
    "sg:postcode":"2283",
    "sg:province":"NSW",
    "wof:name":"Westpac",
    "wof:placetype":"venue"
},
  "geometry": {"coordinates":[151.58074951200001,-33.0651473999],"type":"Point"}
}