{
  "type": "Feature",
  "properties": {
    "addr:full":"PO Box 96 Rosemeadow NSW 2560",
    "addr:postcode":"2560",
    "iso:country":"AU",
    "sg:address":"PO Box 96",
    "sg:city":"Rosemeadow",
    "sg:classifiers":[
        {
            "category":"Retail",
            "subcategory":"Event Space",
            "type":"Services"
        }
    ],
    "sg:phone":"+61 2 4621 3414",
    "sg:postcode":"2560",
    "sg:province":"NSW",
    "sg:tags":[
        "function",
        "organiser"
    ],
    "wof:name":"Heritage Catering",
    "wof:placetype":"venue"
},
  "geometry": {"coordinates":[150.797897339,-34.1005210876],"type":"Point"}
}