{
  "type": "Feature",
  "properties": {
    "iso:country":"AU",
    "sg:address":"Shop 16 Livingston Market Pl Ranford Rd",
    "sg:city":"Canning Vale",
    "sg:classifiers":[
        {
            "category":"Retail",
            "subcategory":"Repair Shop",
            "type":"Services"
        }
    ],
    "sg:phone":"+61 8 9455 6333",
    "sg:postcode":"6155",
    "sg:province":"WA",
    "sg:tags":[
        "mending",
        "clothing",
        "alteration"
    ],
    "wof:name":"Livingston Drycleaners",
    "wof:placetype":"venue"
},
  "geometry": {"coordinates":[115.9226,-32.091831],"type":"Point"}
}