{
  "type": "Feature",
  "properties": {
    "addr:full":"82 Petra St Bicton WA 6157",
    "addr:housenumber":"82",
    "addr:postcode":"6157",
    "addr:street":"Petra St",
    "iso:country":"AU",
    "sg:address":"82 Petra St",
    "sg:city":"Bicton",
    "sg:classifiers":[
        {
            "category":"Travel",
            "subcategory":"Travel Agent",
            "type":"Entertainment"
        }
    ],
    "sg:phone":"+61 8 9339 5199",
    "sg:postcode":"6157",
    "sg:province":"WA",
    "sg:tags":[
        "consultant"
    ],
    "wof:name":"Cruisefinder.com.au",
    "wof:placetype":"venue"
},
  "geometry": {"coordinates":[115.776329,-32.038036],"type":"Point"}
}