{
  "type": "Feature",
  "properties": {
    "addr:full":"PO Box 702 South Perth WA 6151",
    "addr:postcode":"6151",
    "iso:country":"AU",
    "sg:address":"PO Box 702",
    "sg:city":"South Perth",
    "sg:classifiers":[
        {
            "category":"Home & Garden",
            "subcategory":"Carpets & Floor Coverings",
            "type":"Retail Goods"
        }
    ],
    "sg:phone":"+61 433 235 483",
    "sg:postcode":"6151",
    "sg:province":"WA",
    "sg:tags":[
        "flooring",
        "parquet"
    ],
    "wof:name":"Black Label Timber Flooring",
    "wof:placetype":"venue"
},
  "geometry": {"coordinates":[115.870239,-31.98105],"type":"Point"}
}