{
  "type": "Feature",
  "properties": {
    "addr:full":"2 Mikarie St Kirrawee NSW 2232",
    "addr:housenumber":"2",
    "addr:postcode":"2232",
    "addr:street":"Mikarie St",
    "iso:country":"AU",
    "sg:address":"2 Mikarie St",
    "sg:city":"Kirrawee",
    "sg:classifiers":[
        {
            "category":"Education",
            "subcategory":"School",
            "type":"Public Place"
        }
    ],
    "sg:phone":"+61 2 8536 0100",
    "sg:postcode":"2232",
    "sg:province":"NSW",
    "wof:name":"Handicapped Childrens Centre N S W",
    "wof:placetype":"venue"
},
  "geometry": {"coordinates":[151.083709717,-34.0229721069],"type":"Point"}
}