{
  "type": "Feature",
  "properties": {
    "addr:full":"Shop 40 Morayfield Shopping Centre Morayfield QLD 4506",
    "addr:housenumber":"shop 40",
    "addr:postcode":"4506",
    "addr:street":"Morayfield Shopping",
    "iso:country":"AU",
    "sg:address":"Shop 40",
    "sg:city":"Morayfield Shopping Centre Morayfield",
    "sg:classifiers":[
        {
            "category":"Personal",
            "subcategory":"Beauty Salon",
            "type":"Services"
        }
    ],
    "sg:phone":"+61 3 5495 3155",
    "sg:postcode":"4506",
    "sg:province":"QLD",
    "sg:tags":[
        "hairdresser"
    ],
    "wof:name":"Legends Hairdressing Morayfield",
    "wof:placetype":"venue"
},
  "geometry": {"coordinates":[152.949508667,-27.1095695496],"type":"Point"}
}