{
  "type": "Feature",
  "properties": {
    "iso:country":"AU",
    "sg:address":"U3/ 19 Hamersley St",
    "sg:city":"Broome",
    "sg:classifiers":[
        {
            "category":"Professional",
            "subcategory":"Management & Consulting",
            "type":"Services"
        }
    ],
    "sg:phone":"+61 8 9192 8766",
    "sg:postcode":"6725",
    "sg:province":"WA",
    "sg:tags":[
        "consultant"
    ],
    "wof:name":"Kadar Pearson & Partners",
    "wof:placetype":"venue"
},
  "geometry": {"coordinates":[122.240592956,-17.9600200653],"type":"Point"}
}