{
  "type": "Feature",
  "properties": {
    "addr:full":"360 Elgar Rd Box Hill VIC 3128",
    "addr:housenumber":"360",
    "addr:postcode":"3128",
    "addr:street":"Elgar Rd",
    "iso:country":"AU",
    "sg:address":"360 Elgar Rd",
    "sg:city":"Box Hill",
    "sg:classifiers":[
        {
            "category":"Retail",
            "subcategory":"Auto Rental",
            "type":"Services"
        }
    ],
    "sg:phone":"+61 3 9898 2889",
    "sg:postcode":"3128",
    "sg:province":"VIC",
    "sg:tags":[
        "car",
        "wedding"
    ],
    "sg:website":"http://www.alwaysclassiccars.com.au",
    "wof:name":"Always Classic Cars",
    "wof:placetype":"venue"
},
  "geometry": {"coordinates":[145.11369323700001,-37.8247795105],"type":"Point"}
}