{
  "type": "Feature",
  "properties": {
    "addr:full":"107 Dalmeny Drv Narooma NSW 2546",
    "addr:housenumber":"107",
    "addr:postcode":"2546",
    "addr:street":"Dalmeny Drv",
    "iso:country":"AU",
    "sg:address":"107 Dalmeny Drv",
    "sg:city":"Narooma",
    "sg:classifiers":[
        {
            "category":"Building & Trades",
            "subcategory":"Construction",
            "type":"Services"
        }
    ],
    "sg:phone":"+61 2 4476 1132",
    "sg:postcode":"2546",
    "sg:province":"NSW",
    "sg:tags":[
        "contractor"
    ],
    "wof:name":"Kirby Geoff Construction",
    "wof:placetype":"venue"
},
  "geometry": {"coordinates":[150.12924194300001,-36.1996040344],"type":"Point"}
}