{
  "type": "Feature",
  "properties": {
    "addr:full":"Rear 12 Macartney St Ermington NSW 2115",
    "addr:housenumber":"12",
    "addr:postcode":"2115",
    "addr:street":"Macartney St",
    "iso:country":"AU",
    "sg:address":"Rear 12 Macartney St",
    "sg:city":"Ermington",
    "sg:classifiers":[
        {
            "category":"Retail",
            "subcategory":"Repair Shop",
            "type":"Services"
        }
    ],
    "sg:phone":"+61 2 9613 7633",
    "sg:postcode":"2115",
    "sg:province":"NSW",
    "sg:tags":[
        "upholsterer"
    ],
    "wof:name":"Hebblewhite Motor Trimmers",
    "wof:placetype":"venue"
},
  "geometry": {"coordinates":[151.06050109899999,-33.8168678284],"type":"Point"}
}