{
  "type": "Feature",
  "properties": {
    "iso:country":"AU",
    "sg:address":"47 Brady St",
    "sg:city":"South Melbourne",
    "sg:classifiers":[
        {
            "category":"Shopping",
            "subcategory":"Gifts & Souvenirs",
            "type":"Retail Goods"
        }
    ],
    "sg:phone":"+61 3 9646 2222",
    "sg:postcode":"3205",
    "sg:province":"VIC",
    "sg:tags":[
        "shop",
        "supply"
    ],
    "wof:name":"Gateway Collection",
    "wof:placetype":"venue"
},
  "geometry": {"coordinates":[144.943466,-37.826344],"type":"Point"}
}