{
  "type": "Feature",
  "properties": {
    "addr:full":"Westfield Shopng Cntr Belconnen ACT 2617",
    "addr:postcode":"2617",
    "iso:country":"AU",
    "sg:address":"Westfield Shopng Cntr",
    "sg:city":"Belconnen",
    "sg:classifiers":[
        {
            "category":"Farming",
            "subcategory":"Berry Farm",
            "type":"Manufacturing & Wholesale Goods"
        }
    ],
    "sg:phone":"+61 2 6251 2850",
    "sg:postcode":"2617",
    "sg:province":"ACT",
    "sg:tags":[
        "sheet",
        "music"
    ],
    "wof:name":"Dymocks",
    "wof:placetype":"venue"
},
  "geometry": {"coordinates":[149.059417725,-35.2060089111],"type":"Point"}
}