{
  "type": "Feature",
  "properties": {
    "iso:country":"AU",
    "sg:address":"Unit 6 154 Highbury Rd",
    "sg:city":"Burwood",
    "sg:classifiers":[
        {
            "category":"Sports & Exercise",
            "subcategory":"Race Track",
            "type":"Entertainment"
        }
    ],
    "sg:phone":"+61 1300 309 150",
    "sg:postcode":"3125",
    "sg:province":"VIC",
    "sg:tags":[
        "relay"
    ],
    "wof:name":"Ramelec Electronics Pty Ltd",
    "wof:placetype":"venue"
},
  "geometry": {"coordinates":[145.11210632300001,-37.8553962708],"type":"Point"}
}