{
  "type": "Feature",
  "properties": {
    "addr:full":"536 Rode Rd Chermside QLD 4032",
    "addr:postcode":"qld 4032",
    "addr:street":"Rode Rd",
    "iso:country":"AU",
    "sg:address":"536 Rode Rd",
    "sg:city":"Chermside",
    "sg:classifiers":[
        {
            "category":"Retail",
            "subcategory":"Auto Repair",
            "type":"Services"
        }
    ],
    "sg:phone":"+61 7 3350 4366",
    "sg:postcode":"4032",
    "sg:province":"QLD",
    "sg:tags":[
        "electrical"
    ],
    "wof:name":"Alpine Car Air Conditioning",
    "wof:placetype":"venue"
},
  "geometry": {"coordinates":[153.02499399999999,-27.392633],"type":"Point"}
}