{
  "type": "Feature",
  "properties": {
    "addr:full":"206 Nelson Rd Mt Nelson TAS 7007",
    "addr:housenumber":"206",
    "addr:postcode":"7007",
    "addr:street":"Nelson Rd",
    "iso:country":"AU",
    "sg:address":"206 Nelson Rd",
    "sg:city":"Mt Nelson",
    "sg:classifiers":[
        {
            "category":"Education",
            "subcategory":"Music School",
            "type":"Public Place"
        }
    ],
    "sg:phone":"+61 3 6225 3483",
    "sg:postcode":"7007",
    "sg:province":"TAS",
    "sg:tags":[
        "teacher"
    ],
    "wof:name":"Gora Rebecca",
    "wof:placetype":"venue"
},
  "geometry": {"coordinates":[147.323455811,-42.9111557007],"type":"Point"}
}