{
  "type": "Feature",
  "properties": {
    "addr:full":"Level 1 , Sunshine Plaza Maroochydore QLD 4558",
    "addr:postcode":"4558",
    "iso:country":"AU",
    "sg:address":"Level 1",
    "sg:city":", Sunshine Plaza Maroochydore",
    "sg:classifiers":[
        {
            "category":"Shopping",
            "subcategory":"Computers & Home Electronics",
            "type":"Retail Goods"
        }
    ],
    "sg:phone":"+61 7 5479 4793",
    "sg:postcode":"4558",
    "sg:province":"QLD",
    "sg:tags":[
        "equipment",
        "supply"
    ],
    "wof:name":"Digital Biz",
    "wof:placetype":"venue"
},
  "geometry": {"coordinates":[153.08045959500001,-26.6549377441],"type":"Point"}
}