{
  "type": "Feature",
  "properties": {
    "addr:full":"Unit 35/ 15 Valediction Rd Kings Park NSW 2148",
    "addr:housenumber":"/ 15",
    "addr:postcode":"2148",
    "addr:street":"Valediction Rd",
    "iso:country":"AU",
    "sg:address":"Unit 35/ 15 Valediction Rd",
    "sg:city":"Kings Park",
    "sg:classifiers":[
        {
            "category":"Shopping",
            "subcategory":"Bicycles & Sporting Goods",
            "type":"Retail Goods"
        }
    ],
    "sg:phone":"+61 1800 777 255",
    "sg:postcode":"2148",
    "sg:province":"NSW",
    "sg:tags":[
        "chemical",
        "equipment",
        "pool",
        "swimming"
    ],
    "wof:name":"Kreepy Krauly",
    "wof:placetype":"venue"
},
  "geometry": {"coordinates":[150.912765503,-33.7454147339],"type":"Point"}
}