{
  "type": "Feature",
  "properties": {
    "iso:country":"AU",
    "sg:address":"31 Clissold St",
    "sg:city":"Ashfield",
    "sg:classifiers":[
        {
            "category":"Health Services",
            "subcategory":"Nursing And Care Facility",
            "type":"Services"
        }
    ],
    "sg:phone":"+61 2 9798 6766",
    "sg:postcode":"2131",
    "sg:province":"NSW",
    "sg:tags":[
        "home"
    ],
    "wof:name":"Bethel Nursing Home",
    "wof:placetype":"venue"
},
  "geometry": {"coordinates":[151.12533569300001,-33.8956565857],"type":"Point"}
}