{
  "type": "Feature",
  "properties": {
    "addr:full":"21 Belmore Rd Randwick NSW 2031",
    "addr:housenumber":"21",
    "addr:postcode":"2031",
    "addr:street":"Belmore Rd",
    "iso:country":"AU",
    "sg:address":"21 Belmore Rd",
    "sg:city":"Randwick",
    "sg:classifiers":[
        {
            "category":"Education",
            "subcategory":"Special Training",
            "type":"Public Place"
        }
    ],
    "sg:phone":"+61 2 9398 1799",
    "sg:postcode":"2031",
    "sg:province":"NSW",
    "sg:tags":[
        "tuition-educational"
    ],
    "wof:name":"Kip McGrath Education Centres",
    "wof:placetype":"venue"
},
  "geometry": {"coordinates":[151.23980712900001,-33.9133491516],"type":"Point"}
}