{
  "type": "Feature",
  "properties": {
    "iso:country":"AU",
    "sg:address":"76 Duffy St",
    "sg:city":"Ainslie",
    "sg:classifiers":[
        {
            "category":"Personal",
            "subcategory":"Hair Removal",
            "type":"Services"
        }
    ],
    "sg:phone":"+61 2 6247 4926",
    "sg:postcode":"2602",
    "sg:province":"ACT",
    "wof:name":"ALA Continental Beautician",
    "wof:placetype":"venue"
},
  "geometry": {"coordinates":[149.1484375,-35.2643737793],"type":"Point"}
}