{
  "type": "Feature",
  "properties": {
    "iso:country":"AU",
    "sg:address":"1 Honeyeater Pl",
    "sg:city":"Erskine Park",
    "sg:classifiers":[
        {
            "category":"Building & Trades",
            "subcategory":"Construction",
            "type":"Services"
        }
    ],
    "sg:phone":"+61 2 9834 4473",
    "sg:postcode":"2759",
    "sg:province":"NSW",
    "sg:tags":[
        "management"
    ],
    "wof:name":"Construction Management Services Pty Ltd",
    "wof:placetype":"venue"
},
  "geometry": {"coordinates":[150.80653381400001,-33.7982215881],"type":"Point"}
}