{
  "type": "Feature",
  "properties": {
    "iso:country":"AU",
    "sg:address":"40 Queens Rd",
    "sg:city":"Asquith",
    "sg:classifiers":[
        {
            "category":"Professional",
            "subcategory":"Art Services",
            "type":"Services"
        }
    ],
    "sg:phone":"+61 2 9477 3092",
    "sg:postcode":"2077",
    "sg:province":"NSW",
    "sg:tags":[
        "artist"
    ],
    "wof:name":"Mari Ricia",
    "wof:placetype":"venue"
},
  "geometry": {"coordinates":[151.115509033,-33.6847457886],"type":"Point"}
}