{
  "type": "Feature",
  "properties": {
    "addr:full":"Unit 20, 380 Marion St Condell Park NSW 2200",
    "addr:housenumber":"380",
    "addr:postcode":"2200",
    "addr:street":"Marion St",
    "iso:country":"AU",
    "sg:address":"Unit 20, 380 Marion St",
    "sg:city":"Condell Park",
    "sg:classifiers":[
        {
            "category":"Home & Garden",
            "subcategory":"Carpets & Floor Coverings",
            "type":"Retail Goods"
        }
    ],
    "sg:phone":"+61 2 9791 1232",
    "sg:postcode":"2200",
    "sg:province":"NSW",
    "sg:tags":[
        "wood"
    ],
    "wof:name":"Fab Floors",
    "wof:placetype":"venue"
},
  "geometry": {"coordinates":[151.00322,-33.916656],"type":"Point"}
}