{
  "type": "Feature",
  "properties": {
    "addr:full":"U3/ 82 Brookman St Kalgoorlie WA 6430",
    "addr:housenumber":"82",
    "addr:postcode":"6430",
    "addr:street":"U3 /;Brookman St",
    "iso:country":"AU",
    "sg:address":"U3/ 82 Brookman St",
    "sg:city":"Kalgoorlie",
    "sg:classifiers":[
        {
            "category":"Personal",
            "subcategory":"Skin Care",
            "type":"Services"
        }
    ],
    "sg:phone":"+61 8 9021 2725",
    "sg:postcode":"6430",
    "sg:province":"WA",
    "sg:tags":[
        "treatment"
    ],
    "wof:name":"Elite Skin & Body Centre",
    "wof:placetype":"venue"
},
  "geometry": {"coordinates":[121.468788147,-30.7491474152],"type":"Point"}
}