{
  "type": "Feature",
  "properties": {
    "iso:country":"AU",
    "sg:address":"10 Distribution Ave",
    "sg:city":"Nerang",
    "sg:classifiers":[
        {
            "category":"Professional",
            "subcategory":"Printing & Photocopies",
            "type":"Services"
        }
    ],
    "sg:phone":"+61 7 5539 4988",
    "sg:postcode":"4211",
    "sg:province":"QLD",
    "sg:tags":[
        "screen",
        "printer"
    ],
    "wof:name":"Wavelength Clothing Co Pty Ltd",
    "wof:placetype":"venue"
},
  "geometry": {"coordinates":[153.35763549800001,-27.9775848389],"type":"Point"}
}