{
  "type": "Feature",
  "properties": {
    "addr:full":"17 Wyperfeld Ave Taylors Lakes VIC 3038",
    "addr:housenumber":"17",
    "addr:postcode":"3038",
    "addr:street":"Wyperfeld Ave",
    "iso:country":"AU",
    "sg:address":"17 Wyperfeld Ave",
    "sg:city":"Taylors Lakes",
    "sg:classifiers":[
        {
            "category":"Manufacturing",
            "subcategory":"Tools & Machinery",
            "type":"Manufacturing & Wholesale Goods"
        }
    ],
    "sg:phone":"+61 3 9390 4222",
    "sg:postcode":"3038",
    "sg:province":"VIC",
    "sg:tags":[
        "machine",
        "industrial",
        "sewing"
    ],
    "wof:name":"Fleming Sewing Machines Pty Ltd",
    "wof:placetype":"venue"
},
  "geometry": {"coordinates":[144.801773,-37.710938],"type":"Point"}
}