{
  "type": "Feature",
  "properties": {
    "iso:country":"AU",
    "sg:address":"887 South Rd",
    "sg:city":"Clarence Gardens",
    "sg:classifiers":[
        {
            "category":"Shopping",
            "subcategory":"Discount & Variety Stores",
            "type":"Retail Goods"
        }
    ],
    "sg:phone":"+61 8 8297 0855",
    "sg:postcode":"5039",
    "sg:province":"SA",
    "sg:tags":[
        "shop",
        "adult"
    ],
    "wof:name":"Taste Adult Store",
    "wof:placetype":"venue"
},
  "geometry": {"coordinates":[138.573654175,-34.9737434387],"type":"Point"}
}