{
  "type": "Feature",
  "properties": {
    "addr:full":"27 Dandenong Rd East Frankston VIC 3199",
    "addr:housenumber":"27",
    "addr:postcode":"3199",
    "addr:street":"Dandenong Rd East",
    "iso:country":"AU",
    "sg:address":"27 Dandenong Rd East",
    "sg:city":"Frankston",
    "sg:classifiers":[
        {
            "category":"Health Services",
            "subcategory":"Dentist",
            "type":"Services"
        }
    ],
    "sg:phone":"+61 3 9783 3215",
    "sg:postcode":"3199",
    "sg:province":"VIC",
    "sg:tags":[
        "technician",
        "dental"
    ],
    "wof:name":"Wallace Malcolm J",
    "wof:placetype":"venue"
},
  "geometry": {"coordinates":[145.12820434599999,-38.13904953],"type":"Point"}
}