{
  "type": "Feature",
  "properties": {
    "iso:country":"AU",
    "sg:address":"7 Dennis St",
    "sg:city":"Colac",
    "sg:classifiers":[
        {
            "category":"Banks & Credit Unions",
            "subcategory":"Financial Services",
            "type":"Services"
        }
    ],
    "sg:phone":"+61 3 5232 1956",
    "sg:postcode":"3250",
    "sg:province":"VIC",
    "sg:tags":[
        "planning"
    ],
    "wof:name":"Charter Financial Planning Limited",
    "wof:placetype":"venue"
},
  "geometry": {"coordinates":[143.58514400000001,-38.338448],"type":"Point"}
}