{
  "type": "Feature",
  "properties": {
    "addr:full":"Unit 4/ 6 Brooks Ave Wyoming NSW 2250",
    "addr:postcode":"2250",
    "addr:street":"Brooks Ave",
    "iso:country":"AU",
    "sg:address":"Unit 4/ 6 Brooks Ave",
    "sg:city":"Wyoming",
    "sg:classifiers":[
        {
            "category":"Arena",
            "subcategory":"Sports Club",
            "type":"Entertainment"
        }
    ],
    "sg:phone":"+61 2 4328 1477",
    "sg:postcode":"2250",
    "sg:province":"NSW",
    "sg:tags":[
        "defence",
        "supply",
        "self",
        "instruction",
        "martial art"
    ],
    "wof:name":"Ultimate Sport & Fitness",
    "wof:placetype":"venue"
},
  "geometry": {"coordinates":[151.346969605,-33.4009475708],"type":"Point"}
}