{
  "type": "Feature",
  "properties": {
    "iso:country":"AU",
    "sg:address":"Lincoln Hwy",
    "sg:city":"Port Lincoln",
    "sg:classifiers":[
        {
            "category":"Utilities",
            "subcategory":"Electric",
            "type":"Services"
        }
    ],
    "sg:phone":"+61 8 8682 6595",
    "sg:postcode":"5606",
    "sg:province":"SA",
    "sg:tags":[
        "electrical",
        "contractor"
    ],
    "wof:name":"Santic K & G A",
    "wof:placetype":"venue"
},
  "geometry": {"coordinates":[135.853683,-34.717701],"type":"Point"}
}