{
  "type": "Feature",
  "properties": {
    "iso:country":"AU",
    "sg:address":"310 Charman Rd",
    "sg:city":"Cheltenham",
    "sg:classifiers":[
        {
            "category":"Food & Beverages",
            "subcategory":"Fruits & Vegetables",
            "type":"Retail Goods"
        }
    ],
    "sg:phone":"+61 419 318 255",
    "sg:postcode":"3192",
    "sg:province":"VIC",
    "sg:tags":[
        "greengrocer",
        "fruiterer"
    ],
    "wof:name":"Cheltenham Fruit Supplies",
    "wof:placetype":"venue"
},
  "geometry": {"coordinates":[145.05564880399999,-37.9665718079],"type":"Point"}
}