{
  "type": "Feature",
  "properties": {
    "addr:full":"B T U Rd Falls Creek NSW 2540",
    "addr:postcode":"2540",
    "addr:street":"U Rd",
    "iso:country":"AU",
    "sg:address":"B T U Rd",
    "sg:city":"Falls Creek",
    "sg:classifiers":[
        {
            "category":"Manufacturing",
            "subcategory":"Lumber",
            "type":"Manufacturing & Wholesale Goods"
        }
    ],
    "sg:phone":"+61 2 4447 8262",
    "sg:postcode":"2540",
    "sg:province":"NSW",
    "sg:tags":[
        "sawmillers"
    ],
    "wof:name":"Davis & Herbert",
    "wof:placetype":"venue"
},
  "geometry": {"coordinates":[150.601394653,-34.9416847229],"type":"Point"}
}