{
  "type": "Feature",
  "properties": {
    "addr:full":"201 Johnson St Collingwood VIC 3066",
    "addr:housenumber":"201",
    "addr:postcode":"3066",
    "addr:street":"Johnson St",
    "iso:country":"AU",
    "sg:address":"201 Johnson St",
    "sg:city":"Collingwood",
    "sg:classifiers":[
        {
            "category":"Food & Beverages",
            "subcategory":"Liquor & Beverages",
            "type":"Retail Goods"
        }
    ],
    "sg:phone":"+61 3 9417 2647",
    "sg:postcode":"3066",
    "sg:province":"VIC",
    "sg:tags":[
        "store"
    ],
    "wof:name":"Cheeers Liquor Group",
    "wof:placetype":"venue"
},
  "geometry": {"coordinates":[144.99223327600001,-37.7998847961],"type":"Point"}
}