{
  "type": "Feature",
  "properties": {
    "addr:full":"Unit 7a/8- 12 Acacia Ave Port Macquarie NSW 2444",
    "addr:housenumber":"unit 7a / 8 12",
    "addr:postcode":"2444",
    "addr:street":"Acacia Ave",
    "iso:country":"AU",
    "sg:address":"Unit 7a/8- 12 Acacia Ave",
    "sg:city":"Port Macquarie",
    "sg:classifiers":[
        {
            "category":"Wholesale",
            "subcategory":"Electrical",
            "type":"Manufacturing & Wholesale Goods"
        }
    ],
    "sg:phone":"+61 2 6581 1522",
    "sg:postcode":"2444",
    "sg:province":"NSW",
    "sg:tags":[
        "wholesaler"
    ],
    "wof:name":"TLE Electrical",
    "wof:placetype":"venue"
},
  "geometry": {"coordinates":[152.88601700000001,-31.444448],"type":"Point"}
}