{
  "type": "Feature",
  "properties": {
    "addr:full":"49 Tennant St Fyshwick ACT 2609",
    "addr:housenumber":"49",
    "addr:postcode":"2609",
    "addr:street":"Tennant St",
    "iso:country":"AU",
    "sg:address":"49 Tennant St",
    "sg:city":"Fyshwick",
    "sg:classifiers":[
        {
            "category":"Professional",
            "subcategory":"Accounting & Tax Preparation",
            "type":"Services"
        }
    ],
    "sg:phone":"+61 2 6280 4888",
    "sg:postcode":"2609",
    "sg:province":"ACT",
    "sg:tags":[
        "record",
        "business",
        "destruction"
    ],
    "sg:website":"http://www.nrd.com.au",
    "wof:name":"National Record Destruction",
    "wof:placetype":"venue"
},
  "geometry": {"coordinates":[149.187042236,-35.3328361511],"type":"Point"}
}