{
  "type": "Feature",
  "properties": {
    "iso:country":"AU",
    "sg:address":"71 Pikett St",
    "sg:city":"Clontarf",
    "sg:classifiers":[
        {
            "category":"Freight",
            "type":"Transportation"
        }
    ],
    "sg:phone":"+61 418 785 696",
    "sg:postcode":"4019",
    "sg:province":"QLD",
    "sg:tags":[
        "light",
        "carrier"
    ],
    "wof:name":"Redcliffe Freight & Taxi Trucks",
    "wof:placetype":"venue"
},
  "geometry": {"coordinates":[153.087722778,-27.2360458374],"type":"Point"}
}