{
  "type": "Feature",
  "properties": {
    "iso:country":"AU",
    "sg:address":"Rear 52 Roberts St",
    "sg:city":"Footscray West",
    "sg:classifiers":[
        {
            "category":"Community Center",
            "subcategory":"Social",
            "type":"Public Place"
        }
    ],
    "sg:phone":"+61 3 9314 6346",
    "sg:postcode":"3012",
    "sg:province":"VIC",
    "sg:tags":[
        "precision",
        "grinding"
    ],
    "wof:name":"Charles Engineering Pty Ltd",
    "wof:placetype":"venue"
},
  "geometry": {"coordinates":[144.870635986,-37.8052864075],"type":"Point"}
}