{
  "type": "Feature",
  "properties": {
    "addr:full":"29 Melville Pde South Perth WA 6151",
    "addr:housenumber":"29",
    "addr:postcode":"6151",
    "addr:street":"Melville Pde South",
    "iso:country":"AU",
    "sg:address":"29 Melville Pde",
    "sg:city":"South Perth",
    "sg:classifiers":[
        {
            "category":"Travel",
            "subcategory":"Hotels & Motels",
            "type":"Entertainment"
        }
    ],
    "sg:phone":"+61 8 9474 4474",
    "sg:postcode":"6151",
    "sg:province":"WA",
    "sg:website":"http://www.assured.net.au",
    "wof:name":"Assured Waterside Apartments",
    "wof:placetype":"venue"
},
  "geometry": {"coordinates":[115.8479,-31.970457],"type":"Point"}
}