{
  "type": "Feature",
  "properties": {
    "addr:full":"14 Adams Rd Cashmere QLD 4500",
    "addr:housenumber":"14",
    "addr:postcode":"4500",
    "addr:street":"Adams Rd",
    "iso:country":"AU",
    "sg:address":"14 Adams Rd",
    "sg:city":"Cashmere",
    "sg:classifiers":[
        {
            "category":"Professional",
            "subcategory":"Employment Agencies",
            "type":"Services"
        }
    ],
    "sg:phone":"+61 7 3882 0499",
    "sg:postcode":"4500",
    "sg:province":"QLD",
    "wof:name":"Wilson Staffing Solutions Pty Ltd",
    "wof:placetype":"venue"
},
  "geometry": {"coordinates":[152.931472778,-27.291677475],"type":"Point"}
}