{
  "type": "Feature",
  "properties": {
    "iso:country":"AU",
    "sg:address":"11 Leslie St",
    "sg:city":"Nundah",
    "sg:classifiers":[
        {
            "category":"Professional",
            "subcategory":"Computer Services",
            "type":"Services"
        }
    ],
    "sg:phone":"+61 7 3266 3900",
    "sg:postcode":"4012",
    "sg:province":"QLD",
    "sg:tags":[
        "tele-communications",
        "consultant"
    ],
    "wof:name":"Nicstar Telecommunications & Project Management",
    "wof:placetype":"venue"
},
  "geometry": {"coordinates":[153.05653381400001,-27.4036808014],"type":"Point"}
}