{
  "type": "Feature",
  "properties": {
    "iso:country":"AU",
    "sg:address":"162 River Rd (East)",
    "sg:city":"Harwood Island",
    "sg:classifiers":[
        {
            "category":"Building & Trades",
            "subcategory":"Cleaning & Sanitation",
            "type":"Services"
        }
    ],
    "sg:phone":"+61 2 6646 4222",
    "sg:postcode":"2465",
    "sg:province":"NSW",
    "sg:tags":[
        "abrasive",
        "blasting"
    ],
    "wof:name":"Harwood Slipway & Engineering",
    "wof:placetype":"venue"
},
  "geometry": {"coordinates":[153.25306701700001,-29.4248981476],"type":"Point"}
}