{
  "type": "Feature",
  "properties": {
    "addr:full":"39 Hamilton St Gisborne VIC 3437",
    "addr:housenumber":"39",
    "addr:postcode":"3437",
    "addr:street":"Hamilton St",
    "iso:country":"AU",
    "sg:address":"39 Hamilton St",
    "sg:city":"Gisborne",
    "sg:classifiers":[
        {
            "category":"Health Services",
            "subcategory":"Optometrist",
            "type":"Services"
        }
    ],
    "sg:phone":"+61 3 5428 4333",
    "sg:postcode":"3437",
    "sg:province":"VIC",
    "wof:name":"Simon Leong Optometrist",
    "wof:placetype":"venue"
},
  "geometry": {"coordinates":[144.58833313,-37.4876785278],"type":"Point"}
}