{
  "type": "Feature",
  "properties": {
    "iso:country":"AU",
    "sg:address":"4 blair Crt",
    "sg:city":"Lavington",
    "sg:classifiers":[
        {
            "category":"Home & Garden",
            "subcategory":"Carpets & Floor Coverings",
            "type":"Retail Goods"
        }
    ],
    "sg:phone":"+61 2 6025 9598",
    "sg:postcode":"2641",
    "sg:province":"NSW",
    "sg:tags":[
        "tile",
        "wall"
    ],
    "wof:name":"Harrison Lee & Melinda",
    "wof:placetype":"venue"
},
  "geometry": {"coordinates":[146.908081055,-36.0430870056],"type":"Point"}
}