{
  "type": "Feature",
  "properties": {
    "addr:full":"1190 Dandenong Rd Murrumbeena VIC 3163",
    "addr:postcode":"1190;3163",
    "addr:street":"Dandenong Rd",
    "iso:country":"AU",
    "sg:address":"1190 Dandenong Rd",
    "sg:city":"Murrumbeena",
    "sg:classifiers":[
        {
            "category":"Professional",
            "subcategory":"Accounting & Tax Preparation",
            "type":"Services"
        }
    ],
    "sg:phone":"+61 3 9568 0188",
    "sg:postcode":"3163",
    "sg:province":"VIC",
    "sg:tags":[
        "accountant",
        "auditor"
    ],
    "wof:name":"Trytell Wheller & Boucher",
    "wof:placetype":"venue"
},
  "geometry": {"coordinates":[145.06767273,-37.8848075867],"type":"Point"}
}