{
  "type": "Feature",
  "properties": {
    "addr:full":"Brearley Ave Redcliffe WA 6104",
    "addr:postcode":"6104",
    "addr:street":"Brearley Ave",
    "iso:country":"AU",
    "sg:address":"Brearley Ave",
    "sg:city":"Redcliffe",
    "sg:classifiers":[
        {
            "category":"Autos & Motor Vehicles",
            "subcategory":"Fuel & Gas Station",
            "type":"Retail Goods"
        }
    ],
    "sg:phone":"+61 8 9277 3152",
    "sg:postcode":"6104",
    "sg:province":"WA",
    "wof:name":"Shell Airport",
    "wof:placetype":"venue"
},
  "geometry": {"coordinates":[115.947669983,-31.932964325],"type":"Point"}
}