{
  "type": "Feature",
  "properties": {
    "iso:country":"AU",
    "sg:address":"258 Blackburn Rd",
    "sg:city":"Doncaster East",
    "sg:classifiers":[
        {
            "category":"Personal",
            "subcategory":"Beauty Salon",
            "type":"Services"
        }
    ],
    "sg:phone":"+61 3 9841 9946",
    "sg:postcode":"3109",
    "sg:province":"VIC",
    "sg:tags":[
        "hairdresser"
    ],
    "wof:name":"Silkcut Salon",
    "wof:placetype":"venue"
},
  "geometry": {"coordinates":[145.163665772,-37.7821884155],"type":"Point"}
}