{
  "type": "Feature",
  "properties": {
    "addr:full":"125 Greens Rd Dandenong VIC 3175",
    "addr:housenumber":"125",
    "addr:postcode":"3175",
    "addr:street":"Greens Rd",
    "iso:country":"AU",
    "sg:address":"125 Greens Rd",
    "sg:city":"Dandenong",
    "sg:classifiers":[
        {
            "category":"Wholesale",
            "subcategory":"Auto Parts",
            "type":"Manufacturing & Wholesale Goods"
        }
    ],
    "sg:phone":"+61 3 9793 4332",
    "sg:postcode":"3175",
    "sg:province":"VIC",
    "sg:tags":[
        "recyclers"
    ],
    "wof:name":"Jolly's U Pull It",
    "wof:placetype":"venue"
},
  "geometry": {"coordinates":[145.21182250999999,-38.0140419006],"type":"Point"}
}