{
  "type": "Feature",
  "properties": {
    "iso:country":"AU",
    "sg:address":"49 Fairy St",
    "sg:city":"Warrnambool",
    "sg:classifiers":[
        {
            "category":"Building & Trades",
            "subcategory":"Equipment Rental",
            "type":"Services"
        }
    ],
    "sg:phone":"+61 3 5562 2326",
    "sg:postcode":"3280",
    "sg:province":"VIC",
    "sg:tags":[
        "renting",
        "trailer"
    ],
    "wof:name":"Johnsons Garage",
    "wof:placetype":"venue"
},
  "geometry": {"coordinates":[142.477783203,-38.3830986023],"type":"Point"}
}