{
  "type": "Feature",
  "properties": {
    "addr:full":"293 Elizabeth St North Hobart TAS 7000",
    "addr:housenumber":"293",
    "addr:postcode":"7000",
    "addr:street":"Elizabeth St",
    "iso:country":"AU",
    "sg:address":"293 Elizabeth St",
    "sg:city":"North Hobart",
    "sg:classifiers":[
        {
            "category":"Fast Food",
            "type":"Food & Drink"
        }
    ],
    "sg:phone":"+61 3 6234 7246",
    "sg:postcode":"7000",
    "sg:province":"TAS",
    "sg:tags":[
        "away",
        "take"
    ],
    "wof:name":"Fish Bar The",
    "wof:placetype":"venue"
},
  "geometry": {"coordinates":[147.3175354,-42.8748855591],"type":"Point"}
}