{
  "type": "Feature",
  "properties": {
    "addr:full":"98 Lwr Plenty Rd Rosanna VIC 3084",
    "addr:housenumber":"98",
    "addr:postcode":"3084",
    "addr:street":"Lwr Plenty Rd",
    "iso:country":"AU",
    "sg:address":"98 Lwr Plenty Rd",
    "sg:city":"Rosanna",
    "sg:classifiers":[
        {
            "category":"Real Estate",
            "subcategory":"Real Estate Services",
            "type":"Services"
        }
    ],
    "sg:phone":"+61 3 9459 6699",
    "sg:postcode":"3084",
    "sg:province":"VIC",
    "sg:tags":[
        "valuer"
    ],
    "wof:name":"Jeffrey E. McLean & Co",
    "wof:placetype":"venue"
},
  "geometry": {"coordinates":[145.06478881800001,-37.7433891296],"type":"Point"}
}