{
  "type": "Feature",
  "properties": {
    "iso:country":"AU",
    "sg:address":"123 Graham St",
    "sg:city":"Wonthaggi",
    "sg:classifiers":[
        {
            "category":"Manufacturing",
            "subcategory":"Textiles",
            "type":"Manufacturing & Wholesale Goods"
        }
    ],
    "sg:phone":"+61 3 5672 3930",
    "sg:postcode":"3995",
    "sg:province":"VIC",
    "sg:tags":[
        "knitted",
        "woven",
        "fabric"
    ],
    "wof:name":"Wonthaggi Discount Fabrics",
    "wof:placetype":"venue"
},
  "geometry": {"coordinates":[145.589935,-38.606304],"type":"Point"}
}