{
  "type": "Feature",
  "properties": {
    "iso:country":"AU",
    "sg:address":"170 Main Rd",
    "sg:city":"Gawler",
    "sg:classifiers":[
        {
            "category":"Government",
            "subcategory":"Post Office",
            "type":"Public Place"
        }
    ],
    "sg:phone":"+61 3 6425 1113",
    "sg:postcode":"7315",
    "sg:province":"TAS",
    "sg:tags":[
        "postal"
    ],
    "wof:name":"Australia Post",
    "wof:placetype":"venue"
},
  "geometry": {"coordinates":[146.18951415999999,-41.1653594971],"type":"Point"}
}