{
  "type": "Feature",
  "properties": {
    "addr:full":"3 Palara St Buddina QLD 4575",
    "addr:housenumber":"3",
    "addr:postcode":"4575",
    "addr:street":"Palara St",
    "iso:country":"AU",
    "sg:address":"3 Palara St",
    "sg:city":"Buddina",
    "sg:classifiers":[
        {
            "category":"Building & Trades",
            "subcategory":"Cleaning & Sanitation",
            "type":"Services"
        }
    ],
    "sg:phone":"+61 7 5477 7018",
    "sg:postcode":"4575",
    "sg:province":"QLD",
    "sg:tags":[
        "industrial",
        "commercial",
        "contractor"
    ],
    "wof:name":"Coast Professional Cleaning Services",
    "wof:placetype":"venue"
},
  "geometry": {"coordinates":[153.13017300000001,-26.699303],"type":"Point"}
}