{
  "type": "Feature",
  "properties": {
    "addr:full":"127 Main Rd Moonah TAS 7009",
    "addr:housenumber":"127",
    "addr:postcode":"7009",
    "addr:street":"Main Rd",
    "iso:country":"AU",
    "sg:address":"127 Main Rd",
    "sg:city":"Moonah",
    "sg:classifiers":[
        {
            "category":"Fast Food",
            "type":"Food & Drink"
        }
    ],
    "sg:phone":"+61 3 6228 3394",
    "sg:postcode":"7009",
    "sg:province":"TAS",
    "sg:tags":[
        "away",
        "take"
    ],
    "wof:name":"Godfather The",
    "wof:placetype":"venue"
},
  "geometry": {"coordinates":[147.29423523,-42.8455734253],"type":"Point"}
}