{
  "type": "Feature",
  "properties": {
    "iso:country":"AU",
    "sg:address":"26 Station St",
    "sg:city":"Engadine",
    "sg:classifiers":[
        {
            "category":"Building & Trades",
            "subcategory":"Equipment Rental",
            "type":"Services"
        }
    ],
    "sg:phone":"+61 2 9520 4600",
    "sg:postcode":"2233",
    "sg:province":"NSW",
    "sg:tags":[
        "fitness"
    ],
    "wof:name":"Engadine Cycles",
    "wof:placetype":"venue"
},
  "geometry": {"coordinates":[151.01417541500001,-34.0668182373],"type":"Point"}
}