{
  "type": "Feature",
  "properties": {
    "iso:country":"AU",
    "sg:address":"7 Mahomed St",
    "sg:city":"Alice Springs",
    "sg:classifiers":[
        {
            "category":"Building & Trades",
            "subcategory":"Construction",
            "type":"Services"
        }
    ],
    "sg:phone":"+61 411 835 463",
    "sg:postcode":"0870",
    "sg:province":"NT",
    "sg:tags":[
        "joiner",
        "carpenter"
    ],
    "wof:name":"Mid-Aust Maintenance",
    "wof:placetype":"venue"
},
  "geometry": {"coordinates":[133.87205505399999,-23.7207546234],"type":"Point"}
}