{
  "type": "Feature",
  "properties": {
    "iso:country":"AU",
    "sg:address":"114 Park St",
    "sg:city":"South Melbourne",
    "sg:classifiers":[
        {
            "category":"Health Services",
            "subcategory":"Chiropractor",
            "type":"Services"
        }
    ],
    "sg:phone":"+61 3 9645 7788",
    "sg:postcode":"3205",
    "sg:province":"VIC",
    "wof:name":"Schindler Sibille Dr",
    "wof:placetype":"venue"
},
  "geometry": {"coordinates":[144.967133,-37.833477],"type":"Point"}
}