{
  "type": "Feature",
  "properties": {
    "addr:full":"4 O'Connell St Tamworth NSW 2340",
    "addr:housenumber":"4",
    "addr:postcode":"2340",
    "addr:street":"O'Connell St",
    "iso:country":"AU",
    "sg:address":"4 O'Connell St",
    "sg:city":"Tamworth",
    "sg:classifiers":[
        {
            "category":"Insurance",
            "subcategory":"Insurance Agent",
            "type":"Services"
        }
    ],
    "sg:phone":"+61 2 6766 6636",
    "sg:postcode":"2340",
    "sg:province":"NSW",
    "wof:name":"Barnsley Bernard",
    "wof:placetype":"venue"
},
  "geometry": {"coordinates":[150.92788696299999,-31.0802173615],"type":"Point"}
}