{
  "type": "Feature",
  "properties": {
    "iso:country":"AU",
    "sg:address":"101 Marnie Crs",
    "sg:city":"Doonan",
    "sg:classifiers":[
        {
            "category":"Shopping",
            "subcategory":"Musical Instruments",
            "type":"Retail Goods"
        }
    ],
    "sg:phone":"+61 418 155 986",
    "sg:postcode":"4562",
    "sg:province":"QLD",
    "sg:tags":[
        "musician",
        "agent"
    ],
    "wof:name":"Anderson Mike",
    "wof:placetype":"venue"
},
  "geometry": {"coordinates":[153.00785827600001,-26.4438400269],"type":"Point"}
}