{
  "type": "Feature",
  "properties": {
    "addr:full":"22 Christine Ave Miami QLD 4220",
    "addr:housenumber":"22",
    "addr:postcode":"4220",
    "addr:street":"Christine Ave",
    "iso:country":"AU",
    "sg:address":"22 Christine Ave",
    "sg:city":"Miami",
    "sg:classifiers":[
        {
            "category":"Professional",
            "type":"Services"
        }
    ],
    "sg:phone":"+61 7 5535 4399",
    "sg:postcode":"4220",
    "sg:province":"QLD",
    "sg:tags":[
        "spray",
        "painting"
    ],
    "wof:name":"Daves Spray Painting & Panel Beating",
    "wof:placetype":"venue"
},
  "geometry": {"coordinates":[153.442962647,-28.077287674],"type":"Point"}
}