{
  "type": "Feature",
  "properties": {
    "addr:full":"19 Owen St Plympton SA 5038",
    "addr:housenumber":"19",
    "addr:postcode":"5038",
    "addr:street":"Owen St",
    "iso:country":"AU",
    "sg:address":"19 Owen St",
    "sg:city":"Plympton",
    "sg:classifiers":[
        {
            "category":"Education",
            "subcategory":"School",
            "type":"Public Place"
        }
    ],
    "sg:phone":"+61 8 8293 1227",
    "sg:postcode":"5038",
    "sg:province":"SA",
    "sg:tags":[
        "state",
        "except",
        "nsw"
    ],
    "wof:name":"Plympton Primary",
    "wof:placetype":"venue"
},
  "geometry": {"coordinates":[138.55628967300001,-34.9605751038],"type":"Point"}
}