{
  "type": "Feature",
  "properties": {
    "addr:full":"354 Horsley Rd Milperra NSW 2214",
    "addr:housenumber":"354",
    "addr:postcode":"2214",
    "addr:street":"Horsley Rd",
    "iso:country":"AU",
    "sg:address":"354 Horsley Rd",
    "sg:city":"Milperra",
    "sg:classifiers":[
        {
            "category":"Building & Trades",
            "subcategory":"Construction",
            "type":"Services"
        }
    ],
    "sg:phone":"+61 2 9771 4511",
    "sg:postcode":"2214",
    "sg:province":"NSW",
    "sg:tags":[
        "joinery"
    ],
    "wof:name":"Sealed Kore Industries Pty Ltd",
    "wof:placetype":"venue"
},
  "geometry": {"coordinates":[150.99452199999999,-33.939121],"type":"Point"}
}