{
  "type": "Feature",
  "properties": {
    "addr:full":"Suite 9, 46 - 48 Urunga Pde Miranda NSW 2228",
    "addr:housenumber":"46 48",
    "addr:postcode":"2228",
    "addr:street":"Urunga Pde Miranda",
    "iso:country":"AU",
    "sg:address":"Suite 9, 46 - 48 Urunga Pde",
    "sg:city":"Miranda",
    "sg:classifiers":[
        {
            "category":"Banks & Credit Unions",
            "subcategory":"Bank",
            "type":"Services"
        }
    ],
    "sg:phone":"+61 1300 667 847",
    "sg:postcode":"2228",
    "sg:province":"NSW",
    "sg:tags":[
        "broker",
        "mortgage"
    ],
    "wof:name":"Eric Greening Financial Services Pty Ltd",
    "wof:placetype":"venue"
},
  "geometry": {"coordinates":[151.10260009800001,-34.0358467102],"type":"Point"}
}