{
  "type": "Feature",
  "properties": {
    "iso:country":"AU",
    "sg:address":"Grevillea Park Menindee Drv",
    "sg:city":"Barton",
    "sg:classifiers":[
        {
            "category":"Retail",
            "subcategory":"Event Space",
            "type":"Services"
        }
    ],
    "sg:phone":"+61 2 6273 5500",
    "sg:postcode":"2600",
    "sg:province":"ACT",
    "sg:tags":[
        "venue",
        "reception",
        "wedding"
    ],
    "wof:name":"Boat House By The Lake The",
    "wof:placetype":"venue"
},
  "geometry": {"coordinates":[149.14236450199999,-35.3014602661],"type":"Point"}
}