{
  "type": "Feature",
  "properties": {
    "addr:full":"76A Main St Kapunda SA 5373",
    "addr:housenumber":"76a",
    "addr:postcode":"5373",
    "addr:street":"Main St",
    "iso:country":"AU",
    "sg:address":"76A Main St",
    "sg:city":"Kapunda",
    "sg:classifiers":[
        {
            "category":"Health Services",
            "subcategory":"Dentist",
            "type":"Services"
        }
    ],
    "sg:phone":"+61 8 8566 2025",
    "sg:postcode":"5373",
    "sg:province":"SA",
    "wof:name":"Kapunda Dental Clinic",
    "wof:placetype":"venue"
},
  "geometry": {"coordinates":[138.91659545900001,-34.3394317627],"type":"Point"}
}