{
  "type": "Feature",
  "properties": {
    "addr:full":"27a Hall St Bondi Beach NSW 2026",
    "addr:housenumber":"27a",
    "addr:postcode":"2026",
    "addr:street":"Hall St",
    "iso:country":"AU",
    "sg:address":"27a Hall St",
    "sg:city":"Bondi Beach",
    "sg:classifiers":[
        {
            "category":"Shopping",
            "subcategory":"Clothing, Apparel, & Fashions",
            "type":"Retail Goods"
        }
    ],
    "sg:phone":"+61 2 9300 8198",
    "sg:postcode":"2026",
    "sg:province":"NSW",
    "sg:tags":[
        "lady",
        "wear"
    ],
    "wof:name":"Vibes Boutique",
    "wof:placetype":"venue"
},
  "geometry": {"coordinates":[151.273040772,-33.8904724121],"type":"Point"}
}