{
  "type": "Feature",
  "properties": {
    "addr:full":"621 Sturt St Ballarat VIC 3350",
    "addr:housenumber":"621",
    "addr:postcode":"3350",
    "addr:street":"Sturt St",
    "iso:country":"AU",
    "sg:address":"621 Sturt St",
    "sg:city":"Ballarat",
    "sg:classifiers":[
        {
            "category":"Real Estate",
            "subcategory":"Real Estate Agent",
            "type":"Services"
        }
    ],
    "sg:phone":"+61 3 5333 4322",
    "sg:postcode":"3350",
    "sg:province":"VIC",
    "wof:name":"Petrie Trevor Real Estate Pty Ltd",
    "wof:placetype":"venue"
},
  "geometry": {"coordinates":[143.85089111299999,-37.5614624023],"type":"Point"}
}