{
  "type": "Feature",
  "properties": {
    "addr:full":"11-13 Deakin St Traralgon VIC 3844",
    "addr:housenumber":"11-13",
    "addr:postcode":"3844",
    "addr:street":"Deakin St",
    "iso:country":"AU",
    "sg:address":"11-13 Deakin St",
    "sg:city":"Traralgon",
    "sg:classifiers":[
        {
            "category":"Wholesale",
            "subcategory":"Electrical",
            "type":"Manufacturing & Wholesale Goods"
        }
    ],
    "sg:phone":"+61 3 5174 6611",
    "sg:postcode":"3844",
    "sg:province":"VIC",
    "sg:tags":[
        "wholesaler"
    ],
    "wof:name":"Middendorp Electric Co Pty Ltd",
    "wof:placetype":"venue"
},
  "geometry": {"coordinates":[146.53421020499999,-38.1977233887],"type":"Point"}
}