{
  "type": "Feature",
  "properties": {
    "addr:full":"11 McDonald St Boonah QLD 4310",
    "addr:housenumber":"11",
    "addr:postcode":"4310",
    "addr:street":"Mcdonald St",
    "iso:country":"AU",
    "sg:address":"11 McDonald St",
    "sg:city":"Boonah",
    "sg:classifiers":[
        {
            "category":"Utilities",
            "subcategory":"Electric",
            "type":"Services"
        }
    ],
    "sg:phone":"+61 7 5463 2782",
    "sg:postcode":"4310",
    "sg:province":"QLD",
    "sg:tags":[
        "electrical",
        "contractor"
    ],
    "wof:name":"De Main Electrical",
    "wof:placetype":"venue"
},
  "geometry": {"coordinates":[152.692626953,-27.9994525909],"type":"Point"}
}