{
  "type": "Feature",
  "properties": {
    "addr:full":"Unit 52, 566 Gardeners Rd Alexandria NSW 2015",
    "addr:housenumber":"566",
    "addr:postcode":"2015",
    "addr:street":"Gardeners Rd",
    "iso:country":"AU",
    "sg:address":"Unit 52, 566 Gardeners Rd",
    "sg:city":"Alexandria",
    "sg:classifiers":[
        {
            "category":"Shopping",
            "subcategory":"Stationery & Office Supplies",
            "type":"Retail Goods"
        }
    ],
    "sg:phone":"+61 2 8338 0244",
    "sg:postcode":"2015",
    "sg:province":"NSW",
    "sg:tags":[
        "packaging",
        "material"
    ],
    "sg:website":"http://www.owencripps.com.au",
    "wof:name":"Owen Cripps & Co Pty Ltd",
    "wof:placetype":"venue"
},
  "geometry": {"coordinates":[151.18490600600001,-33.9198188782],"type":"Point"}
}