{
  "type": "Feature",
  "properties": {
    "addr:full":"Shop A22, 840 Wellington Rd West Perth WA 6005",
    "addr:housenumber":"840",
    "addr:postcode":"6005",
    "addr:street":"Wellington Rd",
    "iso:country":"AU",
    "sg:address":"Shop A22, 840 Wellington Rd",
    "sg:city":"West Perth",
    "sg:classifiers":[
        {
            "category":"Shopping",
            "subcategory":"Shoes",
            "type":"Retail Goods"
        }
    ],
    "sg:phone":"+61 8 9321 0988",
    "sg:postcode":"6005",
    "sg:province":"WA",
    "sg:tags":[
        "footwear"
    ],
    "wof:name":"PAIRS",
    "wof:placetype":"venue"
},
  "geometry": {"coordinates":[115.847587585,-31.9475536346],"type":"Point"}
}