{
  "type": "Feature",
  "properties": {
    "iso:country":"AU",
    "sg:address":"Shop 1, 4- 10 Bay St",
    "sg:city":"Double Bay",
    "sg:classifiers":[
        {
            "category":"Shopping",
            "subcategory":"Clothing, Apparel, & Fashions",
            "type":"Retail Goods"
        }
    ],
    "sg:phone":"+61 2 9363 5775",
    "sg:postcode":"2028",
    "sg:province":"NSW",
    "sg:tags":[
        "boutique"
    ],
    "wof:name":"La Deuxieme Fois",
    "wof:placetype":"venue"
},
  "geometry": {"coordinates":[151.241287231,-33.8779945374],"type":"Point"}
}