{
  "type": "Feature",
  "properties": {
    "iso:country":"AU",
    "sg:address":"116 Colby Drv",
    "sg:city":"Belgrave South",
    "sg:classifiers":[
        {
            "category":"Arts & Performance",
            "subcategory":"Dance",
            "type":"Entertainment"
        }
    ],
    "sg:phone":"+61 3 9752 6665",
    "sg:postcode":"3160",
    "sg:province":"VIC",
    "sg:tags":[
        "theatrical",
        "ballet",
        "tuition"
    ],
    "wof:name":"State Dance Assoc Inc",
    "wof:placetype":"venue"
},
  "geometry": {"coordinates":[145.357223511,-37.9289970398],"type":"Point"}
}