{
  "type": "Feature",
  "properties": {
    "iso:country":"AU",
    "sg:address":"24 Caloundra St",
    "sg:city":"Landsborough",
    "sg:classifiers":[
        {
            "category":"Retail",
            "subcategory":"Auto Repair",
            "type":"Services"
        }
    ],
    "sg:phone":"+61 7 5494 1055",
    "sg:postcode":"4550",
    "sg:province":"QLD",
    "sg:tags":[
        "repairer",
        "motor",
        "engineer"
    ],
    "wof:name":"George Wegener V8 Specialist",
    "wof:placetype":"venue"
},
  "geometry": {"coordinates":[152.969604492,-26.8096065521],"type":"Point"}
}