{
  "type": "Feature",
  "properties": {
    "iso:country":"AU",
    "sg:address":"18 Tallebudgera Creek Rd",
    "sg:city":"Tallebudgera",
    "sg:classifiers":[
        {
            "category":"Professional",
            "subcategory":"Employment Agencies",
            "type":"Services"
        }
    ],
    "sg:phone":"+61 7 5568 7654",
    "sg:postcode":"4228",
    "sg:province":"QLD",
    "sg:tags":[
        "entertainer",
        "agent"
    ],
    "wof:name":"The Cats Swinton Agency",
    "wof:placetype":"venue"
},
  "geometry": {"coordinates":[153.40162658700001,-28.1533355713],"type":"Point"}
}