{
  "type": "Feature",
  "properties": {
    "addr:full":"2/ 328 Windsor St Richmond NSW 2753",
    "addr:housenumber":"/ 328",
    "addr:postcode":"2753",
    "addr:street":"Windsor St",
    "iso:country":"AU",
    "sg:address":"2/ 328 Windsor St",
    "sg:city":"Richmond",
    "sg:classifiers":[
        {
            "category":"Shopping",
            "subcategory":"Crafts & Fabrics",
            "type":"Retail Goods"
        }
    ],
    "sg:phone":"+61 2 4578 2860",
    "sg:postcode":"2753",
    "sg:province":"NSW",
    "sg:tags":[
        "material",
        "dress"
    ],
    "wof:name":"Fab Fabrics Brynorm's",
    "wof:placetype":"venue"
},
  "geometry": {"coordinates":[150.74864196799999,-33.5958824158],"type":"Point"}
}