{
  "type": "Feature",
  "properties": {
    "iso:country":"AU",
    "sg:address":"258 Whitehorse Rd",
    "sg:city":"Balwyn",
    "sg:classifiers":[
        {
            "category":"Shopping",
            "subcategory":"Clothing, Apparel, & Fashions",
            "type":"Retail Goods"
        }
    ],
    "sg:phone":"+61 3 9830 2877",
    "sg:postcode":"3103",
    "sg:province":"VIC",
    "sg:tags":[
        "boutique"
    ],
    "wof:name":"Semplice Moda Boutique",
    "wof:placetype":"venue"
},
  "geometry": {"coordinates":[145.08209228499999,-37.8130264282],"type":"Point"}
}