{
  "type": "Feature",
  "properties": {
    "addr:full":"Lot 1 Eames St Albury NSW 2640",
    "addr:postcode":"2640",
    "addr:street":"Eames St",
    "iso:country":"AU",
    "sg:address":"Lot 1 Eames St",
    "sg:city":"Albury",
    "sg:classifiers":[
        {
            "category":"Wholesale",
            "subcategory":"Metals & Minerals",
            "type":"Manufacturing & Wholesale Goods"
        }
    ],
    "sg:phone":"+61 2 6041 3399",
    "sg:postcode":"2640",
    "sg:province":"NSW",
    "sg:tags":[
        "steel",
        "merchant"
    ],
    "wof:name":"Bohler Uddeholm Australia Pty Ltd",
    "wof:placetype":"venue"
},
  "geometry": {"coordinates":[146.93133544899999,-36.0692253113],"type":"Point"}
}