{
  "type": "Feature",
  "properties": {
    "iso:country":"AU",
    "sg:address":"3 Miller St",
    "sg:city":"O'Connor",
    "sg:classifiers":[
        {
            "category":"Health Services",
            "subcategory":"Health Practitioner",
            "type":"Services"
        }
    ],
    "sg:phone":"+61 2 6249 8582",
    "sg:postcode":"2602",
    "sg:province":"ACT",
    "sg:tags":[
        "technique",
        "alexander"
    ],
    "wof:name":"Alexander Technique- Freedom in Action",
    "wof:placetype":"venue"
},
  "geometry": {"coordinates":[149.11415100100001,-35.2680168152],"type":"Point"}
}