{
  "type": "Feature",
  "properties": {
    "addr:full":"93 Baumans Rd Peakhurst NSW 2210",
    "addr:housenumber":"93",
    "addr:postcode":"2210",
    "addr:street":"Baumans Rd",
    "iso:country":"AU",
    "sg:address":"93 Baumans Rd",
    "sg:city":"Peakhurst",
    "sg:classifiers":[
        {
            "category":"Health Services",
            "subcategory":"Nursing And Care Facility",
            "type":"Services"
        }
    ],
    "sg:phone":"+61 2 9534 6655",
    "sg:postcode":"2210",
    "sg:province":"NSW",
    "sg:tags":[
        "home"
    ],
    "wof:name":"Uniting Church In Aust",
    "wof:placetype":"venue"
},
  "geometry": {"coordinates":[151.06785600000001,-33.95623],"type":"Point"}
}