{
  "type": "Feature",
  "properties": {
    "addr:full":"Modbury Vlge Shopng Cntr Ladywood Drv Modbury Heights SA 5092",
    "addr:postcode":"5092",
    "addr:street":"Ladywood Drv",
    "iso:country":"AU",
    "sg:address":"Modbury Vlge Shopng Cntr Ladywood Drv",
    "sg:city":"Modbury Heights",
    "sg:classifiers":[
        {
            "category":"Food & Beverages",
            "subcategory":"Liquor & Beverages",
            "type":"Retail Goods"
        }
    ],
    "sg:phone":"+61 8 8396 2716",
    "sg:postcode":"5092",
    "sg:province":"SA",
    "sg:tags":[
        "store"
    ],
    "wof:name":"Liquorland",
    "wof:placetype":"venue"
},
  "geometry": {"coordinates":[138.68632507300001,-34.8114738464],"type":"Point"}
}