{
  "type": "Feature",
  "properties": {
    "addr:full":"36 Compton Rd Underwood QLD 4119",
    "addr:housenumber":"36",
    "addr:postcode":"4119",
    "addr:street":"Compton Rd",
    "iso:country":"AU",
    "sg:address":"36 Compton Rd",
    "sg:city":"Underwood",
    "sg:classifiers":[
        {
            "category":"Shopping",
            "subcategory":"Stationery & Office Supplies",
            "type":"Retail Goods"
        }
    ],
    "sg:phone":"+61 7 3808 1080",
    "sg:postcode":"4119",
    "sg:province":"QLD",
    "sg:tags":[
        "equipment",
        "facsimile"
    ],
    "wof:name":"Australian Office Equipment",
    "wof:placetype":"venue"
},
  "geometry": {"coordinates":[153.112060547,-27.6198787689],"type":"Point"}
}