{
  "type": "Feature",
  "properties": {
    "addr:full":"718-720 Marshall Rd Malaga WA 6090",
    "addr:housenumber":"718-720",
    "addr:postcode":"6090",
    "addr:street":"Marshall Rd",
    "iso:country":"AU",
    "sg:address":"718-720 Marshall Rd",
    "sg:city":"Malaga",
    "sg:classifiers":[
        {
            "category":"Retail",
            "subcategory":"Event Space",
            "type":"Services"
        }
    ],
    "sg:phone":"+61 8 9249 2600",
    "sg:postcode":"6090",
    "sg:province":"WA",
    "sg:tags":[
        "function",
        "organiser"
    ],
    "wof:name":"Crystal Ballroom",
    "wof:placetype":"venue"
},
  "geometry": {"coordinates":[115.903869629,-31.8567886353],"type":"Point"}
}