{
  "type": "Feature",
  "properties": {
    "addr:full":"45 Ashmont Ave Wagga Wagga NSW 2650",
    "addr:housenumber":"45",
    "addr:postcode":"2650",
    "addr:street":"Ashmont Ave",
    "iso:country":"AU",
    "sg:address":"45 Ashmont Ave",
    "sg:city":"Wagga Wagga",
    "sg:classifiers":[
        {
            "category":"Building & Trades",
            "subcategory":"Construction",
            "type":"Services"
        }
    ],
    "sg:phone":"+61 2 6931 2533",
    "sg:postcode":"2650",
    "sg:province":"NSW",
    "sg:tags":[
        "plasterboard",
        "plasterer",
        "fixer"
    ],
    "wof:name":"Wild A J & C F",
    "wof:placetype":"venue"
},
  "geometry": {"coordinates":[147.33535766599999,-35.1237335205],"type":"Point"}
}