{
  "type": "Feature",
  "properties": {
    "addr:full":"12 Fordham St Wavell Heights QLD 4012",
    "addr:housenumber":"12",
    "addr:postcode":"4012",
    "addr:street":"Fordham St",
    "iso:country":"AU",
    "sg:address":"12 Fordham St",
    "sg:city":"Wavell Heights",
    "sg:classifiers":[
        {
            "category":"Shopping",
            "subcategory":"Computers & Home Electronics",
            "type":"Retail Goods"
        }
    ],
    "sg:phone":"+61 407 102 839",
    "sg:postcode":"4012",
    "sg:province":"QLD",
    "sg:tags":[
        "global",
        "positioning",
        "system"
    ],
    "wof:name":"Sound Off Mobile Installations",
    "wof:placetype":"venue"
},
  "geometry": {"coordinates":[153.05511474599999,-27.3920536041],"type":"Point"}
}