{
  "type": "Feature",
  "properties": {
    "iso:country":"AU",
    "sg:address":"Plan 520019",
    "sg:city":"Yarrawonga",
    "sg:classifiers":[
        {
            "category":"Social Services",
            "subcategory":"Adult Care",
            "type":"Services"
        }
    ],
    "sg:phone":"+61 3 5744 3400",
    "sg:postcode":"3730",
    "sg:province":"VIC",
    "sg:tags":[
        "aged"
    ],
    "wof:name":"Woods Point Aged Care",
    "wof:placetype":"venue"
},
  "geometry": {"coordinates":[146.00526428200001,-36.017490387],"type":"Point"}
}