{
  "type": "Feature",
  "properties": {
    "addr:full":"PO Box 460 Quinns Rocks WA 6030",
    "addr:postcode":"6030",
    "iso:country":"AU",
    "sg:address":"PO Box 460",
    "sg:city":"Quinns Rocks",
    "sg:classifiers":[
        {
            "category":"Health Services",
            "subcategory":"Health Practitioner",
            "type":"Services"
        }
    ],
    "sg:phone":"+61 8 9304 6451",
    "sg:postcode":"6030",
    "sg:province":"WA",
    "sg:tags":[
        "psychologist"
    ],
    "wof:name":"Howard Christopher Dr",
    "wof:placetype":"venue"
},
  "geometry": {"coordinates":[115.70501709,-31.6646404266],"type":"Point"}
}