{
  "type": "Feature",
  "properties": {
    "addr:full":"Cnr Darling & Dandenong Rds Malvern East VIC 3145",
    "addr:postcode":"3145",
    "iso:country":"AU",
    "sg:address":"Cnr Darling & Dandenong Rds",
    "sg:city":"Malvern East",
    "sg:classifiers":[
        {
            "category":"Autos & Motor Vehicles",
            "subcategory":"Auto Supplies",
            "type":"Retail Goods"
        }
    ],
    "sg:phone":"+61 3 9571 2888",
    "sg:postcode":"3145",
    "sg:province":"VIC",
    "sg:tags":[
        "tyre"
    ],
    "wof:name":"Delarue Tyres Pty Ltd",
    "wof:placetype":"venue"
},
  "geometry": {"coordinates":[145.04672241200001,-37.8769760132],"type":"Point"}
}