{
  "type": "Feature",
  "properties": {
    "addr:full":"96 Gatton Laidley Rd Forest Hill QLD 4342",
    "addr:housenumber":"96",
    "addr:postcode":"4342",
    "addr:street":"Gatton Laidley Rd",
    "iso:country":"AU",
    "sg:address":"96 Gatton Laidley Rd",
    "sg:city":"Forest Hill",
    "sg:classifiers":[
        {
            "category":"Wholesale",
            "subcategory":"Durable Goods & Equipment",
            "type":"Manufacturing & Wholesale Goods"
        }
    ],
    "sg:phone":"+61 7 5465 4195",
    "sg:postcode":"4342",
    "sg:province":"QLD",
    "sg:tags":[
        "stockyard"
    ],
    "wof:name":"Warwick Cattle Crush Company",
    "wof:placetype":"venue"
},
  "geometry": {"coordinates":[152.35226440400001,-27.5720024109],"type":"Point"}
}