{
  "type": "Feature",
  "properties": {
    "addr:full":"40 Yarrawonga Park Rd Balcolyn NSW 2264",
    "addr:housenumber":"40",
    "addr:postcode":"2264",
    "addr:street":"Park Rd",
    "iso:country":"AU",
    "sg:address":"40 Yarrawonga Park Rd",
    "sg:city":"Balcolyn",
    "sg:classifiers":[
        {
            "category":"Conference Center",
            "type":"Public Place"
        }
    ],
    "sg:phone":"+61 2 9653 1676",
    "sg:postcode":"2264",
    "sg:province":"NSW",
    "sg:tags":[
        "venue",
        "convention"
    ],
    "wof:name":"Lake Mac Outdoor Recreation Centre",
    "wof:placetype":"venue"
},
  "geometry": {"coordinates":[151.54573099999999,-33.096249],"type":"Point"}
}