{
  "type": "Feature",
  "properties": {
    "iso:country":"AU",
    "sg:address":"40 Yarrawonga Park Rd",
    "sg:city":"Balcolyn",
    "sg:classifiers":[
        {
            "category":"Conference Center",
            "type":"Public Place"
        }
    ],
    "sg:phone":"+61 2 9653 1676",
    "sg:postcode":"2264",
    "sg:province":"NSW",
    "sg:tags":[
        "venue",
        "convention"
    ],
    "wof:name":"Lake Mac Outdoor Recreation Centre",
    "wof:placetype":"venue"
},
  "geometry": {"coordinates":[151.545731,-33.096249],"type":"Point"}
}