{
  "type": "Feature",
  "properties": {
    "addr:full":"10 Main St Palmwoods QLD 4555",
    "addr:housenumber":"10",
    "addr:postcode":"4555",
    "addr:street":"Main St",
    "iso:country":"AU",
    "sg:address":"10 Main St",
    "sg:city":"Palmwoods",
    "sg:classifiers":[
        {
            "category":"Restaurant",
            "type":"Food & Drink"
        }
    ],
    "sg:phone":"+61 7 5478 8711",
    "sg:postcode":"4555",
    "sg:province":"QLD",
    "wof:name":"Cafe De Orient",
    "wof:placetype":"venue"
},
  "geometry": {"coordinates":[152.95921325699999,-26.6870326996],"type":"Point"}
}