{
  "type": "Feature",
  "properties": {
    "iso:country":"AU",
    "sg:address":"23 Playfair St",
    "sg:city":"The Rocks",
    "sg:classifiers":[
        {
            "category":"Communications",
            "subcategory":"News Services",
            "type":"Services"
        }
    ],
    "sg:phone":"+61 2 9247 6678",
    "sg:postcode":"2000",
    "sg:province":"NSW",
    "sg:tags":[
        "information",
        "tourist",
        "attractions"
    ],
    "wof:name":"Rocks Walking Tours The",
    "wof:placetype":"venue"
},
  "geometry": {"coordinates":[151.208587647,-33.8580436707],"type":"Point"}
}