{
  "type": "Feature",
  "properties": {
    "addr:full":"36 Day St North Silverwater NSW 2128",
    "addr:housenumber":"36",
    "addr:postcode":"2128",
    "addr:street":"Day St North",
    "iso:country":"AU",
    "sg:address":"36 Day St North",
    "sg:city":"Silverwater",
    "sg:classifiers":[
        {
            "category":"Parking",
            "type":"Transportation"
        }
    ],
    "sg:phone":"+61 2 9871 0916",
    "sg:postcode":"2128",
    "sg:province":"NSW",
    "sg:tags":[
        "equipment",
        "system"
    ],
    "wof:name":"Australian Gate Centre",
    "wof:placetype":"venue"
},
  "geometry": {"coordinates":[151.052276611,-33.8373641968],"type":"Point"}
}