{
  "type": "Feature",
  "properties": {
    "iso:country":"AU",
    "sg:address":"433 Vincent St",
    "sg:city":"West Leederville",
    "sg:classifiers":[
        {
            "category":"Building & Trades",
            "subcategory":"Equipment Rental",
            "type":"Services"
        }
    ],
    "sg:phone":"+61 8 9381 2705",
    "sg:postcode":"6007",
    "sg:province":"WA",
    "sg:tags":[
        "control",
        "vibration"
    ],
    "wof:name":"Bruel & Kjaer",
    "wof:placetype":"venue"
},
  "geometry": {"coordinates":[115.833351135,-31.93491745],"type":"Point"}
}