{
  "type": "Feature",
  "properties": {
    "addr:full":"203 Fairfield Rd Fairfield NSW 2165",
    "addr:housenumber":"203",
    "addr:postcode":"2165",
    "addr:street":"Fairfield Rd",
    "iso:country":"AU",
    "sg:address":"203 Fairfield Rd",
    "sg:city":"Fairfield",
    "sg:classifiers":[
        {
            "category":"Retail",
            "subcategory":"Auto Repair",
            "type":"Services"
        }
    ],
    "sg:phone":"+61 2 9892 4445",
    "sg:postcode":"2165",
    "sg:province":"NSW",
    "sg:tags":[
        "repairer",
        "motor",
        "engineer"
    ],
    "wof:name":"Master Automotive Mechanical Repairs Pty Ltd",
    "wof:placetype":"venue"
},
  "geometry": {"coordinates":[150.96487426799999,-33.8688964844],"type":"Point"}
}