{
  "type": "Feature",
  "properties": {
    "addr:full":"1 Canning St Bega NSW 2550",
    "addr:housenumber":"1",
    "addr:postcode":"2550",
    "addr:street":"Canning St",
    "iso:country":"AU",
    "sg:address":"1 Canning St",
    "sg:city":"Bega",
    "sg:classifiers":[
        {
            "category":"Health Services",
            "subcategory":"Hospital",
            "type":"Services"
        }
    ],
    "sg:phone":"+61 13 12 33",
    "sg:postcode":"2550",
    "sg:province":"NSW",
    "sg:tags":[
        "ambulance"
    ],
    "wof:name":"Ambulance Service Of NSW",
    "wof:placetype":"venue"
},
  "geometry": {"coordinates":[149.84492492699999,-36.6725769043],"type":"Point"}
}