{
  "type": "Feature",
  "properties": {
    "addr:full":"2 Philipson St Albert Park VIC 3206",
    "addr:housenumber":"2",
    "addr:postcode":"3206",
    "addr:street":"Philipson St",
    "iso:country":"AU",
    "sg:address":"2 Philipson St",
    "sg:city":"Albert Park",
    "sg:classifiers":[
        {
            "category":"Retail",
            "subcategory":"Auto Repair",
            "type":"Services"
        }
    ],
    "sg:phone":"+61 3 9699 7139",
    "sg:postcode":"3206",
    "sg:province":"VIC",
    "sg:tags":[
        "repairer",
        "motor",
        "engineer"
    ],
    "wof:name":"The South Melbourne Service Centre Pty Ltd",
    "wof:placetype":"venue"
},
  "geometry": {"coordinates":[144.95271299999999,-37.844883],"type":"Point"}
}