{
  "type": "Feature",
  "properties": {
    "addr:full":"4 Osborne St Dapto NSW 2530",
    "addr:housenumber":"4",
    "addr:postcode":"2530",
    "addr:street":"Osborne St",
    "iso:country":"AU",
    "sg:address":"4 Osborne St",
    "sg:city":"Dapto",
    "sg:classifiers":[
        {
            "category":"Social Services",
            "subcategory":"Child Care",
            "type":"Services"
        }
    ],
    "sg:phone":"+61 2 4261 1466",
    "sg:postcode":"2530",
    "sg:province":"NSW",
    "sg:tags":[
        "support",
        "health"
    ],
    "wof:name":"Early Childhood Centres",
    "wof:placetype":"venue"
},
  "geometry": {"coordinates":[150.79588317899999,-34.490398407],"type":"Point"}
}