{
  "type": "Feature",
  "properties": {
    "addr:full":"48 Wellington Rd Granville NSW 2142",
    "addr:housenumber":"48",
    "addr:postcode":"2142",
    "addr:street":"Wellington Rd",
    "iso:country":"AU",
    "sg:address":"48 Wellington Rd",
    "sg:city":"Granville",
    "sg:classifiers":[
        {
            "category":"Manufacturing",
            "subcategory":"Paper Products",
            "type":"Manufacturing & Wholesale Goods"
        }
    ],
    "sg:phone":"+61 2 9632 8863",
    "sg:postcode":"2142",
    "sg:province":"NSW",
    "sg:tags":[
        "metal",
        "non-ferrous",
        "foundry"
    ],
    "wof:name":"Wellington Founders & Engineering Co Pty Ltd",
    "wof:placetype":"venue"
},
  "geometry": {"coordinates":[151.01139831500001,-33.8628921509],"type":"Point"}
}