{
  "type": "Feature",
  "properties": {
    "iso:country":"AU",
    "sg:address":"1 Berringa Crt",
    "sg:city":"Bundoora",
    "sg:classifiers":[
        {
            "category":"Home & Garden",
            "subcategory":"Kitchen Supply",
            "type":"Retail Goods"
        }
    ],
    "sg:phone":"+61 3 9467 4039",
    "sg:postcode":"3083",
    "sg:province":"VIC",
    "sg:tags":[
        "sharpening"
    ],
    "wof:name":"K.R.S. Industries Pty Ltd",
    "wof:placetype":"venue"
},
  "geometry": {"coordinates":[145.071533203,-37.6956367493],"type":"Point"}
}