{
  "type": "Feature",
  "properties": {
    "addr:full":"DFO Shop 60 100 Bulla Rd Essendon Airport VIC 3041",
    "addr:housenumber":"60",
    "addr:postcode":"100;3041",
    "addr:street":"Bulla Rd",
    "iso:country":"AU",
    "sg:address":"DFO Shop 60 100 Bulla Rd",
    "sg:city":"Essendon Airport",
    "sg:classifiers":[
        {
            "category":"Shopping",
            "type":"Retail Goods"
        }
    ],
    "sg:phone":"+61 3 9937 7299",
    "sg:postcode":"3041",
    "sg:province":"VIC",
    "sg:tags":[
        "repair",
        "travel"
    ],
    "wof:name":"Victoria Station Travel Goods & Handbags",
    "wof:placetype":"venue"
},
  "geometry": {"coordinates":[144.90451049800001,-37.7366218567],"type":"Point"}
}