{
  "type": "Feature",
  "properties": {
    "iso:country":"AU",
    "sg:address":"6 Smith St",
    "sg:city":"Capalaba",
    "sg:classifiers":[
        {
            "category":"Retail",
            "subcategory":"Auto Repair",
            "type":"Services"
        }
    ],
    "sg:phone":"+61 7 3245 5640",
    "sg:postcode":"4157",
    "sg:province":"QLD",
    "sg:tags":[
        "repairer",
        "motor",
        "engineer"
    ],
    "wof:name":"Bayside Performance & Mechanical",
    "wof:placetype":"venue"
},
  "geometry": {"coordinates":[153.19656372099999,-27.5285968781],"type":"Point"}
}