{
  "type": "Feature",
  "properties": {
    "iso:country":"AU",
    "sg:address":"25 Clarence St",
    "sg:city":"Woolgoolga",
    "sg:classifiers":[
        {
            "category":"Travel",
            "subcategory":"Hotels & Motels",
            "type":"Entertainment"
        }
    ],
    "sg:phone":"+61 2 6654 1532",
    "sg:postcode":"2456",
    "sg:province":"NSW",
    "wof:name":"Pine Lodge Motel",
    "wof:placetype":"venue"
},
  "geometry": {"coordinates":[153.19133,-30.112974],"type":"Point"}
}