{
  "type": "Feature",
  "properties": {
    "addr:full":"19 Reid Park Pl Horsley NSW 2530",
    "addr:housenumber":"19",
    "addr:postcode":"2530",
    "addr:street":"Reid Park Pl",
    "iso:country":"AU",
    "sg:address":"19 Reid Park Pl",
    "sg:city":"Horsley",
    "sg:classifiers":[
        {
            "category":"Building & Trades",
            "subcategory":"Plumbing",
            "type":"Services"
        }
    ],
    "sg:phone":"+61 402 906 986",
    "sg:postcode":"2530",
    "sg:province":"NSW",
    "sg:tags":[
        "plumber",
        "gasfitters"
    ],
    "wof:name":"Lighthouse Plumbing",
    "wof:placetype":"venue"
},
  "geometry": {"coordinates":[150.777999878,-34.4960021973],"type":"Point"}
}