{
  "type": "Feature",
  "properties": {
    "addr:full":"Shop 6c, Burwood Plaza, 45 - 50 Railway Pde Burwood NSW 2134",
    "addr:housenumber":"6c;50",
    "addr:postcode":"2134",
    "addr:street":"Shop;Plaza;Railway Pde",
    "iso:country":"AU",
    "sg:address":"Shop 6c, Burwood Plaza, 45 - 50 Railway Pde",
    "sg:city":"Burwood",
    "sg:classifiers":[
        {
            "category":"Personal",
            "subcategory":"Beauty Salon",
            "type":"Services"
        }
    ],
    "sg:phone":"+61 2 9744 8404",
    "sg:postcode":"2134",
    "sg:province":"NSW",
    "sg:tags":[
        "hairdresser"
    ],
    "wof:name":"Denis Hair Care for Men",
    "wof:placetype":"venue"
},
  "geometry": {"coordinates":[151.10040283199999,-33.8770446777],"type":"Point"}
}