{
  "type": "Feature",
  "properties": {
    "iso:country":"AU",
    "sg:address":"Cnr Mary & Addison Sts",
    "sg:city":"Shellharbour",
    "sg:classifiers":[
        {
            "category":"Social Services",
            "subcategory":"Job Training",
            "type":"Services"
        }
    ],
    "sg:phone":"+61 2 4297 8444",
    "sg:postcode":"2529",
    "sg:province":"NSW",
    "sg:tags":[
        "sport"
    ],
    "wof:name":"Fitness Express",
    "wof:placetype":"venue"
},
  "geometry": {"coordinates":[150.86264038100001,-34.5808677673],"type":"Point"}
}