{
  "type": "Feature",
  "properties": {
    "addr:full":"4-10 Arnold St Mandurah WA 6210",
    "addr:housenumber":"4-10",
    "addr:postcode":"6210",
    "addr:street":"Arnold St",
    "iso:country":"AU",
    "sg:address":"4-10 Arnold St",
    "sg:city":"Mandurah",
    "sg:classifiers":[
        {
            "category":"Autos & Motor Vehicles",
            "subcategory":"Auto Supplies",
            "type":"Retail Goods"
        }
    ],
    "sg:phone":"+61 8 9535 4566",
    "sg:postcode":"6210",
    "sg:province":"WA",
    "sg:tags":[
        "battery",
        "automotive"
    ],
    "wof:name":"Beaurepaires",
    "wof:placetype":"venue"
},
  "geometry": {"coordinates":[115.740768,-32.536003],"type":"Point"}
}