{
  "type": "Feature",
  "properties": {
    "addr:full":"115 Sherriffs Rd Reynella SA 5161",
    "addr:housenumber":"115",
    "addr:postcode":"5161",
    "addr:street":"Sherriffs Rd",
    "iso:country":"AU",
    "sg:address":"115 Sherriffs Rd",
    "sg:city":"Reynella",
    "sg:classifiers":[
        {
            "category":"Transit Center",
            "subcategory":"Freight",
            "type":"Transportation"
        }
    ],
    "sg:phone":"+61 8 8381 4144",
    "sg:postcode":"5161",
    "sg:province":"SA",
    "sg:tags":[
        "forklift",
        "truck"
    ],
    "wof:name":"Beaurepaires",
    "wof:placetype":"venue"
},
  "geometry": {"coordinates":[138.52589416500001,-35.105052948],"type":"Point"}
}