{
  "type": "Feature",
  "properties": {
    "addr:full":"O'Dell St Armidale NSW 2350",
    "addr:postcode":"2350",
    "addr:street":"O'Dell St",
    "iso:country":"AU",
    "sg:address":"O'Dell St",
    "sg:city":"Armidale",
    "sg:classifiers":[
        {
            "category":"Health Services",
            "subcategory":"Doctor",
            "type":"Services"
        }
    ],
    "sg:phone":"+61 2 6628 0967",
    "sg:postcode":"2350",
    "sg:province":"NSW",
    "sg:tags":[
        "medical",
        "practitioner"
    ],
    "wof:name":"EEG Service",
    "wof:placetype":"venue"
},
  "geometry": {"coordinates":[151.656524658,-30.505115509],"type":"Point"}
}