{
  "type": "Feature",
  "properties": {
    "addr:full":"17 Henderson Ave Malvern VIC 3144",
    "addr:housenumber":"17",
    "addr:postcode":"3144",
    "addr:street":"Henderson Ave",
    "iso:country":"AU",
    "sg:address":"17 Henderson Ave",
    "sg:city":"Malvern",
    "sg:classifiers":[
        {
            "category":"Banks & Credit Unions",
            "subcategory":"Investment Brokerage",
            "type":"Services"
        }
    ],
    "sg:phone":"+61 3 9824 4811",
    "sg:postcode":"3144",
    "sg:province":"VIC",
    "wof:name":"Ensign Investments Australia Limited",
    "wof:placetype":"venue"
},
  "geometry": {"coordinates":[145.03465270999999,-37.8472442627],"type":"Point"}
}