{
  "type": "Feature",
  "properties": {
    "addr:full":"10 Gould St Strathfield South NSW 2136",
    "addr:housenumber":"10",
    "addr:postcode":"2136",
    "addr:street":"Gould St",
    "iso:country":"AU",
    "sg:address":"10 Gould St",
    "sg:city":"Strathfield South",
    "sg:classifiers":[
        {
            "category":"Landmark",
            "subcategory":"Scenic View",
            "type":"Public Place"
        }
    ],
    "sg:phone":"+61 2 9642 4655",
    "sg:postcode":"2136",
    "sg:province":"NSW",
    "sg:tags":[
        "staircase",
        "handrail"
    ],
    "wof:name":"Illawarra Welding Co Pty Ltd",
    "wof:placetype":"venue"
},
  "geometry": {"coordinates":[151.07258605999999,-33.8882789612],"type":"Point"}
}