{
  "type": "Feature",
  "properties": {
    "addr:full":"Lvl 6/ 402-410 Chapel Rd Bankstown NSW 2200",
    "addr:housenumber":"/ 402-410",
    "addr:postcode":"2200",
    "addr:street":"Chapel Rd",
    "iso:country":"AU",
    "sg:address":"Lvl 6/ 402-410 Chapel Rd",
    "sg:city":"Bankstown",
    "sg:classifiers":[
        {
            "category":"Real Estate",
            "subcategory":"Real Estate Agent",
            "type":"Services"
        }
    ],
    "sg:phone":"+61 2 9707 4000",
    "sg:postcode":"2200",
    "sg:province":"NSW",
    "wof:name":"Commercial Property Partners",
    "wof:placetype":"venue"
},
  "geometry": {"coordinates":[151.033646,-33.915459],"type":"Point"}
}