{
  "type": "Feature",
  "properties": {
    "addr:full":"16 Ingram St Hamilton Hill WA 6163",
    "addr:housenumber":"16",
    "addr:postcode":"6163",
    "addr:street":"Ingram St",
    "iso:country":"AU",
    "sg:address":"16 Ingram St",
    "sg:city":"Hamilton Hill",
    "sg:classifiers":[
        {
            "category":"Health Services",
            "subcategory":"Health Practitioner",
            "type":"Services"
        }
    ],
    "sg:phone":"+61 8 9337 8785",
    "sg:postcode":"6163",
    "sg:province":"WA",
    "sg:tags":[
        "osteopath"
    ],
    "wof:name":"Paul Papaphotis",
    "wof:placetype":"venue"
},
  "geometry": {"coordinates":[115.789421,-32.080254],"type":"Point"}
}