{
  "type": "Feature",
  "properties": {
    "addr:full":"156 Gan Gan Rd Anna Bay NSW 2316",
    "addr:housenumber":"156",
    "addr:postcode":"2316",
    "addr:street":"Gan Gan Rd",
    "iso:country":"AU",
    "sg:address":"156 Gan Gan Rd",
    "sg:city":"Anna Bay",
    "sg:classifiers":[
        {
            "category":"Fast Food",
            "type":"Food & Drink"
        }
    ],
    "sg:phone":"+61 2 4981 9366",
    "sg:postcode":"2316",
    "sg:province":"NSW",
    "sg:tags":[
        "away",
        "take"
    ],
    "wof:name":"Aussie Bobs Fish & Chips",
    "wof:placetype":"venue"
},
  "geometry": {"coordinates":[152.08459500000001,-32.777889],"type":"Point"}
}