{
  "type": "Feature",
  "properties": {
    "addr:full":"79 Derby St Silverwater NSW 2128",
    "addr:housenumber":"79",
    "addr:postcode":"2128",
    "addr:street":"Derby St",
    "iso:country":"AU",
    "sg:address":"79 Derby St",
    "sg:city":"Silverwater",
    "sg:classifiers":[
        {
            "category":"Communications",
            "subcategory":"Television Station",
            "type":"Services"
        }
    ],
    "sg:phone":"+61 2 9748 0421",
    "sg:postcode":"2128",
    "sg:province":"NSW",
    "sg:tags":[
        "screening",
        "machinery",
        "grading"
    ],
    "wof:name":"Flamingo Products",
    "wof:placetype":"venue"
},
  "geometry": {"coordinates":[151.04481506400001,-33.8366775513],"type":"Point"}
}