{
  "type": "Feature",
  "properties": {
    "iso:country":"AU",
    "sg:address":"46 Lenore Rd",
    "sg:city":"Wanneroo",
    "sg:classifiers":[
        {
            "category":"Professional",
            "subcategory":"Accounting & Tax Preparation",
            "type":"Services"
        }
    ],
    "sg:phone":"+61 8 9405 6768",
    "sg:postcode":"6065",
    "sg:province":"WA",
    "sg:tags":[
        "accountant",
        "auditor"
    ],
    "wof:name":"C.S. Bain & Associates",
    "wof:placetype":"venue"
},
  "geometry": {"coordinates":[115.826339722,-31.7627983093],"type":"Point"}
}