{
  "type": "Feature",
  "properties": {
    "iso:country":"AU",
    "sg:address":"2- 4 Grey St",
    "sg:city":"Geraldton",
    "sg:classifiers":[
        {
            "category":"Manufacturing",
            "subcategory":"Motor Vehicles & Parts",
            "type":"Manufacturing & Wholesale Goods"
        }
    ],
    "sg:phone":"+61 8 9921 3930",
    "sg:postcode":"6530",
    "sg:province":"WA",
    "sg:tags":[
        "engine",
        "equipment",
        "diesel"
    ],
    "wof:name":"MTU Detroit Diesel Australia",
    "wof:placetype":"venue"
},
  "geometry": {"coordinates":[114.624923706,-28.7766437531],"type":"Point"}
}