{
  "type": "Feature",
  "properties": {
    "iso:country":"AU",
    "sg:address":"40 Rusden St",
    "sg:city":"Kelvin Grove",
    "sg:classifiers":[
        {
            "category":"Organizations",
            "subcategory":"Professional Association",
            "type":"Services"
        }
    ],
    "sg:phone":"+61 414 722 841",
    "sg:postcode":"4059",
    "sg:province":"QLD",
    "sg:tags":[
        "web",
        "internet"
    ],
    "wof:name":"Kieran Blight Design",
    "wof:placetype":"venue"
},
  "geometry": {"coordinates":[153.00997924800001,-27.4534034729],"type":"Point"}
}