{
  "type": "Feature",
  "properties": {
    "addr:full":"54 Marion St Harris Park NSW 2150",
    "addr:housenumber":"54",
    "addr:postcode":"2150",
    "addr:street":"Marion St",
    "iso:country":"AU",
    "sg:address":"54 Marion St",
    "sg:city":"Harris Park",
    "sg:classifiers":[
        {
            "category":"Retail",
            "subcategory":"Laundry & Dry Cleaning",
            "type":"Services"
        }
    ],
    "sg:phone":"+61 2 9635 3893",
    "sg:postcode":"2150",
    "sg:province":"NSW",
    "wof:name":"Toss in The Towel",
    "wof:placetype":"venue"
},
  "geometry": {"coordinates":[151.00921630900001,-33.822303772],"type":"Point"}
}