{
  "type": "Feature",
  "properties": {
    "addr:full":"39 Jeays St Bowen Hills QLD 4006",
    "addr:housenumber":"39",
    "addr:postcode":"4006",
    "addr:street":"Jeays St",
    "iso:country":"AU",
    "sg:address":"39 Jeays St",
    "sg:city":"Bowen Hills",
    "sg:classifiers":[
        {
            "category":"Real Estate",
            "subcategory":"Surveying",
            "type":"Services"
        }
    ],
    "sg:phone":"+61 7 3252 7946",
    "sg:postcode":"4006",
    "sg:province":"QLD",
    "sg:tags":[
        "surveyor",
        "land"
    ],
    "wof:name":"Gary Hayes & Partners Pty Ltd",
    "wof:placetype":"venue"
},
  "geometry": {"coordinates":[153.03616332999999,-27.4502925873],"type":"Point"}
}