{
  "type": "Feature",
  "properties": {
    "addr:full":"Grove St Medical & Sports Centre, 12a Grove St Cairns QLD 4870",
    "addr:housenumber":"12a",
    "addr:postcode":"4870",
    "addr:street":"Grove;Grove St",
    "iso:country":"AU",
    "sg:address":"Grove St Medical & Sports Centre, 12a Grove St",
    "sg:city":"Cairns",
    "sg:classifiers":[
        {
            "category":"Health Services",
            "subcategory":"Health Practitioner",
            "type":"Services"
        }
    ],
    "sg:phone":"+61 7 4031 3406",
    "sg:postcode":"4870",
    "sg:province":"QLD",
    "sg:tags":[
        "physiotherapist"
    ],
    "wof:name":"Sheree Jacobs",
    "wof:placetype":"venue"
},
  "geometry": {"coordinates":[145.759643555,-16.9180393219],"type":"Point"}
}