{
  "type": "Feature",
  "properties": {
    "addr:full":"6/ 3 Rocklands Rd Wollstonecraft NSW 2065",
    "addr:housenumber":"/ 3",
    "addr:postcode":"2065",
    "addr:street":"Rocklands Rd",
    "iso:country":"AU",
    "sg:address":"6/ 3 Rocklands Rd",
    "sg:city":"Wollstonecraft",
    "sg:classifiers":[
        {
            "category":"Communications",
            "type":"Services"
        }
    ],
    "sg:phone":"+61 2 9959 5547",
    "sg:postcode":"2065",
    "sg:province":"NSW",
    "sg:tags":[
        "data"
    ],
    "wof:name":"C & K Technologies Pty Ltd",
    "wof:placetype":"venue"
},
  "geometry": {"coordinates":[151.19781494099999,-33.8333473206],"type":"Point"}
}