{
  "type": "Feature",
  "properties": {
    "addr:full":"Yatala Vale Rd (cnr Hancock Rd) Surrey Downs SA 5126",
    "addr:postcode":"5126",
    "addr:street":"Vale Rd Cnr Hancock Rd",
    "iso:country":"AU",
    "sg:address":"Yatala Vale Rd (cnr Hancock Rd)",
    "sg:city":"Surrey Downs",
    "sg:classifiers":[
        {
            "category":"Arts & Performance",
            "subcategory":"Theater",
            "type":"Entertainment"
        }
    ],
    "sg:phone":"+61 8 8289 5266",
    "sg:postcode":"5126",
    "sg:province":"SA",
    "sg:tags":[
        "theatre"
    ],
    "wof:name":"Tea Tree Players Theatre",
    "wof:placetype":"venue"
},
  "geometry": {"coordinates":[138.710006714,-34.7953948975],"type":"Point"}
}