{
  "type": "Feature",
  "properties": {
    "addr:full":"50 Banksia Rd Welshpool WA 6106",
    "addr:housenumber":"50",
    "addr:postcode":"6106",
    "addr:street":"Banksia Rd",
    "iso:country":"AU",
    "sg:address":"50 Banksia Rd",
    "sg:city":"Welshpool",
    "sg:classifiers":[
        {
            "category":"Shopping",
            "subcategory":"Pets & Pet Supplies",
            "type":"Retail Goods"
        }
    ],
    "sg:phone":"+61 8 9451 1024",
    "sg:postcode":"6106",
    "sg:province":"WA",
    "sg:tags":[
        "shop",
        "supplier"
    ],
    "wof:name":"Banksia Pet Products",
    "wof:placetype":"venue"
},
  "geometry": {"coordinates":[115.962341309,-31.9958114624],"type":"Point"}
}