{
  "type": "Feature",
  "properties": {
    "iso:country":"AU",
    "sg:address":"369 Boronia Rd",
    "sg:city":"Boronia",
    "sg:classifiers":[
        {
            "category":"Building & Trades",
            "subcategory":"Construction",
            "type":"Services"
        }
    ],
    "sg:phone":"+61 3 9761 3331",
    "sg:postcode":"3155",
    "sg:province":"VIC",
    "sg:tags":[
        "contractor"
    ],
    "wof:name":"Campbell Homes Pty Ltd",
    "wof:placetype":"venue"
},
  "geometry": {"coordinates":[145.257980347,-37.8570518494],"type":"Point"}
}