{
  "type": "Feature",
  "properties": {
    "addr:full":"240 Newmans Rd Woolgoolga NSW 2456",
    "addr:housenumber":"240",
    "addr:postcode":"2456",
    "addr:street":"Newmans Rd",
    "iso:country":"AU",
    "sg:address":"240 Newmans Rd",
    "sg:city":"Woolgoolga",
    "sg:classifiers":[
        {
            "category":"Utilities",
            "subcategory":"Water",
            "type":"Services"
        }
    ],
    "sg:phone":"+61 437 046 088",
    "sg:postcode":"2456",
    "sg:province":"NSW",
    "sg:tags":[
        "cartage"
    ],
    "wof:name":"Ken Ford",
    "wof:placetype":"venue"
},
  "geometry": {"coordinates":[153.190338,-30.11187],"type":"Point"}
}