{
  "type": "Feature",
  "properties": {
    "addr:full":"1064 Victoria Rd West Ryde NSW 2114",
    "addr:housenumber":"1064",
    "addr:postcode":"2114",
    "addr:street":"Victoria Rd",
    "iso:country":"AU",
    "sg:address":"1064 Victoria Rd",
    "sg:city":"West Ryde",
    "sg:classifiers":[
        {
            "category":"Building & Trades",
            "subcategory":"Construction",
            "type":"Services"
        }
    ],
    "sg:phone":"+61 2 9874 5541",
    "sg:postcode":"2114",
    "sg:province":"NSW",
    "sg:tags":[
        "installation",
        "air conditioning"
    ],
    "wof:name":"Brown M M Air Conditioning Pty Ltd",
    "wof:placetype":"venue"
},
  "geometry": {"coordinates":[151.082763672,-33.8070220947],"type":"Point"}
}