{
  "type": "Feature",
  "properties": {
    "addr:full":"Bruce Hwy Yandina QLD 4561",
    "addr:postcode":"4561",
    "addr:street":"Bruce Hwy",
    "iso:country":"AU",
    "sg:address":"Bruce Hwy",
    "sg:city":"Yandina",
    "sg:classifiers":[
        {
            "category":"Autos & Motor Vehicles",
            "subcategory":"Fuel & Gas Station",
            "type":"Retail Goods"
        }
    ],
    "sg:phone":"+61 7 5446 8999",
    "sg:postcode":"4561",
    "sg:province":"QLD",
    "wof:name":"BP Australia Limited",
    "wof:placetype":"venue"
},
  "geometry": {"coordinates":[152.96488952600001,-26.556055069],"type":"Point"}
}