{
  "type": "Feature",
  "properties": {
    "iso:country":"AU",
    "sg:address":"Colonial Shopng Cntr 54 Warrego Hwy",
    "sg:city":"Withcott",
    "sg:classifiers":[
        {
            "category":"Personal",
            "subcategory":"Beauty Salon",
            "type":"Services"
        }
    ],
    "sg:phone":"+61 7 4630 3538",
    "sg:postcode":"4352",
    "sg:province":"QLD",
    "sg:tags":[
        "hairdresser"
    ],
    "wof:name":"Withcott Hairdressing",
    "wof:placetype":"venue"
},
  "geometry": {"coordinates":[152.024414,-27.553505],"type":"Point"}
}