{
  "type": "Feature",
  "properties": {
    "iso:country":"AU",
    "sg:address":"17e Quay St",
    "sg:city":"Bundaberg",
    "sg:classifiers":[
        {
            "category":"Farming",
            "subcategory":"Fish & Marine Products",
            "type":"Manufacturing & Wholesale Goods"
        }
    ],
    "sg:phone":"+61 7 4151 4212",
    "sg:postcode":"4670",
    "sg:province":"QLD",
    "sg:tags":[
        "production",
        "seafood",
        "processing"
    ],
    "wof:name":"Satellite Seafoods",
    "wof:placetype":"venue"
},
  "geometry": {"coordinates":[152.34927368199999,-24.8646011353],"type":"Point"}
}