{
  "type": "Feature",
  "properties": {
    "addr:full":"309 Nepean Hwy Frankston VIC 3199",
    "addr:housenumber":"309",
    "addr:postcode":"3199",
    "addr:street":"Nepean Hwy",
    "iso:country":"AU",
    "sg:address":"309 Nepean Hwy",
    "sg:city":"Frankston",
    "sg:classifiers":[
        {
            "category":"Sports & Exercise",
            "subcategory":"Gym",
            "type":"Entertainment"
        }
    ],
    "sg:phone":"+61 3 9781 5533",
    "sg:postcode":"3199",
    "sg:province":"VIC",
    "sg:tags":[
        "health",
        "fitness"
    ],
    "wof:name":"Trainstation",
    "wof:placetype":"venue"
},
  "geometry": {"coordinates":[145.08287048299999,-37.9927177429],"type":"Point"}
}