{
  "type": "Feature",
  "properties": {
    "addr:full":"11 Hely St Gosford NSW 2250",
    "addr:housenumber":"11",
    "addr:postcode":"2250",
    "addr:street":"Hely St",
    "iso:country":"AU",
    "sg:address":"11 Hely St",
    "sg:city":"Gosford",
    "sg:classifiers":[
        {
            "category":"Utilities",
            "subcategory":"Refuse",
            "type":"Services"
        }
    ],
    "sg:phone":"+61 404 090 028",
    "sg:postcode":"2250",
    "sg:province":"NSW",
    "sg:tags":[
        "remover",
        "rubbish"
    ],
    "wof:name":"A & B Little Aussie Digger",
    "wof:placetype":"venue"
},
  "geometry": {"coordinates":[151.329956055,-33.4264297485],"type":"Point"}
}