{
  "type": "Feature",
  "properties": {
    "iso:country":"AU",
    "sg:address":"190 Anzac Pde",
    "sg:city":"Kensington",
    "sg:classifiers":[
        {
            "category":"Health Services",
            "subcategory":"Health Practitioner",
            "type":"Services"
        }
    ],
    "sg:phone":"+61 2 9313 6011",
    "sg:postcode":"2033",
    "sg:province":"NSW",
    "sg:tags":[
        "acupuncture"
    ],
    "wof:name":"Yong Mary",
    "wof:placetype":"venue"
},
  "geometry": {"coordinates":[151.22352599999999,-33.910416],"type":"Point"}
}