{
  "type": "Feature",
  "properties": {
    "iso:country":"AU",
    "sg:address":"Old Byron News Bldg 142 Bangalow Rd",
    "sg:city":"Byron Bay",
    "sg:classifiers":[
        {
            "category":"Health Services",
            "subcategory":"Chiropractor",
            "type":"Services"
        }
    ],
    "sg:phone":"+61 2 6680 8400",
    "sg:postcode":"2481",
    "sg:province":"NSW",
    "wof:name":"Tselepy Aaron",
    "wof:placetype":"venue"
},
  "geometry": {"coordinates":[153.61428832999999,-28.6629676819],"type":"Point"}
}