{
  "type": "Feature",
  "properties": {
    "addr:full":"40 Frobisher St Osborne Park WA 6017",
    "addr:housenumber":"40",
    "addr:postcode":"6017",
    "addr:street":"Frobisher St",
    "iso:country":"AU",
    "sg:address":"40 Frobisher St",
    "sg:city":"Osborne Park",
    "sg:classifiers":[
        {
            "category":"Government",
            "subcategory":"Post Office",
            "type":"Public Place"
        }
    ],
    "sg:phone":"+61 8 9242 2003",
    "sg:postcode":"6017",
    "sg:province":"WA",
    "sg:tags":[
        "house",
        "doll"
    ],
    "wof:name":"The Play Room",
    "wof:placetype":"venue"
},
  "geometry": {"coordinates":[115.81954956,-31.9099063873],"type":"Point"}
}