{
  "type": "Feature",
  "properties": {
    "iso:country":"AU",
    "sg:address":"Arcadia St",
    "sg:city":"Noosa Junction",
    "sg:classifiers":[
        {
            "category":"Personal",
            "subcategory":"Beauty Salon",
            "type":"Services"
        }
    ],
    "sg:phone":"+61 7 5447 3783",
    "sg:postcode":"4567",
    "sg:province":"QLD",
    "sg:tags":[
        "hairdresser"
    ],
    "wof:name":"Vardys Salon",
    "wof:placetype":"venue"
},
  "geometry": {"coordinates":[153.090209961,-26.3974761963],"type":"Point"}
}