{
  "type": "Feature",
  "properties": {
    "iso:country":"AU",
    "sg:address":"544 Princes Hwy",
    "sg:city":"Bairnsdale",
    "sg:classifiers":[
        {
            "category":"Travel",
            "subcategory":"Hotels & Motels",
            "type":"Entertainment"
        }
    ],
    "sg:phone":"+61 3 5152 5000",
    "sg:postcode":"3875",
    "sg:province":"VIC",
    "wof:name":"Bairnsdale Main Motel",
    "wof:placetype":"venue"
},
  "geometry": {"coordinates":[147.827224731,-37.7086296082],"type":"Point"}
}