{
  "type": "Feature",
  "properties": {
    "addr:full":"82 Callemondah Drv Gladstone QLD 4680",
    "addr:housenumber":"82",
    "addr:postcode":"4680",
    "addr:street":"Callemondah Drv",
    "iso:country":"AU",
    "sg:address":"82 Callemondah Drv",
    "sg:city":"Gladstone",
    "sg:classifiers":[
        {
            "category":"Wholesale",
            "subcategory":"Electrical",
            "type":"Manufacturing & Wholesale Goods"
        }
    ],
    "sg:phone":"+61 7 4978 4000",
    "sg:postcode":"4680",
    "sg:province":"QLD",
    "sg:tags":[
        "wholesaler",
        "mfrs",
        "accessory"
    ],
    "wof:name":"AusProof Pty Ltd",
    "wof:placetype":"venue"
},
  "geometry": {"coordinates":[151.227172852,-23.8671283722],"type":"Point"}
}