{
  "type": "Feature",
  "properties": {
    "addr:full":"210 Wollombi Rd Cessnock NSW 2325",
    "addr:housenumber":"210",
    "addr:postcode":"2325",
    "addr:street":"Wollombi Rd",
    "iso:country":"AU",
    "sg:address":"210 Wollombi Rd",
    "sg:city":"Cessnock",
    "sg:classifiers":[
        {
            "category":"Home & Garden",
            "subcategory":"Building Materials",
            "type":"Retail Goods"
        }
    ],
    "sg:phone":"+61 2 4990 4220",
    "sg:postcode":"2325",
    "sg:province":"NSW",
    "sg:tags":[
        "merchant",
        "glass",
        "glazier"
    ],
    "wof:name":"Cessnock Glass Repairs",
    "wof:placetype":"venue"
},
  "geometry": {"coordinates":[151.353347778,-32.8330612183],"type":"Point"}
}