{
  "type": "Feature",
  "properties": {
    "addr:full":"Suite 14, Stones Arcade, 673-675 Pittwater Rd Dee Why NSW 2099",
    "addr:housenumber":"arcade 673-675",
    "addr:postcode":"2099",
    "addr:street":"Pittwater Rd",
    "iso:country":"AU",
    "sg:address":"Suite 14, Stones Arcade, 673-675 Pittwater Rd",
    "sg:city":"Dee Why",
    "sg:classifiers":[
        {
            "category":"Professional",
            "subcategory":"Art Services",
            "type":"Services"
        }
    ],
    "sg:phone":"+61 415 459 340",
    "sg:postcode":"2099",
    "sg:province":"NSW",
    "sg:website":"http://www.eclecticinteriors-ds.com",
    "wof:name":"Eclectic Interiors & Design Studio",
    "wof:placetype":"venue"
},
  "geometry": {"coordinates":[151.28497314399999,-33.7535705566],"type":"Point"}
}