{
  "type": "Feature",
  "properties": {
    "iso:country":"AU",
    "sg:address":"10 Cimitiere St",
    "sg:city":"Launceston",
    "sg:classifiers":[
        {
            "category":"Taxi",
            "type":"Transportation"
        }
    ],
    "sg:phone":"+61 3 6334 2222",
    "sg:postcode":"7250",
    "sg:province":"TAS",
    "sg:tags":[
        "cab"
    ],
    "wof:name":"Regency V.I.P. Hire Cars (Tas)",
    "wof:placetype":"venue"
},
  "geometry": {"coordinates":[147.14723205600001,-41.4303016663],"type":"Point"}
}