{
  "type": "Feature",
  "properties": {
    "addr:full":"Unit 12/ 13 Fairlight St Mosman Park WA 6012",
    "addr:housenumber":"/ 13",
    "addr:postcode":"6012",
    "addr:street":"St",
    "iso:country":"AU",
    "sg:address":"Unit 12/ 13 Fairlight St",
    "sg:city":"Mosman Park",
    "sg:classifiers":[
        {
            "category":"Shopping",
            "subcategory":"Gifts & Souvenirs",
            "type":"Retail Goods"
        }
    ],
    "sg:phone":"+61 8 9383 4606",
    "sg:postcode":"6012",
    "sg:province":"WA",
    "sg:tags":[
        "shop",
        "supply"
    ],
    "wof:name":"Angels Aglow Figurines",
    "wof:placetype":"venue"
},
  "geometry": {"coordinates":[115.757553101,-32.0106620789],"type":"Point"}
}