{
  "type": "Feature",
  "properties": {
    "addr:full":"17 Canberra St Hemmant QLD 4174",
    "addr:housenumber":"17",
    "addr:postcode":"4174",
    "addr:street":"Canberra St",
    "iso:country":"AU",
    "sg:address":"17 Canberra St",
    "sg:city":"Hemmant",
    "sg:classifiers":[
        {
            "category":"Military Area",
            "subcategory":"Naval Base",
            "type":"Public Place"
        }
    ],
    "sg:phone":"+61 7 3249 9600",
    "sg:postcode":"4174",
    "sg:province":"QLD",
    "sg:tags":[
        "stand",
        "rack"
    ],
    "wof:name":"Skye Concepts",
    "wof:placetype":"venue"
},
  "geometry": {"coordinates":[153.129196167,-27.4443092346],"type":"Point"}
}