{
  "type": "Feature",
  "properties": {
    "iso:country":"AU",
    "sg:address":"34 Albert St",
    "sg:city":"Albany",
    "sg:classifiers":[
        {
            "category":"Food & Beverages",
            "subcategory":"Liquor & Beverages",
            "type":"Retail Goods"
        }
    ],
    "sg:phone":"+61 8 9841 4699",
    "sg:postcode":"6330",
    "sg:province":"WA",
    "sg:tags":[
        "merchant",
        "spirit",
        "wine"
    ],
    "wof:name":"Harbottle On-Premise",
    "wof:placetype":"venue"
},
  "geometry": {"coordinates":[117.88391876199999,-35.0143508911],"type":"Point"}
}