{
  "type": "Feature",
  "properties": {
    "addr:full":"110 Liverpool St Scone NSW 2337",
    "addr:housenumber":"110",
    "addr:postcode":"2337",
    "addr:street":"Liverpool St",
    "iso:country":"AU",
    "sg:address":"110 Liverpool St",
    "sg:city":"Scone",
    "sg:classifiers":[
        {
            "category":"Education",
            "subcategory":"School",
            "type":"Public Place"
        }
    ],
    "sg:phone":"+61 2 6545 1049",
    "sg:postcode":"2337",
    "sg:province":"NSW",
    "sg:tags":[
        "state",
        "-",
        "nsw"
    ],
    "wof:name":"Scone Public School",
    "wof:placetype":"venue"
},
  "geometry": {"coordinates":[150.8699646,-32.0513114929],"type":"Point"}
}