{
  "type": "Feature",
  "properties": {
    "addr:full":"73- 75 Mulgrave Rd Cairns QLD 4870",
    "addr:housenumber":"75",
    "addr:postcode":"4870",
    "addr:street":"Mulgrave Rd",
    "iso:country":"AU",
    "sg:address":"73- 75 Mulgrave Rd",
    "sg:city":"Cairns",
    "sg:classifiers":[
        {
            "category":"Banks & Credit Unions",
            "subcategory":"Investment Brokerage",
            "type":"Services"
        }
    ],
    "sg:phone":"+61 7 4031 8005",
    "sg:postcode":"4870",
    "sg:province":"QLD",
    "sg:tags":[
        "finance",
        "broker"
    ],
    "wof:name":"Affordable Finance Solutions",
    "wof:placetype":"venue"
},
  "geometry": {"coordinates":[145.743896484,-16.9396724701],"type":"Point"}
}