{
  "type": "Feature",
  "properties": {
    "addr:full":"PO Box 57 Cooranbong NSW 2265",
    "addr:postcode":"2265",
    "iso:country":"AU",
    "sg:address":"PO Box 57",
    "sg:city":"Cooranbong",
    "sg:classifiers":[
        {
            "category":"Professional",
            "subcategory":"Management & Consulting",
            "type":"Services"
        }
    ],
    "sg:phone":"+61 2 4977 3899",
    "sg:postcode":"2265",
    "sg:province":"NSW",
    "sg:tags":[
        "consultant",
        "business"
    ],
    "wof:name":"The Echidna Group",
    "wof:placetype":"venue"
},
  "geometry": {"coordinates":[151.46762100000001,-33.06699],"type":"Point"}
}