{
  "type": "Feature",
  "properties": {
    "addr:full":"Spencer Rd Narrikup WA 6326",
    "addr:postcode":"6326",
    "addr:street":"Spencer Rd",
    "iso:country":"AU",
    "sg:address":"Spencer Rd",
    "sg:city":"Narrikup",
    "sg:classifiers":[
        {
            "category":"Farming",
            "subcategory":"Farm",
            "type":"Manufacturing & Wholesale Goods"
        }
    ],
    "sg:phone":"+61 8 9853 2009",
    "sg:postcode":"6326",
    "sg:province":"WA",
    "sg:tags":[
        "farmer"
    ],
    "wof:name":"Treasure J H",
    "wof:placetype":"venue"
},
  "geometry": {"coordinates":[117.70136261,-34.7726593018],"type":"Point"}
}