{
  "type": "Feature",
  "properties": {
    "iso:country":"AU",
    "sg:address":"61 Willington St",
    "sg:city":"Arncliffe",
    "sg:classifiers":[
        {
            "category":"Professional",
            "subcategory":"Computer Services",
            "type":"Services"
        }
    ],
    "sg:phone":"+61 2 9556 1364",
    "sg:postcode":"2205",
    "sg:province":"NSW",
    "sg:tags":[
        "equipment",
        "networking",
        "installation"
    ],
    "wof:name":"D.S.M. Consulting Pty Ltd",
    "wof:placetype":"venue"
},
  "geometry": {"coordinates":[151.140503,-33.93182],"type":"Point"}
}