{
  "type": "Feature",
  "properties": {
    "addr:full":"Level 2 / 31 Merivale St South Brisbane QLD 4101",
    "addr:housenumber":"/ 31",
    "addr:postcode":"4101",
    "addr:street":"Merivale St",
    "iso:country":"AU",
    "sg:address":"Level 2 / 31 Merivale St",
    "sg:city":"South Brisbane",
    "sg:classifiers":[
        {
            "category":"Banks & Credit Unions",
            "subcategory":"Financial Services",
            "type":"Services"
        }
    ],
    "sg:phone":"+61 7 3846 1644",
    "sg:postcode":"4101",
    "sg:province":"QLD",
    "sg:tags":[
        "planning"
    ],
    "wof:name":"Life Balance Financial Professionals Pty Ltd",
    "wof:placetype":"venue"
},
  "geometry": {"coordinates":[153.01594543499999,-27.4739704132],"type":"Point"}
}