{
  "type": "Feature",
  "properties": {
    "addr:full":"216 Riding Rd Balmoral QLD 4171",
    "addr:housenumber":"216",
    "addr:postcode":"4171",
    "addr:street":"Riding Rd",
    "iso:country":"AU",
    "sg:address":"216 Riding Rd",
    "sg:city":"Balmoral",
    "sg:classifiers":[
        {
            "category":"Fast Food",
            "type":"Food & Drink"
        }
    ],
    "sg:phone":"+61 7 3399 9355",
    "sg:postcode":"4171",
    "sg:province":"QLD",
    "sg:tags":[
        "away",
        "take"
    ],
    "wof:name":"Riding Road Seafoods",
    "wof:placetype":"venue"
},
  "geometry": {"coordinates":[153.06301879899999,-27.4595432281],"type":"Point"}
}