{
  "type": "Feature",
  "properties": {
    "iso:country":"AU",
    "sg:address":"105 Killara Rd",
    "sg:city":"Gruyere",
    "sg:classifiers":[
        {
            "category":"Farming",
            "subcategory":"Vineyard",
            "type":"Manufacturing & Wholesale Goods"
        }
    ],
    "sg:phone":"+61 3 5432 9499",
    "sg:postcode":"3770",
    "sg:province":"VIC",
    "sg:tags":[
        "winery"
    ],
    "wof:name":"Stuart.Co Pty Ltd",
    "wof:placetype":"venue"
},
  "geometry": {"coordinates":[145.45459,-37.738411],"type":"Point"}
}