{
  "type": "Feature",
  "properties": {
    "addr:full":"Unit 1/ 134 Erina St Gosford NSW 2250",
    "addr:housenumber":"/ 134",
    "addr:postcode":"2250",
    "addr:street":"Erina St",
    "iso:country":"AU",
    "sg:address":"Unit 1/ 134 Erina St",
    "sg:city":"Gosford",
    "sg:classifiers":[
        {
            "category":"Professional",
            "subcategory":"Accounting & Tax Preparation",
            "type":"Services"
        }
    ],
    "sg:phone":"+61 2 4322 0444",
    "sg:postcode":"2250",
    "sg:province":"NSW",
    "sg:tags":[
        "accountant",
        "auditor"
    ],
    "wof:name":"Jirsch Sutherland",
    "wof:placetype":"venue"
},
  "geometry": {"coordinates":[151.34661865199999,-33.4253921509],"type":"Point"}
}