{
  "type": "Feature",
  "properties": {
    "addr:full":"23 Farmborough Rd Unanderra NSW 2526",
    "addr:housenumber":"23",
    "addr:postcode":"2526",
    "addr:street":"Farmborough Rd",
    "iso:country":"AU",
    "sg:address":"23 Farmborough Rd",
    "sg:city":"Unanderra",
    "sg:classifiers":[
        {
            "category":"Food & Beverages",
            "subcategory":"Bakery",
            "type":"Retail Goods"
        }
    ],
    "sg:phone":"+61 2 4272 4664",
    "sg:postcode":"2526",
    "sg:province":"NSW",
    "sg:tags":[
        "baker"
    ],
    "wof:name":"Farmborough Bread & Cakes",
    "wof:placetype":"venue"
},
  "geometry": {"coordinates":[150.83651733400001,-34.4600601196],"type":"Point"}
}