{
  "type": "Feature",
  "properties": {
    "addr:full":"PO Box 219 Ormeau QLD 4208",
    "addr:postcode":"4208",
    "iso:country":"AU",
    "sg:address":"PO Box 219",
    "sg:city":"Ormeau",
    "sg:classifiers":[
        {
            "category":"Government",
            "subcategory":"Fire Station",
            "type":"Public Place"
        }
    ],
    "sg:phone":"+61 1300 133 440",
    "sg:postcode":"4208",
    "sg:province":"QLD",
    "sg:tags":[
        "cooling",
        "tower"
    ],
    "sg:website":"http://www.ctms.net.au",
    "wof:name":"Cooling Tower Mechanical Services",
    "wof:placetype":"venue"
},
  "geometry": {"coordinates":[153.25682067899999,-27.7804794312],"type":"Point"}
}