{
  "type": "Feature",
  "properties": {
    "addr:full":"20 Phyllis Rd Deer Park VIC 3023",
    "addr:housenumber":"20",
    "addr:postcode":"3023",
    "addr:street":"Phyllis Rd",
    "iso:country":"AU",
    "sg:address":"20 Phyllis Rd",
    "sg:city":"Deer Park",
    "sg:classifiers":[
        {
            "category":"Building & Trades",
            "subcategory":"Construction",
            "type":"Services"
        }
    ],
    "sg:phone":"+61 3 9363 6364",
    "sg:postcode":"3023",
    "sg:province":"VIC",
    "sg:tags":[
        "fencing",
        "contractor"
    ],
    "wof:name":"Alpine Fencing",
    "wof:placetype":"venue"
},
  "geometry": {"coordinates":[144.76637299999999,-37.756031],"type":"Point"}
}