{
  "type": "Feature",
  "properties": {
    "iso:country":"AU",
    "sg:address":"Shop 5/ 58 King St",
    "sg:city":"Woody Point",
    "sg:classifiers":[
        {
            "category":"Personal",
            "subcategory":"Hair Removal",
            "type":"Services"
        }
    ],
    "sg:phone":"+61 7 3283 2009",
    "sg:postcode":"4019",
    "sg:province":"QLD",
    "wof:name":"Suntanium",
    "wof:placetype":"venue"
},
  "geometry": {"coordinates":[153.098510742,-27.2465267181],"type":"Point"}
}