{
  "type": "Feature",
  "properties": {
    "iso:country":"AU",
    "sg:address":"Suite 6",
    "sg:city":"/Eighth Avenue Shopping Centre Palm Beach",
    "sg:classifiers":[
        {
            "category":"Health Services",
            "subcategory":"Health Practitioner",
            "type":"Services"
        }
    ],
    "sg:phone":"+61 7 5534 3347",
    "sg:postcode":"4221",
    "sg:province":"QLD",
    "sg:tags":[
        "physiotherapist"
    ],
    "wof:name":"Eighth Avenue Palm Beach Physiotherapy & Sports Injury Clinic",
    "wof:placetype":"venue"
},
  "geometry": {"coordinates":[153.47279357900001,-28.1213493347],"type":"Point"}
}