{
  "type": "Feature",
  "properties": {
    "addr:full":"42 Maple St Cooroy QLD 4563",
    "addr:housenumber":"42",
    "addr:postcode":"4563",
    "addr:street":"Maple St",
    "iso:country":"AU",
    "sg:address":"42 Maple St",
    "sg:city":"Cooroy",
    "sg:classifiers":[
        {
            "category":"Real Estate",
            "subcategory":"Real Estate Agent",
            "type":"Services"
        }
    ],
    "sg:phone":"+61 7 5447 6666",
    "sg:postcode":"4563",
    "sg:province":"QLD",
    "wof:name":"E-Noosa Realty",
    "wof:placetype":"venue"
},
  "geometry": {"coordinates":[152.909301758,-26.4192352295],"type":"Point"}
}