{
  "type": "Feature",
  "properties": {
    "addr:full":"73 Victoria St Smithfield NSW 2164",
    "addr:housenumber":"73",
    "addr:postcode":"2164",
    "addr:street":"Victoria St",
    "iso:country":"AU",
    "sg:address":"73 Victoria St",
    "sg:city":"Smithfield",
    "sg:classifiers":[
        {
            "category":"Autos & Motor Vehicles",
            "subcategory":"Auto Supplies",
            "type":"Retail Goods"
        }
    ],
    "sg:phone":"+61 1300 558 559",
    "sg:postcode":"2164",
    "sg:province":"NSW",
    "sg:tags":[
        "tyre"
    ],
    "sg:website":"http://www.tyreteam.com.au",
    "wof:name":"Tyre Team",
    "wof:placetype":"venue"
},
  "geometry": {"coordinates":[150.93565368599999,-33.8507804871],"type":"Point"}
}