{
  "type": "Feature",
  "properties": {
    "addr:full":"PO Box 2228 Brookside Centre QLD 4053",
    "addr:postcode":"4053",
    "iso:country":"AU",
    "sg:address":"PO Box 2228",
    "sg:city":"Brookside Centre",
    "sg:classifiers":[
        {
            "category":"Social Services",
            "subcategory":"Retirement Home",
            "type":"Services"
        }
    ],
    "sg:phone":"+61 401 763 775",
    "sg:postcode":"4053",
    "sg:province":"QLD",
    "sg:tags":[
        "life",
        "coaching"
    ],
    "wof:name":"Flowfect",
    "wof:placetype":"venue"
},
  "geometry": {"coordinates":[153.00721740700001,-27.4091491699],"type":"Point"}
}