{
  "type": "Feature",
  "properties": {
    "addr:full":"7 Homedale Crs Connells Point NSW 2221",
    "addr:housenumber":"7",
    "addr:postcode":"2221",
    "addr:street":"Homedale Crs",
    "iso:country":"AU",
    "sg:address":"7 Homedale Crs",
    "sg:city":"Connells Point",
    "sg:classifiers":[
        {
            "category":"Sports & Exercise",
            "subcategory":"Gym",
            "type":"Entertainment"
        }
    ],
    "sg:phone":"+61 412 902 668",
    "sg:postcode":"2221",
    "sg:province":"NSW",
    "sg:tags":[
        "health",
        "fitness"
    ],
    "wof:name":"Higher Level Pty Ltd",
    "wof:placetype":"venue"
},
  "geometry": {"coordinates":[151.097946167,-33.9854393005],"type":"Point"}
}