{
  "type": "Feature",
  "properties": {
    "addr:full":"2 Butcher Rd Roleystone WA 6111",
    "addr:housenumber":"2",
    "addr:postcode":"6111",
    "addr:street":"Butcher Rd",
    "iso:country":"AU",
    "sg:address":"2 Butcher Rd",
    "sg:city":"Roleystone",
    "sg:classifiers":[
        {
            "category":"Government",
            "subcategory":"Court House",
            "type":"Public Place"
        }
    ],
    "sg:phone":"+61 8 9397 5970",
    "sg:postcode":"6111",
    "sg:province":"WA",
    "sg:tags":[
        "personal",
        "marriage",
        "family",
        "counselling"
    ],
    "wof:name":"Health & Rehabilitation Consultants",
    "wof:placetype":"venue"
},
  "geometry": {"coordinates":[116.06118774399999,-32.127040863],"type":"Point"}
}