{
  "type": "Feature",
  "properties": {
    "addr:full":"Unit 2 / 718 Marshall Rd Malaga WA 6090",
    "addr:housenumber":"/ 718",
    "addr:postcode":"6090",
    "addr:street":"Marshall Rd",
    "iso:country":"AU",
    "sg:address":"Unit 2 / 718 Marshall Rd",
    "sg:city":"Malaga",
    "sg:classifiers":[
        {
            "category":"Professional",
            "subcategory":"Art Services",
            "type":"Services"
        }
    ],
    "sg:phone":"+61 8 9248 1286",
    "sg:postcode":"6090",
    "sg:province":"WA",
    "sg:tags":[
        "graphic",
        "designer"
    ],
    "sg:website":"http://www.s-tcolourprint.com",
    "wof:name":"S & T Graphic Design & Colour Print",
    "wof:placetype":"venue"
},
  "geometry": {"coordinates":[115.90425109900001,-31.8568077087],"type":"Point"}
}