{
  "type": "Feature",
  "properties": {
    "iso:country":"AU",
    "sg:address":"Suite 3, 54 Wheatley St",
    "sg:city":"Bellingen",
    "sg:classifiers":[
        {
            "category":"Health Services",
            "subcategory":"Medical Lab",
            "type":"Services"
        }
    ],
    "sg:phone":"+61 2 6655 2380",
    "sg:postcode":"2454",
    "sg:province":"NSW",
    "sg:tags":[
        "laboratory",
        "pathology"
    ],
    "wof:name":"Sullivan Nicolaides Pathology Laboratories",
    "wof:placetype":"venue"
},
  "geometry": {"coordinates":[152.900024,-30.446411],"type":"Point"}
}