{
  "type": "Feature",
  "properties": {
    "addr:full":"61 Chivers Rd Somersby NSW 2250",
    "addr:housenumber":"61",
    "addr:postcode":"2250",
    "addr:street":"Chivers Rd",
    "iso:country":"AU",
    "sg:address":"61 Chivers Rd",
    "sg:city":"Somersby",
    "sg:classifiers":[
        {
            "category":"Shopping",
            "subcategory":"Pets & Pet Supplies",
            "type":"Retail Goods"
        }
    ],
    "sg:phone":"+61 2 4372 1661",
    "sg:postcode":"2250",
    "sg:province":"NSW",
    "sg:tags":[
        "shop",
        "supplier"
    ],
    "wof:name":"Nutra Vet Pet Products",
    "wof:placetype":"venue"
},
  "geometry": {"coordinates":[151.294555664,-33.4093132019],"type":"Point"}
}