{
  "type": "Feature",
  "properties": {
    "iso:country":"AU",
    "sg:address":"Georges River Rd",
    "sg:city":"Jannali",
    "sg:classifiers":[
        {
            "category":"Building & Trades",
            "subcategory":"Construction",
            "type":"Services"
        }
    ],
    "sg:phone":"+61 2 9838 7877",
    "sg:postcode":"2226",
    "sg:province":"NSW",
    "sg:tags":[
        "insulation",
        "contractor"
    ],
    "wof:name":"Golden Fleece Insulation",
    "wof:placetype":"venue"
},
  "geometry": {"coordinates":[151.06944274899999,-34.0158042908],"type":"Point"}
}