{
  "type": "Feature",
  "properties": {
    "iso:country":"AU",
    "sg:address":"PO Box 159",
    "sg:city":"Foster",
    "sg:classifiers":[
        {
            "category":"Professional",
            "subcategory":"Accounting & Tax Preparation",
            "type":"Services"
        }
    ],
    "sg:phone":"+61 3 5682 1576",
    "sg:postcode":"3960",
    "sg:province":"VIC",
    "sg:tags":[
        "bookkeeping"
    ],
    "wof:name":"Linco Services Pty Ltd",
    "wof:placetype":"venue"
},
  "geometry": {"coordinates":[146.20079040499999,-38.652381897],"type":"Point"}
}