{
  "type": "Feature",
  "properties": {
    "addr:full":"109 Church Rd Eatons Hill QLD 4037",
    "addr:housenumber":"109",
    "addr:postcode":"4037",
    "addr:street":"Church Rd",
    "iso:country":"AU",
    "sg:address":"109 Church Rd",
    "sg:city":"Eatons Hill",
    "sg:classifiers":[
        {
            "category":"Professional",
            "type":"Services"
        }
    ],
    "sg:phone":"+61 417 723 725",
    "sg:postcode":"4037",
    "sg:province":"QLD",
    "sg:tags":[
        "courier"
    ],
    "wof:name":"Bell's Parcel Service",
    "wof:placetype":"venue"
},
  "geometry": {"coordinates":[152.93583699999999,-27.336008],"type":"Point"}
}