{
  "type": "Feature",
  "properties": {
    "iso:country":"AU",
    "sg:address":"52 Powell St",
    "sg:city":"Wulguru",
    "sg:classifiers":[
        {
            "category":"Building & Trades",
            "subcategory":"Construction",
            "type":"Services"
        }
    ],
    "sg:phone":"+61 438 893 416",
    "sg:postcode":"4811",
    "sg:province":"QLD",
    "sg:tags":[
        "concrete",
        "contractor"
    ],
    "wof:name":"OK Concrete Constructions Pty Ltd",
    "wof:placetype":"venue"
},
  "geometry": {"coordinates":[146.82081600000001,-19.330498],"type":"Point"}
}