{
  "type": "Feature",
  "properties": {
    "addr:full":"373 North Rocks Rd North Rocks NSW 2151",
    "addr:housenumber":"373",
    "addr:postcode":"2151",
    "addr:street":"North Rocks Rd",
    "iso:country":"AU",
    "sg:address":"373 North Rocks Rd",
    "sg:city":"North Rocks",
    "sg:classifiers":[
        {
            "category":"Home & Garden",
            "subcategory":"Garden Supply",
            "type":"Retail Goods"
        }
    ],
    "sg:phone":"+61 2 9873 3718",
    "sg:postcode":"2151",
    "sg:province":"NSW",
    "sg:tags":[
        "equipment"
    ],
    "wof:name":"North Rocks Mowers",
    "wof:placetype":"venue"
},
  "geometry": {"coordinates":[151.02859497099999,-33.7680244446],"type":"Point"}
}