{
  "type": "Feature",
  "properties": {
    "addr:full":"8 Clare St Gladesville NSW 2111",
    "addr:housenumber":"8",
    "addr:postcode":"2111",
    "addr:street":"Clare St",
    "iso:country":"AU",
    "sg:address":"8 Clare St",
    "sg:city":"Gladesville",
    "sg:classifiers":[
        {
            "category":"Professional",
            "subcategory":"Art Services",
            "type":"Services"
        }
    ],
    "sg:phone":"+61 2 9817 8741",
    "sg:postcode":"2111",
    "sg:province":"NSW",
    "sg:tags":[
        "decorator",
        "painter"
    ],
    "wof:name":"Sky Painters",
    "wof:placetype":"venue"
},
  "geometry": {"coordinates":[151.12176513700001,-33.8366241455],"type":"Point"}
}