{
  "type": "Feature",
  "properties": {
    "addr:full":"176 Burwood Rd Hawthorn VIC 3122",
    "addr:housenumber":"176",
    "addr:postcode":"3122",
    "addr:street":"Burwood Rd",
    "iso:country":"AU",
    "sg:address":"176 Burwood Rd",
    "sg:city":"Hawthorn",
    "sg:classifiers":[
        {
            "category":"Autos & Motor Vehicles",
            "subcategory":"Boat Sales",
            "type":"Retail Goods"
        }
    ],
    "sg:phone":"+61 3 9818 1622",
    "sg:postcode":"3122",
    "sg:province":"VIC",
    "sg:tags":[
        "yacht"
    ],
    "wof:name":"Inflatacraft",
    "wof:placetype":"venue"
},
  "geometry": {"coordinates":[145.02859497099999,-37.8219299316],"type":"Point"}
}