{
  "type": "Feature",
  "properties": {
    "addr:full":"11-18 Douglas Rd Quakers Hill NSW 2763",
    "addr:housenumber":"11-18",
    "addr:postcode":"2763",
    "addr:street":"Douglas Rd",
    "iso:country":"AU",
    "sg:address":"11-18 Douglas Rd",
    "sg:city":"Quakers Hill",
    "sg:classifiers":[
        {
            "category":"Deli",
            "type":"Food & Drink"
        }
    ],
    "sg:phone":"+61 2 9837 8011",
    "sg:postcode":"2763",
    "sg:province":"NSW",
    "sg:tags":[
        "delicatessen"
    ],
    "wof:name":"Yummy Bakery & Delicatessen",
    "wof:placetype":"venue"
},
  "geometry": {"coordinates":[150.88404846200001,-33.7273178101],"type":"Point"}
}