{
  "type": "Feature",
  "properties": {
    "addr:full":"Suite 4A, Standish Medical Centre, 33 Berry St Nowra NSW 2541",
    "addr:housenumber":"33",
    "addr:postcode":"2541",
    "addr:street":"Berry St",
    "iso:country":"AU",
    "sg:address":"Suite 4A, Standish Medical Centre, 33 Berry St",
    "sg:city":"Nowra",
    "sg:classifiers":[
        {
            "category":"Health Services",
            "subcategory":"Doctor",
            "type":"Services"
        }
    ],
    "sg:phone":"+61 2 4423 1944",
    "sg:postcode":"2541",
    "sg:province":"NSW",
    "sg:tags":[
        "medical",
        "practitioner"
    ],
    "wof:name":"Nuclear Medicine (Southern Group)",
    "wof:placetype":"venue"
},
  "geometry": {"coordinates":[150.60020446799999,-34.8756103516],"type":"Point"}
}