{
  "type": "Feature",
  "properties": {
    "addr:full":"263 Ross Rd Ravenshoe QLD 4872",
    "addr:housenumber":"263",
    "addr:postcode":"4872",
    "addr:street":"Ross Rd",
    "iso:country":"AU",
    "sg:address":"263 Ross Rd",
    "sg:city":"Ravenshoe",
    "sg:classifiers":[
        {
            "category":"Professional",
            "subcategory":"Employment Agencies",
            "type":"Services"
        }
    ],
    "sg:phone":"+61 7 4097 6008",
    "sg:postcode":"4872",
    "sg:province":"QLD",
    "sg:tags":[
        "entertainer",
        "agent"
    ],
    "wof:name":"Jim Black",
    "wof:placetype":"venue"
},
  "geometry": {"coordinates":[145.517303467,-17.5531787872],"type":"Point"}
}