{
  "type": "Feature",
  "properties": {
    "addr:full":"Factory 2 - 108 Bell St Preston VIC 3072",
    "addr:housenumber":"108",
    "addr:postcode":"3072",
    "addr:street":"Bell St",
    "iso:country":"AU",
    "sg:address":"Factory 2 - 108 Bell St",
    "sg:city":"Preston",
    "sg:classifiers":[
        {
            "category":"Retail",
            "subcategory":"Auto Repair",
            "type":"Services"
        }
    ],
    "sg:phone":"+61 3 9480 2400",
    "sg:postcode":"3072",
    "sg:province":"VIC",
    "sg:tags":[
        "beater",
        "painter",
        "panel"
    ],
    "wof:name":"Preston Collision Centre",
    "wof:placetype":"venue"
},
  "geometry": {"coordinates":[145.02435302699999,-37.7473869324],"type":"Point"}
}