{
  "type": "Feature",
  "properties": {
    "addr:full":"168 St Johns Rd Glebe NSW 2037",
    "addr:housenumber":"168",
    "addr:postcode":"2037",
    "addr:street":"St Johns Rd",
    "iso:country":"AU",
    "sg:address":"168 St Johns Rd",
    "sg:city":"Glebe",
    "sg:classifiers":[
        {
            "category":"Professional",
            "subcategory":"Art Services",
            "type":"Services"
        }
    ],
    "sg:phone":"+61 2 9660 0328",
    "sg:postcode":"2037",
    "sg:province":"NSW",
    "sg:tags":[
        "picture",
        "frame",
        "framing"
    ],
    "wof:name":"Glebe Picture Frames",
    "wof:placetype":"venue"
},
  "geometry": {"coordinates":[151.18447875999999,-33.8827323914],"type":"Point"}
}