{
  "type": "Feature",
  "properties": {
    "addr:full":"Baillie St Horsham VIC 3400",
    "addr:postcode":"3400",
    "addr:street":"Baillie St",
    "iso:country":"AU",
    "sg:address":"Baillie St",
    "sg:city":"Horsham",
    "sg:classifiers":[
        {
            "category":"Social Services",
            "subcategory":"Child Care",
            "type":"Services"
        }
    ],
    "sg:phone":"+61 419 568 784",
    "sg:postcode":"3400",
    "sg:province":"VIC",
    "wof:name":"Horsham 298 Primary Out of School Hours Care",
    "wof:placetype":"venue"
},
  "geometry": {"coordinates":[142.202728272,-36.7141151428],"type":"Point"}
}