{
  "type": "Feature",
  "properties": {
    "iso:country":"AU",
    "sg:address":"107 Mooney St",
    "sg:city":"Gulliver",
    "sg:classifiers":[
        {
            "category":"Food & Beverages",
            "subcategory":"Bakery",
            "type":"Retail Goods"
        }
    ],
    "sg:phone":"+61 7 4779 2861",
    "sg:postcode":"4812",
    "sg:province":"QLD",
    "sg:tags":[
        "cake",
        "shop",
        "pastry"
    ],
    "sg:website":"http://www.kingscakes.com.au",
    "wof:name":"Kings Home Style Cakes",
    "wof:placetype":"venue"
},
  "geometry": {"coordinates":[146.77134699999999,-19.283621],"type":"Point"}
}