{
  "type": "Feature",
  "properties": {
    "addr:full":"L1 108 Bronte Rd Bondi Junction NSW 2022",
    "addr:housenumber":"108",
    "addr:postcode":"2022",
    "addr:street":"Bronte Rd",
    "iso:country":"AU",
    "sg:address":"L1 108 Bronte Rd",
    "sg:city":"Bondi Junction",
    "sg:classifiers":[
        {
            "category":"Professional",
            "subcategory":"Accounting & Tax Preparation",
            "type":"Services"
        }
    ],
    "sg:phone":"+61 2 9389 9056",
    "sg:postcode":"2022",
    "sg:province":"NSW",
    "sg:tags":[
        "accountant",
        "auditor"
    ],
    "wof:name":"Mansfield P.F.",
    "wof:placetype":"venue"
},
  "geometry": {"coordinates":[151.250930786,-33.8954238892],"type":"Point"}
}