{
  "type": "Feature",
  "properties": {
    "iso:country":"AU",
    "sg:address":"44 Carnarvon Crs",
    "sg:city":"Waterford",
    "sg:classifiers":[
        {
            "category":"Building & Trades",
            "subcategory":"Construction",
            "type":"Services"
        }
    ],
    "sg:phone":"+61 7 3382 7800",
    "sg:postcode":"4133",
    "sg:province":"QLD",
    "sg:tags":[
        "contractor"
    ],
    "wof:name":"Darrington Homes",
    "wof:placetype":"venue"
},
  "geometry": {"coordinates":[153.067016602,-27.7343101501],"type":"Point"}
}