{
  "type": "Feature",
  "properties": {
    "addr:full":"52 Kingston Rd Underwood QLD 4119",
    "addr:housenumber":"52",
    "addr:postcode":"4119",
    "addr:street":"Kingston Rd",
    "iso:country":"AU",
    "sg:address":"52 Kingston Rd",
    "sg:city":"Underwood",
    "sg:classifiers":[
        {
            "category":"Home & Garden",
            "subcategory":"Building Materials",
            "type":"Retail Goods"
        }
    ],
    "sg:phone":"+61 7 3841 0566",
    "sg:postcode":"4119",
    "sg:province":"QLD",
    "sg:tags":[
        "fitting",
        "door"
    ],
    "wof:name":"Door Discounters",
    "wof:placetype":"venue"
},
  "geometry": {"coordinates":[153.113845825,-27.6136932373],"type":"Point"}
}