{
  "type": "Feature",
  "properties": {
    "iso:country":"AU",
    "sg:address":"15 McCauley St",
    "sg:city":"Alexandria",
    "sg:classifiers":[
        {
            "category":"Shopping",
            "subcategory":"Gifts & Souvenirs",
            "type":"Retail Goods"
        }
    ],
    "sg:phone":"+61 2 9698 3933",
    "sg:postcode":"2015",
    "sg:province":"NSW",
    "sg:tags":[
        "greeting",
        "card"
    ],
    "wof:name":"M.F.P.A.",
    "wof:placetype":"venue"
},
  "geometry": {"coordinates":[151.19862365700001,-33.9032554626],"type":"Point"}
}