{
  "type": "Feature",
  "properties": {
    "addr:full":"229 Lyons St Cairns QLD 4870",
    "addr:housenumber":"229",
    "addr:postcode":"4870",
    "addr:street":"Lyons St",
    "iso:country":"AU",
    "sg:address":"229 Lyons St",
    "sg:city":"Cairns",
    "sg:classifiers":[
        {
            "category":"Professional",
            "subcategory":"Advertising",
            "type":"Services"
        }
    ],
    "sg:phone":"+61 419 709 431",
    "sg:postcode":"4870",
    "sg:province":"QLD",
    "sg:tags":[
        "balloon",
        "novelty"
    ],
    "wof:name":"Everything Inflatable Advertising",
    "wof:placetype":"venue"
},
  "geometry": {"coordinates":[145.757446289,-16.9410572052],"type":"Point"}
}