{
  "type": "Feature",
  "properties": {
    "addr:full":"Unit 2, 15 Prindiville Drv Wangara WA 6065",
    "addr:housenumber":"15",
    "addr:postcode":"6065",
    "addr:street":"Prindiville Drv",
    "iso:country":"AU",
    "sg:address":"Unit 2, 15 Prindiville Drv",
    "sg:city":"Wangara",
    "sg:classifiers":[
        {
            "category":"Retail",
            "subcategory":"Auto Repair",
            "type":"Services"
        }
    ],
    "sg:phone":"+61 8 9409 9634",
    "sg:postcode":"6065",
    "sg:province":"WA",
    "sg:tags":[
        "electrical"
    ],
    "wof:name":"North Coast Auto Electrics",
    "wof:placetype":"venue"
},
  "geometry": {"coordinates":[115.816383362,-31.7908382416],"type":"Point"}
}