{
  "type": "Feature",
  "properties": {
    "addr:full":"2a Hilltop Drv Upper Sturt SA 5156",
    "addr:housenumber":"2a",
    "addr:postcode":"5156",
    "addr:street":"Hilltop Drv",
    "iso:country":"AU",
    "sg:address":"2a Hilltop Drv",
    "sg:city":"Upper Sturt",
    "sg:classifiers":[
        {
            "category":"Farming",
            "subcategory":"Nursery",
            "type":"Manufacturing & Wholesale Goods"
        }
    ],
    "sg:phone":"+61 8 8339 1912",
    "sg:postcode":"5156",
    "sg:province":"SA",
    "wof:name":"Hancox Nursery",
    "wof:placetype":"venue"
},
  "geometry": {"coordinates":[138.66987609899999,-35.026386261],"type":"Point"}
}