{
  "type": "Feature",
  "properties": {
    "iso:country":"AU",
    "sg:address":"KMart Plaza Shopping Centre Cnr Creek & Wynnum Rds",
    "sg:city":"Cannon Hill",
    "sg:classifiers":[
        {
            "category":"Insurance",
            "subcategory":"Hazard Insurance",
            "type":"Services"
        }
    ],
    "sg:phone":"+61 13 11 75",
    "sg:postcode":"4170",
    "sg:province":"QLD",
    "sg:tags":[
        "motor",
        "vehicle"
    ],
    "wof:name":"Suncorp",
    "wof:placetype":"venue"
},
  "geometry": {"coordinates":[153.086624145,-27.467956543],"type":"Point"}
}