{
  "type": "Feature",
  "properties": {
    "addr:full":"8 deloraine Rd Edwardstown SA 5039",
    "addr:housenumber":"8",
    "addr:postcode":"5039",
    "addr:street":"Deloraine Rd",
    "iso:country":"AU",
    "sg:address":"8 deloraine Rd",
    "sg:city":"Edwardstown",
    "sg:classifiers":[
        {
            "category":"Manufacturing",
            "subcategory":"Chemicals & Compounds",
            "type":"Manufacturing & Wholesale Goods"
        }
    ],
    "sg:phone":"+61 8 8276 7555",
    "sg:postcode":"5039",
    "sg:province":"SA",
    "sg:tags":[
        "electroplating"
    ],
    "wof:name":"Electrometal",
    "wof:placetype":"venue"
},
  "geometry": {"coordinates":[138.57313537600001,-34.9878311157],"type":"Point"}
}