{
  "type": "Feature",
  "properties": {
    "addr:full":"56 Godwin St Bulimba QLD 4171",
    "addr:housenumber":"56",
    "addr:postcode":"4171",
    "addr:street":"Godwin St",
    "iso:country":"AU",
    "sg:address":"56 Godwin St",
    "sg:city":"Bulimba",
    "sg:classifiers":[
        {
            "category":"Utilities",
            "type":"Services"
        }
    ],
    "sg:phone":"+61 1300 888 504",
    "sg:postcode":"4171",
    "sg:province":"QLD",
    "sg:tags":[
        "refrigeration",
        "industrial",
        "commercial",
        "retail"
    ],
    "wof:name":"Fridge Seals Direct",
    "wof:placetype":"venue"
},
  "geometry": {"coordinates":[153.05607605,-27.4538593292],"type":"Point"}
}