{
  "type": "Feature",
  "properties": {
    "iso:country":"AU",
    "sg:address":"38 Dalmont St",
    "sg:city":"Highett",
    "sg:classifiers":[
        {
            "category":"Professional",
            "subcategory":"Computer Services",
            "type":"Services"
        }
    ],
    "sg:phone":"+61 3 9532 2822",
    "sg:postcode":"3190",
    "sg:province":"VIC",
    "sg:tags":[
        "consultant",
        "system"
    ],
    "wof:name":"Synectic Systems Pty Ltd",
    "wof:placetype":"venue"
},
  "geometry": {"coordinates":[145.02607727,-37.9477806091],"type":"Point"}
}