{
  "type": "Feature",
  "properties": {
    "iso:country":"AU",
    "sg:address":"Level 1, 110 Yambil St",
    "sg:city":"Griffith",
    "sg:classifiers":[
        {
            "category":"Banks & Credit Unions",
            "subcategory":"Bank",
            "type":"Services"
        }
    ],
    "sg:phone":"+61 2 6964 5388",
    "sg:postcode":"2680",
    "sg:province":"NSW",
    "wof:name":"Rabobank",
    "wof:placetype":"venue"
},
  "geometry": {"coordinates":[146.05209400000001,-34.290184],"type":"Point"}
}