{
  "type": "Feature",
  "properties": {
    "addr:full":"9 Hi-Tech Pl Rowville VIC 3178",
    "addr:housenumber":"9",
    "addr:postcode":"3178",
    "addr:street":"Hi-Tech Pl",
    "iso:country":"AU",
    "sg:address":"9 Hi-Tech Pl",
    "sg:city":"Rowville",
    "sg:classifiers":[
        {
            "category":"Shopping",
            "subcategory":"Computers & Home Electronics",
            "type":"Retail Goods"
        }
    ],
    "sg:phone":"+61 1300 888 030",
    "sg:postcode":"3178",
    "sg:province":"VIC",
    "sg:tags":[
        "hardware",
        "equipment"
    ],
    "wof:name":"Xenon",
    "wof:placetype":"venue"
},
  "geometry": {"coordinates":[145.24615478499999,-37.9102706909],"type":"Point"}
}