{
  "type": "Feature",
  "properties": {
    "iso:country":"AU",
    "sg:address":"221 Vulture St",
    "sg:city":"South Brisbane",
    "sg:classifiers":[
        {
            "category":"Real Estate",
            "subcategory":"Real Estate Agent",
            "type":"Services"
        }
    ],
    "sg:phone":"+61 7 3830 5376",
    "sg:postcode":"4101",
    "sg:province":"QLD",
    "wof:name":"Mike McHutchison",
    "wof:placetype":"venue"
},
  "geometry": {"coordinates":[153.020950317,-27.4824619293],"type":"Point"}
}