{
  "type": "Feature",
  "properties": {
    "addr:full":"West Portland Rd Sackville NSW 2756",
    "addr:postcode":"2756",
    "addr:street":"West Portland Rd",
    "iso:country":"AU",
    "sg:address":"West Portland Rd",
    "sg:city":"Sackville",
    "sg:classifiers":[
        {
            "category":"Utilities",
            "subcategory":"Electric",
            "type":"Services"
        }
    ],
    "sg:phone":"+61 427 790 135",
    "sg:postcode":"2756",
    "sg:province":"NSW",
    "sg:tags":[
        "electrical",
        "contractor"
    ],
    "wof:name":"Leigh Williams",
    "wof:placetype":"venue"
},
  "geometry": {"coordinates":[150.869262695,-33.5046463013],"type":"Point"}
}