{
  "type": "Feature",
  "properties": {
    "iso:country":"AU",
    "sg:address":"PO Box 470",
    "sg:city":"Bright",
    "sg:classifiers":[
        {
            "category":"Travel",
            "subcategory":"Travel Agent",
            "type":"Entertainment"
        }
    ],
    "sg:phone":"+61 3 5755 5100",
    "sg:postcode":"3741",
    "sg:province":"VIC",
    "sg:tags":[
        "tour",
        "holiday",
        "adventure"
    ],
    "wof:name":"5 Star Adventure Tours",
    "wof:placetype":"venue"
},
  "geometry": {"coordinates":[146.96012899999999,-36.72739],"type":"Point"}
}