{
  "type": "Feature",
  "properties": {
    "addr:full":"111 Camp Flat Rd Bli Bli QLD 4560",
    "addr:housenumber":"111",
    "addr:postcode":"4560",
    "addr:street":"Camp Flat Rd",
    "iso:country":"AU",
    "sg:address":"111 Camp Flat Rd",
    "sg:city":"Bli Bli",
    "sg:classifiers":[
        {
            "category":"Building & Trades",
            "subcategory":"Construction",
            "type":"Services"
        }
    ],
    "sg:phone":"+61 7 5448 5902",
    "sg:postcode":"4560",
    "sg:province":"QLD",
    "sg:tags":[
        "earth",
        "excavating",
        "moving",
        "contractor"
    ],
    "wof:name":"Bli Bli & Districts Bobcat Services",
    "wof:placetype":"venue"
},
  "geometry": {"coordinates":[153.02084350600001,-26.6084365845],"type":"Point"}
}