{
  "type": "Feature",
  "properties": {
    "iso:country":"AU",
    "sg:address":"408 Main Rd",
    "sg:city":"St Albans West",
    "sg:classifiers":[
        {
            "category":"Health Services",
            "subcategory":"Health Practitioner",
            "type":"Services"
        }
    ],
    "sg:phone":"+61 3 8307 3207",
    "sg:postcode":"3021",
    "sg:province":"VIC",
    "sg:tags":[
        "osteopath"
    ],
    "wof:name":"Peter Malic, Dr",
    "wof:placetype":"venue"
},
  "geometry": {"coordinates":[144.79203799999999,-37.743172],"type":"Point"}
}