{
  "type": "Feature",
  "properties": {
    "addr:full":"40 Kepler St Warrnambool VIC 3280",
    "addr:housenumber":"40",
    "addr:postcode":"3280",
    "addr:street":"Kepler St",
    "iso:country":"AU",
    "sg:address":"40 Kepler St",
    "sg:city":"Warrnambool",
    "sg:classifiers":[
        {
            "category":"Personal",
            "subcategory":"Hair Removal",
            "type":"Services"
        }
    ],
    "sg:phone":"+61 408 997 044",
    "sg:postcode":"3280",
    "sg:province":"VIC",
    "wof:name":"Barely There",
    "wof:placetype":"venue"
},
  "geometry": {"coordinates":[142.48338317899999,-38.3879852295],"type":"Point"}
}