{
  "type": "Feature",
  "properties": {
    "addr:full":"68 Killara Rd Campbellfield VIC 3061",
    "addr:housenumber":"68",
    "addr:postcode":"3061",
    "addr:street":"Killara Rd",
    "iso:country":"AU",
    "sg:address":"68 Killara Rd",
    "sg:city":"Campbellfield",
    "sg:classifiers":[
        {
            "category":"Utilities",
            "subcategory":"Natural Gas",
            "type":"Services"
        }
    ],
    "sg:phone":"+61 3 9357 0022",
    "sg:postcode":"3061",
    "sg:province":"VIC",
    "sg:tags":[
        "pressing",
        "metal",
        "stamping"
    ],
    "wof:name":"Wenlec Pty Ltd",
    "wof:placetype":"venue"
},
  "geometry": {"coordinates":[144.96510314899999,-37.6625938416],"type":"Point"}
}