{
  "type": "Feature",
  "properties": {
    "iso:country":"AU",
    "sg:address":"Shop 3 Kingsley Shopping Centre",
    "sg:city":"Kingsley",
    "sg:classifiers":[
        {
            "category":"Communications",
            "subcategory":"Film & Video Production",
            "type":"Services"
        }
    ],
    "sg:phone":"+61 8 9409 6966",
    "sg:postcode":"6026",
    "sg:province":"WA",
    "sg:tags":[
        "dvd",
        "library"
    ],
    "wof:name":"Video City",
    "wof:placetype":"venue"
},
  "geometry": {"coordinates":[115.788528442,-31.8000850677],"type":"Point"}
}