{
  "type": "Feature",
  "properties": {
    "iso:country":"AU",
    "sg:address":"25 Newcastle St",
    "sg:city":"Morisset",
    "sg:classifiers":[
        {
            "category":"Building & Trades",
            "subcategory":"Construction",
            "type":"Services"
        }
    ],
    "sg:phone":"+61 2 4973 2204",
    "sg:postcode":"2264",
    "sg:province":"NSW",
    "sg:tags":[
        "earth",
        "excavating",
        "moving",
        "contractor"
    ],
    "wof:name":"Greentree John Excavations",
    "wof:placetype":"venue"
},
  "geometry": {"coordinates":[151.48999,-33.105003],"type":"Point"}
}