{
  "type": "Feature",
  "properties": {
    "addr:full":"Shop 12, Target Centre 236 Bourke Melbourne VIC 3000",
    "addr:housenumber":"shop 12;236",
    "addr:postcode":"3000",
    "addr:street":"Bourke",
    "iso:country":"AU",
    "sg:address":"Shop 12, Target Centre 236",
    "sg:city":"Bourke Melbourne",
    "sg:classifiers":[
        {
            "category":"Casinos & Gambling",
            "type":"Entertainment"
        }
    ],
    "sg:phone":"+61 3 9662 1760",
    "sg:postcode":"3000",
    "sg:province":"VIC",
    "sg:tags":[
        "lottery",
        "agent"
    ],
    "wof:name":"Bourke Street Lotto",
    "wof:placetype":"venue"
},
  "geometry": {"coordinates":[144.966064453,-37.8132553101],"type":"Point"}
}