{
  "type": "Feature",
  "properties": {
    "addr:full":"Logan House South, Riverside Corporate Park, 25 Do South Brisbane QLD 4101",
    "addr:housenumber":"25",
    "addr:postcode":"4101",
    "addr:street":"South;Corporate",
    "iso:country":"AU",
    "sg:address":"Logan House South, Riverside Corporate Park, 25 Do",
    "sg:city":"South Brisbane",
    "sg:classifiers":[
        {
            "category":"Professional",
            "subcategory":"Detective & Security Services",
            "type":"Services"
        }
    ],
    "sg:phone":"+61 7 3846 4833",
    "sg:postcode":"4101",
    "sg:province":"QLD",
    "sg:tags":[
        "identification",
        "system"
    ],
    "wof:name":"Mobile Data Systems",
    "wof:placetype":"venue"
},
  "geometry": {"coordinates":[153.008087158,-27.4761943817],"type":"Point"}
}