{
  "type": "Feature",
  "properties": {
    "iso:country":"AU",
    "sg:address":"Shop 5, Goonellabah Village Shopping Centre, Cnr Simeoni & Oliver Drives",
    "sg:city":"Goonellabah",
    "sg:classifiers":[
        {
            "category":"Fast Food",
            "type":"Food & Drink"
        }
    ],
    "sg:phone":"+61 2 6624 7599",
    "sg:postcode":"2480",
    "sg:province":"NSW",
    "sg:tags":[
        "away",
        "take"
    ],
    "wof:name":"Eagle Boys Pizza - Goonellabah",
    "wof:placetype":"venue"
},
  "geometry": {"coordinates":[153.32769775400001,-28.8209667206],"type":"Point"}
}