{
  "type": "Feature",
  "properties": {
    "addr:full":"Shop 2, 64 Ware St Fairfield NSW 2165",
    "addr:housenumber":"shop;64",
    "addr:postcode":"2165",
    "addr:street":"Ware St",
    "iso:country":"AU",
    "sg:address":"Shop 2, 64 Ware St",
    "sg:city":"Fairfield",
    "sg:classifiers":[
        {
            "category":"Shopping",
            "subcategory":"Jewelry",
            "type":"Retail Goods"
        }
    ],
    "sg:phone":"+61 2 9723 9933",
    "sg:postcode":"2165",
    "sg:province":"NSW",
    "sg:tags":[
        "jeweller"
    ],
    "wof:name":"Moden Jewellery",
    "wof:placetype":"venue"
},
  "geometry": {"coordinates":[150.954910278,-33.8706207275],"type":"Point"}
}