{
  "type": "Feature",
  "properties": {
    "addr:full":"220 Harbord Rd Brookvale NSW 2100",
    "addr:housenumber":"220",
    "addr:postcode":"2100",
    "addr:street":"Harbord Rd",
    "iso:country":"AU",
    "sg:address":"220 Harbord Rd",
    "sg:city":"Brookvale",
    "sg:classifiers":[
        {
            "category":"Wholesale",
            "subcategory":"Auto Parts",
            "type":"Manufacturing & Wholesale Goods"
        }
    ],
    "sg:phone":"+61 2 9938 2242",
    "sg:postcode":"2100",
    "sg:province":"NSW",
    "sg:tags":[
        "recyclers"
    ],
    "wof:name":"G.B.s Mini & Moke World",
    "wof:placetype":"venue"
},
  "geometry": {"coordinates":[151.279953003,-33.7611312866],"type":"Point"}
}