{
  "type": "Feature",
  "properties": {
    "iso:country":"AU",
    "sg:address":"253 Hutt St",
    "sg:city":"Adelaide",
    "sg:classifiers":[
        {
            "category":"Food & Beverages",
            "subcategory":"Liquor & Beverages",
            "type":"Retail Goods"
        }
    ],
    "sg:phone":"+61 8 8232 1570",
    "sg:postcode":"5000",
    "sg:province":"SA",
    "sg:tags":[
        "store"
    ],
    "wof:name":"Hutt Street Cellars",
    "wof:placetype":"venue"
},
  "geometry": {"coordinates":[138.612228394,-34.9341621399],"type":"Point"}
}