{
  "type": "Feature",
  "properties": {
    "addr:full":"18 Victoria St Nhill VIC 3418",
    "addr:housenumber":"18",
    "addr:postcode":"3418",
    "addr:street":"Victoria St",
    "iso:country":"AU",
    "sg:address":"18 Victoria St",
    "sg:city":"Nhill",
    "sg:classifiers":[
        {
            "category":"Food & Beverages",
            "subcategory":"Supermarket",
            "type":"Retail Goods"
        }
    ],
    "sg:phone":"+61 3 5391 1119",
    "sg:postcode":"3418",
    "sg:province":"VIC",
    "sg:tags":[
        "grocery",
        "store"
    ],
    "wof:name":"Hoffmans IGA Supermarkets",
    "wof:placetype":"venue"
},
  "geometry": {"coordinates":[141.649093628,-36.3335418701],"type":"Point"}
}