{
  "type": "Feature",
  "properties": {
    "iso:country":"AU",
    "sg:address":"Factory 4 71 Rushdale St",
    "sg:city":"Scoresby",
    "sg:classifiers":[
        {
            "category":"Manufacturing",
            "subcategory":"Rubber & Plastics",
            "type":"Manufacturing & Wholesale Goods"
        }
    ],
    "sg:phone":"+61 3 9764 1622",
    "sg:postcode":"3179",
    "sg:province":"VIC",
    "sg:tags":[
        "equipment",
        "card"
    ],
    "wof:name":"Concept Data Marketing",
    "wof:placetype":"venue"
},
  "geometry": {"coordinates":[145.25296020499999,-37.9009399414],"type":"Point"}
}