{
  "type": "Feature",
  "properties": {
    "addr:full":"14 McIntyre St Mornington TAS 7018",
    "addr:housenumber":"14",
    "addr:postcode":"7018",
    "addr:street":"Mcintyre St",
    "iso:country":"AU",
    "sg:address":"14 McIntyre St",
    "sg:city":"Mornington",
    "sg:classifiers":[
        {
            "category":"Manufacturing",
            "subcategory":"Retail Goods",
            "type":"Manufacturing & Wholesale Goods"
        }
    ],
    "sg:phone":"+61 3 6244 1163",
    "sg:postcode":"7018",
    "sg:province":"TAS",
    "sg:tags":[
        "merchant",
        "pump",
        "mfrs"
    ],
    "wof:name":"Eastern Shore Marine",
    "wof:placetype":"venue"
},
  "geometry": {"coordinates":[147.39573669399999,-42.8602638245],"type":"Point"}
}