{
  "type": "Feature",
  "properties": {
    "addr:full":"Shop 1, Camberwell Centre 570 Burke Rd Camberwell VIC 3124",
    "addr:housenumber":"shop 1;570",
    "addr:postcode":"3124",
    "addr:street":"Camberwell Centre;Burke Rd",
    "iso:country":"AU",
    "sg:address":"Shop 1, Camberwell Centre 570 Burke Rd",
    "sg:city":"Camberwell",
    "sg:classifiers":[
        {
            "category":"Health Services",
            "subcategory":"Optometrist",
            "type":"Services"
        }
    ],
    "sg:phone":"+61 3 9882 8088",
    "sg:postcode":"3124",
    "sg:province":"VIC",
    "wof:name":"Laubman & Pank",
    "wof:placetype":"venue"
},
  "geometry": {"coordinates":[145.05694580100001,-37.8308792114],"type":"Point"}
}