{
  "type": "Feature",
  "properties": {
    "iso:country":"AU",
    "sg:address":"191 Glen Rd",
    "sg:city":"Huonville",
    "sg:classifiers":[
        {
            "category":"Wholesale",
            "subcategory":"Seafood",
            "type":"Manufacturing & Wholesale Goods"
        }
    ],
    "sg:phone":"+61 3 6244 8102",
    "sg:postcode":"7109",
    "sg:province":"TAS",
    "sg:tags":[
        "fish"
    ],
    "wof:name":"Tassal Operations Pty Ltd",
    "wof:placetype":"venue"
},
  "geometry": {"coordinates":[147.06065368599999,-43.0115394592],"type":"Point"}
}