{
  "type": "Feature",
  "properties": {
    "addr:full":"33 Michelle Drv Kiewa VIC 3691",
    "addr:housenumber":"33",
    "addr:postcode":"3691",
    "addr:street":"Michelle Drv",
    "iso:country":"AU",
    "sg:address":"33 Michelle Drv",
    "sg:city":"Kiewa",
    "sg:classifiers":[
        {
            "category":"Building & Trades",
            "subcategory":"Construction",
            "type":"Services"
        }
    ],
    "sg:phone":"+61 438 045 176",
    "sg:postcode":"3691",
    "sg:province":"VIC",
    "sg:tags":[
        "rendering",
        "cement"
    ],
    "wof:name":"David Lambden Rendering",
    "wof:placetype":"venue"
},
  "geometry": {"coordinates":[147.00758400000001,-36.253803],"type":"Point"}
}