{
  "type": "Feature",
  "properties": {
    "addr:full":"PO Box 2533 Brookside Centre QLD 4053",
    "addr:postcode":"4053",
    "iso:country":"AU",
    "sg:address":"PO Box 2533",
    "sg:city":"Brookside Centre",
    "sg:classifiers":[
        {
            "category":"Train Station",
            "subcategory":"Rail",
            "type":"Transportation"
        }
    ],
    "sg:phone":"+61 427 555 730",
    "sg:postcode":"4053",
    "sg:province":"QLD",
    "sg:tags":[
        "repair",
        "vinyl",
        "welding"
    ],
    "wof:name":"Brisbane Vinyl Repair",
    "wof:placetype":"venue"
},
  "geometry": {"coordinates":[152.97911071799999,-27.4088497162],"type":"Point"}
}