{
  "type": "Feature",
  "properties": {
    "addr:full":"136 Wollombi Rd Cessnock NSW 2325",
    "addr:housenumber":"136",
    "addr:postcode":"2325",
    "addr:street":"Wollombi Rd",
    "iso:country":"AU",
    "sg:address":"136 Wollombi Rd",
    "sg:city":"Cessnock",
    "sg:classifiers":[
        {
            "category":"Travel",
            "subcategory":"Hotels & Motels",
            "type":"Entertainment"
        }
    ],
    "sg:phone":"+61 2 4990 1256",
    "sg:postcode":"2325",
    "sg:province":"NSW",
    "sg:tags":[
        "accommodation"
    ],
    "wof:name":"Australia Hotel",
    "wof:placetype":"venue"
},
  "geometry": {"coordinates":[151.3465271,-32.8363571167],"type":"Point"}
}