{
  "type": "Feature",
  "properties": {
    "addr:full":"17 Thwaites Drv Moss Vale NSW 2577",
    "addr:housenumber":"17",
    "addr:postcode":"2577",
    "addr:street":"Thwaites Drv",
    "iso:country":"AU",
    "sg:address":"17 Thwaites Drv",
    "sg:city":"Moss Vale",
    "sg:classifiers":[
        {
            "category":"Building & Trades",
            "subcategory":"Plumbing",
            "type":"Services"
        }
    ],
    "sg:phone":"+61 2 4869 3030",
    "sg:postcode":"2577",
    "sg:province":"NSW",
    "sg:tags":[
        "equipment",
        "valves"
    ],
    "wof:name":"DeZurik",
    "wof:placetype":"venue"
},
  "geometry": {"coordinates":[150.38769531200001,-34.5373344421],"type":"Point"}
}