{
  "type": "Feature",
  "properties": {
    "addr:full":"7 Newton Court, Jan St Newton SA 5074",
    "addr:housenumber":"7",
    "addr:postcode":"5074",
    "addr:street":"Newton Court Jan St",
    "iso:country":"AU",
    "sg:address":"7 Newton Court, Jan St",
    "sg:city":"Newton",
    "sg:classifiers":[
        {
            "category":"Health Services",
            "subcategory":"Health Practitioner",
            "type":"Services"
        }
    ],
    "sg:phone":"+61 8 8337 4755",
    "sg:postcode":"5074",
    "sg:province":"SA",
    "sg:tags":[
        "acupuncture"
    ],
    "wof:name":"Kwong Kwok Wai",
    "wof:placetype":"venue"
},
  "geometry": {"coordinates":[138.67347717300001,-34.8776168823],"type":"Point"}
}