{
  "type": "Feature",
  "properties": {
    "addr:full":"14 Maple St Greystanes NSW 2145",
    "addr:housenumber":"14",
    "addr:postcode":"2145",
    "addr:street":"Maple St",
    "iso:country":"AU",
    "sg:address":"14 Maple St",
    "sg:city":"Greystanes",
    "sg:classifiers":[
        {
            "category":"Utilities",
            "subcategory":"Electric",
            "type":"Services"
        }
    ],
    "sg:phone":"+61 2 9896 5818",
    "sg:postcode":"2145",
    "sg:province":"NSW",
    "sg:tags":[
        "electrical",
        "contractor"
    ],
    "wof:name":"Dedicated Communications & Electrical Services Pty Ltd",
    "wof:placetype":"venue"
},
  "geometry": {"coordinates":[150.956375122,-33.8159637451],"type":"Point"}
}