{
  "type": "Feature",
  "properties": {
    "addr:full":"Collections Centre 209 Brisbane St Dubbo NSW 2830",
    "addr:housenumber":"209",
    "addr:postcode":"2830",
    "addr:street":"Brisbane St",
    "iso:country":"AU",
    "sg:address":"Collections Centre 209 Brisbane St",
    "sg:city":"Dubbo",
    "sg:classifiers":[
        {
            "category":"Health Services",
            "subcategory":"Medical Lab",
            "type":"Services"
        }
    ],
    "sg:phone":"+61 2 6885 3180",
    "sg:postcode":"2830",
    "sg:province":"NSW",
    "sg:tags":[
        "laboratory",
        "pathology"
    ],
    "wof:name":"Orana Pathology Service",
    "wof:placetype":"venue"
},
  "geometry": {"coordinates":[148.600067139,-32.248840332],"type":"Point"}
}