{
  "type": "Feature",
  "properties": {
    "addr:full":"303/ 142 Newmarket Rd Windsor QLD 4030",
    "addr:housenumber":"303 / 142",
    "addr:postcode":"4030",
    "addr:street":"Newmarket Rd",
    "iso:country":"AU",
    "sg:address":"303/ 142 Newmarket Rd",
    "sg:city":"Windsor",
    "sg:classifiers":[
        {
            "category":"Shopping",
            "subcategory":"Clothing, Apparel, & Fashions",
            "type":"Retail Goods"
        }
    ],
    "sg:phone":"+61 7 3357 3333",
    "sg:postcode":"4030",
    "sg:province":"QLD",
    "sg:tags":[
        "maternity",
        "wear"
    ],
    "wof:name":"Mamas Home",
    "wof:placetype":"venue"
},
  "geometry": {"coordinates":[153.02397199999999,-27.437218],"type":"Point"}
}