{
  "type": "Feature",
  "properties": {
    "addr:full":"88 Russell St Goondiwindi QLD 4390",
    "addr:housenumber":"88",
    "addr:postcode":"4390",
    "addr:street":"Russell St",
    "iso:country":"AU",
    "sg:address":"88 Russell St",
    "sg:city":"Goondiwindi",
    "sg:classifiers":[
        {
            "category":"Shopping",
            "type":"Retail Goods"
        }
    ],
    "sg:phone":"+61 7 4671 4214",
    "sg:postcode":"4390",
    "sg:province":"QLD",
    "sg:tags":[
        "produce",
        "grain"
    ],
    "wof:name":"Glasson Produce Supplies",
    "wof:placetype":"venue"
},
  "geometry": {"coordinates":[150.30381774899999,-28.544418335],"type":"Point"}
}