{
  "type": "Feature",
  "properties": {
    "iso:country":"AU",
    "sg:address":"203 Myers St",
    "sg:city":"Geelong",
    "sg:classifiers":[
        {
            "category":"Health Services",
            "subcategory":"Health Practitioner",
            "type":"Services"
        }
    ],
    "sg:phone":"+61 3 5222 2611",
    "sg:postcode":"3220",
    "sg:province":"VIC",
    "sg:tags":[
        "alternative"
    ],
    "wof:name":"Naturopath Julie Durlak",
    "wof:placetype":"venue"
},
  "geometry": {"coordinates":[144.367065,-38.153549],"type":"Point"}
}