{
  "type": "Feature",
  "properties": {
    "addr:full":"- Holdfast Shores Marina Glenelg SA 5045",
    "addr:postcode":"5045",
    "iso:country":"AU",
    "sg:address":"- Holdfast Shores Marina",
    "sg:city":"Glenelg",
    "sg:classifiers":[
        {
            "category":"Autos & Motor Vehicles",
            "subcategory":"Boat Sales",
            "type":"Retail Goods"
        }
    ],
    "sg:phone":"+61 8 8295 9000",
    "sg:postcode":"5045",
    "sg:province":"SA",
    "sg:tags":[
        "equipment",
        "yacht"
    ],
    "wof:name":"R Marine Adelaide",
    "wof:placetype":"venue"
},
  "geometry": {"coordinates":[138.510299683,-34.9770736694],"type":"Point"}
}