{
  "type": "Feature",
  "properties": {
    "addr:full":"Suite 4, 871 - 877 Pacific Hwy Chatswood NSW 2067",
    "addr:housenumber":"871 877",
    "addr:postcode":"2067",
    "addr:street":"Pacific Hwy",
    "iso:country":"AU",
    "sg:address":"Suite 4, 871 - 877 Pacific Hwy",
    "sg:city":"Chatswood",
    "sg:classifiers":[
        {
            "category":"Professional",
            "subcategory":"Art Services",
            "type":"Services"
        }
    ],
    "sg:phone":"+61 2 9419 6407",
    "sg:postcode":"2067",
    "sg:province":"NSW",
    "sg:tags":[
        "interior",
        "decorator"
    ],
    "wof:name":"Blue Nexus designs",
    "wof:placetype":"venue"
},
  "geometry": {"coordinates":[151.18028259299999,-33.792224884],"type":"Point"}
}