{
  "type": "Feature",
  "properties": {
    "addr:full":"14 Cross St Pymble NSW 2073",
    "addr:housenumber":"14",
    "addr:postcode":"2073",
    "addr:street":"Cross St",
    "iso:country":"AU",
    "sg:address":"14 Cross St",
    "sg:city":"Pymble",
    "sg:classifiers":[
        {
            "category":"Organizations",
            "subcategory":"Professional Association",
            "type":"Services"
        }
    ],
    "sg:phone":"+61 2 9403 3049",
    "sg:postcode":"2073",
    "sg:province":"NSW",
    "sg:tags":[
        "web",
        "internet"
    ],
    "wof:name":"CreativMauve",
    "wof:placetype":"venue"
},
  "geometry": {"coordinates":[151.138015747,-33.7543830872],"type":"Point"}
}