{
  "type": "Feature",
  "properties": {
    "iso:country":"AU",
    "sg:address":"93 Logan Rd",
    "sg:city":"Woolloongabba",
    "sg:classifiers":[
        {
            "category":"Food & Beverages",
            "subcategory":"Liquor & Beverages",
            "type":"Retail Goods"
        }
    ],
    "sg:phone":"+61 7 3891 7499",
    "sg:postcode":"4102",
    "sg:province":"QLD",
    "sg:tags":[
        "store"
    ],
    "wof:name":"Stewarts Mini Liquor Mart",
    "wof:placetype":"venue"
},
  "geometry": {"coordinates":[153.038970947,-27.4900512695],"type":"Point"}
}