{
  "type": "Feature",
  "properties": {
    "iso:country":"AU",
    "sg:address":"St Vincents Hospital Scott St",
    "sg:city":"Toowoomba",
    "sg:classifiers":[
        {
            "category":"Health Services",
            "subcategory":"Health Practitioner",
            "type":"Services"
        }
    ],
    "sg:phone":"+61 7 4632 8344",
    "sg:postcode":"4350",
    "sg:province":"QLD",
    "sg:tags":[
        "pathologist",
        "speech"
    ],
    "wof:name":"Hadgraft Speech Pathology",
    "wof:placetype":"venue"
},
  "geometry": {"coordinates":[151.869232,-27.603662],"type":"Point"}
}