{
  "type": "Feature",
  "properties": {
    "addr:full":"130 Male St Brighton VIC 3186",
    "addr:housenumber":"130",
    "addr:postcode":"3186",
    "addr:street":"Male St",
    "iso:country":"AU",
    "sg:address":"130 Male St",
    "sg:city":"Brighton",
    "sg:classifiers":[
        {
            "category":"Health Services",
            "subcategory":"Dentist",
            "type":"Services"
        }
    ],
    "sg:phone":"+61 3 9592 3827",
    "sg:postcode":"3186",
    "sg:province":"VIC",
    "sg:tags":[
        "dental",
        "prosthetist"
    ],
    "wof:name":"Ray Costello",
    "wof:placetype":"venue"
},
  "geometry": {"coordinates":[145.005615234,-37.906829834],"type":"Point"}
}