{
  "type": "Feature",
  "properties": {
    "addr:full":"Mitchell St Camden NSW 2570",
    "addr:postcode":"2570",
    "addr:street":"Mitchell St",
    "iso:country":"AU",
    "sg:address":"Mitchell St",
    "sg:city":"Camden",
    "sg:classifiers":[
        {
            "category":"Social Services",
            "subcategory":"Child Care",
            "type":"Services"
        }
    ],
    "sg:phone":"+61 2 4655 6460",
    "sg:postcode":"2570",
    "sg:province":"NSW",
    "sg:tags":[
        "support",
        "health"
    ],
    "wof:name":"Early Childhood Centres",
    "wof:placetype":"venue"
},
  "geometry": {"coordinates":[150.694091797,-34.0529289246],"type":"Point"}
}