{
  "type": "Feature",
  "properties": {
    "addr:full":"13 Crompton Rd Rockingham WA 6168",
    "addr:housenumber":"13",
    "addr:postcode":"6168",
    "addr:street":"Crompton Rd",
    "iso:country":"AU",
    "sg:address":"13 Crompton Rd",
    "sg:city":"Rockingham",
    "sg:classifiers":[
        {
            "category":"Manufacturing",
            "subcategory":"Motor Vehicles & Parts",
            "type":"Manufacturing & Wholesale Goods"
        }
    ],
    "sg:phone":"+61 8 9592 8488",
    "sg:postcode":"6168",
    "sg:province":"WA",
    "sg:tags":[
        "replacement"
    ],
    "wof:name":"Coventrys",
    "wof:placetype":"venue"
},
  "geometry": {"coordinates":[115.767356873,-32.2748374939],"type":"Point"}
}