{
  "type": "Feature",
  "properties": {
    "addr:full":"687 Anzac Pde Maroubra NSW 2035",
    "addr:housenumber":"687",
    "addr:postcode":"2035",
    "addr:street":"Anzac Pde",
    "iso:country":"AU",
    "sg:address":"687 Anzac Pde",
    "sg:city":"Maroubra",
    "sg:classifiers":[
        {
            "category":"Personal",
            "subcategory":"Beauty Salon",
            "type":"Services"
        }
    ],
    "sg:phone":"+61 2 9344 6322",
    "sg:postcode":"2035",
    "sg:province":"NSW",
    "sg:tags":[
        "hairdresser"
    ],
    "wof:name":"Barbara's Hair Style",
    "wof:placetype":"venue"
},
  "geometry": {"coordinates":[151.23832702600001,-33.9388961792],"type":"Point"}
}