{
  "type": "Feature",
  "properties": {
    "addr:full":"9 Wongan Rd Wongan Hills WA 6603",
    "addr:housenumber":"9",
    "addr:postcode":"6603",
    "addr:street":"Wongan Rd",
    "iso:country":"AU",
    "sg:address":"9 Wongan Rd",
    "sg:city":"Wongan Hills",
    "sg:classifiers":[
        {
            "category":"Autos & Motor Vehicles",
            "subcategory":"Auto Supplies",
            "type":"Retail Goods"
        }
    ],
    "sg:phone":"+61 8 9671 1644",
    "sg:postcode":"6603",
    "sg:province":"WA",
    "sg:tags":[
        "tyre"
    ],
    "wof:name":"Bridgestone Australia Ltd",
    "wof:placetype":"venue"
},
  "geometry": {"coordinates":[116.717948914,-30.8945770264],"type":"Point"}
}