{
  "type": "Feature",
  "properties": {
    "addr:full":"Suite 208/149 Castlereagh Sydney NSW 2000",
    "addr:housenumber":"/ 149",
    "addr:postcode":"2000",
    "iso:country":"AU",
    "sg:address":"Suite 208/149 Castlereagh",
    "sg:city":"Sydney",
    "sg:classifiers":[
        {
            "category":"Shopping",
            "subcategory":"Jewelry",
            "type":"Retail Goods"
        }
    ],
    "sg:phone":"+61 2 9264 9498",
    "sg:postcode":"2000",
    "sg:province":"NSW",
    "sg:tags":[
        "merchant",
        "gem"
    ],
    "wof:name":"Monte Cristo Gems Pty Ltd",
    "wof:placetype":"venue"
},
  "geometry": {"coordinates":[151.209182739,-33.8718948364],"type":"Point"}
}