{
  "type": "Feature",
  "properties": {
    "addr:full":"\"Raylynn\" 65 Old Fernvale Rd Fernvale QLD 4306",
    "addr:housenumber":"65",
    "addr:postcode":"4306",
    "addr:street":"Old Fernvale Rd",
    "iso:country":"AU",
    "sg:address":"\"Raylynn\" 65 Old Fernvale Rd",
    "sg:city":"Fernvale",
    "sg:classifiers":[
        {
            "category":"Farming",
            "subcategory":"Nursery",
            "type":"Manufacturing & Wholesale Goods"
        }
    ],
    "sg:phone":"+61 7 5426 7293",
    "sg:postcode":"4306",
    "sg:province":"QLD",
    "wof:name":"C.L.M. Nursery",
    "wof:placetype":"venue"
},
  "geometry": {"coordinates":[152.632522583,-27.4506797791],"type":"Point"}
}