{
  "type": "Feature",
  "properties": {
    "addr:full":"89 Karinie St Swan Hill VIC 3585",
    "addr:housenumber":"89",
    "addr:postcode":"3585",
    "addr:street":"Karinie St",
    "iso:country":"AU",
    "sg:address":"89 Karinie St",
    "sg:city":"Swan Hill",
    "sg:classifiers":[
        {
            "category":"Manufacturing",
            "subcategory":"Paper Products",
            "type":"Manufacturing & Wholesale Goods"
        }
    ],
    "sg:phone":"+61 3 5032 3794",
    "sg:postcode":"3585",
    "sg:province":"VIC",
    "sg:tags":[
        "box",
        "fibre",
        "carton",
        "cardboard"
    ],
    "wof:name":"Visy Board",
    "wof:placetype":"venue"
},
  "geometry": {"coordinates":[143.55212399999999,-35.327301],"type":"Point"}
}