{
  "type": "Feature",
  "properties": {
    "iso:country":"AU",
    "sg:address":"Cnr Goodwood Rd & Little St",
    "sg:city":"Cumberland Park",
    "sg:classifiers":[
        {
            "category":"Shopping",
            "subcategory":"Clothing, Apparel, & Fashions",
            "type":"Retail Goods"
        }
    ],
    "sg:phone":"+61 8 8373 1776",
    "sg:postcode":"5041",
    "sg:province":"SA",
    "sg:tags":[
        "uniform"
    ],
    "wof:name":"Class School Wear Pty Ltd",
    "wof:placetype":"venue"
},
  "geometry": {"coordinates":[138.591248,-34.972218],"type":"Point"}
}