{
  "type": "Feature",
  "properties": {
    "addr:full":"20 Arizona Rd Charmhaven NSW 2263",
    "addr:housenumber":"20",
    "addr:postcode":"2263",
    "addr:street":"Arizona Rd",
    "iso:country":"AU",
    "sg:address":"20 Arizona Rd",
    "sg:city":"Charmhaven",
    "sg:classifiers":[
        {
            "category":"Manufacturing",
            "subcategory":"Motor Vehicles & Parts",
            "type":"Manufacturing & Wholesale Goods"
        }
    ],
    "sg:phone":"+61 2 4392 2333",
    "sg:postcode":"2263",
    "sg:province":"NSW",
    "sg:tags":[
        "replacement"
    ],
    "wof:name":"Burson Automotive Pty Ltd",
    "wof:placetype":"venue"
},
  "geometry": {"coordinates":[151.49316400000001,-33.241222],"type":"Point"}
}