{
  "type": "Feature",
  "properties": {
    "addr:full":"430 Rathdowne St Carlton North VIC 3054",
    "addr:housenumber":"430",
    "addr:postcode":"3054",
    "addr:street":"Rathdowne St",
    "iso:country":"AU",
    "sg:address":"430 Rathdowne St",
    "sg:city":"Carlton North",
    "sg:classifiers":[
        {
            "category":"Shopping",
            "subcategory":"Baby Store",
            "type":"Retail Goods"
        }
    ],
    "sg:phone":"+61 3 9347 7007",
    "sg:postcode":"3054",
    "sg:province":"VIC",
    "sg:tags":[
        "wear"
    ],
    "wof:name":"A Thousand & One Things For Baby",
    "wof:placetype":"venue"
},
  "geometry": {"coordinates":[144.972488403,-37.7872886658],"type":"Point"}
}