{
  "type": "Feature",
  "properties": {
    "addr:full":"388 Hawksbury Rd Moggill QLD 4070",
    "addr:housenumber":"388",
    "addr:postcode":"4070",
    "addr:street":"Hawksbury Rd",
    "iso:country":"AU",
    "sg:address":"388 Hawksbury Rd",
    "sg:city":"Moggill",
    "sg:classifiers":[
        {
            "category":"Professional",
            "subcategory":"Detective & Security Services",
            "type":"Services"
        }
    ],
    "sg:phone":"+61 7 3202 9619",
    "sg:postcode":"4070",
    "sg:province":"QLD",
    "sg:tags":[
        "distributor",
        "aircraft",
        "mfrs"
    ],
    "wof:name":"Supermarine AirCraft",
    "wof:placetype":"venue"
},
  "geometry": {"coordinates":[152.85789489699999,-27.5562667847],"type":"Point"}
}