{
  "type": "Feature",
  "properties": {
    "iso:country":"AU",
    "sg:address":"Suite 7, Level 1, Childrens Hospital Medical Centre Hainsworth St",
    "sg:city":"Westmead",
    "sg:classifiers":[
        {
            "category":"Health Services",
            "subcategory":"Doctor",
            "type":"Services"
        }
    ],
    "sg:phone":"+61 2 9845 0745",
    "sg:postcode":"2145",
    "sg:province":"NSW",
    "sg:tags":[
        "medical",
        "practitioner"
    ],
    "wof:name":"Magoffin Annabel K. Dr",
    "wof:placetype":"venue"
},
  "geometry": {"coordinates":[150.99269104000001,-33.8024177551],"type":"Point"}
}