{
  "type": "Feature",
  "properties": {
    "addr:full":"68 Barnes St Tamworth NSW 2340",
    "addr:housenumber":"68",
    "addr:postcode":"2340",
    "addr:street":"Barnes St",
    "iso:country":"AU",
    "sg:address":"68 Barnes St",
    "sg:city":"Tamworth",
    "sg:classifiers":[
        {
            "category":"Real Estate",
            "subcategory":"Real Estate Agent",
            "type":"Services"
        }
    ],
    "sg:phone":"+61 2 6765 4977",
    "sg:postcode":"2340",
    "sg:province":"NSW",
    "sg:tags":[
        "handyman's",
        "equipment",
        "hire",
        "builders",
        "contractor"
    ],
    "wof:name":"Wreckair",
    "wof:placetype":"venue"
},
  "geometry": {"coordinates":[150.911499023,-31.0921363831],"type":"Point"}
}