{
  "type": "Feature",
  "properties": {
    "iso:country":"AU",
    "sg:address":"7 /46 Kembla St",
    "sg:city":"Wollongong",
    "sg:classifiers":[
        {
            "category":"Professional",
            "subcategory":"Engineering",
            "type":"Services"
        }
    ],
    "sg:phone":"+61 2 4229 3180",
    "sg:postcode":"2500",
    "sg:province":"NSW",
    "sg:tags":[
        "consulting",
        "engineer"
    ],
    "wof:name":"Wollongong Engineering Design & Survey Services Pty Ltd",
    "wof:placetype":"venue"
},
  "geometry": {"coordinates":[150.898407,-34.420033],"type":"Point"}
}