{
  "type": "Feature",
  "properties": {
    "iso:country":"AU",
    "sg:address":"1059 Gympie Rd",
    "sg:city":"Petrie",
    "sg:classifiers":[
        {
            "category":"Autos & Motor Vehicles",
            "subcategory":"Automobile Sales",
            "type":"Retail Goods"
        }
    ],
    "sg:phone":"+61 7 3285 0600",
    "sg:postcode":"4502",
    "sg:province":"QLD",
    "sg:tags":[
        "car",
        "used"
    ],
    "wof:name":"Village Motors",
    "wof:placetype":"venue"
},
  "geometry": {"coordinates":[152.98883056599999,-27.3023529053],"type":"Point"}
}