{
  "type": "Feature",
  "properties": {
    "addr:full":"Eve St Sandgate QLD 4017",
    "addr:postcode":"4017",
    "addr:street":"Eve St",
    "iso:country":"AU",
    "sg:address":"Eve St",
    "sg:city":"Sandgate",
    "sg:classifiers":[
        {
            "category":"Wholesale",
            "subcategory":"Metals & Minerals",
            "type":"Manufacturing & Wholesale Goods"
        }
    ],
    "sg:phone":"+61 7 3269 4426",
    "sg:postcode":"4017",
    "sg:province":"QLD",
    "sg:tags":[
        "steel",
        "merchant"
    ],
    "wof:name":"R & R Metals",
    "wof:placetype":"venue"
},
  "geometry": {"coordinates":[153.071075439,-27.322101593],"type":"Point"}
}