{
  "type": "Feature",
  "properties": {
    "addr:full":"27 Read St Bronte NSW 2024",
    "addr:housenumber":"27",
    "addr:postcode":"2024",
    "addr:street":"Read St",
    "iso:country":"AU",
    "sg:address":"27 Read St",
    "sg:city":"Bronte",
    "sg:classifiers":[
        {
            "category":"Education",
            "subcategory":"Special Training",
            "type":"Public Place"
        }
    ],
    "sg:phone":"+61 2 9387 6609",
    "sg:postcode":"2024",
    "sg:province":"NSW",
    "sg:tags":[
        "tuition-educational"
    ],
    "wof:name":"WiederChem",
    "wof:placetype":"venue"
},
  "geometry": {"coordinates":[151.26258850100001,-33.8996009827],"type":"Point"}
}