{
  "type": "Feature",
  "properties": {
    "addr:full":"5 Greenlinks Ave Coffs Harbour NSW 2450",
    "addr:housenumber":"5",
    "addr:postcode":"2450",
    "addr:street":"Greenlinks Ave",
    "iso:country":"AU",
    "sg:address":"5 Greenlinks Ave",
    "sg:city":"Coffs Harbour",
    "sg:classifiers":[
        {
            "category":"Building & Trades",
            "subcategory":"Construction",
            "type":"Services"
        }
    ],
    "sg:phone":"+61 2 6651 2612",
    "sg:postcode":"2450",
    "sg:province":"NSW",
    "sg:tags":[
        "contractor"
    ],
    "wof:name":"Advanced Commercial Constructions",
    "wof:placetype":"venue"
},
  "geometry": {"coordinates":[153.111862,-30.305449],"type":"Point"}
}