{
  "type": "Feature",
  "properties": {
    "iso:country":"AU",
    "sg:address":"Suite 3, 2 Small St",
    "sg:city":"Hampton",
    "sg:classifiers":[
        {
            "category":"Real Estate",
            "subcategory":"Architect",
            "type":"Services"
        }
    ],
    "sg:phone":"+61 3 9598 9750",
    "sg:postcode":"3188",
    "sg:province":"VIC",
    "wof:name":"Roberta Rees & Associates Pty Ltd",
    "wof:placetype":"venue"
},
  "geometry": {"coordinates":[145.00064086899999,-37.9394378662],"type":"Point"}
}