{
  "type": "Feature",
  "properties": {
    "iso:country":"AU",
    "sg:address":"Rear 382 Pakington St",
    "sg:city":"Newtown",
    "sg:classifiers":[
        {
            "category":"Utilities",
            "type":"Services"
        }
    ],
    "sg:phone":"+61 3 5221 2500",
    "sg:postcode":"3351",
    "sg:province":"VIC",
    "sg:tags":[
        "refrigeration",
        "industrial",
        "commercial",
        "retail"
    ],
    "wof:name":"Robertson's Refrigeration Pty Ltd",
    "wof:placetype":"venue"
},
  "geometry": {"coordinates":[143.66409300000001,-37.706371],"type":"Point"}
}