{
  "type": "Feature",
  "properties": {
    "iso:country":"AU",
    "sg:address":"19 Glynburn Rd",
    "sg:city":"Glynde",
    "sg:classifiers":[
        {
            "category":"Banks & Credit Unions",
            "subcategory":"Financial Services",
            "type":"Services"
        }
    ],
    "sg:phone":"+61 8 8365 1022",
    "sg:postcode":"5070",
    "sg:province":"SA",
    "sg:tags":[
        "planning"
    ],
    "wof:name":"Asset Protection Services",
    "wof:placetype":"venue"
},
  "geometry": {"coordinates":[138.656524658,-34.8918952942],"type":"Point"}
}