{
  "type": "Feature",
  "properties": {
    "iso:country":"AU",
    "sg:address":"126 Whatley Crs",
    "sg:city":"Maylands",
    "sg:classifiers":[
        {
            "category":"Professional",
            "subcategory":"Computer Services",
            "type":"Services"
        }
    ],
    "sg:phone":"+61 8 9371 0656",
    "sg:postcode":"6051",
    "sg:province":"WA",
    "sg:tags":[
        "repairs",
        "upgrade",
        "equipment"
    ],
    "wof:name":"DIG- IT Computer Services",
    "wof:placetype":"venue"
},
  "geometry": {"coordinates":[115.900459,-31.935789],"type":"Point"}
}