{
  "type": "Feature",
  "properties": {
    "addr:full":"33- 47 Dohertys Rd Laverton North VIC 3026",
    "addr:housenumber":"47",
    "addr:postcode":"3026",
    "addr:street":"Dohertys Rd",
    "iso:country":"AU",
    "sg:address":"33- 47 Dohertys Rd",
    "sg:city":"Laverton North",
    "sg:classifiers":[
        {
            "category":"Freight",
            "type":"Transportation"
        }
    ],
    "sg:phone":"+61 3 9369 0777",
    "sg:postcode":"3026",
    "sg:province":"VIC",
    "sg:tags":[
        "car",
        "carrier",
        "transporting"
    ],
    "wof:name":"AUTOTRANS Express (Aust) Pty Ltd",
    "wof:placetype":"venue"
},
  "geometry": {"coordinates":[144.80633499999999,-37.829819],"type":"Point"}
}