{
  "type": "Feature",
  "properties": {
    "iso:country":"AU",
    "sg:address":"31 Warren Ave",
    "sg:city":"Bankstown",
    "sg:classifiers":[
        {
            "category":"Professional",
            "type":"Services"
        }
    ],
    "sg:phone":"+61 1300 888 458",
    "sg:postcode":"2200",
    "sg:province":"NSW",
    "sg:tags":[
        "control",
        "equipment",
        "traffic"
    ],
    "wof:name":"HVS Services Pty Ltd",
    "wof:placetype":"venue"
},
  "geometry": {"coordinates":[151.036346,-33.932655],"type":"Point"}
}