{
  "type": "Feature",
  "properties": {
    "iso:country":"AU",
    "sg:address":"Carillon City, Hay St",
    "sg:city":"Level Perth",
    "sg:classifiers":[
        {
            "category":"Personal",
            "subcategory":"Beauty Salon",
            "type":"Services"
        }
    ],
    "sg:phone":"+61 8 9321 0121",
    "sg:postcode":"6000",
    "sg:province":"WA",
    "wof:name":"Ella Bach? Perth",
    "wof:placetype":"venue"
},
  "geometry": {"coordinates":[115.853813171,-31.9525032043],"type":"Point"}
}