{
  "type": "Feature",
  "properties": {
    "addr:full":"Shp4/ 37 Main St Balhannah SA 5242",
    "addr:housenumber":"37",
    "addr:postcode":"5242",
    "addr:street":"Main St",
    "iso:country":"AU",
    "sg:address":"Shp4/ 37 Main St",
    "sg:city":"Balhannah",
    "sg:classifiers":[
        {
            "category":"Government",
            "subcategory":"Post Office",
            "type":"Public Place"
        }
    ],
    "sg:phone":"+61 8 8398 2004",
    "sg:postcode":"5242",
    "sg:province":"SA",
    "sg:tags":[
        "house",
        "doll"
    ],
    "wof:name":"Dollshouse Shop",
    "wof:placetype":"venue"
},
  "geometry": {"coordinates":[138.82699585,-34.9902992249],"type":"Point"}
}