{
  "type": "Feature",
  "properties": {
    "addr:full":"99 Drummond St Dennington VIC 3280",
    "addr:housenumber":"99",
    "addr:postcode":"3280",
    "addr:street":"Drummond St",
    "iso:country":"AU",
    "sg:address":"99 Drummond St",
    "sg:city":"Dennington",
    "sg:classifiers":[
        {
            "category":"Building & Trades",
            "subcategory":"Construction",
            "type":"Services"
        }
    ],
    "sg:phone":"+61 3 5562 2416",
    "sg:postcode":"3280",
    "sg:province":"VIC",
    "sg:tags":[
        "ceiling"
    ],
    "wof:name":"Warrnambool Plaster",
    "wof:placetype":"venue"
},
  "geometry": {"coordinates":[142.44219970699999,-38.3561286926],"type":"Point"}
}