{
  "type": "Feature",
  "properties": {
    "addr:full":"2 Dane Crt Dandenong VIC 3175",
    "addr:housenumber":"2",
    "addr:postcode":"3175",
    "addr:street":"Dane Crt",
    "iso:country":"AU",
    "sg:address":"2 Dane Crt",
    "sg:city":"Dandenong",
    "sg:classifiers":[
        {
            "category":"Building & Trades",
            "subcategory":"Landscaping Services",
            "type":"Services"
        }
    ],
    "sg:phone":"+61 407 836 809",
    "sg:postcode":"3175",
    "sg:province":"VIC",
    "sg:tags":[
        "designer",
        "landscape",
        "contractor"
    ],
    "wof:name":"Leisure Scape Gardens",
    "wof:placetype":"venue"
},
  "geometry": {"coordinates":[145.219192505,-37.9656028748],"type":"Point"}
}