{
  "type": "Feature",
  "properties": {
    "iso:country":"AU",
    "sg:address":"23 Karinya Drv",
    "sg:city":"Myers Flat",
    "sg:classifiers":[
        {
            "category":"Building & Trades",
            "subcategory":"Plumbing",
            "type":"Services"
        }
    ],
    "sg:phone":"+61 3 5446 7035",
    "sg:postcode":"3556",
    "sg:province":"VIC",
    "sg:tags":[
        "plumber",
        "gasfitters"
    ],
    "wof:name":"Haughton R & S",
    "wof:placetype":"venue"
},
  "geometry": {"coordinates":[144.20726013199999,-36.7082366943],"type":"Point"}
}