{
  "type": "Feature",
  "properties": {
    "addr:full":"Maroondah Hwy Maindample VIC 3723",
    "addr:postcode":"3723",
    "addr:street":"Maroondah Hwy",
    "iso:country":"AU",
    "sg:address":"Maroondah Hwy",
    "sg:city":"Maindample",
    "sg:classifiers":[
        {
            "category":"Travel",
            "subcategory":"Hotels & Motels",
            "type":"Entertainment"
        }
    ],
    "sg:phone":"+61 3 5778 7281",
    "sg:postcode":"3723",
    "sg:province":"VIC",
    "sg:tags":[
        "accommodation"
    ],
    "wof:name":"Bridge Inn Hotel-Motel",
    "wof:placetype":"venue"
},
  "geometry": {"coordinates":[145.940673828,-37.0287132263],"type":"Point"}
}