{
  "type": "Feature",
  "properties": {
    "iso:country":"AU",
    "sg:address":"1st Floor 116 High St",
    "sg:city":"East Maitland",
    "sg:classifiers":[
        {
            "category":"Shopping",
            "subcategory":"Mobile Phones",
            "type":"Retail Goods"
        }
    ],
    "sg:phone":"+61 2 4969 5099",
    "sg:postcode":"2323",
    "sg:province":"NSW",
    "sg:tags":[
        "wholesaler",
        "mfrs",
        "electrical",
        "switchboard"
    ],
    "wof:name":"Newcastle Electrical Services",
    "wof:placetype":"venue"
},
  "geometry": {"coordinates":[151.58778381400001,-32.7525978088],"type":"Point"}
}