{
  "type": "Feature",
  "properties": {
    "addr:full":"43 Audrey Ave Blair Athol SA 5084",
    "addr:housenumber":"43",
    "addr:postcode":"5084",
    "addr:street":"Audrey Ave",
    "iso:country":"AU",
    "sg:address":"43 Audrey Ave",
    "sg:city":"Blair Athol",
    "sg:classifiers":[
        {
            "category":"Shopping",
            "subcategory":"Bicycles & Sporting Goods",
            "type":"Retail Goods"
        }
    ],
    "sg:phone":"+61 8 8349 5667",
    "sg:postcode":"5084",
    "sg:province":"SA",
    "sg:tags":[
        "water",
        "equipment",
        "skiing"
    ],
    "sg:website":"http://www.twister.com.au",
    "wof:name":"Twister Ski Shop",
    "wof:placetype":"venue"
},
  "geometry": {"coordinates":[138.600265503,-34.8619384766],"type":"Point"}
}