{
  "type": "Feature",
  "properties": {
    "addr:full":"Unit 4, 156 Bestic St Brighton-le-Sands NSW 2216",
    "addr:housenumber":"156",
    "addr:postcode":"2216",
    "addr:street":"Bestic St",
    "iso:country":"AU",
    "sg:address":"Unit 4, 156 Bestic St",
    "sg:city":"Brighton-le-Sands",
    "sg:classifiers":[
        {
            "category":"Building & Trades",
            "subcategory":"Construction",
            "type":"Services"
        }
    ],
    "sg:phone":"+61 403 246 560",
    "sg:postcode":"2216",
    "sg:province":"NSW",
    "sg:tags":[
        "rendering",
        "cement"
    ],
    "wof:name":"Big Brother Constructions",
    "wof:placetype":"venue"
},
  "geometry": {"coordinates":[151.159775,-33.95126],"type":"Point"}
}