{
  "type": "Feature",
  "properties": {
    "iso:country":"AU",
    "sg:address":"219 Russell St",
    "sg:city":"Bathurst",
    "sg:classifiers":[
        {
            "category":"Insurance",
            "subcategory":"Hazard Insurance",
            "type":"Services"
        }
    ],
    "sg:phone":"+61 2 6331 4666",
    "sg:postcode":"2795",
    "sg:province":"NSW",
    "sg:tags":[
        "fire",
        "accident",
        "marine"
    ],
    "wof:name":"GIO General Ltd",
    "wof:placetype":"venue"
},
  "geometry": {"coordinates":[149.57800293,-33.4168014526],"type":"Point"}
}