{
  "type": "Feature",
  "properties": {
    "iso:country":"AU",
    "sg:address":"Shop 2, 58 Reserve Drv",
    "sg:city":"Mandurah",
    "sg:classifiers":[
        {
            "category":"Home & Garden",
            "subcategory":"Furniture",
            "type":"Retail Goods"
        }
    ],
    "sg:phone":"+61 8 9581 8077",
    "sg:postcode":"6210",
    "sg:province":"WA",
    "sg:tags":[
        "outdoor"
    ],
    "wof:name":"Urban Fringe",
    "wof:placetype":"venue"
},
  "geometry": {"coordinates":[115.741508,-32.512741],"type":"Point"}
}