{
  "type": "Feature",
  "properties": {
    "addr:full":"Maroubra Pacific Square Lvl 1/ 707 -725 Anzac Parade Maroubra NSW 2035",
    "addr:housenumber":"/ 707 -725",
    "addr:postcode":"2035",
    "addr:street":"Anzac Parade",
    "iso:country":"AU",
    "sg:address":"Maroubra Pacific Square Lvl 1/ 707",
    "sg:city":"-725 Anzac Parade Maroubra",
    "sg:classifiers":[
        {
            "category":"Health Services",
            "subcategory":"Doctor",
            "type":"Services"
        }
    ],
    "sg:phone":"+61 2 9314 3400",
    "sg:postcode":"2035",
    "sg:province":"NSW",
    "sg:tags":[
        "medical",
        "practitioner"
    ],
    "wof:name":"Gonzaga Valerie Dr",
    "wof:placetype":"venue"
},
  "geometry": {"coordinates":[151.23869323700001,-33.9403038025],"type":"Point"}
}