{
  "type": "Feature",
  "properties": {
    "iso:country":"AU",
    "sg:address":"Unit 3, 68 Sheppard St",
    "sg:city":"Hume",
    "sg:classifiers":[
        {
            "category":"Transit Center",
            "subcategory":"Freight",
            "type":"Transportation"
        }
    ],
    "sg:phone":"+61 2 6260 1787",
    "sg:postcode":"2620",
    "sg:province":"ACT",
    "sg:tags":[
        "forklift",
        "truck"
    ],
    "wof:name":"Crown Equipment",
    "wof:placetype":"venue"
},
  "geometry": {"coordinates":[149.082397461,-35.3620109558],"type":"Point"}
}