{
  "type": "Feature",
  "properties": {
    "iso:country":"AU",
    "sg:address":"59 Whiting St",
    "sg:city":"Artarmon",
    "sg:classifiers":[
        {
            "category":"Autos & Motor Vehicles",
            "subcategory":"Auto Supplies",
            "type":"Retail Goods"
        }
    ],
    "sg:phone":"+61 2 9966 9000",
    "sg:postcode":"2064",
    "sg:province":"NSW",
    "sg:tags":[
        "accessory"
    ],
    "wof:name":"Sunroof Professionals",
    "wof:placetype":"venue"
},
  "geometry": {"coordinates":[151.18182373100001,-33.8157730103],"type":"Point"}
}