{
  "type": "Feature",
  "properties": {
    "addr:full":"7 Hannora Crs Croydon VIC 3136",
    "addr:housenumber":"7",
    "addr:postcode":"3136",
    "addr:street":"Hannora Crs",
    "iso:country":"AU",
    "sg:address":"7 Hannora Crs",
    "sg:city":"Croydon",
    "sg:classifiers":[
        {
            "category":"Utilities",
            "type":"Services"
        }
    ],
    "sg:phone":"+61 415 356 496",
    "sg:postcode":"3136",
    "sg:province":"VIC",
    "sg:tags":[
        "refrigeration",
        "industrial",
        "commercial",
        "retail"
    ],
    "wof:name":"S & C Refrigeration Pty Ltd",
    "wof:placetype":"venue"
},
  "geometry": {"coordinates":[145.279754639,-37.7989196777],"type":"Point"}
}