{
  "type": "Feature",
  "properties": {
    "addr:full":"7 Hogue St Maryville NSW 2293",
    "addr:housenumber":"7",
    "addr:postcode":"2293",
    "addr:street":"Hogue St",
    "iso:country":"AU",
    "sg:address":"7 Hogue St",
    "sg:city":"Maryville",
    "sg:classifiers":[
        {
            "category":"Building & Trades",
            "subcategory":"Cleaning & Sanitation",
            "type":"Services"
        }
    ],
    "sg:phone":"+61 2 4969 5422",
    "sg:postcode":"2293",
    "sg:province":"NSW",
    "sg:tags":[
        "commercial",
        "maintenance"
    ],
    "wof:name":"J & K Shaw Pty Ltd",
    "wof:placetype":"venue"
},
  "geometry": {"coordinates":[151.75680542000001,-32.9117698669],"type":"Point"}
}