{
  "type": "Feature",
  "properties": {
    "addr:full":"55 Howe St Osborne Park WA 6017",
    "addr:housenumber":"55",
    "addr:postcode":"6017",
    "addr:street":"Howe St",
    "iso:country":"AU",
    "sg:address":"55 Howe St",
    "sg:city":"Osborne Park",
    "sg:classifiers":[
        {
            "category":"Professional",
            "subcategory":"Printing & Photocopies",
            "type":"Services"
        }
    ],
    "sg:phone":"+61 8 9201 0300",
    "sg:postcode":"6017",
    "sg:province":"WA",
    "sg:tags":[
        "photocopier"
    ],
    "wof:name":"West Coast Office Equipment",
    "wof:placetype":"venue"
},
  "geometry": {"coordinates":[115.814018249,-31.9069728851],"type":"Point"}
}