{
  "type": "Feature",
  "properties": {
    "addr:full":"122a Narrabeen Park Pde Warriewood NSW 2102",
    "addr:housenumber":"122a",
    "addr:postcode":"2102",
    "addr:street":"Narrabeen Park Pde",
    "iso:country":"AU",
    "sg:address":"122a Narrabeen Park Pde",
    "sg:city":"Warriewood",
    "sg:classifiers":[
        {
            "category":"Professional",
            "subcategory":"Management & Consulting",
            "type":"Services"
        }
    ],
    "sg:phone":"+61 2 9997 1600",
    "sg:postcode":"2102",
    "sg:province":"NSW",
    "sg:tags":[
        "consultant"
    ],
    "wof:name":"The Surfers Group Pty Ltd",
    "wof:placetype":"venue"
},
  "geometry": {"coordinates":[151.30718999999999,-33.691574],"type":"Point"}
}