{
  "type": "Feature",
  "properties": {
    "addr:full":"156 Norman Ave Norman Park QLD 4170",
    "addr:housenumber":"156",
    "addr:postcode":"4170",
    "addr:street":"Norman Ave",
    "iso:country":"AU",
    "sg:address":"156 Norman Ave",
    "sg:city":"Norman Park",
    "sg:classifiers":[
        {
            "category":"Government",
            "subcategory":"City Hall",
            "type":"Public Place"
        }
    ],
    "sg:phone":"+61 7 3395 5167",
    "sg:postcode":"4170",
    "sg:province":"QLD",
    "wof:name":"A.M.O.R.C. Hall",
    "wof:placetype":"venue"
},
  "geometry": {"coordinates":[153.060180664,-27.4801864624],"type":"Point"}
}