{
  "type": "Feature",
  "properties": {
    "iso:country":"AU",
    "sg:address":"32 Davison St",
    "sg:city":"Maddington",
    "sg:classifiers":[
        {
            "category":"Home & Garden",
            "subcategory":"Building Materials",
            "type":"Retail Goods"
        }
    ],
    "sg:phone":"+61 8 9492 1018",
    "sg:postcode":"6109",
    "sg:province":"WA",
    "sg:tags":[
        "pre-mixed",
        "concrete"
    ],
    "wof:name":"Concrete & Crushing Australia",
    "wof:placetype":"venue"
},
  "geometry": {"coordinates":[115.988830566,-32.0445594788],"type":"Point"}
}