{
  "type": "Feature",
  "properties": {
    "addr:full":"Suite 3/ 168 Main St Osborne Park WA 6017",
    "addr:housenumber":"/ 168",
    "addr:postcode":"6017",
    "addr:street":"Main St",
    "iso:country":"AU",
    "sg:address":"Suite 3/ 168 Main St",
    "sg:city":"Osborne Park",
    "sg:classifiers":[
        {
            "category":"Health Services",
            "subcategory":"Dentist",
            "type":"Services"
        }
    ],
    "sg:phone":"+61 8 9345 4533",
    "sg:postcode":"6017",
    "sg:province":"WA",
    "wof:name":"Dr Vinzi Carbone",
    "wof:placetype":"venue"
},
  "geometry": {"coordinates":[115.828422546,-31.8998394012],"type":"Point"}
}