{
  "type": "Feature",
  "properties": {
    "addr:full":"174 Hampden Rd Nedlands WA 6009",
    "addr:housenumber":"174",
    "addr:postcode":"6009",
    "addr:street":"Hampden Rd",
    "iso:country":"AU",
    "sg:address":"174 Hampden Rd",
    "sg:city":"Nedlands",
    "sg:classifiers":[
        {
            "category":"Professional",
            "subcategory":"Employment Agencies",
            "type":"Services"
        }
    ],
    "sg:phone":"+61 1300 304 899",
    "sg:postcode":"6009",
    "sg:province":"WA",
    "sg:tags":[
        "provider",
        "internet"
    ],
    "wof:name":"Starwon Technologies",
    "wof:placetype":"venue"
},
  "geometry": {"coordinates":[115.813622,-31.972872],"type":"Point"}
}