{
  "type": "Feature",
  "properties": {
    "addr:full":"7 Bancell St Campbellfield VIC 3061",
    "addr:housenumber":"7",
    "addr:postcode":"3061",
    "addr:street":"Bancell St",
    "iso:country":"AU",
    "sg:address":"7 Bancell St",
    "sg:city":"Campbellfield",
    "sg:classifiers":[
        {
            "category":"Shopping",
            "subcategory":"Gifts & Souvenirs",
            "type":"Retail Goods"
        }
    ],
    "sg:phone":"+61 3 9357 3287",
    "sg:postcode":"3061",
    "sg:province":"VIC",
    "sg:tags":[
        "shop",
        "supply"
    ],
    "wof:name":"Nacsap Trading Pty Ltd",
    "wof:placetype":"venue"
},
  "geometry": {"coordinates":[144.963821411,-37.6835823059],"type":"Point"}
}