{
  "type": "Feature",
  "properties": {
    "iso:country":"AU",
    "sg:address":"Graham St",
    "sg:city":"Kondinin",
    "sg:classifiers":[
        {
            "category":"Travel",
            "subcategory":"Hotels & Motels",
            "type":"Entertainment"
        }
    ],
    "sg:phone":"+61 8 9889 1190",
    "sg:postcode":"6367",
    "sg:province":"WA",
    "wof:name":"Kondinin Roadhouse Motel",
    "wof:placetype":"venue"
},
  "geometry": {"coordinates":[118.264717,-32.498997],"type":"Point"}
}