{
  "type": "Feature",
  "properties": {
    "addr:full":"2 Pierson St Lockleys SA 5032",
    "addr:housenumber":"2",
    "addr:postcode":"5032",
    "addr:street":"Pierson St",
    "iso:country":"AU",
    "sg:address":"2 Pierson St",
    "sg:city":"Lockleys",
    "sg:classifiers":[
        {
            "category":"Travel",
            "subcategory":"Travel Agent",
            "type":"Entertainment"
        }
    ],
    "sg:phone":"+61 8 8354 4191",
    "sg:postcode":"5032",
    "sg:province":"SA",
    "sg:tags":[
        "tour",
        "holiday",
        "adventure"
    ],
    "wof:name":"Big Country Outback Safaris",
    "wof:placetype":"venue"
},
  "geometry": {"coordinates":[138.53602600100001,-34.9197349548],"type":"Point"}
}