{
  "type": "Feature",
  "properties": {
    "iso:country":"AU",
    "sg:address":"62 Whiters St",
    "sg:city":"Lakes Entrance",
    "sg:classifiers":[
        {
            "category":"Food & Beverages",
            "subcategory":"Specialty",
            "type":"Retail Goods"
        }
    ],
    "sg:phone":"+61 3 5155 1493",
    "sg:postcode":"3909",
    "sg:province":"VIC",
    "sg:tags":[
        "ice",
        "supply"
    ],
    "wof:name":"Lakeland Ice",
    "wof:placetype":"venue"
},
  "geometry": {"coordinates":[148.001495361,-37.8704185486],"type":"Point"}
}