{
  "type": "Feature",
  "properties": {
    "addr:full":"5 Third Ave Rossmoyne WA 6148",
    "addr:housenumber":"5",
    "addr:postcode":"6148",
    "addr:street":"Third Ave",
    "iso:country":"AU",
    "sg:address":"5 Third Ave",
    "sg:city":"Rossmoyne",
    "sg:classifiers":[
        {
            "category":"Food & Beverages",
            "subcategory":"Supermarket",
            "type":"Retail Goods"
        }
    ],
    "sg:phone":"+61 8 9457 5553",
    "sg:postcode":"6148",
    "sg:province":"WA",
    "sg:tags":[
        "grocery",
        "store"
    ],
    "wof:name":"Supa Valu Rossmoyne",
    "wof:placetype":"venue"
},
  "geometry": {"coordinates":[115.86788199999999,-32.039059],"type":"Point"}
}