{
  "type": "Feature",
  "properties": {
    "iso:country":"AU",
    "sg:address":"120 Fyans St",
    "sg:city":"Geelong",
    "sg:classifiers":[
        {
            "category":"Travel",
            "subcategory":"Hotels & Motels",
            "type":"Entertainment"
        }
    ],
    "sg:phone":"+61 3 5221 5736",
    "sg:postcode":"3220",
    "sg:province":"VIC",
    "sg:tags":[
        "accommodation"
    ],
    "wof:name":"Valley Inn Hotel",
    "wof:placetype":"venue"
},
  "geometry": {"coordinates":[144.358871,-38.163132],"type":"Point"}
}