{
  "type": "Feature",
  "properties": {
    "addr:full":"66 Glengala Rd Sunshine West VIC 3020",
    "addr:housenumber":"66",
    "addr:postcode":"3020",
    "addr:street":"Glengala Rd",
    "iso:country":"AU",
    "sg:address":"66 Glengala Rd",
    "sg:city":"Sunshine West",
    "sg:classifiers":[
        {
            "category":"Personal",
            "subcategory":"Beauty Salon",
            "type":"Services"
        }
    ],
    "sg:phone":"+61 3 9311 9005",
    "sg:postcode":"3020",
    "sg:province":"VIC",
    "wof:name":"Glengala Road Pharmacy",
    "wof:placetype":"venue"
},
  "geometry": {"coordinates":[144.81755100000001,-37.790375],"type":"Point"}
}