{
  "type": "Feature",
  "properties": {
    "addr:full":"Cnr Church & Beech Sts Whittlesea VIC 3757",
    "addr:postcode":"3757",
    "addr:street":"Sts",
    "iso:country":"AU",
    "sg:address":"Cnr Church & Beech Sts",
    "sg:city":"Whittlesea",
    "sg:classifiers":[
        {
            "category":"Home & Garden",
            "subcategory":"Household Appliances",
            "type":"Retail Goods"
        }
    ],
    "sg:phone":"+61 3 9716 2008",
    "sg:postcode":"3757",
    "sg:province":"VIC",
    "sg:tags":[
        "equipment",
        "gas"
    ],
    "wof:name":"Whittlesea Gas & Hardware",
    "wof:placetype":"venue"
},
  "geometry": {"coordinates":[145.118134,-37.511532],"type":"Point"}
}