{
  "type": "Feature",
  "properties": {
    "addr:full":"Suite 6, 204 Balcatta Rd Balcatta WA 6021",
    "addr:housenumber":"204",
    "addr:postcode":"6021",
    "addr:street":"Balcatta Rd",
    "iso:country":"AU",
    "sg:address":"Suite 6, 204 Balcatta Rd",
    "sg:city":"Balcatta",
    "sg:classifiers":[
        {
            "category":"Professional",
            "subcategory":"Detective & Security Services",
            "type":"Services"
        }
    ],
    "sg:phone":"+61 8 9240 4414",
    "sg:postcode":"6021",
    "sg:province":"WA",
    "sg:tags":[
        "consultant",
        "system"
    ],
    "wof:name":"Interactive Services",
    "wof:placetype":"venue"
},
  "geometry": {"coordinates":[115.817100525,-31.8624477386],"type":"Point"}
}