{
  "type": "Feature",
  "properties": {
    "addr:full":"PO Box 4016 Kingsway West NSW 2208",
    "addr:postcode":"2208",
    "iso:country":"AU",
    "sg:address":"PO Box 4016",
    "sg:city":"Kingsway West",
    "sg:classifiers":[
        {
            "category":"Real Estate",
            "subcategory":"Real Estate Operator",
            "type":"Services"
        }
    ],
    "sg:phone":"+61 412 232 370",
    "sg:postcode":"2208",
    "sg:province":"NSW",
    "sg:tags":[
        "concrete",
        "pumping"
    ],
    "wof:name":"Longreach Pumping Service",
    "wof:placetype":"venue"
},
  "geometry": {"coordinates":[151.09350599999999,-33.950161],"type":"Point"}
}