{
  "type": "Feature",
  "properties": {
    "addr:full":"11 Derwent Park Rd Derwent Park TAS 7009",
    "addr:housenumber":"11",
    "addr:postcode":"7009",
    "addr:street":"Derwent Park Rd",
    "iso:country":"AU",
    "sg:address":"11 Derwent Park Rd",
    "sg:city":"Derwent Park",
    "sg:classifiers":[
        {
            "category":"Shopping",
            "type":"Retail Goods"
        }
    ],
    "sg:phone":"+61 3 6273 1333",
    "sg:postcode":"7009",
    "sg:province":"TAS",
    "sg:tags":[
        "equipment",
        "safety",
        "accessory"
    ],
    "wof:name":"Blackwood J & Son Ltd",
    "wof:placetype":"venue"
},
  "geometry": {"coordinates":[147.29197692899999,-42.8394622803],"type":"Point"}
}