{
  "type": "Feature",
  "properties": {
    "addr:full":"135c Eighth St Mildura VIC 3500",
    "addr:housenumber":"135c",
    "addr:postcode":"3500",
    "addr:street":"Eighth St",
    "iso:country":"AU",
    "sg:address":"135c Eighth St",
    "sg:city":"Mildura",
    "sg:classifiers":[
        {
            "category":"Professional",
            "subcategory":"Business Services",
            "type":"Services"
        }
    ],
    "sg:phone":"+61 3 5023 3595",
    "sg:postcode":"3500",
    "sg:province":"VIC",
    "sg:tags":[
        "small",
        "advisory"
    ],
    "wof:name":"Jayne Sunbird Enterprises",
    "wof:placetype":"venue"
},
  "geometry": {"coordinates":[142.16177368199999,-34.1844749451],"type":"Point"}
}