{
  "type": "Feature",
  "properties": {
    "iso:country":"AU",
    "sg:address":"21 Missenden Rd",
    "sg:city":"Camperdown",
    "sg:classifiers":[
        {
            "category":"Health Services",
            "subcategory":"Doctor",
            "type":"Services"
        }
    ],
    "sg:phone":"+61 2 9557 5444",
    "sg:postcode":"2050",
    "sg:province":"NSW",
    "sg:tags":[
        "medical",
        "practitioner"
    ],
    "wof:name":"Patrick W G D",
    "wof:placetype":"venue"
},
  "geometry": {"coordinates":[151.179825,-33.887215],"type":"Point"}
}