{
  "type": "Feature",
  "properties": {
    "addr:full":"Unit 3, 30a Cnr Elizabeth & Victoria Sts Wetherill Park NSW 2164",
    "addr:housenumber":"30a",
    "addr:postcode":"2164",
    "addr:street":"Cnr Elizabeth & Victoria Sts",
    "iso:country":"AU",
    "sg:address":"Unit 3, 30a Cnr Elizabeth & Victoria Sts",
    "sg:city":"Wetherill Park",
    "sg:classifiers":[
        {
            "category":"Wholesale",
            "subcategory":"Electrical",
            "type":"Manufacturing & Wholesale Goods"
        }
    ],
    "sg:phone":"+61 2 9609 1222",
    "sg:postcode":"2164",
    "sg:province":"NSW",
    "sg:tags":[
        "wholesaler"
    ],
    "wof:name":"TLE Electrical",
    "wof:placetype":"venue"
},
  "geometry": {"coordinates":[150.90748596200001,-33.8466835022],"type":"Point"}
}