{
  "type": "Feature",
  "properties": {
    "iso:country":"AU",
    "sg:address":"25 Stubbs St",
    "sg:city":"Auburn",
    "sg:classifiers":[
        {
            "category":"Manufacturing",
            "subcategory":"Electronics",
            "type":"Manufacturing & Wholesale Goods"
        }
    ],
    "sg:phone":"+61 2 9202 4100",
    "sg:postcode":"1835",
    "sg:province":"NSW",
    "sg:tags":[
        "wholesaler",
        "equipment",
        "part",
        "mfrs",
        "refrigeration"
    ],
    "wof:name":"Totaline",
    "wof:placetype":"venue"
},
  "geometry": {"coordinates":[151.03666687,-33.8399353027],"type":"Point"}
}