{
  "type": "Feature",
  "properties": {
    "addr:full":"21a Kingsway St Cronulla NSW 2230",
    "addr:housenumber":"21a",
    "addr:postcode":"2230",
    "addr:street":"Kingsway St",
    "iso:country":"AU",
    "sg:address":"21a Kingsway St",
    "sg:city":"Cronulla",
    "sg:classifiers":[
        {
            "category":"Fast Food",
            "type":"Food & Drink"
        }
    ],
    "sg:phone":"+61 2 9523 6532",
    "sg:postcode":"2230",
    "sg:province":"NSW",
    "sg:tags":[
        "away",
        "take"
    ],
    "wof:name":"Blue Pacific Seafood",
    "wof:placetype":"venue"
},
  "geometry": {"coordinates":[151.15255737300001,-34.0510253906],"type":"Point"}
}