{
  "type": "Feature",
  "properties": {
    "iso:country":"AU",
    "sg:address":"361- 363 Sheridan St",
    "sg:city":"Cairns North",
    "sg:classifiers":[
        {
            "category":"Health Services",
            "subcategory":"Dentist",
            "type":"Services"
        }
    ],
    "sg:phone":"+61 7 4051 8501",
    "sg:postcode":"4870",
    "sg:province":"QLD",
    "wof:name":"Richards Daniel",
    "wof:placetype":"venue"
},
  "geometry": {"coordinates":[145.75776672399999,-16.9039020538],"type":"Point"}
}