{
  "type": "Feature",
  "properties": {
    "addr:full":"PO Box 252 Queanbeyan ACT 2620",
    "addr:postcode":"2620",
    "iso:country":"AU",
    "sg:address":"PO Box 252",
    "sg:city":"Queanbeyan",
    "sg:classifiers":[
        {
            "category":"Home & Garden",
            "subcategory":"Building Materials",
            "type":"Retail Goods"
        }
    ],
    "sg:phone":"+61 439 993 270",
    "sg:postcode":"2620",
    "sg:province":"ACT",
    "sg:tags":[
        "merchant",
        "glass",
        "glazier"
    ],
    "wof:name":"AM-PM Glass",
    "wof:placetype":"venue"
},
  "geometry": {"coordinates":[149.217987061,-35.3758049011],"type":"Point"}
}