{
  "type": "Feature",
  "properties": {
    "addr:full":"6 Bolton Ave Hampton VIC 3188",
    "addr:housenumber":"6",
    "addr:postcode":"3188",
    "addr:street":"Bolton Ave",
    "iso:country":"AU",
    "sg:address":"6 Bolton Ave",
    "sg:city":"Hampton",
    "sg:classifiers":[
        {
            "category":"Building & Trades",
            "subcategory":"Plumbing",
            "type":"Services"
        }
    ],
    "sg:phone":"+61 409 557 700",
    "sg:postcode":"3188",
    "sg:province":"VIC",
    "sg:tags":[
        "plumber",
        "gasfitters"
    ],
    "wof:name":"Waterside Plumbing",
    "wof:placetype":"venue"
},
  "geometry": {"coordinates":[144.994506836,-37.9310417175],"type":"Point"}
}