{
  "type": "Feature",
  "properties": {
    "addr:full":"7 Guedecourt Ave Earlwood NSW 2206",
    "addr:housenumber":"7",
    "addr:postcode":"2206",
    "addr:street":"Guedecourt Ave",
    "iso:country":"AU",
    "sg:address":"7 Guedecourt Ave",
    "sg:city":"Earlwood",
    "sg:classifiers":[
        {
            "category":"Manufacturing",
            "subcategory":"Paper Products",
            "type":"Manufacturing & Wholesale Goods"
        }
    ],
    "sg:phone":"+61 2 9559 5033",
    "sg:postcode":"2206",
    "sg:province":"NSW",
    "sg:tags":[
        "disposable"
    ],
    "wof:name":"Milpak Pty Ltd",
    "wof:placetype":"venue"
},
  "geometry": {"coordinates":[151.13009600000001,-33.919868],"type":"Point"}
}