{
  "type": "Feature",
  "properties": {
    "iso:country":"AU",
    "sg:address":"118 Bronte Rd",
    "sg:city":"Bondi Junction",
    "sg:classifiers":[
        {
            "category":"Retail",
            "subcategory":"Auto Repair",
            "type":"Services"
        }
    ],
    "sg:phone":"+61 2 9389 5486",
    "sg:postcode":"2022",
    "sg:province":"NSW",
    "sg:tags":[
        "repairer",
        "motor",
        "engineer"
    ],
    "wof:name":"Tornik Motors",
    "wof:placetype":"venue"
},
  "geometry": {"coordinates":[151.25114440900001,-33.8957443237],"type":"Point"}
}