{
  "type": "Feature",
  "properties": {
    "addr:full":"Mooloolaba Junction Convenience Centre Cnr Brisbane Rd & Kapala St Mooloolaba QLD 4557",
    "addr:postcode":"4557",
    "addr:street":"Cnr Brisbane Rd & Kapala St",
    "iso:country":"AU",
    "sg:address":"Mooloolaba Junction Convenience Centre Cnr Brisbane Rd & Kapala St",
    "sg:city":"Mooloolaba",
    "sg:classifiers":[
        {
            "category":"Fast Food",
            "type":"Food & Drink"
        }
    ],
    "sg:phone":"+61 7 5470 9222",
    "sg:postcode":"4557",
    "sg:province":"QLD",
    "sg:tags":[
        "away",
        "take"
    ],
    "wof:name":"Domino's Pizza",
    "wof:placetype":"venue"
},
  "geometry": {"coordinates":[153.11770629899999,-26.6839618683],"type":"Point"}
}