{
  "type": "Feature",
  "properties": {
    "addr:full":"30 Oxford St Cambridge Park NSW 2747",
    "addr:housenumber":"30",
    "addr:postcode":"2747",
    "addr:street":"Oxford St",
    "iso:country":"AU",
    "sg:address":"30 Oxford St",
    "sg:city":"Cambridge Park",
    "sg:classifiers":[
        {
            "category":"Structure",
            "subcategory":"Office Building",
            "type":"Public Place"
        }
    ],
    "sg:phone":"+61 2 4731 5034",
    "sg:postcode":"2747",
    "sg:province":"NSW",
    "sg:tags":[
        "tie",
        "concrete",
        "formwork",
        "form",
        "accessory"
    ],
    "wof:name":"Graham Fliedner Concreting",
    "wof:placetype":"venue"
},
  "geometry": {"coordinates":[150.72804260300001,-33.7487449646],"type":"Point"}
}