{
  "type": "Feature",
  "properties": {
    "iso:country":"AU",
    "sg:address":"16/ 285 Creek Rd",
    "sg:city":"Mt Gravatt",
    "sg:classifiers":[
        {
            "category":"Home & Garden",
            "subcategory":"Building Materials",
            "type":"Retail Goods"
        }
    ],
    "sg:phone":"+61 404 484 708",
    "sg:postcode":"4122",
    "sg:province":"QLD",
    "sg:tags":[
        "lawn",
        "cutting",
        "maintenance"
    ],
    "wof:name":"Green Force Lawnmowing",
    "wof:placetype":"venue"
},
  "geometry": {"coordinates":[153.093383789,-27.532453537],"type":"Point"}
}