{
  "type": "Feature",
  "properties": {
    "addr:full":"1/ 124 Petra St Bicton WA 6157",
    "addr:housenumber":"/ 124",
    "addr:postcode":"6157",
    "addr:street":"Petra St",
    "iso:country":"AU",
    "sg:address":"1/ 124 Petra St",
    "sg:city":"Bicton",
    "sg:classifiers":[
        {
            "category":"Retail",
            "subcategory":"Repair Shop",
            "type":"Services"
        }
    ],
    "sg:phone":"+61 8 9339 0956",
    "sg:postcode":"6157",
    "sg:province":"WA",
    "sg:tags":[
        "stove",
        "part",
        "range"
    ],
    "wof:name":"A C Pinzone",
    "wof:placetype":"venue"
},
  "geometry": {"coordinates":[115.776291,-32.031696],"type":"Point"}
}