{
  "type": "Feature",
  "properties": {
    "addr:full":"24 Namatjira Crt Broadbeach Waters QLD 4218",
    "addr:housenumber":"24",
    "addr:postcode":"4218",
    "addr:street":"Namatjira Crt",
    "iso:country":"AU",
    "sg:address":"24 Namatjira Crt",
    "sg:city":"Broadbeach Waters",
    "sg:classifiers":[
        {
            "category":"Professional",
            "subcategory":"Accounting & Tax Preparation",
            "type":"Services"
        }
    ],
    "sg:phone":"+61 7 5579 9912",
    "sg:postcode":"4218",
    "sg:province":"QLD",
    "sg:tags":[
        "accountant",
        "auditor"
    ],
    "wof:name":"Restaino & Associates",
    "wof:placetype":"venue"
},
  "geometry": {"coordinates":[153.39256286599999,-28.0292816162],"type":"Point"}
}