{
  "type": "Feature",
  "properties": {
    "addr:full":"U1/ 37 Berriman Drv Wangara WA 6065",
    "addr:housenumber":"37",
    "addr:postcode":"6065",
    "addr:street":"U1 /;Berriman Drv",
    "iso:country":"AU",
    "sg:address":"U1/ 37 Berriman Drv",
    "sg:city":"Wangara",
    "sg:classifiers":[
        {
            "category":"Professional",
            "subcategory":"Detective & Security Services",
            "type":"Services"
        }
    ],
    "sg:phone":"+61 8 9309 5880",
    "sg:postcode":"6065",
    "sg:province":"WA",
    "sg:tags":[
        "equipment",
        "window",
        "doors"
    ],
    "wof:name":"All Aussie Aluminium & Glass",
    "wof:placetype":"venue"
},
  "geometry": {"coordinates":[115.822891235,-31.7934322357],"type":"Point"}
}