{
  "type": "Feature",
  "properties": {
    "addr:full":"9 Stewart St Ardlethan NSW 2665",
    "addr:housenumber":"9",
    "addr:postcode":"2665",
    "addr:street":"Stewart St",
    "iso:country":"AU",
    "sg:address":"9 Stewart St",
    "sg:city":"Ardlethan",
    "sg:classifiers":[
        {
            "category":"Retail",
            "subcategory":"Auto Repair",
            "type":"Services"
        }
    ],
    "sg:phone":"+61 2 6978 2086",
    "sg:postcode":"2665",
    "sg:province":"NSW",
    "sg:tags":[
        "repairer",
        "motor",
        "engineer"
    ],
    "wof:name":"P & D Industry",
    "wof:placetype":"venue"
},
  "geometry": {"coordinates":[146.89956665,-34.3562660217],"type":"Point"}
}