{
  "type": "Feature",
  "properties": {
    "addr:full":"Lot 5 Amsterdam Cct Wyong NSW 2259",
    "addr:housenumber":"5",
    "addr:postcode":"2259",
    "addr:street":"Cct",
    "iso:country":"AU",
    "sg:address":"Lot 5",
    "sg:city":"Amsterdam Cct Wyong",
    "sg:classifiers":[
        {
            "category":"Utilities",
            "subcategory":"Recycling",
            "type":"Services"
        }
    ],
    "sg:phone":"+61 2 4351 1005",
    "sg:postcode":"2259",
    "sg:province":"NSW",
    "wof:name":"McAlisters Metal Recyclers Pty Ltd",
    "wof:placetype":"venue"
},
  "geometry": {"coordinates":[151.45196533199999,-33.2639961243],"type":"Point"}
}