{
  "type": "Feature",
  "properties": {
    "addr:full":"18 Braithwate Ave Bellingen NSW 2454",
    "addr:housenumber":"18",
    "addr:postcode":"2454",
    "addr:street":"Braithwate Ave",
    "iso:country":"AU",
    "sg:address":"18 Braithwate Ave",
    "sg:city":"Bellingen",
    "sg:classifiers":[
        {
            "category":"Professional",
            "subcategory":"Art Services",
            "type":"Services"
        }
    ],
    "sg:phone":"+61 422 802 775",
    "sg:postcode":"2454",
    "sg:province":"NSW",
    "sg:tags":[
        "decorator",
        "painter"
    ],
    "wof:name":"1st Painter",
    "wof:placetype":"venue"
},
  "geometry": {"coordinates":[152.900284,-30.44565],"type":"Point"}
}