{
  "type": "Feature",
  "properties": {
    "iso:country":"AU",
    "sg:address":"191 Patrick St",
    "sg:city":"Laidley",
    "sg:classifiers":[
        {
            "category":"Professional",
            "subcategory":"Art Services",
            "type":"Services"
        }
    ],
    "sg:phone":"+61 7 5465 1747",
    "sg:postcode":"4341",
    "sg:province":"QLD",
    "sg:tags":[
        "decorator",
        "painter"
    ],
    "wof:name":"Bichel K R (Kev)",
    "wof:placetype":"venue"
},
  "geometry": {"coordinates":[152.393844605,-27.6306762695],"type":"Point"}
}