{
  "type": "Feature",
  "properties": {
    "addr:full":"58 Glasshouse Rocks Rd Narooma NSW 2546",
    "addr:housenumber":"58",
    "addr:postcode":"2546",
    "addr:street":"Glasshouse Rocks Rd",
    "iso:country":"AU",
    "sg:address":"58 Glasshouse Rocks Rd",
    "sg:city":"Narooma",
    "sg:classifiers":[
        {
            "category":"Manufacturing",
            "subcategory":"Retail Goods",
            "type":"Manufacturing & Wholesale Goods"
        }
    ],
    "sg:phone":"+61 2 4476 4129",
    "sg:postcode":"2546",
    "sg:province":"NSW",
    "sg:tags":[
        "merchant",
        "pump",
        "mfrs"
    ],
    "wof:name":"Macarthur Tractor & Outdoor Products",
    "wof:placetype":"venue"
},
  "geometry": {"coordinates":[150.13011169399999,-36.231842041],"type":"Point"}
}