{
  "type": "Feature",
  "properties": {
    "addr:full":"5 Wildon St Bellevue WA 6056",
    "addr:housenumber":"5",
    "addr:postcode":"6056",
    "addr:street":"Wildon St",
    "iso:country":"AU",
    "sg:address":"5 Wildon St",
    "sg:city":"Bellevue",
    "sg:classifiers":[
        {
            "category":"Professional",
            "type":"Services"
        }
    ],
    "sg:phone":"+61 8 9274 7232",
    "sg:postcode":"6056",
    "sg:province":"WA",
    "sg:tags":[
        "transport"
    ],
    "wof:name":"Motere Pty Ltd",
    "wof:placetype":"venue"
},
  "geometry": {"coordinates":[116.020362854,-31.9002838135],"type":"Point"}
}