{
  "type": "Feature",
  "properties": {
    "addr:full":"50 Young St Gladstone QLD 4680",
    "addr:housenumber":"50",
    "addr:postcode":"4680",
    "addr:street":"Young St",
    "iso:country":"AU",
    "sg:address":"50 Young St",
    "sg:city":"Gladstone",
    "sg:classifiers":[
        {
            "category":"Organizations",
            "subcategory":"Community Association",
            "type":"Services"
        }
    ],
    "sg:phone":"+61 7 4972 8220",
    "sg:postcode":"4680",
    "sg:province":"QLD",
    "sg:tags":[
        "organisation",
        "family",
        "welfare"
    ],
    "wof:name":"Anglicare Central Queensland",
    "wof:placetype":"venue"
},
  "geometry": {"coordinates":[151.26698303200001,-23.8494281769],"type":"Point"}
}