{
  "type": "Feature",
  "properties": {
    "addr:full":"Lvl 1 / 1 The Esplanade Mt Pleasant WA 6153",
    "addr:housenumber":"/ 1",
    "addr:postcode":"6153",
    "addr:street":"The Esplanade",
    "iso:country":"AU",
    "sg:address":"Lvl 1",
    "sg:city":"/ 1 The Esplanade Mt Pleasant",
    "sg:classifiers":[
        {
            "category":"Professional",
            "subcategory":"Management & Consulting",
            "type":"Services"
        }
    ],
    "sg:phone":"+61 8 9364 8544",
    "sg:postcode":"6153",
    "sg:province":"WA",
    "sg:tags":[
        "consultant"
    ],
    "wof:name":"Northcliffe Strategic Management",
    "wof:placetype":"venue"
},
  "geometry": {"coordinates":[115.850143,-32.012321],"type":"Point"}
}