{
  "type": "Feature",
  "properties": {
    "addr:full":"10 Mossman Ave Bateau Bay NSW 2261",
    "addr:housenumber":"10",
    "addr:postcode":"2261",
    "addr:street":"Mossman Ave",
    "iso:country":"AU",
    "sg:address":"10 Mossman Ave",
    "sg:city":"Bateau Bay",
    "sg:classifiers":[
        {
            "category":"Shopping",
            "subcategory":"Antiques",
            "type":"Retail Goods"
        }
    ],
    "sg:phone":"+61 2 4332 4449",
    "sg:postcode":"2261",
    "sg:province":"NSW",
    "sg:tags":[
        "restoration",
        "reproduction"
    ],
    "wof:name":"Barwick Grant",
    "wof:placetype":"venue"
},
  "geometry": {"coordinates":[151.47174100000001,-33.388081],"type":"Point"}
}