{
  "type": "Feature",
  "properties": {
    "iso:country":"AU",
    "sg:address":"Level 1, 186 Jull St",
    "sg:city":"Armadale",
    "sg:classifiers":[
        {
            "category":"Professional",
            "subcategory":"Accounting & Tax Preparation",
            "type":"Services"
        }
    ],
    "sg:phone":"+61 8 9399 4302",
    "sg:postcode":"6112",
    "sg:province":"WA",
    "sg:tags":[
        "accountant",
        "auditor"
    ],
    "wof:name":"Lancaster R.D.",
    "wof:placetype":"venue"
},
  "geometry": {"coordinates":[116.020591736,-32.1502380371],"type":"Point"}
}