{
  "type": "Feature",
  "properties": {
    "addr:full":"25 Bresnahan Pl Marangaroo WA 6064",
    "addr:housenumber":"25",
    "addr:postcode":"6064",
    "addr:street":"Bresnahan Pl Marangaroo",
    "iso:country":"AU",
    "sg:address":"25 Bresnahan Pl",
    "sg:city":"Marangaroo",
    "sg:classifiers":[
        {
            "category":"Home & Garden",
            "subcategory":"Building Materials",
            "type":"Retail Goods"
        }
    ],
    "sg:phone":"+61 8 9247 5056",
    "sg:postcode":"6064",
    "sg:province":"WA",
    "sg:tags":[
        "lawn",
        "cutting",
        "maintenance"
    ],
    "wof:name":"Karoys Garden & Lawn Maintenance",
    "wof:placetype":"venue"
},
  "geometry": {"coordinates":[115.839439392,-31.8291912079],"type":"Point"}
}