{
  "type": "Feature",
  "properties": {
    "iso:country":"AU",
    "sg:address":"6 Robert St",
    "sg:city":"Telopea",
    "sg:classifiers":[
        {
            "category":"Professional",
            "subcategory":"Accounting & Tax Preparation",
            "type":"Services"
        }
    ],
    "sg:phone":"+61 2 9872 3865",
    "sg:postcode":"2117",
    "sg:province":"NSW",
    "sg:tags":[
        "bookkeeping"
    ],
    "wof:name":"Managed Business Solutions",
    "wof:placetype":"venue"
},
  "geometry": {"coordinates":[151.04031372099999,-33.7942695618],"type":"Point"}
}