{
  "type": "Feature",
  "properties": {
    "addr:full":"5 Cockburn Rd Albany WA 6330",
    "addr:housenumber":"5",
    "addr:postcode":"6330",
    "addr:street":"Cockburn Rd",
    "iso:country":"AU",
    "sg:address":"5 Cockburn Rd",
    "sg:city":"Albany",
    "sg:classifiers":[
        {
            "category":"Professional",
            "subcategory":"Printing & Photocopies",
            "type":"Services"
        }
    ],
    "sg:phone":"+61 8 9841 8755",
    "sg:postcode":"6330",
    "sg:province":"WA",
    "sg:tags":[
        "screen",
        "printer"
    ],
    "wof:name":"Albany Screenprinters & Signwriters",
    "wof:placetype":"venue"
},
  "geometry": {"coordinates":[117.897842407,-35.0158538818],"type":"Point"}
}