{
  "type": "Feature",
  "properties": {
    "addr:full":"Suite 1, Glengarry Specialist Centre 60 Arnisdale Rd Duncraig WA 6023",
    "addr:housenumber":"60",
    "addr:postcode":"6023",
    "addr:street":"Arnisdale Rd",
    "iso:country":"AU",
    "sg:address":"Suite 1, Glengarry Specialist Centre 60 Arnisdale Rd",
    "sg:city":"Duncraig",
    "sg:classifiers":[
        {
            "category":"Health Services",
            "subcategory":"Health Practitioner",
            "type":"Services"
        }
    ],
    "sg:phone":"+61 8 9246 4497",
    "sg:postcode":"6023",
    "sg:province":"WA",
    "sg:tags":[
        "pathologist",
        "speech"
    ],
    "wof:name":"Wells Christine",
    "wof:placetype":"venue"
},
  "geometry": {"coordinates":[115.78269195599999,-31.8352069855],"type":"Point"}
}