{
  "type": "Feature",
  "properties": {
    "addr:full":"93 Beach Rd Legana TAS 7277",
    "addr:housenumber":"93",
    "addr:postcode":"7277",
    "addr:street":"Beach Rd",
    "iso:country":"AU",
    "sg:address":"93 Beach Rd",
    "sg:city":"Legana",
    "sg:classifiers":[
        {
            "category":"Professional",
            "subcategory":"Testing Lab",
            "type":"Services"
        }
    ],
    "sg:phone":"+61 400 134 264",
    "sg:postcode":"7277",
    "sg:province":"TAS",
    "sg:tags":[
        "inspection"
    ],
    "wof:name":"Tas Tech Electrical",
    "wof:placetype":"venue"
},
  "geometry": {"coordinates":[147.04739379899999,-41.3469352722],"type":"Point"}
}