{
  "type": "Feature",
  "properties": {
    "addr:full":"10 Second Ave Unanderra NSW 2526",
    "addr:housenumber":"10",
    "addr:postcode":"2526",
    "addr:street":"Second Ave",
    "iso:country":"AU",
    "sg:address":"10 Second Ave",
    "sg:city":"Unanderra",
    "sg:classifiers":[
        {
            "category":"Wholesale",
            "subcategory":"Electrical",
            "type":"Manufacturing & Wholesale Goods"
        }
    ],
    "sg:phone":"+61 2 4272 1899",
    "sg:postcode":"2526",
    "sg:province":"NSW",
    "sg:tags":[
        "control",
        "equipment",
        "switch"
    ],
    "wof:name":"i Open Pty Ltd",
    "wof:placetype":"venue"
},
  "geometry": {"coordinates":[150.83467102,-34.4674568176],"type":"Point"}
}