{
  "type": "Feature",
  "properties": {
    "addr:full":"Gorge Rd Finch Hatton QLD 4756",
    "addr:postcode":"4756",
    "addr:street":"Gorge Rd",
    "iso:country":"AU",
    "sg:address":"Gorge Rd",
    "sg:city":"Finch Hatton",
    "sg:classifiers":[
        {
            "category":"Farming",
            "subcategory":"Farm",
            "type":"Manufacturing & Wholesale Goods"
        }
    ],
    "sg:phone":"+61 7 4958 3131",
    "sg:postcode":"4756",
    "sg:province":"QLD",
    "sg:tags":[
        "farmer"
    ],
    "wof:name":"Peoples J W",
    "wof:placetype":"venue"
},
  "geometry": {"coordinates":[148.630707,-21.136915],"type":"Point"}
}