{
  "type": "Feature",
  "properties": {
    "addr:full":"Unit 1, 19 Olympic Crt Southport QLD 4215",
    "addr:housenumber":"19",
    "addr:postcode":"4215",
    "addr:street":"Olympic Crt",
    "iso:country":"AU",
    "sg:address":"Unit 1, 19 Olympic Crt",
    "sg:city":"Southport",
    "sg:classifiers":[
        {
            "category":"Retail",
            "subcategory":"Auto Repair",
            "type":"Services"
        }
    ],
    "sg:phone":"+61 7 5531 4550",
    "sg:postcode":"4215",
    "sg:province":"QLD",
    "sg:tags":[
        "beater",
        "painter",
        "panel"
    ],
    "wof:name":"AJA Smash Repairs",
    "wof:placetype":"venue"
},
  "geometry": {"coordinates":[153.39154052699999,-27.9688491821],"type":"Point"}
}