{
  "type": "Feature",
  "properties": {
    "iso:country":"AU",
    "sg:address":"98 Chapman St",
    "sg:city":"Swan Hill",
    "sg:classifiers":[
        {
            "category":"Food & Beverages",
            "subcategory":"Specialty",
            "type":"Retail Goods"
        }
    ],
    "sg:phone":"+61 3 5032 1722",
    "sg:postcode":"3585",
    "sg:province":"VIC",
    "sg:tags":[
        "delicacy"
    ],
    "wof:name":"Mallee's Little Asian Spice Shop",
    "wof:placetype":"venue"
},
  "geometry": {"coordinates":[143.548248,-35.332348],"type":"Point"}
}