{
  "type": "Feature",
  "properties": {
    "iso:country":"AU",
    "sg:address":"551 Glynburn Rd",
    "sg:city":"Hazelwood Park",
    "sg:classifiers":[
        {
            "category":"Shopping",
            "subcategory":"Jewelry",
            "type":"Retail Goods"
        }
    ],
    "sg:phone":"+61 8 8332 3519",
    "sg:postcode":"5066",
    "sg:province":"SA",
    "sg:tags":[
        "jeweller"
    ],
    "wof:name":"Argenta Jewellery & Design",
    "wof:placetype":"venue"
},
  "geometry": {"coordinates":[138.66011047399999,-34.9398880005],"type":"Point"}
}