{
  "type": "Feature",
  "properties": {
    "addr:full":"Shop 11/ 4 Charlotte Cl Woree QLD 4868",
    "addr:housenumber":"shop 11 / 4",
    "addr:postcode":"4868",
    "addr:street":"Charlotte Cl Woree",
    "iso:country":"AU",
    "sg:address":"Shop 11/ 4",
    "sg:city":"Charlotte Cl Woree",
    "sg:classifiers":[
        {
            "category":"Professional",
            "subcategory":"Accounting & Tax Preparation",
            "type":"Services"
        }
    ],
    "sg:phone":"+61 7 4033 0344",
    "sg:postcode":"4868",
    "sg:province":"QLD",
    "sg:tags":[
        "accountant",
        "auditor"
    ],
    "wof:name":"Walsh & Co",
    "wof:placetype":"venue"
},
  "geometry": {"coordinates":[145.74688720699999,-16.954410553],"type":"Point"}
}