{
  "type": "Feature",
  "properties": {
    "iso:country":"AU",
    "sg:address":"48 Prospero St",
    "sg:city":"Murwillumbah",
    "sg:classifiers":[
        {
            "category":"Banks & Credit Unions",
            "subcategory":"Investment Brokerage",
            "type":"Services"
        }
    ],
    "sg:phone":"+61 2 6672 3042",
    "sg:postcode":"2484",
    "sg:province":"NSW",
    "sg:tags":[
        "radiator",
        "motor"
    ],
    "wof:name":"Sunshine Batteries & Radiator Service",
    "wof:placetype":"venue"
},
  "geometry": {"coordinates":[153.40164184599999,-28.3295555115],"type":"Point"}
}