{
  "type": "Feature",
  "properties": {
    "addr:full":"Byford Primary School 36 Clifton St Byford WA 6122",
    "addr:housenumber":"36",
    "addr:postcode":"6122",
    "addr:street":"Clifton St",
    "iso:country":"AU",
    "sg:address":"Byford Primary School 36 Clifton St",
    "sg:city":"Byford",
    "sg:classifiers":[
        {
            "category":"Education",
            "subcategory":"School",
            "type":"Public Place"
        }
    ],
    "sg:phone":"+61 8 9525 1337",
    "sg:postcode":"6122",
    "sg:province":"WA",
    "sg:tags":[
        "state",
        "except",
        "nsw"
    ],
    "wof:name":"Schools Government (Public)",
    "wof:placetype":"venue"
},
  "geometry": {"coordinates":[116.012718201,-32.2204322815],"type":"Point"}
}