{
  "type": "Feature",
  "properties": {
    "addr:full":"105 Gertrude St Port Pirie SA 5540",
    "addr:housenumber":"105",
    "addr:postcode":"5540",
    "addr:street":"Gertrude St",
    "iso:country":"AU",
    "sg:address":"105 Gertrude St",
    "sg:city":"Port Pirie",
    "sg:classifiers":[
        {
            "category":"Education",
            "subcategory":"School",
            "type":"Public Place"
        }
    ],
    "sg:phone":"+61 8 8633 0499",
    "sg:postcode":"5540",
    "sg:province":"SA",
    "wof:name":"Catholic Education Office",
    "wof:placetype":"venue"
},
  "geometry": {"coordinates":[138.007904053,-33.179397583],"type":"Point"}
}