{
  "type": "Feature",
  "properties": {
    "addr:full":"43 Oberthur Crs Bull Creek WA 6149",
    "addr:housenumber":"43",
    "addr:postcode":"6149",
    "addr:street":"Oberthur Crs",
    "iso:country":"AU",
    "sg:address":"43 Oberthur Crs",
    "sg:city":"Bull Creek",
    "sg:classifiers":[
        {
            "category":"Health Services",
            "subcategory":"Doctor",
            "type":"Services"
        }
    ],
    "sg:phone":"+61 8 9332 0265",
    "sg:postcode":"6149",
    "sg:province":"WA",
    "sg:tags":[
        "medical",
        "practitioner"
    ],
    "wof:name":"McCurdy John Dr",
    "wof:placetype":"venue"
},
  "geometry": {"coordinates":[115.86541,-32.056782],"type":"Point"}
}