{
  "type": "Feature",
  "properties": {
    "iso:country":"AU",
    "sg:address":"Lot 21 Sturt Hwy",
    "sg:city":"Trentham Cliffs",
    "sg:classifiers":[
        {
            "category":"Mining & Drilling",
            "type":"Manufacturing & Wholesale Goods"
        }
    ],
    "sg:phone":"+61 3 5024 8791",
    "sg:postcode":"2738",
    "sg:province":"VIC",
    "sg:tags":[
        "boring",
        "contractor"
    ],
    "wof:name":"Budd Drilling Pty Ltd",
    "wof:placetype":"venue"
},
  "geometry": {"coordinates":[142.231186,-34.185699],"type":"Point"}
}