{
  "type": "Feature",
  "properties": {
    "addr:full":"Unit 1, 194 Balcatta Rd Balcatta WA 6021",
    "addr:housenumber":"194",
    "addr:postcode":"6021",
    "addr:street":"Balcatta Rd",
    "iso:country":"AU",
    "sg:address":"Unit 1, 194 Balcatta Rd",
    "sg:city":"Balcatta",
    "sg:classifiers":[
        {
            "category":"Retail",
            "subcategory":"Auto Repair",
            "type":"Services"
        }
    ],
    "sg:phone":"+61 8 9345 3703",
    "sg:postcode":"6021",
    "sg:province":"WA",
    "sg:tags":[
        "clutch",
        "brake"
    ],
    "wof:name":"Balcatta Brake & Clutch",
    "wof:placetype":"venue"
},
  "geometry": {"coordinates":[115.817001343,-31.8624153137],"type":"Point"}
}