{
  "type": "Feature",
  "properties": {
    "addr:full":"73a Strickland St Swanbourne WA 6010",
    "addr:housenumber":"73a",
    "addr:postcode":"6010",
    "addr:street":"Strickland St",
    "iso:country":"AU",
    "sg:address":"73a Strickland St",
    "sg:city":"Swanbourne",
    "sg:classifiers":[
        {
            "category":"Professional",
            "subcategory":"Management & Consulting",
            "type":"Services"
        }
    ],
    "sg:phone":"+61 8 9384 0174",
    "sg:postcode":"6010",
    "sg:province":"WA",
    "sg:tags":[
        "consultant"
    ],
    "wof:name":"Duncanson Associates",
    "wof:placetype":"venue"
},
  "geometry": {"coordinates":[115.775100708,-31.9707393646],"type":"Point"}
}