{
  "type": "Feature",
  "properties": {
    "iso:country":"AU",
    "sg:address":"100 Ewing St",
    "sg:city":"Welshpool",
    "sg:classifiers":[
        {
            "category":"Retail",
            "subcategory":"Driving School",
            "type":"Services"
        }
    ],
    "sg:phone":"+61 411 222 021",
    "sg:postcode":"6106",
    "sg:province":"WA",
    "wof:name":"A B K Driving School",
    "wof:placetype":"venue"
},
  "geometry": {"coordinates":[115.931472778,-31.9948253632],"type":"Point"}
}