{
  "type": "Feature",
  "properties": {
    "iso:country":"AU",
    "sg:address":"Bay View St",
    "sg:city":"Williamstown",
    "sg:classifiers":[
        {
            "category":"Education",
            "subcategory":"School",
            "type":"Public Place"
        }
    ],
    "sg:phone":"+61 3 9399 9228",
    "sg:postcode":"3016",
    "sg:province":"VIC",
    "sg:tags":[
        "state",
        "except",
        "nsw"
    ],
    "wof:name":"Point Gellibrand Girls Secondary College",
    "wof:placetype":"venue"
},
  "geometry": {"coordinates":[144.886627197,-37.8594779968],"type":"Point"}
}