{
  "type": "Feature",
  "properties": {
    "addr:full":"50 Bronte Rd Bondi Junction NSW 1355",
    "addr:housenumber":"50",
    "addr:postcode":"1355",
    "addr:street":"Bronte Rd",
    "iso:country":"AU",
    "sg:address":"50 Bronte Rd",
    "sg:city":"Bondi Junction",
    "sg:classifiers":[
        {
            "category":"Real Estate",
            "subcategory":"Real Estate Agent",
            "type":"Services"
        }
    ],
    "sg:phone":"+61 2 8305 5777",
    "sg:postcode":"1355",
    "sg:province":"NSW",
    "wof:name":"NG Farah Real Estate",
    "wof:placetype":"venue"
},
  "geometry": {"coordinates":[151.25012207,-33.8943328857],"type":"Point"}
}