{
  "type": "Feature",
  "properties": {
    "addr:full":"Salamander St Coffs Harbour NSW 2450",
    "addr:postcode":"2450",
    "addr:street":"Salamander St",
    "iso:country":"AU",
    "sg:address":"Salamander St",
    "sg:city":"Coffs Harbour",
    "sg:classifiers":[
        {
            "category":"Education",
            "subcategory":"School",
            "type":"Public Place"
        }
    ],
    "sg:phone":"+61 2 6652 3355",
    "sg:postcode":"2450",
    "sg:province":"NSW",
    "sg:tags":[
        "state",
        "-",
        "nsw"
    ],
    "wof:name":"Coffs Harbour Public School",
    "wof:placetype":"venue"
},
  "geometry": {"coordinates":[153.12148999999999,-30.302303],"type":"Point"}
}