{
  "type": "Feature",
  "properties": {
    "iso:country":"AU",
    "sg:address":"208 Hall St",
    "sg:city":"Spotswood",
    "sg:classifiers":[
        {
            "category":"Utilities",
            "subcategory":"Electric",
            "type":"Services"
        }
    ],
    "sg:phone":"+61 3 9392 1828",
    "sg:postcode":"3015",
    "sg:province":"VIC",
    "sg:tags":[
        "electrical",
        "contractor"
    ],
    "wof:name":"Solaris Power",
    "wof:placetype":"venue"
},
  "geometry": {"coordinates":[144.88690185600001,-37.8283042908],"type":"Point"}
}