{
  "type": "Feature",
  "properties": {
    "iso:country":"AU",
    "sg:address":"110 Wentworth St",
    "sg:city":"Blackheath",
    "sg:classifiers":[
        {
            "category":"Health Services",
            "subcategory":"Doctor",
            "type":"Services"
        }
    ],
    "sg:phone":"+61 2 4782 3929",
    "sg:postcode":"2785",
    "sg:province":"NSW",
    "sg:tags":[
        "medical",
        "practitioner"
    ],
    "wof:name":"Herborn Katriona Dr",
    "wof:placetype":"venue"
},
  "geometry": {"coordinates":[150.286209106,-33.637298584],"type":"Point"}
}