{
  "type": "Feature",
  "properties": {
    "addr:full":"PO Box 70 Kettering TAS 7155",
    "addr:postcode":"7155",
    "iso:country":"AU",
    "sg:address":"PO Box 70",
    "sg:city":"Kettering",
    "sg:classifiers":[
        {
            "category":"Banks & Credit Unions",
            "subcategory":"Investment Brokerage",
            "type":"Services"
        }
    ],
    "sg:phone":"+61 1300 666 500",
    "sg:postcode":"7155",
    "sg:province":"TAS",
    "sg:tags":[
        "finance",
        "broker"
    ],
    "wof:name":"Workforce Pty Ltd",
    "wof:placetype":"venue"
},
  "geometry": {"coordinates":[147.232254028,-43.1274108887],"type":"Point"}
}