{
  "type": "Feature",
  "properties": {
    "addr:full":"4C Canning St Glenelg North SA 5045",
    "addr:housenumber":"4c",
    "addr:postcode":"5045",
    "addr:street":"Canning St",
    "iso:country":"AU",
    "sg:address":"4C Canning St",
    "sg:city":"Glenelg North",
    "sg:classifiers":[
        {
            "category":"Building & Trades",
            "subcategory":"Construction",
            "type":"Services"
        }
    ],
    "sg:phone":"+61 417 831 931",
    "sg:postcode":"5045",
    "sg:province":"SA",
    "sg:tags":[
        "renovation",
        "alterations",
        "extension",
        "contractor"
    ],
    "wof:name":"Adelaide Building Group Pty Ltd",
    "wof:placetype":"venue"
},
  "geometry": {"coordinates":[138.515106,-34.975391],"type":"Point"}
}