{
  "type": "Feature",
  "properties": {
    "addr:full":"Cnr Victoria & Stephen Sts Bunbury WA 6230",
    "addr:postcode":"6230",
    "addr:street":"Cnr",
    "iso:country":"AU",
    "sg:address":"Cnr Victoria & Stephen Sts",
    "sg:city":"Bunbury",
    "sg:classifiers":[
        {
            "category":"Shopping",
            "subcategory":"Clothing, Apparel, & Fashions",
            "type":"Retail Goods"
        }
    ],
    "sg:phone":"+61 8 9721 2677",
    "sg:postcode":"6230",
    "sg:province":"WA",
    "sg:tags":[
        "menswear"
    ],
    "wof:name":"Mensland",
    "wof:placetype":"venue"
},
  "geometry": {"coordinates":[115.637032,-33.326599],"type":"Point"}
}