{
  "type": "Feature",
  "properties": {
    "iso:country":"AU",
    "sg:address":"Unit 3, 30 Runway Drv",
    "sg:city":"Mudjimba",
    "sg:classifiers":[
        {
            "category":"Retail",
            "subcategory":"Auto Repair",
            "type":"Services"
        }
    ],
    "sg:phone":"+61 7 5448 9222",
    "sg:postcode":"4564",
    "sg:province":"QLD",
    "sg:tags":[
        "transmission",
        "automotive",
        "car"
    ],
    "wof:name":"Miller-Matics",
    "wof:placetype":"venue"
},
  "geometry": {"coordinates":[153.084915161,-26.6072921753],"type":"Point"}
}