{
  "type": "Feature",
  "properties": {
    "iso:country":"AU",
    "sg:address":"Cnr Miles & Grace Sts",
    "sg:city":"Mt Isa",
    "sg:classifiers":[
        {
            "category":"Retail",
            "subcategory":"Auto Repair",
            "type":"Services"
        }
    ],
    "sg:phone":"+61 7 4743 5741",
    "sg:postcode":"4825",
    "sg:province":"QLD",
    "sg:tags":[
        "repairer",
        "motor",
        "engineer"
    ],
    "wof:name":"Grace Miles Mobil Service Centre",
    "wof:placetype":"venue"
},
  "geometry": {"coordinates":[139.481979,-20.73167],"type":"Point"}
}