{
  "type": "Feature",
  "properties": {
    "addr:full":"149 Walcott St Mt Lawley WA 6050",
    "addr:housenumber":"149",
    "addr:postcode":"6050",
    "addr:street":"Walcott St",
    "iso:country":"AU",
    "sg:address":"149 Walcott St",
    "sg:city":"Mt Lawley",
    "sg:classifiers":[
        {
            "category":"Shopping",
            "subcategory":"Clothing, Apparel, & Fashions",
            "type":"Retail Goods"
        }
    ],
    "sg:phone":"+61 8 9227 5607",
    "sg:postcode":"6050",
    "sg:province":"WA",
    "sg:tags":[
        "lady",
        "wear"
    ],
    "sg:website":"http://www.thewardrobe.com.au",
    "wof:name":"The Wardrobe",
    "wof:placetype":"venue"
},
  "geometry": {"coordinates":[115.866996765,-31.9302101135],"type":"Point"}
}