{
  "type": "Feature",
  "properties": {
    "addr:full":"Old Mica Creek Rd Mica Creek QLD 4825",
    "addr:postcode":"4825",
    "addr:street":"Mica Creek Rd",
    "iso:country":"AU",
    "sg:address":"Old Mica Creek Rd",
    "sg:city":"Mica Creek",
    "sg:classifiers":[
        {
            "category":"Home & Garden",
            "subcategory":"Building Materials",
            "type":"Retail Goods"
        }
    ],
    "sg:phone":"+61 7 4743 4999",
    "sg:postcode":"4825",
    "sg:province":"QLD",
    "sg:tags":[
        "pre-mixed",
        "concrete"
    ],
    "wof:name":"Boral",
    "wof:placetype":"venue"
},
  "geometry": {"coordinates":[139.49037170400001,-20.7518291473],"type":"Point"}
}