{
  "type": "Feature",
  "properties": {
    "iso:country":"AU",
    "sg:address":"40 Furlong Rd",
    "sg:city":"Sunshine North",
    "sg:classifiers":[
        {
            "category":"Fast Food",
            "type":"Food & Drink"
        }
    ],
    "sg:phone":"+61 3 9312 5326",
    "sg:postcode":"3020",
    "sg:province":"VIC",
    "sg:tags":[
        "away",
        "take"
    ],
    "wof:name":"Anns Asian Groceries & Takeaway",
    "wof:placetype":"venue"
},
  "geometry": {"coordinates":[144.828522,-37.762192],"type":"Point"}
}