{
  "type": "Feature",
  "properties": {
    "addr:full":"9/ 6 Revelation Cl Tighes Hill NSW 2297",
    "addr:housenumber":"/ 6",
    "addr:postcode":"2297",
    "addr:street":"Revelation Cl",
    "iso:country":"AU",
    "sg:address":"9/ 6",
    "sg:city":"Revelation Cl Tighes Hill",
    "sg:classifiers":[
        {
            "category":"Organizations",
            "subcategory":"Labor Organization",
            "type":"Services"
        }
    ],
    "sg:phone":"+61 2 4961 3606",
    "sg:postcode":"2297",
    "sg:province":"NSW",
    "sg:tags":[
        "dust",
        "fume",
        "control",
        "equipment"
    ],
    "wof:name":"Dustec Australia Pty. Ltd.",
    "wof:placetype":"venue"
},
  "geometry": {"coordinates":[151.755126953,-32.9052505493],"type":"Point"}
}