{
  "type": "Feature",
  "properties": {
    "iso:country":"AU",
    "sg:address":"6 Ritchie St",
    "sg:city":"Rosehill",
    "sg:classifiers":[
        {
            "category":"Building & Trades",
            "subcategory":"Construction",
            "type":"Services"
        }
    ],
    "sg:phone":"+61 2 9637 1864",
    "sg:postcode":"2142",
    "sg:province":"NSW",
    "sg:tags":[
        "window",
        "timber"
    ],
    "wof:name":"Stockwells Joinery Pty Ltd",
    "wof:placetype":"venue"
},
  "geometry": {"coordinates":[151.015335083,-33.8265953064],"type":"Point"}
}