{
  "type": "Feature",
  "properties": {
    "iso:country":"AU",
    "sg:address":"190 Colchester Rd",
    "sg:city":"Kilsyth",
    "sg:classifiers":[
        {
            "category":"Utilities",
            "subcategory":"Natural Gas",
            "type":"Services"
        }
    ],
    "sg:phone":"+61 3 9720 2855",
    "sg:postcode":"3137",
    "sg:province":"VIC",
    "sg:tags":[
        "cylinder",
        "testing"
    ],
    "wof:name":"APA Manufactring Pty Ltd",
    "wof:placetype":"venue"
},
  "geometry": {"coordinates":[145.30331420900001,-37.8272628784],"type":"Point"}
}