{
  "type": "Feature",
  "properties": {
    "addr:full":"7 Teatree Dr South Morang VIC 3752",
    "addr:housenumber":"7",
    "addr:postcode":"3752",
    "addr:street":"Teatree Dr",
    "iso:country":"AU",
    "sg:address":"7 Teatree Dr",
    "sg:city":"South Morang",
    "sg:classifiers":[
        {
            "category":"Utilities",
            "subcategory":"Electric",
            "type":"Services"
        }
    ],
    "sg:phone":"+61 417 575 544",
    "sg:postcode":"3752",
    "sg:province":"VIC",
    "sg:tags":[
        "electrical",
        "contractor"
    ],
    "wof:name":"Damien Reading",
    "wof:placetype":"venue"
},
  "geometry": {"coordinates":[145.099457,-37.654491],"type":"Point"}
}