{
  "type": "Feature",
  "properties": {
    "iso:country":"AU",
    "sg:address":"154 Queens Rd",
    "sg:city":"Canada Bay",
    "sg:classifiers":[
        {
            "category":"Professional",
            "subcategory":"Management & Consulting",
            "type":"Services"
        }
    ],
    "sg:phone":"+61 2 9747 4074",
    "sg:postcode":"2046",
    "sg:province":"NSW",
    "sg:tags":[
        "consultant"
    ],
    "wof:name":"Catherine Lewis",
    "wof:placetype":"venue"
},
  "geometry": {"coordinates":[151.114273,-33.868366],"type":"Point"}
}