{
  "type": "Feature",
  "properties": {
    "addr:full":"2763 Gold Coast Hwy Broadbeach QLD 4218",
    "addr:housenumber":"2763",
    "addr:postcode":"4218",
    "addr:street":"Gold Coast Hwy",
    "iso:country":"AU",
    "sg:address":"2763 Gold Coast Hwy",
    "sg:city":"Broadbeach",
    "sg:classifiers":[
        {
            "category":"Fast Food",
            "type":"Food & Drink"
        }
    ],
    "sg:phone":"+61 7 5539 9933",
    "sg:postcode":"4218",
    "sg:province":"QLD",
    "sg:tags":[
        "away",
        "take"
    ],
    "wof:name":"Donto Sapporo",
    "wof:placetype":"venue"
},
  "geometry": {"coordinates":[153.428924561,-28.023557663],"type":"Point"}
}