{
  "type": "Feature",
  "properties": {
    "addr:full":"26 Welbourn Rd Swan View WA 6056",
    "addr:housenumber":"26",
    "addr:postcode":"6056",
    "addr:street":"Welbourn Rd",
    "iso:country":"AU",
    "sg:address":"26 Welbourn Rd",
    "sg:city":"Swan View",
    "sg:classifiers":[
        {
            "category":"Professional",
            "subcategory":"Computer Services",
            "type":"Services"
        }
    ],
    "sg:phone":"+61 8 9294 1713",
    "sg:postcode":"6056",
    "sg:province":"WA",
    "sg:tags":[
        "consultant",
        "system"
    ],
    "wof:name":"D B Solutions",
    "wof:placetype":"venue"
},
  "geometry": {"coordinates":[116.055488586,-31.889415741],"type":"Point"}
}