{
  "type": "Feature",
  "properties": {
    "addr:full":"4/ 17 Middle St Cleveland QLD 4163",
    "addr:housenumber":"/ 17",
    "addr:postcode":"4163",
    "addr:street":"Middle St",
    "iso:country":"AU",
    "sg:address":"4/ 17 Middle St",
    "sg:city":"Cleveland",
    "sg:classifiers":[
        {
            "category":"Retail",
            "subcategory":"Funeral Services",
            "type":"Services"
        }
    ],
    "sg:phone":"+61 7 3821 4570",
    "sg:postcode":"4163",
    "sg:province":"QLD",
    "sg:tags":[
        "director"
    ],
    "wof:name":"Alex Gow Funerals",
    "wof:placetype":"venue"
},
  "geometry": {"coordinates":[153.26574707,-27.5256557465],"type":"Point"}
}