{
  "type": "Feature",
  "properties": {
    "addr:full":"112 Kelletts Rd Rowville VIC 3178",
    "addr:housenumber":"112",
    "addr:postcode":"3178",
    "addr:street":"Kelletts Rd",
    "iso:country":"AU",
    "sg:address":"112 Kelletts Rd",
    "sg:city":"Rowville",
    "sg:classifiers":[
        {
            "category":"Building & Trades",
            "subcategory":"Construction",
            "type":"Services"
        }
    ],
    "sg:phone":"+61 416 329 208",
    "sg:postcode":"3178",
    "sg:province":"VIC",
    "sg:tags":[
        "concrete",
        "contractor"
    ],
    "wof:name":"Matt Kattle Concreting",
    "wof:placetype":"venue"
},
  "geometry": {"coordinates":[145.24974060100001,-37.9123420715],"type":"Point"}
}