{
  "type": "Feature",
  "properties": {
    "iso:country":"AU",
    "sg:address":"Shop 5, 53 Little St",
    "sg:city":"Coffs Harbour",
    "sg:classifiers":[
        {
            "category":"Home & Garden",
            "subcategory":"Kitchen Supply",
            "type":"Retail Goods"
        }
    ],
    "sg:phone":"+61 2 6652 2511",
    "sg:postcode":"2450",
    "sg:province":"NSW",
    "sg:tags":[
        "photocopying"
    ],
    "wof:name":"Kinninmont Business Machines",
    "wof:placetype":"venue"
},
  "geometry": {"coordinates":[153.113007,-30.298426],"type":"Point"}
}