{
  "type": "Feature",
  "properties": {
    "addr:full":"122a Pittwater Rd Gladesville NSW 2111",
    "addr:housenumber":"122a",
    "addr:postcode":"2111",
    "addr:street":"Pittwater Rd",
    "iso:country":"AU",
    "sg:address":"122a Pittwater Rd",
    "sg:city":"Gladesville",
    "sg:classifiers":[
        {
            "category":"Autos & Motor Vehicles",
            "subcategory":"Boat Sales",
            "type":"Retail Goods"
        }
    ],
    "sg:phone":"+61 2 9879 7749",
    "sg:postcode":"2111",
    "sg:province":"NSW",
    "sg:tags":[
        "builder",
        "yacht",
        "repairer"
    ],
    "wof:name":"Northwind Marine",
    "wof:placetype":"venue"
},
  "geometry": {"coordinates":[151.13343810999999,-33.8230323792],"type":"Point"}
}