{
  "type": "Feature",
  "properties": {
    "addr:full":"Shop 15/16 Glenmore Shopping Village, Cnr Farm St & Bruce Highway North Rockhampton QLD 4701",
    "addr:housenumber":"shop 15 / 16",
    "addr:postcode":"4701",
    "addr:street":"Glenmore;St & Bruce Highway North",
    "iso:country":"AU",
    "sg:address":"Shop 15/16 Glenmore Shopping Village, Cnr Farm St & Bruce Highway",
    "sg:city":"North Rockhampton",
    "sg:classifiers":[
        {
            "category":"Communications",
            "subcategory":"Film & Video Production",
            "type":"Services"
        }
    ],
    "sg:phone":"+61 7 4928 0699",
    "sg:postcode":"4701",
    "sg:province":"QLD",
    "sg:tags":[
        "dvd",
        "library"
    ],
    "wof:name":"Civic Video",
    "wof:placetype":"venue"
},
  "geometry": {"coordinates":[150.52972412099999,-23.3303813934],"type":"Point"}
}