{
  "type": "Feature",
  "properties": {
    "addr:full":"8 Mortimer St Drysdale VIC 3222",
    "addr:housenumber":"8",
    "addr:postcode":"3222",
    "addr:street":"Mortimer St",
    "iso:country":"AU",
    "sg:address":"8 Mortimer St",
    "sg:city":"Drysdale",
    "sg:classifiers":[
        {
            "category":"Organizations",
            "subcategory":"Community Association",
            "type":"Services"
        }
    ],
    "sg:phone":"+61 3 5251 2475",
    "sg:postcode":"3222",
    "sg:province":"VIC",
    "sg:tags":[
        "organisation",
        "family",
        "welfare"
    ],
    "wof:name":"Salvation Army The",
    "wof:placetype":"venue"
},
  "geometry": {"coordinates":[144.575211,-38.173862],"type":"Point"}
}