{
  "type": "Feature",
  "properties": {
    "addr:full":"25 Bridge St Murray Bridge SA 5253",
    "addr:housenumber":"25",
    "addr:postcode":"5253",
    "addr:street":"Bridge St",
    "iso:country":"AU",
    "sg:address":"25 Bridge St",
    "sg:city":"Murray Bridge",
    "sg:classifiers":[
        {
            "category":"Shopping",
            "subcategory":"Jewelry",
            "type":"Retail Goods"
        }
    ],
    "sg:phone":"+61 8 8532 2408",
    "sg:postcode":"5253",
    "sg:province":"SA",
    "sg:tags":[
        "jeweller"
    ],
    "wof:name":"Murray Harvy Jewellers",
    "wof:placetype":"venue"
},
  "geometry": {"coordinates":[139.276153564,-35.1184654236],"type":"Point"}
}