{
  "type": "Feature",
  "properties": {
    "iso:country":"AU",
    "sg:address":"48 Tainton St",
    "sg:city":"Clontarf",
    "sg:classifiers":[
        {
            "category":"Travel",
            "subcategory":"Hostel",
            "type":"Entertainment"
        }
    ],
    "sg:phone":"+61 7 3284 0955",
    "sg:postcode":"4019",
    "sg:province":"QLD",
    "sg:tags":[
        "home"
    ],
    "wof:name":"Ozanam Villa",
    "wof:placetype":"venue"
},
  "geometry": {"coordinates":[153.09434509299999,-27.2491226196],"type":"Point"}
}