{
  "type": "Feature",
  "properties": {
    "addr:full":"15 Male St Brighton VIC 3186",
    "addr:housenumber":"15",
    "addr:postcode":"3186",
    "addr:street":"Male St",
    "iso:country":"AU",
    "sg:address":"15 Male St",
    "sg:city":"Brighton",
    "sg:classifiers":[
        {
            "category":"Education",
            "subcategory":"Dance Studio",
            "type":"Public Place"
        }
    ],
    "sg:phone":"+61 3 9592 8158",
    "sg:postcode":"3186",
    "sg:province":"VIC",
    "sg:tags":[
        "venue",
        "tuition"
    ],
    "sg:website":"http://www.letsgodance.com.au",
    "wof:name":"Let's Go Dance",
    "wof:placetype":"venue"
},
  "geometry": {"coordinates":[144.99688720699999,-37.9156265259],"type":"Point"}
}