{
  "type": "Feature",
  "properties": {
    "addr:full":"Londonderry Rd Londonderry NSW 2753",
    "addr:postcode":"2753",
    "addr:street":"Londonderry Rd",
    "iso:country":"AU",
    "sg:address":"Londonderry Rd",
    "sg:city":"Londonderry",
    "sg:classifiers":[
        {
            "category":"Food & Beverages",
            "subcategory":"Liquor & Beverages",
            "type":"Retail Goods"
        }
    ],
    "sg:phone":"+61 2 4578 2232",
    "sg:postcode":"2753",
    "sg:province":"NSW",
    "sg:tags":[
        "store"
    ],
    "wof:name":"Londonderry Liquor Store",
    "wof:placetype":"venue"
},
  "geometry": {"coordinates":[150.73565673799999,-33.6455497742],"type":"Point"}
}