{
  "type": "Feature",
  "properties": {
    "addr:full":"129 Main Rd Ballarat VIC 3350",
    "addr:housenumber":"129",
    "addr:postcode":"3350",
    "addr:street":"Main Rd",
    "iso:country":"AU",
    "sg:address":"129 Main Rd",
    "sg:city":"Ballarat",
    "sg:classifiers":[
        {
            "category":"Autos & Motor Vehicles",
            "subcategory":"Fuel & Gas Station",
            "type":"Retail Goods"
        }
    ],
    "sg:phone":"+61 3 5332 1130",
    "sg:postcode":"3350",
    "sg:province":"VIC",
    "wof:name":"Mobil Oil Australia Pty Ltd",
    "wof:placetype":"venue"
},
  "geometry": {"coordinates":[143.868561,-37.566734],"type":"Point"}
}