{
  "type": "Feature",
  "properties": {
    "iso:country":"AU",
    "sg:address":"Immerse Vineyard 1548",
    "sg:city":"Melba Hwy, Yarra Valley Dixons Creek",
    "sg:classifiers":[
        {
            "category":"Personal",
            "subcategory":"Massage",
            "type":"Services"
        }
    ],
    "sg:phone":"+61 3 5965 2500",
    "sg:postcode":"3775",
    "sg:province":"VIC",
    "sg:tags":[
        "therapy"
    ],
    "wof:name":"Indulge Spa Retreat",
    "wof:placetype":"venue"
},
  "geometry": {"coordinates":[145.413498,-37.61256],"type":"Point"}
}