{
  "type": "Feature",
  "properties": {
    "iso:country":"AU",
    "sg:address":"284 Anzac Hwy",
    "sg:city":"Plympton",
    "sg:classifiers":[
        {
            "category":"Retail",
            "subcategory":"Veterinary Services",
            "type":"Services"
        }
    ],
    "sg:phone":"+61 8 8293 6855",
    "sg:postcode":"5038",
    "sg:province":"SA",
    "sg:tags":[
        "surgeon"
    ],
    "wof:name":"Abacare Vet Services",
    "wof:placetype":"venue"
},
  "geometry": {"coordinates":[138.555450439,-34.9638442993],"type":"Point"}
}