{
  "type": "Feature",
  "properties": {
    "addr:full":"123 Hogan St Tatura VIC 3616",
    "addr:housenumber":"123",
    "addr:postcode":"3616",
    "addr:street":"Hogan St",
    "iso:country":"AU",
    "sg:address":"123 Hogan St",
    "sg:city":"Tatura",
    "sg:classifiers":[
        {
            "category":"Shopping",
            "subcategory":"Clothing, Apparel, & Fashions",
            "type":"Retail Goods"
        }
    ],
    "sg:phone":"+61 3 5824 1100",
    "sg:postcode":"3616",
    "sg:province":"VIC",
    "sg:tags":[
        "lady",
        "wear"
    ],
    "wof:name":"Mozaik",
    "wof:placetype":"venue"
},
  "geometry": {"coordinates":[145.22715759299999,-36.4399757385],"type":"Point"}
}