{
  "type": "Feature",
  "properties": {
    "iso:country":"AU",
    "sg:address":"Unit 4/ 2 Spanns Rd",
    "sg:city":"Beenleigh",
    "sg:classifiers":[
        {
            "category":"Home & Garden",
            "subcategory":"Hardware",
            "type":"Retail Goods"
        }
    ],
    "sg:phone":"+61 7 3807 7799",
    "sg:postcode":"4207",
    "sg:province":"QLD",
    "sg:tags":[
        "plumber",
        "supply"
    ],
    "wof:name":"Queensland Plumbers Supplies",
    "wof:placetype":"venue"
},
  "geometry": {"coordinates":[153.18838500999999,-27.7127532959],"type":"Point"}
}