{
  "type": "Feature",
  "properties": {
    "addr:full":"81 Frobisher (at rear) St Osborne Park WA 6017",
    "addr:housenumber":"81",
    "addr:postcode":"6017",
    "addr:street":"St",
    "iso:country":"AU",
    "sg:address":"81 Frobisher (at rear) St",
    "sg:city":"Osborne Park",
    "sg:classifiers":[
        {
            "category":"Building & Trades",
            "subcategory":"Equipment Rental",
            "type":"Services"
        }
    ],
    "sg:phone":"+61 8 9444 6836",
    "sg:postcode":"6017",
    "sg:province":"WA",
    "sg:tags":[
        "supply",
        "catering"
    ],
    "wof:name":"European Wood Fired Ovens",
    "wof:placetype":"venue"
},
  "geometry": {"coordinates":[115.81926727299999,-31.9064693451],"type":"Point"}
}