{
  "type": "Feature",
  "properties": {
    "iso:country":"AU",
    "sg:address":"Factory 6/ 21 Yiannis St",
    "sg:city":"Springvale",
    "sg:classifiers":[
        {
            "category":"Utilities",
            "subcategory":"Fuel Oil & Lpg",
            "type":"Services"
        }
    ],
    "sg:phone":"+61 417 129 545",
    "sg:postcode":"3171",
    "sg:province":"VIC",
    "sg:tags":[
        "charcoal"
    ],
    "wof:name":"John Tiras Pty Ltd",
    "wof:placetype":"venue"
},
  "geometry": {"coordinates":[145.14381408700001,-37.9334945679],"type":"Point"}
}