{
  "type": "Feature",
  "properties": {
    "addr:full":"6 Ballarat St Brunswick VIC 3056",
    "addr:housenumber":"6",
    "addr:postcode":"3056",
    "addr:street":"Ballarat St",
    "iso:country":"AU",
    "sg:address":"6 Ballarat St",
    "sg:city":"Brunswick",
    "sg:classifiers":[
        {
            "category":"Industrial Area",
            "type":"Public Place"
        }
    ],
    "sg:phone":"+61 3 9381 2588",
    "sg:postcode":"3056",
    "sg:province":"VIC",
    "sg:tags":[
        "protective",
        "clothing"
    ],
    "wof:name":"Hi-Viz Safety Wear",
    "wof:placetype":"venue"
},
  "geometry": {"coordinates":[144.96136474599999,-37.7658348083],"type":"Point"}
}