{
  "type": "Feature",
  "properties": {
    "addr:full":"32 Cross Rd Myrtle Bank SA 5064",
    "addr:housenumber":"32",
    "addr:postcode":"5064",
    "addr:street":"Cross Rd",
    "iso:country":"AU",
    "sg:address":"32 Cross Rd",
    "sg:city":"Myrtle Bank",
    "sg:classifiers":[
        {
            "category":"Health Services",
            "subcategory":"Nursing And Care Facility",
            "type":"Services"
        }
    ],
    "sg:phone":"+61 8 8338 2110",
    "sg:postcode":"5064",
    "sg:province":"SA",
    "sg:tags":[
        "home"
    ],
    "wof:name":"Ridge Park Health Care Centre",
    "wof:placetype":"venue"
},
  "geometry": {"coordinates":[138.635864258,-34.9639434814],"type":"Point"}
}