{
  "type": "Feature",
  "properties": {
    "iso:country":"AU",
    "sg:address":"4/ 164 Gladstone St",
    "sg:city":"Fyshwick",
    "sg:classifiers":[
        {
            "category":"Mining & Drilling",
            "type":"Manufacturing & Wholesale Goods"
        }
    ],
    "sg:phone":"+61 2 6280 4666",
    "sg:postcode":"2609",
    "sg:province":"ACT",
    "sg:tags":[
        "concrete",
        "breaking",
        "grinding",
        "sawing"
    ],
    "wof:name":"Condrill",
    "wof:placetype":"venue"
},
  "geometry": {"coordinates":[149.18486023,-35.3277740479],"type":"Point"}
}