{
  "type": "Feature",
  "properties": {
    "iso:country":"AU",
    "sg:address":"284 Settlement Rd",
    "sg:city":"Thomastown",
    "sg:classifiers":[
        {
            "category":"Wholesale",
            "subcategory":"Machinery & Supplies",
            "type":"Manufacturing & Wholesale Goods"
        }
    ],
    "sg:phone":"+61 3 9466 2666",
    "sg:postcode":"3074",
    "sg:province":"VIC",
    "sg:tags":[
        "equipment",
        "hydraulic"
    ],
    "wof:name":"Pirtek",
    "wof:placetype":"venue"
},
  "geometry": {"coordinates":[145.029052734,-37.6907730103],"type":"Point"}
}