{
  "type": "Feature",
  "properties": {
    "addr:full":"96 Victoria St West End (Brisbane) QLD 4101",
    "addr:housenumber":"96",
    "addr:postcode":"4101",
    "addr:street":"Victoria St",
    "iso:country":"AU",
    "sg:address":"96 Victoria St",
    "sg:city":"West End (Brisbane)",
    "sg:classifiers":[
        {
            "category":"Building & Trades",
            "subcategory":"Construction",
            "type":"Services"
        }
    ],
    "sg:phone":"+61 7 3844 5900",
    "sg:postcode":"4101",
    "sg:province":"QLD",
    "sg:tags":[
        "management"
    ],
    "wof:name":"Baseline Consulting Pty Ltd",
    "wof:placetype":"venue"
},
  "geometry": {"coordinates":[153.00302124000001,-27.4824466705],"type":"Point"}
}