{
  "type": "Feature",
  "properties": {
    "addr:full":"Shp4/ 42 Rankin St Innisfail QLD 4860",
    "addr:housenumber":"42",
    "addr:postcode":"4860",
    "addr:street":"Rankin St",
    "iso:country":"AU",
    "sg:address":"Shp4/ 42 Rankin St",
    "sg:city":"Innisfail",
    "sg:classifiers":[
        {
            "category":"Professional",
            "subcategory":"Employment Agencies",
            "type":"Services"
        }
    ],
    "sg:phone":"+61 7 4061 3524",
    "sg:postcode":"4860",
    "sg:province":"QLD",
    "wof:name":"Indigenous Job Connections",
    "wof:placetype":"venue"
},
  "geometry": {"coordinates":[146.03086852999999,-17.5236263275],"type":"Point"}
}