{
  "type": "Feature",
  "properties": {
    "iso:country":"AU",
    "sg:address":"Yarrawonga Rd",
    "sg:city":"Wangaratta",
    "sg:classifiers":[
        {
            "category":"Utilities",
            "subcategory":"Electric",
            "type":"Services"
        }
    ],
    "sg:phone":"+61 3 5721 6666",
    "sg:postcode":"3677",
    "sg:province":"VIC",
    "sg:tags":[
        "electrical",
        "contractor"
    ],
    "wof:name":"Anderson Allan D",
    "wof:placetype":"venue"
},
  "geometry": {"coordinates":[146.318527222,-36.3704109192],"type":"Point"}
}