{
  "type": "Feature",
  "properties": {
    "addr:full":"PO Box 142 Keilor VIC 3036",
    "addr:postcode":"3036",
    "iso:country":"AU",
    "sg:address":"PO Box 142",
    "sg:city":"Keilor",
    "sg:classifiers":[
        {
            "category":"Professional",
            "subcategory":"Employment Agencies",
            "type":"Services"
        }
    ],
    "sg:phone":"+61 3 9310 9166",
    "sg:postcode":"3036",
    "sg:province":"VIC",
    "wof:name":"Resume Service Victoria (Essendon/Keilor) Pty Ltd",
    "wof:placetype":"venue"
},
  "geometry": {"coordinates":[144.830963,-37.717381],"type":"Point"}
}