{
  "type": "Feature",
  "properties": {
    "addr:full":"Unit 12, 92A Mona Vale Road (off Daydream street) Warriewood NSW 2102",
    "addr:housenumber":"92a",
    "addr:postcode":"2102",
    "addr:street":"Mona Vale Road Off Daydream Street",
    "iso:country":"AU",
    "sg:address":"Unit 12, 92A Mona Vale Road (off Daydream street)",
    "sg:city":"Warriewood",
    "sg:classifiers":[
        {
            "category":"Shopping",
            "subcategory":"Event Tickets",
            "type":"Retail Goods"
        }
    ],
    "sg:phone":"+61 2 9997 3820",
    "sg:postcode":"2102",
    "sg:province":"NSW",
    "sg:tags":[
        "wholesaler",
        "mfrs",
        "towel"
    ],
    "sg:website":"http://www.blueswimmergroup.com",
    "wof:name":"Blue Swimmer Towels",
    "wof:placetype":"venue"
},
  "geometry": {"coordinates":[151.28919999999999,-33.676109],"type":"Point"}
}