{
  "type": "Feature",
  "properties": {
    "addr:full":"2 Sunset Ave Olinda VIC 3788",
    "addr:housenumber":"2",
    "addr:postcode":"3788",
    "addr:street":"Sunset Ave",
    "iso:country":"AU",
    "sg:address":"2 Sunset Ave",
    "sg:city":"Olinda",
    "sg:classifiers":[
        {
            "category":"Building & Trades",
            "subcategory":"Construction",
            "type":"Services"
        }
    ],
    "sg:phone":"+61 3 9751 2755",
    "sg:postcode":"3788",
    "sg:province":"VIC",
    "sg:tags":[
        "spouting",
        "guttering"
    ],
    "wof:name":"Polymesh Australasia Group Pty Ltd",
    "wof:placetype":"venue"
},
  "geometry": {"coordinates":[145.360703,-37.848843],"type":"Point"}
}