{
  "type": "Feature",
  "properties": {
    "addr:full":"74 Main St Derby TAS 7264",
    "addr:housenumber":"74",
    "addr:postcode":"7264",
    "addr:street":"Main St",
    "iso:country":"AU",
    "sg:address":"74 Main St",
    "sg:city":"Derby",
    "sg:classifiers":[
        {
            "category":"Fast Food",
            "type":"Food & Drink"
        }
    ],
    "sg:phone":"+61 3 6354 2338",
    "sg:postcode":"7264",
    "sg:province":"TAS",
    "sg:tags":[
        "away",
        "take"
    ],
    "wof:name":"Derby General Store",
    "wof:placetype":"venue"
},
  "geometry": {"coordinates":[147.80174299999999,-41.148945],"type":"Point"}
}