{
  "type": "Feature",
  "properties": {
    "iso:country":"AU",
    "sg:address":"131 Mascoma St",
    "sg:city":"Strathmore",
    "sg:classifiers":[
        {
            "category":"Professional",
            "subcategory":"Art Services",
            "type":"Services"
        }
    ],
    "sg:phone":"+61 3 9382 0791",
    "sg:postcode":"3041",
    "sg:province":"VIC",
    "sg:tags":[
        "graphic",
        "designer"
    ],
    "wof:name":"Design Savy",
    "wof:placetype":"venue"
},
  "geometry": {"coordinates":[144.914672852,-37.7239494324],"type":"Point"}
}