{
  "type": "Feature",
  "properties": {
    "iso:country":"AU",
    "sg:address":"14 Fiveash Drv",
    "sg:city":"Pasadena",
    "sg:classifiers":[
        {
            "category":"Fast Food",
            "type":"Food & Drink"
        }
    ],
    "sg:phone":"+61 8 8277 5273",
    "sg:postcode":"5042",
    "sg:province":"SA",
    "sg:tags":[
        "away",
        "take"
    ],
    "wof:name":"Subway",
    "wof:placetype":"venue"
},
  "geometry": {"coordinates":[138.59120200000001,-35.000916],"type":"Point"}
}