{
  "type": "Feature",
  "properties": {
    "addr:full":"8 Gordon St Cranbourne VIC 3977",
    "addr:housenumber":"8",
    "addr:postcode":"3977",
    "addr:street":"Gordon St",
    "iso:country":"AU",
    "sg:address":"8 Gordon St",
    "sg:city":"Cranbourne",
    "sg:classifiers":[
        {
            "category":"Wholesale",
            "subcategory":"Construction Materials",
            "type":"Manufacturing & Wholesale Goods"
        }
    ],
    "sg:phone":"+61 3 5995 3593",
    "sg:postcode":"3977",
    "sg:province":"VIC",
    "sg:tags":[
        "wholesaler",
        "equipment",
        "bathroom",
        "mfrs",
        "accessory"
    ],
    "wof:name":"Aust-China Importer",
    "wof:placetype":"venue"
},
  "geometry": {"coordinates":[145.28782653799999,-38.1053161621],"type":"Point"}
}