{
  "type": "Feature",
  "properties": {
    "addr:full":"2 Lynton St Upper Mt Gravatt QLD 4122",
    "addr:housenumber":"2",
    "addr:postcode":"4122",
    "addr:street":"Lynton St",
    "iso:country":"AU",
    "sg:address":"2 Lynton St",
    "sg:city":"Upper Mt Gravatt",
    "sg:classifiers":[
        {
            "category":"Health Services",
            "subcategory":"Doctor",
            "type":"Services"
        }
    ],
    "sg:phone":"+61 7 3849 6128",
    "sg:postcode":"4122",
    "sg:province":"QLD",
    "sg:tags":[
        "medical",
        "practitioner"
    ],
    "wof:name":"Wishart Road Family Medical Practice",
    "wof:placetype":"venue"
},
  "geometry": {"coordinates":[153.08213806099999,-27.5457324982],"type":"Point"}
}