{
  "type": "Feature",
  "properties": {
    "addr:full":"Ebert St Coolbellup WA 6163",
    "addr:postcode":"6163",
    "addr:street":"Ebert St",
    "iso:country":"AU",
    "sg:address":"Ebert St",
    "sg:city":"Coolbellup",
    "sg:classifiers":[
        {
            "category":"Education",
            "subcategory":"School",
            "type":"Public Place"
        }
    ],
    "sg:phone":"+61 8 9337 1263",
    "sg:postcode":"6163",
    "sg:province":"WA",
    "sg:tags":[
        "state",
        "except",
        "nsw"
    ],
    "wof:name":"Coolbellup Pre-Primary",
    "wof:placetype":"venue"
},
  "geometry": {"coordinates":[115.80229199999999,-32.077969],"type":"Point"}
}