{
  "type": "Feature",
  "properties": {
    "addr:full":"11 Mary St Hindmarsh SA 5007",
    "addr:housenumber":"11",
    "addr:postcode":"5007",
    "addr:street":"Mary St",
    "iso:country":"AU",
    "sg:address":"11 Mary St",
    "sg:city":"Hindmarsh",
    "sg:classifiers":[
        {
            "category":"Retail",
            "subcategory":"Auto Repair",
            "type":"Services"
        }
    ],
    "sg:phone":"+61 8 8340 3321",
    "sg:postcode":"5007",
    "sg:province":"SA",
    "sg:tags":[
        "repairer",
        "motor",
        "engineer"
    ],
    "wof:name":"Pitstop Service Centre",
    "wof:placetype":"venue"
},
  "geometry": {"coordinates":[138.572021484,-34.9077377319],"type":"Point"}
}