{
  "type": "Feature",
  "properties": {
    "addr:full":"1/ 16 Superior Drv Dandenong VIC 3175",
    "addr:housenumber":"/ 16",
    "addr:postcode":"3175",
    "addr:street":"Superior Drv",
    "iso:country":"AU",
    "sg:address":"1/ 16 Superior Drv",
    "sg:city":"Dandenong",
    "sg:classifiers":[
        {
            "category":"Autos & Motor Vehicles",
            "subcategory":"Auto Supplies",
            "type":"Retail Goods"
        }
    ],
    "sg:phone":"+61 431 404 472",
    "sg:postcode":"3175",
    "sg:province":"VIC",
    "sg:tags":[
        "accessory"
    ],
    "wof:name":"Ultimate Auto Trim",
    "wof:placetype":"venue"
},
  "geometry": {"coordinates":[145.20423889200001,-38.0325126648],"type":"Point"}
}