{
  "type": "Feature",
  "properties": {
    "iso:country":"AU",
    "sg:address":"Unit 2 / 23 Dudley St",
    "sg:city":"Eltham",
    "sg:classifiers":[
        {
            "category":"Wholesale",
            "subcategory":"Metals & Minerals",
            "type":"Manufacturing & Wholesale Goods"
        }
    ],
    "sg:phone":"+61 3 9439 1822",
    "sg:postcode":"3095",
    "sg:province":"VIC",
    "sg:tags":[
        "steel",
        "stainless",
        "product",
        "equipment"
    ],
    "wof:name":"Mariljohn Pty Ltd",
    "wof:placetype":"venue"
},
  "geometry": {"coordinates":[145.150512695,-37.7157669067],"type":"Point"}
}