{
  "type": "Feature",
  "properties": {
    "addr:full":"47 Mandolong Rd Mosman NSW 2088",
    "addr:housenumber":"47",
    "addr:postcode":"2088",
    "addr:street":"Mandolong Rd",
    "iso:country":"AU",
    "sg:address":"47 Mandolong Rd",
    "sg:city":"Mosman",
    "sg:classifiers":[
        {
            "category":"Education",
            "subcategory":"School",
            "type":"Public Place"
        }
    ],
    "sg:phone":"+61 2 8968 7777",
    "sg:postcode":"2088",
    "sg:province":"NSW",
    "sg:tags":[
        "girl"
    ],
    "wof:name":"Queenwood School For Girls Senior",
    "wof:placetype":"venue"
},
  "geometry": {"coordinates":[151.24856567399999,-33.8237037659],"type":"Point"}
}