{
  "type": "Feature",
  "properties": {
    "addr:full":"10 Sunshine Beach Rd Noosa Junction QLD 4567",
    "addr:housenumber":"10",
    "addr:postcode":"4567",
    "addr:street":"Sunshine Beach Rd",
    "iso:country":"AU",
    "sg:address":"10 Sunshine Beach Rd",
    "sg:city":"Noosa Junction",
    "sg:classifiers":[
        {
            "category":"Banks & Credit Unions",
            "subcategory":"Bank",
            "type":"Services"
        }
    ],
    "sg:phone":"+61 13 20 32",
    "sg:postcode":"4567",
    "sg:province":"QLD",
    "wof:name":"Westpac",
    "wof:placetype":"venue"
},
  "geometry": {"coordinates":[153.09146118199999,-26.3977680206],"type":"Point"}
}