{
  "type": "Feature",
  "properties": {
    "iso:country":"AU",
    "sg:address":"Suite 1/ Rear 8 Unley Rd",
    "sg:city":"Unley",
    "sg:classifiers":[
        {
            "category":"Professional",
            "subcategory":"Business Services",
            "type":"Services"
        }
    ],
    "sg:phone":"+61 408 514 007",
    "sg:postcode":"5061",
    "sg:province":"SA",
    "sg:tags":[
        "fashion",
        "agent"
    ],
    "wof:name":"Kim Montgomery Agencies",
    "wof:placetype":"venue"
},
  "geometry": {"coordinates":[138.60661315900001,-34.9411048889],"type":"Point"}
}