{
  "type": "Feature",
  "properties": {
    "iso:country":"AU",
    "sg:address":"1 Tina Ave",
    "sg:city":"Springwood",
    "sg:classifiers":[
        {
            "category":"Banks & Credit Unions",
            "subcategory":"Bank",
            "type":"Services"
        }
    ],
    "sg:phone":"+61 7 3442 8888",
    "sg:postcode":"4127",
    "sg:province":"QLD",
    "sg:tags":[
        "broker",
        "mortgage"
    ],
    "wof:name":"Australian Heritage Financial Group Pty",
    "wof:placetype":"venue"
},
  "geometry": {"coordinates":[153.12828064000001,-27.6137466431],"type":"Point"}
}