{
  "type": "Feature",
  "properties": {
    "addr:full":"Unit 3/ 185 Port Hacking Rd Miranda NSW 2228",
    "addr:housenumber":"/ 185",
    "addr:postcode":"2228",
    "addr:street":"Port Hacking Rd",
    "iso:country":"AU",
    "sg:address":"Unit 3/ 185 Port Hacking Rd",
    "sg:city":"Miranda",
    "sg:classifiers":[
        {
            "category":"Building & Trades",
            "subcategory":"Construction",
            "type":"Services"
        }
    ],
    "sg:phone":"+61 2 9544 8881",
    "sg:postcode":"2228",
    "sg:province":"NSW",
    "sg:tags":[
        "contractor"
    ],
    "wof:name":"Hutchison & Quigley (Constructions) Pty Ltd",
    "wof:placetype":"venue"
},
  "geometry": {"coordinates":[151.10662841800001,-34.0244178772],"type":"Point"}
}