{
  "type": "Feature",
  "properties": {
    "iso:country":"AU",
    "sg:address":"23 Sterling Rd",
    "sg:city":"Minchinbury",
    "sg:classifiers":[
        {
            "category":"Home & Garden",
            "subcategory":"Hardware",
            "type":"Retail Goods"
        }
    ],
    "sg:phone":"+61 2 9677 2619",
    "sg:postcode":"2770",
    "sg:province":"NSW",
    "sg:tags":[
        "plumber",
        "supply"
    ],
    "wof:name":"Romwood Pty Ltd",
    "wof:placetype":"venue"
},
  "geometry": {"coordinates":[150.818267822,-33.7824783325],"type":"Point"}
}