{
  "type": "Feature",
  "properties": {
    "iso:country":"AU",
    "sg:address":"54 McLachlan Ave",
    "sg:city":"Rushcutters Bay",
    "sg:classifiers":[
        {
            "category":"Manufacturing",
            "subcategory":"Motor Vehicles & Parts",
            "type":"Manufacturing & Wholesale Goods"
        }
    ],
    "sg:phone":"+61 2 9360 2611",
    "sg:postcode":"2011",
    "sg:province":"NSW",
    "sg:tags":[
        "replacement"
    ],
    "wof:name":"Larke Hoskins Pty Ltd",
    "wof:placetype":"venue"
},
  "geometry": {"coordinates":[151.228607178,-33.8764648438],"type":"Point"}
}