{
  "type": "Feature",
  "properties": {
    "iso:country":"AU",
    "sg:address":"80 Gibson Ave",
    "sg:city":"Padstow",
    "sg:classifiers":[
        {
            "category":"Retail",
            "subcategory":"Auto Repair",
            "type":"Services"
        }
    ],
    "sg:phone":"+61 2 9774 3366",
    "sg:postcode":"2211",
    "sg:province":"NSW",
    "sg:tags":[
        "engine",
        "reconditioning"
    ],
    "wof:name":"Mini Car Clinic Pty Ltd",
    "wof:placetype":"venue"
},
  "geometry": {"coordinates":[151.027954,-33.941177],"type":"Point"}
}