{
  "type": "Feature",
  "properties": {
    "addr:full":"36 Sapphire St Springfield QLD 4300",
    "addr:housenumber":"36",
    "addr:postcode":"4300",
    "addr:street":"Sapphire St",
    "iso:country":"AU",
    "sg:address":"36 Sapphire St",
    "sg:city":"Springfield",
    "sg:classifiers":[
        {
            "category":"Social Services",
            "subcategory":"Child Care",
            "type":"Services"
        }
    ],
    "sg:phone":"+61 7 3818 2900",
    "sg:postcode":"4300",
    "sg:province":"QLD",
    "wof:name":"Springfield Children's Development Centre",
    "wof:placetype":"venue"
},
  "geometry": {"coordinates":[152.91717529300001,-27.6510639191],"type":"Point"}
}