{
  "type": "Feature",
  "properties": {
    "addr:full":"66 Pritchard Rd Virginia QLD 4014",
    "addr:housenumber":"66",
    "addr:postcode":"4014",
    "addr:street":"Pritchard Rd",
    "iso:country":"AU",
    "sg:address":"66 Pritchard Rd",
    "sg:city":"Virginia",
    "sg:classifiers":[
        {
            "category":"Wholesale",
            "subcategory":"Metals & Minerals",
            "type":"Manufacturing & Wholesale Goods"
        }
    ],
    "sg:phone":"+61 7 3865 1588",
    "sg:postcode":"4014",
    "sg:province":"QLD",
    "sg:tags":[
        "steel",
        "stainless",
        "product",
        "equipment"
    ],
    "wof:name":"Austain Fasteners Pty. Ltd.",
    "wof:placetype":"venue"
},
  "geometry": {"coordinates":[153.058029175,-27.3740100861],"type":"Point"}
}