{
  "type": "Feature",
  "properties": {
    "iso:country":"AU",
    "sg:address":"113 Shellharbour Rd",
    "sg:city":"Windang",
    "sg:classifiers":[
        {
            "category":"Building & Trades",
            "subcategory":"Locksmith",
            "type":"Services"
        }
    ],
    "sg:phone":"+61 2 4297 1686",
    "sg:postcode":"2528",
    "sg:province":"NSW",
    "sg:tags":[
        "strongroom",
        "safe",
        "door"
    ],
    "wof:name":"MacArthur Locksmiths (NSW) Pty Ltd.",
    "wof:placetype":"venue"
},
  "geometry": {"coordinates":[150.86036682100001,-34.551612854],"type":"Point"}
}