{
  "type": "Feature",
  "properties": {
    "addr:full":"66 Peverett La Oakford WA 6121",
    "addr:housenumber":"66",
    "addr:postcode":"6121",
    "addr:street":"Peverett La",
    "iso:country":"AU",
    "sg:address":"66 Peverett La",
    "sg:city":"Oakford",
    "sg:classifiers":[
        {
            "category":"Farming",
            "subcategory":"Farm",
            "type":"Manufacturing & Wholesale Goods"
        }
    ],
    "sg:phone":"+61 8 9525 1228",
    "sg:postcode":"6121",
    "sg:province":"WA",
    "sg:tags":[
        "farmer"
    ],
    "wof:name":"Genovesi P & G",
    "wof:placetype":"venue"
},
  "geometry": {"coordinates":[115.93665313699999,-32.2076148987],"type":"Point"}
}