{
  "type": "Feature",
  "properties": {
    "iso:country":"AU",
    "sg:address":"16- 18 Doyle Ave",
    "sg:city":"Unanderra",
    "sg:classifiers":[
        {
            "category":"Banks & Credit Unions",
            "subcategory":"Financial Services",
            "type":"Services"
        }
    ],
    "sg:phone":"+61 2 4260 7777",
    "sg:postcode":"2526",
    "sg:province":"NSW",
    "sg:tags":[
        "wholesaler",
        "mfrs",
        "gear"
    ],
    "wof:name":"C & M Leussink Engineering Pty Ltd",
    "wof:placetype":"venue"
},
  "geometry": {"coordinates":[150.84016418499999,-34.465637207],"type":"Point"}
}