{
  "type": "Feature",
  "properties": {
    "iso:country":"AU",
    "sg:address":"U2/ 77 Lindsay St",
    "sg:city":"Hawthorne",
    "sg:classifiers":[
        {
            "category":"Professional",
            "subcategory":"Management & Consulting",
            "type":"Services"
        }
    ],
    "sg:phone":"+61 7 3899 5223",
    "sg:postcode":"4171",
    "sg:province":"QLD",
    "sg:tags":[
        "consultant"
    ],
    "wof:name":"Venturepro Pty Ltd",
    "wof:placetype":"venue"
},
  "geometry": {"coordinates":[153.05630493199999,-27.4612693787],"type":"Point"}
}