{
  "type": "Feature",
  "properties": {
    "iso:country":"AU",
    "sg:address":"Stokers Rd",
    "sg:city":"Dunbible",
    "sg:classifiers":[
        {
            "category":"Manufacturing",
            "subcategory":"Lumber",
            "type":"Manufacturing & Wholesale Goods"
        }
    ],
    "sg:phone":"+61 2 6672 2510",
    "sg:postcode":"2484",
    "sg:province":"NSW",
    "sg:tags":[
        "sawmillers"
    ],
    "wof:name":"Australian Woodworks",
    "wof:placetype":"venue"
},
  "geometry": {"coordinates":[153.38995361299999,-28.3691329956],"type":"Point"}
}