{
  "type": "Feature",
  "properties": {
    "addr:full":"Unit 3, 6 Carbine Cl Maryland NSW 2287",
    "addr:housenumber":"6",
    "addr:postcode":"2287",
    "addr:street":"Carbine Cl",
    "iso:country":"AU",
    "sg:address":"Unit 3, 6",
    "sg:city":"Carbine Cl Maryland",
    "sg:classifiers":[
        {
            "category":"Autos & Motor Vehicles",
            "subcategory":"Motorcycle Sales",
            "type":"Retail Goods"
        }
    ],
    "sg:phone":"+61 2 4950 2444",
    "sg:postcode":"2287",
    "sg:province":"NSW",
    "sg:tags":[
        "part",
        "recyclers",
        "cycle"
    ],
    "wof:name":"The Wreckery Motorcycle Wreckers",
    "wof:placetype":"venue"
},
  "geometry": {"coordinates":[151.66252136200001,-32.8816184998],"type":"Point"}
}