{
  "type": "Feature",
  "properties": {
    "addr:full":"324 Wantirna Rd Wantirna VIC 3152",
    "addr:housenumber":"324",
    "addr:postcode":"3152",
    "addr:street":"Wantirna Rd",
    "iso:country":"AU",
    "sg:address":"324 Wantirna Rd",
    "sg:city":"Wantirna",
    "sg:classifiers":[
        {
            "category":"Restaurant",
            "type":"Food & Drink"
        }
    ],
    "sg:phone":"+61 3 9887 3555",
    "sg:postcode":"3152",
    "sg:province":"VIC",
    "wof:name":"Cosmopolitan Bar & Restaurant The",
    "wof:placetype":"venue"
},
  "geometry": {"coordinates":[145.22688293499999,-37.8470802307],"type":"Point"}
}