{
  "type": "Feature",
  "properties": {
    "addr:full":"157 Harris Rd Picton WA 6229",
    "addr:housenumber":"157",
    "addr:postcode":"6229",
    "addr:street":"Harris Rd",
    "iso:country":"AU",
    "sg:address":"157 Harris Rd",
    "sg:city":"Picton",
    "sg:classifiers":[
        {
            "category":"Retail",
            "subcategory":"Car Wash",
            "type":"Services"
        }
    ],
    "sg:phone":"+61 1800 654 002",
    "sg:postcode":"6229",
    "sg:province":"WA",
    "sg:tags":[
        "merchant",
        "oil",
        "refiner"
    ],
    "wof:name":"Wren Oil",
    "wof:placetype":"venue"
},
  "geometry": {"coordinates":[115.717049,-33.356415],"type":"Point"}
}