{
  "type": "Feature",
  "properties": {
    "addr:full":"PO Box 1025 Byron Bay NSW 2481",
    "addr:postcode":"2481",
    "iso:country":"AU",
    "sg:address":"PO Box 1025",
    "sg:city":"Byron Bay",
    "sg:classifiers":[
        {
            "category":"Freight",
            "type":"Transportation"
        }
    ],
    "sg:phone":"+61 2 6685 3518",
    "sg:postcode":"2481",
    "sg:province":"NSW",
    "sg:tags":[
        "cargo",
        "container"
    ],
    "wof:name":"Northern Rivers Container Sales & Hire",
    "wof:placetype":"venue"
},
  "geometry": {"coordinates":[153.612823486,-28.6468906403],"type":"Point"}
}