{
  "type": "Feature",
  "properties": {
    "addr:full":"54 Warraba Rd North Narrabeen NSW 2101",
    "addr:housenumber":"54",
    "addr:postcode":"2101",
    "addr:street":"Warraba Rd",
    "iso:country":"AU",
    "sg:address":"54 Warraba Rd",
    "sg:city":"North Narrabeen",
    "sg:classifiers":[
        {
            "category":"Autos & Motor Vehicles",
            "subcategory":"Automobile Sales",
            "type":"Retail Goods"
        }
    ],
    "sg:phone":"+61 410 567 222",
    "sg:postcode":"2101",
    "sg:province":"NSW",
    "sg:tags":[
        "car",
        "used"
    ],
    "wof:name":"Skyline Factory Pty Ltd",
    "wof:placetype":"venue"
},
  "geometry": {"coordinates":[151.29184000000001,-33.698666],"type":"Point"}
}