{
  "type": "Feature",
  "properties": {
    "addr:full":"57 Ocean Beach Rd Woy Woy NSW 2256",
    "addr:housenumber":"57",
    "addr:postcode":"2256",
    "addr:street":"Ocean Beach Rd",
    "iso:country":"AU",
    "sg:address":"57 Ocean Beach Rd",
    "sg:city":"Woy Woy",
    "sg:classifiers":[
        {
            "category":"Home & Garden",
            "subcategory":"Hardware",
            "type":"Retail Goods"
        }
    ],
    "sg:phone":"+61 2 4341 7892",
    "sg:postcode":"2256",
    "sg:province":"NSW",
    "sg:tags":[
        "plumber",
        "supply"
    ],
    "wof:name":"Eagles Plumbing Supplies Pty Ltd",
    "wof:placetype":"venue"
},
  "geometry": {"coordinates":[151.3203125,-33.4941825867],"type":"Point"}
}