{
  "type": "Feature",
  "properties": {
    "iso:country":"AU",
    "sg:address":"8/ 355 Stirling Hwy",
    "sg:city":"Claremont",
    "sg:classifiers":[
        {
            "category":"Real Estate",
            "subcategory":"Architect",
            "type":"Services"
        }
    ],
    "sg:phone":"+61 8 9384 1133",
    "sg:postcode":"6010",
    "sg:province":"WA",
    "wof:name":"Kenneth Broadhurst Architects Pty Ltd",
    "wof:placetype":"venue"
},
  "geometry": {"coordinates":[115.77732849100001,-31.9843559265],"type":"Point"}
}