{
  "type": "Feature",
  "properties": {
    "addr:full":"479 Underwood Rd Rochedale South QLD 4123",
    "addr:housenumber":"479",
    "addr:postcode":"4123",
    "addr:street":"Underwood Rd",
    "iso:country":"AU",
    "sg:address":"479 Underwood Rd",
    "sg:city":"Rochedale South",
    "sg:classifiers":[
        {
            "category":"Professional",
            "subcategory":"Accounting & Tax Preparation",
            "type":"Services"
        }
    ],
    "sg:phone":"+61 7 3841 6690",
    "sg:postcode":"4123",
    "sg:province":"QLD",
    "sg:tags":[
        "consultant",
        "taxation"
    ],
    "wof:name":"Qs Accounting & Taxation Services",
    "wof:placetype":"venue"
},
  "geometry": {"coordinates":[153.14125060999999,-27.5992202759],"type":"Point"}
}