{
  "type": "Feature",
  "properties": {
    "addr:full":"Maroochydore Rd Kunda Park QLD 4556",
    "addr:postcode":"4556",
    "addr:street":"Maroochydore Rd",
    "iso:country":"AU",
    "sg:address":"Maroochydore Rd",
    "sg:city":"Kunda Park",
    "sg:classifiers":[
        {
            "category":"Autos & Motor Vehicles",
            "subcategory":"Fuel & Gas Station",
            "type":"Retail Goods"
        }
    ],
    "sg:phone":"+61 7 5445 4344",
    "sg:postcode":"4556",
    "sg:province":"QLD",
    "wof:name":"Matilda Kunda Park",
    "wof:placetype":"venue"
},
  "geometry": {"coordinates":[153.03819274899999,-26.6630268097],"type":"Point"}
}