{
  "type": "Feature",
  "properties": {
    "iso:country":"AU",
    "sg:address":"Suite 2, 1107 Botany Rd",
    "sg:city":"Mascot",
    "sg:classifiers":[
        {
            "category":"Professional",
            "subcategory":"Employment Agencies",
            "type":"Services"
        }
    ],
    "sg:phone":"+61 2 9700 8133",
    "sg:postcode":"2020",
    "sg:province":"NSW",
    "wof:name":"Impex Personnel",
    "wof:placetype":"venue"
},
  "geometry": {"coordinates":[151.194946289,-33.9289245605],"type":"Point"}
}