{
  "type": "Feature",
  "properties": {
    "addr:full":"3 West Thebarton Rd Thebarton SA 5031",
    "addr:housenumber":"3",
    "addr:postcode":"5031",
    "addr:street":"West Thebarton Rd",
    "iso:country":"AU",
    "sg:address":"3 West Thebarton Rd",
    "sg:city":"Thebarton",
    "sg:classifiers":[
        {
            "category":"Wholesale",
            "subcategory":"Metals & Minerals",
            "type":"Manufacturing & Wholesale Goods"
        }
    ],
    "sg:phone":"+61 8 8234 5288",
    "sg:postcode":"5031",
    "sg:province":"SA",
    "sg:tags":[
        "steel",
        "stainless",
        "product",
        "equipment"
    ],
    "wof:name":"Ackland Sheet Metal",
    "wof:placetype":"venue"
},
  "geometry": {"coordinates":[138.57200622600001,-34.9137115479],"type":"Point"}
}