{
  "type": "Feature",
  "properties": {
    "addr:full":"20 Bishop St Kelvin Grove QLD 4059",
    "addr:housenumber":"20",
    "addr:postcode":"4059",
    "addr:street":"Bishop St",
    "iso:country":"AU",
    "sg:address":"20 Bishop St",
    "sg:city":"Kelvin Grove",
    "sg:classifiers":[
        {
            "category":"Shopping",
            "subcategory":"Music",
            "type":"Retail Goods"
        }
    ],
    "sg:phone":"+61 7 3856 5911",
    "sg:postcode":"4059",
    "sg:province":"QLD",
    "sg:tags":[
        "store"
    ],
    "wof:name":"Mouthbreeder CD Artwork",
    "wof:placetype":"venue"
},
  "geometry": {"coordinates":[153.00840759299999,-27.4436073303],"type":"Point"}
}