{
  "type": "Feature",
  "properties": {
    "addr:full":"Unit 3 282 Maroondah Hwy Chirnside Park VIC 3116",
    "addr:housenumber":"282",
    "addr:postcode":"3116",
    "addr:street":"Maroondah Hwy",
    "iso:country":"AU",
    "sg:address":"Unit 3 282 Maroondah Hwy",
    "sg:city":"Chirnside Park",
    "sg:classifiers":[
        {
            "category":"Sports & Exercise",
            "subcategory":"Gym",
            "type":"Entertainment"
        }
    ],
    "sg:phone":"+61 3 9727 2551",
    "sg:postcode":"3116",
    "sg:province":"VIC",
    "sg:tags":[
        "health",
        "fitness"
    ],
    "wof:name":"Beach House Fitness Centre",
    "wof:placetype":"venue"
},
  "geometry": {"coordinates":[145.30538940400001,-37.7651443481],"type":"Point"}
}