{
  "type": "Feature",
  "properties": {
    "iso:country":"AU",
    "sg:address":"19 Endurance Ave",
    "sg:city":"Queanbeyan",
    "sg:classifiers":[
        {
            "category":"Utilities",
            "subcategory":"Recycling",
            "type":"Services"
        }
    ],
    "sg:phone":"+61 412 210 245",
    "sg:postcode":"2620",
    "sg:province":"ACT",
    "wof:name":"All Recycling",
    "wof:placetype":"venue"
},
  "geometry": {"coordinates":[149.24554443400001,-35.3406028748],"type":"Point"}
}