{
  "type": "Feature",
  "properties": {
    "iso:country":"AU",
    "sg:address":"RMB 3374 Nelson Bay Rd",
    "sg:city":"Salt Ash",
    "sg:classifiers":[
        {
            "category":"Building & Trades",
            "subcategory":"Construction",
            "type":"Services"
        }
    ],
    "sg:phone":"+61 411 095 099",
    "sg:postcode":"2318",
    "sg:province":"NSW",
    "sg:tags":[
        "home",
        "air conditioning"
    ],
    "wof:name":"Salt Ash Installations",
    "wof:placetype":"venue"
},
  "geometry": {"coordinates":[151.890747,-32.798157],"type":"Point"}
}