{
  "type": "Feature",
  "properties": {
    "iso:country":"AU",
    "sg:address":"85a Evans St",
    "sg:city":"Shenton Park",
    "sg:classifiers":[
        {
            "category":"Professional",
            "subcategory":"Engineering",
            "type":"Services"
        }
    ],
    "sg:phone":"+61 8 9380 6921",
    "sg:postcode":"6008",
    "sg:province":"WA",
    "sg:tags":[
        "consultant",
        "geotechnical",
        "engineer"
    ],
    "wof:name":"D E Cooper & Associates Pty Ltd",
    "wof:placetype":"venue"
},
  "geometry": {"coordinates":[115.80718231199999,-31.9601554871],"type":"Point"}
}