{
  "type": "Feature",
  "properties": {
    "iso:country":"AU",
    "sg:address":"Cnr Bay & Davenport Sts",
    "sg:city":"Southport",
    "sg:classifiers":[
        {
            "category":"Organizations",
            "subcategory":"Community Association",
            "type":"Services"
        }
    ],
    "sg:phone":"+61 7 5591 1500",
    "sg:postcode":"4215",
    "sg:province":"QLD",
    "sg:tags":[
        "organisation",
        "family",
        "welfare"
    ],
    "wof:name":"Cancer Fund",
    "wof:placetype":"venue"
},
  "geometry": {"coordinates":[153.41166687,-27.9671287537],"type":"Point"}
}