{
  "type": "Feature",
  "properties": {
    "addr:full":"37 Prime Drv Seven Hills NSW 2147",
    "addr:housenumber":"37",
    "addr:postcode":"2147",
    "addr:street":"Prime Drv",
    "iso:country":"AU",
    "sg:address":"37 Prime Drv",
    "sg:city":"Seven Hills",
    "sg:classifiers":[
        {
            "category":"Home & Garden",
            "subcategory":"Building Materials",
            "type":"Retail Goods"
        }
    ],
    "sg:phone":"+61 13 61 21",
    "sg:postcode":"2147",
    "sg:province":"NSW",
    "sg:tags":[
        "shutter",
        "roller",
        "grille"
    ],
    "sg:website":"http://www.halfpriceshutters.com.au",
    "wof:name":"Half Price Shutters",
    "wof:placetype":"venue"
},
  "geometry": {"coordinates":[150.952667236,-33.772518158],"type":"Point"}
}