{
  "type": "Feature",
  "properties": {
    "addr:full":"U2/ 4 Trades Crt Forster NSW 2428",
    "addr:housenumber":"4",
    "addr:postcode":"2428",
    "addr:street":"U2 /;Trades Crt",
    "iso:country":"AU",
    "sg:address":"U2/ 4 Trades Crt",
    "sg:city":"Forster",
    "sg:classifiers":[
        {
            "category":"Retail",
            "subcategory":"Auto Repair",
            "type":"Services"
        }
    ],
    "sg:phone":"+61 2 6554 5166",
    "sg:postcode":"2428",
    "sg:province":"NSW",
    "sg:tags":[
        "repairer",
        "motor",
        "engineer"
    ],
    "wof:name":"Automotive Services Forster",
    "wof:placetype":"venue"
},
  "geometry": {"coordinates":[152.52394100000001,-32.196625],"type":"Point"}
}