{
  "type": "Feature",
  "properties": {
    "iso:country":"AU",
    "sg:address":"887 - 889 Springvale Rd",
    "sg:city":"Mulgrave",
    "sg:classifiers":[
        {
            "category":"Shopping",
            "subcategory":"Gifts & Souvenirs",
            "type":"Retail Goods"
        }
    ],
    "sg:phone":"+61 1300 738 555",
    "sg:postcode":"3170",
    "sg:province":"VIC",
    "sg:tags":[
        "shop",
        "supply"
    ],
    "wof:name":"Electus Distribution",
    "wof:placetype":"venue"
},
  "geometry": {"coordinates":[145.15846252399999,-37.9210243225],"type":"Point"}
}