{
  "type": "Feature",
  "properties": {
    "addr:full":"115- 117 Riley St Darlinghurst NSW 2010",
    "addr:housenumber":"117",
    "addr:postcode":"2010",
    "addr:street":"Riley St",
    "iso:country":"AU",
    "sg:address":"115- 117 Riley St",
    "sg:city":"Darlinghurst",
    "sg:classifiers":[
        {
            "category":"Retail",
            "subcategory":"Event Space",
            "type":"Services"
        }
    ],
    "sg:phone":"+61 2 9331 1559",
    "sg:postcode":"2010",
    "sg:province":"NSW",
    "sg:tags":[
        "function",
        "organiser"
    ],
    "wof:name":"Two Chefs On Stanley",
    "wof:placetype":"venue"
},
  "geometry": {"coordinates":[151.21472168,-33.8764839172],"type":"Point"}
}