{
  "type": "Feature",
  "properties": {
    "iso:country":"AU",
    "sg:address":"Shop 3/280-284 Main Rd East",
    "sg:city":"St Albans",
    "sg:classifiers":[
        {
            "category":"Personal",
            "subcategory":"Beauty Salon",
            "type":"Services"
        }
    ],
    "sg:phone":"+61 3 9367 1596",
    "sg:postcode":"3021",
    "sg:province":"VIC",
    "sg:tags":[
        "hairdresser"
    ],
    "wof:name":"Sally's Unisex Salon For Men & Women",
    "wof:placetype":"venue"
},
  "geometry": {"coordinates":[144.803024,-37.74445],"type":"Point"}
}