{
  "type": "Feature",
  "properties": {
    "addr:full":"83 Vines Rd Hamlyn Heights VIC 3215",
    "addr:housenumber":"83",
    "addr:postcode":"3215",
    "addr:street":"Vines Rd",
    "iso:country":"AU",
    "sg:address":"83 Vines Rd",
    "sg:city":"Hamlyn Heights",
    "sg:classifiers":[
        {
            "category":"Real Estate",
            "subcategory":"Real Estate Agent",
            "type":"Services"
        }
    ],
    "sg:phone":"+61 3 5275 0404",
    "sg:postcode":"3215",
    "sg:province":"VIC",
    "sg:tags":[
        "handyman's",
        "equipment",
        "hire",
        "builders",
        "contractor"
    ],
    "wof:name":"D.M Hire",
    "wof:placetype":"venue"
},
  "geometry": {"coordinates":[144.32835388199999,-38.1212692261],"type":"Point"}
}