{
  "type": "Feature",
  "properties": {
    "addr:full":"181 Boundary Rd Laverton North VIC 3026",
    "addr:housenumber":"181",
    "addr:postcode":"3026",
    "addr:street":"Boundary Rd",
    "iso:country":"AU",
    "sg:address":"181 Boundary Rd",
    "sg:city":"Laverton North",
    "sg:classifiers":[
        {
            "category":"Wholesale",
            "subcategory":"Machinery & Supplies",
            "type":"Manufacturing & Wholesale Goods"
        }
    ],
    "sg:phone":"+61 3 9369 1188",
    "sg:postcode":"3026",
    "sg:province":"VIC",
    "sg:tags":[
        "agricultural"
    ],
    "wof:name":"Landpower Australia Pty Ltd",
    "wof:placetype":"venue"
},
  "geometry": {"coordinates":[144.78559899999999,-37.813713],"type":"Point"}
}