{
  "type": "Feature",
  "properties": {
    "addr:full":"Unit 2/ 51 Stephen Tce St Peters SA 5069",
    "addr:housenumber":"51",
    "addr:postcode":"5069",
    "addr:street":"Stephen Tce",
    "iso:country":"AU",
    "sg:address":"Unit 2/ 51 Stephen Tce",
    "sg:city":"St Peters",
    "sg:classifiers":[
        {
            "category":"Health Services",
            "subcategory":"Doctor",
            "type":"Services"
        }
    ],
    "sg:phone":"+61 8 8362 1420",
    "sg:postcode":"5069",
    "sg:province":"SA",
    "sg:tags":[
        "podiatrist"
    ],
    "wof:name":"Footcare Centre",
    "wof:placetype":"venue"
},
  "geometry": {"coordinates":[138.623504639,-34.9047203064],"type":"Point"}
}