{
  "type": "Feature",
  "properties": {
    "iso:country":"AU",
    "sg:address":"65 Great North Rd",
    "sg:city":"Five Dock",
    "sg:classifiers":[
        {
            "category":"Professional",
            "subcategory":"Art Services",
            "type":"Services"
        }
    ],
    "sg:phone":"+61 2 9713 8224",
    "sg:postcode":"2046",
    "sg:province":"NSW",
    "sg:tags":[
        "graphic",
        "designer"
    ],
    "wof:name":"Kwik Kopy Print & Design Centres",
    "wof:placetype":"venue"
},
  "geometry": {"coordinates":[151.129089,-33.870308],"type":"Point"}
}