{
  "type": "Feature",
  "properties": {
    "addr:full":"23 Nelson St Woollahra NSW 2025",
    "addr:housenumber":"23",
    "addr:postcode":"2025",
    "addr:street":"Nelson St",
    "iso:country":"AU",
    "sg:address":"23 Nelson St",
    "sg:city":"Woollahra",
    "sg:classifiers":[
        {
            "category":"Travel",
            "subcategory":"Hostel",
            "type":"Entertainment"
        }
    ],
    "sg:phone":"+61 2 9362 3777",
    "sg:postcode":"2025",
    "sg:province":"NSW",
    "sg:tags":[
        "home"
    ],
    "wof:name":"Montefiore Hostel",
    "wof:placetype":"venue"
},
  "geometry": {"coordinates":[151.24223327600001,-33.8873558044],"type":"Point"}
}