{
  "type": "Feature",
  "properties": {
    "addr:full":"Charlotte St Duaringa QLD 4702",
    "addr:postcode":"4702",
    "addr:street":"Charlotte St",
    "iso:country":"AU",
    "sg:address":"Charlotte St",
    "sg:city":"Duaringa",
    "sg:classifiers":[
        {
            "category":"Education",
            "subcategory":"School",
            "type":"Public Place"
        }
    ],
    "sg:phone":"+61 7 4935 7125",
    "sg:postcode":"4702",
    "sg:province":"QLD",
    "sg:tags":[
        "state",
        "except",
        "nsw"
    ],
    "wof:name":"Duaringa Primary School",
    "wof:placetype":"venue"
},
  "geometry": {"coordinates":[150.49159240700001,-23.3746643066],"type":"Point"}
}