{
  "type": "Feature",
  "properties": {
    "addr:full":"Britt St Ouyen VIC 3490",
    "addr:postcode":"3490",
    "addr:street":"Britt St",
    "iso:country":"AU",
    "sg:address":"Britt St",
    "sg:city":"Ouyen",
    "sg:classifiers":[
        {
            "category":"Shopping",
            "type":"Retail Goods"
        }
    ],
    "sg:phone":"+61 427 921 160",
    "sg:postcode":"3490",
    "sg:province":"VIC",
    "sg:tags":[
        "agent",
        "stock"
    ],
    "wof:name":"Ouyen Regional Saleyards",
    "wof:placetype":"venue"
},
  "geometry": {"coordinates":[142.317169189,-35.0733985901],"type":"Point"}
}