{
  "type": "Feature",
  "properties": {
    "addr:full":"365 Glenly St Albury North NSW 2640",
    "addr:housenumber":"365",
    "addr:postcode":"2640",
    "addr:street":"Glenly St",
    "iso:country":"AU",
    "sg:address":"365 Glenly St",
    "sg:city":"Albury North",
    "sg:classifiers":[
        {
            "category":"Banks & Credit Unions",
            "subcategory":"Investment Brokerage",
            "type":"Services"
        }
    ],
    "sg:phone":"+61 2 6025 7536",
    "sg:postcode":"2640",
    "sg:province":"NSW",
    "sg:tags":[
        "bedspread",
        "quilt"
    ],
    "wof:name":"Albury Be Quilted",
    "wof:placetype":"venue"
},
  "geometry": {"coordinates":[146.93138122600001,-36.0611343384],"type":"Point"}
}