{
  "type": "Feature",
  "properties": {
    "addr:full":"41 Taylors Rd St Albans VIC 3021",
    "addr:housenumber":"41",
    "addr:postcode":"3021",
    "addr:street":"Taylors Rd",
    "iso:country":"AU",
    "sg:address":"41 Taylors Rd St",
    "sg:city":"Albans",
    "sg:classifiers":[
        {
            "category":"Health Services",
            "subcategory":"Dentist",
            "type":"Services"
        }
    ],
    "sg:phone":"+61 3 9366 9779",
    "sg:postcode":"3021",
    "sg:province":"VIC",
    "sg:tags":[
        "dental",
        "prosthetist"
    ],
    "wof:name":"Brimbank Denture Clinic",
    "wof:placetype":"venue"
},
  "geometry": {"coordinates":[144.81019599999999,-37.729214],"type":"Point"}
}