{
  "type": "Feature",
  "properties": {
    "iso:country":"AU",
    "sg:address":"Pyalong Rd",
    "sg:city":"Tallarook",
    "sg:classifiers":[
        {
            "category":"Government",
            "subcategory":"Customs House",
            "type":"Public Place"
        }
    ],
    "sg:phone":"+61 3 5793 8380",
    "sg:postcode":"3659",
    "sg:province":"VIC",
    "sg:tags":[
        "title",
        "management",
        "stratum"
    ],
    "wof:name":"Lyndale Park Body Corporate",
    "wof:placetype":"venue"
},
  "geometry": {"coordinates":[145.100631714,-37.0982894897],"type":"Point"}
}