{
  "type": "Feature",
  "properties": {
    "iso:country":"AU",
    "sg:address":"U3/ 122 Long St",
    "sg:city":"Smithfield",
    "sg:classifiers":[
        {
            "category":"Manufacturing",
            "subcategory":"Glass & Minerals",
            "type":"Manufacturing & Wholesale Goods"
        }
    ],
    "sg:phone":"+61 2 9604 8533",
    "sg:postcode":"2164",
    "sg:province":"NSW",
    "sg:tags":[
        "fabricator",
        "fibreglass"
    ],
    "wof:name":"Crystal Centre",
    "wof:placetype":"venue"
},
  "geometry": {"coordinates":[150.93278503400001,-33.8410797119],"type":"Point"}
}