{
  "type": "Feature",
  "properties": {
    "iso:country":"AU",
    "sg:address":"Coorparoo Mall 264 Old Cleveland Rd",
    "sg:city":"Coorparoo",
    "sg:classifiers":[
        {
            "category":"Banks & Credit Unions",
            "subcategory":"Bank",
            "type":"Services"
        }
    ],
    "sg:phone":"+61 7 3397 9033",
    "sg:postcode":"4151",
    "sg:province":"QLD",
    "wof:name":"Bank of Queensland",
    "wof:placetype":"venue"
},
  "geometry": {"coordinates":[153.057693481,-27.4951782227],"type":"Point"}
}