{
  "type": "Feature",
  "properties": {
    "iso:country":"AU",
    "sg:address":"96 Northville Drv",
    "sg:city":"Barnsley",
    "sg:classifiers":[
        {
            "category":"Personal",
            "subcategory":"Beauty Salon",
            "type":"Services"
        }
    ],
    "sg:phone":"+61 2 4955 1055",
    "sg:postcode":"2278",
    "sg:province":"NSW",
    "sg:tags":[
        "hairdresser"
    ],
    "wof:name":"His & Hers Barnsley Hair Flair",
    "wof:placetype":"venue"
},
  "geometry": {"coordinates":[151.58644100000001,-32.931965],"type":"Point"}
}