{
  "type": "Feature",
  "properties": {
    "addr:full":"Harper St Molendinar QLD 4214",
    "addr:postcode":"4214",
    "addr:street":"Harper St",
    "iso:country":"AU",
    "sg:address":"Harper St",
    "sg:city":"Molendinar",
    "sg:classifiers":[
        {
            "category":"Building & Trades",
            "subcategory":"Construction",
            "type":"Services"
        }
    ],
    "sg:phone":"+61 7 5527 9284",
    "sg:postcode":"4214",
    "sg:province":"QLD",
    "sg:tags":[
        "renovation",
        "alterations",
        "extension",
        "contractor"
    ],
    "wof:name":"Patiomagic",
    "wof:placetype":"venue"
},
  "geometry": {"coordinates":[153.361938477,-27.9840259552],"type":"Point"}
}