{
  "type": "Feature",
  "properties": {
    "addr:full":"14 Viridian Drv Neerabup WA 6031",
    "addr:housenumber":"14",
    "addr:postcode":"6031",
    "addr:street":"Viridian Drv",
    "iso:country":"AU",
    "sg:address":"14 Viridian Drv",
    "sg:city":"Neerabup",
    "sg:classifiers":[
        {
            "category":"Education",
            "subcategory":"School",
            "type":"Public Place"
        }
    ],
    "sg:phone":"+61 8 9405 7100",
    "sg:postcode":"6031",
    "sg:province":"WA",
    "sg:tags":[
        "state",
        "except",
        "nsw"
    ],
    "wof:name":"Neerabup Primary School",
    "wof:placetype":"venue"
},
  "geometry": {"coordinates":[115.80754852299999,-31.6999969482],"type":"Point"}
}