{
  "type": "Feature",
  "properties": {
    "addr:full":"Partridge Rd Loxton SA 5333",
    "addr:postcode":"5333",
    "addr:street":"Partridge Rd",
    "iso:country":"AU",
    "sg:address":"Partridge Rd",
    "sg:city":"Loxton",
    "sg:classifiers":[
        {
            "category":"Farming",
            "subcategory":"Berry Farm",
            "type":"Manufacturing & Wholesale Goods"
        }
    ],
    "sg:phone":"+61 8 8584 7653",
    "sg:postcode":"5333",
    "sg:province":"SA",
    "sg:tags":[
        "fruit",
        "grower"
    ],
    "wof:name":"Pontt B J & J M",
    "wof:placetype":"venue"
},
  "geometry": {"coordinates":[140.58267211899999,-34.4686088562],"type":"Point"}
}