{
  "type": "Feature",
  "properties": {
    "addr:full":"PO Box 94 Stanley TAS 7331",
    "addr:postcode":"7331",
    "iso:country":"AU",
    "sg:address":"PO Box 94",
    "sg:city":"Stanley",
    "sg:classifiers":[
        {
            "category":"Sports & Exercise",
            "subcategory":"Sports Center",
            "type":"Entertainment"
        }
    ],
    "sg:phone":"+61 3 6458 1293",
    "sg:postcode":"7331",
    "sg:province":"TAS",
    "sg:tags":[
        "ground"
    ],
    "wof:name":"Stanley Recreational Ground",
    "wof:placetype":"venue"
},
  "geometry": {"coordinates":[145.27461199999999,-40.763649],"type":"Point"}
}