{
  "type": "Feature",
  "properties": {
    "addr:full":"4 Julia St Toowoomba QLD 4350",
    "addr:housenumber":"4",
    "addr:postcode":"4350",
    "addr:street":"Julia St",
    "iso:country":"AU",
    "sg:address":"4 Julia St",
    "sg:city":"Toowoomba",
    "sg:classifiers":[
        {
            "category":"Professional",
            "subcategory":"Accounting & Tax Preparation",
            "type":"Services"
        }
    ],
    "sg:phone":"+61 7 4639 3488",
    "sg:postcode":"4350",
    "sg:province":"QLD",
    "sg:tags":[
        "accountant",
        "auditor"
    ],
    "wof:name":"Haslam & Associates",
    "wof:placetype":"venue"
},
  "geometry": {"coordinates":[151.95674099999999,-27.564051],"type":"Point"}
}