{
  "type": "Feature",
  "properties": {
    "addr:full":"PO Box 630 Duncraig WA 6023",
    "addr:postcode":"6023",
    "iso:country":"AU",
    "sg:address":"PO Box 630",
    "sg:city":"Duncraig",
    "sg:classifiers":[
        {
            "category":"Home & Garden",
            "subcategory":"Building Materials",
            "type":"Retail Goods"
        }
    ],
    "sg:phone":"+61 8 9243 6152",
    "sg:postcode":"6023",
    "sg:province":"WA",
    "sg:tags":[
        "merchant",
        "glass",
        "glazier"
    ],
    "wof:name":"Sorrento Glass Pty Ltd",
    "wof:placetype":"venue"
},
  "geometry": {"coordinates":[115.76262664799999,-31.8187255859],"type":"Point"}
}