{
  "type": "Feature",
  "properties": {
    "addr:full":"Broderick Rd Carrum Downs VIC 3201",
    "addr:postcode":"3201",
    "addr:street":"Broderick Rd",
    "iso:country":"AU",
    "sg:address":"Broderick Rd",
    "sg:city":"Carrum Downs",
    "sg:classifiers":[
        {
            "category":"Education",
            "subcategory":"School",
            "type":"Public Place"
        }
    ],
    "sg:phone":"+61 3 9785 2633",
    "sg:postcode":"3201",
    "sg:province":"VIC",
    "sg:tags":[
        "co-educational"
    ],
    "wof:name":"St Joachim's Primary",
    "wof:placetype":"venue"
},
  "geometry": {"coordinates":[145.175095,-38.103233],"type":"Point"}
}