{
  "type": "Feature",
  "properties": {
    "addr:full":"146 Old Southern Rd Worrigee NSW 2540",
    "addr:housenumber":"146",
    "addr:postcode":"2540",
    "addr:street":"Old Southern Rd",
    "iso:country":"AU",
    "sg:address":"146 Old Southern Rd",
    "sg:city":"Worrigee",
    "sg:classifiers":[
        {
            "category":"Personal",
            "subcategory":"Beauty Salon",
            "type":"Services"
        }
    ],
    "sg:phone":"+61 2 4422 5581",
    "sg:postcode":"2540",
    "sg:province":"NSW",
    "sg:tags":[
        "hairdresser"
    ],
    "wof:name":"Head To Toe Hair & Beauty",
    "wof:placetype":"venue"
},
  "geometry": {"coordinates":[150.62188720699999,-34.8937950134],"type":"Point"}
}