{
  "type": "Feature",
  "properties": {
    "addr:full":"Shop 33-34 Menai Market Place Shopng Cntr Menai NSW 2234",
    "addr:housenumber":"33-34",
    "addr:postcode":"2234",
    "addr:street":"Menai Market Place Shopng",
    "iso:country":"AU",
    "sg:address":"Shop 33-34 Menai Market Place Shopng Cntr",
    "sg:city":"Menai",
    "sg:classifiers":[
        {
            "category":"Shopping",
            "subcategory":"Clothing, Apparel, & Fashions",
            "type":"Retail Goods"
        }
    ],
    "sg:phone":"+61 2 9541 1113",
    "sg:postcode":"2234",
    "sg:province":"NSW",
    "sg:tags":[
        "menswear"
    ],
    "wof:name":"Lowes",
    "wof:placetype":"venue"
},
  "geometry": {"coordinates":[151.010955811,-34.014175415],"type":"Point"}
}