{
  "type": "Feature",
  "properties": {
    "addr:full":"100 Islander Rd Pialba QLD 4655",
    "addr:housenumber":"100",
    "addr:postcode":"4655",
    "addr:street":"Islander Rd",
    "iso:country":"AU",
    "sg:address":"100 Islander Rd",
    "sg:city":"Pialba",
    "sg:classifiers":[
        {
            "category":"Retail",
            "subcategory":"Storage",
            "type":"Services"
        }
    ],
    "sg:phone":"+61 7 4128 3264",
    "sg:postcode":"4655",
    "sg:province":"QLD",
    "wof:name":"Hervey Bay Mini Storage",
    "wof:placetype":"venue"
},
  "geometry": {"coordinates":[152.831467,-25.285175],"type":"Point"}
}