{
  "type": "Feature",
  "properties": {
    "addr:full":"84 Marti St Bayview Heights QLD 4868",
    "addr:housenumber":"84",
    "addr:postcode":"4868",
    "addr:street":"Marti St",
    "iso:country":"AU",
    "sg:address":"84 Marti St",
    "sg:city":"Bayview Heights",
    "sg:classifiers":[
        {
            "category":"Building & Trades",
            "subcategory":"Electrical",
            "type":"Services"
        }
    ],
    "sg:phone":"+61 409 544 174",
    "sg:postcode":"4868",
    "sg:province":"QLD",
    "sg:tags":[
        "repair",
        "generator",
        "electric",
        "motor"
    ],
    "wof:name":"Cairns Motor Rewinding",
    "wof:placetype":"venue"
},
  "geometry": {"coordinates":[145.72697448700001,-16.9568939209],"type":"Point"}
}