{
  "type": "Feature",
  "properties": {
    "iso:country":"AU",
    "sg:address":"31 Ramona St",
    "sg:city":"Quakers Hill",
    "sg:classifiers":[
        {
            "category":"Retail",
            "subcategory":"Storage",
            "type":"Services"
        }
    ],
    "sg:phone":"+61 2 9626 5556",
    "sg:postcode":"2763",
    "sg:province":"NSW",
    "sg:tags":[
        "removal",
        "furniture"
    ],
    "wof:name":"Brayden Removals & Storage",
    "wof:placetype":"venue"
},
  "geometry": {"coordinates":[150.88822937,-33.7275924683],"type":"Point"}
}