{
  "type": "Feature",
  "properties": {
    "iso:country":"AU",
    "sg:address":"37 Palmerston St",
    "sg:city":"Sale",
    "sg:classifiers":[
        {
            "category":"Health Services",
            "subcategory":"Doctor",
            "type":"Services"
        }
    ],
    "sg:phone":"+61 3 5144 4755",
    "sg:postcode":"3850",
    "sg:province":"VIC",
    "sg:tags":[
        "medical",
        "practitioner"
    ],
    "wof:name":"Gippsland Obstetrics & Gynaecology Centre",
    "wof:placetype":"venue"
},
  "geometry": {"coordinates":[147.079711914,-38.1083946228],"type":"Point"}
}