{
  "type": "Feature",
  "properties": {
    "iso:country":"AU",
    "sg:address":"PO Box 2",
    "sg:city":"Canterbury",
    "sg:classifiers":[
        {
            "category":"Building & Trades",
            "subcategory":"Construction",
            "type":"Services"
        }
    ],
    "sg:phone":"+61 403 245 245",
    "sg:postcode":"2193",
    "sg:province":"NSW",
    "sg:tags":[
        "rendering",
        "cement"
    ],
    "wof:name":"Great Building Pty Ltd",
    "wof:placetype":"venue"
},
  "geometry": {"coordinates":[151.114868,-33.913929],"type":"Point"}
}