{
  "type": "Feature",
  "properties": {
    "addr:full":"46 Greenhill Rd Wayville SA 5034",
    "addr:housenumber":"46",
    "addr:postcode":"5034",
    "addr:street":"Greenhill Rd",
    "iso:country":"AU",
    "sg:address":"46 Greenhill Rd",
    "sg:city":"Wayville",
    "sg:classifiers":[
        {
            "category":"Organizations",
            "subcategory":"Labor Organization",
            "type":"Services"
        }
    ],
    "sg:phone":"+61 8 8279 2222",
    "sg:postcode":"5034",
    "sg:province":"SA",
    "sg:tags":[
        "union"
    ],
    "wof:name":"SA Unions",
    "wof:placetype":"venue"
},
  "geometry": {"coordinates":[138.591262817,-34.9419441223],"type":"Point"}
}