{
  "type": "Feature",
  "properties": {
    "addr:full":"17B Edgecliff Rd Woollahra NSW 2025",
    "addr:housenumber":"17b",
    "addr:postcode":"2025",
    "addr:street":"Edgecliff Rd",
    "iso:country":"AU",
    "sg:address":"17B Edgecliff Rd",
    "sg:city":"Woollahra",
    "sg:classifiers":[
        {
            "category":"Building & Trades",
            "subcategory":"Cleaning & Sanitation",
            "type":"Services"
        }
    ],
    "sg:phone":"+61 1800 250 621",
    "sg:postcode":"2025",
    "sg:province":"NSW",
    "sg:tags":[
        "window"
    ],
    "wof:name":"Executive Homes Window Tinting Services",
    "wof:placetype":"venue"
},
  "geometry": {"coordinates":[151.24171447800001,-33.8850975037],"type":"Point"}
}