{
  "type": "Feature",
  "properties": {
    "addr:full":"588 Ballarat Rd Sunshine VIC 3020",
    "addr:housenumber":"588",
    "addr:postcode":"3020",
    "addr:street":"Ballarat Rd",
    "iso:country":"AU",
    "sg:address":"588 Ballarat Rd",
    "sg:city":"Sunshine",
    "sg:classifiers":[
        {
            "category":"Wholesale",
            "subcategory":"Machinery & Supplies",
            "type":"Manufacturing & Wholesale Goods"
        }
    ],
    "sg:phone":"+61 3 9363 8100",
    "sg:postcode":"3020",
    "sg:province":"VIC",
    "sg:tags":[
        "agricultural"
    ],
    "wof:name":"Western Farm Service P/L",
    "wof:placetype":"venue"
},
  "geometry": {"coordinates":[144.80877699999999,-37.77438],"type":"Point"}
}