{
  "type": "Feature",
  "properties": {
    "iso:country":"AU",
    "sg:address":"140 Coromandel St",
    "sg:city":"Goulburn",
    "sg:classifiers":[
        {
            "category":"Professional",
            "subcategory":"Accounting & Tax Preparation",
            "type":"Services"
        }
    ],
    "sg:phone":"+61 2 4821 8865",
    "sg:postcode":"2580",
    "sg:province":"NSW",
    "sg:tags":[
        "accountant",
        "auditor"
    ],
    "wof:name":"JLS Accounting Services",
    "wof:placetype":"venue"
},
  "geometry": {"coordinates":[149.70826721200001,-34.7517089844],"type":"Point"}
}