{
  "type": "Feature",
  "properties": {
    "addr:full":"3 Kindale Crt Pooraka SA 5095",
    "addr:housenumber":"3",
    "addr:postcode":"5095",
    "addr:street":"Kindale Crt",
    "iso:country":"AU",
    "sg:address":"3 Kindale Crt",
    "sg:city":"Pooraka",
    "sg:classifiers":[
        {
            "category":"Manufacturing",
            "subcategory":"Tools & Machinery",
            "type":"Manufacturing & Wholesale Goods"
        }
    ],
    "sg:phone":"+61 8 8260 6858",
    "sg:postcode":"5095",
    "sg:province":"SA",
    "sg:tags":[
        "toolmaker"
    ],
    "wof:name":"Esstek C.N.C",
    "wof:placetype":"venue"
},
  "geometry": {"coordinates":[138.63417053200001,-34.8117332458],"type":"Point"}
}