{
  "type": "Feature",
  "properties": {
    "iso:country":"AU",
    "sg:address":"6 Wyong St",
    "sg:city":"Keilor East",
    "sg:classifiers":[
        {
            "category":"Utilities",
            "subcategory":"Electric",
            "type":"Services"
        }
    ],
    "sg:phone":"+61 418 358 369",
    "sg:postcode":"3033",
    "sg:province":"VIC",
    "sg:tags":[
        "electrical",
        "contractor"
    ],
    "wof:name":"Rileys Electrical Contractors Pty Ltd",
    "wof:placetype":"venue"
},
  "geometry": {"coordinates":[144.865814,-37.735924],"type":"Point"}
}