{
  "type": "Feature",
  "properties": {
    "iso:country":"AU",
    "sg:address":"181 Harbour Drv",
    "sg:city":"Coffs Harbour",
    "sg:classifiers":[
        {
            "category":"Real Estate",
            "subcategory":"Developer",
            "type":"Services"
        }
    ],
    "sg:phone":"+61 2 6659 9888",
    "sg:postcode":"2450",
    "sg:province":"NSW",
    "sg:tags":[
        "development"
    ],
    "wof:name":"Colliers International Coffs Harbour",
    "wof:placetype":"venue"
},
  "geometry": {"coordinates":[153.116974,-30.298115],"type":"Point"}
}