{
  "type": "Feature",
  "properties": {
    "addr:full":"17 Sydney St Mackay QLD 4740",
    "addr:housenumber":"17",
    "addr:postcode":"4740",
    "addr:street":"Sydney St",
    "iso:country":"AU",
    "sg:address":"17 Sydney St",
    "sg:city":"Mackay",
    "sg:classifiers":[
        {
            "category":"Personal",
            "subcategory":"Skin Care",
            "type":"Services"
        }
    ],
    "sg:phone":"+61 7 4957 5605",
    "sg:postcode":"4740",
    "sg:province":"QLD",
    "sg:tags":[
        "treatment"
    ],
    "wof:name":"Just Magic Skin Care Clinic",
    "wof:placetype":"venue"
},
  "geometry": {"coordinates":[149.18734699999999,-21.140099],"type":"Point"}
}