{
  "type": "Feature",
  "properties": {
    "iso:country":"AU",
    "sg:address":"Fcty 3, 43 Havilah Rd",
    "sg:city":"Long Gully",
    "sg:classifiers":[
        {
            "category":"Professional",
            "subcategory":"Detective & Security Services",
            "type":"Services"
        }
    ],
    "sg:phone":"+61 3 5441 2922",
    "sg:postcode":"3550",
    "sg:province":"VIC",
    "sg:tags":[
        "guard",
        "patrol"
    ],
    "wof:name":"Fly In Eagle Group Pty Ltd",
    "wof:placetype":"venue"
},
  "geometry": {"coordinates":[144.263793945,-36.74401474],"type":"Point"}
}