{
  "type": "Feature",
  "properties": {
    "iso:country":"AU",
    "sg:address":"793 Centre Rd",
    "sg:city":"Bentleigh East",
    "sg:classifiers":[
        {
            "category":"Personal",
            "subcategory":"Beauty Salon",
            "type":"Services"
        }
    ],
    "sg:phone":"+61 3 9570 6300",
    "sg:postcode":"3165",
    "sg:province":"VIC",
    "sg:tags":[
        "hairdresser"
    ],
    "wof:name":"Roman's Barber Shop",
    "wof:placetype":"venue"
},
  "geometry": {"coordinates":[145.058349609,-37.9209022522],"type":"Point"}
}