{
  "type": "Feature",
  "properties": {
    "addr:full":"1 Broad St Sarina QLD 4737",
    "addr:housenumber":"1",
    "addr:postcode":"4737",
    "addr:street":"Broad St",
    "iso:country":"AU",
    "sg:address":"1 Broad St",
    "sg:city":"Sarina",
    "sg:classifiers":[
        {
            "category":"Food & Beverages",
            "subcategory":"Supermarket",
            "type":"Retail Goods"
        }
    ],
    "sg:phone":"+61 7 4956 1586",
    "sg:postcode":"4737",
    "sg:province":"QLD",
    "sg:tags":[
        "grocery",
        "store"
    ],
    "wof:name":"Sarina Supermarket",
    "wof:placetype":"venue"
},
  "geometry": {"coordinates":[149.217758,-21.425339],"type":"Point"}
}