{
  "type": "Feature",
  "properties": {
    "addr:full":"139 Main Rd Sorell TAS 7172",
    "addr:housenumber":"139",
    "addr:postcode":"7172",
    "addr:street":"Main Rd",
    "iso:country":"AU",
    "sg:address":"139 Main Rd",
    "sg:city":"Sorell",
    "sg:classifiers":[
        {
            "category":"Home & Garden",
            "subcategory":"Garden Supply",
            "type":"Retail Goods"
        }
    ],
    "sg:phone":"+61 3 6265 3031",
    "sg:postcode":"7172",
    "sg:province":"TAS",
    "sg:tags":[
        "landscape"
    ],
    "wof:name":"South East Garden Centre & Landscaping",
    "wof:placetype":"venue"
},
  "geometry": {"coordinates":[147.563598633,-42.7815818787],"type":"Point"}
}