{
  "type": "Feature",
  "properties": {
    "iso:country":"AU",
    "sg:address":"19 Marsh St",
    "sg:city":"Mackay",
    "sg:classifiers":[
        {
            "category":"Health Services",
            "subcategory":"Health Practitioner",
            "type":"Services"
        }
    ],
    "sg:phone":"+61 417 748 162",
    "sg:postcode":"4740",
    "sg:province":"QLD",
    "sg:tags":[
        "alternative"
    ],
    "wof:name":"Complementary Therapies Clinic",
    "wof:placetype":"venue"
},
  "geometry": {"coordinates":[149.197266,-21.152328],"type":"Point"}
}