{
  "type": "Feature",
  "properties": {
    "addr:full":"PO Box 774 Moss Vale NSW 2577",
    "addr:postcode":"2577",
    "iso:country":"AU",
    "sg:address":"PO Box 774",
    "sg:city":"Moss Vale",
    "sg:classifiers":[
        {
            "category":"Utilities",
            "subcategory":"Electric",
            "type":"Services"
        }
    ],
    "sg:phone":"+61 417 287 767",
    "sg:postcode":"2577",
    "sg:province":"NSW",
    "sg:tags":[
        "electrical",
        "contractor"
    ],
    "wof:name":"Patrick O' Farrell",
    "wof:placetype":"venue"
},
  "geometry": {"coordinates":[150.371170044,-34.5501289368],"type":"Point"}
}