{
  "type": "Feature",
  "properties": {
    "iso:country":"AU",
    "sg:address":"15 Warili St",
    "sg:city":"Aitkenvale",
    "sg:classifiers":[
        {
            "category":"Professional",
            "subcategory":"Business Services",
            "type":"Services"
        }
    ],
    "sg:phone":"+61 7 4725 2972",
    "sg:postcode":"4814",
    "sg:province":"QLD",
    "sg:tags":[
        "small",
        "advisory"
    ],
    "wof:name":"Target Force Sales",
    "wof:placetype":"venue"
},
  "geometry": {"coordinates":[146.776932,-19.295107],"type":"Point"}
}