{
  "type": "Feature",
  "properties": {
    "addr:full":"7 Bellevue Pde Caringbah NSW 2229",
    "addr:housenumber":"7",
    "addr:postcode":"2229",
    "addr:street":"Bellevue Pde",
    "iso:country":"AU",
    "sg:address":"7 Bellevue Pde",
    "sg:city":"Caringbah",
    "sg:classifiers":[
        {
            "category":"Building & Trades",
            "subcategory":"Cleaning & Sanitation",
            "type":"Services"
        }
    ],
    "sg:phone":"+61 2 9525 3663",
    "sg:postcode":"2229",
    "sg:province":"NSW",
    "sg:tags":[
        "cleaner",
        "repairer",
        "roof"
    ],
    "wof:name":"The Roof Doctor",
    "wof:placetype":"venue"
},
  "geometry": {"coordinates":[151.12763977,-34.0401992798],"type":"Point"}
}