{
  "type": "Feature",
  "properties": {
    "addr:full":"Cnr Belconnen Way & Springvale Drv Belconnen ACT 2617",
    "addr:postcode":"2617",
    "addr:street":"Belconnen Way & Springvale Drv",
    "iso:country":"AU",
    "sg:address":"Cnr Belconnen Way & Springvale Drv",
    "sg:city":"Belconnen",
    "sg:classifiers":[
        {
            "category":"Travel",
            "subcategory":"Hotels & Motels",
            "type":"Entertainment"
        }
    ],
    "sg:phone":"+61 2 6254 2222",
    "sg:postcode":"2617",
    "sg:province":"ACT",
    "wof:name":"Belconnen Way Motel & Serviced Apartments",
    "wof:placetype":"venue"
},
  "geometry": {"coordinates":[149.06056213400001,-35.2445869446],"type":"Point"}
}