{
  "type": "Feature",
  "properties": {
    "addr:full":"Heatherhill Rd Frankston VIC 3199",
    "addr:postcode":"3199",
    "addr:street":"Heatherhill Rd",
    "iso:country":"AU",
    "sg:address":"Heatherhill Rd",
    "sg:city":"Frankston",
    "sg:classifiers":[
        {
            "category":"Banks & Credit Unions",
            "subcategory":"Investment Brokerage",
            "type":"Services"
        }
    ],
    "sg:phone":"+61 3 9785 6200",
    "sg:postcode":"3199",
    "sg:province":"VIC",
    "sg:tags":[
        "debt",
        "collection"
    ],
    "wof:name":"Credit Management Services",
    "wof:placetype":"venue"
},
  "geometry": {"coordinates":[145.13479614299999,-38.1575050354],"type":"Point"}
}