{
  "type": "Feature",
  "properties": {
    "addr:full":"162 Blues Point Rd North Sydney NSW 2060",
    "addr:housenumber":"162",
    "addr:postcode":"2060",
    "addr:street":"Blues Point Rd",
    "iso:country":"AU",
    "sg:address":"162 Blues Point Rd",
    "sg:city":"North Sydney",
    "sg:classifiers":[
        {
            "category":"Organizations",
            "subcategory":"Professional Association",
            "type":"Services"
        }
    ],
    "sg:phone":"+61 2 9954 7777",
    "sg:postcode":"2060",
    "sg:province":"NSW",
    "sg:tags":[
        "web",
        "internet"
    ],
    "wof:name":"Airwaves Sound Studio",
    "wof:placetype":"venue"
},
  "geometry": {"coordinates":[151.204421997,-33.843711853],"type":"Point"}
}