{
  "type": "Feature",
  "properties": {
    "iso:country":"AU",
    "sg:address":"185a Burwood Rd",
    "sg:city":"Burwood",
    "sg:classifiers":[
        {
            "category":"Communications",
            "subcategory":"Film & Video Production",
            "type":"Services"
        }
    ],
    "sg:phone":"+61 2 9744 2800",
    "sg:postcode":"2134",
    "sg:province":"NSW",
    "sg:tags":[
        "dvd",
        "library"
    ],
    "wof:name":"Family Videoland Burwood",
    "wof:placetype":"venue"
},
  "geometry": {"coordinates":[151.10299682600001,-33.8799705505],"type":"Point"}
}