{
  "type": "Feature",
  "properties": {
    "iso:country":"AU",
    "sg:address":"1st Floor, 865 Hay St",
    "sg:city":"Perth",
    "sg:classifiers":[
        {
            "category":"Banks & Credit Unions",
            "subcategory":"Financial Services",
            "type":"Services"
        }
    ],
    "sg:phone":"+61 8 9322 6563",
    "sg:postcode":"6000",
    "sg:province":"WA",
    "sg:tags":[
        "settlement",
        "nt",
        "agent",
        "wa"
    ],
    "wof:name":"Cloisters Settlement Services",
    "wof:placetype":"venue"
},
  "geometry": {"coordinates":[115.851318359,-31.9518203735],"type":"Point"}
}