{
  "type": "Feature",
  "properties": {
    "addr:full":"67 Oldaker St Devonport TAS 7310",
    "addr:housenumber":"67",
    "addr:postcode":"7310",
    "addr:street":"Oldaker St",
    "iso:country":"AU",
    "sg:address":"67 Oldaker St",
    "sg:city":"Devonport",
    "sg:classifiers":[
        {
            "category":"Health Services",
            "subcategory":"Dentist",
            "type":"Services"
        }
    ],
    "sg:phone":"+61 3 6424 1232",
    "sg:postcode":"7310",
    "sg:province":"TAS",
    "wof:name":"Young Jeffrey K Dr",
    "wof:placetype":"venue"
},
  "geometry": {"coordinates":[146.3540802,-41.1758842468],"type":"Point"}
}