{
  "type": "Feature",
  "properties": {
    "addr:full":"Sturt Hwy Truro SA 5356",
    "addr:postcode":"5356",
    "addr:street":"Sturt Hwy",
    "iso:country":"AU",
    "sg:address":"Sturt Hwy",
    "sg:city":"Truro",
    "sg:classifiers":[
        {
            "category":"Restaurant",
            "type":"Food & Drink"
        }
    ],
    "sg:phone":"+61 8 8564 0286",
    "sg:postcode":"5356",
    "sg:province":"SA",
    "sg:tags":[
        "roadhouse"
    ],
    "wof:name":"Golden Grill Restaurant & Service Station",
    "wof:placetype":"venue"
},
  "geometry": {"coordinates":[139.132888794,-34.409526825],"type":"Point"}
}