{
  "type": "Feature",
  "properties": {
    "addr:full":"6 Sunter St Strathalbyn SA 5255",
    "addr:housenumber":"6",
    "addr:postcode":"5255",
    "addr:street":"Sunter St",
    "iso:country":"AU",
    "sg:address":"6 Sunter St",
    "sg:city":"Strathalbyn",
    "sg:classifiers":[
        {
            "category":"Real Estate",
            "subcategory":"Real Estate Agent",
            "type":"Services"
        }
    ],
    "sg:phone":"+61 8 8536 2600",
    "sg:postcode":"5255",
    "sg:province":"SA",
    "wof:name":"Dowling City Country",
    "wof:placetype":"venue"
},
  "geometry": {"coordinates":[138.892379761,-35.2557411194],"type":"Point"}
}