{
  "type": "Feature",
  "properties": {
    "iso:country":"AU",
    "sg:address":"4 Market St",
    "sg:city":"Woolgoolga",
    "sg:classifiers":[
        {
            "category":"Communications",
            "subcategory":"Film & Video Production",
            "type":"Services"
        }
    ],
    "sg:phone":"+61 2 6654 2166",
    "sg:postcode":"2456",
    "sg:province":"NSW",
    "sg:tags":[
        "dvd",
        "library"
    ],
    "wof:name":"Top Video",
    "wof:placetype":"venue"
},
  "geometry": {"coordinates":[153.20056199999999,-30.111355],"type":"Point"}
}