{
  "type": "Feature",
  "properties": {
    "addr:full":"91 Cunningham St Dalby QLD 4405",
    "addr:housenumber":"91",
    "addr:postcode":"4405",
    "addr:street":"Cunningham St",
    "iso:country":"AU",
    "sg:address":"91 Cunningham St",
    "sg:city":"Dalby",
    "sg:classifiers":[
        {
            "category":"Professional",
            "subcategory":"Printing & Photocopies",
            "type":"Services"
        }
    ],
    "sg:phone":"+61 7 4662 4084",
    "sg:postcode":"4405",
    "sg:province":"QLD",
    "sg:tags":[
        "photocopying"
    ],
    "wof:name":"Dalby Colour Innovations",
    "wof:placetype":"venue"
},
  "geometry": {"coordinates":[151.26463317899999,-27.1824169159],"type":"Point"}
}