{
  "type": "Feature",
  "properties": {
    "addr:full":"1 Greenleaf St Old Toongabbie NSW 2146",
    "addr:housenumber":"1",
    "addr:postcode":"2146",
    "addr:street":"Greenleaf St",
    "iso:country":"AU",
    "sg:address":"1 Greenleaf St",
    "sg:city":"Old Toongabbie",
    "sg:classifiers":[
        {
            "category":"Professional",
            "subcategory":"Art Services",
            "type":"Services"
        }
    ],
    "sg:phone":"+61 2 9896 8950",
    "sg:postcode":"2146",
    "sg:province":"NSW",
    "sg:tags":[
        "graphic",
        "designer"
    ],
    "wof:name":"T M Graphic Design",
    "wof:placetype":"venue"
},
  "geometry": {"coordinates":[150.97340393100001,-33.7920913696],"type":"Point"}
}