{
  "type": "Feature",
  "properties": {
    "iso:country":"AU",
    "sg:address":"326 New South Head Rd",
    "sg:city":"Double Bay",
    "sg:classifiers":[
        {
            "category":"Travel",
            "subcategory":"Travel Agent",
            "type":"Entertainment"
        }
    ],
    "sg:phone":"+61 2 9327 2011",
    "sg:postcode":"2028",
    "sg:province":"NSW",
    "sg:tags":[
        "consultant"
    ],
    "wof:name":"Double Bay Flight Centre",
    "wof:placetype":"venue"
},
  "geometry": {"coordinates":[151.242279053,-33.8780975342],"type":"Point"}
}