{
  "type": "Feature",
  "properties": {
    "addr:full":"Lot 2 Great Alpine Rd Myrtleford VIC 3737",
    "addr:postcode":"3737",
    "addr:street":"Great Alpine Rd",
    "iso:country":"AU",
    "sg:address":"Lot 2 Great Alpine Rd",
    "sg:city":"Myrtleford",
    "sg:classifiers":[
        {
            "category":"Building & Trades",
            "subcategory":"Cleaning & Sanitation",
            "type":"Services"
        }
    ],
    "sg:phone":"+61 427 737 842",
    "sg:postcode":"3737",
    "sg:province":"VIC",
    "sg:tags":[
        "tank",
        "septic"
    ],
    "wof:name":"North East Liquid Waste",
    "wof:placetype":"venue"
},
  "geometry": {"coordinates":[146.729812622,-36.5664253235],"type":"Point"}
}