{
  "type": "Feature",
  "properties": {
    "iso:country":"AU",
    "sg:address":"Unit 6/ 24 Croydon St",
    "sg:city":"Cronulla",
    "sg:classifiers":[
        {
            "category":"Building & Trades",
            "subcategory":"Plumbing",
            "type":"Services"
        }
    ],
    "sg:phone":"+61 411 548 327",
    "sg:postcode":"2230",
    "sg:province":"NSW",
    "sg:tags":[
        "plumber",
        "gasfitters"
    ],
    "wof:name":"Corey's Plumbing Draining & Gasfitting Service",
    "wof:placetype":"venue"
},
  "geometry": {"coordinates":[151.152633667,-34.0503692627],"type":"Point"}
}