{
  "type": "Feature",
  "properties": {
    "iso:country":"AU",
    "sg:address":"577 Morphett Rd",
    "sg:city":"Seacombe Gardens",
    "sg:classifiers":[
        {
            "category":"Retail",
            "subcategory":"Repair Shop",
            "type":"Services"
        }
    ],
    "sg:phone":"+61 8 8377 2759",
    "sg:postcode":"5047",
    "sg:province":"SA",
    "sg:tags":[
        "upholsterer"
    ],
    "wof:name":"Futuristic Style Pty Ltd",
    "wof:placetype":"venue"
},
  "geometry": {"coordinates":[138.54179400000001,-35.026585],"type":"Point"}
}