{
  "type": "Feature",
  "properties": {
    "addr:full":"Level 2, 44 Bridge St Sydney NSW 2000",
    "addr:housenumber":"44",
    "addr:postcode":"2000",
    "addr:street":"Bridge St",
    "iso:country":"AU",
    "sg:address":"Level 2, 44 Bridge St",
    "sg:city":"Sydney",
    "sg:classifiers":[
        {
            "category":"Health Services",
            "subcategory":"Doctor",
            "type":"Services"
        }
    ],
    "sg:phone":"+61 1300 364 389",
    "sg:postcode":"2000",
    "sg:province":"NSW",
    "sg:tags":[
        "podiatrist"
    ],
    "wof:name":"Bours Paul & Associates",
    "wof:placetype":"venue"
},
  "geometry": {"coordinates":[151.21087646500001,-33.8633155823],"type":"Point"}
}