{
  "type": "Feature",
  "properties": {
    "addr:full":"4 Glenmore Drv Ashmore QLD 4214",
    "addr:housenumber":"4",
    "addr:postcode":"4214",
    "addr:street":"Glenmore Drv",
    "iso:country":"AU",
    "sg:address":"4 Glenmore Drv",
    "sg:city":"Ashmore",
    "sg:classifiers":[
        {
            "category":"Social Services",
            "subcategory":"Adult Care",
            "type":"Services"
        }
    ],
    "sg:phone":"+61 411 719 205",
    "sg:postcode":"4214",
    "sg:province":"QLD",
    "sg:tags":[
        "towing"
    ],
    "wof:name":"Garrards Transport Service G.T.S. Towing",
    "wof:placetype":"venue"
},
  "geometry": {"coordinates":[153.368209839,-27.9911060333],"type":"Point"}
}