{
  "type": "Feature",
  "properties": {
    "iso:country":"AU",
    "sg:address":"River Rd",
    "sg:city":"Cobram",
    "sg:classifiers":[
        {
            "category":"Taxi",
            "type":"Transportation"
        }
    ],
    "sg:phone":"+61 3 5871 1111",
    "sg:postcode":"3644",
    "sg:province":"VIC",
    "sg:tags":[
        "cab"
    ],
    "wof:name":"Cobram Barooga Taxis",
    "wof:placetype":"venue"
},
  "geometry": {"coordinates":[145.66038513199999,-35.9109344482],"type":"Point"}
}