{
  "type": "Feature",
  "properties": {
    "addr:full":"Walker Ave Mannum SA 5238",
    "addr:postcode":"5238",
    "addr:street":"Walker Ave",
    "iso:country":"AU",
    "sg:address":"Walker Ave",
    "sg:city":"Mannum",
    "sg:classifiers":[
        {
            "category":"Education",
            "subcategory":"School",
            "type":"Public Place"
        }
    ],
    "sg:phone":"+61 8 8569 1755",
    "sg:postcode":"5238",
    "sg:province":"SA",
    "sg:tags":[
        "state",
        "except",
        "nsw"
    ],
    "wof:name":"Mannum Primary School",
    "wof:placetype":"venue"
},
  "geometry": {"coordinates":[139.30416870100001,-34.9136009216],"type":"Point"}
}