{
  "type": "Feature",
  "properties": {
    "addr:full":"1 Second St Murray Bridge SA 5253",
    "addr:housenumber":"1",
    "addr:postcode":"5253",
    "addr:street":"Second St",
    "iso:country":"AU",
    "sg:address":"1 Second St",
    "sg:city":"Murray Bridge",
    "sg:classifiers":[
        {
            "category":"Professional",
            "subcategory":"Accounting & Tax Preparation",
            "type":"Services"
        }
    ],
    "sg:phone":"+61 8 8532 5725",
    "sg:postcode":"5253",
    "sg:province":"SA",
    "sg:tags":[
        "accountant",
        "auditor"
    ],
    "wof:name":"N V Accounting Pty Ltd",
    "wof:placetype":"venue"
},
  "geometry": {"coordinates":[139.273162842,-35.1182823181],"type":"Point"}
}