{
  "type": "Feature",
  "properties": {
    "addr:full":"Central Ave Shepparton East VIC 3631",
    "addr:postcode":"3631",
    "addr:street":"Central Ave",
    "iso:country":"AU",
    "sg:address":"Central Ave",
    "sg:city":"Shepparton East",
    "sg:classifiers":[
        {
            "category":"Farming",
            "subcategory":"Orchard",
            "type":"Manufacturing & Wholesale Goods"
        }
    ],
    "sg:phone":"+61 418 371 675",
    "sg:postcode":"3631",
    "sg:province":"VIC",
    "sg:tags":[
        "pear",
        "apple",
        "grower"
    ],
    "wof:name":"Giankos Orchards (Don Giankos)",
    "wof:placetype":"venue"
},
  "geometry": {"coordinates":[145.46191406200001,-36.4048538208],"type":"Point"}
}