{
  "type": "Feature",
  "properties": {
    "addr:full":"58 Madden St Morwell VIC 3840",
    "addr:housenumber":"58",
    "addr:postcode":"3840",
    "addr:street":"Madden St",
    "iso:country":"AU",
    "sg:address":"58 Madden St",
    "sg:city":"Morwell",
    "sg:classifiers":[
        {
            "category":"Professional",
            "subcategory":"Engineering",
            "type":"Services"
        }
    ],
    "sg:phone":"+61 3 5133 9245",
    "sg:postcode":"3840",
    "sg:province":"VIC",
    "sg:tags":[
        "manufacturing",
        "engineer"
    ],
    "wof:name":"R & R Machining & Engineering Pty Ltd",
    "wof:placetype":"venue"
},
  "geometry": {"coordinates":[146.388137817,-38.2304458618],"type":"Point"}
}