{
  "type": "Feature",
  "properties": {
    "addr:full":"Park Centre/ Brittain Rd Bunbury WA 6230",
    "addr:postcode":"6230",
    "addr:street":"Brittain Rd",
    "iso:country":"AU",
    "sg:address":"Park Centre/ Brittain Rd",
    "sg:city":"Bunbury",
    "sg:classifiers":[
        {
            "category":"Fast Food",
            "type":"Food & Drink"
        }
    ],
    "sg:phone":"+61 8 9791 9398",
    "sg:postcode":"6230",
    "sg:province":"WA",
    "sg:tags":[
        "away",
        "take"
    ],
    "wof:name":"Subway Park Centre",
    "wof:placetype":"venue"
},
  "geometry": {"coordinates":[115.64553100000001,-33.359459],"type":"Point"}
}