{
  "type": "Feature",
  "properties": {
    "addr:full":"Cnr Beaumont & Lindsay Sts Hamilton NSW 2303",
    "addr:postcode":"2303",
    "addr:street":"Cnr Beaumont & Lindsay Sts",
    "iso:country":"AU",
    "sg:address":"Cnr Beaumont & Lindsay Sts",
    "sg:city":"Hamilton",
    "sg:classifiers":[
        {
            "category":"Personal",
            "subcategory":"Piercing",
            "type":"Services"
        }
    ],
    "sg:phone":"+61 2 4961 3179",
    "sg:postcode":"2303",
    "sg:province":"NSW",
    "sg:tags":[
        "body",
        "ear"
    ],
    "wof:name":"Hamilton Pharmacy",
    "wof:placetype":"venue"
},
  "geometry": {"coordinates":[151.746994,-32.923527],"type":"Point"}
}