{
  "type": "Feature",
  "properties": {
    "iso:country":"AU",
    "sg:address":"526 Princess Hwy",
    "sg:city":"Rockdale",
    "sg:classifiers":[
        {
            "category":"Personal",
            "subcategory":"Beauty Salon",
            "type":"Services"
        }
    ],
    "sg:phone":"+61 2 9597 6977",
    "sg:postcode":"2216",
    "sg:province":"NSW",
    "sg:tags":[
        "hairdresser"
    ],
    "wof:name":"Secret Delarossi Hair & Beauty",
    "wof:placetype":"venue"
},
  "geometry": {"coordinates":[151.137711,-33.953156],"type":"Point"}
}