{
  "type": "Feature",
  "properties": {
    "iso:country":"AU",
    "sg:address":"Cnr Hawker Pl & Beetaloo St",
    "sg:city":"Hawker",
    "sg:classifiers":[
        {
            "category":"Health Services",
            "subcategory":"Health Practitioner",
            "type":"Services"
        }
    ],
    "sg:phone":"+61 2 6255 2033",
    "sg:postcode":"2614",
    "sg:province":"ACT",
    "sg:tags":[
        "physiotherapist"
    ],
    "wof:name":"Kellett Jennifer Physiotherapy",
    "wof:placetype":"venue"
},
  "geometry": {"coordinates":[149.04234314000001,-35.2431564331],"type":"Point"}
}