{
  "type": "Feature",
  "properties": {
    "addr:full":"267 Bambra Rd Caulfield South VIC 3162",
    "addr:housenumber":"267",
    "addr:postcode":"3162",
    "addr:street":"Bambra Rd",
    "iso:country":"AU",
    "sg:address":"267 Bambra Rd",
    "sg:city":"Caulfield South",
    "sg:classifiers":[
        {
            "category":"Retail",
            "subcategory":"Self-service Laundry",
            "type":"Services"
        }
    ],
    "sg:phone":"+61 3 9528 2126",
    "sg:postcode":"3162",
    "sg:province":"VIC",
    "wof:name":"Bambra Laundry",
    "wof:placetype":"venue"
},
  "geometry": {"coordinates":[145.02775573700001,-37.8922920227],"type":"Point"}
}