{
  "type": "Feature",
  "properties": {
    "addr:full":"Unit 3/ 3 Glenwood Drv Thornton NSW 2322",
    "addr:housenumber":"3",
    "addr:postcode":"2322",
    "addr:street":"Glenwood Drv",
    "iso:country":"AU",
    "sg:address":"Unit 3/ 3 Glenwood Drv",
    "sg:city":"Thornton",
    "sg:classifiers":[
        {
            "category":"Utilities",
            "subcategory":"Telephone",
            "type":"Services"
        }
    ],
    "sg:phone":"+61 2 4966 0391",
    "sg:postcode":"2322",
    "sg:province":"NSW",
    "sg:tags":[
        "equipment",
        "system"
    ],
    "wof:name":"Pinpoint Computer Services",
    "wof:placetype":"venue"
},
  "geometry": {"coordinates":[151.636062622,-32.7904319763],"type":"Point"}
}