{
  "type": "Feature",
  "properties": {
    "addr:full":"Unit 3/ 74 Grange Rd Sandringham VIC 3191",
    "addr:housenumber":"74",
    "addr:postcode":"3191",
    "addr:street":"Grange Rd",
    "iso:country":"AU",
    "sg:address":"Unit 3/ 74 Grange Rd",
    "sg:city":"Sandringham",
    "sg:classifiers":[
        {
            "category":"Real Estate",
            "subcategory":"Real Estate Agent",
            "type":"Services"
        }
    ],
    "sg:phone":"+61 3 9598 8019",
    "sg:postcode":"3191",
    "sg:province":"VIC",
    "sg:tags":[
        "handyman's",
        "equipment",
        "hire",
        "builders",
        "contractor"
    ],
    "wof:name":"Port-A-Fence Hire",
    "wof:placetype":"venue"
},
  "geometry": {"coordinates":[145.01934814399999,-37.9488220215],"type":"Point"}
}