{
  "type": "Feature",
  "properties": {
    "addr:full":"8 Kemble Crt Mitchell ACT 2911",
    "addr:housenumber":"8",
    "addr:postcode":"2911",
    "addr:street":"Kemble Crt",
    "iso:country":"AU",
    "sg:address":"8 Kemble Crt",
    "sg:city":"Mitchell",
    "sg:classifiers":[
        {
            "category":"Professional",
            "type":"Services"
        }
    ],
    "sg:phone":"+61 2 6241 2737",
    "sg:postcode":"2911",
    "sg:province":"ACT",
    "sg:tags":[
        "spray",
        "painting"
    ],
    "wof:name":"Gungahlin Bodyworks",
    "wof:placetype":"venue"
},
  "geometry": {"coordinates":[149.13888549800001,-35.2204437256],"type":"Point"}
}