{
  "type": "Feature",
  "properties": {
    "addr:full":"130 Cabarita Rd Cabarita Beach NSW 2488",
    "addr:housenumber":"130",
    "addr:postcode":"2488",
    "addr:street":"Cabarita Rd",
    "iso:country":"AU",
    "sg:address":"130 Cabarita Rd",
    "sg:city":"Cabarita Beach",
    "sg:classifiers":[
        {
            "category":"Professional",
            "subcategory":"Business Services",
            "type":"Services"
        }
    ],
    "sg:phone":"+61 2 6676 2646",
    "sg:postcode":"2488",
    "sg:province":"NSW",
    "sg:tags":[
        "consultant",
        "system"
    ],
    "wof:name":"A Letter Way",
    "wof:placetype":"venue"
},
  "geometry": {"coordinates":[153.56596400000001,-28.3409],"type":"Point"}
}