{
  "type": "Feature",
  "properties": {
    "addr:full":"22 Victory Rd Airport West VIC 3042",
    "addr:housenumber":"22",
    "addr:postcode":"3042",
    "addr:street":"Victory Rd",
    "iso:country":"AU",
    "sg:address":"22 Victory Rd",
    "sg:city":"Airport West",
    "sg:classifiers":[
        {
            "category":"Professional",
            "subcategory":"Engineering",
            "type":"Services"
        }
    ],
    "sg:phone":"+61 3 9335 1937",
    "sg:postcode":"3042",
    "sg:province":"VIC",
    "sg:tags":[
        "engineer"
    ],
    "wof:name":"Flocut Engineering Pty Ltd",
    "wof:placetype":"venue"
},
  "geometry": {"coordinates":[144.889968872,-37.7184257507],"type":"Point"}
}