{
  "type": "Feature",
  "properties": {
    "addr:full":"81 Chirnside Drv Chirnside Park VIC 3116",
    "addr:housenumber":"81",
    "addr:postcode":"3116",
    "addr:street":"Chirnside Drv",
    "iso:country":"AU",
    "sg:address":"81 Chirnside Drv",
    "sg:city":"Chirnside Park",
    "sg:classifiers":[
        {
            "category":"Utilities",
            "subcategory":"Refuse",
            "type":"Services"
        }
    ],
    "sg:phone":"+61 408 059 816",
    "sg:postcode":"3116",
    "sg:province":"VIC",
    "sg:tags":[
        "boiler"
    ],
    "wof:name":"Valhalla Engineering",
    "wof:placetype":"venue"
},
  "geometry": {"coordinates":[145.31817626899999,-37.7516822815],"type":"Point"}
}