{
  "type": "Feature",
  "properties": {
    "iso:country":"AU",
    "sg:address":"11 Dreyer St",
    "sg:city":"Meckering",
    "sg:classifiers":[
        {
            "category":"Communications",
            "subcategory":"News Services",
            "type":"Services"
        }
    ],
    "sg:phone":"+61 8 9625 1335",
    "sg:postcode":"6405",
    "sg:province":"WA",
    "sg:tags":[
        "information",
        "tourist",
        "attractions"
    ],
    "wof:name":"Big Camera The - Photography Museum",
    "wof:placetype":"venue"
},
  "geometry": {"coordinates":[117.006980896,-31.6314983368],"type":"Point"}
}