{
  "type": "Feature",
  "properties": {
    "addr:full":"10 Beatham St Sandgate QLD 4017",
    "addr:housenumber":"10",
    "addr:postcode":"4017",
    "addr:street":"Beatham St",
    "iso:country":"AU",
    "sg:address":"10 Beatham St",
    "sg:city":"Sandgate",
    "sg:classifiers":[
        {
            "category":"Personal",
            "subcategory":"Massage",
            "type":"Services"
        }
    ],
    "sg:phone":"+61 7 3269 4549",
    "sg:postcode":"4017",
    "sg:province":"QLD",
    "sg:tags":[
        "therapy"
    ],
    "wof:name":"Tranquill Touch Therapy",
    "wof:placetype":"venue"
},
  "geometry": {"coordinates":[153.07525634800001,-27.3230953217],"type":"Point"}
}