{
  "type": "Feature",
  "properties": {
    "iso:country":"AU",
    "sg:address":"26 Whimbrel Crt",
    "sg:city":"Rosebud West",
    "sg:classifiers":[
        {
            "category":"Building & Trades",
            "subcategory":"Construction",
            "type":"Services"
        }
    ],
    "sg:phone":"+61 3 5981 1377",
    "sg:postcode":"3940",
    "sg:province":"VIC",
    "sg:tags":[
        "earth",
        "excavating",
        "moving",
        "contractor"
    ],
    "wof:name":"Tri-Us Excavations Pty Ltd",
    "wof:placetype":"venue"
},
  "geometry": {"coordinates":[144.88067626899999,-38.3779525757],"type":"Point"}
}