{
  "type": "Feature",
  "properties": {
    "addr:full":"145- 153 Mollison St Kyneton VIC 3444",
    "addr:housenumber":"153",
    "addr:postcode":"3444",
    "addr:street":"Mollison St",
    "iso:country":"AU",
    "sg:address":"145- 153 Mollison St",
    "sg:city":"Kyneton",
    "sg:classifiers":[
        {
            "category":"Home & Garden",
            "subcategory":"Furniture",
            "type":"Retail Goods"
        }
    ],
    "sg:phone":"+61 3 5422 1155",
    "sg:postcode":"3444",
    "sg:province":"VIC",
    "sg:tags":[
        "business"
    ],
    "wof:name":"Edmonds Home Furnishings Pty Ltd",
    "wof:placetype":"venue"
},
  "geometry": {"coordinates":[144.453582764,-37.2463264465],"type":"Point"}
}