{
  "type": "Feature",
  "properties": {
    "addr:full":"PO Box 370 Malanda QLD 4885",
    "addr:postcode":"4885",
    "iso:country":"AU",
    "sg:address":"PO Box 370",
    "sg:city":"Malanda",
    "sg:classifiers":[
        {
            "category":"Food & Beverages",
            "subcategory":"Farmers Market",
            "type":"Retail Goods"
        }
    ],
    "sg:phone":"+61 7 4097 6663",
    "sg:postcode":"4885",
    "sg:province":"QLD",
    "sg:tags":[
        "beekeeper"
    ],
    "wof:name":"Fenwick, Ken",
    "wof:placetype":"venue"
},
  "geometry": {"coordinates":[145.61724853499999,-17.3398303986],"type":"Point"}
}