{
  "type": "Feature",
  "properties": {
    "iso:country":"AU",
    "sg:address":"lot 1421 Hardies St",
    "sg:city":"Port Hedland",
    "sg:classifiers":[
        {
            "category":"Wholesale",
            "subcategory":"Electrical",
            "type":"Manufacturing & Wholesale Goods"
        }
    ],
    "sg:phone":"+61 8 9173 3288",
    "sg:postcode":"6721",
    "sg:province":"WA",
    "sg:tags":[
        "control",
        "equipment",
        "switch"
    ],
    "wof:name":"Auslec",
    "wof:placetype":"venue"
},
  "geometry": {"coordinates":[118.46824646,-20.7532691956],"type":"Point"}
}