{
  "type": "Feature",
  "properties": {
    "addr:full":"21 Maud St Newstead QLD 4006",
    "addr:housenumber":"21",
    "addr:postcode":"4006",
    "addr:street":"Maud St",
    "iso:country":"AU",
    "sg:address":"21 Maud St",
    "sg:city":"Newstead",
    "sg:classifiers":[
        {
            "category":"Retail",
            "subcategory":"Auto Repair",
            "type":"Services"
        }
    ],
    "sg:phone":"+61 7 3252 5228",
    "sg:postcode":"4006",
    "sg:province":"QLD",
    "sg:tags":[
        "repairer",
        "motor",
        "engineer"
    ],
    "wof:name":"B & M Auto Specialists",
    "wof:placetype":"venue"
},
  "geometry": {"coordinates":[153.044677734,-27.4450778961],"type":"Point"}
}