{
  "type": "Feature",
  "properties": {
    "addr:full":"36 Vernon Ave Heidelberg West VIC 3081",
    "addr:housenumber":"36",
    "addr:postcode":"3081",
    "addr:street":"Vernon Ave",
    "iso:country":"AU",
    "sg:address":"36 Vernon Ave",
    "sg:city":"Heidelberg West",
    "sg:classifiers":[
        {
            "category":"Professional",
            "subcategory":"Engineering",
            "type":"Services"
        }
    ],
    "sg:phone":"+61 3 9458 1892",
    "sg:postcode":"3081",
    "sg:province":"VIC",
    "sg:tags":[
        "engineer"
    ],
    "wof:name":"John Bradley Engineering Pty Ltd",
    "wof:placetype":"venue"
},
  "geometry": {"coordinates":[145.05081176799999,-37.7320518494],"type":"Point"}
}