{
  "type": "Feature",
  "properties": {
    "addr:full":"212a Lakemba St Lakemba NSW 2195",
    "addr:housenumber":"212a",
    "addr:postcode":"2195",
    "addr:street":"Lakemba St",
    "iso:country":"AU",
    "sg:address":"212a Lakemba St",
    "sg:city":"Lakemba",
    "sg:classifiers":[
        {
            "category":"Wholesale",
            "subcategory":"Painting Supplies",
            "type":"Manufacturing & Wholesale Goods"
        }
    ],
    "sg:phone":"+61 2 9740 6020",
    "sg:postcode":"2195",
    "sg:province":"NSW",
    "sg:tags":[
        "painter"
    ],
    "wof:name":"Sunlight Paints Pty Ltd",
    "wof:placetype":"venue"
},
  "geometry": {"coordinates":[151.07380699999999,-33.918949],"type":"Point"}
}