{
  "type": "Feature",
  "properties": {
    "addr:full":"65 Coolbellup Ave Coolbellup WA 6163",
    "addr:housenumber":"65",
    "addr:postcode":"6163",
    "addr:street":"Coolbellup Ave",
    "iso:country":"AU",
    "sg:address":"65 Coolbellup Ave",
    "sg:city":"Coolbellup",
    "sg:classifiers":[
        {
            "category":"Health Services",
            "subcategory":"Health Practitioner",
            "type":"Services"
        }
    ],
    "sg:phone":"+61 8 9337 4133",
    "sg:postcode":"6163",
    "sg:province":"WA",
    "sg:tags":[
        "physiotherapist"
    ],
    "wof:name":"Coolbellup Physiotherapy Clinic",
    "wof:placetype":"venue"
},
  "geometry": {"coordinates":[115.80658,-32.081562],"type":"Point"}
}