{
  "type": "Feature",
  "properties": {
    "iso:country":"AU",
    "sg:address":"Cnr Tanby Rd & Mc Bean St",
    "sg:city":"Yeppoon",
    "sg:classifiers":[
        {
            "category":"Retail",
            "subcategory":"Auto Repair",
            "type":"Services"
        }
    ],
    "sg:phone":"+61 7 4939 3210",
    "sg:postcode":"4703",
    "sg:province":"QLD",
    "sg:tags":[
        "repairer",
        "motor",
        "engineer"
    ],
    "wof:name":"Yeppoon Motors",
    "wof:placetype":"venue"
},
  "geometry": {"coordinates":[150.737457275,-23.133939743],"type":"Point"}
}