{
  "type": "Feature",
  "properties": {
    "iso:country":"AU",
    "sg:address":"99 Old Cleveland Rd",
    "sg:city":"Capalaba",
    "sg:classifiers":[
        {
            "category":"Shopping",
            "subcategory":"Pawn Shop",
            "type":"Retail Goods"
        }
    ],
    "sg:phone":"+61 7 3245 1622",
    "sg:postcode":"4157",
    "sg:province":"QLD",
    "sg:tags":[
        "pawnbroker"
    ],
    "wof:name":"Capalaba Cash Cow",
    "wof:placetype":"venue"
},
  "geometry": {"coordinates":[153.19969177199999,-27.5218162537],"type":"Point"}
}