{
  "type": "Feature",
  "properties": {
    "addr:full":"86 Barkly St Mornington VIC 3931",
    "addr:housenumber":"86",
    "addr:postcode":"3931",
    "addr:street":"Barkly St",
    "iso:country":"AU",
    "sg:address":"86 Barkly St",
    "sg:city":"Mornington",
    "sg:classifiers":[
        {
            "category":"Government",
            "subcategory":"Court House",
            "type":"Public Place"
        }
    ],
    "sg:phone":"+61 3 5973 6808",
    "sg:postcode":"3931",
    "sg:province":"VIC",
    "sg:tags":[
        "personal",
        "marriage",
        "family",
        "counselling"
    ],
    "wof:name":"Mornington Womens Counselling Centre",
    "wof:placetype":"venue"
},
  "geometry": {"coordinates":[145.042602539,-38.2194480896],"type":"Point"}
}