{
  "type": "Feature",
  "properties": {
    "iso:country":"AU",
    "sg:address":"17 Nantilla Rd",
    "sg:city":"Clayton North",
    "sg:classifiers":[
        {
            "category":"Manufacturing",
            "subcategory":"Tools & Machinery",
            "type":"Manufacturing & Wholesale Goods"
        }
    ],
    "sg:phone":"+61 3 9566 0666",
    "sg:postcode":"3168",
    "sg:province":"VIC",
    "sg:tags":[
        "earth",
        "excavating",
        "moving",
        "equipment"
    ],
    "wof:name":"William Adams",
    "wof:placetype":"venue"
},
  "geometry": {"coordinates":[145.15025329599999,-37.9111213684],"type":"Point"}
}