{
  "type": "Feature",
  "properties": {
    "iso:country":"AU",
    "sg:address":"Shop 5, 512 Mulgrave Rd",
    "sg:city":"Earlville",
    "sg:classifiers":[
        {
            "category":"Banks & Credit Unions",
            "subcategory":"Bank",
            "type":"Services"
        }
    ],
    "sg:phone":"+61 7 4054 7400",
    "sg:postcode":"4870",
    "sg:province":"QLD",
    "sg:tags":[
        "broker",
        "mortgage"
    ],
    "sg:website":"http://www.premiermortgage.com.au",
    "wof:name":"Premier Mortgage Solutions",
    "wof:placetype":"venue"
},
  "geometry": {"coordinates":[145.73843383799999,-16.9433879852],"type":"Point"}
}