{
  "type": "Feature",
  "properties": {
    "addr:full":"2 Highfield Pl Beaumont Hills NSW 2155",
    "addr:housenumber":"2",
    "addr:postcode":"2155",
    "addr:street":"Highfield Pl",
    "iso:country":"AU",
    "sg:address":"2 Highfield Pl",
    "sg:city":"Beaumont Hills",
    "sg:classifiers":[
        {
            "category":"Building & Trades",
            "subcategory":"Construction",
            "type":"Services"
        }
    ],
    "sg:phone":"+61 2 9629 1562",
    "sg:postcode":"2155",
    "sg:province":"NSW",
    "sg:tags":[
        "contractor"
    ],
    "wof:name":"Attard R J",
    "wof:placetype":"venue"
},
  "geometry": {"coordinates":[150.95018005399999,-33.6978378296],"type":"Point"}
}