{
  "type": "Feature",
  "properties": {
    "iso:country":"AU",
    "sg:address":"1 Grant Crt",
    "sg:city":"Shepparton",
    "sg:classifiers":[
        {
            "category":"Retail",
            "subcategory":"Repair Shop",
            "type":"Services"
        }
    ],
    "sg:phone":"+61 3 5831 2650",
    "sg:postcode":"3630",
    "sg:province":"VIC",
    "sg:tags":[
        "upholsterer"
    ],
    "wof:name":"Solar City Canvas & Upholstery",
    "wof:placetype":"venue"
},
  "geometry": {"coordinates":[145.402877808,-36.3499183655],"type":"Point"}
}