{
  "type": "Feature",
  "properties": {
    "addr:full":"139 Merivale St South Brisbane QLD 4101",
    "addr:housenumber":"139",
    "addr:postcode":"4101",
    "addr:street":"Merivale St",
    "iso:country":"AU",
    "sg:address":"139 Merivale St",
    "sg:city":"South Brisbane",
    "sg:classifiers":[
        {
            "category":"Real Estate",
            "subcategory":"Real Estate Agent",
            "type":"Services"
        }
    ],
    "sg:phone":"+61 7 3870 2425",
    "sg:postcode":"4101",
    "sg:province":"QLD",
    "wof:name":"R.D.P. Business Brokers",
    "wof:placetype":"venue"
},
  "geometry": {"coordinates":[153.02134704599999,-27.481880188],"type":"Point"}
}