{
  "type": "Feature",
  "properties": {
    "addr:full":"14 Carter St Katunga VIC 3640",
    "addr:housenumber":"14",
    "addr:postcode":"3640",
    "addr:street":"Carter St",
    "iso:country":"AU",
    "sg:address":"14 Carter St",
    "sg:city":"Katunga",
    "sg:classifiers":[
        {
            "category":"Professional",
            "type":"Services"
        }
    ],
    "sg:phone":"+61 3 5864 6555",
    "sg:postcode":"3640",
    "sg:province":"VIC",
    "sg:tags":[
        "transport"
    ],
    "wof:name":"Rankin Trans",
    "wof:placetype":"venue"
},
  "geometry": {"coordinates":[145.45474243199999,-35.9993019104],"type":"Point"}
}