{
  "type": "Feature",
  "properties": {
    "addr:full":"170 Cornish St Broken Hill NSW 2880",
    "addr:housenumber":"170",
    "addr:postcode":"2880",
    "addr:street":"Cornish St",
    "iso:country":"AU",
    "sg:address":"170 Cornish St",
    "sg:city":"Broken Hill",
    "sg:classifiers":[
        {
            "category":"Arts & Performance",
            "subcategory":"Music",
            "type":"Entertainment"
        }
    ],
    "sg:phone":"+61 8 8088 4036",
    "sg:postcode":"2880",
    "sg:province":"NSW",
    "sg:tags":[
        "mobile",
        "jockey",
        "disc"
    ],
    "wof:name":"Stevos Sound & Video Services",
    "wof:placetype":"venue"
},
  "geometry": {"coordinates":[141.4427948,-31.9664840698],"type":"Point"}
}