{
  "type": "Feature",
  "properties": {
    "iso:country":"AU",
    "sg:address":"34 Burke St",
    "sg:city":"Concord West",
    "sg:classifiers":[
        {
            "category":"Building & Trades",
            "subcategory":"Plumbing",
            "type":"Services"
        }
    ],
    "sg:phone":"+61 2 9736 1820",
    "sg:postcode":"2138",
    "sg:province":"NSW",
    "sg:tags":[
        "plumber",
        "gasfitters"
    ],
    "wof:name":"Williamson Plumbing Pty Ltd",
    "wof:placetype":"venue"
},
  "geometry": {"coordinates":[151.08811950699999,-33.8458862305],"type":"Point"}
}