{
  "type": "Feature",
  "properties": {
    "addr:full":"7 Boyle Crt West Sunshine West VIC 3020",
    "addr:housenumber":"7",
    "addr:postcode":"3020",
    "addr:street":"Boyle Crt West",
    "iso:country":"AU",
    "sg:address":"7 Boyle Crt",
    "sg:city":"West Sunshine West",
    "sg:classifiers":[
        {
            "category":"Professional",
            "subcategory":"Computer Services",
            "type":"Services"
        }
    ],
    "sg:phone":"+61 3 9352 5544",
    "sg:postcode":"3020",
    "sg:province":"VIC",
    "sg:tags":[
        "consultant",
        "system"
    ],
    "wof:name":"MC1 Video Projector Hire",
    "wof:placetype":"venue"
},
  "geometry": {"coordinates":[144.816025,-37.80209],"type":"Point"}
}