{
  "type": "Feature",
  "properties": {
    "addr:full":"U32/ 45 Powers Rd Seven Hills NSW 2147",
    "addr:postcode":"2147",
    "addr:street":"/ 45 Powers Rd",
    "iso:country":"AU",
    "sg:address":"U32/ 45 Powers Rd",
    "sg:city":"Seven Hills",
    "sg:classifiers":[
        {
            "category":"Retail",
            "subcategory":"Auto Repair",
            "type":"Services"
        }
    ],
    "sg:phone":"+61 2 9624 4555",
    "sg:postcode":"2147",
    "sg:province":"NSW",
    "sg:tags":[
        "muffler",
        "exhaust",
        "system"
    ],
    "wof:name":"Racers Choice Pty Ltd",
    "wof:placetype":"venue"
},
  "geometry": {"coordinates":[150.95780944800001,-33.7758598328],"type":"Point"}
}