{
  "type": "Feature",
  "properties": {
    "addr:full":"PO Box 1110 Sandringham VIC 3191",
    "addr:postcode":"3191",
    "iso:country":"AU",
    "sg:address":"PO Box 1110",
    "sg:city":"Sandringham",
    "sg:classifiers":[
        {
            "category":"Shopping",
            "subcategory":"Pets & Pet Supplies",
            "type":"Retail Goods"
        }
    ],
    "sg:phone":"+61 1300 663 610",
    "sg:postcode":"3191",
    "sg:province":"VIC",
    "sg:tags":[
        "food"
    ],
    "wof:name":"Girls Famous Dog Treat Bakery",
    "wof:placetype":"venue"
},
  "geometry": {"coordinates":[145.01231384299999,-37.9524917603],"type":"Point"}
}