{
  "type": "Feature",
  "properties": {
    "addr:full":"9 Stradbroke Ave Frankston South VIC 3199",
    "addr:housenumber":"9",
    "addr:postcode":"3199",
    "addr:street":"Stradbroke Ave",
    "iso:country":"AU",
    "sg:address":"9 Stradbroke Ave",
    "sg:city":"Frankston South",
    "sg:classifiers":[
        {
            "category":"Structure",
            "subcategory":"Building",
            "type":"Public Place"
        }
    ],
    "sg:phone":"+61 425 830 188",
    "sg:postcode":"3199",
    "sg:province":"VIC",
    "sg:tags":[
        "sail",
        "shade"
    ],
    "wof:name":"Pro\\\\vide Maintenance Services",
    "wof:placetype":"venue"
},
  "geometry": {"coordinates":[145.12207031200001,-38.1629447937],"type":"Point"}
}