{
  "type": "Feature",
  "properties": {
    "iso:country":"AU",
    "sg:address":"Lot 2 Enterprise Pl",
    "sg:city":"Wetherill Park",
    "sg:classifiers":[
        {
            "category":"Wholesale",
            "subcategory":"Furniture",
            "type":"Manufacturing & Wholesale Goods"
        }
    ],
    "sg:phone":"+61 2 9756 1992",
    "sg:postcode":"2164",
    "sg:province":"NSW",
    "sg:tags":[
        "wholesaler",
        "mfrs"
    ],
    "wof:name":"Moshy Furniture Pty Ltd",
    "wof:placetype":"venue"
},
  "geometry": {"coordinates":[150.886795044,-33.8525924683],"type":"Point"}
}