{
  "type": "Feature",
  "properties": {
    "iso:country":"AU",
    "sg:address":"Level 1/ 155 Baroona Rd",
    "sg:city":"Rosalie",
    "sg:classifiers":[
        {
            "category":"Banks & Credit Unions",
            "subcategory":"Bank",
            "type":"Services"
        }
    ],
    "sg:phone":"+61 7 3311 1599",
    "sg:postcode":"4064",
    "sg:province":"QLD",
    "sg:tags":[
        "broker",
        "mortgage"
    ],
    "wof:name":"Astute Financial Management",
    "wof:placetype":"venue"
},
  "geometry": {"coordinates":[152.99736023,-27.4660758972],"type":"Point"}
}