{
  "type": "Feature",
  "properties": {
    "addr:full":"100 St James Rd Heidelberg VIC 3084",
    "addr:housenumber":"100",
    "addr:postcode":"3084",
    "addr:street":"St James Rd",
    "iso:country":"AU",
    "sg:address":"100 St James Rd",
    "sg:city":"Heidelberg",
    "sg:classifiers":[
        {
            "category":"Real Estate",
            "subcategory":"Surveying",
            "type":"Services"
        }
    ],
    "sg:phone":"+61 3 9458 4033",
    "sg:postcode":"3084",
    "sg:province":"VIC",
    "sg:tags":[
        "surveyor",
        "quantity"
    ],
    "wof:name":"Baglin Partners",
    "wof:placetype":"venue"
},
  "geometry": {"coordinates":[145.07330322300001,-37.7482337952],"type":"Point"}
}