{
  "type": "Feature",
  "properties": {
    "addr:full":"974 Toorak Road Camberwell South VIC 3124",
    "addr:housenumber":"974",
    "addr:postcode":"3124",
    "addr:street":"Toorak Road",
    "iso:country":"AU",
    "sg:address":"974 Toorak Road",
    "sg:city":"Camberwell South",
    "sg:classifiers":[
        {
            "category":"Personal",
            "subcategory":"Beauty Salon",
            "type":"Services"
        }
    ],
    "sg:phone":"+61 3 9889 3788",
    "sg:postcode":"3124",
    "sg:province":"VIC",
    "sg:tags":[
        "hairdresser"
    ],
    "wof:name":"Hair@974",
    "wof:placetype":"venue"
},
  "geometry": {"coordinates":[145.07528686500001,-37.8481330872],"type":"Point"}
}