{
  "type": "Feature",
  "properties": {
    "iso:country":"AU",
    "sg:address":"35 Caronia Ave",
    "sg:city":"Cronulla",
    "sg:classifiers":[
        {
            "category":"Professional",
            "subcategory":"Detective & Security Services",
            "type":"Services"
        }
    ],
    "sg:phone":"+61 2 9527 2126",
    "sg:postcode":"2230",
    "sg:province":"NSW",
    "sg:tags":[
        "guard",
        "patrol"
    ],
    "wof:name":"Jensen Security",
    "wof:placetype":"venue"
},
  "geometry": {"coordinates":[151.14466857900001,-34.0502662659],"type":"Point"}
}