{
  "type": "Feature",
  "properties": {
    "addr:full":"Unit 3/ 6 Weedon Cl Belconnen ACT 2617",
    "addr:housenumber":"6",
    "addr:postcode":"2617",
    "addr:street":"Weedon Cl",
    "iso:country":"AU",
    "sg:address":"Unit 3/ 6 Weedon Cl",
    "sg:city":"Belconnen",
    "sg:classifiers":[
        {
            "category":"Shopping",
            "subcategory":"Pawn Shop",
            "type":"Retail Goods"
        }
    ],
    "sg:phone":"+61 2 6253 5377",
    "sg:postcode":"2617",
    "sg:province":"ACT",
    "sg:tags":[
        "pawnbroker"
    ],
    "wof:name":"Cash Converters",
    "wof:placetype":"venue"
},
  "geometry": {"coordinates":[149.068283081,-35.2375068665],"type":"Point"}
}