{
  "type": "Feature",
  "properties": {
    "iso:country":"AU",
    "sg:address":"21 Blackman Pl",
    "sg:city":"Port Lincoln",
    "sg:classifiers":[
        {
            "category":"Shopping",
            "subcategory":"Stationery & Office Supplies",
            "type":"Retail Goods"
        }
    ],
    "sg:phone":"+61 8 8683 0433",
    "sg:postcode":"5606",
    "sg:province":"SA",
    "sg:tags":[
        "packaging",
        "material"
    ],
    "wof:name":"Leader Distributors",
    "wof:placetype":"venue"
},
  "geometry": {"coordinates":[135.860794,-34.726265],"type":"Point"}
}