{
  "type": "Feature",
  "properties": {
    "addr:full":"8 Musgrave Ave Hindmarsh West SA 5007",
    "addr:housenumber":"8",
    "addr:postcode":"5007",
    "addr:street":"Musgrave Ave",
    "iso:country":"AU",
    "sg:address":"8 Musgrave Ave",
    "sg:city":"Hindmarsh West",
    "sg:classifiers":[
        {
            "category":"Building & Trades",
            "subcategory":"Construction",
            "type":"Services"
        }
    ],
    "sg:phone":"+61 8 8340 2663",
    "sg:postcode":"5007",
    "sg:province":"SA",
    "sg:tags":[
        "excavation",
        "foundation"
    ],
    "wof:name":"Valtec Constructions",
    "wof:placetype":"venue"
},
  "geometry": {"coordinates":[138.56182861299999,-34.910118103],"type":"Point"}
}