{
  "type": "Feature",
  "properties": {
    "iso:country":"AU",
    "sg:address":"Shop 3, 272 Clovelly Rd",
    "sg:city":"Clovelly",
    "sg:classifiers":[
        {
            "category":"Professional",
            "subcategory":"Printing & Photocopies",
            "type":"Services"
        }
    ],
    "sg:phone":"+61 2 9664 4052",
    "sg:postcode":"2031",
    "sg:province":"NSW",
    "sg:tags":[
        "trophy"
    ],
    "wof:name":"Jimac Jewellery Pty Ltd",
    "wof:placetype":"venue"
},
  "geometry": {"coordinates":[151.25787353499999,-33.9121284485],"type":"Point"}
}