{
  "type": "Feature",
  "properties": {
    "addr:full":"Shop 10/ 43 Sadgroves Crs Winnellie NT 0820",
    "addr:housenumber":"shop 10 / 43",
    "addr:postcode":"nt 0820",
    "addr:street":"Sadgroves Crs",
    "iso:country":"AU",
    "sg:address":"Shop 10/ 43 Sadgroves Crs",
    "sg:city":"Winnellie",
    "sg:classifiers":[
        {
            "category":"Military Area",
            "subcategory":"Air Force Base",
            "type":"Public Place"
        }
    ],
    "sg:phone":"+61 8 8947 0654",
    "sg:postcode":"0820",
    "sg:province":"NT",
    "sg:tags":[
        "men's",
        "tailor"
    ],
    "wof:name":"Jongs",
    "wof:placetype":"venue"
},
  "geometry": {"coordinates":[130.89439392099999,-12.4263296127],"type":"Point"}
}