{
  "type": "Feature",
  "properties": {
    "addr:full":"Unit 3/ 299 Williamstown Rd Port Melbourne VIC 3207",
    "addr:housenumber":"/ 299",
    "addr:postcode":"3207",
    "addr:street":"Williamstown Rd",
    "iso:country":"AU",
    "sg:address":"Unit 3/ 299 Williamstown Rd",
    "sg:city":"Port Melbourne",
    "sg:classifiers":[
        {
            "category":"Autos & Motor Vehicles",
            "subcategory":"Automobile Sales",
            "type":"Retail Goods"
        }
    ],
    "sg:phone":"+61 3 9646 3955",
    "sg:postcode":"3207",
    "sg:province":"VIC",
    "sg:tags":[
        "car",
        "used"
    ],
    "wof:name":"Car Trade & Finance, Direct",
    "wof:placetype":"venue"
},
  "geometry": {"coordinates":[144.922867,-37.835251],"type":"Point"}
}