{
  "type": "Feature",
  "properties": {
    "addr:full":"437 Guildford Rd Bayswater WA 6053",
    "addr:housenumber":"437",
    "addr:postcode":"6053",
    "addr:street":"Guildford Rd",
    "iso:country":"AU",
    "sg:address":"437 Guildford Rd",
    "sg:city":"Bayswater",
    "sg:classifiers":[
        {
            "category":"Health Services",
            "subcategory":"Health Practitioner",
            "type":"Services"
        }
    ],
    "sg:phone":"+61 8 9271 2477",
    "sg:postcode":"6053",
    "sg:province":"WA",
    "sg:tags":[
        "physiotherapist"
    ],
    "wof:name":"Guildford Rd Physiotherapy",
    "wof:placetype":"venue"
},
  "geometry": {"coordinates":[115.91860199,-31.9242858887],"type":"Point"}
}