{
  "type": "Feature",
  "properties": {
    "addr:full":"U 20,6- 8 Enterprise St Molendinar QLD 4214",
    "addr:housenumber":"20,6 8",
    "addr:postcode":"4214",
    "addr:street":"U;Enterprise St",
    "iso:country":"AU",
    "sg:address":"U 20,6- 8 Enterprise St",
    "sg:city":"Molendinar",
    "sg:classifiers":[
        {
            "category":"Real Estate",
            "subcategory":"Developer",
            "type":"Services"
        }
    ],
    "sg:phone":"+61 7 5527 8262",
    "sg:postcode":"4214",
    "sg:province":"QLD",
    "sg:tags":[
        "development"
    ],
    "wof:name":"Linear Developments Pty Ltd",
    "wof:placetype":"venue"
},
  "geometry": {"coordinates":[153.377807617,-27.9766235352],"type":"Point"}
}