{
  "type": "Feature",
  "properties": {
    "iso:country":"AU",
    "sg:address":"77 Perrin St",
    "sg:city":"Robinvale",
    "sg:classifiers":[
        {
            "category":"Health Services",
            "subcategory":"Chiropractor",
            "type":"Services"
        }
    ],
    "sg:phone":"+61 3 5026 1121",
    "sg:postcode":"3549",
    "sg:province":"VIC",
    "wof:name":"Bodinnar N M Chiropractic Services",
    "wof:placetype":"venue"
},
  "geometry": {"coordinates":[142.772705078,-34.5840072632],"type":"Point"}
}