{
  "type": "Feature",
  "properties": {
    "addr:full":"12 Pauline Ave Dingley Village VIC 3172",
    "addr:housenumber":"12",
    "addr:postcode":"3172",
    "addr:street":"Pauline Ave",
    "iso:country":"AU",
    "sg:address":"12 Pauline Ave",
    "sg:city":"Dingley Village",
    "sg:classifiers":[
        {
            "category":"Fast Food",
            "type":"Food & Drink"
        }
    ],
    "sg:phone":"+61 3 9551 7580",
    "sg:postcode":"3172",
    "sg:province":"VIC",
    "sg:tags":[
        "away",
        "take"
    ],
    "wof:name":"Chopsticks Gourmet",
    "wof:placetype":"venue"
},
  "geometry": {"coordinates":[145.13127136200001,-37.9834671021],"type":"Point"}
}