{
  "type": "Feature",
  "properties": {
    "iso:country":"AU",
    "sg:address":"PO Box 156",
    "sg:city":"Maffra",
    "sg:classifiers":[
        {
            "category":"Social Services",
            "subcategory":"Retirement Home",
            "type":"Services"
        }
    ],
    "sg:phone":"+61 418 330 079",
    "sg:postcode":"3860",
    "sg:province":"VIC",
    "sg:tags":[
        "environmental",
        "consultant",
        "pollution"
    ],
    "wof:name":"Gippsland Vegetation Management",
    "wof:placetype":"venue"
},
  "geometry": {"coordinates":[146.98373413100001,-37.971698761],"type":"Point"}
}