{
  "type": "Feature",
  "properties": {
    "iso:country":"AU",
    "sg:address":"2 Kyogle Pl",
    "sg:city":"Grays Point",
    "sg:phone":"+61 2 9524 2293",
    "sg:postcode":"2232",
    "sg:province":"NSW",
    "wof:name":"Without A Drought",
    "wof:placetype":"venue"
},
  "geometry": {"coordinates":[151.076263428,-34.0571594238],"type":"Point"}
}