{
  "type": "Feature",
  "properties": {
    "iso:country":"AU",
    "sg:address":"3/ 21 Duntroon St",
    "sg:city":"Brendale",
    "sg:classifiers":[
        {
            "category":"Manufacturing",
            "subcategory":"Tools & Machinery",
            "type":"Manufacturing & Wholesale Goods"
        }
    ],
    "sg:phone":"+61 7 3205 1408",
    "sg:postcode":"4500",
    "sg:province":"QLD",
    "sg:tags":[
        "equipment",
        "scale",
        "weighing"
    ],
    "wof:name":"Lift & Weigh",
    "wof:placetype":"venue"
},
  "geometry": {"coordinates":[152.98359680199999,-27.3216934204],"type":"Point"}
}