{
  "type": "Feature",
  "properties": {
    "addr:full":"Shop 1 Woodlake Village Shopping Centre Ellenbrook WA 6069",
    "addr:housenumber":"shop 1",
    "addr:postcode":"6069",
    "addr:street":"Woodlake Village",
    "iso:country":"AU",
    "sg:address":"Shop 1 Woodlake Village Shopping Centre",
    "sg:city":"Ellenbrook",
    "sg:classifiers":[
        {
            "category":"Shopping",
            "subcategory":"Clothing, Apparel, & Fashions",
            "type":"Retail Goods"
        }
    ],
    "sg:phone":"+61 8 9296 9841",
    "sg:postcode":"6069",
    "sg:province":"WA",
    "sg:tags":[
        "recycled",
        "clothing"
    ],
    "wof:name":"Salvation Army Family Stores",
    "wof:placetype":"venue"
},
  "geometry": {"coordinates":[115.97013855,-31.7888202667],"type":"Point"}
}