{
  "type": "Feature",
  "properties": {
    "addr:full":"93 Bannockburn Rd Turramurra NSW 2074",
    "addr:housenumber":"93",
    "addr:postcode":"2074",
    "addr:street":"Bannockburn Rd",
    "iso:country":"AU",
    "sg:address":"93 Bannockburn Rd",
    "sg:city":"Turramurra",
    "sg:classifiers":[
        {
            "category":"Social Services",
            "subcategory":"Child Care",
            "type":"Services"
        }
    ],
    "sg:phone":"+61 2 9440 2848",
    "sg:postcode":"2074",
    "sg:province":"NSW",
    "wof:name":"Heritage House Turramurra",
    "wof:placetype":"venue"
},
  "geometry": {"coordinates":[151.141525269,-33.7269821167],"type":"Point"}
}