{
  "type": "Feature",
  "properties": {
    "addr:full":"79 Church St Hawthorn VIC 3122",
    "addr:housenumber":"79",
    "addr:postcode":"3122",
    "addr:street":"Church St",
    "iso:country":"AU",
    "sg:address":"79 Church St",
    "sg:city":"Hawthorn",
    "sg:classifiers":[
        {
            "category":"Professional",
            "subcategory":"Art Services",
            "type":"Services"
        }
    ],
    "sg:phone":"+61 3 8626 9600",
    "sg:postcode":"3122",
    "sg:province":"VIC",
    "sg:tags":[
        "commercial",
        "artist"
    ],
    "wof:name":"Graphic Innovations",
    "wof:placetype":"venue"
},
  "geometry": {"coordinates":[145.021087647,-37.815738678],"type":"Point"}
}