{
  "type": "Feature",
  "properties": {
    "iso:country":"AU",
    "sg:address":"Netherhill Rd",
    "sg:city":"Kenton Valley",
    "sg:classifiers":[
        {
            "category":"Farming",
            "subcategory":"Berry Farm",
            "type":"Manufacturing & Wholesale Goods"
        }
    ],
    "sg:phone":"+61 8 8389 1046",
    "sg:postcode":"5233",
    "sg:province":"SA",
    "sg:tags":[
        "fruit",
        "grower"
    ],
    "wof:name":"Netherhill Strawberry Farm",
    "wof:placetype":"venue"
},
  "geometry": {"coordinates":[138.89210510300001,-34.8488082886],"type":"Point"}
}