{
  "type": "Feature",
  "properties": {
    "addr:full":"127 Erina St Gosford NSW 2250",
    "addr:housenumber":"127",
    "addr:postcode":"2250",
    "addr:street":"Erina St",
    "iso:country":"AU",
    "sg:address":"127 Erina St",
    "sg:city":"Gosford",
    "sg:classifiers":[
        {
            "category":"Health Services",
            "subcategory":"Doctor",
            "type":"Services"
        }
    ],
    "sg:phone":"+61 2 4325 2482",
    "sg:postcode":"2250",
    "sg:province":"NSW",
    "sg:tags":[
        "medical",
        "practitioner"
    ],
    "wof:name":"Arora Anil, Davies Ian",
    "wof:placetype":"venue"
},
  "geometry": {"coordinates":[151.34434509299999,-33.425365448],"type":"Point"}
}