{
  "type": "Feature",
  "properties": {
    "addr:full":"81 Main St Young NSW 2594",
    "addr:housenumber":"81",
    "addr:postcode":"2594",
    "addr:street":"Main St",
    "iso:country":"AU",
    "sg:address":"81 Main St",
    "sg:city":"Young",
    "sg:classifiers":[
        {
            "category":"Real Estate",
            "subcategory":"Real Estate Agent",
            "type":"Services"
        }
    ],
    "sg:phone":"+61 2 6382 4477",
    "sg:postcode":"2594",
    "sg:province":"NSW",
    "wof:name":"John B McGregor Real Estate",
    "wof:placetype":"venue"
},
  "geometry": {"coordinates":[148.29542541500001,-34.3136634827],"type":"Point"}
}