{
  "type": "Feature",
  "properties": {
    "addr:full":"29- 33 Pittwater Rd Manly NSW 2095",
    "addr:housenumber":"33",
    "addr:postcode":"2095",
    "addr:street":"Pittwater Rd",
    "iso:country":"AU",
    "sg:address":"29- 33 Pittwater Rd",
    "sg:city":"Manly",
    "sg:classifiers":[
        {
            "category":"Sports & Exercise",
            "subcategory":"Gym",
            "type":"Entertainment"
        }
    ],
    "sg:phone":"+61 2 9977 6938",
    "sg:postcode":"2095",
    "sg:province":"NSW",
    "sg:tags":[
        "health",
        "fitness"
    ],
    "wof:name":"New Image Gym & Fitness World",
    "wof:placetype":"venue"
},
  "geometry": {"coordinates":[151.28511047399999,-33.7945175171],"type":"Point"}
}