{
  "type": "Feature",
  "properties": {
    "iso:country":"AU",
    "sg:address":"1/ 215 Pacific Hwy",
    "sg:city":"Charmhaven",
    "sg:classifiers":[
        {
            "category":"Personal",
            "subcategory":"Nail Salon",
            "type":"Services"
        }
    ],
    "sg:phone":"+61 2 4393 3442",
    "sg:postcode":"2263",
    "sg:province":"NSW",
    "sg:tags":[
        "artificial"
    ],
    "wof:name":"Your Hair Nails & Beauty",
    "wof:placetype":"venue"
},
  "geometry": {"coordinates":[151.50314299999999,-33.226963],"type":"Point"}
}