{
  "type": "Feature",
  "properties": {
    "iso:country":"AU",
    "sg:address":"Shp 1/ 346 Elizabeth St",
    "sg:city":"North Hobart",
    "sg:classifiers":[
        {
            "category":"Building & Trades",
            "subcategory":"Landscaping Services",
            "type":"Services"
        }
    ],
    "sg:phone":"+61 3 6234 2710",
    "sg:postcode":"7000",
    "sg:province":"TAS",
    "sg:tags":[
        "market"
    ],
    "wof:name":"Fresco Market",
    "wof:placetype":"venue"
},
  "geometry": {"coordinates":[147.316680908,-42.8744010925],"type":"Point"}
}