{
  "type": "Feature",
  "properties": {
    "iso:country":"AU",
    "sg:address":"66 Bromfield St",
    "sg:city":"Colac",
    "sg:classifiers":[
        {
            "category":"Personal",
            "subcategory":"Beauty Salon",
            "type":"Services"
        }
    ],
    "sg:phone":"+61 3 5231 5568",
    "sg:postcode":"3250",
    "sg:province":"VIC",
    "wof:name":"Duryea D M",
    "wof:placetype":"venue"
},
  "geometry": {"coordinates":[143.585724,-38.341057],"type":"Point"}
}