{
  "type": "Feature",
  "properties": {
    "addr:full":"36 Oxford St Belmont VIC 3216",
    "addr:housenumber":"36",
    "addr:postcode":"3216",
    "addr:street":"Oxford St",
    "iso:country":"AU",
    "sg:address":"36 Oxford St",
    "sg:city":"Belmont",
    "sg:classifiers":[
        {
            "category":"Building & Trades",
            "subcategory":"Construction",
            "type":"Services"
        }
    ],
    "sg:phone":"+61 407 411 993",
    "sg:postcode":"3216",
    "sg:province":"VIC",
    "sg:tags":[
        "renovation",
        "alterations",
        "extension",
        "contractor"
    ],
    "wof:name":"Alterations & Additions",
    "wof:placetype":"venue"
},
  "geometry": {"coordinates":[144.336395264,-38.1776123047],"type":"Point"}
}