{
  "type": "Feature",
  "properties": {
    "addr:full":"24 Wendlebury Rd Chipping Norton NSW 2170",
    "addr:housenumber":"24",
    "addr:postcode":"2170",
    "addr:street":"Wendlebury Rd",
    "iso:country":"AU",
    "sg:address":"24 Wendlebury Rd",
    "sg:city":"Chipping Norton",
    "sg:classifiers":[
        {
            "category":"Wholesale",
            "subcategory":"Furniture",
            "type":"Manufacturing & Wholesale Goods"
        }
    ],
    "sg:phone":"+61 2 9755 2388",
    "sg:postcode":"2170",
    "sg:province":"NSW",
    "sg:tags":[
        "wholesaler",
        "mfrs"
    ],
    "wof:name":"D V Kelly Pty Ltd",
    "wof:placetype":"venue"
},
  "geometry": {"coordinates":[150.957122803,-33.9223213196],"type":"Point"}
}