{
  "type": "Feature",
  "properties": {
    "iso:country":"AU",
    "sg:address":"Panorama Drv",
    "sg:city":"Tweed Heads West",
    "sg:classifiers":[
        {
            "category":"Communications",
            "subcategory":"Film & Video Production",
            "type":"Services"
        }
    ],
    "sg:phone":"+61 7 5599 9338",
    "sg:postcode":"2485",
    "sg:province":"NSW",
    "sg:tags":[
        "dvd",
        "library"
    ],
    "wof:name":"Go Video West Tweed",
    "wof:placetype":"venue"
},
  "geometry": {"coordinates":[153.50514221200001,-28.1909618378],"type":"Point"}
}