{
  "type": "Feature",
  "properties": {
    "addr:full":"2/ 76 Tamar St Ballina NSW 2478",
    "addr:housenumber":"/ 76",
    "addr:postcode":"2478",
    "addr:street":"Tamar St",
    "iso:country":"AU",
    "sg:address":"2/ 76 Tamar St",
    "sg:city":"Ballina",
    "sg:classifiers":[
        {
            "category":"Banks & Credit Unions",
            "subcategory":"Financial Services",
            "type":"Services"
        }
    ],
    "sg:phone":"+61 2 6686 6377",
    "sg:postcode":"2478",
    "sg:province":"NSW",
    "sg:tags":[
        "loan",
        "finance",
        "mortgage"
    ],
    "wof:name":"Westlawn Finance Limited",
    "wof:placetype":"venue"
},
  "geometry": {"coordinates":[153.556396484,-28.8674583435],"type":"Point"}
}