{
  "type": "Feature",
  "properties": {
    "addr:full":"100a Dunbar St Margate QLD 4019",
    "addr:housenumber":"100a",
    "addr:postcode":"4019",
    "addr:street":"Dunbar St",
    "iso:country":"AU",
    "sg:address":"100a Dunbar St",
    "sg:city":"Margate",
    "sg:classifiers":[
        {
            "category":"Home & Garden",
            "subcategory":"Building Materials",
            "type":"Retail Goods"
        }
    ],
    "sg:phone":"+61 7 3885 2439",
    "sg:postcode":"4019",
    "sg:province":"QLD",
    "sg:tags":[
        "lawn",
        "cutting",
        "maintenance"
    ],
    "wof:name":"Alpha Lawns & Gardens",
    "wof:placetype":"venue"
},
  "geometry": {"coordinates":[153.096893311,-27.2459259033],"type":"Point"}
}