{
  "type": "Feature",
  "properties": {
    "addr:full":"251 Princes Hwy Arncliffe NSW 2205",
    "addr:housenumber":"251",
    "addr:postcode":"2205",
    "addr:street":"Princes Hwy",
    "iso:country":"AU",
    "sg:address":"251 Princes Hwy",
    "sg:city":"Arncliffe",
    "sg:classifiers":[
        {
            "category":"Retail",
            "subcategory":"Car Wash",
            "type":"Services"
        }
    ],
    "sg:phone":"+61 2 9567 8000",
    "sg:postcode":"2205",
    "sg:province":"NSW",
    "sg:tags":[
        "truck",
        "cleaning"
    ],
    "wof:name":"P & L Detailing",
    "wof:placetype":"venue"
},
  "geometry": {"coordinates":[151.14428699999999,-33.942085],"type":"Point"}
}