{
  "type": "Feature",
  "properties": {
    "iso:country":"AU",
    "sg:address":"Grnd Flr 36 - 38 Victoria St",
    "sg:city":"Burwood",
    "sg:classifiers":[
        {
            "category":"Health Services",
            "subcategory":"Doctor",
            "type":"Services"
        }
    ],
    "sg:phone":"+61 2 9747 5888",
    "sg:postcode":"2134",
    "sg:province":"NSW",
    "sg:tags":[
        "medical",
        "practitioner"
    ],
    "wof:name":"Davies Campbell de Lambert Pathology",
    "wof:placetype":"venue"
},
  "geometry": {"coordinates":[151.105865478,-33.8752937317],"type":"Point"}
}