{
  "type": "Feature",
  "properties": {
    "iso:country":"AU",
    "sg:address":"55 Winton Rd",
    "sg:city":"Joondalup",
    "sg:classifiers":[
        {
            "category":"Wholesale",
            "subcategory":"Machinery & Supplies",
            "type":"Manufacturing & Wholesale Goods"
        }
    ],
    "sg:phone":"+61 8 9300 8822",
    "sg:postcode":"6027",
    "sg:province":"WA",
    "sg:tags":[
        "agricultural"
    ],
    "wof:name":"Devree Equipment Sales",
    "wof:placetype":"venue"
},
  "geometry": {"coordinates":[115.76045227,-31.7471218109],"type":"Point"}
}