{
  "type": "Feature",
  "properties": {
    "addr:full":"1 Park Rd Maryborough VIC 3465",
    "addr:housenumber":"1",
    "addr:postcode":"3465",
    "addr:street":"Park Rd",
    "iso:country":"AU",
    "sg:address":"1 Park Rd",
    "sg:city":"Maryborough",
    "sg:classifiers":[
        {
            "category":"Restaurant",
            "type":"Food & Drink"
        }
    ],
    "sg:phone":"+61 3 5460 5003",
    "sg:postcode":"3465",
    "sg:province":"VIC",
    "wof:name":"Bumpers Woodoven Bakery",
    "wof:placetype":"venue"
},
  "geometry": {"coordinates":[143.740142822,-37.0437736511],"type":"Point"}
}