{
  "type": "Feature",
  "properties": {
    "addr:full":"16 Mehaffey Crs Theodore ACT 2905",
    "addr:housenumber":"16",
    "addr:postcode":"2905",
    "addr:street":"Mehaffey Crs",
    "iso:country":"AU",
    "sg:address":"16 Mehaffey Crs",
    "sg:city":"Theodore",
    "sg:classifiers":[
        {
            "category":"Shopping",
            "subcategory":"Bicycles & Sporting Goods",
            "type":"Retail Goods"
        }
    ],
    "sg:phone":"+61 2 6291 3340",
    "sg:postcode":"2905",
    "sg:province":"ACT",
    "sg:tags":[
        "synthetic",
        "surface"
    ],
    "wof:name":"Allsport Synthetic Surfaces",
    "wof:placetype":"venue"
},
  "geometry": {"coordinates":[149.124557495,-35.4470710754],"type":"Point"}
}