{
  "type": "Feature",
  "properties": {
    "iso:country":"AU",
    "sg:address":"9 Bronhill Crt",
    "sg:city":"Golden Grove",
    "sg:classifiers":[
        {
            "category":"Home & Garden",
            "subcategory":"Carpets & Floor Coverings",
            "type":"Retail Goods"
        }
    ],
    "sg:phone":"+61 412 581 050",
    "sg:postcode":"5125",
    "sg:province":"SA",
    "sg:tags":[
        "tile",
        "wall",
        "layer"
    ],
    "wof:name":"Byrne Tiling",
    "wof:placetype":"venue"
},
  "geometry": {"coordinates":[138.70001199999999,-34.790085],"type":"Point"}
}