{
  "type": "Feature",
  "properties": {
    "addr:full":"700 Sydney Rd Coburg VIC 3058",
    "addr:housenumber":"700",
    "addr:postcode":"3058",
    "addr:street":"Sydney Rd",
    "iso:country":"AU",
    "sg:address":"700 Sydney Rd",
    "sg:city":"Coburg",
    "sg:classifiers":[
        {
            "category":"Building & Trades",
            "subcategory":"Equipment Rental",
            "type":"Services"
        }
    ],
    "sg:phone":"+61 3 9354 1400",
    "sg:postcode":"3058",
    "sg:province":"VIC",
    "sg:tags":[
        "hire",
        "catering"
    ],
    "wof:name":"Kitchens On The Run",
    "wof:placetype":"venue"
},
  "geometry": {"coordinates":[144.96510314899999,-37.732963562],"type":"Point"}
}