{
  "type": "Feature",
  "properties": {
    "addr:full":"238 Taren Point Rd Taren Point NSW 2229",
    "addr:housenumber":"238",
    "addr:postcode":"2229",
    "addr:street":"Taren Point Rd",
    "iso:country":"AU",
    "sg:address":"238 Taren Point Rd",
    "sg:city":"Taren Point",
    "sg:classifiers":[
        {
            "category":"Recreation",
            "subcategory":"Fishing",
            "type":"Entertainment"
        }
    ],
    "sg:phone":"+61 2 9524 4450",
    "sg:postcode":"2229",
    "sg:province":"NSW",
    "sg:tags":[
        "tackle"
    ],
    "wof:name":"Fergo's Tackle World Taren Point",
    "wof:placetype":"venue"
},
  "geometry": {"coordinates":[151.120697022,-34.0263061523],"type":"Point"}
}