{
  "type": "Feature",
  "properties": {
    "addr:full":"44 Mayfield Drv Mt Waverley VIC 3149",
    "addr:housenumber":"44",
    "addr:postcode":"3149",
    "addr:street":"Mayfield Drv Mt",
    "iso:country":"AU",
    "sg:address":"44 Mayfield Drv",
    "sg:city":"Mt Waverley",
    "sg:classifiers":[
        {
            "category":"Building & Trades",
            "subcategory":"Construction",
            "type":"Services"
        }
    ],
    "sg:phone":"+61 3 9515 3672",
    "sg:postcode":"3149",
    "sg:province":"VIC",
    "sg:tags":[
        "contractor"
    ],
    "wof:name":"Bolitho W T",
    "wof:placetype":"venue"
},
  "geometry": {"coordinates":[145.11555480999999,-37.8882713318],"type":"Point"}
}