{
  "type": "Feature",
  "properties": {
    "addr:full":"318a Glenferrie Rd Malvern VIC 3144",
    "addr:housenumber":"318a",
    "addr:postcode":"3144",
    "addr:street":"Glenferrie Rd",
    "iso:country":"AU",
    "sg:address":"318a Glenferrie Rd",
    "sg:city":"Malvern",
    "sg:classifiers":[
        {
            "category":"Shopping",
            "subcategory":"Computers & Home Electronics",
            "type":"Retail Goods"
        }
    ],
    "sg:phone":"+61 3 9822 0674",
    "sg:postcode":"3144",
    "sg:province":"VIC",
    "sg:tags":[
        "equipment",
        "supply"
    ],
    "wof:name":"Apecom",
    "wof:placetype":"venue"
},
  "geometry": {"coordinates":[145.03016662600001,-37.8518676758],"type":"Point"}
}