{
  "type": "Feature",
  "properties": {
    "iso:country":"AU",
    "sg:address":"Solomon St",
    "sg:city":"Mt Waverley",
    "sg:classifiers":[
        {
            "category":"Education",
            "subcategory":"School",
            "type":"Public Place"
        }
    ],
    "sg:phone":"+61 3 9807 8120",
    "sg:postcode":"3149",
    "sg:province":"VIC",
    "sg:tags":[
        "state",
        "except",
        "nsw"
    ],
    "wof:name":"Sussex Heights Primary",
    "wof:placetype":"venue"
},
  "geometry": {"coordinates":[145.11111450199999,-37.8880996704],"type":"Point"}
}