{
  "type": "Feature",
  "properties": {
    "addr:full":"7 Murtho St Renmark SA 5341",
    "addr:housenumber":"7",
    "addr:postcode":"5341",
    "addr:street":"Murtho St",
    "iso:country":"AU",
    "sg:address":"7 Murtho St",
    "sg:city":"Renmark",
    "sg:classifiers":[
        {
            "category":"Insurance",
            "subcategory":"Hazard Insurance",
            "type":"Services"
        }
    ],
    "sg:phone":"+61 8 8586 5791",
    "sg:postcode":"5341",
    "sg:province":"SA",
    "sg:tags":[
        "loss",
        "adjuster",
        "assessor"
    ],
    "wof:name":"Crawford & Company (Riverland)",
    "wof:placetype":"venue"
},
  "geometry": {"coordinates":[140.74357605,-34.1739578247],"type":"Point"}
}