{
  "type": "Feature",
  "properties": {
    "addr:full":"Unit 6 3 Terminus St Castle Hill NSW 2154",
    "addr:housenumber":"3",
    "addr:postcode":"2154",
    "addr:street":"Terminus St",
    "iso:country":"AU",
    "sg:address":"Unit 6 3 Terminus St",
    "sg:city":"Castle Hill",
    "sg:classifiers":[
        {
            "category":"Restaurant",
            "type":"Food & Drink"
        }
    ],
    "sg:phone":"+61 2 9894 8600",
    "sg:postcode":"2154",
    "sg:province":"NSW",
    "wof:name":"Azzurre Restaurant",
    "wof:placetype":"venue"
},
  "geometry": {"coordinates":[151.00674438499999,-33.7332954407],"type":"Point"}
}