{
  "type": "Feature",
  "properties": {
    "addr:full":"105 Pitt St Sydney NSW 2000",
    "addr:housenumber":"105",
    "addr:postcode":"2000",
    "addr:street":"Pitt St",
    "iso:country":"AU",
    "sg:address":"105 Pitt St",
    "sg:city":"Sydney",
    "sg:classifiers":[
        {
            "category":"Professional",
            "subcategory":"Art Services",
            "type":"Services"
        }
    ],
    "sg:phone":"+61 2 9223 5966",
    "sg:postcode":"2000",
    "sg:province":"NSW",
    "sg:tags":[
        "graphic",
        "designer"
    ],
    "sg:website":"http://www.gotham.com.au",
    "wof:name":"Gotham City Press",
    "wof:placetype":"venue"
},
  "geometry": {"coordinates":[151.20846557600001,-33.8659629822],"type":"Point"}
}