{
  "type": "Feature",
  "properties": {
    "addr:full":"5 Shield Crt Leanyer NT 0812",
    "addr:housenumber":"5",
    "addr:postcode":"nt 0812",
    "addr:street":"Shield Crt",
    "iso:country":"AU",
    "sg:address":"5 Shield Crt",
    "sg:city":"Leanyer",
    "sg:classifiers":[
        {
            "category":"Building & Trades",
            "subcategory":"Cleaning & Sanitation",
            "type":"Services"
        }
    ],
    "sg:phone":"+61 8 8927 2338",
    "sg:postcode":"0812",
    "sg:province":"NT",
    "sg:tags":[
        "industrial",
        "commercial",
        "contractor"
    ],
    "wof:name":"Crystal Clear Cleaning Services",
    "wof:placetype":"venue"
},
  "geometry": {"coordinates":[130.89259300000001,-12.37176],"type":"Point"}
}