{
  "type": "Feature",
  "properties": {
    "addr:full":"Shop 5, 158 Pacific Hwy Charlestown NSW 2290",
    "addr:housenumber":"shop 5 158",
    "addr:postcode":"2290",
    "addr:street":"Pacific Hwy",
    "iso:country":"AU",
    "sg:address":"Shop 5, 158 Pacific Hwy",
    "sg:city":"Charlestown",
    "sg:classifiers":[
        {
            "category":"Food & Beverages",
            "subcategory":"Liquor & Beverages",
            "type":"Retail Goods"
        }
    ],
    "sg:phone":"+61 2 4920 8011",
    "sg:postcode":"2290",
    "sg:province":"NSW",
    "sg:tags":[
        "store"
    ],
    "wof:name":"BWS Liquor Stores",
    "wof:placetype":"venue"
},
  "geometry": {"coordinates":[151.695480347,-32.9643096924],"type":"Point"}
}