{
  "type": "Feature",
  "properties": {
    "addr:full":"56 Yadjin Rd Tolga QLD 4882",
    "addr:housenumber":"56",
    "addr:postcode":"4882",
    "addr:street":"Yadjin Rd",
    "iso:country":"AU",
    "sg:address":"56 Yadjin Rd",
    "sg:city":"Tolga",
    "sg:classifiers":[
        {
            "category":"Farming",
            "subcategory":"Farm & Veterinary Services",
            "type":"Manufacturing & Wholesale Goods"
        }
    ],
    "sg:phone":"+61 7 4095 5122",
    "sg:postcode":"4882",
    "sg:province":"QLD",
    "sg:tags":[
        "seedsman"
    ],
    "wof:name":"Atherton Tableland Seed",
    "wof:placetype":"venue"
},
  "geometry": {"coordinates":[145.510986328,-17.208820343],"type":"Point"}
}