{
  "type": "Feature",
  "properties": {
    "addr:full":"Shop 5 398 Tarragindi Rd Moorooka QLD 4105",
    "addr:housenumber":"shop 5",
    "addr:postcode":"398;4105",
    "addr:street":"Tarragindi Rd",
    "iso:country":"AU",
    "sg:address":"Shop 5 398 Tarragindi Rd",
    "sg:city":"Moorooka",
    "sg:classifiers":[
        {
            "category":"Food & Beverages",
            "subcategory":"Liquor & Beverages",
            "type":"Retail Goods"
        }
    ],
    "sg:phone":"+61 7 3392 7050",
    "sg:postcode":"4105",
    "sg:province":"QLD",
    "sg:tags":[
        "store"
    ],
    "wof:name":"BWS Liquor Stores",
    "wof:placetype":"venue"
},
  "geometry": {"coordinates":[153.03257751500001,-27.5353717804],"type":"Point"}
}