{
  "type": "Feature",
  "properties": {
    "iso:country":"AU",
    "sg:address":"1/ 5 Curtis Rd",
    "sg:city":"McGraths Hill",
    "sg:classifiers":[
        {
            "category":"Home & Garden",
            "subcategory":"Carpets & Floor Coverings",
            "type":"Retail Goods"
        }
    ],
    "sg:phone":"+61 2 4577 6955",
    "sg:postcode":"2756",
    "sg:province":"NSW",
    "wof:name":"Allyn Carpet Court",
    "wof:placetype":"venue"
},
  "geometry": {"coordinates":[150.836593628,-33.6229972839],"type":"Point"}
}