{
  "type": "Feature",
  "properties": {
    "addr:full":"23 Anzac St Croydon VIC 3136",
    "addr:housenumber":"23",
    "addr:postcode":"3136",
    "addr:street":"Anzac St",
    "iso:country":"AU",
    "sg:address":"23 Anzac St",
    "sg:city":"Croydon",
    "sg:classifiers":[
        {
            "category":"Building & Trades",
            "subcategory":"Landscaping Services",
            "type":"Services"
        }
    ],
    "sg:phone":"+61 1300 300 828",
    "sg:postcode":"3136",
    "sg:province":"VIC",
    "sg:tags":[
        "consultant"
    ],
    "wof:name":"A AAA Resi-Check",
    "wof:placetype":"venue"
},
  "geometry": {"coordinates":[145.27731323200001,-37.7976837158],"type":"Point"}
}