{
  "type": "Feature",
  "properties": {
    "iso:country":"AU",
    "sg:address":"33 Bolong Rd",
    "sg:city":"Bomaderry",
    "sg:classifiers":[
        {
            "category":"Utilities",
            "subcategory":"Fuel Oil & Lpg",
            "type":"Services"
        }
    ],
    "sg:phone":"+61 2 4423 4200",
    "sg:postcode":"2541",
    "sg:province":"NSW",
    "sg:tags":[
        "heating"
    ],
    "wof:name":"Hill & Co",
    "wof:placetype":"venue"
},
  "geometry": {"coordinates":[150.610565186,-34.8558692932],"type":"Point"}
}