{
  "type": "Feature",
  "properties": {
    "addr:full":"Unit 1/ 32 Greenway Drv Tweed Heads NSW 2485",
    "addr:housenumber":"32",
    "addr:postcode":"2485",
    "addr:street":"Greenway Drv",
    "iso:country":"AU",
    "sg:address":"Unit 1/ 32 Greenway Drv",
    "sg:city":"Tweed Heads",
    "sg:classifiers":[
        {
            "category":"Autos & Motor Vehicles",
            "subcategory":"Auto Supplies",
            "type":"Retail Goods"
        }
    ],
    "sg:phone":"+61 7 5523 1333",
    "sg:postcode":"2485",
    "sg:province":"NSW",
    "sg:tags":[
        "automotive",
        "stereo",
        "radio"
    ],
    "wof:name":"Strathfield",
    "wof:placetype":"venue"
},
  "geometry": {"coordinates":[153.53526306099999,-28.2041873932],"type":"Point"}
}