{
  "type": "Feature",
  "properties": {
    "addr:full":"Shop 8/ 28 Seaport Blv Launceston TAS 7250",
    "addr:housenumber":"shop 8 / 28",
    "addr:postcode":"7250",
    "addr:street":"Seaport Blv",
    "iso:country":"AU",
    "sg:address":"Shop 8/ 28 Seaport Blv",
    "sg:city":"Launceston",
    "sg:classifiers":[
        {
            "category":"Personal",
            "subcategory":"Beauty Salon",
            "type":"Services"
        }
    ],
    "sg:phone":"+61 3 6334 1223",
    "sg:postcode":"7250",
    "sg:province":"TAS",
    "sg:tags":[
        "hairdresser"
    ],
    "wof:name":"Lush Hair Seaport",
    "wof:placetype":"venue"
},
  "geometry": {"coordinates":[147.13299560600001,-41.4327468872],"type":"Point"}
}