{
  "type": "Feature",
  "properties": {
    "addr:full":"27 Welfare Pde Glen Iris VIC 3146",
    "addr:housenumber":"27",
    "addr:postcode":"3146",
    "addr:street":"Welfare Pde",
    "iso:country":"AU",
    "sg:address":"27 Welfare Pde",
    "sg:city":"Glen Iris",
    "sg:classifiers":[
        {
            "category":"Utilities",
            "subcategory":"Electric",
            "type":"Services"
        }
    ],
    "sg:phone":"+61 413 042 469",
    "sg:postcode":"3146",
    "sg:province":"VIC",
    "sg:tags":[
        "electrical",
        "contractor"
    ],
    "wof:name":"Techtrols Pty Ltd",
    "wof:placetype":"venue"
},
  "geometry": {"coordinates":[145.082855225,-37.8595275879],"type":"Point"}
}