{
  "type": "Feature",
  "properties": {
    "addr:full":"33 Botanic Drv Glen Waverley VIC 3150",
    "addr:housenumber":"33",
    "addr:postcode":"3150",
    "addr:street":"Botanic Drv",
    "iso:country":"AU",
    "sg:address":"33 Botanic Drv",
    "sg:city":"Glen Waverley",
    "sg:classifiers":[
        {
            "category":"Retail",
            "subcategory":"Driving School",
            "type":"Services"
        }
    ],
    "sg:phone":"+61 3 9562 1001",
    "sg:postcode":"3150",
    "sg:province":"VIC",
    "wof:name":"Four Wheel Drive Training",
    "wof:placetype":"venue"
},
  "geometry": {"coordinates":[145.16633605999999,-37.8925971985],"type":"Point"}
}