{
  "type": "Feature",
  "properties": {
    "addr:full":"8B/ 12 Barker St Griffith ACT 2603",
    "addr:housenumber":"8b / 12",
    "addr:postcode":"2603",
    "addr:street":"Barker St",
    "iso:country":"AU",
    "sg:address":"8B/ 12 Barker St",
    "sg:city":"Griffith",
    "sg:classifiers":[
        {
            "category":"Health Services",
            "subcategory":"Health Practitioner",
            "type":"Services"
        }
    ],
    "sg:phone":"+61 2 6295 0128",
    "sg:postcode":"2603",
    "sg:province":"ACT",
    "sg:tags":[
        "psychologist"
    ],
    "wof:name":"Griffin Psychology Clinic",
    "wof:placetype":"venue"
},
  "geometry": {"coordinates":[149.14236450199999,-35.3278961182],"type":"Point"}
}