{
  "type": "Feature",
  "properties": {
    "addr:full":"18- 24 The Grange Rd Gleneagle QLD 4285",
    "addr:housenumber":"24",
    "addr:postcode":"4285",
    "addr:street":"The Grange Rd",
    "iso:country":"AU",
    "sg:address":"18- 24 The Grange Rd",
    "sg:city":"Gleneagle",
    "sg:classifiers":[
        {
            "category":"Building & Trades",
            "subcategory":"Construction",
            "type":"Services"
        }
    ],
    "sg:phone":"+61 7 5543 1530",
    "sg:postcode":"4285",
    "sg:province":"QLD",
    "sg:tags":[
        "earth",
        "excavating",
        "moving",
        "contractor"
    ],
    "wof:name":"Johnno's Bobcat & Excavator Hire",
    "wof:placetype":"venue"
},
  "geometry": {"coordinates":[153.001587,-27.941],"type":"Point"}
}