{
  "type": "Feature",
  "properties": {
    "iso:country":"AU",
    "sg:address":"Nicholson Rd",
    "sg:city":"Evanston South",
    "sg:classifiers":[
        {
            "category":"Home & Garden",
            "subcategory":"Building Materials",
            "type":"Retail Goods"
        }
    ],
    "sg:phone":"+61 8 8254 8844",
    "sg:postcode":"5116",
    "sg:province":"SA",
    "sg:tags":[
        "concrete",
        "gutter",
        "kerb"
    ],
    "wof:name":"S.A. Kerbing Pty Ltd",
    "wof:placetype":"venue"
},
  "geometry": {"coordinates":[138.718383789,-34.6512794495],"type":"Point"}
}