{
  "type": "Feature",
  "properties": {
    "addr:full":"Steele Rd Greens Ck Gympie QLD 4570",
    "addr:postcode":"4570",
    "addr:street":"Steele Rd",
    "iso:country":"AU",
    "sg:address":"Steele Rd Greens Ck",
    "sg:city":"Gympie",
    "sg:classifiers":[
        {
            "category":"Professional",
            "subcategory":"Business Services",
            "type":"Services"
        }
    ],
    "sg:phone":"+61 7 5482 4903",
    "sg:postcode":"4570",
    "sg:province":"QLD",
    "sg:tags":[
        "livestock",
        "transport"
    ],
    "wof:name":"Kahler G P & C J",
    "wof:placetype":"venue"
},
  "geometry": {"coordinates":[152.72544860799999,-26.164806366],"type":"Point"}
}