{
  "type": "Feature",
  "properties": {
    "iso:country":"AU",
    "sg:address":"PO Box 800",
    "sg:city":"Swan Hill",
    "sg:classifiers":[
        {
            "category":"Retail",
            "subcategory":"Storage",
            "type":"Services"
        }
    ],
    "sg:phone":"+61 3 5024 6336",
    "sg:postcode":"3585",
    "sg:province":"VIC",
    "sg:tags":[
        "removal",
        "furniture"
    ],
    "wof:name":"Crawford Removals",
    "wof:placetype":"venue"
},
  "geometry": {"coordinates":[143.54852299999999,-35.328381],"type":"Point"}
}