{
  "type": "Feature",
  "properties": {
    "addr:full":"277 Canberra Ave Fyshwick ACT 2609",
    "addr:housenumber":"277",
    "addr:postcode":"2609",
    "addr:street":"Canberra Ave",
    "iso:country":"AU",
    "sg:address":"277 Canberra Ave",
    "sg:city":"Fyshwick",
    "sg:classifiers":[
        {
            "category":"Autos & Motor Vehicles",
            "subcategory":"Automobile Sales",
            "type":"Retail Goods"
        }
    ],
    "sg:phone":"+61 410 576 182",
    "sg:postcode":"2609",
    "sg:province":"ACT",
    "sg:tags":[
        "car",
        "used"
    ],
    "wof:name":"Canberra Used Cars Mark Zanardos",
    "wof:placetype":"venue"
},
  "geometry": {"coordinates":[149.16734314000001,-35.3329277039],"type":"Point"}
}