{
  "type": "Feature",
  "properties": {
    "addr:full":"36 Merrenburn Ave Naremburn NSW 2065",
    "addr:housenumber":"36",
    "addr:postcode":"2065",
    "addr:street":"Merrenburn Ave",
    "iso:country":"AU",
    "sg:address":"36 Merrenburn Ave",
    "sg:city":"Naremburn",
    "sg:classifiers":[
        {
            "category":"Education",
            "subcategory":"Music School",
            "type":"Public Place"
        }
    ],
    "sg:phone":"+61 2 9438 2225",
    "sg:postcode":"2065",
    "sg:province":"NSW",
    "sg:tags":[
        "teacher"
    ],
    "wof:name":"Complete Child & You",
    "wof:placetype":"venue"
},
  "geometry": {"coordinates":[151.201095581,-33.8188285828],"type":"Point"}
}