{
  "type": "Feature",
  "properties": {
    "addr:full":"304 The Entrance Rd Long Jetty NSW 2261",
    "addr:housenumber":"304",
    "addr:postcode":"2261",
    "addr:street":"The Entrance Rd",
    "iso:country":"AU",
    "sg:address":"304 The Entrance Rd",
    "sg:city":"Long Jetty",
    "sg:classifiers":[
        {
            "category":"Fast Food",
            "type":"Food & Drink"
        }
    ],
    "sg:phone":"+61 2 4332 9779",
    "sg:postcode":"2261",
    "sg:province":"NSW",
    "sg:tags":[
        "away",
        "take"
    ],
    "wof:name":"Lunch Break The",
    "wof:placetype":"venue"
},
  "geometry": {"coordinates":[151.48438999999999,-33.359123],"type":"Point"}
}