{
  "type": "Feature",
  "properties": {
    "iso:country":"AU",
    "sg:address":"20 Ascot Drv",
    "sg:city":"Huntingfield",
    "sg:classifiers":[
        {
            "category":"Building & Trades",
            "subcategory":"Plumbing",
            "type":"Services"
        }
    ],
    "sg:phone":"+61 3 6229 5988",
    "sg:postcode":"7055",
    "sg:province":"TAS",
    "sg:tags":[
        "plumber",
        "gasfitters"
    ],
    "wof:name":"J & C Plumbing Pty Ltd",
    "wof:placetype":"venue"
},
  "geometry": {"coordinates":[147.29115300000001,-42.993111],"type":"Point"}
}