{
  "type": "Feature",
  "properties": {
    "addr:full":"41 Liberman Rd Para Hills SA 5096",
    "addr:housenumber":"41",
    "addr:postcode":"5096",
    "addr:street":"Liberman Rd Para",
    "iso:country":"AU",
    "sg:address":"41 Liberman Rd",
    "sg:city":"Para Hills",
    "sg:classifiers":[
        {
            "category":"Education",
            "subcategory":"Kindergarten",
            "type":"Public Place"
        }
    ],
    "sg:phone":"+61 8 8264 1550",
    "sg:postcode":"5096",
    "sg:province":"SA",
    "sg:tags":[
        "pre-schools"
    ],
    "wof:name":"Liberman Kindergarten",
    "wof:placetype":"venue"
},
  "geometry": {"coordinates":[138.656906128,-34.8057403564],"type":"Point"}
}