{
  "type": "Feature",
  "properties": {
    "addr:full":"RMB 6440 Honneckers Rd Buln Buln East VIC 3821",
    "addr:postcode":"3821",
    "addr:street":"Honneckers Rd",
    "iso:country":"AU",
    "sg:address":"RMB 6440 Honneckers Rd",
    "sg:city":"Buln Buln East",
    "sg:classifiers":[
        {
            "category":"Retail",
            "subcategory":"Auto Repair",
            "type":"Services"
        }
    ],
    "sg:phone":"+61 3 5626 6292",
    "sg:postcode":"3821",
    "sg:province":"VIC",
    "sg:tags":[
        "automotive",
        "air conditioning"
    ],
    "wof:name":"McCorriston Refrigeration & Air Conditioning",
    "wof:placetype":"venue"
},
  "geometry": {"coordinates":[146.03166200000001,-38.079296],"type":"Point"}
}