{
  "type": "Feature",
  "properties": {
    "iso:country":"AU",
    "sg:address":"IBM Centre Level 2, 348 Edward St",
    "sg:city":"Brisbane",
    "sg:classifiers":[
        {
            "category":"Health Services",
            "subcategory":"Health Practitioner",
            "type":"Services"
        }
    ],
    "sg:phone":"+61 7 3220 3522",
    "sg:postcode":"4000",
    "sg:province":"QLD",
    "sg:tags":[
        "audiologists"
    ],
    "wof:name":"Neurosensory Unit",
    "wof:placetype":"venue"
},
  "geometry": {"coordinates":[153.02468872099999,-27.465215683],"type":"Point"}
}