{
  "type": "Feature",
  "properties": {
    "addr:full":"79 Princess St East Bundaberg QLD 4670",
    "addr:housenumber":"79",
    "addr:postcode":"4670",
    "addr:street":"Princess St East",
    "iso:country":"AU",
    "sg:address":"79 Princess St",
    "sg:city":"East Bundaberg",
    "sg:classifiers":[
        {
            "category":"Wholesale",
            "subcategory":"Metals & Minerals",
            "type":"Manufacturing & Wholesale Goods"
        }
    ],
    "sg:phone":"+61 7 4132 8888",
    "sg:postcode":"4670",
    "sg:province":"QLD",
    "sg:tags":[
        "steel",
        "merchant"
    ],
    "sg:website":"http://www.onesteel.com",
    "wof:name":"Onesteel Metaland",
    "wof:placetype":"venue"
},
  "geometry": {"coordinates":[152.37156677199999,-24.8564014435],"type":"Point"}
}