{
  "type": "Feature",
  "properties": {
    "iso:country":"AU",
    "sg:address":"U 1/ 264 Tingall Rd",
    "sg:city":"Wynnum",
    "sg:classifiers":[
        {
            "category":"Home & Garden",
            "subcategory":"Hardware",
            "type":"Retail Goods"
        }
    ],
    "sg:phone":"+61 7 3893 3211",
    "sg:postcode":"4178",
    "sg:province":"QLD",
    "sg:tags":[
        "plumber",
        "supply"
    ],
    "wof:name":"Waterloo Bay Plumbing Supplies",
    "wof:placetype":"venue"
},
  "geometry": {"coordinates":[153.16801452600001,-27.4397773743],"type":"Point"}
}