{
  "type": "Feature",
  "properties": {
    "iso:country":"AU",
    "sg:address":"27 McFarlane St",
    "sg:city":"Keilor East",
    "sg:classifiers":[
        {
            "category":"Health Services",
            "subcategory":"Dentist",
            "type":"Services"
        }
    ],
    "sg:phone":"+61 3 9331 1210",
    "sg:postcode":"3033",
    "sg:province":"VIC",
    "wof:name":"Breath Treatment Centre",
    "wof:placetype":"venue"
},
  "geometry": {"coordinates":[144.866425,-37.744579],"type":"Point"}
}