{
  "type": "Feature",
  "properties": {
    "iso:country":"AU",
    "sg:address":"Lot 38 Leeds St",
    "sg:city":"Wingfield",
    "sg:classifiers":[
        {
            "category":"Retail",
            "subcategory":"Auto Repair",
            "type":"Services"
        }
    ],
    "sg:phone":"+61 8 8260 3155",
    "sg:postcode":"5013",
    "sg:province":"SA",
    "sg:tags":[
        "beater",
        "painter",
        "panel"
    ],
    "wof:name":"Wingfield Panel & Chassis Repairs",
    "wof:placetype":"venue"
},
  "geometry": {"coordinates":[138.566696167,-34.8380012512],"type":"Point"}
}