{
  "type": "Feature",
  "properties": {
    "addr:full":"288 Canterbury Rd Surrey Hills VIC 3127",
    "addr:housenumber":"288",
    "addr:postcode":"3127",
    "addr:street":"Canterbury Rd",
    "iso:country":"AU",
    "sg:address":"288 Canterbury Rd",
    "sg:city":"Surrey Hills",
    "sg:classifiers":[
        {
            "category":"Landmark",
            "subcategory":"Square",
            "type":"Public Place"
        }
    ],
    "sg:phone":"+61 3 9836 0836",
    "sg:postcode":"3127",
    "sg:province":"VIC",
    "sg:tags":[
        "lampshade"
    ],
    "wof:name":"Surrey Lighting",
    "wof:placetype":"venue"
},
  "geometry": {"coordinates":[145.08996582,-37.8251571655],"type":"Point"}
}