{
  "type": "Feature",
  "properties": {
    "addr:full":"PO Box 34 Jindera NSW 2642",
    "addr:postcode":"2642",
    "iso:country":"AU",
    "sg:address":"PO Box 34",
    "sg:city":"Jindera",
    "sg:classifiers":[
        {
            "category":"Building & Trades",
            "subcategory":"Construction",
            "type":"Services"
        }
    ],
    "sg:phone":"+61 2 6026 2492",
    "sg:postcode":"2642",
    "sg:province":"NSW",
    "sg:tags":[
        "fencing",
        "contractor"
    ],
    "wof:name":"Whitey's Rural Enterprises",
    "wof:placetype":"venue"
},
  "geometry": {"coordinates":[146.88897705100001,-35.9545898438],"type":"Point"}
}