{
  "type": "Feature",
  "properties": {
    "iso:country":"AU",
    "sg:address":"15 Beilby St",
    "sg:city":"Bayswater",
    "sg:classifiers":[
        {
            "category":"Utilities",
            "subcategory":"Sewage",
            "type":"Services"
        }
    ],
    "sg:phone":"+61 1300 137 691",
    "sg:postcode":"3153",
    "sg:province":"VIC",
    "sg:tags":[
        "arboriculturist"
    ],
    "wof:name":"Root2Leaf Arboricultural Solutions",
    "wof:placetype":"venue"
},
  "geometry": {"coordinates":[145.272994995,-37.851650238],"type":"Point"}
}