{
  "type": "Feature",
  "properties": {
    "iso:country":"AU",
    "sg:address":"37 Ena St",
    "sg:city":"Terrigal",
    "sg:classifiers":[
        {
            "category":"Social Services",
            "subcategory":"Retirement Home",
            "type":"Services"
        }
    ],
    "sg:phone":"+61 423 981 786",
    "sg:postcode":"2260",
    "sg:province":"NSW",
    "sg:tags":[
        "environmental",
        "consultant",
        "pollution"
    ],
    "wof:name":"Pygmy Possum Ecological Consulting",
    "wof:placetype":"venue"
},
  "geometry": {"coordinates":[151.438004,-33.443413],"type":"Point"}
}