{
  "type": "Feature",
  "properties": {
    "addr:full":"37 Ena St Terrigal NSW 2260",
    "addr:housenumber":"37",
    "addr:postcode":"2260",
    "addr:street":"Ena St",
    "iso:country":"AU",
    "sg:address":"37 Ena St",
    "sg:city":"Terrigal",
    "sg:classifiers":[
        {
            "category":"Social Services",
            "subcategory":"Retirement Home",
            "type":"Services"
        }
    ],
    "sg:phone":"+61 423 981 786",
    "sg:postcode":"2260",
    "sg:province":"NSW",
    "sg:tags":[
        "environmental",
        "consultant",
        "pollution"
    ],
    "wof:name":"Pygmy Possum Ecological Consulting",
    "wof:placetype":"venue"
},
  "geometry": {"coordinates":[151.43800400000001,-33.443413],"type":"Point"}
}