{
  "type": "Feature",
  "properties": {
    "addr:full":"Unit 2/ 2 Garden Rd Clayton VIC 3168",
    "addr:housenumber":"2",
    "addr:postcode":"3168",
    "addr:street":"Garden Rd",
    "iso:country":"AU",
    "sg:address":"Unit 2/ 2 Garden Rd",
    "sg:city":"Clayton",
    "sg:classifiers":[
        {
            "category":"Wholesale",
            "subcategory":"Apparel",
            "type":"Manufacturing & Wholesale Goods"
        }
    ],
    "sg:phone":"+61 3 9561 6110",
    "sg:postcode":"3168",
    "sg:province":"VIC",
    "sg:tags":[
        "wholesaler",
        "mfrs",
        "sportswear",
        "women's"
    ],
    "wof:name":"Amco Gymnastics",
    "wof:placetype":"venue"
},
  "geometry": {"coordinates":[145.14718627900001,-37.9176864624],"type":"Point"}
}