{
  "type": "Feature",
  "properties": {
    "addr:full":"Lot 69 45 Great Eastern Hwy Kalgoorlie WA 6430",
    "addr:housenumber":"45",
    "addr:postcode":"6430",
    "addr:street":"Great Eastern Hwy",
    "iso:country":"AU",
    "sg:address":"Lot 69 45 Great Eastern Hwy",
    "sg:city":"Kalgoorlie",
    "sg:classifiers":[
        {
            "category":"Wholesale",
            "subcategory":"Metals & Minerals",
            "type":"Manufacturing & Wholesale Goods"
        }
    ],
    "sg:phone":"+61 8 9024 1388",
    "sg:postcode":"6430",
    "sg:province":"WA",
    "sg:tags":[
        "steel",
        "merchant"
    ],
    "wof:name":"Smorgon Steel",
    "wof:placetype":"venue"
},
  "geometry": {"coordinates":[121.439598084,-30.7759437561],"type":"Point"}
}