{
  "type": "Feature",
  "properties": {
    "addr:full":"Shop 1/ 124-128 Railway Pde Canley Vale NSW 2166",
    "addr:housenumber":"shop 1 / 124-128",
    "addr:postcode":"2166",
    "addr:street":"Railway Pde",
    "iso:country":"AU",
    "sg:address":"Shop 1/ 124-128 Railway Pde",
    "sg:city":"Canley Vale",
    "sg:classifiers":[
        {
            "category":"Home & Garden",
            "subcategory":"Building Materials",
            "type":"Retail Goods"
        }
    ],
    "sg:phone":"+61 2 9728 1218",
    "sg:postcode":"2166",
    "sg:province":"NSW",
    "sg:tags":[
        "merchant",
        "glass",
        "glazier"
    ],
    "wof:name":"NL Glass & Aluminium",
    "wof:placetype":"venue"
},
  "geometry": {"coordinates":[150.94256591800001,-33.8878211975],"type":"Point"}
}