{
  "type": "Feature",
  "properties": {
    "addr:full":"235 Brunswick St Fortitude Valley QLD 4006",
    "addr:housenumber":"235",
    "addr:postcode":"4006",
    "addr:street":"Brunswick St",
    "iso:country":"AU",
    "sg:address":"235 Brunswick St",
    "sg:city":"Fortitude Valley",
    "sg:classifiers":[
        {
            "category":"Insurance",
            "subcategory":"Insurance Agent",
            "type":"Services"
        }
    ],
    "sg:phone":"+61 7 3252 2727",
    "sg:postcode":"4006",
    "sg:province":"QLD",
    "sg:tags":[
        "broker"
    ],
    "wof:name":"Wong R K",
    "wof:placetype":"venue"
},
  "geometry": {"coordinates":[153.03277587900001,-27.4568634033],"type":"Point"}
}