{
  "type": "Feature",
  "properties": {
    "iso:country":"AU",
    "sg:address":"8 Nelson St",
    "sg:city":"Fairfield",
    "sg:classifiers":[
        {
            "category":"Communications",
            "subcategory":"Film & Video Production",
            "type":"Services"
        }
    ],
    "sg:phone":"+61 2 9727 2544",
    "sg:postcode":"2165",
    "sg:province":"NSW",
    "sg:tags":[
        "dvd",
        "library"
    ],
    "wof:name":"Video Ezy",
    "wof:placetype":"venue"
},
  "geometry": {"coordinates":[150.95648193400001,-33.8679275513],"type":"Point"}
}