{
  "type": "Feature",
  "properties": {
    "iso:country":"AU",
    "sg:address":"679 Gympie Rd",
    "sg:city":"Lawnton",
    "sg:classifiers":[
        {
            "category":"Retail",
            "subcategory":"Event Space",
            "type":"Services"
        }
    ],
    "sg:phone":"+61 7 3881 2266",
    "sg:postcode":"4501",
    "sg:province":"QLD",
    "sg:tags":[
        "venue",
        "reception",
        "wedding"
    ],
    "wof:name":"A City Party Hire",
    "wof:placetype":"venue"
},
  "geometry": {"coordinates":[152.982513428,-27.2802600861],"type":"Point"}
}