{
  "type": "Feature",
  "properties": {
    "iso:country":"AU",
    "sg:address":"10 Virginia Rd",
    "sg:city":"Newton",
    "sg:classifiers":[
        {
            "category":"Home & Garden",
            "subcategory":"Building Materials",
            "type":"Retail Goods"
        }
    ],
    "sg:phone":"+61 8 8366 6677",
    "sg:postcode":"5074",
    "sg:province":"SA",
    "sg:tags":[
        "fencing"
    ],
    "wof:name":"Bianco Fencing & Steel Supplies",
    "wof:placetype":"venue"
},
  "geometry": {"coordinates":[138.684524536,-34.8784408569],"type":"Point"}
}