{
  "type": "Feature",
  "properties": {
    "iso:country":"AU",
    "sg:address":"30 Hall Rd",
    "sg:city":"Gympie",
    "sg:classifiers":[
        {
            "category":"Real Estate",
            "subcategory":"Real Estate Agent",
            "type":"Services"
        }
    ],
    "sg:phone":"+61 7 5483 9777",
    "sg:postcode":"4570",
    "sg:province":"QLD",
    "sg:tags":[
        "handyman's",
        "equipment",
        "hire",
        "builders",
        "contractor"
    ],
    "wof:name":"Handy Hire",
    "wof:placetype":"venue"
},
  "geometry": {"coordinates":[152.69456481899999,-26.2210407257],"type":"Point"}
}