{
  "type": "Feature",
  "properties": {
    "addr:full":"Huntriss Rd Karrinyup WA 6018",
    "addr:postcode":"6018",
    "addr:street":"Huntriss Rd",
    "iso:country":"AU",
    "sg:address":"Huntriss Rd",
    "sg:city":"Karrinyup",
    "sg:classifiers":[
        {
            "category":"Arena",
            "subcategory":"Sports Club",
            "type":"Entertainment"
        }
    ],
    "sg:phone":"+61 412 956 742",
    "sg:postcode":"6018",
    "sg:province":"WA",
    "sg:tags":[
        "defence",
        "supply",
        "self",
        "instruction",
        "martial art"
    ],
    "wof:name":"Dalton Martial Arts",
    "wof:placetype":"venue"
},
  "geometry": {"coordinates":[115.787216187,-31.8773117065],"type":"Point"}
}