{
  "type": "Feature",
  "properties": {
    "iso:country":"AU",
    "sg:address":"137 Bomen Rd",
    "sg:city":"Bomen",
    "sg:classifiers":[
        {
            "category":"Cafe",
            "type":"Food & Drink"
        }
    ],
    "sg:phone":"+61 2 6971 7666",
    "sg:postcode":"2650",
    "sg:province":"NSW",
    "wof:name":"Jules' Hot Spot Cafe",
    "wof:placetype":"venue"
},
  "geometry": {"coordinates":[147.41200256400001,-35.0728721619],"type":"Point"}
}