{
  "type": "Feature",
  "properties": {
    "addr:full":"Unit 1/ 43 Shearwater Drv Taylors Beach NSW 2316",
    "addr:housenumber":"43",
    "addr:postcode":"2316",
    "addr:street":"Shearwater Drv",
    "iso:country":"AU",
    "sg:address":"Unit 1/ 43 Shearwater Drv",
    "sg:city":"Taylors Beach",
    "sg:classifiers":[
        {
            "category":"Cafe",
            "type":"Food & Drink"
        }
    ],
    "sg:phone":"+61 2 4982 2208",
    "sg:postcode":"2316",
    "sg:province":"NSW",
    "wof:name":"Shearwater Cafe",
    "wof:placetype":"venue"
},
  "geometry": {"coordinates":[152.070007,-32.752651],"type":"Point"}
}