{
  "type": "Feature",
  "properties": {
    "addr:full":"6 Jersey Rd Woollahra NSW 2025",
    "addr:housenumber":"6",
    "addr:postcode":"2025",
    "addr:street":"Jersey Rd",
    "iso:country":"AU",
    "sg:address":"6 Jersey Rd",
    "sg:city":"Woollahra",
    "sg:classifiers":[
        {
            "category":"Real Estate",
            "subcategory":"Real Estate Agent",
            "type":"Services"
        }
    ],
    "sg:phone":"+61 2 9380 7888",
    "sg:postcode":"2025",
    "sg:province":"NSW",
    "wof:name":"Jocelyn Walker Real Estate",
    "wof:placetype":"venue"
},
  "geometry": {"coordinates":[151.23211669899999,-33.8883018494],"type":"Point"}
}