{
  "type": "Feature",
  "properties": {
    "addr:full":"27 Peacock St Seaforth NSW 2092",
    "addr:housenumber":"27",
    "addr:postcode":"2092",
    "addr:street":"Peacock St",
    "iso:country":"AU",
    "sg:address":"27 Peacock St",
    "sg:city":"Seaforth",
    "sg:classifiers":[
        {
            "category":"Social Services",
            "subcategory":"Child Care",
            "type":"Services"
        }
    ],
    "sg:phone":"+61 2 9949 3503",
    "sg:postcode":"2092",
    "sg:province":"NSW",
    "wof:name":"Peacock Street Long Day Care",
    "wof:placetype":"venue"
},
  "geometry": {"coordinates":[151.24778747600001,-33.7950401306],"type":"Point"}
}