{
  "type": "Feature",
  "properties": {
    "addr:full":"16 David Randall St Williamstown SA 5351",
    "addr:housenumber":"16",
    "addr:postcode":"5351",
    "addr:street":"David Randall St",
    "iso:country":"AU",
    "sg:address":"16 David Randall St",
    "sg:city":"Williamstown",
    "sg:classifiers":[
        {
            "category":"Farming",
            "subcategory":"Farm",
            "type":"Manufacturing & Wholesale Goods"
        }
    ],
    "sg:phone":"+61 8 8524 6320",
    "sg:postcode":"5351",
    "sg:province":"SA",
    "sg:tags":[
        "farmer"
    ],
    "wof:name":"Teusner R G",
    "wof:placetype":"venue"
},
  "geometry": {"coordinates":[138.88519287099999,-34.670085907],"type":"Point"}
}