{
  "type": "Feature",
  "properties": {
    "addr:full":"370 Whitehorse Rd Nunawading VIC 3131",
    "addr:housenumber":"370",
    "addr:postcode":"3131",
    "addr:street":"Whitehorse Rd",
    "iso:country":"AU",
    "sg:address":"370 Whitehorse Rd",
    "sg:city":"Nunawading",
    "sg:classifiers":[
        {
            "category":"Professional",
            "subcategory":"Detective & Security Services",
            "type":"Services"
        }
    ],
    "sg:phone":"+61 3 8878 0866",
    "sg:postcode":"3131",
    "sg:province":"VIC",
    "sg:tags":[
        "consultant",
        "system"
    ],
    "wof:name":"Australian Security Solutions",
    "wof:placetype":"venue"
},
  "geometry": {"coordinates":[145.17831420900001,-37.8187980652],"type":"Point"}
}