{
  "type": "Feature",
  "properties": {
    "iso:country":"AU",
    "sg:address":"68 Winnellie Rd",
    "sg:city":"Winnellie",
    "sg:classifiers":[
        {
            "category":"Manufacturing",
            "subcategory":"Retail Goods",
            "type":"Manufacturing & Wholesale Goods"
        }
    ],
    "sg:phone":"+61 8 8947 1008",
    "sg:postcode":"0820",
    "sg:province":"NT",
    "sg:tags":[
        "merchant",
        "pump",
        "mfrs"
    ],
    "wof:name":"H.D. Pump Sales & Service",
    "wof:placetype":"venue"
},
  "geometry": {"coordinates":[130.878082275,-12.4267578125],"type":"Point"}
}