{
  "type": "Feature",
  "properties": {
    "addr:full":"67 Albion St Warwick QLD 4370",
    "addr:housenumber":"67",
    "addr:postcode":"4370",
    "addr:street":"Albion St",
    "iso:country":"AU",
    "sg:address":"67 Albion St",
    "sg:city":"Warwick",
    "sg:classifiers":[
        {
            "category":"Retail",
            "subcategory":"Event Space",
            "type":"Services"
        }
    ],
    "sg:phone":"+61 7 4661 5288",
    "sg:postcode":"4370",
    "sg:province":"QLD",
    "sg:tags":[
        "venue",
        "reception",
        "wedding"
    ],
    "wof:name":"Chung Hing Licensed Chinese Restaurant",
    "wof:placetype":"venue"
},
  "geometry": {"coordinates":[152.03457641599999,-28.2179279327],"type":"Point"}
}