{
  "type": "Feature",
  "properties": {
    "addr:full":"72 Wentworth St Glen Innes NSW 2370",
    "addr:housenumber":"72",
    "addr:postcode":"2370",
    "addr:street":"Wentworth St",
    "iso:country":"AU",
    "sg:address":"72 Wentworth St",
    "sg:city":"Glen Innes",
    "sg:classifiers":[
        {
            "category":"Home & Garden",
            "subcategory":"Hardware",
            "type":"Retail Goods"
        }
    ],
    "sg:phone":"+61 2 6732 1935",
    "sg:postcode":"2370",
    "sg:province":"NSW",
    "sg:tags":[
        "plumber",
        "supply"
    ],
    "wof:name":"Scotts Paint & Hardware",
    "wof:placetype":"venue"
},
  "geometry": {"coordinates":[151.730300903,-29.7403964996],"type":"Point"}
}