{
  "type": "Feature",
  "properties": {
    "addr:full":"825a New South Head Rd Rose Bay NSW 2029",
    "addr:housenumber":"825a",
    "addr:postcode":"2029",
    "addr:street":"New South Head Rd",
    "iso:country":"AU",
    "sg:address":"825a New South Head Rd",
    "sg:city":"Rose Bay",
    "sg:classifiers":[
        {
            "category":"Personal",
            "subcategory":"Beauty Salon",
            "type":"Services"
        }
    ],
    "sg:phone":"+61 2 9371 0500",
    "sg:postcode":"2029",
    "sg:province":"NSW",
    "sg:tags":[
        "hairdresser"
    ],
    "wof:name":"Hair By Dora K",
    "wof:placetype":"venue"
},
  "geometry": {"coordinates":[151.270187378,-33.8694839478],"type":"Point"}
}