{
  "type": "Feature",
  "properties": {
    "iso:country":"AU",
    "sg:address":"32 George St",
    "sg:city":"Balaklava",
    "sg:classifiers":[
        {
            "category":"Food & Beverages",
            "subcategory":"Bakery",
            "type":"Retail Goods"
        }
    ],
    "sg:phone":"+61 8 8862 1355",
    "sg:postcode":"5461",
    "sg:province":"SA",
    "sg:tags":[
        "baker"
    ],
    "wof:name":"Prices Balaklava Bakery",
    "wof:placetype":"venue"
},
  "geometry": {"coordinates":[138.414444,-34.146091],"type":"Point"}
}