{
  "type": "Feature",
  "properties": {
    "addr:full":"264-278 George St Sydney NSW 2000",
    "addr:housenumber":"264-278",
    "addr:postcode":"2000",
    "addr:street":"George St",
    "iso:country":"AU",
    "sg:address":"264-278 George St",
    "sg:city":"Sydney",
    "sg:classifiers":[
        {
            "category":"Banks & Credit Unions",
            "subcategory":"Investment Brokerage",
            "type":"Services"
        }
    ],
    "sg:phone":"+61 2 9247 0777",
    "sg:postcode":"2000",
    "sg:province":"NSW",
    "wof:name":"Sumitomo Metal Aust Pty Ltd",
    "wof:placetype":"venue"
},
  "geometry": {"coordinates":[151.20750427199999,-33.864906311],"type":"Point"}
}