{
  "type": "Feature",
  "properties": {
    "iso:country":"AU",
    "sg:address":"Market Square Shopping Center Shop 111 Moorabool S",
    "sg:city":"Geelong",
    "sg:classifiers":[
        {
            "category":"Food & Beverages",
            "subcategory":"Bakery",
            "type":"Retail Goods"
        }
    ],
    "sg:phone":"+61 3 5228 5588",
    "sg:postcode":"3220",
    "sg:province":"VIC",
    "sg:tags":[
        "baker"
    ],
    "wof:name":"Banjos",
    "wof:placetype":"venue"
},
  "geometry": {"coordinates":[144.360809,-38.147472],"type":"Point"}
}