{
  "type": "Feature",
  "properties": {
    "addr:full":"38 Stratford St Pingelly WA 6308",
    "addr:housenumber":"38",
    "addr:postcode":"6308",
    "addr:street":"Stratford St",
    "iso:country":"AU",
    "sg:address":"38 Stratford St",
    "sg:city":"Pingelly",
    "sg:classifiers":[
        {
            "category":"Social Services",
            "subcategory":"Child Care",
            "type":"Services"
        }
    ],
    "sg:phone":"+61 8 9887 1455",
    "sg:postcode":"6308",
    "sg:province":"WA",
    "sg:tags":[
        "support",
        "health"
    ],
    "wof:name":"Child Health Services",
    "wof:placetype":"venue"
},
  "geometry": {"coordinates":[117.086997986,-32.5312919617],"type":"Point"}
}