{
  "type": "Feature",
  "properties": {
    "addr:full":"49 Caratel Crs Marayong NSW 2148",
    "addr:housenumber":"49",
    "addr:postcode":"2148",
    "addr:street":"Caratel Crs",
    "iso:country":"AU",
    "sg:address":"49 Caratel Crs",
    "sg:city":"Marayong",
    "sg:classifiers":[
        {
            "category":"Home & Garden",
            "subcategory":"Building Materials",
            "type":"Retail Goods"
        }
    ],
    "sg:phone":"+61 417 227 187",
    "sg:postcode":"2148",
    "sg:province":"NSW",
    "sg:tags":[
        "merchant",
        "glass",
        "glazier"
    ],
    "wof:name":"Ever Clear Glass & Glazing",
    "wof:placetype":"venue"
},
  "geometry": {"coordinates":[150.89976501500001,-33.7462692261],"type":"Point"}
}