{
  "type": "Feature",
  "properties": {
    "iso:country":"AU",
    "sg:address":"Devereaux Creek Rd",
    "sg:city":"Marian",
    "sg:classifiers":[
        {
            "category":"Farming",
            "subcategory":"Crops",
            "type":"Manufacturing & Wholesale Goods"
        }
    ],
    "sg:phone":"+61 7 4954 3796",
    "sg:postcode":"4753",
    "sg:province":"QLD",
    "sg:tags":[
        "sugarcane",
        "mill",
        "grower"
    ],
    "wof:name":"Stroppiana RC & AR",
    "wof:placetype":"venue"
},
  "geometry": {"coordinates":[148.93331900000001,-21.125444],"type":"Point"}
}