{
  "type": "Feature",
  "properties": {
    "addr:full":"174 Alanvale Rd Alanvale TAS 7248",
    "addr:housenumber":"174",
    "addr:postcode":"7248",
    "addr:street":"Alanvale Rd",
    "iso:country":"AU",
    "sg:address":"174 Alanvale Rd",
    "sg:city":"Alanvale",
    "sg:classifiers":[
        {
            "category":"Personal",
            "subcategory":"Massage",
            "type":"Services"
        }
    ],
    "sg:phone":"+61 3 6326 2531",
    "sg:postcode":"7248",
    "sg:province":"TAS",
    "sg:tags":[
        "therapy"
    ],
    "wof:name":"Olsen Tommy H",
    "wof:placetype":"venue"
},
  "geometry": {"coordinates":[147.11201477,-41.3840904236],"type":"Point"}
}