{
  "type": "Feature",
  "properties": {
    "addr:full":"1 Farm Rd Mulgoa NSW 2745",
    "addr:housenumber":"1",
    "addr:postcode":"2745",
    "addr:street":"Farm Rd",
    "iso:country":"AU",
    "sg:address":"1 Farm Rd",
    "sg:city":"Mulgoa",
    "sg:classifiers":[
        {
            "category":"Building & Trades",
            "subcategory":"Pest Control",
            "type":"Services"
        }
    ],
    "sg:phone":"+61 400 341 292",
    "sg:postcode":"2745",
    "sg:province":"NSW",
    "wof:name":"Tim's All Round Pest Control",
    "wof:placetype":"venue"
},
  "geometry": {"coordinates":[150.65736389200001,-33.8331260681],"type":"Point"}
}