{
  "type": "Feature",
  "properties": {
    "addr:full":"86 Arthur St Fortitude Valley QLD 4006",
    "addr:housenumber":"86",
    "addr:postcode":"4006",
    "addr:street":"Arthur St",
    "iso:country":"AU",
    "sg:address":"86 Arthur St",
    "sg:city":"Fortitude Valley",
    "sg:classifiers":[
        {
            "category":"Professional",
            "subcategory":"Employment Agencies",
            "type":"Services"
        }
    ],
    "sg:phone":"+61 7 3358 0000",
    "sg:postcode":"4006",
    "sg:province":"QLD",
    "sg:tags":[
        "entertainer",
        "agent"
    ],
    "wof:name":"Artist & Entertainment Group Management Pty Ltd",
    "wof:placetype":"venue"
},
  "geometry": {"coordinates":[153.039596558,-27.4590740204],"type":"Point"}
}