{
  "type": "Feature",
  "properties": {
    "iso:country":"AU",
    "sg:address":"&#034;Glengrove&#034; Leichart Hwy",
    "sg:city":"Goondiwindi",
    "sg:classifiers":[
        {
            "category":"Building & Trades",
            "subcategory":"Landscaping Services",
            "type":"Services"
        }
    ],
    "sg:phone":"+61 7 4671 3160",
    "sg:postcode":"4390",
    "sg:province":"QLD",
    "sg:tags":[
        "firebreak",
        "clearing",
        "land",
        "contractor"
    ],
    "wof:name":"Greg Hosie Grader Hire",
    "wof:placetype":"venue"
},
  "geometry": {"coordinates":[150.32679748499999,-28.5323181152],"type":"Point"}
}