{
  "type": "Feature",
  "properties": {
    "addr:full":"9 Pleasant St Mowbray TAS 7248",
    "addr:housenumber":"9",
    "addr:postcode":"7248",
    "addr:street":"Pleasant St",
    "iso:country":"AU",
    "sg:address":"9 Pleasant St",
    "sg:city":"Mowbray",
    "sg:classifiers":[
        {
            "category":"Retail",
            "subcategory":"Veterinary Services",
            "type":"Services"
        }
    ],
    "sg:phone":"+61 3 6326 4900",
    "sg:postcode":"7248",
    "sg:province":"TAS",
    "sg:tags":[
        "surgeon"
    ],
    "wof:name":"Mowbray Veterinary Clinic",
    "wof:placetype":"venue"
},
  "geometry": {"coordinates":[147.134109497,-41.4057807922],"type":"Point"}
}