{
  "type": "Feature",
  "properties": {
    "iso:country":"AU",
    "sg:address":"33 Dorset St",
    "sg:city":"Glen Waverley",
    "sg:classifiers":[
        {
            "category":"Social Services",
            "subcategory":"Child Care",
            "type":"Services"
        }
    ],
    "sg:phone":"+61 3 9562 0110",
    "sg:postcode":"3150",
    "sg:province":"VIC",
    "sg:tags":[
        "baby",
        "sitter"
    ],
    "wof:name":"Forest Hill Baby Sitting Service",
    "wof:placetype":"venue"
},
  "geometry": {"coordinates":[145.145950317,-37.9008255005],"type":"Point"}
}