{
  "type": "Feature",
  "properties": {
    "addr:full":"Suite 2, 763 High St Epping VIC 3076",
    "addr:housenumber":"763",
    "addr:postcode":"3076",
    "addr:street":"High St",
    "iso:country":"AU",
    "sg:address":"Suite 2, 763 High St",
    "sg:city":"Epping",
    "sg:classifiers":[
        {
            "category":"Professional",
            "subcategory":"Employment Agencies",
            "type":"Services"
        }
    ],
    "sg:phone":"+61 3 9409 9000",
    "sg:postcode":"3076",
    "sg:province":"VIC",
    "wof:name":"Salvation Army Employment Plus The",
    "wof:placetype":"venue"
},
  "geometry": {"coordinates":[145.013275147,-37.8543968201],"type":"Point"}
}