{
  "type": "Feature",
  "properties": {
    "addr:full":"8 Molly Morgan Drv Greenhills NSW 2323",
    "addr:housenumber":"8",
    "addr:postcode":"2323",
    "addr:street":"Molly Morgan Drv",
    "iso:country":"AU",
    "sg:address":"8 Molly Morgan Drv",
    "sg:city":"Greenhills",
    "sg:classifiers":[
        {
            "category":"Health Services",
            "subcategory":"Dentist",
            "type":"Services"
        }
    ],
    "sg:phone":"+61 2 4933 7988",
    "sg:postcode":"2323",
    "sg:province":"NSW",
    "wof:name":"Liddle Neil",
    "wof:placetype":"venue"
},
  "geometry": {"coordinates":[151.59429931599999,-32.7626686096],"type":"Point"}
}