{
  "type": "Feature",
  "properties": {
    "iso:country":"AU",
    "sg:address":"40 Lord St",
    "sg:city":"Port Macquarie",
    "sg:classifiers":[
        {
            "category":"Professional",
            "subcategory":"Business Services",
            "type":"Services"
        }
    ],
    "sg:phone":"+61 2 6584 6331",
    "sg:postcode":"2444",
    "sg:province":"NSW",
    "sg:tags":[
        "drafting"
    ],
    "wof:name":"CADpro Pty Ltd",
    "wof:placetype":"venue"
},
  "geometry": {"coordinates":[152.91627500000001,-31.447428],"type":"Point"}
}