{
  "type": "Feature",
  "properties": {
    "addr:full":"799 Point Nepean Rd Rosebud VIC 3939",
    "addr:housenumber":"799",
    "addr:postcode":"3939",
    "addr:street":"Point Nepean Rd",
    "iso:country":"AU",
    "sg:address":"799 Point Nepean Rd",
    "sg:city":"Rosebud",
    "sg:classifiers":[
        {
            "category":"Travel",
            "subcategory":"Hotels & Motels",
            "type":"Entertainment"
        }
    ],
    "sg:phone":"+61 3 5950 2222",
    "sg:postcode":"3939",
    "sg:province":"VIC",
    "wof:name":"Admiral Motor Inn",
    "wof:placetype":"venue"
},
  "geometry": {"coordinates":[144.91458129899999,-38.353187561],"type":"Point"}
}