{
  "type": "Feature",
  "properties": {
    "addr:full":"Siena College Crittendon Rd Findon SA 5023",
    "addr:postcode":"5023",
    "addr:street":"Crittendon Rd",
    "iso:country":"AU",
    "sg:address":"Siena College Crittendon Rd",
    "sg:city":"Findon",
    "sg:classifiers":[
        {
            "category":"Arts & Performance",
            "subcategory":"Dance",
            "type":"Entertainment"
        }
    ],
    "sg:phone":"+61 8 8358 1141",
    "sg:postcode":"5023",
    "sg:province":"SA",
    "sg:tags":[
        "theatrical",
        "ballet",
        "tuition"
    ],
    "wof:name":"Susan Cooke School of Ballet",
    "wof:placetype":"venue"
},
  "geometry": {"coordinates":[138.53221130399999,-34.9005203247],"type":"Point"}
}