{
  "type": "Feature",
  "properties": {
    "addr:full":"Shop 1 6, 1 Springfield Lakes Blv Springfield Lakes QLD 4300",
    "addr:housenumber":"shop;6 1",
    "addr:postcode":"4300",
    "addr:street":"Springfield Lakes Blv Springfield",
    "iso:country":"AU",
    "sg:address":"Shop 1",
    "sg:city":"6, 1 Springfield Lakes Blv Springfield Lakes",
    "sg:classifiers":[
        {
            "category":"Restaurant",
            "type":"Food & Drink"
        }
    ],
    "sg:phone":"+61 7 3437 8533",
    "sg:postcode":"4300",
    "sg:province":"QLD",
    "wof:name":"Bollywood Flavour Indian Restaurant",
    "wof:placetype":"venue"
},
  "geometry": {"coordinates":[152.91960144000001,-27.6670856476],"type":"Point"}
}