{
  "type": "Feature",
  "properties": {
    "iso:country":"AU",
    "sg:address":"Herdsman Business Park 2/ 24 Walters Drv",
    "sg:city":"Osborne Park",
    "sg:classifiers":[
        {
            "category":"Professional",
            "subcategory":"Accounting & Tax Preparation",
            "type":"Services"
        }
    ],
    "sg:phone":"+61 8 9244 2184",
    "sg:postcode":"6017",
    "sg:province":"WA",
    "sg:tags":[
        "consultant",
        "taxation"
    ],
    "wof:name":"Warren G.D.",
    "wof:placetype":"venue"
},
  "geometry": {"coordinates":[115.80847168,-31.9092655182],"type":"Point"}
}