{
  "type": "Feature",
  "properties": {
    "addr:full":"103 Rubicon St Sebastopol VIC 3356",
    "addr:housenumber":"103",
    "addr:postcode":"3356",
    "addr:street":"Rubicon St",
    "iso:country":"AU",
    "sg:address":"103 Rubicon St",
    "sg:city":"Sebastopol",
    "sg:classifiers":[
        {
            "category":"Personal",
            "subcategory":"Beauty Salon",
            "type":"Services"
        }
    ],
    "sg:phone":"+61 3 5336 0074",
    "sg:postcode":"3356",
    "sg:province":"VIC",
    "wof:name":"Bodytalk",
    "wof:placetype":"venue"
},
  "geometry": {"coordinates":[143.83976699999999,-37.582256],"type":"Point"}
}