{
  "type": "Feature",
  "properties": {
    "iso:country":"AU",
    "sg:address":"277 Victoria Rd",
    "sg:city":"Marrickville",
    "sg:classifiers":[
        {
            "category":"Arts & Performance",
            "subcategory":"Music",
            "type":"Entertainment"
        }
    ],
    "sg:phone":"+61 2 9568 3248",
    "sg:postcode":"2204",
    "sg:province":"NSW",
    "sg:tags":[
        "hi-fi",
        "equipment"
    ],
    "wof:name":"MB Electronics",
    "wof:placetype":"venue"
},
  "geometry": {"coordinates":[151.160675,-33.911373],"type":"Point"}
}