{
  "type": "Feature",
  "properties": {
    "iso:country":"AU",
    "sg:address":"25 Porter St",
    "sg:city":"Meadowbank",
    "sg:classifiers":[
        {
            "category":"Home & Garden",
            "subcategory":"Building Materials",
            "type":"Retail Goods"
        }
    ],
    "sg:phone":"+61 414 646 939",
    "sg:postcode":"2114",
    "sg:province":"NSW",
    "sg:tags":[
        "gate"
    ],
    "wof:name":"Concord Steel Fabrication",
    "wof:placetype":"venue"
},
  "geometry": {"coordinates":[151.09843444800001,-33.819519043],"type":"Point"}
}