{
  "type": "Feature",
  "properties": {
    "addr:full":"50 Mitchell St Darwin NT 0800",
    "addr:housenumber":"50",
    "addr:postcode":"nt 0800",
    "addr:street":"Mitchell St",
    "iso:country":"AU",
    "sg:address":"50 Mitchell St",
    "sg:city":"Darwin",
    "sg:classifiers":[
        {
            "category":"Travel",
            "subcategory":"Hotels & Motels",
            "type":"Entertainment"
        }
    ],
    "sg:phone":"+61 8 8981 4733",
    "sg:postcode":"0800",
    "sg:province":"NT",
    "wof:name":"Value Inn",
    "wof:placetype":"venue"
},
  "geometry": {"coordinates":[130.839935303,-12.4629478455],"type":"Point"}
}