{
  "type": "Feature",
  "properties": {
    "addr:full":"\"Carinya\" Commercial Rd Murwillumbah NSW 2484",
    "addr:postcode":"2484",
    "addr:street":"Commercial Rd",
    "iso:country":"AU",
    "sg:address":"\"Carinya\" Commercial Rd",
    "sg:city":"Murwillumbah",
    "sg:classifiers":[
        {
            "category":"Banks & Credit Unions",
            "subcategory":"Financial Services",
            "type":"Services"
        }
    ],
    "sg:phone":"+61 2 6672 2265",
    "sg:postcode":"2484",
    "sg:province":"NSW",
    "sg:tags":[
        "planning"
    ],
    "wof:name":"Batten Ian",
    "wof:placetype":"venue"
},
  "geometry": {"coordinates":[153.39686584500001,-28.3359546661],"type":"Point"}
}