{
  "type": "Feature",
  "properties": {
    "addr:full":"34 Placadena Rd Fingal VIC 3939",
    "addr:housenumber":"34",
    "addr:postcode":"3939",
    "addr:street":"Placadena Rd",
    "iso:country":"AU",
    "sg:address":"34 Placadena Rd",
    "sg:city":"Fingal",
    "sg:classifiers":[
        {
            "category":"Farming",
            "subcategory":"Nursery",
            "type":"Manufacturing & Wholesale Goods"
        }
    ],
    "sg:phone":"+61 3 5988 6769",
    "sg:postcode":"3939",
    "sg:province":"VIC",
    "wof:name":"Maritima Plant Nursery",
    "wof:placetype":"venue"
},
  "geometry": {"coordinates":[144.85078430199999,-38.4155845642],"type":"Point"}
}