{
  "type": "Feature",
  "properties": {
    "addr:full":"Unit 3, 5 Aero Rd Ingleburn NSW 2565",
    "addr:housenumber":"5",
    "addr:postcode":"2565",
    "addr:street":"Aero Rd",
    "iso:country":"AU",
    "sg:address":"Unit 3, 5 Aero Rd",
    "sg:city":"Ingleburn",
    "sg:classifiers":[
        {
            "category":"Wholesale",
            "subcategory":"Apparel",
            "type":"Manufacturing & Wholesale Goods"
        }
    ],
    "sg:phone":"+61 2 9829 2222",
    "sg:postcode":"2565",
    "sg:province":"NSW",
    "sg:tags":[
        "wholesaler",
        "mfrs",
        "uniform"
    ],
    "wof:name":"Katrina Trading Co P/L",
    "wof:placetype":"venue"
},
  "geometry": {"coordinates":[150.86671447800001,-33.9939727783],"type":"Point"}
}