{
  "type": "Feature",
  "properties": {
    "iso:country":"AU",
    "sg:address":"704 Freeman's Drv",
    "sg:city":"Cooranbong",
    "sg:classifiers":[
        {
            "category":"Home & Garden",
            "subcategory":"Building Materials",
            "type":"Retail Goods"
        }
    ],
    "sg:phone":"+61 2 4977 1622",
    "sg:postcode":"2265",
    "sg:province":"NSW",
    "sg:tags":[
        "fitting",
        "door"
    ],
    "wof:name":"Eaton Building Materials",
    "wof:placetype":"venue"
},
  "geometry": {"coordinates":[151.456039,-33.013287],"type":"Point"}
}