{
  "type": "Feature",
  "properties": {
    "iso:country":"AU",
    "sg:address":"57 Wills St",
    "sg:city":"Bendigo",
    "sg:classifiers":[
        {
            "category":"Real Estate",
            "subcategory":"Real Estate Agent",
            "type":"Services"
        }
    ],
    "sg:phone":"+61 3 5444 5100",
    "sg:postcode":"3539",
    "sg:province":"VIC",
    "wof:name":"Ken Preston Real Estate Pty Ltd",
    "wof:placetype":"venue"
},
  "geometry": {"coordinates":[144.278915,-36.7645],"type":"Point"}
}