{
  "type": "Feature",
  "properties": {
    "addr:full":"Unit 1, 351 McDonald St Clontarf QLD 4019",
    "addr:housenumber":"351",
    "addr:postcode":"4019",
    "addr:street":"Mcdonald St",
    "iso:country":"AU",
    "sg:address":"Unit 1, 351 McDonald St",
    "sg:city":"Clontarf",
    "sg:classifiers":[
        {
            "category":"Utilities",
            "subcategory":"Telephone",
            "type":"Services"
        }
    ],
    "sg:phone":"+61 7 3453 4119",
    "sg:postcode":"4019",
    "sg:province":"QLD",
    "sg:tags":[
        "equipment",
        "system"
    ],
    "wof:name":"Norcom Pty Ltd",
    "wof:placetype":"venue"
},
  "geometry": {"coordinates":[153.082473755,-27.2592506409],"type":"Point"}
}