{
  "type": "Feature",
  "properties": {
    "addr:full":"2 Hooker St Islington NSW 2296",
    "addr:housenumber":"2",
    "addr:postcode":"2296",
    "addr:street":"Hooker St",
    "iso:country":"AU",
    "sg:address":"2 Hooker St",
    "sg:city":"Islington",
    "sg:classifiers":[
        {
            "category":"Utilities",
            "subcategory":"Telephone",
            "type":"Services"
        }
    ],
    "sg:phone":"+61 2 4962 4455",
    "sg:postcode":"2296",
    "sg:province":"NSW",
    "sg:tags":[
        "equipment",
        "system"
    ],
    "wof:name":"Auzcom Pty Ltd",
    "wof:placetype":"venue"
},
  "geometry": {"coordinates":[151.74484252900001,-32.9110374451],"type":"Point"}
}