{
  "type": "Feature",
  "properties": {
    "iso:country":"AU",
    "sg:address":"Suite 10, 4th Floor St",
    "sg:city":"George Private Medical Centre Kogarah",
    "sg:classifiers":[
        {
            "category":"Health Services",
            "subcategory":"Doctor",
            "type":"Services"
        }
    ],
    "sg:phone":"+61 2 9553 9588",
    "sg:postcode":"2217",
    "sg:province":"NSW",
    "sg:tags":[
        "medical",
        "practitioner"
    ],
    "wof:name":"Philip Clingan Dr",
    "wof:placetype":"venue"
},
  "geometry": {"coordinates":[151.13267500000001,-33.963169],"type":"Point"}
}