{
  "type": "Feature",
  "properties": {
    "iso:country":"AU",
    "sg:address":"11/ 49 Butterfield St",
    "sg:city":"Herston",
    "sg:classifiers":[
        {
            "category":"Shopping",
            "subcategory":"Stationery & Office Supplies",
            "type":"Retail Goods"
        }
    ],
    "sg:phone":"+61 7 3252 4222",
    "sg:postcode":"4006",
    "sg:province":"QLD",
    "sg:tags":[
        "equipment",
        "display",
        "exhibition"
    ],
    "wof:name":"HiDef Interactive",
    "wof:placetype":"venue"
},
  "geometry": {"coordinates":[153.026519775,-27.4451599121],"type":"Point"}
}