{
  "type": "Feature",
  "properties": {
    "addr:full":"201 Raymond St Sale VIC 3850",
    "addr:housenumber":"201",
    "addr:postcode":"3850",
    "addr:street":"Raymond St",
    "iso:country":"AU",
    "sg:address":"201 Raymond St",
    "sg:city":"Sale",
    "sg:classifiers":[
        {
            "category":"Personal",
            "subcategory":"Shoe Repair & Shine",
            "type":"Services"
        }
    ],
    "sg:phone":"+61 3 5144 3909",
    "sg:postcode":"3850",
    "sg:province":"VIC",
    "sg:tags":[
        "footwear"
    ],
    "wof:name":"Schuback Shoes",
    "wof:placetype":"venue"
},
  "geometry": {"coordinates":[147.06553649899999,-38.1088142395],"type":"Point"}
}