{
  "type": "Feature",
  "properties": {
    "iso:country":"AU",
    "sg:address":"Cnr Markeri St",
    "sg:city":"& Robina Parkway Robina",
    "sg:classifiers":[
        {
            "category":"Food & Beverages",
            "subcategory":"Liquor & Beverages",
            "type":"Retail Goods"
        }
    ],
    "sg:phone":"+61 7 5575 9799",
    "sg:postcode":"4226",
    "sg:province":"QLD",
    "sg:tags":[
        "merchant",
        "spirit",
        "wine"
    ],
    "wof:name":"Personal Vintage Wines",
    "wof:placetype":"venue"
},
  "geometry": {"coordinates":[153.3934021,-28.0564594269],"type":"Point"}
}