{
  "type": "Feature",
  "properties": {
    "addr:full":"72 Samaria Rd Benalla VIC 3672",
    "addr:housenumber":"72",
    "addr:postcode":"3672",
    "addr:street":"Samaria Rd",
    "iso:country":"AU",
    "sg:address":"72 Samaria Rd",
    "sg:city":"Benalla",
    "sg:classifiers":[
        {
            "category":"Manufacturing",
            "subcategory":"Textiles",
            "type":"Manufacturing & Wholesale Goods"
        }
    ],
    "sg:phone":"+61 3 5762 2199",
    "sg:postcode":"3672",
    "sg:province":"VIC",
    "sg:tags":[
        "mill"
    ],
    "wof:name":"Benalla Spinners Pty Ltd",
    "wof:placetype":"venue"
},
  "geometry": {"coordinates":[145.99505600000001,-36.557968],"type":"Point"}
}