{
  "type": "Feature",
  "properties": {
    "addr:full":"32 Spencer Rd Nerang QLD 4211",
    "addr:housenumber":"32",
    "addr:postcode":"4211",
    "addr:street":"Spencer Rd",
    "iso:country":"AU",
    "sg:address":"32 Spencer Rd",
    "sg:city":"Nerang",
    "sg:classifiers":[
        {
            "category":"Autos & Motor Vehicles",
            "subcategory":"Automobile Sales",
            "type":"Retail Goods"
        }
    ],
    "sg:phone":"+61 7 5583 6999",
    "sg:postcode":"4211",
    "sg:province":"QLD",
    "sg:tags":[
        "car",
        "new"
    ],
    "wof:name":"Hinterland Toyota Pre Delivery",
    "wof:placetype":"venue"
},
  "geometry": {"coordinates":[153.34010314899999,-28.0005874634],"type":"Point"}
}