{
  "type": "Feature",
  "properties": {
    "addr:full":"366 Moggill Rd Indooroopilly QLD 4068",
    "addr:housenumber":"366",
    "addr:postcode":"4068",
    "addr:street":"Moggill Rd",
    "iso:country":"AU",
    "sg:address":"366 Moggill Rd",
    "sg:city":"Indooroopilly",
    "sg:classifiers":[
        {
            "category":"Education",
            "subcategory":"Special Training",
            "type":"Public Place"
        }
    ],
    "sg:phone":"+61 7 3878 7444",
    "sg:postcode":"4068",
    "sg:province":"QLD",
    "sg:tags":[
        "tuition-educational"
    ],
    "wof:name":"Fruition Tuition",
    "wof:placetype":"venue"
},
  "geometry": {"coordinates":[152.971359253,-27.4979820251],"type":"Point"}
}