{
  "type": "Feature",
  "properties": {
    "iso:country":"AU",
    "sg:address":"325 Creswick Rd",
    "sg:city":"Ballarat",
    "sg:classifiers":[
        {
            "category":"Professional",
            "subcategory":"Accounting & Tax Preparation",
            "type":"Services"
        }
    ],
    "sg:phone":"+61 3 5331 4755",
    "sg:postcode":"3350",
    "sg:province":"VIC",
    "sg:tags":[
        "consultant",
        "taxation"
    ],
    "wof:name":"Ryan & Warren",
    "wof:placetype":"venue"
},
  "geometry": {"coordinates":[143.84989899999999,-37.550495],"type":"Point"}
}