{
  "type": "Feature",
  "properties": {
    "addr:full":"5A Raglan St Manly NSW 2095",
    "addr:housenumber":"5a",
    "addr:postcode":"2095",
    "addr:street":"Raglan St",
    "iso:country":"AU",
    "sg:address":"5A Raglan St",
    "sg:city":"Manly",
    "sg:classifiers":[
        {
            "category":"Real Estate",
            "subcategory":"Real Estate Agent",
            "type":"Services"
        }
    ],
    "sg:phone":"+61 2 9977 7777",
    "sg:postcode":"2095",
    "sg:province":"NSW",
    "wof:name":"Walls Max International Real Estate Agents & Auctioneers",
    "wof:placetype":"venue"
},
  "geometry": {"coordinates":[151.2865448,-33.7958641052],"type":"Point"}
}