{
  "type": "Feature",
  "properties": {
    "iso:country":"AU",
    "sg:address":"584 Beaufort St",
    "sg:city":"Mt Lawley",
    "sg:classifiers":[
        {
            "category":"Shopping",
            "subcategory":"Clothing, Apparel, & Fashions",
            "type":"Retail Goods"
        }
    ],
    "sg:phone":"+61 8 9328 1110",
    "sg:postcode":"6050",
    "sg:province":"WA",
    "sg:tags":[
        "lady",
        "wear"
    ],
    "wof:name":"Boutique Baciano",
    "wof:placetype":"venue"
},
  "geometry": {"coordinates":[115.87109375,-31.9363899231],"type":"Point"}
}