{
  "type": "Feature",
  "properties": {
    "addr:full":"Rockingham City Shopping Centre, Cnr Read St & Simpson Ave Rockingham Park WA 6168",
    "addr:postcode":"6168",
    "addr:street":"Cnr Read St & Simpson Ave",
    "iso:country":"AU",
    "sg:address":"Rockingham City Shopping Centre, Cnr Read St & Simpson Ave",
    "sg:city":"Rockingham Park",
    "sg:classifiers":[
        {
            "category":"Retail",
            "subcategory":"Auto Repair",
            "type":"Services"
        }
    ],
    "sg:phone":"+61 8 9527 2579",
    "sg:postcode":"6168",
    "sg:province":"WA",
    "sg:tags":[
        "repairer",
        "motor",
        "engineer"
    ],
    "wof:name":"Kmart Tyre & Auto Service",
    "wof:placetype":"venue"
},
  "geometry": {"coordinates":[115.749138,-32.28619],"type":"Point"}
}