{
  "type": "Feature",
  "properties": {
    "addr:full":"8 Palmer St Wellington NSW 2820",
    "addr:housenumber":"8",
    "addr:postcode":"2820",
    "addr:street":"Palmer St",
    "iso:country":"AU",
    "sg:address":"8 Palmer St",
    "sg:city":"Wellington",
    "sg:classifiers":[
        {
            "category":"Building & Trades",
            "subcategory":"Construction",
            "type":"Services"
        }
    ],
    "sg:phone":"+61 429 636 138",
    "sg:postcode":"2820",
    "sg:province":"NSW",
    "sg:tags":[
        "concrete",
        "contractor"
    ],
    "wof:name":"Naveau David",
    "wof:placetype":"venue"
},
  "geometry": {"coordinates":[148.94415283199999,-32.5641593933],"type":"Point"}
}