{
  "type": "Feature",
  "properties": {
    "addr:full":"36 Schillings Rd Ipswich QLD 4305",
    "addr:housenumber":"36",
    "addr:postcode":"4305",
    "addr:street":"Schillings Rd",
    "iso:country":"AU",
    "sg:address":"36 Schillings Rd",
    "sg:city":"Ipswich",
    "sg:classifiers":[
        {
            "category":"Professional",
            "subcategory":"Accounting & Tax Preparation",
            "type":"Services"
        }
    ],
    "sg:phone":"+61 419 674 320",
    "sg:postcode":"4305",
    "sg:province":"QLD",
    "sg:tags":[
        "bookkeeping"
    ],
    "wof:name":"Mercy Strudwick",
    "wof:placetype":"venue"
},
  "geometry": {"coordinates":[152.713165283,-27.6060504913],"type":"Point"}
}