{
  "type": "Feature",
  "properties": {
    "iso:country":"AU",
    "sg:address":"52 Newton Rd",
    "sg:city":"Wetherill Park",
    "sg:classifiers":[
        {
            "category":"Building & Trades",
            "subcategory":"Construction",
            "type":"Services"
        }
    ],
    "sg:phone":"+61 2 9756 2555",
    "sg:postcode":"2164",
    "sg:province":"NSW",
    "sg:tags":[
        "welding"
    ],
    "wof:name":"Universal Steel Constructions Australia Pty Ltd",
    "wof:placetype":"venue"
},
  "geometry": {"coordinates":[150.89355468799999,-33.8407325745],"type":"Point"}
}