{
  "type": "Feature",
  "properties": {
    "addr:full":"Shop 1 738 Main St Kangaroo Point QLD 4169",
    "addr:housenumber":"shop 1 738",
    "addr:postcode":"4169",
    "addr:street":"Main St",
    "iso:country":"AU",
    "sg:address":"Shop 1 738 Main St",
    "sg:city":"Kangaroo Point",
    "sg:classifiers":[
        {
            "category":"Fast Food",
            "type":"Food & Drink"
        }
    ],
    "sg:phone":"+61 7 3891 2777",
    "sg:postcode":"4169",
    "sg:province":"QLD",
    "sg:tags":[
        "away",
        "take"
    ],
    "wof:name":"Ipoh Laksa",
    "wof:placetype":"venue"
},
  "geometry": {"coordinates":[153.03596496599999,-27.4820346832],"type":"Point"}
}