{
  "type": "Feature",
  "properties": {
    "addr:full":"19 Wicklow St Kangaroo Point QLD 4169",
    "addr:housenumber":"19",
    "addr:postcode":"4169",
    "addr:street":"Wicklow St",
    "iso:country":"AU",
    "sg:address":"19 Wicklow St",
    "sg:city":"Kangaroo Point",
    "sg:classifiers":[
        {
            "category":"Professional",
            "subcategory":"Business Services",
            "type":"Services"
        }
    ],
    "sg:phone":"+61 414 550 632",
    "sg:postcode":"4169",
    "sg:province":"QLD",
    "sg:tags":[
        "broker"
    ],
    "wof:name":"Mary Martin & Associates",
    "wof:placetype":"venue"
},
  "geometry": {"coordinates":[153.034545898,-27.4665260315],"type":"Point"}
}