{
  "type": "Feature",
  "properties": {
    "iso:country":"AU",
    "sg:address":"20 Rocco Drv",
    "sg:city":"Scoresby",
    "sg:classifiers":[
        {
            "category":"Wholesale",
            "subcategory":"Home Furnishings",
            "type":"Manufacturing & Wholesale Goods"
        }
    ],
    "sg:phone":"+61 3 9753 2444",
    "sg:postcode":"3179",
    "sg:province":"VIC",
    "sg:tags":[
        "wholesaler",
        "mfrs",
        "manchester"
    ],
    "wof:name":"Ladelle Pty Ltd",
    "wof:placetype":"venue"
},
  "geometry": {"coordinates":[145.216964722,-37.8978691101],"type":"Point"}
}