{
  "type": "Feature",
  "properties": {
    "addr:full":"315 Redland Bay Rd Capalaba QLD 4157",
    "addr:housenumber":"315",
    "addr:postcode":"4157",
    "addr:street":"Redland Bay Rd",
    "iso:country":"AU",
    "sg:address":"315 Redland Bay Rd",
    "sg:city":"Capalaba",
    "sg:classifiers":[
        {
            "category":"Home & Garden",
            "subcategory":"Furniture",
            "type":"Retail Goods"
        }
    ],
    "sg:phone":"+61 7 3824 8045",
    "sg:postcode":"4157",
    "sg:province":"QLD",
    "sg:tags":[
        "repair",
        "restoration"
    ],
    "sg:website":"http://www.workin4u.com/classic",
    "wof:name":"A Classic Restorations",
    "wof:placetype":"venue"
},
  "geometry": {"coordinates":[153.20791625999999,-27.5353527069],"type":"Point"}
}