{
  "type": "Feature",
  "properties": {
    "addr:full":"PO Box 440 Kingston TAS 7051",
    "addr:postcode":"7051",
    "iso:country":"AU",
    "sg:address":"PO Box 440",
    "sg:city":"Kingston",
    "sg:classifiers":[
        {
            "category":"Building & Trades",
            "subcategory":"Cleaning & Sanitation",
            "type":"Services"
        }
    ],
    "sg:phone":"+61 412 642 147",
    "sg:postcode":"7051",
    "sg:province":"TAS",
    "sg:tags":[
        "window"
    ],
    "wof:name":"Sheen & Shine Window Cleaners",
    "wof:placetype":"venue"
},
  "geometry": {"coordinates":[147.30839499999999,-42.97686],"type":"Point"}
}