{
  "type": "Feature",
  "properties": {
    "addr:full":"PO Box 938, Springwood, QLD, 4127 Unit 20/ Parramatta Rd Underwood QLD 4119",
    "addr:housenumber":"unit 20 / parramatta",
    "addr:postcode":"4127;4119",
    "addr:street":"Rd",
    "iso:country":"AU",
    "sg:address":"PO Box 938, Springwood, QLD, 4127 Unit 20/ Parramatta Rd",
    "sg:city":"Underwood",
    "sg:classifiers":[
        {
            "category":"Shopping",
            "subcategory":"Stationery & Office Supplies",
            "type":"Retail Goods"
        }
    ],
    "sg:phone":"+61 7 3808 8499",
    "sg:postcode":"4119",
    "sg:province":"QLD",
    "sg:tags":[
        "equipment",
        "display",
        "exhibition"
    ],
    "wof:name":"Auslink Display Systems",
    "wof:placetype":"venue"
},
  "geometry": {"coordinates":[153.11703491200001,-27.6118984222],"type":"Point"}
}