{
  "type": "Feature",
  "properties": {
    "addr:full":"155 Poath Rd Murrumbeena VIC 3163",
    "addr:housenumber":"155",
    "addr:postcode":"3163",
    "addr:street":"Poath Rd",
    "iso:country":"AU",
    "sg:address":"155 Poath Rd",
    "sg:city":"Murrumbeena",
    "sg:classifiers":[
        {
            "category":"Professional",
            "subcategory":"Printing & Photocopies",
            "type":"Services"
        }
    ],
    "sg:phone":"+61 3 9568 4144",
    "sg:postcode":"3163",
    "sg:province":"VIC",
    "sg:tags":[
        "photocopying"
    ],
    "wof:name":"APA Publishing",
    "wof:placetype":"venue"
},
  "geometry": {"coordinates":[145.07620239299999,-37.8966255188],"type":"Point"}
}