{
  "type": "Feature",
  "properties": {
    "addr:full":"26 South St Esk QLD 4312",
    "addr:housenumber":"26",
    "addr:postcode":"4312",
    "addr:street":"South St",
    "iso:country":"AU",
    "sg:address":"26 South St",
    "sg:city":"Esk",
    "sg:classifiers":[
        {
            "category":"Education",
            "subcategory":"Kindergarten",
            "type":"Public Place"
        }
    ],
    "sg:phone":"+61 7 5424 1377",
    "sg:postcode":"4312",
    "sg:province":"QLD",
    "sg:tags":[
        "pre-schools"
    ],
    "wof:name":"C&K Esk & District Kindergarten",
    "wof:placetype":"venue"
},
  "geometry": {"coordinates":[152.42324829099999,-27.2501049042],"type":"Point"}
}