{
  "type": "Feature",
  "properties": {
    "addr:full":"14 Chrome St Salisbury QLD 4107",
    "addr:housenumber":"14",
    "addr:postcode":"4107",
    "addr:street":"Chrome St",
    "iso:country":"AU",
    "sg:address":"14 Chrome St",
    "sg:city":"Salisbury",
    "sg:classifiers":[
        {
            "category":"Education",
            "subcategory":"Dance Studio",
            "type":"Public Place"
        }
    ],
    "sg:phone":"+61 421 761 350",
    "sg:postcode":"4107",
    "sg:province":"QLD",
    "sg:tags":[
        "venue",
        "tuition"
    ],
    "wof:name":"The Funk Factory",
    "wof:placetype":"venue"
},
  "geometry": {"coordinates":[153.02952575699999,-27.5431575775],"type":"Point"}
}