{
  "type": "Feature",
  "properties": {
    "iso:country":"AU",
    "sg:address":"1 Miranda Mrkt Pl",
    "sg:city":"Miranda",
    "sg:classifiers":[
        {
            "category":"Food & Beverages",
            "subcategory":"Supermarket",
            "type":"Retail Goods"
        }
    ],
    "sg:phone":"+61 2 9524 7245",
    "sg:postcode":"2228",
    "sg:province":"NSW",
    "sg:tags":[
        "grocery",
        "store"
    ],
    "wof:name":"Franklins Stores",
    "wof:placetype":"venue"
},
  "geometry": {"coordinates":[151.105560303,-34.0308151245],"type":"Point"}
}