{
  "type": "Feature",
  "properties": {
    "addr:full":"Jose St Mullewa WA 6630",
    "addr:postcode":"6630",
    "addr:street":"Jose St",
    "iso:country":"AU",
    "sg:address":"Jose St",
    "sg:city":"Mullewa",
    "sg:classifiers":[
        {
            "category":"Education",
            "subcategory":"School",
            "type":"Public Place"
        }
    ],
    "sg:phone":"+61 8 9961 1114",
    "sg:postcode":"6630",
    "sg:province":"WA",
    "sg:tags":[
        "state",
        "except",
        "nsw"
    ],
    "wof:name":"Mullewa District High School",
    "wof:placetype":"venue"
},
  "geometry": {"coordinates":[115.512046814,-28.5397472382],"type":"Point"}
}