{
  "type": "Feature",
  "properties": {
    "addr:full":"Lot 42 Industrial Drv Moree NSW 2400",
    "addr:postcode":"2400",
    "addr:street":"Industrial",
    "iso:country":"AU",
    "sg:address":"Lot 42 Industrial Drv",
    "sg:city":"Moree",
    "sg:classifiers":[
        {
            "category":"Home & Garden",
            "subcategory":"Building Materials",
            "type":"Retail Goods"
        }
    ],
    "sg:phone":"+61 429 413 672",
    "sg:postcode":"2400",
    "sg:province":"NSW",
    "sg:tags":[
        "wall",
        "frame",
        "truss",
        "roof"
    ],
    "wof:name":"Moree Truss & Frame",
    "wof:placetype":"venue"
},
  "geometry": {"coordinates":[149.841598511,-29.4661998749],"type":"Point"}
}