{
  "type": "Feature",
  "properties": {
    "addr:full":"3 Greenslade St Hamilton Hill WA 6163",
    "addr:housenumber":"3",
    "addr:postcode":"6163",
    "addr:street":"Greenslade St",
    "iso:country":"AU",
    "sg:address":"3 Greenslade St",
    "sg:city":"Hamilton Hill",
    "sg:classifiers":[
        {
            "category":"Deli",
            "type":"Food & Drink"
        }
    ],
    "sg:phone":"+61 8 9314 1071",
    "sg:postcode":"6163",
    "sg:province":"WA",
    "sg:tags":[
        "delicatessen"
    ],
    "wof:name":"V & S Continental Foods",
    "wof:placetype":"venue"
},
  "geometry": {"coordinates":[115.78806299999999,-32.075043],"type":"Point"}
}