{
  "type": "Feature",
  "properties": {
    "addr:full":"32 Reece St George Town TAS 7253",
    "addr:housenumber":"32",
    "addr:postcode":"7253",
    "addr:street":"Reece St",
    "iso:country":"AU",
    "sg:address":"32 Reece St",
    "sg:city":"George Town",
    "sg:classifiers":[
        {
            "category":"Taxi",
            "type":"Transportation"
        }
    ],
    "sg:phone":"+61 3 6382 1622",
    "sg:postcode":"7253",
    "sg:province":"TAS",
    "sg:tags":[
        "cab"
    ],
    "wof:name":"George Town Taxi Service",
    "wof:placetype":"venue"
},
  "geometry": {"coordinates":[146.824951172,-41.1179199219],"type":"Point"}
}