{
  "type": "Feature",
  "properties": {
    "addr:full":"2 Towong St Dandenong North VIC 3175",
    "addr:housenumber":"2",
    "addr:postcode":"3175",
    "addr:street":"Towong St",
    "iso:country":"AU",
    "sg:address":"2 Towong St",
    "sg:city":"Dandenong North",
    "sg:classifiers":[
        {
            "category":"Building & Trades",
            "subcategory":"Plumbing",
            "type":"Services"
        }
    ],
    "sg:phone":"+61 3 9795 6587",
    "sg:postcode":"3175",
    "sg:province":"VIC",
    "sg:tags":[
        "plumber",
        "gasfitters"
    ],
    "wof:name":"David Brickan Plumbing",
    "wof:placetype":"venue"
},
  "geometry": {"coordinates":[145.216995239,-37.9421272278],"type":"Point"}
}