{
  "type": "Feature",
  "properties": {
    "addr:full":"7 Kurrewa Crt Bellerive TAS 7018",
    "addr:housenumber":"7",
    "addr:postcode":"7018",
    "addr:street":"Kurrewa Crt",
    "iso:country":"AU",
    "sg:address":"7 Kurrewa Crt",
    "sg:city":"Bellerive",
    "sg:classifiers":[
        {
            "category":"Professional",
            "subcategory":"Employment Agencies",
            "type":"Services"
        }
    ],
    "sg:phone":"+61 3 6244 8133",
    "sg:postcode":"7018",
    "sg:province":"TAS",
    "wof:name":"Teach UK",
    "wof:placetype":"venue"
},
  "geometry": {"coordinates":[147.37660217300001,-42.8710250854],"type":"Point"}
}