{
  "type": "Feature",
  "properties": {
    "addr:full":"23 Warung St Yagoona NSW 2199",
    "addr:housenumber":"23",
    "addr:postcode":"2199",
    "addr:street":"Warung St",
    "iso:country":"AU",
    "sg:address":"23 Warung St",
    "sg:city":"Yagoona",
    "sg:classifiers":[
        {
            "category":"Professional",
            "subcategory":"Engineering",
            "type":"Services"
        }
    ],
    "sg:phone":"+61 2 9709 5705",
    "sg:postcode":"2199",
    "sg:province":"NSW",
    "sg:tags":[
        "consulting",
        "engineer"
    ],
    "wof:name":"Brown Neville & Associates Pty Limited",
    "wof:placetype":"venue"
},
  "geometry": {"coordinates":[151.00555399999999,-33.913418],"type":"Point"}
}