{
  "type": "Feature",
  "properties": {
    "iso:country":"AU",
    "sg:address":"22 Alma Rd",
    "sg:city":"New Lambton",
    "sg:classifiers":[
        {
            "category":"Fast Food",
            "type":"Food & Drink"
        }
    ],
    "sg:phone":"+61 2 4952 5989",
    "sg:postcode":"2305",
    "sg:province":"NSW",
    "sg:tags":[
        "away",
        "take"
    ],
    "wof:name":"Paul's Asian Affair Restaurant",
    "wof:placetype":"venue"
},
  "geometry": {"coordinates":[151.71395899999999,-32.922249],"type":"Point"}
}