{
  "type": "Feature",
  "properties": {
    "iso:country":"AU",
    "sg:address":"1173 Logan Rd",
    "sg:city":"Holland Park East",
    "sg:classifiers":[
        {
            "category":"Health Services",
            "subcategory":"Doctor",
            "type":"Services"
        }
    ],
    "sg:phone":"+61 7 3849 6868",
    "sg:postcode":"4121",
    "sg:province":"QLD",
    "sg:tags":[
        "medical",
        "practitioner"
    ],
    "wof:name":"Sharma Pallavi Dr",
    "wof:placetype":"venue"
},
  "geometry": {"coordinates":[153.07072448700001,-27.5285720825],"type":"Point"}
}