{
  "type": "Feature",
  "properties": {
    "iso:country":"AU",
    "sg:address":"46 Hood St",
    "sg:city":"Airport West",
    "sg:classifiers":[
        {
            "category":"Building & Trades",
            "subcategory":"Construction",
            "type":"Services"
        }
    ],
    "sg:phone":"+61 3 9330 3411",
    "sg:postcode":"3042",
    "sg:province":"VIC",
    "sg:tags":[
        "plasterboard",
        "plasterer",
        "fixer"
    ],
    "wof:name":"North West Plaster Products",
    "wof:placetype":"venue"
},
  "geometry": {"coordinates":[144.886230469,-37.7250900269],"type":"Point"}
}