{
  "type": "Feature",
  "properties": {
    "addr:full":"23 Day St Tara QLD 4421",
    "addr:housenumber":"23",
    "addr:postcode":"4421",
    "addr:street":"Day St",
    "iso:country":"AU",
    "sg:address":"23 Day St",
    "sg:city":"Tara",
    "sg:classifiers":[
        {
            "category":"Food & Beverages",
            "subcategory":"Supermarket",
            "type":"Retail Goods"
        }
    ],
    "sg:phone":"+61 7 4665 3188",
    "sg:postcode":"4421",
    "sg:province":"QLD",
    "sg:tags":[
        "grocery",
        "store"
    ],
    "wof:name":"West Co-Op Food Store",
    "wof:placetype":"venue"
},
  "geometry": {"coordinates":[150.458450317,-27.2770252228],"type":"Point"}
}