{
  "type": "Feature",
  "properties": {
    "addr:full":"Lvl 10/ 230 Collins St Melbourne VIC 3000",
    "addr:housenumber":"/ 230",
    "addr:postcode":"3000",
    "addr:street":"Collins St",
    "iso:country":"AU",
    "sg:address":"Lvl 10/ 230 Collins St",
    "sg:city":"Melbourne",
    "sg:classifiers":[
        {
            "category":"Banks & Credit Unions",
            "subcategory":"Bureau De Change",
            "type":"Services"
        }
    ],
    "sg:phone":"+61 3 9662 3086",
    "sg:postcode":"3000",
    "sg:province":"VIC",
    "sg:tags":[
        "currency",
        "exchange",
        "foreign"
    ],
    "wof:name":"Everforex Financial Pty Ltd",
    "wof:placetype":"venue"
},
  "geometry": {"coordinates":[144.9662323,-37.815448761],"type":"Point"}
}