{
  "type": "Feature",
  "properties": {
    "addr:full":"25 Grey Rd Carina QLD 4152",
    "addr:housenumber":"25",
    "addr:postcode":"4152",
    "addr:street":"Grey Rd",
    "iso:country":"AU",
    "sg:address":"25 Grey Rd",
    "sg:city":"Carina",
    "sg:classifiers":[
        {
            "category":"Building & Trades",
            "subcategory":"Construction",
            "type":"Services"
        }
    ],
    "sg:phone":"+61 7 3843 0038",
    "sg:postcode":"4152",
    "sg:province":"QLD",
    "sg:tags":[
        "polishing",
        "sanding",
        "floor"
    ],
    "wof:name":"Go Floor",
    "wof:placetype":"venue"
},
  "geometry": {"coordinates":[153.01626586899999,-27.4711494446],"type":"Point"}
}