{
  "type": "Feature",
  "properties": {
    "addr:full":"47 Tanumbirini St Hawker ACT 2614",
    "addr:housenumber":"47",
    "addr:postcode":"2614",
    "addr:street":"Tanumbirini St",
    "iso:country":"AU",
    "sg:address":"47 Tanumbirini St",
    "sg:city":"Hawker",
    "sg:classifiers":[
        {
            "category":"Real Estate",
            "subcategory":"Real Estate Services",
            "type":"Services"
        }
    ],
    "sg:phone":"+61 2 6254 0380",
    "sg:postcode":"2614",
    "sg:province":"ACT",
    "sg:tags":[
        "consultant",
        "property"
    ],
    "wof:name":"Wesbur Pty Limited",
    "wof:placetype":"venue"
},
  "geometry": {"coordinates":[149.03065490700001,-35.2460021973],"type":"Point"}
}