{
  "type": "Feature",
  "properties": {
    "addr:full":"55 Delmar Pde Dee Why NSW 2099",
    "addr:housenumber":"55",
    "addr:postcode":"2099",
    "addr:street":"Delmar Pde",
    "iso:country":"AU",
    "sg:address":"55 Delmar Pde",
    "sg:city":"Dee Why",
    "sg:classifiers":[
        {
            "category":"Professional",
            "subcategory":"Detective & Security Services",
            "type":"Services"
        }
    ],
    "sg:phone":"+61 418 215 534",
    "sg:postcode":"2099",
    "sg:province":"NSW",
    "sg:tags":[
        "consultant",
        "system"
    ],
    "wof:name":"Abode Antennas",
    "wof:placetype":"venue"
},
  "geometry": {"coordinates":[151.288406372,-33.7563476562],"type":"Point"}
}