{
  "type": "Feature",
  "properties": {
    "iso:country":"AU",
    "sg:address":"39 McKillop St",
    "sg:city":"Geelong",
    "sg:classifiers":[
        {
            "category":"Professional",
            "subcategory":"Employment Agencies",
            "type":"Services"
        }
    ],
    "sg:phone":"+61 3 5226 2277",
    "sg:postcode":"3220",
    "sg:province":"VIC",
    "sg:tags":[
        "hire",
        "labour",
        "contractor"
    ],
    "wof:name":"Marshmans H.R. Services",
    "wof:placetype":"venue"
},
  "geometry": {"coordinates":[144.356277,-38.152756],"type":"Point"}
}