{
  "type": "Feature",
  "properties": {
    "addr:full":"- - St Sheidow Park SA 5158",
    "addr:postcode":"5158",
    "iso:country":"AU",
    "sg:address":"- - St",
    "sg:city":"Sheidow Park",
    "sg:classifiers":[
        {
            "category":"Shopping",
            "subcategory":"Musical Instruments",
            "type":"Retail Goods"
        }
    ],
    "sg:phone":"+61 8 8322 3970",
    "sg:postcode":"5158",
    "sg:province":"SA",
    "sg:tags":[
        "musician",
        "agent"
    ],
    "wof:name":"Bare Necessities",
    "wof:placetype":"venue"
},
  "geometry": {"coordinates":[138.5284729,-35.073638916],"type":"Point"}
}