{
  "type": "Feature",
  "properties": {
    "addr:full":"20 Woodland Crs Narellan NSW 2567",
    "addr:housenumber":"20",
    "addr:postcode":"2567",
    "addr:street":"Woodland Crs",
    "iso:country":"AU",
    "sg:address":"20 Woodland Crs",
    "sg:city":"Narellan",
    "sg:classifiers":[
        {
            "category":"Professional",
            "subcategory":"Art Services",
            "type":"Services"
        }
    ],
    "sg:phone":"+61 414 571 525",
    "sg:postcode":"2567",
    "sg:province":"NSW",
    "sg:tags":[
        "decorator",
        "painter"
    ],
    "wof:name":"Megsy's Painting & Decorating",
    "wof:placetype":"venue"
},
  "geometry": {"coordinates":[150.73526000999999,-34.0400390625],"type":"Point"}
}