{
  "type": "Feature",
  "properties": {
    "addr:full":"113 Queensbridge St Southbank VIC 3006",
    "addr:housenumber":"113",
    "addr:postcode":"3006",
    "addr:street":"Queensbridge St",
    "iso:country":"AU",
    "sg:address":"113 Queensbridge St",
    "sg:city":"Southbank",
    "sg:classifiers":[
        {
            "category":"Manufacturing",
            "subcategory":"Furniture",
            "type":"Manufacturing & Wholesale Goods"
        }
    ],
    "sg:phone":"+61 3 9697 8900",
    "sg:postcode":"3006",
    "sg:province":"VIC",
    "sg:tags":[
        "equipment",
        "hire"
    ],
    "wof:name":"Audiovisuals & Multimedia On Southbank",
    "wof:placetype":"venue"
},
  "geometry": {"coordinates":[144.96051025400001,-37.825012207],"type":"Point"}
}