{
  "type": "Feature",
  "properties": {
    "addr:full":"Sheridan St Cairns QLD 4870",
    "addr:postcode":"4870",
    "addr:street":"Sheridan St",
    "iso:country":"AU",
    "sg:address":"Sheridan St",
    "sg:city":"Cairns",
    "sg:classifiers":[
        {
            "category":"Retail",
            "subcategory":"Auto Rental",
            "type":"Services"
        }
    ],
    "sg:phone":"+61 7 4032 2065",
    "sg:postcode":"4870",
    "sg:province":"QLD",
    "sg:tags":[
        "car",
        "hire",
        "minibus"
    ],
    "wof:name":"Maui",
    "wof:placetype":"venue"
},
  "geometry": {"coordinates":[145.77784729000001,-16.9287967682],"type":"Point"}
}