{
  "type": "Feature",
  "properties": {
    "iso:country":"AU",
    "sg:address":"Unit 10/ 33 Chanwood Rd St",
    "sg:city":"Kilda",
    "sg:classifiers":[
        {
            "category":"Professional",
            "subcategory":"Art Services",
            "type":"Services"
        }
    ],
    "sg:phone":"+61 3 9521 3141",
    "sg:postcode":"3182",
    "sg:province":"VIC",
    "sg:tags":[
        "interior",
        "designer"
    ],
    "wof:name":"Krisp Interiors",
    "wof:placetype":"venue"
},
  "geometry": {"coordinates":[144.98786926299999,-37.8590583801],"type":"Point"}
}