{
  "type": "Feature",
  "properties": {
    "iso:country":"AU",
    "sg:address":"18 Newman Ave",
    "sg:city":"Carnegie",
    "sg:classifiers":[
        {
            "category":"Building & Trades",
            "subcategory":"Landscaping Services",
            "type":"Services"
        }
    ],
    "sg:phone":"+61 3 9504 4769",
    "sg:postcode":"3163",
    "sg:province":"VIC",
    "sg:tags":[
        "gardener"
    ],
    "wof:name":"French Gardener",
    "wof:placetype":"venue"
},
  "geometry": {"coordinates":[145.05250549300001,-37.8996925354],"type":"Point"}
}