{
  "type": "Feature",
  "properties": {
    "iso:country":"AU",
    "sg:address":"46 Highett St",
    "sg:city":"Richmond",
    "sg:classifiers":[
        {
            "category":"Building & Trades",
            "subcategory":"Cleaning & Sanitation",
            "type":"Services"
        }
    ],
    "sg:phone":"+61 3 9415 6287",
    "sg:postcode":"3121",
    "sg:province":"VIC",
    "sg:tags":[
        "industrial",
        "commercial",
        "contractor"
    ],
    "wof:name":"A AAA Richmond Commercial Cleaners",
    "wof:placetype":"venue"
},
  "geometry": {"coordinates":[144.992752075,-37.815196991],"type":"Point"}
}