{
  "type": "Feature",
  "properties": {
    "addr:full":"Carmichael St Tootgarook VIC 3941",
    "addr:postcode":"3941",
    "addr:street":"Carmichael St",
    "iso:country":"AU",
    "sg:address":"Carmichael St",
    "sg:city":"Tootgarook",
    "sg:classifiers":[
        {
            "category":"Education",
            "subcategory":"School",
            "type":"Public Place"
        }
    ],
    "sg:phone":"+61 3 5985 2864",
    "sg:postcode":"3941",
    "sg:province":"VIC",
    "sg:tags":[
        "state",
        "except",
        "nsw"
    ],
    "wof:name":"Tootgarook Primary School",
    "wof:placetype":"venue"
},
  "geometry": {"coordinates":[144.85670471200001,-38.3688163757],"type":"Point"}
}