{
  "type": "Feature",
  "properties": {
    "addr:full":"1 Queen St Nunawading VIC 3131",
    "addr:housenumber":"1",
    "addr:postcode":"3131",
    "addr:street":"Queen St",
    "iso:country":"AU",
    "sg:address":"1 Queen St",
    "sg:city":"Nunawading",
    "sg:classifiers":[
        {
            "category":"Banks & Credit Unions",
            "subcategory":"Investment Brokerage",
            "type":"Services"
        }
    ],
    "sg:phone":"+61 3 9873 3955",
    "sg:postcode":"3131",
    "sg:province":"VIC",
    "sg:tags":[
        "radiator",
        "motor"
    ],
    "wof:name":"Mid East Radiator Centre",
    "wof:placetype":"venue"
},
  "geometry": {"coordinates":[145.184036255,-37.8185997009],"type":"Point"}
}