{
  "type": "Feature",
  "properties": {
    "addr:full":"5 Clermont Ave Concord NSW 2137",
    "addr:housenumber":"5",
    "addr:postcode":"2137",
    "addr:street":"Clermont Ave",
    "iso:country":"AU",
    "sg:address":"5 Clermont Ave",
    "sg:city":"Concord",
    "sg:classifiers":[
        {
            "category":"Building & Trades",
            "subcategory":"Plumbing",
            "type":"Services"
        }
    ],
    "sg:phone":"+61 2 9743 0306",
    "sg:postcode":"2137",
    "sg:province":"NSW",
    "sg:tags":[
        "plumber",
        "gasfitters"
    ],
    "wof:name":"Bathrooms & Plumbing",
    "wof:placetype":"venue"
},
  "geometry": {"coordinates":[151.09463500999999,-33.8567276001],"type":"Point"}
}