{
  "type": "Feature",
  "properties": {
    "iso:country":"AU",
    "sg:address":"43 Nicholson St",
    "sg:city":"Toronto West",
    "sg:classifiers":[
        {
            "category":"Professional",
            "subcategory":"Engineering",
            "type":"Services"
        }
    ],
    "sg:phone":"+61 2 4950 4135",
    "sg:postcode":"2283",
    "sg:province":"NSW",
    "sg:tags":[
        "diesel",
        "engineer"
    ],
    "wof:name":"Craig Wrightson Automotive Pty Ltd",
    "wof:placetype":"venue"
},
  "geometry": {"coordinates":[151.570877075,-33.0013504028],"type":"Point"}
}