{
  "type": "Feature",
  "properties": {
    "iso:country":"AU",
    "sg:address":"20 New South Head Rd",
    "sg:city":"Darling Point",
    "sg:classifiers":[
        {
            "category":"Manufacturing",
            "subcategory":"Glass & Minerals",
            "type":"Manufacturing & Wholesale Goods"
        }
    ],
    "sg:phone":"+61 2 9328 2659",
    "sg:postcode":"2027",
    "sg:province":"NSW",
    "sg:tags":[
        "merchant",
        "granite",
        "marble"
    ],
    "wof:name":"Mediterranean Marble & Granite Pty Ltd",
    "wof:placetype":"venue"
},
  "geometry": {"coordinates":[151.23260498100001,-33.8767662048],"type":"Point"}
}