{
  "type": "Feature",
  "properties": {
    "addr:full":"841 Moggill Rd Kenmore QLD 4069",
    "addr:housenumber":"841",
    "addr:postcode":"4069",
    "addr:street":"Moggill Rd",
    "iso:country":"AU",
    "sg:address":"841 Moggill Rd",
    "sg:city":"Kenmore",
    "sg:classifiers":[
        {
            "category":"Sports & Exercise",
            "subcategory":"Playing Field",
            "type":"Entertainment"
        }
    ],
    "sg:phone":"+61 7 3378 0370",
    "sg:postcode":"4069",
    "sg:province":"QLD",
    "sg:tags":[
        "gaming",
        "venue"
    ],
    "wof:name":"Emerald Mine",
    "wof:placetype":"venue"
},
  "geometry": {"coordinates":[152.948486328,-27.5070571899],"type":"Point"}
}