{
  "type": "Feature",
  "properties": {
    "iso:country":"AU",
    "sg:address":"44 Beatrice St",
    "sg:city":"Doubleview",
    "sg:classifiers":[
        {
            "category":"Building & Trades",
            "subcategory":"Plumbing",
            "type":"Services"
        }
    ],
    "sg:phone":"+61 403 054 384",
    "sg:postcode":"6018",
    "sg:province":"WA",
    "sg:tags":[
        "plumber",
        "gasfitters"
    ],
    "wof:name":"Jireh Plumbing",
    "wof:placetype":"venue"
},
  "geometry": {"coordinates":[115.78632354699999,-31.8939418793],"type":"Point"}
}