{
  "type": "Feature",
  "properties": {
    "iso:country":"AU",
    "sg:address":"Logan River Rd",
    "sg:city":"Beenleigh",
    "sg:classifiers":[
        {
            "category":"Wholesale",
            "subcategory":"Meat",
            "type":"Manufacturing & Wholesale Goods"
        }
    ],
    "sg:phone":"+61 7 3287 2188",
    "sg:postcode":"4207",
    "sg:province":"QLD",
    "sg:tags":[
        "abattoir"
    ],
    "wof:name":"Teys Bros (Beenleigh) Pty Ltd",
    "wof:placetype":"venue"
},
  "geometry": {"coordinates":[153.18698120100001,-27.7138938904],"type":"Point"}
}