{
  "type": "Feature",
  "properties": {
    "addr:full":"18 Castlereagh St Coonamble NSW 2829",
    "addr:housenumber":"18",
    "addr:postcode":"2829",
    "addr:street":"Castlereagh St",
    "iso:country":"AU",
    "sg:address":"18 Castlereagh St",
    "sg:city":"Coonamble",
    "sg:classifiers":[
        {
            "category":"Restaurant",
            "type":"Food & Drink"
        }
    ],
    "sg:phone":"+61 2 6822 1980",
    "sg:postcode":"2829",
    "sg:province":"NSW",
    "wof:name":"Coonamble RSL Club Chinese Restaurant",
    "wof:placetype":"venue"
},
  "geometry": {"coordinates":[148.38862609899999,-30.9519119263],"type":"Point"}
}