{
  "type": "Feature",
  "properties": {
    "addr:full":"PO Box 84 Highpoint City VIC 3032",
    "addr:postcode":"3032",
    "iso:country":"AU",
    "sg:address":"PO Box 84",
    "sg:city":"Highpoint City",
    "sg:classifiers":[
        {
            "category":"Professional",
            "subcategory":"Accounting & Tax Preparation",
            "type":"Services"
        }
    ],
    "sg:phone":"+61 3 9318 6338",
    "sg:postcode":"3032",
    "sg:province":"VIC",
    "sg:tags":[
        "broom",
        "brush"
    ],
    "wof:name":"The Fabric Care Company Of Australia Pty Ltd",
    "wof:placetype":"venue"
},
  "geometry": {"coordinates":[144.878906,-37.769642],"type":"Point"}
}