{
  "type": "Feature",
  "properties": {
    "iso:country":"AU",
    "sg:address":"214 Ogilive Ave",
    "sg:city":"Echuca",
    "sg:classifiers":[
        {
            "category":"Health Services",
            "subcategory":"Doctor",
            "type":"Services"
        }
    ],
    "sg:phone":"+61 3 5480 6700",
    "sg:postcode":"3564",
    "sg:province":"VIC",
    "sg:tags":[
        "medical",
        "practitioner"
    ],
    "wof:name":"Schultz Kathryn Dr",
    "wof:placetype":"venue"
},
  "geometry": {"coordinates":[144.74827575699999,-36.1404953003],"type":"Point"}
}