{
  "type": "Feature",
  "properties": {
    "addr:full":"Village Court,Argyle St Camden NSW 2570",
    "addr:postcode":"2570",
    "addr:street":"Village Court Argyle St",
    "iso:country":"AU",
    "sg:address":"Village Court,Argyle St",
    "sg:city":"Camden",
    "sg:classifiers":[
        {
            "category":"Cafe",
            "type":"Food & Drink"
        }
    ],
    "sg:phone":"+61 2 4655 6285",
    "sg:postcode":"2570",
    "sg:province":"NSW",
    "wof:name":"Village Coffee Shop & Restaurant",
    "wof:placetype":"venue"
},
  "geometry": {"coordinates":[150.69418335,-34.0552787781],"type":"Point"}
}