{
  "type": "Feature",
  "properties": {
    "iso:country":"AU",
    "sg:address":"26 Arabana St",
    "sg:city":"Aranda",
    "sg:classifiers":[
        {
            "category":"Professional",
            "subcategory":"Art Services",
            "type":"Services"
        }
    ],
    "sg:phone":"+61 2 6251 2469",
    "sg:postcode":"2614",
    "sg:province":"ACT",
    "sg:tags":[
        "decorator",
        "painter"
    ],
    "wof:name":"Peter Robbins",
    "wof:placetype":"venue"
},
  "geometry": {"coordinates":[149.08436584500001,-35.2547111511],"type":"Point"}
}