{
  "type": "Feature",
  "properties": {
    "iso:country":"AU",
    "sg:address":"23 Hiam St",
    "sg:city":"Glenbrook",
    "sg:classifiers":[
        {
            "category":"Utilities",
            "subcategory":"Water",
            "type":"Services"
        }
    ],
    "sg:phone":"+61 1300 734 180",
    "sg:postcode":"2773",
    "sg:province":"NSW",
    "sg:tags":[
        "hot",
        "system"
    ],
    "wof:name":"A AAAbound Plumbing & Gasfitting",
    "wof:placetype":"venue"
},
  "geometry": {"coordinates":[150.621170044,-33.7665481567],"type":"Point"}
}