{
  "type": "Feature",
  "properties": {
    "iso:country":"AU",
    "sg:address":"PO Box 487",
    "sg:city":"Nowra",
    "sg:classifiers":[
        {
            "category":"Banks & Credit Unions",
            "subcategory":"Bank",
            "type":"Services"
        }
    ],
    "sg:phone":"+61 2 4423 6660",
    "sg:postcode":"2541",
    "sg:province":"NSW",
    "sg:tags":[
        "broker",
        "mortgage"
    ],
    "wof:name":"Bayside Mortgages",
    "wof:placetype":"venue"
},
  "geometry": {"coordinates":[150.59387207,-34.8777999878],"type":"Point"}
}