{
  "type": "Feature",
  "properties": {
    "addr:full":"Hawker Professional Cntr Hawker Pl Hawker ACT 2614",
    "addr:postcode":"2614",
    "addr:street":"Pl",
    "iso:country":"AU",
    "sg:address":"Hawker Professional Cntr Hawker Pl",
    "sg:city":"Hawker",
    "sg:classifiers":[
        {
            "category":"Professional",
            "subcategory":"Art Services",
            "type":"Services"
        }
    ],
    "sg:phone":"+61 2 6278 8500",
    "sg:postcode":"2614",
    "sg:province":"ACT",
    "sg:tags":[
        "interior",
        "designer"
    ],
    "wof:name":"Small Quinton Coleman Architects",
    "wof:placetype":"venue"
},
  "geometry": {"coordinates":[149.04234314000001,-35.2431564331],"type":"Point"}
}