{
  "type": "Feature",
  "properties": {
    "addr:full":"PO Box 403 + Hamilton VIC 3300",
    "addr:housenumber":"+",
    "addr:postcode":"3300",
    "iso:country":"AU",
    "sg:address":"PO Box 403",
    "sg:city":"+ Hamilton",
    "sg:classifiers":[
        {
            "category":"Insurance",
            "subcategory":"Hazard Insurance",
            "type":"Services"
        }
    ],
    "sg:phone":"+61 408 037 232",
    "sg:postcode":"3300",
    "sg:province":"VIC",
    "sg:tags":[
        "fire",
        "accident",
        "marine"
    ],
    "wof:name":"QBE Insurance (Australia) Limited",
    "wof:placetype":"venue"
},
  "geometry": {"coordinates":[142.021575928,-37.7422294617],"type":"Point"}
}