{
  "type": "Feature",
  "properties": {
    "addr:full":"U 2/ 6 Roslyn Ave Kingston TAS 7050",
    "addr:housenumber":"6",
    "addr:postcode":"7050",
    "addr:street":"Roslyn Ave",
    "iso:country":"AU",
    "sg:address":"U 2/ 6 Roslyn Ave",
    "sg:city":"Kingston",
    "sg:classifiers":[
        {
            "category":"Recreation",
            "subcategory":"Boat Charter",
            "type":"Entertainment"
        }
    ],
    "sg:phone":"+61 407 555 990",
    "sg:postcode":"7050",
    "sg:province":"TAS",
    "wof:name":"Sea Dawn Sailing Charters",
    "wof:placetype":"venue"
},
  "geometry": {"coordinates":[147.31738300000001,-42.978226],"type":"Point"}
}