{
  "type": "Feature",
  "properties": {
    "addr:full":"15 Fleming St Aitkenvale QLD 4814",
    "addr:housenumber":"15",
    "addr:postcode":"4814",
    "addr:street":"Fleming St",
    "iso:country":"AU",
    "sg:address":"15 Fleming St",
    "sg:city":"Aitkenvale",
    "sg:classifiers":[
        {
            "category":"Retail",
            "subcategory":"Auto Repair",
            "type":"Services"
        }
    ],
    "sg:phone":"+61 7 4779 5063",
    "sg:postcode":"4814",
    "sg:province":"QLD",
    "sg:tags":[
        "repairer",
        "motor",
        "engineer"
    ],
    "wof:name":"A Lee Automotive",
    "wof:placetype":"venue"
},
  "geometry": {"coordinates":[146.768463,-19.293497],"type":"Point"}
}