{
  "type": "Feature",
  "properties": {
    "iso:country":"AU",
    "sg:address":"30 Edwin St",
    "sg:city":"Dubbo",
    "sg:classifiers":[
        {
            "category":"Professional",
            "subcategory":"Business Services",
            "type":"Services"
        }
    ],
    "sg:phone":"+61 2 6884 5242",
    "sg:postcode":"2830",
    "sg:province":"NSW",
    "sg:tags":[
        "livestock",
        "transport"
    ],
    "wof:name":"Andersons Stock transport",
    "wof:placetype":"venue"
},
  "geometry": {"coordinates":[148.613891602,-32.2384910583],"type":"Point"}
}