{
  "type": "Feature",
  "properties": {
    "addr:full":"88 Church St Brighton Middle VIC 3186",
    "addr:housenumber":"88",
    "addr:postcode":"3186",
    "addr:street":"Church St",
    "iso:country":"AU",
    "sg:address":"88 Church St",
    "sg:city":"Brighton Middle",
    "sg:classifiers":[
        {
            "category":"Food & Beverages",
            "subcategory":"Groceries & Convenience Stores",
            "type":"Retail Goods"
        }
    ],
    "sg:phone":"+61 3 9592 9370",
    "sg:postcode":"3186",
    "sg:province":"VIC",
    "wof:name":"Zampierollo G",
    "wof:placetype":"venue"
},
  "geometry": {"coordinates":[144.99528503400001,-37.9148483276],"type":"Point"}
}