{
  "type": "Feature",
  "properties": {
    "addr:full":"59 Dellamarta Rd Wangara WA 6065",
    "addr:housenumber":"59",
    "addr:postcode":"6065",
    "addr:street":"Dellamarta Rd",
    "iso:country":"AU",
    "sg:address":"59 Dellamarta Rd",
    "sg:city":"Wangara",
    "sg:classifiers":[
        {
            "category":"Retail",
            "subcategory":"Storage",
            "type":"Services"
        }
    ],
    "sg:phone":"+61 8 9309 6178",
    "sg:postcode":"6065",
    "sg:province":"WA",
    "wof:name":"OSS World Wide Movers",
    "wof:placetype":"venue"
},
  "geometry": {"coordinates":[115.826408386,-31.7903289795],"type":"Point"}
}