{
  "type": "Feature",
  "properties": {
    "addr:full":"Shp 8/ 288 Centre Dandenong Rd Moorabbin Airport VIC 3194",
    "addr:housenumber":"/ 288",
    "addr:postcode":"3194",
    "addr:street":"Centre Dandenong Rd",
    "iso:country":"AU",
    "sg:address":"Shp 8/ 288 Centre Dandenong Rd",
    "sg:city":"Moorabbin Airport",
    "sg:classifiers":[
        {
            "category":"Fast Food",
            "type":"Food & Drink"
        }
    ],
    "sg:phone":"+61 3 9583 4688",
    "sg:postcode":"3194",
    "sg:province":"VIC",
    "sg:tags":[
        "away",
        "take"
    ],
    "wof:name":"Kingston Charcoal Chicken",
    "wof:placetype":"venue"
},
  "geometry": {"coordinates":[145.09544372600001,-37.9702301025],"type":"Point"}
}