{
  "type": "Feature",
  "properties": {
    "addr:full":"31 Kent Rd North Ryde NSW 2113",
    "addr:housenumber":"31",
    "addr:postcode":"2113",
    "addr:street":"Kent Rd",
    "iso:country":"AU",
    "sg:address":"31 Kent Rd",
    "sg:city":"North Ryde",
    "sg:classifiers":[
        {
            "category":"Health Services",
            "subcategory":"Medical Lab",
            "type":"Services"
        }
    ],
    "sg:phone":"+61 2 9878 6256",
    "sg:postcode":"2113",
    "sg:province":"NSW",
    "sg:tags":[
        "laboratory",
        "dental"
    ],
    "wof:name":"H.D.T. Dental Lab",
    "wof:placetype":"venue"
},
  "geometry": {"coordinates":[151.11630249000001,-33.7913475037],"type":"Point"}
}