{
  "type": "Feature",
  "properties": {
    "addr:full":"79 Callandoon St Inglewood QLD 4387",
    "addr:housenumber":"79",
    "addr:postcode":"4387",
    "addr:street":"Callandoon St",
    "iso:country":"AU",
    "sg:address":"79 Callandoon St",
    "sg:city":"Inglewood",
    "sg:classifiers":[
        {
            "category":"Professional",
            "subcategory":"Art Services",
            "type":"Services"
        }
    ],
    "sg:phone":"+61 7 4652 1341",
    "sg:postcode":"4387",
    "sg:province":"QLD",
    "sg:tags":[
        "decorator",
        "painter"
    ],
    "wof:name":"Rowlings D J",
    "wof:placetype":"venue"
},
  "geometry": {"coordinates":[151.07925399999999,-28.411936],"type":"Point"}
}