{
  "type": "Feature",
  "properties": {
    "addr:full":"222 Gladstone St Maryborough VIC 3465",
    "addr:housenumber":"222",
    "addr:postcode":"3465",
    "addr:street":"Gladstone St",
    "iso:country":"AU",
    "sg:address":"222 Gladstone St",
    "sg:city":"Maryborough",
    "sg:classifiers":[
        {
            "category":"Utilities",
            "subcategory":"Electric",
            "type":"Services"
        }
    ],
    "sg:phone":"+61 3 5461 2853",
    "sg:postcode":"3465",
    "sg:province":"VIC",
    "sg:tags":[
        "electrical",
        "contractor"
    ],
    "wof:name":"Beaton David J",
    "wof:placetype":"venue"
},
  "geometry": {"coordinates":[143.73101806599999,-37.0402336121],"type":"Point"}
}