{
  "type": "Feature",
  "properties": {
    "iso:country":"AU",
    "sg:address":"13 Dromana Pl",
    "sg:city":"Craigie",
    "sg:classifiers":[
        {
            "category":"Home & Garden",
            "subcategory":"Household Appliances",
            "type":"Retail Goods"
        }
    ],
    "sg:phone":"+61 8 9402 3113",
    "sg:postcode":"6025",
    "sg:province":"WA",
    "sg:tags":[
        "equipment",
        "gas"
    ],
    "wof:name":"Gas Stoveman",
    "wof:placetype":"venue"
},
  "geometry": {"coordinates":[115.758041382,-31.7832736969],"type":"Point"}
}