{
  "type": "Feature",
  "properties": {
    "addr:full":"Star St Tambo QLD 4478",
    "addr:postcode":"4478",
    "addr:street":"Star St",
    "iso:country":"AU",
    "sg:address":"Star St",
    "sg:city":"Tambo",
    "sg:classifiers":[
        {
            "category":"Personal",
            "subcategory":"Beauty Salon",
            "type":"Services"
        }
    ],
    "sg:phone":"+61 7 4654 6469",
    "sg:postcode":"4478",
    "sg:province":"QLD",
    "sg:tags":[
        "hairdresser"
    ],
    "wof:name":"Mollys Hair Design",
    "wof:placetype":"venue"
},
  "geometry": {"coordinates":[146.25550842300001,-24.8820571899],"type":"Point"}
}