{
  "type": "Feature",
  "properties": {
    "addr:full":"11 Bungan St Mona Vale NSW 2103",
    "addr:housenumber":"11",
    "addr:postcode":"2103",
    "addr:street":"Bungan St",
    "iso:country":"AU",
    "sg:address":"11 Bungan St",
    "sg:city":"Mona Vale",
    "sg:classifiers":[
        {
            "category":"Shopping",
            "subcategory":"Clothing, Apparel, & Fashions",
            "type":"Retail Goods"
        }
    ],
    "sg:phone":"+61 2 9997 3875",
    "sg:postcode":"2103",
    "sg:province":"NSW",
    "sg:tags":[
        "lady",
        "wear"
    ],
    "wof:name":"Three Wishes Boutique",
    "wof:placetype":"venue"
},
  "geometry": {"coordinates":[151.30262756400001,-33.6765441895],"type":"Point"}
}