{
  "type": "Feature",
  "properties": {
    "addr:full":"3077 Logan Rd Underwood QLD 4119",
    "addr:housenumber":"3077",
    "addr:postcode":"4119",
    "addr:street":"Logan Rd",
    "iso:country":"AU",
    "sg:address":"3077 Logan Rd",
    "sg:city":"Underwood",
    "sg:classifiers":[
        {
            "category":"Autos & Motor Vehicles",
            "subcategory":"Fuel & Gas Station",
            "type":"Retail Goods"
        }
    ],
    "sg:phone":"+61 7 3341 1955",
    "sg:postcode":"4119",
    "sg:province":"QLD",
    "wof:name":"Neumann Petroleum",
    "wof:placetype":"venue"
},
  "geometry": {"coordinates":[153.11581420900001,-27.6111888885],"type":"Point"}
}