{
  "type": "Feature",
  "properties": {
    "iso:country":"AU",
    "sg:address":"122 Avoca St",
    "sg:city":"Randwick",
    "sg:classifiers":[
        {
            "category":"Personal",
            "subcategory":"Beauty Salon",
            "type":"Services"
        }
    ],
    "sg:phone":"+61 2 9399 5155",
    "sg:postcode":"2031",
    "sg:province":"NSW",
    "sg:tags":[
        "hairdresser"
    ],
    "wof:name":"That Hair Studio",
    "wof:placetype":"venue"
},
  "geometry": {"coordinates":[151.242019653,-33.912902832],"type":"Point"}
}