{
  "type": "Feature",
  "properties": {
    "iso:country":"AU",
    "sg:address":"61 Main Rd",
    "sg:city":"Wivenhoe",
    "sg:classifiers":[
        {
            "category":"Autos & Motor Vehicles",
            "subcategory":"Automobile Sales",
            "type":"Retail Goods"
        }
    ],
    "sg:phone":"+61 3 6431 9855",
    "sg:postcode":"7320",
    "sg:province":"TAS",
    "sg:tags":[
        "bus",
        "truck",
        "new"
    ],
    "wof:name":"IVECO",
    "wof:placetype":"venue"
},
  "geometry": {"coordinates":[145.94058200000001,-41.067768],"type":"Point"}
}