{
  "type": "Feature",
  "properties": {
    "iso:country":"AU",
    "sg:address":"252 Kensington Rd",
    "sg:city":"Leabrook",
    "sg:classifiers":[
        {
            "category":"Restaurant",
            "type":"Food & Drink"
        }
    ],
    "sg:phone":"+61 8 8431 4288",
    "sg:postcode":"5068",
    "sg:province":"SA",
    "sg:website":"http://www.thespicekitchen.com.au",
    "wof:name":"Dhaba @ The Spice Kitchen",
    "wof:placetype":"venue"
},
  "geometry": {"coordinates":[138.65544128400001,-34.9260864258],"type":"Point"}
}