{
  "type": "Feature",
  "properties": {
    "addr:full":"7 Amaroo Rd Chadstone VIC 3148",
    "addr:housenumber":"7",
    "addr:postcode":"3148",
    "addr:street":"Amaroo Rd",
    "iso:country":"AU",
    "sg:address":"7 Amaroo Rd",
    "sg:city":"Chadstone",
    "sg:classifiers":[
        {
            "category":"Professional",
            "subcategory":"Business Services",
            "type":"Services"
        }
    ],
    "sg:phone":"+61 3 9888 3830",
    "sg:postcode":"3148",
    "sg:province":"VIC",
    "sg:tags":[
        "exporter"
    ],
    "wof:name":"Rima Exports",
    "wof:placetype":"venue"
},
  "geometry": {"coordinates":[145.101470947,-37.8766746521],"type":"Point"}
}