{
  "type": "Feature",
  "properties": {
    "addr:full":"21 Vernon St Spotswood VIC 3015",
    "addr:housenumber":"21",
    "addr:postcode":"3015",
    "addr:street":"Vernon St",
    "iso:country":"AU",
    "sg:address":"21 Vernon St",
    "sg:city":"Spotswood",
    "sg:classifiers":[
        {
            "category":"Food & Beverages",
            "subcategory":"Liquor & Beverages",
            "type":"Retail Goods"
        }
    ],
    "sg:phone":"+61 3 9391 2637",
    "sg:postcode":"3015",
    "sg:province":"VIC",
    "sg:tags":[
        "store"
    ],
    "wof:name":"Tipple J Cellars",
    "wof:placetype":"venue"
},
  "geometry": {"coordinates":[144.87205505399999,-37.8294448853],"type":"Point"}
}