{
  "type": "Feature",
  "properties": {
    "addr:full":"24 Lucy St Ashfield NSW 2131",
    "addr:housenumber":"24",
    "addr:postcode":"2131",
    "addr:street":"Lucy St",
    "iso:country":"AU",
    "sg:address":"24 Lucy St",
    "sg:city":"Ashfield",
    "sg:classifiers":[
        {
            "category":"Professional",
            "subcategory":"Art Services",
            "type":"Services"
        }
    ],
    "sg:phone":"+61 411 753 332",
    "sg:postcode":"2131",
    "sg:province":"NSW",
    "sg:tags":[
        "decorator",
        "painter"
    ],
    "wof:name":"Greg Wisby Painting",
    "wof:placetype":"venue"
},
  "geometry": {"coordinates":[151.123947144,-33.878238678],"type":"Point"}
}