{
  "type": "Feature",
  "properties": {
    "addr:full":"24 Dorothy St Wentworthville NSW 2145",
    "addr:housenumber":"24",
    "addr:postcode":"2145",
    "addr:street":"Dorothy St",
    "iso:country":"AU",
    "sg:address":"24 Dorothy St",
    "sg:city":"Wentworthville",
    "sg:classifiers":[
        {
            "category":"Home & Garden",
            "subcategory":"Hardware",
            "type":"Retail Goods"
        }
    ],
    "sg:phone":"+61 2 9688 1775",
    "sg:postcode":"2145",
    "sg:province":"NSW",
    "sg:tags":[
        "repair",
        "tool",
        "power"
    ],
    "wof:name":"All Handy Electrical Services",
    "wof:placetype":"venue"
},
  "geometry": {"coordinates":[150.966705322,-33.7983283997],"type":"Point"}
}