{
  "type": "Feature",
  "properties": {
    "addr:full":"Unit D, 7 Curban St Underwood QLD 4119",
    "addr:postcode":"4119",
    "addr:street":"Curban St",
    "iso:country":"AU",
    "sg:address":"Unit D, 7 Curban St",
    "sg:city":"Underwood",
    "sg:classifiers":[
        {
            "category":"Professional",
            "subcategory":"Computer Services",
            "type":"Services"
        }
    ],
    "sg:phone":"+61 7 3841 3999",
    "sg:postcode":"4119",
    "sg:province":"QLD",
    "sg:tags":[
        "equipment",
        "networking",
        "installation"
    ],
    "sg:website":"http://www.simcomcity.com",
    "wof:name":"SIMCOM ENTERPRISES PTY LTD",
    "wof:placetype":"venue"
},
  "geometry": {"coordinates":[153.11293029800001,-27.6110439301],"type":"Point"}
}