{
  "type": "Feature",
  "properties": {
    "addr:full":"19- 27 Oborn Rd Mt Barker SA 5251",
    "addr:housenumber":"27",
    "addr:postcode":"5251",
    "addr:street":"Oborn Rd",
    "iso:country":"AU",
    "sg:address":"19- 27 Oborn Rd",
    "sg:city":"Mt Barker",
    "sg:classifiers":[
        {
            "category":"Manufacturing",
            "subcategory":"Paper Products",
            "type":"Manufacturing & Wholesale Goods"
        }
    ],
    "sg:phone":"+61 8 8391 1377",
    "sg:postcode":"5251",
    "sg:province":"SA",
    "sg:tags":[
        "metal",
        "non-ferrous",
        "foundry"
    ],
    "wof:name":"MBP Australia Pty Ltd",
    "wof:placetype":"venue"
},
  "geometry": {"coordinates":[138.87449645999999,-35.0800018311],"type":"Point"}
}