{
  "type": "Feature",
  "properties": {
    "addr:full":"34 McMahons Rd Coburg North VIC 3058",
    "addr:housenumber":"34",
    "addr:postcode":"3058",
    "addr:street":"Mcmahons Rd",
    "iso:country":"AU",
    "sg:address":"34 McMahons Rd",
    "sg:city":"Coburg North",
    "sg:classifiers":[
        {
            "category":"Retail",
            "subcategory":"Repair Shop",
            "type":"Services"
        }
    ],
    "sg:phone":"+61 418 375 548",
    "sg:postcode":"3058",
    "sg:province":"VIC",
    "sg:tags":[
        "upholsterer"
    ],
    "wof:name":"Jewel Upholstery",
    "wof:placetype":"venue"
},
  "geometry": {"coordinates":[144.96961975100001,-37.728061676],"type":"Point"}
}