{
  "type": "Feature",
  "properties": {
    "iso:country":"AU",
    "sg:address":"Iluka Rd",
    "sg:city":"Aspendale",
    "sg:classifiers":[
        {
            "category":"Banks & Credit Unions",
            "subcategory":"Financial Services",
            "type":"Services"
        }
    ],
    "sg:phone":"+61 3 9587 1273",
    "sg:postcode":"3195",
    "sg:province":"VIC",
    "sg:tags":[
        "loan",
        "finance",
        "mortgage"
    ],
    "wof:name":"Mortgage Wisdom",
    "wof:placetype":"venue"
},
  "geometry": {"coordinates":[145.10804748499999,-38.0233612061],"type":"Point"}
}