{
  "type": "Feature",
  "properties": {
    "iso:country":"AU",
    "sg:address":"Scott St",
    "sg:city":"Portsmith",
    "sg:classifiers":[
        {
            "category":"Retail",
            "subcategory":"Auto Repair",
            "type":"Services"
        }
    ],
    "sg:phone":"+61 7 4051 0252",
    "sg:postcode":"4870",
    "sg:province":"QLD",
    "sg:tags":[
        "beater",
        "painter",
        "panel"
    ],
    "wof:name":"Mick Petryszyn Paint & Panel",
    "wof:placetype":"venue"
},
  "geometry": {"coordinates":[145.76588439899999,-16.9294624329],"type":"Point"}
}