{
  "type": "Feature",
  "properties": {
    "iso:country":"AU",
    "sg:address":"PO Box 470",
    "sg:city":"Warburton",
    "sg:classifiers":[
        {
            "category":"Retail",
            "subcategory":"Auto Repair",
            "type":"Services"
        }
    ],
    "sg:phone":"+61 418 396 153",
    "sg:postcode":"3799",
    "sg:province":"VIC",
    "sg:tags":[
        "electrical"
    ],
    "wof:name":"Warburton Mobile Automotive Electrical Service",
    "wof:placetype":"venue"
},
  "geometry": {"coordinates":[145.707305908,-37.7111206055],"type":"Point"}
}