{
  "type": "Feature",
  "properties": {
    "iso:country":"AU",
    "sg:address":"5 Caprice Pl",
    "sg:city":"Narre Warren",
    "sg:classifiers":[
        {
            "category":"Banks & Credit Unions",
            "subcategory":"Investment Brokerage",
            "type":"Services"
        }
    ],
    "sg:phone":"+61 418 538 280",
    "sg:postcode":"3805",
    "sg:province":"VIC",
    "sg:tags":[
        "shutter",
        "louvre"
    ],
    "wof:name":"P K Design",
    "wof:placetype":"venue"
},
  "geometry": {"coordinates":[145.301514,-38.001816],"type":"Point"}
}