{
  "type": "Feature",
  "properties": {
    "addr:full":"98 Commercial Rd New Farm QLD 4005",
    "addr:housenumber":"98",
    "addr:postcode":"4005",
    "addr:street":"Commercial Rd",
    "iso:country":"AU",
    "sg:address":"98 Commercial Rd",
    "sg:city":"New Farm",
    "sg:classifiers":[
        {
            "category":"Real Estate",
            "subcategory":"Real Estate Agent",
            "type":"Services"
        }
    ],
    "sg:phone":"+61 7 3252 5060",
    "sg:postcode":"4005",
    "sg:province":"QLD",
    "wof:name":"PRDnationwide",
    "wof:placetype":"venue"
},
  "geometry": {"coordinates":[153.04661560100001,-27.4540843964],"type":"Point"}
}