{
  "type": "Feature",
  "properties": {
    "addr:full":"6 Brightview Rd Glenore Grove QLD 4342",
    "addr:housenumber":"6",
    "addr:postcode":"4342",
    "addr:street":"Brightview Rd",
    "iso:country":"AU",
    "sg:address":"6 Brightview Rd",
    "sg:city":"Glenore Grove",
    "sg:classifiers":[
        {
            "category":"Food & Beverages",
            "subcategory":"Groceries & Convenience Stores",
            "type":"Retail Goods"
        }
    ],
    "sg:phone":"+61 7 5466 5280",
    "sg:postcode":"4342",
    "sg:province":"QLD",
    "wof:name":"Glenore Grove Store",
    "wof:placetype":"venue"
},
  "geometry": {"coordinates":[152.407836914,-27.530210495],"type":"Point"}
}