{
  "type": "Feature",
  "properties": {
    "iso:country":"AU",
    "sg:address":"Shp3/ 56 Rabaul Rd",
    "sg:city":"Georges Hall",
    "sg:classifiers":[
        {
            "category":"Restaurant",
            "type":"Food & Drink"
        }
    ],
    "sg:phone":"+61 2 9755 5568",
    "sg:postcode":"2198",
    "sg:province":"NSW",
    "wof:name":"Aquarius Seafood Restaurant",
    "wof:placetype":"venue"
},
  "geometry": {"coordinates":[150.974792,-33.915436],"type":"Point"}
}