{
  "type": "Feature",
  "properties": {
    "addr:full":"188 Lyons Rd Drummoyne NSW 2047",
    "addr:housenumber":"188",
    "addr:postcode":"2047",
    "addr:street":"Lyons Rd",
    "iso:country":"AU",
    "sg:address":"188 Lyons Rd",
    "sg:city":"Drummoyne",
    "sg:classifiers":[
        {
            "category":"Personal",
            "subcategory":"Beauty Salon",
            "type":"Services"
        }
    ],
    "sg:phone":"+61 2 9181 3961",
    "sg:postcode":"2047",
    "sg:province":"NSW",
    "sg:tags":[
        "hairdresser"
    ],
    "wof:name":"Heavens Edge Cutters & Stylists",
    "wof:placetype":"venue"
},
  "geometry": {"coordinates":[151.14613299999999,-33.856441],"type":"Point"}
}