{
  "type": "Feature",
  "properties": {
    "addr:full":"Lot 82 Spur Pl Glenorie NSW 2157",
    "addr:postcode":"2157",
    "addr:street":"Pl",
    "iso:country":"AU",
    "sg:address":"Lot 82 Spur Pl",
    "sg:city":"Glenorie",
    "sg:classifiers":[
        {
            "category":"Shopping",
            "subcategory":"Antiques",
            "type":"Retail Goods"
        }
    ],
    "sg:phone":"+61 2 9652 0045",
    "sg:postcode":"2157",
    "sg:province":"NSW",
    "sg:tags":[
        "restoration",
        "reproduction"
    ],
    "wof:name":"Cherrybrook Upholsterers",
    "wof:placetype":"venue"
},
  "geometry": {"coordinates":[151.008056641,-33.5469017029],"type":"Point"}
}