{
  "type": "Feature",
  "properties": {
    "iso:country":"AU",
    "sg:address":"George St",
    "sg:city":"Major's Creek",
    "sg:classifiers":[
        {
            "category":"Travel",
            "subcategory":"Hotels & Motels",
            "type":"Entertainment"
        }
    ],
    "sg:phone":"+61 2 4846 1145",
    "sg:postcode":"2622",
    "sg:province":"NSW",
    "sg:tags":[
        "accommodation"
    ],
    "wof:name":"Elrington Hotel",
    "wof:placetype":"venue"
},
  "geometry": {"coordinates":[149.741165161,-35.563129425],"type":"Point"}
}