{
  "type": "Feature",
  "properties": {
    "addr:full":"122 Cameron St Rockdale NSW 2216",
    "addr:housenumber":"122",
    "addr:postcode":"2216",
    "addr:street":"Cameron St",
    "iso:country":"AU",
    "sg:address":"122 Cameron St",
    "sg:city":"Rockdale",
    "sg:classifiers":[
        {
            "category":"Shopping",
            "subcategory":"Clothing, Apparel, & Fashions",
            "type":"Retail Goods"
        }
    ],
    "sg:phone":"+61 2 9567 1998",
    "sg:postcode":"2216",
    "sg:province":"NSW",
    "sg:tags":[
        "hire",
        "men's",
        "wear",
        "formal"
    ],
    "wof:name":"Formal Knight",
    "wof:placetype":"venue"
},
  "geometry": {"coordinates":[151.14254800000001,-33.954796],"type":"Point"}
}