{
  "type": "Feature",
  "properties": {
    "addr:full":"55 Marshall St Goondiwindi QLD 4390",
    "addr:housenumber":"55",
    "addr:postcode":"4390",
    "addr:street":"Marshall St",
    "iso:country":"AU",
    "sg:address":"55 Marshall St",
    "sg:city":"Goondiwindi",
    "sg:classifiers":[
        {
            "category":"Real Estate",
            "subcategory":"Real Estate Agent",
            "type":"Services"
        }
    ],
    "sg:phone":"+61 7 4671 1922",
    "sg:postcode":"4390",
    "sg:province":"QLD",
    "wof:name":"George Sloss First National",
    "wof:placetype":"venue"
},
  "geometry": {"coordinates":[150.30616760300001,-28.5466537476],"type":"Point"}
}