{
  "type": "Feature",
  "properties": {
    "addr:full":"Unit 2, 136 Railway Pde Granville NSW 2142",
    "addr:housenumber":"136",
    "addr:postcode":"2142",
    "addr:street":"Railway Pde",
    "iso:country":"AU",
    "sg:address":"Unit 2, 136 Railway Pde",
    "sg:city":"Granville",
    "sg:classifiers":[
        {
            "category":"Communications",
            "type":"Services"
        }
    ],
    "sg:phone":"+61 2 8821 9599",
    "sg:postcode":"2142",
    "sg:province":"NSW",
    "sg:tags":[
        "equipment",
        "radio"
    ],
    "sg:website":"http://www.mastercom.com.au",
    "wof:name":"Master Communications",
    "wof:placetype":"venue"
},
  "geometry": {"coordinates":[151.00474548299999,-33.8299331665],"type":"Point"}
}