{
  "type": "Feature",
  "properties": {
    "addr:full":"24 Marine Pde Kingscliff NSW 2487",
    "addr:housenumber":"24",
    "addr:postcode":"2487",
    "addr:street":"Marine Pde",
    "iso:country":"AU",
    "sg:address":"24 Marine Pde",
    "sg:city":"Kingscliff",
    "sg:classifiers":[
        {
            "category":"Health Services",
            "subcategory":"Dentist",
            "type":"Services"
        }
    ],
    "sg:phone":"+61 2 6674 1443",
    "sg:postcode":"2487",
    "sg:province":"NSW",
    "wof:name":"McCullough Bruce D",
    "wof:placetype":"venue"
},
  "geometry": {"coordinates":[153.579833984,-28.2570590973],"type":"Point"}
}