{
  "type": "Feature",
  "properties": {
    "addr:full":"Ste 2/ 628 Canterbury Rd Vermont VIC 3133",
    "addr:housenumber":"/ 628",
    "addr:postcode":"3133",
    "addr:street":"Canterbury Rd",
    "iso:country":"AU",
    "sg:address":"Ste 2/ 628 Canterbury Rd",
    "sg:city":"Vermont",
    "sg:classifiers":[
        {
            "category":"Professional",
            "subcategory":"Accounting & Tax Preparation",
            "type":"Services"
        }
    ],
    "sg:phone":"+61 3 9872 4733",
    "sg:postcode":"3133",
    "sg:province":"VIC",
    "sg:tags":[
        "accountant",
        "auditor"
    ],
    "wof:name":"Capitol Group Advisers",
    "wof:placetype":"venue"
},
  "geometry": {"coordinates":[145.19679260300001,-37.8359718323],"type":"Point"}
}