{
  "type": "Feature",
  "properties": {
    "iso:country":"AU",
    "sg:address":"127 Sir Donald Bradman Drv",
    "sg:city":"Hilton",
    "sg:classifiers":[
        {
            "category":"Fast Food",
            "type":"Food & Drink"
        }
    ],
    "sg:phone":"+61 8 8443 8305",
    "sg:postcode":"5033",
    "sg:province":"SA",
    "sg:tags":[
        "away",
        "take"
    ],
    "wof:name":"Hilton Snack Bar",
    "wof:placetype":"venue"
},
  "geometry": {"coordinates":[138.56532287600001,-34.9323043823],"type":"Point"}
}