{
  "type": "Feature",
  "properties": {
    "addr:full":"97 South St Rydalmere NSW 2116",
    "addr:housenumber":"97",
    "addr:postcode":"2116",
    "addr:street":"South St",
    "iso:country":"AU",
    "sg:address":"97 South St",
    "sg:city":"Rydalmere",
    "sg:classifiers":[
        {
            "category":"Building & Trades",
            "subcategory":"Landscaping Services",
            "type":"Services"
        }
    ],
    "sg:phone":"+61 405 295 973",
    "sg:postcode":"2116",
    "sg:province":"NSW",
    "sg:tags":[
        "stump",
        "tree",
        "felling",
        "removal"
    ],
    "wof:name":"Alex Gardening & Tree Lopping",
    "wof:placetype":"venue"
},
  "geometry": {"coordinates":[151.01083374000001,-33.8357429504],"type":"Point"}
}