{
  "type": "Feature",
  "properties": {
    "iso:country":"AU",
    "sg:address":"33 Boomerang St",
    "sg:city":"Turramurra",
    "sg:classifiers":[
        {
            "category":"Health Services",
            "subcategory":"Health Practitioner",
            "type":"Services"
        }
    ],
    "sg:phone":"+61 2 9449 4244",
    "sg:postcode":"2074",
    "sg:province":"NSW",
    "sg:tags":[
        "psychologist"
    ],
    "wof:name":"Pittwater Psychology",
    "wof:placetype":"venue"
},
  "geometry": {"coordinates":[151.134857178,-33.7286071777],"type":"Point"}
}