{
  "type": "Feature",
  "properties": {
    "iso:country":"AU",
    "sg:address":"60 Liebig St",
    "sg:city":"Warrnambool",
    "sg:classifiers":[
        {
            "category":"Cafe",
            "type":"Food & Drink"
        }
    ],
    "sg:phone":"+61 3 5562 4208",
    "sg:postcode":"3280",
    "sg:province":"VIC",
    "wof:name":"Images Restaurant Cafe Cocktail Bar",
    "wof:placetype":"venue"
},
  "geometry": {"coordinates":[142.48275756800001,-38.3851737976],"type":"Point"}
}