{
  "type": "Feature",
  "properties": {
    "addr:full":"173 Ballinger Rd Buderim QLD 4556",
    "addr:housenumber":"173",
    "addr:postcode":"4556",
    "addr:street":"Ballinger Rd",
    "iso:country":"AU",
    "sg:address":"173 Ballinger Rd",
    "sg:city":"Buderim",
    "sg:classifiers":[
        {
            "category":"Utilities",
            "subcategory":"Electric",
            "type":"Services"
        }
    ],
    "sg:phone":"+61 7 5445 8305",
    "sg:postcode":"4556",
    "sg:province":"QLD",
    "sg:tags":[
        "electrical",
        "contractor"
    ],
    "wof:name":"Static Electrics",
    "wof:placetype":"venue"
},
  "geometry": {"coordinates":[153.062957764,-26.698091507],"type":"Point"}
}