{
  "type": "Feature",
  "properties": {
    "addr:full":"124 Douglas Pde Williamstown VIC 3016",
    "addr:housenumber":"124",
    "addr:postcode":"3016",
    "addr:street":"Douglas Pde",
    "iso:country":"AU",
    "sg:address":"124 Douglas Pde",
    "sg:city":"Williamstown",
    "sg:classifiers":[
        {
            "category":"Restaurant",
            "type":"Food & Drink"
        }
    ],
    "sg:phone":"+61 3 9397 0666",
    "sg:postcode":"3016",
    "sg:province":"VIC",
    "wof:name":"Bend Wine Bar The",
    "wof:placetype":"venue"
},
  "geometry": {"coordinates":[144.89727783199999,-37.8545570374],"type":"Point"}
}