{
  "type": "Feature",
  "properties": {
    "iso:country":"AU",
    "sg:address":"220 Caithness Rd",
    "sg:city":"Koonwarra",
    "sg:classifiers":[
        {
            "category":"Farming",
            "subcategory":"Nursery",
            "type":"Manufacturing & Wholesale Goods"
        }
    ],
    "sg:phone":"+61 3 5664 2202",
    "sg:postcode":"3954",
    "sg:province":"VIC",
    "wof:name":"AA Trees Nurseryman",
    "wof:placetype":"venue"
},
  "geometry": {"coordinates":[145.94573974599999,-38.5654754639],"type":"Point"}
}