{
  "type": "Feature",
  "properties": {
    "iso:country":"AU",
    "sg:address":"10 Angus Crt",
    "sg:city":"Benowa Waters",
    "sg:classifiers":[
        {
            "category":"Personal",
            "subcategory":"Hair Removal",
            "type":"Services"
        }
    ],
    "sg:phone":"+61 7 5539 6271",
    "sg:postcode":"4217",
    "sg:province":"QLD",
    "wof:name":"Diane Maries Massage & Beauty Services",
    "wof:placetype":"venue"
},
  "geometry": {"coordinates":[153.399047852,-28.0135364532],"type":"Point"}
}