{
  "type": "Feature",
  "properties": {
    "addr:full":"Bugle Hut Rd Taldra SA 5311",
    "addr:postcode":"5311",
    "addr:street":"Bugle Hut Rd",
    "iso:country":"AU",
    "sg:address":"Bugle Hut Rd",
    "sg:city":"Taldra",
    "sg:classifiers":[
        {
            "category":"Farming",
            "subcategory":"Farm",
            "type":"Manufacturing & Wholesale Goods"
        }
    ],
    "sg:phone":"+61 8 8595 6009",
    "sg:postcode":"5311",
    "sg:province":"SA",
    "sg:tags":[
        "farmer"
    ],
    "wof:name":"Frahn G A & Y Z S",
    "wof:placetype":"venue"
},
  "geometry": {"coordinates":[140.78732299800001,-34.3107147217],"type":"Point"}
}