{
  "type": "Feature",
  "properties": {
    "addr:full":"96 Maurice Rd Murray Bridge SA 5253",
    "addr:housenumber":"96",
    "addr:postcode":"5253",
    "addr:street":"Maurice Rd",
    "iso:country":"AU",
    "sg:address":"96 Maurice Rd",
    "sg:city":"Murray Bridge",
    "sg:classifiers":[
        {
            "category":"Retail",
            "subcategory":"Auto Repair",
            "type":"Services"
        }
    ],
    "sg:phone":"+61 8 8531 0799",
    "sg:postcode":"5253",
    "sg:province":"SA",
    "sg:tags":[
        "repairer",
        "motor",
        "engineer"
    ],
    "wof:name":"Affordable Mechanical Repairs",
    "wof:placetype":"venue"
},
  "geometry": {"coordinates":[139.25601196299999,-35.1245651245],"type":"Point"}
}