{
  "type": "Feature",
  "properties": {
    "iso:country":"AU",
    "sg:address":"39 Bromfield Dr",
    "sg:city":"Kelmscott",
    "sg:classifiers":[
        {
            "category":"Personal",
            "subcategory":"Massage",
            "type":"Services"
        }
    ],
    "sg:phone":"+61 8 9390 7263",
    "sg:postcode":"6111",
    "sg:province":"WA",
    "sg:tags":[
        "therapy"
    ],
    "wof:name":"Susanne Vock",
    "wof:placetype":"venue"
},
  "geometry": {"coordinates":[116.03388977,-32.132396698],"type":"Point"}
}