{
  "type": "Feature",
  "properties": {
    "iso:country":"AU",
    "sg:address":"13 Penn St",
    "sg:city":"Mackay",
    "sg:classifiers":[
        {
            "category":"Professional",
            "subcategory":"Accounting & Tax Preparation",
            "type":"Services"
        }
    ],
    "sg:phone":"+61 7 4944 1417",
    "sg:postcode":"4740",
    "sg:province":"QLD",
    "sg:tags":[
        "accountant",
        "auditor"
    ],
    "wof:name":"Alec MacDonald (Unlocking Your Profit Potential)",
    "wof:placetype":"venue"
},
  "geometry": {"coordinates":[149.18301399999999,-21.15502],"type":"Point"}
}