{
  "type": "Feature",
  "properties": {
    "iso:country":"AU",
    "sg:address":"10 Chadstone Rd",
    "sg:city":"Malvern East",
    "sg:classifiers":[
        {
            "category":"Building & Trades",
            "subcategory":"Construction",
            "type":"Services"
        }
    ],
    "sg:phone":"+61 414 077 178",
    "sg:postcode":"3145",
    "sg:province":"VIC",
    "sg:tags":[
        "contractor"
    ],
    "wof:name":"Supreme Bathrooms & Kitchens",
    "wof:placetype":"venue"
},
  "geometry": {"coordinates":[145.07879638700001,-37.8846626282],"type":"Point"}
}