{
  "type": "Feature",
  "properties": {
    "addr:full":"The Lane 48 Main St Samford QLD 4520",
    "addr:housenumber":"48",
    "addr:postcode":"4520",
    "addr:street":"The Lane;Main St",
    "iso:country":"AU",
    "sg:address":"The Lane 48 Main St",
    "sg:city":"Samford",
    "sg:classifiers":[
        {
            "category":"Social Services",
            "subcategory":"Retirement Home",
            "type":"Services"
        }
    ],
    "sg:phone":"+61 7 3289 5266",
    "sg:postcode":"4520",
    "sg:province":"QLD",
    "sg:tags":[
        "environmental",
        "consultant",
        "pollution"
    ],
    "wof:name":"Clements Environmental Consultants",
    "wof:placetype":"venue"
},
  "geometry": {"coordinates":[152.88699299999999,-27.370068],"type":"Point"}
}