{
  "type": "Feature",
  "properties": {
    "iso:country":"AU",
    "sg:address":"39 Terry St",
    "sg:city":"Rozelle",
    "sg:classifiers":[
        {
            "category":"Social Services",
            "subcategory":"Job Training",
            "type":"Services"
        }
    ],
    "sg:phone":"+61 2 9555 2288",
    "sg:postcode":"2039",
    "sg:province":"NSW",
    "sg:tags":[
        "hire",
        "computer",
        "leasing"
    ],
    "wof:name":"Discount Computer Rentals",
    "wof:placetype":"venue"
},
  "geometry": {"coordinates":[151.167770386,-33.8606491089],"type":"Point"}
}