{
  "type": "Feature",
  "properties": {
    "addr:full":"129 Sir Donald Bradman Drv Hilton SA 5033",
    "addr:housenumber":"129",
    "addr:postcode":"5033",
    "addr:street":"Sir Donald Bradman Drv",
    "iso:country":"AU",
    "sg:address":"129 Sir Donald Bradman Drv",
    "sg:city":"Hilton",
    "sg:classifiers":[
        {
            "category":"Health Services",
            "subcategory":"Doctor",
            "type":"Services"
        }
    ],
    "sg:phone":"+61 13 13 89",
    "sg:postcode":"5033",
    "sg:province":"SA",
    "sg:tags":[
        "nurse",
        "nursing"
    ],
    "wof:name":"Nurse Bank Australia",
    "wof:placetype":"venue"
},
  "geometry": {"coordinates":[138.565216064,-34.932308197],"type":"Point"}
}