{
  "type": "Feature",
  "properties": {
    "addr:full":"Shp 7/ 3171 Surfers Paradise Blv Surfers Paradise QLD 4217",
    "addr:housenumber":"/ 3171",
    "addr:postcode":"4217",
    "addr:street":"Surfers Paradise Blv",
    "iso:country":"AU",
    "sg:address":"Shp 7/ 3171 Surfers Paradise Blv",
    "sg:city":"Surfers Paradise",
    "sg:classifiers":[
        {
            "category":"Ice Cream",
            "type":"Food & Drink"
        }
    ],
    "sg:phone":"+61 7 5526 9682",
    "sg:postcode":"4217",
    "sg:province":"QLD",
    "sg:tags":[
        "retail"
    ],
    "wof:name":"Baskin Robins",
    "wof:placetype":"venue"
},
  "geometry": {"coordinates":[153.42871093799999,-27.999830246],"type":"Point"}
}