{
  "type": "Feature",
  "properties": {
    "addr:full":"31 Brunel St Malvern East VIC 3145",
    "addr:housenumber":"31",
    "addr:postcode":"3145",
    "addr:street":"Brunel St",
    "iso:country":"AU",
    "sg:address":"31 Brunel St",
    "sg:city":"Malvern East",
    "sg:classifiers":[
        {
            "category":"Utilities",
            "subcategory":"Electric",
            "type":"Services"
        }
    ],
    "sg:phone":"+61 3 9885 7055",
    "sg:postcode":"3145",
    "sg:province":"VIC",
    "sg:tags":[
        "electrical",
        "contractor"
    ],
    "wof:name":"Harris-Barry D & Y",
    "wof:placetype":"venue"
},
  "geometry": {"coordinates":[145.05284118599999,-37.8695068359],"type":"Point"}
}