{
  "type": "Feature",
  "properties": {
    "addr:full":"71 Perouse Rd Randwick NSW 2031",
    "addr:housenumber":"71",
    "addr:postcode":"2031",
    "addr:street":"Perouse Rd",
    "iso:country":"AU",
    "sg:address":"71 Perouse Rd",
    "sg:city":"Randwick",
    "sg:classifiers":[
        {
            "category":"Cafe",
            "type":"Food & Drink"
        }
    ],
    "sg:phone":"+61 2 9398 7994",
    "sg:postcode":"2031",
    "sg:province":"NSW",
    "wof:name":"Tea Scapes Cafe",
    "wof:placetype":"venue"
},
  "geometry": {"coordinates":[151.24302673299999,-33.9208946228],"type":"Point"}
}