{
  "type": "Feature",
  "properties": {
    "addr:full":"Cnr Cleeland & David Sts Dandenong North VIC 3175",
    "addr:postcode":"3175",
    "addr:street":"Cnr",
    "iso:country":"AU",
    "sg:address":"Cnr Cleeland & David Sts",
    "sg:city":"Dandenong North",
    "sg:classifiers":[
        {
            "category":"Education",
            "subcategory":"School",
            "type":"Public Place"
        }
    ],
    "sg:phone":"+61 3 9794 7899",
    "sg:postcode":"3175",
    "sg:province":"VIC",
    "sg:tags":[
        "state",
        "except",
        "nsw"
    ],
    "wof:name":"Dandenong North Primary",
    "wof:placetype":"venue"
},
  "geometry": {"coordinates":[145.21702575699999,-37.9718437195],"type":"Point"}
}