{
  "type": "Feature",
  "properties": {
    "addr:full":"PO Box 149 Ballina NSW 2478",
    "addr:postcode":"2478",
    "iso:country":"AU",
    "sg:address":"PO Box 149",
    "sg:city":"Ballina",
    "sg:classifiers":[
        {
            "category":"Professional",
            "subcategory":"Detective & Security Services",
            "type":"Services"
        }
    ],
    "sg:phone":"+61 2 6686 8789",
    "sg:postcode":"2478",
    "sg:province":"NSW",
    "sg:tags":[
        "equipment",
        "window",
        "doors"
    ],
    "wof:name":"Atlas Awnings Northern Rivers",
    "wof:placetype":"venue"
},
  "geometry": {"coordinates":[153.56430053700001,-28.8569545746],"type":"Point"}
}