{
  "type": "Feature",
  "properties": {
    "addr:full":"4 Spey St Winston Hills NSW 2153",
    "addr:housenumber":"4",
    "addr:postcode":"2153",
    "addr:street":"Spey St",
    "iso:country":"AU",
    "sg:address":"4 Spey St",
    "sg:city":"Winston Hills",
    "sg:classifiers":[
        {
            "category":"Education",
            "subcategory":"Special Training",
            "type":"Public Place"
        }
    ],
    "sg:phone":"+61 2 9639 4454",
    "sg:postcode":"2153",
    "sg:province":"NSW",
    "sg:tags":[
        "school",
        "art"
    ],
    "wof:name":"Agius School Of Music & Arts",
    "wof:placetype":"venue"
},
  "geometry": {"coordinates":[150.98292541500001,-33.7779273987],"type":"Point"}
}