{
  "type": "Feature",
  "properties": {
    "addr:full":"Cnr Roberts Rd Lot 4, Moloney Rd Virginia SA 5120",
    "addr:postcode":"5120",
    "addr:street":"Cnr Roberts Rd;Moloney Rd",
    "iso:country":"AU",
    "sg:address":"Cnr Roberts Rd Lot 4, Moloney Rd",
    "sg:city":"Virginia",
    "sg:classifiers":[
        {
            "category":"Building & Trades",
            "subcategory":"Construction",
            "type":"Services"
        }
    ],
    "sg:phone":"+61 413 179 384",
    "sg:postcode":"5120",
    "sg:province":"SA",
    "sg:tags":[
        "earth",
        "excavating",
        "moving",
        "contractor"
    ],
    "wof:name":"Booth & Elliot Concrete Developments",
    "wof:placetype":"venue"
},
  "geometry": {"coordinates":[138.56080627399999,-34.6675415039],"type":"Point"}
}