{
  "type": "Feature",
  "properties": {
    "iso:country":"AU",
    "sg:address":"7 Loxton St",
    "sg:city":"Kew",
    "sg:classifiers":[
        {
            "category":"Real Estate",
            "subcategory":"Architect",
            "type":"Services"
        }
    ],
    "sg:phone":"+61 3 9817 6212",
    "sg:postcode":"3101",
    "sg:province":"VIC",
    "wof:name":"Tan M H",
    "wof:placetype":"venue"
},
  "geometry": {"coordinates":[145.05816650400001,-37.8165969849],"type":"Point"}
}