{
  "type": "Feature",
  "properties": {
    "iso:country":"AU",
    "sg:address":"7 Anakie St",
    "sg:city":"Emerald",
    "sg:classifiers":[
        {
            "category":"Professional",
            "subcategory":"Accounting & Tax Preparation",
            "type":"Services"
        }
    ],
    "sg:phone":"+61 7 4987 6988",
    "sg:postcode":"4720",
    "sg:province":"QLD",
    "sg:tags":[
        "accountant",
        "auditor"
    ],
    "wof:name":"Christine Peters Accountant",
    "wof:placetype":"venue"
},
  "geometry": {"coordinates":[148.16061400000001,-23.523058],"type":"Point"}
}