{
  "type": "Feature",
  "properties": {
    "addr:full":"180 Railway St Maryborough VIC 3465",
    "addr:housenumber":"180",
    "addr:postcode":"3465",
    "addr:street":"Railway St",
    "iso:country":"AU",
    "sg:address":"180 Railway St",
    "sg:city":"Maryborough",
    "sg:classifiers":[
        {
            "category":"Building & Trades",
            "subcategory":"Construction",
            "type":"Services"
        }
    ],
    "sg:phone":"+61 3 5461 3100",
    "sg:postcode":"3465",
    "sg:province":"VIC",
    "sg:tags":[
        "polishing",
        "sanding",
        "floor"
    ],
    "wof:name":"Bauch Timber Floors",
    "wof:placetype":"venue"
},
  "geometry": {"coordinates":[143.74229431099999,-37.0533370972],"type":"Point"}
}