{
  "type": "Feature",
  "properties": {
    "addr:full":"497 New South Head Rd Double Bay NSW 2028",
    "addr:housenumber":"497",
    "addr:postcode":"2028",
    "addr:street":"New South Head Rd",
    "iso:country":"AU",
    "sg:address":"497 New South Head Rd",
    "sg:city":"Double Bay",
    "sg:classifiers":[
        {
            "category":"Health Services",
            "subcategory":"Health Practitioner",
            "type":"Services"
        }
    ],
    "sg:phone":"+61 412 701 484",
    "sg:postcode":"2028",
    "sg:province":"NSW",
    "sg:tags":[
        "psychologist"
    ],
    "wof:name":"Betts Sharmila",
    "wof:placetype":"venue"
},
  "geometry": {"coordinates":[151.24620056099999,-33.8761405945],"type":"Point"}
}