{
  "type": "Feature",
  "properties": {
    "addr:full":"7 Bollen St Kilkenny SA 5009",
    "addr:housenumber":"7",
    "addr:postcode":"5009",
    "addr:street":"Bollen St",
    "iso:country":"AU",
    "sg:address":"7 Bollen St",
    "sg:city":"Kilkenny",
    "sg:classifiers":[
        {
            "category":"Building & Trades",
            "subcategory":"Plumbing",
            "type":"Services"
        }
    ],
    "sg:phone":"+61 8 8347 4577",
    "sg:postcode":"5009",
    "sg:province":"SA",
    "sg:tags":[
        "pump",
        "repairer"
    ],
    "wof:name":"Crowell Benson & Co. Pty. Ltd.",
    "wof:placetype":"venue"
},
  "geometry": {"coordinates":[138.55595398,-34.8778305054],"type":"Point"}
}