{
  "type": "Feature",
  "properties": {
    "addr:full":"529 High St Northcote VIC 3070",
    "addr:housenumber":"529",
    "addr:postcode":"3070",
    "addr:street":"High St",
    "iso:country":"AU",
    "sg:address":"529 High St",
    "sg:city":"Northcote",
    "sg:classifiers":[
        {
            "category":"Shopping",
            "subcategory":"Music",
            "type":"Retail Goods"
        }
    ],
    "sg:phone":"+61 3 9481 0542",
    "sg:postcode":"3070",
    "sg:province":"VIC",
    "sg:tags":[
        "instrument",
        "musical"
    ],
    "wof:name":"Studio Headquarters",
    "wof:placetype":"venue"
},
  "geometry": {"coordinates":[144.99943500000001,-37.764526],"type":"Point"}
}