{
  "type": "Feature",
  "properties": {
    "iso:country":"AU",
    "sg:address":"Fcty 2, East Court 101-155 Beresford Rd",
    "sg:city":"Lilydale",
    "sg:classifiers":[
        {
            "category":"Building & Trades",
            "subcategory":"Construction",
            "type":"Services"
        }
    ],
    "sg:phone":"+61 3 9739 7199",
    "sg:postcode":"3140",
    "sg:province":"VIC",
    "sg:tags":[
        "joinery"
    ],
    "wof:name":"The Kitchen Business",
    "wof:placetype":"venue"
},
  "geometry": {"coordinates":[145.35130310100001,-37.7512359619],"type":"Point"}
}