{
  "type": "Feature",
  "properties": {
    "addr:full":"410 Poplar Ave Shepparton East VIC 3631",
    "addr:housenumber":"410",
    "addr:postcode":"3631",
    "addr:street":"Poplar Ave",
    "iso:country":"AU",
    "sg:address":"410 Poplar Ave",
    "sg:city":"Shepparton East",
    "sg:classifiers":[
        {
            "category":"Manufacturing",
            "subcategory":"Electronics",
            "type":"Manufacturing & Wholesale Goods"
        }
    ],
    "sg:phone":"+61 3 5829 1067",
    "sg:postcode":"3631",
    "sg:province":"VIC",
    "sg:tags":[
        "wholesaler",
        "equipment",
        "part",
        "mfrs",
        "refrigeration"
    ],
    "wof:name":"Bolt On Parts",
    "wof:placetype":"venue"
},
  "geometry": {"coordinates":[145.45489501899999,-36.3991203308],"type":"Point"}
}