{
  "type": "Feature",
  "properties": {
    "iso:country":"AU",
    "sg:address":"Kyogle Rd",
    "sg:city":"Casino",
    "sg:classifiers":[
        {
            "category":"Education",
            "subcategory":"School",
            "type":"Public Place"
        }
    ],
    "sg:phone":"+61 2 6662 3077",
    "sg:postcode":"2470",
    "sg:province":"NSW",
    "sg:tags":[
        "state",
        "-",
        "nsw"
    ],
    "wof:name":"Casino High School",
    "wof:placetype":"venue"
},
  "geometry": {"coordinates":[153.04057312,-28.8570899963],"type":"Point"}
}