{
  "type": "Feature",
  "properties": {
    "addr:full":"27 Sulphide St Broken Hill NSW 2880",
    "addr:housenumber":"27",
    "addr:postcode":"2880",
    "addr:street":"Sulphide St",
    "iso:country":"AU",
    "sg:address":"27 Sulphide St",
    "sg:city":"Broken Hill",
    "sg:classifiers":[
        {
            "category":"Fast Food",
            "type":"Food & Drink"
        }
    ],
    "sg:phone":"+61 8 8088 2452",
    "sg:postcode":"2880",
    "sg:province":"NSW",
    "sg:tags":[
        "away",
        "take"
    ],
    "wof:name":"Champion Pizza & Chinese Takeaway",
    "wof:placetype":"venue"
},
  "geometry": {"coordinates":[141.46353149399999,-31.959318161],"type":"Point"}
}