{
  "type": "Feature",
  "properties": {
    "iso:country":"AU",
    "sg:address":"2 Fletcher St",
    "sg:city":"East Fremantle",
    "sg:classifiers":[
        {
            "category":"Health Services",
            "subcategory":"Health Practitioner",
            "type":"Services"
        }
    ],
    "sg:phone":"+61 8 9339 0372",
    "sg:postcode":"6158",
    "sg:province":"WA",
    "sg:tags":[
        "pathologist",
        "speech"
    ],
    "wof:name":"Beilby Janet",
    "wof:placetype":"venue"
},
  "geometry": {"coordinates":[115.770142,-32.04353],"type":"Point"}
}