{
  "type": "Feature",
  "properties": {
    "addr:full":"1 Bligh St Gympie QLD 4570",
    "addr:housenumber":"1",
    "addr:postcode":"4570",
    "addr:street":"Bligh St",
    "iso:country":"AU",
    "sg:address":"1 Bligh St",
    "sg:city":"Gympie",
    "sg:classifiers":[
        {
            "category":"Food & Beverages",
            "subcategory":"Groceries & Convenience Stores",
            "type":"Retail Goods"
        }
    ],
    "sg:phone":"+61 7 5482 2621",
    "sg:postcode":"4570",
    "sg:province":"QLD",
    "wof:name":"Murphy's Convenience Store",
    "wof:placetype":"venue"
},
  "geometry": {"coordinates":[152.66848754899999,-26.1910839081],"type":"Point"}
}