{
  "type": "Feature",
  "properties": {
    "iso:country":"AU",
    "sg:address":"Stuart Hwy",
    "sg:city":"Katherine",
    "sg:classifiers":[
        {
            "category":"Building & Trades",
            "subcategory":"Construction",
            "type":"Services"
        }
    ],
    "sg:phone":"+61 8 8972 1639",
    "sg:postcode":"0850",
    "sg:province":"NT",
    "sg:tags":[
        "contractor"
    ],
    "wof:name":"Dee Jay Sanderling Pine Creek",
    "wof:placetype":"venue"
},
  "geometry": {"coordinates":[132.299103,-14.475524],"type":"Point"}
}