{
  "type": "Feature",
  "properties": {
    "iso:country":"AU",
    "sg:address":"61 Queen Victoria St",
    "sg:city":"Fremantle",
    "sg:classifiers":[
        {
            "category":"Retail",
            "subcategory":"Auto Repair",
            "type":"Services"
        }
    ],
    "sg:phone":"+61 8 9336 2733",
    "sg:postcode":"6160",
    "sg:province":"WA",
    "sg:tags":[
        "repairer",
        "motor",
        "engineer"
    ],
    "wof:name":"Auto Masters Fremantle",
    "wof:placetype":"venue"
},
  "geometry": {"coordinates":[115.75018300000001,-32.049435],"type":"Point"}
}