{
  "type": "Feature",
  "properties": {
    "iso:country":"AU",
    "sg:address":"Lot 104 Wattle Rd",
    "sg:city":"Shellharbour",
    "sg:classifiers":[
        {
            "category":"Building & Trades",
            "subcategory":"Construction",
            "type":"Services"
        }
    ],
    "sg:phone":"+61 2 4297 7887",
    "sg:postcode":"2529",
    "sg:province":"NSW",
    "sg:tags":[
        "contractor"
    ],
    "wof:name":"Clarendon Homes (NSW) Pty Limited",
    "wof:placetype":"venue"
},
  "geometry": {"coordinates":[150.85952758799999,-34.5803604126],"type":"Point"}
}