{
  "type": "Feature",
  "properties": {
    "iso:country":"AU",
    "sg:address":"316 Chapel Rd",
    "sg:city":"Bankstown",
    "sg:classifiers":[
        {
            "category":"Food & Beverages",
            "subcategory":"Fruits & Vegetables",
            "type":"Retail Goods"
        }
    ],
    "sg:phone":"+61 2 9796 7754",
    "sg:postcode":"2200",
    "sg:province":"NSW",
    "sg:tags":[
        "greengrocer",
        "fruiterer"
    ],
    "wof:name":"Thanh Long Fruit & Vegetable Shop",
    "wof:placetype":"venue"
},
  "geometry": {"coordinates":[151.03179900000001,-33.919003],"type":"Point"}
}