{
  "type": "Feature",
  "properties": {
    "addr:full":"22 Woodsome St Mt Lawley WA 6050",
    "addr:housenumber":"22",
    "addr:postcode":"6050",
    "addr:street":"Woodsome St",
    "iso:country":"AU",
    "sg:address":"22 Woodsome St",
    "sg:city":"Mt Lawley",
    "sg:classifiers":[
        {
            "category":"Real Estate",
            "subcategory":"Architect",
            "type":"Services"
        }
    ],
    "sg:phone":"+61 8 9272 4674",
    "sg:postcode":"6050",
    "sg:province":"WA",
    "wof:name":"Cockram Colin G",
    "wof:placetype":"venue"
},
  "geometry": {"coordinates":[115.86670684800001,-31.9254684448],"type":"Point"}
}