{
  "type": "Feature",
  "properties": {
    "addr:full":"20 Park St Hamilton NSW 2303",
    "addr:housenumber":"20",
    "addr:postcode":"2303",
    "addr:street":"Park St",
    "iso:country":"AU",
    "sg:address":"20 Park St",
    "sg:city":"Hamilton",
    "sg:classifiers":[
        {
            "category":"Retail",
            "subcategory":"Veterinary Services",
            "type":"Services"
        }
    ],
    "sg:phone":"+61 2 4969 8200",
    "sg:postcode":"2303",
    "sg:province":"NSW",
    "sg:tags":[
        "surgeon"
    ],
    "wof:name":"Mobile Vet Newcastle",
    "wof:placetype":"venue"
},
  "geometry": {"coordinates":[151.74629200000001,-32.930771],"type":"Point"}
}