{
  "type": "Feature",
  "properties": {
    "iso:country":"AU",
    "sg:address":"29 Park Rd",
    "sg:city":"Sans Souci",
    "sg:classifiers":[
        {
            "category":"Autos & Motor Vehicles",
            "subcategory":"Fuel & Gas Station",
            "type":"Retail Goods"
        }
    ],
    "sg:phone":"+61 2 9529 0610",
    "sg:postcode":"2219",
    "sg:province":"NSW",
    "wof:name":"Sans Souci Service Centre",
    "wof:placetype":"venue"
},
  "geometry": {"coordinates":[151.138443,-33.986359],"type":"Point"}
}