{
  "type": "Feature",
  "properties": {
    "iso:country":"AU",
    "sg:address":"Cnr Ruby & Yamala Sts",
    "sg:city":"Emerald",
    "sg:classifiers":[
        {
            "category":"Health Services",
            "subcategory":"Doctor",
            "type":"Services"
        }
    ],
    "sg:phone":"+61 7 4982 4544",
    "sg:postcode":"4720",
    "sg:province":"QLD",
    "sg:tags":[
        "medical",
        "practitioner"
    ],
    "wof:name":"Emerald Medical Group",
    "wof:placetype":"venue"
},
  "geometry": {"coordinates":[148.158157,-23.524878],"type":"Point"}
}