{
  "type": "Feature",
  "properties": {
    "iso:country":"AU",
    "sg:address":"Shop 14 The Phoenician 110 Surf Pde",
    "sg:city":"Broadbeach",
    "sg:classifiers":[
        {
            "category":"Shopping",
            "subcategory":"Shoes",
            "type":"Retail Goods"
        }
    ],
    "sg:phone":"+61 7 5538 5317",
    "sg:postcode":"4218",
    "sg:province":"QLD",
    "sg:tags":[
        "footwear"
    ],
    "wof:name":"Cheran Shoes",
    "wof:placetype":"venue"
},
  "geometry": {"coordinates":[153.431152344,-28.0276355743],"type":"Point"}
}