{
  "type": "Feature",
  "properties": {
    "addr:full":"433 North Rd Ormond VIC 3204",
    "addr:housenumber":"433",
    "addr:postcode":"3204",
    "addr:street":"North Rd",
    "iso:country":"AU",
    "sg:address":"433 North Rd",
    "sg:city":"Ormond",
    "sg:classifiers":[
        {
            "category":"Health Services",
            "subcategory":"Chiropractor",
            "type":"Services"
        }
    ],
    "sg:phone":"+61 3 9578 4912",
    "sg:postcode":"3204",
    "sg:province":"VIC",
    "wof:name":"Family Chiropractic & Natural Health",
    "wof:placetype":"venue"
},
  "geometry": {"coordinates":[145.036957,-37.9034],"type":"Point"}
}