{
  "type": "Feature",
  "properties": {
    "addr:full":"58 Bronte Rd Bondi Junction NSW 2022",
    "addr:housenumber":"58",
    "addr:postcode":"2022",
    "addr:street":"Bronte Rd",
    "iso:country":"AU",
    "sg:address":"58 Bronte Rd",
    "sg:city":"Bondi Junction",
    "sg:classifiers":[
        {
            "category":"Retail",
            "subcategory":"Self-service Laundry",
            "type":"Services"
        }
    ],
    "sg:phone":"+61 2 9387 2007",
    "sg:postcode":"2022",
    "sg:province":"NSW",
    "wof:name":"Wringer Laundry The",
    "wof:placetype":"venue"
},
  "geometry": {"coordinates":[151.25022888199999,-33.8944854736],"type":"Point"}
}