{
  "type": "Feature",
  "properties": {
    "addr:full":"42 Stubb St Flemington VIC 3031",
    "addr:housenumber":"42",
    "addr:postcode":"3031",
    "addr:street":"Stubb St",
    "iso:country":"AU",
    "sg:address":"42 Stubb St",
    "sg:city":"Flemington",
    "sg:classifiers":[
        {
            "category":"Professional",
            "subcategory":"Detective & Security Services",
            "type":"Services"
        }
    ],
    "sg:phone":"+61 3 9329 1711",
    "sg:postcode":"3031",
    "sg:province":"VIC",
    "sg:tags":[
        "guard",
        "patrol"
    ],
    "wof:name":"Nor-West Armoured Car Service",
    "wof:placetype":"venue"
},
  "geometry": {"coordinates":[144.935562,-37.790421],"type":"Point"}
}