{
  "type": "Feature",
  "properties": {
    "iso:country":"AU",
    "sg:address":"PO Box 889",
    "sg:city":"Moss Vale",
    "sg:classifiers":[
        {
            "category":"Building & Trades",
            "subcategory":"Construction",
            "type":"Services"
        }
    ],
    "sg:phone":"+61 421 038 664",
    "sg:postcode":"2577",
    "sg:province":"NSW",
    "sg:tags":[
        "plasterboard",
        "plasterer",
        "fixer"
    ],
    "wof:name":"R. J. Goff Cement Rendering",
    "wof:placetype":"venue"
},
  "geometry": {"coordinates":[150.371170044,-34.5501289368],"type":"Point"}
}