{
  "type": "Feature",
  "properties": {
    "addr:full":"Springwood Rd Springwood QLD 4127",
    "addr:postcode":"4127",
    "addr:street":"Springwood Rd",
    "iso:country":"AU",
    "sg:address":"Springwood Rd",
    "sg:city":"Springwood",
    "sg:classifiers":[
        {
            "category":"Education",
            "subcategory":"School",
            "type":"Public Place"
        }
    ],
    "sg:phone":"+61 7 3341 5133",
    "sg:postcode":"4127",
    "sg:province":"QLD",
    "sg:tags":[
        "state",
        "except",
        "nsw"
    ],
    "wof:name":"Springwood Road Primary",
    "wof:placetype":"venue"
},
  "geometry": {"coordinates":[153.13616943400001,-27.6143341064],"type":"Point"}
}