{
  "type": "Feature",
  "properties": {
    "iso:country":"AU",
    "sg:address":"PO Box 331",
    "sg:city":"Manjimup",
    "sg:classifiers":[
        {
            "category":"Conference Center",
            "type":"Public Place"
        }
    ],
    "sg:phone":"+61 8 9773 1268",
    "sg:postcode":"6258",
    "sg:province":"WA",
    "sg:tags":[
        "venue",
        "convention"
    ],
    "wof:name":"Kin Kin Retreat",
    "wof:placetype":"venue"
},
  "geometry": {"coordinates":[116.14914703399999,-34.2399215698],"type":"Point"}
}