{
  "type": "Feature",
  "properties": {
    "addr:full":"20 Burns Rd Heathcote NSW 2233",
    "addr:housenumber":"20",
    "addr:postcode":"2233",
    "addr:street":"Burns Rd",
    "iso:country":"AU",
    "sg:address":"20 Burns Rd",
    "sg:city":"Heathcote",
    "sg:classifiers":[
        {
            "category":"Utilities",
            "subcategory":"Electric",
            "type":"Services"
        }
    ],
    "sg:phone":"+61 2 9520 8832",
    "sg:postcode":"2233",
    "sg:province":"NSW",
    "sg:tags":[
        "electrical",
        "contractor"
    ],
    "wof:name":"Engadine Electrical Service",
    "wof:placetype":"venue"
},
  "geometry": {"coordinates":[150.99597168,-34.0976333618],"type":"Point"}
}