{
  "type": "Feature",
  "properties": {
    "addr:full":"104 Compton Rd Underwood QLD 4119",
    "addr:housenumber":"104",
    "addr:postcode":"4119",
    "addr:street":"Compton Rd",
    "iso:country":"AU",
    "sg:address":"104 Compton Rd",
    "sg:city":"Underwood",
    "sg:classifiers":[
        {
            "category":"Shopping",
            "subcategory":"Crafts & Fabrics",
            "type":"Retail Goods"
        }
    ],
    "sg:phone":"+61 7 3208 9373",
    "sg:postcode":"4119",
    "sg:province":"QLD",
    "sg:tags":[
        "material",
        "dress"
    ],
    "sg:website":"http://www.selectivefinefabrics.com.au",
    "wof:name":"Selective Fine Fabrics",
    "wof:placetype":"venue"
},
  "geometry": {"coordinates":[153.10552978499999,-27.618894577],"type":"Point"}
}