{
  "type": "Feature",
  "properties": {
    "iso:country":"AU",
    "sg:address":"34 Norval St",
    "sg:city":"Auburn",
    "sg:classifiers":[
        {
            "category":"Health Services",
            "subcategory":"Doctor",
            "type":"Services"
        }
    ],
    "sg:phone":"+61 2 9646 3895",
    "sg:postcode":"2144",
    "sg:province":"NSW",
    "sg:tags":[
        "medical",
        "practitioner"
    ],
    "wof:name":"Lalak A",
    "wof:placetype":"venue"
},
  "geometry": {"coordinates":[151.03239440900001,-33.859413147],"type":"Point"}
}