{
  "type": "Feature",
  "properties": {
    "iso:country":"AU",
    "sg:address":"8 Ulpha Pl",
    "sg:city":"Cranebrook",
    "sg:classifiers":[
        {
            "category":"Professional",
            "subcategory":"Accounting & Tax Preparation",
            "type":"Services"
        }
    ],
    "sg:phone":"+61 2 4729 1307",
    "sg:postcode":"2749",
    "sg:province":"NSW",
    "sg:tags":[
        "consultant",
        "taxation"
    ],
    "wof:name":"Taxline",
    "wof:placetype":"venue"
},
  "geometry": {"coordinates":[150.71360778799999,-33.721660614],"type":"Point"}
}