{
  "type": "Feature",
  "properties": {
    "addr:full":"37 Albion St Harris Park NSW 2150",
    "addr:housenumber":"37",
    "addr:postcode":"2150",
    "addr:street":"Albion St",
    "iso:country":"AU",
    "sg:address":"37 Albion St",
    "sg:city":"Harris Park",
    "sg:classifiers":[
        {
            "category":"Banks & Credit Unions",
            "subcategory":"Financial Services",
            "type":"Services"
        }
    ],
    "sg:phone":"+61 2 9635 0303",
    "sg:postcode":"2150",
    "sg:province":"NSW",
    "sg:tags":[
        "planning"
    ],
    "wof:name":"Friends Group Of Consultants Pty Ltd",
    "wof:placetype":"venue"
},
  "geometry": {"coordinates":[151.00997924800001,-33.8205337524],"type":"Point"}
}