{
  "type": "Feature",
  "properties": {
    "addr:full":"799 Frauenfelder St Albury NSW 2640",
    "addr:housenumber":"799",
    "addr:postcode":"2640",
    "addr:street":"Frauenfelder St",
    "iso:country":"AU",
    "sg:address":"799 Frauenfelder St",
    "sg:city":"Albury",
    "sg:classifiers":[
        {
            "category":"Farming",
            "subcategory":"Farm & Veterinary Services",
            "type":"Manufacturing & Wholesale Goods"
        }
    ],
    "sg:phone":"+61 2 6029 2589",
    "sg:postcode":"2640",
    "sg:province":"NSW",
    "sg:tags":[
        "agricultural",
        "advisory"
    ],
    "wof:name":"Tim Paramore Agronomic Services Pty Ltd",
    "wof:placetype":"venue"
},
  "geometry": {"coordinates":[146.927536011,-36.0662956238],"type":"Point"}
}