{
  "type": "Feature",
  "properties": {
    "iso:country":"AU",
    "sg:address":"Shop 46, Shellharbour Square Shopping Centre",
    "sg:city":"Shellharbour Square",
    "sg:classifiers":[
        {
            "category":"Banks & Credit Unions",
            "subcategory":"Financial Services",
            "type":"Services"
        }
    ],
    "sg:phone":"+61 13 34 62",
    "sg:postcode":"2529",
    "sg:province":"NSW",
    "sg:tags":[
        "building",
        "society"
    ],
    "wof:name":"IMB",
    "wof:placetype":"venue"
},
  "geometry": {"coordinates":[150.861785889,-34.5697059631],"type":"Point"}
}