{
  "type": "Feature",
  "properties": {
    "addr:full":"12 Welder Rd Seven Hills NSW 2147",
    "addr:housenumber":"12",
    "addr:postcode":"2147",
    "addr:street":"Welder Rd",
    "iso:country":"AU",
    "sg:address":"12 Welder Rd",
    "sg:city":"Seven Hills",
    "sg:classifiers":[
        {
            "category":"Manufacturing",
            "subcategory":"Retail Goods",
            "type":"Manufacturing & Wholesale Goods"
        }
    ],
    "sg:phone":"+61 2 8811 2000",
    "sg:postcode":"2147",
    "sg:province":"NSW",
    "sg:tags":[
        "merchant",
        "pump",
        "mfrs"
    ],
    "wof:name":"Prime Pumps",
    "wof:placetype":"venue"
},
  "geometry": {"coordinates":[150.957275391,-33.7692070007],"type":"Point"}
}