{
  "type": "Feature",
  "properties": {
    "addr:full":"155 Main St Osborne Park WA 6017",
    "addr:housenumber":"155",
    "addr:postcode":"6017",
    "addr:street":"Main St",
    "iso:country":"AU",
    "sg:address":"155 Main St",
    "sg:city":"Osborne Park",
    "sg:classifiers":[
        {
            "category":"Insurance",
            "subcategory":"Insurance Agent",
            "type":"Services"
        }
    ],
    "sg:phone":"+61 8 9202 2100",
    "sg:postcode":"6017",
    "sg:province":"WA",
    "sg:tags":[
        "broker"
    ],
    "wof:name":"Unity Insurance Brokers",
    "wof:placetype":"venue"
},
  "geometry": {"coordinates":[115.828086853,-31.9008636475],"type":"Point"}
}