{
  "type": "Feature",
  "properties": {
    "addr:full":"869 Nepean Hwy Mornington VIC 3931",
    "addr:housenumber":"869",
    "addr:postcode":"3931",
    "addr:street":"Nepean Hwy",
    "iso:country":"AU",
    "sg:address":"869 Nepean Hwy",
    "sg:city":"Mornington",
    "sg:classifiers":[
        {
            "category":"Health Services",
            "subcategory":"Health Practitioner",
            "type":"Services"
        }
    ],
    "sg:phone":"+61 3 5975 0299",
    "sg:postcode":"3931",
    "sg:province":"VIC",
    "sg:tags":[
        "herbalist"
    ],
    "wof:name":"Beleura Natural Therapies",
    "wof:placetype":"venue"
},
  "geometry": {"coordinates":[145.04356384299999,-38.2301940918],"type":"Point"}
}