{
  "type": "Feature",
  "properties": {
    "addr:full":"13- 17 Caldwell St Garbutt QLD 4814",
    "addr:housenumber":"17",
    "addr:postcode":"4814",
    "addr:street":"Caldwell St",
    "iso:country":"AU",
    "sg:address":"13- 17 Caldwell St",
    "sg:city":"Garbutt",
    "sg:classifiers":[
        {
            "category":"Professional",
            "type":"Services"
        }
    ],
    "sg:phone":"+61 7 4779 5800",
    "sg:postcode":"4814",
    "sg:province":"QLD",
    "sg:tags":[
        "transport"
    ],
    "wof:name":"Mac's Freightline",
    "wof:placetype":"venue"
},
  "geometry": {"coordinates":[146.76461800000001,-19.266979],"type":"Point"}
}