{
  "type": "Feature",
  "properties": {
    "addr:full":"57 Eton Ave Boondall QLD 4034",
    "addr:housenumber":"57",
    "addr:postcode":"4034",
    "addr:street":"Eton Ave",
    "iso:country":"AU",
    "sg:address":"57 Eton Ave",
    "sg:city":"Boondall",
    "sg:classifiers":[
        {
            "category":"Professional",
            "subcategory":"Art Services",
            "type":"Services"
        }
    ],
    "sg:phone":"+61 7 3865 2604",
    "sg:postcode":"4034",
    "sg:province":"QLD",
    "sg:tags":[
        "graphic",
        "designer"
    ],
    "wof:name":"Bodal Communications & Design",
    "wof:placetype":"venue"
},
  "geometry": {"coordinates":[153.07101399999999,-27.351423],"type":"Point"}
}