{
  "type": "Feature",
  "properties": {
    "addr:full":"5/ 351 King St Newtown NSW 2042",
    "addr:housenumber":"/ 351",
    "addr:postcode":"2042",
    "addr:street":"King St",
    "iso:country":"AU",
    "sg:address":"5/ 351 King St",
    "sg:city":"Newtown",
    "sg:classifiers":[
        {
            "category":"Health Services",
            "subcategory":"Health Practitioner",
            "type":"Services"
        }
    ],
    "sg:phone":"+61 2 9550 1094",
    "sg:postcode":"2042",
    "sg:province":"NSW",
    "sg:tags":[
        "acupuncture"
    ],
    "wof:name":"Register Of Acupuncture & Traditional Chinese Medicine Inc",
    "wof:placetype":"venue"
},
  "geometry": {"coordinates":[151.17806999999999,-33.898331],"type":"Point"}
}