{
  "type": "Feature",
  "properties": {
    "addr:full":"Unit 3/ 42 Newton Rd Wetherill Park NSW 2164",
    "addr:housenumber":"42",
    "addr:postcode":"2164",
    "addr:street":"Newton Rd",
    "iso:country":"AU",
    "sg:address":"Unit 3/ 42 Newton Rd",
    "sg:city":"Wetherill Park",
    "sg:classifiers":[
        {
            "category":"Utilities",
            "subcategory":"Recycling",
            "type":"Services"
        }
    ],
    "sg:phone":"+61 2 9756 5115",
    "sg:postcode":"2164",
    "sg:province":"NSW",
    "wof:name":"Ecogyp Pty Ltd",
    "wof:placetype":"venue"
},
  "geometry": {"coordinates":[150.893478394,-33.8412208557],"type":"Point"}
}