{
  "type": "Feature",
  "properties": {
    "iso:country":"AU",
    "sg:address":"Main Rd",
    "sg:city":"Monbulk",
    "sg:classifiers":[
        {
            "category":"Education",
            "subcategory":"School",
            "type":"Public Place"
        }
    ],
    "sg:phone":"+61 3 9756 6481",
    "sg:postcode":"3793",
    "sg:province":"VIC",
    "sg:tags":[
        "state",
        "except",
        "nsw"
    ],
    "wof:name":"Monbulk Primary School",
    "wof:placetype":"venue"
},
  "geometry": {"coordinates":[145.410064697,-37.8768997192],"type":"Point"}
}