{
  "type": "Feature",
  "properties": {
    "iso:country":"AU",
    "sg:address":"11 Traylen Rd",
    "sg:city":"Kalamunda",
    "sg:classifiers":[
        {
            "category":"Professional",
            "subcategory":"Accounting & Tax Preparation",
            "type":"Services"
        }
    ],
    "sg:phone":"+61 8 9257 2444",
    "sg:postcode":"6076",
    "sg:province":"WA",
    "sg:tags":[
        "accountant",
        "auditor"
    ],
    "wof:name":"Bysterveld A L W",
    "wof:placetype":"venue"
},
  "geometry": {"coordinates":[116.050880432,-31.9729003906],"type":"Point"}
}