{
  "type": "Feature",
  "properties": {
    "addr:full":"478 Argyle St Moss Vale NSW 2577",
    "addr:housenumber":"478",
    "addr:postcode":"2577",
    "addr:street":"Argyle St",
    "iso:country":"AU",
    "sg:address":"478 Argyle St",
    "sg:city":"Moss Vale",
    "sg:classifiers":[
        {
            "category":"Banks & Credit Unions",
            "subcategory":"Financial Services",
            "type":"Services"
        }
    ],
    "sg:phone":"+61 2 4869 1825",
    "sg:postcode":"2577",
    "sg:province":"NSW",
    "sg:tags":[
        "annuity",
        "rollover",
        "superannuation",
        "consultant"
    ],
    "wof:name":"Dartnall Advisers",
    "wof:placetype":"venue"
},
  "geometry": {"coordinates":[150.371185303,-34.5501174927],"type":"Point"}
}