{
  "type": "Feature",
  "properties": {
    "iso:country":"AU",
    "sg:address":"Cnr. Armstrong St. (South) & Eyre St.",
    "sg:city":"Ballarat",
    "sg:classifiers":[
        {
            "category":"Shopping",
            "type":"Retail Goods"
        }
    ],
    "sg:phone":"+61 3 5337 4400",
    "sg:postcode":"3350",
    "sg:province":"VIC",
    "sg:tags":[
        "equipment",
        "safety",
        "accessory"
    ],
    "wof:name":"Camerons Plumbing & Hardware",
    "wof:placetype":"venue"
},
  "geometry": {"coordinates":[143.852432,-37.570969],"type":"Point"}
}