{
  "type": "Feature",
  "properties": {
    "addr:full":"76 Brandon Park Drv Mulgrave VIC 3170",
    "addr:housenumber":"76",
    "addr:postcode":"3170",
    "addr:street":"Brandon Park Drv",
    "iso:country":"AU",
    "sg:address":"76 Brandon Park Drv",
    "sg:city":"Mulgrave",
    "sg:classifiers":[
        {
            "category":"Shopping",
            "subcategory":"Stationery & Office Supplies",
            "type":"Retail Goods"
        }
    ],
    "sg:phone":"+61 3 9561 8832",
    "sg:postcode":"3170",
    "sg:province":"VIC",
    "sg:tags":[
        "partition"
    ],
    "wof:name":"National Office Partitioning Pty Ltd",
    "wof:placetype":"venue"
},
  "geometry": {"coordinates":[145.165527344,-37.9114608765],"type":"Point"}
}