{
  "type": "Feature",
  "properties": {
    "iso:country":"AU",
    "sg:address":"Unit 11 8 Edward St",
    "sg:city":"Eaton",
    "sg:classifiers":[
        {
            "category":"Professional",
            "subcategory":"Accounting & Tax Preparation",
            "type":"Services"
        }
    ],
    "sg:phone":"+61 8 9791 2624",
    "sg:postcode":"6232",
    "sg:province":"WA",
    "sg:tags":[
        "consultant",
        "taxation"
    ],
    "wof:name":"Innis J. D. & Associates",
    "wof:placetype":"venue"
},
  "geometry": {"coordinates":[115.713303,-33.318245],"type":"Point"}
}