{
  "type": "Feature",
  "properties": {
    "iso:country":"AU",
    "sg:address":"5 Littler St",
    "sg:city":"Sunnybank",
    "sg:classifiers":[
        {
            "category":"Utilities",
            "subcategory":"Electric",
            "type":"Services"
        }
    ],
    "sg:phone":"+61 7 3345 3535",
    "sg:postcode":"4109",
    "sg:province":"QLD",
    "sg:tags":[
        "electrical",
        "contractor"
    ],
    "wof:name":"Bert Willems Electrical Contractors Pty Ltd",
    "wof:placetype":"venue"
},
  "geometry": {"coordinates":[153.067962647,-27.5805206299],"type":"Point"}
}