{
  "type": "Feature",
  "properties": {
    "addr:full":"91 Prospect Rd Prospect SA 5082",
    "addr:housenumber":"91",
    "addr:postcode":"5082",
    "addr:street":"Prospect Rd",
    "iso:country":"AU",
    "sg:address":"91 Prospect Rd",
    "sg:city":"Prospect",
    "sg:classifiers":[
        {
            "category":"Recreation",
            "type":"Entertainment"
        }
    ],
    "sg:phone":"+61 8 8344 2722",
    "sg:postcode":"5082",
    "sg:province":"SA",
    "sg:tags":[
        "children's",
        "play",
        "programme"
    ],
    "wof:name":"Playgroup SA Inc",
    "wof:placetype":"venue"
},
  "geometry": {"coordinates":[138.594192505,-34.8874702454],"type":"Point"}
}