{
  "type": "Feature",
  "properties": {
    "addr:full":"24 Second St Katherine NT 0850",
    "addr:housenumber":"24",
    "addr:postcode":"nt 0850",
    "addr:street":"Second St",
    "iso:country":"AU",
    "sg:address":"24 Second St",
    "sg:city":"Katherine",
    "sg:classifiers":[
        {
            "category":"Autos & Motor Vehicles",
            "subcategory":"Automobile Sales",
            "type":"Retail Goods"
        }
    ],
    "sg:phone":"+61 8 8971 0566",
    "sg:postcode":"0850",
    "sg:province":"NT",
    "sg:tags":[
        "car",
        "used"
    ],
    "wof:name":"Katherine Kars",
    "wof:placetype":"venue"
},
  "geometry": {"coordinates":[132.263992,-14.462426],"type":"Point"}
}