{
  "type": "Feature",
  "properties": {
    "addr:full":"Shop4/ 428 Prospect Rd Kilburn SA 5084",
    "addr:housenumber":"428",
    "addr:postcode":"5084",
    "addr:street":"Prospect Rd",
    "iso:country":"AU",
    "sg:address":"Shop4/ 428 Prospect Rd",
    "sg:city":"Kilburn",
    "sg:classifiers":[
        {
            "category":"Food & Beverages",
            "subcategory":"Bakery",
            "type":"Retail Goods"
        }
    ],
    "sg:phone":"+61 8 8349 8842",
    "sg:postcode":"5084",
    "sg:province":"SA",
    "sg:tags":[
        "baker"
    ],
    "wof:name":"Tasty Bread",
    "wof:placetype":"venue"
},
  "geometry": {"coordinates":[138.59205627399999,-34.8557014465],"type":"Point"}
}