{
  "type": "Feature",
  "properties": {
    "iso:country":"AU",
    "sg:address":"33 Barbigal St",
    "sg:city":"Stafford Heights",
    "sg:classifiers":[
        {
            "category":"Building & Trades",
            "subcategory":"Landscaping Services",
            "type":"Services"
        }
    ],
    "sg:phone":"+61 417 140 773",
    "sg:postcode":"4053",
    "sg:province":"QLD",
    "sg:tags":[
        "architect",
        "landscape"
    ],
    "wof:name":"J W Concepts",
    "wof:placetype":"venue"
},
  "geometry": {"coordinates":[153.01269531200001,-27.4029140472],"type":"Point"}
}