{
  "type": "Feature",
  "properties": {
    "addr:full":"15 Lothian St North Melbourne VIC 3051",
    "addr:housenumber":"15",
    "addr:postcode":"3051",
    "addr:street":"Lothian St",
    "iso:country":"AU",
    "sg:address":"15 Lothian St",
    "sg:city":"North Melbourne",
    "sg:classifiers":[
        {
            "category":"Autos & Motor Vehicles",
            "subcategory":"Auto Supplies",
            "type":"Retail Goods"
        }
    ],
    "sg:phone":"+61 3 9329 6966",
    "sg:postcode":"3051",
    "sg:province":"VIC",
    "sg:tags":[
        "battery",
        "automotive"
    ],
    "wof:name":"Beaurepaires",
    "wof:placetype":"venue"
},
  "geometry": {"coordinates":[144.94453430199999,-37.8036308289],"type":"Point"}
}