{
  "type": "Feature",
  "properties": {
    "addr:full":"46 Thomas Drv Chevron Island QLD 4217",
    "addr:housenumber":"46",
    "addr:postcode":"4217",
    "addr:street":"Thomas Drv Chevron",
    "iso:country":"AU",
    "sg:address":"46 Thomas Drv",
    "sg:city":"Chevron Island",
    "sg:classifiers":[
        {
            "category":"Food & Beverages",
            "subcategory":"Supermarket",
            "type":"Retail Goods"
        }
    ],
    "sg:phone":"+61 7 5570 2267",
    "sg:postcode":"4217",
    "sg:province":"QLD",
    "sg:tags":[
        "grocery",
        "store"
    ],
    "wof:name":"Chevron Island 7-Day Express Food Store",
    "wof:placetype":"venue"
},
  "geometry": {"coordinates":[153.41961669899999,-27.998167038],"type":"Point"}
}