{
  "type": "Feature",
  "properties": {
    "iso:country":"AU",
    "sg:address":"87 Brighton Pde",
    "sg:city":"Southport",
    "sg:classifiers":[
        {
            "category":"Retail",
            "subcategory":"Car Wash",
            "type":"Services"
        }
    ],
    "sg:phone":"+61 7 5527 1155",
    "sg:postcode":"4215",
    "sg:province":"QLD",
    "sg:tags":[
        "truck",
        "cleaning"
    ],
    "wof:name":"Auto Affair Car Wash & Coffee",
    "wof:placetype":"venue"
},
  "geometry": {"coordinates":[153.40586852999999,-27.9363689423],"type":"Point"}
}