{
  "type": "Feature",
  "properties": {
    "iso:country":"AU",
    "sg:address":"72 Grahams Rd",
    "sg:city":"Mt Rumney",
    "sg:classifiers":[
        {
            "category":"Real Estate",
            "subcategory":"Surveying",
            "type":"Services"
        }
    ],
    "sg:phone":"+61 3 6248 5224",
    "sg:postcode":"7170",
    "sg:province":"TAS",
    "sg:tags":[
        "surveyor",
        "land"
    ],
    "wof:name":"Woolford T N",
    "wof:placetype":"venue"
},
  "geometry": {"coordinates":[147.428665161,-42.852809906],"type":"Point"}
}