{
  "type": "Feature",
  "properties": {
    "addr:full":"82 Main South Rd Reynella SA 5161",
    "addr:housenumber":"82",
    "addr:postcode":"5161",
    "addr:street":"Main South Rd",
    "iso:country":"AU",
    "sg:address":"82 Main South Rd",
    "sg:city":"Reynella",
    "sg:classifiers":[
        {
            "category":"Autos & Motor Vehicles",
            "subcategory":"Automobile Sales",
            "type":"Retail Goods"
        }
    ],
    "sg:phone":"+61 8 8381 8022",
    "sg:postcode":"5161",
    "sg:province":"SA",
    "sg:tags":[
        "car",
        "used"
    ],
    "wof:name":"Reynella 4WD & Commercial Sales",
    "wof:placetype":"venue"
},
  "geometry": {"coordinates":[138.532302856,-35.0995140076],"type":"Point"}
}