{
  "type": "Feature",
  "properties": {
    "addr:full":"1 Kiln Rd Byford WA 6122",
    "addr:housenumber":"1",
    "addr:postcode":"6122",
    "addr:street":"Kiln Rd",
    "iso:country":"AU",
    "sg:address":"1 Kiln Rd",
    "sg:city":"Byford",
    "sg:classifiers":[
        {
            "category":"Social Services",
            "subcategory":"Child Care",
            "type":"Services"
        }
    ],
    "sg:phone":"+61 8 9526 2394",
    "sg:postcode":"6122",
    "sg:province":"WA",
    "sg:tags":[
        "breeding",
        "artificial"
    ],
    "wof:name":"AI Services",
    "wof:placetype":"venue"
},
  "geometry": {"coordinates":[116.020217895,-32.2486534119],"type":"Point"}
}