{
  "type": "Feature",
  "properties": {
    "addr:full":"56 Maroondah Hwy Ringwood VIC 3134",
    "addr:housenumber":"56",
    "addr:postcode":"3134",
    "addr:street":"Maroondah Hwy",
    "iso:country":"AU",
    "sg:address":"56 Maroondah Hwy",
    "sg:city":"Ringwood",
    "sg:classifiers":[
        {
            "category":"Building & Trades",
            "subcategory":"Construction",
            "type":"Services"
        }
    ],
    "sg:phone":"+61 3 9879 6422",
    "sg:postcode":"3134",
    "sg:province":"VIC",
    "sg:tags":[
        "pool",
        "swimming"
    ],
    "wof:name":"Signature Spas Retail Ringwood",
    "wof:placetype":"venue"
},
  "geometry": {"coordinates":[145.221435547,-37.817276001],"type":"Point"}
}