{
  "type": "Feature",
  "properties": {
    "iso:country":"AU",
    "sg:address":"9 Darling St",
    "sg:city":"North Bourke",
    "sg:classifiers":[
        {
            "category":"Social Services",
            "subcategory":"Child Care",
            "type":"Services"
        }
    ],
    "sg:phone":"+61 2 6872 2904",
    "sg:postcode":"2540",
    "sg:province":"NSW",
    "sg:tags":[
        "shearer"
    ],
    "wof:name":"Tiffen K E",
    "wof:placetype":"venue"
},
  "geometry": {"coordinates":[150.58207702600001,-35.0087890625],"type":"Point"}
}