{
  "type": "Feature",
  "properties": {
    "addr:full":"River Rd Forbes NSW 2871",
    "addr:postcode":"2871",
    "addr:street":"River Rd",
    "iso:country":"AU",
    "sg:address":"River Rd",
    "sg:city":"Forbes",
    "sg:classifiers":[
        {
            "category":"Building & Trades",
            "subcategory":"Construction",
            "type":"Services"
        }
    ],
    "sg:phone":"+61 2 6852 3056",
    "sg:postcode":"2871",
    "sg:province":"NSW",
    "sg:tags":[
        "earth",
        "excavating",
        "moving",
        "contractor"
    ],
    "wof:name":"Forbes Bobcat Service",
    "wof:placetype":"venue"
},
  "geometry": {"coordinates":[147.993515,-33.396294],"type":"Point"}
}