{
  "type": "Feature",
  "properties": {
    "addr:full":"Factory 10/ 34 Stephen Rd Dandenong South VIC 3175",
    "addr:housenumber":"10 / 34",
    "addr:postcode":"3175",
    "addr:street":"Stephen Rd",
    "iso:country":"AU",
    "sg:address":"Factory 10/ 34 Stephen Rd",
    "sg:city":"Dandenong South",
    "sg:classifiers":[
        {
            "category":"Wholesale",
            "subcategory":"Machinery & Supplies",
            "type":"Manufacturing & Wholesale Goods"
        }
    ],
    "sg:phone":"+61 3 9792 3188",
    "sg:postcode":"3175",
    "sg:province":"VIC",
    "sg:tags":[
        "bearing",
        "bushing"
    ],
    "sg:website":"http://www.bearinglogistics.com.au",
    "wof:name":"Bearing Logistics Pty Ltd",
    "wof:placetype":"venue"
},
  "geometry": {"coordinates":[145.212722778,-38.0085067749],"type":"Point"}
}