{
  "type": "Feature",
  "properties": {
    "addr:full":"310 Peel St Tamworth NSW 2340",
    "addr:housenumber":"310",
    "addr:postcode":"2340",
    "addr:street":"Peel St",
    "iso:country":"AU",
    "sg:address":"310 Peel St",
    "sg:city":"Tamworth",
    "sg:classifiers":[
        {
            "category":"Shopping",
            "subcategory":"Crafts & Fabrics",
            "type":"Retail Goods"
        }
    ],
    "sg:phone":"+61 2 6766 6304",
    "sg:postcode":"2340",
    "sg:province":"NSW",
    "sg:tags":[
        "wool",
        "knitting",
        "accessory"
    ],
    "wof:name":"Handy Hands",
    "wof:placetype":"venue"
},
  "geometry": {"coordinates":[150.928924561,-31.0893783569],"type":"Point"}
}