{
  "type": "Feature",
  "properties": {
    "iso:country":"AU",
    "sg:address":"Suite 3, 53 East Esp",
    "sg:city":"Manly",
    "sg:classifiers":[
        {
            "category":"Health Services",
            "subcategory":"Dentist",
            "type":"Services"
        }
    ],
    "sg:phone":"+61 2 9977 1908",
    "sg:postcode":"2095",
    "sg:province":"NSW",
    "wof:name":"Heyworth Peter, Donegan Michelle, Sacco Amy & Associates",
    "wof:placetype":"venue"
},
  "geometry": {"coordinates":[151.28465270999999,-33.799156189],"type":"Point"}
}