{
  "type": "Feature",
  "properties": {
    "addr:full":"Shop 5 The Plaza Cnr Beacon & Main Western Rds North Tamborine QLD 4272",
    "addr:housenumber":"shop 5",
    "addr:postcode":"4272",
    "addr:street":"The;Cnr;Western",
    "iso:country":"AU",
    "sg:address":"Shop 5 The Plaza Cnr Beacon & Main Western Rds",
    "sg:city":"North Tamborine",
    "sg:classifiers":[
        {
            "category":"Fast Food",
            "type":"Food & Drink"
        }
    ],
    "sg:phone":"+61 7 5545 1077",
    "sg:postcode":"4272",
    "sg:province":"QLD",
    "sg:tags":[
        "away",
        "take"
    ],
    "wof:name":"Tamborine Takeaway",
    "wof:placetype":"venue"
},
  "geometry": {"coordinates":[153.18304443400001,-27.9280643463],"type":"Point"}
}