{
  "type": "Feature",
  "properties": {
    "iso:country":"AU",
    "sg:address":"Cnr Tank & Auckland Sts",
    "sg:city":"Gladstone",
    "sg:classifiers":[
        {
            "category":"Communications",
            "type":"Services"
        }
    ],
    "sg:phone":"+61 7 4972 6660",
    "sg:postcode":"4680",
    "sg:province":"QLD",
    "sg:tags":[
        "equipment",
        "radio"
    ],
    "wof:name":"Gladstone Hi-Fi",
    "wof:placetype":"venue"
},
  "geometry": {"coordinates":[151.257568359,-23.8499412537],"type":"Point"}
}