{
  "type": "Feature",
  "properties": {
    "addr:full":"7 Greenwood St Burwood VIC 3125",
    "addr:housenumber":"7",
    "addr:postcode":"3125",
    "addr:street":"Greenwood St",
    "iso:country":"AU",
    "sg:address":"7 Greenwood St",
    "sg:city":"Burwood",
    "sg:classifiers":[
        {
            "category":"Health Services",
            "subcategory":"Health Practitioner",
            "type":"Services"
        }
    ],
    "sg:phone":"+61 431 335 559",
    "sg:postcode":"3125",
    "sg:province":"VIC",
    "sg:tags":[
        "naturopath"
    ],
    "wof:name":"Arnold La",
    "wof:placetype":"venue"
},
  "geometry": {"coordinates":[145.129150391,-37.8508758545],"type":"Point"}
}