{
  "type": "Feature",
  "properties": {
    "addr:full":"1012 Barrenjoey Rd Palm Beach NSW 2108",
    "addr:housenumber":"1012",
    "addr:postcode":"2108",
    "addr:street":"Barrenjoey Rd",
    "iso:country":"AU",
    "sg:address":"1012 Barrenjoey Rd",
    "sg:city":"Palm Beach",
    "sg:classifiers":[
        {
            "category":"Real Estate",
            "subcategory":"Architect",
            "type":"Services"
        }
    ],
    "sg:phone":"+61 2 9974 5639",
    "sg:postcode":"2108",
    "sg:province":"NSW",
    "wof:name":"Bruce James & Partners Pty Ltd",
    "wof:placetype":"venue"
},
  "geometry": {"coordinates":[151.32015991200001,-33.5974807739],"type":"Point"}
}