{
  "type": "Feature",
  "properties": {
    "addr:full":"1/ 1645 Ipswich Rd Rocklea QLD 4106",
    "addr:housenumber":"/ 1645",
    "addr:postcode":"4106",
    "addr:street":"Ipswich Rd",
    "iso:country":"AU",
    "sg:address":"1/ 1645 Ipswich Rd",
    "sg:city":"Rocklea",
    "sg:classifiers":[
        {
            "category":"Professional",
            "subcategory":"Printing & Photocopies",
            "type":"Services"
        }
    ],
    "sg:phone":"+61 7 3277 4499",
    "sg:postcode":"4106",
    "sg:province":"QLD",
    "sg:tags":[
        "photocopying"
    ],
    "wof:name":"Snap Printing",
    "wof:placetype":"venue"
},
  "geometry": {"coordinates":[153.00718689000001,-27.5559310913],"type":"Point"}
}