{
  "type": "Feature",
  "properties": {
    "addr:full":"19 Barklya Pl Marsden QLD 4132",
    "addr:housenumber":"19",
    "addr:postcode":"4132",
    "addr:street":"Barklya Pl",
    "iso:country":"AU",
    "sg:address":"19 Barklya Pl",
    "sg:city":"Marsden",
    "sg:classifiers":[
        {
            "category":"Personal",
            "subcategory":"Adult",
            "type":"Services"
        }
    ],
    "sg:phone":"+61 7 3805 7888",
    "sg:postcode":"4132",
    "sg:province":"QLD",
    "sg:tags":[
        "product"
    ],
    "wof:name":"Adult Rush",
    "wof:placetype":"venue"
},
  "geometry": {"coordinates":[153.11402893100001,-27.6802406311],"type":"Point"}
}