{
  "type": "Feature",
  "properties": {
    "addr:full":"412 Alternate Calder Hwy Lockwood South VIC 3551",
    "addr:housenumber":"412",
    "addr:postcode":"3551",
    "addr:street":"Alternate Calder Hwy",
    "iso:country":"AU",
    "sg:address":"412 Alternate Calder Hwy",
    "sg:city":"Lockwood South",
    "sg:classifiers":[
        {
            "category":"Retail",
            "subcategory":"Auto Repair",
            "type":"Services"
        }
    ],
    "sg:phone":"+61 3 5435 3665",
    "sg:postcode":"3551",
    "sg:province":"VIC",
    "sg:tags":[
        "testing",
        "inspection",
        "motor",
        "vehicle"
    ],
    "wof:name":"P J Organ Motor Repairs",
    "wof:placetype":"venue"
},
  "geometry": {"coordinates":[144.21989440900001,-36.8996963501],"type":"Point"}
}