{
  "type": "Feature",
  "properties": {
    "addr:full":"348 Edward St Wagga Wagga NSW 2650",
    "addr:housenumber":"348",
    "addr:postcode":"2650",
    "addr:street":"Edward St",
    "iso:country":"AU",
    "sg:address":"348 Edward St",
    "sg:city":"Wagga Wagga",
    "sg:classifiers":[
        {
            "category":"Home & Garden",
            "subcategory":"Hardware",
            "type":"Retail Goods"
        }
    ],
    "sg:phone":"+61 2 6925 1418",
    "sg:postcode":"2650",
    "sg:province":"NSW",
    "sg:tags":[
        "generating",
        "set",
        "generator"
    ],
    "wof:name":"B & A Motors",
    "wof:placetype":"venue"
},
  "geometry": {"coordinates":[147.346725464,-35.1158447266],"type":"Point"}
}