{
  "type": "Feature",
  "properties": {
    "addr:full":"3 Kiln St Malaga WA 6090",
    "addr:housenumber":"3",
    "addr:postcode":"6090",
    "addr:street":"Kiln St",
    "iso:country":"AU",
    "sg:address":"3 Kiln St",
    "sg:city":"Malaga",
    "sg:classifiers":[
        {
            "category":"Home & Garden",
            "subcategory":"Garden Supply",
            "type":"Retail Goods"
        }
    ],
    "sg:phone":"+61 8 9249 4244",
    "sg:postcode":"6090",
    "sg:province":"WA",
    "sg:tags":[
        "nursery"
    ],
    "wof:name":"Brunnings Gardening Products W A",
    "wof:placetype":"venue"
},
  "geometry": {"coordinates":[115.891876221,-31.8477153778],"type":"Point"}
}