{
  "type": "Feature",
  "properties": {
    "addr:full":"163 Heagney Crs Chisholm ACT 2905",
    "addr:housenumber":"163",
    "addr:postcode":"2905",
    "addr:street":"Heagney Crs",
    "iso:country":"AU",
    "sg:address":"163 Heagney Crs",
    "sg:city":"Chisholm",
    "sg:classifiers":[
        {
            "category":"Utilities",
            "type":"Services"
        }
    ],
    "sg:phone":"+61 417 421 410",
    "sg:postcode":"2905",
    "sg:province":"ACT",
    "sg:tags":[
        "refrigeration",
        "industrial",
        "commercial",
        "retail"
    ],
    "wof:name":"W & L A Howden Commercial Refrigeration",
    "wof:placetype":"venue"
},
  "geometry": {"coordinates":[149.124176025,-35.4190483093],"type":"Point"}
}