{
  "type": "Feature",
  "properties": {
    "iso:country":"AU",
    "sg:address":"71 Ian Rd",
    "sg:city":"Mt Martha",
    "sg:classifiers":[
        {
            "category":"Building & Trades",
            "subcategory":"Construction",
            "type":"Services"
        }
    ],
    "sg:phone":"+61 3 5988 4070",
    "sg:postcode":"3934",
    "sg:province":"VIC",
    "sg:tags":[
        "fencing",
        "contractor"
    ],
    "wof:name":"Martha Point Fencing",
    "wof:placetype":"venue"
},
  "geometry": {"coordinates":[144.99391174300001,-38.2971229553],"type":"Point"}
}