{
  "type": "Feature",
  "properties": {
    "addr:full":"31 Sycamore St Hoppers Crossing VIC 3029",
    "addr:housenumber":"31",
    "addr:postcode":"3029",
    "addr:street":"Sycamore St",
    "iso:country":"AU",
    "sg:address":"31 Sycamore St",
    "sg:city":"Hoppers Crossing",
    "sg:classifiers":[
        {
            "category":"Education",
            "subcategory":"School",
            "type":"Public Place"
        }
    ],
    "sg:phone":"+61 3 9748 8688",
    "sg:postcode":"3029",
    "sg:province":"VIC",
    "sg:tags":[
        "state",
        "except",
        "nsw"
    ],
    "wof:name":"Derrimut Heath Primary",
    "wof:placetype":"venue"
},
  "geometry": {"coordinates":[144.69137599999999,-37.859959],"type":"Point"}
}