{
  "type": "Feature",
  "properties": {
    "iso:country":"AU",
    "sg:address":"230 Balwyn Rd",
    "sg:city":"Balwyn North",
    "sg:classifiers":[
        {
            "category":"Sports & Exercise",
            "subcategory":"Gym",
            "type":"Entertainment"
        }
    ],
    "sg:phone":"+61 3 9857 8031",
    "sg:postcode":"3104",
    "sg:province":"VIC",
    "sg:tags":[
        "health",
        "fitness"
    ],
    "wof:name":"Balwyn Leisure Centre",
    "wof:placetype":"venue"
},
  "geometry": {"coordinates":[145.08636474599999,-37.7878112793],"type":"Point"}
}