{
  "type": "Feature",
  "properties": {
    "addr:full":"Nelson Rd Darlington WA 6070",
    "addr:postcode":"6070",
    "addr:street":"Nelson Rd",
    "iso:country":"AU",
    "sg:address":"Nelson Rd",
    "sg:city":"Darlington",
    "sg:classifiers":[
        {
            "category":"Farming",
            "subcategory":"Vineyard",
            "type":"Manufacturing & Wholesale Goods"
        }
    ],
    "sg:phone":"+61 8 9299 6268",
    "sg:postcode":"6070",
    "sg:province":"WA",
    "sg:tags":[
        "winery"
    ],
    "wof:name":"Darlington Estate Wines",
    "wof:placetype":"venue"
},
  "geometry": {"coordinates":[116.092590332,-31.9215717316],"type":"Point"}
}