{
  "type": "Feature",
  "properties": {
    "addr:full":"576 Waterworks Rd Ashgrove QLD 4060",
    "addr:housenumber":"576",
    "addr:postcode":"4060",
    "addr:street":"Waterworks Rd",
    "iso:country":"AU",
    "sg:address":"576 Waterworks Rd",
    "sg:city":"Ashgrove",
    "sg:classifiers":[
        {
            "category":"Fast Food",
            "type":"Food & Drink"
        }
    ],
    "sg:phone":"+61 7 3366 6330",
    "sg:postcode":"4060",
    "sg:province":"QLD",
    "sg:tags":[
        "away",
        "take"
    ],
    "wof:name":"Seven Heaven Take Away",
    "wof:placetype":"venue"
},
  "geometry": {"coordinates":[152.974334717,-27.448217392],"type":"Point"}
}