{
  "type": "Feature",
  "properties": {
    "addr:full":"222 The Entrance Rd Erina NSW 2250",
    "addr:housenumber":"222",
    "addr:postcode":"2250",
    "addr:street":"The Entrance Rd",
    "iso:country":"AU",
    "sg:address":"222 The Entrance Rd",
    "sg:city":"Erina",
    "sg:classifiers":[
        {
            "category":"Fast Food",
            "type":"Food & Drink"
        }
    ],
    "sg:phone":"+61 2 4365 1988",
    "sg:postcode":"2250",
    "sg:province":"NSW",
    "sg:tags":[
        "away",
        "take"
    ],
    "wof:name":"Caesars Coffee and Fine Food",
    "wof:placetype":"venue"
},
  "geometry": {"coordinates":[151.390914917,-33.4331970215],"type":"Point"}
}