{
  "type": "Feature",
  "properties": {
    "addr:full":"24 Verene Ave Templestowe Lower VIC 3107",
    "addr:housenumber":"24",
    "addr:postcode":"3107",
    "addr:street":"Verene Ave",
    "iso:country":"AU",
    "sg:address":"24 Verene Ave",
    "sg:city":"Templestowe Lower",
    "sg:classifiers":[
        {
            "category":"Professional",
            "subcategory":"Employment Agencies",
            "type":"Services"
        }
    ],
    "sg:phone":"+61 3 9850 7407",
    "sg:postcode":"3107",
    "sg:province":"VIC",
    "sg:tags":[
        "consultant",
        "corrosion"
    ],
    "wof:name":"CTI Consultants Pty Ltd",
    "wof:placetype":"venue"
},
  "geometry": {"coordinates":[145.11561584500001,-37.7675857544],"type":"Point"}
}