{
  "type": "Feature",
  "properties": {
    "addr:full":"44 Bleigh St Muswellbrook NSW 2333",
    "addr:housenumber":"44",
    "addr:postcode":"2333",
    "addr:street":"Bleigh St",
    "iso:country":"AU",
    "sg:address":"44 Bleigh St",
    "sg:city":"Muswellbrook",
    "sg:classifiers":[
        {
            "category":"Government",
            "subcategory":"Court House",
            "type":"Public Place"
        }
    ],
    "sg:phone":"+61 2 6541 1103",
    "sg:postcode":"2333",
    "sg:province":"NSW",
    "sg:tags":[
        "personal",
        "marriage",
        "family",
        "counselling"
    ],
    "wof:name":"Transformation Training Clinic",
    "wof:placetype":"venue"
},
  "geometry": {"coordinates":[150.894073486,-32.2568778992],"type":"Point"}
}