{
  "type": "Feature",
  "properties": {
    "addr:full":"175 Pitt Town Rd McGraths Hill NSW 2756",
    "addr:housenumber":"175",
    "addr:postcode":"2756",
    "addr:street":"Pitt Town Rd",
    "iso:country":"AU",
    "sg:address":"175 Pitt Town Rd",
    "sg:city":"McGraths Hill",
    "sg:classifiers":[
        {
            "category":"Farming",
            "subcategory":"Livestock Farm",
            "type":"Manufacturing & Wholesale Goods"
        }
    ],
    "sg:phone":"+61 2 4572 3433",
    "sg:postcode":"2756",
    "sg:province":"NSW",
    "sg:tags":[
        "agistment"
    ],
    "wof:name":"Windsor Stables The",
    "wof:placetype":"venue"
},
  "geometry": {"coordinates":[150.852783203,-33.6075553894],"type":"Point"}
}