{
  "type": "Feature",
  "properties": {
    "addr:full":"U27/ 35 -39 South Perth Esp South Perth WA 6151",
    "addr:housenumber":"-39",
    "addr:postcode":"6151",
    "addr:street":"/ 35",
    "iso:country":"AU",
    "sg:address":"U27/ 35",
    "sg:city":"-39 South Perth Esp South Perth",
    "sg:classifiers":[
        {
            "category":"Real Estate",
            "subcategory":"Real Estate Agent",
            "type":"Services"
        }
    ],
    "sg:phone":"+61 413 606 999",
    "sg:postcode":"6151",
    "sg:province":"WA",
    "wof:name":"Tompkin Ron W",
    "wof:placetype":"venue"
},
  "geometry": {"coordinates":[115.85050200000001,-31.969044],"type":"Point"}
}