{
  "type": "Feature",
  "properties": {
    "iso:country":"AU",
    "sg:address":"5/ 110 Gleadow St",
    "sg:city":"Inveresk",
    "sg:classifiers":[
        {
            "category":"Farming",
            "subcategory":"Farm & Veterinary Services",
            "type":"Manufacturing & Wholesale Goods"
        }
    ],
    "sg:phone":"+61 3 6331 9955",
    "sg:postcode":"7248",
    "sg:province":"TAS",
    "sg:tags":[
        "blacksmith",
        "farrier"
    ],
    "wof:name":"Tasmanian Blacksmith & Engineering",
    "wof:placetype":"venue"
},
  "geometry": {"coordinates":[147.125076294,-41.4286270142],"type":"Point"}
}