{
  "type": "Feature",
  "properties": {
    "addr:full":"Shop 3/ 546-562 King St Newtown NSW 2042",
    "addr:housenumber":"shop 3 / 546-562",
    "addr:postcode":"2042",
    "addr:street":"King St",
    "iso:country":"AU",
    "sg:address":"Shop 3/ 546-562 King St",
    "sg:city":"Newtown",
    "sg:classifiers":[
        {
            "category":"Retail",
            "subcategory":"Laundry & Dry Cleaning",
            "type":"Services"
        }
    ],
    "sg:phone":"+61 2 9517 9765",
    "sg:postcode":"2042",
    "sg:province":"NSW",
    "sg:tags":[
        "manicurist"
    ],
    "wof:name":"Serengeti Hair Nail & Beauty",
    "wof:placetype":"venue"
},
  "geometry": {"coordinates":[151.17993200000001,-33.903397],"type":"Point"}
}