{
  "type": "Feature",
  "properties": {
    "addr:full":"Factory 3-4, 64-74 Carroll Rd Oakleigh South VIC 3167",
    "addr:housenumber":"64-74",
    "addr:postcode":"3167",
    "addr:street":"Carroll Rd",
    "iso:country":"AU",
    "sg:address":"Factory 3-4, 64-74 Carroll Rd",
    "sg:city":"Oakleigh South",
    "sg:classifiers":[
        {
            "category":"Manufacturing",
            "subcategory":"Building Materials",
            "type":"Manufacturing & Wholesale Goods"
        }
    ],
    "sg:phone":"+61 3 9570 8666",
    "sg:postcode":"3167",
    "sg:province":"VIC",
    "sg:tags":[
        "stone",
        "product",
        "supply"
    ],
    "wof:name":"Caesar Stone Quartz Surfaces",
    "wof:placetype":"venue"
},
  "geometry": {"coordinates":[145.09416198700001,-37.9313697815],"type":"Point"}
}