{
  "type": "Feature",
  "properties": {
    "addr:full":"18 Clearview Crt Dakabin QLD 4503",
    "addr:housenumber":"18",
    "addr:postcode":"4503",
    "addr:street":"Clearview Crt",
    "iso:country":"AU",
    "sg:address":"18 Clearview Crt",
    "sg:city":"Dakabin",
    "sg:classifiers":[
        {
            "category":"Building & Trades",
            "subcategory":"Construction",
            "type":"Services"
        }
    ],
    "sg:phone":"+61 411 864 048",
    "sg:postcode":"4503",
    "sg:province":"QLD",
    "sg:tags":[
        "renovation",
        "alterations",
        "extension",
        "contractor"
    ],
    "wof:name":"Lyons Landscapes & Building",
    "wof:placetype":"venue"
},
  "geometry": {"coordinates":[152.98130798299999,-27.2131614685],"type":"Point"}
}