{
  "type": "Feature",
  "properties": {
    "iso:country":"AU",
    "sg:address":"5 River Oaks Drv",
    "sg:city":"Eatons Hill",
    "sg:classifiers":[
        {
            "category":"Building & Trades",
            "subcategory":"Plumbing",
            "type":"Services"
        }
    ],
    "sg:phone":"+61 7 3264 7882",
    "sg:postcode":"4037",
    "sg:province":"QLD",
    "sg:tags":[
        "plumber",
        "gasfitters"
    ],
    "wof:name":"Dale Taylor Plumbing",
    "wof:placetype":"venue"
},
  "geometry": {"coordinates":[152.934982,-27.346693],"type":"Point"}
}