{
  "type": "Feature",
  "properties": {
    "addr:full":"90 Rundle St Kent Town SA 5067",
    "addr:housenumber":"90",
    "addr:postcode":"5067",
    "addr:street":"Rundle St",
    "iso:country":"AU",
    "sg:address":"90 Rundle St",
    "sg:city":"Kent Town",
    "sg:classifiers":[
        {
            "category":"Professional",
            "subcategory":"Engineering",
            "type":"Services"
        }
    ],
    "sg:phone":"+61 8 8271 5259",
    "sg:postcode":"5067",
    "sg:province":"SA",
    "sg:tags":[
        "consulting",
        "engineer"
    ],
    "wof:name":"South Australian Foundation Engineering",
    "wof:placetype":"venue"
},
  "geometry": {"coordinates":[138.61842346200001,-34.9203414917],"type":"Point"}
}