{
  "type": "Feature",
  "properties": {
    "addr:full":"192 Barcom Ave Darlinghurst NSW 2010",
    "addr:housenumber":"192",
    "addr:postcode":"2010",
    "addr:street":"Barcom Ave",
    "iso:country":"AU",
    "sg:address":"192 Barcom Ave",
    "sg:city":"Darlinghurst",
    "sg:classifiers":[
        {
            "category":"Building & Trades",
            "subcategory":"Landscaping Services",
            "type":"Services"
        }
    ],
    "sg:phone":"+61 2 9331 7555",
    "sg:postcode":"2010",
    "sg:province":"NSW",
    "sg:tags":[
        "consultant"
    ],
    "wof:name":"C & C Design Construct P/L",
    "wof:placetype":"venue"
},
  "geometry": {"coordinates":[151.222824097,-33.8797721863],"type":"Point"}
}