{
  "type": "Feature",
  "properties": {
    "iso:country":"AU",
    "sg:address":"303 Adelaide St",
    "sg:city":"Brisbane",
    "sg:classifiers":[
        {
            "category":"Banks & Credit Unions",
            "subcategory":"Financial Services",
            "type":"Services"
        }
    ],
    "sg:phone":"+61 7 3220 2211",
    "sg:postcode":"4000",
    "sg:province":"QLD",
    "sg:tags":[
        "planning"
    ],
    "wof:name":"Optimum Financial Consulting Pty Ltd",
    "wof:placetype":"venue"
},
  "geometry": {"coordinates":[153.02932739299999,-27.4652633667],"type":"Point"}
}