{
  "type": "Feature",
  "properties": {
    "addr:full":"17 Hawkins St Bathurst NSW 2795",
    "addr:housenumber":"17",
    "addr:postcode":"2795",
    "addr:street":"Hawkins St",
    "iso:country":"AU",
    "sg:address":"17 Hawkins St",
    "sg:city":"Bathurst",
    "sg:classifiers":[
        {
            "category":"Professional",
            "type":"Services"
        }
    ],
    "sg:phone":"+61 408 650 647",
    "sg:postcode":"2795",
    "sg:province":"NSW",
    "sg:tags":[
        "courier"
    ],
    "wof:name":"R & D Couriers",
    "wof:placetype":"venue"
},
  "geometry": {"coordinates":[149.55560302699999,-33.4108886719],"type":"Point"}
}