{
  "type": "Feature",
  "properties": {
    "addr:full":"Suite 2A,Level 2 4 Belgrave St Kogarah NSW 2217",
    "addr:housenumber":"4",
    "addr:postcode":"2217",
    "addr:street":"Belgrave St",
    "iso:country":"AU",
    "sg:address":"Suite 2A,Level 2 4 Belgrave St",
    "sg:city":"Kogarah",
    "sg:classifiers":[
        {
            "category":"Health Services",
            "subcategory":"Doctor",
            "type":"Services"
        }
    ],
    "sg:phone":"+61 2 9587 8585",
    "sg:postcode":"2217",
    "sg:province":"NSW",
    "sg:tags":[
        "medical",
        "practitioner"
    ],
    "wof:name":"Southern Ophthalmology",
    "wof:placetype":"venue"
},
  "geometry": {"coordinates":[151.13429300000001,-33.969414],"type":"Point"}
}