{
  "type": "Feature",
  "properties": {
    "iso:country":"AU",
    "sg:address":"227 Collins St",
    "sg:city":"Hobart",
    "sg:classifiers":[
        {
            "category":"Home & Garden",
            "subcategory":"Household Appliances",
            "type":"Retail Goods"
        }
    ],
    "sg:phone":"+61 3 6234 7450",
    "sg:postcode":"7000",
    "sg:province":"TAS",
    "sg:tags":[
        "heating",
        "system"
    ],
    "wof:name":"Lorkin Roberts Electrical",
    "wof:placetype":"venue"
},
  "geometry": {"coordinates":[147.32191467300001,-42.8873977661],"type":"Point"}
}