{
  "type": "Feature",
  "properties": {
    "addr:full":"26 Balmoral Ave Dandenong VIC 3175",
    "addr:housenumber":"26",
    "addr:postcode":"3175",
    "addr:street":"Balmoral Ave",
    "iso:country":"AU",
    "sg:address":"26 Balmoral Ave",
    "sg:city":"Dandenong",
    "sg:classifiers":[
        {
            "category":"Retail",
            "subcategory":"Car Wash",
            "type":"Services"
        }
    ],
    "sg:phone":"+61 3 9791 1539",
    "sg:postcode":"3175",
    "sg:province":"VIC",
    "sg:tags":[
        "truck",
        "cleaning"
    ],
    "wof:name":"Central Auto Detailing",
    "wof:placetype":"venue"
},
  "geometry": {"coordinates":[145.19439697300001,-37.9887771606],"type":"Point"}
}