{
  "type": "Feature",
  "properties": {
    "addr:full":"Lvl2/ 144 Crown St Darlinghurst NSW 2010",
    "addr:housenumber":"144",
    "addr:postcode":"2010",
    "addr:street":"Crown St",
    "iso:country":"AU",
    "sg:address":"Lvl2/ 144 Crown St",
    "sg:city":"Darlinghurst",
    "sg:classifiers":[
        {
            "category":"Professional",
            "subcategory":"Management & Consulting",
            "type":"Services"
        }
    ],
    "sg:phone":"+61 2 9331 8627",
    "sg:postcode":"2010",
    "sg:province":"NSW",
    "sg:tags":[
        "consultant",
        "educational"
    ],
    "wof:name":"Boomerang Australia Studies",
    "wof:placetype":"venue"
},
  "geometry": {"coordinates":[151.21621704099999,-33.8754844666],"type":"Point"}
}