{
  "type": "Feature",
  "properties": {
    "addr:full":"27 Storey Rd Kallangur QLD 4503",
    "addr:housenumber":"27",
    "addr:postcode":"4503",
    "addr:street":"Storey Rd",
    "iso:country":"AU",
    "sg:address":"27 Storey Rd",
    "sg:city":"Kallangur",
    "sg:classifiers":[
        {
            "category":"Building & Trades",
            "subcategory":"Construction",
            "type":"Services"
        }
    ],
    "sg:phone":"+61 414 782 237",
    "sg:postcode":"4503",
    "sg:province":"QLD",
    "sg:tags":[
        "renovation",
        "alterations",
        "extension",
        "contractor"
    ],
    "wof:name":"PK Building Pty Ltd",
    "wof:placetype":"venue"
},
  "geometry": {"coordinates":[152.990432739,-27.2492141724],"type":"Point"}
}