{
  "type": "Feature",
  "properties": {
    "iso:country":"AU",
    "sg:address":"3/ 42 Collingwood St",
    "sg:city":"Osborne Park",
    "sg:classifiers":[
        {
            "category":"Professional",
            "subcategory":"Art Services",
            "type":"Services"
        }
    ],
    "sg:phone":"+61 8 9445 2722",
    "sg:postcode":"6017",
    "sg:province":"WA",
    "sg:tags":[
        "picture",
        "frame",
        "framing"
    ],
    "wof:name":"Creative Matboards Pty Ltd",
    "wof:placetype":"venue"
},
  "geometry": {"coordinates":[115.815368652,-31.9030342102],"type":"Point"}
}