{
  "type": "Feature",
  "properties": {
    "iso:country":"AU",
    "sg:address":"Cnr Bussell Hwy & Broadwater Blvd",
    "sg:city":"Busselton",
    "sg:classifiers":[
        {
            "category":"Health Services",
            "subcategory":"Doctor",
            "type":"Services"
        }
    ],
    "sg:phone":"+61 8 9754 3700",
    "sg:postcode":"6280",
    "sg:province":"WA",
    "sg:tags":[
        "medical",
        "practitioner"
    ],
    "wof:name":"Molecare",
    "wof:placetype":"venue"
},
  "geometry": {"coordinates":[115.293296814,-33.6603393555],"type":"Point"}
}