{
  "type": "Feature",
  "properties": {
    "addr:full":"Adelaide Produce Markets Diagonal Rd Pooraka SA 5095",
    "addr:postcode":"5095",
    "addr:street":"Diagonal Rd",
    "iso:country":"AU",
    "sg:address":"Adelaide Produce Markets Diagonal Rd",
    "sg:city":"Pooraka",
    "sg:classifiers":[
        {
            "category":"Food & Beverages",
            "subcategory":"Fruits & Vegetables",
            "type":"Retail Goods"
        }
    ],
    "sg:phone":"+61 8 8349 4528",
    "sg:postcode":"5095",
    "sg:province":"SA",
    "sg:tags":[
        "wholesale"
    ],
    "wof:name":"S.A. Chamber Of Fruit & Vegetable Industries",
    "wof:placetype":"venue"
},
  "geometry": {"coordinates":[138.61585998499999,-34.8260993958],"type":"Point"}
}