{
  "type": "Feature",
  "properties": {
    "addr:full":"6/109 Crown Rd Queenscliff NSW 2096",
    "addr:housenumber":"/ 109",
    "addr:postcode":"2096",
    "addr:street":"Crown Rd",
    "iso:country":"AU",
    "sg:address":"6/109 Crown Rd",
    "sg:city":"Queenscliff",
    "sg:classifiers":[
        {
            "category":"Professional",
            "subcategory":"Employment Agencies",
            "type":"Services"
        }
    ],
    "sg:phone":"+61 2 9939 5593",
    "sg:postcode":"2096",
    "sg:province":"NSW",
    "sg:tags":[
        "provider",
        "internet"
    ],
    "wof:name":"Matt Trembath Cartoons",
    "wof:placetype":"venue"
},
  "geometry": {"coordinates":[151.28483581500001,-33.7812805176],"type":"Point"}
}