{
  "type": "Feature",
  "properties": {
    "addr:full":"36 Salisbury St Orbost VIC 3888",
    "addr:housenumber":"36",
    "addr:postcode":"3888",
    "addr:street":"Salisbury St",
    "iso:country":"AU",
    "sg:address":"36 Salisbury St",
    "sg:city":"Orbost",
    "sg:classifiers":[
        {
            "category":"Retail",
            "subcategory":"Auto Repair",
            "type":"Services"
        }
    ],
    "sg:phone":"+61 3 5154 1777",
    "sg:postcode":"3888",
    "sg:province":"VIC",
    "sg:tags":[
        "repairer",
        "motor",
        "engineer"
    ],
    "wof:name":"Voss Motors",
    "wof:placetype":"venue"
},
  "geometry": {"coordinates":[148.45681762699999,-37.7048301697],"type":"Point"}
}