{
  "type": "Feature",
  "properties": {
    "iso:country":"AU",
    "sg:address":"1104 Sturt St",
    "sg:city":"Ballarat",
    "sg:classifiers":[
        {
            "category":"Autos & Motor Vehicles",
            "subcategory":"Fuel & Gas Station",
            "type":"Retail Goods"
        }
    ],
    "sg:phone":"+61 3 5332 1667",
    "sg:postcode":"3350",
    "sg:province":"VIC",
    "wof:name":"BP Ballarat Central",
    "wof:placetype":"venue"
},
  "geometry": {"coordinates":[143.845078,-37.560158],"type":"Point"}
}