{
  "type": "Feature",
  "properties": {
    "iso:country":"AU",
    "sg:address":"Level 1, 535 High St",
    "sg:city":"Penrith",
    "sg:classifiers":[
        {
            "category":"Organizations",
            "subcategory":"Community Association",
            "type":"Services"
        }
    ],
    "sg:phone":"+61 2 4735 3178",
    "sg:postcode":"2750",
    "sg:province":"NSW",
    "sg:tags":[
        "organisation",
        "family",
        "welfare"
    ],
    "wof:name":"Riverlands Care",
    "wof:placetype":"venue"
},
  "geometry": {"coordinates":[150.91554260300001,-33.8950462341],"type":"Point"}
}