{
  "type": "Feature",
  "properties": {
    "iso:country":"AU",
    "sg:address":"Level 5, 72 Pitt St",
    "sg:city":"Sydney",
    "sg:classifiers":[
        {
            "category":"Health Services",
            "subcategory":"Chiropractor",
            "type":"Services"
        }
    ],
    "sg:phone":"+61 2 9222 9997",
    "sg:postcode":"2000",
    "sg:province":"NSW",
    "wof:name":"Brooks Jeffery",
    "wof:placetype":"venue"
},
  "geometry": {"coordinates":[151.20877075199999,-33.8660430908],"type":"Point"}
}