{
  "type": "Feature",
  "properties": {
    "addr:full":"Thomas Brunton Pde Roxburgh Park VIC 3064",
    "addr:postcode":"3064",
    "iso:country":"AU",
    "sg:address":"Thomas Brunton Pde",
    "sg:city":"Roxburgh Park",
    "sg:classifiers":[
        {
            "category":"Building & Trades",
            "subcategory":"Construction",
            "type":"Services"
        }
    ],
    "sg:phone":"+61 3 9308 9297",
    "sg:postcode":"3064",
    "sg:province":"VIC",
    "sg:tags":[
        "contractor"
    ],
    "wof:name":"CDC Homes Pty Ltd",
    "wof:placetype":"venue"
},
  "geometry": {"coordinates":[144.928268433,-37.6305923462],"type":"Point"}
}