{
  "type": "Feature",
  "properties": {
    "iso:country":"AU",
    "sg:address":"Cnr Hines Rd & Zeta Crs",
    "sg:city":"O&#039;Connor",
    "sg:classifiers":[
        {
            "category":"Fast Food",
            "type":"Food & Drink"
        }
    ],
    "sg:phone":"+61 8 9331 3021",
    "sg:postcode":"6163",
    "sg:province":"WA",
    "sg:tags":[
        "away",
        "take"
    ],
    "wof:name":"Hines Road Lunch Bar",
    "wof:placetype":"venue"
},
  "geometry": {"coordinates":[115.784187,-32.066505],"type":"Point"}
}