{
  "type": "Feature",
  "properties": {
    "addr:full":"8/ 75 Corish Crcle Eastgardens NSW 2036",
    "addr:housenumber":"/ 75",
    "addr:postcode":"2036",
    "addr:street":"Corish Crcle",
    "iso:country":"AU",
    "sg:address":"8/ 75",
    "sg:city":"Corish Crcle Eastgardens",
    "sg:classifiers":[
        {
            "category":"Home & Garden",
            "subcategory":"Furniture",
            "type":"Retail Goods"
        }
    ],
    "sg:phone":"+61 2 9666 6773",
    "sg:postcode":"2036",
    "sg:province":"NSW",
    "sg:tags":[
        "repair",
        "restoration"
    ],
    "wof:name":"G.E. Furniture Restoration P/L",
    "wof:placetype":"venue"
},
  "geometry": {"coordinates":[151.22244262699999,-33.9438705444],"type":"Point"}
}