{
  "type": "Feature",
  "properties": {
    "addr:full":"3/ 8 Ramly Drv Burleigh Heads QLD 4220",
    "addr:housenumber":"/ 8",
    "addr:postcode":"4220",
    "addr:street":"Ramly Drv",
    "iso:country":"AU",
    "sg:address":"3/ 8 Ramly Drv",
    "sg:city":"Burleigh Heads",
    "sg:classifiers":[
        {
            "category":"Building & Trades",
            "subcategory":"Construction",
            "type":"Services"
        }
    ],
    "sg:phone":"+61 7 5508 2486",
    "sg:postcode":"4220",
    "sg:province":"QLD",
    "sg:tags":[
        "fencing",
        "contractor"
    ],
    "wof:name":"Australian Erosion Solutions Pty Ltd",
    "wof:placetype":"venue"
},
  "geometry": {"coordinates":[153.43423461899999,-28.1031780243],"type":"Point"}
}