{
  "type": "Feature",
  "properties": {
    "addr:full":"U2/ 11 Wise Ave Seaford VIC 3198",
    "addr:housenumber":"11",
    "addr:postcode":"3198",
    "addr:street":"U2 /;Wise Ave",
    "iso:country":"AU",
    "sg:address":"U2/ 11 Wise Ave",
    "sg:city":"Seaford",
    "sg:classifiers":[
        {
            "category":"Building & Trades",
            "subcategory":"Construction",
            "type":"Services"
        }
    ],
    "sg:phone":"+61 3 9785 3117",
    "sg:postcode":"3198",
    "sg:province":"VIC",
    "sg:tags":[
        "contractor"
    ],
    "wof:name":"Alexandra's Building Construction Pty Ltd",
    "wof:placetype":"venue"
},
  "geometry": {"coordinates":[145.134643555,-38.1120872498],"type":"Point"}
}