{
  "type": "Feature",
  "properties": {
    "addr:full":"36 Station St Koo Wee Rup VIC 3981",
    "addr:housenumber":"36",
    "addr:postcode":"3981",
    "addr:street":"Station St",
    "iso:country":"AU",
    "sg:address":"36 Station St",
    "sg:city":"Koo Wee Rup",
    "sg:classifiers":[
        {
            "category":"Fast Food",
            "type":"Food & Drink"
        }
    ],
    "sg:phone":"+61 3 5997 1244",
    "sg:postcode":"3981",
    "sg:province":"VIC",
    "sg:tags":[
        "away",
        "take"
    ],
    "wof:name":"Koo Wee Rup Fish & Chips",
    "wof:placetype":"venue"
},
  "geometry": {"coordinates":[145.49041748100001,-38.1990661621],"type":"Point"}
}