{
  "type": "Feature",
  "properties": {
    "addr:full":"108 Lewis Rd Wantirna South VIC 3152",
    "addr:housenumber":"108",
    "addr:postcode":"3152",
    "addr:street":"Lewis Rd",
    "iso:country":"AU",
    "sg:address":"108 Lewis Rd",
    "sg:city":"Wantirna South",
    "sg:classifiers":[
        {
            "category":"Recreation",
            "type":"Entertainment"
        }
    ],
    "sg:phone":"+61 3 9800 3400",
    "sg:postcode":"3152",
    "sg:province":"VIC",
    "sg:tags":[
        "children's",
        "play",
        "programme"
    ],
    "wof:name":"Kidz In Sportz",
    "wof:placetype":"venue"
},
  "geometry": {"coordinates":[145.24952697800001,-37.8695144653],"type":"Point"}
}