{
  "type": "Feature",
  "properties": {
    "addr:full":"Jandakot Aviation Training Centre, 23 Eagle Drv Jandakot WA 6164",
    "addr:housenumber":"23",
    "addr:postcode":"6164",
    "addr:street":"Eagle Drv",
    "iso:country":"AU",
    "sg:address":"Jandakot Aviation Training Centre, 23 Eagle Drv",
    "sg:city":"Jandakot",
    "sg:classifiers":[
        {
            "category":"Education",
            "subcategory":"Vocational School",
            "type":"Public Place"
        }
    ],
    "sg:phone":"+61 8 9414 1590",
    "sg:postcode":"6164",
    "sg:province":"WA",
    "sg:tags":[
        "tafe",
        "college",
        "training"
    ],
    "wof:name":"TAFEWA - SWAN",
    "wof:placetype":"venue"
},
  "geometry": {"coordinates":[115.87545,-32.095959],"type":"Point"}
}