{
  "type": "Feature",
  "properties": {
    "iso:country":"AU",
    "sg:address":"433 Mt Alexander Rd",
    "sg:city":"Ascot Vale",
    "sg:classifiers":[
        {
            "category":"Shopping",
            "subcategory":"Antiques",
            "type":"Retail Goods"
        }
    ],
    "sg:phone":"+61 3 9370 6765",
    "sg:postcode":"3032",
    "sg:province":"VIC",
    "wof:name":"Memory Lane Antiques & Period Style Lighting",
    "wof:placetype":"venue"
},
  "geometry": {"coordinates":[144.927124,-37.773472],"type":"Point"}
}