{
  "type": "Feature",
  "properties": {
    "iso:country":"AU",
    "sg:address":"123 Burgundy St",
    "sg:city":"Heidelberg",
    "sg:classifiers":[
        {
            "category":"Personal",
            "subcategory":"Beauty Salon",
            "type":"Services"
        }
    ],
    "sg:phone":"+61 3 9459 9289",
    "sg:postcode":"3084",
    "sg:province":"VIC",
    "sg:tags":[
        "hairdresser"
    ],
    "wof:name":"Menaje Hair Studio",
    "wof:placetype":"venue"
},
  "geometry": {"coordinates":[145.06581115700001,-37.7562561035],"type":"Point"}
}