{
  "type": "Feature",
  "properties": {
    "iso:country":"AU",
    "sg:address":"159 Russell St",
    "sg:city":"Bathurst",
    "sg:classifiers":[
        {
            "category":"Education",
            "subcategory":"Special Training",
            "type":"Public Place"
        }
    ],
    "sg:phone":"+61 2 6332 4076",
    "sg:postcode":"2795",
    "sg:province":"NSW",
    "sg:tags":[
        "development"
    ],
    "wof:name":"Learning Matters Tuition & Training Centre",
    "wof:placetype":"venue"
},
  "geometry": {"coordinates":[149.582687378,-33.4215698242],"type":"Point"}
}