{
  "type": "Feature",
  "properties": {
    "addr:full":"93 Wellesley Crs Kings Park NSW 2148",
    "addr:housenumber":"93",
    "addr:postcode":"2148",
    "addr:street":"Wellesley Crs",
    "iso:country":"AU",
    "sg:address":"93 Wellesley Crs",
    "sg:city":"Kings Park",
    "sg:classifiers":[
        {
            "category":"Professional",
            "subcategory":"Printing & Photocopies",
            "type":"Services"
        }
    ],
    "sg:phone":"+61 2 9676 4560",
    "sg:postcode":"2148",
    "sg:province":"NSW",
    "sg:tags":[
        "screen",
        "printer"
    ],
    "wof:name":"G & M Screen Printing",
    "wof:placetype":"venue"
},
  "geometry": {"coordinates":[150.91616821299999,-33.748550415],"type":"Point"}
}