{
  "type": "Feature",
  "properties": {
    "addr:full":"Shop 30 Southshore Piazza South Perth WA 6151",
    "addr:housenumber":"shop 30",
    "addr:postcode":"6151",
    "addr:street":"Piazza South",
    "iso:country":"AU",
    "sg:address":"Shop 30 Southshore Piazza",
    "sg:city":"South Perth",
    "sg:classifiers":[
        {
            "category":"Cafe",
            "type":"Food & Drink"
        }
    ],
    "sg:phone":"+61 8 9474 1050",
    "sg:postcode":"6151",
    "sg:province":"WA",
    "wof:name":"C T Cafe",
    "wof:placetype":"venue"
},
  "geometry": {"coordinates":[115.870239,-31.98105],"type":"Point"}
}