{
  "type": "Feature",
  "properties": {
    "addr:full":"575 North East Rd Gilles Plains SA 5086",
    "addr:housenumber":"575",
    "addr:postcode":"5086",
    "addr:street":"North East Rd",
    "iso:country":"AU",
    "sg:address":"575 North East Rd",
    "sg:city":"Gilles Plains",
    "sg:classifiers":[
        {
            "category":"Cafe",
            "type":"Food & Drink"
        }
    ],
    "sg:phone":"+61 8 8261 8446",
    "sg:postcode":"5086",
    "sg:province":"SA",
    "wof:name":"Gilles Plains Snack Bar",
    "wof:placetype":"venue"
},
  "geometry": {"coordinates":[138.658126831,-34.8555641174],"type":"Point"}
}