{
  "type": "Feature",
  "properties": {
    "addr:full":"187 Wandoo Drv Baldivis WA 6171",
    "addr:housenumber":"187",
    "addr:postcode":"6171",
    "addr:street":"Wandoo Drv",
    "iso:country":"AU",
    "sg:address":"187 Wandoo Drv",
    "sg:city":"Baldivis",
    "sg:classifiers":[
        {
            "category":"Building & Trades",
            "subcategory":"Cleaning & Sanitation",
            "type":"Services"
        }
    ],
    "sg:phone":"+61 8 9524 1108",
    "sg:postcode":"6171",
    "sg:province":"WA",
    "sg:tags":[
        "industrial",
        "commercial",
        "contractor"
    ],
    "wof:name":"Shoalwater Cleaning Services",
    "wof:placetype":"venue"
},
  "geometry": {"coordinates":[115.82038900000001,-32.370358],"type":"Point"}
}