{
  "type": "Feature",
  "properties": {
    "addr:full":"383 Crown St Wollongong NSW 2500",
    "addr:housenumber":"383",
    "addr:postcode":"2500",
    "addr:street":"Crown St",
    "iso:country":"AU",
    "sg:address":"383 Crown St",
    "sg:city":"Wollongong",
    "sg:classifiers":[
        {
            "category":"Health Services",
            "subcategory":"Doctor",
            "type":"Services"
        }
    ],
    "sg:phone":"+61 2 4228 7888",
    "sg:postcode":"2500",
    "sg:province":"NSW",
    "sg:tags":[
        "medical",
        "practitioner"
    ],
    "wof:name":"Illawarra Radiology Group",
    "wof:placetype":"venue"
},
  "geometry": {"coordinates":[150.87762499999999,-34.425858],"type":"Point"}
}