{
  "type": "Feature",
  "properties": {
    "addr:full":"Suite 6, Corporate House, 8 Corporation Circuit Tweed Heads South NSW 2486",
    "addr:housenumber":"8",
    "addr:postcode":"2486",
    "addr:street":"Corporation Circuit",
    "iso:country":"AU",
    "sg:address":"Suite 6, Corporate House, 8 Corporation Circuit",
    "sg:city":"Tweed Heads South",
    "sg:classifiers":[
        {
            "category":"Banks & Credit Unions",
            "subcategory":"Financial Services",
            "type":"Services"
        }
    ],
    "sg:phone":"+61 7 5524 2101",
    "sg:postcode":"2486",
    "sg:province":"NSW",
    "sg:tags":[
        "loan",
        "finance",
        "mortgage"
    ],
    "wof:name":"Local Community Home Loans",
    "wof:placetype":"venue"
},
  "geometry": {"coordinates":[153.537841797,-28.2060813904],"type":"Point"}
}