{
  "type": "Feature",
  "properties": {
    "addr:full":"Nagel St Maryborough QLD 4650",
    "addr:postcode":"4650",
    "addr:street":"Nagel St",
    "iso:country":"AU",
    "sg:address":"Nagel St",
    "sg:city":"Maryborough",
    "sg:classifiers":[
        {
            "category":"Education",
            "subcategory":"Vocational School",
            "type":"Public Place"
        }
    ],
    "sg:phone":"+61 1300 656 188",
    "sg:postcode":"4650",
    "sg:province":"QLD",
    "sg:tags":[
        "tafe",
        "college",
        "training"
    ],
    "wof:name":"WideBay Tafe",
    "wof:placetype":"venue"
},
  "geometry": {"coordinates":[152.65448000000001,-25.510098],"type":"Point"}
}