{
  "type": "Feature",
  "properties": {
    "addr:full":"9 Milne Crt Ocean Reef WA 6027",
    "addr:housenumber":"9",
    "addr:postcode":"6027",
    "addr:street":"Milne Crt",
    "iso:country":"AU",
    "sg:address":"9 Milne Crt",
    "sg:city":"Ocean Reef",
    "sg:classifiers":[
        {
            "category":"Professional",
            "subcategory":"Accounting & Tax Preparation",
            "type":"Services"
        }
    ],
    "sg:phone":"+61 8 9401 7581",
    "sg:postcode":"6027",
    "sg:province":"WA",
    "sg:tags":[
        "accountant",
        "auditor"
    ],
    "wof:name":"Mort Wayne",
    "wof:placetype":"venue"
},
  "geometry": {"coordinates":[115.741287231,-31.7574100494],"type":"Point"}
}