{
  "type": "Feature",
  "properties": {
    "addr:full":"12 Noonameena Drv Orange NSW 2800",
    "addr:housenumber":"12",
    "addr:postcode":"2800",
    "addr:street":"Noonameena Drv",
    "iso:country":"AU",
    "sg:address":"12 Noonameena Drv",
    "sg:city":"Orange",
    "sg:classifiers":[
        {
            "category":"Building & Trades",
            "subcategory":"Construction",
            "type":"Services"
        }
    ],
    "sg:phone":"+61 2 6362 9417",
    "sg:postcode":"2800",
    "sg:province":"NSW",
    "sg:tags":[
        "contractor"
    ],
    "wof:name":"Newton Wayne E",
    "wof:placetype":"venue"
},
  "geometry": {"coordinates":[149.07252502399999,-33.2846603394],"type":"Point"}
}