{
  "type": "Feature",
  "properties": {
    "iso:country":"AU",
    "sg:address":"318 Wyndham St",
    "sg:city":"Shepparton",
    "sg:classifiers":[
        {
            "category":"Banks & Credit Unions",
            "subcategory":"Financial Services",
            "type":"Services"
        }
    ],
    "sg:phone":"+61 1300 780 553",
    "sg:postcode":"3630",
    "sg:province":"VIC",
    "sg:tags":[
        "planning"
    ],
    "wof:name":"St Andrews Wealth Management",
    "wof:placetype":"venue"
},
  "geometry": {"coordinates":[145.39932250999999,-36.3802566528],"type":"Point"}
}