{
  "type": "Feature",
  "properties": {
    "addr:full":"25 Morley St Coorparoo QLD 4151",
    "addr:housenumber":"25",
    "addr:postcode":"4151",
    "addr:street":"Morley St",
    "iso:country":"AU",
    "sg:address":"25 Morley St",
    "sg:city":"Coorparoo",
    "sg:classifiers":[
        {
            "category":"Government",
            "subcategory":"Fire Station",
            "type":"Public Place"
        }
    ],
    "sg:phone":"+61 1300 553 473",
    "sg:postcode":"4151",
    "sg:province":"QLD",
    "sg:tags":[
        "equipment",
        "protection",
        "consultant"
    ],
    "wof:name":"OneSteel Fire Systems",
    "wof:placetype":"venue"
},
  "geometry": {"coordinates":[153.05288696299999,-27.4912796021],"type":"Point"}
}