{
  "type": "Feature",
  "properties": {
    "iso:country":"AU",
    "sg:address":"53 Annerley Rd",
    "sg:city":"South Brisbane",
    "sg:classifiers":[
        {
            "category":"Real Estate",
            "subcategory":"Real Estate Services",
            "type":"Services"
        }
    ],
    "sg:phone":"+61 7 3844 0700",
    "sg:postcode":"4101",
    "sg:province":"QLD",
    "sg:tags":[
        "consultant",
        "property"
    ],
    "wof:name":"Metro Commercial First National Real Estate",
    "wof:placetype":"venue"
},
  "geometry": {"coordinates":[153.02833557100001,-27.4881191254],"type":"Point"}
}