{
  "type": "Feature",
  "properties": {
    "addr:full":"53 Commercial Drv Thomastown VIC 3074",
    "addr:housenumber":"53",
    "addr:postcode":"3074",
    "addr:street":"Commercial Drv",
    "iso:country":"AU",
    "sg:address":"53 Commercial Drv",
    "sg:city":"Thomastown",
    "sg:classifiers":[
        {
            "category":"Wholesale",
            "subcategory":"Electrical",
            "type":"Manufacturing & Wholesale Goods"
        }
    ],
    "sg:phone":"+61 3 9464 6555",
    "sg:postcode":"3074",
    "sg:province":"VIC",
    "sg:tags":[
        "control",
        "equipment",
        "switch"
    ],
    "wof:name":"N.A.W. Controls Pty Ltd",
    "wof:placetype":"venue"
},
  "geometry": {"coordinates":[145.039916992,-37.6894760132],"type":"Point"}
}