{
  "type": "Feature",
  "properties": {
    "addr:full":"Factory 2, 1644 Ferntree Gully Rd Knoxfield VIC 3180",
    "addr:housenumber":"2 1644",
    "addr:postcode":"3180",
    "addr:street":"Ferntree Gully Rd",
    "iso:country":"AU",
    "sg:address":"Factory 2, 1644 Ferntree Gully Rd",
    "sg:city":"Knoxfield",
    "sg:classifiers":[
        {
            "category":"Autos & Motor Vehicles",
            "subcategory":"Motorcycle Sales",
            "type":"Retail Goods"
        }
    ],
    "sg:phone":"+61 3 9763 1168",
    "sg:postcode":"3180",
    "sg:province":"VIC",
    "sg:tags":[
        "part",
        "recyclers",
        "cycle"
    ],
    "sg:website":"http://www.motabitz.com.au",
    "wof:name":"Motabitz",
    "wof:placetype":"venue"
},
  "geometry": {"coordinates":[145.25650024399999,-37.8927726746],"type":"Point"}
}