{
  "type": "Feature",
  "properties": {
    "addr:full":"293 Chapel Rd South Bankstown NSW 2200",
    "addr:housenumber":"293",
    "addr:postcode":"2200",
    "addr:street":"Chapel Rd South",
    "iso:country":"AU",
    "sg:address":"293 Chapel Rd South",
    "sg:city":"Bankstown",
    "sg:classifiers":[
        {
            "category":"Health Services",
            "subcategory":"Optometrist",
            "type":"Services"
        }
    ],
    "sg:phone":"+61 2 9796 4114",
    "sg:postcode":"2200",
    "sg:province":"NSW",
    "wof:name":"Bui My Hanh",
    "wof:placetype":"venue"
},
  "geometry": {"coordinates":[151.031769,-33.91967],"type":"Point"}
}