{
  "type": "Feature",
  "properties": {
    "addr:full":"Shop 3 Benowa Place 83 Ashmore Rd (cnr Racecourse Dr) Bundall QLD 4217",
    "addr:housenumber":"shop 3;83",
    "addr:postcode":"4217",
    "addr:street":"Benowa Place;Ashmore Rd Cnr Racecourse Dr",
    "iso:country":"AU",
    "sg:address":"Shop 3 Benowa Place 83 Ashmore Rd",
    "sg:city":"(cnr Racecourse Dr) Bundall",
    "sg:classifiers":[
        {
            "category":"Home & Garden",
            "subcategory":"Furniture",
            "type":"Retail Goods"
        }
    ],
    "sg:phone":"+61 7 5538 9633",
    "sg:postcode":"4217",
    "sg:province":"QLD",
    "sg:tags":[
        "business"
    ],
    "wof:name":"ChairsRUs",
    "wof:placetype":"venue"
},
  "geometry": {"coordinates":[153.404098511,-28.0098819733],"type":"Point"}
}