{
  "type": "Feature",
  "properties": {
    "iso:country":"AU",
    "sg:address":"3 Gaydon St",
    "sg:city":"Ferntree Gully",
    "sg:classifiers":[
        {
            "category":"Building & Trades",
            "subcategory":"Construction",
            "type":"Services"
        }
    ],
    "sg:phone":"+61 3 9758 7788",
    "sg:postcode":"3156",
    "sg:province":"VIC",
    "sg:tags":[
        "contractor"
    ],
    "wof:name":"Kroeger Building",
    "wof:placetype":"venue"
},
  "geometry": {"coordinates":[145.271850586,-37.8866577148],"type":"Point"}
}