{
  "type": "Feature",
  "properties": {
    "addr:full":"680 Bruce Hwy Woree QLD 4868",
    "addr:housenumber":"680",
    "addr:postcode":"4868",
    "addr:street":"Bruce Hwy",
    "iso:country":"AU",
    "sg:address":"680 Bruce Hwy",
    "sg:city":"Woree",
    "sg:classifiers":[
        {
            "category":"Professional",
            "subcategory":"Detective & Security Services",
            "type":"Services"
        }
    ],
    "sg:phone":"+61 7 4054 4166",
    "sg:postcode":"4868",
    "sg:province":"QLD",
    "sg:tags":[
        "consultant",
        "system"
    ],
    "wof:name":"FNSS Guards & Patrols",
    "wof:placetype":"venue"
},
  "geometry": {"coordinates":[145.74681091299999,-16.9574775696],"type":"Point"}
}