{
  "type": "Feature",
  "properties": {
    "iso:country":"AU",
    "sg:address":"Unit 2, 19 Charlton St",
    "sg:city":"Bentleigh",
    "sg:classifiers":[
        {
            "category":"Professional",
            "subcategory":"Accounting & Tax Preparation",
            "type":"Services"
        }
    ],
    "sg:phone":"+61 3 9557 2870",
    "sg:postcode":"3204",
    "sg:province":"VIC",
    "sg:tags":[
        "accountant",
        "auditor"
    ],
    "wof:name":"K & K Accounting Services Pty Ltd",
    "wof:placetype":"venue"
},
  "geometry": {"coordinates":[145.031494,-37.921768],"type":"Point"}
}