{
  "type": "Feature",
  "properties": {
    "iso:country":"AU",
    "sg:address":"M/S 612 \"Maharatta\" Durong via",
    "sg:city":"Kingaroy",
    "sg:classifiers":[
        {
            "category":"Farming",
            "subcategory":"Farm",
            "type":"Manufacturing & Wholesale Goods"
        }
    ],
    "sg:phone":"+61 7 4168 0185",
    "sg:postcode":"4610",
    "sg:province":"QLD",
    "sg:tags":[
        "farmer"
    ],
    "wof:name":"K E Woollett & Co",
    "wof:placetype":"venue"
},
  "geometry": {"coordinates":[151.835845947,-26.5428390503],"type":"Point"}
}