{
  "type": "Feature",
  "properties": {
    "addr:full":"Suite 1, 3 Banksia Ave Dudley NSW 2290",
    "addr:housenumber":"3",
    "addr:postcode":"2290",
    "addr:street":"Banksia Ave",
    "iso:country":"AU",
    "sg:address":"Suite 1, 3 Banksia Ave",
    "sg:city":"Dudley",
    "sg:classifiers":[
        {
            "category":"Health Services",
            "subcategory":"Health Practitioner",
            "type":"Services"
        }
    ],
    "sg:phone":"+61 2 4944 7858",
    "sg:postcode":"2290",
    "sg:province":"NSW",
    "sg:tags":[
        "dietitian"
    ],
    "wof:name":"Dianne Volker Dr ( APD )",
    "wof:placetype":"venue"
},
  "geometry": {"coordinates":[151.71803283700001,-32.9823951721],"type":"Point"}
}