{
  "type": "Feature",
  "properties": {
    "iso:country":"AU",
    "sg:address":"8/143-145 Canterbury Rd",
    "sg:city":"Kilsyth",
    "sg:classifiers":[
        {
            "category":"Utilities",
            "type":"Services"
        }
    ],
    "sg:phone":"+61 3 9761 7822",
    "sg:postcode":"3137",
    "sg:province":"VIC",
    "sg:tags":[
        "refrigeration",
        "industrial",
        "commercial",
        "retail"
    ],
    "wof:name":"Austral Refrigeration",
    "wof:placetype":"venue"
},
  "geometry": {"coordinates":[145.311035156,-37.8195533752],"type":"Point"}
}