{
  "type": "Feature",
  "properties": {
    "iso:country":"AU",
    "sg:address":"1577 Hume Hwy",
    "sg:city":"Campbellfield",
    "sg:classifiers":[
        {
            "category":"Home & Garden",
            "subcategory":"Building Materials",
            "type":"Retail Goods"
        }
    ],
    "sg:phone":"+61 3 9359 6555",
    "sg:postcode":"3061",
    "sg:province":"VIC",
    "sg:tags":[
        "merchant",
        "glass",
        "glazier"
    ],
    "wof:name":"Premium",
    "wof:placetype":"venue"
},
  "geometry": {"coordinates":[144.95599365199999,-37.6768913269],"type":"Point"}
}