{
  "type": "Feature",
  "properties": {
    "addr:full":"PO Box 104 Glenorchy TAS 7010",
    "addr:postcode":"7010",
    "iso:country":"AU",
    "sg:address":"PO Box 104",
    "sg:city":"Glenorchy",
    "sg:classifiers":[
        {
            "category":"Building & Trades",
            "subcategory":"Landscaping Services",
            "type":"Services"
        }
    ],
    "sg:phone":"+61 3 6249 1066",
    "sg:postcode":"7010",
    "sg:province":"TAS",
    "sg:tags":[
        "forestry",
        "consultant"
    ],
    "wof:name":"Total Sylvan Enterprises",
    "wof:placetype":"venue"
},
  "geometry": {"coordinates":[147.279754639,-42.8336982727],"type":"Point"}
}