{
  "type": "Feature",
  "properties": {
    "iso:country":"AU",
    "sg:address":"Shop 3, The Clarence Centre, 46A 46A Wynter St",
    "sg:city":"Taree",
    "sg:classifiers":[
        {
            "category":"Professional",
            "subcategory":"Employment Agencies",
            "type":"Services"
        }
    ],
    "sg:phone":"+61 2 6557 8055",
    "sg:postcode":"2430",
    "sg:province":"NSW",
    "wof:name":"Mission Employment",
    "wof:placetype":"venue"
},
  "geometry": {"coordinates":[152.460251,-31.908955],"type":"Point"}
}