{
  "type": "Feature",
  "properties": {
    "addr:full":"5 Aspinall Pl Mulgrave NSW 2756",
    "addr:housenumber":"5",
    "addr:postcode":"2756",
    "addr:street":"Aspinall Pl",
    "iso:country":"AU",
    "sg:address":"5 Aspinall Pl",
    "sg:city":"Mulgrave",
    "sg:classifiers":[
        {
            "category":"Banks & Credit Unions",
            "subcategory":"Atm",
            "type":"Services"
        }
    ],
    "sg:phone":"+61 2 4577 9347",
    "sg:postcode":"2756",
    "sg:province":"NSW",
    "sg:tags":[
        "detector",
        "gas"
    ],
    "wof:name":"Aust Dynamic Technologies Co",
    "wof:placetype":"venue"
},
  "geometry": {"coordinates":[150.83428955100001,-33.6239891052],"type":"Point"}
}