{
  "type": "Feature",
  "properties": {
    "addr:full":"360 Forest Rd Lara VIC 3212",
    "addr:housenumber":"360",
    "addr:postcode":"3212",
    "addr:street":"Forest Rd",
    "iso:country":"AU",
    "sg:address":"360 Forest Rd",
    "sg:city":"Lara",
    "sg:classifiers":[
        {
            "category":"Social Services",
            "subcategory":"Job Training",
            "type":"Services"
        }
    ],
    "sg:phone":"+61 3 5274 2210",
    "sg:postcode":"3212",
    "sg:province":"VIC",
    "sg:tags":[
        "tannery"
    ],
    "wof:name":"Austanners (Vic) Pty Ltd",
    "wof:placetype":"venue"
},
  "geometry": {"coordinates":[144.40159606899999,-37.9938774109],"type":"Point"}
}