{
  "type": "Feature",
  "properties": {
    "addr:full":"Shop 10 High Street Plaza Toowoomba QLD 4350",
    "addr:housenumber":"shop 10",
    "addr:postcode":"4350",
    "addr:street":"High Street",
    "iso:country":"AU",
    "sg:address":"Shop 10 High Street Plaza",
    "sg:city":"Toowoomba",
    "sg:classifiers":[
        {
            "category":"Shopping",
            "subcategory":"Clothing, Apparel, & Fashions",
            "type":"Retail Goods"
        }
    ],
    "sg:phone":"+61 7 4636 5788",
    "sg:postcode":"4350",
    "sg:province":"QLD",
    "sg:tags":[
        "lady",
        "wear"
    ],
    "wof:name":"Nannette Boutique",
    "wof:placetype":"venue"
},
  "geometry": {"coordinates":[151.979004,-27.579607],"type":"Point"}
}