{
  "type": "Feature",
  "properties": {
    "addr:full":"PO Box 2301 Rockingham DC WA 6168",
    "addr:postcode":"6168",
    "iso:country":"AU",
    "sg:address":"PO Box 2301",
    "sg:city":"Rockingham DC",
    "sg:classifiers":[
        {
            "category":"Arts & Performance",
            "subcategory":"Music",
            "type":"Entertainment"
        }
    ],
    "sg:phone":"+61 418 919 665",
    "sg:postcode":"6168",
    "sg:province":"WA",
    "sg:tags":[
        "mobile",
        "jockey",
        "disc"
    ],
    "wof:name":"Perth's Mr DJ",
    "wof:placetype":"venue"
},
  "geometry": {"coordinates":[115.757622,-32.250061],"type":"Point"}
}