{
  "type": "Feature",
  "properties": {
    "addr:full":"Blaxland Rd Campbelltown NSW 2560",
    "addr:postcode":"2560",
    "addr:street":"Blaxland Rd",
    "iso:country":"AU",
    "sg:address":"Blaxland Rd",
    "sg:city":"Campbelltown",
    "sg:classifiers":[
        {
            "category":"Home & Garden",
            "subcategory":"Carpets & Floor Coverings",
            "type":"Retail Goods"
        }
    ],
    "sg:phone":"+61 2 4628 9215",
    "sg:postcode":"2560",
    "sg:province":"NSW",
    "sg:tags":[
        "mattress"
    ],
    "wof:name":"Sleep Doctor",
    "wof:placetype":"venue"
},
  "geometry": {"coordinates":[150.80262756400001,-34.0680198669],"type":"Point"}
}