{
  "type": "Feature",
  "properties": {
    "iso:country":"AU",
    "sg:address":"PO Box 1004",
    "sg:city":"Chatswood",
    "sg:classifiers":[
        {
            "category":"Professional",
            "subcategory":"Art Services",
            "type":"Services"
        }
    ],
    "sg:phone":"+61 402 031 353",
    "sg:postcode":"2057",
    "sg:province":"NSW",
    "sg:tags":[
        "arranger",
        "music",
        "composer"
    ],
    "wof:name":"Daniel Thornton Music",
    "wof:placetype":"venue"
},
  "geometry": {"coordinates":[151.19012499999999,-33.792439],"type":"Point"}
}