{
  "type": "Feature",
  "properties": {
    "iso:country":"AU",
    "sg:address":"22 Commercial St",
    "sg:city":"Burra",
    "sg:classifiers":[
        {
            "category":"Travel",
            "subcategory":"Hotels & Motels",
            "type":"Entertainment"
        }
    ],
    "sg:phone":"+61 8 8892 2010",
    "sg:postcode":"5417",
    "sg:province":"SA",
    "sg:tags":[
        "pub"
    ],
    "wof:name":"Commercial Hotel, Burra",
    "wof:placetype":"venue"
},
  "geometry": {"coordinates":[138.93838500999999,-33.6826133728],"type":"Point"}
}