{
  "type": "Feature",
  "properties": {
    "addr:full":"17 Tooloon St Coonamble NSW 2829",
    "addr:housenumber":"17",
    "addr:postcode":"2829",
    "addr:street":"Tooloon St",
    "iso:country":"AU",
    "sg:address":"17 Tooloon St",
    "sg:city":"Coonamble",
    "sg:classifiers":[
        {
            "category":"Organizations",
            "subcategory":"Community Association",
            "type":"Services"
        }
    ],
    "sg:phone":"+61 2 6822 2277",
    "sg:postcode":"2829",
    "sg:province":"NSW",
    "sg:tags":[
        "organisation",
        "family",
        "welfare"
    ],
    "wof:name":"Meals On Wheels - Coonamble",
    "wof:placetype":"venue"
},
  "geometry": {"coordinates":[148.38844299300001,-30.9519367218],"type":"Point"}
}