{
  "type": "Feature",
  "properties": {
    "addr:full":"167 Federation Ave Corowa NSW 2646",
    "addr:housenumber":"167",
    "addr:postcode":"2646",
    "addr:street":"Federation Ave",
    "iso:country":"AU",
    "sg:address":"167 Federation Ave",
    "sg:city":"Corowa",
    "sg:classifiers":[
        {
            "category":"Professional",
            "subcategory":"Testing Lab",
            "type":"Services"
        }
    ],
    "sg:phone":"+61 2 6033 3795",
    "sg:postcode":"2646",
    "sg:province":"NSW",
    "sg:tags":[
        "soil",
        "investigation"
    ],
    "wof:name":"Riverina Soil Investigations",
    "wof:placetype":"venue"
},
  "geometry": {"coordinates":[146.38731384299999,-35.9979972839],"type":"Point"}
}