{
  "type": "Feature",
  "properties": {
    "iso:country":"AU",
    "sg:address":"Cnr of Chalmers & Cleveland Sts",
    "sg:city":"Surry Hills",
    "sg:classifiers":[
        {
            "category":"Bars & Pubs",
            "subcategory":"Nightclub",
            "type":"Food & Drink"
        }
    ],
    "sg:phone":"+61 2 9310 4278",
    "sg:postcode":"2010",
    "sg:province":"NSW",
    "sg:tags":[
        "discotheque"
    ],
    "wof:name":"Bookers Night Spot",
    "wof:placetype":"venue"
},
  "geometry": {"coordinates":[151.2081604,-33.8836708069],"type":"Point"}
}