{
  "type": "Feature",
  "properties": {
    "addr:full":"737 Warraba Rd Booral NSW 2425",
    "addr:housenumber":"737",
    "addr:postcode":"2425",
    "addr:street":"Warraba Rd",
    "iso:country":"AU",
    "sg:address":"737 Warraba Rd",
    "sg:city":"Booral",
    "sg:classifiers":[
        {
            "category":"Industrial Area",
            "type":"Public Place"
        }
    ],
    "sg:phone":"+61 2 4997 6729",
    "sg:postcode":"2425",
    "sg:province":"NSW",
    "sg:tags":[
        "rural",
        "shed"
    ],
    "wof:name":"Stablemaster Australia Pty Ltd",
    "wof:placetype":"venue"
},
  "geometry": {"coordinates":[152.008255005,-32.5181121826],"type":"Point"}
}