{
  "type": "Feature",
  "properties": {
    "addr:full":"50 McCrae Drv Camden NSW 2570",
    "addr:housenumber":"50",
    "addr:postcode":"2570",
    "addr:street":"Mccrae Drv",
    "iso:country":"AU",
    "sg:address":"50 McCrae Drv",
    "sg:city":"Camden",
    "sg:classifiers":[
        {
            "category":"Professional",
            "subcategory":"Art Services",
            "type":"Services"
        }
    ],
    "sg:phone":"+61 2 4655 8437",
    "sg:postcode":"2570",
    "sg:province":"NSW",
    "sg:tags":[
        "decorator",
        "painter"
    ],
    "wof:name":"D.G. Interiors",
    "wof:placetype":"venue"
},
  "geometry": {"coordinates":[150.690795898,-34.0774002075],"type":"Point"}
}