{
  "type": "Feature",
  "properties": {
    "addr:full":"30 Hazell Ave Banksia Beach QLD 4507",
    "addr:housenumber":"30",
    "addr:postcode":"4507",
    "addr:street":"Hazell Ave",
    "iso:country":"AU",
    "sg:address":"30 Hazell Ave",
    "sg:city":"Banksia Beach",
    "sg:classifiers":[
        {
            "category":"Shopping",
            "subcategory":"Party Supplies",
            "type":"Retail Goods"
        }
    ],
    "sg:phone":"+61 7 3410 7938",
    "sg:postcode":"4507",
    "sg:province":"QLD",
    "sg:tags":[
        "children's"
    ],
    "wof:name":"Looney Lynne",
    "wof:placetype":"venue"
},
  "geometry": {"coordinates":[153.143066406,-27.0417556763],"type":"Point"}
}