{
  "type": "Feature",
  "properties": {
    "addr:full":"28 Winstanley St Chapman ACT 2611",
    "addr:housenumber":"28",
    "addr:postcode":"2611",
    "addr:street":"Winstanley St",
    "iso:country":"AU",
    "sg:address":"28 Winstanley St",
    "sg:city":"Chapman",
    "sg:classifiers":[
        {
            "category":"Professional",
            "subcategory":"Accounting & Tax Preparation",
            "type":"Services"
        }
    ],
    "sg:phone":"+61 2 6288 5787",
    "sg:postcode":"2611",
    "sg:province":"ACT",
    "sg:tags":[
        "consultant",
        "taxation"
    ],
    "wof:name":"McLenaghan L P",
    "wof:placetype":"venue"
},
  "geometry": {"coordinates":[149.033004761,-35.3571281433],"type":"Point"}
}