{
  "type": "Feature",
  "properties": {
    "iso:country":"AU",
    "sg:address":"Shop 3, 130 Oyster Bay Rd",
    "sg:city":"Oyster Bay",
    "sg:classifiers":[
        {
            "category":"Personal",
            "subcategory":"Beauty Salon",
            "type":"Services"
        }
    ],
    "sg:phone":"+61 2 9528 6147",
    "sg:postcode":"2225",
    "sg:province":"NSW",
    "sg:tags":[
        "hair",
        "wedding"
    ],
    "wof:name":"Chameleon Hair Design",
    "wof:placetype":"venue"
},
  "geometry": {"coordinates":[151.081008911,-34.0069885254],"type":"Point"}
}