{
  "type": "Feature",
  "properties": {
    "iso:country":"AU",
    "sg:address":"362 New Canterbury Rd",
    "sg:city":"Dulwich Hill",
    "sg:classifiers":[
        {
            "category":"Bars & Pubs",
            "subcategory":"Nightclub",
            "type":"Food & Drink"
        }
    ],
    "sg:phone":"+61 2 9569 1511",
    "sg:postcode":"2203",
    "sg:province":"NSW",
    "sg:tags":[
        "discotheque"
    ],
    "wof:name":"Club Ole",
    "wof:placetype":"venue"
},
  "geometry": {"coordinates":[151.136703,-33.905628],"type":"Point"}
}