{
  "type": "Feature",
  "properties": {
    "iso:country":"AU",
    "sg:address":"2/ 2 Barnett Pl",
    "sg:city":"Molendinar",
    "sg:classifiers":[
        {
            "category":"Freight",
            "type":"Transportation"
        }
    ],
    "sg:phone":"+61 1300 655 594",
    "sg:postcode":"4214",
    "sg:province":"QLD",
    "sg:tags":[
        "car",
        "carrier",
        "transporting"
    ],
    "wof:name":"Ceva Logistics",
    "wof:placetype":"venue"
},
  "geometry": {"coordinates":[153.36128234899999,-27.9656276703],"type":"Point"}
}