{
  "type": "Feature",
  "properties": {
    "addr:full":"2 Wiowera Rd Kanwal NSW 2259",
    "addr:housenumber":"2",
    "addr:postcode":"2259",
    "addr:street":"Wiowera Rd",
    "iso:country":"AU",
    "sg:address":"2 Wiowera Rd",
    "sg:city":"Kanwal",
    "sg:classifiers":[
        {
            "category":"Retail",
            "subcategory":"Veterinary Services",
            "type":"Services"
        }
    ],
    "sg:phone":"+61 2 4392 2088",
    "sg:postcode":"2259",
    "sg:province":"NSW",
    "sg:tags":[
        "surgeon"
    ],
    "wof:name":"Jamieson Chris & Associates",
    "wof:placetype":"venue"
},
  "geometry": {"coordinates":[151.48394775400001,-33.2610969543],"type":"Point"}
}