{
  "type": "Feature",
  "properties": {
    "addr:full":"Shop 5,31 Pimlott St Dianella Heights Village Dianella WA 6059",
    "addr:housenumber":"5,31",
    "addr:postcode":"6059",
    "addr:street":"Pimlott St",
    "iso:country":"AU",
    "sg:address":"Shop 5,31 Pimlott St",
    "sg:city":"Dianella Heights Village Dianella",
    "sg:classifiers":[
        {
            "category":"Personal",
            "subcategory":"Beauty Salon",
            "type":"Services"
        }
    ],
    "sg:phone":"+61 8 9276 7717",
    "sg:postcode":"6059",
    "sg:province":"WA",
    "wof:name":"&#034;The Look&#034; Beauty Salon",
    "wof:placetype":"venue"
},
  "geometry": {"coordinates":[115.86607360799999,-31.886762619],"type":"Point"}
}