{
  "type": "Feature",
  "properties": {
    "iso:country":"AU",
    "sg:address":"166 Wentworth St",
    "sg:city":"Port Kembla",
    "sg:classifiers":[
        {
            "category":"Health Services",
            "subcategory":"Health Practitioner",
            "type":"Services"
        }
    ],
    "sg:phone":"+61 2 4276 1918",
    "sg:postcode":"2505",
    "sg:province":"NSW",
    "sg:tags":[
        "acupuncture"
    ],
    "wof:name":"Alison Jones",
    "wof:placetype":"venue"
},
  "geometry": {"coordinates":[150.903366,-34.48288],"type":"Point"}
}