{
  "type": "Feature",
  "properties": {
    "addr:full":"50c King St Sandy Bay TAS 7005",
    "addr:housenumber":"50c",
    "addr:postcode":"7005",
    "addr:street":"King St",
    "iso:country":"AU",
    "sg:address":"50c King St",
    "sg:city":"Sandy Bay",
    "sg:classifiers":[
        {
            "category":"Restaurant",
            "type":"Food & Drink"
        }
    ],
    "sg:phone":"+61 3 6223 3600",
    "sg:postcode":"7005",
    "sg:province":"TAS",
    "wof:name":"Chon-Na-Kan",
    "wof:placetype":"venue"
},
  "geometry": {"coordinates":[147.32623290999999,-42.8946800232],"type":"Point"}
}