{
  "type": "Feature",
  "properties": {
    "addr:full":"33 Hibberson St Gungahlin ACT 2912",
    "addr:housenumber":"33",
    "addr:postcode":"2912",
    "addr:street":"Hibberson St",
    "iso:country":"AU",
    "sg:address":"33 Hibberson St",
    "sg:city":"Gungahlin",
    "sg:classifiers":[
        {
            "category":"Health Services",
            "subcategory":"Doctor",
            "type":"Services"
        }
    ],
    "sg:phone":"+61 2 6241 0888",
    "sg:postcode":"2912",
    "sg:province":"ACT",
    "sg:tags":[
        "medical",
        "practitioner"
    ],
    "wof:name":"Gungahlin Health Centre",
    "wof:placetype":"venue"
},
  "geometry": {"coordinates":[149.133544922,-35.1851348877],"type":"Point"}
}