{
  "type": "Feature",
  "properties": {
    "iso:country":"AU",
    "sg:address":"196 Anzac Hwy",
    "sg:city":"Plympton",
    "sg:classifiers":[
        {
            "category":"Shopping",
            "subcategory":"Jewelry",
            "type":"Retail Goods"
        }
    ],
    "sg:phone":"+61 418 846 551",
    "sg:postcode":"5038",
    "sg:province":"SA",
    "sg:tags":[
        "fashion",
        "jewellery"
    ],
    "wof:name":"Lina's Fashion Jewellery",
    "wof:placetype":"venue"
},
  "geometry": {"coordinates":[138.56312560999999,-34.9588546753],"type":"Point"}
}