{
  "type": "Feature",
  "properties": {
    "addr:full":"Florence Rd Vasse WA 6280",
    "addr:postcode":"6280",
    "addr:street":"Florence Rd",
    "iso:country":"AU",
    "sg:address":"Florence Rd",
    "sg:city":"Vasse",
    "sg:classifiers":[
        {
            "category":"Commercial Area",
            "type":"Public Place"
        }
    ],
    "sg:phone":"+61 8 9755 4032",
    "sg:postcode":"6280",
    "sg:province":"WA",
    "sg:tags":[
        "heavy",
        "carrier"
    ],
    "wof:name":"Vasse Earthmoving",
    "wof:placetype":"venue"
},
  "geometry": {"coordinates":[115.242637634,-33.6843757629],"type":"Point"}
}