{
  "type": "Feature",
  "properties": {
    "iso:country":"AU",
    "sg:address":"141 Bolaro St",
    "sg:city":"Dunedoo",
    "sg:classifiers":[
        {
            "category":"Retail",
            "subcategory":"Auto Repair",
            "type":"Services"
        }
    ],
    "sg:phone":"+61 2 6375 1260",
    "sg:postcode":"2844",
    "sg:province":"NSW",
    "sg:tags":[
        "repairer",
        "motor",
        "engineer"
    ],
    "wof:name":"Westend Dunedoo Service Centre",
    "wof:placetype":"venue"
},
  "geometry": {"coordinates":[149.387589,-32.016331],"type":"Point"}
}