{
  "type": "Feature",
  "properties": {
    "addr:full":"171 Kingsclere Ave Keysborough VIC 3173",
    "addr:housenumber":"171",
    "addr:postcode":"3173",
    "addr:street":"Kingsclere Ave",
    "iso:country":"AU",
    "sg:address":"171 Kingsclere Ave",
    "sg:city":"Keysborough",
    "sg:classifiers":[
        {
            "category":"Health Services",
            "subcategory":"Dentist",
            "type":"Services"
        }
    ],
    "sg:phone":"+61 3 9798 3894",
    "sg:postcode":"3173",
    "sg:province":"VIC",
    "wof:name":"Poon Geoffrey",
    "wof:placetype":"venue"
},
  "geometry": {"coordinates":[145.17581176799999,-37.9932861328],"type":"Point"}
}