{
  "type": "Feature",
  "properties": {
    "addr:full":"60 Queen St St Marys NSW 2760",
    "addr:housenumber":"60",
    "addr:postcode":"2760",
    "addr:street":"Queen St",
    "iso:country":"AU",
    "sg:address":"60 Queen St",
    "sg:city":"St Marys",
    "sg:classifiers":[
        {
            "category":"Shopping",
            "subcategory":"Computers & Home Electronics",
            "type":"Retail Goods"
        }
    ],
    "sg:phone":"+61 2 9833 4127",
    "sg:postcode":"2760",
    "sg:province":"NSW",
    "sg:tags":[
        "small",
        "equipment",
        "business"
    ],
    "wof:name":"Bromley Computers",
    "wof:placetype":"venue"
},
  "geometry": {"coordinates":[150.77456665,-33.7642860413],"type":"Point"}
}