{
  "type": "Feature",
  "properties": {
    "addr:full":"10 Hotham St Preston VIC 3072",
    "addr:housenumber":"10",
    "addr:postcode":"3072",
    "addr:street":"Hotham St",
    "iso:country":"AU",
    "sg:address":"10 Hotham St",
    "sg:city":"Preston",
    "sg:classifiers":[
        {
            "category":"Health Services",
            "subcategory":"Nursing And Care Facility",
            "type":"Services"
        }
    ],
    "sg:phone":"+61 3 8480 1200",
    "sg:postcode":"3072",
    "sg:province":"VIC",
    "sg:tags":[
        "home"
    ],
    "wof:name":"Hilltop Aged Care Facility",
    "wof:placetype":"venue"
},
  "geometry": {"coordinates":[145.00672912600001,-37.7516937256],"type":"Point"}
}