{
  "type": "Feature",
  "properties": {
    "addr:full":"Cnr Blakey & Zandonadi Drv Garbutt QLD 4814",
    "addr:postcode":"4814",
    "addr:street":"Cnr Blakey & Zandonadi Drv",
    "iso:country":"AU",
    "sg:address":"Cnr Blakey & Zandonadi Drv",
    "sg:city":"Garbutt",
    "sg:classifiers":[
        {
            "category":"Shopping",
            "subcategory":"Stationery & Office Supplies",
            "type":"Retail Goods"
        }
    ],
    "sg:phone":"+61 7 4725 3966",
    "sg:postcode":"4814",
    "sg:province":"QLD",
    "sg:tags":[
        "packaging",
        "material"
    ],
    "wof:name":"Chep Australia",
    "wof:placetype":"venue"
},
  "geometry": {"coordinates":[146.75503499999999,-19.263487],"type":"Point"}
}