{
  "type": "Feature",
  "properties": {
    "addr:full":"Shop 10A, Elgin St Maitland NSW 2320",
    "addr:housenumber":"10a",
    "addr:postcode":"2320",
    "addr:street":"Elgin St",
    "iso:country":"AU",
    "sg:address":"Shop 10A, Elgin St",
    "sg:city":"Maitland",
    "sg:classifiers":[
        {
            "category":"Building & Trades",
            "subcategory":"Construction",
            "type":"Services"
        }
    ],
    "sg:phone":"+61 2 4934 5235",
    "sg:postcode":"2320",
    "sg:province":"NSW",
    "sg:tags":[
        "joinery"
    ],
    "wof:name":"First Choice Kitchens",
    "wof:placetype":"venue"
},
  "geometry": {"coordinates":[151.55473327600001,-32.732460022],"type":"Point"}
}