{
  "type": "Feature",
  "properties": {
    "addr:full":"92 Chambers Flat Rd Marsden QLD 4132",
    "addr:housenumber":"92",
    "addr:postcode":"4132",
    "addr:street":"Chambers Flat Rd",
    "iso:country":"AU",
    "sg:address":"92 Chambers Flat Rd",
    "sg:city":"Marsden",
    "sg:classifiers":[
        {
            "category":"Fast Food",
            "type":"Food & Drink"
        }
    ],
    "sg:phone":"+61 7 3200 9142",
    "sg:postcode":"4132",
    "sg:province":"QLD",
    "sg:tags":[
        "away",
        "take"
    ],
    "wof:name":"KFC",
    "wof:placetype":"venue"
},
  "geometry": {"coordinates":[153.11128234899999,-27.6833782196],"type":"Point"}
}