{
  "type": "Feature",
  "properties": {
    "addr:full":"Unit 2/ 28 Jones St Wagga Wagga NSW 2650",
    "addr:housenumber":"28",
    "addr:postcode":"2650",
    "addr:street":"Jones St",
    "iso:country":"AU",
    "sg:address":"Unit 2/ 28 Jones St",
    "sg:city":"Wagga Wagga",
    "sg:classifiers":[
        {
            "category":"Building & Trades",
            "subcategory":"Construction",
            "type":"Services"
        }
    ],
    "sg:phone":"+61 427 497 723",
    "sg:postcode":"2650",
    "sg:province":"NSW",
    "sg:tags":[
        "joinery"
    ],
    "wof:name":"New Image Joinery",
    "wof:placetype":"venue"
},
  "geometry": {"coordinates":[147.38607788100001,-35.12317276],"type":"Point"}
}