{
  "type": "Feature",
  "properties": {
    "addr:full":"9 Beaver St Geraldton WA 6530",
    "addr:housenumber":"9",
    "addr:postcode":"6530",
    "addr:street":"Beaver St",
    "iso:country":"AU",
    "sg:address":"9 Beaver St",
    "sg:city":"Geraldton",
    "sg:classifiers":[
        {
            "category":"Wholesale",
            "subcategory":"Metals & Minerals",
            "type":"Manufacturing & Wholesale Goods"
        }
    ],
    "sg:phone":"+61 8 9964 1101",
    "sg:postcode":"6530",
    "sg:province":"WA",
    "sg:tags":[
        "steel",
        "merchant"
    ],
    "wof:name":"Smorgon Steel Metals Distribution",
    "wof:placetype":"venue"
},
  "geometry": {"coordinates":[114.633811951,-28.7568874359],"type":"Point"}
}