{
  "type": "Feature",
  "properties": {
    "iso:country":"AU",
    "sg:address":"387 Willarong Rd",
    "sg:city":"Caringbah",
    "sg:classifiers":[
        {
            "category":"Building & Trades",
            "subcategory":"Plumbing",
            "type":"Services"
        }
    ],
    "sg:phone":"+61 2 9524 4436",
    "sg:postcode":"2229",
    "sg:province":"NSW",
    "sg:tags":[
        "plumber",
        "gasfitters"
    ],
    "wof:name":"Darron Prince",
    "wof:placetype":"venue"
},
  "geometry": {"coordinates":[151.11164855999999,-34.0564460754],"type":"Point"}
}