{
  "type": "Feature",
  "properties": {
    "addr:full":"Shop 11 Kununurra Shping Cntr Kununurra WA 6743",
    "addr:housenumber":"shop 11",
    "addr:postcode":"6743",
    "iso:country":"AU",
    "sg:address":"Shop 11",
    "sg:city":"Kununurra Shping Cntr Kununurra",
    "sg:classifiers":[
        {
            "category":"Shopping",
            "subcategory":"Baby Store",
            "type":"Retail Goods"
        }
    ],
    "sg:phone":"+61 8 9168 3623",
    "sg:postcode":"6743",
    "sg:province":"WA",
    "sg:tags":[
        "children's",
        "wear"
    ],
    "wof:name":"Bandicutes",
    "wof:placetype":"venue"
},
  "geometry": {"coordinates":[128.73936462399999,-15.7726697922],"type":"Point"}
}