{
  "type": "Feature",
  "properties": {
    "addr:full":"4/ 159 William St Beverley SA 5009",
    "addr:housenumber":"/ 159",
    "addr:postcode":"5009",
    "addr:street":"William St",
    "iso:country":"AU",
    "sg:address":"4/ 159 William St",
    "sg:city":"Beverley",
    "sg:classifiers":[
        {
            "category":"Farming",
            "subcategory":"Fish & Marine Products",
            "type":"Manufacturing & Wholesale Goods"
        }
    ],
    "sg:phone":"+61 418 896 604",
    "sg:postcode":"5009",
    "sg:province":"SA",
    "sg:tags":[
        "slate"
    ],
    "wof:name":"Tasman Chemicals Pty Ltd",
    "wof:placetype":"venue"
},
  "geometry": {"coordinates":[138.54774475100001,-34.9024276733],"type":"Point"}
}