{
  "type": "Feature",
  "properties": {
    "addr:full":"Unit 5, 185 The Entrance Rd Erina NSW 2250",
    "addr:housenumber":"185",
    "addr:postcode":"2250",
    "addr:street":"The Entrance Rd",
    "iso:country":"AU",
    "sg:address":"Unit 5, 185 The Entrance Rd",
    "sg:city":"Erina",
    "sg:classifiers":[
        {
            "category":"Arena",
            "subcategory":"Sports Club",
            "type":"Entertainment"
        }
    ],
    "sg:phone":"+61 2 4367 0357",
    "sg:postcode":"2250",
    "sg:province":"NSW",
    "sg:tags":[
        "defence",
        "supply",
        "self",
        "instruction",
        "martial art"
    ],
    "wof:name":"Munen Muso Martial Arts Studio",
    "wof:placetype":"venue"
},
  "geometry": {"coordinates":[151.38473510700001,-33.4361152649],"type":"Point"}
}