{
  "type": "Feature",
  "properties": {
    "addr:full":"Kent St Nambucca Heads NSW 2448",
    "addr:postcode":"2448",
    "addr:street":"Kent St",
    "iso:country":"AU",
    "sg:address":"Kent St",
    "sg:city":"Nambucca Heads",
    "sg:classifiers":[
        {
            "category":"Taxi",
            "type":"Transportation"
        }
    ],
    "sg:phone":"+61 2 6568 6855",
    "sg:postcode":"2448",
    "sg:province":"NSW",
    "sg:tags":[
        "cab"
    ],
    "wof:name":"Nambucca Radio Cabs",
    "wof:placetype":"venue"
},
  "geometry": {"coordinates":[153.00349399999999,-30.641907],"type":"Point"}
}