{
  "type": "Feature",
  "properties": {
    "addr:full":"64 Sondrio Pl Woree QLD 4868",
    "addr:housenumber":"64",
    "addr:postcode":"4868",
    "addr:street":"Pl",
    "iso:country":"AU",
    "sg:address":"64 Sondrio Pl",
    "sg:city":"Woree",
    "sg:classifiers":[
        {
            "category":"Building & Trades",
            "subcategory":"Construction",
            "type":"Services"
        }
    ],
    "sg:phone":"+61 438 168 845",
    "sg:postcode":"4868",
    "sg:province":"QLD",
    "sg:tags":[
        "polishing",
        "sanding",
        "floor"
    ],
    "wof:name":"Barbieri Angelo",
    "wof:placetype":"venue"
},
  "geometry": {"coordinates":[145.74192810100001,-16.9522342682],"type":"Point"}
}