{
  "type": "Feature",
  "properties": {
    "addr:full":"67 Howard Rd Padstow NSW 2211",
    "addr:housenumber":"67",
    "addr:postcode":"2211",
    "addr:street":"Howard Rd",
    "iso:country":"AU",
    "sg:address":"67 Howard Rd",
    "sg:city":"Padstow",
    "sg:classifiers":[
        {
            "category":"Food & Beverages",
            "subcategory":"Bakery",
            "type":"Retail Goods"
        }
    ],
    "sg:phone":"+61 2 9771 4005",
    "sg:postcode":"2211",
    "sg:province":"NSW",
    "sg:tags":[
        "baker"
    ],
    "wof:name":"Bus Stop Bakery",
    "wof:placetype":"venue"
},
  "geometry": {"coordinates":[151.031418,-33.952335],"type":"Point"}
}