{
  "type": "Feature",
  "properties": {
    "iso:country":"AU",
    "sg:address":"PO Box 296",
    "sg:city":"Greenacres",
    "sg:classifiers":[
        {
            "category":"Sports & Exercise",
            "subcategory":"Golf",
            "type":"Entertainment"
        }
    ],
    "sg:phone":"+61 8 8443 3775",
    "sg:postcode":"5086",
    "sg:province":"SA",
    "sg:tags":[
        "club"
    ],
    "wof:name":"S.A. Veteran Golfers Association",
    "wof:placetype":"venue"
},
  "geometry": {"coordinates":[138.63670349099999,-34.8652000427],"type":"Point"}
}