{
  "type": "Feature",
  "properties": {
    "addr:full":"2/8- 10 Waratah St Mona Vale NSW 2103",
    "addr:housenumber":"/;10",
    "addr:postcode":"2103",
    "addr:street":"8;Waratah St",
    "iso:country":"AU",
    "sg:address":"2/8- 10 Waratah St",
    "sg:city":"Mona Vale",
    "sg:classifiers":[
        {
            "category":"Personal",
            "subcategory":"Beauty Salon",
            "type":"Services"
        }
    ],
    "sg:phone":"+61 2 9997 8399",
    "sg:postcode":"2103",
    "sg:province":"NSW",
    "sg:tags":[
        "hairdresser"
    ],
    "wof:name":"Ecru Hair Studio",
    "wof:placetype":"venue"
},
  "geometry": {"coordinates":[151.30314636200001,-33.6776313782],"type":"Point"}
}