{
  "type": "Feature",
  "properties": {
    "iso:country":"AU",
    "sg:address":"38- 40 James St",
    "sg:city":"Lidcombe",
    "sg:classifiers":[
        {
            "category":"Shopping",
            "subcategory":"Party Supplies",
            "type":"Retail Goods"
        }
    ],
    "sg:phone":"+61 2 9643 8200",
    "sg:postcode":"2141",
    "sg:province":"NSW",
    "sg:tags":[
        "equipment",
        "laminating"
    ],
    "wof:name":"A.E. Hudson",
    "wof:placetype":"venue"
},
  "geometry": {"coordinates":[151.047119141,-33.8667068481],"type":"Point"}
}