{
  "type": "Feature",
  "properties": {
    "addr:full":"321 Beach Rd Black Rock VIC 3193",
    "addr:housenumber":"321",
    "addr:postcode":"3193",
    "addr:street":"Beach Rd",
    "iso:country":"AU",
    "sg:address":"321 Beach Rd",
    "sg:city":"Black Rock",
    "sg:classifiers":[
        {
            "category":"Shopping",
            "subcategory":"Clothing, Apparel, & Fashions",
            "type":"Retail Goods"
        }
    ],
    "sg:phone":"+61 3 9589 5497",
    "sg:postcode":"3193",
    "sg:province":"VIC",
    "sg:tags":[
        "textile",
        "designer"
    ],
    "wof:name":"Sonia Textile Designs",
    "wof:placetype":"venue"
},
  "geometry": {"coordinates":[145.017456055,-37.9783973694],"type":"Point"}
}