{
  "type": "Feature",
  "properties": {
    "iso:country":"AU",
    "sg:address":"Shp12/ 2 The Crs",
    "sg:city":"Midland",
    "sg:classifiers":[
        {
            "category":"Food & Beverages",
            "subcategory":"Groceries & Convenience Stores",
            "type":"Retail Goods"
        }
    ],
    "sg:phone":"+61 8 9250 7635",
    "sg:postcode":"6056",
    "sg:province":"WA",
    "wof:name":"Filipino Oriental Store",
    "wof:placetype":"venue"
},
  "geometry": {"coordinates":[116.006408691,-31.8873844147],"type":"Point"}
}