{
  "type": "Feature",
  "properties": {
    "addr:full":"Kallangur Post Office Building, 1393 Anzac Ave Kallangur QLD 4503",
    "addr:housenumber":"1393",
    "addr:postcode":"4503",
    "addr:street":"Anzac Ave",
    "iso:country":"AU",
    "sg:address":"Kallangur Post Office Building, 1393 Anzac Ave",
    "sg:city":"Kallangur",
    "sg:classifiers":[
        {
            "category":"Professional",
            "subcategory":"Accounting & Tax Preparation",
            "type":"Services"
        }
    ],
    "sg:phone":"+61 7 3204 4000",
    "sg:postcode":"4503",
    "sg:province":"QLD",
    "sg:tags":[
        "accountant",
        "auditor"
    ],
    "wof:name":"Business Result Accountants",
    "wof:placetype":"venue"
},
  "geometry": {"coordinates":[152.99742126500001,-27.24958992],"type":"Point"}
}