{
  "type": "Feature",
  "properties": {
    "iso:country":"AU",
    "sg:address":"Lot 4 Roberts St",
    "sg:city":"Crookwell",
    "sg:classifiers":[
        {
            "category":"Retail",
            "subcategory":"Auto Repair",
            "type":"Services"
        }
    ],
    "sg:phone":"+61 2 4832 1042",
    "sg:postcode":"2583",
    "sg:province":"NSW",
    "sg:tags":[
        "repairer",
        "motor",
        "engineer"
    ],
    "wof:name":"Crookwell Car Care",
    "wof:placetype":"venue"
},
  "geometry": {"coordinates":[149.46791076700001,-34.4572601318],"type":"Point"}
}