{
  "type": "Feature",
  "properties": {
    "addr:full":"Welwyn Ave Shpng Cntr Cnr Welwyn Ave & Bradshaw Crs Manning WA 6152",
    "addr:postcode":"6152",
    "addr:street":"Welwyn Ave Shpng Cntr Cnr Welwyn Ave & Bradshaw Crs",
    "iso:country":"AU",
    "sg:address":"Welwyn Ave Shpng Cntr Cnr Welwyn Ave & Bradshaw Crs",
    "sg:city":"Manning",
    "sg:classifiers":[
        {
            "category":"Health Services",
            "subcategory":"Dentist",
            "type":"Services"
        }
    ],
    "sg:phone":"+61 8 9450 4440",
    "sg:postcode":"6152",
    "sg:province":"WA",
    "wof:name":"White R J",
    "wof:placetype":"venue"
},
  "geometry": {"coordinates":[115.868988,-32.015175],"type":"Point"}
}