{
  "type": "Feature",
  "properties": {
    "addr:full":"10 Lillian Crt Port Macquarie NSW 2444",
    "addr:housenumber":"10",
    "addr:postcode":"2444",
    "addr:street":"Lillian Crt",
    "iso:country":"AU",
    "sg:address":"10 Lillian Crt",
    "sg:city":"Port Macquarie",
    "sg:classifiers":[
        {
            "category":"Building & Trades",
            "subcategory":"Construction",
            "type":"Services"
        }
    ],
    "sg:phone":"+61 2 6582 0575",
    "sg:postcode":"2444",
    "sg:province":"NSW",
    "sg:tags":[
        "joiner",
        "carpenter"
    ],
    "wof:name":"Yeo P M & P",
    "wof:placetype":"venue"
},
  "geometry": {"coordinates":[152.915955,-31.474321],"type":"Point"}
}