{
  "type": "Feature",
  "properties": {
    "iso:country":"AU",
    "sg:address":"76 York St",
    "sg:city":"Launceston",
    "sg:classifiers":[
        {
            "category":"Professional",
            "subcategory":"Art Services",
            "type":"Services"
        }
    ],
    "sg:phone":"+61 438 317 709",
    "sg:postcode":"7250",
    "sg:province":"TAS",
    "sg:tags":[
        "graphic",
        "designer"
    ],
    "wof:name":"Imagen Design",
    "wof:placetype":"venue"
},
  "geometry": {"coordinates":[147.11753845199999,-41.4386177063],"type":"Point"}
}