{
  "type": "Feature",
  "properties": {
    "iso:country":"AU",
    "sg:address":"2 Eclipse St",
    "sg:city":"Chittaway Bay",
    "sg:classifiers":[
        {
            "category":"Health Services",
            "subcategory":"Health Practitioner",
            "type":"Services"
        }
    ],
    "sg:phone":"+61 2 4388 2152",
    "sg:postcode":"2261",
    "sg:province":"NSW",
    "sg:tags":[
        "bowen",
        "therapy"
    ],
    "wof:name":"Pat Quigley",
    "wof:placetype":"venue"
},
  "geometry": {"coordinates":[151.43362400000001,-33.328472],"type":"Point"}
}