{
  "type": "Feature",
  "properties": {
    "iso:country":"AU",
    "sg:address":"Shop 7 72 Simpson St",
    "sg:city":"Beerwah",
    "sg:classifiers":[
        {
            "category":"Personal",
            "subcategory":"Beauty Salon",
            "type":"Services"
        }
    ],
    "sg:phone":"+61 7 5494 6833",
    "sg:postcode":"4519",
    "sg:province":"QLD",
    "wof:name":"Rebecca Greensills",
    "wof:placetype":"venue"
},
  "geometry": {"coordinates":[152.957764,-26.858524],"type":"Point"}
}