{
  "type": "Feature",
  "properties": {
    "addr:full":"46 Justin St Smithfield NSW 2164",
    "addr:housenumber":"46",
    "addr:postcode":"2164",
    "addr:street":"Justin St",
    "iso:country":"AU",
    "sg:address":"46 Justin St",
    "sg:city":"Smithfield",
    "sg:classifiers":[
        {
            "category":"Wholesale",
            "subcategory":"Auto Parts",
            "type":"Manufacturing & Wholesale Goods"
        }
    ],
    "sg:phone":"+61 2 9725 5555",
    "sg:postcode":"2164",
    "sg:province":"NSW",
    "sg:tags":[
        "recyclers"
    ],
    "wof:name":"Maztel Auto Dismantlers",
    "wof:placetype":"venue"
},
  "geometry": {"coordinates":[150.93862915,-33.8508300781],"type":"Point"}
}