{
  "type": "Feature",
  "properties": {
    "addr:full":"51 Magee St Graceville QLD 4075",
    "addr:housenumber":"51",
    "addr:postcode":"4075",
    "addr:street":"Magee St",
    "iso:country":"AU",
    "sg:address":"51 Magee St",
    "sg:city":"Graceville",
    "sg:classifiers":[
        {
            "category":"Organizations",
            "subcategory":"Non-profit Organization",
            "type":"Services"
        }
    ],
    "sg:phone":"+61 7 3379 6021",
    "sg:postcode":"4075",
    "sg:province":"QLD",
    "sg:tags":[
        "environmental",
        "organisation",
        "conservation"
    ],
    "wof:name":"Oxley Creek Environment Group Inc",
    "wof:placetype":"venue"
},
  "geometry": {"coordinates":[152.983184814,-27.5237579346],"type":"Point"}
}