{
  "type": "Feature",
  "properties": {
    "iso:country":"AU",
    "sg:address":"45 New City Rd",
    "sg:city":"Mullumbimby",
    "sg:classifiers":[
        {
            "category":"Professional",
            "subcategory":"Art Services",
            "type":"Services"
        }
    ],
    "sg:phone":"+61 2 6684 1844",
    "sg:postcode":"2482",
    "sg:province":"NSW",
    "sg:tags":[
        "graphic",
        "designer"
    ],
    "wof:name":"Lucinda Cox Graphic Design",
    "wof:placetype":"venue"
},
  "geometry": {"coordinates":[153.50796508799999,-28.5556259155],"type":"Point"}
}