{
  "type": "Feature",
  "properties": {
    "addr:full":"11/ 13 Binney St Euroa VIC 3666",
    "addr:housenumber":"11 / 13",
    "addr:postcode":"3666",
    "addr:street":"Binney St",
    "iso:country":"AU",
    "sg:address":"11/ 13 Binney St",
    "sg:city":"Euroa",
    "sg:classifiers":[
        {
            "category":"Shopping",
            "type":"Retail Goods"
        }
    ],
    "sg:phone":"+61 3 5795 2535",
    "sg:postcode":"3666",
    "sg:province":"VIC",
    "sg:tags":[
        "agent",
        "stock"
    ],
    "wof:name":"Wesfarmers Landmark",
    "wof:placetype":"venue"
},
  "geometry": {"coordinates":[145.56959533700001,-36.7491340637],"type":"Point"}
}