{
  "type": "Feature",
  "properties": {
    "iso:country":"AU",
    "sg:address":"109 Howard Rd",
    "sg:city":"Goodwood",
    "sg:classifiers":[
        {
            "category":"Utilities",
            "type":"Services"
        }
    ],
    "sg:phone":"+61 3 6272 0066",
    "sg:postcode":"7010",
    "sg:province":"TAS",
    "sg:tags":[
        "refrigeration",
        "industrial",
        "commercial",
        "retail"
    ],
    "wof:name":"Christie & Wills Pty Ltd",
    "wof:placetype":"venue"
},
  "geometry": {"coordinates":[147.29702758799999,-42.8271903992],"type":"Point"}
}