{
  "type": "Feature",
  "properties": {
    "iso:country":"AU",
    "sg:address":"Unit 4 257 Grange Rd",
    "sg:city":"Ormond",
    "sg:classifiers":[
        {
            "category":"Shopping",
            "subcategory":"Musical Instruments",
            "type":"Retail Goods"
        }
    ],
    "sg:phone":"+61 3 9578 8014",
    "sg:postcode":"3204",
    "sg:province":"VIC",
    "sg:tags":[
        "musician",
        "agent"
    ],
    "wof:name":"Hawaiian Steel Guitar",
    "wof:placetype":"venue"
},
  "geometry": {"coordinates":[145.044571,-37.900356],"type":"Point"}
}