{
  "type": "Feature",
  "properties": {
    "addr:full":"80 Penshurst St Penshurst NSW 2222",
    "addr:housenumber":"80",
    "addr:postcode":"2222",
    "addr:street":"Penshurst St",
    "iso:country":"AU",
    "sg:address":"80 Penshurst St",
    "sg:city":"Penshurst",
    "sg:classifiers":[
        {
            "category":"Health Services",
            "subcategory":"Doctor",
            "type":"Services"
        }
    ],
    "sg:phone":"+61 2 9579 6777",
    "sg:postcode":"2222",
    "sg:province":"NSW",
    "sg:tags":[
        "medical",
        "practitioner"
    ],
    "wof:name":"Rose Alison",
    "wof:placetype":"venue"
},
  "geometry": {"coordinates":[151.087280273,-33.9637374878],"type":"Point"}
}