{
  "type": "Feature",
  "properties": {
    "addr:full":"Rear 74 Bowen St Malvern East VIC 3145",
    "addr:housenumber":"74",
    "addr:postcode":"3145",
    "addr:street":"Bowen St",
    "iso:country":"AU",
    "sg:address":"Rear 74 Bowen St",
    "sg:city":"Malvern East",
    "sg:classifiers":[
        {
            "category":"Social Services",
            "subcategory":"Child Care",
            "type":"Services"
        }
    ],
    "sg:phone":"+61 3 9569 9500",
    "sg:postcode":"3145",
    "sg:province":"VIC",
    "wof:name":"May Armstrong Child Care Centre",
    "wof:placetype":"venue"
},
  "geometry": {"coordinates":[145.078033447,-37.8813972473],"type":"Point"}
}