{
  "type": "Feature",
  "properties": {
    "iso:country":"AU",
    "sg:address":"Level 1/Suite 104 3 Chester St",
    "sg:city":"Oakleigh",
    "sg:classifiers":[
        {
            "category":"Professional",
            "subcategory":"Computer Services",
            "type":"Services"
        }
    ],
    "sg:phone":"+61 3 9530 9199",
    "sg:postcode":"3166",
    "sg:province":"VIC",
    "sg:tags":[
        "consultant",
        "system"
    ],
    "wof:name":"Vissoft Pty Ltd",
    "wof:placetype":"venue"
},
  "geometry": {"coordinates":[145.087646484,-37.8990859985],"type":"Point"}
}