{
  "type": "Feature",
  "properties": {
    "iso:country":"AU",
    "sg:address":"34 Kiln Rd",
    "sg:city":"Nowergup",
    "sg:classifiers":[
        {
            "category":"Farming",
            "subcategory":"Nursery",
            "type":"Manufacturing & Wholesale Goods"
        }
    ],
    "sg:phone":"+61 8 9407 5363",
    "sg:postcode":"6032",
    "sg:province":"WA",
    "wof:name":"Green Sprig",
    "wof:placetype":"venue"
},
  "geometry": {"coordinates":[115.729736328,-31.6199703217],"type":"Point"}
}