{
  "type": "Feature",
  "properties": {
    "addr:full":"Cnr Poinciana Ave & Moorindil St Tewantin QLD 4565",
    "addr:postcode":"4565",
    "addr:street":"Poinciana Ave & Moorindil St",
    "iso:country":"AU",
    "sg:address":"Cnr Poinciana Ave & Moorindil St",
    "sg:city":"Tewantin",
    "sg:classifiers":[
        {
            "category":"Banks & Credit Unions",
            "subcategory":"Bank",
            "type":"Services"
        }
    ],
    "sg:phone":"+61 7 5430 5420",
    "sg:postcode":"4565",
    "sg:province":"QLD",
    "sg:tags":[
        "broker",
        "mortgage"
    ],
    "wof:name":"Holmans Lending",
    "wof:placetype":"venue"
},
  "geometry": {"coordinates":[153.02911376899999,-26.390417099],"type":"Point"}
}