{
  "type": "Feature",
  "properties": {
    "iso:country":"AU",
    "sg:address":"2/ 23 Castle St",
    "sg:city":"Parramatta",
    "sg:classifiers":[
        {
            "category":"Retail",
            "subcategory":"Auto Rental",
            "type":"Services"
        }
    ],
    "sg:phone":"+61 2 9738 1590",
    "sg:postcode":"2124",
    "sg:province":"NSW",
    "sg:tags":[
        "car",
        "hire",
        "minibus"
    ],
    "wof:name":"All Seasons Car Rental",
    "wof:placetype":"venue"
},
  "geometry": {"coordinates":[151.00462341299999,-33.7981643677],"type":"Point"}
}