{
  "type": "Feature",
  "properties": {
    "iso:country":"AU",
    "sg:address":"PO Box 169",
    "sg:city":"Kingsgrove",
    "sg:classifiers":[
        {
            "category":"Retail",
            "subcategory":"Auto Repair",
            "type":"Services"
        }
    ],
    "sg:phone":"+61 2 9547 3677",
    "sg:postcode":"2208",
    "sg:province":"NSW",
    "sg:tags":[
        "repairer",
        "motor",
        "engineer"
    ],
    "wof:name":"EA Performance Pty Ltd",
    "wof:placetype":"venue"
},
  "geometry": {"coordinates":[151.098938,-33.93948],"type":"Point"}
}