{
  "type": "Feature",
  "properties": {
    "addr:full":"28 Wyndella St Launceston TAS 7250",
    "addr:housenumber":"28",
    "addr:postcode":"7250",
    "addr:street":"Wyndella St",
    "iso:country":"AU",
    "sg:address":"28 Wyndella St",
    "sg:city":"Launceston",
    "sg:classifiers":[
        {
            "category":"Home & Garden",
            "subcategory":"Household Appliances",
            "type":"Retail Goods"
        }
    ],
    "sg:phone":"+61 3 6326 6888",
    "sg:postcode":"7250",
    "sg:province":"TAS",
    "sg:tags":[
        "equipment",
        "gas"
    ],
    "wof:name":"Gaspower Tasmania Pty Ltd",
    "wof:placetype":"venue"
},
  "geometry": {"coordinates":[147.12869262699999,-41.4550437927],"type":"Point"}
}