{
  "type": "Feature",
  "properties": {
    "addr:full":"536 Peel St Tamworth NSW 2340",
    "addr:housenumber":"536",
    "addr:postcode":"2340",
    "addr:street":"Peel St",
    "iso:country":"AU",
    "sg:address":"536 Peel St",
    "sg:city":"Tamworth",
    "sg:classifiers":[
        {
            "category":"Building & Trades",
            "subcategory":"Landscaping Services",
            "type":"Services"
        }
    ],
    "sg:phone":"+61 2 6766 9622",
    "sg:postcode":"2340",
    "sg:province":"NSW",
    "sg:tags":[
        "consultant"
    ],
    "wof:name":"Cox Homes JIM",
    "wof:placetype":"venue"
},
  "geometry": {"coordinates":[150.93785095199999,-31.0991535187],"type":"Point"}
}