{
  "type": "Feature",
  "properties": {
    "iso:country":"AU",
    "sg:address":"PO Box 284",
    "sg:city":"Taree",
    "sg:classifiers":[
        {
            "category":"Building & Trades",
            "subcategory":"Cleaning & Sanitation",
            "type":"Services"
        }
    ],
    "sg:phone":"+61 409 563 309",
    "sg:postcode":"2430",
    "sg:province":"NSW",
    "sg:tags":[
        "asbestos",
        "treatment",
        "removal"
    ],
    "wof:name":"Absolute Demolitions Pty Limited",
    "wof:placetype":"venue"
},
  "geometry": {"coordinates":[152.46151699999999,-31.91313],"type":"Point"}
}