{
  "type": "Feature",
  "properties": {
    "iso:country":"AU",
    "sg:address":"116 Koornang Rd",
    "sg:city":"Carnegie",
    "sg:classifiers":[
        {
            "category":"Building & Trades",
            "subcategory":"Construction",
            "type":"Services"
        }
    ],
    "sg:phone":"+61 3 9569 7894",
    "sg:postcode":"3163",
    "sg:province":"VIC",
    "sg:tags":[
        "polishing",
        "sanding",
        "floor"
    ],
    "wof:name":"Kostralia Floor Care",
    "wof:placetype":"venue"
},
  "geometry": {"coordinates":[145.05741882300001,-37.8881912231],"type":"Point"}
}