{
  "type": "Feature",
  "properties": {
    "iso:country":"AU",
    "sg:address":"\"Haslemere\" RMB 4039 via Wodonga",
    "sg:city":"Mt Alfred",
    "sg:classifiers":[
        {
            "category":"Farming",
            "subcategory":"Farm",
            "type":"Manufacturing & Wholesale Goods"
        }
    ],
    "sg:phone":"+61 2 6037 6210",
    "sg:postcode":"3691",
    "sg:province":"VIC",
    "sg:tags":[
        "farmer"
    ],
    "wof:name":"Plant F N & W M",
    "wof:placetype":"venue"
},
  "geometry": {"coordinates":[146.894363,-36.1138],"type":"Point"}
}