{
  "type": "Feature",
  "properties": {
    "addr:full":"149 Stanley St Townsville QLD 4810",
    "addr:housenumber":"149",
    "addr:postcode":"4810",
    "addr:street":"Stanley St",
    "iso:country":"AU",
    "sg:address":"149 Stanley St",
    "sg:city":"Townsville",
    "sg:classifiers":[
        {
            "category":"Personal",
            "subcategory":"Beauty Salon",
            "type":"Services"
        }
    ],
    "sg:phone":"+61 7 4771 3188",
    "sg:postcode":"4810",
    "sg:province":"QLD",
    "sg:tags":[
        "hairdresser"
    ],
    "wof:name":"Riondino Hair Studio",
    "wof:placetype":"venue"
},
  "geometry": {"coordinates":[146.815414,-19.260992],"type":"Point"}
}