{
  "type": "Feature",
  "properties": {
    "iso:country":"AU",
    "sg:address":"Unit 1/ 19 Toupein Rd",
    "sg:city":"Yarrawonga",
    "sg:classifiers":[
        {
            "category":"Mining & Drilling",
            "type":"Manufacturing & Wholesale Goods"
        }
    ],
    "sg:phone":"+61 8 8931 2511",
    "sg:postcode":"0830",
    "sg:province":"NT",
    "sg:tags":[
        "equipment",
        "quarrying",
        "supply"
    ],
    "wof:name":"Mawpump",
    "wof:placetype":"venue"
},
  "geometry": {"coordinates":[130.98895300000001,-12.47191],"type":"Point"}
}