{
  "type": "Feature",
  "properties": {
    "addr:full":"210 High St Belmont VIC 3216",
    "addr:housenumber":"210",
    "addr:postcode":"3216",
    "addr:street":"High St",
    "iso:country":"AU",
    "sg:address":"210 High St",
    "sg:city":"Belmont",
    "sg:classifiers":[
        {
            "category":"Health Services",
            "subcategory":"Health Practitioner",
            "type":"Services"
        }
    ],
    "sg:phone":"+61 3 5243 9225",
    "sg:postcode":"3216",
    "sg:province":"VIC",
    "sg:tags":[
        "osteopath"
    ],
    "wof:name":"Lane Carrie",
    "wof:placetype":"venue"
},
  "geometry": {"coordinates":[144.34046935999999,-38.1770019531],"type":"Point"}
}