{
  "type": "Feature",
  "properties": {
    "addr:full":"30 Heilbronn Rd Jones Hill QLD 4570",
    "addr:housenumber":"30",
    "addr:postcode":"4570",
    "addr:street":"Heilbronn Rd",
    "iso:country":"AU",
    "sg:address":"30 Heilbronn Rd",
    "sg:city":"Jones Hill",
    "sg:classifiers":[
        {
            "category":"Retail",
            "subcategory":"Auto Rental",
            "type":"Services"
        }
    ],
    "sg:phone":"+61 7 5482 3358",
    "sg:postcode":"4570",
    "sg:province":"QLD",
    "sg:tags":[
        "car",
        "wedding"
    ],
    "wof:name":"Sunshine Carriages",
    "wof:placetype":"venue"
},
  "geometry": {"coordinates":[152.66680908199999,-26.2277450562],"type":"Point"}
}