{
  "type": "Feature",
  "properties": {
    "addr:full":"88 Spencer St Bunbury WA 6230",
    "addr:housenumber":"88",
    "addr:postcode":"6230",
    "addr:street":"Spencer St",
    "iso:country":"AU",
    "sg:address":"88 Spencer St",
    "sg:city":"Bunbury",
    "sg:classifiers":[
        {
            "category":"Banks & Credit Unions",
            "subcategory":"Financial Services",
            "type":"Services"
        }
    ],
    "sg:phone":"+61 8 9721 4422",
    "sg:postcode":"6230",
    "sg:province":"WA",
    "sg:tags":[
        "annuity",
        "rollover",
        "superannuation",
        "consultant"
    ],
    "wof:name":"Garvan Financial Planning",
    "wof:placetype":"venue"
},
  "geometry": {"coordinates":[115.64157899999999,-33.346638],"type":"Point"}
}