{
  "type": "Feature",
  "properties": {
    "addr:full":"5 Eva Crt Western Gardens VIC 3028",
    "addr:housenumber":"5",
    "addr:postcode":"3028",
    "addr:street":"Eva Crt",
    "iso:country":"AU",
    "sg:address":"5 Eva Crt",
    "sg:city":"Western Gardens",
    "sg:classifiers":[
        {
            "category":"Professional",
            "type":"Services"
        }
    ],
    "sg:phone":"+61 3 9327 8900",
    "sg:postcode":"3028",
    "sg:province":"VIC",
    "sg:tags":[
        "forwarding",
        "agent",
        "transport"
    ],
    "wof:name":"Latin Transport",
    "wof:placetype":"venue"
},
  "geometry": {"coordinates":[144.755188,-37.877048],"type":"Point"}
}