{
  "type": "Feature",
  "properties": {
    "addr:full":"253 Main North Rd Clare SA 5453",
    "addr:housenumber":"253",
    "addr:postcode":"5453",
    "addr:street":"Main North Rd",
    "iso:country":"AU",
    "sg:address":"253 Main North Rd",
    "sg:city":"Clare",
    "sg:classifiers":[
        {
            "category":"Government",
            "subcategory":"Post Office",
            "type":"Public Place"
        }
    ],
    "sg:phone":"+61 13 13 18",
    "sg:postcode":"5453",
    "sg:province":"SA",
    "sg:tags":[
        "postal"
    ],
    "wof:name":"Australia Post",
    "wof:placetype":"venue"
},
  "geometry": {"coordinates":[138.61134300000001,-33.832722],"type":"Point"}
}