{
  "type": "Feature",
  "properties": {
    "iso:country":"AU",
    "sg:address":"14 McCulloch St",
    "sg:city":"Bairnsdale",
    "sg:classifiers":[
        {
            "category":"Professional",
            "subcategory":"Accounting & Tax Preparation",
            "type":"Services"
        }
    ],
    "sg:phone":"+61 3 5152 6111",
    "sg:postcode":"3875",
    "sg:province":"VIC",
    "sg:tags":[
        "consultant",
        "taxation"
    ],
    "wof:name":"Buckingham Graeme. E",
    "wof:placetype":"venue"
},
  "geometry": {"coordinates":[147.622116089,-37.8214874268],"type":"Point"}
}