{
  "type": "Feature",
  "properties": {
    "addr:full":"Shop 7/ 455 Greenhill Rd Tusmore SA 5065",
    "addr:housenumber":"shop 7 / 455",
    "addr:postcode":"5065",
    "addr:street":"Greenhill Rd",
    "iso:country":"AU",
    "sg:address":"Shop 7/ 455 Greenhill Rd",
    "sg:city":"Tusmore",
    "sg:classifiers":[
        {
            "category":"Retail",
            "subcategory":"Veterinary Services",
            "type":"Services"
        }
    ],
    "sg:phone":"+61 8 8333 2666",
    "sg:postcode":"5065",
    "sg:province":"SA",
    "sg:tags":[
        "surgeon"
    ],
    "wof:name":"Devereux Veterinary Clinic",
    "wof:placetype":"venue"
},
  "geometry": {"coordinates":[138.65074157699999,-34.9386978149],"type":"Point"}
}