{
  "type": "Feature",
  "properties": {
    "addr:full":"34 Blucher St Strathfieldsaye VIC 3551",
    "addr:housenumber":"34",
    "addr:postcode":"3551",
    "addr:street":"Blucher St",
    "iso:country":"AU",
    "sg:address":"34 Blucher St",
    "sg:city":"Strathfieldsaye",
    "sg:classifiers":[
        {
            "category":"Health Services",
            "subcategory":"Doctor",
            "type":"Services"
        }
    ],
    "sg:phone":"+61 3 5439 4442",
    "sg:postcode":"3551",
    "sg:province":"VIC",
    "sg:tags":[
        "medical",
        "practitioner"
    ],
    "wof:name":"Saeed M. Dr",
    "wof:placetype":"venue"
},
  "geometry": {"coordinates":[144.35856628400001,-36.8059005737],"type":"Point"}
}