{
  "type": "Feature",
  "properties": {
    "iso:country":"AU",
    "sg:address":"264 Campbell St",
    "sg:city":"Swan Hill",
    "sg:classifiers":[
        {
            "category":"Personal",
            "subcategory":"Beauty Salon",
            "type":"Services"
        }
    ],
    "sg:phone":"+61 3 5032 1581",
    "sg:postcode":"3585",
    "sg:province":"VIC",
    "sg:tags":[
        "hairdresser"
    ],
    "wof:name":"Top Knot Hair & Beauty",
    "wof:placetype":"venue"
},
  "geometry": {"coordinates":[143.559845,-35.341156],"type":"Point"}
}