{
  "type": "Feature",
  "properties": {
    "iso:country":"AU",
    "sg:address":"42 Victoria St",
    "sg:city":"Robe",
    "sg:classifiers":[
        {
            "category":"Travel",
            "subcategory":"Hotels & Motels",
            "type":"Entertainment"
        }
    ],
    "sg:phone":"+61 8 8768 2001",
    "sg:postcode":"5276",
    "sg:province":"SA",
    "wof:name":"Guichen Bay Motel",
    "wof:placetype":"venue"
},
  "geometry": {"coordinates":[139.762085,-37.165363],"type":"Point"}
}