{
  "type": "Feature",
  "properties": {
    "iso:country":"AU",
    "sg:address":"U3/ 31 Oxleigh Drv",
    "sg:city":"Malaga",
    "sg:classifiers":[
        {
            "category":"Building & Trades",
            "subcategory":"Plumbing",
            "type":"Services"
        }
    ],
    "sg:phone":"+61 8 9249 4350",
    "sg:postcode":"6090",
    "sg:province":"WA",
    "sg:tags":[
        "plumber",
        "gasfitters"
    ],
    "wof:name":"Streamline Plumbing Pty Ltd",
    "wof:placetype":"venue"
},
  "geometry": {"coordinates":[115.885803223,-31.8501186371],"type":"Point"}
}