{
  "type": "Feature",
  "properties": {
    "iso:country":"AU",
    "sg:address":"1858 Bells Line Of Rd",
    "sg:city":"Kurrajong Heights",
    "sg:classifiers":[
        {
            "category":"Food & Beverages",
            "subcategory":"Bakery",
            "type":"Retail Goods"
        }
    ],
    "sg:phone":"+61 2 4567 8925",
    "sg:postcode":"2758",
    "sg:province":"NSW",
    "sg:tags":[
        "baker"
    ],
    "wof:name":"Divine Pies",
    "wof:placetype":"venue"
},
  "geometry": {"coordinates":[150.58099365199999,-33.5152664185],"type":"Point"}
}