{
  "type": "Feature",
  "properties": {
    "iso:country":"AU",
    "sg:address":"PO Box 4",
    "sg:city":"Kangarilla",
    "sg:classifiers":[
        {
            "category":"Travel",
            "subcategory":"Travel Agent",
            "type":"Entertainment"
        }
    ],
    "sg:phone":"+61 8 8383 7198",
    "sg:postcode":"5157",
    "sg:province":"SA",
    "sg:tags":[
        "tour",
        "holiday",
        "adventure"
    ],
    "wof:name":"Bogong Jack Adventures",
    "wof:placetype":"venue"
},
  "geometry": {"coordinates":[138.65745544399999,-35.148399353],"type":"Point"}
}