{
  "type": "Feature",
  "properties": {
    "iso:country":"AU",
    "sg:address":"173 Millers Rd",
    "sg:city":"Altona North",
    "sg:classifiers":[
        {
            "category":"Health Services",
            "subcategory":"Dentist",
            "type":"Services"
        }
    ],
    "sg:phone":"+61 3 9391 5174",
    "sg:postcode":"3025",
    "sg:province":"VIC",
    "wof:name":"Robertson J A McL",
    "wof:placetype":"venue"
},
  "geometry": {"coordinates":[144.84809899999999,-37.832859],"type":"Point"}
}