{
  "type": "Feature",
  "properties": {
    "addr:full":"160 Onslow Rd Shenton Park WA 6008",
    "addr:housenumber":"160",
    "addr:postcode":"6008",
    "addr:street":"Onslow Rd",
    "iso:country":"AU",
    "sg:address":"160 Onslow Rd",
    "sg:city":"Shenton Park",
    "sg:classifiers":[
        {
            "category":"Health Services",
            "subcategory":"Health Practitioner",
            "type":"Services"
        }
    ],
    "sg:phone":"+61 8 9388 2225",
    "sg:postcode":"6008",
    "sg:province":"WA",
    "sg:tags":[
        "alternative"
    ],
    "wof:name":"Shenton Park Chiropractic Centre",
    "wof:placetype":"venue"
},
  "geometry": {"coordinates":[115.813537598,-31.9607257843],"type":"Point"}
}