{
  "type": "Feature",
  "properties": {
    "addr:full":"1030 Burke Rd Balwyn VIC 3103",
    "addr:housenumber":"1030",
    "addr:postcode":"3103",
    "addr:street":"Burke Rd",
    "iso:country":"AU",
    "sg:address":"1030 Burke Rd",
    "sg:city":"Balwyn",
    "sg:classifiers":[
        {
            "category":"Food & Beverages",
            "subcategory":"Liquor & Beverages",
            "type":"Retail Goods"
        }
    ],
    "sg:phone":"+61 3 9817 2257",
    "sg:postcode":"3103",
    "sg:province":"VIC",
    "sg:tags":[
        "store"
    ],
    "wof:name":"Boccaccio Cellars Pty Ltd",
    "wof:placetype":"venue"
},
  "geometry": {"coordinates":[145.06251525900001,-37.8016624451],"type":"Point"}
}