{
  "type": "Feature",
  "properties": {
    "addr:full":"182 Roe St Northbridge WA 6003",
    "addr:housenumber":"182",
    "addr:postcode":"6003",
    "addr:street":"Roe St",
    "iso:country":"AU",
    "sg:address":"182 Roe St",
    "sg:city":"Northbridge",
    "sg:classifiers":[
        {
            "category":"Autos & Motor Vehicles",
            "subcategory":"Automobile Sales",
            "type":"Retail Goods"
        }
    ],
    "sg:phone":"+61 8 9227 7332",
    "sg:postcode":"6003",
    "sg:province":"WA",
    "sg:tags":[
        "car",
        "used"
    ],
    "wof:name":"Northbridge Auto Wholesale",
    "wof:placetype":"venue"
},
  "geometry": {"coordinates":[115.852111816,-31.9468746185],"type":"Point"}
}