{
  "type": "Feature",
  "properties": {
    "addr:full":"3/ 602 Wynnum Rd Morningside QLD 4170",
    "addr:housenumber":"/ 602",
    "addr:postcode":"4170",
    "addr:street":"Wynnum Rd",
    "iso:country":"AU",
    "sg:address":"3/ 602 Wynnum Rd",
    "sg:city":"Morningside",
    "sg:classifiers":[
        {
            "category":"Real Estate",
            "subcategory":"Real Estate Agent",
            "type":"Services"
        }
    ],
    "sg:phone":"+61 7 3399 5288",
    "sg:postcode":"4170",
    "sg:province":"QLD",
    "wof:name":"Local Agent.com.au",
    "wof:placetype":"venue"
},
  "geometry": {"coordinates":[153.07183837900001,-27.4684658051],"type":"Point"}
}