{
  "type": "Feature",
  "properties": {
    "iso:country":"AU",
    "sg:address":"24 Turnbull St",
    "sg:city":"Fennell Bay",
    "sg:classifiers":[
        {
            "category":"Shopping",
            "subcategory":"Pets & Pet Supplies",
            "type":"Retail Goods"
        }
    ],
    "sg:phone":"+61 2 4950 5238",
    "sg:postcode":"2283",
    "sg:province":"NSW",
    "sg:tags":[
        "food"
    ],
    "wof:name":"Greens Avian Supplies",
    "wof:placetype":"venue"
},
  "geometry": {"coordinates":[151.59486389200001,-32.9890327454],"type":"Point"}
}