{
  "type": "Feature",
  "properties": {
    "addr:full":"3 Distribution Ave Molendinar QLD 4214",
    "addr:housenumber":"3",
    "addr:postcode":"4214",
    "addr:street":"Distribution Ave",
    "iso:country":"AU",
    "sg:address":"3 Distribution Ave",
    "sg:city":"Molendinar",
    "sg:classifiers":[
        {
            "category":"Professional",
            "type":"Services"
        }
    ],
    "sg:phone":"+61 7 5564 7525",
    "sg:postcode":"4214",
    "sg:province":"QLD",
    "sg:tags":[
        "shop",
        "fitting"
    ],
    "sg:website":"http://www.xtremeshopfitting.com.au",
    "wof:name":"Xtreme Shopfitting & Joinery",
    "wof:placetype":"venue"
},
  "geometry": {"coordinates":[153.358917236,-27.976606369],"type":"Point"}
}