{
  "type": "Feature",
  "properties": {
    "iso:country":"AU",
    "sg:address":"33 Edward St",
    "sg:city":"Camden",
    "sg:classifiers":[
        {
            "category":"Retail",
            "subcategory":"Auto Repair",
            "type":"Services"
        }
    ],
    "sg:phone":"+61 2 4655 5000",
    "sg:postcode":"2570",
    "sg:province":"NSW",
    "sg:tags":[
        "repairer",
        "motor",
        "engineer"
    ],
    "wof:name":"Camden Holden",
    "wof:placetype":"venue"
},
  "geometry": {"coordinates":[150.69874572800001,-34.0521659851],"type":"Point"}
}