{
  "type": "Feature",
  "properties": {
    "addr:full":"22 Daniel Crt Warranwood VIC 3134",
    "addr:housenumber":"22",
    "addr:postcode":"3134",
    "addr:street":"Daniel Crt",
    "iso:country":"AU",
    "sg:address":"22 Daniel Crt",
    "sg:city":"Warranwood",
    "sg:classifiers":[
        {
            "category":"Building & Trades",
            "subcategory":"Construction",
            "type":"Services"
        }
    ],
    "sg:phone":"+61 3 9876 6573",
    "sg:postcode":"3134",
    "sg:province":"VIC",
    "sg:tags":[
        "stonework",
        "stone",
        "mason"
    ],
    "wof:name":"I G Parker",
    "wof:placetype":"venue"
},
  "geometry": {"coordinates":[145.24038696299999,-37.7788848877],"type":"Point"}
}