{
  "type": "Feature",
  "properties": {
    "addr:full":"139A South Rd Ridleyton SA 5008",
    "addr:housenumber":"139a",
    "addr:postcode":"5008",
    "addr:street":"South Rd",
    "iso:country":"AU",
    "sg:address":"139A South Rd",
    "sg:city":"Ridleyton",
    "sg:classifiers":[
        {
            "category":"Wholesale",
            "subcategory":"Vending Machines",
            "type":"Manufacturing & Wholesale Goods"
        }
    ],
    "sg:phone":"+61 8 8346 2940",
    "sg:postcode":"5008",
    "sg:province":"SA",
    "sg:tags":[
        "engraving",
        "accessory"
    ],
    "wof:name":"Tek Cad & Cam Systems",
    "wof:placetype":"venue"
},
  "geometry": {"coordinates":[138.56961100000001,-34.890583],"type":"Point"}
}