{
  "type": "Feature",
  "properties": {
    "addr:full":"2/ 31 Expansion St Molendinar QLD 4214",
    "addr:housenumber":"/ 31",
    "addr:postcode":"4214",
    "addr:street":"Expansion St",
    "iso:country":"AU",
    "sg:address":"2/ 31 Expansion St",
    "sg:city":"Molendinar",
    "sg:classifiers":[
        {
            "category":"Home & Garden",
            "subcategory":"Building Materials",
            "type":"Retail Goods"
        }
    ],
    "sg:phone":"+61 7 5539 5567",
    "sg:postcode":"4214",
    "sg:province":"QLD",
    "sg:tags":[
        "gate"
    ],
    "wof:name":"Ken Milne Fencing & Landscaping",
    "wof:placetype":"venue"
},
  "geometry": {"coordinates":[153.35655212399999,-27.9777145386],"type":"Point"}
}