{
  "type": "Feature",
  "properties": {
    "iso:country":"AU",
    "sg:address":"629 High Street Rd",
    "sg:city":"Syndal",
    "sg:classifiers":[
        {
            "category":"Professional",
            "subcategory":"Advertising",
            "type":"Services"
        }
    ],
    "sg:phone":"+61 3 9887 9433",
    "sg:postcode":"3149",
    "sg:province":"VIC",
    "sg:tags":[
        "balloon",
        "novelty"
    ],
    "wof:name":"The Balloon Specialists",
    "wof:placetype":"venue"
},
  "geometry": {"coordinates":[145.147903442,-37.8719863892],"type":"Point"}
}