{
  "type": "Feature",
  "properties": {
    "addr:full":"1 Grafton St Blacktown NSW 2148",
    "addr:housenumber":"1",
    "addr:postcode":"2148",
    "addr:street":"Grafton St",
    "iso:country":"AU",
    "sg:address":"1 Grafton St",
    "sg:city":"Blacktown",
    "sg:classifiers":[
        {
            "category":"Health Services",
            "subcategory":"Doctor",
            "type":"Services"
        }
    ],
    "sg:phone":"+61 2 9622 1680",
    "sg:postcode":"2148",
    "sg:province":"NSW",
    "sg:tags":[
        "medical",
        "practitioner"
    ],
    "wof:name":"Mobbs Dr G A",
    "wof:placetype":"venue"
},
  "geometry": {"coordinates":[150.91409301799999,-33.7735977173],"type":"Point"}
}