{
  "type": "Feature",
  "properties": {
    "iso:country":"AU",
    "sg:address":"168 Curlewis St",
    "sg:city":"Swan Hill",
    "sg:classifiers":[
        {
            "category":"Retail",
            "subcategory":"Funeral Services",
            "type":"Services"
        }
    ],
    "sg:phone":"+61 3 5033 1066",
    "sg:postcode":"3585",
    "sg:province":"VIC",
    "sg:tags":[
        "cremation"
    ],
    "wof:name":"Funerals Lorraine Taverna Swan Hill & Districts",
    "wof:placetype":"venue"
},
  "geometry": {"coordinates":[143.56242399999999,-35.344345],"type":"Point"}
}