{
  "type": "Feature",
  "properties": {
    "addr:full":"Unit 1/ 11 Gateway Blv Morisset NSW 2264",
    "addr:postcode":"2264",
    "addr:street":"Gateway Blv",
    "iso:country":"AU",
    "sg:address":"Unit 1/ 11 Gateway Blv",
    "sg:city":"Morisset",
    "sg:classifiers":[
        {
            "category":"Autos & Motor Vehicles",
            "subcategory":"Auto Supplies",
            "type":"Retail Goods"
        }
    ],
    "sg:phone":"+61 2 4973 5050",
    "sg:postcode":"2264",
    "sg:province":"NSW",
    "sg:tags":[
        "tyre"
    ],
    "wof:name":"Affordable Tyres",
    "wof:placetype":"venue"
},
  "geometry": {"coordinates":[151.471405,-33.117031],"type":"Point"}
}