{
  "type": "Feature",
  "properties": {
    "addr:full":"132 Coogee Bay Rd Coogee NSW 2034",
    "addr:housenumber":"132",
    "addr:postcode":"2034",
    "addr:street":"Coogee Bay Rd",
    "iso:country":"AU",
    "sg:address":"132 Coogee Bay Rd",
    "sg:city":"Coogee",
    "sg:classifiers":[
        {
            "category":"Fast Food",
            "type":"Food & Drink"
        }
    ],
    "sg:phone":"+61 2 9665 0033",
    "sg:postcode":"2034",
    "sg:province":"NSW",
    "sg:tags":[
        "away",
        "take"
    ],
    "wof:name":"Jack's Pizzas",
    "wof:placetype":"venue"
},
  "geometry": {"coordinates":[151.25103759800001,-33.9198379517],"type":"Point"}
}