{
  "type": "Feature",
  "properties": {
    "addr:full":"19 Young St Adelaide SA 5000",
    "addr:housenumber":"19",
    "addr:postcode":"5000",
    "addr:street":"Young St",
    "iso:country":"AU",
    "sg:address":"19 Young St",
    "sg:city":"Adelaide",
    "sg:classifiers":[
        {
            "category":"Professional",
            "subcategory":"Computer Services",
            "type":"Services"
        }
    ],
    "sg:phone":"+61 1300 555 345",
    "sg:postcode":"5000",
    "sg:province":"SA",
    "sg:tags":[
        "training"
    ],
    "wof:name":"Mad Academy",
    "wof:placetype":"venue"
},
  "geometry": {"coordinates":[138.59591674800001,-34.9265785217],"type":"Point"}
}