{
  "type": "Feature",
  "properties": {
    "addr:full":"PO Box 3249 Erina NSW 2250",
    "addr:postcode":"2250",
    "iso:country":"AU",
    "sg:address":"PO Box 3249",
    "sg:city":"Erina",
    "sg:classifiers":[
        {
            "category":"Real Estate",
            "subcategory":"Real Estate Operator",
            "type":"Services"
        }
    ],
    "sg:phone":"+61 409 854 714",
    "sg:postcode":"2250",
    "sg:province":"NSW",
    "sg:tags":[
        "concrete",
        "pumping"
    ],
    "wof:name":"Allcoast Concrete Pump Hire",
    "wof:placetype":"venue"
},
  "geometry": {"coordinates":[151.395217895,-33.4346389771],"type":"Point"}
}