{
  "type": "Feature",
  "properties": {
    "iso:country":"AU",
    "sg:address":"320 Warrigal Rd",
    "sg:city":"Glen Iris",
    "sg:classifiers":[
        {
            "category":"Health Services",
            "subcategory":"Doctor",
            "type":"Services"
        }
    ],
    "sg:phone":"+61 3 9808 8855",
    "sg:postcode":"3146",
    "sg:province":"VIC",
    "sg:tags":[
        "medical",
        "practitioner"
    ],
    "wof:name":"Clinic of Wholistic & Complementary Medicine, The",
    "wof:placetype":"venue"
},
  "geometry": {"coordinates":[145.09393310600001,-37.858833313],"type":"Point"}
}