{
  "type": "Feature",
  "properties": {
    "iso:country":"AU",
    "sg:address":"13 William St",
    "sg:city":"Beaudesert",
    "sg:classifiers":[
        {
            "category":"Food & Beverages",
            "subcategory":"Bakery",
            "type":"Retail Goods"
        }
    ],
    "sg:phone":"+61 7 5541 1065",
    "sg:postcode":"4285",
    "sg:province":"QLD",
    "sg:tags":[
        "baker"
    ],
    "wof:name":"Beaudesert Bakery",
    "wof:placetype":"venue"
},
  "geometry": {"coordinates":[152.996475,-27.988392],"type":"Point"}
}