{
  "type": "Feature",
  "properties": {
    "addr:full":"340 Balcombe Rd Beaumaris VIC 3193",
    "addr:housenumber":"340",
    "addr:postcode":"3193",
    "addr:street":"Balcombe Rd",
    "iso:country":"AU",
    "sg:address":"340 Balcombe Rd",
    "sg:city":"Beaumaris",
    "sg:classifiers":[
        {
            "category":"Cafe",
            "type":"Food & Drink"
        }
    ],
    "sg:phone":"+61 3 9589 4474",
    "sg:postcode":"3193",
    "sg:province":"VIC",
    "wof:name":"Harvest Fare",
    "wof:placetype":"venue"
},
  "geometry": {"coordinates":[145.045974731,-37.9788284302],"type":"Point"}
}