{
  "type": "Feature",
  "properties": {
    "iso:country":"AU",
    "sg:address":"Bradbury Rd",
    "sg:city":"Hamilton Hill",
    "sg:classifiers":[
        {
            "category":"Education",
            "subcategory":"School",
            "type":"Public Place"
        }
    ],
    "sg:phone":"+61 8 9337 1410",
    "sg:postcode":"6163",
    "sg:province":"WA",
    "sg:tags":[
        "state",
        "except",
        "nsw"
    ],
    "wof:name":"East Hamilton Hill Primary School",
    "wof:placetype":"venue"
},
  "geometry": {"coordinates":[115.786369,-32.07674],"type":"Point"}
}