{
  "type": "Feature",
  "properties": {
    "addr:full":"Bradbury Rd Hamilton Hill WA 6163",
    "addr:postcode":"6163",
    "addr:street":"Bradbury Rd",
    "iso:country":"AU",
    "sg:address":"Bradbury Rd",
    "sg:city":"Hamilton Hill",
    "sg:classifiers":[
        {
            "category":"Education",
            "subcategory":"School",
            "type":"Public Place"
        }
    ],
    "sg:phone":"+61 8 9337 1410",
    "sg:postcode":"6163",
    "sg:province":"WA",
    "sg:tags":[
        "state",
        "except",
        "nsw"
    ],
    "wof:name":"East Hamilton Hill Primary School",
    "wof:placetype":"venue"
},
  "geometry": {"coordinates":[115.78636899999999,-32.07674],"type":"Point"}
}