{
  "type": "Feature",
  "properties": {
    "addr:full":"207 Yarra St Warrandyte VIC 3113",
    "addr:housenumber":"207",
    "addr:postcode":"3113",
    "addr:street":"Yarra St",
    "iso:country":"AU",
    "sg:address":"207 Yarra St",
    "sg:city":"Warrandyte",
    "sg:classifiers":[
        {
            "category":"Home & Garden",
            "subcategory":"Home Furnishings",
            "type":"Retail Goods"
        }
    ],
    "sg:phone":"+61 3 9844 3011",
    "sg:postcode":"3113",
    "sg:province":"VIC",
    "sg:tags":[
        "candle"
    ],
    "wof:name":"Scandles World Of Candles",
    "wof:placetype":"venue"
},
  "geometry": {"coordinates":[145.22137451200001,-37.7367477417],"type":"Point"}
}