{
  "type": "Feature",
  "properties": {
    "addr:full":"332 Smith St Collingwood VIC 3066",
    "addr:housenumber":"332",
    "addr:postcode":"3066",
    "addr:street":"Smith St",
    "iso:country":"AU",
    "sg:address":"332 Smith St",
    "sg:city":"Collingwood",
    "sg:classifiers":[
        {
            "category":"Shopping",
            "subcategory":"Pawn Shop",
            "type":"Retail Goods"
        }
    ],
    "sg:phone":"+61 3 9417 4053",
    "sg:postcode":"3066",
    "sg:province":"VIC",
    "sg:tags":[
        "pawnbroker"
    ],
    "wof:name":"Cash Express Loan Company",
    "wof:placetype":"venue"
},
  "geometry": {"coordinates":[144.984375,-37.7992286682],"type":"Point"}
}