{
  "type": "Feature",
  "properties": {
    "addr:full":"16 Derby Rd Kanwal NSW 2259",
    "addr:housenumber":"16",
    "addr:postcode":"2259",
    "addr:street":"Derby Rd",
    "iso:country":"AU",
    "sg:address":"16 Derby Rd",
    "sg:city":"Kanwal",
    "sg:classifiers":[
        {
            "category":"Building & Trades",
            "subcategory":"Construction",
            "type":"Services"
        }
    ],
    "sg:phone":"+61 2 9831 7111",
    "sg:postcode":"2259",
    "sg:province":"NSW",
    "sg:tags":[
        "contractor"
    ],
    "wof:name":"Grovewood Homes",
    "wof:placetype":"venue"
},
  "geometry": {"coordinates":[151.487457275,-33.2568969727],"type":"Point"}
}