{
  "type": "Feature",
  "properties": {
    "addr:full":"Shp216/ 152 Bunnerong Rd Pagewood NSW 2035",
    "addr:housenumber":"152",
    "addr:postcode":"2035",
    "addr:street":"Bunnerong Rd",
    "iso:country":"AU",
    "sg:address":"Shp216/ 152 Bunnerong Rd",
    "sg:city":"Pagewood",
    "sg:classifiers":[
        {
            "category":"Shopping",
            "subcategory":"Jewelry",
            "type":"Retail Goods"
        }
    ],
    "sg:phone":"+61 2 9349 3902",
    "sg:postcode":"2035",
    "sg:province":"NSW",
    "sg:tags":[
        "jeweller"
    ],
    "wof:name":"Chloe Hart",
    "wof:placetype":"venue"
},
  "geometry": {"coordinates":[151.226486206,-33.9449501038],"type":"Point"}
}