{
  "type": "Feature",
  "properties": {
    "iso:country":"AU",
    "sg:address":"Unit 1/ 34 Furniss Rd",
    "sg:city":"Landsdale",
    "sg:classifiers":[
        {
            "category":"Professional",
            "subcategory":"Accounting & Tax Preparation",
            "type":"Services"
        }
    ],
    "sg:phone":"+61 8 9302 2828",
    "sg:postcode":"6065",
    "sg:province":"WA",
    "sg:tags":[
        "insulation",
        "wholesaler",
        "material",
        "mfrs"
    ],
    "sg:website":"http://www.mrinsulation.com.au",
    "wof:name":"Mr Insulation",
    "wof:placetype":"venue"
},
  "geometry": {"coordinates":[115.845169067,-31.8046665192],"type":"Point"}
}