{
  "type": "Feature",
  "properties": {
    "addr:full":"35 Industrial Drv Braeside VIC 3195",
    "addr:housenumber":"35",
    "addr:postcode":"3195",
    "addr:street":"Industrial Drv",
    "iso:country":"AU",
    "sg:address":"35 Industrial Drv",
    "sg:city":"Braeside",
    "sg:classifiers":[
        {
            "category":"Autos & Motor Vehicles",
            "subcategory":"Auto Supplies",
            "type":"Retail Goods"
        }
    ],
    "sg:phone":"+61 3 9580 5912",
    "sg:postcode":"3195",
    "sg:province":"VIC",
    "sg:tags":[
        "wheel",
        "automotive",
        "rim"
    ],
    "wof:name":"Stonestar Engineering Pty Ltd",
    "wof:placetype":"venue"
},
  "geometry": {"coordinates":[145.11119079599999,-38.0052528381],"type":"Point"}
}