{
  "type": "Feature",
  "properties": {
    "addr:full":"47 Tile St Wacol QLD 4076",
    "addr:housenumber":"47",
    "addr:postcode":"4076",
    "addr:street":"Tile St",
    "iso:country":"AU",
    "sg:address":"47 Tile St",
    "sg:city":"Wacol",
    "sg:classifiers":[
        {
            "category":"Manufacturing",
            "subcategory":"Retail Goods",
            "type":"Manufacturing & Wholesale Goods"
        }
    ],
    "sg:phone":"+61 7 3879 3335",
    "sg:postcode":"4076",
    "sg:province":"QLD",
    "sg:tags":[
        "merchant",
        "pump",
        "mfrs"
    ],
    "wof:name":"Austral Pumps",
    "wof:placetype":"venue"
},
  "geometry": {"coordinates":[152.93365478499999,-27.6044006348],"type":"Point"}
}