{
  "type": "Feature",
  "properties": {
    "iso:country":"AU",
    "sg:address":"Level 13, 30 Collins St",
    "sg:city":"Melbourne",
    "sg:classifiers":[
        {
            "category":"Professional",
            "subcategory":"Management & Consulting",
            "type":"Services"
        }
    ],
    "sg:phone":"+61 3 9639 9722",
    "sg:postcode":"3000",
    "sg:province":"VIC",
    "sg:tags":[
        "consultant",
        "relocation"
    ],
    "wof:name":"Global Immigration Services",
    "wof:placetype":"venue"
},
  "geometry": {"coordinates":[144.97265625,-37.8135528564],"type":"Point"}
}