{
  "type": "Feature",
  "properties": {
    "iso:country":"AU",
    "sg:address":"42 Salters Rd",
    "sg:city":"Wilberforce",
    "sg:classifiers":[
        {
            "category":"Shopping Center",
            "type":"Public Place"
        }
    ],
    "sg:phone":"+61 2 4575 1305",
    "sg:postcode":"2756",
    "sg:province":"NSW",
    "sg:tags":[
        "spawn",
        "supplier",
        "mushroom"
    ],
    "wof:name":"Snow White Mushrooms",
    "wof:placetype":"venue"
},
  "geometry": {"coordinates":[150.84991455100001,-33.5467758179],"type":"Point"}
}