{
  "type": "Feature",
  "properties": {
    "iso:country":"AU",
    "sg:address":"650 Nerang Southport Rd",
    "sg:city":"Ashmore",
    "sg:classifiers":[
        {
            "category":"Banks & Credit Unions",
            "subcategory":"Investment Brokerage",
            "type":"Services"
        }
    ],
    "sg:phone":"+61 7 5539 4726",
    "sg:postcode":"4214",
    "sg:province":"QLD",
    "sg:tags":[
        "shutter",
        "louvre"
    ],
    "sg:website":"http://www.victoryshutters.com",
    "wof:name":"Jireh Shutters",
    "wof:placetype":"venue"
},
  "geometry": {"coordinates":[153.339111328,-27.9881858826],"type":"Point"}
}