{
  "type": "Feature",
  "properties": {
    "iso:country":"AU",
    "sg:address":"PO Box 5233",
    "sg:city":"Prestons",
    "sg:classifiers":[
        {
            "category":"Professional",
            "subcategory":"Art Services",
            "type":"Services"
        }
    ],
    "sg:phone":"+61 2 9607 0149",
    "sg:postcode":"2170",
    "sg:province":"NSW",
    "sg:tags":[
        "graphic",
        "designer"
    ],
    "wof:name":"Tamlyn Creative",
    "wof:placetype":"venue"
},
  "geometry": {"coordinates":[150.86526489299999,-33.9515686035],"type":"Point"}
}