{
  "type": "Feature",
  "properties": {
    "iso:country":"AU",
    "sg:address":"2 Meenan St",
    "sg:city":"Garbutt",
    "sg:classifiers":[
        {
            "category":"Wholesale",
            "subcategory":"Painting Supplies",
            "type":"Manufacturing & Wholesale Goods"
        }
    ],
    "sg:phone":"+61 7 4779 5433",
    "sg:postcode":"4814",
    "sg:province":"QLD",
    "sg:tags":[
        "product",
        "cleaning"
    ],
    "wof:name":"OATESCLEAN",
    "wof:placetype":"venue"
},
  "geometry": {"coordinates":[146.774521,-19.264774],"type":"Point"}
}