{
  "type": "Feature",
  "properties": {
    "iso:country":"AU",
    "sg:address":"PO Box 725",
    "sg:city":"Hervey Bay",
    "sg:classifiers":[
        {
            "category":"Building & Trades",
            "subcategory":"Construction",
            "type":"Services"
        }
    ],
    "sg:phone":"+61 7 4124 1330",
    "sg:postcode":"4655",
    "sg:province":"QLD",
    "sg:tags":[
        "renovation",
        "alterations",
        "extension",
        "contractor"
    ],
    "wof:name":"Hedges Construction",
    "wof:placetype":"venue"
},
  "geometry": {"coordinates":[152.838257,-25.287661],"type":"Point"}
}