{
  "type": "Feature",
  "properties": {
    "iso:country":"AU",
    "sg:address":"32 The Promenade, King St",
    "sg:city":"Wharf 5, Sydney",
    "sg:classifiers":[
        {
            "category":"Recreation",
            "subcategory":"Boat Charter",
            "type":"Entertainment"
        }
    ],
    "sg:phone":"+61 2 8296 7222",
    "sg:postcode":"2000",
    "sg:province":"NSW",
    "wof:name":"Magistic Cruises",
    "wof:placetype":"venue"
},
  "geometry": {"coordinates":[151.20994567899999,-33.8690834045],"type":"Point"}
}