{
  "type": "Feature",
  "properties": {
    "addr:full":"62 Koetong Pde Mt Eliza VIC 3930",
    "addr:housenumber":"62",
    "addr:postcode":"3930",
    "addr:street":"Koetong Pde",
    "iso:country":"AU",
    "sg:address":"62 Koetong Pde",
    "sg:city":"Mt Eliza",
    "sg:classifiers":[
        {
            "category":"Retail",
            "subcategory":"Repair Shop",
            "type":"Services"
        }
    ],
    "sg:phone":"+61 413 994 740",
    "sg:postcode":"3930",
    "sg:province":"VIC",
    "sg:tags":[
        "maintenance",
        "pool",
        "swimming"
    ],
    "wof:name":"Aqua Pool Cleaning",
    "wof:placetype":"venue"
},
  "geometry": {"coordinates":[145.08424377399999,-38.1928749084],"type":"Point"}
}