{
  "type": "Feature",
  "properties": {
    "iso:country":"AU",
    "sg:address":"51 Gaine Rd",
    "sg:city":"Dandenong South",
    "sg:classifiers":[
        {
            "category":"Manufacturing",
            "subcategory":"Metals",
            "type":"Manufacturing & Wholesale Goods"
        }
    ],
    "sg:phone":"+61 3 9702 9544",
    "sg:postcode":"3175",
    "sg:province":"VIC",
    "sg:tags":[
        "sheet",
        "worker"
    ],
    "wof:name":"Custom Sheet Metal",
    "wof:placetype":"venue"
},
  "geometry": {"coordinates":[145.241424561,-38.0340270996],"type":"Point"}
}