{
  "type": "Feature",
  "properties": {
    "addr:full":"185 Rocky Point Rd Ramsgate NSW 2217",
    "addr:housenumber":"185",
    "addr:postcode":"2217",
    "addr:street":"Rocky Point Rd",
    "iso:country":"AU",
    "sg:address":"185 Rocky Point Rd",
    "sg:city":"Ramsgate",
    "sg:classifiers":[
        {
            "category":"Personal",
            "type":"Services"
        }
    ],
    "sg:phone":"+61 2 9529 7922",
    "sg:postcode":"2217",
    "sg:province":"NSW",
    "sg:tags":[
        "dressmaker"
    ],
    "wof:name":"Lynne Tallar Dressmakers",
    "wof:placetype":"venue"
},
  "geometry": {"coordinates":[151.13627600000001,-33.983482],"type":"Point"}
}