{
  "type": "Feature",
  "properties": {
    "iso:country":"AU",
    "sg:address":"14 Adam St",
    "sg:city":"Wynnum",
    "sg:classifiers":[
        {
            "category":"Travel",
            "subcategory":"Hotels & Motels",
            "type":"Entertainment"
        }
    ],
    "sg:phone":"+61 7 3396 3037",
    "sg:postcode":"4178",
    "sg:province":"QLD",
    "wof:name":"Anchor Motel",
    "wof:placetype":"venue"
},
  "geometry": {"coordinates":[153.17146301299999,-27.433637619],"type":"Point"}
}