{
  "type": "Feature",
  "properties": {
    "iso:country":"AU",
    "sg:address":"17 Eighth Ave",
    "sg:city":"Campsie",
    "sg:classifiers":[
        {
            "category":"Building & Trades",
            "subcategory":"Plumbing",
            "type":"Services"
        }
    ],
    "sg:phone":"+61 414 949 314",
    "sg:postcode":"2194",
    "sg:province":"NSW",
    "sg:tags":[
        "plumber",
        "gasfitters"
    ],
    "wof:name":"Sublime Plumbing Contractors",
    "wof:placetype":"venue"
},
  "geometry": {"coordinates":[151.101776,-33.906281],"type":"Point"}
}