{
  "type": "Feature",
  "properties": {
    "addr:full":"312 Falcon St Neutral Bay NSW 2089",
    "addr:housenumber":"312",
    "addr:postcode":"2089",
    "addr:street":"Falcon St",
    "iso:country":"AU",
    "sg:address":"312 Falcon St",
    "sg:city":"Neutral Bay",
    "sg:classifiers":[
        {
            "category":"Autos & Motor Vehicles",
            "subcategory":"Automobile Sales",
            "type":"Retail Goods"
        }
    ],
    "sg:phone":"+61 2 9953 1100",
    "sg:postcode":"2089",
    "sg:province":"NSW",
    "sg:tags":[
        "car",
        "used"
    ],
    "wof:name":"Neutral Bay Motors",
    "wof:placetype":"venue"
},
  "geometry": {"coordinates":[151.216995239,-33.8299331665],"type":"Point"}
}