{
  "type": "Feature",
  "properties": {
    "iso:country":"AU",
    "sg:address":"88 Beach Rd",
    "sg:city":"Christies Beach",
    "sg:classifiers":[
        {
            "category":"Personal",
            "subcategory":"Beauty Salon",
            "type":"Services"
        }
    ],
    "sg:phone":"+61 8 8186 1233",
    "sg:postcode":"5165",
    "sg:province":"SA",
    "wof:name":"Give Me Five Nail & Beauty",
    "wof:placetype":"venue"
},
  "geometry": {"coordinates":[138.479736328,-35.139125824],"type":"Point"}
}