{
  "type": "Feature",
  "properties": {
    "addr:full":"5 Westmoreland Ave Collaroy NSW 2097",
    "addr:housenumber":"5",
    "addr:postcode":"2097",
    "addr:street":"Westmoreland Ave",
    "iso:country":"AU",
    "sg:address":"5 Westmoreland Ave",
    "sg:city":"Collaroy",
    "sg:classifiers":[
        {
            "category":"Building & Trades",
            "subcategory":"Construction",
            "type":"Services"
        }
    ],
    "sg:phone":"+61 412 875 699",
    "sg:postcode":"2097",
    "sg:province":"NSW",
    "sg:tags":[
        "contractor"
    ],
    "wof:name":"Behagg W A",
    "wof:placetype":"venue"
},
  "geometry": {"coordinates":[151.29612731899999,-33.7435798645],"type":"Point"}
}