{
  "type": "Feature",
  "properties": {
    "addr:full":"1/ 19 Redcliffe Gardens Drv Clontarf QLD 4019",
    "addr:housenumber":"/ 19",
    "addr:postcode":"4019",
    "addr:street":"Redcliffe Gardens Drv",
    "iso:country":"AU",
    "sg:address":"1/ 19 Redcliffe Gardens Drv",
    "sg:city":"Clontarf",
    "sg:classifiers":[
        {
            "category":"Autos & Motor Vehicles",
            "subcategory":"Auto Supplies",
            "type":"Retail Goods"
        }
    ],
    "sg:phone":"+61 7 3883 3311",
    "sg:postcode":"4019",
    "sg:province":"QLD",
    "sg:tags":[
        "accessory"
    ],
    "wof:name":"Peninsula Auto Spares",
    "wof:placetype":"venue"
},
  "geometry": {"coordinates":[153.082473755,-27.2592506409],"type":"Point"}
}