{
  "type": "Feature",
  "properties": {
    "iso:country":"AU",
    "sg:address":"3 Hawke Crs",
    "sg:city":"Salisbury East",
    "sg:classifiers":[
        {
            "category":"Building & Trades",
            "subcategory":"Cleaning & Sanitation",
            "type":"Services"
        }
    ],
    "sg:phone":"+61 419 856 230",
    "sg:postcode":"5109",
    "sg:province":"SA",
    "sg:tags":[
        "cleaner",
        "repairer",
        "roof"
    ],
    "wof:name":"A & S Charles Roof Plumbing",
    "wof:placetype":"venue"
},
  "geometry": {"coordinates":[138.65983581500001,-34.7865409851],"type":"Point"}
}