{
  "type": "Feature",
  "properties": {
    "iso:country":"AU",
    "sg:address":"215 Lake St",
    "sg:city":"Cairns",
    "sg:classifiers":[
        {
            "category":"Travel",
            "subcategory":"Hotels & Motels",
            "type":"Entertainment"
        }
    ],
    "sg:phone":"+61 7 4051 9922",
    "sg:postcode":"4870",
    "sg:province":"QLD",
    "wof:name":"The Balinese Motel",
    "wof:placetype":"venue"
},
  "geometry": {"coordinates":[145.76889038100001,-16.9141674042],"type":"Point"}
}