{
  "type": "Feature",
  "properties": {
    "addr:full":"Cnr Camford & Douglas Sts Milton QLD 4064",
    "addr:postcode":"4064",
    "addr:street":"Cnr Camford & Douglas Sts",
    "iso:country":"AU",
    "sg:address":"Cnr Camford & Douglas Sts",
    "sg:city":"Milton",
    "sg:classifiers":[
        {
            "category":"Professional",
            "subcategory":"Computer Services",
            "type":"Services"
        }
    ],
    "sg:phone":"+61 7 3369 5866",
    "sg:postcode":"4064",
    "sg:province":"QLD",
    "sg:tags":[
        "consultant",
        "system"
    ],
    "wof:name":"Informed Sources Developments Pty Ltd",
    "wof:placetype":"venue"
},
  "geometry": {"coordinates":[153.00335693400001,-27.4717903137],"type":"Point"}
}