{
  "type": "Feature",
  "properties": {
    "addr:full":"46 Riley Rd Kardinya WA 6163",
    "addr:housenumber":"46",
    "addr:postcode":"6163",
    "addr:street":"Riley Rd",
    "iso:country":"AU",
    "sg:address":"46 Riley Rd",
    "sg:city":"Kardinya",
    "sg:classifiers":[
        {
            "category":"Building & Trades",
            "subcategory":"Landscaping Services",
            "type":"Services"
        }
    ],
    "sg:phone":"+61 8 9331 3031",
    "sg:postcode":"6163",
    "sg:province":"WA",
    "sg:tags":[
        "inspection"
    ],
    "wof:name":"Building & Home Inspection Service",
    "wof:placetype":"venue"
},
  "geometry": {"coordinates":[115.806557,-32.064083],"type":"Point"}
}