{
  "type": "Feature",
  "properties": {
    "iso:country":"AU",
    "sg:address":"Unit 3, 1119 Pittwater Rd",
    "sg:city":"Collaroy",
    "sg:classifiers":[
        {
            "category":"Professional",
            "subcategory":"Accounting & Tax Preparation",
            "type":"Services"
        }
    ],
    "sg:phone":"+61 2 9981 3700",
    "sg:postcode":"2097",
    "sg:province":"NSW",
    "sg:tags":[
        "consultant",
        "taxation"
    ],
    "wof:name":"Ross Accountability",
    "wof:placetype":"venue"
},
  "geometry": {"coordinates":[151.301071167,-33.7322731018],"type":"Point"}
}