{
  "type": "Feature",
  "properties": {
    "iso:country":"AU",
    "sg:address":"394- 396 Bridge Rd",
    "sg:city":"Richmond",
    "sg:classifiers":[
        {
            "category":"Restaurant",
            "type":"Food & Drink"
        }
    ],
    "sg:phone":"+61 3 9428 6455",
    "sg:postcode":"3121",
    "sg:province":"VIC",
    "sg:website":"http://www.curryclubcafe.com.au",
    "wof:name":"The Curry Club",
    "wof:placetype":"venue"
},
  "geometry": {"coordinates":[145.00462341299999,-37.8192176819],"type":"Point"}
}