{
  "type": "Feature",
  "properties": {
    "addr:full":"7- 9 Pearson St Wagga Wagga NSW 2650",
    "addr:housenumber":"9",
    "addr:postcode":"2650",
    "addr:street":"Pearson St",
    "iso:country":"AU",
    "sg:address":"7- 9 Pearson St",
    "sg:city":"Wagga Wagga",
    "sg:classifiers":[
        {
            "category":"Building & Trades",
            "subcategory":"Construction",
            "type":"Services"
        }
    ],
    "sg:phone":"+61 2 6925 2815",
    "sg:postcode":"2650",
    "sg:province":"NSW",
    "sg:tags":[
        "welding"
    ],
    "wof:name":"Harper D. G. Pty Ltd",
    "wof:placetype":"venue"
},
  "geometry": {"coordinates":[147.34393310600001,-35.1236610413],"type":"Point"}
}