{
  "type": "Feature",
  "properties": {
    "addr:full":"26 Coach Rd Auldana SA 5072",
    "addr:housenumber":"26",
    "addr:postcode":"5072",
    "addr:street":"Coach Rd",
    "iso:country":"AU",
    "sg:address":"26 Coach Rd",
    "sg:city":"Auldana",
    "sg:classifiers":[
        {
            "category":"Building & Trades",
            "subcategory":"Locksmith",
            "type":"Services"
        }
    ],
    "sg:phone":"+61 8 8364 4108",
    "sg:postcode":"5072",
    "sg:province":"SA",
    "sg:tags":[
        "lock"
    ],
    "wof:name":"Hignett B P",
    "wof:placetype":"venue"
},
  "geometry": {"coordinates":[138.68391418499999,-34.9226303101],"type":"Point"}
}