{
  "type": "Feature",
  "properties": {
    "iso:country":"AU",
    "sg:address":"68 - 72 York St",
    "sg:city":"South Melbourne",
    "sg:classifiers":[
        {
            "category":"Professional",
            "subcategory":"Computer Services",
            "type":"Services"
        }
    ],
    "sg:phone":"+61 3 9001 0699",
    "sg:postcode":"3205",
    "sg:province":"VIC",
    "sg:tags":[
        "equipment",
        "networking",
        "installation"
    ],
    "wof:name":"Sable Systems",
    "wof:placetype":"venue"
},
  "geometry": {"coordinates":[144.959885,-37.830547],"type":"Point"}
}