{
  "type": "Feature",
  "properties": {
    "addr:full":"Unit 10/ 10 Kennedy St Kingston ACT 2604",
    "addr:housenumber":"/ 10",
    "addr:postcode":"2604",
    "addr:street":"Kennedy St",
    "iso:country":"AU",
    "sg:address":"Unit 10/ 10 Kennedy St",
    "sg:city":"Kingston",
    "sg:classifiers":[
        {
            "category":"Insurance",
            "subcategory":"Life Insurance",
            "type":"Services"
        }
    ],
    "sg:phone":"+61 2 6239 4811",
    "sg:postcode":"2604",
    "sg:province":"ACT",
    "wof:name":"Andrew Leonard Financial Services",
    "wof:placetype":"venue"
},
  "geometry": {"coordinates":[149.14074707,-35.316696167],"type":"Point"}
}