{
  "type": "Feature",
  "properties": {
    "addr:full":"16a Gregory St Sandy Bay TAS 7005",
    "addr:housenumber":"16a",
    "addr:postcode":"7005",
    "addr:street":"Gregory St",
    "iso:country":"AU",
    "sg:address":"16a Gregory St",
    "sg:city":"Sandy Bay",
    "sg:classifiers":[
        {
            "category":"Shopping",
            "subcategory":"Clothing, Apparel, & Fashions",
            "type":"Retail Goods"
        }
    ],
    "sg:phone":"+61 3 6224 2555",
    "sg:postcode":"7005",
    "sg:province":"TAS",
    "sg:tags":[
        "menswear"
    ],
    "wof:name":"Soundy Menswear",
    "wof:placetype":"venue"
},
  "geometry": {"coordinates":[147.32774352999999,-42.8947639465],"type":"Point"}
}