{
  "type": "Feature",
  "properties": {
    "iso:country":"AU",
    "sg:address":"U6/ 1a Sandown Rd",
    "sg:city":"Ascot Vale",
    "sg:classifiers":[
        {
            "category":"Building & Trades",
            "subcategory":"Construction",
            "type":"Services"
        }
    ],
    "sg:phone":"+61 3 9372 2600",
    "sg:postcode":"3032",
    "sg:province":"VIC",
    "sg:tags":[
        "contractor"
    ],
    "wof:name":"In Line Home Builders Pty Ltd",
    "wof:placetype":"venue"
},
  "geometry": {"coordinates":[144.921921,-37.783062],"type":"Point"}
}