{
  "type": "Feature",
  "properties": {
    "iso:country":"AU",
    "sg:address":"55 Norseman Rd",
    "sg:city":"Esperance",
    "sg:classifiers":[
        {
            "category":"Autos & Motor Vehicles",
            "subcategory":"Auto Supplies",
            "type":"Retail Goods"
        }
    ],
    "sg:phone":"+61 8 9071 1378",
    "sg:postcode":"6450",
    "sg:province":"WA",
    "sg:tags":[
        "camper-trailers",
        "caravan",
        "equipment"
    ],
    "wof:name":"Esperance Caravan And Camping Centre",
    "wof:placetype":"venue"
},
  "geometry": {"coordinates":[121.90003967299999,-33.8442306519],"type":"Point"}
}