{
  "type": "Feature",
  "properties": {
    "addr:full":"42 Aberford St Coonamble NSW 2829",
    "addr:housenumber":"42",
    "addr:postcode":"2829",
    "addr:street":"Aberford St",
    "iso:country":"AU",
    "sg:address":"42 Aberford St",
    "sg:city":"Coonamble",
    "sg:classifiers":[
        {
            "category":"Home & Garden",
            "subcategory":"Carpets & Floor Coverings",
            "type":"Retail Goods"
        }
    ],
    "sg:phone":"+61 2 6822 1409",
    "sg:postcode":"2829",
    "sg:province":"NSW",
    "wof:name":"Murray's Floorcoverings",
    "wof:placetype":"venue"
},
  "geometry": {"coordinates":[148.38937377900001,-30.9542713165],"type":"Point"}
}