{
  "type": "Feature",
  "properties": {
    "addr:full":"9 Lomond St Glen Iris VIC 3146",
    "addr:housenumber":"9",
    "addr:postcode":"3146",
    "addr:street":"Lomond St",
    "iso:country":"AU",
    "sg:address":"9 Lomond St",
    "sg:city":"Glen Iris",
    "sg:classifiers":[
        {
            "category":"Wholesale",
            "subcategory":"Medical Equipment & Supplies",
            "type":"Manufacturing & Wholesale Goods"
        }
    ],
    "sg:phone":"+61 3 9809 2920",
    "sg:postcode":"3146",
    "sg:province":"VIC",
    "sg:tags":[
        "aid",
        "care",
        "health",
        "home"
    ],
    "wof:name":"Wan Wheelchairs Pty Ltd",
    "wof:placetype":"venue"
},
  "geometry": {"coordinates":[145.06132507300001,-37.8504142761],"type":"Point"}
}