{
  "type": "Feature",
  "properties": {
    "iso:country":"AU",
    "sg:address":"2 Ralton Ave",
    "sg:city":"Glen Waverley",
    "sg:classifiers":[
        {
            "category":"Military Area",
            "subcategory":"Air Force Base",
            "type":"Public Place"
        }
    ],
    "sg:phone":"+61 3 9560 1573",
    "sg:postcode":"3150",
    "sg:province":"VIC",
    "sg:tags":[
        "fibre",
        "optic"
    ],
    "wof:name":"Future Fibre Technologies Pty Ltd",
    "wof:placetype":"venue"
},
  "geometry": {"coordinates":[145.171340942,-37.8861579895],"type":"Point"}
}