{
  "type": "Feature",
  "properties": {
    "addr:full":"928 Ingham Rd Bohle QLD 4818",
    "addr:housenumber":"928",
    "addr:postcode":"4818",
    "addr:street":"Ingham Rd",
    "iso:country":"AU",
    "sg:address":"928 Ingham Rd",
    "sg:city":"Bohle",
    "sg:classifiers":[
        {
            "category":"Autos & Motor Vehicles",
            "subcategory":"Boat Sales",
            "type":"Retail Goods"
        }
    ],
    "sg:phone":"+61 7 4774 7211",
    "sg:postcode":"4818",
    "sg:province":"QLD",
    "sg:tags":[
        "builder",
        "yacht",
        "repairer"
    ],
    "wof:name":"Turncraft Marine",
    "wof:placetype":"venue"
},
  "geometry": {"coordinates":[146.712524,-19.26251],"type":"Point"}
}