{
  "type": "Feature",
  "properties": {
    "addr:full":"28 The Mall Darwin NT 0800",
    "addr:housenumber":"28",
    "addr:postcode":"nt 0800",
    "addr:street":"The Mall",
    "iso:country":"AU",
    "sg:address":"28 The Mall",
    "sg:city":"Darwin",
    "sg:classifiers":[
        {
            "category":"Personal",
            "subcategory":"Beauty Salon",
            "type":"Services"
        }
    ],
    "sg:phone":"+61 8 8981 4141",
    "sg:postcode":"0800",
    "sg:province":"NT",
    "wof:name":"Natural Beauty",
    "wof:placetype":"venue"
},
  "geometry": {"coordinates":[130.84251403799999,-12.4638319016],"type":"Point"}
}