{
  "type": "Feature",
  "properties": {
    "addr:full":"14a Sea Breeze Pl Boambee NSW 2450",
    "addr:housenumber":"14a",
    "addr:postcode":"2450",
    "addr:street":"Sea;Pl",
    "iso:country":"AU",
    "sg:address":"14a Sea Breeze Pl",
    "sg:city":"Boambee",
    "sg:classifiers":[
        {
            "category":"Health Services",
            "subcategory":"Health Practitioner",
            "type":"Services"
        }
    ],
    "sg:phone":"+61 2 6658 2919",
    "sg:postcode":"2450",
    "sg:province":"NSW",
    "sg:tags":[
        "naturopath"
    ],
    "wof:name":"Pendlington Gail M",
    "wof:placetype":"venue"
},
  "geometry": {"coordinates":[153.06629899999999,-30.35236],"type":"Point"}
}