{
  "type": "Feature",
  "properties": {
    "iso:country":"AU",
    "sg:address":"Hurley St",
    "sg:city":"Coffs Harbour",
    "sg:classifiers":[
        {
            "category":"Retail",
            "subcategory":"Repair Shop",
            "type":"Services"
        }
    ],
    "sg:phone":"+61 2 6652 2713",
    "sg:postcode":"2450",
    "sg:province":"NSW",
    "sg:tags":[
        "repairing",
        "piano",
        "tuning"
    ],
    "wof:name":"Fox Reuben",
    "wof:placetype":"venue"
},
  "geometry": {"coordinates":[153.100967,-30.30884],"type":"Point"}
}