{
  "type": "Feature",
  "properties": {
    "addr:full":"44 Spring St Maryborough VIC 3465",
    "addr:housenumber":"44",
    "addr:postcode":"3465",
    "addr:street":"Spring St",
    "iso:country":"AU",
    "sg:address":"44 Spring St",
    "sg:city":"Maryborough",
    "sg:classifiers":[
        {
            "category":"Professional",
            "subcategory":"Engineering",
            "type":"Services"
        }
    ],
    "sg:phone":"+61 3 5460 5775",
    "sg:postcode":"3465",
    "sg:province":"VIC",
    "sg:tags":[
        "engineer"
    ],
    "wof:name":"Carters Engineering & Maintenance Service",
    "wof:placetype":"venue"
},
  "geometry": {"coordinates":[143.75442504899999,-37.0445823669],"type":"Point"}
}