{
  "type": "Feature",
  "properties": {
    "addr:full":"34 Orchid Ave Surfers Paradise QLD 4217",
    "addr:housenumber":"34",
    "addr:postcode":"4217",
    "addr:street":"Orchid Ave",
    "iso:country":"AU",
    "sg:address":"34 Orchid Ave",
    "sg:city":"Surfers Paradise",
    "sg:classifiers":[
        {
            "category":"Shopping",
            "subcategory":"Jewelry",
            "type":"Retail Goods"
        }
    ],
    "sg:phone":"+61 7 5539 9096",
    "sg:postcode":"4217",
    "sg:province":"QLD",
    "sg:tags":[
        "merchant",
        "gem"
    ],
    "wof:name":"Miura Gems Pty Ltd",
    "wof:placetype":"venue"
},
  "geometry": {"coordinates":[153.42930602999999,-27.999502182],"type":"Point"}
}