{
  "type": "Feature",
  "properties": {
    "iso:country":"AU",
    "sg:address":"1/ 19 School Rd",
    "sg:city":"Mt Tamborine",
    "sg:classifiers":[
        {
            "category":"Education",
            "subcategory":"School",
            "type":"Public Place"
        }
    ],
    "sg:phone":"+61 7 5545 7666",
    "sg:postcode":"4272",
    "sg:province":"QLD",
    "sg:tags":[
        "state",
        "except",
        "nsw"
    ],
    "wof:name":"St Bernard Primary School",
    "wof:placetype":"venue"
},
  "geometry": {"coordinates":[153.198165894,-27.9709396362],"type":"Point"}
}