{
  "type": "Feature",
  "properties": {
    "iso:country":"AU",
    "sg:address":"27 Maren St",
    "sg:city":"Edmonton",
    "sg:classifiers":[
        {
            "category":"Utilities",
            "subcategory":"Electric",
            "type":"Services"
        }
    ],
    "sg:phone":"+61 418 183 193",
    "sg:postcode":"4869",
    "sg:province":"QLD",
    "sg:tags":[
        "electrical",
        "contractor"
    ],
    "wof:name":"Remote Electrics",
    "wof:placetype":"venue"
},
  "geometry": {"coordinates":[145.74101257300001,-17.0316238403],"type":"Point"}
}