{
  "type": "Feature",
  "properties": {
    "addr:full":"287C Old Northern Rd Castle Hill NSW 2154",
    "addr:housenumber":"287c",
    "addr:postcode":"2154",
    "addr:street":"Old Northern Rd",
    "iso:country":"AU",
    "sg:address":"287C Old Northern Rd",
    "sg:city":"Castle Hill",
    "sg:classifiers":[
        {
            "category":"Banks & Credit Unions",
            "subcategory":"Financial Services",
            "type":"Services"
        }
    ],
    "sg:phone":"+61 2 9899 4466",
    "sg:postcode":"2154",
    "sg:province":"NSW",
    "sg:tags":[
        "loan",
        "finance",
        "mortgage"
    ],
    "wof:name":"Mortgage House Of Australia",
    "wof:placetype":"venue"
},
  "geometry": {"coordinates":[151.00526428200001,-33.7328834534],"type":"Point"}
}