{
  "type": "Feature",
  "properties": {
    "iso:country":"AU",
    "sg:address":"Suite 5/256- 258 Anson St",
    "sg:city":"Orange",
    "sg:classifiers":[
        {
            "category":"Health Services",
            "subcategory":"Doctor",
            "type":"Services"
        }
    ],
    "sg:phone":"+61 2 6362 8038",
    "sg:postcode":"2800",
    "sg:province":"NSW",
    "sg:tags":[
        "medical",
        "practitioner"
    ],
    "wof:name":"Lauren Vein Centre",
    "wof:placetype":"venue"
},
  "geometry": {"coordinates":[149.09950256400001,-33.2803649902],"type":"Point"}
}