{
  "type": "Feature",
  "properties": {
    "addr:full":"Shop 3/ 424 Gympie Rd Strathpine QLD 4500",
    "addr:housenumber":"shop 3 / 424",
    "addr:postcode":"4500",
    "addr:street":"Gympie Rd",
    "iso:country":"AU",
    "sg:address":"Shop 3/ 424 Gympie Rd",
    "sg:city":"Strathpine",
    "sg:classifiers":[
        {
            "category":"Shopping",
            "subcategory":"Music",
            "type":"Retail Goods"
        }
    ],
    "sg:phone":"+61 7 3889 7499",
    "sg:postcode":"4500",
    "sg:province":"QLD",
    "sg:tags":[
        "instrument",
        "musical"
    ],
    "wof:name":"Arties Music Max",
    "wof:placetype":"venue"
},
  "geometry": {"coordinates":[152.98843383799999,-27.3024711609],"type":"Point"}
}