{
  "type": "Feature",
  "properties": {
    "addr:full":"14a McMillan Rd Narooma NSW 2546",
    "addr:housenumber":"14a",
    "addr:postcode":"2546",
    "addr:street":"Mcmillan Rd",
    "iso:country":"AU",
    "sg:address":"14a McMillan Rd",
    "sg:city":"Narooma",
    "sg:classifiers":[
        {
            "category":"Utilities",
            "subcategory":"Electric",
            "type":"Services"
        }
    ],
    "sg:phone":"+61 408 693 436",
    "sg:postcode":"2546",
    "sg:province":"NSW",
    "sg:tags":[
        "electrical",
        "contractor"
    ],
    "wof:name":"French Connection",
    "wof:placetype":"venue"
},
  "geometry": {"coordinates":[150.12672424300001,-36.2183761597],"type":"Point"}
}