{
  "type": "Feature",
  "properties": {
    "addr:full":"Unit 2/ 3 Chapman St Blackwood SA 5051",
    "addr:housenumber":"3",
    "addr:postcode":"5051",
    "addr:street":"Chapman St",
    "iso:country":"AU",
    "sg:address":"Unit 2/ 3 Chapman St",
    "sg:city":"Blackwood",
    "sg:classifiers":[
        {
            "category":"Professional",
            "subcategory":"Employment Agencies",
            "type":"Services"
        }
    ],
    "sg:phone":"+61 8 8370 3260",
    "sg:postcode":"5051",
    "sg:province":"SA",
    "sg:tags":[
        "entertainer",
        "agent"
    ],
    "wof:name":"Pianists Galore",
    "wof:placetype":"venue"
},
  "geometry": {"coordinates":[138.61596700000001,-35.016907],"type":"Point"}
}