{
  "type": "Feature",
  "properties": {
    "addr:full":"3 Colorado Crt Morphett Vale SA 5162",
    "addr:housenumber":"3",
    "addr:postcode":"5162",
    "addr:street":"Colorado Crt",
    "iso:country":"AU",
    "sg:address":"3 Colorado Crt",
    "sg:city":"Morphett Vale",
    "sg:classifiers":[
        {
            "category":"Manufacturing",
            "subcategory":"Paper Products",
            "type":"Manufacturing & Wholesale Goods"
        }
    ],
    "sg:phone":"+61 8 8387 7777",
    "sg:postcode":"5162",
    "sg:province":"SA",
    "sg:tags":[
        "disposable"
    ],
    "wof:name":"Milestone Chemicals Pty Ltd",
    "wof:placetype":"venue"
},
  "geometry": {"coordinates":[138.547149658,-35.1101493835],"type":"Point"}
}