{
  "type": "Feature",
  "properties": {
    "addr:full":"Shp3/ 66-92 Main St Croydon VIC 3136",
    "addr:housenumber":"66-92",
    "addr:postcode":"3136",
    "addr:street":"Main St",
    "iso:country":"AU",
    "sg:address":"Shp3/ 66-92 Main St",
    "sg:city":"Croydon",
    "sg:classifiers":[
        {
            "category":"Personal",
            "subcategory":"Nail Salon",
            "type":"Services"
        }
    ],
    "sg:phone":"+61 3 9725 4121",
    "sg:postcode":"3136",
    "sg:province":"VIC",
    "sg:tags":[
        "artificial"
    ],
    "wof:name":"Painted Nail The",
    "wof:placetype":"venue"
},
  "geometry": {"coordinates":[145.280807495,-37.7980995178],"type":"Point"}
}