{
  "type": "Feature",
  "properties": {
    "iso:country":"AU",
    "sg:address":"58 MacKenzie St",
    "sg:city":"Wondai",
    "sg:classifiers":[
        {
            "category":"Travel",
            "subcategory":"Hotels & Motels",
            "type":"Entertainment"
        }
    ],
    "sg:phone":"+61 7 4168 5460",
    "sg:postcode":"4606",
    "sg:province":"QLD",
    "sg:tags":[
        "accommodation"
    ],
    "wof:name":"Hotel Cecil",
    "wof:placetype":"venue"
},
  "geometry": {"coordinates":[151.87413,-26.318172],"type":"Point"}
}