{
  "type": "Feature",
  "properties": {
    "addr:full":"28 Reid Ave Tranmere SA 5073",
    "addr:housenumber":"28",
    "addr:postcode":"5073",
    "addr:street":"Reid Ave",
    "iso:country":"AU",
    "sg:address":"28 Reid Ave",
    "sg:city":"Tranmere",
    "sg:classifiers":[
        {
            "category":"Farming",
            "subcategory":"Farm & Veterinary Services",
            "type":"Manufacturing & Wholesale Goods"
        }
    ],
    "sg:phone":"+61 8 8337 0630",
    "sg:postcode":"5073",
    "sg:province":"SA",
    "sg:tags":[
        "poultry",
        "processing",
        "supply"
    ],
    "wof:name":"Forest Poultry Products",
    "wof:placetype":"venue"
},
  "geometry": {"coordinates":[138.66012573200001,-34.8974914551],"type":"Point"}
}