{
  "type": "Feature",
  "properties": {
    "addr:full":"Channel Hwy Middleton TAS 7163",
    "addr:postcode":"7163",
    "addr:street":"Channel Hwy",
    "iso:country":"AU",
    "sg:address":"Channel Hwy",
    "sg:city":"Middleton",
    "sg:classifiers":[
        {
            "category":"Government",
            "subcategory":"Post Office",
            "type":"Public Place"
        }
    ],
    "sg:phone":"+61 3 6292 1638",
    "sg:postcode":"7163",
    "sg:province":"TAS",
    "sg:tags":[
        "postal"
    ],
    "wof:name":"Australia Post Offices",
    "wof:placetype":"venue"
},
  "geometry": {"coordinates":[147.25042724599999,-43.2332839966],"type":"Point"}
}