{
  "type": "Feature",
  "properties": {
    "iso:country":"AU",
    "sg:address":"Cnr Kildare Rd & Macquarie St",
    "sg:city":"Blacktown",
    "sg:classifiers":[
        {
            "category":"Health Services",
            "subcategory":"Health Practitioner",
            "type":"Services"
        }
    ],
    "sg:phone":"+61 2 9831 2433",
    "sg:postcode":"2148",
    "sg:province":"NSW",
    "sg:tags":[
        "physiotherapist"
    ],
    "wof:name":"McKerihan M",
    "wof:placetype":"venue"
},
  "geometry": {"coordinates":[150.898681641,-33.7698402405],"type":"Point"}
}