{
  "type": "Feature",
  "properties": {
    "addr:full":"179-181 Brisbane Rd Mooloolaba QLD 4557",
    "addr:housenumber":"179-181",
    "addr:postcode":"4557",
    "addr:street":"Brisbane Rd",
    "iso:country":"AU",
    "sg:address":"179-181 Brisbane Rd",
    "sg:city":"Mooloolaba",
    "sg:classifiers":[
        {
            "category":"Communications",
            "subcategory":"Film & Video Production",
            "type":"Services"
        }
    ],
    "sg:phone":"+61 7 5478 3877",
    "sg:postcode":"4557",
    "sg:province":"QLD",
    "sg:tags":[
        "dvd",
        "library"
    ],
    "wof:name":"Blockbuster Video",
    "wof:placetype":"venue"
},
  "geometry": {"coordinates":[153.11528015100001,-26.6919822693],"type":"Point"}
}