{
  "type": "Feature",
  "properties": {
    "iso:country":"AU",
    "sg:address":"59 Pound Rd",
    "sg:city":"Warrandyte",
    "sg:classifiers":[
        {
            "category":"Health Services",
            "subcategory":"Health Practitioner",
            "type":"Services"
        }
    ],
    "sg:phone":"+61 3 9458 2781",
    "sg:postcode":"3113",
    "sg:province":"VIC",
    "sg:tags":[
        "hypnotherapy"
    ],
    "wof:name":"Victorian College Of Clinical Hypnotherapy",
    "wof:placetype":"venue"
},
  "geometry": {"coordinates":[145.198654175,-37.7432289124],"type":"Point"}
}