{
  "type": "Feature",
  "properties": {
    "addr:full":"21 Shoalhaven St Wakeley NSW 2176",
    "addr:housenumber":"21",
    "addr:postcode":"2176",
    "addr:street":"Shoalhaven St",
    "iso:country":"AU",
    "sg:address":"21 Shoalhaven St",
    "sg:city":"Wakeley",
    "sg:classifiers":[
        {
            "category":"Retail",
            "subcategory":"Driving School",
            "type":"Services"
        }
    ],
    "sg:phone":"+61 2 9757 3860",
    "sg:postcode":"2176",
    "sg:province":"NSW",
    "wof:name":"Highway Driving School",
    "wof:placetype":"venue"
},
  "geometry": {"coordinates":[150.912200928,-33.8700942993],"type":"Point"}
}