{
  "type": "Feature",
  "properties": {
    "addr:full":"29 Carlisle St Hughesdale VIC 3166",
    "addr:housenumber":"29",
    "addr:postcode":"3166",
    "addr:street":"Carlisle St",
    "iso:country":"AU",
    "sg:address":"29 Carlisle St",
    "sg:city":"Hughesdale",
    "sg:classifiers":[
        {
            "category":"Building & Trades",
            "subcategory":"Landscaping Services",
            "type":"Services"
        }
    ],
    "sg:phone":"+61 3 9569 0943",
    "sg:postcode":"3166",
    "sg:province":"VIC",
    "sg:tags":[
        "gardener"
    ],
    "wof:name":"Gardens That Grow",
    "wof:placetype":"venue"
},
  "geometry": {"coordinates":[145.07951355,-37.8969650269],"type":"Point"}
}