{
  "type": "Feature",
  "properties": {
    "addr:full":"Suite 202 11-15 Falcon St Crows Nest NSW 2065",
    "addr:housenumber":"11-15",
    "addr:postcode":"2065",
    "addr:street":"Falcon St",
    "iso:country":"AU",
    "sg:address":"Suite 202 11-15 Falcon St",
    "sg:city":"Crows Nest",
    "sg:classifiers":[
        {
            "category":"Sports & Exercise",
            "subcategory":"Gym",
            "type":"Entertainment"
        }
    ],
    "sg:phone":"+61 2 9438 2299",
    "sg:postcode":"2065",
    "sg:province":"NSW",
    "sg:tags":[
        "personal",
        "trainer",
        "fitness"
    ],
    "wof:name":"Human Engineering",
    "wof:placetype":"venue"
},
  "geometry": {"coordinates":[151.19985961899999,-33.8219032288],"type":"Point"}
}