{
  "type": "Feature",
  "properties": {
    "addr:full":"7/ 197 Springvale Rd Nunawading VIC 3131",
    "addr:housenumber":"/ 197",
    "addr:postcode":"3131",
    "addr:street":"Springvale Rd",
    "iso:country":"AU",
    "sg:address":"7/ 197 Springvale Rd",
    "sg:city":"Nunawading",
    "sg:classifiers":[
        {
            "category":"Personal",
            "subcategory":"Beauty Salon",
            "type":"Services"
        }
    ],
    "sg:phone":"+61 3 9878 9265",
    "sg:postcode":"3131",
    "sg:province":"VIC",
    "wof:name":"Ella Bache Nunawading",
    "wof:placetype":"venue"
},
  "geometry": {"coordinates":[145.17564392099999,-37.8218193054],"type":"Point"}
}