{
  "type": "Feature",
  "properties": {
    "addr:full":"301 Cranbourne-Frankston Rd Langwarrin VIC 3910",
    "addr:housenumber":"301",
    "addr:postcode":"3910",
    "addr:street":"Cranbourne-Frankston Rd",
    "iso:country":"AU",
    "sg:address":"301 Cranbourne-Frankston Rd",
    "sg:city":"Langwarrin",
    "sg:classifiers":[
        {
            "category":"Professional",
            "subcategory":"Printing & Photocopies",
            "type":"Services"
        }
    ],
    "sg:phone":"+61 3 9789 4979",
    "sg:postcode":"3910",
    "sg:province":"VIC",
    "sg:tags":[
        "trophy"
    ],
    "wof:name":"C&D Trophies",
    "wof:placetype":"venue"
},
  "geometry": {"coordinates":[145.22856140100001,-38.1337661743],"type":"Point"}
}