{
  "type": "Feature",
  "properties": {
    "iso:country":"AU",
    "sg:address":"PO Box 76",
    "sg:city":"Austral",
    "sg:classifiers":[
        {
            "category":"Building & Trades",
            "subcategory":"Construction",
            "type":"Services"
        }
    ],
    "sg:phone":"+61 418 298 149",
    "sg:postcode":"2171",
    "sg:province":"NSW",
    "sg:tags":[
        "builder",
        "designer",
        "room",
        "cool"
    ],
    "wof:name":"Mr Coolrooms",
    "wof:placetype":"venue"
},
  "geometry": {"coordinates":[150.846237183,-33.9284286499],"type":"Point"}
}