{
  "type": "Feature",
  "properties": {
    "addr:full":"4 Cascade Drv Seaford SA 5169",
    "addr:housenumber":"4",
    "addr:postcode":"5169",
    "addr:street":"Cascade Drv",
    "iso:country":"AU",
    "sg:address":"4 Cascade Drv",
    "sg:city":"Seaford",
    "sg:classifiers":[
        {
            "category":"Health Services",
            "subcategory":"Doctor",
            "type":"Services"
        }
    ],
    "sg:phone":"+61 8 8327 3777",
    "sg:postcode":"5169",
    "sg:province":"SA",
    "sg:tags":[
        "medical",
        "practitioner"
    ],
    "wof:name":"Trinity Medical Centre (Seaford)",
    "wof:placetype":"venue"
},
  "geometry": {"coordinates":[138.478790283,-35.1917304993],"type":"Point"}
}