{
  "type": "Feature",
  "properties": {
    "iso:country":"AU",
    "sg:address":"10 Sunningdale St",
    "sg:city":"Oxley",
    "sg:classifiers":[
        {
            "category":"Shopping",
            "subcategory":"Clothing, Apparel, & Fashions",
            "type":"Retail Goods"
        }
    ],
    "sg:phone":"+61 7 3278 9790",
    "sg:postcode":"4075",
    "sg:province":"QLD",
    "sg:tags":[
        "accessory"
    ],
    "wof:name":"Kamalz Indian Fashion",
    "wof:placetype":"venue"
},
  "geometry": {"coordinates":[152.98387145999999,-27.571975708],"type":"Point"}
}