{
  "type": "Feature",
  "properties": {
    "addr:full":"Cnr Wickham & Channon Sts Gympie QLD 4570",
    "addr:postcode":"4570",
    "addr:street":"Cnr",
    "iso:country":"AU",
    "sg:address":"Cnr Wickham & Channon Sts",
    "sg:city":"Gympie",
    "sg:classifiers":[
        {
            "category":"Fast Food",
            "type":"Food & Drink"
        }
    ],
    "sg:phone":"+61 7 5482 4080",
    "sg:postcode":"4570",
    "sg:province":"QLD",
    "sg:tags":[
        "away",
        "take"
    ],
    "wof:name":"KFC",
    "wof:placetype":"venue"
},
  "geometry": {"coordinates":[152.65594482399999,-26.190279007],"type":"Point"}
}