{
  "type": "Feature",
  "properties": {
    "addr:full":"Stronach Ave East Maitland NSW 2323",
    "addr:postcode":"2323",
    "addr:street":"Stronach Ave",
    "iso:country":"AU",
    "sg:address":"Stronach Ave",
    "sg:city":"East Maitland",
    "sg:classifiers":[
        {
            "category":"Travel",
            "subcategory":"Hostel",
            "type":"Entertainment"
        }
    ],
    "sg:phone":"+61 2 4933 8722",
    "sg:postcode":"2323",
    "sg:province":"NSW",
    "sg:tags":[
        "home"
    ],
    "wof:name":"Greenhills Churches Of Christ Hostel",
    "wof:placetype":"venue"
},
  "geometry": {"coordinates":[151.589187622,-32.7627372742],"type":"Point"}
}