{
  "type": "Feature",
  "properties": {
    "iso:country":"AU",
    "sg:address":"396 Walcott St",
    "sg:city":"Mt Lawley",
    "sg:classifiers":[
        {
            "category":"Building & Trades",
            "subcategory":"Cleaning & Sanitation",
            "type":"Services"
        }
    ],
    "sg:phone":"+61 8 9242 2804",
    "sg:postcode":"6050",
    "sg:province":"WA",
    "sg:tags":[
        "industrial",
        "commercial",
        "contractor"
    ],
    "wof:name":"P.P.M. Cleaning Services",
    "wof:placetype":"venue"
},
  "geometry": {"coordinates":[115.86885833700001,-31.9314002991],"type":"Point"}
}