{
  "type": "Feature",
  "properties": {
    "addr:full":"3 Phillips St Thebarton SA 5031",
    "addr:housenumber":"3",
    "addr:postcode":"5031",
    "addr:street":"Phillips St",
    "iso:country":"AU",
    "sg:address":"3 Phillips St",
    "sg:city":"Thebarton",
    "sg:classifiers":[
        {
            "category":"Professional",
            "subcategory":"Business Services",
            "type":"Services"
        }
    ],
    "sg:phone":"+61 8 8234 0840",
    "sg:postcode":"5031",
    "sg:province":"SA",
    "sg:tags":[
        "fashion",
        "agent"
    ],
    "wof:name":"Bill Walkley Agencies",
    "wof:placetype":"venue"
},
  "geometry": {"coordinates":[138.57734680199999,-34.9135322571],"type":"Point"}
}