{
  "type": "Feature",
  "properties": {
    "iso:country":"AU",
    "sg:address":"42 Trade Pl",
    "sg:city":"Coburg",
    "sg:classifiers":[
        {
            "category":"Building & Trades",
            "subcategory":"Construction",
            "type":"Services"
        }
    ],
    "sg:phone":"+61 3 9354 2220",
    "sg:postcode":"3058",
    "sg:province":"VIC",
    "sg:tags":[
        "concrete",
        "contractor"
    ],
    "wof:name":"A V C Constructions Pty Ltd",
    "wof:placetype":"venue"
},
  "geometry": {"coordinates":[144.970794678,-37.7241287231],"type":"Point"}
}