{
  "type": "Feature",
  "properties": {
    "addr:full":"27 Childs Rd Chipping Norton NSW 2170",
    "addr:housenumber":"27",
    "addr:postcode":"2170",
    "addr:street":"Childs Rd",
    "iso:country":"AU",
    "sg:address":"27 Childs Rd",
    "sg:city":"Chipping Norton",
    "sg:classifiers":[
        {
            "category":"Food & Beverages",
            "subcategory":"Groceries & Convenience Stores",
            "type":"Retail Goods"
        }
    ],
    "sg:phone":"+61 2 9755 3533",
    "sg:postcode":"2170",
    "sg:province":"NSW",
    "wof:name":"Loui's Frozen Foods",
    "wof:placetype":"venue"
},
  "geometry": {"coordinates":[150.96217346200001,-33.9188423157],"type":"Point"}
}