{
  "type": "Feature",
  "properties": {
    "addr:full":"3 Gerald St Murrumbeena VIC 3163",
    "addr:housenumber":"3",
    "addr:postcode":"3163",
    "addr:street":"Gerald St",
    "iso:country":"AU",
    "sg:address":"3 Gerald St",
    "sg:city":"Murrumbeena",
    "sg:classifiers":[
        {
            "category":"Wholesale",
            "subcategory":"Toys & Hobbies",
            "type":"Manufacturing & Wholesale Goods"
        }
    ],
    "sg:phone":"+61 3 9568 0267",
    "sg:postcode":"3163",
    "sg:province":"VIC",
    "wof:name":"Equine Manufacturing Co",
    "wof:placetype":"venue"
},
  "geometry": {"coordinates":[145.06951904300001,-37.8945350647],"type":"Point"}
}