{
  "type": "Feature",
  "properties": {
    "addr:full":"152 Francisco St Belmont WA 6104",
    "addr:housenumber":"152",
    "addr:postcode":"6104",
    "addr:street":"Francisco St",
    "iso:country":"AU",
    "sg:address":"152 Francisco St",
    "sg:city":"Belmont",
    "sg:classifiers":[
        {
            "category":"Professional",
            "subcategory":"Engineering",
            "type":"Services"
        }
    ],
    "sg:phone":"+61 8 9477 2600",
    "sg:postcode":"6104",
    "sg:province":"WA",
    "sg:tags":[
        "installation",
        "maintenance",
        "engineer"
    ],
    "wof:name":"Aqua Valet (Aust)Pty Ltd",
    "wof:placetype":"venue"
},
  "geometry": {"coordinates":[115.924026489,-31.95337677],"type":"Point"}
}