{
  "type": "Feature",
  "properties": {
    "iso:country":"AU",
    "sg:address":"459 Smollett St",
    "sg:city":"Albury",
    "sg:classifiers":[
        {
            "category":"Food & Beverages",
            "subcategory":"Groceries & Convenience Stores",
            "type":"Retail Goods"
        }
    ],
    "sg:phone":"+61 2 6023 1572",
    "sg:postcode":"2640",
    "sg:province":"NSW",
    "wof:name":"CafeNmore",
    "wof:placetype":"venue"
},
  "geometry": {"coordinates":[146.91178894000001,-36.0824546814],"type":"Point"}
}