{
  "type": "Feature",
  "properties": {
    "addr:full":"7 Northgate Shopping Complex Geraldton WA 6530",
    "addr:housenumber":"7",
    "addr:postcode":"6530",
    "addr:street":"Northgate Shopping Complex",
    "iso:country":"AU",
    "sg:address":"7 Northgate Shopping Complex",
    "sg:city":"Geraldton",
    "sg:classifiers":[
        {
            "category":"Shopping",
            "subcategory":"Clothing, Apparel, & Fashions",
            "type":"Retail Goods"
        }
    ],
    "sg:phone":"+61 8 9921 6343",
    "sg:postcode":"6530",
    "sg:province":"WA",
    "sg:tags":[
        "jean"
    ],
    "wof:name":"JeansWest",
    "wof:placetype":"venue"
},
  "geometry": {"coordinates":[114.64060974100001,-28.7494506836],"type":"Point"}
}