{
  "type": "Feature",
  "properties": {
    "addr:full":"Lot 1 Lockheed St Tamworth NSW 2340",
    "addr:postcode":"2340",
    "addr:street":"Lockheed St",
    "iso:country":"AU",
    "sg:address":"Lot 1 Lockheed St",
    "sg:city":"Tamworth",
    "sg:classifiers":[
        {
            "category":"Professional",
            "type":"Services"
        }
    ],
    "sg:phone":"+61 2 6762 1303",
    "sg:postcode":"2340",
    "sg:province":"NSW",
    "sg:tags":[
        "auctioneer"
    ],
    "wof:name":"Tamworth Auction Services",
    "wof:placetype":"venue"
},
  "geometry": {"coordinates":[150.9090271,-31.0889339447],"type":"Point"}
}