{
  "type": "Feature",
  "properties": {
    "iso:country":"AU",
    "sg:address":"Lvl 4/ 224 Queen St",
    "sg:city":"Melbourne",
    "sg:classifiers":[
        {
            "category":"Banks & Credit Unions",
            "subcategory":"Bank",
            "type":"Services"
        }
    ],
    "sg:phone":"+61 3 9600 0885",
    "sg:postcode":"3000",
    "sg:province":"VIC",
    "sg:tags":[
        "broker",
        "mortgage"
    ],
    "wof:name":"Asset Lending Solutions",
    "wof:placetype":"venue"
},
  "geometry": {"coordinates":[144.96034240700001,-37.814540863],"type":"Point"}
}