{
  "type": "Feature",
  "properties": {
    "addr:full":"Shop 1 Main Rd Kinglake VIC 3763",
    "addr:housenumber":"shop 1",
    "addr:postcode":"3763",
    "addr:street":"Main Rd",
    "iso:country":"AU",
    "sg:address":"Shop 1 Main Rd",
    "sg:city":"Kinglake",
    "sg:classifiers":[
        {
            "category":"Government",
            "subcategory":"Post Office",
            "type":"Public Place"
        }
    ],
    "sg:phone":"+61 3 5786 1209",
    "sg:postcode":"3763",
    "sg:province":"VIC",
    "sg:tags":[
        "postal"
    ],
    "wof:name":"Australia Post",
    "wof:placetype":"venue"
},
  "geometry": {"coordinates":[145.34014892600001,-37.5305786133],"type":"Point"}
}