{
  "type": "Feature",
  "properties": {
    "addr:full":"Shop 9, 163- 185 Mary St Gympie QLD 4570",
    "addr:housenumber":"shop 9;185",
    "addr:postcode":"163;4570",
    "addr:street":"Mary St",
    "iso:country":"AU",
    "sg:address":"Shop 9, 163- 185 Mary St",
    "sg:city":"Gympie",
    "sg:classifiers":[
        {
            "category":"Real Estate",
            "subcategory":"Real Estate Agent",
            "type":"Services"
        }
    ],
    "sg:phone":"+61 7 5482 3966",
    "sg:postcode":"4570",
    "sg:province":"QLD",
    "wof:name":"Harcourts Gympie",
    "wof:placetype":"venue"
},
  "geometry": {"coordinates":[152.66041564899999,-26.1892490387],"type":"Point"}
}