{
  "type": "Feature",
  "properties": {
    "addr:full":"8 Albert Rd Lesmurdie WA 6076",
    "addr:housenumber":"8",
    "addr:postcode":"6076",
    "addr:street":"Albert Rd",
    "iso:country":"AU",
    "sg:address":"8 Albert Rd",
    "sg:city":"Lesmurdie",
    "sg:classifiers":[
        {
            "category":"Retail",
            "subcategory":"Car Wash",
            "type":"Services"
        }
    ],
    "sg:phone":"+61 8 9291 6592",
    "sg:postcode":"6076",
    "sg:province":"WA",
    "sg:tags":[
        "bitumen",
        "spraying"
    ],
    "wof:name":"Dalpave Bitumen Paving",
    "wof:placetype":"venue"
},
  "geometry": {"coordinates":[116.04881286600001,-32.0146141052],"type":"Point"}
}