{
  "type": "Feature",
  "properties": {
    "iso:country":"AU",
    "sg:address":"130 Belar Ave",
    "sg:city":"Villawood",
    "sg:classifiers":[
        {
            "category":"Arts & Performance",
            "subcategory":"Music",
            "type":"Entertainment"
        }
    ],
    "sg:phone":"+61 2 9726 5671",
    "sg:postcode":"2163",
    "sg:province":"NSW",
    "sg:tags":[
        "hi-fi",
        "equipment"
    ],
    "wof:name":"Goddards Audio Installations",
    "wof:placetype":"venue"
},
  "geometry": {"coordinates":[150.978637695,-33.8911476135],"type":"Point"}
}