{
  "type": "Feature",
  "properties": {
    "addr:full":"144 Anzac Highway Glandore SA 5037",
    "addr:housenumber":"144",
    "addr:postcode":"5037",
    "addr:street":"Anzac Highway",
    "iso:country":"AU",
    "sg:address":"144 Anzac Highway",
    "sg:city":"Glandore",
    "sg:classifiers":[
        {
            "category":"Wholesale",
            "subcategory":"Construction Materials",
            "type":"Manufacturing & Wholesale Goods"
        }
    ],
    "sg:phone":"+61 8 8293 6464",
    "sg:postcode":"5037",
    "sg:province":"SA",
    "sg:tags":[
        "wholesaler",
        "lighting",
        "mfrs",
        "accessory"
    ],
    "sg:website":"http://www.instylelighting.com.au",
    "wof:name":"Instyle Lighting",
    "wof:placetype":"venue"
},
  "geometry": {"coordinates":[138.56802368199999,-34.9556655884],"type":"Point"}
}