{
  "type": "Feature",
  "properties": {
    "addr:full":"66 Seventh Ave St Peters SA 5069",
    "addr:housenumber":"66",
    "addr:postcode":"5069",
    "addr:street":"Seventh Ave",
    "iso:country":"AU",
    "sg:address":"66 Seventh Ave",
    "sg:city":"St Peters",
    "sg:classifiers":[
        {
            "category":"Food & Beverages",
            "subcategory":"Bakery",
            "type":"Retail Goods"
        }
    ],
    "sg:phone":"+61 8 8362 2191",
    "sg:postcode":"5069",
    "sg:province":"SA",
    "sg:tags":[
        "baker"
    ],
    "wof:name":"St Peters Bakehouse & Coffee Shop",
    "wof:placetype":"venue"
},
  "geometry": {"coordinates":[138.621749878,-34.9034347534],"type":"Point"}
}