{
  "type": "Feature",
  "properties": {
    "addr:full":"5 Edward St Cessnock NSW 2325",
    "addr:housenumber":"5",
    "addr:postcode":"2325",
    "addr:street":"Edward St",
    "iso:country":"AU",
    "sg:address":"5 Edward St",
    "sg:city":"Cessnock",
    "sg:classifiers":[
        {
            "category":"Professional",
            "subcategory":"Engineering",
            "type":"Services"
        }
    ],
    "sg:phone":"+61 2 4991 7171",
    "sg:postcode":"2325",
    "sg:province":"NSW",
    "sg:tags":[
        "consulting",
        "engineer"
    ],
    "wof:name":"ACM Landmark Pty Ltd",
    "wof:placetype":"venue"
},
  "geometry": {"coordinates":[151.35731506400001,-32.8337211609],"type":"Point"}
}