{
  "type": "Feature",
  "properties": {
    "addr:full":"5/ 13 Turley St Raceview QLD 4305",
    "addr:housenumber":"/ 13",
    "addr:postcode":"4305",
    "addr:street":"Turley St",
    "iso:country":"AU",
    "sg:address":"5/ 13 Turley St",
    "sg:city":"Raceview",
    "sg:classifiers":[
        {
            "category":"Autos & Motor Vehicles",
            "subcategory":"Automobile Sales",
            "type":"Retail Goods"
        }
    ],
    "sg:phone":"+61 7 3281 6964",
    "sg:postcode":"4305",
    "sg:province":"QLD",
    "sg:tags":[
        "equipment",
        "trailer"
    ],
    "wof:name":"Pigdog Trailers",
    "wof:placetype":"venue"
},
  "geometry": {"coordinates":[152.759765625,-27.6343536377],"type":"Point"}
}