{
  "type": "Feature",
  "properties": {
    "addr:full":"102 Byangum Rd Murwillumbah NSW 2484",
    "addr:housenumber":"102",
    "addr:postcode":"2484",
    "addr:street":"Byangum Rd",
    "iso:country":"AU",
    "sg:address":"102 Byangum Rd",
    "sg:city":"Murwillumbah",
    "sg:classifiers":[
        {
            "category":"Professional",
            "subcategory":"Computer Services",
            "type":"Services"
        }
    ],
    "sg:phone":"+61 418 734 201",
    "sg:postcode":"2484",
    "sg:province":"NSW",
    "sg:tags":[
        "repairs",
        "upgrade",
        "equipment"
    ],
    "wof:name":"Pro-File Data Systems",
    "wof:placetype":"venue"
},
  "geometry": {"coordinates":[153.38192749000001,-28.3306617737],"type":"Point"}
}