{
  "type": "Feature",
  "properties": {
    "addr:full":"66 Thomas Drv Chevron Island QLD 4217",
    "addr:housenumber":"66",
    "addr:postcode":"4217",
    "addr:street":"Thomas Drv Chevron",
    "iso:country":"AU",
    "sg:address":"66 Thomas Drv",
    "sg:city":"Chevron Island",
    "sg:classifiers":[
        {
            "category":"Professional",
            "subcategory":"Art Services",
            "type":"Services"
        }
    ],
    "sg:phone":"+61 7 5538 4955",
    "sg:postcode":"4217",
    "sg:province":"QLD",
    "sg:tags":[
        "interior",
        "decorator"
    ],
    "wof:name":"Doug Kingsman Interior Designer",
    "wof:placetype":"venue"
},
  "geometry": {"coordinates":[153.418243408,-27.9979095459],"type":"Point"}
}