{
  "type": "Feature",
  "properties": {
    "addr:full":"31 Woodvale Pl Castle Hill NSW 2154",
    "addr:housenumber":"31",
    "addr:postcode":"2154",
    "addr:street":"Woodvale Pl",
    "iso:country":"AU",
    "sg:address":"31 Woodvale Pl",
    "sg:city":"Castle Hill",
    "sg:classifiers":[
        {
            "category":"Education",
            "subcategory":"Special Training",
            "type":"Public Place"
        }
    ],
    "sg:phone":"+61 2 9899 5900",
    "sg:postcode":"2154",
    "sg:province":"NSW",
    "sg:tags":[
        "tuition-educational"
    ],
    "wof:name":"Everest Coaching Colleges",
    "wof:placetype":"venue"
},
  "geometry": {"coordinates":[151.00953674300001,-33.7236824036],"type":"Point"}
}