{
  "type": "Feature",
  "properties": {
    "addr:full":"250 English St Essendon Airport VIC 3041",
    "addr:housenumber":"250",
    "addr:postcode":"3041",
    "addr:street":"English St",
    "iso:country":"AU",
    "sg:address":"250 English St",
    "sg:city":"Essendon Airport",
    "sg:classifiers":[
        {
            "category":"Health Services",
            "subcategory":"Dentist",
            "type":"Services"
        }
    ],
    "sg:phone":"+61 3 9379 0300",
    "sg:postcode":"3041",
    "sg:province":"VIC",
    "wof:name":"Dr Frank Davis",
    "wof:placetype":"venue"
},
  "geometry": {"coordinates":[144.91159057600001,-37.7268600464],"type":"Point"}
}