{
  "type": "Feature",
  "properties": {
    "addr:full":"Shop 4 92 Pine Mountain Rd Brassall QLD 4305",
    "addr:housenumber":"shop;92",
    "addr:postcode":"4305",
    "addr:street":"Pine Mountain Rd",
    "iso:country":"AU",
    "sg:address":"Shop 4 92 Pine Mountain Rd",
    "sg:city":"Brassall",
    "sg:classifiers":[
        {
            "category":"Fast Food",
            "type":"Food & Drink"
        }
    ],
    "sg:phone":"+61 7 3813 0998",
    "sg:postcode":"4305",
    "sg:province":"QLD",
    "sg:tags":[
        "away",
        "take"
    ],
    "wof:name":"Thai 2 Go",
    "wof:placetype":"venue"
},
  "geometry": {"coordinates":[152.74949645999999,-27.5885372162],"type":"Point"}
}