{
  "type": "Feature",
  "properties": {
    "iso:country":"AU",
    "sg:address":"137 Nelson St",
    "sg:city":"Wallsend",
    "sg:classifiers":[
        {
            "category":"Health Services",
            "subcategory":"Health Practitioner",
            "type":"Services"
        }
    ],
    "sg:phone":"+61 2 4950 0271",
    "sg:postcode":"2287",
    "sg:province":"NSW",
    "sg:tags":[
        "alternative"
    ],
    "wof:name":"Seddon Venetia",
    "wof:placetype":"venue"
},
  "geometry": {"coordinates":[151.6693573,-32.9017295837],"type":"Point"}
}