{
  "type": "Feature",
  "properties": {
    "iso:country":"AU",
    "sg:address":"1489 Point Nepean Rd",
    "sg:city":"Rosebud",
    "sg:classifiers":[
        {
            "category":"Food & Beverages",
            "subcategory":"Specialty",
            "type":"Retail Goods"
        }
    ],
    "sg:phone":"+61 3 5982 0522",
    "sg:postcode":"3939",
    "sg:province":"VIC",
    "sg:tags":[
        "delicacy"
    ],
    "wof:name":"The Tasting Station",
    "wof:placetype":"venue"
},
  "geometry": {"coordinates":[144.887329102,-38.3607063293],"type":"Point"}
}