{
  "type": "Feature",
  "properties": {
    "iso:country":"AU",
    "sg:address":"14 Hindmarsh Drv",
    "sg:city":"Phillip",
    "sg:classifiers":[
        {
            "category":"Building & Trades",
            "subcategory":"Construction",
            "type":"Services"
        }
    ],
    "sg:phone":"+61 2 6122 2555",
    "sg:postcode":"2606",
    "sg:province":"ACT",
    "sg:tags":[
        "window",
        "timber"
    ],
    "wof:name":"Stegbar",
    "wof:placetype":"venue"
},
  "geometry": {"coordinates":[149.08885192899999,-35.3488311768],"type":"Point"}
}