{
  "type": "Feature",
  "properties": {
    "addr:full":"115 Main Rd McLaren Vale SA 5171",
    "addr:housenumber":"115",
    "addr:postcode":"5171",
    "addr:street":"Main Rd",
    "iso:country":"AU",
    "sg:address":"115 Main Rd",
    "sg:city":"McLaren Vale",
    "sg:classifiers":[
        {
            "category":"Manufacturing",
            "subcategory":"Retail Goods",
            "type":"Manufacturing & Wholesale Goods"
        }
    ],
    "sg:phone":"+61 8 8323 8160",
    "sg:postcode":"5171",
    "sg:province":"SA",
    "sg:tags":[
        "merchant",
        "pump",
        "mfrs"
    ],
    "wof:name":"The Rural Shop",
    "wof:placetype":"venue"
},
  "geometry": {"coordinates":[138.53712463400001,-35.2149467468],"type":"Point"}
}