{
  "type": "Feature",
  "properties": {
    "iso:country":"AU",
    "sg:address":"3 Clarke St",
    "sg:city":"Wayville",
    "sg:classifiers":[
        {
            "category":"Personal",
            "subcategory":"Beauty Salon",
            "type":"Services"
        }
    ],
    "sg:phone":"+61 405 124 124",
    "sg:postcode":"5034",
    "sg:province":"SA",
    "wof:name":"Tanapans Skin Care",
    "wof:placetype":"venue"
},
  "geometry": {"coordinates":[138.596969605,-34.9434967041],"type":"Point"}
}