{
  "type": "Feature",
  "properties": {
    "addr:full":"585 Mersey Rd Osborne SA 5017",
    "addr:housenumber":"585",
    "addr:postcode":"5017",
    "addr:street":"Mersey Rd",
    "iso:country":"AU",
    "sg:address":"585 Mersey Rd",
    "sg:city":"Osborne",
    "sg:classifiers":[
        {
            "category":"Farming",
            "subcategory":"Fish & Marine Products",
            "type":"Manufacturing & Wholesale Goods"
        }
    ],
    "sg:phone":"+61 8 8248 8700",
    "sg:postcode":"5017",
    "sg:province":"SA",
    "sg:tags":[
        "equipment",
        "salvage"
    ],
    "wof:name":"Maritime Constructions",
    "wof:placetype":"venue"
},
  "geometry": {"coordinates":[138.50706481899999,-34.8101997375],"type":"Point"}
}