{
  "type": "Feature",
  "properties": {
    "addr:full":"35 Lannercost St Ingham QLD 4850",
    "addr:housenumber":"35",
    "addr:postcode":"4850",
    "addr:street":"Lannercost St",
    "iso:country":"AU",
    "sg:address":"35 Lannercost St",
    "sg:city":"Ingham",
    "sg:classifiers":[
        {
            "category":"Banks & Credit Unions",
            "subcategory":"Investment Brokerage",
            "type":"Services"
        }
    ],
    "sg:phone":"+61 7 4776 2466",
    "sg:postcode":"4850",
    "sg:province":"QLD",
    "wof:name":"Professional Investment Services Pty Ltd",
    "wof:placetype":"venue"
},
  "geometry": {"coordinates":[146.15423584000001,-18.6507148743],"type":"Point"}
}