{
  "type": "Feature",
  "properties": {
    "addr:full":"PO Box 1493 Bairnsdale VIC 3875",
    "addr:postcode":"3875",
    "iso:country":"AU",
    "sg:address":"PO Box 1493",
    "sg:city":"Bairnsdale",
    "sg:classifiers":[
        {
            "category":"Building & Trades",
            "subcategory":"Landscaping Services",
            "type":"Services"
        }
    ],
    "sg:phone":"+61 3 5157 9228",
    "sg:postcode":"3875",
    "sg:province":"VIC",
    "sg:tags":[
        "firebreak",
        "clearing",
        "land",
        "contractor"
    ],
    "wof:name":"Riley Earthmoving Pty Ltd",
    "wof:placetype":"venue"
},
  "geometry": {"coordinates":[147.61129760700001,-37.8314208984],"type":"Point"}
}