{
  "type": "Feature",
  "properties": {
    "addr:full":"77 St Georges Tce Perth WA 6000",
    "addr:housenumber":"77",
    "addr:postcode":"6000",
    "addr:street":"St Georges Tce",
    "iso:country":"AU",
    "sg:address":"77 St Georges Tce",
    "sg:city":"Perth",
    "sg:classifiers":[
        {
            "category":"Professional",
            "subcategory":"Management & Consulting",
            "type":"Services"
        }
    ],
    "sg:phone":"+61 8 9225 6066",
    "sg:postcode":"6000",
    "sg:province":"WA",
    "sg:tags":[
        "consultant",
        "migration"
    ],
    "wof:name":"Michell Sillar McPhee",
    "wof:placetype":"venue"
},
  "geometry": {"coordinates":[115.85836792000001,-31.9554367065],"type":"Point"}
}