{
  "type": "Feature",
  "properties": {
    "iso:country":"AU",
    "sg:address":"576 Victoria Pde",
    "sg:city":"East Melbourne",
    "sg:classifiers":[
        {
            "category":"Professional",
            "subcategory":"Accounting & Tax Preparation",
            "type":"Services"
        }
    ],
    "sg:phone":"+61 3 9419 5633",
    "sg:postcode":"3002",
    "sg:province":"VIC",
    "sg:tags":[
        "pregnancy",
        "related",
        "counselling"
    ],
    "wof:name":"Centacare Catholic Family Services",
    "wof:placetype":"venue"
},
  "geometry": {"coordinates":[144.99021911599999,-37.8100700378],"type":"Point"}
}