{
  "type": "Feature",
  "properties": {
    "iso:country":"AU",
    "sg:address":"28 Pelican St",
    "sg:city":"Peregian Beach",
    "sg:classifiers":[
        {
            "category":"Military Area",
            "subcategory":"Army Base",
            "type":"Public Place"
        }
    ],
    "sg:phone":"+61 412 049 525",
    "sg:postcode":"4573",
    "sg:province":"QLD",
    "sg:tags":[
        "concrete",
        "slab",
        "floor"
    ],
    "wof:name":"B & C Fielden",
    "wof:placetype":"venue"
},
  "geometry": {"coordinates":[153.095795,-26.477301],"type":"Point"}
}