{
  "type": "Feature",
  "properties": {
    "iso:country":"AU",
    "sg:address":"Unit 3 Cnr Racecourse Rd & Shipley Drv",
    "sg:city":"Rutherford",
    "sg:classifiers":[
        {
            "category":"Industrial Area",
            "type":"Public Place"
        }
    ],
    "sg:phone":"+61 2 4932 6995",
    "sg:postcode":"2320",
    "sg:province":"NSW",
    "sg:tags":[
        "protective",
        "clothing"
    ],
    "wof:name":"DPS Workwear",
    "wof:placetype":"venue"
},
  "geometry": {"coordinates":[151.51470947300001,-32.7143745422],"type":"Point"}
}