{
  "type": "Feature",
  "properties": {
    "iso:country":"AU",
    "sg:address":"495 Blackburn Rd",
    "sg:city":"Mt Waverley",
    "sg:classifiers":[
        {
            "category":"Professional",
            "subcategory":"Art Services",
            "type":"Services"
        }
    ],
    "sg:phone":"+61 3 9211 7700",
    "sg:postcode":"3149",
    "sg:province":"VIC",
    "sg:tags":[
        "product",
        "industrial",
        "designer"
    ],
    "wof:name":"Invetech",
    "wof:placetype":"venue"
},
  "geometry": {"coordinates":[145.14364624000001,-37.8963241577],"type":"Point"}
}