{
  "type": "Feature",
  "properties": {
    "addr:full":"37 Boyland Ave Coopers Plains QLD 4108",
    "addr:housenumber":"37",
    "addr:postcode":"4108",
    "addr:street":"Boyland Ave",
    "iso:country":"AU",
    "sg:address":"37 Boyland Ave",
    "sg:city":"Coopers Plains",
    "sg:classifiers":[
        {
            "category":"Building & Trades",
            "subcategory":"Construction",
            "type":"Services"
        }
    ],
    "sg:phone":"+61 7 3277 8383",
    "sg:postcode":"4108",
    "sg:province":"QLD",
    "sg:tags":[
        "underpinning"
    ],
    "wof:name":"Monteverde R & M Pty Ltd",
    "wof:placetype":"venue"
},
  "geometry": {"coordinates":[153.024932861,-27.5640048981],"type":"Point"}
}