{
  "type": "Feature",
  "properties": {
    "addr:full":"Fcty5/ 17 Hazel Ave Dandenong VIC 3175",
    "addr:housenumber":"17",
    "addr:postcode":"3175",
    "addr:street":"Hazel Ave",
    "iso:country":"AU",
    "sg:address":"Fcty5/ 17 Hazel Ave",
    "sg:city":"Dandenong",
    "sg:classifiers":[
        {
            "category":"Arena",
            "subcategory":"Sports Club",
            "type":"Entertainment"
        }
    ],
    "sg:phone":"+61 3 9701 3873",
    "sg:postcode":"3175",
    "sg:province":"VIC",
    "sg:tags":[
        "defence",
        "supply",
        "self",
        "instruction",
        "martial art"
    ],
    "wof:name":"Ultimate Martial Arts Academy",
    "wof:placetype":"venue"
},
  "geometry": {"coordinates":[145.19648742699999,-37.9922866821],"type":"Point"}
}