{
  "type": "Feature",
  "properties": {
    "iso:country":"AU",
    "sg:address":"Main St",
    "sg:city":"Maldon",
    "sg:classifiers":[
        {
            "category":"Autos & Motor Vehicles",
            "subcategory":"Auto Supplies",
            "type":"Retail Goods"
        }
    ],
    "sg:phone":"+61 3 5475 1584",
    "sg:postcode":"3463",
    "sg:province":"VIC",
    "sg:tags":[
        "part",
        "cycles",
        "accessory"
    ],
    "wof:name":"The Motorcyclists Emporium",
    "wof:placetype":"venue"
},
  "geometry": {"coordinates":[143.903366089,-36.8268852234],"type":"Point"}
}