{
  "type": "Feature",
  "properties": {
    "iso:country":"AU",
    "sg:address":"4 Rockingham Rd",
    "sg:city":"Hamilton Hill",
    "sg:classifiers":[
        {
            "category":"Manufacturing",
            "subcategory":"Furniture",
            "type":"Manufacturing & Wholesale Goods"
        }
    ],
    "sg:phone":"+61 8 9430 9233",
    "sg:postcode":"6163",
    "sg:province":"WA",
    "sg:tags":[
        "builder",
        "designer",
        "custom"
    ],
    "wof:name":"Fremantle Wood Company",
    "wof:placetype":"venue"
},
  "geometry": {"coordinates":[115.762039,-32.078354],"type":"Point"}
}