{
  "type": "Feature",
  "properties": {
    "iso:country":"AU",
    "sg:address":"17 Shaw Rd",
    "sg:city":"Dianella",
    "sg:classifiers":[
        {
            "category":"Arts & Performance",
            "subcategory":"Music",
            "type":"Entertainment"
        }
    ],
    "sg:phone":"+61 412 939 372",
    "sg:postcode":"6059",
    "sg:province":"WA",
    "sg:tags":[
        "mobile",
        "jockey",
        "disc"
    ],
    "wof:name":"Doctor Sounds 5 Star DJ's",
    "wof:placetype":"venue"
},
  "geometry": {"coordinates":[115.794067383,-31.8909721375],"type":"Point"}
}