{
  "type": "Feature",
  "properties": {
    "iso:country":"AU",
    "sg:address":"43 Irrawong Rd",
    "sg:city":"North Narrabeen",
    "sg:classifiers":[
        {
            "category":"Professional",
            "subcategory":"Computer Services",
            "type":"Services"
        }
    ],
    "sg:phone":"+61 2 9944 6417",
    "sg:postcode":"2101",
    "sg:province":"NSW",
    "sg:tags":[
        "repairs",
        "upgrade",
        "equipment"
    ],
    "wof:name":"Computer and Camera Repairs",
    "wof:placetype":"venue"
},
  "geometry": {"coordinates":[151.28587300000001,-33.693413],"type":"Point"}
}