{
  "type": "Feature",
  "properties": {
    "iso:country":"AU",
    "sg:address":"53 St Albans Rd St",
    "sg:city":"Albans",
    "sg:classifiers":[
        {
            "category":"Food & Beverages",
            "subcategory":"Bakery",
            "type":"Retail Goods"
        }
    ],
    "sg:phone":"+61 3 9367 6167",
    "sg:postcode":"3021",
    "sg:province":"VIC",
    "sg:tags":[
        "baker"
    ],
    "wof:name":"St Augustine Bakery",
    "wof:placetype":"venue"
},
  "geometry": {"coordinates":[144.80616800000001,-37.752171],"type":"Point"}
}