{
  "type": "Feature",
  "properties": {
    "iso:country":"AU",
    "sg:address":"37 Walker St",
    "sg:city":"Maryborough",
    "sg:classifiers":[
        {
            "category":"Food & Beverages",
            "subcategory":"Liquor & Beverages",
            "type":"Retail Goods"
        }
    ],
    "sg:phone":"+61 7 4121 3374",
    "sg:postcode":"4650",
    "sg:province":"QLD",
    "sg:tags":[
        "store"
    ],
    "wof:name":"White Lion Hotel",
    "wof:placetype":"venue"
},
  "geometry": {"coordinates":[152.684387,-25.518955],"type":"Point"}
}