{
  "type": "Feature",
  "properties": {
    "addr:full":"96 Goondoon St Gladstone QLD 4680",
    "addr:housenumber":"96",
    "addr:postcode":"4680",
    "addr:street":"Goondoon St",
    "iso:country":"AU",
    "sg:address":"96 Goondoon St",
    "sg:city":"Gladstone",
    "sg:classifiers":[
        {
            "category":"Personal",
            "subcategory":"Beauty Salon",
            "type":"Services"
        }
    ],
    "sg:phone":"+61 7 4972 1046",
    "sg:postcode":"4680",
    "sg:province":"QLD",
    "sg:tags":[
        "hairdresser"
    ],
    "wof:name":"Rosette Styles For Hair",
    "wof:placetype":"venue"
},
  "geometry": {"coordinates":[151.255615234,-23.8426456451],"type":"Point"}
}