{
  "type": "Feature",
  "properties": {
    "addr:full":"15-19 Adams Rd Sheidow Park SA 5158",
    "addr:housenumber":"15-19",
    "addr:postcode":"5158",
    "addr:street":"Adams Rd",
    "iso:country":"AU",
    "sg:address":"15-19 Adams Rd",
    "sg:city":"Sheidow Park",
    "sg:classifiers":[
        {
            "category":"Health Services",
            "subcategory":"Health Practitioner",
            "type":"Services"
        }
    ],
    "sg:phone":"+61 8 8387 9111",
    "sg:postcode":"5158",
    "sg:province":"SA",
    "sg:tags":[
        "naturopath"
    ],
    "wof:name":"Natural Therapy Centre",
    "wof:placetype":"venue"
},
  "geometry": {"coordinates":[138.53041076700001,-35.0716400146],"type":"Point"}
}