{
  "type": "Feature",
  "properties": {
    "addr:full":"16 Marshall St Ivanhoe VIC 3079",
    "addr:housenumber":"16",
    "addr:postcode":"3079",
    "addr:street":"Marshall St",
    "iso:country":"AU",
    "sg:address":"16 Marshall St",
    "sg:city":"Ivanhoe",
    "sg:classifiers":[
        {
            "category":"Building & Trades",
            "subcategory":"Construction",
            "type":"Services"
        }
    ],
    "sg:phone":"+61 3 9499 4224",
    "sg:postcode":"3079",
    "sg:province":"VIC",
    "sg:tags":[
        "home",
        "air conditioning"
    ],
    "wof:name":"Cascone Air",
    "wof:placetype":"venue"
},
  "geometry": {"coordinates":[145.04612731899999,-37.7755813599],"type":"Point"}
}