{
  "type": "Feature",
  "properties": {
    "addr:full":"169 Chester Pass Rd Albany WA 6330",
    "addr:housenumber":"169",
    "addr:postcode":"6330",
    "addr:street":"Chester Pass Rd",
    "iso:country":"AU",
    "sg:address":"169 Chester Pass Rd",
    "sg:city":"Albany",
    "sg:classifiers":[
        {
            "category":"Wholesale",
            "subcategory":"Auto Parts",
            "type":"Manufacturing & Wholesale Goods"
        }
    ],
    "sg:phone":"+61 8 9842 8722",
    "sg:postcode":"6330",
    "sg:province":"WA",
    "sg:tags":[
        "transmission",
        "automotive",
        "truck"
    ],
    "wof:name":"Truckline Truck & Trailer Parts",
    "wof:placetype":"venue"
},
  "geometry": {"coordinates":[117.875076294,-34.989982605],"type":"Point"}
}