{
  "type": "Feature",
  "properties": {
    "addr:full":"Groud Floor, 101-103 Queens Pde Clifton Hill VIC 3068",
    "addr:housenumber":"101-103",
    "addr:postcode":"3068",
    "addr:street":"Queens Pde",
    "iso:country":"AU",
    "sg:address":"Groud Floor, 101-103 Queens Pde",
    "sg:city":"Clifton Hill",
    "sg:classifiers":[
        {
            "category":"Sports & Exercise",
            "subcategory":"Gym",
            "type":"Entertainment"
        }
    ],
    "sg:phone":"+61 3 9481 2955",
    "sg:postcode":"3068",
    "sg:province":"VIC",
    "sg:tags":[
        "pilate",
        "method"
    ],
    "wof:name":"Body Logic Pilates",
    "wof:placetype":"venue"
},
  "geometry": {"coordinates":[144.98980712900001,-37.7894515991],"type":"Point"}
}