{
  "type": "Feature",
  "properties": {
    "addr:full":"112 Evans St Port Melbourne VIC 3207",
    "addr:housenumber":"112",
    "addr:postcode":"3207",
    "addr:street":"Evans St",
    "iso:country":"AU",
    "sg:address":"112 Evans St",
    "sg:city":"Port Melbourne",
    "sg:classifiers":[
        {
            "category":"Professional",
            "subcategory":"Management & Consulting",
            "type":"Services"
        }
    ],
    "sg:phone":"+61 3 9681 9577",
    "sg:postcode":"3207",
    "sg:province":"VIC",
    "sg:tags":[
        "consultant"
    ],
    "wof:name":"Corporate Reflection & Decision Associates",
    "wof:placetype":"venue"
},
  "geometry": {"coordinates":[144.941788,-37.833519],"type":"Point"}
}