{
  "type": "Feature",
  "properties": {
    "addr:full":"13 Market Pl Forest Hill VIC 3131",
    "addr:housenumber":"13",
    "addr:postcode":"3131",
    "addr:street":"Market Pl",
    "iso:country":"AU",
    "sg:address":"13 Market Pl",
    "sg:city":"Forest Hill",
    "sg:classifiers":[
        {
            "category":"Food & Beverages",
            "subcategory":"Specialty",
            "type":"Retail Goods"
        }
    ],
    "sg:phone":"+61 3 9877 5705",
    "sg:postcode":"3131",
    "sg:province":"VIC",
    "sg:tags":[
        "product",
        "health"
    ],
    "wof:name":"Long Life Health",
    "wof:placetype":"venue"
},
  "geometry": {"coordinates":[145.176437378,-37.8214797974],"type":"Point"}
}