{
  "type": "Feature",
  "properties": {
    "addr:full":"139 Hare St Echuca VIC 3564",
    "addr:housenumber":"139",
    "addr:postcode":"3564",
    "addr:street":"Hare St",
    "iso:country":"AU",
    "sg:address":"139 Hare St",
    "sg:city":"Echuca",
    "sg:classifiers":[
        {
            "category":"Shopping",
            "subcategory":"Jewelry",
            "type":"Retail Goods"
        }
    ],
    "sg:phone":"+61 3 5482 2454",
    "sg:postcode":"3564",
    "sg:province":"VIC",
    "sg:tags":[
        "jeweller"
    ],
    "wof:name":"Simply Irresistible Jewellery",
    "wof:placetype":"venue"
},
  "geometry": {"coordinates":[144.749343872,-36.1277427673],"type":"Point"}
}