{
  "type": "Feature",
  "properties": {
    "addr:full":"Shop 2/101 Matthews Ave (cnr. Dromana St) Airport West VIC 3042",
    "addr:housenumber":"shop 2 / 101",
    "addr:postcode":"3042",
    "addr:street":"Matthews Ave Cnr. Dromana St",
    "iso:country":"AU",
    "sg:address":"Shop 2/101 Matthews Ave",
    "sg:city":"(cnr. Dromana St) Airport West",
    "sg:classifiers":[
        {
            "category":"Wholesale",
            "subcategory":"Painting Supplies",
            "type":"Manufacturing & Wholesale Goods"
        }
    ],
    "sg:phone":"+61 3 8336 1778",
    "sg:postcode":"3042",
    "sg:province":"VIC",
    "sg:tags":[
        "wholesaler",
        "paint",
        "mfrs"
    ],
    "wof:name":"Solver Paints",
    "wof:placetype":"venue"
},
  "geometry": {"coordinates":[144.890014648,-37.7137260437],"type":"Point"}
}