{
  "type": "Feature",
  "properties": {
    "addr:full":"170 Jacaranda Ave Kingston QLD 4114",
    "addr:housenumber":"170",
    "addr:postcode":"4114",
    "addr:street":"Jacaranda Ave",
    "iso:country":"AU",
    "sg:address":"170 Jacaranda Ave",
    "sg:city":"Kingston",
    "sg:classifiers":[
        {
            "category":"Fast Food",
            "type":"Food & Drink"
        }
    ],
    "sg:phone":"+61 7 3208 3662",
    "sg:postcode":"4114",
    "sg:province":"QLD",
    "sg:tags":[
        "away",
        "take"
    ],
    "wof:name":"Five Star Takeaway Food",
    "wof:placetype":"venue"
},
  "geometry": {"coordinates":[153.11091613799999,-27.6542701721],"type":"Point"}
}