{
  "type": "Feature",
  "properties": {
    "iso:country":"AU",
    "sg:address":"Main St",
    "sg:city":"Cowwarr",
    "sg:classifiers":[
        {
            "category":"Autos & Motor Vehicles",
            "subcategory":"Fuel & Gas Station",
            "type":"Retail Goods"
        }
    ],
    "sg:phone":"+61 3 5148 9266",
    "sg:postcode":"3857",
    "sg:province":"VIC",
    "wof:name":"Cowwarr Motors",
    "wof:placetype":"venue"
},
  "geometry": {"coordinates":[146.695587158,-38.0140266418],"type":"Point"}
}