{
  "type": "Feature",
  "properties": {
    "iso:country":"AU",
    "sg:address":"No.3 52 O\ufffdloughlin Tce",
    "sg:city":"Ceduna",
    "sg:classifiers":[
        {
            "category":"Airline",
            "type":"Transportation"
        }
    ],
    "sg:phone":"+61 8 8625 2780",
    "sg:postcode":"5690",
    "sg:province":"SA",
    "sg:tags":[
        "agent"
    ],
    "wof:name":"Travelworld Ceduna",
    "wof:placetype":"venue"
},
  "geometry": {"coordinates":[133.67393493599999,-32.1243782043],"type":"Point"}
}