{
  "type": "Feature",
  "properties": {
    "addr:full":"Cnr Commercial Dr & Springfield Parkway Springfield QLD 4300",
    "addr:postcode":"4300",
    "addr:street":"Commercial;Parkway",
    "iso:country":"AU",
    "sg:address":"Cnr Commercial Dr",
    "sg:city":"& Springfield Parkway Springfield",
    "sg:classifiers":[
        {
            "category":"Travel",
            "subcategory":"Hotels & Motels",
            "type":"Entertainment"
        }
    ],
    "sg:phone":"+61 7 3818 2822",
    "sg:postcode":"4300",
    "sg:province":"QLD",
    "sg:tags":[
        "pub"
    ],
    "wof:name":"Springfield Tavern",
    "wof:placetype":"venue"
},
  "geometry": {"coordinates":[152.919525147,-27.65350914],"type":"Point"}
}