{
  "type": "Feature",
  "properties": {
    "iso:country":"AU",
    "sg:address":"22- 24",
    "sg:city":"Newton Wetherill Park",
    "sg:classifiers":[
        {
            "category":"Home & Garden",
            "subcategory":"Building Materials",
            "type":"Retail Goods"
        }
    ],
    "sg:phone":"+61 2 9756 3188",
    "sg:postcode":"2164",
    "sg:province":"NSW",
    "sg:tags":[
        "merchant",
        "glass",
        "glazier"
    ],
    "wof:name":"V & N Glass Pty Ltd",
    "wof:placetype":"venue"
},
  "geometry": {"coordinates":[150.89338684099999,-33.8421173096],"type":"Point"}
}