{
  "type": "Feature",
  "properties": {
    "addr:full":"Lot 1295 Banksia St Loch Sport VIC 3851",
    "addr:housenumber":"1295",
    "addr:postcode":"3851",
    "addr:street":"Banksia St",
    "iso:country":"AU",
    "sg:address":"Lot 1295 Banksia St",
    "sg:city":"Loch Sport",
    "sg:classifiers":[
        {
            "category":"Utilities",
            "subcategory":"Electric",
            "type":"Services"
        }
    ],
    "sg:phone":"+61 3 5146 0640",
    "sg:postcode":"3851",
    "sg:province":"VIC",
    "sg:tags":[
        "electrical",
        "contractor"
    ],
    "wof:name":"McFarlane Ray H Electrical Services",
    "wof:placetype":"venue"
},
  "geometry": {"coordinates":[147.592193603,-38.0381622314],"type":"Point"}
}