{
  "type": "Feature",
  "properties": {
    "addr:full":"9 Sim St Mt Waverley VIC 3149",
    "addr:housenumber":"9",
    "addr:postcode":"3149",
    "addr:street":"Sim St Mt",
    "iso:country":"AU",
    "sg:address":"9 Sim St",
    "sg:city":"Mt Waverley",
    "sg:classifiers":[
        {
            "category":"Professional",
            "subcategory":"Engineering",
            "type":"Services"
        }
    ],
    "sg:phone":"+61 3 9515 5237",
    "sg:postcode":"3149",
    "sg:province":"VIC",
    "sg:tags":[
        "electronic",
        "engineer"
    ],
    "wof:name":"Eucatec Enterprises",
    "wof:placetype":"venue"
},
  "geometry": {"coordinates":[145.14169311500001,-37.8638534546],"type":"Point"}
}