{
  "type": "Feature",
  "properties": {
    "addr:full":"Winters La Narre Warren North VIC 3804",
    "addr:postcode":"3804",
    "addr:street":"Winters La",
    "iso:country":"AU",
    "sg:address":"Winters La",
    "sg:city":"Narre Warren North",
    "sg:classifiers":[
        {
            "category":"Education",
            "subcategory":"Kindergarten",
            "type":"Public Place"
        }
    ],
    "sg:phone":"+61 3 9796 8259",
    "sg:postcode":"3804",
    "sg:province":"VIC",
    "sg:tags":[
        "pre-schools"
    ],
    "wof:name":"Narre Warren North Pre-School Centre",
    "wof:placetype":"venue"
},
  "geometry": {"coordinates":[145.31582641599999,-37.979385376],"type":"Point"}
}