{
  "type": "Feature",
  "properties": {
    "addr:full":"PO Box 89 Chadstone VIC 3148",
    "addr:postcode":"3148",
    "iso:country":"AU",
    "sg:address":"PO Box 89",
    "sg:city":"Chadstone",
    "sg:classifiers":[
        {
            "category":"Professional",
            "subcategory":"Art Services",
            "type":"Services"
        }
    ],
    "sg:phone":"+61 419 884 756",
    "sg:postcode":"3148",
    "sg:province":"VIC",
    "sg:tags":[
        "decorator",
        "painter"
    ],
    "wof:name":"Trends",
    "wof:placetype":"venue"
},
  "geometry": {"coordinates":[145.096893311,-37.881111145],"type":"Point"}
}