{
  "type": "Feature",
  "properties": {
    "addr:full":"120 Mourilyan Rd East Innisfail QLD 4860",
    "addr:housenumber":"120",
    "addr:postcode":"4860",
    "addr:street":"Mourilyan Rd",
    "iso:country":"AU",
    "sg:address":"120 Mourilyan Rd",
    "sg:city":"East Innisfail",
    "sg:classifiers":[
        {
            "category":"Building & Trades",
            "subcategory":"Construction",
            "type":"Services"
        }
    ],
    "sg:phone":"+61 7 4061 6366",
    "sg:postcode":"4860",
    "sg:province":"QLD",
    "sg:tags":[
        "contractor"
    ],
    "wof:name":"Kyabra Property Development Pty Ltd",
    "wof:placetype":"venue"
},
  "geometry": {"coordinates":[146.03237915,-17.5390129089],"type":"Point"}
}