{
  "type": "Feature",
  "properties": {
    "addr:full":"Shop 20 Ingle Farm Shopping Centre Montague Rd Ingle Farm SA 5098",
    "addr:housenumber":"shop 20",
    "addr:postcode":"5098",
    "addr:street":"Montague Rd",
    "iso:country":"AU",
    "sg:address":"Shop 20 Ingle Farm Shopping Centre Montague Rd",
    "sg:city":"Ingle Farm",
    "sg:classifiers":[
        {
            "category":"Shopping",
            "subcategory":"Jewelry",
            "type":"Retail Goods"
        }
    ],
    "sg:phone":"+61 8 8264 3540",
    "sg:postcode":"5098",
    "sg:province":"SA",
    "sg:tags":[
        "jeweller"
    ],
    "wof:name":"Beaumont Jewellers",
    "wof:placetype":"venue"
},
  "geometry": {"coordinates":[138.650756836,-34.828704834],"type":"Point"}
}