{
  "type": "Feature",
  "properties": {
    "iso:country":"AU",
    "sg:address":"14 Bruce Ave",
    "sg:city":"Caringbah",
    "sg:classifiers":[
        {
            "category":"Building & Trades",
            "subcategory":"Construction",
            "type":"Services"
        }
    ],
    "sg:phone":"+61 2 9524 9485",
    "sg:postcode":"2229",
    "sg:province":"NSW",
    "sg:tags":[
        "plasterboard",
        "plasterer",
        "fixer"
    ],
    "wof:name":"Evans G",
    "wof:placetype":"venue"
},
  "geometry": {"coordinates":[151.11378479000001,-34.0579605103],"type":"Point"}
}