{
  "type": "Feature",
  "properties": {
    "iso:country":"AU",
    "sg:address":"Cnr Nineteenth Ave & Avocado St",
    "sg:city":"Elanora",
    "sg:classifiers":[
        {
            "category":"Education",
            "subcategory":"School",
            "type":"Public Place"
        }
    ],
    "sg:phone":"+61 7 5533 9299",
    "sg:postcode":"4221",
    "sg:province":"QLD",
    "sg:tags":[
        "state",
        "except",
        "nsw"
    ],
    "wof:name":"Elanora Secondary School",
    "wof:placetype":"venue"
},
  "geometry": {"coordinates":[153.45921325699999,-28.1270103455],"type":"Point"}
}