{
  "type": "Feature",
  "properties": {
    "addr:full":"10 Ryan Rd Mt Isa QLD 4825",
    "addr:housenumber":"10",
    "addr:postcode":"4825",
    "addr:street":"Ryan Rd",
    "iso:country":"AU",
    "sg:address":"10 Ryan Rd",
    "sg:city":"Mt Isa",
    "sg:classifiers":[
        {
            "category":"Manufacturing",
            "subcategory":"Retail Goods",
            "type":"Manufacturing & Wholesale Goods"
        }
    ],
    "sg:phone":"+61 1800 810 568",
    "sg:postcode":"4825",
    "sg:province":"QLD",
    "sg:tags":[
        "merchant",
        "pump",
        "mfrs"
    ],
    "wof:name":"Prime Pump Co.",
    "wof:placetype":"venue"
},
  "geometry": {"coordinates":[139.497635,-20.70236],"type":"Point"}
}