{
  "type": "Feature",
  "properties": {
    "iso:country":"AU",
    "sg:address":"44 Days Rd",
    "sg:city":"Grange",
    "sg:classifiers":[
        {
            "category":"Education",
            "subcategory":"Special Training",
            "type":"Public Place"
        }
    ],
    "sg:phone":"+61 7 3352 4622",
    "sg:postcode":"4051",
    "sg:province":"QLD",
    "sg:tags":[
        "tuition-educational"
    ],
    "wof:name":"Fruition Tuition",
    "wof:placetype":"venue"
},
  "geometry": {"coordinates":[153.021240234,-27.4269657135],"type":"Point"}
}