{
  "type": "Feature",
  "properties": {
    "addr:full":"146 Vimiera Rd Eastwood NSW 2122",
    "addr:housenumber":"146",
    "addr:postcode":"2122",
    "addr:street":"Vimiera Rd",
    "iso:country":"AU",
    "sg:address":"146 Vimiera Rd",
    "sg:city":"Eastwood",
    "sg:classifiers":[
        {
            "category":"Social Services",
            "subcategory":"Child Care",
            "type":"Services"
        }
    ],
    "sg:phone":"+61 2 9869 7100",
    "sg:postcode":"2122",
    "sg:province":"NSW",
    "wof:name":"Acre Woods Childcare- Eastwood",
    "wof:placetype":"venue"
},
  "geometry": {"coordinates":[151.09742736800001,-33.7767868042],"type":"Point"}
}