{
  "type": "Feature",
  "properties": {
    "addr:full":"Shop 6, 385 Pacific Hwy Crows Nest NSW 2065",
    "addr:housenumber":"shop 6 385",
    "addr:postcode":"2065",
    "addr:street":"Pacific Hwy",
    "iso:country":"AU",
    "sg:address":"Shop 6, 385 Pacific Hwy",
    "sg:city":"Crows Nest",
    "sg:classifiers":[
        {
            "category":"Professional",
            "subcategory":"Employment Agencies",
            "type":"Services"
        }
    ],
    "sg:phone":"+61 2 9966 1077",
    "sg:postcode":"2065",
    "sg:province":"NSW",
    "sg:tags":[
        "provider",
        "internet"
    ],
    "wof:name":"Internet Shop The",
    "wof:placetype":"venue"
},
  "geometry": {"coordinates":[151.19866943400001,-33.8252754211],"type":"Point"}
}