{
  "type": "Feature",
  "properties": {
    "iso:country":"AU",
    "sg:address":"72 Lachlan St",
    "sg:city":"Hay",
    "sg:classifiers":[
        {
            "category":"Travel",
            "subcategory":"Hotels & Motels",
            "type":"Entertainment"
        }
    ],
    "sg:phone":"+61 2 6993 3411",
    "sg:postcode":"2711",
    "sg:province":"NSW",
    "sg:tags":[
        "accommodation"
    ],
    "wof:name":"Caledonian Hotel",
    "wof:placetype":"venue"
},
  "geometry": {"coordinates":[144.84361267099999,-34.509765625],"type":"Point"}
}