{
  "type": "Feature",
  "properties": {
    "addr:full":"Belmont, Shop K 227 Belmont Ave Cloverdale WA 6105",
    "addr:housenumber":"227",
    "addr:postcode":"6105",
    "addr:street":"Belmont Ave",
    "iso:country":"AU",
    "sg:address":"Belmont, Shop K 227 Belmont Ave",
    "sg:city":"Cloverdale",
    "sg:classifiers":[
        {
            "category":"Cafe",
            "type":"Food & Drink"
        }
    ],
    "sg:phone":"+61 8 9277 6695",
    "sg:postcode":"6105",
    "sg:province":"WA",
    "wof:name":"Caffissimo",
    "wof:placetype":"venue"
},
  "geometry": {"coordinates":[115.93396758999999,-31.9660186768],"type":"Point"}
}