{
  "type": "Feature",
  "properties": {
    "addr:full":"4 Palm Pl Wilson WA 6107",
    "addr:housenumber":"4",
    "addr:postcode":"6107",
    "addr:street":"Palm Pl",
    "iso:country":"AU",
    "sg:address":"4 Palm Pl",
    "sg:city":"Wilson",
    "sg:classifiers":[
        {
            "category":"Arts & Performance",
            "subcategory":"Dance",
            "type":"Entertainment"
        }
    ],
    "sg:phone":"+61 8 9458 2113",
    "sg:postcode":"6107",
    "sg:province":"WA",
    "sg:tags":[
        "theatrical",
        "ballet",
        "tuition"
    ],
    "wof:name":"Glenda Foreman",
    "wof:placetype":"venue"
},
  "geometry": {"coordinates":[115.91983795199999,-32.0173797607],"type":"Point"}
}