{
  "type": "Feature",
  "properties": {
    "addr:full":"Factory 3, 766 Burwood Hwy Ferntree Gully VIC 3156",
    "addr:housenumber":"766",
    "addr:postcode":"3156",
    "addr:street":"Burwood Hwy",
    "iso:country":"AU",
    "sg:address":"Factory 3, 766 Burwood Hwy",
    "sg:city":"Ferntree Gully",
    "sg:classifiers":[
        {
            "category":"Home & Garden",
            "subcategory":"Furniture",
            "type":"Retail Goods"
        }
    ],
    "sg:phone":"+61 3 9752 2264",
    "sg:postcode":"3156",
    "sg:province":"VIC",
    "sg:tags":[
        "business"
    ],
    "wof:name":"Direct Office Solutions",
    "wof:placetype":"venue"
},
  "geometry": {"coordinates":[145.30078125,-37.8910903931],"type":"Point"}
}