{
  "type": "Feature",
  "properties": {
    "addr:full":"Pacific Hwy Newrybar NSW 2479",
    "addr:postcode":"2479",
    "addr:street":"Pacific Hwy",
    "iso:country":"AU",
    "sg:address":"Pacific Hwy",
    "sg:city":"Newrybar",
    "sg:classifiers":[
        {
            "category":"Farming",
            "subcategory":"Nursery",
            "type":"Manufacturing & Wholesale Goods"
        }
    ],
    "sg:phone":"+61 2 6687 1106",
    "sg:postcode":"2479",
    "sg:province":"NSW",
    "wof:name":"Camwil Palms",
    "wof:placetype":"venue"
},
  "geometry": {"coordinates":[153.53131103499999,-28.7197818756],"type":"Point"}
}