{
  "type": "Feature",
  "properties": {
    "addr:full":"Suite 15/ 102 Princes Hwy Unanderra NSW 2526",
    "addr:housenumber":"15 / 102",
    "addr:postcode":"2526",
    "addr:street":"Princes Hwy",
    "iso:country":"AU",
    "sg:address":"Suite 15/ 102 Princes Hwy",
    "sg:city":"Unanderra",
    "sg:classifiers":[
        {
            "category":"Government",
            "subcategory":"Post Office",
            "type":"Public Place"
        }
    ],
    "sg:phone":"+61 2 4272 9034",
    "sg:postcode":"2526",
    "sg:province":"NSW",
    "sg:tags":[
        "equipment",
        "hole",
        "contractor"
    ],
    "wof:name":"National Power Service Pty Ltd",
    "wof:placetype":"venue"
},
  "geometry": {"coordinates":[150.84490966800001,-34.4546394348],"type":"Point"}
}