{
  "type": "Feature",
  "properties": {
    "addr:full":"1st Floor 118 Halifax St Adelaide SA 5000",
    "addr:housenumber":"118",
    "addr:postcode":"5000",
    "addr:street":"Halifax St",
    "iso:country":"AU",
    "sg:address":"1st Floor 118 Halifax St",
    "sg:city":"Adelaide",
    "sg:classifiers":[
        {
            "category":"Travel",
            "subcategory":"Travel Agent",
            "type":"Entertainment"
        }
    ],
    "sg:phone":"+61 8 8223 2177",
    "sg:postcode":"5000",
    "sg:province":"SA",
    "sg:tags":[
        "consultant"
    ],
    "wof:name":"Leonore Stratford Travel Consultant",
    "wof:placetype":"venue"
},
  "geometry": {"coordinates":[138.60479736299999,-34.932472229],"type":"Point"}
}