{
  "type": "Feature",
  "properties": {
    "addr:full":"114 Balhan Rd Rocklea QLD 4106",
    "addr:housenumber":"114",
    "addr:postcode":"4106",
    "addr:street":"Balhan Rd",
    "iso:country":"AU",
    "sg:address":"114 Balhan Rd",
    "sg:city":"Rocklea",
    "sg:classifiers":[
        {
            "category":"Retail",
            "subcategory":"Storage",
            "type":"Services"
        }
    ],
    "sg:phone":"+61 1300 766 233",
    "sg:postcode":"4106",
    "sg:province":"QLD",
    "sg:tags":[
        "removal",
        "furniture"
    ],
    "wof:name":"Grace Fine Art",
    "wof:placetype":"venue"
},
  "geometry": {"coordinates":[153.011993408,-27.5612545013],"type":"Point"}
}