{
  "type": "Feature",
  "properties": {
    "addr:full":"3 View St Burleigh Heads QLD 4220",
    "addr:housenumber":"3",
    "addr:postcode":"4220",
    "addr:street":"View St",
    "iso:country":"AU",
    "sg:address":"3 View St",
    "sg:city":"Burleigh Heads",
    "sg:classifiers":[
        {
            "category":"Building & Trades",
            "subcategory":"Construction",
            "type":"Services"
        }
    ],
    "sg:phone":"+61 419 644 597",
    "sg:postcode":"4220",
    "sg:province":"QLD",
    "sg:tags":[
        "contractor"
    ],
    "wof:name":"M G L Builders",
    "wof:placetype":"venue"
},
  "geometry": {"coordinates":[153.447189331,-28.0921821594],"type":"Point"}
}