{
  "type": "Feature",
  "properties": {
    "addr:full":"98 Forrest St Kalgoorlie WA 6430",
    "addr:housenumber":"98",
    "addr:postcode":"6430",
    "addr:street":"Forrest St",
    "iso:country":"AU",
    "sg:address":"98 Forrest St",
    "sg:city":"Kalgoorlie",
    "sg:classifiers":[
        {
            "category":"Retail",
            "subcategory":"Storage",
            "type":"Services"
        }
    ],
    "sg:phone":"+61 8 9021 6514",
    "sg:postcode":"6430",
    "sg:province":"WA",
    "sg:tags":[
        "removal",
        "furniture"
    ],
    "wof:name":"Safe & Sound Storage",
    "wof:placetype":"venue"
},
  "geometry": {"coordinates":[121.465766907,-30.7480792999],"type":"Point"}
}