{
  "type": "Feature",
  "properties": {
    "iso:country":"AU",
    "sg:address":"21c Bourbong St",
    "sg:city":"Bundaberg",
    "sg:classifiers":[
        {
            "category":"Home & Garden",
            "subcategory":"Hardware",
            "type":"Retail Goods"
        }
    ],
    "sg:phone":"+61 7 4152 3479",
    "sg:postcode":"4670",
    "sg:province":"QLD",
    "sg:tags":[
        "repair",
        "tool",
        "power"
    ],
    "wof:name":"Hansen Power Tools",
    "wof:placetype":"venue"
},
  "geometry": {"coordinates":[152.35069274899999,-24.8653774261],"type":"Point"}
}