{
  "type": "Feature",
  "properties": {
    "addr:full":"M.S.216 Henderson Drv Innisfail QLD 4860",
    "addr:postcode":"4860",
    "addr:street":"Henderson Drv",
    "iso:country":"AU",
    "sg:address":"M.S.216 Henderson Drv",
    "sg:city":"Innisfail",
    "sg:classifiers":[
        {
            "category":"Farming",
            "subcategory":"Poultry Farm",
            "type":"Manufacturing & Wholesale Goods"
        }
    ],
    "sg:phone":"+61 7 4064 4177",
    "sg:postcode":"4860",
    "sg:province":"QLD",
    "sg:tags":[
        "farmer"
    ],
    "wof:name":"Yamagishism Life Cairns Jikkenchi",
    "wof:placetype":"venue"
},
  "geometry": {"coordinates":[145.997116089,-17.5968818665],"type":"Point"}
}