{
  "type": "Feature",
  "properties": {
    "addr:full":"15 Wigzell St Littlehampton SA 5250",
    "addr:housenumber":"15",
    "addr:postcode":"5250",
    "addr:street":"Wigzell St",
    "iso:country":"AU",
    "sg:address":"15 Wigzell St",
    "sg:city":"Littlehampton",
    "sg:classifiers":[
        {
            "category":"Building & Trades",
            "subcategory":"Landscaping Services",
            "type":"Services"
        }
    ],
    "sg:phone":"+61 8 8398 2212",
    "sg:postcode":"5250",
    "sg:province":"SA",
    "sg:tags":[
        "horticultural",
        "consultant"
    ],
    "wof:name":"Wilton Alan",
    "wof:placetype":"venue"
},
  "geometry": {"coordinates":[138.87106323200001,-35.0503234863],"type":"Point"}
}