{
  "type": "Feature",
  "properties": {
    "addr:full":"108 Wardell Rd Alstonville NSW 2477",
    "addr:housenumber":"108",
    "addr:postcode":"2477",
    "addr:street":"Wardell Rd",
    "iso:country":"AU",
    "sg:address":"108 Wardell Rd",
    "sg:city":"Alstonville",
    "sg:classifiers":[
        {
            "category":"Shopping",
            "subcategory":"Musical Instruments",
            "type":"Retail Goods"
        }
    ],
    "sg:phone":"+61 417 713 682",
    "sg:postcode":"2477",
    "sg:province":"NSW",
    "sg:tags":[
        "musician",
        "agent"
    ],
    "wof:name":"Corazon Ministies Ltd",
    "wof:placetype":"venue"
},
  "geometry": {"coordinates":[153.436676025,-28.8502483368],"type":"Point"}
}