{
  "type": "Feature",
  "properties": {
    "addr:full":"PO Box 301 Crows Nest NSW 2065",
    "addr:postcode":"2065",
    "iso:country":"AU",
    "sg:address":"PO Box 301",
    "sg:city":"Crows Nest",
    "sg:classifiers":[
        {
            "category":"Utilities",
            "subcategory":"Telephone",
            "type":"Services"
        }
    ],
    "sg:phone":"+61 2 9978 7009",
    "sg:postcode":"2065",
    "sg:province":"NSW",
    "sg:tags":[
        "equipment",
        "system"
    ],
    "wof:name":"Open Access",
    "wof:placetype":"venue"
},
  "geometry": {"coordinates":[151.198928833,-33.8221549988],"type":"Point"}
}