{
  "type": "Feature",
  "properties": {
    "addr:full":"Lot 51 Cnr Simmons & Racecourse Drv Ballina NSW 2478",
    "addr:housenumber":"cnr",
    "addr:postcode":"2478",
    "addr:street":"Simmons;Drv",
    "iso:country":"AU",
    "sg:address":"Lot 51 Cnr Simmons & Racecourse Drv",
    "sg:city":"Ballina",
    "sg:classifiers":[
        {
            "category":"Autos & Motor Vehicles",
            "subcategory":"Auto Supplies",
            "type":"Retail Goods"
        }
    ],
    "sg:phone":"+61 2 6686 4190",
    "sg:postcode":"2478",
    "sg:province":"NSW",
    "sg:tags":[
        "paint",
        "automotive"
    ],
    "wof:name":"Peter Brown Paint & Panel",
    "wof:placetype":"venue"
},
  "geometry": {"coordinates":[153.55778503400001,-28.8496513367],"type":"Point"}
}