{
  "type": "Feature",
  "properties": {
    "iso:country":"AU",
    "sg:address":"195 Fingal St",
    "sg:city":"Tarragindi",
    "sg:classifiers":[
        {
            "category":"Personal",
            "subcategory":"Massage",
            "type":"Services"
        }
    ],
    "sg:phone":"+61 7 3892 7920",
    "sg:postcode":"4121",
    "sg:province":"QLD",
    "sg:tags":[
        "therapy"
    ],
    "wof:name":"Balanced Body Muscle Therapy",
    "wof:placetype":"venue"
},
  "geometry": {"coordinates":[153.044998169,-27.5281467438],"type":"Point"}
}