{
  "type": "Feature",
  "properties": {
    "iso:country":"AU",
    "sg:address":"35 Downard St",
    "sg:city":"Braeside",
    "sg:classifiers":[
        {
            "category":"Autos & Motor Vehicles",
            "subcategory":"Boat Sales",
            "type":"Retail Goods"
        }
    ],
    "sg:phone":"+61 3 9587 7744",
    "sg:postcode":"3195",
    "sg:province":"VIC",
    "sg:tags":[
        "equipment",
        "yacht"
    ],
    "wof:name":"BLA",
    "wof:placetype":"venue"
},
  "geometry": {"coordinates":[145.11090087900001,-37.9928283691],"type":"Point"}
}