{
  "type": "Feature",
  "properties": {
    "iso:country":"AU",
    "sg:address":"Myer Level 1 240 Margaret St",
    "sg:city":"Toowoomba",
    "sg:classifiers":[
        {
            "category":"Shopping",
            "subcategory":"Optical Goods",
            "type":"Retail Goods"
        }
    ],
    "sg:phone":"+61 7 4639 4130",
    "sg:postcode":"4350",
    "sg:province":"QLD",
    "sg:tags":[
        "dispenser",
        "prescription"
    ],
    "wof:name":"The Optical Superstore",
    "wof:placetype":"venue"
},
  "geometry": {"coordinates":[151.95282,-27.560789],"type":"Point"}
}