{
  "type": "Feature",
  "properties": {
    "iso:country":"AU",
    "sg:address":"537 Sandgate Rd",
    "sg:city":"Clayfield",
    "sg:classifiers":[
        {
            "category":"Health Services",
            "subcategory":"Dentist",
            "type":"Services"
        }
    ],
    "sg:phone":"+61 7 3862 2018",
    "sg:postcode":"4011",
    "sg:province":"QLD",
    "wof:name":"Podesta Victor A",
    "wof:placetype":"venue"
},
  "geometry": {"coordinates":[153.05081200000001,-27.425766],"type":"Point"}
}