{
  "type": "Feature",
  "properties": {
    "iso:country":"AU",
    "sg:address":"74 Melville St",
    "sg:city":"Numurkah",
    "sg:classifiers":[
        {
            "category":"Shopping",
            "subcategory":"Crafts & Fabrics",
            "type":"Retail Goods"
        }
    ],
    "sg:phone":"+61 3 5862 1943",
    "sg:postcode":"3636",
    "sg:province":"VIC",
    "sg:tags":[
        "supply"
    ],
    "wof:name":"Common Thread The",
    "wof:placetype":"venue"
},
  "geometry": {"coordinates":[145.44221496599999,-36.0909309387],"type":"Point"}
}