{
  "type": "Feature",
  "properties": {
    "addr:full":"18 Station St Wentworthville NSW 2145",
    "addr:housenumber":"18",
    "addr:postcode":"2145",
    "addr:street":"Station St",
    "iso:country":"AU",
    "sg:address":"18 Station St",
    "sg:city":"Wentworthville",
    "sg:classifiers":[
        {
            "category":"Health Services",
            "subcategory":"Doctor",
            "type":"Services"
        }
    ],
    "sg:phone":"+61 2 9636 4500",
    "sg:postcode":"2145",
    "sg:province":"NSW",
    "sg:tags":[
        "medical",
        "practitioner"
    ],
    "wof:name":"Wong Vincent Dr",
    "wof:placetype":"venue"
},
  "geometry": {"coordinates":[150.972366333,-33.807762146],"type":"Point"}
}