{
  "type": "Feature",
  "properties": {
    "iso:country":"AU",
    "sg:address":"56 Vindex St",
    "sg:city":"Winton",
    "sg:classifiers":[
        {
            "category":"Building & Trades",
            "subcategory":"Construction",
            "type":"Services"
        }
    ],
    "sg:phone":"+61 7 4657 1485",
    "sg:postcode":"4735",
    "sg:province":"QLD",
    "sg:tags":[
        "earth",
        "excavating",
        "moving",
        "contractor"
    ],
    "wof:name":"Kavanagh D F & M M",
    "wof:placetype":"venue"
},
  "geometry": {"coordinates":[143.041611,-22.389709],"type":"Point"}
}