{
  "type": "Feature",
  "properties": {
    "iso:country":"AU",
    "sg:address":"22 Camberwell Rd",
    "sg:city":"Hawthorn East",
    "sg:classifiers":[
        {
            "category":"Home & Garden",
            "subcategory":"Furniture",
            "type":"Retail Goods"
        }
    ],
    "sg:phone":"+61 3 9813 0200",
    "sg:postcode":"3123",
    "sg:province":"VIC",
    "sg:tags":[
        "business"
    ],
    "wof:name":"Home Office Made Easy Pty Ltd",
    "wof:placetype":"venue"
},
  "geometry": {"coordinates":[145.0493927,-37.8252220154],"type":"Point"}
}