{
  "type": "Feature",
  "properties": {
    "addr:full":"71 Charles St Moonah TAS 7009",
    "addr:housenumber":"71",
    "addr:postcode":"7009",
    "addr:street":"Charles St",
    "iso:country":"AU",
    "sg:address":"71 Charles St",
    "sg:city":"Moonah",
    "sg:classifiers":[
        {
            "category":"Manufacturing",
            "subcategory":"Tools & Machinery",
            "type":"Manufacturing & Wholesale Goods"
        }
    ],
    "sg:phone":"+61 3 6274 1880",
    "sg:postcode":"7009",
    "sg:province":"TAS",
    "sg:tags":[
        "fastener",
        "industrial"
    ],
    "wof:name":"Infix",
    "wof:placetype":"venue"
},
  "geometry": {"coordinates":[147.290481567,-42.8432846069],"type":"Point"}
}