{
  "type": "Feature",
  "properties": {
    "addr:full":"Suite 63, 25A Marks St Naremburn NSW 2065",
    "addr:housenumber":"25a",
    "addr:postcode":"2065",
    "addr:street":"Marks St",
    "iso:country":"AU",
    "sg:address":"Suite 63, 25A Marks St",
    "sg:city":"Naremburn",
    "sg:classifiers":[
        {
            "category":"Professional",
            "subcategory":"Computer Services",
            "type":"Services"
        }
    ],
    "sg:phone":"+61 2 9439 2989",
    "sg:postcode":"2065",
    "sg:province":"NSW",
    "sg:tags":[
        "consultant",
        "system"
    ],
    "wof:name":"BestMinds Consulting",
    "wof:placetype":"venue"
},
  "geometry": {"coordinates":[151.20645141599999,-33.8188362122],"type":"Point"}
}