{
  "type": "Feature",
  "properties": {
    "addr:full":"67 Jacks Ave Dingley Village VIC 3172",
    "addr:housenumber":"67",
    "addr:postcode":"3172",
    "addr:street":"Jacks Ave",
    "iso:country":"AU",
    "sg:address":"67 Jacks Ave",
    "sg:city":"Dingley Village",
    "sg:classifiers":[
        {
            "category":"Education",
            "subcategory":"Kindergarten",
            "type":"Public Place"
        }
    ],
    "sg:phone":"+61 3 9551 2425",
    "sg:postcode":"3172",
    "sg:province":"VIC",
    "sg:tags":[
        "pre-schools"
    ],
    "wof:name":"Dingley Kindergarten Centres Inc",
    "wof:placetype":"venue"
},
  "geometry": {"coordinates":[145.12588500999999,-37.9843711853],"type":"Point"}
}