{
  "type": "Feature",
  "properties": {
    "addr:full":"71 Frasers Rd Ashgrove QLD 4060",
    "addr:housenumber":"71",
    "addr:postcode":"4060",
    "addr:street":"Frasers Rd",
    "iso:country":"AU",
    "sg:address":"71 Frasers Rd",
    "sg:city":"Ashgrove",
    "sg:classifiers":[
        {
            "category":"Banks & Credit Unions",
            "subcategory":"Financial Services",
            "type":"Services"
        }
    ],
    "sg:phone":"+61 7 3366 9266",
    "sg:postcode":"4060",
    "sg:province":"QLD",
    "sg:tags":[
        "loan",
        "finance",
        "mortgage"
    ],
    "wof:name":"Oasis Loans",
    "wof:placetype":"venue"
},
  "geometry": {"coordinates":[152.984207153,-27.4380397797],"type":"Point"}
}