{
  "type": "Feature",
  "properties": {
    "addr:full":"Old Chittaway Rd Ourimbah NSW 2258",
    "addr:postcode":"2258",
    "addr:street":"Chittaway Rd",
    "iso:country":"AU",
    "sg:address":"Old Chittaway Rd",
    "sg:city":"Ourimbah",
    "sg:classifiers":[
        {
            "category":"Utilities",
            "subcategory":"Electric",
            "type":"Services"
        }
    ],
    "sg:phone":"+61 416 294 921",
    "sg:postcode":"2258",
    "sg:province":"NSW",
    "sg:tags":[
        "electrical",
        "contractor"
    ],
    "wof:name":"MWC Electrical Pty Ltd",
    "wof:placetype":"venue"
},
  "geometry": {"coordinates":[151.38705444300001,-33.343585968],"type":"Point"}
}