{
  "type": "Feature",
  "properties": {
    "addr:full":"119 Brighton Rd Sandgate QLD 4017",
    "addr:housenumber":"119",
    "addr:postcode":"4017",
    "addr:street":"Brighton Rd",
    "iso:country":"AU",
    "sg:address":"119 Brighton Rd",
    "sg:city":"Sandgate",
    "sg:classifiers":[
        {
            "category":"Personal",
            "subcategory":"Massage",
            "type":"Services"
        }
    ],
    "sg:phone":"+61 7 3869 1099",
    "sg:postcode":"4017",
    "sg:province":"QLD",
    "sg:tags":[
        "therapy"
    ],
    "wof:name":"Carson Kathy",
    "wof:placetype":"venue"
},
  "geometry": {"coordinates":[153.06785583499999,-27.3177375793],"type":"Point"}
}