{
  "type": "Feature",
  "properties": {
    "iso:country":"AU",
    "sg:address":"19 Leigh Crs",
    "sg:city":"Ulladulla",
    "sg:classifiers":[
        {
            "category":"Home & Garden",
            "subcategory":"Carpets & Floor Coverings",
            "type":"Retail Goods"
        }
    ],
    "sg:phone":"+61 2 4454 2081",
    "sg:postcode":"2539",
    "sg:province":"NSW",
    "sg:tags":[
        "tile",
        "wall",
        "layer"
    ],
    "wof:name":"Craig Puglisi",
    "wof:placetype":"venue"
},
  "geometry": {"coordinates":[150.475631714,-35.3509788513],"type":"Point"}
}