{
  "type": "Feature",
  "properties": {
    "iso:country":"AU",
    "sg:address":"76a Paddington St",
    "sg:city":"Paddington",
    "sg:classifiers":[
        {
            "category":"Shopping",
            "subcategory":"Clothing, Apparel, & Fashions",
            "type":"Retail Goods"
        }
    ],
    "sg:phone":"+61 2 9362 0085",
    "sg:postcode":"2021",
    "sg:province":"NSW",
    "sg:tags":[
        "maternity",
        "wear"
    ],
    "wof:name":"Fragile",
    "wof:placetype":"venue"
},
  "geometry": {"coordinates":[151.23246765100001,-33.8852348328],"type":"Point"}
}