{
  "type": "Feature",
  "properties": {
    "addr:full":"PO Box 864 Sanderson NT 0813",
    "addr:postcode":"nt 0813",
    "iso:country":"AU",
    "sg:address":"PO Box 864",
    "sg:city":"Sanderson",
    "sg:classifiers":[
        {
            "category":"Personal",
            "subcategory":"Beauty Salon",
            "type":"Services"
        }
    ],
    "sg:phone":"+61 402 473 561",
    "sg:postcode":"0813",
    "sg:province":"NT",
    "wof:name":"Defining Beauty",
    "wof:placetype":"venue"
},
  "geometry": {"coordinates":[130.89891052199999,-12.3905000687],"type":"Point"}
}