{
  "type": "Feature",
  "properties": {
    "addr:full":"36 McCoy St Melville WA 6156",
    "addr:housenumber":"36",
    "addr:postcode":"6156",
    "addr:street":"Mccoy St",
    "iso:country":"AU",
    "sg:address":"36 McCoy St",
    "sg:city":"Melville",
    "sg:classifiers":[
        {
            "category":"Autos & Motor Vehicles",
            "subcategory":"Auto Supplies",
            "type":"Retail Goods"
        }
    ],
    "sg:phone":"+61 8 9317 5777",
    "sg:postcode":"6156",
    "sg:province":"WA",
    "sg:tags":[
        "part",
        "cycles",
        "accessory"
    ],
    "wof:name":"Prestige Honda",
    "wof:placetype":"venue"
},
  "geometry": {"coordinates":[115.811378,-32.043457],"type":"Point"}
}