{
  "type": "Feature",
  "properties": {
    "iso:country":"AU",
    "sg:address":"8 Avon St",
    "sg:city":"Stratford",
    "sg:classifiers":[
        {
            "category":"Building & Trades",
            "subcategory":"Construction",
            "type":"Services"
        }
    ],
    "sg:phone":"+61 7 4055 1803",
    "sg:postcode":"4870",
    "sg:province":"QLD",
    "sg:tags":[
        "renovation",
        "alterations",
        "extension",
        "contractor"
    ],
    "wof:name":"Chris Footner",
    "wof:placetype":"venue"
},
  "geometry": {"coordinates":[145.72343444800001,-16.8787231445],"type":"Point"}
}