{
  "type": "Feature",
  "properties": {
    "addr:full":"45 Murray St Anglesea VIC 3230",
    "addr:housenumber":"45",
    "addr:postcode":"3230",
    "addr:street":"Murray St",
    "iso:country":"AU",
    "sg:address":"45 Murray St",
    "sg:city":"Anglesea",
    "sg:classifiers":[
        {
            "category":"Travel",
            "subcategory":"Hotels & Motels",
            "type":"Entertainment"
        }
    ],
    "sg:phone":"+61 3 5263 1640",
    "sg:postcode":"3230",
    "sg:province":"VIC",
    "wof:name":"Anglesea BIG4 Holiday Park",
    "wof:placetype":"venue"
},
  "geometry": {"coordinates":[144.18156400000001,-38.409416],"type":"Point"}
}