{
  "type": "Feature",
  "properties": {
    "iso:country":"AU",
    "sg:address":"33 Clements Ave",
    "sg:city":"Bundoora",
    "sg:classifiers":[
        {
            "category":"Mining & Drilling",
            "type":"Manufacturing & Wholesale Goods"
        }
    ],
    "sg:phone":"+61 3 9467 8888",
    "sg:postcode":"3083",
    "sg:province":"VIC",
    "sg:tags":[
        "boring",
        "contractor"
    ],
    "wof:name":"Ace Drilling & Construction",
    "wof:placetype":"venue"
},
  "geometry": {"coordinates":[145.07383727999999,-37.703037262],"type":"Point"}
}