{
  "type": "Feature",
  "properties": {
    "iso:country":"AU",
    "sg:address":"1108 Waugh Rd",
    "sg:city":"Albury North",
    "sg:classifiers":[
        {
            "category":"Real Estate",
            "subcategory":"Real Estate Agent",
            "type":"Services"
        }
    ],
    "sg:phone":"+61 2 6025 5258",
    "sg:postcode":"2640",
    "sg:province":"NSW",
    "wof:name":"Kelvin Gilder Property Sales",
    "wof:placetype":"venue"
},
  "geometry": {"coordinates":[146.93284606899999,-36.0526695251],"type":"Point"}
}