{
  "type": "Feature",
  "properties": {
    "iso:country":"AU",
    "sg:address":"Shop 21",
    "sg:city":"a, Clifford Gardens, James St, Toowoomba",
    "sg:classifiers":[
        {
            "category":"Shopping",
            "type":"Retail Goods"
        }
    ],
    "sg:phone":"+61 7 4633 0166",
    "sg:postcode":"4350",
    "sg:province":"QLD",
    "sg:tags":[
        "clearance",
        "factory",
        "outlet"
    ],
    "wof:name":"Givoni",
    "wof:placetype":"venue"
},
  "geometry": {"coordinates":[151.92970299999999,-27.565884],"type":"Point"}
}