{
  "type": "Feature",
  "properties": {
    "addr:full":"28 Princess Mary St St Marys NSW 2760",
    "addr:housenumber":"28",
    "addr:postcode":"2760",
    "addr:street":"Princess Mary St",
    "iso:country":"AU",
    "sg:address":"28 Princess Mary St",
    "sg:city":"St Marys",
    "sg:classifiers":[
        {
            "category":"Health Services",
            "subcategory":"Chiropractor",
            "type":"Services"
        }
    ],
    "sg:phone":"+61 2 9623 3466",
    "sg:postcode":"2760",
    "sg:province":"NSW",
    "wof:name":"St Marys Chiropractic Centre",
    "wof:placetype":"venue"
},
  "geometry": {"coordinates":[150.77052307100001,-33.7710456848],"type":"Point"}
}