{
  "type": "Feature",
  "properties": {
    "iso:country":"AU",
    "sg:address":"Goodwood Rd",
    "sg:city":"Capel",
    "sg:classifiers":[
        {
            "category":"Food & Beverages",
            "subcategory":"Meat & Fish",
            "type":"Retail Goods"
        }
    ],
    "sg:phone":"+61 8 9727 2288",
    "sg:postcode":"6271",
    "sg:province":"WA",
    "sg:tags":[
        "aquaculture"
    ],
    "wof:name":"Capel Marron",
    "wof:placetype":"venue"
},
  "geometry": {"coordinates":[115.56124115,-33.5584602356],"type":"Point"}
}