{
  "type": "Feature",
  "properties": {
    "addr:full":"53 Greensborough Hwy Macleod VIC 3085",
    "addr:housenumber":"53",
    "addr:postcode":"3085",
    "addr:street":"Greensborough Hwy",
    "iso:country":"AU",
    "sg:address":"53 Greensborough Hwy",
    "sg:city":"Macleod",
    "sg:classifiers":[
        {
            "category":"Education",
            "subcategory":"Kindergarten",
            "type":"Public Place"
        }
    ],
    "sg:phone":"+61 3 9459 1384",
    "sg:postcode":"3085",
    "sg:province":"VIC",
    "sg:tags":[
        "pre-schools"
    ],
    "wof:name":"Rainbow Childrens Early Learning Centre",
    "wof:placetype":"venue"
},
  "geometry": {"coordinates":[145.081665039,-37.7168540955],"type":"Point"}
}