{
  "type": "Feature",
  "properties": {
    "addr:full":"Lvl 1, 155 Fullarton Rd Rose Park SA 5067",
    "addr:housenumber":"155",
    "addr:postcode":"5067",
    "addr:street":"Fullarton Rd Rose",
    "iso:country":"AU",
    "sg:address":"Lvl 1, 155 Fullarton Rd",
    "sg:city":"Rose Park",
    "sg:classifiers":[
        {
            "category":"Banks & Credit Unions",
            "subcategory":"Financial Services",
            "type":"Services"
        }
    ],
    "sg:phone":"+61 8 8331 9099",
    "sg:postcode":"5067",
    "sg:province":"SA",
    "sg:tags":[
        "planning"
    ],
    "wof:name":"Genesys Wealth Advisers",
    "wof:placetype":"venue"
},
  "geometry": {"coordinates":[138.62416076700001,-34.9316673279],"type":"Point"}
}