{
  "type": "Feature",
  "properties": {
    "iso:country":"AU",
    "sg:address":"364 Victoria Pl",
    "sg:city":"Drummoyne",
    "sg:classifiers":[
        {
            "category":"Retail",
            "subcategory":"Auto Repair",
            "type":"Services"
        }
    ],
    "sg:phone":"+61 2 9181 5166",
    "sg:postcode":"2047",
    "sg:province":"NSW",
    "sg:tags":[
        "repairer",
        "motor",
        "engineer"
    ],
    "wof:name":"Drummoyne Auto Care",
    "wof:placetype":"venue"
},
  "geometry": {"coordinates":[151.145645,-33.844692],"type":"Point"}
}