{
  "type": "Feature",
  "properties": {
    "addr:full":"411 Main St Kangaroo Point QLD 4169",
    "addr:housenumber":"411",
    "addr:postcode":"4169",
    "addr:street":"Main St",
    "iso:country":"AU",
    "sg:address":"411 Main St",
    "sg:city":"Kangaroo Point",
    "sg:classifiers":[
        {
            "category":"Health Services",
            "subcategory":"Nursing And Care Facility",
            "type":"Services"
        }
    ],
    "sg:phone":"+61 7 3240 1111",
    "sg:postcode":"4169",
    "sg:province":"QLD",
    "sg:tags":[
        "home"
    ],
    "wof:name":"Lilian Cooper Nursing home",
    "wof:placetype":"venue"
},
  "geometry": {"coordinates":[153.035446167,-27.4742107391],"type":"Point"}
}