{
  "type": "Feature",
  "properties": {
    "iso:country":"AU",
    "sg:address":"75b Regent St",
    "sg:city":"New Lambton",
    "sg:classifiers":[
        {
            "category":"Food & Beverages",
            "subcategory":"Specialty",
            "type":"Retail Goods"
        }
    ],
    "sg:phone":"+61 2 4952 7671",
    "sg:postcode":"2305",
    "sg:province":"NSW",
    "sg:tags":[
        "product",
        "health"
    ],
    "wof:name":"New Lambton Health Foods",
    "wof:placetype":"venue"
},
  "geometry": {"coordinates":[151.713425,-32.923698],"type":"Point"}
}