{
  "type": "Feature",
  "properties": {
    "addr:full":"Suite 6, 15 Stockton St Nelson Bay NSW 2315",
    "addr:housenumber":"15",
    "addr:postcode":"2315",
    "addr:street":"Stockton St",
    "iso:country":"AU",
    "sg:address":"Suite 6, 15 Stockton St",
    "sg:city":"Nelson Bay",
    "sg:classifiers":[
        {
            "category":"Building & Trades",
            "subcategory":"Construction",
            "type":"Services"
        }
    ],
    "sg:phone":"+61 2 4981 4013",
    "sg:postcode":"2315",
    "sg:province":"NSW",
    "sg:tags":[
        "contractor"
    ],
    "wof:name":"S & M Building",
    "wof:placetype":"venue"
},
  "geometry": {"coordinates":[152.143799,-32.721458],"type":"Point"}
}