{
  "type": "Feature",
  "properties": {
    "addr:full":"283 Ingham Rd Garbutt QLD 4814",
    "addr:housenumber":"283",
    "addr:postcode":"4814",
    "addr:street":"Ingham Rd",
    "iso:country":"AU",
    "sg:address":"283 Ingham Rd",
    "sg:city":"Garbutt",
    "sg:classifiers":[
        {
            "category":"Manufacturing",
            "subcategory":"Electronics",
            "type":"Manufacturing & Wholesale Goods"
        }
    ],
    "sg:phone":"+61 7 4725 3595",
    "sg:postcode":"4814",
    "sg:province":"QLD",
    "sg:tags":[
        "wholesaler",
        "equipment",
        "part",
        "mfrs",
        "refrigeration"
    ],
    "wof:name":"Bonlec Controls",
    "wof:placetype":"venue"
},
  "geometry": {"coordinates":[146.77514600000001,-19.265293],"type":"Point"}
}