{
  "type": "Feature",
  "properties": {
    "addr:full":"28a Hastings St Noosa Heads QLD 4567",
    "addr:housenumber":"28a",
    "addr:postcode":"4567",
    "addr:street":"Hastings St",
    "iso:country":"AU",
    "sg:address":"28a Hastings St",
    "sg:city":"Noosa Heads",
    "sg:classifiers":[
        {
            "category":"Real Estate",
            "subcategory":"Real Estate Agent",
            "type":"Services"
        }
    ],
    "sg:phone":"+61 7 5447 2021",
    "sg:postcode":"4567",
    "sg:province":"QLD",
    "wof:name":"Century 21",
    "wof:placetype":"venue"
},
  "geometry": {"coordinates":[153.089477539,-26.3865642548],"type":"Point"}
}