{
  "type": "Feature",
  "properties": {
    "addr:full":"75a Osborne Ave Springvale VIC 3171",
    "addr:housenumber":"75a",
    "addr:postcode":"3171",
    "addr:street":"Osborne Ave",
    "iso:country":"AU",
    "sg:address":"75a Osborne Ave",
    "sg:city":"Springvale",
    "sg:classifiers":[
        {
            "category":"Retail",
            "subcategory":"Auto Repair",
            "type":"Services"
        }
    ],
    "sg:phone":"+61 3 9548 0164",
    "sg:postcode":"3171",
    "sg:province":"VIC",
    "sg:tags":[
        "repairer",
        "motor",
        "engineer"
    ],
    "wof:name":"Ba Thang Motors",
    "wof:placetype":"venue"
},
  "geometry": {"coordinates":[145.140136719,-37.9457969666],"type":"Point"}
}