{
  "type": "Feature",
  "properties": {
    "addr:full":"Suite 3A, 559 Sydney Rd Seaforth NSW 2092",
    "addr:housenumber":"559",
    "addr:postcode":"2092",
    "addr:street":"Sydney Rd",
    "iso:country":"AU",
    "sg:address":"Suite 3A, 559 Sydney Rd",
    "sg:city":"Seaforth",
    "sg:classifiers":[
        {
            "category":"Professional",
            "subcategory":"Computer Services",
            "type":"Services"
        }
    ],
    "sg:phone":"+61 421 431 553",
    "sg:postcode":"2092",
    "sg:province":"NSW",
    "sg:tags":[
        "technical",
        "support"
    ],
    "wof:name":"Computassist",
    "wof:placetype":"venue"
},
  "geometry": {"coordinates":[151.25074768100001,-33.7974433899],"type":"Point"}
}