{
  "type": "Feature",
  "properties": {
    "iso:country":"AU",
    "sg:address":"5 Jarrah Crt",
    "sg:city":"Traralgon",
    "sg:classifiers":[
        {
            "category":"Building & Trades",
            "subcategory":"Construction",
            "type":"Services"
        }
    ],
    "sg:phone":"+61 3 5174 8938",
    "sg:postcode":"3844",
    "sg:province":"VIC",
    "sg:tags":[
        "renovation",
        "alterations",
        "extension",
        "contractor"
    ],
    "wof:name":"Kistler Frank",
    "wof:placetype":"venue"
},
  "geometry": {"coordinates":[146.51898193400001,-38.2089996338],"type":"Point"}
}