{
  "type": "Feature",
  "properties": {
    "iso:country":"AU",
    "sg:address":"Ste10/ 186 Hay St",
    "sg:city":"Subiaco",
    "sg:classifiers":[
        {
            "category":"Professional",
            "subcategory":"Computer Services",
            "type":"Services"
        }
    ],
    "sg:phone":"+61 1300 668 491",
    "sg:postcode":"6008",
    "sg:province":"WA",
    "sg:tags":[
        "repairs",
        "upgrade",
        "equipment"
    ],
    "wof:name":"Vizible Solutions",
    "wof:placetype":"venue"
},
  "geometry": {"coordinates":[115.83204650899999,-31.9469337463],"type":"Point"}
}