{
  "type": "Feature",
  "properties": {
    "iso:country":"AU",
    "sg:address":"17 Hillview St",
    "sg:city":"Sans Souci",
    "sg:classifiers":[
        {
            "category":"Community Center",
            "subcategory":"Ethnic",
            "type":"Public Place"
        }
    ],
    "sg:phone":"+61 2 9529 6954",
    "sg:postcode":"2219",
    "sg:province":"NSW",
    "sg:tags":[
        "wood",
        "carver"
    ],
    "wof:name":"Dimitriadis E",
    "wof:placetype":"venue"
},
  "geometry": {"coordinates":[151.133698,-33.986279],"type":"Point"}
}