{
  "type": "Feature",
  "properties": {
    "addr:full":"279 Lower Heidelberg Rd Ivanhoe East VIC 3079",
    "addr:housenumber":"279",
    "addr:postcode":"3079",
    "addr:street":"Lower Heidelberg Rd",
    "iso:country":"AU",
    "sg:address":"279 Lower Heidelberg Rd",
    "sg:city":"Ivanhoe East",
    "sg:classifiers":[
        {
            "category":"Professional",
            "subcategory":"Employment Agencies",
            "type":"Services"
        }
    ],
    "sg:phone":"+61 3 9499 9184",
    "sg:postcode":"3079",
    "sg:province":"VIC",
    "sg:tags":[
        "provider",
        "internet"
    ],
    "wof:name":"Consolidated Business Solutions Pty Ltd",
    "wof:placetype":"venue"
},
  "geometry": {"coordinates":[145.06016540499999,-37.7727813721],"type":"Point"}
}