{
  "type": "Feature",
  "properties": {
    "iso:country":"AU",
    "sg:address":"13 Bourke St",
    "sg:city":"North Parramatta",
    "sg:classifiers":[
        {
            "category":"Manufacturing",
            "subcategory":"Motor Vehicles & Parts",
            "type":"Manufacturing & Wholesale Goods"
        }
    ],
    "sg:phone":"+61 2 9890 5050",
    "sg:postcode":"2151",
    "sg:province":"NSW",
    "sg:tags":[
        "replacement"
    ],
    "wof:name":"Exoticar Parts Pty Ltd",
    "wof:placetype":"venue"
},
  "geometry": {"coordinates":[151.00239563,-33.7948074341],"type":"Point"}
}