{
  "type": "Feature",
  "properties": {
    "addr:full":"Landcox St Brighton East VIC 3187",
    "addr:postcode":"3187",
    "addr:street":"St",
    "iso:country":"AU",
    "sg:address":"Landcox St",
    "sg:city":"Brighton East",
    "sg:classifiers":[
        {
            "category":"Health Services",
            "subcategory":"Health Practitioner",
            "type":"Services"
        }
    ],
    "sg:phone":"+61 419 877 864",
    "sg:postcode":"3187",
    "sg:province":"VIC",
    "sg:tags":[
        "naturopath"
    ],
    "wof:name":"Body Orchid Pty Ltd, The",
    "wof:placetype":"venue"
},
  "geometry": {"coordinates":[145.01434326200001,-37.9072952271],"type":"Point"}
}