{
  "type": "Feature",
  "properties": {
    "addr:full":"111 Adelaide St (Cnr Kangaroo St East) Raymond Terrace NSW 2324",
    "addr:housenumber":"111",
    "addr:postcode":"2324",
    "addr:street":"Adelaide St Cnr Kangaroo St East",
    "iso:country":"AU",
    "sg:address":"111 Adelaide St (Cnr Kangaroo St East)",
    "sg:city":"Raymond Terrace",
    "sg:classifiers":[
        {
            "category":"Shopping",
            "subcategory":"Gifts & Souvenirs",
            "type":"Retail Goods"
        }
    ],
    "sg:phone":"+61 2 4987 1954",
    "sg:postcode":"2324",
    "sg:province":"NSW",
    "sg:tags":[
        "print",
        "poster",
        "pictures"
    ],
    "wof:name":"Cunningham's Custom Picture Frames",
    "wof:placetype":"venue"
},
  "geometry": {"coordinates":[151.749511719,-32.7602958679],"type":"Point"}
}