{
  "type": "Feature",
  "properties": {
    "addr:full":"2/88 Pinjarra Rd (Cnr Forrest St), Mandurah WA 6210",
    "addr:housenumber":"/ 88",
    "addr:postcode":"6210",
    "addr:street":"Pinjarra Rd Cnr Forrest St",
    "iso:country":"AU",
    "sg:address":"2/88 Pinjarra Rd (Cnr Forrest St),",
    "sg:city":"Mandurah",
    "sg:classifiers":[
        {
            "category":"Home & Garden",
            "subcategory":"Carpets & Floor Coverings",
            "type":"Retail Goods"
        }
    ],
    "sg:phone":"+61 8 9581 1574",
    "sg:postcode":"6210",
    "sg:province":"WA",
    "sg:tags":[
        "flooring",
        "parquet"
    ],
    "wof:name":"Knox On Wood Flooring Pty Ltd",
    "wof:placetype":"venue"
},
  "geometry": {"coordinates":[115.8349,-32.601208],"type":"Point"}
}