{
  "type": "Feature",
  "properties": {
    "iso:country":"AU",
    "sg:address":"22 Vincent St",
    "sg:city":"Nedlands",
    "sg:classifiers":[
        {
            "category":"Utilities",
            "subcategory":"Refuse",
            "type":"Services"
        }
    ],
    "sg:phone":"+61 8 9389 8744",
    "sg:postcode":"6009",
    "sg:province":"WA",
    "sg:tags":[
        "remover",
        "rubbish"
    ],
    "wof:name":"Pete's Gold Bins",
    "wof:placetype":"venue"
},
  "geometry": {"coordinates":[115.799004,-31.982159],"type":"Point"}
}