{
  "type": "Feature",
  "properties": {
    "iso:country":"AU",
    "sg:address":"7/ 68 Railway Ave",
    "sg:city":"Townsville",
    "sg:classifiers":[
        {
            "category":"Real Estate",
            "subcategory":"Real Estate Agent",
            "type":"Services"
        }
    ],
    "sg:phone":"+61 7 4721 1433",
    "sg:postcode":"4810",
    "sg:province":"QLD",
    "wof:name":"Keating Yvonne Real Estate",
    "wof:placetype":"venue"
},
  "geometry": {"coordinates":[146.815186,-19.277655],"type":"Point"}
}