{
  "type": "Feature",
  "properties": {
    "iso:country":"AU",
    "sg:address":"455 Bluff Rd",
    "sg:city":"Hampton",
    "sg:classifiers":[
        {
            "category":"Social Services",
            "subcategory":"Retirement Home",
            "type":"Services"
        }
    ],
    "sg:phone":"+61 3 9533 1111",
    "sg:postcode":"3188",
    "sg:province":"VIC",
    "sg:tags":[
        "accommodation",
        "special"
    ],
    "wof:name":"Raynes Park Court",
    "wof:placetype":"venue"
},
  "geometry": {"coordinates":[145.02366638199999,-37.9374313354],"type":"Point"}
}