{
  "type": "Feature",
  "properties": {
    "iso:country":"AU",
    "sg:address":"24- 36 Flood St",
    "sg:city":"Bondi",
    "sg:classifiers":[
        {
            "category":"Social Services",
            "subcategory":"Retirement Home",
            "type":"Services"
        }
    ],
    "sg:phone":"+61 2 9669 5633",
    "sg:postcode":"2026",
    "sg:province":"NSW",
    "sg:tags":[
        "village"
    ],
    "wof:name":"Lifestylemanor Bondi",
    "wof:placetype":"venue"
},
  "geometry": {"coordinates":[151.25907898,-33.891910553],"type":"Point"}
}