{
  "type": "Feature",
  "properties": {
    "iso:country":"AU",
    "sg:address":"169 Veivers Rd",
    "sg:city":"Cedar Creek",
    "sg:classifiers":[
        {
            "category":"Utilities",
            "subcategory":"Telephone",
            "type":"Services"
        }
    ],
    "sg:phone":"+61 414 299 329",
    "sg:postcode":"4207",
    "sg:province":"QLD",
    "sg:tags":[
        "installation",
        "system",
        "maintenance"
    ],
    "sg:website":"http://www.montereycommunications",
    "wof:name":"Monterey Communications",
    "wof:placetype":"venue"
},
  "geometry": {"coordinates":[153.17024230999999,-27.811920166],"type":"Point"}
}