{
  "type": "Feature",
  "properties": {
    "addr:full":"139- 141 Lygon St Carlton VIC 3053",
    "addr:housenumber":"141",
    "addr:postcode":"3053",
    "addr:street":"Lygon St",
    "iso:country":"AU",
    "sg:address":"139- 141 Lygon St",
    "sg:city":"Carlton",
    "sg:classifiers":[
        {
            "category":"Restaurant",
            "type":"Food & Drink"
        }
    ],
    "sg:phone":"+61 3 9347 4393",
    "sg:postcode":"3053",
    "sg:province":"VIC",
    "sg:website":"http://www.universalpizza.com.au",
    "wof:name":"Universal Pizza Italian Restaurant",
    "wof:placetype":"venue"
},
  "geometry": {"coordinates":[144.966186523,-37.8039665222],"type":"Point"}
}