{
  "type": "Feature",
  "properties": {
    "addr:full":"PO Box 146 Killara NSW 2071",
    "addr:postcode":"2071",
    "iso:country":"AU",
    "sg:address":"PO Box 146",
    "sg:city":"Killara",
    "sg:classifiers":[
        {
            "category":"Utilities",
            "subcategory":"Electric",
            "type":"Services"
        }
    ],
    "sg:phone":"+61 2 9499 9500",
    "sg:postcode":"2071",
    "sg:province":"NSW",
    "sg:tags":[
        "electrical",
        "contractor"
    ],
    "wof:name":"Spaceage Electrics Pty Ltd",
    "wof:placetype":"venue"
},
  "geometry": {"coordinates":[151.15687560999999,-33.7663116455],"type":"Point"}
}