{
  "type": "Feature",
  "properties": {
    "addr:full":"11 Kimberley Rd Hillarys WA 6025",
    "addr:housenumber":"11",
    "addr:postcode":"6025",
    "addr:street":"Kimberley Rd",
    "iso:country":"AU",
    "sg:address":"11 Kimberley Rd",
    "sg:city":"Hillarys",
    "sg:classifiers":[
        {
            "category":"Mining & Drilling",
            "type":"Manufacturing & Wholesale Goods"
        }
    ],
    "sg:phone":"+61 8 9402 8011",
    "sg:postcode":"6025",
    "sg:province":"WA",
    "sg:tags":[
        "concrete",
        "breaking",
        "grinding",
        "sawing"
    ],
    "wof:name":"Tru-Cut Concrete Cutting & Drilling",
    "wof:placetype":"venue"
},
  "geometry": {"coordinates":[115.74594116199999,-31.8131885529],"type":"Point"}
}