{
  "type": "Feature",
  "properties": {
    "addr:full":"Bylong Rd Rylstone NSW 2849",
    "addr:postcode":"2849",
    "addr:street":"Bylong Rd",
    "iso:country":"AU",
    "sg:address":"Bylong Rd",
    "sg:city":"Rylstone",
    "sg:classifiers":[
        {
            "category":"Farming",
            "subcategory":"Farm",
            "type":"Manufacturing & Wholesale Goods"
        }
    ],
    "sg:phone":"+61 2 6379 1041",
    "sg:postcode":"2849",
    "sg:province":"NSW",
    "sg:tags":[
        "farmer"
    ],
    "wof:name":"Harding J E",
    "wof:placetype":"venue"
},
  "geometry": {"coordinates":[149.97171,-32.790977],"type":"Point"}
}