{
  "type": "Feature",
  "properties": {
    "addr:full":"6 Frankston Gardens Drv Carrum Downs VIC 3201",
    "addr:housenumber":"6",
    "addr:postcode":"3201",
    "addr:street":"Frankston Gardens Drv",
    "iso:country":"AU",
    "sg:address":"6 Frankston Gardens Drv",
    "sg:city":"Carrum Downs",
    "sg:classifiers":[
        {
            "category":"Train Station",
            "subcategory":"Rail",
            "type":"Transportation"
        }
    ],
    "sg:phone":"+61 3 9776 8555",
    "sg:postcode":"3201",
    "sg:province":"VIC",
    "sg:tags":[
        "wallboard"
    ],
    "wof:name":"Ideal Plaster",
    "wof:placetype":"venue"
},
  "geometry": {"coordinates":[145.163635,-38.106308],"type":"Point"}
}