{
  "type": "Feature",
  "properties": {
    "addr:full":"Level 4/ 84 William St Melbourne VIC 3000",
    "addr:housenumber":"/ 84",
    "addr:postcode":"3000",
    "addr:street":"William St",
    "iso:country":"AU",
    "sg:address":"Level 4/ 84 William St",
    "sg:city":"Melbourne",
    "sg:classifiers":[
        {
            "category":"Retail",
            "subcategory":"Auto Repair",
            "type":"Services"
        }
    ],
    "sg:phone":"+61 3 9600 3988",
    "sg:postcode":"3000",
    "sg:province":"VIC",
    "sg:tags":[
        "beater",
        "painter",
        "panel"
    ],
    "wof:name":"Aars",
    "wof:placetype":"venue"
},
  "geometry": {"coordinates":[144.959182739,-37.817440033],"type":"Point"}
}