{
  "type": "Feature",
  "properties": {
    "addr:full":"8 Beale Crt Templestowe VIC 3106",
    "addr:housenumber":"8",
    "addr:postcode":"3106",
    "addr:street":"Beale Crt",
    "iso:country":"AU",
    "sg:address":"8 Beale Crt",
    "sg:city":"Templestowe",
    "sg:classifiers":[
        {
            "category":"Education",
            "subcategory":"Special Training",
            "type":"Public Place"
        }
    ],
    "sg:phone":"+61 3 9846 1800",
    "sg:postcode":"3106",
    "sg:province":"VIC",
    "sg:tags":[
        "development"
    ],
    "wof:name":"Intergrated Training Solutions (Aust) Pty Ltd",
    "wof:placetype":"venue"
},
  "geometry": {"coordinates":[145.13937377900001,-37.7557830811],"type":"Point"}
}