{
  "type": "Feature",
  "properties": {
    "addr:full":"6154 Pacific Hwy Nambucca Heads NSW 2448",
    "addr:housenumber":"6154",
    "addr:postcode":"2448",
    "addr:street":"Pacific Hwy",
    "iso:country":"AU",
    "sg:address":"6154 Pacific Hwy",
    "sg:city":"Nambucca Heads",
    "sg:classifiers":[
        {
            "category":"Travel",
            "subcategory":"Hotels & Motels",
            "type":"Entertainment"
        }
    ],
    "sg:phone":"+61 2 6568 6204",
    "sg:postcode":"2448",
    "sg:province":"NSW",
    "wof:name":"Motel Jabiru",
    "wof:placetype":"venue"
},
  "geometry": {"coordinates":[152.98225400000001,-30.665567],"type":"Point"}
}