{
  "type": "Feature",
  "properties": {
    "addr:full":"119 Winstanley St Carina Heights QLD 4152",
    "addr:housenumber":"119",
    "addr:postcode":"4152",
    "addr:street":"Winstanley St",
    "iso:country":"AU",
    "sg:address":"119 Winstanley St",
    "sg:city":"Carina Heights",
    "sg:classifiers":[
        {
            "category":"Restaurant",
            "type":"Food & Drink"
        }
    ],
    "sg:phone":"+61 7 3843 1333",
    "sg:postcode":"4152",
    "sg:province":"QLD",
    "wof:name":"Elio's Osteria BYO Carina",
    "wof:placetype":"venue"
},
  "geometry": {"coordinates":[153.09303283700001,-27.5043773651],"type":"Point"}
}