{
  "type": "Feature",
  "properties": {
    "iso:country":"AU",
    "sg:address":"3 Palmerston Ave",
    "sg:city":"Winston Hills",
    "sg:classifiers":[
        {
            "category":"Utilities",
            "subcategory":"Electric",
            "type":"Services"
        }
    ],
    "sg:phone":"+61 2 9686 4213",
    "sg:postcode":"2153",
    "sg:province":"NSW",
    "sg:tags":[
        "electrical",
        "contractor"
    ],
    "wof:name":"S.J.F. Electrical",
    "wof:placetype":"venue"
},
  "geometry": {"coordinates":[150.991577148,-33.7714500427],"type":"Point"}
}