{
  "type": "Feature",
  "properties": {
    "addr:full":"Shop 3/ 658 Pittwater Rd Brookvale NSW 2100",
    "addr:housenumber":"shop 3 / 658",
    "addr:postcode":"2100",
    "addr:street":"Pittwater Rd",
    "iso:country":"AU",
    "sg:address":"Shop 3/ 658 Pittwater Rd",
    "sg:city":"Brookvale",
    "sg:classifiers":[
        {
            "category":"Professional",
            "subcategory":"Computer Services",
            "type":"Services"
        }
    ],
    "sg:phone":"+61 2 9905 8522",
    "sg:postcode":"2100",
    "sg:province":"NSW",
    "sg:tags":[
        "repairs",
        "upgrade",
        "equipment"
    ],
    "wof:name":"Pier Computers",
    "wof:placetype":"venue"
},
  "geometry": {"coordinates":[151.271575928,-33.7639770508],"type":"Point"}
}