{
  "type": "Feature",
  "properties": {
    "addr:full":"15 Bastow Pl Mulgrave VIC 3170",
    "addr:housenumber":"15",
    "addr:postcode":"3170",
    "addr:street":"Bastow Pl",
    "iso:country":"AU",
    "sg:address":"15 Bastow Pl",
    "sg:city":"Mulgrave",
    "sg:classifiers":[
        {
            "category":"Wholesale",
            "subcategory":"Electrical",
            "type":"Manufacturing & Wholesale Goods"
        }
    ],
    "sg:phone":"+61 3 9560 7611",
    "sg:postcode":"3170",
    "sg:province":"VIC",
    "sg:tags":[
        "equipment",
        "testing",
        "electronic",
        "electric"
    ],
    "wof:name":"Nesco Electrical Products",
    "wof:placetype":"venue"
},
  "geometry": {"coordinates":[145.151657105,-37.9235649109],"type":"Point"}
}