{
  "type": "Feature",
  "properties": {
    "addr:full":"52 Wee Waa St Walgett NSW 2832",
    "addr:housenumber":"52",
    "addr:postcode":"2832",
    "addr:street":"Wee Waa St",
    "iso:country":"AU",
    "sg:address":"52 Wee Waa St",
    "sg:city":"Walgett",
    "sg:classifiers":[
        {
            "category":"Professional",
            "subcategory":"Accounting & Tax Preparation",
            "type":"Services"
        }
    ],
    "sg:phone":"+61 2 6828 1309",
    "sg:postcode":"2832",
    "sg:province":"NSW",
    "sg:tags":[
        "consultant",
        "taxation"
    ],
    "wof:name":"Mair R J",
    "wof:placetype":"venue"
},
  "geometry": {"coordinates":[148.116363525,-30.0213432312],"type":"Point"}
}