{
  "type": "Feature",
  "properties": {
    "addr:full":"142 Pitt St Sydney NSW 2000",
    "addr:housenumber":"142",
    "addr:postcode":"2000",
    "addr:street":"Pitt St",
    "iso:country":"AU",
    "sg:address":"142 Pitt St",
    "sg:city":"Sydney",
    "sg:classifiers":[
        {
            "category":"Shopping",
            "subcategory":"Clothing, Apparel, & Fashions",
            "type":"Retail Goods"
        }
    ],
    "sg:phone":"+61 2 9233 4433",
    "sg:postcode":"2000",
    "sg:province":"NSW",
    "sg:tags":[
        "lady",
        "wear"
    ],
    "wof:name":"Sussan Corporation Pty Ltd",
    "wof:placetype":"venue"
},
  "geometry": {"coordinates":[151.20848083499999,-33.868598938],"type":"Point"}
}