{
  "type": "Feature",
  "properties": {
    "addr:full":"47 Prince St Brighton QLD 4017",
    "addr:housenumber":"47",
    "addr:postcode":"4017",
    "addr:street":"Prince St",
    "iso:country":"AU",
    "sg:address":"47 Prince St",
    "sg:city":"Brighton",
    "sg:classifiers":[
        {
            "category":"Personal",
            "subcategory":"Beauty Salon",
            "type":"Services"
        }
    ],
    "sg:phone":"+61 7 3269 2919",
    "sg:postcode":"4017",
    "sg:province":"QLD",
    "wof:name":"A Touch Of Elegance Paramedical Skin Rejuvenation Clinics",
    "wof:placetype":"venue"
},
  "geometry": {"coordinates":[153.060455322,-27.2952270508],"type":"Point"}
}