{
  "type": "Feature",
  "properties": {
    "addr:full":"207 Treasure Rd Queens Park WA 6107",
    "addr:housenumber":"207",
    "addr:postcode":"6107",
    "addr:street":"Treasure Rd",
    "iso:country":"AU",
    "sg:address":"207 Treasure Rd",
    "sg:city":"Queens Park",
    "sg:classifiers":[
        {
            "category":"Food & Beverages",
            "subcategory":"Meat & Fish",
            "type":"Retail Goods"
        }
    ],
    "sg:phone":"+61 8 9451 4384",
    "sg:postcode":"6107",
    "sg:province":"WA",
    "sg:tags":[
        "seafood"
    ],
    "wof:name":"Treasure Road Fish & Takeaway",
    "wof:placetype":"venue"
},
  "geometry": {"coordinates":[115.939979553,-32.0030097961],"type":"Point"}
}