{
  "type": "Feature",
  "properties": {
    "addr:full":"Unit 3/ 14 Childs Rd Chipping Norton NSW 2170",
    "addr:housenumber":"14",
    "addr:postcode":"2170",
    "addr:street":"Childs Rd",
    "iso:country":"AU",
    "sg:address":"Unit 3/ 14 Childs Rd",
    "sg:city":"Chipping Norton",
    "sg:classifiers":[
        {
            "category":"Food & Beverages",
            "subcategory":"Specialty",
            "type":"Retail Goods"
        }
    ],
    "sg:phone":"+61 2 9327 1955",
    "sg:postcode":"2170",
    "sg:province":"NSW",
    "sg:tags":[
        "product",
        "health"
    ],
    "wof:name":"Go Vita Your Health Store",
    "wof:placetype":"venue"
},
  "geometry": {"coordinates":[150.96536254899999,-33.9189491272],"type":"Point"}
}