{
  "type": "Feature",
  "properties": {
    "iso:country":"AU",
    "sg:address":"Lot 12 Blacktop Rd",
    "sg:city":"One Tree Hill",
    "sg:classifiers":[
        {
            "category":"Building & Trades",
            "subcategory":"Plumbing",
            "type":"Services"
        }
    ],
    "sg:phone":"+61 417 823 796",
    "sg:postcode":"5114",
    "sg:province":"SA",
    "sg:tags":[
        "plumber",
        "gasfitters"
    ],
    "wof:name":"Norris Plumbing Services",
    "wof:placetype":"venue"
},
  "geometry": {"coordinates":[138.76478576700001,-34.7188644409],"type":"Point"}
}