{
  "type": "Feature",
  "properties": {
    "addr:full":"PO Box 1058 Camden NSW 2570",
    "addr:postcode":"2570",
    "iso:country":"AU",
    "sg:address":"PO Box 1058",
    "sg:city":"Camden",
    "sg:classifiers":[
        {
            "category":"Government",
            "subcategory":"Court House",
            "type":"Public Place"
        }
    ],
    "sg:phone":"+61 425 354 312",
    "sg:postcode":"2570",
    "sg:province":"NSW",
    "sg:tags":[
        "personal",
        "marriage",
        "family",
        "counselling"
    ],
    "wof:name":"Life Consultancy Services",
    "wof:placetype":"venue"
},
  "geometry": {"coordinates":[150.694015503,-34.0563583374],"type":"Point"}
}