{
  "type": "Feature",
  "properties": {
    "addr:full":"3/ 23 Dennis Rd Springwood QLD 4127",
    "addr:housenumber":"/ 23",
    "addr:postcode":"4127",
    "addr:street":"Dennis Rd",
    "iso:country":"AU",
    "sg:address":"3/ 23 Dennis Rd",
    "sg:city":"Springwood",
    "sg:classifiers":[
        {
            "category":"Professional",
            "subcategory":"Employment Agencies",
            "type":"Services"
        }
    ],
    "sg:phone":"+61 7 3808 1966",
    "sg:postcode":"4127",
    "sg:province":"QLD",
    "sg:tags":[
        "provider",
        "internet"
    ],
    "wof:name":"Quicknet Internet Provider Pty Ltd",
    "wof:placetype":"venue"
},
  "geometry": {"coordinates":[153.129806519,-27.6200637817],"type":"Point"}
}