{
  "type": "Feature",
  "properties": {
    "addr:full":"304 Keilor Rd Essendon North VIC 3041",
    "addr:housenumber":"304",
    "addr:postcode":"3041",
    "addr:street":"Keilor Rd",
    "iso:country":"AU",
    "sg:address":"304 Keilor Rd",
    "sg:city":"Essendon North",
    "sg:classifiers":[
        {
            "category":"Restaurant",
            "type":"Food & Drink"
        }
    ],
    "sg:phone":"+61 3 9379 1099",
    "sg:postcode":"3041",
    "sg:province":"VIC",
    "wof:name":"Che&#039; Zena Authentic Lebanese Cuisine",
    "wof:placetype":"venue"
},
  "geometry": {"coordinates":[144.89431762699999,-37.7379264832],"type":"Point"}
}