{
  "type": "Feature",
  "properties": {
    "addr:full":"Stuart St Goodna QLD 4300",
    "addr:postcode":"4300",
    "addr:street":"Stuart St",
    "iso:country":"AU",
    "sg:address":"Stuart St",
    "sg:city":"Goodna",
    "sg:classifiers":[
        {
            "category":"Retail",
            "subcategory":"Funeral Services",
            "type":"Services"
        }
    ],
    "sg:phone":"+61 7 3818 0023",
    "sg:postcode":"4300",
    "sg:province":"QLD",
    "sg:tags":[
        "cemetery"
    ],
    "wof:name":"Goodna Cemetery Trust",
    "wof:placetype":"venue"
},
  "geometry": {"coordinates":[152.88897705100001,-27.6063232422],"type":"Point"}
}