{
  "type": "Feature",
  "properties": {
    "addr:full":"83 Erindale Rd Balcatta WA 6021",
    "addr:housenumber":"83",
    "addr:postcode":"6021",
    "addr:street":"Erindale Rd",
    "iso:country":"AU",
    "sg:address":"83 Erindale Rd",
    "sg:city":"Balcatta",
    "sg:classifiers":[
        {
            "category":"Manufacturing",
            "subcategory":"Motor Vehicles & Parts",
            "type":"Manufacturing & Wholesale Goods"
        }
    ],
    "sg:phone":"+61 8 9344 5122",
    "sg:postcode":"6021",
    "sg:province":"WA",
    "sg:tags":[
        "replacement"
    ],
    "wof:name":"Auto One Parts And Accessories",
    "wof:placetype":"venue"
},
  "geometry": {"coordinates":[115.80658721899999,-31.8662948608],"type":"Point"}
}