{
  "type": "Feature",
  "properties": {
    "addr:full":"2/ 32 Kincaid St Wagga Wagga NSW 2650",
    "addr:housenumber":"/ 32",
    "addr:postcode":"2650",
    "addr:street":"Kincaid St",
    "iso:country":"AU",
    "sg:address":"2/ 32 Kincaid St",
    "sg:city":"Wagga Wagga",
    "sg:classifiers":[
        {
            "category":"Professional",
            "subcategory":"Accounting & Tax Preparation",
            "type":"Services"
        }
    ],
    "sg:phone":"+61 2 6971 9055",
    "sg:postcode":"2650",
    "sg:province":"NSW",
    "sg:tags":[
        "consultant",
        "taxation"
    ],
    "wof:name":"JP Pallister & Associates Chartered Accountants",
    "wof:placetype":"venue"
},
  "geometry": {"coordinates":[147.366897583,-35.1103286743],"type":"Point"}
}