{
  "type": "Feature",
  "properties": {
    "addr:full":"Livingstone St Avenel VIC 3664",
    "addr:postcode":"3664",
    "addr:street":"Livingstone St",
    "iso:country":"AU",
    "sg:address":"Livingstone St",
    "sg:city":"Avenel",
    "sg:classifiers":[
        {
            "category":"Education",
            "subcategory":"School",
            "type":"Public Place"
        }
    ],
    "sg:phone":"+61 3 5796 2264",
    "sg:postcode":"3664",
    "sg:province":"VIC",
    "sg:tags":[
        "state",
        "except",
        "nsw"
    ],
    "wof:name":"Avenel Primary School",
    "wof:placetype":"venue"
},
  "geometry": {"coordinates":[145.231765747,-36.8970298767],"type":"Point"}
}