{
  "type": "Feature",
  "properties": {
    "addr:full":"Whitford Crs Nangwarry SA 5277",
    "addr:postcode":"5277",
    "addr:street":"Whitford Crs",
    "iso:country":"AU",
    "sg:address":"Whitford Crs",
    "sg:city":"Nangwarry",
    "sg:classifiers":[
        {
            "category":"Education",
            "subcategory":"School",
            "type":"Public Place"
        }
    ],
    "sg:phone":"+61 8 8739 7241",
    "sg:postcode":"5277",
    "sg:province":"SA",
    "sg:tags":[
        "state",
        "except",
        "nsw"
    ],
    "wof:name":"Nangwarry Primary School",
    "wof:placetype":"venue"
},
  "geometry": {"coordinates":[140.81480400000001,-37.543289],"type":"Point"}
}