{
  "type": "Feature",
  "properties": {
    "iso:country":"AU",
    "sg:address":"20 Queen St",
    "sg:city":"Numurkah",
    "sg:classifiers":[
        {
            "category":"Building & Trades",
            "subcategory":"Construction",
            "type":"Services"
        }
    ],
    "sg:phone":"+61 3 5862 2208",
    "sg:postcode":"3636",
    "sg:province":"VIC",
    "sg:tags":[
        "ceiling"
    ],
    "wof:name":"Pryde I R & L M",
    "wof:placetype":"venue"
},
  "geometry": {"coordinates":[145.44241332999999,-36.0858459473],"type":"Point"}
}