{
  "type": "Feature",
  "properties": {
    "addr:full":"34 Shane Ave Point Cook VIC 3030",
    "addr:housenumber":"34",
    "addr:postcode":"3030",
    "addr:street":"Shane Ave",
    "iso:country":"AU",
    "sg:address":"34 Shane Ave",
    "sg:city":"Point Cook",
    "sg:classifiers":[
        {
            "category":"Utilities",
            "subcategory":"Natural Gas",
            "type":"Services"
        }
    ],
    "sg:phone":"+61 402 069 159",
    "sg:postcode":"3030",
    "sg:province":"VIC",
    "sg:tags":[
        "solid",
        "plasterer"
    ],
    "wof:name":"Zanette Home Improvements",
    "wof:placetype":"venue"
},
  "geometry": {"coordinates":[144.755707,-37.875687],"type":"Point"}
}