{
  "type": "Feature",
  "properties": {
    "iso:country":"AU",
    "sg:address":"56a Old Barrenjoey Rd",
    "sg:city":"Avalon Beach",
    "sg:classifiers":[
        {
            "category":"Health Services",
            "subcategory":"Chiropractor",
            "type":"Services"
        }
    ],
    "sg:phone":"+61 2 9973 1255",
    "sg:postcode":"2107",
    "sg:province":"NSW",
    "wof:name":"Swanton Megan D.O.C.",
    "wof:placetype":"venue"
},
  "geometry": {"coordinates":[151.328887939,-33.6373138428],"type":"Point"}
}