{
  "type": "Feature",
  "properties": {
    "iso:country":"AU",
    "sg:address":"Bago Rd",
    "sg:city":"Wauchope",
    "sg:classifiers":[
        {
            "category":"Home & Garden",
            "subcategory":"Building Materials",
            "type":"Retail Goods"
        }
    ],
    "sg:phone":"+61 2 6585 1698",
    "sg:postcode":"2446",
    "sg:province":"NSW",
    "sg:tags":[
        "pre-mixed",
        "concrete"
    ],
    "wof:name":"Boral Country-Concrete & Quarries",
    "wof:placetype":"venue"
},
  "geometry": {"coordinates":[152.728546,-31.485729],"type":"Point"}
}