{
  "type": "Feature",
  "properties": {
    "addr:full":"Aminya St Mansfield QLD 4122",
    "addr:postcode":"4122",
    "addr:street":"St",
    "iso:country":"AU",
    "sg:address":"Aminya St",
    "sg:city":"Mansfield",
    "sg:classifiers":[
        {
            "category":"Building & Trades",
            "subcategory":"Plumbing",
            "type":"Services"
        }
    ],
    "sg:phone":"+61 7 3849 7641",
    "sg:postcode":"4122",
    "sg:province":"QLD",
    "sg:tags":[
        "plumber",
        "gasfitters"
    ],
    "wof:name":"A Ron Buhmann Plumbing & Tiling",
    "wof:placetype":"venue"
},
  "geometry": {"coordinates":[153.097900391,-27.539182663],"type":"Point"}
}