{
  "type": "Feature",
  "properties": {
    "iso:country":"AU",
    "sg:address":"109 Broadway St",
    "sg:city":"Dunolly",
    "sg:classifiers":[
        {
            "category":"Communications",
            "subcategory":"News Services",
            "type":"Services"
        }
    ],
    "sg:phone":"+61 3 5468 1205",
    "sg:postcode":"3472",
    "sg:province":"VIC",
    "sg:tags":[
        "information",
        "tourist",
        "attractions"
    ],
    "wof:name":"Dunolly Visitor Information Centre",
    "wof:placetype":"venue"
},
  "geometry": {"coordinates":[143.730743408,-36.858833313],"type":"Point"}
}