{
  "type": "Feature",
  "properties": {
    "iso:country":"AU",
    "sg:address":"Shp 3/ 35 Terry St",
    "sg:city":"Balmain",
    "sg:classifiers":[
        {
            "category":"Food & Beverages",
            "subcategory":"Supermarket",
            "type":"Retail Goods"
        }
    ],
    "sg:phone":"+61 2 9555 4088",
    "sg:postcode":"2041",
    "sg:province":"NSW",
    "sg:tags":[
        "grocery",
        "store"
    ],
    "wof:name":"Balmain Cove Convenience Store",
    "wof:placetype":"venue"
},
  "geometry": {"coordinates":[151.170944,-33.857998],"type":"Point"}
}