{
  "type": "Feature",
  "properties": {
    "iso:country":"AU",
    "sg:address":"Lot 7 Mather Rd",
    "sg:city":"Yungaburra",
    "sg:classifiers":[
        {
            "category":"Building & Trades",
            "subcategory":"Construction",
            "type":"Services"
        }
    ],
    "sg:phone":"+61 7 4095 3425",
    "sg:postcode":"4872",
    "sg:province":"QLD",
    "sg:tags":[
        "renovation",
        "alterations",
        "extension",
        "contractor"
    ],
    "wof:name":"Mackenzie K G & M",
    "wof:placetype":"venue"
},
  "geometry": {"coordinates":[145.58357238799999,-17.2789402008],"type":"Point"}
}