{
  "type": "Feature",
  "properties": {
    "addr:full":"Unit 1/ 16 Murray St North Parramatta NSW 2151",
    "addr:housenumber":"16",
    "addr:postcode":"2151",
    "addr:street":"Murray St",
    "iso:country":"AU",
    "sg:address":"Unit 1/ 16 Murray St",
    "sg:city":"North Parramatta",
    "sg:classifiers":[
        {
            "category":"Professional",
            "subcategory":"Computer Services",
            "type":"Services"
        }
    ],
    "sg:phone":"+61 413 459 544",
    "sg:postcode":"2151",
    "sg:province":"NSW",
    "sg:tags":[
        "repairs",
        "upgrade",
        "equipment"
    ],
    "wof:name":"Absolute Mobile Computer Solutions",
    "wof:placetype":"venue"
},
  "geometry": {"coordinates":[151.02096557600001,-33.8031158447],"type":"Point"}
}