{
  "type": "Feature",
  "properties": {
    "addr:full":"106 Sheedy Rd Gisborne VIC 3437",
    "addr:housenumber":"106",
    "addr:postcode":"3437",
    "addr:street":"Sheedy Rd",
    "iso:country":"AU",
    "sg:address":"106 Sheedy Rd",
    "sg:city":"Gisborne",
    "sg:classifiers":[
        {
            "category":"Travel",
            "subcategory":"Hotels & Motels",
            "type":"Entertainment"
        }
    ],
    "sg:phone":"+61 3 5428 2414",
    "sg:postcode":"3437",
    "sg:province":"VIC",
    "wof:name":"Gisborne Motel",
    "wof:placetype":"venue"
},
  "geometry": {"coordinates":[144.60516357399999,-37.4974632263],"type":"Point"}
}