{
  "type": "Feature",
  "properties": {
    "addr:full":"Un 1, 4 Tarlington Pl Smithfield NSW 2164",
    "addr:housenumber":"4",
    "addr:postcode":"2164",
    "addr:street":"Tarlington Pl",
    "iso:country":"AU",
    "sg:address":"Un 1, 4 Tarlington Pl",
    "sg:city":"Smithfield",
    "sg:classifiers":[
        {
            "category":"Building & Trades",
            "subcategory":"Cleaning & Sanitation",
            "type":"Services"
        }
    ],
    "sg:phone":"+61 2 9757 3730",
    "sg:postcode":"2164",
    "sg:province":"NSW",
    "sg:tags":[
        "cleaner",
        "repairer",
        "roof"
    ],
    "wof:name":"G & S Building Services Pty Ltd",
    "wof:placetype":"venue"
},
  "geometry": {"coordinates":[150.92843627900001,-33.8357429504],"type":"Point"}
}