{
  "type": "Feature",
  "properties": {
    "addr:full":"Oakey Rd Gowrie Mountain QLD 4350",
    "addr:postcode":"4350",
    "addr:street":"Oakey Rd",
    "iso:country":"AU",
    "sg:address":"Oakey Rd",
    "sg:city":"Gowrie Mountain",
    "sg:classifiers":[
        {
            "category":"Farming",
            "subcategory":"Farm & Veterinary Services",
            "type":"Manufacturing & Wholesale Goods"
        }
    ],
    "sg:phone":"+61 7 4630 0633",
    "sg:postcode":"4350",
    "sg:province":"QLD",
    "sg:tags":[
        "agricultural",
        "advisory"
    ],
    "wof:name":"Michael Newbury Ag-Marketing Pty Ltd",
    "wof:placetype":"venue"
},
  "geometry": {"coordinates":[151.824265,-27.50696],"type":"Point"}
}