{
  "type": "Feature",
  "properties": {
    "iso:country":"AU",
    "sg:address":"11 McLernon Pl",
    "sg:city":"South Lake",
    "sg:classifiers":[
        {
            "category":"Building & Trades",
            "subcategory":"Landscaping Services",
            "type":"Services"
        }
    ],
    "sg:phone":"+61 419 956 468",
    "sg:postcode":"6164",
    "sg:province":"WA",
    "sg:tags":[
        "consultant"
    ],
    "wof:name":"Lakes Building Advisory Service",
    "wof:placetype":"venue"
},
  "geometry": {"coordinates":[115.849892,-32.107677],"type":"Point"}
}