{
  "type": "Feature",
  "properties": {
    "iso:country":"AU",
    "sg:address":"134 Sanger St",
    "sg:city":"Corowa",
    "sg:classifiers":[
        {
            "category":"Retail",
            "subcategory":"Auto Repair",
            "type":"Services"
        }
    ],
    "sg:phone":"+61 2 6033 2813",
    "sg:postcode":"2646",
    "sg:province":"NSW",
    "sg:tags":[
        "muffler",
        "exhaust",
        "system"
    ],
    "wof:name":"Carline Mufflers",
    "wof:placetype":"venue"
},
  "geometry": {"coordinates":[146.391357422,-35.9954872131],"type":"Point"}
}