{
  "type": "Feature",
  "properties": {
    "addr:full":"52 Were St Brighton VIC 3186",
    "addr:housenumber":"52",
    "addr:postcode":"3186",
    "addr:street":"Were St",
    "iso:country":"AU",
    "sg:address":"52 Were St",
    "sg:city":"Brighton",
    "sg:classifiers":[
        {
            "category":"Professional",
            "subcategory":"Management & Consulting",
            "type":"Services"
        }
    ],
    "sg:phone":"+61 418 993 344",
    "sg:postcode":"3186",
    "sg:province":"VIC",
    "sg:tags":[
        "consultant"
    ],
    "wof:name":"Stucley G N",
    "wof:placetype":"venue"
},
  "geometry": {"coordinates":[144.99299621599999,-37.9249000549],"type":"Point"}
}