{
  "type": "Feature",
  "properties": {
    "addr:full":"309 Anzac Pde Kingsford NSW 2032",
    "addr:housenumber":"309",
    "addr:postcode":"2032",
    "addr:street":"Anzac Pde",
    "iso:country":"AU",
    "sg:address":"309 Anzac Pde",
    "sg:city":"Kingsford",
    "sg:classifiers":[
        {
            "category":"Recreation",
            "type":"Entertainment"
        }
    ],
    "sg:phone":"+61 2 9663 3535",
    "sg:postcode":"2032",
    "sg:province":"NSW",
    "sg:tags":[
        "supply",
        "outdoor",
        "adventure",
        "activity"
    ],
    "wof:name":"Kingsford Camping & BBQs",
    "wof:placetype":"venue"
},
  "geometry": {"coordinates":[151.22674560600001,-33.9220581055],"type":"Point"}
}