{
  "type": "Feature",
  "properties": {
    "addr:full":"210 Days Rd Grange QLD 4051",
    "addr:housenumber":"210",
    "addr:postcode":"4051",
    "addr:street":"Days Rd",
    "iso:country":"AU",
    "sg:address":"210 Days Rd",
    "sg:city":"Grange",
    "sg:classifiers":[
        {
            "category":"Utilities",
            "subcategory":"Electric",
            "type":"Services"
        }
    ],
    "sg:phone":"+61 1300 726 527",
    "sg:postcode":"4051",
    "sg:province":"QLD",
    "sg:tags":[
        "vehicle"
    ],
    "wof:name":"Scoot To Commute Pty Ltd",
    "wof:placetype":"venue"
},
  "geometry": {"coordinates":[153.01405334500001,-27.425994873],"type":"Point"}
}