{
  "type": "Feature",
  "properties": {
    "addr:full":"Goddard St Lathlain WA 6100",
    "addr:postcode":"6100",
    "addr:street":"Goddard St",
    "iso:country":"AU",
    "sg:address":"Goddard St",
    "sg:city":"Lathlain",
    "sg:classifiers":[
        {
            "category":"Retail",
            "subcategory":"Event Space",
            "type":"Services"
        }
    ],
    "sg:phone":"+61 8 9362 4499",
    "sg:postcode":"6100",
    "sg:province":"WA",
    "sg:tags":[
        "function",
        "organiser"
    ],
    "wof:name":"Perth Function Centre",
    "wof:placetype":"venue"
},
  "geometry": {"coordinates":[115.90878295900001,-31.9663505554],"type":"Point"}
}