{
  "type": "Feature",
  "properties": {
    "iso:country":"AU",
    "sg:address":"12 Newry Island Drv",
    "sg:city":"Newry Island",
    "sg:classifiers":[
        {
            "category":"Building & Trades",
            "subcategory":"Landscaping Services",
            "type":"Services"
        }
    ],
    "sg:phone":"+61 2 6655 7040",
    "sg:postcode":"2455",
    "sg:province":"NSW",
    "sg:tags":[
        "architect",
        "landscape"
    ],
    "wof:name":"Keith Tutor Rockmaking",
    "wof:placetype":"venue"
},
  "geometry": {"coordinates":[153.005539,-30.484812],"type":"Point"}
}