{
  "type": "Feature",
  "properties": {
    "iso:country":"AU",
    "sg:address":"64 Scarborough Beach Rd",
    "sg:city":"North Perth",
    "sg:classifiers":[
        {
            "category":"Manufacturing",
            "subcategory":"Motor Vehicles & Parts",
            "type":"Manufacturing & Wholesale Goods"
        }
    ],
    "sg:phone":"+61 8 9443 2122",
    "sg:postcode":"6006",
    "sg:province":"WA",
    "sg:tags":[
        "wholesaler",
        "cycle",
        "mfrs",
        "accessory"
    ],
    "wof:name":"Bike-Doctor Motorcycle Repairs",
    "wof:placetype":"venue"
},
  "geometry": {"coordinates":[115.84677124,-31.924200058],"type":"Point"}
}