{
  "type": "Feature",
  "properties": {
    "addr:full":"36 Duneba Ave West Pymble NSW 2073",
    "addr:housenumber":"36",
    "addr:postcode":"2073",
    "addr:street":"Duneba Ave",
    "iso:country":"AU",
    "sg:address":"36 Duneba Ave",
    "sg:city":"West Pymble",
    "sg:classifiers":[
        {
            "category":"Retail",
            "subcategory":"Auto Repair",
            "type":"Services"
        }
    ],
    "sg:phone":"+61 2 9499 4658",
    "sg:postcode":"2073",
    "sg:province":"NSW",
    "sg:tags":[
        "repairer",
        "motor",
        "engineer"
    ],
    "wof:name":"Kuring-Gai Mobile Car Repairs",
    "wof:placetype":"venue"
},
  "geometry": {"coordinates":[151.138595581,-33.7625350952],"type":"Point"}
}