{
  "type": "Feature",
  "properties": {
    "addr:full":"41 Latrobe Tce Paddington QLD 4064",
    "addr:housenumber":"41",
    "addr:postcode":"4064",
    "addr:street":"Latrobe Tce",
    "iso:country":"AU",
    "sg:address":"41 Latrobe Tce",
    "sg:city":"Paddington",
    "sg:classifiers":[
        {
            "category":"Personal",
            "subcategory":"Beauty Salon",
            "type":"Services"
        }
    ],
    "sg:phone":"+61 7 3511 7393",
    "sg:postcode":"4064",
    "sg:province":"QLD",
    "sg:website":"http://www.michellesbeauty.com.au",
    "wof:name":"Michelle's Skin & Body Solutions",
    "wof:placetype":"venue"
},
  "geometry": {"coordinates":[153.00064086899999,-27.4586315155],"type":"Point"}
}