{
  "type": "Feature",
  "properties": {
    "iso:country":"AU",
    "sg:address":"Alexandra St",
    "sg:city":"Mirani",
    "sg:classifiers":[
        {
            "category":"Organizations",
            "subcategory":"Community Association",
            "type":"Services"
        }
    ],
    "sg:phone":"+61 7 4959 1570",
    "sg:postcode":"4754",
    "sg:province":"QLD",
    "sg:tags":[
        "organisation",
        "family",
        "welfare"
    ],
    "wof:name":"Mirani District Meals On Wheels",
    "wof:placetype":"venue"
},
  "geometry": {"coordinates":[148.861008,-21.158539],"type":"Point"}
}