{
  "type": "Feature",
  "properties": {
    "addr:full":"Lot 24 Lower King Rd Albany WA 6330",
    "addr:postcode":"6330",
    "addr:street":"Lower King Rd",
    "iso:country":"AU",
    "sg:address":"Lot 24 Lower King Rd",
    "sg:city":"Albany",
    "sg:classifiers":[
        {
            "category":"Shopping",
            "subcategory":"Clothing, Apparel, & Fashions",
            "type":"Retail Goods"
        }
    ],
    "sg:phone":"+61 8 9844 1869",
    "sg:postcode":"6330",
    "sg:province":"WA",
    "sg:tags":[
        "recycled",
        "clothing"
    ],
    "wof:name":"Living Waters Opportunity Shop",
    "wof:placetype":"venue"
},
  "geometry": {"coordinates":[117.917541504,-34.9984550476],"type":"Point"}
}