{
  "type": "Feature",
  "properties": {
    "addr:full":"Level 2, 63 Market St Wollongong NSW 2500",
    "addr:housenumber":"63",
    "addr:postcode":"2500",
    "addr:street":"Market St",
    "iso:country":"AU",
    "sg:address":"Level 2, 63 Market St",
    "sg:city":"Wollongong",
    "sg:classifiers":[
        {
            "category":"Professional",
            "subcategory":"Computer Services",
            "type":"Services"
        }
    ],
    "sg:phone":"+61 2 4228 8599",
    "sg:postcode":"2500",
    "sg:province":"NSW",
    "sg:tags":[
        "consultant",
        "system"
    ],
    "wof:name":"Infocomp Pty Ltd",
    "wof:placetype":"venue"
},
  "geometry": {"coordinates":[150.894226,-34.423626],"type":"Point"}
}