{
  "type": "Feature",
  "properties": {
    "addr:full":"Shop 4, Mercury Plaza, 94-96 Gorge Rd Newton SA 5074",
    "addr:housenumber":"shop 4;94-96",
    "addr:postcode":"5074",
    "addr:street":"Mercury Plaza;Gorge Rd",
    "iso:country":"AU",
    "sg:address":"Shop 4, Mercury Plaza, 94-96 Gorge Rd",
    "sg:city":"Newton",
    "sg:classifiers":[
        {
            "category":"Personal",
            "subcategory":"Beauty Salon",
            "type":"Services"
        }
    ],
    "sg:phone":"+61 8 8365 5581",
    "sg:postcode":"5074",
    "sg:province":"SA",
    "sg:tags":[
        "hairdresser"
    ],
    "wof:name":"L S Hair & Beauty Studio",
    "wof:placetype":"venue"
},
  "geometry": {"coordinates":[138.67604064899999,-34.8763313293],"type":"Point"}
}