{
  "type": "Feature",
  "properties": {
    "addr:full":"111 French St Hamilton VIC 3300",
    "addr:housenumber":"111",
    "addr:postcode":"3300",
    "addr:street":"French St",
    "iso:country":"AU",
    "sg:address":"111 French St",
    "sg:city":"Hamilton",
    "sg:classifiers":[
        {
            "category":"Autos & Motor Vehicles",
            "subcategory":"Auto Supplies",
            "type":"Retail Goods"
        }
    ],
    "sg:phone":"+61 3 5572 2144",
    "sg:postcode":"3300",
    "sg:province":"VIC",
    "sg:tags":[
        "tyre"
    ],
    "wof:name":"GRAMPIANS TYRE SERVICE",
    "wof:placetype":"venue"
},
  "geometry": {"coordinates":[142.02691650400001,-37.7444114685],"type":"Point"}
}