{
  "type": "Feature",
  "properties": {
    "addr:full":"264 Homebush Rd Strathfield NSW 2135",
    "addr:housenumber":"264",
    "addr:postcode":"2135",
    "addr:street":"Homebush Rd",
    "iso:country":"AU",
    "sg:address":"264 Homebush Rd",
    "sg:city":"Strathfield",
    "sg:classifiers":[
        {
            "category":"Health Services",
            "subcategory":"Doctor",
            "type":"Services"
        }
    ],
    "sg:phone":"+61 2 9642 3317",
    "sg:postcode":"2135",
    "sg:province":"NSW",
    "sg:tags":[
        "medical",
        "practitioner"
    ],
    "wof:name":"Guirguis Waseem S",
    "wof:placetype":"venue"
},
  "geometry": {"coordinates":[151.083618164,-33.8914527893],"type":"Point"}
}