{
  "type": "Feature",
  "properties": {
    "addr:full":"Unit 52, 566 Gardeners Rd Alexandria NSW 2015",
    "addr:housenumber":"566",
    "addr:postcode":"2015",
    "addr:street":"Gardeners Rd",
    "iso:country":"AU",
    "sg:address":"Unit 52, 566 Gardeners Rd",
    "sg:city":"Alexandria",
    "sg:classifiers":[
        {
            "category":"Manufacturing",
            "subcategory":"Paper Products",
            "type":"Manufacturing & Wholesale Goods"
        }
    ],
    "sg:phone":"+61 1800 899 555",
    "sg:postcode":"2015",
    "sg:province":"NSW",
    "sg:tags":[
        "box",
        "fibre",
        "carton",
        "cardboard"
    ],
    "wof:name":"All Packaging Materials",
    "wof:placetype":"venue"
},
  "geometry": {"coordinates":[151.18490600600001,-33.9198188782],"type":"Point"}
}