{
  "type": "Feature",
  "properties": {
    "iso:country":"AU",
    "sg:address":"251- 257 Lava St",
    "sg:city":"Warrnambool",
    "sg:classifiers":[
        {
            "category":"Food & Beverages",
            "subcategory":"Groceries & Convenience Stores",
            "type":"Retail Goods"
        }
    ],
    "sg:phone":"+61 3 5561 1679",
    "sg:postcode":"3280",
    "sg:province":"VIC",
    "wof:name":"Jewel Food Stores",
    "wof:placetype":"venue"
},
  "geometry": {"coordinates":[142.478683472,-38.3790588379],"type":"Point"}
}