{
  "type": "Feature",
  "properties": {
    "iso:country":"AU",
    "sg:address":"1 Woods La",
    "sg:city":"Ferny Creek",
    "sg:classifiers":[
        {
            "category":"Building & Trades",
            "subcategory":"Cleaning & Sanitation",
            "type":"Services"
        }
    ],
    "sg:phone":"+61 1800 766 316",
    "sg:postcode":"3786",
    "sg:province":"VIC",
    "sg:tags":[
        "cleaner",
        "repairer",
        "roof"
    ],
    "wof:name":"Secure Roofing",
    "wof:placetype":"venue"
},
  "geometry": {"coordinates":[145.3423,-37.869827],"type":"Point"}
}