{
  "type": "Feature",
  "properties": {
    "iso:country":"AU",
    "sg:address":"McNamara St",
    "sg:city":"Moorak",
    "sg:classifiers":[
        {
            "category":"Organizations",
            "subcategory":"Membership Organization",
            "type":"Services"
        }
    ],
    "sg:phone":"+61 8 8726 6281",
    "sg:postcode":"5291",
    "sg:province":"SA",
    "sg:tags":[
        "club",
        "car"
    ],
    "wof:name":"Mount Gambier Motor Cycle & Light Car Club Incorporated",
    "wof:placetype":"venue"
},
  "geometry": {"coordinates":[140.64549299999999,-37.842087],"type":"Point"}
}