{
  "type": "Feature",
  "properties": {
    "iso:country":"AU",
    "sg:address":"50 Highridge Crs",
    "sg:city":"Airport West",
    "sg:classifiers":[
        {
            "category":"Building & Trades",
            "subcategory":"Construction",
            "type":"Services"
        }
    ],
    "sg:phone":"+61 418 585 977",
    "sg:postcode":"3042",
    "sg:province":"VIC",
    "sg:tags":[
        "earth",
        "excavating",
        "moving",
        "contractor"
    ],
    "sg:website":"http://www.adsdrilling.com.au",
    "wof:name":"A.D.S. Drilling & Construction",
    "wof:placetype":"venue"
},
  "geometry": {"coordinates":[144.87109375,-37.7291107178],"type":"Point"}
}