{
  "type": "Feature",
  "properties": {
    "iso:country":"AU",
    "sg:address":"1/ 32 Belgrave St",
    "sg:city":"Kempsey",
    "sg:classifiers":[
        {
            "category":"Utilities",
            "type":"Services"
        }
    ],
    "sg:phone":"+61 2 6562 7066",
    "sg:postcode":"2440",
    "sg:province":"NSW",
    "sg:tags":[
        "refrigeration",
        "industrial",
        "commercial",
        "retail"
    ],
    "wof:name":"Trial Bay Refrigeration & Air-Conditioning",
    "wof:placetype":"venue"
},
  "geometry": {"coordinates":[152.841125,-31.080694],"type":"Point"}
}