{
  "type": "Feature",
  "properties": {
    "iso:country":"AU",
    "sg:address":"21 McNaughton St",
    "sg:city":"Penrith",
    "sg:classifiers":[
        {
            "category":"Social Services",
            "subcategory":"Child Care",
            "type":"Services"
        }
    ],
    "sg:phone":"+61 2 4732 1936",
    "sg:postcode":"2750",
    "sg:province":"NSW",
    "wof:name":"McNaughton Preschool",
    "wof:placetype":"venue"
},
  "geometry": {"coordinates":[150.68205261200001,-33.7614707947],"type":"Point"}
}