{
  "type": "Feature",
  "properties": {
    "addr:full":"Ewing St Murwillumbah NSW 2484",
    "addr:postcode":"2484",
    "addr:street":"Ewing St",
    "iso:country":"AU",
    "sg:address":"Ewing St",
    "sg:city":"Murwillumbah",
    "sg:classifiers":[
        {
            "category":"Health Services",
            "subcategory":"Doctor",
            "type":"Services"
        }
    ],
    "sg:phone":"+61 2 6672 0299",
    "sg:postcode":"2484",
    "sg:province":"NSW",
    "sg:tags":[
        "medical",
        "practitioner"
    ],
    "wof:name":"Gold Coast Medical Imaging Pty Ltd",
    "wof:placetype":"venue"
},
  "geometry": {"coordinates":[153.39579773,-28.3240032196],"type":"Point"}
}