{
  "type": "Feature",
  "properties": {
    "iso:country":"AU",
    "sg:address":"Unit 3/4 26 Carey St",
    "sg:city":"Bunbury",
    "sg:classifiers":[
        {
            "category":"Health Services",
            "subcategory":"Dentist",
            "type":"Services"
        }
    ],
    "sg:phone":"+61 8 9791 2270",
    "sg:postcode":"6230",
    "sg:province":"WA",
    "wof:name":"Dentistry on Marlston",
    "wof:placetype":"venue"
},
  "geometry": {"coordinates":[115.637199,-33.319847],"type":"Point"}
}