{
  "type": "Feature",
  "properties": {
    "addr:full":"14-16 Farley St Derwent Park TAS 7009",
    "addr:housenumber":"14-16",
    "addr:postcode":"7009",
    "addr:street":"Farley St",
    "iso:country":"AU",
    "sg:address":"14-16 Farley St",
    "sg:city":"Derwent Park",
    "sg:classifiers":[
        {
            "category":"Social Services",
            "subcategory":"Adult Care",
            "type":"Services"
        }
    ],
    "sg:phone":"+61 3 6273 3251",
    "sg:postcode":"7009",
    "sg:province":"TAS",
    "sg:tags":[
        "aged"
    ],
    "wof:name":"Community Transport Services Tasmania Inc",
    "wof:placetype":"venue"
},
  "geometry": {"coordinates":[147.28692626899999,-42.8344268799],"type":"Point"}
}