{
  "type": "Feature",
  "properties": {
    "addr:full":"45 Park La Wangaratta VIC 3677",
    "addr:housenumber":"45",
    "addr:postcode":"3677",
    "addr:street":"Park La",
    "iso:country":"AU",
    "sg:address":"45 Park La",
    "sg:city":"Wangaratta",
    "sg:classifiers":[
        {
            "category":"Building & Trades",
            "subcategory":"Construction",
            "type":"Services"
        }
    ],
    "sg:phone":"+61 428 500 053",
    "sg:postcode":"3677",
    "sg:province":"VIC",
    "sg:tags":[
        "earth",
        "excavating",
        "moving",
        "contractor"
    ],
    "wof:name":"Hockings Mini Earthmoving",
    "wof:placetype":"venue"
},
  "geometry": {"coordinates":[146.31265258799999,-36.3413887024],"type":"Point"}
}