{
  "type": "Feature",
  "properties": {
    "addr:full":"37 Kendal St Cowra NSW 2794",
    "addr:housenumber":"37",
    "addr:postcode":"2794",
    "addr:street":"Kendal St",
    "iso:country":"AU",
    "sg:address":"37 Kendal St",
    "sg:city":"Cowra",
    "sg:classifiers":[
        {
            "category":"Banks & Credit Unions",
            "subcategory":"Financial Services",
            "type":"Services"
        }
    ],
    "sg:phone":"+61 2 6341 2309",
    "sg:postcode":"2794",
    "sg:province":"NSW",
    "sg:tags":[
        "planning"
    ],
    "wof:name":"Maclean Beth Financial Adviser",
    "wof:placetype":"venue"
},
  "geometry": {"coordinates":[148.69776916500001,-33.8355636597],"type":"Point"}
}