{
  "type": "Feature",
  "properties": {
    "addr:full":"Troys Rd Charlton QLD 4350",
    "addr:postcode":"4350",
    "addr:street":"Troys Rd",
    "iso:country":"AU",
    "sg:address":"Troys Rd",
    "sg:city":"Charlton",
    "sg:classifiers":[
        {
            "category":"Travel",
            "subcategory":"Hostel",
            "type":"Entertainment"
        }
    ],
    "sg:phone":"+61 7 4630 4181",
    "sg:postcode":"4350",
    "sg:province":"QLD",
    "sg:tags":[
        "home"
    ],
    "wof:name":"Haven Association Incorporated The",
    "wof:placetype":"venue"
},
  "geometry": {"coordinates":[151.87249800000001,-27.530344],"type":"Point"}
}