{
  "type": "Feature",
  "properties": {
    "addr:full":"1st Floor 86 St Kilda Rd St Kilda VIC 3182",
    "addr:housenumber":"86",
    "addr:postcode":"3182",
    "addr:street":"St Kilda Rd",
    "iso:country":"AU",
    "sg:address":"1st Floor 86 St Kilda Rd",
    "sg:city":"St Kilda",
    "sg:classifiers":[
        {
            "category":"Professional",
            "subcategory":"Accounting & Tax Preparation",
            "type":"Services"
        }
    ],
    "sg:phone":"+61 1300 267 835",
    "sg:postcode":"3182",
    "sg:province":"VIC",
    "sg:tags":[
        "bookkeeping"
    ],
    "wof:name":"Bortell Pty Ltd",
    "wof:placetype":"venue"
},
  "geometry": {"coordinates":[144.984085083,-37.8588523865],"type":"Point"}
}