{
  "type": "Feature",
  "properties": {
    "addr:full":"PO Box 7245 Upper Ferntree Gully VIC 3156",
    "addr:postcode":"3156",
    "iso:country":"AU",
    "sg:address":"PO Box 7245",
    "sg:city":"Upper Ferntree Gully",
    "sg:classifiers":[
        {
            "category":"Transit Center",
            "subcategory":"Passenger",
            "type":"Transportation"
        }
    ],
    "sg:phone":"+61 3 9755 3202",
    "sg:postcode":"3156",
    "sg:province":"VIC",
    "sg:tags":[
        "retail",
        "toiletry",
        "perfume"
    ],
    "wof:name":"Fragrance Choice",
    "wof:placetype":"venue"
},
  "geometry": {"coordinates":[145.261184692,-37.8898849487],"type":"Point"}
}