{
  "type": "Feature",
  "properties": {
    "addr:full":"60 Young Rd Lambton NSW 2299",
    "addr:housenumber":"60",
    "addr:postcode":"2299",
    "addr:street":"Young Rd",
    "iso:country":"AU",
    "sg:address":"60 Young Rd",
    "sg:city":"Lambton",
    "sg:classifiers":[
        {
            "category":"Arts & Performance",
            "subcategory":"Music",
            "type":"Entertainment"
        }
    ],
    "sg:phone":"+61 423 245 800",
    "sg:postcode":"2299",
    "sg:province":"NSW",
    "sg:tags":[
        "mobile",
        "jockey",
        "disc"
    ],
    "wof:name":"Ben Marchant",
    "wof:placetype":"venue"
},
  "geometry": {"coordinates":[151.71945190400001,-32.9155464172],"type":"Point"}
}