{
  "type": "Feature",
  "properties": {
    "addr:full":"Woodlawn Rd Lismore NSW 2480",
    "addr:postcode":"2480",
    "addr:street":"Woodlawn Rd",
    "iso:country":"AU",
    "sg:address":"Woodlawn Rd",
    "sg:city":"Lismore",
    "sg:classifiers":[
        {
            "category":"Retail",
            "subcategory":"Auto Repair",
            "type":"Services"
        }
    ],
    "sg:phone":"+61 418 697 817",
    "sg:postcode":"2480",
    "sg:province":"NSW",
    "sg:tags":[
        "repairer",
        "motor",
        "engineer"
    ],
    "wof:name":"Woodlawn Motors",
    "wof:placetype":"venue"
},
  "geometry": {"coordinates":[153.29124450699999,-28.7874984741],"type":"Point"}
}