{
  "type": "Feature",
  "properties": {
    "addr:full":"PO Box 2364 South Hedland WA 6722",
    "addr:postcode":"6722",
    "addr:street":"South",
    "iso:country":"AU",
    "sg:address":"PO Box 2364",
    "sg:city":"South Hedland",
    "sg:classifiers":[
        {
            "category":"Building & Trades",
            "subcategory":"Construction",
            "type":"Services"
        }
    ],
    "sg:phone":"+61 418 934 936",
    "sg:postcode":"6722",
    "sg:province":"WA",
    "sg:tags":[
        "concrete",
        "contractor"
    ],
    "wof:name":"B & G Kerbing",
    "wof:placetype":"venue"
},
  "geometry": {"coordinates":[118.60131072999999,-20.4081993103],"type":"Point"}
}