{
  "type": "Feature",
  "properties": {
    "iso:country":"AU",
    "sg:address":"37 Myrtle St",
    "sg:city":"Chippendale",
    "sg:classifiers":[
        {
            "category":"Real Estate",
            "subcategory":"Real Estate Agent",
            "type":"Services"
        }
    ],
    "sg:phone":"+61 2 9699 1321",
    "sg:postcode":"2008",
    "sg:province":"NSW",
    "wof:name":"La Gonda Pty Ltd",
    "wof:placetype":"venue"
},
  "geometry": {"coordinates":[151.195236206,-33.8870429993],"type":"Point"}
}