{
  "type": "Feature",
  "properties": {
    "addr:full":"PO Box 521 Kensington NSW 1465",
    "addr:postcode":"1465",
    "iso:country":"AU",
    "sg:address":"PO Box 521",
    "sg:city":"Kensington",
    "sg:classifiers":[
        {
            "category":"Professional",
            "subcategory":"Art Services",
            "type":"Services"
        }
    ],
    "sg:phone":"+61 414 544 866",
    "sg:postcode":"1465",
    "sg:province":"NSW",
    "sg:tags":[
        "interior",
        "decorator"
    ],
    "wof:name":"Downie Thomson Interior Design",
    "wof:placetype":"venue"
},
  "geometry": {"coordinates":[151.223419189,-33.9090003967],"type":"Point"}
}