{
  "type": "Feature",
  "properties": {
    "addr:full":"11 Gilbert St Long Jetty NSW 2261",
    "addr:housenumber":"11",
    "addr:postcode":"2261",
    "addr:street":"Gilbert St",
    "iso:country":"AU",
    "sg:address":"11 Gilbert St",
    "sg:city":"Long Jetty",
    "sg:classifiers":[
        {
            "category":"Education",
            "subcategory":"Music School",
            "type":"Public Place"
        }
    ],
    "sg:phone":"+61 2 4333 3344",
    "sg:postcode":"2261",
    "sg:province":"NSW",
    "sg:tags":[
        "teacher"
    ],
    "wof:name":"David Hill",
    "wof:placetype":"venue"
},
  "geometry": {"coordinates":[151.495743,-33.351532],"type":"Point"}
}