{
  "type": "Feature",
  "properties": {
    "addr:full":"Moody St Koo Wee Rup VIC 3981",
    "addr:postcode":"3981",
    "addr:street":"Moody St",
    "iso:country":"AU",
    "sg:address":"Moody St",
    "sg:city":"Koo Wee Rup",
    "sg:classifiers":[
        {
            "category":"Education",
            "subcategory":"School",
            "type":"Public Place"
        }
    ],
    "sg:phone":"+61 3 5997 1272",
    "sg:postcode":"3981",
    "sg:province":"VIC",
    "sg:tags":[
        "state",
        "except",
        "nsw"
    ],
    "wof:name":"Koo Wee Rup Primary School",
    "wof:placetype":"venue"
},
  "geometry": {"coordinates":[145.48831176799999,-38.1978645325],"type":"Point"}
}