{
  "type": "Feature",
  "properties": {
    "addr:full":"2 Malcolm St North Narrabeen NSW 2101",
    "addr:housenumber":"2",
    "addr:postcode":"2101",
    "addr:street":"Malcolm St",
    "iso:country":"AU",
    "sg:address":"2 Malcolm St",
    "sg:city":"North Narrabeen",
    "sg:classifiers":[
        {
            "category":"Arena",
            "subcategory":"Sports Club",
            "type":"Entertainment"
        }
    ],
    "sg:phone":"+61 2 9913 8810",
    "sg:postcode":"2101",
    "sg:province":"NSW",
    "sg:tags":[
        "life",
        "surfing",
        "saving"
    ],
    "wof:name":"North Narrabeen Surf Life Saving Club",
    "wof:placetype":"venue"
},
  "geometry": {"coordinates":[151.303574,-33.705578],"type":"Point"}
}