{
  "type": "Feature",
  "properties": {
    "addr:full":"Level 8 33 Franklin St Adelaide SA 5000",
    "addr:housenumber":"33",
    "addr:postcode":"5000",
    "addr:street":"Franklin St",
    "iso:country":"AU",
    "sg:address":"Level 8 33 Franklin St",
    "sg:city":"Adelaide",
    "sg:classifiers":[
        {
            "category":"Shopping",
            "subcategory":"News",
            "type":"Retail Goods"
        }
    ],
    "sg:phone":"+61 8 8132 7000",
    "sg:postcode":"5000",
    "sg:province":"SA",
    "sg:tags":[
        "magazine",
        "periodical"
    ],
    "wof:name":"Attitude Magazine",
    "wof:placetype":"venue"
},
  "geometry": {"coordinates":[138.59786987300001,-34.9273910522],"type":"Point"}
}