{
  "type": "Feature",
  "properties": {
    "iso:country":"AU",
    "sg:address":"9 Sleat Rd",
    "sg:city":"Applecross",
    "sg:classifiers":[
        {
            "category":"Retail",
            "subcategory":"Veterinary Services",
            "type":"Services"
        }
    ],
    "sg:phone":"+61 8 9364 7666",
    "sg:postcode":"6153",
    "sg:province":"WA",
    "sg:tags":[
        "surgeon"
    ],
    "wof:name":"McDowell Ian",
    "wof:placetype":"venue"
},
  "geometry": {"coordinates":[115.846626,-32.013634],"type":"Point"}
}