{
  "type": "Feature",
  "properties": {
    "iso:country":"AU",
    "sg:address":"PO Box 6086",
    "sg:city":"Griffith",
    "sg:classifiers":[
        {
            "category":"Utilities",
            "subcategory":"Electric",
            "type":"Services"
        }
    ],
    "sg:phone":"+61 2 6295 0212",
    "sg:postcode":"2603",
    "sg:province":"ACT",
    "sg:tags":[
        "electrical",
        "contractor"
    ],
    "wof:name":"Monaro Electrics",
    "wof:placetype":"venue"
},
  "geometry": {"coordinates":[149.14610290499999,-35.3248291016],"type":"Point"}
}