{
  "type": "Feature",
  "properties": {
    "addr:full":"164 Campbell St Hobart TAS 7000",
    "addr:housenumber":"164",
    "addr:postcode":"7000",
    "addr:street":"Campbell St",
    "iso:country":"AU",
    "sg:address":"164 Campbell St",
    "sg:city":"Hobart",
    "sg:classifiers":[
        {
            "category":"Utilities",
            "type":"Services"
        }
    ],
    "sg:phone":"+61 3 6231 3726",
    "sg:postcode":"7000",
    "sg:province":"TAS",
    "sg:tags":[
        "equipment",
        "towing"
    ],
    "wof:name":"Battery World Hobart",
    "wof:placetype":"venue"
},
  "geometry": {"coordinates":[147.324050903,-42.8750648499],"type":"Point"}
}