{
  "type": "Feature",
  "properties": {
    "iso:country":"AU",
    "sg:address":"9 Havelock St",
    "sg:city":"West Perth",
    "sg:classifiers":[
        {
            "category":"Professional",
            "subcategory":"Art Services",
            "type":"Services"
        }
    ],
    "sg:phone":"+61 8 9485 2122",
    "sg:postcode":"6005",
    "sg:province":"WA",
    "sg:tags":[
        "interior",
        "designer"
    ],
    "wof:name":"Paterson Group Architects",
    "wof:placetype":"venue"
},
  "geometry": {"coordinates":[115.84472656200001,-31.9482059479],"type":"Point"}
}