{
  "type": "Feature",
  "properties": {
    "iso:country":"AU",
    "sg:address":"Lvl1/ 86 Vulture St",
    "sg:city":"West End (Brisbane)",
    "sg:classifiers":[
        {
            "category":"Real Estate",
            "subcategory":"Architect",
            "type":"Services"
        }
    ],
    "sg:phone":"+61 7 3846 0064",
    "sg:postcode":"4101",
    "sg:province":"QLD",
    "wof:name":"Tim Bennetton Architects Pty Ltd",
    "wof:placetype":"venue"
},
  "geometry": {"coordinates":[153.01094055199999,-27.4770545959],"type":"Point"}
}