{
  "type": "Feature",
  "properties": {
    "addr:full":"Suite 1/ 85 River St Ballina NSW 2478",
    "addr:housenumber":"85",
    "addr:postcode":"2478",
    "addr:street":"River St",
    "iso:country":"AU",
    "sg:address":"Suite 1/ 85 River St",
    "sg:city":"Ballina",
    "sg:classifiers":[
        {
            "category":"Professional",
            "subcategory":"Accounting & Tax Preparation",
            "type":"Services"
        }
    ],
    "sg:phone":"+61 2 6686 9988",
    "sg:postcode":"2478",
    "sg:province":"NSW",
    "sg:tags":[
        "accountant",
        "auditor"
    ],
    "wof:name":"Lucy & Hepworth",
    "wof:placetype":"venue"
},
  "geometry": {"coordinates":[153.561767578,-28.8708515167],"type":"Point"}
}