{
  "type": "Feature",
  "properties": {
    "iso:country":"AU",
    "sg:address":"32 Wurley Drv",
    "sg:city":"Wurtulla",
    "sg:classifiers":[
        {
            "category":"Building & Trades",
            "subcategory":"Construction",
            "type":"Services"
        }
    ],
    "sg:phone":"+61 418 738 517",
    "sg:postcode":"4575",
    "sg:province":"QLD",
    "sg:tags":[
        "earth",
        "excavating",
        "moving",
        "contractor"
    ],
    "wof:name":"Lovell Excavations",
    "wof:placetype":"venue"
},
  "geometry": {"coordinates":[153.13017300000001,-26.746918],"type":"Point"}
}