{
  "type": "Feature",
  "properties": {
    "addr:full":"8 Yarrinup Ave Chadstone VIC 3148",
    "addr:housenumber":"8",
    "addr:postcode":"3148",
    "addr:street":"Yarrinup Ave",
    "iso:country":"AU",
    "sg:address":"8 Yarrinup Ave",
    "sg:city":"Chadstone",
    "sg:classifiers":[
        {
            "category":"Professional",
            "subcategory":"Computer Services",
            "type":"Services"
        }
    ],
    "sg:phone":"+61 408 012 100",
    "sg:postcode":"3148",
    "sg:province":"VIC",
    "sg:tags":[
        "consultant",
        "system"
    ],
    "wof:name":"Globe Business Consulting",
    "wof:placetype":"venue"
},
  "geometry": {"coordinates":[145.10528564399999,-37.8754768372],"type":"Point"}
}