{
  "type": "Feature",
  "properties": {
    "addr:full":"12 Federal Rd Kalgoorlie WA 6430",
    "addr:housenumber":"12",
    "addr:postcode":"6430",
    "addr:street":"Federal Rd",
    "iso:country":"AU",
    "sg:address":"12 Federal Rd",
    "sg:city":"Kalgoorlie",
    "sg:classifiers":[
        {
            "category":"Manufacturing",
            "subcategory":"Motor Vehicles & Parts",
            "type":"Manufacturing & Wholesale Goods"
        }
    ],
    "sg:phone":"+61 8 9021 8164",
    "sg:postcode":"6430",
    "sg:province":"WA",
    "sg:tags":[
        "wholesaler",
        "cycle",
        "mfrs",
        "accessory"
    ],
    "wof:name":"Goldfields Bikeworks",
    "wof:placetype":"venue"
},
  "geometry": {"coordinates":[121.48654174799999,-30.7600631714],"type":"Point"}
}