{
  "type": "Feature",
  "properties": {
    "addr:full":"PO Box 858 Mittagong NSW 2575",
    "addr:postcode":"2575",
    "iso:country":"AU",
    "sg:address":"PO Box 858",
    "sg:city":"Mittagong",
    "sg:classifiers":[
        {
            "category":"Professional",
            "type":"Services"
        }
    ],
    "sg:phone":"+61 419 615 139",
    "sg:postcode":"2575",
    "sg:province":"NSW",
    "sg:tags":[
        "courier"
    ],
    "wof:name":"Quick Trips Courier Service",
    "wof:placetype":"venue"
},
  "geometry": {"coordinates":[150.44688415499999,-34.4510002136],"type":"Point"}
}