{
  "type": "Feature",
  "properties": {
    "addr:full":"Suite 4 / 608- 610 Willoughby Rd Willoughby NSW 2068",
    "addr:housenumber":"/ 608 610",
    "addr:postcode":"2068",
    "addr:street":"Willoughby Rd",
    "iso:country":"AU",
    "sg:address":"Suite 4 / 608- 610 Willoughby Rd",
    "sg:city":"Willoughby",
    "sg:classifiers":[
        {
            "category":"Manufacturing",
            "subcategory":"Furniture",
            "type":"Manufacturing & Wholesale Goods"
        }
    ],
    "sg:phone":"+61 2 9967 4343",
    "sg:postcode":"2068",
    "sg:province":"NSW",
    "sg:tags":[
        "builder",
        "designer",
        "custom"
    ],
    "wof:name":"Interior Expressions",
    "wof:placetype":"venue"
},
  "geometry": {"coordinates":[151.19903564399999,-33.8060302734],"type":"Point"}
}