{
  "type": "Feature",
  "properties": {
    "iso:country":"AU",
    "sg:address":"PO Box 4096",
    "sg:city":"Mataranka",
    "sg:classifiers":[
        {
            "category":"Retail",
            "subcategory":"Auto Repair",
            "type":"Services"
        }
    ],
    "sg:phone":"+61 8 8975 4614",
    "sg:postcode":"0852",
    "sg:province":"NT",
    "sg:tags":[
        "repairer",
        "motor",
        "engineer"
    ],
    "wof:name":"Northern Diesel Services (N.T.)",
    "wof:placetype":"venue"
},
  "geometry": {"coordinates":[133.075333,-14.958],"type":"Point"}
}