{
  "type": "Feature",
  "properties": {
    "addr:full":"63 Levistone St Seaton SA 5023",
    "addr:housenumber":"63",
    "addr:postcode":"5023",
    "addr:street":"Levistone St",
    "iso:country":"AU",
    "sg:address":"63 Levistone St",
    "sg:city":"Seaton",
    "sg:classifiers":[
        {
            "category":"Building & Trades",
            "subcategory":"Plumbing",
            "type":"Services"
        }
    ],
    "sg:phone":"+61 8 8244 2480",
    "sg:postcode":"5023",
    "sg:province":"SA",
    "sg:tags":[
        "plumber",
        "gasfitters"
    ],
    "wof:name":"Chris Watson Plumbing",
    "wof:placetype":"venue"
},
  "geometry": {"coordinates":[138.52180480999999,-34.8895187378],"type":"Point"}
}