{
  "type": "Feature",
  "properties": {
    "addr:full":"Shop 190, Westfield Shoppingtown, Cnr Gympie & Ham Chermside QLD 4032",
    "addr:housenumber":"190",
    "addr:postcode":"qld 4032",
    "addr:street":"Westfield Shoppingtown Cnr Gympie & Ham",
    "iso:country":"AU",
    "sg:address":"Shop 190, Westfield Shoppingtown, Cnr Gympie & Ham",
    "sg:city":"Chermside",
    "sg:classifiers":[
        {
            "category":"Travel",
            "subcategory":"Travel Agent",
            "type":"Entertainment"
        }
    ],
    "sg:phone":"+61 7 3861 4266",
    "sg:postcode":"4032",
    "sg:province":"QLD",
    "sg:tags":[
        "consultant"
    ],
    "wof:name":"STA Travel",
    "wof:placetype":"venue"
},
  "geometry": {"coordinates":[153.031113,-27.386387],"type":"Point"}
}