{
  "type": "Feature",
  "properties": {
    "iso:country":"AU",
    "sg:address":"71- 73 Alexander St",
    "sg:city":"Crows Nest",
    "sg:classifiers":[
        {
            "category":"Professional",
            "subcategory":"Art Services",
            "type":"Services"
        }
    ],
    "sg:phone":"+61 418 209 518",
    "sg:postcode":"2065",
    "sg:province":"NSW",
    "sg:tags":[
        "graphic",
        "designer"
    ],
    "wof:name":"Next Level Productions Pty Ltd",
    "wof:placetype":"venue"
},
  "geometry": {"coordinates":[151.20234680199999,-33.8265075684],"type":"Point"}
}