{
  "type": "Feature",
  "properties": {
    "addr:full":"6 John St Mt Gambier SA 5290",
    "addr:housenumber":"6",
    "addr:postcode":"5290",
    "addr:street":"John St",
    "iso:country":"AU",
    "sg:address":"6 John St",
    "sg:city":"Mt Gambier",
    "sg:classifiers":[
        {
            "category":"Home & Garden",
            "subcategory":"Building Materials",
            "type":"Retail Goods"
        }
    ],
    "sg:phone":"+61 8 8725 9433",
    "sg:postcode":"5290",
    "sg:province":"SA",
    "sg:tags":[
        "supply"
    ],
    "wof:name":"Norm's Plumbing & Building Supplies",
    "wof:placetype":"venue"
},
  "geometry": {"coordinates":[140.78791799999999,-37.82946],"type":"Point"}
}