{
  "type": "Feature",
  "properties": {
    "addr:full":"PO Box 1125 Park Ridge QLD 4125",
    "addr:postcode":"4125",
    "iso:country":"AU",
    "sg:address":"PO Box 1125",
    "sg:city":"Park Ridge",
    "sg:classifiers":[
        {
            "category":"Building & Trades",
            "subcategory":"Construction",
            "type":"Services"
        }
    ],
    "sg:phone":"+61 7 3269 4911",
    "sg:postcode":"4125",
    "sg:province":"QLD",
    "sg:tags":[
        "stonework",
        "stone",
        "mason"
    ],
    "wof:name":"Queensland Heritage Masonry Pty Ltd",
    "wof:placetype":"venue"
},
  "geometry": {"coordinates":[153.06152343799999,-27.703950882],"type":"Point"}
}