{
  "type": "Feature",
  "properties": {
    "addr:full":"109 Hertford St Sebastopol VIC 3356",
    "addr:housenumber":"109",
    "addr:postcode":"3356",
    "addr:street":"Hertford St",
    "iso:country":"AU",
    "sg:address":"109 Hertford St",
    "sg:city":"Sebastopol",
    "sg:classifiers":[
        {
            "category":"Wholesale",
            "subcategory":"Medical Equipment & Supplies",
            "type":"Manufacturing & Wholesale Goods"
        }
    ],
    "sg:phone":"+61 3 5336 3900",
    "sg:postcode":"3356",
    "sg:province":"VIC",
    "sg:tags":[
        "aid",
        "care",
        "health",
        "home"
    ],
    "wof:name":"Astec Equipment Services",
    "wof:placetype":"venue"
},
  "geometry": {"coordinates":[143.82681299999999,-37.587357],"type":"Point"}
}