{
  "type": "Feature",
  "properties": {
    "iso:country":"AU",
    "sg:address":"Shop 4, Cnr Of How & Aldinga Beach Rd",
    "sg:city":", Aldinga Beach 5173 Aldinga Beach",
    "sg:classifiers":[
        {
            "category":"Shopping",
            "subcategory":"Party Supplies",
            "type":"Retail Goods"
        }
    ],
    "sg:phone":"+61 418 832 809",
    "sg:postcode":"5173",
    "sg:province":"SA",
    "wof:name":"Alaska Mobile Coolroom Hire",
    "wof:placetype":"venue"
},
  "geometry": {"coordinates":[138.45703125,-35.2785873413],"type":"Point"}
}