{
  "type": "Feature",
  "properties": {
    "addr:full":"498 King Georges Rd Beverly Hills NSW 2209",
    "addr:housenumber":"498",
    "addr:postcode":"2209",
    "addr:street":"King Georges Rd",
    "iso:country":"AU",
    "sg:address":"498 King Georges Rd",
    "sg:city":"Beverly Hills",
    "sg:classifiers":[
        {
            "category":"Restaurant",
            "type":"Food & Drink"
        }
    ],
    "sg:phone":"+61 2 9580 6721",
    "sg:postcode":"2209",
    "sg:province":"NSW",
    "wof:name":"Bamboo Inn",
    "wof:placetype":"venue"
},
  "geometry": {"coordinates":[151.08152799999999,-33.949883],"type":"Point"}
}