{
  "type": "Feature",
  "properties": {
    "addr:full":"1 Julia Crt Bittern VIC 3918",
    "addr:housenumber":"1",
    "addr:postcode":"3918",
    "addr:street":"Julia Crt",
    "iso:country":"AU",
    "sg:address":"1 Julia Crt",
    "sg:city":"Bittern",
    "sg:classifiers":[
        {
            "category":"Communications",
            "subcategory":"Television Station",
            "type":"Services"
        }
    ],
    "sg:phone":"+61 3 5979 4557",
    "sg:postcode":"3918",
    "sg:province":"VIC",
    "sg:tags":[
        "mfrs",
        "tank",
        "installation",
        "septic"
    ],
    "wof:name":"Sweet Water Plumbing",
    "wof:placetype":"venue"
},
  "geometry": {"coordinates":[145.170211792,-38.3369865417],"type":"Point"}
}