{
  "type": "Feature",
  "properties": {
    "addr:full":"9/ 338 Botany Rd Alexandria NSW 2015",
    "addr:housenumber":"/ 338",
    "addr:postcode":"2015",
    "addr:street":"Botany Rd",
    "iso:country":"AU",
    "sg:address":"9/ 338 Botany Rd",
    "sg:city":"Alexandria",
    "sg:classifiers":[
        {
            "category":"Retail",
            "subcategory":"Auto Repair",
            "type":"Services"
        }
    ],
    "sg:phone":"+61 2 9319 3281",
    "sg:postcode":"2015",
    "sg:province":"NSW",
    "sg:tags":[
        "repairer",
        "motor",
        "engineer"
    ],
    "wof:name":"ATM Mechanical Repairers",
    "wof:placetype":"venue"
},
  "geometry": {"coordinates":[151.202682495,-33.908115387],"type":"Point"}
}