{
  "type": "Feature",
  "properties": {
    "iso:country":"AU",
    "sg:address":"Clarkson St",
    "sg:city":"Nabiac",
    "sg:classifiers":[
        {
            "category":"Personal",
            "subcategory":"Beauty Salon",
            "type":"Services"
        }
    ],
    "sg:phone":"+61 2 6554 1455",
    "sg:postcode":"2312",
    "sg:province":"NSW",
    "sg:tags":[
        "hairdresser"
    ],
    "wof:name":"Reflections Hair & Beauty",
    "wof:placetype":"venue"
},
  "geometry": {"coordinates":[152.376114,-32.099827],"type":"Point"}
}