{
  "type": "Feature",
  "properties": {
    "iso:country":"AU",
    "sg:address":"50 Great Eastern Hwy",
    "sg:city":"South Guildford",
    "sg:classifiers":[
        {
            "category":"Building & Trades",
            "subcategory":"Equipment Rental",
            "type":"Services"
        }
    ],
    "sg:phone":"+61 1300 658 888",
    "sg:postcode":"6055",
    "sg:province":"WA",
    "sg:tags":[
        "crane",
        "hire"
    ],
    "wof:name":"Tat Hong Rental",
    "wof:placetype":"venue"
},
  "geometry": {"coordinates":[115.960518,-31.918264],"type":"Point"}
}