{
  "type": "Feature",
  "properties": {
    "addr:full":"2 Beach Rd Redhead NSW 2290",
    "addr:housenumber":"2",
    "addr:postcode":"2290",
    "addr:street":"Beach Rd",
    "iso:country":"AU",
    "sg:address":"2 Beach Rd",
    "sg:city":"Redhead",
    "sg:classifiers":[
        {
            "category":"Home & Garden",
            "subcategory":"Garden Supply",
            "type":"Retail Goods"
        }
    ],
    "sg:phone":"+61 2 4946 0110",
    "sg:postcode":"2290",
    "sg:province":"NSW",
    "sg:tags":[
        "fertilizer"
    ],
    "wof:name":"Newcastle Greenkeepers Supplies Pty Ltd",
    "wof:placetype":"venue"
},
  "geometry": {"coordinates":[151.71675109899999,-33.0124397278],"type":"Point"}
}