{
  "type": "Feature",
  "properties": {
    "iso:country":"AU",
    "sg:address":"Level 2, 170 Greenhill Rd",
    "sg:city":"Eastwood",
    "sg:classifiers":[
        {
            "category":"Farming",
            "subcategory":"Fish & Marine Products",
            "type":"Manufacturing & Wholesale Goods"
        }
    ],
    "sg:phone":"+61 8 8357 1633",
    "sg:postcode":"5063",
    "sg:province":"SA",
    "sg:tags":[
        "chemical",
        "supplier"
    ],
    "wof:name":"IMCD Australia Limited",
    "wof:placetype":"venue"
},
  "geometry": {"coordinates":[138.618377686,-34.9405899048],"type":"Point"}
}