{
  "type": "Feature",
  "properties": {
    "addr:full":"2 Northey Drv Armidale NSW 2350",
    "addr:housenumber":"2",
    "addr:postcode":"2350",
    "addr:street":"Northey Drv",
    "iso:country":"AU",
    "sg:address":"2 Northey Drv",
    "sg:city":"Armidale",
    "sg:classifiers":[
        {
            "category":"Building & Trades",
            "subcategory":"Plumbing",
            "type":"Services"
        }
    ],
    "sg:phone":"+61 2 6772 6340",
    "sg:postcode":"2350",
    "sg:province":"NSW",
    "sg:tags":[
        "plumber",
        "gasfitters"
    ],
    "wof:name":"Roach G W & J M",
    "wof:placetype":"venue"
},
  "geometry": {"coordinates":[151.68487548799999,-30.5058021545],"type":"Point"}
}