{
  "type": "Feature",
  "properties": {
    "iso:country":"AU",
    "sg:address":"311 Petrie Creek Rd",
    "sg:city":"Nambour",
    "sg:classifiers":[
        {
            "category":"Farming",
            "subcategory":"Nursery",
            "type":"Manufacturing & Wholesale Goods"
        }
    ],
    "sg:phone":"+61 7 5441 5221",
    "sg:postcode":"4560",
    "sg:province":"QLD",
    "wof:name":"Palm Fascinations",
    "wof:placetype":"venue"
},
  "geometry": {"coordinates":[153.00335693400001,-26.6218357086],"type":"Point"}
}