{
  "type": "Feature",
  "properties": {
    "iso:country":"AU",
    "sg:address":"2 Fitzroy Rd",
    "sg:city":"Warrnambool",
    "sg:classifiers":[
        {
            "category":"Shopping",
            "subcategory":"Antiques",
            "type":"Retail Goods"
        }
    ],
    "sg:phone":"+61 3 5561 1132",
    "sg:postcode":"3280",
    "sg:province":"VIC",
    "sg:tags":[
        "restoration",
        "reproduction"
    ],
    "wof:name":"Don Haugh",
    "wof:placetype":"venue"
},
  "geometry": {"coordinates":[142.47259521500001,-38.3714599609],"type":"Point"}
}