{
  "type": "Feature",
  "properties": {
    "iso:country":"AU",
    "sg:address":"Cnr Frankston-Dandenong & O'Grady's Rds",
    "sg:city":"Carrum Downs",
    "sg:classifiers":[
        {
            "category":"Travel",
            "subcategory":"Hotels & Motels",
            "type":"Entertainment"
        }
    ],
    "sg:phone":"+61 3 9786 8355",
    "sg:postcode":"3201",
    "sg:province":"VIC",
    "wof:name":"Carrum Downs Motel",
    "wof:placetype":"venue"
},
  "geometry": {"coordinates":[145.174103,-38.09787],"type":"Point"}
}