{
  "type": "Feature",
  "properties": {
    "addr:full":"625 Victoria Rd Ermington NSW 2115",
    "addr:housenumber":"625",
    "addr:postcode":"2115",
    "addr:street":"Victoria Rd",
    "iso:country":"AU",
    "sg:address":"625 Victoria Rd",
    "sg:city":"Ermington",
    "sg:classifiers":[
        {
            "category":"Building & Trades",
            "subcategory":"Construction",
            "type":"Services"
        }
    ],
    "sg:phone":"+61 2 9684 5414",
    "sg:postcode":"2115",
    "sg:province":"NSW",
    "sg:tags":[
        "stonework",
        "stone",
        "mason"
    ],
    "wof:name":"J A & I Gassmann",
    "wof:placetype":"venue"
},
  "geometry": {"coordinates":[151.063156128,-33.8117446899],"type":"Point"}
}