{
  "type": "Feature",
  "properties": {
    "addr:full":"17 Moon St Moolap VIC 3221",
    "addr:housenumber":"17",
    "addr:postcode":"3221",
    "addr:street":"Moon St",
    "iso:country":"AU",
    "sg:address":"17 Moon St",
    "sg:city":"Moolap",
    "sg:classifiers":[
        {
            "category":"Building & Trades",
            "subcategory":"Construction",
            "type":"Services"
        }
    ],
    "sg:phone":"+61 3 5248 2013",
    "sg:postcode":"3221",
    "sg:province":"VIC",
    "sg:tags":[
        "window",
        "timber"
    ],
    "wof:name":"S. Stacey Joinery",
    "wof:placetype":"venue"
},
  "geometry": {"coordinates":[144.413895,-38.165424],"type":"Point"}
}