{
  "type": "Feature",
  "properties": {
    "addr:full":"5 Todd La Romsey VIC 3434",
    "addr:housenumber":"5",
    "addr:postcode":"3434",
    "addr:street":"Todd La",
    "iso:country":"AU",
    "sg:address":"5 Todd La",
    "sg:city":"Romsey",
    "sg:classifiers":[
        {
            "category":"Farming",
            "subcategory":"Vineyard",
            "type":"Manufacturing & Wholesale Goods"
        }
    ],
    "sg:phone":"+61 3 5429 5757",
    "sg:postcode":"3434",
    "sg:province":"VIC",
    "sg:tags":[
        "winery"
    ],
    "wof:name":"McAvoys Estate",
    "wof:placetype":"venue"
},
  "geometry": {"coordinates":[144.739303589,-37.3535385132],"type":"Point"}
}