{
  "type": "Feature",
  "properties": {
    "addr:full":"105 Marlborough St Henley Beach SA 5022",
    "addr:housenumber":"105",
    "addr:postcode":"5022",
    "addr:street":"Marlborough St",
    "iso:country":"AU",
    "sg:address":"105 Marlborough St",
    "sg:city":"Henley Beach",
    "sg:classifiers":[
        {
            "category":"Retail",
            "subcategory":"Auto Repair",
            "type":"Services"
        }
    ],
    "sg:phone":"+61 8 8353 2044",
    "sg:postcode":"5022",
    "sg:province":"SA",
    "sg:tags":[
        "beater",
        "painter",
        "panel"
    ],
    "wof:name":"Cole Motors Crash Repairs",
    "wof:placetype":"venue"
},
  "geometry": {"coordinates":[138.49508667000001,-34.9139633179],"type":"Point"}
}