{
  "type": "Feature",
  "properties": {
    "addr:full":"York St Nimmitabel NSW 2631",
    "addr:postcode":"2631",
    "addr:street":"York St",
    "iso:country":"AU",
    "sg:address":"York St",
    "sg:city":"Nimmitabel",
    "sg:classifiers":[
        {
            "category":"Manufacturing",
            "subcategory":"Wood Products",
            "type":"Manufacturing & Wholesale Goods"
        }
    ],
    "sg:phone":"+61 2 6454 6454",
    "sg:postcode":"2631",
    "sg:province":"NSW",
    "sg:tags":[
        "polisher",
        "french"
    ],
    "wof:name":"Bligh G F",
    "wof:placetype":"venue"
},
  "geometry": {"coordinates":[149.28222656200001,-36.5102577209],"type":"Point"}
}