{
  "type": "Feature",
  "properties": {
    "addr:full":"77 Munibung Rd Cardiff NSW 2285",
    "addr:housenumber":"77",
    "addr:postcode":"2285",
    "addr:street":"Munibung Rd",
    "iso:country":"AU",
    "sg:address":"77 Munibung Rd",
    "sg:city":"Cardiff",
    "sg:classifiers":[
        {
            "category":"Home & Garden",
            "subcategory":"Building Materials",
            "type":"Retail Goods"
        }
    ],
    "sg:phone":"+61 2 4954 3200",
    "sg:postcode":"2285",
    "sg:province":"NSW",
    "sg:tags":[
        "shutter",
        "roller",
        "grille"
    ],
    "wof:name":"Metzen Industries (NSW) Pty Ltd",
    "wof:placetype":"venue"
},
  "geometry": {"coordinates":[151.64002990700001,-32.9426994324],"type":"Point"}
}