{
  "type": "Feature",
  "properties": {
    "addr:full":"34 Finchley Ave Glenroy VIC 3046",
    "addr:housenumber":"34",
    "addr:postcode":"3046",
    "addr:street":"Finchley Ave",
    "iso:country":"AU",
    "sg:address":"34 Finchley Ave",
    "sg:city":"Glenroy",
    "sg:classifiers":[
        {
            "category":"Health Services",
            "subcategory":"Nursing And Care Facility",
            "type":"Services"
        }
    ],
    "sg:phone":"+61 3 9306 7789",
    "sg:postcode":"3046",
    "sg:province":"VIC",
    "sg:tags":[
        "home"
    ],
    "wof:name":"Glenlyn Aged Care Facility",
    "wof:placetype":"venue"
},
  "geometry": {"coordinates":[144.9115448,-37.7028579712],"type":"Point"}
}