{
  "type": "Feature",
  "properties": {
    "addr:full":"350 Pakington St Newtown VIC 3220",
    "addr:housenumber":"350",
    "addr:postcode":"3220",
    "addr:street":"Pakington St",
    "iso:country":"AU",
    "sg:address":"350 Pakington St",
    "sg:city":"Newtown",
    "sg:classifiers":[
        {
            "category":"Food & Beverages",
            "subcategory":"Bakery",
            "type":"Retail Goods"
        }
    ],
    "sg:phone":"+61 3 5221 1253",
    "sg:postcode":"3220",
    "sg:province":"VIC",
    "sg:tags":[
        "baker"
    ],
    "wof:name":"West Coast Bakeries Pty Ltd",
    "wof:placetype":"venue"
},
  "geometry": {"coordinates":[144.34520000000001,-38.157997],"type":"Point"}
}