{
  "type": "Feature",
  "properties": {
    "addr:full":"360 Bong Bong St Bowral NSW 2576",
    "addr:housenumber":"360",
    "addr:postcode":"2576",
    "addr:street":"Bong Bong St",
    "iso:country":"AU",
    "sg:address":"360 Bong Bong St",
    "sg:city":"Bowral",
    "sg:classifiers":[
        {
            "category":"Real Estate",
            "subcategory":"Real Estate Agent",
            "type":"Services"
        }
    ],
    "sg:phone":"+61 2 4861 4600",
    "sg:postcode":"2576",
    "sg:province":"NSW",
    "wof:name":"Peter Shaw First National",
    "wof:placetype":"venue"
},
  "geometry": {"coordinates":[150.417694092,-34.4803924561],"type":"Point"}
}