{
  "type": "Feature",
  "properties": {
    "addr:full":"Southern Cross Drv Ballina NSW 2478",
    "addr:postcode":"2478",
    "addr:street":"Southern Cross Drv",
    "iso:country":"AU",
    "sg:address":"Southern Cross Drv",
    "sg:city":"Ballina",
    "sg:classifiers":[
        {
            "category":"Food & Beverages",
            "subcategory":"Specialty",
            "type":"Retail Goods"
        }
    ],
    "sg:phone":"+61 2 6686 7999",
    "sg:postcode":"2478",
    "sg:province":"NSW",
    "sg:tags":[
        "delicacy"
    ],
    "wof:name":"Eagle Fine Foods",
    "wof:placetype":"venue"
},
  "geometry": {"coordinates":[153.55601501500001,-28.8523006439],"type":"Point"}
}