{
  "type": "Feature",
  "properties": {
    "addr:full":"63a Westbrook Ave Wahroonga NSW 2076",
    "addr:housenumber":"63a",
    "addr:postcode":"2076",
    "addr:street":"Westbrook Ave",
    "iso:country":"AU",
    "sg:address":"63a Westbrook Ave",
    "sg:city":"Wahroonga",
    "sg:classifiers":[
        {
            "category":"Professional",
            "subcategory":"Art Services",
            "type":"Services"
        }
    ],
    "sg:phone":"+61 2 9487 6145",
    "sg:postcode":"2076",
    "sg:province":"NSW",
    "sg:tags":[
        "interior",
        "decorator"
    ],
    "wof:name":"Peter Wainwright Pty Ltd",
    "wof:placetype":"venue"
},
  "geometry": {"coordinates":[151.13648986800001,-33.7091712952],"type":"Point"}
}