{
  "type": "Feature",
  "properties": {
    "addr:full":"1A Mackay St Prahran VIC 3181",
    "addr:housenumber":"1a",
    "addr:postcode":"3181",
    "addr:street":"Mackay St",
    "iso:country":"AU",
    "sg:address":"1A Mackay St",
    "sg:city":"Prahran",
    "sg:classifiers":[
        {
            "category":"Education",
            "subcategory":"Music School",
            "type":"Public Place"
        }
    ],
    "sg:phone":"+61 3 9529 4629",
    "sg:postcode":"3181",
    "sg:province":"VIC",
    "sg:tags":[
        "teacher"
    ],
    "wof:name":"Prahran Piano Tuition",
    "wof:placetype":"venue"
},
  "geometry": {"coordinates":[144.99993896500001,-37.8495941162],"type":"Point"}
}