{
  "type": "Feature",
  "properties": {
    "addr:full":"Nicholson St Mall Bairnsdale VIC 3875",
    "addr:postcode":"3875",
    "addr:street":"Nicholson St Mall",
    "iso:country":"AU",
    "sg:address":"Nicholson St",
    "sg:city":"Mall Bairnsdale",
    "sg:classifiers":[
        {
            "category":"Health Services",
            "subcategory":"Optometrist",
            "type":"Services"
        }
    ],
    "sg:phone":"+61 3 5152 1668",
    "sg:postcode":"3875",
    "sg:province":"VIC",
    "wof:name":"Long K.R.",
    "wof:placetype":"venue"
},
  "geometry": {"coordinates":[147.61708068900001,-37.8277397156],"type":"Point"}
}