{
  "type": "Feature",
  "properties": {
    "addr:full":"Shop 20 Eastgate Shopping Centre Bondi Junction NSW 2022",
    "addr:housenumber":"shop 20",
    "addr:postcode":"2022",
    "addr:street":"Eastgate Shopping",
    "iso:country":"AU",
    "sg:address":"Shop 20 Eastgate Shopping Centre",
    "sg:city":"Bondi Junction",
    "sg:classifiers":[
        {
            "category":"Food & Beverages",
            "subcategory":"Liquor & Beverages",
            "type":"Retail Goods"
        }
    ],
    "sg:phone":"+61 2 9387 7322",
    "sg:postcode":"2022",
    "sg:province":"NSW",
    "sg:tags":[
        "store"
    ],
    "wof:name":"Liquorland",
    "wof:placetype":"venue"
},
  "geometry": {"coordinates":[151.24720764200001,-33.892829895],"type":"Point"}
}