{
  "type": "Feature",
  "properties": {
    "addr:full":"30 Chard Rd Brookvale NSW 2100",
    "addr:housenumber":"30",
    "addr:postcode":"2100",
    "addr:street":"Chard Rd",
    "iso:country":"AU",
    "sg:address":"30 Chard Rd",
    "sg:city":"Brookvale",
    "sg:classifiers":[
        {
            "category":"Manufacturing",
            "subcategory":"Motor Vehicles & Parts",
            "type":"Manufacturing & Wholesale Goods"
        }
    ],
    "sg:phone":"+61 2 9938 6522",
    "sg:postcode":"2100",
    "sg:province":"NSW",
    "sg:tags":[
        "replacement"
    ],
    "wof:name":"Federal Mogul Parts Centre",
    "wof:placetype":"venue"
},
  "geometry": {"coordinates":[151.27430725100001,-33.7631835938],"type":"Point"}
}