{
  "type": "Feature",
  "properties": {
    "addr:full":"596 High St Echuca VIC 3564",
    "addr:housenumber":"596",
    "addr:postcode":"3564",
    "addr:street":"High St",
    "iso:country":"AU",
    "sg:address":"596 High St",
    "sg:city":"Echuca",
    "sg:classifiers":[
        {
            "category":"Manufacturing",
            "subcategory":"Rubber & Plastics",
            "type":"Manufacturing & Wholesale Goods"
        }
    ],
    "sg:phone":"+61 3 5482 3041",
    "sg:postcode":"3564",
    "sg:province":"VIC",
    "sg:tags":[
        "product",
        "retail"
    ],
    "wof:name":"Echuca Foam",
    "wof:placetype":"venue"
},
  "geometry": {"coordinates":[144.75296020499999,-36.147895813],"type":"Point"}
}