{
  "type": "Feature",
  "properties": {
    "addr:full":"Duff Pl Deakin ACT 2600",
    "addr:postcode":"2600",
    "addr:street":"Duff Pl Deakin",
    "iso:country":"AU",
    "sg:address":"Duff Pl",
    "sg:city":"Deakin",
    "sg:classifiers":[
        {
            "category":"Fast Food",
            "type":"Food & Drink"
        }
    ],
    "sg:phone":"+61 2 6281 3533",
    "sg:postcode":"2600",
    "sg:province":"ACT",
    "sg:tags":[
        "away",
        "take"
    ],
    "wof:name":"Cafe D&#039;Lish",
    "wof:placetype":"venue"
},
  "geometry": {"coordinates":[149.107589722,-35.3147239685],"type":"Point"}
}