{
  "type": "Feature",
  "properties": {
    "addr:full":"Unit 16, 191 Parramatta Rd Auburn NSW 2144",
    "addr:housenumber":"191",
    "addr:postcode":"2144",
    "addr:street":"Parramatta Rd",
    "iso:country":"AU",
    "sg:address":"Unit 16, 191 Parramatta Rd",
    "sg:city":"Auburn",
    "sg:classifiers":[
        {
            "category":"Professional",
            "subcategory":"Art Services",
            "type":"Services"
        }
    ],
    "sg:phone":"+61 2 9534 7988",
    "sg:postcode":"2144",
    "sg:province":"NSW",
    "sg:tags":[
        "decorator",
        "painter"
    ],
    "wof:name":"Riley Shelley",
    "wof:placetype":"venue"
},
  "geometry": {"coordinates":[151.03492736800001,-33.8406944275],"type":"Point"}
}