{
  "type": "Feature",
  "properties": {
    "iso:country":"AU",
    "sg:address":"1961 Gympie Rd",
    "sg:city":"Bald Hills",
    "sg:classifiers":[
        {
            "category":"Shopping",
            "type":"Retail Goods"
        }
    ],
    "sg:phone":"+61 7 3261 8124",
    "sg:postcode":"4036",
    "sg:province":"QLD",
    "sg:tags":[
        "produce",
        "grain"
    ],
    "wof:name":"Brisbane Northside Produce",
    "wof:placetype":"venue"
},
  "geometry": {"coordinates":[153.008972,-27.328869],"type":"Point"}
}