{
  "type": "Feature",
  "properties": {
    "addr:full":"53 Wises Rd Maroochydore QLD 4558",
    "addr:housenumber":"53",
    "addr:postcode":"4558",
    "addr:street":"Wises Rd",
    "iso:country":"AU",
    "sg:address":"53 Wises Rd",
    "sg:city":"Maroochydore",
    "sg:classifiers":[
        {
            "category":"Manufacturing",
            "subcategory":"Tools & Machinery",
            "type":"Manufacturing & Wholesale Goods"
        }
    ],
    "sg:phone":"+61 7 5451 0388",
    "sg:postcode":"4558",
    "sg:province":"QLD",
    "sg:tags":[
        "fastener",
        "industrial"
    ],
    "wof:name":"Infix",
    "wof:placetype":"venue"
},
  "geometry": {"coordinates":[153.08555602999999,-26.6713409424],"type":"Point"}
}