{
  "type": "Feature",
  "properties": {
    "addr:full":"114 Abercrombie St Chippendale NSW 2008",
    "addr:housenumber":"114",
    "addr:postcode":"2008",
    "addr:street":"Abercrombie St",
    "iso:country":"AU",
    "sg:address":"114 Abercrombie St",
    "sg:city":"Chippendale",
    "sg:classifiers":[
        {
            "category":"Food & Beverages",
            "subcategory":"Liquor & Beverages",
            "type":"Retail Goods"
        }
    ],
    "sg:phone":"+61 2 9310 4167",
    "sg:postcode":"2008",
    "sg:province":"NSW",
    "sg:tags":[
        "store"
    ],
    "wof:name":"Chippendale Cellars",
    "wof:placetype":"venue"
},
  "geometry": {"coordinates":[151.19898986800001,-33.8878593445],"type":"Point"}
}