{
  "type": "Feature",
  "properties": {
    "iso:country":"AU",
    "sg:address":"40 Stewart Ave",
    "sg:city":"Parkdale",
    "sg:classifiers":[
        {
            "category":"Professional",
            "subcategory":"Employment Agencies",
            "type":"Services"
        }
    ],
    "sg:phone":"+61 412 365 711",
    "sg:postcode":"3194",
    "sg:province":"VIC",
    "sg:tags":[
        "entertainer",
        "agent"
    ],
    "wof:name":"Mojo The Clown & Magician",
    "wof:placetype":"venue"
},
  "geometry": {"coordinates":[145.079956055,-37.9906387329],"type":"Point"}
}