{
  "type": "Feature",
  "properties": {
    "iso:country":"AU",
    "sg:address":"830 Leakes Rd",
    "sg:city":"Tarneit",
    "sg:classifiers":[
        {
            "category":"Home & Garden",
            "subcategory":"Garden Supply",
            "type":"Retail Goods"
        }
    ],
    "sg:phone":"+61 3 9749 4200",
    "sg:postcode":"3029",
    "sg:province":"VIC",
    "sg:tags":[
        "fertilizer"
    ],
    "wof:name":"C & J Squires",
    "wof:placetype":"venue"
},
  "geometry": {"coordinates":[144.66343699999999,-37.830662],"type":"Point"}
}