{
  "type": "Feature",
  "properties": {
    "iso:country":"AU",
    "sg:address":"1 1 Cambridge St",
    "sg:city":"Fairfield West",
    "sg:classifiers":[
        {
            "category":"Professional",
            "subcategory":"Detective & Security Services",
            "type":"Services"
        }
    ],
    "sg:phone":"+61 2 9729 0243",
    "sg:postcode":"2165",
    "sg:province":"NSW",
    "sg:tags":[
        "guard",
        "patrol"
    ],
    "wof:name":"Chopper Security services pty LTD",
    "wof:placetype":"venue"
},
  "geometry": {"coordinates":[150.926437378,-33.8701629639],"type":"Point"}
}