{
  "type": "Feature",
  "properties": {
    "addr:full":"Shp 10 Seymour Arcade Seymour St Traralgon VIC 3844",
    "addr:housenumber":"10",
    "addr:postcode":"3844",
    "addr:street":"Seymour Arcade Seymour St",
    "iso:country":"AU",
    "sg:address":"Shp 10 Seymour Arcade Seymour St",
    "sg:city":"Traralgon",
    "sg:classifiers":[
        {
            "category":"Personal",
            "subcategory":"Tattoo Parlor",
            "type":"Services"
        }
    ],
    "sg:phone":"+61 401 626 818",
    "sg:postcode":"3844",
    "sg:province":"VIC",
    "sg:tags":[
        "tattooing"
    ],
    "wof:name":"H.U.B Piercing",
    "wof:placetype":"venue"
},
  "geometry": {"coordinates":[146.53953552199999,-38.1961898804],"type":"Point"}
}