{
  "type": "Feature",
  "properties": {
    "addr:full":"7 Pascoe Pl Tarcoola Beach WA 6530",
    "addr:housenumber":"7",
    "addr:postcode":"6530",
    "addr:street":"Pascoe Pl",
    "iso:country":"AU",
    "sg:address":"7 Pascoe Pl",
    "sg:city":"Tarcoola Beach",
    "sg:classifiers":[
        {
            "category":"Retail",
            "subcategory":"Driving School",
            "type":"Services"
        }
    ],
    "sg:phone":"+61 408 951 080",
    "sg:postcode":"6530",
    "sg:province":"WA",
    "wof:name":"KBs Driving School",
    "wof:placetype":"venue"
},
  "geometry": {"coordinates":[114.625457764,-28.8140964508],"type":"Point"}
}