{
  "type": "Feature",
  "properties": {
    "iso:country":"AU",
    "sg:address":"Shp 5/ 209 Days Rd",
    "sg:city":"Grange",
    "sg:classifiers":[
        {
            "category":"Real Estate",
            "subcategory":"Architect",
            "type":"Services"
        }
    ],
    "sg:phone":"+61 7 3856 5135",
    "sg:postcode":"4051",
    "sg:province":"QLD",
    "wof:name":"MullArch",
    "wof:placetype":"venue"
},
  "geometry": {"coordinates":[153.01390075699999,-27.4257221222],"type":"Point"}
}