{
  "type": "Feature",
  "properties": {
    "iso:country":"AU",
    "sg:address":"60 Fisher St",
    "sg:city":"Kyabram",
    "sg:classifiers":[
        {
            "category":"Retail",
            "subcategory":"Driving School",
            "type":"Services"
        }
    ],
    "sg:phone":"+61 3 5852 2387",
    "sg:postcode":"3620",
    "sg:province":"VIC",
    "wof:name":"Kyabram Driving School",
    "wof:placetype":"venue"
},
  "geometry": {"coordinates":[145.05186462399999,-36.3181724548],"type":"Point"}
}