{
  "type": "Feature",
  "properties": {
    "iso:country":"AU",
    "sg:address":"Shp33/ 235 Bourke St",
    "sg:city":"Melbourne",
    "sg:classifiers":[
        {
            "category":"Professional",
            "subcategory":"Management & Consulting",
            "type":"Services"
        }
    ],
    "sg:phone":"+61 3 9663 4655",
    "sg:postcode":"3000",
    "sg:province":"VIC",
    "sg:tags":[
        "consultant",
        "educational"
    ],
    "wof:name":"Future Education & Migration Solutions Pty Ltd",
    "wof:placetype":"venue"
},
  "geometry": {"coordinates":[144.96647644000001,-37.8134002686],"type":"Point"}
}