{
  "type": "Feature",
  "properties": {
    "addr:full":"Unit 5/ 271 Selby St Churchlands WA 6018",
    "addr:housenumber":"/ 271",
    "addr:postcode":"6018",
    "addr:street":"Selby St",
    "iso:country":"AU",
    "sg:address":"Unit 5/ 271 Selby St",
    "sg:city":"Churchlands",
    "sg:classifiers":[
        {
            "category":"Food & Beverages",
            "subcategory":"Bakery",
            "type":"Retail Goods"
        }
    ],
    "sg:phone":"+61 8 9387 8300",
    "sg:postcode":"6018",
    "sg:province":"WA",
    "sg:tags":[
        "cake",
        "shop",
        "pastry"
    ],
    "wof:name":"The Gingerbread People",
    "wof:placetype":"venue"
},
  "geometry": {"coordinates":[115.80397796600001,-31.9318447113],"type":"Point"}
}