{
  "type": "Feature",
  "properties": {
    "addr:full":"5 Rivers St Bibra Lake WA 6163",
    "addr:housenumber":"5",
    "addr:postcode":"6163",
    "addr:street":"Rivers St",
    "iso:country":"AU",
    "sg:address":"5 Rivers St",
    "sg:city":"Bibra Lake",
    "sg:classifiers":[
        {
            "category":"Autos & Motor Vehicles",
            "subcategory":"Boat Sales",
            "type":"Retail Goods"
        }
    ],
    "sg:phone":"+61 8 9418 6461",
    "sg:postcode":"6163",
    "sg:province":"WA",
    "sg:tags":[
        "yacht"
    ],
    "wof:name":"Keywest Boats",
    "wof:placetype":"venue"
},
  "geometry": {"coordinates":[115.80265799999999,-32.112934],"type":"Point"}
}