{
  "type": "Feature",
  "properties": {
    "addr:full":"Shop 24 455 Hampton St Hampton VIC 3188",
    "addr:housenumber":"shop 24 455",
    "addr:postcode":"3188",
    "addr:street":"Hampton St",
    "iso:country":"AU",
    "sg:address":"Shop 24 455 Hampton St",
    "sg:city":"Hampton",
    "sg:classifiers":[
        {
            "category":"Shopping",
            "subcategory":"Discount & Variety Stores",
            "type":"Retail Goods"
        }
    ],
    "sg:phone":"+61 3 9598 8860",
    "sg:postcode":"3188",
    "sg:province":"VIC",
    "sg:tags":[
        "shop",
        "adult"
    ],
    "wof:name":"Qpids",
    "wof:placetype":"venue"
},
  "geometry": {"coordinates":[145.002975464,-37.9339447021],"type":"Point"}
}