{
  "type": "Feature",
  "properties": {
    "addr:full":"Shop 6/ 428 Prospect Rd Kilburn SA 5084",
    "addr:housenumber":"shop 6 / 428",
    "addr:postcode":"5084",
    "addr:street":"Prospect Rd",
    "iso:country":"AU",
    "sg:address":"Shop 6/ 428 Prospect Rd",
    "sg:city":"Kilburn",
    "sg:classifiers":[
        {
            "category":"Shopping",
            "subcategory":"Pets & Pet Supplies",
            "type":"Retail Goods"
        }
    ],
    "sg:phone":"+61 8 8349 7885",
    "sg:postcode":"5084",
    "sg:province":"SA",
    "sg:tags":[
        "food"
    ],
    "wof:name":"Pet Stop",
    "wof:placetype":"venue"
},
  "geometry": {"coordinates":[138.59205627399999,-34.8557014465],"type":"Point"}
}