{
  "type": "Feature",
  "properties": {
    "addr:full":"52 Chapple St Gladstone QLD 4680",
    "addr:housenumber":"52",
    "addr:postcode":"4680",
    "addr:street":"Chapple St",
    "iso:country":"AU",
    "sg:address":"52 Chapple St",
    "sg:city":"Gladstone",
    "sg:classifiers":[
        {
            "category":"Home & Garden",
            "subcategory":"Building Materials",
            "type":"Retail Goods"
        }
    ],
    "sg:phone":"+61 7 4972 9651",
    "sg:postcode":"4680",
    "sg:province":"QLD",
    "sg:tags":[
        "decorative",
        "coating"
    ],
    "wof:name":"Granosite",
    "wof:placetype":"venue"
},
  "geometry": {"coordinates":[151.24075317399999,-23.8424873352],"type":"Point"}
}