{
  "type": "Feature",
  "properties": {
    "addr:full":"278 Melbourne St North Adelaide SA 5006",
    "addr:housenumber":"278",
    "addr:postcode":"5006",
    "addr:street":"Melbourne St",
    "iso:country":"AU",
    "sg:address":"278 Melbourne St",
    "sg:city":"North Adelaide",
    "sg:classifiers":[
        {
            "category":"Banks & Credit Unions",
            "subcategory":"Financial Services",
            "type":"Services"
        }
    ],
    "sg:phone":"+61 8 8267 8100",
    "sg:postcode":"5006",
    "sg:province":"SA",
    "sg:tags":[
        "planning"
    ],
    "wof:name":"Kingsford Financial Group",
    "wof:placetype":"venue"
},
  "geometry": {"coordinates":[138.60189819300001,-34.9098358154],"type":"Point"}
}