{
  "type": "Feature",
  "properties": {
    "addr:full":"PO Box 384 Mannum SA 5238",
    "addr:postcode":"5238",
    "iso:country":"AU",
    "sg:address":"PO Box 384",
    "sg:city":"Mannum",
    "sg:classifiers":[
        {
            "category":"Travel",
            "subcategory":"Travel Agent",
            "type":"Entertainment"
        }
    ],
    "sg:phone":"+61 1800 236 569",
    "sg:postcode":"5238",
    "sg:province":"SA",
    "sg:tags":[
        "tour",
        "holiday",
        "adventure"
    ],
    "wof:name":"Breeze Houseboat Booking Centre",
    "wof:placetype":"venue"
},
  "geometry": {"coordinates":[139.28233337399999,-34.9041213989],"type":"Point"}
}