{
  "type": "Feature",
  "properties": {
    "iso:country":"AU",
    "sg:address":"1 Deacon Ave",
    "sg:city":"Richmond",
    "sg:classifiers":[
        {
            "category":"Home & Garden",
            "subcategory":"Carpets & Floor Coverings",
            "type":"Retail Goods"
        }
    ],
    "sg:phone":"+61 8 8152 0531",
    "sg:postcode":"5033",
    "sg:province":"SA",
    "sg:tags":[
        "tile",
        "wall"
    ],
    "wof:name":"Tile Wizards (Aust) Pty Ltd",
    "wof:placetype":"venue"
},
  "geometry": {"coordinates":[138.570404053,-34.9375114441],"type":"Point"}
}