{
  "type": "Feature",
  "properties": {
    "addr:full":"46 Binbrook Drv Croydon VIC 3136",
    "addr:housenumber":"46",
    "addr:postcode":"3136",
    "addr:street":"Binbrook Drv",
    "iso:country":"AU",
    "sg:address":"46 Binbrook Drv",
    "sg:city":"Croydon",
    "sg:classifiers":[
        {
            "category":"Insurance",
            "subcategory":"Insurance Agent",
            "type":"Services"
        }
    ],
    "sg:phone":"+61 3 9725 9142",
    "sg:postcode":"3136",
    "sg:province":"VIC",
    "sg:tags":[
        "broker"
    ],
    "wof:name":"Fraser & Associates Insurance Brokers Pty Ltd",
    "wof:placetype":"venue"
},
  "geometry": {"coordinates":[145.266723633,-37.7852401733],"type":"Point"}
}