{
  "type": "Feature",
  "properties": {
    "addr:full":"11 Galvin St Lawnton QLD 4501",
    "addr:housenumber":"11",
    "addr:postcode":"4501",
    "addr:street":"Galvin St",
    "iso:country":"AU",
    "sg:address":"11 Galvin St",
    "sg:city":"Lawnton",
    "sg:classifiers":[
        {
            "category":"Personal",
            "subcategory":"Massage",
            "type":"Services"
        }
    ],
    "sg:phone":"+61 7 3285 4354",
    "sg:postcode":"4501",
    "sg:province":"QLD",
    "sg:tags":[
        "therapy"
    ],
    "wof:name":"Martins Natural Therapies",
    "wof:placetype":"venue"
},
  "geometry": {"coordinates":[152.97854614299999,-27.2832622528],"type":"Point"}
}