{
  "type": "Feature",
  "properties": {
    "addr:full":"44 William St Raymond Terrace NSW 2324",
    "addr:housenumber":"44",
    "addr:postcode":"2324",
    "addr:street":"William St",
    "iso:country":"AU",
    "sg:address":"44 William St",
    "sg:city":"Raymond Terrace",
    "sg:classifiers":[
        {
            "category":"Health Services",
            "subcategory":"Medical Lab",
            "type":"Services"
        }
    ],
    "sg:phone":"+61 2 4983 1302",
    "sg:postcode":"2324",
    "sg:province":"NSW",
    "sg:tags":[
        "laboratory",
        "pathology"
    ],
    "wof:name":"Hampson Pathology",
    "wof:placetype":"venue"
},
  "geometry": {"coordinates":[151.74429321299999,-32.7632789612],"type":"Point"}
}