{
  "type": "Feature",
  "properties": {
    "addr:full":"63 Kembla St Wollongong NSW 2500",
    "addr:housenumber":"63",
    "addr:postcode":"2500",
    "addr:street":"Kembla St",
    "iso:country":"AU",
    "sg:address":"63 Kembla St",
    "sg:city":"Wollongong",
    "sg:classifiers":[
        {
            "category":"Food & Beverages",
            "subcategory":"Fruits & Vegetables",
            "type":"Retail Goods"
        }
    ],
    "sg:phone":"+61 2 4228 1800",
    "sg:postcode":"2500",
    "sg:province":"NSW",
    "sg:tags":[
        "consultant",
        "catering"
    ],
    "wof:name":"Culinarius By Monika",
    "wof:placetype":"venue"
},
  "geometry": {"coordinates":[150.897705,-34.424862],"type":"Point"}
}