{
  "type": "Feature",
  "properties": {
    "iso:country":"AU",
    "sg:address":"Suite 2, 1 Jacobs St",
    "sg:city":"Bankstown",
    "sg:classifiers":[
        {
            "category":"Professional",
            "subcategory":"Accounting & Tax Preparation",
            "type":"Services"
        }
    ],
    "sg:phone":"+61 2 9708 5522",
    "sg:postcode":"2200",
    "sg:province":"NSW",
    "sg:tags":[
        "accountant",
        "auditor"
    ],
    "wof:name":"Davies Keith G & Associates",
    "wof:placetype":"venue"
},
  "geometry": {"coordinates":[151.036957,-33.915752],"type":"Point"}
}