{
  "type": "Feature",
  "properties": {
    "addr:full":"Shop 12 Balo Sq Moree NSW 2400",
    "addr:housenumber":"shop 12",
    "addr:postcode":"2400",
    "addr:street":"Balo Sq",
    "iso:country":"AU",
    "sg:address":"Shop 12 Balo Sq",
    "sg:city":"Moree",
    "sg:classifiers":[
        {
            "category":"Shopping",
            "subcategory":"Clothing, Apparel, & Fashions",
            "type":"Retail Goods"
        }
    ],
    "sg:phone":"+61 2 6752 3724",
    "sg:postcode":"2400",
    "sg:province":"NSW",
    "sg:tags":[
        "lady",
        "wear"
    ],
    "wof:name":"Suzanne Grae",
    "wof:placetype":"venue"
},
  "geometry": {"coordinates":[149.84175109899999,-29.4633140564],"type":"Point"}
}