{
  "type": "Feature",
  "properties": {
    "addr:full":"8 Alice St Bassendean WA 6054",
    "addr:housenumber":"8",
    "addr:postcode":"6054",
    "addr:street":"Alice St",
    "iso:country":"AU",
    "sg:address":"8 Alice St",
    "sg:city":"Bassendean",
    "sg:classifiers":[
        {
            "category":"Retail",
            "subcategory":"Storage",
            "type":"Services"
        }
    ],
    "sg:phone":"+61 8 9347 8800",
    "sg:postcode":"6054",
    "sg:province":"WA",
    "wof:name":"Summit Storage Products",
    "wof:placetype":"venue"
},
  "geometry": {"coordinates":[115.93132018999999,-31.9077377319],"type":"Point"}
}