{
  "type": "Feature",
  "properties": {
    "addr:full":"16 Telford St Toowoomba QLD 4350",
    "addr:housenumber":"16",
    "addr:postcode":"4350",
    "addr:street":"Telford St",
    "iso:country":"AU",
    "sg:address":"16 Telford St",
    "sg:city":"Toowoomba",
    "sg:phone":"+61 7 4632 3935",
    "sg:postcode":"4350",
    "sg:province":"QLD",
    "wof:name":"Willy Bros Pty Ltd",
    "wof:placetype":"venue"
},
  "geometry": {"coordinates":[151.95031700000001,-27.567024],"type":"Point"}
}