{
  "type": "Feature",
  "properties": {
    "addr:full":"14 Mclaren Pl Buderim QLD 4556",
    "addr:housenumber":"14",
    "addr:postcode":"4556",
    "addr:street":"Mclaren Pl",
    "iso:country":"AU",
    "sg:address":"14 Mclaren Pl",
    "sg:city":"Buderim",
    "sg:classifiers":[
        {
            "category":"Personal",
            "subcategory":"Beauty Salon",
            "type":"Services"
        }
    ],
    "sg:phone":"+61 438 663 302",
    "sg:postcode":"4556",
    "sg:province":"QLD",
    "wof:name":"A Touch Of Paris",
    "wof:placetype":"venue"
},
  "geometry": {"coordinates":[153.07725524899999,-26.6939983368],"type":"Point"}
}