{
  "type": "Feature",
  "properties": {
    "addr:full":"Hanger 752 Camden Airport Camden NSW 2570",
    "addr:housenumber":"752",
    "addr:postcode":"2570",
    "addr:street":"Hanger;Camden Airport",
    "iso:country":"AU",
    "sg:address":"Hanger 752 Camden Airport",
    "sg:city":"Camden",
    "sg:classifiers":[
        {
            "category":"Professional",
            "subcategory":"Detective & Security Services",
            "type":"Services"
        }
    ],
    "sg:phone":"+61 2 4655 5250",
    "sg:postcode":"2570",
    "sg:province":"NSW",
    "sg:tags":[
        "distributor",
        "aircraft",
        "mfrs"
    ],
    "wof:name":"Red Star Aviation",
    "wof:placetype":"venue"
},
  "geometry": {"coordinates":[150.73912048299999,-34.0504798889],"type":"Point"}
}