{
  "type": "Feature",
  "properties": {
    "addr:full":"Lvl 10/ 60 Waymouth St Adelaide SA 5000",
    "addr:housenumber":"/ 60",
    "addr:postcode":"5000",
    "addr:street":"Waymouth St",
    "iso:country":"AU",
    "sg:address":"Lvl 10/ 60 Waymouth St",
    "sg:city":"Adelaide",
    "sg:classifiers":[
        {
            "category":"Wholesale",
            "subcategory":"Home Furnishings",
            "type":"Manufacturing & Wholesale Goods"
        }
    ],
    "sg:phone":"+61 1300 304 353",
    "sg:postcode":"5000",
    "sg:province":"SA",
    "sg:tags":[
        "tile",
        "wholesaler",
        "mfrs",
        "carpet"
    ],
    "wof:name":"Interface Aust Pty Limited",
    "wof:placetype":"venue"
},
  "geometry": {"coordinates":[138.59901428200001,-34.9259376526],"type":"Point"}
}