{
  "type": "Feature",
  "properties": {
    "iso:country":"AU",
    "sg:address":"1312 Pittwater Rd",
    "sg:city":"Narrabeen",
    "sg:classifiers":[
        {
            "category":"Health Services",
            "subcategory":"Dentist",
            "type":"Services"
        }
    ],
    "sg:phone":"+61 2 9913 1466",
    "sg:postcode":"2101",
    "sg:province":"NSW",
    "wof:name":"Narrabeen Dental Care",
    "wof:placetype":"venue"
},
  "geometry": {"coordinates":[151.29718,-33.715321],"type":"Point"}
}