{
  "type": "Feature",
  "properties": {
    "addr:full":"University General Practice 64 Wirraway Pde Inala QLD 4077",
    "addr:housenumber":"64",
    "addr:postcode":"4077",
    "addr:street":"Wirraway Pde",
    "iso:country":"AU",
    "sg:address":"University General Practice 64 Wirraway Pde",
    "sg:city":"Inala",
    "sg:classifiers":[
        {
            "category":"Health Services",
            "subcategory":"Doctor",
            "type":"Services"
        }
    ],
    "sg:phone":"+61 7 3275 5444",
    "sg:postcode":"4077",
    "sg:province":"QLD",
    "sg:tags":[
        "medical",
        "practitioner"
    ],
    "wof:name":"Smith Jane",
    "wof:placetype":"venue"
},
  "geometry": {"coordinates":[152.971923828,-27.6006374359],"type":"Point"}
}