{
  "type": "Feature",
  "properties": {
    "iso:country":"AU",
    "sg:address":"54 Kathleen St",
    "sg:city":"Trigg",
    "sg:classifiers":[
        {
            "category":"Professional",
            "subcategory":"Detective & Security Services",
            "type":"Services"
        }
    ],
    "sg:phone":"+61 8 9203 7214",
    "sg:postcode":"6029",
    "sg:province":"WA",
    "sg:tags":[
        "consultant",
        "system"
    ],
    "wof:name":"Vulnerability Assessment Group",
    "wof:placetype":"venue"
},
  "geometry": {"coordinates":[115.758239746,-31.8770694733],"type":"Point"}
}