{
  "type": "Feature",
  "properties": {
    "iso:country":"AU",
    "sg:address":"113 Raglan St",
    "sg:city":"Sale",
    "sg:classifiers":[
        {
            "category":"Personal",
            "subcategory":"Beauty Salon",
            "type":"Services"
        }
    ],
    "sg:phone":"+61 3 5144 5903",
    "sg:postcode":"3850",
    "sg:province":"VIC",
    "sg:tags":[
        "hairdresser"
    ],
    "wof:name":"Topp Notch Hair Design",
    "wof:placetype":"venue"
},
  "geometry": {"coordinates":[147.071365356,-38.0985832214],"type":"Point"}
}