{
  "type": "Feature",
  "properties": {
    "addr:full":"9 Foamcrest Ave Newport Beach NSW 2106",
    "addr:housenumber":"9",
    "addr:postcode":"2106",
    "addr:street":"Foamcrest Ave",
    "iso:country":"AU",
    "sg:address":"9 Foamcrest Ave",
    "sg:city":"Newport Beach",
    "sg:classifiers":[
        {
            "category":"Professional",
            "subcategory":"Accounting & Tax Preparation",
            "type":"Services"
        }
    ],
    "sg:phone":"+61 2 9997 6360",
    "sg:postcode":"2106",
    "sg:province":"NSW",
    "sg:tags":[
        "consultant",
        "taxation"
    ],
    "wof:name":"Wiseman J",
    "wof:placetype":"venue"
},
  "geometry": {"coordinates":[151.318527222,-33.6553268433],"type":"Point"}
}