{
  "type": "Feature",
  "properties": {
    "iso:country":"AU",
    "sg:address":"12 James Crt",
    "sg:city":"Diamond Creek",
    "sg:classifiers":[
        {
            "category":"Real Estate",
            "subcategory":"Surveying",
            "type":"Services"
        }
    ],
    "sg:phone":"+61 3 9432 2733",
    "sg:postcode":"3089",
    "sg:province":"VIC",
    "sg:tags":[
        "acoustic",
        "material"
    ],
    "wof:name":"Shamrock Consulting Pty Ltd",
    "wof:placetype":"venue"
},
  "geometry": {"coordinates":[145.127029,-37.679276],"type":"Point"}
}