{
  "type": "Feature",
  "properties": {
    "addr:full":"12 James Crt Diamond Creek VIC 3089",
    "addr:housenumber":"12",
    "addr:postcode":"3089",
    "addr:street":"James Crt",
    "iso:country":"AU",
    "sg:address":"12 James Crt",
    "sg:city":"Diamond Creek",
    "sg:classifiers":[
        {
            "category":"Real Estate",
            "subcategory":"Surveying",
            "type":"Services"
        }
    ],
    "sg:phone":"+61 3 9432 2733",
    "sg:postcode":"3089",
    "sg:province":"VIC",
    "sg:tags":[
        "acoustic",
        "material"
    ],
    "wof:name":"Shamrock Consulting Pty Ltd",
    "wof:placetype":"venue"
},
  "geometry": {"coordinates":[145.12702899999999,-37.679276],"type":"Point"}
}