{
  "type": "Feature",
  "properties": {
    "addr:full":"21 Bates St Merredin WA 6415",
    "addr:housenumber":"21",
    "addr:postcode":"6415",
    "addr:street":"Bates St",
    "iso:country":"AU",
    "sg:address":"21 Bates St",
    "sg:city":"Merredin",
    "sg:classifiers":[
        {
            "category":"Professional",
            "subcategory":"Employment Agencies",
            "type":"Services"
        }
    ],
    "sg:phone":"+61 1300 884 283",
    "sg:postcode":"6415",
    "sg:province":"WA",
    "sg:tags":[
        "provider",
        "internet"
    ],
    "wof:name":"Timegate Systems",
    "wof:placetype":"venue"
},
  "geometry": {"coordinates":[118.278800964,-31.4809608459],"type":"Point"}
}