{
  "type": "Feature",
  "properties": {
    "iso:country":"AU",
    "sg:address":"Pagan Rd",
    "sg:city":"Stanmore",
    "sg:classifiers":[
        {
            "category":"Building & Trades",
            "subcategory":"Plumbing",
            "type":"Services"
        }
    ],
    "sg:phone":"+61 7 3287 2695",
    "sg:postcode":"4514",
    "sg:province":"QLD",
    "sg:tags":[
        "plumber",
        "gasfitters"
    ],
    "wof:name":"Watt G D",
    "wof:placetype":"venue"
},
  "geometry": {"coordinates":[152.77720600000001,-26.90469],"type":"Point"}
}