{
  "type": "Feature",
  "properties": {
    "iso:country":"AU",
    "sg:address":"374 Murray St",
    "sg:city":"Colac",
    "sg:classifiers":[
        {
            "category":"Manufacturing",
            "subcategory":"Motor Vehicles & Parts",
            "type":"Manufacturing & Wholesale Goods"
        }
    ],
    "sg:phone":"+61 3 5231 4273",
    "sg:postcode":"3250",
    "sg:province":"VIC",
    "sg:tags":[
        "wholesaler",
        "cycle",
        "mfrs",
        "accessory"
    ],
    "wof:name":"Rye Graham Kawasaki",
    "wof:placetype":"venue"
},
  "geometry": {"coordinates":[143.58689899999999,-38.339806],"type":"Point"}
}