{
  "type": "Feature",
  "properties": {
    "iso:country":"AU",
    "sg:address":"PO Box 4282",
    "sg:city":"Gosford East",
    "sg:classifiers":[
        {
            "category":"Building & Trades",
            "subcategory":"Cleaning & Sanitation",
            "type":"Services"
        }
    ],
    "sg:phone":"+61 2 4324 4246",
    "sg:postcode":"2250",
    "sg:province":"NSW",
    "sg:tags":[
        "chemical",
        "pressure",
        "steam",
        "contractor"
    ],
    "wof:name":"Country Classic",
    "wof:placetype":"venue"
},
  "geometry": {"coordinates":[151.32798767099999,-33.4495162964],"type":"Point"}
}