{
  "type": "Feature",
  "properties": {
    "addr:full":"12 Mungarra Ave St Ives NSW 2075",
    "addr:housenumber":"12",
    "addr:postcode":"2075",
    "addr:street":"Mungarra Ave",
    "iso:country":"AU",
    "sg:address":"12 Mungarra Ave St",
    "sg:city":"Ives",
    "sg:classifiers":[
        {
            "category":"Social Services",
            "subcategory":"Child Care",
            "type":"Services"
        }
    ],
    "sg:phone":"+61 2 9449 9133",
    "sg:postcode":"2075",
    "sg:province":"NSW",
    "wof:name":"Rainbow Cottage Long Day Care Centre",
    "wof:placetype":"venue"
},
  "geometry": {"coordinates":[151.15443420400001,-33.7244682312],"type":"Point"}
}