{
  "type": "Feature",
  "properties": {
    "addr:full":"199 Gray St Hamilton VIC 3300",
    "addr:housenumber":"199",
    "addr:postcode":"3300",
    "addr:street":"Gray St",
    "iso:country":"AU",
    "sg:address":"199 Gray St",
    "sg:city":"Hamilton",
    "sg:classifiers":[
        {
            "category":"Home & Garden",
            "subcategory":"Carpets & Floor Coverings",
            "type":"Retail Goods"
        }
    ],
    "sg:phone":"+61 3 5572 3619",
    "sg:postcode":"3300",
    "sg:province":"VIC",
    "sg:tags":[
        "tile",
        "wall"
    ],
    "wof:name":"Zenith Tiles & Lighting",
    "wof:placetype":"venue"
},
  "geometry": {"coordinates":[142.02537536599999,-37.7425079346],"type":"Point"}
}