{
  "type": "Feature",
  "properties": {
    "iso:country":"AU",
    "sg:address":"6 Firetail Pl",
    "sg:city":"Glenview",
    "sg:classifiers":[
        {
            "category":"Wholesale",
            "subcategory":"Seafood",
            "type":"Manufacturing & Wholesale Goods"
        }
    ],
    "sg:phone":"+61 7 5439 6333",
    "sg:postcode":"4553",
    "sg:province":"QLD",
    "sg:tags":[
        "fish"
    ],
    "wof:name":"B & T Trading",
    "wof:placetype":"venue"
},
  "geometry": {"coordinates":[153.01919599999999,-26.76186],"type":"Point"}
}