{
  "type": "Feature",
  "properties": {
    "iso:country":"AU",
    "sg:address":"96 Frederick St",
    "sg:city":"Welland",
    "sg:classifiers":[
        {
            "category":"Freight",
            "type":"Transportation"
        }
    ],
    "sg:phone":"+61 8 8346 9577",
    "sg:postcode":"5007",
    "sg:province":"SA",
    "sg:tags":[
        "light",
        "carrier"
    ],
    "wof:name":"Black & White Trucks",
    "wof:placetype":"venue"
},
  "geometry": {"coordinates":[138.557693481,-34.9053421021],"type":"Point"}
}