{
  "type": "Feature",
  "properties": {
    "addr:full":"1 Adelaide Rd Mallala SA 5502",
    "addr:housenumber":"1",
    "addr:postcode":"5502",
    "addr:street":"Adelaide Rd",
    "iso:country":"AU",
    "sg:address":"1 Adelaide Rd",
    "sg:city":"Mallala",
    "sg:classifiers":[
        {
            "category":"Travel",
            "subcategory":"Hotels & Motels",
            "type":"Entertainment"
        }
    ],
    "sg:phone":"+61 8 8527 2249",
    "sg:postcode":"5502",
    "sg:province":"SA",
    "sg:tags":[
        "accommodation"
    ],
    "wof:name":"Mallala Hotel",
    "wof:placetype":"venue"
},
  "geometry": {"coordinates":[138.51002500000001,-34.438278],"type":"Point"}
}