{
  "type": "Feature",
  "properties": {
    "addr:full":"Lot 2 8 Maurice Rd Murray Bridge SA 5253",
    "addr:housenumber":"8",
    "addr:postcode":"5253",
    "addr:street":"Maurice Rd",
    "iso:country":"AU",
    "sg:address":"Lot 2 8 Maurice Rd",
    "sg:city":"Murray Bridge",
    "sg:classifiers":[
        {
            "category":"Home & Garden",
            "subcategory":"Carpets & Floor Coverings",
            "type":"Retail Goods"
        }
    ],
    "sg:phone":"+61 407 712 592",
    "sg:postcode":"5253",
    "sg:province":"SA",
    "sg:tags":[
        "flooring",
        "parquet"
    ],
    "wof:name":"Floor Restore",
    "wof:placetype":"venue"
},
  "geometry": {"coordinates":[139.260055542,-35.1294174194],"type":"Point"}
}