{
  "type": "Feature",
  "properties": {
    "addr:full":"37 Brisbane St Mackay QLD 4740",
    "addr:housenumber":"37",
    "addr:postcode":"4740",
    "addr:street":"Brisbane St",
    "iso:country":"AU",
    "sg:address":"37 Brisbane St",
    "sg:city":"Mackay",
    "sg:classifiers":[
        {
            "category":"Train Station",
            "subcategory":"Light Rail",
            "type":"Transportation"
        }
    ],
    "sg:phone":"+61 7 4957 8166",
    "sg:postcode":"4740",
    "sg:province":"QLD",
    "sg:tags":[
        "equipment",
        "energy",
        "solar"
    ],
    "wof:name":"AJK Air Conditioning",
    "wof:placetype":"venue"
},
  "geometry": {"coordinates":[149.18806499999999,-21.14456],"type":"Point"}
}