{
  "type": "Feature",
  "properties": {
    "addr:full":"Dunreath Rd Strathalbyn SA 5255",
    "addr:postcode":"5255",
    "addr:street":"Dunreath Rd",
    "iso:country":"AU",
    "sg:address":"Dunreath Rd",
    "sg:city":"Strathalbyn",
    "sg:classifiers":[
        {
            "category":"Farming",
            "subcategory":"Livestock Farm",
            "type":"Manufacturing & Wholesale Goods"
        }
    ],
    "sg:phone":"+61 8 8536 2013",
    "sg:postcode":"5255",
    "sg:province":"SA",
    "sg:tags":[
        "breeder",
        "horse",
        "stud"
    ],
    "wof:name":"Khesan Quarter Horse & Appaloosa Stud",
    "wof:placetype":"venue"
},
  "geometry": {"coordinates":[138.893844605,-35.269618988],"type":"Point"}
}