{
  "type": "Feature",
  "properties": {
    "addr:full":"Shed 2, 461 Burton Rd Burton SA 5110",
    "addr:housenumber":"2 461",
    "addr:postcode":"5110",
    "addr:street":"Burton Rd",
    "iso:country":"AU",
    "sg:address":"Shed 2, 461 Burton Rd",
    "sg:city":"Burton",
    "sg:classifiers":[
        {
            "category":"Manufacturing",
            "subcategory":"Tools & Machinery",
            "type":"Manufacturing & Wholesale Goods"
        }
    ],
    "sg:phone":"+61 417 881 129",
    "sg:postcode":"5110",
    "sg:province":"SA",
    "sg:tags":[
        "manufactured",
        "specially",
        "designed"
    ],
    "wof:name":"Trymoss Engineering",
    "wof:placetype":"venue"
},
  "geometry": {"coordinates":[138.58692932100001,-34.7421607971],"type":"Point"}
}