{
  "type": "Feature",
  "properties": {
    "addr:full":"Cnr Gaffney & Mc Donald Sts Coburg VIC 3058",
    "addr:postcode":"3058",
    "addr:street":"Cnr",
    "iso:country":"AU",
    "sg:address":"Cnr Gaffney & Mc Donald Sts",
    "sg:city":"Coburg",
    "sg:classifiers":[
        {
            "category":"Manufacturing",
            "subcategory":"Tools & Machinery",
            "type":"Manufacturing & Wholesale Goods"
        }
    ],
    "sg:phone":"+61 3 9354 3255",
    "sg:postcode":"3058",
    "sg:province":"VIC",
    "sg:tags":[
        "wholesaler",
        "mfrs",
        "hosiery"
    ],
    "wof:name":"Pantex Australia Pty Ltd",
    "wof:placetype":"venue"
},
  "geometry": {"coordinates":[144.964767456,-37.7338523865],"type":"Point"}
}