{
  "type": "Feature",
  "properties": {
    "addr:full":"311 Brunswick St Fitzroy VIC 3065",
    "addr:housenumber":"311",
    "addr:postcode":"3065",
    "addr:street":"Brunswick St",
    "iso:country":"AU",
    "sg:address":"311 Brunswick St",
    "sg:city":"Fitzroy",
    "sg:classifiers":[
        {
            "category":"Fast Food",
            "type":"Food & Drink"
        }
    ],
    "sg:phone":"+61 3 9415 1217",
    "sg:postcode":"3065",
    "sg:province":"VIC",
    "sg:tags":[
        "away",
        "take"
    ],
    "wof:name":"Souvlaki King",
    "wof:placetype":"venue"
},
  "geometry": {"coordinates":[144.97836303700001,-37.7978668213],"type":"Point"}
}