{
  "type": "Feature",
  "properties": {
    "addr:full":"77 Fretwell Rd White Rock QLD 4868",
    "addr:housenumber":"77",
    "addr:postcode":"4868",
    "addr:street":"Fretwell Rd",
    "iso:country":"AU",
    "sg:address":"77 Fretwell Rd",
    "sg:city":"White Rock",
    "sg:classifiers":[
        {
            "category":"Utilities",
            "type":"Services"
        }
    ],
    "sg:phone":"+61 7 4036 1144",
    "sg:postcode":"4868",
    "sg:province":"QLD",
    "sg:tags":[
        "refrigeration",
        "industrial",
        "commercial",
        "retail"
    ],
    "wof:name":"Grays Refrigeration & Electrical Service Pty Ltd",
    "wof:placetype":"venue"
},
  "geometry": {"coordinates":[145.750076294,-16.9940490723],"type":"Point"}
}