{
  "type": "Feature",
  "properties": {
    "addr:full":"36 Park Ave Helensburgh NSW 2508",
    "addr:housenumber":"36",
    "addr:postcode":"2508",
    "addr:street":"Park Ave",
    "iso:country":"AU",
    "sg:address":"36 Park Ave",
    "sg:city":"Helensburgh",
    "sg:classifiers":[
        {
            "category":"Building & Trades",
            "subcategory":"Construction",
            "type":"Services"
        }
    ],
    "sg:phone":"+61 419 429 395",
    "sg:postcode":"2508",
    "sg:province":"NSW",
    "sg:tags":[
        "contractor"
    ],
    "wof:name":"A Overell Finish Building Services",
    "wof:placetype":"venue"
},
  "geometry": {"coordinates":[150.97813400000001,-34.18914],"type":"Point"}
}