{
  "type": "Feature",
  "properties": {
    "addr:full":"8 Callister St Shepparton VIC 3630",
    "addr:housenumber":"8",
    "addr:postcode":"3630",
    "addr:street":"Callister St",
    "iso:country":"AU",
    "sg:address":"8 Callister St",
    "sg:city":"Shepparton",
    "sg:classifiers":[
        {
            "category":"Government",
            "subcategory":"Police Station",
            "type":"Public Place"
        }
    ],
    "sg:phone":"+61 3 5822 2749",
    "sg:postcode":"3630",
    "sg:province":"VIC",
    "sg:tags":[
        "steering",
        "power"
    ],
    "wof:name":"Straight Drive Power Steering & Suspension",
    "wof:placetype":"venue"
},
  "geometry": {"coordinates":[145.41485595699999,-36.3847045898],"type":"Point"}
}