{
  "type": "Feature",
  "properties": {
    "addr:full":"Sturt Hwy Renmark SA 5341",
    "addr:postcode":"5341",
    "addr:street":"Sturt Hwy",
    "iso:country":"AU",
    "sg:address":"Sturt Hwy",
    "sg:city":"Renmark",
    "sg:classifiers":[
        {
            "category":"Park",
            "subcategory":"County",
            "type":"Public Place"
        }
    ],
    "sg:phone":"+61 8 8595 1431",
    "sg:postcode":"5341",
    "sg:province":"SA",
    "sg:tags":[
        "sanctuary",
        "zoos",
        "animal"
    ],
    "wof:name":"Bredl's Wonderworld Of Wildlife",
    "wof:placetype":"venue"
},
  "geometry": {"coordinates":[140.744506836,-34.1759490967],"type":"Point"}
}