{
  "type": "Feature",
  "properties": {
    "addr:full":"156 Victoria St Kings Cross NSW 2011",
    "addr:housenumber":"156",
    "addr:postcode":"2011",
    "addr:street":"Victoria St",
    "iso:country":"AU",
    "sg:address":"156 Victoria St",
    "sg:city":"Kings Cross",
    "sg:classifiers":[
        {
            "category":"Travel",
            "subcategory":"Hostel",
            "type":"Entertainment"
        }
    ],
    "sg:phone":"+61 2 9358 4606",
    "sg:postcode":"2011",
    "sg:province":"NSW",
    "sg:tags":[
        "home"
    ],
    "wof:name":"Travellers Rest Backpackers Hostel",
    "wof:placetype":"venue"
},
  "geometry": {"coordinates":[151.222488403,-33.8741760254],"type":"Point"}
}