{
  "type": "Feature",
  "properties": {
    "iso:country":"AU",
    "sg:address":"89 Travers Dr",
    "sg:city":"Australind",
    "sg:classifiers":[
        {
            "category":"Professional",
            "subcategory":"Business Services",
            "type":"Services"
        }
    ],
    "sg:phone":"+61 8 9725 8873",
    "sg:postcode":"6233",
    "sg:province":"WA",
    "sg:tags":[
        "drafting"
    ],
    "wof:name":"Westdale Manor Pty Ltd",
    "wof:placetype":"venue"
},
  "geometry": {"coordinates":[115.72126799999999,-33.269718],"type":"Point"}
}