{
  "type": "Feature",
  "properties": {
    "iso:country":"AU",
    "sg:address":"39 Union Rd",
    "sg:city":"Dandenong South",
    "sg:classifiers":[
        {
            "category":"Manufacturing",
            "subcategory":"Metals",
            "type":"Manufacturing & Wholesale Goods"
        }
    ],
    "sg:phone":"+61 3 9706 9899",
    "sg:postcode":"3175",
    "sg:province":"VIC",
    "sg:tags":[
        "steel",
        "fabricator",
        "mfrs"
    ],
    "wof:name":"Elite Steel Pty Ltd",
    "wof:placetype":"venue"
},
  "geometry": {"coordinates":[145.199127197,-38.0071372986],"type":"Point"}
}