{
  "type": "Feature",
  "properties": {
    "addr:full":"111 Camden Rd Douglas Park NSW 2569",
    "addr:housenumber":"111",
    "addr:postcode":"2569",
    "addr:street":"Camden Rd",
    "iso:country":"AU",
    "sg:address":"111 Camden Rd",
    "sg:city":"Douglas Park",
    "sg:classifiers":[
        {
            "category":"Education",
            "subcategory":"School",
            "type":"Public Place"
        }
    ],
    "sg:phone":"+61 2 4632 7261",
    "sg:postcode":"2569",
    "sg:province":"NSW",
    "sg:tags":[
        "state",
        "-",
        "nsw"
    ],
    "wof:name":"Douglas Park Public School",
    "wof:placetype":"venue"
},
  "geometry": {"coordinates":[150.712524414,-34.1790733337],"type":"Point"}
}