{
  "type": "Feature",
  "properties": {
    "addr:full":"18 Stuart St Dernancourt SA 5075",
    "addr:housenumber":"18",
    "addr:postcode":"5075",
    "addr:street":"Stuart St",
    "iso:country":"AU",
    "sg:address":"18 Stuart St",
    "sg:city":"Dernancourt",
    "sg:classifiers":[
        {
            "category":"Professional",
            "subcategory":"Art Services",
            "type":"Services"
        }
    ],
    "sg:phone":"+61 8 8261 0966",
    "sg:postcode":"5075",
    "sg:province":"SA",
    "sg:tags":[
        "decorator",
        "painter"
    ],
    "wof:name":"J & J Painting & Decorating Services",
    "wof:placetype":"venue"
},
  "geometry": {"coordinates":[138.67098999000001,-34.8623924255],"type":"Point"}
}