{
  "type": "Feature",
  "properties": {
    "addr:full":"15 Garden St Greenslopes QLD 4120",
    "addr:housenumber":"15",
    "addr:postcode":"4120",
    "addr:street":"Garden St",
    "iso:country":"AU",
    "sg:address":"15 Garden St",
    "sg:city":"Greenslopes",
    "sg:classifiers":[
        {
            "category":"Manufacturing",
            "subcategory":"Glass & Minerals",
            "type":"Manufacturing & Wholesale Goods"
        }
    ],
    "sg:phone":"+61 7 3342 0725",
    "sg:postcode":"4120",
    "sg:province":"QLD",
    "sg:tags":[
        "exploration"
    ],
    "wof:name":"Solid Geology Pty Ltd",
    "wof:placetype":"venue"
},
  "geometry": {"coordinates":[153.042572022,-27.5098438263],"type":"Point"}
}