{
  "type": "Feature",
  "properties": {
    "addr:full":"228- 230 Macquarie Rd Springwood NSW 2777",
    "addr:housenumber":"230",
    "addr:postcode":"2777",
    "addr:street":"Macquarie Rd",
    "iso:country":"AU",
    "sg:address":"228- 230 Macquarie Rd",
    "sg:city":"Springwood",
    "sg:classifiers":[
        {
            "category":"Personal",
            "subcategory":"Beauty Salon",
            "type":"Services"
        }
    ],
    "sg:phone":"+61 2 4751 3759",
    "sg:postcode":"2777",
    "sg:province":"NSW",
    "sg:tags":[
        "hairdresser"
    ],
    "wof:name":"Hakuna Matatas",
    "wof:placetype":"venue"
},
  "geometry": {"coordinates":[150.56407165499999,-33.6991348267],"type":"Point"}
}