{
  "type": "Feature",
  "properties": {
    "addr:full":"1 Boyd St Tweed Heads NSW 2485",
    "addr:housenumber":"1",
    "addr:postcode":"2485",
    "addr:street":"Boyd St",
    "iso:country":"AU",
    "sg:address":"1 Boyd St",
    "sg:city":"Tweed Heads",
    "sg:classifiers":[
        {
            "category":"Personal",
            "subcategory":"Massage",
            "type":"Services"
        }
    ],
    "sg:phone":"+61 7 5599 2514",
    "sg:postcode":"2485",
    "sg:province":"NSW",
    "sg:tags":[
        "therapy"
    ],
    "sg:website":"http://www.beyondmassage.com.au",
    "wof:name":"Therapies On Boyd",
    "wof:placetype":"venue"
},
  "geometry": {"coordinates":[153.53973388700001,-28.1775550842],"type":"Point"}
}