{
  "type": "Feature",
  "properties": {
    "iso:country":"AU",
    "sg:address":"Unit 2/ 164 Princes Hwy",
    "sg:city":"Nowra South",
    "sg:classifiers":[
        {
            "category":"Home & Garden",
            "subcategory":"Building Materials",
            "type":"Retail Goods"
        }
    ],
    "sg:phone":"+61 2 4443 7993",
    "sg:postcode":"2541",
    "sg:province":"NSW",
    "sg:tags":[
        "balustrading"
    ],
    "wof:name":"Unique Balustrading & Handrails",
    "wof:placetype":"venue"
},
  "geometry": {"coordinates":[150.603683472,-34.9138641357],"type":"Point"}
}