{
  "type": "Feature",
  "properties": {
    "addr:full":"19 Gerrale St Cronulla NSW 2230",
    "addr:housenumber":"19",
    "addr:postcode":"2230",
    "addr:street":"Gerrale St",
    "iso:country":"AU",
    "sg:address":"19 Gerrale St",
    "sg:city":"Cronulla",
    "sg:classifiers":[
        {
            "category":"Health Services",
            "subcategory":"Doctor",
            "type":"Services"
        }
    ],
    "sg:phone":"+61 2 9527 1366",
    "sg:postcode":"2230",
    "sg:province":"NSW",
    "sg:tags":[
        "medical",
        "practitioner"
    ],
    "wof:name":"Biggs Daniel",
    "wof:placetype":"venue"
},
  "geometry": {"coordinates":[151.15365600600001,-34.0541305542],"type":"Point"}
}