{
  "type": "Feature",
  "properties": {
    "iso:country":"AU",
    "sg:address":"17 Albert St",
    "sg:city":"Edgecliff",
    "sg:classifiers":[
        {
            "category":"Health Services",
            "subcategory":"Doctor",
            "type":"Services"
        }
    ],
    "sg:phone":"+61 2 9328 7417",
    "sg:postcode":"2027",
    "sg:province":"NSW",
    "sg:tags":[
        "medical",
        "practitioner"
    ],
    "wof:name":"Philips J",
    "wof:placetype":"venue"
},
  "geometry": {"coordinates":[151.23915100100001,-33.881072998],"type":"Point"}
}