{
  "type": "Feature",
  "properties": {
    "iso:country":"AU",
    "sg:address":"18 Unit 10, Shropshire Pl",
    "sg:city":"Queanbeyan",
    "sg:classifiers":[
        {
            "category":"Shopping",
            "subcategory":"Crafts & Fabrics",
            "type":"Retail Goods"
        }
    ],
    "sg:phone":"+61 2 6298 1331",
    "sg:postcode":"2620",
    "sg:province":"ACT",
    "sg:tags":[
        "supply"
    ],
    "wof:name":"Beadiac Australia",
    "wof:placetype":"venue"
},
  "geometry": {"coordinates":[149.233154297,-35.3603744507],"type":"Point"}
}