{
  "type": "Feature",
  "properties": {
    "iso:country":"AU",
    "sg:address":"98 Duke St",
    "sg:city":"Scarborough",
    "sg:classifiers":[
        {
            "category":"Building & Trades",
            "subcategory":"Landscaping Services",
            "type":"Services"
        }
    ],
    "sg:phone":"+61 8 9341 7079",
    "sg:postcode":"6019",
    "sg:province":"WA",
    "sg:tags":[
        "designer",
        "landscape",
        "contractor"
    ],
    "wof:name":"Waterbearer Reticulation",
    "wof:placetype":"venue"
},
  "geometry": {"coordinates":[115.77176666299999,-31.8888778687],"type":"Point"}
}