{
  "type": "Feature",
  "properties": {
    "addr:full":"2/ 22 Elizabeth St Artarmon NSW 2064",
    "addr:housenumber":"/ 22",
    "addr:postcode":"2064",
    "addr:street":"Elizabeth St",
    "iso:country":"AU",
    "sg:address":"2/ 22 Elizabeth St",
    "sg:city":"Artarmon",
    "sg:classifiers":[
        {
            "category":"Shopping",
            "subcategory":"Computers & Home Electronics",
            "type":"Retail Goods"
        }
    ],
    "sg:phone":"+61 2 9413 4285",
    "sg:postcode":"2064",
    "sg:province":"NSW",
    "sg:tags":[
        "wholesaler",
        "equipment",
        "electronic",
        "mfrs"
    ],
    "wof:name":"Home Video Technology Pty Ltd",
    "wof:placetype":"venue"
},
  "geometry": {"coordinates":[151.18507385300001,-33.8080215454],"type":"Point"}
}