{
  "type": "Feature",
  "properties": {
    "addr:full":"21 Coachwood Crt Burleigh Waters QLD 4220",
    "addr:housenumber":"21",
    "addr:postcode":"4220",
    "addr:street":"Coachwood Crt",
    "iso:country":"AU",
    "sg:address":"21 Coachwood Crt",
    "sg:city":"Burleigh Waters",
    "sg:classifiers":[
        {
            "category":"Shopping",
            "type":"Retail Goods"
        }
    ],
    "sg:phone":"+61 7 5520 2286",
    "sg:postcode":"4220",
    "sg:province":"QLD",
    "sg:tags":[
        "repair",
        "travel"
    ],
    "wof:name":"Sewn Up",
    "wof:placetype":"venue"
},
  "geometry": {"coordinates":[153.42338562,-28.0962238312],"type":"Point"}
}