{
  "type": "Feature",
  "properties": {
    "addr:full":"Cnr Hakea Drv & Nepean Hwy Mt Martha VIC 3934",
    "addr:postcode":"3934",
    "addr:street":"Cnr Hakea Drv & Nepean Hwy Mt Martha",
    "iso:country":"AU",
    "sg:address":"Cnr Hakea Drv & Nepean Hwy",
    "sg:city":"Mt Martha",
    "sg:classifiers":[
        {
            "category":"Health Services",
            "subcategory":"Health Practitioner",
            "type":"Services"
        }
    ],
    "sg:phone":"+61 3 5975 9099",
    "sg:postcode":"3934",
    "sg:province":"VIC",
    "sg:tags":[
        "naturopath"
    ],
    "wof:name":"Mornington Natural Therapy Centre",
    "wof:placetype":"venue"
},
  "geometry": {"coordinates":[145.03294372600001,-38.2740859985],"type":"Point"}
}