{
  "type": "Feature",
  "properties": {
    "addr:full":"Morley Senior High School 19- 43 Bramwell Rd Morley WA 6062",
    "addr:housenumber":"43",
    "addr:postcode":"6062",
    "addr:street":"Bramwell Rd",
    "iso:country":"AU",
    "sg:address":"Morley Senior High School 19- 43 Bramwell Rd",
    "sg:city":"Morley",
    "sg:classifiers":[
        {
            "category":"Education",
            "subcategory":"School",
            "type":"Public Place"
        }
    ],
    "sg:phone":"+61 8 9376 5555",
    "sg:postcode":"6062",
    "sg:province":"WA",
    "sg:tags":[
        "state",
        "except",
        "nsw"
    ],
    "wof:name":"Schools Government (Public)",
    "wof:placetype":"venue"
},
  "geometry": {"coordinates":[115.88481903100001,-31.8754405975],"type":"Point"}
}