{
  "type": "Feature",
  "properties": {
    "iso:country":"AU",
    "sg:address":"187 Logan Rd",
    "sg:city":"Woolloongabba",
    "sg:classifiers":[
        {
            "category":"Retail",
            "subcategory":"Auto Repair",
            "type":"Services"
        }
    ],
    "sg:phone":"+61 7 3249 6488",
    "sg:postcode":"4102",
    "sg:province":"QLD",
    "sg:tags":[
        "repairer",
        "motor",
        "engineer"
    ],
    "wof:name":"Southside Landrover",
    "wof:placetype":"venue"
},
  "geometry": {"coordinates":[153.04122924800001,-27.4947605133],"type":"Point"}
}