{
  "type": "Feature",
  "properties": {
    "addr:full":"Unit 1, 11 Stoddart Rd Prospect NSW 2148",
    "addr:housenumber":"11",
    "addr:postcode":"2148",
    "addr:street":"Stoddart Rd",
    "iso:country":"AU",
    "sg:address":"Unit 1, 11 Stoddart Rd",
    "sg:city":"Prospect",
    "sg:classifiers":[
        {
            "category":"Professional",
            "subcategory":"Detective & Security Services",
            "type":"Services"
        }
    ],
    "sg:phone":"+61 2 8868 3500",
    "sg:postcode":"2148",
    "sg:province":"NSW",
    "sg:tags":[
        "domestic",
        "alarm",
        "commercial",
        "burglar"
    ],
    "wof:name":"Stegar Electronic Security",
    "wof:placetype":"venue"
},
  "geometry": {"coordinates":[150.92198181099999,-33.8001785278],"type":"Point"}
}