{
  "type": "Feature",
  "properties": {
    "addr:full":"PO Box 4685 Darwin NT 0800",
    "addr:postcode":"nt 0800",
    "iso:country":"AU",
    "sg:address":"PO Box 4685",
    "sg:city":"Darwin",
    "sg:classifiers":[
        {
            "category":"Retail",
            "subcategory":"Repair Shop",
            "type":"Services"
        }
    ],
    "sg:phone":"+61 403 262 104",
    "sg:postcode":"0800",
    "sg:province":"NT",
    "sg:tags":[
        "windscreen"
    ],
    "wof:name":"Dek-a-dent NT",
    "wof:placetype":"venue"
},
  "geometry": {"coordinates":[130.84231567399999,-12.4620399475],"type":"Point"}
}