{
  "type": "Feature",
  "properties": {
    "addr:full":"23 Market La Narre Warren South VIC 3804",
    "addr:housenumber":"23",
    "addr:postcode":"3804",
    "addr:street":"Market La",
    "iso:country":"AU",
    "sg:address":"23 Market La",
    "sg:city":"Narre Warren South",
    "sg:classifiers":[
        {
            "category":"Retail",
            "subcategory":"Auto Repair",
            "type":"Services"
        }
    ],
    "sg:phone":"+61 429 138 739",
    "sg:postcode":"3804",
    "sg:province":"VIC",
    "sg:tags":[
        "camper-trailers",
        "caravan",
        "servicing"
    ],
    "wof:name":"Vantag",
    "wof:placetype":"venue"
},
  "geometry": {"coordinates":[145.313430786,-37.9869728088],"type":"Point"}
}