{
  "type": "Feature",
  "properties": {
    "iso:country":"AU",
    "sg:address":"PO Box 392",
    "sg:city":"Lennox Head",
    "sg:classifiers":[
        {
            "category":"Building & Trades",
            "subcategory":"Construction",
            "type":"Services"
        }
    ],
    "sg:phone":"+61 405 509 642",
    "sg:postcode":"2478",
    "sg:province":"NSW",
    "sg:tags":[
        "pool",
        "swimming"
    ],
    "wof:name":"Liquid Pool Design",
    "wof:placetype":"venue"
},
  "geometry": {"coordinates":[153.592727661,-28.7983398438],"type":"Point"}
}