{
  "type": "Feature",
  "properties": {
    "iso:country":"AU",
    "sg:address":"9 Beach Crt",
    "sg:city":"Victoria Point",
    "sg:classifiers":[
        {
            "category":"Organizations",
            "subcategory":"Professional Association",
            "type":"Services"
        }
    ],
    "sg:phone":"+61 1300 364 721",
    "sg:postcode":"4165",
    "sg:province":"QLD",
    "sg:tags":[
        "web",
        "internet"
    ],
    "wof:name":"Boost I T",
    "wof:placetype":"venue"
},
  "geometry": {"coordinates":[153.30572509800001,-27.5900783539],"type":"Point"}
}