{
  "type": "Feature",
  "properties": {
    "addr:full":"Ste 4, 14 Reid Prm Joondalup WA 6027",
    "addr:housenumber":"14",
    "addr:postcode":"6027",
    "addr:street":"Reid Prm",
    "iso:country":"AU",
    "sg:address":"Ste 4, 14 Reid Prm",
    "sg:city":"Joondalup",
    "sg:classifiers":[
        {
            "category":"Professional",
            "subcategory":"Accounting & Tax Preparation",
            "type":"Services"
        }
    ],
    "sg:phone":"+61 8 9300 0088",
    "sg:postcode":"6027",
    "sg:province":"WA",
    "sg:tags":[
        "consultant",
        "taxation"
    ],
    "wof:name":"H&R Block",
    "wof:placetype":"venue"
},
  "geometry": {"coordinates":[115.741592407,-31.7619953156],"type":"Point"}
}