{
  "type": "Feature",
  "properties": {
    "iso:country":"AU",
    "sg:address":"PO Box 31",
    "sg:city":"Maitland North",
    "sg:classifiers":[
        {
            "category":"Building & Trades",
            "subcategory":"Construction",
            "type":"Services"
        }
    ],
    "sg:phone":"+61 409 990 290",
    "sg:postcode":"2320",
    "sg:province":"NSW",
    "sg:tags":[
        "joiner",
        "carpenter"
    ],
    "wof:name":"Parsons CA, DM & MC",
    "wof:placetype":"venue"
},
  "geometry": {"coordinates":[151.572067261,-32.7033996582],"type":"Point"}
}