{
  "type": "Feature",
  "properties": {
    "addr:full":"6 Monterey Rd Bilgola Plateau NSW 2107",
    "addr:housenumber":"6",
    "addr:postcode":"2107",
    "addr:street":"Monterey Rd",
    "iso:country":"AU",
    "sg:address":"6 Monterey Rd",
    "sg:city":"Bilgola Plateau",
    "sg:classifiers":[
        {
            "category":"Building & Trades",
            "subcategory":"Construction",
            "type":"Services"
        }
    ],
    "sg:phone":"+61 410 314 827",
    "sg:postcode":"2107",
    "sg:province":"NSW",
    "sg:tags":[
        "earth",
        "excavating",
        "moving",
        "contractor"
    ],
    "wof:name":"Pure Earthworks",
    "wof:placetype":"venue"
},
  "geometry": {"coordinates":[151.31976318400001,-33.6463546753],"type":"Point"}
}