{
  "type": "Feature",
  "properties": {
    "iso:country":"AU",
    "sg:address":"6 Enterprise St",
    "sg:city":"Richlands",
    "sg:classifiers":[
        {
            "category":"Building & Trades",
            "subcategory":"Construction",
            "type":"Services"
        }
    ],
    "sg:phone":"+61 7 3713 7588",
    "sg:postcode":"4077",
    "sg:province":"QLD",
    "sg:tags":[
        "equipment",
        "system",
        "automation"
    ],
    "wof:name":"Mox Products",
    "wof:placetype":"venue"
},
  "geometry": {"coordinates":[152.94656372099999,-27.5857257843],"type":"Point"}
}