{
  "type": "Feature",
  "properties": {
    "addr:full":"46 Rowland Rees Crs Greenway ACT 2900",
    "addr:housenumber":"46",
    "addr:postcode":"2900",
    "addr:street":"Rowland Rees Crs",
    "iso:country":"AU",
    "sg:address":"46 Rowland Rees Crs",
    "sg:city":"Greenway",
    "sg:classifiers":[
        {
            "category":"Retail",
            "subcategory":"Event Space",
            "type":"Services"
        }
    ],
    "sg:phone":"+61 2 6293 3666",
    "sg:postcode":"2900",
    "sg:province":"ACT",
    "sg:tags":[
        "venue",
        "reception",
        "wedding"
    ],
    "wof:name":"Country Comfort Greenway",
    "wof:placetype":"venue"
},
  "geometry": {"coordinates":[149.068267822,-35.4185600281],"type":"Point"}
}