{
  "type": "Feature",
  "properties": {
    "addr:full":"683 Darling St Rozelle NSW 2039",
    "addr:housenumber":"683",
    "addr:postcode":"2039",
    "addr:street":"Darling St",
    "iso:country":"AU",
    "sg:address":"683 Darling St",
    "sg:city":"Rozelle",
    "sg:classifiers":[
        {
            "category":"Shopping",
            "subcategory":"Clothing, Apparel, & Fashions",
            "type":"Retail Goods"
        }
    ],
    "sg:phone":"+61 2 9810 3453",
    "sg:postcode":"2039",
    "sg:province":"NSW",
    "sg:tags":[
        "recycled",
        "clothing"
    ],
    "wof:name":"St Vincent De Paul Society",
    "wof:placetype":"venue"
},
  "geometry": {"coordinates":[151.169631958,-33.864025116],"type":"Point"}
}