{
  "type": "Feature",
  "properties": {
    "addr:full":"774 Princes Hwy Sandown VIC 3171",
    "addr:housenumber":"774",
    "addr:postcode":"3171",
    "addr:street":"Princes Hwy",
    "iso:country":"AU",
    "sg:address":"774 Princes Hwy",
    "sg:city":"Sandown",
    "sg:classifiers":[
        {
            "category":"Personal",
            "type":"Services"
        }
    ],
    "sg:phone":"+61 1800 888 336",
    "sg:postcode":"3171",
    "sg:province":"VIC",
    "sg:tags":[
        "gift"
    ],
    "wof:name":"Abundance Hampers",
    "wof:placetype":"venue"
},
  "geometry": {"coordinates":[145.16600036599999,-37.9410247803],"type":"Point"}
}