{
  "type": "Feature",
  "properties": {
    "addr:full":"47 Nardie St Eight Mile Plains QLD 4113",
    "addr:housenumber":"47",
    "addr:postcode":"4113",
    "addr:street":"Nardie St",
    "iso:country":"AU",
    "sg:address":"47 Nardie St",
    "sg:city":"Eight Mile Plains",
    "sg:classifiers":[
        {
            "category":"Travel",
            "subcategory":"Travel Agent",
            "type":"Entertainment"
        }
    ],
    "sg:phone":"+61 7 3341 0043",
    "sg:postcode":"4113",
    "sg:province":"QLD",
    "sg:tags":[
        "tour",
        "holiday",
        "adventure"
    ],
    "wof:name":"Two Fat Wheels",
    "wof:placetype":"venue"
},
  "geometry": {"coordinates":[153.09768676799999,-27.5704536438],"type":"Point"}
}