{
  "type": "Feature",
  "properties": {
    "addr:full":"Old Newell Hwy Narrabri NSW 2390",
    "addr:postcode":"2390",
    "addr:street":"Old Newell Hwy",
    "iso:country":"AU",
    "sg:address":"Old Newell Hwy",
    "sg:city":"Narrabri",
    "sg:classifiers":[
        {
            "category":"Professional",
            "subcategory":"Testing Lab",
            "type":"Services"
        }
    ],
    "sg:phone":"+61 2 6792 6511",
    "sg:postcode":"2390",
    "sg:province":"NSW",
    "sg:tags":[
        "soil",
        "investigation"
    ],
    "wof:name":"South Qld Soils Pty Ltd",
    "wof:placetype":"venue"
},
  "geometry": {"coordinates":[149.76687622099999,-30.3389778137],"type":"Point"}
}