{
  "type": "Feature",
  "properties": {
    "addr:full":"8 Else St Cundletown NSW 2430",
    "addr:housenumber":"8",
    "addr:postcode":"2430",
    "addr:street":"Else St",
    "iso:country":"AU",
    "sg:address":"8 Else St",
    "sg:city":"Cundletown",
    "sg:classifiers":[
        {
            "category":"Food & Beverages",
            "subcategory":"Liquor & Beverages",
            "type":"Retail Goods"
        }
    ],
    "sg:phone":"+61 2 6553 9650",
    "sg:postcode":"2430",
    "sg:province":"NSW",
    "sg:tags":[
        "store"
    ],
    "wof:name":"Cundle Cellars",
    "wof:placetype":"venue"
},
  "geometry": {"coordinates":[152.517731,-31.89806],"type":"Point"}
}