{
  "type": "Feature",
  "properties": {
    "addr:full":"569 Old Cleveland Rd Camp Hill QLD 4152",
    "addr:housenumber":"569",
    "addr:postcode":"4152",
    "addr:street":"Old Cleveland Rd",
    "iso:country":"AU",
    "sg:address":"569 Old Cleveland Rd",
    "sg:city":"Camp Hill",
    "sg:classifiers":[
        {
            "category":"Shopping",
            "subcategory":"Stationery & Office Supplies",
            "type":"Retail Goods"
        }
    ],
    "sg:phone":"+61 7 3398 3953",
    "sg:postcode":"4152",
    "sg:province":"QLD",
    "wof:name":"Officesmart",
    "wof:placetype":"venue"
},
  "geometry": {"coordinates":[153.07211303700001,-27.4921474457],"type":"Point"}
}