{
  "type": "Feature",
  "properties": {
    "iso:country":"AU",
    "sg:address":"Kiosk100/ Henry Parry Drv",
    "sg:city":"Gosford",
    "sg:classifiers":[
        {
            "category":"Retail",
            "subcategory":"Car Wash",
            "type":"Services"
        }
    ],
    "sg:phone":"+61 2 4322 0088",
    "sg:postcode":"2250",
    "sg:province":"NSW",
    "sg:tags":[
        "truck",
        "cleaning"
    ],
    "wof:name":"Zip Car Wash",
    "wof:placetype":"venue"
},
  "geometry": {"coordinates":[151.34492492699999,-33.4237785339],"type":"Point"}
}