{
  "type": "Feature",
  "properties": {
    "addr:full":"Noumea St Shalvey NSW 2770",
    "addr:postcode":"2770",
    "iso:country":"AU",
    "sg:address":"Noumea St",
    "sg:city":"Shalvey",
    "sg:classifiers":[
        {
            "category":"Education",
            "subcategory":"School",
            "type":"Public Place"
        }
    ],
    "sg:phone":"+61 2 9628 7777",
    "sg:postcode":"2770",
    "sg:province":"NSW",
    "sg:tags":[
        "state",
        "-",
        "nsw"
    ],
    "wof:name":"Noumea Primary School",
    "wof:placetype":"venue"
},
  "geometry": {"coordinates":[150.80853271500001,-33.7300453186],"type":"Point"}
}