{
  "type": "Feature",
  "properties": {
    "addr:full":"21 - 23 Colrado Crt Hallam VIC 3803",
    "addr:housenumber":"23",
    "addr:postcode":"3803",
    "addr:street":"Colrado Crt",
    "iso:country":"AU",
    "sg:address":"21 - 23 Colrado Crt",
    "sg:city":"Hallam",
    "sg:classifiers":[
        {
            "category":"Manufacturing",
            "subcategory":"Metals",
            "type":"Manufacturing & Wholesale Goods"
        }
    ],
    "sg:phone":"+61 3 8786 3188",
    "sg:postcode":"3803",
    "sg:province":"VIC",
    "sg:tags":[
        "steel",
        "fabricator",
        "mfrs"
    ],
    "wof:name":"Sutcliffe Fabrications",
    "wof:placetype":"venue"
},
  "geometry": {"coordinates":[145.274932861,-38.0139579773],"type":"Point"}
}