{
  "type": "Feature",
  "properties": {
    "iso:country":"AU",
    "sg:address":"5 Coongie Ave",
    "sg:city":"Edwardstown",
    "sg:classifiers":[
        {
            "category":"Professional",
            "type":"Services"
        }
    ],
    "sg:phone":"+61 8 8276 1088",
    "sg:postcode":"5039",
    "sg:province":"SA",
    "sg:tags":[
        "shop",
        "fitting"
    ],
    "wof:name":"Kenlore Furniture Pty Ltd",
    "wof:placetype":"venue"
},
  "geometry": {"coordinates":[138.57281494099999,-34.9905853271],"type":"Point"}
}