{
  "type": "Feature",
  "properties": {
    "iso:country":"AU",
    "sg:address":"Shop 33",
    "sg:city":", Fairfield Forum Fairfield",
    "sg:classifiers":[
        {
            "category":"Food & Beverages",
            "subcategory":"Specialty",
            "type":"Retail Goods"
        }
    ],
    "sg:phone":"+61 2 9726 0330",
    "sg:postcode":"2165",
    "sg:province":"NSW",
    "sg:tags":[
        "product",
        "health"
    ],
    "wof:name":"Natures Drop",
    "wof:placetype":"venue"
},
  "geometry": {"coordinates":[150.97203064000001,-33.8685302734],"type":"Point"}
}