{
  "type": "Feature",
  "properties": {
    "addr:full":"334 Wagga Rd Lavington NSW 2641",
    "addr:housenumber":"334",
    "addr:postcode":"2641",
    "addr:street":"Wagga Rd",
    "iso:country":"AU",
    "sg:address":"334 Wagga Rd",
    "sg:city":"Lavington",
    "sg:classifiers":[
        {
            "category":"Retail",
            "subcategory":"Repair Shop",
            "type":"Services"
        }
    ],
    "sg:phone":"+61 2 6040 8221",
    "sg:postcode":"2641",
    "sg:province":"NSW",
    "sg:tags":[
        "leadlights"
    ],
    "wof:name":"Lavington Stained Glass Supplies",
    "wof:placetype":"venue"
},
  "geometry": {"coordinates":[146.942596436,-36.0458908081],"type":"Point"}
}