{
  "type": "Feature",
  "properties": {
    "addr:full":"158 Laidlaws Rd Buckley Swamp VIC 3301",
    "addr:housenumber":"158",
    "addr:postcode":"3301",
    "addr:street":"Laidlaws Rd",
    "iso:country":"AU",
    "sg:address":"158 Laidlaws Rd",
    "sg:city":"Buckley Swamp",
    "sg:classifiers":[
        {
            "category":"Building & Trades",
            "subcategory":"Construction",
            "type":"Services"
        }
    ],
    "sg:phone":"+61 3 5572 4976",
    "sg:postcode":"3301",
    "sg:province":"VIC",
    "sg:tags":[
        "contractor"
    ],
    "wof:name":"Stephens B",
    "wof:placetype":"venue"
},
  "geometry": {"coordinates":[142.08729553200001,-37.8490028381],"type":"Point"}
}