{
  "type": "Feature",
  "properties": {
    "addr:full":"2/ 59 Elwin St Peakhurst NSW 2210",
    "addr:housenumber":"/ 59",
    "addr:postcode":"2210",
    "addr:street":"Elwin St",
    "iso:country":"AU",
    "sg:address":"2/ 59 Elwin St",
    "sg:city":"Peakhurst",
    "sg:classifiers":[
        {
            "category":"Communications",
            "type":"Services"
        }
    ],
    "sg:phone":"+61 403 622 561",
    "sg:postcode":"2210",
    "sg:province":"NSW",
    "sg:tags":[
        "public",
        "system",
        "address"
    ],
    "wof:name":"Oz Sound",
    "wof:placetype":"venue"
},
  "geometry": {"coordinates":[151.04362499999999,-33.961208],"type":"Point"}
}