{
  "type": "Feature",
  "properties": {
    "iso:country":"AU",
    "sg:address":"4 Ilford Pl",
    "sg:city":"Thornlie",
    "sg:classifiers":[
        {
            "category":"Organizations",
            "subcategory":"Professional Association",
            "type":"Services"
        }
    ],
    "sg:phone":"+61 403 997 891",
    "sg:postcode":"6108",
    "sg:province":"WA",
    "sg:tags":[
        "web",
        "internet"
    ],
    "wof:name":"Netsmart Solutions",
    "wof:placetype":"venue"
},
  "geometry": {"coordinates":[115.965286255,-32.0473747253],"type":"Point"}
}