{
  "type": "Feature",
  "properties": {
    "iso:country":"AU",
    "sg:address":"26 Anderson St",
    "sg:city":"Thebarton",
    "sg:classifiers":[
        {
            "category":"Professional",
            "subcategory":"Engineering",
            "type":"Services"
        }
    ],
    "sg:phone":"+61 8 8238 9400",
    "sg:postcode":"5031",
    "sg:province":"SA",
    "sg:tags":[
        "consulting",
        "engineer"
    ],
    "wof:name":"SDA Engineering Pty Ltd",
    "wof:placetype":"venue"
},
  "geometry": {"coordinates":[138.573654175,-34.9117774963],"type":"Point"}
}