{
  "type": "Feature",
  "properties": {
    "addr:full":"Shop 1 & 2/ 12 Mount Barker Rd Stirling SA 5152",
    "addr:housenumber":"shop 1 & 2 / 12",
    "addr:postcode":"5152",
    "addr:street":"Mount Barker Rd",
    "iso:country":"AU",
    "sg:address":"Shop 1 & 2/ 12 Mount Barker Rd",
    "sg:city":"Stirling",
    "sg:classifiers":[
        {
            "category":"Fast Food",
            "type":"Food & Drink"
        }
    ],
    "sg:phone":"+61 8 8339 5555",
    "sg:postcode":"5152",
    "sg:province":"SA",
    "sg:tags":[
        "away",
        "take"
    ],
    "wof:name":"Subway",
    "wof:placetype":"venue"
},
  "geometry": {"coordinates":[138.723144531,-35.0081214905],"type":"Point"}
}