{
  "type": "Feature",
  "properties": {
    "addr:full":"Shop 2 Sorrento Qy Hillarys WA 6025",
    "addr:housenumber":"shop 2",
    "addr:postcode":"6025",
    "addr:street":"Sorrento Qy",
    "iso:country":"AU",
    "sg:address":"Shop 2",
    "sg:city":"Sorrento Qy Hillarys",
    "sg:classifiers":[
        {
            "category":"Health Services",
            "subcategory":"Chiropractor",
            "type":"Services"
        }
    ],
    "sg:phone":"+61 8 9246 1399",
    "sg:postcode":"6025",
    "sg:province":"WA",
    "wof:name":"Galbraith P. W.",
    "wof:placetype":"venue"
},
  "geometry": {"coordinates":[115.7527771,-31.8595352173],"type":"Point"}
}