{
  "type": "Feature",
  "properties": {
    "addr:full":"Dubbo St Warren NSW 2824",
    "addr:postcode":"2824",
    "addr:street":"Dubbo St",
    "iso:country":"AU",
    "sg:address":"Dubbo St",
    "sg:city":"Warren",
    "sg:classifiers":[
        {
            "category":"Restaurant",
            "type":"Food & Drink"
        }
    ],
    "sg:phone":"+61 2 6847 3333",
    "sg:postcode":"2824",
    "sg:province":"NSW",
    "wof:name":"Benny's Chinese Restaurant",
    "wof:placetype":"venue"
},
  "geometry": {"coordinates":[147.83697509800001,-31.7009925842],"type":"Point"}
}