{
  "type": "Feature",
  "properties": {
    "iso:country":"AU",
    "sg:address":"87 Rundle Rd",
    "sg:city":"Salisbury South",
    "sg:classifiers":[
        {
            "category":"Wholesale",
            "subcategory":"Auto Parts",
            "type":"Manufacturing & Wholesale Goods"
        }
    ],
    "sg:phone":"+61 8 8285 7043",
    "sg:postcode":"5106",
    "sg:province":"SA",
    "sg:tags":[
        "recyclers"
    ],
    "wof:name":"Hyunauto Spares",
    "wof:placetype":"venue"
},
  "geometry": {"coordinates":[138.64485199999999,-34.786461],"type":"Point"}
}