{
  "type": "Feature",
  "properties": {
    "addr:full":"454 Honour Ave Corowa NSW 2646",
    "addr:housenumber":"454",
    "addr:postcode":"2646",
    "addr:street":"Honour Ave",
    "iso:country":"AU",
    "sg:address":"454 Honour Ave",
    "sg:city":"Corowa",
    "sg:classifiers":[
        {
            "category":"Travel",
            "subcategory":"Hotels & Motels",
            "type":"Entertainment"
        }
    ],
    "sg:phone":"+61 2 6033 2500",
    "sg:postcode":"2646",
    "sg:province":"NSW",
    "wof:name":"Bindaree Motel & Caravan Park",
    "wof:placetype":"venue"
},
  "geometry": {"coordinates":[146.391235352,-35.9941368103],"type":"Point"}
}