{
  "type": "Feature",
  "properties": {
    "addr:full":"89 Brookes St Fortitude Valley QLD 4006",
    "addr:housenumber":"89",
    "addr:postcode":"4006",
    "addr:street":"Brookes St",
    "iso:country":"AU",
    "sg:address":"89 Brookes St",
    "sg:city":"Fortitude Valley",
    "sg:classifiers":[
        {
            "category":"Professional",
            "subcategory":"Art Services",
            "type":"Services"
        }
    ],
    "sg:phone":"+61 7 3252 8899",
    "sg:postcode":"4006",
    "sg:province":"QLD",
    "sg:tags":[
        "interior",
        "designer"
    ],
    "wof:name":"Brand & Slater Architects Pty Ltd",
    "wof:placetype":"venue"
},
  "geometry": {"coordinates":[153.03660583499999,-27.4526004791],"type":"Point"}
}