{
  "type": "Feature",
  "properties": {
    "addr:full":"121 Moore St Moe VIC 3825",
    "addr:housenumber":"121",
    "addr:postcode":"3825",
    "addr:street":"Moore St",
    "iso:country":"AU",
    "sg:address":"121 Moore St",
    "sg:city":"Moe",
    "sg:classifiers":[
        {
            "category":"Manufacturing",
            "subcategory":"Tools & Machinery",
            "type":"Manufacturing & Wholesale Goods"
        }
    ],
    "sg:phone":"+61 3 5126 1222",
    "sg:postcode":"3825",
    "sg:province":"VIC",
    "sg:tags":[
        "crankshaft",
        "cylinder",
        "grinding"
    ],
    "wof:name":"Moe Engine Reconditioning",
    "wof:placetype":"venue"
},
  "geometry": {"coordinates":[146.263992,-38.16193],"type":"Point"}
}