{
  "type": "Feature",
  "properties": {
    "addr:full":"Suite 145/ Cornwallis St Redfern NSW 2016",
    "addr:housenumber":"/",
    "addr:postcode":"2016",
    "addr:street":"Cornwallis St",
    "iso:country":"AU",
    "sg:address":"Suite 145/ Cornwallis St",
    "sg:city":"Redfern",
    "sg:classifiers":[
        {
            "category":"Banks & Credit Unions",
            "subcategory":"Bureau De Change",
            "type":"Services"
        }
    ],
    "sg:phone":"+61 2 9209 4033",
    "sg:postcode":"2016",
    "sg:province":"NSW",
    "sg:tags":[
        "preparation",
        "processing",
        "data"
    ],
    "wof:name":"Agile Data Mining",
    "wof:placetype":"venue"
},
  "geometry": {"coordinates":[151.19781494099999,-33.8932647705],"type":"Point"}
}