{
  "type": "Feature",
  "properties": {
    "addr:full":"Chester St Newstead QLD 4006",
    "addr:postcode":"4006",
    "addr:street":"Chester St",
    "iso:country":"AU",
    "sg:address":"Chester St",
    "sg:city":"Newstead",
    "sg:classifiers":[
        {
            "category":"Education",
            "subcategory":"Special Training",
            "type":"Public Place"
        }
    ],
    "sg:phone":"+61 7 3252 6702",
    "sg:postcode":"4006",
    "sg:province":"QLD",
    "sg:tags":[
        "development"
    ],
    "wof:name":"NSPI Australia",
    "wof:placetype":"venue"
},
  "geometry": {"coordinates":[153.04246520999999,-27.4555492401],"type":"Point"}
}