{
  "type": "Feature",
  "properties": {
    "addr:full":"Units 4 & 5, 37-39 Little Boundary Rd Laverton VIC 3028",
    "addr:housenumber":"units 4 & 5 37-39",
    "addr:postcode":"3028",
    "addr:street":"Little Boundary Rd",
    "iso:country":"AU",
    "sg:address":"Units 4 & 5, 37-39 Little Boundary Rd",
    "sg:city":"Laverton",
    "sg:classifiers":[
        {
            "category":"Shopping",
            "subcategory":"Party Supplies",
            "type":"Retail Goods"
        }
    ],
    "sg:phone":"+61 3 9314 1711",
    "sg:postcode":"3028",
    "sg:province":"VIC",
    "sg:tags":[
        "equipment",
        "laminating"
    ],
    "wof:name":"Anitech",
    "wof:placetype":"venue"
},
  "geometry": {"coordinates":[144.818085,-37.817783],"type":"Point"}
}