{
  "type": "Feature",
  "properties": {
    "addr:full":"45 Front St Mossman QLD 4873",
    "addr:housenumber":"45",
    "addr:postcode":"4873",
    "addr:street":"Front St",
    "iso:country":"AU",
    "sg:address":"45 Front St",
    "sg:city":"Mossman",
    "sg:classifiers":[
        {
            "category":"Shopping",
            "subcategory":"Clothing, Apparel, & Fashions",
            "type":"Retail Goods"
        }
    ],
    "sg:phone":"+61 7 4098 3666",
    "sg:postcode":"4873",
    "sg:province":"QLD",
    "sg:tags":[
        "menswear"
    ],
    "wof:name":"Mensland",
    "wof:placetype":"venue"
},
  "geometry": {"coordinates":[145.373336792,-16.4623699188],"type":"Point"}
}