{
  "type": "Feature",
  "properties": {
    "addr:full":"17 Barrett St Robertson QLD 4109",
    "addr:housenumber":"17",
    "addr:postcode":"4109",
    "addr:street":"Barrett St",
    "iso:country":"AU",
    "sg:address":"17 Barrett St",
    "sg:city":"Robertson",
    "sg:classifiers":[
        {
            "category":"Food & Beverages",
            "subcategory":"Groceries & Convenience Stores",
            "type":"Retail Goods"
        }
    ],
    "sg:phone":"+61 7 3875 1368",
    "sg:postcode":"4109",
    "sg:province":"QLD",
    "wof:name":"Robertson Convenience Store",
    "wof:placetype":"venue"
},
  "geometry": {"coordinates":[153.05140685999999,-27.5608005524],"type":"Point"}
}