{
  "type": "Feature",
  "properties": {
    "addr:full":"13 Inglewood St Gungahlin ACT 2912",
    "addr:housenumber":"13",
    "addr:postcode":"2912",
    "addr:street":"Inglewood St",
    "iso:country":"AU",
    "sg:address":"13 Inglewood St",
    "sg:city":"Gungahlin",
    "sg:classifiers":[
        {
            "category":"Home & Garden",
            "subcategory":"Building Materials",
            "type":"Retail Goods"
        }
    ],
    "sg:phone":"+61 1800 818 815",
    "sg:postcode":"2912",
    "sg:province":"ACT",
    "sg:tags":[
        "shutter",
        "roller",
        "grille"
    ],
    "wof:name":"Focus Home Improvements",
    "wof:placetype":"venue"
},
  "geometry": {"coordinates":[149.13897705100001,-35.1789207458],"type":"Point"}
}