{
  "type": "Feature",
  "properties": {
    "iso:country":"AU",
    "sg:address":"328 Guildford Rd",
    "sg:city":"Guildford",
    "sg:classifiers":[
        {
            "category":"Health Services",
            "subcategory":"Optometrist",
            "type":"Services"
        }
    ],
    "sg:phone":"+61 2 9681 1117",
    "sg:postcode":"2161",
    "sg:province":"NSW",
    "wof:name":"McIntyre Robert G",
    "wof:placetype":"venue"
},
  "geometry": {"coordinates":[150.986053467,-33.8541107178],"type":"Point"}
}