{
  "type": "Feature",
  "properties": {
    "addr:full":"13-15 Curtis St (Cnr Settlement Rd) Belmont VIC 3216",
    "addr:housenumber":"13-15",
    "addr:postcode":"3216",
    "addr:street":"Curtis St Cnr Settlement Rd",
    "iso:country":"AU",
    "sg:address":"13-15 Curtis St",
    "sg:city":"(Cnr Settlement Rd) Belmont",
    "sg:classifiers":[
        {
            "category":"Autos & Motor Vehicles",
            "subcategory":"Automobile Sales",
            "type":"Retail Goods"
        }
    ],
    "sg:phone":"+61 3 5243 4240",
    "sg:postcode":"3216",
    "sg:province":"VIC",
    "sg:tags":[
        "car",
        "used"
    ],
    "wof:name":"Orix Car Centre",
    "wof:placetype":"venue"
},
  "geometry": {"coordinates":[144.35177612300001,-38.1783943176],"type":"Point"}
}