{
  "type": "Feature",
  "properties": {
    "addr:full":"78- 80 Parramatta Rd Granville NSW 2142",
    "addr:housenumber":"80",
    "addr:postcode":"2142",
    "addr:street":"Parramatta Rd",
    "iso:country":"AU",
    "sg:address":"78- 80 Parramatta Rd",
    "sg:city":"Granville",
    "sg:classifiers":[
        {
            "category":"Retail",
            "subcategory":"Auto Rental",
            "type":"Services"
        }
    ],
    "sg:phone":"+61 2 9637 1566",
    "sg:postcode":"2142",
    "sg:province":"NSW",
    "sg:tags":[
        "car",
        "hire",
        "minibus"
    ],
    "wof:name":"Hertz",
    "wof:placetype":"venue"
},
  "geometry": {"coordinates":[151.01560974099999,-33.8321990967],"type":"Point"}
}