{
  "type": "Feature",
  "properties": {
    "iso:country":"AU",
    "sg:address":"2 Nilmar Ave",
    "sg:city":"Wodonga",
    "sg:classifiers":[
        {
            "category":"Professional",
            "subcategory":"Engineering",
            "type":"Services"
        }
    ],
    "sg:phone":"+61 2 6056 1255",
    "sg:postcode":"3690",
    "sg:province":"VIC",
    "sg:tags":[
        "civil",
        "engineer"
    ],
    "wof:name":"Belvoir Consulting Pty Ltd",
    "wof:placetype":"venue"
},
  "geometry": {"coordinates":[146.88778686500001,-36.1252861023],"type":"Point"}
}