{
  "type": "Feature",
  "properties": {
    "iso:country":"AU",
    "sg:address":"352 Llandilo Rd",
    "sg:city":"Llandilo",
    "sg:classifiers":[
        {
            "category":"Home & Garden",
            "subcategory":"Garden Supply",
            "type":"Retail Goods"
        }
    ],
    "sg:phone":"+61 406 097 249",
    "sg:postcode":"2747",
    "sg:province":"NSW",
    "sg:tags":[
        "shed"
    ],
    "wof:name":"Affordable Cubbies",
    "wof:placetype":"venue"
},
  "geometry": {"coordinates":[150.759033203,-33.69688797],"type":"Point"}
}