{
  "type": "Feature",
  "properties": {
    "iso:country":"AU",
    "sg:address":"Queens Park Rd",
    "sg:city":"Bondi Junction",
    "sg:classifiers":[
        {
            "category":"Education",
            "subcategory":"School",
            "type":"Public Place"
        }
    ],
    "sg:phone":"+61 2 9387 3555",
    "sg:postcode":"2022",
    "sg:province":"NSW",
    "wof:name":"Moriah War Memorial College",
    "wof:placetype":"venue"
},
  "geometry": {"coordinates":[151.24388122600001,-33.8985481262],"type":"Point"}
}