{
  "type": "Feature",
  "properties": {
    "addr:full":"PO Box 763 Capalaba QLD 4157",
    "addr:postcode":"4157",
    "iso:country":"AU",
    "sg:address":"PO Box 763",
    "sg:city":"Capalaba",
    "sg:classifiers":[
        {
            "category":"Building & Trades",
            "subcategory":"Construction",
            "type":"Services"
        }
    ],
    "sg:phone":"+61 1300 762 687",
    "sg:postcode":"4157",
    "sg:province":"QLD",
    "sg:tags":[
        "equipment",
        "system",
        "automation"
    ],
    "wof:name":"Kenetik Robotics & Automation Systems Pty Ltd",
    "wof:placetype":"venue"
},
  "geometry": {"coordinates":[153.21090698200001,-27.5379695892],"type":"Point"}
}