{
  "type": "Feature",
  "properties": {
    "iso:country":"AU",
    "sg:address":"148 John St",
    "sg:city":"Singleton",
    "sg:classifiers":[
        {
            "category":"Travel",
            "subcategory":"Hotels & Motels",
            "type":"Entertainment"
        }
    ],
    "sg:phone":"+61 2 6571 2712",
    "sg:postcode":"2330",
    "sg:province":"NSW",
    "sg:tags":[
        "accommodation"
    ],
    "wof:name":"The Criterion Hotel",
    "wof:placetype":"venue"
},
  "geometry": {"coordinates":[151.168274,-32.5639],"type":"Point"}
}