{
  "type": "Feature",
  "properties": {
    "addr:full":"Shop 10, Jimboomba Shopping Centre, Mt Lindesay Hw Jimboomba QLD 4280",
    "addr:housenumber":"shop 10",
    "addr:postcode":"4280",
    "addr:street":"Mt Lindesay Hw",
    "iso:country":"AU",
    "sg:address":"Shop 10, Jimboomba Shopping Centre, Mt Lindesay Hw",
    "sg:city":"Jimboomba",
    "sg:classifiers":[
        {
            "category":"Shopping",
            "subcategory":"Crafts & Fabrics",
            "type":"Retail Goods"
        }
    ],
    "sg:phone":"+61 7 5546 9599",
    "sg:postcode":"4280",
    "sg:province":"QLD",
    "sg:tags":[
        "material",
        "dress"
    ],
    "wof:name":"Pats Fabric Center",
    "wof:placetype":"venue"
},
  "geometry": {"coordinates":[153.02891500000001,-27.813429],"type":"Point"}
}