{
  "type": "Feature",
  "properties": {
    "iso:country":"AU",
    "sg:address":"111 Augusta Rd",
    "sg:city":"Lenah Valley",
    "sg:classifiers":[
        {
            "category":"Personal",
            "subcategory":"Beauty Salon",
            "type":"Services"
        }
    ],
    "sg:phone":"+61 3 6228 6758",
    "sg:postcode":"7008",
    "sg:province":"TAS",
    "sg:tags":[
        "hair",
        "wedding"
    ],
    "wof:name":"Tsunami Hair & Beauty",
    "wof:placetype":"venue"
},
  "geometry": {"coordinates":[147.29580688499999,-42.8654441833],"type":"Point"}
}