{
  "type": "Feature",
  "properties": {
    "addr:full":"172 Great Western Hwy Blaxland NSW 2774",
    "addr:housenumber":"172",
    "addr:postcode":"2774",
    "addr:street":"Great Western Hwy",
    "iso:country":"AU",
    "sg:address":"172 Great Western Hwy",
    "sg:city":"Blaxland",
    "sg:classifiers":[
        {
            "category":"Health Services",
            "subcategory":"Dentist",
            "type":"Services"
        }
    ],
    "sg:phone":"+61 2 4739 0885",
    "sg:postcode":"2774",
    "sg:province":"NSW",
    "sg:tags":[
        "technician",
        "dental"
    ],
    "wof:name":"Blaxland Cottage Denture Clinic",
    "wof:placetype":"venue"
},
  "geometry": {"coordinates":[150.605377197,-33.7401390076],"type":"Point"}
}