{
  "type": "Feature",
  "properties": {
    "addr:full":"18 Turley St Ipswich QLD 4305",
    "addr:housenumber":"18",
    "addr:postcode":"4305",
    "addr:street":"Turley St",
    "iso:country":"AU",
    "sg:address":"18 Turley St",
    "sg:city":"Ipswich",
    "sg:classifiers":[
        {
            "category":"Autos & Motor Vehicles",
            "subcategory":"Motorcycle Sales",
            "type":"Retail Goods"
        }
    ],
    "sg:phone":"+61 7 3282 8144",
    "sg:postcode":"4305",
    "sg:province":"QLD",
    "sg:tags":[
        "outboard"
    ],
    "wof:name":"Ipswich Marine",
    "wof:placetype":"venue"
},
  "geometry": {"coordinates":[152.750366211,-27.6215763092],"type":"Point"}
}