{
  "type": "Feature",
  "properties": {
    "addr:full":"15 Kirkdale St Brunswick East VIC 3057",
    "addr:housenumber":"15",
    "addr:postcode":"3057",
    "addr:street":"Kirkdale St",
    "iso:country":"AU",
    "sg:address":"15 Kirkdale St",
    "sg:city":"Brunswick East",
    "sg:classifiers":[
        {
            "category":"Building & Trades",
            "subcategory":"Plumbing",
            "type":"Services"
        }
    ],
    "sg:phone":"+61 3 9387 9322",
    "sg:postcode":"3057",
    "sg:province":"VIC",
    "sg:tags":[
        "plumber",
        "gasfitters"
    ],
    "wof:name":"Melbourne Building Maintenance",
    "wof:placetype":"venue"
},
  "geometry": {"coordinates":[144.981155395,-37.7698402405],"type":"Point"}
}