{
  "type": "Feature",
  "properties": {
    "addr:full":"Peterson Rd Morayfield QLD 4506",
    "addr:postcode":"4506",
    "addr:street":"Peterson Rd",
    "iso:country":"AU",
    "sg:address":"Peterson Rd",
    "sg:city":"Morayfield",
    "sg:classifiers":[
        {
            "category":"Arena",
            "subcategory":"Sports Club",
            "type":"Entertainment"
        }
    ],
    "sg:phone":"+61 7 5498 6400",
    "sg:postcode":"4506",
    "sg:province":"QLD",
    "sg:tags":[
        "union",
        "rugby"
    ],
    "wof:name":"Caboolture Rugby Union Club",
    "wof:placetype":"venue"
},
  "geometry": {"coordinates":[152.948394775,-27.1095638275],"type":"Point"}
}