{
  "type": "Feature",
  "properties": {
    "iso:country":"AU",
    "sg:address":"251 Old Eltham Rd",
    "sg:city":"Lower Plenty",
    "sg:classifiers":[
        {
            "category":"Professional",
            "subcategory":"Computer Services",
            "type":"Services"
        }
    ],
    "sg:phone":"+61 3 9431 2190",
    "sg:postcode":"3093",
    "sg:province":"VIC",
    "sg:tags":[
        "consultant",
        "system"
    ],
    "wof:name":"Sys Pro",
    "wof:placetype":"venue"
},
  "geometry": {"coordinates":[145.133743286,-37.7337760925],"type":"Point"}
}