{
  "type": "Feature",
  "properties": {
    "iso:country":"AU",
    "sg:address":"423 Victoria St",
    "sg:city":"Brunswick",
    "sg:classifiers":[
        {
            "category":"Manufacturing",
            "subcategory":"Food",
            "type":"Manufacturing & Wholesale Goods"
        }
    ],
    "sg:phone":"+61 3 9381 1444",
    "sg:postcode":"3056",
    "sg:province":"VIC",
    "sg:tags":[
        "product",
        "nut",
        "edible"
    ],
    "wof:name":"Bas Foods Australia",
    "wof:placetype":"venue"
},
  "geometry": {"coordinates":[144.952514648,-37.7657241821],"type":"Point"}
}