{
  "type": "Feature",
  "properties": {
    "addr:full":"11 Kenny St Bassendean WA 6054",
    "addr:housenumber":"11",
    "addr:postcode":"6054",
    "addr:street":"Kenny St",
    "iso:country":"AU",
    "sg:address":"11 Kenny St",
    "sg:city":"Bassendean",
    "sg:classifiers":[
        {
            "category":"Health Services",
            "subcategory":"Doctor",
            "type":"Services"
        }
    ],
    "sg:phone":"+61 8 9378 1811",
    "sg:postcode":"6054",
    "sg:province":"WA",
    "sg:tags":[
        "medical",
        "practitioner"
    ],
    "wof:name":"Fine M D",
    "wof:placetype":"venue"
},
  "geometry": {"coordinates":[115.947059631,-31.9048786163],"type":"Point"}
}