{
  "type": "Feature",
  "properties": {
    "addr:full":"33 Sixth St Granville NSW 2142",
    "addr:housenumber":"33",
    "addr:postcode":"2142",
    "addr:street":"Sixth St",
    "iso:country":"AU",
    "sg:address":"33 Sixth St",
    "sg:city":"Granville",
    "sg:classifiers":[
        {
            "category":"Professional",
            "type":"Services"
        }
    ],
    "sg:phone":"+61 2 8840 9425",
    "sg:postcode":"2142",
    "sg:province":"NSW",
    "sg:tags":[
        "transport"
    ],
    "wof:name":"Mary Transport Pty Ltd",
    "wof:placetype":"venue"
},
  "geometry": {"coordinates":[151.01441955600001,-33.8417549133],"type":"Point"}
}