{
  "type": "Feature",
  "properties": {
    "addr:full":"53 Fernleigh Rd Wagga Wagga NSW 2650",
    "addr:housenumber":"53",
    "addr:postcode":"2650",
    "addr:street":"Fernleigh Rd",
    "iso:country":"AU",
    "sg:address":"53 Fernleigh Rd",
    "sg:city":"Wagga Wagga",
    "sg:classifiers":[
        {
            "category":"Health Services",
            "subcategory":"Doctor",
            "type":"Services"
        }
    ],
    "sg:phone":"+61 2 6925 5766",
    "sg:postcode":"2650",
    "sg:province":"NSW",
    "sg:tags":[
        "medical",
        "practitioner"
    ],
    "wof:name":"Mayne Laverty Pathology Collection Centres",
    "wof:placetype":"venue"
},
  "geometry": {"coordinates":[147.357666016,-35.1327362061],"type":"Point"}
}