{
  "type": "Feature",
  "properties": {
    "iso:country":"AU",
    "sg:address":"36 Railway St",
    "sg:city":"Corrimal",
    "sg:classifiers":[
        {
            "category":"Retail",
            "subcategory":"Auto Repair",
            "type":"Services"
        }
    ],
    "sg:phone":"+61 2 4284 3293",
    "sg:postcode":"2518",
    "sg:province":"NSW",
    "sg:tags":[
        "repairer",
        "motor",
        "engineer"
    ],
    "wof:name":"Pioneer Service Centre",
    "wof:placetype":"venue"
},
  "geometry": {"coordinates":[150.904922,-34.37384],"type":"Point"}
}