{
  "type": "Feature",
  "properties": {
    "iso:country":"AU",
    "sg:address":"45 Shore St",
    "sg:city":"Cleveland",
    "sg:classifiers":[
        {
            "category":"Utilities",
            "subcategory":"Refuse",
            "type":"Services"
        }
    ],
    "sg:phone":"+61 7 3821 3200",
    "sg:postcode":"4163",
    "sg:province":"QLD",
    "sg:tags":[
        "remover",
        "rubbish"
    ],
    "wof:name":"Handybin Waste Services",
    "wof:placetype":"venue"
},
  "geometry": {"coordinates":[153.25918579099999,-27.5244483948],"type":"Point"}
}