{
  "type": "Feature",
  "properties": {
    "iso:country":"AU",
    "sg:address":"2 Byways Drv",
    "sg:city":"Ringwood East",
    "sg:classifiers":[
        {
            "category":"Professional",
            "subcategory":"Management & Consulting",
            "type":"Services"
        }
    ],
    "sg:phone":"+61 3 9870 7773",
    "sg:postcode":"3135",
    "sg:province":"VIC",
    "sg:tags":[
        "consultant"
    ],
    "wof:name":"Neil G O'Loghlen Total Quality Pty Ltd",
    "wof:placetype":"venue"
},
  "geometry": {"coordinates":[145.25685119600001,-37.8169136047],"type":"Point"}
}