{
  "type": "Feature",
  "properties": {
    "addr:full":"629 Logan Rd Greenslopes QLD 4120",
    "addr:housenumber":"629",
    "addr:postcode":"4120",
    "addr:street":"Logan Rd",
    "iso:country":"AU",
    "sg:address":"629 Logan Rd",
    "sg:city":"Greenslopes",
    "sg:classifiers":[
        {
            "category":"Shopping",
            "subcategory":"Computers & Home Electronics",
            "type":"Retail Goods"
        }
    ],
    "sg:phone":"+61 7 3397 0566",
    "sg:postcode":"4120",
    "sg:province":"QLD",
    "sg:tags":[
        "equipment",
        "supply"
    ],
    "wof:name":"Cartridge World",
    "wof:placetype":"venue"
},
  "geometry": {"coordinates":[153.051635742,-27.508682251],"type":"Point"}
}