{
  "type": "Feature",
  "properties": {
    "addr:full":"31 Kenny Drv Labrador QLD 4215",
    "addr:housenumber":"31",
    "addr:postcode":"4215",
    "addr:street":"Kenny Drv",
    "iso:country":"AU",
    "sg:address":"31 Kenny Drv",
    "sg:city":"Labrador",
    "sg:classifiers":[
        {
            "category":"Retail",
            "subcategory":"Repair Shop",
            "type":"Services"
        }
    ],
    "sg:phone":"+61 414 759 385",
    "sg:postcode":"4215",
    "sg:province":"QLD",
    "sg:tags":[
        "maintenance",
        "pool",
        "swimming"
    ],
    "wof:name":"Perfect Balance Pool & Spa Care",
    "wof:placetype":"venue"
},
  "geometry": {"coordinates":[153.39486694300001,-27.9400691986],"type":"Point"}
}