{
  "type": "Feature",
  "properties": {
    "addr:full":"18 Farrell St Yandina QLD 4561",
    "addr:housenumber":"18",
    "addr:postcode":"4561",
    "addr:street":"Farrell St",
    "iso:country":"AU",
    "sg:address":"18 Farrell St",
    "sg:city":"Yandina",
    "sg:classifiers":[
        {
            "category":"Health Services",
            "subcategory":"Dentist",
            "type":"Services"
        }
    ],
    "sg:phone":"+61 7 5446 8677",
    "sg:postcode":"4561",
    "sg:province":"QLD",
    "wof:name":"Ray Robinson",
    "wof:placetype":"venue"
},
  "geometry": {"coordinates":[152.95639038100001,-26.5611553192],"type":"Point"}
}