{
  "type": "Feature",
  "properties": {
    "addr:full":"4 Tower St Inverloch VIC 3996",
    "addr:housenumber":"4",
    "addr:postcode":"3996",
    "addr:street":"Tower St",
    "iso:country":"AU",
    "sg:address":"4 Tower St",
    "sg:city":"Inverloch",
    "sg:classifiers":[
        {
            "category":"Retail",
            "subcategory":"Auto Repair",
            "type":"Services"
        }
    ],
    "sg:phone":"+61 412 149 853",
    "sg:postcode":"3996",
    "sg:province":"VIC",
    "sg:tags":[
        "repairer",
        "motor",
        "engineer"
    ],
    "wof:name":"Dowel Frank Mobile Mechanic",
    "wof:placetype":"venue"
},
  "geometry": {"coordinates":[145.73228499999999,-38.627308],"type":"Point"}
}