{
  "type": "Feature",
  "properties": {
    "addr:full":"80 Nicholson St Mall Footscray VIC 3011",
    "addr:housenumber":"80",
    "addr:postcode":"3011",
    "addr:street":"Nicholson St Mall",
    "iso:country":"AU",
    "sg:address":"80 Nicholson St Mall",
    "sg:city":"Footscray",
    "sg:classifiers":[
        {
            "category":"Banks & Credit Unions",
            "subcategory":"Investment Brokerage",
            "type":"Services"
        }
    ],
    "sg:phone":"+61 1800 653 061",
    "sg:postcode":"3011",
    "sg:province":"VIC",
    "wof:name":"Commonwealth Financial Planning",
    "wof:placetype":"venue"
},
  "geometry": {"coordinates":[144.89938354500001,-37.799911499],"type":"Point"}
}