{
  "type": "Feature",
  "properties": {
    "iso:country":"AU",
    "sg:address":"111 Thomas St",
    "sg:city":"Brighton East",
    "sg:classifiers":[
        {
            "category":"Building & Trades",
            "subcategory":"Construction",
            "type":"Services"
        }
    ],
    "sg:phone":"+61 411 111 285",
    "sg:postcode":"3187",
    "sg:province":"VIC",
    "sg:tags":[
        "management"
    ],
    "wof:name":"I.S.T",
    "wof:placetype":"venue"
},
  "geometry": {"coordinates":[145.02455139200001,-37.9090576172],"type":"Point"}
}