{
  "type": "Feature",
  "properties": {
    "addr:full":"256 Thoms La Thornton VIC 3712",
    "addr:housenumber":"256",
    "addr:postcode":"3712",
    "addr:street":"Thoms La",
    "iso:country":"AU",
    "sg:address":"256 Thoms La",
    "sg:city":"Thornton",
    "sg:classifiers":[
        {
            "category":"Professional",
            "subcategory":"Business Services",
            "type":"Services"
        }
    ],
    "sg:phone":"+61 3 5773 2283",
    "sg:postcode":"3712",
    "sg:province":"VIC",
    "sg:tags":[
        "broker"
    ],
    "wof:name":"Majura Management Services",
    "wof:placetype":"venue"
},
  "geometry": {"coordinates":[145.82191467300001,-37.2499923706],"type":"Point"}
}