{
  "type": "Feature",
  "properties": {
    "addr:full":"737 Nicholson St Carlton North VIC 3054",
    "addr:housenumber":"737",
    "addr:postcode":"3054",
    "addr:street":"Nicholson St",
    "iso:country":"AU",
    "sg:address":"737 Nicholson St",
    "sg:city":"Carlton North",
    "sg:classifiers":[
        {
            "category":"Professional",
            "subcategory":"Art Services",
            "type":"Services"
        }
    ],
    "sg:phone":"+61 3 9388 0407",
    "sg:postcode":"3054",
    "sg:province":"VIC",
    "sg:tags":[
        "product",
        "industrial",
        "designer"
    ],
    "wof:name":"i Design Pty Ltd",
    "wof:placetype":"venue"
},
  "geometry": {"coordinates":[144.97752380399999,-37.7820892334],"type":"Point"}
}