{
  "type": "Feature",
  "properties": {
    "addr:full":"Unit 4/ 6 Bluegum Cl Tuggerah NSW 2259",
    "addr:housenumber":"6",
    "addr:postcode":"2259",
    "addr:street":"Bluegum Cl",
    "iso:country":"AU",
    "sg:address":"Unit 4/ 6",
    "sg:city":"Bluegum Cl Tuggerah",
    "sg:classifiers":[
        {
            "category":"Landmark",
            "subcategory":"Scenic View",
            "type":"Public Place"
        }
    ],
    "sg:phone":"+61 2 4353 4474",
    "sg:postcode":"2259",
    "sg:province":"NSW",
    "sg:tags":[
        "staircase",
        "handrail"
    ],
    "wof:name":"Sturdy Stairs",
    "wof:placetype":"venue"
},
  "geometry": {"coordinates":[151.420410156,-33.3050003052],"type":"Point"}
}