{
  "type": "Feature",
  "properties": {
    "iso:country":"AU",
    "sg:address":"96 Innamincka Rd",
    "sg:city":"Greenmount",
    "sg:classifiers":[
        {
            "category":"Education",
            "subcategory":"School",
            "type":"Public Place"
        }
    ],
    "sg:phone":"+61 8 9255 1133",
    "sg:postcode":"6056",
    "sg:province":"WA",
    "wof:name":"St Anthony's",
    "wof:placetype":"venue"
},
  "geometry": {"coordinates":[116.04470825200001,-31.8968467712],"type":"Point"}
}