{
  "type": "Feature",
  "properties": {
    "iso:country":"AU",
    "sg:address":"Unit 3 8 Carnarvon Rd",
    "sg:city":"Gosford West",
    "sg:classifiers":[
        {
            "category":"Professional",
            "type":"Services"
        }
    ],
    "sg:phone":"+61 2 4323 9822",
    "sg:postcode":"2250",
    "sg:province":"NSW",
    "sg:tags":[
        "shop",
        "fitting"
    ],
    "wof:name":"Instyle Interiors",
    "wof:placetype":"venue"
},
  "geometry": {"coordinates":[151.31874084500001,-33.4200019836],"type":"Point"}
}