{
  "type": "Feature",
  "properties": {
    "addr:full":"PO Box 3266 Burleigh Town QLD 4220",
    "addr:postcode":"4220",
    "iso:country":"AU",
    "sg:address":"PO Box 3266",
    "sg:city":"Burleigh Town",
    "sg:classifiers":[
        {
            "category":"Home & Garden",
            "subcategory":"Carpets & Floor Coverings",
            "type":"Retail Goods"
        }
    ],
    "sg:phone":"+61 7 5522 0882",
    "sg:postcode":"4220",
    "sg:province":"QLD",
    "sg:tags":[
        "wood"
    ],
    "wof:name":"Ablaze Installations & Maintenance",
    "wof:placetype":"venue"
},
  "geometry": {"coordinates":[153.44102477999999,-28.0978603363],"type":"Point"}
}