{
  "type": "Feature",
  "properties": {
    "iso:country":"AU",
    "sg:address":"Lvl 1/ 351- 353 Elizabeth St",
    "sg:city":"Melbourne",
    "sg:classifiers":[
        {
            "category":"Professional",
            "subcategory":"Management & Consulting",
            "type":"Services"
        }
    ],
    "sg:phone":"+61 3 9642 4090",
    "sg:postcode":"3000",
    "sg:province":"VIC",
    "sg:tags":[
        "consultant"
    ],
    "wof:name":"Uncommon Sense",
    "wof:placetype":"venue"
},
  "geometry": {"coordinates":[144.96124267600001,-37.8104286194],"type":"Point"}
}