{
  "type": "Feature",
  "properties": {
    "addr:full":"246 River Ave Merbein VIC 3505",
    "addr:housenumber":"246",
    "addr:postcode":"3505",
    "addr:street":"River Ave",
    "iso:country":"AU",
    "sg:address":"246 River Ave",
    "sg:city":"Merbein",
    "sg:classifiers":[
        {
            "category":"Building & Trades",
            "subcategory":"Landscaping Services",
            "type":"Services"
        }
    ],
    "sg:phone":"+61 3 5025 2120",
    "sg:postcode":"3505",
    "sg:province":"VIC",
    "sg:tags":[
        "horticultural",
        "consultant"
    ],
    "wof:name":"Merbein Vine Nursery",
    "wof:placetype":"venue"
},
  "geometry": {"coordinates":[142.07389831500001,-34.1760406494],"type":"Point"}
}