{
  "type": "Feature",
  "properties": {
    "iso:country":"AU",
    "sg:address":"29 Darcy La",
    "sg:city":"Kalgoorlie",
    "sg:classifiers":[
        {
            "category":"Manufacturing",
            "subcategory":"Motor Vehicles & Parts",
            "type":"Manufacturing & Wholesale Goods"
        }
    ],
    "sg:phone":"+61 8 9091 2700",
    "sg:postcode":"6430",
    "sg:province":"WA",
    "sg:tags":[
        "engine",
        "equipment",
        "diesel"
    ],
    "wof:name":"Deutz",
    "wof:placetype":"venue"
},
  "geometry": {"coordinates":[121.434120178,-30.7801895142],"type":"Point"}
}