{
  "type": "Feature",
  "properties": {
    "addr:full":"Lyons Pl Lyons ACT 2606",
    "addr:postcode":"2606",
    "addr:street":"Pl",
    "iso:country":"AU",
    "sg:address":"Lyons Pl",
    "sg:city":"Lyons",
    "sg:classifiers":[
        {
            "category":"Banks & Credit Unions",
            "subcategory":"Financial Services",
            "type":"Services"
        }
    ],
    "sg:phone":"+61 2 6285 3944",
    "sg:postcode":"2606",
    "sg:province":"ACT",
    "sg:tags":[
        "annuity",
        "rollover",
        "superannuation",
        "consultant"
    ],
    "wof:name":"Brammall Financial",
    "wof:placetype":"venue"
},
  "geometry": {"coordinates":[149.076934814,-35.3391609192],"type":"Point"}
}