{
  "type": "Feature",
  "properties": {
    "iso:country":"AU",
    "sg:address":"487 Princes Hwy",
    "sg:city":"Kirrawee",
    "sg:classifiers":[
        {
            "category":"Autos & Motor Vehicles",
            "subcategory":"Fuel & Gas Station",
            "type":"Retail Goods"
        }
    ],
    "sg:phone":"+61 2 9521 4225",
    "sg:postcode":"2232",
    "sg:province":"NSW",
    "wof:name":"Cheapa Petrol",
    "wof:placetype":"venue"
},
  "geometry": {"coordinates":[151.08087158199999,-34.0293502808],"type":"Point"}
}