{
  "type": "Feature",
  "properties": {
    "addr:full":"1422 New Cleveland Rd Capalaba QLD 4157",
    "addr:housenumber":"1422",
    "addr:postcode":"4157",
    "addr:street":"New Cleveland Rd",
    "iso:country":"AU",
    "sg:address":"1422 New Cleveland Rd",
    "sg:city":"Capalaba",
    "sg:classifiers":[
        {
            "category":"Building & Trades",
            "subcategory":"Construction",
            "type":"Services"
        }
    ],
    "sg:phone":"+61 7 3390 1923",
    "sg:postcode":"4157",
    "sg:province":"QLD",
    "sg:tags":[
        "fencing",
        "contractor"
    ],
    "wof:name":"Forever Fencing Queensland",
    "wof:placetype":"venue"
},
  "geometry": {"coordinates":[153.179443359,-27.5118122101],"type":"Point"}
}