{
  "type": "Feature",
  "properties": {
    "addr:full":"88 Woods Rd Sefton NSW 2162",
    "addr:housenumber":"88",
    "addr:postcode":"2162",
    "addr:street":"Woods Rd",
    "iso:country":"AU",
    "sg:address":"88 Woods Rd",
    "sg:city":"Sefton",
    "sg:classifiers":[
        {
            "category":"Utilities",
            "subcategory":"Electric",
            "type":"Services"
        }
    ],
    "sg:phone":"+61 408 971 228",
    "sg:postcode":"2162",
    "sg:province":"NSW",
    "sg:tags":[
        "electrical",
        "contractor"
    ],
    "wof:name":"CVS Electrical Services",
    "wof:placetype":"venue"
},
  "geometry": {"coordinates":[151.01400756800001,-33.8946075439],"type":"Point"}
}