{
  "type": "Feature",
  "properties": {
    "iso:country":"AU",
    "sg:address":"23 Fischer St",
    "sg:city":"Lalor",
    "sg:classifiers":[
        {
            "category":"Building & Trades",
            "subcategory":"Construction",
            "type":"Services"
        }
    ],
    "sg:phone":"+61 438 100 376",
    "sg:postcode":"3075",
    "sg:province":"VIC",
    "sg:tags":[
        "earth",
        "excavating",
        "moving",
        "contractor"
    ],
    "wof:name":"Extreme Earthworks",
    "wof:placetype":"venue"
},
  "geometry": {"coordinates":[144.953735352,-37.7347297668],"type":"Point"}
}