{
  "type": "Feature",
  "properties": {
    "iso:country":"AU",
    "sg:address":"24 Hargraves Pl",
    "sg:city":"Wetherill Park",
    "sg:classifiers":[
        {
            "category":"Manufacturing",
            "subcategory":"Metals",
            "type":"Manufacturing & Wholesale Goods"
        }
    ],
    "sg:phone":"+61 2 9725 2844",
    "sg:postcode":"2164",
    "sg:province":"NSW",
    "sg:tags":[
        "fabricator",
        "aluminium"
    ],
    "wof:name":"Abstract Aluminium and Glazing Co.",
    "wof:placetype":"venue"
},
  "geometry": {"coordinates":[150.899734497,-33.8428611755],"type":"Point"}
}