{
  "type": "Feature",
  "properties": {
    "addr:full":"208 Waverley Rd Mt Waverley VIC 3149",
    "addr:housenumber":"208",
    "addr:postcode":"3149",
    "addr:street":"Waverley Rd",
    "iso:country":"AU",
    "sg:address":"208 Waverley Rd",
    "sg:city":"Mt Waverley",
    "sg:classifiers":[
        {
            "category":"Retail",
            "subcategory":"Auto Repair",
            "type":"Services"
        }
    ],
    "sg:phone":"+61 3 9807 8842",
    "sg:postcode":"3149",
    "sg:province":"VIC",
    "sg:tags":[
        "repairer",
        "motor",
        "engineer"
    ],
    "wof:name":"Chapel Street Automotive",
    "wof:placetype":"venue"
},
  "geometry": {"coordinates":[145.124343872,-37.8844490051],"type":"Point"}
}