{
  "type": "Feature",
  "properties": {
    "addr:full":"10 Hutton St Osborne Park WA 6017",
    "addr:housenumber":"10",
    "addr:postcode":"6017",
    "addr:street":"Hutton St",
    "iso:country":"AU",
    "sg:address":"10 Hutton St",
    "sg:city":"Osborne Park",
    "sg:classifiers":[
        {
            "category":"Fast Food",
            "type":"Food & Drink"
        }
    ],
    "sg:phone":"+61 8 9444 4195",
    "sg:postcode":"6017",
    "sg:province":"WA",
    "sg:tags":[
        "away",
        "take"
    ],
    "wof:name":"Mainstream Diner",
    "wof:placetype":"venue"
},
  "geometry": {"coordinates":[115.817398071,-31.9042663574],"type":"Point"}
}