{
  "type": "Feature",
  "properties": {
    "addr:full":"1 Willoughby Rd Crows Nest NSW 2065",
    "addr:housenumber":"1",
    "addr:postcode":"2065",
    "addr:street":"Willoughby Rd",
    "iso:country":"AU",
    "sg:address":"1 Willoughby Rd",
    "sg:city":"Crows Nest",
    "sg:classifiers":[
        {
            "category":"Travel",
            "subcategory":"Hotels & Motels",
            "type":"Entertainment"
        }
    ],
    "sg:phone":"+61 2 9436 4887",
    "sg:postcode":"2065",
    "sg:province":"NSW",
    "sg:tags":[
        "pub"
    ],
    "wof:name":"Crows Nest Hotel",
    "wof:placetype":"venue"
},
  "geometry": {"coordinates":[151.201049805,-33.8275489807],"type":"Point"}
}