{
  "type": "Feature",
  "properties": {
    "iso:country":"AU",
    "sg:address":"Bombala St",
    "sg:city":"Delegate",
    "sg:classifiers":[
        {
            "category":"Sports & Exercise",
            "subcategory":"Golf",
            "type":"Entertainment"
        }
    ],
    "sg:phone":"+61 2 6458 8169",
    "sg:postcode":"2633",
    "sg:province":"NSW",
    "sg:tags":[
        "club"
    ],
    "wof:name":"Delegate Country Club Ltd",
    "wof:placetype":"venue"
},
  "geometry": {"coordinates":[148.93890380900001,-37.044254303],"type":"Point"}
}