{
  "type": "Feature",
  "properties": {
    "addr:full":"37 King St Heathcote NSW 2233",
    "addr:housenumber":"37",
    "addr:postcode":"2233",
    "addr:street":"King St",
    "iso:country":"AU",
    "sg:address":"37 King St",
    "sg:city":"Heathcote",
    "sg:classifiers":[
        {
            "category":"Health Services",
            "subcategory":"Health Practitioner",
            "type":"Services"
        }
    ],
    "sg:phone":"+61 2 9520 0877",
    "sg:postcode":"2233",
    "sg:province":"NSW",
    "sg:tags":[
        "alternative"
    ],
    "wof:name":"Lidia Pascale",
    "wof:placetype":"venue"
},
  "geometry": {"coordinates":[151.00477600100001,-34.0823554993],"type":"Point"}
}