{
  "type": "Feature",
  "properties": {
    "addr:full":"46 Lyon Rd Rosanna East VIC 3084",
    "addr:housenumber":"46",
    "addr:postcode":"3084",
    "addr:street":"Lyon Rd",
    "iso:country":"AU",
    "sg:address":"46 Lyon Rd",
    "sg:city":"Rosanna East",
    "sg:classifiers":[
        {
            "category":"Home & Garden",
            "subcategory":"Carpets & Floor Coverings",
            "type":"Retail Goods"
        }
    ],
    "sg:phone":"+61 412 557 893",
    "sg:postcode":"3084",
    "sg:province":"VIC",
    "sg:tags":[
        "tile",
        "wall",
        "layer"
    ],
    "wof:name":"Como Tilers",
    "wof:placetype":"venue"
},
  "geometry": {"coordinates":[145.085205078,-37.7359771729],"type":"Point"}
}