{
  "type": "Feature",
  "properties": {
    "iso:country":"AU",
    "sg:address":"255 Plenty River Drv",
    "sg:city":"Greensborough",
    "sg:classifiers":[
        {
            "category":"Retail",
            "subcategory":"Auto Repair",
            "type":"Services"
        }
    ],
    "sg:phone":"+61 3 9435 6654",
    "sg:postcode":"3088",
    "sg:province":"VIC",
    "sg:tags":[
        "body",
        "motor",
        "trimmer"
    ],
    "wof:name":"Newell Autotrim",
    "wof:placetype":"venue"
},
  "geometry": {"coordinates":[145.11444091800001,-37.6828231812],"type":"Point"}
}