{
  "type": "Feature",
  "properties": {
    "addr:full":"7 Marco Crs Newton SA 5074",
    "addr:housenumber":"7",
    "addr:postcode":"5074",
    "addr:street":"Marco Crs",
    "iso:country":"AU",
    "sg:address":"7 Marco Crs",
    "sg:city":"Newton",
    "sg:classifiers":[
        {
            "category":"Personal",
            "subcategory":"Beauty Salon",
            "type":"Services"
        }
    ],
    "sg:phone":"+61 8 8336 3495",
    "sg:postcode":"5074",
    "sg:province":"SA",
    "sg:tags":[
        "hairdresser"
    ],
    "wof:name":"Simply For Men Hair Designs",
    "wof:placetype":"venue"
},
  "geometry": {"coordinates":[138.682495117,-34.8811416626],"type":"Point"}
}