{
  "type": "Feature",
  "properties": {
    "addr:full":"653 Beaufort St Mt Lawley WA 6050",
    "addr:housenumber":"653",
    "addr:postcode":"6050",
    "addr:street":"Beaufort St",
    "iso:country":"AU",
    "sg:address":"653 Beaufort St",
    "sg:city":"Mt Lawley",
    "sg:classifiers":[
        {
            "category":"Shopping",
            "subcategory":"Clothing, Apparel, & Fashions",
            "type":"Retail Goods"
        }
    ],
    "sg:phone":"+61 8 9272 2633",
    "sg:postcode":"6050",
    "sg:province":"WA",
    "sg:tags":[
        "menswear"
    ],
    "wof:name":"Jack Clothing",
    "wof:placetype":"venue"
},
  "geometry": {"coordinates":[115.868537903,-31.9404678345],"type":"Point"}
}