{
  "type": "Feature",
  "properties": {
    "addr:full":"22 Powers Rd Seven Hills NSW 2147",
    "addr:housenumber":"22",
    "addr:postcode":"2147",
    "addr:street":"Powers Rd",
    "iso:country":"AU",
    "sg:address":"22 Powers Rd",
    "sg:city":"Seven Hills",
    "sg:classifiers":[
        {
            "category":"Professional",
            "subcategory":"Accounting & Tax Preparation",
            "type":"Services"
        }
    ],
    "sg:phone":"+61 2 9624 2888",
    "sg:postcode":"2147",
    "sg:province":"NSW",
    "sg:tags":[
        "accountant",
        "auditor"
    ],
    "wof:name":"Parramatta Taxation Services Pty Ltd",
    "wof:placetype":"venue"
},
  "geometry": {"coordinates":[150.95726013199999,-33.7792205811],"type":"Point"}
}