{
  "type": "Feature",
  "properties": {
    "iso:country":"AU",
    "sg:address":"267 King St",
    "sg:city":"Newtown",
    "sg:classifiers":[
        {
            "category":"Utilities",
            "subcategory":"Mobile Phone",
            "type":"Services"
        }
    ],
    "sg:phone":"+61 2 9557 4858",
    "sg:postcode":"2042",
    "sg:province":"NSW",
    "sg:tags":[
        "repair",
        "telephone"
    ],
    "wof:name":"Frankes Fones",
    "wof:placetype":"venue"
},
  "geometry": {"coordinates":[151.180267,-33.89616],"type":"Point"}
}