{
  "type": "Feature",
  "properties": {
    "iso:country":"AU",
    "sg:address":"Lot 11 Sunnybanks Crt",
    "sg:city":"Bumberrah",
    "sg:classifiers":[
        {
            "category":"Personal",
            "type":"Services"
        }
    ],
    "sg:phone":"+61 3 5156 4005",
    "sg:postcode":"3902",
    "sg:province":"VIC",
    "sg:tags":[
        "gift"
    ],
    "wof:name":"True Hardwood",
    "wof:placetype":"venue"
},
  "geometry": {"coordinates":[147.83161926299999,-37.782043457],"type":"Point"}
}