{
  "type": "Feature",
  "properties": {
    "addr:full":"Shed1/ 24 Separation St North Geelong VIC 3215",
    "addr:postcode":"3215",
    "addr:street":"Separation St",
    "iso:country":"AU",
    "sg:address":"Shed1/ 24 Separation St",
    "sg:city":"North Geelong",
    "sg:classifiers":[
        {
            "category":"Manufacturing",
            "subcategory":"Motor Vehicles & Parts",
            "type":"Manufacturing & Wholesale Goods"
        }
    ],
    "sg:phone":"+61 3 5278 6228",
    "sg:postcode":"3215",
    "sg:province":"VIC",
    "sg:tags":[
        "replacement"
    ],
    "wof:name":"Bob Carters Auto Centre",
    "wof:placetype":"venue"
},
  "geometry": {"coordinates":[144.34927368199999,-38.1113090515],"type":"Point"}
}