{
  "type": "Feature",
  "properties": {
    "addr:full":"Charthouse Shopping Centre Charthouse St Waikiki WA 6169",
    "addr:postcode":"6169",
    "addr:street":"Charthouse St",
    "iso:country":"AU",
    "sg:address":"Charthouse Shopping Centre Charthouse St",
    "sg:city":"Waikiki",
    "sg:classifiers":[
        {
            "category":"Banks & Credit Unions",
            "subcategory":"Investment Brokerage",
            "type":"Services"
        }
    ],
    "sg:phone":"+61 8 9314 6688",
    "sg:postcode":"6169",
    "sg:province":"WA",
    "sg:tags":[
        "management",
        "property"
    ],
    "wof:name":"Charthouse Shopping Centre",
    "wof:placetype":"venue"
},
  "geometry": {"coordinates":[115.750259,-32.318348],"type":"Point"}
}