{
  "type": "Feature",
  "properties": {
    "iso:country":"AU",
    "sg:address":"1635 Dandenong-Hastings Rd",
    "sg:city":"Pearcedale",
    "sg:classifiers":[
        {
            "category":"Mining & Drilling",
            "type":"Manufacturing & Wholesale Goods"
        }
    ],
    "sg:phone":"+61 3 5978 6999",
    "sg:postcode":"3912",
    "sg:province":"VIC",
    "sg:tags":[
        "boring",
        "contractor"
    ],
    "wof:name":"B & R Boring",
    "wof:placetype":"venue"
},
  "geometry": {"coordinates":[145.217163086,-38.1931877136],"type":"Point"}
}