{
  "type": "Feature",
  "properties": {
    "addr:full":"Unit 7 442 Metcalfe Rd Ferndale WA 6148",
    "addr:housenumber":"442",
    "addr:postcode":"6148",
    "addr:street":"Metcalfe Rd",
    "iso:country":"AU",
    "sg:address":"Unit 7 442 Metcalfe Rd",
    "sg:city":"Ferndale",
    "sg:classifiers":[
        {
            "category":"Professional",
            "subcategory":"Accounting & Tax Preparation",
            "type":"Services"
        }
    ],
    "sg:phone":"+61 411 036 750",
    "sg:postcode":"6148",
    "sg:province":"WA",
    "sg:tags":[
        "jukebox"
    ],
    "wof:name":"Southside Juke Box Hire",
    "wof:placetype":"venue"
},
  "geometry": {"coordinates":[115.925888,-32.0355],"type":"Point"}
}