{
  "type": "Feature",
  "properties": {
    "iso:country":"AU",
    "sg:address":"335 Gorge Rd",
    "sg:city":"Athelstone",
    "sg:classifiers":[
        {
            "category":"Health Services",
            "subcategory":"Health Practitioner",
            "type":"Services"
        }
    ],
    "sg:phone":"+61 409 270 877",
    "sg:postcode":"5076",
    "sg:province":"SA",
    "sg:tags":[
        "psychologist"
    ],
    "wof:name":"Morton Kate",
    "wof:placetype":"venue"
},
  "geometry": {"coordinates":[138.704681397,-34.8693161011],"type":"Point"}
}