{
  "type": "Feature",
  "properties": {
    "addr:full":"2 Elsum Ave Bayswater North VIC 3153",
    "addr:housenumber":"2",
    "addr:postcode":"3153",
    "addr:street":"Elsum Ave",
    "iso:country":"AU",
    "sg:address":"2 Elsum Ave",
    "sg:city":"Bayswater North",
    "sg:classifiers":[
        {
            "category":"Manufacturing",
            "subcategory":"Rubber & Plastics",
            "type":"Manufacturing & Wholesale Goods"
        }
    ],
    "sg:phone":"+61 3 9720 0246",
    "sg:postcode":"3153",
    "sg:province":"VIC",
    "sg:tags":[
        "moulders"
    ],
    "wof:name":"Plastivac",
    "wof:placetype":"venue"
},
  "geometry": {"coordinates":[145.27967834500001,-37.8249206543],"type":"Point"}
}