{
  "type": "Feature",
  "properties": {
    "iso:country":"AU",
    "sg:address":"PO Box 955",
    "sg:city":", Wahgunyah",
    "sg:classifiers":[
        {
            "category":"Home & Garden",
            "subcategory":"Building Materials",
            "type":"Retail Goods"
        }
    ],
    "sg:phone":"+61 416 019 433",
    "sg:postcode":"3687",
    "sg:province":"VIC",
    "sg:tags":[
        "lawn",
        "cutting",
        "maintenance"
    ],
    "wof:name":"Ground-Cover Property Maintenance",
    "wof:placetype":"venue"
},
  "geometry": {"coordinates":[146.419678,-36.002869],"type":"Point"}
}