{
  "type": "Feature",
  "properties": {
    "iso:country":"AU",
    "sg:address":"10 Belah Rd",
    "sg:city":"Port Macquarie",
    "sg:classifiers":[
        {
            "category":"Banks & Credit Unions",
            "subcategory":"Bank",
            "type":"Services"
        }
    ],
    "sg:phone":"+61 2 6581 1144",
    "sg:postcode":"2444",
    "sg:province":"NSW",
    "sg:tags":[
        "concrete",
        "reinforcement"
    ],
    "wof:name":"OneSteel Reinforcing",
    "wof:placetype":"venue"
},
  "geometry": {"coordinates":[152.885986,-31.45188],"type":"Point"}
}