{
  "type": "Feature",
  "properties": {
    "addr:full":"Kanwal Village Wallarah Rd Kanwal NSW 2259",
    "addr:postcode":"2259",
    "addr:street":"Wallarah Rd",
    "iso:country":"AU",
    "sg:address":"Kanwal Village Wallarah Rd",
    "sg:city":"Kanwal",
    "sg:classifiers":[
        {
            "category":"Personal",
            "subcategory":"Beauty Salon",
            "type":"Services"
        }
    ],
    "sg:phone":"+61 2 4392 6922",
    "sg:postcode":"2259",
    "sg:province":"NSW",
    "sg:tags":[
        "hairdresser"
    ],
    "wof:name":"Kimz Kutz Family Hair Care",
    "wof:placetype":"venue"
},
  "geometry": {"coordinates":[151.490112305,-33.2523002625],"type":"Point"}
}