{
  "type": "Feature",
  "properties": {
    "addr:full":"Westbase Industrial Building 75 Ashley St Braybrook VIC 3019",
    "addr:housenumber":"75",
    "addr:postcode":"3019",
    "addr:street":"Ashley St",
    "iso:country":"AU",
    "sg:address":"Westbase Industrial Building 75 Ashley St",
    "sg:city":"Braybrook",
    "sg:classifiers":[
        {
            "category":"Organizations",
            "subcategory":"Non-profit Organization",
            "type":"Services"
        }
    ],
    "sg:phone":"+61 3 9362 7344",
    "sg:postcode":"3019",
    "sg:province":"VIC",
    "sg:tags":[
        "support",
        "disability",
        "organisation"
    ],
    "wof:name":"Foster Grandparent Scheme (Victoria) Inc",
    "wof:placetype":"venue"
},
  "geometry": {"coordinates":[144.86346435600001,-37.7911491394],"type":"Point"}
}