{
  "type": "Feature",
  "properties": {
    "addr:full":"6 Gwandalan Rd Padstow NSW 2211",
    "addr:housenumber":"6",
    "addr:postcode":"2211",
    "addr:street":"Gwandalan Rd",
    "iso:country":"AU",
    "sg:address":"6 Gwandalan Rd",
    "sg:city":"Padstow",
    "sg:classifiers":[
        {
            "category":"Education",
            "subcategory":"Kindergarten",
            "type":"Public Place"
        }
    ],
    "sg:phone":"+61 2 9773 7380",
    "sg:postcode":"2211",
    "sg:province":"NSW",
    "sg:tags":[
        "pre-schools"
    ],
    "wof:name":"Kim's Kindy",
    "wof:placetype":"venue"
},
  "geometry": {"coordinates":[151.02879300000001,-33.942745],"type":"Point"}
}