{
  "type": "Feature",
  "properties": {
    "addr:full":"67 Lr West Burleigh Rd Burleigh Heads QLD 4220",
    "addr:housenumber":"67",
    "addr:postcode":"4220",
    "addr:street":"Lr West Burleigh Rd",
    "iso:country":"AU",
    "sg:address":"67 Lr West Burleigh Rd",
    "sg:city":"Burleigh Heads",
    "sg:classifiers":[
        {
            "category":"Retail",
            "subcategory":"Auto Repair",
            "type":"Services"
        }
    ],
    "sg:phone":"+61 7 5535 2288",
    "sg:postcode":"4220",
    "sg:province":"QLD",
    "sg:tags":[
        "clutch",
        "brake"
    ],
    "wof:name":"Goodyear Auto Service Centre-Tyre Guys",
    "wof:placetype":"venue"
},
  "geometry": {"coordinates":[153.44526672399999,-28.0911102295],"type":"Point"}
}