{
  "type": "Feature",
  "properties": {
    "addr:full":"Masonic Lodge 56 Cherry St Ballina NSW 2478",
    "addr:housenumber":"56",
    "addr:postcode":"2478",
    "addr:street":"Cherry St",
    "iso:country":"AU",
    "sg:address":"Masonic Lodge 56 Cherry St",
    "sg:city":"Ballina",
    "sg:classifiers":[
        {
            "category":"Arts & Performance",
            "subcategory":"Dance",
            "type":"Entertainment"
        }
    ],
    "sg:phone":"+61 412 618 868",
    "sg:postcode":"2478",
    "sg:province":"NSW",
    "sg:tags":[
        "theatrical",
        "ballet",
        "tuition"
    ],
    "wof:name":"Northern Rivers Dance Studios",
    "wof:placetype":"venue"
},
  "geometry": {"coordinates":[153.56146240199999,-28.8706035614],"type":"Point"}
}