{
  "type": "Feature",
  "properties": {
    "addr:full":"Fulford Rd Wonga Park VIC 3115",
    "addr:postcode":"3115",
    "addr:street":"Fulford Rd",
    "iso:country":"AU",
    "sg:address":"Fulford Rd",
    "sg:city":"Wonga Park",
    "sg:classifiers":[
        {
            "category":"Farming",
            "subcategory":"Vineyard",
            "type":"Manufacturing & Wholesale Goods"
        }
    ],
    "sg:phone":"+61 3 9722 1304",
    "sg:postcode":"3115",
    "sg:province":"VIC",
    "sg:tags":[
        "winery"
    ],
    "wof:name":"Kellybrook Winery",
    "wof:placetype":"venue"
},
  "geometry": {"coordinates":[145.27786254899999,-37.727104187],"type":"Point"}
}