{
  "type": "Feature",
  "properties": {
    "addr:full":"61 Machan St Machans Beach QLD 4878",
    "addr:housenumber":"61",
    "addr:postcode":"4878",
    "addr:street":"Machan St",
    "iso:country":"AU",
    "sg:address":"61 Machan St",
    "sg:city":"Machans Beach",
    "sg:classifiers":[
        {
            "category":"Education",
            "subcategory":"School",
            "type":"Public Place"
        }
    ],
    "sg:phone":"+61 7 4055 9410",
    "sg:postcode":"4878",
    "sg:province":"QLD",
    "sg:tags":[
        "state",
        "except",
        "nsw"
    ],
    "wof:name":"Machans Beach Primary School",
    "wof:placetype":"venue"
},
  "geometry": {"coordinates":[145.74551391599999,-16.8522834778],"type":"Point"}
}