{
  "type": "Feature",
  "properties": {
    "addr:full":"21 Ellerslie St Premer NSW 2381",
    "addr:housenumber":"21",
    "addr:postcode":"2381",
    "addr:street":"Ellerslie St",
    "iso:country":"AU",
    "sg:address":"21 Ellerslie St",
    "sg:city":"Premer",
    "sg:classifiers":[
        {
            "category":"Travel",
            "subcategory":"Hotels & Motels",
            "type":"Entertainment"
        }
    ],
    "sg:phone":"+61 2 6744 2106",
    "sg:postcode":"2381",
    "sg:province":"NSW",
    "sg:tags":[
        "pub"
    ],
    "wof:name":"Hotel Premer",
    "wof:placetype":"venue"
},
  "geometry": {"coordinates":[149.90179443400001,-31.4532566071],"type":"Point"}
}