{
  "type": "Feature",
  "properties": {
    "iso:country":"AU",
    "sg:address":"21- 25",
    "sg:city":"Venture Way Braeside",
    "sg:classifiers":[
        {
            "category":"Communications",
            "subcategory":"Film & Video Production",
            "type":"Services"
        }
    ],
    "sg:phone":"+61 3 9587 4444",
    "sg:postcode":"3195",
    "sg:province":"VIC",
    "sg:tags":[
        "mirror"
    ],
    "wof:name":"Kwikfix Pty Ltd",
    "wof:placetype":"venue"
},
  "geometry": {"coordinates":[145.116622925,-37.9985809326],"type":"Point"}
}