{
  "type": "Feature",
  "properties": {
    "addr:full":"38 Great Western Hwy Valley Heights NSW 2777",
    "addr:housenumber":"38",
    "addr:postcode":"2777",
    "addr:street":"Great Western Hwy",
    "iso:country":"AU",
    "sg:address":"38 Great Western Hwy",
    "sg:city":"Valley Heights",
    "sg:classifiers":[
        {
            "category":"Building & Trades",
            "subcategory":"Construction",
            "type":"Services"
        }
    ],
    "sg:phone":"+61 2 4751 3838",
    "sg:postcode":"2777",
    "sg:province":"NSW",
    "sg:tags":[
        "pool",
        "swimming"
    ],
    "wof:name":"Phil Price Pools Pty Ltd",
    "wof:placetype":"venue"
},
  "geometry": {"coordinates":[150.58181762699999,-33.7023658752],"type":"Point"}
}