{
  "type": "Feature",
  "properties": {
    "iso:country":"AU",
    "sg:address":"Level 1 220 St",
    "sg:city":"Georges Tce Perth",
    "sg:classifiers":[
        {
            "category":"Professional",
            "subcategory":"Secretarial Services",
            "type":"Services"
        }
    ],
    "sg:phone":"+61 8 9321 7899",
    "sg:postcode":"6000",
    "sg:province":"WA",
    "sg:tags":[
        "typing"
    ],
    "wof:name":"Par Excellence",
    "wof:placetype":"venue"
},
  "geometry": {"coordinates":[115.85191345200001,-31.9530467987],"type":"Point"}
}