{
  "type": "Feature",
  "properties": {
    "addr:full":"8 Webber Pl Kings Langley NSW 2147",
    "addr:housenumber":"8",
    "addr:postcode":"2147",
    "addr:street":"Webber Pl",
    "iso:country":"AU",
    "sg:address":"8 Webber Pl",
    "sg:city":"Kings Langley",
    "sg:classifiers":[
        {
            "category":"Home & Garden",
            "subcategory":"Carpets & Floor Coverings",
            "type":"Retail Goods"
        }
    ],
    "sg:phone":"+61 2 9621 4485",
    "sg:postcode":"2147",
    "sg:province":"NSW",
    "sg:tags":[
        "layer",
        "planner"
    ],
    "wof:name":"Dixon's Floor Covering Service Pty Ltd",
    "wof:placetype":"venue"
},
  "geometry": {"coordinates":[150.91888427699999,-33.7404899597],"type":"Point"}
}