{
  "type": "Feature",
  "properties": {
    "addr:full":"41 Mittagang Rd Cooma NSW 2630",
    "addr:housenumber":"41",
    "addr:postcode":"2630",
    "addr:street":"Mittagang Rd",
    "iso:country":"AU",
    "sg:address":"41 Mittagang Rd",
    "sg:city":"Cooma",
    "sg:classifiers":[
        {
            "category":"Food & Beverages",
            "subcategory":"Groceries & Convenience Stores",
            "type":"Retail Goods"
        }
    ],
    "sg:phone":"+61 2 6452 4018",
    "sg:postcode":"2630",
    "sg:province":"NSW",
    "wof:name":"Cooma North Corner Store",
    "wof:placetype":"venue"
},
  "geometry": {"coordinates":[149.13154602,-36.2323493958],"type":"Point"}
}