{
  "type": "Feature",
  "properties": {
    "iso:country":"AU",
    "sg:address":"655 London Rd",
    "sg:city":"Chandler",
    "sg:classifiers":[
        {
            "category":"Building & Trades",
            "subcategory":"Construction",
            "type":"Services"
        }
    ],
    "sg:phone":"+61 7 3245 4407",
    "sg:postcode":"4155",
    "sg:province":"QLD",
    "sg:tags":[
        "earth",
        "excavating",
        "moving",
        "contractor"
    ],
    "wof:name":"B & E Mini Excavations",
    "wof:placetype":"venue"
},
  "geometry": {"coordinates":[153.15997314399999,-27.5033454895],"type":"Point"}
}