{
  "type": "Feature",
  "properties": {
    "addr:full":"2 Collins St Melbourne VIC 3000",
    "addr:housenumber":"2",
    "addr:postcode":"3000",
    "addr:street":"Collins St",
    "iso:country":"AU",
    "sg:address":"2 Collins St",
    "sg:city":"Melbourne",
    "sg:classifiers":[
        {
            "category":"Real Estate",
            "subcategory":"Architect",
            "type":"Services"
        }
    ],
    "sg:phone":"+61 3 9650 2827",
    "sg:postcode":"3000",
    "sg:province":"VIC",
    "wof:name":"Gribble John",
    "wof:placetype":"venue"
},
  "geometry": {"coordinates":[144.97381591800001,-37.8132171631],"type":"Point"}
}