{
  "type": "Feature",
  "properties": {
    "iso:country":"AU",
    "sg:address":"179 Clarendon St",
    "sg:city":"South Melbourne",
    "sg:classifiers":[
        {
            "category":"Restaurant",
            "type":"Food & Drink"
        }
    ],
    "sg:phone":"+61 3 9690 7588",
    "sg:postcode":"3205",
    "sg:province":"VIC",
    "wof:name":"Daimonji Japanese Restaurant",
    "wof:placetype":"venue"
},
  "geometry": {"coordinates":[144.95929,-37.829838],"type":"Point"}
}