{
  "type": "Feature",
  "properties": {
    "addr:full":"48 King William Rd Goodwood SA 5034",
    "addr:housenumber":"48",
    "addr:postcode":"5034",
    "addr:street":"King William Rd",
    "iso:country":"AU",
    "sg:address":"48 King William Rd",
    "sg:city":"Goodwood",
    "sg:classifiers":[
        {
            "category":"Health Services",
            "subcategory":"Doctor",
            "type":"Services"
        }
    ],
    "sg:phone":"+61 8 8273 5666",
    "sg:postcode":"5034",
    "sg:province":"SA",
    "sg:tags":[
        "medical",
        "practitioner"
    ],
    "wof:name":"Newcombe Graeme N",
    "wof:placetype":"venue"
},
  "geometry": {"coordinates":[138.59965515100001,-34.9513664246],"type":"Point"}
}