{
  "type": "Feature",
  "properties": {
    "addr:full":"182 Banks Drv St Clair NSW 2759",
    "addr:housenumber":"182",
    "addr:postcode":"2759",
    "addr:street":"Banks Drv",
    "iso:country":"AU",
    "sg:address":"182 Banks Drv",
    "sg:city":"St Clair",
    "sg:classifiers":[
        {
            "category":"Education",
            "subcategory":"School",
            "type":"Public Place"
        }
    ],
    "sg:phone":"+61 2 9670 6506",
    "sg:postcode":"2759",
    "sg:province":"NSW",
    "sg:tags":[
        "state",
        "-",
        "nsw"
    ],
    "wof:name":"Banks Public School",
    "wof:placetype":"venue"
},
  "geometry": {"coordinates":[150.77554321299999,-33.7950782776],"type":"Point"}
}