{
  "type": "Feature",
  "properties": {
    "addr:full":"Pitt St Stockton NSW 2295",
    "addr:postcode":"2295",
    "addr:street":"Pitt St",
    "iso:country":"AU",
    "sg:address":"Pitt St",
    "sg:city":"Stockton",
    "sg:classifiers":[
        {
            "category":"Cafe",
            "type":"Food & Drink"
        }
    ],
    "sg:phone":"+61 2 4928 4226",
    "sg:postcode":"2295",
    "sg:province":"NSW",
    "wof:name":"Stockton Beack Kiosk",
    "wof:placetype":"venue"
},
  "geometry": {"coordinates":[151.78793335,-32.9157142639],"type":"Point"}
}