{
  "type": "Feature",
  "properties": {
    "addr:full":"PO Box 10768 Southport QLD 4215",
    "addr:postcode":"4215",
    "iso:country":"AU",
    "sg:address":"PO Box 10768",
    "sg:city":"Southport",
    "sg:classifiers":[
        {
            "category":"Utilities",
            "subcategory":"Electric",
            "type":"Services"
        }
    ],
    "sg:phone":"+61 422 028 090",
    "sg:postcode":"4215",
    "sg:province":"QLD",
    "sg:tags":[
        "electrical",
        "contractor"
    ],
    "wof:name":"Bone & Wortmann Electrical",
    "wof:placetype":"venue"
},
  "geometry": {"coordinates":[153.415557861,-27.9655303955],"type":"Point"}
}