{
  "type": "Feature",
  "properties": {
    "addr:full":"Lot 1 Cundinup Rd Kirup WA 6251",
    "addr:postcode":"6251",
    "addr:street":"Cundinup Rd",
    "iso:country":"AU",
    "sg:address":"Lot 1 Cundinup Rd",
    "sg:city":"Kirup",
    "sg:classifiers":[
        {
            "category":"Arts & Performance",
            "subcategory":"Art Gallery",
            "type":"Entertainment"
        }
    ],
    "sg:phone":"+61 8 9731 6129",
    "sg:postcode":"6251",
    "sg:province":"WA",
    "wof:name":"African Legacy Gallery",
    "wof:placetype":"venue"
},
  "geometry": {"coordinates":[115.89372253400001,-33.7087593079],"type":"Point"}
}