{
  "type": "Feature",
  "properties": {
    "addr:full":"7 Daisy Ave Penshurst NSW 2222",
    "addr:housenumber":"7",
    "addr:postcode":"2222",
    "addr:street":"Daisy Ave",
    "iso:country":"AU",
    "sg:address":"7 Daisy Ave",
    "sg:city":"Penshurst",
    "sg:classifiers":[
        {
            "category":"Professional",
            "subcategory":"Engineering",
            "type":"Services"
        }
    ],
    "sg:phone":"+61 2 9580 3319",
    "sg:postcode":"2222",
    "sg:province":"NSW",
    "sg:tags":[
        "consulting",
        "engineer"
    ],
    "wof:name":"Mackenzie Roderick & Associates Pty Ltd",
    "wof:placetype":"venue"
},
  "geometry": {"coordinates":[151.09266662600001,-33.9676322937],"type":"Point"}
}