{
  "type": "Feature",
  "properties": {
    "iso:country":"AU",
    "sg:address":"50 Chamberlain Rd",
    "sg:city":"Bexley",
    "sg:classifiers":[
        {
            "category":"Professional",
            "subcategory":"Business Services",
            "type":"Services"
        }
    ],
    "sg:phone":"+61 2 9567 9961",
    "sg:postcode":"2207",
    "sg:province":"NSW",
    "sg:tags":[
        "drafting"
    ],
    "wof:name":"Yao's Architectural Design & Drafting",
    "wof:placetype":"venue"
},
  "geometry": {"coordinates":[151.122696,-33.944019],"type":"Point"}
}