{
  "type": "Feature",
  "properties": {
    "addr:full":"Lot 2 Craigeburn Rd Yuroke VIC 3063",
    "addr:postcode":"3063",
    "addr:street":"Craigeburn Rd",
    "iso:country":"AU",
    "sg:address":"Lot 2 Craigeburn Rd",
    "sg:city":"Yuroke",
    "sg:classifiers":[
        {
            "category":"Personal",
            "type":"Services"
        }
    ],
    "sg:phone":"+61 3 9333 1888",
    "sg:postcode":"3063",
    "sg:province":"VIC",
    "sg:tags":[
        "gift"
    ],
    "wof:name":"Bottle Bags R Us Pty Ltd",
    "wof:placetype":"venue"
},
  "geometry": {"coordinates":[144.876831055,-37.5893974304],"type":"Point"}
}