{
  "type": "Feature",
  "properties": {
    "addr:full":"109 Leichhardt St Spring Hill QLD 4000",
    "addr:housenumber":"109",
    "addr:postcode":"4000",
    "addr:street":"Leichhardt St",
    "iso:country":"AU",
    "sg:address":"109 Leichhardt St",
    "sg:city":"Spring Hill",
    "sg:classifiers":[
        {
            "category":"Professional",
            "subcategory":"Accounting & Tax Preparation",
            "type":"Services"
        }
    ],
    "sg:phone":"+61 7 3839 8135",
    "sg:postcode":"4000",
    "sg:province":"QLD",
    "sg:tags":[
        "accountant",
        "auditor"
    ],
    "wof:name":"Beer David & Co",
    "wof:placetype":"venue"
},
  "geometry": {"coordinates":[153.024490356,-27.4628410339],"type":"Point"}
}