{
  "type": "Feature",
  "properties": {
    "addr:full":"Level 5, 387 George St Sydney NSW 2000",
    "addr:housenumber":"387",
    "addr:postcode":"2000",
    "addr:street":"George St",
    "iso:country":"AU",
    "sg:address":"Level 5, 387 George St",
    "sg:city":"Sydney",
    "sg:classifiers":[
        {
            "category":"Travel",
            "subcategory":"Travel Agent",
            "type":"Entertainment"
        }
    ],
    "sg:phone":"+61 1300 667 277",
    "sg:postcode":"2000",
    "sg:province":"NSW",
    "sg:tags":[
        "tour",
        "holiday",
        "adventure"
    ],
    "wof:name":"Kumuka Worldwide",
    "wof:placetype":"venue"
},
  "geometry": {"coordinates":[151.20631408700001,-33.8694419861],"type":"Point"}
}