{
  "type": "Feature",
  "properties": {
    "addr:full":"17 Brindabella St Ruse NSW 2560",
    "addr:housenumber":"17",
    "addr:postcode":"2560",
    "addr:street":"Brindabella St",
    "iso:country":"AU",
    "sg:address":"17 Brindabella St",
    "sg:city":"Ruse",
    "sg:classifiers":[
        {
            "category":"Professional",
            "subcategory":"Printing & Photocopies",
            "type":"Services"
        }
    ],
    "sg:phone":"+61 406 603 764",
    "sg:postcode":"2560",
    "sg:province":"NSW",
    "sg:tags":[
        "photocopying"
    ],
    "wof:name":"R&H Office Technology",
    "wof:placetype":"venue"
},
  "geometry": {"coordinates":[150.84844970699999,-34.0719184875],"type":"Point"}
}