{
  "type": "Feature",
  "properties": {
    "addr:full":"Higgins Pl Higgins ACT 2615",
    "addr:postcode":"2615",
    "addr:street":"Higgins Pl Higgins",
    "iso:country":"AU",
    "sg:address":"Higgins Pl",
    "sg:city":"Higgins",
    "sg:classifiers":[
        {
            "category":"Food & Beverages",
            "subcategory":"Liquor & Beverages",
            "type":"Retail Goods"
        }
    ],
    "sg:phone":"+61 2 6254 2371",
    "sg:postcode":"2615",
    "sg:province":"ACT",
    "sg:tags":[
        "store"
    ],
    "wof:name":"Local Liquor",
    "wof:placetype":"venue"
},
  "geometry": {"coordinates":[149.02708435100001,-35.2317085266],"type":"Point"}
}