{
  "type": "Feature",
  "properties": {
    "iso:country":"AU",
    "sg:address":"39 Ladera Drv",
    "sg:city":"Copacabana",
    "sg:classifiers":[
        {
            "category":"Building & Trades",
            "subcategory":"Construction",
            "type":"Services"
        }
    ],
    "sg:phone":"+61 2 4382 1560",
    "sg:postcode":"2251",
    "sg:province":"NSW",
    "sg:tags":[
        "concrete",
        "contractor"
    ],
    "wof:name":"Kelly D E",
    "wof:placetype":"venue"
},
  "geometry": {"coordinates":[151.426269531,-33.4881896973],"type":"Point"}
}