{
  "type": "Feature",
  "properties": {
    "iso:country":"AU",
    "sg:address":"29 Roberna St",
    "sg:city":"Moorabbin",
    "sg:classifiers":[
        {
            "category":"Manufacturing",
            "subcategory":"Chemicals & Compounds",
            "type":"Manufacturing & Wholesale Goods"
        }
    ],
    "sg:phone":"+61 3 9553 5662",
    "sg:postcode":"3189",
    "sg:province":"VIC",
    "sg:tags":[
        "electroplating"
    ],
    "wof:name":"Applied Chrome Deposits Pty Ltd",
    "wof:placetype":"venue"
},
  "geometry": {"coordinates":[145.06756591800001,-37.9454612732],"type":"Point"}
}