{
  "type": "Feature",
  "properties": {
    "iso:country":"AU",
    "sg:address":"5 Currie St",
    "sg:city":"Adelaide",
    "sg:classifiers":[
        {
            "category":"Professional",
            "subcategory":"Computer Services",
            "type":"Services"
        }
    ],
    "sg:phone":"+61 8 8415 5141",
    "sg:postcode":"5000",
    "sg:province":"SA",
    "sg:tags":[
        "consultant",
        "system"
    ],
    "wof:name":"Independent Test Services (Australia) Pty Ltd",
    "wof:placetype":"venue"
},
  "geometry": {"coordinates":[138.59927368199999,-34.9244728088],"type":"Point"}
}