{
  "type": "Feature",
  "properties": {
    "addr:full":"39 Ilya St MacGregor QLD 4109",
    "addr:housenumber":"39",
    "addr:postcode":"4109",
    "addr:street":"Ilya St",
    "iso:country":"AU",
    "sg:address":"39 Ilya St",
    "sg:city":"MacGregor",
    "sg:classifiers":[
        {
            "category":"Education",
            "subcategory":"Music School",
            "type":"Public Place"
        }
    ],
    "sg:phone":"+61 7 3420 3630",
    "sg:postcode":"4109",
    "sg:province":"QLD",
    "sg:tags":[
        "teacher"
    ],
    "wof:name":"A.A.C. Australian Accordion Centre",
    "wof:placetype":"venue"
},
  "geometry": {"coordinates":[153.07098388700001,-27.5567264557],"type":"Point"}
}