{
  "type": "Feature",
  "properties": {
    "addr:full":"17 George St Highett VIC 3190",
    "addr:housenumber":"17",
    "addr:postcode":"3190",
    "addr:street":"George St",
    "iso:country":"AU",
    "sg:address":"17 George St",
    "sg:city":"Highett",
    "sg:classifiers":[
        {
            "category":"Shopping",
            "subcategory":"Party Supplies",
            "type":"Retail Goods"
        }
    ],
    "sg:phone":"+61 3 9532 2349",
    "sg:postcode":"3190",
    "sg:province":"VIC",
    "sg:tags":[
        "selling",
        "plan"
    ],
    "wof:name":"Tri Nature jene&#039; Skin Care",
    "wof:placetype":"venue"
},
  "geometry": {"coordinates":[145.03228759800001,-37.9485092163],"type":"Point"}
}