{
  "type": "Feature",
  "properties": {
    "iso:country":"AU",
    "sg:address":"4/ 7000 Pacific hey Hwy",
    "sg:city":"Upper Coomera",
    "sg:classifiers":[
        {
            "category":"Building & Trades",
            "subcategory":"Pest Control",
            "type":"Services"
        }
    ],
    "sg:phone":"+61 419 013 973",
    "sg:postcode":"4209",
    "sg:province":"QLD",
    "wof:name":"Smartway Pest Management",
    "wof:placetype":"venue"
},
  "geometry": {"coordinates":[153.31643676799999,-27.8990020752],"type":"Point"}
}