{
  "type": "Feature",
  "properties": {
    "addr:full":"4 Kay St Murwillumbah NSW 2484",
    "addr:housenumber":"4",
    "addr:postcode":"2484",
    "addr:street":"Kay St",
    "iso:country":"AU",
    "sg:address":"4 Kay St",
    "sg:city":"Murwillumbah",
    "sg:classifiers":[
        {
            "category":"Retail",
            "subcategory":"Storage",
            "type":"Services"
        }
    ],
    "sg:phone":"+61 1800 454 131",
    "sg:postcode":"2484",
    "sg:province":"NSW",
    "wof:name":"Pack And Stack Storage Solutions",
    "wof:placetype":"venue"
},
  "geometry": {"coordinates":[153.41131591800001,-28.3293685913],"type":"Point"}
}