{
  "type": "Feature",
  "properties": {
    "iso:country":"AU",
    "sg:address":"20 Mena St",
    "sg:city":"North Strathfield",
    "sg:classifiers":[
        {
            "category":"Building & Trades",
            "subcategory":"Construction",
            "type":"Services"
        }
    ],
    "sg:phone":"+61 2 9743 4504",
    "sg:postcode":"2137",
    "sg:province":"NSW",
    "sg:tags":[
        "contractor"
    ],
    "wof:name":"Chiswick Alan",
    "wof:placetype":"venue"
},
  "geometry": {"coordinates":[151.08343505900001,-33.8546485901],"type":"Point"}
}