{
  "type": "Feature",
  "properties": {
    "addr:full":"20 Moor St Fitzroy VIC 3065",
    "addr:housenumber":"20",
    "addr:postcode":"3065",
    "addr:street":"Moor St",
    "iso:country":"AU",
    "sg:address":"20 Moor St",
    "sg:city":"Fitzroy",
    "sg:classifiers":[
        {
            "category":"Building & Trades",
            "subcategory":"Landscaping Services",
            "type":"Services"
        }
    ],
    "sg:phone":"+61 418 382 325",
    "sg:postcode":"3065",
    "sg:province":"VIC",
    "sg:tags":[
        "designer",
        "landscape",
        "contractor"
    ],
    "sg:website":"http://www.metrolandscaping.com.au",
    "wof:name":"Metro Landscape & Irrigation",
    "wof:placetype":"venue"
},
  "geometry": {"coordinates":[144.97523498499999,-37.8014259338],"type":"Point"}
}