{
  "type": "Feature",
  "properties": {
    "addr:full":"14 Baron St Cooma NSW 2630",
    "addr:housenumber":"14",
    "addr:postcode":"2630",
    "addr:street":"Baron St",
    "iso:country":"AU",
    "sg:address":"14 Baron St",
    "sg:city":"Cooma",
    "sg:classifiers":[
        {
            "category":"Social Services",
            "subcategory":"Child Care",
            "type":"Services"
        }
    ],
    "sg:phone":"+61 2 6452 5573",
    "sg:postcode":"2630",
    "sg:province":"NSW",
    "wof:name":"Dymples Long Day Care Centre",
    "wof:placetype":"venue"
},
  "geometry": {"coordinates":[149.12782287600001,-36.2300071716],"type":"Point"}
}