{
  "type": "Feature",
  "properties": {
    "addr:full":"143 Butler St Armidale NSW 2350",
    "addr:housenumber":"143",
    "addr:postcode":"2350",
    "addr:street":"Butler St",
    "iso:country":"AU",
    "sg:address":"143 Butler St",
    "sg:city":"Armidale",
    "sg:classifiers":[
        {
            "category":"Professional",
            "subcategory":"Art Services",
            "type":"Services"
        }
    ],
    "sg:phone":"+61 401 341 103",
    "sg:postcode":"2350",
    "sg:province":"NSW",
    "sg:tags":[
        "decorator",
        "painter"
    ],
    "wof:name":"Stewart David Painting Contractor",
    "wof:placetype":"venue"
},
  "geometry": {"coordinates":[151.65577697800001,-30.5145759583],"type":"Point"}
}