{
  "type": "Feature",
  "properties": {
    "addr:full":"Buchanan Rd Smithfield Plains SA 5114",
    "addr:postcode":"5114",
    "addr:street":"Buchanan Rd",
    "iso:country":"AU",
    "sg:address":"Buchanan Rd",
    "sg:city":"Smithfield Plains",
    "sg:classifiers":[
        {
            "category":"Education",
            "subcategory":"School",
            "type":"Public Place"
        }
    ],
    "sg:phone":"+61 8 8254 6266",
    "sg:postcode":"5114",
    "sg:province":"SA",
    "sg:tags":[
        "state",
        "except",
        "nsw"
    ],
    "wof:name":"Smithfield Plains Primary",
    "wof:placetype":"venue"
},
  "geometry": {"coordinates":[138.679443359,-34.6761703491],"type":"Point"}
}