{
  "type": "Feature",
  "properties": {
    "addr:full":"31 Beryl St Balcatta WA 6021",
    "addr:housenumber":"31",
    "addr:postcode":"6021",
    "addr:street":"Beryl St",
    "iso:country":"AU",
    "sg:address":"31 Beryl St",
    "sg:city":"Balcatta",
    "sg:classifiers":[
        {
            "category":"Government",
            "subcategory":"Fire Station",
            "type":"Public Place"
        }
    ],
    "sg:phone":"+61 8 9344 1995",
    "sg:postcode":"6021",
    "sg:province":"WA",
    "sg:tags":[
        "spring",
        "shock",
        "absorbers",
        "suspension"
    ],
    "wof:name":"Autoride Suspensions",
    "wof:placetype":"venue"
},
  "geometry": {"coordinates":[115.824867248,-31.8773612976],"type":"Point"}
}