{
  "type": "Feature",
  "properties": {
    "addr:full":"26B Fairfield Gardens Shopping Centre, Fairfield Road Fairfield QLD 4103",
    "addr:housenumber":"26b",
    "addr:postcode":"4103",
    "addr:street":"Fairfield Gardens;Fairfield Road",
    "iso:country":"AU",
    "sg:address":"26B Fairfield Gardens Shopping Centre, Fairfield Road",
    "sg:city":"Fairfield",
    "sg:classifiers":[
        {
            "category":"Social Services",
            "subcategory":"Retirement Home",
            "type":"Services"
        }
    ],
    "sg:phone":"+61 7 3255 0400",
    "sg:postcode":"4103",
    "sg:province":"QLD",
    "sg:tags":[
        "village"
    ],
    "sg:website":"http://www.yerongavillage.com.au",
    "wof:name":"Yeronga Village Pty Ltd",
    "wof:placetype":"venue"
},
  "geometry": {"coordinates":[153.02313232399999,-27.5101451874],"type":"Point"}
}