{
  "type": "Feature",
  "properties": {
    "addr:full":"12 Reynolds St Mansfield VIC 3722",
    "addr:housenumber":"12",
    "addr:postcode":"3722",
    "addr:street":"Reynolds St",
    "iso:country":"AU",
    "sg:address":"12 Reynolds St",
    "sg:city":"Mansfield",
    "sg:classifiers":[
        {
            "category":"Travel",
            "subcategory":"Travel Agent",
            "type":"Entertainment"
        }
    ],
    "sg:phone":"+61 3 5775 2886",
    "sg:postcode":"3722",
    "sg:province":"VIC",
    "sg:tags":[
        "tour",
        "holiday",
        "adventure"
    ],
    "wof:name":"McCormack's Mountain Valley Trail Rides",
    "wof:placetype":"venue"
},
  "geometry": {"coordinates":[146.090774536,-37.0601768494],"type":"Point"}
}