{
  "type": "Feature",
  "properties": {
    "addr:full":"Shop 9a Whitsunday Shopping Centre Cannonvale QLD 4802",
    "addr:housenumber":"shop 9a whitsunday",
    "addr:postcode":"4802",
    "iso:country":"AU",
    "sg:address":"Shop 9a Whitsunday Shopping Centre",
    "sg:city":"Cannonvale",
    "sg:classifiers":[
        {
            "category":"Personal",
            "subcategory":"Skin Care",
            "type":"Services"
        }
    ],
    "sg:phone":"+61 7 4946 4801",
    "sg:postcode":"4802",
    "sg:province":"QLD",
    "sg:tags":[
        "treatment"
    ],
    "wof:name":"Inner Sanctum Health & Beauty",
    "wof:placetype":"venue"
},
  "geometry": {"coordinates":[148.78736877399999,-20.2876834869],"type":"Point"}
}