{
  "type": "Feature",
  "properties": {
    "addr:full":"204 Belmore Rd Riverwood NSW 2210",
    "addr:housenumber":"204",
    "addr:postcode":"2210",
    "addr:street":"Belmore Rd",
    "iso:country":"AU",
    "sg:address":"204 Belmore Rd",
    "sg:city":"Riverwood",
    "sg:classifiers":[
        {
            "category":"Banks & Credit Unions",
            "subcategory":"Bank",
            "type":"Services"
        }
    ],
    "sg:phone":"+61 2 9584 2633",
    "sg:postcode":"2210",
    "sg:province":"NSW",
    "wof:name":"St George Bank Limited",
    "wof:placetype":"venue"
},
  "geometry": {"coordinates":[151.052277,-33.952656],"type":"Point"}
}