{
  "type": "Feature",
  "properties": {
    "addr:full":"4 Bosworth Rd Woolgoolga NSW 2456",
    "addr:housenumber":"4",
    "addr:postcode":"2456",
    "addr:street":"Bosworth Rd",
    "iso:country":"AU",
    "sg:address":"4 Bosworth Rd",
    "sg:city":"Woolgoolga",
    "sg:classifiers":[
        {
            "category":"Building & Trades",
            "subcategory":"Construction",
            "type":"Services"
        }
    ],
    "sg:phone":"+61 2 6654 2337",
    "sg:postcode":"2456",
    "sg:province":"NSW",
    "sg:tags":[
        "welding"
    ],
    "wof:name":"Woolgoolga Welding Service",
    "wof:placetype":"venue"
},
  "geometry": {"coordinates":[153.19244399999999,-30.125036],"type":"Point"}
}