{
  "type": "Feature",
  "properties": {
    "iso:country":"AU",
    "sg:address":"140 Rainbow St",
    "sg:city":"Randwick",
    "sg:classifiers":[
        {
            "category":"Building & Trades",
            "subcategory":"Construction",
            "type":"Services"
        }
    ],
    "sg:phone":"+61 416 180 111",
    "sg:postcode":"2031",
    "sg:province":"NSW",
    "sg:tags":[
        "contractor"
    ],
    "wof:name":"Peter Gavrielatos",
    "wof:placetype":"venue"
},
  "geometry": {"coordinates":[151.24229431099999,-33.9258613586],"type":"Point"}
}