{
  "type": "Feature",
  "properties": {
    "addr:full":"17 Pitcairn St Glenorchy TAS 7010",
    "addr:housenumber":"17",
    "addr:postcode":"7010",
    "addr:street":"Pitcairn St",
    "iso:country":"AU",
    "sg:address":"17 Pitcairn St",
    "sg:city":"Glenorchy",
    "sg:classifiers":[
        {
            "category":"Food & Beverages",
            "subcategory":"Liquor & Beverages",
            "type":"Retail Goods"
        }
    ],
    "sg:phone":"+61 3 6274 4000",
    "sg:postcode":"7010",
    "sg:province":"TAS",
    "sg:tags":[
        "merchant",
        "spirit",
        "wine"
    ],
    "wof:name":"Australian Liquor Marketers",
    "wof:placetype":"venue"
},
  "geometry": {"coordinates":[147.26495361299999,-42.8350067139],"type":"Point"}
}