{
  "type": "Feature",
  "properties": {
    "addr:full":"1 Howell Ave Beaumaris VIC 3193",
    "addr:housenumber":"1",
    "addr:postcode":"3193",
    "addr:street":"Howell Ave",
    "iso:country":"AU",
    "sg:address":"1 Howell Ave",
    "sg:city":"Beaumaris",
    "sg:classifiers":[
        {
            "category":"Building & Trades",
            "subcategory":"Plumbing",
            "type":"Services"
        }
    ],
    "sg:phone":"+61 3 9583 1466",
    "sg:postcode":"3193",
    "sg:province":"VIC",
    "sg:tags":[
        "plumber",
        "gasfitters"
    ],
    "wof:name":"Beaumaris Plumbers",
    "wof:placetype":"venue"
},
  "geometry": {"coordinates":[145.050384522,-37.9792327881],"type":"Point"}
}