{
  "type": "Feature",
  "properties": {
    "addr:full":"Montpellier St Port Elliot SA 5212",
    "addr:postcode":"5212",
    "addr:street":"Montpellier St",
    "iso:country":"AU",
    "sg:address":"Montpellier St",
    "sg:city":"Port Elliot",
    "sg:classifiers":[
        {
            "category":"Health Services",
            "subcategory":"Doctor",
            "type":"Services"
        }
    ],
    "sg:phone":"+61 8 8554 2440",
    "sg:postcode":"5212",
    "sg:province":"SA",
    "sg:tags":[
        "medical",
        "practitioner"
    ],
    "wof:name":"Port Elliot Medical Clinic",
    "wof:placetype":"venue"
},
  "geometry": {"coordinates":[138.67637634299999,-35.5261802673],"type":"Point"}
}