{
  "type": "Feature",
  "properties": {
    "iso:country":"AU",
    "sg:address":"43 Tristania St",
    "sg:city":"Bangalow",
    "sg:classifiers":[
        {
            "category":"Utilities",
            "subcategory":"Electric",
            "type":"Services"
        }
    ],
    "sg:phone":"+61 2 6687 2218",
    "sg:postcode":"2479",
    "sg:province":"NSW",
    "sg:tags":[
        "electrical",
        "contractor"
    ],
    "wof:name":"Ridgley Simon",
    "wof:placetype":"venue"
},
  "geometry": {"coordinates":[153.51300048799999,-28.6907348633],"type":"Point"}
}