{
  "type": "Feature",
  "properties": {
    "addr:full":"174 Millbank Rd Terara NSW 2540",
    "addr:housenumber":"174",
    "addr:postcode":"2540",
    "addr:street":"Millbank Rd",
    "iso:country":"AU",
    "sg:address":"174 Millbank Rd",
    "sg:city":"Terara",
    "sg:classifiers":[
        {
            "category":"Farming",
            "subcategory":"Livestock Farm",
            "type":"Manufacturing & Wholesale Goods"
        }
    ],
    "sg:phone":"+61 2 4422 4999",
    "sg:postcode":"2540",
    "sg:province":"NSW",
    "sg:tags":[
        "agistment"
    ],
    "wof:name":"Kygra-Lee Saddlery",
    "wof:placetype":"venue"
},
  "geometry": {"coordinates":[150.62767028799999,-34.8801689148],"type":"Point"}
}