{
  "type": "Feature",
  "properties": {
    "addr:full":"Cnr Bellevue St & Victoria St Coburg VIC 3058",
    "addr:postcode":"3058",
    "addr:street":"Cnr Bellevue St & Victoria St",
    "iso:country":"AU",
    "sg:address":"Cnr Bellevue St & Victoria St",
    "sg:city":"Coburg",
    "sg:classifiers":[
        {
            "category":"Sports & Exercise",
            "subcategory":"Sports Center",
            "type":"Entertainment"
        }
    ],
    "sg:phone":"+61 414 094 738",
    "sg:postcode":"3058",
    "sg:province":"VIC",
    "sg:tags":[
        "coach",
        "tennis"
    ],
    "wof:name":"Coburg Tennis Club - Matchplay Tennis Academy",
    "wof:placetype":"venue"
},
  "geometry": {"coordinates":[144.95370483400001,-37.7420082092],"type":"Point"}
}