{
  "type": "Feature",
  "properties": {
    "iso:country":"AU",
    "sg:address":"Suite D 435 Walnut Ave",
    "sg:city":"Mildura",
    "sg:classifiers":[
        {
            "category":"Real Estate",
            "subcategory":"Real Estate Services",
            "type":"Services"
        }
    ],
    "sg:phone":"+61 3 5023 5575",
    "sg:postcode":"3500",
    "sg:province":"VIC",
    "sg:tags":[
        "valuer"
    ],
    "wof:name":"Edward J Wesolek",
    "wof:placetype":"venue"
},
  "geometry": {"coordinates":[142.131912231,-34.2019348145],"type":"Point"}
}