{
  "type": "Feature",
  "properties": {
    "iso:country":"AU",
    "sg:address":"955 Main Rd",
    "sg:city":"Pheasant Creek",
    "sg:classifiers":[
        {
            "category":"Building & Trades",
            "subcategory":"Construction",
            "type":"Services"
        }
    ],
    "sg:phone":"+61 3 5786 5363",
    "sg:postcode":"3757",
    "sg:province":"VIC",
    "sg:tags":[
        "earth",
        "excavating",
        "moving",
        "contractor"
    ],
    "wof:name":"Keating Constructions Pty Ltd",
    "wof:placetype":"venue"
},
  "geometry": {"coordinates":[145.144501,-37.395367],"type":"Point"}
}