{
  "type": "Feature",
  "properties": {
    "iso:country":"AU",
    "sg:address":"PO Box 456",
    "sg:city":"Gordonvale",
    "sg:classifiers":[
        {
            "category":"Wholesale",
            "subcategory":"Plants",
            "type":"Manufacturing & Wholesale Goods"
        }
    ],
    "sg:phone":"+61 7 4056 2325",
    "sg:postcode":"4865",
    "sg:province":"QLD",
    "sg:tags":[
        "florist"
    ],
    "wof:name":"Tropical Blooms Pty Ltd",
    "wof:placetype":"venue"
},
  "geometry": {"coordinates":[145.78074645999999,-17.0994606018],"type":"Point"}
}