{
  "type": "Feature",
  "properties": {
    "addr:full":"850 Heatherton Rd Springvale South VIC 3172",
    "addr:housenumber":"850",
    "addr:postcode":"3172",
    "addr:street":"Heatherton Rd",
    "iso:country":"AU",
    "sg:address":"850 Heatherton Rd",
    "sg:city":"Springvale South",
    "sg:classifiers":[
        {
            "category":"Health Services",
            "subcategory":"Dentist",
            "type":"Services"
        }
    ],
    "sg:phone":"+61 3 9547 1542",
    "sg:postcode":"3172",
    "sg:province":"VIC",
    "wof:name":"Leung Vincent K",
    "wof:placetype":"venue"
},
  "geometry": {"coordinates":[145.148071289,-37.9619789124],"type":"Point"}
}