{
  "type": "Feature",
  "properties": {
    "addr:full":"Cnr Kings Rd & Woolcock St Hyde Park QLD 4812",
    "addr:postcode":"4812",
    "addr:street":"Cnr Kings Rd & Woolcock St",
    "iso:country":"AU",
    "sg:address":"Cnr Kings Rd & Woolcock St",
    "sg:city":"Hyde Park",
    "sg:classifiers":[
        {
            "category":"Shopping",
            "subcategory":"Clothing, Apparel, & Fashions",
            "type":"Retail Goods"
        }
    ],
    "sg:phone":"+61 7 4724 5524",
    "sg:postcode":"4812",
    "sg:province":"QLD",
    "sg:tags":[
        "sportswear"
    ],
    "wof:name":"Figgers",
    "wof:placetype":"venue"
},
  "geometry": {"coordinates":[146.79182399999999,-19.278521],"type":"Point"}
}