{
  "type": "Feature",
  "properties": {
    "addr:full":"89 Frederick St Annerley QLD 4103",
    "addr:housenumber":"89",
    "addr:postcode":"4103",
    "addr:street":"Frederick St",
    "iso:country":"AU",
    "sg:address":"89 Frederick St",
    "sg:city":"Annerley",
    "sg:classifiers":[
        {
            "category":"Real Estate",
            "subcategory":"Architect",
            "type":"Services"
        }
    ],
    "sg:phone":"+61 7 3848 1641",
    "sg:postcode":"4103",
    "sg:province":"QLD",
    "wof:name":"Jamieson W S",
    "wof:placetype":"venue"
},
  "geometry": {"coordinates":[153.02638244600001,-27.5173072815],"type":"Point"}
}