{
  "type": "Feature",
  "properties": {
    "addr:full":"10- 12 Airds Rd Minto NSW 2566",
    "addr:housenumber":"12",
    "addr:postcode":"2566",
    "addr:street":"Airds Rd",
    "iso:country":"AU",
    "sg:address":"10- 12 Airds Rd",
    "sg:city":"Minto",
    "sg:classifiers":[
        {
            "category":"Banks & Credit Unions",
            "subcategory":"Investment Brokerage",
            "type":"Services"
        }
    ],
    "sg:phone":"+61 2 9603 5511",
    "sg:postcode":"2566",
    "sg:province":"NSW",
    "sg:tags":[
        "mfrg",
        "wholesale",
        "product",
        "sheepskin"
    ],
    "wof:name":"Mandic Shoes Co Pty Ltd",
    "wof:placetype":"venue"
},
  "geometry": {"coordinates":[150.8409729,-34.022769928],"type":"Point"}
}