{
  "type": "Feature",
  "properties": {
    "iso:country":"AU",
    "sg:address":"27 Main St",
    "sg:city":"Pakenham",
    "sg:classifiers":[
        {
            "category":"Education",
            "subcategory":"Kindergarten",
            "type":"Public Place"
        }
    ],
    "sg:phone":"+61 3 5941 1319",
    "sg:postcode":"3810",
    "sg:province":"VIC",
    "sg:tags":[
        "pre-schools"
    ],
    "wof:name":"Pakenham Kindergarten",
    "wof:placetype":"venue"
},
  "geometry": {"coordinates":[145.47839400000001,-38.074474],"type":"Point"}
}