{
  "type": "Feature",
  "properties": {
    "addr:full":"Bridgepoint Shopng Cntr Lvl 1, Cnr Military Rd & Brady St Mosman NSW 2088",
    "addr:housenumber":"cnr",
    "addr:postcode":"2088",
    "addr:street":"Military Rd & Brady St",
    "iso:country":"AU",
    "sg:address":"Bridgepoint Shopng Cntr Lvl 1, Cnr Military Rd & Brady St",
    "sg:city":"Mosman",
    "sg:classifiers":[
        {
            "category":"Health Services",
            "subcategory":"Health Practitioner",
            "type":"Services"
        }
    ],
    "sg:phone":"+61 2 9968 3424",
    "sg:postcode":"2088",
    "sg:province":"NSW",
    "sg:tags":[
        "physiotherapist"
    ],
    "wof:name":"Bridgepoint Physiotherapy & Sports Injury Centre",
    "wof:placetype":"venue"
},
  "geometry": {"coordinates":[151.24055480999999,-33.8225517273],"type":"Point"}
}