{
  "type": "Feature",
  "properties": {
    "addr:full":"Suite 12,Stradbroke Plaza, 66 Marine Pde Southport QLD 4215",
    "addr:housenumber":"66",
    "addr:postcode":"4215",
    "addr:street":"Marine Pde",
    "iso:country":"AU",
    "sg:address":"Suite 12,Stradbroke Plaza, 66 Marine Pde",
    "sg:city":"Southport",
    "sg:classifiers":[
        {
            "category":"Professional",
            "subcategory":"Engineering",
            "type":"Services"
        }
    ],
    "sg:phone":"+61 7 5532 5596",
    "sg:postcode":"4215",
    "sg:province":"QLD",
    "sg:tags":[
        "consulting",
        "engineer"
    ],
    "wof:name":"McAnany Consulting Pty Ltd",
    "wof:placetype":"venue"
},
  "geometry": {"coordinates":[153.414825439,-27.9647598267],"type":"Point"}
}