{
  "type": "Feature",
  "properties": {
    "addr:full":"22 Peel Rd O&#039;Connor WA 6163",
    "addr:housenumber":"22",
    "addr:postcode":"6163",
    "addr:street":"Peel Rd",
    "iso:country":"AU",
    "sg:address":"22 Peel Rd",
    "sg:city":"O&#039;Connor",
    "sg:classifiers":[
        {
            "category":"Industrial Area",
            "type":"Public Place"
        }
    ],
    "sg:phone":"+61 8 9337 9811",
    "sg:postcode":"6163",
    "sg:province":"WA",
    "sg:tags":[
        "floor"
    ],
    "wof:name":"Vigil Antislip",
    "wof:placetype":"venue"
},
  "geometry": {"coordinates":[115.792686,-32.060059],"type":"Point"}
}