{
  "type": "Feature",
  "properties": {
    "addr:full":"570 Colac-Lavers Hill Rd Barongarook West VIC 3249",
    "addr:housenumber":"570",
    "addr:postcode":"3249",
    "addr:street":"Colac-Lavers Hill Rd",
    "iso:country":"AU",
    "sg:address":"570 Colac-Lavers Hill Rd",
    "sg:city":"Barongarook West",
    "sg:classifiers":[
        {
            "category":"Utilities",
            "subcategory":"Electric",
            "type":"Services"
        }
    ],
    "sg:phone":"+61 3 5233 8388",
    "sg:postcode":"3249",
    "sg:province":"VIC",
    "sg:tags":[
        "electrical",
        "contractor"
    ],
    "wof:name":"Paton Doug",
    "wof:placetype":"venue"
},
  "geometry": {"coordinates":[143.58250427199999,-38.418384552],"type":"Point"}
}