{
  "type": "Feature",
  "properties": {
    "addr:full":"1/ 33 Slater Pde Keilor East VIC 3033",
    "addr:housenumber":"/ 33",
    "addr:postcode":"3033",
    "addr:street":"Slater Pde",
    "iso:country":"AU",
    "sg:address":"1/ 33 Slater Pde",
    "sg:city":"Keilor East",
    "sg:classifiers":[
        {
            "category":"Retail",
            "subcategory":"Auto Repair",
            "type":"Services"
        }
    ],
    "sg:phone":"+61 3 9331 6893",
    "sg:postcode":"3033",
    "sg:province":"VIC",
    "sg:tags":[
        "gas",
        "conversion",
        "natural",
        "lp",
        "vehicle"
    ],
    "wof:name":"Ezi-Pay Auto Gas",
    "wof:placetype":"venue"
},
  "geometry": {"coordinates":[144.85375999999999,-37.735657],"type":"Point"}
}