{
  "type": "Feature",
  "properties": {
    "iso:country":"AU",
    "sg:address":"259 Samsonvale Rd",
    "sg:city":"Bray Park",
    "sg:classifiers":[
        {
            "category":"Professional",
            "subcategory":"Art Services",
            "type":"Services"
        }
    ],
    "sg:phone":"+61 417 641 292",
    "sg:postcode":"4500",
    "sg:province":"QLD",
    "sg:tags":[
        "decorator",
        "painter"
    ],
    "wof:name":"Wayne Quinlan Painting",
    "wof:placetype":"venue"
},
  "geometry": {"coordinates":[152.96359252900001,-27.2946643829],"type":"Point"}
}