{
  "type": "Feature",
  "properties": {
    "iso:country":"AU",
    "sg:address":"Unit 18, 8-10 Barry Rd",
    "sg:city":"Chipping Norton",
    "sg:classifiers":[
        {
            "category":"Manufacturing",
            "subcategory":"Motor Vehicles & Parts",
            "type":"Manufacturing & Wholesale Goods"
        }
    ],
    "sg:phone":"+61 2 9755 9111",
    "sg:postcode":"2170",
    "sg:province":"NSW",
    "sg:tags":[
        "body",
        "builder",
        "supply"
    ],
    "wof:name":"Lillian Pty Ltd",
    "wof:placetype":"venue"
},
  "geometry": {"coordinates":[150.966064453,-33.9151916504],"type":"Point"}
}