{
  "type": "Feature",
  "properties": {
    "addr:full":"2 Yertchuk Ave Ashwood VIC 3147",
    "addr:housenumber":"2",
    "addr:postcode":"3147",
    "addr:street":"Yertchuk Ave",
    "iso:country":"AU",
    "sg:address":"2 Yertchuk Ave",
    "sg:city":"Ashwood",
    "sg:classifiers":[
        {
            "category":"Utilities",
            "subcategory":"Electric",
            "type":"Services"
        }
    ],
    "sg:phone":"+61 3 9888 1611",
    "sg:postcode":"3147",
    "sg:province":"VIC",
    "sg:tags":[
        "electrical",
        "contractor"
    ],
    "wof:name":"Wallgates Electrical Services",
    "wof:placetype":"venue"
},
  "geometry": {"coordinates":[145.106964111,-37.8605918884],"type":"Point"}
}