{
  "type": "Feature",
  "properties": {
    "addr:full":"1 Illawong Ave Bondi NSW 2026",
    "addr:housenumber":"1",
    "addr:postcode":"2026",
    "addr:street":"Illawong Ave",
    "iso:country":"AU",
    "sg:address":"1 Illawong Ave",
    "sg:city":"Bondi",
    "sg:classifiers":[
        {
            "category":"Social Services",
            "subcategory":"Child Care",
            "type":"Services"
        }
    ],
    "sg:phone":"+61 2 9365 6600",
    "sg:postcode":"2026",
    "sg:province":"NSW",
    "wof:name":"Kindamindi Childcare Centre",
    "wof:placetype":"venue"
},
  "geometry": {"coordinates":[151.268066406,-33.8963928223],"type":"Point"}
}