{
  "type": "Feature",
  "properties": {
    "addr:full":"384 Hunter St Newcastle NSW 2300",
    "addr:housenumber":"384",
    "addr:postcode":"2300",
    "addr:street":"Hunter St",
    "iso:country":"AU",
    "sg:address":"384 Hunter St",
    "sg:city":"Newcastle",
    "sg:classifiers":[
        {
            "category":"Insurance",
            "subcategory":"Health Insurance",
            "type":"Services"
        }
    ],
    "sg:phone":"+61 2 4929 4516",
    "sg:postcode":"2300",
    "sg:province":"NSW",
    "wof:name":"NIB Health Funds",
    "wof:placetype":"venue"
},
  "geometry": {"coordinates":[151.773788,-32.92667],"type":"Point"}
}