{
  "type": "Feature",
  "properties": {
    "addr:full":"123 Green Oakes Drv Coolum Beach QLD 4573",
    "addr:housenumber":"123",
    "addr:postcode":"4573",
    "addr:street":"Green Oakes Drv",
    "iso:country":"AU",
    "sg:address":"123 Green Oakes Drv",
    "sg:city":"Coolum Beach",
    "sg:classifiers":[
        {
            "category":"Retail",
            "subcategory":"Auto Repair",
            "type":"Services"
        }
    ],
    "sg:phone":"+61 418 156 794",
    "sg:postcode":"4573",
    "sg:province":"QLD",
    "sg:tags":[
        "electrical"
    ],
    "wof:name":"Shaun's Auto Electrics",
    "wof:placetype":"venue"
},
  "geometry": {"coordinates":[153.07925399999999,-26.536993],"type":"Point"}
}