{
  "type": "Feature",
  "properties": {
    "addr:full":"PO Box 612 Lavington NSW 2641",
    "addr:postcode":"2641",
    "iso:country":"AU",
    "sg:address":"PO Box 612",
    "sg:city":"Lavington",
    "sg:classifiers":[
        {
            "category":"Utilities",
            "subcategory":"Electric",
            "type":"Services"
        }
    ],
    "sg:phone":"+61 2 6025 8777",
    "sg:postcode":"2641",
    "sg:province":"NSW",
    "sg:tags":[
        "electrical",
        "contractor"
    ],
    "wof:name":"Hall Douglas",
    "wof:placetype":"venue"
},
  "geometry": {"coordinates":[146.948974609,-36.0430412292],"type":"Point"}
}