{
  "type": "Feature",
  "properties": {
    "iso:country":"AU",
    "sg:address":"Ereton Drv",
    "sg:city":"Labrador",
    "sg:classifiers":[
        {
            "category":"Building & Trades",
            "subcategory":"Construction",
            "type":"Services"
        }
    ],
    "sg:phone":"+61 7 5537 7233",
    "sg:postcode":"4215",
    "sg:province":"QLD",
    "sg:tags":[
        "earth",
        "excavating",
        "moving",
        "contractor"
    ],
    "wof:name":"Marshall & Rankin",
    "wof:placetype":"venue"
},
  "geometry": {"coordinates":[153.385894775,-27.9356002808],"type":"Point"}
}