{
  "type": "Feature",
  "properties": {
    "addr:full":"193 Station St Corio VIC 3214",
    "addr:housenumber":"193",
    "addr:postcode":"3214",
    "addr:street":"Station St",
    "iso:country":"AU",
    "sg:address":"193 Station St",
    "sg:city":"Corio",
    "sg:classifiers":[
        {
            "category":"Manufacturing",
            "subcategory":"Petroleum Products",
            "type":"Manufacturing & Wholesale Goods"
        }
    ],
    "sg:phone":"+61 3 5274 2442",
    "sg:postcode":"3214",
    "sg:province":"VIC",
    "sg:tags":[
        "magnesium",
        "supply"
    ],
    "wof:name":"Alloy Engineers Pty Ltd",
    "wof:placetype":"venue"
},
  "geometry": {"coordinates":[144.36819457999999,-38.0798416138],"type":"Point"}
}