{
  "type": "Feature",
  "properties": {
    "addr:full":"30 Gladstone St Gladstone SA 5473",
    "addr:housenumber":"30",
    "addr:postcode":"5473",
    "addr:street":"Gladstone St",
    "iso:country":"AU",
    "sg:address":"30 Gladstone St",
    "sg:city":"Gladstone",
    "sg:classifiers":[
        {
            "category":"Professional",
            "subcategory":"Accounting & Tax Preparation",
            "type":"Services"
        }
    ],
    "sg:phone":"+61 8 8662 2677",
    "sg:postcode":"5473",
    "sg:province":"SA",
    "sg:tags":[
        "consultant",
        "taxation"
    ],
    "wof:name":"Abram David & Associates Pty Ltd",
    "wof:placetype":"venue"
},
  "geometry": {"coordinates":[138.356674,-33.269161],"type":"Point"}
}