{
  "type": "Feature",
  "properties": {
    "iso:country":"AU",
    "sg:address":"15 The Groves Longwood St",
    "sg:city":"Minyama",
    "sg:classifiers":[
        {
            "category":"Education",
            "subcategory":"Vocational School",
            "type":"Public Place"
        }
    ],
    "sg:phone":"+61 7 5444 6603",
    "sg:postcode":"4575",
    "sg:province":"QLD",
    "sg:tags":[
        "cake",
        "decorating",
        "decorator"
    ],
    "wof:name":"A Beautiful Cake",
    "wof:placetype":"venue"
},
  "geometry": {"coordinates":[153.121567,-26.700562],"type":"Point"}
}