{
  "type": "Feature",
  "properties": {
    "addr:full":"15 Kildare Rd Blacktown NSW 2148",
    "addr:housenumber":"15",
    "addr:postcode":"2148",
    "addr:street":"Kildare Rd",
    "iso:country":"AU",
    "sg:address":"15 Kildare Rd",
    "sg:city":"Blacktown",
    "sg:classifiers":[
        {
            "category":"Cafe",
            "type":"Food & Drink"
        }
    ],
    "sg:phone":"+61 2 9671 4174",
    "sg:postcode":"2148",
    "sg:province":"NSW",
    "wof:name":"Raiana",
    "wof:placetype":"venue"
},
  "geometry": {"coordinates":[150.90524292000001,-33.7687721252],"type":"Point"}
}