{
  "type": "Feature",
  "properties": {
    "iso:country":"AU",
    "sg:address":"191 Peninsula Rd",
    "sg:city":"Maylands",
    "sg:classifiers":[
        {
            "category":"Insurance",
            "subcategory":"Life Insurance",
            "type":"Services"
        }
    ],
    "sg:phone":"+61 8 9370 1911",
    "sg:postcode":"6051",
    "sg:province":"WA",
    "wof:name":"Kevin Hobbs",
    "wof:placetype":"venue"
},
  "geometry": {"coordinates":[115.902199,-31.937542],"type":"Point"}
}