{
  "type": "Feature",
  "properties": {
    "iso:country":"AU",
    "sg:address":"40 Bell St",
    "sg:city":"Moe",
    "sg:classifiers":[
        {
            "category":"Home & Garden",
            "subcategory":"Building Materials",
            "type":"Retail Goods"
        }
    ],
    "sg:phone":"+61 407 343 083",
    "sg:postcode":"3825",
    "sg:province":"VIC",
    "sg:tags":[
        "merchant",
        "glass",
        "glazier"
    ],
    "wof:name":"Hack's Glass & Home Maintenance Service",
    "wof:placetype":"venue"
},
  "geometry": {"coordinates":[146.25676,-38.172417],"type":"Point"}
}