{
  "type": "Feature",
  "properties": {
    "addr:full":"17- 29 Lamington Tce Nambour QLD 4560",
    "addr:housenumber":"29",
    "addr:postcode":"4560",
    "addr:street":"Lamington Tce",
    "iso:country":"AU",
    "sg:address":"17- 29",
    "sg:city":"Lamington Tce Nambour",
    "sg:classifiers":[
        {
            "category":"Retail",
            "subcategory":"Auto Repair",
            "type":"Services"
        }
    ],
    "sg:phone":"+61 7 5441 9000",
    "sg:postcode":"4560",
    "sg:province":"QLD",
    "sg:tags":[
        "repairer",
        "motor",
        "engineer"
    ],
    "wof:name":"A Cullen & Son",
    "wof:placetype":"venue"
},
  "geometry": {"coordinates":[152.960845947,-26.6332492828],"type":"Point"}
}