{
  "type": "Feature",
  "properties": {
    "addr:full":"Suite 402 Level 4 343 Little Collins St Melbourne VIC 3000",
    "addr:housenumber":"343",
    "addr:postcode":"3000",
    "addr:street":"402;Little Collins St",
    "iso:country":"AU",
    "sg:address":"Suite 402 Level 4 343 Little Collins St",
    "sg:city":"Melbourne",
    "sg:classifiers":[
        {
            "category":"Professional",
            "subcategory":"Management & Consulting",
            "type":"Services"
        }
    ],
    "sg:phone":"+61 3 9670 1010",
    "sg:postcode":"3000",
    "sg:province":"VIC",
    "sg:tags":[
        "consultant",
        "migration"
    ],
    "wof:name":"My Visa Online",
    "wof:placetype":"venue"
},
  "geometry": {"coordinates":[144.96336364699999,-37.8154258728],"type":"Point"}
}