{
  "type": "Feature",
  "properties": {
    "iso:country":"AU",
    "sg:address":"PO Box 597",
    "sg:city":"Runaway Bay",
    "sg:classifiers":[
        {
            "category":"Building & Trades",
            "subcategory":"Construction",
            "type":"Services"
        }
    ],
    "sg:phone":"+61 1300 426 396",
    "sg:postcode":"4216",
    "sg:province":"QLD",
    "sg:tags":[
        "renovation",
        "alterations",
        "extension",
        "contractor"
    ],
    "wof:name":"The Handyman Team",
    "wof:placetype":"venue"
},
  "geometry": {"coordinates":[153.403930664,-27.9242191315],"type":"Point"}
}