{
  "type": "Feature",
  "properties": {
    "addr:full":"14 Gladstone Rd Briar Hill VIC 3088",
    "addr:housenumber":"14",
    "addr:postcode":"3088",
    "addr:street":"Gladstone Rd",
    "iso:country":"AU",
    "sg:address":"14 Gladstone Rd",
    "sg:city":"Briar Hill",
    "sg:classifiers":[
        {
            "category":"Professional",
            "subcategory":"Accounting & Tax Preparation",
            "type":"Services"
        }
    ],
    "sg:phone":"+61 3 9434 7080",
    "sg:postcode":"3088",
    "sg:province":"VIC",
    "sg:tags":[
        "accountant",
        "auditor"
    ],
    "wof:name":"Hayhoe E J",
    "wof:placetype":"venue"
},
  "geometry": {"coordinates":[145.11813354500001,-37.7090339661],"type":"Point"}
}