{
  "type": "Feature",
  "properties": {
    "addr:full":"Gateway Professional Suites, 716 Main Rd Eltham VIC 3095",
    "addr:housenumber":"716",
    "addr:postcode":"3095",
    "addr:street":"Main Rd",
    "iso:country":"AU",
    "sg:address":"Gateway Professional Suites, 716 Main Rd",
    "sg:city":"Eltham",
    "sg:classifiers":[
        {
            "category":"Professional",
            "subcategory":"Detective & Security Services",
            "type":"Services"
        }
    ],
    "sg:phone":"+61 3 9439 9485",
    "sg:postcode":"3095",
    "sg:province":"VIC",
    "sg:tags":[
        "consultant",
        "system"
    ],
    "wof:name":"Pro Active Strategies Pty Ltd",
    "wof:placetype":"venue"
},
  "geometry": {"coordinates":[145.14588928200001,-37.7231636047],"type":"Point"}
}