{
  "type": "Feature",
  "properties": {
    "addr:full":"PO Box 7 Underwood QLD 4119",
    "addr:postcode":"4119",
    "iso:country":"AU",
    "sg:address":"PO Box 7",
    "sg:city":"Underwood",
    "sg:classifiers":[
        {
            "category":"Professional",
            "subcategory":"Accounting & Tax Preparation",
            "type":"Services"
        }
    ],
    "sg:phone":"+61 408 959 745",
    "sg:postcode":"4119",
    "sg:province":"QLD",
    "sg:tags":[
        "bookkeeping"
    ],
    "wof:name":"G T Administration",
    "wof:placetype":"venue"
},
  "geometry": {"coordinates":[153.11244201700001,-27.6068191528],"type":"Point"}
}