{
  "type": "Feature",
  "properties": {
    "iso:country":"AU",
    "sg:address":"Moss St",
    "sg:city":"Springwood",
    "sg:classifiers":[
        {
            "category":"Retail",
            "subcategory":"Repair Shop",
            "type":"Services"
        }
    ],
    "sg:phone":"+61 416 040 954",
    "sg:postcode":"4127",
    "sg:province":"QLD",
    "sg:tags":[
        "upholsterer"
    ],
    "wof:name":"Mandy Waters",
    "wof:placetype":"venue"
},
  "geometry": {"coordinates":[153.12435913100001,-27.6212425232],"type":"Point"}
}