{
  "type": "Feature",
  "properties": {
    "iso:country":"AU",
    "sg:address":"Kirkland Ave",
    "sg:city":"Euroa",
    "sg:classifiers":[
        {
            "category":"Organizations",
            "subcategory":"Community Association",
            "type":"Services"
        }
    ],
    "sg:phone":"+61 3 5795 2116",
    "sg:postcode":"3666",
    "sg:province":"VIC",
    "sg:tags":[
        "club",
        "senior",
        "citizen"
    ],
    "wof:name":"Euroa Senior Citizens Club",
    "wof:placetype":"venue"
},
  "geometry": {"coordinates":[145.57286071799999,-36.7514915466],"type":"Point"}
}