{
  "type": "Feature",
  "properties": {
    "iso:country":"AU",
    "sg:address":"Shop 7/ 1065 Frankston-Flinders Rd",
    "sg:city":"Somerville",
    "sg:classifiers":[
        {
            "category":"Banks & Credit Unions",
            "subcategory":"Financial Services",
            "type":"Services"
        }
    ],
    "sg:phone":"+61 3 5977 9545",
    "sg:postcode":"3912",
    "sg:province":"VIC",
    "sg:tags":[
        "planning"
    ],
    "wof:name":"Southern Mortgage Solutions Pty Ltd",
    "wof:placetype":"venue"
},
  "geometry": {"coordinates":[145.176055908,-38.2239875793],"type":"Point"}
}