{
  "type": "Feature",
  "properties": {
    "addr:full":"58 Turner St Wonthaggi VIC 3995",
    "addr:housenumber":"58",
    "addr:postcode":"3995",
    "addr:street":"Turner St",
    "iso:country":"AU",
    "sg:address":"58 Turner St",
    "sg:city":"Wonthaggi",
    "sg:classifiers":[
        {
            "category":"Building & Trades",
            "subcategory":"Construction",
            "type":"Services"
        }
    ],
    "sg:phone":"+61 3 5672 3347",
    "sg:postcode":"3995",
    "sg:province":"VIC",
    "sg:tags":[
        "contractor"
    ],
    "wof:name":"Hughes J D & E",
    "wof:placetype":"venue"
},
  "geometry": {"coordinates":[145.599976,-38.590572],"type":"Point"}
}