{
  "type": "Feature",
  "properties": {
    "iso:country":"AU",
    "sg:address":"3 Godfrey St",
    "sg:city":"Darlington",
    "sg:classifiers":[
        {
            "category":"Building & Trades",
            "subcategory":"Construction",
            "type":"Services"
        }
    ],
    "sg:phone":"+61 8 8358 5366",
    "sg:postcode":"5047",
    "sg:province":"SA",
    "sg:tags":[
        "renovation",
        "alterations",
        "extension",
        "contractor"
    ],
    "wof:name":"Pro Clad South Australia",
    "wof:placetype":"venue"
},
  "geometry": {"coordinates":[138.557068,-35.030453],"type":"Point"}
}