{
  "type": "Feature",
  "properties": {
    "addr:full":"45 Elizabeth St Devonport TAS 7310",
    "addr:housenumber":"45",
    "addr:postcode":"7310",
    "addr:street":"Elizabeth St",
    "iso:country":"AU",
    "sg:address":"45 Elizabeth St",
    "sg:city":"Devonport",
    "sg:classifiers":[
        {
            "category":"Professional",
            "subcategory":"Art Services",
            "type":"Services"
        }
    ],
    "sg:phone":"+61 3 6424 8428",
    "sg:postcode":"7310",
    "sg:province":"TAS",
    "sg:tags":[
        "graphic",
        "designer"
    ],
    "wof:name":"Dahl Signs & Design",
    "wof:placetype":"venue"
},
  "geometry": {"coordinates":[146.35214233400001,-41.1670570374],"type":"Point"}
}