{
  "type": "Feature",
  "properties": {
    "addr:full":"99 Adelaide Terrace Perth WA 6000",
    "addr:housenumber":"99",
    "addr:postcode":"6000",
    "addr:street":"Adelaide Terrace",
    "iso:country":"AU",
    "sg:address":"99 Adelaide Terrace",
    "sg:city":"Perth",
    "sg:classifiers":[
        {
            "category":"Retail",
            "subcategory":"Event Space",
            "type":"Services"
        }
    ],
    "sg:phone":"+61 8 9225 1234",
    "sg:postcode":"6000",
    "sg:province":"WA",
    "sg:tags":[
        "venue",
        "reception",
        "wedding"
    ],
    "sg:website":"http://www.perth.regency.hyatt.com",
    "wof:name":"Hyatt Regency Perth",
    "wof:placetype":"venue"
},
  "geometry": {"coordinates":[115.874450684,-31.9607048035],"type":"Point"}
}