{
  "type": "Feature",
  "properties": {
    "iso:country":"AU",
    "sg:address":"U11/ 31 Wentworth St",
    "sg:city":"Greenacre",
    "sg:classifiers":[
        {
            "category":"Building & Trades",
            "subcategory":"Construction",
            "type":"Services"
        }
    ],
    "sg:phone":"+61 2 9742 1622",
    "sg:postcode":"2190",
    "sg:province":"NSW",
    "sg:tags":[
        "concrete",
        "contractor"
    ],
    "wof:name":"Azzurri Concrete Pty Ltd",
    "wof:placetype":"venue"
},
  "geometry": {"coordinates":[151.06964099999999,-33.900391],"type":"Point"}
}