{
  "type": "Feature",
  "properties": {
    "iso:country":"AU",
    "sg:address":"3 Gardenia Crt",
    "sg:city":"Narre Warren South",
    "sg:classifiers":[
        {
            "category":"Building & Trades",
            "subcategory":"Construction",
            "type":"Services"
        }
    ],
    "sg:phone":"+61 417 318 034",
    "sg:postcode":"3804",
    "sg:province":"VIC",
    "sg:tags":[
        "concrete",
        "contractor"
    ],
    "wof:name":"R.J. Concrete Designs",
    "wof:placetype":"venue"
},
  "geometry": {"coordinates":[145.313430786,-37.9869728088],"type":"Point"}
}