{
  "type": "Feature",
  "properties": {
    "addr:full":"495 Malvern Rd South Yarra VIC 3141",
    "addr:housenumber":"495",
    "addr:postcode":"3141",
    "addr:street":"Malvern Rd",
    "iso:country":"AU",
    "sg:address":"495 Malvern Rd",
    "sg:city":"South Yarra",
    "sg:classifiers":[
        {
            "category":"Professional",
            "subcategory":"Art Services",
            "type":"Services"
        }
    ],
    "sg:phone":"+61 3 9827 6465",
    "sg:postcode":"3141",
    "sg:province":"VIC",
    "sg:tags":[
        "decorator",
        "painter"
    ],
    "wof:name":"List (Master Painters) Pty Ltd",
    "wof:placetype":"venue"
},
  "geometry": {"coordinates":[145.00289917000001,-37.8479156494],"type":"Point"}
}