{
  "type": "Feature",
  "properties": {
    "addr:full":"844 Old Caulder Hwy Keilor VIC 3036",
    "addr:housenumber":"844",
    "addr:postcode":"3036",
    "addr:street":"Old Caulder Hwy",
    "iso:country":"AU",
    "sg:address":"844 Old Caulder Hwy",
    "sg:city":"Keilor",
    "sg:classifiers":[
        {
            "category":"Building & Trades",
            "subcategory":"Construction",
            "type":"Services"
        }
    ],
    "sg:phone":"+61 412 326 726",
    "sg:postcode":"3036",
    "sg:province":"VIC",
    "sg:tags":[
        "contractor"
    ],
    "wof:name":"Hammer And Nails Home Improvement",
    "wof:placetype":"venue"
},
  "geometry": {"coordinates":[144.81373600000001,-37.704449],"type":"Point"}
}