{
  "type": "Feature",
  "properties": {
    "addr:full":"477 Redland Bay Rd Capalaba QLD 4157",
    "addr:housenumber":"477",
    "addr:postcode":"4157",
    "addr:street":"Redland Bay Rd",
    "iso:country":"AU",
    "sg:address":"477 Redland Bay Rd",
    "sg:city":"Capalaba",
    "sg:classifiers":[
        {
            "category":"Farming",
            "subcategory":"Nursery",
            "type":"Manufacturing & Wholesale Goods"
        }
    ],
    "sg:phone":"+61 7 3206 0222",
    "sg:postcode":"4157",
    "sg:province":"QLD",
    "wof:name":"Green Secrets Nursery",
    "wof:placetype":"venue"
},
  "geometry": {"coordinates":[153.20697021500001,-27.53515625],"type":"Point"}
}