{
  "type": "Feature",
  "properties": {
    "iso:country":"AU",
    "sg:address":"6 Bluehaven Crt",
    "sg:city":"Bokarina",
    "sg:classifiers":[
        {
            "category":"Health Services",
            "subcategory":"Health Practitioner",
            "type":"Services"
        }
    ],
    "sg:phone":"+61 7 5493 6446",
    "sg:postcode":"4575",
    "sg:province":"QLD",
    "sg:tags":[
        "physiotherapist"
    ],
    "wof:name":"Bokarina Physiotherapy",
    "wof:placetype":"venue"
},
  "geometry": {"coordinates":[153.133087,-26.740555],"type":"Point"}
}