{
  "type": "Feature",
  "properties": {
    "addr:full":"PO Box 160 Red Cliffs VIC 3496",
    "addr:postcode":"3496",
    "iso:country":"AU",
    "sg:address":"PO Box 160",
    "sg:city":"Red Cliffs",
    "sg:classifiers":[
        {
            "category":"Retail",
            "subcategory":"Auto Rental",
            "type":"Services"
        }
    ],
    "sg:phone":"+61 1300 852 021",
    "sg:postcode":"3496",
    "sg:province":"VIC",
    "sg:tags":[
        "chauffeur",
        "car",
        "hire",
        "driven",
        "limousine"
    ],
    "wof:name":"Chauffeured Occasions",
    "wof:placetype":"venue"
},
  "geometry": {"coordinates":[142.18652343799999,-34.3077087402],"type":"Point"}
}