{
  "type": "Feature",
  "properties": {
    "addr:full":"57 Molesworth St Lismore NSW 2480",
    "addr:housenumber":"57",
    "addr:postcode":"2480",
    "addr:street":"Molesworth St",
    "iso:country":"AU",
    "sg:address":"57 Molesworth St",
    "sg:city":"Lismore",
    "sg:classifiers":[
        {
            "category":"Shopping",
            "subcategory":"Computers & Home Electronics",
            "type":"Retail Goods"
        }
    ],
    "sg:phone":"+61 2 6622 8282",
    "sg:postcode":"2480",
    "sg:province":"NSW",
    "sg:tags":[
        "hardware",
        "equipment"
    ],
    "wof:name":"Northern Technical Services",
    "wof:placetype":"venue"
},
  "geometry": {"coordinates":[153.27699279800001,-28.8073501587],"type":"Point"}
}