{
  "type": "Feature",
  "properties": {
    "addr:full":"9a Stretton Pl Balcatta WA 6021",
    "addr:housenumber":"9a",
    "addr:postcode":"6021",
    "addr:street":"Pl",
    "iso:country":"AU",
    "sg:address":"9a Stretton Pl",
    "sg:city":"Balcatta",
    "sg:classifiers":[
        {
            "category":"Building & Trades",
            "subcategory":"Pest Control",
            "type":"Services"
        }
    ],
    "sg:phone":"+61 8 9240 6670",
    "sg:postcode":"6021",
    "sg:province":"WA",
    "sg:tags":[
        "wholesaler",
        "mfrs",
        "diary"
    ],
    "wof:name":"Presa Diaries",
    "wof:placetype":"venue"
},
  "geometry": {"coordinates":[115.805717468,-31.8612937927],"type":"Point"}
}