{
  "type": "Feature",
  "properties": {
    "iso:country":"AU",
    "sg:address":"46 Penshurst St",
    "sg:city":"Penshurst",
    "sg:classifiers":[
        {
            "category":"Retail",
            "subcategory":"Laundry & Dry Cleaning",
            "type":"Services"
        }
    ],
    "sg:phone":"+61 2 9570 5213",
    "sg:postcode":"2222",
    "sg:province":"NSW",
    "wof:name":"Penshurst Laundrette",
    "wof:placetype":"venue"
},
  "geometry": {"coordinates":[151.088058472,-33.9646759033],"type":"Point"}
}