{
  "type": "Feature",
  "properties": {
    "iso:country":"AU",
    "sg:address":"6 Harrington St",
    "sg:city":"Glenroy",
    "sg:classifiers":[
        {
            "category":"Organizations",
            "subcategory":"Membership Organization",
            "type":"Services"
        }
    ],
    "sg:phone":"+61 418 170 556",
    "sg:postcode":"3046",
    "sg:province":"VIC",
    "sg:tags":[
        "support",
        "health",
        "organisation"
    ],
    "wof:name":"Needle Syringe Program North Western Mobile",
    "wof:placetype":"venue"
},
  "geometry": {"coordinates":[144.91755676299999,-37.703327179],"type":"Point"}
}