{
  "type": "Feature",
  "properties": {
    "addr:full":"3 Malland St Myaree WA 6154",
    "addr:housenumber":"3",
    "addr:postcode":"6154",
    "addr:street":"Malland St",
    "iso:country":"AU",
    "sg:address":"3 Malland St",
    "sg:city":"Myaree",
    "sg:classifiers":[
        {
            "category":"Autos & Motor Vehicles",
            "subcategory":"Boat Sales",
            "type":"Retail Goods"
        }
    ],
    "sg:phone":"+61 8 9330 3800",
    "sg:postcode":"6154",
    "sg:province":"WA",
    "sg:tags":[
        "equipment",
        "yacht"
    ],
    "wof:name":"Parkes Metal Windows",
    "wof:placetype":"venue"
},
  "geometry": {"coordinates":[115.82023599999999,-32.040169],"type":"Point"}
}