{
  "type": "Feature",
  "properties": {
    "addr:full":"11 Hastings Rd Frankston VIC 3199",
    "addr:housenumber":"11",
    "addr:postcode":"3199",
    "addr:street":"Hastings Rd",
    "iso:country":"AU",
    "sg:address":"11 Hastings Rd",
    "sg:city":"Frankston",
    "sg:classifiers":[
        {
            "category":"Health Services",
            "subcategory":"Doctor",
            "type":"Services"
        }
    ],
    "sg:phone":"+61 3 9783 8466",
    "sg:postcode":"3199",
    "sg:province":"VIC",
    "sg:tags":[
        "medical",
        "practitioner"
    ],
    "wof:name":"McIntyre Richard L E",
    "wof:placetype":"venue"
},
  "geometry": {"coordinates":[145.05152893100001,-37.8315963745],"type":"Point"}
}