{
  "type": "Feature",
  "properties": {
    "addr:full":"144a Henley Beach Rd Mile End SA 5031",
    "addr:housenumber":"144a",
    "addr:postcode":"5031",
    "addr:street":"Henley Beach Rd",
    "iso:country":"AU",
    "sg:address":"144a Henley Beach Rd",
    "sg:city":"Mile End",
    "sg:classifiers":[
        {
            "category":"Personal",
            "subcategory":"Beauty Salon",
            "type":"Services"
        }
    ],
    "sg:phone":"+61 8 8443 7427",
    "sg:postcode":"5031",
    "sg:province":"SA",
    "sg:tags":[
        "hairdresser"
    ],
    "wof:name":"Styles For All",
    "wof:placetype":"venue"
},
  "geometry": {"coordinates":[138.564987183,-34.9241638184],"type":"Point"}
}