{
  "type": "Feature",
  "properties": {
    "addr:full":"344 Flagstaff Rd Berkeley NSW 2506",
    "addr:housenumber":"344",
    "addr:postcode":"2506",
    "addr:street":"Flagstaff Rd",
    "iso:country":"AU",
    "sg:address":"344 Flagstaff Rd",
    "sg:city":"Berkeley",
    "sg:classifiers":[
        {
            "category":"Professional",
            "subcategory":"Art Services",
            "type":"Services"
        }
    ],
    "sg:phone":"+61 2 4272 8131",
    "sg:postcode":"2506",
    "sg:province":"NSW",
    "sg:tags":[
        "decorator",
        "painter"
    ],
    "wof:name":"J Janssen",
    "wof:placetype":"venue"
},
  "geometry": {"coordinates":[150.85874899999999,-34.48008],"type":"Point"}
}