{
  "type": "Feature",
  "properties": {
    "addr:full":"4B Cromwell St Burwood VIC 3125",
    "addr:housenumber":"4b",
    "addr:postcode":"3125",
    "addr:street":"Cromwell St",
    "iso:country":"AU",
    "sg:address":"4B Cromwell St",
    "sg:city":"Burwood",
    "sg:classifiers":[
        {
            "category":"Building & Trades",
            "subcategory":"Cleaning & Sanitation",
            "type":"Services"
        }
    ],
    "sg:phone":"+61 3 9888 9701",
    "sg:postcode":"3125",
    "sg:province":"VIC",
    "sg:tags":[
        "industrial",
        "commercial",
        "contractor"
    ],
    "sg:website":"http://www.shiningknight.com.au",
    "wof:name":"Shining Knight Cleaning",
    "wof:placetype":"venue"
},
  "geometry": {"coordinates":[145.10458374000001,-37.8510055542],"type":"Point"}
}