{
  "type": "Feature",
  "properties": {
    "addr:full":"79 Deering Ave Badger Creek VIC 3777",
    "addr:housenumber":"79",
    "addr:postcode":"3777",
    "addr:street":"Deering Ave",
    "iso:country":"AU",
    "sg:address":"79 Deering Ave",
    "sg:city":"Badger Creek",
    "sg:classifiers":[
        {
            "category":"Farming",
            "subcategory":"Farm",
            "type":"Manufacturing & Wholesale Goods"
        }
    ],
    "sg:phone":"+61 3 5962 4885",
    "sg:postcode":"3777",
    "sg:province":"VIC",
    "sg:tags":[
        "farmer"
    ],
    "wof:name":"Bailey D P",
    "wof:placetype":"venue"
},
  "geometry": {"coordinates":[145.543915,-37.698502],"type":"Point"}
}