{
  "type": "Feature",
  "properties": {
    "iso:country":"AU",
    "sg:address":"28 George St",
    "sg:city":"Moe",
    "sg:classifiers":[
        {
            "category":"Health Services",
            "subcategory":"Doctor",
            "type":"Services"
        }
    ],
    "sg:phone":"+61 3 5127 9800",
    "sg:postcode":"3825",
    "sg:province":"VIC",
    "sg:tags":[
        "medical",
        "practitioner"
    ],
    "wof:name":"Central Gippsland Family Practice",
    "wof:placetype":"venue"
},
  "geometry": {"coordinates":[146.262741,-38.17614],"type":"Point"}
}