{
  "type": "Feature",
  "properties": {
    "iso:country":"AU",
    "sg:address":"Unit 3/ 3 Moorlands Rd",
    "sg:city":"Ingleburn",
    "sg:classifiers":[
        {
            "category":"Shopping",
            "subcategory":"Mobile Phones",
            "type":"Retail Goods"
        }
    ],
    "sg:phone":"+61 2 9829 5311",
    "sg:postcode":"2565",
    "sg:province":"NSW",
    "sg:tags":[
        "wholesaler",
        "mfrs",
        "electrical",
        "switchboard"
    ],
    "wof:name":"Kuilder Industries Pty Ltd",
    "wof:placetype":"venue"
},
  "geometry": {"coordinates":[150.85354614299999,-34.0021743774],"type":"Point"}
}