{
  "type": "Feature",
  "properties": {
    "iso:country":"AU",
    "sg:address":"Shop 1065",
    "sg:city":"A Westfield Shoppingtown Tuggerah",
    "sg:classifiers":[
        {
            "category":"Banks & Credit Unions",
            "subcategory":"Financial Services",
            "type":"Services"
        }
    ],
    "sg:phone":"+61 13 19 87",
    "sg:postcode":"2259",
    "sg:province":"NSW",
    "sg:tags":[
        "building",
        "society"
    ],
    "wof:name":"Newcastle Permanent Building Society Ltd",
    "wof:placetype":"venue"
},
  "geometry": {"coordinates":[151.415557861,-33.306930542],"type":"Point"}
}