{
  "type": "Feature",
  "properties": {
    "addr:full":"3 Tay Crt Banksia Park SA 5091",
    "addr:housenumber":"3",
    "addr:postcode":"5091",
    "addr:street":"Tay Crt",
    "iso:country":"AU",
    "sg:address":"3 Tay Crt",
    "sg:city":"Banksia Park",
    "sg:classifiers":[
        {
            "category":"Utilities",
            "subcategory":"Electric",
            "type":"Services"
        }
    ],
    "sg:phone":"+61 408 847 297",
    "sg:postcode":"5091",
    "sg:province":"SA",
    "sg:tags":[
        "electrical",
        "contractor"
    ],
    "wof:name":"Grant Martyn Electrical",
    "wof:placetype":"venue"
},
  "geometry": {"coordinates":[138.72943115199999,-34.8132324219],"type":"Point"}
}