{
  "type": "Feature",
  "properties": {
    "iso:country":"AU",
    "sg:address":"12 Gretham Rd",
    "sg:city":"Westminster",
    "sg:classifiers":[
        {
            "category":"Structure",
            "subcategory":"Office Building",
            "type":"Public Place"
        }
    ],
    "sg:phone":"+61 412 998 961",
    "sg:postcode":"6061",
    "sg:province":"WA",
    "sg:tags":[
        "equipment",
        "system",
        "drainage"
    ],
    "wof:name":"Jebb Contracting",
    "wof:placetype":"venue"
},
  "geometry": {"coordinates":[115.832473755,-31.864774704],"type":"Point"}
}