{
  "type": "Feature",
  "properties": {
    "addr:full":"85 Leven St Ulverstone TAS 7315",
    "addr:housenumber":"85",
    "addr:postcode":"7315",
    "addr:street":"Leven St",
    "iso:country":"AU",
    "sg:address":"85 Leven St",
    "sg:city":"Ulverstone",
    "sg:classifiers":[
        {
            "category":"Banks & Credit Unions",
            "subcategory":"Investment Brokerage",
            "type":"Services"
        }
    ],
    "sg:phone":"+61 408 140 613",
    "sg:postcode":"7315",
    "sg:province":"TAS",
    "sg:tags":[
        "radiator",
        "motor"
    ],
    "wof:name":"Daggy Daves Radiators",
    "wof:placetype":"venue"
},
  "geometry": {"coordinates":[146.178634644,-41.162109375],"type":"Point"}
}