{
  "type": "Feature",
  "properties": {
    "iso:country":"AU",
    "sg:address":"2 Arthur St",
    "sg:city":"Belmont",
    "sg:classifiers":[
        {
            "category":"Shopping",
            "subcategory":"Crafts & Fabrics",
            "type":"Retail Goods"
        }
    ],
    "sg:phone":"+61 3 5244 0997",
    "sg:postcode":"3216",
    "sg:province":"VIC",
    "sg:tags":[
        "supply"
    ],
    "wof:name":"VICSTITCH",
    "wof:placetype":"venue"
},
  "geometry": {"coordinates":[144.33392334000001,-38.1786346436],"type":"Point"}
}