{
  "type": "Feature",
  "properties": {
    "addr:full":"Shop 8/ 29 Dwyer Rd Oaklands Park SA 5046",
    "addr:housenumber":"shop 8 / 29",
    "addr:postcode":"5046",
    "addr:street":"Dwyer Rd",
    "iso:country":"AU",
    "sg:address":"Shop 8/ 29 Dwyer Rd",
    "sg:city":"Oaklands Park",
    "sg:classifiers":[
        {
            "category":"Farming",
            "subcategory":"Dairy Farm",
            "type":"Manufacturing & Wholesale Goods"
        }
    ],
    "sg:phone":"+61 8 8298 9972",
    "sg:postcode":"5046",
    "sg:province":"SA",
    "sg:tags":[
        "wholesaler",
        "product",
        "mfrs"
    ],
    "wof:name":"Yoghurt Stop",
    "wof:placetype":"venue"
},
  "geometry": {"coordinates":[138.54603576700001,-35.0101585388],"type":"Point"}
}