{
  "type": "Feature",
  "properties": {
    "iso:country":"AU",
    "sg:address":"11 Ranelagh Crt",
    "sg:city":"Golden Grove",
    "sg:classifiers":[
        {
            "category":"Professional",
            "subcategory":"Accounting & Tax Preparation",
            "type":"Services"
        }
    ],
    "sg:phone":"+61 8 8344 5559",
    "sg:postcode":"5125",
    "sg:province":"SA",
    "sg:tags":[
        "accountant",
        "auditor"
    ],
    "wof:name":"Accounting Australia Pty Ltd",
    "wof:placetype":"venue"
},
  "geometry": {"coordinates":[138.72558593799999,-34.7745094299],"type":"Point"}
}