{
  "type": "Feature",
  "properties": {
    "iso:country":"AU",
    "sg:address":"Unit 21/ 65 Myrtle St",
    "sg:city":"Chippendale",
    "sg:classifiers":[
        {
            "category":"Wholesale",
            "subcategory":"Photographic Equipment",
            "type":"Manufacturing & Wholesale Goods"
        }
    ],
    "sg:phone":"+61 414 277 727",
    "sg:postcode":"2008",
    "sg:province":"NSW",
    "sg:tags":[
        "wholesaler",
        "mfrs",
        "supply"
    ],
    "wof:name":"Abacom Pty Ltd",
    "wof:placetype":"venue"
},
  "geometry": {"coordinates":[151.197174072,-33.8875198364],"type":"Point"}
}