{
  "type": "Feature",
  "properties": {
    "addr:full":"411 Magill Rd St Morris SA 5068",
    "addr:housenumber":"411",
    "addr:postcode":"5068",
    "addr:street":"Magill Rd",
    "iso:country":"AU",
    "sg:address":"411 Magill Rd St",
    "sg:city":"Morris",
    "sg:classifiers":[
        {
            "category":"Social Services",
            "subcategory":"Job Training",
            "type":"Services"
        }
    ],
    "sg:phone":"+61 8 8364 3783",
    "sg:postcode":"5068",
    "sg:province":"SA",
    "sg:tags":[
        "sport"
    ],
    "wof:name":"Step Up Advanced Fitness Studio",
    "wof:placetype":"venue"
},
  "geometry": {"coordinates":[138.654495239,-34.9139671326],"type":"Point"}
}