{
  "type": "Feature",
  "properties": {
    "addr:full":"18 Hewitt St Cheltenham VIC 3192",
    "addr:housenumber":"18",
    "addr:postcode":"3192",
    "addr:street":"Hewitt St",
    "iso:country":"AU",
    "sg:address":"18 Hewitt St",
    "sg:city":"Cheltenham",
    "sg:classifiers":[
        {
            "category":"Social Services",
            "subcategory":"Child Care",
            "type":"Services"
        }
    ],
    "sg:phone":"+61 3 9535 5022",
    "sg:postcode":"3192",
    "sg:province":"VIC",
    "sg:tags":[
        "childbirth"
    ],
    "wof:name":"Life Cycles",
    "wof:placetype":"venue"
},
  "geometry": {"coordinates":[145.061599731,-37.9494438171],"type":"Point"}
}