{
  "type": "Feature",
  "properties": {
    "iso:country":"AU",
    "sg:address":"111 Mullens St",
    "sg:city":"Balmain",
    "sg:classifiers":[
        {
            "category":"Real Estate",
            "subcategory":"Architect",
            "type":"Services"
        }
    ],
    "sg:phone":"+61 412 217 141",
    "sg:postcode":"2041",
    "sg:province":"NSW",
    "wof:name":"Housing Simplified",
    "wof:placetype":"venue"
},
  "geometry": {"coordinates":[151.176224,-33.862381],"type":"Point"}
}