{
  "type": "Feature",
  "properties": {
    "addr:full":"Shp 48b Royal Randwick Shopng Cntr Randwick NSW 2031",
    "addr:housenumber":"48b",
    "addr:postcode":"2031",
    "addr:street":"Royal Randwick Shopng Cntr",
    "iso:country":"AU",
    "sg:address":"Shp 48b Royal Randwick Shopng Cntr",
    "sg:city":"Randwick",
    "sg:classifiers":[
        {
            "category":"Shopping",
            "subcategory":"Clothing, Apparel, & Fashions",
            "type":"Retail Goods"
        }
    ],
    "sg:phone":"+61 2 9398 9294",
    "sg:postcode":"2031",
    "sg:province":"NSW",
    "sg:tags":[
        "jean"
    ],
    "wof:name":"Clothes Encounter",
    "wof:placetype":"venue"
},
  "geometry": {"coordinates":[151.24847412099999,-33.9152488708],"type":"Point"}
}