{
  "type": "Feature",
  "properties": {
    "addr:full":"118 Curlewis St Swan Hill NSW 3585",
    "addr:housenumber":"118",
    "addr:postcode":"3585",
    "addr:street":"Curlewis St",
    "iso:country":"AU",
    "sg:address":"118 Curlewis St",
    "sg:city":"Swan Hill",
    "sg:classifiers":[
        {
            "category":"Banks & Credit Unions",
            "subcategory":"Financial Services",
            "type":"Services"
        }
    ],
    "sg:phone":"+61 3 5032 9900",
    "sg:postcode":"3585",
    "sg:province":"NSW",
    "sg:tags":[
        "loan",
        "finance",
        "mortgage"
    ],
    "wof:name":"Rural Finance Corporation of Victoria",
    "wof:placetype":"venue"
},
  "geometry": {"coordinates":[143.56054700000001,-35.337933],"type":"Point"}
}