{
  "type": "Feature",
  "properties": {
    "addr:full":"15 Edol St Geelong North VIC 3215",
    "addr:housenumber":"15",
    "addr:postcode":"3215",
    "addr:street":"Edol St",
    "iso:country":"AU",
    "sg:address":"15 Edol St",
    "sg:city":"Geelong North",
    "sg:classifiers":[
        {
            "category":"Autos & Motor Vehicles",
            "subcategory":"Auto Supplies",
            "type":"Retail Goods"
        }
    ],
    "sg:phone":"+61 3 5278 7635",
    "sg:postcode":"3215",
    "sg:province":"VIC",
    "sg:tags":[
        "equipment",
        "part",
        "truck"
    ],
    "wof:name":"Pacific Trailers",
    "wof:placetype":"venue"
},
  "geometry": {"coordinates":[144.35060119600001,-38.1097679138],"type":"Point"}
}