{
  "type": "Feature",
  "properties": {
    "addr:full":"Shop 9 South Tce Piazza Fremantle WA 6160",
    "addr:housenumber":"shop 9",
    "addr:postcode":"6160",
    "addr:street":"South Tce Piazza Fremantle",
    "iso:country":"AU",
    "sg:address":"Shop 9 South Tce Piazza",
    "sg:city":"Fremantle",
    "sg:classifiers":[
        {
            "category":"Shopping",
            "subcategory":"Bridal",
            "type":"Retail Goods"
        }
    ],
    "sg:phone":"+61 8 9335 4698",
    "sg:postcode":"6160",
    "sg:province":"WA",
    "sg:tags":[
        "hire",
        "wear"
    ],
    "wof:name":"Into Camelot",
    "wof:placetype":"venue"
},
  "geometry": {"coordinates":[115.75592,-32.05257],"type":"Point"}
}