{
  "type": "Feature",
  "properties": {
    "iso:country":"AU",
    "sg:address":"193 Byrnes St",
    "sg:city":"Mareeba",
    "sg:classifiers":[
        {
            "category":"Health Services",
            "subcategory":"Chiropractor",
            "type":"Services"
        }
    ],
    "sg:phone":"+61 7 4092 5835",
    "sg:postcode":"4880",
    "sg:province":"QLD",
    "wof:name":"John Pettit",
    "wof:placetype":"venue"
},
  "geometry": {"coordinates":[145.42288207999999,-16.995426178],"type":"Point"}
}