{
  "type": "Feature",
  "properties": {
    "addr:full":"10 Keperra St Keperra QLD 4054",
    "addr:housenumber":"10",
    "addr:postcode":"4054",
    "addr:street":"Keperra St",
    "iso:country":"AU",
    "sg:address":"10 Keperra St",
    "sg:city":"Keperra",
    "sg:classifiers":[
        {
            "category":"Education",
            "subcategory":"Dance Studio",
            "type":"Public Place"
        }
    ],
    "sg:phone":"+61 7 3355 4916",
    "sg:postcode":"4054",
    "sg:province":"QLD",
    "sg:tags":[
        "venue",
        "tuition"
    ],
    "wof:name":"Thistle Highland Dancing Studio",
    "wof:placetype":"venue"
},
  "geometry": {"coordinates":[152.952667236,-27.4139900208],"type":"Point"}
}