{
  "type": "Feature",
  "properties": {
    "addr:full":"PO Box 2 Deer Park VIC 3023",
    "addr:postcode":"3023",
    "iso:country":"AU",
    "sg:address":"PO Box 2",
    "sg:city":"Deer Park",
    "sg:classifiers":[
        {
            "category":"Professional",
            "subcategory":"Computer Services",
            "type":"Services"
        }
    ],
    "sg:phone":"+61 3 9266 2939",
    "sg:postcode":"3023",
    "sg:province":"VIC",
    "sg:tags":[
        "consultant",
        "system"
    ],
    "wof:name":"Oasys Computer Consultants Pty Ltd",
    "wof:placetype":"venue"
},
  "geometry": {"coordinates":[144.774857,-37.76955],"type":"Point"}
}