{
  "type": "Feature",
  "properties": {
    "iso:country":"AU",
    "sg:address":"Frederick House 70-74 Frederick St",
    "sg:city":"Albany",
    "sg:classifiers":[
        {
            "category":"Organizations",
            "subcategory":"Professional Association",
            "type":"Services"
        }
    ],
    "sg:phone":"+61 8 9841 3725",
    "sg:postcode":"6330",
    "sg:province":"WA",
    "sg:tags":[
        "organisation",
        "business"
    ],
    "wof:name":"Albany Employment Development Committee Inc The",
    "wof:placetype":"venue"
},
  "geometry": {"coordinates":[117.82144928,-35.0080871582],"type":"Point"}
}