{
  "type": "Feature",
  "properties": {
    "addr:full":"&#039;Bretts Wharf&#039;, Kingsford Smith Drv Hamilton QLD 4007",
    "addr:postcode":"4007",
    "addr:street":"Bretts;Kingsford Smith Drv",
    "iso:country":"AU",
    "sg:address":"&#039;Bretts Wharf&#039;, Kingsford Smith Drv",
    "sg:city":"Hamilton",
    "sg:classifiers":[
        {
            "category":"Retail",
            "subcategory":"Event Space",
            "type":"Services"
        }
    ],
    "sg:phone":"+61 7 3630 2666",
    "sg:postcode":"4007",
    "sg:province":"QLD",
    "sg:tags":[
        "venue",
        "reception",
        "wedding"
    ],
    "wof:name":"Brisbane Cruises",
    "wof:placetype":"venue"
},
  "geometry": {"coordinates":[153.06234699999999,-27.439682],"type":"Point"}
}