{
  "type": "Feature",
  "properties": {
    "addr:full":"1 Kelson Pl Acton Park TAS 7170",
    "addr:housenumber":"1",
    "addr:postcode":"7170",
    "addr:street":"Kelson Pl",
    "iso:country":"AU",
    "sg:address":"1 Kelson Pl",
    "sg:city":"Acton Park",
    "sg:classifiers":[
        {
            "category":"Farming",
            "subcategory":"Vineyard",
            "type":"Manufacturing & Wholesale Goods"
        }
    ],
    "sg:phone":"+61 3 6248 4401",
    "sg:postcode":"7170",
    "sg:province":"TAS",
    "sg:tags":[
        "winery"
    ],
    "wof:name":"Danehill Estate Wines",
    "wof:placetype":"venue"
},
  "geometry": {"coordinates":[147.47770690900001,-42.8486328125],"type":"Point"}
}