{
  "type": "Feature",
  "properties": {
    "addr:full":"Webb Rd Eton QLD 4741",
    "addr:postcode":"4741",
    "addr:street":"Webb Rd",
    "iso:country":"AU",
    "sg:address":"Webb Rd",
    "sg:city":"Eton",
    "sg:classifiers":[
        {
            "category":"Farming",
            "subcategory":"Farm",
            "type":"Manufacturing & Wholesale Goods"
        }
    ],
    "sg:phone":"+61 7 4954 1109",
    "sg:postcode":"4741",
    "sg:province":"QLD",
    "sg:tags":[
        "farmer"
    ],
    "wof:name":"Lay K & N M",
    "wof:placetype":"venue"
},
  "geometry": {"coordinates":[148.971619,-21.26549],"type":"Point"}
}