{
  "type": "Feature",
  "properties": {
    "iso:country":"AU",
    "sg:address":"Unit 3 21 Barry St",
    "sg:city":"Bayswater",
    "sg:classifiers":[
        {
            "category":"Retail",
            "subcategory":"Auto Repair",
            "type":"Services"
        }
    ],
    "sg:phone":"+61 1300 763 961",
    "sg:postcode":"3153",
    "sg:province":"VIC",
    "sg:tags":[
        "camper-trailers",
        "caravan",
        "servicing"
    ],
    "sg:website":"http://www.solarforce.com.au",
    "wof:name":"Solarforce Pty Ltd",
    "wof:placetype":"venue"
},
  "geometry": {"coordinates":[145.27554321299999,-37.8469009399],"type":"Point"}
}