{
  "type": "Feature",
  "properties": {
    "addr:full":"St Leonards Rd Healesville VIC 3777",
    "addr:postcode":"3777",
    "addr:street":"St Leonards Rd",
    "iso:country":"AU",
    "sg:address":"St Leonards Rd",
    "sg:city":"Healesville",
    "sg:classifiers":[
        {
            "category":"Social Services",
            "subcategory":"Retirement Home",
            "type":"Services"
        }
    ],
    "sg:phone":"+61 3 5962 2353",
    "sg:postcode":"3777",
    "sg:province":"VIC",
    "sg:tags":[
        "accommodation",
        "special"
    ],
    "wof:name":"Gracefield Special Accommodation House",
    "wof:placetype":"venue"
},
  "geometry": {"coordinates":[145.52311700000001,-37.65028],"type":"Point"}
}