{
  "type": "Feature",
  "properties": {
    "addr:full":"95 Lethbridge St Penrith NSW 2750",
    "addr:housenumber":"95",
    "addr:postcode":"2750",
    "addr:street":"Lethbridge St",
    "iso:country":"AU",
    "sg:address":"95 Lethbridge St",
    "sg:city":"Penrith",
    "sg:classifiers":[
        {
            "category":"Health Services",
            "subcategory":"Health Practitioner",
            "type":"Services"
        }
    ],
    "sg:phone":"+61 2 4731 2959",
    "sg:postcode":"2750",
    "sg:province":"NSW",
    "sg:tags":[
        "physiotherapist"
    ],
    "wof:name":"Cunningham Stephen",
    "wof:placetype":"venue"
},
  "geometry": {"coordinates":[150.70225524899999,-33.7567253113],"type":"Point"}
}