{
  "type": "Feature",
  "properties": {
    "addr:full":"Flatrock Rd Nowra NSW 2541",
    "addr:postcode":"2541",
    "addr:street":"Flatrock Rd",
    "iso:country":"AU",
    "sg:address":"Flatrock Rd",
    "sg:city":"Nowra",
    "sg:classifiers":[
        {
            "category":"Utilities",
            "subcategory":"Recycling",
            "type":"Services"
        }
    ],
    "sg:phone":"+61 2 4421 5281",
    "sg:postcode":"2541",
    "sg:province":"NSW",
    "wof:name":"Nowra Waste Depot",
    "wof:placetype":"venue"
},
  "geometry": {"coordinates":[150.55325317399999,-34.8868751526],"type":"Point"}
}