{
  "type": "Feature",
  "properties": {
    "iso:country":"AU",
    "sg:address":"81 Edith St",
    "sg:city":"Wynnum",
    "sg:classifiers":[
        {
            "category":"Personal",
            "type":"Services"
        }
    ],
    "sg:phone":"+61 7 3396 7877",
    "sg:postcode":"4178",
    "sg:province":"QLD",
    "sg:tags":[
        "gift"
    ],
    "wof:name":"Baskets Of Balmoral",
    "wof:placetype":"venue"
},
  "geometry": {"coordinates":[153.17367553700001,-27.4446353912],"type":"Point"}
}