{
  "type": "Feature",
  "properties": {
    "iso:country":"AU",
    "sg:address":"Grd Lvl 43 River St",
    "sg:city":"Mackay",
    "sg:classifiers":[
        {
            "category":"Professional",
            "subcategory":"Employment Agencies",
            "type":"Services"
        }
    ],
    "sg:phone":"+61 7 4957 4740",
    "sg:postcode":"4740",
    "sg:province":"QLD",
    "wof:name":"ITEC Employment",
    "wof:placetype":"venue"
},
  "geometry": {"coordinates":[149.18487500000001,-21.138756],"type":"Point"}
}