{
  "type": "Feature",
  "properties": {
    "addr:full":"13 Mount Druitt Rd Mt Druitt NSW 2770",
    "addr:housenumber":"13",
    "addr:postcode":"2770",
    "addr:street":"Mount Druitt Rd",
    "iso:country":"AU",
    "sg:address":"13 Mount Druitt Rd",
    "sg:city":"Mt Druitt",
    "sg:classifiers":[
        {
            "category":"Food & Beverages",
            "subcategory":"Liquor & Beverages",
            "type":"Retail Goods"
        }
    ],
    "sg:phone":"+61 2 9832 0011",
    "sg:postcode":"2770",
    "sg:province":"NSW",
    "sg:tags":[
        "store"
    ],
    "wof:name":"Mt Druitt Liquor Barn",
    "wof:placetype":"venue"
},
  "geometry": {"coordinates":[150.81265258799999,-33.769115448],"type":"Point"}
}