{
  "type": "Feature",
  "properties": {
    "iso:country":"AU",
    "sg:address":"7 Turner St",
    "sg:city":"Beerwah",
    "sg:classifiers":[
        {
            "category":"Government",
            "subcategory":"Post Office",
            "type":"Public Place"
        }
    ],
    "sg:phone":"+61 7 5494 6280",
    "sg:postcode":"4519",
    "sg:province":"QLD",
    "sg:tags":[
        "postal"
    ],
    "wof:name":"Australia Post",
    "wof:placetype":"venue"
},
  "geometry": {"coordinates":[152.95687899999999,-26.857445],"type":"Point"}
}