{
  "type": "Feature",
  "properties": {
    "iso:country":"AU",
    "sg:address":"10 Pitt St",
    "sg:city":"Adelaide",
    "sg:classifiers":[
        {
            "category":"Cafe",
            "type":"Food & Drink"
        }
    ],
    "sg:phone":"+61 8 8231 8278",
    "sg:postcode":"5000",
    "sg:province":"SA",
    "wof:name":"Pitt Stop Coffee Shop",
    "wof:placetype":"venue"
},
  "geometry": {"coordinates":[138.597366333,-34.9279518127],"type":"Point"}
}