{
  "type": "Feature",
  "properties": {
    "addr:full":"10 Sturt Pl Taree NSW 2430",
    "addr:housenumber":"10",
    "addr:postcode":"2430",
    "addr:street":"Sturt Pl",
    "iso:country":"AU",
    "sg:address":"10 Sturt Pl",
    "sg:city":"Taree",
    "sg:classifiers":[
        {
            "category":"Structure",
            "subcategory":"Office Building",
            "type":"Public Place"
        }
    ],
    "sg:phone":"+61 2 6552 2390",
    "sg:postcode":"2430",
    "sg:province":"NSW",
    "sg:tags":[
        "slater",
        "tiler",
        "roof"
    ],
    "wof:name":"P & T Taylor Pty Ltd",
    "wof:placetype":"venue"
},
  "geometry": {"coordinates":[152.47938500000001,-31.893028],"type":"Point"}
}