{
  "type": "Feature",
  "properties": {
    "addr:full":"21 Newcastle St Fairfield QLD 4103",
    "addr:housenumber":"21",
    "addr:postcode":"4103",
    "addr:street":"Newcastle St",
    "iso:country":"AU",
    "sg:address":"21 Newcastle St",
    "sg:city":"Fairfield",
    "sg:classifiers":[
        {
            "category":"Professional",
            "subcategory":"Art Services",
            "type":"Services"
        }
    ],
    "sg:phone":"+61 7 3844 4126",
    "sg:postcode":"4103",
    "sg:province":"QLD",
    "sg:tags":[
        "graphic",
        "designer"
    ],
    "wof:name":"Trigger Graphics",
    "wof:placetype":"venue"
},
  "geometry": {"coordinates":[153.02017211899999,-27.5059967041],"type":"Point"}
}