{
  "type": "Feature",
  "properties": {
    "addr:full":"Grand Central Shopping Centre Toowoomba QLD 4350",
    "addr:postcode":"4350",
    "iso:country":"AU",
    "sg:address":"Grand Central Shopping Centre",
    "sg:city":"Toowoomba",
    "sg:classifiers":[
        {
            "category":"Building & Trades",
            "subcategory":"Locksmith",
            "type":"Services"
        }
    ],
    "sg:phone":"+61 7 4639 4982",
    "sg:postcode":"4350",
    "sg:province":"QLD",
    "sg:tags":[
        "lock"
    ],
    "wof:name":"Mister Minit",
    "wof:placetype":"venue"
},
  "geometry": {"coordinates":[151.94923399999999,-27.563356],"type":"Point"}
}