{
  "type": "Feature",
  "properties": {
    "addr:full":"296- 298 Hartley St Cairns QLD 4870",
    "addr:housenumber":"298",
    "addr:postcode":"4870",
    "addr:street":"Hartley St",
    "iso:country":"AU",
    "sg:address":"296- 298 Hartley St",
    "sg:city":"Cairns",
    "sg:classifiers":[
        {
            "category":"Retail",
            "subcategory":"Storage",
            "type":"Services"
        }
    ],
    "sg:phone":"+61 7 4035 2694",
    "sg:postcode":"4870",
    "sg:province":"QLD",
    "sg:tags":[
        "removal",
        "furniture"
    ],
    "wof:name":"Allied Pickfords",
    "wof:placetype":"venue"
},
  "geometry": {"coordinates":[145.75338745100001,-16.9457511902],"type":"Point"}
}