{
  "type": "Feature",
  "properties": {
    "addr:full":"unit 10, 30 Argyle St Camden NSW 2570",
    "addr:housenumber":"30",
    "addr:postcode":"2570",
    "addr:street":"Argyle St",
    "iso:country":"AU",
    "sg:address":"unit 10, 30 Argyle St",
    "sg:city":"Camden",
    "sg:classifiers":[
        {
            "category":"Home & Garden",
            "subcategory":"Building Materials",
            "type":"Retail Goods"
        }
    ],
    "sg:phone":"+61 2 4655 8877",
    "sg:postcode":"2570",
    "sg:province":"NSW",
    "sg:tags":[
        "fitting",
        "door"
    ],
    "wof:name":"Renovators Haven",
    "wof:placetype":"venue"
},
  "geometry": {"coordinates":[150.69879150400001,-34.0535240173],"type":"Point"}
}