{
  "type": "Feature",
  "properties": {
    "addr:full":"54 Farris St Innaloo WA 6018",
    "addr:housenumber":"54",
    "addr:postcode":"6018",
    "addr:street":"Farris St",
    "iso:country":"AU",
    "sg:address":"54 Farris St",
    "sg:city":"Innaloo",
    "sg:classifiers":[
        {
            "category":"Sports & Exercise",
            "subcategory":"Sports Center",
            "type":"Entertainment"
        }
    ],
    "sg:phone":"+61 8 9204 3442",
    "sg:postcode":"6018",
    "sg:province":"WA",
    "sg:tags":[
        "coach",
        "tennis"
    ],
    "wof:name":"Tiny Tots Tennis West Coast",
    "wof:placetype":"venue"
},
  "geometry": {"coordinates":[115.789550781,-31.8893222809],"type":"Point"}
}