{
  "type": "Feature",
  "properties": {
    "addr:full":"333 Darling St Balmain NSW 2041",
    "addr:housenumber":"333",
    "addr:postcode":"2041",
    "addr:street":"Darling St",
    "iso:country":"AU",
    "sg:address":"333 Darling St",
    "sg:city":"Balmain",
    "sg:classifiers":[
        {
            "category":"Cafe",
            "type":"Food & Drink"
        }
    ],
    "sg:phone":"+61 2 9810 1393",
    "sg:postcode":"2041",
    "sg:province":"NSW",
    "wof:name":"Omnivore",
    "wof:placetype":"venue"
},
  "geometry": {"coordinates":[151.17929100000001,-33.85659],"type":"Point"}
}