{
  "type": "Feature",
  "properties": {
    "iso:country":"AU",
    "sg:address":"155 Rickard Rd",
    "sg:city":"North Narrabeen",
    "sg:classifiers":[
        {
            "category":"Retail",
            "subcategory":"Repair Shop",
            "type":"Services"
        }
    ],
    "sg:phone":"+61 2 9913 3641",
    "sg:postcode":"2101",
    "sg:province":"NSW",
    "sg:tags":[
        "maintenance",
        "pool",
        "swimming"
    ],
    "wof:name":"Warringah Pump Repairs",
    "wof:placetype":"venue"
},
  "geometry": {"coordinates":[151.287125,-33.704163],"type":"Point"}
}