{
  "type": "Feature",
  "properties": {
    "iso:country":"AU",
    "sg:address":"17 Ellesmere Ave",
    "sg:city":"Bli Bli",
    "sg:classifiers":[
        {
            "category":"Professional",
            "subcategory":"Business Services",
            "type":"Services"
        }
    ],
    "sg:phone":"+61 7 5448 5527",
    "sg:postcode":"4560",
    "sg:province":"QLD",
    "sg:tags":[
        "drafting"
    ],
    "wof:name":"Cooper J G",
    "wof:placetype":"venue"
},
  "geometry": {"coordinates":[153.035614014,-26.6109352112],"type":"Point"}
}