{
  "type": "Feature",
  "properties": {
    "addr:full":"Tooronga Village Shopping Centre Cnr Tooronga & Toorak Rds Hawthorn East VIC 3123",
    "addr:postcode":"3123",
    "addr:street":"Cnr",
    "iso:country":"AU",
    "sg:address":"Tooronga Village Shopping Centre Cnr Tooronga & Toorak Rds",
    "sg:city":"Hawthorn East",
    "sg:classifiers":[
        {
            "category":"Health Services",
            "subcategory":"Optometrist",
            "type":"Services"
        }
    ],
    "sg:phone":"+61 3 9822 8911",
    "sg:postcode":"3123",
    "sg:province":"VIC",
    "wof:name":"Attilio Giola",
    "wof:placetype":"venue"
},
  "geometry": {"coordinates":[145.04745483400001,-37.8315734863],"type":"Point"}
}