{
  "type": "Feature",
  "properties": {
    "iso:country":"AU",
    "sg:address":"Suite F, Level 3, 75 O&#039;Riordan St",
    "sg:city":"Alexandria",
    "sg:classifiers":[
        {
            "category":"Health Services",
            "subcategory":"Doctor",
            "type":"Services"
        }
    ],
    "sg:phone":"+61 2 8338 9844",
    "sg:postcode":"2015",
    "sg:province":"NSW",
    "sg:tags":[
        "occupational",
        "safety"
    ],
    "wof:name":"Skin Patrol",
    "wof:placetype":"venue"
},
  "geometry": {"coordinates":[151.197097778,-33.9120788574],"type":"Point"}
}