{
  "type": "Feature",
  "properties": {
    "addr:full":"Lvl 5 Edgecliff Cntr 203- 233 New South Head Rd Edgecliff NSW 2027",
    "addr:housenumber":"203 233",
    "addr:postcode":"2027",
    "addr:street":"Cntr;New South Head Rd",
    "iso:country":"AU",
    "sg:address":"Lvl 5 Edgecliff Cntr 203- 233 New South Head Rd",
    "sg:city":"Edgecliff",
    "sg:classifiers":[
        {
            "category":"Personal",
            "type":"Services"
        }
    ],
    "sg:phone":"+61 2 9328 7039",
    "sg:postcode":"2027",
    "sg:province":"NSW",
    "sg:tags":[
        "career",
        "counselling"
    ],
    "wof:name":"Linder-Pelz Susie Dr",
    "wof:placetype":"venue"
},
  "geometry": {"coordinates":[151.235961914,-33.8788223267],"type":"Point"}
}