{
  "type": "Feature",
  "properties": {
    "addr:full":"GPO Box 4916 Melbourne VIC 3001",
    "addr:postcode":"3001",
    "iso:country":"AU",
    "sg:address":"GPO Box 4916",
    "sg:city":"Melbourne",
    "sg:classifiers":[
        {
            "category":"Social Services",
            "subcategory":"Retirement Home",
            "type":"Services"
        }
    ],
    "sg:phone":"+61 410 441 757",
    "sg:postcode":"3001",
    "sg:province":"VIC",
    "sg:tags":[
        "life",
        "coaching"
    ],
    "wof:name":"Halina's Place Pty Ltd",
    "wof:placetype":"venue"
},
  "geometry": {"coordinates":[144.963165283,-37.814250946],"type":"Point"}
}