{
  "type": "Feature",
  "properties": {
    "iso:country":"AU",
    "sg:address":"Cnr Biellara Drv & Niklin Way",
    "sg:city":"Currimundi",
    "sg:classifiers":[
        {
            "category":"Health Services",
            "subcategory":"Doctor",
            "type":"Services"
        }
    ],
    "sg:phone":"+61 7 5491 9044",
    "sg:postcode":"4551",
    "sg:province":"QLD",
    "sg:tags":[
        "medical",
        "practitioner"
    ],
    "wof:name":"Jennifer Cooke",
    "wof:placetype":"venue"
},
  "geometry": {"coordinates":[153.131912231,-26.7745132446],"type":"Point"}
}