{
  "type": "Feature",
  "properties": {
    "addr:full":"267 Great Eastern Hwy Midland WA 6056",
    "addr:housenumber":"267",
    "addr:postcode":"6056",
    "addr:street":"Great Eastern Hwy",
    "iso:country":"AU",
    "sg:address":"267 Great Eastern Hwy",
    "sg:city":"Midland",
    "sg:classifiers":[
        {
            "category":"Professional",
            "subcategory":"Computer Services",
            "type":"Services"
        }
    ],
    "sg:phone":"+61 8 9250 4800",
    "sg:postcode":"6056",
    "sg:province":"WA",
    "sg:tags":[
        "repairs",
        "upgrade",
        "equipment"
    ],
    "wof:name":"Pc Stop The",
    "wof:placetype":"venue"
},
  "geometry": {"coordinates":[116.012123108,-31.8917694092],"type":"Point"}
}