{
  "type": "Feature",
  "properties": {
    "iso:country":"AU",
    "sg:address":"53 George St",
    "sg:city":"Launceston",
    "sg:classifiers":[
        {
            "category":"Bars & Pubs",
            "subcategory":"Dive Bar",
            "type":"Food & Drink"
        }
    ],
    "sg:phone":"+61 3 6331 2539",
    "sg:postcode":"7250",
    "sg:province":"TAS",
    "sg:tags":[
        "knitwear",
        "retail"
    ],
    "wof:name":"Sheeps Back! The",
    "wof:placetype":"venue"
},
  "geometry": {"coordinates":[147.13981628400001,-41.4352035522],"type":"Point"}
}