{
  "type": "Feature",
  "properties": {
    "addr:full":"73 Ellesmere Rd Wellsford Forest VIC 3551",
    "addr:housenumber":"73",
    "addr:postcode":"3551",
    "addr:street":"Ellesmere Rd",
    "iso:country":"AU",
    "sg:address":"73 Ellesmere Rd",
    "sg:city":"Wellsford Forest",
    "sg:classifiers":[
        {
            "category":"Retail",
            "subcategory":"Event Space",
            "type":"Services"
        }
    ],
    "sg:phone":"+61 3 5448 4121",
    "sg:postcode":"3551",
    "sg:province":"VIC",
    "sg:tags":[
        "venue",
        "reception",
        "wedding"
    ],
    "wof:name":"Wellsford Forest Retreat",
    "wof:placetype":"venue"
},
  "geometry": {"coordinates":[144.504470825,-36.7430992126],"type":"Point"}
}