{
  "type": "Feature",
  "properties": {
    "addr:full":"Williams Rd Narrogin WA 6312",
    "addr:postcode":"6312",
    "addr:street":"Williams Rd",
    "iso:country":"AU",
    "sg:address":"Williams Rd",
    "sg:city":"Narrogin",
    "sg:classifiers":[
        {
            "category":"Sports & Exercise",
            "subcategory":"Golf",
            "type":"Entertainment"
        }
    ],
    "sg:phone":"+61 8 9881 1446",
    "sg:postcode":"6312",
    "sg:province":"WA",
    "sg:tags":[
        "club"
    ],
    "wof:name":"Narrogin Golf Club Inc",
    "wof:placetype":"venue"
},
  "geometry": {"coordinates":[117.175170898,-32.9338798523],"type":"Point"}
}