{
  "type": "Feature",
  "properties": {
    "addr:full":"1846 Horsley Drv Horsley Park NSW 2164",
    "addr:housenumber":"1846",
    "addr:postcode":"2164",
    "addr:street":"Horsley Drv",
    "iso:country":"AU",
    "sg:address":"1846 Horsley Drv",
    "sg:city":"Horsley Park",
    "sg:classifiers":[
        {
            "category":"Structure",
            "subcategory":"Bridge",
            "type":"Public Place"
        }
    ],
    "sg:phone":"+61 2 9620 1569",
    "sg:postcode":"2164",
    "sg:province":"NSW",
    "sg:tags":[
        "chainsaw",
        "brushcutters"
    ],
    "wof:name":"Horsley Park Mower Ctr",
    "wof:placetype":"venue"
},
  "geometry": {"coordinates":[150.91950988799999,-33.8440704346],"type":"Point"}
}