{
  "type": "Feature",
  "properties": {
    "addr:full":"305 Raymond St Sale VIC 3850",
    "addr:housenumber":"305",
    "addr:postcode":"3850",
    "addr:street":"Raymond St",
    "iso:country":"AU",
    "sg:address":"305 Raymond St",
    "sg:city":"Sale",
    "sg:classifiers":[
        {
            "category":"Cafe",
            "type":"Food & Drink"
        }
    ],
    "sg:phone":"+61 3 5144 6767",
    "sg:postcode":"3850",
    "sg:province":"VIC",
    "wof:name":"PJ&#039;S Snack Shack",
    "wof:placetype":"venue"
},
  "geometry": {"coordinates":[147.06539917000001,-38.106754303],"type":"Point"}
}