{
  "type": "Feature",
  "properties": {
    "iso:country":"AU",
    "sg:address":"Cnr Hudson & Mimminup Rds",
    "sg:city":"Bunbury",
    "sg:classifiers":[
        {
            "category":"Food & Beverages",
            "subcategory":"Supermarket",
            "type":"Retail Goods"
        }
    ],
    "sg:phone":"+61 8 9795 8200",
    "sg:postcode":"6230",
    "sg:province":"WA",
    "sg:tags":[
        "grocery",
        "store"
    ],
    "wof:name":"Farmer Jack's Supermarkets",
    "wof:placetype":"venue"
},
  "geometry": {"coordinates":[115.636391,-33.365311],"type":"Point"}
}