{
  "type": "Feature",
  "properties": {
    "addr:full":"Reichardt Rd Winnellie NT 0820",
    "addr:postcode":"nt 0820",
    "addr:street":"Reichardt Rd",
    "iso:country":"AU",
    "sg:address":"Reichardt Rd",
    "sg:city":"Winnellie",
    "sg:classifiers":[
        {
            "category":"Shopping",
            "subcategory":"Stationery & Office Supplies",
            "type":"Retail Goods"
        }
    ],
    "sg:phone":"+61 8 8984 3211",
    "sg:postcode":"0820",
    "sg:province":"NT",
    "sg:tags":[
        "packaging",
        "material"
    ],
    "wof:name":"C & R Distributors Pty Ltd",
    "wof:placetype":"venue"
},
  "geometry": {"coordinates":[130.87283325199999,-12.4285621643],"type":"Point"}
}