{
  "type": "Feature",
  "properties": {
    "addr:full":"6 Westbrook St Kew East VIC 3102",
    "addr:housenumber":"6",
    "addr:postcode":"3102",
    "addr:street":"Westbrook St",
    "iso:country":"AU",
    "sg:address":"6 Westbrook St",
    "sg:city":"Kew East",
    "sg:classifiers":[
        {
            "category":"Professional",
            "subcategory":"Accounting & Tax Preparation",
            "type":"Services"
        }
    ],
    "sg:phone":"+61 3 8851 3666",
    "sg:postcode":"3102",
    "sg:province":"VIC",
    "sg:tags":[
        "accountant",
        "auditor"
    ],
    "wof:name":"Huntington & Associates",
    "wof:placetype":"venue"
},
  "geometry": {"coordinates":[145.052337647,-37.7985572815],"type":"Point"}
}