{
  "type": "Feature",
  "properties": {
    "iso:country":"AU",
    "sg:address":"8- 10 Mercury Drv",
    "sg:city":"Shepparton",
    "sg:classifiers":[
        {
            "category":"Building & Trades",
            "subcategory":"Construction",
            "type":"Services"
        }
    ],
    "sg:phone":"+61 3 5821 2544",
    "sg:postcode":"3630",
    "sg:province":"VIC",
    "sg:tags":[
        "window",
        "aluminium"
    ],
    "wof:name":"O'Sullivan Bricks & Windows",
    "wof:placetype":"venue"
},
  "geometry": {"coordinates":[145.39981079099999,-36.3531074524],"type":"Point"}
}