{
  "type": "Feature",
  "properties": {
    "addr:full":"Suite 1/ 110 Main St Romsey VIC 3434",
    "addr:housenumber":"/ 110",
    "addr:postcode":"3434",
    "addr:street":"Main St",
    "iso:country":"AU",
    "sg:address":"Suite 1/ 110 Main St",
    "sg:city":"Romsey",
    "sg:classifiers":[
        {
            "category":"Building & Trades",
            "subcategory":"Construction",
            "type":"Services"
        }
    ],
    "sg:phone":"+61 3 5429 5722",
    "sg:postcode":"3434",
    "sg:province":"VIC",
    "sg:tags":[
        "roof"
    ],
    "wof:name":"Rix Roofing",
    "wof:placetype":"venue"
},
  "geometry": {"coordinates":[144.743118286,-37.349029541],"type":"Point"}
}