{
  "type": "Feature",
  "properties": {
    "addr:full":"350 St Georges Rd Thornbury VIC 3071",
    "addr:housenumber":"350",
    "addr:postcode":"3071",
    "addr:street":"St Georges Rd",
    "iso:country":"AU",
    "sg:address":"350 St Georges Rd",
    "sg:city":"Thornbury",
    "sg:classifiers":[
        {
            "category":"Home & Garden",
            "subcategory":"Home Furnishings",
            "type":"Retail Goods"
        }
    ],
    "sg:phone":"+61 3 9480 1879",
    "sg:postcode":"3071",
    "sg:province":"VIC",
    "sg:tags":[
        "shower",
        "screen"
    ],
    "wof:name":"Preston Glass & Mirrors",
    "wof:placetype":"venue"
},
  "geometry": {"coordinates":[144.99383544899999,-37.7584953308],"type":"Point"}
}