{
  "type": "Feature",
  "properties": {
    "addr:full":"3/ 474 Nepean Hwy Frankston VIC 3199",
    "addr:housenumber":"/ 474",
    "addr:postcode":"3199",
    "addr:street":"Nepean Hwy",
    "iso:country":"AU",
    "sg:address":"3/ 474 Nepean Hwy",
    "sg:city":"Frankston",
    "sg:classifiers":[
        {
            "category":"Real Estate",
            "subcategory":"Real Estate Agent",
            "type":"Services"
        }
    ],
    "sg:phone":"+61 3 9783 6300",
    "sg:postcode":"3199",
    "sg:province":"VIC",
    "wof:name":"Property Link Real Estate Pty Ltd",
    "wof:placetype":"venue"
},
  "geometry": {"coordinates":[145.120635986,-38.1435699463],"type":"Point"}
}