{
  "type": "Feature",
  "properties": {
    "addr:full":"11 Production Ave Ernest QLD 4214",
    "addr:housenumber":"11",
    "addr:postcode":"4214",
    "addr:street":"Production Ave Ernest",
    "iso:country":"AU",
    "sg:address":"11 Production Ave",
    "sg:city":"Ernest",
    "sg:classifiers":[
        {
            "category":"Retail",
            "subcategory":"Auto Repair",
            "type":"Services"
        }
    ],
    "sg:phone":"+61 7 5574 6811",
    "sg:postcode":"4214",
    "sg:province":"QLD",
    "sg:tags":[
        "repairer",
        "motor",
        "engineer"
    ],
    "wof:name":"Bryce Racing Developments",
    "wof:placetype":"venue"
},
  "geometry": {"coordinates":[153.362091064,-27.9675712585],"type":"Point"}
}