{
  "type": "Feature",
  "properties": {
    "addr:full":"1/ 184 New Town Rd New Town TAS 7008",
    "addr:housenumber":"/ 184",
    "addr:postcode":"7008",
    "addr:street":"New Town Rd",
    "iso:country":"AU",
    "sg:address":"1/ 184 New Town Rd",
    "sg:city":"New Town",
    "sg:classifiers":[
        {
            "category":"Retail",
            "subcategory":"Repair Shop",
            "type":"Services"
        }
    ],
    "sg:phone":"+61 3 6228 3754",
    "sg:postcode":"7008",
    "sg:province":"TAS",
    "sg:tags":[
        "upholsterer"
    ],
    "wof:name":"Affordable Curtains & Blinds",
    "wof:placetype":"venue"
},
  "geometry": {"coordinates":[147.304244995,-42.8582038879],"type":"Point"}
}