{
  "type": "Feature",
  "properties": {
    "addr:full":"21 Sylvan Crs Surrey Downs SA 5126",
    "addr:housenumber":"21",
    "addr:postcode":"5126",
    "addr:street":"Sylvan Crs",
    "iso:country":"AU",
    "sg:address":"21 Sylvan Crs",
    "sg:city":"Surrey Downs",
    "sg:classifiers":[
        {
            "category":"Building & Trades",
            "subcategory":"Construction",
            "type":"Services"
        }
    ],
    "sg:phone":"+61 418 846 909",
    "sg:postcode":"5126",
    "sg:province":"SA",
    "sg:tags":[
        "earth",
        "excavating",
        "moving",
        "contractor"
    ],
    "wof:name":"Jones C G",
    "wof:placetype":"venue"
},
  "geometry": {"coordinates":[138.70582580600001,-34.8008804321],"type":"Point"}
}