{
  "type": "Feature",
  "properties": {
    "addr:full":"23 Church St Kangaroo Flat VIC 3555",
    "addr:housenumber":"23",
    "addr:postcode":"3555",
    "addr:street":"Church St",
    "iso:country":"AU",
    "sg:address":"23 Church St",
    "sg:city":"Kangaroo Flat",
    "sg:classifiers":[
        {
            "category":"Shopping",
            "subcategory":"Party Supplies",
            "type":"Retail Goods"
        }
    ],
    "sg:phone":"+61 3 5447 8219",
    "sg:postcode":"3555",
    "sg:province":"VIC",
    "sg:tags":[
        "hire",
        "costume"
    ],
    "wof:name":"Costume Cupboard The",
    "wof:placetype":"venue"
},
  "geometry": {"coordinates":[144.24493408199999,-36.7996101379],"type":"Point"}
}