{
  "type": "Feature",
  "properties": {
    "addr:full":"Tonkin St Wharf Cronulla NSW 2230",
    "addr:postcode":"2230",
    "addr:street":"Tonkin St",
    "iso:country":"AU",
    "sg:address":"Tonkin St Wharf",
    "sg:city":"Cronulla",
    "sg:classifiers":[
        {
            "category":"Recreation",
            "subcategory":"Boat Charter",
            "type":"Entertainment"
        }
    ],
    "sg:phone":"+61 2 9525 1667",
    "sg:postcode":"2230",
    "sg:province":"NSW",
    "wof:name":"Bianca Deep Sea & Game Fishing Charters",
    "wof:placetype":"venue"
},
  "geometry": {"coordinates":[151.15130615199999,-34.0549240112],"type":"Point"}
}