{
  "type": "Feature",
  "properties": {
    "iso:country":"AU",
    "sg:address":"Ksk7/ 620 Victoria St",
    "sg:city":"Richmond",
    "sg:classifiers":[
        {
            "category":"Personal",
            "subcategory":"Shoe Repair & Shine",
            "type":"Services"
        }
    ],
    "sg:phone":"+61 3 9421 0005",
    "sg:postcode":"3121",
    "sg:province":"VIC",
    "sg:tags":[
        "footwear"
    ],
    "wof:name":"Yes We Do Shoe And Watch Repairs",
    "wof:placetype":"venue"
},
  "geometry": {"coordinates":[145.012741089,-37.8118362427],"type":"Point"}
}