{
  "type": "Feature",
  "properties": {
    "iso:country":"AU",
    "sg:address":"55 Henry St",
    "sg:city":"Lilyfield",
    "sg:classifiers":[
        {
            "category":"Arts & Performance",
            "subcategory":"Music",
            "type":"Entertainment"
        }
    ],
    "sg:phone":"+61 1800 100 606",
    "sg:postcode":"2040",
    "sg:province":"NSW",
    "sg:tags":[
        "mobile",
        "jockey",
        "disc"
    ],
    "wof:name":"Mobydisc",
    "wof:placetype":"venue"
},
  "geometry": {"coordinates":[151.157455,-33.874203],"type":"Point"}
}