{
  "type": "Feature",
  "properties": {
    "iso:country":"AU",
    "sg:address":"Shop 2, 238 Young Rd",
    "sg:city":"Narangba",
    "sg:classifiers":[
        {
            "category":"Real Estate",
            "subcategory":"Real Estate Agent",
            "type":"Services"
        }
    ],
    "sg:phone":"+61 7 3385 5244",
    "sg:postcode":"4504",
    "sg:province":"QLD",
    "wof:name":"PRDnationwide Narangba",
    "wof:placetype":"venue"
},
  "geometry": {"coordinates":[152.93885803200001,-27.1735038757],"type":"Point"}
}