{
  "type": "Feature",
  "properties": {
    "iso:country":"AU",
    "sg:address":"5- 25 Berkeley Rd",
    "sg:city":"Berkeley Vale",
    "sg:classifiers":[
        {
            "category":"Education",
            "subcategory":"School",
            "type":"Public Place"
        }
    ],
    "sg:phone":"+61 2 4388 1899",
    "sg:postcode":"2261",
    "sg:province":"NSW",
    "sg:tags":[
        "state",
        "-",
        "nsw"
    ],
    "wof:name":"Berkeley Vale Community High School",
    "wof:placetype":"venue"
},
  "geometry": {"coordinates":[151.417526,-33.338886],"type":"Point"}
}