{
  "type": "Feature",
  "properties": {
    "addr:full":"RSM 84 Busselton WA 6280",
    "addr:housenumber":"84",
    "addr:postcode":"6280",
    "addr:street":"Rsm",
    "iso:country":"AU",
    "sg:address":"RSM 84",
    "sg:city":"Busselton",
    "sg:classifiers":[
        {
            "category":"Building & Trades",
            "subcategory":"Landscaping Services",
            "type":"Services"
        }
    ],
    "sg:phone":"+61 8 9755 4072",
    "sg:postcode":"6280",
    "sg:province":"WA",
    "sg:tags":[
        "control",
        "weed"
    ],
    "wof:name":"Abbey Pest Control.",
    "wof:placetype":"venue"
},
  "geometry": {"coordinates":[115.248596191,-33.6812400818],"type":"Point"}
}