{
  "type": "Feature",
  "properties": {
    "addr:full":"60 Herbert St Allora QLD 4362",
    "addr:housenumber":"60",
    "addr:postcode":"4362",
    "addr:street":"Herbert St",
    "iso:country":"AU",
    "sg:address":"60 Herbert St",
    "sg:city":"Allora",
    "sg:classifiers":[
        {
            "category":"Arts & Performance",
            "subcategory":"Art Gallery",
            "type":"Entertainment"
        }
    ],
    "sg:phone":"+61 438 173 926",
    "sg:postcode":"4362",
    "sg:province":"QLD",
    "wof:name":"The Sunflower Gallery",
    "wof:placetype":"venue"
},
  "geometry": {"coordinates":[151.98277282699999,-28.0346813202],"type":"Point"}
}