{
  "type": "Feature",
  "properties": {
    "addr:full":"14 McEwan St Belmont NSW 2280",
    "addr:housenumber":"14",
    "addr:postcode":"2280",
    "addr:street":"Mcewan St",
    "iso:country":"AU",
    "sg:address":"14 McEwan St",
    "sg:city":"Belmont",
    "sg:classifiers":[
        {
            "category":"Building & Trades",
            "subcategory":"Construction",
            "type":"Services"
        }
    ],
    "sg:phone":"+61 2 4947 0350",
    "sg:postcode":"2280",
    "sg:province":"NSW",
    "sg:tags":[
        "concrete",
        "contractor"
    ],
    "wof:name":"Newcastle Pump Action",
    "wof:placetype":"venue"
},
  "geometry": {"coordinates":[151.657745361,-33.0479698181],"type":"Point"}
}