{
  "type": "Feature",
  "properties": {
    "addr:full":"300- 314 The Driftway Londonderry NSW 2753",
    "addr:housenumber":"314",
    "addr:postcode":"2753",
    "addr:street":"The Driftway",
    "iso:country":"AU",
    "sg:address":"300- 314 The Driftway",
    "sg:city":"Londonderry",
    "sg:classifiers":[
        {
            "category":"Commercial Area",
            "type":"Public Place"
        }
    ],
    "sg:phone":"+61 2 4572 5551",
    "sg:postcode":"2753",
    "sg:province":"NSW",
    "sg:tags":[
        "heavy",
        "carrier"
    ],
    "wof:name":"Drury's Transport Pty Ltd",
    "wof:placetype":"venue"
},
  "geometry": {"coordinates":[150.740036011,-33.623840332],"type":"Point"}
}