{
  "type": "Feature",
  "properties": {
    "addr:full":"9 Yarabah Ave Gordon NSW 2072",
    "addr:housenumber":"9",
    "addr:postcode":"2072",
    "addr:street":"Yarabah Ave",
    "iso:country":"AU",
    "sg:address":"9 Yarabah Ave",
    "sg:city":"Gordon",
    "sg:classifiers":[
        {
            "category":"Utilities",
            "subcategory":"Mobile Phone",
            "type":"Services"
        }
    ],
    "sg:phone":"+61 2 9498 6663",
    "sg:postcode":"2072",
    "sg:province":"NSW",
    "sg:tags":[
        "assembly",
        "part",
        "electronic"
    ],
    "wof:name":"Derian Pty Ltd",
    "wof:placetype":"venue"
},
  "geometry": {"coordinates":[151.15315246599999,-33.7601356506],"type":"Point"}
}