{
  "type": "Feature",
  "properties": {
    "addr:full":"(Level 3), Melbourne Central Shopping Centre, Cnr Swanston and LaTrobe Sts Melbourne VIC 3000",
    "addr:postcode":"3000",
    "addr:street":"Cnr Swanston;Sts",
    "iso:country":"AU",
    "sg:address":"(Level 3), Melbourne Central Shopping Centre, Cnr Swanston and LaTrobe Sts",
    "sg:city":"Melbourne",
    "sg:classifiers":[
        {
            "category":"Restaurant",
            "type":"Food & Drink"
        }
    ],
    "sg:phone":"+61 3 9663 1940",
    "sg:postcode":"3000",
    "sg:province":"VIC",
    "sg:website":"http://www.tomodachimelbournecentral.com/",
    "wof:name":"Tomodachi Melbourne Central",
    "wof:placetype":"venue"
},
  "geometry": {"coordinates":[144.96641540499999,-37.8152236938],"type":"Point"}
}