{
  "type": "Feature",
  "properties": {
    "addr:full":"23 Cotswold St Morayfield QLD 4506",
    "addr:housenumber":"23",
    "addr:postcode":"4506",
    "addr:street":"Cotswold St",
    "iso:country":"AU",
    "sg:address":"23 Cotswold St",
    "sg:city":"Morayfield",
    "sg:classifiers":[
        {
            "category":"Utilities",
            "subcategory":"Electric",
            "type":"Services"
        }
    ],
    "sg:phone":"+61 417 615 534",
    "sg:postcode":"4506",
    "sg:province":"QLD",
    "sg:tags":[
        "electrical",
        "contractor"
    ],
    "wof:name":"Bell D C Powerpoles",
    "wof:placetype":"venue"
},
  "geometry": {"coordinates":[152.95690918,-27.1140232086],"type":"Point"}
}