{
  "type": "Feature",
  "properties": {
    "addr:full":"3/ 145 William St East Sydney NSW 2010",
    "addr:housenumber":"/ 145",
    "addr:postcode":"2010",
    "addr:street":"William St East",
    "iso:country":"AU",
    "sg:address":"3/ 145 William St",
    "sg:city":"East Sydney",
    "sg:classifiers":[
        {
            "category":"Professional",
            "subcategory":"Computer Services",
            "type":"Services"
        }
    ],
    "sg:phone":"+61 2 9368 1699",
    "sg:postcode":"2010",
    "sg:province":"NSW",
    "sg:tags":[
        "consultant",
        "system"
    ],
    "wof:name":"Data Recovery Experts",
    "wof:placetype":"venue"
},
  "geometry": {"coordinates":[151.21841430699999,-33.8748588562],"type":"Point"}
}