{
  "type": "Feature",
  "properties": {
    "addr:full":"996 Wanneroo Rd Wanneroo WA 6065",
    "addr:housenumber":"996",
    "addr:postcode":"6065",
    "addr:street":"Wanneroo Rd",
    "iso:country":"AU",
    "sg:address":"996 Wanneroo Rd",
    "sg:city":"Wanneroo",
    "sg:classifiers":[
        {
            "category":"Fast Food",
            "type":"Food & Drink"
        }
    ],
    "sg:phone":"+61 8 9405 7433",
    "sg:postcode":"6065",
    "sg:province":"WA",
    "sg:tags":[
        "away",
        "take"
    ],
    "wof:name":"McDonald's Family Restaurants",
    "wof:placetype":"venue"
},
  "geometry": {"coordinates":[115.78510284399999,-31.7216415405],"type":"Point"}
}