{
  "type": "Feature",
  "properties": {
    "addr:full":"Bldg c/ 210 Evans Rd Salisbury QLD 4107",
    "addr:housenumber":"210",
    "addr:postcode":"4107",
    "addr:street":"C /;Evans Rd",
    "iso:country":"AU",
    "sg:address":"Bldg c/ 210 Evans Rd",
    "sg:city":"Salisbury",
    "sg:classifiers":[
        {
            "category":"Wholesale",
            "subcategory":"Machinery & Supplies",
            "type":"Manufacturing & Wholesale Goods"
        }
    ],
    "sg:phone":"+61 7 3277 0737",
    "sg:postcode":"4107",
    "sg:province":"QLD",
    "sg:tags":[
        "equipment",
        "welding"
    ],
    "wof:name":"UTP Sales",
    "wof:placetype":"venue"
},
  "geometry": {"coordinates":[153.03195190400001,-27.5449352264],"type":"Point"}
}