{
  "type": "Feature",
  "properties": {
    "addr:full":"597 Elizabeth St Melbourne VIC 3000",
    "addr:housenumber":"597",
    "addr:postcode":"3000",
    "addr:street":"Elizabeth St",
    "iso:country":"AU",
    "sg:address":"597 Elizabeth St",
    "sg:city":"Melbourne",
    "sg:classifiers":[
        {
            "category":"Fast Food",
            "type":"Food & Drink"
        }
    ],
    "sg:phone":"+61 3 9329 4040",
    "sg:postcode":"3000",
    "sg:province":"VIC",
    "sg:tags":[
        "away",
        "take"
    ],
    "wof:name":"Classic Curry Company",
    "wof:placetype":"venue"
},
  "geometry": {"coordinates":[144.958221436,-37.804271698],"type":"Point"}
}