{
  "type": "Feature",
  "properties": {
    "iso:country":"AU",
    "sg:address":"365 Ocean Drv",
    "sg:city":"Laurieton",
    "sg:classifiers":[
        {
            "category":"Building & Trades",
            "subcategory":"Construction",
            "type":"Services"
        }
    ],
    "sg:phone":"+61 2 6559 9581",
    "sg:postcode":"2443",
    "sg:province":"NSW",
    "sg:tags":[
        "contractor"
    ],
    "wof:name":"Faddy RJ & MJ Pty Ltd",
    "wof:placetype":"venue"
},
  "geometry": {"coordinates":[152.78633099999999,-31.636118],"type":"Point"}
}