{
  "type": "Feature",
  "properties": {
    "addr:full":"6113 Wellington St Bondi NSW 2026",
    "addr:housenumber":"6113",
    "addr:postcode":"2026",
    "addr:street":"Wellington St",
    "iso:country":"AU",
    "sg:address":"6113 Wellington St",
    "sg:city":"Bondi",
    "sg:classifiers":[
        {
            "category":"Sports & Exercise",
            "subcategory":"Gym",
            "type":"Entertainment"
        }
    ],
    "sg:phone":"+61 418 806 039",
    "sg:postcode":"2026",
    "sg:province":"NSW",
    "sg:tags":[
        "health",
        "fitness"
    ],
    "wof:name":"P B Fitness",
    "wof:placetype":"venue"
},
  "geometry": {"coordinates":[151.264694214,-33.8909988403],"type":"Point"}
}