{
  "type": "Feature",
  "properties": {
    "addr:full":"Shop 8/ 6 Lawson St Byron Bay NSW 2481",
    "addr:housenumber":"shop 8 / 6",
    "addr:postcode":"2481",
    "addr:street":"Lawson St",
    "iso:country":"AU",
    "sg:address":"Shop 8/ 6 Lawson St",
    "sg:city":"Byron Bay",
    "sg:classifiers":[
        {
            "category":"Wholesale",
            "subcategory":"Apparel",
            "type":"Manufacturing & Wholesale Goods"
        }
    ],
    "sg:phone":"+61 2 6680 7370",
    "sg:postcode":"2481",
    "sg:province":"NSW",
    "sg:tags":[
        "wholesaler",
        "mfrs",
        "sportswear",
        "women's"
    ],
    "wof:name":"Funksta",
    "wof:placetype":"venue"
},
  "geometry": {"coordinates":[153.61297607399999,-28.642414093],"type":"Point"}
}