{
  "type": "Feature",
  "properties": {
    "iso:country":"AU",
    "sg:address":"Lvl 18/ 123 Pitt St",
    "sg:city":"Sydney",
    "sg:classifiers":[
        {
            "category":"Real Estate",
            "subcategory":"Real Estate Services",
            "type":"Services"
        }
    ],
    "sg:phone":"+61 2 9036 6772",
    "sg:postcode":"2000",
    "sg:province":"NSW",
    "sg:tags":[
        "valuer"
    ],
    "wof:name":"Knight Frank Valuations",
    "wof:placetype":"venue"
},
  "geometry": {"coordinates":[151.20838928200001,-33.8667030334],"type":"Point"}
}