{
  "type": "Feature",
  "properties": {
    "addr:full":"681 Darling St Rozelle NSW 2039",
    "addr:housenumber":"681",
    "addr:postcode":"2039",
    "addr:street":"Darling St",
    "iso:country":"AU",
    "sg:address":"681 Darling St",
    "sg:city":"Rozelle",
    "sg:classifiers":[
        {
            "category":"Fast Food",
            "type":"Food & Drink"
        }
    ],
    "sg:phone":"+61 2 9818 7166",
    "sg:postcode":"2039",
    "sg:province":"NSW",
    "sg:tags":[
        "away",
        "take"
    ],
    "wof:name":"Rozelle Pizzeria",
    "wof:placetype":"venue"
},
  "geometry": {"coordinates":[151.16966247600001,-33.8640060425],"type":"Point"}
}