{
  "type": "Feature",
  "properties": {
    "addr:full":"19 Clavering Rd Bayswater WA 6053",
    "addr:housenumber":"19",
    "addr:postcode":"6053",
    "addr:street":"Clavering Rd",
    "iso:country":"AU",
    "sg:address":"19 Clavering Rd",
    "sg:city":"Bayswater",
    "sg:classifiers":[
        {
            "category":"Building & Trades",
            "subcategory":"Pest Control",
            "type":"Services"
        }
    ],
    "sg:phone":"+61 8 9473 0120",
    "sg:postcode":"6053",
    "sg:province":"WA",
    "sg:tags":[
        "vibratory",
        "feeding",
        "equipment"
    ],
    "wof:name":"Vibration Systems & Solutions",
    "wof:placetype":"venue"
},
  "geometry": {"coordinates":[115.920120239,-31.9152946472],"type":"Point"}
}