{
  "type": "Feature",
  "properties": {
    "iso:country":"AU",
    "sg:address":"Shop 3 258 Ross River Rd",
    "sg:city":"Aitkenvale",
    "sg:classifiers":[
        {
            "category":"Personal",
            "subcategory":"Piercing",
            "type":"Services"
        }
    ],
    "sg:phone":"+61 7 4775 1080",
    "sg:postcode":"4814",
    "sg:province":"QLD",
    "sg:tags":[
        "body",
        "ear"
    ],
    "wof:name":"Lees Tattooing & Body Piercing Studio",
    "wof:placetype":"venue"
},
  "geometry": {"coordinates":[146.769211,-19.296791],"type":"Point"}
}