{
  "type": "Feature",
  "properties": {
    "addr:full":"210 Brunker Rd Adamstown NSW 2289",
    "addr:housenumber":"210",
    "addr:postcode":"2289",
    "addr:street":"Brunker Rd",
    "iso:country":"AU",
    "sg:address":"210 Brunker Rd",
    "sg:city":"Adamstown",
    "sg:classifiers":[
        {
            "category":"Manufacturing",
            "subcategory":"Electronics",
            "type":"Manufacturing & Wholesale Goods"
        }
    ],
    "sg:phone":"+61 2 4952 9733",
    "sg:postcode":"2289",
    "sg:province":"NSW",
    "sg:tags":[
        "oven",
        "microwave"
    ],
    "wof:name":"J & P TV & Electronics",
    "wof:placetype":"venue"
},
  "geometry": {"coordinates":[151.72624206500001,-32.9333114624],"type":"Point"}
}