{
  "type": "Feature",
  "properties": {
    "addr:full":"Suite 1 1263 North East Rd Ridgehaven SA 5097",
    "addr:housenumber":"1263",
    "addr:postcode":"5097",
    "addr:street":"North East Rd",
    "iso:country":"AU",
    "sg:address":"Suite 1 1263 North East Rd",
    "sg:city":"Ridgehaven",
    "sg:classifiers":[
        {
            "category":"Professional",
            "subcategory":"Accounting & Tax Preparation",
            "type":"Services"
        }
    ],
    "sg:phone":"+61 8 8264 9000",
    "sg:postcode":"5097",
    "sg:province":"SA",
    "sg:tags":[
        "accountant",
        "auditor"
    ],
    "wof:name":"CTA Accountants Pty Ltd",
    "wof:placetype":"venue"
},
  "geometry": {"coordinates":[138.716705322,-34.8208808899],"type":"Point"}
}