{
  "type": "Feature",
  "properties": {
    "addr:full":"PO Box 216 Tynong VIC 3813",
    "addr:postcode":"3813",
    "iso:country":"AU",
    "sg:address":"PO Box 216",
    "sg:city":"Tynong",
    "sg:classifiers":[
        {
            "category":"Building & Trades",
            "subcategory":"Construction",
            "type":"Services"
        }
    ],
    "sg:phone":"+61 409 850 043",
    "sg:postcode":"3813",
    "sg:province":"VIC",
    "sg:tags":[
        "earth",
        "excavating",
        "moving",
        "contractor"
    ],
    "wof:name":"Tribuzi",
    "wof:placetype":"venue"
},
  "geometry": {"coordinates":[145.630447,-38.07053],"type":"Point"}
}