{
  "type": "Feature",
  "properties": {
    "addr:full":"17 Belmont Rd Glen Waverley VIC 3150",
    "addr:housenumber":"17",
    "addr:postcode":"3150",
    "addr:street":"Belmont Rd",
    "iso:country":"AU",
    "sg:address":"17 Belmont Rd",
    "sg:city":"Glen Waverley",
    "sg:classifiers":[
        {
            "category":"Building & Trades",
            "subcategory":"Construction",
            "type":"Services"
        }
    ],
    "sg:phone":"+61 3 9802 7588",
    "sg:postcode":"3150",
    "sg:province":"VIC",
    "sg:tags":[
        "contractor"
    ],
    "wof:name":"O B J & A J Snowball",
    "wof:placetype":"venue"
},
  "geometry": {"coordinates":[145.15785217300001,-37.8627128601],"type":"Point"}
}