{
  "type": "Feature",
  "properties": {
    "addr:full":"Shp2095/Lvl2/ 33 Macquarie St Liverpool NSW 2170",
    "addr:housenumber":"33",
    "addr:postcode":"2170",
    "addr:street":"Macquarie St",
    "iso:country":"AU",
    "sg:address":"Shp2095/Lvl2/ 33 Macquarie St",
    "sg:city":"Liverpool",
    "sg:classifiers":[
        {
            "category":"Health Services",
            "subcategory":"Health Practitioner",
            "type":"Services"
        }
    ],
    "sg:phone":"+61 2 9734 8088",
    "sg:postcode":"2170",
    "sg:province":"NSW",
    "sg:tags":[
        "herbalist"
    ],
    "wof:name":"Fire Dragon Healing Centre",
    "wof:placetype":"venue"
},
  "geometry": {"coordinates":[150.92625427199999,-33.9145584106],"type":"Point"}
}