{
  "type": "Feature",
  "properties": {
    "addr:full":"13 Rose St Manjimup WA 6258",
    "addr:housenumber":"13",
    "addr:postcode":"6258",
    "addr:street":"Rose St",
    "iso:country":"AU",
    "sg:address":"13 Rose St",
    "sg:city":"Manjimup",
    "sg:classifiers":[
        {
            "category":"Home & Garden",
            "subcategory":"Garden Supply",
            "type":"Retail Goods"
        }
    ],
    "sg:phone":"+61 8 9772 4470",
    "sg:postcode":"6258",
    "sg:province":"WA",
    "sg:tags":[
        "turf",
        "lawn"
    ],
    "wof:name":"Killarney Nursery",
    "wof:placetype":"venue"
},
  "geometry": {"coordinates":[116.144432068,-34.241985321],"type":"Point"}
}