{
  "type": "Feature",
  "properties": {
    "addr:full":"Lvl 7/ 140 Bourke St Melbourne VIC 3000",
    "addr:housenumber":"/ 140",
    "addr:postcode":"3000",
    "addr:street":"Bourke St",
    "iso:country":"AU",
    "sg:address":"Lvl 7/ 140 Bourke St",
    "sg:city":"Melbourne",
    "sg:classifiers":[
        {
            "category":"Real Estate",
            "subcategory":"Real Estate Agent",
            "type":"Services"
        }
    ],
    "sg:phone":"+61 3 9650 6014",
    "sg:postcode":"3000",
    "sg:province":"VIC",
    "sg:tags":[
        "buyer"
    ],
    "wof:name":"Georgia Property Pty Ltd",
    "wof:placetype":"venue"
},
  "geometry": {"coordinates":[144.969039917,-37.8123855591],"type":"Point"}
}