{
  "type": "Feature",
  "properties": {
    "addr:full":"Caloundra Village Shopping Centre Ormuz Ave (Next to the Post Office) Caloundra QLD 4551",
    "addr:postcode":"4551",
    "addr:street":"Ave Next",
    "iso:country":"AU",
    "sg:address":"Caloundra Village Shopping Centre Ormuz Ave (Next to the Post Office)",
    "sg:city":"Caloundra",
    "sg:classifiers":[
        {
            "category":"Personal",
            "subcategory":"Beauty Salon",
            "type":"Services"
        }
    ],
    "sg:phone":"+61 7 5492 6733",
    "sg:postcode":"4551",
    "sg:province":"QLD",
    "sg:tags":[
        "hairdresser"
    ],
    "wof:name":"Hot Hair Works",
    "wof:placetype":"venue"
},
  "geometry": {"coordinates":[153.132324219,-26.8036308289],"type":"Point"}
}