{
  "type": "Feature",
  "properties": {
    "addr:full":"South Western Hwy Manjimup WA 6258",
    "addr:postcode":"6258",
    "addr:street":"South Western Hwy",
    "iso:country":"AU",
    "sg:address":"South Western Hwy",
    "sg:city":"Manjimup",
    "sg:classifiers":[
        {
            "category":"Autos & Motor Vehicles",
            "subcategory":"Fuel & Gas Station",
            "type":"Retail Goods"
        }
    ],
    "sg:phone":"+61 8 9771 1892",
    "sg:postcode":"6258",
    "sg:province":"WA",
    "wof:name":"Ampol",
    "wof:placetype":"venue"
},
  "geometry": {"coordinates":[116.14914703399999,-34.2399177551],"type":"Point"}
}