{
  "type": "Feature",
  "properties": {
    "addr:full":"66 Avenue Rd Mosman NSW 2088",
    "addr:housenumber":"66",
    "addr:postcode":"2088",
    "addr:street":"Avenue Rd",
    "iso:country":"AU",
    "sg:address":"66 Avenue Rd",
    "sg:city":"Mosman",
    "sg:classifiers":[
        {
            "category":"Health Services",
            "subcategory":"Doctor",
            "type":"Services"
        }
    ],
    "sg:phone":"+61 2 9969 8080",
    "sg:postcode":"2088",
    "sg:province":"NSW",
    "sg:tags":[
        "medical",
        "practitioner"
    ],
    "wof:name":"Rowley Sue Dr",
    "wof:placetype":"venue"
},
  "geometry": {"coordinates":[151.23890685999999,-33.8316307068],"type":"Point"}
}