{
  "type": "Feature",
  "properties": {
    "addr:full":"17-21 Bushman Drv Jimboomba QLD 4280",
    "addr:housenumber":"17-21",
    "addr:postcode":"4280",
    "addr:street":"Bushman Drv",
    "iso:country":"AU",
    "sg:address":"17-21 Bushman Drv",
    "sg:city":"Jimboomba",
    "sg:classifiers":[
        {
            "category":"Social Services",
            "subcategory":"Adult Care",
            "type":"Services"
        }
    ],
    "sg:phone":"+61 7 3386 0144",
    "sg:postcode":"4280",
    "sg:province":"QLD",
    "sg:tags":[
        "towing"
    ],
    "wof:name":"Bega Towing & Transport Services",
    "wof:placetype":"venue"
},
  "geometry": {"coordinates":[152.966949,-27.816729],"type":"Point"}
}