{
  "type": "Feature",
  "properties": {
    "iso:country":"AU",
    "sg:address":"PO Box 107",
    "sg:city":"Kangarilla",
    "sg:classifiers":[
        {
            "category":"Building & Trades",
            "subcategory":"Equipment Rental",
            "type":"Services"
        }
    ],
    "sg:phone":"+61 427 826 370",
    "sg:postcode":"5157",
    "sg:province":"SA",
    "sg:tags":[
        "crane",
        "hire"
    ],
    "wof:name":"Skyhooks Crane Trucks",
    "wof:placetype":"venue"
},
  "geometry": {"coordinates":[138.65745544399999,-35.148399353],"type":"Point"}
}