{
  "type": "Feature",
  "properties": {
    "iso:country":"AU",
    "sg:address":"11 Jardine St",
    "sg:city":"Fairy Meadow",
    "sg:classifiers":[
        {
            "category":"Retail",
            "subcategory":"Repair Shop",
            "type":"Services"
        }
    ],
    "sg:phone":"+61 2 4284 7379",
    "sg:postcode":"2519",
    "sg:province":"NSW",
    "sg:tags":[
        "machine",
        "repairs",
        "part",
        "dryer",
        "washing"
    ],
    "wof:name":"Kings Refrigeration",
    "wof:placetype":"venue"
},
  "geometry": {"coordinates":[150.89747600000001,-34.388447],"type":"Point"}
}