{
  "type": "Feature",
  "properties": {
    "addr:full":"21 Jarrah Rd Roleystone WA 6111",
    "addr:housenumber":"21",
    "addr:postcode":"6111",
    "addr:street":"Jarrah Rd",
    "iso:country":"AU",
    "sg:address":"21 Jarrah Rd",
    "sg:city":"Roleystone",
    "sg:classifiers":[
        {
            "category":"Food & Beverages",
            "subcategory":"Liquor & Beverages",
            "type":"Retail Goods"
        }
    ],
    "sg:phone":"+61 8 9397 5545",
    "sg:postcode":"6111",
    "sg:province":"WA",
    "sg:tags":[
        "store"
    ],
    "wof:name":"Cellarbrations",
    "wof:placetype":"venue"
},
  "geometry": {"coordinates":[116.069419861,-32.1133041382],"type":"Point"}
}