{
  "type": "Feature",
  "properties": {
    "addr:full":"117 Victoria St Taree NSW 2430",
    "addr:housenumber":"117",
    "addr:postcode":"2430",
    "addr:street":"Victoria St",
    "iso:country":"AU",
    "sg:address":"117 Victoria St",
    "sg:city":"Taree",
    "sg:classifiers":[
        {
            "category":"Real Estate",
            "subcategory":"Real Estate Agent",
            "type":"Services"
        }
    ],
    "sg:phone":"+61 2 6551 7440",
    "sg:postcode":"2430",
    "sg:province":"NSW",
    "wof:name":"Equity Conveyancing",
    "wof:placetype":"venue"
},
  "geometry": {"coordinates":[152.46238700000001,-31.912453],"type":"Point"}
}