{
  "type": "Feature",
  "properties": {
    "addr:full":"316 Findon Rd Kidman Park SA 5025",
    "addr:housenumber":"316",
    "addr:postcode":"5025",
    "addr:street":"Findon Rd",
    "iso:country":"AU",
    "sg:address":"316 Findon Rd",
    "sg:city":"Kidman Park",
    "sg:classifiers":[
        {
            "category":"Sports & Exercise",
            "subcategory":"Sports Center",
            "type":"Entertainment"
        }
    ],
    "sg:phone":"+61 8 8235 0890",
    "sg:postcode":"5025",
    "sg:province":"SA",
    "sg:tags":[
        "ground"
    ],
    "wof:name":"Adelaide Indoor Sports Centre",
    "wof:placetype":"venue"
},
  "geometry": {"coordinates":[138.534866333,-34.9158439636],"type":"Point"}
}