{
  "type": "Feature",
  "properties": {
    "addr:full":"112 A Ernest St Crows Nest NSW 2065",
    "addr:housenumber":"112 a",
    "addr:postcode":"2065",
    "addr:street":"Ernest St",
    "iso:country":"AU",
    "sg:address":"112 A Ernest St",
    "sg:city":"Crows Nest",
    "sg:classifiers":[
        {
            "category":"School Buses",
            "type":"Transportation"
        }
    ],
    "sg:phone":"+61 2 9460 4608",
    "sg:postcode":"2065",
    "sg:province":"NSW",
    "sg:tags":[
        "nanny"
    ],
    "wof:name":"Nanny Australia",
    "wof:placetype":"venue"
},
  "geometry": {"coordinates":[151.20208740199999,-33.8258247375],"type":"Point"}
}