{
  "type": "Feature",
  "properties": {
    "addr:full":"13 Hakeville Ave Nunawading VIC 3131",
    "addr:housenumber":"13",
    "addr:postcode":"3131",
    "addr:street":"Hakeville Ave",
    "iso:country":"AU",
    "sg:address":"13 Hakeville Ave",
    "sg:city":"Nunawading",
    "sg:classifiers":[
        {
            "category":"Building & Trades",
            "subcategory":"Cleaning & Sanitation",
            "type":"Services"
        }
    ],
    "sg:phone":"+61 3 9877 4232",
    "sg:postcode":"3131",
    "sg:province":"VIC",
    "sg:tags":[
        "grease",
        "trap"
    ],
    "wof:name":"Royal Flush Liquid Waste",
    "wof:placetype":"venue"
},
  "geometry": {"coordinates":[145.18006897000001,-37.8046188354],"type":"Point"}
}