{
  "type": "Feature",
  "properties": {
    "iso:country":"AU",
    "sg:address":"PO Box 326",
    "sg:city":"Healesville",
    "sg:classifiers":[
        {
            "category":"Building & Trades",
            "subcategory":"Cleaning & Sanitation",
            "type":"Services"
        }
    ],
    "sg:phone":"+61 3 5962 4841",
    "sg:postcode":"3777",
    "sg:province":"VIC",
    "sg:tags":[
        "grease",
        "trap"
    ],
    "wof:name":"Yarra Valley Liquid Waste",
    "wof:placetype":"venue"
},
  "geometry": {"coordinates":[145.52145400000001,-37.651909],"type":"Point"}
}