{
  "type": "Feature",
  "properties": {
    "addr:full":"135 King St Bendigo VIC 3550",
    "addr:housenumber":"135",
    "addr:postcode":"3550",
    "addr:street":"King St",
    "iso:country":"AU",
    "sg:address":"135 King St",
    "sg:city":"Bendigo",
    "sg:classifiers":[
        {
            "category":"Travel",
            "subcategory":"Hotels & Motels",
            "type":"Entertainment"
        }
    ],
    "sg:phone":"+61 3 5443 6063",
    "sg:postcode":"3550",
    "sg:province":"VIC",
    "sg:tags":[
        "accommodation"
    ],
    "wof:name":"Golden Vine Hotel",
    "wof:placetype":"venue"
},
  "geometry": {"coordinates":[144.27471923799999,-36.7664985657],"type":"Point"}
}