{
  "type": "Feature",
  "properties": {
    "iso:country":"AU",
    "sg:address":"245 Dowling St",
    "sg:city":"Dungog",
    "sg:classifiers":[
        {
            "category":"Health Services",
            "subcategory":"Doctor",
            "type":"Services"
        }
    ],
    "sg:phone":"+61 2 4992 1739",
    "sg:postcode":"2420",
    "sg:province":"NSW",
    "sg:tags":[
        "medical",
        "practitioner"
    ],
    "wof:name":"Dew Duncan Dr",
    "wof:placetype":"venue"
},
  "geometry": {"coordinates":[151.758072,-32.400349],"type":"Point"}
}