{
  "type": "Feature",
  "properties": {
    "addr:full":"31 Lorensen Ave Merlynston VIC 3058",
    "addr:housenumber":"31",
    "addr:postcode":"3058",
    "addr:street":"Lorensen Ave",
    "iso:country":"AU",
    "sg:address":"31 Lorensen Ave",
    "sg:city":"Merlynston",
    "sg:classifiers":[
        {
            "category":"Personal",
            "subcategory":"Beauty Salon",
            "type":"Services"
        }
    ],
    "sg:phone":"+61 3 9354 1021",
    "sg:postcode":"3058",
    "sg:province":"VIC",
    "sg:tags":[
        "hairdresser"
    ],
    "wof:name":"Maxinne's Hair Design",
    "wof:placetype":"venue"
},
  "geometry": {"coordinates":[144.960403442,-37.7212867737],"type":"Point"}
}