{
  "type": "Feature",
  "properties": {
    "addr:full":"169 Phillip St Waterloo NSW 2017",
    "addr:housenumber":"169",
    "addr:postcode":"2017",
    "addr:street":"Phillip St",
    "iso:country":"AU",
    "sg:address":"169 Phillip St",
    "sg:city":"Waterloo",
    "sg:classifiers":[
        {
            "category":"Real Estate",
            "subcategory":"Architect",
            "type":"Services"
        }
    ],
    "sg:phone":"+61 2 9310 4533",
    "sg:postcode":"2017",
    "sg:province":"NSW",
    "wof:name":"Folk Lichtman & Associates Pty Ltd",
    "wof:placetype":"venue"
},
  "geometry": {"coordinates":[151.210494995,-33.8967247009],"type":"Point"}
}