{
  "type": "Feature",
  "properties": {
    "addr:full":"Shop 8, Mosman Arcade, 880 Military Rd Mosman NSW 2088",
    "addr:housenumber":"shop 8;880",
    "addr:postcode":"2088",
    "addr:street":"Mosman Arcade;Military Rd",
    "iso:country":"AU",
    "sg:address":"Shop 8, Mosman Arcade, 880 Military Rd",
    "sg:city":"Mosman",
    "sg:classifiers":[
        {
            "category":"Shopping",
            "subcategory":"Bridal",
            "type":"Retail Goods"
        }
    ],
    "sg:phone":"+61 2 9968 1480",
    "sg:postcode":"2088",
    "sg:province":"NSW",
    "sg:tags":[
        "hire",
        "wear"
    ],
    "wof:name":"Effie Bridal & Alterations",
    "wof:placetype":"venue"
},
  "geometry": {"coordinates":[151.244308472,-33.829914093],"type":"Point"}
}