{
  "type": "Feature",
  "properties": {
    "iso:country":"AU",
    "sg:address":"Cnr Marsden & Victoria Rds",
    "sg:city":"West Ryde",
    "sg:classifiers":[
        {
            "category":"Wholesale",
            "subcategory":"Medical Equipment & Supplies",
            "type":"Manufacturing & Wholesale Goods"
        }
    ],
    "sg:phone":"+61 2 9874 6912",
    "sg:postcode":"2114",
    "sg:province":"NSW",
    "sg:tags":[
        "aid",
        "care",
        "health",
        "home"
    ],
    "wof:name":"Wallace Pharmacy",
    "wof:placetype":"venue"
},
  "geometry": {"coordinates":[151.07090759299999,-33.8069381714],"type":"Point"}
}