{
  "type": "Feature",
  "properties": {
    "iso:country":"AU",
    "sg:address":"106 Lamb St",
    "sg:city":"Murgon",
    "sg:classifiers":[
        {
            "category":"Real Estate",
            "subcategory":"Real Estate Services",
            "type":"Services"
        }
    ],
    "sg:phone":"+61 7 4168 2922",
    "sg:postcode":"4605",
    "sg:province":"QLD",
    "sg:tags":[
        "auctioneer"
    ],
    "wof:name":"Murgon Real Estate",
    "wof:placetype":"venue"
},
  "geometry": {"coordinates":[151.94032300000001,-26.241245],"type":"Point"}
}