{
  "type": "Feature",
  "properties": {
    "addr:full":"Caloundra Rd & Bronwyn St Caloundra QLD 4551",
    "addr:postcode":"4551",
    "addr:street":"Caloundra Rd & Bronwyn St",
    "iso:country":"AU",
    "sg:address":"Caloundra Rd & Bronwyn St",
    "sg:city":"Caloundra",
    "sg:classifiers":[
        {
            "category":"Autos & Motor Vehicles",
            "subcategory":"Fuel & Gas Station",
            "type":"Retail Goods"
        }
    ],
    "sg:phone":"+61 7 5491 7666",
    "sg:postcode":"4551",
    "sg:province":"QLD",
    "wof:name":"Mobil Oil Australia Ltd",
    "wof:placetype":"venue"
},
  "geometry": {"coordinates":[153.11076355,-26.7962303162],"type":"Point"}
}