{
  "type": "Feature",
  "properties": {
    "iso:country":"AU",
    "sg:address":"2 Beatrice Crt",
    "sg:city":"Springwood",
    "sg:classifiers":[
        {
            "category":"Wholesale",
            "subcategory":"Seafood",
            "type":"Manufacturing & Wholesale Goods"
        }
    ],
    "sg:phone":"+61 7 3208 8555",
    "sg:postcode":"4127",
    "sg:province":"QLD",
    "sg:tags":[
        "fish"
    ],
    "wof:name":"Australian Seafood Producers Pty Ltd",
    "wof:placetype":"venue"
},
  "geometry": {"coordinates":[153.13563537600001,-27.6215724945],"type":"Point"}
}