{
  "type": "Feature",
  "properties": {
    "iso:country":"AU",
    "sg:address":"727 Point Nepean Rd",
    "sg:city":"Rosebud",
    "sg:classifiers":[
        {
            "category":"Retail",
            "subcategory":"Auto Repair",
            "type":"Services"
        }
    ],
    "sg:phone":"+61 3 5986 1682",
    "sg:postcode":"3939",
    "sg:province":"VIC",
    "sg:tags":[
        "repairer",
        "motor",
        "engineer"
    ],
    "wof:name":"Fluidrive Automatic Transmissions P/L",
    "wof:placetype":"venue"
},
  "geometry": {"coordinates":[144.923065186,-38.3507614136],"type":"Point"}
}