{
  "type": "Feature",
  "properties": {
    "addr:full":"Suite 3, 474 Victoria St Richmond VIC 3121",
    "addr:housenumber":"474",
    "addr:postcode":"3121",
    "addr:street":"Victoria St",
    "iso:country":"AU",
    "sg:address":"Suite 3, 474 Victoria St",
    "sg:city":"Richmond",
    "sg:classifiers":[
        {
            "category":"Health Services",
            "subcategory":"Health Practitioner",
            "type":"Services"
        }
    ],
    "sg:phone":"+61 3 9826 2006",
    "sg:postcode":"3121",
    "sg:province":"VIC",
    "sg:tags":[
        "myotherapy"
    ],
    "wof:name":"Elite Myotherapy",
    "wof:placetype":"venue"
},
  "geometry": {"coordinates":[145.00749206500001,-37.8113555908],"type":"Point"}
}