{
  "type": "Feature",
  "properties": {
    "addr:full":"Whylandra St Dubbo NSW 2830",
    "addr:postcode":"2830",
    "addr:street":"St",
    "iso:country":"AU",
    "sg:address":"Whylandra St",
    "sg:city":"Dubbo",
    "sg:classifiers":[
        {
            "category":"Restaurant",
            "type":"Food & Drink"
        }
    ],
    "sg:phone":"+61 2 6884 3000",
    "sg:postcode":"2830",
    "sg:province":"NSW",
    "wof:name":"West Dubbo Bowling Club Ltd",
    "wof:placetype":"venue"
},
  "geometry": {"coordinates":[148.59898376500001,-32.2430419922],"type":"Point"}
}