{
  "type": "Feature",
  "properties": {
    "iso:country":"AU",
    "sg:address":"1278 South Rd",
    "sg:city":"Clovelly Park",
    "sg:classifiers":[
        {
            "category":"Autos & Motor Vehicles",
            "subcategory":"Automobile Sales",
            "type":"Retail Goods"
        }
    ],
    "sg:phone":"+61 1300 137 766",
    "sg:postcode":"5042",
    "sg:province":"SA",
    "sg:tags":[
        "car",
        "new"
    ],
    "wof:name":"Toyota",
    "wof:placetype":"venue"
},
  "geometry": {"coordinates":[138.575577,-35.005402],"type":"Point"}
}