{
  "type": "Feature",
  "properties": {
    "iso:country":"AU",
    "sg:address":"2B Madison St",
    "sg:city":"Canning Vale",
    "sg:classifiers":[
        {
            "category":"Transit Center",
            "subcategory":"Passenger",
            "type":"Transportation"
        }
    ],
    "sg:phone":"+61 8 9455 6444",
    "sg:postcode":"6155",
    "sg:province":"WA",
    "sg:tags":[
        "packing",
        "gasket"
    ],
    "wof:name":"ACL Specialised Gaskets",
    "wof:placetype":"venue"
},
  "geometry": {"coordinates":[115.927757,-32.058647],"type":"Point"}
}