{
  "type": "Feature",
  "properties": {
    "addr:full":"316 Barrenjoey Rd Newport Beach NSW 2106",
    "addr:housenumber":"316",
    "addr:postcode":"2106",
    "addr:street":"Barrenjoey Rd",
    "iso:country":"AU",
    "sg:address":"316 Barrenjoey Rd",
    "sg:city":"Newport Beach",
    "sg:classifiers":[
        {
            "category":"Retail",
            "subcategory":"Auto Rental",
            "type":"Services"
        }
    ],
    "sg:phone":"+61 2 9999 1295",
    "sg:postcode":"2106",
    "sg:province":"NSW",
    "sg:tags":[
        "bus",
        "truck"
    ],
    "wof:name":"Ampol Seabreeze",
    "wof:placetype":"venue"
},
  "geometry": {"coordinates":[151.318435669,-33.6568565369],"type":"Point"}
}