{
  "type": "Feature",
  "properties": {
    "iso:country":"AU",
    "sg:address":"77 Myall St",
    "sg:city":"Dubbo",
    "sg:classifiers":[
        {
            "category":"Fast Food",
            "type":"Food & Drink"
        }
    ],
    "sg:phone":"+61 2 6882 9145",
    "sg:postcode":"2830",
    "sg:province":"NSW",
    "sg:tags":[
        "away",
        "take"
    ],
    "wof:name":"Manera Mini Mart & Take Away",
    "wof:placetype":"venue"
},
  "geometry": {"coordinates":[148.612457275,-32.2398109436],"type":"Point"}
}