{
  "type": "Feature",
  "properties": {
    "addr:full":"111 High St Thomastown VIC 3074",
    "addr:housenumber":"111",
    "addr:postcode":"3074",
    "addr:street":"High St",
    "iso:country":"AU",
    "sg:address":"111 High St",
    "sg:city":"Thomastown",
    "sg:classifiers":[
        {
            "category":"Health Services",
            "subcategory":"Doctor",
            "type":"Services"
        }
    ],
    "sg:phone":"+61 3 9347 0431",
    "sg:postcode":"3074",
    "sg:province":"VIC",
    "sg:tags":[
        "medical",
        "practitioner"
    ],
    "wof:name":"Hunter John",
    "wof:placetype":"venue"
},
  "geometry": {"coordinates":[145.0131073,-37.68334198],"type":"Point"}
}