{
  "type": "Feature",
  "properties": {
    "iso:country":"AU",
    "sg:address":"109 Maybe St",
    "sg:city":"Bombala",
    "sg:classifiers":[
        {
            "category":"Shopping",
            "subcategory":"Clothing, Apparel, & Fashions",
            "type":"Retail Goods"
        }
    ],
    "sg:phone":"+61 2 6458 4008",
    "sg:postcode":"2632",
    "sg:province":"NSW",
    "sg:tags":[
        "accessory"
    ],
    "wof:name":"Final Touches",
    "wof:placetype":"venue"
},
  "geometry": {"coordinates":[149.23869323700001,-36.9117584229],"type":"Point"}
}