{
  "type": "Feature",
  "properties": {
    "addr:full":"U2/ 2 Yallourn St Fyshwick ACT 2609",
    "addr:postcode":"2609",
    "addr:street":"U2 / 2 Yallourn St",
    "iso:country":"AU",
    "sg:address":"U2/ 2 Yallourn St",
    "sg:city":"Fyshwick",
    "sg:classifiers":[
        {
            "category":"Building & Trades",
            "subcategory":"Construction",
            "type":"Services"
        }
    ],
    "sg:phone":"+61 2 6239 1113",
    "sg:postcode":"2609",
    "sg:province":"ACT",
    "sg:tags":[
        "management"
    ],
    "wof:name":"Capezio & Co Pty Ltd",
    "wof:placetype":"venue"
},
  "geometry": {"coordinates":[149.17506408700001,-35.3271255493],"type":"Point"}
}