{
  "type": "Feature",
  "properties": {
    "iso:country":"AU",
    "sg:address":"104 Carrs Drv",
    "sg:city":"Yamba",
    "sg:classifiers":[
        {
            "category":"Building & Trades",
            "subcategory":"Pest Control",
            "type":"Services"
        }
    ],
    "sg:phone":"+61 2 6646 1025",
    "sg:postcode":"2464",
    "sg:province":"NSW",
    "wof:name":"The White Ant Company",
    "wof:placetype":"venue"
},
  "geometry": {"coordinates":[153.33074951200001,-29.4460468292],"type":"Point"}
}