{
  "type": "Feature",
  "properties": {
    "iso:country":"AU",
    "sg:address":"Shp 211/ 72-80 Marine Pde",
    "sg:city":"Coolangatta",
    "sg:classifiers":[
        {
            "category":"Sports & Exercise",
            "subcategory":"Gym",
            "type":"Entertainment"
        }
    ],
    "sg:phone":"+61 7 5536 6340",
    "sg:postcode":"4225",
    "sg:province":"QLD",
    "sg:tags":[
        "health",
        "fitness"
    ],
    "wof:name":"Contours Coolangatta",
    "wof:placetype":"venue"
},
  "geometry": {"coordinates":[153.53819274899999,-28.1674137115],"type":"Point"}
}