{
  "type": "Feature",
  "properties": {
    "addr:full":"31 Exhibition Rd South Side QLD 4570",
    "addr:housenumber":"31",
    "addr:postcode":"4570",
    "addr:street":"Exhibition Rd",
    "iso:country":"AU",
    "sg:address":"31 Exhibition Rd",
    "sg:city":"South Side",
    "sg:classifiers":[
        {
            "category":"Fast Food",
            "type":"Food & Drink"
        }
    ],
    "sg:phone":"+61 7 5482 4660",
    "sg:postcode":"4570",
    "sg:province":"QLD",
    "sg:tags":[
        "away",
        "take"
    ],
    "wof:name":"Southside Take Aways",
    "wof:placetype":"venue"
},
  "geometry": {"coordinates":[152.64944457999999,-26.198217392],"type":"Point"}
}