{
  "type": "Feature",
  "properties": {
    "addr:full":"Cnr Fox & Edward Sts Wagga Wagga NSW 2650",
    "addr:postcode":"2650",
    "addr:street":"Cnr",
    "iso:country":"AU",
    "sg:address":"Cnr Fox & Edward Sts",
    "sg:city":"Wagga Wagga",
    "sg:classifiers":[
        {
            "category":"Fast Food",
            "type":"Food & Drink"
        }
    ],
    "sg:phone":"+61 2 6921 6100",
    "sg:postcode":"2650",
    "sg:province":"NSW",
    "sg:tags":[
        "away",
        "take"
    ],
    "wof:name":"McDonald's Family Restaurants",
    "wof:placetype":"venue"
},
  "geometry": {"coordinates":[147.542144775,-35.1158332825],"type":"Point"}
}