{
  "type": "Feature",
  "properties": {
    "addr:full":"PO Box 208 Bangalow NSW 2479",
    "addr:postcode":"2479",
    "iso:country":"AU",
    "sg:address":"PO Box 208",
    "sg:city":"Bangalow",
    "sg:classifiers":[
        {
            "category":"Utilities",
            "subcategory":"Water",
            "type":"Services"
        }
    ],
    "sg:phone":"+61 427 291 767",
    "sg:postcode":"2479",
    "sg:province":"NSW",
    "sg:tags":[
        "hot",
        "system"
    ],
    "wof:name":"Birks Electrical",
    "wof:placetype":"venue"
},
  "geometry": {"coordinates":[153.53315734899999,-28.6822795868],"type":"Point"}
}