{
  "type": "Feature",
  "properties": {
    "addr:full":"203 Salisbury St Bedford WA 6052",
    "addr:housenumber":"203",
    "addr:postcode":"6052",
    "addr:street":"Salisbury St",
    "iso:country":"AU",
    "sg:address":"203 Salisbury St",
    "sg:city":"Bedford",
    "sg:classifiers":[
        {
            "category":"Health Services",
            "subcategory":"Doctor",
            "type":"Services"
        }
    ],
    "sg:phone":"+61 8 9271 4000",
    "sg:postcode":"6052",
    "sg:province":"WA",
    "sg:tags":[
        "medical",
        "practitioner"
    ],
    "wof:name":"Bedford Family Practice",
    "wof:placetype":"venue"
},
  "geometry": {"coordinates":[115.881019592,-31.9082775116],"type":"Point"}
}