{
  "type": "Feature",
  "properties": {
    "addr:full":"35 Mockingbird Rd Pheasants Nest NSW 2574",
    "addr:housenumber":"35",
    "addr:postcode":"2574",
    "addr:street":"Mockingbird Rd",
    "iso:country":"AU",
    "sg:address":"35 Mockingbird Rd",
    "sg:city":"Pheasants Nest",
    "sg:classifiers":[
        {
            "category":"Utilities",
            "subcategory":"Electric",
            "type":"Services"
        }
    ],
    "sg:phone":"+61 2 4684 1239",
    "sg:postcode":"2574",
    "sg:province":"NSW",
    "sg:tags":[
        "electrical",
        "contractor"
    ],
    "wof:name":"Boab Electrics",
    "wof:placetype":"venue"
},
  "geometry": {"coordinates":[150.62542724599999,-34.2804527283],"type":"Point"}
}