{
  "type": "Feature",
  "properties": {
    "addr:full":"12- 14 Solent Cct Baulkham Hills NSW 2153",
    "addr:housenumber":"14",
    "addr:postcode":"2153",
    "addr:street":"Solent Cct",
    "iso:country":"AU",
    "sg:address":"12- 14",
    "sg:city":"Solent Cct Baulkham Hills",
    "sg:classifiers":[
        {
            "category":"Professional",
            "subcategory":"Printing & Photocopies",
            "type":"Services"
        }
    ],
    "sg:phone":"+61 2 8814 7627",
    "sg:postcode":"2153",
    "sg:province":"NSW",
    "sg:tags":[
        "photocopying"
    ],
    "wof:name":"Snap Printing Pty Ltd",
    "wof:placetype":"venue"
},
  "geometry": {"coordinates":[150.959182739,-33.7336006165],"type":"Point"}
}