{
  "type": "Feature",
  "properties": {
    "addr:full":"31 Long St Hendra QLD 4011",
    "addr:housenumber":"31",
    "addr:postcode":"4011",
    "addr:street":"Long St",
    "iso:country":"AU",
    "sg:address":"31 Long St",
    "sg:city":"Hendra",
    "sg:classifiers":[
        {
            "category":"Real Estate",
            "subcategory":"Surveying",
            "type":"Services"
        }
    ],
    "sg:phone":"+61 7 3268 2212",
    "sg:postcode":"4011",
    "sg:province":"QLD",
    "sg:tags":[
        "surveyor",
        "quantity"
    ],
    "wof:name":"Wildermuth Building Services Pty Ltd",
    "wof:placetype":"venue"
},
  "geometry": {"coordinates":[153.07489000000001,-27.422672],"type":"Point"}
}