{
  "type": "Feature",
  "properties": {
    "addr:full":"403 Bourke St Surry Hills NSW 2010",
    "addr:housenumber":"403",
    "addr:postcode":"2010",
    "addr:street":"Bourke St",
    "iso:country":"AU",
    "sg:address":"403 Bourke St",
    "sg:city":"Surry Hills",
    "sg:classifiers":[
        {
            "category":"Bars & Pubs",
            "subcategory":"Biergarten",
            "type":"Food & Drink"
        }
    ],
    "sg:phone":"+61 2 9360 4674",
    "sg:postcode":"2010",
    "sg:province":"NSW",
    "sg:tags":[
        "tailor",
        "lady"
    ],
    "wof:name":"Louies Tailoring",
    "wof:placetype":"venue"
},
  "geometry": {"coordinates":[151.216400147,-33.8816375732],"type":"Point"}
}