{
  "type": "Feature",
  "properties": {
    "addr:full":"17 Valentine Rd Perth Airport WA 6105",
    "addr:housenumber":"17",
    "addr:postcode":"6105",
    "addr:street":"Valentine Rd",
    "iso:country":"AU",
    "sg:address":"17 Valentine Rd",
    "sg:city":"Perth Airport",
    "sg:classifiers":[
        {
            "category":"Manufacturing",
            "subcategory":"Aerospace",
            "type":"Manufacturing & Wholesale Goods"
        }
    ],
    "sg:phone":"+61 8 9267 1600",
    "sg:postcode":"6105",
    "sg:province":"WA",
    "sg:tags":[
        "equipment",
        "aircraft",
        "maintenance"
    ],
    "wof:name":"Helicopters (Australia) Pty Ltd",
    "wof:placetype":"venue"
},
  "geometry": {"coordinates":[115.9610672,-31.9246063232],"type":"Point"}
}