{
  "type": "Feature",
  "properties": {
    "iso:country":"AU",
    "sg:address":"Lvl 3 Toowong Tower 9 Sherwood Rd",
    "sg:city":"Toowong",
    "sg:classifiers":[
        {
            "category":"Insurance",
            "subcategory":"Hazard Insurance",
            "type":"Services"
        }
    ],
    "sg:phone":"+61 7 3871 3941",
    "sg:postcode":"4066",
    "sg:province":"QLD",
    "sg:tags":[
        "fire",
        "accident",
        "marine"
    ],
    "wof:name":"Australian Aviation Underwriting Pool Pty Ltd",
    "wof:placetype":"venue"
},
  "geometry": {"coordinates":[152.99188232399999,-27.4853534698],"type":"Point"}
}