{
  "type": "Feature",
  "properties": {
    "addr:full":"Level 2/ 240 Margaret St Brisbane QLD 4000",
    "addr:housenumber":"/ 240",
    "addr:postcode":"4000",
    "addr:street":"Margaret St",
    "iso:country":"AU",
    "sg:address":"Level 2/ 240 Margaret St",
    "sg:city":"Brisbane",
    "sg:classifiers":[
        {
            "category":"Professional",
            "subcategory":"Computer Services",
            "type":"Services"
        }
    ],
    "sg:phone":"+61 7 3236 0499",
    "sg:postcode":"4000",
    "sg:province":"QLD",
    "sg:tags":[
        "on-line",
        "provider"
    ],
    "wof:name":"Austec Pacific Pty Ltd",
    "wof:placetype":"venue"
},
  "geometry": {"coordinates":[153.02569580100001,-27.4746265411],"type":"Point"}
}