{
  "type": "Feature",
  "properties": {
    "iso:country":"AU",
    "sg:address":"415 Hampton St",
    "sg:city":"Hampton",
    "sg:classifiers":[
        {
            "category":"Professional",
            "subcategory":"Art Services",
            "type":"Services"
        }
    ],
    "sg:phone":"+61 3 9521 8291",
    "sg:postcode":"3188",
    "sg:province":"VIC",
    "sg:tags":[
        "interior",
        "decorator"
    ],
    "wof:name":"Alexandra Keys Interior Decorators",
    "wof:placetype":"venue"
},
  "geometry": {"coordinates":[145.00270080600001,-37.9355392456],"type":"Point"}
}