{
  "type": "Feature",
  "properties": {
    "addr:full":"164 Hoddle St Abbotsford VIC 3067",
    "addr:housenumber":"164",
    "addr:postcode":"3067",
    "addr:street":"Hoddle St",
    "iso:country":"AU",
    "sg:address":"164 Hoddle St",
    "sg:city":"Abbotsford",
    "sg:classifiers":[
        {
            "category":"Shopping",
            "subcategory":"Stationery & Office Supplies",
            "type":"Retail Goods"
        }
    ],
    "sg:phone":"+61 3 9417 7799",
    "sg:postcode":"3067",
    "sg:province":"VIC",
    "sg:tags":[
        "equipment",
        "display",
        "exhibition"
    ],
    "wof:name":"Clarkson Chas",
    "wof:placetype":"venue"
},
  "geometry": {"coordinates":[144.992843628,-37.8022880554],"type":"Point"}
}