{
  "type": "Feature",
  "properties": {
    "addr:full":"30 Marconi St Morley WA 6062",
    "addr:housenumber":"30",
    "addr:postcode":"6062",
    "addr:street":"Marconi St",
    "iso:country":"AU",
    "sg:address":"30 Marconi St",
    "sg:city":"Morley",
    "sg:classifiers":[
        {
            "category":"Building & Trades",
            "subcategory":"Plumbing",
            "type":"Services"
        }
    ],
    "sg:phone":"+61 8 9279 2471",
    "sg:postcode":"6062",
    "sg:province":"WA",
    "sg:tags":[
        "plumber",
        "gasfitters"
    ],
    "wof:name":"Sutton B E & P M",
    "wof:placetype":"venue"
},
  "geometry": {"coordinates":[115.927146912,-31.8857402802],"type":"Point"}
}