{
  "type": "Feature",
  "properties": {
    "addr:full":"142 Breakfast Creek Rd Breakfast Creek QLD 4010",
    "addr:housenumber":"142",
    "addr:postcode":"4010",
    "addr:street":"Breakfast Creek Rd",
    "iso:country":"AU",
    "sg:address":"142 Breakfast Creek Rd",
    "sg:city":"Breakfast Creek",
    "sg:classifiers":[
        {
            "category":"Autos & Motor Vehicles",
            "subcategory":"Automobile Sales",
            "type":"Retail Goods"
        }
    ],
    "sg:phone":"+61 7 3109 6600",
    "sg:postcode":"4010",
    "sg:province":"QLD",
    "sg:tags":[
        "car",
        "new"
    ],
    "wof:name":"Mitsubishi City",
    "wof:placetype":"venue"
},
  "geometry": {"coordinates":[153.04530334500001,-27.4416561127],"type":"Point"}
}