{
  "type": "Feature",
  "properties": {
    "iso:country":"AU",
    "sg:address":"Shop 5/352 South St",
    "sg:city":"Hilton",
    "sg:classifiers":[
        {
            "category":"Shopping",
            "subcategory":"Clothing, Apparel, & Fashions",
            "type":"Retail Goods"
        }
    ],
    "sg:phone":"+61 8 9337 9179",
    "sg:postcode":"6163",
    "sg:province":"WA",
    "sg:tags":[
        "recycled",
        "clothing"
    ],
    "wof:name":"Vinnies Retail Centres",
    "wof:placetype":"venue"
},
  "geometry": {"coordinates":[115.785683,-32.063046],"type":"Point"}
}