{
  "type": "Feature",
  "properties": {
    "addr:full":"5 Rowton Ave Northmead NSW 2152",
    "addr:housenumber":"5",
    "addr:postcode":"2152",
    "addr:street":"Rowton Ave",
    "iso:country":"AU",
    "sg:address":"5 Rowton Ave",
    "sg:city":"Northmead",
    "sg:classifiers":[
        {
            "category":"Wholesale",
            "subcategory":"Machinery & Supplies",
            "type":"Manufacturing & Wholesale Goods"
        }
    ],
    "sg:phone":"+61 2 9890 8883",
    "sg:postcode":"2152",
    "sg:province":"NSW",
    "wof:name":"Technicstar Communications",
    "wof:placetype":"venue"
},
  "geometry": {"coordinates":[150.991622925,-33.7905311584],"type":"Point"}
}