{
  "type": "Feature",
  "properties": {
    "addr:full":"Greenfield Shopping Village Greenfield Rd Greenfield Park NSW 2176",
    "addr:postcode":"2176",
    "addr:street":"Greenfield Rd",
    "iso:country":"AU",
    "sg:address":"Greenfield Shopping Village Greenfield Rd",
    "sg:city":"Greenfield Park",
    "sg:classifiers":[
        {
            "category":"Food & Beverages",
            "subcategory":"Groceries & Convenience Stores",
            "type":"Retail Goods"
        }
    ],
    "sg:phone":"+61 2 9610 2009",
    "sg:postcode":"2176",
    "sg:province":"NSW",
    "wof:name":"Persepolis Continental Food",
    "wof:placetype":"venue"
},
  "geometry": {"coordinates":[150.89126586899999,-33.872253418],"type":"Point"}
}