{
  "type": "Feature",
  "properties": {
    "addr:full":"86 Main St Alstonville NSW 2477",
    "addr:housenumber":"86",
    "addr:postcode":"2477",
    "addr:street":"Main St",
    "iso:country":"AU",
    "sg:address":"86 Main St",
    "sg:city":"Alstonville",
    "sg:classifiers":[
        {
            "category":"Cafe",
            "type":"Food & Drink"
        }
    ],
    "sg:phone":"+61 2 6628 3333",
    "sg:postcode":"2477",
    "sg:province":"NSW",
    "wof:name":"Alstonville Cafe Giardino",
    "wof:placetype":"venue"
},
  "geometry": {"coordinates":[153.43586730999999,-28.8379573822],"type":"Point"}
}