{
  "type": "Feature",
  "properties": {
    "addr:full":"476 Coolangatta Rd Tugun QLD 4224",
    "addr:housenumber":"476",
    "addr:postcode":"4224",
    "addr:street":"Coolangatta Rd",
    "iso:country":"AU",
    "sg:address":"476 Coolangatta Rd",
    "sg:city":"Tugun",
    "sg:classifiers":[
        {
            "category":"Building & Trades",
            "subcategory":"Plumbing",
            "type":"Services"
        }
    ],
    "sg:phone":"+61 7 5534 4346",
    "sg:postcode":"4224",
    "sg:province":"QLD",
    "sg:tags":[
        "plumber",
        "gasfitters"
    ],
    "wof:name":"Power George Licenced Plumber",
    "wof:placetype":"venue"
},
  "geometry": {"coordinates":[153.496337891,-28.1462554932],"type":"Point"}
}