{
  "type": "Feature",
  "properties": {
    "addr:full":"121 Wollongong St Fyshwick ACT 2609",
    "addr:housenumber":"121",
    "addr:postcode":"2609",
    "addr:street":"Wollongong St",
    "iso:country":"AU",
    "sg:address":"121 Wollongong St",
    "sg:city":"Fyshwick",
    "sg:classifiers":[
        {
            "category":"Professional",
            "subcategory":"Detective & Security Services",
            "type":"Services"
        }
    ],
    "sg:phone":"+61 2 6239 1801",
    "sg:postcode":"2609",
    "sg:province":"ACT",
    "sg:tags":[
        "domestic",
        "alarm",
        "commercial",
        "burglar"
    ],
    "wof:name":"Jaycar Electronics Pty Ltd",
    "wof:placetype":"venue"
},
  "geometry": {"coordinates":[149.176147461,-35.3223152161],"type":"Point"}
}