{
  "type": "Feature",
  "properties": {
    "addr:full":"35 Benabrow Ave Bribie Island QLD 4507",
    "addr:housenumber":"35",
    "addr:postcode":"4507",
    "addr:street":"Benabrow Ave Bribie",
    "iso:country":"AU",
    "sg:address":"35 Benabrow Ave",
    "sg:city":"Bribie Island",
    "sg:classifiers":[
        {
            "category":"Real Estate",
            "subcategory":"Real Estate Agent",
            "type":"Services"
        }
    ],
    "sg:phone":"+61 7 3408 8188",
    "sg:postcode":"4507",
    "sg:province":"QLD",
    "wof:name":"HARCOURTS QUEENSLAND PTY LTD",
    "wof:placetype":"venue"
},
  "geometry": {"coordinates":[153.151123047,-27.0656261444],"type":"Point"}
}