{
  "type": "Feature",
  "properties": {
    "addr:full":"4 Russell St Evandale TAS 7212",
    "addr:housenumber":"4",
    "addr:postcode":"7212",
    "addr:street":"Russell St",
    "iso:country":"AU",
    "sg:address":"4 Russell St",
    "sg:city":"Evandale",
    "sg:classifiers":[
        {
            "category":"Food & Beverages",
            "subcategory":"Bakery",
            "type":"Retail Goods"
        }
    ],
    "sg:phone":"+61 3 6391 8682",
    "sg:postcode":"7212",
    "sg:province":"TAS",
    "sg:tags":[
        "baker"
    ],
    "wof:name":"Ingleside Bakery Pty Ltd",
    "wof:placetype":"venue"
},
  "geometry": {"coordinates":[147.24813800000001,-41.571159],"type":"Point"}
}