{
  "type": "Feature",
  "properties": {
    "addr:full":"213 Nicholson St Footscray VIC 3011",
    "addr:housenumber":"213",
    "addr:postcode":"3011",
    "addr:street":"Nicholson St",
    "iso:country":"AU",
    "sg:address":"213 Nicholson St",
    "sg:city":"Footscray",
    "sg:classifiers":[
        {
            "category":"Professional",
            "subcategory":"Business Services",
            "type":"Services"
        }
    ],
    "sg:phone":"+61 417 577 410",
    "sg:postcode":"3011",
    "sg:province":"VIC",
    "sg:tags":[
        "broker"
    ],
    "wof:name":"Robbie &#034;C&#034;s Presentation",
    "wof:placetype":"venue"
},
  "geometry": {"coordinates":[144.89906310999999,-37.8034934998],"type":"Point"}
}