{
  "type": "Feature",
  "properties": {
    "iso:country":"AU",
    "sg:address":"110 Badger Creek Rd",
    "sg:city":"Healesville",
    "sg:classifiers":[
        {
            "category":"Manufacturing",
            "subcategory":"Food",
            "type":"Manufacturing & Wholesale Goods"
        }
    ],
    "sg:phone":"+61 419 388 895",
    "sg:postcode":"3777",
    "sg:province":"VIC",
    "sg:tags":[
        "function",
        "catering"
    ],
    "wof:name":"Yarra Valley Picnics",
    "wof:placetype":"venue"
},
  "geometry": {"coordinates":[145.528305,-37.667374],"type":"Point"}
}