{
  "type": "Feature",
  "properties": {
    "addr:full":"3- 5 George St North Strathfield NSW 2137",
    "addr:housenumber":"5",
    "addr:postcode":"2137",
    "addr:street":"George St",
    "iso:country":"AU",
    "sg:address":"3- 5 George St",
    "sg:city":"North Strathfield",
    "sg:classifiers":[
        {
            "category":"Retail",
            "subcategory":"Event Space",
            "type":"Services"
        }
    ],
    "sg:phone":"+61 2 9746 0700",
    "sg:postcode":"2137",
    "sg:province":"NSW",
    "sg:tags":[
        "function",
        "organiser"
    ],
    "wof:name":"AMF Bowling Centre",
    "wof:placetype":"venue"
},
  "geometry": {"coordinates":[151.08799743599999,-33.8629875183],"type":"Point"}
}