{
  "type": "Feature",
  "properties": {
    "iso:country":"AU",
    "sg:address":"Co-op Complex Moorong St",
    "sg:city":"Wagga Wagga",
    "sg:classifiers":[
        {
            "category":"Cafe",
            "type":"Food & Drink"
        }
    ],
    "sg:phone":"+61 2 6925 9113",
    "sg:postcode":"2650",
    "sg:province":"NSW",
    "wof:name":"Cafe Moorish",
    "wof:placetype":"venue"
},
  "geometry": {"coordinates":[147.34796142600001,-35.107509613],"type":"Point"}
}