{
  "type": "Feature",
  "properties": {
    "iso:country":"AU",
    "sg:address":"8 Wood St",
    "sg:city":"Nunawading",
    "sg:classifiers":[
        {
            "category":"Health Services",
            "subcategory":"Dentist",
            "type":"Services"
        }
    ],
    "sg:phone":"+61 3 9878 7023",
    "sg:postcode":"3131",
    "sg:province":"VIC",
    "wof:name":"Gan Robert Dr",
    "wof:placetype":"venue"
},
  "geometry": {"coordinates":[145.176971436,-37.8211326599],"type":"Point"}
}