{
  "type": "Feature",
  "properties": {
    "iso:country":"AU",
    "sg:address":"Pingaring Rd",
    "sg:city":"Kulin East",
    "sg:classifiers":[
        {
            "category":"Farming",
            "subcategory":"Farm",
            "type":"Manufacturing & Wholesale Goods"
        }
    ],
    "sg:phone":"+61 8 9880 4060",
    "sg:postcode":"6365",
    "sg:province":"WA",
    "sg:tags":[
        "farmer"
    ],
    "wof:name":"Riseborough P C & K A",
    "wof:placetype":"venue"
},
  "geometry": {"coordinates":[118.14868199999999,-32.675648],"type":"Point"}
}