{
  "type": "Feature",
  "properties": {
    "addr:full":"Unit 1, 30 Smart St Fairfield NSW 2165",
    "addr:housenumber":"30",
    "addr:postcode":"2165",
    "addr:street":"Smart St",
    "iso:country":"AU",
    "sg:address":"Unit 1, 30 Smart St",
    "sg:city":"Fairfield",
    "sg:classifiers":[
        {
            "category":"Travel",
            "subcategory":"Travel Agent",
            "type":"Entertainment"
        }
    ],
    "sg:phone":"+61 2 9724 6334",
    "sg:postcode":"2165",
    "sg:province":"NSW",
    "sg:tags":[
        "consultant"
    ],
    "wof:name":"Liaison Travel Pty Ltd",
    "wof:placetype":"venue"
},
  "geometry": {"coordinates":[150.956573486,-33.870677948],"type":"Point"}
}