{
  "type": "Feature",
  "properties": {
    "iso:country":"AU",
    "sg:address":"PO Box 1040",
    "sg:city":"Fyshwick",
    "sg:classifiers":[
        {
            "category":"Building & Trades",
            "subcategory":"Construction",
            "type":"Services"
        }
    ],
    "sg:phone":"+61 2 6241 0446",
    "sg:postcode":"2609",
    "sg:province":"ACT",
    "sg:tags":[
        "earth",
        "excavating",
        "moving",
        "contractor"
    ],
    "wof:name":"Bruces Bobcats & Landscaping",
    "wof:placetype":"venue"
},
  "geometry": {"coordinates":[149.17616272000001,-35.3273696899],"type":"Point"}
}