{
  "type": "Feature",
  "properties": {
    "addr:full":"13 Charlton Rd Quambatook VIC 3540",
    "addr:housenumber":"13",
    "addr:postcode":"3540",
    "addr:street":"Charlton Rd",
    "iso:country":"AU",
    "sg:address":"13 Charlton Rd",
    "sg:city":"Quambatook",
    "sg:classifiers":[
        {
            "category":"Education",
            "subcategory":"School",
            "type":"Public Place"
        }
    ],
    "sg:phone":"+61 3 5457 1208",
    "sg:postcode":"3540",
    "sg:province":"VIC",
    "sg:tags":[
        "state",
        "except",
        "nsw"
    ],
    "wof:name":"Quambatook Primary School",
    "wof:placetype":"venue"
},
  "geometry": {"coordinates":[143.519775391,-35.8559570312],"type":"Point"}
}