{
  "type": "Feature",
  "properties": {
    "addr:full":"Lot 21 Bishopwood Crt Upper Coomera QLD 4209",
    "addr:postcode":"4209",
    "addr:street":"Crt",
    "iso:country":"AU",
    "sg:address":"Lot 21 Bishopwood Crt",
    "sg:city":"Upper Coomera",
    "sg:classifiers":[
        {
            "category":"Building & Trades",
            "subcategory":"Construction",
            "type":"Services"
        }
    ],
    "sg:phone":"+61 7 5630 3166",
    "sg:postcode":"4209",
    "sg:province":"QLD",
    "sg:tags":[
        "contractor"
    ],
    "wof:name":"Hallmark Homes Pty Ltd",
    "wof:placetype":"venue"
},
  "geometry": {"coordinates":[153.30148315400001,-27.8433551788],"type":"Point"}
}