{
  "type": "Feature",
  "properties": {
    "addr:full":"77 Hoffmans Rd Niddrie VIC 3042",
    "addr:housenumber":"77",
    "addr:postcode":"3042",
    "addr:street":"Hoffmans Rd",
    "iso:country":"AU",
    "sg:address":"77 Hoffmans Rd",
    "sg:city":"Niddrie",
    "sg:classifiers":[
        {
            "category":"Fast Food",
            "type":"Food & Drink"
        }
    ],
    "sg:phone":"+61 3 9331 2188",
    "sg:postcode":"3042",
    "sg:province":"VIC",
    "sg:tags":[
        "away",
        "take"
    ],
    "wof:name":"Pizza Haven",
    "wof:placetype":"venue"
},
  "geometry": {"coordinates":[144.89109802199999,-37.7441673279],"type":"Point"}
}