{
  "type": "Feature",
  "properties": {
    "addr:full":"12 Bangalay Pl Berwick VIC 3806",
    "addr:housenumber":"12",
    "addr:postcode":"3806",
    "addr:street":"Bangalay Pl",
    "iso:country":"AU",
    "sg:address":"12 Bangalay Pl",
    "sg:city":"Berwick",
    "sg:classifiers":[
        {
            "category":"Retail",
            "subcategory":"Auto Rental",
            "type":"Services"
        }
    ],
    "sg:phone":"+61 425 771 098",
    "sg:postcode":"3806",
    "sg:province":"VIC",
    "sg:tags":[
        "camper-trailers",
        "caravan",
        "hire"
    ],
    "wof:name":"Campalot Trailer Hire",
    "wof:placetype":"venue"
},
  "geometry": {"coordinates":[145.325073242,-38.0207824707],"type":"Point"}
}