{
  "type": "Feature",
  "properties": {
    "iso:country":"AU",
    "sg:address":"91 Glenferrie Rd",
    "sg:city":"Malvern",
    "sg:classifiers":[
        {
            "category":"Personal",
            "subcategory":"Beauty Salon",
            "type":"Services"
        }
    ],
    "sg:phone":"+61 3 9509 1487",
    "sg:postcode":"3144",
    "sg:province":"VIC",
    "sg:tags":[
        "hairdresser"
    ],
    "wof:name":"Sochi Hair",
    "wof:placetype":"venue"
},
  "geometry": {"coordinates":[145.02812194800001,-37.862701416],"type":"Point"}
}