{
  "type": "Feature",
  "properties": {
    "iso:country":"AU",
    "sg:address":"53 Fernleigh Rd",
    "sg:city":"Wagga Wagga",
    "sg:classifiers":[
        {
            "category":"Personal",
            "subcategory":"Beauty Salon",
            "type":"Services"
        }
    ],
    "sg:phone":"+61 2 6925 1991",
    "sg:postcode":"2650",
    "sg:province":"NSW",
    "sg:tags":[
        "hairdresser"
    ],
    "wof:name":"John Roy Hairdressers",
    "wof:placetype":"venue"
},
  "geometry": {"coordinates":[147.357666016,-35.1327362061],"type":"Point"}
}