{
  "type": "Feature",
  "properties": {
    "addr:full":"14 Charmaine Crt Highfields QLD 4352",
    "addr:housenumber":"14",
    "addr:postcode":"4352",
    "addr:street":"Charmaine Crt",
    "iso:country":"AU",
    "sg:address":"14 Charmaine Crt",
    "sg:city":"Highfields",
    "sg:classifiers":[
        {
            "category":"Home & Garden",
            "subcategory":"Building Materials",
            "type":"Retail Goods"
        }
    ],
    "sg:phone":"+61 400 968 160",
    "sg:postcode":"4352",
    "sg:province":"QLD",
    "sg:tags":[
        "concrete",
        "gutter",
        "kerb"
    ],
    "wof:name":"Kwik Kerb Highfields",
    "wof:placetype":"venue"
},
  "geometry": {"coordinates":[151.95129399999999,-27.435333],"type":"Point"}
}