{
  "type": "Feature",
  "properties": {
    "iso:country":"AU",
    "sg:address":"4/41 Railway Rd",
    "sg:city":"Blackburn",
    "sg:classifiers":[
        {
            "category":"Real Estate",
            "subcategory":"Real Estate Agent",
            "type":"Services"
        }
    ],
    "sg:phone":"+61 3 9878 4000",
    "sg:postcode":"3130",
    "sg:province":"VIC",
    "wof:name":"Lawrence Butler Commercial",
    "wof:placetype":"venue"
},
  "geometry": {"coordinates":[145.15098571799999,-37.8196907043],"type":"Point"}
}