{
  "type": "Feature",
  "properties": {
    "iso:country":"AU",
    "sg:address":"Nathan St",
    "sg:city":"Aitkenvale",
    "sg:classifiers":[
        {
            "category":"Travel",
            "subcategory":"Hotels & Motels",
            "type":"Entertainment"
        }
    ],
    "sg:phone":"+61 7 4772 9777",
    "sg:postcode":"4814",
    "sg:province":"QLD",
    "sg:tags":[
        "pub"
    ],
    "wof:name":"Toms Tavern",
    "wof:placetype":"venue"
},
  "geometry": {"coordinates":[146.761948,-19.295038],"type":"Point"}
}