{
  "type": "Feature",
  "properties": {
    "addr:full":"1217 South Rd St Marys SA 5042",
    "addr:housenumber":"1217",
    "addr:postcode":"5042",
    "addr:street":"South Rd",
    "iso:country":"AU",
    "sg:address":"1217 South Rd",
    "sg:city":"St Marys",
    "sg:classifiers":[
        {
            "category":"Building & Trades",
            "subcategory":"Construction",
            "type":"Services"
        }
    ],
    "sg:phone":"+61 8 8299 0159",
    "sg:postcode":"5042",
    "sg:province":"SA",
    "sg:tags":[
        "fencing",
        "contractor"
    ],
    "wof:name":"Trellis Factory",
    "wof:placetype":"venue"
},
  "geometry": {"coordinates":[138.57557700000001,-34.999458],"type":"Point"}
}