{
  "type": "Feature",
  "properties": {
    "iso:country":"AU",
    "sg:address":"Hangar 464",
    "sg:city":", Birch St, Bankstown Airport Bankstown",
    "sg:classifiers":[
        {
            "category":"Airline",
            "type":"Transportation"
        }
    ],
    "sg:phone":"+61 2 9791 1900",
    "sg:postcode":"2200",
    "sg:province":"NSW",
    "sg:tags":[
        "aircraft",
        "rental",
        "charter"
    ],
    "wof:name":"Helicopters Pty Limited",
    "wof:placetype":"venue"
},
  "geometry": {"coordinates":[150.997696,-33.918667],"type":"Point"}
}