{
  "type": "Feature",
  "properties": {
    "addr:full":"3 Brassey Ave Rosanna VIC 3084",
    "addr:housenumber":"3",
    "addr:postcode":"3084",
    "addr:street":"Brassey Ave",
    "iso:country":"AU",
    "sg:address":"3 Brassey Ave",
    "sg:city":"Rosanna",
    "sg:classifiers":[
        {
            "category":"Building & Trades",
            "subcategory":"Pest Control",
            "type":"Services"
        }
    ],
    "sg:phone":"+61 3 9459 3499",
    "sg:postcode":"3084",
    "sg:province":"VIC",
    "wof:name":"Golden Orb Pty Ltd",
    "wof:placetype":"venue"
},
  "geometry": {"coordinates":[145.07432556099999,-37.7369499207],"type":"Point"}
}