{
  "type": "Feature",
  "properties": {
    "addr:full":"45 Albert Rd Moonah TAS 7009",
    "addr:housenumber":"45",
    "addr:postcode":"7009",
    "addr:street":"Albert Rd",
    "iso:country":"AU",
    "sg:address":"45 Albert Rd",
    "sg:city":"Moonah",
    "sg:classifiers":[
        {
            "category":"Home & Garden",
            "subcategory":"Carpets & Floor Coverings",
            "type":"Retail Goods"
        }
    ],
    "sg:phone":"+61 3 6278 2200",
    "sg:postcode":"7009",
    "sg:province":"TAS",
    "sg:tags":[
        "tile",
        "wall",
        "layer"
    ],
    "wof:name":"Montile Pty Ltd",
    "wof:placetype":"venue"
},
  "geometry": {"coordinates":[147.29747009299999,-42.8477973938],"type":"Point"}
}