{
  "type": "Feature",
  "properties": {
    "addr:full":"Lvl 43, 55 Collins St Melbourne VIC 3004",
    "addr:housenumber":"55",
    "addr:postcode":"3004",
    "addr:street":"Collins St",
    "iso:country":"AU",
    "sg:address":"Lvl 43, 55 Collins St",
    "sg:city":"Melbourne",
    "sg:classifiers":[
        {
            "category":"Professional",
            "subcategory":"Management & Consulting",
            "type":"Services"
        }
    ],
    "sg:phone":"+61 3 9639 2300",
    "sg:postcode":"3004",
    "sg:province":"VIC",
    "sg:tags":[
        "consultant"
    ],
    "wof:name":"Royce (Vic) Pty Ltd",
    "wof:placetype":"venue"
},
  "geometry": {"coordinates":[144.971633911,-37.814125061],"type":"Point"}
}