{
  "type": "Feature",
  "properties": {
    "addr:full":"385 Burnley St Burnley VIC 3121",
    "addr:housenumber":"385",
    "addr:postcode":"3121",
    "addr:street":"Burnley St",
    "iso:country":"AU",
    "sg:address":"385 Burnley St",
    "sg:city":"Burnley",
    "sg:classifiers":[
        {
            "category":"Health Services",
            "subcategory":"Health Practitioner",
            "type":"Services"
        }
    ],
    "sg:phone":"+61 3 9428 4985",
    "sg:postcode":"3121",
    "sg:province":"VIC",
    "sg:tags":[
        "acupuncture"
    ],
    "wof:name":"Zhao Chen Colin",
    "wof:placetype":"venue"
},
  "geometry": {"coordinates":[145.007202148,-37.8264732361],"type":"Point"}
}