{
  "type": "Feature",
  "properties": {
    "addr:full":"Shp 1/ 81 Hibiscus St Greystanes NSW 2145",
    "addr:housenumber":"/ 81",
    "addr:postcode":"2145",
    "addr:street":"Hibiscus St",
    "iso:country":"AU",
    "sg:address":"Shp 1/ 81 Hibiscus St",
    "sg:city":"Greystanes",
    "sg:classifiers":[
        {
            "category":"Fast Food",
            "type":"Food & Drink"
        }
    ],
    "sg:phone":"+61 2 9604 9054",
    "sg:postcode":"2145",
    "sg:province":"NSW",
    "sg:tags":[
        "away",
        "take"
    ],
    "wof:name":"Greystanes Take Away & Mixed Business",
    "wof:placetype":"venue"
},
  "geometry": {"coordinates":[150.93717956500001,-33.8321990967],"type":"Point"}
}