{
  "type": "Feature",
  "properties": {
    "iso:country":"AU",
    "sg:address":"Oxley Plaza 455 Oxley Drv",
    "sg:city":"Runaway Bay",
    "sg:classifiers":[
        {
            "category":"Fast Food",
            "type":"Food & Drink"
        }
    ],
    "sg:phone":"+61 7 5529 0305",
    "sg:postcode":"4216",
    "sg:province":"QLD",
    "sg:tags":[
        "away",
        "take"
    ],
    "wof:name":"Vinnies Pizza Pasta Ribs",
    "wof:placetype":"venue"
},
  "geometry": {"coordinates":[153.38772582999999,-27.9208393097],"type":"Point"}
}