{
  "type": "Feature",
  "properties": {
    "iso:country":"AU",
    "sg:address":"Fussell St",
    "sg:city":"Ballarat East",
    "sg:classifiers":[
        {
            "category":"Travel",
            "subcategory":"Hostel",
            "type":"Entertainment"
        }
    ],
    "sg:phone":"+61 3 5337 1550",
    "sg:postcode":"3350",
    "sg:province":"VIC",
    "sg:tags":[
        "home"
    ],
    "wof:name":"Eureka Village Hostel",
    "wof:placetype":"venue"
},
  "geometry": {"coordinates":[143.891907,-37.56023],"type":"Point"}
}