{
  "type": "Feature",
  "properties": {
    "iso:country":"AU",
    "sg:address":"103 Main St",
    "sg:city":"Croydon",
    "sg:classifiers":[
        {
            "category":"Shopping",
            "subcategory":"Gifts & Souvenirs",
            "type":"Retail Goods"
        }
    ],
    "sg:phone":"+61 3 9725 3372",
    "sg:postcode":"3136",
    "sg:province":"VIC",
    "sg:tags":[
        "greeting",
        "card"
    ],
    "wof:name":"Luvenkisses Cards & Gift Shop",
    "wof:placetype":"venue"
},
  "geometry": {"coordinates":[145.28077697800001,-37.7967834473],"type":"Point"}
}