{
  "type": "Feature",
  "properties": {
    "iso:country":"AU",
    "sg:address":"Shp4/ Mcpherson St",
    "sg:city":"Hyden",
    "sg:classifiers":[
        {
            "category":"Food & Beverages",
            "subcategory":"Bakery",
            "type":"Retail Goods"
        }
    ],
    "sg:phone":"+61 8 9880 5678",
    "sg:postcode":"6359",
    "sg:province":"WA",
    "sg:tags":[
        "baker"
    ],
    "wof:name":"Bush Bakehouse",
    "wof:placetype":"venue"
},
  "geometry": {"coordinates":[118.862877,-32.449379],"type":"Point"}
}