{
  "type": "Feature",
  "properties": {
    "iso:country":"AU",
    "sg:address":"Level 18/ 300 Queen St",
    "sg:city":"Brisbane",
    "sg:classifiers":[
        {
            "category":"Professional",
            "subcategory":"Accounting & Tax Preparation",
            "type":"Services"
        }
    ],
    "sg:phone":"+61 7 3237 5999",
    "sg:postcode":"4001",
    "sg:province":"QLD",
    "sg:tags":[
        "accountant",
        "auditor"
    ],
    "wof:name":"Sheehan Peter",
    "wof:placetype":"venue"
},
  "geometry": {"coordinates":[153.02821350100001,-27.4671478271],"type":"Point"}
}