{
  "type": "Feature",
  "properties": {
    "addr:full":"241 Waterworth Drv Mt Annan NSW 2567",
    "addr:housenumber":"241",
    "addr:postcode":"2567",
    "addr:street":"Waterworth Drv",
    "iso:country":"AU",
    "sg:address":"241 Waterworth Drv",
    "sg:city":"Mt Annan",
    "sg:classifiers":[
        {
            "category":"Food & Beverages",
            "subcategory":"Groceries & Convenience Stores",
            "type":"Retail Goods"
        }
    ],
    "sg:phone":"+61 2 9837 2103",
    "sg:postcode":"2567",
    "sg:province":"NSW",
    "wof:name":"Shell Select",
    "wof:placetype":"venue"
},
  "geometry": {"coordinates":[150.76054382300001,-34.0494995117],"type":"Point"}
}