{
  "type": "Feature",
  "properties": {
    "addr:full":"20 Seymour Rd Elsternwick VIC 3185",
    "addr:housenumber":"20",
    "addr:postcode":"3185",
    "addr:street":"Seymour Rd",
    "iso:country":"AU",
    "sg:address":"20 Seymour Rd",
    "sg:city":"Elsternwick",
    "sg:classifiers":[
        {
            "category":"Government",
            "subcategory":"Court House",
            "type":"Public Place"
        }
    ],
    "sg:phone":"+61 3 9532 9838",
    "sg:postcode":"3185",
    "sg:province":"VIC",
    "sg:tags":[
        "personal",
        "marriage",
        "family",
        "counselling"
    ],
    "wof:name":"Ash Hilary",
    "wof:placetype":"venue"
},
  "geometry": {"coordinates":[145.00851440400001,-37.8805656433],"type":"Point"}
}