{
  "type": "Feature",
  "properties": {
    "addr:full":"Shop 2, 9 Young St Sydney NSW 2000",
    "addr:housenumber":"shop;9",
    "addr:postcode":"2000",
    "addr:street":"Young St",
    "iso:country":"AU",
    "sg:address":"Shop 2, 9 Young St",
    "sg:city":"Sydney",
    "sg:classifiers":[
        {
            "category":"Health Services",
            "subcategory":"Chiropractor",
            "type":"Services"
        }
    ],
    "sg:phone":"+61 2 9251 3411",
    "sg:postcode":"2000",
    "sg:province":"NSW",
    "wof:name":"Castorina Jan",
    "wof:placetype":"venue"
},
  "geometry": {"coordinates":[151.21098327600001,-33.8626899719],"type":"Point"}
}