{
  "type": "Feature",
  "properties": {
    "iso:country":"AU",
    "sg:address":"3 Roxborough Park Rd",
    "sg:city":"Baulkham Hills",
    "sg:classifiers":[
        {
            "category":"Building & Trades",
            "subcategory":"Construction",
            "type":"Services"
        }
    ],
    "sg:phone":"+61 2 9639 0724",
    "sg:postcode":"2153",
    "sg:province":"NSW",
    "sg:tags":[
        "earth",
        "excavating",
        "moving",
        "contractor"
    ],
    "wof:name":"Mini Excavator Rentals",
    "wof:placetype":"venue"
},
  "geometry": {"coordinates":[150.98651123100001,-33.7496337891],"type":"Point"}
}