{
  "type": "Feature",
  "properties": {
    "addr:full":"1791 Pittwater Rd Mona Vale NSW 2103",
    "addr:housenumber":"1791",
    "addr:postcode":"2103",
    "addr:street":"Pittwater Rd",
    "iso:country":"AU",
    "sg:address":"1791 Pittwater Rd",
    "sg:city":"Mona Vale",
    "sg:classifiers":[
        {
            "category":"Health Services",
            "subcategory":"Doctor",
            "type":"Services"
        }
    ],
    "sg:phone":"+61 2 9997 3911",
    "sg:postcode":"2103",
    "sg:province":"NSW",
    "sg:tags":[
        "medical",
        "practitioner"
    ],
    "wof:name":"Pittwater Family Practice",
    "wof:placetype":"venue"
},
  "geometry": {"coordinates":[151.30299377399999,-33.6749153137],"type":"Point"}
}