{
  "type": "Feature",
  "properties": {
    "addr:full":"31 Austral St Mt Druitt NSW 2770",
    "addr:housenumber":"31",
    "addr:postcode":"2770",
    "addr:street":"Austral St Mt",
    "iso:country":"AU",
    "sg:address":"31 Austral St",
    "sg:city":"Mt Druitt",
    "sg:classifiers":[
        {
            "category":"Autos & Motor Vehicles",
            "subcategory":"Recreational Vehicle Sales",
            "type":"Retail Goods"
        }
    ],
    "sg:phone":"+61 2 9675 7314",
    "sg:postcode":"2770",
    "sg:province":"NSW",
    "sg:tags":[
        "industrial",
        "sewing",
        "contractor"
    ],
    "wof:name":"Ranias Sewing",
    "wof:placetype":"venue"
},
  "geometry": {"coordinates":[150.815795898,-33.7613945007],"type":"Point"}
}