{
  "type": "Feature",
  "properties": {
    "addr:full":"19 Tincogin St Mullumbimby NSW 2482",
    "addr:housenumber":"19",
    "addr:postcode":"2482",
    "addr:street":"Tincogin St",
    "iso:country":"AU",
    "sg:address":"19 Tincogin St",
    "sg:city":"Mullumbimby",
    "sg:classifiers":[
        {
            "category":"Arena",
            "subcategory":"Sports Club",
            "type":"Entertainment"
        }
    ],
    "sg:phone":"+61 2 6684 1959",
    "sg:postcode":"2482",
    "sg:province":"NSW",
    "sg:tags":[
        "organisation",
        "sporting"
    ],
    "wof:name":"Community Bicycle Club",
    "wof:placetype":"venue"
},
  "geometry": {"coordinates":[153.49920654300001,-28.5548000336],"type":"Point"}
}