{
  "type": "Feature",
  "properties": {
    "addr:full":"11 Maybrook Ave Cromer NSW 2099",
    "addr:housenumber":"11",
    "addr:postcode":"2099",
    "addr:street":"Maybrook Ave",
    "iso:country":"AU",
    "sg:address":"11 Maybrook Ave",
    "sg:city":"Cromer",
    "sg:classifiers":[
        {
            "category":"Building & Trades",
            "subcategory":"Construction",
            "type":"Services"
        }
    ],
    "sg:phone":"+61 2 9401 4672",
    "sg:postcode":"2099",
    "sg:province":"NSW",
    "sg:tags":[
        "renovation",
        "alterations",
        "extension",
        "contractor"
    ],
    "wof:name":"AASAR Performance Engines",
    "wof:placetype":"venue"
},
  "geometry": {"coordinates":[151.26649475100001,-33.7368087769],"type":"Point"}
}