{
  "type": "Feature",
  "properties": {
    "addr:full":"Wingate St Greenacres SA 5086",
    "addr:postcode":"5086",
    "addr:street":"Wingate St",
    "iso:country":"AU",
    "sg:address":"Wingate St",
    "sg:city":"Greenacres",
    "sg:classifiers":[
        {
            "category":"Professional",
            "subcategory":"Business Services",
            "type":"Services"
        }
    ],
    "sg:phone":"+61 418 822 496",
    "sg:postcode":"5086",
    "sg:province":"SA",
    "sg:tags":[
        "drafting"
    ],
    "wof:name":"Creative Designs Drafting Services",
    "wof:placetype":"venue"
},
  "geometry": {"coordinates":[138.62709045400001,-34.866394043],"type":"Point"}
}