{
  "type": "Feature",
  "properties": {
    "iso:country":"AU",
    "sg:address":"PO Box 588",
    "sg:city":"Braeside",
    "sg:classifiers":[
        {
            "category":"Autos & Motor Vehicles",
            "subcategory":"Auto Supplies",
            "type":"Retail Goods"
        }
    ],
    "sg:phone":"+61 3 8587 1220",
    "sg:postcode":"3195",
    "sg:province":"VIC",
    "sg:tags":[
        "wheel",
        "four",
        "equipment",
        "drive",
        "accessory"
    ],
    "wof:name":"4x4 Gear Australia",
    "wof:placetype":"venue"
},
  "geometry": {"coordinates":[145.11375427199999,-38.0084381104],"type":"Point"}
}