{
  "type": "Feature",
  "properties": {
    "iso:country":"AU",
    "sg:address":"302 Box Rd",
    "sg:city":"Sylvania",
    "sg:classifiers":[
        {
            "category":"Organizations",
            "subcategory":"Non-profit Organization",
            "type":"Services"
        }
    ],
    "sg:phone":"+61 2 9544 8059",
    "sg:postcode":"2224",
    "sg:province":"NSW",
    "sg:tags":[
        "support",
        "disability",
        "organisation"
    ],
    "wof:name":"St George Area Intellectual Disability Services Ltd",
    "wof:placetype":"venue"
},
  "geometry": {"coordinates":[151.09379577600001,-34.0201797485],"type":"Point"}
}