{
  "type": "Feature",
  "properties": {
    "iso:country":"AU",
    "sg:address":"19 Eighth Ave",
    "sg:city":"Sawtell",
    "sg:classifiers":[
        {
            "category":"Home & Garden",
            "subcategory":"Carpets & Floor Coverings",
            "type":"Retail Goods"
        }
    ],
    "sg:phone":"+61 2 6653 1088",
    "sg:postcode":"2452",
    "sg:province":"NSW",
    "sg:tags":[
        "tile",
        "wall",
        "layer"
    ],
    "wof:name":"TJ & RD West",
    "wof:placetype":"venue"
},
  "geometry": {"coordinates":[153.097336,-30.367338],"type":"Point"}
}