{
  "type": "Feature",
  "properties": {
    "addr:full":"7 Keys Ave Brighton East VIC 3187",
    "addr:housenumber":"7",
    "addr:postcode":"3187",
    "addr:street":"Keys Ave",
    "iso:country":"AU",
    "sg:address":"7 Keys Ave",
    "sg:city":"Brighton East",
    "sg:classifiers":[
        {
            "category":"Real Estate",
            "subcategory":"Architect",
            "type":"Services"
        }
    ],
    "sg:phone":"+61 3 9596 6699",
    "sg:postcode":"3187",
    "sg:province":"VIC",
    "wof:name":"Witorz John",
    "wof:placetype":"venue"
},
  "geometry": {"coordinates":[145.01173400900001,-37.9071235657],"type":"Point"}
}