{
  "type": "Feature",
  "properties": {
    "addr:full":"1 Innes St Glenorchy TAS 7010",
    "addr:housenumber":"1",
    "addr:postcode":"7010",
    "addr:street":"Innes St",
    "iso:country":"AU",
    "sg:address":"1 Innes St",
    "sg:city":"Glenorchy",
    "sg:classifiers":[
        {
            "category":"Farming",
            "subcategory":"Farm & Veterinary Services",
            "type":"Manufacturing & Wholesale Goods"
        }
    ],
    "sg:phone":"+61 3 6273 5567",
    "sg:postcode":"7010",
    "sg:province":"TAS",
    "sg:tags":[
        "poultry",
        "processing",
        "supply"
    ],
    "wof:name":"Creative Chicken & Meat",
    "wof:placetype":"venue"
},
  "geometry": {"coordinates":[147.26991272000001,-42.829536438],"type":"Point"}
}