{
  "type": "Feature",
  "properties": {
    "addr:full":"312 Pacific Hwy Artarmon NSW 2064",
    "addr:housenumber":"312",
    "addr:postcode":"2064",
    "addr:street":"Pacific Hwy",
    "iso:country":"AU",
    "sg:address":"312 Pacific Hwy",
    "sg:city":"Artarmon",
    "sg:classifiers":[
        {
            "category":"Travel",
            "subcategory":"Hotels & Motels",
            "type":"Entertainment"
        }
    ],
    "sg:phone":"+61 2 9439 6333",
    "sg:postcode":"2064",
    "sg:province":"NSW",
    "wof:name":"Linwood Lodge Motel",
    "wof:placetype":"venue"
},
  "geometry": {"coordinates":[151.17958068900001,-33.8172302246],"type":"Point"}
}