{
  "type": "Feature",
  "properties": {
    "addr:full":"17 James St Charlestown NSW 2290",
    "addr:housenumber":"17",
    "addr:postcode":"2290",
    "addr:street":"James St",
    "iso:country":"AU",
    "sg:address":"17 James St",
    "sg:city":"Charlestown",
    "sg:classifiers":[
        {
            "category":"Organizations",
            "subcategory":"Non-profit Organization",
            "type":"Services"
        }
    ],
    "sg:phone":"+61 2 4943 9786",
    "sg:postcode":"2290",
    "sg:province":"NSW",
    "sg:tags":[
        "support",
        "disability",
        "organisation"
    ],
    "wof:name":"Stroke & Disability Information (Hunter) Inc",
    "wof:placetype":"venue"
},
  "geometry": {"coordinates":[151.69778442399999,-32.9690704346],"type":"Point"}
}