{
  "type": "Feature",
  "properties": {
    "iso:country":"AU",
    "sg:address":"Ridley St",
    "sg:city":"Hindmarsh",
    "sg:classifiers":[
        {
            "category":"Building & Trades",
            "subcategory":"Construction",
            "type":"Services"
        }
    ],
    "sg:phone":"+61 403 834 229",
    "sg:postcode":"5007",
    "sg:province":"SA",
    "sg:tags":[
        "fencing",
        "contractor"
    ],
    "wof:name":"The Cast Iron Fence Company",
    "wof:placetype":"venue"
},
  "geometry": {"coordinates":[138.569091797,-34.9019050598],"type":"Point"}
}