{
  "type": "Feature",
  "properties": {
    "addr:full":"48a Oxford St Epping NSW 2121",
    "addr:housenumber":"48a",
    "addr:postcode":"2121",
    "addr:street":"Oxford St",
    "iso:country":"AU",
    "sg:address":"48a Oxford St",
    "sg:city":"Epping",
    "sg:classifiers":[
        {
            "category":"Education",
            "subcategory":"School",
            "type":"Public Place"
        }
    ],
    "sg:phone":"+61 2 9869 8033",
    "sg:postcode":"2121",
    "sg:province":"NSW",
    "sg:tags":[
        "girl"
    ],
    "wof:name":"Our Lady Of Mercy College",
    "wof:placetype":"venue"
},
  "geometry": {"coordinates":[151.08366394000001,-33.7699356079],"type":"Point"}
}