{
  "type": "Feature",
  "properties": {
    "iso:country":"AU",
    "sg:address":"55- 59 Shellharbour Rd",
    "sg:city":"Port Kembla",
    "sg:classifiers":[
        {
            "category":"Building & Trades",
            "subcategory":"Construction",
            "type":"Services"
        }
    ],
    "sg:phone":"+61 2 4276 2662",
    "sg:postcode":"2505",
    "sg:province":"NSW",
    "sg:tags":[
        "management"
    ],
    "wof:name":"Malsave Pty Ltd",
    "wof:placetype":"venue"
},
  "geometry": {"coordinates":[150.888443,-34.480892],"type":"Point"}
}