{
  "type": "Feature",
  "properties": {
    "addr:full":"99 River St Ballina NSW 2478",
    "addr:housenumber":"99",
    "addr:postcode":"2478",
    "addr:street":"River St",
    "iso:country":"AU",
    "sg:address":"99 River St",
    "sg:city":"Ballina",
    "sg:classifiers":[
        {
            "category":"Shopping",
            "subcategory":"Jewelry",
            "type":"Retail Goods"
        }
    ],
    "sg:phone":"+61 2 6686 3248",
    "sg:postcode":"2478",
    "sg:province":"NSW",
    "sg:tags":[
        "jeweller"
    ],
    "wof:name":"Riverside Jewellers",
    "wof:placetype":"venue"
},
  "geometry": {"coordinates":[153.56138610799999,-28.8709545135],"type":"Point"}
}