{
  "type": "Feature",
  "properties": {
    "addr:full":"39 Wyong Rd Tumbi Umbi NSW 2261",
    "addr:housenumber":"39",
    "addr:postcode":"2261",
    "addr:street":"Wyong Rd",
    "iso:country":"AU",
    "sg:address":"39 Wyong Rd",
    "sg:city":"Tumbi Umbi",
    "sg:classifiers":[
        {
            "category":"Home & Garden",
            "subcategory":"Household Appliances",
            "type":"Retail Goods"
        }
    ],
    "sg:phone":"+61 2 4388 1274",
    "sg:postcode":"2261",
    "sg:province":"NSW",
    "sg:tags":[
        "heating",
        "system"
    ],
    "wof:name":"Tumbi Mowers",
    "wof:placetype":"venue"
},
  "geometry": {"coordinates":[151.44654800000001,-33.362415],"type":"Point"}
}