{
  "type": "Feature",
  "properties": {
    "iso:country":"AU",
    "sg:address":"57 Ourimbah Rd",
    "sg:city":"Tweed Heads",
    "sg:classifiers":[
        {
            "category":"Building & Trades",
            "subcategory":"Construction",
            "type":"Services"
        }
    ],
    "sg:phone":"+61 7 5536 2549",
    "sg:postcode":"2485",
    "sg:province":"NSW",
    "sg:tags":[
        "scaffolding"
    ],
    "wof:name":"Secura Scaffold Queensland",
    "wof:placetype":"venue"
},
  "geometry": {"coordinates":[153.522872925,-28.1752738953],"type":"Point"}
}