{
  "type": "Feature",
  "properties": {
    "addr:full":"Shp1b/ 7075 Great Eastern Hwy Mundaring WA 6073",
    "addr:housenumber":"7075",
    "addr:postcode":"6073",
    "addr:street":"Great Eastern Hwy",
    "iso:country":"AU",
    "sg:address":"Shp1b/ 7075 Great Eastern Hwy",
    "sg:city":"Mundaring",
    "sg:classifiers":[
        {
            "category":"Sports & Exercise",
            "subcategory":"Gym",
            "type":"Entertainment"
        }
    ],
    "sg:phone":"+61 8 9295 6088",
    "sg:postcode":"6073",
    "sg:province":"WA",
    "sg:tags":[
        "health",
        "fitness"
    ],
    "wof:name":"Contours Express Mundaring",
    "wof:placetype":"venue"
},
  "geometry": {"coordinates":[116.16490936300001,-31.9015674591],"type":"Point"}
}