{
  "type": "Feature",
  "properties": {
    "addr:full":"201 Dyson Rd Lonsdale SA 5160",
    "addr:housenumber":"201",
    "addr:postcode":"5160",
    "addr:street":"Dyson Rd",
    "iso:country":"AU",
    "sg:address":"201 Dyson Rd",
    "sg:city":"Lonsdale",
    "sg:classifiers":[
        {
            "category":"Building & Trades",
            "subcategory":"Construction",
            "type":"Services"
        }
    ],
    "sg:phone":"+61 8 8384 6235",
    "sg:postcode":"5160",
    "sg:province":"SA",
    "sg:tags":[
        "insulation",
        "contractor"
    ],
    "wof:name":"Energy Insulation Centre",
    "wof:placetype":"venue"
},
  "geometry": {"coordinates":[138.49151611299999,-35.1175422668],"type":"Point"}
}