{
  "type": "Feature",
  "properties": {
    "addr:full":"1A Norfolk St Fremantle WA 6160",
    "addr:housenumber":"1a",
    "addr:postcode":"6160",
    "addr:street":"Norfolk St",
    "iso:country":"AU",
    "sg:address":"1A Norfolk St",
    "sg:city":"Fremantle",
    "sg:classifiers":[
        {
            "category":"Personal",
            "subcategory":"Beauty Salon",
            "type":"Services"
        }
    ],
    "sg:phone":"+61 8 9336 5000",
    "sg:postcode":"6160",
    "sg:province":"WA",
    "wof:name":"Maki 2 Beauty Therapy",
    "wof:placetype":"venue"
},
  "geometry": {"coordinates":[115.74749799999999,-32.058395],"type":"Point"}
}