{
  "type": "Feature",
  "properties": {
    "addr:full":"40 Stud Rd Dandenong VIC 3175",
    "addr:housenumber":"40",
    "addr:postcode":"3175",
    "addr:street":"Stud Rd",
    "iso:country":"AU",
    "sg:address":"40 Stud Rd",
    "sg:city":"Dandenong",
    "sg:classifiers":[
        {
            "category":"Personal",
            "subcategory":"Hair Removal",
            "type":"Services"
        }
    ],
    "sg:phone":"+61 3 9521 9502",
    "sg:postcode":"3175",
    "sg:province":"VIC",
    "wof:name":"Elias Elena",
    "wof:placetype":"venue"
},
  "geometry": {"coordinates":[145.221557617,-37.9818496704],"type":"Point"}
}