{
  "type": "Feature",
  "properties": {
    "iso:country":"AU",
    "sg:address":"431 Suite 1 Burke Rd",
    "sg:city":"Glen Iris",
    "sg:classifiers":[
        {
            "category":"Professional",
            "subcategory":"Computer Services",
            "type":"Services"
        }
    ],
    "sg:phone":"+61 3 9819 9000",
    "sg:postcode":"3146",
    "sg:province":"VIC",
    "sg:tags":[
        "package",
        "software"
    ],
    "wof:name":"Business To Business Technology Pty Ltd",
    "wof:placetype":"venue"
},
  "geometry": {"coordinates":[145.04765319800001,-37.8778343201],"type":"Point"}
}