{
  "type": "Feature",
  "properties": {
    "addr:full":"30 Pittwater Rd Manly NSW 2095",
    "addr:housenumber":"30",
    "addr:postcode":"2095",
    "addr:street":"Pittwater Rd",
    "iso:country":"AU",
    "sg:address":"30 Pittwater Rd",
    "sg:city":"Manly",
    "sg:classifiers":[
        {
            "category":"Building & Trades",
            "subcategory":"Construction",
            "type":"Services"
        }
    ],
    "sg:phone":"+61 2 9976 3466",
    "sg:postcode":"2095",
    "sg:province":"NSW",
    "sg:tags":[
        "industrial",
        "commercial",
        "air conditioning"
    ],
    "wof:name":"Rafrow Pty Ltd",
    "wof:placetype":"venue"
},
  "geometry": {"coordinates":[151.285354614,-33.7948455811],"type":"Point"}
}