{
  "type": "Feature",
  "properties": {
    "addr:full":"88 Pacific Hwy Roseville NSW 2069",
    "addr:housenumber":"88",
    "addr:postcode":"2069",
    "addr:street":"Pacific Hwy",
    "iso:country":"AU",
    "sg:address":"88 Pacific Hwy",
    "sg:city":"Roseville",
    "sg:classifiers":[
        {
            "category":"Health Services",
            "subcategory":"Health Practitioner",
            "type":"Services"
        }
    ],
    "sg:phone":"+61 2 9411 2800",
    "sg:postcode":"2069",
    "sg:province":"NSW",
    "sg:tags":[
        "psychologist"
    ],
    "wof:name":"Hoey Peter Dr",
    "wof:placetype":"venue"
},
  "geometry": {"coordinates":[151.17730712900001,-33.7849960327],"type":"Point"}
}