{
  "type": "Feature",
  "properties": {
    "iso:country":"AU",
    "sg:address":"85 Racecourse Rd",
    "sg:city":"Ascot",
    "sg:classifiers":[
        {
            "category":"Banks & Credit Unions",
            "subcategory":"Investment Brokerage",
            "type":"Services"
        }
    ],
    "sg:phone":"+61 1800 680 097",
    "sg:postcode":"4007",
    "sg:province":"QLD",
    "sg:tags":[
        "management",
        "property"
    ],
    "wof:name":"Conias Rentals",
    "wof:placetype":"venue"
},
  "geometry": {"coordinates":[153.06506300000001,-27.435431],"type":"Point"}
}