{
  "type": "Feature",
  "properties": {
    "addr:full":"57 Cliff Drv Katoomba NSW 2780",
    "addr:housenumber":"57",
    "addr:postcode":"2780",
    "addr:street":"Cliff Drv",
    "iso:country":"AU",
    "sg:address":"57 Cliff Drv",
    "sg:city":"Katoomba",
    "sg:classifiers":[
        {
            "category":"Home & Garden",
            "subcategory":"Carpets & Floor Coverings",
            "type":"Retail Goods"
        }
    ],
    "sg:phone":"+61 419 442 034",
    "sg:postcode":"2780",
    "sg:province":"NSW",
    "sg:tags":[
        "tile",
        "wall"
    ],
    "wof:name":"Dege H.E.",
    "wof:placetype":"venue"
},
  "geometry": {"coordinates":[150.31651306099999,-33.7243232727],"type":"Point"}
}