{
  "type": "Feature",
  "properties": {
    "addr:full":"3 Beitz Rd Alberton QLD 4207",
    "addr:housenumber":"3",
    "addr:postcode":"4207",
    "addr:street":"Beitz Rd",
    "iso:country":"AU",
    "sg:address":"3 Beitz Rd",
    "sg:city":"Alberton",
    "sg:classifiers":[
        {
            "category":"Retail",
            "subcategory":"Laundry & Dry Cleaning",
            "type":"Services"
        }
    ],
    "sg:phone":"+61 7 5546 2718",
    "sg:postcode":"4207",
    "sg:province":"QLD",
    "sg:tags":[
        "truck",
        "tip",
        "contractor"
    ],
    "wof:name":"Pritchett Tipper Haulage",
    "wof:placetype":"venue"
},
  "geometry": {"coordinates":[153.27757263199999,-27.7013092041],"type":"Point"}
}