{
  "type": "Feature",
  "properties": {
    "addr:full":"4 Yangoora Pl Greensborough VIC 3088",
    "addr:housenumber":"4",
    "addr:postcode":"3088",
    "addr:street":"Yangoora Pl",
    "iso:country":"AU",
    "sg:address":"4 Yangoora Pl",
    "sg:city":"Greensborough",
    "sg:classifiers":[
        {
            "category":"Building & Trades",
            "subcategory":"Equipment Rental",
            "type":"Services"
        }
    ],
    "sg:phone":"+61 416 137 540",
    "sg:postcode":"3088",
    "sg:province":"VIC",
    "sg:tags":[
        "crane",
        "hire"
    ],
    "wof:name":"NAB Crane Truck Services",
    "wof:placetype":"venue"
},
  "geometry": {"coordinates":[145.12747192399999,-37.7016448975],"type":"Point"}
}