{
  "type": "Feature",
  "properties": {
    "addr:full":"Lot 187 3 Smith St Emu Plains NSW 2750",
    "addr:housenumber":"3",
    "addr:postcode":"2750",
    "addr:street":"Smith St",
    "iso:country":"AU",
    "sg:address":"Lot 187 3 Smith St",
    "sg:city":"Emu Plains",
    "sg:classifiers":[
        {
            "category":"Retail",
            "subcategory":"Auto Repair",
            "type":"Services"
        }
    ],
    "sg:phone":"+61 2 4735 4868",
    "sg:postcode":"2750",
    "sg:province":"NSW",
    "sg:tags":[
        "bus",
        "truck"
    ],
    "wof:name":"G.H.J. Diesel Spares & Repairs",
    "wof:placetype":"venue"
},
  "geometry": {"coordinates":[150.67074585,-33.7430915833],"type":"Point"}
}