{
  "type": "Feature",
  "properties": {
    "addr:full":"2nd Floor 108 Flinders St Melbourne VIC 3000",
    "addr:housenumber":"108",
    "addr:postcode":"3000",
    "addr:street":"Flinders St",
    "iso:country":"AU",
    "sg:address":"2nd Floor 108 Flinders St",
    "sg:city":"Melbourne",
    "sg:classifiers":[
        {
            "category":"Professional",
            "subcategory":"Accounting & Tax Preparation",
            "type":"Services"
        }
    ],
    "sg:phone":"+61 3 9654 8804",
    "sg:postcode":"3000",
    "sg:province":"VIC",
    "sg:tags":[
        "accountant",
        "auditor"
    ],
    "wof:name":"Professional Business Secretariat",
    "wof:placetype":"venue"
},
  "geometry": {"coordinates":[144.971313477,-37.8161811829],"type":"Point"}
}