{
  "type": "Feature",
  "properties": {
    "iso:country":"AU",
    "sg:address":"Coronation Drv",
    "sg:city":"Brisbane",
    "sg:classifiers":[
        {
            "category":"Organizations",
            "subcategory":"Community Association",
            "type":"Services"
        }
    ],
    "sg:phone":"+61 7 3235 9999",
    "sg:postcode":"4000",
    "sg:province":"QLD",
    "sg:tags":[
        "organisation",
        "family",
        "welfare"
    ],
    "wof:name":"Crisis Care",
    "wof:placetype":"venue"
},
  "geometry": {"coordinates":[153.017410278,-27.467748642],"type":"Point"}
}