{
  "type": "Feature",
  "properties": {
    "iso:country":"AU",
    "sg:address":"107 Ormond Rd",
    "sg:city":"Elwood",
    "sg:classifiers":[
        {
            "category":"Cafe",
            "type":"Food & Drink"
        }
    ],
    "sg:phone":"+61 3 9531 3755",
    "sg:postcode":"3184",
    "sg:province":"VIC",
    "wof:name":"Indulge Coffee & Chocolates Pty Ltd",
    "wof:placetype":"venue"
},
  "geometry": {"coordinates":[144.98773193400001,-37.8852806091],"type":"Point"}
}