{
  "type": "Feature",
  "properties": {
    "addr:full":"Lot 4 Majors Rd Eaglehawk VIC 3556",
    "addr:postcode":"3556",
    "addr:street":"Majors Rd",
    "iso:country":"AU",
    "sg:address":"Lot 4 Majors Rd",
    "sg:city":"Eaglehawk",
    "sg:classifiers":[
        {
            "category":"Utilities",
            "subcategory":"Telephone",
            "type":"Services"
        }
    ],
    "sg:phone":"+61 401 915 399",
    "sg:postcode":"3556",
    "sg:province":"VIC",
    "sg:tags":[
        "equipment",
        "system"
    ],
    "wof:name":"Voice Technology Solutions",
    "wof:placetype":"venue"
},
  "geometry": {"coordinates":[144.266967773,-36.7076683044],"type":"Point"}
}