{
  "type": "Feature",
  "properties": {
    "addr:full":"3 Mayfair Crt Croydon VIC 3136",
    "addr:housenumber":"3",
    "addr:postcode":"3136",
    "addr:street":"Mayfair Crt",
    "iso:country":"AU",
    "sg:address":"3 Mayfair Crt",
    "sg:city":"Croydon",
    "sg:classifiers":[
        {
            "category":"Sports & Exercise",
            "subcategory":"Gym",
            "type":"Entertainment"
        }
    ],
    "sg:phone":"+61 3 9723 3429",
    "sg:postcode":"3136",
    "sg:province":"VIC",
    "sg:tags":[
        "meditation"
    ],
    "wof:name":"Aspirational Personal Health",
    "wof:placetype":"venue"
},
  "geometry": {"coordinates":[145.27471923799999,-37.7880477905],"type":"Point"}
}