{
  "type": "Feature",
  "properties": {
    "addr:full":"6 Bradwardine Rd Bathurst NSW 2795",
    "addr:housenumber":"6",
    "addr:postcode":"2795",
    "addr:street":"Bradwardine Rd",
    "iso:country":"AU",
    "sg:address":"6 Bradwardine Rd",
    "sg:city":"Bathurst",
    "sg:classifiers":[
        {
            "category":"Building & Trades",
            "subcategory":"Construction",
            "type":"Services"
        }
    ],
    "sg:phone":"+61 2 6331 2882",
    "sg:postcode":"2795",
    "sg:province":"NSW",
    "sg:tags":[
        "fencing",
        "contractor"
    ],
    "wof:name":"Sunset Fencing",
    "wof:placetype":"venue"
},
  "geometry": {"coordinates":[149.54408264200001,-33.4147605896],"type":"Point"}
}