{
  "type": "Feature",
  "properties": {
    "addr:full":"PO Box 285 Terrey Hills NSW 2084",
    "addr:postcode":"2084",
    "iso:country":"AU",
    "sg:address":"PO Box 285",
    "sg:city":"Terrey Hills",
    "sg:classifiers":[
        {
            "category":"Recreation",
            "type":"Entertainment"
        }
    ],
    "sg:phone":"+61 418 252 050",
    "sg:postcode":"2084",
    "sg:province":"NSW",
    "sg:tags":[
        "supply",
        "outdoor",
        "adventure",
        "activity"
    ],
    "wof:name":"Sydney Outdoor Leisure & Recreation",
    "wof:placetype":"venue"
},
  "geometry": {"coordinates":[151.229705811,-33.6837692261],"type":"Point"}
}