{
  "type": "Feature",
  "properties": {
    "iso:country":"AU",
    "sg:address":"35 Meeks Rd",
    "sg:city":"Marrickville",
    "sg:classifiers":[
        {
            "category":"Food & Beverages",
            "subcategory":"Bakery",
            "type":"Retail Goods"
        }
    ],
    "sg:phone":"+61 2 9516 4121",
    "sg:postcode":"2204",
    "sg:province":"NSW",
    "sg:tags":[
        "baker"
    ],
    "wof:name":"Mr Focaccia",
    "wof:placetype":"venue"
},
  "geometry": {"coordinates":[151.161957,-33.91177],"type":"Point"}
}