{
  "type": "Feature",
  "properties": {
    "iso:country":"AU",
    "sg:address":"22 Boundary Rd",
    "sg:city":"East Geelong",
    "sg:classifiers":[
        {
            "category":"Recreation",
            "subcategory":"Fishing",
            "type":"Entertainment"
        }
    ],
    "sg:phone":"+61 3 5248 8338",
    "sg:postcode":"3219",
    "sg:province":"VIC",
    "sg:tags":[
        "tackle"
    ],
    "wof:name":"Pro-Angler Geelong",
    "wof:placetype":"venue"
},
  "geometry": {"coordinates":[144.38607788100001,-38.1594429016],"type":"Point"}
}