{
  "type": "Feature",
  "properties": {
    "addr:full":"1/ 30 Railway Ave Thornton NSW 2322",
    "addr:housenumber":"/ 30",
    "addr:postcode":"2322",
    "addr:street":"Railway Ave",
    "iso:country":"AU",
    "sg:address":"1/ 30 Railway Ave",
    "sg:city":"Thornton",
    "sg:classifiers":[
        {
            "category":"Banks & Credit Unions",
            "subcategory":"Investment Brokerage",
            "type":"Services"
        }
    ],
    "sg:phone":"+61 2 4964 1455",
    "sg:postcode":"2322",
    "sg:province":"NSW",
    "sg:tags":[
        "management",
        "property"
    ],
    "wof:name":"Fetterplace Real Estate",
    "wof:placetype":"venue"
},
  "geometry": {"coordinates":[151.64120483400001,-32.7837333679],"type":"Point"}
}