{
  "type": "Feature",
  "properties": {
    "addr:full":"116 Dunsmore Rd Cowes VIC 3922",
    "addr:housenumber":"116",
    "addr:postcode":"3922",
    "addr:street":"Dunsmore Rd",
    "iso:country":"AU",
    "sg:address":"116 Dunsmore Rd",
    "sg:city":"Cowes",
    "sg:classifiers":[
        {
            "category":"Wholesale",
            "subcategory":"Auto Parts",
            "type":"Manufacturing & Wholesale Goods"
        }
    ],
    "sg:phone":"+61 3 5952 5055",
    "sg:postcode":"3922",
    "sg:province":"VIC",
    "sg:tags":[
        "recyclers"
    ],
    "wof:name":"F - Trucks &#039;R&#039; Us Pty Ltd",
    "wof:placetype":"venue"
},
  "geometry": {"coordinates":[145.24855041500001,-38.4587287903],"type":"Point"}
}