{
  "type": "Feature",
  "properties": {
    "iso:country":"AU",
    "sg:address":"7- 9 Hampton Rd",
    "sg:city":"Burleigh Heads",
    "sg:classifiers":[
        {
            "category":"Building & Trades",
            "subcategory":"Equipment Rental",
            "type":"Services"
        }
    ],
    "sg:phone":"+61 7 5593 8689",
    "sg:postcode":"4220",
    "sg:province":"QLD",
    "sg:tags":[
        "supply",
        "catering"
    ],
    "wof:name":"JinDu International Pty. Ltd.",
    "wof:placetype":"venue"
},
  "geometry": {"coordinates":[153.42393493599999,-28.1034698486],"type":"Point"}
}