{
  "type": "Feature",
  "properties": {
    "addr:full":"129 Military Rd Avondale Heights VIC 3034",
    "addr:housenumber":"129",
    "addr:postcode":"3034",
    "addr:street":"Military Rd",
    "iso:country":"AU",
    "sg:address":"129 Military Rd",
    "sg:city":"Avondale Heights",
    "sg:classifiers":[
        {
            "category":"Real Estate",
            "subcategory":"Architect",
            "type":"Services"
        }
    ],
    "sg:phone":"+61 412 991 005",
    "sg:postcode":"3034",
    "sg:province":"VIC",
    "sg:tags":[
        "building",
        "designer"
    ],
    "wof:name":"Hedjes Design & Project Management",
    "wof:placetype":"venue"
},
  "geometry": {"coordinates":[144.86120600000001,-37.760696],"type":"Point"}
}