{
  "type": "Feature",
  "properties": {
    "addr:full":"1051a/b High St Armadale VIC 3143",
    "addr:housenumber":"1051a / b",
    "addr:postcode":"3143",
    "addr:street":"High St",
    "iso:country":"AU",
    "sg:address":"1051a/b High St",
    "sg:city":"Armadale",
    "sg:classifiers":[
        {
            "category":"Health Services",
            "subcategory":"Health Practitioner",
            "type":"Services"
        }
    ],
    "sg:phone":"+61 3 9824 7755",
    "sg:postcode":"3143",
    "sg:province":"VIC",
    "sg:tags":[
        "psychologist"
    ],
    "wof:name":"Neil Sandra Dr",
    "wof:placetype":"venue"
},
  "geometry": {"coordinates":[145.01965332,-37.8553466797],"type":"Point"}
}