{
  "type": "Feature",
  "properties": {
    "iso:country":"AU",
    "sg:address":"Cnr Parkes St & Old Princes Hwy",
    "sg:city":"Helensburgh",
    "sg:classifiers":[
        {
            "category":"Professional",
            "subcategory":"Accounting & Tax Preparation",
            "type":"Services"
        }
    ],
    "sg:phone":"+61 2 4294 4462",
    "sg:postcode":"2508",
    "sg:province":"NSW",
    "sg:tags":[
        "accountant",
        "auditor"
    ],
    "wof:name":"Small Business Accountants Pty Ltd",
    "wof:placetype":"venue"
},
  "geometry": {"coordinates":[150.981064,-34.190742],"type":"Point"}
}