{
  "type": "Feature",
  "properties": {
    "addr:full":"Gardens Point Campus 2 George St Brisbane QLD 4000",
    "addr:housenumber":"2",
    "addr:postcode":"4000",
    "addr:street":"Gardens;George St",
    "iso:country":"AU",
    "sg:address":"Gardens Point Campus 2 George St",
    "sg:city":"Brisbane",
    "sg:classifiers":[
        {
            "category":"Education",
            "subcategory":"Kindergarten",
            "type":"Public Place"
        }
    ],
    "sg:phone":"+61 7 3864 1690",
    "sg:postcode":"4000",
    "sg:province":"QLD",
    "sg:tags":[
        "pre-schools"
    ],
    "wof:name":"QUT Student Guild Child Care Centre",
    "wof:placetype":"venue"
},
  "geometry": {"coordinates":[153.02708435100001,-27.474773407],"type":"Point"}
}