{
  "type": "Feature",
  "properties": {
    "addr:full":"Ste 5 14 -16 Garden Blv Dingley VIC 3172",
    "addr:housenumber":"14 -16",
    "addr:postcode":"3172",
    "addr:street":"Garden Blv",
    "iso:country":"AU",
    "sg:address":"Ste 5 14",
    "sg:city":"-16 Garden Blv Dingley",
    "sg:classifiers":[
        {
            "category":"Professional",
            "subcategory":"Computer Services",
            "type":"Services"
        }
    ],
    "sg:phone":"+61 3 9558 1989",
    "sg:postcode":"3172",
    "sg:province":"VIC",
    "sg:tags":[
        "training"
    ],
    "wof:name":"Datatask Pty Ltd",
    "wof:placetype":"venue"
},
  "geometry": {"coordinates":[145.11369323700001,-37.9806785583],"type":"Point"}
}