{
  "type": "Feature",
  "properties": {
    "addr:full":"Level 4/ 29 Christy St St Leonards NSW 2065",
    "addr:housenumber":"/ 29",
    "addr:postcode":"2065",
    "addr:street":"Christy St",
    "iso:country":"AU",
    "sg:address":"Level 4/ 29 Christy St",
    "sg:city":"St Leonards",
    "sg:classifiers":[
        {
            "category":"Building & Trades",
            "subcategory":"Construction",
            "type":"Services"
        }
    ],
    "sg:phone":"+61 2 9906 6977",
    "sg:postcode":"2065",
    "sg:province":"NSW",
    "sg:tags":[
        "contractor"
    ],
    "wof:name":"ISIS Projects Pty Limited",
    "wof:placetype":"venue"
},
  "geometry": {"coordinates":[151.19920349099999,-33.8258094788],"type":"Point"}
}