{
  "type": "Feature",
  "properties": {
    "iso:country":"AU",
    "sg:address":"15 English Ave",
    "sg:city":"Camden",
    "sg:classifiers":[
        {
            "category":"Building & Trades",
            "subcategory":"Landscaping Services",
            "type":"Services"
        }
    ],
    "sg:phone":"+61 2 4655 2224",
    "sg:postcode":"2570",
    "sg:province":"NSW",
    "sg:tags":[
        "consultant"
    ],
    "wof:name":"Bill Benad & Co.",
    "wof:placetype":"venue"
},
  "geometry": {"coordinates":[150.69691467300001,-34.0883560181],"type":"Point"}
}