{
  "type": "Feature",
  "properties": {
    "iso:country":"AU",
    "sg:address":"PO Box 1073",
    "sg:city":"Booragoon",
    "sg:classifiers":[
        {
            "category":"Education",
            "subcategory":"Special Training",
            "type":"Public Place"
        }
    ],
    "sg:phone":"+61 438 853 785",
    "sg:postcode":"6154",
    "sg:province":"WA",
    "sg:tags":[
        "school",
        "sailing"
    ],
    "wof:name":"Go Windsurfing",
    "wof:placetype":"venue"
},
  "geometry": {"coordinates":[115.832329,-32.036018],"type":"Point"}
}