{
  "type": "Feature",
  "properties": {
    "addr:full":"Mackay Marina, Mulherin Drv Mackay Harbour QLD 4740",
    "addr:postcode":"4740",
    "addr:street":"Mulherin Drv",
    "iso:country":"AU",
    "sg:address":"Mackay Marina, Mulherin Drv",
    "sg:city":"Mackay Harbour",
    "sg:classifiers":[
        {
            "category":"Building & Trades",
            "subcategory":"Cleaning & Sanitation",
            "type":"Services"
        }
    ],
    "sg:phone":"+61 7 4959 5829",
    "sg:postcode":"4740",
    "sg:province":"QLD",
    "sg:tags":[
        "industrial",
        "commercial",
        "contractor"
    ],
    "wof:name":"Boutique Marine",
    "wof:placetype":"venue"
},
  "geometry": {"coordinates":[149.22177099999999,-21.114086],"type":"Point"}
}