{
  "type": "Feature",
  "properties": {
    "addr:full":"Suite 22/ 10 Bridge St Granville NSW 2142",
    "addr:housenumber":"22 / 10",
    "addr:postcode":"2142",
    "addr:street":"Bridge St",
    "iso:country":"AU",
    "sg:address":"Suite 22/ 10 Bridge St",
    "sg:city":"Granville",
    "sg:classifiers":[
        {
            "category":"Insurance",
            "subcategory":"Insurance Agent",
            "type":"Services"
        }
    ],
    "sg:phone":"+61 2 9955 4366",
    "sg:postcode":"2142",
    "sg:province":"NSW",
    "wof:name":"INPRO Australia Pty Ltd",
    "wof:placetype":"venue"
},
  "geometry": {"coordinates":[151.01219177199999,-33.8323860168],"type":"Point"}
}