{
  "type": "Feature",
  "properties": {
    "addr:full":"Mason St Altona North VIC 3025",
    "addr:postcode":"3025",
    "addr:street":"Mason St",
    "iso:country":"AU",
    "sg:address":"Mason St",
    "sg:city":"Altona North",
    "sg:classifiers":[
        {
            "category":"Arena",
            "subcategory":"Sports Club",
            "type":"Entertainment"
        }
    ],
    "sg:phone":"+61 3 9391 0880",
    "sg:postcode":"3025",
    "sg:province":"VIC",
    "sg:tags":[
        "organisation",
        "sporting"
    ],
    "wof:name":"Western Suburbs Badminton Assoc.",
    "wof:placetype":"venue"
},
  "geometry": {"coordinates":[144.84703099999999,-37.838394],"type":"Point"}
}