{
  "type": "Feature",
  "properties": {
    "addr:full":"Lvl 2, 175- 181 Oxford St Bondi Junction NSW 2022",
    "addr:housenumber":"175 181",
    "addr:postcode":"2022",
    "addr:street":"Oxford St",
    "iso:country":"AU",
    "sg:address":"Lvl 2, 175- 181 Oxford St",
    "sg:city":"Bondi Junction",
    "sg:classifiers":[
        {
            "category":"Real Estate",
            "subcategory":"Real Estate Services",
            "type":"Services"
        }
    ],
    "sg:phone":"+61 2 9130 6666",
    "sg:postcode":"2022",
    "sg:province":"NSW",
    "sg:tags":[
        "valuer"
    ],
    "wof:name":"Australian Real Estate Services Pty Ltd",
    "wof:placetype":"venue"
},
  "geometry": {"coordinates":[151.24876403799999,-33.8921012878],"type":"Point"}
}