{
  "type": "Feature",
  "properties": {
    "iso:country":"AU",
    "sg:address":"143 Gipps Rd",
    "sg:city":"Gwynneville",
    "sg:classifiers":[
        {
            "category":"Education",
            "subcategory":"Dance Studio",
            "type":"Public Place"
        }
    ],
    "sg:phone":"+61 2 4225 8855",
    "sg:postcode":"2500",
    "sg:province":"NSW",
    "sg:tags":[
        "venue",
        "tuition"
    ],
    "wof:name":"R-Star Performers",
    "wof:placetype":"venue"
},
  "geometry": {"coordinates":[150.884399,-34.416134],"type":"Point"}
}