{
  "type": "Feature",
  "properties": {
    "addr:full":"114 Tyner Rd Wantirna South VIC 3152",
    "addr:housenumber":"114",
    "addr:postcode":"3152",
    "addr:street":"Tyner Rd",
    "iso:country":"AU",
    "sg:address":"114 Tyner Rd",
    "sg:city":"Wantirna South",
    "sg:classifiers":[
        {
            "category":"Health Services",
            "subcategory":"Health Practitioner",
            "type":"Services"
        }
    ],
    "sg:phone":"+61 3 9887 1962",
    "sg:postcode":"3152",
    "sg:province":"VIC",
    "sg:tags":[
        "physiotherapist"
    ],
    "wof:name":"Cheng Martha",
    "wof:placetype":"venue"
},
  "geometry": {"coordinates":[145.243286133,-37.8748092651],"type":"Point"}
}