{
  "type": "Feature",
  "properties": {
    "addr:full":"130 Military Rd Guildford NSW 2161",
    "addr:housenumber":"130",
    "addr:postcode":"2161",
    "addr:street":"Military Rd",
    "iso:country":"AU",
    "sg:address":"130 Military Rd",
    "sg:city":"Guildford",
    "sg:classifiers":[
        {
            "category":"Health Services",
            "subcategory":"Doctor",
            "type":"Services"
        }
    ],
    "sg:phone":"+61 2 9681 3448",
    "sg:postcode":"2161",
    "sg:province":"NSW",
    "sg:tags":[
        "medical",
        "practitioner"
    ],
    "wof:name":"Chan J Dr",
    "wof:placetype":"venue"
},
  "geometry": {"coordinates":[150.98394775400001,-33.854385376],"type":"Point"}
}