{
  "type": "Feature",
  "properties": {
    "iso:country":"AU",
    "sg:address":"29 Nellbern Rd",
    "sg:city":"Moorabbin",
    "sg:classifiers":[
        {
            "category":"Wholesale",
            "subcategory":"Metals & Minerals",
            "type":"Manufacturing & Wholesale Goods"
        }
    ],
    "sg:phone":"+61 3 9555 8086",
    "sg:postcode":"3189",
    "sg:province":"VIC",
    "sg:tags":[
        "steel",
        "stainless",
        "product",
        "equipment"
    ],
    "wof:name":"Handyman Steel Supplies Pty Ltd",
    "wof:placetype":"venue"
},
  "geometry": {"coordinates":[145.06698608400001,-37.9395561218],"type":"Point"}
}