{
  "type": "Feature",
  "properties": {
    "iso:country":"AU",
    "sg:address":"18 Horswood Rd",
    "sg:city":"Narre Warren North",
    "sg:classifiers":[
        {
            "category":"Farming",
            "subcategory":"Livestock Farm",
            "type":"Manufacturing & Wholesale Goods"
        }
    ],
    "sg:phone":"+61 3 9796 8302",
    "sg:postcode":"3804",
    "sg:province":"VIC",
    "sg:tags":[
        "agistment"
    ],
    "wof:name":"PineLodge Agistment Farm",
    "wof:placetype":"venue"
},
  "geometry": {"coordinates":[145.305450439,-37.966217041],"type":"Point"}
}