{
  "type": "Feature",
  "properties": {
    "addr:full":"180 Bay St Brighton VIC 3186",
    "addr:housenumber":"180",
    "addr:postcode":"3186",
    "addr:street":"Bay St",
    "iso:country":"AU",
    "sg:address":"180 Bay St",
    "sg:city":"Brighton",
    "sg:classifiers":[
        {
            "category":"Health Services",
            "subcategory":"Dentist",
            "type":"Services"
        }
    ],
    "sg:phone":"+61 3 9596 2092",
    "sg:postcode":"3186",
    "sg:province":"VIC",
    "wof:name":"Brown Anthony P",
    "wof:placetype":"venue"
},
  "geometry": {"coordinates":[144.998413086,-37.9050827026],"type":"Point"}
}