{
  "type": "Feature",
  "properties": {
    "iso:country":"AU",
    "sg:address":"12 Senga St",
    "sg:city":"Manly West",
    "sg:classifiers":[
        {
            "category":"Utilities",
            "subcategory":"Mobile Phone",
            "type":"Services"
        }
    ],
    "sg:phone":"+61 7 3893 0103",
    "sg:postcode":"4179",
    "sg:province":"QLD",
    "sg:tags":[
        "aviation",
        "consultant"
    ],
    "wof:name":"Han-Bry Aviation Consultancy",
    "wof:placetype":"venue"
},
  "geometry": {"coordinates":[153.167877197,-27.4650707245],"type":"Point"}
}