{
  "type": "Feature",
  "properties": {
    "iso:country":"AU",
    "sg:address":"1463 Anzac Ave",
    "sg:city":"Kallangur",
    "sg:classifiers":[
        {
            "category":"Utilities",
            "subcategory":"Electric",
            "type":"Services"
        }
    ],
    "sg:phone":"+61 7 3886 4663",
    "sg:postcode":"4503",
    "sg:province":"QLD",
    "sg:tags":[
        "electrical",
        "contractor"
    ],
    "wof:name":"C.S. Benson Electrical",
    "wof:placetype":"venue"
},
  "geometry": {"coordinates":[153.002227783,-27.2490139008],"type":"Point"}
}