{
  "type": "Feature",
  "properties": {
    "addr:full":"Lot 3 Brigeta Rd Paulls Valley WA 6076",
    "addr:postcode":"6076",
    "addr:street":"Brigeta Rd",
    "iso:country":"AU",
    "sg:address":"Lot 3 Brigeta Rd",
    "sg:city":"Paulls Valley",
    "sg:classifiers":[
        {
            "category":"Transit Center",
            "subcategory":"Freight",
            "type":"Transportation"
        }
    ],
    "sg:phone":"+61 8 9293 1401",
    "sg:postcode":"6076",
    "sg:province":"WA",
    "sg:tags":[
        "turner",
        "wood"
    ],
    "wof:name":"Turnit",
    "wof:placetype":"venue"
},
  "geometry": {"coordinates":[116.11528015099999,-31.9498462677],"type":"Point"}
}