{
  "type": "Feature",
  "properties": {
    "addr:full":"38 Bourke St Wagga Wagga NSW 2650",
    "addr:housenumber":"38",
    "addr:postcode":"2650",
    "addr:street":"Bourke St",
    "iso:country":"AU",
    "sg:address":"38 Bourke St",
    "sg:city":"Wagga Wagga",
    "sg:classifiers":[
        {
            "category":"Shopping",
            "subcategory":"Pets & Pet Supplies",
            "type":"Retail Goods"
        }
    ],
    "sg:phone":"+61 2 6925 6002",
    "sg:postcode":"2650",
    "sg:province":"NSW",
    "sg:tags":[
        "food"
    ],
    "wof:name":"Amanda's Grooming Parlour",
    "wof:placetype":"venue"
},
  "geometry": {"coordinates":[147.35409545900001,-35.1267089844],"type":"Point"}
}