{
  "type": "Feature",
  "properties": {
    "addr:full":"105 Burpengary Rd Burpengary QLD 4505",
    "addr:housenumber":"105",
    "addr:postcode":"4505",
    "addr:street":"Burpengary Rd",
    "iso:country":"AU",
    "sg:address":"105 Burpengary Rd",
    "sg:city":"Burpengary",
    "sg:classifiers":[
        {
            "category":"Utilities",
            "subcategory":"Electric",
            "type":"Services"
        }
    ],
    "sg:phone":"+61 418 155 632",
    "sg:postcode":"4505",
    "sg:province":"QLD",
    "sg:tags":[
        "electrical",
        "contractor"
    ],
    "wof:name":"P K Electrical",
    "wof:placetype":"venue"
},
  "geometry": {"coordinates":[152.95449829099999,-27.1721763611],"type":"Point"}
}