{
  "type": "Feature",
  "properties": {
    "iso:country":"AU",
    "sg:address":"54 Cormack Rd",
    "sg:city":"Wingfield",
    "sg:classifiers":[
        {
            "category":"Wholesale",
            "subcategory":"Machinery & Supplies",
            "type":"Manufacturing & Wholesale Goods"
        }
    ],
    "sg:phone":"+61 8 8244 6804",
    "sg:postcode":"5013",
    "sg:province":"SA",
    "sg:tags":[
        "equipment",
        "system",
        "elevating",
        "conveying"
    ],
    "wof:name":"Diamond Conveyers",
    "wof:placetype":"venue"
},
  "geometry": {"coordinates":[138.56756591800001,-34.8402366638],"type":"Point"}
}