{
  "type": "Feature",
  "properties": {
    "addr:full":"Cnr Old Geelong & Heath&#039;s Rd Hoppers Crossing VIC 3029",
    "addr:postcode":"3029",
    "addr:street":"Cnr Old;S Rd",
    "iso:country":"AU",
    "sg:address":"Cnr Old Geelong & Heath&#039;s Rd",
    "sg:city":"Hoppers Crossing",
    "sg:classifiers":[
        {
            "category":"Food & Beverages",
            "subcategory":"Groceries & Convenience Stores",
            "type":"Retail Goods"
        }
    ],
    "sg:phone":"+61 3 9748 8034",
    "sg:postcode":"3029",
    "sg:province":"VIC",
    "wof:name":"Quix Food Stores",
    "wof:placetype":"venue"
},
  "geometry": {"coordinates":[144.76507599999999,-37.883202],"type":"Point"}
}