{
  "type": "Feature",
  "properties": {
    "iso:country":"AU",
    "sg:address":"207 Harbour Drv",
    "sg:city":"Coffs Harbour",
    "sg:classifiers":[
        {
            "category":"Social Services",
            "subcategory":"Child Care",
            "type":"Services"
        }
    ],
    "sg:phone":"+61 2 6652 6620",
    "sg:postcode":"2450",
    "sg:province":"NSW",
    "wof:name":"Happy Days Pre-School & Long Day Care Centre",
    "wof:placetype":"venue"
},
  "geometry": {"coordinates":[153.120041,-30.300232],"type":"Point"}
}