{
  "type": "Feature",
  "properties": {
    "iso:country":"AU",
    "sg:address":"115 Oak St",
    "sg:city":"Barcaldine",
    "sg:classifiers":[
        {
            "category":"Cafe",
            "type":"Food & Drink"
        }
    ],
    "sg:phone":"+61 7 4651 6211",
    "sg:postcode":"4725",
    "sg:province":"QLD",
    "wof:name":"Base Camp Cafe",
    "wof:placetype":"venue"
},
  "geometry": {"coordinates":[145.28303500000001,-23.552086],"type":"Point"}
}