{
  "type": "Feature",
  "properties": {
    "addr:full":"34A Percy St Portland VIC 3305",
    "addr:housenumber":"34a",
    "addr:postcode":"3305",
    "addr:street":"Percy St",
    "iso:country":"AU",
    "sg:address":"34A Percy St",
    "sg:city":"Portland",
    "sg:classifiers":[
        {
            "category":"Personal",
            "subcategory":"Massage",
            "type":"Services"
        }
    ],
    "sg:phone":"+61 3 5523 5844",
    "sg:postcode":"3305",
    "sg:province":"VIC",
    "sg:tags":[
        "therapy"
    ],
    "wof:name":"Johnson Susanne",
    "wof:placetype":"venue"
},
  "geometry": {"coordinates":[141.603759766,-38.3491096497],"type":"Point"}
}