{
  "type": "Feature",
  "properties": {
    "addr:full":"92-96 O'Sullivan Beach Rd Lonsdale SA 5160",
    "addr:housenumber":"92-96",
    "addr:postcode":"5160",
    "addr:street":"O'Sullivan Beach Rd",
    "iso:country":"AU",
    "sg:address":"92-96 O'Sullivan Beach Rd",
    "sg:city":"Lonsdale",
    "sg:classifiers":[
        {
            "category":"Home & Garden",
            "subcategory":"Building Materials",
            "type":"Retail Goods"
        }
    ],
    "sg:phone":"+61 8 8384 7191",
    "sg:postcode":"5160",
    "sg:province":"SA",
    "sg:tags":[
        "supply"
    ],
    "wof:name":"Southern Timber & Building Supply Pty Ltd",
    "wof:placetype":"venue"
},
  "geometry": {"coordinates":[138.50384521500001,-35.1168632507],"type":"Point"}
}