{
  "type": "Feature",
  "properties": {
    "iso:country":"AU",
    "sg:address":"252 Woronora Rd",
    "sg:city":"Engadine",
    "sg:classifiers":[
        {
            "category":"Social Services",
            "subcategory":"Child Care",
            "type":"Services"
        }
    ],
    "sg:phone":"+61 2 9548 2332",
    "sg:postcode":"2233",
    "sg:province":"NSW",
    "wof:name":"Engadine T.L.C. Childcare Centre",
    "wof:placetype":"venue"
},
  "geometry": {"coordinates":[151.00668335,-34.0686225891],"type":"Point"}
}