{
  "type": "Feature",
  "properties": {
    "iso:country":"AU",
    "sg:address":"11 George St",
    "sg:city":"Cambooya",
    "sg:classifiers":[
        {
            "category":"Retail",
            "subcategory":"Storage",
            "type":"Services"
        }
    ],
    "sg:phone":"+61 7 4696 1278",
    "sg:postcode":"4358",
    "sg:province":"QLD",
    "sg:tags":[
        "removal",
        "furniture"
    ],
    "wof:name":"Burgess Removals",
    "wof:placetype":"venue"
},
  "geometry": {"coordinates":[151.87162799999999,-27.706726],"type":"Point"}
}