{
  "type": "Feature",
  "properties": {
    "addr:full":"2441 Frankston-Flinders Rd Hastings VIC 3915",
    "addr:housenumber":"2441",
    "addr:postcode":"3915",
    "addr:street":"Frankston-Flinders Rd",
    "iso:country":"AU",
    "sg:address":"2441 Frankston-Flinders Rd",
    "sg:city":"Hastings",
    "sg:classifiers":[
        {
            "category":"Wholesale",
            "subcategory":"Machinery & Supplies",
            "type":"Manufacturing & Wholesale Goods"
        }
    ],
    "sg:phone":"+61 3 5979 4375",
    "sg:postcode":"3915",
    "sg:province":"VIC",
    "sg:tags":[
        "bearing",
        "bushing"
    ],
    "wof:name":"Consolidated Bearings",
    "wof:placetype":"venue"
},
  "geometry": {"coordinates":[145.18359375,-38.2879943848],"type":"Point"}
}