{
  "type": "Feature",
  "properties": {
    "iso:country":"AU",
    "sg:address":"2 Strzelecki Crs",
    "sg:city":"Narrabundah",
    "sg:classifiers":[
        {
            "category":"Utilities",
            "subcategory":"Water",
            "type":"Services"
        }
    ],
    "sg:phone":"+61 2 6295 8514",
    "sg:postcode":"2604",
    "sg:province":"ACT",
    "sg:tags":[
        "hot",
        "system"
    ],
    "wof:name":"A.D. Dorman Electrical",
    "wof:placetype":"venue"
},
  "geometry": {"coordinates":[149.14549255399999,-35.3285255432],"type":"Point"}
}