{
  "type": "Feature",
  "properties": {
    "iso:country":"AU",
    "sg:address":"Shop 97 Belmont Forum Shopping Centre, Belmont Ave",
    "sg:city":"Belmont",
    "sg:classifiers":[
        {
            "category":"Shopping",
            "subcategory":"Clothing, Apparel, & Fashions",
            "type":"Retail Goods"
        }
    ],
    "sg:phone":"+61 8 9277 7861",
    "sg:postcode":"6104",
    "sg:province":"WA",
    "sg:tags":[
        "jean"
    ],
    "wof:name":"Westco Jeans Pty Ltd",
    "wof:placetype":"venue"
},
  "geometry": {"coordinates":[115.91805267300001,-31.9526023865],"type":"Point"}
}