{
  "type": "Feature",
  "properties": {
    "addr:full":"75 Serviceton Ave Inala QLD 4077",
    "addr:housenumber":"75",
    "addr:postcode":"4077",
    "addr:street":"Serviceton Ave Inala",
    "iso:country":"AU",
    "sg:address":"75 Serviceton Ave",
    "sg:city":"Inala",
    "sg:classifiers":[
        {
            "category":"Health Services",
            "subcategory":"Dentist",
            "type":"Services"
        }
    ],
    "sg:phone":"+61 7 3372 1738",
    "sg:postcode":"4077",
    "sg:province":"QLD",
    "wof:name":"Full Smile Dental",
    "wof:placetype":"venue"
},
  "geometry": {"coordinates":[152.97569274899999,-27.5934486389],"type":"Point"}
}