{
  "type": "Feature",
  "properties": {
    "addr:full":"67 Jetty Rd Brighton SA 5048",
    "addr:housenumber":"67",
    "addr:postcode":"5048",
    "addr:street":"Jetty Rd",
    "iso:country":"AU",
    "sg:address":"67 Jetty Rd",
    "sg:city":"Brighton",
    "sg:classifiers":[
        {
            "category":"Shopping",
            "subcategory":"Jewelry",
            "type":"Retail Goods"
        }
    ],
    "sg:phone":"+61 8 8296 5199",
    "sg:postcode":"5048",
    "sg:province":"SA",
    "sg:tags":[
        "fashion",
        "jewellery"
    ],
    "wof:name":"Joli",
    "wof:placetype":"venue"
},
  "geometry": {"coordinates":[138.51586900000001,-35.017406],"type":"Point"}
}