{
  "type": "Feature",
  "properties": {
    "addr:full":"Shp 4/ 165 Baroona Rd Rosalie QLD 4064",
    "addr:housenumber":"/ 165",
    "addr:postcode":"4064",
    "addr:street":"Baroona Rd",
    "iso:country":"AU",
    "sg:address":"Shp 4/ 165 Baroona Rd",
    "sg:city":"Rosalie",
    "sg:classifiers":[
        {
            "category":"Fast Food",
            "type":"Food & Drink"
        }
    ],
    "sg:phone":"+61 7 3217 6511",
    "sg:postcode":"4064",
    "sg:province":"QLD",
    "sg:tags":[
        "away",
        "take"
    ],
    "wof:name":"Fish Lovers",
    "wof:placetype":"venue"
},
  "geometry": {"coordinates":[152.99681091299999,-27.4660263062],"type":"Point"}
}