{
  "type": "Feature",
  "properties": {
    "addr:full":"3 Packard St Larrakeyah NT 0820",
    "addr:housenumber":"3",
    "addr:postcode":"nt 0820",
    "addr:street":"Packard St",
    "iso:country":"AU",
    "sg:address":"3 Packard St",
    "sg:city":"Larrakeyah",
    "sg:classifiers":[
        {
            "category":"Education",
            "subcategory":"School",
            "type":"Public Place"
        }
    ],
    "sg:phone":"+61 8 8981 9091",
    "sg:postcode":"0820",
    "sg:province":"NT",
    "sg:tags":[
        "state",
        "except",
        "nsw"
    ],
    "wof:name":"Larrakeyah Pre-School",
    "wof:placetype":"venue"
},
  "geometry": {"coordinates":[130.829833984,-12.458445549],"type":"Point"}
}