{
  "type": "Feature",
  "properties": {
    "iso:country":"AU",
    "sg:address":"Shop 5 Ackers St",
    "sg:city":"Hermit Park",
    "sg:classifiers":[
        {
            "category":"Personal",
            "subcategory":"Beauty Salon",
            "type":"Services"
        }
    ],
    "sg:phone":"+61 7 4772 3821",
    "sg:postcode":"4812",
    "sg:province":"QLD",
    "wof:name":"In Touch Beauty",
    "wof:placetype":"venue"
},
  "geometry": {"coordinates":[146.800995,-19.277542],"type":"Point"}
}