{
  "type": "Feature",
  "properties": {
    "addr:full":"Ground Fl, CHR House 224 Victoria St Mackay QLD 4740",
    "addr:housenumber":"224",
    "addr:postcode":"4740",
    "addr:street":"Victoria St",
    "iso:country":"AU",
    "sg:address":"Ground Fl, CHR House 224 Victoria St",
    "sg:city":"Mackay",
    "sg:classifiers":[
        {
            "category":"Professional",
            "subcategory":"Employment Agencies",
            "type":"Services"
        }
    ],
    "sg:phone":"+61 7 4969 1111",
    "sg:postcode":"4740",
    "sg:province":"QLD",
    "wof:name":"CHR",
    "wof:placetype":"venue"
},
  "geometry": {"coordinates":[149.18012999999999,-21.140276],"type":"Point"}
}