{
  "type": "Feature",
  "properties": {
    "addr:full":"Williamstown Rd Port Melbourne VIC 3207",
    "addr:postcode":"3207",
    "addr:street":"Williamstown Rd",
    "iso:country":"AU",
    "sg:address":"Williamstown Rd",
    "sg:city":"Port Melbourne",
    "sg:classifiers":[
        {
            "category":"Professional",
            "subcategory":"Detective & Security Services",
            "type":"Services"
        }
    ],
    "sg:phone":"+61 3 9646 0064",
    "sg:postcode":"3207",
    "sg:province":"VIC",
    "sg:tags":[
        "shuttering"
    ],
    "wof:name":"Abel Shutter Service",
    "wof:placetype":"venue"
},
  "geometry": {"coordinates":[144.92358400000001,-37.835239],"type":"Point"}
}