{
  "type": "Feature",
  "properties": {
    "addr:full":"72- 76 Westgarth St Fitzroy VIC 3065",
    "addr:housenumber":"76",
    "addr:postcode":"3065",
    "addr:street":"Westgarth St",
    "iso:country":"AU",
    "sg:address":"72- 76 Westgarth St",
    "sg:city":"Fitzroy",
    "sg:classifiers":[
        {
            "category":"Farming",
            "subcategory":"Orchard",
            "type":"Manufacturing & Wholesale Goods"
        }
    ],
    "sg:phone":"+61 3 9486 9477",
    "sg:postcode":"3065",
    "sg:province":"VIC",
    "sg:tags":[
        "wholesaler",
        "jean",
        "mfrs"
    ],
    "wof:name":"Nobody Pty Ltd",
    "wof:placetype":"venue"
},
  "geometry": {"coordinates":[144.97810363799999,-37.7947349548],"type":"Point"}
}