{
  "type": "Feature",
  "properties": {
    "addr:full":"3 / 99 Orlando St Hampton VIC 3188",
    "addr:housenumber":"/ 99",
    "addr:postcode":"3188",
    "addr:street":"Orlando St",
    "iso:country":"AU",
    "sg:address":"3 / 99 Orlando St",
    "sg:city":"Hampton",
    "sg:classifiers":[
        {
            "category":"Retail",
            "subcategory":"Repair Shop",
            "type":"Services"
        }
    ],
    "sg:phone":"+61 3 9521 0525",
    "sg:postcode":"3188",
    "sg:province":"VIC",
    "sg:tags":[
        "leadlights"
    ],
    "wof:name":"Hampton Leadlights",
    "wof:placetype":"venue"
},
  "geometry": {"coordinates":[144.99588012699999,-37.9349250793],"type":"Point"}
}