{
  "type": "Feature",
  "properties": {
    "addr:full":"48 Coolabah Rd Dapto NSW 2530",
    "addr:housenumber":"48",
    "addr:postcode":"2530",
    "addr:street":"Coolabah Rd",
    "iso:country":"AU",
    "sg:address":"48 Coolabah Rd",
    "sg:city":"Dapto",
    "sg:classifiers":[
        {
            "category":"Building & Trades",
            "subcategory":"Pest Control",
            "type":"Services"
        }
    ],
    "sg:phone":"+61 427 611 754",
    "sg:postcode":"2530",
    "sg:province":"NSW",
    "wof:name":"Keira Pest Control",
    "wof:placetype":"venue"
},
  "geometry": {"coordinates":[150.801712036,-34.4879112244],"type":"Point"}
}