{
  "type": "Feature",
  "properties": {
    "addr:full":"Level 1/ 40 Lord St Botany NSW 2019",
    "addr:housenumber":"/ 40",
    "addr:postcode":"2019",
    "addr:street":"Lord St",
    "iso:country":"AU",
    "sg:address":"Level 1/ 40 Lord St",
    "sg:city":"Botany",
    "sg:classifiers":[
        {
            "category":"Utilities",
            "subcategory":"Sewage",
            "type":"Services"
        }
    ],
    "sg:phone":"+61 2 9666 1776",
    "sg:postcode":"2019",
    "sg:province":"NSW",
    "sg:tags":[
        "electricity",
        "retailer"
    ],
    "wof:name":"Powerdirect",
    "wof:placetype":"venue"
},
  "geometry": {"coordinates":[151.19999694800001,-33.9394035339],"type":"Point"}
}