{
  "type": "Feature",
  "properties": {
    "addr:full":"1/ 251 Balcatta Rd Balcatta WA 6021",
    "addr:housenumber":"/ 251",
    "addr:postcode":"6021",
    "addr:street":"Balcatta Rd",
    "iso:country":"AU",
    "sg:address":"1/ 251 Balcatta Rd",
    "sg:city":"Balcatta",
    "sg:classifiers":[
        {
            "category":"Professional",
            "subcategory":"Employment Agencies",
            "type":"Services"
        }
    ],
    "sg:phone":"+61 8 9240 9999",
    "sg:postcode":"6021",
    "sg:province":"WA",
    "wof:name":"Stirling Skills Training Inc.",
    "wof:placetype":"venue"
},
  "geometry": {"coordinates":[115.823722839,-31.8634357452],"type":"Point"}
}