{
  "type": "Feature",
  "properties": {
    "addr:full":"20 Barry Ave Mortdale NSW 2223",
    "addr:housenumber":"20",
    "addr:postcode":"2223",
    "addr:street":"Barry Ave",
    "iso:country":"AU",
    "sg:address":"20 Barry Ave",
    "sg:city":"Mortdale",
    "sg:classifiers":[
        {
            "category":"Wholesale",
            "subcategory":"Construction Materials",
            "type":"Manufacturing & Wholesale Goods"
        }
    ],
    "sg:phone":"+61 2 9570 7322",
    "sg:postcode":"2223",
    "sg:province":"NSW",
    "sg:tags":[
        "wholesaler",
        "lighting",
        "mfrs",
        "accessory"
    ],
    "wof:name":"Lighting Components Pty Ltd",
    "wof:placetype":"venue"
},
  "geometry": {"coordinates":[151.06967163100001,-33.966884613],"type":"Point"}
}