{
  "type": "Feature",
  "properties": {
    "addr:full":"Norfolk House 62 Victoria St Victor Harbor SA 5211",
    "addr:housenumber":"62",
    "addr:postcode":"5211",
    "addr:street":"Victoria St",
    "iso:country":"AU",
    "sg:address":"Norfolk House 62 Victoria St",
    "sg:city":"Victor Harbor",
    "sg:classifiers":[
        {
            "category":"Health Services",
            "subcategory":"Doctor",
            "type":"Services"
        }
    ],
    "sg:phone":"+61 8 8552 3900",
    "sg:postcode":"5211",
    "sg:province":"SA",
    "sg:tags":[
        "medical",
        "practitioner"
    ],
    "wof:name":"Norton S L",
    "wof:placetype":"venue"
},
  "geometry": {"coordinates":[138.61744689899999,-35.5571784973],"type":"Point"}
}