{
  "type": "Feature",
  "properties": {
    "addr:full":"583 Fisher St Broken Hill NSW 2880",
    "addr:housenumber":"583",
    "addr:postcode":"2880",
    "addr:street":"Fisher St",
    "iso:country":"AU",
    "sg:address":"583 Fisher St",
    "sg:city":"Broken Hill",
    "sg:classifiers":[
        {
            "category":"Professional",
            "subcategory":"Accounting & Tax Preparation",
            "type":"Services"
        }
    ],
    "sg:phone":"+61 8 8087 3087",
    "sg:postcode":"2880",
    "sg:province":"NSW",
    "sg:tags":[
        "accountant",
        "auditor"
    ],
    "wof:name":"Martin Colin J",
    "wof:placetype":"venue"
},
  "geometry": {"coordinates":[141.46998596200001,-31.9390258789],"type":"Point"}
}