{
  "type": "Feature",
  "properties": {
    "iso:country":"AU",
    "sg:address":"290 South Gippsland Hwy",
    "sg:city":"Cranbourne",
    "sg:classifiers":[
        {
            "category":"Manufacturing",
            "subcategory":"Motor Vehicles & Parts",
            "type":"Manufacturing & Wholesale Goods"
        }
    ],
    "sg:phone":"+61 3 9556 8735",
    "sg:postcode":"3977",
    "sg:province":"VIC",
    "sg:tags":[
        "replacement"
    ],
    "wof:name":"Cranbourne Auto Market Daihatsu",
    "wof:placetype":"venue"
},
  "geometry": {"coordinates":[145.28213500999999,-38.0942497253],"type":"Point"}
}