{
  "type": "Feature",
  "properties": {
    "iso:country":"AU",
    "sg:address":"20 Evan St",
    "sg:city":"Penrith",
    "sg:classifiers":[
        {
            "category":"Health Services",
            "subcategory":"Dentist",
            "type":"Services"
        }
    ],
    "sg:phone":"+61 2 4721 2818",
    "sg:postcode":"2750",
    "sg:province":"NSW",
    "wof:name":"Perri Joe & Stanton Belinda",
    "wof:placetype":"venue"
},
  "geometry": {"coordinates":[150.70240783700001,-33.7555961609],"type":"Point"}
}