{
  "type": "Feature",
  "properties": {
    "iso:country":"AU",
    "sg:address":"3/ 127 Blair St",
    "sg:city":"North Bondi",
    "sg:classifiers":[
        {
            "category":"Professional",
            "subcategory":"Art Services",
            "type":"Services"
        }
    ],
    "sg:phone":"+61 403 769 901",
    "sg:postcode":"2026",
    "sg:province":"NSW",
    "sg:tags":[
        "graphic",
        "designer"
    ],
    "wof:name":"Soul Creative",
    "wof:placetype":"venue"
},
  "geometry": {"coordinates":[151.28123474099999,-33.8859558105],"type":"Point"}
}