{
  "type": "Feature",
  "properties": {
    "iso:country":"AU",
    "sg:address":"135 - 137 Hoskins St",
    "sg:city":"Temora",
    "sg:classifiers":[
        {
            "category":"Autos & Motor Vehicles",
            "subcategory":"Auto Supplies",
            "type":"Retail Goods"
        }
    ],
    "sg:phone":"+61 2 6977 2092",
    "sg:postcode":"2666",
    "sg:province":"NSW",
    "sg:tags":[
        "battery",
        "automotive"
    ],
    "wof:name":"Beaurepaires",
    "wof:placetype":"venue"
},
  "geometry": {"coordinates":[147.53338623100001,-34.4462814331],"type":"Point"}
}