{
  "type": "Feature",
  "properties": {
    "addr:full":"22 St George St Willunga SA 5172",
    "addr:housenumber":"22",
    "addr:postcode":"5172",
    "addr:street":"St George St",
    "iso:country":"AU",
    "sg:address":"22 St George St",
    "sg:city":"Willunga",
    "sg:classifiers":[
        {
            "category":"Retail",
            "subcategory":"Veterinary Services",
            "type":"Services"
        }
    ],
    "sg:phone":"+61 8 8556 2040",
    "sg:postcode":"5172",
    "sg:province":"SA",
    "sg:tags":[
        "surgeon"
    ],
    "wof:name":"Embryo Transfer Services Of SA",
    "wof:placetype":"venue"
},
  "geometry": {"coordinates":[138.558135986,-35.2781715393],"type":"Point"}
}