{
  "type": "Feature",
  "properties": {
    "addr:full":"366 Reservoir Rd Lavington NSW 2641",
    "addr:housenumber":"366",
    "addr:postcode":"2641",
    "addr:street":"Reservoir Rd",
    "iso:country":"AU",
    "sg:address":"366 Reservoir Rd",
    "sg:city":"Lavington",
    "sg:classifiers":[
        {
            "category":"Retail",
            "subcategory":"Auto Repair",
            "type":"Services"
        }
    ],
    "sg:phone":"+61 418 203 364",
    "sg:postcode":"2641",
    "sg:province":"NSW",
    "sg:tags":[
        "repairer",
        "motor",
        "engineer"
    ],
    "wof:name":"Mobile Mechanics",
    "wof:placetype":"venue"
},
  "geometry": {"coordinates":[146.91993713400001,-36.0462722778],"type":"Point"}
}