{
  "type": "Feature",
  "properties": {
    "addr:full":"8 Rafferty Rd Mandurah WA 6210",
    "addr:housenumber":"8",
    "addr:postcode":"6210",
    "addr:street":"Rafferty Rd",
    "iso:country":"AU",
    "sg:address":"8 Rafferty Rd",
    "sg:city":"Mandurah",
    "sg:classifiers":[
        {
            "category":"Retail",
            "subcategory":"Auto Repair",
            "type":"Services"
        }
    ],
    "sg:phone":"+61 8 9535 6061",
    "sg:postcode":"6210",
    "sg:province":"WA",
    "sg:tags":[
        "repairer",
        "motor",
        "engineer"
    ],
    "wof:name":"Peter Dutton Automotive Services",
    "wof:placetype":"venue"
},
  "geometry": {"coordinates":[115.74498699999999,-32.517456],"type":"Point"}
}