{
  "type": "Feature",
  "properties": {
    "iso:country":"AU",
    "sg:address":"8 Milne Rd",
    "sg:city":"Park Orchards",
    "sg:classifiers":[
        {
            "category":"Professional",
            "subcategory":"Research",
            "type":"Services"
        }
    ],
    "sg:phone":"+61 3 9879 0765",
    "sg:postcode":"3114",
    "sg:province":"VIC",
    "sg:tags":[
        "actuary"
    ],
    "wof:name":"Stott Phil Consulting Pty Ltd",
    "wof:placetype":"venue"
},
  "geometry": {"coordinates":[145.231933594,-37.7840270996],"type":"Point"}
}