{
  "type": "Feature",
  "properties": {
    "addr:full":"32 Bantry Rd Frenchs Forest NSW 2086",
    "addr:housenumber":"32",
    "addr:postcode":"2086",
    "addr:street":"Bantry Rd",
    "iso:country":"AU",
    "sg:address":"32 Bantry Rd",
    "sg:city":"Frenchs Forest",
    "sg:classifiers":[
        {
            "category":"Real Estate",
            "subcategory":"Real Estate Agent",
            "type":"Services"
        }
    ],
    "sg:phone":"+61 2 9453 3477",
    "sg:postcode":"2086",
    "sg:province":"NSW",
    "wof:name":"Raine & Horne Frenchs Forest",
    "wof:placetype":"venue"
},
  "geometry": {"coordinates":[151.23309326200001,-33.7512054443],"type":"Point"}
}