{
  "type": "Feature",
  "properties": {
    "addr:full":"Unit 4/ 12 Arcadia St Penshurst NSW 2222",
    "addr:housenumber":"12",
    "addr:postcode":"2222",
    "addr:street":"Arcadia St",
    "iso:country":"AU",
    "sg:address":"Unit 4/ 12 Arcadia St",
    "sg:city":"Penshurst",
    "sg:classifiers":[
        {
            "category":"Building & Trades",
            "subcategory":"Construction",
            "type":"Services"
        }
    ],
    "sg:phone":"+61 401 867 338",
    "sg:postcode":"2222",
    "sg:province":"NSW",
    "sg:tags":[
        "industrial",
        "commercial",
        "air conditioning"
    ],
    "wof:name":"Alex Air Conditioning",
    "wof:placetype":"venue"
},
  "geometry": {"coordinates":[151.08824157699999,-33.9625244141],"type":"Point"}
}