{
  "type": "Feature",
  "properties": {
    "iso:country":"AU",
    "sg:address":"27- 29 Malvern St",
    "sg:city":"Bayswater",
    "sg:classifiers":[
        {
            "category":"Wholesale",
            "subcategory":"Auto Parts",
            "type":"Manufacturing & Wholesale Goods"
        }
    ],
    "sg:phone":"+61 3 9729 7566",
    "sg:postcode":"3153",
    "sg:province":"VIC",
    "sg:tags":[
        "recyclers"
    ],
    "wof:name":"Hall 4 x 4 Salvage",
    "wof:placetype":"venue"
},
  "geometry": {"coordinates":[145.27456665,-37.8430557251],"type":"Point"}
}