{
  "type": "Feature",
  "properties": {
    "iso:country":"AU",
    "sg:address":"Basil Brown Drv",
    "sg:city":"Tamworth",
    "sg:classifiers":[
        {
            "category":"Farming",
            "subcategory":"Poultry Farm",
            "type":"Manufacturing & Wholesale Goods"
        }
    ],
    "sg:phone":"+61 2 6764 9200",
    "sg:postcode":"2340",
    "sg:province":"NSW",
    "sg:tags":[
        "farmer"
    ],
    "wof:name":"Baiada Poultry Pty Limited",
    "wof:placetype":"venue"
},
  "geometry": {"coordinates":[150.849685669,-31.0864658356],"type":"Point"}
}