{
  "type": "Feature",
  "properties": {
    "addr:full":"Greenwell Point Rd Nowra NSW 2540",
    "addr:postcode":"2540",
    "addr:street":"Greenwell;Rd",
    "iso:country":"AU",
    "sg:address":"Greenwell Point Rd",
    "sg:city":"Nowra",
    "sg:classifiers":[
        {
            "category":"Restaurant",
            "type":"Food & Drink"
        }
    ],
    "sg:phone":"+61 2 4422 0388",
    "sg:postcode":"2540",
    "sg:province":"NSW",
    "wof:name":"Annas Family Bistro",
    "wof:placetype":"venue"
},
  "geometry": {"coordinates":[150.82716369600001,-35.0167198181],"type":"Point"}
}