{
  "type": "Feature",
  "properties": {
    "addr:full":"Gwalia Rd Northampton WA 6535",
    "addr:postcode":"6535",
    "addr:street":"Gwalia Rd",
    "iso:country":"AU",
    "sg:address":"Gwalia Rd",
    "sg:city":"Northampton",
    "sg:classifiers":[
        {
            "category":"Professional",
            "type":"Services"
        }
    ],
    "sg:phone":"+61 8 9934 1136",
    "sg:postcode":"6535",
    "sg:province":"WA",
    "sg:tags":[
        "transport"
    ],
    "wof:name":"Northampton Road Transport",
    "wof:placetype":"venue"
},
  "geometry": {"coordinates":[114.629867554,-28.3565998077],"type":"Point"}
}