{
  "type": "Feature",
  "properties": {
    "addr:full":"260 William St Northbridge WA 6003",
    "addr:housenumber":"260",
    "addr:postcode":"6003",
    "addr:street":"William St",
    "iso:country":"AU",
    "sg:address":"260 William St",
    "sg:city":"Northbridge",
    "sg:classifiers":[
        {
            "category":"Personal",
            "subcategory":"Beauty Salon",
            "type":"Services"
        }
    ],
    "sg:phone":"+61 8 9328 3298",
    "sg:postcode":"6003",
    "sg:province":"WA",
    "sg:tags":[
        "hairdresser"
    ],
    "wof:name":"Rosan Hair & Beauty",
    "wof:placetype":"venue"
},
  "geometry": {"coordinates":[115.860298157,-31.9477291107],"type":"Point"}
}