{
  "type": "Feature",
  "properties": {
    "addr:full":"Units 1 & 4, 22 Junction Rd West Burleigh QLD 4219",
    "addr:housenumber":"units 1 &;22",
    "addr:postcode":"4219",
    "addr:street":"4;Junction Rd",
    "iso:country":"AU",
    "sg:address":"Units 1 & 4, 22 Junction Rd",
    "sg:city":"West Burleigh",
    "sg:classifiers":[
        {
            "category":"Building & Trades",
            "subcategory":"Construction",
            "type":"Services"
        }
    ],
    "sg:phone":"+61 7 5593 6834",
    "sg:postcode":"4219",
    "sg:province":"QLD",
    "sg:tags":[
        "welding"
    ],
    "wof:name":"Ironstar",
    "wof:placetype":"venue"
},
  "geometry": {"coordinates":[153.425415039,-28.1047534943],"type":"Point"}
}