{
  "type": "Feature",
  "properties": {
    "iso:country":"AU",
    "sg:address":"Hillview Rd",
    "sg:city":"Kingswood",
    "sg:classifiers":[
        {
            "category":"Education",
            "subcategory":"School",
            "type":"Public Place"
        }
    ],
    "sg:phone":"+61 8 8271 2227",
    "sg:postcode":"5062",
    "sg:province":"SA",
    "sg:tags":[
        "state",
        "except",
        "nsw"
    ],
    "wof:name":"Mitcham Primary",
    "wof:placetype":"venue"
},
  "geometry": {"coordinates":[138.61476135300001,-34.9716453552],"type":"Point"}
}