{
  "type": "Feature",
  "properties": {
    "addr:full":"410 Sheridan St Cairns QLD 4870",
    "addr:housenumber":"410",
    "addr:postcode":"4870",
    "addr:street":"Sheridan St",
    "iso:country":"AU",
    "sg:address":"410 Sheridan St",
    "sg:city":"Cairns",
    "sg:classifiers":[
        {
            "category":"Retail",
            "subcategory":"Auto Repair",
            "type":"Services"
        }
    ],
    "sg:phone":"+61 7 4053 1066",
    "sg:postcode":"4870",
    "sg:province":"QLD",
    "sg:tags":[
        "repairer",
        "motor",
        "engineer"
    ],
    "wof:name":"Cairns Brakes & Mechanical Services",
    "wof:placetype":"venue"
},
  "geometry": {"coordinates":[145.75508117699999,-16.8964519501],"type":"Point"}
}