{
  "type": "Feature",
  "properties": {
    "addr:full":"90 Dundas Rd High Wycombe WA 6057",
    "addr:housenumber":"90",
    "addr:postcode":"6057",
    "addr:street":"Dundas Rd",
    "iso:country":"AU",
    "sg:address":"90 Dundas Rd",
    "sg:city":"High Wycombe",
    "sg:classifiers":[
        {
            "category":"Farming",
            "subcategory":"Fish & Marine Products",
            "type":"Manufacturing & Wholesale Goods"
        }
    ],
    "sg:phone":"+61 8 9454 8546",
    "sg:postcode":"6057",
    "sg:province":"WA",
    "sg:tags":[
        "lead",
        "supply"
    ],
    "wof:name":"Boyce Western Glass",
    "wof:placetype":"venue"
},
  "geometry": {"coordinates":[115.990821838,-31.9405097961],"type":"Point"}
}