{
  "type": "Feature",
  "properties": {
    "addr:full":"189 Beaudesert Rd Moorooka QLD 4105",
    "addr:housenumber":"189",
    "addr:postcode":"4105",
    "addr:street":"Beaudesert Rd",
    "iso:country":"AU",
    "sg:address":"189 Beaudesert Rd",
    "sg:city":"Moorooka",
    "sg:classifiers":[
        {
            "category":"Banks & Credit Unions",
            "subcategory":"Investment Brokerage",
            "type":"Services"
        }
    ],
    "sg:phone":"+61 1800 642 730",
    "sg:postcode":"4105",
    "sg:province":"QLD",
    "wof:name":"Commonwealth Financial Planning",
    "wof:placetype":"venue"
},
  "geometry": {"coordinates":[153.02444457999999,-27.5325737],"type":"Point"}
}