{
  "type": "Feature",
  "properties": {
    "addr:full":"319-321 Liverpool Rd (Cnr Willee St) Enfield NSW 2136",
    "addr:housenumber":"319-321",
    "addr:postcode":"2136",
    "addr:street":"Liverpool Rd Cnr Willee St",
    "iso:country":"AU",
    "sg:address":"319-321 Liverpool Rd",
    "sg:city":"(Cnr Willee St) Enfield",
    "sg:classifiers":[
        {
            "category":"Food & Beverages",
            "subcategory":"Liquor & Beverages",
            "type":"Retail Goods"
        }
    ],
    "sg:phone":"+61 2 9745 2358",
    "sg:postcode":"2136",
    "sg:province":"NSW",
    "sg:tags":[
        "store"
    ],
    "wof:name":"Liquorstop",
    "wof:placetype":"venue"
},
  "geometry": {"coordinates":[151.09223938,-33.8867454529],"type":"Point"}
}