{
  "type": "Feature",
  "properties": {
    "addr:full":"49 Grant Ave Rose Park SA 5067",
    "addr:housenumber":"49",
    "addr:postcode":"5067",
    "addr:street":"Grant Ave Rose",
    "iso:country":"AU",
    "sg:address":"49 Grant Ave",
    "sg:city":"Rose Park",
    "sg:classifiers":[
        {
            "category":"Wholesale",
            "subcategory":"Fruits & Vegetables",
            "type":"Manufacturing & Wholesale Goods"
        }
    ],
    "sg:phone":"+61 8 8333 1666",
    "sg:postcode":"5067",
    "sg:province":"SA",
    "sg:tags":[
        "produce",
        "grain"
    ],
    "wof:name":"Ausfeed",
    "wof:placetype":"venue"
},
  "geometry": {"coordinates":[138.630096436,-34.9319152832],"type":"Point"}
}