{
  "type": "Feature",
  "properties": {
    "addr:full":"Shp 1/ 79 Main St Alstonville NSW 2477",
    "addr:housenumber":"/ 79",
    "addr:postcode":"2477",
    "addr:street":"Main St",
    "iso:country":"AU",
    "sg:address":"Shp 1/ 79 Main St",
    "sg:city":"Alstonville",
    "sg:classifiers":[
        {
            "category":"Cafe",
            "type":"Food & Drink"
        }
    ],
    "sg:phone":"+61 2 6628 5070",
    "sg:postcode":"2477",
    "sg:province":"NSW",
    "wof:name":"Alstonville Cafe Deli",
    "wof:placetype":"venue"
},
  "geometry": {"coordinates":[153.435913086,-28.8379993439],"type":"Point"}
}