{
  "type": "Feature",
  "properties": {
    "addr:full":"92 Wedge St Epping VIC 3076",
    "addr:housenumber":"92",
    "addr:postcode":"3076",
    "addr:street":"Wedge St",
    "iso:country":"AU",
    "sg:address":"92 Wedge St",
    "sg:city":"Epping",
    "sg:classifiers":[
        {
            "category":"Professional",
            "subcategory":"Printing & Photocopies",
            "type":"Services"
        }
    ],
    "sg:phone":"+61 3 9401 1955",
    "sg:postcode":"3076",
    "sg:province":"VIC",
    "sg:tags":[
        "photocopying"
    ],
    "wof:name":"Minuteman Press",
    "wof:placetype":"venue"
},
  "geometry": {"coordinates":[145.02171325699999,-37.6505317688],"type":"Point"}
}