{
  "type": "Feature",
  "properties": {
    "addr:full":"108 Holmes Rd Bendigo VIC 3550",
    "addr:housenumber":"108",
    "addr:postcode":"3550",
    "addr:street":"Holmes Rd",
    "iso:country":"AU",
    "sg:address":"108 Holmes Rd",
    "sg:city":"Bendigo",
    "sg:classifiers":[
        {
            "category":"Building & Trades",
            "subcategory":"Construction",
            "type":"Services"
        }
    ],
    "sg:phone":"+61 3 5442 2033",
    "sg:postcode":"3550",
    "sg:province":"VIC",
    "sg:tags":[
        "joinery"
    ],
    "wof:name":"Bendigo Kitchen Centre",
    "wof:placetype":"venue"
},
  "geometry": {"coordinates":[144.27415466299999,-36.7436485291],"type":"Point"}
}