{
  "type": "Feature",
  "properties": {
    "addr:full":"6 Davey St Mandurah WA 6210",
    "addr:housenumber":"6",
    "addr:postcode":"6210",
    "addr:street":"Davey St",
    "iso:country":"AU",
    "sg:address":"6 Davey St",
    "sg:city":"Mandurah",
    "sg:classifiers":[
        {
            "category":"Home & Garden",
            "subcategory":"Garden Supply",
            "type":"Retail Goods"
        }
    ],
    "sg:phone":"+61 8 9581 4415",
    "sg:postcode":"6210",
    "sg:province":"WA",
    "sg:tags":[
        "equipment"
    ],
    "wof:name":"Exotic Eden Nursery",
    "wof:placetype":"venue"
},
  "geometry": {"coordinates":[115.723099,-32.533596],"type":"Point"}
}