{
  "type": "Feature",
  "properties": {
    "addr:full":"7 Flinders Crt Mt Ommaney QLD 4074",
    "addr:housenumber":"7",
    "addr:postcode":"4074",
    "addr:street":"Flinders Crt Mt Ommaney",
    "iso:country":"AU",
    "sg:address":"7 Flinders Crt",
    "sg:city":"Mt Ommaney",
    "sg:classifiers":[
        {
            "category":"Real Estate",
            "subcategory":"Architect",
            "type":"Services"
        }
    ],
    "sg:phone":"+61 7 3376 8982",
    "sg:postcode":"4074",
    "sg:province":"QLD",
    "wof:name":"Orange, Rodney Architect",
    "wof:placetype":"venue"
},
  "geometry": {"coordinates":[152.94015502900001,-27.5453968048],"type":"Point"}
}