{
  "type": "Feature",
  "properties": {
    "addr:full":"The Full Moon Hotel 118 Eagle Tce Sandgate QLD 4017",
    "addr:housenumber":"118",
    "addr:postcode":"4017",
    "addr:street":"Eagle Tce",
    "iso:country":"AU",
    "sg:address":"The Full Moon Hotel 118",
    "sg:city":"Eagle Tce Sandgate",
    "sg:classifiers":[
        {
            "category":"Education",
            "subcategory":"Special Training",
            "type":"Public Place"
        }
    ],
    "sg:phone":"+61 7 3368 4942",
    "sg:postcode":"4017",
    "sg:province":"QLD",
    "sg:tags":[
        "development"
    ],
    "wof:name":"Ron Pollak",
    "wof:placetype":"venue"
},
  "geometry": {"coordinates":[153.073760986,-27.3209533691],"type":"Point"}
}