{
  "type": "Feature",
  "properties": {
    "iso:country":"AU",
    "sg:address":"Suite 306, 500 Centre Rd",
    "sg:city":"Bentleigh",
    "sg:classifiers":[
        {
            "category":"Education",
            "subcategory":"Special Training",
            "type":"Public Place"
        }
    ],
    "sg:phone":"+61 3 9570 9088",
    "sg:postcode":"3204",
    "sg:province":"VIC",
    "sg:tags":[
        "development"
    ],
    "wof:name":"1st Choice Appointments",
    "wof:placetype":"venue"
},
  "geometry": {"coordinates":[145.040817,-37.918831],"type":"Point"}
}