{
  "type": "Feature",
  "properties": {
    "iso:country":"AU",
    "sg:address":"Shop 4, The Jetty Welsby Pde",
    "sg:city":"Bribie Island",
    "sg:classifiers":[
        {
            "category":"Fast Food",
            "type":"Food & Drink"
        }
    ],
    "sg:phone":"+61 7 3408 1175",
    "sg:postcode":"4507",
    "sg:province":"QLD",
    "sg:tags":[
        "away",
        "take"
    ],
    "wof:name":"Golden Prawn Seafoods & Take Away",
    "wof:placetype":"venue"
},
  "geometry": {"coordinates":[153.11285400400001,-27.0225105286],"type":"Point"}
}