{
  "type": "Feature",
  "properties": {
    "addr:full":"18 Old Gympie Rd Yandina QLD 4561",
    "addr:housenumber":"18",
    "addr:postcode":"4561",
    "addr:street":"Old Gympie Rd",
    "iso:country":"AU",
    "sg:address":"18 Old Gympie Rd",
    "sg:city":"Yandina",
    "sg:classifiers":[
        {
            "category":"Health Services",
            "subcategory":"Health Practitioner",
            "type":"Services"
        }
    ],
    "sg:phone":"+61 7 5472 8838",
    "sg:postcode":"4561",
    "sg:province":"QLD",
    "sg:tags":[
        "naturopath"
    ],
    "wof:name":"Anna Husqee",
    "wof:placetype":"venue"
},
  "geometry": {"coordinates":[152.95530700699999,-26.5624656677],"type":"Point"}
}