{
  "type": "Feature",
  "properties": {
    "addr:full":"Level 2,Number 1 Transvaal Ave Double Bay NSW 2028",
    "addr:postcode":"2028",
    "addr:street":"Transvaal Ave",
    "iso:country":"AU",
    "sg:address":"Level 2,Number 1 Transvaal Ave",
    "sg:city":"Double Bay",
    "sg:classifiers":[
        {
            "category":"Real Estate",
            "subcategory":"Developer",
            "type":"Services"
        }
    ],
    "sg:phone":"+61 2 9362 3090",
    "sg:postcode":"2028",
    "sg:province":"NSW",
    "sg:tags":[
        "development"
    ],
    "wof:name":"Bamburgh Properties Pty Ltd",
    "wof:placetype":"venue"
},
  "geometry": {"coordinates":[151.243972778,-33.8765411377],"type":"Point"}
}