{
  "type": "Feature",
  "properties": {
    "addr:full":"9 Hallam St Charlestown NSW 2290",
    "addr:housenumber":"9",
    "addr:postcode":"2290",
    "addr:street":"Hallam St",
    "iso:country":"AU",
    "sg:address":"9 Hallam St",
    "sg:city":"Charlestown",
    "sg:classifiers":[
        {
            "category":"Education",
            "subcategory":"Dance Studio",
            "type":"Public Place"
        }
    ],
    "sg:phone":"+61 1800 643 277",
    "sg:postcode":"2290",
    "sg:province":"NSW",
    "sg:tags":[
        "venue",
        "tuition"
    ],
    "wof:name":"The Hunter Valley Square Dance Society Inc",
    "wof:placetype":"venue"
},
  "geometry": {"coordinates":[151.69981384299999,-32.975353241],"type":"Point"}
}