{
  "type": "Feature",
  "properties": {
    "addr:full":"42a Bridge St Richmond TAS 7025",
    "addr:housenumber":"42a",
    "addr:postcode":"7025",
    "addr:street":"Bridge St",
    "iso:country":"AU",
    "sg:address":"42a Bridge St",
    "sg:city":"Richmond",
    "sg:classifiers":[
        {
            "category":"Shopping",
            "subcategory":"Crafts & Fabrics",
            "type":"Retail Goods"
        }
    ],
    "sg:phone":"+61 3 6260 2493",
    "sg:postcode":"7025",
    "sg:province":"TAS",
    "sg:tags":[
        "merchant",
        "lace"
    ],
    "wof:name":"Ambrosial Grange The Lace Shop",
    "wof:placetype":"venue"
},
  "geometry": {"coordinates":[147.436645508,-42.7362480164],"type":"Point"}
}