{
  "type": "Feature",
  "properties": {
    "addr:full":"3 Drouin St Broadmeadows VIC 3047",
    "addr:housenumber":"3",
    "addr:postcode":"3047",
    "addr:street":"Drouin St",
    "iso:country":"AU",
    "sg:address":"3 Drouin St",
    "sg:city":"Broadmeadows",
    "sg:classifiers":[
        {
            "category":"Banks & Credit Unions",
            "subcategory":"Financial Services",
            "type":"Services"
        }
    ],
    "sg:phone":"+61 418 404 367",
    "sg:postcode":"3047",
    "sg:province":"VIC",
    "sg:tags":[
        "assistance",
        "roadside"
    ],
    "wof:name":"City & Country Towing Services",
    "wof:placetype":"venue"
},
  "geometry": {"coordinates":[144.934692383,-37.671295166],"type":"Point"}
}