{
  "type": "Feature",
  "properties": {
    "addr:full":"40 Penshurst St Penshurst NSW 2222",
    "addr:housenumber":"40",
    "addr:postcode":"2222",
    "addr:street":"Penshurst St",
    "iso:country":"AU",
    "sg:address":"40 Penshurst St",
    "sg:city":"Penshurst",
    "sg:classifiers":[
        {
            "category":"Retail",
            "subcategory":"Repair Shop",
            "type":"Services"
        }
    ],
    "sg:phone":"+61 2 9580 8692",
    "sg:postcode":"2222",
    "sg:province":"NSW",
    "sg:tags":[
        "mending",
        "clothing",
        "alteration"
    ],
    "wof:name":"Ladies & Gents Alterations",
    "wof:placetype":"venue"
},
  "geometry": {"coordinates":[151.088287353,-33.9649238586],"type":"Point"}
}