{
  "type": "Feature",
  "properties": {
    "addr:full":"20 Main St Blacktown NSW 2148",
    "addr:housenumber":"20",
    "addr:postcode":"2148",
    "addr:street":"Main St",
    "iso:country":"AU",
    "sg:address":"20 Main St",
    "sg:city":"Blacktown",
    "sg:classifiers":[
        {
            "category":"Fast Food",
            "type":"Food & Drink"
        }
    ],
    "sg:phone":"+61 2 9622 1452",
    "sg:postcode":"2148",
    "sg:province":"NSW",
    "sg:tags":[
        "away",
        "take"
    ],
    "wof:name":"Fill Em Up",
    "wof:placetype":"venue"
},
  "geometry": {"coordinates":[150.90745544399999,-33.7689971924],"type":"Point"}
}