{
  "type": "Feature",
  "properties": {
    "iso:country":"AU",
    "sg:address":"Unit 4/ 2 Shelley Rd",
    "sg:city":"Moruya North",
    "sg:classifiers":[
        {
            "category":"Building & Trades",
            "subcategory":"Construction",
            "type":"Services"
        }
    ],
    "sg:phone":"+61 2 4474 3300",
    "sg:postcode":"2537",
    "sg:province":"NSW",
    "sg:tags":[
        "joinery"
    ],
    "wof:name":"Glendale Kitchens",
    "wof:placetype":"venue"
},
  "geometry": {"coordinates":[150.07621765100001,-35.920501709],"type":"Point"}
}