{
  "type": "Feature",
  "properties": {
    "addr:full":"21 Wildwood Drv Bendigo VIC 3539",
    "addr:housenumber":"21",
    "addr:postcode":"3539",
    "addr:street":"Wildwood Drv",
    "iso:country":"AU",
    "sg:address":"21 Wildwood Drv",
    "sg:city":"Bendigo",
    "sg:classifiers":[
        {
            "category":"Building & Trades",
            "subcategory":"Construction",
            "type":"Services"
        }
    ],
    "sg:phone":"+61 418 507 354",
    "sg:postcode":"3539",
    "sg:province":"VIC",
    "sg:tags":[
        "contractor"
    ],
    "wof:name":"Dale Hodges",
    "wof:placetype":"venue"
},
  "geometry": {"coordinates":[144.318558,-36.771969],"type":"Point"}
}