{
  "type": "Feature",
  "properties": {
    "addr:full":"106 Charles St Moonah TAS 7009",
    "addr:housenumber":"106",
    "addr:postcode":"7009",
    "addr:street":"Charles St",
    "iso:country":"AU",
    "sg:address":"106 Charles St",
    "sg:city":"Moonah",
    "sg:classifiers":[
        {
            "category":"Building & Trades",
            "subcategory":"Cleaning & Sanitation",
            "type":"Services"
        }
    ],
    "sg:phone":"+61 408 739 266",
    "sg:postcode":"7009",
    "sg:province":"TAS",
    "sg:tags":[
        "industrial",
        "commercial",
        "contractor"
    ],
    "wof:name":"Cleanit Now",
    "wof:placetype":"venue"
},
  "geometry": {"coordinates":[147.28904724099999,-42.8419418335],"type":"Point"}
}