{
  "type": "Feature",
  "properties": {
    "iso:country":"AU",
    "sg:address":"Red Rover Rd",
    "sg:city":"Gladstone",
    "sg:classifiers":[
        {
            "category":"Utilities",
            "subcategory":"Natural Gas",
            "type":"Services"
        }
    ],
    "sg:phone":"+61 7 4972 2533",
    "sg:postcode":"4680",
    "sg:province":"QLD",
    "sg:tags":[
        "supplier"
    ],
    "wof:name":"BOC Gases",
    "wof:placetype":"venue"
},
  "geometry": {"coordinates":[151.224884033,-23.8522758484],"type":"Point"}
}