{
  "type": "Feature",
  "properties": {
    "iso:country":"AU",
    "sg:address":"89 Winston Ave",
    "sg:city":"Daw Park",
    "sg:classifiers":[
        {
            "category":"Communications",
            "subcategory":"Film & Video Production",
            "type":"Services"
        }
    ],
    "sg:phone":"+61 8 8299 0014",
    "sg:postcode":"5041",
    "sg:province":"SA",
    "sg:tags":[
        "dvd",
        "library"
    ],
    "wof:name":"Winston Dvd",
    "wof:placetype":"venue"
},
  "geometry": {"coordinates":[138.583557,-34.988132],"type":"Point"}
}