{
  "type": "Feature",
  "properties": {
    "iso:country":"AU",
    "sg:address":"54- 56 Wells St",
    "sg:city":"Frankston",
    "sg:classifiers":[
        {
            "category":"Health Services",
            "subcategory":"Doctor",
            "type":"Services"
        }
    ],
    "sg:phone":"+61 3 9769 6311",
    "sg:postcode":"3199",
    "sg:province":"VIC",
    "sg:tags":[
        "medical",
        "practitioner"
    ],
    "wof:name":"Premier Care Medical Centres (A Division of NM&IG Radiology Pty Ltd)",
    "wof:placetype":"venue"
},
  "geometry": {"coordinates":[144.96862793,-37.827255249],"type":"Point"}
}