{
  "type": "Feature",
  "properties": {
    "iso:country":"AU",
    "sg:address":"79 Moray St",
    "sg:city":"New Farm",
    "sg:classifiers":[
        {
            "category":"Social Services",
            "subcategory":"Retirement Home",
            "type":"Services"
        }
    ],
    "sg:phone":"+61 7 4124 8955",
    "sg:postcode":"4005",
    "sg:province":"QLD",
    "sg:tags":[
        "village"
    ],
    "wof:name":"Gleneagles On The River",
    "wof:placetype":"venue"
},
  "geometry": {"coordinates":[153.040817261,-27.466424942],"type":"Point"}
}