{
  "type": "Feature",
  "properties": {
    "iso:country":"AU",
    "sg:address":"5 Kiewa Pl",
    "sg:city":"Kirrawee",
    "sg:classifiers":[
        {
            "category":"Professional",
            "subcategory":"Detective & Security Services",
            "type":"Services"
        }
    ],
    "sg:phone":"+61 2 9545 2944",
    "sg:postcode":"2232",
    "sg:province":"NSW",
    "sg:tags":[
        "consultant",
        "system"
    ],
    "wof:name":"VingCard/Elsafe",
    "wof:placetype":"venue"
},
  "geometry": {"coordinates":[151.072174072,-34.0241088867],"type":"Point"}
}