{
  "type": "Feature",
  "properties": {
    "addr:full":"Shp 162 Gladstone Park Shopng Cntr Gladstone Park VIC 3043",
    "addr:housenumber":"162",
    "addr:postcode":"3043",
    "addr:street":"Gladstone",
    "iso:country":"AU",
    "sg:address":"Shp 162",
    "sg:city":"Gladstone Park Shopng Cntr Gladstone Park",
    "sg:classifiers":[
        {
            "category":"Fast Food",
            "type":"Food & Drink"
        }
    ],
    "sg:phone":"+61 3 9330 0309",
    "sg:postcode":"3043",
    "sg:province":"VIC",
    "sg:tags":[
        "away",
        "take"
    ],
    "wof:name":"The Roast House",
    "wof:placetype":"venue"
},
  "geometry": {"coordinates":[144.88259887699999,-37.6881256104],"type":"Point"}
}