{
  "type": "Feature",
  "properties": {
    "addr:full":"1 Rural Pl Wagga Wagga NSW 2650",
    "addr:housenumber":"1",
    "addr:postcode":"2650",
    "addr:street":"Rural Pl",
    "iso:country":"AU",
    "sg:address":"1 Rural Pl",
    "sg:city":"Wagga Wagga",
    "sg:classifiers":[
        {
            "category":"Organizations",
            "subcategory":"Community Association",
            "type":"Services"
        }
    ],
    "sg:phone":"+61 2 6921 2205",
    "sg:postcode":"2650",
    "sg:province":"NSW",
    "sg:tags":[
        "organisation",
        "family",
        "welfare"
    ],
    "wof:name":"Meals On Wheels",
    "wof:placetype":"venue"
},
  "geometry": {"coordinates":[147.37135314899999,-35.107585907],"type":"Point"}
}