{
  "type": "Feature",
  "properties": {
    "iso:country":"AU",
    "sg:address":"PO Box 478",
    "sg:city":"Kwinana Private Boxes",
    "sg:classifiers":[
        {
            "category":"Building & Trades",
            "subcategory":"Construction",
            "type":"Services"
        }
    ],
    "sg:phone":"+61 416 098 225",
    "sg:postcode":"6966",
    "sg:province":"WA",
    "sg:tags":[
        "fencing",
        "contractor"
    ],
    "wof:name":"V.I.P. Fencing & Landscaping",
    "wof:placetype":"venue"
},
  "geometry": {"coordinates":[115.813454,-32.247662],"type":"Point"}
}