{
  "type": "Feature",
  "properties": {
    "addr:full":"1 Palmer St Katherine NT 0850",
    "addr:housenumber":"1",
    "addr:postcode":"nt 0850",
    "addr:street":"Palmer St",
    "iso:country":"AU",
    "sg:address":"1 Palmer St",
    "sg:city":"Katherine",
    "sg:classifiers":[
        {
            "category":"Building & Trades",
            "subcategory":"Construction",
            "type":"Services"
        }
    ],
    "sg:phone":"+61 8 8971 7447",
    "sg:postcode":"0850",
    "sg:province":"NT",
    "sg:tags":[
        "contractor"
    ],
    "wof:name":"Harris Builders",
    "wof:placetype":"venue"
},
  "geometry": {"coordinates":[132.29070999999999,-14.475845],"type":"Point"}
}