{
  "type": "Feature",
  "properties": {
    "addr:full":"39 Lawson St Penrith NSW 2750",
    "addr:housenumber":"39",
    "addr:postcode":"2750",
    "addr:street":"Lawson St",
    "iso:country":"AU",
    "sg:address":"39 Lawson St",
    "sg:city":"Penrith",
    "sg:classifiers":[
        {
            "category":"Personal",
            "subcategory":"Barber",
            "type":"Services"
        }
    ],
    "sg:phone":"+61 2 4731 4143",
    "sg:postcode":"2750",
    "sg:province":"NSW",
    "wof:name":"Gabriel's Barber Shop",
    "wof:placetype":"venue"
},
  "geometry": {"coordinates":[150.66273498499999,-33.750415802],"type":"Point"}
}