{
  "type": "Feature",
  "properties": {
    "addr:full":"PO Box 7609 Baulkham Hills BC NSW 2153",
    "addr:postcode":"nsw 2153",
    "iso:country":"AU",
    "sg:address":"PO Box 7609",
    "sg:city":"Baulkham Hills BC",
    "sg:classifiers":[
        {
            "category":"Banks & Credit Unions",
            "subcategory":"Investment Brokerage",
            "type":"Services"
        }
    ],
    "sg:phone":"+61 2 9659 6111",
    "sg:postcode":"2153",
    "sg:province":"NSW",
    "sg:tags":[
        "finance",
        "broker"
    ],
    "wof:name":"Senator Group Pty Ltd The",
    "wof:placetype":"venue"
},
  "geometry": {"coordinates":[150.96582031200001,-33.7307853699],"type":"Point"}
}