{
  "type": "Feature",
  "properties": {
    "addr:full":"54 Keys Rd Keysborough VIC 3173",
    "addr:housenumber":"54",
    "addr:postcode":"3173",
    "addr:street":"Keys Rd",
    "iso:country":"AU",
    "sg:address":"54 Keys Rd",
    "sg:city":"Keysborough",
    "sg:classifiers":[
        {
            "category":"Utilities",
            "subcategory":"Refuse",
            "type":"Services"
        }
    ],
    "sg:phone":"+61 3 9706 3777",
    "sg:postcode":"3173",
    "sg:province":"VIC",
    "sg:tags":[
        "remover",
        "rubbish"
    ],
    "wof:name":"Andreano Rubbish Removal & Bin Hire",
    "wof:placetype":"venue"
},
  "geometry": {"coordinates":[145.17689514200001,-38.0240707397],"type":"Point"}
}