{
  "type": "Feature",
  "properties": {
    "addr:full":"42 Princes Hwy Narooma NSW 2546",
    "addr:housenumber":"42",
    "addr:postcode":"2546",
    "addr:street":"Princes Hwy",
    "iso:country":"AU",
    "sg:address":"42 Princes Hwy",
    "sg:city":"Narooma",
    "sg:classifiers":[
        {
            "category":"Shopping",
            "subcategory":"Computers & Home Electronics",
            "type":"Retail Goods"
        }
    ],
    "sg:phone":"+61 2 4476 1755",
    "sg:postcode":"2546",
    "sg:province":"NSW",
    "sg:tags":[
        "equipment",
        "part",
        "electronic"
    ],
    "wof:name":"Narooma Picture Framing",
    "wof:placetype":"venue"
},
  "geometry": {"coordinates":[150.12515258799999,-36.2149047852],"type":"Point"}
}