{
  "type": "Feature",
  "properties": {
    "addr:full":"52 Reid St Wangaratta VIC 3677",
    "addr:housenumber":"52",
    "addr:postcode":"3677",
    "addr:street":"Reid St",
    "iso:country":"AU",
    "sg:address":"52 Reid St",
    "sg:city":"Wangaratta",
    "sg:classifiers":[
        {
            "category":"Organizations",
            "subcategory":"Membership Organization",
            "type":"Services"
        }
    ],
    "sg:phone":"+61 408 221 420",
    "sg:postcode":"3677",
    "sg:province":"VIC",
    "sg:tags":[
        "railway"
    ],
    "wof:name":"Rail Safety (Vic) Pty Ltd",
    "wof:placetype":"venue"
},
  "geometry": {"coordinates":[146.326461792,-36.3549537659],"type":"Point"}
}