{
  "type": "Feature",
  "properties": {
    "addr:full":"168 Pittwater Rd Manly NSW 2095",
    "addr:housenumber":"168",
    "addr:postcode":"2095",
    "addr:street":"Pittwater Rd",
    "iso:country":"AU",
    "sg:address":"168 Pittwater Rd",
    "sg:city":"Manly",
    "sg:classifiers":[
        {
            "category":"Retail",
            "subcategory":"Storage",
            "type":"Services"
        }
    ],
    "sg:phone":"+61 2 9977 2447",
    "sg:postcode":"2095",
    "sg:province":"NSW",
    "sg:tags":[
        "removal",
        "furniture"
    ],
    "wof:name":"Reliable Removals",
    "wof:placetype":"venue"
},
  "geometry": {"coordinates":[151.285064697,-33.7896003723],"type":"Point"}
}