{
  "type": "Feature",
  "properties": {
    "addr:full":"57 Turon Pde Woolgoolga NSW 2456",
    "addr:housenumber":"57",
    "addr:postcode":"2456",
    "addr:street":"Turon Pde",
    "iso:country":"AU",
    "sg:address":"57 Turon Pde",
    "sg:city":"Woolgoolga",
    "sg:classifiers":[
        {
            "category":"Home & Garden",
            "subcategory":"Carpets & Floor Coverings",
            "type":"Retail Goods"
        }
    ],
    "sg:phone":"+61 2 6654 2056",
    "sg:postcode":"2456",
    "sg:province":"NSW",
    "sg:tags":[
        "banana",
        "grower"
    ],
    "wof:name":"Singh Sohan & Jaswinder",
    "wof:placetype":"venue"
},
  "geometry": {"coordinates":[153.19241299999999,-30.111925],"type":"Point"}
}