{
  "type": "Feature",
  "properties": {
    "iso:country":"AU",
    "sg:address":"10/ 31 Stuart St",
    "sg:city":"Tweed Heads",
    "sg:classifiers":[
        {
            "category":"Professional",
            "subcategory":"Printing & Photocopies",
            "type":"Services"
        }
    ],
    "sg:phone":"+61 7 5599 3844",
    "sg:postcode":"2485",
    "sg:province":"NSW",
    "sg:tags":[
        "trophy"
    ],
    "wof:name":"Joys Names, Gifts & Trophies",
    "wof:placetype":"venue"
},
  "geometry": {"coordinates":[153.54202270499999,-28.1693935394],"type":"Point"}
}