{
  "type": "Feature",
  "properties": {
    "iso:country":"AU",
    "sg:address":"244 Flinders St",
    "sg:city":"Melbourne",
    "sg:classifiers":[
        {
            "category":"Organizations",
            "subcategory":"Non-profit Organization",
            "type":"Services"
        }
    ],
    "sg:phone":"+61 3 9650 4077",
    "sg:postcode":"3000",
    "sg:province":"VIC",
    "sg:tags":[
        "support",
        "disability",
        "organisation"
    ],
    "wof:name":"Yooralla",
    "wof:placetype":"venue"
},
  "geometry": {"coordinates":[144.966262817,-37.8176689148],"type":"Point"}
}