{
  "type": "Feature",
  "properties": {
    "iso:country":"AU",
    "sg:address":"12 Camira St",
    "sg:city":"Regency Park",
    "sg:classifiers":[
        {
            "category":"Wholesale",
            "subcategory":"Machinery & Supplies",
            "type":"Manufacturing & Wholesale Goods"
        }
    ],
    "sg:phone":"+61 8 8346 5522",
    "sg:postcode":"5010",
    "sg:province":"SA",
    "sg:tags":[
        "machine",
        "tool",
        "engineer"
    ],
    "wof:name":"FW Hercus",
    "wof:placetype":"venue"
},
  "geometry": {"coordinates":[138.573852539,-34.865978241],"type":"Point"}
}