{
  "type": "Feature",
  "properties": {
    "addr:full":"21 Osborne Drv Narangba QLD 4504",
    "addr:housenumber":"21",
    "addr:postcode":"4504",
    "addr:street":"Osborne Drv",
    "iso:country":"AU",
    "sg:address":"21 Osborne Drv",
    "sg:city":"Narangba",
    "sg:classifiers":[
        {
            "category":"Manufacturing",
            "subcategory":"Glass & Minerals",
            "type":"Manufacturing & Wholesale Goods"
        }
    ],
    "sg:phone":"+61 7 3888 6110",
    "sg:postcode":"4504",
    "sg:province":"QLD",
    "sg:tags":[
        "exploration"
    ],
    "wof:name":"Geochem Solutions",
    "wof:placetype":"venue"
},
  "geometry": {"coordinates":[152.954467773,-27.1825847626],"type":"Point"}
}