{
  "type": "Feature",
  "properties": {
    "addr:full":"Un 3/ 42 Paisley Drv Lawnton QLD 4501",
    "addr:housenumber":"42",
    "addr:postcode":"4501",
    "addr:street":"Paisley Drv",
    "iso:country":"AU",
    "sg:address":"Un 3/ 42 Paisley Drv",
    "sg:city":"Lawnton",
    "sg:classifiers":[
        {
            "category":"Health Services",
            "subcategory":"Doctor",
            "type":"Services"
        }
    ],
    "sg:phone":"+61 7 3285 4243",
    "sg:postcode":"4501",
    "sg:province":"QLD",
    "sg:tags":[
        "occupational",
        "safety"
    ],
    "wof:name":"Individual Training Concepts Pty Ltd",
    "wof:placetype":"venue"
},
  "geometry": {"coordinates":[152.98846435600001,-27.2846164703],"type":"Point"}
}