{
  "type": "Feature",
  "properties": {
    "addr:full":"65 Eyre St North Ward QLD 4810",
    "addr:housenumber":"65",
    "addr:postcode":"4810",
    "addr:street":"Eyre St",
    "iso:country":"AU",
    "sg:address":"65 Eyre St",
    "sg:city":"North Ward",
    "sg:classifiers":[
        {
            "category":"Health Services",
            "subcategory":"Doctor",
            "type":"Services"
        }
    ],
    "sg:phone":"+61 7 4772 2711",
    "sg:postcode":"4810",
    "sg:province":"QLD",
    "sg:tags":[
        "medical",
        "practitioner"
    ],
    "wof:name":"Likely Michael Dr",
    "wof:placetype":"venue"
},
  "geometry": {"coordinates":[146.803833,-19.242037],"type":"Point"}
}