{
  "type": "Feature",
  "properties": {
    "addr:full":"70- 75 Nolan St Maryborough VIC 3465",
    "addr:housenumber":"75",
    "addr:postcode":"3465",
    "addr:street":"Nolan St",
    "iso:country":"AU",
    "sg:address":"70- 75 Nolan St",
    "sg:city":"Maryborough",
    "sg:classifiers":[
        {
            "category":"Food & Beverages",
            "subcategory":"Liquor & Beverages",
            "type":"Retail Goods"
        }
    ],
    "sg:phone":"+61 3 5460 5653",
    "sg:postcode":"3465",
    "sg:province":"VIC",
    "sg:tags":[
        "store"
    ],
    "wof:name":"Harrys Liquor",
    "wof:placetype":"venue"
},
  "geometry": {"coordinates":[143.73875427199999,-37.0479354858],"type":"Point"}
}