{
  "type": "Feature",
  "properties": {
    "iso:country":"AU",
    "sg:address":"15-17 Blaxland Rd",
    "sg:city":"Rhodes",
    "sg:classifiers":[
        {
            "category":"Government",
            "subcategory":"Court House",
            "type":"Public Place"
        }
    ],
    "sg:phone":"+61 2 9743 2831",
    "sg:postcode":"2138",
    "sg:province":"NSW",
    "sg:tags":[
        "personal",
        "marriage",
        "family",
        "counselling"
    ],
    "wof:name":"Salvation Army Counselling Service",
    "wof:placetype":"venue"
},
  "geometry": {"coordinates":[151.08793640100001,-33.8288574219],"type":"Point"}
}