{
  "type": "Feature",
  "properties": {
    "iso:country":"AU",
    "sg:address":"Shop 349",
    "sg:city":"The Corner, Erina Fair Erina",
    "sg:classifiers":[
        {
            "category":"Personal",
            "subcategory":"Beauty Salon",
            "type":"Services"
        }
    ],
    "sg:phone":"+61 2 4365 3600",
    "sg:postcode":"2250",
    "sg:province":"NSW",
    "sg:tags":[
        "hairdresser"
    ],
    "wof:name":"Just Cuts",
    "wof:placetype":"venue"
},
  "geometry": {"coordinates":[151.347412109,-33.4256591797],"type":"Point"}
}