{
  "type": "Feature",
  "properties": {
    "addr:full":"305/ 87 Griffith St Coolangatta QLD 4225",
    "addr:housenumber":"305 / 87",
    "addr:postcode":"4225",
    "addr:street":"Griffith St",
    "iso:country":"AU",
    "sg:address":"305/ 87 Griffith St",
    "sg:city":"Coolangatta",
    "sg:classifiers":[
        {
            "category":"Wholesale",
            "subcategory":"Scrap",
            "type":"Manufacturing & Wholesale Goods"
        }
    ],
    "sg:phone":"+61 1800 108 420",
    "sg:postcode":"4225",
    "sg:province":"QLD",
    "sg:tags":[
        "merchant",
        "metal"
    ],
    "wof:name":"Crazy Recycling",
    "wof:placetype":"venue"
},
  "geometry": {"coordinates":[153.53947448700001,-28.1685657501],"type":"Point"}
}