{
  "type": "Feature",
  "properties": {
    "addr:full":"1173 Logan St Holland Park QLD 4121",
    "addr:housenumber":"1173",
    "addr:postcode":"4121",
    "addr:street":"Logan St",
    "iso:country":"AU",
    "sg:address":"1173 Logan St",
    "sg:city":"Holland Park",
    "sg:classifiers":[
        {
            "category":"Health Services",
            "subcategory":"Health Practitioner",
            "type":"Services"
        }
    ],
    "sg:phone":"+61 416 125 610",
    "sg:postcode":"4121",
    "sg:province":"QLD",
    "sg:tags":[
        "psychologist"
    ],
    "wof:name":"Dyer Marianne",
    "wof:placetype":"venue"
},
  "geometry": {"coordinates":[153.07072448700001,-27.5285720825],"type":"Point"}
}