{
  "type": "Feature",
  "properties": {
    "iso:country":"AU",
    "sg:address":"Suite 2B &#034;Warina Walk Arcade&#034; 114 Main S",
    "sg:city":"Murwillumbah",
    "sg:classifiers":[
        {
            "category":"Real Estate",
            "subcategory":"Real Estate Agent",
            "type":"Services"
        }
    ],
    "sg:phone":"+61 2 6672 8484",
    "sg:postcode":"2484",
    "sg:province":"NSW",
    "wof:name":"All-In-1 Real Estate",
    "wof:placetype":"venue"
},
  "geometry": {"coordinates":[153.40342712399999,-28.3228321075],"type":"Point"}
}