{
  "type": "Feature",
  "properties": {
    "addr:full":"17 Albany Hwy Albany WA 6330",
    "addr:housenumber":"17",
    "addr:postcode":"6330",
    "addr:street":"Albany Hwy",
    "iso:country":"AU",
    "sg:address":"17 Albany Hwy",
    "sg:city":"Albany",
    "sg:classifiers":[
        {
            "category":"Retail",
            "subcategory":"Repair Shop",
            "type":"Services"
        }
    ],
    "sg:phone":"+61 8 9841 2500",
    "sg:postcode":"6330",
    "sg:province":"WA",
    "sg:tags":[
        "machine",
        "sewing"
    ],
    "wof:name":"Albany Sewing & Knitting Centre",
    "wof:placetype":"venue"
},
  "geometry": {"coordinates":[117.8828125,-35.0210189819],"type":"Point"}
}