{
  "type": "Feature",
  "properties": {
    "addr:full":"U1/ 2 Tangarra St Croydon Park NSW 2133",
    "addr:postcode":"2133",
    "addr:street":"U1 / 2 Tangarra St",
    "iso:country":"AU",
    "sg:address":"U1/ 2 Tangarra St",
    "sg:city":"Croydon Park",
    "sg:classifiers":[
        {
            "category":"Banks & Credit Unions",
            "subcategory":"Bank",
            "type":"Services"
        }
    ],
    "sg:phone":"+61 2 9701 0780",
    "sg:postcode":"2133",
    "sg:province":"NSW",
    "sg:tags":[
        "broker",
        "mortgage"
    ],
    "wof:name":"Follow Me Home Loans",
    "wof:placetype":"venue"
},
  "geometry": {"coordinates":[151.097122192,-33.8959693909],"type":"Point"}
}