{
  "type": "Feature",
  "properties": {
    "iso:country":"AU",
    "sg:address":"5A Wheeler St",
    "sg:city":"Shepparton",
    "sg:classifiers":[
        {
            "category":"Utilities",
            "type":"Services"
        }
    ],
    "sg:phone":"+61 3 5821 8787",
    "sg:postcode":"3630",
    "sg:province":"VIC",
    "sg:tags":[
        "refrigeration",
        "industrial",
        "commercial",
        "retail"
    ],
    "wof:name":"Brett Collins Refrigeration",
    "wof:placetype":"venue"
},
  "geometry": {"coordinates":[145.41986084000001,-36.3726921082],"type":"Point"}
}