{
  "type": "Feature",
  "properties": {
    "iso:country":"AU",
    "sg:address":"62 Lochard Drv",
    "sg:city":"Torquay",
    "sg:classifiers":[
        {
            "category":"Industrial Area",
            "type":"Public Place"
        }
    ],
    "sg:phone":"+61 3 5261 9775",
    "sg:postcode":"3228",
    "sg:province":"VIC",
    "sg:tags":[
        "protective",
        "clothing"
    ],
    "wof:name":"Cherie Australia",
    "wof:placetype":"venue"
},
  "geometry": {"coordinates":[144.335709,-38.318859],"type":"Point"}
}