{
  "type": "Feature",
  "properties": {
    "iso:country":"AU",
    "sg:address":"Suite E2/ 118 Railway St",
    "sg:city":"West Perth",
    "sg:classifiers":[
        {
            "category":"Government",
            "subcategory":"Customs House",
            "type":"Public Place"
        }
    ],
    "sg:phone":"+61 8 9486 1866",
    "sg:postcode":"6005",
    "sg:province":"WA",
    "sg:tags":[
        "title",
        "management",
        "stratum"
    ],
    "wof:name":"Strata Titles Institute Of WA (Inc)",
    "wof:placetype":"venue"
},
  "geometry": {"coordinates":[115.843650818,-31.943819046],"type":"Point"}
}