{
  "type": "Feature",
  "properties": {
    "iso:country":"AU",
    "sg:address":"8 King St",
    "sg:city":"Airport West",
    "sg:classifiers":[
        {
            "category":"Wholesale",
            "subcategory":"Electrical",
            "type":"Manufacturing & Wholesale Goods"
        }
    ],
    "sg:phone":"+61 3 9338 6266",
    "sg:postcode":"3042",
    "sg:province":"VIC",
    "sg:tags":[
        "control",
        "equipment",
        "switch"
    ],
    "wof:name":"Lawrence & Hanson Electrical Distributors",
    "wof:placetype":"venue"
},
  "geometry": {"coordinates":[144.89030456500001,-37.7233924866],"type":"Point"}
}