{
  "type": "Feature",
  "properties": {
    "addr:full":"3/ 413 Victoria St Wetherill Park NSW 2164",
    "addr:housenumber":"/ 413",
    "addr:postcode":"2164",
    "addr:street":"Victoria St",
    "iso:country":"AU",
    "sg:address":"3/ 413 Victoria St",
    "sg:city":"Wetherill Park",
    "sg:classifiers":[
        {
            "category":"Home & Garden",
            "subcategory":"Building Materials",
            "type":"Retail Goods"
        }
    ],
    "sg:phone":"+61 1800 600 602",
    "sg:postcode":"2164",
    "sg:province":"NSW",
    "sg:tags":[
        "fitting",
        "door"
    ],
    "wof:name":"Autoslide Pty Ltd",
    "wof:placetype":"venue"
},
  "geometry": {"coordinates":[150.89581298799999,-33.8449821472],"type":"Point"}
}