{
  "type": "Feature",
  "properties": {
    "addr:full":"PO Box 279 St Helens TAS 7216",
    "addr:postcode":"7216",
    "iso:country":"AU",
    "sg:address":"PO Box 279 St",
    "sg:city":"Helens",
    "sg:classifiers":[
        {
            "category":"Building & Trades",
            "subcategory":"Equipment Rental",
            "type":"Services"
        }
    ],
    "sg:phone":"+61 408 131 587",
    "sg:postcode":"7216",
    "sg:province":"TAS",
    "sg:tags":[
        "crane",
        "hire"
    ],
    "wof:name":"St Helens Crane Hire",
    "wof:placetype":"venue"
},
  "geometry": {"coordinates":[148.23994400000001,-41.316879],"type":"Point"}
}