{
  "type": "Feature",
  "properties": {
    "iso:country":"AU",
    "sg:address":"St",
    "sg:city":"Peters",
    "sg:classifiers":[
        {
            "category":"Building & Trades",
            "subcategory":"Construction",
            "type":"Services"
        }
    ],
    "sg:phone":"+61 411 050 060",
    "sg:postcode":"5069",
    "sg:province":"SA",
    "sg:tags":[
        "repair",
        "maintenance",
        "contractor"
    ],
    "wof:name":"Heritage House Renovations",
    "wof:placetype":"venue"
},
  "geometry": {"coordinates":[138.623504639,-34.9047203064],"type":"Point"}
}