{
  "type": "Feature",
  "properties": {
    "iso:country":"AU",
    "sg:address":"11 Rowe St",
    "sg:city":"Malaga",
    "sg:classifiers":[
        {
            "category":"Shopping",
            "subcategory":"Pets & Pet Supplies",
            "type":"Retail Goods"
        }
    ],
    "sg:phone":"+61 8 9249 9038",
    "sg:postcode":"6090",
    "sg:province":"WA",
    "sg:tags":[
        "boring",
        "drilling",
        "equipment"
    ],
    "wof:name":"Drillstar Engineering",
    "wof:placetype":"venue"
},
  "geometry": {"coordinates":[115.889923096,-31.8569602966],"type":"Point"}
}