{
  "type": "Feature",
  "properties": {
    "addr:full":"Opp. Flower Power Old Northern Rd Glenhaven NSW 2156",
    "addr:postcode":"2156",
    "addr:street":"Opp.;Old Northern Rd",
    "iso:country":"AU",
    "sg:address":"Opp. Flower Power Old Northern Rd",
    "sg:city":"Glenhaven",
    "sg:classifiers":[
        {
            "category":"Health Services",
            "subcategory":"Health Practitioner",
            "type":"Services"
        }
    ],
    "sg:phone":"+61 2 9680 4960",
    "sg:postcode":"2156",
    "sg:province":"NSW",
    "sg:tags":[
        "physiotherapist"
    ],
    "wof:name":"Glenhaven Physiotherapy Centre",
    "wof:placetype":"venue"
},
  "geometry": {"coordinates":[151.011154175,-33.7069206238],"type":"Point"}
}