{
  "type": "Feature",
  "properties": {
    "iso:country":"AU",
    "sg:address":"Lot 97 Melrose Rd",
    "sg:city":"Cowell",
    "sg:classifiers":[
        {
            "category":"Building & Trades",
            "subcategory":"Construction",
            "type":"Services"
        }
    ],
    "sg:phone":"+61 417 813 345",
    "sg:postcode":"5602",
    "sg:province":"SA",
    "sg:tags":[
        "renovation",
        "alterations",
        "extension",
        "contractor"
    ],
    "wof:name":"Stening Bronte Construction",
    "wof:placetype":"venue"
},
  "geometry": {"coordinates":[136.919189,-33.676495],"type":"Point"}
}