{
  "type": "Feature",
  "properties": {
    "addr:full":"1 River Rd Wivenhoe TAS 7320",
    "addr:housenumber":"1",
    "addr:postcode":"7320",
    "addr:street":"River Rd",
    "iso:country":"AU",
    "sg:address":"1 River Rd",
    "sg:city":"Wivenhoe",
    "sg:classifiers":[
        {
            "category":"Professional",
            "subcategory":"Engineering",
            "type":"Services"
        }
    ],
    "sg:phone":"+61 3 6430 2777",
    "sg:postcode":"7320",
    "sg:province":"TAS",
    "sg:tags":[
        "diesel",
        "engineer"
    ],
    "wof:name":"A.J.L. Mechanical Service Pty Ltd",
    "wof:placetype":"venue"
},
  "geometry": {"coordinates":[145.925949,-41.067474],"type":"Point"}
}