{
  "type": "Feature",
  "properties": {
    "iso:country":"AU",
    "sg:address":"7 Powerhouse Rd",
    "sg:city":"Howard",
    "sg:phone":"+61 7 4129 4334",
    "sg:postcode":"4659",
    "sg:province":"QLD",
    "wof:name":"All Things Outside",
    "wof:placetype":"venue"
},
  "geometry": {"coordinates":[152.568359,-25.322512],"type":"Point"}
}