{
  "type": "Feature",
  "properties": {
    "addr:full":"14 Fairway Crt Invermay Park VIC 3350",
    "addr:housenumber":"14",
    "addr:postcode":"3350",
    "addr:street":"Fairway Crt",
    "iso:country":"AU",
    "sg:address":"14 Fairway Crt",
    "sg:city":"Invermay Park",
    "sg:classifiers":[
        {
            "category":"Building & Trades",
            "subcategory":"Construction",
            "type":"Services"
        }
    ],
    "sg:phone":"+61 3 5332 3069",
    "sg:postcode":"3350",
    "sg:province":"VIC",
    "sg:tags":[
        "contractor"
    ],
    "wof:name":"Haintz N J & A M",
    "wof:placetype":"venue"
},
  "geometry": {"coordinates":[143.85723899999999,-37.530285],"type":"Point"}
}