{
  "type": "Feature",
  "properties": {
    "addr:full":"20 The Entrance Rd The Entrance NSW 2261",
    "addr:housenumber":"20",
    "addr:postcode":"2261",
    "addr:street":"The Entrance Rd",
    "iso:country":"AU",
    "sg:address":"20 The Entrance Rd",
    "sg:city":"The Entrance",
    "sg:classifiers":[
        {
            "category":"Shopping",
            "subcategory":"Pets & Pet Supplies",
            "type":"Retail Goods"
        }
    ],
    "sg:phone":"+61 2 4332 0222",
    "sg:postcode":"2261",
    "sg:province":"NSW",
    "sg:tags":[
        "equipment",
        "ceramic"
    ],
    "wof:name":"Holloway's Creations",
    "wof:placetype":"venue"
},
  "geometry": {"coordinates":[151.497635,-33.343227],"type":"Point"}
}