{
  "type": "Feature",
  "properties": {
    "addr:full":"Ballina West Shopping Centre+ Shop 12 -13 Ballina NSW 2478",
    "addr:housenumber":"12 -13",
    "addr:postcode":"2478",
    "iso:country":"AU",
    "sg:address":"Ballina West Shopping Centre+ Shop 12",
    "sg:city":"-13 Ballina",
    "sg:classifiers":[
        {
            "category":"Health Services",
            "subcategory":"Doctor",
            "type":"Services"
        }
    ],
    "sg:phone":"+61 2 6681 1333",
    "sg:postcode":"2478",
    "sg:province":"NSW",
    "sg:tags":[
        "medical",
        "practitioner"
    ],
    "wof:name":"Morrison Noel Dr",
    "wof:placetype":"venue"
},
  "geometry": {"coordinates":[153.59291076700001,-28.800037384],"type":"Point"}
}