{
  "type": "Feature",
  "properties": {
    "addr:full":"45 Victoria St Nhill VIC 3418",
    "addr:housenumber":"45",
    "addr:postcode":"3418",
    "addr:street":"Victoria St",
    "iso:country":"AU",
    "sg:address":"45 Victoria St",
    "sg:city":"Nhill",
    "sg:classifiers":[
        {
            "category":"Professional",
            "subcategory":"Accounting & Tax Preparation",
            "type":"Services"
        }
    ],
    "sg:phone":"+61 3 5391 1113",
    "sg:postcode":"3418",
    "sg:province":"VIC",
    "sg:tags":[
        "consultant",
        "taxation"
    ],
    "wof:name":"West Currie Consultants",
    "wof:placetype":"venue"
},
  "geometry": {"coordinates":[141.64921569800001,-36.334438324],"type":"Point"}
}