{
  "type": "Feature",
  "properties": {
    "addr:full":"3 Alfred St Woody Point QLD 4019",
    "addr:housenumber":"3",
    "addr:postcode":"4019",
    "addr:street":"Alfred St",
    "iso:country":"AU",
    "sg:address":"3 Alfred St",
    "sg:city":"Woody Point",
    "sg:classifiers":[
        {
            "category":"Building & Trades",
            "subcategory":"Construction",
            "type":"Services"
        }
    ],
    "sg:phone":"+61 7 3283 1271",
    "sg:postcode":"4019",
    "sg:province":"QLD",
    "sg:tags":[
        "contractor"
    ],
    "wof:name":"Don Kraushaar Constructions",
    "wof:placetype":"venue"
},
  "geometry": {"coordinates":[153.107299805,-27.2604484558],"type":"Point"}
}