{
  "type": "Feature",
  "properties": {
    "iso:country":"AU",
    "sg:address":"Reserve Rd",
    "sg:city":"Oxley",
    "sg:classifiers":[
        {
            "category":"Farming",
            "subcategory":"Livestock Farm",
            "type":"Manufacturing & Wholesale Goods"
        }
    ],
    "sg:phone":"+61 413 930 764",
    "sg:postcode":"3678",
    "sg:province":"VIC",
    "sg:tags":[
        "breeder",
        "horse",
        "stud"
    ],
    "wof:name":"McDonald Quarter Horses",
    "wof:placetype":"venue"
},
  "geometry": {"coordinates":[146.51184082,-36.2082901001],"type":"Point"}
}