{
  "type": "Feature",
  "properties": {
    "addr:full":"2 Cochranes Rd Moorabbin VIC 3189",
    "addr:housenumber":"2",
    "addr:postcode":"3189",
    "addr:street":"Cochranes Rd",
    "iso:country":"AU",
    "sg:address":"2 Cochranes Rd",
    "sg:city":"Moorabbin",
    "sg:classifiers":[
        {
            "category":"Building & Trades",
            "subcategory":"Equipment Rental",
            "type":"Services"
        }
    ],
    "sg:phone":"+61 3 9553 3533",
    "sg:postcode":"3189",
    "sg:province":"VIC",
    "sg:tags":[
        "fitness"
    ],
    "wof:name":"Workout Workshop Gymnasium Equipment",
    "wof:placetype":"venue"
},
  "geometry": {"coordinates":[145.060348511,-37.9420394897],"type":"Point"}
}