{
  "type": "Feature",
  "properties": {
    "addr:full":"PO Box 295 Barmera SA 5345",
    "addr:postcode":"5345",
    "iso:country":"AU",
    "sg:address":"PO Box 295",
    "sg:city":"Barmera",
    "sg:classifiers":[
        {
            "category":"Utilities",
            "subcategory":"Electric",
            "type":"Services"
        }
    ],
    "sg:phone":"+61 418 307 628",
    "sg:postcode":"5345",
    "sg:province":"SA",
    "sg:tags":[
        "electrical",
        "contractor"
    ],
    "wof:name":"W.S. Ridley Electrical",
    "wof:placetype":"venue"
},
  "geometry": {"coordinates":[140.46356201200001,-34.2567710876],"type":"Point"}
}