{
  "type": "Feature",
  "properties": {
    "addr:full":"1/ 100 Burnett St Buderim QLD 4556",
    "addr:housenumber":"/ 100",
    "addr:postcode":"4556",
    "addr:street":"Burnett St",
    "iso:country":"AU",
    "sg:address":"1/ 100 Burnett St",
    "sg:city":"Buderim",
    "sg:classifiers":[
        {
            "category":"Real Estate",
            "subcategory":"Real Estate Agent",
            "type":"Services"
        }
    ],
    "sg:phone":"+61 7 5476 7654",
    "sg:postcode":"4556",
    "sg:province":"QLD",
    "wof:name":"Trevor Hicks Realty on Buderim",
    "wof:placetype":"venue"
},
  "geometry": {"coordinates":[153.04718017600001,-26.6883468628],"type":"Point"}
}