{
  "type": "Feature",
  "properties": {
    "addr:full":"368 Ross River Rd Cranbrook QLD 4814",
    "addr:housenumber":"368",
    "addr:postcode":"4814",
    "addr:street":"Ross River Rd",
    "iso:country":"AU",
    "sg:address":"368 Ross River Rd",
    "sg:city":"Cranbrook",
    "sg:classifiers":[
        {
            "category":"Government",
            "subcategory":"City Hall",
            "type":"Public Place"
        }
    ],
    "sg:phone":"+61 7 4796 0255",
    "sg:postcode":"4814",
    "sg:province":"QLD",
    "wof:name":"Ignatius Park College Assembly Hall",
    "wof:placetype":"venue"
},
  "geometry": {"coordinates":[146.75868199999999,-19.299047],"type":"Point"}
}