{
  "type": "Feature",
  "properties": {
    "addr:full":"PO Box 136 Mt Compass SA 5210",
    "addr:postcode":"5210",
    "iso:country":"AU",
    "sg:address":"PO Box 136",
    "sg:city":"Mt Compass",
    "sg:classifiers":[
        {
            "category":"Building & Trades",
            "subcategory":"Cleaning & Sanitation",
            "type":"Services"
        }
    ],
    "sg:phone":"+61 8 8555 4128",
    "sg:postcode":"5210",
    "sg:province":"SA",
    "sg:tags":[
        "grease",
        "trap"
    ],
    "wof:name":"Compass Liquid Waste",
    "wof:placetype":"venue"
},
  "geometry": {"coordinates":[138.62506103499999,-35.355140686],"type":"Point"}
}