{
  "type": "Feature",
  "properties": {
    "iso:country":"AU",
    "sg:address":"33 Yallamurra St",
    "sg:city":"The Gap",
    "sg:classifiers":[
        {
            "category":"Shopping",
            "subcategory":"Computers & Home Electronics",
            "type":"Retail Goods"
        }
    ],
    "sg:phone":"+61 405 767 508",
    "sg:postcode":"4061",
    "sg:province":"QLD",
    "sg:tags":[
        "hardware",
        "equipment"
    ],
    "wof:name":"OZeBusiness.com",
    "wof:placetype":"venue"
},
  "geometry": {"coordinates":[152.953582764,-27.4545326233],"type":"Point"}
}