{
  "type": "Feature",
  "properties": {
    "iso:country":"AU",
    "sg:address":"Ridge St",
    "sg:city":"Bega",
    "sg:classifiers":[
        {
            "category":"Retail",
            "subcategory":"Auto Repair",
            "type":"Services"
        }
    ],
    "sg:phone":"+61 2 6492 2826",
    "sg:postcode":"2550",
    "sg:province":"NSW",
    "sg:tags":[
        "engine",
        "reconditioning"
    ],
    "wof:name":"Express Head & Engine Reconditioning",
    "wof:placetype":"venue"
},
  "geometry": {"coordinates":[149.822265625,-36.6658935547],"type":"Point"}
}