{
  "type": "Feature",
  "properties": {
    "addr:full":"382 Bell St Preston VIC 3072",
    "addr:housenumber":"382",
    "addr:postcode":"3072",
    "addr:street":"Bell St",
    "iso:country":"AU",
    "sg:address":"382 Bell St",
    "sg:city":"Preston",
    "sg:classifiers":[
        {
            "category":"Government",
            "subcategory":"City Hall",
            "type":"Public Place"
        }
    ],
    "sg:phone":"+61 3 9484 2029",
    "sg:postcode":"3072",
    "sg:province":"VIC",
    "wof:name":"Masonic Hall",
    "wof:placetype":"venue"
},
  "geometry": {"coordinates":[144.99966430699999,-37.7445983887],"type":"Point"}
}