{
  "type": "Feature",
  "properties": {
    "iso:country":"AU",
    "sg:address":"79 Wingbourne Rd",
    "sg:city":"Brookvale",
    "sg:classifiers":[
        {
            "category":"Retail",
            "subcategory":"Auto Repair",
            "type":"Services"
        }
    ],
    "sg:phone":"+61 2 9905 1678",
    "sg:postcode":"2100",
    "sg:province":"NSW",
    "sg:tags":[
        "beater",
        "painter",
        "panel"
    ],
    "wof:name":"PJB Smash Repairs",
    "wof:placetype":"venue"
},
  "geometry": {"coordinates":[151.274993897,-33.7616157532],"type":"Point"}
}