{
  "type": "Feature",
  "properties": {
    "iso:country":"AU",
    "sg:address":"411 Grimshaw St",
    "sg:city":"Bundoora",
    "sg:classifiers":[
        {
            "category":"Education",
            "subcategory":"School",
            "type":"Public Place"
        }
    ],
    "sg:phone":"+61 3 9467 3972",
    "sg:postcode":"3083",
    "sg:province":"VIC",
    "sg:tags":[
        "state",
        "except",
        "nsw"
    ],
    "wof:name":"Concord School",
    "wof:placetype":"venue"
},
  "geometry": {"coordinates":[145.06541442899999,-37.7007064819],"type":"Point"}
}