{
  "type": "Feature",
  "properties": {
    "addr:full":"51 Langridge St Collingwood VIC 3066",
    "addr:housenumber":"51",
    "addr:postcode":"3066",
    "addr:street":"Langridge St",
    "iso:country":"AU",
    "sg:address":"51 Langridge St",
    "sg:city":"Collingwood",
    "sg:classifiers":[
        {
            "category":"Parking",
            "type":"Transportation"
        }
    ],
    "sg:phone":"+61 407 415 121",
    "sg:postcode":"3066",
    "sg:province":"VIC",
    "sg:tags":[
        "branding",
        "animal"
    ],
    "wof:name":"Ian Paterson Freeze branding",
    "wof:placetype":"venue"
},
  "geometry": {"coordinates":[144.986160278,-37.8067054749],"type":"Point"}
}