{
  "type": "Feature",
  "properties": {
    "addr:full":"717 Canterbury Rd Belmore NSW 2192",
    "addr:housenumber":"717",
    "addr:postcode":"2192",
    "addr:street":"Canterbury Rd",
    "iso:country":"AU",
    "sg:address":"717 Canterbury Rd",
    "sg:city":"Belmore",
    "sg:classifiers":[
        {
            "category":"Wholesale",
            "subcategory":"Furniture",
            "type":"Manufacturing & Wholesale Goods"
        }
    ],
    "sg:phone":"+61 2 9750 7010",
    "sg:postcode":"2192",
    "sg:province":"NSW",
    "sg:tags":[
        "wholesaler",
        "mfrs"
    ],
    "wof:name":"A H L Furniture",
    "wof:placetype":"venue"
},
  "geometry": {"coordinates":[151.09179700000001,-33.923618],"type":"Point"}
}