{
  "type": "Feature",
  "properties": {
    "addr:full":"136b Main St Mornington VIC 3931",
    "addr:housenumber":"136b",
    "addr:postcode":"3931",
    "addr:street":"Main St",
    "iso:country":"AU",
    "sg:address":"136b Main St",
    "sg:city":"Mornington",
    "sg:classifiers":[
        {
            "category":"Retail",
            "subcategory":"Repair Shop",
            "type":"Services"
        }
    ],
    "sg:phone":"+61 3 5977 0501",
    "sg:postcode":"3931",
    "sg:province":"VIC",
    "sg:tags":[
        "mending",
        "clothing",
        "alteration"
    ],
    "wof:name":"Mornington Clothing Alterations",
    "wof:placetype":"venue"
},
  "geometry": {"coordinates":[145.03929138199999,-38.2202110291],"type":"Point"}
}