{
  "type": "Feature",
  "properties": {
    "iso:country":"AU",
    "sg:address":"439 Henley Beach Rd",
    "sg:city":"Lockleys",
    "sg:classifiers":[
        {
            "category":"Building & Trades",
            "subcategory":"Construction",
            "type":"Services"
        }
    ],
    "sg:phone":"+61 412 347 302",
    "sg:postcode":"5032",
    "sg:province":"SA",
    "sg:tags":[
        "contractor"
    ],
    "wof:name":"Anthony Homes Pty Ltd",
    "wof:placetype":"venue"
},
  "geometry": {"coordinates":[138.52879333499999,-34.9262084961],"type":"Point"}
}