{
  "type": "Feature",
  "properties": {
    "addr:full":"Unit 1, 15 May Holman Drv Bassendean WA 6054",
    "addr:housenumber":"15",
    "addr:postcode":"6054",
    "addr:street":"May Holman Drv",
    "iso:country":"AU",
    "sg:address":"Unit 1, 15 May Holman Drv",
    "sg:city":"Bassendean",
    "sg:classifiers":[
        {
            "category":"Manufacturing",
            "subcategory":"Metals",
            "type":"Manufacturing & Wholesale Goods"
        }
    ],
    "sg:phone":"+61 8 9379 3588",
    "sg:postcode":"6054",
    "sg:province":"WA",
    "sg:tags":[
        "steel",
        "fabricator",
        "mfrs"
    ],
    "wof:name":"Eden Fabrication",
    "wof:placetype":"venue"
},
  "geometry": {"coordinates":[115.939331055,-31.9067802429],"type":"Point"}
}