{
  "type": "Feature",
  "properties": {
    "addr:full":"Unit 2- 30 Smith St Capalaba QLD 4157",
    "addr:housenumber":"30",
    "addr:postcode":"4157",
    "addr:street":"Smith St",
    "iso:country":"AU",
    "sg:address":"Unit 2- 30 Smith St",
    "sg:city":"Capalaba",
    "sg:classifiers":[
        {
            "category":"Building & Trades",
            "subcategory":"Construction",
            "type":"Services"
        }
    ],
    "sg:phone":"+61 1300 766 385",
    "sg:postcode":"4157",
    "sg:province":"QLD",
    "sg:tags":[
        "fencing",
        "contractor"
    ],
    "sg:website":"http://www.csafeglass.com.au",
    "wof:name":"C Safe Glass Fencing System",
    "wof:placetype":"venue"
},
  "geometry": {"coordinates":[153.19932556099999,-27.5289649963],"type":"Point"}
}