{
  "type": "Feature",
  "properties": {
    "iso:country":"AU",
    "sg:address":"2 Libere Crt",
    "sg:city":"Doncaster",
    "sg:classifiers":[
        {
            "category":"Professional",
            "subcategory":"Engineering",
            "type":"Services"
        }
    ],
    "sg:phone":"+61 3 9891 6826",
    "sg:postcode":"3108",
    "sg:province":"VIC",
    "sg:tags":[
        "consulting",
        "engineer"
    ],
    "wof:name":"Basilcom Engineering",
    "wof:placetype":"venue"
},
  "geometry": {"coordinates":[145.14312744099999,-37.784740448],"type":"Point"}
}