{
  "type": "Feature",
  "properties": {
    "addr:full":"291 Clayton Rd Clayton VIC 3168",
    "addr:housenumber":"291",
    "addr:postcode":"3168",
    "addr:street":"Clayton Rd",
    "iso:country":"AU",
    "sg:address":"291 Clayton Rd",
    "sg:city":"Clayton",
    "sg:classifiers":[
        {
            "category":"Health Services",
            "subcategory":"Doctor",
            "type":"Services"
        }
    ],
    "sg:phone":"+61 3 9544 8333",
    "sg:postcode":"3168",
    "sg:province":"VIC",
    "sg:tags":[
        "medical",
        "practitioner"
    ],
    "wof:name":"Cohen Jeffery Dr",
    "wof:placetype":"venue"
},
  "geometry": {"coordinates":[145.120162964,-37.9220046997],"type":"Point"}
}