{
  "type": "Feature",
  "properties": {
    "iso:country":"AU",
    "sg:address":"Medina Rd",
    "sg:city":"Glen Waverley",
    "sg:classifiers":[
        {
            "category":"Education",
            "subcategory":"School",
            "type":"Public Place"
        }
    ],
    "sg:phone":"+61 3 9803 1330",
    "sg:postcode":"3150",
    "sg:province":"VIC",
    "sg:tags":[
        "state",
        "except",
        "nsw"
    ],
    "wof:name":"Glendal Primary",
    "wof:placetype":"venue"
},
  "geometry": {"coordinates":[145.153839111,-37.8722877502],"type":"Point"}
}