{
  "type": "Feature",
  "properties": {
    "addr:full":"Pacific Hwy North Sydney NSW 2060",
    "addr:postcode":"2060",
    "addr:street":"Pacific Hwy",
    "iso:country":"AU",
    "sg:address":"Pacific Hwy",
    "sg:city":"North Sydney",
    "sg:classifiers":[
        {
            "category":"Building & Trades",
            "subcategory":"Plumbing",
            "type":"Services"
        }
    ],
    "sg:phone":"+61 2 9954 9999",
    "sg:postcode":"2060",
    "sg:province":"NSW",
    "sg:tags":[
        "plumber",
        "gasfitters"
    ],
    "wof:name":"Sydney Plumbing Services",
    "wof:placetype":"venue"
},
  "geometry": {"coordinates":[151.206542969,-33.8383331299],"type":"Point"}
}