{
  "type": "Feature",
  "properties": {
    "addr:full":"11 B McCallum Crs Ardross WA 6153",
    "addr:housenumber":"11 b",
    "addr:postcode":"6153",
    "addr:street":"Mccallum Crs",
    "iso:country":"AU",
    "sg:address":"11 B McCallum Crs",
    "sg:city":"Ardross",
    "sg:classifiers":[
        {
            "category":"Mining & Drilling",
            "type":"Manufacturing & Wholesale Goods"
        }
    ],
    "sg:phone":"+61 403 774 303",
    "sg:postcode":"6153",
    "sg:province":"WA",
    "sg:tags":[
        "boring",
        "contractor"
    ],
    "wof:name":"Ground Water Drilling",
    "wof:placetype":"venue"
},
  "geometry": {"coordinates":[115.833641,-32.022907],"type":"Point"}
}