{
  "type": "Feature",
  "properties": {
    "iso:country":"AU",
    "sg:address":"117 South Rd",
    "sg:city":"Braybrook",
    "sg:classifiers":[
        {
            "category":"Food & Beverages",
            "subcategory":"Bakery",
            "type":"Retail Goods"
        }
    ],
    "sg:phone":"+61 3 9311 6740",
    "sg:postcode":"3019",
    "sg:province":"VIC",
    "sg:tags":[
        "baker"
    ],
    "wof:name":"Best In The West Hot Bread",
    "wof:placetype":"venue"
},
  "geometry": {"coordinates":[144.846069336,-37.7908592224],"type":"Point"}
}