{
  "type": "Feature",
  "properties": {
    "addr:full":"82 Billyard Ave Wahroonga NSW 2076",
    "addr:housenumber":"82",
    "addr:postcode":"2076",
    "addr:street":"Billyard Ave",
    "iso:country":"AU",
    "sg:address":"82 Billyard Ave",
    "sg:city":"Wahroonga",
    "sg:classifiers":[
        {
            "category":"Shopping",
            "subcategory":"Computers & Home Electronics",
            "type":"Retail Goods"
        }
    ],
    "sg:phone":"+61 417 287 345",
    "sg:postcode":"2076",
    "sg:province":"NSW",
    "sg:tags":[
        "hardware",
        "equipment"
    ],
    "wof:name":"Network Appliance Inc",
    "wof:placetype":"venue"
},
  "geometry": {"coordinates":[151.12948608400001,-33.7186164856],"type":"Point"}
}