{
  "type": "Feature",
  "properties": {
    "addr:full":"Suite 8, 132 Muller Rd Greenacres SA 5086",
    "addr:housenumber":"132",
    "addr:postcode":"5086",
    "addr:street":"Muller Rd",
    "iso:country":"AU",
    "sg:address":"Suite 8, 132 Muller Rd",
    "sg:city":"Greenacres",
    "sg:classifiers":[
        {
            "category":"Health Services",
            "subcategory":"Health Practitioner",
            "type":"Services"
        }
    ],
    "sg:phone":"+61 8 8261 0177",
    "sg:postcode":"5086",
    "sg:province":"SA",
    "sg:tags":[
        "acupuncture"
    ],
    "wof:name":"Julie Williams Physiotherapy",
    "wof:placetype":"venue"
},
  "geometry": {"coordinates":[138.633865356,-34.8711662292],"type":"Point"}
}