{
  "type": "Feature",
  "properties": {
    "addr:full":"Plently Rd Mill Park VIC 3082",
    "addr:postcode":"3082",
    "addr:street":"Plently Rd",
    "iso:country":"AU",
    "sg:address":"Plently Rd",
    "sg:city":"Mill Park",
    "sg:classifiers":[
        {
            "category":"Retail",
            "subcategory":"Auto Repair",
            "type":"Services"
        }
    ],
    "sg:phone":"+61 3 9436 4445",
    "sg:postcode":"3082",
    "sg:province":"VIC",
    "sg:tags":[
        "electrical"
    ],
    "wof:name":"Papaconstantinou Peter",
    "wof:placetype":"venue"
},
  "geometry": {"coordinates":[145.07162475600001,-37.6665534973],"type":"Point"}
}