{
  "type": "Feature",
  "properties": {
    "addr:full":"Shop 2 Royal Hotel Horton St Port Macquarie NSW 2444",
    "addr:housenumber":"shop 2",
    "addr:postcode":"2444",
    "addr:street":"Horton St",
    "iso:country":"AU",
    "sg:address":"Shop 2 Royal Hotel Horton St",
    "sg:city":"Port Macquarie",
    "sg:classifiers":[
        {
            "category":"Ice Cream",
            "type":"Food & Drink"
        }
    ],
    "sg:phone":"+61 2 6584 7288",
    "sg:postcode":"2444",
    "sg:province":"NSW",
    "sg:tags":[
        "retail"
    ],
    "wof:name":"Baskin 31 Robbins Ice Cream & Yogurt",
    "wof:placetype":"venue"
},
  "geometry": {"coordinates":[152.908188,-31.42959],"type":"Point"}
}