{
  "type": "Feature",
  "properties": {
    "addr:full":"12- 14 Kilpa Rd Moorabbin VIC 3189",
    "addr:housenumber":"14",
    "addr:postcode":"3189",
    "addr:street":"Kilpa Rd",
    "iso:country":"AU",
    "sg:address":"12- 14 Kilpa Rd",
    "sg:city":"Moorabbin",
    "sg:classifiers":[
        {
            "category":"Retail",
            "subcategory":"Auto Repair",
            "type":"Services"
        }
    ],
    "sg:phone":"+61 3 9555 8997",
    "sg:postcode":"3189",
    "sg:province":"VIC",
    "sg:tags":[
        "beater",
        "painter",
        "panel"
    ],
    "wof:name":"Mr Gloss Pty Ltd",
    "wof:placetype":"venue"
},
  "geometry": {"coordinates":[145.07321167000001,-37.9478111267],"type":"Point"}
}