{
  "type": "Feature",
  "properties": {
    "iso:country":"AU",
    "sg:address":"17 Wycombe St",
    "sg:city":"Queanbeyan",
    "sg:classifiers":[
        {
            "category":"Home & Garden",
            "subcategory":"Building Materials",
            "type":"Retail Goods"
        }
    ],
    "sg:phone":"+61 2 6299 3907",
    "sg:postcode":"2620",
    "sg:province":"NSW",
    "sg:tags":[
        "tile",
        "roofing"
    ],
    "wof:name":"K.W. Jacobs Pty Ltd",
    "wof:placetype":"venue"
},
  "geometry": {"coordinates":[149.245803833,-35.3357467651],"type":"Point"}
}