{
  "type": "Feature",
  "properties": {
    "addr:full":"Shop 32 B Sunnybank Plaza Sunnybank QLD 4109",
    "addr:housenumber":"shop 32 b",
    "addr:postcode":"4109",
    "addr:street":"Sunnybank Plaza",
    "iso:country":"AU",
    "sg:address":"Shop 32",
    "sg:city":"B Sunnybank Plaza Sunnybank",
    "sg:classifiers":[
        {
            "category":"Health Services",
            "subcategory":"Optometrist",
            "type":"Services"
        }
    ],
    "sg:phone":"+61 7 3216 9188",
    "sg:postcode":"4109",
    "sg:province":"QLD",
    "wof:name":"Ronnie Lui Optometrist",
    "wof:placetype":"venue"
},
  "geometry": {"coordinates":[153.066802978,-27.5965270996],"type":"Point"}
}