{
  "type": "Feature",
  "properties": {
    "iso:country":"AU",
    "sg:address":"14 Pittwater Rd",
    "sg:city":"Manly",
    "sg:classifiers":[
        {
            "category":"Organizations",
            "subcategory":"Membership Organization",
            "type":"Services"
        }
    ],
    "sg:phone":"+61 2 9977 2666",
    "sg:postcode":"2095",
    "sg:province":"NSW",
    "sg:tags":[
        "support",
        "health",
        "organisation"
    ],
    "wof:name":"Manly Exchange",
    "wof:placetype":"venue"
},
  "geometry": {"coordinates":[151.28529357900001,-33.7951431274],"type":"Point"}
}