{
  "type": "Feature",
  "properties": {
    "iso:country":"AU",
    "sg:address":"Farr Pl",
    "sg:city":"Isaacs",
    "sg:classifiers":[
        {
            "category":"Social Services",
            "subcategory":"Child Care",
            "type":"Services"
        }
    ],
    "sg:phone":"+61 2 6286 8886",
    "sg:postcode":"2607",
    "sg:province":"ACT",
    "wof:name":"Jellybeans Child Care & Pre-School Centre",
    "wof:placetype":"venue"
},
  "geometry": {"coordinates":[149.11119079599999,-35.3697319031],"type":"Point"}
}