{
  "type": "Feature",
  "properties": {
    "iso:country":"AU",
    "sg:address":"39A Powell Rd",
    "sg:city":"Blackmans Bay",
    "sg:classifiers":[
        {
            "category":"Real Estate",
            "subcategory":"Architect",
            "type":"Services"
        }
    ],
    "sg:phone":"+61 3 6229 4140",
    "sg:postcode":"7052",
    "sg:province":"TAS",
    "wof:name":"Gilby Paul",
    "wof:placetype":"venue"
},
  "geometry": {"coordinates":[147.328568,-42.995628],"type":"Point"}
}