{
  "type": "Feature",
  "properties": {
    "addr:full":"521-523 Burke Rd Camberwell VIC 3124",
    "addr:housenumber":"521-523",
    "addr:postcode":"3124",
    "addr:street":"Burke Rd",
    "iso:country":"AU",
    "sg:address":"521-523 Burke Rd",
    "sg:city":"Camberwell",
    "sg:classifiers":[
        {
            "category":"Real Estate",
            "subcategory":"Surveying",
            "type":"Services"
        }
    ],
    "sg:phone":"+61 3 9822 9044",
    "sg:postcode":"3124",
    "sg:province":"VIC",
    "sg:tags":[
        "building",
        "surveyor"
    ],
    "wof:name":"Thomas Nicholas",
    "wof:placetype":"venue"
},
  "geometry": {"coordinates":[145.05410766599999,-37.8441543579],"type":"Point"}
}