{
  "type": "Feature",
  "properties": {
    "addr:full":"17 Knight St Clayton VIC 3168",
    "addr:housenumber":"17",
    "addr:postcode":"3168",
    "addr:street":"Knight St",
    "iso:country":"AU",
    "sg:address":"17 Knight St",
    "sg:city":"Clayton",
    "sg:classifiers":[
        {
            "category":"Shopping",
            "subcategory":"Computers & Home Electronics",
            "type":"Retail Goods"
        }
    ],
    "sg:phone":"+61 3 9548 9207",
    "sg:postcode":"3168",
    "sg:province":"VIC",
    "sg:tags":[
        "hardware",
        "equipment"
    ],
    "wof:name":"Leader Computer Systems",
    "wof:placetype":"venue"
},
  "geometry": {"coordinates":[145.11427307100001,-37.9306030273],"type":"Point"}
}