{
  "type": "Feature",
  "properties": {
    "addr:full":"Lot 16A Light Industrial Area Tom Price WA 6751",
    "addr:postcode":"6751",
    "iso:country":"AU",
    "sg:address":"Lot 16A Light Industrial Area",
    "sg:city":"Tom Price",
    "sg:classifiers":[
        {
            "category":"Building & Trades",
            "subcategory":"Construction",
            "type":"Services"
        }
    ],
    "sg:phone":"+61 8 9188 1198",
    "sg:postcode":"6751",
    "sg:province":"WA",
    "sg:tags":[
        "contractor"
    ],
    "wof:name":"Blakers Building Maintenance",
    "wof:placetype":"venue"
},
  "geometry": {"coordinates":[117.784286499,-22.6861400604],"type":"Point"}
}