{
  "type": "Feature",
  "properties": {
    "addr:full":"389 Victoria St Abbotsford VIC 3067",
    "addr:housenumber":"389",
    "addr:postcode":"3067",
    "addr:street":"Victoria St",
    "iso:country":"AU",
    "sg:address":"389 Victoria St",
    "sg:city":"Abbotsford",
    "sg:classifiers":[
        {
            "category":"Travel",
            "subcategory":"Travel Agent",
            "type":"Entertainment"
        }
    ],
    "sg:phone":"+61 3 9421 3788",
    "sg:postcode":"3067",
    "sg:province":"VIC",
    "sg:tags":[
        "consultant"
    ],
    "wof:name":"Chang's Round World Travel Service",
    "wof:placetype":"venue"
},
  "geometry": {"coordinates":[144.99861145,-37.8102111816],"type":"Point"}
}