{
  "type": "Feature",
  "properties": {
    "addr:full":"92a William St Bathurst NSW 2795",
    "addr:housenumber":"92a",
    "addr:postcode":"2795",
    "addr:street":"William St",
    "iso:country":"AU",
    "sg:address":"92a William St",
    "sg:city":"Bathurst",
    "sg:classifiers":[
        {
            "category":"Food & Beverages",
            "subcategory":"Bakery",
            "type":"Retail Goods"
        }
    ],
    "sg:phone":"+61 2 6332 5747",
    "sg:postcode":"2795",
    "sg:province":"NSW",
    "sg:tags":[
        "baker"
    ],
    "wof:name":"Panorama Hot Bread Shop",
    "wof:placetype":"venue"
},
  "geometry": {"coordinates":[149.57911682100001,-33.4192695618],"type":"Point"}
}