{
  "type": "Feature",
  "properties": {
    "addr:full":"Shop 37-38 Gosnells Railway Markets, Fremantle Rd Gosnells WA 6110",
    "addr:housenumber":"37-38",
    "addr:postcode":"6110",
    "addr:street":"Gosnells;Fremantle Rd",
    "iso:country":"AU",
    "sg:address":"Shop 37-38 Gosnells Railway Markets, Fremantle Rd",
    "sg:city":"Gosnells",
    "sg:classifiers":[
        {
            "category":"Professional",
            "subcategory":"Printing & Photocopies",
            "type":"Services"
        }
    ],
    "sg:phone":"+61 8 9398 2353",
    "sg:postcode":"6110",
    "sg:province":"WA",
    "sg:tags":[
        "embroidery"
    ],
    "wof:name":"Westcoats",
    "wof:placetype":"venue"
},
  "geometry": {"coordinates":[115.999313355,-32.0687980652],"type":"Point"}
}