{
  "type": "Feature",
  "properties": {
    "iso:country":"AU",
    "sg:address":"28 Ovata Drv",
    "sg:city":"Tullamarine",
    "sg:classifiers":[
        {
            "category":"Utilities",
            "type":"Services"
        }
    ],
    "sg:phone":"+61 3 9338 5388",
    "sg:postcode":"3043",
    "sg:province":"VIC",
    "sg:tags":[
        "equipment",
        "towing"
    ],
    "wof:name":"Melbourne Towbar Centre",
    "wof:placetype":"venue"
},
  "geometry": {"coordinates":[144.86570739699999,-37.7093963623],"type":"Point"}
}