{
  "type": "Feature",
  "properties": {
    "addr:full":"David Jones Complex 260-261 Allinga St Canberra ACT 2601",
    "addr:housenumber":"260-261",
    "addr:postcode":"2601",
    "addr:street":"Allinga St",
    "iso:country":"AU",
    "sg:address":"David Jones Complex 260-261 Allinga St",
    "sg:city":"Canberra",
    "sg:classifiers":[
        {
            "category":"Shopping",
            "subcategory":"Clothing, Apparel, & Fashions",
            "type":"Retail Goods"
        }
    ],
    "sg:phone":"+61 2 6230 1148",
    "sg:postcode":"2601",
    "sg:province":"ACT",
    "sg:tags":[
        "lady",
        "wear"
    ],
    "wof:name":"Anthea Crawford (Australia) Pty Ltd",
    "wof:placetype":"venue"
},
  "geometry": {"coordinates":[149.12925720199999,-35.278377533],"type":"Point"}
}