{
  "type": "Feature",
  "properties": {
    "iso:country":"AU",
    "sg:address":"78 - 80 Murray St",
    "sg:city":"Gawler",
    "sg:classifiers":[
        {
            "category":"Industrial Area",
            "type":"Public Place"
        }
    ],
    "sg:phone":"+61 8 8522 1622",
    "sg:postcode":"5118",
    "sg:province":"SA",
    "sg:tags":[
        "protective",
        "clothing"
    ],
    "wof:name":"Crosbys Of Gawler",
    "wof:placetype":"venue"
},
  "geometry": {"coordinates":[138.748886,-34.596355],"type":"Point"}
}