{
  "type": "Feature",
  "properties": {
    "addr:full":"614 Stanley St South Bank QLD 4101",
    "addr:housenumber":"614",
    "addr:postcode":"4101",
    "addr:street":"Stanley St",
    "iso:country":"AU",
    "sg:address":"614 Stanley St",
    "sg:city":"South Bank",
    "sg:classifiers":[
        {
            "category":"Professional",
            "subcategory":"Business Services",
            "type":"Services"
        }
    ],
    "sg:phone":"+61 7 3846 2526",
    "sg:postcode":"4101",
    "sg:province":"QLD",
    "sg:tags":[
        "broker"
    ],
    "wof:name":"Business Advisory Services",
    "wof:placetype":"venue"
},
  "geometry": {"coordinates":[153.02981567399999,-27.4854049683],"type":"Point"}
}