{
  "type": "Feature",
  "properties": {
    "addr:full":"44 Lennox St Richmond NSW 2753",
    "addr:housenumber":"44",
    "addr:postcode":"2753",
    "addr:street":"Lennox St",
    "iso:country":"AU",
    "sg:address":"44 Lennox St",
    "sg:city":"Richmond",
    "sg:classifiers":[
        {
            "category":"Banks & Credit Unions",
            "subcategory":"Atm",
            "type":"Services"
        }
    ],
    "sg:phone":"+61 433 188 492",
    "sg:postcode":"2753",
    "sg:province":"NSW",
    "sg:tags":[
        "control",
        "soil",
        "erosion",
        "stabilisation"
    ],
    "wof:name":"Hawkesbury Outdoor Equipment - Gabbion Consultancy",
    "wof:placetype":"venue"
},
  "geometry": {"coordinates":[150.754364014,-33.6023979187],"type":"Point"}
}