{
  "type": "Feature",
  "properties": {
    "iso:country":"AU",
    "sg:address":"Unit 2/ 4a Hayes St",
    "sg:city":"Balgowlah",
    "sg:classifiers":[
        {
            "category":"Sports & Exercise",
            "subcategory":"Gym",
            "type":"Entertainment"
        }
    ],
    "sg:phone":"+61 2 9984 7191",
    "sg:postcode":"2093",
    "sg:province":"NSW",
    "sg:tags":[
        "health",
        "fitness"
    ],
    "wof:name":"White Collar Boxing & Personal Training",
    "wof:placetype":"venue"
},
  "geometry": {"coordinates":[151.26719665499999,-33.7883148193],"type":"Point"}
}