{
  "type": "Feature",
  "properties": {
    "addr:full":"Lot 12 Port Wakefield Rd Burton SA 5110",
    "addr:postcode":"5110",
    "addr:street":"Port Wakefield Rd",
    "iso:country":"AU",
    "sg:address":"Lot 12 Port Wakefield Rd",
    "sg:city":"Burton",
    "sg:classifiers":[
        {
            "category":"Commercial Area",
            "type":"Public Place"
        }
    ],
    "sg:phone":"+61 8 8280 8841",
    "sg:postcode":"5110",
    "sg:province":"SA",
    "sg:tags":[
        "heavy",
        "carrier"
    ],
    "wof:name":"Northern House Transport",
    "wof:placetype":"venue"
},
  "geometry": {"coordinates":[138.585662842,-34.7397117615],"type":"Point"}
}