{
  "type": "Feature",
  "properties": {
    "iso:country":"AU",
    "sg:address":"37 Sale St",
    "sg:city":"Orange",
    "sg:classifiers":[
        {
            "category":"Real Estate",
            "subcategory":"Real Estate Agent",
            "type":"Services"
        }
    ],
    "sg:phone":"+61 2 6362 6966",
    "sg:postcode":"2800",
    "sg:province":"NSW",
    "wof:name":"Williams Machin First National Real Estate",
    "wof:placetype":"venue"
},
  "geometry": {"coordinates":[149.095977783,-33.2836036682],"type":"Point"}
}