{
  "type": "Feature",
  "properties": {
    "iso:country":"AU",
    "sg:address":"483 Pacific Hwy",
    "sg:city":"Asquith",
    "sg:classifiers":[
        {
            "category":"Personal",
            "subcategory":"Beauty Salon",
            "type":"Services"
        }
    ],
    "sg:phone":"+61 2 9476 5709",
    "sg:postcode":"2077",
    "sg:province":"NSW",
    "sg:tags":[
        "supply",
        "artist",
        "make-up"
    ],
    "wof:name":"All Creations Make Up & Hair Service",
    "wof:placetype":"venue"
},
  "geometry": {"coordinates":[151.11068725600001,-33.6812057495],"type":"Point"}
}