{
  "type": "Feature",
  "properties": {
    "iso:country":"AU",
    "sg:address":"Shp 6 31 Main Rd",
    "sg:city":"Beachmere",
    "sg:classifiers":[
        {
            "category":"Food & Beverages",
            "subcategory":"Liquor & Beverages",
            "type":"Retail Goods"
        }
    ],
    "sg:phone":"+61 7 5496 2510",
    "sg:postcode":"4510",
    "sg:province":"QLD",
    "sg:tags":[
        "store"
    ],
    "wof:name":"Beachmere Cellars",
    "wof:placetype":"venue"
},
  "geometry": {"coordinates":[153.051117,-27.130739],"type":"Point"}
}