{
  "type": "Feature",
  "properties": {
    "addr:full":"Unit 13, 38- 46 South St Rydalmere NSW 1701",
    "addr:housenumber":"38 46",
    "addr:postcode":"1701",
    "addr:street":"South St",
    "iso:country":"AU",
    "sg:address":"Unit 13, 38- 46 South St",
    "sg:city":"Rydalmere",
    "sg:classifiers":[
        {
            "category":"Social Services",
            "subcategory":"Job Training",
            "type":"Services"
        }
    ],
    "sg:phone":"+61 1300 130 234",
    "sg:postcode":"1701",
    "sg:province":"NSW",
    "sg:tags":[
        "hire",
        "computer",
        "leasing"
    ],
    "wof:name":"Tech-Rentals Pty Ltd",
    "wof:placetype":"venue"
},
  "geometry": {"coordinates":[151.010894775,-33.8338279724],"type":"Point"}
}