{
  "type": "Feature",
  "properties": {
    "addr:full":"Suite 4, Mermaid Central Medical Centre 2431 Gold Coast QLD 4218",
    "addr:housenumber":"2431",
    "addr:postcode":"4218",
    "iso:country":"AU",
    "sg:address":"Suite 4, Mermaid Central Medical Centre 2431",
    "sg:city":"Gold Coast",
    "sg:classifiers":[
        {
            "category":"Wholesale",
            "subcategory":"Medical Equipment & Supplies",
            "type":"Manufacturing & Wholesale Goods"
        }
    ],
    "sg:phone":"+61 1800 624 412",
    "sg:postcode":"4218",
    "sg:province":"QLD",
    "sg:tags":[
        "aids",
        "hearing"
    ],
    "wof:name":"Hearing Solutions",
    "wof:placetype":"venue"
},
  "geometry": {"coordinates":[153.43557739299999,-28.0465373993],"type":"Point"}
}