{
  "type": "Feature",
  "properties": {
    "iso:country":"AU",
    "sg:address":"Unit 11 10 Belmore St",
    "sg:city":"Ryde",
    "sg:classifiers":[
        {
            "category":"Professional",
            "subcategory":"Computer Services",
            "type":"Services"
        }
    ],
    "sg:phone":"+61 2 9807 2780",
    "sg:postcode":"2112",
    "sg:province":"NSW",
    "sg:tags":[
        "repairs",
        "upgrade",
        "equipment"
    ],
    "wof:name":"Borg Industries",
    "wof:placetype":"venue"
},
  "geometry": {"coordinates":[151.103424072,-33.8133354187],"type":"Point"}
}