{
  "type": "Feature",
  "properties": {
    "iso:country":"AU",
    "sg:address":"Lot 12 Boundary Rd",
    "sg:city":"Maraylya",
    "sg:classifiers":[
        {
            "category":"Manufacturing",
            "subcategory":"Metals",
            "type":"Manufacturing & Wholesale Goods"
        }
    ],
    "sg:phone":"+61 2 4573 6520",
    "sg:postcode":"2765",
    "sg:province":"NSW",
    "sg:tags":[
        "steel",
        "fabricator",
        "mfrs"
    ],
    "wof:name":"J & J E Hill Pty Ltd",
    "wof:placetype":"venue"
},
  "geometry": {"coordinates":[150.876785278,-33.6526107788],"type":"Point"}
}