{
  "type": "Feature",
  "properties": {
    "iso:country":"AU",
    "sg:address":"16 Matheson St",
    "sg:city":"Virginia",
    "sg:classifiers":[
        {
            "category":"Retail",
            "subcategory":"Auto Repair",
            "type":"Services"
        }
    ],
    "sg:phone":"+61 7 3216 2319",
    "sg:postcode":"4014",
    "sg:province":"QLD",
    "sg:tags":[
        "repairer",
        "motor",
        "engineer"
    ],
    "wof:name":"Sportivo Automotive",
    "wof:placetype":"venue"
},
  "geometry": {"coordinates":[153.06068420400001,-27.3693561554],"type":"Point"}
}