{
  "type": "Feature",
  "properties": {
    "iso:country":"AU",
    "sg:address":"49 Bonar St",
    "sg:city":"Arncliffe",
    "sg:classifiers":[
        {
            "category":"Home & Garden",
            "subcategory":"Furniture",
            "type":"Retail Goods"
        }
    ],
    "sg:phone":"+61 1300 769 698",
    "sg:postcode":"2205",
    "sg:province":"NSW",
    "sg:tags":[
        "repair",
        "restoration"
    ],
    "wof:name":"Cuir Care Technology Pty Ld",
    "wof:placetype":"venue"
},
  "geometry": {"coordinates":[151.14666700000001,-33.932079],"type":"Point"}
}