{
  "type": "Feature",
  "properties": {
    "addr:full":"260- 284 Frankston Rd Dandenong VIC 3175",
    "addr:housenumber":"260 284",
    "addr:postcode":"3175",
    "addr:street":"Frankston Rd",
    "iso:country":"AU",
    "sg:address":"260- 284 Frankston Rd",
    "sg:city":"Dandenong",
    "sg:classifiers":[
        {
            "category":"Autos & Motor Vehicles",
            "subcategory":"Automobile Sales",
            "type":"Retail Goods"
        }
    ],
    "sg:phone":"+61 3 9797 4111",
    "sg:postcode":"3175",
    "sg:province":"VIC",
    "sg:tags":[
        "car",
        "new"
    ],
    "wof:name":"Nissan Motor Co (Aust) Pty Ltd",
    "wof:placetype":"venue"
},
  "geometry": {"coordinates":[145.24302673299999,-37.9498977661],"type":"Point"}
}