{
  "type": "Feature",
  "properties": {
    "iso:country":"AU",
    "sg:address":"PO Box 1064",
    "sg:city":"Horsham",
    "sg:classifiers":[
        {
            "category":"Building & Trades",
            "subcategory":"Construction",
            "type":"Services"
        }
    ],
    "sg:phone":"+61 3 5382 2291",
    "sg:postcode":"3400",
    "sg:province":"VIC",
    "sg:tags":[
        "plasterboard",
        "plasterer",
        "fixer"
    ],
    "wof:name":"Horsham & District Plastering",
    "wof:placetype":"venue"
},
  "geometry": {"coordinates":[142.19619750999999,-36.7172393799],"type":"Point"}
}