{
  "type": "Feature",
  "properties": {
    "iso:country":"AU",
    "sg:address":"Unit 1 / 80 Brice Ave",
    "sg:city":"Mooroolbark",
    "sg:classifiers":[
        {
            "category":"Personal",
            "subcategory":"Nail Salon",
            "type":"Services"
        }
    ],
    "sg:phone":"+61 3 9727 1224",
    "sg:postcode":"3138",
    "sg:province":"VIC",
    "sg:tags":[
        "artificial"
    ],
    "wof:name":"Le&#039; Blah Nails",
    "wof:placetype":"venue"
},
  "geometry": {"coordinates":[145.315383911,-37.7858772278],"type":"Point"}
}