{
  "type": "Feature",
  "properties": {
    "iso:country":"AU",
    "sg:address":"PO Box 551",
    "sg:city":"Nightcliff Private Boxes",
    "sg:classifiers":[
        {
            "category":"Banks & Credit Unions",
            "subcategory":"Financial Services",
            "type":"Services"
        }
    ],
    "sg:phone":"+61 412 130 520",
    "sg:postcode":"0814",
    "sg:province":"NT",
    "sg:tags":[
        "surge",
        "protection",
        "lightning"
    ],
    "wof:name":"Proactive Solutions",
    "wof:placetype":"venue"
},
  "geometry": {"coordinates":[130.856064,-12.387455],"type":"Point"}
}