{
  "type": "Feature",
  "properties": {
    "iso:country":"AU",
    "sg:address":"5 Powdrill Rd",
    "sg:city":"Prestons",
    "sg:classifiers":[
        {
            "category":"Professional",
            "type":"Services"
        }
    ],
    "sg:phone":"+61 2 9607 6799",
    "sg:postcode":"2170",
    "sg:province":"NSW",
    "sg:tags":[
        "shop",
        "fitting"
    ],
    "wof:name":"TSM Fitouts",
    "wof:placetype":"venue"
},
  "geometry": {"coordinates":[150.889572144,-33.9343147278],"type":"Point"}
}