{
  "type": "Feature",
  "properties": {
    "addr:full":"60b Stephen St Toowoomba QLD 4350",
    "addr:housenumber":"60b",
    "addr:postcode":"4350",
    "addr:street":"Stephen St",
    "iso:country":"AU",
    "sg:address":"60b Stephen St",
    "sg:city":"Toowoomba",
    "sg:classifiers":[
        {
            "category":"Home & Garden",
            "subcategory":"Carpets & Floor Coverings",
            "type":"Retail Goods"
        }
    ],
    "sg:phone":"+61 7 4639 1155",
    "sg:postcode":"4350",
    "sg:province":"QLD",
    "wof:name":"Toowoomba Tile Warehouse",
    "wof:placetype":"venue"
},
  "geometry": {"coordinates":[151.94212300000001,-27.572485],"type":"Point"}
}