{
  "type": "Feature",
  "properties": {
    "addr:full":"5/ 251 Blackburn Rd Mt Waverley VIC 3149",
    "addr:housenumber":"/ 251",
    "addr:postcode":"3149",
    "addr:street":"Blackburn Rd",
    "iso:country":"AU",
    "sg:address":"5/ 251 Blackburn Rd",
    "sg:city":"Mt Waverley",
    "sg:classifiers":[
        {
            "category":"Real Estate",
            "subcategory":"Real Estate Operator",
            "type":"Services"
        }
    ],
    "sg:phone":"+61 3 9887 9100",
    "sg:postcode":"3149",
    "sg:province":"VIC",
    "sg:tags":[
        "paging",
        "radio",
        "system"
    ],
    "wof:name":"Unicom Pty Ltd",
    "wof:placetype":"venue"
},
  "geometry": {"coordinates":[145.147338867,-37.8766593933],"type":"Point"}
}