{
  "type": "Feature",
  "properties": {
    "addr:full":"992 Stanley St East Brisbane QLD 4169",
    "addr:housenumber":"992",
    "addr:postcode":"4169",
    "addr:street":"Stanley St",
    "iso:country":"AU",
    "sg:address":"992 Stanley St",
    "sg:city":"East Brisbane",
    "sg:classifiers":[
        {
            "category":"Utilities",
            "subcategory":"Electric",
            "type":"Services"
        }
    ],
    "sg:phone":"+61 7 3217 4316",
    "sg:postcode":"4169",
    "sg:province":"QLD",
    "sg:tags":[
        "electrical",
        "contractor"
    ],
    "wof:name":"Altrad Electrical",
    "wof:placetype":"venue"
},
  "geometry": {"coordinates":[153.04765319800001,-27.4881744385],"type":"Point"}
}