{
  "type": "Feature",
  "properties": {
    "addr:full":"Crn David Drv & Nelson Bay Rd Salt Ash NSW 2318",
    "addr:postcode":"2318",
    "addr:street":"Crn David Drv & Nelson Bay Rd",
    "iso:country":"AU",
    "sg:address":"Crn David Drv & Nelson Bay Rd",
    "sg:city":"Salt Ash",
    "sg:classifiers":[
        {
            "category":"Manufacturing",
            "subcategory":"Pottery",
            "type":"Manufacturing & Wholesale Goods"
        }
    ],
    "sg:phone":"+61 2 4982 6088",
    "sg:postcode":"2318",
    "sg:province":"NSW",
    "wof:name":"Pots & Palms",
    "wof:placetype":"venue"
},
  "geometry": {"coordinates":[151.899124,-32.791637],"type":"Point"}
}