{
  "type": "Feature",
  "properties": {
    "addr:full":"Level 1, 13 Cawarra Rd Taren Point NSW 2229",
    "addr:housenumber":"13",
    "addr:postcode":"2229",
    "addr:street":"Cawarra Rd",
    "iso:country":"AU",
    "sg:address":"Level 1, 13 Cawarra Rd",
    "sg:city":"Taren Point",
    "sg:classifiers":[
        {
            "category":"Shopping",
            "subcategory":"Computers & Home Electronics",
            "type":"Retail Goods"
        }
    ],
    "sg:phone":"+61 2 9525 1344",
    "sg:postcode":"2229",
    "sg:province":"NSW",
    "sg:tags":[
        "equipment",
        "multimedia"
    ],
    "wof:name":"Ridge Films",
    "wof:placetype":"venue"
},
  "geometry": {"coordinates":[151.12631225600001,-34.027053833],"type":"Point"}
}