{
  "type": "Feature",
  "properties": {
    "addr:full":"80 North St Grafton NSW 2460",
    "addr:housenumber":"80",
    "addr:postcode":"2460",
    "addr:street":"North St",
    "iso:country":"AU",
    "sg:address":"80 North St",
    "sg:city":"Grafton",
    "sg:classifiers":[
        {
            "category":"Building & Trades",
            "subcategory":"Pest Control",
            "type":"Services"
        }
    ],
    "sg:phone":"+61 2 6642 5270",
    "sg:postcode":"2460",
    "sg:province":"NSW",
    "wof:name":"Puresafe Pest Control",
    "wof:placetype":"venue"
},
  "geometry": {"coordinates":[152.94581604000001,-29.6721477509],"type":"Point"}
}