{
  "type": "Feature",
  "properties": {
    "iso:country":"AU",
    "sg:address":"Shp1/ 24 Coondoo St",
    "sg:city":"Kuranda",
    "sg:classifiers":[
        {
            "category":"Cafe",
            "type":"Food & Drink"
        }
    ],
    "sg:phone":"+61 7 4093 8448",
    "sg:postcode":"4881",
    "sg:province":"QLD",
    "wof:name":"Nevermind Cafe",
    "wof:placetype":"venue"
},
  "geometry": {"coordinates":[145.63577270499999,-16.8195209503],"type":"Point"}
}