{
  "type": "Feature",
  "properties": {
    "addr:full":"2/ 1 Barkly St Warragul VIC 3820",
    "addr:housenumber":"/ 1",
    "addr:postcode":"3820",
    "addr:street":"Barkly St",
    "iso:country":"AU",
    "sg:address":"2/ 1 Barkly St",
    "sg:city":"Warragul",
    "sg:classifiers":[
        {
            "category":"Building & Trades",
            "subcategory":"Landscaping Services",
            "type":"Services"
        }
    ],
    "sg:phone":"+61 3 5623 6950",
    "sg:postcode":"3820",
    "sg:province":"VIC",
    "sg:tags":[
        "consultant"
    ],
    "wof:name":"Colin A. Brown and Associates",
    "wof:placetype":"venue"
},
  "geometry": {"coordinates":[145.93287699999999,-38.160683],"type":"Point"}
}