{
  "type": "Feature",
  "properties": {
    "addr:full":"41 Annaville Rd Jensen QLD 4818",
    "addr:housenumber":"41",
    "addr:postcode":"4818",
    "addr:street":"Annaville Rd",
    "iso:country":"AU",
    "sg:address":"41 Annaville Rd",
    "sg:city":"Jensen",
    "sg:classifiers":[
        {
            "category":"Building & Trades",
            "subcategory":"Construction",
            "type":"Services"
        }
    ],
    "sg:phone":"+61 413 269 000",
    "sg:postcode":"4818",
    "sg:province":"QLD",
    "sg:tags":[
        "concrete",
        "contractor"
    ],
    "wof:name":"G & S Hancock Concreting",
    "wof:placetype":"venue"
},
  "geometry": {"coordinates":[146.63467399999999,-19.255915],"type":"Point"}
}