{
  "type": "Feature",
  "properties": {
    "addr:full":"24 Twakurra St Rye VIC 3941",
    "addr:housenumber":"24",
    "addr:postcode":"3941",
    "addr:street":"Twakurra St",
    "iso:country":"AU",
    "sg:address":"24 Twakurra St",
    "sg:city":"Rye",
    "sg:classifiers":[
        {
            "category":"Home & Garden",
            "subcategory":"Household Appliances",
            "type":"Retail Goods"
        }
    ],
    "sg:phone":"+61 428 508 279",
    "sg:postcode":"3941",
    "sg:province":"VIC",
    "sg:tags":[
        "equipment",
        "gas"
    ],
    "wof:name":"Eric's Hydronics",
    "wof:placetype":"venue"
},
  "geometry": {"coordinates":[144.820236206,-38.3854446411],"type":"Point"}
}