{
  "type": "Feature",
  "properties": {
    "addr:full":"2110 Plenty Rd Whittlesea VIC 3757",
    "addr:housenumber":"2110",
    "addr:postcode":"3757",
    "addr:street":"Plenty Rd",
    "iso:country":"AU",
    "sg:address":"2110 Plenty Rd",
    "sg:city":"Whittlesea",
    "sg:classifiers":[
        {
            "category":"Autos & Motor Vehicles",
            "subcategory":"Auto Supplies",
            "type":"Retail Goods"
        }
    ],
    "sg:phone":"+61 3 9716 2019",
    "sg:postcode":"3757",
    "sg:province":"VIC",
    "sg:tags":[
        "part",
        "cycles",
        "accessory"
    ],
    "wof:name":"Whittlesea Motorcycles",
    "wof:placetype":"venue"
},
  "geometry": {"coordinates":[145.10981799999999,-37.544716],"type":"Point"}
}