{
  "type": "Feature",
  "properties": {
    "iso:country":"AU",
    "sg:address":"Suite 5 Level 1, 531 Sandgate Rd",
    "sg:city":"Clayfield",
    "sg:classifiers":[
        {
            "category":"Health Services",
            "subcategory":"Doctor",
            "type":"Services"
        }
    ],
    "sg:phone":"+61 7 3262 7642",
    "sg:postcode":"4011",
    "sg:province":"QLD",
    "sg:tags":[
        "medical",
        "practitioner"
    ],
    "wof:name":"Shine Womens Health & Cosmetic Clinic",
    "wof:placetype":"venue"
},
  "geometry": {"coordinates":[153.050766,-27.42606],"type":"Point"}
}