{
  "type": "Feature",
  "properties": {
    "addr:full":"165 George St Gunnedah NSW 2380",
    "addr:housenumber":"165",
    "addr:postcode":"2380",
    "addr:street":"George St",
    "iso:country":"AU",
    "sg:address":"165 George St",
    "sg:city":"Gunnedah",
    "sg:classifiers":[
        {
            "category":"Shopping",
            "type":"Retail Goods"
        }
    ],
    "sg:phone":"+61 2 6742 1633",
    "sg:postcode":"2380",
    "sg:province":"NSW",
    "sg:tags":[
        "agent",
        "stock"
    ],
    "wof:name":"Carpenter Noel Agencies",
    "wof:placetype":"venue"
},
  "geometry": {"coordinates":[150.25932312,-30.9898529053],"type":"Point"}
}