{
  "type": "Feature",
  "properties": {
    "iso:country":"AU",
    "sg:address":"450 Belmont Ave",
    "sg:city":"Kewdale",
    "sg:classifiers":[
        {
            "category":"Farming",
            "subcategory":"Crops",
            "type":"Manufacturing & Wholesale Goods"
        }
    ],
    "sg:phone":"+61 8 9353 1132",
    "sg:postcode":"6105",
    "sg:province":"WA",
    "sg:tags":[
        "warehousing"
    ],
    "wof:name":"SembCorp Logistics (Australia) Pty Ltd",
    "wof:placetype":"venue"
},
  "geometry": {"coordinates":[115.946403503,-31.9769325256],"type":"Point"}
}