{
  "type": "Feature",
  "properties": {
    "addr:full":"4 Massey St East Bundaberg QLD 4670",
    "addr:housenumber":"4",
    "addr:postcode":"4670",
    "addr:street":"Massey St East",
    "iso:country":"AU",
    "sg:address":"4 Massey St",
    "sg:city":"East Bundaberg",
    "sg:classifiers":[
        {
            "category":"Retail",
            "subcategory":"Repair Shop",
            "type":"Services"
        }
    ],
    "sg:phone":"+61 7 4151 5262",
    "sg:postcode":"4670",
    "sg:province":"QLD",
    "sg:tags":[
        "upholsterer"
    ],
    "wof:name":"Bundaberg Upholstery & Restoration",
    "wof:placetype":"venue"
},
  "geometry": {"coordinates":[152.37075805699999,-24.8528709412],"type":"Point"}
}