{
  "type": "Feature",
  "properties": {
    "iso:country":"AU",
    "sg:address":"Jacksons Rd",
    "sg:city":"Warrenheip",
    "sg:classifiers":[
        {
            "category":"Building & Trades",
            "subcategory":"Cleaning & Sanitation",
            "type":"Services"
        }
    ],
    "sg:phone":"+61 3 5334 7884",
    "sg:postcode":"3352",
    "sg:province":"VIC",
    "sg:tags":[
        "industrial",
        "commercial",
        "contractor"
    ],
    "wof:name":"Right Choice Cleaning Services Pty Ltd",
    "wof:placetype":"venue"
},
  "geometry": {"coordinates":[143.924286,-37.563992],"type":"Point"}
}