{
  "type": "Feature",
  "properties": {
    "iso:country":"AU",
    "sg:address":"Christies Homemaker Centre, 34 Goggs Rd",
    "sg:city":"Jindalee",
    "sg:classifiers":[
        {
            "category":"Communications",
            "subcategory":"Film & Video Production",
            "type":"Services"
        }
    ],
    "sg:phone":"+61 7 3812 0033",
    "sg:postcode":"4074",
    "sg:province":"QLD",
    "sg:tags":[
        "dvd",
        "library"
    ],
    "wof:name":"Network Video Jindalee",
    "wof:placetype":"venue"
},
  "geometry": {"coordinates":[152.948974609,-27.5351352692],"type":"Point"}
}