{
  "type": "Feature",
  "properties": {
    "addr:full":"16 Canning St Bega NSW 2550",
    "addr:housenumber":"16",
    "addr:postcode":"2550",
    "addr:street":"Canning St",
    "iso:country":"AU",
    "sg:address":"16 Canning St",
    "sg:city":"Bega",
    "sg:classifiers":[
        {
            "category":"Health Services",
            "subcategory":"Doctor",
            "type":"Services"
        }
    ],
    "sg:phone":"+61 2 6492 4232",
    "sg:postcode":"2550",
    "sg:province":"NSW",
    "sg:tags":[
        "medical",
        "practitioner"
    ],
    "wof:name":"Den B",
    "wof:placetype":"venue"
},
  "geometry": {"coordinates":[149.84472656200001,-36.6735343933],"type":"Point"}
}