{
  "type": "Feature",
  "properties": {
    "addr:full":"71 Phillips St Esperance WA 6450",
    "addr:housenumber":"71",
    "addr:postcode":"6450",
    "addr:street":"Phillips St",
    "iso:country":"AU",
    "sg:address":"71 Phillips St",
    "sg:city":"Esperance",
    "sg:classifiers":[
        {
            "category":"Deli",
            "type":"Food & Drink"
        }
    ],
    "sg:phone":"+61 8 9071 4622",
    "sg:postcode":"6450",
    "sg:province":"WA",
    "sg:tags":[
        "delicatessen"
    ],
    "wof:name":"West Beach Deli",
    "wof:placetype":"venue"
},
  "geometry": {"coordinates":[121.88130188,-33.8738670349],"type":"Point"}
}