{
  "type": "Feature",
  "properties": {
    "iso:country":"AU",
    "sg:address":"Camp St",
    "sg:city":"Watchem",
    "sg:classifiers":[
        {
            "category":"Shopping",
            "type":"Retail Goods"
        }
    ],
    "sg:phone":"+61 3 5498 1254",
    "sg:postcode":"3482",
    "sg:province":"VIC",
    "sg:tags":[
        "agent",
        "stock"
    ],
    "wof:name":"Merrett R H",
    "wof:placetype":"venue"
},
  "geometry": {"coordinates":[142.85934448200001,-36.1466407776],"type":"Point"}
}