{
  "type": "Feature",
  "properties": {
    "addr:full":"Shp 15 Yamba Shopng Fair Yamba NSW 2464",
    "addr:housenumber":"15",
    "addr:postcode":"2464",
    "iso:country":"AU",
    "sg:address":"Shp 15",
    "sg:city":"Yamba Shopng Fair Yamba",
    "sg:classifiers":[
        {
            "category":"Banks & Credit Unions",
            "subcategory":"Bank",
            "type":"Services"
        }
    ],
    "sg:phone":"+61 2 6646 2663",
    "sg:postcode":"2464",
    "sg:province":"NSW",
    "wof:name":"St.George Bank Limited",
    "wof:placetype":"venue"
},
  "geometry": {"coordinates":[153.33317565900001,-29.4309635162],"type":"Point"}
}