{
  "type": "Feature",
  "properties": {
    "addr:full":"5 Youngingbill Pl Bowral NSW 2576",
    "addr:housenumber":"5",
    "addr:postcode":"2576",
    "addr:street":"Youngingbill Pl",
    "iso:country":"AU",
    "sg:address":"5 Youngingbill Pl",
    "sg:city":"Bowral",
    "sg:classifiers":[
        {
            "category":"Building & Trades",
            "subcategory":"Construction",
            "type":"Services"
        }
    ],
    "sg:phone":"+61 2 4862 4492",
    "sg:postcode":"2576",
    "sg:province":"NSW",
    "sg:tags":[
        "brick",
        "paving"
    ],
    "wof:name":"Createscape",
    "wof:placetype":"venue"
},
  "geometry": {"coordinates":[150.385894775,-34.4550590515],"type":"Point"}
}