{
  "type": "Feature",
  "properties": {
    "addr:full":"160 O.G. Rd Felixstow SA 5070",
    "addr:housenumber":"160",
    "addr:postcode":"5070",
    "addr:street":"O.G. Rd",
    "iso:country":"AU",
    "sg:address":"160 O.G. Rd",
    "sg:city":"Felixstow",
    "sg:classifiers":[
        {
            "category":"Travel",
            "subcategory":"Hostel",
            "type":"Entertainment"
        }
    ],
    "sg:phone":"+61 8 8206 0411",
    "sg:postcode":"5070",
    "sg:province":"SA",
    "sg:tags":[
        "home"
    ],
    "wof:name":"Aldersgate Aged Care",
    "wof:placetype":"venue"
},
  "geometry": {"coordinates":[138.64068603499999,-34.8918533325],"type":"Point"}
}