{
  "type": "Feature",
  "properties": {
    "iso:country":"AU",
    "sg:address":"47 Cumberland St",
    "sg:city":"Cessnock",
    "sg:classifiers":[
        {
            "category":"Education",
            "subcategory":"Kindergarten",
            "type":"Public Place"
        }
    ],
    "sg:phone":"+61 2 4991 1734",
    "sg:postcode":"2325",
    "sg:province":"NSW",
    "sg:tags":[
        "pre-schools"
    ],
    "wof:name":"Cessnock Occasional Child Care Centre",
    "wof:placetype":"venue"
},
  "geometry": {"coordinates":[151.356933594,-32.8364448547],"type":"Point"}
}