{
  "type": "Feature",
  "properties": {
    "addr:full":"78 Terry Rd Box Hill NSW 2765",
    "addr:housenumber":"78",
    "addr:postcode":"2765",
    "addr:street":"Terry Rd",
    "iso:country":"AU",
    "sg:address":"78 Terry Rd",
    "sg:city":"Box Hill",
    "sg:classifiers":[
        {
            "category":"Health Services",
            "subcategory":"Doctor",
            "type":"Services"
        }
    ],
    "sg:phone":"+61 2 9679 1060",
    "sg:postcode":"2765",
    "sg:province":"NSW",
    "sg:tags":[
        "occupational",
        "safety"
    ],
    "wof:name":"Mobility Innovations",
    "wof:placetype":"venue"
},
  "geometry": {"coordinates":[150.904022217,-33.6400184631],"type":"Point"}
}