{
  "type": "Feature",
  "properties": {
    "iso:country":"AU",
    "sg:address":"1 King St",
    "sg:city":"Lorn",
    "sg:classifiers":[
        {
            "category":"Health Services",
            "subcategory":"Health Practitioner",
            "type":"Services"
        }
    ],
    "sg:phone":"+61 2 4933 6970",
    "sg:postcode":"2320",
    "sg:province":"NSW",
    "sg:tags":[
        "psychologist"
    ],
    "wof:name":"De Jong Therese",
    "wof:placetype":"venue"
},
  "geometry": {"coordinates":[151.55926513700001,-32.7289123535],"type":"Point"}
}