{
  "type": "Feature",
  "properties": {
    "iso:country":"AU",
    "sg:address":"873 Kingsford Smith Drv",
    "sg:city":"Eagle Farm",
    "sg:classifiers":[
        {
            "category":"Autos & Motor Vehicles",
            "subcategory":"Auto Supplies",
            "type":"Retail Goods"
        }
    ],
    "sg:phone":"+61 7 3268 4477",
    "sg:postcode":"4009",
    "sg:province":"QLD",
    "sg:tags":[
        "tyre"
    ],
    "wof:name":"Millard Tyre Centres",
    "wof:placetype":"venue"
},
  "geometry": {"coordinates":[153.090011597,-27.4313144684],"type":"Point"}
}