{
  "type": "Feature",
  "properties": {
    "addr:full":"40 Alford St Kingaroy QLD 4610",
    "addr:housenumber":"40",
    "addr:postcode":"4610",
    "addr:street":"Alford St",
    "iso:country":"AU",
    "sg:address":"40 Alford St",
    "sg:city":"Kingaroy",
    "sg:classifiers":[
        {
            "category":"Retail",
            "subcategory":"Auto Repair",
            "type":"Services"
        }
    ],
    "sg:phone":"+61 7 4162 4848",
    "sg:postcode":"4610",
    "sg:province":"QLD",
    "sg:tags":[
        "repairer",
        "motor",
        "engineer"
    ],
    "wof:name":"Mal's Motors",
    "wof:placetype":"venue"
},
  "geometry": {"coordinates":[151.83636474599999,-26.5404663086],"type":"Point"}
}