{
  "type": "Feature",
  "properties": {
    "iso:country":"AU",
    "sg:address":"9 Production Ave",
    "sg:city":"Kogarah",
    "sg:classifiers":[
        {
            "category":"Organizations",
            "subcategory":"Professional Association",
            "type":"Services"
        }
    ],
    "sg:phone":"+61 2 9791 5832",
    "sg:postcode":"2217",
    "sg:province":"NSW",
    "sg:tags":[
        "web",
        "internet"
    ],
    "wof:name":"DR NET# Internet Remedies",
    "wof:placetype":"venue"
},
  "geometry": {"coordinates":[151.137421,-33.978237],"type":"Point"}
}