{
  "type": "Feature",
  "properties": {
    "iso:country":"AU",
    "sg:address":"184 Albany Hwy",
    "sg:city":"Victoria Park",
    "sg:classifiers":[
        {
            "category":"Autos & Motor Vehicles",
            "subcategory":"Automobile Sales",
            "type":"Retail Goods"
        }
    ],
    "sg:phone":"+61 8 9472 3000",
    "sg:postcode":"6100",
    "sg:province":"WA",
    "sg:tags":[
        "car",
        "used"
    ],
    "wof:name":"Cyber Cars",
    "wof:placetype":"venue"
},
  "geometry": {"coordinates":[115.893882752,-31.9715270996],"type":"Point"}
}