{
  "type": "Feature",
  "properties": {
    "addr:full":"6 Wilray St Grovedale VIC 3216",
    "addr:housenumber":"6",
    "addr:postcode":"3216",
    "addr:street":"Wilray St",
    "iso:country":"AU",
    "sg:address":"6 Wilray St",
    "sg:city":"Grovedale",
    "sg:classifiers":[
        {
            "category":"Home & Garden",
            "subcategory":"Carpets & Floor Coverings",
            "type":"Retail Goods"
        }
    ],
    "sg:phone":"+61 3 5241 1243",
    "sg:postcode":"3216",
    "sg:province":"VIC",
    "sg:tags":[
        "wholesaler",
        "worsted",
        "product",
        "woollen",
        "mfrs"
    ],
    "wof:name":"O E Textiles International",
    "wof:placetype":"venue"
},
  "geometry": {"coordinates":[144.34687805199999,-38.195514679],"type":"Point"}
}