{
  "type": "Feature",
  "properties": {
    "addr:full":"RMB 116 Nundle Rd Nemingha NSW 2340",
    "addr:postcode":"2340",
    "addr:street":"Nundle Rd",
    "iso:country":"AU",
    "sg:address":"RMB 116 Nundle Rd",
    "sg:city":"Nemingha",
    "sg:classifiers":[
        {
            "category":"Farming",
            "subcategory":"Farm",
            "type":"Manufacturing & Wholesale Goods"
        }
    ],
    "sg:phone":"+61 2 6760 9261",
    "sg:postcode":"2340",
    "sg:province":"NSW",
    "sg:tags":[
        "farmer"
    ],
    "wof:name":"Jacobs A H & Sons",
    "wof:placetype":"venue"
},
  "geometry": {"coordinates":[150.999710083,-31.128036499],"type":"Point"}
}