{
  "type": "Feature",
  "properties": {
    "addr:full":"1060 South Rd Edwardstown SA 5039",
    "addr:housenumber":"1060",
    "addr:postcode":"5039",
    "addr:street":"South Rd",
    "iso:country":"AU",
    "sg:address":"1060 South Rd",
    "sg:city":"Edwardstown",
    "sg:classifiers":[
        {
            "category":"Professional",
            "subcategory":"Accounting & Tax Preparation",
            "type":"Services"
        }
    ],
    "sg:phone":"+61 8 8374 0788",
    "sg:postcode":"5039",
    "sg:province":"SA",
    "sg:tags":[
        "consultant",
        "taxation"
    ],
    "wof:name":"I.T.P. The Income Tax Professionals",
    "wof:placetype":"venue"
},
  "geometry": {"coordinates":[138.57432556099999,-34.9881248474],"type":"Point"}
}