{
  "type": "Feature",
  "properties": {
    "iso:country":"AU",
    "sg:address":"Cnr Poinciana & Mango Sts",
    "sg:city":"Kununurra",
    "sg:classifiers":[
        {
            "category":"Autos & Motor Vehicles",
            "subcategory":"Auto Supplies",
            "type":"Retail Goods"
        }
    ],
    "sg:phone":"+61 8 9169 1150",
    "sg:postcode":"6743",
    "sg:province":"WA",
    "sg:tags":[
        "wheel",
        "four",
        "equipment",
        "drive",
        "accessory"
    ],
    "wof:name":"Kununurra Four Wheel Drive Spares",
    "wof:placetype":"venue"
},
  "geometry": {"coordinates":[128.733322144,-15.7789449692],"type":"Point"}
}