{
  "type": "Feature",
  "properties": {
    "addr:full":"Lesmurdie Primary School 49 Sanderson Rd Lesmurdie WA 6076",
    "addr:housenumber":"49",
    "addr:postcode":"6076",
    "addr:street":"Sanderson Rd",
    "iso:country":"AU",
    "sg:address":"Lesmurdie Primary School 49 Sanderson Rd",
    "sg:city":"Lesmurdie",
    "sg:classifiers":[
        {
            "category":"Education",
            "subcategory":"School",
            "type":"Public Place"
        }
    ],
    "sg:phone":"+61 8 9291 9855",
    "sg:postcode":"6076",
    "sg:province":"WA",
    "sg:tags":[
        "state",
        "except",
        "nsw"
    ],
    "wof:name":"Schools Government (Public)",
    "wof:placetype":"venue"
},
  "geometry": {"coordinates":[116.04596710200001,-32.0041618347],"type":"Point"}
}