{
  "type": "Feature",
  "properties": {
    "addr:full":"121 Ingham Rd Townsville QLD 4810",
    "addr:housenumber":"121",
    "addr:postcode":"4810",
    "addr:street":"Ingham Rd",
    "iso:country":"AU",
    "sg:address":"121 Ingham Rd",
    "sg:city":"Townsville",
    "sg:classifiers":[
        {
            "category":"Organizations",
            "subcategory":"Professional Association",
            "type":"Services"
        }
    ],
    "sg:phone":"+61 1300 654 699",
    "sg:postcode":"4810",
    "sg:province":"QLD",
    "sg:tags":[
        "web",
        "internet"
    ],
    "wof:name":"ABC Web Design",
    "wof:placetype":"venue"
},
  "geometry": {"coordinates":[146.794861,-19.267508],"type":"Point"}
}