{
  "type": "Feature",
  "properties": {
    "addr:full":"U1/ 341 Oxford St Leederville WA 6007",
    "addr:housenumber":"341",
    "addr:postcode":"6007",
    "addr:street":"U1 /;Oxford St",
    "iso:country":"AU",
    "sg:address":"U1/ 341 Oxford St",
    "sg:city":"Leederville",
    "sg:classifiers":[
        {
            "category":"Professional",
            "subcategory":"Engineering",
            "type":"Services"
        }
    ],
    "sg:phone":"+61 8 9444 9990",
    "sg:postcode":"6007",
    "sg:province":"WA",
    "sg:tags":[
        "civil",
        "engineer"
    ],
    "wof:name":"Delta Civil WA",
    "wof:placetype":"venue"
},
  "geometry": {"coordinates":[115.841072083,-31.9272499084],"type":"Point"}
}