{
  "type": "Feature",
  "properties": {
    "addr:full":"5 Waratah Rd Engadine NSW 2233",
    "addr:housenumber":"5",
    "addr:postcode":"2233",
    "addr:street":"Waratah Rd",
    "iso:country":"AU",
    "sg:address":"5 Waratah Rd",
    "sg:city":"Engadine",
    "sg:classifiers":[
        {
            "category":"Professional",
            "subcategory":"Management & Consulting",
            "type":"Services"
        }
    ],
    "sg:phone":"+61 2 9520 2505",
    "sg:postcode":"2233",
    "sg:province":"NSW",
    "sg:tags":[
        "project"
    ],
    "wof:name":"C Rivera & Company Pty Ltd",
    "wof:placetype":"venue"
},
  "geometry": {"coordinates":[151.01234435999999,-34.0641479492],"type":"Point"}
}