{
  "type": "Feature",
  "properties": {
    "addr:full":"8 Netherway St Camberwell VIC 3124",
    "addr:housenumber":"8",
    "addr:postcode":"3124",
    "addr:street":"Netherway St",
    "iso:country":"AU",
    "sg:address":"8 Netherway St",
    "sg:city":"Camberwell",
    "sg:classifiers":[
        {
            "category":"Professional",
            "subcategory":"Management & Consulting",
            "type":"Services"
        }
    ],
    "sg:phone":"+61 3 8810 4835",
    "sg:postcode":"3124",
    "sg:province":"VIC",
    "sg:tags":[
        "consultant"
    ],
    "wof:name":"Sebire & Associates",
    "wof:placetype":"venue"
},
  "geometry": {"coordinates":[145.08953857399999,-37.8412971497],"type":"Point"}
}