{
  "type": "Feature",
  "properties": {
    "addr:full":"92 Osborne Ave Mt Waverley VIC 3149",
    "addr:housenumber":"92",
    "addr:postcode":"3149",
    "addr:street":"Osborne Ave Mt",
    "iso:country":"AU",
    "sg:address":"92 Osborne Ave",
    "sg:city":"Mt Waverley",
    "sg:classifiers":[
        {
            "category":"Building & Trades",
            "subcategory":"Construction",
            "type":"Services"
        }
    ],
    "sg:phone":"+61 412 544 232",
    "sg:postcode":"3149",
    "sg:province":"VIC",
    "sg:tags":[
        "tennis court",
        "repair"
    ],
    "wof:name":"Dargan P & J",
    "wof:placetype":"venue"
},
  "geometry": {"coordinates":[145.11227417000001,-37.8937110901],"type":"Point"}
}