{
  "type": "Feature",
  "properties": {
    "iso:country":"AU",
    "sg:address":"184 Hoskins St",
    "sg:city":"Temora",
    "sg:classifiers":[
        {
            "category":"Shopping",
            "type":"Retail Goods"
        }
    ],
    "sg:phone":"+61 2 6977 1710",
    "sg:postcode":"2666",
    "sg:province":"NSW",
    "sg:tags":[
        "agent",
        "stock"
    ],
    "wof:name":"Gersbach Firman",
    "wof:placetype":"venue"
},
  "geometry": {"coordinates":[147.533599853,-34.4467430115],"type":"Point"}
}