{
  "type": "Feature",
  "properties": {
    "addr:full":"8 Simmons St Wagga Wagga NSW 2650",
    "addr:housenumber":"8",
    "addr:postcode":"2650",
    "addr:street":"Simmons St",
    "iso:country":"AU",
    "sg:address":"8 Simmons St",
    "sg:city":"Wagga Wagga",
    "sg:classifiers":[
        {
            "category":"Health Services",
            "subcategory":"Doctor",
            "type":"Services"
        }
    ],
    "sg:phone":"+61 2 6971 9101",
    "sg:postcode":"2650",
    "sg:province":"NSW",
    "sg:tags":[
        "medical",
        "practitioner"
    ],
    "wof:name":"Knowles Phillip Dr",
    "wof:placetype":"venue"
},
  "geometry": {"coordinates":[147.365600586,-35.1089820862],"type":"Point"}
}