{
  "type": "Feature",
  "properties": {
    "addr:full":"Shop 9, Wingham Arcade 54 Bent St Wingham NSW 2429",
    "addr:housenumber":"shop 9;54",
    "addr:postcode":"2429",
    "addr:street":"Wingham Arcade;Bent St",
    "iso:country":"AU",
    "sg:address":"Shop 9, Wingham Arcade 54 Bent St",
    "sg:city":"Wingham",
    "sg:classifiers":[
        {
            "category":"Personal",
            "subcategory":"Massage",
            "type":"Services"
        }
    ],
    "sg:phone":"+61 2 6557 0844",
    "sg:postcode":"2429",
    "sg:province":"NSW",
    "sg:tags":[
        "therapy"
    ],
    "wof:name":"Rod Robinson",
    "wof:placetype":"venue"
},
  "geometry": {"coordinates":[152.374054,-31.869213],"type":"Point"}
}