{
  "type": "Feature",
  "properties": {
    "addr:full":"29 Peachtree Rd Penrith NSW 2750",
    "addr:housenumber":"29",
    "addr:postcode":"2750",
    "addr:street":"Peachtree Rd",
    "iso:country":"AU",
    "sg:address":"29 Peachtree Rd",
    "sg:city":"Penrith",
    "sg:classifiers":[
        {
            "category":"Home & Garden",
            "subcategory":"Building Materials",
            "type":"Retail Goods"
        }
    ],
    "sg:phone":"+61 2 4722 8686",
    "sg:postcode":"2750",
    "sg:province":"NSW",
    "sg:tags":[
        "ventilating",
        "equipment",
        "system"
    ],
    "wof:name":"westaflex (Aust) P/L",
    "wof:placetype":"venue"
},
  "geometry": {"coordinates":[150.97419738799999,-33.7886352539],"type":"Point"}
}