{
  "type": "Feature",
  "properties": {
    "iso:country":"AU",
    "sg:address":"31 Hoskins Ave",
    "sg:city":"Warrawong",
    "sg:classifiers":[
        {
            "category":"Utilities",
            "type":"Services"
        }
    ],
    "sg:phone":"+61 2 4276 2488",
    "sg:postcode":"2502",
    "sg:province":"NSW",
    "sg:tags":[
        "equipment",
        "towing"
    ],
    "wof:name":"South Coast Tow Bars",
    "wof:placetype":"venue"
},
  "geometry": {"coordinates":[150.889725,-34.490181],"type":"Point"}
}