{
  "type": "Feature",
  "properties": {
    "addr:full":"20 William St Gatton QLD 4343",
    "addr:housenumber":"20",
    "addr:postcode":"4343",
    "addr:street":"William St",
    "iso:country":"AU",
    "sg:address":"20 William St",
    "sg:city":"Gatton",
    "sg:classifiers":[
        {
            "category":"Banks & Credit Unions",
            "subcategory":"Investment Brokerage",
            "type":"Services"
        }
    ],
    "sg:phone":"+61 7 5462 4066",
    "sg:postcode":"4343",
    "sg:province":"QLD",
    "sg:tags":[
        "finance",
        "broker"
    ],
    "wof:name":"Northern City Finance Lockyer & Downs",
    "wof:placetype":"venue"
},
  "geometry": {"coordinates":[152.278274536,-27.5595207214],"type":"Point"}
}