{
  "type": "Feature",
  "properties": {
    "addr:full":"5 Lindfield Ave Lindfield NSW 2070",
    "addr:housenumber":"5",
    "addr:postcode":"2070",
    "addr:street":"Lindfield Ave",
    "iso:country":"AU",
    "sg:address":"5 Lindfield Ave",
    "sg:city":"Lindfield",
    "sg:classifiers":[
        {
            "category":"Shopping",
            "subcategory":"Clothing, Apparel, & Fashions",
            "type":"Retail Goods"
        }
    ],
    "sg:phone":"+61 2 9416 2415",
    "sg:postcode":"2070",
    "sg:province":"NSW",
    "sg:tags":[
        "lingerie",
        "hosiery",
        "sleepwear"
    ],
    "wof:name":"Pam's Place",
    "wof:placetype":"venue"
},
  "geometry": {"coordinates":[151.16961669899999,-33.7752685547],"type":"Point"}
}