{
  "type": "Feature",
  "properties": {
    "addr:full":"232 Mary St Gympie QLD 4570",
    "addr:housenumber":"232",
    "addr:postcode":"4570",
    "addr:street":"Mary St",
    "iso:country":"AU",
    "sg:address":"232 Mary St",
    "sg:city":"Gympie",
    "sg:classifiers":[
        {
            "category":"Professional",
            "subcategory":"Accounting & Tax Preparation",
            "type":"Services"
        }
    ],
    "sg:phone":"+61 7 5483 6701",
    "sg:postcode":"4570",
    "sg:province":"QLD",
    "sg:tags":[
        "accountant",
        "auditor"
    ],
    "wof:name":"Shahid Khan",
    "wof:placetype":"venue"
},
  "geometry": {"coordinates":[152.658935547,-26.1888217926],"type":"Point"}
}