{
  "type": "Feature",
  "properties": {
    "addr:full":"Shop 6 Loveridge Wlk Berwick VIC 3806",
    "addr:housenumber":"shop 6",
    "addr:postcode":"3806",
    "addr:street":"Loveridge Wlk",
    "iso:country":"AU",
    "sg:address":"Shop 6 Loveridge Wlk",
    "sg:city":"Berwick",
    "sg:classifiers":[
        {
            "category":"Personal",
            "subcategory":"Beauty Salon",
            "type":"Services"
        }
    ],
    "sg:phone":"+61 3 9707 4747",
    "sg:postcode":"3806",
    "sg:province":"VIC",
    "sg:tags":[
        "hairdresser"
    ],
    "wof:name":"It's Individual Hair Design",
    "wof:placetype":"venue"
},
  "geometry": {"coordinates":[145.34602355999999,-38.0307312012],"type":"Point"}
}