{
  "type": "Feature",
  "properties": {
    "addr:full":"PO Box 375 Serpentine WA 6125",
    "addr:postcode":"6125",
    "iso:country":"AU",
    "sg:address":"PO Box 375",
    "sg:city":"Serpentine",
    "sg:classifiers":[
        {
            "category":"Home & Garden",
            "subcategory":"Building Materials",
            "type":"Retail Goods"
        }
    ],
    "sg:phone":"+61 404 176 875",
    "sg:postcode":"6125",
    "sg:province":"WA",
    "sg:tags":[
        "concrete",
        "gutter",
        "kerb"
    ],
    "wof:name":"Kwik Kerb Serpentine",
    "wof:placetype":"venue"
},
  "geometry": {"coordinates":[115.852149963,-32.362663269],"type":"Point"}
}