{
  "type": "Feature",
  "properties": {
    "addr:full":"6 Chaucer St Hamilton VIC 3300",
    "addr:housenumber":"6",
    "addr:postcode":"3300",
    "addr:street":"Chaucer St",
    "iso:country":"AU",
    "sg:address":"6 Chaucer St",
    "sg:city":"Hamilton",
    "sg:classifiers":[
        {
            "category":"Health Services",
            "subcategory":"Health Practitioner",
            "type":"Services"
        }
    ],
    "sg:phone":"+61 429 351 320",
    "sg:postcode":"3300",
    "sg:province":"VIC",
    "sg:tags":[
        "physiotherapist"
    ],
    "wof:name":"Physio Freedom",
    "wof:placetype":"venue"
},
  "geometry": {"coordinates":[142.02331543,-37.7393112183],"type":"Point"}
}