{
  "type": "Feature",
  "properties": {
    "addr:full":"34 Sailfish Drv Mountain Creek QLD 4557",
    "addr:housenumber":"34",
    "addr:postcode":"4557",
    "addr:street":"Sailfish Drv",
    "iso:country":"AU",
    "sg:address":"34 Sailfish Drv",
    "sg:city":"Mountain Creek",
    "sg:classifiers":[
        {
            "category":"Personal",
            "subcategory":"Massage",
            "type":"Services"
        }
    ],
    "sg:phone":"+61 7 5444 0008",
    "sg:postcode":"4557",
    "sg:province":"QLD",
    "sg:tags":[
        "therapy"
    ],
    "wof:name":"Soothing The Way",
    "wof:placetype":"venue"
},
  "geometry": {"coordinates":[153.08982849099999,-26.7054309845],"type":"Point"}
}