{
  "type": "Feature",
  "properties": {
    "iso:country":"AU",
    "sg:address":"42 Baldwin Ave",
    "sg:city":"Asquith",
    "sg:classifiers":[
        {
            "category":"Retail",
            "subcategory":"Repair Shop",
            "type":"Services"
        }
    ],
    "sg:phone":"+61 2 9477 2238",
    "sg:postcode":"2077",
    "sg:province":"NSW",
    "sg:tags":[
        "upholsterer"
    ],
    "wof:name":"Asquith Upholstery",
    "wof:placetype":"venue"
},
  "geometry": {"coordinates":[151.11419677699999,-33.6889038086],"type":"Point"}
}