{
  "type": "Feature",
  "properties": {
    "addr:full":"Shp4/ 400 Pound Rd Hampton Park VIC 3976",
    "addr:housenumber":"400",
    "addr:postcode":"3976",
    "addr:street":"Pound Rd",
    "iso:country":"AU",
    "sg:address":"Shp4/ 400 Pound Rd",
    "sg:city":"Hampton Park",
    "sg:classifiers":[
        {
            "category":"Personal",
            "subcategory":"Beauty Salon",
            "type":"Services"
        }
    ],
    "sg:phone":"+61 3 9799 8528",
    "sg:postcode":"3976",
    "sg:province":"VIC",
    "sg:tags":[
        "hairdresser"
    ],
    "wof:name":"Vamp Hair",
    "wof:placetype":"venue"
},
  "geometry": {"coordinates":[145.28262329099999,-38.032535553],"type":"Point"}
}