{
  "type": "Feature",
  "properties": {
    "addr:full":"18c Louise Ave Ingleburn NSW 2565",
    "addr:housenumber":"18c",
    "addr:postcode":"2565",
    "addr:street":"Louise Ave",
    "iso:country":"AU",
    "sg:address":"18c Louise Ave",
    "sg:city":"Ingleburn",
    "sg:classifiers":[
        {
            "category":"Building & Trades",
            "subcategory":"Cleaning & Sanitation",
            "type":"Services"
        }
    ],
    "sg:phone":"+61 423 834 683",
    "sg:postcode":"2565",
    "sg:province":"NSW",
    "sg:tags":[
        "commercial",
        "maintenance"
    ],
    "wof:name":"M J & S Building Services Pty Ltd",
    "wof:placetype":"venue"
},
  "geometry": {"coordinates":[150.86581420900001,-33.9952201843],"type":"Point"}
}