{
  "type": "Feature",
  "properties": {
    "iso:country":"AU",
    "sg:address":"0 Bishop Rd",
    "sg:city":"Beachmere",
    "sg:classifiers":[
        {
            "category":"Home & Garden",
            "subcategory":"Garden Supply",
            "type":"Retail Goods"
        }
    ],
    "sg:phone":"+61 7 3211 3939",
    "sg:postcode":"4510",
    "sg:province":"QLD",
    "sg:tags":[
        "turf",
        "lawn"
    ],
    "wof:name":"Australian Wholesale Turf Supplies",
    "wof:placetype":"venue"
},
  "geometry": {"coordinates":[153.05244400000001,-27.128777],"type":"Point"}
}