{
  "type": "Feature",
  "properties": {
    "addr:full":"41 High St Longford TAS 7301",
    "addr:housenumber":"41",
    "addr:postcode":"7301",
    "addr:street":"High St",
    "iso:country":"AU",
    "sg:address":"41 High St",
    "sg:city":"Longford",
    "sg:classifiers":[
        {
            "category":"Retail",
            "subcategory":"Auto Repair",
            "type":"Services"
        }
    ],
    "sg:phone":"+61 3 6391 1325",
    "sg:postcode":"7301",
    "sg:province":"TAS",
    "sg:tags":[
        "repairer",
        "motor",
        "engineer"
    ],
    "wof:name":"Mathew Smith Mechanical Repairs",
    "wof:placetype":"venue"
},
  "geometry": {"coordinates":[147.11502100000001,-41.597336],"type":"Point"}
}