{
  "type": "Feature",
  "properties": {
    "addr:full":"Level 15/ 123 Queen St Melbourne VIC 3000",
    "addr:housenumber":"/ 123",
    "addr:postcode":"3000",
    "addr:street":"Queen St",
    "iso:country":"AU",
    "sg:address":"Level 15/ 123 Queen St",
    "sg:city":"Melbourne",
    "sg:classifiers":[
        {
            "category":"Bars & Pubs",
            "subcategory":"Wine Bar",
            "type":"Food & Drink"
        }
    ],
    "sg:phone":"+61 3 8801 2720",
    "sg:postcode":"3000",
    "sg:province":"VIC",
    "wof:name":"Blue Diamond Social Salon And Cabaret",
    "wof:placetype":"venue"
},
  "geometry": {"coordinates":[144.96087646500001,-37.8156929016],"type":"Point"}
}