{
  "type": "Feature",
  "properties": {
    "addr:full":"129 Auburn Rd Hawthorn VIC 3122",
    "addr:housenumber":"129",
    "addr:postcode":"3122",
    "addr:street":"Auburn Rd",
    "iso:country":"AU",
    "sg:address":"129 Auburn Rd",
    "sg:city":"Hawthorn",
    "sg:classifiers":[
        {
            "category":"Banks & Credit Unions",
            "subcategory":"Financial Services",
            "type":"Services"
        }
    ],
    "sg:phone":"+61 3 9882 8422",
    "sg:postcode":"3122",
    "sg:province":"VIC",
    "sg:tags":[
        "financier"
    ],
    "wof:name":"Kanebridge Finance Melbourne Pty Ltd",
    "wof:placetype":"venue"
},
  "geometry": {"coordinates":[145.04185485799999,-37.8388137817],"type":"Point"}
}