{
  "type": "Feature",
  "properties": {
    "iso:country":"AU",
    "sg:address":"10- 12 Birdwood Ave",
    "sg:city":"Norlane",
    "sg:classifiers":[
        {
            "category":"Structure",
            "subcategory":"Office Building",
            "type":"Public Place"
        }
    ],
    "sg:phone":"+61 418 520 804",
    "sg:postcode":"3214",
    "sg:province":"VIC",
    "sg:tags":[
        "tie",
        "concrete",
        "formwork",
        "form",
        "accessory"
    ],
    "wof:name":"J & T Mullahy Company Pty Ltd",
    "wof:placetype":"venue"
},
  "geometry": {"coordinates":[144.35272216800001,-38.1006584167],"type":"Point"}
}