{
  "type": "Feature",
  "properties": {
    "addr:full":"Suite 601 - Level 6 243-249 Coward St Mascot NSW 2020",
    "addr:housenumber":"601 level 6",
    "addr:postcode":"243-249;2020",
    "addr:street":"St",
    "iso:country":"AU",
    "sg:address":"Suite 601 - Level 6 243-249 Coward St",
    "sg:city":"Mascot",
    "sg:classifiers":[
        {
            "category":"Organizations",
            "subcategory":"Labor Organization",
            "type":"Services"
        }
    ],
    "sg:phone":"+61 2 8307 7777",
    "sg:postcode":"2020",
    "sg:province":"NSW",
    "sg:tags":[
        "union"
    ],
    "wof:name":"Australian & International Pilots Association",
    "wof:placetype":"venue"
},
  "geometry": {"coordinates":[151.184524536,-33.9239768982],"type":"Point"}
}