{
  "type": "Feature",
  "properties": {
    "iso:country":"AU",
    "sg:address":"85 Main St",
    "sg:city":"Bridport",
    "sg:classifiers":[
        {
            "category":"Health Services",
            "subcategory":"Health Practitioner",
            "type":"Services"
        }
    ],
    "sg:phone":"+61 3 6356 0006",
    "sg:postcode":"7262",
    "sg:province":"TAS",
    "sg:tags":[
        "physiotherapist"
    ],
    "wof:name":"No Payne Physiotherapy",
    "wof:placetype":"venue"
},
  "geometry": {"coordinates":[147.402496,-41.012123],"type":"Point"}
}