{
  "type": "Feature",
  "properties": {
    "addr:full":"Shop 5054 Westfield Shoppingtown Parramatta NSW 2150",
    "addr:housenumber":"5054;shoppingtown",
    "addr:postcode":"2150",
    "addr:street":"Westfield",
    "iso:country":"AU",
    "sg:address":"Shop 5054 Westfield Shoppingtown",
    "sg:city":"Parramatta",
    "sg:classifiers":[
        {
            "category":"Fast Food",
            "type":"Food & Drink"
        }
    ],
    "sg:phone":"+61 2 9687 2293",
    "sg:postcode":"2150",
    "sg:province":"NSW",
    "sg:tags":[
        "away",
        "take"
    ],
    "wof:name":"Oporto Portugese Style Chicken",
    "wof:placetype":"venue"
},
  "geometry": {"coordinates":[151.00227355999999,-33.8176116943],"type":"Point"}
}