{
  "type": "Feature",
  "properties": {
    "addr:full":"129 A Hakone Rd Woongarrah NSW 2259",
    "addr:housenumber":"129 a",
    "addr:postcode":"2259",
    "addr:street":"Hakone Rd",
    "iso:country":"AU",
    "sg:address":"129 A Hakone Rd",
    "sg:city":"Woongarrah",
    "sg:classifiers":[
        {
            "category":"Building & Trades",
            "subcategory":"Pest Control",
            "type":"Services"
        }
    ],
    "sg:phone":"+61 439 411 448",
    "sg:postcode":"2259",
    "sg:province":"NSW",
    "sg:tags":[
        "horse",
        "transport"
    ],
    "wof:name":"Sundowner Lodge",
    "wof:placetype":"venue"
},
  "geometry": {"coordinates":[151.48895263700001,-33.2387962341],"type":"Point"}
}