{
  "type": "Feature",
  "properties": {
    "addr:full":"Cnr Macquarie & Murray Sts Hobart TAS 7000",
    "addr:postcode":"7000",
    "iso:country":"AU",
    "sg:address":"Cnr Macquarie & Murray Sts",
    "sg:city":"Hobart",
    "sg:classifiers":[
        {
            "category":"Banks & Credit Unions",
            "subcategory":"Financial Services",
            "type":"Services"
        }
    ],
    "sg:phone":"+61 3 6214 0688",
    "sg:postcode":"7000",
    "sg:province":"TAS",
    "sg:tags":[
        "loan",
        "finance",
        "mortgage"
    ],
    "wof:name":"Tasmania Finance",
    "wof:placetype":"venue"
},
  "geometry": {"coordinates":[147.32818603499999,-42.8843154907],"type":"Point"}
}