{
  "type": "Feature",
  "properties": {
    "iso:country":"AU",
    "sg:address":"89 Gow St",
    "sg:city":"Padstow",
    "sg:classifiers":[
        {
            "category":"Shopping",
            "subcategory":"Party Supplies",
            "type":"Retail Goods"
        }
    ],
    "sg:phone":"+61 2 9796 2011",
    "sg:postcode":"2211",
    "sg:province":"NSW",
    "sg:tags":[
        "equipment",
        "metal",
        "spraying"
    ],
    "wof:name":"Metco Thermal Spray Technology",
    "wof:placetype":"venue"
},
  "geometry": {"coordinates":[151.030487,-33.937115],"type":"Point"}
}