{
  "type": "Feature",
  "properties": {
    "addr:full":"26- 28 Glassford Rd Kewdale WA 6105",
    "addr:housenumber":"28",
    "addr:postcode":"6105",
    "addr:street":"Glassford Rd",
    "iso:country":"AU",
    "sg:address":"26- 28 Glassford Rd",
    "sg:city":"Kewdale",
    "sg:classifiers":[
        {
            "category":"Wholesale",
            "subcategory":"Auto Parts",
            "type":"Manufacturing & Wholesale Goods"
        }
    ],
    "sg:phone":"+61 8 9353 1755",
    "sg:postcode":"6105",
    "sg:province":"WA",
    "sg:tags":[
        "tyre"
    ],
    "wof:name":"Tyremaster (Wholesale) Pty Ltd",
    "wof:placetype":"venue"
},
  "geometry": {"coordinates":[115.956993103,-31.9707565308],"type":"Point"}
}