{
  "type": "Feature",
  "properties": {
    "iso:country":"AU",
    "sg:address":"64 Guthrie St",
    "sg:city":"Osborne Park",
    "sg:classifiers":[
        {
            "category":"Retail",
            "subcategory":"Auto Rental",
            "type":"Services"
        }
    ],
    "sg:phone":"+61 8 9447 7399",
    "sg:postcode":"6017",
    "sg:province":"WA",
    "sg:tags":[
        "car",
        "wedding"
    ],
    "wof:name":"Manhattan Limousine Hire",
    "wof:placetype":"venue"
},
  "geometry": {"coordinates":[115.81439209,-31.9048404694],"type":"Point"}
}