{
  "type": "Feature",
  "properties": {
    "iso:country":"AU",
    "sg:address":"107 Fitzgerald Rd",
    "sg:city":"Laverton North",
    "sg:classifiers":[
        {
            "category":"Transit Center",
            "subcategory":"Freight",
            "type":"Transportation"
        }
    ],
    "sg:phone":"+61 3 9931 1132",
    "sg:postcode":"3026",
    "sg:province":"VIC",
    "sg:tags":[
        "forklift",
        "truck"
    ],
    "wof:name":"Ashi Hire Pty Ltd",
    "wof:placetype":"venue"
},
  "geometry": {"coordinates":[144.786545,-37.822041],"type":"Point"}
}