{
  "type": "Feature",
  "properties": {
    "addr:full":"Pope St Geraldton WA 6530",
    "addr:postcode":"6530",
    "addr:street":"Pope St",
    "iso:country":"AU",
    "sg:address":"Pope St",
    "sg:city":"Geraldton",
    "sg:classifiers":[
        {
            "category":"Building & Trades",
            "subcategory":"Construction",
            "type":"Services"
        }
    ],
    "sg:phone":"+61 407 300 221",
    "sg:postcode":"6530",
    "sg:province":"WA",
    "sg:tags":[
        "earth",
        "excavating",
        "moving",
        "contractor"
    ],
    "wof:name":"Geraldton Mini Earthmovers",
    "wof:placetype":"venue"
},
  "geometry": {"coordinates":[114.62223815900001,-28.7549915314],"type":"Point"}
}