{
  "type": "Feature",
  "properties": {
    "addr:full":"36 Holland St Thebarton SA 5031",
    "addr:housenumber":"36",
    "addr:postcode":"5031",
    "addr:street":"Holland St",
    "iso:country":"AU",
    "sg:address":"36 Holland St",
    "sg:city":"Thebarton",
    "sg:classifiers":[
        {
            "category":"Wholesale",
            "subcategory":"Machinery & Supplies",
            "type":"Manufacturing & Wholesale Goods"
        }
    ],
    "sg:phone":"+61 8 8234 7955",
    "sg:postcode":"5031",
    "sg:province":"SA",
    "sg:tags":[
        "equipment",
        "laboratory"
    ],
    "sg:website":"http://www.adelab.com.au",
    "wof:name":"Adelab Scientific",
    "wof:placetype":"venue"
},
  "geometry": {"coordinates":[138.57415771500001,-34.9126815796],"type":"Point"}
}