{
  "type": "Feature",
  "properties": {
    "addr:full":"24 Sinclair Crs Seymour VIC 3660",
    "addr:housenumber":"24",
    "addr:postcode":"3660",
    "addr:street":"Sinclair Crs",
    "iso:country":"AU",
    "sg:address":"24 Sinclair Crs",
    "sg:city":"Seymour",
    "sg:classifiers":[
        {
            "category":"Building & Trades",
            "subcategory":"Construction",
            "type":"Services"
        }
    ],
    "sg:phone":"+61 431 805 523",
    "sg:postcode":"3660",
    "sg:province":"VIC",
    "sg:tags":[
        "renovation",
        "alterations",
        "extension",
        "contractor"
    ],
    "wof:name":"A & A Mulvey Constructions",
    "wof:placetype":"venue"
},
  "geometry": {"coordinates":[145.14083862300001,-37.0149497986],"type":"Point"}
}