{
  "type": "Feature",
  "properties": {
    "iso:country":"AU",
    "sg:address":"Cnr University Way & Scholars Drv",
    "sg:city":"Sippy Downs",
    "sg:classifiers":[
        {
            "category":"Real Estate",
            "subcategory":"Developer",
            "type":"Services"
        }
    ],
    "sg:phone":"+61 7 5476 9422",
    "sg:postcode":"4556",
    "sg:province":"QLD",
    "sg:tags":[
        "development"
    ],
    "wof:name":"Chancellor Park Estate",
    "wof:placetype":"venue"
},
  "geometry": {"coordinates":[153.05116272000001,-26.7169647217],"type":"Point"}
}