{
  "type": "Feature",
  "properties": {
    "iso:country":"AU",
    "sg:address":"20 Amiens Ave",
    "sg:city":"Glenorchy",
    "sg:classifiers":[
        {
            "category":"Real Estate",
            "subcategory":"Architect",
            "type":"Services"
        }
    ],
    "sg:phone":"+61 3 6223 3866",
    "sg:postcode":"7010",
    "sg:province":"TAS",
    "wof:name":"Pyefinch Jonathan",
    "wof:placetype":"venue"
},
  "geometry": {"coordinates":[147.286087036,-42.8376731873],"type":"Point"}
}