{
  "type": "Feature",
  "properties": {
    "addr:full":"2692d Princes Hwy Wandandian NSW 2540",
    "addr:housenumber":"2692d",
    "addr:postcode":"2540",
    "addr:street":"Princes Hwy",
    "iso:country":"AU",
    "sg:address":"2692d Princes Hwy",
    "sg:city":"Wandandian",
    "sg:classifiers":[
        {
            "category":"Recreation",
            "subcategory":"Fishing",
            "type":"Entertainment"
        }
    ],
    "sg:phone":"+61 2 4443 6091",
    "sg:postcode":"2540",
    "sg:province":"NSW",
    "sg:tags":[
        "tackle"
    ],
    "wof:name":"Coastal Angler",
    "wof:placetype":"venue"
},
  "geometry": {"coordinates":[150.509567261,-35.0892715454],"type":"Point"}
}