{
  "type": "Feature",
  "properties": {
    "addr:full":"35- 37 Wellington St St Kilda VIC 3182",
    "addr:housenumber":"37",
    "addr:postcode":"3182",
    "addr:street":"Wellington St",
    "iso:country":"AU",
    "sg:address":"35- 37 Wellington St",
    "sg:city":"St Kilda",
    "sg:classifiers":[
        {
            "category":"Professional",
            "subcategory":"Computer Services",
            "type":"Services"
        }
    ],
    "sg:phone":"+61 3 8517 5555",
    "sg:postcode":"3182",
    "sg:province":"VIC",
    "sg:tags":[
        "consultant",
        "system"
    ],
    "wof:name":"Hospitality Information Systems",
    "wof:placetype":"venue"
},
  "geometry": {"coordinates":[144.98512268100001,-37.8564071655],"type":"Point"}
}