{
  "type": "Feature",
  "properties": {
    "addr:full":"2/ 347 Sheridan St Cairns QLD 4870",
    "addr:housenumber":"/ 347",
    "addr:postcode":"4870",
    "addr:street":"Sheridan St",
    "iso:country":"AU",
    "sg:address":"2/ 347 Sheridan St",
    "sg:city":"Cairns",
    "sg:classifiers":[
        {
            "category":"Professional",
            "subcategory":"Business Services",
            "type":"Services"
        }
    ],
    "sg:phone":"+61 7 4031 2409",
    "sg:postcode":"4870",
    "sg:province":"QLD",
    "sg:tags":[
        "drafting"
    ],
    "wof:name":"Trinity Drafting Services Pty Ltd",
    "wof:placetype":"venue"
},
  "geometry": {"coordinates":[145.75852966299999,-16.9050064087],"type":"Point"}
}