{
  "type": "Feature",
  "properties": {
    "addr:full":"92 Woods St Darwin NT 0800",
    "addr:housenumber":"92",
    "addr:postcode":"nt 0800",
    "addr:street":"Woods St",
    "iso:country":"AU",
    "sg:address":"92 Woods St",
    "sg:city":"Darwin",
    "sg:classifiers":[
        {
            "category":"Travel",
            "subcategory":"Hotels & Motels",
            "type":"Entertainment"
        }
    ],
    "sg:phone":"+61 8 8941 0568",
    "sg:postcode":"0800",
    "sg:province":"NT",
    "wof:name":"Darwin Ti-Tree Holiday Apartments",
    "wof:placetype":"venue"
},
  "geometry": {"coordinates":[130.83917236299999,-12.4563951492],"type":"Point"}
}