{
  "type": "Feature",
  "properties": {
    "iso:country":"AU",
    "sg:address":"16 Little Latrobe St",
    "sg:city":"Melbourne",
    "sg:classifiers":[
        {
            "category":"Cafe",
            "type":"Food & Drink"
        }
    ],
    "sg:phone":"+61 3 9663 3008",
    "sg:postcode":"3000",
    "sg:province":"VIC",
    "wof:name":"Stax",
    "wof:placetype":"venue"
},
  "geometry": {"coordinates":[144.96310424800001,-37.8090438843],"type":"Point"}
}