{
  "type": "Feature",
  "properties": {
    "addr:full":"55 Morialta Rd Rostrevor SA 5073",
    "addr:housenumber":"55",
    "addr:postcode":"5073",
    "addr:street":"Morialta Rd",
    "iso:country":"AU",
    "sg:address":"55 Morialta Rd",
    "sg:city":"Rostrevor",
    "sg:classifiers":[
        {
            "category":"Education",
            "subcategory":"Dance Studio",
            "type":"Public Place"
        }
    ],
    "sg:phone":"+61 8 8336 1443",
    "sg:postcode":"5073",
    "sg:province":"SA",
    "sg:tags":[
        "venue",
        "tuition"
    ],
    "wof:name":"North Eastern Academy Of Dance",
    "wof:placetype":"venue"
},
  "geometry": {"coordinates":[138.68206787099999,-34.9004058838],"type":"Point"}
}