{
  "type": "Feature",
  "properties": {
    "addr:full":"17 Cascade St Paddington NSW 2021",
    "addr:housenumber":"17",
    "addr:postcode":"2021",
    "addr:street":"Cascade St",
    "iso:country":"AU",
    "sg:address":"17 Cascade St",
    "sg:city":"Paddington",
    "sg:classifiers":[
        {
            "category":"Professional",
            "subcategory":"Detective & Security Services",
            "type":"Services"
        }
    ],
    "sg:phone":"+61 419 333 552",
    "sg:postcode":"2021",
    "sg:province":"NSW",
    "sg:tags":[
        "guard",
        "patrol"
    ],
    "wof:name":"BSR Security",
    "wof:placetype":"venue"
},
  "geometry": {"coordinates":[151.23170471200001,-33.8840103149],"type":"Point"}
}