{
  "type": "Feature",
  "properties": {
    "addr:full":"284 Wynnum Rd Norman Park QLD 4170",
    "addr:housenumber":"284",
    "addr:postcode":"4170",
    "addr:street":"Wynnum Rd",
    "iso:country":"AU",
    "sg:address":"284 Wynnum Rd",
    "sg:city":"Norman Park",
    "sg:classifiers":[
        {
            "category":"Personal",
            "subcategory":"Beauty Salon",
            "type":"Services"
        }
    ],
    "sg:phone":"+61 400 727 357",
    "sg:postcode":"4170",
    "sg:province":"QLD",
    "sg:tags":[
        "hair",
        "wedding"
    ],
    "wof:name":"Extraordinary Lengths",
    "wof:placetype":"venue"
},
  "geometry": {"coordinates":[153.061447144,-27.4723758698],"type":"Point"}
}