{
  "type": "Feature",
  "properties": {
    "addr:full":"6 Tennyson Rd Bellevue WA 6056",
    "addr:housenumber":"6",
    "addr:postcode":"6056",
    "addr:street":"Tennyson Rd",
    "iso:country":"AU",
    "sg:address":"6 Tennyson Rd",
    "sg:city":"Bellevue",
    "sg:classifiers":[
        {
            "category":"Education",
            "subcategory":"Special Training",
            "type":"Public Place"
        }
    ],
    "sg:phone":"+61 8 9250 2849",
    "sg:postcode":"6056",
    "sg:province":"WA",
    "sg:tags":[
        "diving",
        "school",
        "scuba"
    ],
    "wof:name":"Personal Dive Training",
    "wof:placetype":"venue"
},
  "geometry": {"coordinates":[116.03249359100001,-31.897146225],"type":"Point"}
}