{
  "type": "Feature",
  "properties": {
    "iso:country":"AU",
    "sg:address":"24 Ryrie Rd",
    "sg:city":"Earlwood",
    "sg:classifiers":[
        {
            "category":"Retail",
            "subcategory":"Repair Shop",
            "type":"Services"
        }
    ],
    "sg:phone":"+61 2 9789 6639",
    "sg:postcode":"2206",
    "sg:province":"NSW",
    "sg:tags":[
        "upholsterer"
    ],
    "wof:name":"Doggies Upholstery",
    "wof:placetype":"venue"
},
  "geometry": {"coordinates":[151.10966500000001,-33.924938],"type":"Point"}
}