{
  "type": "Feature",
  "properties": {
    "addr:full":"Mount Rd Ridgley TAS 7321",
    "addr:postcode":"7321",
    "addr:street":"Mount Rd",
    "iso:country":"AU",
    "sg:address":"Mount Rd",
    "sg:city":"Ridgley",
    "sg:classifiers":[
        {
            "category":"Autos & Motor Vehicles",
            "subcategory":"Fuel & Gas Station",
            "type":"Retail Goods"
        }
    ],
    "sg:phone":"+61 3 6435 7273",
    "sg:postcode":"7321",
    "sg:province":"TAS",
    "wof:name":"BP Australia Limited",
    "wof:placetype":"venue"
},
  "geometry": {"coordinates":[145.89308199999999,-41.090359],"type":"Point"}
}