{
  "type": "Feature",
  "properties": {
    "addr:full":"26 Wrentmore St Fairfield NSW 2165",
    "addr:housenumber":"26",
    "addr:postcode":"2165",
    "addr:street":"Wrentmore St",
    "iso:country":"AU",
    "sg:address":"26 Wrentmore St",
    "sg:city":"Fairfield",
    "sg:classifiers":[
        {
            "category":"Health Services",
            "subcategory":"Health Practitioner",
            "type":"Services"
        }
    ],
    "sg:phone":"+61 2 9726 1144",
    "sg:postcode":"2165",
    "sg:province":"NSW",
    "sg:tags":[
        "physiotherapist"
    ],
    "wof:name":"Jon Chong Physiotherapy",
    "wof:placetype":"venue"
},
  "geometry": {"coordinates":[150.951080322,-33.8701553345],"type":"Point"}
}