{
  "type": "Feature",
  "properties": {
    "addr:full":"12A Station St Mt Evelyn VIC 3796",
    "addr:housenumber":"12a",
    "addr:postcode":"3796",
    "addr:street":"Station St",
    "iso:country":"AU",
    "sg:address":"12A Station St",
    "sg:city":"Mt Evelyn",
    "sg:classifiers":[
        {
            "category":"Arena",
            "subcategory":"Sports Club",
            "type":"Entertainment"
        }
    ],
    "sg:phone":"+61 3 9736 2919",
    "sg:postcode":"3796",
    "sg:province":"VIC",
    "sg:tags":[
        "defence",
        "supply",
        "self",
        "instruction",
        "martial art"
    ],
    "wof:name":"Victorian Freestyle Karate",
    "wof:placetype":"venue"
},
  "geometry": {"coordinates":[145.37901306099999,-37.7862052917],"type":"Point"}
}