{
  "type": "Feature",
  "properties": {
    "addr:full":"35 Gawler St Mt Barker SA 5251",
    "addr:housenumber":"35",
    "addr:postcode":"5251",
    "addr:street":"Gawler St Mt",
    "iso:country":"AU",
    "sg:address":"35 Gawler St",
    "sg:city":"Mt Barker",
    "sg:classifiers":[
        {
            "category":"Shopping",
            "subcategory":"Clothing, Apparel, & Fashions",
            "type":"Retail Goods"
        }
    ],
    "sg:phone":"+61 8 8391 2379",
    "sg:postcode":"5251",
    "sg:province":"SA",
    "sg:tags":[
        "recycled",
        "clothing"
    ],
    "wof:name":"Goodwill",
    "wof:placetype":"venue"
},
  "geometry": {"coordinates":[138.859283447,-35.0671005249],"type":"Point"}
}