{
  "type": "Feature",
  "properties": {
    "addr:full":"6 Kia Crt Preston VIC 3072",
    "addr:housenumber":"6",
    "addr:postcode":"3072",
    "addr:street":"Kia Crt",
    "iso:country":"AU",
    "sg:address":"6 Kia Crt",
    "sg:city":"Preston",
    "sg:classifiers":[
        {
            "category":"Utilities",
            "subcategory":"Electric",
            "type":"Services"
        }
    ],
    "sg:phone":"+61 3 9480 2600",
    "sg:postcode":"3072",
    "sg:province":"VIC",
    "sg:tags":[
        "electrical",
        "contractor"
    ],
    "wof:name":"Macnick Electrical Pty Ltd",
    "wof:placetype":"venue"
},
  "geometry": {"coordinates":[145.03355407699999,-37.7438697815],"type":"Point"}
}