{
  "type": "Feature",
  "properties": {
    "iso:country":"AU",
    "sg:address":"10 St Albans St",
    "sg:city":"Abbotsford",
    "sg:classifiers":[
        {
            "category":"Building & Trades",
            "subcategory":"Construction",
            "type":"Services"
        }
    ],
    "sg:phone":"+61 2 9713 7102",
    "sg:postcode":"2046",
    "sg:province":"NSW",
    "sg:tags":[
        "rendering",
        "cement"
    ],
    "wof:name":"J F Plastering & Constructions (NSW) PTY LTD",
    "wof:placetype":"venue"
},
  "geometry": {"coordinates":[151.127014,-33.850922],"type":"Point"}
}