{
  "type": "Feature",
  "properties": {
    "addr:full":"21 Toongoon Rd Burradoo NSW 2576",
    "addr:housenumber":"21",
    "addr:postcode":"2576",
    "addr:street":"Toongoon Rd",
    "iso:country":"AU",
    "sg:address":"21 Toongoon Rd",
    "sg:city":"Burradoo",
    "sg:classifiers":[
        {
            "category":"Professional",
            "subcategory":"Art Services",
            "type":"Services"
        }
    ],
    "sg:phone":"+61 2 4861 1579",
    "sg:postcode":"2576",
    "sg:province":"NSW",
    "sg:tags":[
        "caricaturist",
        "cartoonist"
    ],
    "wof:name":"Akhurst B J",
    "wof:placetype":"venue"
},
  "geometry": {"coordinates":[150.41749572800001,-34.5040969849],"type":"Point"}
}