{
  "type": "Feature",
  "properties": {
    "addr:full":"9 Williamson Rd Ingleburn NSW 2565",
    "addr:housenumber":"9",
    "addr:postcode":"2565",
    "addr:street":"Williamson Rd",
    "iso:country":"AU",
    "sg:address":"9 Williamson Rd",
    "sg:city":"Ingleburn",
    "sg:classifiers":[
        {
            "category":"Professional",
            "type":"Services"
        }
    ],
    "sg:phone":"+61 2 9829 2322",
    "sg:postcode":"2565",
    "sg:province":"NSW",
    "sg:tags":[
        "packaging",
        "filling",
        "assembling"
    ],
    "wof:name":"Pax Australia Pty Ltd",
    "wof:placetype":"venue"
},
  "geometry": {"coordinates":[150.85055542000001,-33.9974021912],"type":"Point"}
}