{
  "type": "Feature",
  "properties": {
    "iso:country":"AU",
    "sg:address":"124 White St",
    "sg:city":"Mordialloc",
    "sg:classifiers":[
        {
            "category":"Wholesale",
            "subcategory":"Furniture",
            "type":"Manufacturing & Wholesale Goods"
        }
    ],
    "sg:phone":"+61 419 202 232",
    "sg:postcode":"3195",
    "sg:province":"VIC",
    "sg:tags":[
        "wholesaler",
        "mfrs"
    ],
    "wof:name":"Absolutely Luvit Imports",
    "wof:placetype":"venue"
},
  "geometry": {"coordinates":[145.101104736,-38.0005073547],"type":"Point"}
}