{
  "type": "Feature",
  "properties": {
    "addr:full":"Pioneer Rd Grovedale VIC 3216",
    "addr:postcode":"3216",
    "addr:street":"Pioneer Rd",
    "iso:country":"AU",
    "sg:address":"Pioneer Rd",
    "sg:city":"Grovedale",
    "sg:classifiers":[
        {
            "category":"Food & Beverages",
            "subcategory":"Bakery",
            "type":"Retail Goods"
        }
    ],
    "sg:phone":"+61 3 5244 1333",
    "sg:postcode":"3216",
    "sg:province":"VIC",
    "sg:tags":[
        "baker"
    ],
    "wof:name":"Town & Country Bakery",
    "wof:placetype":"venue"
},
  "geometry": {"coordinates":[144.340866089,-38.2030754089],"type":"Point"}
}