{
  "type": "Feature",
  "properties": {
    "addr:full":"109 Herbert St Gulgong NSW 2852",
    "addr:housenumber":"109",
    "addr:postcode":"2852",
    "addr:street":"Herbert St",
    "iso:country":"AU",
    "sg:address":"109 Herbert St",
    "sg:city":"Gulgong",
    "sg:classifiers":[
        {
            "category":"Communications",
            "subcategory":"News Services",
            "type":"Services"
        }
    ],
    "sg:phone":"+61 2 6374 1202",
    "sg:postcode":"2852",
    "sg:province":"NSW",
    "sg:tags":[
        "information",
        "tourist",
        "attractions"
    ],
    "wof:name":"Visitor Information Centres",
    "wof:placetype":"venue"
},
  "geometry": {"coordinates":[149.53331,-32.364132],"type":"Point"}
}