{
  "type": "Feature",
  "properties": {
    "addr:full":"1f Robinson Ave Perth WA 6000",
    "addr:housenumber":"1f",
    "addr:postcode":"6000",
    "addr:street":"Robinson Ave",
    "iso:country":"AU",
    "sg:address":"1f Robinson Ave",
    "sg:city":"Perth",
    "sg:classifiers":[
        {
            "category":"Sports & Exercise",
            "subcategory":"Gym",
            "type":"Entertainment"
        }
    ],
    "sg:phone":"+61 419 196 089",
    "sg:postcode":"6000",
    "sg:province":"WA",
    "sg:tags":[
        "health",
        "fitness"
    ],
    "wof:name":"Pixi Personal Fitness Training",
    "wof:placetype":"venue"
},
  "geometry": {"coordinates":[115.86428832999999,-31.9446907043],"type":"Point"}
}