{
  "type": "Feature",
  "properties": {
    "iso:country":"AU",
    "sg:address":"Shop 236 Westfields Eastgarden",
    "sg:city":"Pagewood",
    "sg:classifiers":[
        {
            "category":"Shopping",
            "subcategory":"Clothing, Apparel, & Fashions",
            "type":"Retail Goods"
        }
    ],
    "sg:phone":"+61 2 9349 8336",
    "sg:postcode":"2035",
    "sg:province":"NSW",
    "sg:tags":[
        "lady",
        "wear"
    ],
    "wof:name":"Valleygirl Fashions Pty Ltd",
    "wof:placetype":"venue"
},
  "geometry": {"coordinates":[151.213348389,-33.9418907166],"type":"Point"}
}