{
  "type": "Feature",
  "properties": {
    "addr:full":"84 Tucker St Breakwater VIC 3219",
    "addr:housenumber":"84",
    "addr:postcode":"3219",
    "addr:street":"Tucker St",
    "iso:country":"AU",
    "sg:address":"84 Tucker St",
    "sg:city":"Breakwater",
    "sg:classifiers":[
        {
            "category":"Professional",
            "subcategory":"Engineering",
            "type":"Services"
        }
    ],
    "sg:phone":"+61 3 5223 1100",
    "sg:postcode":"3219",
    "sg:province":"VIC",
    "sg:tags":[
        "engineer"
    ],
    "wof:name":"Geelong Stainless",
    "wof:placetype":"venue"
},
  "geometry": {"coordinates":[144.366424561,-38.1834373474],"type":"Point"}
}