{
  "type": "Feature",
  "properties": {
    "addr:full":"63 Mary St Noosaville QLD 4566",
    "addr:housenumber":"63",
    "addr:postcode":"4566",
    "addr:street":"Mary St",
    "iso:country":"AU",
    "sg:address":"63 Mary St",
    "sg:city":"Noosaville",
    "sg:classifiers":[
        {
            "category":"Shopping",
            "subcategory":"Beauty & Cosmetics",
            "type":"Retail Goods"
        }
    ],
    "sg:phone":"+61 7 5474 1788",
    "sg:postcode":"4566",
    "sg:province":"QLD",
    "sg:tags":[
        "equipment",
        "salon",
        "supply"
    ],
    "wof:name":"Margi Fox Distributors",
    "wof:placetype":"venue"
},
  "geometry": {"coordinates":[153.06803894000001,-26.4007530212],"type":"Point"}
}