{
  "type": "Feature",
  "properties": {
    "addr:full":"Albany Creek Shopping Centre, Albany Creek Rd Albany Creek QLD 4035",
    "addr:postcode":"4035",
    "addr:street":"Albany Creek Rd",
    "iso:country":"AU",
    "sg:address":"Albany Creek Shopping Centre, Albany Creek Rd",
    "sg:city":"Albany Creek",
    "sg:classifiers":[
        {
            "category":"Fast Food",
            "type":"Food & Drink"
        }
    ],
    "sg:phone":"+61 7 3284 8800",
    "sg:postcode":"4035",
    "sg:province":"QLD",
    "sg:tags":[
        "away",
        "take"
    ],
    "wof:name":"Subway",
    "wof:placetype":"venue"
},
  "geometry": {"coordinates":[152.96705600000001,-27.345362],"type":"Point"}
}