{
  "type": "Feature",
  "properties": {
    "addr:full":"Lot 40 Capel Drv Capel WA 6271",
    "addr:postcode":"6271",
    "addr:street":"Capel Drv",
    "iso:country":"AU",
    "sg:address":"Lot 40 Capel Drv",
    "sg:city":"Capel",
    "sg:classifiers":[
        {
            "category":"Building & Trades",
            "subcategory":"Construction",
            "type":"Services"
        }
    ],
    "sg:phone":"+61 8 9727 2031",
    "sg:postcode":"6271",
    "sg:province":"WA",
    "sg:tags":[
        "contractor"
    ],
    "wof:name":"I.P. & S.T. Elson",
    "wof:placetype":"venue"
},
  "geometry": {"coordinates":[115.557777405,-33.5525054932],"type":"Point"}
}