{
  "type": "Feature",
  "properties": {
    "addr:full":"18 Laidley Pl Florey ACT 2615",
    "addr:housenumber":"18",
    "addr:postcode":"2615",
    "addr:street":"Laidley Pl",
    "iso:country":"AU",
    "sg:address":"18 Laidley Pl",
    "sg:city":"Florey",
    "sg:classifiers":[
        {
            "category":"Personal",
            "subcategory":"Massage",
            "type":"Services"
        }
    ],
    "sg:phone":"+61 2 6258 4240",
    "sg:postcode":"2615",
    "sg:province":"ACT",
    "sg:tags":[
        "therapy"
    ],
    "wof:name":"Bogomiagkov Natalia",
    "wof:placetype":"venue"
},
  "geometry": {"coordinates":[149.045684814,-35.2210540771],"type":"Point"}
}