{
  "type": "Feature",
  "properties": {
    "addr:full":"545 St Kilda Rd Melbourne VIC 3000",
    "addr:housenumber":"545",
    "addr:postcode":"3000",
    "addr:street":"St Kilda Rd",
    "iso:country":"AU",
    "sg:address":"545 St Kilda Rd",
    "sg:city":"Melbourne",
    "sg:classifiers":[
        {
            "category":"Banks & Credit Unions",
            "subcategory":"Investment Brokerage",
            "type":"Services"
        }
    ],
    "sg:phone":"+61 1300 664 223",
    "sg:postcode":"3000",
    "sg:province":"VIC",
    "sg:tags":[
        "debt",
        "collection"
    ],
    "sg:website":"http://www.jmagency.com.au",
    "wof:name":"James Mercantile Agency Pty Ltd",
    "wof:placetype":"venue"
},
  "geometry": {"coordinates":[144.979705811,-37.8465805054],"type":"Point"}
}