{
  "type": "Feature",
  "properties": {
    "iso:country":"AU",
    "sg:address":"197 Yarra St",
    "sg:city":"Geelong",
    "sg:classifiers":[
        {
            "category":"Food & Beverages",
            "subcategory":"Groceries & Convenience Stores",
            "type":"Retail Goods"
        }
    ],
    "sg:phone":"+61 3 5221 2107",
    "sg:postcode":"3220",
    "sg:province":"VIC",
    "wof:name":"Peppies Milk Bar",
    "wof:placetype":"venue"
},
  "geometry": {"coordinates":[144.359497,-38.156471],"type":"Point"}
}