{
  "type": "Feature",
  "properties": {
    "iso:country":"AU",
    "sg:address":"PO Box 1486",
    "sg:city":"Albany",
    "sg:classifiers":[
        {
            "category":"Building & Trades",
            "subcategory":"Construction",
            "type":"Services"
        }
    ],
    "sg:phone":"+61 8 9841 8030",
    "sg:postcode":"6330",
    "sg:province":"WA",
    "sg:tags":[
        "earth",
        "excavating",
        "moving",
        "contractor"
    ],
    "wof:name":"Dean Norton Bobcat Services",
    "wof:placetype":"venue"
},
  "geometry": {"coordinates":[117.94029998800001,-34.8903007507],"type":"Point"}
}