{
  "type": "Feature",
  "properties": {
    "iso:country":"AU",
    "sg:address":"695 Mandalong Rd",
    "sg:city":"Mandalong",
    "sg:classifiers":[
        {
            "category":"Building & Trades",
            "subcategory":"Equipment Rental",
            "type":"Services"
        }
    ],
    "sg:phone":"+61 2 4977 1673",
    "sg:postcode":"2264",
    "sg:province":"NSW",
    "sg:tags":[
        "party",
        "hire"
    ],
    "wof:name":"Alpha Amusements",
    "wof:placetype":"venue"
},
  "geometry": {"coordinates":[151.422363,-33.134892],"type":"Point"}
}