{
  "type": "Feature",
  "properties": {
    "addr:full":"Unit 4/ 74 Cantonment St Fremantle WA 6160",
    "addr:housenumber":"74",
    "addr:postcode":"6160",
    "addr:street":"Cantonment St",
    "iso:country":"AU",
    "sg:address":"Unit 4/ 74 Cantonment St",
    "sg:city":"Fremantle",
    "sg:classifiers":[
        {
            "category":"Professional",
            "subcategory":"Computer Services",
            "type":"Services"
        }
    ],
    "sg:phone":"+61 8 9335 3360",
    "sg:postcode":"6160",
    "sg:province":"WA",
    "sg:tags":[
        "consultant",
        "system"
    ],
    "wof:name":"Groupwise Consulting",
    "wof:placetype":"venue"
},
  "geometry": {"coordinates":[115.748543,-32.0504],"type":"Point"}
}