{
  "type": "Feature",
  "properties": {
    "addr:full":"Cnr Peachey Rd & Vaughan Drv Ormeau QLD 4208",
    "addr:postcode":"4208",
    "addr:street":"Cnr Peachey Rd & Vaughan Drv",
    "iso:country":"AU",
    "sg:address":"Cnr Peachey Rd & Vaughan Drv",
    "sg:city":"Ormeau",
    "sg:classifiers":[
        {
            "category":"Health Services",
            "subcategory":"Doctor",
            "type":"Services"
        }
    ],
    "sg:phone":"+61 7 5547 5666",
    "sg:postcode":"4208",
    "sg:province":"QLD",
    "sg:tags":[
        "medical",
        "practitioner"
    ],
    "wof:name":"Ormeau Physiotherapy",
    "wof:placetype":"venue"
},
  "geometry": {"coordinates":[153.23666381800001,-27.7798137665],"type":"Point"}
}