{
  "type": "Feature",
  "properties": {
    "addr:full":"69 Phillip St Parramatta NSW 2150",
    "addr:housenumber":"69",
    "addr:postcode":"2150",
    "addr:street":"Phillip St",
    "iso:country":"AU",
    "sg:address":"69 Phillip St",
    "sg:city":"Parramatta",
    "sg:classifiers":[
        {
            "category":"Professional",
            "subcategory":"Printing & Photocopies",
            "type":"Services"
        }
    ],
    "sg:phone":"+61 2 9633 4808",
    "sg:postcode":"2150",
    "sg:province":"NSW",
    "sg:tags":[
        "photocopying"
    ],
    "wof:name":"Snap Printing",
    "wof:placetype":"venue"
},
  "geometry": {"coordinates":[150.96452331500001,-33.8519248962],"type":"Point"}
}