{
  "type": "Feature",
  "properties": {
    "addr:full":"22 Church St Traralgon VIC 3844",
    "addr:housenumber":"22",
    "addr:postcode":"3844",
    "addr:street":"Church St",
    "iso:country":"AU",
    "sg:address":"22 Church St",
    "sg:city":"Traralgon",
    "sg:classifiers":[
        {
            "category":"Manufacturing",
            "subcategory":"Food",
            "type":"Manufacturing & Wholesale Goods"
        }
    ],
    "sg:phone":"+61 3 5174 6122",
    "sg:postcode":"3844",
    "sg:province":"VIC",
    "sg:tags":[
        "function",
        "catering"
    ],
    "wof:name":"PJs",
    "wof:placetype":"venue"
},
  "geometry": {"coordinates":[146.535400391,-38.1968841553],"type":"Point"}
}