{
  "type": "Feature",
  "properties": {
    "iso:country":"AU",
    "sg:address":"213 Watton St",
    "sg:city":"Werribee",
    "sg:classifiers":[
        {
            "category":"Real Estate",
            "subcategory":"Surveying",
            "type":"Services"
        }
    ],
    "sg:phone":"+61 3 9742 4920",
    "sg:postcode":"3030",
    "sg:province":"VIC",
    "sg:tags":[
        "surveyor",
        "land"
    ],
    "wof:name":"All General Surveying Pty Ltd",
    "wof:placetype":"venue"
},
  "geometry": {"coordinates":[144.654465,-37.905304],"type":"Point"}
}