{
  "type": "Feature",
  "properties": {
    "addr:full":"6 Balrothery St Bracken Ridge QLD 4017",
    "addr:housenumber":"6",
    "addr:postcode":"4017",
    "addr:street":"Balrothery St",
    "iso:country":"AU",
    "sg:address":"6 Balrothery St",
    "sg:city":"Bracken Ridge",
    "sg:classifiers":[
        {
            "category":"Home & Garden",
            "subcategory":"Home Furnishings",
            "type":"Retail Goods"
        }
    ],
    "sg:phone":"+61 7 3261 1946",
    "sg:postcode":"4017",
    "sg:province":"QLD",
    "sg:tags":[
        "candle"
    ],
    "wof:name":"Candlecraft",
    "wof:placetype":"venue"
},
  "geometry": {"coordinates":[153.023834228,-27.3136558533],"type":"Point"}
}