{
  "type": "Feature",
  "properties": {
    "addr:full":"188 Bong Bong St Bowral NSW 2576",
    "addr:housenumber":"188",
    "addr:postcode":"2576",
    "addr:street":"Bong Bong St",
    "iso:country":"AU",
    "sg:address":"188 Bong Bong St",
    "sg:city":"Bowral",
    "sg:classifiers":[
        {
            "category":"Insurance",
            "subcategory":"Hazard Insurance",
            "type":"Services"
        }
    ],
    "sg:phone":"+61 2 4862 1966",
    "sg:postcode":"2576",
    "sg:province":"NSW",
    "sg:tags":[
        "motor",
        "vehicle"
    ],
    "wof:name":"Macey Insurance Brokers Pty Ltd",
    "wof:placetype":"venue"
},
  "geometry": {"coordinates":[150.41831970199999,-34.4774665833],"type":"Point"}
}