{
  "type": "Feature",
  "properties": {
    "iso:country":"AU",
    "sg:address":"7 Gladys St",
    "sg:city":"Stones Corner",
    "sg:classifiers":[
        {
            "category":"Retail",
            "subcategory":"Auto Repair",
            "type":"Services"
        }
    ],
    "sg:phone":"+61 7 3394 1411",
    "sg:postcode":"4120",
    "sg:province":"QLD",
    "sg:tags":[
        "repairer",
        "motor",
        "engineer"
    ],
    "wof:name":"Saab Care",
    "wof:placetype":"venue"
},
  "geometry": {"coordinates":[153.04525756800001,-27.4975757599],"type":"Point"}
}