{
  "type": "Feature",
  "properties": {
    "addr:full":"Unit 1, 15 Fremantle St Burleigh Waters QLD 4220",
    "addr:housenumber":"15",
    "addr:postcode":"4220",
    "addr:street":"Fremantle St",
    "iso:country":"AU",
    "sg:address":"Unit 1, 15 Fremantle St",
    "sg:city":"Burleigh Waters",
    "sg:classifiers":[
        {
            "category":"Arts & Performance",
            "subcategory":"Music",
            "type":"Entertainment"
        }
    ],
    "sg:phone":"+61 7 5593 4947",
    "sg:postcode":"4220",
    "sg:province":"QLD",
    "sg:tags":[
        "hi-fi",
        "equipment"
    ],
    "wof:name":"A-Line Audio",
    "wof:placetype":"venue"
},
  "geometry": {"coordinates":[153.42300415,-28.1096534729],"type":"Point"}
}