{
  "type": "Feature",
  "properties": {
    "iso:country":"AU",
    "sg:address":"Unit 6 25 Redwood Drv",
    "sg:city":"Dingley",
    "sg:classifiers":[
        {
            "category":"Building & Trades",
            "subcategory":"Locksmith",
            "type":"Services"
        }
    ],
    "sg:phone":"+61 3 9558 1233",
    "sg:postcode":"3172",
    "sg:province":"VIC",
    "sg:tags":[
        "supply"
    ],
    "wof:name":"Keyman Australia Pty Ltd",
    "wof:placetype":"venue"
},
  "geometry": {"coordinates":[145.113815308,-37.9840393066],"type":"Point"}
}