{
  "type": "Feature",
  "properties": {
    "addr:full":"19 Frawley Rd Hallam VIC 3803",
    "addr:housenumber":"19",
    "addr:postcode":"3803",
    "addr:street":"Frawley Rd",
    "iso:country":"AU",
    "sg:address":"19 Frawley Rd",
    "sg:city":"Hallam",
    "sg:classifiers":[
        {
            "category":"Home & Garden",
            "subcategory":"Building Materials",
            "type":"Retail Goods"
        }
    ],
    "sg:phone":"+61 411 755 392",
    "sg:postcode":"3803",
    "sg:province":"VIC",
    "sg:tags":[
        "concrete",
        "gutter",
        "kerb"
    ],
    "wof:name":"A D Jeffery",
    "wof:placetype":"venue"
},
  "geometry": {"coordinates":[145.254592895,-37.9969978333],"type":"Point"}
}