{
  "type": "Feature",
  "properties": {
    "iso:country":"AU",
    "sg:address":"1/ 23 De Havilland Crs",
    "sg:city":"Ballina",
    "sg:classifiers":[
        {
            "category":"Autos & Motor Vehicles",
            "subcategory":"Auto Supplies",
            "type":"Retail Goods"
        }
    ],
    "sg:phone":"+61 2 6686 2644",
    "sg:postcode":"2478",
    "sg:province":"NSW",
    "sg:tags":[
        "tyre"
    ],
    "wof:name":"Frank Vanz Lismore Tyre Company Pty Limited",
    "wof:placetype":"venue"
},
  "geometry": {"coordinates":[153.5572052,-28.8472175598],"type":"Point"}
}