{
  "type": "Feature",
  "properties": {
    "iso:country":"AU",
    "sg:address":"6915 Great Eastern Hwy Mundaring Town Centre",
    "sg:city":"Mundaring",
    "sg:classifiers":[
        {
            "category":"Health Services",
            "subcategory":"Dentist",
            "type":"Services"
        }
    ],
    "sg:phone":"+61 8 9295 2881",
    "sg:postcode":"6073",
    "sg:province":"WA",
    "sg:tags":[
        "dental",
        "prosthetist"
    ],
    "wof:name":"Mundaring Denture Company",
    "wof:placetype":"venue"
},
  "geometry": {"coordinates":[116.16338348399999,-31.9014568329],"type":"Point"}
}