{
  "type": "Feature",
  "properties": {
    "addr:full":"6 Centro Ave Subiaco WA 6008",
    "addr:housenumber":"6",
    "addr:postcode":"6008",
    "addr:street":"Centro Ave",
    "iso:country":"AU",
    "sg:address":"6 Centro Ave",
    "sg:city":"Subiaco",
    "sg:classifiers":[
        {
            "category":"Manufacturing",
            "subcategory":"Glass & Minerals",
            "type":"Manufacturing & Wholesale Goods"
        }
    ],
    "sg:phone":"+61 8 9380 4236",
    "sg:postcode":"6008",
    "sg:province":"WA",
    "sg:tags":[
        "exploration"
    ],
    "wof:name":"Talisman Mininh Pty Ltd",
    "wof:placetype":"venue"
},
  "geometry": {"coordinates":[115.820541382,-31.9445362091],"type":"Point"}
}