{
  "type": "Feature",
  "properties": {
    "addr:full":"3 Mendip Rd Reservoir VIC 3073",
    "addr:housenumber":"3",
    "addr:postcode":"3073",
    "addr:street":"Mendip Rd",
    "iso:country":"AU",
    "sg:address":"3 Mendip Rd",
    "sg:city":"Reservoir",
    "sg:classifiers":[
        {
            "category":"Health Services",
            "subcategory":"Medical Lab",
            "type":"Services"
        }
    ],
    "sg:phone":"+61 3 9478 0560",
    "sg:postcode":"3073",
    "sg:province":"VIC",
    "sg:tags":[
        "laboratory",
        "dental"
    ],
    "wof:name":"Prodent Dental Laboratory",
    "wof:placetype":"venue"
},
  "geometry": {"coordinates":[145.01550293,-37.7236671448],"type":"Point"}
}