{
  "type": "Feature",
  "properties": {
    "iso:country":"AU",
    "sg:address":"9 Quinn Crt",
    "sg:city":"Rowville",
    "sg:classifiers":[
        {
            "category":"Retail",
            "subcategory":"Driving School",
            "type":"Services"
        }
    ],
    "sg:phone":"+61 3 9752 7567",
    "sg:postcode":"3178",
    "sg:province":"VIC",
    "wof:name":"Green Arrow Driving School",
    "wof:placetype":"venue"
},
  "geometry": {"coordinates":[145.27375793499999,-37.9155349731],"type":"Point"}
}