{
  "type": "Feature",
  "properties": {
    "addr:full":"Lot 10 Boonah Rathdownie Rd Boonah QLD 4310",
    "addr:postcode":"4310",
    "addr:street":"Rathdownie Rd",
    "iso:country":"AU",
    "sg:address":"Lot 10 Boonah Rathdownie Rd",
    "sg:city":"Boonah",
    "sg:classifiers":[
        {
            "category":"Farming",
            "subcategory":"Livestock Farm",
            "type":"Manufacturing & Wholesale Goods"
        }
    ],
    "sg:phone":"+61 427 631 766",
    "sg:postcode":"4310",
    "sg:province":"QLD",
    "sg:tags":[
        "breeder",
        "horse",
        "stud"
    ],
    "wof:name":"Eldorado Minature Horse Stud",
    "wof:placetype":"venue"
},
  "geometry": {"coordinates":[152.68057250999999,-28.0052928925],"type":"Point"}
}