{
  "type": "Feature",
  "properties": {
    "iso:country":"AU",
    "sg:address":"345 Mont Albert Rd",
    "sg:city":"Mont Albert",
    "sg:classifiers":[
        {
            "category":"Home & Garden",
            "subcategory":"Building Materials",
            "type":"Retail Goods"
        }
    ],
    "sg:phone":"+61 3 9890 1059",
    "sg:postcode":"3127",
    "sg:province":"VIC",
    "sg:tags":[
        "fencing"
    ],
    "wof:name":"Standrite Australia Pty Ltd",
    "wof:placetype":"venue"
},
  "geometry": {"coordinates":[145.104125977,-37.8209915161],"type":"Point"}
}