{
  "type": "Feature",
  "properties": {
    "iso:country":"AU",
    "sg:address":"Unit 12/ 1645 Ipswich Rd",
    "sg:city":"Rocklea",
    "sg:classifiers":[
        {
            "category":"Shopping",
            "subcategory":"Stationery & Office Supplies",
            "type":"Retail Goods"
        }
    ],
    "sg:phone":"+61 7 3276 8777",
    "sg:postcode":"4106",
    "sg:province":"QLD",
    "sg:tags":[
        "partition"
    ],
    "sg:website":"http://www.signature-projects.com.au",
    "wof:name":"Signature Projects Pty Ltd",
    "wof:placetype":"venue"
},
  "geometry": {"coordinates":[153.00718689000001,-27.5559310913],"type":"Point"}
}