{
  "type": "Feature",
  "properties": {
    "iso:country":"AU",
    "sg:address":"20 Lawler St",
    "sg:city":"Picnic Point",
    "sg:classifiers":[
        {
            "category":"Social Services",
            "type":"Services"
        }
    ],
    "sg:phone":"+61 2 9771 5156",
    "sg:postcode":"2213",
    "sg:province":"NSW",
    "sg:tags":[
        "disabled",
        "person",
        "equipment"
    ],
    "wof:name":"Wheelabout Wheel Chair Transport & Maxi Taxi Service",
    "wof:placetype":"venue"
},
  "geometry": {"coordinates":[151.00238,-33.96545],"type":"Point"}
}