{
  "type": "Feature",
  "properties": {
    "addr:full":"1 Castle St Blakehurst NSW 2221",
    "addr:housenumber":"1",
    "addr:postcode":"2221",
    "addr:street":"Castle St",
    "iso:country":"AU",
    "sg:address":"1 Castle St",
    "sg:city":"Blakehurst",
    "sg:classifiers":[
        {
            "category":"Banks & Credit Unions",
            "subcategory":"Investment Brokerage",
            "type":"Services"
        }
    ],
    "sg:phone":"+61 2 9547 3331",
    "sg:postcode":"2221",
    "sg:province":"NSW",
    "sg:tags":[
        "finance",
        "broker"
    ],
    "wof:name":"Hayden Consulting Pty Ltd",
    "wof:placetype":"venue"
},
  "geometry": {"coordinates":[151.10731506400001,-33.9999198914],"type":"Point"}
}