{
  "type": "Feature",
  "properties": {
    "iso:country":"AU",
    "sg:address":"5/ 39 Toombul Rd",
    "sg:city":"Northgate",
    "sg:classifiers":[
        {
            "category":"Manufacturing",
            "subcategory":"Motor Vehicles & Parts",
            "type":"Manufacturing & Wholesale Goods"
        }
    ],
    "sg:phone":"+61 7 3256 9444",
    "sg:postcode":"4013",
    "sg:province":"QLD",
    "sg:tags":[
        "wholesaler",
        "piston",
        "ring",
        "mfrs"
    ],
    "wof:name":"Mick Cashell Engines & Parts",
    "wof:placetype":"venue"
},
  "geometry": {"coordinates":[153.06515502900001,-27.3844013214],"type":"Point"}
}