{
  "type": "Feature",
  "properties": {
    "iso:country":"AU",
    "sg:address":"46 Berry St",
    "sg:city":"Nowra",
    "sg:classifiers":[
        {
            "category":"Cafe",
            "type":"Food & Drink"
        }
    ],
    "sg:phone":"+61 2 4422 0900",
    "sg:postcode":"2541",
    "sg:province":"NSW",
    "wof:name":"Tea Club Cafe",
    "wof:placetype":"venue"
},
  "geometry": {"coordinates":[150.600463867,-34.8758430481],"type":"Point"}
}