{
  "type": "Feature",
  "properties": {
    "addr:full":"Level 8, 5 Mill St Perth WA 6000",
    "addr:housenumber":"5",
    "addr:postcode":"6000",
    "addr:street":"Mill St",
    "iso:country":"AU",
    "sg:address":"Level 8, 5 Mill St",
    "sg:city":"Perth",
    "sg:classifiers":[
        {
            "category":"Professional",
            "subcategory":"Employment Agencies",
            "type":"Services"
        }
    ],
    "sg:phone":"+61 8 9287 9800",
    "sg:postcode":"6000",
    "sg:province":"WA",
    "wof:name":"DFP Recruitment Services Pty Ltd",
    "wof:placetype":"venue"
},
  "geometry": {"coordinates":[115.852630615,-31.954957962],"type":"Point"}
}