{
  "type": "Feature",
  "properties": {
    "iso:country":"AU",
    "sg:address":"PO Box 164",
    "sg:city":"Essendon North",
    "sg:classifiers":[
        {
            "category":"Real Estate",
            "subcategory":"Real Estate Agent",
            "type":"Services"
        }
    ],
    "sg:phone":"+61 3 9337 8267",
    "sg:postcode":"3041",
    "sg:province":"VIC",
    "sg:tags":[
        "handyman's",
        "equipment",
        "hire",
        "builders",
        "contractor"
    ],
    "wof:name":"Egans Plant Hire",
    "wof:placetype":"venue"
},
  "geometry": {"coordinates":[144.89601135300001,-37.7387313843],"type":"Point"}
}