{
  "type": "Feature",
  "properties": {
    "addr:full":"79 Webb St Fountain Gate VIC 3805",
    "addr:housenumber":"79",
    "addr:postcode":"3805",
    "addr:street":"Webb St Fountain",
    "iso:country":"AU",
    "sg:address":"79 Webb St",
    "sg:city":"Fountain Gate",
    "sg:classifiers":[
        {
            "category":"Home & Garden",
            "subcategory":"Carpets & Floor Coverings",
            "type":"Retail Goods"
        }
    ],
    "sg:phone":"+61 3 8796 6777",
    "sg:postcode":"3805",
    "sg:province":"VIC",
    "sg:tags":[
        "wood"
    ],
    "wof:name":"Harvey Norman Flooring",
    "wof:placetype":"venue"
},
  "geometry": {"coordinates":[145.30633499999999,-38.021442],"type":"Point"}
}