{
  "type": "Feature",
  "properties": {
    "addr:full":"503 Melton Hwy Sydenham VIC 3037",
    "addr:housenumber":"503",
    "addr:postcode":"3037",
    "addr:street":"Melton Hwy",
    "iso:country":"AU",
    "sg:address":"503 Melton Hwy",
    "sg:city":"Sydenham",
    "sg:classifiers":[
        {
            "category":"Health Services",
            "subcategory":"Doctor",
            "type":"Services"
        }
    ],
    "sg:phone":"+61 3 9390 3311",
    "sg:postcode":"3037",
    "sg:province":"VIC",
    "sg:tags":[
        "medical",
        "practitioner"
    ],
    "wof:name":"Phan Cao Dr",
    "wof:placetype":"venue"
},
  "geometry": {"coordinates":[144.76850899999999,-37.695156],"type":"Point"}
}