{
  "type": "Feature",
  "properties": {
    "addr:full":"8 Croobyar Rd Milton NSW 2538",
    "addr:housenumber":"8",
    "addr:postcode":"2538",
    "addr:street":"Croobyar Rd",
    "iso:country":"AU",
    "sg:address":"8 Croobyar Rd",
    "sg:city":"Milton",
    "sg:classifiers":[
        {
            "category":"Sports & Exercise",
            "subcategory":"Gym",
            "type":"Entertainment"
        }
    ],
    "sg:phone":"+61 2 4455 3063",
    "sg:postcode":"2538",
    "sg:province":"NSW",
    "sg:tags":[
        "health",
        "fitness"
    ],
    "wof:name":"Healthfit",
    "wof:placetype":"venue"
},
  "geometry": {"coordinates":[150.43347168,-35.3197822571],"type":"Point"}
}