{
  "type": "Feature",
  "properties": {
    "addr:full":"Suite 2/ 33 Market St Merimbula NSW 2548",
    "addr:housenumber":"33",
    "addr:postcode":"2548",
    "addr:street":"Market St",
    "iso:country":"AU",
    "sg:address":"Suite 2/ 33 Market St",
    "sg:city":"Merimbula",
    "sg:classifiers":[
        {
            "category":"Education",
            "subcategory":"Special Training",
            "type":"Public Place"
        }
    ],
    "sg:phone":"+61 2 6495 4195",
    "sg:postcode":"2548",
    "sg:province":"NSW",
    "sg:tags":[
        "tuition-educational"
    ],
    "wof:name":"Kip McGrath Education Centres",
    "wof:placetype":"venue"
},
  "geometry": {"coordinates":[149.91046142600001,-36.8886489868],"type":"Point"}
}