{
  "type": "Feature",
  "properties": {
    "addr:full":"49 Parramatta Rd Five Dock NSW 2046",
    "addr:housenumber":"49",
    "addr:postcode":"2046",
    "addr:street":"Parramatta Rd",
    "iso:country":"AU",
    "sg:address":"49 Parramatta Rd",
    "sg:city":"Five Dock",
    "sg:classifiers":[
        {
            "category":"Autos & Motor Vehicles",
            "subcategory":"Automobile Sales",
            "type":"Retail Goods"
        }
    ],
    "sg:phone":"+61 2 9799 1386",
    "sg:postcode":"2046",
    "sg:province":"NSW",
    "sg:tags":[
        "car",
        "used"
    ],
    "wof:name":"Motor Market The Original",
    "wof:placetype":"venue"
},
  "geometry": {"coordinates":[151.12397799999999,-33.871525],"type":"Point"}
}