{
  "type": "Feature",
  "properties": {
    "addr:full":"272 Moggill Rd Indooroopilly QLD 4068",
    "addr:housenumber":"272",
    "addr:postcode":"4068",
    "addr:street":"Moggill Rd",
    "iso:country":"AU",
    "sg:address":"272 Moggill Rd",
    "sg:city":"Indooroopilly",
    "sg:classifiers":[
        {
            "category":"Shopping",
            "subcategory":"Crafts & Fabrics",
            "type":"Retail Goods"
        }
    ],
    "sg:phone":"+61 7 3878 5199",
    "sg:postcode":"4068",
    "sg:province":"QLD",
    "sg:tags":[
        "material",
        "dress"
    ],
    "wof:name":"Spotlight",
    "wof:placetype":"venue"
},
  "geometry": {"coordinates":[152.975708008,-27.4964141846],"type":"Point"}
}