{
  "type": "Feature",
  "properties": {
    "addr:full":"26 Clareville Ave Dolls Point NSW 2219",
    "addr:housenumber":"26",
    "addr:postcode":"2219",
    "addr:street":"Clareville Ave",
    "iso:country":"AU",
    "sg:address":"26 Clareville Ave",
    "sg:city":"Dolls Point",
    "sg:classifiers":[
        {
            "category":"Real Estate",
            "subcategory":"Real Estate Agent",
            "type":"Services"
        }
    ],
    "sg:phone":"+61 2 9529 3822",
    "sg:postcode":"2219",
    "sg:province":"NSW",
    "wof:name":"Century 21 Bayside",
    "wof:placetype":"venue"
},
  "geometry": {"coordinates":[151.140244,-33.994076],"type":"Point"}
}