{
  "type": "Feature",
  "properties": {
    "addr:full":"86 Robey St Mascot NSW 2020",
    "addr:housenumber":"86",
    "addr:postcode":"2020",
    "addr:street":"Robey St",
    "iso:country":"AU",
    "sg:address":"86 Robey St",
    "sg:city":"Mascot",
    "sg:classifiers":[
        {
            "category":"Professional",
            "type":"Services"
        }
    ],
    "sg:phone":"+61 2 9667 1325",
    "sg:postcode":"2020",
    "sg:province":"NSW",
    "sg:tags":[
        "spray",
        "painting"
    ],
    "wof:name":"Cougar Industrial Spray Painters Pty Ltd",
    "wof:placetype":"venue"
},
  "geometry": {"coordinates":[151.18907165499999,-33.9311676025],"type":"Point"}
}