{
  "type": "Feature",
  "properties": {
    "addr:full":"65 Ocean St Victor Harbor SA 5211",
    "addr:housenumber":"65",
    "addr:postcode":"5211",
    "addr:street":"Ocean St",
    "iso:country":"AU",
    "sg:address":"65 Ocean St",
    "sg:city":"Victor Harbor",
    "sg:classifiers":[
        {
            "category":"Health Services",
            "subcategory":"Doctor",
            "type":"Services"
        }
    ],
    "sg:phone":"+61 8 8552 1444",
    "sg:postcode":"5211",
    "sg:province":"SA",
    "sg:tags":[
        "medical",
        "practitioner"
    ],
    "wof:name":"Doley A G",
    "wof:placetype":"venue"
},
  "geometry": {"coordinates":[138.62274169899999,-35.5525512695],"type":"Point"}
}