{
  "type": "Feature",
  "properties": {
    "addr:full":"4/ 22 Jaygee Crt Nerang QLD 4211",
    "addr:housenumber":"/ 22",
    "addr:postcode":"4211",
    "addr:street":"Jaygee Crt",
    "iso:country":"AU",
    "sg:address":"4/ 22 Jaygee Crt",
    "sg:city":"Nerang",
    "sg:classifiers":[
        {
            "category":"Retail",
            "subcategory":"Auto Repair",
            "type":"Services"
        }
    ],
    "sg:phone":"+61 7 5596 6005",
    "sg:postcode":"4211",
    "sg:province":"QLD",
    "sg:tags":[
        "repairer",
        "motor",
        "engineer"
    ],
    "wof:name":"Pizzi Automotive",
    "wof:placetype":"venue"
},
  "geometry": {"coordinates":[153.343917847,-28.0043907166],"type":"Point"}
}