{
  "type": "Feature",
  "properties": {
    "iso:country":"AU",
    "sg:address":"2593 Point Nepean Rd",
    "sg:city":"Rye",
    "sg:classifiers":[
        {
            "category":"Building & Trades",
            "subcategory":"Construction",
            "type":"Services"
        }
    ],
    "sg:phone":"+61 448 880 760",
    "sg:postcode":"3941",
    "sg:province":"VIC",
    "sg:tags":[
        "fencing",
        "contractor"
    ],
    "wof:name":"Beachouse Maintenance Company",
    "wof:placetype":"venue"
},
  "geometry": {"coordinates":[144.81671142600001,-38.3696594238],"type":"Point"}
}