{
  "type": "Feature",
  "properties": {
    "addr:full":"PO Box 1219 Young NSW 2594",
    "addr:postcode":"2594",
    "iso:country":"AU",
    "sg:address":"PO Box 1219",
    "sg:city":"Young",
    "sg:classifiers":[
        {
            "category":"Building & Trades",
            "subcategory":"Equipment Rental",
            "type":"Services"
        }
    ],
    "sg:phone":"+61 2 6382 3679",
    "sg:postcode":"2594",
    "sg:province":"NSW",
    "sg:tags":[
        "party",
        "hire"
    ],
    "wof:name":"Cherry Capital Cool Rooms",
    "wof:placetype":"venue"
},
  "geometry": {"coordinates":[148.29434204099999,-34.3139686584],"type":"Point"}
}