{
  "type": "Feature",
  "properties": {
    "addr:full":"Hudson Drv Wagga Wagga NSW 2650",
    "addr:postcode":"2650",
    "addr:street":"Hudson Drv",
    "iso:country":"AU",
    "sg:address":"Hudson Drv",
    "sg:city":"Wagga Wagga",
    "sg:classifiers":[
        {
            "category":"Building & Trades",
            "subcategory":"Cleaning & Sanitation",
            "type":"Services"
        }
    ],
    "sg:phone":"+61 7 5590 7851",
    "sg:postcode":"2650",
    "sg:province":"NSW",
    "sg:tags":[
        "cleaner",
        "repairer",
        "roof"
    ],
    "wof:name":"Carey D & J",
    "wof:placetype":"venue"
},
  "geometry": {"coordinates":[147.334716797,-35.149433136],"type":"Point"}
}