{
  "type": "Feature",
  "properties": {
    "addr:full":"Basement Sheffield House, 713 Hay Street Mall Perth WA 6000",
    "addr:housenumber":"713",
    "addr:postcode":"6000",
    "addr:street":"Hay Street Mall",
    "iso:country":"AU",
    "sg:address":"Basement Sheffield House, 713",
    "sg:city":"Hay Street Mall Perth",
    "sg:classifiers":[
        {
            "category":"Shopping",
            "subcategory":"Music",
            "type":"Retail Goods"
        }
    ],
    "sg:phone":"+61 8 9485 1277",
    "sg:postcode":"6000",
    "sg:province":"WA",
    "sg:tags":[
        "store"
    ],
    "wof:name":"JB HI-FI",
    "wof:placetype":"venue"
},
  "geometry": {"coordinates":[115.855072022,-31.9530620575],"type":"Point"}
}