{
  "type": "Feature",
  "properties": {
    "addr:full":"15 Mill Rd Campbelltown NSW 2560",
    "addr:housenumber":"15",
    "addr:postcode":"2560",
    "addr:street":"Mill Rd",
    "iso:country":"AU",
    "sg:address":"15 Mill Rd",
    "sg:city":"Campbelltown",
    "sg:classifiers":[
        {
            "category":"Autos & Motor Vehicles",
            "subcategory":"Motorcycle Sales",
            "type":"Retail Goods"
        }
    ],
    "sg:phone":"+61 2 4628 5000",
    "sg:postcode":"2560",
    "sg:province":"NSW",
    "sg:tags":[
        "outboard"
    ],
    "wof:name":"Marine Scene Pty Ltd",
    "wof:placetype":"venue"
},
  "geometry": {"coordinates":[150.82139587399999,-34.052734375],"type":"Point"}
}