{
  "type": "Feature",
  "properties": {
    "addr:full":"42 eLINGWORTH Pde Box Hill VIC 3128",
    "addr:housenumber":"42",
    "addr:postcode":"3128",
    "addr:street":"Elingworth Pde",
    "iso:country":"AU",
    "sg:address":"42 eLINGWORTH Pde",
    "sg:city":"Box Hill",
    "sg:classifiers":[
        {
            "category":"Education",
            "subcategory":"School",
            "type":"Public Place"
        }
    ],
    "sg:phone":"+61 3 9896 5000",
    "sg:postcode":"3128",
    "sg:province":"VIC",
    "sg:tags":[
        "teaching",
        "aid"
    ],
    "wof:name":"Renaissance Learning Australia",
    "wof:placetype":"venue"
},
  "geometry": {"coordinates":[145.12759399399999,-37.8210296631],"type":"Point"}
}