{
  "type": "Feature",
  "properties": {
    "addr:full":"13 Dunlop St Ashburton VIC 3147",
    "addr:housenumber":"13",
    "addr:postcode":"3147",
    "addr:street":"Dunlop St",
    "iso:country":"AU",
    "sg:address":"13 Dunlop St",
    "sg:city":"Ashburton",
    "sg:classifiers":[
        {
            "category":"Insurance",
            "subcategory":"Title Insurance",
            "type":"Services"
        }
    ],
    "sg:phone":"+61 411 642 699",
    "sg:postcode":"3147",
    "sg:province":"VIC",
    "sg:tags":[
        "searcher"
    ],
    "wof:name":"S.L. Mitchell Pty Ltd",
    "wof:placetype":"venue"
},
  "geometry": {"coordinates":[145.06675720199999,-37.866973877],"type":"Point"}
}