{
  "type": "Feature",
  "properties": {
    "iso:country":"AU",
    "sg:address":"45 Minjungbal Drv",
    "sg:city":"Tweed Heads South",
    "sg:classifiers":[
        {
            "category":"Home & Garden",
            "subcategory":"Carpets & Floor Coverings",
            "type":"Retail Goods"
        }
    ],
    "sg:phone":"+61 7 5524 2011",
    "sg:postcode":"2486",
    "sg:province":"NSW",
    "sg:tags":[
        "tile",
        "wall"
    ],
    "wof:name":"Metro Tiles",
    "wof:placetype":"venue"
},
  "geometry": {"coordinates":[153.540817261,-28.191576004],"type":"Point"}
}