{
  "type": "Feature",
  "properties": {
    "addr:full":"106 Kent Rd Pascoe Vale VIC 3044",
    "addr:housenumber":"106",
    "addr:postcode":"3044",
    "addr:street":"Kent Rd",
    "iso:country":"AU",
    "sg:address":"106 Kent Rd",
    "sg:city":"Pascoe Vale",
    "sg:classifiers":[
        {
            "category":"Personal",
            "subcategory":"Beauty Salon",
            "type":"Services"
        }
    ],
    "sg:phone":"+61 3 9350 5786",
    "sg:postcode":"3044",
    "sg:province":"VIC",
    "sg:tags":[
        "hairdresser"
    ],
    "wof:name":"106 Hair Design",
    "wof:placetype":"venue"
},
  "geometry": {"coordinates":[144.940963745,-37.7200279236],"type":"Point"}
}