{
  "type": "Feature",
  "properties": {
    "addr:full":"PO Box 275 Patterson Lakes VIC 3197",
    "addr:postcode":"3197",
    "iso:country":"AU",
    "sg:address":"PO Box 275",
    "sg:city":"Patterson Lakes",
    "sg:classifiers":[
        {
            "category":"Home & Garden",
            "subcategory":"Garden Supply",
            "type":"Retail Goods"
        }
    ],
    "sg:phone":"+61 3 9773 9670",
    "sg:postcode":"3197",
    "sg:province":"VIC",
    "sg:tags":[
        "turf",
        "lawn"
    ],
    "wof:name":"A.A.A. Lawn & Seed Company",
    "wof:placetype":"venue"
},
  "geometry": {"coordinates":[145.145187378,-38.074131012],"type":"Point"}
}