{
  "type": "Feature",
  "properties": {
    "iso:country":"AU",
    "sg:address":"29 Lasiandra Crs",
    "sg:city":"Mt Gambier",
    "sg:classifiers":[
        {
            "category":"Home & Garden",
            "subcategory":"Carpets & Floor Coverings",
            "type":"Retail Goods"
        }
    ],
    "sg:phone":"+61 8 8725 2326",
    "sg:postcode":"5290",
    "sg:province":"SA",
    "sg:tags":[
        "layer"
    ],
    "wof:name":"Ellis R J",
    "wof:placetype":"venue"
},
  "geometry": {"coordinates":[140.77169799999999,-37.812534],"type":"Point"}
}