{
  "type": "Feature",
  "properties": {
    "iso:country":"AU",
    "sg:address":"Unit 6/ 14 - 16 Exchange Pde",
    "sg:city":"Narellan Delivery Cntr",
    "sg:classifiers":[
        {
            "category":"Health Services",
            "subcategory":"Health Practitioner",
            "type":"Services"
        }
    ],
    "sg:phone":"+61 419 638 225",
    "sg:postcode":"2567",
    "sg:province":"NSW",
    "sg:tags":[
        "psychologist"
    ],
    "wof:name":"Jan Dunshea Child Psychologist",
    "wof:placetype":"venue"
},
  "geometry": {"coordinates":[150.74891662600001,-34.0393791199],"type":"Point"}
}