{
  "type": "Feature",
  "properties": {
    "iso:country":"AU",
    "sg:address":"528 Great Western Hwy St",
    "sg:city":"Marys",
    "sg:classifiers":[
        {
            "category":"Retail",
            "subcategory":"Auto Repair",
            "type":"Services"
        }
    ],
    "sg:phone":"+61 2 9623 1551",
    "sg:postcode":"2760",
    "sg:province":"NSW",
    "sg:tags":[
        "repairer",
        "motor",
        "engineer"
    ],
    "wof:name":"On Track Automotive",
    "wof:placetype":"venue"
},
  "geometry": {"coordinates":[150.76487731899999,-33.7699165344],"type":"Point"}
}