{
  "type": "Feature",
  "properties": {
    "addr:full":"218 Fulham St Cloverdale WA 6105",
    "addr:housenumber":"218",
    "addr:postcode":"6105",
    "addr:street":"Fulham St",
    "iso:country":"AU",
    "sg:address":"218 Fulham St",
    "sg:city":"Cloverdale",
    "sg:classifiers":[
        {
            "category":"Professional",
            "subcategory":"Art Services",
            "type":"Services"
        }
    ],
    "sg:phone":"+61 8 9479 3505",
    "sg:postcode":"6105",
    "sg:province":"WA",
    "sg:tags":[
        "picture",
        "frame",
        "framing"
    ],
    "wof:name":"Art Cottage Picture Framers",
    "wof:placetype":"venue"
},
  "geometry": {"coordinates":[115.936210632,-31.9660453796],"type":"Point"}
}