{
  "type": "Feature",
  "properties": {
    "iso:country":"AU",
    "sg:address":"GPO Box 82",
    "sg:city":"Thirroul",
    "sg:classifiers":[
        {
            "category":"Building & Trades",
            "subcategory":"Construction",
            "type":"Services"
        }
    ],
    "sg:phone":"+61 417 290 518",
    "sg:postcode":"2515",
    "sg:province":"NSW",
    "sg:tags":[
        "installation",
        "air conditioning"
    ],
    "wof:name":"Seabreeze Airconditioning",
    "wof:placetype":"venue"
},
  "geometry": {"coordinates":[150.922318,-34.315479],"type":"Point"}
}