{
  "type": "Feature",
  "properties": {
    "addr:full":"23 Eastern Rd Traralgon VIC 3844",
    "addr:housenumber":"23",
    "addr:postcode":"3844",
    "addr:street":"Eastern Rd",
    "iso:country":"AU",
    "sg:address":"23 Eastern Rd",
    "sg:city":"Traralgon",
    "sg:classifiers":[
        {
            "category":"Freight",
            "type":"Transportation"
        }
    ],
    "sg:phone":"+61 13 23 45",
    "sg:postcode":"3844",
    "sg:province":"VIC",
    "sg:tags":[
        "light",
        "carrier"
    ],
    "wof:name":"Star Track Express",
    "wof:placetype":"venue"
},
  "geometry": {"coordinates":[146.569091797,-38.1902275085],"type":"Point"}
}