{
  "type": "Feature",
  "properties": {
    "iso:country":"AU",
    "sg:address":"18 Little St",
    "sg:city":"Forster",
    "sg:classifiers":[
        {
            "category":"Personal",
            "subcategory":"Beauty Salon",
            "type":"Services"
        }
    ],
    "sg:phone":"+61 2 6554 6329",
    "sg:postcode":"2428",
    "sg:province":"NSW",
    "wof:name":"AvantGarde Hair Creations",
    "wof:placetype":"venue"
},
  "geometry": {"coordinates":[152.51298499999999,-32.182938],"type":"Point"}
}