{
  "type": "Feature",
  "properties": {
    "iso:country":"AU",
    "sg:address":"40 Sir Donald Bradman Drv",
    "sg:city":"Mile End",
    "sg:classifiers":[
        {
            "category":"Education",
            "subcategory":"Special Training",
            "type":"Public Place"
        }
    ],
    "sg:phone":"+61 8 8354 3244",
    "sg:postcode":"5031",
    "sg:province":"SA",
    "sg:tags":[
        "development"
    ],
    "wof:name":"Management and Research Centre (MARC)",
    "wof:placetype":"venue"
},
  "geometry": {"coordinates":[138.571975708,-34.9315414429],"type":"Point"}
}