{
  "type": "Feature",
  "properties": {
    "addr:full":"702 High St Prahran VIC 3181",
    "addr:housenumber":"702",
    "addr:postcode":"3181",
    "addr:street":"High St",
    "iso:country":"AU",
    "sg:address":"702 High St",
    "sg:city":"Prahran",
    "sg:classifiers":[
        {
            "category":"Communications",
            "subcategory":"Film & Video Production",
            "type":"Services"
        }
    ],
    "sg:phone":"+61 3 9529 4814",
    "sg:postcode":"3181",
    "sg:province":"VIC",
    "sg:tags":[
        "dvd",
        "library"
    ],
    "wof:name":"Network Video",
    "wof:placetype":"venue"
},
  "geometry": {"coordinates":[145.011322022,-37.854309082],"type":"Point"}
}