{
  "type": "Feature",
  "properties": {
    "addr:full":"Shop 1 Island Cove Cnr Lae & Oxley Drvs Runaway Bay QLD 4216",
    "addr:housenumber":"shop 1",
    "addr:postcode":"4216",
    "addr:street":"Island Cove Cnr Lae &",
    "iso:country":"AU",
    "sg:address":"Shop 1 Island Cove Cnr Lae & Oxley Drvs",
    "sg:city":"Runaway Bay",
    "sg:classifiers":[
        {
            "category":"Internet Cafe",
            "subcategory":"None",
            "type":"Food & Drink"
        }
    ],
    "sg:phone":"+61 7 5529 2655",
    "sg:postcode":"4216",
    "sg:province":"QLD",
    "wof:name":"Runaway Bay Internet Cafe",
    "wof:placetype":"venue"
},
  "geometry": {"coordinates":[153.40147399899999,-27.9125118256],"type":"Point"}
}