{
  "type": "Feature",
  "properties": {
    "addr:full":"122 Corunna La Stanmore NSW 2048",
    "addr:housenumber":"122",
    "addr:postcode":"2048",
    "addr:street":"Corunna La",
    "iso:country":"AU",
    "sg:address":"122 Corunna La",
    "sg:city":"Stanmore",
    "sg:classifiers":[
        {
            "category":"Wholesale",
            "subcategory":"Seafood",
            "type":"Manufacturing & Wholesale Goods"
        }
    ],
    "sg:phone":"+61 2 9560 6670",
    "sg:postcode":"2048",
    "sg:province":"NSW",
    "sg:tags":[
        "fish"
    ],
    "wof:name":"Seafood Systems Australia Pty Ltd",
    "wof:placetype":"venue"
},
  "geometry": {"coordinates":[151.16421500000001,-33.889008],"type":"Point"}
}