{
  "type": "Feature",
  "properties": {
    "iso:country":"AU",
    "sg:address":"Shp13/ 4 Old Coast Rd",
    "sg:city":"Halls Head",
    "sg:classifiers":[
        {
            "category":"Fast Food",
            "type":"Food & Drink"
        }
    ],
    "sg:phone":"+61 8 9586 3388",
    "sg:postcode":"6210",
    "sg:province":"WA",
    "sg:tags":[
        "away",
        "take"
    ],
    "wof:name":"Marina Pearl Chinese Takeaway",
    "wof:placetype":"venue"
},
  "geometry": {"coordinates":[115.714798,-32.536434],"type":"Point"}
}