{
  "type": "Feature",
  "properties": {
    "addr:full":"9 Bryant St Tighes Hill NSW 2297",
    "addr:housenumber":"9",
    "addr:postcode":"2297",
    "addr:street":"Bryant St",
    "iso:country":"AU",
    "sg:address":"9 Bryant St",
    "sg:city":"Tighes Hill",
    "sg:classifiers":[
        {
            "category":"Professional",
            "subcategory":"Printing & Photocopies",
            "type":"Services"
        }
    ],
    "sg:phone":"+61 2 4969 4044",
    "sg:postcode":"2297",
    "sg:province":"NSW",
    "sg:tags":[
        "photocopying"
    ],
    "wof:name":"Who Printing & Presentations",
    "wof:placetype":"venue"
},
  "geometry": {"coordinates":[151.74888610799999,-32.908000946],"type":"Point"}
}