{
  "type": "Feature",
  "properties": {
    "addr:full":"121 Lewis Rd Wantirna South VIC 3152",
    "addr:housenumber":"121",
    "addr:postcode":"3152",
    "addr:street":"Lewis Rd",
    "iso:country":"AU",
    "sg:address":"121 Lewis Rd",
    "sg:city":"Wantirna South",
    "sg:classifiers":[
        {
            "category":"Shopping",
            "subcategory":"Stationery & Office Supplies",
            "type":"Retail Goods"
        }
    ],
    "sg:phone":"+61 3 9814 4400",
    "sg:postcode":"3152",
    "sg:province":"VIC",
    "sg:tags":[
        "packaging",
        "material"
    ],
    "wof:name":"Cospak",
    "wof:placetype":"venue"
},
  "geometry": {"coordinates":[145.24873352,-37.8717536926],"type":"Point"}
}