{
  "type": "Feature",
  "properties": {
    "iso:country":"AU",
    "sg:address":"43- 47 Coonans Rd",
    "sg:city":"Pascoe Vale South",
    "sg:classifiers":[
        {
            "category":"Retail",
            "subcategory":"Car Wash",
            "type":"Services"
        }
    ],
    "sg:phone":"+61 3 9383 5300",
    "sg:postcode":"3044",
    "sg:province":"VIC",
    "sg:tags":[
        "truck",
        "cleaning"
    ],
    "wof:name":"Blue Bubble Hand Car Wash",
    "wof:placetype":"venue"
},
  "geometry": {"coordinates":[144.935455322,-37.7480583191],"type":"Point"}
}