{
  "type": "Feature",
  "properties": {
    "addr:full":"26 Rifle Range Rd Narangba QLD 4504",
    "addr:housenumber":"26",
    "addr:postcode":"4504",
    "addr:street":"Rifle Range Rd",
    "iso:country":"AU",
    "sg:address":"26 Rifle Range Rd",
    "sg:city":"Narangba",
    "sg:classifiers":[
        {
            "category":"Manufacturing",
            "subcategory":"Food",
            "type":"Manufacturing & Wholesale Goods"
        }
    ],
    "sg:phone":"+61 7 3385 5613",
    "sg:postcode":"4504",
    "sg:province":"QLD",
    "sg:tags":[
        "function",
        "catering"
    ],
    "wof:name":"Hangi Man",
    "wof:placetype":"venue"
},
  "geometry": {"coordinates":[152.931716919,-27.1871757507],"type":"Point"}
}