{
  "type": "Feature",
  "properties": {
    "addr:full":"199 Carlisle St Balaclava VIC 3183",
    "addr:housenumber":"199",
    "addr:postcode":"3183",
    "addr:street":"Carlisle St",
    "iso:country":"AU",
    "sg:address":"199 Carlisle St",
    "sg:city":"Balaclava",
    "sg:classifiers":[
        {
            "category":"Personal",
            "subcategory":"Beauty Salon",
            "type":"Services"
        }
    ],
    "sg:phone":"+61 3 9531 7779",
    "sg:postcode":"3183",
    "sg:province":"VIC",
    "sg:tags":[
        "hairdresser"
    ],
    "wof:name":"Arte & Frank",
    "wof:placetype":"venue"
},
  "geometry": {"coordinates":[144.99346923799999,-37.8688697815],"type":"Point"}
}