{
  "type": "Feature",
  "properties": {
    "iso:country":"AU",
    "sg:address":"Shop1/ 145 Bryants Rd",
    "sg:city":"Loganholme",
    "sg:classifiers":[
        {
            "category":"Personal",
            "subcategory":"Beauty Salon",
            "type":"Services"
        }
    ],
    "sg:phone":"+61 7 3801 4963",
    "sg:postcode":"4129",
    "sg:province":"QLD",
    "sg:tags":[
        "hairdresser"
    ],
    "wof:name":"Ebony Hair Design",
    "wof:placetype":"venue"
},
  "geometry": {"coordinates":[153.18614196799999,-27.6659736633],"type":"Point"}
}