{
  "type": "Feature",
  "properties": {
    "iso:country":"AU",
    "sg:address":"7 The Seven Ways",
    "sg:city":"Rockdale",
    "sg:classifiers":[
        {
            "category":"Health Services",
            "subcategory":"Dentist",
            "type":"Services"
        }
    ],
    "sg:phone":"+61 2 9567 6155",
    "sg:postcode":"2216",
    "sg:province":"NSW",
    "sg:tags":[
        "dental",
        "prosthetist"
    ],
    "wof:name":"Harmony Dental Ceramics Pty Ltd",
    "wof:placetype":"venue"
},
  "geometry": {"coordinates":[151.138092,-33.951809],"type":"Point"}
}