{
  "type": "Feature",
  "properties": {
    "addr:full":"62 De Havilland Rd Mordialloc VIC 3195",
    "addr:postcode":"3195",
    "addr:street":"62 De Havilland Rd",
    "iso:country":"AU",
    "sg:address":"62 De Havilland Rd",
    "sg:city":"Mordialloc",
    "sg:classifiers":[
        {
            "category":"Shopping",
            "subcategory":"Pets & Pet Supplies",
            "type":"Retail Goods"
        }
    ],
    "sg:phone":"+61 3 9580 5539",
    "sg:postcode":"3195",
    "sg:province":"VIC",
    "sg:tags":[
        "equipment",
        "foundry"
    ],
    "wof:name":"Beasley K L Pty Ltd",
    "wof:placetype":"venue"
},
  "geometry": {"coordinates":[145.10040283199999,-37.9916763306],"type":"Point"}
}