{
  "type": "Feature",
  "properties": {
    "addr:full":"19 Lawley Crs Mt Lawley WA 6050",
    "addr:housenumber":"19",
    "addr:postcode":"6050",
    "addr:street":"Lawley Crs",
    "iso:country":"AU",
    "sg:address":"19 Lawley Crs",
    "sg:city":"Mt Lawley",
    "sg:classifiers":[
        {
            "category":"Social Services",
            "subcategory":"Retirement Home",
            "type":"Services"
        }
    ],
    "sg:phone":"+61 8 9271 6947",
    "sg:postcode":"6050",
    "sg:province":"WA",
    "sg:tags":[
        "village"
    ],
    "wof:name":"St David's Retirement Centre",
    "wof:placetype":"venue"
},
  "geometry": {"coordinates":[115.85504913299999,-31.9378433228],"type":"Point"}
}