{
  "type": "Feature",
  "properties": {
    "iso:country":"AU",
    "sg:address":"Lot 458 Veal St",
    "sg:city":"Hopetoun",
    "sg:classifiers":[
        {
            "category":"Travel",
            "subcategory":"Hotels & Motels",
            "type":"Entertainment"
        }
    ],
    "sg:phone":"+61 8 9838 3219",
    "sg:postcode":"6348",
    "sg:province":"WA",
    "wof:name":"Hopetoun Motel & Chalet Village",
    "wof:placetype":"venue"
},
  "geometry": {"coordinates":[120.126328,-33.942596],"type":"Point"}
}