{
  "type": "Feature",
  "properties": {
    "addr:full":"2/ 4 O&#039;Hart Cl Charmhaven NSW 2263",
    "addr:housenumber":"/ 4 o",
    "addr:postcode":"2263",
    "addr:street":"Hart Cl Charmhaven",
    "iso:country":"AU",
    "sg:address":"2/ 4",
    "sg:city":"O&#039;Hart Cl Charmhaven",
    "sg:classifiers":[
        {
            "category":"Wholesale",
            "subcategory":"Metals & Minerals",
            "type":"Manufacturing & Wholesale Goods"
        }
    ],
    "sg:phone":"+61 2 4393 1235",
    "sg:postcode":"2263",
    "sg:province":"NSW",
    "sg:tags":[
        "steel",
        "stainless",
        "product",
        "equipment"
    ],
    "wof:name":"Coast & Country Shade Sails",
    "wof:placetype":"venue"
},
  "geometry": {"coordinates":[151.501068,-33.236889],"type":"Point"}
}