{
  "type": "Feature",
  "properties": {
    "addr:full":"Unit 10/ 9 Monterey Rd Dandenong VIC 3175",
    "addr:housenumber":"/ 9",
    "addr:postcode":"3175",
    "addr:street":"Monterey Rd",
    "iso:country":"AU",
    "sg:address":"Unit 10/ 9 Monterey Rd",
    "sg:city":"Dandenong",
    "sg:classifiers":[
        {
            "category":"Professional",
            "type":"Services"
        }
    ],
    "sg:phone":"+61 3 9706 9511",
    "sg:postcode":"3175",
    "sg:province":"VIC",
    "sg:tags":[
        "packaging",
        "filling",
        "assembling"
    ],
    "wof:name":"Sabre Packaging & Distribution Pty Ltd",
    "wof:placetype":"venue"
},
  "geometry": {"coordinates":[145.21878051799999,-38.0244293213],"type":"Point"}
}