{
  "type": "Feature",
  "properties": {
    "iso:country":"AU",
    "sg:address":"183 Princes Hwy",
    "sg:city":"Kogarah",
    "sg:classifiers":[
        {
            "category":"Health Services",
            "subcategory":"Health Practitioner",
            "type":"Services"
        }
    ],
    "sg:phone":"+61 2 9588 5555",
    "sg:postcode":"2217",
    "sg:province":"NSW",
    "sg:tags":[
        "physiotherapist"
    ],
    "wof:name":"Burn Newell & Associates Physiotherapists",
    "wof:placetype":"venue"
},
  "geometry": {"coordinates":[151.13473500000001,-33.969913],"type":"Point"}
}