{
  "type": "Feature",
  "properties": {
    "addr:full":"21 Lindstrom Crt Runcorn QLD 4113",
    "addr:housenumber":"21",
    "addr:postcode":"4113",
    "addr:street":"Lindstrom Crt",
    "iso:country":"AU",
    "sg:address":"21 Lindstrom Crt",
    "sg:city":"Runcorn",
    "sg:classifiers":[
        {
            "category":"Home & Garden",
            "subcategory":"Carpets & Floor Coverings",
            "type":"Retail Goods"
        }
    ],
    "sg:phone":"+61 413 736 106",
    "sg:postcode":"4113",
    "sg:province":"QLD",
    "sg:tags":[
        "wood"
    ],
    "wof:name":"Phoenix Wood Floors",
    "wof:placetype":"venue"
},
  "geometry": {"coordinates":[153.08563232399999,-27.5993690491],"type":"Point"}
}