{
  "type": "Feature",
  "properties": {
    "iso:country":"AU",
    "sg:address":"48 St Georges Rd",
    "sg:city":"Northcote",
    "sg:classifiers":[
        {
            "category":"Personal",
            "type":"Services"
        }
    ],
    "sg:phone":"+61 3 9486 2254",
    "sg:postcode":"3070",
    "sg:province":"VIC",
    "sg:tags":[
        "dressmaker"
    ],
    "wof:name":"Margarette Louise Couture",
    "wof:placetype":"venue"
},
  "geometry": {"coordinates":[144.99028000000001,-37.775547],"type":"Point"}
}