{
  "type": "Feature",
  "properties": {
    "addr:full":"76 Oatley Crt Belconnen ACT 2617",
    "addr:housenumber":"76",
    "addr:postcode":"2617",
    "addr:street":"Oatley Crt",
    "iso:country":"AU",
    "sg:address":"76 Oatley Crt",
    "sg:city":"Belconnen",
    "sg:classifiers":[
        {
            "category":"Wholesale",
            "subcategory":"Painting Supplies",
            "type":"Manufacturing & Wholesale Goods"
        }
    ],
    "sg:phone":"+61 2 6253 2404",
    "sg:postcode":"2617",
    "sg:province":"ACT",
    "sg:tags":[
        "painter"
    ],
    "wof:name":"Bristol",
    "wof:placetype":"venue"
},
  "geometry": {"coordinates":[149.05853271500001,-35.2424240112],"type":"Point"}
}