{
  "type": "Feature",
  "properties": {
    "iso:country":"AU",
    "sg:address":"396 Centre Rd",
    "sg:city":"Bentleigh",
    "sg:classifiers":[
        {
            "category":"Real Estate",
            "subcategory":"Real Estate Agent",
            "type":"Services"
        }
    ],
    "sg:phone":"+61 418 331 533",
    "sg:postcode":"3204",
    "sg:province":"VIC",
    "wof:name":"Pollard J",
    "wof:placetype":"venue"
},
  "geometry": {"coordinates":[145.036453,-37.918274],"type":"Point"}
}