{
  "type": "Feature",
  "properties": {
    "addr:full":"42 Unumgar St Woodenbong NSW 2476",
    "addr:housenumber":"42",
    "addr:postcode":"2476",
    "addr:street":"Unumgar St",
    "iso:country":"AU",
    "sg:address":"42 Unumgar St",
    "sg:city":"Woodenbong",
    "sg:classifiers":[
        {
            "category":"Building & Trades",
            "subcategory":"Construction",
            "type":"Services"
        }
    ],
    "sg:phone":"+61 2 6635 1336",
    "sg:postcode":"2476",
    "sg:province":"NSW",
    "sg:tags":[
        "earth",
        "excavating",
        "moving",
        "contractor"
    ],
    "wof:name":"J Watson & Son Pty Ltd",
    "wof:placetype":"venue"
},
  "geometry": {"coordinates":[152.61210632300001,-28.388710022],"type":"Point"}
}