{
  "type": "Feature",
  "properties": {
    "addr:full":"Lot 25/ Kanandah Pl Broken Hill NSW 2880",
    "addr:housenumber":"/ kanandah",
    "addr:postcode":"2880",
    "addr:street":"Pl",
    "iso:country":"AU",
    "sg:address":"Lot 25/ Kanandah Pl",
    "sg:city":"Broken Hill",
    "sg:classifiers":[
        {
            "category":"Shopping",
            "subcategory":"Pets & Pet Supplies",
            "type":"Retail Goods"
        }
    ],
    "sg:phone":"+61 8 8087 6200",
    "sg:postcode":"2880",
    "sg:province":"NSW",
    "sg:tags":[
        "boring",
        "drilling",
        "equipment"
    ],
    "wof:name":"Silver City Drilling (Nsw) Pty Ltd",
    "wof:placetype":"venue"
},
  "geometry": {"coordinates":[141.43226623499999,-31.9847068787],"type":"Point"}
}