{
  "type": "Feature",
  "properties": {
    "addr:full":"25 Gunnedah Rd Tamworth NSW 2340",
    "addr:housenumber":"25",
    "addr:postcode":"2340",
    "addr:street":"Gunnedah Rd",
    "iso:country":"AU",
    "sg:address":"25 Gunnedah Rd",
    "sg:city":"Tamworth",
    "sg:classifiers":[
        {
            "category":"Retail",
            "subcategory":"Auto Repair",
            "type":"Services"
        }
    ],
    "sg:phone":"+61 2 6762 2133",
    "sg:postcode":"2340",
    "sg:province":"NSW",
    "sg:tags":[
        "bus",
        "truck"
    ],
    "wof:name":"Thompsons Machinery Sales Pty. Ltd.",
    "wof:placetype":"venue"
},
  "geometry": {"coordinates":[150.90687560999999,-31.0967102051],"type":"Point"}
}