{
  "type": "Feature",
  "properties": {
    "iso:country":"AU",
    "sg:address":"22 Crofton St",
    "sg:city":"Bundaberg",
    "sg:classifiers":[
        {
            "category":"Health Services",
            "subcategory":"Doctor",
            "type":"Services"
        }
    ],
    "sg:phone":"+61 7 4153 3692",
    "sg:postcode":"4670",
    "sg:province":"QLD",
    "sg:tags":[
        "podiatrist"
    ],
    "wof:name":"Julia Horton Podiatry",
    "wof:placetype":"venue"
},
  "geometry": {"coordinates":[152.34957885700001,-24.8697605133],"type":"Point"}
}