{
  "type": "Feature",
  "properties": {
    "addr:full":"37- 47 Golden Wattle Dr Narangba QLD 4504",
    "addr:housenumber":"47",
    "addr:postcode":"4504",
    "addr:street":"Golden Wattle Dr",
    "iso:country":"AU",
    "sg:address":"37- 47 Golden Wattle Dr",
    "sg:city":"Narangba",
    "sg:classifiers":[
        {
            "category":"Travel",
            "subcategory":"Hotels & Motels",
            "type":"Entertainment"
        }
    ],
    "sg:phone":"+61 7 3491 1000",
    "sg:postcode":"4504",
    "sg:province":"QLD",
    "sg:tags":[
        "pub"
    ],
    "wof:name":"Narangba Valley Tavern",
    "wof:placetype":"venue"
},
  "geometry": {"coordinates":[152.93913269000001,-27.1735210419],"type":"Point"}
}