{
  "type": "Feature",
  "properties": {
    "addr:full":"165 Neerim Rd Carnegie VIC 3163",
    "addr:housenumber":"165",
    "addr:postcode":"3163",
    "addr:street":"Neerim Rd",
    "iso:country":"AU",
    "sg:address":"165 Neerim Rd",
    "sg:city":"Carnegie",
    "sg:classifiers":[
        {
            "category":"Shopping",
            "subcategory":"Computers & Home Electronics",
            "type":"Retail Goods"
        }
    ],
    "sg:phone":"+61 3 9572 1164",
    "sg:postcode":"3163",
    "sg:province":"VIC",
    "sg:tags":[
        "hardware",
        "equipment"
    ],
    "wof:name":"A & W George Computing Pty Ltd",
    "wof:placetype":"venue"
},
  "geometry": {"coordinates":[145.052856445,-37.8882064819],"type":"Point"}
}