{
  "type": "Feature",
  "properties": {
    "addr:full":"1 Sevenoaks Ave Croydon VIC 3136",
    "addr:housenumber":"1",
    "addr:postcode":"3136",
    "addr:street":"Sevenoaks Ave",
    "iso:country":"AU",
    "sg:address":"1 Sevenoaks Ave",
    "sg:city":"Croydon",
    "sg:classifiers":[
        {
            "category":"Health Services",
            "subcategory":"Health Practitioner",
            "type":"Services"
        }
    ],
    "sg:phone":"+61 3 9723 4937",
    "sg:postcode":"3136",
    "sg:province":"VIC",
    "sg:tags":[
        "psychologist"
    ],
    "wof:name":"Hocking Sandra",
    "wof:placetype":"venue"
},
  "geometry": {"coordinates":[145.275512695,-37.7859916687],"type":"Point"}
}