{
  "type": "Feature",
  "properties": {
    "addr:full":"2625 Gold Coast Hwy Broadbeach QLD 4218",
    "addr:housenumber":"2625",
    "addr:postcode":"4218",
    "addr:street":"Gold Coast Hwy",
    "iso:country":"AU",
    "sg:address":"2625 Gold Coast Hwy",
    "sg:city":"Broadbeach",
    "sg:classifiers":[
        {
            "category":"Food & Beverages",
            "subcategory":"Supermarket",
            "type":"Retail Goods"
        }
    ],
    "sg:phone":"+61 7 5561 0166",
    "sg:postcode":"4218",
    "sg:province":"QLD",
    "sg:tags":[
        "grocery",
        "store"
    ],
    "wof:name":"Iga Express Broadbeach",
    "wof:placetype":"venue"
},
  "geometry": {"coordinates":[153.431808472,-28.0359535217],"type":"Point"}
}