{
  "type": "Feature",
  "properties": {
    "iso:country":"AU",
    "sg:address":"6 Nightingale St",
    "sg:city":"Woolgoolga",
    "sg:classifiers":[
        {
            "category":"Health Services",
            "subcategory":"Doctor",
            "type":"Services"
        }
    ],
    "sg:phone":"+61 2 6654 1899",
    "sg:postcode":"2456",
    "sg:province":"NSW",
    "sg:tags":[
        "medical",
        "practitioner"
    ],
    "wof:name":"More A S",
    "wof:placetype":"venue"
},
  "geometry": {"coordinates":[153.19992099999999,-30.111334],"type":"Point"}
}