{
  "type": "Feature",
  "properties": {
    "iso:country":"AU",
    "sg:address":"Lot 1 Boundary Hill Rd",
    "sg:city":"Boho South",
    "sg:classifiers":[
        {
            "category":"Conference Center",
            "type":"Public Place"
        }
    ],
    "sg:phone":"+61 3 5790 8580",
    "sg:postcode":"3669",
    "sg:province":"VIC",
    "sg:tags":[
        "venue",
        "convention"
    ],
    "wof:name":"Kallara Conference Centre",
    "wof:placetype":"venue"
},
  "geometry": {"coordinates":[145.77987670900001,-36.7946357727],"type":"Point"}
}