{
  "type": "Feature",
  "properties": {
    "addr:full":"56 Cambria Rd Keysborough VIC 3173",
    "addr:housenumber":"56",
    "addr:postcode":"3173",
    "addr:street":"Cambria Rd",
    "iso:country":"AU",
    "sg:address":"56 Cambria Rd",
    "sg:city":"Keysborough",
    "sg:classifiers":[
        {
            "category":"Manufacturing",
            "subcategory":"Motor Vehicles & Parts",
            "type":"Manufacturing & Wholesale Goods"
        }
    ],
    "sg:phone":"+61 3 9798 7166",
    "sg:postcode":"3173",
    "sg:province":"VIC",
    "sg:tags":[
        "replacement"
    ],
    "wof:name":"Japwreck",
    "wof:placetype":"venue"
},
  "geometry": {"coordinates":[145.189376831,-37.9893569946],"type":"Point"}
}