{
  "type": "Feature",
  "properties": {
    "iso:country":"AU",
    "sg:address":"3/ 36 Old Cleveland Rd",
    "sg:city":"Capalaba",
    "sg:classifiers":[
        {
            "category":"Health Services",
            "subcategory":"Doctor",
            "type":"Services"
        }
    ],
    "sg:phone":"+61 7 3843 8910",
    "sg:postcode":"4157",
    "sg:province":"QLD",
    "sg:tags":[
        "nurse",
        "nursing"
    ],
    "wof:name":"1st Choice Care",
    "wof:placetype":"venue"
},
  "geometry": {"coordinates":[153.197555542,-27.5210933685],"type":"Point"}
}