{
  "type": "Feature",
  "properties": {
    "addr:full":"24 Neat St Pelaw Main NSW 2327",
    "addr:housenumber":"24",
    "addr:postcode":"2327",
    "addr:street":"Neat St",
    "iso:country":"AU",
    "sg:address":"24 Neat St",
    "sg:city":"Pelaw Main",
    "sg:classifiers":[
        {
            "category":"Home & Garden",
            "subcategory":"Carpets & Floor Coverings",
            "type":"Retail Goods"
        }
    ],
    "sg:phone":"+61 408 429 290",
    "sg:postcode":"2327",
    "sg:province":"NSW",
    "sg:tags":[
        "layer",
        "planner"
    ],
    "wof:name":"DJ & ML Urquhart",
    "wof:placetype":"venue"
},
  "geometry": {"coordinates":[151.48245239299999,-32.8334465027],"type":"Point"}
}