{
  "type": "Feature",
  "properties": {
    "iso:country":"AU",
    "sg:address":"10 Ti Tree Crs",
    "sg:city":"Berowra",
    "sg:classifiers":[
        {
            "category":"Retail",
            "subcategory":"Repair Shop",
            "type":"Services"
        }
    ],
    "sg:phone":"+61 2 9477 3368",
    "sg:postcode":"2081",
    "sg:province":"NSW",
    "sg:tags":[
        "machine",
        "repairs",
        "part",
        "dryer",
        "washing"
    ],
    "wof:name":"Pacific Fridges & Washers Pty Ltd",
    "wof:placetype":"venue"
},
  "geometry": {"coordinates":[151.150390625,-33.6227493286],"type":"Point"}
}