{
  "type": "Feature",
  "properties": {
    "addr:full":"Fcty 2 61- 24 Queen St Mitcham VIC 3132",
    "addr:housenumber":"61 24",
    "addr:postcode":"3132",
    "addr:street":"Queen St",
    "iso:country":"AU",
    "sg:address":"Fcty 2 61- 24 Queen St",
    "sg:city":"Mitcham",
    "sg:classifiers":[
        {
            "category":"Utilities",
            "subcategory":"Water",
            "type":"Services"
        }
    ],
    "sg:phone":"+61 3 9872 6055",
    "sg:postcode":"3132",
    "sg:province":"VIC",
    "sg:tags":[
        "hot",
        "system"
    ],
    "wof:name":"Camberwell Plumbing Services",
    "wof:placetype":"venue"
},
  "geometry": {"coordinates":[145.18687439000001,-37.8184204102],"type":"Point"}
}