{
  "type": "Feature",
  "properties": {
    "addr:full":"176 Mulgrave Rd Mulgrave NSW 2756",
    "addr:housenumber":"176",
    "addr:postcode":"2756",
    "addr:street":"Mulgrave Rd",
    "iso:country":"AU",
    "sg:address":"176 Mulgrave Rd",
    "sg:city":"Mulgrave",
    "sg:classifiers":[
        {
            "category":"Wholesale",
            "subcategory":"Metals & Minerals",
            "type":"Manufacturing & Wholesale Goods"
        }
    ],
    "sg:phone":"+61 2 4587 9724",
    "sg:postcode":"2756",
    "sg:province":"NSW",
    "sg:tags":[
        "steel",
        "stainless",
        "product",
        "equipment"
    ],
    "wof:name":"Allset Engineering Pty Ltd",
    "wof:placetype":"venue"
},
  "geometry": {"coordinates":[150.83074951200001,-33.6294212341],"type":"Point"}
}