{
  "type": "Feature",
  "properties": {
    "iso:country":"AU",
    "sg:address":"Rear 33 Fitzpatrick St",
    "sg:city":"Revesby",
    "sg:classifiers":[
        {
            "category":"Military Area",
            "subcategory":"Air Force Base",
            "type":"Public Place"
        }
    ],
    "sg:phone":"+61 2 9774 1400",
    "sg:postcode":"2212",
    "sg:province":"NSW",
    "sg:tags":[
        "box",
        "case",
        "wood"
    ],
    "wof:name":"Isar Australia Pty Ltd",
    "wof:placetype":"venue"
},
  "geometry": {"coordinates":[151.003174,-33.936962],"type":"Point"}
}