{
  "type": "Feature",
  "properties": {
    "iso:country":"AU",
    "sg:address":"Suite 3, Level 1, 7 Ventnor Ave",
    "sg:city":"West Perth",
    "sg:classifiers":[
        {
            "category":"Shopping",
            "subcategory":"Computers & Home Electronics",
            "type":"Retail Goods"
        }
    ],
    "sg:phone":"+61 8 9321 0677",
    "sg:postcode":"6005",
    "sg:province":"WA",
    "sg:tags":[
        "small",
        "equipment",
        "business"
    ],
    "wof:name":"E-Centre International",
    "wof:placetype":"venue"
},
  "geometry": {"coordinates":[115.837463379,-31.9506950378],"type":"Point"}
}