{
  "type": "Feature",
  "properties": {
    "iso:country":"AU",
    "sg:address":"4/ 1787 Albany Hwy",
    "sg:city":"Kenwick",
    "sg:classifiers":[
        {
            "category":"Retail",
            "subcategory":"Auto Repair",
            "type":"Services"
        }
    ],
    "sg:phone":"+61 8 9493 2411",
    "sg:postcode":"6107",
    "sg:province":"WA",
    "sg:tags":[
        "repairer",
        "motor",
        "engineer"
    ],
    "wof:name":"UltraTune",
    "wof:placetype":"venue"
},
  "geometry": {"coordinates":[115.974159241,-32.0452156067],"type":"Point"}
}