{
  "type": "Feature",
  "properties": {
    "iso:country":"AU",
    "sg:address":"2 Ratcliffe Crt",
    "sg:city":"Keysborough",
    "sg:classifiers":[
        {
            "category":"Building & Trades",
            "subcategory":"Plumbing",
            "type":"Services"
        }
    ],
    "sg:phone":"+61 425 758 370",
    "sg:postcode":"3173",
    "sg:province":"VIC",
    "sg:tags":[
        "plumber",
        "gasfitters"
    ],
    "wof:name":"Mount Waverley Gas Appliance Servicing",
    "wof:placetype":"venue"
},
  "geometry": {"coordinates":[145.18385314899999,-37.9897346497],"type":"Point"}
}