{
  "type": "Feature",
  "properties": {
    "addr:full":"927 Sturt St Ballarat VIC 3350",
    "addr:housenumber":"927",
    "addr:postcode":"3350",
    "addr:street":"Sturt St",
    "iso:country":"AU",
    "sg:address":"927 Sturt St",
    "sg:city":"Ballarat",
    "sg:classifiers":[
        {
            "category":"Banks & Credit Unions",
            "subcategory":"Bank",
            "type":"Services"
        }
    ],
    "sg:phone":"+61 13 13 14",
    "sg:postcode":"3350",
    "sg:province":"VIC",
    "wof:name":"ANZ",
    "wof:placetype":"venue"
},
  "geometry": {"coordinates":[143.84610000000001,-37.560909],"type":"Point"}
}