{
  "type": "Feature",
  "properties": {
    "addr:full":"525- 527 Chapel St South Yarra VIC 3141",
    "addr:housenumber":"527",
    "addr:postcode":"3141",
    "addr:street":"Chapel St",
    "iso:country":"AU",
    "sg:address":"525- 527 Chapel St",
    "sg:city":"South Yarra",
    "sg:classifiers":[
        {
            "category":"Shopping",
            "subcategory":"Clothing, Apparel, & Fashions",
            "type":"Retail Goods"
        }
    ],
    "sg:phone":"+61 3 9827 4399",
    "sg:postcode":"3141",
    "sg:province":"VIC",
    "sg:tags":[
        "lady",
        "wear"
    ],
    "wof:name":"Esprit (Retail) Pty Ltd",
    "wof:placetype":"venue"
},
  "geometry": {"coordinates":[144.9949646,-37.8419837952],"type":"Point"}
}