{
  "type": "Feature",
  "properties": {
    "iso:country":"AU",
    "sg:address":"Shop 4/ 1",
    "sg:city":"Plaistow Street (Cnr Grand Boulevard) Joondal",
    "sg:classifiers":[
        {
            "category":"Professional",
            "subcategory":"Art Services",
            "type":"Services"
        }
    ],
    "sg:phone":"+61 8 9300 2058",
    "sg:postcode":"6027",
    "sg:province":"WA",
    "sg:tags":[
        "picture",
        "frame",
        "framing"
    ],
    "sg:website":"http://www.featureframes.com.au",
    "wof:name":"Feature Frames Of Joondalup",
    "wof:placetype":"venue"
},
  "geometry": {"coordinates":[115.769332886,-31.7356529236],"type":"Point"}
}