{
  "type": "Feature",
  "properties": {
    "addr:full":"859 Boundary Rd Coopers Plains QLD 4108",
    "addr:housenumber":"859",
    "addr:postcode":"4108",
    "addr:street":"Boundary Rd",
    "iso:country":"AU",
    "sg:address":"859 Boundary Rd",
    "sg:city":"Coopers Plains",
    "sg:classifiers":[
        {
            "category":"Manufacturing",
            "subcategory":"Glass & Minerals",
            "type":"Manufacturing & Wholesale Goods"
        }
    ],
    "sg:phone":"+61 7 3345 7828",
    "sg:postcode":"4108",
    "sg:province":"QLD",
    "sg:tags":[
        "repair",
        "fibreglass",
        "product"
    ],
    "wof:name":"Rod's Custom Shop",
    "wof:placetype":"venue"
},
  "geometry": {"coordinates":[153.03077697800001,-27.5694179535],"type":"Point"}
}