{
  "type": "Feature",
  "properties": {
    "iso:country":"AU",
    "sg:address":"15- 31",
    "sg:city":"Thistlewaite Strs South Melbourne",
    "sg:classifiers":[
        {
            "category":"Building & Trades",
            "subcategory":"Equipment Rental",
            "type":"Services"
        }
    ],
    "sg:phone":"+61 3 9699 6789",
    "sg:postcode":"3205",
    "sg:province":"VIC",
    "sg:tags":[
        "party",
        "hire"
    ],
    "wof:name":"Essential Napery",
    "wof:placetype":"venue"
},
  "geometry": {"coordinates":[144.955856,-37.833881],"type":"Point"}
}