{
  "type": "Feature",
  "properties": {
    "iso:country":"AU",
    "sg:address":"Factory 4 18 Hilldon Crt",
    "sg:city":"Nerang",
    "sg:classifiers":[
        {
            "category":"Professional",
            "type":"Services"
        }
    ],
    "sg:phone":"+61 7 5596 5088",
    "sg:postcode":"4211",
    "sg:province":"QLD",
    "sg:tags":[
        "shop",
        "fitting"
    ],
    "wof:name":"Custom Design Shopfitting",
    "wof:placetype":"venue"
},
  "geometry": {"coordinates":[153.34288024899999,-28.0001964569],"type":"Point"}
}