{
  "type": "Feature",
  "properties": {
    "addr:full":"49 Levanto St Mentone VIC 3194",
    "addr:housenumber":"49",
    "addr:postcode":"3194",
    "addr:street":"Levanto St",
    "iso:country":"AU",
    "sg:address":"49 Levanto St",
    "sg:city":"Mentone",
    "sg:classifiers":[
        {
            "category":"Wholesale",
            "subcategory":"Auto Parts",
            "type":"Manufacturing & Wholesale Goods"
        }
    ],
    "sg:phone":"+61 417 388 580",
    "sg:postcode":"3194",
    "sg:province":"VIC",
    "sg:tags":[
        "recyclers"
    ],
    "wof:name":"Car Donations",
    "wof:placetype":"venue"
},
  "geometry": {"coordinates":[145.07559204099999,-37.9773712158],"type":"Point"}
}