{
  "type": "Feature",
  "properties": {
    "addr:full":"Shop 9 Uni Plaza 462 West St Toowoomba QLD 4350",
    "addr:housenumber":"shop 9;462",
    "addr:postcode":"4350",
    "addr:street":"Uni;West St",
    "iso:country":"AU",
    "sg:address":"Shop 9 Uni Plaza 462 West St",
    "sg:city":"Toowoomba",
    "sg:classifiers":[
        {
            "category":"Internet Cafe",
            "subcategory":"None",
            "type":"Food & Drink"
        }
    ],
    "sg:phone":"+61 7 4637 2882",
    "sg:postcode":"4350",
    "sg:province":"QLD",
    "wof:name":"Infinity Cybercafe",
    "wof:placetype":"venue"
},
  "geometry": {"coordinates":[151.935303,-27.606701],"type":"Point"}
}