{
  "type": "Feature",
  "properties": {
    "iso:country":"AU",
    "sg:address":"95 Reilly St",
    "sg:city":"Lurnea",
    "sg:classifiers":[
        {
            "category":"Utilities",
            "subcategory":"Electric",
            "type":"Services"
        }
    ],
    "sg:phone":"+61 2 9602 0506",
    "sg:postcode":"2170",
    "sg:province":"NSW",
    "sg:tags":[
        "electrical",
        "contractor"
    ],
    "wof:name":"G.J.F Electrical",
    "wof:placetype":"venue"
},
  "geometry": {"coordinates":[150.90470886200001,-33.9329795837],"type":"Point"}
}