{
  "type": "Feature",
  "properties": {
    "iso:country":"AU",
    "sg:address":"Suite 6, 115 Hawthorn Rd",
    "sg:city":"Caulfield North",
    "sg:classifiers":[
        {
            "category":"Social Services",
            "subcategory":"Retirement Home",
            "type":"Services"
        }
    ],
    "sg:phone":"+61 3 9528 4444",
    "sg:postcode":"3161",
    "sg:province":"VIC",
    "sg:tags":[
        "environmental",
        "consultant",
        "pollution"
    ],
    "wof:name":"Beveridge Williams & Co Pty Ltd",
    "wof:placetype":"venue"
},
  "geometry": {"coordinates":[145.02456665,-37.8741836548],"type":"Point"}
}