{
  "type": "Feature",
  "properties": {
    "addr:full":"328 Main Rd East St Albans VIC 3021",
    "addr:housenumber":"328",
    "addr:postcode":"3021",
    "addr:street":"Main Rd East",
    "iso:country":"AU",
    "sg:address":"328 Main Rd East",
    "sg:city":"St Albans",
    "sg:classifiers":[
        {
            "category":"Shopping",
            "subcategory":"Clothing, Apparel, & Fashions",
            "type":"Retail Goods"
        }
    ],
    "sg:phone":"+61 3 9366 3451",
    "sg:postcode":"3021",
    "sg:province":"VIC",
    "sg:tags":[
        "lady",
        "wear"
    ],
    "wof:name":"Best Direction Pty Ltd",
    "wof:placetype":"venue"
},
  "geometry": {"coordinates":[144.80075099999999,-37.744179],"type":"Point"}
}