{
  "type": "Feature",
  "properties": {
    "addr:full":"Unit 1/ 272 Williams Rd Toorak VIC 3142",
    "addr:housenumber":"/ 272",
    "addr:postcode":"3142",
    "addr:street":"Williams Rd",
    "iso:country":"AU",
    "sg:address":"Unit 1/ 272 Williams Rd",
    "sg:city":"Toorak",
    "sg:phone":"+61 3 9827 5906",
    "sg:postcode":"3142",
    "sg:province":"VIC",
    "wof:name":"Evans Rainwater Tanks & Pumps",
    "wof:placetype":"venue"
},
  "geometry": {"coordinates":[145.00469970699999,-37.8414001465],"type":"Point"}
}