{
  "type": "Feature",
  "properties": {
    "iso:country":"AU",
    "sg:address":"49b Boundary Rd",
    "sg:city":"Rocklea",
    "sg:classifiers":[
        {
            "category":"Professional",
            "type":"Services"
        }
    ],
    "sg:phone":"+61 7 3717 0001",
    "sg:postcode":"4106",
    "sg:province":"QLD",
    "sg:tags":[
        "transport"
    ],
    "wof:name":"Toll Liquid Distribution",
    "wof:placetype":"venue"
},
  "geometry": {"coordinates":[152.99307250999999,-27.5642814636],"type":"Point"}
}