{
  "type": "Feature",
  "properties": {
    "addr:full":"113b Booth St Annandale NSW 2038",
    "addr:housenumber":"113b",
    "addr:postcode":"2038",
    "addr:street":"Booth St",
    "iso:country":"AU",
    "sg:address":"113b Booth St",
    "sg:city":"Annandale",
    "sg:classifiers":[
        {
            "category":"Health Services",
            "subcategory":"Health Practitioner",
            "type":"Services"
        }
    ],
    "sg:phone":"+61 2 9692 9016",
    "sg:postcode":"2038",
    "sg:province":"NSW",
    "sg:tags":[
        "acupuncture"
    ],
    "wof:name":"Ngaio Richards",
    "wof:placetype":"venue"
},
  "geometry": {"coordinates":[151.17088317899999,-33.8813438416],"type":"Point"}
}