{
  "type": "Feature",
  "properties": {
    "addr:full":"20 Thomas St Ferntree Gully VIC 3156",
    "addr:housenumber":"20",
    "addr:postcode":"3156",
    "addr:street":"Thomas St",
    "iso:country":"AU",
    "sg:address":"20 Thomas St",
    "sg:city":"Ferntree Gully",
    "sg:classifiers":[
        {
            "category":"Building & Trades",
            "subcategory":"Construction",
            "type":"Services"
        }
    ],
    "sg:phone":"+61 3 9756 0122",
    "sg:postcode":"3156",
    "sg:province":"VIC",
    "sg:tags":[
        "welding"
    ],
    "wof:name":"Brisk Welding",
    "wof:placetype":"venue"
},
  "geometry": {"coordinates":[145.281860352,-37.8865127563],"type":"Point"}
}