{
  "type": "Feature",
  "properties": {
    "addr:full":"Shp 1/ 610 Collins St Melbourne VIC 3000",
    "addr:housenumber":"/ 610",
    "addr:postcode":"3000",
    "addr:street":"Collins St",
    "iso:country":"AU",
    "sg:address":"Shp 1/ 610 Collins St",
    "sg:city":"Melbourne",
    "sg:classifiers":[
        {
            "category":"Manufacturing",
            "subcategory":"Food",
            "type":"Manufacturing & Wholesale Goods"
        }
    ],
    "sg:phone":"+61 3 9620 5255",
    "sg:postcode":"3000",
    "sg:province":"VIC",
    "sg:tags":[
        "function",
        "catering"
    ],
    "wof:name":"J Ts Fine Catering",
    "wof:placetype":"venue"
},
  "geometry": {"coordinates":[144.95449829099999,-37.8188362122],"type":"Point"}
}