{
  "type": "Feature",
  "properties": {
    "iso:country":"AU",
    "sg:address":"19 Ferdinand St",
    "sg:city":"Campbell",
    "sg:classifiers":[
        {
            "category":"Education",
            "subcategory":"Music School",
            "type":"Public Place"
        }
    ],
    "sg:phone":"+61 2 6247 0002",
    "sg:postcode":"2612",
    "sg:province":"ACT",
    "sg:tags":[
        "therapy",
        "relaxation"
    ],
    "wof:name":"Marie Ray",
    "wof:placetype":"venue"
},
  "geometry": {"coordinates":[149.15428161599999,-35.2816200256],"type":"Point"}
}