{
  "type": "Feature",
  "properties": {
    "addr:full":"17 Gaspian Crt Woodcroft SA 5162",
    "addr:housenumber":"17",
    "addr:postcode":"5162",
    "addr:street":"Gaspian Crt",
    "iso:country":"AU",
    "sg:address":"17 Gaspian Crt",
    "sg:city":"Woodcroft",
    "sg:classifiers":[
        {
            "category":"Building & Trades",
            "subcategory":"Construction",
            "type":"Services"
        }
    ],
    "sg:phone":"+61 8 8381 4885",
    "sg:postcode":"5162",
    "sg:province":"SA",
    "sg:tags":[
        "earth",
        "excavating",
        "moving",
        "contractor"
    ],
    "wof:name":"S & B Landscaping",
    "wof:placetype":"venue"
},
  "geometry": {"coordinates":[138.55705261200001,-35.1035385132],"type":"Point"}
}