{
  "type": "Feature",
  "properties": {
    "addr:full":"50 Beaufort St Woodville Park SA 5011",
    "addr:housenumber":"50",
    "addr:postcode":"5011",
    "addr:street":"Beaufort St",
    "iso:country":"AU",
    "sg:address":"50 Beaufort St",
    "sg:city":"Woodville Park",
    "sg:classifiers":[
        {
            "category":"Social Services",
            "subcategory":"Child Care",
            "type":"Services"
        }
    ],
    "sg:phone":"+61 8 8445 6573",
    "sg:postcode":"5011",
    "sg:province":"SA",
    "sg:tags":[
        "baby",
        "sitter"
    ],
    "wof:name":"Goyan M",
    "wof:placetype":"venue"
},
  "geometry": {"coordinates":[138.547042847,-34.8796691895],"type":"Point"}
}