{
  "type": "Feature",
  "properties": {
    "addr:full":"103 Peter St Wagga Wagga NSW 2650",
    "addr:housenumber":"103",
    "addr:postcode":"2650",
    "addr:street":"Peter St",
    "iso:country":"AU",
    "sg:address":"103 Peter St",
    "sg:city":"Wagga Wagga",
    "sg:classifiers":[
        {
            "category":"Real Estate",
            "subcategory":"Surveying",
            "type":"Services"
        }
    ],
    "sg:phone":"+61 2 6921 3312",
    "sg:postcode":"2650",
    "sg:province":"NSW",
    "sg:tags":[
        "surveyor",
        "land"
    ],
    "wof:name":"Esler & Associates",
    "wof:placetype":"venue"
},
  "geometry": {"coordinates":[147.36863708499999,-35.1126403809],"type":"Point"}
}