{
  "type": "Feature",
  "properties": {
    "iso:country":"AU",
    "sg:address":"Fact 57, 174 Bridge Rd",
    "sg:city":"Keysborough",
    "sg:classifiers":[
        {
            "category":"Retail",
            "subcategory":"Repair Shop",
            "type":"Services"
        }
    ],
    "sg:phone":"+61 3 9769 0633",
    "sg:postcode":"3173",
    "sg:province":"VIC",
    "sg:tags":[
        "upholsterer"
    ],
    "wof:name":"Rickard Upholstery",
    "wof:placetype":"venue"
},
  "geometry": {"coordinates":[145.19247436500001,-37.9838867188],"type":"Point"}
}