{
  "type": "Feature",
  "properties": {
    "iso:country":"AU",
    "sg:address":"5 Blackburn St",
    "sg:city":"Pearce",
    "sg:classifiers":[
        {
            "category":"Education",
            "subcategory":"University",
            "type":"Public Place"
        }
    ],
    "sg:phone":"+61 2 6286 3652",
    "sg:postcode":"2607",
    "sg:province":"ACT",
    "sg:tags":[
        "educational",
        "organisation",
        "cultural"
    ],
    "wof:name":"Canberra Art Workshop Inc",
    "wof:placetype":"venue"
},
  "geometry": {"coordinates":[149.07754516599999,-35.3598060608],"type":"Point"}
}