{
  "type": "Feature",
  "properties": {
    "addr:full":"932 South Rd Edwardstown SA 5039",
    "addr:housenumber":"932",
    "addr:postcode":"5039",
    "addr:street":"South Rd",
    "iso:country":"AU",
    "sg:address":"932 South Rd",
    "sg:city":"Edwardstown",
    "sg:classifiers":[
        {
            "category":"Health Services",
            "subcategory":"Doctor",
            "type":"Services"
        }
    ],
    "sg:phone":"+61 8 8351 1909",
    "sg:postcode":"5039",
    "sg:province":"SA",
    "sg:tags":[
        "medical",
        "practitioner"
    ],
    "wof:name":"Edwardstown Medical Centre",
    "wof:placetype":"venue"
},
  "geometry": {"coordinates":[138.57347106899999,-34.9765281677],"type":"Point"}
}