{
  "type": "Feature",
  "properties": {
    "iso:country":"AU",
    "sg:address":"113 Bridge St",
    "sg:city":"West Tamworth",
    "sg:classifiers":[
        {
            "category":"Fast Food",
            "type":"Food & Drink"
        }
    ],
    "sg:phone":"+61 2 6765 7049",
    "sg:postcode":"2340",
    "sg:province":"NSW",
    "sg:tags":[
        "away",
        "take"
    ],
    "wof:name":"Chung Kin Chinese Restaurant",
    "wof:placetype":"venue"
},
  "geometry": {"coordinates":[150.91169738799999,-31.0953731537],"type":"Point"}
}