{
  "type": "Feature",
  "properties": {
    "addr:full":"267 Anzac Hwy Plympton SA 5038",
    "addr:housenumber":"267",
    "addr:postcode":"5038",
    "addr:street":"Anzac Hwy",
    "iso:country":"AU",
    "sg:address":"267 Anzac Hwy",
    "sg:city":"Plympton",
    "sg:classifiers":[
        {
            "category":"Government",
            "subcategory":"Court House",
            "type":"Public Place"
        }
    ],
    "sg:phone":"+61 8 8297 7887",
    "sg:postcode":"5038",
    "sg:province":"SA",
    "sg:tags":[
        "personal",
        "marriage",
        "family",
        "counselling"
    ],
    "wof:name":"George Walker & Associates",
    "wof:placetype":"venue"
},
  "geometry": {"coordinates":[138.55674743599999,-34.9624671936],"type":"Point"}
}