{
  "type": "Feature",
  "properties": {
    "iso:country":"AU",
    "sg:address":"162 Hogan St",
    "sg:city":"Tatura",
    "sg:classifiers":[
        {
            "category":"Travel",
            "subcategory":"Hotels & Motels",
            "type":"Entertainment"
        }
    ],
    "sg:phone":"+61 3 5824 1891",
    "sg:postcode":"3616",
    "sg:province":"VIC",
    "sg:tags":[
        "accommodation"
    ],
    "wof:name":"Criterion Hotel",
    "wof:placetype":"venue"
},
  "geometry": {"coordinates":[145.22903442399999,-36.4402427673],"type":"Point"}
}