{
  "type": "Feature",
  "properties": {
    "iso:country":"AU",
    "sg:address":"24 Mary Ave",
    "sg:city":"Highett",
    "sg:classifiers":[
        {
            "category":"Real Estate",
            "subcategory":"Architect",
            "type":"Services"
        }
    ],
    "sg:phone":"+61 3 9555 6355",
    "sg:postcode":"3190",
    "sg:province":"VIC",
    "sg:tags":[
        "fuel",
        "equipment",
        "pump",
        "carburettor"
    ],
    "wof:name":"Sandy Carbies",
    "wof:placetype":"venue"
},
  "geometry": {"coordinates":[145.03805542000001,-37.9550018311],"type":"Point"}
}