{
  "type": "Feature",
  "properties": {
    "iso:country":"AU",
    "sg:address":"Fulham Rd",
    "sg:city":"Pimlico",
    "sg:classifiers":[
        {
            "category":"Education",
            "subcategory":"School",
            "type":"Public Place"
        }
    ],
    "sg:phone":"+61 7 4759 3444",
    "sg:postcode":"4812",
    "sg:province":"QLD",
    "sg:tags":[
        "state",
        "except",
        "nsw"
    ],
    "wof:name":"Pimlico High School",
    "wof:placetype":"venue"
},
  "geometry": {"coordinates":[146.787384,-19.289333],"type":"Point"}
}