{
  "type": "Feature",
  "properties": {
    "addr:full":"Level 5 Shop 5049 Westfield Parramatta Parramatta NSW 2150",
    "addr:housenumber":"shop 5049 westfield",
    "addr:postcode":"2150",
    "iso:country":"AU",
    "sg:address":"Level 5 Shop 5049 Westfield Parramatta",
    "sg:city":"Parramatta",
    "sg:classifiers":[
        {
            "category":"Wholesale",
            "subcategory":"Machinery & Supplies",
            "type":"Manufacturing & Wholesale Goods"
        }
    ],
    "sg:phone":"+61 2 9635 8977",
    "sg:postcode":"2150",
    "sg:province":"NSW",
    "sg:tags":[
        "equipment",
        "welding"
    ],
    "wof:name":"Straight From The Heart",
    "wof:placetype":"venue"
},
  "geometry": {"coordinates":[151.00479125999999,-33.8275146484],"type":"Point"}
}