{
  "type": "Feature",
  "properties": {
    "addr:full":"276 Formosa Rd Milton QLD 4064",
    "addr:housenumber":"276",
    "addr:postcode":"4064",
    "addr:street":"Formosa Rd",
    "iso:country":"AU",
    "sg:address":"276 Formosa Rd",
    "sg:city":"Milton",
    "sg:classifiers":[
        {
            "category":"Insurance",
            "subcategory":"Insurance Agent",
            "type":"Services"
        }
    ],
    "sg:phone":"+61 7 3390 6600",
    "sg:postcode":"4064",
    "sg:province":"QLD",
    "wof:name":"Barclay M.I.S Risk Management",
    "wof:placetype":"venue"
},
  "geometry": {"coordinates":[153.0052948,-27.4685897827],"type":"Point"}
}