{
  "type": "Feature",
  "properties": {
    "addr:full":"28 Hawthorne Ave Chatswood NSW 2067",
    "addr:housenumber":"28",
    "addr:postcode":"2067",
    "addr:street":"Hawthorne Ave",
    "iso:country":"AU",
    "sg:address":"28 Hawthorne Ave",
    "sg:city":"Chatswood",
    "sg:classifiers":[
        {
            "category":"Professional",
            "subcategory":"Art Services",
            "type":"Services"
        }
    ],
    "sg:phone":"+61 412 235 368",
    "sg:postcode":"2067",
    "sg:province":"NSW",
    "sg:tags":[
        "picture",
        "frame",
        "framing"
    ],
    "wof:name":"Frank's Picture Framing",
    "wof:placetype":"venue"
},
  "geometry": {"coordinates":[151.163574219,-33.7958488464],"type":"Point"}
}