{
  "type": "Feature",
  "properties": {
    "iso:country":"AU",
    "sg:address":"9 Bridge St",
    "sg:city":"Eltham",
    "sg:classifiers":[
        {
            "category":"Utilities",
            "subcategory":"Fuel Oil & Lpg",
            "type":"Services"
        }
    ],
    "sg:phone":"+61 3 9439 9066",
    "sg:postcode":"3095",
    "sg:province":"VIC",
    "sg:tags":[
        "merchant"
    ],
    "wof:name":"Eltham Fuel Supply",
    "wof:placetype":"venue"
},
  "geometry": {"coordinates":[145.138946533,-37.7177734375],"type":"Point"}
}