{
  "type": "Feature",
  "properties": {
    "iso:country":"AU",
    "sg:address":"4/ 25 Research Rd",
    "sg:city":"Pooraka",
    "sg:classifiers":[
        {
            "category":"Education",
            "subcategory":"Dance Studio",
            "type":"Public Place"
        }
    ],
    "sg:phone":"+61 8 8349 4377",
    "sg:postcode":"5095",
    "sg:province":"SA",
    "sg:tags":[
        "venue",
        "tuition"
    ],
    "wof:name":"Dance Force",
    "wof:placetype":"venue"
},
  "geometry": {"coordinates":[138.63502502399999,-34.8163642883],"type":"Point"}
}