{
  "type": "Feature",
  "properties": {
    "addr:full":"7 Kildonan. St Aspley QLD 4034",
    "addr:housenumber":"7",
    "addr:postcode":"4034",
    "addr:street":"Kildonan. St",
    "iso:country":"AU",
    "sg:address":"7 Kildonan. St",
    "sg:city":"Aspley",
    "sg:classifiers":[
        {
            "category":"Building & Trades",
            "subcategory":"Construction",
            "type":"Services"
        }
    ],
    "sg:phone":"+61 7 3350 2505",
    "sg:postcode":"4034",
    "sg:province":"QLD",
    "sg:tags":[
        "joiner",
        "carpenter"
    ],
    "wof:name":"Graham Dick Builders",
    "wof:placetype":"venue"
},
  "geometry": {"coordinates":[153.02304100000001,-27.375273],"type":"Point"}
}