{
  "type": "Feature",
  "properties": {
    "iso:country":"AU",
    "sg:address":"14- 16 Hartnett Drv",
    "sg:city":"Seaford",
    "sg:classifiers":[
        {
            "category":"Retail",
            "subcategory":"Auto Repair",
            "type":"Services"
        }
    ],
    "sg:phone":"+61 3 9776 8899",
    "sg:postcode":"3198",
    "sg:province":"VIC",
    "sg:tags":[
        "electrical"
    ],
    "wof:name":"Bayside Auto Electrical",
    "wof:placetype":"venue"
},
  "geometry": {"coordinates":[145.141479492,-38.1124534607],"type":"Point"}
}