{
  "type": "Feature",
  "properties": {
    "addr:full":"297 Bringelly Rd Leppington NSW 2171",
    "addr:housenumber":"297",
    "addr:postcode":"2171",
    "addr:street":"Bringelly Rd",
    "iso:country":"AU",
    "sg:address":"297 Bringelly Rd",
    "sg:city":"Leppington",
    "sg:classifiers":[
        {
            "category":"Social Services",
            "subcategory":"Child Care",
            "type":"Services"
        }
    ],
    "sg:phone":"+61 2 9606 7002",
    "sg:postcode":"2171",
    "sg:province":"NSW",
    "wof:name":"Little Amigos Child Care & Early Learning Centre",
    "wof:placetype":"venue"
},
  "geometry": {"coordinates":[150.80778503400001,-33.9506263733],"type":"Point"}
}