{
  "type": "Feature",
  "properties": {
    "addr:full":"Ste3/ 10 Brookfield Rd Kenmore QLD 4069",
    "addr:housenumber":"10",
    "addr:postcode":"4069",
    "addr:street":"Brookfield Rd",
    "iso:country":"AU",
    "sg:address":"Ste3/ 10 Brookfield Rd",
    "sg:city":"Kenmore",
    "sg:classifiers":[
        {
            "category":"Personal",
            "type":"Services"
        }
    ],
    "sg:phone":"+61 7 3878 7185",
    "sg:postcode":"4069",
    "sg:province":"QLD",
    "sg:tags":[
        "reducing",
        "treatment",
        "weight"
    ],
    "wof:name":"Curves At Kenmore",
    "wof:placetype":"venue"
},
  "geometry": {"coordinates":[152.938323975,-27.507194519],"type":"Point"}
}