{
  "type": "Feature",
  "properties": {
    "iso:country":"AU",
    "sg:address":"Cnr Flint & Bathurst Sts",
    "sg:city":"Forbes",
    "sg:classifiers":[
        {
            "category":"Home & Garden",
            "subcategory":"Household Appliances",
            "type":"Retail Goods"
        }
    ],
    "sg:phone":"+61 2 6852 1955",
    "sg:postcode":"2871",
    "sg:province":"NSW",
    "sg:tags":[
        "heating",
        "system"
    ],
    "wof:name":"AGL Energy Shop Forbes",
    "wof:placetype":"venue"
},
  "geometry": {"coordinates":[148.015427,-33.398842],"type":"Point"}
}