{
  "type": "Feature",
  "properties": {
    "iso:country":"AU",
    "sg:address":"15 Commercial Rd",
    "sg:city":"Ferntree Gully",
    "sg:classifiers":[
        {
            "category":"Building & Trades",
            "subcategory":"Construction",
            "type":"Services"
        }
    ],
    "sg:phone":"+61 3 9758 3404",
    "sg:postcode":"3156",
    "sg:province":"VIC",
    "sg:tags":[
        "earth",
        "excavating",
        "moving",
        "contractor"
    ],
    "wof:name":"Campbell Excavations",
    "wof:placetype":"venue"
},
  "geometry": {"coordinates":[145.281646728,-37.8798179626],"type":"Point"}
}