{
  "type": "Feature",
  "properties": {
    "addr:full":"Shop 3 558B Pennant Hills Rd West Pennant Hills NSW 2125",
    "addr:housenumber":"shop 3 558b",
    "addr:postcode":"2125",
    "addr:street":"Pennant Hills Rd",
    "iso:country":"AU",
    "sg:address":"Shop 3 558B Pennant Hills Rd",
    "sg:city":"West Pennant Hills",
    "sg:classifiers":[
        {
            "category":"Food & Beverages",
            "subcategory":"Bakery",
            "type":"Retail Goods"
        }
    ],
    "sg:phone":"+61 2 9980 6100",
    "sg:postcode":"2125",
    "sg:province":"NSW",
    "sg:tags":[
        "baker"
    ],
    "wof:name":"Bakers Delight Ltd",
    "wof:placetype":"venue"
},
  "geometry": {"coordinates":[151.04745483400001,-33.7538948059],"type":"Point"}
}