{
  "type": "Feature",
  "properties": {
    "addr:full":"15 Davidson Pl Carrara QLD 4211",
    "addr:housenumber":"15",
    "addr:postcode":"4211",
    "addr:street":"Pl",
    "iso:country":"AU",
    "sg:address":"15 Davidson Pl",
    "sg:city":"Carrara",
    "sg:classifiers":[
        {
            "category":"Building & Trades",
            "subcategory":"Construction",
            "type":"Services"
        }
    ],
    "sg:phone":"+61 412 268 485",
    "sg:postcode":"4211",
    "sg:province":"QLD",
    "sg:tags":[
        "plasterboard",
        "plasterer",
        "fixer"
    ],
    "wof:name":"Sanford M & J",
    "wof:placetype":"venue"
},
  "geometry": {"coordinates":[153.364303589,-28.0198669434],"type":"Point"}
}