{
  "type": "Feature",
  "properties": {
    "addr:full":"Lot 3 Moores Rd Toowoomba QLD 4350",
    "addr:postcode":"4350",
    "addr:street":"Moores Rd",
    "iso:country":"AU",
    "sg:address":"Lot 3 Moores Rd",
    "sg:city":"Toowoomba",
    "sg:classifiers":[
        {
            "category":"Building & Trades",
            "subcategory":"Pest Control",
            "type":"Services"
        }
    ],
    "sg:phone":"+61 7 4634 1350",
    "sg:postcode":"4350",
    "sg:province":"QLD",
    "sg:tags":[
        "horse",
        "transport"
    ],
    "wof:name":"Higgins Thoroughbred Transport",
    "wof:placetype":"venue"
},
  "geometry": {"coordinates":[151.89042699999999,-27.54265],"type":"Point"}
}