{
  "type": "Feature",
  "properties": {
    "addr:full":"Shop 3,The Mortimer Centre,90- 94 Mortimer St, Mudgee NSW 2850",
    "addr:housenumber":"shop 3;90 94",
    "addr:postcode":"2850",
    "addr:street":"The;Mortimer St",
    "iso:country":"AU",
    "sg:address":"Shop 3,The Mortimer Centre,90- 94",
    "sg:city":"Mortimer St, Mudgee",
    "sg:classifiers":[
        {
            "category":"Building & Trades",
            "subcategory":"Construction",
            "type":"Services"
        }
    ],
    "sg:phone":"+61 1300 138 657",
    "sg:postcode":"2850",
    "sg:province":"NSW",
    "sg:tags":[
        "management"
    ],
    "wof:name":"Barnson",
    "wof:placetype":"venue"
},
  "geometry": {"coordinates":[149.57728599999999,-32.59174],"type":"Point"}
}