{
  "type": "Feature",
  "properties": {
    "addr:full":"LWM House, Lvl 1, 106 Erina Gosford NSW 2250",
    "addr:housenumber":"106",
    "addr:postcode":"2250",
    "iso:country":"AU",
    "sg:address":"LWM House, Lvl 1, 106",
    "sg:city":"Erina Gosford",
    "sg:classifiers":[
        {
            "category":"Professional",
            "subcategory":"Accounting & Tax Preparation",
            "type":"Services"
        }
    ],
    "sg:phone":"+61 2 4324 2988",
    "sg:postcode":"2250",
    "sg:province":"NSW",
    "sg:tags":[
        "accountant",
        "auditor"
    ],
    "wof:name":"LWM Group",
    "wof:placetype":"venue"
},
  "geometry": {"coordinates":[151.34271240199999,-33.4248847961],"type":"Point"}
}