{
  "type": "Feature",
  "properties": {
    "iso:country":"AU",
    "sg:address":"20 Lynor Ave",
    "sg:city":"Para Hills",
    "sg:classifiers":[
        {
            "category":"Building & Trades",
            "subcategory":"Plumbing",
            "type":"Services"
        }
    ],
    "sg:phone":"+61 8 8265 9606",
    "sg:postcode":"5096",
    "sg:province":"SA",
    "sg:tags":[
        "plumber",
        "gasfitters"
    ],
    "wof:name":"Odd Hours Service",
    "wof:placetype":"venue"
},
  "geometry": {"coordinates":[138.666915894,-34.8132705688],"type":"Point"}
}