{
  "type": "Feature",
  "properties": {
    "addr:full":"Church St Medical Centre, 144 Church St Parramatta NSW 2150",
    "addr:housenumber":"144",
    "addr:postcode":"2150",
    "addr:street":"Church;Church St",
    "iso:country":"AU",
    "sg:address":"Church St Medical Centre, 144 Church St",
    "sg:city":"Parramatta",
    "sg:classifiers":[
        {
            "category":"Health Services",
            "subcategory":"Doctor",
            "type":"Services"
        }
    ],
    "sg:phone":"+61 2 9893 8733",
    "sg:postcode":"2150",
    "sg:province":"NSW",
    "sg:tags":[
        "medical",
        "practitioner"
    ],
    "wof:name":"X-Ray Centre The",
    "wof:placetype":"venue"
},
  "geometry": {"coordinates":[151.177856445,-33.9131889343],"type":"Point"}
}