{
  "type": "Feature",
  "properties": {
    "iso:country":"AU",
    "sg:address":"46 Hudson Crs",
    "sg:city":"Lavington",
    "sg:classifiers":[
        {
            "category":"Retail",
            "subcategory":"Auto Repair",
            "type":"Services"
        }
    ],
    "sg:phone":"+61 2 6040 4640",
    "sg:postcode":"2641",
    "sg:province":"NSW",
    "sg:tags":[
        "muffler",
        "exhaust",
        "system"
    ],
    "wof:name":"Humex Exhausts",
    "wof:placetype":"venue"
},
  "geometry": {"coordinates":[146.948974609,-36.0430412292],"type":"Point"}
}