{
  "type": "Feature",
  "properties": {
    "addr:full":"281 Rex Rd Campbellfield VIC 3061",
    "addr:housenumber":"281",
    "addr:postcode":"3061",
    "addr:street":"Rex Rd",
    "iso:country":"AU",
    "sg:address":"281 Rex Rd",
    "sg:city":"Campbellfield",
    "sg:classifiers":[
        {
            "category":"Wholesale",
            "subcategory":"Machinery & Supplies",
            "type":"Manufacturing & Wholesale Goods"
        }
    ],
    "sg:phone":"+61 3 9357 9575",
    "sg:postcode":"3061",
    "sg:province":"VIC",
    "sg:tags":[
        "equipment",
        "system",
        "elevating",
        "conveying"
    ],
    "wof:name":"Conveyor Industries Pty Ltd",
    "wof:placetype":"venue"
},
  "geometry": {"coordinates":[144.96295165999999,-37.6470527649],"type":"Point"}
}