{
  "type": "Feature",
  "properties": {
    "iso:country":"AU",
    "sg:address":"69 King St",
    "sg:city":"Perth",
    "sg:classifiers":[
        {
            "category":"Manufacturing",
            "subcategory":"Jewelry",
            "type":"Manufacturing & Wholesale Goods"
        }
    ],
    "sg:phone":"+61 8 9481 0057",
    "sg:postcode":"6000",
    "sg:province":"WA",
    "sg:tags":[
        "mfrg",
        "jeweller"
    ],
    "wof:name":"World Fashion Agency",
    "wof:placetype":"venue"
},
  "geometry": {"coordinates":[115.855392456,-31.9510593414],"type":"Point"}
}