{
  "type": "Feature",
  "properties": {
    "iso:country":"AU",
    "sg:address":"PO Box 390",
    "sg:city":"Creswick",
    "sg:classifiers":[
        {
            "category":"Home & Garden",
            "subcategory":"Building Materials",
            "type":"Retail Goods"
        }
    ],
    "sg:phone":"+61 3 5345 6229",
    "sg:postcode":"3363",
    "sg:province":"VIC",
    "sg:tags":[
        "fencing"
    ],
    "wof:name":"Hepburn Fencing",
    "wof:placetype":"venue"
},
  "geometry": {"coordinates":[143.894897461,-37.4234008789],"type":"Point"}
}