{
  "type": "Feature",
  "properties": {
    "iso:country":"AU",
    "sg:address":"361 Napier St",
    "sg:city":"Bendigo",
    "sg:classifiers":[
        {
            "category":"Health Services",
            "subcategory":"Health Practitioner",
            "type":"Services"
        }
    ],
    "sg:phone":"+61 3 5442 4710",
    "sg:postcode":"3550",
    "sg:province":"VIC",
    "sg:tags":[
        "osteopath"
    ],
    "wof:name":"Jessica Cunningham",
    "wof:placetype":"venue"
},
  "geometry": {"coordinates":[144.296951294,-36.7414855957],"type":"Point"}
}