{
  "type": "Feature",
  "properties": {
    "addr:full":"48 Caravan Head Rd Oyster Bay NSW 2225",
    "addr:housenumber":"48",
    "addr:postcode":"2225",
    "addr:street":"Caravan Head Rd",
    "iso:country":"AU",
    "sg:address":"48 Caravan Head Rd",
    "sg:city":"Oyster Bay",
    "sg:classifiers":[
        {
            "category":"Manufacturing",
            "subcategory":"Tools & Machinery",
            "type":"Manufacturing & Wholesale Goods"
        }
    ],
    "sg:phone":"+61 2 9528 9632",
    "sg:postcode":"2225",
    "sg:province":"NSW",
    "wof:name":"The Tool Van",
    "wof:placetype":"venue"
},
  "geometry": {"coordinates":[151.08172607399999,-34.0030708313],"type":"Point"}
}