{
  "type": "Feature",
  "properties": {
    "iso:country":"AU",
    "sg:address":"19 Harnett Drv",
    "sg:city":"Seaford",
    "sg:classifiers":[
        {
            "category":"Home & Garden",
            "subcategory":"Building Materials",
            "type":"Retail Goods"
        }
    ],
    "sg:phone":"+61 13 63 60",
    "sg:postcode":"3198",
    "sg:province":"VIC",
    "sg:tags":[
        "merchant",
        "glass",
        "glazier"
    ],
    "wof:name":"Tint.A.Car",
    "wof:placetype":"venue"
},
  "geometry": {"coordinates":[145.14195251500001,-38.1124954224],"type":"Point"}
}