{
  "type": "Feature",
  "properties": {
    "addr:full":"48 Barker Rd Strathfield NSW 2135",
    "addr:housenumber":"48",
    "addr:postcode":"2135",
    "addr:street":"Barker Rd",
    "iso:country":"AU",
    "sg:address":"48 Barker Rd",
    "sg:city":"Strathfield",
    "sg:classifiers":[
        {
            "category":"Real Estate",
            "subcategory":"Real Estate Agent",
            "type":"Services"
        }
    ],
    "sg:phone":"+61 2 9746 7771",
    "sg:postcode":"2135",
    "sg:province":"NSW",
    "wof:name":"Real Estate World Pty Ltd",
    "wof:placetype":"venue"
},
  "geometry": {"coordinates":[151.07791137699999,-33.8769760132],"type":"Point"}
}