{
  "type": "Feature",
  "properties": {
    "addr:full":"Shop 2 Douglas St Thursday Island QLD 4875",
    "addr:housenumber":"shop 2",
    "addr:postcode":"4875",
    "addr:street":"Douglas St",
    "iso:country":"AU",
    "sg:address":"Shop 2 Douglas St",
    "sg:city":"Thursday Island",
    "sg:classifiers":[
        {
            "category":"Personal",
            "subcategory":"Beauty Salon",
            "type":"Services"
        }
    ],
    "sg:phone":"+61 7 4069 2405",
    "sg:postcode":"4875",
    "sg:province":"QLD",
    "sg:tags":[
        "hairdresser"
    ],
    "wof:name":"Dreamtime Hair Studio",
    "wof:placetype":"venue"
},
  "geometry": {"coordinates":[142.21601867699999,-10.5837574005],"type":"Point"}
}