{
  "type": "Feature",
  "properties": {
    "addr:full":"314 William St Northbridge WA 6003",
    "addr:housenumber":"314",
    "addr:postcode":"6003",
    "addr:street":"William St",
    "iso:country":"AU",
    "sg:address":"314 William St",
    "sg:city":"Northbridge",
    "sg:classifiers":[
        {
            "category":"Shopping",
            "subcategory":"Discount & Variety Stores",
            "type":"Retail Goods"
        }
    ],
    "sg:phone":"+61 8 9227 9883",
    "sg:postcode":"6003",
    "sg:province":"WA",
    "sg:tags":[
        "shop",
        "adult"
    ],
    "wof:name":"Risque Erotica",
    "wof:placetype":"venue"
},
  "geometry": {"coordinates":[115.861000061,-31.9466209412],"type":"Point"}
}