{
  "type": "Feature",
  "properties": {
    "iso:country":"AU",
    "sg:address":"University Drv",
    "sg:city":"Mt Helen",
    "sg:classifiers":[
        {
            "category":"Professional",
            "subcategory":"Art Services",
            "type":"Services"
        }
    ],
    "sg:phone":"+61 3 5330 2800",
    "sg:postcode":"3350",
    "sg:province":"VIC",
    "sg:tags":[
        "graphic",
        "designer"
    ],
    "wof:name":"Colourfield Creative",
    "wof:placetype":"venue"
},
  "geometry": {"coordinates":[143.880157,-37.624775],"type":"Point"}
}