{
  "type": "Feature",
  "properties": {
    "iso:country":"AU",
    "sg:address":"26 Howleys Rd",
    "sg:city":"Notting Hill",
    "sg:classifiers":[
        {
            "category":"Building & Trades",
            "subcategory":"Construction",
            "type":"Services"
        }
    ],
    "sg:phone":"+61 3 9562 9997",
    "sg:postcode":"3168",
    "sg:province":"VIC",
    "sg:tags":[
        "equipment",
        "system",
        "automation"
    ],
    "wof:name":"Intemation Engineering Pty Ltd",
    "wof:placetype":"venue"
},
  "geometry": {"coordinates":[145.138183594,-37.9022827148],"type":"Point"}
}