{
  "type": "Feature",
  "properties": {
    "iso:country":"AU",
    "sg:address":"170 Smith St",
    "sg:city":"Naracoorte",
    "sg:classifiers":[
        {
            "category":"Professional",
            "type":"Services"
        }
    ],
    "sg:phone":"+61 8 8762 0999",
    "sg:postcode":"5271",
    "sg:province":"SA",
    "sg:tags":[
        "courier"
    ],
    "wof:name":"Fastway Couriers",
    "wof:placetype":"venue"
},
  "geometry": {"coordinates":[140.745346,-36.955147],"type":"Point"}
}