{
  "type": "Feature",
  "properties": {
    "iso:country":"AU",
    "sg:address":"Shp 7 Swan View Shopng Cntr Malboro Rd",
    "sg:city":"Swan View",
    "sg:classifiers":[
        {
            "category":"Personal",
            "subcategory":"Beauty Salon",
            "type":"Services"
        }
    ],
    "sg:phone":"+61 8 9255 3419",
    "sg:postcode":"6056",
    "sg:province":"WA",
    "sg:tags":[
        "hairdresser"
    ],
    "wof:name":"Volona & Associates",
    "wof:placetype":"venue"
},
  "geometry": {"coordinates":[116.060546875,-31.889081955],"type":"Point"}
}