{
  "type": "Feature",
  "properties": {
    "iso:country":"AU",
    "sg:address":"6 Dawson St North",
    "sg:city":"Ballarat",
    "sg:classifiers":[
        {
            "category":"Real Estate",
            "subcategory":"Surveying",
            "type":"Services"
        }
    ],
    "sg:phone":"+61 3 5333 2699",
    "sg:postcode":"3350",
    "sg:province":"VIC",
    "sg:tags":[
        "surveyor",
        "land"
    ],
    "wof:name":"Steele Surveying Pty Ltd",
    "wof:placetype":"venue"
},
  "geometry": {"coordinates":[143.853607,-37.560822],"type":"Point"}
}