{
  "type": "Feature",
  "properties": {
    "iso:country":"AU",
    "sg:address":"10 Tanner St",
    "sg:city":"Breakwater",
    "sg:classifiers":[
        {
            "category":"Personal",
            "subcategory":"Beauty Salon",
            "type":"Services"
        }
    ],
    "sg:phone":"+61 3 5222 6576",
    "sg:postcode":"3219",
    "sg:province":"VIC",
    "sg:tags":[
        "hairdresser"
    ],
    "wof:name":"Pretty In Pink Hair Design",
    "wof:placetype":"venue"
},
  "geometry": {"coordinates":[144.369308472,-38.1767349243],"type":"Point"}
}