{
  "type": "Feature",
  "properties": {
    "iso:country":"AU",
    "sg:address":"PO Box 120",
    "sg:city":"Kingscote",
    "sg:classifiers":[
        {
            "category":"Communications",
            "subcategory":"News Services",
            "type":"Services"
        }
    ],
    "sg:phone":"+61 8 8553 2657",
    "sg:postcode":"5223",
    "sg:province":"SA",
    "sg:tags":[
        "information",
        "tourist",
        "attractions"
    ],
    "wof:name":"Kangaroo Island Tourist Services",
    "wof:placetype":"venue"
},
  "geometry": {"coordinates":[137.62815856899999,-35.6524391174],"type":"Point"}
}