{
  "type": "Feature",
  "properties": {
    "addr:full":"29 Walnut St Whittlesea VIC 3757",
    "addr:housenumber":"29",
    "addr:postcode":"3757",
    "addr:street":"Walnut St",
    "iso:country":"AU",
    "sg:address":"29 Walnut St",
    "sg:city":"Whittlesea",
    "sg:classifiers":[
        {
            "category":"Professional",
            "subcategory":"Accounting & Tax Preparation",
            "type":"Services"
        }
    ],
    "sg:phone":"+61 3 9716 1029",
    "sg:postcode":"3757",
    "sg:province":"VIC",
    "sg:tags":[
        "consultant",
        "taxation"
    ],
    "wof:name":"TAXAT Partners Pty Ltd",
    "wof:placetype":"venue"
},
  "geometry": {"coordinates":[145.118301,-37.511948],"type":"Point"}
}