{
  "type": "Feature",
  "properties": {
    "addr:full":"3/ 356 Manns Rd West Gosford NSW 2250",
    "addr:housenumber":"/ 356",
    "addr:postcode":"2250",
    "addr:street":"Manns Rd",
    "iso:country":"AU",
    "sg:address":"3/ 356 Manns Rd",
    "sg:city":"West Gosford",
    "sg:classifiers":[
        {
            "category":"Sports & Exercise",
            "subcategory":"Gym",
            "type":"Entertainment"
        }
    ],
    "sg:phone":"+61 2 4322 5209",
    "sg:postcode":"2250",
    "sg:province":"NSW",
    "sg:tags":[
        "health",
        "fitness"
    ],
    "wof:name":"Curves",
    "wof:placetype":"venue"
},
  "geometry": {"coordinates":[151.31933593799999,-33.4247207642],"type":"Point"}
}