{
  "type": "Feature",
  "properties": {
    "addr:full":"PO Box 2480 Boulder WA 6432",
    "addr:postcode":"6432",
    "iso:country":"AU",
    "sg:address":"PO Box 2480",
    "sg:city":"Boulder",
    "sg:classifiers":[
        {
            "category":"Professional",
            "type":"Services"
        }
    ],
    "sg:phone":"+61 8 9022 9877",
    "sg:postcode":"6432",
    "sg:province":"WA",
    "sg:tags":[
        "transport"
    ],
    "wof:name":"DCN Transport",
    "wof:placetype":"venue"
},
  "geometry": {"coordinates":[121.489463806,-30.7818393707],"type":"Point"}
}