{
  "type": "Feature",
  "properties": {
    "addr:full":"24 Bernard Crt Industrial Park Gawler Belt SA 5118",
    "addr:housenumber":"24",
    "addr:postcode":"5118",
    "addr:street":"Bernard Crt Industrial",
    "iso:country":"AU",
    "sg:address":"24 Bernard Crt",
    "sg:city":"Industrial Park Gawler Belt",
    "sg:classifiers":[
        {
            "category":"Wholesale",
            "subcategory":"Metals & Minerals",
            "type":"Manufacturing & Wholesale Goods"
        }
    ],
    "sg:phone":"+61 8 8523 2522",
    "sg:postcode":"5118",
    "sg:province":"SA",
    "sg:tags":[
        "steel",
        "merchant"
    ],
    "wof:name":"Boss Steel & Metal",
    "wof:placetype":"venue"
},
  "geometry": {"coordinates":[138.74766500000001,-34.567982],"type":"Point"}
}