{
  "type": "Feature",
  "properties": {
    "iso:country":"AU",
    "sg:address":"192 Ann St",
    "sg:city":"Brisbane",
    "sg:classifiers":[
        {
            "category":"Education",
            "subcategory":"Dance Studio",
            "type":"Public Place"
        }
    ],
    "sg:phone":"+61 7 3229 9196",
    "sg:postcode":"4000",
    "sg:province":"QLD",
    "sg:tags":[
        "instruction",
        "language"
    ],
    "wof:name":"Langports English Language College",
    "wof:placetype":"venue"
},
  "geometry": {"coordinates":[153.02517700199999,-27.4669017792],"type":"Point"}
}