{
  "type": "Feature",
  "properties": {
    "iso:country":"AU",
    "sg:address":"17 Farnley St",
    "sg:city":"Croydon",
    "sg:classifiers":[
        {
            "category":"Manufacturing",
            "subcategory":"Furniture",
            "type":"Manufacturing & Wholesale Goods"
        }
    ],
    "sg:phone":"+61 3 9725 9813",
    "sg:postcode":"3136",
    "sg:province":"VIC",
    "sg:tags":[
        "builder",
        "designer",
        "custom"
    ],
    "wof:name":"Bunyip Pine Furniture",
    "wof:placetype":"venue"
},
  "geometry": {"coordinates":[145.29867553700001,-37.7987213135],"type":"Point"}
}