{
  "type": "Feature",
  "properties": {
    "addr:full":"Cnr Medway St & Ipswich Rd Rocklea QLD 4106",
    "addr:postcode":"4106",
    "addr:street":"Cnr Medway St & Ipswich Rd",
    "iso:country":"AU",
    "sg:address":"Cnr Medway St & Ipswich Rd",
    "sg:city":"Rocklea",
    "sg:classifiers":[
        {
            "category":"Personal",
            "subcategory":"Barber",
            "type":"Services"
        }
    ],
    "sg:phone":"+61 7 3892 1470",
    "sg:postcode":"4106",
    "sg:province":"QLD",
    "wof:name":"Medway St Barber",
    "wof:placetype":"venue"
},
  "geometry": {"coordinates":[153.01133727999999,-27.5428180695],"type":"Point"}
}