{
  "type": "Feature",
  "properties": {
    "addr:full":"Tod St Gawler SA 5118",
    "addr:postcode":"5118",
    "addr:street":"Tod St",
    "iso:country":"AU",
    "sg:address":"Tod St",
    "sg:city":"Gawler",
    "sg:classifiers":[
        {
            "category":"Government",
            "subcategory":"Post Office",
            "type":"Public Place"
        }
    ],
    "sg:phone":"+61 13 13 18",
    "sg:postcode":"5118",
    "sg:province":"SA",
    "sg:tags":[
        "postal"
    ],
    "wof:name":"Australia Post",
    "wof:placetype":"venue"
},
  "geometry": {"coordinates":[138.74464399999999,-34.599213],"type":"Point"}
}