{
  "type": "Feature",
  "properties": {
    "addr:full":"1st Floor, 82 Main St Blacktown NSW 2148",
    "addr:housenumber":"82",
    "addr:postcode":"2148",
    "addr:street":"Main St",
    "iso:country":"AU",
    "sg:address":"1st Floor, 82 Main St",
    "sg:city":"Blacktown",
    "sg:classifiers":[
        {
            "category":"Health Services",
            "subcategory":"Dentist",
            "type":"Services"
        }
    ],
    "sg:phone":"+61 2 9831 7282",
    "sg:postcode":"2148",
    "sg:province":"NSW",
    "wof:name":"Dr Joanna Karefylakis & Dr Vicki Rozos",
    "wof:placetype":"venue"
},
  "geometry": {"coordinates":[150.90931701700001,-33.7703018188],"type":"Point"}
}