{
  "type": "Feature",
  "properties": {
    "addr:full":"324 Queens Pde Clifton Hill VIC 3068",
    "addr:housenumber":"324",
    "addr:postcode":"3068",
    "addr:street":"Queens Pde",
    "iso:country":"AU",
    "sg:address":"324 Queens Pde",
    "sg:city":"Clifton Hill",
    "sg:classifiers":[
        {
            "category":"Real Estate",
            "subcategory":"Real Estate Agent",
            "type":"Services"
        }
    ],
    "sg:phone":"+61 3 9481 6800",
    "sg:postcode":"3068",
    "sg:province":"VIC",
    "wof:name":"Jellis Craig Clifton Hill",
    "wof:placetype":"venue"
},
  "geometry": {"coordinates":[144.99026489299999,-37.7885475159],"type":"Point"}
}