{
  "type": "Feature",
  "properties": {
    "addr:full":"PO Box 4024 Ashmore QLD 4214",
    "addr:postcode":"4214",
    "iso:country":"AU",
    "sg:address":"PO Box 4024",
    "sg:city":"Ashmore",
    "sg:classifiers":[
        {
            "category":"Retail",
            "subcategory":"Auto Rental",
            "type":"Services"
        }
    ],
    "sg:phone":"+61 1800 260 294",
    "sg:postcode":"4214",
    "sg:province":"QLD",
    "sg:tags":[
        "chauffeur",
        "car",
        "hire",
        "driven",
        "limousine"
    ],
    "wof:name":"Paradise Cruiser",
    "wof:placetype":"venue"
},
  "geometry": {"coordinates":[153.38270568900001,-27.9863395691],"type":"Point"}
}