{
  "type": "Feature",
  "properties": {
    "iso:country":"AU",
    "sg:address":"cnr Moondara Drv & Nicklin Way",
    "sg:city":"Wurtulla",
    "sg:classifiers":[
        {
            "category":"Fast Food",
            "type":"Food & Drink"
        }
    ],
    "sg:phone":"+61 7 5493 2386",
    "sg:postcode":"4575",
    "sg:province":"QLD",
    "sg:tags":[
        "away",
        "take"
    ],
    "wof:name":"China Flute Gourmet Restaurant",
    "wof:placetype":"venue"
},
  "geometry": {"coordinates":[153.124146,-26.760635],"type":"Point"}
}