{
  "type": "Feature",
  "properties": {
    "addr:full":"1/ 3 Highview Ave Manly Vale NSW 2093",
    "addr:housenumber":"/ 3",
    "addr:postcode":"2093",
    "addr:street":"Highview Ave",
    "iso:country":"AU",
    "sg:address":"1/ 3 Highview Ave",
    "sg:city":"Manly Vale",
    "sg:classifiers":[
        {
            "category":"Banks & Credit Unions",
            "subcategory":"Bank",
            "type":"Services"
        }
    ],
    "sg:phone":"+61 414 792 287",
    "sg:postcode":"2093",
    "sg:province":"NSW",
    "sg:tags":[
        "broker",
        "mortgage"
    ],
    "wof:name":"Fowler Finances",
    "wof:placetype":"venue"
},
  "geometry": {"coordinates":[151.26495361299999,-33.7860488892],"type":"Point"}
}