{
  "type": "Feature",
  "properties": {
    "addr:full":"PO Box 70 Port Kembla NSW 2505",
    "addr:postcode":"2505",
    "iso:country":"AU",
    "sg:address":"PO Box 70",
    "sg:city":"Port Kembla",
    "sg:classifiers":[
        {
            "category":"Retail",
            "subcategory":"Laundry & Dry Cleaning",
            "type":"Services"
        }
    ],
    "sg:phone":"+61 405 079 570",
    "sg:postcode":"2505",
    "sg:province":"NSW",
    "sg:tags":[
        "cloth",
        "supply"
    ],
    "wof:name":"Russell Vale Rag Service",
    "wof:placetype":"venue"
},
  "geometry": {"coordinates":[150.90188599999999,-34.47971],"type":"Point"}
}