{
  "type": "Feature",
  "properties": {
    "addr:full":"Ponderosa Rd Rollingstone QLD 4816",
    "addr:postcode":"4816",
    "addr:street":"Ponderosa Rd",
    "iso:country":"AU",
    "sg:address":"Ponderosa Rd",
    "sg:city":"Rollingstone",
    "sg:classifiers":[
        {
            "category":"Farming",
            "subcategory":"Berry Farm",
            "type":"Manufacturing & Wholesale Goods"
        }
    ],
    "sg:phone":"+61 7 4770 8182",
    "sg:postcode":"4816",
    "sg:province":"QLD",
    "sg:tags":[
        "fruit",
        "grower"
    ],
    "wof:name":"Ollera Tropical Orchards",
    "wof:placetype":"venue"
},
  "geometry": {"coordinates":[146.315247,-18.992098],"type":"Point"}
}