{
  "type": "Feature",
  "properties": {
    "addr:full":"10 Palmer St North Mackay QLD 4740",
    "addr:housenumber":"10",
    "addr:postcode":"4740",
    "addr:street":"Palmer St",
    "iso:country":"AU",
    "sg:address":"10 Palmer St",
    "sg:city":"North Mackay",
    "sg:classifiers":[
        {
            "category":"Autos & Motor Vehicles",
            "subcategory":"Boat Sales",
            "type":"Retail Goods"
        }
    ],
    "sg:phone":"+61 7 4953 4752",
    "sg:postcode":"4740",
    "sg:province":"QLD",
    "sg:tags":[
        "equipment",
        "yacht"
    ],
    "wof:name":"Fishabout Marine Technologies",
    "wof:placetype":"venue"
},
  "geometry": {"coordinates":[149.19042999999999,-21.124624],"type":"Point"}
}