{
  "type": "Feature",
  "properties": {
    "addr:full":"30 Doris St Murrumbeena VIC 3163",
    "addr:housenumber":"30",
    "addr:postcode":"3163",
    "addr:street":"Doris St",
    "iso:country":"AU",
    "sg:address":"30 Doris St",
    "sg:city":"Murrumbeena",
    "sg:classifiers":[
        {
            "category":"Communications",
            "type":"Services"
        }
    ],
    "sg:phone":"+61 3 9562 6864",
    "sg:postcode":"3163",
    "sg:province":"VIC",
    "sg:tags":[
        "public",
        "system",
        "address"
    ],
    "wof:name":"Galjay Production Concepts Pty Ltd",
    "wof:placetype":"venue"
},
  "geometry": {"coordinates":[145.07258605999999,-37.9002799988],"type":"Point"}
}