{
  "type": "Feature",
  "properties": {
    "addr:full":"PO Box 249 Wingham NSW 2429",
    "addr:postcode":"2429",
    "iso:country":"AU",
    "sg:address":"PO Box 249",
    "sg:city":"Wingham",
    "sg:classifiers":[
        {
            "category":"Education",
            "subcategory":"Special Training",
            "type":"Public Place"
        }
    ],
    "sg:phone":"+61 2 6557 0397",
    "sg:postcode":"2429",
    "sg:province":"NSW",
    "sg:tags":[
        "development"
    ],
    "wof:name":"Bar International Training School",
    "wof:placetype":"venue"
},
  "geometry": {"coordinates":[152.36668399999999,-31.869881],"type":"Point"}
}