{
  "type": "Feature",
  "properties": {
    "addr:full":"401-403 High St Ashwood VIC 3147",
    "addr:housenumber":"401-403",
    "addr:postcode":"3147",
    "addr:street":"High St",
    "iso:country":"AU",
    "sg:address":"401-403 High St",
    "sg:city":"Ashwood",
    "sg:classifiers":[
        {
            "category":"Shopping",
            "subcategory":"Clothing, Apparel, & Fashions",
            "type":"Retail Goods"
        }
    ],
    "sg:phone":"+61 3 9885 4965",
    "sg:postcode":"3147",
    "sg:province":"VIC",
    "sg:tags":[
        "recycled",
        "clothing"
    ],
    "wof:name":"Baptcare Bargain Centre",
    "wof:placetype":"venue"
},
  "geometry": {"coordinates":[145.09280395499999,-37.8647994995],"type":"Point"}
}