{
  "type": "Feature",
  "properties": {
    "iso:country":"AU",
    "sg:address":"PO Box 437",
    "sg:city":"Mitcham",
    "sg:classifiers":[
        {
            "category":"Banks & Credit Unions",
            "subcategory":"Bank",
            "type":"Services"
        }
    ],
    "sg:phone":"+61 3 8802 4330",
    "sg:postcode":"3132",
    "sg:province":"VIC",
    "sg:tags":[
        "broker",
        "mortgage"
    ],
    "wof:name":"Key Finance Pty Ltd",
    "wof:placetype":"venue"
},
  "geometry": {"coordinates":[145.192596436,-37.8167114258],"type":"Point"}
}