{
  "type": "Feature",
  "properties": {
    "addr:full":". Drinie Rd Brandon QLD 4808",
    "addr:postcode":"4808",
    "addr:street":"Drinie Rd",
    "iso:country":"AU",
    "sg:address":". Drinie Rd",
    "sg:city":"Brandon",
    "sg:classifiers":[
        {
            "category":"Wholesale",
            "subcategory":"Farm Supplies",
            "type":"Manufacturing & Wholesale Goods"
        }
    ],
    "sg:phone":"+61 7 4782 5995",
    "sg:postcode":"4808",
    "sg:province":"QLD",
    "sg:tags":[
        "feed",
        "supplement",
        "stock"
    ],
    "wof:name":"Performance Feed Pty Ltd",
    "wof:placetype":"venue"
},
  "geometry": {"coordinates":[147.336334228,-19.5520401001],"type":"Point"}
}