{
  "type": "Feature",
  "properties": {
    "addr:full":"15 Pignat Pl Goonellabah NSW 2480",
    "addr:housenumber":"15",
    "addr:postcode":"2480",
    "addr:street":"Pignat Pl",
    "iso:country":"AU",
    "sg:address":"15 Pignat Pl",
    "sg:city":"Goonellabah",
    "sg:classifiers":[
        {
            "category":"Professional",
            "type":"Services"
        }
    ],
    "sg:phone":"+61 412 660 325",
    "sg:postcode":"2480",
    "sg:province":"NSW",
    "sg:tags":[
        "courier"
    ],
    "wof:name":"Lismore Couriers",
    "wof:placetype":"venue"
},
  "geometry": {"coordinates":[153.34761047399999,-28.8133220673],"type":"Point"}
}