{
  "type": "Feature",
  "properties": {
    "iso:country":"AU",
    "sg:address":"Suite 3/ 77a Orlando St",
    "sg:city":"Coffs Harbour",
    "sg:classifiers":[
        {
            "category":"Building & Trades",
            "subcategory":"Construction",
            "type":"Services"
        }
    ],
    "sg:phone":"+61 2 6652 9238",
    "sg:postcode":"2450",
    "sg:province":"NSW",
    "sg:tags":[
        "pool",
        "swimming"
    ],
    "wof:name":"Aquatic Pools & Spas",
    "wof:placetype":"venue"
},
  "geometry": {"coordinates":[153.130157,-30.288412],"type":"Point"}
}