{
  "type": "Feature",
  "properties": {
    "iso:country":"AU",
    "sg:address":"Ravenswood St",
    "sg:city":"Bega",
    "sg:classifiers":[
        {
            "category":"Retail",
            "subcategory":"Car Wash",
            "type":"Services"
        }
    ],
    "sg:phone":"+61 427 260 423",
    "sg:postcode":"2550",
    "sg:province":"NSW",
    "sg:tags":[
        "bitumen",
        "spraying"
    ],
    "wof:name":"Grant M S & K A Bobcat Hire",
    "wof:placetype":"venue"
},
  "geometry": {"coordinates":[149.83206176799999,-36.6932067871],"type":"Point"}
}