{
  "type": "Feature",
  "properties": {
    "addr:full":"56 Cemetery Rd Raceview QLD 4305",
    "addr:housenumber":"56",
    "addr:postcode":"4305",
    "addr:street":"Cemetery Rd",
    "iso:country":"AU",
    "sg:address":"56 Cemetery Rd",
    "sg:city":"Raceview",
    "sg:classifiers":[
        {
            "category":"Food & Beverages",
            "subcategory":"Groceries & Convenience Stores",
            "type":"Retail Goods"
        }
    ],
    "sg:phone":"+61 7 3281 4473",
    "sg:postcode":"4305",
    "sg:province":"QLD",
    "wof:name":"Cemetery Road Convenience Store",
    "wof:placetype":"venue"
},
  "geometry": {"coordinates":[152.76878356899999,-27.6321544647],"type":"Point"}
}