{
  "type": "Feature",
  "properties": {
    "addr:full":"Unit 1, 350 Edgar St Condell Park NSW 2200",
    "addr:housenumber":"350",
    "addr:postcode":"2200",
    "addr:street":"Edgar St",
    "iso:country":"AU",
    "sg:address":"Unit 1, 350 Edgar St",
    "sg:city":"Condell Park",
    "sg:classifiers":[
        {
            "category":"Manufacturing",
            "subcategory":"Printing",
            "type":"Manufacturing & Wholesale Goods"
        }
    ],
    "sg:phone":"+61 2 9791 0811",
    "sg:postcode":"2200",
    "sg:province":"NSW",
    "sg:tags":[
        "wholesaler",
        "mfrs",
        "greeting",
        "card"
    ],
    "wof:name":"Care & Share Products Pty Ltd",
    "wof:placetype":"venue"
},
  "geometry": {"coordinates":[151.01190199999999,-33.932102],"type":"Point"}
}