{
  "type": "Feature",
  "properties": {
    "addr:full":"Shop 2/ 1 Grose Vale Rd North Richmond NSW 2754",
    "addr:housenumber":"shop 2 / 1",
    "addr:postcode":"2754",
    "addr:street":"Grose Vale Rd",
    "iso:country":"AU",
    "sg:address":"Shop 2/ 1 Grose Vale Rd",
    "sg:city":"North Richmond",
    "sg:classifiers":[
        {
            "category":"Personal",
            "subcategory":"Beauty Salon",
            "type":"Services"
        }
    ],
    "sg:phone":"+61 2 4571 1294",
    "sg:postcode":"2754",
    "sg:province":"NSW",
    "wof:name":"Ella Bache&#039; North Richmond",
    "wof:placetype":"venue"
},
  "geometry": {"coordinates":[150.71917724599999,-33.5803489685],"type":"Point"}
}