{
  "type": "Feature",
  "properties": {
    "addr:full":"PO Box 146 Blackall QLD 4472",
    "addr:postcode":"4472",
    "iso:country":"AU",
    "sg:address":"PO Box 146",
    "sg:city":"Blackall",
    "sg:classifiers":[
        {
            "category":"Building & Trades",
            "subcategory":"Plumbing",
            "type":"Services"
        }
    ],
    "sg:phone":"+61 427 445 555",
    "sg:postcode":"4472",
    "sg:province":"QLD",
    "sg:tags":[
        "plumber",
        "gasfitters"
    ],
    "wof:name":"Barcoo Plumbing",
    "wof:placetype":"venue"
},
  "geometry": {"coordinates":[145.46400451700001,-24.424030304],"type":"Point"}
}