{
  "type": "Feature",
  "properties": {
    "iso:country":"AU",
    "sg:address":"26 Gibson St",
    "sg:city":"Wangaratta",
    "sg:classifiers":[
        {
            "category":"Manufacturing",
            "subcategory":"Metals",
            "type":"Manufacturing & Wholesale Goods"
        }
    ],
    "sg:phone":"+61 3 5722 3122",
    "sg:postcode":"3677",
    "sg:province":"VIC",
    "sg:tags":[
        "steel",
        "fabricator",
        "mfrs"
    ],
    "wof:name":"Fitweld Engineering Pty Ltd",
    "wof:placetype":"venue"
},
  "geometry": {"coordinates":[146.29199218799999,-36.3636894226],"type":"Point"}
}