{
  "type": "Feature",
  "properties": {
    "iso:country":"AU",
    "sg:address":"Shop 14 165 Woodford Rd",
    "sg:city":"Elizabeth North",
    "sg:classifiers":[
        {
            "category":"Fast Food",
            "type":"Food & Drink"
        }
    ],
    "sg:phone":"+61 8 8287 5411",
    "sg:postcode":"5113",
    "sg:province":"SA",
    "sg:tags":[
        "away",
        "take"
    ],
    "wof:name":"Pedro's Dial Pizza",
    "wof:placetype":"venue"
},
  "geometry": {"coordinates":[138.67677307100001,-34.700958252],"type":"Point"}
}