{
  "type": "Feature",
  "properties": {
    "iso:country":"AU",
    "sg:address":"24 Landale Ave",
    "sg:city":"Mt Clear",
    "sg:classifiers":[
        {
            "category":"Health Services",
            "subcategory":"Health Practitioner",
            "type":"Services"
        }
    ],
    "sg:phone":"+61 3 5330 3010",
    "sg:postcode":"3350",
    "sg:province":"VIC",
    "sg:tags":[
        "naturopath"
    ],
    "wof:name":"Wise Womens Well Being",
    "wof:placetype":"venue"
},
  "geometry": {"coordinates":[143.86451700000001,-37.60741],"type":"Point"}
}