{
  "type": "Feature",
  "properties": {
    "addr:full":"36 Mary St Gympie QLD 4570",
    "addr:housenumber":"36",
    "addr:postcode":"4570",
    "addr:street":"Mary St",
    "iso:country":"AU",
    "sg:address":"36 Mary St",
    "sg:city":"Gympie",
    "sg:classifiers":[
        {
            "category":"Shopping",
            "subcategory":"Music",
            "type":"Retail Goods"
        }
    ],
    "sg:phone":"+61 7 5482 3226",
    "sg:postcode":"4570",
    "sg:province":"QLD",
    "sg:tags":[
        "instrument",
        "musical"
    ],
    "wof:name":"Gympie Musicland",
    "wof:placetype":"venue"
},
  "geometry": {"coordinates":[152.664428711,-26.1902332306],"type":"Point"}
}