{
  "type": "Feature",
  "properties": {
    "addr:full":"13 Doncaster Ave Narellan NSW 2567",
    "addr:housenumber":"13",
    "addr:postcode":"2567",
    "addr:street":"Doncaster Ave",
    "iso:country":"AU",
    "sg:address":"13 Doncaster Ave",
    "sg:city":"Narellan",
    "sg:classifiers":[
        {
            "category":"Retail",
            "subcategory":"Auto Rental",
            "type":"Services"
        }
    ],
    "sg:phone":"+61 2 4647 3121",
    "sg:postcode":"2567",
    "sg:province":"NSW",
    "sg:tags":[
        "car",
        "wedding"
    ],
    "wof:name":"Wyarreden Wedding Cars",
    "wof:placetype":"venue"
},
  "geometry": {"coordinates":[150.74087524399999,-34.0410881042],"type":"Point"}
}