{
  "type": "Feature",
  "properties": {
    "addr:full":"5 East St Charleville QLD 4470",
    "addr:housenumber":"5",
    "addr:postcode":"4470",
    "addr:street":"East St",
    "iso:country":"AU",
    "sg:address":"5 East St",
    "sg:city":"Charleville",
    "sg:classifiers":[
        {
            "category":"Utilities",
            "subcategory":"Natural Gas",
            "type":"Services"
        }
    ],
    "sg:phone":"+61 7 4654 1811",
    "sg:postcode":"4470",
    "sg:province":"QLD",
    "sg:tags":[
        "supplier"
    ],
    "wof:name":"Balsillie Gas Sales & Service",
    "wof:placetype":"venue"
},
  "geometry": {"coordinates":[146.254074097,-26.392124176],"type":"Point"}
}