{
  "type": "Feature",
  "properties": {
    "addr:full":"North Calliope St Springsure QLD 4722",
    "addr:postcode":"4722",
    "addr:street":"North Calliope St",
    "iso:country":"AU",
    "sg:address":"North Calliope St",
    "sg:city":"Springsure",
    "sg:classifiers":[
        {
            "category":"Freight",
            "type":"Transportation"
        }
    ],
    "sg:phone":"+61 7 4984 1288",
    "sg:postcode":"4722",
    "sg:province":"QLD",
    "sg:tags":[
        "light",
        "carrier"
    ],
    "wof:name":"Dendles Transport",
    "wof:placetype":"venue"
},
  "geometry": {"coordinates":[148.092285,-24.118986],"type":"Point"}
}