{
  "type": "Feature",
  "properties": {
    "iso:country":"AU",
    "sg:address":"Vidal St",
    "sg:city":"Wetherill Park",
    "sg:classifiers":[
        {
            "category":"Real Estate",
            "subcategory":"Architect",
            "type":"Services"
        }
    ],
    "sg:phone":"+61 2 9604 4260",
    "sg:postcode":"2164",
    "sg:province":"NSW",
    "wof:name":"Architectural Illustrator Julie Whicker",
    "wof:placetype":"venue"
},
  "geometry": {"coordinates":[150.904586792,-33.8534164429],"type":"Point"}
}