{
  "type": "Feature",
  "properties": {
    "addr:full":"4/ 35 Dunlop Rd Mulgrave VIC 3170",
    "addr:housenumber":"/ 35",
    "addr:postcode":"3170",
    "addr:street":"Dunlop Rd",
    "iso:country":"AU",
    "sg:address":"4/ 35 Dunlop Rd",
    "sg:city":"Mulgrave",
    "sg:classifiers":[
        {
            "category":"Building & Trades",
            "subcategory":"Pest Control",
            "type":"Services"
        }
    ],
    "sg:phone":"+61 3 9590 0138",
    "sg:postcode":"3170",
    "sg:province":"VIC",
    "sg:tags":[
        "part",
        "radio",
        "distributors"
    ],
    "wof:name":"Audioxtra International",
    "wof:placetype":"venue"
},
  "geometry": {"coordinates":[145.155715942,-37.910194397],"type":"Point"}
}