{
  "type": "Feature",
  "properties": {
    "addr:full":"3/45- 47 Hopetoun Gr Eaglemont VIC 3084",
    "addr:housenumber":"/;47",
    "addr:postcode":"3084",
    "addr:street":"45",
    "iso:country":"AU",
    "sg:address":"3/45- 47",
    "sg:city":"Hopetoun Gr Eaglemont",
    "sg:classifiers":[
        {
            "category":"Professional",
            "subcategory":"Accounting & Tax Preparation",
            "type":"Services"
        }
    ],
    "sg:phone":"+61 3 9499 1828",
    "sg:postcode":"3084",
    "sg:province":"VIC",
    "sg:tags":[
        "accountant",
        "auditor"
    ],
    "wof:name":"Curtain John",
    "wof:placetype":"venue"
},
  "geometry": {"coordinates":[145.055145264,-37.7658157349],"type":"Point"}
}