{
  "type": "Feature",
  "properties": {
    "addr:full":"21 Cambride Ave Lemon Tree Passage NSW 2319",
    "addr:housenumber":"21",
    "addr:postcode":"2319",
    "addr:street":"Cambride Ave;Passage",
    "iso:country":"AU",
    "sg:address":"21 Cambride Ave",
    "sg:city":"Lemon Tree Passage",
    "sg:classifiers":[
        {
            "category":"Education",
            "subcategory":"Special Training",
            "type":"Public Place"
        }
    ],
    "sg:phone":"+61 2 4982 3061",
    "sg:postcode":"2319",
    "sg:province":"NSW",
    "sg:tags":[
        "tuition-educational"
    ],
    "wof:name":"Peter Brown",
    "wof:placetype":"venue"
},
  "geometry": {"coordinates":[152.03645299999999,-32.730713],"type":"Point"}
}