{
  "type": "Feature",
  "properties": {
    "iso:country":"AU",
    "sg:address":"20 Birmingham St",
    "sg:city":"Alexandria",
    "sg:classifiers":[
        {
            "category":"Retail",
            "subcategory":"Auto Repair",
            "type":"Services"
        }
    ],
    "sg:phone":"+61 2 9669 3862",
    "sg:postcode":"2015",
    "sg:province":"NSW",
    "sg:tags":[
        "beater",
        "painter",
        "panel"
    ],
    "wof:name":"Safeguard",
    "wof:placetype":"venue"
},
  "geometry": {"coordinates":[151.196334839,-33.920211792],"type":"Point"}
}