{
  "type": "Feature",
  "properties": {
    "addr:full":"Ste 7/72- 74 Cecil Ave Castle Hill NSW 2154",
    "addr:housenumber":"74",
    "addr:postcode":"2154",
    "addr:street":"Cecil Ave",
    "iso:country":"AU",
    "sg:address":"Ste 7/72- 74 Cecil Ave",
    "sg:city":"Castle Hill",
    "sg:classifiers":[
        {
            "category":"Health Services",
            "subcategory":"Doctor",
            "type":"Services"
        }
    ],
    "sg:phone":"+61 2 9659 5466",
    "sg:postcode":"2154",
    "sg:province":"NSW",
    "sg:tags":[
        "medical",
        "practitioner"
    ],
    "wof:name":"Davies Campbell de Lambert Pathology",
    "wof:placetype":"venue"
},
  "geometry": {"coordinates":[151.004104614,-33.7353172302],"type":"Point"}
}