{
  "type": "Feature",
  "properties": {
    "addr:full":"Level 3, 333 George St Sydney NSW 2000",
    "addr:housenumber":"333",
    "addr:postcode":"2000",
    "addr:street":"George St",
    "iso:country":"AU",
    "sg:address":"Level 3, 333 George St",
    "sg:city":"Sydney",
    "sg:classifiers":[
        {
            "category":"Organizations",
            "subcategory":"Community Association",
            "type":"Services"
        }
    ],
    "sg:phone":"+61 2 9249 1210",
    "sg:postcode":"2000",
    "sg:province":"NSW",
    "sg:tags":[
        "registered",
        "trustee",
        "bankruptcy"
    ],
    "wof:name":"Worrells",
    "wof:placetype":"venue"
},
  "geometry": {"coordinates":[151.20698547399999,-33.8669166565],"type":"Point"}
}