{
  "type": "Feature",
  "properties": {
    "addr:full":"38 Aldinga St Redbank Plains QLD 4301",
    "addr:housenumber":"38",
    "addr:postcode":"4301",
    "addr:street":"Aldinga St",
    "iso:country":"AU",
    "sg:address":"38 Aldinga St",
    "sg:city":"Redbank Plains",
    "sg:classifiers":[
        {
            "category":"Building & Trades",
            "subcategory":"Plumbing",
            "type":"Services"
        }
    ],
    "sg:phone":"+61 408 734 886",
    "sg:postcode":"4301",
    "sg:province":"QLD",
    "sg:tags":[
        "plumber",
        "gasfitters"
    ],
    "wof:name":"Georges Plumbing",
    "wof:placetype":"venue"
},
  "geometry": {"coordinates":[152.86453247099999,-27.6605815887],"type":"Point"}
}