{
  "type": "Feature",
  "properties": {
    "addr:full":"17 Station St Kogarah NSW 2217",
    "addr:housenumber":"17",
    "addr:postcode":"2217",
    "addr:street":"Station St",
    "iso:country":"AU",
    "sg:address":"17 Station St",
    "sg:city":"Kogarah",
    "sg:classifiers":[
        {
            "category":"Food & Beverages",
            "subcategory":"Supermarket",
            "type":"Retail Goods"
        }
    ],
    "sg:phone":"+61 2 9587 3378",
    "sg:postcode":"2217",
    "sg:province":"NSW",
    "sg:tags":[
        "grocery",
        "store"
    ],
    "wof:name":"Kim Tan Asian Grocery",
    "wof:placetype":"venue"
},
  "geometry": {"coordinates":[151.13189700000001,-33.962452],"type":"Point"}
}