{
  "type": "Feature",
  "properties": {
    "addr:full":"209 Lava St Warrnambool VIC 3280",
    "addr:housenumber":"209",
    "addr:postcode":"3280",
    "addr:street":"Lava St",
    "iso:country":"AU",
    "sg:address":"209 Lava St",
    "sg:city":"Warrnambool",
    "sg:classifiers":[
        {
            "category":"Retail",
            "subcategory":"Veterinary Services",
            "type":"Services"
        }
    ],
    "sg:phone":"+61 3 5561 1366",
    "sg:postcode":"3280",
    "sg:province":"VIC",
    "sg:tags":[
        "surgeon"
    ],
    "wof:name":"Cowell James & Eleanor And Associates",
    "wof:placetype":"venue"
},
  "geometry": {"coordinates":[142.48153686500001,-38.3803825378],"type":"Point"}
}