{
  "type": "Feature",
  "properties": {
    "addr:full":"Suite 3 150 Pacific Hwy Coffs Harbour NSW 2450",
    "addr:housenumber":"150",
    "addr:postcode":"2450",
    "addr:street":"Pacific Hwy",
    "iso:country":"AU",
    "sg:address":"Suite 3 150 Pacific Hwy",
    "sg:city":"Coffs Harbour",
    "sg:classifiers":[
        {
            "category":"Professional",
            "subcategory":"Engineering",
            "type":"Services"
        }
    ],
    "sg:phone":"+61 2 6652 3800",
    "sg:postcode":"2450",
    "sg:province":"NSW",
    "sg:tags":[
        "consulting",
        "engineer"
    ],
    "wof:name":"O&#039;Meara Wood & Accociates",
    "wof:placetype":"venue"
},
  "geometry": {"coordinates":[153.09053,-30.318281],"type":"Point"}
}