{
  "type": "Feature",
  "properties": {
    "addr:full":"Level 10, ING Building 100 Edward St Brisbane QLD 4000",
    "addr:housenumber":"100",
    "addr:postcode":"4000",
    "addr:street":"Edward St",
    "iso:country":"AU",
    "sg:address":"Level 10, ING Building 100 Edward St",
    "sg:city":"Brisbane",
    "sg:classifiers":[
        {
            "category":"Real Estate",
            "subcategory":"Surveying",
            "type":"Services"
        }
    ],
    "sg:phone":"+61 7 3210 1366",
    "sg:postcode":"4000",
    "sg:province":"QLD",
    "sg:tags":[
        "surveyor",
        "quantity"
    ],
    "wof:name":"Currie & Brown",
    "wof:placetype":"venue"
},
  "geometry": {"coordinates":[153.02877807600001,-27.4703922272],"type":"Point"}
}