{
  "type": "Feature",
  "properties": {
    "addr:full":"3 Vines Ave Forestville NSW 2087",
    "addr:housenumber":"3",
    "addr:postcode":"2087",
    "addr:street":"Vines Ave",
    "iso:country":"AU",
    "sg:address":"3 Vines Ave",
    "sg:city":"Forestville",
    "sg:classifiers":[
        {
            "category":"Education",
            "subcategory":"University",
            "type":"Public Place"
        }
    ],
    "sg:phone":"+61 2 9450 1737",
    "sg:postcode":"2087",
    "sg:province":"NSW",
    "sg:tags":[
        "educational",
        "organisation",
        "cultural"
    ],
    "wof:name":"Gurdjieff Foundation Of Australia",
    "wof:placetype":"venue"
},
  "geometry": {"coordinates":[151.214111328,-33.7530097961],"type":"Point"}
}