{
  "type": "Feature",
  "properties": {
    "addr:full":"172 South Pine Rd Strathpine QLD 4500",
    "addr:housenumber":"172",
    "addr:postcode":"4500",
    "addr:street":"South Pine Rd",
    "iso:country":"AU",
    "sg:address":"172 South Pine Rd",
    "sg:city":"Strathpine",
    "sg:classifiers":[
        {
            "category":"Professional",
            "subcategory":"Printing & Photocopies",
            "type":"Services"
        }
    ],
    "sg:phone":"+61 7 3881 3133",
    "sg:postcode":"4500",
    "sg:province":"QLD",
    "sg:tags":[
        "photocopying"
    ],
    "wof:name":"Kwik Kopy Print & Design Centres",
    "wof:placetype":"venue"
},
  "geometry": {"coordinates":[152.98733520499999,-27.3245258331],"type":"Point"}
}