{
  "type": "Feature",
  "properties": {
    "iso:country":"AU",
    "sg:address":"38- 56 Caseys Rd",
    "sg:city":"Hope Island",
    "sg:classifiers":[
        {
            "category":"Social Services",
            "subcategory":"Retirement Home",
            "type":"Services"
        }
    ],
    "sg:phone":"+61 7 5510 8985",
    "sg:postcode":"4212",
    "sg:province":"QLD",
    "sg:tags":[
        "village"
    ],
    "wof:name":"Ritz Care Centre",
    "wof:placetype":"venue"
},
  "geometry": {"coordinates":[153.35168457,-27.8633480072],"type":"Point"}
}