{
  "type": "Feature",
  "properties": {
    "iso:country":"AU",
    "sg:address":"239- 245 Midland Hwy",
    "sg:city":"Epsom",
    "sg:classifiers":[
        {
            "category":"Wholesale",
            "subcategory":"Stationery",
            "type":"Manufacturing & Wholesale Goods"
        }
    ],
    "sg:phone":"+61 3 5448 4233",
    "sg:postcode":"3551",
    "sg:province":"VIC",
    "sg:tags":[
        "mfrg"
    ],
    "wof:name":"Espress Printers",
    "wof:placetype":"venue"
},
  "geometry": {"coordinates":[144.31718444800001,-36.6990585327],"type":"Point"}
}