{
  "type": "Feature",
  "properties": {
    "iso:country":"AU",
    "sg:address":"Preston Rd",
    "sg:city":"Collie",
    "sg:classifiers":[
        {
            "category":"Manufacturing",
            "subcategory":"Lumber",
            "type":"Manufacturing & Wholesale Goods"
        }
    ],
    "sg:phone":"+61 8 9734 1383",
    "sg:postcode":"6225",
    "sg:province":"WA",
    "sg:tags":[
        "sawmillers"
    ],
    "wof:name":"Saunders Sawmill",
    "wof:placetype":"venue"
},
  "geometry": {"coordinates":[116.154037,-33.366085],"type":"Point"}
}