{
  "type": "Feature",
  "properties": {
    "addr:full":"Cnr Currie & Maud Sts Nambour QLD 4560",
    "addr:postcode":"4560",
    "addr:street":"Cnr",
    "iso:country":"AU",
    "sg:address":"Cnr Currie & Maud Sts",
    "sg:city":"Nambour",
    "sg:classifiers":[
        {
            "category":"Organizations",
            "subcategory":"Non-profit Organization",
            "type":"Services"
        }
    ],
    "sg:phone":"+61 7 5453 8000",
    "sg:postcode":"4560",
    "sg:province":"QLD",
    "sg:tags":[
        "support",
        "disability",
        "organisation"
    ],
    "wof:name":"Endeavour",
    "wof:placetype":"venue"
},
  "geometry": {"coordinates":[152.95921325699999,-26.6250762939],"type":"Point"}
}