{
  "type": "Feature",
  "properties": {
    "addr:full":"102 Gale Rd Maroubra NSW 2035",
    "addr:housenumber":"102",
    "addr:postcode":"2035",
    "addr:street":"Gale Rd",
    "iso:country":"AU",
    "sg:address":"102 Gale Rd",
    "sg:city":"Maroubra",
    "sg:classifiers":[
        {
            "category":"Health Services",
            "subcategory":"Doctor",
            "type":"Services"
        }
    ],
    "sg:phone":"+61 2 9344 5022",
    "sg:postcode":"2035",
    "sg:province":"NSW",
    "sg:tags":[
        "medical",
        "practitioner"
    ],
    "wof:name":"Horowitz G",
    "wof:placetype":"venue"
},
  "geometry": {"coordinates":[151.23817443900001,-33.9382972717],"type":"Point"}
}