{
  "type": "Feature",
  "properties": {
    "iso:country":"AU",
    "sg:address":"211 Gallipoli Rd",
    "sg:city":"Carina Heights",
    "sg:classifiers":[
        {
            "category":"Building & Trades",
            "subcategory":"Plumbing",
            "type":"Services"
        }
    ],
    "sg:phone":"+61 7 3398 9188",
    "sg:postcode":"4152",
    "sg:province":"QLD",
    "sg:tags":[
        "drainers"
    ],
    "wof:name":"B & L Terehoff Plumbing Service",
    "wof:placetype":"venue"
},
  "geometry": {"coordinates":[153.092254639,-27.5063838959],"type":"Point"}
}