{
  "type": "Feature",
  "properties": {
    "addr:full":"PO Box 3191 Wheelers Hill VIC 3150",
    "addr:postcode":"3150",
    "iso:country":"AU",
    "sg:address":"PO Box 3191",
    "sg:city":"Wheelers Hill",
    "sg:classifiers":[
        {
            "category":"Banks & Credit Unions",
            "subcategory":"Bureau De Change",
            "type":"Services"
        }
    ],
    "sg:phone":"+61 3 9561 3374",
    "sg:postcode":"3150",
    "sg:province":"VIC",
    "sg:tags":[
        "escort",
        "transport",
        "pilot"
    ],
    "wof:name":"Get Smart's Pilot Service",
    "wof:placetype":"venue"
},
  "geometry": {"coordinates":[145.184417725,-37.9114112854],"type":"Point"}
}