{
  "type": "Feature",
  "properties": {
    "addr:full":"48 Dollis St Rocklea QLD 4106",
    "addr:housenumber":"48",
    "addr:postcode":"4106",
    "addr:street":"Dollis St",
    "iso:country":"AU",
    "sg:address":"48 Dollis St",
    "sg:city":"Rocklea",
    "sg:classifiers":[
        {
            "category":"Retail",
            "subcategory":"Auto Repair",
            "type":"Services"
        }
    ],
    "sg:phone":"+61 7 3276 8714",
    "sg:postcode":"4106",
    "sg:province":"QLD",
    "sg:tags":[
        "repairer",
        "motor",
        "engineer"
    ],
    "wof:name":"Subaru Specialist",
    "wof:placetype":"venue"
},
  "geometry": {"coordinates":[153.022415161,-27.5553703308],"type":"Point"}
}