{
  "type": "Feature",
  "properties": {
    "iso:country":"AU",
    "sg:address":"7a Wentworth St",
    "sg:city":"Manly",
    "sg:classifiers":[
        {
            "category":"Health Services",
            "subcategory":"Doctor",
            "type":"Services"
        }
    ],
    "sg:phone":"+61 2 9977 7555",
    "sg:postcode":"2095",
    "sg:province":"NSW",
    "sg:tags":[
        "medical",
        "practitioner"
    ],
    "wof:name":"Anderson Catherine J",
    "wof:placetype":"venue"
},
  "geometry": {"coordinates":[151.28640747099999,-33.7992248535],"type":"Point"}
}