{
  "type": "Feature",
  "properties": {
    "addr:full":"560 Mitcham Rd Mitcham VIC 3132",
    "addr:housenumber":"560",
    "addr:postcode":"3132",
    "addr:street":"Mitcham Rd",
    "iso:country":"AU",
    "sg:address":"560 Mitcham Rd",
    "sg:city":"Mitcham",
    "sg:classifiers":[
        {
            "category":"Food & Beverages",
            "subcategory":"Bakery",
            "type":"Retail Goods"
        }
    ],
    "sg:phone":"+61 3 9874 6566",
    "sg:postcode":"3132",
    "sg:province":"VIC",
    "sg:tags":[
        "baker"
    ],
    "wof:name":"Brumby's Bakeries",
    "wof:placetype":"venue"
},
  "geometry": {"coordinates":[145.194412231,-37.8274497986],"type":"Point"}
}