{
  "type": "Feature",
  "properties": {
    "iso:country":"AU",
    "sg:address":"2999 Moss Vale Rd",
    "sg:city":"Fitzroy Falls",
    "sg:classifiers":[
        {
            "category":"Health Services",
            "subcategory":"Doctor",
            "type":"Services"
        }
    ],
    "sg:phone":"+61 2 4465 1362",
    "sg:postcode":"2577",
    "sg:province":"NSW",
    "sg:tags":[
        "holiday",
        "retreat"
    ],
    "wof:name":"Cedarvale Health & Education Centre Ltd",
    "wof:placetype":"venue"
},
  "geometry": {"coordinates":[150.55856323200001,-34.7449035645],"type":"Point"}
}