{
  "type": "Feature",
  "properties": {
    "iso:country":"AU",
    "sg:address":"31 Aubrey St",
    "sg:city":"Surfers Paradise",
    "sg:classifiers":[
        {
            "category":"Food & Beverages",
            "subcategory":"Supermarket",
            "type":"Retail Goods"
        }
    ],
    "sg:phone":"+61 7 5531 5309",
    "sg:postcode":"4217",
    "sg:province":"QLD",
    "sg:tags":[
        "grocery",
        "store"
    ],
    "wof:name":"Pit Stop News & Supermarkets",
    "wof:placetype":"venue"
},
  "geometry": {"coordinates":[153.42984008799999,-28.0112762451],"type":"Point"}
}