{
  "type": "Feature",
  "properties": {
    "iso:country":"AU",
    "sg:address":"Lot 22 Boulavard North Paradise Palms",
    "sg:city":"Cairns",
    "sg:classifiers":[
        {
            "category":"Communications",
            "type":"Services"
        }
    ],
    "sg:phone":"+61 7 4055 6266",
    "sg:postcode":"4870",
    "sg:province":"QLD",
    "sg:tags":[
        "translation"
    ],
    "wof:name":"Languagehelp",
    "wof:placetype":"venue"
},
  "geometry": {"coordinates":[145.73220825199999,-16.937171936],"type":"Point"}
}