{
  "type": "Feature",
  "properties": {
    "iso:country":"AU",
    "sg:address":"502 Princes Hwy",
    "sg:city":"Woonona",
    "sg:classifiers":[
        {
            "category":"Retail",
            "subcategory":"Auto Repair",
            "type":"Services"
        }
    ],
    "sg:phone":"+61 2 4284 8170",
    "sg:postcode":"2517",
    "sg:province":"NSW",
    "sg:tags":[
        "repairer",
        "motor",
        "engineer"
    ],
    "wof:name":"Purely Mechanical",
    "wof:placetype":"venue"
},
  "geometry": {"coordinates":[150.90339700000001,-34.350491],"type":"Point"}
}