{
  "type": "Feature",
  "properties": {
    "addr:full":"604 Terrigal Drv Erina NSW 2250",
    "addr:housenumber":"604",
    "addr:postcode":"2250",
    "addr:street":"Terrigal Drv",
    "iso:country":"AU",
    "sg:address":"604 Terrigal Drv",
    "sg:city":"Erina",
    "sg:classifiers":[
        {
            "category":"Social Services",
            "subcategory":"Retirement Home",
            "type":"Services"
        }
    ],
    "sg:phone":"+61 2 4365 9777",
    "sg:postcode":"2250",
    "sg:province":"NSW",
    "sg:tags":[
        "accommodation",
        "special"
    ],
    "wof:name":"Tarragal Glen Manor",
    "wof:placetype":"venue"
},
  "geometry": {"coordinates":[151.39616394000001,-33.4348907471],"type":"Point"}
}