{
  "type": "Feature",
  "properties": {
    "addr:full":"77 Rundell St Ararat VIC 3377",
    "addr:housenumber":"77",
    "addr:postcode":"3377",
    "addr:street":"Rundell St",
    "iso:country":"AU",
    "sg:address":"77 Rundell St",
    "sg:city":"Ararat",
    "sg:classifiers":[
        {
            "category":"Building & Trades",
            "subcategory":"Plumbing",
            "type":"Services"
        }
    ],
    "sg:phone":"+61 400 052 251",
    "sg:postcode":"3377",
    "sg:province":"VIC",
    "sg:tags":[
        "plumber",
        "gasfitters"
    ],
    "wof:name":"D & A Murley Plumbing",
    "wof:placetype":"venue"
},
  "geometry": {"coordinates":[142.94143676799999,-37.2760505676],"type":"Point"}
}