{
  "type": "Feature",
  "properties": {
    "iso:country":"AU",
    "sg:address":"781 Pacific Highway  Suite 506",
    "sg:city":"Chatswood",
    "sg:classifiers":[
        {
            "category":"Professional",
            "subcategory":"Computer Services",
            "type":"Services"
        }
    ],
    "sg:postcode":"NSW 2067",
    "sg:tags":[
        "itil-service-management",
        "kinetic-data",
        "business-services-management",
        "service-delivery-management",
        "it-service-catalog",
        "help-de3sk-survey-software"
    ],
    "sg:website":"http://www.kineticdata.com",
    "wof:name":"Kinetic Data",
    "wof:placetype":"venue"
},
  "geometry": {"coordinates":[151.17898400000001,-33.798642],"type":"Point"}
}