{
  "type": "Feature",
  "properties": {
    "addr:full":"15e Quay St East Bundaberg QLD 4670",
    "addr:postcode":"4670",
    "addr:street":"15E Quay St East",
    "iso:country":"AU",
    "sg:address":"15e Quay St",
    "sg:city":"East Bundaberg",
    "sg:classifiers":[
        {
            "category":"Farming",
            "subcategory":"Fish & Marine Products",
            "type":"Manufacturing & Wholesale Goods"
        }
    ],
    "sg:phone":"+61 7 4153 4800",
    "sg:postcode":"4670",
    "sg:province":"QLD",
    "sg:tags":[
        "production",
        "seafood",
        "processing"
    ],
    "wof:name":"Fishmac Pty Ltd",
    "wof:placetype":"venue"
},
  "geometry": {"coordinates":[152.35955810600001,-24.8619937897],"type":"Point"}
}