{
  "type": "Feature",
  "properties": {
    "iso:country":"AU",
    "sg:address":"U6/ 31 Salisbury Rd",
    "sg:city":"Hornsby",
    "sg:classifiers":[
        {
            "category":"Professional",
            "subcategory":"Printing & Photocopies",
            "type":"Services"
        }
    ],
    "sg:phone":"+61 2 9987 2217",
    "sg:postcode":"2077",
    "sg:province":"NSW",
    "sg:tags":[
        "screen",
        "printer"
    ],
    "wof:name":"Triple 3 Screenprinting",
    "wof:placetype":"venue"
},
  "geometry": {"coordinates":[151.11126709000001,-33.6954116821],"type":"Point"}
}