{
  "type": "Feature",
  "properties": {
    "addr:full":"Merton St Boggabri NSW 2382",
    "addr:postcode":"2382",
    "addr:street":"Merton St",
    "iso:country":"AU",
    "sg:address":"Merton St",
    "sg:city":"Boggabri",
    "sg:classifiers":[
        {
            "category":"Education",
            "subcategory":"School",
            "type":"Public Place"
        }
    ],
    "sg:phone":"+61 2 6743 4526",
    "sg:postcode":"2382",
    "sg:province":"NSW",
    "sg:tags":[
        "state",
        "-",
        "nsw"
    ],
    "wof:name":"Boggabri Public School",
    "wof:placetype":"venue"
},
  "geometry": {"coordinates":[150.04301452600001,-30.7097625732],"type":"Point"}
}