{
  "type": "Feature",
  "properties": {
    "addr:full":"120 Wharf Rd Johns River NSW 2443",
    "addr:housenumber":"120",
    "addr:postcode":"2443",
    "addr:street":"Wharf Rd",
    "iso:country":"AU",
    "sg:address":"120 Wharf Rd",
    "sg:city":"Johns River",
    "sg:classifiers":[
        {
            "category":"Utilities",
            "subcategory":"Natural Gas",
            "type":"Services"
        }
    ],
    "sg:phone":"+61 2 6556 5099",
    "sg:postcode":"2443",
    "sg:province":"NSW",
    "sg:tags":[
        "consultant",
        "resource"
    ],
    "wof:name":"I D Landscape Management P/L",
    "wof:placetype":"venue"
},
  "geometry": {"coordinates":[152.722397,-31.725723],"type":"Point"}
}