{
  "type": "Feature",
  "properties": {
    "addr:full":"8 Landau Crt Taylors Lakes VIC 3038",
    "addr:housenumber":"8",
    "addr:postcode":"3038",
    "addr:street":"Landau Crt",
    "iso:country":"AU",
    "sg:address":"8 Landau Crt",
    "sg:city":"Taylors Lakes",
    "sg:classifiers":[
        {
            "category":"Retail",
            "subcategory":"Driving School",
            "type":"Services"
        }
    ],
    "sg:phone":"+61 3 8390 9315",
    "sg:postcode":"3038",
    "sg:province":"VIC",
    "wof:name":"Glens Driver Education",
    "wof:placetype":"venue"
},
  "geometry": {"coordinates":[144.78907799999999,-37.693291],"type":"Point"}
}