{
  "type": "Feature",
  "properties": {
    "addr:full":"1 MacArthur St Melbourne VIC 3000",
    "addr:housenumber":"1",
    "addr:postcode":"3000",
    "addr:street":"Macarthur St",
    "iso:country":"AU",
    "sg:address":"1 MacArthur St",
    "sg:city":"Melbourne",
    "sg:classifiers":[
        {
            "category":"Manufacturing",
            "subcategory":"Food",
            "type":"Manufacturing & Wholesale Goods"
        }
    ],
    "sg:phone":"+61 3 9651 5625",
    "sg:postcode":"3000",
    "sg:province":"VIC",
    "sg:tags":[
        "function",
        "catering"
    ],
    "wof:name":"Treasury Deli",
    "wof:placetype":"venue"
},
  "geometry": {"coordinates":[144.97457885700001,-37.8124809265],"type":"Point"}
}