{
  "type": "Feature",
  "properties": {
    "iso:country":"AU",
    "sg:address":"45 Dawson Rd",
    "sg:city":"Gladstone",
    "sg:classifiers":[
        {
            "category":"Fast Food",
            "type":"Food & Drink"
        }
    ],
    "sg:phone":"+61 7 4972 4722",
    "sg:postcode":"4680",
    "sg:province":"QLD",
    "sg:tags":[
        "away",
        "take"
    ],
    "wof:name":"Subway Gladstone",
    "wof:placetype":"venue"
},
  "geometry": {"coordinates":[151.24935913100001,-23.853767395],"type":"Point"}
}