{
  "type": "Feature",
  "properties": {
    "iso:country":"AU",
    "sg:address":"357-359 Bong Bong St",
    "sg:city":"Bowral",
    "sg:classifiers":[
        {
            "category":"Real Estate",
            "subcategory":"Architect",
            "type":"Services"
        }
    ],
    "sg:phone":"+61 2 4861 4570",
    "sg:postcode":"2576",
    "sg:province":"NSW",
    "sg:tags":[
        "building",
        "designer"
    ],
    "wof:name":"Webb John R & Associates",
    "wof:placetype":"venue"
},
  "geometry": {"coordinates":[150.417694092,-34.4803962708],"type":"Point"}
}