{
  "type": "Feature",
  "properties": {
    "addr:full":"Level 1, 793 George St Sydney NSW 2000",
    "addr:housenumber":"793",
    "addr:postcode":"2000",
    "addr:street":"George St",
    "iso:country":"AU",
    "sg:address":"Level 1, 793 George St",
    "sg:city":"Sydney",
    "sg:classifiers":[
        {
            "category":"Health Services",
            "subcategory":"Dentist",
            "type":"Services"
        }
    ],
    "sg:phone":"+61 2 9211 1011",
    "sg:postcode":"2000",
    "sg:province":"NSW",
    "wof:name":"George Street Cosmetic and General Dentistry - Dr William Zafiropoulos, Dr Selwy",
    "wof:placetype":"venue"
},
  "geometry": {"coordinates":[151.20411682100001,-33.8826179504],"type":"Point"}
}