{
  "type": "Feature",
  "properties": {
    "addr:full":"394 Jamison Rd Jamisontown NSW 2750",
    "addr:housenumber":"394",
    "addr:postcode":"2750",
    "addr:street":"Jamison Rd",
    "iso:country":"AU",
    "sg:address":"394 Jamison Rd",
    "sg:city":"Jamisontown",
    "sg:classifiers":[
        {
            "category":"Recreation",
            "subcategory":"Amusement Park",
            "type":"Entertainment"
        }
    ],
    "sg:phone":"+61 2 4722 9424",
    "sg:postcode":"2750",
    "sg:province":"NSW",
    "wof:name":"Putt Putt Wonderland",
    "wof:placetype":"venue"
},
  "geometry": {"coordinates":[150.67718505900001,-33.7599830627],"type":"Point"}
}