{
  "type": "Feature",
  "properties": {
    "addr:full":"71 Renou St East Cannington WA 6107",
    "addr:housenumber":"71",
    "addr:postcode":"6107",
    "addr:street":"Renou St East",
    "iso:country":"AU",
    "sg:address":"71 Renou St",
    "sg:city":"East Cannington",
    "sg:phone":"+61 8 9458 2879",
    "sg:postcode":"6107",
    "sg:province":"WA",
    "wof:name":"Panichi F & Co (1974)",
    "wof:placetype":"venue"
},
  "geometry": {"coordinates":[115.947982788,-32.0132026672],"type":"Point"}
}