{
  "type": "Feature",
  "properties": {
    "iso:country":"AU",
    "sg:address":"U2, 23 Armada Pl",
    "sg:city":"Banyo",
    "sg:classifiers":[
        {
            "category":"Professional",
            "subcategory":"Employment Agencies",
            "type":"Services"
        }
    ],
    "sg:phone":"+61 7 3267 9115",
    "sg:postcode":"4014",
    "sg:province":"QLD",
    "sg:tags":[
        "broker",
        "custom"
    ],
    "wof:name":"JSP Logistics",
    "wof:placetype":"venue"
},
  "geometry": {"coordinates":[153.08969116200001,-27.384885788],"type":"Point"}
}