{
  "type": "Feature",
  "properties": {
    "addr:full":"19 Webster Rd Stafford QLD 4053",
    "addr:housenumber":"19",
    "addr:postcode":"4053",
    "addr:street":"Webster Rd",
    "iso:country":"AU",
    "sg:address":"19 Webster Rd",
    "sg:city":"Stafford",
    "sg:classifiers":[
        {
            "category":"Retail",
            "subcategory":"Auto Repair",
            "type":"Services"
        }
    ],
    "sg:phone":"+61 7 3856 4156",
    "sg:postcode":"4053",
    "sg:province":"QLD",
    "sg:tags":[
        "body",
        "motor",
        "trimmer"
    ],
    "wof:name":"John Faulkner Motor Trimming",
    "wof:placetype":"venue"
},
  "geometry": {"coordinates":[153.015792847,-27.4179267883],"type":"Point"}
}