{
  "type": "Feature",
  "properties": {
    "iso:country":"AU",
    "sg:address":"359 North Rd",
    "sg:city":"Caulfield South",
    "sg:classifiers":[
        {
            "category":"Building & Trades",
            "subcategory":"Equipment Rental",
            "type":"Services"
        }
    ],
    "sg:phone":"+61 3 9576 9150",
    "sg:postcode":"3162",
    "sg:province":"VIC",
    "sg:tags":[
        "saw"
    ],
    "wof:name":"Trade Tools Pty Ltd",
    "wof:placetype":"venue"
},
  "geometry": {"coordinates":[145.02859497099999,-37.9023246765],"type":"Point"}
}