{
  "type": "Feature",
  "properties": {
    "addr:full":"48b Murray St Nuriootpa SA 5355",
    "addr:housenumber":"48b",
    "addr:postcode":"5355",
    "addr:street":"Murray St",
    "iso:country":"AU",
    "sg:address":"48b Murray St",
    "sg:city":"Nuriootpa",
    "sg:classifiers":[
        {
            "category":"Industrial Area",
            "type":"Public Place"
        }
    ],
    "sg:phone":"+61 8 8565 7111",
    "sg:postcode":"5355",
    "sg:province":"SA",
    "sg:tags":[
        "rural",
        "shed"
    ],
    "wof:name":"Valley Sheds",
    "wof:placetype":"venue"
},
  "geometry": {"coordinates":[138.99690246599999,-34.4705848694],"type":"Point"}
}