{
  "type": "Feature",
  "properties": {
    "iso:country":"AU",
    "sg:address":"414 Eatonvale Rd",
    "sg:city":"Maryborough",
    "sg:classifiers":[
        {
            "category":"Utilities",
            "subcategory":"Electric",
            "type":"Services"
        }
    ],
    "sg:phone":"+61 7 4121 3569",
    "sg:postcode":"4650",
    "sg:province":"QLD",
    "sg:tags":[
        "electrical",
        "contractor"
    ],
    "wof:name":"Steve Thomas Electrician Pty Ltd",
    "wof:placetype":"venue"
},
  "geometry": {"coordinates":[152.651825,-25.520765],"type":"Point"}
}