{
  "type": "Feature",
  "properties": {
    "addr:full":"Shop 84, Centro Seven Hills Cnr Prospect Highway & Seven Hills NSW 2147",
    "addr:housenumber":"shop 84",
    "addr:postcode":"2147",
    "addr:street":"Cnr Prospect Highway &",
    "iso:country":"AU",
    "sg:address":"Shop 84, Centro Seven Hills Cnr Prospect Highway &",
    "sg:city":"Seven Hills",
    "sg:classifiers":[
        {
            "category":"Home & Garden",
            "subcategory":"Home Furnishings",
            "type":"Retail Goods"
        }
    ],
    "sg:phone":"+61 2 9621 1377",
    "sg:postcode":"2147",
    "sg:province":"NSW",
    "sg:tags":[
        "candle"
    ],
    "wof:name":"Candles & More",
    "wof:placetype":"venue"
},
  "geometry": {"coordinates":[150.93389892600001,-33.7759590149],"type":"Point"}
}