{
  "type": "Feature",
  "properties": {
    "addr:full":"Shp1/ 236 Port Elliot Rd Hayborough SA 5211",
    "addr:housenumber":"236",
    "addr:postcode":"5211",
    "addr:street":"Port Elliot Rd",
    "iso:country":"AU",
    "sg:address":"Shp1/ 236 Port Elliot Rd",
    "sg:city":"Hayborough",
    "sg:classifiers":[
        {
            "category":"Sports & Exercise",
            "subcategory":"Gym",
            "type":"Entertainment"
        }
    ],
    "sg:phone":"+61 8 8552 3183",
    "sg:postcode":"5211",
    "sg:province":"SA",
    "sg:tags":[
        "health",
        "fitness"
    ],
    "wof:name":"Efm Victor Harbour",
    "wof:placetype":"venue"
},
  "geometry": {"coordinates":[138.64747619600001,-35.5354385376],"type":"Point"}
}