{
  "type": "Feature",
  "properties": {
    "iso:country":"AU",
    "sg:address":"58a Frenchs Rd",
    "sg:city":"Willoughby",
    "sg:classifiers":[
        {
            "category":"Health Services",
            "subcategory":"Health Practitioner",
            "type":"Services"
        }
    ],
    "sg:phone":"+61 2 9967 2101",
    "sg:postcode":"2068",
    "sg:province":"NSW",
    "sg:tags":[
        "naturopath"
    ],
    "wof:name":"Wild Heather",
    "wof:placetype":"venue"
},
  "geometry": {"coordinates":[151.20010375999999,-33.8073120117],"type":"Point"}
}