{
  "type": "Feature",
  "properties": {
    "addr:full":"3 Deany St Springvale VIC 3171",
    "addr:housenumber":"3",
    "addr:postcode":"3171",
    "addr:street":"Deany St",
    "iso:country":"AU",
    "sg:address":"3 Deany St",
    "sg:city":"Springvale",
    "sg:classifiers":[
        {
            "category":"Professional",
            "subcategory":"Printing & Photocopies",
            "type":"Services"
        }
    ],
    "sg:phone":"+61 3 9546 8733",
    "sg:postcode":"3171",
    "sg:province":"VIC",
    "sg:tags":[
        "trophy"
    ],
    "wof:name":"Anthonys Trophies & Engraving",
    "wof:placetype":"venue"
},
  "geometry": {"coordinates":[145.15953064000001,-37.9439277649],"type":"Point"}
}