{
  "type": "Feature",
  "properties": {
    "iso:country":"AU",
    "sg:address":"35 Carlton Rd",
    "sg:city":"Greenbank",
    "sg:classifiers":[
        {
            "category":"Professional",
            "subcategory":"Engineering",
            "type":"Services"
        }
    ],
    "sg:phone":"+61 7 3809 3283",
    "sg:postcode":"4124",
    "sg:province":"QLD",
    "sg:tags":[
        "consulting",
        "engineer"
    ],
    "wof:name":"Aus Engineers",
    "wof:placetype":"venue"
},
  "geometry": {"coordinates":[153.01148986800001,-27.6990127563],"type":"Point"}
}