{
  "type": "Feature",
  "properties": {
    "iso:country":"AU",
    "sg:address":"Shop 3/ 319 High St",
    "sg:city":"Northcote",
    "sg:classifiers":[
        {
            "category":"Shopping",
            "subcategory":"Antiques",
            "type":"Retail Goods"
        }
    ],
    "sg:phone":"+61 3 9481 8154",
    "sg:postcode":"3070",
    "sg:province":"VIC",
    "sg:tags":[
        "restoration",
        "reproduction"
    ],
    "wof:name":"Hidden City Upholstery",
    "wof:placetype":"venue"
},
  "geometry": {"coordinates":[144.998505,-37.771088],"type":"Point"}
}