{
  "type": "Feature",
  "properties": {
    "iso:country":"AU",
    "sg:address":"23 Rundle St",
    "sg:city":"Kent Town",
    "sg:classifiers":[
        {
            "category":"Organizations",
            "subcategory":"Professional Association",
            "type":"Services"
        }
    ],
    "sg:phone":"+61 8 8363 0616",
    "sg:postcode":"5067",
    "sg:province":"SA",
    "sg:tags":[
        "web",
        "internet"
    ],
    "wof:name":"Evolved Web Solutions Pty. Ltd.",
    "wof:placetype":"venue"
},
  "geometry": {"coordinates":[138.61686706500001,-34.9211235046],"type":"Point"}
}