{
  "type": "Feature",
  "properties": {
    "iso:country":"AU",
    "sg:address":"289 Hobart Rd",
    "sg:city":"Youngtown",
    "sg:classifiers":[
        {
            "category":"Shopping",
            "subcategory":"Clothing, Apparel, & Fashions",
            "type":"Retail Goods"
        }
    ],
    "sg:phone":"+61 3 6344 7133",
    "sg:postcode":"7249",
    "sg:province":"TAS",
    "sg:tags":[
        "recycled",
        "clothing"
    ],
    "wof:name":"Encore Clothing",
    "wof:placetype":"venue"
},
  "geometry": {"coordinates":[147.16661071799999,-41.4791412354],"type":"Point"}
}