{
  "type": "Feature",
  "properties": {
    "iso:country":"AU",
    "sg:address":"2/302 Chapel Rd",
    "sg:city":"Sth Bankstown",
    "sg:classifiers":[
        {
            "category":"Health Services",
            "subcategory":"Dentist",
            "type":"Services"
        }
    ],
    "sg:phone":"+61 2 9708 6569",
    "sg:postcode":"2200",
    "sg:province":"NSW",
    "sg:tags":[
        "dental",
        "prosthetist"
    ],
    "wof:name":"Campbelltown Denture Clinic",
    "wof:placetype":"venue"
},
  "geometry": {"coordinates":[151.031586,-33.919312],"type":"Point"}
}