{
  "type": "Feature",
  "properties": {
    "addr:full":"Byford Surgery 4 Clifton St Byford WA 6122",
    "addr:housenumber":"4",
    "addr:postcode":"6122",
    "addr:street":"Clifton St",
    "iso:country":"AU",
    "sg:address":"Byford Surgery 4 Clifton St",
    "sg:city":"Byford",
    "sg:classifiers":[
        {
            "category":"Health Services",
            "subcategory":"Medical Lab",
            "type":"Services"
        }
    ],
    "sg:phone":"+61 8 9525 0893",
    "sg:postcode":"6122",
    "sg:province":"WA",
    "sg:tags":[
        "laboratory",
        "pathology"
    ],
    "wof:name":"Pathwest",
    "wof:placetype":"venue"
},
  "geometry": {"coordinates":[116.00935363799999,-32.2202796936],"type":"Point"}
}