{
  "type": "Feature",
  "properties": {
    "addr:full":"Suite 1B, 1st Floor The Terrace 40 Panmure St Rouse Hill NSW 2155",
    "addr:housenumber":"suite 1b 1st floor;40",
    "addr:postcode":"2155",
    "addr:street":"The Terrace;Panmure St",
    "iso:country":"AU",
    "sg:address":"Suite 1B, 1st Floor The Terrace 40 Panmure St",
    "sg:city":"Rouse Hill",
    "sg:classifiers":[
        {
            "category":"Health Services",
            "subcategory":"Dentist",
            "type":"Services"
        }
    ],
    "sg:phone":"+61 2 8814 5255",
    "sg:postcode":"2155",
    "sg:province":"NSW",
    "wof:name":"Rouse Hill Dental",
    "wof:placetype":"venue"
},
  "geometry": {"coordinates":[150.91737365700001,-33.6828804016],"type":"Point"}
}