{
  "type": "Feature",
  "properties": {
    "iso:country":"AU",
    "sg:address":"4 Castle Crt",
    "sg:city":"Forrestfield",
    "sg:classifiers":[
        {
            "category":"Building & Trades",
            "subcategory":"Landscaping Services",
            "type":"Services"
        }
    ],
    "sg:phone":"+61 1800 888 771",
    "sg:postcode":"6058",
    "sg:province":"WA",
    "sg:tags":[
        "inspection"
    ],
    "wof:name":"HomeCert",
    "wof:placetype":"venue"
},
  "geometry": {"coordinates":[116.014900208,-31.9944095612],"type":"Point"}
}