{
  "type": "Feature",
  "properties": {
    "addr:full":"The Rocks Village, Gordon Young Drv South West Rocks NSW 2431",
    "addr:postcode":"2431",
    "addr:street":"Young Drv South West Rocks",
    "iso:country":"AU",
    "sg:address":"The Rocks Village, Gordon Young Drv",
    "sg:city":"South West Rocks",
    "sg:classifiers":[
        {
            "category":"Building & Trades",
            "subcategory":"Construction",
            "type":"Services"
        }
    ],
    "sg:phone":"+61 408 434 566",
    "sg:postcode":"2431",
    "sg:province":"NSW",
    "sg:tags":[
        "contractor"
    ],
    "wof:name":"Colles Manufactured Homes Pty Ltd",
    "wof:placetype":"venue"
},
  "geometry": {"coordinates":[153.037949,-30.890211],"type":"Point"}
}