{
  "type": "Feature",
  "properties": {
    "iso:country":"AU",
    "sg:address":"36 Ormond Rd",
    "sg:city":"Ivanhoe",
    "sg:classifiers":[
        {
            "category":"Utilities",
            "subcategory":"Electric",
            "type":"Services"
        }
    ],
    "sg:phone":"+61 3 9499 5077",
    "sg:postcode":"3079",
    "sg:province":"VIC",
    "sg:tags":[
        "electrical",
        "contractor"
    ],
    "wof:name":"Cornell Peter Pty Ltd",
    "wof:placetype":"venue"
},
  "geometry": {"coordinates":[145.05801391599999,-37.766658783],"type":"Point"}
}