{
  "type": "Feature",
  "properties": {
    "addr:full":"19 Russell St Woonona NSW 2517",
    "addr:housenumber":"19",
    "addr:postcode":"2517",
    "addr:street":"Russell St",
    "iso:country":"AU",
    "sg:address":"19 Russell St",
    "sg:city":"Woonona",
    "sg:classifiers":[
        {
            "category":"Health Services",
            "subcategory":"Dentist",
            "type":"Services"
        }
    ],
    "sg:phone":"+61 2 4284 5671",
    "sg:postcode":"2517",
    "sg:province":"NSW",
    "wof:name":"Fryer F Shane",
    "wof:placetype":"venue"
},
  "geometry": {"coordinates":[150.90887499999999,-34.34108],"type":"Point"}
}