{
  "type": "Feature",
  "properties": {
    "iso:country":"AU",
    "sg:address":"PO Box 48",
    "sg:city":"Hervey Bay",
    "sg:classifiers":[
        {
            "category":"Building & Trades",
            "subcategory":"Construction",
            "type":"Services"
        }
    ],
    "sg:phone":"+61 419 779 462",
    "sg:postcode":"4655",
    "sg:province":"QLD",
    "sg:tags":[
        "plasterboard",
        "plasterer",
        "fixer"
    ],
    "wof:name":"Hervey Bay Plastering",
    "wof:placetype":"venue"
},
  "geometry": {"coordinates":[152.82931500000001,-25.302172],"type":"Point"}
}