{
  "type": "Feature",
  "properties": {
    "iso:country":"AU",
    "sg:address":"23/ 58 Box Rd",
    "sg:city":"Caringbah",
    "sg:classifiers":[
        {
            "category":"Wholesale",
            "subcategory":"Medical Equipment & Supplies",
            "type":"Manufacturing & Wholesale Goods"
        }
    ],
    "sg:phone":"+61 2 9526 5944",
    "sg:postcode":"2229",
    "sg:province":"NSW",
    "sg:tags":[
        "watchmaker"
    ],
    "wof:name":"JJ's National Marketing Pty Ltd",
    "wof:placetype":"venue"
},
  "geometry": {"coordinates":[151.119873047,-34.024181366],"type":"Point"}
}