{
  "type": "Feature",
  "properties": {
    "addr:full":"7 King William Rd Unley SA 5061",
    "addr:housenumber":"7",
    "addr:postcode":"5061",
    "addr:street":"King William Rd",
    "iso:country":"AU",
    "sg:address":"7 King William Rd",
    "sg:city":"Unley",
    "sg:classifiers":[
        {
            "category":"Professional",
            "subcategory":"Employment Agencies",
            "type":"Services"
        }
    ],
    "sg:phone":"+61 8 8271 4133",
    "sg:postcode":"5061",
    "sg:province":"SA",
    "wof:name":"David Sladden & Associates Pty Ltd",
    "wof:placetype":"venue"
},
  "geometry": {"coordinates":[138.600372314,-34.9422073364],"type":"Point"}
}