{
  "type": "Feature",
  "properties": {
    "iso:country":"AU",
    "sg:address":"T1.4, 1.5, 1.6a, 1.6 Cnr O&#039;Riordan & Doody St",
    "sg:city":"Alexandria",
    "sg:classifiers":[
        {
            "category":"Shopping",
            "subcategory":"Crafts & Fabrics",
            "type":"Retail Goods"
        }
    ],
    "sg:phone":"+61 1300 730 140",
    "sg:postcode":"1431",
    "sg:province":"NSW",
    "sg:tags":[
        "material",
        "dress"
    ],
    "wof:name":"Lincraft",
    "wof:placetype":"venue"
},
  "geometry": {"coordinates":[151.19683800000001,-33.916367],"type":"Point"}
}