{
  "type": "Feature",
  "properties": {
    "iso:country":"AU",
    "sg:address":"1 Archibald St",
    "sg:city":"Lockington",
    "sg:classifiers":[
        {
            "category":"Travel",
            "subcategory":"Hotels & Motels",
            "type":"Entertainment"
        }
    ],
    "sg:phone":"+61 3 5486 2394",
    "sg:postcode":"3563",
    "sg:province":"VIC",
    "sg:tags":[
        "accommodation"
    ],
    "wof:name":"Lockington Hotel",
    "wof:placetype":"venue"
},
  "geometry": {"coordinates":[144.497498,-36.270741],"type":"Point"}
}