{
  "type": "Feature",
  "properties": {
    "iso:country":"AU",
    "sg:address":"65 Lusher Rd",
    "sg:city":"Croydon",
    "sg:classifiers":[
        {
            "category":"Autos & Motor Vehicles",
            "subcategory":"Auto Supplies",
            "type":"Retail Goods"
        }
    ],
    "sg:phone":"+61 3 9723 6134",
    "sg:postcode":"3136",
    "sg:province":"VIC",
    "sg:tags":[
        "equipment",
        "part",
        "truck"
    ],
    "wof:name":"A.C.E. Filters",
    "wof:placetype":"venue"
},
  "geometry": {"coordinates":[145.27809143100001,-37.805683136],"type":"Point"}
}