{
  "type": "Feature",
  "properties": {
    "addr:full":"13 Depot Rd Nowra West NSW 2541",
    "addr:housenumber":"13",
    "addr:postcode":"2541",
    "addr:street":"Depot Rd",
    "iso:country":"AU",
    "sg:address":"13 Depot Rd",
    "sg:city":"Nowra West",
    "sg:classifiers":[
        {
            "category":"Professional",
            "subcategory":"Employment Agencies",
            "type":"Services"
        }
    ],
    "sg:phone":"+61 410 433 822",
    "sg:postcode":"2541",
    "sg:province":"NSW",
    "sg:tags":[
        "entertainer",
        "agent"
    ],
    "wof:name":"Just Janine",
    "wof:placetype":"venue"
},
  "geometry": {"coordinates":[150.586013794,-34.8909378052],"type":"Point"}
}