{
  "type": "Feature",
  "properties": {
    "iso:country":"AU",
    "sg:address":"19 Market Rd",
    "sg:city":"Sunshine",
    "sg:classifiers":[
        {
            "category":"Retail",
            "subcategory":"Auto Repair",
            "type":"Services"
        }
    ],
    "sg:phone":"+61 3 9312 7478",
    "sg:postcode":"3020",
    "sg:province":"VIC",
    "sg:tags":[
        "repairer",
        "motor",
        "engineer"
    ],
    "wof:name":"Allright Mechanical & Tyre Service",
    "wof:placetype":"venue"
},
  "geometry": {"coordinates":[144.839325,-37.799679],"type":"Point"}
}