{
  "type": "Feature",
  "properties": {
    "addr:full":"200 Logan Rd Woolloongabba QLD 4102",
    "addr:housenumber":"200",
    "addr:postcode":"4102",
    "addr:street":"Logan Rd",
    "iso:country":"AU",
    "sg:address":"200 Logan Rd",
    "sg:city":"Woolloongabba",
    "sg:classifiers":[
        {
            "category":"Retail",
            "subcategory":"Auto Repair",
            "type":"Services"
        }
    ],
    "sg:phone":"+61 7 3891 3699",
    "sg:postcode":"4102",
    "sg:province":"QLD",
    "sg:tags":[
        "clutch",
        "brake"
    ],
    "wof:name":"Bridgestone Tyre Centres",
    "wof:placetype":"venue"
},
  "geometry": {"coordinates":[153.04148864699999,-27.4952583313],"type":"Point"}
}