{
  "type": "Feature",
  "properties": {
    "addr:full":"Rear 7 Marion St Parramatta NSW 2150",
    "addr:housenumber":"7",
    "addr:postcode":"2150",
    "addr:street":"Marion St",
    "iso:country":"AU",
    "sg:address":"Rear 7 Marion St",
    "sg:city":"Parramatta",
    "sg:classifiers":[
        {
            "category":"Retail",
            "subcategory":"Auto Repair",
            "type":"Services"
        }
    ],
    "sg:phone":"+61 2 9633 4471",
    "sg:postcode":"2150",
    "sg:province":"NSW",
    "sg:tags":[
        "body",
        "motor",
        "trimmer"
    ],
    "wof:name":"Grimshaw Car Upholstery",
    "wof:placetype":"venue"
},
  "geometry": {"coordinates":[151.00523376500001,-33.8224906921],"type":"Point"}
}