{
  "type": "Feature",
  "properties": {
    "addr:full":"21 Munro Ave Sunshine VIC 3020",
    "addr:housenumber":"21",
    "addr:postcode":"3020",
    "addr:street":"Munro Ave",
    "iso:country":"AU",
    "sg:address":"21 Munro Ave",
    "sg:city":"Sunshine",
    "sg:classifiers":[
        {
            "category":"Autos & Motor Vehicles",
            "subcategory":"Auto Supplies",
            "type":"Retail Goods"
        }
    ],
    "sg:phone":"+61 3 9362 1611",
    "sg:postcode":"3020",
    "sg:province":"VIC",
    "sg:tags":[
        "tyre"
    ],
    "wof:name":"Tyres R Us",
    "wof:placetype":"venue"
},
  "geometry": {"coordinates":[144.844269,-37.758652],"type":"Point"}
}