{
  "type": "Feature",
  "properties": {
    "addr:full":"340 Bussell Hwy Busselton WA 6280",
    "addr:housenumber":"340",
    "addr:postcode":"6280",
    "addr:street":"Bussell Hwy",
    "iso:country":"AU",
    "sg:address":"340 Bussell Hwy",
    "sg:city":"Busselton",
    "sg:classifiers":[
        {
            "category":"Travel",
            "subcategory":"Hotels & Motels",
            "type":"Entertainment"
        }
    ],
    "sg:phone":"+61 8 9754 4600",
    "sg:postcode":"6280",
    "sg:province":"WA",
    "wof:name":"Restawile Motel",
    "wof:placetype":"venue"
},
  "geometry": {"coordinates":[115.319007873,-33.6562957764],"type":"Point"}
}