{
  "type": "Feature",
  "properties": {
    "addr:full":"Shop 4, The Colonial Shopping Village, 689 Cusack Lane Jimboomba QLD 4280",
    "addr:housenumber":"shop 4;689",
    "addr:postcode":"4280",
    "addr:street":"The;Cusack Lane",
    "iso:country":"AU",
    "sg:address":"Shop 4, The Colonial Shopping Village, 689",
    "sg:city":"Cusack Lane Jimboomba",
    "sg:classifiers":[
        {
            "category":"Real Estate",
            "subcategory":"Real Estate Agent",
            "type":"Services"
        }
    ],
    "sg:phone":"+61 7 5546 9100",
    "sg:postcode":"4280",
    "sg:province":"QLD",
    "wof:name":"Harcourts Jimboomba Drews Real Estate",
    "wof:placetype":"venue"
},
  "geometry": {"coordinates":[153.02836600000001,-27.831526],"type":"Point"}
}