{
  "type": "Feature",
  "properties": {
    "addr:full":"20 Burwood Rd Concord NSW 2137",
    "addr:housenumber":"20",
    "addr:postcode":"2137",
    "addr:street":"Burwood Rd",
    "iso:country":"AU",
    "sg:address":"20 Burwood Rd",
    "sg:city":"Concord",
    "sg:classifiers":[
        {
            "category":"Retail",
            "subcategory":"Auto Rental",
            "type":"Services"
        }
    ],
    "sg:phone":"+61 2 9744 0257",
    "sg:postcode":"2137",
    "sg:province":"NSW",
    "sg:tags":[
        "car",
        "hire",
        "minibus"
    ],
    "wof:name":"Exel Car Rental",
    "wof:placetype":"venue"
},
  "geometry": {"coordinates":[151.11666870100001,-33.8585472107],"type":"Point"}
}