{
  "type": "Feature",
  "properties": {
    "iso:country":"AU",
    "sg:address":"Cnr Drayton & George Sts",
    "sg:city":"Nanango",
    "sg:classifiers":[
        {
            "category":"Home & Garden",
            "subcategory":"Hardware",
            "type":"Retail Goods"
        }
    ],
    "sg:phone":"+61 7 4163 2366",
    "sg:postcode":"4615",
    "sg:province":"QLD",
    "sg:tags":[
        "plumber",
        "supply"
    ],
    "wof:name":"Pascoe Plumbing & Supplies",
    "wof:placetype":"venue"
},
  "geometry": {"coordinates":[152.00210571299999,-26.6711654663],"type":"Point"}
}