{
  "type": "Feature",
  "properties": {
    "addr:full":"196 Dowding St Oxley QLD 4075",
    "addr:housenumber":"196",
    "addr:postcode":"4075",
    "addr:street":"Dowding St",
    "iso:country":"AU",
    "sg:address":"196 Dowding St",
    "sg:city":"Oxley",
    "sg:classifiers":[
        {
            "category":"Building & Trades",
            "subcategory":"Landscaping Services",
            "type":"Services"
        }
    ],
    "sg:phone":"+61 412 045 483",
    "sg:postcode":"4075",
    "sg:province":"QLD",
    "sg:tags":[
        "gardener"
    ],
    "wof:name":"Unit Care (Australia) Pty Ltd",
    "wof:placetype":"venue"
},
  "geometry": {"coordinates":[152.96542358400001,-27.5681724548],"type":"Point"}
}