{
  "type": "Feature",
  "properties": {
    "iso:country":"AU",
    "sg:address":"183 Tufnell Rd",
    "sg:city":"Banyo",
    "sg:classifiers":[
        {
            "category":"Health Services",
            "subcategory":"Doctor",
            "type":"Services"
        }
    ],
    "sg:phone":"+61 7 3267 5088",
    "sg:postcode":"4014",
    "sg:province":"QLD",
    "sg:tags":[
        "medical",
        "practitioner"
    ],
    "wof:name":"Morris Craig A",
    "wof:placetype":"venue"
},
  "geometry": {"coordinates":[153.07675170900001,-27.3745479584],"type":"Point"}
}