{
  "type": "Feature",
  "properties": {
    "iso:country":"AU",
    "sg:address":"7 Franklyn St",
    "sg:city":"Glebe",
    "sg:classifiers":[
        {
            "category":"Health Services",
            "subcategory":"Doctor",
            "type":"Services"
        }
    ],
    "sg:phone":"+61 2 9552 2380",
    "sg:postcode":"2037",
    "sg:province":"NSW",
    "sg:tags":[
        "occupational",
        "safety"
    ],
    "sg:website":"http://www.courtenell.com.au",
    "wof:name":"Courtenell Pty Ltd",
    "wof:placetype":"venue"
},
  "geometry": {"coordinates":[151.19258117699999,-33.8828392029],"type":"Point"}
}