{
  "type": "Feature",
  "properties": {
    "iso:country":"AU",
    "sg:address":"PO Box 480",
    "sg:city":"South Melbourne",
    "sg:classifiers":[
        {
            "category":"Building & Trades",
            "subcategory":"Construction",
            "type":"Services"
        }
    ],
    "sg:phone":"+61 412 058 554",
    "sg:postcode":"3205",
    "sg:province":"VIC",
    "sg:tags":[
        "management"
    ],
    "wof:name":"Project Management Building Services",
    "wof:placetype":"venue"
},
  "geometry": {"coordinates":[144.95585600000001,-37.833881],"type":"Point"}
}