{
  "type": "Feature",
  "properties": {
    "addr:full":"58 Gibson St Ayr QLD 4807",
    "addr:housenumber":"58",
    "addr:postcode":"4807",
    "addr:street":"Gibson St",
    "iso:country":"AU",
    "sg:address":"58 Gibson St",
    "sg:city":"Ayr",
    "sg:classifiers":[
        {
            "category":"Building & Trades",
            "subcategory":"Construction",
            "type":"Services"
        }
    ],
    "sg:phone":"+61 7 4783 2262",
    "sg:postcode":"4807",
    "sg:province":"QLD",
    "sg:tags":[
        "contractor"
    ],
    "wof:name":"Malas Constructions",
    "wof:placetype":"venue"
},
  "geometry": {"coordinates":[147.41506957999999,-19.564655304],"type":"Point"}
}