{
  "type": "Feature",
  "properties": {
    "addr:full":"1 Holterman St Crows Nest NSW 2065",
    "addr:housenumber":"1",
    "addr:postcode":"2065",
    "addr:street":"Holterman St",
    "iso:country":"AU",
    "sg:address":"1 Holterman St",
    "sg:city":"Crows Nest",
    "sg:classifiers":[
        {
            "category":"Government",
            "subcategory":"Post Office",
            "type":"Public Place"
        }
    ],
    "sg:phone":"+61 2 9436 1231",
    "sg:postcode":"2065",
    "sg:province":"NSW",
    "sg:tags":[
        "yoga"
    ],
    "wof:name":"Mantra Yoga",
    "wof:placetype":"venue"
},
  "geometry": {"coordinates":[151.202514648,-33.8244361877],"type":"Point"}
}