{
  "type": "Feature",
  "properties": {
    "iso:country":"AU",
    "sg:address":"64 Montefiores Rd",
    "sg:city":"Wellington",
    "sg:classifiers":[
        {
            "category":"Building & Trades",
            "subcategory":"Plumbing",
            "type":"Services"
        }
    ],
    "sg:phone":"+61 418 636 659",
    "sg:postcode":"2820",
    "sg:province":"NSW",
    "sg:tags":[
        "plumber",
        "gasfitters"
    ],
    "wof:name":"Andy Byrne Plumbing Service",
    "wof:placetype":"venue"
},
  "geometry": {"coordinates":[148.93455505399999,-32.5409736633],"type":"Point"}
}