{
  "type": "Feature",
  "properties": {
    "addr:full":"19- 25 Cowan St Angle Park SA 5010",
    "addr:housenumber":"25",
    "addr:postcode":"5010",
    "addr:street":"Cowan St",
    "iso:country":"AU",
    "sg:address":"19- 25 Cowan St",
    "sg:city":"Angle Park",
    "sg:classifiers":[
        {
            "category":"Social Services",
            "subcategory":"Child Care",
            "type":"Services"
        }
    ],
    "sg:phone":"+61 8 8244 1488",
    "sg:postcode":"5010",
    "sg:province":"SA",
    "wof:name":"ABC Learning Centres",
    "wof:placetype":"venue"
},
  "geometry": {"coordinates":[138.55917358400001,-34.859336853],"type":"Point"}
}