{
  "type": "Feature",
  "properties": {
    "addr:full":"56 Carrington St West Wallsend NSW 2286",
    "addr:housenumber":"56",
    "addr:postcode":"2286",
    "addr:street":"Carrington St",
    "iso:country":"AU",
    "sg:address":"56 Carrington St",
    "sg:city":"West Wallsend",
    "sg:classifiers":[
        {
            "category":"Retail",
            "subcategory":"Auto Repair",
            "type":"Services"
        }
    ],
    "sg:phone":"+61 2 4953 2958",
    "sg:postcode":"2286",
    "sg:province":"NSW",
    "sg:tags":[
        "repairer",
        "motor",
        "engineer"
    ],
    "wof:name":"John Hodder Auto Repairs",
    "wof:placetype":"venue"
},
  "geometry": {"coordinates":[151.582687378,-32.9026298523],"type":"Point"}
}