{
  "type": "Feature",
  "properties": {
    "addr:full":"101- 103 Drummond Rd Shepparton VIC 3630",
    "addr:housenumber":"103",
    "addr:postcode":"3630",
    "addr:street":"Drummond Rd",
    "iso:country":"AU",
    "sg:address":"101- 103 Drummond Rd",
    "sg:city":"Shepparton",
    "sg:classifiers":[
        {
            "category":"Shopping",
            "subcategory":"Stationery & Office Supplies",
            "type":"Retail Goods"
        }
    ],
    "sg:phone":"+61 3 5821 4948",
    "sg:postcode":"3630",
    "sg:province":"VIC",
    "sg:tags":[
        "packaging",
        "material"
    ],
    "wof:name":"G M Packaging",
    "wof:placetype":"venue"
},
  "geometry": {"coordinates":[145.42318725600001,-36.37733078],"type":"Point"}
}