{
  "type": "Feature",
  "properties": {
    "addr:full":"23 Hilldon Crt Nerang QLD 4211",
    "addr:housenumber":"23",
    "addr:postcode":"4211",
    "addr:street":"Hilldon Crt",
    "iso:country":"AU",
    "sg:address":"23 Hilldon Crt",
    "sg:city":"Nerang",
    "sg:classifiers":[
        {
            "category":"Professional",
            "subcategory":"Research",
            "type":"Services"
        }
    ],
    "sg:phone":"+61 7 5596 6947",
    "sg:postcode":"4211",
    "sg:province":"QLD",
    "sg:tags":[
        "industrial",
        "scientific"
    ],
    "wof:name":"Andrews Aerodynamics",
    "wof:placetype":"venue"
},
  "geometry": {"coordinates":[153.340209961,-28.0002613068],"type":"Point"}
}