{
  "type": "Feature",
  "properties": {
    "addr:full":"24 Mercedes Drv Thomastown VIC 3074",
    "addr:housenumber":"24",
    "addr:postcode":"3074",
    "addr:street":"Mercedes Drv",
    "iso:country":"AU",
    "sg:address":"24 Mercedes Drv",
    "sg:city":"Thomastown",
    "sg:classifiers":[
        {
            "category":"Home & Garden",
            "subcategory":"Carpets & Floor Coverings",
            "type":"Retail Goods"
        }
    ],
    "sg:phone":"+61 3 9464 4629",
    "sg:postcode":"3074",
    "sg:province":"VIC",
    "sg:tags":[
        "layer",
        "planner"
    ],
    "wof:name":"Overflow Carpets",
    "wof:placetype":"venue"
},
  "geometry": {"coordinates":[145.01695251500001,-37.6872138977],"type":"Point"}
}