{
  "type": "Feature",
  "properties": {
    "addr:full":"2 Owen St Kallista VIC 3791",
    "addr:housenumber":"2",
    "addr:postcode":"3791",
    "addr:street":"Owen St",
    "iso:country":"AU",
    "sg:address":"2 Owen St",
    "sg:city":"Kallista",
    "sg:classifiers":[
        {
            "category":"Building & Trades",
            "subcategory":"Cleaning & Sanitation",
            "type":"Services"
        }
    ],
    "sg:phone":"+61 3 9755 3317",
    "sg:postcode":"3791",
    "sg:province":"VIC",
    "sg:tags":[
        "cleaner",
        "repairer",
        "roof"
    ],
    "wof:name":"Aus-tech Roofing",
    "wof:placetype":"venue"
},
  "geometry": {"coordinates":[145.36854553200001,-37.8839149475],"type":"Point"}
}