{
  "type": "Feature",
  "properties": {
    "iso:country":"AU",
    "sg:address":"66 Duporth Ave",
    "sg:city":"Maroochydore",
    "sg:classifiers":[
        {
            "category":"Professional",
            "subcategory":"Accounting & Tax Preparation",
            "type":"Services"
        }
    ],
    "sg:phone":"+61 7 5443 2600",
    "sg:postcode":"4558",
    "sg:province":"QLD",
    "sg:tags":[
        "accountant",
        "auditor"
    ],
    "wof:name":"Love & Partners",
    "wof:placetype":"venue"
},
  "geometry": {"coordinates":[153.089111328,-26.6494693756],"type":"Point"}
}