{
  "type": "Feature",
  "properties": {
    "iso:country":"AU",
    "sg:address":"4 Roper Crt",
    "sg:city":"West Lakes Shore",
    "sg:classifiers":[
        {
            "category":"Building & Trades",
            "subcategory":"Construction",
            "type":"Services"
        }
    ],
    "sg:phone":"+61 414 495 202",
    "sg:postcode":"5020",
    "sg:province":"SA",
    "sg:tags":[
        "pool",
        "swimming"
    ],
    "wof:name":"Outhouse Design",
    "wof:placetype":"venue"
},
  "geometry": {"coordinates":[138.48509216299999,-34.859916687],"type":"Point"}
}