{
  "type": "Feature",
  "properties": {
    "addr:full":"2 North St Dodges Ferry TAS 7173",
    "addr:housenumber":"2",
    "addr:postcode":"7173",
    "addr:street":"North St",
    "iso:country":"AU",
    "sg:address":"2 North St",
    "sg:city":"Dodges Ferry",
    "sg:classifiers":[
        {
            "category":"Utilities",
            "subcategory":"Electric",
            "type":"Services"
        }
    ],
    "sg:phone":"+61 409 435 301",
    "sg:postcode":"7173",
    "sg:province":"TAS",
    "sg:tags":[
        "electrical",
        "contractor"
    ],
    "wof:name":"Spec Home",
    "wof:placetype":"venue"
},
  "geometry": {"coordinates":[147.616897583,-42.8660316467],"type":"Point"}
}