{
  "type": "Feature",
  "properties": {
    "addr:full":"56 Chester St Newstead QLD 4006",
    "addr:housenumber":"56",
    "addr:postcode":"4006",
    "addr:street":"Chester St",
    "iso:country":"AU",
    "sg:address":"56 Chester St",
    "sg:city":"Newstead",
    "sg:classifiers":[
        {
            "category":"Real Estate",
            "subcategory":"Real Estate Agent",
            "type":"Services"
        }
    ],
    "sg:phone":"+61 7 3254 2500",
    "sg:postcode":"4006",
    "sg:province":"QLD",
    "wof:name":"Ivan Lazarou Real Estate",
    "wof:placetype":"venue"
},
  "geometry": {"coordinates":[153.04344177199999,-27.4565105438],"type":"Point"}
}