{
  "type": "Feature",
  "properties": {
    "addr:full":"4 Garfield St Fitzroy VIC 3065",
    "addr:housenumber":"4",
    "addr:postcode":"3065",
    "addr:street":"Garfield St",
    "iso:country":"AU",
    "sg:address":"4 Garfield St",
    "sg:city":"Fitzroy",
    "sg:classifiers":[
        {
            "category":"Real Estate",
            "subcategory":"Real Estate Agent",
            "type":"Services"
        }
    ],
    "sg:phone":"+61 3 9417 7296",
    "sg:postcode":"3065",
    "sg:province":"VIC",
    "wof:name":"Jordel Properties",
    "wof:placetype":"venue"
},
  "geometry": {"coordinates":[144.975067139,-37.8007202148],"type":"Point"}
}