{
  "type": "Feature",
  "properties": {
    "addr:full":"55 Labouchere Rd South Perth WA 6151",
    "addr:housenumber":"55",
    "addr:postcode":"6151",
    "addr:street":"Labouchere Rd",
    "iso:country":"AU",
    "sg:address":"55 Labouchere Rd",
    "sg:city":"South Perth",
    "sg:classifiers":[
        {
            "category":"Health Services",
            "subcategory":"Dentist",
            "type":"Services"
        }
    ],
    "sg:phone":"+61 8 9592 3180",
    "sg:postcode":"6151",
    "sg:province":"WA",
    "sg:tags":[
        "state",
        "orthodontist",
        "qld",
        "exc"
    ],
    "wof:name":"Chris Orloff Dr",
    "wof:placetype":"venue"
},
  "geometry": {"coordinates":[115.852028,-31.976484],"type":"Point"}
}