{
  "type": "Feature",
  "properties": {
    "addr:full":"47 Harvest Rd Morley WA 6062",
    "addr:housenumber":"47",
    "addr:postcode":"6062",
    "addr:street":"Harvest Rd",
    "iso:country":"AU",
    "sg:address":"47 Harvest Rd",
    "sg:city":"Morley",
    "sg:classifiers":[
        {
            "category":"Social Services",
            "subcategory":"Adult Care",
            "type":"Services"
        }
    ],
    "sg:phone":"+61 439 693 350",
    "sg:postcode":"6062",
    "sg:province":"WA",
    "sg:tags":[
        "towing"
    ],
    "wof:name":"Abra Towing & Salvage Services",
    "wof:placetype":"venue"
},
  "geometry": {"coordinates":[115.918586731,-31.8914813995],"type":"Point"}
}