{
  "type": "Feature",
  "properties": {
    "addr:full":"3/76 Matheson Rd Applecross WA 6153",
    "addr:housenumber":"/ 76",
    "addr:postcode":"6153",
    "addr:street":"Matheson Rd",
    "iso:country":"AU",
    "sg:address":"3/76 Matheson Rd",
    "sg:city":"Applecross",
    "sg:classifiers":[
        {
            "category":"Real Estate",
            "subcategory":"Surveying",
            "type":"Services"
        }
    ],
    "sg:phone":"+61 8 9316 4249",
    "sg:postcode":"6153",
    "sg:province":"WA",
    "sg:tags":[
        "surveyor",
        "quantity"
    ],
    "wof:name":"Walker Darryl",
    "wof:placetype":"venue"
},
  "geometry": {"coordinates":[115.831444,-32.015263],"type":"Point"}
}