{
  "type": "Feature",
  "properties": {
    "iso:country":"AU",
    "sg:address":"469a Marrickville Rd",
    "sg:city":"Dulwich Hill",
    "sg:classifiers":[
        {
            "category":"Restaurant",
            "type":"Food & Drink"
        }
    ],
    "sg:phone":"+61 2 9569 0522",
    "sg:postcode":"2203",
    "sg:province":"NSW",
    "wof:name":"Denim Bar",
    "wof:placetype":"venue"
},
  "geometry": {"coordinates":[151.14357,-33.904236],"type":"Point"}
}