{
  "type": "Feature",
  "properties": {
    "addr:full":"6a Shaw St Bexley North NSW 2207",
    "addr:housenumber":"6a",
    "addr:postcode":"2207",
    "addr:street":"Shaw St",
    "iso:country":"AU",
    "sg:address":"6a Shaw St",
    "sg:city":"Bexley North",
    "sg:classifiers":[
        {
            "category":"Health Services",
            "subcategory":"Health Practitioner",
            "type":"Services"
        }
    ],
    "sg:phone":"+61 2 9150 4800",
    "sg:postcode":"2207",
    "sg:province":"NSW",
    "sg:tags":[
        "physiotherapist"
    ],
    "wof:name":"Wong B",
    "wof:placetype":"venue"
},
  "geometry": {"coordinates":[151.114105,-33.93803],"type":"Point"}
}