{
  "type": "Feature",
  "properties": {
    "addr:full":"17 Davenport St Millicent SA 5280",
    "addr:housenumber":"17",
    "addr:postcode":"5280",
    "addr:street":"Davenport St",
    "iso:country":"AU",
    "sg:address":"17 Davenport St",
    "sg:city":"Millicent",
    "sg:classifiers":[
        {
            "category":"Professional",
            "subcategory":"Computer Services",
            "type":"Services"
        }
    ],
    "sg:phone":"+61 8 8733 3990",
    "sg:postcode":"5280",
    "sg:province":"SA",
    "sg:tags":[
        "repairs",
        "upgrade",
        "equipment"
    ],
    "wof:name":"Howe Home Systems",
    "wof:placetype":"venue"
},
  "geometry": {"coordinates":[140.35253900000001,-37.595165],"type":"Point"}
}