{
  "type": "Feature",
  "properties": {
    "addr:full":"2 Allen Pl Wetherill Park NSW 2164",
    "addr:housenumber":"2",
    "addr:postcode":"2164",
    "addr:street":"Allen Pl",
    "iso:country":"AU",
    "sg:address":"2 Allen Pl",
    "sg:city":"Wetherill Park",
    "sg:classifiers":[
        {
            "category":"Home & Garden",
            "subcategory":"Carpets & Floor Coverings",
            "type":"Retail Goods"
        }
    ],
    "sg:phone":"+61 2 9725 3133",
    "sg:postcode":"2164",
    "sg:province":"NSW",
    "sg:tags":[
        "tile",
        "wall",
        "layer"
    ],
    "wof:name":"Trend Tile",
    "wof:placetype":"venue"
},
  "geometry": {"coordinates":[150.89950561500001,-33.8480873108],"type":"Point"}
}