{
  "type": "Feature",
  "properties": {
    "addr:full":"543 Elizabeth St Surry Hills NSW 2010",
    "addr:housenumber":"543",
    "addr:postcode":"2010",
    "addr:street":"Elizabeth St",
    "iso:country":"AU",
    "sg:address":"543 Elizabeth St",
    "sg:city":"Surry Hills",
    "sg:classifiers":[
        {
            "category":"Food & Beverages",
            "subcategory":"Supermarket",
            "type":"Retail Goods"
        }
    ],
    "sg:phone":"+61 2 9318 2181",
    "sg:postcode":"2010",
    "sg:province":"NSW",
    "sg:tags":[
        "grocery",
        "store"
    ],
    "wof:name":"Zhejiantex Pty Ltd",
    "wof:placetype":"venue"
},
  "geometry": {"coordinates":[151.207855225,-33.8890647888],"type":"Point"}
}