{
  "type": "Feature",
  "properties": {
    "addr:full":"Suite 1, 17 Aplin St Cairns QLD 4870",
    "addr:housenumber":"17",
    "addr:postcode":"4870",
    "addr:street":"Aplin St",
    "iso:country":"AU",
    "sg:address":"Suite 1, 17 Aplin St",
    "sg:city":"Cairns",
    "sg:classifiers":[
        {
            "category":"Banks & Credit Unions",
            "subcategory":"Bank",
            "type":"Services"
        }
    ],
    "sg:phone":"+61 7 4041 4494",
    "sg:postcode":"4870",
    "sg:province":"QLD",
    "sg:tags":[
        "broker",
        "mortgage"
    ],
    "sg:website":"http://www.mortgagewiz.com.au",
    "wof:name":"Mortgage Wiz",
    "wof:placetype":"venue"
},
  "geometry": {"coordinates":[145.772827148,-16.9217643738],"type":"Point"}
}