{
  "type": "Feature",
  "properties": {
    "iso:country":"AU",
    "sg:address":"11th Floor 24 Collins St",
    "sg:city":"Melbourne",
    "sg:classifiers":[
        {
            "category":"Health Services",
            "subcategory":"Dentist",
            "type":"Services"
        }
    ],
    "sg:phone":"+61 3 9654 5844",
    "sg:postcode":"3000",
    "sg:province":"VIC",
    "wof:name":"Marvan Elishka",
    "wof:placetype":"venue"
},
  "geometry": {"coordinates":[144.972854614,-37.813495636],"type":"Point"}
}