{
  "type": "Feature",
  "properties": {
    "addr:full":"31 Archer St Rockhampton QLD 4700",
    "addr:housenumber":"31",
    "addr:postcode":"4700",
    "addr:street":"Archer St",
    "iso:country":"AU",
    "sg:address":"31 Archer St",
    "sg:city":"Rockhampton",
    "sg:classifiers":[
        {
            "category":"Food & Beverages",
            "subcategory":"Groceries & Convenience Stores",
            "type":"Retail Goods"
        }
    ],
    "sg:phone":"+61 7 4921 3103",
    "sg:postcode":"4700",
    "sg:province":"QLD",
    "wof:name":"Rockhampton Fine Foods",
    "wof:placetype":"venue"
},
  "geometry": {"coordinates":[150.49531555199999,-23.3846492767],"type":"Point"}
}