{
  "type": "Feature",
  "properties": {
    "addr:full":"59 Central La Gladstone QLD 4680",
    "addr:housenumber":"59",
    "addr:postcode":"4680",
    "addr:street":"Central La",
    "iso:country":"AU",
    "sg:address":"59 Central La",
    "sg:city":"Gladstone",
    "sg:classifiers":[
        {
            "category":"Shopping",
            "subcategory":"Gifts & Souvenirs",
            "type":"Retail Goods"
        }
    ],
    "sg:phone":"+61 7 4972 2493",
    "sg:postcode":"4680",
    "sg:province":"QLD",
    "sg:tags":[
        "print",
        "poster",
        "pictures"
    ],
    "wof:name":"Gladstone Picture Framing",
    "wof:placetype":"venue"
},
  "geometry": {"coordinates":[151.25355529800001,-23.8438205719],"type":"Point"}
}