{
  "type": "Feature",
  "properties": {
    "addr:full":"Unit G 2 Reliance Drv, Tuggerah Business Pk Tuggerah NSW 2259",
    "addr:housenumber":"2",
    "addr:postcode":"2259",
    "addr:street":"Reliance Drv;Business Pk",
    "iso:country":"AU",
    "sg:address":"Unit G 2",
    "sg:city":"Reliance Drv, Tuggerah Business Pk Tuggerah",
    "sg:classifiers":[
        {
            "category":"Professional",
            "subcategory":"Employment Agencies",
            "type":"Services"
        }
    ],
    "sg:phone":"+61 1300 130 077",
    "sg:postcode":"2259",
    "sg:province":"NSW",
    "sg:tags":[
        "hire",
        "labour",
        "contractor"
    ],
    "wof:name":"Advantage Recruitment",
    "wof:placetype":"venue"
},
  "geometry": {"coordinates":[151.421142578,-33.3138313293],"type":"Point"}
}