{
  "type": "Feature",
  "properties": {
    "addr:full":"957 New Cleveland Rd Gumdale QLD 4154",
    "addr:housenumber":"957",
    "addr:postcode":"4154",
    "addr:street":"New Cleveland Rd",
    "iso:country":"AU",
    "sg:address":"957 New Cleveland Rd",
    "sg:city":"Gumdale",
    "sg:classifiers":[
        {
            "category":"Professional",
            "subcategory":"Detective & Security Services",
            "type":"Services"
        }
    ],
    "sg:phone":"+61 7 3823 1488",
    "sg:postcode":"4154",
    "sg:province":"QLD",
    "sg:tags":[
        "consultant",
        "system"
    ],
    "wof:name":"Brisbane All Breed Dog Training & Kennels",
    "wof:placetype":"venue"
},
  "geometry": {"coordinates":[153.16612243599999,-27.492893219],"type":"Point"}
}