{
  "type": "Feature",
  "properties": {
    "iso:country":"AU",
    "sg:address":"690 Dandaloo Rd",
    "sg:city":"Narromine",
    "sg:classifiers":[
        {
            "category":"Farming",
            "subcategory":"Nursery",
            "type":"Manufacturing & Wholesale Goods"
        }
    ],
    "sg:phone":"+61 2 6889 4300",
    "sg:postcode":"2821",
    "sg:province":"NSW",
    "wof:name":"Grazing Management Systems Pty Ltd",
    "wof:placetype":"venue"
},
  "geometry": {"coordinates":[148.234085083,-32.2331237793],"type":"Point"}
}