{
  "type": "Feature",
  "properties": {
    "iso:country":"AU",
    "sg:address":"Shop 3/ 182 Little Collins St",
    "sg:city":"Melbourne",
    "sg:classifiers":[
        {
            "category":"Shopping",
            "subcategory":"Clothing, Apparel, & Fashions",
            "type":"Retail Goods"
        }
    ],
    "sg:phone":"+61 3 9654 8826",
    "sg:postcode":"3000",
    "sg:province":"VIC",
    "sg:tags":[
        "menswear"
    ],
    "wof:name":"Calibre Clothing",
    "wof:placetype":"venue"
},
  "geometry": {"coordinates":[144.96774292000001,-37.8138771057],"type":"Point"}
}