{
  "type": "Feature",
  "properties": {
    "addr:full":"11A Summerhill Crt Mudgeeraba QLD 4213",
    "addr:housenumber":"11a",
    "addr:postcode":"4213",
    "addr:street":"Summerhill Crt",
    "iso:country":"AU",
    "sg:address":"11A Summerhill Crt",
    "sg:city":"Mudgeeraba",
    "sg:classifiers":[
        {
            "category":"Building & Trades",
            "subcategory":"Construction",
            "type":"Services"
        }
    ],
    "sg:phone":"+61 403 059 366",
    "sg:postcode":"4213",
    "sg:province":"QLD",
    "sg:tags":[
        "plasterboard",
        "plasterer",
        "fixer"
    ],
    "wof:name":"Aaron Koschel Solid Plastering",
    "wof:placetype":"venue"
},
  "geometry": {"coordinates":[153.360794067,-28.0781650543],"type":"Point"}
}