{
  "type": "Feature",
  "properties": {
    "addr:full":"33 Pacific Hwy Wahroonga NSW 2076",
    "addr:housenumber":"33",
    "addr:postcode":"2076",
    "addr:street":"Pacific Hwy",
    "iso:country":"AU",
    "sg:address":"33 Pacific Hwy",
    "sg:city":"Wahroonga",
    "sg:classifiers":[
        {
            "category":"Travel",
            "subcategory":"Hotels & Motels",
            "type":"Entertainment"
        }
    ],
    "sg:phone":"+61 2 9487 3800",
    "sg:postcode":"2076",
    "sg:province":"NSW",
    "wof:name":"Temame Pty Ltd",
    "wof:placetype":"venue"
},
  "geometry": {"coordinates":[151.10824585,-33.7147789001],"type":"Point"}
}