{
  "type": "Feature",
  "properties": {
    "iso:country":"AU",
    "sg:address":"Cnr Buttle & Macquoid Sts",
    "sg:city":"Queanbeyan",
    "sg:classifiers":[
        {
            "category":"Education",
            "subcategory":"University",
            "type":"Public Place"
        }
    ],
    "sg:phone":"+61 2 6299 1377",
    "sg:postcode":"2620",
    "sg:province":"ACT",
    "sg:tags":[
        "college",
        "tertiary"
    ],
    "wof:name":"Queanbeyan TAFE",
    "wof:placetype":"venue"
},
  "geometry": {"coordinates":[149.24359130900001,-35.349697113],"type":"Point"}
}