{
  "type": "Feature",
  "properties": {
    "addr:full":"28 Mill St Bendigo VIC 3550",
    "addr:housenumber":"28",
    "addr:postcode":"3550",
    "addr:street":"Mill St",
    "iso:country":"AU",
    "sg:address":"28 Mill St",
    "sg:city":"Bendigo",
    "sg:classifiers":[
        {
            "category":"Professional",
            "subcategory":"Art Services",
            "type":"Services"
        }
    ],
    "sg:phone":"+61 3 5443 1259",
    "sg:postcode":"3550",
    "sg:province":"VIC",
    "sg:tags":[
        "artist"
    ],
    "wof:name":"Delecca Bill",
    "wof:placetype":"venue"
},
  "geometry": {"coordinates":[144.306564331,-36.7637329102],"type":"Point"}
}