{
  "type": "Feature",
  "properties": {
    "addr:full":"\"Nanjomara\" RMB 9130 Old Sale Road Willow Grove VIC 3825",
    "addr:housenumber":"9130",
    "addr:postcode":"3825",
    "addr:street":"Old Sale Road",
    "iso:country":"AU",
    "sg:address":"\"Nanjomara\" RMB 9130 Old Sale Road",
    "sg:city":"Willow Grove",
    "sg:classifiers":[
        {
            "category":"Farming",
            "subcategory":"Farm",
            "type":"Manufacturing & Wholesale Goods"
        }
    ],
    "sg:phone":"+61 3 5635 2203",
    "sg:postcode":"3825",
    "sg:province":"VIC",
    "sg:tags":[
        "farmer"
    ],
    "wof:name":"Bergamin Pastoral Co",
    "wof:placetype":"venue"
},
  "geometry": {"coordinates":[146.15025299999999,-38.098114],"type":"Point"}
}