{
  "type": "Feature",
  "properties": {
    "iso:country":"AU",
    "sg:address":"3 Rose St",
    "sg:city":"Grenfell",
    "sg:classifiers":[
        {
            "category":"Professional",
            "type":"Services"
        }
    ],
    "sg:phone":"+61 2 6343 1832",
    "sg:postcode":"2810",
    "sg:province":"NSW",
    "sg:tags":[
        "transport"
    ],
    "wof:name":"Stevens Andy Transport",
    "wof:placetype":"venue"
},
  "geometry": {"coordinates":[148.15742492699999,-33.8995819092],"type":"Point"}
}