{
  "type": "Feature",
  "properties": {
    "addr:full":"49 Bullara St Pambula NSW 2549",
    "addr:housenumber":"49",
    "addr:postcode":"2549",
    "addr:street":"Bullara St",
    "iso:country":"AU",
    "sg:address":"49 Bullara St",
    "sg:city":"Pambula",
    "sg:classifiers":[
        {
            "category":"Food & Beverages",
            "subcategory":"Fruits & Vegetables",
            "type":"Retail Goods"
        }
    ],
    "sg:phone":"+61 2 6495 6992",
    "sg:postcode":"2549",
    "sg:province":"NSW",
    "sg:tags":[
        "wholesale"
    ],
    "wof:name":"Pambula Fruit Barn",
    "wof:placetype":"venue"
},
  "geometry": {"coordinates":[149.870040894,-36.9315834045],"type":"Point"}
}