{
  "type": "Feature",
  "properties": {
    "iso:country":"AU",
    "sg:address":"Cnr Bridge & Phillip Sts",
    "sg:city":"Tamworth",
    "sg:classifiers":[
        {
            "category":"Food & Beverages",
            "subcategory":"Fruits & Vegetables",
            "type":"Retail Goods"
        }
    ],
    "sg:phone":"+61 2 6765 2200",
    "sg:postcode":"2340",
    "sg:province":"NSW",
    "sg:tags":[
        "greengrocer",
        "fruiterer"
    ],
    "wof:name":"Farmer Bob's Fruit Markets",
    "wof:placetype":"venue"
},
  "geometry": {"coordinates":[150.91290283199999,-31.0953865051],"type":"Point"}
}