{
  "type": "Feature",
  "properties": {
    "addr:full":"485a Hampton St Hampton VIC 3188",
    "addr:housenumber":"485a",
    "addr:postcode":"3188",
    "addr:street":"Hampton St",
    "iso:country":"AU",
    "sg:address":"485a Hampton St",
    "sg:city":"Hampton",
    "sg:classifiers":[
        {
            "category":"Restaurant",
            "type":"Food & Drink"
        }
    ],
    "sg:phone":"+61 3 9521 9139",
    "sg:postcode":"3188",
    "sg:province":"VIC",
    "wof:name":"A Taste Of Siam (Thai) Restaurant",
    "wof:placetype":"venue"
},
  "geometry": {"coordinates":[145.00320434599999,-37.9328727722],"type":"Point"}
}