{
  "type": "Feature",
  "properties": {
    "addr:full":"20 Patricia Rd Kalamunda WA 6076",
    "addr:housenumber":"20",
    "addr:postcode":"6076",
    "addr:street":"Patricia Rd",
    "iso:country":"AU",
    "sg:address":"20 Patricia Rd",
    "sg:city":"Kalamunda",
    "sg:classifiers":[
        {
            "category":"Farming",
            "subcategory":"Nursery",
            "type":"Manufacturing & Wholesale Goods"
        }
    ],
    "sg:phone":"+61 8 9293 2569",
    "sg:postcode":"6076",
    "sg:province":"WA",
    "wof:name":"Orange Valley Nursery",
    "wof:placetype":"venue"
},
  "geometry": {"coordinates":[116.04878234900001,-31.9853248596],"type":"Point"}
}