{
  "type": "Feature",
  "properties": {
    "iso:country":"AU",
    "sg:address":"182 Graham St",
    "sg:city":"Wonthaggi",
    "sg:classifiers":[
        {
            "category":"Health Services",
            "subcategory":"Doctor",
            "type":"Services"
        }
    ],
    "sg:phone":"+61 3 5672 2309",
    "sg:postcode":"3995",
    "sg:province":"VIC",
    "sg:tags":[
        "podiatrist"
    ],
    "wof:name":"Bass Coast Podiatry",
    "wof:placetype":"venue"
},
  "geometry": {"coordinates":[145.58772300000001,-38.606262],"type":"Point"}
}