{
  "type": "Feature",
  "properties": {
    "iso:country":"AU",
    "sg:address":"12B Fletcher St",
    "sg:city":"Applecross",
    "sg:classifiers":[
        {
            "category":"Farming",
            "subcategory":"Fish & Marine Products",
            "type":"Manufacturing & Wholesale Goods"
        }
    ],
    "sg:phone":"+61 8 9364 9993",
    "sg:postcode":"6153",
    "sg:province":"WA",
    "sg:tags":[
        "slate"
    ],
    "wof:name":"A. Golden Slate",
    "wof:placetype":"venue"
},
  "geometry": {"coordinates":[115.833702,-32.017586],"type":"Point"}
}