{
  "type": "Feature",
  "properties": {
    "iso:country":"AU",
    "sg:address":"16 Prosper St",
    "sg:city":"Rozelle",
    "sg:classifiers":[
        {
            "category":"Real Estate",
            "subcategory":"Architect",
            "type":"Services"
        }
    ],
    "sg:phone":"+61 2 9810 8942",
    "sg:postcode":"2039",
    "sg:province":"NSW",
    "sg:tags":[
        "building",
        "designer"
    ],
    "wof:name":"L A Reiv Designs",
    "wof:placetype":"venue"
},
  "geometry": {"coordinates":[151.171585083,-33.8640327454],"type":"Point"}
}