{
  "type": "Feature",
  "properties": {
    "addr:full":"Shp 72, Morayfield Shopng Cntr 165-175 Morayfield Morayfield QLD 4506",
    "addr:housenumber":"72",
    "addr:postcode":"165-175;4506",
    "addr:street":"Morayfield Shopng Cntr",
    "iso:country":"AU",
    "sg:address":"Shp 72, Morayfield Shopng Cntr 165-175 Morayfield",
    "sg:city":"Morayfield",
    "sg:classifiers":[
        {
            "category":"Shopping",
            "subcategory":"Mobile Phones",
            "type":"Retail Goods"
        }
    ],
    "sg:phone":"+61 7 5498 3533",
    "sg:postcode":"4506",
    "sg:province":"QLD",
    "sg:tags":[
        "telephone",
        "accessory"
    ],
    "wof:name":"Optus World",
    "wof:placetype":"venue"
},
  "geometry": {"coordinates":[152.95079040499999,-27.1113796234],"type":"Point"}
}