{
  "type": "Feature",
  "properties": {
    "addr:full":"111 View St Bendigo VIC 3550",
    "addr:housenumber":"111",
    "addr:postcode":"3550",
    "addr:street":"View St",
    "iso:country":"AU",
    "sg:address":"111 View St",
    "sg:city":"Bendigo",
    "sg:classifiers":[
        {
            "category":"Shopping",
            "subcategory":"Clothing, Apparel, & Fashions",
            "type":"Retail Goods"
        }
    ],
    "sg:phone":"+61 3 5442 6283",
    "sg:postcode":"3550",
    "sg:province":"VIC",
    "sg:tags":[
        "recycled",
        "clothing"
    ],
    "wof:name":"Julie's Clothing Boutique",
    "wof:placetype":"venue"
},
  "geometry": {"coordinates":[144.27610778799999,-36.757686615],"type":"Point"}
}