{
  "type": "Feature",
  "properties": {
    "addr:full":"Unit 7 216-228 Cowli Shaw St Tuggeranong ACT 2900",
    "addr:housenumber":"216-228",
    "addr:postcode":"2900",
    "addr:street":"Cowli Shaw St",
    "iso:country":"AU",
    "sg:address":"Unit 7 216-228 Cowli Shaw St",
    "sg:city":"Tuggeranong",
    "sg:classifiers":[
        {
            "category":"Travel",
            "subcategory":"Travel Agent",
            "type":"Entertainment"
        }
    ],
    "sg:phone":"+61 2 6293 2900",
    "sg:postcode":"2900",
    "sg:province":"ACT",
    "sg:tags":[
        "consultant"
    ],
    "wof:name":"Valley Travel Centre",
    "wof:placetype":"venue"
},
  "geometry": {"coordinates":[149.068267822,-35.4145126343],"type":"Point"}
}