{
  "type": "Feature",
  "properties": {
    "iso:country":"AU",
    "sg:address":"519 Metcalfe Rd",
    "sg:city":"Ferndale",
    "sg:classifiers":[
        {
            "category":"Building & Trades",
            "subcategory":"Landscaping Services",
            "type":"Services"
        }
    ],
    "sg:phone":"+61 412 195 647",
    "sg:postcode":"6148",
    "sg:province":"WA",
    "sg:tags":[
        "designer",
        "landscape",
        "contractor"
    ],
    "wof:name":"Garden Park Developments Pty Ltd",
    "wof:placetype":"venue"
},
  "geometry": {"coordinates":[115.925499,-32.036194],"type":"Point"}
}