{
  "type": "Feature",
  "properties": {
    "addr:full":"498 Hargreaves St Bendigo VIC 3550",
    "addr:housenumber":"498",
    "addr:postcode":"3550",
    "addr:street":"Hargreaves St",
    "iso:country":"AU",
    "sg:address":"498 Hargreaves St",
    "sg:city":"Bendigo",
    "sg:classifiers":[
        {
            "category":"Professional",
            "subcategory":"Accounting & Tax Preparation",
            "type":"Services"
        }
    ],
    "sg:phone":"+61 3 5444 4406",
    "sg:postcode":"3550",
    "sg:province":"VIC",
    "sg:tags":[
        "consultant",
        "taxation"
    ],
    "wof:name":"Craig John G.",
    "wof:placetype":"venue"
},
  "geometry": {"coordinates":[144.27272033700001,-36.7653121948],"type":"Point"}
}