{
  "type": "Feature",
  "properties": {
    "addr:full":"2/ 59 Cawarra Rd Caringbah NSW 2229",
    "addr:housenumber":"/ 59",
    "addr:postcode":"2229",
    "addr:street":"Cawarra Rd",
    "iso:country":"AU",
    "sg:address":"2/ 59 Cawarra Rd",
    "sg:city":"Caringbah",
    "sg:classifiers":[
        {
            "category":"Personal",
            "subcategory":"Nail Salon",
            "type":"Services"
        }
    ],
    "sg:phone":"+61 2 9542 7707",
    "sg:postcode":"2229",
    "sg:province":"NSW",
    "sg:tags":[
        "foil",
        "printing",
        "stamping"
    ],
    "sg:website":"http://www.multicolor.com.au",
    "wof:name":"J K Multicolor Pty Ltd",
    "wof:placetype":"venue"
},
  "geometry": {"coordinates":[151.13021850600001,-34.0293922424],"type":"Point"}
}