{
  "type": "Feature",
  "properties": {
    "iso:country":"AU",
    "sg:address":"1/ 9 Sir John Overall Drv",
    "sg:city":"Helensvale",
    "sg:classifiers":[
        {
            "category":"Health Services",
            "subcategory":"Chiropractor",
            "type":"Services"
        }
    ],
    "sg:phone":"+61 7 5500 0631",
    "sg:postcode":"4212",
    "sg:province":"QLD",
    "wof:name":"Nigel Nulty",
    "wof:placetype":"venue"
},
  "geometry": {"coordinates":[153.33575439399999,-27.9225196838],"type":"Point"}
}