{
  "type": "Feature",
  "properties": {
    "addr:full":"3 Cynga St Preston VIC 3072",
    "addr:housenumber":"3",
    "addr:postcode":"3072",
    "addr:street":"Cynga St",
    "iso:country":"AU",
    "sg:address":"3 Cynga St",
    "sg:city":"Preston",
    "sg:classifiers":[
        {
            "category":"Building & Trades",
            "subcategory":"Plumbing",
            "type":"Services"
        }
    ],
    "sg:phone":"+61 3 9484 4996",
    "sg:postcode":"3072",
    "sg:province":"VIC",
    "sg:tags":[
        "plumber",
        "gasfitters"
    ],
    "wof:name":"M.F. 23 Hour Emergency Service Plumbing",
    "wof:placetype":"venue"
},
  "geometry": {"coordinates":[145.021575928,-37.7453842163],"type":"Point"}
}