{
  "type": "Feature",
  "properties": {
    "addr:full":"Shop 4/ 5 Village Rw Yanchep WA 6035",
    "addr:housenumber":"shop 4 / 5",
    "addr:postcode":"6035",
    "addr:street":"Village Rw",
    "iso:country":"AU",
    "sg:address":"Shop 4/ 5 Village Rw",
    "sg:city":"Yanchep",
    "sg:classifiers":[
        {
            "category":"Personal",
            "subcategory":"Beauty Salon",
            "type":"Services"
        }
    ],
    "sg:phone":"+61 8 9561 5780",
    "sg:postcode":"6035",
    "sg:province":"WA",
    "sg:tags":[
        "hairdresser"
    ],
    "wof:name":"Chantarz Hair & Beauty",
    "wof:placetype":"venue"
},
  "geometry": {"coordinates":[115.679710388,-31.4855995178],"type":"Point"}
}