{
  "type": "Feature",
  "properties": {
    "iso:country":"AU",
    "sg:address":"15 Armstrong Rd",
    "sg:city":"Toormina",
    "sg:classifiers":[
        {
            "category":"Home & Garden",
            "subcategory":"Carpets & Floor Coverings",
            "type":"Retail Goods"
        }
    ],
    "sg:phone":"+61 410 458 377",
    "sg:postcode":"2452",
    "sg:province":"NSW",
    "sg:tags":[
        "tile",
        "wall"
    ],
    "wof:name":"Johnson's Tiling & Waterproofing",
    "wof:placetype":"venue"
},
  "geometry": {"coordinates":[153.086868,-30.350313],"type":"Point"}
}