{
  "type": "Feature",
  "properties": {
    "addr:full":"179 Burwood Rd Burwood NSW 2134",
    "addr:housenumber":"179",
    "addr:postcode":"2134",
    "addr:street":"Burwood Rd",
    "iso:country":"AU",
    "sg:address":"179 Burwood Rd",
    "sg:city":"Burwood",
    "sg:classifiers":[
        {
            "category":"Health Services",
            "subcategory":"Doctor",
            "type":"Services"
        }
    ],
    "sg:phone":"+61 2 9747 6327",
    "sg:postcode":"2134",
    "sg:province":"NSW",
    "sg:tags":[
        "medical",
        "practitioner"
    ],
    "wof:name":"Burwood Medical Practice",
    "wof:placetype":"venue"
},
  "geometry": {"coordinates":[151.10307312,-33.879573822],"type":"Point"}
}