{
  "type": "Feature",
  "properties": {
    "iso:country":"AU",
    "sg:address":"28 Verdant Siding Rd",
    "sg:city":"Bundaberg",
    "sg:classifiers":[
        {
            "category":"Freight",
            "type":"Transportation"
        }
    ],
    "sg:phone":"+61 7 4152 8444",
    "sg:postcode":"4670",
    "sg:province":"QLD",
    "sg:tags":[
        "transport",
        "refrigerated"
    ],
    "wof:name":"Bundaberg Refridgerated Transport",
    "wof:placetype":"venue"
},
  "geometry": {"coordinates":[152.36302185100001,-24.902256012],"type":"Point"}
}