{
  "type": "Feature",
  "properties": {
    "iso:country":"AU",
    "sg:address":"29 Bellrick St",
    "sg:city":"Acacia Ridge",
    "sg:classifiers":[
        {
            "category":"Professional",
            "type":"Services"
        }
    ],
    "sg:phone":"+61 7 3344 2855",
    "sg:postcode":"4110",
    "sg:province":"QLD",
    "sg:tags":[
        "shop",
        "fitting"
    ],
    "wof:name":"Intershop-Bentley (QLD) Pty Ltd",
    "wof:placetype":"venue"
},
  "geometry": {"coordinates":[153.03724670400001,-27.5805568695],"type":"Point"}
}