{
  "type": "Feature",
  "properties": {
    "addr:full":"276 Liverpool Rd Ashfield NSW 2131",
    "addr:housenumber":"276",
    "addr:postcode":"2131",
    "addr:street":"Liverpool Rd",
    "iso:country":"AU",
    "sg:address":"276 Liverpool Rd",
    "sg:city":"Ashfield",
    "sg:classifiers":[
        {
            "category":"Real Estate",
            "subcategory":"Real Estate Agent",
            "type":"Services"
        }
    ],
    "sg:phone":"+61 2 9799 1400",
    "sg:postcode":"2131",
    "sg:province":"NSW",
    "wof:name":"Elders Real Estate",
    "wof:placetype":"venue"
},
  "geometry": {"coordinates":[151.12400817899999,-33.8883552551],"type":"Point"}
}