{
  "type": "Feature",
  "properties": {
    "addr:full":"Lvl 3/ 10 Bridge St Sydney NSW 2000",
    "addr:housenumber":"/ 10",
    "addr:postcode":"2000",
    "addr:street":"Bridge St",
    "iso:country":"AU",
    "sg:address":"Lvl 3/ 10 Bridge St",
    "sg:city":"Sydney",
    "sg:classifiers":[
        {
            "category":"Banks & Credit Unions",
            "subcategory":"Investment Brokerage",
            "type":"Services"
        }
    ],
    "sg:phone":"+61 1300 376 233",
    "sg:postcode":"2000",
    "sg:province":"NSW",
    "sg:tags":[
        "share",
        "broker",
        "stock"
    ],
    "sg:website":"http://www.fpmarkets.com.au",
    "wof:name":"First Prudential Market Pty Ltd",
    "wof:placetype":"venue"
},
  "geometry": {"coordinates":[151.20814514200001,-33.86353302],"type":"Point"}
}