{
  "type": "Feature",
  "properties": {
    "iso:country":"AU",
    "sg:address":"5 Frederick St",
    "sg:city":"Northcote",
    "sg:classifiers":[
        {
            "category":"Organizations",
            "subcategory":"Community Association",
            "type":"Services"
        }
    ],
    "sg:phone":"+61 3 9489 0222",
    "sg:postcode":"3070",
    "sg:province":"VIC",
    "sg:tags":[
        "soldering"
    ],
    "wof:name":"Multicore Solders (Aust.) Pty.Ltd.",
    "wof:placetype":"venue"
},
  "geometry": {"coordinates":[144.998886,-37.772541],"type":"Point"}
}