{
  "type": "Feature",
  "properties": {
    "addr:full":"255. Wellington St Collingwood VIC 3066",
    "addr:housenumber":"255",
    "addr:postcode":"3066",
    "addr:street":"Wellington St",
    "iso:country":"AU",
    "sg:address":"255. Wellington St",
    "sg:city":"Collingwood",
    "sg:classifiers":[
        {
            "category":"Education",
            "subcategory":"Special Training",
            "type":"Public Place"
        }
    ],
    "sg:phone":"+61 3 9416 1011",
    "sg:postcode":"3066",
    "sg:province":"VIC",
    "sg:tags":[
        "development"
    ],
    "wof:name":"A.V. Sales & Installation",
    "wof:placetype":"venue"
},
  "geometry": {"coordinates":[144.98724365199999,-37.7988891602],"type":"Point"}
}