{
  "type": "Feature",
  "properties": {
    "addr:full":"105 Lennox St Richmond NSW 2753",
    "addr:housenumber":"105",
    "addr:postcode":"2753",
    "addr:street":"Lennox St",
    "iso:country":"AU",
    "sg:address":"105 Lennox St",
    "sg:city":"Richmond",
    "sg:classifiers":[
        {
            "category":"Health Services",
            "subcategory":"Health Practitioner",
            "type":"Services"
        }
    ],
    "sg:phone":"+61 2 4588 6623",
    "sg:postcode":"2753",
    "sg:province":"NSW",
    "sg:tags":[
        "psychologist"
    ],
    "wof:name":"Bernadette Keegan & Associates",
    "wof:placetype":"venue"
},
  "geometry": {"coordinates":[150.74913024899999,-33.5995750427],"type":"Point"}
}