{
  "type": "Feature",
  "properties": {
    "addr:full":"6 Scott St Hampton East VIC 3188",
    "addr:housenumber":"6",
    "addr:postcode":"3188",
    "addr:street":"Scott St",
    "iso:country":"AU",
    "sg:address":"6 Scott St",
    "sg:city":"Hampton East",
    "sg:classifiers":[
        {
            "category":"Home & Garden",
            "subcategory":"Carpets & Floor Coverings",
            "type":"Retail Goods"
        }
    ],
    "sg:phone":"+61 419 000 508",
    "sg:postcode":"3188",
    "sg:province":"VIC",
    "sg:tags":[
        "tile",
        "wall",
        "layer"
    ],
    "wof:name":"Donavan Peter",
    "wof:placetype":"venue"
},
  "geometry": {"coordinates":[145.03669738799999,-37.9438209534],"type":"Point"}
}