{
  "type": "Feature",
  "properties": {
    "addr:full":"Unit 5/ 7 Inglewood Pl Bella Vista NSW 2153",
    "addr:housenumber":"7",
    "addr:postcode":"2153",
    "addr:street":"Inglewood Pl",
    "iso:country":"AU",
    "sg:address":"Unit 5/ 7 Inglewood Pl",
    "sg:city":"Bella Vista",
    "sg:classifiers":[
        {
            "category":"Shopping",
            "subcategory":"Optical Goods",
            "type":"Retail Goods"
        }
    ],
    "sg:phone":"+61 418 242 348",
    "sg:postcode":"2153",
    "sg:province":"NSW",
    "sg:tags":[
        "supply"
    ],
    "wof:name":"Cytosol Ophtalmics Aust Pty Ltd",
    "wof:placetype":"venue"
},
  "geometry": {"coordinates":[150.95939636200001,-33.7352638245],"type":"Point"}
}