{
  "type": "Feature",
  "properties": {
    "addr:full":"New Veteran Rd Veteran QLD 4570",
    "addr:postcode":"4570",
    "addr:street":"Veteran Rd",
    "iso:country":"AU",
    "sg:address":"New Veteran Rd",
    "sg:city":"Veteran",
    "sg:classifiers":[
        {
            "category":"Farming",
            "subcategory":"Farm",
            "type":"Manufacturing & Wholesale Goods"
        }
    ],
    "sg:phone":"+61 7 5483 3725",
    "sg:postcode":"4570",
    "sg:province":"QLD",
    "sg:tags":[
        "farmer"
    ],
    "wof:name":"Mitchell I M",
    "wof:placetype":"venue"
},
  "geometry": {"coordinates":[152.711303711,-26.1539306641],"type":"Point"}
}