{
  "type": "Feature",
  "properties": {
    "iso:country":"AU",
    "sg:address":"1/ 85 Sheffield Rd",
    "sg:city":"Welshpool",
    "sg:classifiers":[
        {
            "category":"Local Transit",
            "type":"Transportation"
        }
    ],
    "sg:phone":"+61 8 9350 5596",
    "sg:postcode":"6106",
    "sg:province":"WA",
    "sg:tags":[
        "winch"
    ],
    "wof:name":"Thomas Winch",
    "wof:placetype":"venue"
},
  "geometry": {"coordinates":[115.97392273,-31.9945697784],"type":"Point"}
}