{
  "type": "Feature",
  "properties": {
    "addr:full":"19 Commercial St Korumburra VIC 3950",
    "addr:housenumber":"19",
    "addr:postcode":"3950",
    "addr:street":"Commercial St",
    "iso:country":"AU",
    "sg:address":"19 Commercial St",
    "sg:city":"Korumburra",
    "sg:classifiers":[
        {
            "category":"Professional",
            "subcategory":"Accounting & Tax Preparation",
            "type":"Services"
        }
    ],
    "sg:phone":"+61 3 5655 2311",
    "sg:postcode":"3950",
    "sg:province":"VIC",
    "sg:tags":[
        "consultant",
        "taxation"
    ],
    "wof:name":"Williams & Edwards",
    "wof:placetype":"venue"
},
  "geometry": {"coordinates":[145.82281494099999,-38.4323501587],"type":"Point"}
}