{
  "type": "Feature",
  "properties": {
    "iso:country":"AU",
    "sg:address":"394 Lawrence Hargrave Drv",
    "sg:city":"Thirroul",
    "sg:classifiers":[
        {
            "category":"Shopping",
            "subcategory":"Antiques",
            "type":"Retail Goods"
        }
    ],
    "sg:phone":"+61 2 4268 4128",
    "sg:postcode":"2515",
    "sg:province":"NSW",
    "wof:name":"Thirroul Antique Centre",
    "wof:placetype":"venue"
},
  "geometry": {"coordinates":[150.91661099999999,-34.318104],"type":"Point"}
}