{
  "type": "Feature",
  "properties": {
    "addr:full":"2 Parke St Katoomba NSW 2780",
    "addr:housenumber":"2",
    "addr:postcode":"2780",
    "addr:street":"Parke St",
    "iso:country":"AU",
    "sg:address":"2 Parke St",
    "sg:city":"Katoomba",
    "sg:classifiers":[
        {
            "category":"Fast Food",
            "type":"Food & Drink"
        }
    ],
    "sg:phone":"+61 2 4782 2242",
    "sg:postcode":"2780",
    "sg:province":"NSW",
    "sg:tags":[
        "away",
        "take"
    ],
    "wof:name":"Katoomba Charcoal Chicken",
    "wof:placetype":"venue"
},
  "geometry": {"coordinates":[150.309814453,-33.7151679993],"type":"Point"}
}