{
  "type": "Feature",
  "properties": {
    "iso:country":"AU",
    "sg:address":"104 Jacka St",
    "sg:city":"Bittern",
    "sg:classifiers":[
        {
            "category":"Autos & Motor Vehicles",
            "subcategory":"Auto Supplies",
            "type":"Retail Goods"
        }
    ],
    "sg:phone":"+61 3 5983 0145",
    "sg:postcode":"3918",
    "sg:province":"VIC",
    "sg:tags":[
        "paint",
        "automotive"
    ],
    "wof:name":"Scratch & Match Victoria",
    "wof:placetype":"venue"
},
  "geometry": {"coordinates":[145.18536376899999,-38.3429527283],"type":"Point"}
}