{
  "type": "Feature",
  "properties": {
    "iso:country":"AU",
    "sg:address":"62 Auburn St",
    "sg:city":"Wollongong",
    "sg:classifiers":[
        {
            "category":"Retail",
            "subcategory":"Auto Repair",
            "type":"Services"
        }
    ],
    "sg:phone":"+61 2 4228 8111",
    "sg:postcode":"2500",
    "sg:province":"NSW",
    "sg:tags":[
        "repairer",
        "motor",
        "engineer"
    ],
    "wof:name":"Dr Tune",
    "wof:placetype":"venue"
},
  "geometry": {"coordinates":[150.88848899999999,-34.431152],"type":"Point"}
}