{
  "type": "Feature",
  "properties": {
    "addr:full":"7 Mill St Mooroopna VIC 3629",
    "addr:housenumber":"7",
    "addr:postcode":"3629",
    "addr:street":"Mill St",
    "iso:country":"AU",
    "sg:address":"7 Mill St",
    "sg:city":"Mooroopna",
    "sg:classifiers":[
        {
            "category":"Home & Garden",
            "subcategory":"Building Materials",
            "type":"Retail Goods"
        }
    ],
    "sg:phone":"+61 3 5825 4660",
    "sg:postcode":"3629",
    "sg:province":"VIC",
    "sg:tags":[
        "supply"
    ],
    "wof:name":"Mooroopna Home Timber & Hardware",
    "wof:placetype":"venue"
},
  "geometry": {"coordinates":[145.36068725600001,-36.3938293457],"type":"Point"}
}