{
  "type": "Feature",
  "properties": {
    "addr:full":"PO Box 50 Newport Beach NSW 2106",
    "addr:postcode":"2106",
    "iso:country":"AU",
    "sg:address":"PO Box 50",
    "sg:city":"Newport Beach",
    "sg:classifiers":[
        {
            "category":"Personal",
            "type":"Services"
        }
    ],
    "sg:phone":"+61 2 9979 4949",
    "sg:postcode":"2106",
    "sg:province":"NSW",
    "sg:tags":[
        "career",
        "counselling"
    ],
    "wof:name":"Life By Design",
    "wof:placetype":"venue"
},
  "geometry": {"coordinates":[151.32052612300001,-33.6487770081],"type":"Point"}
}