{
  "type": "Feature",
  "properties": {
    "addr:full":"200 Homer St Earlwood NSW 2206",
    "addr:housenumber":"200",
    "addr:postcode":"2206",
    "addr:street":"Homer St",
    "iso:country":"AU",
    "sg:address":"200 Homer St",
    "sg:city":"Earlwood",
    "sg:classifiers":[
        {
            "category":"Retail",
            "subcategory":"Auto Rental",
            "type":"Services"
        }
    ],
    "sg:phone":"+61 2 9558 5155",
    "sg:postcode":"2206",
    "sg:province":"NSW",
    "sg:tags":[
        "car",
        "hire",
        "minibus"
    ],
    "wof:name":"AA Asydney Hire",
    "wof:placetype":"venue"
},
  "geometry": {"coordinates":[151.12329099999999,-33.928062],"type":"Point"}
}