{
  "type": "Feature",
  "properties": {
    "addr:full":"Shp 3/ 3078 Surfers Paradise Blv Surfers Paradise QLD 4217",
    "addr:housenumber":"/ 3078",
    "addr:postcode":"4217",
    "addr:street":"Surfers Paradise Blv",
    "iso:country":"AU",
    "sg:address":"Shp 3/ 3078 Surfers Paradise Blv",
    "sg:city":"Surfers Paradise",
    "sg:classifiers":[
        {
            "category":"Real Estate",
            "subcategory":"Real Estate Agent",
            "type":"Services"
        }
    ],
    "sg:phone":"+61 7 5527 6199",
    "sg:postcode":"4217",
    "sg:province":"QLD",
    "wof:name":"Boutique Estates",
    "wof:placetype":"venue"
},
  "geometry": {"coordinates":[153.42872619600001,-28.0046710968],"type":"Point"}
}