{
  "type": "Feature",
  "properties": {
    "iso:country":"AU",
    "sg:address":"2/ 22 Violet St",
    "sg:city":"Revesby",
    "sg:classifiers":[
        {
            "category":"Building & Trades",
            "subcategory":"Construction",
            "type":"Services"
        }
    ],
    "sg:phone":"+61 2 9771 1011",
    "sg:postcode":"2212",
    "sg:province":"NSW",
    "sg:tags":[
        "brick",
        "paving"
    ],
    "wof:name":"Advanced Building Systems Pty Ltd",
    "wof:placetype":"venue"
},
  "geometry": {"coordinates":[151.00614899999999,-33.935062],"type":"Point"}
}