{
  "type": "Feature",
  "properties": {
    "addr:full":"Shp1/ 58 Cavill Ave Surfers Paradise QLD 4217",
    "addr:postcode":"4217",
    "addr:street":"Cavill Ave",
    "iso:country":"AU",
    "sg:address":"Shp1/ 58 Cavill Ave",
    "sg:city":"Surfers Paradise",
    "sg:classifiers":[
        {
            "category":"Fast Food",
            "type":"Food & Drink"
        }
    ],
    "sg:phone":"+61 7 5538 2818",
    "sg:postcode":"4217",
    "sg:province":"QLD",
    "sg:tags":[
        "away",
        "take"
    ],
    "wof:name":"Atomic Crust",
    "wof:placetype":"venue"
},
  "geometry": {"coordinates":[153.426055908,-28.0015792847],"type":"Point"}
}