{
  "type": "Feature",
  "properties": {
    "addr:full":"207 Pacific Hwy St Leonards NSW 2065",
    "addr:housenumber":"207",
    "addr:postcode":"2065",
    "addr:street":"Pacific Hwy",
    "iso:country":"AU",
    "sg:address":"207 Pacific Hwy",
    "sg:city":"St Leonards",
    "sg:classifiers":[
        {
            "category":"Real Estate",
            "subcategory":"Real Estate Operator",
            "type":"Services"
        }
    ],
    "sg:phone":"+61 1300 133 585",
    "sg:postcode":"2065",
    "sg:province":"NSW",
    "sg:tags":[
        "paging",
        "radio",
        "system"
    ],
    "wof:name":"3 Paging & Messaging",
    "wof:placetype":"venue"
},
  "geometry": {"coordinates":[151.198944092,-33.8255500793],"type":"Point"}
}