{
  "type": "Feature",
  "properties": {
    "addr:full":"Shp 10/ 152 Graham St Wonthaggi VIC 3995",
    "addr:housenumber":"10 / 152",
    "addr:postcode":"3995",
    "addr:street":"Graham St",
    "iso:country":"AU",
    "sg:address":"Shp 10/ 152 Graham St",
    "sg:city":"Wonthaggi",
    "sg:classifiers":[
        {
            "category":"Shopping",
            "subcategory":"Party Supplies",
            "type":"Retail Goods"
        }
    ],
    "sg:phone":"+61 3 5672 2456",
    "sg:postcode":"3995",
    "sg:province":"VIC",
    "wof:name":"Balloon Bazaar",
    "wof:placetype":"venue"
},
  "geometry": {"coordinates":[145.589325,-38.606106],"type":"Point"}
}