{
  "type": "Feature",
  "properties": {
    "addr:full":"87 Onkaparinga Rd Bridgewater SA 5155",
    "addr:housenumber":"87",
    "addr:postcode":"5155",
    "addr:street":"Onkaparinga Rd",
    "iso:country":"AU",
    "sg:address":"87 Onkaparinga Rd",
    "sg:city":"Bridgewater",
    "sg:classifiers":[
        {
            "category":"Education",
            "subcategory":"Kindergarten",
            "type":"Public Place"
        }
    ],
    "sg:phone":"+61 8 8339 2681",
    "sg:postcode":"5155",
    "sg:province":"SA",
    "sg:tags":[
        "pre-schools"
    ],
    "wof:name":"Bridgewater Kindergarten",
    "wof:placetype":"venue"
},
  "geometry": {"coordinates":[138.769699097,-35.005771637],"type":"Point"}
}