{
  "type": "Feature",
  "properties": {
    "addr:full":"Cnr Ducat St & Kennedy Drv Tweed Heads NSW 2485",
    "addr:postcode":"2485",
    "addr:street":"Cnr Ducat St & Kennedy Drv",
    "iso:country":"AU",
    "sg:address":"Cnr Ducat St & Kennedy Drv",
    "sg:city":"Tweed Heads",
    "sg:classifiers":[
        {
            "category":"Personal",
            "subcategory":"Beauty Salon",
            "type":"Services"
        }
    ],
    "sg:phone":"+61 7 5536 7966",
    "sg:postcode":"2485",
    "sg:province":"NSW",
    "sg:tags":[
        "hairdresser"
    ],
    "wof:name":"Kylie Goodwin Hair & Beauty",
    "wof:placetype":"venue"
},
  "geometry": {"coordinates":[153.52603149399999,-28.183473587],"type":"Point"}
}