{
  "type": "Feature",
  "properties": {
    "iso:country":"AU",
    "sg:address":"51 Dixon Rd",
    "sg:city":"Rockingham",
    "sg:classifiers":[
        {
            "category":"Home & Garden",
            "subcategory":"Garden Supply",
            "type":"Retail Goods"
        }
    ],
    "sg:phone":"+61 8 9527 2907",
    "sg:postcode":"6168",
    "sg:province":"WA",
    "sg:tags":[
        "landscape"
    ],
    "wof:name":"Old Landscape Yard",
    "wof:placetype":"venue"
},
  "geometry": {"coordinates":[115.75499000000001,-32.276825],"type":"Point"}
}