{
  "type": "Feature",
  "properties": {
    "iso:country":"AU",
    "sg:address":"152- 162 Riley St",
    "sg:city":"East Sydney",
    "sg:classifiers":[
        {
            "category":"Insurance",
            "subcategory":"Insurance Agent",
            "type":"Services"
        }
    ],
    "sg:phone":"+61 2 9630 4299",
    "sg:postcode":"2010",
    "sg:province":"NSW",
    "sg:tags":[
        "broker"
    ],
    "wof:name":"Michael V Mahoney Insurance Brokers Pty Ltd",
    "wof:placetype":"venue"
},
  "geometry": {"coordinates":[151.214675903,-33.8780517578],"type":"Point"}
}