{
  "type": "Feature",
  "properties": {
    "iso:country":"AU",
    "sg:address":"Cnr Charleston Rd & Nolan St",
    "sg:city":"Bendigo",
    "sg:classifiers":[
        {
            "category":"Structure",
            "subcategory":"Bridge",
            "type":"Public Place"
        }
    ],
    "sg:phone":"+61 3 5443 5242",
    "sg:postcode":"3550",
    "sg:province":"VIC",
    "sg:tags":[
        "chainsaw",
        "brushcutters"
    ],
    "wof:name":"Bendigo Mower Service",
    "wof:placetype":"venue"
},
  "geometry": {"coordinates":[144.29060363799999,-36.7569541931],"type":"Point"}
}