{
  "type": "Feature",
  "properties": {
    "addr:full":"5 Wiradjuri Pl Griffith NSW 2680",
    "addr:housenumber":"5",
    "addr:postcode":"2680",
    "addr:street":"Wiradjuri Pl",
    "iso:country":"AU",
    "sg:address":"5 Wiradjuri Pl",
    "sg:city":"Griffith",
    "sg:classifiers":[
        {
            "category":"Health Services",
            "subcategory":"Doctor",
            "type":"Services"
        }
    ],
    "sg:phone":"+61 2 6964 4533",
    "sg:postcode":"2680",
    "sg:province":"NSW",
    "sg:tags":[
        "medical",
        "practitioner"
    ],
    "wof:name":"Griffith Aboriginal Medical Service",
    "wof:placetype":"venue"
},
  "geometry": {"coordinates":[146.05032299999999,-34.28944],"type":"Point"}
}