{
  "type": "Feature",
  "properties": {
    "addr:full":"PO Box 7200 Urangan QLD 4655",
    "addr:postcode":"4655",
    "iso:country":"AU",
    "sg:address":"PO Box 7200",
    "sg:city":"Urangan",
    "sg:classifiers":[
        {
            "category":"Communications",
            "type":"Services"
        }
    ],
    "sg:phone":"+61 7 4125 3342",
    "sg:postcode":"4655",
    "sg:province":"QLD",
    "sg:tags":[
        "antenna"
    ],
    "wof:name":"Hansen's Antennas",
    "wof:placetype":"venue"
},
  "geometry": {"coordinates":[152.89695699999999,-25.28817],"type":"Point"}
}