{
  "type": "Feature",
  "properties": {
    "iso:country":"AU",
    "sg:address":"44 Park Rd",
    "sg:city":"Cabramatta",
    "sg:classifiers":[
        {
            "category":"Fast Food",
            "type":"Food & Drink"
        }
    ],
    "sg:phone":"+61 2 9724 4551",
    "sg:postcode":"2166",
    "sg:province":"NSW",
    "sg:tags":[
        "away",
        "take"
    ],
    "wof:name":"Dong Son Take Away",
    "wof:placetype":"venue"
},
  "geometry": {"coordinates":[150.937255859,-33.8937530518],"type":"Point"}
}