{
  "type": "Feature",
  "properties": {
    "addr:full":"PO Box 117 Underwood QLD 4119",
    "addr:postcode":"4119",
    "iso:country":"AU",
    "sg:address":"PO Box 117",
    "sg:city":"Underwood",
    "sg:classifiers":[
        {
            "category":"Building & Trades",
            "subcategory":"Construction",
            "type":"Services"
        }
    ],
    "sg:phone":"+61 7 3219 7455",
    "sg:postcode":"4119",
    "sg:province":"QLD",
    "sg:tags":[
        "contractor"
    ],
    "wof:name":"Lynn Civil Pty Ltd",
    "wof:placetype":"venue"
},
  "geometry": {"coordinates":[153.11244201700001,-27.6068191528],"type":"Point"}
}