{
  "type": "Feature",
  "properties": {
    "iso:country":"AU",
    "sg:address":"Unit 2, 103 Auburn St",
    "sg:city":"Wollongong",
    "sg:classifiers":[
        {
            "category":"Retail",
            "subcategory":"Auto Repair",
            "type":"Services"
        }
    ],
    "sg:phone":"+61 2 4227 6808",
    "sg:postcode":"2500",
    "sg:province":"NSW",
    "sg:tags":[
        "repairer",
        "motor",
        "engineer"
    ],
    "wof:name":"Motortech",
    "wof:placetype":"venue"
},
  "geometry": {"coordinates":[150.88754299999999,-34.436619],"type":"Point"}
}