{
  "type": "Feature",
  "properties": {
    "iso:country":"AU",
    "sg:address":"Cnr Mansfield St & Princess Hwy",
    "sg:city":"Berwick",
    "sg:classifiers":[
        {
            "category":"Health Services",
            "subcategory":"Health Practitioner",
            "type":"Services"
        }
    ],
    "sg:phone":"+61 3 9796 2111",
    "sg:postcode":"3806",
    "sg:province":"VIC",
    "sg:tags":[
        "physiotherapist"
    ],
    "wof:name":"Berwick Lodge Physiotherapy",
    "wof:placetype":"venue"
},
  "geometry": {"coordinates":[145.343292236,-38.0330619812],"type":"Point"}
}