{
  "type": "Feature",
  "properties": {
    "addr:full":"16 Princess St Kew VIC 3101",
    "addr:housenumber":"16",
    "addr:postcode":"3101",
    "addr:street":"Princess St",
    "iso:country":"AU",
    "sg:address":"16 Princess St",
    "sg:city":"Kew",
    "sg:classifiers":[
        {
            "category":"Professional",
            "subcategory":"Art Services",
            "type":"Services"
        }
    ],
    "sg:phone":"+61 3 9853 9250",
    "sg:postcode":"3101",
    "sg:province":"VIC",
    "sg:tags":[
        "decorator",
        "painter"
    ],
    "wof:name":"Lifetime Property Maintenance",
    "wof:placetype":"venue"
},
  "geometry": {"coordinates":[145.029052734,-37.8065986633],"type":"Point"}
}