{
  "type": "Feature",
  "properties": {
    "iso:country":"AU",
    "sg:address":"Daweville Cut",
    "sg:city":"Mandurah",
    "sg:classifiers":[
        {
            "category":"Cafe",
            "type":"Food & Drink"
        }
    ],
    "sg:phone":"+61 8 9534 4144",
    "sg:postcode":"6210",
    "sg:province":"WA",
    "wof:name":"Jolly Frog",
    "wof:placetype":"venue"
},
  "geometry": {"coordinates":[115.641724,-32.603649],"type":"Point"}
}