{
  "type": "Feature",
  "properties": {
    "addr:full":"Starkie Rd Manjimup WA 6258",
    "addr:postcode":"6258",
    "addr:street":"Starkie Rd",
    "iso:country":"AU",
    "sg:address":"Starkie Rd",
    "sg:city":"Manjimup",
    "sg:classifiers":[
        {
            "category":"Building & Trades",
            "subcategory":"Landscaping Services",
            "type":"Services"
        }
    ],
    "sg:phone":"+61 8 9771 2130",
    "sg:postcode":"6258",
    "sg:province":"WA",
    "sg:tags":[
        "forestry",
        "consultant"
    ],
    "wof:name":"Casuarina Forest Services",
    "wof:placetype":"venue"
},
  "geometry": {"coordinates":[116.137672424,-34.2652168274],"type":"Point"}
}