{
  "type": "Feature",
  "properties": {
    "addr:full":"350 Galston Rd Galston NSW 2159",
    "addr:housenumber":"350",
    "addr:postcode":"2159",
    "addr:street":"Galston Rd",
    "iso:country":"AU",
    "sg:address":"350 Galston Rd",
    "sg:city":"Galston",
    "sg:classifiers":[
        {
            "category":"Food & Beverages",
            "subcategory":"Fruits & Vegetables",
            "type":"Retail Goods"
        }
    ],
    "sg:phone":"+61 2 9653 3577",
    "sg:postcode":"2159",
    "sg:province":"NSW",
    "sg:tags":[
        "greengrocer",
        "fruiterer"
    ],
    "wof:name":"Galston Greengrocer",
    "wof:placetype":"venue"
},
  "geometry": {"coordinates":[151.04627990700001,-33.6528930664],"type":"Point"}
}