{
  "type": "Feature",
  "properties": {
    "iso:country":"AU",
    "sg:address":"Unit 1, 16 Sunshine Pde",
    "sg:city":"Miami",
    "sg:classifiers":[
        {
            "category":"Building & Trades",
            "subcategory":"Construction",
            "type":"Services"
        }
    ],
    "sg:phone":"+61 7 5576 3342",
    "sg:postcode":"4220",
    "sg:province":"QLD",
    "sg:tags":[
        "rendering",
        "cement"
    ],
    "wof:name":"Ivan Veg",
    "wof:placetype":"venue"
},
  "geometry": {"coordinates":[153.44358825699999,-28.0745449066],"type":"Point"}
}