{
  "type": "Feature",
  "properties": {
    "iso:country":"AU",
    "sg:address":"Shop 113, 2nd Gallery Level, 412-414 George St",
    "sg:city":"Sydney",
    "sg:classifiers":[
        {
            "category":"Personal",
            "subcategory":"Skin Care",
            "type":"Services"
        }
    ],
    "sg:phone":"+61 2 9232 7138",
    "sg:postcode":"2000",
    "sg:province":"NSW",
    "sg:tags":[
        "treatment"
    ],
    "wof:name":"Face Of Man Skincare For Men",
    "wof:placetype":"venue"
},
  "geometry": {"coordinates":[151.207122803,-33.8694572449],"type":"Point"}
}