{
  "type": "Feature",
  "properties": {
    "addr:full":"26 Bulcock St Caloundra QLD 4551",
    "addr:housenumber":"26",
    "addr:postcode":"4551",
    "addr:street":"Bulcock St",
    "iso:country":"AU",
    "sg:address":"26 Bulcock St",
    "sg:city":"Caloundra",
    "sg:classifiers":[
        {
            "category":"Shopping",
            "subcategory":"Clothing, Apparel, & Fashions",
            "type":"Retail Goods"
        }
    ],
    "sg:phone":"+61 7 5491 1107",
    "sg:postcode":"4551",
    "sg:province":"QLD",
    "sg:tags":[
        "lady",
        "wear"
    ],
    "wof:name":"Sussanah's of Caloundra",
    "wof:placetype":"venue"
},
  "geometry": {"coordinates":[153.129730225,-26.8046760559],"type":"Point"}
}