{
  "type": "Feature",
  "properties": {
    "iso:country":"AU",
    "sg:address":"31 Shepherd St",
    "sg:city":"Marrickville",
    "sg:classifiers":[
        {
            "category":"Manufacturing",
            "subcategory":"Building Materials",
            "type":"Manufacturing & Wholesale Goods"
        }
    ],
    "sg:phone":"+61 2 9560 4969",
    "sg:postcode":"2204",
    "sg:province":"NSW",
    "sg:tags":[
        "equipment",
        "handling"
    ],
    "wof:name":"Paul Rhino Lift",
    "wof:placetype":"venue"
},
  "geometry": {"coordinates":[151.16372699999999,-33.904007],"type":"Point"}
}