{
  "type": "Feature",
  "properties": {
    "iso:country":"AU",
    "sg:address":"52 Camden St",
    "sg:city":"Fairfield Heights",
    "sg:classifiers":[
        {
            "category":"Social Services",
            "subcategory":"Child Care",
            "type":"Services"
        }
    ],
    "sg:phone":"+61 2 9727 5777",
    "sg:postcode":"2165",
    "sg:province":"NSW",
    "wof:name":"Roly Poly Educational Child Care",
    "wof:placetype":"venue"
},
  "geometry": {"coordinates":[150.94073486299999,-33.8668746948],"type":"Point"}
}