{
  "type": "Feature",
  "properties": {
    "iso:country":"AU",
    "sg:address":"8 Ward St",
    "sg:city":"Gladstone",
    "sg:classifiers":[
        {
            "category":"Building & Trades",
            "subcategory":"Landscaping Services",
            "type":"Services"
        }
    ],
    "sg:phone":"+61 8 8662 2222",
    "sg:postcode":"5473",
    "sg:province":"SA",
    "sg:tags":[
        "stump",
        "tree",
        "felling",
        "removal"
    ],
    "wof:name":"Shane Gill Backhoe & Cherry Picker Hire",
    "wof:placetype":"venue"
},
  "geometry": {"coordinates":[138.355682,-33.26318],"type":"Point"}
}