{
  "type": "Feature",
  "properties": {
    "iso:country":"AU",
    "sg:address":"56 Perfection Ave",
    "sg:city":"Stanhope Gardens",
    "sg:classifiers":[
        {
            "category":"Building & Trades",
            "subcategory":"Construction",
            "type":"Services"
        }
    ],
    "sg:phone":"+61 408 670 924",
    "sg:postcode":"2768",
    "sg:province":"NSW",
    "sg:tags":[
        "roof"
    ],
    "wof:name":"J V Z Steel Roof",
    "wof:placetype":"venue"
},
  "geometry": {"coordinates":[150.929382,-33.714458],"type":"Point"}
}