{
  "type": "Feature",
  "properties": {
    "addr:full":"Unit 5, 32 May La Neutral Bay NSW 2089",
    "addr:housenumber":"32",
    "addr:postcode":"2089",
    "addr:street":"May La",
    "iso:country":"AU",
    "sg:address":"Unit 5, 32 May La",
    "sg:city":"Neutral Bay",
    "sg:classifiers":[
        {
            "category":"Juice Bar",
            "subcategory":"None",
            "type":"Food & Drink"
        }
    ],
    "sg:phone":"+61 2 9904 2020",
    "sg:postcode":"2089",
    "sg:province":"NSW",
    "sg:tags":[
        "merchant",
        "fruit",
        "processor"
    ],
    "wof:name":"Foremils Int'l Trading",
    "wof:placetype":"venue"
},
  "geometry": {"coordinates":[151.221923828,-33.8320884705],"type":"Point"}
}