{
  "type": "Feature",
  "properties": {
    "iso:country":"AU",
    "sg:address":"Corea St",
    "sg:city":"Miranda",
    "sg:classifiers":[
        {
            "category":"Health Services",
            "subcategory":"Dentist",
            "type":"Services"
        }
    ],
    "sg:phone":"+61 2 9522 6518",
    "sg:postcode":"2228",
    "sg:province":"NSW",
    "wof:name":"Kalliris S",
    "wof:placetype":"venue"
},
  "geometry": {"coordinates":[151.09791564899999,-34.0243797302],"type":"Point"}
}