{
  "type": "Feature",
  "properties": {
    "iso:country":"AU",
    "sg:address":"Comet Bay College Allatoona Ave",
    "sg:city":"Secret Harbour",
    "sg:classifiers":[
        {
            "category":"Education",
            "subcategory":"School",
            "type":"Public Place"
        }
    ],
    "sg:phone":"+61 8 9553 8100",
    "sg:postcode":"6173",
    "sg:province":"WA",
    "sg:tags":[
        "state",
        "except",
        "nsw"
    ],
    "wof:name":"Schools Government (Public)",
    "wof:placetype":"venue"
},
  "geometry": {"coordinates":[115.764847,-32.41526],"type":"Point"}
}