{
  "type": "Feature",
  "properties": {
    "iso:country":"AU",
    "sg:address":"212 Mair St",
    "sg:city":"Ballarat Central",
    "sg:classifiers":[
        {
            "category":"Autos & Motor Vehicles",
            "subcategory":"Auto Supplies",
            "type":"Retail Goods"
        }
    ],
    "sg:phone":"+61 3 5334 4386",
    "sg:postcode":"3350",
    "sg:province":"VIC",
    "sg:tags":[
        "part",
        "cycles",
        "accessory"
    ],
    "wof:name":"H.O.D Hardware",
    "wof:placetype":"venue"
},
  "geometry": {"coordinates":[143.857773,-37.559521],"type":"Point"}
}