{
  "type": "Feature",
  "properties": {
    "addr:full":"1 Wenhams La Wangaratta VIC 3677",
    "addr:housenumber":"1",
    "addr:postcode":"3677",
    "addr:street":"Wenhams La",
    "iso:country":"AU",
    "sg:address":"1 Wenhams La",
    "sg:city":"Wangaratta",
    "sg:classifiers":[
        {
            "category":"Manufacturing",
            "subcategory":"Motor Vehicles & Parts",
            "type":"Manufacturing & Wholesale Goods"
        }
    ],
    "sg:phone":"+61 3 5721 4419",
    "sg:postcode":"3677",
    "sg:province":"VIC",
    "sg:tags":[
        "engine",
        "equipment",
        "diesel"
    ],
    "wof:name":"Cheshire & Williams Repairs Pty Ltd",
    "wof:placetype":"venue"
},
  "geometry": {"coordinates":[146.32835388199999,-36.382774353],"type":"Point"}
}