{
  "type": "Feature",
  "properties": {
    "iso:country":"AU",
    "sg:address":"(Cnr Benningfield Rd) 1 Leichhardt St",
    "sg:city":"Bull Creek",
    "sg:classifiers":[
        {
            "category":"Health Services",
            "subcategory":"Health Practitioner",
            "type":"Services"
        }
    ],
    "sg:phone":"+61 8 9312 3120",
    "sg:postcode":"6149",
    "sg:province":"WA",
    "sg:tags":[
        "physiotherapist"
    ],
    "wof:name":"Bullcreek Physiotherapy Centre",
    "wof:placetype":"venue"
},
  "geometry": {"coordinates":[115.85791,-32.062843],"type":"Point"}
}