{
  "type": "Feature",
  "properties": {
    "addr:full":"10 Wattle Rd Brookvale NSW 2100",
    "addr:housenumber":"10",
    "addr:postcode":"2100",
    "addr:street":"Wattle Rd",
    "iso:country":"AU",
    "sg:address":"10 Wattle Rd",
    "sg:city":"Brookvale",
    "sg:classifiers":[
        {
            "category":"Food & Beverages",
            "subcategory":"Fruits & Vegetables",
            "type":"Retail Goods"
        }
    ],
    "sg:phone":"+61 2 9938 2195",
    "sg:postcode":"2100",
    "sg:province":"NSW",
    "sg:tags":[
        "wholesale"
    ],
    "wof:name":"Leos Wholesale",
    "wof:placetype":"venue"
},
  "geometry": {"coordinates":[151.27784729000001,-33.7681350708],"type":"Point"}
}