{
  "type": "Feature",
  "properties": {
    "addr:full":"Cnr South St & Calley Drv Leeming WA 6149",
    "addr:postcode":"6149",
    "addr:street":"Cnr South St & Calley Drv",
    "iso:country":"AU",
    "sg:address":"Cnr South St & Calley Drv",
    "sg:city":"Leeming",
    "sg:classifiers":[
        {
            "category":"Health Services",
            "subcategory":"Doctor",
            "type":"Services"
        }
    ],
    "sg:phone":"+61 8 9310 3330",
    "sg:postcode":"6149",
    "sg:province":"WA",
    "sg:tags":[
        "medical",
        "practitioner"
    ],
    "wof:name":"Beilin Raphael",
    "wof:placetype":"venue"
},
  "geometry": {"coordinates":[115.86019899999999,-32.065849],"type":"Point"}
}