{
  "type": "Feature",
  "properties": {
    "addr:full":"142 McCormack St Manunda QLD 4870",
    "addr:housenumber":"142",
    "addr:postcode":"4870",
    "addr:street":"Mccormack St",
    "iso:country":"AU",
    "sg:address":"142 McCormack St",
    "sg:city":"Manunda",
    "sg:classifiers":[
        {
            "category":"Health Services",
            "subcategory":"Medical Lab",
            "type":"Services"
        }
    ],
    "sg:phone":"+61 7 4053 2726",
    "sg:postcode":"4870",
    "sg:province":"QLD",
    "sg:tags":[
        "laboratory",
        "dental"
    ],
    "wof:name":"Cairns Chrome Castings",
    "wof:placetype":"venue"
},
  "geometry": {"coordinates":[145.745040894,-16.9175376892],"type":"Point"}
}