{
  "type": "Feature",
  "properties": {
    "iso:country":"AU",
    "sg:address":"39 North Pde",
    "sg:city":"Campsie",
    "sg:classifiers":[
        {
            "category":"Banks & Credit Unions",
            "subcategory":"Financial Services",
            "type":"Services"
        }
    ],
    "sg:phone":"+61 1800 622 892",
    "sg:postcode":"2194",
    "sg:province":"NSW",
    "sg:tags":[
        "planning"
    ],
    "wof:name":"Count Wealth Accountants",
    "wof:placetype":"venue"
},
  "geometry": {"coordinates":[151.104263,-33.909824],"type":"Point"}
}