{
  "type": "Feature",
  "properties": {
    "iso:country":"AU",
    "sg:address":"Suite 1, 140 Russell St",
    "sg:city":"Toowoomba",
    "sg:classifiers":[
        {
            "category":"Professional",
            "subcategory":"Employment Agencies",
            "type":"Services"
        }
    ],
    "sg:phone":"+61 7 4638 9966",
    "sg:postcode":"4350",
    "sg:province":"QLD",
    "sg:tags":[
        "broker",
        "custom"
    ],
    "wof:name":"International Cargo Express Pty Ltd",
    "wof:placetype":"venue"
},
  "geometry": {"coordinates":[151.943985,-27.557863],"type":"Point"}
}