{
  "type": "Feature",
  "properties": {
    "iso:country":"AU",
    "sg:address":"Shop T58, Wendouree Village Norman St",
    "sg:city":"Ballarat",
    "sg:classifiers":[
        {
            "category":"Personal",
            "subcategory":"Beauty Salon",
            "type":"Services"
        }
    ],
    "sg:phone":"+61 3 5339 3500",
    "sg:postcode":"3350",
    "sg:province":"VIC",
    "sg:tags":[
        "hairdresser"
    ],
    "wof:name":"Just Cuts",
    "wof:placetype":"venue"
},
  "geometry": {"coordinates":[143.86625699999999,-37.537292],"type":"Point"}
}