{
  "type": "Feature",
  "properties": {
    "iso:country":"AU",
    "sg:address":"261 Charters Towers Rd",
    "sg:city":"Hermit Park",
    "sg:classifiers":[
        {
            "category":"Communications",
            "subcategory":"Film & Video Production",
            "type":"Services"
        }
    ],
    "sg:phone":"+61 7 4725 4533",
    "sg:postcode":"4812",
    "sg:province":"QLD",
    "sg:tags":[
        "dvd",
        "library"
    ],
    "wof:name":"Video Ezy",
    "wof:placetype":"venue"
},
  "geometry": {"coordinates":[146.79643200000001,-19.288822],"type":"Point"}
}