{
  "type": "Feature",
  "properties": {
    "addr:full":"Penhurst St Willoughby NSW 2068",
    "addr:postcode":"2068",
    "addr:street":"Penhurst St",
    "iso:country":"AU",
    "sg:address":"Penhurst St",
    "sg:city":"Willoughby",
    "sg:classifiers":[
        {
            "category":"Health Services",
            "subcategory":"Health Practitioner",
            "type":"Services"
        }
    ],
    "sg:phone":"+61 2 9967 3051",
    "sg:postcode":"2068",
    "sg:province":"NSW",
    "sg:tags":[
        "hypnotherapy"
    ],
    "wof:name":"Australian Hypnotherapists Association",
    "wof:placetype":"venue"
},
  "geometry": {"coordinates":[151.19874572800001,-33.7999801636],"type":"Point"}
}