{
  "type": "Feature",
  "properties": {
    "addr:full":"Lvl3/ 145 Flinders La Melbourne VIC 3000",
    "addr:postcode":"3000",
    "addr:street":"Flinders La",
    "iso:country":"AU",
    "sg:address":"Lvl3/ 145 Flinders La",
    "sg:city":"Melbourne",
    "sg:classifiers":[
        {
            "category":"Social Services",
            "subcategory":"Retirement Home",
            "type":"Services"
        }
    ],
    "sg:phone":"+61 3 9650 1001",
    "sg:postcode":"3000",
    "sg:province":"VIC",
    "sg:tags":[
        "environmental",
        "consultant",
        "pollution"
    ],
    "wof:name":"Thrive Sustainability Services",
    "wof:placetype":"venue"
},
  "geometry": {"coordinates":[144.96974182100001,-37.8158035278],"type":"Point"}
}