{
  "type": "Feature",
  "properties": {
    "addr:full":"Unit 1/ 711 Boundary Rd Coopers Plains QLD 4108",
    "addr:housenumber":"/ 711",
    "addr:postcode":"4108",
    "addr:street":"Boundary Rd",
    "iso:country":"AU",
    "sg:address":"Unit 1/ 711 Boundary Rd",
    "sg:city":"Coopers Plains",
    "sg:classifiers":[
        {
            "category":"Professional",
            "type":"Services"
        }
    ],
    "sg:phone":"+61 7 3272 7222",
    "sg:postcode":"4108",
    "sg:province":"QLD",
    "sg:tags":[
        "courier"
    ],
    "wof:name":"Black Thunder Express",
    "wof:placetype":"venue"
},
  "geometry": {"coordinates":[153.02560424800001,-27.5686683655],"type":"Point"}
}