{
  "type": "Feature",
  "properties": {
    "addr:full":"175 Cooper St Epping VIC 3076",
    "addr:housenumber":"175",
    "addr:postcode":"3076",
    "addr:street":"Cooper St",
    "iso:country":"AU",
    "sg:address":"175 Cooper St",
    "sg:city":"Epping",
    "sg:classifiers":[
        {
            "category":"Health Services",
            "subcategory":"Dentist",
            "type":"Services"
        }
    ],
    "sg:phone":"+61 1300 733 077",
    "sg:postcode":"3076",
    "sg:province":"VIC",
    "wof:name":"Smile Council Orthodontics",
    "wof:placetype":"venue"
},
  "geometry": {"coordinates":[145.01603698700001,-37.6513519287],"type":"Point"}
}