{
  "type": "Feature",
  "properties": {
    "iso:country":"AU",
    "sg:address":"Cnr Argyle Pde & Harcourt Road",
    "sg:city":"Darra",
    "sg:classifiers":[
        {
            "category":"Retail",
            "subcategory":"Auto Repair",
            "type":"Services"
        }
    ],
    "sg:phone":"+61 7 3255 5588",
    "sg:postcode":"4076",
    "sg:province":"QLD",
    "sg:tags":[
        "bus",
        "truck"
    ],
    "wof:name":"Alltrucks Master Mechanics & Fabrication Pty Ltd",
    "wof:placetype":"venue"
},
  "geometry": {"coordinates":[152.95774841299999,-27.5647773743],"type":"Point"}
}