{
  "type": "Feature",
  "properties": {
    "iso:country":"AU",
    "sg:address":"4 Phillip St",
    "sg:city":"Panania",
    "sg:classifiers":[
        {
            "category":"Professional",
            "subcategory":"Printing & Photocopies",
            "type":"Services"
        }
    ],
    "sg:phone":"+61 418 426 562",
    "sg:postcode":"2213",
    "sg:province":"NSW",
    "sg:tags":[
        "embroidery"
    ],
    "wof:name":"Leonards Embroidery",
    "wof:placetype":"venue"
},
  "geometry": {"coordinates":[150.998077,-33.963257],"type":"Point"}
}