{
  "type": "Feature",
  "properties": {
    "addr:full":"56 Marshall St Dapto NSW 2530",
    "addr:housenumber":"56",
    "addr:postcode":"2530",
    "addr:street":"Marshall St",
    "iso:country":"AU",
    "sg:address":"56 Marshall St",
    "sg:city":"Dapto",
    "sg:classifiers":[
        {
            "category":"Home & Garden",
            "subcategory":"Building Materials",
            "type":"Retail Goods"
        }
    ],
    "sg:phone":"+61 2 4261 7072",
    "sg:postcode":"2530",
    "sg:province":"NSW",
    "sg:tags":[
        "fencing"
    ],
    "wof:name":"Perry's Timber & Fencing",
    "wof:placetype":"venue"
},
  "geometry": {"coordinates":[150.78958129899999,-34.4988670349],"type":"Point"}
}