{
  "type": "Feature",
  "properties": {
    "addr:full":"41 Beech Drv Cashmere QLD 4500",
    "addr:housenumber":"41",
    "addr:postcode":"4500",
    "addr:street":"Beech Drv",
    "iso:country":"AU",
    "sg:address":"41 Beech Drv",
    "sg:city":"Cashmere",
    "sg:classifiers":[
        {
            "category":"Building & Trades",
            "subcategory":"Construction",
            "type":"Services"
        }
    ],
    "sg:phone":"+61 7 3298 6111",
    "sg:postcode":"4500",
    "sg:province":"QLD",
    "sg:tags":[
        "contractor"
    ],
    "wof:name":"Taylor C J & D",
    "wof:placetype":"venue"
},
  "geometry": {"coordinates":[152.92666625999999,-27.3213920593],"type":"Point"}
}