{
  "type": "Feature",
  "properties": {
    "addr:full":"25 Moore St Moonee Ponds VIC 3039",
    "addr:housenumber":"25",
    "addr:postcode":"3039",
    "addr:street":"Moore St",
    "iso:country":"AU",
    "sg:address":"25 Moore St",
    "sg:city":"Moonee Ponds",
    "sg:classifiers":[
        {
            "category":"Health Services",
            "subcategory":"Health Practitioner",
            "type":"Services"
        }
    ],
    "sg:phone":"+61 3 9370 5441",
    "sg:postcode":"3039",
    "sg:province":"VIC",
    "sg:tags":[
        "physiotherapist"
    ],
    "wof:name":"Cransberg Emma",
    "wof:placetype":"venue"
},
  "geometry": {"coordinates":[144.920288,-37.768436],"type":"Point"}
}