{
  "type": "Feature",
  "properties": {
    "addr:full":"41 McCathie St Ayr QLD 4807",
    "addr:housenumber":"41",
    "addr:postcode":"4807",
    "addr:street":"Mccathie St",
    "iso:country":"AU",
    "sg:address":"41 McCathie St",
    "sg:city":"Ayr",
    "sg:classifiers":[
        {
            "category":"Wholesale",
            "subcategory":"Scrap",
            "type":"Manufacturing & Wholesale Goods"
        }
    ],
    "sg:phone":"+61 408 703 257",
    "sg:postcode":"4807",
    "sg:province":"QLD",
    "sg:tags":[
        "merchant",
        "metal"
    ],
    "wof:name":"Ellsley Scrap Metals",
    "wof:placetype":"venue"
},
  "geometry": {"coordinates":[147.395217895,-19.5594654083],"type":"Point"}
}