{
  "type": "Feature",
  "properties": {
    "iso:country":"AU",
    "sg:address":"3 338 Frankston Dandenong Rd",
    "sg:city":"Dandenong",
    "sg:classifiers":[
        {
            "category":"Retail",
            "subcategory":"Auto Repair",
            "type":"Services"
        }
    ],
    "sg:phone":"+61 3 9768 3886",
    "sg:postcode":"3175",
    "sg:province":"VIC",
    "sg:tags":[
        "bus",
        "truck"
    ],
    "wof:name":"Total Truck Bodies Pty Ltd",
    "wof:placetype":"venue"
},
  "geometry": {"coordinates":[145.21119689899999,-38.034160614],"type":"Point"}
}