{
  "type": "Feature",
  "properties": {
    "iso:country":"AU",
    "sg:address":"Shop 1 - 10a Atherton Rd",
    "sg:city":"Oakleigh",
    "sg:classifiers":[
        {
            "category":"Health Services",
            "subcategory":"Chiropractor",
            "type":"Services"
        }
    ],
    "sg:phone":"+61 3 9563 1277",
    "sg:postcode":"3166",
    "sg:province":"VIC",
    "wof:name":"Adamopoulos John",
    "wof:placetype":"venue"
},
  "geometry": {"coordinates":[145.08998107900001,-37.8985824585],"type":"Point"}
}