{
  "type": "Feature",
  "properties": {
    "iso:country":"AU",
    "sg:address":"169 Elliott St",
    "sg:city":"Whyalla Playford",
    "sg:classifiers":[
        {
            "category":"Manufacturing",
            "subcategory":"Signs",
            "type":"Manufacturing & Wholesale Goods"
        }
    ],
    "sg:phone":"+61 8 8645 9997",
    "sg:postcode":"5600",
    "sg:province":"SA",
    "sg:tags":[
        "traffic",
        "safety"
    ],
    "wof:name":"King Signs",
    "wof:placetype":"venue"
},
  "geometry": {"coordinates":[137.560654,-33.025833],"type":"Point"}
}