{
  "type": "Feature",
  "properties": {
    "iso:country":"AU",
    "sg:address":"14 Lock Rd",
    "sg:city":"Rhyll",
    "sg:classifiers":[
        {
            "category":"Cafe",
            "type":"Food & Drink"
        }
    ],
    "sg:phone":"+61 3 5956 9530",
    "sg:postcode":"3923",
    "sg:province":"VIC",
    "wof:name":"Janssons Cottage",
    "wof:placetype":"venue"
},
  "geometry": {"coordinates":[145.307128906,-38.4632072449],"type":"Point"}
}