{
  "type": "Feature",
  "properties": {
    "addr:full":"247 Whitehorse Rd Balwyn VIC 3103",
    "addr:housenumber":"247",
    "addr:postcode":"3103",
    "addr:street":"Whitehorse Rd",
    "iso:country":"AU",
    "sg:address":"247 Whitehorse Rd",
    "sg:city":"Balwyn",
    "sg:classifiers":[
        {
            "category":"Professional",
            "subcategory":"Employment Agencies",
            "type":"Services"
        }
    ],
    "sg:phone":"+61 3 9817 5360",
    "sg:postcode":"3103",
    "sg:province":"VIC",
    "sg:tags":[
        "provider",
        "internet"
    ],
    "wof:name":"Websurf",
    "wof:placetype":"venue"
},
  "geometry": {"coordinates":[145.07658386200001,-37.8120994568],"type":"Point"}
}