{
  "type": "Feature",
  "properties": {
    "addr:full":"4 Loretta Ave Gelorup WA 6230",
    "addr:housenumber":"4",
    "addr:postcode":"6230",
    "addr:street":"Loretta Ave",
    "iso:country":"AU",
    "sg:address":"4 Loretta Ave",
    "sg:city":"Gelorup",
    "sg:classifiers":[
        {
            "category":"Food & Beverages",
            "subcategory":"Specialty",
            "type":"Retail Goods"
        }
    ],
    "sg:phone":"+61 8 9795 8768",
    "sg:postcode":"6230",
    "sg:province":"WA",
    "sg:tags":[
        "product",
        "health"
    ],
    "wof:name":"Herbal Life",
    "wof:placetype":"venue"
},
  "geometry": {"coordinates":[115.639473,-33.399445],"type":"Point"}
}