{
  "type": "Feature",
  "properties": {
    "addr:full":"230 Beaconsfield Emerald Rd Dewhurst VIC 3808",
    "addr:housenumber":"230",
    "addr:postcode":"3808",
    "addr:street":"Beaconsfield Emerald Rd",
    "iso:country":"AU",
    "sg:address":"230 Beaconsfield Emerald Rd",
    "sg:city":"Dewhurst",
    "sg:classifiers":[
        {
            "category":"Professional",
            "subcategory":"Printing & Photocopies",
            "type":"Services"
        }
    ],
    "sg:phone":"+61 3 5944 4430",
    "sg:postcode":"3808",
    "sg:province":"VIC",
    "sg:tags":[
        "screen",
        "printer"
    ],
    "wof:name":"The Big Screenprint Company",
    "wof:placetype":"venue"
},
  "geometry": {"coordinates":[145.46386699999999,-37.979092],"type":"Point"}
}