{
  "type": "Feature",
  "properties": {
    "iso:country":"AU",
    "sg:address":"285 Victoria St",
    "sg:city":"North Melbourne",
    "sg:classifiers":[
        {
            "category":"Manufacturing",
            "subcategory":"Musical Instruments",
            "type":"Manufacturing & Wholesale Goods"
        }
    ],
    "sg:phone":"+61 3 9326 3759",
    "sg:postcode":"3051",
    "sg:province":"VIC",
    "sg:tags":[
        "repair",
        "maker"
    ],
    "wof:name":"Lovell Guitars",
    "wof:placetype":"venue"
},
  "geometry": {"coordinates":[144.95181274399999,-37.8055152893],"type":"Point"}
}