{
  "type": "Feature",
  "properties": {
    "addr:full":"129 Nerang St Southport QLD 4215",
    "addr:housenumber":"129",
    "addr:postcode":"4215",
    "addr:street":"Nerang St",
    "iso:country":"AU",
    "sg:address":"129 Nerang St",
    "sg:city":"Southport",
    "sg:classifiers":[
        {
            "category":"Health Services",
            "subcategory":"Dentist",
            "type":"Services"
        }
    ],
    "sg:phone":"+61 7 5532 3433",
    "sg:postcode":"4215",
    "sg:province":"QLD",
    "wof:name":"Gullotta Orthodontics",
    "wof:placetype":"venue"
},
  "geometry": {"coordinates":[153.40733337399999,-27.9711151123],"type":"Point"}
}