{
  "type": "Feature",
  "properties": {
    "addr:full":"15 Deep Creek Rd Mitcham VIC 3132",
    "addr:housenumber":"15",
    "addr:postcode":"3132",
    "addr:street":"Deep Creek Rd",
    "iso:country":"AU",
    "sg:address":"15 Deep Creek Rd",
    "sg:city":"Mitcham",
    "sg:classifiers":[
        {
            "category":"Building & Trades",
            "subcategory":"Construction",
            "type":"Services"
        }
    ],
    "sg:phone":"+61 419 622 213",
    "sg:postcode":"3132",
    "sg:province":"VIC",
    "sg:tags":[
        "contractor"
    ],
    "wof:name":"Universal Building Enterprise Pty Ltd",
    "wof:placetype":"venue"
},
  "geometry": {"coordinates":[145.20774841299999,-37.8165092468],"type":"Point"}
}