{
  "type": "Feature",
  "properties": {
    "iso:country":"AU",
    "sg:address":"17 Beach St",
    "sg:city":"Harrington",
    "sg:classifiers":[
        {
            "category":"Food & Beverages",
            "subcategory":"Liquor & Beverages",
            "type":"Retail Goods"
        }
    ],
    "sg:phone":"+61 2 6556 1437",
    "sg:postcode":"2427",
    "sg:province":"NSW",
    "sg:tags":[
        "store"
    ],
    "wof:name":"Harrington Cellars",
    "wof:placetype":"venue"
},
  "geometry": {"coordinates":[152.686966,-31.871096],"type":"Point"}
}