{
  "type": "Feature",
  "properties": {
    "addr:full":"PO Box 4022 Mataranka NT 0852",
    "addr:postcode":"nt 0852",
    "iso:country":"AU",
    "sg:address":"PO Box 4022",
    "sg:city":"Mataranka",
    "sg:classifiers":[
        {
            "category":"Education",
            "subcategory":"School",
            "type":"Public Place"
        }
    ],
    "sg:phone":"+61 8 8975 4543",
    "sg:postcode":"0852",
    "sg:province":"NT",
    "sg:tags":[
        "state",
        "except",
        "nsw"
    ],
    "wof:name":"Mataranka Primary School",
    "wof:placetype":"venue"
},
  "geometry": {"coordinates":[133.075333,-14.958],"type":"Point"}
}