{
  "type": "Feature",
  "properties": {
    "addr:full":"265 High St Thomastown VIC 3074",
    "addr:housenumber":"265",
    "addr:postcode":"3074",
    "addr:street":"High St",
    "iso:country":"AU",
    "sg:address":"265 High St",
    "sg:city":"Thomastown",
    "sg:classifiers":[
        {
            "category":"Fast Food",
            "type":"Food & Drink"
        }
    ],
    "sg:phone":"+61 3 9464 4833",
    "sg:postcode":"3074",
    "sg:province":"VIC",
    "sg:tags":[
        "away",
        "take"
    ],
    "wof:name":"Thomastown Kebab House",
    "wof:placetype":"venue"
},
  "geometry": {"coordinates":[145.01402282699999,-37.6784286499],"type":"Point"}
}