{
  "type": "Feature",
  "properties": {
    "iso:country":"AU",
    "sg:address":"13 Broughton St",
    "sg:city":"Kirribilli",
    "sg:classifiers":[
        {
            "category":"Health Services",
            "subcategory":"Doctor",
            "type":"Services"
        }
    ],
    "sg:phone":"+61 2 9955 3642",
    "sg:postcode":"2061",
    "sg:province":"NSW",
    "sg:tags":[
        "nurse",
        "nursing"
    ],
    "wof:name":"Medi-Call Placements",
    "wof:placetype":"venue"
},
  "geometry": {"coordinates":[151.21295165999999,-33.8465843201],"type":"Point"}
}