{
  "type": "Feature",
  "properties": {
    "iso:country":"AU",
    "sg:address":"1103/201 Collins St",
    "sg:city":"Melbourne",
    "sg:classifiers":[
        {
            "category":"Professional",
            "subcategory":"Management & Consulting",
            "type":"Services"
        }
    ],
    "sg:phone":"+61 3 9639 5189",
    "sg:postcode":"3000",
    "sg:province":"VIC",
    "sg:tags":[
        "consultant"
    ],
    "wof:name":"Skill Corp Pty Ltd",
    "wof:placetype":"venue"
},
  "geometry": {"coordinates":[144.967285156,-37.8153991699],"type":"Point"}
}