{
  "type": "Feature",
  "properties": {
    "addr:full":"8 Jacaranda St Bridgeman Downs QLD 4035",
    "addr:housenumber":"8",
    "addr:postcode":"4035",
    "addr:street":"Jacaranda St",
    "iso:country":"AU",
    "sg:address":"8 Jacaranda St",
    "sg:city":"Bridgeman Downs",
    "sg:classifiers":[
        {
            "category":"Arts & Performance",
            "subcategory":"Dance",
            "type":"Entertainment"
        }
    ],
    "sg:phone":"+61 431 219 202",
    "sg:postcode":"4035",
    "sg:province":"QLD",
    "sg:tags":[
        "theatrical",
        "ballet",
        "tuition"
    ],
    "wof:name":"Heather Gerrard",
    "wof:placetype":"venue"
},
  "geometry": {"coordinates":[153.00065599999999,-27.360168],"type":"Point"}
}