{
  "type": "Feature",
  "properties": {
    "addr:full":"Bryant Rd Ararat VIC 3377",
    "addr:postcode":"3377",
    "addr:street":"Bryant Rd",
    "iso:country":"AU",
    "sg:address":"Bryant Rd",
    "sg:city":"Ararat",
    "sg:classifiers":[
        {
            "category":"Professional",
            "type":"Services"
        }
    ],
    "sg:phone":"+61 438 388 214",
    "sg:postcode":"3377",
    "sg:province":"VIC",
    "sg:tags":[
        "transport"
    ],
    "wof:name":"Midnight Transport",
    "wof:placetype":"venue"
},
  "geometry": {"coordinates":[142.92880249000001,-37.2997932434],"type":"Point"}
}