{
  "type": "Feature",
  "properties": {
    "iso:country":"AU",
    "sg:address":"17 Eena St",
    "sg:city":"Yelarbon",
    "sg:classifiers":[
        {
            "category":"Education",
            "subcategory":"School",
            "type":"Public Place"
        }
    ],
    "sg:phone":"+61 7 4675 1109",
    "sg:postcode":"4388",
    "sg:province":"QLD",
    "sg:tags":[
        "state",
        "except",
        "nsw"
    ],
    "wof:name":"Yelarbon Primary",
    "wof:placetype":"venue"
},
  "geometry": {"coordinates":[150.752884,-28.573118],"type":"Point"}
}