{
  "type": "Feature",
  "properties": {
    "iso:country":"AU",
    "sg:address":"Basement 228 Flinders La",
    "sg:city":"Melbourne",
    "sg:classifiers":[
        {
            "category":"Travel",
            "subcategory":"Hotels & Motels",
            "type":"Entertainment"
        }
    ],
    "sg:phone":"+61 3 9650 2977",
    "sg:postcode":"3000",
    "sg:province":"VIC",
    "sg:tags":[
        "pub"
    ],
    "wof:name":"6 Links",
    "wof:placetype":"venue"
},
  "geometry": {"coordinates":[144.96629333499999,-37.8165512085],"type":"Point"}
}