{
  "type": "Feature",
  "properties": {
    "addr:full":"20 Thomson St Earlville QLD 4870",
    "addr:housenumber":"20",
    "addr:postcode":"4870",
    "addr:street":"Thomson St",
    "iso:country":"AU",
    "sg:address":"20 Thomson St",
    "sg:city":"Earlville",
    "sg:classifiers":[
        {
            "category":"Home & Garden",
            "subcategory":"Carpets & Floor Coverings",
            "type":"Retail Goods"
        }
    ],
    "sg:phone":"+61 412 398 765",
    "sg:postcode":"4870",
    "sg:province":"QLD",
    "sg:tags":[
        "tile",
        "wall",
        "layer"
    ],
    "wof:name":"Coral Coast Tiling",
    "wof:placetype":"venue"
},
  "geometry": {"coordinates":[145.74095153799999,-16.9393348694],"type":"Point"}
}