{
  "type": "Feature",
  "properties": {
    "addr:full":"Nottle Rd Gawler Belt SA 5118",
    "addr:postcode":"5118",
    "addr:street":"Nottle Rd",
    "iso:country":"AU",
    "sg:address":"Nottle Rd",
    "sg:city":"Gawler Belt",
    "sg:classifiers":[
        {
            "category":"Building & Trades",
            "subcategory":"Construction",
            "type":"Services"
        }
    ],
    "sg:phone":"+61 428 834 140",
    "sg:postcode":"5118",
    "sg:province":"SA",
    "sg:tags":[
        "earth",
        "excavating",
        "moving",
        "contractor"
    ],
    "wof:name":"Hilton Nap Earthmovers",
    "wof:placetype":"venue"
},
  "geometry": {"coordinates":[138.712357,-34.583874],"type":"Point"}
}