{
  "type": "Feature",
  "properties": {
    "addr:full":"PO Box 5873 Rockhampton Mail Cntr QLD 4702",
    "addr:postcode":"4702",
    "addr:street":"Cntr",
    "iso:country":"AU",
    "sg:address":"PO Box 5873",
    "sg:city":"Rockhampton Mail Cntr",
    "sg:classifiers":[
        {
            "category":"Retail",
            "subcategory":"Repair Shop",
            "type":"Services"
        }
    ],
    "sg:phone":"+61 408 185 008",
    "sg:postcode":"4702",
    "sg:province":"QLD",
    "sg:tags":[
        "machine",
        "repairs",
        "part",
        "dryer",
        "washing"
    ],
    "wof:name":"Rohan's Electrical",
    "wof:placetype":"venue"
},
  "geometry": {"coordinates":[150.43182373100001,-25.0342769623],"type":"Point"}
}