{
  "type": "Feature",
  "properties": {
    "addr:full":"174 Woodward St Orange NSW 2800",
    "addr:housenumber":"174",
    "addr:postcode":"2800",
    "addr:street":"Woodward St",
    "iso:country":"AU",
    "sg:address":"174 Woodward St",
    "sg:city":"Orange",
    "sg:classifiers":[
        {
            "category":"Autos & Motor Vehicles",
            "subcategory":"Fuel & Gas Station",
            "type":"Retail Goods"
        }
    ],
    "sg:phone":"+61 2 6362 1592",
    "sg:postcode":"2800",
    "sg:province":"NSW",
    "wof:name":"Mobil Oil Australia Pty Ltd",
    "wof:placetype":"venue"
},
  "geometry": {"coordinates":[149.08631897000001,-33.2819099426],"type":"Point"}
}