{
  "type": "Feature",
  "properties": {
    "iso:country":"AU",
    "sg:address":"111 Adelaide Rd",
    "sg:city":"Murray Bridge",
    "sg:classifiers":[
        {
            "category":"Banks & Credit Unions",
            "subcategory":"Bureau De Change",
            "type":"Services"
        }
    ],
    "sg:phone":"+61 1300 134 820",
    "sg:postcode":"5253",
    "sg:province":"SA",
    "sg:tags":[
        "repairs",
        "part",
        "appliance",
        "electrical"
    ],
    "wof:name":"OUR Service Company",
    "wof:placetype":"venue"
},
  "geometry": {"coordinates":[139.26792907699999,-35.1222953796],"type":"Point"}
}