{
  "type": "Feature",
  "properties": {
    "iso:country":"AU",
    "sg:address":"Pacific Hwy",
    "sg:city":"Ballina",
    "sg:classifiers":[
        {
            "category":"Travel",
            "subcategory":"Hotels & Motels",
            "type":"Entertainment"
        }
    ],
    "sg:phone":"+61 2 6686 3982",
    "sg:postcode":"2478",
    "sg:province":"NSW",
    "wof:name":"Fun &#039;N&#039; Sun Motel",
    "wof:placetype":"venue"
},
  "geometry": {"coordinates":[153.554962158,-28.8678760529],"type":"Point"}
}