{
  "type": "Feature",
  "properties": {
    "iso:country":"AU",
    "sg:address":"500 South Rd",
    "sg:city":"Kurralta Park",
    "sg:classifiers":[
        {
            "category":"Retail",
            "subcategory":"Car Wash",
            "type":"Services"
        }
    ],
    "sg:phone":"+61 8 8293 7453",
    "sg:postcode":"5037",
    "sg:province":"SA",
    "sg:tags":[
        "truck",
        "cleaning"
    ],
    "wof:name":"Big Bucket Car Wash",
    "wof:placetype":"venue"
},
  "geometry": {"coordinates":[138.57128906200001,-34.947517395],"type":"Point"}
}