{
  "type": "Feature",
  "properties": {
    "iso:country":"AU",
    "sg:address":"112 Glenora St",
    "sg:city":"Wynnum",
    "sg:classifiers":[
        {
            "category":"Retail",
            "subcategory":"Auto Repair",
            "type":"Services"
        }
    ],
    "sg:phone":"+61 7 3393 6364",
    "sg:postcode":"4178",
    "sg:province":"QLD",
    "sg:tags":[
        "repairer",
        "motor",
        "engineer"
    ],
    "wof:name":"Mike Price Mechanical",
    "wof:placetype":"venue"
},
  "geometry": {"coordinates":[153.16668701200001,-27.4375934601],"type":"Point"}
}