{
  "type": "Feature",
  "properties": {
    "iso:country":"AU",
    "sg:address":"Westfield Shoppingtown Tuggerah Shop 1040",
    "sg:city":"Tuggerah",
    "sg:classifiers":[
        {
            "category":"Education",
            "subcategory":"School",
            "type":"Public Place"
        }
    ],
    "sg:phone":"+61 2 4353 5301",
    "sg:postcode":"2259",
    "sg:province":"NSW",
    "sg:tags":[
        "supply"
    ],
    "wof:name":"Dymocks",
    "wof:placetype":"venue"
},
  "geometry": {"coordinates":[151.41519165,-33.306842804],"type":"Point"}
}