{
  "type": "Feature",
  "properties": {
    "addr:full":"Gantheaume Point Rd Broome WA 6725",
    "addr:postcode":"6725",
    "addr:street":"Rd",
    "iso:country":"AU",
    "sg:address":"Gantheaume Point Rd",
    "sg:city":"Broome",
    "sg:classifiers":[
        {
            "category":"Arena",
            "subcategory":"Sports Club",
            "type":"Entertainment"
        }
    ],
    "sg:phone":"+61 8 9192 2085",
    "sg:postcode":"6725",
    "sg:province":"WA",
    "sg:tags":[
        "hunt",
        "racing"
    ],
    "wof:name":"Broome Turf Club",
    "wof:placetype":"venue"
},
  "geometry": {"coordinates":[122.209877014,-17.9642562866],"type":"Point"}
}