{
  "type": "Feature",
  "properties": {
    "addr:full":"37 Elanora Drv Rockingham WA 6168",
    "addr:housenumber":"37",
    "addr:postcode":"6168",
    "addr:street":"Elanora Drv",
    "iso:country":"AU",
    "sg:address":"37 Elanora Drv",
    "sg:city":"Rockingham",
    "sg:classifiers":[
        {
            "category":"Health Services",
            "subcategory":"Dentist",
            "type":"Services"
        }
    ],
    "sg:phone":"+61 1300 483 384",
    "sg:postcode":"6168",
    "sg:province":"WA",
    "wof:name":"DB Dental",
    "wof:placetype":"venue"
},
  "geometry": {"coordinates":[115.762878,-32.294498],"type":"Point"}
}