{
  "type": "Feature",
  "properties": {
    "addr:full":"131 Auburn Rd Hawthorn VIC 3122",
    "addr:housenumber":"131",
    "addr:postcode":"3122",
    "addr:street":"Auburn Rd",
    "iso:country":"AU",
    "sg:address":"131 Auburn Rd",
    "sg:city":"Hawthorn",
    "sg:classifiers":[
        {
            "category":"Shopping",
            "subcategory":"Bridal",
            "type":"Retail Goods"
        }
    ],
    "sg:phone":"+61 3 9813 3777",
    "sg:postcode":"3122",
    "sg:province":"VIC",
    "sg:tags":[
        "hire",
        "wear"
    ],
    "wof:name":"Libby Naylor Designs",
    "wof:placetype":"venue"
},
  "geometry": {"coordinates":[145.04185485799999,-37.8388175964],"type":"Point"}
}