{
  "type": "Feature",
  "properties": {
    "addr:full":"6 Silkhorn Crs Mt Martha VIC 3934",
    "addr:housenumber":"6",
    "addr:postcode":"3934",
    "addr:street":"Silkhorn Crs Mt Martha",
    "iso:country":"AU",
    "sg:address":"6 Silkhorn Crs",
    "sg:city":"Mt Martha",
    "sg:classifiers":[
        {
            "category":"Farming",
            "subcategory":"Fish & Marine Products",
            "type":"Manufacturing & Wholesale Goods"
        }
    ],
    "sg:phone":"+61 3 5974 4481",
    "sg:postcode":"3934",
    "sg:province":"VIC",
    "sg:tags":[
        "asphalt",
        "supply"
    ],
    "wof:name":"ABC Driveways Pty Ltd",
    "wof:placetype":"venue"
},
  "geometry": {"coordinates":[145.030853272,-38.2737808228],"type":"Point"}
}