{
  "type": "Feature",
  "properties": {
    "iso:country":"AU",
    "sg:address":"Shp 3/ 178 Great Western Hwy",
    "sg:city":"Kingswood",
    "sg:classifiers":[
        {
            "category":"Fast Food",
            "type":"Food & Drink"
        }
    ],
    "sg:phone":"+61 2 4736 1775",
    "sg:postcode":"2747",
    "sg:province":"NSW",
    "sg:tags":[
        "away",
        "take"
    ],
    "wof:name":"Sub Way Kingswood",
    "wof:placetype":"venue"
},
  "geometry": {"coordinates":[150.720870972,-33.7590446472],"type":"Point"}
}