{
  "type": "Feature",
  "properties": {
    "iso:country":"AU",
    "sg:address":"8 Blair St",
    "sg:city":"Culcairn",
    "sg:classifiers":[
        {
            "category":"Education",
            "subcategory":"School",
            "type":"Public Place"
        }
    ],
    "sg:phone":"+61 2 6029 8577",
    "sg:postcode":"2660",
    "sg:province":"NSW",
    "wof:name":"St Joseph's Primary School",
    "wof:placetype":"venue"
},
  "geometry": {"coordinates":[147.03562927199999,-35.6683425903],"type":"Point"}
}