{
  "type": "Feature",
  "properties": {
    "addr:full":"1/ 18 Bentley St Williamstown VIC 3016",
    "addr:housenumber":"/ 18",
    "addr:postcode":"3016",
    "addr:street":"Bentley St",
    "iso:country":"AU",
    "sg:address":"1/ 18 Bentley St",
    "sg:city":"Williamstown",
    "sg:classifiers":[
        {
            "category":"Retail",
            "subcategory":"Auto Repair",
            "type":"Services"
        }
    ],
    "sg:phone":"+61 3 9399 8801",
    "sg:postcode":"3016",
    "sg:province":"VIC",
    "sg:tags":[
        "repairer",
        "motor",
        "engineer"
    ],
    "wof:name":"Ricky Ricardos Fuel Injection Specialist",
    "wof:placetype":"venue"
},
  "geometry": {"coordinates":[144.860229492,-37.8519821167],"type":"Point"}
}