{
  "type": "Feature",
  "properties": {
    "iso:country":"AU",
    "sg:address":"39a Manton St",
    "sg:city":"Hindmarsh",
    "sg:classifiers":[
        {
            "category":"Home & Garden",
            "subcategory":"Garden Supply",
            "type":"Retail Goods"
        }
    ],
    "sg:phone":"+61 8 8342 6011",
    "sg:postcode":"5007",
    "sg:province":"SA",
    "sg:tags":[
        "equipment",
        "hydroponics"
    ],
    "wof:name":"Applied Hydroponics & Gardening",
    "wof:placetype":"venue"
},
  "geometry": {"coordinates":[138.569702148,-34.9067077637],"type":"Point"}
}