{
  "type": "Feature",
  "properties": {
    "iso:country":"AU",
    "sg:address":"Shop 22, Kingston Town Shopping Centre, Maranoa Rd",
    "sg:city":"Kingston",
    "sg:classifiers":[
        {
            "category":"Shopping",
            "subcategory":"Shoes",
            "type":"Retail Goods"
        }
    ],
    "sg:phone":"+61 3 6229 1922",
    "sg:postcode":"7050",
    "sg:province":"TAS",
    "sg:tags":[
        "footwear"
    ],
    "wof:name":"Payless Shoes",
    "wof:placetype":"venue"
},
  "geometry": {"coordinates":[147.307175,-42.976063],"type":"Point"}
}