{
  "type": "Feature",
  "properties": {
    "iso:country":"AU",
    "sg:address":"Shp56/ 18 Church Ave",
    "sg:city":"Mascot",
    "sg:classifiers":[
        {
            "category":"Shopping",
            "subcategory":"Computers & Home Electronics",
            "type":"Retail Goods"
        }
    ],
    "sg:phone":"+61 2 9317 3743",
    "sg:postcode":"2020",
    "sg:province":"NSW",
    "sg:tags":[
        "hardware",
        "equipment"
    ],
    "wof:name":"B & M Computers Pty Ltd",
    "wof:placetype":"venue"
},
  "geometry": {"coordinates":[151.19415283199999,-33.9310417175],"type":"Point"}
}