{
  "type": "Feature",
  "properties": {
    "iso:country":"AU",
    "sg:address":"17 Lansell Rd",
    "sg:city":"Werribee",
    "sg:classifiers":[
        {
            "category":"Building & Trades",
            "subcategory":"Construction",
            "type":"Services"
        }
    ],
    "sg:phone":"+61 3 9741 1405",
    "sg:postcode":"3030",
    "sg:province":"VIC",
    "sg:tags":[
        "home",
        "air conditioning"
    ],
    "wof:name":"Footscray & District Refrigeration Service",
    "wof:placetype":"venue"
},
  "geometry": {"coordinates":[144.618164,-37.889614],"type":"Point"}
}