{
  "type": "Feature",
  "properties": {
    "addr:full":"46 Parklands Rd North Ryde NSW 2113",
    "addr:housenumber":"46",
    "addr:postcode":"2113",
    "addr:street":"Parklands Rd",
    "iso:country":"AU",
    "sg:address":"46 Parklands Rd",
    "sg:city":"North Ryde",
    "sg:classifiers":[
        {
            "category":"Professional",
            "subcategory":"Art Services",
            "type":"Services"
        }
    ],
    "sg:phone":"+61 2 9805 0770",
    "sg:postcode":"2113",
    "sg:province":"NSW",
    "sg:tags":[
        "decorator",
        "painter"
    ],
    "wof:name":"Rohy Painting",
    "wof:placetype":"venue"
},
  "geometry": {"coordinates":[151.118743897,-33.7875823975],"type":"Point"}
}