{
  "type": "Feature",
  "properties": {
    "addr:full":"Shop 16 Carine Glades Shopping Centre Carine WA 6020",
    "addr:housenumber":"shop 16",
    "addr:postcode":"6020",
    "iso:country":"AU",
    "sg:address":"Shop 16 Carine Glades Shopping Centre",
    "sg:city":"Carine",
    "sg:classifiers":[
        {
            "category":"Fast Food",
            "type":"Food & Drink"
        }
    ],
    "sg:phone":"+61 8 9447 7133",
    "sg:postcode":"6020",
    "sg:province":"WA",
    "sg:tags":[
        "away",
        "take"
    ],
    "wof:name":"Splash's Fish House",
    "wof:placetype":"venue"
},
  "geometry": {"coordinates":[115.776611328,-31.8511104584],"type":"Point"}
}