{
  "type": "Feature",
  "properties": {
    "iso:country":"AU",
    "sg:address":"109 Marius St",
    "sg:city":"Tamworth",
    "sg:classifiers":[
        {
            "category":"Personal",
            "subcategory":"Beauty Salon",
            "type":"Services"
        }
    ],
    "sg:phone":"+61 2 6766 6126",
    "sg:postcode":"2340",
    "sg:province":"NSW",
    "sg:tags":[
        "hairdresser"
    ],
    "wof:name":"Colour By Numbers",
    "wof:placetype":"venue"
},
  "geometry": {"coordinates":[150.92703247099999,-31.0844650269],"type":"Point"}
}