{
  "type": "Feature",
  "properties": {
    "addr:full":"Crooked Brook Rd Dardanup WA 6236",
    "addr:postcode":"6236",
    "addr:street":"Brook Rd",
    "iso:country":"AU",
    "sg:address":"Crooked Brook Rd",
    "sg:city":"Dardanup",
    "sg:classifiers":[
        {
            "category":"Farming",
            "subcategory":"Dairy Farm",
            "type":"Manufacturing & Wholesale Goods"
        }
    ],
    "sg:phone":"+61 8 9728 3011",
    "sg:postcode":"6236",
    "sg:province":"WA",
    "wof:name":"Mountford C G",
    "wof:placetype":"venue"
},
  "geometry": {"coordinates":[115.753761,-33.411121],"type":"Point"}
}