{
  "type": "Feature",
  "properties": {
    "addr:full":"172 Old Hamilton Rd Haven VIC 3401",
    "addr:housenumber":"172",
    "addr:postcode":"3401",
    "addr:street":"Old Hamilton Rd",
    "iso:country":"AU",
    "sg:address":"172 Old Hamilton Rd",
    "sg:city":"Haven",
    "sg:classifiers":[
        {
            "category":"Building & Trades",
            "subcategory":"Construction",
            "type":"Services"
        }
    ],
    "sg:phone":"+61 3 5382 2817",
    "sg:postcode":"3401",
    "sg:province":"VIC",
    "sg:tags":[
        "contractor"
    ],
    "wof:name":"Cross P.& S. Builders",
    "wof:placetype":"venue"
},
  "geometry": {"coordinates":[142.20510864299999,-36.7554740906],"type":"Point"}
}