{
  "type": "Feature",
  "properties": {
    "addr:full":"172 Jacobs Drv Sussex Inlet NSW 2540",
    "addr:housenumber":"172",
    "addr:postcode":"2540",
    "addr:street":"Jacobs Drv",
    "iso:country":"AU",
    "sg:address":"172 Jacobs Drv",
    "sg:city":"Sussex Inlet",
    "sg:classifiers":[
        {
            "category":"Shopping",
            "subcategory":"Clothing, Apparel, & Fashions",
            "type":"Retail Goods"
        }
    ],
    "sg:phone":"+61 2 4441 1800",
    "sg:postcode":"2540",
    "sg:province":"NSW",
    "sg:tags":[
        "lady",
        "wear"
    ],
    "wof:name":"Chattaboks Fashions",
    "wof:placetype":"venue"
},
  "geometry": {"coordinates":[150.59979248100001,-35.1569061279],"type":"Point"}
}