{
  "type": "Feature",
  "properties": {
    "addr:full":"17 Glendower St Rosemeadow NSW 2560",
    "addr:housenumber":"17",
    "addr:postcode":"2560",
    "addr:street":"Glendower St",
    "iso:country":"AU",
    "sg:address":"17 Glendower St",
    "sg:city":"Rosemeadow",
    "sg:classifiers":[
        {
            "category":"Professional",
            "subcategory":"Art Services",
            "type":"Services"
        }
    ],
    "sg:phone":"+61 411 567 111",
    "sg:postcode":"2560",
    "sg:province":"NSW",
    "sg:tags":[
        "product",
        "industrial",
        "designer"
    ],
    "wof:name":"Abalos Dennis",
    "wof:placetype":"venue"
},
  "geometry": {"coordinates":[150.791259766,-34.1081047058],"type":"Point"}
}