{
  "type": "Feature",
  "properties": {
    "addr:full":"297 Trafalgar St Petersham NSW 2049",
    "addr:housenumber":"297",
    "addr:postcode":"2049",
    "addr:street":"Trafalgar St",
    "iso:country":"AU",
    "sg:address":"297 Trafalgar St",
    "sg:city":"Petersham",
    "sg:classifiers":[
        {
            "category":"Education",
            "subcategory":"University",
            "type":"Public Place"
        }
    ],
    "sg:phone":"+61 2 9568 8600",
    "sg:postcode":"2049",
    "sg:province":"NSW",
    "sg:tags":[
        "educational",
        "organisation",
        "cultural"
    ],
    "wof:name":"New Mardi Gras",
    "wof:placetype":"venue"
},
  "geometry": {"coordinates":[151.155136,-33.894447],"type":"Point"}
}