{
  "type": "Feature",
  "properties": {
    "addr:full":"20 Druids Ave Stirling SA 5152",
    "addr:housenumber":"20",
    "addr:postcode":"5152",
    "addr:street":"Druids Ave",
    "iso:country":"AU",
    "sg:address":"20 Druids Ave",
    "sg:city":"Stirling",
    "sg:classifiers":[
        {
            "category":"Utilities",
            "subcategory":"Electric",
            "type":"Services"
        }
    ],
    "sg:phone":"+61 8 8339 7287",
    "sg:postcode":"5152",
    "sg:province":"SA",
    "sg:tags":[
        "electrical",
        "contractor"
    ],
    "wof:name":"P.S.B. Electrical",
    "wof:placetype":"venue"
},
  "geometry": {"coordinates":[138.715133667,-35.006439209],"type":"Point"}
}