{
  "type": "Feature",
  "properties": {
    "iso:country":"AU",
    "sg:address":"5 Crawford St",
    "sg:city":"Ulverstone",
    "sg:classifiers":[
        {
            "category":"Building & Trades",
            "subcategory":"Locksmith",
            "type":"Services"
        }
    ],
    "sg:phone":"+61 438 254 989",
    "sg:postcode":"7315",
    "sg:province":"TAS",
    "sg:tags":[
        "equipment",
        "operating",
        "door",
        "gate"
    ],
    "wof:name":"Tasgate Pty Ltd",
    "wof:placetype":"venue"
},
  "geometry": {"coordinates":[146.18878173799999,-41.1552658081],"type":"Point"}
}