{
  "type": "Feature",
  "properties": {
    "addr:full":"2C Margaret St Woolwich NSW 2110",
    "addr:housenumber":"2c",
    "addr:postcode":"2110",
    "addr:street":"Margaret St",
    "iso:country":"AU",
    "sg:address":"2C Margaret St",
    "sg:city":"Woolwich",
    "sg:classifiers":[
        {
            "category":"Autos & Motor Vehicles",
            "subcategory":"Boat Sales",
            "type":"Retail Goods"
        }
    ],
    "sg:phone":"+61 2 9879 0189",
    "sg:postcode":"2110",
    "sg:province":"NSW",
    "sg:tags":[
        "builder",
        "yacht",
        "repairer"
    ],
    "wof:name":"Walsh Joe Mast & Yacht Rigging",
    "wof:placetype":"venue"
},
  "geometry": {"coordinates":[151.16893005399999,-33.8423233032],"type":"Point"}
}