{
  "type": "Feature",
  "properties": {
    "addr:full":"155 Utley Rd Serpentine WA 6125",
    "addr:housenumber":"155",
    "addr:postcode":"6125",
    "addr:street":"Utley Rd",
    "iso:country":"AU",
    "sg:address":"155 Utley Rd",
    "sg:city":"Serpentine",
    "sg:classifiers":[
        {
            "category":"Farming",
            "subcategory":"Livestock Farm",
            "type":"Manufacturing & Wholesale Goods"
        }
    ],
    "sg:phone":"+61 417 916 934",
    "sg:postcode":"6125",
    "sg:province":"WA",
    "sg:tags":[
        "agistment"
    ],
    "wof:name":"K & T Broad",
    "wof:placetype":"venue"
},
  "geometry": {"coordinates":[115.96293640099999,-32.3959770203],"type":"Point"}
}