{
  "type": "Feature",
  "properties": {
    "addr:full":"Royal Mail Hotel 90 Brisbane Tce Goodna QLD 4300",
    "addr:housenumber":"90",
    "addr:postcode":"4300",
    "addr:street":"Brisbane Tce",
    "iso:country":"AU",
    "sg:address":"Royal Mail Hotel 90 Brisbane Tce",
    "sg:city":"Goodna",
    "sg:classifiers":[
        {
            "category":"Food & Beverages",
            "subcategory":"Liquor & Beverages",
            "type":"Retail Goods"
        }
    ],
    "sg:phone":"+61 7 3288 2213",
    "sg:postcode":"4300",
    "sg:province":"QLD",
    "sg:tags":[
        "store"
    ],
    "wof:name":"Liquorwise",
    "wof:placetype":"venue"
},
  "geometry": {"coordinates":[152.89401245100001,-27.6006717682],"type":"Point"}
}