{
  "type": "Feature",
  "properties": {
    "addr:full":"Unit 3, 18 Price St Southport QLD 4215",
    "addr:housenumber":"18",
    "addr:postcode":"4215",
    "addr:street":"Price St",
    "iso:country":"AU",
    "sg:address":"Unit 3, 18 Price St",
    "sg:city":"Southport",
    "sg:classifiers":[
        {
            "category":"Manufacturing",
            "subcategory":"Tools & Machinery",
            "type":"Manufacturing & Wholesale Goods"
        }
    ],
    "sg:phone":"+61 7 5591 7455",
    "sg:postcode":"4215",
    "sg:province":"QLD",
    "sg:tags":[
        "crankshaft",
        "cylinder",
        "grinding"
    ],
    "wof:name":"John Wilson Engineering Pty Ltd",
    "wof:placetype":"venue"
},
  "geometry": {"coordinates":[153.40403747600001,-27.9662322998],"type":"Point"}
}