{
  "type": "Feature",
  "properties": {
    "addr:full":"4 Connolly St Webberton WA 6530",
    "addr:housenumber":"4",
    "addr:postcode":"6530",
    "addr:street":"Connolly St",
    "iso:country":"AU",
    "sg:address":"4 Connolly St",
    "sg:city":"Webberton",
    "sg:classifiers":[
        {
            "category":"Retail",
            "subcategory":"Auto Repair",
            "type":"Services"
        }
    ],
    "sg:phone":"+61 8 9964 2488",
    "sg:postcode":"6530",
    "sg:province":"WA",
    "sg:tags":[
        "recapping",
        "repairing",
        "retreading",
        "tyre"
    ],
    "wof:name":"Geraldton Secondhand Tyres",
    "wof:placetype":"venue"
},
  "geometry": {"coordinates":[114.629066467,-28.7489490509],"type":"Point"}
}