{
  "type": "Feature",
  "properties": {
    "addr:full":"14 Winchester Drv Nerang QLD 4211",
    "addr:housenumber":"14",
    "addr:postcode":"4211",
    "addr:street":"Winchester Drv",
    "iso:country":"AU",
    "sg:address":"14 Winchester Drv",
    "sg:city":"Nerang",
    "sg:classifiers":[
        {
            "category":"Home & Garden",
            "subcategory":"Carpets & Floor Coverings",
            "type":"Retail Goods"
        }
    ],
    "sg:phone":"+61 412 269 495",
    "sg:postcode":"4211",
    "sg:province":"QLD",
    "wof:name":"Down On All Floors",
    "wof:placetype":"venue"
},
  "geometry": {"coordinates":[153.31509399399999,-28.0034236908],"type":"Point"}
}