{
  "type": "Feature",
  "properties": {
    "addr:full":"260 Morayfield Rd Morayfield QLD 4506",
    "addr:housenumber":"260",
    "addr:postcode":"4506",
    "addr:street":"Morayfield Rd",
    "iso:country":"AU",
    "sg:address":"260 Morayfield Rd",
    "sg:city":"Morayfield",
    "sg:classifiers":[
        {
            "category":"Professional",
            "subcategory":"Engineering",
            "type":"Services"
        }
    ],
    "sg:phone":"+61 7 5497 9899",
    "sg:postcode":"4506",
    "sg:province":"QLD",
    "sg:tags":[
        "consulting",
        "engineer"
    ],
    "wof:name":"Hendriks/House Consulting Engineers",
    "wof:placetype":"venue"
},
  "geometry": {"coordinates":[152.95037841800001,-27.1116046906],"type":"Point"}
}