{
  "type": "Feature",
  "properties": {
    "addr:full":"45 Yale Drv Epping VIC 3076",
    "addr:housenumber":"45",
    "addr:postcode":"3076",
    "addr:street":"Yale Drv",
    "iso:country":"AU",
    "sg:address":"45 Yale Drv",
    "sg:city":"Epping",
    "sg:classifiers":[
        {
            "category":"Manufacturing",
            "subcategory":"Metals",
            "type":"Manufacturing & Wholesale Goods"
        }
    ],
    "sg:phone":"+61 3 9408 8933",
    "sg:postcode":"3076",
    "sg:province":"VIC",
    "sg:tags":[
        "sheet",
        "worker"
    ],
    "wof:name":"Garth Sheet Metal",
    "wof:placetype":"venue"
},
  "geometry": {"coordinates":[145.012115478,-37.646270752],"type":"Point"}
}