{
  "type": "Feature",
  "properties": {
    "iso:country":"AU",
    "sg:address":"Broadmeadow Rd",
    "sg:city":"Broadmeadow",
    "sg:classifiers":[
        {
            "category":"Recreation",
            "subcategory":"Fishing",
            "type":"Entertainment"
        }
    ],
    "sg:phone":"+61 2 4927 6627",
    "sg:postcode":"2292",
    "sg:province":"NSW",
    "sg:tags":[
        "bait"
    ],
    "wof:name":"Freddy's Fishing World",
    "wof:placetype":"venue"
},
  "geometry": {"coordinates":[151.73489379899999,-32.9210968018],"type":"Point"}
}