{
  "type": "Feature",
  "properties": {
    "addr:full":"4a Commercial Drv Dandenong VIC 3175",
    "addr:housenumber":"4a",
    "addr:postcode":"3175",
    "addr:street":"Commercial Drv",
    "iso:country":"AU",
    "sg:address":"4a Commercial Drv",
    "sg:city":"Dandenong",
    "sg:classifiers":[
        {
            "category":"Fast Food",
            "type":"Food & Drink"
        }
    ],
    "sg:phone":"+61 3 9768 3574",
    "sg:postcode":"3175",
    "sg:province":"VIC",
    "sg:tags":[
        "away",
        "take"
    ],
    "wof:name":"Dandy Diner",
    "wof:placetype":"venue"
},
  "geometry": {"coordinates":[145.227783203,-38.0277900696],"type":"Point"}
}