{
  "type": "Feature",
  "properties": {
    "addr:full":"123 Claisebrook St Perth WA 6000",
    "addr:housenumber":"123",
    "addr:postcode":"6000",
    "addr:street":"Claisebrook St",
    "iso:country":"AU",
    "sg:address":"123 Claisebrook St",
    "sg:city":"Perth",
    "sg:classifiers":[
        {
            "category":"Organizations",
            "subcategory":"Labor Organization",
            "type":"Services"
        }
    ],
    "sg:phone":"+61 1300 656 512",
    "sg:postcode":"6000",
    "sg:province":"WA",
    "sg:tags":[
        "union"
    ],
    "wof:name":"Media Entertainment & Arts Alliance",
    "wof:placetype":"venue"
},
  "geometry": {"coordinates":[115.87310791,-31.9478130341],"type":"Point"}
}