{
  "type": "Feature",
  "properties": {
    "addr:full":"48 Clarendon St Derby WA 6728",
    "addr:housenumber":"48",
    "addr:postcode":"6728",
    "addr:street":"Clarendon St",
    "iso:country":"AU",
    "sg:address":"48 Clarendon St",
    "sg:city":"Derby",
    "sg:classifiers":[
        {
            "category":"Communications",
            "subcategory":"Film & Video Production",
            "type":"Services"
        }
    ],
    "sg:phone":"+61 8 9193 1951",
    "sg:postcode":"6728",
    "sg:province":"WA",
    "sg:tags":[
        "dvd",
        "library"
    ],
    "wof:name":"Civic Video",
    "wof:placetype":"venue"
},
  "geometry": {"coordinates":[123.629707336,-17.3051681519],"type":"Point"}
}