{
  "type": "Feature",
  "properties": {
    "addr:full":"734 Albany Hwy East Victoria Park WA 6101",
    "addr:housenumber":"734",
    "addr:postcode":"6101",
    "addr:street":"Albany Hwy",
    "iso:country":"AU",
    "sg:address":"734 Albany Hwy",
    "sg:city":"East Victoria Park",
    "sg:classifiers":[
        {
            "category":"Health Services",
            "subcategory":"Doctor",
            "type":"Services"
        }
    ],
    "sg:phone":"+61 8 9473 7888",
    "sg:postcode":"6101",
    "sg:province":"WA",
    "sg:tags":[
        "medical",
        "practitioner"
    ],
    "wof:name":"Czajko Paul Dr",
    "wof:placetype":"venue"
},
  "geometry": {"coordinates":[115.90180206300001,-31.9823551178],"type":"Point"}
}