{
  "type": "Feature",
  "properties": {
    "addr:full":"94 Kooyong Rd Rivervale WA 6103",
    "addr:housenumber":"94",
    "addr:postcode":"6103",
    "addr:street":"Kooyong Rd",
    "iso:country":"AU",
    "sg:address":"94 Kooyong Rd",
    "sg:city":"Rivervale",
    "sg:classifiers":[
        {
            "category":"Health Services",
            "subcategory":"Doctor",
            "type":"Services"
        }
    ],
    "sg:phone":"+61 8 9361 7166",
    "sg:postcode":"6103",
    "sg:province":"WA",
    "sg:tags":[
        "medical",
        "practitioner"
    ],
    "wof:name":"Leong Y M Dr",
    "wof:placetype":"venue"
},
  "geometry": {"coordinates":[115.91397857699999,-31.9620094299],"type":"Point"}
}