{
  "type": "Feature",
  "properties": {
    "addr:full":"457 Canterbury Rd Vermont VIC 3133",
    "addr:housenumber":"457",
    "addr:postcode":"3133",
    "addr:street":"Canterbury Rd",
    "iso:country":"AU",
    "sg:address":"457 Canterbury Rd",
    "sg:city":"Vermont",
    "sg:classifiers":[
        {
            "category":"Manufacturing",
            "subcategory":"Aerospace",
            "type":"Manufacturing & Wholesale Goods"
        }
    ],
    "sg:phone":"+61 3 9872 3233",
    "sg:postcode":"3133",
    "sg:province":"VIC",
    "sg:tags":[
        "equipment",
        "aircraft",
        "maintenance"
    ],
    "wof:name":"Aircraft Tracking Avionics",
    "wof:placetype":"venue"
},
  "geometry": {"coordinates":[145.19392395,-37.8361434937],"type":"Point"}
}