{
  "type": "Feature",
  "properties": {
    "addr:full":"The Old Courthouse 37 Albert St Mordialloc VIC 3195",
    "addr:housenumber":"37",
    "addr:postcode":"3195",
    "addr:street":"Albert St",
    "iso:country":"AU",
    "sg:address":"The Old Courthouse 37 Albert St",
    "sg:city":"Mordialloc",
    "sg:classifiers":[
        {
            "category":"Education",
            "subcategory":"University",
            "type":"Public Place"
        }
    ],
    "sg:phone":"+61 3 9580 8328",
    "sg:postcode":"3195",
    "sg:province":"VIC",
    "sg:tags":[
        "educational",
        "organisation",
        "cultural"
    ],
    "wof:name":"Universities Of The Third Age (U3A) - Victorian Network",
    "wof:placetype":"venue"
},
  "geometry": {"coordinates":[145.08631897000001,-38.0040397644],"type":"Point"}
}