{
  "type": "Feature",
  "properties": {
    "iso:country":"AU",
    "sg:address":"Castle Pl",
    "sg:city":"Castle Hill",
    "sg:classifiers":[
        {
            "category":"Building & Trades",
            "subcategory":"Construction",
            "type":"Services"
        }
    ],
    "sg:phone":"+61 2 9894 6137",
    "sg:postcode":"2154",
    "sg:province":"NSW",
    "sg:tags":[
        "pool",
        "swimming"
    ],
    "wof:name":"Riviera Pools Spas & Renovations",
    "wof:placetype":"venue"
},
  "geometry": {"coordinates":[151.004562378,-33.7321662903],"type":"Point"}
}