{
  "type": "Feature",
  "properties": {
    "iso:country":"AU",
    "sg:address":"Level 1, 529 Pittwater Rd",
    "sg:city":"Brookvale",
    "sg:classifiers":[
        {
            "category":"Health Services",
            "subcategory":"Doctor",
            "type":"Services"
        }
    ],
    "sg:phone":"+61 2 9936 7900",
    "sg:postcode":"2100",
    "sg:province":"NSW",
    "sg:tags":[
        "nurse",
        "nursing"
    ],
    "wof:name":"Wesley Noakes Nursing Service",
    "wof:placetype":"venue"
},
  "geometry": {"coordinates":[151.27455139200001,-33.7611083984],"type":"Point"}
}