{
  "type": "Feature",
  "properties": {
    "addr:full":"1 Rowan St Croydon VIC 3136",
    "addr:housenumber":"1",
    "addr:postcode":"3136",
    "addr:street":"Rowan St",
    "iso:country":"AU",
    "sg:address":"1 Rowan St",
    "sg:city":"Croydon",
    "sg:classifiers":[
        {
            "category":"Building & Trades",
            "subcategory":"Construction",
            "type":"Services"
        }
    ],
    "sg:phone":"+61 3 9723 1318",
    "sg:postcode":"3136",
    "sg:province":"VIC",
    "sg:tags":[
        "fencing",
        "contractor"
    ],
    "wof:name":"Update Fencing",
    "wof:placetype":"venue"
},
  "geometry": {"coordinates":[145.285522461,-37.8067893982],"type":"Point"}
}