{
  "type": "Feature",
  "properties": {
    "iso:country":"AU",
    "sg:address":"Shp2/ 32 Gladstone Rd",
    "sg:city":"Dandenong",
    "sg:classifiers":[
        {
            "category":"Deli",
            "type":"Food & Drink"
        }
    ],
    "sg:phone":"+61 3 9794 9692",
    "sg:postcode":"3175",
    "sg:province":"VIC",
    "sg:tags":[
        "delicatessen"
    ],
    "wof:name":"Roma Deli",
    "wof:placetype":"venue"
},
  "geometry": {"coordinates":[145.20436096200001,-37.9715499878],"type":"Point"}
}