{
  "type": "Feature",
  "properties": {
    "addr:full":"Unit 4, 33 Jade Drv Nerang QLD 4211",
    "addr:housenumber":"33",
    "addr:postcode":"4211",
    "addr:street":"Jade Drv",
    "iso:country":"AU",
    "sg:address":"Unit 4, 33 Jade Drv",
    "sg:city":"Nerang",
    "sg:classifiers":[
        {
            "category":"Home & Garden",
            "subcategory":"Garden Supply",
            "type":"Retail Goods"
        }
    ],
    "sg:phone":"+61 7 5597 5882",
    "sg:postcode":"4211",
    "sg:province":"QLD",
    "sg:tags":[
        "statuary",
        "fountains",
        "sundial"
    ],
    "wof:name":"Techno Water Designs",
    "wof:placetype":"venue"
},
  "geometry": {"coordinates":[153.358932495,-27.9815044403],"type":"Point"}
}