{
  "type": "Feature",
  "properties": {
    "iso:country":"AU",
    "sg:address":"114 Molonglo St",
    "sg:city":"Bungendore",
    "sg:classifiers":[
        {
            "category":"Home & Garden",
            "subcategory":"Building Materials",
            "type":"Retail Goods"
        }
    ],
    "sg:phone":"+61 2 6238 1517",
    "sg:postcode":"2621",
    "sg:province":"NSW",
    "sg:tags":[
        "fencing"
    ],
    "wof:name":"Bungendore Rural Services",
    "wof:placetype":"venue"
},
  "geometry": {"coordinates":[149.43841552699999,-35.2538909912],"type":"Point"}
}