{
  "type": "Feature",
  "properties": {
    "addr:full":"18 Beckett Rd Donvale VIC 3111",
    "addr:housenumber":"18",
    "addr:postcode":"3111",
    "addr:street":"Beckett Rd",
    "iso:country":"AU",
    "sg:address":"18 Beckett Rd",
    "sg:city":"Donvale",
    "sg:classifiers":[
        {
            "category":"Professional",
            "subcategory":"Secretarial Services",
            "type":"Services"
        }
    ],
    "sg:phone":"+61 3 9874 2924",
    "sg:postcode":"3111",
    "sg:province":"VIC",
    "sg:tags":[
        "typing"
    ],
    "wof:name":"Impact Secretarial Solutions",
    "wof:placetype":"venue"
},
  "geometry": {"coordinates":[145.20750427199999,-37.7980537415],"type":"Point"}
}