{
  "type": "Feature",
  "properties": {
    "addr:full":"14 Kitawah St Lonsdale SA 5160",
    "addr:housenumber":"14",
    "addr:postcode":"5160",
    "addr:street":"Kitawah St",
    "iso:country":"AU",
    "sg:address":"14 Kitawah St",
    "sg:city":"Lonsdale",
    "sg:classifiers":[
        {
            "category":"Personal",
            "subcategory":"Sauna",
            "type":"Services"
        }
    ],
    "sg:phone":"+61 8 8326 8166",
    "sg:postcode":"5160",
    "sg:province":"SA",
    "sg:tags":[
        "equipment",
        "accessory"
    ],
    "sg:website":"http://www.thesaunaking.com.au",
    "wof:name":"The Sauna King",
    "wof:placetype":"venue"
},
  "geometry": {"coordinates":[138.499267578,-35.1097221375],"type":"Point"}
}