{
  "type": "Feature",
  "properties": {
    "iso:country":"AU",
    "sg:address":"26- 32 Akubra Pl",
    "sg:city":"Kempsey",
    "sg:classifiers":[
        {
            "category":"Professional",
            "subcategory":"Engineering",
            "type":"Services"
        }
    ],
    "sg:phone":"+61 2 6562 7644",
    "sg:postcode":"2440",
    "sg:province":"NSW",
    "sg:tags":[
        "manufacturing",
        "engineer"
    ],
    "wof:name":"Hand H.F. Constructors Pty. Ltd.",
    "wof:placetype":"venue"
},
  "geometry": {"coordinates":[152.8237,-31.097641],"type":"Point"}
}