{
  "type": "Feature",
  "properties": {
    "iso:country":"AU",
    "sg:address":"Unit 3/ 16 Benambra St",
    "sg:city":"Preston West",
    "sg:classifiers":[
        {
            "category":"Building & Trades",
            "subcategory":"Construction",
            "type":"Services"
        }
    ],
    "sg:phone":"+61 419 899 214",
    "sg:postcode":"3072",
    "sg:province":"VIC",
    "sg:tags":[
        "roof"
    ],
    "wof:name":"Reservoir Roofing Pty Ltd",
    "wof:placetype":"venue"
},
  "geometry": {"coordinates":[144.98883056599999,-37.7331809998],"type":"Point"}
}