{
  "type": "Feature",
  "properties": {
    "iso:country":"AU",
    "sg:address":"395 Middleborough Rd",
    "sg:city":"Box Hill",
    "sg:classifiers":[
        {
            "category":"Retail",
            "subcategory":"Funeral Services",
            "type":"Services"
        }
    ],
    "sg:phone":"+61 3 9890 1229",
    "sg:postcode":"3128",
    "sg:province":"VIC",
    "sg:tags":[
        "cemetery"
    ],
    "wof:name":"Box Hill Cemetery",
    "wof:placetype":"venue"
},
  "geometry": {"coordinates":[145.138061523,-37.8205070496],"type":"Point"}
}