{
  "type": "Feature",
  "properties": {
    "iso:country":"AU",
    "sg:address":"727 Burwood Rd",
    "sg:city":"Hawthorn",
    "sg:classifiers":[
        {
            "category":"Home & Garden",
            "subcategory":"Furniture",
            "type":"Retail Goods"
        }
    ],
    "sg:phone":"+61 3 9882 1293",
    "sg:postcode":"3122",
    "sg:province":"VIC",
    "sg:tags":[
        "repair",
        "restoration"
    ],
    "wof:name":"Bull A W",
    "wof:placetype":"venue"
},
  "geometry": {"coordinates":[145.048065186,-37.8239517212],"type":"Point"}
}