{
  "type": "Feature",
  "properties": {
    "iso:country":"AU",
    "sg:address":"69 Henderson St",
    "sg:city":"Camp Hill",
    "sg:classifiers":[
        {
            "category":"Professional",
            "subcategory":"Accounting & Tax Preparation",
            "type":"Services"
        }
    ],
    "sg:phone":"+61 7 3843 3444",
    "sg:postcode":"4152",
    "sg:province":"QLD",
    "sg:tags":[
        "consultant",
        "taxation"
    ],
    "wof:name":"Denene S Cashin",
    "wof:placetype":"venue"
},
  "geometry": {"coordinates":[153.07699585,-27.4901828766],"type":"Point"}
}