{
  "type": "Feature",
  "properties": {
    "addr:full":"Headlands Ave Austinmer NSW 2515",
    "addr:postcode":"2515",
    "addr:street":"Headlands Ave",
    "iso:country":"AU",
    "sg:address":"Headlands Ave",
    "sg:city":"Austinmer",
    "sg:classifiers":[
        {
            "category":"Travel",
            "subcategory":"Hotels & Motels",
            "type":"Entertainment"
        }
    ],
    "sg:phone":"+61 2 4267 1146",
    "sg:postcode":"2515",
    "sg:province":"NSW",
    "sg:tags":[
        "accommodation"
    ],
    "wof:name":"Headlands Hotel",
    "wof:placetype":"venue"
},
  "geometry": {"coordinates":[150.93800400000001,-34.300598],"type":"Point"}
}