{
  "type": "Feature",
  "properties": {
    "addr:full":"2 Sonia St Carrum Downs VIC 3201",
    "addr:housenumber":"2",
    "addr:postcode":"3201",
    "addr:street":"Sonia St",
    "iso:country":"AU",
    "sg:address":"2 Sonia St",
    "sg:city":"Carrum Downs",
    "sg:classifiers":[
        {
            "category":"Professional",
            "subcategory":"Research",
            "type":"Services"
        }
    ],
    "sg:phone":"+61 3 9770 3150",
    "sg:postcode":"3201",
    "sg:province":"VIC",
    "sg:tags":[
        "industrial",
        "scientific"
    ],
    "wof:name":"Libwil Technology",
    "wof:placetype":"venue"
},
  "geometry": {"coordinates":[145.16154499999999,-38.097786],"type":"Point"}
}