{
  "type": "Feature",
  "properties": {
    "addr:full":"65 Guthrie St Osborne Park WA 6017",
    "addr:housenumber":"65",
    "addr:postcode":"6017",
    "addr:street":"Guthrie St",
    "iso:country":"AU",
    "sg:address":"65 Guthrie St",
    "sg:city":"Osborne Park",
    "sg:classifiers":[
        {
            "category":"Shopping",
            "subcategory":"Stationery & Office Supplies",
            "type":"Retail Goods"
        }
    ],
    "sg:phone":"+61 8 9244 2233",
    "sg:postcode":"6017",
    "sg:province":"WA",
    "sg:tags":[
        "equipment",
        "display",
        "exhibition"
    ],
    "sg:website":"http://www.toucan.com.au",
    "wof:name":"Toucan Display Systems",
    "wof:placetype":"venue"
},
  "geometry": {"coordinates":[115.815338135,-31.9053859711],"type":"Point"}
}