{
  "type": "Feature",
  "properties": {
    "addr:full":"18 Strickland St Spalding WA 6530",
    "addr:housenumber":"18",
    "addr:postcode":"6530",
    "addr:street":"Strickland St",
    "iso:country":"AU",
    "sg:address":"18 Strickland St",
    "sg:city":"Spalding",
    "sg:classifiers":[
        {
            "category":"Home & Garden",
            "subcategory":"Household Appliances",
            "type":"Retail Goods"
        }
    ],
    "sg:phone":"+61 8 9923 1947",
    "sg:postcode":"6530",
    "sg:province":"WA",
    "sg:tags":[
        "equipment",
        "gas"
    ],
    "wof:name":"Hadley CW & PM",
    "wof:placetype":"venue"
},
  "geometry": {"coordinates":[114.62541198700001,-28.74036026],"type":"Point"}
}