{
  "type": "Feature",
  "properties": {
    "addr:full":"136 Bennett St East Perth WA 6004",
    "addr:housenumber":"136",
    "addr:postcode":"6004",
    "addr:street":"Bennett St East",
    "iso:country":"AU",
    "sg:address":"136 Bennett St",
    "sg:city":"East Perth",
    "sg:classifiers":[
        {
            "category":"Education",
            "subcategory":"Music School",
            "type":"Public Place"
        }
    ],
    "sg:phone":"+61 8 9325 5653",
    "sg:postcode":"6004",
    "sg:province":"WA",
    "sg:tags":[
        "singing",
        "teacher"
    ],
    "wof:name":"Shirley Flesfader Singing Studio",
    "wof:placetype":"venue"
},
  "geometry": {"coordinates":[115.87361145,-31.9549045563],"type":"Point"}
}