{
  "type": "Feature",
  "properties": {
    "addr:full":"PO Box 776 Kyogle NSW 2474",
    "addr:postcode":"2474",
    "iso:country":"AU",
    "sg:address":"PO Box 776",
    "sg:city":"Kyogle",
    "sg:classifiers":[
        {
            "category":"Insurance",
            "subcategory":"Life Insurance",
            "type":"Services"
        }
    ],
    "sg:phone":"+61 2 6689 7335",
    "sg:postcode":"2474",
    "sg:province":"NSW",
    "wof:name":"Keevers Phil",
    "wof:placetype":"venue"
},
  "geometry": {"coordinates":[153.00375366200001,-28.6239795685],"type":"Point"}
}