{
  "type": "Feature",
  "properties": {
    "iso:country":"AU",
    "sg:address":"PO Box 1357",
    "sg:city":"Castle Hill",
    "sg:classifiers":[
        {
            "category":"Banks & Credit Unions",
            "subcategory":"Bank",
            "type":"Services"
        }
    ],
    "sg:phone":"+61 2 9634 1837",
    "sg:postcode":"1765",
    "sg:province":"NSW",
    "sg:tags":[
        "broker",
        "mortgage"
    ],
    "wof:name":"The North West Home Loan Company",
    "wof:placetype":"venue"
},
  "geometry": {"coordinates":[151.01724200000001,-33.730858],"type":"Point"}
}