{
  "type": "Feature",
  "properties": {
    "addr:full":"9 Spence Pl Leeming WA 6149",
    "addr:housenumber":"9",
    "addr:postcode":"6149",
    "addr:street":"Spence Pl",
    "iso:country":"AU",
    "sg:address":"9 Spence Pl",
    "sg:city":"Leeming",
    "sg:classifiers":[
        {
            "category":"Organizations",
            "subcategory":"Non-profit Organization",
            "type":"Services"
        }
    ],
    "sg:phone":"+61 8 9249 3218",
    "sg:postcode":"6149",
    "sg:province":"WA",
    "sg:tags":[
        "support",
        "disability",
        "organisation"
    ],
    "wof:name":"Cleft Lip & Palate Society of Western Australia",
    "wof:placetype":"venue"
},
  "geometry": {"coordinates":[115.865623,-32.067944],"type":"Point"}
}