{
  "type": "Feature",
  "properties": {
    "addr:full":"186 Abbotsford Rd Bowen Hills QLD 4006",
    "addr:housenumber":"186",
    "addr:postcode":"4006",
    "addr:street":"Abbotsford Rd",
    "iso:country":"AU",
    "sg:address":"186 Abbotsford Rd",
    "sg:city":"Bowen Hills",
    "sg:classifiers":[
        {
            "category":"Retail",
            "subcategory":"Auto Repair",
            "type":"Services"
        }
    ],
    "sg:phone":"+61 7 3852 1811",
    "sg:postcode":"4006",
    "sg:province":"QLD",
    "sg:tags":[
        "beater",
        "painter",
        "panel"
    ],
    "wof:name":"Bowen Hills Smash Repairs",
    "wof:placetype":"venue"
},
  "geometry": {"coordinates":[153.04086303700001,-27.4373989105],"type":"Point"}
}