{
  "type": "Feature",
  "properties": {
    "iso:country":"AU",
    "sg:address":"Cnr Martin & White St",
    "sg:city":"Nerang",
    "sg:classifiers":[
        {
            "category":"Education",
            "subcategory":"School",
            "type":"Public Place"
        }
    ],
    "sg:phone":"+61 7 5578 1866",
    "sg:postcode":"4211",
    "sg:province":"QLD",
    "sg:tags":[
        "state",
        "except",
        "nsw"
    ],
    "wof:name":"Nerang Pre School",
    "wof:placetype":"venue"
},
  "geometry": {"coordinates":[153.33453369099999,-27.9910869598],"type":"Point"}
}