{
  "type": "Feature",
  "properties": {
    "iso:country":"AU",
    "sg:address":"16 Oxford St",
    "sg:city":"Woollahra",
    "sg:classifiers":[
        {
            "category":"Health Services",
            "subcategory":"Doctor",
            "type":"Services"
        }
    ],
    "sg:phone":"+61 2 9360 4712",
    "sg:postcode":"2025",
    "sg:province":"NSW",
    "sg:tags":[
        "medical",
        "practitioner"
    ],
    "wof:name":"Matthew Jane E",
    "wof:placetype":"venue"
},
  "geometry": {"coordinates":[151.23243713400001,-33.8887138367],"type":"Point"}
}