{
  "type": "Feature",
  "properties": {
    "iso:country":"AU",
    "sg:address":"PO Box 85",
    "sg:city":"Rainbow Beach",
    "sg:classifiers":[
        {
            "category":"Building & Trades",
            "subcategory":"Cleaning & Sanitation",
            "type":"Services"
        }
    ],
    "sg:phone":"+61 7 5486 3387",
    "sg:postcode":"4581",
    "sg:province":"QLD",
    "sg:tags":[
        "cleaner",
        "repairer",
        "roof"
    ],
    "wof:name":"Cooloola Roofing Pty Ltd",
    "wof:placetype":"venue"
},
  "geometry": {"coordinates":[153.09068298299999,-25.9046707153],"type":"Point"}
}