{
  "type": "Feature",
  "properties": {
    "iso:country":"AU",
    "sg:address":"35 Edward St",
    "sg:city":"Brunswick",
    "sg:classifiers":[
        {
            "category":"Professional",
            "subcategory":"Detective & Security Services",
            "type":"Services"
        }
    ],
    "sg:phone":"+61 3 9387 4122",
    "sg:postcode":"3055",
    "sg:province":"VIC",
    "sg:tags":[
        "equipment",
        "window",
        "doors"
    ],
    "wof:name":"Canon Doors & Shower Screens Centre",
    "wof:placetype":"venue"
},
  "geometry": {"coordinates":[144.97125244099999,-37.7689094543],"type":"Point"}
}