{
  "type": "Feature",
  "properties": {
    "addr:full":"Unit 1, 5 Rowe St Malaga WA 6090",
    "addr:housenumber":"5",
    "addr:postcode":"6090",
    "addr:street":"Rowe St",
    "iso:country":"AU",
    "sg:address":"Unit 1, 5 Rowe St",
    "sg:city":"Malaga",
    "sg:classifiers":[
        {
            "category":"Building & Trades",
            "subcategory":"Locksmith",
            "type":"Services"
        }
    ],
    "sg:phone":"+61 8 9248 2200",
    "sg:postcode":"6090",
    "sg:province":"WA",
    "sg:tags":[
        "lock"
    ],
    "wof:name":"Absolute Security",
    "wof:placetype":"venue"
},
  "geometry": {"coordinates":[115.890052795,-31.8570556641],"type":"Point"}
}