{
  "type": "Feature",
  "properties": {
    "iso:country":"AU",
    "sg:address":"1121 Riverway Drv",
    "sg:city":"Rasmussen",
    "sg:classifiers":[
        {
            "category":"Education",
            "subcategory":"Kindergarten",
            "type":"Public Place"
        }
    ],
    "sg:phone":"+61 7 4789 1511",
    "sg:postcode":"4815",
    "sg:province":"QLD",
    "sg:tags":[
        "pre-schools"
    ],
    "wof:name":"Captain Teddys Kindy & Early Education Centre",
    "wof:placetype":"venue"
},
  "geometry": {"coordinates":[146.728714,-19.345501],"type":"Point"}
}