{
  "type": "Feature",
  "properties": {
    "iso:country":"AU",
    "sg:address":"64 Enterprise St",
    "sg:city":"Kunda Park",
    "sg:classifiers":[
        {
            "category":"Home & Garden",
            "subcategory":"Building Materials",
            "type":"Retail Goods"
        }
    ],
    "sg:phone":"+61 7 5445 8477",
    "sg:postcode":"4556",
    "sg:province":"QLD",
    "sg:tags":[
        "roofing"
    ],
    "wof:name":"Stoddart Building Products",
    "wof:placetype":"venue"
},
  "geometry": {"coordinates":[153.02987670900001,-26.6665344238],"type":"Point"}
}