{
  "type": "Feature",
  "properties": {
    "addr:full":"30 Russell Crs Westleigh NSW 2120",
    "addr:housenumber":"30",
    "addr:postcode":"2120",
    "addr:street":"Russell Crs",
    "iso:country":"AU",
    "sg:address":"30 Russell Crs",
    "sg:city":"Westleigh",
    "sg:classifiers":[
        {
            "category":"Professional",
            "subcategory":"Computer Services",
            "type":"Services"
        }
    ],
    "sg:phone":"+61 2 9875 3713",
    "sg:postcode":"2120",
    "sg:province":"NSW",
    "sg:tags":[
        "consultant",
        "system"
    ],
    "wof:name":"Decorpalm Pty Ltd",
    "wof:placetype":"venue"
},
  "geometry": {"coordinates":[151.06840515100001,-33.7193603516],"type":"Point"}
}