{
  "type": "Feature",
  "properties": {
    "iso:country":"AU",
    "sg:address":"93 Darby St",
    "sg:city":"Cooks Hill",
    "sg:classifiers":[
        {
            "category":"Real Estate",
            "subcategory":"Developer",
            "type":"Services"
        }
    ],
    "sg:phone":"+61 2 4926 1188",
    "sg:postcode":"2300",
    "sg:province":"NSW",
    "sg:tags":[
        "development"
    ],
    "wof:name":"Solid Property Services",
    "wof:placetype":"venue"
},
  "geometry": {"coordinates":[151.768539,-32.934696],"type":"Point"}
}