{
  "type": "Feature",
  "properties": {
    "iso:country":"AU",
    "sg:address":"Unit 14A/ 64 Bannister Rd",
    "sg:city":"Canning Vale",
    "sg:classifiers":[
        {
            "category":"Professional",
            "subcategory":"Detective & Security Services",
            "type":"Services"
        }
    ],
    "sg:phone":"+61 8 9456 5122",
    "sg:postcode":"6155",
    "sg:province":"WA",
    "sg:tags":[
        "consultant",
        "system"
    ],
    "wof:name":"Advancetag",
    "wof:placetype":"venue"
},
  "geometry": {"coordinates":[115.92614,-32.063076],"type":"Point"}
}