{
  "type": "Feature",
  "properties": {
    "addr:full":"Unit 14A/ 64 Bannister Rd Canning Vale WA 6155",
    "addr:housenumber":"unit 14a / 64",
    "addr:postcode":"6155",
    "addr:street":"Bannister Rd",
    "iso:country":"AU",
    "sg:address":"Unit 14A/ 64 Bannister Rd",
    "sg:city":"Canning Vale",
    "sg:classifiers":[
        {
            "category":"Professional",
            "subcategory":"Detective & Security Services",
            "type":"Services"
        }
    ],
    "sg:phone":"+61 8 9456 5122",
    "sg:postcode":"6155",
    "sg:province":"WA",
    "sg:tags":[
        "consultant",
        "system"
    ],
    "wof:name":"Advancetag",
    "wof:placetype":"venue"
},
  "geometry": {"coordinates":[115.92614,-32.063076],"type":"Point"}
}