{
  "type": "Feature",
  "properties": {
    "addr:full":"10 Glasgow St St Andrews NSW 2566",
    "addr:housenumber":"10",
    "addr:postcode":"2566",
    "addr:street":"Glasgow St",
    "iso:country":"AU",
    "sg:address":"10 Glasgow St St",
    "sg:city":"Andrews",
    "sg:classifiers":[
        {
            "category":"Government",
            "subcategory":"Court House",
            "type":"Public Place"
        }
    ],
    "sg:phone":"+61 2 9603 6369",
    "sg:postcode":"2566",
    "sg:province":"NSW",
    "sg:tags":[
        "personal",
        "marriage",
        "family",
        "counselling"
    ],
    "wof:name":"Confidence Through Counselling",
    "wof:placetype":"venue"
},
  "geometry": {"coordinates":[150.83340454099999,-34.016494751],"type":"Point"}
}