{
  "type": "Feature",
  "properties": {
    "addr:full":"169 Alexander Drv Mission Beach QLD 4852",
    "addr:housenumber":"169",
    "addr:postcode":"4852",
    "addr:street":"Alexander Drv",
    "iso:country":"AU",
    "sg:address":"169 Alexander Drv",
    "sg:city":"Mission Beach",
    "sg:classifiers":[
        {
            "category":"Manufacturing",
            "subcategory":"Petroleum Products",
            "type":"Manufacturing & Wholesale Goods"
        }
    ],
    "sg:phone":"+61 7 4068 7633",
    "sg:postcode":"4852",
    "sg:province":"QLD",
    "sg:tags":[
        "lubricant"
    ],
    "wof:name":"Mako Technologies Australia",
    "wof:placetype":"venue"
},
  "geometry": {"coordinates":[146.10023498499999,-17.8292446136],"type":"Point"}
}