{
  "type": "Feature",
  "properties": {
    "addr:full":"Ste 2/13- 17 Gymea Bay Rd Gymea NSW 2227",
    "addr:housenumber":"17",
    "addr:postcode":"2227",
    "addr:street":"Gymea Bay Rd",
    "iso:country":"AU",
    "sg:address":"Ste 2/13- 17 Gymea Bay Rd",
    "sg:city":"Gymea",
    "sg:classifiers":[
        {
            "category":"Health Services",
            "subcategory":"Health Practitioner",
            "type":"Services"
        }
    ],
    "sg:phone":"+61 2 9525 6979",
    "sg:postcode":"2227",
    "sg:province":"NSW",
    "sg:tags":[
        "physiotherapist"
    ],
    "wof:name":"Morgan G J & C M",
    "wof:placetype":"venue"
},
  "geometry": {"coordinates":[151.08514404300001,-34.0336151123],"type":"Point"}
}