{
  "type": "Feature",
  "properties": {
    "addr:full":"14 Wangara Rd Sandringham VIC 3191",
    "addr:housenumber":"14",
    "addr:postcode":"3191",
    "addr:street":"Wangara Rd",
    "iso:country":"AU",
    "sg:address":"14 Wangara Rd",
    "sg:city":"Sandringham",
    "sg:classifiers":[
        {
            "category":"Manufacturing",
            "subcategory":"Apparel",
            "type":"Manufacturing & Wholesale Goods"
        }
    ],
    "sg:phone":"+61 3 9533 5556",
    "sg:postcode":"3191",
    "sg:province":"VIC",
    "sg:tags":[
        "makers-up",
        "clothing"
    ],
    "wof:name":"Streetwize Clothing",
    "wof:placetype":"venue"
},
  "geometry": {"coordinates":[145.030227661,-37.9576377869],"type":"Point"}
}