{
  "type": "Feature",
  "properties": {
    "iso:country":"AU",
    "sg:address":"106 Sunnyholt Rd",
    "sg:city":"Blacktown",
    "sg:classifiers":[
        {
            "category":"Autos & Motor Vehicles",
            "subcategory":"Automobile Sales",
            "type":"Retail Goods"
        }
    ],
    "sg:phone":"+61 2 8811 6100",
    "sg:postcode":"2148",
    "sg:province":"NSW",
    "sg:tags":[
        "car",
        "new"
    ],
    "wof:name":"West End Motor Group Pty Ltd",
    "wof:placetype":"venue"
},
  "geometry": {"coordinates":[150.91429138199999,-33.757434845],"type":"Point"}
}