{
  "type": "Feature",
  "properties": {
    "addr:full":"Factory 2/ 4 Ovata Drv Tullamarine VIC 3043",
    "addr:housenumber":"/ 4",
    "addr:postcode":"3043",
    "addr:street":"Ovata Drv",
    "iso:country":"AU",
    "sg:address":"Factory 2/ 4 Ovata Drv",
    "sg:city":"Tullamarine",
    "sg:classifiers":[
        {
            "category":"Building & Trades",
            "subcategory":"Construction",
            "type":"Services"
        }
    ],
    "sg:phone":"+61 419 368 987",
    "sg:postcode":"3043",
    "sg:province":"VIC",
    "sg:tags":[
        "contractor"
    ],
    "wof:name":"Creative Constructions & Shopfitting P/L",
    "wof:placetype":"venue"
},
  "geometry": {"coordinates":[144.865722656,-37.7117385864],"type":"Point"}
}