{
  "type": "Feature",
  "properties": {
    "addr:full":"97 Coghlan Rd Subiaco WA 6008",
    "addr:housenumber":"97",
    "addr:postcode":"6008",
    "addr:street":"Coghlan Rd",
    "iso:country":"AU",
    "sg:address":"97 Coghlan Rd",
    "sg:city":"Subiaco",
    "sg:classifiers":[
        {
            "category":"Professional",
            "subcategory":"Research",
            "type":"Services"
        }
    ],
    "sg:phone":"+61 8 9382 4620",
    "sg:postcode":"6008",
    "sg:province":"WA",
    "sg:tags":[
        "actuary"
    ],
    "wof:name":"Brett John",
    "wof:placetype":"venue"
},
  "geometry": {"coordinates":[115.83280944800001,-31.9489154816],"type":"Point"}
}