{
  "type": "Feature",
  "properties": {
    "iso:country":"AU",
    "sg:address":"Cnr Jacobs Drv & Neilson Rd",
    "sg:city":"Sussex Inlet",
    "sg:classifiers":[
        {
            "category":"Social Services",
            "subcategory":"Child Care",
            "type":"Services"
        }
    ],
    "sg:phone":"+61 2 4441 2373",
    "sg:postcode":"2540",
    "sg:province":"NSW",
    "sg:tags":[
        "support",
        "health"
    ],
    "wof:name":"Early Childhood Centres",
    "wof:placetype":"venue"
},
  "geometry": {"coordinates":[150.49911499000001,-35.1127586365],"type":"Point"}
}