{
  "type": "Feature",
  "properties": {
    "addr:full":"St Helens Medical Centre St Helens TAS 7216",
    "addr:postcode":"7216",
    "iso:country":"AU",
    "sg:address":"St Helens Medical Centre",
    "sg:city":"St Helens",
    "sg:classifiers":[
        {
            "category":"Health Services",
            "subcategory":"Optometrist",
            "type":"Services"
        }
    ],
    "sg:phone":"+61 3 6376 1374",
    "sg:postcode":"7216",
    "sg:province":"TAS",
    "wof:name":"Dennis Gregory",
    "wof:placetype":"venue"
},
  "geometry": {"coordinates":[148.23994400000001,-41.316879],"type":"Point"}
}