{
  "type": "Feature",
  "properties": {
    "addr:full":"Ground Floor, 21 Keane St Midland WA 6056",
    "addr:housenumber":"21",
    "addr:postcode":"6056",
    "addr:street":"Keane St",
    "iso:country":"AU",
    "sg:address":"Ground Floor, 21 Keane St",
    "sg:city":"Midland",
    "sg:classifiers":[
        {
            "category":"Professional",
            "subcategory":"Employment Agencies",
            "type":"Services"
        }
    ],
    "sg:phone":"+61 8 9250 2455",
    "sg:postcode":"6056",
    "sg:province":"WA",
    "wof:name":"PVS Workfind",
    "wof:placetype":"venue"
},
  "geometry": {"coordinates":[116.005432129,-31.886554718],"type":"Point"}
}