{
  "type": "Feature",
  "properties": {
    "iso:country":"AU",
    "sg:address":"Lot 8, 112 The Esplanade",
    "sg:city":"Burleigh Heads",
    "sg:classifiers":[
        {
            "category":"Professional",
            "subcategory":"Computer Services",
            "type":"Services"
        }
    ],
    "sg:phone":"+61 7 3102 9523",
    "sg:postcode":"4220",
    "sg:province":"QLD",
    "sg:tags":[
        "consultant",
        "system"
    ],
    "wof:name":"Australian Pacific Computers Pty Ltd",
    "wof:placetype":"venue"
},
  "geometry": {"coordinates":[153.44915771500001,-28.0829563141],"type":"Point"}
}