{
  "type": "Feature",
  "properties": {
    "addr:full":"3rd Floor, 3 Wellington St St Kilda VIC 3182",
    "addr:housenumber":"3",
    "addr:postcode":"3182",
    "addr:street":"Wellington St",
    "iso:country":"AU",
    "sg:address":"3rd Floor, 3 Wellington St St",
    "sg:city":"Kilda",
    "sg:classifiers":[
        {
            "category":"Professional",
            "subcategory":"Employment Agencies",
            "type":"Services"
        }
    ],
    "sg:phone":"+61 1300 477 324",
    "sg:postcode":"3182",
    "sg:province":"VIC",
    "wof:name":"Precision Recruitment",
    "wof:placetype":"venue"
},
  "geometry": {"coordinates":[144.98326110799999,-37.8560829163],"type":"Point"}
}