{
  "type": "Feature",
  "properties": {
    "addr:full":"35 Camooweal St Mt Isa QLD 4825",
    "addr:housenumber":"35",
    "addr:postcode":"4825",
    "addr:street":"Camooweal St",
    "iso:country":"AU",
    "sg:address":"35 Camooweal St",
    "sg:city":"Mt Isa",
    "sg:classifiers":[
        {
            "category":"Wholesale",
            "subcategory":"Machinery & Supplies",
            "type":"Manufacturing & Wholesale Goods"
        }
    ],
    "sg:phone":"+61 7 4743 2977",
    "sg:postcode":"4825",
    "sg:province":"QLD",
    "sg:tags":[
        "engineer"
    ],
    "wof:name":"Atkins Industrial",
    "wof:placetype":"venue"
},
  "geometry": {"coordinates":[139.492142,-20.73156],"type":"Point"}
}