{
  "type": "Feature",
  "properties": {
    "addr:full":"Ferny Ave Surfers Paradise QLD 4217",
    "addr:postcode":"4217",
    "addr:street":"Ferny Ave",
    "iso:country":"AU",
    "sg:address":"Ferny Ave",
    "sg:city":"Surfers Paradise",
    "sg:classifiers":[
        {
            "category":"Recreation",
            "subcategory":"Boat Charter",
            "type":"Entertainment"
        }
    ],
    "sg:phone":"+61 7 5531 6176",
    "sg:postcode":"4217",
    "sg:province":"QLD",
    "sg:tags":[
        "hire",
        "drive"
    ],
    "wof:name":"Captain Barb-E Boat Hire",
    "wof:placetype":"venue"
},
  "geometry": {"coordinates":[153.426437378,-28.0017776489],"type":"Point"}
}