{
  "type": "Feature",
  "properties": {
    "addr:full":"PO Box 822 Warana QLD 4575",
    "addr:postcode":"4575",
    "iso:country":"AU",
    "sg:address":"PO Box 822",
    "sg:city":"Warana",
    "sg:classifiers":[
        {
            "category":"Professional",
            "type":"Services"
        }
    ],
    "sg:phone":"+61 7 5493 2046",
    "sg:postcode":"4575",
    "sg:province":"QLD",
    "sg:tags":[
        "courier"
    ],
    "wof:name":"Nicks Transport",
    "wof:placetype":"venue"
},
  "geometry": {"coordinates":[153.13076799999999,-26.719839],"type":"Point"}
}