{
  "type": "Feature",
  "properties": {
    "iso:country":"AU",
    "sg:address":"6B Robert St",
    "sg:city":"Atherton",
    "sg:classifiers":[
        {
            "category":"Professional",
            "subcategory":"Printing & Photocopies",
            "type":"Services"
        }
    ],
    "sg:phone":"+61 7 4091 3260",
    "sg:postcode":"4883",
    "sg:province":"QLD",
    "sg:tags":[
        "trophy"
    ],
    "wof:name":"Atherton Trophies & Engraving",
    "wof:placetype":"venue"
},
  "geometry": {"coordinates":[145.47535705600001,-17.2549953461],"type":"Point"}
}