{
  "type": "Feature",
  "properties": {
    "addr:full":"20 Tamborine St Jimboomba QLD 4280",
    "addr:housenumber":"20",
    "addr:postcode":"4280",
    "addr:street":"Tamborine St",
    "iso:country":"AU",
    "sg:address":"20 Tamborine St",
    "sg:city":"Jimboomba",
    "sg:classifiers":[
        {
            "category":"Utilities",
            "subcategory":"Sewage",
            "type":"Services"
        }
    ],
    "sg:phone":"+61 7 5546 0293",
    "sg:postcode":"4280",
    "sg:province":"QLD",
    "sg:tags":[
        "water",
        "waste",
        "treatment"
    ],
    "wof:name":"AAA Superior Sewage Treatment",
    "wof:placetype":"venue"
},
  "geometry": {"coordinates":[153.030777,-27.821968],"type":"Point"}
}