{
  "type": "Feature",
  "properties": {
    "addr:full":"52 Park Ave Caves Beach NSW 2281",
    "addr:housenumber":"52",
    "addr:postcode":"2281",
    "addr:street":"Park Ave",
    "iso:country":"AU",
    "sg:address":"52 Park Ave",
    "sg:city":"Caves Beach",
    "sg:classifiers":[
        {
            "category":"Education",
            "subcategory":"Kindergarten",
            "type":"Public Place"
        }
    ],
    "sg:phone":"+61 2 4971 3258",
    "sg:postcode":"2281",
    "sg:province":"NSW",
    "sg:tags":[
        "pre-schools"
    ],
    "wof:name":"Caves Beach Uniting Pre-School",
    "wof:placetype":"venue"
},
  "geometry": {"coordinates":[151.64073181099999,-33.1066246033],"type":"Point"}
}