{
  "type": "Feature",
  "properties": {
    "iso:country":"AU",
    "sg:address":"47 Fox St",
    "sg:city":"Strathpine",
    "sg:classifiers":[
        {
            "category":"Education",
            "subcategory":"Music School",
            "type":"Public Place"
        }
    ],
    "sg:phone":"+61 7 3205 4979",
    "sg:postcode":"4500",
    "sg:province":"QLD",
    "sg:tags":[
        "teacher"
    ],
    "wof:name":"Lorraines Music",
    "wof:placetype":"venue"
},
  "geometry": {"coordinates":[152.995697022,-27.2974433899],"type":"Point"}
}