{
  "type": "Feature",
  "properties": {
    "addr:full":"46 High St Redcliffe QLD 4020",
    "addr:housenumber":"46",
    "addr:postcode":"4020",
    "addr:street":"High St",
    "iso:country":"AU",
    "sg:address":"46 High St",
    "sg:city":"Redcliffe",
    "sg:classifiers":[
        {
            "category":"Professional",
            "type":"Services"
        }
    ],
    "sg:phone":"+61 7 3284 0199",
    "sg:postcode":"4020",
    "sg:province":"QLD",
    "sg:tags":[
        "packaging",
        "filling",
        "assembling"
    ],
    "wof:name":"Endeavour Business Service Redcliffe",
    "wof:placetype":"venue"
},
  "geometry": {"coordinates":[153.09274300000001,-27.226551],"type":"Point"}
}