{
  "type": "Feature",
  "properties": {
    "addr:full":"44 Princes Hwy Kogarah NSW 2217",
    "addr:housenumber":"44",
    "addr:postcode":"2217",
    "addr:street":"Princes Hwy",
    "iso:country":"AU",
    "sg:address":"44 Princes Hwy",
    "sg:city":"Kogarah",
    "sg:classifiers":[
        {
            "category":"Government",
            "subcategory":"Fire Station",
            "type":"Public Place"
        }
    ],
    "sg:phone":"+61 2 9553 1555",
    "sg:postcode":"2217",
    "sg:province":"NSW",
    "sg:tags":[
        "spring",
        "shock",
        "absorbers",
        "suspension"
    ],
    "wof:name":"Roadrunner Suspension",
    "wof:placetype":"venue"
},
  "geometry": {"coordinates":[151.133713,-33.970924],"type":"Point"}
}