{
  "type": "Feature",
  "properties": {
    "addr:full":"108 Franklin Rd Wanneroo WA 6065",
    "addr:housenumber":"108",
    "addr:postcode":"6065",
    "addr:street":"Franklin Rd",
    "iso:country":"AU",
    "sg:address":"108 Franklin Rd",
    "sg:city":"Wanneroo",
    "sg:classifiers":[
        {
            "category":"Home & Garden",
            "subcategory":"Garden Supply",
            "type":"Retail Goods"
        }
    ],
    "sg:phone":"+61 8 9306 1065",
    "sg:postcode":"6065",
    "sg:province":"WA",
    "sg:tags":[
        "turf",
        "lawn"
    ],
    "wof:name":"Greenfields Turf Farm",
    "wof:placetype":"venue"
},
  "geometry": {"coordinates":[115.829589844,-31.7509021759],"type":"Point"}
}