{
  "type": "Feature",
  "properties": {
    "addr:full":"1/13 White Lodge Crt Donvale VIC 3111",
    "addr:housenumber":"/ 13",
    "addr:postcode":"3111",
    "addr:street":"White Lodge Crt",
    "iso:country":"AU",
    "sg:address":"1/13 White Lodge Crt",
    "sg:city":"Donvale",
    "sg:classifiers":[
        {
            "category":"Professional",
            "subcategory":"Management & Consulting",
            "type":"Services"
        }
    ],
    "sg:phone":"+61 3 9872 4215",
    "sg:postcode":"3111",
    "sg:province":"VIC",
    "sg:tags":[
        "consultant"
    ],
    "wof:name":"Millennium Consulting Group International Pty Ltd",
    "wof:placetype":"venue"
},
  "geometry": {"coordinates":[145.191894531,-37.7948265076],"type":"Point"}
}