{
  "type": "Feature",
  "properties": {
    "addr:full":"Shop T66, Centro Mildura VIC 3500",
    "addr:postcode":"3500",
    "iso:country":"AU",
    "sg:address":"Shop T66, Centro",
    "sg:city":"Mildura",
    "sg:classifiers":[
        {
            "category":"Airline",
            "type":"Transportation"
        }
    ],
    "sg:phone":"+61 3 5022 1555",
    "sg:postcode":"3500",
    "sg:province":"VIC",
    "sg:tags":[
        "agent"
    ],
    "wof:name":"Harvey World Travel",
    "wof:placetype":"venue"
},
  "geometry": {"coordinates":[142.154098511,-34.2107391357],"type":"Point"}
}