{
  "type": "Feature",
  "properties": {
    "addr:full":"1-241 Lower Plenty Rd Rosanna VIC 3084",
    "addr:housenumber":"1-241",
    "addr:postcode":"3084",
    "addr:street":"Lower Plenty Rd",
    "iso:country":"AU",
    "sg:address":"1-241 Lower Plenty Rd",
    "sg:city":"Rosanna",
    "sg:classifiers":[
        {
            "category":"Building & Trades",
            "subcategory":"Construction",
            "type":"Services"
        }
    ],
    "sg:phone":"+61 430 082 290",
    "sg:postcode":"3084",
    "sg:province":"VIC",
    "sg:tags":[
        "polishing",
        "sanding",
        "floor"
    ],
    "wof:name":"All Aboard Floors",
    "wof:placetype":"venue"
},
  "geometry": {"coordinates":[145.07310485799999,-37.7381095886],"type":"Point"}
}