{
  "type": "Feature",
  "properties": {
    "iso:country":"AU",
    "sg:address":"142 Brisbane Rd",
    "sg:city":"Labrador",
    "sg:classifiers":[
        {
            "category":"Home & Garden",
            "subcategory":"Home Furnishings",
            "type":"Retail Goods"
        }
    ],
    "sg:phone":"+61 7 5529 2428",
    "sg:postcode":"4215",
    "sg:province":"QLD",
    "sg:tags":[
        "wicker",
        "cane",
        "furniture"
    ],
    "wof:name":"Java Wood & Cane",
    "wof:placetype":"venue"
},
  "geometry": {"coordinates":[153.392501831,-27.9351291656],"type":"Point"}
}