{
  "type": "Feature",
  "properties": {
    "iso:country":"AU",
    "sg:address":"70 Bundulla St",
    "sg:city":"Mendooran",
    "sg:classifiers":[
        {
            "category":"Autos & Motor Vehicles",
            "subcategory":"Fuel & Gas Station",
            "type":"Retail Goods"
        }
    ],
    "sg:phone":"+61 2 6886 1158",
    "sg:postcode":"2842",
    "sg:province":"NSW",
    "wof:name":"Mendooran Central Motors",
    "wof:placetype":"venue"
},
  "geometry": {"coordinates":[149.117599,-31.822392],"type":"Point"}
}