{
  "type": "Feature",
  "properties": {
    "iso:country":"AU",
    "sg:address":"Crosby Rd",
    "sg:city":"Malinong",
    "sg:classifiers":[
        {
            "category":"Food & Beverages",
            "subcategory":"Farmers Market",
            "type":"Retail Goods"
        }
    ],
    "sg:phone":"+61 8 8575 1881",
    "sg:postcode":"5259",
    "sg:province":"SA",
    "sg:tags":[
        "beekeeper"
    ],
    "wof:name":"Coorong Apiaries",
    "wof:placetype":"venue"
},
  "geometry": {"coordinates":[139.48045349099999,-35.5287017822],"type":"Point"}
}