{
  "type": "Feature",
  "properties": {
    "addr:full":"Suite 3/ 174 Roe St Northbridge WA 6003",
    "addr:housenumber":"/ 174",
    "addr:postcode":"6003",
    "addr:street":"Roe St",
    "iso:country":"AU",
    "sg:address":"Suite 3/ 174 Roe St",
    "sg:city":"Northbridge",
    "sg:classifiers":[
        {
            "category":"Professional",
            "subcategory":"Employment Agencies",
            "type":"Services"
        }
    ],
    "sg:phone":"+61 1800 806 050",
    "sg:postcode":"6003",
    "sg:province":"WA",
    "wof:name":"Westaff",
    "wof:placetype":"venue"
},
  "geometry": {"coordinates":[115.85247039799999,-31.9470233917],"type":"Point"}
}