{
  "type": "Feature",
  "properties": {
    "addr:full":"925 Nepean Hwy Mornington VIC 3931",
    "addr:housenumber":"925",
    "addr:postcode":"3931",
    "addr:street":"Nepean Hwy",
    "iso:country":"AU",
    "sg:address":"925 Nepean Hwy",
    "sg:city":"Mornington",
    "sg:classifiers":[
        {
            "category":"Personal",
            "type":"Services"
        }
    ],
    "sg:phone":"+61 3 5978 8224",
    "sg:postcode":"3931",
    "sg:province":"VIC",
    "sg:tags":[
        "counselling",
        "alcohol",
        "drug"
    ],
    "wof:name":"Beleura Clinic",
    "wof:placetype":"venue"
},
  "geometry": {"coordinates":[145.049758911,-38.2254295349],"type":"Point"}
}