{
  "type": "Feature",
  "properties": {
    "addr:full":"Shop 12, Tooronga Village, 354 Tooronga Rd Hawthorn East VIC 3123",
    "addr:housenumber":"shop 12;354",
    "addr:postcode":"3123",
    "addr:street":"Tooronga Village;Tooronga Rd",
    "iso:country":"AU",
    "sg:address":"Shop 12, Tooronga Village, 354 Tooronga Rd",
    "sg:city":"Hawthorn East",
    "sg:classifiers":[
        {
            "category":"Food & Beverages",
            "subcategory":"Bakery",
            "type":"Retail Goods"
        }
    ],
    "sg:phone":"+61 3 9804 3722",
    "sg:postcode":"3123",
    "sg:province":"VIC",
    "sg:tags":[
        "baker"
    ],
    "wof:name":"Bakers Delight Ltd",
    "wof:placetype":"venue"
},
  "geometry": {"coordinates":[145.04719543499999,-37.8321151733],"type":"Point"}
}