{
  "type": "Feature",
  "properties": {
    "iso:country":"AU",
    "sg:address":"132 Toongabbie Rd",
    "sg:city":"Girraween",
    "sg:classifiers":[
        {
            "category":"Manufacturing",
            "subcategory":"Tools & Machinery",
            "type":"Manufacturing & Wholesale Goods"
        }
    ],
    "sg:phone":"+61 2 8868 9700",
    "sg:postcode":"2145",
    "sg:province":"NSW",
    "sg:tags":[
        "earth",
        "excavating",
        "moving",
        "equipment"
    ],
    "sg:website":"http://www.dynapac.com",
    "wof:name":"Dynapac",
    "wof:placetype":"venue"
},
  "geometry": {"coordinates":[150.93995666500001,-33.7938995361],"type":"Point"}
}