{
  "type": "Feature",
  "properties": {
    "addr:full":"Unit 10/ 11 Alloa St Maddington WA 6109",
    "addr:housenumber":"/ 11",
    "addr:postcode":"6109",
    "addr:street":"Alloa St",
    "iso:country":"AU",
    "sg:address":"Unit 10/ 11 Alloa St",
    "sg:city":"Maddington",
    "sg:classifiers":[
        {
            "category":"Utilities",
            "subcategory":"Natural Gas",
            "type":"Services"
        }
    ],
    "sg:phone":"+61 8 9492 1900",
    "sg:postcode":"6109",
    "sg:province":"WA",
    "sg:tags":[
        "pressing",
        "metal",
        "stamping"
    ],
    "sg:website":"http://www.ceilings.com.au",
    "wof:name":"Ceilings.com.au",
    "wof:placetype":"venue"
},
  "geometry": {"coordinates":[115.98445892300001,-32.044883728],"type":"Point"}
}