{
  "type": "Feature",
  "properties": {
    "iso:country":"AU",
    "sg:address":"2 Grey St",
    "sg:city":"Northam",
    "sg:classifiers":[
        {
            "category":"Cafe",
            "type":"Food & Drink"
        }
    ],
    "sg:phone":"+61 8 9622 5635",
    "sg:postcode":"6401",
    "sg:province":"WA",
    "wof:name":"Riversedge Cafe",
    "wof:placetype":"venue"
},
  "geometry": {"coordinates":[116.671882629,-31.6519050598],"type":"Point"}
}