{
  "type": "Feature",
  "properties": {
    "addr:full":"55 Webb St Croydon NSW 2132",
    "addr:housenumber":"55",
    "addr:postcode":"2132",
    "addr:street":"Webb St",
    "iso:country":"AU",
    "sg:address":"55 Webb St",
    "sg:city":"Croydon",
    "sg:classifiers":[
        {
            "category":"Education",
            "subcategory":"Kindergarten",
            "type":"Public Place"
        }
    ],
    "sg:phone":"+61 2 9744 2080",
    "sg:postcode":"2132",
    "sg:province":"NSW",
    "sg:tags":[
        "pre-schools"
    ],
    "wof:name":"Kiddies Kapers",
    "wof:placetype":"venue"
},
  "geometry": {"coordinates":[151.11294555699999,-33.879486084],"type":"Point"}
}