{
  "type": "Feature",
  "properties": {
    "addr:full":"50 Edward St Oakleigh VIC 3166",
    "addr:housenumber":"50",
    "addr:postcode":"3166",
    "addr:street":"Edward St",
    "iso:country":"AU",
    "sg:address":"50 Edward St",
    "sg:city":"Oakleigh",
    "sg:classifiers":[
        {
            "category":"Home & Garden",
            "subcategory":"Building Materials",
            "type":"Retail Goods"
        }
    ],
    "sg:phone":"+61 3 8574 3833",
    "sg:postcode":"3166",
    "sg:province":"VIC",
    "sg:tags":[
        "shutter",
        "roller",
        "grille"
    ],
    "wof:name":"Besam Australia",
    "wof:placetype":"venue"
},
  "geometry": {"coordinates":[145.10293579099999,-37.9059562683],"type":"Point"}
}