{
  "type": "Feature",
  "properties": {
    "addr:full":"Thomasen Rd Clayton QLD 4705",
    "addr:postcode":"4705",
    "addr:street":"Thomasen Rd",
    "iso:country":"AU",
    "sg:address":"Thomasen Rd",
    "sg:city":"Clayton",
    "sg:classifiers":[
        {
            "category":"Farming",
            "subcategory":"Farm & Veterinary Services",
            "type":"Manufacturing & Wholesale Goods"
        }
    ],
    "sg:phone":"+61 7 4159 7326",
    "sg:postcode":"4705",
    "sg:province":"QLD",
    "sg:tags":[
        "contracting"
    ],
    "wof:name":"Harte B W & V J",
    "wof:placetype":"venue"
},
  "geometry": {"coordinates":[149.28944397000001,-22.7087192535],"type":"Point"}
}