{
  "type": "Feature",
  "properties": {
    "iso:country":"AU",
    "sg:address":"Factory 2 17 Commercial Drv",
    "sg:city":"Dandenong",
    "sg:classifiers":[
        {
            "category":"Retail",
            "subcategory":"Auto Repair",
            "type":"Services"
        }
    ],
    "sg:phone":"+61 3 9768 2633",
    "sg:postcode":"3175",
    "sg:province":"VIC",
    "sg:tags":[
        "repairer",
        "motor",
        "engineer"
    ],
    "wof:name":"Norling C & S Pty Ltd",
    "wof:placetype":"venue"
},
  "geometry": {"coordinates":[145.22833251899999,-38.024307251],"type":"Point"}
}