{
  "type": "Feature",
  "properties": {
    "iso:country":"AU",
    "sg:address":"51 Garden St",
    "sg:city":"South Yarra",
    "sg:classifiers":[
        {
            "category":"Building & Trades",
            "subcategory":"Construction",
            "type":"Services"
        }
    ],
    "sg:phone":"+61 3 9826 4448",
    "sg:postcode":"3141",
    "sg:province":"VIC",
    "sg:tags":[
        "contractor"
    ],
    "wof:name":"Arundel Constructions Pty Ltd",
    "wof:placetype":"venue"
},
  "geometry": {"coordinates":[144.997436523,-37.8434181213],"type":"Point"}
}