{
  "type": "Feature",
  "properties": {
    "iso:country":"AU",
    "sg:address":"78b Scarborough Beach Rd",
    "sg:city":"Scarborough",
    "sg:classifiers":[
        {
            "category":"Professional",
            "subcategory":"Accounting & Tax Preparation",
            "type":"Services"
        }
    ],
    "sg:phone":"+61 8 9245 1366",
    "sg:postcode":"6019",
    "sg:province":"WA",
    "sg:tags":[
        "accountant",
        "auditor"
    ],
    "wof:name":"MacPherson & Associates",
    "wof:placetype":"venue"
},
  "geometry": {"coordinates":[115.76467895499999,-31.8940353394],"type":"Point"}
}