{
  "type": "Feature",
  "properties": {
    "addr:full":"9 Floor, 20 Collins St Melbourne VIC 3000",
    "addr:housenumber":"20",
    "addr:postcode":"3000",
    "addr:street":"Collins St",
    "iso:country":"AU",
    "sg:address":"9 Floor, 20 Collins St",
    "sg:city":"Melbourne",
    "sg:classifiers":[
        {
            "category":"Health Services",
            "subcategory":"Doctor",
            "type":"Services"
        }
    ],
    "sg:phone":"+61 3 9650 1641",
    "sg:postcode":"3000",
    "sg:province":"VIC",
    "sg:tags":[
        "medical",
        "practitioner"
    ],
    "wof:name":"Lazarus Mark Dr",
    "wof:placetype":"venue"
},
  "geometry": {"coordinates":[144.973190308,-37.8134040833],"type":"Point"}
}