{
  "type": "Feature",
  "properties": {
    "iso:country":"AU",
    "sg:address":"1088 Raglan Pde",
    "sg:city":"Warrnambool",
    "sg:classifiers":[
        {
            "category":"Manufacturing",
            "subcategory":"Metals",
            "type":"Manufacturing & Wholesale Goods"
        }
    ],
    "sg:phone":"+61 3 5561 2596",
    "sg:postcode":"3280",
    "sg:province":"VIC",
    "sg:tags":[
        "sheet",
        "worker"
    ],
    "wof:name":"Raglan Sheet Metal",
    "wof:placetype":"venue"
},
  "geometry": {"coordinates":[142.45622253400001,-38.361946106],"type":"Point"}
}