{
  "type": "Feature",
  "properties": {
    "addr:full":"59 Margaret St Toowoomba QLD 4350",
    "addr:housenumber":"59",
    "addr:postcode":"4350",
    "addr:street":"Margaret St",
    "iso:country":"AU",
    "sg:address":"59 Margaret St",
    "sg:city":"Toowoomba",
    "sg:classifiers":[
        {
            "category":"Health Services",
            "subcategory":"Doctor",
            "type":"Services"
        }
    ],
    "sg:phone":"+61 7 4632 1022",
    "sg:postcode":"4350",
    "sg:province":"QLD",
    "sg:tags":[
        "medical",
        "practitioner"
    ],
    "wof:name":"Zabell Keith W",
    "wof:placetype":"venue"
},
  "geometry": {"coordinates":[151.95510899999999,-27.561071],"type":"Point"}
}