{
  "type": "Feature",
  "properties": {
    "addr:full":"4/ 59 Winnellie Rd Winnellie NT 0820",
    "addr:housenumber":"/ 59",
    "addr:postcode":"nt 0820",
    "addr:street":"Winnellie Rd",
    "iso:country":"AU",
    "sg:address":"4/ 59 Winnellie Rd",
    "sg:city":"Winnellie",
    "sg:classifiers":[
        {
            "category":"Building & Trades",
            "subcategory":"Construction",
            "type":"Services"
        }
    ],
    "sg:phone":"+61 1300 883 308",
    "sg:postcode":"0820",
    "sg:province":"NT",
    "sg:tags":[
        "industrial",
        "commercial",
        "air conditioning"
    ],
    "wof:name":"Haden Engineering Pty Ltd",
    "wof:placetype":"venue"
},
  "geometry": {"coordinates":[130.87922668499999,-12.4264888763],"type":"Point"}
}