{
  "type": "Feature",
  "properties": {
    "addr:full":"16 Bellambi La Bellambi NSW 2518",
    "addr:housenumber":"16",
    "addr:postcode":"2518",
    "addr:street":"Bellambi La Bellambi",
    "iso:country":"AU",
    "sg:address":"16 Bellambi La",
    "sg:city":"Bellambi",
    "sg:classifiers":[
        {
            "category":"Shopping",
            "type":"Retail Goods"
        }
    ],
    "sg:phone":"+61 2 4283 8335",
    "sg:postcode":"2518",
    "sg:province":"NSW",
    "sg:tags":[
        "clearance",
        "factory",
        "outlet"
    ],
    "wof:name":"King Gee Factory Outlet",
    "wof:placetype":"venue"
},
  "geometry": {"coordinates":[150.887787,-34.373608],"type":"Point"}
}