{
  "type": "Feature",
  "properties": {
    "addr:full":"18 Bridge St Stanthorpe QLD 4380",
    "addr:housenumber":"18",
    "addr:postcode":"4380",
    "addr:street":"Bridge St",
    "iso:country":"AU",
    "sg:address":"18 Bridge St",
    "sg:city":"Stanthorpe",
    "sg:classifiers":[
        {
            "category":"Farming",
            "subcategory":"Orchard",
            "type":"Manufacturing & Wholesale Goods"
        }
    ],
    "sg:phone":"+61 7 4681 1270",
    "sg:postcode":"4380",
    "sg:province":"QLD",
    "sg:tags":[
        "pear",
        "apple",
        "grower"
    ],
    "wof:name":"Pozzebon C & Co",
    "wof:placetype":"venue"
},
  "geometry": {"coordinates":[151.93109100000001,-28.660307],"type":"Point"}
}