{
  "type": "Feature",
  "properties": {
    "addr:full":"Unit 1/ 10 Essex St Minto NSW 2566",
    "addr:postcode":"2566",
    "addr:street":"Essex St",
    "iso:country":"AU",
    "sg:address":"Unit 1/ 10 Essex St",
    "sg:city":"Minto",
    "sg:classifiers":[
        {
            "category":"Wholesale",
            "subcategory":"Painting Supplies",
            "type":"Manufacturing & Wholesale Goods"
        }
    ],
    "sg:phone":"+61 2 9603 8266",
    "sg:postcode":"2566",
    "sg:province":"NSW",
    "sg:tags":[
        "product",
        "cleaning"
    ],
    "wof:name":"Aljen Services Pty Ltd",
    "wof:placetype":"venue"
},
  "geometry": {"coordinates":[150.84278869600001,-34.0208930969],"type":"Point"}
}