{
  "type": "Feature",
  "properties": {
    "addr:full":"8 Southey St Brighton VIC 3186",
    "addr:housenumber":"8",
    "addr:postcode":"3186",
    "addr:street":"Southey St",
    "iso:country":"AU",
    "sg:address":"8 Southey St",
    "sg:city":"Brighton",
    "sg:classifiers":[
        {
            "category":"Personal",
            "subcategory":"Beauty Salon",
            "type":"Services"
        }
    ],
    "sg:phone":"+61 3 9592 3482",
    "sg:postcode":"3186",
    "sg:province":"VIC",
    "sg:tags":[
        "supply",
        "artist",
        "make-up"
    ],
    "wof:name":"J B Blush",
    "wof:placetype":"venue"
},
  "geometry": {"coordinates":[145.006256103,-37.9074821472],"type":"Point"}
}