{
  "type": "Feature",
  "properties": {
    "addr:full":"34c Vincent St Cessnock NSW 2325",
    "addr:housenumber":"34c",
    "addr:postcode":"2325",
    "addr:street":"Vincent St",
    "iso:country":"AU",
    "sg:address":"34c Vincent St",
    "sg:city":"Cessnock",
    "sg:classifiers":[
        {
            "category":"Personal",
            "subcategory":"Beauty Salon",
            "type":"Services"
        }
    ],
    "sg:phone":"+61 2 4990 7411",
    "sg:postcode":"2325",
    "sg:province":"NSW",
    "sg:tags":[
        "hairdresser"
    ],
    "wof:name":"Strands On Vincent",
    "wof:placetype":"venue"
},
  "geometry": {"coordinates":[151.35667419399999,-32.8336410522],"type":"Point"}
}