{
  "type": "Feature",
  "properties": {
    "addr:full":"Shop 33, Yorktown Rd Craigmore SA 5114",
    "addr:housenumber":"shop 33",
    "addr:postcode":"5114",
    "addr:street":"Yorktown Rd",
    "iso:country":"AU",
    "sg:address":"Shop 33, Yorktown Rd",
    "sg:city":"Craigmore",
    "sg:classifiers":[
        {
            "category":"Wholesale",
            "subcategory":"Medical Equipment & Supplies",
            "type":"Manufacturing & Wholesale Goods"
        }
    ],
    "sg:phone":"+61 1800 006 303",
    "sg:postcode":"5114",
    "sg:province":"SA",
    "sg:tags":[
        "aids",
        "hearing"
    ],
    "wof:name":"Hearing Care",
    "wof:placetype":"venue"
},
  "geometry": {"coordinates":[138.72929382300001,-34.7101173401],"type":"Point"}
}