{
  "type": "Feature",
  "properties": {
    "addr:full":"14 Driffield Rd Morwell VIC 3840",
    "addr:postcode":"3840",
    "addr:street":"14 Driffield Rd",
    "iso:country":"AU",
    "sg:address":"14 Driffield Rd",
    "sg:city":"Morwell",
    "sg:classifiers":[
        {
            "category":"Retail",
            "subcategory":"Auto Rental",
            "type":"Services"
        }
    ],
    "sg:phone":"+61 3 5134 2733",
    "sg:postcode":"3840",
    "sg:province":"VIC",
    "sg:tags":[
        "car",
        "armoured"
    ],
    "wof:name":"Armaguard",
    "wof:placetype":"venue"
},
  "geometry": {"coordinates":[146.38442993199999,-38.2355461121],"type":"Point"}
}