{
  "type": "Feature",
  "properties": {
    "iso:country":"AU",
    "sg:address":"Unit 1/ 88 Albany Hwy",
    "sg:city":"Kojonup",
    "sg:classifiers":[
        {
            "category":"Cafe",
            "type":"Food & Drink"
        }
    ],
    "sg:phone":"+61 8 9831 1338",
    "sg:postcode":"6395",
    "sg:province":"WA",
    "wof:name":"Kojonup Country Kitchen",
    "wof:placetype":"venue"
},
  "geometry": {"coordinates":[117.159553528,-33.8365211487],"type":"Point"}
}