{
  "type": "Feature",
  "properties": {
    "addr:full":"28 Crofton St Bundaberg QLD 4670",
    "addr:housenumber":"28",
    "addr:postcode":"4670",
    "addr:street":"Crofton St",
    "iso:country":"AU",
    "sg:address":"28 Crofton St",
    "sg:city":"Bundaberg",
    "sg:classifiers":[
        {
            "category":"Health Services",
            "subcategory":"Health Practitioner",
            "type":"Services"
        }
    ],
    "sg:phone":"+61 7 4153 6644",
    "sg:postcode":"4670",
    "sg:province":"QLD",
    "sg:tags":[
        "physiotherapist"
    ],
    "wof:name":"Harbourne Trudy M",
    "wof:placetype":"venue"
},
  "geometry": {"coordinates":[152.348953247,-24.869934082],"type":"Point"}
}