{
  "type": "Feature",
  "properties": {
    "iso:country":"AU",
    "sg:address":"143 Kippax St",
    "sg:city":"Surry Hills",
    "sg:classifiers":[
        {
            "category":"Government",
            "subcategory":"Court House",
            "type":"Public Place"
        }
    ],
    "sg:phone":"+61 414 333 037",
    "sg:postcode":"2010",
    "sg:province":"NSW",
    "sg:tags":[
        "personal",
        "marriage",
        "family",
        "counselling"
    ],
    "wof:name":"Margaret Noonan",
    "wof:placetype":"venue"
},
  "geometry": {"coordinates":[151.21191406200001,-33.8858146667],"type":"Point"}
}