{
  "type": "Feature",
  "properties": {
    "addr:full":"325 Liverpool Rd Strathfield NSW 2135",
    "addr:housenumber":"325",
    "addr:postcode":"2135",
    "addr:street":"Liverpool Rd",
    "iso:country":"AU",
    "sg:address":"325 Liverpool Rd",
    "sg:city":"Strathfield",
    "sg:classifiers":[
        {
            "category":"Home & Garden",
            "subcategory":"Carpets & Floor Coverings",
            "type":"Retail Goods"
        }
    ],
    "sg:phone":"+61 2 9701 0148",
    "sg:postcode":"2135",
    "sg:province":"NSW",
    "wof:name":"Complete Floors",
    "wof:placetype":"venue"
},
  "geometry": {"coordinates":[151.09213256800001,-33.8868293762],"type":"Point"}
}