{
  "type": "Feature",
  "properties": {
    "addr:full":"2/ 1 Stansfield Ave Bankstown NSW 2200",
    "addr:housenumber":"/ 1",
    "addr:postcode":"2200",
    "addr:street":"Stansfield Ave",
    "iso:country":"AU",
    "sg:address":"2/ 1 Stansfield Ave",
    "sg:city":"Bankstown",
    "sg:classifiers":[
        {
            "category":"Travel",
            "subcategory":"Hotels & Motels",
            "type":"Entertainment"
        }
    ],
    "sg:phone":"+61 410 786 019",
    "sg:postcode":"2200",
    "sg:province":"NSW",
    "sg:tags":[
        "accommodation"
    ],
    "wof:name":"Amazon Travel Online",
    "wof:placetype":"venue"
},
  "geometry": {"coordinates":[151.04548600000001,-33.918076],"type":"Point"}
}