{
  "type": "Feature",
  "properties": {
    "addr:full":"Unit 8 143 Correen Ave Penrith NSW 2750",
    "addr:housenumber":"143",
    "addr:postcode":"2750",
    "addr:street":"Correen Ave",
    "iso:country":"AU",
    "sg:address":"Unit 8 143 Correen Ave",
    "sg:city":"Penrith",
    "sg:classifiers":[
        {
            "category":"Professional",
            "subcategory":"Engineering",
            "type":"Services"
        }
    ],
    "sg:phone":"+61 2 4732 3285",
    "sg:postcode":"2750",
    "sg:province":"NSW",
    "sg:tags":[
        "engineer"
    ],
    "wof:name":"Hyslop B & M",
    "wof:placetype":"venue"
},
  "geometry": {"coordinates":[150.69433593799999,-33.743560791],"type":"Point"}
}