{
  "type": "Feature",
  "properties": {
    "addr:full":"216 Glenmore Rd Paddington NSW 2021",
    "addr:housenumber":"216",
    "addr:postcode":"2021",
    "addr:street":"Glenmore Rd",
    "iso:country":"AU",
    "sg:address":"216 Glenmore Rd",
    "sg:city":"Paddington",
    "sg:classifiers":[
        {
            "category":"Health Services",
            "subcategory":"Chiropractor",
            "type":"Services"
        }
    ],
    "sg:phone":"+61 2 9331 0400",
    "sg:postcode":"2021",
    "sg:province":"NSW",
    "wof:name":"Euan McMillian",
    "wof:placetype":"venue"
},
  "geometry": {"coordinates":[151.22773742699999,-33.8820762634],"type":"Point"}
}