{
  "type": "Feature",
  "properties": {
    "iso:country":"AU",
    "sg:address":"13 Carlotta Rd",
    "sg:city":"Double Bay",
    "sg:classifiers":[
        {
            "category":"Real Estate",
            "subcategory":"Architect",
            "type":"Services"
        }
    ],
    "sg:phone":"+61 2 9363 2222",
    "sg:postcode":"2028",
    "sg:province":"NSW",
    "wof:name":"Abram Philip, Architect",
    "wof:placetype":"venue"
},
  "geometry": {"coordinates":[151.24673461899999,-33.8794784546],"type":"Point"}
}