{
  "type": "Feature",
  "properties": {
    "addr:full":"Point Leo Rd Merricks VIC 3916",
    "addr:postcode":"3916",
    "addr:street":"Point Leo Rd",
    "iso:country":"AU",
    "sg:address":"Point Leo Rd",
    "sg:city":"Merricks",
    "sg:classifiers":[
        {
            "category":"Home & Garden",
            "subcategory":"Furniture",
            "type":"Retail Goods"
        }
    ],
    "sg:phone":"+61 3 5989 8215",
    "sg:postcode":"3916",
    "sg:province":"VIC",
    "sg:tags":[
        "baby",
        "children's"
    ],
    "wof:name":"St Vincent's Boys' Orphanage",
    "wof:placetype":"venue"
},
  "geometry": {"coordinates":[145.06712341299999,-38.4087715149],"type":"Point"}
}