{
  "type": "Feature",
  "properties": {
    "addr:full":"104 Dunbar Rd Burpengary QLD 4505",
    "addr:housenumber":"104",
    "addr:postcode":"4505",
    "addr:street":"Dunbar Rd",
    "iso:country":"AU",
    "sg:address":"104 Dunbar Rd",
    "sg:city":"Burpengary",
    "sg:classifiers":[
        {
            "category":"Utilities",
            "subcategory":"Electric",
            "type":"Services"
        }
    ],
    "sg:phone":"+61 7 5428 6781",
    "sg:postcode":"4505",
    "sg:province":"QLD",
    "sg:tags":[
        "electrical",
        "contractor"
    ],
    "wof:name":"Andrew Walton Electrical",
    "wof:placetype":"venue"
},
  "geometry": {"coordinates":[153.01809692399999,-27.1334724426],"type":"Point"}
}