{
  "type": "Feature",
  "properties": {
    "addr:full":"57 Myers St Bendigo VIC 3550",
    "addr:housenumber":"57",
    "addr:postcode":"3550",
    "addr:street":"Myers St",
    "iso:country":"AU",
    "sg:address":"57 Myers St",
    "sg:city":"Bendigo",
    "sg:classifiers":[
        {
            "category":"Real Estate",
            "subcategory":"Real Estate Services",
            "type":"Services"
        }
    ],
    "sg:phone":"+61 3 5441 5288",
    "sg:postcode":"3550",
    "sg:province":"VIC",
    "sg:tags":[
        "valuer"
    ],
    "wof:name":"Woodland Valuers Pty Ltd",
    "wof:placetype":"venue"
},
  "geometry": {"coordinates":[144.286987305,-36.7585334778],"type":"Point"}
}