{
  "type": "Feature",
  "properties": {
    "iso:country":"AU",
    "sg:address":"10 Saltwater Pl",
    "sg:city":"Redland Bay",
    "sg:classifiers":[
        {
            "category":"Building & Trades",
            "subcategory":"Landscaping Services",
            "type":"Services"
        }
    ],
    "sg:phone":"+61 7 3206 8005",
    "sg:postcode":"4165",
    "sg:province":"QLD",
    "sg:tags":[
        "designer",
        "landscape",
        "contractor"
    ],
    "wof:name":"All Unique Landscaping",
    "wof:placetype":"venue"
},
  "geometry": {"coordinates":[153.308685303,-27.6353874207],"type":"Point"}
}