{
  "type": "Feature",
  "properties": {
    "addr:full":"63 Myers St Geelong VIC 3220",
    "addr:housenumber":"63",
    "addr:postcode":"3220",
    "addr:street":"Myers St",
    "iso:country":"AU",
    "sg:address":"63 Myers St",
    "sg:city":"Geelong",
    "sg:classifiers":[
        {
            "category":"Shopping",
            "subcategory":"Clothing, Apparel, & Fashions",
            "type":"Retail Goods"
        }
    ],
    "sg:phone":"+61 3 5221 9199",
    "sg:postcode":"3220",
    "sg:province":"VIC",
    "sg:tags":[
        "uniform"
    ],
    "wof:name":"Bellarine Uniforms",
    "wof:placetype":"venue"
},
  "geometry": {"coordinates":[144.357101,-38.150711],"type":"Point"}
}