{
  "type": "Feature",
  "properties": {
    "addr:full":"Kneipp St Ashford NSW 2361",
    "addr:postcode":"2361",
    "addr:street":"Kneipp St",
    "iso:country":"AU",
    "sg:address":"Kneipp St",
    "sg:city":"Ashford",
    "sg:classifiers":[
        {
            "category":"Travel",
            "subcategory":"Hostel",
            "type":"Entertainment"
        }
    ],
    "sg:phone":"+61 2 6725 4223",
    "sg:postcode":"2361",
    "sg:province":"NSW",
    "sg:tags":[
        "home"
    ],
    "wof:name":"Sunhaven Hostel",
    "wof:placetype":"venue"
},
  "geometry": {"coordinates":[151.08987426799999,-29.3206329346],"type":"Point"}
}