{
  "type": "Feature",
  "properties": {
    "iso:country":"AU",
    "sg:address":"Unit 5, 8 - 10 Barry Rd",
    "sg:city":"Chipping Norton",
    "sg:classifiers":[
        {
            "category":"Manufacturing",
            "subcategory":"Electronics",
            "type":"Manufacturing & Wholesale Goods"
        }
    ],
    "sg:phone":"+61 1300 729 566",
    "sg:postcode":"2170",
    "sg:province":"NSW",
    "sg:tags":[
        "equipment",
        "supply"
    ],
    "wof:name":"DCT Australia",
    "wof:placetype":"venue"
},
  "geometry": {"coordinates":[150.966064453,-33.9151916504],"type":"Point"}
}