{
  "type": "Feature",
  "properties": {
    "iso:country":"AU",
    "sg:address":"PO Box 19",
    "sg:city":"The Junction",
    "sg:classifiers":[
        {
            "category":"Train Station",
            "subcategory":"Light Rail",
            "type":"Transportation"
        }
    ],
    "sg:phone":"+61 2 4963 5077",
    "sg:postcode":"2291",
    "sg:province":"NSW",
    "sg:tags":[
        "equipment",
        "energy",
        "solar"
    ],
    "wof:name":"Demand Solar Hunter",
    "wof:placetype":"venue"
},
  "geometry": {"coordinates":[151.759887695,-32.9372406006],"type":"Point"}
}