{
  "type": "Feature",
  "properties": {
    "addr:full":"Shop G6A Beach St Frankston VIC 3199",
    "addr:postcode":"3199",
    "addr:street":"St",
    "iso:country":"AU",
    "sg:address":"Shop G6A Beach St",
    "sg:city":"Frankston",
    "sg:classifiers":[
        {
            "category":"Retail",
            "subcategory":"Repair Shop",
            "type":"Services"
        }
    ],
    "sg:phone":"+61 3 9783 1900",
    "sg:postcode":"3199",
    "sg:province":"VIC",
    "sg:tags":[
        "mending",
        "clothing",
        "alteration"
    ],
    "wof:name":"Brown Gouge",
    "wof:placetype":"venue"
},
  "geometry": {"coordinates":[145.12179565400001,-38.1415710449],"type":"Point"}
}