{
  "type": "Feature",
  "properties": {
    "addr:full":"145 Elliott Rd Banyo QLD 4014",
    "addr:housenumber":"145",
    "addr:postcode":"4014",
    "addr:street":"Elliott Rd",
    "iso:country":"AU",
    "sg:address":"145 Elliott Rd",
    "sg:city":"Banyo",
    "sg:classifiers":[
        {
            "category":"Retail",
            "subcategory":"Auto Repair",
            "type":"Services"
        }
    ],
    "sg:phone":"+61 7 3267 6716",
    "sg:postcode":"4014",
    "sg:province":"QLD",
    "sg:tags":[
        "beater",
        "painter",
        "panel"
    ],
    "wof:name":"Banyo Smash Repairs",
    "wof:placetype":"venue"
},
  "geometry": {"coordinates":[153.07864379899999,-27.3676948547],"type":"Point"}
}