{
  "type": "Feature",
  "properties": {
    "addr:full":"Shops 3 & 4, 54 Clyde St Hamilton North NSW 2292",
    "addr:housenumber":"shops 3 &;54",
    "addr:postcode":"2292",
    "addr:street":"4;Clyde St",
    "iso:country":"AU",
    "sg:address":"Shops 3 & 4, 54 Clyde St",
    "sg:city":"Hamilton North",
    "sg:classifiers":[
        {
            "category":"Shopping",
            "subcategory":"Antiques",
            "type":"Retail Goods"
        }
    ],
    "sg:phone":"+61 2 4969 6492",
    "sg:postcode":"2292",
    "sg:province":"NSW",
    "wof:name":"Islington 2nd Hand",
    "wof:placetype":"venue"
},
  "geometry": {"coordinates":[151.736572266,-32.9120483398],"type":"Point"}
}