{
  "type": "Feature",
  "properties": {
    "addr:full":"121 Macqueen St Aberdeen NSW 2336",
    "addr:housenumber":"121",
    "addr:postcode":"2336",
    "addr:street":"Macqueen St",
    "iso:country":"AU",
    "sg:address":"121 Macqueen St",
    "sg:city":"Aberdeen",
    "sg:classifiers":[
        {
            "category":"Cafe",
            "type":"Food & Drink"
        }
    ],
    "sg:phone":"+61 2 6543 7121",
    "sg:postcode":"2336",
    "sg:province":"NSW",
    "wof:name":"Cafe 121 On Macqueen",
    "wof:placetype":"venue"
},
  "geometry": {"coordinates":[150.89140319800001,-32.1673927307],"type":"Point"}
}