{
  "type": "Feature",
  "properties": {
    "addr:full":"17 Alanvale Rd Alanvale TAS 7248",
    "addr:housenumber":"17",
    "addr:postcode":"7248",
    "addr:street":"Alanvale Rd",
    "iso:country":"AU",
    "sg:address":"17 Alanvale Rd",
    "sg:city":"Alanvale",
    "sg:classifiers":[
        {
            "category":"Travel",
            "subcategory":"Hotels & Motels",
            "type":"Entertainment"
        }
    ],
    "sg:phone":"+61 3 6326 3600",
    "sg:postcode":"7248",
    "sg:province":"TAS",
    "wof:name":"Archers&#039; Manor",
    "wof:placetype":"venue"
},
  "geometry": {"coordinates":[147.12550354000001,-41.3953704834],"type":"Point"}
}