{
  "type": "Feature",
  "properties": {
    "iso:country":"AU",
    "sg:address":"10 Riflebird Ave",
    "sg:city":"Caloundra",
    "sg:classifiers":[
        {
            "category":"Farming",
            "subcategory":"Farm & Veterinary Services",
            "type":"Manufacturing & Wholesale Goods"
        }
    ],
    "sg:phone":"+61 7 5491 5124",
    "sg:postcode":"4551",
    "sg:province":"QLD",
    "sg:tags":[
        "agricultural",
        "advisory"
    ],
    "wof:name":"Agribusiness Services Pty Ltd",
    "wof:placetype":"venue"
},
  "geometry": {"coordinates":[153.115524292,-26.7786540985],"type":"Point"}
}