{
  "type": "Feature",
  "properties": {
    "iso:country":"AU",
    "sg:address":"3 Burr Ave",
    "sg:city":"Nowra",
    "sg:classifiers":[
        {
            "category":"Donuts",
            "subcategory":"None",
            "type":"Food & Drink"
        }
    ],
    "sg:phone":"+61 2 4423 0502",
    "sg:postcode":"2541",
    "sg:province":"NSW",
    "sg:tags":[
        "die",
        "engraver",
        "sinker"
    ],
    "wof:name":"D & F South Coast Trophies & Engraving",
    "wof:placetype":"venue"
},
  "geometry": {"coordinates":[150.5987854,-34.8765640259],"type":"Point"}
}