{
  "type": "Feature",
  "properties": {
    "iso:country":"AU",
    "sg:address":"17 Arizona Rd",
    "sg:city":"Charmhaven",
    "sg:classifiers":[
        {
            "category":"Manufacturing",
            "subcategory":"Metals",
            "type":"Manufacturing & Wholesale Goods"
        }
    ],
    "sg:phone":"+61 2 4392 5833",
    "sg:postcode":"2263",
    "sg:province":"NSW",
    "sg:tags":[
        "expanded"
    ],
    "wof:name":"Expanded Metal Products Pty Ltd",
    "wof:placetype":"venue"
},
  "geometry": {"coordinates":[151.493607,-33.241627],"type":"Point"}
}