{
  "type": "Feature",
  "properties": {
    "addr:full":"4 Girraween Ave Erina NSW 2250",
    "addr:housenumber":"4",
    "addr:postcode":"2250",
    "addr:street":"Girraween Ave",
    "iso:country":"AU",
    "sg:address":"4 Girraween Ave",
    "sg:city":"Erina",
    "sg:classifiers":[
        {
            "category":"Personal",
            "subcategory":"Beauty Salon",
            "type":"Services"
        }
    ],
    "sg:phone":"+61 2 4365 1672",
    "sg:postcode":"2250",
    "sg:province":"NSW",
    "wof:name":"dazzle Beauty Therapy",
    "wof:placetype":"venue"
},
  "geometry": {"coordinates":[151.3931427,-33.4324302673],"type":"Point"}
}