{
  "type": "Feature",
  "properties": {
    "iso:country":"AU",
    "sg:address":"12 Bougainville St",
    "sg:city":"Manuka",
    "sg:classifiers":[
        {
            "category":"Health Services",
            "subcategory":"Dentist",
            "type":"Services"
        }
    ],
    "sg:phone":"+61 2 6239 5447",
    "sg:postcode":"2603",
    "sg:province":"ACT",
    "wof:name":"Mirek Szokalski Dr",
    "wof:placetype":"venue"
},
  "geometry": {"coordinates":[149.13299560600001,-35.3212738037],"type":"Point"}
}