{
  "type": "Feature",
  "properties": {
    "addr:full":"15 Bridgman Drv Reedy Creek QLD 4228",
    "addr:housenumber":"15",
    "addr:postcode":"4228",
    "addr:street":"Bridgman Drv",
    "iso:country":"AU",
    "sg:address":"15 Bridgman Drv",
    "sg:city":"Reedy Creek",
    "sg:classifiers":[
        {
            "category":"Sports & Exercise",
            "subcategory":"Gym",
            "type":"Entertainment"
        }
    ],
    "sg:phone":"+61 415 852 758",
    "sg:postcode":"4228",
    "sg:province":"QLD",
    "sg:tags":[
        "health",
        "fitness"
    ],
    "wof:name":"100% Fitness",
    "wof:placetype":"venue"
},
  "geometry": {"coordinates":[153.403030395,-28.1017894745],"type":"Point"}
}