{
  "type": "Feature",
  "properties": {
    "addr:full":"Breeze Pde Forster NSW 2428",
    "addr:postcode":"2428",
    "addr:street":"Breeze Pde",
    "iso:country":"AU",
    "sg:address":"Breeze Pde",
    "sg:city":"Forster",
    "sg:classifiers":[
        {
            "category":"Social Services",
            "subcategory":"Child Care",
            "type":"Services"
        }
    ],
    "sg:phone":"+61 2 6555 6822",
    "sg:postcode":"2428",
    "sg:province":"NSW",
    "sg:tags":[
        "support",
        "health"
    ],
    "wof:name":"Early Childhood Health Centres",
    "wof:placetype":"venue"
},
  "geometry": {"coordinates":[152.52041600000001,-32.200291],"type":"Point"}
}