{
  "type": "Feature",
  "properties": {
    "addr:full":"252- 256 Sydney Rd Balgowlah NSW 2093",
    "addr:housenumber":"256",
    "addr:postcode":"2093",
    "addr:street":"Sydney Rd",
    "iso:country":"AU",
    "sg:address":"252- 256 Sydney Rd",
    "sg:city":"Balgowlah",
    "sg:classifiers":[
        {
            "category":"Banks & Credit Unions",
            "subcategory":"Bank",
            "type":"Services"
        }
    ],
    "sg:phone":"+61 2 9948 6966",
    "sg:postcode":"2093",
    "sg:province":"NSW",
    "sg:tags":[
        "broker",
        "mortgage"
    ],
    "wof:name":"Mortgage Choice",
    "wof:placetype":"venue"
},
  "geometry": {"coordinates":[151.26550293,-33.7945518494],"type":"Point"}
}