{
  "type": "Feature",
  "properties": {
    "addr:full":"3 Wilson St Newtown NSW 2042",
    "addr:housenumber":"3",
    "addr:postcode":"2042",
    "addr:street":"Wilson St",
    "iso:country":"AU",
    "sg:address":"3 Wilson St",
    "sg:city":"Newtown",
    "sg:classifiers":[
        {
            "category":"Shopping",
            "subcategory":"Music",
            "type":"Retail Goods"
        }
    ],
    "sg:phone":"+61 2 9550 6056",
    "sg:postcode":"2042",
    "sg:province":"NSW",
    "sg:tags":[
        "store"
    ],
    "wof:name":"Egg Records",
    "wof:placetype":"venue"
},
  "geometry": {"coordinates":[151.179474,-33.897263],"type":"Point"}
}