{
  "type": "Feature",
  "properties": {
    "addr:full":"Cnr South Pine & Gympie Rds Strathpine QLD 4500",
    "addr:postcode":"4500",
    "addr:street":"Cnr South Pine & Gympie Rds",
    "iso:country":"AU",
    "sg:address":"Cnr South Pine & Gympie Rds",
    "sg:city":"Strathpine",
    "sg:classifiers":[
        {
            "category":"Health Services",
            "subcategory":"Doctor",
            "type":"Services"
        }
    ],
    "sg:phone":"+61 7 3881 3995",
    "sg:postcode":"4500",
    "sg:province":"QLD",
    "sg:tags":[
        "podiatrist"
    ],
    "wof:name":"Christopher Hope",
    "wof:placetype":"venue"
},
  "geometry": {"coordinates":[152.991455078,-27.3119659424],"type":"Point"}
}