{
  "type": "Feature",
  "properties": {
    "iso:country":"AU",
    "sg:address":"7 Galyung Rd",
    "sg:city":"Bunbury",
    "sg:classifiers":[
        {
            "category":"Building & Trades",
            "subcategory":"Construction",
            "type":"Services"
        }
    ],
    "sg:phone":"+61 418 950 649",
    "sg:postcode":"6230",
    "sg:province":"WA",
    "sg:tags":[
        "polishing",
        "sanding",
        "floor"
    ],
    "wof:name":"Don Clemson Floorsanding",
    "wof:placetype":"venue"
},
  "geometry": {"coordinates":[115.65593,-33.352211],"type":"Point"}
}