{
  "type": "Feature",
  "properties": {
    "iso:country":"AU",
    "sg:address":"208 Caves Beach Rd",
    "sg:city":"Caves Beach",
    "sg:classifiers":[
        {
            "category":"Home & Garden",
            "subcategory":"Building Materials",
            "type":"Retail Goods"
        }
    ],
    "sg:phone":"+61 2 4971 3860",
    "sg:postcode":"2281",
    "sg:province":"NSW",
    "sg:tags":[
        "balustrading"
    ],
    "wof:name":"C & A Cooper Woodturning",
    "wof:placetype":"venue"
},
  "geometry": {"coordinates":[151.64317321799999,-33.1175308228],"type":"Point"}
}