{
  "type": "Feature",
  "properties": {
    "iso:country":"AU",
    "sg:address":"87 Bateman Rd",
    "sg:city":"Mt Pleasant",
    "sg:classifiers":[
        {
            "category":"Building & Trades",
            "subcategory":"Construction",
            "type":"Services"
        }
    ],
    "sg:phone":"+61 8 9364 2765",
    "sg:postcode":"6153",
    "sg:province":"WA",
    "sg:tags":[
        "contractor"
    ],
    "wof:name":"Miriudo Constructions",
    "wof:placetype":"venue"
},
  "geometry": {"coordinates":[115.852051,-32.031914],"type":"Point"}
}