{
  "type": "Feature",
  "properties": {
    "addr:full":"8 Govan St Seaford VIC 3198",
    "addr:housenumber":"8",
    "addr:postcode":"3198",
    "addr:street":"Govan St",
    "iso:country":"AU",
    "sg:address":"8 Govan St",
    "sg:city":"Seaford",
    "sg:classifiers":[
        {
            "category":"Autos & Motor Vehicles",
            "subcategory":"Automobile Sales",
            "type":"Retail Goods"
        }
    ],
    "sg:phone":"+61 13 26 26",
    "sg:postcode":"3198",
    "sg:province":"VIC",
    "sg:tags":[
        "car",
        "new"
    ],
    "wof:name":"Trading Post",
    "wof:placetype":"venue"
},
  "geometry": {"coordinates":[145.13247680699999,-38.1145744324],"type":"Point"}
}