{
  "type": "Feature",
  "properties": {
    "addr:full":"Shop 1/1- 3 Bridges St Kurnell NSW 2231",
    "addr:housenumber":"shop 1 / 1 3",
    "addr:postcode":"2231",
    "addr:street":"Bridges St",
    "iso:country":"AU",
    "sg:address":"Shop 1/1- 3 Bridges St",
    "sg:city":"Kurnell",
    "sg:classifiers":[
        {
            "category":"Fast Food",
            "type":"Food & Drink"
        }
    ],
    "sg:phone":"+61 2 9668 8994",
    "sg:postcode":"2231",
    "sg:province":"NSW",
    "sg:tags":[
        "away",
        "take"
    ],
    "wof:name":"Pizza's With Muscle-Kurnell",
    "wof:placetype":"venue"
},
  "geometry": {"coordinates":[151.209228516,-34.0116767883],"type":"Point"}
}