{
  "type": "Feature",
  "properties": {
    "addr:full":"Unit 3 15 Trade Rd Malaga WA 6090",
    "addr:housenumber":"15",
    "addr:postcode":"6090",
    "addr:street":"Trade Rd",
    "iso:country":"AU",
    "sg:address":"Unit 3 15 Trade Rd",
    "sg:city":"Malaga",
    "sg:classifiers":[
        {
            "category":"Manufacturing",
            "subcategory":"Building Materials",
            "type":"Manufacturing & Wholesale Goods"
        }
    ],
    "sg:phone":"+61 8 9249 7531",
    "sg:postcode":"6090",
    "sg:province":"WA",
    "sg:tags":[
        "equipment",
        "handling"
    ],
    "wof:name":"Pit Top Conveyor Products Pty Ltd",
    "wof:placetype":"venue"
},
  "geometry": {"coordinates":[115.895896912,-31.8594207764],"type":"Point"}
}