{
  "type": "Feature",
  "properties": {
    "addr:full":"58b Gawler Pl Adelaide SA 5000",
    "addr:housenumber":"58b",
    "addr:postcode":"5000",
    "addr:street":"Gawler Pl",
    "iso:country":"AU",
    "sg:address":"58b Gawler Pl",
    "sg:city":"Adelaide",
    "sg:classifiers":[
        {
            "category":"Personal",
            "type":"Services"
        }
    ],
    "sg:phone":"+61 8 8232 2115",
    "sg:postcode":"5000",
    "sg:province":"SA",
    "sg:tags":[
        "gift"
    ],
    "wof:name":"Nest Adelaide",
    "wof:placetype":"venue"
},
  "geometry": {"coordinates":[138.60206604000001,-34.9234733582],"type":"Point"}
}