{
  "type": "Feature",
  "properties": {
    "addr:full":"28 Christine Ave Miami QLD 4220",
    "addr:housenumber":"28",
    "addr:postcode":"4220",
    "addr:street":"Christine Ave",
    "iso:country":"AU",
    "sg:address":"28 Christine Ave",
    "sg:city":"Miami",
    "sg:classifiers":[
        {
            "category":"Retail",
            "subcategory":"Auto Repair",
            "type":"Services"
        }
    ],
    "sg:phone":"+61 7 5535 5338",
    "sg:postcode":"4220",
    "sg:province":"QLD",
    "sg:tags":[
        "repairer",
        "motor",
        "engineer"
    ],
    "wof:name":"Milburn Motors",
    "wof:placetype":"venue"
},
  "geometry": {"coordinates":[153.4425354,-28.0774078369],"type":"Point"}
}