{
  "type": "Feature",
  "properties": {
    "addr:full":"Unit 11, 160 Churchill Rd Cavan SA 5094",
    "addr:housenumber":"160",
    "addr:postcode":"5094",
    "addr:street":"Churchill Rd",
    "iso:country":"AU",
    "sg:address":"Unit 11, 160 Churchill Rd",
    "sg:city":"Cavan",
    "sg:classifiers":[
        {
            "category":"Home & Garden",
            "subcategory":"Hardware",
            "type":"Retail Goods"
        }
    ],
    "sg:phone":"+61 8 8349 5864",
    "sg:postcode":"5094",
    "sg:province":"SA",
    "sg:tags":[
        "trolley",
        "truck",
        "hand"
    ],
    "wof:name":"TDP Mobile Services",
    "wof:placetype":"venue"
},
  "geometry": {"coordinates":[138.59426879899999,-34.8316993713],"type":"Point"}
}