{
  "type": "Feature",
  "properties": {
    "iso:country":"AU",
    "sg:address":"12-14 Ormond Pde",
    "sg:city":"Hurstville",
    "sg:classifiers":[
        {
            "category":"Health Services",
            "subcategory":"Dentist",
            "type":"Services"
        }
    ],
    "sg:phone":"+61 2 9262 9318",
    "sg:postcode":"2220",
    "sg:province":"NSW",
    "wof:name":"Austin Bruce W",
    "wof:placetype":"venue"
},
  "geometry": {"coordinates":[151.10316467300001,-33.9682731628],"type":"Point"}
}