{
  "type": "Feature",
  "properties": {
    "addr:full":"7 Palings Crt Nerang QLD 4211",
    "addr:housenumber":"7",
    "addr:postcode":"4211",
    "addr:street":"Palings Crt",
    "iso:country":"AU",
    "sg:address":"7 Palings Crt",
    "sg:city":"Nerang",
    "sg:classifiers":[
        {
            "category":"Professional",
            "subcategory":"Computer Services",
            "type":"Services"
        }
    ],
    "sg:phone":"+61 7 5596 1377",
    "sg:postcode":"4211",
    "sg:province":"QLD",
    "sg:tags":[
        "technical",
        "support"
    ],
    "wof:name":"Abcom I.T. Services",
    "wof:placetype":"venue"
},
  "geometry": {"coordinates":[153.34068298299999,-27.9808330536],"type":"Point"}
}