{
  "type": "Feature",
  "properties": {
    "iso:country":"AU",
    "sg:address":"5 Petersen Ave",
    "sg:city":"Southport",
    "sg:classifiers":[
        {
            "category":"Real Estate",
            "subcategory":"Developer",
            "type":"Services"
        }
    ],
    "sg:phone":"+61 7 5532 2200",
    "sg:postcode":"4215",
    "sg:province":"QLD",
    "sg:tags":[
        "development"
    ],
    "wof:name":"Eastern Pacific Developments Pty Ltd",
    "wof:placetype":"venue"
},
  "geometry": {"coordinates":[153.41047668499999,-27.987323761],"type":"Point"}
}