{
  "type": "Feature",
  "properties": {
    "addr:full":"1 Ellis Rd Preston Beach WA 6210",
    "addr:housenumber":"1",
    "addr:postcode":"6210",
    "addr:street":"Ellis Rd",
    "iso:country":"AU",
    "sg:address":"1 Ellis Rd",
    "sg:city":"Preston Beach",
    "sg:classifiers":[
        {
            "category":"Farming",
            "subcategory":"Farm & Veterinary Services",
            "type":"Manufacturing & Wholesale Goods"
        }
    ],
    "sg:phone":"+61 8 9739 1152",
    "sg:postcode":"6210",
    "sg:province":"WA",
    "sg:tags":[
        "deer",
        "farmer"
    ],
    "wof:name":"Preston Park Deer Farm",
    "wof:placetype":"venue"
},
  "geometry": {"coordinates":[115.728363,-32.528973],"type":"Point"}
}