{
  "type": "Feature",
  "properties": {
    "iso:country":"AU",
    "sg:address":"178 Burgundy St",
    "sg:city":"Heidelberg",
    "sg:classifiers":[
        {
            "category":"Fast Food",
            "type":"Food & Drink"
        }
    ],
    "sg:phone":"+61 3 9459 9433",
    "sg:postcode":"3084",
    "sg:province":"VIC",
    "sg:tags":[
        "away",
        "take"
    ],
    "wof:name":"A2z Noodle N Rice",
    "wof:placetype":"venue"
},
  "geometry": {"coordinates":[145.06410217300001,-37.7557983398],"type":"Point"}
}