{
  "type": "Feature",
  "properties": {
    "addr:full":"Ste 27/ 15 Barron Pde Joondalup WA 6027",
    "addr:housenumber":"/ 15",
    "addr:postcode":"6027",
    "addr:street":"Barron Pde",
    "iso:country":"AU",
    "sg:address":"Ste 27/ 15 Barron Pde",
    "sg:city":"Joondalup",
    "sg:classifiers":[
        {
            "category":"Professional",
            "subcategory":"Business Services",
            "type":"Services"
        }
    ],
    "sg:phone":"+61 8 9305 8004",
    "sg:postcode":"6027",
    "sg:province":"WA",
    "sg:tags":[
        "drafting"
    ],
    "wof:name":"Colin Atkinson Design & Drafting",
    "wof:placetype":"venue"
},
  "geometry": {"coordinates":[115.767700195,-31.7503623962],"type":"Point"}
}