{
  "type": "Feature",
  "properties": {
    "iso:country":"AU",
    "sg:address":"PO Box 4962",
    "sg:city":", Robina Town Centre Robina",
    "sg:classifiers":[
        {
            "category":"Professional",
            "subcategory":"Engineering",
            "type":"Services"
        }
    ],
    "sg:phone":"+61 7 5580 8075",
    "sg:postcode":"4230",
    "sg:province":"QLD",
    "sg:tags":[
        "consulting",
        "engineer"
    ],
    "wof:name":"Arthur Kay Consulting Services",
    "wof:placetype":"venue"
},
  "geometry": {"coordinates":[153.38531494099999,-28.0774707794],"type":"Point"}
}