{
  "type": "Feature",
  "properties": {
    "addr:full":"12 Windermere Crt Woodcroft SA 5162",
    "addr:housenumber":"12",
    "addr:postcode":"5162",
    "addr:street":"Windermere Crt",
    "iso:country":"AU",
    "sg:address":"12 Windermere Crt",
    "sg:city":"Woodcroft",
    "sg:classifiers":[
        {
            "category":"Personal",
            "subcategory":"Beauty Salon",
            "type":"Services"
        }
    ],
    "sg:phone":"+61 421 184 400",
    "sg:postcode":"5162",
    "sg:province":"SA",
    "sg:tags":[
        "hairdresser"
    ],
    "wof:name":"A+ Hair & Beauty",
    "wof:placetype":"venue"
},
  "geometry": {"coordinates":[138.55317688,-35.0939865112],"type":"Point"}
}