{
  "type": "Feature",
  "properties": {
    "addr:full":"27 Hamilton St Bassendean WA 6054",
    "addr:housenumber":"27",
    "addr:postcode":"6054",
    "addr:street":"Hamilton St",
    "iso:country":"AU",
    "sg:address":"27 Hamilton St",
    "sg:city":"Bassendean",
    "sg:classifiers":[
        {
            "category":"Health Services",
            "subcategory":"Nursing And Care Facility",
            "type":"Services"
        }
    ],
    "sg:phone":"+61 8 9279 4258",
    "sg:postcode":"6054",
    "sg:province":"WA",
    "sg:tags":[
        "home"
    ],
    "wof:name":"Bassendean Aged Care",
    "wof:placetype":"venue"
},
  "geometry": {"coordinates":[115.951370239,-31.9053020477],"type":"Point"}
}