{
  "type": "Feature",
  "properties": {
    "addr:full":"Shop 2 Centro Springwood Springwood QLD 4127",
    "addr:housenumber":"shop 2",
    "addr:postcode":"4127",
    "iso:country":"AU",
    "sg:address":"Shop 2",
    "sg:city":"Centro Springwood Springwood",
    "sg:classifiers":[
        {
            "category":"Real Estate",
            "subcategory":"Real Estate Agent",
            "type":"Services"
        }
    ],
    "sg:phone":"+61 7 3208 0377",
    "sg:postcode":"4127",
    "sg:province":"QLD",
    "wof:name":"Raine & Horne (Qld) Pty Ltd",
    "wof:placetype":"venue"
},
  "geometry": {"coordinates":[153.13616943400001,-27.6143341064],"type":"Point"}
}