{
  "type": "Feature",
  "properties": {
    "addr:full":"124 Wicks Rd North Ryde NSW 2113",
    "addr:housenumber":"124",
    "addr:postcode":"2113",
    "addr:street":"Wicks Rd",
    "iso:country":"AU",
    "sg:address":"124 Wicks Rd",
    "sg:city":"North Ryde",
    "sg:classifiers":[
        {
            "category":"Fast Food",
            "type":"Food & Drink"
        }
    ],
    "sg:phone":"+61 2 9878 3833",
    "sg:postcode":"2113",
    "sg:province":"NSW",
    "sg:tags":[
        "away",
        "take"
    ],
    "wof:name":"De Malaya Restaurant",
    "wof:placetype":"venue"
},
  "geometry": {"coordinates":[151.12858581500001,-33.792640686],"type":"Point"}
}