{
  "type": "Feature",
  "properties": {
    "addr:full":"76 Hector St Osborne Park WA 6017",
    "addr:housenumber":"76",
    "addr:postcode":"6017",
    "addr:street":"Hector St",
    "iso:country":"AU",
    "sg:address":"76 Hector St",
    "sg:city":"Osborne Park",
    "sg:classifiers":[
        {
            "category":"Home & Garden",
            "subcategory":"Hardware",
            "type":"Retail Goods"
        }
    ],
    "sg:phone":"+61 8 9445 9711",
    "sg:postcode":"6017",
    "sg:province":"WA",
    "sg:tags":[
        "plumber",
        "supply"
    ],
    "wof:name":"Tradelink Plumbing Centres",
    "wof:placetype":"venue"
},
  "geometry": {"coordinates":[115.823257446,-31.9043045044],"type":"Point"}
}