{
  "type": "Feature",
  "properties": {
    "addr:full":"96 Marine Pde Kingscliff NSW 2487",
    "addr:housenumber":"96",
    "addr:postcode":"2487",
    "addr:street":"Marine Pde",
    "iso:country":"AU",
    "sg:address":"96 Marine Pde",
    "sg:city":"Kingscliff",
    "sg:classifiers":[
        {
            "category":"Personal",
            "subcategory":"Beauty Salon",
            "type":"Services"
        }
    ],
    "sg:phone":"+61 2 6674 0506",
    "sg:postcode":"2487",
    "sg:province":"NSW",
    "sg:tags":[
        "hairdresser"
    ],
    "wof:name":"Kerrie & Karina Hair By",
    "wof:placetype":"venue"
},
  "geometry": {"coordinates":[153.576370239,-28.2555122375],"type":"Point"}
}