{
  "type": "Feature",
  "properties": {
    "addr:full":"Whitney Pl Weston ACT 2611",
    "addr:postcode":"2611",
    "addr:street":"Pl",
    "iso:country":"AU",
    "sg:address":"Whitney Pl",
    "sg:city":"Weston",
    "sg:classifiers":[
        {
            "category":"Building & Trades",
            "subcategory":"Plumbing",
            "type":"Services"
        }
    ],
    "sg:phone":"+61 2 6287 7888",
    "sg:postcode":"2611",
    "sg:province":"ACT",
    "sg:tags":[
        "pump",
        "repairer"
    ],
    "wof:name":"Weston Pool Shop",
    "wof:placetype":"venue"
},
  "geometry": {"coordinates":[149.05340576200001,-35.3417625427],"type":"Point"}
}