{
  "type": "Feature",
  "properties": {
    "iso:country":"AU",
    "sg:address":"PO Box 685",
    "sg:city":"Dunsborough",
    "sg:classifiers":[
        {
            "category":"Social Services",
            "subcategory":"Retirement Home",
            "type":"Services"
        }
    ],
    "sg:phone":"+61 8 9759 1960",
    "sg:postcode":"6281",
    "sg:province":"WA",
    "sg:tags":[
        "environmental",
        "consultant",
        "pollution"
    ],
    "wof:name":"Ecosystem Solutions Pty Ltd",
    "wof:placetype":"venue"
},
  "geometry": {"coordinates":[115.102020264,-33.6174812317],"type":"Point"}
}