{
  "type": "Feature",
  "properties": {
    "iso:country":"AU",
    "sg:address":"2 Marles St",
    "sg:city":"Coffs Harbour",
    "sg:classifiers":[
        {
            "category":"Building & Trades",
            "subcategory":"Construction",
            "type":"Services"
        }
    ],
    "sg:phone":"+61 2 6652 2828",
    "sg:postcode":"2450",
    "sg:province":"NSW",
    "sg:tags":[
        "earth",
        "excavating",
        "moving",
        "contractor"
    ],
    "wof:name":"Dorrington A G & R",
    "wof:placetype":"venue"
},
  "geometry": {"coordinates":[153.129761,-30.297625],"type":"Point"}
}