{
  "type": "Feature",
  "properties": {
    "iso:country":"AU",
    "sg:address":"Ste 8/ 540 Sydney Rd",
    "sg:city":"Seaforth",
    "sg:classifiers":[
        {
            "category":"Banks & Credit Unions",
            "subcategory":"Financial Services",
            "type":"Services"
        }
    ],
    "sg:phone":"+61 2 9949 7398",
    "sg:postcode":"2092",
    "sg:province":"NSW",
    "sg:tags":[
        "loan",
        "finance",
        "mortgage"
    ],
    "wof:name":"Symmetry Finance Solutions Pty Ltd",
    "wof:placetype":"venue"
},
  "geometry": {"coordinates":[151.251708984,-33.7965545654],"type":"Point"}
}