{
  "type": "Feature",
  "properties": {
    "addr:full":"237a Whitehorse Rd Balwyn VIC 3103",
    "addr:housenumber":"237a",
    "addr:postcode":"3103",
    "addr:street":"Whitehorse Rd",
    "iso:country":"AU",
    "sg:address":"237a Whitehorse Rd",
    "sg:city":"Balwyn",
    "sg:classifiers":[
        {
            "category":"Manufacturing",
            "subcategory":"Musical Instruments",
            "type":"Manufacturing & Wholesale Goods"
        }
    ],
    "sg:phone":"+61 3 9817 6644",
    "sg:postcode":"3103",
    "sg:province":"VIC",
    "sg:tags":[
        "repair",
        "maker"
    ],
    "wof:name":"Buckmaster Roger",
    "wof:placetype":"venue"
},
  "geometry": {"coordinates":[145.075881958,-37.8120307922],"type":"Point"}
}