{
  "type": "Feature",
  "properties": {
    "iso:country":"AU",
    "sg:address":"PO Box 245",
    "sg:city":"Moonta",
    "sg:classifiers":[
        {
            "category":"Utilities",
            "type":"Services"
        }
    ],
    "sg:phone":"+61 8 8825 1800",
    "sg:postcode":"5558",
    "sg:province":"SA",
    "sg:tags":[
        "refrigeration",
        "industrial",
        "commercial",
        "retail"
    ],
    "wof:name":"Copper Coast Refrigeration",
    "wof:placetype":"venue"
},
  "geometry": {"coordinates":[137.59390258799999,-34.0681495667],"type":"Point"}
}