{
  "type": "Feature",
  "properties": {
    "addr:full":"124 Long St Smithfield NSW 2164",
    "addr:housenumber":"124",
    "addr:postcode":"2164",
    "addr:street":"Long St",
    "iso:country":"AU",
    "sg:address":"124 Long St",
    "sg:city":"Smithfield",
    "sg:classifiers":[
        {
            "category":"Professional",
            "subcategory":"Engineering",
            "type":"Services"
        }
    ],
    "sg:phone":"+61 2 9609 7833",
    "sg:postcode":"2164",
    "sg:province":"NSW",
    "sg:tags":[
        "manufacturing",
        "engineer"
    ],
    "wof:name":"Andrews & Rech Pty Ltd",
    "wof:placetype":"venue"
},
  "geometry": {"coordinates":[150.93278503400001,-33.8410797119],"type":"Point"}
}