{
  "type": "Feature",
  "properties": {
    "iso:country":"AU",
    "sg:address":"PO Box 316",
    "sg:city":"Sans Souci",
    "sg:classifiers":[
        {
            "category":"Professional",
            "subcategory":"Detective & Security Services",
            "type":"Services"
        }
    ],
    "sg:phone":"+61 411 880 907",
    "sg:postcode":"2219",
    "sg:province":"NSW",
    "sg:tags":[
        "guard",
        "patrol"
    ],
    "wof:name":"Oceania Security Services Pty Ltd",
    "wof:placetype":"venue"
},
  "geometry": {"coordinates":[151.132172,-33.992779],"type":"Point"}
}