{
  "type": "Feature",
  "properties": {
    "addr:full":"16 - 18 Coulson Way Canning Vale WA 6155",
    "addr:housenumber":"18",
    "addr:postcode":"6155",
    "addr:street":"Coulson Way",
    "iso:country":"AU",
    "sg:address":"16 - 18",
    "sg:city":"Coulson Way Canning Vale",
    "sg:classifiers":[
        {
            "category":"Manufacturing",
            "subcategory":"Wood Products",
            "type":"Manufacturing & Wholesale Goods"
        }
    ],
    "sg:phone":"+61 8 9455 1012",
    "sg:postcode":"6155",
    "sg:province":"WA",
    "sg:tags":[
        "resin"
    ],
    "wof:name":"Nuplex Industries (Aust) Pty Ltd",
    "wof:placetype":"venue"
},
  "geometry": {"coordinates":[115.929512,-32.055706],"type":"Point"}
}