{
  "type": "Feature",
  "properties": {
    "addr:full":"Lvl2/ 258 Little Bourke St Melbourne VIC 3000",
    "addr:housenumber":"258",
    "addr:postcode":"3000",
    "addr:street":"Little Bourke St",
    "iso:country":"AU",
    "sg:address":"Lvl2/ 258 Little Bourke St",
    "sg:city":"Melbourne",
    "sg:classifiers":[
        {
            "category":"Retail",
            "subcategory":"Repair Shop",
            "type":"Services"
        }
    ],
    "sg:phone":"+61 3 9662 9022",
    "sg:postcode":"3000",
    "sg:province":"VIC",
    "sg:tags":[
        "mending",
        "clothing",
        "alteration"
    ],
    "wof:name":"Marcella Alterations",
    "wof:placetype":"venue"
},
  "geometry": {"coordinates":[144.96498107900001,-37.812461853],"type":"Point"}
}