{
  "type": "Feature",
  "properties": {
    "iso:country":"AU",
    "sg:address":"392 Burke Rd",
    "sg:city":"Camberwell",
    "sg:classifiers":[
        {
            "category":"Professional",
            "subcategory":"Art Services",
            "type":"Services"
        }
    ],
    "sg:phone":"+61 3 9889 9711",
    "sg:postcode":"3124",
    "sg:province":"VIC",
    "sg:tags":[
        "interior",
        "designer"
    ],
    "wof:name":"Arthur Taylor Pty Ltd",
    "wof:placetype":"venue"
},
  "geometry": {"coordinates":[145.054153442,-37.8455696106],"type":"Point"}
}