{
  "type": "Feature",
  "properties": {
    "addr:full":"Building 2B, 18 Torbey St Sunnybank Hills QLD 4109",
    "addr:housenumber":"2b 18",
    "addr:postcode":"4109",
    "addr:street":"Building;Torbey St",
    "iso:country":"AU",
    "sg:address":"Building 2B, 18 Torbey St",
    "sg:city":"Sunnybank Hills",
    "sg:classifiers":[
        {
            "category":"Personal",
            "subcategory":"Massage",
            "type":"Services"
        }
    ],
    "sg:phone":"+61 7 3345 3333",
    "sg:postcode":"4109",
    "sg:province":"QLD",
    "sg:tags":[
        "therapy"
    ],
    "wof:name":"Russell Tatlow RMT",
    "wof:placetype":"venue"
},
  "geometry": {"coordinates":[153.05825805699999,-27.5870456696],"type":"Point"}
}