{
  "type": "Feature",
  "properties": {
    "iso:country":"AU",
    "sg:address":"18 Prosser St",
    "sg:city":"South Bunbury",
    "sg:classifiers":[
        {
            "category":"Education",
            "subcategory":"Special Training",
            "type":"Public Place"
        }
    ],
    "sg:phone":"+61 8 9791 4398",
    "sg:postcode":"6230",
    "sg:province":"WA",
    "sg:tags":[
        "tuition-educational"
    ],
    "wof:name":"1 on 1 Tutoring",
    "wof:placetype":"venue"
},
  "geometry": {"coordinates":[115.642197,-33.339436],"type":"Point"}
}