{
  "type": "Feature",
  "properties": {
    "iso:country":"AU",
    "sg:address":"104 Curlewis St",
    "sg:city":"Swan Hill",
    "sg:classifiers":[
        {
            "category":"Retail",
            "subcategory":"Auto Repair",
            "type":"Services"
        }
    ],
    "sg:phone":"+61 3 5032 1683",
    "sg:postcode":"3585",
    "sg:province":"NSW",
    "sg:tags":[
        "automotive",
        "air conditioning"
    ],
    "wof:name":"Pioneer & Northern Radiators",
    "wof:placetype":"venue"
},
  "geometry": {"coordinates":[143.56012,-35.336365],"type":"Point"}
}