{
  "type": "Feature",
  "properties": {
    "addr:full":"Suite 6/ 29 Windsor Rd Kellyville NSW 2155",
    "addr:postcode":"2155",
    "addr:street":"Windsor Rd",
    "iso:country":"AU",
    "sg:address":"Suite 6/ 29 Windsor Rd",
    "sg:city":"Kellyville",
    "sg:classifiers":[
        {
            "category":"Banks & Credit Unions",
            "subcategory":"Investment Brokerage",
            "type":"Services"
        }
    ],
    "sg:phone":"+61 2 9629 1559",
    "sg:postcode":"2155",
    "sg:province":"NSW",
    "sg:tags":[
        "finance",
        "broker"
    ],
    "wof:name":"Allcorp Finance",
    "wof:placetype":"venue"
},
  "geometry": {"coordinates":[150.95838928200001,-33.7125053406],"type":"Point"}
}