{
  "type": "Feature",
  "properties": {
    "addr:full":"10 Cottswold Pl Wantirna South VIC 3152",
    "addr:housenumber":"10",
    "addr:postcode":"3152",
    "addr:street":"Cottswold Pl",
    "iso:country":"AU",
    "sg:address":"10 Cottswold Pl",
    "sg:city":"Wantirna South",
    "sg:classifiers":[
        {
            "category":"Building & Trades",
            "subcategory":"Landscaping Services",
            "type":"Services"
        }
    ],
    "sg:phone":"+61 414 507 714",
    "sg:postcode":"3152",
    "sg:province":"VIC",
    "sg:tags":[
        "stump",
        "tree",
        "felling",
        "removal"
    ],
    "wof:name":"Don's Tree Lopping",
    "wof:placetype":"venue"
},
  "geometry": {"coordinates":[145.239303589,-37.8660392761],"type":"Point"}
}