{
  "type": "Feature",
  "properties": {
    "addr:full":"Fcty 2/ 23 Nelson St Moorabbin VIC 3189",
    "addr:housenumber":"/ 23",
    "addr:postcode":"3189",
    "addr:street":"Nelson St",
    "iso:country":"AU",
    "sg:address":"Fcty 2/ 23 Nelson St",
    "sg:city":"Moorabbin",
    "sg:classifiers":[
        {
            "category":"Building & Trades",
            "subcategory":"Construction",
            "type":"Services"
        }
    ],
    "sg:phone":"+61 3 9532 3806",
    "sg:postcode":"3189",
    "sg:province":"VIC",
    "sg:tags":[
        "fencing",
        "contractor"
    ],
    "wof:name":"A A JLM Fencing",
    "wof:placetype":"venue"
},
  "geometry": {"coordinates":[145.07081604000001,-37.9445953369],"type":"Point"}
}