{
  "type": "Feature",
  "properties": {
    "iso:country":"AU",
    "sg:address":"Shop 5, 116 Tannery St",
    "sg:city":"Unanderra",
    "sg:classifiers":[
        {
            "category":"Personal",
            "subcategory":"Beauty Salon",
            "type":"Services"
        }
    ],
    "sg:phone":"+61 2 4271 4442",
    "sg:postcode":"2526",
    "sg:province":"NSW",
    "sg:tags":[
        "hairdresser"
    ],
    "wof:name":"Lush Hair Gallery",
    "wof:placetype":"venue"
},
  "geometry": {"coordinates":[150.842407227,-34.4535102844],"type":"Point"}
}