{
  "type": "Feature",
  "properties": {
    "addr:full":"5/ 26 Nicklin Way Minyama QLD 4575",
    "addr:housenumber":"/ 26",
    "addr:postcode":"4575",
    "addr:street":"Nicklin Way",
    "iso:country":"AU",
    "sg:address":"5/ 26",
    "sg:city":"Nicklin Way Minyama",
    "sg:classifiers":[
        {
            "category":"Wholesale",
            "subcategory":"Medical Equipment & Supplies",
            "type":"Manufacturing & Wholesale Goods"
        }
    ],
    "sg:phone":"+61 7 5477 7166",
    "sg:postcode":"4575",
    "sg:province":"QLD",
    "sg:tags":[
        "aid",
        "care",
        "health",
        "home"
    ],
    "wof:name":"Nancarrows Bed Barn",
    "wof:placetype":"venue"
},
  "geometry": {"coordinates":[153.12217699999999,-26.700069],"type":"Point"}
}