{
  "type": "Feature",
  "properties": {
    "addr:full":"86 Nicholson St Fitzroy VIC 3065",
    "addr:housenumber":"86",
    "addr:postcode":"3065",
    "addr:street":"Nicholson St",
    "iso:country":"AU",
    "sg:address":"86 Nicholson St",
    "sg:city":"Fitzroy",
    "sg:classifiers":[
        {
            "category":"Health Services",
            "subcategory":"Chiropractor",
            "type":"Services"
        }
    ],
    "sg:phone":"+61 3 9416 0082",
    "sg:postcode":"3065",
    "sg:province":"VIC",
    "wof:name":"Aris Peter",
    "wof:placetype":"venue"
},
  "geometry": {"coordinates":[144.9740448,-37.8042831421],"type":"Point"}
}