{
  "type": "Feature",
  "properties": {
    "iso:country":"AU",
    "sg:address":"9 Bundarra Pl",
    "sg:city":"West Moonah",
    "sg:classifiers":[
        {
            "category":"Building & Trades",
            "subcategory":"Construction",
            "type":"Services"
        }
    ],
    "sg:phone":"+61 3 6272 2898",
    "sg:postcode":"7009",
    "sg:province":"TAS",
    "sg:tags":[
        "contractor"
    ],
    "wof:name":"D C & A M Duggan",
    "wof:placetype":"venue"
},
  "geometry": {"coordinates":[147.28834533700001,-42.8488502502],"type":"Point"}
}