{
  "type": "Feature",
  "properties": {
    "iso:country":"AU",
    "sg:address":"Shop 12",
    "sg:city":"Duncraig Shopping Centre Duncraig",
    "sg:classifiers":[
        {
            "category":"Food & Beverages",
            "subcategory":"Liquor & Beverages",
            "type":"Retail Goods"
        }
    ],
    "sg:phone":"+61 8 9447 5288",
    "sg:postcode":"6023",
    "sg:province":"WA",
    "sg:tags":[
        "store"
    ],
    "wof:name":"Vintage Cellars",
    "wof:placetype":"venue"
},
  "geometry": {"coordinates":[115.76625824,-31.8337917328],"type":"Point"}
}