{
  "type": "Feature",
  "properties": {
    "addr:full":"36b Semaphore Rd Semaphore SA 5019",
    "addr:housenumber":"36b",
    "addr:postcode":"5019",
    "addr:street":"Semaphore Rd",
    "iso:country":"AU",
    "sg:address":"36b Semaphore Rd",
    "sg:city":"Semaphore",
    "sg:classifiers":[
        {
            "category":"Cafe",
            "type":"Food & Drink"
        }
    ],
    "sg:phone":"+61 8 8242 7919",
    "sg:postcode":"5019",
    "sg:province":"SA",
    "wof:name":"Cafe Froot",
    "wof:placetype":"venue"
},
  "geometry": {"coordinates":[138.48434448200001,-34.8391838074],"type":"Point"}
}