{
  "type": "Feature",
  "properties": {
    "addr:full":"60 Fleet St Carlton NSW 2218",
    "addr:housenumber":"60",
    "addr:postcode":"2218",
    "addr:street":"Fleet St",
    "iso:country":"AU",
    "sg:address":"60 Fleet St",
    "sg:city":"Carlton",
    "sg:classifiers":[
        {
            "category":"Shopping",
            "subcategory":"Musical Instruments",
            "type":"Retail Goods"
        }
    ],
    "sg:phone":"+61 409 825 950",
    "sg:postcode":"2218",
    "sg:province":"NSW",
    "sg:tags":[
        "musician",
        "agent"
    ],
    "wof:name":"The Wonderbrass",
    "wof:placetype":"venue"
},
  "geometry": {"coordinates":[151.11663799999999,-33.965275],"type":"Point"}
}