{
  "type": "Feature",
  "properties": {
    "addr:full":"1/ 19 James St Burleigh Heads QLD 4220",
    "addr:housenumber":"/ 19",
    "addr:postcode":"4220",
    "addr:street":"James St",
    "iso:country":"AU",
    "sg:address":"1/ 19 James St",
    "sg:city":"Burleigh Heads",
    "sg:classifiers":[
        {
            "category":"Personal",
            "subcategory":"Massage",
            "type":"Services"
        }
    ],
    "sg:phone":"+61 404 254 781",
    "sg:postcode":"4220",
    "sg:province":"QLD",
    "sg:tags":[
        "therapy"
    ],
    "wof:name":"Rose Grosser",
    "wof:placetype":"venue"
},
  "geometry": {"coordinates":[153.451339722,-28.0892219543],"type":"Point"}
}