{
  "type": "Feature",
  "properties": {
    "addr:full":"87 Burnett St Buderim QLD 4556",
    "addr:housenumber":"87",
    "addr:postcode":"4556",
    "addr:street":"Burnett St",
    "iso:country":"AU",
    "sg:address":"87 Burnett St",
    "sg:city":"Buderim",
    "sg:classifiers":[
        {
            "category":"Restaurant",
            "type":"Food & Drink"
        }
    ],
    "sg:phone":"+61 7 5476 6288",
    "sg:postcode":"4556",
    "sg:province":"QLD",
    "wof:name":"Dec's On Buderim",
    "wof:placetype":"venue"
},
  "geometry": {"coordinates":[153.04786682100001,-26.6883163452],"type":"Point"}
}