{
  "type": "Feature",
  "properties": {
    "addr:full":"76 Crown St Wollongong NSW 2500",
    "addr:housenumber":"76",
    "addr:postcode":"2500",
    "addr:street":"Crown St",
    "iso:country":"AU",
    "sg:address":"76 Crown St",
    "sg:city":"Wollongong",
    "sg:classifiers":[
        {
            "category":"Restaurant",
            "type":"Food & Drink"
        }
    ],
    "sg:phone":"+61 2 4229 8344",
    "sg:postcode":"2500",
    "sg:province":"NSW",
    "wof:name":"Antics",
    "wof:placetype":"venue"
},
  "geometry": {"coordinates":[150.89856,-34.425541],"type":"Point"}
}