{
  "type": "Feature",
  "properties": {
    "addr:full":"173 Graham St Wonthaggi VIC 3995",
    "addr:housenumber":"173",
    "addr:postcode":"3995",
    "addr:street":"Graham St",
    "iso:country":"AU",
    "sg:address":"173 Graham St",
    "sg:city":"Wonthaggi",
    "sg:classifiers":[
        {
            "category":"Personal",
            "subcategory":"Piercing",
            "type":"Services"
        }
    ],
    "sg:phone":"+61 3 5672 1153",
    "sg:postcode":"3995",
    "sg:province":"VIC",
    "sg:tags":[
        "body",
        "ear"
    ],
    "wof:name":"Enter Hair",
    "wof:placetype":"venue"
},
  "geometry": {"coordinates":[145.58880600000001,-38.606415],"type":"Point"}
}