{
  "type": "Feature",
  "properties": {
    "iso:country":"AU",
    "sg:address":"136 Ocean St",
    "sg:city":"Edgecliff",
    "sg:classifiers":[
        {
            "category":"Professional",
            "subcategory":"Art Services",
            "type":"Services"
        }
    ],
    "sg:phone":"+61 2 9327 7112",
    "sg:postcode":"2027",
    "sg:province":"NSW",
    "sg:tags":[
        "graphic",
        "designer"
    ],
    "wof:name":"Signum Graphic Design",
    "wof:placetype":"venue"
},
  "geometry": {"coordinates":[151.237915039,-33.8813171387],"type":"Point"}
}