{
  "type": "Feature",
  "properties": {
    "addr:full":"141 Johnson St Maffra VIC 3860",
    "addr:housenumber":"141",
    "addr:postcode":"3860",
    "addr:street":"Johnson St",
    "iso:country":"AU",
    "sg:address":"141 Johnson St",
    "sg:city":"Maffra",
    "sg:classifiers":[
        {
            "category":"Health Services",
            "subcategory":"Chiropractor",
            "type":"Services"
        }
    ],
    "sg:phone":"+61 3 5141 1966",
    "sg:postcode":"3860",
    "sg:province":"VIC",
    "wof:name":"Darby Damian",
    "wof:placetype":"venue"
},
  "geometry": {"coordinates":[146.97511291500001,-37.9648857117],"type":"Point"}
}