{
  "type": "Feature",
  "properties": {
    "iso:country":"AU",
    "sg:address":"6 Shute Crs",
    "sg:city":"Paradise Point",
    "sg:classifiers":[
        {
            "category":"Building & Trades",
            "subcategory":"Construction",
            "type":"Services"
        }
    ],
    "sg:phone":"+61 7 5564 2650",
    "sg:postcode":"4216",
    "sg:province":"QLD",
    "sg:tags":[
        "ceiling"
    ],
    "wof:name":"McCullum & Gould Constructions",
    "wof:placetype":"venue"
},
  "geometry": {"coordinates":[153.387573242,-27.8792877197],"type":"Point"}
}