{
  "type": "Feature",
  "properties": {
    "addr:full":"36 Colledge Rd Karana Downs QLD 4306",
    "addr:housenumber":"36",
    "addr:postcode":"4306",
    "addr:street":"Colledge Rd",
    "iso:country":"AU",
    "sg:address":"36 Colledge Rd",
    "sg:city":"Karana Downs",
    "sg:classifiers":[
        {
            "category":"Social Services",
            "subcategory":"Child Care",
            "type":"Services"
        }
    ],
    "sg:phone":"+61 7 3201 1145",
    "sg:postcode":"4306",
    "sg:province":"QLD",
    "wof:name":"Karana Early Education Centre",
    "wof:placetype":"venue"
},
  "geometry": {"coordinates":[152.810836792,-27.5526447296],"type":"Point"}
}