{
  "type": "Feature",
  "properties": {
    "addr:full":"135 Poole St Welshpool WA 6106",
    "addr:housenumber":"135",
    "addr:postcode":"6106",
    "addr:street":"Poole St",
    "iso:country":"AU",
    "sg:address":"135 Poole St",
    "sg:city":"Welshpool",
    "sg:classifiers":[
        {
            "category":"Home & Garden",
            "subcategory":"Hardware",
            "type":"Retail Goods"
        }
    ],
    "sg:phone":"+61 8 9358 5089",
    "sg:postcode":"6106",
    "sg:province":"WA",
    "sg:tags":[
        "generating",
        "set",
        "generator"
    ],
    "sg:website":"http://www.hipower.com.au",
    "wof:name":"HiPower Australia",
    "wof:placetype":"venue"
},
  "geometry": {"coordinates":[115.94589233400001,-31.9936408997],"type":"Point"}
}