{
  "type": "Feature",
  "properties": {
    "iso:country":"AU",
    "sg:address":"Unit 41, Brendale Business Park, 193 South Pine Rd",
    "sg:city":"Brendale",
    "sg:classifiers":[
        {
            "category":"Recreation",
            "subcategory":"Boat Charter",
            "type":"Entertainment"
        }
    ],
    "sg:phone":"+61 427 557 403",
    "sg:postcode":"4500",
    "sg:province":"QLD",
    "sg:tags":[
        "canopy",
        "motor"
    ],
    "wof:name":"All Alloy Creations",
    "wof:placetype":"venue"
},
  "geometry": {"coordinates":[152.97962951700001,-27.3262500763],"type":"Point"}
}