{
  "type": "Feature",
  "properties": {
    "addr:full":"Cnr Church & George Sts Parramatta NSW 2150",
    "addr:postcode":"2150",
    "iso:country":"AU",
    "sg:address":"Cnr Church & George Sts",
    "sg:city":"Parramatta",
    "sg:classifiers":[
        {
            "category":"Banks & Credit Unions",
            "subcategory":"Bank",
            "type":"Services"
        }
    ],
    "sg:phone":"+61 13 20 32",
    "sg:postcode":"2150",
    "sg:province":"NSW",
    "wof:name":"Westpac",
    "wof:placetype":"venue"
},
  "geometry": {"coordinates":[151.00668335,-33.81483078],"type":"Point"}
}