{
  "type": "Feature",
  "properties": {
    "iso:country":"AU",
    "sg:address":"601 Parramatta Rd",
    "sg:city":"Leichhardt",
    "sg:classifiers":[
        {
            "category":"Utilities",
            "type":"Services"
        }
    ],
    "sg:phone":"+61 2 9560 4523",
    "sg:postcode":"2040",
    "sg:province":"NSW",
    "sg:tags":[
        "equipment",
        "towing"
    ],
    "sg:website":"http://www.fastfitbullbars.com.au",
    "wof:name":"Fastfit Towbars",
    "wof:placetype":"venue"
},
  "geometry": {"coordinates":[151.150223,-33.889465],"type":"Point"}
}