{
  "type": "Feature",
  "properties": {
    "addr:full":"29 Albemarle Ave Rose Bay NSW 2029",
    "addr:housenumber":"29",
    "addr:postcode":"2029",
    "addr:street":"Albemarle Ave",
    "iso:country":"AU",
    "sg:address":"29 Albemarle Ave",
    "sg:city":"Rose Bay",
    "sg:classifiers":[
        {
            "category":"Building & Trades",
            "subcategory":"Landscaping Services",
            "type":"Services"
        }
    ],
    "sg:phone":"+61 2 9371 9086",
    "sg:postcode":"2029",
    "sg:province":"NSW",
    "sg:tags":[
        "consultant"
    ],
    "wof:name":"Oates Holdings Pty Ltd",
    "wof:placetype":"venue"
},
  "geometry": {"coordinates":[151.271972656,-33.8748245239],"type":"Point"}
}