{
  "type": "Feature",
  "properties": {
    "addr:full":"King St Scottsdale TAS 7260",
    "addr:postcode":"7260",
    "addr:street":"King St",
    "iso:country":"AU",
    "sg:address":"King St",
    "sg:city":"Scottsdale",
    "sg:classifiers":[
        {
            "category":"Autos & Motor Vehicles",
            "subcategory":"Fuel & Gas Station",
            "type":"Retail Goods"
        }
    ],
    "sg:phone":"+61 3 6352 2339",
    "sg:postcode":"7260",
    "sg:province":"TAS",
    "wof:name":"BP Australia Limited",
    "wof:placetype":"venue"
},
  "geometry": {"coordinates":[147.518021,-41.159988],"type":"Point"}
}