{
  "type": "Feature",
  "properties": {
    "addr:full":"Shop 17/ Martin Pl Sydney NSW 2000",
    "addr:housenumber":"shop 17 /",
    "addr:postcode":"2000",
    "addr:street":"Martin Pl",
    "iso:country":"AU",
    "sg:address":"Shop 17/ Martin Pl",
    "sg:city":"Sydney",
    "sg:classifiers":[
        {
            "category":"Fast Food",
            "type":"Food & Drink"
        }
    ],
    "sg:phone":"+61 2 9221 1058",
    "sg:postcode":"2000",
    "sg:province":"NSW",
    "sg:tags":[
        "away",
        "take"
    ],
    "wof:name":"Eat Lulu Australia",
    "wof:placetype":"venue"
},
  "geometry": {"coordinates":[151.20863342300001,-33.8674125671],"type":"Point"}
}