{
  "type": "Feature",
  "properties": {
    "addr:full":"Sandhills Rd Forbes NSW 2871",
    "addr:postcode":"2871",
    "addr:street":"Sandhills Rd",
    "iso:country":"AU",
    "sg:address":"Sandhills Rd",
    "sg:city":"Forbes",
    "sg:classifiers":[
        {
            "category":"Professional",
            "subcategory":"Business Services",
            "type":"Services"
        }
    ],
    "sg:phone":"+61 2 6852 3247",
    "sg:postcode":"2871",
    "sg:province":"NSW",
    "sg:tags":[
        "livestock",
        "transport"
    ],
    "wof:name":"White H L",
    "wof:placetype":"venue"
},
  "geometry": {"coordinates":[148.04229699999999,-33.376129],"type":"Point"}
}