{
  "type": "Feature",
  "properties": {
    "addr:full":"PO Box 2212 Graceville QLD 4075",
    "addr:postcode":"4075",
    "iso:country":"AU",
    "sg:address":"PO Box 2212",
    "sg:city":"Graceville",
    "sg:classifiers":[
        {
            "category":"Personal",
            "type":"Services"
        }
    ],
    "sg:phone":"+61 7 3278 0424",
    "sg:postcode":"4075",
    "sg:province":"QLD",
    "sg:tags":[
        "dressmaker"
    ],
    "wof:name":"Aiga's Sewing Service",
    "wof:placetype":"venue"
},
  "geometry": {"coordinates":[152.98178100600001,-27.5219535828],"type":"Point"}
}