{
  "type": "Feature",
  "properties": {
    "iso:country":"AU",
    "sg:address":"Wollombi Rd",
    "sg:city":"Millfield",
    "sg:classifiers":[
        {
            "category":"Manufacturing",
            "subcategory":"Lumber",
            "type":"Manufacturing & Wholesale Goods"
        }
    ],
    "sg:phone":"+61 2 4998 1224",
    "sg:postcode":"2325",
    "sg:province":"NSW",
    "sg:tags":[
        "sawmillers"
    ],
    "wof:name":"Sweetman's Timber Pty Ltd",
    "wof:placetype":"venue"
},
  "geometry": {"coordinates":[151.262329102,-32.8887672424],"type":"Point"}
}