{
  "type": "Feature",
  "properties": {
    "iso:country":"AU",
    "sg:address":"The Wharf Parkyn Pde",
    "sg:city":"Mooloolaba",
    "sg:classifiers":[
        {
            "category":"Education",
            "subcategory":"Special Training",
            "type":"Public Place"
        }
    ],
    "sg:phone":"+61 7 5444 8595",
    "sg:postcode":"4557",
    "sg:province":"QLD",
    "sg:tags":[
        "diving",
        "school",
        "scuba"
    ],
    "wof:name":"Scuba World",
    "wof:placetype":"venue"
},
  "geometry": {"coordinates":[153.122924805,-26.6829833984],"type":"Point"}
}