{
  "type": "Feature",
  "properties": {
    "addr:full":"PO Box 8176 Station Arcade Adelaide SA 5001",
    "addr:postcode":"5001",
    "iso:country":"AU",
    "sg:address":"PO Box 8176 Station Arcade",
    "sg:city":"Adelaide",
    "sg:classifiers":[
        {
            "category":"Recreation",
            "subcategory":"Fishing",
            "type":"Entertainment"
        }
    ],
    "sg:phone":"+61 414 294 639",
    "sg:postcode":"5001",
    "sg:province":"SA",
    "sg:tags":[
        "tackle"
    ],
    "wof:name":"Beyond Trout",
    "wof:placetype":"venue"
},
  "geometry": {"coordinates":[138.599731445,-34.9257698059],"type":"Point"}
}