{
  "type": "Feature",
  "properties": {
    "addr:full":"264- 268 High St Ashburton VIC 3147",
    "addr:housenumber":"268",
    "addr:postcode":"3147",
    "addr:street":"High St",
    "iso:country":"AU",
    "sg:address":"264- 268 High St",
    "sg:city":"Ashburton",
    "sg:classifiers":[
        {
            "category":"Social Services",
            "subcategory":"Retirement Home",
            "type":"Services"
        }
    ],
    "sg:phone":"+61 3 9813 8566",
    "sg:postcode":"3147",
    "sg:province":"VIC",
    "sg:tags":[
        "accommodation",
        "special"
    ],
    "wof:name":"Iris Manor",
    "wof:placetype":"venue"
},
  "geometry": {"coordinates":[145.081954956,-37.8638038635],"type":"Point"}
}