{
  "type": "Feature",
  "properties": {
    "iso:country":"AU",
    "sg:address":"Captain Cook Shopping Centre Arnhem Rd",
    "sg:city":"Nhulunbuy",
    "sg:classifiers":[
        {
            "category":"Professional",
            "subcategory":"Accounting & Tax Preparation",
            "type":"Services"
        }
    ],
    "sg:phone":"+61 8 8987 3202",
    "sg:postcode":"0880",
    "sg:province":"NT",
    "sg:tags":[
        "consultant",
        "taxation"
    ],
    "wof:name":"Arnhem Accountancy & Taxation Services",
    "wof:placetype":"venue"
},
  "geometry": {"coordinates":[136.774216,-12.188903],"type":"Point"}
}