{
  "type": "Feature",
  "properties": {
    "addr:full":"Shop GF23, Braodway on the Mall, 170 Queen St Broadway QLD 4006",
    "addr:housenumber":"170",
    "addr:postcode":"4006",
    "addr:street":"Queen St",
    "iso:country":"AU",
    "sg:address":"Shop GF23, Braodway on the Mall, 170 Queen St",
    "sg:city":"Broadway",
    "sg:classifiers":[
        {
            "category":"Personal",
            "subcategory":"Beauty Salon",
            "type":"Services"
        }
    ],
    "sg:phone":"+61 7 3221 5955",
    "sg:postcode":"4006",
    "sg:province":"QLD",
    "sg:tags":[
        "hairdresser"
    ],
    "wof:name":"Price Attack",
    "wof:placetype":"venue"
},
  "geometry": {"coordinates":[153.02607727,-27.4688072205],"type":"Point"}
}