{
  "type": "Feature",
  "properties": {
    "iso:country":"AU",
    "sg:address":"1 Yarrabung Rd",
    "sg:city":"St Ives",
    "sg:classifiers":[
        {
            "category":"Professional",
            "subcategory":"Accounting & Tax Preparation",
            "type":"Services"
        }
    ],
    "sg:phone":"+61 2 9488 8582",
    "sg:postcode":"2075",
    "sg:province":"NSW",
    "sg:tags":[
        "accountant",
        "auditor"
    ],
    "wof:name":"Forsythe D R",
    "wof:placetype":"venue"
},
  "geometry": {"coordinates":[151.170166016,-33.7278594971],"type":"Point"}
}