{
  "type": "Feature",
  "properties": {
    "addr:full":"62 Robey St Mascot NSW 2020",
    "addr:housenumber":"62",
    "addr:postcode":"2020",
    "addr:street":"Robey St",
    "iso:country":"AU",
    "sg:address":"62 Robey St",
    "sg:city":"Mascot",
    "sg:classifiers":[
        {
            "category":"Retail",
            "subcategory":"Auto Repair",
            "type":"Services"
        }
    ],
    "sg:phone":"+61 2 9693 1866",
    "sg:postcode":"2020",
    "sg:province":"NSW",
    "sg:tags":[
        "repairer",
        "motor",
        "engineer"
    ],
    "wof:name":"Robey Motor Works",
    "wof:placetype":"venue"
},
  "geometry": {"coordinates":[151.190475464,-33.9313049316],"type":"Point"}
}