{
  "type": "Feature",
  "properties": {
    "iso:country":"AU",
    "sg:address":"90 Station St",
    "sg:city":"Waratah",
    "sg:classifiers":[
        {
            "category":"Home & Garden",
            "subcategory":"Furniture",
            "type":"Retail Goods"
        }
    ],
    "sg:phone":"+61 2 4968 1258",
    "sg:postcode":"2298",
    "sg:province":"NSW",
    "sg:tags":[
        "repair",
        "restoration"
    ],
    "wof:name":"Marshall Restorations",
    "wof:placetype":"venue"
},
  "geometry": {"coordinates":[151.72491455100001,-32.9028968811],"type":"Point"}
}