{
  "type": "Feature",
  "properties": {
    "addr:full":"Unit 9/ 258 Ross River Rd Townsville QLD 4810",
    "addr:housenumber":"/ 258",
    "addr:postcode":"4810",
    "addr:street":"Ross River Rd",
    "iso:country":"AU",
    "sg:address":"Unit 9/ 258 Ross River Rd",
    "sg:city":"Townsville",
    "sg:classifiers":[
        {
            "category":"Professional",
            "subcategory":"Employment Agencies",
            "type":"Services"
        }
    ],
    "sg:phone":"+61 7 4725 8711",
    "sg:postcode":"4810",
    "sg:province":"QLD",
    "wof:name":"Mission Australia",
    "wof:placetype":"venue"
},
  "geometry": {"coordinates":[146.76921100000001,-19.296791],"type":"Point"}
}