{
  "type": "Feature",
  "properties": {
    "iso:country":"AU",
    "sg:address":"68 Dunsborough-Lakes Drv",
    "sg:city":"Dunsborough",
    "sg:classifiers":[
        {
            "category":"Building & Trades",
            "subcategory":"Cleaning & Sanitation",
            "type":"Services"
        }
    ],
    "sg:phone":"+61 8 9756 8746",
    "sg:postcode":"6281",
    "sg:province":"WA",
    "sg:tags":[
        "chemical",
        "pressure",
        "steam",
        "contractor"
    ],
    "wof:name":"Modern Window Cleaning",
    "wof:placetype":"venue"
},
  "geometry": {"coordinates":[115.100257873,-33.6254997253],"type":"Point"}
}