{
  "type": "Feature",
  "properties": {
    "addr:full":"24 Clive St Inverell NSW 2360",
    "addr:housenumber":"24",
    "addr:postcode":"2360",
    "addr:street":"Clive St",
    "iso:country":"AU",
    "sg:address":"24 Clive St",
    "sg:city":"Inverell",
    "sg:classifiers":[
        {
            "category":"Food & Beverages",
            "subcategory":"Groceries & Convenience Stores",
            "type":"Retail Goods"
        }
    ],
    "sg:phone":"+61 2 6722 3581",
    "sg:postcode":"2360",
    "sg:province":"NSW",
    "wof:name":"Albion Mini Mart",
    "wof:placetype":"venue"
},
  "geometry": {"coordinates":[151.12701415999999,-29.7804832458],"type":"Point"}
}