{
  "type": "Feature",
  "properties": {
    "addr:full":"56 Stevenson St Paddington QLD 4064",
    "addr:housenumber":"56",
    "addr:postcode":"4064",
    "addr:street":"Stevenson St",
    "iso:country":"AU",
    "sg:address":"56 Stevenson St",
    "sg:city":"Paddington",
    "sg:classifiers":[
        {
            "category":"Professional",
            "subcategory":"Art Services",
            "type":"Services"
        }
    ],
    "sg:phone":"+61 7 3367 1489",
    "sg:postcode":"4064",
    "sg:province":"QLD",
    "sg:tags":[
        "graphic",
        "designer"
    ],
    "wof:name":"Hummingbird Creative",
    "wof:placetype":"venue"
},
  "geometry": {"coordinates":[152.99530029300001,-27.4608783722],"type":"Point"}
}