{
  "type": "Feature",
  "properties": {
    "iso:country":"AU",
    "sg:address":"103 Sturt Ave",
    "sg:city":"Georges Hall",
    "sg:classifiers":[
        {
            "category":"Building & Trades",
            "subcategory":"Construction",
            "type":"Services"
        }
    ],
    "sg:phone":"+61 2 9708 1380",
    "sg:postcode":"2198",
    "sg:province":"NSW",
    "sg:tags":[
        "contractor"
    ],
    "wof:name":"Alma Building Pty Ltd",
    "wof:placetype":"venue"
},
  "geometry": {"coordinates":[150.998093,-33.912296],"type":"Point"}
}