{
  "type": "Feature",
  "properties": {
    "addr:full":"26 Statham Ave North Rocks NSW 2151",
    "addr:housenumber":"26",
    "addr:postcode":"2151",
    "addr:street":"Statham Ave",
    "iso:country":"AU",
    "sg:address":"26 Statham Ave",
    "sg:city":"North Rocks",
    "sg:classifiers":[
        {
            "category":"Retail",
            "subcategory":"Auto Repair",
            "type":"Services"
        }
    ],
    "sg:phone":"+61 2 9872 1758",
    "sg:postcode":"2151",
    "sg:province":"NSW",
    "sg:tags":[
        "body",
        "motor",
        "trimmer"
    ],
    "wof:name":"Carl Bowerman",
    "wof:placetype":"venue"
},
  "geometry": {"coordinates":[151.02384948700001,-33.777759552],"type":"Point"}
}