{
  "type": "Feature",
  "properties": {
    "iso:country":"AU",
    "sg:address":"13- 19 Johansson Rd",
    "sg:city":"Wingfield",
    "sg:classifiers":[
        {
            "category":"Professional",
            "subcategory":"Engineering",
            "type":"Services"
        }
    ],
    "sg:phone":"+61 8 8349 9000",
    "sg:postcode":"5013",
    "sg:province":"SA",
    "sg:tags":[
        "manufacturing",
        "engineer"
    ],
    "wof:name":"Numetric Manufacturing Pty Ltd",
    "wof:placetype":"venue"
},
  "geometry": {"coordinates":[138.56976318400001,-34.8410453796],"type":"Point"}
}