{
  "type": "Feature",
  "properties": {
    "iso:country":"AU",
    "sg:address":"34 Mainsail Drv",
    "sg:city":"Ocean Reef",
    "sg:classifiers":[
        {
            "category":"Retail",
            "subcategory":"Auto Repair",
            "type":"Services"
        }
    ],
    "sg:phone":"+61 418 943 791",
    "sg:postcode":"6027",
    "sg:province":"WA",
    "sg:tags":[
        "repairer",
        "motor",
        "engineer"
    ],
    "wof:name":"Home Car Servicing",
    "wof:placetype":"venue"
},
  "geometry": {"coordinates":[115.734512329,-31.7613506317],"type":"Point"}
}