{
  "type": "Feature",
  "properties": {
    "iso:country":"AU",
    "sg:address":"South Rd",
    "sg:city":"Serviceton",
    "sg:classifiers":[
        {
            "category":"Mining & Drilling",
            "type":"Manufacturing & Wholesale Goods"
        }
    ],
    "sg:phone":"+61 3 5393 1273",
    "sg:postcode":"3420",
    "sg:province":"VIC",
    "sg:tags":[
        "boring",
        "contractor"
    ],
    "wof:name":"Maidment Drilling",
    "wof:placetype":"venue"
},
  "geometry": {"coordinates":[140.99012756400001,-36.3790283203],"type":"Point"}
}