{
  "type": "Feature",
  "properties": {
    "addr:full":"116 Enoggera Tce Paddington QLD 4064",
    "addr:housenumber":"116",
    "addr:postcode":"4064",
    "addr:street":"Enoggera Tce",
    "iso:country":"AU",
    "sg:address":"116 Enoggera Tce",
    "sg:city":"Paddington",
    "sg:classifiers":[
        {
            "category":"Shopping",
            "subcategory":"Mobile Phones",
            "type":"Retail Goods"
        }
    ],
    "sg:phone":"+61 7 3367 3444",
    "sg:postcode":"4064",
    "sg:province":"QLD",
    "sg:tags":[
        "telephone",
        "accessory"
    ],
    "wof:name":"Future Communication Solutions Pty Ltd",
    "wof:placetype":"venue"
},
  "geometry": {"coordinates":[153.007736206,-27.4666595459],"type":"Point"}
}