{
  "type": "Feature",
  "properties": {
    "addr:full":"Shop 5, 2- 4 Main St Mt Annan NSW 2567",
    "addr:housenumber":"shop;2 4",
    "addr:postcode":"2567",
    "addr:street":"Main St",
    "iso:country":"AU",
    "sg:address":"Shop 5, 2- 4 Main St",
    "sg:city":"Mt Annan",
    "sg:classifiers":[
        {
            "category":"Fast Food",
            "type":"Food & Drink"
        }
    ],
    "sg:phone":"+61 2 4647 0799",
    "sg:postcode":"2567",
    "sg:province":"NSW",
    "sg:tags":[
        "away",
        "take"
    ],
    "wof:name":"Mr. Ho Chinese Restaurant",
    "wof:placetype":"venue"
},
  "geometry": {"coordinates":[150.756958008,-34.0492324829],"type":"Point"}
}