{
  "type": "Feature",
  "properties": {
    "addr:full":"Level 1, 46 Railway Rd Marayong NSW 2148",
    "addr:housenumber":"46",
    "addr:postcode":"2148",
    "addr:street":"Railway Rd",
    "iso:country":"AU",
    "sg:address":"Level 1, 46 Railway Rd",
    "sg:city":"Marayong",
    "sg:classifiers":[
        {
            "category":"Shopping",
            "type":"Retail Goods"
        }
    ],
    "sg:phone":"+61 2 9621 8828",
    "sg:postcode":"2148",
    "sg:province":"NSW",
    "sg:tags":[
        "equipment",
        "safety",
        "accessory"
    ],
    "wof:name":"Paramount Safety Products",
    "wof:placetype":"venue"
},
  "geometry": {"coordinates":[150.89994812,-33.7477493286],"type":"Point"}
}