{
  "type": "Feature",
  "properties": {
    "addr:full":"Studio6/ 46 Regent St Richmond VIC 3121",
    "addr:housenumber":"46",
    "addr:postcode":"3121",
    "addr:street":"Regent St",
    "iso:country":"AU",
    "sg:address":"Studio6/ 46 Regent St",
    "sg:city":"Richmond",
    "sg:classifiers":[
        {
            "category":"Professional",
            "subcategory":"Business Services",
            "type":"Services"
        }
    ],
    "sg:phone":"+61 3 9416 3729",
    "sg:postcode":"3121",
    "sg:province":"VIC",
    "sg:tags":[
        "management",
        "event"
    ],
    "wof:name":"Pronto Productions",
    "wof:placetype":"venue"
},
  "geometry": {"coordinates":[144.99188232399999,-37.8118515015],"type":"Point"}
}