{
  "type": "Feature",
  "properties": {
    "addr:full":"122 Calvert Rd Glen Aplin QLD 4381",
    "addr:housenumber":"122",
    "addr:postcode":"4381",
    "addr:street":"Calvert Rd",
    "iso:country":"AU",
    "sg:address":"122 Calvert Rd",
    "sg:city":"Glen Aplin",
    "sg:classifiers":[
        {
            "category":"Shopping",
            "subcategory":"Crafts & Fabrics",
            "type":"Retail Goods"
        }
    ],
    "sg:phone":"+61 7 4683 4158",
    "sg:postcode":"4381",
    "sg:province":"QLD",
    "sg:tags":[
        "supply"
    ],
    "wof:name":"Artisan's Attic",
    "wof:placetype":"venue"
},
  "geometry": {"coordinates":[151.88168300000001,-28.740194],"type":"Point"}
}