{
  "type": "Feature",
  "properties": {
    "addr:full":"Gardens-R-Us Centre 75 Gardeners Rd Kingsford NSW 2032",
    "addr:housenumber":"75",
    "addr:postcode":"2032",
    "addr:street":"Gardeners Rd",
    "iso:country":"AU",
    "sg:address":"Gardens-R-Us Centre 75 Gardeners Rd",
    "sg:city":"Kingsford",
    "sg:classifiers":[
        {
            "category":"Cafe",
            "type":"Food & Drink"
        }
    ],
    "sg:phone":"+61 2 9662 4910",
    "sg:postcode":"2032",
    "sg:province":"NSW",
    "wof:name":"Lakeview Cafe",
    "wof:placetype":"venue"
},
  "geometry": {"coordinates":[151.218353272,-33.9252052307],"type":"Point"}
}