{
  "type": "Feature",
  "properties": {
    "addr:full":"9 Irwin Ave Altona North VIC 3025",
    "addr:housenumber":"9",
    "addr:postcode":"3025",
    "addr:street":"Irwin Ave",
    "iso:country":"AU",
    "sg:address":"9 Irwin Ave",
    "sg:city":"Altona North",
    "sg:classifiers":[
        {
            "category":"Building & Trades",
            "subcategory":"Construction",
            "type":"Services"
        }
    ],
    "sg:phone":"+61 3 9314 0830",
    "sg:postcode":"3025",
    "sg:province":"VIC",
    "sg:tags":[
        "concrete",
        "paving"
    ],
    "wof:name":"Bellini Concrete Contractor",
    "wof:placetype":"venue"
},
  "geometry": {"coordinates":[144.84213299999999,-37.829746],"type":"Point"}
}