{
  "type": "Feature",
  "properties": {
    "iso:country":"AU",
    "sg:address":"125 Palmerston St",
    "sg:city":"Currajong",
    "sg:classifiers":[
        {
            "category":"Building & Trades",
            "subcategory":"Plumbing",
            "type":"Services"
        }
    ],
    "sg:phone":"+61 7 4725 2955",
    "sg:postcode":"4812",
    "sg:province":"QLD",
    "sg:tags":[
        "plumber",
        "gasfitters"
    ],
    "wof:name":"K Royes Plumbing",
    "wof:placetype":"venue"
},
  "geometry": {"coordinates":[146.77694700000001,-19.280226],"type":"Point"}
}