{
  "type": "Feature",
  "properties": {
    "iso:country":"AU",
    "sg:address":"1/ 10a Atherton Rd",
    "sg:city":"Oakleigh",
    "sg:classifiers":[
        {
            "category":"Health Services",
            "subcategory":"Chiropractor",
            "type":"Services"
        }
    ],
    "sg:phone":"+61 3 9563 1277",
    "sg:postcode":"3166",
    "sg:province":"VIC",
    "wof:name":"Atherton Road Chiropractic Centre",
    "wof:placetype":"venue"
},
  "geometry": {"coordinates":[145.088500977,-37.8986587524],"type":"Point"}
}