{
  "type": "Feature",
  "properties": {
    "addr:full":"49 Mather Rd Mt Eliza VIC 3930",
    "addr:housenumber":"49",
    "addr:postcode":"3930",
    "addr:street":"Mather Rd",
    "iso:country":"AU",
    "sg:address":"49 Mather Rd",
    "sg:city":"Mt Eliza",
    "sg:classifiers":[
        {
            "category":"Building & Trades",
            "subcategory":"Cleaning & Sanitation",
            "type":"Services"
        }
    ],
    "sg:phone":"+61 3 9775 4776",
    "sg:postcode":"3930",
    "sg:province":"VIC",
    "sg:tags":[
        "window"
    ],
    "wof:name":"Curtis Window Cleaning",
    "wof:placetype":"venue"
},
  "geometry": {"coordinates":[145.112457275,-38.1919364929],"type":"Point"}
}