{
  "type": "Feature",
  "properties": {
    "iso:country":"AU",
    "sg:address":"3 Dolphin St",
    "sg:city":"Scarborough",
    "sg:classifiers":[
        {
            "category":"Building & Trades",
            "subcategory":"Plumbing",
            "type":"Services"
        }
    ],
    "sg:phone":"+61 419 698 411",
    "sg:postcode":"4020",
    "sg:province":"QLD",
    "sg:tags":[
        "consultant"
    ],
    "wof:name":"Newport Plumbing & Bathrooms",
    "wof:placetype":"venue"
},
  "geometry": {"coordinates":[153.09826699999999,-27.204449],"type":"Point"}
}