{
  "type": "Feature",
  "properties": {
    "addr:full":"8 Sailors Gully Rd Eaglehawk VIC 3556",
    "addr:housenumber":"8",
    "addr:postcode":"3556",
    "addr:street":"Sailors Gully Rd",
    "iso:country":"AU",
    "sg:address":"8 Sailors Gully Rd",
    "sg:city":"Eaglehawk",
    "sg:classifiers":[
        {
            "category":"Personal",
            "subcategory":"Beauty Salon",
            "type":"Services"
        }
    ],
    "sg:phone":"+61 3 5446 2730",
    "sg:postcode":"3556",
    "sg:province":"VIC",
    "sg:tags":[
        "hairdresser"
    ],
    "wof:name":"Zambou",
    "wof:placetype":"venue"
},
  "geometry": {"coordinates":[144.238967895,-36.7085647583],"type":"Point"}
}