{
  "type": "Feature",
  "properties": {
    "addr:full":"Unit 4, 19 - 25 Kembla St Fyshwick ACT 2609",
    "addr:housenumber":"19 25",
    "addr:postcode":"2609",
    "addr:street":"Kembla St",
    "iso:country":"AU",
    "sg:address":"Unit 4, 19 - 25 Kembla St",
    "sg:city":"Fyshwick",
    "sg:classifiers":[
        {
            "category":"Building & Trades",
            "subcategory":"Construction",
            "type":"Services"
        }
    ],
    "sg:phone":"+61 2 6239 2665",
    "sg:postcode":"2609",
    "sg:province":"ACT",
    "sg:tags":[
        "concrete",
        "contractor"
    ],
    "sg:website":"http://www.ellcon.com.au",
    "wof:name":"Ellcon Concrete",
    "wof:placetype":"venue"
},
  "geometry": {"coordinates":[149.17706298799999,-35.3247833252],"type":"Point"}
}