{
  "type": "Feature",
  "properties": {
    "iso:country":"AU",
    "sg:address":"47 Normanby Rd",
    "sg:city":"Kew",
    "sg:classifiers":[
        {
            "category":"Personal",
            "subcategory":"Massage",
            "type":"Services"
        }
    ],
    "sg:phone":"+61 417 552 512",
    "sg:postcode":"3101",
    "sg:province":"VIC",
    "sg:tags":[
        "therapy"
    ],
    "wof:name":"Braams Conrad",
    "wof:placetype":"venue"
},
  "geometry": {"coordinates":[145.05401611299999,-37.8063163757],"type":"Point"}
}