{
  "type": "Feature",
  "properties": {
    "addr:full":"5 Murray St Pittsworth QLD 4356",
    "addr:housenumber":"5",
    "addr:postcode":"4356",
    "addr:street":"Murray St",
    "iso:country":"AU",
    "sg:address":"5 Murray St",
    "sg:city":"Pittsworth",
    "sg:classifiers":[
        {
            "category":"Retail",
            "subcategory":"Auto Repair",
            "type":"Services"
        }
    ],
    "sg:phone":"+61 7 4693 1285",
    "sg:postcode":"4356",
    "sg:province":"QLD",
    "sg:tags":[
        "repairer",
        "motor",
        "engineer"
    ],
    "wof:name":"Willday Motors",
    "wof:placetype":"venue"
},
  "geometry": {"coordinates":[151.636932,-27.715952],"type":"Point"}
}