{
  "type": "Feature",
  "properties": {
    "addr:full":"21 Potts St Richmond NSW 2753",
    "addr:housenumber":"21",
    "addr:postcode":"2753",
    "addr:street":"Potts St",
    "iso:country":"AU",
    "sg:address":"21 Potts St",
    "sg:city":"Richmond",
    "sg:classifiers":[
        {
            "category":"Building & Trades",
            "subcategory":"Cleaning & Sanitation",
            "type":"Services"
        }
    ],
    "sg:phone":"+61 405 209 991",
    "sg:postcode":"2753",
    "sg:province":"NSW",
    "sg:tags":[
        "chemical",
        "pressure",
        "steam",
        "contractor"
    ],
    "wof:name":"Driveway Lovers",
    "wof:placetype":"venue"
},
  "geometry": {"coordinates":[150.741256714,-33.6079063416],"type":"Point"}
}