{
  "type": "Feature",
  "properties": {
    "iso:country":"AU",
    "sg:address":"7 Granby Crt",
    "sg:city":"Endeavour Hills",
    "sg:classifiers":[
        {
            "category":"Building & Trades",
            "subcategory":"Cleaning & Sanitation",
            "type":"Services"
        }
    ],
    "sg:phone":"+61 439 931 138",
    "sg:postcode":"3802",
    "sg:province":"VIC",
    "sg:tags":[
        "cleaner",
        "repairer",
        "roof"
    ],
    "wof:name":"New Ridge Roof Restoration",
    "wof:placetype":"venue"
},
  "geometry": {"coordinates":[145.251556397,-37.9718666077],"type":"Point"}
}