{
  "type": "Feature",
  "properties": {
    "iso:country":"AU",
    "sg:address":"Balfours Rd",
    "sg:city":"Willow Grove",
    "sg:classifiers":[
        {
            "category":"Social Services",
            "subcategory":"Child Care",
            "type":"Services"
        }
    ],
    "sg:phone":"+61 3 5635 2240",
    "sg:postcode":"3825",
    "sg:province":"VIC",
    "sg:tags":[
        "breeding",
        "artificial"
    ],
    "wof:name":"Eastern Genetics Herd Improvement",
    "wof:placetype":"venue"
},
  "geometry": {"coordinates":[146.15713500000001,-38.089451],"type":"Point"}
}