{
  "type": "Feature",
  "properties": {
    "iso:country":"AU",
    "sg:address":"5/28- 32 Stepney St",
    "sg:city":"Stepney",
    "sg:classifiers":[
        {
            "category":"Retail",
            "subcategory":"Auto Repair",
            "type":"Services"
        }
    ],
    "sg:phone":"+61 8 8132 1622",
    "sg:postcode":"5069",
    "sg:province":"SA",
    "sg:tags":[
        "fuel",
        "petrol",
        "injection"
    ],
    "wof:name":"Petro-Ject Training & Equipment",
    "wof:placetype":"venue"
},
  "geometry": {"coordinates":[138.626586914,-34.9125442505],"type":"Point"}
}