{
  "type": "Feature",
  "properties": {
    "addr:full":"91 Percy St Warwick QLD 4370",
    "addr:housenumber":"91",
    "addr:postcode":"4370",
    "addr:street":"Percy St",
    "iso:country":"AU",
    "sg:address":"91 Percy St",
    "sg:city":"Warwick",
    "sg:classifiers":[
        {
            "category":"Home & Garden",
            "subcategory":"Building Materials",
            "type":"Retail Goods"
        }
    ],
    "sg:phone":"+61 7 4661 1266",
    "sg:postcode":"4370",
    "sg:province":"QLD",
    "sg:tags":[
        "merchant",
        "glass",
        "glazier"
    ],
    "wof:name":"Warwick Home Improvement Centre Inc. Shaddock & Woods Pty Ltd",
    "wof:placetype":"venue"
},
  "geometry": {"coordinates":[152.03027343799999,-28.2180614471],"type":"Point"}
}