{
  "type": "Feature",
  "properties": {
    "addr:full":"550 Stirling Hwy Peppermint Grove WA 6011",
    "addr:housenumber":"550",
    "addr:postcode":"6011",
    "addr:street":"Stirling Hwy",
    "iso:country":"AU",
    "sg:address":"550 Stirling Hwy",
    "sg:city":"Peppermint Grove",
    "sg:classifiers":[
        {
            "category":"Building & Trades",
            "subcategory":"Landscaping Services",
            "type":"Services"
        }
    ],
    "sg:phone":"+61 8 9383 0888",
    "sg:postcode":"6011",
    "sg:province":"WA",
    "sg:tags":[
        "architect",
        "landscape"
    ],
    "wof:name":"Blackwell & Associates Pty Ltd",
    "wof:placetype":"venue"
},
  "geometry": {"coordinates":[115.760231018,-32.0033416748],"type":"Point"}
}