{
  "type": "Feature",
  "properties": {
    "iso:country":"AU",
    "sg:address":"43 Olympic Crt",
    "sg:city":"Southport",
    "sg:classifiers":[
        {
            "category":"Retail",
            "subcategory":"Repair Shop",
            "type":"Services"
        }
    ],
    "sg:phone":"+61 7 5526 3411",
    "sg:postcode":"4215",
    "sg:province":"QLD",
    "sg:tags":[
        "upholsterer"
    ],
    "wof:name":"Extreme Trimming",
    "wof:placetype":"venue"
},
  "geometry": {"coordinates":[153.39085388199999,-27.9705505371],"type":"Point"}
}