{
  "type": "Feature",
  "properties": {
    "iso:country":"AU",
    "sg:address":"Un 82/ 26 Kirketon Rd",
    "sg:city":"Darlinghurst",
    "sg:classifiers":[
        {
            "category":"Building & Trades",
            "subcategory":"Cleaning & Sanitation",
            "type":"Services"
        }
    ],
    "sg:phone":"+61 2 9357 2294",
    "sg:postcode":"2010",
    "sg:province":"NSW",
    "sg:tags":[
        "industrial",
        "commercial",
        "contractor"
    ],
    "wof:name":"Bennett Commercial Cleaning Pty Ltd",
    "wof:placetype":"venue"
},
  "geometry": {"coordinates":[151.22059631400001,-33.8765411377],"type":"Point"}
}