{
  "type": "Feature",
  "properties": {
    "iso:country":"AU",
    "sg:address":"57 Sydney Rd",
    "sg:city":"Manly",
    "sg:classifiers":[
        {
            "category":"Health Services",
            "subcategory":"Dentist",
            "type":"Services"
        }
    ],
    "sg:phone":"+61 2 9977 2442",
    "sg:postcode":"2095",
    "sg:province":"NSW",
    "wof:name":"Marel Alan C",
    "wof:placetype":"venue"
},
  "geometry": {"coordinates":[151.28317260700001,-33.7966308594],"type":"Point"}
}