{
  "type": "Feature",
  "properties": {
    "iso:country":"AU",
    "sg:address":"6 Carter St",
    "sg:city":"Cammeray",
    "sg:classifiers":[
        {
            "category":"Deli",
            "type":"Food & Drink"
        }
    ],
    "sg:phone":"+61 2 9922 5229",
    "sg:postcode":"2062",
    "sg:province":"NSW",
    "sg:tags":[
        "delicatessen"
    ],
    "wof:name":"Jim's Deli",
    "wof:placetype":"venue"
},
  "geometry": {"coordinates":[151.212966919,-33.8215065002],"type":"Point"}
}