{
  "type": "Feature",
  "properties": {
    "addr:full":"Shop 20, 87-89 Great Ocean Rd Anglesea VIC 3230",
    "addr:housenumber":"shop 20 87-89",
    "addr:postcode":"3230",
    "addr:street":"Great Ocean Rd",
    "iso:country":"AU",
    "sg:address":"Shop 20, 87-89 Great Ocean Rd",
    "sg:city":"Anglesea",
    "sg:classifiers":[
        {
            "category":"Banks & Credit Unions",
            "subcategory":"Financial Services",
            "type":"Services"
        }
    ],
    "sg:phone":"+61 3 5263 3964",
    "sg:postcode":"3230",
    "sg:province":"VIC",
    "sg:tags":[
        "annuity",
        "rollover",
        "superannuation",
        "consultant"
    ],
    "wof:name":"Coastline Financial Group Pty Ltd",
    "wof:placetype":"venue"
},
  "geometry": {"coordinates":[144.18966699999999,-38.404701],"type":"Point"}
}