{
  "type": "Feature",
  "properties": {
    "addr:full":"23 Nelson Rd North Strathfield NSW 2137",
    "addr:housenumber":"23",
    "addr:postcode":"2137",
    "addr:street":"Nelson Rd",
    "iso:country":"AU",
    "sg:address":"23 Nelson Rd",
    "sg:city":"North Strathfield",
    "sg:classifiers":[
        {
            "category":"Building & Trades",
            "subcategory":"Plumbing",
            "type":"Services"
        }
    ],
    "sg:phone":"+61 411 102 910",
    "sg:postcode":"2137",
    "sg:province":"NSW",
    "sg:tags":[
        "plumber",
        "gasfitters"
    ],
    "wof:name":"Environmental Plumbing Services",
    "wof:placetype":"venue"
},
  "geometry": {"coordinates":[151.09144592300001,-33.860786438],"type":"Point"}
}