{
  "type": "Feature",
  "properties": {
    "addr:full":"McPherson Park Recreation Reserve, Coburns Rd Melton VIC 3337",
    "addr:postcode":"3337",
    "addr:street":"Coburns Rd",
    "iso:country":"AU",
    "sg:address":"McPherson Park Recreation Reserve, Coburns Rd",
    "sg:city":"Melton",
    "sg:classifiers":[
        {
            "category":"Arena",
            "subcategory":"Sports Club",
            "type":"Entertainment"
        }
    ],
    "sg:phone":"+61 3 9740 0038",
    "sg:postcode":"3337",
    "sg:province":"VIC",
    "sg:tags":[
        "union",
        "rugby"
    ],
    "wof:name":"Melton Rugby Union Club",
    "wof:placetype":"venue"
},
  "geometry": {"coordinates":[144.56874099999999,-37.681881],"type":"Point"}
}