{
  "type": "Feature",
  "properties": {
    "iso:country":"AU",
    "sg:address":"Carol Crt",
    "sg:city":"Frankston",
    "sg:classifiers":[
        {
            "category":"Shopping",
            "subcategory":"Antiques",
            "type":"Retail Goods"
        }
    ],
    "sg:phone":"+61 1300 792 661",
    "sg:postcode":"3199",
    "sg:province":"VIC",
    "sg:tags":[
        "restoration",
        "reproduction"
    ],
    "wof:name":"Furniture Restoration Centre",
    "wof:placetype":"venue"
},
  "geometry": {"coordinates":[145.12179565400001,-38.1415710449],"type":"Point"}
}