{
  "type": "Feature",
  "properties": {
    "addr:full":"Shp 1, Lynwood Village Lynwood WA 6147",
    "addr:housenumber":"1",
    "addr:postcode":"6147",
    "addr:street":"Lynwood Village",
    "iso:country":"AU",
    "sg:address":"Shp 1, Lynwood Village",
    "sg:city":"Lynwood",
    "sg:classifiers":[
        {
            "category":"Food & Beverages",
            "subcategory":"Supermarket",
            "type":"Retail Goods"
        }
    ],
    "sg:phone":"+61 8 9458 3796",
    "sg:postcode":"6147",
    "sg:province":"WA",
    "sg:tags":[
        "grocery",
        "store"
    ],
    "wof:name":"IGA Supermarkets",
    "wof:placetype":"venue"
},
  "geometry": {"coordinates":[115.926552,-32.035641],"type":"Point"}
}