{
  "type": "Feature",
  "properties": {
    "addr:full":"PO Box 8250 Mt Pleasant QLD 4740",
    "addr:postcode":"4740",
    "addr:street":"Pleasant",
    "iso:country":"AU",
    "sg:address":"PO Box 8250",
    "sg:city":"Mt Pleasant",
    "sg:classifiers":[
        {
            "category":"Building & Trades",
            "subcategory":"Pest Control",
            "type":"Services"
        }
    ],
    "sg:phone":"+61 1300 664 548",
    "sg:postcode":"4740",
    "sg:province":"QLD",
    "wof:name":"Leaf Shield Gutter Protection Mackay",
    "wof:placetype":"venue"
},
  "geometry": {"coordinates":[149.15718100000001,-21.11883],"type":"Point"}
}