{
  "type": "Feature",
  "properties": {
    "iso:country":"AU",
    "sg:address":"Cnr Quantum Close & South Gippsland Hwy",
    "sg:city":"Dandenong South",
    "sg:classifiers":[
        {
            "category":"Retail",
            "subcategory":"Auto Repair",
            "type":"Services"
        }
    ],
    "sg:phone":"+61 3 9797 3700",
    "sg:postcode":"3175",
    "sg:province":"VIC",
    "sg:tags":[
        "body",
        "builder",
        "motor"
    ],
    "wof:name":"Vawdrey Bodies Pty Ltd",
    "wof:placetype":"venue"
},
  "geometry": {"coordinates":[145.23263549800001,-38.0160484314],"type":"Point"}
}