{
  "type": "Feature",
  "properties": {
    "addr:full":"Bay 1 No 6 Bosworth Rd Woolgoolga NSW 2456",
    "addr:postcode":"2456",
    "addr:street":"Bosworth Rd",
    "iso:country":"AU",
    "sg:address":"Bay 1 No 6 Bosworth Rd",
    "sg:city":"Woolgoolga",
    "sg:classifiers":[
        {
            "category":"Utilities",
            "subcategory":"Electric",
            "type":"Services"
        }
    ],
    "sg:phone":"+61 2 6654 2770",
    "sg:postcode":"2456",
    "sg:province":"NSW",
    "sg:tags":[
        "element"
    ],
    "wof:name":"Australian Heating Elements",
    "wof:placetype":"venue"
},
  "geometry": {"coordinates":[153.19662500000001,-30.12184],"type":"Point"}
}