{
  "type": "Feature",
  "properties": {
    "iso:country":"AU",
    "sg:address":"45 Sarich Crt",
    "sg:city":"Osborne Park",
    "sg:classifiers":[
        {
            "category":"Professional",
            "subcategory":"Computer Services",
            "type":"Services"
        }
    ],
    "sg:phone":"+61 13 16 32",
    "sg:postcode":"6017",
    "sg:province":"WA",
    "sg:tags":[
        "repairs",
        "upgrade",
        "equipment"
    ],
    "wof:name":"NEC Australia Pty Ltd",
    "wof:placetype":"venue"
},
  "geometry": {"coordinates":[115.806297302,-31.8971691132],"type":"Point"}
}