{
  "type": "Feature",
  "properties": {
    "iso:country":"AU",
    "sg:address":"44 Edith St",
    "sg:city":"Leichhardt",
    "sg:classifiers":[
        {
            "category":"Communications",
            "type":"Services"
        }
    ],
    "sg:phone":"+61 2 9560 9143",
    "sg:postcode":"2040",
    "sg:province":"NSW",
    "sg:tags":[
        "translation"
    ],
    "wof:name":"Polyglot Translations Agency",
    "wof:placetype":"venue"
},
  "geometry": {"coordinates":[151.150803,-33.884048],"type":"Point"}
}