{
  "type": "Feature",
  "properties": {
    "addr:full":"Shop 4 65 The Terrace Ocean Grove VIC 3226",
    "addr:housenumber":"shop;65",
    "addr:postcode":"3226",
    "addr:street":"The Terrace",
    "iso:country":"AU",
    "sg:address":"Shop 4 65",
    "sg:city":"The Terrace Ocean Grove",
    "sg:classifiers":[
        {
            "category":"Fast Food",
            "type":"Food & Drink"
        }
    ],
    "sg:phone":"+61 3 5255 2424",
    "sg:postcode":"3226",
    "sg:province":"VIC",
    "sg:tags":[
        "away",
        "take"
    ],
    "wof:name":"Oceania Chinese Takeaway Foods",
    "wof:placetype":"venue"
},
  "geometry": {"coordinates":[144.52224699999999,-38.267723],"type":"Point"}
}