{
  "type": "Feature",
  "properties": {
    "iso:country":"AU",
    "sg:address":"1 Blaydon St",
    "sg:city":"Kings Meadows",
    "sg:classifiers":[
        {
            "category":"Professional",
            "subcategory":"Accounting & Tax Preparation",
            "type":"Services"
        }
    ],
    "sg:phone":"+61 3 6344 9655",
    "sg:postcode":"7249",
    "sg:province":"TAS",
    "sg:tags":[
        "consultant",
        "taxation"
    ],
    "wof:name":"Reed Scott",
    "wof:placetype":"venue"
},
  "geometry": {"coordinates":[147.16026306099999,-41.468460083],"type":"Point"}
}