{
  "type": "Feature",
  "properties": {
    "addr:full":"4 Sportsground Rd Cambrai SA 5353",
    "addr:housenumber":"4",
    "addr:postcode":"5353",
    "addr:street":"Sportsground Rd",
    "iso:country":"AU",
    "sg:address":"4 Sportsground Rd",
    "sg:city":"Cambrai",
    "sg:classifiers":[
        {
            "category":"Autos & Motor Vehicles",
            "subcategory":"Auto Supplies",
            "type":"Retail Goods"
        }
    ],
    "sg:phone":"+61 8 8564 5122",
    "sg:postcode":"5353",
    "sg:province":"SA",
    "sg:tags":[
        "part",
        "cycles",
        "accessory"
    ],
    "wof:name":"Reband Pty Ltd",
    "wof:placetype":"venue"
},
  "geometry": {"coordinates":[139.28294372600001,-34.6572685242],"type":"Point"}
}