{
  "type": "Feature",
  "properties": {
    "iso:country":"AU",
    "sg:address":"Unit 2 10 Casino Rd",
    "sg:city":"Casino",
    "sg:classifiers":[
        {
            "category":"Manufacturing",
            "subcategory":"Rubber & Plastics",
            "type":"Manufacturing & Wholesale Goods"
        }
    ],
    "sg:phone":"+61 2 6662 6668",
    "sg:postcode":"2470",
    "sg:province":"NSW",
    "sg:tags":[
        "moulders"
    ],
    "wof:name":"Newton Plastics",
    "wof:placetype":"venue"
},
  "geometry": {"coordinates":[153.068893433,-28.8592529297],"type":"Point"}
}