{
  "type": "Feature",
  "properties": {
    "addr:full":"Koombekine Rd Dowerin WA 6461",
    "addr:postcode":"6461",
    "addr:street":"Koombekine Rd",
    "iso:country":"AU",
    "sg:address":"Koombekine Rd",
    "sg:city":"Dowerin",
    "sg:classifiers":[
        {
            "category":"Farming",
            "subcategory":"Farm",
            "type":"Manufacturing & Wholesale Goods"
        }
    ],
    "sg:phone":"+61 8 9631 1072",
    "sg:postcode":"6461",
    "sg:province":"WA",
    "sg:tags":[
        "farmer"
    ],
    "wof:name":"King P R & S D",
    "wof:placetype":"venue"
},
  "geometry": {"coordinates":[117.034759522,-31.1758079529],"type":"Point"}
}