{
  "type": "Feature",
  "properties": {
    "addr:full":"68 Drummond St Sinnamon Park QLD 4073",
    "addr:housenumber":"68",
    "addr:postcode":"4073",
    "addr:street":"Drummond St",
    "iso:country":"AU",
    "sg:address":"68 Drummond St",
    "sg:city":"Sinnamon Park",
    "sg:classifiers":[
        {
            "category":"Professional",
            "subcategory":"Business Services",
            "type":"Services"
        }
    ],
    "sg:phone":"+61 7 3279 0588",
    "sg:postcode":"4073",
    "sg:province":"QLD",
    "sg:tags":[
        "exporter"
    ],
    "wof:name":"Link Access Pty Ltd",
    "wof:placetype":"venue"
},
  "geometry": {"coordinates":[152.94891357399999,-27.5429897308],"type":"Point"}
}