{
  "type": "Feature",
  "properties": {
    "addr:full":"Lvl 1/90 Mona Vale Suite 33 Mona Vale NSW 2103",
    "addr:housenumber":"/ 90;33",
    "addr:postcode":"2103",
    "addr:street":"Mona",
    "iso:country":"AU",
    "sg:address":"Lvl 1/90 Mona Vale Suite 33",
    "sg:city":"Mona Vale",
    "sg:classifiers":[
        {
            "category":"Health Services",
            "subcategory":"Doctor",
            "type":"Services"
        }
    ],
    "sg:phone":"+61 415 319 940",
    "sg:postcode":"2103",
    "sg:province":"NSW",
    "sg:tags":[
        "medical",
        "practitioner"
    ],
    "wof:name":"Black Dr Frances",
    "wof:placetype":"venue"
},
  "geometry": {"coordinates":[151.28941345199999,-33.6761665344],"type":"Point"}
}