{
  "type": "Feature",
  "properties": {
    "addr:full":"51 Temple Drv Thomastown VIC 3074",
    "addr:housenumber":"51",
    "addr:postcode":"3074",
    "addr:street":"Temple Drv",
    "iso:country":"AU",
    "sg:address":"51 Temple Drv",
    "sg:city":"Thomastown",
    "sg:classifiers":[
        {
            "category":"Manufacturing",
            "subcategory":"Glass & Minerals",
            "type":"Manufacturing & Wholesale Goods"
        }
    ],
    "sg:phone":"+61 3 9465 8599",
    "sg:postcode":"3074",
    "sg:province":"VIC",
    "sg:tags":[
        "fabricator",
        "foam",
        "processor"
    ],
    "wof:name":"A.B.C. Foam Makers",
    "wof:placetype":"venue"
},
  "geometry": {"coordinates":[145.01510620100001,-37.6901626587],"type":"Point"}
}