{
  "type": "Feature",
  "properties": {
    "iso:country":"AU",
    "sg:address":"Cnr Pacific Hwy & Warabrook Blv",
    "sg:city":"Warabrook",
    "sg:classifiers":[
        {
            "category":"Professional",
            "subcategory":"Accounting & Tax Preparation",
            "type":"Services"
        }
    ],
    "sg:phone":"+61 2 4923 4000",
    "sg:postcode":"2304",
    "sg:province":"NSW",
    "sg:tags":[
        "accountant",
        "auditor"
    ],
    "wof:name":"Croese Tony",
    "wof:placetype":"venue"
},
  "geometry": {"coordinates":[151.71620178200001,-32.8793029785],"type":"Point"}
}