{
  "type": "Feature",
  "properties": {
    "addr:full":"4 Gheringhap St Geelong VIC 3220",
    "addr:housenumber":"4",
    "addr:postcode":"3220",
    "addr:street":"Gheringhap St",
    "iso:country":"AU",
    "sg:address":"4 Gheringhap St",
    "sg:city":"Geelong",
    "sg:classifiers":[
        {
            "category":"Organizations",
            "subcategory":"Labor Organization",
            "type":"Services"
        }
    ],
    "sg:phone":"+61 3 5229 1415",
    "sg:postcode":"3220",
    "sg:province":"VIC",
    "sg:tags":[
        "union"
    ],
    "wof:name":"Trades Hall Council",
    "wof:placetype":"venue"
},
  "geometry": {"coordinates":[144.35931400000001,-38.143661],"type":"Point"}
}