{
  "type": "Feature",
  "properties": {
    "addr:full":"59 High St Wodonga VIC 3690",
    "addr:housenumber":"59",
    "addr:postcode":"3690",
    "addr:street":"High St",
    "iso:country":"AU",
    "sg:address":"59 High St",
    "sg:city":"Wodonga",
    "sg:classifiers":[
        {
            "category":"Sports & Exercise",
            "subcategory":"Ski Slope",
            "type":"Entertainment"
        }
    ],
    "sg:phone":"+61 2 6056 1388",
    "sg:postcode":"3690",
    "sg:province":"VIC",
    "sg:tags":[
        "equipment",
        "hire",
        "retail",
        "snow"
    ],
    "wof:name":"Brunoskis Ski Hire",
    "wof:placetype":"venue"
},
  "geometry": {"coordinates":[146.890014648,-36.1174888611],"type":"Point"}
}