{
  "type": "Feature",
  "properties": {
    "addr:full":"Unit 7/ 24 Vale St Malaga WA 6090",
    "addr:housenumber":"24",
    "addr:postcode":"6090",
    "addr:street":"Vale St",
    "iso:country":"AU",
    "sg:address":"Unit 7/ 24 Vale St",
    "sg:city":"Malaga",
    "sg:classifiers":[
        {
            "category":"Communications",
            "subcategory":"Film & Video Production",
            "type":"Services"
        }
    ],
    "sg:phone":"+61 8 9248 6330",
    "sg:postcode":"6090",
    "sg:province":"WA",
    "sg:tags":[
        "equipment",
        "window",
        "operating"
    ],
    "wof:name":"2RM Installations",
    "wof:placetype":"venue"
},
  "geometry": {"coordinates":[115.892700195,-31.848405838],"type":"Point"}
}