{
  "type": "Feature",
  "properties": {
    "addr:full":"6 Neptune Crt Mt Sheridan QLD 4868",
    "addr:housenumber":"6",
    "addr:postcode":"4868",
    "addr:street":"Neptune Crt Mt",
    "iso:country":"AU",
    "sg:address":"6 Neptune Crt",
    "sg:city":"Mt Sheridan",
    "sg:classifiers":[
        {
            "category":"Professional",
            "subcategory":"Business Services",
            "type":"Services"
        }
    ],
    "sg:phone":"+61 7 4036 1690",
    "sg:postcode":"4868",
    "sg:province":"QLD",
    "sg:tags":[
        "drafting"
    ],
    "wof:name":"Jim Papas Drafting Pty Ltd",
    "wof:placetype":"venue"
},
  "geometry": {"coordinates":[145.73817443900001,-16.9963092804],"type":"Point"}
}