{
  "type": "Feature",
  "properties": {
    "iso:country":"AU",
    "sg:address":"10 Derwent Ave",
    "sg:city":"Wagga Wagga",
    "sg:classifiers":[
        {
            "category":"Professional",
            "subcategory":"Computer Services",
            "type":"Services"
        }
    ],
    "sg:phone":"+61 2 6926 1700",
    "sg:postcode":"2650",
    "sg:province":"NSW",
    "sg:tags":[
        "consultant",
        "system"
    ],
    "wof:name":"Wagga Systems Support Services",
    "wof:placetype":"venue"
},
  "geometry": {"coordinates":[147.360794067,-35.1580276489],"type":"Point"}
}