{
  "type": "Feature",
  "properties": {
    "iso:country":"AU",
    "sg:address":"447 King St",
    "sg:city":"Newtown",
    "sg:classifiers":[
        {
            "category":"Personal",
            "subcategory":"Massage",
            "type":"Services"
        }
    ],
    "sg:phone":"+61 2 9557 2663",
    "sg:postcode":"2042",
    "sg:province":"NSW",
    "sg:tags":[
        "therapy"
    ],
    "wof:name":"Sabai Thai Therapeutic Massage",
    "wof:placetype":"venue"
},
  "geometry": {"coordinates":[151.178436,-33.901157],"type":"Point"}
}