{
  "type": "Feature",
  "properties": {
    "iso:country":"AU",
    "sg:address":"Level 1, Suite 107 26- 28 Gibbs St",
    "sg:city":"Miranda",
    "sg:classifiers":[
        {
            "category":"Health Services",
            "subcategory":"Health Practitioner",
            "type":"Services"
        }
    ],
    "sg:phone":"+61 2 9531 7370",
    "sg:postcode":"2228",
    "sg:province":"NSW",
    "sg:tags":[
        "acupuncture"
    ],
    "wof:name":"Acufirst Acupuncture & Chinese Medicine Clinic",
    "wof:placetype":"venue"
},
  "geometry": {"coordinates":[151.10267639200001,-34.0367355347],"type":"Point"}
}