{
  "type": "Feature",
  "properties": {
    "addr:full":"15-17 Jennifer Ave Ridgehaven SA 5097",
    "addr:housenumber":"15-17",
    "addr:postcode":"5097",
    "addr:street":"Jennifer Ave",
    "iso:country":"AU",
    "sg:address":"15-17 Jennifer Ave",
    "sg:city":"Ridgehaven",
    "sg:classifiers":[
        {
            "category":"Building & Trades",
            "subcategory":"Construction",
            "type":"Services"
        }
    ],
    "sg:phone":"+61 8 8396 7011",
    "sg:postcode":"5097",
    "sg:province":"SA",
    "sg:tags":[
        "fencing",
        "contractor"
    ],
    "wof:name":"Lysaght",
    "wof:placetype":"venue"
},
  "geometry": {"coordinates":[138.69790649399999,-34.8246841431],"type":"Point"}
}