{
  "type": "Feature",
  "properties": {
    "addr:full":"21 Dudley St Punchbowl NSW 2196",
    "addr:housenumber":"21",
    "addr:postcode":"2196",
    "addr:street":"Dudley St",
    "iso:country":"AU",
    "sg:address":"21 Dudley St",
    "sg:city":"Punchbowl",
    "sg:classifiers":[
        {
            "category":"Social Services",
            "subcategory":"Child Care",
            "type":"Services"
        }
    ],
    "sg:phone":"+61 2 9759 1327",
    "sg:postcode":"2196",
    "sg:province":"NSW",
    "wof:name":"Playtime Pre-School Long Day Care Centre Punchbowl",
    "wof:placetype":"venue"
},
  "geometry": {"coordinates":[151.05961600000001,-33.925667],"type":"Point"}
}