{
  "type": "Feature",
  "properties": {
    "iso:country":"AU",
    "sg:address":"26 Hilda St",
    "sg:city":"Balwyn",
    "sg:classifiers":[
        {
            "category":"Social Services",
            "subcategory":"Retirement Home",
            "type":"Services"
        }
    ],
    "sg:phone":"+61 3 9817 5595",
    "sg:postcode":"3103",
    "sg:province":"VIC",
    "sg:tags":[
        "environmental",
        "consultant",
        "pollution"
    ],
    "wof:name":"Lyons Mike & Associates Pty Ltd",
    "wof:placetype":"venue"
},
  "geometry": {"coordinates":[145.075775147,-37.805065155],"type":"Point"}
}