{
  "type": "Feature",
  "properties": {
    "addr:full":"23 Ann St Dandenong VIC 3175",
    "addr:housenumber":"23",
    "addr:postcode":"3175",
    "addr:street":"Ann St",
    "iso:country":"AU",
    "sg:address":"23 Ann St",
    "sg:city":"Dandenong",
    "sg:classifiers":[
        {
            "category":"Education",
            "subcategory":"School",
            "type":"Public Place"
        }
    ],
    "sg:phone":"+61 3 8792 7200",
    "sg:postcode":"3175",
    "sg:province":"VIC",
    "sg:tags":[
        "state",
        "except",
        "nsw"
    ],
    "wof:name":"Cleeland Secondary College",
    "wof:placetype":"venue"
},
  "geometry": {"coordinates":[145.21290588400001,-37.9784545898],"type":"Point"}
}