{
  "type": "Feature",
  "properties": {
    "addr:full":"7 Mary Crt Hillbank SA 5112",
    "addr:housenumber":"7",
    "addr:postcode":"5112",
    "addr:street":"Mary Crt",
    "iso:country":"AU",
    "sg:address":"7 Mary Crt",
    "sg:city":"Hillbank",
    "sg:classifiers":[
        {
            "category":"Retail",
            "subcategory":"Auto Repair",
            "type":"Services"
        }
    ],
    "sg:phone":"+61 411 180 080",
    "sg:postcode":"5112",
    "sg:province":"SA",
    "sg:tags":[
        "beater",
        "painter",
        "panel"
    ],
    "wof:name":"Fix-A-Dent",
    "wof:placetype":"venue"
},
  "geometry": {"coordinates":[138.68284606899999,-34.7527275085],"type":"Point"}
}