{
  "type": "Feature",
  "properties": {
    "addr:full":"18- 24 Townshend St Phillip ACT 2606",
    "addr:housenumber":"24",
    "addr:postcode":"2606",
    "addr:street":"Townshend St",
    "iso:country":"AU",
    "sg:address":"18- 24 Townshend St",
    "sg:city":"Phillip",
    "sg:classifiers":[
        {
            "category":"Coffee & Tea",
            "type":"Food & Drink"
        }
    ],
    "sg:phone":"+61 2 6282 3424",
    "sg:postcode":"2606",
    "sg:province":"ACT",
    "sg:tags":[
        "kayak",
        "canoe"
    ],
    "wof:name":"Great Outdoors Centre",
    "wof:placetype":"venue"
},
  "geometry": {"coordinates":[149.087814331,-35.3519630432],"type":"Point"}
}