{
  "type": "Feature",
  "properties": {
    "addr:full":"Shop 6, 179- 181 Avoca Drv Avoca Beach NSW 2251",
    "addr:housenumber":"shop 6;181",
    "addr:postcode":"179;2251",
    "addr:street":"Avoca Drv",
    "iso:country":"AU",
    "sg:address":"Shop 6, 179- 181 Avoca Drv",
    "sg:city":"Avoca Beach",
    "sg:classifiers":[
        {
            "category":"Personal",
            "subcategory":"Beauty Salon",
            "type":"Services"
        }
    ],
    "sg:phone":"+61 2 4382 3995",
    "sg:postcode":"2251",
    "sg:province":"NSW",
    "wof:name":"Classique Beaute Therapy",
    "wof:placetype":"venue"
},
  "geometry": {"coordinates":[151.43394470199999,-33.4671630859],"type":"Point"}
}