{
  "type": "Feature",
  "properties": {
    "addr:full":"18 Anderson St Williamstown VIC 3016",
    "addr:housenumber":"18",
    "addr:postcode":"3016",
    "addr:street":"Anderson St",
    "iso:country":"AU",
    "sg:address":"18 Anderson St",
    "sg:city":"Williamstown",
    "sg:classifiers":[
        {
            "category":"Building & Trades",
            "subcategory":"Plumbing",
            "type":"Services"
        }
    ],
    "sg:phone":"+61 3 9397 5544",
    "sg:postcode":"3016",
    "sg:province":"VIC",
    "sg:tags":[
        "plumber",
        "gasfitters"
    ],
    "wof:name":"A & C Plumbing",
    "wof:placetype":"venue"
},
  "geometry": {"coordinates":[144.87843322800001,-37.8448829651],"type":"Point"}
}