{
  "type": "Feature",
  "properties": {
    "iso:country":"AU",
    "sg:address":"1a William St",
    "sg:city":"Esperance",
    "sg:classifiers":[
        {
            "category":"Travel",
            "subcategory":"Hotels & Motels",
            "type":"Entertainment"
        }
    ],
    "sg:phone":"+61 8 9071 3587",
    "sg:postcode":"6450",
    "sg:province":"WA",
    "wof:name":"Clearwater Motel Apartments",
    "wof:placetype":"venue"
},
  "geometry": {"coordinates":[121.891052246,-33.8648033142],"type":"Point"}
}