{
  "type": "Feature",
  "properties": {
    "addr:full":"2A/ 49 Sherwood Rd Toowong QLD 4066",
    "addr:housenumber":"2a / 49",
    "addr:postcode":"4066",
    "addr:street":"Sherwood Rd",
    "iso:country":"AU",
    "sg:address":"2A/ 49 Sherwood Rd",
    "sg:city":"Toowong",
    "sg:classifiers":[
        {
            "category":"Real Estate",
            "subcategory":"Real Estate Agent",
            "type":"Services"
        }
    ],
    "sg:phone":"+61 7 3870 1800",
    "sg:postcode":"4066",
    "sg:province":"QLD",
    "wof:name":"Property House Toowong",
    "wof:placetype":"venue"
},
  "geometry": {"coordinates":[152.99079895,-27.4851932526],"type":"Point"}
}