{
  "type": "Feature",
  "properties": {
    "addr:full":"500 Magill Rd Magill SA 5072",
    "addr:housenumber":"500",
    "addr:postcode":"5072",
    "addr:street":"Magill Rd",
    "iso:country":"AU",
    "sg:address":"500 Magill Rd",
    "sg:city":"Magill",
    "sg:classifiers":[
        {
            "category":"Health Services",
            "subcategory":"Health Practitioner",
            "type":"Services"
        }
    ],
    "sg:phone":"+61 402 763 222",
    "sg:postcode":"5072",
    "sg:province":"SA",
    "sg:tags":[
        "dietitian"
    ],
    "wof:name":"Pamela Zhang",
    "wof:placetype":"venue"
},
  "geometry": {"coordinates":[138.66911315900001,-34.9135055542],"type":"Point"}
}