{
  "type": "Feature",
  "properties": {
    "addr:full":"48 Exhibition Rd Gympie QLD 4570",
    "addr:housenumber":"48",
    "addr:postcode":"4570",
    "addr:street":"Exhibition Rd",
    "iso:country":"AU",
    "sg:address":"48 Exhibition Rd",
    "sg:city":"Gympie",
    "sg:classifiers":[
        {
            "category":"Food & Beverages",
            "subcategory":"Groceries & Convenience Stores",
            "type":"Retail Goods"
        }
    ],
    "sg:phone":"+61 7 5482 4236",
    "sg:postcode":"4570",
    "sg:province":"QLD",
    "wof:name":"Southside Shop",
    "wof:placetype":"venue"
},
  "geometry": {"coordinates":[152.647613525,-26.1991996765],"type":"Point"}
}