{
  "type": "Feature",
  "properties": {
    "iso:country":"AU",
    "sg:address":"9 Milton St",
    "sg:city":"Beresfield",
    "sg:classifiers":[
        {
            "category":"Social Services",
            "subcategory":"Child Care",
            "type":"Services"
        }
    ],
    "sg:phone":"+61 2 4966 1262",
    "sg:postcode":"2322",
    "sg:province":"NSW",
    "wof:name":"Beresfield Child Care Centre",
    "wof:placetype":"venue"
},
  "geometry": {"coordinates":[151.657546997,-32.8000946045],"type":"Point"}
}