{
  "type": "Feature",
  "properties": {
    "iso:country":"AU",
    "sg:address":"15 Elkhorn Pl",
    "sg:city":"Alfords Point",
    "sg:classifiers":[
        {
            "category":"Building & Trades",
            "subcategory":"Pest Control",
            "type":"Services"
        }
    ],
    "sg:phone":"+61 2 9543 0093",
    "sg:postcode":"2234",
    "sg:province":"NSW",
    "wof:name":"Pest and Termite Pty Ltd",
    "wof:placetype":"venue"
},
  "geometry": {"coordinates":[151.04200744600001,-33.9986190796],"type":"Point"}
}