{
  "type": "Feature",
  "properties": {
    "addr:full":"13 Waringa Drv Wendouree VIC 3355",
    "addr:housenumber":"13",
    "addr:postcode":"3355",
    "addr:street":"Waringa Drv",
    "iso:country":"AU",
    "sg:address":"13 Waringa Drv",
    "sg:city":"Wendouree",
    "sg:classifiers":[
        {
            "category":"Manufacturing",
            "subcategory":"Tools & Machinery",
            "type":"Manufacturing & Wholesale Goods"
        }
    ],
    "sg:phone":"+61 3 5338 1010",
    "sg:postcode":"3355",
    "sg:province":"VIC",
    "sg:tags":[
        "fastener",
        "industrial"
    ],
    "wof:name":"Ozpress",
    "wof:placetype":"venue"
},
  "geometry": {"coordinates":[143.80917400000001,-37.518711],"type":"Point"}
}