{
  "type": "Feature",
  "properties": {
    "addr:full":"3970 Mareeba Dimbulah Rd Dimbulah QLD 4872",
    "addr:postcode":"3970;4872",
    "addr:street":"Dimbulah Rd",
    "iso:country":"AU",
    "sg:address":"3970 Mareeba Dimbulah Rd",
    "sg:city":"Dimbulah",
    "sg:classifiers":[
        {
            "category":"Farming",
            "subcategory":"Farm",
            "type":"Manufacturing & Wholesale Goods"
        }
    ],
    "sg:phone":"+61 7 4093 1180",
    "sg:postcode":"4872",
    "sg:province":"QLD",
    "sg:tags":[
        "farmer"
    ],
    "wof:name":"Pozzebon E & A P",
    "wof:placetype":"venue"
},
  "geometry": {"coordinates":[145.11717224099999,-17.1461334229],"type":"Point"}
}