{
  "type": "Feature",
  "properties": {
    "addr:full":"150 Johnston St Collingwood VIC 3066",
    "addr:housenumber":"150",
    "addr:postcode":"3066",
    "addr:street":"Johnston St",
    "iso:country":"AU",
    "sg:address":"150 Johnston St",
    "sg:city":"Collingwood",
    "sg:classifiers":[
        {
            "category":"Government",
            "subcategory":"Post Office",
            "type":"Public Place"
        }
    ],
    "sg:phone":"+61 3 9415 6510",
    "sg:postcode":"3066",
    "sg:province":"VIC",
    "sg:tags":[
        "yoga"
    ],
    "wof:name":"Samata Yoga International",
    "wof:placetype":"venue"
},
  "geometry": {"coordinates":[144.990112305,-37.7994117737],"type":"Point"}
}