{
  "type": "Feature",
  "properties": {
    "iso:country":"AU",
    "sg:address":"33a Langtree Ave",
    "sg:city":"Mildura",
    "sg:classifiers":[
        {
            "category":"Personal",
            "type":"Services"
        }
    ],
    "sg:phone":"+61 3 5023 2347",
    "sg:postcode":"3500",
    "sg:province":"VIC",
    "sg:tags":[
        "gift"
    ],
    "wof:name":"Derimar Florists",
    "wof:placetype":"venue"
},
  "geometry": {"coordinates":[142.16200256400001,-34.1835708618],"type":"Point"}
}