{
  "type": "Feature",
  "properties": {
    "iso:country":"AU",
    "sg:address":"42- 50 Rowe St",
    "sg:city":"Eastwood",
    "sg:classifiers":[
        {
            "category":"Home & Garden",
            "subcategory":"Hardware",
            "type":"Retail Goods"
        }
    ],
    "sg:phone":"+61 2 9874 8777",
    "sg:postcode":"2122",
    "sg:province":"NSW",
    "sg:tags":[
        "plumber",
        "supply"
    ],
    "sg:website":"http://www.pscoop.com.au",
    "wof:name":"Plumbers Supplies",
    "wof:placetype":"venue"
},
  "geometry": {"coordinates":[151.084838867,-33.7909164429],"type":"Point"}
}