{
  "type": "Feature",
  "properties": {
    "addr:full":"11/10- 14 Robert St Telopea NSW 2117",
    "addr:housenumber":"11 / 10 14",
    "addr:postcode":"2117",
    "addr:street":"Robert St",
    "iso:country":"AU",
    "sg:address":"11/10- 14 Robert St",
    "sg:city":"Telopea",
    "sg:classifiers":[
        {
            "category":"Education",
            "subcategory":"Music School",
            "type":"Public Place"
        }
    ],
    "sg:phone":"+61 2 9871 4507",
    "sg:postcode":"2117",
    "sg:province":"NSW",
    "sg:tags":[
        "teacher"
    ],
    "wof:name":"Clift C.M.",
    "wof:placetype":"venue"
},
  "geometry": {"coordinates":[151.040283203,-33.7942619324],"type":"Point"}
}