{
  "type": "Feature",
  "properties": {
    "iso:country":"AU",
    "sg:address":"Suite 5, 18",
    "sg:city":"Napier Cl Deakin",
    "sg:classifiers":[
        {
            "category":"Banks & Credit Unions",
            "subcategory":"Financial Services",
            "type":"Services"
        }
    ],
    "sg:phone":"+61 2 6282 2324",
    "sg:postcode":"2600",
    "sg:province":"ACT",
    "sg:tags":[
        "planning"
    ],
    "wof:name":"Associated Planners Financial Services Ltd",
    "wof:placetype":"venue"
},
  "geometry": {"coordinates":[149.10842895499999,-35.314781189],"type":"Point"}
}