{
  "type": "Feature",
  "properties": {
    "iso:country":"AU",
    "sg:address":"6 Illawara Crt",
    "sg:city":"Beaconsfield",
    "sg:classifiers":[
        {
            "category":"Building & Trades",
            "subcategory":"Construction",
            "type":"Services"
        }
    ],
    "sg:phone":"+61 7 4942 1025",
    "sg:postcode":"4740",
    "sg:province":"QLD",
    "sg:tags":[
        "concrete",
        "contractor"
    ],
    "wof:name":"Mather Concrete Services",
    "wof:placetype":"venue"
},
  "geometry": {"coordinates":[149.170456,-21.096771],"type":"Point"}
}