{
  "type": "Feature",
  "properties": {
    "addr:full":"568 Englehardt St Albury NSW 2640",
    "addr:housenumber":"568",
    "addr:postcode":"2640",
    "addr:street":"Englehardt St",
    "iso:country":"AU",
    "sg:address":"568 Englehardt St",
    "sg:city":"Albury",
    "sg:classifiers":[
        {
            "category":"Health Services",
            "subcategory":"Chiropractor",
            "type":"Services"
        }
    ],
    "sg:phone":"+61 2 6021 3879",
    "sg:postcode":"2640",
    "sg:province":"NSW",
    "wof:name":"Alchin Chiropractic",
    "wof:placetype":"venue"
},
  "geometry": {"coordinates":[146.91456604000001,-36.0779685974],"type":"Point"}
}