{
  "type": "Feature",
  "properties": {
    "addr:full":"1536 Nepean Hwy Mt Eliza VIC 3930",
    "addr:housenumber":"1536",
    "addr:postcode":"3930",
    "addr:street":"Nepean Hwy",
    "iso:country":"AU",
    "sg:address":"1536 Nepean Hwy",
    "sg:city":"Mt Eliza",
    "sg:classifiers":[
        {
            "category":"Personal",
            "type":"Services"
        }
    ],
    "sg:phone":"+61 3 9787 8923",
    "sg:postcode":"3930",
    "sg:province":"VIC",
    "sg:tags":[
        "reducing",
        "treatment",
        "weight"
    ],
    "wof:name":"Bayside Hypnotherapy",
    "wof:placetype":"venue"
},
  "geometry": {"coordinates":[145.09706115700001,-38.1851387024],"type":"Point"}
}