{
  "type": "Feature",
  "properties": {
    "iso:country":"AU",
    "sg:address":"13 Chelona School Acess Rd",
    "sg:city":"Chelona",
    "sg:classifiers":[
        {
            "category":"Education",
            "subcategory":"School",
            "type":"Public Place"
        }
    ],
    "sg:phone":"+61 7 4959 5216",
    "sg:postcode":"4740",
    "sg:province":"QLD",
    "sg:tags":[
        "state",
        "except",
        "nsw"
    ],
    "wof:name":"Chelona Primary School",
    "wof:placetype":"venue"
},
  "geometry": {"coordinates":[149.1436,-21.260824],"type":"Point"}
}