{
  "type": "Feature",
  "properties": {
    "addr:full":"13 Chelona School Acess Rd Chelona QLD 4740",
    "addr:housenumber":"13",
    "addr:postcode":"4740",
    "addr:street":"Chelona;Acess Rd",
    "iso:country":"AU",
    "sg:address":"13 Chelona School Acess Rd",
    "sg:city":"Chelona",
    "sg:classifiers":[
        {
            "category":"Education",
            "subcategory":"School",
            "type":"Public Place"
        }
    ],
    "sg:phone":"+61 7 4959 5216",
    "sg:postcode":"4740",
    "sg:province":"QLD",
    "sg:tags":[
        "state",
        "except",
        "nsw"
    ],
    "wof:name":"Chelona Primary School",
    "wof:placetype":"venue"
},
  "geometry": {"coordinates":[149.14359999999999,-21.260824],"type":"Point"}
}