{
  "type": "Feature",
  "properties": {
    "iso:country":"AU",
    "sg:address":"Park St",
    "sg:city":"Pingelly",
    "sg:classifiers":[
        {
            "category":"Education",
            "subcategory":"School",
            "type":"Public Place"
        }
    ],
    "sg:phone":"+61 8 9887 1061",
    "sg:postcode":"6308",
    "sg:province":"WA",
    "sg:tags":[
        "state",
        "except",
        "nsw"
    ],
    "wof:name":"Pingelly District High School",
    "wof:placetype":"venue"
},
  "geometry": {"coordinates":[117.08344268800001,-32.5327606201],"type":"Point"}
}