{
  "type": "Feature",
  "properties": {
    "iso:country":"AU",
    "sg:address":"1/ 7 Lear Jet Drv",
    "sg:city":"Caboolture",
    "sg:classifiers":[
        {
            "category":"Utilities",
            "subcategory":"Telephone",
            "type":"Services"
        }
    ],
    "sg:phone":"+61 7 5428 0288",
    "sg:postcode":"4510",
    "sg:province":"QLD",
    "sg:tags":[
        "installation",
        "system",
        "maintenance"
    ],
    "wof:name":"A.C.L. Electronics",
    "wof:placetype":"venue"
},
  "geometry": {"coordinates":[152.98049900000001,-27.080149],"type":"Point"}
}