{
  "type": "Feature",
  "properties": {
    "iso:country":"AU",
    "sg:address":"49 South Rd",
    "sg:city":"Hindmarsh",
    "sg:classifiers":[
        {
            "category":"Professional",
            "type":"Services"
        }
    ],
    "sg:phone":"+61 8 8340 0542",
    "sg:postcode":"5007",
    "sg:province":"SA",
    "sg:tags":[
        "spray",
        "painting"
    ],
    "wof:name":"Pro Paint 'n Panel",
    "wof:placetype":"venue"
},
  "geometry": {"coordinates":[138.56524658199999,-34.9085159302],"type":"Point"}
}