{
  "type": "Feature",
  "properties": {
    "iso:country":"AU",
    "sg:address":"5 Mitala St",
    "sg:city":"Newport",
    "sg:classifiers":[
        {
            "category":"Building & Trades",
            "subcategory":"Construction",
            "type":"Services"
        }
    ],
    "sg:phone":"+61 2 9979 1286",
    "sg:postcode":"2106",
    "sg:province":"NSW",
    "sg:tags":[
        "contractor"
    ],
    "wof:name":"Broken Bay Constructions",
    "wof:placetype":"venue"
},
  "geometry": {"coordinates":[151.30563354500001,-33.6550254822],"type":"Point"}
}