{
  "type": "Feature",
  "properties": {
    "iso:country":"AU",
    "sg:address":"70 Kingsway Drv",
    "sg:city":"Lalor",
    "sg:classifiers":[
        {
            "category":"Farming",
            "subcategory":"Farm & Veterinary Services",
            "type":"Manufacturing & Wholesale Goods"
        }
    ],
    "sg:phone":"+61 3 9464 3233",
    "sg:postcode":"3075",
    "sg:province":"VIC",
    "sg:tags":[
        "poultry",
        "processing",
        "supply"
    ],
    "wof:name":"Mario's Poultry",
    "wof:placetype":"venue"
},
  "geometry": {"coordinates":[145.008178711,-37.6644592285],"type":"Point"}
}