{
  "type": "Feature",
  "properties": {
    "addr:full":"11 Banool Ave Mt Evelyn VIC 3796",
    "addr:housenumber":"11",
    "addr:postcode":"3796",
    "addr:street":"Banool Ave",
    "iso:country":"AU",
    "sg:address":"11 Banool Ave",
    "sg:city":"Mt Evelyn",
    "sg:classifiers":[
        {
            "category":"Building & Trades",
            "subcategory":"Construction",
            "type":"Services"
        }
    ],
    "sg:phone":"+61 3 9736 1661",
    "sg:postcode":"3796",
    "sg:province":"VIC",
    "sg:tags":[
        "contractor"
    ],
    "wof:name":"Geere R V",
    "wof:placetype":"venue"
},
  "geometry": {"coordinates":[145.387252808,-37.793056488],"type":"Point"}
}