{
  "type": "Feature",
  "properties": {
    "addr:full":"27 Skye Crt Kellyville NSW 2155",
    "addr:housenumber":"27",
    "addr:postcode":"2155",
    "addr:street":"Skye Crt",
    "iso:country":"AU",
    "sg:address":"27 Skye Crt",
    "sg:city":"Kellyville",
    "sg:classifiers":[
        {
            "category":"Professional",
            "subcategory":"Art Services",
            "type":"Services"
        }
    ],
    "sg:phone":"+61 413 024 499",
    "sg:postcode":"2155",
    "sg:province":"NSW",
    "sg:tags":[
        "decorator",
        "painter"
    ],
    "wof:name":"Cubic Painting & Decorating Pty Ltd",
    "wof:placetype":"venue"
},
  "geometry": {"coordinates":[150.97134399399999,-33.7021141052],"type":"Point"}
}