{
  "type": "Feature",
  "properties": {
    "addr:full":"32 Greenwell Point Rd Greenwell Point NSW 2540",
    "addr:housenumber":"32",
    "addr:postcode":"2540",
    "addr:street":"Greenwell Point Rd",
    "iso:country":"AU",
    "sg:address":"32 Greenwell Point Rd",
    "sg:city":"Greenwell Point",
    "sg:classifiers":[
        {
            "category":"Farming",
            "subcategory":"Fish & Marine Products",
            "type":"Manufacturing & Wholesale Goods"
        }
    ],
    "sg:phone":"+61 2 4447 1290",
    "sg:postcode":"2540",
    "sg:province":"NSW",
    "sg:tags":[
        "supplier",
        "oyster",
        "farmer"
    ],
    "wof:name":"Shoalhaven Oyster Service",
    "wof:placetype":"venue"
},
  "geometry": {"coordinates":[150.56593322800001,-34.8235549927],"type":"Point"}
}