{
  "type": "Feature",
  "properties": {
    "addr:full":"536 Melton Hwy Sydenham VIC 3037",
    "addr:housenumber":"536",
    "addr:postcode":"3037",
    "addr:street":"Melton Hwy",
    "iso:country":"AU",
    "sg:address":"536 Melton Hwy",
    "sg:city":"Sydenham",
    "sg:classifiers":[
        {
            "category":"Health Services",
            "subcategory":"Dentist",
            "type":"Services"
        }
    ],
    "sg:phone":"+61 3 9390 4533",
    "sg:postcode":"3037",
    "sg:province":"VIC",
    "wof:name":"Maimur A",
    "wof:placetype":"venue"
},
  "geometry": {"coordinates":[144.76333600000001,-37.693909],"type":"Point"}
}