{
  "type": "Feature",
  "properties": {
    "addr:full":"PO Box 92 Woodanilling WA 6316",
    "addr:postcode":"6316",
    "iso:country":"AU",
    "sg:address":"PO Box 92",
    "sg:city":"Woodanilling",
    "sg:classifiers":[
        {
            "category":"Farming",
            "subcategory":"Farm",
            "type":"Manufacturing & Wholesale Goods"
        }
    ],
    "sg:phone":"+61 8 9823 1515",
    "sg:postcode":"6316",
    "sg:province":"WA",
    "sg:tags":[
        "farmer"
    ],
    "wof:name":"Garstone R & J",
    "wof:placetype":"venue"
},
  "geometry": {"coordinates":[117.423820496,-33.5626792908],"type":"Point"}
}