{
  "type": "Feature",
  "properties": {
    "addr:full":"Ryan St Forbes NSW 2871",
    "addr:postcode":"2871",
    "addr:street":"Ryan St",
    "iso:country":"AU",
    "sg:address":"Ryan St",
    "sg:city":"Forbes",
    "sg:classifiers":[
        {
            "category":"Professional",
            "subcategory":"Art Services",
            "type":"Services"
        }
    ],
    "sg:phone":"+61 2 6852 2605",
    "sg:postcode":"2871",
    "sg:province":"NSW",
    "sg:tags":[
        "decorator",
        "painter"
    ],
    "wof:name":"Moore L P",
    "wof:placetype":"venue"
},
  "geometry": {"coordinates":[148.004807,-33.372353],"type":"Point"}
}