{
  "type": "Feature",
  "properties": {
    "addr:full":"34 Verbena Crs Dianella WA 6059",
    "addr:housenumber":"34",
    "addr:postcode":"6059",
    "addr:street":"Verbena Crs",
    "iso:country":"AU",
    "sg:address":"34 Verbena Crs",
    "sg:city":"Dianella",
    "sg:classifiers":[
        {
            "category":"Building & Trades",
            "subcategory":"Cleaning & Sanitation",
            "type":"Services"
        }
    ],
    "sg:phone":"+61 8 9349 0911",
    "sg:postcode":"6059",
    "sg:province":"WA",
    "sg:tags":[
        "chemical",
        "pressure",
        "steam",
        "contractor"
    ],
    "wof:name":"Avablast High Pressure Cleaning",
    "wof:placetype":"venue"
},
  "geometry": {"coordinates":[115.871528626,-31.8887805939],"type":"Point"}
}