{
  "type": "Feature",
  "properties": {
    "iso:country":"AU",
    "sg:address":"19 Chapel St",
    "sg:city":"Windsor",
    "sg:classifiers":[
        {
            "category":"Fast Food",
            "type":"Food & Drink"
        }
    ],
    "sg:phone":"+61 3 9510 1566",
    "sg:postcode":"3181",
    "sg:province":"VIC",
    "sg:tags":[
        "away",
        "take"
    ],
    "wof:name":"Papalino's Pizza Delivery",
    "wof:placetype":"venue"
},
  "geometry": {"coordinates":[144.99223327600001,-37.8570022583],"type":"Point"}
}