{
  "type": "Feature",
  "properties": {
    "addr:full":"Gt Western Hwy Springwood NSW 2777",
    "addr:postcode":"2777",
    "addr:street":"Western Hwy",
    "iso:country":"AU",
    "sg:address":"Gt Western Hwy",
    "sg:city":"Springwood",
    "sg:classifiers":[
        {
            "category":"Shopping",
            "subcategory":"Computers & Home Electronics",
            "type":"Retail Goods"
        }
    ],
    "sg:phone":"+61 2 4754 2561",
    "sg:postcode":"2777",
    "sg:province":"NSW",
    "sg:tags":[
        "equipment",
        "multimedia"
    ],
    "wof:name":"Projectorama",
    "wof:placetype":"venue"
},
  "geometry": {"coordinates":[150.57145690900001,-33.698184967],"type":"Point"}
}