{
  "type": "Feature",
  "properties": {
    "addr:full":"288 Belgrave-Gembrook Rd Clematis VIC 3782",
    "addr:housenumber":"288",
    "addr:postcode":"3782",
    "addr:street":"Belgrave-Gembrook Rd",
    "iso:country":"AU",
    "sg:address":"288 Belgrave-Gembrook Rd",
    "sg:city":"Clematis",
    "sg:classifiers":[
        {
            "category":"Shopping",
            "subcategory":"Antiques",
            "type":"Retail Goods"
        }
    ],
    "sg:phone":"+61 3 5968 3723",
    "sg:postcode":"3782",
    "sg:province":"VIC",
    "wof:name":"Old Clematis Store The",
    "wof:placetype":"venue"
},
  "geometry": {"coordinates":[145.42379800000001,-37.929375],"type":"Point"}
}