{
  "type": "Feature",
  "properties": {
    "addr:full":"16 - 20 Kerr St Fitzroy VIC 3065",
    "addr:housenumber":"20",
    "addr:postcode":"3065",
    "addr:street":"Kerr St",
    "iso:country":"AU",
    "sg:address":"16 - 20 Kerr St",
    "sg:city":"Fitzroy",
    "sg:classifiers":[
        {
            "category":"Wholesale",
            "subcategory":"Auto Parts",
            "type":"Manufacturing & Wholesale Goods"
        }
    ],
    "sg:phone":"+61 3 9419 2688",
    "sg:postcode":"3065",
    "sg:province":"VIC",
    "sg:tags":[
        "recyclers"
    ],
    "wof:name":"Hondcivic Parts",
    "wof:placetype":"venue"
},
  "geometry": {"coordinates":[144.976074219,-37.7965698242],"type":"Point"}
}