{
  "type": "Feature",
  "properties": {
    "addr:full":"465 Great Western Hwy Faulconbridge NSW 2776",
    "addr:housenumber":"465",
    "addr:postcode":"2776",
    "addr:street":"Great Western Hwy",
    "iso:country":"AU",
    "sg:address":"465 Great Western Hwy",
    "sg:city":"Faulconbridge",
    "sg:classifiers":[
        {
            "category":"Communications",
            "subcategory":"Film & Video Production",
            "type":"Services"
        }
    ],
    "sg:phone":"+61 2 4751 6119",
    "sg:postcode":"2776",
    "sg:province":"NSW",
    "sg:tags":[
        "facsimile",
        "telex"
    ],
    "wof:name":"Springwood Printing Co. Pty. Ltd.",
    "wof:placetype":"venue"
},
  "geometry": {"coordinates":[150.547805786,-33.6934928894],"type":"Point"}
}