{
  "type": "Feature",
  "properties": {
    "iso:country":"AU",
    "sg:address":"32 Martin St",
    "sg:city":"Stockinbingal",
    "sg:classifiers":[
        {
            "category":"Travel",
            "subcategory":"Hotels & Motels",
            "type":"Entertainment"
        }
    ],
    "sg:phone":"+61 2 6943 1472",
    "sg:postcode":"2725",
    "sg:province":"NSW",
    "sg:tags":[
        "accommodation"
    ],
    "wof:name":"Commercial Hotel Stockinbingal",
    "wof:placetype":"venue"
},
  "geometry": {"coordinates":[147.884079,-34.49921],"type":"Point"}
}