{
  "type": "Feature",
  "properties": {
    "addr:full":"4 Arthur St Belmont VIC 3216",
    "addr:housenumber":"4",
    "addr:postcode":"3216",
    "addr:street":"Arthur St",
    "iso:country":"AU",
    "sg:address":"4 Arthur St",
    "sg:city":"Belmont",
    "sg:classifiers":[
        {
            "category":"Communications",
            "type":"Services"
        }
    ],
    "sg:phone":"+61 3 5243 3896",
    "sg:postcode":"3216",
    "sg:province":"VIC",
    "sg:tags":[
        "antenna"
    ],
    "wof:name":"Torquay Electronics Services",
    "wof:placetype":"venue"
},
  "geometry": {"coordinates":[144.33387756400001,-38.1788635254],"type":"Point"}
}