{
  "type": "Feature",
  "properties": {
    "addr:full":"Cnr Mayne & Victoria St Murrurundi NSW 2338",
    "addr:postcode":"2338",
    "addr:street":"Cnr;St",
    "iso:country":"AU",
    "sg:address":"Cnr Mayne & Victoria St",
    "sg:city":"Murrurundi",
    "sg:classifiers":[
        {
            "category":"Wholesale",
            "subcategory":"Farm Supplies",
            "type":"Manufacturing & Wholesale Goods"
        }
    ],
    "sg:phone":"+61 2 6546 6306",
    "sg:postcode":"2338",
    "sg:province":"NSW",
    "sg:tags":[
        "equipment"
    ],
    "wof:name":"Murrurundi Produce",
    "wof:placetype":"venue"
},
  "geometry": {"coordinates":[150.834182739,-31.763299942],"type":"Point"}
}