{
  "type": "Feature",
  "properties": {
    "addr:full":"130 Argyle St Camden NSW 2570",
    "addr:housenumber":"130",
    "addr:postcode":"2570",
    "addr:street":"Argyle St",
    "iso:country":"AU",
    "sg:address":"130 Argyle St",
    "sg:city":"Camden",
    "sg:classifiers":[
        {
            "category":"Health Services",
            "subcategory":"Health Practitioner",
            "type":"Services"
        }
    ],
    "sg:phone":"+61 2 4655 6999",
    "sg:postcode":"2570",
    "sg:province":"NSW",
    "sg:tags":[
        "dietitian"
    ],
    "wof:name":"Lynden Maureen",
    "wof:placetype":"venue"
},
  "geometry": {"coordinates":[150.695404053,-34.0548973083],"type":"Point"}
}