{
  "type": "Feature",
  "properties": {
    "addr:full":"236 Old Cleveland Rd Coorparoo QLD 4151",
    "addr:housenumber":"236",
    "addr:postcode":"4151",
    "addr:street":"Old Cleveland Rd",
    "iso:country":"AU",
    "sg:address":"236 Old Cleveland Rd",
    "sg:city":"Coorparoo",
    "sg:classifiers":[
        {
            "category":"Sports & Exercise",
            "subcategory":"Gym",
            "type":"Entertainment"
        }
    ],
    "sg:phone":"+61 1300 667 022",
    "sg:postcode":"4151",
    "sg:province":"QLD",
    "sg:tags":[
        "health",
        "fitness"
    ],
    "wof:name":"Pure Health Clubs",
    "wof:placetype":"venue"
},
  "geometry": {"coordinates":[153.056396484,-27.4960384369],"type":"Point"}
}