{
  "type": "Feature",
  "properties": {
    "addr:full":"Level 5, 33 Elkhorn Ave Surfers Paradise QLD 4217",
    "addr:housenumber":"33",
    "addr:postcode":"4217",
    "addr:street":"Elkhorn Ave",
    "iso:country":"AU",
    "sg:address":"Level 5, 33 Elkhorn Ave",
    "sg:city":"Surfers Paradise",
    "sg:classifiers":[
        {
            "category":"Professional",
            "subcategory":"Management & Consulting",
            "type":"Services"
        }
    ],
    "sg:phone":"+61 7 5504 6111",
    "sg:postcode":"4217",
    "sg:province":"QLD",
    "sg:tags":[
        "consultant",
        "migration"
    ],
    "wof:name":"Sharon Harris And Associates",
    "wof:placetype":"venue"
},
  "geometry": {"coordinates":[153.42759704599999,-27.9986419678],"type":"Point"}
}