{
  "type": "Feature",
  "properties": {
    "addr:full":"57 Grove Ave Marleston SA 5033",
    "addr:housenumber":"57",
    "addr:postcode":"5033",
    "addr:street":"Grove Ave",
    "iso:country":"AU",
    "sg:address":"57 Grove Ave",
    "sg:city":"Marleston",
    "sg:classifiers":[
        {
            "category":"Professional",
            "type":"Services"
        }
    ],
    "sg:phone":"+61 8 8297 5666",
    "sg:postcode":"5033",
    "sg:province":"SA",
    "sg:tags":[
        "shop",
        "fitting"
    ],
    "wof:name":"Display & Storage Systems Pty Ltd",
    "wof:placetype":"venue"
},
  "geometry": {"coordinates":[138.56291198700001,-34.9481086731],"type":"Point"}
}