{
  "type": "Feature",
  "properties": {
    "iso:country":"AU",
    "sg:address":"5/ 541 Old Cleveland Rd",
    "sg:city":"Camp Hill",
    "sg:classifiers":[
        {
            "category":"Social Services",
            "subcategory":"Retirement Home",
            "type":"Services"
        }
    ],
    "sg:phone":"+61 7 3398 4992",
    "sg:postcode":"4152",
    "sg:province":"QLD",
    "sg:tags":[
        "environmental",
        "consultant",
        "pollution"
    ],
    "wof:name":"Storm Water Consulting Pty Ltd",
    "wof:placetype":"venue"
},
  "geometry": {"coordinates":[153.070480347,-27.4915237427],"type":"Point"}
}