{
  "type": "Feature",
  "properties": {
    "iso:country":"AU",
    "sg:address":"238 Riley St",
    "sg:city":"Surry Hills",
    "sg:classifiers":[
        {
            "category":"Professional",
            "subcategory":"Computer Services",
            "type":"Services"
        }
    ],
    "sg:phone":"+61 2 9281 2110",
    "sg:postcode":"2010",
    "sg:province":"NSW",
    "sg:tags":[
        "technical",
        "support"
    ],
    "wof:name":"EDU Technology Solutions Pty Ltd",
    "wof:placetype":"venue"
},
  "geometry": {"coordinates":[151.21353149399999,-33.8821411133],"type":"Point"}
}