{
  "type": "Feature",
  "properties": {
    "addr:full":"5/58 Perkins St Townsville QLD 4810",
    "addr:housenumber":"/ 58",
    "addr:postcode":"4810",
    "addr:street":"Perkins St",
    "iso:country":"AU",
    "sg:address":"5/58 Perkins St",
    "sg:city":"Townsville",
    "sg:classifiers":[
        {
            "category":"Building & Trades",
            "subcategory":"Equipment Rental",
            "type":"Services"
        }
    ],
    "sg:phone":"+61 7 4772 1069",
    "sg:postcode":"4810",
    "sg:province":"QLD",
    "sg:tags":[
        "charting",
        "chart"
    ],
    "wof:name":"Navigation Centre The",
    "wof:placetype":"venue"
},
  "geometry": {"coordinates":[146.81965600000001,-19.270231],"type":"Point"}
}