{
  "type": "Feature",
  "properties": {
    "addr:full":"339 Brunswick St Fitzroy VIC 3065",
    "addr:housenumber":"339",
    "addr:postcode":"3065",
    "addr:street":"Brunswick St",
    "iso:country":"AU",
    "sg:address":"339 Brunswick St",
    "sg:city":"Fitzroy",
    "sg:classifiers":[
        {
            "category":"Food & Beverages",
            "subcategory":"Bakery",
            "type":"Retail Goods"
        }
    ],
    "sg:phone":"+61 3 9417 7003",
    "sg:postcode":"3065",
    "sg:province":"VIC",
    "sg:tags":[
        "cake",
        "shop",
        "pastry"
    ],
    "wof:name":"Garances",
    "wof:placetype":"venue"
},
  "geometry": {"coordinates":[144.97850036599999,-37.7970504761],"type":"Point"}
}