{
  "type": "Feature",
  "properties": {
    "iso:country":"AU",
    "sg:address":"96 whitsfield St",
    "sg:city":"Jurien Bay",
    "sg:classifiers":[
        {
            "category":"Health Services",
            "subcategory":"Doctor",
            "type":"Services"
        }
    ],
    "sg:phone":"+61 8 9652 1484",
    "sg:postcode":"6516",
    "sg:province":"WA",
    "sg:tags":[
        "medical",
        "practitioner"
    ],
    "wof:name":"Jurien Medical Centre",
    "wof:placetype":"venue"
},
  "geometry": {"coordinates":[115.04238100000001,-30.304165],"type":"Point"}
}