{
  "type": "Feature",
  "properties": {
    "iso:country":"AU",
    "sg:address":"1 Ina Pl",
    "sg:city":"Cooma",
    "sg:classifiers":[
        {
            "category":"Professional",
            "subcategory":"Secretarial Services",
            "type":"Services"
        }
    ],
    "sg:phone":"+61 2 6452 4419",
    "sg:postcode":"2630",
    "sg:province":"NSW",
    "sg:tags":[
        "typing"
    ],
    "wof:name":"Cooma Secretarial Services",
    "wof:placetype":"venue"
},
  "geometry": {"coordinates":[149.14419555699999,-36.2216377258],"type":"Point"}
}