{
  "type": "Feature",
  "properties": {
    "iso:country":"AU",
    "sg:address":"86 Jennaer St",
    "sg:city":"Nundah",
    "sg:classifiers":[
        {
            "category":"Real Estate",
            "subcategory":"Surveying",
            "type":"Services"
        }
    ],
    "sg:phone":"+61 408 151 092",
    "sg:postcode":"4012",
    "sg:province":"QLD",
    "sg:tags":[
        "surveyor",
        "quantity"
    ],
    "wof:name":"Quad Consulting Pty Ltd",
    "wof:placetype":"venue"
},
  "geometry": {"coordinates":[153.066314697,-27.4005355835],"type":"Point"}
}