{
  "type": "Feature",
  "properties": {
    "iso:country":"AU",
    "sg:address":"Suite 7, North West Medical Centre 21 Brickport Rd",
    "sg:city":"Burnie",
    "sg:classifiers":[
        {
            "category":"Health Services",
            "subcategory":"Doctor",
            "type":"Services"
        }
    ],
    "sg:phone":"+61 3 6431 9361",
    "sg:postcode":"7320",
    "sg:province":"TAS",
    "sg:tags":[
        "medical",
        "practitioner"
    ],
    "wof:name":"Shugg Bert",
    "wof:placetype":"venue"
},
  "geometry": {"coordinates":[145.877579,-41.045776],"type":"Point"}
}