{
  "type": "Feature",
  "properties": {
    "iso:country":"AU",
    "sg:address":"59 Frankston Garden Drv",
    "sg:city":"Carrum Downs",
    "sg:classifiers":[
        {
            "category":"Mining & Drilling",
            "type":"Manufacturing & Wholesale Goods"
        }
    ],
    "sg:phone":"+61 3 9788 5000",
    "sg:postcode":"3201",
    "sg:province":"VIC",
    "sg:tags":[
        "concrete",
        "breaking",
        "grinding",
        "sawing"
    ],
    "sg:website":"http://www.advancedsawing.com.au",
    "wof:name":"Advanced Sawing & Drilling",
    "wof:placetype":"venue"
},
  "geometry": {"coordinates":[145.15954600000001,-38.101322],"type":"Point"}
}