{
  "type": "Feature",
  "properties": {
    "addr:full":"East St Kilmore VIC 3764",
    "addr:postcode":"3764",
    "addr:street":"East St",
    "iso:country":"AU",
    "sg:address":"East St",
    "sg:city":"Kilmore",
    "sg:classifiers":[
        {
            "category":"Retail",
            "subcategory":"Event Space",
            "type":"Services"
        }
    ],
    "sg:phone":"+61 3 5783 0777",
    "sg:postcode":"3764",
    "sg:province":"VIC",
    "sg:tags":[
        "venue",
        "reception",
        "wedding"
    ],
    "wof:name":"Kilmore Trackside Tabaret",
    "wof:placetype":"venue"
},
  "geometry": {"coordinates":[144.958587647,-37.2960662842],"type":"Point"}
}