{
  "type": "Feature",
  "properties": {
    "addr:full":"55 Tulip St Sandringham VIC 3191",
    "addr:housenumber":"55",
    "addr:postcode":"3191",
    "addr:street":"Tulip St",
    "iso:country":"AU",
    "sg:address":"55 Tulip St",
    "sg:city":"Sandringham",
    "sg:classifiers":[
        {
            "category":"Professional",
            "subcategory":"Accounting & Tax Preparation",
            "type":"Services"
        }
    ],
    "sg:phone":"+61 3 9597 0111",
    "sg:postcode":"3191",
    "sg:province":"VIC",
    "sg:tags":[
        "accountant",
        "auditor"
    ],
    "wof:name":"Mark D Fisher",
    "wof:placetype":"venue"
},
  "geometry": {"coordinates":[145.02833557100001,-37.96301651],"type":"Point"}
}