{
  "type": "Feature",
  "properties": {
    "addr:full":"31 Ferguson St Forestville NSW 2087",
    "addr:housenumber":"31",
    "addr:postcode":"2087",
    "addr:street":"Ferguson St",
    "iso:country":"AU",
    "sg:address":"31 Ferguson St",
    "sg:city":"Forestville",
    "sg:classifiers":[
        {
            "category":"Utilities",
            "subcategory":"Water",
            "type":"Services"
        }
    ],
    "sg:phone":"+61 2 9451 8252",
    "sg:postcode":"2087",
    "sg:province":"NSW",
    "sg:tags":[
        "hot",
        "system"
    ],
    "wof:name":"Mann H (1919) Pty. Ltd.",
    "wof:placetype":"venue"
},
  "geometry": {"coordinates":[151.214233398,-33.7590751648],"type":"Point"}
}