{
  "type": "Feature",
  "properties": {
    "addr:full":"51 Majors Bay Rd Concord NSW 2137",
    "addr:housenumber":"51",
    "addr:postcode":"2137",
    "addr:street":"Majors Bay Rd",
    "iso:country":"AU",
    "sg:address":"51 Majors Bay Rd",
    "sg:city":"Concord",
    "sg:classifiers":[
        {
            "category":"Restaurant",
            "type":"Food & Drink"
        }
    ],
    "sg:phone":"+61 2 9743 2942",
    "sg:postcode":"2137",
    "sg:province":"NSW",
    "wof:name":"Concord Pizza Bar",
    "wof:placetype":"venue"
},
  "geometry": {"coordinates":[151.10348510700001,-33.8565254211],"type":"Point"}
}