{
  "type": "Feature",
  "properties": {
    "iso:country":"AU",
    "sg:address":"575 Ross River Rd",
    "sg:city":"Kirwan",
    "sg:classifiers":[
        {
            "category":"Manufacturing",
            "subcategory":"Tools & Machinery",
            "type":"Manufacturing & Wholesale Goods"
        }
    ],
    "sg:phone":"+61 7 4772 5366",
    "sg:postcode":"4817",
    "sg:province":"QLD",
    "sg:tags":[
        "machine",
        "industrial",
        "sewing"
    ],
    "wof:name":"Singer Brother Sewing Shop",
    "wof:placetype":"venue"
},
  "geometry": {"coordinates":[146.737198,-19.313841],"type":"Point"}
}