{
  "type": "Feature",
  "properties": {
    "iso:country":"AU",
    "sg:address":"10 Sir Joseph Banks St",
    "sg:city":"Botany",
    "sg:classifiers":[
        {
            "category":"Retail",
            "subcategory":"Auto Repair",
            "type":"Services"
        }
    ],
    "sg:phone":"+61 2 9316 4985",
    "sg:postcode":"2019",
    "sg:province":"NSW",
    "sg:tags":[
        "beater",
        "painter",
        "panel"
    ],
    "wof:name":"East Side Collision Centre Pty Ltd",
    "wof:placetype":"venue"
},
  "geometry": {"coordinates":[151.20179748499999,-33.9524765015],"type":"Point"}
}