{
  "type": "Feature",
  "properties": {
    "addr:full":"45 Gatwick Rd Bayswater North VIC 3153",
    "addr:housenumber":"45",
    "addr:postcode":"3153",
    "addr:street":"Gatwick Rd",
    "iso:country":"AU",
    "sg:address":"45 Gatwick Rd",
    "sg:city":"Bayswater North",
    "sg:classifiers":[
        {
            "category":"Home & Garden",
            "subcategory":"Building Materials",
            "type":"Retail Goods"
        }
    ],
    "sg:phone":"+61 3 9761 4566",
    "sg:postcode":"3153",
    "sg:province":"VIC",
    "sg:tags":[
        "supply"
    ],
    "wof:name":"Allied Tekform Pty Ltd",
    "wof:placetype":"venue"
},
  "geometry": {"coordinates":[145.29693603499999,-37.8200569153],"type":"Point"}
}