{
  "type": "Feature",
  "properties": {
    "addr:full":"11 Gibbes St Chatswood NSW 2067",
    "addr:housenumber":"11",
    "addr:postcode":"2067",
    "addr:street":"Gibbes St",
    "iso:country":"AU",
    "sg:address":"11 Gibbes St",
    "sg:city":"Chatswood",
    "sg:classifiers":[
        {
            "category":"Retail",
            "subcategory":"Auto Repair",
            "type":"Services"
        }
    ],
    "sg:phone":"+61 2 9417 6304",
    "sg:postcode":"2067",
    "sg:province":"NSW",
    "sg:tags":[
        "repairer",
        "motor",
        "engineer"
    ],
    "wof:name":"Sydney-Wide Auto Air Conditioning",
    "wof:placetype":"venue"
},
  "geometry": {"coordinates":[151.20037841800001,-33.789768219],"type":"Point"}
}