{
  "type": "Feature",
  "properties": {
    "addr:full":"U2/ 153 Victoria Ave Chatswood NSW 2067",
    "addr:housenumber":"153",
    "addr:postcode":"2067",
    "addr:street":"U2 /;Victoria Ave",
    "iso:country":"AU",
    "sg:address":"U2/ 153 Victoria Ave",
    "sg:city":"Chatswood",
    "sg:classifiers":[
        {
            "category":"Banks & Credit Unions",
            "subcategory":"Investment Brokerage",
            "type":"Services"
        }
    ],
    "sg:phone":"+61 2 9419 7033",
    "sg:postcode":"2067",
    "sg:province":"NSW",
    "sg:tags":[
        "finance",
        "broker"
    ],
    "wof:name":"Insight Family Wealth Consultants",
    "wof:placetype":"venue"
},
  "geometry": {"coordinates":[151.19473266599999,-33.7925376892],"type":"Point"}
}