{
  "type": "Feature",
  "properties": {
    "addr:full":"2 Pademelon Crt Greenbank QLD 4124",
    "addr:housenumber":"2",
    "addr:postcode":"4124",
    "addr:street":"Pademelon Crt",
    "iso:country":"AU",
    "sg:address":"2 Pademelon Crt",
    "sg:city":"Greenbank",
    "sg:classifiers":[
        {
            "category":"Building & Trades",
            "subcategory":"Landscaping Services",
            "type":"Services"
        }
    ],
    "sg:phone":"+61 7 3297 5983",
    "sg:postcode":"4124",
    "sg:province":"QLD",
    "sg:tags":[
        "stump",
        "tree",
        "felling",
        "removal"
    ],
    "wof:name":"Simon Docker",
    "wof:placetype":"venue"
},
  "geometry": {"coordinates":[152.929122925,-27.7298755646],"type":"Point"}
}