{
  "type": "Feature",
  "properties": {
    "addr:full":"Shop 9/ 1259 Pacific Hwy Turramurra NSW 2074",
    "addr:housenumber":"shop 9 / 1259",
    "addr:postcode":"2074",
    "addr:street":"Pacific Hwy",
    "iso:country":"AU",
    "sg:address":"Shop 9/ 1259 Pacific Hwy",
    "sg:city":"Turramurra",
    "sg:classifiers":[
        {
            "category":"Professional",
            "subcategory":"Art Services",
            "type":"Services"
        }
    ],
    "sg:phone":"+61 2 9449 9086",
    "sg:postcode":"2074",
    "sg:province":"NSW",
    "sg:tags":[
        "interior",
        "decorator"
    ],
    "wof:name":"Wahroonga Interiors",
    "wof:placetype":"venue"
},
  "geometry": {"coordinates":[151.130569458,-33.7330627441],"type":"Point"}
}