{
  "type": "Feature",
  "properties": {
    "iso:country":"AU",
    "sg:address":"646 Sydney Rd",
    "sg:city":"Brunswick",
    "sg:classifiers":[
        {
            "category":"Shopping",
            "subcategory":"Computers & Home Electronics",
            "type":"Retail Goods"
        }
    ],
    "sg:phone":"+61 3 9384 3001",
    "sg:postcode":"3056",
    "sg:province":"VIC",
    "sg:tags":[
        "hardware",
        "equipment"
    ],
    "wof:name":"Salnex Microsystems Pty Ltd",
    "wof:placetype":"venue"
},
  "geometry": {"coordinates":[144.96304321299999,-37.7624359131],"type":"Point"}
}