{
  "type": "Feature",
  "properties": {
    "iso:country":"AU",
    "sg:address":"4/ 74 Bendigo Ave",
    "sg:city":"Bentleigh",
    "sg:classifiers":[
        {
            "category":"Professional",
            "subcategory":"Computer Services",
            "type":"Services"
        }
    ],
    "sg:phone":"+61 3 9576 9753",
    "sg:postcode":"3204",
    "sg:province":"VIC",
    "sg:tags":[
        "package",
        "software"
    ],
    "wof:name":"RP Omega Operations",
    "wof:placetype":"venue"
},
  "geometry": {"coordinates":[145.03753699999999,-37.918785],"type":"Point"}
}