{
  "type": "Feature",
  "properties": {
    "addr:full":"30 Garden St Maryborough QLD 4650",
    "addr:housenumber":"30",
    "addr:postcode":"4650",
    "addr:street":"Garden St",
    "iso:country":"AU",
    "sg:address":"30 Garden St",
    "sg:city":"Maryborough",
    "sg:classifiers":[
        {
            "category":"Retail",
            "subcategory":"Repair Shop",
            "type":"Services"
        }
    ],
    "sg:phone":"+61 412 988 655",
    "sg:postcode":"4650",
    "sg:province":"QLD",
    "sg:tags":[
        "windscreen"
    ],
    "wof:name":"Rocky's Glass Direct",
    "wof:placetype":"venue"
},
  "geometry": {"coordinates":[152.69723500000001,-25.524982],"type":"Point"}
}