{
  "type": "Feature",
  "properties": {
    "iso:country":"AU",
    "sg:address":"Cnr Anzac Ave & The Crescent",
    "sg:city":"Kallangur",
    "sg:classifiers":[
        {
            "category":"Fast Food",
            "type":"Food & Drink"
        }
    ],
    "sg:phone":"+61 7 3204 5284",
    "sg:postcode":"4503",
    "sg:province":"QLD",
    "sg:tags":[
        "away",
        "take"
    ],
    "wof:name":"Red Rooster",
    "wof:placetype":"venue"
},
  "geometry": {"coordinates":[152.99528503400001,-27.2501354218],"type":"Point"}
}