{
  "type": "Feature",
  "properties": {
    "addr:full":"7 Edgecombe Crt Moorabbin VIC 3189",
    "addr:housenumber":"7",
    "addr:postcode":"3189",
    "addr:street":"Edgecombe Crt",
    "iso:country":"AU",
    "sg:address":"7 Edgecombe Crt",
    "sg:city":"Moorabbin",
    "sg:classifiers":[
        {
            "category":"Landmark",
            "subcategory":"Scenic View",
            "type":"Public Place"
        }
    ],
    "sg:phone":"+61 3 9532 0224",
    "sg:postcode":"3189",
    "sg:province":"VIC",
    "sg:tags":[
        "staircase",
        "handrail"
    ],
    "wof:name":"Modular Stairs",
    "wof:placetype":"venue"
},
  "geometry": {"coordinates":[145.07164001500001,-37.9421768188],"type":"Point"}
}