{
  "type": "Feature",
  "properties": {
    "addr:full":"44 Rocket St Bathurst NSW 2795",
    "addr:housenumber":"44",
    "addr:postcode":"2795",
    "addr:street":"Rocket St",
    "iso:country":"AU",
    "sg:address":"44 Rocket St",
    "sg:city":"Bathurst",
    "sg:classifiers":[
        {
            "category":"Food & Beverages",
            "subcategory":"Groceries & Convenience Stores",
            "type":"Retail Goods"
        }
    ],
    "sg:phone":"+61 2 6331 1053",
    "sg:postcode":"2795",
    "sg:province":"NSW",
    "wof:name":"South Bathurst Food Market",
    "wof:placetype":"venue"
},
  "geometry": {"coordinates":[149.57679748499999,-33.4292411804],"type":"Point"}
}