{
  "type": "Feature",
  "properties": {
    "addr:full":"4 Busby Pl Frenchs Forest NSW 2086",
    "addr:housenumber":"4",
    "addr:postcode":"2086",
    "addr:street":"Pl",
    "iso:country":"AU",
    "sg:address":"4 Busby Pl",
    "sg:city":"Frenchs Forest",
    "sg:classifiers":[
        {
            "category":"Organizations",
            "subcategory":"Membership Organization",
            "type":"Services"
        }
    ],
    "sg:phone":"+61 2 9975 3388",
    "sg:postcode":"2086",
    "sg:province":"NSW",
    "sg:tags":[
        "recording",
        "system",
        "time"
    ],
    "wof:name":"Timekeeping International Pty Ltd",
    "wof:placetype":"venue"
},
  "geometry": {"coordinates":[151.207107544,-33.7486228943],"type":"Point"}
}