{
  "type": "Feature",
  "properties": {
    "addr:full":"Shop 1 397 Diagonal Rd Sturt SA 5047",
    "addr:housenumber":"shop 1",
    "addr:postcode":"397;5047",
    "addr:street":"Diagonal Rd",
    "iso:country":"AU",
    "sg:address":"Shop 1 397 Diagonal Rd",
    "sg:city":"Sturt",
    "sg:classifiers":[
        {
            "category":"Wholesale",
            "subcategory":"Furniture",
            "type":"Manufacturing & Wholesale Goods"
        }
    ],
    "sg:phone":"+61 8 8296 0206",
    "sg:postcode":"5047",
    "sg:province":"SA",
    "sg:tags":[
        "wholesaler",
        "mfrs"
    ],
    "wof:name":"M.E.R. Furniture",
    "wof:placetype":"venue"
},
  "geometry": {"coordinates":[138.55235300000001,-35.024567],"type":"Point"}
}