{
  "type": "Feature",
  "properties": {
    "addr:full":"PO Box 289 Mitchell ACT 2911",
    "addr:postcode":"2911",
    "iso:country":"AU",
    "sg:address":"PO Box 289",
    "sg:city":"Mitchell",
    "sg:classifiers":[
        {
            "category":"Building & Trades",
            "subcategory":"Construction",
            "type":"Services"
        }
    ],
    "sg:phone":"+61 411 699 776",
    "sg:postcode":"2911",
    "sg:province":"ACT",
    "sg:tags":[
        "concrete",
        "contractor"
    ],
    "wof:name":"Modern Spray On & Concreting Service",
    "wof:placetype":"venue"
},
  "geometry": {"coordinates":[149.13471984899999,-35.2194900513],"type":"Point"}
}