{
  "type": "Feature",
  "properties": {
    "addr:full":"Cnr Balmain Rd & Perry St Leichhardt NSW 2040",
    "addr:postcode":"2040",
    "addr:street":"Cnr Balmain Rd & Perry St",
    "iso:country":"AU",
    "sg:address":"Cnr Balmain Rd & Perry St",
    "sg:city":"Leichhardt",
    "sg:classifiers":[
        {
            "category":"Education",
            "subcategory":"Special Training",
            "type":"Public Place"
        }
    ],
    "sg:phone":"+61 2 9555 7411",
    "sg:postcode":"2040",
    "sg:province":"NSW",
    "sg:tags":[
        "development"
    ],
    "wof:name":"Sydney Community College Inc",
    "wof:placetype":"venue"
},
  "geometry": {"coordinates":[151.16073600000001,-33.876099],"type":"Point"}
}