{
  "type": "Feature",
  "properties": {
    "iso:country":"AU",
    "sg:address":"Suite 7/ 86 High St",
    "sg:city":"Berwick",
    "sg:classifiers":[
        {
            "category":"Building & Trades",
            "subcategory":"Locksmith",
            "type":"Services"
        }
    ],
    "sg:phone":"+61 3 9707 5846",
    "sg:postcode":"3806",
    "sg:province":"VIC",
    "sg:tags":[
        "strongroom",
        "safe",
        "door"
    ],
    "wof:name":"Secure Safe Solutions",
    "wof:placetype":"venue"
},
  "geometry": {"coordinates":[145.345504761,-38.031463623],"type":"Point"}
}