{
  "type": "Feature",
  "properties": {
    "addr:full":"2-4 Pear Ave Derwent Park TAS 7009",
    "addr:housenumber":"2-4",
    "addr:postcode":"7009",
    "addr:street":"Pear Ave",
    "iso:country":"AU",
    "sg:address":"2-4 Pear Ave",
    "sg:city":"Derwent Park",
    "sg:classifiers":[
        {
            "category":"Building & Trades",
            "subcategory":"Equipment Rental",
            "type":"Services"
        }
    ],
    "sg:phone":"+61 438 637 552",
    "sg:postcode":"7009",
    "sg:province":"TAS",
    "sg:tags":[
        "crane",
        "hire"
    ],
    "wof:name":"Transbuild",
    "wof:placetype":"venue"
},
  "geometry": {"coordinates":[147.298583984,-42.8356285095],"type":"Point"}
}