{
  "type": "Feature",
  "properties": {
    "addr:full":"6 Timaru Crt Wheelers Hill VIC 3150",
    "addr:housenumber":"6",
    "addr:postcode":"3150",
    "addr:street":"Timaru Crt",
    "iso:country":"AU",
    "sg:address":"6 Timaru Crt",
    "sg:city":"Wheelers Hill",
    "sg:classifiers":[
        {
            "category":"Building & Trades",
            "subcategory":"Locksmith",
            "type":"Services"
        }
    ],
    "sg:phone":"+61 3 9562 0779",
    "sg:postcode":"3150",
    "sg:province":"VIC",
    "sg:tags":[
        "lock"
    ],
    "wof:name":"New England Locksmith",
    "wof:placetype":"venue"
},
  "geometry": {"coordinates":[145.17474365199999,-37.9169960022],"type":"Point"}
}