{
  "type": "Feature",
  "properties": {
    "iso:country":"AU",
    "sg:address":"Lvel 5, 203 New South Head Rd",
    "sg:city":"Edgecliff",
    "sg:classifiers":[
        {
            "category":"Education",
            "subcategory":"Special Training",
            "type":"Public Place"
        }
    ],
    "sg:phone":"+61 2 9328 6240",
    "sg:postcode":"2027",
    "sg:province":"NSW",
    "sg:tags":[
        "development"
    ],
    "wof:name":"Human Resource Management International",
    "wof:placetype":"venue"
},
  "geometry": {"coordinates":[151.23535156200001,-33.8787155151],"type":"Point"}
}