{
  "type": "Feature",
  "properties": {
    "addr:full":"12 Gipps St Collingwood VIC 3066",
    "addr:housenumber":"12",
    "addr:postcode":"3066",
    "addr:street":"Gipps St",
    "iso:country":"AU",
    "sg:address":"12 Gipps St",
    "sg:city":"Collingwood",
    "sg:classifiers":[
        {
            "category":"Professional",
            "subcategory":"Art Services",
            "type":"Services"
        }
    ],
    "sg:phone":"+61 3 9473 1913",
    "sg:postcode":"3066",
    "sg:province":"VIC",
    "sg:tags":[
        "graphic",
        "designer"
    ],
    "wof:name":"Yoke Pty Ltd",
    "wof:placetype":"venue"
},
  "geometry": {"coordinates":[144.98696899399999,-37.8043365479],"type":"Point"}
}