{
  "type": "Feature",
  "properties": {
    "addr:full":"3/ 327 Maitland Rd Cessnock NSW 2325",
    "addr:housenumber":"/ 327",
    "addr:postcode":"2325",
    "addr:street":"Maitland Rd",
    "iso:country":"AU",
    "sg:address":"3/ 327 Maitland Rd",
    "sg:city":"Cessnock",
    "sg:classifiers":[
        {
            "category":"Shopping",
            "subcategory":"Computers & Home Electronics",
            "type":"Retail Goods"
        }
    ],
    "sg:phone":"+61 2 4991 1392",
    "sg:postcode":"2325",
    "sg:province":"NSW",
    "sg:tags":[
        "equipment",
        "supply"
    ],
    "wof:name":"Cartridges Kilpatrick",
    "wof:placetype":"venue"
},
  "geometry": {"coordinates":[151.37374877900001,-32.8286857605],"type":"Point"}
}