{
  "type": "Feature",
  "properties": {
    "addr:full":"119 Dunlop St Mortlake VIC 3272",
    "addr:housenumber":"119",
    "addr:postcode":"3272",
    "addr:street":"Dunlop St",
    "iso:country":"AU",
    "sg:address":"119 Dunlop St",
    "sg:city":"Mortlake",
    "sg:classifiers":[
        {
            "category":"Home & Garden",
            "subcategory":"Household Appliances",
            "type":"Retail Goods"
        }
    ],
    "sg:phone":"+61 3 5599 2159",
    "sg:postcode":"3272",
    "sg:province":"VIC",
    "sg:tags":[
        "equipment",
        "gas"
    ],
    "wof:name":"J Goldsworthy & Sons",
    "wof:placetype":"venue"
},
  "geometry": {"coordinates":[142.80778503400001,-38.0812606812],"type":"Point"}
}