{
  "type": "Feature",
  "properties": {
    "iso:country":"AU",
    "sg:address":"65 Charles St",
    "sg:city":"Footscray",
    "sg:classifiers":[
        {
            "category":"Professional",
            "subcategory":"Art Services",
            "type":"Services"
        }
    ],
    "sg:phone":"+61 3 9687 2577",
    "sg:postcode":"3011",
    "sg:province":"VIC",
    "sg:tags":[
        "graphic",
        "designer"
    ],
    "wof:name":"Kwik Kopy Print & Design Centres",
    "wof:placetype":"venue"
},
  "geometry": {"coordinates":[144.89219665499999,-37.8068351746],"type":"Point"}
}