{
  "type": "Feature",
  "properties": {
    "addr:full":"55 Currans Hill Drv Currans Hill NSW 2567",
    "addr:housenumber":"55",
    "addr:postcode":"2567",
    "addr:street":"Currans Hill Drv",
    "iso:country":"AU",
    "sg:address":"55 Currans Hill Drv",
    "sg:city":"Currans Hill",
    "sg:classifiers":[
        {
            "category":"Social Services",
            "subcategory":"Adult Care",
            "type":"Services"
        }
    ],
    "sg:phone":"+61 2 4628 1214",
    "sg:postcode":"2567",
    "sg:province":"NSW",
    "sg:tags":[
        "towing"
    ],
    "wof:name":"Chain Towing & Tilt Tray Pty Ltd",
    "wof:placetype":"venue"
},
  "geometry": {"coordinates":[150.76866149899999,-34.0459747314],"type":"Point"}
}