{
  "type": "Feature",
  "properties": {
    "addr:full":"Rochester Drv Mt Warren Park QLD 4207",
    "addr:postcode":"4207",
    "addr:street":"Rochester Drv Mt Warren",
    "iso:country":"AU",
    "sg:address":"Rochester Drv",
    "sg:city":"Mt Warren Park",
    "sg:classifiers":[
        {
            "category":"Food & Beverages",
            "subcategory":"Liquor & Beverages",
            "type":"Retail Goods"
        }
    ],
    "sg:phone":"+61 7 3807 7922",
    "sg:postcode":"4207",
    "sg:province":"QLD",
    "sg:tags":[
        "store"
    ],
    "wof:name":"Mt Warren Cellars",
    "wof:placetype":"venue"
},
  "geometry": {"coordinates":[153.199127197,-27.7244110107],"type":"Point"}
}