{
  "type": "Feature",
  "properties": {
    "iso:country":"AU",
    "sg:address":"35- 39 Scarfe St",
    "sg:city":"Camdale",
    "sg:classifiers":[
        {
            "category":"Wholesale",
            "subcategory":"Machinery & Supplies",
            "type":"Manufacturing & Wholesale Goods"
        }
    ],
    "sg:phone":"+61 3 6435 2205",
    "sg:postcode":"7320",
    "sg:province":"TAS",
    "sg:tags":[
        "equipment",
        "system",
        "elevating",
        "conveying"
    ],
    "wof:name":"Statewide Belting Service",
    "wof:placetype":"venue"
},
  "geometry": {"coordinates":[145.841003,-41.042294],"type":"Point"}
}