{
  "type": "Feature",
  "properties": {
    "addr:full":"499 Sandgate Rd Albion Heights QLD 4010",
    "addr:housenumber":"499",
    "addr:postcode":"4010",
    "addr:street":"Sandgate Rd",
    "iso:country":"AU",
    "sg:address":"499 Sandgate Rd",
    "sg:city":"Albion Heights",
    "sg:classifiers":[
        {
            "category":"Health Services",
            "subcategory":"Doctor",
            "type":"Services"
        }
    ],
    "sg:phone":"+61 7 3262 2351",
    "sg:postcode":"4010",
    "sg:province":"QLD",
    "sg:tags":[
        "medical",
        "practitioner"
    ],
    "wof:name":"Wagon Rory",
    "wof:placetype":"venue"
},
  "geometry": {"coordinates":[153.04148864699999,-27.4299106598],"type":"Point"}
}