{
  "type": "Feature",
  "properties": {
    "addr:full":"Unit 1/ 40 Resource Way Malaga WA 6090",
    "addr:housenumber":"40",
    "addr:postcode":"6090",
    "addr:street":"Resource Way",
    "iso:country":"AU",
    "sg:address":"Unit 1/ 40 Resource Way",
    "sg:city":"Malaga",
    "sg:classifiers":[
        {
            "category":"Social Services",
            "type":"Services"
        }
    ],
    "sg:phone":"+61 8 9249 7483",
    "sg:postcode":"6090",
    "sg:province":"WA",
    "sg:tags":[
        "disabled",
        "person",
        "equipment"
    ],
    "wof:name":"Australian Mobility Equipment",
    "wof:placetype":"venue"
},
  "geometry": {"coordinates":[115.910263062,-31.8585853577],"type":"Point"}
}