{
  "type": "Feature",
  "properties": {
    "addr:full":"21 Macedon Rd Lower Templestowe VIC 3107",
    "addr:housenumber":"21",
    "addr:postcode":"3107",
    "addr:street":"Macedon Rd",
    "iso:country":"AU",
    "sg:address":"21 Macedon Rd",
    "sg:city":"Lower Templestowe",
    "sg:classifiers":[
        {
            "category":"Banks & Credit Unions",
            "subcategory":"Financial Services",
            "type":"Services"
        }
    ],
    "sg:phone":"+61 3 9850 4077",
    "sg:postcode":"3107",
    "sg:province":"VIC",
    "sg:tags":[
        "planning"
    ],
    "wof:name":"Muir-Smith Investment Services Pty Ltd",
    "wof:placetype":"venue"
},
  "geometry": {"coordinates":[145.11224365199999,-37.7727890015],"type":"Point"}
}