{
  "type": "Feature",
  "properties": {
    "addr:full":"Shop 39/40, Floreat Forum Shopping Centre Floreat WA 6014",
    "addr:housenumber":"shop 39 / 40",
    "addr:postcode":"6014",
    "iso:country":"AU",
    "sg:address":"Shop 39/40, Floreat Forum Shopping Centre",
    "sg:city":"Floreat",
    "sg:classifiers":[
        {
            "category":"Shopping",
            "subcategory":"Clothing, Apparel, & Fashions",
            "type":"Retail Goods"
        }
    ],
    "sg:phone":"+61 8 9383 7299",
    "sg:postcode":"6014",
    "sg:province":"WA",
    "sg:tags":[
        "lady",
        "wear"
    ],
    "wof:name":"Brown Sugar",
    "wof:placetype":"venue"
},
  "geometry": {"coordinates":[115.792808533,-31.940164566],"type":"Point"}
}