{
  "type": "Feature",
  "properties": {
    "addr:full":"49 Greycliffe St Queenscliff NSW 2096",
    "addr:housenumber":"49",
    "addr:postcode":"2096",
    "addr:street":"Greycliffe St",
    "iso:country":"AU",
    "sg:address":"49 Greycliffe St",
    "sg:city":"Queenscliff",
    "sg:classifiers":[
        {
            "category":"Personal",
            "subcategory":"Beauty Salon",
            "type":"Services"
        }
    ],
    "sg:phone":"+61 2 9938 5880",
    "sg:postcode":"2096",
    "sg:province":"NSW",
    "sg:tags":[
        "hairdresser"
    ],
    "wof:name":"Susie Sumner",
    "wof:placetype":"venue"
},
  "geometry": {"coordinates":[151.28587341299999,-33.7841377258],"type":"Point"}
}