{
  "type": "Feature",
  "properties": {
    "addr:full":"31 Carrington St Queanbeyan NSW 2620",
    "addr:housenumber":"31",
    "addr:postcode":"2620",
    "addr:street":"Carrington St",
    "iso:country":"AU",
    "sg:address":"31 Carrington St",
    "sg:city":"Queanbeyan",
    "sg:classifiers":[
        {
            "category":"Wholesale",
            "subcategory":"Metals & Minerals",
            "type":"Manufacturing & Wholesale Goods"
        }
    ],
    "sg:phone":"+61 2 6297 3651",
    "sg:postcode":"2620",
    "sg:province":"NSW",
    "sg:tags":[
        "steel",
        "stainless",
        "product",
        "equipment"
    ],
    "wof:name":"Stainless Steel Fabrications",
    "wof:placetype":"venue"
},
  "geometry": {"coordinates":[149.241455078,-35.340423584],"type":"Point"}
}