{
  "type": "Feature",
  "properties": {
    "addr:full":"1st Fl, 18 Duggan St Toowoomba QLD 4350",
    "addr:housenumber":"18",
    "addr:postcode":"4350",
    "addr:street":"Duggan St",
    "iso:country":"AU",
    "sg:address":"1st Fl, 18 Duggan St",
    "sg:city":"Toowoomba",
    "sg:classifiers":[
        {
            "category":"Education",
            "subcategory":"Vocational School",
            "type":"Public Place"
        }
    ],
    "sg:phone":"+61 7 4639 4495",
    "sg:postcode":"4350",
    "sg:province":"QLD",
    "sg:tags":[
        "beauty"
    ],
    "wof:name":"CJs Plus Education",
    "wof:placetype":"venue"
},
  "geometry": {"coordinates":[151.95202599999999,-27.562897],"type":"Point"}
}