{
  "type": "Feature",
  "properties": {
    "addr:full":"Lot 1/ 19 Walkers La Woodford QLD 4514",
    "addr:housenumber":"1 / 19",
    "addr:postcode":"4514",
    "addr:street":"Walkers La",
    "iso:country":"AU",
    "sg:address":"Lot 1/ 19 Walkers La",
    "sg:city":"Woodford",
    "sg:classifiers":[
        {
            "category":"Building & Trades",
            "subcategory":"Construction",
            "type":"Services"
        }
    ],
    "sg:phone":"+61 418 711 422",
    "sg:postcode":"4514",
    "sg:province":"QLD",
    "sg:tags":[
        "earth",
        "excavating",
        "moving",
        "contractor"
    ],
    "wof:name":"Clyne Don Earthmoving",
    "wof:placetype":"venue"
},
  "geometry": {"coordinates":[152.75372300000001,-26.962406],"type":"Point"}
}