{
  "type": "Feature",
  "properties": {
    "addr:full":"23 Wills St Charleville QLD 4470",
    "addr:housenumber":"23",
    "addr:postcode":"4470",
    "addr:street":"Wills St",
    "iso:country":"AU",
    "sg:address":"23 Wills St",
    "sg:city":"Charleville",
    "sg:classifiers":[
        {
            "category":"Professional",
            "subcategory":"Accounting & Tax Preparation",
            "type":"Services"
        }
    ],
    "sg:phone":"+61 7 4654 1013",
    "sg:postcode":"4470",
    "sg:province":"QLD",
    "sg:tags":[
        "accountant",
        "auditor"
    ],
    "wof:name":"Wagner Tom",
    "wof:placetype":"venue"
},
  "geometry": {"coordinates":[146.24029540999999,-26.4017486572],"type":"Point"}
}