{
  "type": "Feature",
  "properties": {
    "addr:full":"158 Hare St Echuca VIC 3564",
    "addr:housenumber":"158",
    "addr:postcode":"3564",
    "addr:street":"Hare St",
    "iso:country":"AU",
    "sg:address":"158 Hare St",
    "sg:city":"Echuca",
    "sg:classifiers":[
        {
            "category":"Fast Food",
            "type":"Food & Drink"
        }
    ],
    "sg:phone":"+61 3 5480 0011",
    "sg:postcode":"3564",
    "sg:province":"VIC",
    "sg:tags":[
        "away",
        "take"
    ],
    "wof:name":"Fish Bite Seafood",
    "wof:placetype":"venue"
},
  "geometry": {"coordinates":[144.749145508,-36.1270103455],"type":"Point"}
}