{
  "type": "Feature",
  "properties": {
    "addr:full":"Beaudesert Rd Calamvale QLD 4116",
    "addr:postcode":"4116",
    "addr:street":"Beaudesert Rd",
    "iso:country":"AU",
    "sg:address":"Beaudesert Rd",
    "sg:city":"Calamvale",
    "sg:classifiers":[
        {
            "category":"Health Services",
            "subcategory":"Dentist",
            "type":"Services"
        }
    ],
    "sg:phone":"+61 7 3711 4999",
    "sg:postcode":"4116",
    "sg:province":"QLD",
    "wof:name":"Duval Craig",
    "wof:placetype":"venue"
},
  "geometry": {"coordinates":[153.049438477,-27.6217956543],"type":"Point"}
}