{
  "type": "Feature",
  "properties": {
    "addr:full":"22- 34 Aplin St Cairns QLD 4870",
    "addr:housenumber":"34",
    "addr:postcode":"4870",
    "addr:street":"Aplin St",
    "iso:country":"AU",
    "sg:address":"22- 34 Aplin St",
    "sg:city":"Cairns",
    "sg:classifiers":[
        {
            "category":"Building & Trades",
            "subcategory":"Construction",
            "type":"Services"
        }
    ],
    "sg:phone":"+61 7 4031 1833",
    "sg:postcode":"4870",
    "sg:province":"QLD",
    "sg:tags":[
        "contractor"
    ],
    "wof:name":"Glenwood Homes",
    "wof:placetype":"venue"
},
  "geometry": {"coordinates":[145.77244567899999,-16.9217319489],"type":"Point"}
}