{
  "type": "Feature",
  "properties": {
    "addr:full":"PO Box 3123 Broome WA 6725",
    "addr:postcode":"6725",
    "iso:country":"AU",
    "sg:address":"PO Box 3123",
    "sg:city":"Broome",
    "sg:classifiers":[
        {
            "category":"Building & Trades",
            "subcategory":"Landscaping Services",
            "type":"Services"
        }
    ],
    "sg:phone":"+61 408 083 271",
    "sg:postcode":"6725",
    "sg:province":"WA",
    "sg:tags":[
        "designer",
        "landscape",
        "contractor"
    ],
    "wof:name":"Pindan Landscape",
    "wof:placetype":"venue"
},
  "geometry": {"coordinates":[122.677589416,-18.2141704559],"type":"Point"}
}