{
  "type": "Feature",
  "properties": {
    "iso:country":"AU",
    "sg:address":"Vereker St",
    "sg:city":"Humpty Doo",
    "sg:classifiers":[
        {
            "category":"Health Services",
            "subcategory":"Health Practitioner",
            "type":"Services"
        }
    ],
    "sg:phone":"+61 8 8988 2987",
    "sg:postcode":"0836",
    "sg:province":"NT",
    "sg:tags":[
        "acupuncture"
    ],
    "wof:name":"Humpty Doo Top Health Physiotherapy & Acupuncture",
    "wof:placetype":"venue"
},
  "geometry": {"coordinates":[131.10020399999999,-12.574069],"type":"Point"}
}