{
  "type": "Feature",
  "properties": {
    "addr:full":"300 Selby St Osborne Park WA 6017",
    "addr:housenumber":"300",
    "addr:postcode":"6017",
    "addr:street":"Selby St",
    "iso:country":"AU",
    "sg:address":"300 Selby St",
    "sg:city":"Osborne Park",
    "sg:classifiers":[
        {
            "category":"Education",
            "subcategory":"School",
            "type":"Public Place"
        }
    ],
    "sg:phone":"+61 8 9446 3335",
    "sg:postcode":"6017",
    "sg:province":"WA",
    "sg:tags":[
        "supply"
    ],
    "wof:name":"W.A. Library Supplies",
    "wof:placetype":"venue"
},
  "geometry": {"coordinates":[115.804229736,-31.9083900452],"type":"Point"}
}