{
  "type": "Feature",
  "properties": {
    "iso:country":"AU",
    "sg:address":"250 Mitchells Flat Rd",
    "sg:city":"Singleton",
    "sg:classifiers":[
        {
            "category":"Building & Trades",
            "subcategory":"Construction",
            "type":"Services"
        }
    ],
    "sg:phone":"+61 2 6574 1314",
    "sg:postcode":"2330",
    "sg:province":"NSW",
    "sg:tags":[
        "earth",
        "excavating",
        "moving",
        "contractor"
    ],
    "wof:name":"Badior Earthmoving",
    "wof:placetype":"venue"
},
  "geometry": {"coordinates":[151.284637,-32.55764],"type":"Point"}
}