{
  "type": "Feature",
  "properties": {
    "addr:full":"26/ 5 Telopea St Wollstonecraft NSW 2065",
    "addr:housenumber":"26 / 5",
    "addr:postcode":"2065",
    "addr:street":"Telopea St",
    "iso:country":"AU",
    "sg:address":"26/ 5 Telopea St",
    "sg:city":"Wollstonecraft",
    "sg:classifiers":[
        {
            "category":"Personal",
            "type":"Services"
        }
    ],
    "sg:phone":"+61 2 9436 1315",
    "sg:postcode":"2065",
    "sg:province":"NSW",
    "sg:tags":[
        "introduction",
        "social"
    ],
    "wof:name":"Seniors Introduction Service",
    "wof:placetype":"venue"
},
  "geometry": {"coordinates":[151.191116333,-33.8325920105],"type":"Point"}
}