{
  "type": "Feature",
  "properties": {
    "addr:full":"Westlakes Denture Clinic 8 Kingsland Ave Rathmines NSW 2283",
    "addr:housenumber":"8",
    "addr:postcode":"2283",
    "addr:street":"Kingsland Ave",
    "iso:country":"AU",
    "sg:address":"Westlakes Denture Clinic 8 Kingsland Ave",
    "sg:city":"Rathmines",
    "sg:classifiers":[
        {
            "category":"Health Services",
            "subcategory":"Dentist",
            "type":"Services"
        }
    ],
    "sg:phone":"+61 2 4975 3391",
    "sg:postcode":"2283",
    "sg:province":"NSW",
    "sg:tags":[
        "dental",
        "prosthetist"
    ],
    "wof:name":"Eager K R",
    "wof:placetype":"venue"
},
  "geometry": {"coordinates":[151.57975769000001,-33.0463523865],"type":"Point"}
}