{
  "type": "Feature",
  "properties": {
    "addr:full":"93 Kensington Rd Norwood SA 5067",
    "addr:housenumber":"93",
    "addr:postcode":"5067",
    "addr:street":"Kensington Rd",
    "iso:country":"AU",
    "sg:address":"93 Kensington Rd",
    "sg:city":"Norwood",
    "sg:classifiers":[
        {
            "category":"Health Services",
            "subcategory":"Doctor",
            "type":"Services"
        }
    ],
    "sg:phone":"+61 8 8431 5506",
    "sg:postcode":"5067",
    "sg:province":"SA",
    "sg:tags":[
        "medical",
        "practitioner"
    ],
    "wof:name":"Montanaro Patricia Dr",
    "wof:placetype":"venue"
},
  "geometry": {"coordinates":[138.63148498499999,-34.9272842407],"type":"Point"}
}