{
  "type": "Feature",
  "properties": {
    "iso:country":"AU",
    "sg:address":"32 Reichelt Ave",
    "sg:city":"Montmorency",
    "sg:classifiers":[
        {
            "category":"Professional",
            "subcategory":"Engineering",
            "type":"Services"
        }
    ],
    "sg:phone":"+61 3 9439 7163",
    "sg:postcode":"3094",
    "sg:province":"VIC",
    "sg:tags":[
        "electrical",
        "engineer"
    ],
    "wof:name":"Rolec Pty Ltd",
    "wof:placetype":"venue"
},
  "geometry": {"coordinates":[145.13372802699999,-37.7274703979],"type":"Point"}
}