{
  "type": "Feature",
  "properties": {
    "addr:full":"1 Milne St Thomastown VIC 3074",
    "addr:housenumber":"1",
    "addr:postcode":"3074",
    "addr:street":"Milne St",
    "iso:country":"AU",
    "sg:address":"1 Milne St",
    "sg:city":"Thomastown",
    "sg:classifiers":[
        {
            "category":"Professional",
            "type":"Services"
        }
    ],
    "sg:phone":"+61 3 9464 1399",
    "sg:postcode":"3074",
    "sg:province":"VIC",
    "sg:tags":[
        "transport"
    ],
    "wof:name":"Concord Park Pty Ltd",
    "wof:placetype":"venue"
},
  "geometry": {"coordinates":[145.01792907699999,-37.6890106201],"type":"Point"}
}