{
  "type": "Feature",
  "properties": {
    "iso:country":"AU",
    "sg:address":"201 Galena St",
    "sg:city":"Broken Hill",
    "sg:classifiers":[
        {
            "category":"Travel",
            "subcategory":"Hotels & Motels",
            "type":"Entertainment"
        }
    ],
    "sg:phone":"+61 8 8088 7013",
    "sg:postcode":"2880",
    "sg:province":"NSW",
    "sg:tags":[
        "accommodation"
    ],
    "wof:name":"Gateway Motor Inn",
    "wof:placetype":"venue"
},
  "geometry": {"coordinates":[141.44471740700001,-31.9597167969],"type":"Point"}
}