{
  "type": "Feature",
  "properties": {
    "addr:full":"108 Minimine St Stafford QLD 4053",
    "addr:housenumber":"108",
    "addr:postcode":"4053",
    "addr:street":"Minimine St",
    "iso:country":"AU",
    "sg:address":"108 Minimine St",
    "sg:city":"Stafford",
    "sg:classifiers":[
        {
            "category":"Home & Garden",
            "subcategory":"Hardware",
            "type":"Retail Goods"
        }
    ],
    "sg:phone":"+61 7 3356 4284",
    "sg:postcode":"4053",
    "sg:province":"QLD",
    "sg:tags":[
        "rope",
        "twine"
    ],
    "wof:name":"Innovative Displays",
    "wof:placetype":"venue"
},
  "geometry": {"coordinates":[153.012207031,-27.4061641693],"type":"Point"}
}