{
  "type": "Feature",
  "properties": {
    "addr:full":"252 Prospect Rd Prospect SA 5082",
    "addr:housenumber":"252",
    "addr:postcode":"5082",
    "addr:street":"Prospect Rd",
    "iso:country":"AU",
    "sg:address":"252 Prospect Rd",
    "sg:city":"Prospect",
    "sg:classifiers":[
        {
            "category":"Government",
            "subcategory":"Customs House",
            "type":"Public Place"
        }
    ],
    "sg:phone":"+61 8 8342 1544",
    "sg:postcode":"5082",
    "sg:province":"SA",
    "sg:tags":[
        "title",
        "management",
        "stratum"
    ],
    "wof:name":"Ace Body Corporate Management",
    "wof:placetype":"venue"
},
  "geometry": {"coordinates":[138.59315490700001,-34.8765068054],"type":"Point"}
}