{
  "type": "Feature",
  "properties": {
    "iso:country":"AU",
    "sg:address":"88 Rausch St",
    "sg:city":"Toongabbie",
    "sg:classifiers":[
        {
            "category":"Professional",
            "subcategory":"Art Services",
            "type":"Services"
        }
    ],
    "sg:phone":"+61 419 403 570",
    "sg:postcode":"2146",
    "sg:province":"NSW",
    "sg:tags":[
        "decorator",
        "painter"
    ],
    "wof:name":"M & M Better Painting Service",
    "wof:placetype":"venue"
},
  "geometry": {"coordinates":[150.95962524399999,-33.7832107544],"type":"Point"}
}