{
  "type": "Feature",
  "properties": {
    "iso:country":"AU",
    "sg:address":"Suite 2/ 608 Bruce Hwy",
    "sg:city":"Woree",
    "sg:classifiers":[
        {
            "category":"Banks & Credit Unions",
            "subcategory":"Financial Services",
            "type":"Services"
        }
    ],
    "sg:phone":"+61 7 4033 7366",
    "sg:postcode":"4868",
    "sg:province":"QLD",
    "sg:tags":[
        "annuity",
        "rollover",
        "superannuation",
        "consultant"
    ],
    "wof:name":"KIB",
    "wof:placetype":"venue"
},
  "geometry": {"coordinates":[145.74621582,-16.9537143707],"type":"Point"}
}