{
  "type": "Feature",
  "properties": {
    "iso:country":"AU",
    "sg:address":"16 Palmerston St",
    "sg:city":"Drysdale",
    "sg:classifiers":[
        {
            "category":"Travel",
            "subcategory":"Hostel",
            "type":"Entertainment"
        }
    ],
    "sg:phone":"+61 3 5253 2582",
    "sg:postcode":"3222",
    "sg:province":"VIC",
    "sg:tags":[
        "home"
    ],
    "wof:name":"Palmerston Court Hostel Aged Care",
    "wof:placetype":"venue"
},
  "geometry": {"coordinates":[144.567429,-38.173897],"type":"Point"}
}