{
  "type": "Feature",
  "properties": {
    "addr:full":"35 Cook St Parndana SA 5220",
    "addr:housenumber":"35",
    "addr:postcode":"5220",
    "addr:street":"Cook St",
    "iso:country":"AU",
    "sg:address":"35 Cook St",
    "sg:city":"Parndana",
    "sg:classifiers":[
        {
            "category":"Government",
            "subcategory":"Post Office",
            "type":"Public Place"
        }
    ],
    "sg:phone":"+61 8 8559 6051",
    "sg:postcode":"5220",
    "sg:province":"SA",
    "sg:tags":[
        "postal"
    ],
    "wof:name":"Australia Post",
    "wof:placetype":"venue"
},
  "geometry": {"coordinates":[137.262207031,-35.7905960083],"type":"Point"}
}