{
  "type": "Feature",
  "properties": {
    "addr:full":"506 Torrens Rd Woodville North SA 5012",
    "addr:housenumber":"506",
    "addr:postcode":"5012",
    "addr:street":"Torrens Rd",
    "iso:country":"AU",
    "sg:address":"506 Torrens Rd",
    "sg:city":"Woodville North",
    "sg:classifiers":[
        {
            "category":"Retail",
            "subcategory":"Auto Repair",
            "type":"Services"
        }
    ],
    "sg:phone":"+61 8 8347 1717",
    "sg:postcode":"5012",
    "sg:province":"SA",
    "sg:tags":[
        "repairer",
        "motor",
        "engineer"
    ],
    "wof:name":"Naz's Auto Repairs",
    "wof:placetype":"venue"
},
  "geometry": {"coordinates":[138.54556274399999,-34.8731842041],"type":"Point"}
}