{
  "type": "Feature",
  "properties": {
    "addr:full":"Shp 19B Woodcroft Shopng Cntr Cnr Woodcroft & Richmond Rds Doonside NSW 2767",
    "addr:housenumber":"19b",
    "addr:postcode":"2767",
    "addr:street":"Woodcroft Shopng Cntr Cnr",
    "iso:country":"AU",
    "sg:address":"Shp 19B Woodcroft Shopng Cntr Cnr Woodcroft & Richmond Rds",
    "sg:city":"Doonside",
    "sg:classifiers":[
        {
            "category":"Food & Beverages",
            "subcategory":"Liquor & Beverages",
            "type":"Retail Goods"
        }
    ],
    "sg:phone":"+61 2 9672 3441",
    "sg:postcode":"2767",
    "sg:province":"NSW",
    "sg:tags":[
        "store"
    ],
    "wof:name":"Liquorland",
    "wof:placetype":"venue"
},
  "geometry": {"coordinates":[150.88047790499999,-33.7595176697],"type":"Point"}
}