{
  "type": "Feature",
  "properties": {
    "addr:full":"1170 South Rd Clovelly Park SA 5042",
    "addr:housenumber":"1170",
    "addr:postcode":"5042",
    "addr:street":"South Rd",
    "iso:country":"AU",
    "sg:address":"1170 South Rd",
    "sg:city":"Clovelly Park",
    "sg:classifiers":[
        {
            "category":"Wholesale",
            "subcategory":"Painting Supplies",
            "type":"Manufacturing & Wholesale Goods"
        }
    ],
    "sg:phone":"+61 8 8277 2111",
    "sg:postcode":"5042",
    "sg:province":"SA",
    "sg:tags":[
        "wholesaler",
        "paint",
        "mfrs"
    ],
    "wof:name":"Solver Paints",
    "wof:placetype":"venue"
},
  "geometry": {"coordinates":[138.57492099999999,-34.99646],"type":"Point"}
}