{
  "type": "Feature",
  "properties": {
    "iso:country":"AU",
    "sg:address":"Fairford Rd",
    "sg:city":"Ingham",
    "sg:classifiers":[
        {
            "category":"Farming",
            "subcategory":"Crops",
            "type":"Manufacturing & Wholesale Goods"
        }
    ],
    "sg:phone":"+61 7 4776 1808",
    "sg:postcode":"4850",
    "sg:province":"QLD",
    "sg:tags":[
        "sugarcane",
        "mill",
        "grower"
    ],
    "wof:name":"Herbert Cane Productivity Services Ltd",
    "wof:placetype":"venue"
},
  "geometry": {"coordinates":[146.14736938499999,-18.6501960754],"type":"Point"}
}