{
  "type": "Feature",
  "properties": {
    "addr:full":"Suite 15, Cnr Edmondson Ave & Fiffteenth Ave Austral NSW 2171",
    "addr:housenumber":"cnr",
    "addr:postcode":"2171",
    "addr:street":"Edmondson Ave & Fiffteenth Ave Austral",
    "iso:country":"AU",
    "sg:address":"Suite 15, Cnr Edmondson Ave & Fiffteenth Ave",
    "sg:city":"Austral",
    "sg:classifiers":[
        {
            "category":"Health Services",
            "subcategory":"Doctor",
            "type":"Services"
        }
    ],
    "sg:phone":"+61 2 9606 0145",
    "sg:postcode":"2171",
    "sg:province":"NSW",
    "sg:tags":[
        "medical",
        "practitioner"
    ],
    "wof:name":"West Hoxton Medical Centre",
    "wof:placetype":"venue"
},
  "geometry": {"coordinates":[150.846237183,-33.9284286499],"type":"Point"}
}