{
  "type": "Feature",
  "properties": {
    "addr:full":"48 Rochester Drv Mindarie WA 6030",
    "addr:housenumber":"48",
    "addr:postcode":"6030",
    "addr:street":"Rochester Drv",
    "iso:country":"AU",
    "sg:address":"48 Rochester Drv",
    "sg:city":"Mindarie",
    "sg:classifiers":[
        {
            "category":"Building & Trades",
            "subcategory":"Construction",
            "type":"Services"
        }
    ],
    "sg:phone":"+61 8 9407 8017",
    "sg:postcode":"6030",
    "sg:province":"WA",
    "sg:tags":[
        "contractor"
    ],
    "wof:name":"Ventura Homes Pty Ltd",
    "wof:placetype":"venue"
},
  "geometry": {"coordinates":[115.713287353,-31.6838130951],"type":"Point"}
}