{
  "type": "Feature",
  "properties": {
    "iso:country":"AU",
    "sg:address":"264 Charles St",
    "sg:city":"North Perth",
    "sg:classifiers":[
        {
            "category":"Shopping",
            "subcategory":"Stationery & Office Supplies",
            "type":"Retail Goods"
        }
    ],
    "sg:phone":"+61 8 9227 8586",
    "sg:postcode":"6006",
    "sg:province":"WA",
    "sg:tags":[
        "partition"
    ],
    "wof:name":"Apex Ceilings & Partitions",
    "wof:placetype":"venue"
},
  "geometry": {"coordinates":[115.85269928,-31.9301185608],"type":"Point"}
}