{
  "type": "Feature",
  "properties": {
    "addr:full":"363 Hargreaves St Bendigo VIC 3550",
    "addr:housenumber":"363",
    "addr:postcode":"3550",
    "addr:street":"Hargreaves St",
    "iso:country":"AU",
    "sg:address":"363 Hargreaves St",
    "sg:city":"Bendigo",
    "sg:classifiers":[
        {
            "category":"Home & Garden",
            "subcategory":"Kitchen Supply",
            "type":"Retail Goods"
        }
    ],
    "sg:phone":"+61 3 5441 6337",
    "sg:postcode":"3550",
    "sg:province":"VIC",
    "sg:tags":[
        "equipment",
        "diving"
    ],
    "wof:name":"Bendigo Skin Ski & Surf",
    "wof:placetype":"venue"
},
  "geometry": {"coordinates":[144.2787323,-36.761302948],"type":"Point"}
}