{
  "type": "Feature",
  "properties": {
    "addr:full":"38 - 44 Franklin St George Town TAS 7253",
    "addr:housenumber":"44;st",
    "addr:postcode":"7253",
    "addr:street":"Franklin",
    "iso:country":"AU",
    "sg:address":"38 - 44 Franklin St",
    "sg:city":"George Town",
    "sg:classifiers":[
        {
            "category":"Wholesale",
            "subcategory":"Seafood",
            "type":"Manufacturing & Wholesale Goods"
        }
    ],
    "sg:phone":"+61 3 6382 3466",
    "sg:postcode":"7253",
    "sg:province":"TAS",
    "sg:tags":[
        "fish"
    ],
    "wof:name":"George Town Seafoods Pty Ltd",
    "wof:placetype":"venue"
},
  "geometry": {"coordinates":[146.836837769,-41.1158638],"type":"Point"}
}