{
  "type": "Feature",
  "properties": {
    "addr:full":"52 Ridley St Charlestown NSW 2290",
    "addr:housenumber":"52",
    "addr:postcode":"2290",
    "addr:street":"Ridley St",
    "iso:country":"AU",
    "sg:address":"52 Ridley St",
    "sg:city":"Charlestown",
    "sg:classifiers":[
        {
            "category":"Health Services",
            "subcategory":"Doctor",
            "type":"Services"
        }
    ],
    "sg:phone":"+61 2 4943 3166",
    "sg:postcode":"2290",
    "sg:province":"NSW",
    "sg:tags":[
        "medical",
        "practitioner"
    ],
    "wof:name":"Manners Seth",
    "wof:placetype":"venue"
},
  "geometry": {"coordinates":[151.69569397000001,-32.9623184204],"type":"Point"}
}