{
  "type": "Feature",
  "properties": {
    "addr:full":"Shop 3 116 Payneham Rd Stepney SA 5069",
    "addr:housenumber":"shop 3",
    "addr:postcode":"116;5069",
    "addr:street":"Payneham Rd",
    "iso:country":"AU",
    "sg:address":"Shop 3 116 Payneham Rd",
    "sg:city":"Stepney",
    "sg:classifiers":[
        {
            "category":"Personal",
            "subcategory":"Hair Removal",
            "type":"Services"
        }
    ],
    "sg:phone":"+61 8 8362 7311",
    "sg:postcode":"5069",
    "sg:province":"SA",
    "wof:name":"Beth Jamieson Beauty Therapist",
    "wof:placetype":"venue"
},
  "geometry": {"coordinates":[138.627044678,-34.9102668762],"type":"Point"}
}