{
  "type": "Feature",
  "properties": {
    "addr:full":"1 Walter St Boonah QLD 4310",
    "addr:housenumber":"1",
    "addr:postcode":"4310",
    "addr:street":"Walter St",
    "iso:country":"AU",
    "sg:address":"1 Walter St",
    "sg:city":"Boonah",
    "sg:classifiers":[
        {
            "category":"Retail",
            "subcategory":"Auto Repair",
            "type":"Services"
        }
    ],
    "sg:phone":"+61 7 5463 1624",
    "sg:postcode":"4310",
    "sg:province":"QLD",
    "sg:tags":[
        "electrical"
    ],
    "wof:name":"Fassifern Automotive Electrics",
    "wof:placetype":"venue"
},
  "geometry": {"coordinates":[152.68309020999999,-27.9988918304],"type":"Point"}
}