{
  "type": "Feature",
  "properties": {
    "addr:full":"St Andrews La Busselton WA 6280",
    "addr:postcode":"6280",
    "addr:street":"St Andrews La",
    "iso:country":"AU",
    "sg:address":"St Andrews La",
    "sg:city":"Busselton",
    "sg:classifiers":[
        {
            "category":"Home & Garden",
            "subcategory":"Building Materials",
            "type":"Retail Goods"
        }
    ],
    "sg:phone":"+61 8 9753 1211",
    "sg:postcode":"6280",
    "sg:province":"WA",
    "sg:tags":[
        "lawn",
        "cutting",
        "maintenance"
    ],
    "wof:name":"Woodward A & D Mowing Service",
    "wof:placetype":"venue"
},
  "geometry": {"coordinates":[115.349700928,-33.6929397583],"type":"Point"}
}