{
  "type": "Feature",
  "properties": {
    "iso:country":"AU",
    "sg:address":"Greystanes Shopping Centre, Shop 5a, 655-699 Merrylands Road",
    "sg:city":"Greystanes",
    "sg:classifiers":[
        {
            "category":"Health Services",
            "subcategory":"Dentist",
            "type":"Services"
        }
    ],
    "sg:phone":"+61 2 9631 1766",
    "sg:postcode":"2145",
    "sg:province":"NSW",
    "wof:name":"Greystanes Dental Surgery",
    "wof:placetype":"venue"
},
  "geometry": {"coordinates":[150.951538086,-33.8292579651],"type":"Point"}
}