{
  "type": "Feature",
  "properties": {
    "addr:full":"107- 109 Mann St Gosford NSW 2250",
    "addr:housenumber":"109",
    "addr:postcode":"2250",
    "addr:street":"Mann St",
    "iso:country":"AU",
    "sg:address":"107- 109 Mann St",
    "sg:city":"Gosford",
    "sg:classifiers":[
        {
            "category":"Real Estate",
            "subcategory":"Real Estate Agent",
            "type":"Services"
        }
    ],
    "sg:phone":"+61 2 4323 3433",
    "sg:postcode":"2250",
    "sg:province":"NSW",
    "wof:name":"Richardson & Wrench Gosford",
    "wof:placetype":"venue"
},
  "geometry": {"coordinates":[151.34202575699999,-33.4268112183],"type":"Point"}
}