{
  "type": "Feature",
  "properties": {
    "addr:full":"32 Scoresby St Kerang VIC 3579",
    "addr:housenumber":"32",
    "addr:postcode":"3579",
    "addr:street":"Scoresby St",
    "iso:country":"AU",
    "sg:address":"32 Scoresby St",
    "sg:city":"Kerang",
    "sg:classifiers":[
        {
            "category":"Personal",
            "subcategory":"Beauty Salon",
            "type":"Services"
        }
    ],
    "sg:phone":"+61 3 5452 2252",
    "sg:postcode":"3579",
    "sg:province":"VIC",
    "sg:tags":[
        "hairdresser"
    ],
    "wof:name":"Kerang Hair Shack",
    "wof:placetype":"venue"
},
  "geometry": {"coordinates":[143.920120239,-35.7330703735],"type":"Point"}
}