{
  "type": "Feature",
  "properties": {
    "iso:country":"AU",
    "sg:address":"76 Graham St",
    "sg:city":"Moama",
    "sg:classifiers":[
        {
            "category":"Wholesale",
            "subcategory":"Seafood",
            "type":"Manufacturing & Wholesale Goods"
        }
    ],
    "sg:phone":"+61 3 5482 1840",
    "sg:postcode":"2731",
    "sg:province":"NSW",
    "sg:tags":[
        "fish"
    ],
    "wof:name":"Fresh Seafood Supplies",
    "wof:placetype":"venue"
},
  "geometry": {"coordinates":[144.768692,-36.104092],"type":"Point"}
}