{
  "type": "Feature",
  "properties": {
    "iso:country":"AU",
    "sg:address":"Suite 103/ 5 Commercial Rd",
    "sg:city":"Kingsgrove",
    "sg:classifiers":[
        {
            "category":"Organizations",
            "subcategory":"Non-profit Organization",
            "type":"Services"
        }
    ],
    "sg:phone":"+61 2 9503 1666",
    "sg:postcode":"2208",
    "sg:province":"NSW",
    "sg:tags":[
        "support",
        "disability",
        "organisation"
    ],
    "wof:name":"Acrod Limited NSW Division",
    "wof:placetype":"venue"
},
  "geometry": {"coordinates":[151.100815,-33.94009],"type":"Point"}
}