{
  "type": "Feature",
  "properties": {
    "iso:country":"AU",
    "sg:address":"Unit 1, Lorimer Business Park, 31 Sabre Drv",
    "sg:city":"Port Melbourne",
    "sg:classifiers":[
        {
            "category":"Wholesale",
            "subcategory":"Medical Equipment & Supplies",
            "type":"Manufacturing & Wholesale Goods"
        }
    ],
    "sg:phone":"+61 3 8698 6300",
    "sg:postcode":"3207",
    "sg:province":"VIC",
    "sg:tags":[
        "dental"
    ],
    "wof:name":"Sirona Dental Systems P/L",
    "wof:placetype":"venue"
},
  "geometry": {"coordinates":[144.906967,-37.827694],"type":"Point"}
}