{
  "type": "Feature",
  "properties": {
    "addr:full":"Unit 4, 16 Railway Rd Carnegie VIC 3163",
    "addr:housenumber":"16",
    "addr:postcode":"3163",
    "addr:street":"Railway Rd",
    "iso:country":"AU",
    "sg:address":"Unit 4, 16 Railway Rd",
    "sg:city":"Carnegie",
    "sg:classifiers":[
        {
            "category":"Shopping",
            "subcategory":"Stationery & Office Supplies",
            "type":"Retail Goods"
        }
    ],
    "sg:phone":"+61 1300 767 844",
    "sg:postcode":"3163",
    "sg:province":"VIC",
    "sg:tags":[
        "equipment",
        "display",
        "exhibition"
    ],
    "sg:website":"http://www.barneys.com.au",
    "wof:name":"Barney's Print Management",
    "wof:placetype":"venue"
},
  "geometry": {"coordinates":[145.05340576200001,-37.8933753967],"type":"Point"}
}