{
  "type": "Feature",
  "properties": {
    "addr:full":"65 Temple St Heyfield VIC 3858",
    "addr:housenumber":"65",
    "addr:postcode":"3858",
    "addr:street":"Temple St",
    "iso:country":"AU",
    "sg:address":"65 Temple St",
    "sg:city":"Heyfield",
    "sg:classifiers":[
        {
            "category":"Social Services",
            "subcategory":"Child Care",
            "type":"Services"
        }
    ],
    "sg:phone":"+61 3 5148 2524",
    "sg:postcode":"3858",
    "sg:province":"VIC",
    "sg:tags":[
        "support",
        "health"
    ],
    "wof:name":"Maternal & Child Health Centres",
    "wof:placetype":"venue"
},
  "geometry": {"coordinates":[146.78494262699999,-37.9839248657],"type":"Point"}
}