{
  "type": "Feature",
  "properties": {
    "addr:full":"13 McCabe St Greystanes NSW 2145",
    "addr:housenumber":"13",
    "addr:postcode":"2145",
    "addr:street":"Mccabe St",
    "iso:country":"AU",
    "sg:address":"13 McCabe St",
    "sg:city":"Greystanes",
    "sg:classifiers":[
        {
            "category":"Structure",
            "subcategory":"Office Building",
            "type":"Public Place"
        }
    ],
    "sg:phone":"+61 2 9636 9747",
    "sg:postcode":"2145",
    "sg:province":"NSW",
    "sg:tags":[
        "slater",
        "tiler",
        "roof"
    ],
    "wof:name":"Squire Roof Tiling",
    "wof:placetype":"venue"
},
  "geometry": {"coordinates":[150.936203003,-33.8272972107],"type":"Point"}
}