{
  "type": "Feature",
  "properties": {
    "addr:full":"27 Miller St Thornbury VIC 3071",
    "addr:housenumber":"27",
    "addr:postcode":"3071",
    "addr:street":"Miller St",
    "iso:country":"AU",
    "sg:address":"27 Miller St",
    "sg:city":"Thornbury",
    "sg:classifiers":[
        {
            "category":"Professional",
            "subcategory":"Computer Services",
            "type":"Services"
        }
    ],
    "sg:phone":"+61 3 9480 1592",
    "sg:postcode":"3071",
    "sg:province":"VIC",
    "sg:tags":[
        "consultant",
        "system"
    ],
    "wof:name":"Supply Technology",
    "wof:placetype":"venue"
},
  "geometry": {"coordinates":[144.993743897,-37.7516860962],"type":"Point"}
}