{
  "type": "Feature",
  "properties": {
    "iso:country":"AU",
    "sg:address":"PO Box 229",
    "sg:city":"Nunawading",
    "sg:classifiers":[
        {
            "category":"Education",
            "subcategory":"Dance Studio",
            "type":"Public Place"
        }
    ],
    "sg:phone":"+61 3 9872 5399",
    "sg:postcode":"3131",
    "sg:province":"VIC",
    "sg:tags":[
        "square",
        "caller",
        "dancing"
    ],
    "wof:name":"The Victorian Callers Association Inc",
    "wof:placetype":"venue"
},
  "geometry": {"coordinates":[145.17576599099999,-37.8192710876],"type":"Point"}
}