{
  "type": "Feature",
  "properties": {
    "addr:full":"45 McRoyle St Wacol QLD 4076",
    "addr:housenumber":"45",
    "addr:postcode":"4076",
    "addr:street":"Mcroyle St",
    "iso:country":"AU",
    "sg:address":"45 McRoyle St",
    "sg:city":"Wacol",
    "sg:classifiers":[
        {
            "category":"Professional",
            "subcategory":"Accounting & Tax Preparation",
            "type":"Services"
        }
    ],
    "sg:phone":"+61 7 3879 4276",
    "sg:postcode":"4076",
    "sg:province":"QLD",
    "sg:tags":[
        "record",
        "business",
        "destruction"
    ],
    "sg:website":"http://www.australianmobileshredding.com.au",
    "wof:name":"Australian Mobile Shredding",
    "wof:placetype":"venue"
},
  "geometry": {"coordinates":[152.93385314899999,-27.5974216461],"type":"Point"}
}