{
  "type": "Feature",
  "properties": {
    "iso:country":"AU",
    "sg:address":"Ste216/ 737 Burwood Rd",
    "sg:city":"Hawthorn East",
    "sg:classifiers":[
        {
            "category":"Banks & Credit Unions",
            "subcategory":"Financial Services",
            "type":"Services"
        }
    ],
    "sg:phone":"+61 3 8862 6368",
    "sg:postcode":"3123",
    "sg:province":"VIC",
    "sg:tags":[
        "annuity",
        "rollover",
        "superannuation",
        "consultant"
    ],
    "wof:name":"Super Sphere Pty Ltd",
    "wof:placetype":"venue"
},
  "geometry": {"coordinates":[145.05026245100001,-37.8242530823],"type":"Point"}
}