{
  "type": "Feature",
  "properties": {
    "addr:full":"Shop 114 Upper Level Hyperdome Tuggeranong ACT 2900",
    "addr:housenumber":"114",
    "addr:postcode":"2900",
    "addr:street":"Upper Level Hyperdome",
    "iso:country":"AU",
    "sg:address":"Shop 114",
    "sg:city":"Upper Level Hyperdome Tuggeranong",
    "sg:classifiers":[
        {
            "category":"Professional",
            "subcategory":"Printing & Photocopies",
            "type":"Services"
        }
    ],
    "sg:phone":"+61 2 6293 3166",
    "sg:postcode":"2900",
    "sg:province":"ACT",
    "sg:tags":[
        "laminating"
    ],
    "wof:name":"Copy & Design",
    "wof:placetype":"venue"
},
  "geometry": {"coordinates":[149.065795898,-35.4151611328],"type":"Point"}
}