{
  "type": "Feature",
  "properties": {
    "iso:country":"AU",
    "sg:address":"52A Lee St",
    "sg:city":"Bathurst",
    "sg:classifiers":[
        {
            "category":"Home & Garden",
            "subcategory":"Household Appliances",
            "type":"Retail Goods"
        }
    ],
    "sg:phone":"+61 2 6331 4300",
    "sg:postcode":"2795",
    "sg:province":"NSW",
    "sg:tags":[
        "equipment",
        "gas"
    ],
    "wof:name":"Ice-Air",
    "wof:placetype":"venue"
},
  "geometry": {"coordinates":[149.608688355,-33.4226799011],"type":"Point"}
}