{
  "type": "Feature",
  "properties": {
    "iso:country":"AU",
    "sg:address":"PO Box 995",
    "sg:city":"Subiaco Private Boxes",
    "sg:classifiers":[
        {
            "category":"Professional",
            "subcategory":"Accounting & Tax Preparation",
            "type":"Services"
        }
    ],
    "sg:phone":"+61 8 9382 1316",
    "sg:postcode":"6904",
    "sg:province":"WA",
    "sg:tags":[
        "bookkeeping"
    ],
    "wof:name":"Busy Bookkeeping Western Suburbs",
    "wof:placetype":"venue"
},
  "geometry": {"coordinates":[115.829773,-31.943567],"type":"Point"}
}