{
  "type": "Feature",
  "properties": {
    "addr:full":"11 Chapman Valley Rd Geraldton WA 6530",
    "addr:housenumber":"11",
    "addr:postcode":"6530",
    "addr:street":"Chapman Valley Rd",
    "iso:country":"AU",
    "sg:address":"11 Chapman Valley Rd",
    "sg:city":"Geraldton",
    "sg:classifiers":[
        {
            "category":"Home & Garden",
            "subcategory":"Building Materials",
            "type":"Retail Goods"
        }
    ],
    "sg:phone":"+61 8 9938 2171",
    "sg:postcode":"6530",
    "sg:province":"WA",
    "sg:tags":[
        "lawn",
        "cutting",
        "maintenance"
    ],
    "wof:name":"Baytree Gardening Services",
    "wof:placetype":"venue"
},
  "geometry": {"coordinates":[114.636741638,-28.719991684],"type":"Point"}
}