{
  "type": "Feature",
  "properties": {
    "iso:country":"AU",
    "sg:address":"18 Allanton Ave",
    "sg:city":"Port Noarlunga",
    "sg:classifiers":[
        {
            "category":"Professional",
            "subcategory":"Business Services",
            "type":"Services"
        }
    ],
    "sg:phone":"+61 8 8186 3081",
    "sg:postcode":"5167",
    "sg:province":"SA",
    "sg:tags":[
        "drafting"
    ],
    "wof:name":"G & K Drafting",
    "wof:placetype":"venue"
},
  "geometry": {"coordinates":[138.484741211,-35.1510696411],"type":"Point"}
}