{
  "type": "Feature",
  "properties": {
    "addr:full":"214 McDonald Rd Lisarow NSW 2250",
    "addr:housenumber":"214",
    "addr:postcode":"2250",
    "addr:street":"Mcdonald Rd",
    "iso:country":"AU",
    "sg:address":"214 McDonald Rd",
    "sg:city":"Lisarow",
    "sg:classifiers":[
        {
            "category":"Building & Trades",
            "subcategory":"Cleaning & Sanitation",
            "type":"Services"
        }
    ],
    "sg:phone":"+61 2 4362 7656",
    "sg:postcode":"2250",
    "sg:province":"NSW",
    "sg:tags":[
        "grease",
        "trap"
    ],
    "wof:name":"Flood J W",
    "wof:placetype":"venue"
},
  "geometry": {"coordinates":[151.37466430699999,-33.3800773621],"type":"Point"}
}