{
  "type": "Feature",
  "properties": {
    "iso:country":"AU",
    "sg:address":"Blackmur St",
    "sg:city":"Marian",
    "sg:classifiers":[
        {
            "category":"Education",
            "subcategory":"Dance Studio",
            "type":"Public Place"
        }
    ],
    "sg:phone":"+61 7 4954 3766",
    "sg:postcode":"4753",
    "sg:province":"QLD",
    "sg:tags":[
        "venue",
        "tuition"
    ],
    "wof:name":"Pioneer Valley School Of Dance",
    "wof:placetype":"venue"
},
  "geometry": {"coordinates":[148.94429,-21.145536],"type":"Point"}
}