{
  "type": "Feature",
  "properties": {
    "iso:country":"AU",
    "sg:address":"247 Flinders La",
    "sg:city":"Melbourne",
    "sg:classifiers":[
        {
            "category":"Professional",
            "subcategory":"Computer Services",
            "type":"Services"
        }
    ],
    "sg:phone":"+61 3 9654 5800",
    "sg:postcode":"3000",
    "sg:province":"VIC",
    "sg:tags":[
        "training"
    ],
    "wof:name":"Mac Advice",
    "wof:placetype":"venue"
},
  "geometry": {"coordinates":[144.96611023,-37.8168678284],"type":"Point"}
}