{
  "type": "Feature",
  "properties": {
    "addr:full":"41 St Mary's Rd Berkshire Park NSW 2765",
    "addr:housenumber":"41",
    "addr:postcode":"2765",
    "addr:street":"St Mary'S Rd",
    "iso:country":"AU",
    "sg:address":"41 St Mary's Rd",
    "sg:city":"Berkshire Park",
    "sg:classifiers":[
        {
            "category":"Retail",
            "subcategory":"Auto Rental",
            "type":"Services"
        }
    ],
    "sg:phone":"+61 2 4572 5700",
    "sg:postcode":"2765",
    "sg:province":"NSW",
    "sg:tags":[
        "chauffeur",
        "car",
        "hire",
        "driven",
        "limousine"
    ],
    "wof:name":"Ace American Convertibles",
    "wof:placetype":"venue"
},
  "geometry": {"coordinates":[150.77061462399999,-33.7093772888],"type":"Point"}
}