{
  "type": "Feature",
  "properties": {
    "addr:full":"19- 23 Rosalie St Springvale VIC 3171",
    "addr:housenumber":"23",
    "addr:postcode":"3171",
    "addr:street":"Rosalie St",
    "iso:country":"AU",
    "sg:address":"19- 23 Rosalie St",
    "sg:city":"Springvale",
    "sg:classifiers":[
        {
            "category":"Organizations",
            "subcategory":"Membership Organization",
            "type":"Services"
        }
    ],
    "sg:phone":"+61 3 9574 6346",
    "sg:postcode":"3171",
    "sg:province":"VIC",
    "sg:tags":[
        "club",
        "car"
    ],
    "wof:name":"Austin-Healey Owners Club Inc",
    "wof:placetype":"venue"
},
  "geometry": {"coordinates":[145.156646728,-37.9449806213],"type":"Point"}
}