{
  "type": "Feature",
  "properties": {
    "iso:country":"AU",
    "sg:address":"22 Chesterman St",
    "sg:city":"Derwent Park",
    "sg:classifiers":[
        {
            "category":"Home & Garden",
            "subcategory":"Garden Supply",
            "type":"Retail Goods"
        }
    ],
    "sg:phone":"+61 3 6273 1411",
    "sg:postcode":"7009",
    "sg:province":"TAS",
    "sg:tags":[
        "equipment",
        "hydroponics"
    ],
    "wof:name":"The Hydroponics Company",
    "wof:placetype":"venue"
},
  "geometry": {"coordinates":[147.29606628400001,-42.8404121399],"type":"Point"}
}