{
  "type": "Feature",
  "properties": {
    "iso:country":"AU",
    "sg:address":"114 Maitland St",
    "sg:city":"Hackett",
    "sg:classifiers":[
        {
            "category":"Organizations",
            "subcategory":"Community Association",
            "type":"Services"
        }
    ],
    "sg:phone":"+61 2 6295 0236",
    "sg:postcode":"2602",
    "sg:province":"ACT",
    "sg:tags":[
        "organisation",
        "family",
        "welfare"
    ],
    "wof:name":"National Youth Coalition For Housing",
    "wof:placetype":"venue"
},
  "geometry": {"coordinates":[149.16325378400001,-35.2498016357],"type":"Point"}
}