{
  "type": "Feature",
  "properties": {
    "addr:full":"Smiths Beach Rd Yallingup WA 6282",
    "addr:postcode":"6282",
    "addr:street":"Smiths Beach Rd",
    "iso:country":"AU",
    "sg:address":"Smiths Beach Rd",
    "sg:city":"Yallingup",
    "sg:classifiers":[
        {
            "category":"Travel",
            "subcategory":"Hotels & Motels",
            "type":"Entertainment"
        }
    ],
    "sg:phone":"+61 8 9755 2116",
    "sg:postcode":"6282",
    "sg:province":"WA",
    "sg:tags":[
        "accommodation"
    ],
    "wof:name":"Canal Rocks Beach Resort",
    "wof:placetype":"venue"
},
  "geometry": {"coordinates":[115.016197205,-33.6668891907],"type":"Point"}
}