{
  "type": "Feature",
  "properties": {
    "iso:country":"AU",
    "sg:address":"20 Beau Vorno Ave",
    "sg:city":"Keysborough",
    "sg:classifiers":[
        {
            "category":"Professional",
            "subcategory":"Detective & Security Services",
            "type":"Services"
        }
    ],
    "sg:phone":"+61 3 9769 0232",
    "sg:postcode":"3173",
    "sg:province":"VIC",
    "sg:tags":[
        "information",
        "adoption"
    ],
    "wof:name":"Association of Relinquishing Mothers (Vic) Inc.",
    "wof:placetype":"venue"
},
  "geometry": {"coordinates":[145.16000366200001,-37.9913749695],"type":"Point"}
}