{
  "type": "Feature",
  "properties": {
    "addr:full":"179 Conadilly St Gunnedah NSW 2380",
    "addr:housenumber":"179",
    "addr:postcode":"2380",
    "addr:street":"Conadilly St",
    "iso:country":"AU",
    "sg:address":"179 Conadilly St",
    "sg:city":"Gunnedah",
    "sg:classifiers":[
        {
            "category":"Shopping",
            "subcategory":"Music",
            "type":"Retail Goods"
        }
    ],
    "sg:phone":"+61 2 6742 2508",
    "sg:postcode":"2380",
    "sg:province":"NSW",
    "sg:tags":[
        "store"
    ],
    "wof:name":"Gunnedah Sound Centre",
    "wof:placetype":"venue"
},
  "geometry": {"coordinates":[150.25227355999999,-30.97722435],"type":"Point"}
}