{
  "type": "Feature",
  "properties": {
    "addr:full":"67-69 Cranbourne-Frankston Rd Langwarrin VIC 3910",
    "addr:housenumber":"67-69",
    "addr:postcode":"3910",
    "addr:street":"Cranbourne-Frankston Rd",
    "iso:country":"AU",
    "sg:address":"67-69 Cranbourne-Frankston Rd",
    "sg:city":"Langwarrin",
    "sg:classifiers":[
        {
            "category":"Education",
            "subcategory":"Special Training",
            "type":"Public Place"
        }
    ],
    "sg:phone":"+61 3 9789 3090",
    "sg:postcode":"3910",
    "sg:province":"VIC",
    "sg:tags":[
        "tuition-educational"
    ],
    "wof:name":"Visionary Spiritual Institute Of Australia",
    "wof:placetype":"venue"
},
  "geometry": {"coordinates":[145.22856140100001,-38.1337661743],"type":"Point"}
}