{
  "type": "Feature",
  "properties": {
    "iso:country":"AU",
    "sg:address":"3/ 198 Balgownie Rd",
    "sg:city":"Balgownie",
    "sg:classifiers":[
        {
            "category":"Building & Trades",
            "subcategory":"Construction",
            "type":"Services"
        }
    ],
    "sg:phone":"+61 412 529 766",
    "sg:postcode":"2519",
    "sg:province":"NSW",
    "sg:tags":[
        "joiner",
        "carpenter"
    ],
    "wof:name":"Peter King",
    "wof:placetype":"venue"
},
  "geometry": {"coordinates":[150.875504,-34.388176],"type":"Point"}
}