{
  "type": "Feature",
  "properties": {
    "addr:full":"Shop 26, Domayne Complex 119 Parramatta Rd Auburn NSW 2144",
    "addr:housenumber":"shop 26;119",
    "addr:postcode":"2144",
    "addr:street":"Domayne Complex;Parramatta Rd",
    "iso:country":"AU",
    "sg:address":"Shop 26, Domayne Complex 119 Parramatta Rd",
    "sg:city":"Auburn",
    "sg:classifiers":[
        {
            "category":"Home & Garden",
            "subcategory":"Carpets & Floor Coverings",
            "type":"Retail Goods"
        }
    ],
    "sg:phone":"+61 1300 853 353",
    "sg:postcode":"2144",
    "sg:province":"NSW",
    "sg:tags":[
        "wood"
    ],
    "wof:name":"Floors Dominion",
    "wof:placetype":"venue"
},
  "geometry": {"coordinates":[151.040893555,-33.8439979553],"type":"Point"}
}