{
  "type": "Feature",
  "properties": {
    "addr:full":"Level 8, 140 Arthur North Sydney NSW 2060",
    "addr:housenumber":"140",
    "addr:postcode":"2060",
    "addr:street":"Arthur",
    "iso:country":"AU",
    "sg:address":"Level 8, 140",
    "sg:city":"Arthur North Sydney",
    "sg:classifiers":[
        {
            "category":"Education",
            "subcategory":"Special Training",
            "type":"Public Place"
        }
    ],
    "sg:phone":"+61 1300 657 282",
    "sg:postcode":"2060",
    "sg:province":"NSW",
    "sg:tags":[
        "development"
    ],
    "wof:name":"New South Wales Small Business Training Co Ltd",
    "wof:placetype":"venue"
},
  "geometry": {"coordinates":[151.21005249000001,-33.8381767273],"type":"Point"}
}