{
  "type": "Feature",
  "properties": {
    "iso:country":"AU",
    "sg:address":"14/ 670 Trouts Rd",
    "sg:city":"Aspley",
    "sg:classifiers":[
        {
            "category":"Personal",
            "type":"Services"
        }
    ],
    "sg:phone":"+61 7 3030 5040",
    "sg:postcode":"4034",
    "sg:province":"QLD",
    "sg:tags":[
        "reducing",
        "treatment",
        "weight"
    ],
    "wof:name":"Herbalife Independent Distributor",
    "wof:placetype":"venue"
},
  "geometry": {"coordinates":[153.003326,-27.364786],"type":"Point"}
}