{
  "type": "Feature",
  "properties": {
    "addr:full":"14/ 670 Trouts Rd Aspley QLD 4034",
    "addr:housenumber":"14 / 670",
    "addr:postcode":"4034",
    "addr:street":"Trouts Rd",
    "iso:country":"AU",
    "sg:address":"14/ 670 Trouts Rd",
    "sg:city":"Aspley",
    "sg:classifiers":[
        {
            "category":"Personal",
            "type":"Services"
        }
    ],
    "sg:phone":"+61 7 3030 5040",
    "sg:postcode":"4034",
    "sg:province":"QLD",
    "sg:tags":[
        "reducing",
        "treatment",
        "weight"
    ],
    "wof:name":"Herbalife Independent Distributor",
    "wof:placetype":"venue"
},
  "geometry": {"coordinates":[153.00332599999999,-27.364786],"type":"Point"}
}