{
  "type": "Feature",
  "properties": {
    "addr:full":"290 Manns Rd Gosford West NSW 2250",
    "addr:housenumber":"290",
    "addr:postcode":"2250",
    "addr:street":"Manns Rd",
    "iso:country":"AU",
    "sg:address":"290 Manns Rd",
    "sg:city":"Gosford West",
    "sg:classifiers":[
        {
            "category":"Retail",
            "subcategory":"Auto Repair",
            "type":"Services"
        }
    ],
    "sg:phone":"+61 2 4323 4098",
    "sg:postcode":"2250",
    "sg:province":"NSW",
    "sg:tags":[
        "clutch",
        "brake"
    ],
    "wof:name":"Davey Mechanics Pty Limited",
    "wof:placetype":"venue"
},
  "geometry": {"coordinates":[151.31939697300001,-33.4245262146],"type":"Point"}
}