{
  "type": "Feature",
  "properties": {
    "addr:full":"15 Landau Crt Taylors Lakes VIC 3038",
    "addr:housenumber":"15",
    "addr:postcode":"3038",
    "addr:street":"Landau Crt",
    "iso:country":"AU",
    "sg:address":"15 Landau Crt",
    "sg:city":"Taylors Lakes",
    "sg:classifiers":[
        {
            "category":"Building & Trades",
            "subcategory":"Cleaning & Sanitation",
            "type":"Services"
        }
    ],
    "sg:phone":"+61 412 377 528",
    "sg:postcode":"3038",
    "sg:province":"VIC",
    "sg:tags":[
        "industrial",
        "commercial",
        "contractor"
    ],
    "wof:name":"Star Cleaning Services",
    "wof:placetype":"venue"
},
  "geometry": {"coordinates":[144.78916899999999,-37.69371],"type":"Point"}
}