{
  "type": "Feature",
  "properties": {
    "iso:country":"AU",
    "sg:address":"12 Chapel Rd",
    "sg:city":"Keysborough",
    "sg:classifiers":[
        {
            "category":"Food & Beverages",
            "subcategory":"Fruits & Vegetables",
            "type":"Retail Goods"
        }
    ],
    "sg:phone":"+61 3 9798 8792",
    "sg:postcode":"3173",
    "sg:province":"VIC",
    "sg:tags":[
        "grower"
    ],
    "wof:name":"Alphonsius Schoormans",
    "wof:placetype":"venue"
},
  "geometry": {"coordinates":[145.16273498499999,-37.9942092896],"type":"Point"}
}