{
  "type": "Feature",
  "properties": {
    "addr:full":"Lvl3/ 20 Council St Camberwell VIC 3124",
    "addr:postcode":"3124",
    "addr:street":"Council St",
    "iso:country":"AU",
    "sg:address":"Lvl3/ 20 Council St",
    "sg:city":"Camberwell",
    "sg:classifiers":[
        {
            "category":"Health Services",
            "subcategory":"Health Practitioner",
            "type":"Services"
        }
    ],
    "sg:phone":"+61 3 9882 5188",
    "sg:postcode":"3124",
    "sg:province":"VIC",
    "sg:tags":[
        "psychologist"
    ],
    "wof:name":"Winney Merril",
    "wof:placetype":"venue"
},
  "geometry": {"coordinates":[145.05413818400001,-37.8303871155],"type":"Point"}
}