{
  "type": "Feature",
  "properties": {
    "addr:full":"76 Park Ave Kotara NSW 2289",
    "addr:housenumber":"76",
    "addr:postcode":"2289",
    "addr:street":"Park Ave",
    "iso:country":"AU",
    "sg:address":"76 Park Ave",
    "sg:city":"Kotara",
    "sg:classifiers":[
        {
            "category":"Professional",
            "subcategory":"Management & Consulting",
            "type":"Services"
        }
    ],
    "sg:phone":"+61 2 4965 5650",
    "sg:postcode":"2289",
    "sg:province":"NSW",
    "sg:tags":[
        "consultant",
        "industrial",
        "relation"
    ],
    "wof:name":"Tyler Industrial Management Consultants Pty Ltd",
    "wof:placetype":"venue"
},
  "geometry": {"coordinates":[151.71107482900001,-32.9405097961],"type":"Point"}
}