{
  "type": "Feature",
  "properties": {
    "iso:country":"AU",
    "sg:address":"Shop 2 170 Martin St",
    "sg:city":"Brighton North",
    "sg:classifiers":[
        {
            "category":"Professional",
            "subcategory":"Accounting & Tax Preparation",
            "type":"Services"
        }
    ],
    "sg:phone":"+61 3 9596 9922",
    "sg:postcode":"3186",
    "sg:province":"VIC",
    "sg:tags":[
        "accountant",
        "auditor"
    ],
    "wof:name":"Chavoly Tom Avrohom Chartered Accountant",
    "wof:placetype":"venue"
},
  "geometry": {"coordinates":[145.00523376500001,-37.8976707458],"type":"Point"}
}