{
  "type": "Feature",
  "properties": {
    "addr:full":"385 Hargreaves St Bendigo VIC 3550",
    "addr:housenumber":"385",
    "addr:postcode":"3550",
    "addr:street":"Hargreaves St",
    "iso:country":"AU",
    "sg:address":"385 Hargreaves St",
    "sg:city":"Bendigo",
    "sg:classifiers":[
        {
            "category":"Banks & Credit Unions",
            "subcategory":"Bank",
            "type":"Services"
        }
    ],
    "sg:phone":"+61 3 5445 2000",
    "sg:postcode":"3550",
    "sg:province":"VIC",
    "sg:tags":[
        "broker",
        "mortgage"
    ],
    "wof:name":"Aussie Home Loans",
    "wof:placetype":"venue"
},
  "geometry": {"coordinates":[144.27813720699999,-36.76171875],"type":"Point"}
}