{
  "type": "Feature",
  "properties": {
    "iso:country":"AU",
    "sg:address":"62 Sanctuary Point Rd",
    "sg:city":"Sanctuary Point",
    "sg:classifiers":[
        {
            "category":"Building & Trades",
            "subcategory":"Plumbing",
            "type":"Services"
        }
    ],
    "sg:phone":"+61 2 4443 0847",
    "sg:postcode":"2540",
    "sg:province":"NSW",
    "sg:tags":[
        "drainers"
    ],
    "wof:name":"Mark Luscombe",
    "wof:placetype":"venue"
},
  "geometry": {"coordinates":[150.63752746599999,-35.1025161743],"type":"Point"}
}