{
  "type": "Feature",
  "properties": {
    "iso:country":"AU",
    "sg:address":"38 Puckle St",
    "sg:city":"Moonee Ponds",
    "sg:classifiers":[
        {
            "category":"Shopping",
            "subcategory":"Clothing, Apparel, & Fashions",
            "type":"Retail Goods"
        }
    ],
    "sg:phone":"+61 3 9370 6421",
    "sg:postcode":"3039",
    "sg:province":"VIC",
    "sg:tags":[
        "lady",
        "wear"
    ],
    "wof:name":"Portmans Consolidated Pty Ltd",
    "wof:placetype":"venue"
},
  "geometry": {"coordinates":[144.92318700000001,-37.766781],"type":"Point"}
}