{
  "type": "Feature",
  "properties": {
    "addr:full":"254 Lakedge Ave Berkeley Vale NSW 2261",
    "addr:housenumber":"254",
    "addr:postcode":"2261",
    "addr:street":"Lakedge Ave",
    "iso:country":"AU",
    "sg:address":"254 Lakedge Ave",
    "sg:city":"Berkeley Vale",
    "sg:classifiers":[
        {
            "category":"Real Estate",
            "subcategory":"Real Estate Agent",
            "type":"Services"
        }
    ],
    "sg:phone":"+61 2 4388 3333",
    "sg:postcode":"2261",
    "sg:province":"NSW",
    "wof:name":"Re/max Coast & Country Properties",
    "wof:placetype":"venue"
},
  "geometry": {"coordinates":[151.441788,-33.349022],"type":"Point"}
}