{
  "type": "Feature",
  "properties": {
    "iso:country":"AU",
    "sg:address":"PO Box 205",
    "sg:city":"Newport Beach",
    "sg:classifiers":[
        {
            "category":"Home & Garden",
            "subcategory":"Building Materials",
            "type":"Retail Goods"
        }
    ],
    "sg:phone":"+61 416 183 686",
    "sg:postcode":"2106",
    "sg:province":"NSW",
    "sg:tags":[
        "lawn",
        "cutting",
        "maintenance"
    ],
    "wof:name":"Five Star Mowing & Trees",
    "wof:placetype":"venue"
},
  "geometry": {"coordinates":[151.32278442399999,-33.6524810791],"type":"Point"}
}