{
  "type": "Feature",
  "properties": {
    "iso:country":"AU",
    "sg:address":"28 Blake St",
    "sg:city":"Rose Bay",
    "sg:classifiers":[
        {
            "category":"Shopping",
            "subcategory":"Musical Instruments",
            "type":"Retail Goods"
        }
    ],
    "sg:phone":"+61 2 9371 8886",
    "sg:postcode":"2029",
    "sg:province":"NSW",
    "sg:tags":[
        "musician",
        "agent"
    ],
    "wof:name":"Luciano Victor",
    "wof:placetype":"venue"
},
  "geometry": {"coordinates":[151.27682495100001,-33.8718719482],"type":"Point"}
}