{
  "type": "Feature",
  "properties": {
    "addr:full":"22 Meadowvale Rd Modbury SA 5092",
    "addr:housenumber":"22",
    "addr:postcode":"5092",
    "addr:street":"Meadowvale Rd",
    "iso:country":"AU",
    "sg:address":"22 Meadowvale Rd",
    "sg:city":"Modbury",
    "sg:classifiers":[
        {
            "category":"Utilities",
            "subcategory":"Water",
            "type":"Services"
        }
    ],
    "sg:phone":"+61 409 679 427",
    "sg:postcode":"5092",
    "sg:province":"SA",
    "sg:tags":[
        "hot",
        "system"
    ],
    "wof:name":"AAA Maintenance Plumbing P/L",
    "wof:placetype":"venue"
},
  "geometry": {"coordinates":[138.69155883799999,-34.8367881775],"type":"Point"}
}