{
  "type": "Feature",
  "properties": {
    "addr:full":"5 Albert St Stanley TAS 7331",
    "addr:housenumber":"5",
    "addr:postcode":"7331",
    "addr:street":"Albert St",
    "iso:country":"AU",
    "sg:address":"5 Albert St",
    "sg:city":"Stanley",
    "sg:classifiers":[
        {
            "category":"Farming",
            "subcategory":"Fish & Marine Products",
            "type":"Manufacturing & Wholesale Goods"
        }
    ],
    "sg:phone":"+61 3 6458 1160",
    "sg:postcode":"7331",
    "sg:province":"TAS",
    "sg:tags":[
        "fisherman"
    ],
    "wof:name":"Temma Fisheries Pty Ltd",
    "wof:placetype":"venue"
},
  "geometry": {"coordinates":[145.289963,-40.760056],"type":"Point"}
}