{
  "type": "Feature",
  "properties": {
    "iso:country":"AU",
    "sg:address":"1-14 Raleigh St",
    "sg:city":"Cardwell",
    "sg:classifiers":[
        {
            "category":"Professional",
            "subcategory":"Art Services",
            "type":"Services"
        }
    ],
    "sg:phone":"+61 7 4066 8414",
    "sg:postcode":"4849",
    "sg:province":"QLD",
    "sg:tags":[
        "interior",
        "decorator"
    ],
    "wof:name":"Colour Harmony",
    "wof:placetype":"venue"
},
  "geometry": {"coordinates":[146.017014,-18.255812],"type":"Point"}
}