{
  "type": "Feature",
  "properties": {
    "iso:country":"AU",
    "sg:address":"27 Shoalhaven Drv",
    "sg:city":"Woy Woy",
    "sg:classifiers":[
        {
            "category":"Recreation",
            "subcategory":"Boat Charter",
            "type":"Entertainment"
        }
    ],
    "sg:phone":"+61 2 4341 8038",
    "sg:postcode":"2256",
    "sg:province":"NSW",
    "sg:tags":[
        "canopy",
        "motor"
    ],
    "wof:name":"Peninsula Motor Trimming & Upholstery",
    "wof:placetype":"venue"
},
  "geometry": {"coordinates":[151.302490234,-33.5016441345],"type":"Point"}
}