{
  "type": "Feature",
  "properties": {
    "addr:full":"9 George Crt Greensborough VIC 3088",
    "addr:housenumber":"9",
    "addr:postcode":"3088",
    "addr:street":"George Crt",
    "iso:country":"AU",
    "sg:address":"9 George Crt",
    "sg:city":"Greensborough",
    "sg:classifiers":[
        {
            "category":"Retail",
            "subcategory":"Auto Repair",
            "type":"Services"
        }
    ],
    "sg:phone":"+61 3 9432 7500",
    "sg:postcode":"3088",
    "sg:province":"VIC",
    "sg:tags":[
        "testing",
        "inspection",
        "motor",
        "vehicle"
    ],
    "wof:name":"Niss Serv",
    "wof:placetype":"venue"
},
  "geometry": {"coordinates":[145.112915039,-37.7100410461],"type":"Point"}
}