{
  "type": "Feature",
  "properties": {
    "addr:full":"4 Caston Crt Birkdale QLD 4159",
    "addr:housenumber":"4",
    "addr:postcode":"4159",
    "addr:street":"Caston Crt",
    "iso:country":"AU",
    "sg:address":"4 Caston Crt",
    "sg:city":"Birkdale",
    "sg:classifiers":[
        {
            "category":"Professional",
            "subcategory":"Printing & Photocopies",
            "type":"Services"
        }
    ],
    "sg:phone":"+61 7 3822 6011",
    "sg:postcode":"4159",
    "sg:province":"QLD",
    "sg:tags":[
        "photocopier"
    ],
    "wof:name":"AGW Copiers",
    "wof:placetype":"venue"
},
  "geometry": {"coordinates":[153.19679260300001,-27.4964771271],"type":"Point"}
}