{
  "type": "Feature",
  "properties": {
    "addr:full":"37- 39 Separation St Geelong North VIC 3215",
    "addr:housenumber":"39",
    "addr:postcode":"3215",
    "addr:street":"Separation St",
    "iso:country":"AU",
    "sg:address":"37- 39 Separation St",
    "sg:city":"Geelong North",
    "sg:classifiers":[
        {
            "category":"Shopping",
            "subcategory":"Party Supplies",
            "type":"Retail Goods"
        }
    ],
    "sg:phone":"+61 3 5277 2100",
    "sg:postcode":"3215",
    "sg:province":"VIC",
    "sg:tags":[
        "children's"
    ],
    "wof:name":"Crazy Critters",
    "wof:placetype":"venue"
},
  "geometry": {"coordinates":[144.345977783,-38.1111869812],"type":"Point"}
}