{
  "type": "Feature",
  "properties": {
    "addr:full":"90 Bradshaw St Essendon VIC 3040",
    "addr:housenumber":"90",
    "addr:postcode":"3040",
    "addr:street":"Bradshaw St",
    "iso:country":"AU",
    "sg:address":"90 Bradshaw St",
    "sg:city":"Essendon",
    "sg:classifiers":[
        {
            "category":"Social Services",
            "subcategory":"Retirement Home",
            "type":"Services"
        }
    ],
    "sg:phone":"+61 3 9379 2580",
    "sg:postcode":"3040",
    "sg:province":"VIC",
    "sg:tags":[
        "accommodation",
        "special"
    ],
    "wof:name":"Pineview Lodge",
    "wof:placetype":"venue"
},
  "geometry": {"coordinates":[144.89540100100001,-37.7410354614],"type":"Point"}
}