{
  "type": "Feature",
  "properties": {
    "addr:full":"Cnr Sturt Hwy & Pioneer Ave Gumly Gumly NSW 2652",
    "addr:postcode":"2652",
    "addr:street":"Sturt Hwy & Pioneer Ave",
    "iso:country":"AU",
    "sg:address":"Cnr Sturt Hwy & Pioneer Ave",
    "sg:city":"Gumly Gumly",
    "sg:classifiers":[
        {
            "category":"Cafe",
            "type":"Food & Drink"
        }
    ],
    "sg:phone":"+61 2 6922 8844",
    "sg:postcode":"2652",
    "sg:province":"NSW",
    "wof:name":"At The Farm",
    "wof:placetype":"venue"
},
  "geometry": {"coordinates":[147.43901062,-35.1304168701],"type":"Point"}
}