{
  "type": "Feature",
  "properties": {
    "addr:full":"Cnr City View & Boundary Rds Pennant Hills NSW 2120",
    "addr:postcode":"2120",
    "iso:country":"AU",
    "sg:address":"Cnr City View & Boundary Rds",
    "sg:city":"Pennant Hills",
    "sg:classifiers":[
        {
            "category":"Retail",
            "subcategory":"Event Space",
            "type":"Services"
        }
    ],
    "sg:phone":"+61 2 9980 6999",
    "sg:postcode":"2120",
    "sg:province":"NSW",
    "sg:tags":[
        "venue",
        "reception",
        "wedding"
    ],
    "wof:name":"The Chifley On City View",
    "wof:placetype":"venue"
},
  "geometry": {"coordinates":[151.06869506800001,-33.7393035889],"type":"Point"}
}