{
  "type": "Feature",
  "properties": {
    "iso:country":"AU",
    "sg:address":"126 Sandy Creek Rd",
    "sg:city":"Yatala",
    "sg:classifiers":[
        {
            "category":"Building & Trades",
            "subcategory":"Cleaning & Sanitation",
            "type":"Services"
        }
    ],
    "sg:phone":"+61 7 3382 7997",
    "sg:postcode":"4207",
    "sg:province":"QLD",
    "sg:tags":[
        "grease",
        "trap"
    ],
    "sg:website":"http://www.specialisedwasteservices.com.au",
    "wof:name":"Specialised Waste Services",
    "wof:placetype":"venue"
},
  "geometry": {"coordinates":[153.22137451200001,-27.7605228424],"type":"Point"}
}