{
  "type": "Feature",
  "properties": {
    "addr:full":"39- 45 Parap Rd Parap NT 0820",
    "addr:housenumber":"45",
    "addr:postcode":"nt 0820",
    "addr:street":"Parap Rd",
    "iso:country":"AU",
    "sg:address":"39- 45 Parap Rd",
    "sg:city":"Parap",
    "sg:classifiers":[
        {
            "category":"Travel",
            "subcategory":"Hotels & Motels",
            "type":"Entertainment"
        }
    ],
    "sg:phone":"+61 8 8943 0500",
    "sg:postcode":"0820",
    "sg:province":"NT",
    "wof:name":"Parap Village Apartments",
    "wof:placetype":"venue"
},
  "geometry": {"coordinates":[130.843185425,-12.4306669235],"type":"Point"}
}