{
  "type": "Feature",
  "properties": {
    "iso:country":"AU",
    "sg:address":"7 Kennedy Crt",
    "sg:city":"Moe",
    "sg:classifiers":[
        {
            "category":"Education",
            "subcategory":"Music School",
            "type":"Public Place"
        }
    ],
    "sg:phone":"+61 412 415 503",
    "sg:postcode":"3825",
    "sg:province":"VIC",
    "sg:tags":[
        "choir",
        "bands",
        "orchestra"
    ],
    "wof:name":"Cats in the Kitchen",
    "wof:placetype":"venue"
},
  "geometry": {"coordinates":[146.284836,-38.180023],"type":"Point"}
}