{
  "type": "Feature",
  "properties": {
    "iso:country":"AU",
    "sg:address":"368-372 Lawrence Hargrave Drv",
    "sg:city":"Thirroul",
    "sg:classifiers":[
        {
            "category":"Personal",
            "subcategory":"Beauty Salon",
            "type":"Services"
        }
    ],
    "sg:phone":"+61 2 4268 6299",
    "sg:postcode":"2515",
    "sg:province":"NSW",
    "sg:tags":[
        "hairdresser"
    ],
    "wof:name":"Chelsea Hair Body Face",
    "wof:placetype":"venue"
},
  "geometry": {"coordinates":[150.91803,-34.317211],"type":"Point"}
}