{
  "type": "Feature",
  "properties": {
    "addr:full":"PO Box 1212 Bowral NSW 2576",
    "addr:postcode":"2576",
    "iso:country":"AU",
    "sg:address":"PO Box 1212",
    "sg:city":"Bowral",
    "sg:classifiers":[
        {
            "category":"Professional",
            "subcategory":"Art Services",
            "type":"Services"
        }
    ],
    "sg:phone":"+61 418 207 708",
    "sg:postcode":"2576",
    "sg:province":"NSW",
    "sg:tags":[
        "decorator",
        "painter"
    ],
    "wof:name":"Father & Son",
    "wof:placetype":"venue"
},
  "geometry": {"coordinates":[150.385894775,-34.4550590515],"type":"Point"}
}