{
  "type": "Feature",
  "properties": {
    "addr:full":"28 Oakwood Ave Dandenong North VIC 3175",
    "addr:housenumber":"28",
    "addr:postcode":"3175",
    "addr:street":"Oakwood Ave",
    "iso:country":"AU",
    "sg:address":"28 Oakwood Ave",
    "sg:city":"Dandenong North",
    "sg:classifiers":[
        {
            "category":"Transit Center",
            "subcategory":"Freight",
            "type":"Transportation"
        }
    ],
    "sg:phone":"+61 3 9625 1808",
    "sg:postcode":"3175",
    "sg:province":"VIC",
    "sg:tags":[
        "transfer",
        "emblem"
    ],
    "wof:name":"Pro Print",
    "wof:placetype":"venue"
},
  "geometry": {"coordinates":[145.20254516599999,-37.9642982483],"type":"Point"}
}