{
  "type": "Feature",
  "properties": {
    "iso:country":"AU",
    "sg:address":"6 Centaurus St",
    "sg:city":"Giralang",
    "sg:classifiers":[
        {
            "category":"Building & Trades",
            "subcategory":"Landscaping Services",
            "type":"Services"
        }
    ],
    "sg:phone":"+61 414 413 383",
    "sg:postcode":"2617",
    "sg:province":"ACT",
    "sg:tags":[
        "designer",
        "landscape",
        "contractor"
    ],
    "wof:name":"Travis Morse",
    "wof:placetype":"venue"
},
  "geometry": {"coordinates":[149.09400939899999,-35.2104148865],"type":"Point"}
}