{
  "type": "Feature",
  "properties": {
    "iso:country":"AU",
    "sg:address":"13 Brighton Rd",
    "sg:city":"Glenelg",
    "sg:classifiers":[
        {
            "category":"Banks & Credit Unions",
            "subcategory":"Investment Brokerage",
            "type":"Services"
        }
    ],
    "sg:phone":"+61 8 8295 4777",
    "sg:postcode":"5045",
    "sg:province":"SA",
    "sg:tags":[
        "finance",
        "broker"
    ],
    "wof:name":"Freeman Peter Finance",
    "wof:placetype":"venue"
},
  "geometry": {"coordinates":[138.520035,-34.979698],"type":"Point"}
}