{
  "type": "Feature",
  "properties": {
    "addr:full":"Cnr Spence & Bunda Sts Cairns QLD 4870",
    "addr:postcode":"4870",
    "addr:street":"Cnr",
    "iso:country":"AU",
    "sg:address":"Cnr Spence & Bunda Sts",
    "sg:city":"Cairns",
    "sg:classifiers":[
        {
            "category":"Insurance",
            "subcategory":"Insurance Agent",
            "type":"Services"
        }
    ],
    "sg:phone":"+61 7 4033 5235",
    "sg:postcode":"4870",
    "sg:province":"QLD",
    "wof:name":"Alan Jenkins",
    "wof:placetype":"venue"
},
  "geometry": {"coordinates":[145.75108337399999,-16.9450416565],"type":"Point"}
}