{
  "type": "Feature",
  "properties": {
    "addr:full":"12 McGill St Lewisham NSW 2049",
    "addr:housenumber":"12",
    "addr:postcode":"2049",
    "addr:street":"Mcgill St",
    "iso:country":"AU",
    "sg:address":"12 McGill St",
    "sg:city":"Lewisham",
    "sg:classifiers":[
        {
            "category":"Wholesale",
            "subcategory":"Machinery & Supplies",
            "type":"Manufacturing & Wholesale Goods"
        }
    ],
    "sg:phone":"+61 2 9564 0508",
    "sg:postcode":"2049",
    "sg:province":"NSW",
    "sg:tags":[
        "instrument",
        "scientific"
    ],
    "wof:name":"AMLAB Technologies",
    "wof:placetype":"venue"
},
  "geometry": {"coordinates":[151.14372299999999,-33.894577],"type":"Point"}
}