{
  "type": "Feature",
  "properties": {
    "addr:full":"36 Killarney Drv Killarney Heights NSW 2087",
    "addr:housenumber":"36",
    "addr:postcode":"2087",
    "addr:street":"Killarney Drv",
    "iso:country":"AU",
    "sg:address":"36 Killarney Drv",
    "sg:city":"Killarney Heights",
    "sg:classifiers":[
        {
            "category":"Professional",
            "type":"Services"
        }
    ],
    "sg:phone":"+61 2 9453 4269",
    "sg:postcode":"2087",
    "sg:province":"NSW",
    "sg:tags":[
        "message",
        "answering",
        "telephone"
    ],
    "wof:name":"Psitek (Australia) Pty Ltd",
    "wof:placetype":"venue"
},
  "geometry": {"coordinates":[151.21487426799999,-33.7737426758],"type":"Point"}
}