{
  "type": "Feature",
  "properties": {
    "iso:country":"AU",
    "sg:address":"18 Sturway St",
    "sg:city":"Ermington",
    "sg:classifiers":[
        {
            "category":"Building & Trades",
            "subcategory":"Construction",
            "type":"Services"
        }
    ],
    "sg:phone":"+61 415 255 255",
    "sg:postcode":"2115",
    "sg:province":"NSW",
    "sg:tags":[
        "earth",
        "excavating",
        "moving",
        "contractor"
    ],
    "wof:name":"Amigos Excavation & Demolition Pty Ltd",
    "wof:placetype":"venue"
},
  "geometry": {"coordinates":[151.05467224099999,-33.8074455261],"type":"Point"}
}