{
  "type": "Feature",
  "properties": {
    "addr:full":"10 Elphin Rd Launceston TAS 7250",
    "addr:housenumber":"10",
    "addr:postcode":"7250",
    "addr:street":"Elphin Rd",
    "iso:country":"AU",
    "sg:address":"10 Elphin Rd",
    "sg:city":"Launceston",
    "sg:classifiers":[
        {
            "category":"Health Services",
            "subcategory":"Medical Lab",
            "type":"Services"
        }
    ],
    "sg:phone":"+61 3 6334 5640",
    "sg:postcode":"7250",
    "sg:province":"TAS",
    "sg:tags":[
        "laboratory",
        "dental"
    ],
    "wof:name":"Orthodontic Laboratories Pty Ltd",
    "wof:placetype":"venue"
},
  "geometry": {"coordinates":[147.14683532699999,-41.4317016602],"type":"Point"}
}