{
  "type": "Feature",
  "properties": {
    "iso:country":"AU",
    "sg:address":"2 / 73 Lawrence Drv",
    "sg:city":"Nerang",
    "sg:classifiers":[
        {
            "category":"Home & Garden",
            "subcategory":"Carpets & Floor Coverings",
            "type":"Retail Goods"
        }
    ],
    "sg:phone":"+61 7 5596 0766",
    "sg:postcode":"4211",
    "sg:province":"QLD",
    "sg:tags":[
        "tile",
        "wall"
    ],
    "wof:name":"Cymbal Enterprises Pty Ltd",
    "wof:placetype":"venue"
},
  "geometry": {"coordinates":[153.346435547,-27.9979324341],"type":"Point"}
}