{
  "type": "Feature",
  "properties": {
    "addr:full":"6 David Muir St Slade Point QLD 4740",
    "addr:housenumber":"6",
    "addr:postcode":"4740",
    "addr:street":"David Muir St",
    "iso:country":"AU",
    "sg:address":"6 David Muir St",
    "sg:city":"Slade Point",
    "sg:classifiers":[
        {
            "category":"Building & Trades",
            "subcategory":"Construction",
            "type":"Services"
        }
    ],
    "sg:phone":"+61 7 4955 1155",
    "sg:postcode":"4740",
    "sg:province":"QLD",
    "sg:tags":[
        "concrete",
        "paving"
    ],
    "wof:name":"Boral",
    "wof:placetype":"venue"
},
  "geometry": {"coordinates":[149.21534700000001,-21.089565],"type":"Point"}
}