{
  "type": "Feature",
  "properties": {
    "addr:full":"1 Main St Warooka SA 5577",
    "addr:housenumber":"1",
    "addr:postcode":"5577",
    "addr:street":"Main St",
    "iso:country":"AU",
    "sg:address":"1 Main St",
    "sg:city":"Warooka",
    "sg:classifiers":[
        {
            "category":"Professional",
            "subcategory":"Business Services",
            "type":"Services"
        }
    ],
    "sg:phone":"+61 8 8854 5233",
    "sg:postcode":"5577",
    "sg:province":"SA",
    "sg:tags":[
        "broker"
    ],
    "wof:name":"Regional Small Business Network Pty Ltd",
    "wof:placetype":"venue"
},
  "geometry": {"coordinates":[137.407302856,-34.9945259094],"type":"Point"}
}