{
  "type": "Feature",
  "properties": {
    "addr:full":"47 Caloundra Rd Caloundra QLD 4551",
    "addr:housenumber":"47",
    "addr:postcode":"4551",
    "addr:street":"Caloundra Rd",
    "iso:country":"AU",
    "sg:address":"47 Caloundra Rd",
    "sg:city":"Caloundra",
    "sg:classifiers":[
        {
            "category":"Wholesale",
            "subcategory":"Electrical",
            "type":"Manufacturing & Wholesale Goods"
        }
    ],
    "sg:phone":"+61 7 5436 4000",
    "sg:postcode":"4551",
    "sg:province":"QLD",
    "sg:tags":[
        "wholesaler"
    ],
    "wof:name":"Ideal Electrical Suppliers",
    "wof:placetype":"venue"
},
  "geometry": {"coordinates":[153.10838317899999,-26.7956047058],"type":"Point"}
}