{
  "type": "Feature",
  "properties": {
    "iso:country":"AU",
    "sg:address":"21 Harlington Ave",
    "sg:city":"Eltham",
    "sg:classifiers":[
        {
            "category":"Utilities",
            "subcategory":"Water",
            "type":"Services"
        }
    ],
    "sg:phone":"+61 3 9439 2087",
    "sg:postcode":"3095",
    "sg:province":"VIC",
    "sg:tags":[
        "hot",
        "system"
    ],
    "wof:name":"Viewton Plumbing Pty Ltd",
    "wof:placetype":"venue"
},
  "geometry": {"coordinates":[145.15592956500001,-37.7196769714],"type":"Point"}
}