{
  "type": "Feature",
  "properties": {
    "iso:country":"AU",
    "sg:address":"149 Pacific Hwy",
    "sg:city":"Charlestown",
    "sg:classifiers":[
        {
            "category":"Health Services",
            "subcategory":"Doctor",
            "type":"Services"
        }
    ],
    "sg:phone":"+61 2 4943 9777",
    "sg:postcode":"2290",
    "sg:province":"NSW",
    "sg:tags":[
        "medical",
        "practitioner"
    ],
    "wof:name":"Cooke Peter",
    "wof:placetype":"venue"
},
  "geometry": {"coordinates":[151.69615173299999,-32.9631500244],"type":"Point"}
}