{
  "type": "Feature",
  "properties": {
    "iso:country":"AU",
    "sg:address":"190 Francis St",
    "sg:city":"Belmont",
    "sg:classifiers":[
        {
            "category":"Building & Trades",
            "subcategory":"Plumbing",
            "type":"Services"
        }
    ],
    "sg:phone":"+61 3 5261 4322",
    "sg:postcode":"3216",
    "sg:province":"VIC",
    "sg:tags":[
        "plumber",
        "gasfitters"
    ],
    "wof:name":"All Areas Affordable Plumbing",
    "wof:placetype":"venue"
},
  "geometry": {"coordinates":[144.346557617,-38.1872253418],"type":"Point"}
}