{
  "type": "Feature",
  "properties": {
    "iso:country":"AU",
    "sg:address":"246 Great Western Hwy",
    "sg:city":"Blackheath",
    "sg:classifiers":[
        {
            "category":"Cafe",
            "type":"Food & Drink"
        }
    ],
    "sg:phone":"+61 2 4787 7269",
    "sg:postcode":"2785",
    "sg:province":"NSW",
    "wof:name":"Banksia Cafe",
    "wof:placetype":"venue"
},
  "geometry": {"coordinates":[150.284622192,-33.6337013245],"type":"Point"}
}