{
  "type": "Feature",
  "properties": {
    "addr:full":"Lvl 7 Suite 7c Fred McKay House Inland Drv Tugun QLD 4224",
    "addr:postcode":"4224",
    "addr:street":"Inland Drv",
    "iso:country":"AU",
    "sg:address":"Lvl 7 Suite 7c Fred McKay House Inland Drv",
    "sg:city":"Tugun",
    "sg:classifiers":[
        {
            "category":"Health Services",
            "subcategory":"Doctor",
            "type":"Services"
        }
    ],
    "sg:phone":"+61 7 5598 0644",
    "sg:postcode":"4224",
    "sg:province":"QLD",
    "sg:tags":[
        "medical",
        "practitioner"
    ],
    "wof:name":"Ghusn Danielle Dr",
    "wof:placetype":"venue"
},
  "geometry": {"coordinates":[153.49212646500001,-28.1418399811],"type":"Point"}
}