{
  "type": "Feature",
  "properties": {
    "addr:full":"10 Dixon Crt Greensborough VIC 3088",
    "addr:housenumber":"10",
    "addr:postcode":"3088",
    "addr:street":"Dixon Crt",
    "iso:country":"AU",
    "sg:address":"10 Dixon Crt",
    "sg:city":"Greensborough",
    "sg:classifiers":[
        {
            "category":"Building & Trades",
            "subcategory":"Construction",
            "type":"Services"
        }
    ],
    "sg:phone":"+61 3 9432 0242",
    "sg:postcode":"3088",
    "sg:province":"VIC",
    "sg:tags":[
        "plasterboard",
        "plasterer",
        "fixer"
    ],
    "wof:name":"Palmer Brian E",
    "wof:placetype":"venue"
},
  "geometry": {"coordinates":[145.11773681599999,-37.7011032104],"type":"Point"}
}