{
  "type": "Feature",
  "properties": {
    "addr:full":"22 Miller Ave Bexley North NSW 2207",
    "addr:housenumber":"22",
    "addr:postcode":"2207",
    "addr:street":"Miller Ave",
    "iso:country":"AU",
    "sg:address":"22 Miller Ave",
    "sg:city":"Bexley North",
    "sg:classifiers":[
        {
            "category":"Building & Trades",
            "subcategory":"Construction",
            "type":"Services"
        }
    ],
    "sg:phone":"+61 2 9758 6098",
    "sg:postcode":"2207",
    "sg:province":"NSW",
    "sg:tags":[
        "rendering",
        "cement"
    ],
    "wof:name":"No Fuss Cement",
    "wof:placetype":"venue"
},
  "geometry": {"coordinates":[151.11669900000001,-33.942219],"type":"Point"}
}