{
  "type": "Feature",
  "properties": {
    "addr:full":"36 Excalibur Ave Castle Hill NSW 2154",
    "addr:housenumber":"36",
    "addr:postcode":"2154",
    "addr:street":"Excalibur Ave",
    "iso:country":"AU",
    "sg:address":"36 Excalibur Ave",
    "sg:city":"Castle Hill",
    "sg:classifiers":[
        {
            "category":"Health Services",
            "subcategory":"Doctor",
            "type":"Services"
        }
    ],
    "sg:phone":"+61 2 9680 2560",
    "sg:postcode":"2154",
    "sg:province":"NSW",
    "sg:tags":[
        "medical",
        "practitioner"
    ],
    "wof:name":"Medical Consumers Association",
    "wof:placetype":"venue"
},
  "geometry": {"coordinates":[150.99171447800001,-33.7105331421],"type":"Point"}
}