{
  "type": "Feature",
  "properties": {
    "iso:country":"AU",
    "sg:address":"Thangool Rd",
    "sg:city":"Thangool",
    "sg:classifiers":[
        {
            "category":"Autos & Motor Vehicles",
            "subcategory":"Fuel & Gas Station",
            "type":"Retail Goods"
        }
    ],
    "sg:phone":"+61 7 4995 8311",
    "sg:postcode":"4716",
    "sg:province":"QLD",
    "wof:name":"BP Australia Limited",
    "wof:placetype":"venue"
},
  "geometry": {"coordinates":[150.574295044,-24.4864597321],"type":"Point"}
}