{
  "type": "Feature",
  "properties": {
    "addr:full":"19 Rayleigh Ave Highbury SA 5089",
    "addr:housenumber":"19",
    "addr:postcode":"5089",
    "addr:street":"Rayleigh Ave",
    "iso:country":"AU",
    "sg:address":"19 Rayleigh Ave",
    "sg:city":"Highbury",
    "sg:classifiers":[
        {
            "category":"Professional",
            "subcategory":"Art Services",
            "type":"Services"
        }
    ],
    "sg:phone":"+61 8 8396 2872",
    "sg:postcode":"5089",
    "sg:province":"SA",
    "sg:tags":[
        "decorator",
        "painter"
    ],
    "wof:name":"Coccia G",
    "wof:placetype":"venue"
},
  "geometry": {"coordinates":[138.69042968799999,-34.8579864502],"type":"Point"}
}