{
  "type": "Feature",
  "properties": {
    "iso:country":"AU",
    "sg:address":"25- 29 Water St",
    "sg:city":"Strathfield South",
    "sg:classifiers":[
        {
            "category":"Building & Trades",
            "subcategory":"Equipment Rental",
            "type":"Services"
        }
    ],
    "sg:phone":"+61 2 9642 7811",
    "sg:postcode":"2136",
    "sg:province":"NSW",
    "sg:tags":[
        "party",
        "hire"
    ],
    "sg:website":"http://www.hamiltonshospitality.com.au",
    "wof:name":"Hamiltons Hospitality",
    "wof:placetype":"venue"
},
  "geometry": {"coordinates":[151.08270263700001,-33.8981513977],"type":"Point"}
}