{
  "type": "Feature",
  "properties": {
    "iso:country":"AU",
    "sg:address":"9- 11 Spinnaker Drv",
    "sg:city":"Sandstone Point",
    "sg:classifiers":[
        {
            "category":"Autos & Motor Vehicles",
            "subcategory":"Motorcycle Sales",
            "type":"Retail Goods"
        }
    ],
    "sg:phone":"+61 7 5497 6733",
    "sg:postcode":"4511",
    "sg:province":"QLD",
    "sg:tags":[
        "outboard"
    ],
    "wof:name":"Spinnaker Sound Marine Workshop",
    "wof:placetype":"venue"
},
  "geometry": {"coordinates":[153.1362,-27.071457],"type":"Point"}
}