{
  "type": "Feature",
  "properties": {
    "iso:country":"AU",
    "sg:address":"4 Ellendale St",
    "sg:city":"Balwyn North",
    "sg:classifiers":[
        {
            "category":"Education",
            "subcategory":"Special Training",
            "type":"Public Place"
        }
    ],
    "sg:phone":"+61 3 9816 3287",
    "sg:postcode":"3104",
    "sg:province":"VIC",
    "sg:tags":[
        "tuition-educational"
    ],
    "wof:name":"Maths Know-How",
    "wof:placetype":"venue"
},
  "geometry": {"coordinates":[145.090942383,-37.7899360657],"type":"Point"}
}