{
  "type": "Feature",
  "properties": {
    "addr:full":"Shop 3, 735- 755 Fifteenth St Mildura VIC 3500",
    "addr:housenumber":"shop 3",
    "addr:postcode":"735 755;3500",
    "addr:street":"Fifteenth St",
    "iso:country":"AU",
    "sg:address":"Shop 3, 735- 755 Fifteenth St",
    "sg:city":"Mildura",
    "sg:classifiers":[
        {
            "category":"Home & Garden",
            "subcategory":"Carpets & Floor Coverings",
            "type":"Retail Goods"
        }
    ],
    "sg:phone":"+61 3 5021 1116",
    "sg:postcode":"3500",
    "sg:province":"VIC",
    "sg:tags":[
        "flooring",
        "parquet"
    ],
    "wof:name":"Max Millers Carpet Choice",
    "wof:placetype":"venue"
},
  "geometry": {"coordinates":[142.144134522,-34.2127799988],"type":"Point"}
}