{
  "type": "Feature",
  "properties": {
    "addr:full":"56 Church St Hawthorn VIC 3122",
    "addr:housenumber":"56",
    "addr:postcode":"3122",
    "addr:street":"Church St",
    "iso:country":"AU",
    "sg:address":"56 Church St",
    "sg:city":"Hawthorn",
    "sg:classifiers":[
        {
            "category":"Health Services",
            "subcategory":"Doctor",
            "type":"Services"
        }
    ],
    "sg:phone":"+61 3 9819 5077",
    "sg:postcode":"3122",
    "sg:province":"VIC",
    "sg:tags":[
        "medical",
        "practitioner"
    ],
    "wof:name":"Wood J Dr",
    "wof:placetype":"venue"
},
  "geometry": {"coordinates":[145.02151489299999,-37.8148956299],"type":"Point"}
}