{
  "type": "Feature",
  "properties": {
    "addr:full":"Curio Crt Tamborine Mountain QLD 4272",
    "addr:postcode":"4272",
    "addr:street":"Curio",
    "iso:country":"AU",
    "sg:address":"Curio Crt",
    "sg:city":"Tamborine Mountain",
    "sg:classifiers":[
        {
            "category":"Building & Trades",
            "subcategory":"Construction",
            "type":"Services"
        }
    ],
    "sg:phone":"+61 402 012 034",
    "sg:postcode":"4272",
    "sg:province":"QLD",
    "sg:tags":[
        "waterproofing",
        "contractor"
    ],
    "wof:name":"Tamborine Joint Sealing",
    "wof:placetype":"venue"
},
  "geometry": {"coordinates":[153.184616089,-27.9589214325],"type":"Point"}
}