{
  "type": "Feature",
  "properties": {
    "addr:full":"Unit 6/ 35 Cooper Rd Jandakot WA 6164",
    "addr:housenumber":"35",
    "addr:postcode":"6164",
    "addr:street":"Cooper Rd",
    "iso:country":"AU",
    "sg:address":"Unit 6/ 35 Cooper Rd",
    "sg:city":"Jandakot",
    "sg:classifiers":[
        {
            "category":"Manufacturing",
            "subcategory":"Metals",
            "type":"Manufacturing & Wholesale Goods"
        }
    ],
    "sg:phone":"+61 8 9417 7765",
    "sg:postcode":"6164",
    "sg:province":"WA",
    "sg:tags":[
        "steel",
        "fabricator",
        "mfrs"
    ],
    "wof:name":"Barker Metal Working Services",
    "wof:placetype":"venue"
},
  "geometry": {"coordinates":[115.845596,-32.124748],"type":"Point"}
}