{
  "type": "Feature",
  "properties": {
    "iso:country":"AU",
    "sg:address":"2/ 104 Gympie Rd",
    "sg:city":"Strathpine",
    "sg:classifiers":[
        {
            "category":"Professional",
            "subcategory":"Art Services",
            "type":"Services"
        }
    ],
    "sg:phone":"+61 7 3881 3441",
    "sg:postcode":"4500",
    "sg:province":"QLD",
    "sg:tags":[
        "picture",
        "frame",
        "framing"
    ],
    "sg:website":"http://www.directframing.com.au",
    "wof:name":"Direct Framing",
    "wof:placetype":"venue"
},
  "geometry": {"coordinates":[152.98826599099999,-27.3018550873],"type":"Point"}
}