{
  "type": "Feature",
  "properties": {
    "iso:country":"AU",
    "sg:address":"Suite 1, 1st Floor , 28 Burwood Rd",
    "sg:city":"Burwood",
    "sg:classifiers":[
        {
            "category":"Health Services",
            "subcategory":"Dentist",
            "type":"Services"
        }
    ],
    "sg:phone":"+61 2 9747 6835",
    "sg:postcode":"2134",
    "sg:province":"NSW",
    "wof:name":"Gomez Roger M",
    "wof:placetype":"venue"
},
  "geometry": {"coordinates":[151.10516357399999,-33.8706283569],"type":"Point"}
}