{
  "type": "Feature",
  "properties": {
    "addr:full":"PO Box 18 Reynella SA 5161",
    "addr:postcode":"5161",
    "iso:country":"AU",
    "sg:address":"PO Box 18",
    "sg:city":"Reynella",
    "sg:classifiers":[
        {
            "category":"Professional",
            "subcategory":"Detective & Security Services",
            "type":"Services"
        }
    ],
    "sg:phone":"+61 417 885 031",
    "sg:postcode":"5161",
    "sg:province":"SA",
    "sg:tags":[
        "investigator"
    ],
    "wof:name":"Regency Investigations",
    "wof:placetype":"venue"
},
  "geometry": {"coordinates":[138.531784058,-35.1002388],"type":"Point"}
}