{
  "type": "Feature",
  "properties": {
    "iso:country":"AU",
    "sg:address":"Lot 8 One Tree Hill Rd",
    "sg:city":"Golden Grove",
    "sg:classifiers":[
        {
            "category":"Building & Trades",
            "subcategory":"Construction",
            "type":"Services"
        }
    ],
    "sg:phone":"+61 413 118 688",
    "sg:postcode":"5125",
    "sg:province":"SA",
    "sg:tags":[
        "earth",
        "excavating",
        "moving",
        "contractor"
    ],
    "wof:name":"A & K Ricci Earthmovers",
    "wof:placetype":"venue"
},
  "geometry": {"coordinates":[138.728256,-34.776115],"type":"Point"}
}