{
  "type": "Feature",
  "properties": {
    "addr:full":"20 Perwilllowen Rd Nambour QLD 4560",
    "addr:housenumber":"20",
    "addr:postcode":"4560",
    "addr:street":"Perwilllowen Rd",
    "iso:country":"AU",
    "sg:address":"20 Perwilllowen Rd",
    "sg:city":"Nambour",
    "sg:classifiers":[
        {
            "category":"Military Area",
            "subcategory":"Army Base",
            "type":"Public Place"
        }
    ],
    "sg:phone":"+61 7 5476 1644",
    "sg:postcode":"4560",
    "sg:province":"QLD",
    "sg:tags":[
        "wholesaler",
        "clutch",
        "brake",
        "mfrs",
        "equipment"
    ],
    "wof:name":"Car Bitz & Accessories",
    "wof:placetype":"venue"
},
  "geometry": {"coordinates":[152.95376586899999,-26.6316719055],"type":"Point"}
}