{
  "type": "Feature",
  "properties": {
    "addr:full":"60 Unley Rd Unley SA 5061",
    "addr:housenumber":"60",
    "addr:postcode":"5061",
    "addr:street":"Unley Rd",
    "iso:country":"AU",
    "sg:address":"60 Unley Rd",
    "sg:city":"Unley",
    "sg:classifiers":[
        {
            "category":"Manufacturing",
            "subcategory":"Food",
            "type":"Manufacturing & Wholesale Goods"
        }
    ],
    "sg:phone":"+61 8 8272 2624",
    "sg:postcode":"5061",
    "sg:province":"SA",
    "sg:tags":[
        "function",
        "catering"
    ],
    "wof:name":"The Snake Charmer",
    "wof:placetype":"venue"
},
  "geometry": {"coordinates":[138.60812377900001,-34.9563102722],"type":"Point"}
}