{
  "type": "Feature",
  "properties": {
    "addr:full":"64 Currumbin Creek Rd Currumbin QLD 4223",
    "addr:housenumber":"64",
    "addr:postcode":"4223",
    "addr:street":"Currumbin Creek Rd",
    "iso:country":"AU",
    "sg:address":"64 Currumbin Creek Rd",
    "sg:city":"Currumbin",
    "sg:classifiers":[
        {
            "category":"Professional",
            "subcategory":"Accounting & Tax Preparation",
            "type":"Services"
        }
    ],
    "sg:phone":"+61 7 5534 3207",
    "sg:postcode":"4223",
    "sg:province":"QLD",
    "sg:tags":[
        "distributor",
        "lock",
        "mfrs"
    ],
    "wof:name":"MBL Lock Supplies",
    "wof:placetype":"venue"
},
  "geometry": {"coordinates":[153.47233581500001,-28.144197464],"type":"Point"}
}