{
  "type": "Feature",
  "properties": {
    "addr:full":"682 Cabramatta Rd Bonnyrigg NSW 2177",
    "addr:housenumber":"682",
    "addr:postcode":"2177",
    "addr:street":"Cabramatta Rd",
    "iso:country":"AU",
    "sg:address":"682 Cabramatta Rd",
    "sg:city":"Bonnyrigg",
    "sg:classifiers":[
        {
            "category":"Retail",
            "subcategory":"Event Space",
            "type":"Services"
        }
    ],
    "sg:phone":"+61 2 9823 7500",
    "sg:postcode":"2177",
    "sg:province":"NSW",
    "sg:tags":[
        "venue",
        "reception",
        "wedding"
    ],
    "wof:name":"Novella Events",
    "wof:placetype":"venue"
},
  "geometry": {"coordinates":[150.89202880900001,-33.8934173584],"type":"Point"}
}