{
  "type": "Feature",
  "properties": {
    "addr:full":"9 Niven Pl Belrose NSW 2085",
    "addr:housenumber":"9",
    "addr:postcode":"2085",
    "addr:street":"Niven Pl",
    "iso:country":"AU",
    "sg:address":"9 Niven Pl",
    "sg:city":"Belrose",
    "sg:classifiers":[
        {
            "category":"Personal",
            "type":"Services"
        }
    ],
    "sg:phone":"+61 2 8230 3427",
    "sg:postcode":"2085",
    "sg:province":"NSW",
    "sg:tags":[
        "reducing",
        "treatment",
        "weight"
    ],
    "wof:name":"Herbalife Belrose",
    "wof:placetype":"venue"
},
  "geometry": {"coordinates":[151.224884033,-33.7321128845],"type":"Point"}
}