{
  "type": "Feature",
  "properties": {
    "addr:full":"Level 57, MLC Centre, Martin Place Sydney NSW 2000",
    "addr:postcode":"2000",
    "addr:street":"Place",
    "iso:country":"AU",
    "sg:address":"Level 57, MLC Centre, Martin Place",
    "sg:city":"Sydney",
    "sg:classifiers":[
        {
            "category":"Banks & Credit Unions",
            "subcategory":"Financial Services",
            "type":"Services"
        }
    ],
    "sg:phone":"+61 1300 880 126",
    "sg:postcode":"2000",
    "sg:province":"NSW",
    "sg:tags":[
        "advisory",
        "planning",
        "retirement"
    ],
    "sg:website":"http://www.ofp.net.au",
    "wof:name":"The Office Of Financial Planning",
    "wof:placetype":"venue"
},
  "geometry": {"coordinates":[151.210006714,-33.8695793152],"type":"Point"}
}