{
  "type": "Feature",
  "properties": {
    "addr:full":"31 Waples Rd Unanderra NSW 2526",
    "addr:housenumber":"31",
    "addr:postcode":"2526",
    "addr:street":"Waples Rd",
    "iso:country":"AU",
    "sg:address":"31 Waples Rd",
    "sg:city":"Unanderra",
    "sg:classifiers":[
        {
            "category":"Retail",
            "subcategory":"Laundry & Dry Cleaning",
            "type":"Services"
        }
    ],
    "sg:phone":"+61 2 4272 3380",
    "sg:postcode":"2526",
    "sg:province":"NSW",
    "wof:name":"Smart Press Laundrette",
    "wof:placetype":"venue"
},
  "geometry": {"coordinates":[150.830368042,-34.4565315247],"type":"Point"}
}