{
  "type": "Feature",
  "properties": {
    "iso:country":"AU",
    "sg:address":"74 Lincoln Rd",
    "sg:city":"Essendon",
    "sg:classifiers":[
        {
            "category":"Personal",
            "subcategory":"Beauty Salon",
            "type":"Services"
        }
    ],
    "sg:phone":"+61 3 9379 4387",
    "sg:postcode":"3040",
    "sg:province":"VIC",
    "sg:tags":[
        "hairdresser"
    ],
    "wof:name":"Lincoln Salon Hair & Beauty",
    "wof:placetype":"venue"
},
  "geometry": {"coordinates":[144.91001892099999,-37.7457427979],"type":"Point"}
}