{
  "type": "Feature",
  "properties": {
    "iso:country":"AU",
    "sg:address":"Unit 4/ 31 Sterling Rd",
    "sg:city":"Minchinbury",
    "sg:classifiers":[
        {
            "category":"Autos & Motor Vehicles",
            "subcategory":"Recreational Vehicle Sales",
            "type":"Retail Goods"
        }
    ],
    "sg:phone":"+61 2 9625 7334",
    "sg:postcode":"2770",
    "sg:province":"NSW",
    "sg:tags":[
        "industrial",
        "sewing",
        "contractor"
    ],
    "wof:name":"Anitta Sewing Pty Ltd",
    "wof:placetype":"venue"
},
  "geometry": {"coordinates":[150.817337036,-33.7822685242],"type":"Point"}
}