{
  "type": "Feature",
  "properties": {
    "addr:full":"1 Riverside Ave Werribee VIC 3030",
    "addr:housenumber":"1",
    "addr:postcode":"3030",
    "addr:street":"Riverside Ave",
    "iso:country":"AU",
    "sg:address":"1 Riverside Ave",
    "sg:city":"Werribee",
    "sg:classifiers":[
        {
            "category":"Retail",
            "subcategory":"Auto Repair",
            "type":"Services"
        }
    ],
    "sg:phone":"+61 3 9741 9774",
    "sg:postcode":"3030",
    "sg:province":"VIC",
    "sg:tags":[
        "repairer",
        "motor",
        "engineer"
    ],
    "wof:name":"Riverside Ave Motors",
    "wof:placetype":"venue"
},
  "geometry": {"coordinates":[144.65910299999999,-37.911999],"type":"Point"}
}