{
  "type": "Feature",
  "properties": {
    "iso:country":"AU",
    "sg:address":"8 Proprietary St",
    "sg:city":"Tingalpa",
    "sg:classifiers":[
        {
            "category":"Wholesale",
            "subcategory":"Electrical",
            "type":"Manufacturing & Wholesale Goods"
        }
    ],
    "sg:phone":"+61 7 3390 4811",
    "sg:postcode":"4173",
    "sg:province":"QLD",
    "sg:tags":[
        "wholesaler"
    ],
    "wof:name":"Middendorp Electric Co Pty Ltd",
    "wof:placetype":"venue"
},
  "geometry": {"coordinates":[153.108688355,-27.4724407196],"type":"Point"}
}