{
  "type": "Feature",
  "properties": {
    "addr:full":"2 Solent Crt Daisy Hill QLD 4127",
    "addr:housenumber":"2",
    "addr:postcode":"4127",
    "addr:street":"Solent Crt",
    "iso:country":"AU",
    "sg:address":"2 Solent Crt",
    "sg:city":"Daisy Hill",
    "sg:classifiers":[
        {
            "category":"Manufacturing",
            "subcategory":"Musical Instruments",
            "type":"Manufacturing & Wholesale Goods"
        }
    ],
    "sg:phone":"+61 7 3209 3859",
    "sg:postcode":"4127",
    "sg:province":"QLD",
    "sg:tags":[
        "repair",
        "maker"
    ],
    "wof:name":"Allwinds Instrument Repairs",
    "wof:placetype":"venue"
},
  "geometry": {"coordinates":[153.141479492,-27.6392288208],"type":"Point"}
}