{
  "type": "Feature",
  "properties": {
    "addr:full":"Smith St Innisfail QLD 4860",
    "addr:postcode":"4860",
    "addr:street":"Smith St",
    "iso:country":"AU",
    "sg:address":"Smith St",
    "sg:city":"Innisfail",
    "sg:classifiers":[
        {
            "category":"Banks & Credit Unions",
            "subcategory":"Investment Brokerage",
            "type":"Services"
        }
    ],
    "sg:phone":"+61 7 4061 8733",
    "sg:postcode":"4860",
    "sg:province":"QLD",
    "wof:name":"Jordan Financial Services",
    "wof:placetype":"venue"
},
  "geometry": {"coordinates":[146.028244019,-17.5247402191],"type":"Point"}
}