{
  "type": "Feature",
  "properties": {
    "iso:country":"AU",
    "sg:address":"Innovation House, 1st Ave Mawson Lakes",
    "sg:city":"Mawson Lakes",
    "sg:classifiers":[
        {
            "category":"Utilities",
            "subcategory":"Mobile Phone",
            "type":"Services"
        }
    ],
    "sg:phone":"+61 8 8260 3799",
    "sg:postcode":"5095",
    "sg:province":"SA",
    "sg:tags":[
        "assembly",
        "part",
        "electronic"
    ],
    "wof:name":"PCB World Solutions Pty Ltd",
    "wof:placetype":"venue"
},
  "geometry": {"coordinates":[138.619338989,-34.8145675659],"type":"Point"}
}