{
  "type": "Feature",
  "properties": {
    "iso:country":"AU",
    "sg:address":"Flinders Ave",
    "sg:city":"Whyalla Stuart",
    "sg:classifiers":[
        {
            "category":"Deli",
            "type":"Food & Drink"
        }
    ],
    "sg:phone":"+61 8 8649 3290",
    "sg:postcode":"5608",
    "sg:province":"SA",
    "sg:tags":[
        "delicatessen"
    ],
    "wof:name":"One Stop Deli",
    "wof:placetype":"venue"
},
  "geometry": {"coordinates":[137.517426,-33.026585],"type":"Point"}
}