{
  "type": "Feature",
  "properties": {
    "addr:full":"Shop 10 Village Centre Gibson Rd Noosaville QLD 4566",
    "addr:housenumber":"shop 10",
    "addr:postcode":"4566",
    "addr:street":"Village Centre Gibson Rd",
    "iso:country":"AU",
    "sg:address":"Shop 10 Village Centre Gibson Rd",
    "sg:city":"Noosaville",
    "sg:classifiers":[
        {
            "category":"Shopping",
            "subcategory":"Jewelry",
            "type":"Retail Goods"
        }
    ],
    "sg:phone":"+61 7 5474 2322",
    "sg:postcode":"4566",
    "sg:province":"QLD",
    "sg:tags":[
        "jeweller"
    ],
    "wof:name":"Noosa Village Jewellers",
    "wof:placetype":"venue"
},
  "geometry": {"coordinates":[153.05279540999999,-26.4004974365],"type":"Point"}
}