{
  "type": "Feature",
  "properties": {
    "addr:full":"5 Monterey Rd Dandenong VIC 3175",
    "addr:housenumber":"5",
    "addr:postcode":"3175",
    "addr:street":"Monterey Rd",
    "iso:country":"AU",
    "sg:address":"5 Monterey Rd",
    "sg:city":"Dandenong",
    "sg:classifiers":[
        {
            "category":"Retail",
            "subcategory":"Auto Repair",
            "type":"Services"
        }
    ],
    "sg:phone":"+61 1300 767 040",
    "sg:postcode":"3175",
    "sg:province":"VIC",
    "sg:tags":[
        "engine",
        "reconditioning"
    ],
    "wof:name":"HM GEM Engines",
    "wof:placetype":"venue"
},
  "geometry": {"coordinates":[145.21607971200001,-38.0241622925],"type":"Point"}
}