{
  "type": "Feature",
  "properties": {
    "iso:country":"AU",
    "sg:address":"Bayside Drv",
    "sg:city":"Walkerville",
    "sg:classifiers":[
        {
            "category":"Fast Food",
            "type":"Food & Drink"
        }
    ],
    "sg:phone":"+61 3 5663 2321",
    "sg:postcode":"3956",
    "sg:province":"VIC",
    "sg:tags":[
        "away",
        "take"
    ],
    "wof:name":"Walkerville Kiosk",
    "wof:placetype":"venue"
},
  "geometry": {"coordinates":[145.99697875999999,-38.831401825],"type":"Point"}
}