{
  "type": "Feature",
  "properties": {
    "iso:country":"AU",
    "sg:address":"PO Box 32",
    "sg:city":"Kerrimuir",
    "sg:classifiers":[
        {
            "category":"Building & Trades",
            "subcategory":"Construction",
            "type":"Services"
        }
    ],
    "sg:phone":"+61 418 333 415",
    "sg:postcode":"3129",
    "sg:province":"VIC",
    "sg:tags":[
        "home",
        "air conditioning"
    ],
    "wof:name":"ABC Airconditioning",
    "wof:placetype":"venue"
},
  "geometry": {"coordinates":[145.138580322,-37.8100013733],"type":"Point"}
}