{
  "type": "Feature",
  "properties": {
    "iso:country":"AU",
    "sg:address":"78 Mount Ettalong Rd",
    "sg:city":"Umina",
    "sg:classifiers":[
        {
            "category":"Utilities",
            "subcategory":"Electric",
            "type":"Services"
        }
    ],
    "sg:phone":"+61 2 4341 5936",
    "sg:postcode":"2257",
    "sg:province":"NSW",
    "sg:tags":[
        "electrical",
        "contractor"
    ],
    "wof:name":"A & S McKenna",
    "wof:placetype":"venue"
},
  "geometry": {"coordinates":[151.30804443400001,-33.5278320312],"type":"Point"}
}