{
  "type": "Feature",
  "properties": {
    "iso:country":"AU",
    "sg:address":"18 Kabbarli St",
    "sg:city":"Wyndham",
    "sg:classifiers":[
        {
            "category":"Airline",
            "type":"Transportation"
        }
    ],
    "sg:phone":"+61 8 9161 1366",
    "sg:postcode":"6740",
    "sg:province":"WA",
    "sg:tags":[
        "agent"
    ],
    "wof:name":"Oasis Air",
    "wof:placetype":"venue"
},
  "geometry": {"coordinates":[128.12362670900001,-15.4840583801],"type":"Point"}
}