{
  "type": "Feature",
  "properties": {
    "addr:full":"88 Piper St Kyneton VIC 3444",
    "addr:housenumber":"88",
    "addr:postcode":"3444",
    "addr:street":"Piper St",
    "iso:country":"AU",
    "sg:address":"88 Piper St",
    "sg:city":"Kyneton",
    "sg:classifiers":[
        {
            "category":"Wholesale",
            "subcategory":"Machinery & Supplies",
            "type":"Manufacturing & Wholesale Goods"
        }
    ],
    "sg:phone":"+61 3 5422 1821",
    "sg:postcode":"3444",
    "sg:province":"VIC",
    "sg:tags":[
        "agricultural"
    ],
    "wof:name":"Sheppard L & G & Sons",
    "wof:placetype":"venue"
},
  "geometry": {"coordinates":[144.447189331,-37.2437362671],"type":"Point"}
}