{
  "type": "Feature",
  "properties": {
    "iso:country":"AU",
    "sg:address":"Ste2/ 162 Goulburn St",
    "sg:city":"Surry Hills",
    "sg:classifiers":[
        {
            "category":"Professional",
            "subcategory":"Management & Consulting",
            "type":"Services"
        }
    ],
    "sg:phone":"+61 2 8021 4040",
    "sg:postcode":"2010",
    "sg:province":"NSW",
    "sg:tags":[
        "consultant"
    ],
    "wof:name":"Gemba Group Pty Ltd",
    "wof:placetype":"venue"
},
  "geometry": {"coordinates":[151.21229553200001,-33.8787727356],"type":"Point"}
}