{
  "type": "Feature",
  "properties": {
    "iso:country":"AU",
    "sg:address":"195 Briens Rd",
    "sg:city":"Northmead",
    "sg:classifiers":[
        {
            "category":"Farming",
            "subcategory":"Fish & Marine Products",
            "type":"Manufacturing & Wholesale Goods"
        }
    ],
    "sg:phone":"+61 2 9630 3307",
    "sg:postcode":"2152",
    "sg:province":"NSW",
    "sg:tags":[
        "slate"
    ],
    "wof:name":"Bellstone & Tile P/L",
    "wof:placetype":"venue"
},
  "geometry": {"coordinates":[150.981079102,-33.7995796204],"type":"Point"}
}