{
  "type": "Feature",
  "properties": {
    "addr:full":"116 Paddington St Paddington NSW 2021",
    "addr:housenumber":"116",
    "addr:postcode":"2021",
    "addr:street":"Paddington St",
    "iso:country":"AU",
    "sg:address":"116 Paddington St",
    "sg:city":"Paddington",
    "sg:classifiers":[
        {
            "category":"Education",
            "subcategory":"Kindergarten",
            "type":"Public Place"
        }
    ],
    "sg:phone":"+61 2 9363 3213",
    "sg:postcode":"2021",
    "sg:province":"NSW",
    "sg:tags":[
        "pre-schools"
    ],
    "wof:name":"Church Of Christ Kindergarten",
    "wof:placetype":"venue"
},
  "geometry": {"coordinates":[151.233642578,-33.8860359192],"type":"Point"}
}