{
  "type": "Feature",
  "properties": {
    "addr:full":"7/ 85 Pacific Pde Dee Why NSW 2099",
    "addr:housenumber":"/ 85",
    "addr:postcode":"2099",
    "addr:street":"Pacific Pde",
    "iso:country":"AU",
    "sg:address":"7/ 85 Pacific Pde",
    "sg:city":"Dee Why",
    "sg:classifiers":[
        {
            "category":"Government",
            "subcategory":"Fire Station",
            "type":"Public Place"
        }
    ],
    "sg:phone":"+61 412 256 415",
    "sg:postcode":"2099",
    "sg:province":"NSW",
    "sg:tags":[
        "equipment",
        "protection",
        "consultant"
    ],
    "wof:name":"Dale Moore Electrical",
    "wof:placetype":"venue"
},
  "geometry": {"coordinates":[151.29124450699999,-33.7554168701],"type":"Point"}
}