{
  "type": "Feature",
  "properties": {
    "addr:full":"357 Bourke St Darlinghurst NSW 2010",
    "addr:housenumber":"357",
    "addr:postcode":"2010",
    "addr:street":"Bourke St",
    "iso:country":"AU",
    "sg:address":"357 Bourke St",
    "sg:city":"Darlinghurst",
    "sg:classifiers":[
        {
            "category":"Social Services",
            "subcategory":"Job Training",
            "type":"Services"
        }
    ],
    "sg:phone":"+61 2 9358 4188",
    "sg:postcode":"2010",
    "sg:province":"NSW",
    "sg:tags":[
        "interpreter"
    ],
    "wof:name":"Language Professionals",
    "wof:placetype":"venue"
},
  "geometry": {"coordinates":[151.216873169,-33.8795623779],"type":"Point"}
}