{
  "type": "Feature",
  "properties": {
    "addr:full":"1 Milan Crt Dandenong North VIC 3175",
    "addr:housenumber":"1",
    "addr:postcode":"3175",
    "addr:street":"Milan Crt",
    "iso:country":"AU",
    "sg:address":"1 Milan Crt",
    "sg:city":"Dandenong North",
    "sg:classifiers":[
        {
            "category":"Social Services",
            "subcategory":"Child Care",
            "type":"Services"
        }
    ],
    "sg:phone":"+61 3 9795 4894",
    "sg:postcode":"3175",
    "sg:province":"VIC",
    "sg:tags":[
        "support",
        "health"
    ],
    "wof:name":"Maternal & Child Health Centres",
    "wof:placetype":"venue"
},
  "geometry": {"coordinates":[145.215133667,-37.9561042786],"type":"Point"}
}