{
  "type": "Feature",
  "properties": {
    "iso:country":"AU",
    "sg:address":"61- 63 Dora St",
    "sg:city":"Morisset",
    "sg:classifiers":[
        {
            "category":"Manufacturing",
            "subcategory":"Motor Vehicles & Parts",
            "type":"Manufacturing & Wholesale Goods"
        }
    ],
    "sg:phone":"+61 2 4973 1189",
    "sg:postcode":"2264",
    "sg:province":"NSW",
    "sg:tags":[
        "replacement"
    ],
    "wof:name":"Bullseye Autopart Centre",
    "wof:placetype":"venue"
},
  "geometry": {"coordinates":[151.489685,-33.107628],"type":"Point"}
}