{
  "type": "Feature",
  "properties": {
    "addr:full":"Parafield Airport Kitty Hawk La Parafield SA 5106",
    "addr:postcode":"5106",
    "iso:country":"AU",
    "sg:address":"Parafield Airport Kitty Hawk La",
    "sg:city":"Parafield",
    "sg:classifiers":[
        {
            "category":"Airline",
            "type":"Transportation"
        }
    ],
    "sg:phone":"+61 8 8258 1902",
    "sg:postcode":"5106",
    "sg:province":"SA",
    "sg:tags":[
        "aircraft",
        "rental",
        "charter"
    ],
    "wof:name":"SAATAS",
    "wof:placetype":"venue"
},
  "geometry": {"coordinates":[138.63166799999999,-34.78244],"type":"Point"}
}