{
  "type": "Feature",
  "properties": {
    "addr:full":"56 McKinnon Rd Christie Downs SA 5164",
    "addr:housenumber":"56",
    "addr:postcode":"5164",
    "addr:street":"Mckinnon Rd",
    "iso:country":"AU",
    "sg:address":"56 McKinnon Rd",
    "sg:city":"Christie Downs",
    "sg:classifiers":[
        {
            "category":"Building & Trades",
            "subcategory":"Cleaning & Sanitation",
            "type":"Services"
        }
    ],
    "sg:phone":"+61 8 8186 4491",
    "sg:postcode":"5164",
    "sg:province":"SA",
    "sg:tags":[
        "commercial",
        "maintenance"
    ],
    "wof:name":"Snell Ryan",
    "wof:placetype":"venue"
},
  "geometry": {"coordinates":[138.490722656,-35.132106781],"type":"Point"}
}