{
  "type": "Feature",
  "properties": {
    "addr:full":"210 Cottons Rd Bondoola QLD 4702",
    "addr:housenumber":"210",
    "addr:postcode":"4702",
    "addr:street":"Cottons Rd",
    "iso:country":"AU",
    "sg:address":"210 Cottons Rd",
    "sg:city":"Bondoola",
    "sg:classifiers":[
        {
            "category":"Building & Trades",
            "subcategory":"Construction",
            "type":"Services"
        }
    ],
    "sg:phone":"+61 413 112 406",
    "sg:postcode":"4702",
    "sg:province":"QLD",
    "sg:tags":[
        "plasterboard",
        "plasterer",
        "fixer"
    ],
    "wof:name":"T Prinsen Plasterers",
    "wof:placetype":"venue"
},
  "geometry": {"coordinates":[150.68588256800001,-23.1672954559],"type":"Point"}
}