{
  "type": "Feature",
  "properties": {
    "addr:full":"Burnett Hwy Dululu QLD 4702",
    "addr:postcode":"4702",
    "addr:street":"Burnett Hwy",
    "iso:country":"AU",
    "sg:address":"Burnett Hwy",
    "sg:city":"Dululu",
    "sg:classifiers":[
        {
            "category":"Food & Beverages",
            "subcategory":"Groceries & Convenience Stores",
            "type":"Retail Goods"
        }
    ],
    "sg:phone":"+61 7 4937 1365",
    "sg:postcode":"4702",
    "sg:province":"QLD",
    "wof:name":"Dululu Store",
    "wof:placetype":"venue"
},
  "geometry": {"coordinates":[150.262084961,-23.8461227417],"type":"Point"}
}