{
  "type": "Feature",
  "properties": {
    "addr:full":"313 Glenferrie Rd Malvern VIC 3144",
    "addr:housenumber":"313",
    "addr:postcode":"3144",
    "addr:street":"Glenferrie Rd",
    "iso:country":"AU",
    "sg:address":"313 Glenferrie Rd",
    "sg:city":"Malvern",
    "sg:classifiers":[
        {
            "category":"Professional",
            "subcategory":"Accounting & Tax Preparation",
            "type":"Services"
        }
    ],
    "sg:phone":"+61 3 9824 8111",
    "sg:postcode":"3144",
    "sg:province":"VIC",
    "sg:tags":[
        "accountant",
        "auditor"
    ],
    "wof:name":"Krampel Newman Partners Pty Ltd",
    "wof:placetype":"venue"
},
  "geometry": {"coordinates":[145.029220581,-37.8558425903],"type":"Point"}
}