{
  "type": "Feature",
  "properties": {
    "iso:country":"AU",
    "sg:address":"57 McCallum Rd",
    "sg:city":"Doncaster",
    "sg:classifiers":[
        {
            "category":"Communications",
            "type":"Services"
        }
    ],
    "sg:phone":"+61 413 800 167",
    "sg:postcode":"3108",
    "sg:province":"VIC",
    "sg:tags":[
        "translation"
    ],
    "wof:name":"Zorina-Epshtein L",
    "wof:placetype":"venue"
},
  "geometry": {"coordinates":[145.13409423799999,-37.7774925232],"type":"Point"}
}