{
  "type": "Feature",
  "properties": {
    "iso:country":"AU",
    "sg:address":"8 Auster Crt",
    "sg:city":"Caboolture",
    "sg:classifiers":[
        {
            "category":"Building & Trades",
            "subcategory":"Equipment Rental",
            "type":"Services"
        }
    ],
    "sg:phone":"+61 7 5495 5733",
    "sg:postcode":"4510",
    "sg:province":"QLD",
    "sg:tags":[
        "builder",
        "contractor"
    ],
    "wof:name":"Caboolture On Site Rentals",
    "wof:placetype":"venue"
},
  "geometry": {"coordinates":[152.98417699999999,-27.083694],"type":"Point"}
}