{
  "type": "Feature",
  "properties": {
    "addr:full":"18 Graham St Albany WA 6330",
    "addr:housenumber":"18",
    "addr:postcode":"6330",
    "addr:street":"Graham St",
    "iso:country":"AU",
    "sg:address":"18 Graham St",
    "sg:city":"Albany",
    "sg:classifiers":[
        {
            "category":"Building & Trades",
            "subcategory":"Construction",
            "type":"Services"
        }
    ],
    "sg:phone":"+61 417 962 506",
    "sg:postcode":"6330",
    "sg:province":"WA",
    "sg:tags":[
        "contractor"
    ],
    "wof:name":"Wauters Enterprises",
    "wof:placetype":"venue"
},
  "geometry": {"coordinates":[117.88060760499999,-35.0123748779],"type":"Point"}
}