{
  "type": "Feature",
  "properties": {
    "addr:full":"Shop 9, 27- 35 William St Fremantle WA 6160",
    "addr:housenumber":"shop;27 35",
    "addr:postcode":"6160",
    "addr:street":"William St",
    "iso:country":"AU",
    "sg:address":"Shop 9, 27- 35 William St",
    "sg:city":"Fremantle",
    "sg:classifiers":[
        {
            "category":"Personal",
            "subcategory":"Beauty Salon",
            "type":"Services"
        }
    ],
    "sg:phone":"+61 8 9433 2811",
    "sg:postcode":"6160",
    "sg:province":"WA",
    "sg:tags":[
        "hairdresser"
    ],
    "wof:name":"Morph Hair & Beauty",
    "wof:placetype":"venue"
},
  "geometry": {"coordinates":[115.748611,-32.054993],"type":"Point"}
}