{
  "type": "Feature",
  "properties": {
    "addr:full":"19a Philip Rd Mona Vale NSW 2103",
    "addr:housenumber":"19a",
    "addr:postcode":"2103",
    "addr:street":"Philip Rd",
    "iso:country":"AU",
    "sg:address":"19a Philip Rd",
    "sg:city":"Mona Vale",
    "sg:classifiers":[
        {
            "category":"Recreation",
            "type":"Entertainment"
        }
    ],
    "sg:phone":"+61 2 9973 2486",
    "sg:postcode":"2103",
    "sg:province":"NSW",
    "sg:tags":[
        "supply",
        "outdoor",
        "adventure",
        "activity"
    ],
    "wof:name":"Pure Power Motor Sports",
    "wof:placetype":"venue"
},
  "geometry": {"coordinates":[151.31358337399999,-33.6690254211],"type":"Point"}
}