{
  "type": "Feature",
  "properties": {
    "iso:country":"AU",
    "sg:address":"Thurston Rd",
    "sg:city":"Snowtown",
    "sg:classifiers":[
        {
            "category":"Farming",
            "subcategory":"Farm",
            "type":"Manufacturing & Wholesale Goods"
        }
    ],
    "sg:phone":"+61 409 098 356",
    "sg:postcode":"5520",
    "sg:province":"SA",
    "sg:tags":[
        "farmer"
    ],
    "wof:name":"The Thurleigh Trust",
    "wof:placetype":"venue"
},
  "geometry": {"coordinates":[138.228713989,-33.8456993103],"type":"Point"}
}