{
  "type": "Feature",
  "properties": {
    "addr:full":"Unit 2, 118 Newcastle Rd Wallsend NSW 2287",
    "addr:housenumber":"118",
    "addr:postcode":"2287",
    "addr:street":"Newcastle Rd",
    "iso:country":"AU",
    "sg:address":"Unit 2, 118 Newcastle Rd",
    "sg:city":"Wallsend",
    "sg:classifiers":[
        {
            "category":"Sports & Exercise",
            "subcategory":"Gym",
            "type":"Entertainment"
        }
    ],
    "sg:phone":"+61 2 4951 2288",
    "sg:postcode":"2287",
    "sg:province":"NSW",
    "sg:tags":[
        "health",
        "fitness"
    ],
    "wof:name":"Contours Express",
    "wof:placetype":"venue"
},
  "geometry": {"coordinates":[151.68443298299999,-32.9037208557],"type":"Point"}
}