{
  "type": "Feature",
  "properties": {
    "iso:country":"AU",
    "sg:address":"2/ 168 Jacobs Drv",
    "sg:city":"Sussex Inlet",
    "sg:classifiers":[
        {
            "category":"Real Estate",
            "subcategory":"Real Estate Agent",
            "type":"Services"
        }
    ],
    "sg:phone":"+61 2 4441 1550",
    "sg:postcode":"2540",
    "sg:province":"NSW",
    "wof:name":"Elders Real Estate",
    "wof:placetype":"venue"
},
  "geometry": {"coordinates":[150.59942626899999,-35.1569900513],"type":"Point"}
}