{
  "type": "Feature",
  "properties": {
    "addr:full":"Wattle St Mt Gambier SA 5290",
    "addr:postcode":"5290",
    "addr:street":"Wattle St",
    "iso:country":"AU",
    "sg:address":"Wattle St",
    "sg:city":"Mt Gambier",
    "sg:classifiers":[
        {
            "category":"Social Services",
            "subcategory":"Job Training",
            "type":"Services"
        }
    ],
    "sg:phone":"+61 418 849 218",
    "sg:postcode":"5290",
    "sg:province":"SA",
    "sg:tags":[
        "tannery"
    ],
    "wof:name":"Craike Lea Tanneries Pty Ltd",
    "wof:placetype":"venue"
},
  "geometry": {"coordinates":[140.75398300000001,-37.822079],"type":"Point"}
}