{
  "type": "Feature",
  "properties": {
    "addr:full":"Ste5/ 35 Terry St Rozelle NSW 2039",
    "addr:housenumber":"35",
    "addr:postcode":"2039",
    "addr:street":"Terry St",
    "iso:country":"AU",
    "sg:address":"Ste5/ 35 Terry St",
    "sg:city":"Rozelle",
    "sg:classifiers":[
        {
            "category":"Insurance",
            "subcategory":"Insurance Agent",
            "type":"Services"
        }
    ],
    "sg:phone":"+61 2 9818 3115",
    "sg:postcode":"2039",
    "sg:province":"NSW",
    "sg:tags":[
        "broker"
    ],
    "wof:name":"Accountancy Insurance Brokers Pty Ltd",
    "wof:placetype":"venue"
},
  "geometry": {"coordinates":[151.16801452600001,-33.8605155945],"type":"Point"}
}