{
  "type": "Feature",
  "properties": {
    "addr:full":"26 Edward St Orange NSW 2800",
    "addr:housenumber":"26",
    "addr:postcode":"2800",
    "addr:street":"Edward St",
    "iso:country":"AU",
    "sg:address":"26 Edward St",
    "sg:city":"Orange",
    "sg:classifiers":[
        {
            "category":"Retail",
            "subcategory":"Repair Shop",
            "type":"Services"
        }
    ],
    "sg:phone":"+61 2 6361 3556",
    "sg:postcode":"2800",
    "sg:province":"NSW",
    "sg:tags":[
        "windscreen"
    ],
    "wof:name":"A Duobond Windscreen Repairs",
    "wof:placetype":"venue"
},
  "geometry": {"coordinates":[149.104904175,-33.2930374146],"type":"Point"}
}