{
  "type": "Feature",
  "properties": {
    "iso:country":"AU",
    "sg:address":"PO Box 2179",
    "sg:city":"Malaga",
    "sg:classifiers":[
        {
            "category":"Wholesale",
            "subcategory":"Machinery & Supplies",
            "type":"Manufacturing & Wholesale Goods"
        }
    ],
    "sg:phone":"+61 8 9248 5108",
    "sg:postcode":"6944",
    "sg:province":"WA",
    "sg:tags":[
        "equipment",
        "welding"
    ],
    "wof:name":"Malaga Welding & Industrial Supplies Pty Ltd",
    "wof:placetype":"venue"
},
  "geometry": {"coordinates":[115.893409729,-31.8554382324],"type":"Point"}
}