{
  "type": "Feature",
  "properties": {
    "addr:full":"PO Box 2253 Berala NSW 2141",
    "addr:postcode":"2141",
    "iso:country":"AU",
    "sg:address":"PO Box 2253",
    "sg:city":"Berala",
    "sg:classifiers":[
        {
            "category":"Mining & Drilling",
            "type":"Manufacturing & Wholesale Goods"
        }
    ],
    "sg:phone":"+61 401 888 789",
    "sg:postcode":"2141",
    "sg:province":"NSW",
    "sg:tags":[
        "concrete",
        "breaking",
        "grinding",
        "sawing"
    ],
    "wof:name":"All Over Concrete Cutting Pty Ltd",
    "wof:placetype":"venue"
},
  "geometry": {"coordinates":[151.03363037099999,-33.8706703186],"type":"Point"}
}