{
  "type": "Feature",
  "properties": {
    "iso:country":"AU",
    "sg:address":"947 Beaudesert Rd",
    "sg:city":"Coopers Plains",
    "sg:classifiers":[
        {
            "category":"Freight",
            "type":"Transportation"
        }
    ],
    "sg:phone":"+61 7 3274 2345",
    "sg:postcode":"4108",
    "sg:province":"QLD",
    "sg:tags":[
        "light",
        "carrier"
    ],
    "wof:name":"X L Express Pty Ltd",
    "wof:placetype":"venue"
},
  "geometry": {"coordinates":[153.023513794,-27.5664482117],"type":"Point"}
}