{
  "type": "Feature",
  "properties": {
    "addr:full":"50 Churchill St Childers QLD 4660",
    "addr:housenumber":"50",
    "addr:postcode":"4660",
    "addr:street":"Churchill St",
    "iso:country":"AU",
    "sg:address":"50 Churchill St",
    "sg:city":"Childers",
    "sg:classifiers":[
        {
            "category":"Real Estate",
            "subcategory":"Real Estate Agent",
            "type":"Services"
        }
    ],
    "sg:phone":"+61 7 4126 1742",
    "sg:postcode":"4660",
    "sg:province":"QLD",
    "wof:name":"Brian Chappell & Buxton Real Estate",
    "wof:placetype":"venue"
},
  "geometry": {"coordinates":[152.27961730999999,-25.2363471985],"type":"Point"}
}