{
  "type": "Feature",
  "properties": {
    "addr:full":"Canberra Hospital (Foyer) Yamba Drv Garran ACT 2605",
    "addr:postcode":"2605",
    "addr:street":"Drv",
    "iso:country":"AU",
    "sg:address":"Canberra Hospital (Foyer) Yamba Drv",
    "sg:city":"Garran",
    "sg:classifiers":[
        {
            "category":"Personal",
            "subcategory":"Beauty Salon",
            "type":"Services"
        }
    ],
    "sg:phone":"+61 2 6281 0441",
    "sg:postcode":"2605",
    "sg:province":"ACT",
    "sg:tags":[
        "hairdresser"
    ],
    "wof:name":"Hair Dressing Room",
    "wof:placetype":"venue"
},
  "geometry": {"coordinates":[149.099487305,-35.3455352783],"type":"Point"}
}