{
  "type": "Feature",
  "properties": {
    "addr:full":"Sue&#039;s Korner 2128 Sandgate Rd Boondall QLD 4034",
    "addr:housenumber":"2128",
    "addr:postcode":"4034",
    "addr:street":"S Korner;Sandgate Rd",
    "iso:country":"AU",
    "sg:address":"Sue&#039;s Korner 2128 Sandgate Rd",
    "sg:city":"Boondall",
    "sg:classifiers":[
        {
            "category":"Shopping",
            "subcategory":"Pawn Shop",
            "type":"Retail Goods"
        }
    ],
    "sg:phone":"+61 7 3865 1563",
    "sg:postcode":"4034",
    "sg:province":"QLD",
    "sg:tags":[
        "pawnbroker"
    ],
    "wof:name":"Brisbane Pawnbrokers",
    "wof:placetype":"venue"
},
  "geometry": {"coordinates":[153.06033300000001,-27.352106],"type":"Point"}
}