{
  "type": "Feature",
  "properties": {
    "addr:full":"15 Chuter St North Sydney NSW 2060",
    "addr:housenumber":"15",
    "addr:postcode":"2060",
    "addr:street":"Chuter St",
    "iso:country":"AU",
    "sg:address":"15 Chuter St",
    "sg:city":"North Sydney",
    "sg:classifiers":[
        {
            "category":"Professional",
            "subcategory":"Art Services",
            "type":"Services"
        }
    ],
    "sg:phone":"+61 2 9929 9800",
    "sg:postcode":"2060",
    "sg:province":"NSW",
    "sg:tags":[
        "graphic",
        "designer"
    ],
    "wof:name":"Equation Corporate Design Pty Ltd",
    "wof:placetype":"venue"
},
  "geometry": {"coordinates":[151.203048706,-33.8425941467],"type":"Point"}
}