{
  "type": "Feature",
  "properties": {
    "addr:full":"4 Burnage St Toowoomba QLD 4350",
    "addr:housenumber":"4",
    "addr:postcode":"4350",
    "addr:street":"Burnage St",
    "iso:country":"AU",
    "sg:address":"4 Burnage St",
    "sg:city":"Toowoomba",
    "sg:classifiers":[
        {
            "category":"Travel",
            "subcategory":"Hotels & Motels",
            "type":"Entertainment"
        }
    ],
    "sg:phone":"+61 7 4639 3707",
    "sg:postcode":"4350",
    "sg:province":"QLD",
    "sg:website":"http://www.coachman-motel.com",
    "wof:name":"Coachman Motel",
    "wof:placetype":"venue"
},
  "geometry": {"coordinates":[151.979187,-27.565832],"type":"Point"}
}