{
  "type": "Feature",
  "properties": {
    "addr:full":"170a Murray St Gawler SA 5118",
    "addr:housenumber":"170a",
    "addr:postcode":"5118",
    "addr:street":"Murray St",
    "iso:country":"AU",
    "sg:address":"170a Murray St",
    "sg:city":"Gawler",
    "sg:classifiers":[
        {
            "category":"Real Estate",
            "subcategory":"Real Estate Agent",
            "type":"Services"
        }
    ],
    "sg:phone":"+61 8 8522 5599",
    "sg:postcode":"5118",
    "sg:province":"SA",
    "sg:tags":[
        "handyman's",
        "equipment",
        "hire",
        "builders",
        "contractor"
    ],
    "wof:name":"Bobcat Groundforce",
    "wof:placetype":"venue"
},
  "geometry": {"coordinates":[138.74877900000001,-34.593739],"type":"Point"}
}