{
  "type": "Feature",
  "properties": {
    "addr:full":"26 Wollong St Gosford NSW 2250",
    "addr:housenumber":"26",
    "addr:postcode":"2250",
    "addr:street":"Wollong St",
    "iso:country":"AU",
    "sg:address":"26 Wollong St",
    "sg:city":"Gosford",
    "sg:classifiers":[
        {
            "category":"Wholesale",
            "subcategory":"Furniture",
            "type":"Manufacturing & Wholesale Goods"
        }
    ],
    "sg:phone":"+61 2 4324 8700",
    "sg:postcode":"2250",
    "sg:province":"NSW",
    "sg:tags":[
        "wholesaler",
        "mfrs"
    ],
    "wof:name":"R.H. Bullard Custom Timber Furniture",
    "wof:placetype":"venue"
},
  "geometry": {"coordinates":[151.32734680199999,-33.4264717102],"type":"Point"}
}