{
  "type": "Feature",
  "properties": {
    "addr:full":"221 Burwood Hwy Burwood VIC 3125",
    "addr:housenumber":"221",
    "addr:postcode":"3125",
    "addr:street":"Burwood Hwy",
    "iso:country":"AU",
    "sg:address":"221 Burwood Hwy",
    "sg:city":"Burwood",
    "sg:classifiers":[
        {
            "category":"Manufacturing",
            "subcategory":"Food",
            "type":"Manufacturing & Wholesale Goods"
        }
    ],
    "sg:phone":"+61 3 9251 7087",
    "sg:postcode":"3125",
    "sg:province":"VIC",
    "sg:tags":[
        "function",
        "catering"
    ],
    "wof:name":"Deakin Uni Student Assoc Catering",
    "wof:placetype":"venue"
},
  "geometry": {"coordinates":[145.11231994600001,-37.8494262695],"type":"Point"}
}