{
  "type": "Feature",
  "properties": {
    "addr:full":"6a Miowera Rd North Turramurra NSW 2074",
    "addr:housenumber":"6a",
    "addr:postcode":"2074",
    "addr:street":"Miowera Rd",
    "iso:country":"AU",
    "sg:address":"6a Miowera Rd",
    "sg:city":"North Turramurra",
    "sg:classifiers":[
        {
            "category":"Professional",
            "subcategory":"Art Services",
            "type":"Services"
        }
    ],
    "sg:phone":"+61 2 9144 2828",
    "sg:postcode":"2074",
    "sg:province":"NSW",
    "sg:tags":[
        "graphic",
        "designer"
    ],
    "wof:name":"Visual Banquet Pty Ltd",
    "wof:placetype":"venue"
},
  "geometry": {"coordinates":[151.15013122600001,-33.7154960632],"type":"Point"}
}