{
  "type": "Feature",
  "properties": {
    "iso:country":"AU",
    "sg:address":"2/164- 166 Charters Towers Rd",
    "sg:city":"Hermit Park",
    "sg:classifiers":[
        {
            "category":"Health Services",
            "subcategory":"Chiropractor",
            "type":"Services"
        }
    ],
    "sg:phone":"+61 7 4728 3200",
    "sg:postcode":"4812",
    "sg:province":"QLD",
    "wof:name":"Back2health Chiropractic",
    "wof:placetype":"venue"
},
  "geometry": {"coordinates":[146.78904700000001,-19.289375],"type":"Point"}
}