{
  "type": "Feature",
  "properties": {
    "iso:country":"AU",
    "sg:address":"2 Kennedy Rd",
    "sg:city":"Bli Bli",
    "sg:classifiers":[
        {
            "category":"Retail",
            "subcategory":"Veterinary Services",
            "type":"Services"
        }
    ],
    "sg:phone":"+61 7 5448 5055",
    "sg:postcode":"4560",
    "sg:province":"QLD",
    "sg:tags":[
        "surgeon"
    ],
    "wof:name":"Bli Bli Veterinary Surgery",
    "wof:placetype":"venue"
},
  "geometry": {"coordinates":[153.03715515100001,-26.6189651489],"type":"Point"}
}