{
  "type": "Feature",
  "properties": {
    "iso:country":"AU",
    "sg:address":"8 Picnic Point Rd",
    "sg:city":"Revesby",
    "sg:classifiers":[
        {
            "category":"Building & Trades",
            "subcategory":"Cleaning & Sanitation",
            "type":"Services"
        }
    ],
    "sg:phone":"+61 2 9774 4038",
    "sg:postcode":"2212",
    "sg:province":"NSW",
    "sg:tags":[
        "window"
    ],
    "wof:name":"Ben's Professional Window Cleaning Service",
    "wof:placetype":"venue"
},
  "geometry": {"coordinates":[151.003082,-33.957699],"type":"Point"}
}