{
  "type": "Feature",
  "properties": {
    "addr:full":"Shp92/ 580 Botany Rd Alexandria NSW 2015",
    "addr:housenumber":"580",
    "addr:postcode":"2015",
    "addr:street":"Botany Rd",
    "iso:country":"AU",
    "sg:address":"Shp92/ 580 Botany Rd",
    "sg:city":"Alexandria",
    "sg:classifiers":[
        {
            "category":"Food & Beverages",
            "subcategory":"Groceries & Convenience Stores",
            "type":"Retail Goods"
        }
    ],
    "sg:phone":"+61 2 8338 8320",
    "sg:postcode":"2015",
    "sg:province":"NSW",
    "wof:name":"Paradise Convenience Store",
    "wof:placetype":"venue"
},
  "geometry": {"coordinates":[151.20001220699999,-33.9166564941],"type":"Point"}
}