{
  "type": "Feature",
  "properties": {
    "addr:full":"4/ 95 Drummond Rd Shepparton VIC 3630",
    "addr:housenumber":"/ 95",
    "addr:postcode":"3630",
    "addr:street":"Drummond Rd",
    "iso:country":"AU",
    "sg:address":"4/ 95 Drummond Rd",
    "sg:city":"Shepparton",
    "sg:classifiers":[
        {
            "category":"Utilities",
            "type":"Services"
        }
    ],
    "sg:phone":"+61 3 5821 4961",
    "sg:postcode":"3630",
    "sg:province":"VIC",
    "sg:tags":[
        "refrigeration",
        "industrial",
        "commercial",
        "retail"
    ],
    "wof:name":"Brett Collins Refrigeration Pty Ltd",
    "wof:placetype":"venue"
},
  "geometry": {"coordinates":[145.42314148,-36.3761024475],"type":"Point"}
}