{
  "type": "Feature",
  "properties": {
    "iso:country":"AU",
    "sg:address":"2092 Sandgate Rd",
    "sg:city":"Boondall",
    "sg:classifiers":[
        {
            "category":"Travel",
            "subcategory":"Hotels & Motels",
            "type":"Entertainment"
        }
    ],
    "sg:phone":"+61 7 3265 1722",
    "sg:postcode":"4034",
    "sg:province":"QLD",
    "wof:name":"Boondall Motel",
    "wof:placetype":"venue"
},
  "geometry": {"coordinates":[153.06062299999999,-27.355257],"type":"Point"}
}