{
  "type": "Feature",
  "properties": {
    "addr:full":"111 Gladstone Rd Highgate Hill QLD 4101",
    "addr:housenumber":"111",
    "addr:postcode":"4101",
    "addr:street":"Gladstone Rd",
    "iso:country":"AU",
    "sg:address":"111 Gladstone Rd",
    "sg:city":"Highgate Hill",
    "sg:classifiers":[
        {
            "category":"Health Services",
            "subcategory":"Doctor",
            "type":"Services"
        }
    ],
    "sg:phone":"+61 7 3844 1180",
    "sg:postcode":"4101",
    "sg:province":"QLD",
    "sg:tags":[
        "medical",
        "practitioner"
    ],
    "wof:name":"Byth Susan",
    "wof:placetype":"venue"
},
  "geometry": {"coordinates":[153.018478394,-27.4893760681],"type":"Point"}
}