{
  "type": "Feature",
  "properties": {
    "iso:country":"AU",
    "sg:address":"498a Pacific Hwy",
    "sg:city":"Boambee",
    "sg:classifiers":[
        {
            "category":"Farming",
            "subcategory":"Livestock Farm",
            "type":"Manufacturing & Wholesale Goods"
        }
    ],
    "sg:phone":"+61 2 6653 2090",
    "sg:postcode":"2450",
    "sg:province":"NSW",
    "sg:tags":[
        "agistment"
    ],
    "wof:name":"Boambee Equestrian Centre",
    "wof:placetype":"venue"
},
  "geometry": {"coordinates":[153.082062,-30.330906],"type":"Point"}
}