{
  "type": "Feature",
  "properties": {
    "iso:country":"AU",
    "sg:address":"Fountain Gate Shopping Centre, Princes Hwy",
    "sg:city":"Narre Warren",
    "sg:classifiers":[
        {
            "category":"Autos & Motor Vehicles",
            "subcategory":"Auto Supplies",
            "type":"Retail Goods"
        }
    ],
    "sg:phone":"+61 3 9744 8065",
    "sg:postcode":"3805",
    "sg:province":"VIC",
    "sg:tags":[
        "tyre"
    ],
    "wof:name":"Kmart Tyre & Auto Service Narrewarren",
    "wof:placetype":"venue"
},
  "geometry": {"coordinates":[145.301834,-38.02269],"type":"Point"}
}