{
  "type": "Feature",
  "properties": {
    "addr:full":"Unit 3/ 31 Taree St Burleigh Heads QLD 4220",
    "addr:postcode":"4220",
    "addr:street":"Taree St",
    "iso:country":"AU",
    "sg:address":"Unit 3/ 31 Taree St",
    "sg:city":"Burleigh Heads",
    "sg:classifiers":[
        {
            "category":"Shopping",
            "subcategory":"Discount & Variety Stores",
            "type":"Retail Goods"
        }
    ],
    "sg:phone":"+61 7 5593 5408",
    "sg:postcode":"4220",
    "sg:province":"QLD",
    "sg:tags":[
        "shop",
        "adult"
    ],
    "wof:name":"Everything Adult",
    "wof:placetype":"venue"
},
  "geometry": {"coordinates":[153.421707153,-28.1057929993],"type":"Point"}
}