{
  "type": "Feature",
  "properties": {
    "addr:full":"471 Varley St Yorkeys Knob QLD 4878",
    "addr:housenumber":"471",
    "addr:postcode":"4878",
    "addr:street":"Varley St",
    "iso:country":"AU",
    "sg:address":"471 Varley St",
    "sg:city":"Yorkeys Knob",
    "sg:classifiers":[
        {
            "category":"Personal",
            "subcategory":"Beauty Salon",
            "type":"Services"
        }
    ],
    "sg:phone":"+61 7 4055 7269",
    "sg:postcode":"4878",
    "sg:province":"QLD",
    "sg:tags":[
        "hairdresser"
    ],
    "wof:name":"Hair Thou Art",
    "wof:placetype":"venue"
},
  "geometry": {"coordinates":[145.720825195,-16.8108577728],"type":"Point"}
}