{
  "type": "Feature",
  "properties": {
    "iso:country":"AU",
    "sg:address":"PO Box 246",
    "sg:city":"Southtown",
    "sg:classifiers":[
        {
            "category":"Real Estate",
            "subcategory":"Real Estate Agent",
            "type":"Services"
        }
    ],
    "sg:phone":"+61 7 4613 4688",
    "sg:postcode":"4350",
    "sg:province":"QLD",
    "wof:name":"Real Estate Property Sales",
    "wof:placetype":"venue"
},
  "geometry": {"coordinates":[151.875641,-27.55761],"type":"Point"}
}