{
  "type": "Feature",
  "properties": {
    "iso:country":"AU",
    "sg:address":"19 Irrubel Rd",
    "sg:city":"Newport Beach",
    "sg:classifiers":[
        {
            "category":"Building & Trades",
            "subcategory":"Construction",
            "type":"Services"
        }
    ],
    "sg:phone":"+61 409 054 265",
    "sg:postcode":"2106",
    "sg:province":"NSW",
    "sg:tags":[
        "contractor"
    ],
    "wof:name":"Price R J",
    "wof:placetype":"venue"
},
  "geometry": {"coordinates":[151.314285278,-33.6553878784],"type":"Point"}
}