{
  "type": "Feature",
  "properties": {
    "addr:full":"35 Tanah Merah Ave Tanah Merah QLD 4128",
    "addr:postcode":"4128",
    "addr:street":"Tanah Merah Ave",
    "iso:country":"AU",
    "sg:address":"35 Tanah Merah Ave",
    "sg:city":"Tanah Merah",
    "sg:classifiers":[
        {
            "category":"Professional",
            "subcategory":"Art Services",
            "type":"Services"
        }
    ],
    "sg:phone":"+61 412 053 864",
    "sg:postcode":"4128",
    "sg:province":"QLD",
    "sg:tags":[
        "decorator",
        "painter"
    ],
    "wof:name":"Avenbury Pty Ltd",
    "wof:placetype":"venue"
},
  "geometry": {"coordinates":[153.168411255,-27.6672744751],"type":"Point"}
}