{
  "type": "Feature",
  "properties": {
    "iso:country":"AU",
    "sg:address":"56 The Entrance Rd",
    "sg:city":"The Entrance",
    "sg:classifiers":[
        {
            "category":"Shopping",
            "subcategory":"Clothing, Apparel, & Fashions",
            "type":"Retail Goods"
        }
    ],
    "sg:phone":"+61 2 4332 2529",
    "sg:postcode":"2261",
    "sg:province":"NSW",
    "sg:tags":[
        "lady",
        "wear"
    ],
    "wof:name":"Riviera Frocks & Sportswear",
    "wof:placetype":"venue"
},
  "geometry": {"coordinates":[151.49693300000001,-33.344193],"type":"Point"}
}