{
  "type": "Feature",
  "properties": {
    "addr:full":"175a Stephen St Yarraville VIC 3013",
    "addr:housenumber":"175a",
    "addr:postcode":"3013",
    "addr:street":"Stephen St",
    "iso:country":"AU",
    "sg:address":"175a Stephen St",
    "sg:city":"Yarraville",
    "sg:classifiers":[
        {
            "category":"Retail",
            "subcategory":"Auto Repair",
            "type":"Services"
        }
    ],
    "sg:phone":"+61 3 9362 0266",
    "sg:postcode":"3013",
    "sg:province":"VIC",
    "sg:tags":[
        "sport",
        "motor"
    ],
    "wof:name":"Total Performance",
    "wof:placetype":"venue"
},
  "geometry": {"coordinates":[144.89378356899999,-37.8204193115],"type":"Point"}
}