{
  "type": "Feature",
  "properties": {
    "addr:full":"6/ 411 Equity Pl Canley Vale NSW 2166",
    "addr:housenumber":"/ 411",
    "addr:postcode":"2166",
    "addr:street":"Equity Pl",
    "iso:country":"AU",
    "sg:address":"6/ 411 Equity Pl",
    "sg:city":"Canley Vale",
    "sg:classifiers":[
        {
            "category":"Building & Trades",
            "subcategory":"Construction",
            "type":"Services"
        }
    ],
    "sg:phone":"+61 2 9726 2315",
    "sg:postcode":"2166",
    "sg:province":"NSW",
    "sg:tags":[
        "ceiling"
    ],
    "wof:name":"McKail Ceilings",
    "wof:placetype":"venue"
},
  "geometry": {"coordinates":[150.93734741200001,-33.8889770508],"type":"Point"}
}