{
  "type": "Feature",
  "properties": {
    "addr:full":"701 Burbridge Rd West Beach SA 5024",
    "addr:housenumber":"701",
    "addr:postcode":"5024",
    "addr:street":"Burbridge Rd",
    "iso:country":"AU",
    "sg:address":"701 Burbridge Rd",
    "sg:city":"West Beach",
    "sg:classifiers":[
        {
            "category":"Shopping",
            "subcategory":"Shoes",
            "type":"Retail Goods"
        }
    ],
    "sg:phone":"+61 8 8355 0622",
    "sg:postcode":"5024",
    "sg:province":"SA",
    "sg:tags":[
        "footwear"
    ],
    "wof:name":"Lisa Jane Comfort Shoes",
    "wof:placetype":"venue"
},
  "geometry": {"coordinates":[138.50309753400001,-34.9373970032],"type":"Point"}
}