{
  "type": "Feature",
  "properties": {
    "iso:country":"AU",
    "sg:address":"583 Canning Hwy",
    "sg:city":"Alfred Cove",
    "sg:classifiers":[
        {
            "category":"Fast Food",
            "type":"Food & Drink"
        }
    ],
    "sg:phone":"+61 8 9330 5935",
    "sg:postcode":"6154",
    "sg:province":"WA",
    "sg:tags":[
        "away",
        "take"
    ],
    "wof:name":"Mai Thai Restaurant",
    "wof:placetype":"venue"
},
  "geometry": {"coordinates":[115.81471999999999,-32.031265],"type":"Point"}
}