{
  "type": "Feature",
  "properties": {
    "iso:country":"AU",
    "sg:address":"30 Bronte Rd",
    "sg:city":"Bondi Junction",
    "sg:classifiers":[
        {
            "category":"Health Services",
            "subcategory":"Dentist",
            "type":"Services"
        }
    ],
    "sg:phone":"+61 2 9369 2323",
    "sg:postcode":"2022",
    "sg:province":"NSW",
    "sg:tags":[
        "technician",
        "dental"
    ],
    "wof:name":"Ken Lloyd",
    "wof:placetype":"venue"
},
  "geometry": {"coordinates":[151.249725342,-33.8933753967],"type":"Point"}
}