{
  "type": "Feature",
  "properties": {
    "addr:full":"Unit 2/ 28 Firebrick Drv Thornton NSW 2322",
    "addr:postcode":"2322",
    "addr:street":"28 Firebrick Drv",
    "iso:country":"AU",
    "sg:address":"Unit 2/ 28 Firebrick Drv",
    "sg:city":"Thornton",
    "sg:classifiers":[
        {
            "category":"Professional",
            "type":"Services"
        }
    ],
    "sg:phone":"+61 2 4964 2239",
    "sg:postcode":"2322",
    "sg:province":"NSW",
    "sg:tags":[
        "control",
        "equipment",
        "traffic"
    ],
    "wof:name":"Statewide Traffic Control",
    "wof:placetype":"venue"
},
  "geometry": {"coordinates":[151.63351440400001,-32.7854118347],"type":"Point"}
}