{
  "type": "Feature",
  "properties": {
    "iso:country":"AU",
    "sg:address":"123 Eagleview Rd",
    "sg:city":"Minto",
    "sg:classifiers":[
        {
            "category":"Building & Trades",
            "subcategory":"Construction",
            "type":"Services"
        }
    ],
    "sg:phone":"+61 418 205 295",
    "sg:postcode":"2566",
    "sg:province":"NSW",
    "sg:tags":[
        "home",
        "air conditioning"
    ],
    "wof:name":"Jay's Air Conditioning & Ventilation Pty Ltd",
    "wof:placetype":"venue"
},
  "geometry": {"coordinates":[150.861526489,-34.0296707153],"type":"Point"}
}