{
  "type": "Feature",
  "properties": {
    "addr:full":"77 Stanbel Rd Salisbury Plain SA 5109",
    "addr:housenumber":"77",
    "addr:postcode":"5109",
    "addr:street":"Stanbel Rd",
    "iso:country":"AU",
    "sg:address":"77 Stanbel Rd",
    "sg:city":"Salisbury Plain",
    "sg:classifiers":[
        {
            "category":"Manufacturing",
            "subcategory":"Motor Vehicles & Parts",
            "type":"Manufacturing & Wholesale Goods"
        }
    ],
    "sg:phone":"+61 8 8258 9611",
    "sg:postcode":"5109",
    "sg:province":"SA",
    "sg:tags":[
        "replacement"
    ],
    "wof:name":"FAL-COM AUTO DISMANTLERS",
    "wof:placetype":"venue"
},
  "geometry": {"coordinates":[138.66317749000001,-34.7718696594],"type":"Point"}
}