{
  "type": "Feature",
  "properties": {
    "addr:full":"70 Frederick St Albany WA 6330",
    "addr:housenumber":"70",
    "addr:postcode":"6330",
    "addr:street":"Frederick St",
    "iso:country":"AU",
    "sg:address":"70 Frederick St",
    "sg:city":"Albany",
    "sg:classifiers":[
        {
            "category":"Banks & Credit Unions",
            "subcategory":"Financial Services",
            "type":"Services"
        }
    ],
    "sg:phone":"+61 8 9841 5100",
    "sg:postcode":"6330",
    "sg:province":"WA",
    "sg:tags":[
        "financier"
    ],
    "wof:name":"Albany Finance Ltd",
    "wof:placetype":"venue"
},
  "geometry": {"coordinates":[117.885719299,-35.0259056091],"type":"Point"}
}