{
  "type": "Feature",
  "properties": {
    "iso:country":"AU",
    "sg:address":"1/ 6 Tardard Drv",
    "sg:city":"Braeside",
    "sg:classifiers":[
        {
            "category":"Building & Trades",
            "subcategory":"Equipment Rental",
            "type":"Services"
        }
    ],
    "sg:phone":"+61 418 559 788",
    "sg:postcode":"3195",
    "sg:province":"VIC",
    "sg:tags":[
        "fitness"
    ],
    "wof:name":"Gymrepairs Australia Pty Ltd",
    "wof:placetype":"venue"
},
  "geometry": {"coordinates":[145.11102294899999,-37.9892272949],"type":"Point"}
}