{
  "type": "Feature",
  "properties": {
    "iso:country":"AU",
    "sg:address":"ShpFC3/ 217 Auburn St",
    "sg:city":"Goulburn",
    "sg:classifiers":[
        {
            "category":"Fast Food",
            "type":"Food & Drink"
        }
    ],
    "sg:phone":"+61 2 4823 6610",
    "sg:postcode":"2580",
    "sg:province":"NSW",
    "sg:tags":[
        "away",
        "take"
    ],
    "wof:name":"Ali Baba Lebanese Cuisine Pty Ltd",
    "wof:placetype":"venue"
},
  "geometry": {"coordinates":[149.720336914,-34.7525749207],"type":"Point"}
}