{
  "type": "Feature",
  "properties": {
    "addr:full":"288 York Street Sale VIC 3850",
    "addr:housenumber":"288",
    "addr:postcode":"3850",
    "addr:street":"York Street",
    "iso:country":"AU",
    "sg:address":"288 York Street",
    "sg:city":"Sale",
    "sg:classifiers":[
        {
            "category":"Banks & Credit Unions",
            "subcategory":"Bank",
            "type":"Services"
        }
    ],
    "sg:phone":"+61 3 5144 5988",
    "sg:postcode":"3850",
    "sg:province":"VIC",
    "sg:tags":[
        "castor"
    ],
    "wof:name":"Gippsland Bearing Supplies Pty Ltd",
    "wof:placetype":"venue"
},
  "geometry": {"coordinates":[147.06825256400001,-38.1034088135],"type":"Point"}
}