{
  "type": "Feature",
  "properties": {
    "addr:full":"130 New Town Rd New Town TAS 7008",
    "addr:housenumber":"130",
    "addr:postcode":"7008",
    "addr:street":"New Town Rd",
    "iso:country":"AU",
    "sg:address":"130 New Town Rd",
    "sg:city":"New Town",
    "sg:classifiers":[
        {
            "category":"Health Services",
            "subcategory":"Dentist",
            "type":"Services"
        }
    ],
    "sg:phone":"+61 3 6278 2844",
    "sg:postcode":"7008",
    "sg:province":"TAS",
    "wof:name":"Cai B J",
    "wof:placetype":"venue"
},
  "geometry": {"coordinates":[147.30743408199999,-42.8604545593],"type":"Point"}
}