{
  "type": "Feature",
  "properties": {
    "addr:full":"Robert St Urangan QLD 4655",
    "addr:postcode":"4655",
    "addr:street":"Robert St",
    "iso:country":"AU",
    "sg:address":"Robert St",
    "sg:city":"Urangan",
    "sg:classifiers":[
        {
            "category":"Education",
            "subcategory":"School",
            "type":"Public Place"
        }
    ],
    "sg:phone":"+61 7 4197 0111",
    "sg:postcode":"4655",
    "sg:province":"QLD",
    "sg:tags":[
        "state",
        "except",
        "nsw"
    ],
    "wof:name":"Urangan High School",
    "wof:placetype":"venue"
},
  "geometry": {"coordinates":[152.877197,-25.288296],"type":"Point"}
}