{
  "type": "Feature",
  "properties": {
    "addr:full":"PO Box 5765 South Windsor NSW 2756",
    "addr:postcode":"2756",
    "iso:country":"AU",
    "sg:address":"PO Box 5765",
    "sg:city":"South Windsor",
    "sg:phone":"+61 1800 509 237",
    "sg:postcode":"2756",
    "sg:province":"NSW",
    "wof:name":"D & G Perfection Tanks Pty Ltd",
    "wof:placetype":"venue"
},
  "geometry": {"coordinates":[150.804412842,-33.621761322],"type":"Point"}
}