{
  "type": "Feature",
  "properties": {
    "addr:full":"371 Somerville Rd Footscray West VIC 3012",
    "addr:housenumber":"371",
    "addr:postcode":"3012",
    "addr:street":"Somerville Rd",
    "iso:country":"AU",
    "sg:address":"371 Somerville Rd",
    "sg:city":"Footscray West",
    "sg:classifiers":[
        {
            "category":"Wholesale",
            "subcategory":"Machinery & Supplies",
            "type":"Manufacturing & Wholesale Goods"
        }
    ],
    "sg:phone":"+61 3 9315 1655",
    "sg:postcode":"3012",
    "sg:province":"VIC",
    "sg:tags":[
        "engineer"
    ],
    "wof:name":"A.E. Baker & Co",
    "wof:placetype":"venue"
},
  "geometry": {"coordinates":[144.86578369099999,-37.8108940125],"type":"Point"}
}