{
  "type": "Feature",
  "properties": {
    "addr:full":"Suite 3/ 872 Beaufort St Inglewood WA 6052",
    "addr:housenumber":"/ 872",
    "addr:postcode":"6052",
    "addr:street":"Beaufort St",
    "iso:country":"AU",
    "sg:address":"Suite 3/ 872 Beaufort St",
    "sg:city":"Inglewood",
    "sg:classifiers":[
        {
            "category":"Banks & Credit Unions",
            "subcategory":"Bank",
            "type":"Services"
        }
    ],
    "sg:phone":"+61 1800 180 800",
    "sg:postcode":"6052",
    "sg:province":"WA",
    "sg:tags":[
        "broker",
        "mortgage"
    ],
    "wof:name":"Mortgage Australia",
    "wof:placetype":"venue"
},
  "geometry": {"coordinates":[115.88513946499999,-31.9222221375],"type":"Point"}
}