{
  "type": "Feature",
  "properties": {
    "addr:full":"24 Negara Crs Glenorchy TAS 7010",
    "addr:housenumber":"24",
    "addr:postcode":"7010",
    "addr:street":"Negara Crs",
    "iso:country":"AU",
    "sg:address":"24 Negara Crs",
    "sg:city":"Glenorchy",
    "sg:classifiers":[
        {
            "category":"Autos & Motor Vehicles",
            "subcategory":"Boat Sales",
            "type":"Retail Goods"
        }
    ],
    "sg:phone":"+61 3 6273 0090",
    "sg:postcode":"7010",
    "sg:province":"TAS",
    "sg:tags":[
        "builder",
        "yacht",
        "repairer"
    ],
    "wof:name":"Derwent Marine",
    "wof:placetype":"venue"
},
  "geometry": {"coordinates":[147.279754639,-42.8336982727],"type":"Point"}
}