{
  "type": "Feature",
  "properties": {
    "addr:full":"2/ 34 North St Hectorville SA 5073",
    "addr:housenumber":"/ 34",
    "addr:postcode":"5073",
    "addr:street":"North St",
    "iso:country":"AU",
    "sg:address":"2/ 34 North St",
    "sg:city":"Hectorville",
    "sg:classifiers":[
        {
            "category":"Social Services",
            "subcategory":"Job Training",
            "type":"Services"
        }
    ],
    "sg:phone":"+61 404 049 845",
    "sg:postcode":"5073",
    "sg:province":"SA",
    "sg:tags":[
        "sport"
    ],
    "wof:name":"Strategic Fit",
    "wof:placetype":"venue"
},
  "geometry": {"coordinates":[138.66110229500001,-34.8909912109],"type":"Point"}
}