{
  "type": "Feature",
  "properties": {
    "addr:full":"18 Berry St Churchill QLD 4305",
    "addr:housenumber":"18",
    "addr:postcode":"4305",
    "addr:street":"Berry St",
    "iso:country":"AU",
    "sg:address":"18 Berry St",
    "sg:city":"Churchill",
    "sg:classifiers":[
        {
            "category":"Education",
            "subcategory":"Vocational School",
            "type":"Public Place"
        }
    ],
    "sg:phone":"+61 7 3281 9215",
    "sg:postcode":"4305",
    "sg:province":"QLD",
    "sg:tags":[
        "cake",
        "decorating",
        "decorator"
    ],
    "wof:name":"Pauline Herrmann",
    "wof:placetype":"venue"
},
  "geometry": {"coordinates":[152.748443603,-27.644449234],"type":"Point"}
}