{
  "type": "Feature",
  "properties": {
    "iso:country":"AU",
    "sg:address":"275 Port Rd",
    "sg:city":"Hindmarsh",
    "sg:classifiers":[
        {
            "category":"Health Services",
            "subcategory":"Doctor",
            "type":"Services"
        }
    ],
    "sg:phone":"+61 8 8340 2233",
    "sg:postcode":"5007",
    "sg:province":"SA",
    "sg:tags":[
        "medical",
        "practitioner"
    ],
    "wof:name":"Hurn M Dr",
    "wof:placetype":"venue"
},
  "geometry": {"coordinates":[138.56950378400001,-34.9031448364],"type":"Point"}
}