{
  "type": "Feature",
  "properties": {
    "iso:country":"AU",
    "sg:address":"Kosciusko Rd",
    "sg:city":"Smiggin Holes",
    "sg:classifiers":[
        {
            "category":"Sports & Exercise",
            "subcategory":"Ski Resort",
            "type":"Entertainment"
        }
    ],
    "sg:phone":"+61 2 6457 5375",
    "sg:postcode":"2624",
    "sg:province":"NSW",
    "sg:tags":[
        "tour",
        "centres"
    ],
    "wof:name":"Smiggins Hotel & Chalet Apartments",
    "wof:placetype":"venue"
},
  "geometry": {"coordinates":[148.45280456500001,-36.3844947815],"type":"Point"}
}