{
  "type": "Feature",
  "properties": {
    "iso:country":"AU",
    "sg:address":"Blackdog Drv",
    "sg:city":"Melton South",
    "sg:classifiers":[
        {
            "category":"Social Services",
            "subcategory":"Child Care",
            "type":"Services"
        }
    ],
    "sg:phone":"+61 3 9747 8150",
    "sg:postcode":"3338",
    "sg:province":"VIC",
    "sg:tags":[
        "support",
        "health"
    ],
    "wof:name":"Maternal & Child Health Centres",
    "wof:placetype":"venue"
},
  "geometry": {"coordinates":[144.56544500000001,-37.695126],"type":"Point"}
}