{
  "type": "Feature",
  "properties": {
    "addr:full":"170 King St Westbury TAS 7303",
    "addr:housenumber":"170",
    "addr:postcode":"7303",
    "addr:street":"King St",
    "iso:country":"AU",
    "sg:address":"170 King St",
    "sg:city":"Westbury",
    "sg:classifiers":[
        {
            "category":"Food & Beverages",
            "subcategory":"Bakery",
            "type":"Retail Goods"
        }
    ],
    "sg:phone":"+61 3 6393 1067",
    "sg:postcode":"7303",
    "sg:province":"TAS",
    "sg:tags":[
        "baker"
    ],
    "wof:name":"Whitehouse Bakery",
    "wof:placetype":"venue"
},
  "geometry": {"coordinates":[146.82914700000001,-41.52953],"type":"Point"}
}