{
  "type": "Feature",
  "properties": {
    "addr:full":"PO Box 31 Glenbrook NSW 2773",
    "addr:postcode":"2773",
    "iso:country":"AU",
    "sg:address":"PO Box 31",
    "sg:city":"Glenbrook",
    "sg:classifiers":[
        {
            "category":"Building & Trades",
            "subcategory":"Construction",
            "type":"Services"
        }
    ],
    "sg:phone":"+61 2 4739 0777",
    "sg:postcode":"2773",
    "sg:province":"NSW",
    "sg:tags":[
        "contractor"
    ],
    "wof:name":"Hotondo Sydney Builders",
    "wof:placetype":"venue"
},
  "geometry": {"coordinates":[150.621170044,-33.7665481567],"type":"Point"}
}