{
  "type": "Feature",
  "properties": {
    "addr:full":"80 Station St Somerville VIC 3912",
    "addr:housenumber":"80",
    "addr:postcode":"3912",
    "addr:street":"Station St",
    "iso:country":"AU",
    "sg:address":"80 Station St",
    "sg:city":"Somerville",
    "sg:classifiers":[
        {
            "category":"Home & Garden",
            "subcategory":"Household Appliances",
            "type":"Retail Goods"
        }
    ],
    "sg:phone":"+61 3 5977 5789",
    "sg:postcode":"3912",
    "sg:province":"VIC",
    "sg:tags":[
        "equipment",
        "gas"
    ],
    "wof:name":"Natural & L.P. Gas Service Pty. Ltd.",
    "wof:placetype":"venue"
},
  "geometry": {"coordinates":[145.17498779300001,-38.2247085571],"type":"Point"}
}