{
  "type": "Feature",
  "properties": {
    "iso:country":"AU",
    "sg:address":"Cardwell St",
    "sg:city":"Arakoon",
    "sg:classifiers":[
        {
            "category":"Communications",
            "subcategory":"News Services",
            "type":"Services"
        }
    ],
    "sg:phone":"+61 2 6566 6168",
    "sg:postcode":"2431",
    "sg:province":"NSW",
    "sg:tags":[
        "information",
        "tourist",
        "attractions"
    ],
    "wof:name":"Arakoon State Conservation Area",
    "wof:placetype":"venue"
},
  "geometry": {"coordinates":[153.070724,-30.885241],"type":"Point"}
}