{
  "type": "Feature",
  "properties": {
    "addr:full":"587 Gilbert Rd Preston VIC 3072",
    "addr:housenumber":"587",
    "addr:postcode":"3072",
    "addr:street":"Gilbert Rd",
    "iso:country":"AU",
    "sg:address":"587 Gilbert Rd",
    "sg:city":"Preston",
    "sg:classifiers":[
        {
            "category":"Professional",
            "subcategory":"Art Services",
            "type":"Services"
        }
    ],
    "sg:phone":"+61 3 9470 2933",
    "sg:postcode":"3072",
    "sg:province":"VIC",
    "sg:tags":[
        "interior",
        "decorator"
    ],
    "wof:name":"Total Furnishing Solutions",
    "wof:placetype":"venue"
},
  "geometry": {"coordinates":[144.991333008,-37.7292175293],"type":"Point"}
}