{
  "type": "Feature",
  "properties": {
    "addr:full":"780 Old Calder Hwy Keilor VIC 3036",
    "addr:housenumber":"780",
    "addr:postcode":"3036",
    "addr:street":"Old Calder Hwy",
    "iso:country":"AU",
    "sg:address":"780 Old Calder Hwy",
    "sg:city":"Keilor",
    "sg:classifiers":[
        {
            "category":"Utilities",
            "subcategory":"Natural Gas",
            "type":"Services"
        }
    ],
    "sg:phone":"+61 411 407 718",
    "sg:postcode":"3036",
    "sg:province":"VIC",
    "sg:tags":[
        "solid",
        "plasterer"
    ],
    "wof:name":"Finishing Coats Solid Plastering",
    "wof:placetype":"venue"
},
  "geometry": {"coordinates":[144.82257100000001,-37.71143],"type":"Point"}
}