{
  "type": "Feature",
  "properties": {
    "addr:full":"PO Box 1126 Capalaba QLD 4157",
    "addr:postcode":"4157",
    "iso:country":"AU",
    "sg:address":"PO Box 1126",
    "sg:city":"Capalaba",
    "sg:classifiers":[
        {
            "category":"Structure",
            "subcategory":"Office Building",
            "type":"Public Place"
        }
    ],
    "sg:phone":"+61 7 3245 6726",
    "sg:postcode":"4157",
    "sg:province":"QLD",
    "sg:tags":[
        "fire",
        "window",
        "door"
    ],
    "wof:name":"All Door Solutions Pty Ltd",
    "wof:placetype":"venue"
},
  "geometry": {"coordinates":[153.201080322,-27.5341873169],"type":"Point"}
}