{
  "type": "Feature",
  "properties": {
    "addr:full":"Lot 2889 Pemberton Way Karratha WA 6714",
    "addr:housenumber":"2889",
    "addr:postcode":"6714",
    "addr:street":"Pemberton Way",
    "iso:country":"AU",
    "sg:address":"Lot 2889 Pemberton Way",
    "sg:city":"Karratha",
    "sg:classifiers":[
        {
            "category":"Mining & Drilling",
            "type":"Manufacturing & Wholesale Goods"
        }
    ],
    "sg:phone":"+61 8 9185 2727",
    "sg:postcode":"6714",
    "sg:province":"WA",
    "sg:tags":[
        "equipment",
        "quarrying",
        "supply"
    ],
    "wof:name":"North West Laser Alignment",
    "wof:placetype":"venue"
},
  "geometry": {"coordinates":[116.881797791,-20.7654857635],"type":"Point"}
}