{
  "type": "Feature",
  "properties": {
    "iso:country":"AU",
    "sg:address":"5-7 Rohini St",
    "sg:city":"Turramurra",
    "sg:classifiers":[
        {
            "category":"Sports & Exercise",
            "subcategory":"Gym",
            "type":"Entertainment"
        }
    ],
    "sg:phone":"+61 2 9440 7130",
    "sg:postcode":"2074",
    "sg:province":"NSW",
    "sg:tags":[
        "pilate",
        "method"
    ],
    "wof:name":"Pilates International Turramurra",
    "wof:placetype":"venue"
},
  "geometry": {"coordinates":[151.12971496599999,-33.7328567505],"type":"Point"}
}