{
  "type": "Feature",
  "properties": {
    "addr:full":"11 Runyon Rd Midvale WA 6056",
    "addr:housenumber":"11",
    "addr:postcode":"6056",
    "addr:street":"Runyon Rd",
    "iso:country":"AU",
    "sg:address":"11 Runyon Rd",
    "sg:city":"Midvale",
    "sg:classifiers":[
        {
            "category":"Retail",
            "subcategory":"Auto Repair",
            "type":"Services"
        }
    ],
    "sg:phone":"+61 8 9250 8574",
    "sg:postcode":"6056",
    "sg:province":"WA",
    "sg:tags":[
        "gas",
        "conversion",
        "natural",
        "lp",
        "vehicle"
    ],
    "wof:name":"Rage LPG Racing",
    "wof:placetype":"venue"
},
  "geometry": {"coordinates":[116.034919739,-31.8949146271],"type":"Point"}
}