{
  "type": "Feature",
  "properties": {
    "addr:full":"Lot 15 Almond St Wilton NSW 2571",
    "addr:housenumber":"15",
    "addr:postcode":"2571",
    "addr:street":"Almond St",
    "iso:country":"AU",
    "sg:address":"Lot 15 Almond St",
    "sg:city":"Wilton",
    "sg:classifiers":[
        {
            "category":"Professional",
            "subcategory":"Engineering",
            "type":"Services"
        }
    ],
    "sg:phone":"+61 2 4630 9161",
    "sg:postcode":"2571",
    "sg:province":"NSW",
    "sg:tags":[
        "diesel",
        "engineer"
    ],
    "wof:name":"Fitzsimmons Diesel",
    "wof:placetype":"venue"
},
  "geometry": {"coordinates":[150.69801330600001,-34.2320098877],"type":"Point"}
}