{
  "type": "Feature",
  "properties": {
    "iso:country":"AU",
    "sg:address":"Suite 21 Forest Lakes Shopng Cntr",
    "sg:city":"Thornlie",
    "sg:classifiers":[
        {
            "category":"Real Estate",
            "subcategory":"Real Estate Agent",
            "type":"Services"
        }
    ],
    "sg:phone":"+61 8 9459 9000",
    "sg:postcode":"6108",
    "sg:province":"WA",
    "wof:name":"The Professionals",
    "wof:placetype":"venue"
},
  "geometry": {"coordinates":[115.949829102,-32.0704727173],"type":"Point"}
}