{
  "type": "Feature",
  "properties": {
    "addr:full":"3 White St Williamstown VIC 3016",
    "addr:housenumber":"3",
    "addr:postcode":"3016",
    "addr:street":"White St",
    "iso:country":"AU",
    "sg:address":"3 White St",
    "sg:city":"Williamstown",
    "sg:classifiers":[
        {
            "category":"Government",
            "subcategory":"Court House",
            "type":"Public Place"
        }
    ],
    "sg:phone":"+61 3 9397 5962",
    "sg:postcode":"3016",
    "sg:province":"VIC",
    "sg:tags":[
        "personal",
        "marriage",
        "family",
        "counselling"
    ],
    "wof:name":"Santosha Health - Learn To Relax",
    "wof:placetype":"venue"
},
  "geometry": {"coordinates":[144.89068603499999,-37.8519058228],"type":"Point"}
}