{
  "type": "Feature",
  "properties": {
    "addr:full":"745 Nambour-Mapleton Rd Kureelpa QLD 4560",
    "addr:housenumber":"745",
    "addr:postcode":"4560",
    "addr:street":"Nambour-Mapleton Rd",
    "iso:country":"AU",
    "sg:address":"745 Nambour-Mapleton Rd",
    "sg:city":"Kureelpa",
    "sg:classifiers":[
        {
            "category":"Professional",
            "subcategory":"Art Services",
            "type":"Services"
        }
    ],
    "sg:phone":"+61 7 5445 7007",
    "sg:postcode":"4560",
    "sg:province":"QLD",
    "sg:tags":[
        "picture",
        "frame",
        "framing"
    ],
    "wof:name":"Prime Picture Framing",
    "wof:placetype":"venue"
},
  "geometry": {"coordinates":[152.883636475,-26.6201133728],"type":"Point"}
}