{
  "type": "Feature",
  "properties": {
    "addr:full":"739 Progress Rd Wacol QLD 4076",
    "addr:housenumber":"739",
    "addr:postcode":"4076",
    "addr:street":"Progress Rd",
    "iso:country":"AU",
    "sg:address":"739 Progress Rd",
    "sg:city":"Wacol",
    "sg:classifiers":[
        {
            "category":"Shopping",
            "subcategory":"Discount & Variety Stores",
            "type":"Retail Goods"
        }
    ],
    "sg:phone":"+61 7 3879 3838",
    "sg:postcode":"4076",
    "sg:province":"QLD",
    "sg:tags":[
        "dangerous",
        "storage"
    ],
    "wof:name":"Dangerous Goods Logistics",
    "wof:placetype":"venue"
},
  "geometry": {"coordinates":[152.92967224099999,-27.5904598236],"type":"Point"}
}