{
  "type": "Feature",
  "properties": {
    "addr:full":"38 Blossom Drv Doveton VIC 3177",
    "addr:housenumber":"38",
    "addr:postcode":"3177",
    "addr:street":"Blossom Drv",
    "iso:country":"AU",
    "sg:address":"38 Blossom Drv",
    "sg:city":"Doveton",
    "sg:classifiers":[
        {
            "category":"Landmark",
            "subcategory":"Scenic View",
            "type":"Public Place"
        }
    ],
    "sg:phone":"+61 3 9791 3317",
    "sg:postcode":"3177",
    "sg:province":"VIC",
    "sg:tags":[
        "staircase",
        "handrail"
    ],
    "wof:name":"Balustrading Quotation & Installation",
    "wof:placetype":"venue"
},
  "geometry": {"coordinates":[145.231765747,-37.9906425476],"type":"Point"}
}