{
  "type": "Feature",
  "properties": {
    "addr:full":"Shop 5/ 65 Burelli St Wollongong NSW 2500",
    "addr:housenumber":"shop 5 / 65",
    "addr:postcode":"2500",
    "addr:street":"Burelli St",
    "iso:country":"AU",
    "sg:address":"Shop 5/ 65 Burelli St",
    "sg:city":"Wollongong",
    "sg:classifiers":[
        {
            "category":"Cafe",
            "type":"Food & Drink"
        }
    ],
    "sg:phone":"+61 2 4228 1611",
    "sg:postcode":"2500",
    "sg:province":"NSW",
    "wof:name":"Cafe Burelli & Internet",
    "wof:placetype":"venue"
},
  "geometry": {"coordinates":[150.895355,-34.426472],"type":"Point"}
}