{
  "type": "Feature",
  "properties": {
    "addr:full":"Level 13 276 Pitt St Sydney NSW 2000",
    "addr:housenumber":"276",
    "addr:postcode":"2000",
    "addr:street":"Pitt St",
    "iso:country":"AU",
    "sg:address":"Level 13 276 Pitt St",
    "sg:city":"Sydney",
    "sg:classifiers":[
        {
            "category":"Wholesale",
            "subcategory":"Medical Equipment & Supplies",
            "type":"Manufacturing & Wholesale Goods"
        }
    ],
    "sg:phone":"+61 2 9264 7533",
    "sg:postcode":"2000",
    "sg:province":"NSW",
    "sg:tags":[
        "dental"
    ],
    "wof:name":"Precious Dental Alloys (Aust) Pty Ltd",
    "wof:placetype":"venue"
},
  "geometry": {"coordinates":[151.20820617699999,-33.8738594055],"type":"Point"}
}