{
  "type": "Feature",
  "properties": {
    "addr:full":"Shop 3 Mitchell Plz East Maitland NSW 2323",
    "addr:housenumber":"shop 3",
    "addr:postcode":"2323",
    "addr:street":"Mitchell Plz",
    "iso:country":"AU",
    "sg:address":"Shop 3",
    "sg:city":"Mitchell Plz East Maitland",
    "sg:classifiers":[
        {
            "category":"Professional",
            "subcategory":"Employment Agencies",
            "type":"Services"
        }
    ],
    "sg:phone":"+61 2 4934 2952",
    "sg:postcode":"2323",
    "sg:province":"NSW",
    "sg:tags":[
        "provider",
        "internet"
    ],
    "wof:name":"Netcentral",
    "wof:placetype":"venue"
},
  "geometry": {"coordinates":[151.59182739299999,-32.7603645325],"type":"Point"}
}