{
  "type": "Feature",
  "properties": {
    "iso:country":"AU",
    "sg:address":"17 Stephen St",
    "sg:city":"Belmont",
    "sg:classifiers":[
        {
            "category":"Personal",
            "subcategory":"Beauty Salon",
            "type":"Services"
        }
    ],
    "sg:phone":"+61 3 5243 9607",
    "sg:postcode":"3216",
    "sg:province":"VIC",
    "sg:tags":[
        "hairdresser"
    ],
    "wof:name":"Koko's Hairdressing",
    "wof:placetype":"venue"
},
  "geometry": {"coordinates":[144.327850342,-38.1815910339],"type":"Point"}
}