{
  "type": "Feature",
  "properties": {
    "addr:full":"1/ 1142 Gold Coast Hwy Palm Beach QLD 4221",
    "addr:housenumber":"/ 1142",
    "addr:postcode":"4221",
    "addr:street":"Gold Coast Hwy",
    "iso:country":"AU",
    "sg:address":"1/ 1142 Gold Coast Hwy",
    "sg:city":"Palm Beach",
    "sg:classifiers":[
        {
            "category":"Personal",
            "subcategory":"Tanning Parlor",
            "type":"Services"
        }
    ],
    "sg:phone":"+61 7 5525 0243",
    "sg:postcode":"4221",
    "sg:province":"QLD",
    "sg:tags":[
        "solarium"
    ],
    "wof:name":"A Touch Of Bronze",
    "wof:placetype":"venue"
},
  "geometry": {"coordinates":[153.47201538100001,-28.1203479767],"type":"Point"}
}