{
  "type": "Feature",
  "properties": {
    "iso:country":"AU",
    "sg:address":"35 Furniss Rd",
    "sg:city":"Darch",
    "sg:classifiers":[
        {
            "category":"Professional",
            "subcategory":"Engineering",
            "type":"Services"
        }
    ],
    "sg:phone":"+61 8 9302 1076",
    "sg:postcode":"6065",
    "sg:province":"WA",
    "sg:tags":[
        "engineer"
    ],
    "wof:name":"Procam Cnc Routers",
    "wof:placetype":"venue"
},
  "geometry": {"coordinates":[115.845428467,-31.8049354553],"type":"Point"}
}