{
  "type": "Feature",
  "properties": {
    "addr:full":"Cranbourne Rd Cranbourne VIC 3977",
    "addr:postcode":"3977",
    "addr:street":"Cranbourne Rd",
    "iso:country":"AU",
    "sg:address":"Cranbourne Rd",
    "sg:city":"Cranbourne",
    "sg:classifiers":[
        {
            "category":"Professional",
            "subcategory":"Art Services",
            "type":"Services"
        }
    ],
    "sg:phone":"+61 425 739 406",
    "sg:postcode":"3977",
    "sg:province":"VIC",
    "sg:tags":[
        "decorator",
        "painter"
    ],
    "wof:name":"The Painting Professionals",
    "wof:placetype":"venue"
},
  "geometry": {"coordinates":[145.22787475600001,-38.1340408325],"type":"Point"}
}