{
  "type": "Feature",
  "properties": {
    "iso:country":"AU",
    "sg:address":"74 Pearson Rd",
    "sg:city":"Yatala",
    "sg:classifiers":[
        {
            "category":"Structure",
            "subcategory":"Office Building",
            "type":"Public Place"
        }
    ],
    "sg:phone":"+61 7 3807 9522",
    "sg:postcode":"4207",
    "sg:province":"QLD",
    "sg:tags":[
        "tie",
        "concrete",
        "formwork",
        "form",
        "accessory"
    ],
    "wof:name":"Bosform Formwork Contractors",
    "wof:placetype":"venue"
},
  "geometry": {"coordinates":[153.2293396,-27.7635555267],"type":"Point"}
}