{
  "type": "Feature",
  "properties": {
    "addr:full":"PO Box 88 Wallsend NSW 2287",
    "addr:postcode":"2287",
    "iso:country":"AU",
    "sg:address":"PO Box 88",
    "sg:city":"Wallsend",
    "sg:classifiers":[
        {
            "category":"Organizations",
            "subcategory":"Professional Association",
            "type":"Services"
        }
    ],
    "sg:phone":"+61 1800 550 232",
    "sg:postcode":"2287",
    "sg:province":"NSW",
    "sg:tags":[
        "web",
        "internet"
    ],
    "wof:name":"Arien Designs",
    "wof:placetype":"venue"
},
  "geometry": {"coordinates":[151.669387817,-32.9025688171],"type":"Point"}
}