{
  "type": "Feature",
  "properties": {
    "addr:full":"51 Hampstead Rd Maidstone VIC 3012",
    "addr:housenumber":"51",
    "addr:postcode":"3012",
    "addr:street":"Hampstead Rd",
    "iso:country":"AU",
    "sg:address":"51 Hampstead Rd",
    "sg:city":"Maidstone",
    "sg:classifiers":[
        {
            "category":"Shopping",
            "subcategory":"Stationery & Office Supplies",
            "type":"Retail Goods"
        }
    ],
    "sg:phone":"+61 3 9318 5988",
    "sg:postcode":"3012",
    "sg:province":"VIC",
    "sg:tags":[
        "partition"
    ],
    "wof:name":"Octanorm",
    "wof:placetype":"venue"
},
  "geometry": {"coordinates":[144.877441406,-37.7771949768],"type":"Point"}
}