{
  "type": "Feature",
  "properties": {
    "addr:full":"8 Rose Ave Collaroy Plateau NSW 2097",
    "addr:housenumber":"8",
    "addr:postcode":"2097",
    "addr:street":"Rose Ave",
    "iso:country":"AU",
    "sg:address":"8 Rose Ave",
    "sg:city":"Collaroy Plateau",
    "sg:classifiers":[
        {
            "category":"Education",
            "subcategory":"School",
            "type":"Public Place"
        }
    ],
    "sg:phone":"+61 2 9982 1467",
    "sg:postcode":"2097",
    "sg:province":"NSW",
    "wof:name":"St Rose School",
    "wof:placetype":"venue"
},
  "geometry": {"coordinates":[151.286087036,-33.7267494202],"type":"Point"}
}