{
  "type": "Feature",
  "properties": {
    "iso:country":"AU",
    "sg:address":"Gerrymberrym Rd",
    "sg:city":"Seelands",
    "sg:classifiers":[
        {
            "category":"Building & Trades",
            "subcategory":"Construction",
            "type":"Services"
        }
    ],
    "sg:phone":"+61 2 6644 9607",
    "sg:postcode":"2460",
    "sg:province":"NSW",
    "sg:tags":[
        "earth",
        "excavating",
        "moving",
        "contractor"
    ],
    "wof:name":"Green Rod",
    "wof:placetype":"venue"
},
  "geometry": {"coordinates":[152.87638855,-29.6597232819],"type":"Point"}
}