{
  "type": "Feature",
  "properties": {
    "iso:country":"AU",
    "sg:address":"Penghana Rd",
    "sg:city":"Queenstown",
    "sg:classifiers":[
        {
            "category":"Travel",
            "subcategory":"Hotels & Motels",
            "type":"Entertainment"
        }
    ],
    "sg:phone":"+61 3 6471 1755",
    "sg:postcode":"7467",
    "sg:province":"TAS",
    "wof:name":"Silver Hills Motel",
    "wof:placetype":"venue"
},
  "geometry": {"coordinates":[145.55696105999999,-42.0761795044],"type":"Point"}
}