{
  "type": "Feature",
  "properties": {
    "iso:country":"AU",
    "sg:address":"56 Doncaster Rd",
    "sg:city":"Balwyn North",
    "sg:classifiers":[
        {
            "category":"Health Services",
            "subcategory":"Health Practitioner",
            "type":"Services"
        }
    ],
    "sg:phone":"+61 3 9859 5585",
    "sg:postcode":"3104",
    "sg:province":"VIC",
    "sg:tags":[
        "physiotherapist"
    ],
    "wof:name":"Schwarz Sally",
    "wof:placetype":"venue"
},
  "geometry": {"coordinates":[145.06997680699999,-37.7926902771],"type":"Point"}
}