{
  "type": "Feature",
  "properties": {
    "iso:country":"AU",
    "sg:address":"PO Box 480",
    "sg:city":"Camden",
    "sg:classifiers":[
        {
            "category":"Manufacturing",
            "subcategory":"Tools & Machinery",
            "type":"Manufacturing & Wholesale Goods"
        }
    ],
    "sg:phone":"+61 2 4654 5611",
    "sg:postcode":"2570",
    "sg:province":"NSW",
    "sg:tags":[
        "earth",
        "excavating",
        "moving",
        "equipment"
    ],
    "wof:name":"Avijohn Contracting Pty Ltd",
    "wof:placetype":"venue"
},
  "geometry": {"coordinates":[150.694015503,-34.0563583374],"type":"Point"}
}