{
  "type": "Feature",
  "properties": {
    "iso:country":"AU",
    "sg:address":"9 Barker St",
    "sg:city":"Willaston",
    "sg:classifiers":[
        {
            "category":"Utilities",
            "subcategory":"Electric",
            "type":"Services"
        }
    ],
    "sg:phone":"+61 8 8522 2701",
    "sg:postcode":"5118",
    "sg:province":"SA",
    "sg:tags":[
        "electrical",
        "contractor"
    ],
    "wof:name":"Reinke Allan",
    "wof:placetype":"venue"
},
  "geometry": {"coordinates":[138.74650600000001,-34.587952],"type":"Point"}
}