{
  "type": "Feature",
  "properties": {
    "addr:full":"600 Springvale Rd Springvale South VIC 3172",
    "addr:housenumber":"600",
    "addr:postcode":"3172",
    "addr:street":"Springvale Rd",
    "iso:country":"AU",
    "sg:address":"600 Springvale Rd",
    "sg:city":"Springvale South",
    "sg:classifiers":[
        {
            "category":"Utilities",
            "subcategory":"Fuel Oil & Lpg",
            "type":"Services"
        }
    ],
    "sg:phone":"+61 3 9546 1692",
    "sg:postcode":"3172",
    "sg:province":"VIC",
    "sg:tags":[
        "merchant"
    ],
    "wof:name":"Redgum Firewood Springvale",
    "wof:placetype":"venue"
},
  "geometry": {"coordinates":[145.14666748100001,-37.9785842896],"type":"Point"}
}