{
  "type": "Feature",
  "properties": {
    "iso:country":"AU",
    "sg:address":"43 Beveridge St",
    "sg:city":"Swan Hill",
    "sg:classifiers":[
        {
            "category":"Personal",
            "subcategory":"Massage",
            "type":"Services"
        }
    ],
    "sg:phone":"+61 3 5032 9366",
    "sg:postcode":"3585",
    "sg:province":"NSW",
    "sg:tags":[
        "therapy"
    ],
    "wof:name":"K.C. Muscle Works",
    "wof:placetype":"venue"
},
  "geometry": {"coordinates":[143.557205,-35.335476],"type":"Point"}
}