{
  "type": "Feature",
  "properties": {
    "addr:full":"9 Egan Rd Dandenong VIC 3175",
    "addr:housenumber":"9",
    "addr:postcode":"3175",
    "addr:street":"Egan Rd",
    "iso:country":"AU",
    "sg:address":"9 Egan Rd",
    "sg:city":"Dandenong",
    "sg:classifiers":[
        {
            "category":"Building & Trades",
            "subcategory":"Plumbing",
            "type":"Services"
        }
    ],
    "sg:phone":"+61 3 9793 2644",
    "sg:postcode":"3175",
    "sg:province":"VIC",
    "sg:tags":[
        "pump",
        "repairer"
    ],
    "wof:name":"Fluid Sealing Pty Ltd",
    "wof:placetype":"venue"
},
  "geometry": {"coordinates":[145.194381714,-37.9951095581],"type":"Point"}
}