{
  "type": "Feature",
  "properties": {
    "addr:full":"13 Bolton St Beaconsfield TAS 7270",
    "addr:housenumber":"13",
    "addr:postcode":"7270",
    "addr:street":"Bolton St",
    "iso:country":"AU",
    "sg:address":"13 Bolton St",
    "sg:city":"Beaconsfield",
    "sg:classifiers":[
        {
            "category":"Health Services",
            "subcategory":"Health Practitioner",
            "type":"Services"
        }
    ],
    "sg:phone":"+61 3 6383 1104",
    "sg:postcode":"7270",
    "sg:province":"TAS",
    "sg:tags":[
        "physiotherapist"
    ],
    "wof:name":"West Tamar Physiotherapy",
    "wof:placetype":"venue"
},
  "geometry": {"coordinates":[146.80641174300001,-41.1931648254],"type":"Point"}
}