{
  "type": "Feature",
  "properties": {
    "addr:full":"89 Spencer Rd Nerang QLD 4211",
    "addr:housenumber":"89",
    "addr:postcode":"4211",
    "addr:street":"Spencer Rd",
    "iso:country":"AU",
    "sg:address":"89 Spencer Rd",
    "sg:city":"Nerang",
    "sg:classifiers":[
        {
            "category":"Manufacturing",
            "subcategory":"Motor Vehicles & Parts",
            "type":"Manufacturing & Wholesale Goods"
        }
    ],
    "sg:phone":"+61 7 5596 3972",
    "sg:postcode":"4211",
    "sg:province":"QLD",
    "sg:tags":[
        "engine",
        "equipment",
        "diesel"
    ],
    "wof:name":"Diesel Torque",
    "wof:placetype":"venue"
},
  "geometry": {"coordinates":[153.34455871599999,-28.0076808929],"type":"Point"}
}