{
  "type": "Feature",
  "properties": {
    "addr:full":"2 Arrino Close Gwelup WA 6018",
    "addr:housenumber":"2",
    "addr:postcode":"6018",
    "addr:street":"Arrino Close",
    "iso:country":"AU",
    "sg:address":"2 Arrino Close",
    "sg:city":"Gwelup",
    "sg:classifiers":[
        {
            "category":"Building & Trades",
            "subcategory":"Construction",
            "type":"Services"
        }
    ],
    "sg:phone":"+61 419 771 323",
    "sg:postcode":"6018",
    "sg:province":"WA",
    "sg:tags":[
        "earth",
        "excavating",
        "moving",
        "contractor"
    ],
    "sg:website":"http://www.bobcatworks.com",
    "wof:name":"Bobcat Works",
    "wof:placetype":"venue"
},
  "geometry": {"coordinates":[115.79209136999999,-31.8594493866],"type":"Point"}
}