{
  "type": "Feature",
  "properties": {
    "addr:full":"U3/ 31 Londor Cl Hemmant QLD 4174",
    "addr:postcode":"4174",
    "addr:street":"U3 / 31 Londor Cl Hemmant",
    "iso:country":"AU",
    "sg:address":"U3/ 31 Londor Cl",
    "sg:city":"Hemmant",
    "sg:classifiers":[
        {
            "category":"Freight",
            "type":"Transportation"
        }
    ],
    "sg:phone":"+61 7 3348 9000",
    "sg:postcode":"4174",
    "sg:province":"QLD",
    "sg:tags":[
        "cargo",
        "container"
    ],
    "wof:name":"Aero Performance",
    "wof:placetype":"venue"
},
  "geometry": {"coordinates":[153.12551879899999,-27.4454803467],"type":"Point"}
}