{
  "type": "Feature",
  "properties": {
    "iso:country":"AU",
    "sg:address":"10 Union St",
    "sg:city":"Wickham",
    "sg:classifiers":[
        {
            "category":"Wholesale",
            "subcategory":"Construction Materials",
            "type":"Manufacturing & Wholesale Goods"
        }
    ],
    "sg:phone":"+61 2 4969 6555",
    "sg:postcode":"2293",
    "sg:province":"NSW",
    "sg:tags":[
        "wholesaler",
        "lighting",
        "mfrs",
        "accessory"
    ],
    "wof:name":"Stramac Pty Ltd",
    "wof:placetype":"venue"
},
  "geometry": {"coordinates":[151.757736206,-32.9230880737],"type":"Point"}
}