{
  "type": "Feature",
  "properties": {
    "addr:full":"165 Varsity Pde Varsity Lakes QLD 4226",
    "addr:housenumber":"165",
    "addr:postcode":"4226",
    "addr:street":"Varsity Pde",
    "iso:country":"AU",
    "sg:address":"165 Varsity Pde",
    "sg:city":"Varsity Lakes",
    "sg:classifiers":[
        {
            "category":"Banks & Credit Unions",
            "subcategory":"Bank",
            "type":"Services"
        }
    ],
    "sg:phone":"+61 7 5562 2661",
    "sg:postcode":"4226",
    "sg:province":"QLD",
    "sg:tags":[
        "equipment",
        "sale",
        "point"
    ],
    "wof:name":"Scancare Limited",
    "wof:placetype":"venue"
},
  "geometry": {"coordinates":[153.41093444800001,-28.0804958344],"type":"Point"}
}