{
  "type": "Feature",
  "properties": {
    "addr:full":"12 Urch St Geraldton WA 6530",
    "addr:housenumber":"12",
    "addr:postcode":"6530",
    "addr:street":"Urch St",
    "iso:country":"AU",
    "sg:address":"12 Urch St",
    "sg:city":"Geraldton",
    "sg:classifiers":[
        {
            "category":"Manufacturing",
            "subcategory":"Food",
            "type":"Manufacturing & Wholesale Goods"
        }
    ],
    "sg:phone":"+61 8 9964 2056",
    "sg:postcode":"6530",
    "sg:province":"WA",
    "sg:tags":[
        "function",
        "catering"
    ],
    "wof:name":"Lucas Catering Service",
    "wof:placetype":"venue"
},
  "geometry": {"coordinates":[114.616989136,-28.7634601593],"type":"Point"}
}