{
  "type": "Feature",
  "properties": {
    "addr:full":"9 Fortune St Nambour QLD 4560",
    "addr:housenumber":"9",
    "addr:postcode":"4560",
    "addr:street":"Fortune St",
    "iso:country":"AU",
    "sg:address":"9 Fortune St",
    "sg:city":"Nambour",
    "sg:classifiers":[
        {
            "category":"Recreation",
            "subcategory":"Sailing Club",
            "type":"Entertainment"
        }
    ],
    "sg:phone":"+61 7 5486 7247",
    "sg:postcode":"4560",
    "sg:province":"QLD",
    "sg:tags":[
        "gliding",
        "flying"
    ],
    "wof:name":"Gympie Gliding Club",
    "wof:placetype":"venue"
},
  "geometry": {"coordinates":[152.973266602,-26.6348953247],"type":"Point"}
}