{
  "type": "Feature",
  "properties": {
    "addr:full":"7 Anthea St Hazelmere WA 6055",
    "addr:housenumber":"7",
    "addr:postcode":"6055",
    "addr:street":"Anthea St",
    "iso:country":"AU",
    "sg:address":"7 Anthea St",
    "sg:city":"Hazelmere",
    "sg:classifiers":[
        {
            "category":"Building & Trades",
            "subcategory":"Landscaping Services",
            "type":"Services"
        }
    ],
    "sg:phone":"+61 413 043 501",
    "sg:postcode":"6055",
    "sg:province":"WA",
    "sg:tags":[
        "stump",
        "tree",
        "felling",
        "removal"
    ],
    "wof:name":"A. Tweeds Tree Services Pty Ltd",
    "wof:placetype":"venue"
},
  "geometry": {"coordinates":[115.991722,-31.904449],"type":"Point"}
}