{
  "type": "Feature",
  "properties": {
    "addr:full":"142 Bank St Howlong NSW 2643",
    "addr:housenumber":"142",
    "addr:postcode":"2643",
    "addr:street":"Bank St",
    "iso:country":"AU",
    "sg:address":"142 Bank St",
    "sg:city":"Howlong",
    "sg:classifiers":[
        {
            "category":"Building & Trades",
            "subcategory":"Construction",
            "type":"Services"
        }
    ],
    "sg:phone":"+61 2 6026 5398",
    "sg:postcode":"2643",
    "sg:province":"NSW",
    "sg:tags":[
        "contractor"
    ],
    "wof:name":"Glen Hall Homes",
    "wof:placetype":"venue"
},
  "geometry": {"coordinates":[146.62554931599999,-35.9828796387],"type":"Point"}
}