{
  "type": "Feature",
  "properties": {
    "iso:country":"AU",
    "sg:address":"10 Wittenberg Drv",
    "sg:city":"Canning Vale",
    "sg:classifiers":[
        {
            "category":"Autos & Motor Vehicles",
            "subcategory":"Boat Sales",
            "type":"Retail Goods"
        }
    ],
    "sg:phone":"+61 8 9456 0559",
    "sg:postcode":"6155",
    "sg:province":"WA",
    "sg:tags":[
        "machine",
        "dishwashing"
    ],
    "wof:name":"Eswood Australia Pty Ltd",
    "wof:placetype":"venue"
},
  "geometry": {"coordinates":[115.927048,-32.064831],"type":"Point"}
}