{
  "type": "Feature",
  "properties": {
    "iso:country":"AU",
    "sg:address":"8 Carnsworth Ave",
    "sg:city":"Kew",
    "sg:classifiers":[
        {
            "category":"Health Services",
            "subcategory":"Doctor",
            "type":"Services"
        }
    ],
    "sg:phone":"+61 3 9853 5216",
    "sg:postcode":"3101",
    "sg:province":"VIC",
    "sg:tags":[
        "medical",
        "practitioner"
    ],
    "wof:name":"O&#039;Brien Denis",
    "wof:placetype":"venue"
},
  "geometry": {"coordinates":[145.023239136,-37.8037338257],"type":"Point"}
}