{
  "type": "Feature",
  "properties": {
    "iso:country":"AU",
    "sg:address":"PO Box 1541",
    "sg:city":"Warriewood",
    "sg:classifiers":[
        {
            "category":"Utilities",
            "subcategory":"Refuse",
            "type":"Services"
        }
    ],
    "sg:phone":"+61 2 9997 5285",
    "sg:postcode":"2102",
    "sg:province":"NSW",
    "sg:tags":[
        "disposal",
        "reduction",
        "waste"
    ],
    "wof:name":"AAA Jacks Rubbish Removals",
    "wof:placetype":"venue"
},
  "geometry": {"coordinates":[151.29744,-33.688911],"type":"Point"}
}