{
  "type": "Feature",
  "properties": {
    "iso:country":"AU",
    "sg:address":"5/ 34 Carrick Drv",
    "sg:city":"Tullamarine",
    "sg:classifiers":[
        {
            "category":"Shopping",
            "subcategory":"Stationery & Office Supplies",
            "type":"Retail Goods"
        }
    ],
    "sg:phone":"+61 3 9330 5920",
    "sg:postcode":"3043",
    "sg:province":"VIC",
    "sg:tags":[
        "packaging",
        "material"
    ],
    "wof:name":"Icee Containers",
    "wof:placetype":"venue"
},
  "geometry": {"coordinates":[144.88768005399999,-37.699256897],"type":"Point"}
}