{
  "type": "Feature",
  "properties": {
    "iso:country":"AU",
    "sg:address":"Unit 2/3, 84- 86 Batt St",
    "sg:city":"Penrith",
    "sg:classifiers":[
        {
            "category":"Manufacturing",
            "subcategory":"Building Materials",
            "type":"Manufacturing & Wholesale Goods"
        }
    ],
    "sg:phone":"+61 2 4731 4862",
    "sg:postcode":"2750",
    "sg:province":"NSW",
    "sg:tags":[
        "concrete",
        "product"
    ],
    "wof:name":"Hi-Tech Stencilcrete Pty Ltd",
    "wof:placetype":"venue"
},
  "geometry": {"coordinates":[150.68447875999999,-33.7679367065],"type":"Point"}
}