{
  "type": "Feature",
  "properties": {
    "addr:full":"348 Melton Rd Northgate QLD 4013",
    "addr:housenumber":"348",
    "addr:postcode":"4013",
    "addr:street":"Melton Rd",
    "iso:country":"AU",
    "sg:address":"348 Melton Rd",
    "sg:city":"Northgate",
    "sg:classifiers":[
        {
            "category":"Utilities",
            "type":"Services"
        }
    ],
    "sg:phone":"+61 428 196 948",
    "sg:postcode":"4013",
    "sg:province":"QLD",
    "sg:tags":[
        "refrigeration",
        "industrial",
        "commercial",
        "retail"
    ],
    "wof:name":"Whip &#039;N&#039; Serve",
    "wof:placetype":"venue"
},
  "geometry": {"coordinates":[153.07090759299999,-27.3935451508],"type":"Point"}
}