{
  "type": "Feature",
  "properties": {
    "addr:full":"6a Munro St Coburg VIC 3058",
    "addr:housenumber":"6a",
    "addr:postcode":"3058",
    "addr:street":"Munro St",
    "iso:country":"AU",
    "sg:address":"6a Munro St",
    "sg:city":"Coburg",
    "sg:classifiers":[
        {
            "category":"Personal",
            "subcategory":"Beauty Salon",
            "type":"Services"
        }
    ],
    "sg:phone":"+61 3 9350 6149",
    "sg:postcode":"3058",
    "sg:province":"VIC",
    "sg:tags":[
        "hairdresser"
    ],
    "wof:name":"Zen Hair",
    "wof:placetype":"venue"
},
  "geometry": {"coordinates":[144.96522522000001,-37.7447128296],"type":"Point"}
}