{
  "type": "Feature",
  "properties": {
    "addr:full":"65 Morehead Ave Norman Park QLD 4170",
    "addr:housenumber":"65",
    "addr:postcode":"4170",
    "addr:street":"Morehead Ave",
    "iso:country":"AU",
    "sg:address":"65 Morehead Ave",
    "sg:city":"Norman Park",
    "sg:classifiers":[
        {
            "category":"Utilities",
            "subcategory":"Electric",
            "type":"Services"
        }
    ],
    "sg:phone":"+61 411 184 443",
    "sg:postcode":"4170",
    "sg:province":"QLD",
    "sg:tags":[
        "electrical",
        "contractor"
    ],
    "wof:name":"Bob Massie Electrical",
    "wof:placetype":"venue"
},
  "geometry": {"coordinates":[153.068557739,-27.4830627441],"type":"Point"}
}