{
  "type": "Feature",
  "properties": {
    "addr:full":"17 Nevada Ave Corio VIC 3214",
    "addr:housenumber":"17",
    "addr:postcode":"3214",
    "addr:street":"Nevada Ave",
    "iso:country":"AU",
    "sg:address":"17 Nevada Ave",
    "sg:city":"Corio",
    "sg:classifiers":[
        {
            "category":"Fast Food",
            "type":"Food & Drink"
        }
    ],
    "sg:phone":"+61 3 5275 6600",
    "sg:postcode":"3214",
    "sg:province":"VIC",
    "sg:tags":[
        "away",
        "take"
    ],
    "wof:name":"Nevada Pizza",
    "wof:placetype":"venue"
},
  "geometry": {"coordinates":[144.35287475600001,-38.0821876526],"type":"Point"}
}