{
  "type": "Feature",
  "properties": {
    "addr:full":"40b Ballarat St Yarraville VIC 3013",
    "addr:housenumber":"40b",
    "addr:postcode":"3013",
    "addr:street":"Ballarat St",
    "iso:country":"AU",
    "sg:address":"40b Ballarat St",
    "sg:city":"Yarraville",
    "sg:classifiers":[
        {
            "category":"Communications",
            "subcategory":"Film & Video Production",
            "type":"Services"
        }
    ],
    "sg:phone":"+61 3 9689 3344",
    "sg:postcode":"3013",
    "sg:province":"VIC",
    "sg:tags":[
        "dvd",
        "library"
    ],
    "wof:name":"Top Video",
    "wof:placetype":"venue"
},
  "geometry": {"coordinates":[144.89057922399999,-37.8175582886],"type":"Point"}
}