{
  "type": "Feature",
  "properties": {
    "addr:full":"6 Bruce Ave Marleston SA 5033",
    "addr:housenumber":"6",
    "addr:postcode":"5033",
    "addr:street":"Bruce Ave",
    "iso:country":"AU",
    "sg:address":"6 Bruce Ave",
    "sg:city":"Marleston",
    "sg:classifiers":[
        {
            "category":"Structure",
            "subcategory":"Bridge",
            "type":"Public Place"
        }
    ],
    "sg:phone":"+61 8 8292 8204",
    "sg:postcode":"5033",
    "sg:province":"SA",
    "sg:tags":[
        "chainsaw",
        "brushcutters"
    ],
    "wof:name":"Solo Outdoor Products",
    "wof:placetype":"venue"
},
  "geometry": {"coordinates":[138.565673828,-34.9439125061],"type":"Point"}
}