{
  "type": "Feature",
  "properties": {
    "iso:country":"AU",
    "sg:address":"906 Military Rd",
    "sg:city":"Mosman",
    "sg:classifiers":[
        {
            "category":"Food & Beverages",
            "subcategory":"Fruits & Vegetables",
            "type":"Retail Goods"
        }
    ],
    "sg:phone":"+61 2 9969 6114",
    "sg:postcode":"2088",
    "sg:province":"NSW",
    "sg:tags":[
        "greengrocer",
        "fruiterer"
    ],
    "wof:name":"Arena's Fruit Shop",
    "wof:placetype":"venue"
},
  "geometry": {"coordinates":[151.24436950699999,-33.8305587769],"type":"Point"}
}