{
  "type": "Feature",
  "properties": {
    "addr:full":"41 Daley Ave Daleys Point NSW 2257",
    "addr:housenumber":"41",
    "addr:postcode":"2257",
    "addr:street":"Daley Ave",
    "iso:country":"AU",
    "sg:address":"41 Daley Ave",
    "sg:city":"Daleys Point",
    "sg:classifiers":[
        {
            "category":"Landmark",
            "subcategory":"City Walls",
            "type":"Public Place"
        }
    ],
    "sg:phone":"+61 2 4341 6913",
    "sg:postcode":"2257",
    "sg:province":"NSW",
    "sg:tags":[
        "finish"
    ],
    "wof:name":"Daleys Point Cement Rendering Pty Ltd",
    "wof:placetype":"venue"
},
  "geometry": {"coordinates":[151.35177612300001,-33.5035858154],"type":"Point"}
}