{
  "type": "Feature",
  "properties": {
    "addr:full":"47 Paramount Drv Wangara WA 6065",
    "addr:housenumber":"47",
    "addr:postcode":"6065",
    "addr:street":"Paramount Drv",
    "iso:country":"AU",
    "sg:address":"47 Paramount Drv",
    "sg:city":"Wangara",
    "sg:classifiers":[
        {
            "category":"Retail",
            "subcategory":"Auto Repair",
            "type":"Services"
        }
    ],
    "sg:phone":"+61 8 9302 1179",
    "sg:postcode":"6065",
    "sg:province":"WA",
    "sg:tags":[
        "beater",
        "painter",
        "panel"
    ],
    "wof:name":"Wheels Panel & Paint",
    "wof:placetype":"venue"
},
  "geometry": {"coordinates":[115.83190918,-31.7908344269],"type":"Point"}
}