{
  "type": "Feature",
  "properties": {
    "addr:full":"78 Beringarra Ave Malaga WA 6090",
    "addr:housenumber":"78",
    "addr:postcode":"6090",
    "addr:street":"Beringarra Ave",
    "iso:country":"AU",
    "sg:address":"78 Beringarra Ave",
    "sg:city":"Malaga",
    "sg:classifiers":[
        {
            "category":"Manufacturing",
            "subcategory":"Tools & Machinery",
            "type":"Manufacturing & Wholesale Goods"
        }
    ],
    "sg:phone":"+61 8 9248 8552",
    "sg:postcode":"6090",
    "sg:province":"WA",
    "sg:tags":[
        "toolmaker"
    ],
    "wof:name":"Quality Moulding & Tooling",
    "wof:placetype":"venue"
},
  "geometry": {"coordinates":[115.901657105,-31.8638553619],"type":"Point"}
}