{
  "type": "Feature",
  "properties": {
    "addr:full":"Factory 5 16 Rosemary Crt Mulgrave VIC 3170",
    "addr:housenumber":"16",
    "addr:postcode":"3170",
    "addr:street":"Rosemary Crt",
    "iso:country":"AU",
    "sg:address":"Factory 5 16 Rosemary Crt",
    "sg:city":"Mulgrave",
    "sg:classifiers":[
        {
            "category":"Manufacturing",
            "subcategory":"Tools & Machinery",
            "type":"Manufacturing & Wholesale Goods"
        }
    ],
    "sg:phone":"+61 3 9561 6122",
    "sg:postcode":"3170",
    "sg:province":"VIC",
    "sg:tags":[
        "wholesaler",
        "mfrs",
        "hosiery"
    ],
    "wof:name":"Bosun Knitting Mills Pty Ltd",
    "wof:placetype":"venue"
},
  "geometry": {"coordinates":[145.15757751500001,-37.9047470093],"type":"Point"}
}