{
  "type": "Feature",
  "properties": {
    "addr:full":"Unit 6/ 4 Lynne St Caloundra QLD 4551",
    "addr:housenumber":"4",
    "addr:postcode":"4551",
    "addr:street":"Lynne St",
    "iso:country":"AU",
    "sg:address":"Unit 6/ 4 Lynne St",
    "sg:city":"Caloundra",
    "sg:classifiers":[
        {
            "category":"Banks & Credit Unions",
            "subcategory":"Bank",
            "type":"Services"
        }
    ],
    "sg:phone":"+61 7 5491 7741",
    "sg:postcode":"4551",
    "sg:province":"QLD",
    "sg:tags":[
        "equipment",
        "sale",
        "point"
    ],
    "wof:name":"Miles Plastics Pty Ltd",
    "wof:placetype":"venue"
},
  "geometry": {"coordinates":[153.11045837399999,-26.7929573059],"type":"Point"}
}