{
  "type": "Feature",
  "properties": {
    "addr:full":"212 Logan Rd Upper Mt Gravatt QLD 4122",
    "addr:housenumber":"212",
    "addr:postcode":"4122",
    "addr:street":"Logan Rd Upper",
    "iso:country":"AU",
    "sg:address":"212 Logan Rd",
    "sg:city":"Upper Mt Gravatt",
    "sg:classifiers":[
        {
            "category":"Fast Food",
            "type":"Food & Drink"
        }
    ],
    "sg:phone":"+61 7 3219 1034",
    "sg:postcode":"4122",
    "sg:province":"QLD",
    "sg:tags":[
        "away",
        "take"
    ],
    "wof:name":"Cafe Colosseum",
    "wof:placetype":"venue"
},
  "geometry": {"coordinates":[153.072631836,-27.5305557251],"type":"Point"}
}