{
  "type": "Feature",
  "properties": {
    "iso:country":"AU",
    "sg:address":"83 Preston Boundary Rd",
    "sg:city":"Preston",
    "sg:classifiers":[
        {
            "category":"Farming",
            "subcategory":"Poultry Farm",
            "type":"Manufacturing & Wholesale Goods"
        }
    ],
    "sg:phone":"+61 7 4630 9266",
    "sg:postcode":"4352",
    "sg:province":"QLD",
    "sg:tags":[
        "farmer"
    ],
    "wof:name":"Wissemann M",
    "wof:placetype":"venue"
},
  "geometry": {"coordinates":[151.97027600000001,-27.652731],"type":"Point"}
}