{
  "type": "Feature",
  "properties": {
    "addr:full":"Blain St Alice Springs NT 0870",
    "addr:postcode":"nt 0870",
    "addr:street":"Blain St",
    "iso:country":"AU",
    "sg:address":"Blain St",
    "sg:city":"Alice Springs",
    "sg:classifiers":[
        {
            "category":"Education",
            "subcategory":"School",
            "type":"Public Place"
        }
    ],
    "sg:phone":"+61 8 8955 0121",
    "sg:postcode":"0870",
    "sg:province":"NT",
    "wof:name":"Araluen Christian School",
    "wof:placetype":"venue"
},
  "geometry": {"coordinates":[133.85357665999999,-23.7090759277],"type":"Point"}
}