{
  "type": "Feature",
  "properties": {
    "addr:full":"2/ 33 Machinery St Darra QLD 4076",
    "addr:housenumber":"/ 33",
    "addr:postcode":"4076",
    "addr:street":"Machinery St",
    "iso:country":"AU",
    "sg:address":"2/ 33 Machinery St",
    "sg:city":"Darra",
    "sg:classifiers":[
        {
            "category":"Communications",
            "subcategory":"Television Station",
            "type":"Services"
        }
    ],
    "sg:phone":"+61 7 3713 7744",
    "sg:postcode":"4076",
    "sg:province":"QLD",
    "sg:tags":[
        "screening",
        "machinery",
        "grading"
    ],
    "wof:name":"Advanced Engineering Group",
    "wof:placetype":"venue"
},
  "geometry": {"coordinates":[152.947799683,-27.5779037476],"type":"Point"}
}