{
  "type": "Feature",
  "properties": {
    "iso:country":"AU",
    "sg:address":"Shop 1/ 268 Kingston Rd",
    "sg:city":"Slacks Creek",
    "sg:classifiers":[
        {
            "category":"Food & Beverages",
            "subcategory":"Groceries & Convenience Stores",
            "type":"Retail Goods"
        }
    ],
    "sg:phone":"+61 7 3804 3818",
    "sg:postcode":"4127",
    "sg:province":"QLD",
    "wof:name":"Mc's Indian & Island Food",
    "wof:placetype":"venue"
},
  "geometry": {"coordinates":[153.11888122600001,-27.6397533417],"type":"Point"}
}