{
  "type": "Feature",
  "properties": {
    "addr:full":"Lvl2/ 171 La Trobe St Melbourne VIC 3000",
    "addr:housenumber":"171",
    "addr:postcode":"3000",
    "addr:street":"La Trobe St",
    "iso:country":"AU",
    "sg:address":"Lvl2/ 171 La Trobe St",
    "sg:city":"Melbourne",
    "sg:classifiers":[
        {
            "category":"Professional",
            "subcategory":"Management & Consulting",
            "type":"Services"
        }
    ],
    "sg:phone":"+61 3 9663 3737",
    "sg:postcode":"3000",
    "sg:province":"VIC",
    "sg:tags":[
        "consultant",
        "migration"
    ],
    "wof:name":"Dream Overseas",
    "wof:placetype":"venue"
},
  "geometry": {"coordinates":[144.96664428700001,-37.8088989258],"type":"Point"}
}