{
  "type": "Feature",
  "properties": {
    "iso:country":"AU",
    "sg:address":"2 Stonepark Rd",
    "sg:city":"Ballarat",
    "sg:classifiers":[
        {
            "category":"Manufacturing",
            "subcategory":"Chemicals & Compounds",
            "type":"Manufacturing & Wholesale Goods"
        }
    ],
    "sg:phone":"+61 3 5335 6288",
    "sg:postcode":"3350",
    "sg:province":"VIC",
    "sg:tags":[
        "agricultural"
    ],
    "wof:name":"Landlink Seeds & Chemicals",
    "wof:placetype":"venue"
},
  "geometry": {"coordinates":[143.817184,-37.570801],"type":"Point"}
}