{
  "type": "Feature",
  "properties": {
    "addr:full":"37 Beech Drv Cashmere QLD 4500",
    "addr:housenumber":"37",
    "addr:postcode":"4500",
    "addr:street":"Beech Drv",
    "iso:country":"AU",
    "sg:address":"37 Beech Drv",
    "sg:city":"Cashmere",
    "sg:classifiers":[
        {
            "category":"Building & Trades",
            "subcategory":"Construction",
            "type":"Services"
        }
    ],
    "sg:phone":"+61 1800 654 844",
    "sg:postcode":"4500",
    "sg:province":"QLD",
    "sg:tags":[
        "home",
        "air conditioning"
    ],
    "wof:name":"A1 Home Maintenance & Inspection Service",
    "wof:placetype":"venue"
},
  "geometry": {"coordinates":[152.92759704599999,-27.3216667175],"type":"Point"}
}