{
  "type": "Feature",
  "properties": {
    "addr:full":"25 Christian Rd Cottles Bridge VIC 3099",
    "addr:housenumber":"25",
    "addr:postcode":"3099",
    "addr:street":"Christian Rd",
    "iso:country":"AU",
    "sg:address":"25 Christian Rd",
    "sg:city":"Cottles Bridge",
    "sg:classifiers":[
        {
            "category":"Building & Trades",
            "subcategory":"Construction",
            "type":"Services"
        }
    ],
    "sg:phone":"+61 3 9718 2378",
    "sg:postcode":"3099",
    "sg:province":"VIC",
    "sg:tags":[
        "earth",
        "excavating",
        "moving",
        "contractor"
    ],
    "wof:name":"Diamond Valley Excavations",
    "wof:placetype":"venue"
},
  "geometry": {"coordinates":[145.21720886200001,-37.622959137],"type":"Point"}
}