{
  "type": "Feature",
  "properties": {
    "addr:full":"70 Main St Bruthen VIC 3885",
    "addr:housenumber":"70",
    "addr:postcode":"3885",
    "addr:street":"Main St",
    "iso:country":"AU",
    "sg:address":"70 Main St",
    "sg:city":"Bruthen",
    "sg:classifiers":[
        {
            "category":"Autos & Motor Vehicles",
            "subcategory":"Fuel & Gas Station",
            "type":"Retail Goods"
        }
    ],
    "sg:phone":"+61 3 5157 5262",
    "sg:postcode":"3885",
    "sg:province":"VIC",
    "wof:name":"Bruthen Motors",
    "wof:placetype":"venue"
},
  "geometry": {"coordinates":[147.83403015100001,-37.7085800171],"type":"Point"}
}