{
  "type": "Feature",
  "properties": {
    "iso:country":"AU",
    "sg:address":"170 Queen St",
    "sg:city":"Melbourne",
    "sg:classifiers":[
        {
            "category":"Food & Beverages",
            "subcategory":"Liquor & Beverages",
            "type":"Retail Goods"
        }
    ],
    "sg:phone":"+61 3 9642 5317",
    "sg:postcode":"3000",
    "sg:province":"VIC",
    "sg:tags":[
        "merchant",
        "spirit",
        "wine"
    ],
    "wof:name":"Wine Yard",
    "wof:placetype":"venue"
},
  "geometry": {"coordinates":[144.960647583,-37.8144836426],"type":"Point"}
}