{
  "type": "Feature",
  "properties": {
    "addr:full":"15 Ferguson St Warrnambool VIC 3280",
    "addr:housenumber":"15",
    "addr:postcode":"3280",
    "addr:street":"Ferguson St",
    "iso:country":"AU",
    "sg:address":"15 Ferguson St",
    "sg:city":"Warrnambool",
    "sg:classifiers":[
        {
            "category":"Professional",
            "subcategory":"Accounting & Tax Preparation",
            "type":"Services"
        }
    ],
    "sg:phone":"+61 3 5562 8886",
    "sg:postcode":"3280",
    "sg:province":"VIC",
    "sg:tags":[
        "accountant",
        "auditor"
    ],
    "wof:name":"McLaren G A",
    "wof:placetype":"venue"
},
  "geometry": {"coordinates":[142.51336669899999,-38.3887329102],"type":"Point"}
}