{
  "type": "Feature",
  "properties": {
    "addr:full":"Shop 11 Fountain Plaza Erina NSW 2250",
    "addr:housenumber":"shop 11",
    "addr:postcode":"2250",
    "addr:street":"Fountain Plaza",
    "iso:country":"AU",
    "sg:address":"Shop 11",
    "sg:city":"Fountain Plaza Erina",
    "sg:classifiers":[
        {
            "category":"Shopping",
            "subcategory":"Musical Instruments",
            "type":"Retail Goods"
        }
    ],
    "sg:phone":"+61 2 4367 8500",
    "sg:postcode":"2250",
    "sg:province":"NSW",
    "sg:tags":[
        "piano",
        "organ"
    ],
    "wof:name":"Macron Music",
    "wof:placetype":"venue"
},
  "geometry": {"coordinates":[151.33767700199999,-33.3974380493],"type":"Point"}
}