{
  "type": "Feature",
  "properties": {
    "addr:full":"3 Stutt St Wanniassa ACT 2903",
    "addr:housenumber":"3",
    "addr:postcode":"2903",
    "addr:street":"Stutt St",
    "iso:country":"AU",
    "sg:address":"3 Stutt St",
    "sg:city":"Wanniassa",
    "sg:classifiers":[
        {
            "category":"Home & Garden",
            "subcategory":"Building Materials",
            "type":"Retail Goods"
        }
    ],
    "sg:phone":"+61 409 712 721",
    "sg:postcode":"2903",
    "sg:province":"ACT",
    "sg:tags":[
        "lawn",
        "cutting",
        "maintenance"
    ],
    "wof:name":"Bishop Jason",
    "wof:placetype":"venue"
},
  "geometry": {"coordinates":[149.08067321799999,-35.3984184265],"type":"Point"}
}