{
  "type": "Feature",
  "properties": {
    "addr:full":"2/ 12 Gordon St Bairnsdale VIC 3875",
    "addr:housenumber":"/ 12",
    "addr:postcode":"3875",
    "addr:street":"Gordon St",
    "iso:country":"AU",
    "sg:address":"2/ 12 Gordon St",
    "sg:city":"Bairnsdale",
    "sg:classifiers":[
        {
            "category":"Education",
            "subcategory":"Special Training",
            "type":"Public Place"
        }
    ],
    "sg:phone":"+61 3 5153 2010",
    "sg:postcode":"3875",
    "sg:province":"VIC",
    "sg:tags":[
        "diving",
        "school",
        "scuba"
    ],
    "wof:name":"Cross Diving Services",
    "wof:placetype":"venue"
},
  "geometry": {"coordinates":[147.608917236,-37.8348388672],"type":"Point"}
}