{
  "type": "Feature",
  "properties": {
    "addr:full":"15 Narrabeen Park Pde North Narrabeen NSW 2101",
    "addr:housenumber":"15",
    "addr:postcode":"2101",
    "addr:street":"Narrabeen Park Pde",
    "iso:country":"AU",
    "sg:address":"15 Narrabeen Park Pde",
    "sg:city":"North Narrabeen",
    "sg:classifiers":[
        {
            "category":"Shopping",
            "subcategory":"Stationery & Office Supplies",
            "type":"Retail Goods"
        }
    ],
    "sg:phone":"+61 1800 090 787",
    "sg:postcode":"2101",
    "sg:province":"NSW",
    "wof:name":"Profile Of Design",
    "wof:placetype":"venue"
},
  "geometry": {"coordinates":[151.307526,-33.699558],"type":"Point"}
}