{
  "type": "Feature",
  "properties": {
    "addr:full":"31 George St Riverstone NSW 2765",
    "addr:housenumber":"31",
    "addr:postcode":"2765",
    "addr:street":"George St",
    "iso:country":"AU",
    "sg:address":"31 George St",
    "sg:city":"Riverstone",
    "sg:classifiers":[
        {
            "category":"Building & Trades",
            "subcategory":"Landscaping Services",
            "type":"Services"
        }
    ],
    "sg:phone":"+61 2 9627 2661",
    "sg:postcode":"2765",
    "sg:province":"NSW",
    "sg:tags":[
        "designer",
        "landscape",
        "contractor"
    ],
    "wof:name":"Giuliano J",
    "wof:placetype":"venue"
},
  "geometry": {"coordinates":[150.861694336,-33.6736106873],"type":"Point"}
}