{
  "type": "Feature",
  "properties": {
    "addr:full":"2/33 Smith St Capalaba QLD 4157",
    "addr:housenumber":"/ 33",
    "addr:postcode":"4157",
    "addr:street":"Smith St",
    "iso:country":"AU",
    "sg:address":"2/33 Smith St",
    "sg:city":"Capalaba",
    "sg:phone":"+61 7 3245 7777",
    "sg:postcode":"4157",
    "sg:province":"QLD",
    "wof:name":"Aquatic Oasis",
    "wof:placetype":"venue"
},
  "geometry": {"coordinates":[153.20039367699999,-27.5293827057],"type":"Point"}
}