{
  "type": "Feature",
  "properties": {
    "addr:full":"27 Bank St Meadowbank NSW 2114",
    "addr:housenumber":"27",
    "addr:postcode":"2114",
    "addr:street":"Bank St",
    "iso:country":"AU",
    "sg:address":"27 Bank St",
    "sg:city":"Meadowbank",
    "sg:classifiers":[
        {
            "category":"Health Services",
            "subcategory":"Doctor",
            "type":"Services"
        }
    ],
    "sg:phone":"+61 2 9809 1088",
    "sg:postcode":"2114",
    "sg:province":"NSW",
    "sg:tags":[
        "medical",
        "practitioner"
    ],
    "wof:name":"Goh T C M",
    "wof:placetype":"venue"
},
  "geometry": {"coordinates":[151.08958435100001,-33.8156471252],"type":"Point"}
}