{
  "type": "Feature",
  "properties": {
    "addr:full":"637 Pearsall St Lavington NSW 2641",
    "addr:housenumber":"637",
    "addr:postcode":"2641",
    "addr:street":"Pearsall St",
    "iso:country":"AU",
    "sg:address":"637 Pearsall St",
    "sg:city":"Lavington",
    "sg:classifiers":[
        {
            "category":"Building & Trades",
            "subcategory":"Construction",
            "type":"Services"
        }
    ],
    "sg:phone":"+61 2 6025 1094",
    "sg:postcode":"2641",
    "sg:province":"NSW",
    "sg:tags":[
        "plasterboard",
        "plasterer",
        "fixer"
    ],
    "wof:name":"Webb R & S",
    "wof:placetype":"venue"
},
  "geometry": {"coordinates":[146.923904419,-36.0379943848],"type":"Point"}
}