{
  "type": "Feature",
  "properties": {
    "addr:full":"Ellen St Port Pirie SA 5540",
    "addr:postcode":"5540",
    "addr:street":"Ellen St",
    "iso:country":"AU",
    "sg:address":"Ellen St",
    "sg:city":"Port Pirie",
    "sg:classifiers":[
        {
            "category":"Autos & Motor Vehicles",
            "subcategory":"Auto Supplies",
            "type":"Retail Goods"
        }
    ],
    "sg:phone":"+61 8 8632 1940",
    "sg:postcode":"5540",
    "sg:province":"SA",
    "sg:tags":[
        "oil",
        "spirit"
    ],
    "wof:name":"Perry L H & Sons Pty Ltd",
    "wof:placetype":"venue"
},
  "geometry": {"coordinates":[138.01051330600001,-33.1726226807],"type":"Point"}
}