{
  "type": "Feature",
  "properties": {
    "addr:full":"128 Pacific Hwy Charlestown NSW 2290",
    "addr:housenumber":"128",
    "addr:postcode":"2290",
    "addr:street":"Pacific Hwy",
    "iso:country":"AU",
    "sg:address":"128 Pacific Hwy",
    "sg:city":"Charlestown",
    "sg:classifiers":[
        {
            "category":"Autos & Motor Vehicles",
            "subcategory":"Fuel & Gas Station",
            "type":"Retail Goods"
        }
    ],
    "sg:phone":"+61 2 4943 7155",
    "sg:postcode":"2290",
    "sg:province":"NSW",
    "wof:name":"Shell Australia Limited",
    "wof:placetype":"venue"
},
  "geometry": {"coordinates":[151.69525146500001,-32.9654960632],"type":"Point"}
}