{
  "type": "Feature",
  "properties": {
    "addr:full":"433 Back Swamp Rd Bathurst NSW 2795",
    "addr:housenumber":"433",
    "addr:postcode":"2795",
    "addr:street":"Back Swamp Rd",
    "iso:country":"AU",
    "sg:address":"433 Back Swamp Rd",
    "sg:city":"Bathurst",
    "sg:classifiers":[
        {
            "category":"Professional",
            "subcategory":"Accounting & Tax Preparation",
            "type":"Services"
        }
    ],
    "sg:phone":"+61 2 6337 3894",
    "sg:postcode":"2795",
    "sg:province":"NSW",
    "sg:tags":[
        "bookkeeping"
    ],
    "wof:name":"G & W Tisdell Office Services",
    "wof:placetype":"venue"
},
  "geometry": {"coordinates":[149.45057678200001,-33.4258384705],"type":"Point"}
}