{
  "type": "Feature",
  "properties": {
    "addr:full":"32 Murray St Tanunda SA 5352",
    "addr:housenumber":"32",
    "addr:postcode":"5352",
    "addr:street":"Murray St",
    "iso:country":"AU",
    "sg:address":"32 Murray St",
    "sg:city":"Tanunda",
    "sg:classifiers":[
        {
            "category":"Professional",
            "subcategory":"Art Services",
            "type":"Services"
        }
    ],
    "sg:phone":"+61 8 8563 0222",
    "sg:postcode":"5352",
    "sg:province":"SA",
    "sg:tags":[
        "picture",
        "frame",
        "framing"
    ],
    "wof:name":"Barossa Valley Framed",
    "wof:placetype":"venue"
},
  "geometry": {"coordinates":[138.96115112300001,-34.5231323242],"type":"Point"}
}