{
  "type": "Feature",
  "properties": {
    "iso:country":"AU",
    "sg:address":"901A Skipton St",
    "sg:city":"Ballarat",
    "sg:classifiers":[
        {
            "category":"Health Services",
            "subcategory":"Doctor",
            "type":"Services"
        }
    ],
    "sg:phone":"+61 3 5336 2971",
    "sg:postcode":"3350",
    "sg:province":"VIC",
    "sg:tags":[
        "medical",
        "practitioner"
    ],
    "wof:name":"McCallum Heather Dr",
    "wof:placetype":"venue"
},
  "geometry": {"coordinates":[143.854507,-37.567726],"type":"Point"}
}