{
  "type": "Feature",
  "properties": {
    "addr:full":"51 Weyba St Sunshine Beach QLD 4567",
    "addr:housenumber":"51",
    "addr:postcode":"4567",
    "addr:street":"Weyba St",
    "iso:country":"AU",
    "sg:address":"51 Weyba St",
    "sg:city":"Sunshine Beach",
    "sg:classifiers":[
        {
            "category":"Utilities",
            "subcategory":"Electric",
            "type":"Services"
        }
    ],
    "sg:phone":"+61 412 378 558",
    "sg:postcode":"4567",
    "sg:province":"QLD",
    "sg:tags":[
        "electrical",
        "contractor"
    ],
    "wof:name":"Weyba Electrical",
    "wof:placetype":"venue"
},
  "geometry": {"coordinates":[153.08221435600001,-26.4044094086],"type":"Point"}
}