{
  "type": "Feature",
  "properties": {
    "addr:full":"Lvl 4/ 303 Adelaide St Brisbane QLD 4000",
    "addr:housenumber":"/ 303",
    "addr:postcode":"4000",
    "addr:street":"Adelaide St",
    "iso:country":"AU",
    "sg:address":"Lvl 4/ 303 Adelaide St",
    "sg:city":"Brisbane",
    "sg:classifiers":[
        {
            "category":"Real Estate",
            "subcategory":"Architect",
            "type":"Services"
        }
    ],
    "sg:phone":"+61 7 3211 7183",
    "sg:postcode":"4000",
    "sg:province":"QLD",
    "wof:name":"Fox Daniel R Architect",
    "wof:placetype":"venue"
},
  "geometry": {"coordinates":[153.02932739299999,-27.4652633667],"type":"Point"}
}