{
  "type": "Feature",
  "properties": {
    "iso:country":"AU",
    "sg:address":"PO Box 782",
    "sg:city":"Mosman",
    "sg:classifiers":[
        {
            "category":"Professional",
            "subcategory":"Computer Services",
            "type":"Services"
        }
    ],
    "sg:phone":"+61 2 9960 4747",
    "sg:postcode":"2088",
    "sg:province":"NSW",
    "sg:tags":[
        "package",
        "software"
    ],
    "wof:name":"Kardinia Software Pty Ltd",
    "wof:placetype":"venue"
},
  "geometry": {"coordinates":[151.24026489299999,-33.8244895935],"type":"Point"}
}