{
  "type": "Feature",
  "properties": {
    "iso:country":"AU",
    "sg:address":"29 Centreway St",
    "sg:city":"Keilor East",
    "sg:classifiers":[
        {
            "category":"Personal",
            "subcategory":"Beauty Salon",
            "type":"Services"
        }
    ],
    "sg:phone":"+61 3 9331 7762",
    "sg:postcode":"3033",
    "sg:province":"VIC",
    "sg:tags":[
        "hairdresser"
    ],
    "wof:name":"M Style Melbourne",
    "wof:placetype":"venue"
},
  "geometry": {"coordinates":[144.866287,-37.733242],"type":"Point"}
}