{
  "type": "Feature",
  "properties": {
    "iso:country":"AU",
    "sg:address":"Lot 270 Encounter St",
    "sg:city":"Karalee",
    "sg:classifiers":[
        {
            "category":"Professional",
            "type":"Services"
        }
    ],
    "sg:phone":"+61 7 3294 7898",
    "sg:postcode":"4306",
    "sg:province":"QLD",
    "sg:tags":[
        "transport"
    ],
    "wof:name":"Send With Us",
    "wof:placetype":"venue"
},
  "geometry": {"coordinates":[152.81687927199999,-27.570766449],"type":"Point"}
}