{
  "type": "Feature",
  "properties": {
    "addr:full":"2 Tait St Kelvin Grove QLD 4059",
    "addr:housenumber":"2",
    "addr:postcode":"4059",
    "addr:street":"Tait St",
    "iso:country":"AU",
    "sg:address":"2 Tait St",
    "sg:city":"Kelvin Grove",
    "sg:classifiers":[
        {
            "category":"Banks & Credit Unions",
            "subcategory":"Bank",
            "type":"Services"
        }
    ],
    "sg:phone":"+61 1300 762 603",
    "sg:postcode":"4059",
    "sg:province":"QLD",
    "sg:tags":[
        "equipment",
        "sale",
        "point"
    ],
    "wof:name":"POS Shop Pty Ltd",
    "wof:placetype":"venue"
},
  "geometry": {"coordinates":[153.008056641,-27.4448852539],"type":"Point"}
}