{
  "type": "Feature",
  "properties": {
    "addr:full":"205 Mitcham Rd Donvale VIC 3111",
    "addr:housenumber":"205",
    "addr:postcode":"3111",
    "addr:street":"Mitcham Rd",
    "iso:country":"AU",
    "sg:address":"205 Mitcham Rd",
    "sg:city":"Donvale",
    "sg:classifiers":[
        {
            "category":"Professional",
            "subcategory":"Art Services",
            "type":"Services"
        }
    ],
    "sg:phone":"+61 414 226 208",
    "sg:postcode":"3111",
    "sg:province":"VIC",
    "sg:tags":[
        "decorator",
        "painter"
    ],
    "wof:name":"A 1 Rona Painter",
    "wof:placetype":"venue"
},
  "geometry": {"coordinates":[145.18992614699999,-37.8046760559],"type":"Point"}
}