{
  "type": "Feature",
  "properties": {
    "addr:full":"Shop 6, 6 Commercial Drv Springfield QLD 4300",
    "addr:housenumber":"shop;6",
    "addr:postcode":"4300",
    "addr:street":"Commercial Drv",
    "iso:country":"AU",
    "sg:address":"Shop 6, 6 Commercial Drv",
    "sg:city":"Springfield",
    "sg:classifiers":[
        {
            "category":"Health Services",
            "subcategory":"Dentist",
            "type":"Services"
        }
    ],
    "sg:phone":"+61 7 3818 9100",
    "sg:postcode":"4300",
    "sg:province":"QLD",
    "wof:name":"Springfield Dental Care",
    "wof:placetype":"venue"
},
  "geometry": {"coordinates":[152.91786193900001,-27.6556854248],"type":"Point"}
}