{
  "type": "Feature",
  "properties": {
    "iso:country":"AU",
    "sg:address":"PO Box 239",
    "sg:city":"Armadale",
    "sg:classifiers":[
        {
            "category":"Professional",
            "subcategory":"Business Services",
            "type":"Services"
        }
    ],
    "sg:phone":"+61 3 9509 4050",
    "sg:postcode":"3143",
    "sg:province":"VIC",
    "sg:tags":[
        "management",
        "event"
    ],
    "wof:name":"In Front Events Pty Ltd",
    "wof:placetype":"venue"
},
  "geometry": {"coordinates":[145.01930236800001,-37.8576812744],"type":"Point"}
}