{
  "type": "Feature",
  "properties": {
    "iso:country":"AU",
    "sg:address":"11 Clifton Springs Rd",
    "sg:city":"Drysdale",
    "sg:classifiers":[
        {
            "category":"Real Estate",
            "subcategory":"Real Estate Agent",
            "type":"Services"
        }
    ],
    "sg:phone":"+61 3 5251 2847",
    "sg:postcode":"3222",
    "sg:province":"VIC",
    "wof:name":"Allpoints Real Estate Drysdale",
    "wof:placetype":"venue"
},
  "geometry": {"coordinates":[144.573486,-38.159431],"type":"Point"}
}