{
  "type": "Feature",
  "properties": {
    "addr:full":"Shop 37 Lakes Village Shopping Centre Mt Gambier SA 5290",
    "addr:housenumber":"shop 37",
    "addr:postcode":"5290",
    "addr:street":"Lakes Village",
    "iso:country":"AU",
    "sg:address":"Shop 37 Lakes Village Shopping Centre",
    "sg:city":"Mt Gambier",
    "sg:classifiers":[
        {
            "category":"Shopping",
            "subcategory":"Clothing, Apparel, & Fashions",
            "type":"Retail Goods"
        }
    ],
    "sg:phone":"+61 8 8723 0895",
    "sg:postcode":"5290",
    "sg:province":"SA",
    "sg:tags":[
        "jean"
    ],
    "wof:name":"JeansWest",
    "wof:placetype":"venue"
},
  "geometry": {"coordinates":[140.78329500000001,-37.826321],"type":"Point"}
}