{
  "type": "Feature",
  "properties": {
    "addr:full":"920 Toork Rd Camberwell VIC 3124",
    "addr:housenumber":"920",
    "addr:postcode":"3124",
    "addr:street":"Toork Rd",
    "iso:country":"AU",
    "sg:address":"920 Toork Rd",
    "sg:city":"Camberwell",
    "sg:classifiers":[
        {
            "category":"Professional",
            "subcategory":"Business Services",
            "type":"Services"
        }
    ],
    "sg:phone":"+61 412 549 871",
    "sg:postcode":"3124",
    "sg:province":"VIC",
    "sg:tags":[
        "drafting"
    ],
    "wof:name":"Bonacci Design",
    "wof:placetype":"venue"
},
  "geometry": {"coordinates":[145.07518005399999,-37.8481254578],"type":"Point"}
}