{
  "type": "Feature",
  "properties": {
    "addr:full":"Shp22/ 906 Main Rd Eltham VIC 3095",
    "addr:housenumber":"906",
    "addr:postcode":"3095",
    "addr:street":"Main Rd",
    "iso:country":"AU",
    "sg:address":"Shp22/ 906 Main Rd",
    "sg:city":"Eltham",
    "sg:classifiers":[
        {
            "category":"Fast Food",
            "type":"Food & Drink"
        }
    ],
    "sg:phone":"+61 3 9431 6044",
    "sg:postcode":"3095",
    "sg:province":"VIC",
    "sg:tags":[
        "away",
        "take"
    ],
    "wof:name":"Eltham Noodle World",
    "wof:placetype":"venue"
},
  "geometry": {"coordinates":[145.14848327600001,-37.7146530151],"type":"Point"}
}