{
  "type": "Feature",
  "properties": {
    "addr:full":"53 Nelson St Golden Beach QLD 4551",
    "addr:housenumber":"53",
    "addr:postcode":"4551",
    "addr:street":"Nelson St",
    "iso:country":"AU",
    "sg:address":"53 Nelson St",
    "sg:city":"Golden Beach",
    "sg:classifiers":[
        {
            "category":"Building & Trades",
            "subcategory":"Construction",
            "type":"Services"
        }
    ],
    "sg:phone":"+61 7 5437 3446",
    "sg:postcode":"4551",
    "sg:province":"QLD",
    "sg:tags":[
        "bridge",
        "contractor"
    ],
    "wof:name":"Mackay & Sons",
    "wof:placetype":"venue"
},
  "geometry": {"coordinates":[153.11587524399999,-26.8222732544],"type":"Point"}
}