{
  "type": "Feature",
  "properties": {
    "iso:country":"AU",
    "sg:address":"4/ 125 Lysaght St",
    "sg:city":"Mitchell",
    "sg:classifiers":[
        {
            "category":"Home & Garden",
            "subcategory":"Carpets & Floor Coverings",
            "type":"Retail Goods"
        }
    ],
    "sg:phone":"+61 2 6241 7117",
    "sg:postcode":"2911",
    "sg:province":"ACT",
    "sg:tags":[
        "tile",
        "wall"
    ],
    "wof:name":"Slate Man The",
    "wof:placetype":"venue"
},
  "geometry": {"coordinates":[149.13941955600001,-35.2153549194],"type":"Point"}
}