{
  "type": "Feature",
  "properties": {
    "iso:country":"AU",
    "sg:address":"25 Lyons St",
    "sg:city":"Mundubbera",
    "sg:classifiers":[
        {
            "category":"Professional",
            "subcategory":"Accounting & Tax Preparation",
            "type":"Services"
        }
    ],
    "sg:phone":"+61 7 4165 4237",
    "sg:postcode":"4626",
    "sg:province":"QLD",
    "sg:tags":[
        "accountant",
        "auditor"
    ],
    "wof:name":"Powers Chartered Accountants",
    "wof:placetype":"venue"
},
  "geometry": {"coordinates":[151.299789,-25.591566],"type":"Point"}
}