{
  "type": "Feature",
  "properties": {
    "addr:full":"21 Railway Pde Condell Park NSW 2200",
    "addr:housenumber":"21",
    "addr:postcode":"2200",
    "addr:street":"Railway Pde",
    "iso:country":"AU",
    "sg:address":"21 Railway Pde",
    "sg:city":"Condell Park",
    "sg:classifiers":[
        {
            "category":"Retail",
            "subcategory":"Repair Shop",
            "type":"Services"
        }
    ],
    "sg:phone":"+61 2 9709 6166",
    "sg:postcode":"2200",
    "sg:province":"NSW",
    "sg:tags":[
        "upholsterer"
    ],
    "wof:name":"Decorative Upholestery Sydney",
    "wof:placetype":"venue"
},
  "geometry": {"coordinates":[151.007858,-33.924793],"type":"Point"}
}