{
  "type": "Feature",
  "properties": {
    "iso:country":"AU",
    "sg:address":"95 Eddy St",
    "sg:city":"Merrylands West",
    "sg:classifiers":[
        {
            "category":"Farming",
            "subcategory":"Fish & Marine Products",
            "type":"Manufacturing & Wholesale Goods"
        }
    ],
    "sg:phone":"+61 415 246 018",
    "sg:postcode":"2160",
    "sg:province":"NSW",
    "sg:tags":[
        "slate"
    ],
    "wof:name":"M Tiling & Polishing",
    "wof:placetype":"venue"
},
  "geometry": {"coordinates":[150.966064453,-33.8355522156],"type":"Point"}
}