{
  "type": "Feature",
  "properties": {
    "addr:full":"Cnr James & Hume Sts Toowoomba QLD 4350",
    "addr:postcode":"4350",
    "addr:street":"Cnr",
    "iso:country":"AU",
    "sg:address":"Cnr James & Hume Sts",
    "sg:city":"Toowoomba",
    "sg:classifiers":[
        {
            "category":"Autos & Motor Vehicles",
            "subcategory":"Automobile Sales",
            "type":"Retail Goods"
        }
    ],
    "sg:phone":"+61 7 4639 0111",
    "sg:postcode":"4350",
    "sg:province":"QLD",
    "sg:tags":[
        "car",
        "new"
    ],
    "wof:name":"West-Star Motors - Mercedes Benz",
    "wof:placetype":"venue"
},
  "geometry": {"coordinates":[151.956512,-27.568443],"type":"Point"}
}