{
  "type": "Feature",
  "properties": {
    "addr:full":"unit 4, 3 Ozone St Chinderah NSW 2487",
    "addr:housenumber":"3",
    "addr:postcode":"2487",
    "addr:street":"Ozone St",
    "iso:country":"AU",
    "sg:address":"unit 4, 3 Ozone St",
    "sg:city":"Chinderah",
    "sg:classifiers":[
        {
            "category":"Retail",
            "subcategory":"Auto Repair",
            "type":"Services"
        }
    ],
    "sg:phone":"+61 2 6674 4999",
    "sg:postcode":"2487",
    "sg:province":"NSW",
    "sg:tags":[
        "repairer",
        "motor",
        "engineer"
    ],
    "wof:name":"Tweed Valley Service Centre",
    "wof:placetype":"venue"
},
  "geometry": {"coordinates":[153.55592346200001,-28.2443256378],"type":"Point"}
}