{
  "type": "Feature",
  "properties": {
    "iso:country":"AU",
    "sg:address":"42- 46 Gordon Ave",
    "sg:city":"Geelong",
    "sg:classifiers":[
        {
            "category":"Wholesale",
            "subcategory":"Electrical",
            "type":"Manufacturing & Wholesale Goods"
        }
    ],
    "sg:phone":"+61 3 5221 6222",
    "sg:postcode":"3220",
    "sg:province":"VIC",
    "sg:tags":[
        "wholesaler"
    ],
    "wof:name":"AWM Electrical",
    "wof:placetype":"venue"
},
  "geometry": {"coordinates":[144.34837300000001,-38.143646],"type":"Point"}
}