{
  "type": "Feature",
  "properties": {
    "addr:full":"Cnr Conara St & Maroochydore Rd Kunda Park QLD 4556",
    "addr:postcode":"4556",
    "addr:street":"Cnr Conara St & Maroochydore Rd",
    "iso:country":"AU",
    "sg:address":"Cnr Conara St & Maroochydore Rd",
    "sg:city":"Kunda Park",
    "sg:classifiers":[
        {
            "category":"Manufacturing",
            "subcategory":"Motor Vehicles & Parts",
            "type":"Manufacturing & Wholesale Goods"
        }
    ],
    "sg:phone":"+61 7 5476 6722",
    "sg:postcode":"4556",
    "sg:province":"QLD",
    "sg:tags":[
        "replacement"
    ],
    "wof:name":"Aussie Auto",
    "wof:placetype":"venue"
},
  "geometry": {"coordinates":[153.03819274899999,-26.6630268097],"type":"Point"}
}