{
  "type": "Feature",
  "properties": {
    "addr:full":"9 Mair Pl Mullaloo WA 6027",
    "addr:housenumber":"9",
    "addr:postcode":"6027",
    "addr:street":"Mair Pl",
    "iso:country":"AU",
    "sg:address":"9 Mair Pl",
    "sg:city":"Mullaloo",
    "sg:classifiers":[
        {
            "category":"Personal",
            "type":"Services"
        }
    ],
    "sg:phone":"+61 8 9307 4826",
    "sg:postcode":"6027",
    "sg:province":"WA",
    "sg:tags":[
        "dressmaker"
    ],
    "wof:name":"Linda Ellis Designs",
    "wof:placetype":"venue"
},
  "geometry": {"coordinates":[115.736198425,-31.7816123962],"type":"Point"}
}