{
  "type": "Feature",
  "properties": {
    "iso:country":"AU",
    "sg:address":"PO Box 185",
    "sg:city":"Ararat",
    "sg:classifiers":[
        {
            "category":"Building & Trades",
            "subcategory":"Cleaning & Sanitation",
            "type":"Services"
        }
    ],
    "sg:phone":"+61 3 5352 3888",
    "sg:postcode":"3377",
    "sg:province":"VIC",
    "sg:tags":[
        "tank",
        "septic"
    ],
    "wof:name":"Ararat & District Septic Tank Cleaning",
    "wof:placetype":"venue"
},
  "geometry": {"coordinates":[142.93130493199999,-37.2824211121],"type":"Point"}
}