{
  "type": "Feature",
  "properties": {
    "addr:full":"21 Crosby St Floreat WA 6014",
    "addr:housenumber":"21",
    "addr:postcode":"6014",
    "addr:street":"Crosby St",
    "iso:country":"AU",
    "sg:address":"21 Crosby St",
    "sg:city":"Floreat",
    "sg:classifiers":[
        {
            "category":"Shopping",
            "subcategory":"Gifts & Souvenirs",
            "type":"Retail Goods"
        }
    ],
    "sg:phone":"+61 8 9387 7973",
    "sg:postcode":"6014",
    "sg:province":"WA",
    "sg:tags":[
        "shop",
        "supply"
    ],
    "wof:name":"Sprite Agencies Gifts & Homewares",
    "wof:placetype":"venue"
},
  "geometry": {"coordinates":[115.80185699499999,-31.9348163605],"type":"Point"}
}