{
  "type": "Feature",
  "properties": {
    "addr:full":"160 Kingswood Rd Engadine NSW 2233",
    "addr:housenumber":"160",
    "addr:postcode":"2233",
    "addr:street":"Kingswood Rd",
    "iso:country":"AU",
    "sg:address":"160 Kingswood Rd",
    "sg:city":"Engadine",
    "sg:classifiers":[
        {
            "category":"Building & Trades",
            "subcategory":"Plumbing",
            "type":"Services"
        }
    ],
    "sg:phone":"+61 2 9520 5569",
    "sg:postcode":"2233",
    "sg:province":"NSW",
    "sg:tags":[
        "tool",
        "air",
        "accessory",
        "supply"
    ],
    "wof:name":"Rowe Pneumatics",
    "wof:placetype":"venue"
},
  "geometry": {"coordinates":[151.01872253400001,-34.0515098572],"type":"Point"}
}