{
  "type": "Feature",
  "properties": {
    "iso:country":"AU",
    "sg:address":"PO Box 209",
    "sg:city":"N Cairns",
    "sg:classifiers":[
        {
            "category":"Education",
            "subcategory":"Dance Studio",
            "type":"Public Place"
        }
    ],
    "sg:phone":"+61 7 4055 2136",
    "sg:postcode":"4870",
    "sg:province":"QLD",
    "sg:tags":[
        "instruction",
        "language"
    ],
    "wof:name":"Study House Australia",
    "wof:placetype":"venue"
},
  "geometry": {"coordinates":[145.66958618199999,-17.0185699463],"type":"Point"}
}