{
  "type": "Feature",
  "properties": {
    "addr:full":"Cnr Princes Hwy & St Vincent St Ulladulla NSW 2539",
    "addr:postcode":"2539",
    "addr:street":"Cnr Princes Hwy & St Vincent St",
    "iso:country":"AU",
    "sg:address":"Cnr Princes Hwy & St Vincent St",
    "sg:city":"Ulladulla",
    "sg:classifiers":[
        {
            "category":"Health Services",
            "subcategory":"Health Practitioner",
            "type":"Services"
        }
    ],
    "sg:phone":"+61 2 4454 5154",
    "sg:postcode":"2539",
    "sg:province":"NSW",
    "sg:tags":[
        "alternative"
    ],
    "wof:name":"Ulladulla Alternate Healing Centre",
    "wof:placetype":"venue"
},
  "geometry": {"coordinates":[150.47564697300001,-35.3510398865],"type":"Point"}
}