{
  "type": "Feature",
  "properties": {
    "iso:country":"AU",
    "sg:address":"9 Ranton St",
    "sg:city":"Cardiff",
    "sg:classifiers":[
        {
            "category":"Bars & Pubs",
            "subcategory":"Gay Bar",
            "type":"Food & Drink"
        }
    ],
    "sg:phone":"+61 2 4954 2966",
    "sg:postcode":"2285",
    "sg:province":"NSW",
    "sg:tags":[
        "plywood",
        "veneer"
    ],
    "wof:name":"Newcastle Timber Trading Co Pty Limited",
    "wof:placetype":"venue"
},
  "geometry": {"coordinates":[151.647216797,-32.9442214966],"type":"Point"}
}