{
  "type": "Feature",
  "properties": {
    "iso:country":"AU",
    "sg:address":"82 City Rd",
    "sg:city":"Beenleigh",
    "sg:classifiers":[
        {
            "category":"Personal",
            "subcategory":"Piercing",
            "type":"Services"
        }
    ],
    "sg:phone":"+61 1300 303 145",
    "sg:postcode":"4207",
    "sg:province":"QLD",
    "sg:tags":[
        "body",
        "ear"
    ],
    "wof:name":"Body Bizarre",
    "wof:placetype":"venue"
},
  "geometry": {"coordinates":[153.20254516599999,-27.714176178],"type":"Point"}
}