{
  "type": "Feature",
  "properties": {
    "iso:country":"AU",
    "sg:address":"136 Railway St",
    "sg:city":"Ayr",
    "sg:classifiers":[
        {
            "category":"Retail",
            "subcategory":"Auto Repair",
            "type":"Services"
        }
    ],
    "sg:phone":"+61 7 4783 5688",
    "sg:postcode":"4807",
    "sg:province":"QLD",
    "sg:tags":[
        "electrical"
    ],
    "wof:name":"Noel's Auto Electrical",
    "wof:placetype":"venue"
},
  "geometry": {"coordinates":[147.401779175,-19.5785102844],"type":"Point"}
}