{
  "type": "Feature",
  "properties": {
    "iso:country":"AU",
    "sg:address":"27 Tone Rd",
    "sg:city":"Wangaratta",
    "sg:classifiers":[
        {
            "category":"Wholesale",
            "subcategory":"Farm Supplies",
            "type":"Manufacturing & Wholesale Goods"
        }
    ],
    "sg:phone":"+61 3 5722 2262",
    "sg:postcode":"3677",
    "sg:province":"VIC",
    "sg:tags":[
        "feed",
        "supplement",
        "stock"
    ],
    "wof:name":"Hunter W B Pty Ltd",
    "wof:placetype":"venue"
},
  "geometry": {"coordinates":[146.308502197,-36.3614959717],"type":"Point"}
}