{
  "type": "Feature",
  "properties": {
    "iso:country":"AU",
    "sg:address":"99 Barkly St",
    "sg:city":"Ararat",
    "sg:classifiers":[
        {
            "category":"Banks & Credit Unions",
            "subcategory":"Financial Services",
            "type":"Services"
        }
    ],
    "sg:phone":"+61 3 5352 4544",
    "sg:postcode":"3377",
    "sg:province":"VIC",
    "sg:tags":[
        "planning"
    ],
    "wof:name":"WHK Financial Planning",
    "wof:placetype":"venue"
},
  "geometry": {"coordinates":[142.92843627900001,-37.2841186523],"type":"Point"}
}