{
  "type": "Feature",
  "properties": {
    "addr:full":"PO Box 61 Deniliquin NSW 2710",
    "addr:postcode":"2710",
    "iso:country":"AU",
    "sg:address":"PO Box 61",
    "sg:city":"Deniliquin",
    "sg:classifiers":[
        {
            "category":"Organizations",
            "subcategory":"Professional Association",
            "type":"Services"
        }
    ],
    "sg:phone":"+61 3 5881 1055",
    "sg:postcode":"2710",
    "sg:province":"NSW",
    "sg:tags":[
        "rural",
        "organisation",
        "production",
        "primary"
    ],
    "wof:name":"Riverina Rural Lands Protection Board",
    "wof:placetype":"venue"
},
  "geometry": {"coordinates":[144.957397461,-35.529499054],"type":"Point"}
}