{
  "type": "Feature",
  "properties": {
    "addr:full":"276 High St (Near CSIRO) Belmont VIC 3216",
    "addr:housenumber":"276",
    "addr:postcode":"3216",
    "addr:street":"High St Near Csiro",
    "iso:country":"AU",
    "sg:address":"276 High St",
    "sg:city":"(Near CSIRO) Belmont",
    "sg:classifiers":[
        {
            "category":"Retail",
            "subcategory":"Auto Repair",
            "type":"Services"
        }
    ],
    "sg:phone":"+61 3 5241 2922",
    "sg:postcode":"3216",
    "sg:province":"VIC",
    "sg:tags":[
        "testing",
        "inspection",
        "motor",
        "vehicle"
    ],
    "wof:name":"Belmont Service Centre",
    "wof:placetype":"venue"
},
  "geometry": {"coordinates":[144.333786011,-38.1832046509],"type":"Point"}
}