{
  "type": "Feature",
  "properties": {
    "addr:full":"U1/ 13 Adventure Pl Caringbah NSW 2229",
    "addr:housenumber":"13",
    "addr:postcode":"2229",
    "addr:street":"U1 /;Pl",
    "iso:country":"AU",
    "sg:address":"U1/ 13 Adventure Pl",
    "sg:city":"Caringbah",
    "sg:classifiers":[
        {
            "category":"Home & Garden",
            "subcategory":"Furniture",
            "type":"Retail Goods"
        }
    ],
    "sg:phone":"+61 2 9531 5465",
    "sg:postcode":"2229",
    "sg:province":"NSW",
    "sg:tags":[
        "business"
    ],
    "wof:name":"Gapcomm Interiors",
    "wof:placetype":"venue"
},
  "geometry": {"coordinates":[151.12994384800001,-34.0292053223],"type":"Point"}
}