{
  "type": "Feature",
  "properties": {
    "addr:full":"12 Fifth St Wingfield SA 5013",
    "addr:housenumber":"12",
    "addr:postcode":"5013",
    "addr:street":"Fifth St",
    "iso:country":"AU",
    "sg:address":"12 Fifth St",
    "sg:city":"Wingfield",
    "sg:classifiers":[
        {
            "category":"Manufacturing",
            "subcategory":"Motor Vehicles & Parts",
            "type":"Manufacturing & Wholesale Goods"
        }
    ],
    "sg:phone":"+61 8 8347 0083",
    "sg:postcode":"5013",
    "sg:province":"SA",
    "sg:tags":[
        "engine",
        "equipment",
        "diesel"
    ],
    "wof:name":"A W Diesel Repair Services",
    "wof:placetype":"venue"
},
  "geometry": {"coordinates":[138.54766845699999,-34.8470993042],"type":"Point"}
}