{
  "type": "Feature",
  "properties": {
    "addr:full":"Shop 7/ 115 Anzac Ave Seymour VIC 3660",
    "addr:housenumber":"shop 7 / 115",
    "addr:postcode":"3660",
    "addr:street":"Anzac Ave",
    "iso:country":"AU",
    "sg:address":"Shop 7/ 115 Anzac Ave",
    "sg:city":"Seymour",
    "sg:classifiers":[
        {
            "category":"Fast Food",
            "type":"Food & Drink"
        }
    ],
    "sg:phone":"+61 3 5799 2667",
    "sg:postcode":"3660",
    "sg:province":"VIC",
    "sg:tags":[
        "away",
        "take"
    ],
    "wof:name":"The Ritz Fish & chips",
    "wof:placetype":"venue"
},
  "geometry": {"coordinates":[145.14649963400001,-37.0302505493],"type":"Point"}
}