{
  "type": "Feature",
  "properties": {
    "iso:country":"AU",
    "sg:address":"PO Box 197",
    "sg:city":"Nightcliff",
    "sg:classifiers":[
        {
            "category":"Banks & Credit Unions",
            "subcategory":"Bank",
            "type":"Services"
        }
    ],
    "sg:phone":"+61 8 8985 2127",
    "sg:postcode":"0814",
    "sg:province":"NT",
    "sg:tags":[
        "broker",
        "mortgage"
    ],
    "wof:name":"All Purpose Loans",
    "wof:placetype":"venue"
},
  "geometry": {"coordinates":[130.856064,-12.387455],"type":"Point"}
}