{
  "type": "Feature",
  "properties": {
    "addr:full":"61 Leabons La Seven Hills NSW 2147",
    "addr:housenumber":"61",
    "addr:postcode":"2147",
    "addr:street":"Leabons La",
    "iso:country":"AU",
    "sg:address":"61 Leabons La",
    "sg:city":"Seven Hills",
    "sg:classifiers":[
        {
            "category":"Food & Beverages",
            "subcategory":"Bakery",
            "type":"Retail Goods"
        }
    ],
    "sg:phone":"+61 2 9671 2191",
    "sg:postcode":"2147",
    "sg:province":"NSW",
    "sg:tags":[
        "cake",
        "shop",
        "pastry"
    ],
    "wof:name":"Cheesecake Shop The",
    "wof:placetype":"venue"
},
  "geometry": {"coordinates":[150.921142578,-33.7799987793],"type":"Point"}
}