{
  "type": "Feature",
  "properties": {
    "iso:country":"AU",
    "sg:address":"1471 Pittwater Rd",
    "sg:city":"North Narrabeen",
    "sg:classifiers":[
        {
            "category":"Autos & Motor Vehicles",
            "subcategory":"Automobile Sales",
            "type":"Retail Goods"
        }
    ],
    "sg:phone":"+61 2 9913 8499",
    "sg:postcode":"2101",
    "sg:province":"NSW",
    "sg:tags":[
        "car",
        "used"
    ],
    "wof:name":"North Narrabeen Motors",
    "wof:placetype":"venue"
},
  "geometry": {"coordinates":[151.301819,-33.695698],"type":"Point"}
}