{
  "type": "Feature",
  "properties": {
    "addr:full":"7/ 1 Ada St Randwick NSW 2031",
    "addr:housenumber":"/ 1",
    "addr:postcode":"2031",
    "addr:street":"Ada St",
    "iso:country":"AU",
    "sg:address":"7/ 1 Ada St",
    "sg:city":"Randwick",
    "sg:classifiers":[
        {
            "category":"Personal",
            "type":"Services"
        }
    ],
    "sg:phone":"+61 410 307 720",
    "sg:postcode":"2031",
    "sg:province":"NSW",
    "sg:tags":[
        "introduction",
        "social"
    ],
    "wof:name":"Eat Drink Man Woman Cooking Classes & Events",
    "wof:placetype":"venue"
},
  "geometry": {"coordinates":[151.24357605,-33.9167633057],"type":"Point"}
}