{
  "type": "Feature",
  "properties": {
    "addr:full":"1 Coonamble Coonabarabran Rd Bugaldie NSW 2357",
    "addr:housenumber":"1",
    "addr:postcode":"2357",
    "addr:street":"Coonabarabran Rd",
    "iso:country":"AU",
    "sg:address":"1 Coonamble Coonabarabran Rd",
    "sg:city":"Bugaldie",
    "sg:classifiers":[
        {
            "category":"Food & Beverages",
            "subcategory":"Groceries & Convenience Stores",
            "type":"Retail Goods"
        }
    ],
    "sg:phone":"+61 2 6843 4426",
    "sg:postcode":"2357",
    "sg:province":"NSW",
    "wof:name":"Bugaldie General Store",
    "wof:placetype":"venue"
},
  "geometry": {"coordinates":[149.287506103,-31.2750701904],"type":"Point"}
}