{
  "type": "Feature",
  "properties": {
    "addr:full":"19 Warehouse Rd Southport QLD 4215",
    "addr:housenumber":"19",
    "addr:postcode":"4215",
    "addr:street":"Warehouse Rd",
    "iso:country":"AU",
    "sg:address":"19 Warehouse Rd",
    "sg:city":"Southport",
    "sg:classifiers":[
        {
            "category":"Home & Garden",
            "subcategory":"Carpets & Floor Coverings",
            "type":"Retail Goods"
        }
    ],
    "sg:phone":"+61 7 5591 4788",
    "sg:postcode":"4215",
    "sg:province":"QLD",
    "sg:tags":[
        "wood"
    ],
    "wof:name":"Carpet One Southport",
    "wof:placetype":"venue"
},
  "geometry": {"coordinates":[153.408935547,-27.979801178],"type":"Point"}
}