{
  "type": "Feature",
  "properties": {
    "iso:country":"AU",
    "sg:address":"590 Bourke St",
    "sg:city":"Surry Hills",
    "sg:classifiers":[
        {
            "category":"Education",
            "subcategory":"School",
            "type":"Public Place"
        }
    ],
    "sg:phone":"+61 2 9699 1571",
    "sg:postcode":"2010",
    "sg:province":"NSW",
    "sg:tags":[
        "state",
        "-",
        "nsw"
    ],
    "wof:name":"Bourke Street Public School",
    "wof:placetype":"venue"
},
  "geometry": {"coordinates":[151.21496582,-33.8903923035],"type":"Point"}
}