{
  "type": "Feature",
  "properties": {
    "addr:full":"247 Glebe Point Rd Glebe NSW 2037",
    "addr:housenumber":"247",
    "addr:postcode":"2037",
    "addr:street":"Glebe Point Rd",
    "iso:country":"AU",
    "sg:address":"247 Glebe Point Rd",
    "sg:city":"Glebe",
    "sg:classifiers":[
        {
            "category":"Real Estate",
            "subcategory":"Real Estate Agent",
            "type":"Services"
        }
    ],
    "sg:phone":"+61 2 9660 2211",
    "sg:postcode":"2037",
    "sg:province":"NSW",
    "wof:name":"Raine & Horne",
    "wof:placetype":"venue"
},
  "geometry": {"coordinates":[151.18678283700001,-33.8792724609],"type":"Point"}
}