{
  "type": "Feature",
  "properties": {
    "addr:full":"19 York St Kalgoorlie WA 6430",
    "addr:housenumber":"19",
    "addr:postcode":"6430",
    "addr:street":"York St",
    "iso:country":"AU",
    "sg:address":"19 York St",
    "sg:city":"Kalgoorlie",
    "sg:classifiers":[
        {
            "category":"Health Services",
            "subcategory":"Doctor",
            "type":"Services"
        }
    ],
    "sg:phone":"+61 8 9091 2363",
    "sg:postcode":"6430",
    "sg:province":"WA",
    "sg:tags":[
        "nurse",
        "nursing"
    ],
    "wof:name":"Silver Chain",
    "wof:placetype":"venue"
},
  "geometry": {"coordinates":[121.488929748,-30.7732868195],"type":"Point"}
}