{
  "type": "Feature",
  "properties": {
    "iso:country":"AU",
    "sg:address":"25- 27 Green St",
    "sg:city":"Banksmeadow",
    "sg:classifiers":[
        {
            "category":"Manufacturing",
            "subcategory":"Glass & Minerals",
            "type":"Manufacturing & Wholesale Goods"
        }
    ],
    "sg:phone":"+61 2 9666 3788",
    "sg:postcode":"2019",
    "sg:province":"NSW",
    "sg:tags":[
        "fabricator",
        "foam",
        "processor"
    ],
    "wof:name":"Era Polymers Pty Ltd",
    "wof:placetype":"venue"
},
  "geometry": {"coordinates":[151.21388244600001,-33.9441566467],"type":"Point"}
}