{
  "type": "Feature",
  "properties": {
    "addr:full":"340 Whitehorse Rd Balwyn VIC 3103",
    "addr:housenumber":"340",
    "addr:postcode":"3103",
    "addr:street":"Whitehorse Rd",
    "iso:country":"AU",
    "sg:address":"340 Whitehorse Rd",
    "sg:city":"Balwyn",
    "sg:classifiers":[
        {
            "category":"Health Services",
            "subcategory":"Dentist",
            "type":"Services"
        }
    ],
    "sg:phone":"+61 3 9817 6044",
    "sg:postcode":"3103",
    "sg:province":"VIC",
    "sg:tags":[
        "dental",
        "prosthetist"
    ],
    "wof:name":"Nash Gregory P",
    "wof:placetype":"venue"
},
  "geometry": {"coordinates":[145.08605957,-37.8135261536],"type":"Point"}
}