{
  "type": "Feature",
  "properties": {
    "iso:country":"AU",
    "sg:address":"28- 30 Rymill Crt",
    "sg:city":"Altona North",
    "sg:classifiers":[
        {
            "category":"Health Services",
            "subcategory":"Nursing And Care Facility",
            "type":"Services"
        }
    ],
    "sg:phone":"+61 3 9318 9155",
    "sg:postcode":"3025",
    "sg:province":"VIC",
    "sg:tags":[
        "home"
    ],
    "wof:name":"Hobson's Bay Nursing Centre",
    "wof:placetype":"venue"
},
  "geometry": {"coordinates":[144.839447,-37.832703],"type":"Point"}
}