{
  "type": "Feature",
  "properties": {
    "addr:full":"Sharland Rd Corio VIC 3214",
    "addr:postcode":"3214",
    "addr:street":"Sharland Rd",
    "iso:country":"AU",
    "sg:address":"Sharland Rd",
    "sg:city":"Corio",
    "sg:classifiers":[
        {
            "category":"Education",
            "subcategory":"School",
            "type":"Public Place"
        }
    ],
    "sg:phone":"+61 3 5275 3986",
    "sg:postcode":"3214",
    "sg:province":"VIC",
    "sg:tags":[
        "state",
        "except",
        "nsw"
    ],
    "wof:name":"Rosewall Primary School",
    "wof:placetype":"venue"
},
  "geometry": {"coordinates":[144.36833190900001,-38.0654144287],"type":"Point"}
}