{
  "type": "Feature",
  "properties": {
    "addr:full":"PO Box 257 Richmond VIC 3121",
    "addr:postcode":"3121",
    "iso:country":"AU",
    "sg:address":"PO Box 257",
    "sg:city":"Richmond",
    "sg:classifiers":[
        {
            "category":"Professional",
            "subcategory":"Accounting & Tax Preparation",
            "type":"Services"
        }
    ],
    "sg:phone":"+61 3 9420 7400",
    "sg:postcode":"3121",
    "sg:province":"VIC",
    "sg:tags":[
        "accountant",
        "auditor"
    ],
    "wof:name":"Manning & Perry",
    "wof:placetype":"venue"
},
  "geometry": {"coordinates":[144.99945068400001,-37.8170204163],"type":"Point"}
}