{
  "type": "Feature",
  "properties": {
    "addr:full":"48 Hope St Brunswick VIC 3056",
    "addr:housenumber":"48",
    "addr:postcode":"3056",
    "addr:street":"Hope St",
    "iso:country":"AU",
    "sg:address":"48 Hope St",
    "sg:city":"Brunswick",
    "sg:classifiers":[
        {
            "category":"Wholesale",
            "subcategory":"Home Furnishings",
            "type":"Manufacturing & Wholesale Goods"
        }
    ],
    "sg:phone":"+61 3 9387 2382",
    "sg:postcode":"3056",
    "sg:province":"VIC",
    "sg:tags":[
        "wholesaler",
        "bedding",
        "mfrs",
        "bed"
    ],
    "wof:name":"Thomas International Design",
    "wof:placetype":"venue"
},
  "geometry": {"coordinates":[144.95863342300001,-37.7636375427],"type":"Point"}
}