{
  "type": "Feature",
  "properties": {
    "addr:full":"82 Harris St Pyrmont NSW 2009",
    "addr:housenumber":"82",
    "addr:postcode":"2009",
    "addr:street":"Harris St",
    "iso:country":"AU",
    "sg:address":"82 Harris St",
    "sg:city":"Pyrmont",
    "sg:classifiers":[
        {
            "category":"Professional",
            "subcategory":"Business Services",
            "type":"Services"
        }
    ],
    "sg:phone":"+61 2 9571 1288",
    "sg:postcode":"2009",
    "sg:province":"NSW",
    "sg:tags":[
        "management",
        "event"
    ],
    "wof:name":"thirdeye Australia Pty Ltd",
    "wof:placetype":"venue"
},
  "geometry": {"coordinates":[151.19314575199999,-33.8680686951],"type":"Point"}
}