{
  "type": "Feature",
  "properties": {
    "addr:full":"78 Prince St Grafton NSW 2460",
    "addr:housenumber":"78",
    "addr:postcode":"2460",
    "addr:street":"Prince St",
    "iso:country":"AU",
    "sg:address":"78 Prince St",
    "sg:city":"Grafton",
    "sg:classifiers":[
        {
            "category":"Personal",
            "subcategory":"Beauty Salon",
            "type":"Services"
        }
    ],
    "sg:phone":"+61 2 6642 2209",
    "sg:postcode":"2460",
    "sg:province":"NSW",
    "sg:tags":[
        "hairdresser"
    ],
    "wof:name":"Images Naturally",
    "wof:placetype":"venue"
},
  "geometry": {"coordinates":[152.93443298299999,-29.6900978088],"type":"Point"}
}