{
  "type": "Feature",
  "properties": {
    "addr:full":"67 Milson Rd Cremorne Point NSW 2090",
    "addr:housenumber":"67",
    "addr:postcode":"2090",
    "addr:street":"Milson Rd",
    "iso:country":"AU",
    "sg:address":"67 Milson Rd",
    "sg:city":"Cremorne Point",
    "sg:classifiers":[
        {
            "category":"Real Estate",
            "subcategory":"Architect",
            "type":"Services"
        }
    ],
    "sg:phone":"+61 2 9909 1277",
    "sg:postcode":"2090",
    "sg:province":"NSW",
    "wof:name":"Berkemeier Paul Architect Pty Ltd",
    "wof:placetype":"venue"
},
  "geometry": {"coordinates":[151.227584839,-33.8425598145],"type":"Point"}
}