{
  "type": "Feature",
  "properties": {
    "iso:country":"AU",
    "sg:address":"160 Bacchus Marsh Rd",
    "sg:city":"Corio",
    "sg:classifiers":[
        {
            "category":"Autos & Motor Vehicles",
            "subcategory":"Fuel & Gas Station",
            "type":"Retail Goods"
        }
    ],
    "sg:phone":"+61 3 5274 9959",
    "sg:postcode":"3214",
    "sg:province":"VIC",
    "wof:name":"United Petroleum",
    "wof:placetype":"venue"
},
  "geometry": {"coordinates":[144.35919189399999,-38.0714263916],"type":"Point"}
}