{
  "type": "Feature",
  "properties": {
    "addr:full":"15- 17 Bowen Rd Mundingburra QLD 4812",
    "addr:housenumber":"17",
    "addr:postcode":"4812",
    "addr:street":"Bowen Rd",
    "iso:country":"AU",
    "sg:address":"15- 17 Bowen Rd",
    "sg:city":"Mundingburra",
    "sg:classifiers":[
        {
            "category":"Autos & Motor Vehicles",
            "subcategory":"Automobile Sales",
            "type":"Retail Goods"
        }
    ],
    "sg:phone":"+61 7 4725 6222",
    "sg:postcode":"4812",
    "sg:province":"QLD",
    "sg:tags":[
        "car",
        "used"
    ],
    "wof:name":"Honeycombes Automotive Group",
    "wof:placetype":"venue"
},
  "geometry": {"coordinates":[146.79585299999999,-19.292467],"type":"Point"}
}