{
  "type": "Feature",
  "properties": {
    "addr:full":"PO Box 161 Mermaid Waters QLD 4218",
    "addr:postcode":"4218",
    "iso:country":"AU",
    "sg:address":"PO Box 161",
    "sg:city":"Mermaid Waters",
    "sg:classifiers":[
        {
            "category":"Building & Trades",
            "subcategory":"Landscaping Services",
            "type":"Services"
        }
    ],
    "sg:phone":"+61 7 5524 2211",
    "sg:postcode":"4218",
    "sg:province":"QLD",
    "sg:tags":[
        "stump",
        "tree",
        "felling",
        "removal"
    ],
    "wof:name":"Joe Lop",
    "wof:placetype":"venue"
},
  "geometry": {"coordinates":[153.432037353,-28.0367908478],"type":"Point"}
}