{
  "type": "Feature",
  "properties": {
    "iso:country":"AU",
    "sg:address":"3 Hockley La",
    "sg:city":"Urangan",
    "sg:classifiers":[
        {
            "category":"Building & Trades",
            "subcategory":"Plumbing",
            "type":"Services"
        }
    ],
    "sg:phone":"+61 7 4125 1846",
    "sg:postcode":"4655",
    "sg:province":"QLD",
    "sg:tags":[
        "plumber",
        "gasfitters"
    ],
    "wof:name":"Peart AC & HC Plumbing",
    "wof:placetype":"venue"
},
  "geometry": {"coordinates":[152.88913,-25.281742],"type":"Point"}
}