{
  "type": "Feature",
  "properties": {
    "addr:full":"99 Liverpool St Scone NSW 2337",
    "addr:housenumber":"99",
    "addr:postcode":"2337",
    "addr:street":"Liverpool St",
    "iso:country":"AU",
    "sg:address":"99 Liverpool St",
    "sg:city":"Scone",
    "sg:classifiers":[
        {
            "category":"Professional",
            "subcategory":"Art Services",
            "type":"Services"
        }
    ],
    "sg:phone":"+61 2 6545 9899",
    "sg:postcode":"2337",
    "sg:province":"NSW",
    "sg:tags":[
        "interior",
        "decorator"
    ],
    "wof:name":"plain# English",
    "wof:placetype":"venue"
},
  "geometry": {"coordinates":[150.86492919899999,-32.0504341125],"type":"Point"}
}