{
  "type": "Feature",
  "properties": {
    "iso:country":"AU",
    "sg:address":"2 Fitzalan St",
    "sg:city":"Bowen",
    "sg:classifiers":[
        {
            "category":"Transit Center",
            "subcategory":"Freight",
            "type":"Transportation"
        }
    ],
    "sg:phone":"+61 7 4786 2993",
    "sg:postcode":"4805",
    "sg:province":"QLD",
    "sg:tags":[
        "forklift",
        "truck"
    ],
    "wof:name":"Bowen Forklift Repairs",
    "wof:placetype":"venue"
},
  "geometry": {"coordinates":[148.22836303700001,-19.9967441559],"type":"Point"}
}