{
  "type": "Feature",
  "properties": {
    "iso:country":"AU",
    "sg:address":"27 Separation St",
    "sg:city":"Geelong North",
    "sg:classifiers":[
        {
            "category":"Retail",
            "subcategory":"Auto Repair",
            "type":"Services"
        }
    ],
    "sg:phone":"+61 3 5272 2044",
    "sg:postcode":"3215",
    "sg:province":"VIC",
    "sg:tags":[
        "repairer",
        "motor",
        "engineer"
    ],
    "wof:name":"Campana Car Sales & Service",
    "wof:placetype":"venue"
},
  "geometry": {"coordinates":[144.34783935600001,-38.1114273071],"type":"Point"}
}