{
  "type": "Feature",
  "properties": {
    "addr:full":"213 Westblade Ave Kerang VIC 3579",
    "addr:housenumber":"213",
    "addr:postcode":"3579",
    "addr:street":"Westblade Ave",
    "iso:country":"AU",
    "sg:address":"213 Westblade Ave",
    "sg:city":"Kerang",
    "sg:classifiers":[
        {
            "category":"Professional",
            "subcategory":"Art Services",
            "type":"Services"
        }
    ],
    "sg:phone":"+61 417 561 008",
    "sg:postcode":"3579",
    "sg:province":"VIC",
    "sg:tags":[
        "decorator",
        "painter"
    ],
    "wof:name":"Tony Southern",
    "wof:placetype":"venue"
},
  "geometry": {"coordinates":[143.923370361,-35.726020813],"type":"Point"}
}