{
  "type": "Feature",
  "properties": {
    "iso:country":"AU",
    "sg:address":"40 Roscommon Rd",
    "sg:city":"Boondall",
    "sg:classifiers":[
        {
            "category":"Professional",
            "subcategory":"Detective & Security Services",
            "type":"Services"
        }
    ],
    "sg:phone":"+61 404 042 091",
    "sg:postcode":"4034",
    "sg:province":"QLD",
    "sg:tags":[
        "consultant",
        "system"
    ],
    "wof:name":"Ideal Security Systems",
    "wof:placetype":"venue"
},
  "geometry": {"coordinates":[153.061905,-27.349007],"type":"Point"}
}