{
  "type": "Feature",
  "properties": {
    "addr:full":"\"Mayfield\", Kane Rd Gundillion NSW 2622",
    "addr:postcode":"2622",
    "addr:street":"Kane Rd",
    "iso:country":"AU",
    "sg:address":"\"Mayfield\", Kane Rd",
    "sg:city":"Gundillion",
    "sg:classifiers":[
        {
            "category":"Building & Trades",
            "subcategory":"Landscaping Services",
            "type":"Services"
        }
    ],
    "sg:phone":"+61 2 4847 1124",
    "sg:postcode":"2622",
    "sg:province":"NSW",
    "sg:tags":[
        "grazier"
    ],
    "wof:name":"Hobday J M",
    "wof:placetype":"venue"
},
  "geometry": {"coordinates":[149.75262451200001,-35.3117485046],"type":"Point"}
}