{
  "type": "Feature",
  "properties": {
    "addr:full":"12/ 520 Mt Dandenong Rd Kilsyth VIC 3137",
    "addr:housenumber":"12 / 520",
    "addr:postcode":"3137",
    "addr:street":"Mt Dandenong Rd",
    "iso:country":"AU",
    "sg:address":"12/ 520 Mt Dandenong Rd",
    "sg:city":"Kilsyth",
    "sg:classifiers":[
        {
            "category":"Real Estate",
            "subcategory":"Real Estate Agent",
            "type":"Services"
        }
    ],
    "sg:phone":"+61 3 9725 9900",
    "sg:postcode":"3137",
    "sg:province":"VIC",
    "wof:name":"Max Brown Real Estate",
    "wof:placetype":"venue"
},
  "geometry": {"coordinates":[145.30946350100001,-37.802066803],"type":"Point"}
}