{
  "type": "Feature",
  "properties": {
    "addr:full":"25 Carlisle Rd Hallam VIC 3803",
    "addr:housenumber":"25",
    "addr:postcode":"3803",
    "addr:street":"Carlisle Rd",
    "iso:country":"AU",
    "sg:address":"25 Carlisle Rd",
    "sg:city":"Hallam",
    "sg:classifiers":[
        {
            "category":"Home & Garden",
            "subcategory":"Carpets & Floor Coverings",
            "type":"Retail Goods"
        }
    ],
    "sg:phone":"+61 3 9703 0224",
    "sg:postcode":"3803",
    "sg:province":"VIC",
    "sg:tags":[
        "tile",
        "wall"
    ],
    "wof:name":"Aqua Tiling",
    "wof:placetype":"venue"
},
  "geometry": {"coordinates":[145.25454711899999,-38.0004692078],"type":"Point"}
}