{
  "type": "Feature",
  "properties": {
    "addr:full":"13 Heathbrook Crt Caboolture QLD 4510",
    "addr:housenumber":"13",
    "addr:postcode":"4510",
    "addr:street":"Heathbrook Crt",
    "iso:country":"AU",
    "sg:address":"13 Heathbrook Crt",
    "sg:city":"Caboolture",
    "sg:classifiers":[
        {
            "category":"Professional",
            "subcategory":"Detective & Security Services",
            "type":"Services"
        }
    ],
    "sg:phone":"+61 7 5499 2788",
    "sg:postcode":"4510",
    "sg:province":"QLD",
    "sg:tags":[
        "equipment",
        "window",
        "doors"
    ],
    "wof:name":"Field Enterprises Qld",
    "wof:placetype":"venue"
},
  "geometry": {"coordinates":[152.94137599999999,-27.049761],"type":"Point"}
}