{
  "type": "Feature",
  "properties": {
    "iso:country":"AU",
    "sg:address":"Chinderah Bay Drv",
    "sg:city":"Chinderah",
    "sg:classifiers":[
        {
            "category":"Professional",
            "subcategory":"Engineering",
            "type":"Services"
        }
    ],
    "sg:phone":"+61 2 6674 1306",
    "sg:postcode":"2487",
    "sg:province":"NSW",
    "sg:tags":[
        "engineer"
    ],
    "wof:name":"Rico Recovery System Aust Pty Ltd",
    "wof:placetype":"venue"
},
  "geometry": {"coordinates":[153.54649352999999,-28.2411727905],"type":"Point"}
}