{
  "type": "Feature",
  "properties": {
    "addr:full":"56 Foster St Dandenong VIC 3175",
    "addr:housenumber":"56",
    "addr:postcode":"3175",
    "addr:street":"Foster St",
    "iso:country":"AU",
    "sg:address":"56 Foster St",
    "sg:city":"Dandenong",
    "sg:classifiers":[
        {
            "category":"Wholesale",
            "subcategory":"Apparel",
            "type":"Manufacturing & Wholesale Goods"
        }
    ],
    "sg:phone":"+61 3 9792 0424",
    "sg:postcode":"3175",
    "sg:province":"VIC",
    "sg:tags":[
        "wholesaler",
        "men's",
        "mfrs",
        "sportswear"
    ],
    "wof:name":"Frimley Sports Uniforms",
    "wof:placetype":"venue"
},
  "geometry": {"coordinates":[145.211227417,-37.9897613525],"type":"Point"}
}