{
  "type": "Feature",
  "properties": {
    "addr:full":"288 Gnangara Rd Landsdale WA 6065",
    "addr:housenumber":"288",
    "addr:postcode":"6065",
    "addr:street":"Gnangara Rd",
    "iso:country":"AU",
    "sg:address":"288 Gnangara Rd",
    "sg:city":"Landsdale",
    "sg:classifiers":[
        {
            "category":"Autos & Motor Vehicles",
            "subcategory":"Boat Sales",
            "type":"Retail Goods"
        }
    ],
    "sg:phone":"+61 8 9302 2293",
    "sg:postcode":"6065",
    "sg:province":"WA",
    "sg:tags":[
        "builder",
        "yacht",
        "repairer"
    ],
    "wof:name":"Marineline Boatbuilders",
    "wof:placetype":"venue"
},
  "geometry": {"coordinates":[115.84883117699999,-31.7977828979],"type":"Point"}
}