{
  "type": "Feature",
  "properties": {
    "iso:country":"AU",
    "sg:address":"Suite 16 / 279 Lord St",
    "sg:city":"East Perth",
    "sg:classifiers":[
        {
            "category":"Professional",
            "subcategory":"Business Services",
            "type":"Services"
        }
    ],
    "sg:phone":"+61 8 9227 1366",
    "sg:postcode":"6004",
    "sg:province":"WA",
    "sg:tags":[
        "drafting"
    ],
    "wof:name":"Mitsopoulos T & Associates Structural Drafting Services",
    "wof:placetype":"venue"
},
  "geometry": {"coordinates":[115.872642517,-31.9446792603],"type":"Point"}
}