{
  "type": "Feature",
  "properties": {
    "iso:country":"AU",
    "sg:address":"Cnr Bridge & Walnut St",
    "sg:city":"Reynella",
    "sg:classifiers":[
        {
            "category":"Social Services",
            "subcategory":"Retirement Home",
            "type":"Services"
        }
    ],
    "sg:phone":"+61 8 8322 8044",
    "sg:postcode":"5161",
    "sg:province":"SA",
    "sg:tags":[
        "village"
    ],
    "wof:name":"Walnut Grove Estate Pty Ltd",
    "wof:placetype":"venue"
},
  "geometry": {"coordinates":[138.53814697300001,-35.0929908752],"type":"Point"}
}