{
  "type": "Feature",
  "properties": {
    "addr:full":"PO Box 305 Belconnen ACT 2616",
    "addr:postcode":"2616",
    "iso:country":"AU",
    "sg:address":"PO Box 305",
    "sg:city":"Belconnen",
    "sg:classifiers":[
        {
            "category":"Education",
            "subcategory":"Music School",
            "type":"Public Place"
        }
    ],
    "sg:phone":"+61 2 6259 3891",
    "sg:postcode":"2616",
    "sg:province":"ACT",
    "sg:tags":[
        "teacher"
    ],
    "wof:name":"Blue Phoenix Music Studio",
    "wof:placetype":"venue"
},
  "geometry": {"coordinates":[149.06735229500001,-35.2362289429],"type":"Point"}
}