{
  "type": "Feature",
  "properties": {
    "addr:full":"34 Corporate Drv Cannon Hill QLD 4170",
    "addr:housenumber":"34",
    "addr:postcode":"4170",
    "addr:street":"Corporate Drv",
    "iso:country":"AU",
    "sg:address":"34 Corporate Drv",
    "sg:city":"Cannon Hill",
    "sg:classifiers":[
        {
            "category":"Professional",
            "subcategory":"Detective & Security Services",
            "type":"Services"
        }
    ],
    "sg:phone":"+61 13 10 05",
    "sg:postcode":"4170",
    "sg:province":"QLD",
    "sg:tags":[
        "consultant",
        "system"
    ],
    "wof:name":"Sensormatic",
    "wof:placetype":"venue"
},
  "geometry": {"coordinates":[153.09034729000001,-27.4669322968],"type":"Point"}
}