{
  "type": "Feature",
  "properties": {
    "addr:full":"PO Box 466 Cannon Hill QLD 4170",
    "addr:postcode":"4170",
    "iso:country":"AU",
    "sg:address":"PO Box 466",
    "sg:city":"Cannon Hill",
    "sg:classifiers":[
        {
            "category":"Utilities",
            "subcategory":"Refuse",
            "type":"Services"
        }
    ],
    "sg:phone":"+61 1300 253 276",
    "sg:postcode":"4170",
    "sg:province":"QLD",
    "sg:tags":[
        "remover",
        "rubbish"
    ],
    "wof:name":"1300 Clearout Pty Ltd",
    "wof:placetype":"venue"
},
  "geometry": {"coordinates":[153.089447022,-27.4577693939],"type":"Point"}
}