{
  "type": "Feature",
  "properties": {
    "iso:country":"AU",
    "sg:address":"3 Shuffrey St",
    "sg:city":"Fremantle",
    "sg:classifiers":[
        {
            "category":"Professional",
            "subcategory":"Business Services",
            "type":"Services"
        }
    ],
    "sg:phone":"+61 8 9335 5511",
    "sg:postcode":"6160",
    "sg:province":"WA",
    "sg:tags":[
        "exporter"
    ],
    "wof:name":"Culley Group Australia Pty Ltd",
    "wof:placetype":"venue"
},
  "geometry": {"coordinates":[115.752052,-32.048],"type":"Point"}
}