{
  "type": "Feature",
  "properties": {
    "addr:full":"14 Gum Ave Dry Creek SA 5094",
    "addr:housenumber":"14",
    "addr:postcode":"5094",
    "addr:street":"Gum Ave Dry",
    "iso:country":"AU",
    "sg:address":"14 Gum Ave",
    "sg:city":"Dry Creek",
    "sg:classifiers":[
        {
            "category":"Home & Garden",
            "subcategory":"Building Materials",
            "type":"Retail Goods"
        }
    ],
    "sg:phone":"+61 408 282 101",
    "sg:postcode":"5094",
    "sg:province":"SA",
    "sg:tags":[
        "secondhand"
    ],
    "wof:name":"DPC Demolition & Salvage",
    "wof:placetype":"venue"
},
  "geometry": {"coordinates":[138.589233398,-34.8376045227],"type":"Point"}
}