{
  "type": "Feature",
  "properties": {
    "addr:full":"199 Spooners Ave Kempsey NSW 2440",
    "addr:housenumber":"199",
    "addr:postcode":"2440",
    "addr:street":"Spooners Ave",
    "iso:country":"AU",
    "sg:address":"199 Spooners Ave",
    "sg:city":"Kempsey",
    "sg:classifiers":[
        {
            "category":"Farming",
            "subcategory":"Vineyard",
            "type":"Manufacturing & Wholesale Goods"
        }
    ],
    "sg:phone":"+61 2 6563 1356",
    "sg:postcode":"2440",
    "sg:province":"NSW",
    "sg:tags":[
        "winery"
    ],
    "wof:name":"Dangars Creek Vineyard",
    "wof:placetype":"venue"
},
  "geometry": {"coordinates":[152.80690000000001,-31.033249],"type":"Point"}
}