{
  "type": "Feature",
  "properties": {
    "addr:full":"32 Ada Ave Strathfield NSW 2135",
    "addr:housenumber":"32",
    "addr:postcode":"2135",
    "addr:street":"Ada Ave",
    "iso:country":"AU",
    "sg:address":"32 Ada Ave",
    "sg:city":"Strathfield",
    "sg:classifiers":[
        {
            "category":"Wholesale",
            "subcategory":"Construction Materials",
            "type":"Manufacturing & Wholesale Goods"
        }
    ],
    "sg:phone":"+61 2 9758 7868",
    "sg:postcode":"2135",
    "sg:province":"NSW",
    "sg:tags":[
        "wholesaler",
        "lighting",
        "mfrs",
        "accessory"
    ],
    "wof:name":"Ideal Corporation Pty Ltd",
    "wof:placetype":"venue"
},
  "geometry": {"coordinates":[151.07818603499999,-33.8815078735],"type":"Point"}
}