{
  "type": "Feature",
  "properties": {
    "iso:country":"AU",
    "sg:address":"332 Alison Rd",
    "sg:city":"Coogee",
    "sg:classifiers":[
        {
            "category":"Manufacturing",
            "subcategory":"Jewelry",
            "type":"Manufacturing & Wholesale Goods"
        }
    ],
    "sg:phone":"+61 2 9665 2264",
    "sg:postcode":"2034",
    "sg:province":"NSW",
    "sg:tags":[
        "designer",
        "jewellery"
    ],
    "wof:name":"Hablitschek John Gems Pty Ltd",
    "wof:placetype":"venue"
},
  "geometry": {"coordinates":[151.25497436500001,-33.915222168],"type":"Point"}
}