{
  "type": "Feature",
  "properties": {
    "addr:full":"214 Kensington Rd Marryatville SA 5068",
    "addr:housenumber":"214",
    "addr:postcode":"5068",
    "addr:street":"Kensington Rd",
    "iso:country":"AU",
    "sg:address":"214 Kensington Rd",
    "sg:city":"Marryatville",
    "sg:classifiers":[
        {
            "category":"Health Services",
            "subcategory":"Dentist",
            "type":"Services"
        }
    ],
    "sg:phone":"+61 8 8378 1620",
    "sg:postcode":"5068",
    "sg:province":"SA",
    "wof:name":"Marryatville Dental Surgery",
    "wof:placetype":"venue"
},
  "geometry": {"coordinates":[138.64855957,-34.9267044067],"type":"Point"}
}