{
  "type": "Feature",
  "properties": {
    "addr:full":"19 Gozo Rd Greystanes NSW 2145",
    "addr:housenumber":"19",
    "addr:postcode":"2145",
    "addr:street":"Gozo Rd",
    "iso:country":"AU",
    "sg:address":"19 Gozo Rd",
    "sg:city":"Greystanes",
    "sg:classifiers":[
        {
            "category":"Social Services",
            "subcategory":"Child Care",
            "type":"Services"
        }
    ],
    "sg:phone":"+61 2 9896 2772",
    "sg:postcode":"2145",
    "sg:province":"NSW",
    "wof:name":"Munchkin Manor Child Care Centre",
    "wof:placetype":"venue"
},
  "geometry": {"coordinates":[150.937210083,-33.8206672668],"type":"Point"}
}