{
  "type": "Feature",
  "properties": {
    "addr:full":"13 Heath St Lonsdale SA 5160",
    "addr:housenumber":"13",
    "addr:postcode":"5160",
    "addr:street":"Heath St",
    "iso:country":"AU",
    "sg:address":"13 Heath St",
    "sg:city":"Lonsdale",
    "sg:classifiers":[
        {
            "category":"Manufacturing",
            "subcategory":"Metals",
            "type":"Manufacturing & Wholesale Goods"
        }
    ],
    "sg:phone":"+61 8 8326 3955",
    "sg:postcode":"5160",
    "sg:province":"SA",
    "sg:tags":[
        "steel",
        "fabricator",
        "mfrs"
    ],
    "wof:name":"Combined Resource Engineering",
    "wof:placetype":"venue"
},
  "geometry": {"coordinates":[138.50050354000001,-35.1132316589],"type":"Point"}
}