{
  "type": "Feature",
  "properties": {
    "iso:country":"AU",
    "sg:address":"29 Clark St",
    "sg:city":"Wangaratta",
    "sg:classifiers":[
        {
            "category":"Health Services",
            "subcategory":"Doctor",
            "type":"Services"
        }
    ],
    "sg:phone":"+61 3 5722 1162",
    "sg:postcode":"3677",
    "sg:province":"VIC",
    "sg:tags":[
        "medical",
        "practitioner"
    ],
    "wof:name":"Wangaratta Cardiology & Respiratory Centre",
    "wof:placetype":"venue"
},
  "geometry": {"coordinates":[146.312896728,-36.3494148254],"type":"Point"}
}