{
  "type": "Feature",
  "properties": {
    "iso:country":"AU",
    "sg:address":"119 Greville St",
    "sg:city":"Prahran",
    "sg:classifiers":[
        {
            "category":"Personal",
            "subcategory":"Beauty Salon",
            "type":"Services"
        }
    ],
    "sg:phone":"+61 3 9510 1974",
    "sg:postcode":"3181",
    "sg:province":"VIC",
    "wof:name":"Brazilian Butterfly",
    "wof:placetype":"venue"
},
  "geometry": {"coordinates":[144.99078369099999,-37.8490524292],"type":"Point"}
}