{
  "type": "Feature",
  "properties": {
    "addr:full":"2 Grain Store Crt Langwarrin VIC 3910",
    "addr:housenumber":"2",
    "addr:postcode":"3910",
    "addr:street":"Grain;Crt",
    "iso:country":"AU",
    "sg:address":"2 Grain Store Crt",
    "sg:city":"Langwarrin",
    "sg:classifiers":[
        {
            "category":"Manufacturing",
            "subcategory":"Wood Products",
            "type":"Manufacturing & Wholesale Goods"
        }
    ],
    "sg:phone":"+61 3 9775 7501",
    "sg:postcode":"3910",
    "sg:province":"VIC",
    "sg:tags":[
        "polisher",
        "french"
    ],
    "wof:name":"Hatchers Furniture Polishing",
    "wof:placetype":"venue"
},
  "geometry": {"coordinates":[145.212158203,-38.1403083801],"type":"Point"}
}