{
  "type": "Feature",
  "properties": {
    "addr:full":"140 North Fenton St Devonport TAS 7310",
    "addr:housenumber":"140",
    "addr:postcode":"7310",
    "addr:street":"North Fenton St",
    "iso:country":"AU",
    "sg:address":"140 North Fenton St",
    "sg:city":"Devonport",
    "sg:classifiers":[
        {
            "category":"Travel",
            "subcategory":"Hotels & Motels",
            "type":"Entertainment"
        }
    ],
    "sg:phone":"+61 3 6424 8411",
    "sg:postcode":"7310",
    "sg:province":"TAS",
    "wof:name":"Comfort Inn Sunrise",
    "wof:placetype":"venue"
},
  "geometry": {"coordinates":[146.36131286599999,-41.1675758362],"type":"Point"}
}