{
  "type": "Feature",
  "properties": {
    "iso:country":"AU",
    "sg:address":"37 Albert Rd",
    "sg:city":"Moonah",
    "sg:classifiers":[
        {
            "category":"Health Services",
            "subcategory":"Dentist",
            "type":"Services"
        }
    ],
    "sg:phone":"+61 3 6228 1470",
    "sg:postcode":"7009",
    "sg:province":"TAS",
    "wof:name":"Djordjevic Danny Dr",
    "wof:placetype":"venue"
},
  "geometry": {"coordinates":[147.29675293,-42.8477973938],"type":"Point"}
}