{
  "type": "Feature",
  "properties": {
    "addr:full":"45 Meakin St Greensborough VIC 3088",
    "addr:housenumber":"45",
    "addr:postcode":"3088",
    "addr:street":"Meakin St",
    "iso:country":"AU",
    "sg:address":"45 Meakin St",
    "sg:city":"Greensborough",
    "sg:classifiers":[
        {
            "category":"Building & Trades",
            "subcategory":"Locksmith",
            "type":"Services"
        }
    ],
    "sg:phone":"+61 3 9432 3343",
    "sg:postcode":"3088",
    "sg:province":"VIC",
    "sg:tags":[
        "lock"
    ],
    "wof:name":"A Wynn's Locksmiths",
    "wof:placetype":"venue"
},
  "geometry": {"coordinates":[145.08729553200001,-37.7000427246],"type":"Point"}
}