{
  "type": "Feature",
  "properties": {
    "addr:full":"Ste 3/ 35 Main St Greensborough VIC 3088",
    "addr:housenumber":"35",
    "addr:postcode":"3088",
    "addr:street":"Main St",
    "iso:country":"AU",
    "sg:address":"Ste 3/ 35 Main St",
    "sg:city":"Greensborough",
    "sg:classifiers":[
        {
            "category":"Personal",
            "subcategory":"Beauty Salon",
            "type":"Services"
        }
    ],
    "sg:phone":"+61 3 9432 0722",
    "sg:postcode":"3088",
    "sg:province":"VIC",
    "sg:tags":[
        "hairdresser"
    ],
    "wof:name":"Studio 3 Hair Dressing Salon",
    "wof:placetype":"venue"
},
  "geometry": {"coordinates":[145.10366821299999,-37.7035942078],"type":"Point"}
}