{
  "type": "Feature",
  "properties": {
    "addr:full":"2/ 125 Garden St Narrabeen NSW 2101",
    "addr:housenumber":"/ 125",
    "addr:postcode":"2101",
    "addr:street":"Garden St",
    "iso:country":"AU",
    "sg:address":"2/ 125 Garden St",
    "sg:city":"Narrabeen",
    "sg:classifiers":[
        {
            "category":"Shopping",
            "subcategory":"Stationery & Office Supplies",
            "type":"Retail Goods"
        }
    ],
    "sg:phone":"+61 414 971 008",
    "sg:postcode":"2101",
    "sg:province":"NSW",
    "sg:tags":[
        "partition"
    ],
    "wof:name":"Kim Kelly Plastering Pty Ltd",
    "wof:placetype":"venue"
},
  "geometry": {"coordinates":[151.29032900000001,-33.695419],"type":"Point"}
}