{
  "type": "Feature",
  "properties": {
    "addr:full":"116 Kingsclear Ave Keysborough VIC 3173",
    "addr:housenumber":"116",
    "addr:postcode":"3173",
    "addr:street":"Kingsclear Ave",
    "iso:country":"AU",
    "sg:address":"116 Kingsclear Ave",
    "sg:city":"Keysborough",
    "sg:classifiers":[
        {
            "category":"Health Services",
            "subcategory":"Dentist",
            "type":"Services"
        }
    ],
    "sg:phone":"+61 1300 661 158",
    "sg:postcode":"3173",
    "sg:province":"VIC",
    "wof:name":"A Whiter Smiley",
    "wof:placetype":"venue"
},
  "geometry": {"coordinates":[145.170822144,-37.9905433655],"type":"Point"}
}