{
  "type": "Feature",
  "properties": {
    "addr:full":"Shp 54/ 54 Major Rd Fawkner VIC 3060",
    "addr:housenumber":"54 / 54",
    "addr:postcode":"3060",
    "addr:street":"Major Rd",
    "iso:country":"AU",
    "sg:address":"Shp 54/ 54 Major Rd",
    "sg:city":"Fawkner",
    "sg:classifiers":[
        {
            "category":"Fast Food",
            "type":"Food & Drink"
        }
    ],
    "sg:phone":"+61 3 9359 4506",
    "sg:postcode":"3060",
    "sg:province":"VIC",
    "sg:tags":[
        "away",
        "take"
    ],
    "wof:name":"Darwefh",
    "wof:placetype":"venue"
},
  "geometry": {"coordinates":[144.970245361,-37.7074546814],"type":"Point"}
}