{
  "type": "Feature",
  "properties": {
    "addr:full":"2035 Gold Coast Hwy Miami QLD 4220",
    "addr:housenumber":"2035",
    "addr:postcode":"4220",
    "addr:street":"Gold Coast Hwy",
    "iso:country":"AU",
    "sg:address":"2035 Gold Coast Hwy",
    "sg:city":"Miami",
    "sg:classifiers":[
        {
            "category":"Social Services",
            "type":"Services"
        }
    ],
    "sg:phone":"+61 7 5520 2555",
    "sg:postcode":"4220",
    "sg:province":"QLD",
    "sg:tags":[
        "kinesiology"
    ],
    "wof:name":"Dr Maylene Goodwin",
    "wof:placetype":"venue"
},
  "geometry": {"coordinates":[153.444656372,-28.0733318329],"type":"Point"}
}