{
  "type": "Feature",
  "properties": {
    "addr:full":"7 Vivienne Ave Boronia VIC 3155",
    "addr:housenumber":"7",
    "addr:postcode":"3155",
    "addr:street":"Vivienne Ave",
    "iso:country":"AU",
    "sg:address":"7 Vivienne Ave",
    "sg:city":"Boronia",
    "sg:classifiers":[
        {
            "category":"Communications",
            "type":"Services"
        }
    ],
    "sg:phone":"+61 3 9761 0422",
    "sg:postcode":"3155",
    "sg:province":"VIC",
    "sg:tags":[
        "equipment",
        "satellite"
    ],
    "wof:name":"Philippine Video",
    "wof:placetype":"venue"
},
  "geometry": {"coordinates":[145.27479553200001,-37.8646392822],"type":"Point"}
}