{
  "type": "Feature",
  "properties": {
    "addr:full":"13 Clermont Ave Ryde NSW 2112",
    "addr:housenumber":"13",
    "addr:postcode":"2112",
    "addr:street":"Clermont Ave",
    "iso:country":"AU",
    "sg:address":"13 Clermont Ave",
    "sg:city":"Ryde",
    "sg:classifiers":[
        {
            "category":"Education",
            "subcategory":"Kindergarten",
            "type":"Public Place"
        }
    ],
    "sg:phone":"+61 2 9808 3015",
    "sg:postcode":"2112",
    "sg:province":"NSW",
    "sg:tags":[
        "pre-schools"
    ],
    "wof:name":"North Ryde Community Pre-School Centre",
    "wof:placetype":"venue"
},
  "geometry": {"coordinates":[151.106933594,-33.8013801575],"type":"Point"}
}