{
  "type": "Feature",
  "properties": {
    "addr:full":"55- 59 Central Rd Rossmoyne WA 6148",
    "addr:housenumber":"59",
    "addr:postcode":"6148",
    "addr:street":"Central Rd",
    "iso:country":"AU",
    "sg:address":"55- 59 Central Rd",
    "sg:city":"Rossmoyne",
    "sg:classifiers":[
        {
            "category":"Real Estate",
            "subcategory":"Real Estate Agent",
            "type":"Services"
        }
    ],
    "sg:phone":"+61 8 9457 6966",
    "sg:postcode":"6148",
    "sg:province":"WA",
    "wof:name":"John Hayes & Son",
    "wof:placetype":"venue"
},
  "geometry": {"coordinates":[115.868393,-32.038734],"type":"Point"}
}