{
  "type": "Feature",
  "properties": {
    "addr:full":"124 Goodwin Drv Bongaree QLD 4507",
    "addr:housenumber":"124",
    "addr:postcode":"4507",
    "addr:street":"Goodwin Drv",
    "iso:country":"AU",
    "sg:address":"124 Goodwin Drv",
    "sg:city":"Bongaree",
    "sg:classifiers":[
        {
            "category":"Personal",
            "subcategory":"Beauty Salon",
            "type":"Services"
        }
    ],
    "sg:phone":"+61 7 3408 3311",
    "sg:postcode":"4507",
    "sg:province":"QLD",
    "sg:tags":[
        "hairdresser"
    ],
    "wof:name":"Family Hair Care Centre",
    "wof:placetype":"venue"
},
  "geometry": {"coordinates":[153.16314697300001,-27.0735664368],"type":"Point"}
}