{
  "type": "Feature",
  "properties": {
    "iso:country":"AU",
    "sg:address":"PO Box 21",
    "sg:city":"Kiama",
    "sg:classifiers":[
        {
            "category":"Arena",
            "subcategory":"Sports Club",
            "type":"Entertainment"
        }
    ],
    "sg:phone":"+61 2 4232 1694",
    "sg:postcode":"2533",
    "sg:province":"NSW",
    "sg:tags":[
        "defence",
        "supply",
        "self",
        "instruction",
        "martial art"
    ],
    "wof:name":"Illawara Wing Chun School",
    "wof:placetype":"venue"
},
  "geometry": {"coordinates":[150.851806641,-34.6771583557],"type":"Point"}
}