{
  "type": "Feature",
  "properties": {
    "iso:country":"AU",
    "sg:address":"Shop T14, Woodgrove Shopping Centre, 553-555 High St",
    "sg:city":"Melton",
    "sg:classifiers":[
        {
            "category":"Food & Beverages",
            "subcategory":"Bakery",
            "type":"Retail Goods"
        }
    ],
    "sg:phone":"+61 3 9746 9960",
    "sg:postcode":"3337",
    "sg:province":"VIC",
    "sg:tags":[
        "baker"
    ],
    "wof:name":"Bakers Delight Ltd",
    "wof:placetype":"venue"
},
  "geometry": {"coordinates":[144.581985,-37.683426],"type":"Point"}
}