{
  "type": "Feature",
  "properties": {
    "addr:full":"4 Brett Drv Carrum Downs VIC 3201",
    "addr:housenumber":"4",
    "addr:postcode":"3201",
    "addr:street":"Brett Drv",
    "iso:country":"AU",
    "sg:address":"4 Brett Drv",
    "sg:city":"Carrum Downs",
    "sg:classifiers":[
        {
            "category":"Professional",
            "type":"Services"
        }
    ],
    "sg:phone":"+61 3 9775 1444",
    "sg:postcode":"3201",
    "sg:province":"VIC",
    "sg:tags":[
        "packaging",
        "filling",
        "assembling"
    ],
    "wof:name":"Packaging Needs Pty Ltd",
    "wof:placetype":"venue"
},
  "geometry": {"coordinates":[145.16313199999999,-38.097778],"type":"Point"}
}