{
  "type": "Feature",
  "properties": {
    "iso:country":"AU",
    "sg:address":"136 Greville St",
    "sg:city":"Prahran",
    "sg:classifiers":[
        {
            "category":"Shopping",
            "subcategory":"Clothing, Apparel, & Fashions",
            "type":"Retail Goods"
        }
    ],
    "sg:phone":"+61 3 9510 1301",
    "sg:postcode":"3181",
    "sg:province":"VIC",
    "sg:tags":[
        "menswear"
    ],
    "wof:name":"Calibre Clothing",
    "wof:placetype":"venue"
},
  "geometry": {"coordinates":[144.99090576200001,-37.8493232727],"type":"Point"}
}