{
  "type": "Feature",
  "properties": {
    "iso:country":"AU",
    "sg:address":"U4/ 10 Bortfield Drv",
    "sg:city":"Chiswick",
    "sg:classifiers":[
        {
            "category":"Building & Trades",
            "subcategory":"Construction",
            "type":"Services"
        }
    ],
    "sg:phone":"+61 2 9712 4691",
    "sg:postcode":"2046",
    "sg:province":"NSW",
    "sg:tags":[
        "rendering",
        "cement"
    ],
    "wof:name":"Renderex Pty Ltd",
    "wof:placetype":"venue"
},
  "geometry": {"coordinates":[151.14064,-33.847225],"type":"Point"}
}