{
  "type": "Feature",
  "properties": {
    "addr:full":"Shop 8, North Adelaide Village S/Ctr 81 O&#039;Con North Adelaide SA 5006",
    "addr:housenumber":"shop 8;81",
    "addr:postcode":"5006",
    "addr:street":"Village;/",
    "iso:country":"AU",
    "sg:address":"Shop 8, North Adelaide Village S/Ctr 81 O&#039;Con",
    "sg:city":"North Adelaide",
    "sg:classifiers":[
        {
            "category":"Manufacturing",
            "subcategory":"Food",
            "type":"Manufacturing & Wholesale Goods"
        }
    ],
    "sg:phone":"+61 8 8361 8031",
    "sg:postcode":"5006",
    "sg:province":"SA",
    "sg:tags":[
        "function",
        "catering"
    ],
    "wof:name":"Zoom Espresso",
    "wof:placetype":"venue"
},
  "geometry": {"coordinates":[138.59637451200001,-34.9079818726],"type":"Point"}
}