{
  "type": "Feature",
  "properties": {
    "addr:full":"PO Box 104 Nichols Point VIC 3501",
    "addr:postcode":"3501",
    "iso:country":"AU",
    "sg:address":"PO Box 104",
    "sg:city":"Nichols Point",
    "sg:classifiers":[
        {
            "category":"Farming",
            "subcategory":"Farm & Veterinary Services",
            "type":"Manufacturing & Wholesale Goods"
        }
    ],
    "sg:phone":"+61 407 274 392",
    "sg:postcode":"3501",
    "sg:province":"VIC",
    "sg:tags":[
        "irrigation",
        "reticulation",
        "system"
    ],
    "wof:name":"AD Williams Industries",
    "wof:placetype":"venue"
},
  "geometry": {"coordinates":[142.17770385700001,-34.2065315247],"type":"Point"}
}