{
  "type": "Feature",
  "properties": {
    "addr:full":"30 Collings St Balmoral QLD 4171",
    "addr:housenumber":"30",
    "addr:postcode":"4171",
    "addr:street":"Collings St",
    "iso:country":"AU",
    "sg:address":"30 Collings St",
    "sg:city":"Balmoral",
    "sg:classifiers":[
        {
            "category":"Health Services",
            "subcategory":"Health Practitioner",
            "type":"Services"
        }
    ],
    "sg:phone":"+61 7 3399 1936",
    "sg:postcode":"4171",
    "sg:province":"QLD",
    "sg:tags":[
        "alternative"
    ],
    "wof:name":"Universe Networks",
    "wof:placetype":"venue"
},
  "geometry": {"coordinates":[153.06471252399999,-27.4601459503],"type":"Point"}
}