{
  "type": "Feature",
  "properties": {
    "iso:country":"AU",
    "sg:address":"15 Jane St",
    "sg:city":"Arana Hills",
    "sg:classifiers":[
        {
            "category":"Shopping",
            "subcategory":"Computers & Home Electronics",
            "type":"Retail Goods"
        }
    ],
    "sg:phone":"+61 7 3851 3839",
    "sg:postcode":"4054",
    "sg:province":"QLD",
    "sg:tags":[
        "small",
        "equipment",
        "business"
    ],
    "wof:name":"Oblong Software Products",
    "wof:placetype":"venue"
},
  "geometry": {"coordinates":[152.95863342300001,-27.4020557404],"type":"Point"}
}