{
  "type": "Feature",
  "properties": {
    "iso:country":"AU",
    "sg:address":"38 Pickering St",
    "sg:city":"Enoggera",
    "sg:classifiers":[
        {
            "category":"Retail",
            "subcategory":"Auto Repair",
            "type":"Services"
        }
    ],
    "sg:phone":"+61 7 3355 9888",
    "sg:postcode":"4051",
    "sg:province":"QLD",
    "sg:tags":[
        "automotive",
        "air conditioning"
    ],
    "wof:name":"Checkpoint",
    "wof:placetype":"venue"
},
  "geometry": {"coordinates":[152.99684143100001,-27.4199638367],"type":"Point"}
}