{
  "type": "Feature",
  "properties": {
    "addr:full":"146 Queen St Concord West NSW 2138",
    "addr:housenumber":"146",
    "addr:postcode":"2138",
    "addr:street":"Queen St",
    "iso:country":"AU",
    "sg:address":"146 Queen St",
    "sg:city":"Concord West",
    "sg:classifiers":[
        {
            "category":"Professional",
            "subcategory":"Art Services",
            "type":"Services"
        }
    ],
    "sg:phone":"+61 416 048 854",
    "sg:postcode":"2138",
    "sg:province":"NSW",
    "sg:tags":[
        "decorator",
        "painter"
    ],
    "wof:name":"Touchard Patrick",
    "wof:placetype":"venue"
},
  "geometry": {"coordinates":[151.0859375,-33.8431396484],"type":"Point"}
}