{
  "type": "Feature",
  "properties": {
    "addr:full":"42 Hopkins St Footscray VIC 3011",
    "addr:housenumber":"42",
    "addr:postcode":"3011",
    "addr:street":"Hopkins St",
    "iso:country":"AU",
    "sg:address":"42 Hopkins St",
    "sg:city":"Footscray",
    "sg:classifiers":[
        {
            "category":"Retail",
            "subcategory":"Auto Rental",
            "type":"Services"
        }
    ],
    "sg:phone":"+61 3 9689 9044",
    "sg:postcode":"3011",
    "sg:province":"VIC",
    "sg:tags":[
        "car",
        "hire",
        "minibus"
    ],
    "wof:name":"Thrifty",
    "wof:placetype":"venue"
},
  "geometry": {"coordinates":[144.905349731,-37.8002662659],"type":"Point"}
}