{
  "type": "Feature",
  "properties": {
    "iso:country":"AU",
    "sg:address":"67 Oatley Crt",
    "sg:city":"Belconnen",
    "sg:classifiers":[
        {
            "category":"Retail",
            "subcategory":"Repair Shop",
            "type":"Services"
        }
    ],
    "sg:phone":"+61 2 6251 5444",
    "sg:postcode":"2617",
    "sg:province":"ACT",
    "sg:tags":[
        "machine",
        "repairs",
        "part",
        "dryer",
        "washing"
    ],
    "wof:name":"Complete Electrical Services",
    "wof:placetype":"venue"
},
  "geometry": {"coordinates":[149.05990600600001,-35.242149353],"type":"Point"}
}