{
  "type": "Feature",
  "properties": {
    "addr:full":"Cavendish St Mittagong NSW 2575",
    "addr:postcode":"2575",
    "addr:street":"Cavendish St",
    "iso:country":"AU",
    "sg:address":"Cavendish St",
    "sg:city":"Mittagong",
    "sg:classifiers":[
        {
            "category":"Wholesale",
            "subcategory":"Furniture",
            "type":"Manufacturing & Wholesale Goods"
        }
    ],
    "sg:phone":"+61 2 4871 1239",
    "sg:postcode":"2575",
    "sg:province":"NSW",
    "sg:tags":[
        "wholesaler",
        "mfrs"
    ],
    "wof:name":"E W Goulder & Sons Pty Ltd",
    "wof:placetype":"venue"
},
  "geometry": {"coordinates":[150.433868408,-34.4485092163],"type":"Point"}
}