{
  "type": "Feature",
  "properties": {
    "addr:full":"38 Park Rd McGraths Hill NSW 2756",
    "addr:housenumber":"38",
    "addr:postcode":"2756",
    "addr:street":"Park Rd",
    "iso:country":"AU",
    "sg:address":"38 Park Rd",
    "sg:city":"McGraths Hill",
    "sg:classifiers":[
        {
            "category":"Banks & Credit Unions",
            "subcategory":"Bank",
            "type":"Services"
        }
    ],
    "sg:phone":"+61 2 4587 9679",
    "sg:postcode":"2756",
    "sg:province":"NSW",
    "sg:tags":[
        "concrete",
        "reinforcement"
    ],
    "wof:name":"OneSteel Reinforcing",
    "wof:placetype":"venue"
},
  "geometry": {"coordinates":[150.83651733400001,-33.6352157593],"type":"Point"}
}