{
  "type": "Feature",
  "properties": {
    "iso:country":"AU",
    "sg:address":"65 Norma Rd",
    "sg:city":"Myaree",
    "sg:classifiers":[
        {
            "category":"Manufacturing",
            "subcategory":"Retail Goods",
            "type":"Manufacturing & Wholesale Goods"
        }
    ],
    "sg:phone":"+61 8 9330 7944",
    "sg:postcode":"6154",
    "sg:province":"WA",
    "sg:tags":[
        "merchant",
        "pump",
        "mfrs"
    ],
    "wof:name":"Garden Decor",
    "wof:placetype":"venue"
},
  "geometry": {"coordinates":[115.822151,-32.040062],"type":"Point"}
}