{
  "type": "Feature",
  "properties": {
    "iso:country":"AU",
    "sg:address":"Shp 2/ 162 Rokeby Rd",
    "sg:city":"Subiaco",
    "sg:classifiers":[
        {
            "category":"Shopping",
            "subcategory":"Clothing, Apparel, & Fashions",
            "type":"Retail Goods"
        }
    ],
    "sg:phone":"+61 8 9388 8895",
    "sg:postcode":"6008",
    "sg:province":"WA",
    "sg:tags":[
        "boutique"
    ],
    "wof:name":"Tokay Boutique",
    "wof:placetype":"venue"
},
  "geometry": {"coordinates":[115.824142456,-31.9495010376],"type":"Point"}
}