{
  "type": "Feature",
  "properties": {
    "addr:full":"439 George St Fitzroy VIC 3065",
    "addr:housenumber":"439",
    "addr:postcode":"3065",
    "addr:street":"George St",
    "iso:country":"AU",
    "sg:address":"439 George St",
    "sg:city":"Fitzroy",
    "sg:classifiers":[
        {
            "category":"Professional",
            "subcategory":"Management & Consulting",
            "type":"Services"
        }
    ],
    "sg:phone":"+61 3 9419 5584",
    "sg:postcode":"3065",
    "sg:province":"VIC",
    "sg:tags":[
        "consultant"
    ],
    "wof:name":"Nexus Hr Consulting",
    "wof:placetype":"venue"
},
  "geometry": {"coordinates":[144.98208618199999,-37.7965164185],"type":"Point"}
}