{
  "type": "Feature",
  "properties": {
    "iso:country":"AU",
    "sg:address":"2 Buntz Crt",
    "sg:city":"Wodonga",
    "sg:classifiers":[
        {
            "category":"Shopping",
            "subcategory":"Computers & Home Electronics",
            "type":"Retail Goods"
        }
    ],
    "sg:phone":"+61 2 6024 7070",
    "sg:postcode":"3690",
    "sg:province":"VIC",
    "sg:tags":[
        "equipment",
        "part",
        "electronic"
    ],
    "wof:name":"J.S.A. Electronics",
    "wof:placetype":"venue"
},
  "geometry": {"coordinates":[146.86601257300001,-36.1369247437],"type":"Point"}
}