{
  "type": "Feature",
  "properties": {
    "iso:country":"AU",
    "sg:address":"26 Duporth Ave",
    "sg:city":"Maroochydore",
    "sg:classifiers":[
        {
            "category":"Real Estate",
            "subcategory":"Real Estate Agent",
            "type":"Services"
        }
    ],
    "sg:phone":"+61 7 5443 5088",
    "sg:postcode":"4558",
    "sg:province":"QLD",
    "wof:name":"Savills",
    "wof:placetype":"venue"
},
  "geometry": {"coordinates":[153.089385986,-26.6498432159],"type":"Point"}
}