{
  "type": "Feature",
  "properties": {
    "iso:country":"AU",
    "sg:address":"43 Belgrave St",
    "sg:city":"Manly",
    "sg:classifiers":[
        {
            "category":"Health Services",
            "subcategory":"Doctor",
            "type":"Services"
        }
    ],
    "sg:phone":"+61 2 9977 8733",
    "sg:postcode":"2095",
    "sg:province":"NSW",
    "sg:tags":[
        "medical",
        "practitioner"
    ],
    "wof:name":"Ly Lin",
    "wof:placetype":"venue"
},
  "geometry": {"coordinates":[151.28541564899999,-33.7957496643],"type":"Point"}
}