{
  "type": "Feature",
  "properties": {
    "iso:country":"AU",
    "sg:address":"462 Morphett St",
    "sg:city":"Adelaide",
    "sg:classifiers":[
        {
            "category":"Professional",
            "subcategory":"Printing & Photocopies",
            "type":"Services"
        }
    ],
    "sg:phone":"+61 8 8211 8474",
    "sg:postcode":"5000",
    "sg:province":"SA",
    "sg:tags":[
        "photocopying"
    ],
    "wof:name":"Independent Business Equipment Pty Ltd",
    "wof:placetype":"venue"
},
  "geometry": {"coordinates":[138.59454345699999,-34.9354743958],"type":"Point"}
}