{
  "type": "Feature",
  "properties": {
    "addr:full":"18 Elliott St Midvale WA 6056",
    "addr:housenumber":"18",
    "addr:postcode":"6056",
    "addr:street":"Elliott St",
    "iso:country":"AU",
    "sg:address":"18 Elliott St",
    "sg:city":"Midvale",
    "sg:classifiers":[
        {
            "category":"Manufacturing",
            "subcategory":"Soap",
            "type":"Manufacturing & Wholesale Goods"
        }
    ],
    "sg:phone":"+61 8 9274 1992",
    "sg:postcode":"6056",
    "sg:province":"WA",
    "sg:tags":[
        "detergent"
    ],
    "wof:name":"Big Bubble",
    "wof:placetype":"venue"
},
  "geometry": {"coordinates":[116.03060913100001,-31.8938922882],"type":"Point"}
}