{
  "type": "Feature",
  "properties": {
    "addr:full":"Shop 31a & 31b Menai Marketplace, 152 Allison Crs Menai NSW 2234",
    "addr:housenumber":"31a & 31b;152",
    "addr:postcode":"2234",
    "addr:street":"Allison Crs",
    "iso:country":"AU",
    "sg:address":"Shop 31a & 31b Menai Marketplace, 152 Allison Crs",
    "sg:city":"Menai",
    "sg:classifiers":[
        {
            "category":"Shopping",
            "subcategory":"Computers & Home Electronics",
            "type":"Retail Goods"
        }
    ],
    "sg:phone":"+61 2 9532 0888",
    "sg:postcode":"2234",
    "sg:province":"NSW",
    "sg:tags":[
        "equipment",
        "part",
        "electronic"
    ],
    "wof:name":"Tandy",
    "wof:placetype":"venue"
},
  "geometry": {"coordinates":[151.010955811,-34.014175415],"type":"Point"}
}