{
  "type": "Feature",
  "properties": {
    "iso:country":"AU",
    "sg:address":"Unit 404/ 73 Flinders La",
    "sg:city":"Melbourne",
    "sg:classifiers":[
        {
            "category":"Community Center",
            "subcategory":"Senior",
            "type":"Public Place"
        }
    ],
    "sg:phone":"+61 3 9650 8911",
    "sg:postcode":"3000",
    "sg:province":"VIC",
    "sg:tags":[
        "finance",
        "equity"
    ],
    "wof:name":"Falconer Bellomo & Company Ltd",
    "wof:placetype":"venue"
},
  "geometry": {"coordinates":[144.97218322800001,-37.8150787354],"type":"Point"}
}