{
  "type": "Feature",
  "properties": {
    "addr:full":"Suite 1/ 50 Hunter St Newcastle NSW 2300",
    "addr:housenumber":"50",
    "addr:postcode":"2300",
    "addr:street":"Hunter St",
    "iso:country":"AU",
    "sg:address":"Suite 1/ 50 Hunter St",
    "sg:city":"Newcastle",
    "sg:classifiers":[
        {
            "category":"Building & Trades",
            "subcategory":"Cleaning & Sanitation",
            "type":"Services"
        }
    ],
    "sg:phone":"+61 2 4929 3329",
    "sg:postcode":"2300",
    "sg:province":"NSW",
    "sg:tags":[
        "industrial",
        "commercial",
        "contractor"
    ],
    "wof:name":"Surfside Cleaners",
    "wof:placetype":"venue"
},
  "geometry": {"coordinates":[151.78500399999999,-32.927841],"type":"Point"}
}