{
  "type": "Feature",
  "properties": {
    "iso:country":"AU",
    "sg:address":"124 Catherine St",
    "sg:city":"Leichhardt",
    "sg:classifiers":[
        {
            "category":"Retail",
            "subcategory":"Auto Repair",
            "type":"Services"
        }
    ],
    "sg:phone":"+61 2 9550 0618",
    "sg:postcode":"2040",
    "sg:province":"NSW",
    "sg:tags":[
        "repairer",
        "motor",
        "engineer"
    ],
    "wof:name":"A.B.P. Mechanical Repairs",
    "wof:placetype":"venue"
},
  "geometry": {"coordinates":[151.162552,-33.883457],"type":"Point"}
}