{
  "type": "Feature",
  "properties": {
    "iso:country":"AU",
    "sg:address":"PO Box 149",
    "sg:city":"Ayr",
    "sg:classifiers":[
        {
            "category":"Sports & Exercise",
            "subcategory":"Sports Center",
            "type":"Entertainment"
        }
    ],
    "sg:phone":"+61 419 795 548",
    "sg:postcode":"4807",
    "sg:province":"QLD",
    "sg:tags":[
        "coach",
        "tennis"
    ],
    "wof:name":"Arron Klumpp Tennis Coaching",
    "wof:placetype":"venue"
},
  "geometry": {"coordinates":[147.404296875,-19.572479248],"type":"Point"}
}