{
  "type": "Feature",
  "properties": {
    "addr:full":"Shop 5 , Pacific Point Arcade, Sydney Rd, Manly NSW 2095",
    "addr:housenumber":"shop 5",
    "addr:postcode":"2095",
    "addr:street":"Pacific;Sydney Rd",
    "iso:country":"AU",
    "sg:address":"Shop 5",
    "sg:city":", Pacific Point Arcade, Sydney Rd, Manly",
    "sg:classifiers":[
        {
            "category":"Personal",
            "subcategory":"Beauty Salon",
            "type":"Services"
        }
    ],
    "sg:phone":"+61 2 9977 4148",
    "sg:postcode":"2095",
    "sg:province":"NSW",
    "wof:name":"Nicoles Beauty Rooms",
    "wof:placetype":"venue"
},
  "geometry": {"coordinates":[151.28761291500001,-33.7972869873],"type":"Point"}
}