{
  "type": "Feature",
  "properties": {
    "addr:full":"21 Elliott St Balmain NSW 2041",
    "addr:housenumber":"21",
    "addr:postcode":"2041",
    "addr:street":"Elliott St",
    "iso:country":"AU",
    "sg:address":"21 Elliott St",
    "sg:city":"Balmain",
    "sg:classifiers":[
        {
            "category":"Social Services",
            "subcategory":"Adult Care",
            "type":"Services"
        }
    ],
    "sg:phone":"+61 2 9555 6655",
    "sg:postcode":"2041",
    "sg:province":"NSW",
    "sg:tags":[
        "aged"
    ],
    "wof:name":"Aged Care Accommodation & Advisory Services Pty Ltd",
    "wof:placetype":"venue"
},
  "geometry": {"coordinates":[151.17501799999999,-33.858158],"type":"Point"}
}