{
  "type": "Feature",
  "properties": {
    "addr:full":"Unit 2, 12- 14 Mangrove La Taren Point NSW 2229",
    "addr:housenumber":"12 14",
    "addr:postcode":"2229",
    "addr:street":"Mangrove La",
    "iso:country":"AU",
    "sg:address":"Unit 2, 12- 14 Mangrove La",
    "sg:city":"Taren Point",
    "sg:classifiers":[
        {
            "category":"Wholesale",
            "subcategory":"Electrical",
            "type":"Manufacturing & Wholesale Goods"
        }
    ],
    "sg:phone":"+61 2 9540 3955",
    "sg:postcode":"2229",
    "sg:province":"NSW",
    "sg:tags":[
        "wholesaler",
        "mfrs",
        "accessory"
    ],
    "wof:name":"Hellermann Tyton Australia Pty Ltd",
    "wof:placetype":"venue"
},
  "geometry": {"coordinates":[151.131591797,-34.0240211487],"type":"Point"}
}