{
  "type": "Feature",
  "properties": {
    "iso:country":"AU",
    "sg:address":"16B Cooroyba Crt",
    "sg:city":"North Haven",
    "sg:classifiers":[
        {
            "category":"Professional",
            "subcategory":"Business Services",
            "type":"Services"
        }
    ],
    "sg:phone":"+61 8 8248 0877",
    "sg:postcode":"5018",
    "sg:province":"SA",
    "sg:tags":[
        "broker"
    ],
    "wof:name":"Schwartz E",
    "wof:placetype":"venue"
},
  "geometry": {"coordinates":[138.48728942899999,-34.7959671021],"type":"Point"}
}