{
  "type": "Feature",
  "properties": {
    "iso:country":"AU",
    "sg:address":"263 Bank St",
    "sg:city":"South Melbourne",
    "sg:classifiers":[
        {
            "category":"Real Estate",
            "subcategory":"Architect",
            "type":"Services"
        }
    ],
    "sg:phone":"+61 3 9690 7705",
    "sg:postcode":"3205",
    "sg:province":"VIC",
    "wof:name":"Tim Hall & Associates Pty Ltd",
    "wof:placetype":"venue"
},
  "geometry": {"coordinates":[144.957382,-37.835285],"type":"Point"}
}