{
  "type": "Feature",
  "properties": {
    "iso:country":"AU",
    "sg:address":"545 Alice St",
    "sg:city":"Maryborough",
    "sg:classifiers":[
        {
            "category":"Education",
            "subcategory":"School",
            "type":"Public Place"
        }
    ],
    "sg:phone":"+61 7 4121 5223",
    "sg:postcode":"4650",
    "sg:province":"QLD",
    "sg:tags":[
        "state",
        "except",
        "nsw"
    ],
    "wof:name":"Sunbury Primary",
    "wof:placetype":"venue"
},
  "geometry": {"coordinates":[152.675781,-25.522911],"type":"Point"}
}