{
  "type": "Feature",
  "properties": {
    "addr:full":"Office 112/ 243 Pyrmont St Pyrmont NSW 2009",
    "addr:housenumber":"112 / 243",
    "addr:postcode":"2009",
    "addr:street":"Pyrmont St",
    "iso:country":"AU",
    "sg:address":"Office 112/ 243 Pyrmont St",
    "sg:city":"Pyrmont",
    "sg:classifiers":[
        {
            "category":"Building & Trades",
            "subcategory":"Landscaping Services",
            "type":"Services"
        }
    ],
    "sg:phone":"+61 1300 557 047",
    "sg:postcode":"2009",
    "sg:province":"NSW",
    "sg:tags":[
        "inspection"
    ],
    "sg:website":"http://www.inspectit.com.au",
    "wof:name":"Inspect It",
    "wof:placetype":"venue"
},
  "geometry": {"coordinates":[151.19711303700001,-33.8734931946],"type":"Point"}
}