{
  "type": "Feature",
  "properties": {
    "iso:country":"AU",
    "sg:address":"388 Forest St",
    "sg:city":"Wendouree",
    "sg:classifiers":[
        {
            "category":"Home & Garden",
            "subcategory":"Building Materials",
            "type":"Retail Goods"
        }
    ],
    "sg:phone":"+61 3 5339 1114",
    "sg:postcode":"3355",
    "sg:province":"VIC",
    "sg:tags":[
        "lawn",
        "cutting",
        "maintenance"
    ],
    "wof:name":"Ballarat Lawns & Gardens",
    "wof:placetype":"venue"
},
  "geometry": {"coordinates":[143.834442,-37.524658],"type":"Point"}
}