{
  "type": "Feature",
  "properties": {
    "addr:full":"94 Waterman St Old Bar NSW 2430",
    "addr:housenumber":"94",
    "addr:postcode":"2430",
    "addr:street":"Waterman St",
    "iso:country":"AU",
    "sg:address":"94 Waterman St",
    "sg:city":"Old Bar",
    "sg:classifiers":[
        {
            "category":"Building & Trades",
            "subcategory":"Construction",
            "type":"Services"
        }
    ],
    "sg:phone":"+61 2 6553 3080",
    "sg:postcode":"2430",
    "sg:province":"NSW",
    "sg:tags":[
        "contractor"
    ],
    "wof:name":"Barlin Building Contractor",
    "wof:placetype":"venue"
},
  "geometry": {"coordinates":[152.58781400000001,-31.960754],"type":"Point"}
}