{
  "type": "Feature",
  "properties": {
    "addr:full":"86a Pacific Hwy Roseville NSW 2069",
    "addr:housenumber":"86a",
    "addr:postcode":"2069",
    "addr:street":"Pacific Hwy",
    "iso:country":"AU",
    "sg:address":"86a Pacific Hwy",
    "sg:city":"Roseville",
    "sg:classifiers":[
        {
            "category":"Health Services",
            "subcategory":"Health Practitioner",
            "type":"Services"
        }
    ],
    "sg:phone":"+61 2 9999 6216",
    "sg:postcode":"2069",
    "sg:province":"NSW",
    "sg:tags":[
        "psychologist"
    ],
    "wof:name":"Roseville Psychology Practice",
    "wof:placetype":"venue"
},
  "geometry": {"coordinates":[151.17735290499999,-33.7850608826],"type":"Point"}
}