{
  "type": "Feature",
  "properties": {
    "addr:full":"3 Kelly Ave Barmera SA 5345",
    "addr:housenumber":"3",
    "addr:postcode":"5345",
    "addr:street":"Kelly Ave",
    "iso:country":"AU",
    "sg:address":"3 Kelly Ave",
    "sg:city":"Barmera",
    "sg:classifiers":[
        {
            "category":"Building & Trades",
            "subcategory":"Construction",
            "type":"Services"
        }
    ],
    "sg:phone":"+61 8 8588 2656",
    "sg:postcode":"5345",
    "sg:province":"SA",
    "sg:tags":[
        "contractor"
    ],
    "wof:name":"VanHensbergen E & M",
    "wof:placetype":"venue"
},
  "geometry": {"coordinates":[140.47445678700001,-34.2404289246],"type":"Point"}
}