{
  "type": "Feature",
  "properties": {
    "addr:full":"40 Shingler St Leongatha VIC 3953",
    "addr:housenumber":"40",
    "addr:postcode":"3953",
    "addr:street":"Shingler St",
    "iso:country":"AU",
    "sg:address":"40 Shingler St",
    "sg:city":"Leongatha",
    "sg:classifiers":[
        {
            "category":"Building & Trades",
            "subcategory":"Plumbing",
            "type":"Services"
        }
    ],
    "sg:phone":"+61 3 5662 2817",
    "sg:postcode":"3953",
    "sg:province":"VIC",
    "sg:tags":[
        "plumber",
        "gasfitters"
    ],
    "wof:name":"Rosser D T & K",
    "wof:placetype":"venue"
},
  "geometry": {"coordinates":[145.93743896500001,-38.4713096619],"type":"Point"}
}