{
  "type": "Feature",
  "properties": {
    "iso:country":"AU",
    "sg:address":"1 Camira Crt",
    "sg:city":"Grovedale",
    "sg:classifiers":[
        {
            "category":"Home & Garden",
            "subcategory":"Carpets & Floor Coverings",
            "type":"Retail Goods"
        }
    ],
    "sg:phone":"+61 414 268 376",
    "sg:postcode":"3216",
    "sg:province":"VIC",
    "sg:tags":[
        "tile",
        "wall",
        "layer"
    ],
    "wof:name":"Rosewood Tiling",
    "wof:placetype":"venue"
},
  "geometry": {"coordinates":[144.33375549300001,-38.2054672241],"type":"Point"}
}