{
  "type": "Feature",
  "properties": {
    "addr:full":"20 Peppermint Drv Cashmere QLD 4500",
    "addr:housenumber":"20",
    "addr:postcode":"4500",
    "addr:street":"Peppermint Drv",
    "iso:country":"AU",
    "sg:address":"20 Peppermint Drv",
    "sg:city":"Cashmere",
    "sg:classifiers":[
        {
            "category":"Professional",
            "subcategory":"Accounting & Tax Preparation",
            "type":"Services"
        }
    ],
    "sg:phone":"+61 7 3298 5508",
    "sg:postcode":"4500",
    "sg:province":"QLD",
    "sg:tags":[
        "accountant",
        "auditor"
    ],
    "wof:name":"Schoenmaker R",
    "wof:placetype":"venue"
},
  "geometry": {"coordinates":[152.92669677699999,-27.3156089783],"type":"Point"}
}