{
  "type": "Feature",
  "properties": {
    "iso:country":"AU",
    "sg:address":"430 Gleniffer Rd",
    "sg:city":"Bonville",
    "sg:classifiers":[
        {
            "category":"Farming",
            "subcategory":"Farm & Veterinary Services",
            "type":"Manufacturing & Wholesale Goods"
        }
    ],
    "sg:phone":"+61 2 6653 4449",
    "sg:postcode":"2441",
    "sg:province":"NSW",
    "sg:tags":[
        "agricultural",
        "advisory"
    ],
    "wof:name":"Kiwi Down Under Organic Farm Consulting",
    "wof:placetype":"venue"
},
  "geometry": {"coordinates":[153.02562,-30.377743],"type":"Point"}
}