{
  "type": "Feature",
  "properties": {
    "addr:full":"355 Argent St Broken Hill NSW 2880",
    "addr:housenumber":"355",
    "addr:postcode":"2880",
    "addr:street":"Argent St",
    "iso:country":"AU",
    "sg:address":"355 Argent St",
    "sg:city":"Broken Hill",
    "sg:classifiers":[
        {
            "category":"Real Estate",
            "subcategory":"Real Estate Agent",
            "type":"Services"
        }
    ],
    "sg:phone":"+61 8 8087 2297",
    "sg:postcode":"2880",
    "sg:province":"NSW",
    "wof:name":"Century 21 McLeod's Broken Hill",
    "wof:placetype":"venue"
},
  "geometry": {"coordinates":[141.466720581,-31.9577522278],"type":"Point"}
}