{
  "type": "Feature",
  "properties": {
    "addr:full":"Bourke St Dubbo NSW 2830",
    "addr:postcode":"2830",
    "addr:street":"Bourke St",
    "iso:country":"AU",
    "sg:address":"Bourke St",
    "sg:city":"Dubbo",
    "sg:classifiers":[
        {
            "category":"Shopping",
            "type":"Retail Goods"
        }
    ],
    "sg:phone":"+61 2 6882 1311",
    "sg:postcode":"2830",
    "sg:province":"NSW",
    "sg:tags":[
        "agent",
        "stock"
    ],
    "wof:name":"Landmark Operations Limited",
    "wof:placetype":"venue"
},
  "geometry": {"coordinates":[148.60879516599999,-32.2503242493],"type":"Point"}
}