{
  "type": "Feature",
  "properties": {
    "addr:full":"14 Colbert Rd Campbellfield VIC 3061",
    "addr:housenumber":"14",
    "addr:postcode":"3061",
    "addr:street":"Colbert Rd",
    "iso:country":"AU",
    "sg:address":"14 Colbert Rd",
    "sg:city":"Campbellfield",
    "sg:classifiers":[
        {
            "category":"Building & Trades",
            "subcategory":"Cleaning & Sanitation",
            "type":"Services"
        }
    ],
    "sg:phone":"+61 3 9357 8711",
    "sg:postcode":"3061",
    "sg:province":"VIC",
    "sg:tags":[
        "abrasive",
        "blasting"
    ],
    "wof:name":"Autostrip",
    "wof:placetype":"venue"
},
  "geometry": {"coordinates":[144.96052551299999,-37.6708831787],"type":"Point"}
}