{
  "type": "Feature",
  "properties": {
    "iso:country":"AU",
    "sg:address":"162 Barrett St",
    "sg:city":"Bracken Ridge",
    "sg:classifiers":[
        {
            "category":"Shopping",
            "subcategory":"Bicycles & Sporting Goods",
            "type":"Retail Goods"
        }
    ],
    "sg:phone":"+61 7 3269 7665",
    "sg:postcode":"4017",
    "sg:province":"QLD",
    "sg:tags":[
        "chemical",
        "equipment",
        "pool",
        "swimming"
    ],
    "wof:name":"Proswim Pool Care",
    "wof:placetype":"venue"
},
  "geometry": {"coordinates":[153.040359497,-27.3192615509],"type":"Point"}
}