{
  "type": "Feature",
  "properties": {
    "addr:full":"38 Armstrong Way Highland Park QLD 4211",
    "addr:housenumber":"38",
    "addr:postcode":"4211",
    "addr:street":"Armstrong Way",
    "iso:country":"AU",
    "sg:address":"38 Armstrong Way",
    "sg:city":"Highland Park",
    "sg:classifiers":[
        {
            "category":"Social Services",
            "subcategory":"Child Care",
            "type":"Services"
        }
    ],
    "sg:phone":"+61 7 5596 3005",
    "sg:postcode":"4211",
    "sg:province":"QLD",
    "wof:name":"Kinder Cottage",
    "wof:placetype":"venue"
},
  "geometry": {"coordinates":[153.328521728,-28.0136299133],"type":"Point"}
}