{
  "type": "Feature",
  "properties": {
    "addr:full":"(Rear) 30 High St Seymour VIC 3660",
    "addr:housenumber":"30",
    "addr:postcode":"3660",
    "addr:street":"High St",
    "iso:country":"AU",
    "sg:address":"(Rear) 30 High St",
    "sg:city":"Seymour",
    "sg:classifiers":[
        {
            "category":"Professional",
            "subcategory":"Engineering",
            "type":"Services"
        }
    ],
    "sg:phone":"+61 3 5799 0888",
    "sg:postcode":"3660",
    "sg:province":"VIC",
    "sg:tags":[
        "diesel",
        "engineer"
    ],
    "wof:name":"Mac's Diesel",
    "wof:placetype":"venue"
},
  "geometry": {"coordinates":[145.160644531,-37.0263328552],"type":"Point"}
}