{
  "type": "Feature",
  "properties": {
    "iso:country":"AU",
    "sg:address":"25 Shannon Pl",
    "sg:city":"Virginia",
    "sg:classifiers":[
        {
            "category":"Manufacturing",
            "subcategory":"Furniture",
            "type":"Manufacturing & Wholesale Goods"
        }
    ],
    "sg:phone":"+61 7 3632 1900",
    "sg:postcode":"4014",
    "sg:province":"QLD",
    "sg:tags":[
        "mfrs",
        "supply"
    ],
    "wof:name":"Nover",
    "wof:placetype":"venue"
},
  "geometry": {"coordinates":[153.06051635700001,-27.37541008],"type":"Point"}
}