{
  "type": "Feature",
  "properties": {
    "iso:country":"AU",
    "sg:address":"11 Willoughby Rd",
    "sg:city":"Crows Nest",
    "sg:classifiers":[
        {
            "category":"Food & Beverages",
            "subcategory":"Bakery",
            "type":"Retail Goods"
        }
    ],
    "sg:phone":"+61 2 9438 3222",
    "sg:postcode":"2065",
    "sg:province":"NSW",
    "sg:tags":[
        "baker"
    ],
    "wof:name":"Bakers Delight Ltd",
    "wof:placetype":"venue"
},
  "geometry": {"coordinates":[151.20103454599999,-33.8272895813],"type":"Point"}
}