{
  "type": "Feature",
  "properties": {
    "addr:full":"7 Norma Rd Forest Hill VIC 3131",
    "addr:housenumber":"7",
    "addr:postcode":"3131",
    "addr:street":"Norma Rd",
    "iso:country":"AU",
    "sg:address":"7 Norma Rd",
    "sg:city":"Forest Hill",
    "sg:classifiers":[
        {
            "category":"Arena",
            "subcategory":"Sports Club",
            "type":"Entertainment"
        }
    ],
    "sg:phone":"+61 3 9877 1106",
    "sg:postcode":"3131",
    "sg:province":"VIC",
    "sg:tags":[
        "defence",
        "supply",
        "self",
        "instruction",
        "martial art"
    ],
    "wof:name":"Aiki-Do Takemusu",
    "wof:placetype":"venue"
},
  "geometry": {"coordinates":[145.167510986,-37.8415870667],"type":"Point"}
}