{
  "type": "Feature",
  "properties": {
    "addr:full":"Unit 20/ 6 Isabella St North Parramatta NSW 2151",
    "addr:housenumber":"/ 6",
    "addr:postcode":"2151",
    "addr:street":"Isabella St",
    "iso:country":"AU",
    "sg:address":"Unit 20/ 6 Isabella St",
    "sg:city":"North Parramatta",
    "sg:classifiers":[
        {
            "category":"Professional",
            "subcategory":"Computer Services",
            "type":"Services"
        }
    ],
    "sg:phone":"+61 2 9630 1630",
    "sg:postcode":"2151",
    "sg:province":"NSW",
    "sg:tags":[
        "training"
    ],
    "wof:name":"Computer Buddies",
    "wof:placetype":"venue"
},
  "geometry": {"coordinates":[151.007537842,-33.8025360107],"type":"Point"}
}