{
  "type": "Feature",
  "properties": {
    "addr:full":"43 Stanley St Kanwal NSW 2259",
    "addr:housenumber":"43",
    "addr:postcode":"2259",
    "addr:street":"Stanley St",
    "iso:country":"AU",
    "sg:address":"43 Stanley St",
    "sg:city":"Kanwal",
    "sg:classifiers":[
        {
            "category":"Building & Trades",
            "subcategory":"Construction",
            "type":"Services"
        }
    ],
    "sg:phone":"+61 412 618 550",
    "sg:postcode":"2259",
    "sg:province":"NSW",
    "sg:tags":[
        "concrete",
        "contractor"
    ],
    "wof:name":"Palmcot Pty Ltd",
    "wof:placetype":"venue"
},
  "geometry": {"coordinates":[151.489700317,-33.2674407959],"type":"Point"}
}