{
  "type": "Feature",
  "properties": {
    "addr:full":"1 Jarrah Crt Ourimbah NSW 2258",
    "addr:housenumber":"1",
    "addr:postcode":"2258",
    "addr:street":"Jarrah Crt",
    "iso:country":"AU",
    "sg:address":"1 Jarrah Crt",
    "sg:city":"Ourimbah",
    "sg:classifiers":[
        {
            "category":"Health Services",
            "subcategory":"Health Practitioner",
            "type":"Services"
        }
    ],
    "sg:phone":"+61 410 234 490",
    "sg:postcode":"2258",
    "sg:province":"NSW",
    "sg:tags":[
        "naturopath"
    ],
    "wof:name":"Bodywise Therapies",
    "wof:placetype":"venue"
},
  "geometry": {"coordinates":[151.38026428200001,-33.3646430969],"type":"Point"}
}