{
  "type": "Feature",
  "properties": {
    "addr:full":"5/ 871 Boundary Rd Coopers Plains QLD 4108",
    "addr:housenumber":"/ 871",
    "addr:postcode":"4108",
    "addr:street":"Boundary Rd",
    "iso:country":"AU",
    "sg:address":"5/ 871 Boundary Rd",
    "sg:city":"Coopers Plains",
    "sg:classifiers":[
        {
            "category":"Food & Beverages",
            "subcategory":"Bakery",
            "type":"Retail Goods"
        }
    ],
    "sg:phone":"+61 7 3344 4690",
    "sg:postcode":"4108",
    "sg:province":"QLD",
    "sg:tags":[
        "baker"
    ],
    "wof:name":"Byblos Bakery",
    "wof:placetype":"venue"
},
  "geometry": {"coordinates":[153.031158447,-27.5694465637],"type":"Point"}
}