{
  "type": "Feature",
  "properties": {
    "addr:full":"37 Hume St Huntingdale VIC 3166",
    "addr:housenumber":"37",
    "addr:postcode":"3166",
    "addr:street":"Hume St",
    "iso:country":"AU",
    "sg:address":"37 Hume St",
    "sg:city":"Huntingdale",
    "sg:classifiers":[
        {
            "category":"Professional",
            "type":"Services"
        }
    ],
    "sg:phone":"+61 3 9544 1251",
    "sg:postcode":"3166",
    "sg:province":"VIC",
    "sg:tags":[
        "spray",
        "painting"
    ],
    "wof:name":"P.K. Panels Pty Ltd",
    "wof:placetype":"venue"
},
  "geometry": {"coordinates":[145.104003906,-37.9106864929],"type":"Point"}
}