{
  "type": "Feature",
  "properties": {
    "iso:country":"AU",
    "sg:address":"27 Mars Rd",
    "sg:city":"Lane Cove",
    "sg:classifiers":[
        {
            "category":"Food & Beverages",
            "subcategory":"Liquor & Beverages",
            "type":"Retail Goods"
        }
    ],
    "sg:phone":"+61 2 9418 3499",
    "sg:postcode":"2066",
    "sg:province":"NSW",
    "sg:tags":[
        "store"
    ],
    "wof:name":"Wine Brothers",
    "wof:placetype":"venue"
},
  "geometry": {"coordinates":[151.144363403,-33.8100624084],"type":"Point"}
}