{
  "type": "Feature",
  "properties": {
    "addr:full":"Level 50 101 96-104 Dryburgh St North Melbourne VIC 3051",
    "addr:housenumber":"101",
    "addr:postcode":"96-104;3051",
    "addr:street":"Dryburgh St",
    "iso:country":"AU",
    "sg:address":"Level 50 101 96-104 Dryburgh St",
    "sg:city":"North Melbourne",
    "sg:classifiers":[
        {
            "category":"Professional",
            "subcategory":"Detective & Security Services",
            "type":"Services"
        }
    ],
    "sg:phone":"+61 1300 131 395",
    "sg:postcode":"3051",
    "sg:province":"VIC",
    "sg:tags":[
        "guard",
        "patrol"
    ],
    "wof:name":"ADF Group",
    "wof:placetype":"venue"
},
  "geometry": {"coordinates":[144.94351196299999,-37.8042106628],"type":"Point"}
}