{
  "type": "Feature",
  "properties": {
    "iso:country":"AU",
    "sg:address":"956a Whitehorse Rd",
    "sg:city":"Box Hill",
    "sg:classifiers":[
        {
            "category":"Food & Beverages",
            "subcategory":"Specialty",
            "type":"Retail Goods"
        }
    ],
    "sg:phone":"+61 3 9890 3718",
    "sg:postcode":"3128",
    "sg:province":"VIC",
    "sg:tags":[
        "product",
        "health"
    ],
    "wof:name":"Golden Dragon Wood",
    "wof:placetype":"venue"
},
  "geometry": {"coordinates":[145.123657227,-37.8183746338],"type":"Point"}
}