{
  "type": "Feature",
  "properties": {
    "iso:country":"AU",
    "sg:address":"6 Kyogle Pl",
    "sg:city":"Port Macquarie",
    "sg:classifiers":[
        {
            "category":"Building & Trades",
            "subcategory":"Construction",
            "type":"Services"
        }
    ],
    "sg:phone":"+61 2 6581 1595",
    "sg:postcode":"2444",
    "sg:province":"NSW",
    "sg:tags":[
        "rendering",
        "cement"
    ],
    "wof:name":"Murphy Joyce McCleery",
    "wof:placetype":"venue"
},
  "geometry": {"coordinates":[152.89746099999999,-31.442335],"type":"Point"}
}