{
  "type": "Feature",
  "properties": {
    "addr:full":"14 Grice St Clontarf QLD 4019",
    "addr:housenumber":"14",
    "addr:postcode":"4019",
    "addr:street":"Grice St",
    "iso:country":"AU",
    "sg:address":"14 Grice St",
    "sg:city":"Clontarf",
    "sg:classifiers":[
        {
            "category":"Professional",
            "subcategory":"Printing & Photocopies",
            "type":"Services"
        }
    ],
    "sg:phone":"+61 7 3284 4466",
    "sg:postcode":"4019",
    "sg:province":"QLD",
    "sg:tags":[
        "screen",
        "printer"
    ],
    "wof:name":"Digiprint and Screen Pty Ltd",
    "wof:placetype":"venue"
},
  "geometry": {"coordinates":[153.080078125,-27.2395648956],"type":"Point"}
}