{
  "type": "Feature",
  "properties": {
    "addr:full":"5 / 100 Sugar Rd Maroochydore QLD 4558",
    "addr:housenumber":"/ 100",
    "addr:postcode":"4558",
    "addr:street":"Sugar Rd",
    "iso:country":"AU",
    "sg:address":"5 / 100 Sugar Rd",
    "sg:city":"Maroochydore",
    "sg:classifiers":[
        {
            "category":"Banks & Credit Unions",
            "subcategory":"Investment Brokerage",
            "type":"Services"
        }
    ],
    "sg:phone":"+61 7 5479 3118",
    "sg:postcode":"4558",
    "sg:province":"QLD",
    "sg:tags":[
        "equipment",
        "spray",
        "painting",
        "supply"
    ],
    "wof:name":"Peninsula Paint Supplies",
    "wof:placetype":"venue"
},
  "geometry": {"coordinates":[153.09483337399999,-26.6692047119],"type":"Point"}
}