{
  "type": "Feature",
  "properties": {
    "iso:country":"AU",
    "sg:address":"Narara Valley Drv",
    "sg:city":"Niagara Park",
    "sg:classifiers":[
        {
            "category":"Shopping",
            "subcategory":"Musical Instruments",
            "type":"Retail Goods"
        }
    ],
    "sg:phone":"+61 2 4329 5195",
    "sg:postcode":"2250",
    "sg:province":"NSW",
    "sg:tags":[
        "musician",
        "agent"
    ],
    "wof:name":"David Martucci",
    "wof:placetype":"venue"
},
  "geometry": {"coordinates":[151.35025024399999,-33.3835601807],"type":"Point"}
}