{
  "type": "Feature",
  "properties": {
    "addr:full":"Shop 18, Mirrabooka Shopping Centre, 43 Yirrigan D Mirrabooka WA 6061",
    "addr:housenumber":"shop 18;43",
    "addr:postcode":"6061",
    "addr:street":"Yirrigan D",
    "iso:country":"AU",
    "sg:address":"Shop 18, Mirrabooka Shopping Centre, 43 Yirrigan D",
    "sg:city":"Mirrabooka",
    "sg:classifiers":[
        {
            "category":"Shopping",
            "subcategory":"Clothing, Apparel, & Fashions",
            "type":"Retail Goods"
        }
    ],
    "sg:phone":"+61 8 9440 6635",
    "sg:postcode":"6061",
    "sg:province":"WA",
    "sg:tags":[
        "lady",
        "wear"
    ],
    "wof:name":"Gabrielles Fashions",
    "wof:placetype":"venue"
},
  "geometry": {"coordinates":[115.86032104500001,-31.8728408813],"type":"Point"}
}