{
  "type": "Feature",
  "properties": {
    "iso:country":"AU",
    "sg:address":"290 Springwood Rd",
    "sg:city":"Springwood",
    "sg:classifiers":[
        {
            "category":"Building & Trades",
            "subcategory":"Construction",
            "type":"Services"
        }
    ],
    "sg:phone":"+61 7 3808 7447",
    "sg:postcode":"4127",
    "sg:province":"QLD",
    "sg:tags":[
        "tennis court",
        "repair"
    ],
    "wof:name":"CCS",
    "wof:placetype":"venue"
},
  "geometry": {"coordinates":[153.13981628400001,-27.6178302765],"type":"Point"}
}