{
  "type": "Feature",
  "properties": {
    "addr:full":"119a Military Rd Semaphore SA 5019",
    "addr:housenumber":"119a",
    "addr:postcode":"5019",
    "addr:street":"Military Rd",
    "iso:country":"AU",
    "sg:address":"119a Military Rd",
    "sg:city":"Semaphore",
    "sg:classifiers":[
        {
            "category":"Fast Food",
            "type":"Food & Drink"
        }
    ],
    "sg:phone":"+61 8 8242 1011",
    "sg:postcode":"5019",
    "sg:province":"SA",
    "sg:tags":[
        "away",
        "take"
    ],
    "wof:name":"Bellinis Pizza Bar",
    "wof:placetype":"venue"
},
  "geometry": {"coordinates":[138.48171997099999,-34.8440093994],"type":"Point"}
}