{
  "type": "Feature",
  "properties": {
    "iso:country":"AU",
    "sg:address":"3 Maple St",
    "sg:city":"Maleny",
    "sg:classifiers":[
        {
            "category":"Cafe",
            "type":"Food & Drink"
        }
    ],
    "sg:phone":"+61 7 5499 9177",
    "sg:postcode":"4552",
    "sg:province":"QLD",
    "wof:name":"Maple 3 Cafe",
    "wof:placetype":"venue"
},
  "geometry": {"coordinates":[152.852294922,-26.7581825256],"type":"Point"}
}