{
  "type": "Feature",
  "properties": {
    "iso:country":"AU",
    "sg:address":"Ground Floor, 369 Royal Pde",
    "sg:city":"Parkville",
    "sg:classifiers":[
        {
            "category":"Shopping",
            "subcategory":"Bicycles & Sporting Goods",
            "type":"Retail Goods"
        }
    ],
    "sg:phone":"+61 419 877 108",
    "sg:postcode":"3052",
    "sg:province":"VIC",
    "sg:tags":[
        "synthetic",
        "surface"
    ],
    "wof:name":"Fake It Grass",
    "wof:placetype":"venue"
},
  "geometry": {"coordinates":[144.959060669,-37.7848052979],"type":"Point"}
}