{
  "type": "Feature",
  "properties": {
    "addr:full":"3/ 80 Centennial Cct Byron Bay NSW 2481",
    "addr:housenumber":"/ 80",
    "addr:postcode":"2481",
    "addr:street":"Centennial Cct",
    "iso:country":"AU",
    "sg:address":"3/ 80",
    "sg:city":"Centennial Cct Byron Bay",
    "sg:classifiers":[
        {
            "category":"Retail",
            "subcategory":"Auto Repair",
            "type":"Services"
        }
    ],
    "sg:phone":"+61 2 6685 7776",
    "sg:postcode":"2481",
    "sg:province":"NSW",
    "sg:tags":[
        "electrical"
    ],
    "wof:name":"Byron Bay Car Airconditioning",
    "wof:placetype":"venue"
},
  "geometry": {"coordinates":[153.57937622099999,-28.6370677948],"type":"Point"}
}