{
  "type": "Feature",
  "properties": {
    "iso:country":"AU",
    "sg:address":"PO Box 4487",
    "sg:city":"Forest Lake",
    "sg:classifiers":[
        {
            "category":"Shopping",
            "subcategory":"Stationery & Office Supplies",
            "type":"Retail Goods"
        }
    ],
    "sg:phone":"+61 419 015 648",
    "sg:postcode":"4078",
    "sg:province":"QLD",
    "sg:tags":[
        "equipment",
        "badge",
        "making"
    ],
    "wof:name":"DVMS Badges",
    "wof:placetype":"venue"
},
  "geometry": {"coordinates":[152.97018432600001,-27.6128292084],"type":"Point"}
}