{
  "type": "Feature",
  "properties": {
    "addr:full":"205 Koornang Rd Carnegie VIC 3163",
    "addr:housenumber":"205",
    "addr:postcode":"3163",
    "addr:street":"Koornang Rd",
    "iso:country":"AU",
    "sg:address":"205 Koornang Rd",
    "sg:city":"Carnegie",
    "sg:classifiers":[
        {
            "category":"Health Services",
            "subcategory":"Doctor",
            "type":"Services"
        }
    ],
    "sg:phone":"+61 3 9563 5999",
    "sg:postcode":"3163",
    "sg:province":"VIC",
    "sg:tags":[
        "medical",
        "practitioner"
    ],
    "wof:name":"Kioussis John",
    "wof:placetype":"venue"
},
  "geometry": {"coordinates":[145.05670165999999,-37.8919334412],"type":"Point"}
}