{
  "type": "Feature",
  "properties": {
    "iso:country":"AU",
    "sg:address":"9 Peace St",
    "sg:city":"Paget",
    "sg:classifiers":[
        {
            "category":"Building & Trades",
            "subcategory":"Construction",
            "type":"Services"
        }
    ],
    "sg:phone":"+61 7 4952 1140",
    "sg:postcode":"4740",
    "sg:province":"QLD",
    "sg:tags":[
        "home",
        "air conditioning"
    ],
    "wof:name":"McGuire Air",
    "wof:placetype":"venue"
},
  "geometry": {"coordinates":[149.172653,-21.172089],"type":"Point"}
}