{
  "type": "Feature",
  "properties": {
    "iso:country":"AU",
    "sg:address":"Main Rd",
    "sg:city":"Wivenhoe",
    "sg:classifiers":[
        {
            "category":"Home & Garden",
            "subcategory":"Building Materials",
            "type":"Retail Goods"
        }
    ],
    "sg:phone":"+61 3 6431 1688",
    "sg:postcode":"7320",
    "sg:province":"TAS",
    "sg:tags":[
        "supply"
    ],
    "wof:name":"Gunns Timber & Hardware",
    "wof:placetype":"venue"
},
  "geometry": {"coordinates":[145.92659,-41.06723],"type":"Point"}
}