{
  "type": "Feature",
  "properties": {
    "addr:full":"58 Forge Creek Rd Bairnsdale VIC 3875",
    "addr:housenumber":"58",
    "addr:postcode":"3875",
    "addr:street":"Forge Creek Rd",
    "iso:country":"AU",
    "sg:address":"58 Forge Creek Rd",
    "sg:city":"Bairnsdale",
    "sg:classifiers":[
        {
            "category":"Landmark",
            "subcategory":"Scenic View",
            "type":"Public Place"
        }
    ],
    "sg:phone":"+61 3 5153 0440",
    "sg:postcode":"3875",
    "sg:province":"VIC",
    "sg:tags":[
        "staircase",
        "handrail"
    ],
    "wof:name":"Riviera Joinery",
    "wof:placetype":"venue"
},
  "geometry": {"coordinates":[147.669723511,-37.8946495056],"type":"Point"}
}