{
  "type": "Feature",
  "properties": {
    "addr:full":"2 Keele Pl Kidman Park SA 5025",
    "addr:housenumber":"2",
    "addr:postcode":"5025",
    "addr:street":"Keele Pl",
    "iso:country":"AU",
    "sg:address":"2 Keele Pl",
    "sg:city":"Kidman Park",
    "sg:classifiers":[
        {
            "category":"Retail",
            "subcategory":"Auto Repair",
            "type":"Services"
        }
    ],
    "sg:phone":"+61 8 8235 2095",
    "sg:postcode":"5025",
    "sg:province":"SA",
    "sg:tags":[
        "repairer",
        "motor",
        "engineer"
    ],
    "wof:name":"Mancini Mechanical Repairs Pty Ltd",
    "wof:placetype":"venue"
},
  "geometry": {"coordinates":[138.53268432600001,-34.9111404419],"type":"Point"}
}