{
  "type": "Feature",
  "properties": {
    "addr:full":"35 Forge St Blacktown NSW 2148",
    "addr:housenumber":"35",
    "addr:postcode":"2148",
    "addr:street":"Forge St",
    "iso:country":"AU",
    "sg:address":"35 Forge St",
    "sg:city":"Blacktown",
    "sg:classifiers":[
        {
            "category":"Autos & Motor Vehicles",
            "subcategory":"Automobile Sales",
            "type":"Retail Goods"
        }
    ],
    "sg:phone":"+61 425 346 660",
    "sg:postcode":"2148",
    "sg:province":"NSW",
    "sg:tags":[
        "equipment",
        "trailer"
    ],
    "wof:name":"D.M.S. Colrain Wholesalers",
    "wof:placetype":"venue"
},
  "geometry": {"coordinates":[150.91026306099999,-33.7540054321],"type":"Point"}
}