{
  "type": "Feature",
  "properties": {
    "iso:country":"AU",
    "sg:address":"98 O'Sullivan Beach Rd",
    "sg:city":"Lonsdale",
    "sg:classifiers":[
        {
            "category":"Building & Trades",
            "subcategory":"Construction",
            "type":"Services"
        }
    ],
    "sg:phone":"+61 8 8384 8622",
    "sg:postcode":"5160",
    "sg:province":"SA",
    "sg:tags":[
        "welding"
    ],
    "wof:name":"Tonkin Radiators",
    "wof:placetype":"venue"
},
  "geometry": {"coordinates":[138.50384521500001,-35.1168632507],"type":"Point"}
}