{
  "type": "Feature",
  "properties": {
    "addr:full":"4 Connecticut Ave Five Dock NSW 2046",
    "addr:housenumber":"4",
    "addr:postcode":"2046",
    "addr:street":"Connecticut Ave",
    "iso:country":"AU",
    "sg:address":"4 Connecticut Ave",
    "sg:city":"Five Dock",
    "sg:classifiers":[
        {
            "category":"Professional",
            "subcategory":"Computer Services",
            "type":"Services"
        }
    ],
    "sg:phone":"+61 2 9712 0693",
    "sg:postcode":"2046",
    "sg:province":"NSW",
    "sg:tags":[
        "consultant",
        "system"
    ],
    "wof:name":"Rivendell Consulting Pty Ltd",
    "wof:placetype":"venue"
},
  "geometry": {"coordinates":[151.13514699999999,-33.871193],"type":"Point"}
}