{
  "type": "Feature",
  "properties": {
    "iso:country":"AU",
    "sg:address":"50 Wises Rd",
    "sg:city":"Gympie",
    "sg:classifiers":[
        {
            "category":"Building & Trades",
            "subcategory":"Cleaning & Sanitation",
            "type":"Services"
        }
    ],
    "sg:phone":"+61 7 5482 3279",
    "sg:postcode":"4570",
    "sg:province":"QLD",
    "sg:tags":[
        "industrial",
        "commercial",
        "contractor"
    ],
    "wof:name":"Columbia Cleaning Service",
    "wof:placetype":"venue"
},
  "geometry": {"coordinates":[152.68409729000001,-26.194480896],"type":"Point"}
}