{
  "type": "Feature",
  "properties": {
    "iso:country":"AU",
    "sg:address":"52 Faull St",
    "sg:city":"Charters Towers",
    "sg:classifiers":[
        {
            "category":"Building & Trades",
            "subcategory":"Landscaping Services",
            "type":"Services"
        }
    ],
    "sg:phone":"+61 7 4787 1521",
    "sg:postcode":"4820",
    "sg:province":"QLD",
    "sg:tags":[
        "grazier"
    ],
    "wof:name":"Axford I F (Grazing) Pty Ltd",
    "wof:placetype":"venue"
},
  "geometry": {"coordinates":[146.248062,-20.077406],"type":"Point"}
}