{
  "type": "Feature",
  "properties": {
    "iso:country":"AU",
    "sg:address":"PO Box 7040",
    "sg:city":"Brendale",
    "sg:classifiers":[
        {
            "category":"Arts & Performance",
            "subcategory":"Music",
            "type":"Entertainment"
        }
    ],
    "sg:phone":"+61 407 730 294",
    "sg:postcode":"4500",
    "sg:province":"QLD",
    "sg:tags":[
        "mobile",
        "jockey",
        "disc"
    ],
    "wof:name":"Club DJ",
    "wof:placetype":"venue"
},
  "geometry": {"coordinates":[152.982345581,-27.32695961],"type":"Point"}
}