{
  "type": "Feature",
  "properties": {
    "iso:country":"AU",
    "sg:address":"Marryatville Shopping Centre, Shop 5/ 242-248 Kensington Rd",
    "sg:city":"Marryatville",
    "sg:classifiers":[
        {
            "category":"Fast Food",
            "type":"Food & Drink"
        }
    ],
    "sg:phone":"+61 8 8431 9380",
    "sg:postcode":"5068",
    "sg:province":"SA",
    "sg:tags":[
        "away",
        "take"
    ],
    "wof:name":"Noodle Box",
    "wof:placetype":"venue"
},
  "geometry": {"coordinates":[138.65005493199999,-34.926612854],"type":"Point"}
}