{
  "type": "Feature",
  "properties": {
    "iso:country":"AU",
    "sg:address":"29 Berkeley Crs",
    "sg:city":"Floreat",
    "sg:classifiers":[
        {
            "category":"Professional",
            "subcategory":"Art Services",
            "type":"Services"
        }
    ],
    "sg:phone":"+61 8 9387 3936",
    "sg:postcode":"6014",
    "sg:province":"WA",
    "sg:tags":[
        "graphic",
        "designer"
    ],
    "wof:name":"Perpetual Motion Design Services Pty Ltd",
    "wof:placetype":"venue"
},
  "geometry": {"coordinates":[115.795776367,-31.9442691803],"type":"Point"}
}