{
  "type": "Feature",
  "properties": {
    "addr:full":"4 Fay Crt Croydon VIC 3136",
    "addr:housenumber":"4",
    "addr:postcode":"3136",
    "addr:street":"Fay Crt",
    "iso:country":"AU",
    "sg:address":"4 Fay Crt",
    "sg:city":"Croydon",
    "sg:classifiers":[
        {
            "category":"Autos & Motor Vehicles",
            "subcategory":"Auto Supplies",
            "type":"Retail Goods"
        }
    ],
    "sg:phone":"+61 3 9723 0199",
    "sg:postcode":"3136",
    "sg:province":"VIC",
    "sg:tags":[
        "part",
        "cycles",
        "accessory"
    ],
    "wof:name":"Precision Shims Australia",
    "wof:placetype":"venue"
},
  "geometry": {"coordinates":[145.299484253,-37.8032722473],"type":"Point"}
}