{
  "type": "Feature",
  "properties": {
    "iso:country":"AU",
    "sg:address":"714b Pennant Hills St",
    "sg:city":"Carlingford",
    "sg:classifiers":[
        {
            "category":"Health Services",
            "subcategory":"Doctor",
            "type":"Services"
        }
    ],
    "sg:phone":"+61 2 9871 2633",
    "sg:postcode":"2118",
    "sg:province":"NSW",
    "sg:tags":[
        "medical",
        "practitioner"
    ],
    "wof:name":"Jameson Jeanette & Hay J A",
    "wof:placetype":"venue"
},
  "geometry": {"coordinates":[151.04725647000001,-33.7661743164],"type":"Point"}
}