{
  "type": "Feature",
  "properties": {
    "addr:full":"5 / 111 Flora Tce North Beach WA 6020",
    "addr:housenumber":"/ 111",
    "addr:postcode":"6020",
    "addr:street":"Flora Tce",
    "iso:country":"AU",
    "sg:address":"5 / 111 Flora Tce",
    "sg:city":"North Beach",
    "sg:classifiers":[
        {
            "category":"Professional",
            "subcategory":"Accounting & Tax Preparation",
            "type":"Services"
        }
    ],
    "sg:phone":"+61 1300 724 430",
    "sg:postcode":"6020",
    "sg:province":"WA",
    "sg:tags":[
        "consultant",
        "taxation"
    ],
    "wof:name":"Cabot Square - North Beach",
    "wof:placetype":"venue"
},
  "geometry": {"coordinates":[115.754249573,-31.8561286926],"type":"Point"}
}