{
  "type": "Feature",
  "properties": {
    "iso:country":"AU",
    "sg:address":"46 Sentinel Crt",
    "sg:city":"Cleveland",
    "sg:classifiers":[
        {
            "category":"Real Estate",
            "subcategory":"Developer",
            "type":"Services"
        }
    ],
    "sg:phone":"+61 7 3821 2015",
    "sg:postcode":"4163",
    "sg:province":"QLD",
    "sg:tags":[
        "development"
    ],
    "wof:name":"Cherish Enterprises Pty Ltd",
    "wof:placetype":"venue"
},
  "geometry": {"coordinates":[153.27406310999999,-27.5166416168],"type":"Point"}
}