{
  "type": "Feature",
  "properties": {
    "addr:full":"399 Melton-Keilor Hwy Sydenham VIC 3037",
    "addr:housenumber":"399",
    "addr:postcode":"3037",
    "addr:street":"Melton-Keilor Hwy",
    "iso:country":"AU",
    "sg:address":"399 Melton-Keilor Hwy",
    "sg:city":"Sydenham",
    "sg:classifiers":[
        {
            "category":"Autos & Motor Vehicles",
            "subcategory":"Fuel & Gas Station",
            "type":"Retail Goods"
        }
    ],
    "sg:phone":"+61 3 9390 4311",
    "sg:postcode":"3037",
    "sg:province":"VIC",
    "wof:name":"Plus Petrol",
    "wof:placetype":"venue"
},
  "geometry": {"coordinates":[144.763428,-37.701809],"type":"Point"}
}