{
  "type": "Feature",
  "properties": {
    "addr:full":"Allamonda Surgi Centre 103 Nerang St Southport QLD 4215",
    "addr:housenumber":"103",
    "addr:postcode":"4215",
    "addr:street":"Nerang St",
    "iso:country":"AU",
    "sg:address":"Allamonda Surgi Centre 103 Nerang St",
    "sg:city":"Southport",
    "sg:classifiers":[
        {
            "category":"Health Services",
            "subcategory":"Medical Lab",
            "type":"Services"
        }
    ],
    "sg:phone":"+61 7 5573 8805",
    "sg:postcode":"4215",
    "sg:province":"QLD",
    "sg:tags":[
        "laboratory",
        "pathology"
    ],
    "wof:name":"Sullivan Nicolaides Pathology Laboratories",
    "wof:placetype":"venue"
},
  "geometry": {"coordinates":[153.4087677,-27.9703159332],"type":"Point"}
}