{
  "type": "Feature",
  "properties": {
    "iso:country":"AU",
    "sg:address":"Watergardens Homemaker Cntr, 399 Melton Hwy",
    "sg:city":"Taylors Lakes",
    "sg:classifiers":[
        {
            "category":"Home & Garden",
            "subcategory":"Garden Supply",
            "type":"Retail Goods"
        }
    ],
    "sg:phone":"+61 3 8390 7666",
    "sg:postcode":"3038",
    "sg:province":"VIC",
    "sg:tags":[
        "equipment"
    ],
    "wof:name":"Flower Power Garden Centres",
    "wof:placetype":"venue"
},
  "geometry": {"coordinates":[144.778427,-37.696995],"type":"Point"}
}