{
  "type": "Feature",
  "properties": {
    "addr:full":"3 Tottenham Court Rd Port Elliot SA 5212",
    "addr:housenumber":"3",
    "addr:postcode":"5212",
    "addr:street":"Tottenham Court Rd",
    "iso:country":"AU",
    "sg:address":"3 Tottenham Court Rd",
    "sg:city":"Port Elliot",
    "sg:classifiers":[
        {
            "category":"Utilities",
            "subcategory":"Water",
            "type":"Services"
        }
    ],
    "sg:phone":"+61 8 8554 2770",
    "sg:postcode":"5212",
    "sg:province":"SA",
    "sg:tags":[
        "hot",
        "system"
    ],
    "wof:name":"Horseshoe Bay Plumbing Service.",
    "wof:placetype":"venue"
},
  "geometry": {"coordinates":[138.67701721200001,-35.5305557251],"type":"Point"}
}