{
  "type": "Feature",
  "properties": {
    "addr:full":"196 Brooklands Rd Hall ACT 2618",
    "addr:housenumber":"196",
    "addr:postcode":"2618",
    "addr:street":"Brooklands Rd",
    "iso:country":"AU",
    "sg:address":"196 Brooklands Rd",
    "sg:city":"Hall",
    "sg:classifiers":[
        {
            "category":"Farming",
            "subcategory":"Vineyard",
            "type":"Manufacturing & Wholesale Goods"
        }
    ],
    "sg:phone":"+61 2 6230 2831",
    "sg:postcode":"2618",
    "sg:province":"ACT",
    "sg:tags":[
        "winery"
    ],
    "wof:name":"Wallaroo Wines",
    "wof:placetype":"venue"
},
  "geometry": {"coordinates":[148.97808837900001,-35.1618041992],"type":"Point"}
}