{
  "type": "Feature",
  "properties": {
    "addr:full":"79 Regent St Shepparton VIC 3630",
    "addr:housenumber":"79",
    "addr:postcode":"3630",
    "addr:street":"Regent St",
    "iso:country":"AU",
    "sg:address":"79 Regent St",
    "sg:city":"Shepparton",
    "sg:classifiers":[
        {
            "category":"Farming",
            "subcategory":"Farm & Veterinary Services",
            "type":"Manufacturing & Wholesale Goods"
        }
    ],
    "sg:phone":"+61 3 5821 3961",
    "sg:postcode":"3630",
    "sg:province":"VIC",
    "sg:tags":[
        "seedsman"
    ],
    "wof:name":"Ford W L",
    "wof:placetype":"venue"
},
  "geometry": {"coordinates":[145.39822387699999,-36.3693466187],"type":"Point"}
}