{
  "type": "Feature",
  "properties": {
    "addr:full":"Unit 3/ 27 Dale St Brookvale NSW 2100",
    "addr:housenumber":"27",
    "addr:postcode":"2100",
    "addr:street":"Dale St",
    "iso:country":"AU",
    "sg:address":"Unit 3/ 27 Dale St",
    "sg:city":"Brookvale",
    "sg:classifiers":[
        {
            "category":"Wholesale",
            "subcategory":"Metals & Minerals",
            "type":"Manufacturing & Wholesale Goods"
        }
    ],
    "sg:phone":"+61 2 9905 3277",
    "sg:postcode":"2100",
    "sg:province":"NSW",
    "sg:tags":[
        "steel",
        "stainless",
        "product",
        "equipment"
    ],
    "wof:name":"Stainless Piping Products Pty Ltd",
    "wof:placetype":"venue"
},
  "geometry": {"coordinates":[151.26858520499999,-33.765045166],"type":"Point"}
}