{
  "type": "Feature",
  "properties": {
    "addr:full":"137 Victoria Rd Rozelle NSW 2039",
    "addr:housenumber":"137",
    "addr:postcode":"2039",
    "addr:street":"Victoria Rd",
    "iso:country":"AU",
    "sg:address":"137 Victoria Rd",
    "sg:city":"Rozelle",
    "sg:classifiers":[
        {
            "category":"Professional",
            "type":"Services"
        }
    ],
    "sg:phone":"+61 2 9810 7482",
    "sg:postcode":"2039",
    "sg:province":"NSW",
    "sg:tags":[
        "spray",
        "painting"
    ],
    "wof:name":"Victoria Road Smash Repairs & Bodyworks Pty Ltd",
    "wof:placetype":"venue"
},
  "geometry": {"coordinates":[151.16673278799999,-33.8616638184],"type":"Point"}
}