{
  "type": "Feature",
  "properties": {
    "iso:country":"AU",
    "sg:address":"235 St",
    "sg:city":"Georges Tce Perth",
    "sg:classifiers":[
        {
            "category":"Building & Trades",
            "subcategory":"Plumbing",
            "type":"Services"
        }
    ],
    "sg:phone":"+61 8 9227 7242",
    "sg:postcode":"6000",
    "sg:province":"WA",
    "sg:tags":[
        "consultant"
    ],
    "wof:name":"R.C. Oma Design Services Pty Ltd",
    "wof:placetype":"venue"
},
  "geometry": {"coordinates":[115.851257324,-31.9531135559],"type":"Point"}
}