{
  "type": "Feature",
  "properties": {
    "addr:full":"Langslow St Castlemaine VIC 3450",
    "addr:postcode":"3450",
    "addr:street":"Langslow St",
    "iso:country":"AU",
    "sg:address":"Langslow St",
    "sg:city":"Castlemaine",
    "sg:classifiers":[
        {
            "category":"Real Estate",
            "subcategory":"Real Estate Agent",
            "type":"Services"
        }
    ],
    "sg:phone":"+61 3 5472 4302",
    "sg:postcode":"3450",
    "sg:province":"VIC",
    "sg:tags":[
        "steel",
        "foundry",
        "iron"
    ],
    "wof:name":"Billmans Foundry Pty Ltd",
    "wof:placetype":"venue"
},
  "geometry": {"coordinates":[144.20179748499999,-37.0711479187],"type":"Point"}
}