{
  "type": "Feature",
  "properties": {
    "addr:full":"PO Box 8330 South Gladstone QLD 4680",
    "addr:postcode":"4680",
    "addr:street":"South",
    "iso:country":"AU",
    "sg:address":"PO Box 8330",
    "sg:city":"South Gladstone",
    "sg:classifiers":[
        {
            "category":"Professional",
            "subcategory":"Accounting & Tax Preparation",
            "type":"Services"
        }
    ],
    "sg:phone":"+61 411 440 878",
    "sg:postcode":"4680",
    "sg:province":"QLD",
    "sg:tags":[
        "bookkeeping"
    ],
    "wof:name":"Adept Bookkeeping & Administration Services",
    "wof:placetype":"venue"
},
  "geometry": {"coordinates":[151.26481628400001,-23.8740692139],"type":"Point"}
}