{
  "type": "Feature",
  "properties": {
    "iso:country":"AU",
    "sg:address":"260 Captain Cook Drv",
    "sg:city":"Kurnell",
    "sg:classifiers":[
        {
            "category":"Home & Garden",
            "subcategory":"Furniture",
            "type":"Retail Goods"
        }
    ],
    "sg:phone":"+61 2 9668 8400",
    "sg:postcode":"2231",
    "sg:province":"NSW",
    "sg:tags":[
        "business"
    ],
    "wof:name":"Versatec Industries Pty Ltd",
    "wof:placetype":"venue"
},
  "geometry": {"coordinates":[151.21601867699999,-34.0071411133],"type":"Point"}
}