{
  "type": "Feature",
  "properties": {
    "iso:country":"AU",
    "sg:address":"45 Stuart St",
    "sg:city":"Toowoomba City",
    "sg:classifiers":[
        {
            "category":"Organizations",
            "subcategory":"Membership Organization",
            "type":"Services"
        }
    ],
    "sg:phone":"+61 7 4638 4808",
    "sg:postcode":"4350",
    "sg:province":"QLD",
    "sg:tags":[
        "club",
        "bridge"
    ],
    "wof:name":"Toowoomba Bridge Club Inc",
    "wof:placetype":"venue"
},
  "geometry": {"coordinates":[151.9487,-27.568518],"type":"Point"}
}