{
  "type": "Feature",
  "properties": {
    "addr:full":"Level5, 165 Flinders La Melbourne VIC 3000",
    "addr:housenumber":"165",
    "addr:postcode":"3000",
    "addr:street":"Level5;Flinders La",
    "iso:country":"AU",
    "sg:address":"Level5, 165 Flinders La",
    "sg:city":"Melbourne",
    "sg:classifiers":[
        {
            "category":"Building & Trades",
            "subcategory":"Landscaping Services",
            "type":"Services"
        }
    ],
    "sg:phone":"+61 3 9639 0391",
    "sg:postcode":"3000",
    "sg:province":"VIC",
    "sg:tags":[
        "architect",
        "landscape"
    ],
    "wof:name":"Site Office",
    "wof:placetype":"venue"
},
  "geometry": {"coordinates":[144.96896362300001,-37.816028595],"type":"Point"}
}