{
  "type": "Feature",
  "properties": {
    "addr:full":"Grnd Floor 225 Greenhill Rd Dulwich SA 5065",
    "addr:housenumber":"225",
    "addr:postcode":"5065",
    "addr:street":"Grnd Floor;Greenhill Rd",
    "iso:country":"AU",
    "sg:address":"Grnd Floor 225 Greenhill Rd",
    "sg:city":"Dulwich",
    "sg:classifiers":[
        {
            "category":"Banks & Credit Unions",
            "subcategory":"Financial Services",
            "type":"Services"
        }
    ],
    "sg:phone":"+61 8 8364 8000",
    "sg:postcode":"5065",
    "sg:province":"SA",
    "sg:tags":[
        "planning"
    ],
    "wof:name":"Genesys Wealth Advisers",
    "wof:placetype":"venue"
},
  "geometry": {"coordinates":[138.63221740700001,-34.9396514893],"type":"Point"}
}