{
  "type": "Feature",
  "properties": {
    "iso:country":"AU",
    "sg:address":"36 A Park Ave",
    "sg:city":"Mosman",
    "sg:classifiers":[
        {
            "category":"Professional",
            "subcategory":"Business Services",
            "type":"Services"
        }
    ],
    "sg:phone":"+61 2 9969 6166",
    "sg:postcode":"2088",
    "sg:province":"NSW",
    "sg:tags":[
        "drafting"
    ],
    "wof:name":"Blakeney Michael",
    "wof:placetype":"venue"
},
  "geometry": {"coordinates":[151.23576355,-33.8325424194],"type":"Point"}
}