{
  "type": "Feature",
  "properties": {
    "addr:full":"Cnr Queen & Prince Sts Busselton WA 6280",
    "addr:postcode":"6280",
    "addr:street":"Cnr",
    "iso:country":"AU",
    "sg:address":"Cnr Queen & Prince Sts",
    "sg:city":"Busselton",
    "sg:classifiers":[
        {
            "category":"Food & Beverages",
            "subcategory":"Bakery",
            "type":"Retail Goods"
        }
    ],
    "sg:phone":"+61 8 9754 6789",
    "sg:postcode":"6280",
    "sg:province":"WA",
    "sg:tags":[
        "baker"
    ],
    "wof:name":"Brumby's WA & NT",
    "wof:placetype":"venue"
},
  "geometry": {"coordinates":[115.344818115,-33.652141571],"type":"Point"}
}