{
  "type": "Feature",
  "properties": {
    "iso:country":"AU",
    "sg:address":"Cnr Maitland St & Rutherford Rd",
    "sg:city":"Muswellbrook",
    "sg:classifiers":[
        {
            "category":"Autos & Motor Vehicles",
            "subcategory":"Automobile Sales",
            "type":"Retail Goods"
        }
    ],
    "sg:phone":"+61 2 6543 3066",
    "sg:postcode":"2333",
    "sg:province":"NSW",
    "sg:tags":[
        "car",
        "new"
    ],
    "wof:name":"Muswellbrook City Ssang Yong",
    "wof:placetype":"venue"
},
  "geometry": {"coordinates":[150.89918518100001,-32.2796707153],"type":"Point"}
}