{
  "type": "Feature",
  "properties": {
    "addr:full":"75 Altson Rd Narre Warren East VIC 3804",
    "addr:housenumber":"75",
    "addr:postcode":"3804",
    "addr:street":"Altson Rd",
    "iso:country":"AU",
    "sg:address":"75 Altson Rd",
    "sg:city":"Narre Warren East",
    "sg:classifiers":[
        {
            "category":"Utilities",
            "subcategory":"Natural Gas",
            "type":"Services"
        }
    ],
    "sg:phone":"+61 419 885 189",
    "sg:postcode":"3804",
    "sg:province":"VIC",
    "sg:tags":[
        "solid",
        "plasterer"
    ],
    "wof:name":"Bell Rob Plastering",
    "wof:placetype":"venue"
},
  "geometry": {"coordinates":[145.367553711,-37.9598999023],"type":"Point"}
}