{
  "type": "Feature",
  "properties": {
    "iso:country":"AU",
    "sg:address":"Lvl 2/ 401 Swanston St",
    "sg:city":"Melbourne",
    "sg:classifiers":[
        {
            "category":"Bars & Pubs",
            "subcategory":"Wine Bar",
            "type":"Food & Drink"
        }
    ],
    "sg:phone":"+61 3 9663 6707",
    "sg:postcode":"3000",
    "sg:province":"VIC",
    "wof:name":"The Order Of Melbourne",
    "wof:placetype":"venue"
},
  "geometry": {"coordinates":[144.963348389,-37.8089141846],"type":"Point"}
}