{
  "type": "Feature",
  "properties": {
    "addr:full":"168A Lilyfield Rd Leichhardt NSW 2040",
    "addr:housenumber":"168a",
    "addr:postcode":"2040",
    "addr:street":"Lilyfield Rd",
    "iso:country":"AU",
    "sg:address":"168A Lilyfield Rd",
    "sg:city":"Leichhardt",
    "sg:classifiers":[
        {
            "category":"Manufacturing",
            "subcategory":"Leather Goods",
            "type":"Manufacturing & Wholesale Goods"
        }
    ],
    "sg:phone":"+61 2 9564 2904",
    "sg:postcode":"2040",
    "sg:province":"NSW",
    "sg:tags":[
        "wholesaler",
        "mfrs"
    ],
    "wof:name":"Estilo Emporio Pty Ltd",
    "wof:placetype":"venue"
},
  "geometry": {"coordinates":[151.15803500000001,-33.874401],"type":"Point"}
}