{
  "type": "Feature",
  "properties": {
    "addr:full":"Shp 19 Falmouth Rd Marayong NSW 2148",
    "addr:housenumber":"19",
    "addr:postcode":"2148",
    "addr:street":"Falmouth Rd",
    "iso:country":"AU",
    "sg:address":"Shp 19 Falmouth Rd",
    "sg:city":"Marayong",
    "sg:classifiers":[
        {
            "category":"Food & Beverages",
            "subcategory":"Meat & Fish",
            "type":"Retail Goods"
        }
    ],
    "sg:phone":"+61 2 9626 1031",
    "sg:postcode":"2148",
    "sg:province":"NSW",
    "sg:tags":[
        "seafood"
    ],
    "wof:name":"Quakers Seafood",
    "wof:placetype":"venue"
},
  "geometry": {"coordinates":[150.88417053200001,-33.7412910461],"type":"Point"}
}