{
  "type": "Feature",
  "properties": {
    "addr:full":"91- 111 Turton Rd Waratah NSW 2298",
    "addr:housenumber":"111",
    "addr:postcode":"2298",
    "addr:street":"91;Turton Rd",
    "iso:country":"AU",
    "sg:address":"91- 111 Turton Rd",
    "sg:city":"Waratah",
    "sg:classifiers":[
        {
            "category":"Communications",
            "subcategory":"Film & Video Production",
            "type":"Services"
        }
    ],
    "sg:phone":"+61 2 4968 3555",
    "sg:postcode":"2298",
    "sg:province":"NSW",
    "sg:tags":[
        "dvd",
        "library"
    ],
    "wof:name":"Blockbuster",
    "wof:placetype":"venue"
},
  "geometry": {"coordinates":[151.727325439,-32.9070320129],"type":"Point"}
}