{
  "type": "Feature",
  "properties": {
    "iso:country":"AU",
    "sg:address":"Cnr May & Mooramba Rds",
    "sg:city":"Dee Why",
    "sg:classifiers":[
        {
            "category":"Autos & Motor Vehicles",
            "subcategory":"Automobile Sales",
            "type":"Retail Goods"
        }
    ],
    "sg:phone":"+61 2 9982 1311",
    "sg:postcode":"2099",
    "sg:province":"NSW",
    "sg:tags":[
        "car",
        "new"
    ],
    "wof:name":"Peninsula Holden Deewhy",
    "wof:placetype":"venue"
},
  "geometry": {"coordinates":[151.28334045400001,-33.7541236877],"type":"Point"}
}