{
  "type": "Feature",
  "properties": {
    "addr:full":"16b Lockhart St Caulfield VIC 3162",
    "addr:housenumber":"16b",
    "addr:postcode":"3162",
    "addr:street":"Lockhart St",
    "iso:country":"AU",
    "sg:address":"16b Lockhart St",
    "sg:city":"Caulfield",
    "sg:classifiers":[
        {
            "category":"Banks & Credit Unions",
            "subcategory":"Investment Brokerage",
            "type":"Services"
        }
    ],
    "sg:phone":"+61 3 9532 8618",
    "sg:postcode":"3162",
    "sg:province":"VIC",
    "wof:name":"Levin Cuttings Pty Ltd",
    "wof:placetype":"venue"
},
  "geometry": {"coordinates":[145.02053832999999,-37.8840255737],"type":"Point"}
}