{
  "type": "Feature",
  "properties": {
    "addr:full":"Lot 106 Louisiana Rd Warnervale NSW 2259",
    "addr:postcode":"2259",
    "addr:street":"Louisiana Rd",
    "iso:country":"AU",
    "sg:address":"Lot 106 Louisiana Rd",
    "sg:city":"Warnervale",
    "sg:classifiers":[
        {
            "category":"Building & Trades",
            "subcategory":"Construction",
            "type":"Services"
        }
    ],
    "sg:phone":"+61 2 4392 3667",
    "sg:postcode":"2259",
    "sg:province":"NSW",
    "sg:tags":[
        "contractor"
    ],
    "wof:name":"Long Homes",
    "wof:placetype":"venue"
},
  "geometry": {"coordinates":[151.47494506800001,-33.2558822632],"type":"Point"}
}