{
  "type": "Feature",
  "properties": {
    "addr:full":"Southwell Primary School 26 Grandpre Crs Hamilton Hill WA 6163",
    "addr:housenumber":"26",
    "addr:postcode":"6163",
    "addr:street":"Grandpre Crs",
    "iso:country":"AU",
    "sg:address":"Southwell Primary School 26 Grandpre Crs",
    "sg:city":"Hamilton Hill",
    "sg:classifiers":[
        {
            "category":"Education",
            "subcategory":"School",
            "type":"Public Place"
        }
    ],
    "sg:phone":"+61 8 9418 1622",
    "sg:postcode":"6163",
    "sg:province":"WA",
    "sg:tags":[
        "state",
        "except",
        "nsw"
    ],
    "wof:name":"Schools Government (Public)",
    "wof:placetype":"venue"
},
  "geometry": {"coordinates":[115.77831999999999,-32.080891],"type":"Point"}
}