{
  "type": "Feature",
  "properties": {
    "iso:country":"AU",
    "sg:address":"14 Enterprise St",
    "sg:city":"Maryborough",
    "sg:classifiers":[
        {
            "category":"Manufacturing",
            "subcategory":"Glass & Minerals",
            "type":"Manufacturing & Wholesale Goods"
        }
    ],
    "sg:phone":"+61 7 4123 2122",
    "sg:postcode":"4650",
    "sg:province":"QLD",
    "sg:tags":[
        "bending",
        "tube"
    ],
    "wof:name":"Rotech Industries Pty",
    "wof:placetype":"venue"
},
  "geometry": {"coordinates":[152.664627,-25.491184],"type":"Point"}
}