{
  "type": "Feature",
  "properties": {
    "iso:country":"AU",
    "sg:address":"Hursley Rd",
    "sg:city":"Wauchope",
    "sg:classifiers":[
        {
            "category":"Farming",
            "subcategory":"Farm",
            "type":"Manufacturing & Wholesale Goods"
        }
    ],
    "sg:phone":"+61 2 6585 9208",
    "sg:postcode":"2446",
    "sg:province":"NSW",
    "sg:tags":[
        "farmer"
    ],
    "wof:name":"Avery John & Carole",
    "wof:placetype":"venue"
},
  "geometry": {"coordinates":[152.755264,-31.418484],"type":"Point"}
}