{
  "type": "Feature",
  "properties": {
    "addr:full":"Unit 5/ 3 Linton Ave Moe VIC 3825",
    "addr:housenumber":"3",
    "addr:postcode":"3825",
    "addr:street":"Linton Ave",
    "iso:country":"AU",
    "sg:address":"Unit 5/ 3 Linton Ave",
    "sg:city":"Moe",
    "sg:classifiers":[
        {
            "category":"Personal",
            "subcategory":"Massage",
            "type":"Services"
        }
    ],
    "sg:phone":"+61 3 5127 7995",
    "sg:postcode":"3825",
    "sg:province":"VIC",
    "sg:tags":[
        "therapy"
    ],
    "wof:name":"Teresa Mullins",
    "wof:placetype":"venue"
},
  "geometry": {"coordinates":[146.263793945,-38.1774902344],"type":"Point"}
}