{
  "type": "Feature",
  "properties": {
    "addr:full":"29 Hammond Rd Dandenong VIC 3175",
    "addr:housenumber":"29",
    "addr:postcode":"3175",
    "addr:street":"Hammond Rd",
    "iso:country":"AU",
    "sg:address":"29 Hammond Rd",
    "sg:city":"Dandenong",
    "sg:classifiers":[
        {
            "category":"Retail",
            "subcategory":"Auto Repair",
            "type":"Services"
        }
    ],
    "sg:phone":"+61 3 9792 9088",
    "sg:postcode":"3175",
    "sg:province":"VIC",
    "sg:tags":[
        "repairer",
        "motor",
        "engineer"
    ],
    "wof:name":"Barabasz J Motors",
    "wof:placetype":"venue"
},
  "geometry": {"coordinates":[145.21005249000001,-37.9931488037],"type":"Point"}
}