{
  "type": "Feature",
  "properties": {
    "addr:full":"12 Basalt St Geebung QLD 4034",
    "addr:housenumber":"12",
    "addr:postcode":"4034",
    "addr:street":"Basalt St",
    "iso:country":"AU",
    "sg:address":"12 Basalt St",
    "sg:city":"Geebung",
    "sg:classifiers":[
        {
            "category":"Wholesale",
            "subcategory":"Furniture",
            "type":"Manufacturing & Wholesale Goods"
        }
    ],
    "sg:phone":"+61 7 3865 3922",
    "sg:postcode":"4034",
    "sg:province":"QLD",
    "sg:tags":[
        "wholesaler",
        "mfrs"
    ],
    "wof:name":"Statewide Commercial Furniture",
    "wof:placetype":"venue"
},
  "geometry": {"coordinates":[153.05029300000001,-27.364899],"type":"Point"}
}