{
  "type": "Feature",
  "properties": {
    "addr:full":"Shop 2/ 183 Coogee Bay Rd Coogee NSW 2034",
    "addr:housenumber":"shop 2 / 183",
    "addr:postcode":"2034",
    "addr:street":"Coogee Bay Rd",
    "iso:country":"AU",
    "sg:address":"Shop 2/ 183 Coogee Bay Rd",
    "sg:city":"Coogee",
    "sg:classifiers":[
        {
            "category":"Government",
            "subcategory":"Customs House",
            "type":"Public Place"
        }
    ],
    "sg:phone":"+61 2 9665 0111",
    "sg:postcode":"2034",
    "sg:province":"NSW",
    "sg:tags":[
        "title",
        "management",
        "stratum"
    ],
    "wof:name":"Lea Real Estate Pty Ltd",
    "wof:placetype":"venue"
},
  "geometry": {"coordinates":[151.25364685100001,-33.9204597473],"type":"Point"}
}