{
  "type": "Feature",
  "properties": {
    "addr:full":"33 Gladstone St Moonee Ponds VIC 3039",
    "addr:housenumber":"33",
    "addr:postcode":"3039",
    "addr:street":"Gladstone St",
    "iso:country":"AU",
    "sg:address":"33 Gladstone St",
    "sg:city":"Moonee Ponds",
    "sg:classifiers":[
        {
            "category":"Health Services",
            "subcategory":"Health Practitioner",
            "type":"Services"
        }
    ],
    "sg:phone":"+61 3 9372 9511",
    "sg:postcode":"3039",
    "sg:province":"VIC",
    "sg:tags":[
        "osteopath"
    ],
    "wof:name":"Inner City Osteopathy",
    "wof:placetype":"venue"
},
  "geometry": {"coordinates":[144.92086800000001,-37.768616],"type":"Point"}
}