{
  "type": "Feature",
  "properties": {
    "iso:country":"AU",
    "sg:address":"121 Nelson St",
    "sg:city":"Nhill",
    "sg:classifiers":[
        {
            "category":"Retail",
            "subcategory":"Funeral Services",
            "type":"Services"
        }
    ],
    "sg:phone":"+61 3 5391 3280",
    "sg:postcode":"3418",
    "sg:province":"VIC",
    "sg:tags":[
        "director"
    ],
    "wof:name":"Nhill & District Funerals",
    "wof:placetype":"venue"
},
  "geometry": {"coordinates":[141.648345947,-36.3330688477],"type":"Point"}
}