{
  "type": "Feature",
  "properties": {
    "addr:full":"67a Whyte St Coleraine VIC 3315",
    "addr:housenumber":"67a",
    "addr:postcode":"3315",
    "addr:street":"Whyte St",
    "iso:country":"AU",
    "sg:address":"67a Whyte St",
    "sg:city":"Coleraine",
    "sg:classifiers":[
        {
            "category":"Deli",
            "type":"Food & Drink"
        }
    ],
    "sg:phone":"+61 3 5575 2186",
    "sg:postcode":"3315",
    "sg:province":"VIC",
    "sg:tags":[
        "delicatessen"
    ],
    "wof:name":"Youl R M & A E",
    "wof:placetype":"venue"
},
  "geometry": {"coordinates":[141.69236755399999,-37.5983810425],"type":"Point"}
}