{
  "type": "Feature",
  "properties": {
    "addr:full":"1379 Malvern Rd Malvern VIC 3144",
    "addr:housenumber":"1379",
    "addr:postcode":"3144",
    "addr:street":"Malvern Rd",
    "iso:country":"AU",
    "sg:address":"1379 Malvern Rd",
    "sg:city":"Malvern",
    "sg:classifiers":[
        {
            "category":"Manufacturing",
            "subcategory":"Metals",
            "type":"Manufacturing & Wholesale Goods"
        }
    ],
    "sg:phone":"+61 3 9521 2386",
    "sg:postcode":"3144",
    "sg:province":"VIC",
    "sg:tags":[
        "leaf",
        "gold"
    ],
    "wof:name":"Meirelles A M",
    "wof:placetype":"venue"
},
  "geometry": {"coordinates":[145.04017639200001,-37.8528213501],"type":"Point"}
}