{
  "type": "Feature",
  "properties": {
    "addr:full":"Wyong Golf Club Pacific Hwy Wyong NSW 2259",
    "addr:postcode":"2259",
    "addr:street":"Pacific Hwy",
    "iso:country":"AU",
    "sg:address":"Wyong Golf Club Pacific Hwy",
    "sg:city":"Wyong",
    "sg:classifiers":[
        {
            "category":"Restaurant",
            "type":"Food & Drink"
        }
    ],
    "sg:phone":"+61 2 4352 1999",
    "sg:postcode":"2259",
    "sg:province":"NSW",
    "wof:name":"Chefs Table",
    "wof:placetype":"venue"
},
  "geometry": {"coordinates":[151.425537109,-33.2829093933],"type":"Point"}
}