{
  "type": "Feature",
  "properties": {
    "addr:full":"53 Hedges Ave Mermaid Beach QLD 4218",
    "addr:housenumber":"53",
    "addr:postcode":"4218",
    "addr:street":"Hedges Ave",
    "iso:country":"AU",
    "sg:address":"53 Hedges Ave",
    "sg:city":"Mermaid Beach",
    "sg:classifiers":[
        {
            "category":"Banks & Credit Unions",
            "subcategory":"Investment Brokerage",
            "type":"Services"
        }
    ],
    "sg:phone":"+61 7 5526 0918",
    "sg:postcode":"4218",
    "sg:province":"QLD",
    "wof:name":"McNiven & Co Pty Ltd",
    "wof:placetype":"venue"
},
  "geometry": {"coordinates":[153.439086914,-28.0487537384],"type":"Point"}
}