{
  "type": "Feature",
  "properties": {
    "iso:country":"AU",
    "sg:address":"92 Munro St",
    "sg:city":"Ascot Vale",
    "sg:classifiers":[
        {
            "category":"Real Estate",
            "subcategory":"Architect",
            "type":"Services"
        }
    ],
    "sg:phone":"+61 3 9326 2554",
    "sg:postcode":"3032",
    "sg:province":"VIC",
    "wof:name":"Gasparetto Nadia",
    "wof:placetype":"venue"
},
  "geometry": {"coordinates":[144.910339,-37.77533],"type":"Point"}
}