{
  "type": "Feature",
  "properties": {
    "iso:country":"AU",
    "sg:address":"33 Spence St",
    "sg:city":"Cairns",
    "sg:classifiers":[
        {
            "category":"Retail",
            "subcategory":"Event Space",
            "type":"Services"
        }
    ],
    "sg:phone":"+61 7 4041 2533",
    "sg:postcode":"4870",
    "sg:province":"QLD",
    "sg:tags":[
        "function",
        "organiser"
    ],
    "wof:name":"Chris Cameron Group",
    "wof:placetype":"venue"
},
  "geometry": {"coordinates":[145.777053833,-16.924161911],"type":"Point"}
}