{
  "type": "Feature",
  "properties": {
    "iso:country":"AU",
    "sg:address":"105 Malop St",
    "sg:city":"Geelong",
    "sg:classifiers":[
        {
            "category":"Shopping",
            "subcategory":"Department Store",
            "type":"Retail Goods"
        }
    ],
    "sg:phone":"+61 3 5227 6555",
    "sg:postcode":"3220",
    "sg:province":"VIC",
    "wof:name":"Myer Geelong",
    "wof:placetype":"venue"
},
  "geometry": {"coordinates":[144.362503,-38.147533],"type":"Point"}
}