{
  "type": "Feature",
  "properties": {
    "addr:full":"101 Pitt Town Rd Kenthurst NSW 2156",
    "addr:housenumber":"101",
    "addr:postcode":"2156",
    "addr:street":"Pitt Town Rd",
    "iso:country":"AU",
    "sg:address":"101 Pitt Town Rd",
    "sg:city":"Kenthurst",
    "sg:classifiers":[
        {
            "category":"Building & Trades",
            "subcategory":"Construction",
            "type":"Services"
        }
    ],
    "sg:phone":"+61 418 113 484",
    "sg:postcode":"2156",
    "sg:province":"NSW",
    "sg:tags":[
        "fencing",
        "contractor"
    ],
    "wof:name":"Moore Joseph G",
    "wof:placetype":"venue"
},
  "geometry": {"coordinates":[150.976486206,-33.6546669006],"type":"Point"}
}