{
  "type": "Feature",
  "properties": {
    "addr:full":"95 Balo St Moree NSW 2400",
    "addr:housenumber":"95",
    "addr:postcode":"2400",
    "addr:street":"Balo St",
    "iso:country":"AU",
    "sg:address":"95 Balo St",
    "sg:city":"Moree",
    "sg:classifiers":[
        {
            "category":"Personal",
            "subcategory":"Beauty Salon",
            "type":"Services"
        }
    ],
    "sg:phone":"+61 2 6751 1199",
    "sg:postcode":"2400",
    "sg:province":"NSW",
    "sg:tags":[
        "hairdresser"
    ],
    "wof:name":"Trims Hair Design Moree",
    "wof:placetype":"venue"
},
  "geometry": {"coordinates":[149.84175109899999,-29.4649181366],"type":"Point"}
}