{
  "type": "Feature",
  "properties": {
    "iso:country":"AU",
    "sg:address":"28 Benison Rd",
    "sg:city":"Winnellie",
    "sg:classifiers":[
        {
            "category":"Fast Food",
            "type":"Food & Drink"
        }
    ],
    "sg:phone":"+61 8 8947 1593",
    "sg:postcode":"0820",
    "sg:province":"NT",
    "sg:tags":[
        "away",
        "take"
    ],
    "wof:name":"Lunch Heaven Take Away",
    "wof:placetype":"venue"
},
  "geometry": {"coordinates":[130.86416625999999,-12.4305458069],"type":"Point"}
}