{
  "type": "Feature",
  "properties": {
    "iso:country":"AU",
    "sg:address":"51 - 55 Stephenson St",
    "sg:city":"Richmond",
    "sg:classifiers":[
        {
            "category":"Shopping",
            "subcategory":"Clothing, Apparel, & Fashions",
            "type":"Retail Goods"
        }
    ],
    "sg:phone":"+61 3 9427 0044",
    "sg:postcode":"3121",
    "sg:province":"VIC",
    "sg:tags":[
        "wholesaler",
        "children's",
        "mfrs",
        "wear"
    ],
    "wof:name":"Chino Kids Pty Ltd",
    "wof:placetype":"venue"
},
  "geometry": {"coordinates":[144.99369812,-37.8287010193],"type":"Point"}
}