{
  "type": "Feature",
  "properties": {
    "iso:country":"AU",
    "sg:address":"10609 New England Hwy",
    "sg:city":"Highfields",
    "sg:classifiers":[
        {
            "category":"Fast Food",
            "type":"Food & Drink"
        }
    ],
    "sg:phone":"+61 7 4698 7999",
    "sg:postcode":"4352",
    "sg:province":"QLD",
    "sg:tags":[
        "away",
        "take"
    ],
    "wof:name":"Rooster On The Run",
    "wof:placetype":"venue"
},
  "geometry": {"coordinates":[151.95768699999999,-27.460949],"type":"Point"}
}