{
  "type": "Feature",
  "properties": {
    "iso:country":"AU",
    "sg:address":"6 Reid St",
    "sg:city":"Lindfield",
    "sg:classifiers":[
        {
            "category":"Professional",
            "subcategory":"Management & Consulting",
            "type":"Services"
        }
    ],
    "sg:phone":"+61 2 8923 2619",
    "sg:postcode":"2070",
    "sg:province":"NSW",
    "sg:tags":[
        "consultant"
    ],
    "wof:name":"PacAlliance (Australia) Pty Ltd",
    "wof:placetype":"venue"
},
  "geometry": {"coordinates":[151.16778564399999,-33.771812439],"type":"Point"}
}