{
  "type": "Feature",
  "properties": {
    "addr:full":"Queen St St Marys NSW 2760",
    "addr:postcode":"2760",
    "addr:street":"Queen St",
    "iso:country":"AU",
    "sg:address":"Queen St",
    "sg:city":"St Marys",
    "sg:classifiers":[
        {
            "category":"Health Services",
            "subcategory":"Doctor",
            "type":"Services"
        }
    ],
    "sg:phone":"+61 2 9623 4288",
    "sg:postcode":"2760",
    "sg:province":"NSW",
    "sg:tags":[
        "medical",
        "practitioner"
    ],
    "wof:name":"Lui Anita",
    "wof:placetype":"venue"
},
  "geometry": {"coordinates":[150.77482605,-33.763671875],"type":"Point"}
}