{
  "type": "Feature",
  "properties": {
    "addr:full":"Albert St Footscray VIC 3011",
    "addr:postcode":"3011",
    "addr:street":"Albert St",
    "iso:country":"AU",
    "sg:address":"Albert St",
    "sg:city":"Footscray",
    "sg:classifiers":[
        {
            "category":"Personal",
            "subcategory":"Beauty Salon",
            "type":"Services"
        }
    ],
    "sg:phone":"+61 3 9687 3053",
    "sg:postcode":"3011",
    "sg:province":"VIC",
    "sg:tags":[
        "hairdresser"
    ],
    "wof:name":"Jenny Hair & Beauty Salon",
    "wof:placetype":"venue"
},
  "geometry": {"coordinates":[144.90626525900001,-37.8056678772],"type":"Point"}
}