{
  "type": "Feature",
  "properties": {
    "addr:full":"316 Norfolk St Albury NSW 2640",
    "addr:housenumber":"316",
    "addr:postcode":"2640",
    "addr:street":"Norfolk St",
    "iso:country":"AU",
    "sg:address":"316 Norfolk St",
    "sg:city":"Albury",
    "sg:classifiers":[
        {
            "category":"Organizations",
            "subcategory":"Professional Association",
            "type":"Services"
        }
    ],
    "sg:phone":"+61 2 6021 5110",
    "sg:postcode":"2640",
    "sg:province":"NSW",
    "sg:tags":[
        "web",
        "internet"
    ],
    "wof:name":"Ian Cossor Design",
    "wof:placetype":"venue"
},
  "geometry": {"coordinates":[146.93035888700001,-36.0842514038],"type":"Point"}
}