{
  "type": "Feature",
  "properties": {
    "addr:full":"Ste 2/ 14 Albert St Blackburn VIC 3130",
    "addr:housenumber":"14",
    "addr:postcode":"3130",
    "addr:street":"Albert St",
    "iso:country":"AU",
    "sg:address":"Ste 2/ 14 Albert St",
    "sg:city":"Blackburn",
    "sg:classifiers":[
        {
            "category":"Real Estate",
            "subcategory":"Real Estate Agent",
            "type":"Services"
        }
    ],
    "sg:phone":"+61 3 8878 9999",
    "sg:postcode":"3130",
    "sg:province":"VIC",
    "wof:name":"Thompson May Commercial",
    "wof:placetype":"venue"
},
  "geometry": {"coordinates":[145.152435303,-37.8189888],"type":"Point"}
}