{
  "type": "Feature",
  "properties": {
    "addr:full":"Cnr Prospect Rd & Florence St Blair Athol SA 5084",
    "addr:postcode":"5084",
    "addr:street":"Cnr Prospect Rd & Florence St",
    "iso:country":"AU",
    "sg:address":"Cnr Prospect Rd & Florence St",
    "sg:city":"Blair Athol",
    "sg:classifiers":[
        {
            "category":"Food & Beverages",
            "subcategory":"Supermarket",
            "type":"Retail Goods"
        }
    ],
    "sg:phone":"+61 8 8262 2336",
    "sg:postcode":"5084",
    "sg:province":"SA",
    "sg:tags":[
        "grocery",
        "store"
    ],
    "wof:name":"Bi-Lo",
    "wof:placetype":"venue"
},
  "geometry": {"coordinates":[138.59213256800001,-34.8592033386],"type":"Point"}
}