{
  "type": "Feature",
  "properties": {
    "iso:country":"AU",
    "sg:address":"79 Lord St",
    "sg:city":"Sandy Bay",
    "sg:classifiers":[
        {
            "category":"Building & Trades",
            "subcategory":"Construction",
            "type":"Services"
        }
    ],
    "sg:phone":"+61 3 6223 2293",
    "sg:postcode":"7005",
    "sg:province":"TAS",
    "sg:tags":[
        "renovation",
        "alterations",
        "extension",
        "contractor"
    ],
    "wof:name":"Hasell Home Maintenance Pty Ltd",
    "wof:placetype":"venue"
},
  "geometry": {"coordinates":[147.32043457,-42.9000968933],"type":"Point"}
}