{
  "type": "Feature",
  "properties": {
    "addr:full":"804 South Rd Penguin TAS 7316",
    "addr:housenumber":"804",
    "addr:postcode":"7316",
    "addr:street":"South Rd",
    "iso:country":"AU",
    "sg:address":"804 South Rd",
    "sg:city":"Penguin",
    "sg:classifiers":[
        {
            "category":"Manufacturing",
            "subcategory":"Lumber",
            "type":"Manufacturing & Wholesale Goods"
        }
    ],
    "sg:phone":"+61 3 6437 0700",
    "sg:postcode":"7316",
    "sg:province":"TAS",
    "sg:tags":[
        "sawmillers"
    ],
    "wof:name":"G & W Harvesting",
    "wof:placetype":"venue"
},
  "geometry": {"coordinates":[146.08702087399999,-41.1306724548],"type":"Point"}
}