{
  "type": "Feature",
  "properties": {
    "addr:full":"40 Thompson St Bowen Hills QLD 4006",
    "addr:housenumber":"40",
    "addr:postcode":"4006",
    "addr:street":"Thompson St",
    "iso:country":"AU",
    "sg:address":"40 Thompson St",
    "sg:city":"Bowen Hills",
    "sg:classifiers":[
        {
            "category":"Professional",
            "subcategory":"Engineering",
            "type":"Services"
        }
    ],
    "sg:phone":"+61 7 3257 4711",
    "sg:postcode":"4006",
    "sg:province":"QLD",
    "sg:tags":[
        "consulting",
        "engineer"
    ],
    "wof:name":"Pace Consulting Engineers (Qld) Pty Ltd",
    "wof:placetype":"venue"
},
  "geometry": {"coordinates":[153.040527344,-27.4401283264],"type":"Point"}
}