{
  "type": "Feature",
  "properties": {
    "iso:country":"AU",
    "sg:address":"Cnr Simmons St & Selems Pde",
    "sg:city":"Revesby",
    "sg:classifiers":[
        {
            "category":"Health Services",
            "subcategory":"Dentist",
            "type":"Services"
        }
    ],
    "sg:phone":"+61 2 9773 9873",
    "sg:postcode":"2212",
    "sg:province":"NSW",
    "wof:name":"Doan Thuc T",
    "wof:placetype":"venue"
},
  "geometry": {"coordinates":[151.015671,-33.951523],"type":"Point"}
}