{
  "type": "Feature",
  "properties": {
    "addr:full":"37 Mclaughlin Drv Blacks Beach QLD 4740",
    "addr:housenumber":"37",
    "addr:postcode":"4740",
    "addr:street":"Mclaughlin Drv",
    "iso:country":"AU",
    "sg:address":"37 Mclaughlin Drv",
    "sg:city":"Blacks Beach",
    "sg:classifiers":[
        {
            "category":"Retail",
            "subcategory":"Auto Rental",
            "type":"Services"
        }
    ],
    "sg:phone":"+61 7 4954 9610",
    "sg:postcode":"4740",
    "sg:province":"QLD",
    "sg:tags":[
        "chauffeur",
        "car",
        "hire",
        "driven",
        "limousine"
    ],
    "wof:name":"Up And Rolling Limousines.",
    "wof:placetype":"venue"
},
  "geometry": {"coordinates":[149.181152,-21.052954],"type":"Point"}
}