{
  "type": "Feature",
  "properties": {
    "addr:full":"301 Hebbard St Broken Hill NSW 2880",
    "addr:housenumber":"301",
    "addr:postcode":"2880",
    "addr:street":"Hebbard St",
    "iso:country":"AU",
    "sg:address":"301 Hebbard St",
    "sg:city":"Broken Hill",
    "sg:classifiers":[
        {
            "category":"Professional",
            "subcategory":"Detective & Security Services",
            "type":"Services"
        }
    ],
    "sg:phone":"+61 8 8087 2617",
    "sg:postcode":"2880",
    "sg:province":"NSW",
    "sg:tags":[
        "consultant",
        "system"
    ],
    "wof:name":"Intruder Alarm Services of Broken Hill",
    "wof:placetype":"venue"
},
  "geometry": {"coordinates":[141.46583557100001,-31.9749526978],"type":"Point"}
}