{
  "type": "Feature",
  "properties": {
    "iso:country":"AU",
    "sg:address":"10 Day Rd",
    "sg:city":"Rockingham",
    "sg:classifiers":[
        {
            "category":"Autos & Motor Vehicles",
            "subcategory":"Automobile Sales",
            "type":"Retail Goods"
        }
    ],
    "sg:phone":"+61 8 9592 2844",
    "sg:postcode":"6168",
    "sg:province":"WA",
    "sg:tags":[
        "car",
        "used"
    ],
    "wof:name":"Casino Motors",
    "wof:placetype":"venue"
},
  "geometry": {"coordinates":[115.774101,-32.275612],"type":"Point"}
}