{
  "type": "Feature",
  "properties": {
    "iso:country":"AU",
    "sg:address":"1 Roberts St",
    "sg:city":"Kalgoorlie",
    "sg:classifiers":[
        {
            "category":"Retail",
            "subcategory":"Auto Repair",
            "type":"Services"
        }
    ],
    "sg:phone":"+61 418 216 087",
    "sg:postcode":"6430",
    "sg:province":"WA",
    "sg:tags":[
        "body",
        "motor",
        "trimmer"
    ],
    "wof:name":"Goldfields Upholstery Services",
    "wof:placetype":"venue"
},
  "geometry": {"coordinates":[121.472816467,-30.7581653595],"type":"Point"}
}