{
  "type": "Feature",
  "properties": {
    "addr:full":"381 High St Penrith NSW 2751",
    "addr:housenumber":"381",
    "addr:postcode":"2751",
    "addr:street":"High St",
    "iso:country":"AU",
    "sg:address":"381 High St",
    "sg:city":"Penrith",
    "sg:classifiers":[
        {
            "category":"Health Services",
            "subcategory":"Optometrist",
            "type":"Services"
        }
    ],
    "sg:phone":"+61 2 4721 5297",
    "sg:postcode":"2751",
    "sg:province":"NSW",
    "wof:name":"Eyecare Plus Optometrists",
    "wof:placetype":"venue"
},
  "geometry": {"coordinates":[150.91557312,-33.8948440552],"type":"Point"}
}