{
  "type": "Feature",
  "properties": {
    "addr:full":"306 Olsen Ave Parkwood QLD 4214",
    "addr:housenumber":"306",
    "addr:postcode":"4214",
    "addr:street":"Olsen Ave",
    "iso:country":"AU",
    "sg:address":"306 Olsen Ave",
    "sg:city":"Parkwood",
    "sg:classifiers":[
        {
            "category":"Health Services",
            "subcategory":"Doctor",
            "type":"Services"
        }
    ],
    "sg:phone":"+61 7 5571 7233",
    "sg:postcode":"4214",
    "sg:province":"QLD",
    "sg:tags":[
        "medical",
        "practitioner"
    ],
    "wof:name":"Graeme Doherty",
    "wof:placetype":"venue"
},
  "geometry": {"coordinates":[153.38081359899999,-27.9569244385],"type":"Point"}
}