{
  "type": "Feature",
  "properties": {
    "addr:full":"8 Tandara St Mt Gambier SA 5290",
    "addr:housenumber":"8",
    "addr:postcode":"5290",
    "addr:street":"Tandara St",
    "iso:country":"AU",
    "sg:address":"8 Tandara St",
    "sg:city":"Mt Gambier",
    "sg:classifiers":[
        {
            "category":"Farming",
            "subcategory":"Farm & Veterinary Services",
            "type":"Manufacturing & Wholesale Goods"
        }
    ],
    "sg:phone":"+61 8 8725 7477",
    "sg:postcode":"5290",
    "sg:province":"SA",
    "sg:tags":[
        "seedsman"
    ],
    "wof:name":"Gambier Seeds",
    "wof:placetype":"venue"
},
  "geometry": {"coordinates":[140.78628499999999,-37.833809],"type":"Point"}
}