{
  "type": "Feature",
  "properties": {
    "addr:full":"38 Hargreaves Drv Taree NSW 2430",
    "addr:housenumber":"38",
    "addr:postcode":"2430",
    "addr:street":"Hargreaves Drv",
    "iso:country":"AU",
    "sg:address":"38 Hargreaves Drv",
    "sg:city":"Taree",
    "sg:classifiers":[
        {
            "category":"Retail",
            "subcategory":"Auto Repair",
            "type":"Services"
        }
    ],
    "sg:phone":"+61 2 6552 5856",
    "sg:postcode":"2430",
    "sg:province":"NSW",
    "sg:tags":[
        "body",
        "builder",
        "motor"
    ],
    "sg:website":"http://www.thommostrucks.com.au",
    "wof:name":"Thompson (Taree) Motor Body Builders Pty Ltd",
    "wof:placetype":"venue"
},
  "geometry": {"coordinates":[152.42138700000001,-31.879934],"type":"Point"}
}