{
  "type": "Feature",
  "properties": {
    "addr:full":"17 Orchard Rd Coconut Grove NT 0810",
    "addr:housenumber":"17",
    "addr:postcode":"0810",
    "addr:street":"Orchard Rd",
    "iso:country":"AU",
    "sg:address":"17 Orchard Rd",
    "sg:city":"Coconut Grove",
    "sg:classifiers":[
        {
            "category":"Personal",
            "subcategory":"Beauty Salon",
            "type":"Services"
        }
    ],
    "sg:phone":"+61 8 8948 2435",
    "sg:postcode":"0810",
    "sg:province":"NT",
    "sg:tags":[
        "hairdresser"
    ],
    "wof:name":"The Cottage Hairdressing",
    "wof:placetype":"venue"
},
  "geometry": {"coordinates":[130.84837341299999,-12.3966665268],"type":"Point"}
}