{
  "type": "Feature",
  "properties": {
    "addr:full":"8 Nicholas Drv Dandenong VIC 3175",
    "addr:housenumber":"8",
    "addr:postcode":"3175",
    "addr:street":"Nicholas Drv",
    "iso:country":"AU",
    "sg:address":"8 Nicholas Drv",
    "sg:city":"Dandenong",
    "sg:classifiers":[
        {
            "category":"Retail",
            "subcategory":"Storage",
            "type":"Services"
        }
    ],
    "sg:phone":"+61 3 9706 5544",
    "sg:postcode":"3175",
    "sg:province":"VIC",
    "sg:tags":[
        "removal",
        "furniture"
    ],
    "wof:name":"Blue Lion Moving & Storage",
    "wof:placetype":"venue"
},
  "geometry": {"coordinates":[145.20709228499999,-38.0350875854],"type":"Point"}
}