{
  "type": "Feature",
  "properties": {
    "addr:full":"5 Abrams St Balcatta WA 6021",
    "addr:housenumber":"5",
    "addr:postcode":"6021",
    "addr:street":"Abrams St",
    "iso:country":"AU",
    "sg:address":"5 Abrams St",
    "sg:city":"Balcatta",
    "sg:classifiers":[
        {
            "category":"Mining & Drilling",
            "type":"Manufacturing & Wholesale Goods"
        }
    ],
    "sg:phone":"+61 8 9344 5655",
    "sg:postcode":"6021",
    "sg:province":"WA",
    "sg:tags":[
        "equipment",
        "quarrying",
        "supply"
    ],
    "wof:name":"Dysons Packaging Pty Ltd",
    "wof:placetype":"venue"
},
  "geometry": {"coordinates":[115.805351257,-31.8649291992],"type":"Point"}
}