{
  "type": "Feature",
  "properties": {
    "addr:full":"108- 110 Northgate Drv Thomastown VIC 3074",
    "addr:housenumber":"110",
    "addr:postcode":"3074",
    "addr:street":"Northgate Drv",
    "iso:country":"AU",
    "sg:address":"108- 110 Northgate Drv",
    "sg:city":"Thomastown",
    "sg:classifiers":[
        {
            "category":"Home & Garden",
            "subcategory":"Hardware",
            "type":"Retail Goods"
        }
    ],
    "sg:phone":"+61 3 9465 8022",
    "sg:postcode":"3074",
    "sg:province":"VIC",
    "sg:tags":[
        "part",
        "air conditioning"
    ],
    "wof:name":"Polyaire Pty Ltd",
    "wof:placetype":"venue"
},
  "geometry": {"coordinates":[145.03106689399999,-37.6882209778],"type":"Point"}
}