{
  "type": "Feature",
  "properties": {
    "iso:country":"AU",
    "sg:address":"274 High St",
    "sg:city":"Windsor",
    "sg:classifiers":[
        {
            "category":"Organizations",
            "subcategory":"Community Association",
            "type":"Services"
        }
    ],
    "sg:phone":"+61 3 9521 5666",
    "sg:postcode":"3181",
    "sg:province":"VIC",
    "sg:tags":[
        "organisation",
        "family",
        "welfare"
    ],
    "wof:name":"Family Resource Centre",
    "wof:placetype":"venue"
},
  "geometry": {"coordinates":[144.9972229,-37.8524894714],"type":"Point"}
}