{
  "type": "Feature",
  "properties": {
    "addr:full":"380 Midland Hwy Brighton TAS 7030",
    "addr:housenumber":"380",
    "addr:postcode":"7030",
    "addr:street":"Midland Hwy",
    "iso:country":"AU",
    "sg:address":"380 Midland Hwy",
    "sg:city":"Brighton",
    "sg:classifiers":[
        {
            "category":"Wholesale",
            "subcategory":"Auto Parts",
            "type":"Manufacturing & Wholesale Goods"
        }
    ],
    "sg:phone":"+61 3 6263 3886",
    "sg:postcode":"7030",
    "sg:province":"TAS",
    "sg:tags":[
        "recyclers"
    ],
    "wof:name":"Delta Auto Recyclers",
    "wof:placetype":"venue"
},
  "geometry": {"coordinates":[147.25123596200001,-42.6994590759],"type":"Point"}
}