{
  "type": "Feature",
  "properties": {
    "iso:country":"AU",
    "sg:address":"1st Floor, 281 King St",
    "sg:city":"Newtown",
    "sg:classifiers":[
        {
            "category":"Health Services",
            "subcategory":"Chiropractor",
            "type":"Services"
        }
    ],
    "sg:phone":"+61 2 9550 6634",
    "sg:postcode":"2042",
    "sg:province":"NSW",
    "wof:name":"Fish Robert",
    "wof:placetype":"venue"
},
  "geometry": {"coordinates":[151.179779,-33.896427],"type":"Point"}
}