{
  "type": "Feature",
  "properties": {
    "iso:country":"AU",
    "sg:address":"Factory 12 5 Edelmaier St",
    "sg:city":"Bayswater",
    "sg:classifiers":[
        {
            "category":"Retail",
            "subcategory":"Auto Repair",
            "type":"Services"
        }
    ],
    "sg:phone":"+61 3 9720 0244",
    "sg:postcode":"3153",
    "sg:province":"VIC",
    "sg:tags":[
        "beater",
        "painter",
        "panel"
    ],
    "wof:name":"AMMI Automotive Services",
    "wof:placetype":"venue"
},
  "geometry": {"coordinates":[145.27464294399999,-37.8467407227],"type":"Point"}
}