{
  "type": "Feature",
  "properties": {
    "addr:full":"25 Glenelg St South Brisbane QLD 4101",
    "addr:housenumber":"25",
    "addr:postcode":"4101",
    "addr:street":"Glenelg St",
    "iso:country":"AU",
    "sg:address":"25 Glenelg St",
    "sg:city":"South Brisbane",
    "sg:classifiers":[
        {
            "category":"Building & Trades",
            "subcategory":"Construction",
            "type":"Services"
        }
    ],
    "sg:phone":"+61 7 3844 7051",
    "sg:postcode":"4101",
    "sg:province":"QLD",
    "sg:tags":[
        "concrete",
        "treatment",
        "repair"
    ],
    "wof:name":"Mainline Waterproofing QLD Pty Ltd",
    "wof:placetype":"venue"
},
  "geometry": {"coordinates":[153.01841735799999,-27.4785461426],"type":"Point"}
}