{
  "type": "Feature",
  "properties": {
    "addr:full":"91 Ivory Creek Rd Toogoolawah QLD 4313",
    "addr:housenumber":"91",
    "addr:postcode":"4313",
    "addr:street":"Ivory Creek Rd",
    "iso:country":"AU",
    "sg:address":"91 Ivory Creek Rd",
    "sg:city":"Toogoolawah",
    "sg:classifiers":[
        {
            "category":"Organizations",
            "subcategory":"Professional Association",
            "type":"Services"
        }
    ],
    "sg:phone":"+61 7 5423 1336",
    "sg:postcode":"4313",
    "sg:province":"QLD",
    "sg:tags":[
        "rural",
        "organisation",
        "production",
        "primary"
    ],
    "wof:name":"Toogoolawah Show Socy",
    "wof:placetype":"venue"
},
  "geometry": {"coordinates":[152.37762451200001,-27.0841941833],"type":"Point"}
}