{
  "type": "Feature",
  "properties": {
    "addr:full":"Lvl 1/ 160 Cotlew St Ashmore QLD 4214",
    "addr:housenumber":"/ 160",
    "addr:postcode":"4214",
    "addr:street":"Cotlew St",
    "iso:country":"AU",
    "sg:address":"Lvl 1/ 160 Cotlew St",
    "sg:city":"Ashmore",
    "sg:classifiers":[
        {
            "category":"Banks & Credit Unions",
            "subcategory":"Investment Brokerage",
            "type":"Services"
        }
    ],
    "sg:phone":"+61 438 699 667",
    "sg:postcode":"4214",
    "sg:province":"QLD",
    "sg:tags":[
        "finance",
        "broker"
    ],
    "wof:name":"Crediflex Gold Coast Pty Ltd",
    "wof:placetype":"venue"
},
  "geometry": {"coordinates":[153.38392639200001,-27.9867839813],"type":"Point"}
}