{
  "type": "Feature",
  "properties": {
    "addr:full":"2 Pavana Crt Hallett SA 5419",
    "addr:housenumber":"2",
    "addr:postcode":"5419",
    "addr:street":"Pavana Crt",
    "iso:country":"AU",
    "sg:address":"2 Pavana Crt",
    "sg:city":"Hallett",
    "sg:classifiers":[
        {
            "category":"Wholesale",
            "subcategory":"Machinery & Supplies",
            "type":"Manufacturing & Wholesale Goods"
        }
    ],
    "sg:phone":"+61 417 087 998",
    "sg:postcode":"5419",
    "sg:province":"SA",
    "sg:tags":[
        "agricultural"
    ],
    "wof:name":"Silcox Rural Agencies",
    "wof:placetype":"venue"
},
  "geometry": {"coordinates":[138.89068603499999,-33.410949707],"type":"Point"}
}