{
  "type": "Feature",
  "properties": {
    "addr:full":"1 First St Murray Bridge SA 5253",
    "addr:housenumber":"1",
    "addr:postcode":"5253",
    "addr:street":"First St",
    "iso:country":"AU",
    "sg:address":"1 First St",
    "sg:city":"Murray Bridge",
    "sg:classifiers":[
        {
            "category":"Banks & Credit Unions",
            "subcategory":"Financial Services",
            "type":"Services"
        }
    ],
    "sg:phone":"+61 8 8532 1500",
    "sg:postcode":"5253",
    "sg:province":"SA",
    "sg:tags":[
        "loan",
        "finance",
        "mortgage"
    ],
    "wof:name":"Graham Quast Home Loans",
    "wof:placetype":"venue"
},
  "geometry": {"coordinates":[139.27227783199999,-35.1177711487],"type":"Point"}
}