{
  "type": "Feature",
  "properties": {
    "addr:full":"85 Belgravia St Belmont WA 6104",
    "addr:housenumber":"85",
    "addr:postcode":"6104",
    "addr:street":"Belgravia St",
    "iso:country":"AU",
    "sg:address":"85 Belgravia St",
    "sg:city":"Belmont",
    "sg:classifiers":[
        {
            "category":"Professional",
            "type":"Services"
        }
    ],
    "sg:phone":"+61 1300 306 830",
    "sg:postcode":"6104",
    "sg:province":"WA",
    "sg:tags":[
        "control",
        "equipment",
        "traffic"
    ],
    "wof:name":"Workforce International Pty.Ltd.",
    "wof:placetype":"venue"
},
  "geometry": {"coordinates":[115.929710388,-31.9495029449],"type":"Point"}
}