{
  "type": "Feature",
  "properties": {
    "addr:full":"231 Sherbourne Rd Eltham VIC 3095",
    "addr:housenumber":"231",
    "addr:postcode":"3095",
    "addr:street":"Sherbourne Rd",
    "iso:country":"AU",
    "sg:address":"231 Sherbourne Rd",
    "sg:city":"Eltham",
    "sg:classifiers":[
        {
            "category":"Autos & Motor Vehicles",
            "subcategory":"Auto Supplies",
            "type":"Retail Goods"
        }
    ],
    "sg:phone":"+61 3 9431 3011",
    "sg:postcode":"3095",
    "sg:province":"VIC",
    "sg:tags":[
        "wheel",
        "four",
        "equipment",
        "drive",
        "accessory"
    ],
    "wof:name":"Bob Jane T-Marts",
    "wof:placetype":"venue"
},
  "geometry": {"coordinates":[145.13749694800001,-37.7171783447],"type":"Point"}
}