{
  "type": "Feature",
  "properties": {
    "iso:country":"AU",
    "sg:address":"8/ 169 Railway Rd",
    "sg:city":"Gooseberry Hill",
    "sg:classifiers":[
        {
            "category":"Health Services",
            "subcategory":"Dentist",
            "type":"Services"
        }
    ],
    "sg:phone":"+61 8 9257 1885",
    "sg:postcode":"6076",
    "sg:province":"WA",
    "wof:name":"Throssell James",
    "wof:placetype":"venue"
},
  "geometry": {"coordinates":[116.051963806,-31.9578838348],"type":"Point"}
}