{
  "type": "Feature",
  "properties": {
    "addr:full":"120 Taralga Rd Goulburn NSW 2580",
    "addr:housenumber":"120",
    "addr:postcode":"2580",
    "addr:street":"Taralga Rd",
    "iso:country":"AU",
    "sg:address":"120 Taralga Rd",
    "sg:city":"Goulburn",
    "sg:classifiers":[
        {
            "category":"Social Services",
            "subcategory":"Child Care",
            "type":"Services"
        }
    ],
    "sg:phone":"+61 2 4822 1543",
    "sg:postcode":"2580",
    "sg:province":"NSW",
    "wof:name":"Daniel's Den Daycare",
    "wof:placetype":"venue"
},
  "geometry": {"coordinates":[149.74497985799999,-34.7239990234],"type":"Point"}
}