{
  "type": "Feature",
  "properties": {
    "addr:full":"88 Ransworth Rd Hocking WA 6065",
    "addr:housenumber":"88",
    "addr:postcode":"6065",
    "addr:street":"Ransworth Rd",
    "iso:country":"AU",
    "sg:address":"88 Ransworth Rd",
    "sg:city":"Hocking",
    "sg:classifiers":[
        {
            "category":"Building & Trades",
            "subcategory":"Pest Control",
            "type":"Services"
        }
    ],
    "sg:phone":"+61 413 325 770",
    "sg:postcode":"6065",
    "sg:province":"WA",
    "wof:name":"Insight Termite & Pest Management",
    "wof:placetype":"venue"
},
  "geometry": {"coordinates":[115.82141876199999,-31.771194458],"type":"Point"}
}