{
  "type": "Feature",
  "properties": {
    "iso:country":"AU",
    "sg:address":"76 Pirie St",
    "sg:city":"Adelaide",
    "sg:classifiers":[
        {
            "category":"Health Services",
            "subcategory":"Optometrist",
            "type":"Services"
        }
    ],
    "sg:phone":"+61 1300 115 115",
    "sg:postcode":"5000",
    "sg:province":"SA",
    "wof:name":"Johnston Kirsty",
    "wof:placetype":"venue"
},
  "geometry": {"coordinates":[138.60256957999999,-34.9255027771],"type":"Point"}
}