{
  "type": "Feature",
  "properties": {
    "addr:full":"237 Lilyfield Rd Lilyfield NSW 2040",
    "addr:housenumber":"237",
    "addr:postcode":"2040",
    "addr:street":"Lilyfield Rd",
    "iso:country":"AU",
    "sg:address":"237 Lilyfield Rd",
    "sg:city":"Lilyfield",
    "sg:classifiers":[
        {
            "category":"Building & Trades",
            "subcategory":"Construction",
            "type":"Services"
        }
    ],
    "sg:phone":"+61 414 953 724",
    "sg:postcode":"2040",
    "sg:province":"NSW",
    "sg:tags":[
        "joinery"
    ],
    "wof:name":"Balmain Carpentry",
    "wof:placetype":"venue"
},
  "geometry": {"coordinates":[151.15438800000001,-33.873093],"type":"Point"}
}