{
  "type": "Feature",
  "properties": {
    "addr:full":"Shop 1C 24-44 Main St Blacktown NSW 2148",
    "addr:housenumber":"1c 24-44",
    "addr:postcode":"2148",
    "addr:street":"Shop;Main St",
    "iso:country":"AU",
    "sg:address":"Shop 1C 24-44 Main St",
    "sg:city":"Blacktown",
    "sg:classifiers":[
        {
            "category":"Personal",
            "subcategory":"Beauty Salon",
            "type":"Services"
        }
    ],
    "sg:phone":"+61 2 9679 9544",
    "sg:postcode":"2148",
    "sg:province":"NSW",
    "sg:tags":[
        "hairdresser"
    ],
    "wof:name":"Lories Hair & Beauty Salon",
    "wof:placetype":"venue"
},
  "geometry": {"coordinates":[150.908294678,-33.76927948],"type":"Point"}
}