{
  "type": "Feature",
  "properties": {
    "addr:full":"PO Box 739 Bathurst NSW 2795",
    "addr:postcode":"2795",
    "iso:country":"AU",
    "sg:address":"PO Box 739",
    "sg:city":"Bathurst",
    "sg:classifiers":[
        {
            "category":"Utilities",
            "subcategory":"Electric",
            "type":"Services"
        }
    ],
    "sg:phone":"+61 2 6331 2196",
    "sg:postcode":"2795",
    "sg:province":"NSW",
    "sg:tags":[
        "electrical",
        "contractor"
    ],
    "wof:name":"Deehan SM & SJ Electrical",
    "wof:placetype":"venue"
},
  "geometry": {"coordinates":[149.55354309099999,-33.5437316895],"type":"Point"}
}