{
  "type": "Feature",
  "properties": {
    "addr:full":"40 Lanhams Rd Winston Hills NSW 2153",
    "addr:housenumber":"40",
    "addr:postcode":"2153",
    "addr:street":"Lanhams Rd",
    "iso:country":"AU",
    "sg:address":"40 Lanhams Rd",
    "sg:city":"Winston Hills",
    "sg:classifiers":[
        {
            "category":"Professional",
            "subcategory":"Art Services",
            "type":"Services"
        }
    ],
    "sg:phone":"+61 2 9686 6654",
    "sg:postcode":"2153",
    "sg:province":"NSW",
    "sg:tags":[
        "decorator",
        "painter"
    ],
    "wof:name":"Lotus Decor Pty Ltd",
    "wof:placetype":"venue"
},
  "geometry": {"coordinates":[150.97932434099999,-33.7758102417],"type":"Point"}
}