{
  "type": "Feature",
  "properties": {
    "iso:country":"AU",
    "sg:address":"Government Rd",
    "sg:city":"Nelson Bay",
    "sg:classifiers":[
        {
            "category":"Travel",
            "subcategory":"Hotels & Motels",
            "type":"Entertainment"
        }
    ],
    "sg:phone":"+61 2 4981 3393",
    "sg:postcode":"2315",
    "sg:province":"NSW",
    "wof:name":"Central Motel",
    "wof:placetype":"venue"
},
  "geometry": {"coordinates":[152.142426,-32.720539],"type":"Point"}
}