{
  "type": "Feature",
  "properties": {
    "iso:country":"AU",
    "sg:address":"154 Murrah St",
    "sg:city":"Bermagui",
    "sg:classifiers":[
        {
            "category":"Recreation",
            "subcategory":"Boat Charter",
            "type":"Entertainment"
        }
    ],
    "sg:phone":"+61 2 6493 4568",
    "sg:postcode":"2546",
    "sg:province":"NSW",
    "wof:name":"Bill Collector Game Fishing",
    "wof:placetype":"venue"
},
  "geometry": {"coordinates":[150.070236206,-36.4285888672],"type":"Point"}
}