{
  "type": "Feature",
  "properties": {
    "addr:full":"148 Cnr Hornibrook Esplanade & Main Rd Clontarf QLD 4019",
    "addr:housenumber":"148",
    "addr:postcode":"4019",
    "addr:street":"Cnr Hornibrook Esplanade & Main Rd",
    "iso:country":"AU",
    "sg:address":"148 Cnr Hornibrook Esplanade & Main Rd",
    "sg:city":"Clontarf",
    "sg:classifiers":[
        {
            "category":"Professional",
            "subcategory":"Accounting & Tax Preparation",
            "type":"Services"
        }
    ],
    "sg:phone":"+61 7 3883 2222",
    "sg:postcode":"4019",
    "sg:province":"QLD",
    "sg:tags":[
        "consultant",
        "taxation"
    ],
    "wof:name":"QTAX",
    "wof:placetype":"venue"
},
  "geometry": {"coordinates":[153.08244323700001,-27.259262085],"type":"Point"}
}