{
  "type": "Feature",
  "properties": {
    "addr:full":"18 Pile Rd Somersby NSW 2250",
    "addr:housenumber":"18",
    "addr:postcode":"2250",
    "addr:street":"Pile Rd",
    "iso:country":"AU",
    "sg:address":"18 Pile Rd",
    "sg:city":"Somersby",
    "sg:classifiers":[
        {
            "category":"Home & Garden",
            "subcategory":"Building Materials",
            "type":"Retail Goods"
        }
    ],
    "sg:phone":"+61 2 4340 4100",
    "sg:postcode":"2250",
    "sg:province":"NSW",
    "sg:tags":[
        "retaining",
        "wall"
    ],
    "wof:name":"Ozblock Masonry",
    "wof:placetype":"venue"
},
  "geometry": {"coordinates":[151.284988403,-33.4100036621],"type":"Point"}
}