{
  "type": "Feature",
  "properties": {
    "iso:country":"AU",
    "sg:address":"Paralowie Veterinary Surgery, 136 Waterloo Corner",
    "sg:city":"Paralowie",
    "sg:classifiers":[
        {
            "category":"Retail",
            "subcategory":"Veterinary Services",
            "type":"Services"
        }
    ],
    "sg:phone":"+61 8 8258 2220",
    "sg:postcode":"5108",
    "sg:province":"SA",
    "sg:tags":[
        "surgeon"
    ],
    "wof:name":"Hamood Wendy",
    "wof:placetype":"venue"
},
  "geometry": {"coordinates":[138.61312866200001,-34.7450828552],"type":"Point"}
}