{
  "type": "Feature",
  "properties": {
    "addr:full":"Suite 5 85 Mount Barker Rd Stirling SA 5152",
    "addr:housenumber":"85",
    "addr:postcode":"5152",
    "addr:street":"Mount Barker Rd",
    "iso:country":"AU",
    "sg:address":"Suite 5 85 Mount Barker Rd",
    "sg:city":"Stirling",
    "sg:classifiers":[
        {
            "category":"Building & Trades",
            "subcategory":"Landscaping Services",
            "type":"Services"
        }
    ],
    "sg:phone":"+61 8 8339 4388",
    "sg:postcode":"5152",
    "sg:province":"SA",
    "sg:tags":[
        "grazier"
    ],
    "wof:name":"City Meat Co Pty Ltd",
    "wof:placetype":"venue"
},
  "geometry": {"coordinates":[138.722198486,-35.0080337524],"type":"Point"}
}