{
  "type": "Feature",
  "properties": {
    "addr:full":"44 Rowley St Seven Hills NSW 2147",
    "addr:housenumber":"44",
    "addr:postcode":"2147",
    "addr:street":"Rowley St",
    "iso:country":"AU",
    "sg:address":"44 Rowley St",
    "sg:city":"Seven Hills",
    "sg:classifiers":[
        {
            "category":"Professional",
            "subcategory":"Art Services",
            "type":"Services"
        }
    ],
    "sg:phone":"+61 2 9620 4164",
    "sg:postcode":"2147",
    "sg:province":"NSW",
    "sg:tags":[
        "decorator",
        "painter"
    ],
    "wof:name":"J.C.T. Painting Services",
    "wof:placetype":"venue"
},
  "geometry": {"coordinates":[150.93092346200001,-33.7718429565],"type":"Point"}
}