{
  "type": "Feature",
  "properties": {
    "iso:country":"AU",
    "sg:address":"Unit 2, 133 Long St",
    "sg:city":"Smithfield",
    "sg:classifiers":[
        {
            "category":"Mining & Drilling",
            "type":"Manufacturing & Wholesale Goods"
        }
    ],
    "sg:phone":"+61 2 9757 2566",
    "sg:postcode":"2164",
    "sg:province":"NSW",
    "sg:tags":[
        "boring",
        "contractor"
    ],
    "wof:name":"UEA",
    "wof:placetype":"venue"
},
  "geometry": {"coordinates":[150.93275451700001,-33.8410644531],"type":"Point"}
}