{
  "type": "Feature",
  "properties": {
    "addr:full":"63- 65 Logan River Rd Beenleigh QLD 4207",
    "addr:housenumber":"65",
    "addr:postcode":"4207",
    "addr:street":"Logan River Rd",
    "iso:country":"AU",
    "sg:address":"63- 65 Logan River Rd",
    "sg:city":"Beenleigh",
    "sg:classifiers":[
        {
            "category":"Autos & Motor Vehicles",
            "subcategory":"Boat Sales",
            "type":"Retail Goods"
        }
    ],
    "sg:phone":"+61 7 3807 6666",
    "sg:postcode":"4207",
    "sg:province":"QLD",
    "sg:tags":[
        "equipment",
        "yacht"
    ],
    "sg:website":"http://www.activefabrications.com.au",
    "wof:name":"A Active Fabrications Qld Pty Ltd",
    "wof:placetype":"venue"
},
  "geometry": {"coordinates":[153.186447144,-27.7136726379],"type":"Point"}
}