{
  "type": "Feature",
  "properties": {
    "addr:full":"20 Arrionga Pl Hornsby NSW 2077",
    "addr:housenumber":"20",
    "addr:postcode":"2077",
    "addr:street":"Arrionga Pl",
    "iso:country":"AU",
    "sg:address":"20 Arrionga Pl",
    "sg:city":"Hornsby",
    "sg:classifiers":[
        {
            "category":"Professional",
            "subcategory":"Printing & Photocopies",
            "type":"Services"
        }
    ],
    "sg:phone":"+61 2 9940 3929",
    "sg:postcode":"2077",
    "sg:province":"NSW",
    "sg:tags":[
        "embroidery"
    ],
    "wof:name":"Annie's Designs",
    "wof:placetype":"venue"
},
  "geometry": {"coordinates":[151.090454102,-33.6923217773],"type":"Point"}
}