{
  "type": "Feature",
  "properties": {
    "addr:full":"41 Victoria Pde., (HWY 1) Port Augusta SA 5700",
    "addr:housenumber":"41",
    "addr:postcode":"5700",
    "addr:street":"Victoria Pde. Hwy 1",
    "iso:country":"AU",
    "sg:address":"41 Victoria Pde., (HWY 1)",
    "sg:city":"Port Augusta",
    "sg:classifiers":[
        {
            "category":"Retail",
            "subcategory":"Auto Repair",
            "type":"Services"
        }
    ],
    "sg:phone":"+61 8 8642 2474",
    "sg:postcode":"5700",
    "sg:province":"SA",
    "sg:tags":[
        "repairer",
        "motor",
        "engineer"
    ],
    "wof:name":"Ralph's Auto Electrical & Car Airconditioning",
    "wof:placetype":"venue"
},
  "geometry": {"coordinates":[137.775146484,-32.4976997375],"type":"Point"}
}