{
  "type": "Feature",
  "properties": {
    "iso:country":"AU",
    "sg:address":"Level 1, 64 Railway Pde",
    "sg:city":"Kogarah",
    "sg:classifiers":[
        {
            "category":"Professional",
            "subcategory":"Accounting & Tax Preparation",
            "type":"Services"
        }
    ],
    "sg:phone":"+61 2 9587 7777",
    "sg:postcode":"2217",
    "sg:province":"NSW",
    "sg:tags":[
        "consultant",
        "taxation"
    ],
    "wof:name":"Tax Tips Kogarah",
    "wof:placetype":"venue"
},
  "geometry": {"coordinates":[151.131775,-33.96286],"type":"Point"}
}