{
  "type": "Feature",
  "properties": {
    "addr:full":"Shop 4, 134 - 136 Pascoe Vale Rd Moonee Ponds VIC 3039",
    "addr:housenumber":"shop 4;136",
    "addr:postcode":"134;3039",
    "addr:street":"Pascoe Vale Rd",
    "iso:country":"AU",
    "sg:address":"Shop 4, 134 - 136 Pascoe Vale Rd",
    "sg:city":"Moonee Ponds",
    "sg:classifiers":[
        {
            "category":"Health Services",
            "subcategory":"Health Practitioner",
            "type":"Services"
        }
    ],
    "sg:phone":"+61 3 9370 7888",
    "sg:postcode":"3039",
    "sg:province":"VIC",
    "sg:tags":[
        "osteopath"
    ],
    "wof:name":"Moonee Valley Osteopathy",
    "wof:placetype":"venue"
},
  "geometry": {"coordinates":[144.926163,-37.760811],"type":"Point"}
}