{
  "type": "Feature",
  "properties": {
    "addr:full":"278 Inkerman St St Kilda VIC 3182",
    "addr:housenumber":"278",
    "addr:postcode":"3182",
    "addr:street":"Inkerman St",
    "iso:country":"AU",
    "sg:address":"278 Inkerman St",
    "sg:city":"St Kilda",
    "sg:classifiers":[
        {
            "category":"Health Services",
            "subcategory":"Doctor",
            "type":"Services"
        }
    ],
    "sg:phone":"+61 3 9525 8300",
    "sg:postcode":"3182",
    "sg:province":"VIC",
    "sg:tags":[
        "medical",
        "practitioner"
    ],
    "wof:name":"Gyorki Dr J.J.",
    "wof:placetype":"venue"
},
  "geometry": {"coordinates":[144.99305725100001,-37.865688324],"type":"Point"}
}