{
  "type": "Feature",
  "properties": {
    "addr:full":"Industry Ave Narromine NSW 2821",
    "addr:postcode":"2821",
    "addr:street":"Industry Ave",
    "iso:country":"AU",
    "sg:address":"Industry Ave",
    "sg:city":"Narromine",
    "sg:classifiers":[
        {
            "category":"Retail",
            "subcategory":"Auto Repair",
            "type":"Services"
        }
    ],
    "sg:phone":"+61 2 6889 2551",
    "sg:postcode":"2821",
    "sg:province":"NSW",
    "sg:tags":[
        "engine",
        "reconditioning"
    ],
    "wof:name":"Jansen Len Engine Reconditioning",
    "wof:placetype":"venue"
},
  "geometry": {"coordinates":[148.25918579099999,-32.2389183044],"type":"Point"}
}