{
  "type": "Feature",
  "properties": {
    "iso:country":"AU",
    "sg:address":"Suite 3, 9th Floor 118 Queens St",
    "sg:city":"Melbourne",
    "sg:classifiers":[
        {
            "category":"Health Services",
            "subcategory":"Health Practitioner",
            "type":"Services"
        }
    ],
    "sg:phone":"+61 3 9521 5532",
    "sg:postcode":"3000",
    "sg:province":"VIC",
    "sg:tags":[
        "psychologist"
    ],
    "wof:name":"Pizer Michelle",
    "wof:placetype":"venue"
},
  "geometry": {"coordinates":[144.961227417,-37.8157234192],"type":"Point"}
}