{
  "type": "Feature",
  "properties": {
    "addr:full":"121A Vincent St Cessnock NSW 2325",
    "addr:housenumber":"121a",
    "addr:postcode":"2325",
    "addr:street":"Vincent St",
    "iso:country":"AU",
    "sg:address":"121A Vincent St",
    "sg:city":"Cessnock",
    "sg:classifiers":[
        {
            "category":"Real Estate",
            "subcategory":"Surveying",
            "type":"Services"
        }
    ],
    "sg:phone":"+61 2 4990 1711",
    "sg:postcode":"2325",
    "sg:province":"NSW",
    "sg:tags":[
        "surveyor",
        "land"
    ],
    "wof:name":"Marshall Scott",
    "wof:placetype":"venue"
},
  "geometry": {"coordinates":[151.35598754899999,-32.8358573914],"type":"Point"}
}