{
  "type": "Feature",
  "properties": {
    "addr:full":"1 Jacka St Macleod VIC 3085",
    "addr:housenumber":"1",
    "addr:postcode":"3085",
    "addr:street":"Jacka St",
    "iso:country":"AU",
    "sg:address":"1 Jacka St",
    "sg:city":"Macleod",
    "sg:classifiers":[
        {
            "category":"Retail",
            "subcategory":"Auto Repair",
            "type":"Services"
        }
    ],
    "sg:phone":"+61 3 9459 6424",
    "sg:postcode":"3085",
    "sg:province":"VIC",
    "sg:tags":[
        "repairer",
        "motor",
        "engineer"
    ],
    "wof:name":"Furness Motors",
    "wof:placetype":"venue"
},
  "geometry": {"coordinates":[145.067062378,-37.729888916],"type":"Point"}
}