{
  "type": "Feature",
  "properties": {
    "iso:country":"AU",
    "sg:address":"Two Wells Rd",
    "sg:city":"Tintinara",
    "sg:classifiers":[
        {
            "category":"Building & Trades",
            "subcategory":"Landscaping Services",
            "type":"Services"
        }
    ],
    "sg:phone":"+61 8 8757 2218",
    "sg:postcode":"5266",
    "sg:province":"SA",
    "sg:tags":[
        "grazier"
    ],
    "wof:name":"Pye T M",
    "wof:placetype":"venue"
},
  "geometry": {"coordinates":[140.058273,-35.901146],"type":"Point"}
}