{
  "type": "Feature",
  "properties": {
    "addr:full":"7 Teal Pl Hinchinbrook NSW 2168",
    "addr:housenumber":"7",
    "addr:postcode":"2168",
    "addr:street":"Teal Pl",
    "iso:country":"AU",
    "sg:address":"7 Teal Pl",
    "sg:city":"Hinchinbrook",
    "sg:classifiers":[
        {
            "category":"Building & Trades",
            "subcategory":"Construction",
            "type":"Services"
        }
    ],
    "sg:phone":"+61 403 219 626",
    "sg:postcode":"2168",
    "sg:province":"NSW",
    "sg:tags":[
        "rendering",
        "cement"
    ],
    "wof:name":"F Conclaves Cement Rendering",
    "wof:placetype":"venue"
},
  "geometry": {"coordinates":[150.865966797,-33.9127426147],"type":"Point"}
}