{
  "type": "Feature",
  "properties": {
    "iso:country":"AU",
    "sg:address":"12 Chelva St",
    "sg:city":"Wishart",
    "sg:classifiers":[
        {
            "category":"Social Services",
            "subcategory":"Retirement Home",
            "type":"Services"
        }
    ],
    "sg:phone":"+61 7 3343 2237",
    "sg:postcode":"4122",
    "sg:province":"QLD",
    "sg:tags":[
        "life",
        "coaching"
    ],
    "wof:name":"Be Happy In Life",
    "wof:placetype":"venue"
},
  "geometry": {"coordinates":[153.09584045400001,-27.5570964813],"type":"Point"}
}