{
  "type": "Feature",
  "properties": {
    "iso:country":"AU",
    "sg:address":"Suite 3",
    "sg:city":"/14 Pioneer Avenue Tuggerah Business Park, Tu",
    "sg:classifiers":[
        {
            "category":"Education",
            "subcategory":"Special Training",
            "type":"Public Place"
        }
    ],
    "sg:phone":"+61 1800 249 579",
    "sg:postcode":"2259",
    "sg:province":"NSW",
    "sg:tags":[
        "development"
    ],
    "wof:name":"A W Workwise",
    "wof:placetype":"venue"
},
  "geometry": {"coordinates":[151.42060852,-33.3156661987],"type":"Point"}
}