{
  "type": "Feature",
  "properties": {
    "iso:country":"AU",
    "sg:address":"55 Lyrebird Drv",
    "sg:city":"Carrum Downs",
    "sg:classifiers":[
        {
            "category":"Food & Beverages",
            "subcategory":"Groceries & Convenience Stores",
            "type":"Retail Goods"
        }
    ],
    "sg:phone":"+61 3 9786 1371",
    "sg:postcode":"3201",
    "sg:province":"VIC",
    "wof:name":"Lyrebird Drive Convenience Store",
    "wof:placetype":"venue"
},
  "geometry": {"coordinates":[145.175095,-38.111053],"type":"Point"}
}