{
  "type": "Feature",
  "properties": {
    "addr:full":"Whitmore Rd Maraylya NSW 2765",
    "addr:postcode":"2765",
    "addr:street":"Whitmore Rd",
    "iso:country":"AU",
    "sg:address":"Whitmore Rd",
    "sg:city":"Maraylya",
    "sg:classifiers":[
        {
            "category":"Organizations",
            "subcategory":"Non-profit Organization",
            "type":"Services"
        }
    ],
    "sg:phone":"+61 2 4573 6323",
    "sg:postcode":"2765",
    "sg:province":"NSW",
    "sg:tags":[
        "environmental",
        "organisation",
        "conservation"
    ],
    "wof:name":"Longneck Lagoon Field Studies Centre",
    "wof:placetype":"venue"
},
  "geometry": {"coordinates":[150.90472412099999,-33.5833396912],"type":"Point"}
}