{
  "type": "Feature",
  "properties": {
    "addr:full":"Cnr. Victoria St & Justin Sts Smithfield NSW 2164",
    "addr:postcode":"2164",
    "addr:street":"Victoria St & Justin Sts",
    "iso:country":"AU",
    "sg:address":"Cnr. Victoria St & Justin Sts",
    "sg:city":"Smithfield",
    "sg:classifiers":[
        {
            "category":"Home & Garden",
            "subcategory":"Building Materials",
            "type":"Retail Goods"
        }
    ],
    "sg:phone":"+61 2 8788 7100",
    "sg:postcode":"2164",
    "sg:province":"NSW",
    "sg:tags":[
        "supply"
    ],
    "wof:name":"Buildit Mitre 10 Home & Trade",
    "wof:placetype":"venue"
},
  "geometry": {"coordinates":[150.931243897,-33.8501205444],"type":"Point"}
}