{
  "type": "Feature",
  "properties": {
    "addr:full":"7 Woodrush Crt Dural NSW 2158",
    "addr:housenumber":"7",
    "addr:postcode":"2158",
    "addr:street":"Woodrush Crt",
    "iso:country":"AU",
    "sg:address":"7 Woodrush Crt",
    "sg:city":"Dural",
    "sg:classifiers":[
        {
            "category":"Professional",
            "subcategory":"Business Services",
            "type":"Services"
        }
    ],
    "sg:phone":"+61 2 9651 3661",
    "sg:postcode":"2158",
    "sg:province":"NSW",
    "sg:tags":[
        "management",
        "event"
    ],
    "wof:name":"Timeless Photography",
    "wof:placetype":"venue"
},
  "geometry": {"coordinates":[151.033493042,-33.7138824463],"type":"Point"}
}