{
  "type": "Feature",
  "properties": {
    "addr:full":"46 Yass Rd Queanbeyan ACT 2620",
    "addr:housenumber":"46",
    "addr:postcode":"2620",
    "addr:street":"Yass Rd",
    "iso:country":"AU",
    "sg:address":"46 Yass Rd",
    "sg:city":"Queanbeyan",
    "sg:classifiers":[
        {
            "category":"Retail",
            "subcategory":"Auto Repair",
            "type":"Services"
        }
    ],
    "sg:phone":"+61 2 6297 2180",
    "sg:postcode":"2620",
    "sg:province":"ACT",
    "sg:tags":[
        "electrical"
    ],
    "wof:name":"Taunton's (Queanbeyan)",
    "wof:placetype":"venue"
},
  "geometry": {"coordinates":[149.24432373100001,-35.3415374756],"type":"Point"}
}