{
  "type": "Feature",
  "properties": {
    "addr:full":"22 Laurel Bank Pde Newtown VIC 3220",
    "addr:housenumber":"22",
    "addr:postcode":"3220",
    "addr:street":"Laurel Bank Pde",
    "iso:country":"AU",
    "sg:address":"22 Laurel Bank Pde",
    "sg:city":"Newtown",
    "sg:classifiers":[
        {
            "category":"Real Estate",
            "subcategory":"Architect",
            "type":"Services"
        }
    ],
    "sg:phone":"+61 419 553 319",
    "sg:postcode":"3220",
    "sg:province":"VIC",
    "wof:name":"Millar Watson Architects",
    "wof:placetype":"venue"
},
  "geometry": {"coordinates":[144.34927400000001,-38.150791],"type":"Point"}
}