{
  "type": "Feature",
  "properties": {
    "iso:country":"AU",
    "sg:address":"30 Palmer St",
    "sg:city":"North Mackay",
    "sg:classifiers":[
        {
            "category":"Retail",
            "subcategory":"Repair Shop",
            "type":"Services"
        }
    ],
    "sg:phone":"+61 7 4953 1945",
    "sg:postcode":"4740",
    "sg:province":"QLD",
    "sg:tags":[
        "maintenance",
        "pool",
        "swimming"
    ],
    "wof:name":"Mackay Pools & Spas",
    "wof:placetype":"venue"
},
  "geometry": {"coordinates":[149.187729,-21.124277],"type":"Point"}
}