{
  "type": "Feature",
  "properties": {
    "iso:country":"AU",
    "sg:address":"35 Blackburn Rd",
    "sg:city":"Mt Waverley",
    "sg:classifiers":[
        {
            "category":"Health Services",
            "subcategory":"Doctor",
            "type":"Services"
        }
    ],
    "sg:phone":"+61 3 9802 7799",
    "sg:postcode":"3149",
    "sg:province":"VIC",
    "sg:tags":[
        "medical",
        "practitioner"
    ],
    "wof:name":"Tally Ho Medical Centre",
    "wof:placetype":"venue"
},
  "geometry": {"coordinates":[145.150466919,-37.8605384827],"type":"Point"}
}