{
  "type": "Feature",
  "properties": {
    "addr:full":"6/ 10 Boron St Sumner Park QLD 4074",
    "addr:housenumber":"/ 10",
    "addr:postcode":"4074",
    "addr:street":"Boron St",
    "iso:country":"AU",
    "sg:address":"6/ 10 Boron St",
    "sg:city":"Sumner Park",
    "sg:classifiers":[
        {
            "category":"Retail",
            "subcategory":"Auto Repair",
            "type":"Services"
        }
    ],
    "sg:phone":"+61 412 475 913",
    "sg:postcode":"4074",
    "sg:province":"QLD",
    "sg:tags":[
        "car",
        "restoration",
        "supply"
    ],
    "wof:name":"JCR Motorsport",
    "wof:placetype":"venue"
},
  "geometry": {"coordinates":[152.935150147,-27.5635929108],"type":"Point"}
}