{
  "type": "Feature",
  "properties": {
    "iso:country":"AU",
    "sg:address":"Gairdner South Rd",
    "sg:city":"Gairdner",
    "sg:classifiers":[
        {
            "category":"Education",
            "subcategory":"School",
            "type":"Public Place"
        }
    ],
    "sg:phone":"+61 8 9836 1014",
    "sg:postcode":"6337",
    "sg:province":"WA",
    "sg:tags":[
        "state",
        "except",
        "nsw"
    ],
    "wof:name":"Gairdner Primary School",
    "wof:placetype":"venue"
},
  "geometry": {"coordinates":[118.936637878,-34.2106819153],"type":"Point"}
}