{
  "type": "Feature",
  "properties": {
    "iso:country":"AU",
    "sg:address":"82a Albert St",
    "sg:city":"Preston",
    "sg:classifiers":[
        {
            "category":"Home & Garden",
            "subcategory":"Carpets & Floor Coverings",
            "type":"Retail Goods"
        }
    ],
    "sg:phone":"+61 3 9470 1920",
    "sg:postcode":"3072",
    "sg:province":"VIC",
    "sg:tags":[
        "machine"
    ],
    "wof:name":"Sandpaper Plus",
    "wof:placetype":"venue"
},
  "geometry": {"coordinates":[145.02264404300001,-37.7433891296],"type":"Point"}
}