{
  "type": "Feature",
  "properties": {
    "iso:country":"AU",
    "sg:address":"PO Box 81",
    "sg:city":"Nagambie",
    "sg:classifiers":[
        {
            "category":"Building & Trades",
            "subcategory":"Plumbing",
            "type":"Services"
        }
    ],
    "sg:phone":"+61 418 575 385",
    "sg:postcode":"3608",
    "sg:province":"VIC",
    "sg:tags":[
        "plumber",
        "gasfitters"
    ],
    "wof:name":"J & N Hilton Plumbing Pty Ltd",
    "wof:placetype":"venue"
},
  "geometry": {"coordinates":[145.15234375,-36.7899703979],"type":"Point"}
}