{
  "type": "Feature",
  "properties": {
    "iso:country":"AU",
    "sg:address":"87 Womerah Ave",
    "sg:city":"Darlinghurst",
    "sg:classifiers":[
        {
            "category":"Health Services",
            "subcategory":"Health Practitioner",
            "type":"Services"
        }
    ],
    "sg:phone":"+61 2 9361 3617",
    "sg:postcode":"2010",
    "sg:province":"NSW",
    "sg:tags":[
        "acupuncture"
    ],
    "wof:name":"Lisner Raymond",
    "wof:placetype":"venue"
},
  "geometry": {"coordinates":[151.22442626899999,-33.8774719238],"type":"Point"}
}