{
  "type": "Feature",
  "properties": {
    "addr:full":"845 Howitt St Wendouree VIC 3355",
    "addr:housenumber":"845",
    "addr:postcode":"3355",
    "addr:street":"Howitt St",
    "iso:country":"AU",
    "sg:address":"845 Howitt St",
    "sg:city":"Wendouree",
    "sg:classifiers":[
        {
            "category":"Insurance",
            "subcategory":"Hazard Insurance",
            "type":"Services"
        }
    ],
    "sg:phone":"+61 3 5339 6200",
    "sg:postcode":"3355",
    "sg:province":"VIC",
    "sg:tags":[
        "motor",
        "vehicle"
    ],
    "wof:name":"Motorcycle Land Ballarat",
    "wof:placetype":"venue"
},
  "geometry": {"coordinates":[143.84440599999999,-37.541962],"type":"Point"}
}