{
  "type": "Feature",
  "properties": {
    "iso:country":"AU",
    "sg:address":"31 Porter St",
    "sg:city":"Port Lincoln",
    "sg:classifiers":[
        {
            "category":"Autos & Motor Vehicles",
            "subcategory":"Motorcycle Sales",
            "type":"Retail Goods"
        }
    ],
    "sg:phone":"+61 1800 818 123",
    "sg:postcode":"5606",
    "sg:province":"SA",
    "sg:tags":[
        "outboard"
    ],
    "wof:name":"Johnnies Marine",
    "wof:placetype":"venue"
},
  "geometry": {"coordinates":[135.86183199999999,-34.727051],"type":"Point"}
}