{
  "type": "Feature",
  "properties": {
    "iso:country":"AU",
    "sg:address":"3 Rivergum Drv",
    "sg:city":"Mill Park",
    "sg:classifiers":[
        {
            "category":"Health Services",
            "subcategory":"Health Practitioner",
            "type":"Services"
        }
    ],
    "sg:phone":"+61 3 9436 0700",
    "sg:postcode":"3082",
    "sg:province":"VIC",
    "sg:tags":[
        "physiotherapist"
    ],
    "wof:name":"Saleh Karim",
    "wof:placetype":"venue"
},
  "geometry": {"coordinates":[145.07432556099999,-37.6633377075],"type":"Point"}
}