{
  "type": "Feature",
  "properties": {
    "addr:full":"377 Fitzgerald St North Perth WA 6006",
    "addr:housenumber":"377",
    "addr:postcode":"6006",
    "addr:street":"Fitzgerald St",
    "iso:country":"AU",
    "sg:address":"377 Fitzgerald St",
    "sg:city":"North Perth",
    "sg:classifiers":[
        {
            "category":"Shopping",
            "subcategory":"Antiques",
            "type":"Retail Goods"
        }
    ],
    "sg:phone":"+61 8 9227 5502",
    "sg:postcode":"6006",
    "sg:province":"WA",
    "sg:tags":[
        "restoration",
        "reproduction"
    ],
    "wof:name":"North Perth Antique Centre",
    "wof:placetype":"venue"
},
  "geometry": {"coordinates":[115.858932495,-31.9332542419],"type":"Point"}
}