{
  "type": "Feature",
  "properties": {
    "addr:full":"1 Church St Bellingen NSW 2454",
    "addr:housenumber":"1",
    "addr:postcode":"2454",
    "addr:street":"Church St",
    "iso:country":"AU",
    "sg:address":"1 Church St",
    "sg:city":"Bellingen",
    "sg:classifiers":[
        {
            "category":"Education",
            "subcategory":"Special Training",
            "type":"Public Place"
        }
    ],
    "sg:phone":"+61 2 6655 2083",
    "sg:postcode":"2454",
    "sg:province":"NSW",
    "sg:tags":[
        "development"
    ],
    "wof:name":"ETC",
    "wof:placetype":"venue"
},
  "geometry": {"coordinates":[152.89704900000001,-30.451296],"type":"Point"}
}