{
  "type": "Feature",
  "properties": {
    "addr:full":"9 Hamilton Rd High Wycombe WA 6057",
    "addr:housenumber":"9",
    "addr:postcode":"6057",
    "addr:street":"Hamilton Rd",
    "iso:country":"AU",
    "sg:address":"9 Hamilton Rd",
    "sg:city":"High Wycombe",
    "sg:classifiers":[
        {
            "category":"Professional",
            "subcategory":"Accounting & Tax Preparation",
            "type":"Services"
        }
    ],
    "sg:phone":"+61 8 9454 7970",
    "sg:postcode":"6057",
    "sg:province":"WA",
    "sg:tags":[
        "bookkeeping"
    ],
    "wof:name":"Bookkeeping Made Easy",
    "wof:placetype":"venue"
},
  "geometry": {"coordinates":[116.002449036,-31.9382839203],"type":"Point"}
}