{
  "type": "Feature",
  "properties": {
    "addr:full":"Shp 16/ 110 Wattletree Rd Armadale VIC 3143",
    "addr:housenumber":"16 / 110",
    "addr:postcode":"3143",
    "addr:street":"Wattletree Rd",
    "iso:country":"AU",
    "sg:address":"Shp 16/ 110 Wattletree Rd",
    "sg:city":"Armadale",
    "sg:classifiers":[
        {
            "category":"Personal",
            "subcategory":"Beauty Salon",
            "type":"Services"
        }
    ],
    "sg:phone":"+61 3 9509 5688",
    "sg:postcode":"3143",
    "sg:province":"VIC",
    "wof:name":"Professionail",
    "wof:placetype":"venue"
},
  "geometry": {"coordinates":[145.027252197,-37.8623313904],"type":"Point"}
}