{
  "type": "Feature",
  "properties": {
    "addr:full":"2 Market St Trentham VIC 3458",
    "addr:housenumber":"2",
    "addr:postcode":"3458",
    "addr:street":"Market St",
    "iso:country":"AU",
    "sg:address":"2 Market St",
    "sg:city":"Trentham",
    "sg:classifiers":[
        {
            "category":"Home & Garden",
            "subcategory":"Garden Supply",
            "type":"Retail Goods"
        }
    ],
    "sg:phone":"+61 3 5424 1128",
    "sg:postcode":"3458",
    "sg:province":"VIC",
    "sg:tags":[
        "statuary",
        "fountains",
        "sundial"
    ],
    "wof:name":"Trentham Garden Ornaments",
    "wof:placetype":"venue"
},
  "geometry": {"coordinates":[144.32324218799999,-37.3867149353],"type":"Point"}
}