{
  "type": "Feature",
  "properties": {
    "addr:full":"915 Pacific Hwy Pymble NSW 2073",
    "addr:housenumber":"915",
    "addr:postcode":"2073",
    "addr:street":"Pacific Hwy",
    "iso:country":"AU",
    "sg:address":"915 Pacific Hwy",
    "sg:city":"Pymble",
    "sg:classifiers":[
        {
            "category":"Wholesale",
            "subcategory":"Stationery",
            "type":"Manufacturing & Wholesale Goods"
        }
    ],
    "sg:phone":"+61 2 9988 3566",
    "sg:postcode":"2073",
    "sg:province":"NSW",
    "sg:tags":[
        "mfrg"
    ],
    "wof:name":"Pymble Office Supplies Pty Ltd",
    "wof:placetype":"venue"
},
  "geometry": {"coordinates":[151.145065308,-33.7464790344],"type":"Point"}
}