{
  "type": "Feature",
  "properties": {
    "addr:full":"23 Reynolds Rd Capel WA 6271",
    "addr:housenumber":"23",
    "addr:postcode":"6271",
    "addr:street":"Reynolds Rd",
    "iso:country":"AU",
    "sg:address":"23 Reynolds Rd",
    "sg:city":"Capel",
    "sg:classifiers":[
        {
            "category":"Building & Trades",
            "subcategory":"Landscaping Services",
            "type":"Services"
        }
    ],
    "sg:phone":"+61 8 9727 2797",
    "sg:postcode":"6271",
    "sg:province":"WA",
    "sg:tags":[
        "stump",
        "tree",
        "felling",
        "removal"
    ],
    "wof:name":"Hays Tree Lopping",
    "wof:placetype":"venue"
},
  "geometry": {"coordinates":[115.572898865,-33.5538368225],"type":"Point"}
}