{
  "type": "Feature",
  "properties": {
    "addr:full":"Pipeclay La Mudgee NSW 2850",
    "addr:postcode":"2850",
    "iso:country":"AU",
    "sg:address":"Pipeclay La",
    "sg:city":"Mudgee",
    "sg:classifiers":[
        {
            "category":"Home & Garden",
            "subcategory":"Garden Supply",
            "type":"Retail Goods"
        }
    ],
    "sg:phone":"+61 2 6373 3819",
    "sg:postcode":"2850",
    "sg:province":"NSW",
    "sg:tags":[
        "turf",
        "lawn"
    ],
    "wof:name":"Plummer R & J",
    "wof:placetype":"venue"
},
  "geometry": {"coordinates":[149.656937,-32.539284],"type":"Point"}
}