{
  "type": "Feature",
  "properties": {
    "addr:full":"53-55 Emu Bay Rd Deloraine TAS 7304",
    "addr:housenumber":"53-55",
    "addr:postcode":"7304",
    "addr:street":"Emu Bay Rd",
    "iso:country":"AU",
    "sg:address":"53-55 Emu Bay Rd",
    "sg:city":"Deloraine",
    "sg:classifiers":[
        {
            "category":"Personal",
            "subcategory":"Beauty Salon",
            "type":"Services"
        }
    ],
    "sg:phone":"+61 3 6362 2300",
    "sg:postcode":"7304",
    "sg:province":"TAS",
    "sg:tags":[
        "hairdresser"
    ],
    "wof:name":"Edge Hair Studio",
    "wof:placetype":"venue"
},
  "geometry": {"coordinates":[146.654236,-41.525173],"type":"Point"}
}