{
  "type": "Feature",
  "properties": {
    "addr:full":"3 Boxwood Cl Ourimbah NSW 2258",
    "addr:housenumber":"3",
    "addr:postcode":"2258",
    "addr:street":"Boxwood Cl",
    "iso:country":"AU",
    "sg:address":"3 Boxwood Cl",
    "sg:city":"Ourimbah",
    "sg:classifiers":[
        {
            "category":"Health Services",
            "subcategory":"Health Practitioner",
            "type":"Services"
        }
    ],
    "sg:phone":"+61 2 4362 2795",
    "sg:postcode":"2258",
    "sg:province":"NSW",
    "sg:tags":[
        "naturopath"
    ],
    "sg:website":"http://www.atms.com.au",
    "wof:name":"Natural Health & Fertility Care Clinic",
    "wof:placetype":"venue"
},
  "geometry": {"coordinates":[151.369750977,-33.3518981934],"type":"Point"}
}