{
  "type": "Feature",
  "properties": {
    "iso:country":"AU",
    "sg:address":"43 Quinn St",
    "sg:city":"Preston",
    "sg:classifiers":[
        {
            "category":"Industrial Area",
            "type":"Public Place"
        }
    ],
    "sg:phone":"+61 3 9495 1299",
    "sg:postcode":"3072",
    "sg:province":"VIC",
    "sg:tags":[
        "protective",
        "clothing"
    ],
    "wof:name":"Stewart & Heaton Clothing Co Pty Ltd",
    "wof:placetype":"venue"
},
  "geometry": {"coordinates":[145.03233337399999,-37.7451133728],"type":"Point"}
}