{
  "type": "Feature",
  "properties": {
    "addr:full":"50 Tattersall Rd Blacktown NSW 2148",
    "addr:housenumber":"50",
    "addr:postcode":"2148",
    "addr:street":"Tattersall Rd",
    "iso:country":"AU",
    "sg:address":"50 Tattersall Rd",
    "sg:city":"Blacktown",
    "sg:classifiers":[
        {
            "category":"Social Services",
            "subcategory":"Adult Care",
            "type":"Services"
        }
    ],
    "sg:phone":"+61 2 9671 5719",
    "sg:postcode":"2148",
    "sg:province":"NSW",
    "sg:tags":[
        "towing"
    ],
    "wof:name":"Kevin Waters Towing",
    "wof:placetype":"venue"
},
  "geometry": {"coordinates":[150.91085815400001,-33.7485313416],"type":"Point"}
}