{
  "type": "Feature",
  "properties": {
    "addr:full":"Level 1, 414 Toorak Rd Toorak VIC 3142",
    "addr:housenumber":"414",
    "addr:postcode":"3142",
    "addr:street":"Toorak Rd",
    "iso:country":"AU",
    "sg:address":"Level 1, 414 Toorak Rd",
    "sg:city":"Toorak",
    "sg:classifiers":[
        {
            "category":"Insurance",
            "subcategory":"Life Insurance",
            "type":"Services"
        }
    ],
    "sg:phone":"+61 3 9828 6700",
    "sg:postcode":"3142",
    "sg:province":"VIC",
    "wof:name":"GWS Genco Group",
    "wof:placetype":"venue"
},
  "geometry": {"coordinates":[145.007446289,-37.8410415649],"type":"Point"}
}