{
  "type": "Feature",
  "properties": {
    "iso:country":"AU",
    "sg:address":"Main St",
    "sg:city":"Winnaleah",
    "sg:classifiers":[
        {
            "category":"Travel",
            "subcategory":"Hotels & Motels",
            "type":"Entertainment"
        }
    ],
    "sg:phone":"+61 3 6354 2331",
    "sg:postcode":"7265",
    "sg:province":"TAS",
    "sg:tags":[
        "accommodation"
    ],
    "wof:name":"Winnaleah Hotel",
    "wof:placetype":"venue"
},
  "geometry": {"coordinates":[147.822144,-41.098091],"type":"Point"}
}