{
  "type": "Feature",
  "properties": {
    "iso:country":"AU",
    "sg:address":"20 Herbert St",
    "sg:city":"Goondiwindi",
    "sg:classifiers":[
        {
            "category":"Retail",
            "subcategory":"Self-service Laundry",
            "type":"Services"
        }
    ],
    "sg:phone":"+61 7 4671 2744",
    "sg:postcode":"4390",
    "sg:province":"QLD",
    "wof:name":"Goondiwindi Laundrymat",
    "wof:placetype":"venue"
},
  "geometry": {"coordinates":[150.30552673299999,-28.5457706451],"type":"Point"}
}