{
  "type": "Feature",
  "properties": {
    "iso:country":"AU",
    "sg:address":"Railway Rd",
    "sg:city":"Burradoo",
    "sg:classifiers":[
        {
            "category":"Farming",
            "subcategory":"Livestock Farm",
            "type":"Manufacturing & Wholesale Goods"
        }
    ],
    "sg:phone":"+61 2 4861 1166",
    "sg:postcode":"2576",
    "sg:province":"NSW",
    "sg:tags":[
        "breeder",
        "horse",
        "stud"
    ],
    "wof:name":"Retford Equine Veterinary Clinic",
    "wof:placetype":"venue"
},
  "geometry": {"coordinates":[150.44172668499999,-34.4840202332],"type":"Point"}
}