{
  "type": "Feature",
  "properties": {
    "iso:country":"AU",
    "sg:address":"7 Cullen Pl",
    "sg:city":"Smithfield",
    "sg:classifiers":[
        {
            "category":"Home & Garden",
            "subcategory":"Hardware",
            "type":"Retail Goods"
        }
    ],
    "sg:phone":"+61 2 9725 5733",
    "sg:postcode":"2164",
    "sg:province":"NSW",
    "sg:tags":[
        "plumber",
        "supply"
    ],
    "wof:name":"Febco Blockflow Prevention",
    "wof:placetype":"venue"
},
  "geometry": {"coordinates":[150.95001220699999,-33.8416824341],"type":"Point"}
}