{
  "type": "Feature",
  "properties": {
    "addr:full":"12 Woorang St Milperra NSW 2214",
    "addr:housenumber":"12",
    "addr:postcode":"2214",
    "addr:street":"Woorang St",
    "iso:country":"AU",
    "sg:address":"12 Woorang St",
    "sg:city":"Milperra",
    "sg:classifiers":[
        {
            "category":"Autos & Motor Vehicles",
            "subcategory":"Auto Supplies",
            "type":"Retail Goods"
        }
    ],
    "sg:phone":"+61 2 9774 4077",
    "sg:postcode":"2214",
    "sg:province":"NSW",
    "sg:tags":[
        "equipment",
        "part",
        "truck"
    ],
    "wof:name":"Ezilift Services",
    "wof:placetype":"venue"
},
  "geometry": {"coordinates":[151.00041200000001,-33.931774],"type":"Point"}
}