{
  "type": "Feature",
  "properties": {
    "iso:country":"AU",
    "sg:address":"Bell St",
    "sg:city":"Torquay",
    "sg:classifiers":[
        {
            "category":"Autos & Motor Vehicles",
            "subcategory":"Fuel & Gas Station",
            "type":"Retail Goods"
        }
    ],
    "sg:phone":"+61 3 5261 2397",
    "sg:postcode":"3228",
    "sg:province":"VIC",
    "wof:name":"BP Australia Limited",
    "wof:placetype":"venue"
},
  "geometry": {"coordinates":[144.31701699999999,-38.337322],"type":"Point"}
}