{
  "type": "Feature",
  "properties": {
    "addr:full":"Cnr Manchester Rd & Market St Carrara QLD 4211",
    "addr:postcode":"4211",
    "addr:street":"Cnr Manchester Rd & Market St",
    "iso:country":"AU",
    "sg:address":"Cnr Manchester Rd & Market St",
    "sg:city":"Carrara",
    "sg:classifiers":[
        {
            "category":"Manufacturing",
            "subcategory":"Building Materials",
            "type":"Manufacturing & Wholesale Goods"
        }
    ],
    "sg:phone":"+61 7 5579 8255",
    "sg:postcode":"4211",
    "sg:province":"QLD",
    "sg:tags":[
        "stone",
        "product",
        "supply"
    ],
    "wof:name":"Sandstone Works Gold Coast",
    "wof:placetype":"venue"
},
  "geometry": {"coordinates":[153.386627197,-28.0280303955],"type":"Point"}
}