{
  "type": "Feature",
  "properties": {
    "addr:full":"Lvl 1 Shop 18b (Bridgepoint Shopping Centre) 3 Brady Street Mosman NSW 2088",
    "addr:housenumber":"shop 18b;3",
    "addr:postcode":"2088",
    "addr:street":"Shopping;Brady",
    "iso:country":"AU",
    "sg:address":"Lvl 1 Shop 18b (Bridgepoint Shopping Centre) 3",
    "sg:city":"Brady Street Mosman",
    "sg:classifiers":[
        {
            "category":"Personal",
            "subcategory":"Shoe Repair & Shine",
            "type":"Services"
        }
    ],
    "sg:phone":"+61 2 9969 4636",
    "sg:postcode":"2088",
    "sg:province":"NSW",
    "sg:tags":[
        "footwear"
    ],
    "wof:name":"Messina Shoe Repairs",
    "wof:placetype":"venue"
},
  "geometry": {"coordinates":[151.24055480999999,-33.8225517273],"type":"Point"}
}