{
  "type": "Feature",
  "properties": {
    "addr:full":"Henty Hwy Beulah VIC 3395",
    "addr:postcode":"3395",
    "addr:street":"Henty Hwy",
    "iso:country":"AU",
    "sg:address":"Henty Hwy",
    "sg:city":"Beulah",
    "sg:classifiers":[
        {
            "category":"Autos & Motor Vehicles",
            "subcategory":"Fuel & Gas Station",
            "type":"Retail Goods"
        }
    ],
    "sg:phone":"+61 3 5390 2363",
    "sg:postcode":"3395",
    "sg:province":"VIC",
    "wof:name":"BP Australia Limited",
    "wof:placetype":"venue"
},
  "geometry": {"coordinates":[142.41928100600001,-35.9449882507],"type":"Point"}
}