{
  "type": "Feature",
  "properties": {
    "addr:full":"Suite 4/ 57 Kinghorne St Nowra NSW 2541",
    "addr:postcode":"2541",
    "addr:street":"57 Kinghorne St",
    "iso:country":"AU",
    "sg:address":"Suite 4/ 57 Kinghorne St",
    "sg:city":"Nowra",
    "sg:classifiers":[
        {
            "category":"Shopping",
            "subcategory":"Clothing, Apparel, & Fashions",
            "type":"Retail Goods"
        }
    ],
    "sg:phone":"+61 2 4422 5593",
    "sg:postcode":"2541",
    "sg:province":"NSW",
    "sg:tags":[
        "lady",
        "wear"
    ],
    "wof:name":"Dress With Finesse",
    "wof:placetype":"venue"
},
  "geometry": {"coordinates":[150.60215759299999,-34.8781013489],"type":"Point"}
}