{
  "type": "Feature",
  "properties": {
    "addr:full":"Fcty8/ 96-100 Briggs St Welshpool WA 6106",
    "addr:housenumber":"96-100",
    "addr:postcode":"6106",
    "addr:street":"Briggs St",
    "iso:country":"AU",
    "sg:address":"Fcty8/ 96-100 Briggs St",
    "sg:city":"Welshpool",
    "sg:classifiers":[
        {
            "category":"Professional",
            "subcategory":"Art Services",
            "type":"Services"
        }
    ],
    "sg:phone":"+61 416 656 673",
    "sg:postcode":"6106",
    "sg:province":"WA",
    "sg:tags":[
        "product",
        "industrial",
        "designer"
    ],
    "wof:name":"Selectrix Industries Pty Ltd",
    "wof:placetype":"venue"
},
  "geometry": {"coordinates":[115.92768859900001,-31.9833049774],"type":"Point"}
}