{
  "type": "Feature",
  "properties": {
    "iso:country":"AU",
    "sg:address":"70 Blackburn Rd",
    "sg:city":"Glen Waverley",
    "sg:classifiers":[
        {
            "category":"Retail",
            "subcategory":"Veterinary Services",
            "type":"Services"
        }
    ],
    "sg:phone":"+61 3 9887 8844",
    "sg:postcode":"3150",
    "sg:province":"VIC",
    "sg:tags":[
        "surgeon"
    ],
    "wof:name":"Preston Chris Dr",
    "wof:placetype":"venue"
},
  "geometry": {"coordinates":[145.15069580100001,-37.8610954285],"type":"Point"}
}