{
  "type": "Feature",
  "properties": {
    "iso:country":"AU",
    "sg:address":"37 Armstrong St",
    "sg:city":"Ballarat",
    "sg:classifiers":[
        {
            "category":"Shopping",
            "subcategory":"Luggage & Leather Goods",
            "type":"Retail Goods"
        }
    ],
    "sg:phone":"+61 3 5334 4257",
    "sg:postcode":"3350",
    "sg:province":"VIC",
    "sg:tags":[
        "reconditioning"
    ],
    "wof:name":"Central Equestrian & Canvas Repairs",
    "wof:placetype":"venue"
},
  "geometry": {"coordinates":[143.855804,-37.563473],"type":"Point"}
}