{
  "type": "Feature",
  "properties": {
    "addr:full":"3 Victoria St (North) Taree NSW 2430",
    "addr:housenumber":"3",
    "addr:postcode":"2430",
    "addr:street":"Victoria St North",
    "iso:country":"AU",
    "sg:address":"3 Victoria St",
    "sg:city":"(North) Taree",
    "sg:classifiers":[
        {
            "category":"Manufacturing",
            "subcategory":"Motor Vehicles & Parts",
            "type":"Manufacturing & Wholesale Goods"
        }
    ],
    "sg:phone":"+61 13 61 31",
    "sg:postcode":"2430",
    "sg:province":"NSW",
    "sg:tags":[
        "replacement"
    ],
    "wof:name":"Auto One",
    "wof:placetype":"venue"
},
  "geometry": {"coordinates":[152.46998600000001,-31.907787],"type":"Point"}
}