{
  "type": "Feature",
  "properties": {
    "addr:full":"136 Kuramun Pl Parkerville WA 6081",
    "addr:housenumber":"136",
    "addr:postcode":"6081",
    "addr:street":"Kuramun Pl",
    "iso:country":"AU",
    "sg:address":"136 Kuramun Pl",
    "sg:city":"Parkerville",
    "sg:classifiers":[
        {
            "category":"Retail",
            "subcategory":"Repair Shop",
            "type":"Services"
        }
    ],
    "sg:phone":"+61 8 9295 4424",
    "sg:postcode":"6081",
    "sg:province":"WA",
    "sg:tags":[
        "upholsterer"
    ],
    "wof:name":"R & B Upholsterers",
    "wof:placetype":"venue"
},
  "geometry": {"coordinates":[116.126426697,-31.8539676666],"type":"Point"}
}