{
  "type": "Feature",
  "properties": {
    "addr:full":"Magid Drv Fountain Gate VIC 3805",
    "addr:postcode":"3805",
    "addr:street":"Magid Drv Fountain",
    "iso:country":"AU",
    "sg:address":"Magid Drv",
    "sg:city":"Fountain Gate",
    "sg:classifiers":[
        {
            "category":"Manufacturing",
            "subcategory":"Jewelry",
            "type":"Manufacturing & Wholesale Goods"
        }
    ],
    "sg:phone":"+61 3 9796 6880",
    "sg:postcode":"3805",
    "sg:province":"VIC",
    "sg:tags":[
        "mfrg",
        "jeweller"
    ],
    "wof:name":"Gold N Power Fountain Gate",
    "wof:placetype":"venue"
},
  "geometry": {"coordinates":[145.30024700000001,-38.016224],"type":"Point"}
}