{
  "type": "Feature",
  "properties": {
    "addr:full":"4 York Pl Bundoora VIC 3083",
    "addr:housenumber":"4",
    "addr:postcode":"3083",
    "addr:street":"York Pl",
    "iso:country":"AU",
    "sg:address":"4 York Pl",
    "sg:city":"Bundoora",
    "sg:classifiers":[
        {
            "category":"Professional",
            "subcategory":"Printing & Photocopies",
            "type":"Services"
        }
    ],
    "sg:phone":"+61 3 9467 3436",
    "sg:postcode":"3083",
    "sg:province":"VIC",
    "sg:tags":[
        "trophy"
    ],
    "wof:name":"Bundoora Trophies",
    "wof:placetype":"venue"
},
  "geometry": {"coordinates":[145.06956481899999,-37.6976623535],"type":"Point"}
}