{
  "type": "Feature",
  "properties": {
    "iso:country":"AU",
    "sg:address":"1 Wissota Pl",
    "sg:city":"Secret Harbour",
    "sg:classifiers":[
        {
            "category":"Building & Trades",
            "subcategory":"Landscaping Services",
            "type":"Services"
        }
    ],
    "sg:phone":"+61 402 438 333",
    "sg:postcode":"6173",
    "sg:province":"WA",
    "sg:tags":[
        "designer",
        "landscape",
        "contractor"
    ],
    "wof:name":"Secret Harbour Waterboring & Reticulation Service",
    "wof:placetype":"venue"
},
  "geometry": {"coordinates":[115.763062,-32.407482],"type":"Point"}
}