{
  "type": "Feature",
  "properties": {
    "iso:country":"AU",
    "sg:address":"P.O. Box 3120 Rundle Mall",
    "sg:city":"Adelaide",
    "sg:classifiers":[
        {
            "category":"Organizations",
            "subcategory":"Professional Association",
            "type":"Services"
        }
    ],
    "sg:phone":"+61 1300 788 209",
    "sg:postcode":"5000",
    "sg:province":"SA",
    "sg:tags":[
        "web",
        "internet"
    ],
    "wof:name":"Geek Support",
    "wof:placetype":"venue"
},
  "geometry": {"coordinates":[138.600097656,-34.9229545593],"type":"Point"}
}