{
  "type": "Feature",
  "properties": {
    "addr:full":"5 Bartlett St Noosaville QLD 4566",
    "addr:housenumber":"5",
    "addr:postcode":"4566",
    "addr:street":"Bartlett St",
    "iso:country":"AU",
    "sg:address":"5 Bartlett St",
    "sg:city":"Noosaville",
    "sg:classifiers":[
        {
            "category":"Retail",
            "subcategory":"Storage",
            "type":"Services"
        }
    ],
    "sg:phone":"+61 7 5474 2923",
    "sg:postcode":"4566",
    "sg:province":"QLD",
    "wof:name":"Luxury Lock-Up Storage",
    "wof:placetype":"venue"
},
  "geometry": {"coordinates":[153.042144775,-26.4148044586],"type":"Point"}
}