{
  "type": "Feature",
  "properties": {
    "addr:full":"23- 27 Wellington St Windsor VIC 3181",
    "addr:housenumber":"27",
    "addr:postcode":"3181",
    "addr:street":"Wellington St",
    "iso:country":"AU",
    "sg:address":"23- 27 Wellington St",
    "sg:city":"Windsor",
    "sg:classifiers":[
        {
            "category":"Utilities",
            "subcategory":"Telephone",
            "type":"Services"
        }
    ],
    "sg:phone":"+61 3 9520 2666",
    "sg:postcode":"3181",
    "sg:province":"VIC",
    "sg:tags":[
        "equipment",
        "system"
    ],
    "wof:name":"NSC - Northshore Connections",
    "wof:placetype":"venue"
},
  "geometry": {"coordinates":[144.984573364,-37.8563117981],"type":"Point"}
}