{
  "type": "Feature",
  "properties": {
    "addr:full":"Cooper Rd Birrong NSW 2143",
    "addr:postcode":"2143",
    "addr:street":"Cooper Rd",
    "iso:country":"AU",
    "sg:address":"Cooper Rd",
    "sg:city":"Birrong",
    "sg:classifiers":[
        {
            "category":"Education",
            "subcategory":"School",
            "type":"Public Place"
        }
    ],
    "sg:phone":"+61 2 9644 5057",
    "sg:postcode":"2143",
    "sg:province":"NSW",
    "sg:tags":[
        "state",
        "-",
        "nsw"
    ],
    "wof:name":"Birrong Girls' High School",
    "wof:placetype":"venue"
},
  "geometry": {"coordinates":[151.02650451700001,-33.8927116394],"type":"Point"}
}