{
  "type": "Feature",
  "properties": {
    "addr:full":"14 Young St Port Augusta SA 5700",
    "addr:housenumber":"14",
    "addr:postcode":"5700",
    "addr:street":"Young St",
    "iso:country":"AU",
    "sg:address":"14 Young St",
    "sg:city":"Port Augusta",
    "sg:classifiers":[
        {
            "category":"Home & Garden",
            "subcategory":"Carpets & Floor Coverings",
            "type":"Retail Goods"
        }
    ],
    "sg:phone":"+61 8 8642 5433",
    "sg:postcode":"5700",
    "sg:province":"SA",
    "wof:name":"Solomons Flooring",
    "wof:placetype":"venue"
},
  "geometry": {"coordinates":[137.76431274399999,-32.4894218445],"type":"Point"}
}