{
  "type": "Feature",
  "properties": {
    "iso:country":"AU",
    "sg:address":"237 Rocky Point Rd",
    "sg:city":"Ramsgate",
    "sg:classifiers":[
        {
            "category":"Shopping",
            "subcategory":"Bicycles & Sporting Goods",
            "type":"Retail Goods"
        }
    ],
    "sg:phone":"+61 2 9529 2044",
    "sg:postcode":"2217",
    "sg:province":"NSW",
    "sg:tags":[
        "chemical",
        "equipment",
        "pool",
        "swimming"
    ],
    "wof:name":"Swimart Pool & Spa Services",
    "wof:placetype":"venue"
},
  "geometry": {"coordinates":[151.135971,-33.984917],"type":"Point"}
}