{
  "type": "Feature",
  "properties": {
    "iso:country":"AU",
    "sg:address":"22 Wyandra Crescent,",
    "sg:city":"Port Macquarie",
    "sg:classifiers":[
        {
            "category":"Health Services",
            "subcategory":"Health Practitioner",
            "type":"Services"
        }
    ],
    "sg:phone":"+61 2 6584 2734",
    "sg:postcode":"2444",
    "sg:province":"NSW",
    "sg:tags":[
        "physiotherapist"
    ],
    "wof:name":"Fizzsport Physiotherapy",
    "wof:placetype":"venue"
},
  "geometry": {"coordinates":[152.906509,-31.442259],"type":"Point"}
}