{
  "type": "Feature",
  "properties": {
    "addr:full":"111 Yarragon Rd Leongatha VIC 3953",
    "addr:housenumber":"111",
    "addr:postcode":"3953",
    "addr:street":"Yarragon Rd",
    "iso:country":"AU",
    "sg:address":"111 Yarragon Rd",
    "sg:city":"Leongatha",
    "sg:classifiers":[
        {
            "category":"Retail",
            "subcategory":"Repair Shop",
            "type":"Services"
        }
    ],
    "sg:phone":"+61 3 5662 2229",
    "sg:postcode":"3953",
    "sg:province":"VIC",
    "sg:tags":[
        "upholsterer"
    ],
    "wof:name":"Dinky Di",
    "wof:placetype":"venue"
},
  "geometry": {"coordinates":[145.950775147,-38.4682388306],"type":"Point"}
}