{
  "type": "Feature",
  "properties": {
    "iso:country":"AU",
    "sg:address":"33 HArold St",
    "sg:city":"Ascot Vale",
    "sg:classifiers":[
        {
            "category":"Real Estate",
            "subcategory":"Architect",
            "type":"Services"
        }
    ],
    "sg:phone":"+61 3 9370 3995",
    "sg:postcode":"3032",
    "sg:province":"VIC",
    "wof:name":"Rudolf Arends Architect & Building Consultant",
    "wof:placetype":"venue"
},
  "geometry": {"coordinates":[144.900772,-37.772755],"type":"Point"}
}