{
  "type": "Feature",
  "properties": {
    "addr:full":"61 Canterbury Ave Trinity Gardens SA 5068",
    "addr:housenumber":"61",
    "addr:postcode":"5068",
    "addr:street":"Canterbury Ave Trinity Gardens",
    "iso:country":"AU",
    "sg:address":"61 Canterbury Ave",
    "sg:city":"Trinity Gardens",
    "sg:classifiers":[
        {
            "category":"Building & Trades",
            "subcategory":"Construction",
            "type":"Services"
        }
    ],
    "sg:phone":"+61 8 8332 8126",
    "sg:postcode":"5068",
    "sg:province":"SA",
    "sg:tags":[
        "polishing",
        "sanding",
        "floor"
    ],
    "wof:name":"All In One Services",
    "wof:placetype":"venue"
},
  "geometry": {"coordinates":[138.64689636200001,-34.9086685181],"type":"Point"}
}