{
  "type": "Feature",
  "properties": {
    "iso:country":"AU",
    "sg:address":"54 Synnot St",
    "sg:city":"Werribee",
    "sg:classifiers":[
        {
            "category":"Communications",
            "subcategory":"Film & Video Production",
            "type":"Services"
        }
    ],
    "sg:phone":"+61 3 9731 1175",
    "sg:postcode":"3030",
    "sg:province":"VIC",
    "sg:tags":[
        "dvd",
        "library"
    ],
    "wof:name":"Video Ezy",
    "wof:placetype":"venue"
},
  "geometry": {"coordinates":[144.66001900000001,-37.903336],"type":"Point"}
}