{
  "type": "Feature",
  "properties": {
    "addr:full":"Cnr Hume Hwy & Kiewa St Albury NSW 2640",
    "addr:postcode":"2640",
    "addr:street":"Cnr Hume Hwy & Kiewa St",
    "iso:country":"AU",
    "sg:address":"Cnr Hume Hwy & Kiewa St",
    "sg:city":"Albury",
    "sg:classifiers":[
        {
            "category":"Shopping",
            "subcategory":"Mobile Phones",
            "type":"Retail Goods"
        }
    ],
    "sg:phone":"+61 2 6041 4411",
    "sg:postcode":"2640",
    "sg:province":"NSW",
    "sg:tags":[
        "telephone",
        "accessory"
    ],
    "wof:name":"Optus World",
    "wof:placetype":"venue"
},
  "geometry": {"coordinates":[146.91807556099999,-36.0676994324],"type":"Point"}
}