{
  "type": "Feature",
  "properties": {
    "iso:country":"AU",
    "sg:address":"Ste 8/ 3",
    "sg:city":"Benjamin Way Rockingham",
    "sg:classifiers":[
        {
            "category":"Personal",
            "type":"Services"
        }
    ],
    "sg:phone":"+61 8 9592 6486",
    "sg:postcode":"6168",
    "sg:province":"WA",
    "sg:tags":[
        "reducing",
        "treatment",
        "weight"
    ],
    "wof:name":"Natural Way (WA) Rockingham",
    "wof:placetype":"venue"
},
  "geometry": {"coordinates":[115.734268,-32.279724],"type":"Point"}
}