{
  "type": "Feature",
  "properties": {
    "addr:full":"1 - 9 Marriner St Colac VIC 3250",
    "addr:housenumber":"9",
    "addr:postcode":"3250",
    "addr:street":"Marriner St",
    "iso:country":"AU",
    "sg:address":"1 - 9 Marriner St",
    "sg:city":"Colac",
    "sg:classifiers":[
        {
            "category":"Wholesale",
            "subcategory":"Farm Supplies",
            "type":"Manufacturing & Wholesale Goods"
        }
    ],
    "sg:phone":"+61 3 5231 6644",
    "sg:postcode":"3250",
    "sg:province":"VIC",
    "sg:tags":[
        "feed",
        "supplement",
        "stock"
    ],
    "wof:name":"Teangi Stock Feeds",
    "wof:placetype":"venue"
},
  "geometry": {"coordinates":[143.61203,-38.330631],"type":"Point"}
}