{
  "type": "Feature",
  "properties": {
    "addr:full":"Perouse Medical Centre 84 Perouse Rd Randwick NSW 2031",
    "addr:housenumber":"84",
    "addr:postcode":"2031",
    "addr:street":"Perouse Rd",
    "iso:country":"AU",
    "sg:address":"Perouse Medical Centre 84 Perouse Rd",
    "sg:city":"Randwick",
    "sg:classifiers":[
        {
            "category":"Health Services",
            "subcategory":"Doctor",
            "type":"Services"
        }
    ],
    "sg:phone":"+61 2 9398 5744",
    "sg:postcode":"2031",
    "sg:province":"NSW",
    "sg:tags":[
        "medical",
        "practitioner"
    ],
    "wof:name":"Kevin J B R",
    "wof:placetype":"venue"
},
  "geometry": {"coordinates":[151.24296569800001,-33.9215087891],"type":"Point"}
}