{
  "type": "Feature",
  "properties": {
    "iso:country":"AU",
    "sg:address":"22 Prospect St",
    "sg:city":"Fortitude Valley",
    "sg:classifiers":[
        {
            "category":"Building & Trades",
            "subcategory":"Plumbing",
            "type":"Services"
        }
    ],
    "sg:phone":"+61 7 3252 2015",
    "sg:postcode":"4006",
    "sg:province":"QLD",
    "sg:tags":[
        "plumber",
        "gasfitters"
    ],
    "wof:name":"Qld Plumbing",
    "wof:placetype":"venue"
},
  "geometry": {"coordinates":[153.037765503,-27.4514884949],"type":"Point"}
}