{
  "type": "Feature",
  "properties": {
    "addr:full":"PO Box 128 Lakemba NSW 2195",
    "addr:postcode":"2195",
    "iso:country":"AU",
    "sg:address":"PO Box 128",
    "sg:city":"Lakemba",
    "sg:classifiers":[
        {
            "category":"Social Services",
            "subcategory":"Adult Care",
            "type":"Services"
        }
    ],
    "sg:phone":"+61 2 9150 6366",
    "sg:postcode":"2195",
    "sg:province":"NSW",
    "sg:tags":[
        "towing"
    ],
    "wof:name":"M5 Towing",
    "wof:placetype":"venue"
},
  "geometry": {"coordinates":[151.07754499999999,-33.920731],"type":"Point"}
}