{
  "type": "Feature",
  "properties": {
    "iso:country":"AU",
    "sg:address":"St Francis Drive, Leichardt Medical Centre",
    "sg:city":"Moranbah",
    "sg:classifiers":[
        {
            "category":"Health Services",
            "subcategory":"Optometrist",
            "type":"Services"
        }
    ],
    "sg:phone":"+61 7 4941 8562",
    "sg:postcode":"4744",
    "sg:province":"QLD",
    "wof:name":"Central Highlands Optical",
    "wof:placetype":"venue"
},
  "geometry": {"coordinates":[148.04434204099999,-22.0015354156],"type":"Point"}
}