{
  "type": "Feature",
  "properties": {
    "iso:country":"AU",
    "sg:address":"116- 122 Somerton Rd",
    "sg:city":"Somerton",
    "sg:classifiers":[
        {
            "category":"Home & Garden",
            "subcategory":"Garden Supply",
            "type":"Retail Goods"
        }
    ],
    "sg:phone":"+61 3 9305 1441",
    "sg:postcode":"3062",
    "sg:province":"VIC",
    "sg:tags":[
        "equipment"
    ],
    "wof:name":"Roxburgh Park Garden Supplies",
    "wof:placetype":"venue"
},
  "geometry": {"coordinates":[144.93971252399999,-37.6417961121],"type":"Point"}
}