{
  "type": "Feature",
  "properties": {
    "addr:full":"Westfield Shoppingtown Hamilton Rd Chermside QLD 4032",
    "addr:postcode":"qld 4032",
    "addr:street":"Hamilton Rd",
    "iso:country":"AU",
    "sg:address":"Westfield Shoppingtown Hamilton Rd",
    "sg:city":"Chermside",
    "sg:classifiers":[
        {
            "category":"Shopping",
            "subcategory":"Shoes",
            "type":"Retail Goods"
        }
    ],
    "sg:phone":"+61 1800 651 185",
    "sg:postcode":"4032",
    "sg:province":"QLD",
    "sg:tags":[
        "footwear"
    ],
    "wof:name":"Clarks",
    "wof:placetype":"venue"
},
  "geometry": {"coordinates":[153.03396599999999,-27.386354],"type":"Point"}
}