{
  "type": "Feature",
  "properties": {
    "addr:full":"69 Derby St Silverwater NSW 2128",
    "addr:housenumber":"69",
    "addr:postcode":"2128",
    "addr:street":"Derby St",
    "iso:country":"AU",
    "sg:address":"69 Derby St",
    "sg:city":"Silverwater",
    "sg:classifiers":[
        {
            "category":"Manufacturing",
            "subcategory":"Retail Goods",
            "type":"Manufacturing & Wholesale Goods"
        }
    ],
    "sg:phone":"+61 2 9737 9797",
    "sg:postcode":"2128",
    "sg:province":"NSW",
    "sg:tags":[
        "merchant",
        "pump",
        "mfrs"
    ],
    "wof:name":"Kerrick",
    "wof:placetype":"venue"
},
  "geometry": {"coordinates":[151.04591369600001,-33.8372955322],"type":"Point"}
}