{
  "type": "Feature",
  "properties": {
    "addr:full":"Factory 2, 395 Old Geelong Road Hoppers Crossing VIC 3029",
    "addr:housenumber":"395",
    "addr:postcode":"3029",
    "addr:street":"Old Geelong Road",
    "iso:country":"AU",
    "sg:address":"Factory 2, 395 Old Geelong Road",
    "sg:city":"Hoppers Crossing",
    "sg:classifiers":[
        {
            "category":"Retail",
            "subcategory":"Auto Repair",
            "type":"Services"
        }
    ],
    "sg:phone":"+61 3 9360 0360",
    "sg:postcode":"3029",
    "sg:province":"VIC",
    "sg:tags":[
        "wheel",
        "balancing",
        "alignment"
    ],
    "wof:name":"All Affordable Tyres",
    "wof:placetype":"venue"
},
  "geometry": {"coordinates":[144.72889699999999,-37.869793],"type":"Point"}
}