{
  "type": "Feature",
  "properties": {
    "addr:full":"25 Wynnstay Rd Mt Eliza VIC 3930",
    "addr:housenumber":"25",
    "addr:postcode":"3930",
    "addr:street":"Wynnstay Rd",
    "iso:country":"AU",
    "sg:address":"25 Wynnstay Rd",
    "sg:city":"Mt Eliza",
    "sg:classifiers":[
        {
            "category":"Building & Trades",
            "subcategory":"Construction",
            "type":"Services"
        }
    ],
    "sg:phone":"+61 3 9787 5070",
    "sg:postcode":"3930",
    "sg:province":"VIC",
    "sg:tags":[
        "brick",
        "paving"
    ],
    "wof:name":"Native Landscapes Of Mt Eliza",
    "wof:placetype":"venue"
},
  "geometry": {"coordinates":[145.094314575,-38.206943512],"type":"Point"}
}