{
  "type": "Feature",
  "properties": {
    "addr:full":"262 Cross Rd Kings Park SA 5034",
    "addr:housenumber":"262",
    "addr:postcode":"5034",
    "addr:street":"Cross Rd",
    "iso:country":"AU",
    "sg:address":"262 Cross Rd",
    "sg:city":"Kings Park",
    "sg:classifiers":[
        {
            "category":"Social Services",
            "subcategory":"Retirement Home",
            "type":"Services"
        }
    ],
    "sg:phone":"+61 8 8299 9055",
    "sg:postcode":"5034",
    "sg:province":"SA",
    "sg:tags":[
        "village"
    ],
    "wof:name":"Auscare Retirement",
    "wof:placetype":"venue"
},
  "geometry": {"coordinates":[138.59211730999999,-34.9660606384],"type":"Point"}
}