{
  "type": "Feature",
  "properties": {
    "iso:country":"AU",
    "sg:address":"Kiosk 10, Baulkham Hill S/C Windsor Rd",
    "sg:city":"Baulkham Hills",
    "sg:classifiers":[
        {
            "category":"Shopping",
            "subcategory":"Mobile Phones",
            "type":"Retail Goods"
        }
    ],
    "sg:phone":"+61 2 9686 3299",
    "sg:postcode":"2153",
    "sg:province":"NSW",
    "sg:tags":[
        "telephone",
        "accessory"
    ],
    "wof:name":"TeleChoice",
    "wof:placetype":"venue"
},
  "geometry": {"coordinates":[150.989624023,-33.7578811646],"type":"Point"}
}