{
  "type": "Feature",
  "properties": {
    "addr:full":"143 Henley Beach Rd Mile End SA 5031",
    "addr:housenumber":"143",
    "addr:postcode":"5031",
    "addr:street":"Henley Beach Rd",
    "iso:country":"AU",
    "sg:address":"143 Henley Beach Rd",
    "sg:city":"Mile End",
    "sg:classifiers":[
        {
            "category":"Real Estate",
            "subcategory":"Real Estate Agent",
            "type":"Services"
        }
    ],
    "sg:phone":"+61 8 8159 8500",
    "sg:postcode":"5031",
    "sg:province":"SA",
    "wof:name":"RE\\\\MAX Home Centre Realty",
    "wof:placetype":"venue"
},
  "geometry": {"coordinates":[138.564086914,-34.9242134094],"type":"Point"}
}