{
  "type": "Feature",
  "properties": {
    "addr:full":"2 Bellevue Drv Korora NSW 2450",
    "addr:housenumber":"2",
    "addr:postcode":"2450",
    "addr:street":"Bellevue Drv",
    "iso:country":"AU",
    "sg:address":"2 Bellevue Drv",
    "sg:city":"Korora",
    "sg:classifiers":[
        {
            "category":"Arts & Performance",
            "subcategory":"Dance",
            "type":"Entertainment"
        }
    ],
    "sg:phone":"+61 431 455 190",
    "sg:postcode":"2450",
    "sg:province":"NSW",
    "sg:tags":[
        "theatrical",
        "ballet",
        "tuition"
    ],
    "wof:name":"Francesca Boros",
    "wof:placetype":"venue"
},
  "geometry": {"coordinates":[153.13682600000001,-30.257435],"type":"Point"}
}