{
  "type": "Feature",
  "properties": {
    "iso:country":"AU",
    "sg:address":"2 Bellevue Drv",
    "sg:city":"Korora",
    "sg:classifiers":[
        {
            "category":"Arts & Performance",
            "subcategory":"Dance",
            "type":"Entertainment"
        }
    ],
    "sg:phone":"+61 431 455 190",
    "sg:postcode":"2450",
    "sg:province":"NSW",
    "sg:tags":[
        "theatrical",
        "ballet",
        "tuition"
    ],
    "wof:name":"Francesca Boros",
    "wof:placetype":"venue"
},
  "geometry": {"coordinates":[153.136826,-30.257435],"type":"Point"}
}