{
  "type": "Feature",
  "properties": {
    "addr:full":"13 Stoke St New Town TAS 7008",
    "addr:housenumber":"13",
    "addr:postcode":"7008",
    "addr:street":"Stoke St",
    "iso:country":"AU",
    "sg:address":"13 Stoke St",
    "sg:city":"New Town",
    "sg:classifiers":[
        {
            "category":"Retail",
            "subcategory":"Auto Rental",
            "type":"Services"
        }
    ],
    "sg:phone":"+61 3 6228 2745",
    "sg:postcode":"7008",
    "sg:province":"TAS",
    "sg:tags":[
        "chauffeur",
        "car",
        "hire",
        "driven",
        "limousine"
    ],
    "wof:name":"Clark Classic Cars",
    "wof:placetype":"venue"
},
  "geometry": {"coordinates":[147.31265258799999,-42.8642654419],"type":"Point"}
}