{
  "type": "Feature",
  "properties": {
    "addr:full":"78 Wommin Bay Rd Kingscliff NSW 2487",
    "addr:housenumber":"78",
    "addr:postcode":"2487",
    "addr:street":"Wommin Bay Rd",
    "iso:country":"AU",
    "sg:address":"78 Wommin Bay Rd",
    "sg:city":"Kingscliff",
    "sg:classifiers":[
        {
            "category":"Health Services",
            "subcategory":"Chiropractor",
            "type":"Services"
        }
    ],
    "sg:phone":"+61 2 6674 4032",
    "sg:postcode":"2487",
    "sg:province":"NSW",
    "wof:name":"Tweed Coast Chiropractic",
    "wof:placetype":"venue"
},
  "geometry": {"coordinates":[153.57818603499999,-28.2569828033],"type":"Point"}
}