{
  "type": "Feature",
  "properties": {
    "addr:full":"948 Botany St Mascot NSW 2020",
    "addr:housenumber":"948",
    "addr:postcode":"2020",
    "addr:street":"Botany St",
    "iso:country":"AU",
    "sg:address":"948 Botany St",
    "sg:city":"Mascot",
    "sg:classifiers":[
        {
            "category":"Shopping",
            "subcategory":"Clothing, Apparel, & Fashions",
            "type":"Retail Goods"
        }
    ],
    "sg:phone":"+61 2 9693 1631",
    "sg:postcode":"2020",
    "sg:province":"NSW",
    "sg:tags":[
        "recycled",
        "clothing"
    ],
    "wof:name":"St Vincent De Paul Society",
    "wof:placetype":"venue"
},
  "geometry": {"coordinates":[151.194290161,-33.9304847717],"type":"Point"}
}