{
  "type": "Feature",
  "properties": {
    "addr:full":"4a/ 20 Brex Crt Reservoir VIC 3073",
    "addr:housenumber":"4a / 20",
    "addr:postcode":"3073",
    "addr:street":"Brex Crt",
    "iso:country":"AU",
    "sg:address":"4a/ 20 Brex Crt",
    "sg:city":"Reservoir",
    "sg:classifiers":[
        {
            "category":"Utilities",
            "type":"Services"
        }
    ],
    "sg:phone":"+61 3 9460 2679",
    "sg:postcode":"3073",
    "sg:province":"VIC",
    "sg:tags":[
        "refrigeration",
        "industrial",
        "commercial",
        "retail"
    ],
    "wof:name":"H & P Refrigeration Engineers Pty Ltd",
    "wof:placetype":"venue"
},
  "geometry": {"coordinates":[144.982620239,-37.7085113525],"type":"Point"}
}