{
  "type": "Feature",
  "properties": {
    "iso:country":"AU",
    "sg:address":"66 Albert Rd",
    "sg:city":"South Melbourne",
    "sg:classifiers":[
        {
            "category":"Banks & Credit Unions",
            "subcategory":"Financial Services",
            "type":"Services"
        }
    ],
    "sg:phone":"+61 3 9690 2800",
    "sg:postcode":"3205",
    "sg:province":"VIC",
    "sg:tags":[
        "planning"
    ],
    "wof:name":"Lifespan Financial Planning Pty Ltd",
    "wof:placetype":"venue"
},
  "geometry": {"coordinates":[144.971085,-37.834663],"type":"Point"}
}