{
  "type": "Feature",
  "properties": {
    "addr:full":"103 Mort St Toowoomba QLD 4350",
    "addr:housenumber":"103",
    "addr:postcode":"4350",
    "addr:street":"Mort St",
    "iso:country":"AU",
    "sg:address":"103 Mort St",
    "sg:city":"Toowoomba",
    "sg:classifiers":[
        {
            "category":"Building & Trades",
            "subcategory":"Construction",
            "type":"Services"
        }
    ],
    "sg:phone":"+61 7 3875 1130",
    "sg:postcode":"4350",
    "sg:province":"QLD",
    "sg:tags":[
        "home",
        "air conditioning"
    ],
    "wof:name":"Breezair",
    "wof:placetype":"venue"
},
  "geometry": {"coordinates":[151.94987499999999,-27.553223],"type":"Point"}
}