{
  "type": "Feature",
  "properties": {
    "iso:country":"AU",
    "sg:address":"Suite 34 Mount Medical Centre, 146 Mounts Bay Rd",
    "sg:city":"Perth",
    "sg:classifiers":[
        {
            "category":"Health Services",
            "subcategory":"Doctor",
            "type":"Services"
        }
    ],
    "sg:phone":"+61 8 9481 5171",
    "sg:postcode":"6000",
    "sg:province":"WA",
    "sg:tags":[
        "medical",
        "practitioner"
    ],
    "wof:name":"Larbalestier Robert Dr",
    "wof:placetype":"venue"
},
  "geometry": {"coordinates":[115.848472595,-31.9553432465],"type":"Point"}
}