{
  "type": "Feature",
  "properties": {
    "iso:country":"AU",
    "sg:address":"Shop 16 East End Centre Cnr Parker & MacMillan Sts",
    "sg:city":"Ayr",
    "sg:classifiers":[
        {
            "category":"Deli",
            "type":"Food & Drink"
        }
    ],
    "sg:phone":"+61 7 4783 2622",
    "sg:postcode":"4807",
    "sg:province":"QLD",
    "sg:tags":[
        "delicatessen"
    ],
    "wof:name":"Dal Santo's Continental Deli",
    "wof:placetype":"venue"
},
  "geometry": {"coordinates":[147.407546997,-19.5751247406],"type":"Point"}
}