{
  "type": "Feature",
  "properties": {
    "iso:country":"AU",
    "sg:address":"1 Robert St",
    "sg:city":"Lalor",
    "sg:classifiers":[
        {
            "category":"Retail",
            "subcategory":"Driving School",
            "type":"Services"
        }
    ],
    "sg:phone":"+61 412 366 405",
    "sg:postcode":"3075",
    "sg:province":"VIC",
    "wof:name":"Dean T.S.Way",
    "wof:placetype":"venue"
},
  "geometry": {"coordinates":[145.12750244099999,-37.7171592712],"type":"Point"}
}