{
  "type": "Feature",
  "properties": {
    "addr:full":"Cnr North East & Grand Junction Rds Valley View SA 5093",
    "addr:postcode":"5093",
    "addr:street":"Cnr North East &",
    "iso:country":"AU",
    "sg:address":"Cnr North East & Grand Junction Rds",
    "sg:city":"Valley View",
    "sg:classifiers":[
        {
            "category":"Home & Garden",
            "subcategory":"Hardware",
            "type":"Retail Goods"
        }
    ],
    "sg:phone":"+61 8 8395 6611",
    "sg:postcode":"5093",
    "sg:province":"SA",
    "sg:tags":[
        "generating",
        "set",
        "generator"
    ],
    "wof:name":"Kennards Generator Hire",
    "wof:placetype":"venue"
},
  "geometry": {"coordinates":[138.67106628400001,-34.8446388245],"type":"Point"}
}