{
  "type": "Feature",
  "properties": {
    "addr:full":"32 Ariostoc Rd Glen Waverley VIC 3150",
    "addr:housenumber":"32",
    "addr:postcode":"3150",
    "addr:street":"Ariostoc Rd",
    "iso:country":"AU",
    "sg:address":"32 Ariostoc Rd",
    "sg:city":"Glen Waverley",
    "sg:classifiers":[
        {
            "category":"Building & Trades",
            "subcategory":"Construction",
            "type":"Services"
        }
    ],
    "sg:phone":"+61 400 999 321",
    "sg:postcode":"3150",
    "sg:province":"VIC",
    "sg:tags":[
        "concrete",
        "contractor"
    ],
    "wof:name":"The Kerb Crew",
    "wof:placetype":"venue"
},
  "geometry": {"coordinates":[145.15751648,-37.887928009],"type":"Point"}
}