{
  "type": "Feature",
  "properties": {
    "addr:full":"PO Box 1905 Mandurah WA 6210",
    "addr:postcode":"6210",
    "iso:country":"AU",
    "sg:address":"PO Box 1905",
    "sg:city":"Mandurah",
    "sg:classifiers":[
        {
            "category":"Building & Trades",
            "subcategory":"Construction",
            "type":"Services"
        }
    ],
    "sg:phone":"+61 418 902 615",
    "sg:postcode":"6210",
    "sg:province":"WA",
    "sg:tags":[
        "brick",
        "paving"
    ],
    "wof:name":"Brickpaving & Landscaping",
    "wof:placetype":"venue"
},
  "geometry": {"coordinates":[115.78473700000001,-32.509258],"type":"Point"}
}