{
  "type": "Feature",
  "properties": {
    "addr:full":"22 Gorge Rd Trevallyn TAS 7250",
    "addr:housenumber":"22",
    "addr:postcode":"7250",
    "addr:street":"Gorge Rd",
    "iso:country":"AU",
    "sg:address":"22 Gorge Rd",
    "sg:city":"Trevallyn",
    "sg:classifiers":[
        {
            "category":"Personal",
            "subcategory":"Beauty Salon",
            "type":"Services"
        }
    ],
    "sg:phone":"+61 3 6331 4293",
    "sg:postcode":"7250",
    "sg:province":"TAS",
    "sg:tags":[
        "hairdresser"
    ],
    "wof:name":"Trevallyn Hair & Beauty Salon",
    "wof:placetype":"venue"
},
  "geometry": {"coordinates":[147.118850708,-41.4355545044],"type":"Point"}
}