{
  "type": "Feature",
  "properties": {
    "addr:full":"72 Duke St Daylesford VIC 3460",
    "addr:housenumber":"72",
    "addr:postcode":"3460",
    "addr:street":"Duke St",
    "iso:country":"AU",
    "sg:address":"72 Duke St",
    "sg:city":"Daylesford",
    "sg:classifiers":[
        {
            "category":"Professional",
            "subcategory":"Engineering",
            "type":"Services"
        }
    ],
    "sg:phone":"+61 3 5348 3851",
    "sg:postcode":"3460",
    "sg:province":"VIC",
    "sg:tags":[
        "consulting",
        "engineer"
    ],
    "wof:name":"Brotchie Robert & Associates Pty Ltd",
    "wof:placetype":"venue"
},
  "geometry": {"coordinates":[144.14227294899999,-37.3501091003],"type":"Point"}
}