{
  "type": "Feature",
  "properties": {
    "iso:country":"AU",
    "sg:address":"23 Catalina Ave",
    "sg:city":"Parafield Gardens",
    "sg:classifiers":[
        {
            "category":"Health Services",
            "subcategory":"Doctor",
            "type":"Services"
        }
    ],
    "sg:phone":"+61 8 8258 1137",
    "sg:postcode":"5107",
    "sg:province":"SA",
    "sg:tags":[
        "medical",
        "practitioner"
    ],
    "wof:name":"Sim David S L Dr",
    "wof:placetype":"venue"
},
  "geometry": {"coordinates":[138.614868164,-34.7887496948],"type":"Point"}
}