{
  "type": "Feature",
  "properties": {
    "iso:country":"AU",
    "sg:address":"473 New Canterbury Rd",
    "sg:city":"Dulwich Hill",
    "sg:classifiers":[
        {
            "category":"Autos & Motor Vehicles",
            "subcategory":"Fuel & Gas Station",
            "type":"Retail Goods"
        }
    ],
    "sg:phone":"+61 2 9569 7778",
    "sg:postcode":"2203",
    "sg:province":"NSW",
    "wof:name":"Ampol",
    "wof:placetype":"venue"
},
  "geometry": {"coordinates":[151.141113,-33.903679],"type":"Point"}
}