{
  "type": "Feature",
  "properties": {
    "addr:full":"198 Old Prospect Rd Greystanes NSW 2145",
    "addr:housenumber":"198",
    "addr:postcode":"2145",
    "addr:street":"Old Prospect Rd",
    "iso:country":"AU",
    "sg:address":"198 Old Prospect Rd",
    "sg:city":"Greystanes",
    "sg:classifiers":[
        {
            "category":"Education",
            "subcategory":"School",
            "type":"Public Place"
        }
    ],
    "sg:phone":"+61 2 9636 1800",
    "sg:postcode":"2145",
    "sg:province":"NSW",
    "sg:tags":[
        "boy"
    ],
    "wof:name":"St.Pauls Catholic College",
    "wof:placetype":"venue"
},
  "geometry": {"coordinates":[150.95161438,-33.8185462952],"type":"Point"}
}