{
  "type": "Feature",
  "properties": {
    "iso:country":"AU",
    "sg:address":"Quarry Rd",
    "sg:city":"Murwillumbah",
    "sg:classifiers":[
        {
            "category":"Professional",
            "type":"Services"
        }
    ],
    "sg:phone":"+61 2 6672 8350",
    "sg:postcode":"2484",
    "sg:province":"NSW",
    "sg:tags":[
        "transport"
    ],
    "wof:name":"Shoobridge Transport",
    "wof:placetype":"venue"
},
  "geometry": {"coordinates":[153.41481018100001,-28.3334445953],"type":"Point"}
}