{
  "type": "Feature",
  "properties": {
    "addr:full":"Bldg1/ 22 Don Rd Devonport TAS 7310",
    "addr:housenumber":"22",
    "addr:postcode":"7310",
    "addr:street":"Don Rd",
    "iso:country":"AU",
    "sg:address":"Bldg1/ 22 Don Rd",
    "sg:city":"Devonport",
    "sg:classifiers":[
        {
            "category":"Autos & Motor Vehicles",
            "subcategory":"Automobile Sales",
            "type":"Retail Goods"
        }
    ],
    "sg:phone":"+61 3 6424 2800",
    "sg:postcode":"7310",
    "sg:province":"TAS",
    "sg:tags":[
        "car",
        "used"
    ],
    "wof:name":"Northwest Auto Wholesalers",
    "wof:placetype":"venue"
},
  "geometry": {"coordinates":[146.33784484899999,-41.1796913147],"type":"Point"}
}