{
  "type": "Feature",
  "properties": {
    "addr:full":"38 Nepean Hwy Mentone VIC 3194",
    "addr:housenumber":"38",
    "addr:postcode":"3194",
    "addr:street":"Nepean Hwy",
    "iso:country":"AU",
    "sg:address":"38 Nepean Hwy",
    "sg:city":"Mentone",
    "sg:classifiers":[
        {
            "category":"Home & Garden",
            "subcategory":"Hardware",
            "type":"Retail Goods"
        }
    ],
    "sg:phone":"+61 3 9584 9864",
    "sg:postcode":"3194",
    "sg:province":"VIC",
    "sg:tags":[
        "plumber",
        "supply"
    ],
    "wof:name":"Reece Pty Ltd",
    "wof:placetype":"venue"
},
  "geometry": {"coordinates":[145.06585693400001,-37.9762992859],"type":"Point"}
}