{
  "type": "Feature",
  "properties": {
    "iso:country":"AU",
    "sg:address":"Unit 1 24 Trade Rd",
    "sg:city":"Malaga",
    "sg:classifiers":[
        {
            "category":"Shopping",
            "subcategory":"Gifts & Souvenirs",
            "type":"Retail Goods"
        }
    ],
    "sg:phone":"+61 8 9248 1899",
    "sg:postcode":"6090",
    "sg:province":"WA",
    "sg:tags":[
        "shop",
        "supply"
    ],
    "wof:name":"Double A Trading",
    "wof:placetype":"venue"
},
  "geometry": {"coordinates":[115.895462036,-31.8569297791],"type":"Point"}
}