{
  "type": "Feature",
  "properties": {
    "iso:country":"AU",
    "sg:address":"371 King St",
    "sg:city":"Melbourne",
    "sg:classifiers":[
        {
            "category":"Building & Trades",
            "subcategory":"Construction",
            "type":"Services"
        }
    ],
    "sg:phone":"+61 3 9555 4911",
    "sg:postcode":"3000",
    "sg:province":"VIC",
    "sg:tags":[
        "window",
        "tinting"
    ],
    "wof:name":"Instant Tint",
    "wof:placetype":"venue"
},
  "geometry": {"coordinates":[144.95335388199999,-37.8115653992],"type":"Point"}
}