{
  "type": "Feature",
  "properties": {
    "addr:full":"Suite 1, 224- 238 George St Liverpool NSW 2170",
    "addr:housenumber":"224 238",
    "addr:postcode":"2170",
    "addr:street":"George St",
    "iso:country":"AU",
    "sg:address":"Suite 1, 224- 238 George St",
    "sg:city":"Liverpool",
    "sg:classifiers":[
        {
            "category":"Health Services",
            "subcategory":"Health Practitioner",
            "type":"Services"
        }
    ],
    "sg:phone":"+61 2 9672 1888",
    "sg:postcode":"2170",
    "sg:province":"NSW",
    "sg:tags":[
        "acupuncture"
    ],
    "wof:name":"Chen Acupuncture & Natural Therapies Centre",
    "wof:placetype":"venue"
},
  "geometry": {"coordinates":[150.92489624000001,-33.9235343933],"type":"Point"}
}