{
  "type": "Feature",
  "properties": {
    "addr:full":"96 Kinterbury Drv St Albans VIC 3021",
    "addr:housenumber":"96",
    "addr:postcode":"3021",
    "addr:street":"Kinterbury Drv",
    "iso:country":"AU",
    "sg:address":"96 Kinterbury Drv St",
    "sg:city":"Albans",
    "sg:classifiers":[
        {
            "category":"Social Services",
            "subcategory":"Adult Care",
            "type":"Services"
        }
    ],
    "sg:phone":"+61 417 510 507",
    "sg:postcode":"3021",
    "sg:province":"VIC",
    "sg:tags":[
        "towing"
    ],
    "wof:name":"Deans Car Removal & Towing",
    "wof:placetype":"venue"
},
  "geometry": {"coordinates":[144.76362599999999,-37.738159],"type":"Point"}
}