{
  "type": "Feature",
  "properties": {
    "addr:full":"U 13&14/ George Turner House/ 11 McKay Gardns Turner ACT 2612",
    "addr:housenumber":"13 & 14 / george;11",
    "addr:postcode":"2612",
    "addr:street":"Mckay Gardns",
    "iso:country":"AU",
    "sg:address":"U 13&14/ George Turner House/ 11 McKay Gardns",
    "sg:city":"Turner",
    "sg:classifiers":[
        {
            "category":"Insurance",
            "subcategory":"Insurance Agent",
            "type":"Services"
        }
    ],
    "sg:phone":"+61 2 6257 6200",
    "sg:postcode":"2612",
    "sg:province":"ACT",
    "sg:tags":[
        "broker"
    ],
    "wof:name":"InsuraLife",
    "wof:placetype":"venue"
},
  "geometry": {"coordinates":[149.126556397,-35.2747383118],"type":"Point"}
}