{
  "type": "Feature",
  "properties": {
    "addr:full":"270 Carp St Bega NSW 2550",
    "addr:housenumber":"270",
    "addr:postcode":"2550",
    "addr:street":"Carp St",
    "iso:country":"AU",
    "sg:address":"270 Carp St",
    "sg:city":"Bega",
    "sg:classifiers":[
        {
            "category":"Communications",
            "type":"Services"
        }
    ],
    "sg:phone":"+61 2 6492 3000",
    "sg:postcode":"2550",
    "sg:province":"NSW",
    "sg:tags":[
        "equipment",
        "radio"
    ],
    "wof:name":"O&#039;Brien P J Electronics Pty Ltd",
    "wof:placetype":"venue"
},
  "geometry": {"coordinates":[149.84379577600001,-36.6742935181],"type":"Point"}
}