{
  "type": "Feature",
  "properties": {
    "addr:full":"87 Lord St Port Macquarie NSW 2444",
    "addr:housenumber":"87",
    "addr:postcode":"2444",
    "addr:street":"Lord St",
    "iso:country":"AU",
    "sg:address":"87 Lord St",
    "sg:city":"Port Macquarie",
    "sg:classifiers":[
        {
            "category":"Professional",
            "subcategory":"Engineering",
            "type":"Services"
        }
    ],
    "sg:phone":"+61 2 6583 5322",
    "sg:postcode":"2444",
    "sg:province":"NSW",
    "sg:tags":[
        "consulting",
        "engineer"
    ],
    "wof:name":"Walch & Roberts Consulting Engineers",
    "wof:placetype":"venue"
},
  "geometry": {"coordinates":[152.917633,-31.438646],"type":"Point"}
}