{
  "type": "Feature",
  "properties": {
    "iso:country":"AU",
    "sg:address":"U3/ 44 Barrett St",
    "sg:city":"Kensington",
    "sg:classifiers":[
        {
            "category":"Building & Trades",
            "subcategory":"Cleaning & Sanitation",
            "type":"Services"
        }
    ],
    "sg:phone":"+61 3 9372 5407",
    "sg:postcode":"3031",
    "sg:province":"VIC",
    "sg:tags":[
        "window"
    ],
    "wof:name":"Advanced Window Cleaning Services Pty Ltd",
    "wof:placetype":"venue"
},
  "geometry": {"coordinates":[144.934525,-37.798264],"type":"Point"}
}