{
  "type": "Feature",
  "properties": {
    "addr:full":"Unit 3 18 Overlord Pl Acacia Ridge QLD 4110",
    "addr:housenumber":"18",
    "addr:postcode":"4110",
    "addr:street":"Overlord Pl",
    "iso:country":"AU",
    "sg:address":"Unit 3 18 Overlord Pl",
    "sg:city":"Acacia Ridge",
    "sg:classifiers":[
        {
            "category":"Building & Trades",
            "subcategory":"Equipment Rental",
            "type":"Services"
        }
    ],
    "sg:phone":"+61 7 3272 1255",
    "sg:postcode":"4110",
    "sg:province":"QLD",
    "sg:tags":[
        "fitness"
    ],
    "wof:name":"The Fitness Generation Pty Ltd",
    "wof:placetype":"venue"
},
  "geometry": {"coordinates":[153.037353516,-27.5947856903],"type":"Point"}
}