{
  "type": "Feature",
  "properties": {
    "addr:full":"47768 South Coast Hwy Albany WA 6330",
    "addr:housenumber":"47768",
    "addr:postcode":"6330",
    "addr:street":"South Coast Hwy",
    "iso:country":"AU",
    "sg:address":"47768 South Coast Hwy",
    "sg:city":"Albany",
    "sg:classifiers":[
        {
            "category":"Farming",
            "subcategory":"Nursery",
            "type":"Manufacturing & Wholesale Goods"
        }
    ],
    "sg:phone":"+61 8 9841 3220",
    "sg:postcode":"6330",
    "sg:province":"WA",
    "wof:name":"Growmart Hydroponics",
    "wof:placetype":"venue"
},
  "geometry": {"coordinates":[117.824028015,-34.9987411499],"type":"Point"}
}