{
  "type": "Feature",
  "properties": {
    "iso:country":"AU",
    "sg:address":"52 Reservoir St",
    "sg:city":"Surry Hills",
    "sg:classifiers":[
        {
            "category":"Real Estate",
            "subcategory":"Architect",
            "type":"Services"
        }
    ],
    "sg:phone":"+61 2 9212 1055",
    "sg:postcode":"2010",
    "sg:province":"NSW",
    "wof:name":"Brenchley Architects",
    "wof:placetype":"venue"
},
  "geometry": {"coordinates":[151.20945739699999,-33.8811073303],"type":"Point"}
}