{
  "type": "Feature",
  "properties": {
    "addr:full":"Cnr Stafford Rd & Appleby St Stafford QLD 4053",
    "addr:postcode":"4053",
    "addr:street":"Stafford Rd & Appleby St",
    "iso:country":"AU",
    "sg:address":"Cnr Stafford Rd & Appleby St",
    "sg:city":"Stafford",
    "sg:classifiers":[
        {
            "category":"Autos & Motor Vehicles",
            "subcategory":"Fuel & Gas Station",
            "type":"Retail Goods"
        }
    ],
    "sg:phone":"+61 7 3356 7368",
    "sg:postcode":"4053",
    "sg:province":"QLD",
    "wof:name":"Mobil Oil Australia Pty Ltd",
    "wof:placetype":"venue"
},
  "geometry": {"coordinates":[153.007202148,-27.4091072083],"type":"Point"}
}