{
  "type": "Feature",
  "properties": {
    "addr:full":"92 Tamar St Ballina NSW 2478",
    "addr:housenumber":"92",
    "addr:postcode":"2478",
    "addr:street":"Tamar St",
    "iso:country":"AU",
    "sg:address":"92 Tamar St",
    "sg:city":"Ballina",
    "sg:classifiers":[
        {
            "category":"Food & Beverages",
            "subcategory":"Bakery",
            "type":"Retail Goods"
        }
    ],
    "sg:phone":"+61 2 6686 5219",
    "sg:postcode":"2478",
    "sg:province":"NSW",
    "sg:tags":[
        "baker"
    ],
    "wof:name":"Martin's Hot Bread Kitchen",
    "wof:placetype":"venue"
},
  "geometry": {"coordinates":[153.55613708499999,-28.8673439026],"type":"Point"}
}