{
  "type": "Feature",
  "properties": {
    "iso:country":"AU",
    "sg:address":"65 Victoria St",
    "sg:city":"Cardwell",
    "sg:classifiers":[
        {
            "category":"Banks & Credit Unions",
            "subcategory":"Investment Brokerage",
            "type":"Services"
        }
    ],
    "sg:phone":"+61 7 4066 8700",
    "sg:postcode":"4849",
    "sg:province":"QLD",
    "sg:tags":[
        "management",
        "property"
    ],
    "wof:name":"Hinchinbrook Real Estate",
    "wof:placetype":"venue"
},
  "geometry": {"coordinates":[146.02903699999999,-18.266903],"type":"Point"}
}