{
  "type": "Feature",
  "properties": {
    "addr:full":"37 Lingle St Robertson QLD 4109",
    "addr:housenumber":"37",
    "addr:postcode":"4109",
    "addr:street":"Lingle St",
    "iso:country":"AU",
    "sg:address":"37 Lingle St",
    "sg:city":"Robertson",
    "sg:classifiers":[
        {
            "category":"Building & Trades",
            "subcategory":"Construction",
            "type":"Services"
        }
    ],
    "sg:phone":"+61 7 3343 3454",
    "sg:postcode":"4109",
    "sg:province":"QLD",
    "sg:tags":[
        "earth",
        "excavating",
        "moving",
        "contractor"
    ],
    "wof:name":"Tuckey L M & J A",
    "wof:placetype":"venue"
},
  "geometry": {"coordinates":[153.06251525900001,-27.5624237061],"type":"Point"}
}