{
  "type": "Feature",
  "properties": {
    "addr:full":"6/ 17 Southern Cross Drv Ballina NSW 2478",
    "addr:housenumber":"/ 17",
    "addr:postcode":"2478",
    "addr:street":"Southern Cross Drv",
    "iso:country":"AU",
    "sg:address":"6/ 17 Southern Cross Drv",
    "sg:city":"Ballina",
    "sg:classifiers":[
        {
            "category":"Building & Trades",
            "subcategory":"Construction",
            "type":"Services"
        }
    ],
    "sg:phone":"+61 2 6686 6300",
    "sg:postcode":"2478",
    "sg:province":"NSW",
    "sg:tags":[
        "window",
        "tinting"
    ],
    "wof:name":"Mastertint",
    "wof:placetype":"venue"
},
  "geometry": {"coordinates":[153.556518555,-28.8520107269],"type":"Point"}
}