{
  "type": "Feature",
  "properties": {
    "addr:full":"44 High St Trentham VIC 3458",
    "addr:housenumber":"44",
    "addr:postcode":"3458",
    "addr:street":"High St",
    "iso:country":"AU",
    "sg:address":"44 High St",
    "sg:city":"Trentham",
    "sg:classifiers":[
        {
            "category":"Cafe",
            "type":"Food & Drink"
        }
    ],
    "sg:phone":"+61 3 5424 1730",
    "sg:postcode":"3458",
    "sg:province":"VIC",
    "wof:name":"Trentham Cafe",
    "wof:placetype":"venue"
},
  "geometry": {"coordinates":[144.32223510700001,-37.3887290955],"type":"Point"}
}