{
  "type": "Feature",
  "properties": {
    "addr:full":"Tuggerah Medical Cntr, 1050B Westfield Shoppingtown Tuggerah NSW 2259",
    "addr:housenumber":"1050b",
    "addr:postcode":"2259",
    "addr:street":"Westfield Shoppingtown",
    "iso:country":"AU",
    "sg:address":"Tuggerah Medical Cntr, 1050B Westfield Shoppingtown",
    "sg:city":"Tuggerah",
    "sg:classifiers":[
        {
            "category":"Health Services",
            "subcategory":"Doctor",
            "type":"Services"
        }
    ],
    "sg:phone":"+61 2 4353 5620",
    "sg:postcode":"2259",
    "sg:province":"NSW",
    "sg:tags":[
        "medical",
        "practitioner"
    ],
    "wof:name":"Mayne Laverty Pathology Collection Centres",
    "wof:placetype":"venue"
},
  "geometry": {"coordinates":[151.415557861,-33.306930542],"type":"Point"}
}