{
  "type": "Feature",
  "properties": {
    "iso:country":"AU",
    "sg:address":"Suite 1/ 738 Burke St",
    "sg:city":"Camberwell",
    "sg:classifiers":[
        {
            "category":"Professional",
            "subcategory":"Computer Services",
            "type":"Services"
        }
    ],
    "sg:phone":"+61 1300 765 436",
    "sg:postcode":"3124",
    "sg:province":"VIC",
    "sg:tags":[
        "consultant",
        "system"
    ],
    "wof:name":"Solisma Pty Ltd",
    "wof:placetype":"venue"
},
  "geometry": {"coordinates":[145.057937622,-37.8257484436],"type":"Point"}
}