{
  "type": "Feature",
  "properties": {
    "iso:country":"AU",
    "sg:address":"1 Austral St",
    "sg:city":"Kogarah",
    "sg:classifiers":[
        {
            "category":"Building & Trades",
            "subcategory":"Locksmith",
            "type":"Services"
        }
    ],
    "sg:phone":"+61 2 9588 4919",
    "sg:postcode":"2217",
    "sg:province":"NSW",
    "sg:tags":[
        "lock"
    ],
    "wof:name":"Clockwork Locksmiths",
    "wof:placetype":"venue"
},
  "geometry": {"coordinates":[151.13653600000001,-33.97263],"type":"Point"}
}