{
  "type": "Feature",
  "properties": {
    "addr:full":"Suite 1/ 735 New South Head Rd Rose Bay NSW 2029",
    "addr:housenumber":"/ 735",
    "addr:postcode":"2029",
    "addr:street":"New South Head Rd",
    "iso:country":"AU",
    "sg:address":"Suite 1/ 735 New South Head Rd",
    "sg:city":"Rose Bay",
    "sg:classifiers":[
        {
            "category":"Real Estate",
            "subcategory":"Architect",
            "type":"Services"
        }
    ],
    "sg:phone":"+61 2 9388 3344",
    "sg:postcode":"2029",
    "sg:province":"NSW",
    "wof:name":"Baroukh & Associates Architects",
    "wof:placetype":"venue"
},
  "geometry": {"coordinates":[151.26756286599999,-33.8711585999],"type":"Point"}
}