{
  "type": "Feature",
  "properties": {
    "addr:full":"9 Edinboro St Mt Hawthorn WA 6016",
    "addr:housenumber":"9",
    "addr:postcode":"6016",
    "addr:street":"Edinboro St Mt",
    "iso:country":"AU",
    "sg:address":"9 Edinboro St",
    "sg:city":"Mt Hawthorn",
    "sg:classifiers":[
        {
            "category":"Shopping",
            "subcategory":"Pets & Pet Supplies",
            "type":"Retail Goods"
        }
    ],
    "sg:phone":"+61 8 9242 4149",
    "sg:postcode":"6016",
    "sg:province":"WA",
    "sg:tags":[
        "boring",
        "drilling",
        "equipment"
    ],
    "wof:name":"National Drill Brokers",
    "wof:placetype":"venue"
},
  "geometry": {"coordinates":[115.841491699,-31.9213924408],"type":"Point"}
}