{
  "type": "Feature",
  "properties": {
    "iso:country":"AU",
    "sg:address":"Hannell & Gross Sts",
    "sg:city":"Carrington",
    "sg:classifiers":[
        {
            "category":"Autos & Motor Vehicles",
            "subcategory":"Fuel & Gas Station",
            "type":"Retail Goods"
        }
    ],
    "sg:phone":"+61 2 4969 4397",
    "sg:postcode":"2294",
    "sg:province":"NSW",
    "wof:name":"BP Australia Limited",
    "wof:placetype":"venue"
},
  "geometry": {"coordinates":[151.75953674300001,-32.9100914001],"type":"Point"}
}