{
  "type": "Feature",
  "properties": {
    "addr:full":"1a Fleet St Somerton VIC 3062",
    "addr:housenumber":"1a",
    "addr:postcode":"3062",
    "addr:street":"Fleet St",
    "iso:country":"AU",
    "sg:address":"1a Fleet St",
    "sg:city":"Somerton",
    "sg:classifiers":[
        {
            "category":"Cafe",
            "type":"Food & Drink"
        }
    ],
    "sg:phone":"+61 3 9303 7733",
    "sg:postcode":"3062",
    "sg:province":"VIC",
    "wof:name":"GTAs Cafe",
    "wof:placetype":"venue"
},
  "geometry": {"coordinates":[144.96351623499999,-37.6433982849],"type":"Point"}
}