{
  "type": "Feature",
  "properties": {
    "iso:country":"AU",
    "sg:address":"27 Clarendon St",
    "sg:city":"Cranbourne",
    "sg:classifiers":[
        {
            "category":"Food & Beverages",
            "subcategory":"Groceries & Convenience Stores",
            "type":"Retail Goods"
        }
    ],
    "sg:phone":"+61 3 5996 3418",
    "sg:postcode":"3977",
    "sg:province":"VIC",
    "wof:name":"El-Ali Ali",
    "wof:placetype":"venue"
},
  "geometry": {"coordinates":[145.275115967,-38.1044845581],"type":"Point"}
}