{
  "type": "Feature",
  "properties": {
    "iso:country":"AU",
    "sg:address":"5 Genesta Pl",
    "sg:city":"Two Rocks",
    "sg:classifiers":[
        {
            "category":"Professional",
            "subcategory":"Computer Services",
            "type":"Services"
        }
    ],
    "sg:phone":"+61 8 9561 1922",
    "sg:postcode":"6037",
    "sg:province":"WA",
    "sg:tags":[
        "training"
    ],
    "wof:name":"Jenesse Pty Ltd",
    "wof:placetype":"venue"
},
  "geometry": {"coordinates":[115.58869934099999,-31.4930725098],"type":"Point"}
}