{
  "type": "Feature",
  "properties": {
    "addr:full":"278 Princes Hwy Bulli NSW 2516",
    "addr:housenumber":"278",
    "addr:postcode":"2516",
    "addr:street":"Princes Hwy",
    "iso:country":"AU",
    "sg:address":"278 Princes Hwy",
    "sg:city":"Bulli",
    "sg:classifiers":[
        {
            "category":"Retail",
            "subcategory":"Funeral Services",
            "type":"Services"
        }
    ],
    "sg:phone":"+61 2 4284 3163",
    "sg:postcode":"2516",
    "sg:province":"NSW",
    "sg:tags":[
        "director"
    ],
    "wof:name":"H. Parsons Funeral Directors",
    "wof:placetype":"venue"
},
  "geometry": {"coordinates":[150.912735,-34.335499],"type":"Point"}
}