{
  "type": "Feature",
  "properties": {
    "iso:country":"AU",
    "sg:address":"Shop 20 - 21 Homemaker City, 825 Zillmere Road",
    "sg:city":"Aspley",
    "sg:classifiers":[
        {
            "category":"Home & Garden",
            "subcategory":"Carpets & Floor Coverings",
            "type":"Retail Goods"
        }
    ],
    "sg:phone":"+61 7 3263 4477",
    "sg:postcode":"4034",
    "sg:province":"QLD",
    "sg:tags":[
        "mattress"
    ],
    "wof:name":"Bedshed",
    "wof:placetype":"venue"
},
  "geometry": {"coordinates":[153.017517,-27.356058],"type":"Point"}
}