{
  "type": "Feature",
  "properties": {
    "addr:full":"134 Oriel Rd Ascot QLD 4007",
    "addr:housenumber":"134",
    "addr:postcode":"4007",
    "addr:street":"Oriel Rd",
    "iso:country":"AU",
    "sg:address":"134 Oriel Rd",
    "sg:city":"Ascot",
    "sg:classifiers":[
        {
            "category":"Building & Trades",
            "subcategory":"Plumbing",
            "type":"Services"
        }
    ],
    "sg:phone":"+61 1800 427 238",
    "sg:postcode":"4007",
    "sg:province":"QLD",
    "sg:tags":[
        "plumber",
        "gasfitters"
    ],
    "wof:name":"Guildcraft Plumbing & Gas Service",
    "wof:placetype":"venue"
},
  "geometry": {"coordinates":[153.05917400000001,-27.427507],"type":"Point"}
}