{
  "type": "Feature",
  "properties": {
    "iso:country":"AU",
    "sg:address":"271 Bolsover St",
    "sg:city":"Rockhampton",
    "sg:classifiers":[
        {
            "category":"Professional",
            "type":"Services"
        }
    ],
    "sg:phone":"+61 7 4922 9119",
    "sg:postcode":"4700",
    "sg:province":"QLD",
    "sg:tags":[
        "transport"
    ],
    "wof:name":"Straightway Freight",
    "wof:placetype":"venue"
},
  "geometry": {"coordinates":[150.51968383799999,-23.3886737823],"type":"Point"}
}