{
  "type": "Feature",
  "properties": {
    "addr:full":"101a Fitzgerald Rd Laverton North VIC 3026",
    "addr:housenumber":"101a",
    "addr:postcode":"3026",
    "addr:street":"Fitzgerald Rd",
    "iso:country":"AU",
    "sg:address":"101a Fitzgerald Rd",
    "sg:city":"Laverton North",
    "sg:classifiers":[
        {
            "category":"Retail",
            "subcategory":"Auto Repair",
            "type":"Services"
        }
    ],
    "sg:phone":"+61 3 9369 2659",
    "sg:postcode":"3026",
    "sg:province":"VIC",
    "sg:tags":[
        "bus",
        "truck"
    ],
    "wof:name":"Complete Steering Australia",
    "wof:placetype":"venue"
},
  "geometry": {"coordinates":[144.78654499999999,-37.822041],"type":"Point"}
}