{
  "type": "Feature",
  "properties": {
    "addr:full":"42 Strathdee St Mundubbera QLD 4626",
    "addr:housenumber":"42",
    "addr:postcode":"4626",
    "addr:street":"Strathdee St",
    "iso:country":"AU",
    "sg:address":"42 Strathdee St",
    "sg:city":"Mundubbera",
    "sg:classifiers":[
        {
            "category":"Travel",
            "subcategory":"Hotels & Motels",
            "type":"Entertainment"
        }
    ],
    "sg:phone":"+61 7 4165 3111",
    "sg:postcode":"4626",
    "sg:province":"QLD",
    "wof:name":"Mundubbera Motel",
    "wof:placetype":"venue"
},
  "geometry": {"coordinates":[151.30090300000001,-25.586767],"type":"Point"}
}