{
  "type": "Feature",
  "properties": {
    "addr:full":"2 Oaks Rd Thirlmere NSW 2572",
    "addr:postcode":"2572",
    "addr:street":"2 Oaks Rd",
    "iso:country":"AU",
    "sg:address":"2 Oaks Rd",
    "sg:city":"Thirlmere",
    "sg:classifiers":[
        {
            "category":"Cafe",
            "type":"Food & Drink"
        }
    ],
    "sg:phone":"+61 2 4683 3123",
    "sg:postcode":"2572",
    "sg:province":"NSW",
    "wof:name":"Whistle Stop Cafe The",
    "wof:placetype":"venue"
},
  "geometry": {"coordinates":[150.563064575,-34.2026443481],"type":"Point"}
}