{
  "type": "Feature",
  "properties": {
    "addr:full":"39 Teasdale Crs Kialla VIC 3631",
    "addr:housenumber":"39",
    "addr:postcode":"3631",
    "addr:street":"Teasdale Crs",
    "iso:country":"AU",
    "sg:address":"39 Teasdale Crs",
    "sg:city":"Kialla",
    "sg:classifiers":[
        {
            "category":"Professional",
            "subcategory":"Accounting & Tax Preparation",
            "type":"Services"
        }
    ],
    "sg:phone":"+61 3 5823 1706",
    "sg:postcode":"3631",
    "sg:province":"VIC",
    "sg:tags":[
        "accountant",
        "auditor"
    ],
    "wof:name":"Luscombe G D & K M",
    "wof:placetype":"venue"
},
  "geometry": {"coordinates":[145.38958740199999,-36.4276008606],"type":"Point"}
}