{
  "type": "Feature",
  "properties": {
    "addr:full":"10 Charles St Redfern NSW 2016",
    "addr:housenumber":"10",
    "addr:postcode":"2016",
    "addr:street":"Charles St",
    "iso:country":"AU",
    "sg:address":"10 Charles St",
    "sg:city":"Redfern",
    "sg:classifiers":[
        {
            "category":"Real Estate",
            "subcategory":"Architect",
            "type":"Services"
        }
    ],
    "sg:phone":"+61 2 9310 4211",
    "sg:postcode":"2016",
    "sg:province":"NSW",
    "wof:name":"Campbell Luscombe Associates Pty Ltd",
    "wof:placetype":"venue"
},
  "geometry": {"coordinates":[151.215408325,-33.8937644958],"type":"Point"}
}