{
  "type": "Feature",
  "properties": {
    "addr:full":"Factory 1, 121 Cnr Tyabb Rd & Progress St Mornington VIC 3931",
    "addr:housenumber":"121",
    "addr:postcode":"3931",
    "addr:street":"Cnr Tyabb Rd & Progress St",
    "iso:country":"AU",
    "sg:address":"Factory 1, 121 Cnr Tyabb Rd & Progress St",
    "sg:city":"Mornington",
    "sg:classifiers":[
        {
            "category":"Retail",
            "subcategory":"Auto Repair",
            "type":"Services"
        }
    ],
    "sg:phone":"+61 3 5977 0866",
    "sg:postcode":"3931",
    "sg:province":"VIC",
    "sg:tags":[
        "testing",
        "inspection",
        "motor",
        "vehicle"
    ],
    "wof:name":"Wells Automotive",
    "wof:placetype":"venue"
},
  "geometry": {"coordinates":[145.0574646,-38.2342720032],"type":"Point"}
}