{
  "type": "Feature",
  "properties": {
    "addr:full":"17 Cutter Ave Kawana QLD 4701",
    "addr:housenumber":"17",
    "addr:postcode":"4701",
    "addr:street":"Cutter Ave",
    "iso:country":"AU",
    "sg:address":"17 Cutter Ave",
    "sg:city":"Kawana",
    "sg:classifiers":[
        {
            "category":"Building & Trades",
            "subcategory":"Construction",
            "type":"Services"
        }
    ],
    "sg:phone":"+61 7 5437 9797",
    "sg:postcode":"4701",
    "sg:province":"QLD",
    "sg:tags":[
        "contractor"
    ],
    "wof:name":"Hallmark Homes Pty Ltd",
    "wof:placetype":"venue"
},
  "geometry": {"coordinates":[150.51556396500001,-23.3370304108],"type":"Point"}
}