{
  "type": "Feature",
  "properties": {
    "iso:country":"AU",
    "sg:address":"8/ 166 Main South Rd",
    "sg:city":"Morphett Vale",
    "sg:classifiers":[
        {
            "category":"Health Services",
            "subcategory":"Chiropractor",
            "type":"Services"
        }
    ],
    "sg:phone":"+61 8 8384 1666",
    "sg:postcode":"5162",
    "sg:province":"SA",
    "wof:name":"Belle George",
    "wof:placetype":"venue"
},
  "geometry": {"coordinates":[138.523727417,-35.124370575],"type":"Point"}
}