{
  "type": "Feature",
  "properties": {
    "iso:country":"AU",
    "sg:address":"Unit 6 / 290 Victoria Rd",
    "sg:city":"Malaga",
    "sg:phone":"+61 8 9248 1688",
    "sg:postcode":"6090",
    "sg:province":"WA",
    "wof:name":"Dunbar Services (WA) Pty Ltd",
    "wof:placetype":"venue"
},
  "geometry": {"coordinates":[115.88948822,-31.8616752625],"type":"Point"}
}