{
  "type": "Feature",
  "properties": {
    "addr:full":"Caridean St Heathridge WA 6027",
    "addr:postcode":"6027",
    "iso:country":"AU",
    "sg:address":"Caridean St",
    "sg:city":"Heathridge",
    "sg:classifiers":[
        {
            "category":"Food & Beverages",
            "subcategory":"Bakery",
            "type":"Retail Goods"
        }
    ],
    "sg:phone":"+61 8 9402 4647",
    "sg:postcode":"6027",
    "sg:province":"WA",
    "sg:tags":[
        "cake",
        "shop",
        "pastry"
    ],
    "wof:name":"Cheesecake Shop The",
    "wof:placetype":"venue"
},
  "geometry": {"coordinates":[115.765220642,-31.7600021362],"type":"Point"}
}