{
  "type": "Feature",
  "properties": {
    "addr:full":"9 Bryan Crt Melton VIC 3337",
    "addr:housenumber":"9",
    "addr:postcode":"3337",
    "addr:street":"Bryan Crt",
    "iso:country":"AU",
    "sg:address":"9 Bryan Crt",
    "sg:city":"Melton",
    "sg:classifiers":[
        {
            "category":"Health Services",
            "subcategory":"Dentist",
            "type":"Services"
        }
    ],
    "sg:phone":"+61 3 9743 9434",
    "sg:postcode":"3337",
    "sg:province":"VIC",
    "sg:tags":[
        "dental",
        "prosthetist"
    ],
    "wof:name":"Willis Stuart",
    "wof:placetype":"venue"
},
  "geometry": {"coordinates":[144.57101399999999,-37.680408],"type":"Point"}
}