{
  "type": "Feature",
  "properties": {
    "iso:country":"AU",
    "sg:address":"54 Mt Pleasant Rd",
    "sg:city":"Kingston",
    "sg:classifiers":[
        {
            "category":"Retail",
            "subcategory":"Veterinary Services",
            "type":"Services"
        }
    ],
    "sg:phone":"+61 3 6229 8556",
    "sg:postcode":"7050",
    "sg:province":"TAS",
    "sg:tags":[
        "surgeon"
    ],
    "wof:name":"Veterinary Home Visits",
    "wof:placetype":"venue"
},
  "geometry": {"coordinates":[147.27475000000001,-42.975845],"type":"Point"}
}