{
  "type": "Feature",
  "properties": {
    "addr:full":"19 Harry Mills Drv Worongary QLD 4213",
    "addr:housenumber":"19",
    "addr:postcode":"4213",
    "addr:street":"Harry Mills Drv",
    "iso:country":"AU",
    "sg:address":"19 Harry Mills Drv",
    "sg:city":"Worongary",
    "sg:classifiers":[
        {
            "category":"Retail",
            "subcategory":"Auto Repair",
            "type":"Services"
        }
    ],
    "sg:phone":"+61 412 751 612",
    "sg:postcode":"4213",
    "sg:province":"QLD",
    "sg:tags":[
        "repairer",
        "motor",
        "engineer"
    ],
    "wof:name":"Coastal Disc Brake Service",
    "wof:placetype":"venue"
},
  "geometry": {"coordinates":[153.327514648,-28.0466938019],"type":"Point"}
}