{
  "type": "Feature",
  "properties": {
    "addr:full":"31 Rosa St Goodwood SA 5034",
    "addr:housenumber":"31",
    "addr:postcode":"5034",
    "addr:street":"Rosa St",
    "iso:country":"AU",
    "sg:address":"31 Rosa St",
    "sg:city":"Goodwood",
    "sg:classifiers":[
        {
            "category":"Social Services",
            "subcategory":"Child Care",
            "type":"Services"
        }
    ],
    "sg:phone":"+61 8 8272 1666",
    "sg:postcode":"5034",
    "sg:province":"SA",
    "wof:name":"Goodwood Community Childcare Centre",
    "wof:placetype":"venue"
},
  "geometry": {"coordinates":[138.59019470199999,-34.9513626099],"type":"Point"}
}