{
  "type": "Feature",
  "properties": {
    "addr:full":"Camp St Talbot VIC 3371",
    "addr:postcode":"3371",
    "addr:street":"St",
    "iso:country":"AU",
    "sg:address":"Camp St",
    "sg:city":"Talbot",
    "sg:classifiers":[
        {
            "category":"Travel",
            "subcategory":"Hotels & Motels",
            "type":"Entertainment"
        }
    ],
    "sg:phone":"+61 3 5463 2204",
    "sg:postcode":"3371",
    "sg:province":"VIC",
    "sg:tags":[
        "accommodation"
    ],
    "wof:name":"Talbot Hotel-Motel",
    "wof:placetype":"venue"
},
  "geometry": {"coordinates":[143.70173645,-37.1712341309],"type":"Point"}
}