{
  "type": "Feature",
  "properties": {
    "addr:full":"Shop 12a, Stockland Mall Baulkham Hills NSW 2153",
    "addr:housenumber":"12a",
    "addr:postcode":"2153",
    "iso:country":"AU",
    "sg:address":"Shop 12a, Stockland Mall",
    "sg:city":"Baulkham Hills",
    "sg:classifiers":[
        {
            "category":"Shopping",
            "subcategory":"Crafts & Fabrics",
            "type":"Retail Goods"
        }
    ],
    "sg:phone":"+61 2 9686 6062",
    "sg:postcode":"2153",
    "sg:province":"NSW",
    "sg:tags":[
        "supply"
    ],
    "wof:name":"Philips Ted-E-Bear Supplies",
    "wof:placetype":"venue"
},
  "geometry": {"coordinates":[150.969512939,-33.8031196594],"type":"Point"}
}