{
  "type": "Feature",
  "properties": {
    "iso:country":"AU",
    "sg:address":"188 Humphries Rd",
    "sg:city":"Mt Eliza",
    "sg:classifiers":[
        {
            "category":"Food & Beverages",
            "subcategory":"Supermarket",
            "type":"Retail Goods"
        }
    ],
    "sg:phone":"+61 3 9787 7053",
    "sg:postcode":"3930",
    "sg:province":"VIC",
    "sg:tags":[
        "grocery",
        "store"
    ],
    "wof:name":"Eliza Park MiniMart",
    "wof:placetype":"venue"
},
  "geometry": {"coordinates":[145.12356567399999,-38.1936454773],"type":"Point"}
}