{
  "type": "Feature",
  "properties": {
    "iso:country":"AU",
    "sg:address":"189 Fenaughty St",
    "sg:city":"Kyabram",
    "sg:classifiers":[
        {
            "category":"Professional",
            "subcategory":"Printing & Photocopies",
            "type":"Services"
        }
    ],
    "sg:phone":"+61 3 5852 2800",
    "sg:postcode":"3620",
    "sg:province":"VIC",
    "sg:tags":[
        "screen",
        "printer"
    ],
    "wof:name":"Kyabram Screenprint",
    "wof:placetype":"venue"
},
  "geometry": {"coordinates":[145.04757690400001,-36.3144683838],"type":"Point"}
}