{
  "type": "Feature",
  "properties": {
    "addr:full":"St Leonards VIC 3223",
    "addr:postcode":"3223",
    "iso:country":"AU",
    "sg:address":"St",
    "sg:city":"Leonards",
    "sg:classifiers":[
        {
            "category":"Building & Trades",
            "subcategory":"Construction",
            "type":"Services"
        }
    ],
    "sg:phone":"+61 3 5257 1985",
    "sg:postcode":"3223",
    "sg:province":"VIC",
    "sg:tags":[
        "contractor"
    ],
    "wof:name":"St Leonards Pergolas & Decks",
    "wof:placetype":"venue"
},
  "geometry": {"coordinates":[144.716095,-38.171749],"type":"Point"}
}