{
  "type": "Feature",
  "properties": {
    "addr:full":"2/ 6 Paramount Pl Oxenford QLD 4210",
    "addr:housenumber":"/ 6",
    "addr:postcode":"4210",
    "iso:country":"AU",
    "sg:address":"2/ 6 Paramount Pl",
    "sg:city":"Oxenford",
    "sg:classifiers":[
        {
            "category":"Home & Garden",
            "subcategory":"Hardware",
            "type":"Retail Goods"
        }
    ],
    "sg:phone":"+61 410 566 555",
    "sg:postcode":"4210",
    "sg:province":"QLD",
    "sg:tags":[
        "supply",
        "maker",
        "cabinet"
    ],
    "wof:name":"Precise Cabinet Installations",
    "wof:placetype":"venue"
},
  "geometry": {"coordinates":[153.32252502399999,-27.9241676331],"type":"Point"}
}