{
  "type": "Feature",
  "properties": {
    "addr:full":"998 Hamilton Rd McDowall QLD 4053",
    "addr:housenumber":"998",
    "addr:postcode":"4053",
    "addr:street":"Hamilton Rd",
    "iso:country":"AU",
    "sg:address":"998 Hamilton Rd",
    "sg:city":"McDowall",
    "sg:classifiers":[
        {
            "category":"Building & Trades",
            "subcategory":"Construction",
            "type":"Services"
        }
    ],
    "sg:phone":"+61 7 3353 4151",
    "sg:postcode":"4053",
    "sg:province":"QLD",
    "sg:tags":[
        "contractor"
    ],
    "wof:name":"West Pacific Properties Pty Ltd",
    "wof:placetype":"venue"
},
  "geometry": {"coordinates":[152.98504638700001,-27.3790473938],"type":"Point"}
}