{
  "type": "Feature",
  "properties": {
    "iso:country":"AU",
    "sg:address":"PO Box 527",
    "sg:city":"Geelong",
    "sg:classifiers":[
        {
            "category":"Building & Trades",
            "subcategory":"Cleaning & Sanitation",
            "type":"Services"
        }
    ],
    "sg:phone":"+61 413 315 789",
    "sg:postcode":"3220",
    "sg:province":"VIC",
    "sg:tags":[
        "window"
    ],
    "wof:name":"Crystal Vision Window & Contract Cleaning",
    "wof:placetype":"venue"
},
  "geometry": {"coordinates":[144.346054,-38.157108],"type":"Point"}
}