{
  "type": "Feature",
  "properties": {
    "iso:country":"AU",
    "sg:address":"19 Alacrity Pl",
    "sg:city":"Henderson",
    "sg:classifiers":[
        {
            "category":"Communications",
            "subcategory":"Television Station",
            "type":"Services"
        }
    ],
    "sg:phone":"+61 8 9451 5711",
    "sg:postcode":"6166",
    "sg:province":"WA",
    "sg:tags":[
        "screening",
        "machinery",
        "grading"
    ],
    "wof:name":"CGC",
    "wof:placetype":"venue"
},
  "geometry": {"coordinates":[115.77658099999999,-32.165684],"type":"Point"}
}