{
  "type": "Feature",
  "properties": {
    "addr:full":"PO Box 421 Kiama NSW 2533",
    "addr:postcode":"2533",
    "iso:country":"AU",
    "sg:address":"PO Box 421",
    "sg:city":"Kiama",
    "sg:classifiers":[
        {
            "category":"Building & Trades",
            "subcategory":"Cleaning & Sanitation",
            "type":"Services"
        }
    ],
    "sg:phone":"+61 2 4233 1975",
    "sg:postcode":"2533",
    "sg:province":"NSW",
    "sg:tags":[
        "chemical",
        "pressure",
        "steam",
        "contractor"
    ],
    "wof:name":"Hancocks Property Maintenance",
    "wof:placetype":"venue"
},
  "geometry": {"coordinates":[150.851806641,-34.6771583557],"type":"Point"}
}