{
  "type": "Feature",
  "properties": {
    "iso:country":"AU",
    "sg:address":"178 Macquarie St",
    "sg:city":"Hobart",
    "sg:classifiers":[
        {
            "category":"Real Estate",
            "subcategory":"Real Estate Agent",
            "type":"Services"
        }
    ],
    "sg:phone":"+61 405 838 888",
    "sg:postcode":"7000",
    "sg:province":"TAS",
    "wof:name":"Ricky Courtney Real Estate Pty Ltd",
    "wof:placetype":"venue"
},
  "geometry": {"coordinates":[147.32569885300001,-42.8864135742],"type":"Point"}
}