{
  "type": "Feature",
  "properties": {
    "addr:full":"25 A Chalgrove Ave Rockingham WA 6168",
    "addr:housenumber":"25 a",
    "addr:postcode":"6168",
    "addr:street":"Chalgrove Ave",
    "iso:country":"AU",
    "sg:address":"25 A Chalgrove Ave",
    "sg:city":"Rockingham",
    "sg:classifiers":[
        {
            "category":"Shopping",
            "subcategory":"Bridal",
            "type":"Retail Goods"
        }
    ],
    "sg:phone":"+61 8 9592 1893",
    "sg:postcode":"6168",
    "sg:province":"WA",
    "sg:tags":[
        "hire",
        "wear"
    ],
    "wof:name":"Donnabella Bridal",
    "wof:placetype":"venue"
},
  "geometry": {"coordinates":[115.743149,-32.286144],"type":"Point"}
}