{
  "type": "Feature",
  "properties": {
    "addr:full":"4 Ridgway Crt Marian QLD 4753",
    "addr:housenumber":"4",
    "addr:postcode":"4753",
    "addr:street":"Ridgway Crt",
    "iso:country":"AU",
    "sg:address":"4 Ridgway Crt",
    "sg:city":"Marian",
    "sg:classifiers":[
        {
            "category":"Shopping",
            "subcategory":"Clothing, Apparel, & Fashions",
            "type":"Retail Goods"
        }
    ],
    "sg:phone":"+61 7 4954 3697",
    "sg:postcode":"4753",
    "sg:province":"QLD",
    "sg:tags":[
        "sportswear"
    ],
    "wof:name":"Greenies Bowls Wear & Accessories",
    "wof:placetype":"venue"
},
  "geometry": {"coordinates":[148.95611600000001,-21.152439],"type":"Point"}
}