{
  "type": "Feature",
  "properties": {
    "iso:country":"AU",
    "sg:address":"Woolshed Rd",
    "sg:city":"Kersbrook",
    "sg:classifiers":[
        {
            "category":"Building & Trades",
            "subcategory":"Landscaping Services",
            "type":"Services"
        }
    ],
    "sg:phone":"+61 411 645 870",
    "sg:postcode":"5231",
    "sg:province":"SA",
    "sg:tags":[
        "grazier"
    ],
    "wof:name":"Brookfield Partners",
    "wof:placetype":"venue"
},
  "geometry": {"coordinates":[138.851104736,-34.7835998535],"type":"Point"}
}