{
  "type": "Feature",
  "properties": {
    "iso:country":"AU",
    "sg:address":"34 Garden St",
    "sg:city":"South Yarra",
    "sg:classifiers":[
        {
            "category":"Shopping",
            "subcategory":"Clothing, Apparel, & Fashions",
            "type":"Retail Goods"
        }
    ],
    "sg:phone":"+61 3 9804 7906",
    "sg:postcode":"3141",
    "sg:province":"VIC",
    "sg:tags":[
        "lady",
        "wear"
    ],
    "wof:name":"Kookai",
    "wof:placetype":"venue"
},
  "geometry": {"coordinates":[144.99424743599999,-37.8365783691],"type":"Point"}
}