{
  "type": "Feature",
  "properties": {
    "addr:full":"985 Kingsford Smith Drv Eagle Farm QLD 4009",
    "addr:housenumber":"985",
    "addr:postcode":"4009",
    "addr:street":"Kingsford Smith Drv",
    "iso:country":"AU",
    "sg:address":"985 Kingsford Smith Drv",
    "sg:city":"Eagle Farm",
    "sg:classifiers":[
        {
            "category":"Government",
            "subcategory":"Post Office",
            "type":"Public Place"
        }
    ],
    "sg:phone":"+61 7 3868 3860",
    "sg:postcode":"4009",
    "sg:province":"QLD",
    "sg:tags":[
        "postal"
    ],
    "wof:name":"Eagle Farm Business Centre",
    "wof:placetype":"venue"
},
  "geometry": {"coordinates":[153.09397888199999,-27.4301261902],"type":"Point"}
}