{
  "type": "Feature",
  "properties": {
    "addr:full":"313A Reserve Rd Cheltenham VIC 3192",
    "addr:housenumber":"313a",
    "addr:postcode":"3192",
    "addr:street":"Reserve Rd",
    "iso:country":"AU",
    "sg:address":"313A Reserve Rd",
    "sg:city":"Cheltenham",
    "sg:classifiers":[
        {
            "category":"Retail",
            "subcategory":"Auto Repair",
            "type":"Services"
        }
    ],
    "sg:phone":"+61 3 9583 3766",
    "sg:postcode":"3192",
    "sg:province":"VIC",
    "sg:tags":[
        "testing",
        "inspection",
        "motor",
        "vehicle"
    ],
    "wof:name":"Serv Group (AUST)",
    "wof:placetype":"venue"
},
  "geometry": {"coordinates":[145.037185669,-37.9633102417],"type":"Point"}
}