{
  "type": "Feature",
  "properties": {
    "iso:country":"AU",
    "sg:address":"75 Lochlomond Drv",
    "sg:city":"Banora Point",
    "sg:classifiers":[
        {
            "category":"Utilities",
            "subcategory":"Electric",
            "type":"Services"
        }
    ],
    "sg:phone":"+61 7 5524 8333",
    "sg:postcode":"2486",
    "sg:province":"NSW",
    "sg:tags":[
        "electrical",
        "contractor"
    ],
    "wof:name":"A Aaron Electrical",
    "wof:placetype":"venue"
},
  "geometry": {"coordinates":[153.53770446799999,-28.2287044525],"type":"Point"}
}