{
  "type": "Feature",
  "properties": {
    "iso:country":"AU",
    "sg:address":"PO Box 3595",
    "sg:city":"Hermit Park",
    "sg:classifiers":[
        {
            "category":"Utilities",
            "subcategory":"Electric",
            "type":"Services"
        }
    ],
    "sg:phone":"+61 7 4755 0922",
    "sg:postcode":"4812",
    "sg:province":"QLD",
    "sg:tags":[
        "electrical",
        "contractor"
    ],
    "wof:name":"B.E. Electrical & Air-Conditioning Services Pty Ltd",
    "wof:placetype":"venue"
},
  "geometry": {"coordinates":[146.805527,-19.282761],"type":"Point"}
}