{
  "type": "Feature",
  "properties": {
    "iso:country":"AU",
    "sg:address":"14A 96 Wilkie St",
    "sg:city":"Yeerongpilly",
    "sg:classifiers":[
        {
            "category":"Wholesale",
            "subcategory":"Metals & Minerals",
            "type":"Manufacturing & Wholesale Goods"
        }
    ],
    "sg:phone":"+61 7 3426 4100",
    "sg:postcode":"4105",
    "sg:province":"QLD",
    "sg:tags":[
        "steel",
        "merchant"
    ],
    "wof:name":"Global Metals",
    "wof:placetype":"venue"
},
  "geometry": {"coordinates":[153.013961792,-27.5254745483],"type":"Point"}
}