{
  "type": "Feature",
  "properties": {
    "iso:country":"AU",
    "sg:address":"449 Church St",
    "sg:city":"North Parramatta",
    "sg:classifiers":[
        {
            "category":"Fast Food",
            "type":"Food & Drink"
        }
    ],
    "sg:phone":"+61 2 9683 1744",
    "sg:postcode":"2151",
    "sg:province":"NSW",
    "sg:tags":[
        "away",
        "take"
    ],
    "wof:name":"Charcoal Thai",
    "wof:placetype":"venue"
},
  "geometry": {"coordinates":[151.005737305,-33.8042106628],"type":"Point"}
}