{
  "type": "Feature",
  "properties": {
    "addr:full":"244/ 248 Edward St Wagga Wagga NSW 2650",
    "addr:housenumber":"244 / 248",
    "addr:postcode":"2650",
    "addr:street":"Edward St",
    "iso:country":"AU",
    "sg:address":"244/ 248 Edward St",
    "sg:city":"Wagga Wagga",
    "sg:classifiers":[
        {
            "category":"Travel",
            "subcategory":"Hotels & Motels",
            "type":"Entertainment"
        }
    ],
    "sg:phone":"+61 2 6921 4099",
    "sg:postcode":"2650",
    "sg:province":"NSW",
    "wof:name":"Heritage Motor Inn",
    "wof:placetype":"venue"
},
  "geometry": {"coordinates":[147.35916137699999,-35.1175918579],"type":"Point"}
}