{
  "type": "Feature",
  "properties": {
    "addr:full":"PO Box 1270 Canberra ACT 2601",
    "addr:postcode":"2601",
    "iso:country":"AU",
    "sg:address":"PO Box 1270",
    "sg:city":"Canberra",
    "sg:classifiers":[
        {
            "category":"Farming",
            "subcategory":"Crops",
            "type":"Manufacturing & Wholesale Goods"
        }
    ],
    "sg:phone":"+61 1800 643 277",
    "sg:postcode":"2601",
    "sg:province":"ACT",
    "sg:tags":[
        "club",
        "dance"
    ],
    "wof:name":"ACT Square Dance Society",
    "wof:placetype":"venue"
},
  "geometry": {"coordinates":[149.111816406,-35.2768592834],"type":"Point"}
}