{
  "type": "Feature",
  "properties": {
    "addr:full":"Shp 5/ 10 Langton Rd Mt Barker WA 6324",
    "addr:housenumber":"/ 10",
    "addr:postcode":"6324",
    "addr:street":"Langton Rd",
    "iso:country":"AU",
    "sg:address":"Shp 5/ 10 Langton Rd",
    "sg:city":"Mt Barker",
    "sg:classifiers":[
        {
            "category":"Social Services",
            "subcategory":"Retirement Home",
            "type":"Services"
        }
    ],
    "sg:phone":"+61 8 9851 1666",
    "sg:postcode":"6324",
    "sg:province":"WA",
    "sg:tags":[
        "village"
    ],
    "wof:name":"Plantagenet Village Homes",
    "wof:placetype":"venue"
},
  "geometry": {"coordinates":[117.66053008999999,-34.6275939941],"type":"Point"}
}