{
  "type": "Feature",
  "properties": {
    "iso:country":"AU",
    "sg:address":"Grand Central Margaret St",
    "sg:city":"Toowoomba",
    "sg:classifiers":[
        {
            "category":"Food & Beverages",
            "subcategory":"Specialty",
            "type":"Retail Goods"
        }
    ],
    "sg:phone":"+61 7 4638 4488",
    "sg:postcode":"4350",
    "sg:province":"QLD",
    "sg:tags":[
        "product",
        "health"
    ],
    "wof:name":"Healthy Life",
    "wof:placetype":"venue"
},
  "geometry": {"coordinates":[151.941757,-27.560299],"type":"Point"}
}