{
  "type": "Feature",
  "properties": {
    "addr:full":"9 Ballantyne Rd Kewdale WA 6105",
    "addr:housenumber":"9",
    "addr:postcode":"6105",
    "addr:street":"Ballantyne Rd",
    "iso:country":"AU",
    "sg:address":"9 Ballantyne Rd",
    "sg:city":"Kewdale",
    "sg:classifiers":[
        {
            "category":"Wholesale",
            "subcategory":"Painting Supplies",
            "type":"Manufacturing & Wholesale Goods"
        }
    ],
    "sg:phone":"+61 8 9353 4433",
    "sg:postcode":"6105",
    "sg:province":"WA",
    "sg:tags":[
        "wholesaler",
        "paint",
        "mfrs"
    ],
    "wof:name":"Uniseal Manufacturing",
    "wof:placetype":"venue"
},
  "geometry": {"coordinates":[115.937141419,-31.984910965],"type":"Point"}
}