{
  "type": "Feature",
  "properties": {
    "addr:full":"\"Brecon\" Phoines Rd Muntham VIC 3312",
    "addr:postcode":"3312",
    "addr:street":"Phoines Rd",
    "iso:country":"AU",
    "sg:address":"\"Brecon\" Phoines Rd",
    "sg:city":"Muntham",
    "sg:classifiers":[
        {
            "category":"Farming",
            "subcategory":"Farm",
            "type":"Manufacturing & Wholesale Goods"
        }
    ],
    "sg:phone":"+61 3 5575 3240",
    "sg:postcode":"3312",
    "sg:province":"VIC",
    "sg:tags":[
        "farmer"
    ],
    "wof:name":"Munro P G & S",
    "wof:placetype":"venue"
},
  "geometry": {"coordinates":[141.471893311,-37.5378341675],"type":"Point"}
}