{
  "type": "Feature",
  "properties": {
    "addr:full":"949 Whitehorse Rd Box Hill VIC 3128",
    "addr:housenumber":"949",
    "addr:postcode":"3128",
    "addr:street":"Whitehorse Rd",
    "iso:country":"AU",
    "sg:address":"949 Whitehorse Rd",
    "sg:city":"Box Hill",
    "sg:classifiers":[
        {
            "category":"Banks & Credit Unions",
            "subcategory":"Financial Services",
            "type":"Services"
        }
    ],
    "sg:phone":"+61 1300 262 933",
    "sg:postcode":"3128",
    "sg:province":"VIC",
    "sg:tags":[
        "financier"
    ],
    "sg:website":"http://www.amazingloans.com.au",
    "wof:name":"Amazing Loans",
    "wof:placetype":"venue"
},
  "geometry": {"coordinates":[145.12362670900001,-37.8177566528],"type":"Point"}
}