{
  "type": "Feature",
  "properties": {
    "addr:full":"28 Kepler St Warrnambool VIC 3280",
    "addr:housenumber":"28",
    "addr:postcode":"3280",
    "addr:street":"Kepler St",
    "iso:country":"AU",
    "sg:address":"28 Kepler St",
    "sg:city":"Warrnambool",
    "sg:classifiers":[
        {
            "category":"Professional",
            "subcategory":"Testing Lab",
            "type":"Services"
        }
    ],
    "sg:phone":"+61 3 5561 3939",
    "sg:postcode":"3280",
    "sg:province":"VIC",
    "sg:tags":[
        "soil",
        "investigation"
    ],
    "wof:name":"Brian Consulting",
    "wof:placetype":"venue"
},
  "geometry": {"coordinates":[142.480300903,-38.3843269348],"type":"Point"}
}