{
  "type": "Feature",
  "properties": {
    "iso:country":"AU",
    "sg:address":"9- 12 Ovens Crt",
    "sg:city":"Sunshine",
    "sg:classifiers":[
        {
            "category":"Professional",
            "type":"Services"
        }
    ],
    "sg:phone":"+61 3 9312 3377",
    "sg:postcode":"3020",
    "sg:province":"VIC",
    "sg:tags":[
        "forwarding",
        "agent",
        "transport"
    ],
    "wof:name":"Straightline Transport Australia Pty Ltd",
    "wof:placetype":"venue"
},
  "geometry": {"coordinates":[144.81561300000001,-37.811794],"type":"Point"}
}