{
  "type": "Feature",
  "properties": {
    "addr:full":"4 Short St Kingaroy QLD 4610",
    "addr:housenumber":"4",
    "addr:postcode":"4610",
    "addr:street":"Short St",
    "iso:country":"AU",
    "sg:address":"4 Short St",
    "sg:city":"Kingaroy",
    "sg:classifiers":[
        {
            "category":"Cinema",
            "subcategory":"Movie Theater",
            "type":"Entertainment"
        }
    ],
    "sg:phone":"+61 7 4162 7199",
    "sg:postcode":"4610",
    "sg:province":"QLD",
    "wof:name":"Kingaroy Satellite Cinema",
    "wof:placetype":"venue"
},
  "geometry": {"coordinates":[151.84048461899999,-26.5422420502],"type":"Point"}
}