{
  "type": "Feature",
  "properties": {
    "addr:full":"10 Gough Pl Noranda WA 6062",
    "addr:housenumber":"10",
    "addr:postcode":"6062",
    "addr:street":"Gough Pl",
    "iso:country":"AU",
    "sg:address":"10 Gough Pl",
    "sg:city":"Noranda",
    "sg:classifiers":[
        {
            "category":"Real Estate",
            "subcategory":"Real Estate Agent",
            "type":"Services"
        }
    ],
    "sg:phone":"+61 8 9275 4444",
    "sg:postcode":"6062",
    "sg:province":"WA",
    "wof:name":"Butler Gerard & Associates",
    "wof:placetype":"venue"
},
  "geometry": {"coordinates":[115.88027954099999,-31.8727359772],"type":"Point"}
}