{
  "type": "Feature",
  "properties": {
    "addr:full":"Frank & Baker St Labrador QLD 4215",
    "addr:postcode":"4215",
    "addr:street":"St",
    "iso:country":"AU",
    "sg:address":"Frank & Baker St",
    "sg:city":"Labrador",
    "sg:classifiers":[
        {
            "category":"Autos & Motor Vehicles",
            "subcategory":"Fuel & Gas Station",
            "type":"Retail Goods"
        }
    ],
    "sg:phone":"+61 7 5531 3281",
    "sg:postcode":"4215",
    "sg:province":"QLD",
    "wof:name":"BP Australia Limited",
    "wof:placetype":"venue"
},
  "geometry": {"coordinates":[153.40901184099999,-27.9450206757],"type":"Point"}
}