{
  "type": "Feature",
  "properties": {
    "addr:full":"38 Ryan Pl Beacon Hill NSW 2100",
    "addr:housenumber":"38",
    "addr:postcode":"2100",
    "addr:street":"Ryan Pl",
    "iso:country":"AU",
    "sg:address":"38 Ryan Pl",
    "sg:city":"Beacon Hill",
    "sg:classifiers":[
        {
            "category":"Shopping",
            "subcategory":"Party Supplies",
            "type":"Retail Goods"
        }
    ],
    "sg:phone":"+61 2 9400 9020",
    "sg:postcode":"2100",
    "sg:province":"NSW",
    "sg:tags":[
        "children's"
    ],
    "wof:name":"Sparrow Sports",
    "wof:placetype":"venue"
},
  "geometry": {"coordinates":[151.26521301299999,-33.7599716187],"type":"Point"}
}