{
  "type": "Feature",
  "properties": {
    "iso:country":"AU",
    "sg:address":"151 Uriarra Rd",
    "sg:city":"Queanbeyan",
    "sg:classifiers":[
        {
            "category":"Autos & Motor Vehicles",
            "subcategory":"Auto Supplies",
            "type":"Retail Goods"
        }
    ],
    "sg:phone":"+61 2 6299 2733",
    "sg:postcode":"2620",
    "sg:province":"NSW",
    "sg:tags":[
        "battery",
        "automotive"
    ],
    "wof:name":"Alpine Batteries",
    "wof:placetype":"venue"
},
  "geometry": {"coordinates":[149.21324157699999,-35.3430709839],"type":"Point"}
}