{
  "type": "Feature",
  "properties": {
    "iso:country":"AU",
    "sg:address":"1 Chambers Rd",
    "sg:city":"Altona North",
    "sg:classifiers":[
        {
            "category":"Building & Trades",
            "subcategory":"Plumbing",
            "type":"Services"
        }
    ],
    "sg:phone":"+61 3 9391 9984",
    "sg:postcode":"3025",
    "sg:province":"VIC",
    "sg:tags":[
        "plumber",
        "gasfitters"
    ],
    "wof:name":"Dredge-Link Pty Ltd",
    "wof:placetype":"venue"
},
  "geometry": {"coordinates":[144.840576,-37.846107],"type":"Point"}
}