{
  "type": "Feature",
  "properties": {
    "addr:full":"Ballarat Rd Deer Park VIC 3023",
    "addr:postcode":"3023",
    "addr:street":"Ballarat Rd",
    "iso:country":"AU",
    "sg:address":"Ballarat Rd",
    "sg:city":"Deer Park",
    "sg:classifiers":[
        {
            "category":"Home & Garden",
            "subcategory":"Hardware",
            "type":"Retail Goods"
        }
    ],
    "sg:phone":"+61 3 9217 6111",
    "sg:postcode":"3023",
    "sg:province":"VIC",
    "sg:tags":[
        "product",
        "treatment",
        "floor"
    ],
    "wof:name":"ICI Polyurethanes",
    "wof:placetype":"venue"
},
  "geometry": {"coordinates":[144.774384,-37.77002],"type":"Point"}
}