{
  "type": "Feature",
  "properties": {
    "iso:country":"AU",
    "sg:address":"20 Ferrier St",
    "sg:city":"Narangba",
    "sg:classifiers":[
        {
            "category":"Building & Trades",
            "subcategory":"Pest Control",
            "type":"Services"
        }
    ],
    "sg:phone":"+61 7 3888 6777",
    "sg:postcode":"4504",
    "sg:province":"QLD",
    "wof:name":"Termite Alert Pty Ltd",
    "wof:placetype":"venue"
},
  "geometry": {"coordinates":[152.977127075,-27.205575943],"type":"Point"}
}