{
  "type": "Feature",
  "properties": {
    "addr:full":"8 Lawsons Crt Templestowe VIC 3106",
    "addr:housenumber":"8",
    "addr:postcode":"3106",
    "addr:street":"Lawsons Crt",
    "iso:country":"AU",
    "sg:address":"8 Lawsons Crt",
    "sg:city":"Templestowe",
    "sg:classifiers":[
        {
            "category":"Professional",
            "subcategory":"Accounting & Tax Preparation",
            "type":"Services"
        }
    ],
    "sg:phone":"+61 412 591 134",
    "sg:postcode":"3106",
    "sg:province":"VIC",
    "sg:tags":[
        "bookkeeping"
    ],
    "wof:name":"Leading Edge Bookkeeping",
    "wof:placetype":"venue"
},
  "geometry": {"coordinates":[145.163818359,-37.7580909729],"type":"Point"}
}