{
  "type": "Feature",
  "properties": {
    "iso:country":"AU",
    "sg:address":"Unit B Enterprise Park, 22 College St",
    "sg:city":"Gladesville",
    "sg:classifiers":[
        {
            "category":"Banks & Credit Unions",
            "subcategory":"Atm",
            "type":"Services"
        }
    ],
    "sg:phone":"+61 2 9879 6133",
    "sg:postcode":"2111",
    "sg:province":"NSW",
    "sg:tags":[
        "wholesaler",
        "mfrs",
        "envelope"
    ],
    "wof:name":"Reding Paper Products",
    "wof:placetype":"venue"
},
  "geometry": {"coordinates":[151.12335205100001,-33.8217391968],"type":"Point"}
}