{
  "type": "Feature",
  "properties": {
    "addr:full":"34 North Station Rd Booval North QLD 4304",
    "addr:housenumber":"34",
    "addr:postcode":"4304",
    "addr:street":"North Station Rd",
    "iso:country":"AU",
    "sg:address":"34 North Station Rd",
    "sg:city":"Booval North",
    "sg:classifiers":[
        {
            "category":"Professional",
            "subcategory":"Computer Services",
            "type":"Services"
        }
    ],
    "sg:phone":"+61 7 3282 5063",
    "sg:postcode":"4304",
    "sg:province":"QLD",
    "sg:tags":[
        "equipment",
        "networking",
        "installation"
    ],
    "wof:name":"Allyad Computer Consultants",
    "wof:placetype":"venue"
},
  "geometry": {"coordinates":[152.78984069800001,-27.6089553833],"type":"Point"}
}