{
  "type": "Feature",
  "properties": {
    "addr:full":"2b Arab Rd Padstow NSW 2211",
    "addr:housenumber":"2b",
    "addr:postcode":"2211",
    "addr:street":"Arab Rd",
    "iso:country":"AU",
    "sg:address":"2b Arab Rd",
    "sg:city":"Padstow",
    "sg:classifiers":[
        {
            "category":"Professional",
            "subcategory":"Engineering",
            "type":"Services"
        }
    ],
    "sg:phone":"+61 2 9792 4782",
    "sg:postcode":"2211",
    "sg:province":"NSW",
    "sg:tags":[
        "installation",
        "maintenance",
        "engineer"
    ],
    "wof:name":"Tellston Industries Pty Ltd",
    "wof:placetype":"venue"
},
  "geometry": {"coordinates":[151.03613300000001,-33.94471],"type":"Point"}
}