{
  "type": "Feature",
  "properties": {
    "addr:full":"89 Kent Rd Wooloowin QLD 4030",
    "addr:housenumber":"89",
    "addr:postcode":"4030",
    "addr:street":"Kent Rd",
    "iso:country":"AU",
    "sg:address":"89 Kent Rd",
    "sg:city":"Wooloowin",
    "sg:classifiers":[
        {
            "category":"Government",
            "subcategory":"Court House",
            "type":"Public Place"
        }
    ],
    "sg:phone":"+61 7 3843 3300",
    "sg:postcode":"4030",
    "sg:province":"QLD",
    "sg:tags":[
        "personal",
        "marriage",
        "family",
        "counselling"
    ],
    "wof:name":"Something More Counselling Services",
    "wof:placetype":"venue"
},
  "geometry": {"coordinates":[153.043137,-27.414003],"type":"Point"}
}