{
  "type": "Feature",
  "properties": {
    "iso:country":"AU",
    "sg:address":"PO Box 3272",
    "sg:city":"Bassendean DC",
    "sg:classifiers":[
        {
            "category":"Professional",
            "subcategory":"Art Services",
            "type":"Services"
        }
    ],
    "sg:phone":"+61 8 9477 5200",
    "sg:postcode":"6942",
    "sg:province":"WA",
    "sg:tags":[
        "interior",
        "decorator"
    ],
    "wof:name":"Riley Shelley Western Australia",
    "wof:placetype":"venue"
},
  "geometry": {"coordinates":[115.922943115,-31.9122695923],"type":"Point"}
}