{
  "type": "Feature",
  "properties": {
    "addr:full":"5a Broughton St Kirribilli NSW 2061",
    "addr:housenumber":"5a",
    "addr:postcode":"2061",
    "addr:street":"Broughton St",
    "iso:country":"AU",
    "sg:address":"5a Broughton St",
    "sg:city":"Kirribilli",
    "sg:classifiers":[
        {
            "category":"Food & Beverages",
            "subcategory":"Groceries & Convenience Stores",
            "type":"Retail Goods"
        }
    ],
    "sg:phone":"+61 2 9955 3503",
    "sg:postcode":"2061",
    "sg:province":"NSW",
    "wof:name":"Kirribilli Cut Price Market Food Store",
    "wof:placetype":"venue"
},
  "geometry": {"coordinates":[151.21299743599999,-33.8468170166],"type":"Point"}
}