{
  "type": "Feature",
  "properties": {
    "addr:full":"2 Church La Cranebrook NSW 2749",
    "addr:housenumber":"2",
    "addr:postcode":"2749",
    "addr:street":"Church La",
    "iso:country":"AU",
    "sg:address":"2 Church La",
    "sg:city":"Cranebrook",
    "sg:classifiers":[
        {
            "category":"Professional",
            "type":"Services"
        }
    ],
    "sg:phone":"+61 415 673 791",
    "sg:postcode":"2749",
    "sg:province":"NSW",
    "sg:tags":[
        "shop",
        "fitting"
    ],
    "wof:name":"DNA Constructions",
    "wof:placetype":"venue"
},
  "geometry": {"coordinates":[150.699508667,-33.6993484497],"type":"Point"}
}