{
  "type": "Feature",
  "properties": {
    "addr:full":"Myponga Post Office SA 5202 Myponga SA 5202",
    "addr:housenumber":"5202",
    "addr:postcode":"myponga;5202",
    "iso:country":"AU",
    "sg:address":"Myponga Post Office SA 5202",
    "sg:city":"Myponga",
    "sg:classifiers":[
        {
            "category":"Building & Trades",
            "subcategory":"Construction",
            "type":"Services"
        }
    ],
    "sg:phone":"+61 8 8554 7222",
    "sg:postcode":"5202",
    "sg:province":"SA",
    "sg:tags":[
        "fencing",
        "contractor"
    ],
    "wof:name":"Country Gates",
    "wof:placetype":"venue"
},
  "geometry": {"coordinates":[138.41691599999999,-35.411404],"type":"Point"}
}