{
  "type": "Feature",
  "properties": {
    "iso:country":"AU",
    "sg:address":"Shop 31, Medical Centre Hillarys Beach Shopping Centre",
    "sg:city":"Hillarys",
    "sg:classifiers":[
        {
            "category":"Health Services",
            "subcategory":"Doctor",
            "type":"Services"
        }
    ],
    "sg:phone":"+61 8 9403 6801",
    "sg:postcode":"6025",
    "sg:province":"WA",
    "sg:tags":[
        "podiatrist"
    ],
    "wof:name":"Clover Podiatry Services",
    "wof:placetype":"venue"
},
  "geometry": {"coordinates":[115.74561309800001,-31.8076992035],"type":"Point"}
}