{
  "type": "Feature",
  "properties": {
    "addr:full":"Mulgathing Station PMB 37 via Port Augusta SA 5710",
    "addr:housenumber":"37",
    "addr:postcode":"5710",
    "addr:street":"Pmb;Via Port Augusta",
    "iso:country":"AU",
    "sg:address":"Mulgathing Station PMB 37 via",
    "sg:city":"Port Augusta",
    "sg:classifiers":[
        {
            "category":"Building & Trades",
            "subcategory":"Landscaping Services",
            "type":"Services"
        }
    ],
    "sg:phone":"+61 8 8672 1920",
    "sg:postcode":"5710",
    "sg:province":"SA",
    "sg:tags":[
        "grazier"
    ],
    "wof:name":"Mulgathing Station",
    "wof:placetype":"venue"
},
  "geometry": {"coordinates":[135.001022339,-29.6619091034],"type":"Point"}
}