{
  "type": "Feature",
  "properties": {
    "addr:full":"230 Rodeo Drv Macksville NSW 2447",
    "addr:housenumber":"230",
    "addr:postcode":"2447",
    "addr:street":"Rodeo Drv",
    "iso:country":"AU",
    "sg:address":"230 Rodeo Drv",
    "sg:city":"Macksville",
    "sg:classifiers":[
        {
            "category":"Communications",
            "type":"Services"
        }
    ],
    "sg:phone":"+61 427 683 700",
    "sg:postcode":"2447",
    "sg:province":"NSW",
    "sg:tags":[
        "antenna"
    ],
    "wof:name":"Oz Antennas",
    "wof:placetype":"venue"
},
  "geometry": {"coordinates":[152.92004399999999,-30.684772],"type":"Point"}
}