{
  "type": "Feature",
  "properties": {
    "iso:country":"AU",
    "sg:address":"230 Rodeo Drv",
    "sg:city":"Macksville",
    "sg:classifiers":[
        {
            "category":"Communications",
            "type":"Services"
        }
    ],
    "sg:phone":"+61 427 683 700",
    "sg:postcode":"2447",
    "sg:province":"NSW",
    "sg:tags":[
        "antenna"
    ],
    "wof:name":"Oz Antennas",
    "wof:placetype":"venue"
},
  "geometry": {"coordinates":[152.920044,-30.684772],"type":"Point"}
}