{
  "type": "Feature",
  "properties": {
    "addr:full":"285 Mons Rd Forest Glen QLD 4556",
    "addr:housenumber":"285",
    "addr:postcode":"4556",
    "addr:street":"Mons Rd",
    "iso:country":"AU",
    "sg:address":"285 Mons Rd",
    "sg:city":"Forest Glen",
    "sg:classifiers":[
        {
            "category":"Building & Trades",
            "subcategory":"Construction",
            "type":"Services"
        }
    ],
    "sg:phone":"+61 7 5477 1877",
    "sg:postcode":"4556",
    "sg:province":"QLD",
    "sg:tags":[
        "earth",
        "excavating",
        "moving",
        "contractor"
    ],
    "wof:name":"Dingo Hire",
    "wof:placetype":"venue"
},
  "geometry": {"coordinates":[153.012207031,-26.6885185242],"type":"Point"}
}