{
  "type": "Feature",
  "properties": {
    "addr:full":"U7/ 9 Taringa St Ashfield NSW 2131",
    "addr:housenumber":"9",
    "addr:postcode":"2131",
    "addr:street":"U7 /;St",
    "iso:country":"AU",
    "sg:address":"U7/ 9 Taringa St",
    "sg:city":"Ashfield",
    "sg:classifiers":[
        {
            "category":"Utilities",
            "subcategory":"Electric",
            "type":"Services"
        }
    ],
    "sg:phone":"+61 2 9798 4803",
    "sg:postcode":"2131",
    "sg:province":"NSW",
    "sg:tags":[
        "electrical",
        "contractor"
    ],
    "wof:name":"Tigerden Communications & Electrical Services",
    "wof:placetype":"venue"
},
  "geometry": {"coordinates":[151.12559509299999,-33.8805770874],"type":"Point"}
}