{
  "type": "Feature",
  "properties": {
    "addr:full":"2 Daniel Crs Caulfield VIC 3162",
    "addr:housenumber":"2",
    "addr:postcode":"3162",
    "addr:street":"Daniel Crs",
    "iso:country":"AU",
    "sg:address":"2 Daniel Crs",
    "sg:city":"Caulfield",
    "sg:classifiers":[
        {
            "category":"Professional",
            "subcategory":"Art Services",
            "type":"Services"
        }
    ],
    "sg:phone":"+61 3 9571 2229",
    "sg:postcode":"3162",
    "sg:province":"VIC",
    "sg:tags":[
        "artist"
    ],
    "wof:name":"McGilchrist E M",
    "wof:placetype":"venue"
},
  "geometry": {"coordinates":[145.02273559599999,-37.8799514771],"type":"Point"}
}