{
  "type": "Feature",
  "properties": {
    "addr:full":"South Pacific Hwy Doyalson NSW 2262",
    "addr:postcode":"2262",
    "addr:street":"South Pacific Hwy",
    "iso:country":"AU",
    "sg:address":"South Pacific Hwy",
    "sg:city":"Doyalson",
    "sg:classifiers":[
        {
            "category":"Autos & Motor Vehicles",
            "subcategory":"Fuel & Gas Station",
            "type":"Retail Goods"
        }
    ],
    "sg:phone":"+61 2 4399 2669",
    "sg:postcode":"2262",
    "sg:province":"NSW",
    "wof:name":"Mobil Oil Aust Pty Ltd",
    "wof:placetype":"venue"
},
  "geometry": {"coordinates":[151.523605,-33.198326],"type":"Point"}
}