{
  "type": "Feature",
  "properties": {
    "iso:country":"AU",
    "sg:address":"Shop 9A 8 Grice Ave",
    "sg:city":"Paradise Point",
    "sg:classifiers":[
        {
            "category":"Travel",
            "subcategory":"Travel Agent",
            "type":"Entertainment"
        }
    ],
    "sg:phone":"+61 1800 257 226",
    "sg:postcode":"4216",
    "sg:province":"QLD",
    "sg:tags":[
        "consultant"
    ],
    "wof:name":"Ross & Turner Travel Associates",
    "wof:placetype":"venue"
},
  "geometry": {"coordinates":[153.394256592,-27.8860797882],"type":"Point"}
}