{
  "type": "Feature",
  "properties": {
    "addr:full":"84A Hope St Geelong West VIC 3218",
    "addr:housenumber":"84a",
    "addr:postcode":"3218",
    "addr:street":"Hope St",
    "iso:country":"AU",
    "sg:address":"84A Hope St",
    "sg:city":"Geelong West",
    "sg:classifiers":[
        {
            "category":"Fast Food",
            "type":"Food & Drink"
        }
    ],
    "sg:phone":"+61 3 5229 1363",
    "sg:postcode":"3218",
    "sg:province":"VIC",
    "sg:tags":[
        "away",
        "take"
    ],
    "wof:name":"Jill's Sandwich Bar",
    "wof:placetype":"venue"
},
  "geometry": {"coordinates":[144.34817504899999,-38.1420326233],"type":"Point"}
}