{
  "type": "Feature",
  "properties": {
    "addr:full":"11 Apollo Drv Gladstone QLD 4680",
    "addr:housenumber":"11",
    "addr:postcode":"4680",
    "addr:street":"Apollo Drv",
    "iso:country":"AU",
    "sg:address":"11 Apollo Drv",
    "sg:city":"Gladstone",
    "sg:classifiers":[
        {
            "category":"Education",
            "subcategory":"Music School",
            "type":"Public Place"
        }
    ],
    "sg:phone":"+61 404 176 459",
    "sg:postcode":"4680",
    "sg:province":"QLD",
    "sg:tags":[
        "teacher"
    ],
    "wof:name":"K.A Instrumental Music Academy",
    "wof:placetype":"venue"
},
  "geometry": {"coordinates":[151.21615600600001,-23.8773384094],"type":"Point"}
}