{
  "type": "Feature",
  "properties": {
    "addr:full":"C/o Coles Express 651 Kessels Rd Upper Mt Gravatt QLD 4122",
    "addr:housenumber":"651",
    "addr:postcode":"4122",
    "addr:street":"C;Kessels Rd Upper",
    "iso:country":"AU",
    "sg:address":"C/o Coles Express 651 Kessels Rd",
    "sg:city":"Upper Mt Gravatt",
    "sg:classifiers":[
        {
            "category":"Autos & Motor Vehicles",
            "subcategory":"Auto Supplies",
            "type":"Retail Goods"
        }
    ],
    "sg:phone":"+61 7 3349 6833",
    "sg:postcode":"4122",
    "sg:province":"QLD",
    "sg:tags":[
        "tyre"
    ],
    "wof:name":"Kmart Tyre & Auto Service",
    "wof:placetype":"venue"
},
  "geometry": {"coordinates":[153.07875060999999,-27.5608692169],"type":"Point"}
}