{
  "type": "Feature",
  "properties": {
    "addr:full":"18 Airdrie Rd Caulfield North VIC 3161",
    "addr:housenumber":"18",
    "addr:postcode":"3161",
    "addr:street":"Airdrie Rd",
    "iso:country":"AU",
    "sg:address":"18 Airdrie Rd",
    "sg:city":"Caulfield North",
    "sg:classifiers":[
        {
            "category":"Building & Trades",
            "subcategory":"Construction",
            "type":"Services"
        }
    ],
    "sg:phone":"+61 3 9532 8444",
    "sg:postcode":"3161",
    "sg:province":"VIC",
    "sg:tags":[
        "installation",
        "air conditioning"
    ],
    "wof:name":"Lennox Equipment Services",
    "wof:placetype":"venue"
},
  "geometry": {"coordinates":[145.01995849599999,-37.8744354248],"type":"Point"}
}