{
  "type": "Feature",
  "properties": {
    "iso:country":"AU",
    "sg:address":"44 Main St",
    "sg:city":"Woodside",
    "sg:classifiers":[
        {
            "category":"Fast Food",
            "type":"Food & Drink"
        }
    ],
    "sg:phone":"+61 8 8389 7106",
    "sg:postcode":"5244",
    "sg:province":"SA",
    "sg:tags":[
        "away",
        "take"
    ],
    "wof:name":"Homestead Takeaway Food & Coffee Shop",
    "wof:placetype":"venue"
},
  "geometry": {"coordinates":[138.87408447300001,-34.9066925049],"type":"Point"}
}