{
  "type": "Feature",
  "properties": {
    "iso:country":"AU",
    "sg:address":"28 Robertson St",
    "sg:city":"Mudgee",
    "sg:classifiers":[
        {
            "category":"Transit Center",
            "subcategory":"Freight",
            "type":"Transportation"
        }
    ],
    "sg:phone":"+61 2 6372 2359",
    "sg:postcode":"2850",
    "sg:province":"NSW",
    "sg:tags":[
        "honey",
        "merchant"
    ],
    "wof:name":"Mudgee Honey Co Pty Ltd The",
    "wof:placetype":"venue"
},
  "geometry": {"coordinates":[149.592285,-32.604095],"type":"Point"}
}