{
  "type": "Feature",
  "properties": {
    "addr:full":"U1/ 15 Crawford St Jindabyne NSW 2627",
    "addr:housenumber":"15",
    "addr:postcode":"2627",
    "addr:street":"U1 /;Crawford St",
    "iso:country":"AU",
    "sg:address":"U1/ 15 Crawford St",
    "sg:city":"Jindabyne",
    "sg:classifiers":[
        {
            "category":"Fast Food",
            "type":"Food & Drink"
        }
    ],
    "sg:phone":"+61 2 6456 1600",
    "sg:postcode":"2627",
    "sg:province":"NSW",
    "sg:tags":[
        "away",
        "take"
    ],
    "wof:name":"Rokits Edibles",
    "wof:placetype":"venue"
},
  "geometry": {"coordinates":[148.60235595699999,-36.4375305176],"type":"Point"}
}