{
  "type": "Feature",
  "properties": {
    "addr:full":"\"Orana\" 24999 Warrego Hwy Chinchilla QLD 4413",
    "addr:postcode":"24999;4413",
    "addr:street":"Warrego Hwy",
    "iso:country":"AU",
    "sg:address":"\"Orana\" 24999 Warrego Hwy",
    "sg:city":"Chinchilla",
    "sg:classifiers":[
        {
            "category":"Wholesale",
            "subcategory":"Machinery & Supplies",
            "type":"Manufacturing & Wholesale Goods"
        }
    ],
    "sg:phone":"+61 7 4665 2289",
    "sg:postcode":"4413",
    "sg:province":"QLD",
    "sg:tags":[
        "agricultural"
    ],
    "wof:name":"Gosden's Machinery",
    "wof:placetype":"venue"
},
  "geometry": {"coordinates":[150.64865112300001,-26.7513542175],"type":"Point"}
}