{
  "type": "Feature",
  "properties": {
    "iso:country":"AU",
    "sg:address":"12 Barfield Crs",
    "sg:city":"Elizabeth West",
    "sg:classifiers":[
        {
            "category":"Retail",
            "subcategory":"Event Space",
            "type":"Services"
        }
    ],
    "sg:phone":"+61 8 8255 6804",
    "sg:postcode":"5113",
    "sg:province":"SA",
    "sg:tags":[
        "venue",
        "reception",
        "wedding"
    ],
    "wof:name":"Playford Entertainment Centre",
    "wof:placetype":"venue"
},
  "geometry": {"coordinates":[138.663970947,-34.7029800415],"type":"Point"}
}