{
  "type": "Feature",
  "properties": {
    "addr:full":"PO Box 682 Mundaring WA 6073",
    "addr:postcode":"6073",
    "iso:country":"AU",
    "sg:address":"PO Box 682",
    "sg:city":"Mundaring",
    "sg:classifiers":[
        {
            "category":"Government",
            "subcategory":"Fire Station",
            "type":"Public Place"
        }
    ],
    "sg:phone":"+61 414 364 433",
    "sg:postcode":"6073",
    "sg:province":"WA",
    "sg:tags":[
        "equipment",
        "protection",
        "consultant"
    ],
    "wof:name":"Sepmar",
    "wof:placetype":"venue"
},
  "geometry": {"coordinates":[116.167037964,-31.921880722],"type":"Point"}
}