{
  "type": "Feature",
  "properties": {
    "iso:country":"AU",
    "sg:address":"7 Harley St",
    "sg:city":"Sylvania Heights",
    "sg:classifiers":[
        {
            "category":"Utilities",
            "subcategory":"Electric",
            "type":"Services"
        }
    ],
    "sg:phone":"+61 2 9522 3785",
    "sg:postcode":"2224",
    "sg:province":"NSW",
    "sg:tags":[
        "electrical",
        "contractor"
    ],
    "wof:name":"ARC Group Pty Ltd",
    "wof:placetype":"venue"
},
  "geometry": {"coordinates":[151.09573364299999,-34.0147361755],"type":"Point"}
}