{
  "type": "Feature",
  "properties": {
    "addr:full":"PO Box 7607 Baulkham Hills BC NSW 2153",
    "addr:postcode":"nsw 2153",
    "iso:country":"AU",
    "sg:address":"PO Box 7607",
    "sg:city":"Baulkham Hills BC",
    "sg:classifiers":[
        {
            "category":"Health Services",
            "subcategory":"Doctor",
            "type":"Services"
        }
    ],
    "sg:phone":"+61 1300 733 510",
    "sg:postcode":"2153",
    "sg:province":"NSW",
    "sg:tags":[
        "nurse",
        "nursing"
    ],
    "wof:name":"Kincare",
    "wof:placetype":"venue"
},
  "geometry": {"coordinates":[150.96694946299999,-33.7341308594],"type":"Point"}
}