{
  "type": "Feature",
  "properties": {
    "iso:country":"AU",
    "sg:address":"311 Pacific Hwy",
    "sg:city":"Heatherbrae",
    "sg:classifiers":[
        {
            "category":"Commercial Area",
            "type":"Public Place"
        }
    ],
    "sg:phone":"+61 2 4983 2038",
    "sg:postcode":"2324",
    "sg:province":"NSW",
    "sg:tags":[
        "heavy",
        "carrier"
    ],
    "wof:name":"Molly's Tilt Tray Service",
    "wof:placetype":"venue"
},
  "geometry": {"coordinates":[151.73182678200001,-32.7860870361],"type":"Point"}
}