{
  "type": "Feature",
  "properties": {
    "addr:full":"Unit 5/ 35 Cranbrook Rd Batemans Bay NSW 2536",
    "addr:housenumber":"35",
    "addr:postcode":"2536",
    "addr:street":"Cranbrook Rd",
    "iso:country":"AU",
    "sg:address":"Unit 5/ 35 Cranbrook Rd",
    "sg:city":"Batemans Bay",
    "sg:classifiers":[
        {
            "category":"Wholesale",
            "subcategory":"Seafood",
            "type":"Manufacturing & Wholesale Goods"
        }
    ],
    "sg:phone":"+61 2 4472 9514",
    "sg:postcode":"2536",
    "sg:province":"NSW",
    "sg:tags":[
        "fish"
    ],
    "wof:name":"C & J Jagelman",
    "wof:placetype":"venue"
},
  "geometry": {"coordinates":[150.17083740199999,-35.7196311951],"type":"Point"}
}