{
  "type": "Feature",
  "properties": {
    "addr:full":"PO Box 4907 Dubbo NSW 2830",
    "addr:postcode":"2830",
    "iso:country":"AU",
    "sg:address":"PO Box 4907",
    "sg:city":"Dubbo",
    "sg:classifiers":[
        {
            "category":"Building & Trades",
            "subcategory":"Construction",
            "type":"Services"
        }
    ],
    "sg:phone":"+61 2 6884 6294",
    "sg:postcode":"2830",
    "sg:province":"NSW",
    "sg:tags":[
        "waterproofing",
        "contractor"
    ],
    "wof:name":"Perfect Seal Australia",
    "wof:placetype":"venue"
},
  "geometry": {"coordinates":[148.646118164,-32.2421646118],"type":"Point"}
}