{
  "type": "Feature",
  "properties": {
    "addr:full":"Dennistoun Ave Guildford NSW 2161",
    "addr:postcode":"2161",
    "addr:street":"Dennistoun Ave",
    "iso:country":"AU",
    "sg:address":"Dennistoun Ave",
    "sg:city":"Guildford",
    "sg:classifiers":[
        {
            "category":"Organizations",
            "subcategory":"Professional Association",
            "type":"Services"
        }
    ],
    "sg:phone":"+61 2 9892 4551",
    "sg:postcode":"2161",
    "sg:province":"NSW",
    "sg:tags":[
        "rural",
        "organisation",
        "production",
        "primary"
    ],
    "wof:name":"Woolmark Company The",
    "wof:placetype":"venue"
},
  "geometry": {"coordinates":[150.976104736,-33.8566932678],"type":"Point"}
}