{
  "type": "Feature",
  "properties": {
    "addr:full":"11 Royal St Osborne Park WA 6017",
    "addr:housenumber":"11",
    "addr:postcode":"6017",
    "addr:street":"Royal St",
    "iso:country":"AU",
    "sg:address":"11 Royal St",
    "sg:city":"Osborne Park",
    "sg:classifiers":[
        {
            "category":"Education",
            "subcategory":"University",
            "type":"Public Place"
        }
    ],
    "sg:phone":"+61 8 9275 9842",
    "sg:postcode":"6017",
    "sg:province":"WA",
    "sg:tags":[
        "educational",
        "organisation",
        "cultural"
    ],
    "wof:name":"West Australian Floral Arts Society",
    "wof:placetype":"venue"
},
  "geometry": {"coordinates":[115.82923889200001,-31.8964347839],"type":"Point"}
}