{
  "type": "Feature",
  "properties": {
    "addr:full":"Cnr Berrigan & South Lake Drv South Lake WA 6164",
    "addr:postcode":"6164",
    "addr:street":"Cnr;South Lake Drv",
    "iso:country":"AU",
    "sg:address":"Cnr Berrigan & South Lake Drv",
    "sg:city":"South Lake",
    "sg:classifiers":[
        {
            "category":"Food & Beverages",
            "subcategory":"Supermarket",
            "type":"Retail Goods"
        }
    ],
    "sg:phone":"+61 8 9417 2044",
    "sg:postcode":"6164",
    "sg:province":"WA",
    "sg:tags":[
        "grocery",
        "store"
    ],
    "wof:name":"Supa IGA",
    "wof:placetype":"venue"
},
  "geometry": {"coordinates":[115.846611,-32.110638],"type":"Point"}
}