{
  "type": "Feature",
  "properties": {
    "addr:full":"Lot 48 Saleyards Rd Parkes NSW 2870",
    "addr:postcode":"2870",
    "addr:street":"Saleyards Rd",
    "iso:country":"AU",
    "sg:address":"Lot 48 Saleyards Rd",
    "sg:city":"Parkes",
    "sg:classifiers":[
        {
            "category":"Home & Garden",
            "subcategory":"Building Materials",
            "type":"Retail Goods"
        }
    ],
    "sg:phone":"+61 2 6862 6600",
    "sg:postcode":"2870",
    "sg:province":"NSW",
    "sg:tags":[
        "wall",
        "frame",
        "truss",
        "roof"
    ],
    "wof:name":"Hay Timber Frame & Truss Co.",
    "wof:placetype":"venue"
},
  "geometry": {"coordinates":[148.16494800000001,-33.154541],"type":"Point"}
}