{
  "type": "Feature",
  "properties": {
    "addr:full":"261 Macquarie St Hobart TAS 7000",
    "addr:housenumber":"261",
    "addr:postcode":"7000",
    "addr:street":"Macquarie St",
    "iso:country":"AU",
    "sg:address":"261 Macquarie St",
    "sg:city":"Hobart",
    "sg:classifiers":[
        {
            "category":"Health Services",
            "subcategory":"Health Practitioner",
            "type":"Services"
        }
    ],
    "sg:phone":"+61 3 6224 5555",
    "sg:postcode":"7000",
    "sg:province":"TAS",
    "sg:tags":[
        "psychologist"
    ],
    "wof:name":"Fourez John",
    "wof:placetype":"venue"
},
  "geometry": {"coordinates":[147.32144165,-42.8893165588],"type":"Point"}
}