{
  "type": "Feature",
  "properties": {
    "iso:country":"AU",
    "sg:address":"Main St",
    "sg:city":"Coorow",
    "sg:classifiers":[
        {
            "category":"Food & Beverages",
            "subcategory":"Groceries & Convenience Stores",
            "type":"Retail Goods"
        }
    ],
    "sg:phone":"+61 8 9952 1031",
    "sg:postcode":"6515",
    "sg:province":"WA",
    "wof:name":"Family Shopping Centre",
    "wof:placetype":"venue"
},
  "geometry": {"coordinates":[116.022171,-29.882086],"type":"Point"}
}