{
  "type": "Feature",
  "properties": {
    "addr:full":"139 Dowling St Woolloomooloo NSW 2011",
    "addr:housenumber":"139",
    "addr:postcode":"2011",
    "addr:street":"Dowling St",
    "iso:country":"AU",
    "sg:address":"139 Dowling St",
    "sg:city":"Woolloomooloo",
    "sg:classifiers":[
        {
            "category":"Wholesale",
            "subcategory":"Apparel",
            "type":"Manufacturing & Wholesale Goods"
        }
    ],
    "sg:phone":"+61 2 9356 3700",
    "sg:postcode":"2011",
    "sg:province":"NSW",
    "sg:tags":[
        "wholesaler",
        "mfrs",
        "dress"
    ],
    "wof:name":"Vivian Chan Shaw Pty Ltd",
    "wof:placetype":"venue"
},
  "geometry": {"coordinates":[151.22056579599999,-33.873336792],"type":"Point"}
}