{
  "type": "Feature",
  "properties": {
    "iso:country":"AU",
    "sg:address":"26 Evans Ave",
    "sg:city":"North Mackay",
    "sg:classifiers":[
        {
            "category":"Personal",
            "subcategory":"Beauty Salon",
            "type":"Services"
        }
    ],
    "sg:phone":"+61 7 4957 5792",
    "sg:postcode":"4740",
    "sg:province":"QLD",
    "sg:tags":[
        "hairdresser"
    ],
    "wof:name":"La-Pelo-Tienda",
    "wof:placetype":"venue"
},
  "geometry": {"coordinates":[149.183395,-21.120588],"type":"Point"}
}