{
  "type": "Feature",
  "properties": {
    "iso:country":"AU",
    "sg:address":"41 Molesworth St",
    "sg:city":"Seaford",
    "sg:classifiers":[
        {
            "category":"Wholesale",
            "subcategory":"Painting Supplies",
            "type":"Manufacturing & Wholesale Goods"
        }
    ],
    "sg:phone":"+61 3 9786 4607",
    "sg:postcode":"3198",
    "sg:province":"VIC",
    "sg:tags":[
        "product",
        "cleaning"
    ],
    "wof:name":"Amway Of Australia Pty Ltd",
    "wof:placetype":"venue"
},
  "geometry": {"coordinates":[145.15000915499999,-38.1132202148],"type":"Point"}
}