{
  "type": "Feature",
  "properties": {
    "addr:full":"PO Box 6990 Wetherill Park DC NSW 1851",
    "addr:postcode":"1851",
    "iso:country":"AU",
    "sg:address":"PO Box 6990",
    "sg:city":"Wetherill Park DC",
    "sg:classifiers":[
        {
            "category":"Building & Trades",
            "subcategory":"Pest Control",
            "type":"Services"
        }
    ],
    "sg:phone":"+61 1800 633 963",
    "sg:postcode":"1851",
    "sg:province":"NSW",
    "wof:name":"World Wide Pest Control",
    "wof:placetype":"venue"
},
  "geometry": {"coordinates":[150.91319274899999,-33.8475112915],"type":"Point"}
}