{
  "type": "Feature",
  "properties": {
    "addr:full":"9 Havlock St West Perth WA 6005",
    "addr:housenumber":"9",
    "addr:postcode":"6005",
    "addr:street":"Havlock St",
    "iso:country":"AU",
    "sg:address":"9 Havlock St",
    "sg:city":"West Perth",
    "sg:classifiers":[
        {
            "category":"Professional",
            "subcategory":"Management & Consulting",
            "type":"Services"
        }
    ],
    "sg:phone":"+61 8 9481 2022",
    "sg:postcode":"6005",
    "sg:province":"WA",
    "sg:tags":[
        "consultant"
    ],
    "wof:name":"Sable Management Pty Ltd",
    "wof:placetype":"venue"
},
  "geometry": {"coordinates":[115.84472656200001,-31.9482059479],"type":"Point"}
}