{
  "type": "Feature",
  "properties": {
    "addr:full":"41 Duckett St Beaudesert QLD 4285",
    "addr:housenumber":"41",
    "addr:postcode":"4285",
    "addr:street":"Duckett St",
    "iso:country":"AU",
    "sg:address":"41 Duckett St",
    "sg:city":"Beaudesert",
    "sg:classifiers":[
        {
            "category":"Home & Garden",
            "subcategory":"Household Appliances",
            "type":"Retail Goods"
        }
    ],
    "sg:phone":"+61 7 5541 1440",
    "sg:postcode":"4285",
    "sg:province":"QLD",
    "sg:tags":[
        "equipment",
        "gas"
    ],
    "wof:name":"Wilcox Appliance Electrical Electronic Service",
    "wof:placetype":"venue"
},
  "geometry": {"coordinates":[153.00108299999999,-27.985416],"type":"Point"}
}