{
  "type": "Feature",
  "properties": {
    "addr:full":"Unit 2, 60 Greenway Drv Tweed Heads South QLD 2486",
    "addr:housenumber":"60",
    "addr:postcode":"2486",
    "addr:street":"Greenway Drv",
    "iso:country":"AU",
    "sg:address":"Unit 2, 60 Greenway Drv",
    "sg:city":"Tweed Heads South",
    "sg:classifiers":[
        {
            "category":"Home & Garden",
            "subcategory":"Garden Supply",
            "type":"Retail Goods"
        }
    ],
    "sg:phone":"+61 7 5524 4589",
    "sg:postcode":"2486",
    "sg:province":"QLD",
    "sg:tags":[
        "equipment"
    ],
    "wof:name":"Cossy's Mower Centre",
    "wof:placetype":"venue"
},
  "geometry": {"coordinates":[153.54002380399999,-28.2005844116],"type":"Point"}
}