{
  "type": "Feature",
  "properties": {
    "iso:country":"AU",
    "sg:address":"120 Malibu Rd",
    "sg:city":"Safety Bay",
    "sg:classifiers":[
        {
            "category":"Retail",
            "subcategory":"Veterinary Services",
            "type":"Services"
        }
    ],
    "sg:phone":"+61 8 9528 3333",
    "sg:postcode":"6169",
    "sg:province":"WA",
    "sg:tags":[
        "surgeon"
    ],
    "wof:name":"Twomey D",
    "wof:placetype":"venue"
},
  "geometry": {"coordinates":[115.74543,-32.303837],"type":"Point"}
}