{
  "type": "Feature",
  "properties": {
    "addr:full":"4 Northwood Rd Northwood NSW 2066",
    "addr:housenumber":"4",
    "addr:postcode":"2066",
    "addr:street":"Northwood Rd",
    "iso:country":"AU",
    "sg:address":"4 Northwood Rd",
    "sg:city":"Northwood",
    "sg:classifiers":[
        {
            "category":"Autos & Motor Vehicles",
            "subcategory":"Fuel & Gas Station",
            "type":"Retail Goods"
        }
    ],
    "sg:phone":"+61 2 9428 1215",
    "sg:postcode":"2066",
    "sg:province":"NSW",
    "wof:name":"Australian Petroleum Pty Ltd",
    "wof:placetype":"venue"
},
  "geometry": {"coordinates":[151.17237854000001,-33.8239936829],"type":"Point"}
}