{
  "type": "Feature",
  "properties": {
    "addr:full":"61 Edmund St Caloundra QLD 4551",
    "addr:housenumber":"61",
    "addr:postcode":"4551",
    "addr:street":"Edmund St",
    "iso:country":"AU",
    "sg:address":"61 Edmund St",
    "sg:city":"Caloundra",
    "sg:classifiers":[
        {
            "category":"Social Services",
            "subcategory":"Child Care",
            "type":"Services"
        }
    ],
    "sg:phone":"+61 7 5491 1414",
    "sg:postcode":"4551",
    "sg:province":"QLD",
    "wof:name":"Family Day Care",
    "wof:placetype":"venue"
},
  "geometry": {"coordinates":[153.14239501899999,-26.7974586487],"type":"Point"}
}