{
  "type": "Feature",
  "properties": {
    "addr:full":"1/ 401 Terrigal Drv Erina NSW 2250",
    "addr:housenumber":"/ 401",
    "addr:postcode":"2250",
    "addr:street":"Terrigal Drv",
    "iso:country":"AU",
    "sg:address":"1/ 401 Terrigal Drv",
    "sg:city":"Erina",
    "sg:classifiers":[
        {
            "category":"Banks & Credit Unions",
            "subcategory":"Financial Services",
            "type":"Services"
        }
    ],
    "sg:phone":"+61 416 015 871",
    "sg:postcode":"2250",
    "sg:province":"NSW",
    "sg:tags":[
        "loan",
        "finance",
        "mortgage"
    ],
    "wof:name":"Narelle Burgess",
    "wof:placetype":"venue"
},
  "geometry": {"coordinates":[151.39358520499999,-33.434211731],"type":"Point"}
}