{
  "type": "Feature",
  "properties": {
    "addr:full":"41 William St Caloundra QLD 4551",
    "addr:housenumber":"41",
    "addr:postcode":"4551",
    "addr:street":"William St",
    "iso:country":"AU",
    "sg:address":"41 William St",
    "sg:city":"Caloundra",
    "sg:classifiers":[
        {
            "category":"Home & Garden",
            "subcategory":"Building Materials",
            "type":"Retail Goods"
        }
    ],
    "sg:phone":"+61 7 5491 5933",
    "sg:postcode":"4551",
    "sg:province":"QLD",
    "sg:tags":[
        "merchant",
        "glass",
        "glazier"
    ],
    "wof:name":"Glassfix Australia Pty Ltd",
    "wof:placetype":"venue"
},
  "geometry": {"coordinates":[153.13258361800001,-26.7928771973],"type":"Point"}
}