{
  "type": "Feature",
  "properties": {
    "iso:country":"AU",
    "sg:address":"696 Calder Hwy",
    "sg:city":"Keilor",
    "sg:classifiers":[
        {
            "category":"Fast Food",
            "type":"Food & Drink"
        }
    ],
    "sg:phone":"+61 3 9336 7922",
    "sg:postcode":"3036",
    "sg:province":"VIC",
    "sg:tags":[
        "away",
        "take"
    ],
    "wof:name":"Keilor Village Take Away",
    "wof:placetype":"venue"
},
  "geometry": {"coordinates":[144.83291600000001,-37.713474],"type":"Point"}
}