{
  "type": "Feature",
  "properties": {
    "addr:full":"19 Emma Ave Warrnambool VIC 3280",
    "addr:housenumber":"19",
    "addr:postcode":"3280",
    "addr:street":"Emma Ave",
    "iso:country":"AU",
    "sg:address":"19 Emma Ave",
    "sg:city":"Warrnambool",
    "sg:classifiers":[
        {
            "category":"Building & Trades",
            "subcategory":"Plumbing",
            "type":"Services"
        }
    ],
    "sg:phone":"+61 438 696 001",
    "sg:postcode":"3280",
    "sg:province":"VIC",
    "sg:tags":[
        "plumber",
        "gasfitters"
    ],
    "wof:name":"Henderson Matthew",
    "wof:placetype":"venue"
},
  "geometry": {"coordinates":[142.50303649899999,-38.3883934021],"type":"Point"}
}