{
  "type": "Feature",
  "properties": {
    "iso:country":"AU",
    "sg:address":"1113 Pittwater Rd",
    "sg:city":"Collaroy Beach",
    "sg:classifiers":[
        {
            "category":"Food & Beverages",
            "subcategory":"Supermarket",
            "type":"Retail Goods"
        }
    ],
    "sg:phone":"+61 2 9981 2716",
    "sg:postcode":"2097",
    "sg:province":"NSW",
    "sg:tags":[
        "grocery",
        "store"
    ],
    "wof:name":"Collaroy Beach Mixed Business & Milk Bar",
    "wof:placetype":"venue"
},
  "geometry": {"coordinates":[151.30113220199999,-33.7324028015],"type":"Point"}
}