{
  "type": "Feature",
  "properties": {
    "iso:country":"AU",
    "sg:address":"Newcastle St",
    "sg:city":"Leabrook",
    "sg:classifiers":[
        {
            "category":"Health Services",
            "subcategory":"Health Practitioner",
            "type":"Services"
        }
    ],
    "sg:phone":"+61 8 8332 2789",
    "sg:postcode":"5068",
    "sg:province":"SA",
    "sg:tags":[
        "hypnotherapy"
    ],
    "wof:name":"Turner Deborah",
    "wof:placetype":"venue"
},
  "geometry": {"coordinates":[138.65072631800001,-34.9318275452],"type":"Point"}
}