{
  "type": "Feature",
  "properties": {
    "iso:country":"AU",
    "sg:address":"64 Buckmaster Drv",
    "sg:city":"Mill Park",
    "sg:classifiers":[
        {
            "category":"Professional",
            "subcategory":"Art Services",
            "type":"Services"
        }
    ],
    "sg:phone":"+61 418 503 924",
    "sg:postcode":"3082",
    "sg:province":"VIC",
    "sg:tags":[
        "decorator",
        "painter"
    ],
    "wof:name":"Dovac Painting",
    "wof:placetype":"venue"
},
  "geometry": {"coordinates":[145.069824219,-37.6675186157],"type":"Point"}
}