{
  "type": "Feature",
  "properties": {
    "addr:full":"Murdoch Drv Bateman WA 6150",
    "addr:postcode":"6150",
    "addr:street":"Murdoch Drv",
    "iso:country":"AU",
    "sg:address":"Murdoch Drv",
    "sg:city":"Bateman",
    "sg:classifiers":[
        {
            "category":"Education",
            "subcategory":"School",
            "type":"Public Place"
        }
    ],
    "sg:phone":"+61 8 9332 4844",
    "sg:postcode":"6150",
    "sg:province":"WA",
    "sg:tags":[
        "co-educational"
    ],
    "wof:name":"Corpus Christi College",
    "wof:placetype":"venue"
},
  "geometry": {"coordinates":[115.842293,-32.053886],"type":"Point"}
}