{
  "type": "Feature",
  "properties": {
    "addr:full":"1/ 228 Manning Rd Manning WA 6152",
    "addr:housenumber":"/ 228",
    "addr:postcode":"6152",
    "addr:street":"Manning Rd",
    "iso:country":"AU",
    "sg:address":"1/ 228 Manning Rd",
    "sg:city":"Manning",
    "sg:classifiers":[
        {
            "category":"Communications",
            "subcategory":"Film & Video Production",
            "type":"Services"
        }
    ],
    "sg:phone":"+61 8 9313 2314",
    "sg:postcode":"6152",
    "sg:province":"WA",
    "sg:tags":[
        "dvd",
        "library"
    ],
    "wof:name":"Blockbuster",
    "wof:placetype":"venue"
},
  "geometry": {"coordinates":[115.885391,-32.012066],"type":"Point"}
}