{
  "type": "Feature",
  "properties": {
    "addr:full":"Unit 1, 50 Reserve Drv Mandurah WA 6210",
    "addr:housenumber":"50",
    "addr:postcode":"6210",
    "addr:street":"Reserve Drv",
    "iso:country":"AU",
    "sg:address":"Unit 1, 50 Reserve Drv",
    "sg:city":"Mandurah",
    "sg:classifiers":[
        {
            "category":"Organizations",
            "subcategory":"Non-profit Organization",
            "type":"Services"
        }
    ],
    "sg:phone":"+61 8 9582 6105",
    "sg:postcode":"6210",
    "sg:province":"WA",
    "sg:tags":[
        "support",
        "disability",
        "organisation"
    ],
    "wof:name":"Peel Community Living Inc",
    "wof:placetype":"venue"
},
  "geometry": {"coordinates":[115.741829,-32.513367],"type":"Point"}
}