{
  "type": "Feature",
  "properties": {
    "addr:full":"41 Kylta Rd Heidelberg West VIC 3081",
    "addr:housenumber":"41",
    "addr:postcode":"3081",
    "addr:street":"Kylta Rd",
    "iso:country":"AU",
    "sg:address":"41 Kylta Rd",
    "sg:city":"Heidelberg West",
    "sg:classifiers":[
        {
            "category":"Utilities",
            "subcategory":"Electric",
            "type":"Services"
        }
    ],
    "sg:phone":"+61 3 9450 1300",
    "sg:postcode":"3081",
    "sg:province":"VIC",
    "sg:tags":[
        "electrical",
        "contractor"
    ],
    "wof:name":"Total Systems Integration",
    "wof:placetype":"venue"
},
  "geometry": {"coordinates":[145.044647217,-37.7318840027],"type":"Point"}
}