{
  "type": "Feature",
  "properties": {
    "iso:country":"AU",
    "sg:address":"7200 Goulburn Valley Hwy",
    "sg:city":"Kialla West",
    "sg:classifiers":[
        {
            "category":"Social Services",
            "subcategory":"Adult Care",
            "type":"Services"
        }
    ],
    "sg:phone":"+61 408 545 205",
    "sg:postcode":"3631",
    "sg:province":"VIC",
    "sg:tags":[
        "towing"
    ],
    "wof:name":"A & H Tilt & Crane Trucks",
    "wof:placetype":"venue"
},
  "geometry": {"coordinates":[145.38882446299999,-36.4637527466],"type":"Point"}
}