{
  "type": "Feature",
  "properties": {
    "iso:country":"AU",
    "sg:address":"25 Anzac Hwy",
    "sg:city":"Keswick",
    "sg:classifiers":[
        {
            "category":"Wholesale",
            "subcategory":"Home Furnishings",
            "type":"Manufacturing & Wholesale Goods"
        }
    ],
    "sg:phone":"+61 8 8371 4844",
    "sg:postcode":"5035",
    "sg:province":"SA",
    "sg:tags":[
        "wholesaler",
        "curtain",
        "mfrs"
    ],
    "wof:name":"Flair Curtains & Blinds",
    "wof:placetype":"venue"
},
  "geometry": {"coordinates":[138.58001709000001,-34.9452095032],"type":"Point"}
}