{
  "type": "Feature",
  "properties": {
    "addr:full":"155 Mills St Middle Park VIC 3206",
    "addr:housenumber":"155",
    "addr:postcode":"3206",
    "addr:street":"Mills St",
    "iso:country":"AU",
    "sg:address":"155 Mills St",
    "sg:city":"Middle Park",
    "sg:classifiers":[
        {
            "category":"Arts & Performance",
            "subcategory":"Art Gallery",
            "type":"Entertainment"
        }
    ],
    "sg:phone":"+61 3 9699 1515",
    "sg:postcode":"3206",
    "sg:province":"VIC",
    "wof:name":"Middle Park Fine Art Gallery & Studio",
    "wof:placetype":"venue"
},
  "geometry": {"coordinates":[144.95619199999999,-37.849247],"type":"Point"}
}