{
  "type": "Feature",
  "properties": {
    "addr:full":"494 Neill Rd Eudlo QLD 4554",
    "addr:housenumber":"494",
    "addr:postcode":"4554",
    "addr:street":"Neill Rd",
    "iso:country":"AU",
    "sg:address":"494 Neill Rd",
    "sg:city":"Eudlo",
    "sg:classifiers":[
        {
            "category":"Building & Trades",
            "subcategory":"Landscaping Services",
            "type":"Services"
        }
    ],
    "sg:phone":"+61 7 5445 9531",
    "sg:postcode":"4554",
    "sg:province":"QLD",
    "sg:tags":[
        "designer",
        "landscape",
        "contractor"
    ],
    "wof:name":"Harmony Landscapes",
    "wof:placetype":"venue"
},
  "geometry": {"coordinates":[152.92515564000001,-26.7463531494],"type":"Point"}
}