{
  "type": "Feature",
  "properties": {
    "iso:country":"AU",
    "sg:address":"40 Third Ave",
    "sg:city":"Blacktown",
    "sg:classifiers":[
        {
            "category":"Health Services",
            "subcategory":"Doctor",
            "type":"Services"
        }
    ],
    "sg:phone":"+61 2 9831 7911",
    "sg:postcode":"2148",
    "sg:province":"NSW",
    "sg:tags":[
        "medical",
        "practitioner"
    ],
    "wof:name":"Highview/Summit Family Medical Practice",
    "wof:placetype":"venue"
},
  "geometry": {"coordinates":[150.908294678,-33.7651100159],"type":"Point"}
}