{
  "type": "Feature",
  "properties": {
    "iso:country":"AU",
    "sg:address":"61 Piper St",
    "sg:city":"Kyneton",
    "sg:classifiers":[
        {
            "category":"Professional",
            "subcategory":"Art Services",
            "type":"Services"
        }
    ],
    "sg:phone":"+61 3 5422 1211",
    "sg:postcode":"3444",
    "sg:province":"VIC",
    "sg:tags":[
        "interior",
        "decorator"
    ],
    "wof:name":"Macedon Ranges Interiors",
    "wof:placetype":"venue"
},
  "geometry": {"coordinates":[144.449295044,-37.2442588806],"type":"Point"}
}