{
  "type": "Feature",
  "properties": {
    "addr:full":"210 Baylis St Wagga Wagga NSW 2650",
    "addr:housenumber":"210",
    "addr:postcode":"2650",
    "addr:street":"Baylis St",
    "iso:country":"AU",
    "sg:address":"210 Baylis St",
    "sg:city":"Wagga Wagga",
    "sg:classifiers":[
        {
            "category":"Health Services",
            "subcategory":"Optometrist",
            "type":"Services"
        }
    ],
    "sg:phone":"+61 2 6971 0044",
    "sg:postcode":"2650",
    "sg:province":"NSW",
    "wof:name":"Zac Zacharia",
    "wof:placetype":"venue"
},
  "geometry": {"coordinates":[147.37013244600001,-35.1111183167],"type":"Point"}
}