{
  "type": "Feature",
  "properties": {
    "addr:full":"436 Burwood Rd Belmore NSW 2192",
    "addr:housenumber":"436",
    "addr:postcode":"2192",
    "addr:street":"Burwood Rd",
    "iso:country":"AU",
    "sg:address":"436 Burwood Rd",
    "sg:city":"Belmore",
    "sg:classifiers":[
        {
            "category":"Organizations",
            "subcategory":"Membership Organization",
            "type":"Services"
        }
    ],
    "sg:phone":"+61 2 9750 9744",
    "sg:postcode":"2192",
    "sg:province":"NSW",
    "sg:tags":[
        "support",
        "health",
        "organisation"
    ],
    "wof:name":"Carer Assist",
    "wof:placetype":"venue"
},
  "geometry": {"coordinates":[151.08952300000001,-33.919815],"type":"Point"}
}