{
  "type": "Feature",
  "properties": {
    "addr:full":"25 Rosina St Fairfield West NSW 2165",
    "addr:housenumber":"25",
    "addr:postcode":"2165",
    "addr:street":"Rosina St",
    "iso:country":"AU",
    "sg:address":"25 Rosina St",
    "sg:city":"Fairfield West",
    "sg:classifiers":[
        {
            "category":"Professional",
            "subcategory":"Computer Services",
            "type":"Services"
        }
    ],
    "sg:phone":"+61 417 804 830",
    "sg:postcode":"2165",
    "sg:province":"NSW",
    "sg:tags":[
        "equipment",
        "networking",
        "installation"
    ],
    "wof:name":"3b Networks",
    "wof:placetype":"venue"
},
  "geometry": {"coordinates":[150.93649292000001,-33.8739776611],"type":"Point"}
}