{
  "type": "Feature",
  "properties": {
    "iso:country":"AU",
    "sg:address":"Lands Rd",
    "sg:city":"Butcher's Creek",
    "sg:classifiers":[
        {
            "category":"Farming",
            "subcategory":"Farm",
            "type":"Manufacturing & Wholesale Goods"
        }
    ],
    "sg:phone":"+61 7 4096 8151",
    "sg:postcode":"4885",
    "sg:province":"QLD",
    "sg:tags":[
        "farmer"
    ],
    "wof:name":"Conole M W",
    "wof:placetype":"venue"
},
  "geometry": {"coordinates":[145.624465942,-17.3850193024],"type":"Point"}
}