{
  "type": "Feature",
  "properties": {
    "addr:full":"Woodlands Shopng Cntr Palm Drv Deeragun QLD 4818",
    "addr:postcode":"4818",
    "addr:street":"Palm Drv",
    "iso:country":"AU",
    "sg:address":"Woodlands Shopng Cntr Palm Drv",
    "sg:city":"Deeragun",
    "sg:classifiers":[
        {
            "category":"Health Services",
            "subcategory":"Dentist",
            "type":"Services"
        }
    ],
    "sg:phone":"+61 7 4751 6868",
    "sg:postcode":"4818",
    "sg:province":"QLD",
    "wof:name":"Pryde Brian Dr",
    "wof:placetype":"venue"
},
  "geometry": {"coordinates":[146.66392500000001,-19.239189],"type":"Point"}
}