{
  "type": "Feature",
  "properties": {
    "addr:full":"Francis Hollis Drv Tathra NSW 2550",
    "addr:postcode":"2550",
    "addr:street":"Hollis Drv",
    "iso:country":"AU",
    "sg:address":"Francis Hollis Drv",
    "sg:city":"Tathra",
    "sg:classifiers":[
        {
            "category":"Food & Beverages",
            "subcategory":"Groceries & Convenience Stores",
            "type":"Retail Goods"
        }
    ],
    "sg:phone":"+61 2 6494 1327",
    "sg:postcode":"2550",
    "sg:province":"NSW",
    "wof:name":"Auckland Store",
    "wof:placetype":"venue"
},
  "geometry": {"coordinates":[149.977905273,-36.7258911133],"type":"Point"}
}