{
  "type": "Feature",
  "properties": {
    "addr:full":"Shop 34 South Hedland Shopping Centre South Hedland WA 6722",
    "addr:housenumber":"shop 34",
    "addr:postcode":"6722",
    "addr:street":"South;South",
    "iso:country":"AU",
    "sg:address":"Shop 34",
    "sg:city":"South Hedland Shopping Centre South Hedland",
    "sg:classifiers":[
        {
            "category":"Shopping",
            "subcategory":"Jewelry",
            "type":"Retail Goods"
        }
    ],
    "sg:phone":"+61 8 9172 1872",
    "sg:postcode":"6722",
    "sg:province":"WA",
    "sg:tags":[
        "jeweller"
    ],
    "wof:name":"Appelbees",
    "wof:placetype":"venue"
},
  "geometry": {"coordinates":[118.60131072999999,-20.4081993103],"type":"Point"}
}