{
  "type": "Feature",
  "properties": {
    "addr:full":"619 Canterbury Rd Surrey Hills VIC 3127",
    "addr:housenumber":"619",
    "addr:postcode":"3127",
    "addr:street":"Canterbury Rd",
    "iso:country":"AU",
    "sg:address":"619 Canterbury Rd",
    "sg:city":"Surrey Hills",
    "sg:classifiers":[
        {
            "category":"Professional",
            "type":"Services"
        }
    ],
    "sg:phone":"+61 412 176 111",
    "sg:postcode":"3127",
    "sg:province":"VIC",
    "sg:tags":[
        "auctioneer"
    ],
    "wof:name":"Bragg Christopher Auctions",
    "wof:placetype":"venue"
},
  "geometry": {"coordinates":[145.09803772000001,-37.8259429932],"type":"Point"}
}