{
  "type": "Feature",
  "properties": {
    "iso:country":"AU",
    "sg:address":"Unit 2B Slough Business Park Janine St",
    "sg:city":"Scoresby",
    "sg:classifiers":[
        {
            "category":"Wholesale",
            "subcategory":"Home Furnishings",
            "type":"Manufacturing & Wholesale Goods"
        }
    ],
    "sg:phone":"+61 3 9763 8366",
    "sg:postcode":"3179",
    "sg:province":"VIC",
    "sg:tags":[
        "wholesaler",
        "mfrs",
        "manchester"
    ],
    "wof:name":"United Bonded Fabric / Crestell Industries",
    "wof:placetype":"venue"
},
  "geometry": {"coordinates":[145.230300903,-37.9011497498],"type":"Point"}
}