{
  "type": "Feature",
  "properties": {
    "iso:country":"AU",
    "sg:address":"Unit 1/ 19 Flight Drv",
    "sg:city":"Tullamarine",
    "sg:classifiers":[
        {
            "category":"Professional",
            "type":"Services"
        }
    ],
    "sg:phone":"+61 3 9330 4223",
    "sg:postcode":"3043",
    "sg:province":"VIC",
    "sg:tags":[
        "forwarding",
        "agent",
        "transport"
    ],
    "wof:name":"Worldwide Freight Shipping & Forwarding",
    "wof:placetype":"venue"
},
  "geometry": {"coordinates":[144.85476684599999,-37.7103729248],"type":"Point"}
}