{
  "type": "Feature",
  "properties": {
    "iso:country":"AU",
    "sg:address":"2/ 18 Stapleton St",
    "sg:city":"Glenorchy",
    "sg:classifiers":[
        {
            "category":"Retail",
            "subcategory":"Repair Shop",
            "type":"Services"
        }
    ],
    "sg:phone":"+61 3 6273 0150",
    "sg:postcode":"7010",
    "sg:province":"TAS",
    "sg:tags":[
        "leadlights"
    ],
    "wof:name":"Tanner Jo",
    "wof:placetype":"venue"
},
  "geometry": {"coordinates":[147.27130126899999,-42.8434333801],"type":"Point"}
}