{
  "type": "Feature",
  "properties": {
    "iso:country":"AU",
    "sg:address":"31 Evenwood St",
    "sg:city":"Coopers Plains",
    "sg:classifiers":[
        {
            "category":"Professional",
            "subcategory":"Art Services",
            "type":"Services"
        }
    ],
    "sg:phone":"+61 7 3344 3308",
    "sg:postcode":"4108",
    "sg:province":"QLD",
    "sg:tags":[
        "decorator",
        "painter"
    ],
    "wof:name":"Quality Assured Painting",
    "wof:placetype":"venue"
},
  "geometry": {"coordinates":[153.03941345199999,-27.573600769],"type":"Point"}
}