{
  "type": "Feature",
  "properties": {
    "addr:full":"Lot 6 William St Cowra NSW 2794",
    "addr:housenumber":"6",
    "addr:postcode":"2794",
    "addr:street":"William St",
    "iso:country":"AU",
    "sg:address":"Lot 6 William St",
    "sg:city":"Cowra",
    "sg:classifiers":[
        {
            "category":"Social Services",
            "subcategory":"Child Care",
            "type":"Services"
        }
    ],
    "sg:phone":"+61 2 6341 1156",
    "sg:postcode":"2794",
    "sg:province":"NSW",
    "wof:name":"Mobile Service",
    "wof:placetype":"venue"
},
  "geometry": {"coordinates":[148.67417907699999,-33.8397483826],"type":"Point"}
}