{
  "type": "Feature",
  "properties": {
    "addr:full":"70 Melbourne Rd Riverstone NSW 2765",
    "addr:housenumber":"70",
    "addr:postcode":"2765",
    "addr:street":"Melbourne Rd",
    "iso:country":"AU",
    "sg:address":"70 Melbourne Rd",
    "sg:city":"Riverstone",
    "sg:classifiers":[
        {
            "category":"Mining & Drilling",
            "type":"Manufacturing & Wholesale Goods"
        }
    ],
    "sg:phone":"+61 2 9627 7497",
    "sg:postcode":"2765",
    "sg:province":"NSW",
    "sg:tags":[
        "concrete",
        "breaking",
        "grinding",
        "sawing"
    ],
    "wof:name":"Uppercut Concrete Drilling & Sawing",
    "wof:placetype":"venue"
},
  "geometry": {"coordinates":[150.86026000999999,-33.6621398926],"type":"Point"}
}