{
  "type": "Feature",
  "properties": {
    "addr:full":"63 Carmen Drv Carlingford NSW 2118",
    "addr:housenumber":"63",
    "addr:postcode":"2118",
    "addr:street":"Carmen Drv",
    "iso:country":"AU",
    "sg:address":"63 Carmen Drv",
    "sg:city":"Carlingford",
    "sg:classifiers":[
        {
            "category":"Professional",
            "subcategory":"Accounting & Tax Preparation",
            "type":"Services"
        }
    ],
    "sg:phone":"+61 2 9871 5969",
    "sg:postcode":"2118",
    "sg:province":"NSW",
    "sg:tags":[
        "consultant",
        "taxation"
    ],
    "wof:name":"Gray Philip",
    "wof:placetype":"venue"
},
  "geometry": {"coordinates":[151.037643433,-33.7622795105],"type":"Point"}
}