{
  "type": "Feature",
  "properties": {
    "iso:country":"AU",
    "sg:address":"3 Mundon Pl",
    "sg:city":"West Pennant Hills",
    "sg:classifiers":[
        {
            "category":"Professional",
            "subcategory":"Management & Consulting",
            "type":"Services"
        }
    ],
    "sg:phone":"+61 2 9873 4390",
    "sg:postcode":"2125",
    "sg:province":"NSW",
    "sg:tags":[
        "consultant",
        "educational"
    ],
    "wof:name":"Innovations Pride",
    "wof:placetype":"venue"
},
  "geometry": {"coordinates":[151.04145813,-33.7587471008],"type":"Point"}
}