{
  "type": "Feature",
  "properties": {
    "iso:country":"AU",
    "sg:address":"4b Murchison St",
    "sg:city":"Marysville",
    "sg:classifiers":[
        {
            "category":"Personal",
            "subcategory":"Beauty Salon",
            "type":"Services"
        }
    ],
    "sg:phone":"+61 3 5963 3739",
    "sg:postcode":"3779",
    "sg:province":"VIC",
    "sg:tags":[
        "hairdresser"
    ],
    "wof:name":"Lettuce Do Hair",
    "wof:placetype":"venue"
},
  "geometry": {"coordinates":[145.74589499999999,-37.510464],"type":"Point"}
}