{
  "type": "Feature",
  "properties": {
    "addr:full":"1 Wells St Frankston VIC 3199",
    "addr:housenumber":"1",
    "addr:postcode":"3199",
    "addr:street":"Wells St",
    "iso:country":"AU",
    "sg:address":"1 Wells St",
    "sg:city":"Frankston",
    "sg:classifiers":[
        {
            "category":"Health Services",
            "subcategory":"Dentist",
            "type":"Services"
        }
    ],
    "sg:phone":"+61 3 9783 4422",
    "sg:postcode":"3199",
    "sg:province":"VIC",
    "sg:tags":[
        "dental",
        "prosthetist"
    ],
    "wof:name":"Greg Sharman Dental Prosthetist",
    "wof:placetype":"venue"
},
  "geometry": {"coordinates":[145.088790894,-37.819152832],"type":"Point"}
}