{
  "type": "Feature",
  "properties": {
    "addr:full":"Unit 6 19 Oxleigh Drv Malaga WA 6090",
    "addr:housenumber":"19",
    "addr:postcode":"6090",
    "addr:street":"Oxleigh Drv",
    "iso:country":"AU",
    "sg:address":"Unit 6 19 Oxleigh Drv",
    "sg:city":"Malaga",
    "sg:classifiers":[
        {
            "category":"Building & Trades",
            "subcategory":"Construction",
            "type":"Services"
        }
    ],
    "sg:phone":"+61 8 9249 3333",
    "sg:postcode":"6090",
    "sg:province":"WA",
    "sg:tags":[
        "contractor"
    ],
    "wof:name":"Easy Living Homes",
    "wof:placetype":"venue"
},
  "geometry": {"coordinates":[115.88583374,-31.8513393402],"type":"Point"}
}