{
  "type": "Feature",
  "properties": {
    "addr:full":"Ballina Central Shop 26/ 44 Pacific Hwy Ballina NSW 2478",
    "addr:housenumber":"26 / 44",
    "addr:postcode":"2478",
    "addr:street":"Pacific Hwy",
    "iso:country":"AU",
    "sg:address":"Ballina Central Shop 26/ 44 Pacific Hwy",
    "sg:city":"Ballina",
    "sg:classifiers":[
        {
            "category":"Health Services",
            "subcategory":"Dentist",
            "type":"Services"
        }
    ],
    "sg:phone":"+61 2 6681 6680",
    "sg:postcode":"2478",
    "sg:province":"NSW",
    "wof:name":"Bytes Dental",
    "wof:placetype":"venue"
},
  "geometry": {"coordinates":[153.51048278799999,-28.8644638062],"type":"Point"}
}