{
  "type": "Feature",
  "properties": {
    "iso:country":"AU",
    "sg:address":"678 North East Rd",
    "sg:city":"Holden Hill",
    "sg:classifiers":[
        {
            "category":"Wholesale",
            "subcategory":"Construction Materials",
            "type":"Manufacturing & Wholesale Goods"
        }
    ],
    "sg:phone":"+61 8 8266 3723",
    "sg:postcode":"5088",
    "sg:province":"SA",
    "sg:tags":[
        "protective",
        "coating"
    ],
    "wof:name":"L P H Painting Co Pty Ltd",
    "wof:placetype":"venue"
},
  "geometry": {"coordinates":[138.667114258,-34.8516426086],"type":"Point"}
}