{
  "type": "Feature",
  "properties": {
    "iso:country":"AU",
    "sg:address":"45 Primrose St",
    "sg:city":"Grange",
    "sg:classifiers":[
        {
            "category":"Professional",
            "subcategory":"Detective & Security Services",
            "type":"Services"
        }
    ],
    "sg:phone":"+61 7 3236 9810",
    "sg:postcode":"4051",
    "sg:province":"QLD",
    "sg:tags":[
        "investigator"
    ],
    "wof:name":"Axiom-AIS",
    "wof:placetype":"venue"
},
  "geometry": {"coordinates":[153.01289367699999,-27.4285430908],"type":"Point"}
}