{
  "type": "Feature",
  "properties": {
    "iso:country":"AU",
    "sg:address":"69 Kewdale Rd",
    "sg:city":"Welshpool",
    "sg:classifiers":[
        {
            "category":"Manufacturing",
            "subcategory":"Tools & Machinery",
            "type":"Manufacturing & Wholesale Goods"
        }
    ],
    "sg:phone":"+61 8 9352 3360",
    "sg:postcode":"6106",
    "sg:province":"WA",
    "sg:tags":[
        "abrasive"
    ],
    "wof:name":"Flexovit/Norton Abrasives",
    "wof:placetype":"venue"
},
  "geometry": {"coordinates":[115.954162598,-31.9847049713],"type":"Point"}
}