{
  "type": "Feature",
  "properties": {
    "addr:full":"327 Main North Rd Enfield SA 5085",
    "addr:housenumber":"327",
    "addr:postcode":"5085",
    "addr:street":"Main North Rd",
    "iso:country":"AU",
    "sg:address":"327 Main North Rd",
    "sg:city":"Enfield",
    "sg:classifiers":[
        {
            "category":"Autos & Motor Vehicles",
            "subcategory":"Auto Supplies",
            "type":"Retail Goods"
        }
    ],
    "sg:phone":"+61 8 8344 9833",
    "sg:postcode":"5085",
    "sg:province":"SA",
    "sg:tags":[
        "accessory"
    ],
    "wof:name":"Autopro",
    "wof:placetype":"venue"
},
  "geometry": {"coordinates":[138.601837158,-34.8676986694],"type":"Point"}
}