{
  "type": "Feature",
  "properties": {
    "addr:full":"137 High Rd Burpengary QLD 4505",
    "addr:housenumber":"137",
    "addr:postcode":"4505",
    "addr:street":"High Rd",
    "iso:country":"AU",
    "sg:address":"137 High Rd",
    "sg:city":"Burpengary",
    "sg:classifiers":[
        {
            "category":"Building & Trades",
            "subcategory":"Plumbing",
            "type":"Services"
        }
    ],
    "sg:phone":"+61 412 747 717",
    "sg:postcode":"4505",
    "sg:province":"QLD",
    "sg:tags":[
        "plumber",
        "gasfitters"
    ],
    "wof:name":"Martin's Gas Service",
    "wof:placetype":"venue"
},
  "geometry": {"coordinates":[153.020874023,-27.1337947845],"type":"Point"}
}