{
  "type": "Feature",
  "properties": {
    "addr:full":"143 Makebery St Coleraine VIC 3315",
    "addr:housenumber":"143",
    "addr:postcode":"3315",
    "addr:street":"Makebery St",
    "iso:country":"AU",
    "sg:address":"143 Makebery St",
    "sg:city":"Coleraine",
    "sg:classifiers":[
        {
            "category":"Building & Trades",
            "subcategory":"Plumbing",
            "type":"Services"
        }
    ],
    "sg:phone":"+61 417 512 705",
    "sg:postcode":"3315",
    "sg:province":"VIC",
    "sg:tags":[
        "plumber",
        "gasfitters"
    ],
    "wof:name":"Dave Joss",
    "wof:placetype":"venue"
},
  "geometry": {"coordinates":[141.68251037600001,-37.6034851074],"type":"Point"}
}