{
  "type": "Feature",
  "properties": {
    "addr:full":"14 Hinkler Rd Mordialloc VIC 3195",
    "addr:housenumber":"14",
    "addr:postcode":"3195",
    "addr:street":"Hinkler Rd",
    "iso:country":"AU",
    "sg:address":"14 Hinkler Rd",
    "sg:city":"Mordialloc",
    "sg:classifiers":[
        {
            "category":"Home & Garden",
            "subcategory":"Hardware",
            "type":"Retail Goods"
        }
    ],
    "sg:phone":"+61 3 9580 3202",
    "sg:postcode":"3195",
    "sg:province":"VIC",
    "sg:tags":[
        "pumping",
        "contractor"
    ],
    "wof:name":"R.S. Gray Electrical & Mechanical Services",
    "wof:placetype":"venue"
},
  "geometry": {"coordinates":[145.09930419899999,-37.9879112244],"type":"Point"}
}