{
  "type": "Feature",
  "properties": {
    "addr:full":"18 Gray St Kogarah NSW 2217",
    "addr:housenumber":"18",
    "addr:postcode":"2217",
    "addr:street":"Gray St",
    "iso:country":"AU",
    "sg:address":"18 Gray St",
    "sg:city":"Kogarah",
    "sg:classifiers":[
        {
            "category":"Social Services",
            "subcategory":"Child Care",
            "type":"Services"
        }
    ],
    "sg:phone":"+61 2 9587 6474",
    "sg:postcode":"2217",
    "sg:province":"NSW",
    "wof:name":"Kogarah Uniting Church Long Day Care Centre",
    "wof:placetype":"venue"
},
  "geometry": {"coordinates":[151.131653,-33.966133],"type":"Point"}
}