{
  "type": "Feature",
  "properties": {
    "addr:full":"73 Rowan St Manilla NSW 2346",
    "addr:housenumber":"73",
    "addr:postcode":"2346",
    "addr:street":"Rowan St",
    "iso:country":"AU",
    "sg:address":"73 Rowan St",
    "sg:city":"Manilla",
    "sg:classifiers":[
        {
            "category":"Food & Beverages",
            "subcategory":"Farmers Market",
            "type":"Retail Goods"
        }
    ],
    "sg:phone":"+61 2 6785 1247",
    "sg:postcode":"2346",
    "sg:province":"NSW",
    "sg:tags":[
        "beekeeper"
    ],
    "wof:name":"Dutton I H & I E M",
    "wof:placetype":"venue"
},
  "geometry": {"coordinates":[150.72239685100001,-30.7481536865],"type":"Point"}
}