{
  "type": "Feature",
  "properties": {
    "addr:full":"46 Logan Rd Woolloongabba QLD 4102",
    "addr:housenumber":"46",
    "addr:postcode":"4102",
    "addr:street":"Logan Rd",
    "iso:country":"AU",
    "sg:address":"46 Logan Rd",
    "sg:city":"Woolloongabba",
    "sg:classifiers":[
        {
            "category":"Professional",
            "subcategory":"Employment Agencies",
            "type":"Services"
        }
    ],
    "sg:phone":"+61 1300 366 606",
    "sg:postcode":"4102",
    "sg:province":"QLD",
    "sg:tags":[
        "hire",
        "labour",
        "contractor"
    ],
    "wof:name":"Skilled",
    "wof:placetype":"venue"
},
  "geometry": {"coordinates":[153.03846740700001,-27.4892234802],"type":"Point"}
}