{
  "type": "Feature",
  "properties": {
    "iso:country":"AU",
    "sg:address":"25 Fitzroy St",
    "sg:city":"Kerang",
    "sg:classifiers":[
        {
            "category":"Autos & Motor Vehicles",
            "subcategory":"Automobile Sales",
            "type":"Retail Goods"
        }
    ],
    "sg:phone":"+61 3 5452 2022",
    "sg:postcode":"3579",
    "sg:province":"VIC",
    "sg:tags":[
        "car",
        "used"
    ],
    "wof:name":"Franzini A Pty Ltd",
    "wof:placetype":"venue"
},
  "geometry": {"coordinates":[143.919021606,-35.7338485718],"type":"Point"}
}