{
  "type": "Feature",
  "properties": {
    "addr:full":"Longwood Rd Longwood VIC 3665",
    "addr:postcode":"3665",
    "addr:street":"Longwood Rd",
    "iso:country":"AU",
    "sg:address":"Longwood Rd",
    "sg:city":"Longwood",
    "sg:classifiers":[
        {
            "category":"Building & Trades",
            "subcategory":"Construction",
            "type":"Services"
        }
    ],
    "sg:phone":"+61 3 5798 5412",
    "sg:postcode":"3665",
    "sg:province":"VIC",
    "sg:tags":[
        "earth",
        "excavating",
        "moving",
        "contractor"
    ],
    "wof:name":"Steve Wright",
    "wof:placetype":"venue"
},
  "geometry": {"coordinates":[145.398925781,-36.8306999207],"type":"Point"}
}