{
  "type": "Feature",
  "properties": {
    "addr:full":"U2/ 147 Park Rd Woolloongabba QLD 4102",
    "addr:housenumber":"147",
    "addr:postcode":"4102",
    "addr:street":"U2 /;Park Rd",
    "iso:country":"AU",
    "sg:address":"U2/ 147 Park Rd",
    "sg:city":"Woolloongabba",
    "sg:classifiers":[
        {
            "category":"Shopping",
            "subcategory":"Musical Instruments",
            "type":"Retail Goods"
        }
    ],
    "sg:phone":"+61 7 3392 3412",
    "sg:postcode":"4102",
    "sg:province":"QLD",
    "sg:tags":[
        "musician",
        "agent"
    ],
    "wof:name":"Rockin Records",
    "wof:placetype":"venue"
},
  "geometry": {"coordinates":[153.03184509299999,-27.492521286],"type":"Point"}
}