{
  "type": "Feature",
  "properties": {
    "iso:country":"AU",
    "sg:address":"1257 Anzac Ave",
    "sg:city":"Kallangur",
    "sg:classifiers":[
        {
            "category":"Retail",
            "subcategory":"Auto Repair",
            "type":"Services"
        }
    ],
    "sg:phone":"+61 7 3285 2941",
    "sg:postcode":"4503",
    "sg:province":"QLD",
    "sg:tags":[
        "electrical"
    ],
    "wof:name":"Roadside Auto Care",
    "wof:placetype":"venue"
},
  "geometry": {"coordinates":[152.99732971200001,-27.2496070862],"type":"Point"}
}