{
  "type": "Feature",
  "properties": {
    "addr:full":"Kentish Rd Gawler Belt SA 5118",
    "addr:postcode":"5118",
    "addr:street":"Kentish Rd",
    "iso:country":"AU",
    "sg:address":"Kentish Rd",
    "sg:city":"Gawler Belt",
    "sg:classifiers":[
        {
            "category":"Education",
            "subcategory":"School",
            "type":"Public Place"
        }
    ],
    "sg:phone":"+61 8 8523 0088",
    "sg:postcode":"5118",
    "sg:province":"SA",
    "wof:name":"Xavier College",
    "wof:placetype":"venue"
},
  "geometry": {"coordinates":[138.733047,-34.574486],"type":"Point"}
}