{
  "type": "Feature",
  "properties": {
    "addr:full":"43 Station St Wentworthville NSW 2145",
    "addr:housenumber":"43",
    "addr:postcode":"2145",
    "addr:street":"Station St",
    "iso:country":"AU",
    "sg:address":"43 Station St",
    "sg:city":"Wentworthville",
    "sg:classifiers":[
        {
            "category":"Real Estate",
            "subcategory":"Real Estate Agent",
            "type":"Services"
        }
    ],
    "sg:phone":"+61 2 9896 0200",
    "sg:postcode":"2145",
    "sg:province":"NSW",
    "wof:name":"Ray White Wentworthville",
    "wof:placetype":"venue"
},
  "geometry": {"coordinates":[150.971969605,-33.8080024719],"type":"Point"}
}