{
  "type": "Feature",
  "properties": {
    "addr:full":"18 Delmont Ave Altona VIC 3018",
    "addr:housenumber":"18",
    "addr:postcode":"3018",
    "addr:street":"Delmont Ave",
    "iso:country":"AU",
    "sg:address":"18 Delmont Ave",
    "sg:city":"Altona",
    "sg:classifiers":[
        {
            "category":"Professional",
            "subcategory":"Accounting & Tax Preparation",
            "type":"Services"
        }
    ],
    "sg:phone":"+61 3 9315 9798",
    "sg:postcode":"3018",
    "sg:province":"VIC",
    "sg:tags":[
        "bookkeeping"
    ],
    "wof:name":"Patricks Bookkeeping & Secretarial Service",
    "wof:placetype":"venue"
},
  "geometry": {"coordinates":[144.8150177,-37.8599739075],"type":"Point"}
}