{
  "type": "Feature",
  "properties": {
    "addr:full":"Shop 1038 , Indooroopilly Shopping Ctr Indooroopilly QLD 4068",
    "addr:housenumber":"1038",
    "addr:postcode":"4068",
    "addr:street":"Indooroopilly Shopping Ctr",
    "iso:country":"AU",
    "sg:address":"Shop 1038",
    "sg:city":", Indooroopilly Shopping Ctr Indooroopilly",
    "sg:classifiers":[
        {
            "category":"Shopping",
            "subcategory":"Mobile Phones",
            "type":"Retail Goods"
        }
    ],
    "sg:phone":"+61 7 3018 4504",
    "sg:postcode":"4068",
    "sg:province":"QLD",
    "sg:tags":[
        "telephone",
        "accessory"
    ],
    "wof:name":"Vodafone",
    "wof:placetype":"venue"
},
  "geometry": {"coordinates":[152.99017334000001,-27.4945602417],"type":"Point"}
}