{
  "type": "Feature",
  "properties": {
    "addr:full":"34 Kananook Crs Belmont North NSW 2280",
    "addr:housenumber":"34",
    "addr:postcode":"2280",
    "addr:street":"Kananook Crs",
    "iso:country":"AU",
    "sg:address":"34 Kananook Crs",
    "sg:city":"Belmont North",
    "sg:classifiers":[
        {
            "category":"Autos & Motor Vehicles",
            "subcategory":"Auto Supplies",
            "type":"Retail Goods"
        }
    ],
    "sg:phone":"+61 419 616 637",
    "sg:postcode":"2280",
    "sg:province":"NSW",
    "sg:tags":[
        "accessory"
    ],
    "wof:name":"Chisel's Striping & Graphics",
    "wof:placetype":"venue"
},
  "geometry": {"coordinates":[151.66792297399999,-33.0193481445],"type":"Point"}
}