{
  "type": "Feature",
  "properties": {
    "iso:country":"AU",
    "sg:address":"1236 Glen Huntly Rd",
    "sg:city":"Glen Huntly",
    "sg:classifiers":[
        {
            "category":"Manufacturing",
            "subcategory":"Textiles",
            "type":"Manufacturing & Wholesale Goods"
        }
    ],
    "sg:phone":"+61 3 9571 7666",
    "sg:postcode":"3163",
    "sg:province":"VIC",
    "sg:tags":[
        "wholesaler",
        "knitwear",
        "mfrs"
    ],
    "wof:name":"Besserman Knitwear",
    "wof:placetype":"venue"
},
  "geometry": {"coordinates":[145.04560852,-37.8899345398],"type":"Point"}
}