{
  "type": "Feature",
  "properties": {
    "iso:country":"AU",
    "sg:address":"2/ 76 Smith St",
    "sg:city":"Darwin",
    "sg:classifiers":[
        {
            "category":"Personal",
            "subcategory":"Beauty Salon",
            "type":"Services"
        }
    ],
    "sg:phone":"+61 8 8981 5166",
    "sg:postcode":"0800",
    "sg:province":"NT",
    "sg:tags":[
        "hairdresser"
    ],
    "wof:name":"Stylecuts 4 U",
    "wof:placetype":"venue"
},
  "geometry": {"coordinates":[130.83914184599999,-12.4607334137],"type":"Point"}
}