{
  "type": "Feature",
  "properties": {
    "iso:country":"AU",
    "sg:address":"162 Pitt Rd",
    "sg:city":"Curl Curl",
    "sg:classifiers":[
        {
            "category":"Building & Trades",
            "subcategory":"Construction",
            "type":"Services"
        }
    ],
    "sg:phone":"+61 419 997 335",
    "sg:postcode":"2096",
    "sg:province":"NSW",
    "sg:tags":[
        "roof"
    ],
    "wof:name":"Niland Roofing",
    "wof:placetype":"venue"
},
  "geometry": {"coordinates":[151.28521728499999,-33.7638587952],"type":"Point"}
}