{
  "type": "Feature",
  "properties": {
    "iso:country":"AU",
    "sg:address":"584 Pacific Hwy",
    "sg:city":"Belmont",
    "sg:classifiers":[
        {
            "category":"Banks & Credit Unions",
            "subcategory":"Bank",
            "type":"Services"
        }
    ],
    "sg:phone":"+61 2 4945 3511",
    "sg:postcode":"2280",
    "sg:province":"NSW",
    "wof:name":"St George Bank Limited",
    "wof:placetype":"venue"
},
  "geometry": {"coordinates":[151.65992736800001,-33.03673172],"type":"Point"}
}