{
  "type": "Feature",
  "properties": {
    "iso:country":"AU",
    "sg:address":"7 Commercial Drv",
    "sg:city":"Thomastown",
    "sg:classifiers":[
        {
            "category":"Manufacturing",
            "subcategory":"Motor Vehicles & Parts",
            "type":"Manufacturing & Wholesale Goods"
        }
    ],
    "sg:phone":"+61 3 9465 1366",
    "sg:postcode":"3074",
    "sg:province":"VIC",
    "sg:tags":[
        "replacement"
    ],
    "wof:name":"A AA Ace Auto Salvage",
    "wof:placetype":"venue"
},
  "geometry": {"coordinates":[145.04049682600001,-37.6931114197],"type":"Point"}
}