{
  "type": "Feature",
  "properties": {
    "iso:country":"AU",
    "sg:address":"Sports Medicine Glengarry 64 Arnisdale Rd",
    "sg:city":"Duncraig",
    "sg:classifiers":[
        {
            "category":"Health Services",
            "subcategory":"Doctor",
            "type":"Services"
        }
    ],
    "sg:phone":"+61 8 9246 4055",
    "sg:postcode":"6023",
    "sg:province":"WA",
    "sg:tags":[
        "medical",
        "practitioner"
    ],
    "wof:name":"Geddes Anthony Mr",
    "wof:placetype":"venue"
},
  "geometry": {"coordinates":[115.782043457,-31.8295669556],"type":"Point"}
}