{
  "type": "Feature",
  "properties": {
    "iso:country":"AU",
    "sg:address":"31 Malcolm St",
    "sg:city":"West Perth",
    "sg:classifiers":[
        {
            "category":"Arts & Performance",
            "subcategory":"Art Gallery",
            "type":"Entertainment"
        }
    ],
    "sg:phone":"+61 8 9324 2460",
    "sg:postcode":"6005",
    "sg:province":"WA",
    "wof:name":"Goddard De Fiddes Gallery",
    "wof:placetype":"venue"
},
  "geometry": {"coordinates":[115.847358704,-31.9530849457],"type":"Point"}
}