{
  "type": "Feature",
  "properties": {
    "iso:country":"AU",
    "sg:address":"Cnr Hassal & Alexandria Sts",
    "sg:city":"Westmead",
    "sg:classifiers":[
        {
            "category":"Retail",
            "subcategory":"Auto Repair",
            "type":"Services"
        }
    ],
    "sg:phone":"+61 2 9635 6658",
    "sg:postcode":"2145",
    "sg:province":"NSW",
    "sg:tags":[
        "repairer",
        "motor",
        "engineer"
    ],
    "wof:name":"Bonham Mechanical Repairs",
    "wof:placetype":"venue"
},
  "geometry": {"coordinates":[150.98710632300001,-33.8080406189],"type":"Point"}
}