{
  "type": "Feature",
  "properties": {
    "iso:country":"AU",
    "sg:address":"Unit 4 15 Hampden Rd",
    "sg:city":"Artarmon",
    "sg:classifiers":[
        {
            "category":"Real Estate",
            "subcategory":"Architect",
            "type":"Services"
        }
    ],
    "sg:phone":"+61 2 9419 7039",
    "sg:postcode":"2064",
    "sg:province":"NSW",
    "wof:name":"Bassarov Architects Pty Ltd",
    "wof:placetype":"venue"
},
  "geometry": {"coordinates":[151.18800354000001,-33.8116149902],"type":"Point"}
}