{
  "type": "Feature",
  "properties": {
    "addr:full":"1130 Anzac Pde Maroubra NSW 2035",
    "addr:housenumber":"1130",
    "addr:postcode":"2035",
    "addr:street":"Anzac Pde",
    "iso:country":"AU",
    "sg:address":"1130 Anzac Pde",
    "sg:city":"Maroubra",
    "sg:classifiers":[
        {
            "category":"Education",
            "subcategory":"School",
            "type":"Public Place"
        }
    ],
    "sg:phone":"+61 2 9311 3340",
    "sg:postcode":"2035",
    "sg:province":"NSW",
    "wof:name":"St Spyridon College High School",
    "wof:placetype":"venue"
},
  "geometry": {"coordinates":[151.24232482900001,-33.9526786804],"type":"Point"}
}