{
  "type": "Feature",
  "properties": {
    "addr:full":"29 Washington Drv Mildura VIC 3500",
    "addr:housenumber":"29",
    "addr:postcode":"3500",
    "addr:street":"Washington Drv",
    "iso:country":"AU",
    "sg:address":"29 Washington Drv",
    "sg:city":"Mildura",
    "sg:classifiers":[
        {
            "category":"Shopping",
            "subcategory":"Computers & Home Electronics",
            "type":"Retail Goods"
        }
    ],
    "sg:phone":"+61 3 5022 7100",
    "sg:postcode":"3500",
    "sg:province":"VIC",
    "sg:tags":[
        "hi-fi",
        "equipment"
    ],
    "wof:name":"Sunraysia Smart Homes",
    "wof:placetype":"venue"
},
  "geometry": {"coordinates":[142.152786255,-34.1711463928],"type":"Point"}
}