{
  "type": "Feature",
  "properties": {
    "addr:full":"Curtin University, Kent St Bentley WA 6102",
    "addr:postcode":"6102",
    "addr:street":"Kent St",
    "iso:country":"AU",
    "sg:address":"Curtin University, Kent St",
    "sg:city":"Bentley",
    "sg:classifiers":[
        {
            "category":"Education",
            "subcategory":"University",
            "type":"Public Place"
        }
    ],
    "sg:phone":"+61 8 9266 2900",
    "sg:postcode":"6102",
    "sg:province":"WA",
    "sg:tags":[
        "college",
        "tertiary"
    ],
    "wof:name":"Curtin Student Guild",
    "wof:placetype":"venue"
},
  "geometry": {"coordinates":[115.88838958700001,-32.0050468445],"type":"Point"}
}