{
  "type": "Feature",
  "properties": {
    "addr:full":"Shop 1012 Westfield Shoppingtown Hornsby NSW 2077",
    "addr:housenumber":"1012",
    "addr:postcode":"2077",
    "addr:street":"Westfield Shoppingtown",
    "iso:country":"AU",
    "sg:address":"Shop 1012 Westfield Shoppingtown",
    "sg:city":"Hornsby",
    "sg:classifiers":[
        {
            "category":"Retail",
            "subcategory":"Repair Shop",
            "type":"Services"
        }
    ],
    "sg:phone":"+61 2 9476 6605",
    "sg:postcode":"2077",
    "sg:province":"NSW",
    "sg:tags":[
        "cleaner",
        "part",
        "vacuum"
    ],
    "wof:name":"Godfreys",
    "wof:placetype":"venue"
},
  "geometry": {"coordinates":[151.09687805199999,-33.7007789612],"type":"Point"}
}