{
  "type": "Feature",
  "properties": {
    "addr:full":"Cnr of new England High Way &Mayfair Lane La & New England Hwy Stanthorpe QLD 4380",
    "addr:postcode":"4380",
    "addr:street":"High Way & Mayfair Lane;Hwy",
    "iso:country":"AU",
    "sg:address":"Cnr of new England High Way &Mayfair Lane La & New England Hwy",
    "sg:city":"Stanthorpe",
    "sg:classifiers":[
        {
            "category":"Fast Food",
            "type":"Food & Drink"
        }
    ],
    "sg:phone":"+61 7 4681 0422",
    "sg:postcode":"4380",
    "sg:province":"QLD",
    "sg:tags":[
        "away",
        "take"
    ],
    "wof:name":"McDonald's Family Restaurants",
    "wof:placetype":"venue"
},
  "geometry": {"coordinates":[151.95164500000001,-28.628773],"type":"Point"}
}