{
  "type": "Feature",
  "properties": {
    "iso:country":"AU",
    "sg:address":"Cnr Ipswich Rd & Cornwall St",
    "sg:city":"Buranda",
    "sg:classifiers":[
        {
            "category":"Sports & Exercise",
            "subcategory":"Gym",
            "type":"Entertainment"
        }
    ],
    "sg:phone":"+61 7 3891 6746",
    "sg:postcode":"4102",
    "sg:province":"QLD",
    "sg:tags":[
        "health",
        "fitness"
    ],
    "wof:name":"Movements Fitness Centre",
    "wof:placetype":"venue"
},
  "geometry": {"coordinates":[153.03518676799999,-27.5005073547],"type":"Point"}
}