{
  "type": "Feature",
  "properties": {
    "addr:full":"8 Willunga Pl West Pennant Hills NSW 2125",
    "addr:housenumber":"8",
    "addr:postcode":"2125",
    "addr:street":"Willunga Pl",
    "iso:country":"AU",
    "sg:address":"8 Willunga Pl",
    "sg:city":"West Pennant Hills",
    "sg:classifiers":[
        {
            "category":"Professional",
            "subcategory":"Business Services",
            "type":"Services"
        }
    ],
    "sg:phone":"+61 2 9680 7192",
    "sg:postcode":"2125",
    "sg:province":"NSW",
    "sg:tags":[
        "exporter"
    ],
    "wof:name":"Benore Pty Ltd",
    "wof:placetype":"venue"
},
  "geometry": {"coordinates":[151.02708435100001,-33.7377128601],"type":"Point"}
}