{
  "type": "Feature",
  "properties": {
    "addr:full":"165 Acland St St Kilda VIC 3182",
    "addr:housenumber":"165",
    "addr:postcode":"3182",
    "addr:street":"Acland St",
    "iso:country":"AU",
    "sg:address":"165 Acland St",
    "sg:city":"St Kilda",
    "sg:classifiers":[
        {
            "category":"Food & Beverages",
            "subcategory":"Specialty",
            "type":"Retail Goods"
        }
    ],
    "sg:phone":"+61 3 9534 4646",
    "sg:postcode":"3182",
    "sg:province":"VIC",
    "sg:tags":[
        "product",
        "health"
    ],
    "wof:name":"GNC Live Well",
    "wof:placetype":"venue"
},
  "geometry": {"coordinates":[144.98016357399999,-37.8691635132],"type":"Point"}
}