{
  "type": "Feature",
  "properties": {
    "addr:full":"Cnr Osburn & Kendall Sts Wodonga VIC 3690",
    "addr:postcode":"3690",
    "addr:street":"Cnr",
    "iso:country":"AU",
    "sg:address":"Cnr Osburn & Kendall Sts",
    "sg:city":"Wodonga",
    "sg:classifiers":[
        {
            "category":"Home & Garden",
            "subcategory":"Carpets & Floor Coverings",
            "type":"Retail Goods"
        }
    ],
    "sg:phone":"+61 2 6056 3434",
    "sg:postcode":"3690",
    "sg:province":"VIC",
    "wof:name":"Floorworld",
    "wof:placetype":"venue"
},
  "geometry": {"coordinates":[146.888305664,-36.115776062],"type":"Point"}
}