{
  "type": "Feature",
  "properties": {
    "addr:full":"Level 5 / 207 Kent St Sydney NSW 2000",
    "addr:housenumber":"/ 207",
    "addr:postcode":"2000",
    "addr:street":"Kent St",
    "iso:country":"AU",
    "sg:address":"Level 5 / 207 Kent St",
    "sg:city":"Sydney",
    "sg:classifiers":[
        {
            "category":"Manufacturing",
            "subcategory":"Food",
            "type":"Manufacturing & Wholesale Goods"
        }
    ],
    "sg:phone":"+61 2 9247 0408",
    "sg:postcode":"2000",
    "sg:province":"NSW",
    "sg:tags":[
        "function",
        "catering"
    ],
    "wof:name":"Milestones Catering Service",
    "wof:placetype":"venue"
},
  "geometry": {"coordinates":[151.203857422,-33.863910675],"type":"Point"}
}