{
  "type": "Feature",
  "properties": {
    "addr:full":"80 Bay St Ultimo NSW 2007",
    "addr:housenumber":"80",
    "addr:postcode":"2007",
    "addr:street":"Bay St",
    "iso:country":"AU",
    "sg:address":"80 Bay St",
    "sg:city":"Ultimo",
    "sg:classifiers":[
        {
            "category":"Personal",
            "subcategory":"Beauty Salon",
            "type":"Services"
        }
    ],
    "sg:phone":"+61 2 9211 0499",
    "sg:postcode":"2007",
    "sg:province":"NSW",
    "sg:tags":[
        "hairdresser"
    ],
    "wof:name":"Imperial Hair Broadway",
    "wof:placetype":"venue"
},
  "geometry": {"coordinates":[151.195114136,-33.8835334778],"type":"Point"}
}