{
  "type": "Feature",
  "properties": {
    "addr:full":"Shop 2/ 127A Pine Ave Leeton NSW 2705",
    "addr:housenumber":"shop 2 / 127a",
    "addr:postcode":"2705",
    "addr:street":"Pine Ave",
    "iso:country":"AU",
    "sg:address":"Shop 2/ 127A Pine Ave",
    "sg:city":"Leeton",
    "sg:classifiers":[
        {
            "category":"Banks & Credit Unions",
            "subcategory":"Bank",
            "type":"Services"
        }
    ],
    "sg:phone":"+61 2 6953 8061",
    "sg:postcode":"2705",
    "sg:province":"NSW",
    "wof:name":"Resources Credit Union",
    "wof:placetype":"venue"
},
  "geometry": {"coordinates":[146.40545654300001,-34.5515708923],"type":"Point"}
}