{
  "type": "Feature",
  "properties": {
    "addr:full":"4 High St South Strathfield NSW 2136",
    "addr:housenumber":"4",
    "addr:postcode":"2136",
    "addr:street":"High St South",
    "iso:country":"AU",
    "sg:address":"4 High St",
    "sg:city":"South Strathfield",
    "sg:classifiers":[
        {
            "category":"Health Services",
            "subcategory":"Doctor",
            "type":"Services"
        }
    ],
    "sg:phone":"+61 2 9642 8495",
    "sg:postcode":"2136",
    "sg:province":"NSW",
    "sg:tags":[
        "medical",
        "practitioner"
    ],
    "wof:name":"Selim June Dr",
    "wof:placetype":"venue"
},
  "geometry": {"coordinates":[151.089233398,-33.8901748657],"type":"Point"}
}