{
  "type": "Feature",
  "properties": {
    "addr:full":"Shop 276 The Glen Shopng Cntr Glen Waverley VIC 3150",
    "addr:housenumber":"276",
    "addr:postcode":"3150",
    "addr:street":"The Glen;Cntr",
    "iso:country":"AU",
    "sg:address":"Shop 276",
    "sg:city":"The Glen Shopng Cntr Glen Waverley",
    "sg:classifiers":[
        {
            "category":"Health Services",
            "subcategory":"Optometrist",
            "type":"Services"
        }
    ],
    "sg:phone":"+61 3 9886 8800",
    "sg:postcode":"3150",
    "sg:province":"VIC",
    "wof:name":"Budget Eyewear",
    "wof:placetype":"venue"
},
  "geometry": {"coordinates":[145.16778564399999,-37.8688812256],"type":"Point"}
}