{
  "type": "Feature",
  "properties": {
    "iso:country":"AU",
    "sg:address":"Kerry Rd",
    "sg:city":"Beaudesert",
    "sg:classifiers":[
        {
            "category":"Building & Trades",
            "subcategory":"Construction",
            "type":"Services"
        }
    ],
    "sg:phone":"+61 7 5541 2444",
    "sg:postcode":"4285",
    "sg:province":"QLD",
    "sg:tags":[
        "contractor"
    ],
    "wof:name":"Moss M V & N L",
    "wof:placetype":"venue"
},
  "geometry": {"coordinates":[153.002197,-27.999414],"type":"Point"}
}