{
  "type": "Feature",
  "properties": {
    "addr:full":"45 Hayes St Bunbury WA 6230",
    "addr:housenumber":"45",
    "addr:postcode":"6230",
    "addr:street":"Hayes St",
    "iso:country":"AU",
    "sg:address":"45 Hayes St",
    "sg:city":"Bunbury",
    "sg:classifiers":[
        {
            "category":"Utilities",
            "subcategory":"Water",
            "type":"Services"
        }
    ],
    "sg:phone":"+61 8 9721 7788",
    "sg:postcode":"6230",
    "sg:province":"WA",
    "sg:tags":[
        "hot",
        "system"
    ],
    "wof:name":"Quantum Refrigeration",
    "wof:placetype":"venue"
},
  "geometry": {"coordinates":[115.646782,-33.328754],"type":"Point"}
}