{
  "type": "Feature",
  "properties": {
    "addr:full":"1 Malmsbury Drv Meadow Heights VIC 3048",
    "addr:housenumber":"1",
    "addr:postcode":"3048",
    "addr:street":"Malmsbury Drv",
    "iso:country":"AU",
    "sg:address":"1 Malmsbury Drv",
    "sg:city":"Meadow Heights",
    "sg:classifiers":[
        {
            "category":"Professional",
            "subcategory":"Art Services",
            "type":"Services"
        }
    ],
    "sg:phone":"+61 411 800 901",
    "sg:postcode":"3048",
    "sg:province":"VIC",
    "sg:tags":[
        "decorator",
        "painter"
    ],
    "wof:name":"B.E Issa Painting",
    "wof:placetype":"venue"
},
  "geometry": {"coordinates":[144.91449,-37.663258],"type":"Point"}
}