{
  "type": "Feature",
  "properties": {
    "iso:country":"AU",
    "sg:address":"2/ 131 Bedford St",
    "sg:city":"Newtown",
    "sg:classifiers":[
        {
            "category":"Arena",
            "subcategory":"Sports Club",
            "type":"Entertainment"
        }
    ],
    "sg:phone":"+61 421 340 560",
    "sg:postcode":"2042",
    "sg:province":"NSW",
    "sg:tags":[
        "defence",
        "supply",
        "self",
        "instruction",
        "martial art"
    ],
    "wof:name":"Murray's Martial Arts",
    "wof:placetype":"venue"
},
  "geometry": {"coordinates":[151.17300399999999,-33.895676],"type":"Point"}
}