{
  "type": "Feature",
  "properties": {
    "addr:full":"23 Alfonso St North Perth WA 6006",
    "addr:housenumber":"23",
    "addr:postcode":"6006",
    "addr:street":"Alfonso St",
    "iso:country":"AU",
    "sg:address":"23 Alfonso St",
    "sg:city":"North Perth",
    "sg:classifiers":[
        {
            "category":"Health Services",
            "subcategory":"Health Practitioner",
            "type":"Services"
        }
    ],
    "sg:phone":"+61 8 9328 6624",
    "sg:postcode":"6006",
    "sg:province":"WA",
    "sg:tags":[
        "pathologist",
        "speech"
    ],
    "wof:name":"Sherwood Mellanie",
    "wof:placetype":"venue"
},
  "geometry": {"coordinates":[115.85353088399999,-31.9345664978],"type":"Point"}
}