{
  "type": "Feature",
  "properties": {
    "iso:country":"AU",
    "sg:address":"1 Greaves St",
    "sg:city":"Dandenong",
    "sg:classifiers":[
        {
            "category":"Wholesale",
            "subcategory":"Farm Supplies",
            "type":"Manufacturing & Wholesale Goods"
        }
    ],
    "sg:phone":"+61 3 9792 3540",
    "sg:postcode":"3175",
    "sg:province":"VIC",
    "sg:tags":[
        "feed",
        "supplement",
        "stock"
    ],
    "wof:name":"Dandenong Stockfoods Claude Telford Pty Ltd",
    "wof:placetype":"venue"
},
  "geometry": {"coordinates":[145.20799255399999,-37.9914016724],"type":"Point"}
}