{
  "type": "Feature",
  "properties": {
    "addr:full":"88A High St Broadford VIC 3658",
    "addr:housenumber":"88a",
    "addr:postcode":"3658",
    "addr:street":"High St",
    "iso:country":"AU",
    "sg:address":"88A High St",
    "sg:city":"Broadford",
    "sg:classifiers":[
        {
            "category":"Health Services",
            "subcategory":"Chiropractor",
            "type":"Services"
        }
    ],
    "sg:phone":"+61 3 5784 3511",
    "sg:postcode":"3658",
    "sg:province":"VIC",
    "wof:name":"Broadford Chiropractic & Natural Health",
    "wof:placetype":"venue"
},
  "geometry": {"coordinates":[145.04864501899999,-37.2040405273],"type":"Point"}
}