{
  "type": "Feature",
  "properties": {
    "iso:country":"AU",
    "sg:address":"45 Russell St",
    "sg:city":"Toowoomba",
    "sg:classifiers":[
        {
            "category":"Shopping",
            "subcategory":"Clothing, Apparel, & Fashions",
            "type":"Retail Goods"
        }
    ],
    "sg:phone":"+61 7 4639 3687",
    "sg:postcode":"4350",
    "sg:province":"QLD",
    "sg:tags":[
        "lady",
        "wear"
    ],
    "wof:name":"Jo-Annes",
    "wof:placetype":"venue"
},
  "geometry": {"coordinates":[151.95282,-27.55888],"type":"Point"}
}