{
  "type": "Feature",
  "properties": {
    "addr:full":"165 Kesters Rd Para Hills SA 5096",
    "addr:housenumber":"165",
    "addr:postcode":"5096",
    "addr:street":"Kesters Rd Para",
    "iso:country":"AU",
    "sg:address":"165 Kesters Rd",
    "sg:city":"Para Hills",
    "sg:classifiers":[
        {
            "category":"Health Services",
            "subcategory":"Doctor",
            "type":"Services"
        }
    ],
    "sg:phone":"+61 8 8264 1322",
    "sg:postcode":"5096",
    "sg:province":"SA",
    "sg:tags":[
        "medical",
        "practitioner"
    ],
    "wof:name":"Northern Clinic",
    "wof:placetype":"venue"
},
  "geometry": {"coordinates":[138.64964294399999,-34.8071250916],"type":"Point"}
}