{
  "type": "Feature",
  "properties": {
    "addr:full":"208 Hutt St Adelaide SA 5000",
    "addr:housenumber":"208",
    "addr:postcode":"5000",
    "addr:street":"Hutt St",
    "iso:country":"AU",
    "sg:address":"208 Hutt St",
    "sg:city":"Adelaide",
    "sg:classifiers":[
        {
            "category":"Health Services",
            "subcategory":"Dentist",
            "type":"Services"
        }
    ],
    "sg:phone":"+61 8 8223 6921",
    "sg:postcode":"5000",
    "sg:province":"SA",
    "wof:name":"Lange Brian A",
    "wof:placetype":"venue"
},
  "geometry": {"coordinates":[138.61260986299999,-34.9325637817],"type":"Point"}
}