{
  "type": "Feature",
  "properties": {
    "addr:full":"Unit 2/ 22 Ironbark Cl Warabrook NSW 2304",
    "addr:housenumber":"22",
    "addr:postcode":"2304",
    "addr:street":"Ironbark Cl",
    "iso:country":"AU",
    "sg:address":"Unit 2/ 22",
    "sg:city":"Ironbark Cl Warabrook",
    "sg:classifiers":[
        {
            "category":"Train Station",
            "subcategory":"Light Rail",
            "type":"Transportation"
        }
    ],
    "sg:phone":"+61 2 4960 3273",
    "sg:postcode":"2304",
    "sg:province":"NSW",
    "sg:tags":[
        "survey",
        "traffic"
    ],
    "wof:name":"Asset Management Products & Services Pty Ltd",
    "wof:placetype":"venue"
},
  "geometry": {"coordinates":[151.80911254899999,-32.8621902466],"type":"Point"}
}