{
  "type": "Feature",
  "properties": {
    "iso:country":"AU",
    "sg:address":"1 Karkoo St",
    "sg:city":"Seaview Downs",
    "sg:classifiers":[
        {
            "category":"Building & Trades",
            "subcategory":"Cleaning & Sanitation",
            "type":"Services"
        }
    ],
    "sg:phone":"+61 405 421 095",
    "sg:postcode":"5049",
    "sg:province":"SA",
    "sg:tags":[
        "window"
    ],
    "wof:name":"Ove Hansen",
    "wof:placetype":"venue"
},
  "geometry": {"coordinates":[138.540131,-35.037594],"type":"Point"}
}