{
  "type": "Feature",
  "properties": {
    "iso:country":"AU",
    "sg:address":"233 George St",
    "sg:city":"Liverpool",
    "sg:classifiers":[
        {
            "category":"Education",
            "subcategory":"School",
            "type":"Public Place"
        }
    ],
    "sg:phone":"+61 2 9602 7377",
    "sg:postcode":"2170",
    "sg:province":"NSW",
    "sg:tags":[
        "supply"
    ],
    "wof:name":"Duckworths Stationery & School Supplies",
    "wof:placetype":"venue"
},
  "geometry": {"coordinates":[150.92449951200001,-33.9239654541],"type":"Point"}
}