{
  "type": "Feature",
  "properties": {
    "addr:full":"105 Sauls Rd Mandalong NSW 2264",
    "addr:housenumber":"105",
    "addr:postcode":"2264",
    "addr:street":"Sauls Rd",
    "iso:country":"AU",
    "sg:address":"105 Sauls Rd",
    "sg:city":"Mandalong",
    "sg:classifiers":[
        {
            "category":"Building & Trades",
            "subcategory":"Construction",
            "type":"Services"
        }
    ],
    "sg:phone":"+61 2 4977 3130",
    "sg:postcode":"2264",
    "sg:province":"NSW",
    "sg:tags":[
        "scaffolding"
    ],
    "wof:name":"Banks Hoardings Pty Ltd",
    "wof:placetype":"venue"
},
  "geometry": {"coordinates":[151.41764800000001,-33.110191],"type":"Point"}
}