{
  "type": "Feature",
  "properties": {
    "addr:full":"U4/ 80 Webster Rd Stafford QLD 4053",
    "addr:housenumber":"80",
    "addr:postcode":"4053",
    "addr:street":"U4 /;Webster Rd",
    "iso:country":"AU",
    "sg:address":"U4/ 80 Webster Rd",
    "sg:city":"Stafford",
    "sg:classifiers":[
        {
            "category":"Home & Garden",
            "subcategory":"Carpets & Floor Coverings",
            "type":"Retail Goods"
        }
    ],
    "sg:phone":"+61 7 3856 1300",
    "sg:postcode":"4053",
    "sg:province":"QLD",
    "sg:tags":[
        "tile",
        "wall"
    ],
    "wof:name":"Andersons Ceramics Stafford",
    "wof:placetype":"venue"
},
  "geometry": {"coordinates":[153.01588439899999,-27.4149494171],"type":"Point"}
}