{
  "type": "Feature",
  "properties": {
    "addr:full":"49-51 Inkerman St St Kilda VIC 3182",
    "addr:housenumber":"49-51",
    "addr:postcode":"3182",
    "addr:street":"Inkerman St",
    "iso:country":"AU",
    "sg:address":"49-51 Inkerman St",
    "sg:city":"St Kilda",
    "sg:classifiers":[
        {
            "category":"Home & Garden",
            "subcategory":"Furniture",
            "type":"Retail Goods"
        }
    ],
    "sg:phone":"+61 3 9537 1800",
    "sg:postcode":"3182",
    "sg:province":"VIC",
    "sg:tags":[
        "outdoor"
    ],
    "wof:name":"Zen Flowers & Garden",
    "wof:placetype":"venue"
},
  "geometry": {"coordinates":[144.98374939000001,-37.864490509],"type":"Point"}
}