{
  "type": "Feature",
  "properties": {
    "addr:full":"182 Parker St Cootamundra NSW 2590",
    "addr:housenumber":"182",
    "addr:postcode":"2590",
    "addr:street":"Parker St",
    "iso:country":"AU",
    "sg:address":"182 Parker St",
    "sg:city":"Cootamundra",
    "sg:classifiers":[
        {
            "category":"Professional",
            "subcategory":"Printing & Photocopies",
            "type":"Services"
        }
    ],
    "sg:phone":"+61 2 6942 4956",
    "sg:postcode":"2590",
    "sg:province":"NSW",
    "sg:tags":[
        "embroidery"
    ],
    "wof:name":"Baileyana Embroidery",
    "wof:placetype":"venue"
},
  "geometry": {"coordinates":[148.02178955100001,-34.641242981],"type":"Point"}
}