{
  "type": "Feature",
  "properties": {
    "addr:full":"PO Box 343 Edge Hill QLD 4870",
    "addr:postcode":"4870",
    "iso:country":"AU",
    "sg:address":"PO Box 343",
    "sg:city":"Edge Hill",
    "sg:classifiers":[
        {
            "category":"Professional",
            "subcategory":"Testing Lab",
            "type":"Services"
        }
    ],
    "sg:phone":"+61 7 4093 0740",
    "sg:postcode":"4870",
    "sg:province":"QLD",
    "sg:tags":[
        "inspection"
    ],
    "wof:name":"Plantown Building Inspections",
    "wof:placetype":"venue"
},
  "geometry": {"coordinates":[145.740066528,-16.9015407562],"type":"Point"}
}