{
  "type": "Feature",
  "properties": {
    "addr:full":"79 Gosport St Hemmant QLD 4174",
    "addr:housenumber":"79",
    "addr:postcode":"4174",
    "addr:street":"Gosport St",
    "iso:country":"AU",
    "sg:address":"79 Gosport St",
    "sg:city":"Hemmant",
    "sg:classifiers":[
        {
            "category":"Manufacturing",
            "subcategory":"Tools & Machinery",
            "type":"Manufacturing & Wholesale Goods"
        }
    ],
    "sg:phone":"+61 7 3348 7399",
    "sg:postcode":"4174",
    "sg:province":"QLD",
    "sg:tags":[
        "earth",
        "excavating",
        "moving",
        "equipment"
    ],
    "wof:name":"Fin Engineering",
    "wof:placetype":"venue"
},
  "geometry": {"coordinates":[153.132247925,-27.4394493103],"type":"Point"}
}