{
  "type": "Feature",
  "properties": {
    "addr:full":"511 Marrickville Rd Dulwich Hill NSW 2203",
    "addr:housenumber":"511",
    "addr:postcode":"2203",
    "addr:street":"Marrickville Rd",
    "iso:country":"AU",
    "sg:address":"511 Marrickville Rd",
    "sg:city":"Dulwich Hill",
    "sg:classifiers":[
        {
            "category":"Shopping",
            "subcategory":"Clothing, Apparel, & Fashions",
            "type":"Retail Goods"
        }
    ],
    "sg:phone":"+61 2 9569 1261",
    "sg:postcode":"2203",
    "sg:province":"NSW",
    "sg:tags":[
        "menswear"
    ],
    "wof:name":"Nicholas Menswear",
    "wof:placetype":"venue"
},
  "geometry": {"coordinates":[151.14262400000001,-33.903313],"type":"Point"}
}