{
  "type": "Feature",
  "properties": {
    "addr:full":"58a Wellington St Mackay QLD 4740",
    "addr:housenumber":"58a",
    "addr:postcode":"4740",
    "addr:street":"Wellington St",
    "iso:country":"AU",
    "sg:address":"58a Wellington St",
    "sg:city":"Mackay",
    "sg:classifiers":[
        {
            "category":"Health Services",
            "subcategory":"Health Practitioner",
            "type":"Services"
        }
    ],
    "sg:phone":"+61 7 4944 1208",
    "sg:postcode":"4740",
    "sg:province":"QLD",
    "sg:tags":[
        "naturopath"
    ],
    "wof:name":"Lifesprings Natural Medicine & Massage Clinic",
    "wof:placetype":"venue"
},
  "geometry": {"coordinates":[149.17950400000001,-21.148666],"type":"Point"}
}