{
  "type": "Feature",
  "properties": {
    "addr:full":"Cat & Fiddle Centre 407 Flinders St Townsville QLD 4810",
    "addr:housenumber":"407",
    "addr:postcode":"4810",
    "addr:street":"Flinders St",
    "iso:country":"AU",
    "sg:address":"Cat & Fiddle Centre 407 Flinders St",
    "sg:city":"Townsville",
    "sg:classifiers":[
        {
            "category":"Fast Food",
            "type":"Food & Drink"
        }
    ],
    "sg:phone":"+61 7 4772 2296",
    "sg:postcode":"4810",
    "sg:province":"QLD",
    "sg:tags":[
        "away",
        "take"
    ],
    "wof:name":"Townsville Tucker Box Takeaway",
    "wof:placetype":"venue"
},
  "geometry": {"coordinates":[146.80955499999999,-19.266781],"type":"Point"}
}