{
  "type": "Feature",
  "properties": {
    "addr:full":"7 Leeds St Rhodes NSW 2138",
    "addr:housenumber":"7",
    "addr:postcode":"2138",
    "addr:street":"Leeds St",
    "iso:country":"AU",
    "sg:address":"7 Leeds St",
    "sg:city":"Rhodes",
    "sg:classifiers":[
        {
            "category":"Social Services",
            "subcategory":"Retirement Home",
            "type":"Services"
        }
    ],
    "sg:phone":"+61 2 9736 8266",
    "sg:postcode":"2138",
    "sg:province":"NSW",
    "sg:tags":[
        "environmental",
        "consultant",
        "pollution"
    ],
    "wof:name":"NCS International",
    "wof:placetype":"venue"
},
  "geometry": {"coordinates":[151.09127807600001,-33.8243484497],"type":"Point"}
}