{
  "type": "Feature",
  "properties": {
    "addr:full":"8 Beafield Rd Para Hills West SA 5096",
    "addr:housenumber":"8",
    "addr:postcode":"5096",
    "addr:street":"Beafield Rd Para Hills West",
    "iso:country":"AU",
    "sg:address":"8 Beafield Rd",
    "sg:city":"Para Hills West",
    "sg:classifiers":[
        {
            "category":"Home & Garden",
            "subcategory":"Building Materials",
            "type":"Retail Goods"
        }
    ],
    "sg:phone":"+61 8 8281 6903",
    "sg:postcode":"5096",
    "sg:province":"SA",
    "sg:tags":[
        "merchant",
        "glass",
        "glazier"
    ],
    "wof:name":"North-East Glass & Glazing",
    "wof:placetype":"venue"
},
  "geometry": {"coordinates":[138.643188477,-34.7966194153],"type":"Point"}
}