{
  "type": "Feature",
  "properties": {
    "addr:full":"Bakers Rd Oakleigh South VIC 3167",
    "addr:postcode":"3167",
    "addr:street":"Bakers Rd",
    "iso:country":"AU",
    "sg:address":"Bakers Rd",
    "sg:city":"Oakleigh South",
    "sg:classifiers":[
        {
            "category":"Education",
            "subcategory":"School",
            "type":"Public Place"
        }
    ],
    "sg:phone":"+61 3 9579 2322",
    "sg:postcode":"3167",
    "sg:province":"VIC",
    "sg:tags":[
        "state",
        "except",
        "nsw"
    ],
    "wof:name":"South Oakleigh Secondary College",
    "wof:placetype":"venue"
},
  "geometry": {"coordinates":[145.08921814000001,-37.9243774414],"type":"Point"}
}