{
  "type": "Feature",
  "properties": {
    "addr:full":"3 / 33 Lawrence Drv Nerang QLD 4211",
    "addr:housenumber":"/ 33",
    "addr:postcode":"4211",
    "addr:street":"Lawrence Drv",
    "iso:country":"AU",
    "sg:address":"3 / 33 Lawrence Drv",
    "sg:city":"Nerang",
    "sg:classifiers":[
        {
            "category":"Home & Garden",
            "subcategory":"Garden Supply",
            "type":"Retail Goods"
        }
    ],
    "sg:phone":"+61 7 5578 2907",
    "sg:postcode":"4211",
    "sg:province":"QLD",
    "sg:tags":[
        "nursery"
    ],
    "wof:name":"Botany Horticultural",
    "wof:placetype":"venue"
},
  "geometry": {"coordinates":[153.346893311,-27.9970436096],"type":"Point"}
}