{
  "type": "Feature",
  "properties": {
    "addr:full":"112 Mileham St South Windsor NSW 2756",
    "addr:housenumber":"112",
    "addr:postcode":"2756",
    "addr:street":"Mileham St",
    "iso:country":"AU",
    "sg:address":"112 Mileham St",
    "sg:city":"South Windsor",
    "sg:classifiers":[
        {
            "category":"Professional",
            "type":"Services"
        }
    ],
    "sg:phone":"+61 2 4577 3700",
    "sg:postcode":"2756",
    "sg:province":"NSW",
    "sg:tags":[
        "transport"
    ],
    "wof:name":"S & M Bennett Transport Pty Ltd",
    "wof:placetype":"venue"
},
  "geometry": {"coordinates":[150.809204102,-33.6193161011],"type":"Point"}
}