{
  "type": "Feature",
  "properties": {
    "addr:full":"Unit 2, 67 Coronation Ave Nambour QLD 4560",
    "addr:housenumber":"67",
    "addr:postcode":"4560",
    "addr:street":"Coronation Ave",
    "iso:country":"AU",
    "sg:address":"Unit 2, 67 Coronation Ave",
    "sg:city":"Nambour",
    "sg:classifiers":[
        {
            "category":"Communications",
            "type":"Services"
        }
    ],
    "sg:phone":"+61 7 5441 2078",
    "sg:postcode":"4560",
    "sg:province":"QLD",
    "sg:tags":[
        "equipment",
        "radio"
    ],
    "wof:name":"Ralph Hill Communications",
    "wof:placetype":"venue"
},
  "geometry": {"coordinates":[152.96568298299999,-26.61992836],"type":"Point"}
}