{
  "type": "Feature",
  "properties": {
    "iso:country":"AU",
    "sg:address":"310 Liverpool St",
    "sg:city":"Hobart",
    "sg:classifiers":[
        {
            "category":"Building & Trades",
            "subcategory":"Construction",
            "type":"Services"
        }
    ],
    "sg:phone":"+61 408 291 301",
    "sg:postcode":"7000",
    "sg:province":"TAS",
    "sg:tags":[
        "contractor"
    ],
    "wof:name":"Freeman Building",
    "wof:placetype":"venue"
},
  "geometry": {"coordinates":[147.321075439,-42.8871231079],"type":"Point"}
}