{
  "type": "Feature",
  "properties": {
    "iso:country":"AU",
    "sg:address":"5 Hope St",
    "sg:city":"Brunswick",
    "sg:classifiers":[
        {
            "category":"Retail",
            "subcategory":"Auto Repair",
            "type":"Services"
        }
    ],
    "sg:phone":"+61 3 9380 1749",
    "sg:postcode":"3056",
    "sg:province":"VIC",
    "sg:tags":[
        "transmission",
        "automotive",
        "car"
    ],
    "wof:name":"Brunswick Automatics",
    "wof:placetype":"venue"
},
  "geometry": {"coordinates":[144.961669922,-37.7642745972],"type":"Point"}
}