{
  "type": "Feature",
  "properties": {
    "addr:full":"125 Abercrombie St Chippendale NSW 2008",
    "addr:housenumber":"125",
    "addr:postcode":"2008",
    "addr:street":"Abercrombie St",
    "iso:country":"AU",
    "sg:address":"125 Abercrombie St",
    "sg:city":"Chippendale",
    "sg:classifiers":[
        {
            "category":"Building & Trades",
            "subcategory":"Pest Control",
            "type":"Services"
        }
    ],
    "sg:phone":"+61 433 150 858",
    "sg:postcode":"2008",
    "sg:province":"NSW",
    "wof:name":"C & C Pest Control",
    "wof:placetype":"venue"
},
  "geometry": {"coordinates":[151.19866943400001,-33.8883247375],"type":"Point"}
}