{
  "type": "Feature",
  "properties": {
    "addr:full":"Shops 12 & 14, Australind Shopping Centre, Old Coa Australind WA 6233",
    "addr:housenumber":"12 & 14",
    "addr:postcode":"6233",
    "addr:street":"Australind Shopping;Old",
    "iso:country":"AU",
    "sg:address":"Shops 12 & 14, Australind Shopping Centre, Old Coa",
    "sg:city":"Australind",
    "sg:classifiers":[
        {
            "category":"Personal",
            "subcategory":"Piercing",
            "type":"Services"
        }
    ],
    "sg:phone":"+61 8 9797 1303",
    "sg:postcode":"6233",
    "sg:province":"WA",
    "sg:tags":[
        "body",
        "ear"
    ],
    "wof:name":"Chemmart",
    "wof:placetype":"venue"
},
  "geometry": {"coordinates":[115.714844,-33.275146],"type":"Point"}
}