{
  "type": "Feature",
  "properties": {
    "addr:full":"8 Clarendon Drv Melton South VIC 3338",
    "addr:housenumber":"8",
    "addr:postcode":"3338",
    "addr:street":"Clarendon Drv",
    "iso:country":"AU",
    "sg:address":"8 Clarendon Drv",
    "sg:city":"Melton South",
    "sg:classifiers":[
        {
            "category":"Building & Trades",
            "subcategory":"Construction",
            "type":"Services"
        }
    ],
    "sg:phone":"+61 3 8746 2627",
    "sg:postcode":"3338",
    "sg:province":"VIC",
    "sg:tags":[
        "fencing",
        "contractor"
    ],
    "wof:name":"Bills Fencing",
    "wof:placetype":"venue"
},
  "geometry": {"coordinates":[144.561554,-37.711277],"type":"Point"}
}