{
  "type": "Feature",
  "properties": {
    "addr:full":"69 Silsoe St Mayfield NSW 2304",
    "addr:housenumber":"69",
    "addr:postcode":"2304",
    "addr:street":"Silsoe St",
    "iso:country":"AU",
    "sg:address":"69 Silsoe St",
    "sg:city":"Mayfield",
    "sg:classifiers":[
        {
            "category":"Communications",
            "type":"Services"
        }
    ],
    "sg:phone":"+61 425 258 700",
    "sg:postcode":"2304",
    "sg:province":"NSW",
    "sg:tags":[
        "antenna"
    ],
    "wof:name":"Geoff Akhurst",
    "wof:placetype":"venue"
},
  "geometry": {"coordinates":[151.74298095699999,-32.9050254822],"type":"Point"}
}