{
  "type": "Feature",
  "properties": {
    "addr:full":"44 Fitzpatrick St Toowoomba QLD 4350",
    "addr:housenumber":"44",
    "addr:postcode":"4350",
    "addr:street":"Fitzpatrick St",
    "iso:country":"AU",
    "sg:address":"44 Fitzpatrick St",
    "sg:city":"Toowoomba",
    "sg:classifiers":[
        {
            "category":"Train Station",
            "subcategory":"Light Rail",
            "type":"Transportation"
        }
    ],
    "sg:phone":"+61 7 4634 1330",
    "sg:postcode":"4350",
    "sg:province":"QLD",
    "sg:tags":[
        "equipment",
        "energy",
        "solar"
    ],
    "wof:name":"O R & J C Ost",
    "wof:placetype":"venue"
},
  "geometry": {"coordinates":[151.92558299999999,-27.540754],"type":"Point"}
}