{
  "type": "Feature",
  "properties": {
    "iso:country":"AU",
    "sg:address":"305 Taylor St",
    "sg:city":"Toowoomba",
    "sg:classifiers":[
        {
            "category":"Sports & Exercise",
            "subcategory":"Sports Center",
            "type":"Entertainment"
        }
    ],
    "sg:phone":"+61 7 4634 6842",
    "sg:postcode":"4350",
    "sg:province":"QLD",
    "sg:tags":[
        "ground"
    ],
    "wof:name":"Action Arenas",
    "wof:placetype":"venue"
},
  "geometry": {"coordinates":[151.914627,-27.551617],"type":"Point"}
}