{
  "type": "Feature",
  "properties": {
    "addr:full":"36- 44 Parkhill Drv Berwick VIC 3806",
    "addr:housenumber":"44",
    "addr:postcode":"3806",
    "addr:street":"Parkhill Drv",
    "iso:country":"AU",
    "sg:address":"36- 44 Parkhill Drv",
    "sg:city":"Berwick",
    "sg:classifiers":[
        {
            "category":"Social Services",
            "subcategory":"Child Care",
            "type":"Services"
        }
    ],
    "sg:phone":"+61 3 8786 5870",
    "sg:postcode":"3806",
    "sg:province":"VIC",
    "wof:name":"Sunkids",
    "wof:placetype":"venue"
},
  "geometry": {"coordinates":[145.324386597,-38.0254898071],"type":"Point"}
}