{
  "type": "Feature",
  "properties": {
    "addr:full":"35 East St Guildford WA 6055",
    "addr:housenumber":"35",
    "addr:postcode":"6055",
    "addr:street":"East St",
    "iso:country":"AU",
    "sg:address":"35 East St",
    "sg:city":"Guildford",
    "sg:classifiers":[
        {
            "category":"Social Services",
            "subcategory":"Adult Care",
            "type":"Services"
        }
    ],
    "sg:phone":"+61 427 180 575",
    "sg:postcode":"6055",
    "sg:province":"WA",
    "sg:tags":[
        "towing"
    ],
    "wof:name":"Double One Towing & Recovery",
    "wof:placetype":"venue"
},
  "geometry": {"coordinates":[115.981621,-31.899113],"type":"Point"}
}