{
  "type": "Feature",
  "properties": {
    "iso:country":"AU",
    "sg:address":"312 St. Vincent St",
    "sg:city":"Port Adelaide",
    "sg:classifiers":[
        {
            "category":"Home & Garden",
            "subcategory":"Carpets & Floor Coverings",
            "type":"Retail Goods"
        }
    ],
    "sg:phone":"+61 8 8240 4900",
    "sg:postcode":"5015",
    "sg:province":"SA",
    "sg:tags":[
        "tile",
        "wall"
    ],
    "wof:name":"Harbour Ceramics",
    "wof:placetype":"venue"
},
  "geometry": {"coordinates":[138.50997924800001,-34.8435974121],"type":"Point"}
}