{
  "type": "Feature",
  "properties": {
    "addr:full":"6 Hillary St West Pymble NSW 2073",
    "addr:housenumber":"6",
    "addr:postcode":"2073",
    "addr:street":"Hillary St",
    "iso:country":"AU",
    "sg:address":"6 Hillary St",
    "sg:city":"West Pymble",
    "sg:classifiers":[
        {
            "category":"Shopping",
            "subcategory":"Musical Instruments",
            "type":"Retail Goods"
        }
    ],
    "sg:phone":"+61 2 9144 4190",
    "sg:postcode":"2073",
    "sg:province":"NSW",
    "sg:tags":[
        "musician",
        "agent"
    ],
    "wof:name":"Front of House Productions",
    "wof:placetype":"venue"
},
  "geometry": {"coordinates":[151.12290954599999,-33.762046814],"type":"Point"}
}