{
  "type": "Feature",
  "properties": {
    "iso:country":"AU",
    "sg:address":"140 Gilles St",
    "sg:city":"Adelaide",
    "sg:classifiers":[
        {
            "category":"Shopping",
            "subcategory":"Bicycles & Sporting Goods",
            "type":"Retail Goods"
        }
    ],
    "sg:phone":"+61 8 8224 0344",
    "sg:postcode":"5000",
    "sg:province":"SA",
    "sg:tags":[
        "chemical",
        "equipment",
        "pool",
        "swimming"
    ],
    "wof:name":"Aqua Tune",
    "wof:placetype":"venue"
},
  "geometry": {"coordinates":[138.60548400900001,-34.9339065552],"type":"Point"}
}