{
  "type": "Feature",
  "properties": {
    "addr:full":"134 Captain Cook Drv Barrack Heights NSW 2528",
    "addr:housenumber":"134",
    "addr:postcode":"2528",
    "addr:street":"Captain Cook Drv",
    "iso:country":"AU",
    "sg:address":"134 Captain Cook Drv",
    "sg:city":"Barrack Heights",
    "sg:classifiers":[
        {
            "category":"Professional",
            "subcategory":"Art Services",
            "type":"Services"
        }
    ],
    "sg:phone":"+61 407 965 984",
    "sg:postcode":"2528",
    "sg:province":"NSW",
    "sg:tags":[
        "interior",
        "decorator"
    ],
    "wof:name":"Art2interiors",
    "wof:placetype":"venue"
},
  "geometry": {"coordinates":[150.84762573200001,-34.5589179993],"type":"Point"}
}