{
  "type": "Feature",
  "properties": {
    "iso:country":"AU",
    "sg:address":"39 Wren Rd",
    "sg:city":"Moorabbin",
    "sg:classifiers":[
        {
            "category":"Manufacturing",
            "subcategory":"Motor Vehicles & Parts",
            "type":"Manufacturing & Wholesale Goods"
        }
    ],
    "sg:phone":"+61 3 9555 5044",
    "sg:postcode":"3189",
    "sg:province":"VIC",
    "sg:tags":[
        "replacement"
    ],
    "wof:name":"Pedders",
    "wof:placetype":"venue"
},
  "geometry": {"coordinates":[145.079315186,-37.93983078],"type":"Point"}
}