{
  "type": "Feature",
  "properties": {
    "addr:full":"1/ 12 Merchant Ave Thomastown VIC 3074",
    "addr:housenumber":"/ 12",
    "addr:postcode":"3074",
    "addr:street":"Merchant Ave",
    "iso:country":"AU",
    "sg:address":"1/ 12 Merchant Ave",
    "sg:city":"Thomastown",
    "sg:classifiers":[
        {
            "category":"Utilities",
            "subcategory":"Refuse",
            "type":"Services"
        }
    ],
    "sg:phone":"+61 425 734 957",
    "sg:postcode":"3074",
    "sg:province":"VIC",
    "sg:tags":[
        "remover",
        "rubbish"
    ],
    "wof:name":"Skip'n Around Bin Hire",
    "wof:placetype":"venue"
},
  "geometry": {"coordinates":[145.04095459000001,-37.6913261414],"type":"Point"}
}