{
  "type": "Feature",
  "properties": {
    "addr:full":"59 Desmond St Merrylands West NSW 2160",
    "addr:housenumber":"59",
    "addr:postcode":"2160",
    "addr:street":"Desmond St",
    "iso:country":"AU",
    "sg:address":"59 Desmond St",
    "sg:city":"Merrylands West",
    "sg:classifiers":[
        {
            "category":"Real Estate",
            "subcategory":"Architect",
            "type":"Services"
        }
    ],
    "sg:phone":"+61 2 9681 4125",
    "sg:postcode":"2160",
    "sg:province":"NSW",
    "wof:name":"Baini Sign",
    "wof:placetype":"venue"
},
  "geometry": {"coordinates":[150.97503662099999,-33.8378715515],"type":"Point"}
}