{
  "type": "Feature",
  "properties": {
    "addr:full":"40 Johnson St Bruce Rock WA 6418",
    "addr:housenumber":"40",
    "addr:postcode":"6418",
    "addr:street":"Johnson St",
    "iso:country":"AU",
    "sg:address":"40 Johnson St",
    "sg:city":"Bruce Rock",
    "sg:classifiers":[
        {
            "category":"Banks & Credit Unions",
            "subcategory":"Bank",
            "type":"Services"
        }
    ],
    "sg:phone":"+61 13 20 32",
    "sg:postcode":"6418",
    "sg:province":"WA",
    "wof:name":"Westpac",
    "wof:placetype":"venue"
},
  "geometry": {"coordinates":[118.148696899,-31.8779125214],"type":"Point"}
}