{
  "type": "Feature",
  "properties": {
    "addr:full":"PO Box 2219 Hawthorn VIC 3122",
    "addr:postcode":"3122",
    "iso:country":"AU",
    "sg:address":"PO Box 2219",
    "sg:city":"Hawthorn",
    "sg:classifiers":[
        {
            "category":"Health Services",
            "subcategory":"Doctor",
            "type":"Services"
        }
    ],
    "sg:phone":"+61 3 9819 4597",
    "sg:postcode":"3122",
    "sg:province":"VIC",
    "sg:tags":[
        "nurse",
        "nursing"
    ],
    "wof:name":"Syster Pty Ltd",
    "wof:placetype":"venue"
},
  "geometry": {"coordinates":[145.03062439000001,-37.8286209106],"type":"Point"}
}