{
  "type": "Feature",
  "properties": {
    "addr:full":"2/ 7a Argyle St Arncliffe NSW 2205",
    "addr:housenumber":"/ 7a",
    "addr:postcode":"2205",
    "addr:street":"Argyle St",
    "iso:country":"AU",
    "sg:address":"2/ 7a Argyle St",
    "sg:city":"Arncliffe",
    "sg:classifiers":[
        {
            "category":"Wholesale",
            "subcategory":"Painting Supplies",
            "type":"Manufacturing & Wholesale Goods"
        }
    ],
    "sg:phone":"+61 2 9556 1085",
    "sg:postcode":"2205",
    "sg:province":"NSW",
    "sg:tags":[
        "painter"
    ],
    "wof:name":"Spede Autopaints",
    "wof:placetype":"venue"
},
  "geometry": {"coordinates":[151.15130600000001,-33.934048],"type":"Point"}
}