{
  "type": "Feature",
  "properties": {
    "addr:full":"25 Temple Drv Thomastown VIC 3074",
    "addr:housenumber":"25",
    "addr:postcode":"3074",
    "addr:street":"Temple Drv",
    "iso:country":"AU",
    "sg:address":"25 Temple Drv",
    "sg:city":"Thomastown",
    "sg:classifiers":[
        {
            "category":"Shopping",
            "subcategory":"Clothing, Apparel, & Fashions",
            "type":"Retail Goods"
        }
    ],
    "sg:phone":"+61 3 9464 2204",
    "sg:postcode":"3074",
    "sg:province":"VIC",
    "sg:tags":[
        "wholesaler",
        "children's",
        "mfrs",
        "wear"
    ],
    "wof:name":"Baby Trend",
    "wof:placetype":"venue"
},
  "geometry": {"coordinates":[145.01895141599999,-37.690826416],"type":"Point"}
}