{
  "type": "Feature",
  "properties": {
    "iso:country":"AU",
    "sg:address":"1 Wynyard St",
    "sg:city":"South Melbourne",
    "sg:classifiers":[
        {
            "category":"Professional",
            "subcategory":"Art Services",
            "type":"Services"
        }
    ],
    "sg:phone":"+61 3 9696 4690",
    "sg:postcode":"3205",
    "sg:province":"VIC",
    "sg:tags":[
        "graphic",
        "designer"
    ],
    "wof:name":"Brothers Geoff",
    "wof:placetype":"venue"
},
  "geometry": {"coordinates":[144.961426,-37.834526],"type":"Point"}
}