{
  "type": "Feature",
  "properties": {
    "addr:full":"PO Box 571 Mudgeeraba QLD 4213",
    "addr:postcode":"4213",
    "iso:country":"AU",
    "sg:address":"PO Box 571",
    "sg:city":"Mudgeeraba",
    "sg:classifiers":[
        {
            "category":"Shopping",
            "subcategory":"Stationery & Office Supplies",
            "type":"Retail Goods"
        }
    ],
    "sg:phone":"+61 7 5525 3955",
    "sg:postcode":"4213",
    "sg:province":"QLD",
    "sg:tags":[
        "equipment",
        "display",
        "exhibition"
    ],
    "wof:name":"Real Estate Displays",
    "wof:placetype":"venue"
},
  "geometry": {"coordinates":[153.364578247,-28.0756206512],"type":"Point"}
}