{
  "type": "Feature",
  "properties": {
    "iso:country":"AU",
    "sg:address":"Shop 4, 107- 111 Portrush Rd",
    "sg:city":"Evandale",
    "sg:classifiers":[
        {
            "category":"Professional",
            "subcategory":"Detective & Security Services",
            "type":"Services"
        }
    ],
    "sg:phone":"+61 1300 069 779",
    "sg:postcode":"5069",
    "sg:province":"SA",
    "sg:tags":[
        "consultant",
        "system"
    ],
    "wof:name":"OzSpy Adelaide",
    "wof:placetype":"venue"
},
  "geometry": {"coordinates":[138.639602661,-34.9053955078],"type":"Point"}
}