{
  "type": "Feature",
  "properties": {
    "iso:country":"AU",
    "sg:address":"39 Maitland Rd",
    "sg:city":"Branxton",
    "sg:classifiers":[
        {
            "category":"Food & Beverages",
            "subcategory":"Meat & Fish",
            "type":"Retail Goods"
        }
    ],
    "sg:phone":"+61 2 4938 1090",
    "sg:postcode":"2335",
    "sg:province":"NSW",
    "sg:tags":[
        "seafood"
    ],
    "wof:name":"Branxton Fish & Chip Shop",
    "wof:placetype":"venue"
},
  "geometry": {"coordinates":[151.35348510700001,-32.6558151245],"type":"Point"}
}