{
  "type": "Feature",
  "properties": {
    "iso:country":"AU",
    "sg:address":"Cnr Norris & Telegraph Rds",
    "sg:city":"Bracken Ridge",
    "sg:classifiers":[
        {
            "category":"Health Services",
            "subcategory":"Health Practitioner",
            "type":"Services"
        }
    ],
    "sg:phone":"+61 7 3261 5125",
    "sg:postcode":"4017",
    "sg:province":"QLD",
    "sg:tags":[
        "physiotherapist"
    ],
    "wof:name":"Bracken Ridge Physio Solutions",
    "wof:placetype":"venue"
},
  "geometry": {"coordinates":[153.025314331,-27.3308849335],"type":"Point"}
}