{
  "type": "Feature",
  "properties": {
    "addr:full":"Philp Rd Ravensbourne QLD 4352",
    "addr:postcode":"4352",
    "addr:street":"Philp Rd",
    "iso:country":"AU",
    "sg:address":"Philp Rd",
    "sg:city":"Ravensbourne",
    "sg:classifiers":[
        {
            "category":"Home & Garden",
            "subcategory":"Building Materials",
            "type":"Retail Goods"
        }
    ],
    "sg:phone":"+61 7 4697 8188",
    "sg:postcode":"4352",
    "sg:province":"QLD",
    "sg:tags":[
        "pre-mixed",
        "concrete"
    ],
    "wof:name":"Pioneer Construction Materials Pty Ltd",
    "wof:placetype":"venue"
},
  "geometry": {"coordinates":[152.186172,-27.330524],"type":"Point"}
}