{
  "type": "Feature",
  "properties": {
    "iso:country":"AU",
    "sg:address":"1/68 Paring Ave",
    "sg:city":"Somerton Park",
    "sg:classifiers":[
        {
            "category":"Bars & Pubs",
            "subcategory":"Biergarten",
            "type":"Food & Drink"
        }
    ],
    "sg:phone":"+61 8 8376 7911",
    "sg:postcode":"5044",
    "sg:province":"SA",
    "sg:tags":[
        "eucalyptus",
        "oil",
        "tree",
        "essential",
        "tea"
    ],
    "wof:name":"International Flavours & Fragrances (Australia) Ltd",
    "wof:placetype":"venue"
},
  "geometry": {"coordinates":[138.52922100000001,-34.998627],"type":"Point"}
}