{
  "type": "Feature",
  "properties": {
    "addr:full":"529 Willoughby Rd Willoughby NSW 2068",
    "addr:housenumber":"529",
    "addr:postcode":"2068",
    "addr:street":"Willoughby Rd",
    "iso:country":"AU",
    "sg:address":"529 Willoughby Rd",
    "sg:city":"Willoughby",
    "sg:classifiers":[
        {
            "category":"Social Services",
            "subcategory":"Adult Care",
            "type":"Services"
        }
    ],
    "sg:phone":"+61 2 9403 5521",
    "sg:postcode":"2068",
    "sg:province":"NSW",
    "sg:tags":[
        "towing"
    ],
    "wof:name":"All Northside Towing Services",
    "wof:placetype":"venue"
},
  "geometry": {"coordinates":[151.19947814899999,-33.8068885803],"type":"Point"}
}