{
  "type": "Feature",
  "properties": {
    "addr:full":"92 Main St Mittagong NSW 2575",
    "addr:housenumber":"92",
    "addr:postcode":"2575",
    "addr:street":"Main St",
    "iso:country":"AU",
    "sg:address":"92 Main St",
    "sg:city":"Mittagong",
    "sg:classifiers":[
        {
            "category":"Food & Beverages",
            "subcategory":"Fruits & Vegetables",
            "type":"Retail Goods"
        }
    ],
    "sg:phone":"+61 2 4871 1370",
    "sg:postcode":"2575",
    "sg:province":"NSW",
    "sg:tags":[
        "greengrocer",
        "fruiterer"
    ],
    "wof:name":"Highlands Fresh Pty Ltd",
    "wof:placetype":"venue"
},
  "geometry": {"coordinates":[150.44761657699999,-34.4511184692],"type":"Point"}
}