{
  "type": "Feature",
  "properties": {
    "addr:full":"Unit A/ 10 Bilinga Rd Kincumber NSW 2251",
    "addr:housenumber":"unit;/ 10",
    "addr:postcode":"2251",
    "addr:street":"Bilinga Rd",
    "iso:country":"AU",
    "sg:address":"Unit A/ 10 Bilinga Rd",
    "sg:city":"Kincumber",
    "sg:classifiers":[
        {
            "category":"Education",
            "subcategory":"Dance Studio",
            "type":"Public Place"
        }
    ],
    "sg:phone":"+61 2 4368 1814",
    "sg:postcode":"2251",
    "sg:province":"NSW",
    "sg:tags":[
        "venue",
        "tuition"
    ],
    "wof:name":"dancEnergy# Studio",
    "wof:placetype":"venue"
},
  "geometry": {"coordinates":[151.390136719,-33.473400116],"type":"Point"}
}