{
  "type": "Feature",
  "properties": {
    "addr:full":"32 Elizabeth St Parramatta NSW 2150",
    "addr:housenumber":"32",
    "addr:postcode":"2150",
    "addr:street":"Elizabeth St",
    "iso:country":"AU",
    "sg:address":"32 Elizabeth St",
    "sg:city":"Parramatta",
    "sg:classifiers":[
        {
            "category":"Health Services",
            "subcategory":"Chiropractor",
            "type":"Services"
        }
    ],
    "sg:phone":"+61 2 9683 1110",
    "sg:postcode":"2150",
    "sg:province":"NSW",
    "wof:name":"Campagna Lorenzo",
    "wof:placetype":"venue"
},
  "geometry": {"coordinates":[151.00723266599999,-33.8379631042],"type":"Point"}
}