{
  "type": "Feature",
  "properties": {
    "addr:full":"Unit 2 7 Pritchard St O&#039;Connor WA 6163",
    "addr:housenumber":"7",
    "addr:postcode":"6163",
    "addr:street":"Pritchard St",
    "iso:country":"AU",
    "sg:address":"Unit 2 7 Pritchard St",
    "sg:city":"O&#039;Connor",
    "sg:classifiers":[
        {
            "category":"Shopping",
            "subcategory":"Shoes",
            "type":"Retail Goods"
        }
    ],
    "sg:phone":"+61 8 9314 6182",
    "sg:postcode":"6163",
    "sg:province":"WA",
    "sg:tags":[
        "footwear"
    ],
    "sg:website":"http://www.superstraps.com.au",
    "wof:name":"Superstraps",
    "wof:placetype":"venue"
},
  "geometry": {"coordinates":[115.792709,-32.062767],"type":"Point"}
}