{
  "type": "Feature",
  "properties": {
    "iso:country":"AU",
    "sg:address":"28- 30 Eastment St",
    "sg:city":"Northcote",
    "sg:classifiers":[
        {
            "category":"Shopping",
            "subcategory":"Clothing, Apparel, & Fashions",
            "type":"Retail Goods"
        }
    ],
    "sg:phone":"+61 1800 809 059",
    "sg:postcode":"3070",
    "sg:province":"VIC",
    "sg:tags":[
        "uniform"
    ],
    "wof:name":"Dura-Wear Uniforms",
    "wof:placetype":"venue"
},
  "geometry": {"coordinates":[144.99736,-37.772877],"type":"Point"}
}