{
  "type": "Feature",
  "properties": {
    "iso:country":"AU",
    "sg:address":"Keams Rd",
    "sg:city":"Moree",
    "sg:classifiers":[
        {
            "category":"Building & Trades",
            "subcategory":"Construction",
            "type":"Services"
        }
    ],
    "sg:phone":"+61 2 6752 9188",
    "sg:postcode":"2400",
    "sg:province":"NSW",
    "sg:tags":[
        "earth",
        "excavating",
        "moving",
        "contractor"
    ],
    "wof:name":"Bagshaw D J & S E",
    "wof:placetype":"venue"
},
  "geometry": {"coordinates":[149.841598511,-29.4661998749],"type":"Point"}
}