{
  "type": "Feature",
  "properties": {
    "addr:full":"Raynors Rd Midway Point TAS 7171",
    "addr:postcode":"7171",
    "addr:street":"Raynors Rd",
    "iso:country":"AU",
    "sg:address":"Raynors Rd",
    "sg:city":"Midway Point",
    "sg:classifiers":[
        {
            "category":"Organizations",
            "subcategory":"Community Association",
            "type":"Services"
        }
    ],
    "sg:phone":"+61 3 6265 1584",
    "sg:postcode":"7171",
    "sg:province":"TAS",
    "sg:tags":[
        "club",
        "senior",
        "citizen"
    ],
    "wof:name":"Midway Point Senior Citizens Club",
    "wof:placetype":"venue"
},
  "geometry": {"coordinates":[147.532592773,-42.8026237488],"type":"Point"}
}