{
  "type": "Feature",
  "properties": {
    "addr:full":"964 Whitehorse Rd Box Hill VIC 3128",
    "addr:housenumber":"964",
    "addr:postcode":"3128",
    "addr:street":"Whitehorse Rd",
    "iso:country":"AU",
    "sg:address":"964 Whitehorse Rd",
    "sg:city":"Box Hill",
    "sg:classifiers":[
        {
            "category":"Professional",
            "subcategory":"Credit Reporting & Collection",
            "type":"Services"
        }
    ],
    "sg:phone":"+61 1800 700 071",
    "sg:postcode":"3128",
    "sg:province":"VIC",
    "sg:tags":[
        "management"
    ],
    "wof:name":"TUOMEC",
    "wof:placetype":"venue"
},
  "geometry": {"coordinates":[145.12408447300001,-37.8184318542],"type":"Point"}
}