{
  "type": "Feature",
  "properties": {
    "addr:full":"111 Bourke St Carrington NSW 2294",
    "addr:housenumber":"111",
    "addr:postcode":"2294",
    "addr:street":"Bourke St",
    "iso:country":"AU",
    "sg:address":"111 Bourke St",
    "sg:city":"Carrington",
    "sg:classifiers":[
        {
            "category":"Wholesale",
            "subcategory":"Metals & Minerals",
            "type":"Manufacturing & Wholesale Goods"
        }
    ],
    "sg:phone":"+61 2 4962 2300",
    "sg:postcode":"2294",
    "sg:province":"NSW",
    "sg:tags":[
        "steel",
        "merchant"
    ],
    "wof:name":"Blackwood Group Metals Division",
    "wof:placetype":"venue"
},
  "geometry": {"coordinates":[151.76837158199999,-32.9141273499],"type":"Point"}
}