{
  "type": "Feature",
  "properties": {
    "addr:full":"36 Bowman Ave Camden NSW 2570",
    "addr:housenumber":"36",
    "addr:postcode":"2570",
    "addr:street":"Bowman Ave",
    "iso:country":"AU",
    "sg:address":"36 Bowman Ave",
    "sg:city":"Camden",
    "sg:classifiers":[
        {
            "category":"Home & Garden",
            "subcategory":"Carpets & Floor Coverings",
            "type":"Retail Goods"
        }
    ],
    "sg:phone":"+61 2 4655 8149",
    "sg:postcode":"2570",
    "sg:province":"NSW",
    "sg:tags":[
        "tile",
        "wall",
        "layer"
    ],
    "wof:name":"K.B. Tiles",
    "wof:placetype":"venue"
},
  "geometry": {"coordinates":[150.696655273,-34.0857009888],"type":"Point"}
}