{
  "type": "Feature",
  "properties": {
    "iso:country":"AU",
    "sg:address":"Stockwell Rd",
    "sg:city":"Angaston",
    "sg:classifiers":[
        {
            "category":"Freight",
            "type":"Transportation"
        }
    ],
    "sg:phone":"+61 8 8563 8217",
    "sg:postcode":"5353",
    "sg:province":"SA",
    "sg:tags":[
        "light",
        "carrier"
    ],
    "wof:name":"Nexday Pty Ltd",
    "wof:placetype":"venue"
},
  "geometry": {"coordinates":[139.02738952600001,-34.4931678772],"type":"Point"}
}