{
  "type": "Feature",
  "properties": {
    "addr:full":"Shed 2 17 Webb Pl Armidale NSW 2350",
    "addr:housenumber":"17",
    "addr:postcode":"2350",
    "addr:street":"Webb Pl",
    "iso:country":"AU",
    "sg:address":"Shed 2 17 Webb Pl",
    "sg:city":"Armidale",
    "sg:classifiers":[
        {
            "category":"Professional",
            "type":"Services"
        }
    ],
    "sg:phone":"+61 427 458 939",
    "sg:postcode":"2350",
    "sg:province":"NSW",
    "sg:tags":[
        "buyer",
        "merchant",
        "wool"
    ],
    "wof:name":"High Country Wool Pty Ltd",
    "wof:placetype":"venue"
},
  "geometry": {"coordinates":[151.64202880900001,-30.5161781311],"type":"Point"}
}