{
  "type": "Feature",
  "properties": {
    "addr:full":"Unit 2 / 21 Stennett Rd Ingleburn NSW 2565",
    "addr:postcode":"2565",
    "addr:street":"21 Stennett Rd",
    "iso:country":"AU",
    "sg:address":"Unit 2 / 21 Stennett Rd",
    "sg:city":"Ingleburn",
    "sg:classifiers":[
        {
            "category":"Building & Trades",
            "subcategory":"Plumbing",
            "type":"Services"
        }
    ],
    "sg:phone":"+61 2 9605 8222",
    "sg:postcode":"2565",
    "sg:province":"NSW",
    "sg:tags":[
        "equipment",
        "valves"
    ],
    "wof:name":"T & S Valves & Fitting Supplies Pty Ltd",
    "wof:placetype":"venue"
},
  "geometry": {"coordinates":[150.85252380399999,-34.0036354065],"type":"Point"}
}