{
  "type": "Feature",
  "properties": {
    "iso:country":"AU",
    "sg:address":"4/ 7 Hinde St",
    "sg:city":"Ashmore",
    "sg:classifiers":[
        {
            "category":"Professional",
            "subcategory":"Art Services",
            "type":"Services"
        }
    ],
    "sg:phone":"+61 7 5576 6180",
    "sg:postcode":"4214",
    "sg:province":"QLD",
    "sg:tags":[
        "graphic",
        "designer"
    ],
    "wof:name":"Nu-Scan Pty Ltd",
    "wof:placetype":"venue"
},
  "geometry": {"coordinates":[153.38789367699999,-27.9783401489],"type":"Point"}
}