{
  "type": "Feature",
  "properties": {
    "iso:country":"AU",
    "sg:address":"22 Leda Drv",
    "sg:city":"Andrews",
    "sg:classifiers":[
        {
            "category":"Donuts",
            "subcategory":"None",
            "type":"Food & Drink"
        }
    ],
    "sg:phone":"+61 7 5576 1900",
    "sg:postcode":"4220",
    "sg:province":"QLD",
    "sg:tags":[
        "die",
        "engraver",
        "sinker"
    ],
    "wof:name":"Mastercut Technologies Pty Ltd",
    "wof:placetype":"venue"
},
  "geometry": {"coordinates":[153.43179321299999,-28.105014801],"type":"Point"}
}