{
  "type": "Feature",
  "properties": {
    "addr:full":"Suite 1102a 33 Bligh St Sydney NSW 2000",
    "addr:housenumber":"33",
    "addr:postcode":"2000",
    "addr:street":"Bligh St",
    "iso:country":"AU",
    "sg:address":"Suite 1102a 33 Bligh St",
    "sg:city":"Sydney",
    "sg:classifiers":[
        {
            "category":"Wholesale",
            "subcategory":"Meat",
            "type":"Manufacturing & Wholesale Goods"
        }
    ],
    "sg:phone":"+61 2 9232 4777",
    "sg:postcode":"2000",
    "sg:province":"NSW",
    "sg:tags":[
        "packing",
        "exporting"
    ],
    "wof:name":"RMT International Pty Ltd",
    "wof:placetype":"venue"
},
  "geometry": {"coordinates":[151.209915161,-33.8659210205],"type":"Point"}
}