{
  "type": "Feature",
  "properties": {
    "iso:country":"AU",
    "sg:address":"Unit 1/ 60 Greenway Drv",
    "sg:city":"Tweed Heads South",
    "sg:classifiers":[
        {
            "category":"Autos & Motor Vehicles",
            "subcategory":"Auto Supplies",
            "type":"Retail Goods"
        }
    ],
    "sg:phone":"+61 7 5523 2525",
    "sg:postcode":"2486",
    "sg:province":"QLD",
    "sg:tags":[
        "tyre"
    ],
    "wof:name":"Tweed Heads Tyre Centre Pty Ltd",
    "wof:placetype":"venue"
},
  "geometry": {"coordinates":[153.53436279300001,-28.212228775],"type":"Point"}
}