{
  "type": "Feature",
  "properties": {
    "addr:full":"93 Whitehorse Rd Balwyn VIC 3103",
    "addr:housenumber":"93",
    "addr:postcode":"3103",
    "addr:street":"Whitehorse Rd",
    "iso:country":"AU",
    "sg:address":"93 Whitehorse Rd",
    "sg:city":"Balwyn",
    "sg:classifiers":[
        {
            "category":"Travel",
            "subcategory":"Travel Agent",
            "type":"Entertainment"
        }
    ],
    "sg:phone":"+61 3 9816 9922",
    "sg:postcode":"3103",
    "sg:province":"VIC",
    "sg:tags":[
        "consultant"
    ],
    "wof:name":"Sue Barnett Travel Agents",
    "wof:placetype":"venue"
},
  "geometry": {"coordinates":[145.066131592,-37.8108634949],"type":"Point"}
}