{
  "type": "Feature",
  "properties": {
    "iso:country":"AU",
    "sg:address":"47 Tango Ave",
    "sg:city":"Dee Why",
    "sg:classifiers":[
        {
            "category":"Professional",
            "subcategory":"Employment Agencies",
            "type":"Services"
        }
    ],
    "sg:phone":"+61 2 9972 9814",
    "sg:postcode":"2099",
    "sg:province":"NSW",
    "sg:tags":[
        "entertainer",
        "agent"
    ],
    "wof:name":"Aah The Wedding Singer",
    "wof:placetype":"venue"
},
  "geometry": {"coordinates":[151.28546142600001,-33.7581672668],"type":"Point"}
}