{
  "type": "Feature",
  "properties": {
    "iso:country":"AU",
    "sg:address":"1 Alana Rd",
    "sg:city":"Esperance",
    "sg:classifiers":[
        {
            "category":"Building & Trades",
            "subcategory":"Landscaping Services",
            "type":"Services"
        }
    ],
    "sg:phone":"+61 8 9072 1306",
    "sg:postcode":"6450",
    "sg:province":"WA",
    "sg:tags":[
        "stump",
        "tree",
        "felling",
        "removal"
    ],
    "wof:name":"Esperance Tree Lopping",
    "wof:placetype":"venue"
},
  "geometry": {"coordinates":[121.854347229,-33.8608436584],"type":"Point"}
}