{
  "type": "Feature",
  "properties": {
    "iso:country":"AU",
    "sg:address":"55B Bourbong St",
    "sg:city":"Bundaberg",
    "sg:classifiers":[
        {
            "category":"Personal",
            "subcategory":"Beauty Salon",
            "type":"Services"
        }
    ],
    "sg:phone":"+61 7 4152 7366",
    "sg:postcode":"4670",
    "sg:province":"QLD",
    "sg:tags":[
        "hairdresser"
    ],
    "wof:name":"Stag Mens Hairstylists",
    "wof:placetype":"venue"
},
  "geometry": {"coordinates":[152.35018920900001,-24.8655185699],"type":"Point"}
}