{
  "type": "Feature",
  "properties": {
    "addr:full":"10 Leichardt St Sunbury VIC 3429",
    "addr:housenumber":"10",
    "addr:postcode":"3429",
    "addr:street":"Leichardt St",
    "iso:country":"AU",
    "sg:address":"10 Leichardt St",
    "sg:city":"Sunbury",
    "sg:classifiers":[
        {
            "category":"Building & Trades",
            "subcategory":"Construction",
            "type":"Services"
        }
    ],
    "sg:phone":"+61 409 553 143",
    "sg:postcode":"3429",
    "sg:province":"VIC",
    "sg:tags":[
        "home",
        "air conditioning"
    ],
    "wof:name":"4 Way Air Conditioning Refrigeration Electrical",
    "wof:placetype":"venue"
},
  "geometry": {"coordinates":[144.707199097,-37.5821762085],"type":"Point"}
}