{
  "type": "Feature",
  "properties": {
    "addr:full":"50- 54 Millers Rd Wingfield SA 5013",
    "addr:housenumber":"54",
    "addr:postcode":"5013",
    "addr:street":"Millers Rd",
    "iso:country":"AU",
    "sg:address":"50- 54 Millers Rd",
    "sg:city":"Wingfield",
    "sg:classifiers":[
        {
            "category":"Building & Trades",
            "subcategory":"Construction",
            "type":"Services"
        }
    ],
    "sg:phone":"+61 8 8347 2030",
    "sg:postcode":"5013",
    "sg:province":"SA",
    "sg:tags":[
        "bitumen",
        "paving",
        "asphalt"
    ],
    "wof:name":"Metropolitan Bitumen Pavers",
    "wof:placetype":"venue"
},
  "geometry": {"coordinates":[138.55917358400001,-34.8347511292],"type":"Point"}
}