{
  "type": "Feature",
  "properties": {
    "addr:full":"3 Watkins St Tully QLD 4854",
    "addr:housenumber":"3",
    "addr:postcode":"4854",
    "addr:street":"Watkins St",
    "iso:country":"AU",
    "sg:address":"3 Watkins St",
    "sg:city":"Tully",
    "sg:classifiers":[
        {
            "category":"Fast Food",
            "type":"Food & Drink"
        }
    ],
    "sg:phone":"+61 7 4068 3222",
    "sg:postcode":"4854",
    "sg:province":"QLD",
    "sg:tags":[
        "away",
        "take"
    ],
    "wof:name":"Moodys",
    "wof:placetype":"venue"
},
  "geometry": {"coordinates":[145.92304992699999,-17.9340286255],"type":"Point"}
}