{
  "type": "Feature",
  "properties": {
    "addr:full":"47 Regent St Kogarah NSW 2217",
    "addr:housenumber":"47",
    "addr:postcode":"2217",
    "addr:street":"Regent St",
    "iso:country":"AU",
    "sg:address":"47 Regent St",
    "sg:city":"Kogarah",
    "sg:classifiers":[
        {
            "category":"Health Services",
            "subcategory":"Doctor",
            "type":"Services"
        }
    ],
    "sg:phone":"+61 2 9553 0700",
    "sg:postcode":"2217",
    "sg:province":"NSW",
    "sg:tags":[
        "medical",
        "practitioner"
    ],
    "wof:name":"Cook Natasha",
    "wof:placetype":"venue"
},
  "geometry": {"coordinates":[151.13481100000001,-33.961918],"type":"Point"}
}