{
  "type": "Feature",
  "properties": {
    "iso:country":"AU",
    "sg:address":"47 Regent St",
    "sg:city":"Kogarah",
    "sg:classifiers":[
        {
            "category":"Health Services",
            "subcategory":"Doctor",
            "type":"Services"
        }
    ],
    "sg:phone":"+61 2 9553 0700",
    "sg:postcode":"2217",
    "sg:province":"NSW",
    "sg:tags":[
        "medical",
        "practitioner"
    ],
    "wof:name":"Cook Natasha",
    "wof:placetype":"venue"
},
  "geometry": {"coordinates":[151.134811,-33.961918],"type":"Point"}
}