{
  "type": "Feature",
  "properties": {
    "addr:full":"Bay Junction S/C Cnr Jetty & Brighton Road Glenelg SA 5045",
    "addr:postcode":"5045",
    "addr:street":"Cnr;Road",
    "iso:country":"AU",
    "sg:address":"Bay Junction S/C Cnr Jetty & Brighton Road",
    "sg:city":"Glenelg",
    "sg:classifiers":[
        {
            "category":"Personal",
            "subcategory":"Shoe Repair & Shine",
            "type":"Services"
        }
    ],
    "sg:phone":"+61 8 8376 2600",
    "sg:postcode":"5045",
    "sg:province":"SA",
    "sg:tags":[
        "footwear"
    ],
    "sg:website":"http://www.stateshoes.com",
    "wof:name":"State Shoe Repairs",
    "wof:placetype":"venue"
},
  "geometry": {"coordinates":[138.51959199999999,-34.980057],"type":"Point"}
}