{
  "type": "Feature",
  "properties": {
    "addr:full":"118 Crozier Ave Melrose Park SA 5039",
    "addr:housenumber":"118",
    "addr:postcode":"5039",
    "addr:street":"Crozier Ave",
    "iso:country":"AU",
    "sg:address":"118 Crozier Ave",
    "sg:city":"Melrose Park",
    "sg:classifiers":[
        {
            "category":"Building & Trades",
            "subcategory":"Construction",
            "type":"Services"
        }
    ],
    "sg:phone":"+61 8 8177 0507",
    "sg:postcode":"5039",
    "sg:province":"SA",
    "sg:tags":[
        "repair",
        "maintenance",
        "contractor"
    ],
    "wof:name":"Ozwiz Care",
    "wof:placetype":"venue"
},
  "geometry": {"coordinates":[138.581375122,-34.9872665405],"type":"Point"}
}