{
  "type": "Feature",
  "properties": {
    "iso:country":"AU",
    "sg:address":"44 Shakespeare St",
    "sg:city":"Mt Hawthorn",
    "sg:classifiers":[
        {
            "category":"Personal",
            "subcategory":"Beauty Salon",
            "type":"Services"
        }
    ],
    "sg:phone":"+61 438 942 251",
    "sg:postcode":"6016",
    "sg:province":"WA",
    "sg:tags":[
        "hairdresser"
    ],
    "wof:name":"Webster Hairdressing",
    "wof:placetype":"venue"
},
  "geometry": {"coordinates":[115.84326934800001,-31.921787262],"type":"Point"}
}