{
  "type": "Feature",
  "properties": {
    "addr:full":"13 Church St Oatlands TAS 7120",
    "addr:housenumber":"13",
    "addr:postcode":"7120",
    "addr:street":"Church St",
    "iso:country":"AU",
    "sg:address":"13 Church St",
    "sg:city":"Oatlands",
    "sg:classifiers":[
        {
            "category":"Health Services",
            "subcategory":"Optometrist",
            "type":"Services"
        }
    ],
    "sg:phone":"+61 1300 653 937",
    "sg:postcode":"7120",
    "sg:province":"TAS",
    "wof:name":"Dennis Gregory",
    "wof:placetype":"venue"
},
  "geometry": {"coordinates":[147.37031555199999,-42.299949646],"type":"Point"}
}