{
  "type": "Feature",
  "properties": {
    "addr:full":"16 Southey St Jerilderie NSW 2716",
    "addr:housenumber":"16",
    "addr:postcode":"2716",
    "addr:street":"Southey St",
    "iso:country":"AU",
    "sg:address":"16 Southey St",
    "sg:city":"Jerilderie",
    "sg:classifiers":[
        {
            "category":"Home & Garden",
            "subcategory":"Garden Supply",
            "type":"Retail Goods"
        }
    ],
    "sg:phone":"+61 3 5886 1609",
    "sg:postcode":"2716",
    "sg:province":"NSW",
    "sg:tags":[
        "fertilizer"
    ],
    "wof:name":"Jerilderie Fertilizers & Traders",
    "wof:placetype":"venue"
},
  "geometry": {"coordinates":[145.724517822,-35.3553886414],"type":"Point"}
}