{
  "type": "Feature",
  "properties": {
    "addr:full":"4 Timothy Crt Wallan VIC 3756",
    "addr:housenumber":"4",
    "addr:postcode":"3756",
    "addr:street":"Timothy Crt",
    "iso:country":"AU",
    "sg:address":"4 Timothy Crt",
    "sg:city":"Wallan",
    "sg:classifiers":[
        {
            "category":"Building & Trades",
            "subcategory":"Construction",
            "type":"Services"
        }
    ],
    "sg:phone":"+61 417 577 830",
    "sg:postcode":"3756",
    "sg:province":"VIC",
    "sg:tags":[
        "concrete",
        "contractor"
    ],
    "wof:name":"Highway Paving",
    "wof:placetype":"venue"
},
  "geometry": {"coordinates":[144.972015,-37.412899],"type":"Point"}
}