{
  "type": "Feature",
  "properties": {
    "iso:country":"AU",
    "sg:address":"36 Victoria St",
    "sg:city":"Kurri Kurri",
    "sg:classifiers":[
        {
            "category":"Autos & Motor Vehicles",
            "subcategory":"Auto Supplies",
            "type":"Retail Goods"
        }
    ],
    "sg:phone":"+61 2 4936 2077",
    "sg:postcode":"2327",
    "sg:province":"NSW",
    "sg:tags":[
        "tyre"
    ],
    "wof:name":"Claremont Distributors",
    "wof:placetype":"venue"
},
  "geometry": {"coordinates":[151.48358154300001,-32.8188400269],"type":"Point"}
}