{
  "type": "Feature",
  "properties": {
    "iso:country":"AU",
    "sg:address":"Level 11/ 459 Little Collins St",
    "sg:city":"Melbourne",
    "sg:classifiers":[
        {
            "category":"Education",
            "subcategory":"Vocational School",
            "type":"Public Place"
        }
    ],
    "sg:phone":"+61 3 9760 5155",
    "sg:postcode":"3000",
    "sg:province":"VIC",
    "sg:tags":[
        "tafe",
        "college",
        "training"
    ],
    "wof:name":"The Ashmark Institute of Australia",
    "wof:placetype":"venue"
},
  "geometry": {"coordinates":[144.95942688,-37.8165664673],"type":"Point"}
}