{
  "type": "Feature",
  "properties": {
    "addr:full":"200 Pakenham St Echuca VIC 3564",
    "addr:housenumber":"200",
    "addr:postcode":"3564",
    "addr:street":"Pakenham St",
    "iso:country":"AU",
    "sg:address":"200 Pakenham St",
    "sg:city":"Echuca",
    "sg:classifiers":[
        {
            "category":"Professional",
            "subcategory":"Printing & Photocopies",
            "type":"Services"
        }
    ],
    "sg:phone":"+61 3 5482 3009",
    "sg:postcode":"3564",
    "sg:province":"VIC",
    "sg:tags":[
        "photocopier"
    ],
    "wof:name":"Peat's Office National",
    "wof:placetype":"venue"
},
  "geometry": {"coordinates":[144.75160217300001,-36.1279525757],"type":"Point"}
}