{
  "type": "Feature",
  "properties": {
    "iso:country":"AU",
    "sg:address":"25 Lancelot Ave",
    "sg:city":"Hazelwood Park",
    "sg:classifiers":[
        {
            "category":"Government",
            "subcategory":"Post Office",
            "type":"Public Place"
        }
    ],
    "sg:phone":"+61 8 8338 1267",
    "sg:postcode":"5066",
    "sg:province":"SA",
    "sg:tags":[
        "yoga"
    ],
    "wof:name":"Sebelis Sandra",
    "wof:placetype":"venue"
},
  "geometry": {"coordinates":[138.65403747600001,-34.9427032471],"type":"Point"}
}