{
  "type": "Feature",
  "properties": {
    "addr:full":"100 Franklins St Adelaide SA 5000",
    "addr:housenumber":"100",
    "addr:postcode":"5000",
    "addr:street":"Franklins St",
    "iso:country":"AU",
    "sg:address":"100 Franklins St",
    "sg:city":"Adelaide",
    "sg:classifiers":[
        {
            "category":"Professional",
            "type":"Services"
        }
    ],
    "sg:phone":"+61 13 32 78",
    "sg:postcode":"5000",
    "sg:province":"SA",
    "sg:tags":[
        "courier"
    ],
    "wof:name":"Toll Fast",
    "wof:placetype":"venue"
},
  "geometry": {"coordinates":[138.59539794899999,-34.9272537231],"type":"Point"}
}