{
  "type": "Feature",
  "properties": {
    "addr:full":"3 Vivian St Bellevue Hill NSW 2023",
    "addr:housenumber":"3",
    "addr:postcode":"2023",
    "addr:street":"Vivian St",
    "iso:country":"AU",
    "sg:address":"3 Vivian St",
    "sg:city":"Bellevue Hill",
    "sg:classifiers":[
        {
            "category":"Health Services",
            "subcategory":"Doctor",
            "type":"Services"
        }
    ],
    "sg:phone":"+61 2 9326 2658",
    "sg:postcode":"2023",
    "sg:province":"NSW",
    "sg:tags":[
        "medical",
        "practitioner"
    ],
    "wof:name":"Skin Ca Screening Maps",
    "wof:placetype":"venue"
},
  "geometry": {"coordinates":[151.25683593799999,-33.88230896],"type":"Point"}
}