{
  "type": "Feature",
  "properties": {
    "iso:country":"AU",
    "sg:address":"29 Bedford St",
    "sg:city":"Nedlands",
    "sg:classifiers":[
        {
            "category":"Shopping",
            "subcategory":"Pets & Pet Supplies",
            "type":"Retail Goods"
        }
    ],
    "sg:phone":"+61 8 9389 8800",
    "sg:postcode":"6009",
    "sg:province":"WA",
    "sg:tags":[
        "boring",
        "drilling",
        "equipment"
    ],
    "sg:website":"http://www.surplusequipment.com.au",
    "wof:name":"Surplus Equipment Brokers",
    "wof:placetype":"venue"
},
  "geometry": {"coordinates":[115.798752,-31.977625],"type":"Point"}
}