{
  "type": "Feature",
  "properties": {
    "iso:country":"AU",
    "sg:address":"4 Aurora Ave",
    "sg:city":"Queanbeyan",
    "sg:classifiers":[
        {
            "category":"Wholesale",
            "subcategory":"Auto Parts",
            "type":"Manufacturing & Wholesale Goods"
        }
    ],
    "sg:phone":"+61 2 6297 5791",
    "sg:postcode":"2620",
    "sg:province":"ACT",
    "sg:tags":[
        "recyclers"
    ],
    "wof:name":"Waneroo Auto Dismantlers",
    "wof:placetype":"venue"
},
  "geometry": {"coordinates":[149.24429321299999,-35.3390960693],"type":"Point"}
}