{
  "type": "Feature",
  "properties": {
    "iso:country":"AU",
    "sg:address":"238 Hoskins St",
    "sg:city":"Temora",
    "sg:classifiers":[
        {
            "category":"Travel",
            "subcategory":"Hotels & Motels",
            "type":"Entertainment"
        }
    ],
    "sg:phone":"+61 2 6978 1254",
    "sg:postcode":"2666",
    "sg:province":"NSW",
    "sg:tags":[
        "accommodation"
    ],
    "wof:name":"Royal Hotel Temora",
    "wof:placetype":"venue"
},
  "geometry": {"coordinates":[147.53428649899999,-34.4483947754],"type":"Point"}
}