{
  "type": "Feature",
  "properties": {
    "addr:full":"Unit 2, 2 Crown St Tamworth NSW 2340",
    "addr:housenumber":"2",
    "addr:postcode":"2340",
    "addr:street":"Crown St",
    "iso:country":"AU",
    "sg:address":"Unit 2, 2 Crown St",
    "sg:city":"Tamworth",
    "sg:classifiers":[
        {
            "category":"Transit Center",
            "subcategory":"Freight",
            "type":"Transportation"
        }
    ],
    "sg:phone":"+61 2 6765 5040",
    "sg:postcode":"2340",
    "sg:province":"NSW",
    "sg:tags":[
        "forklift",
        "truck"
    ],
    "wof:name":"Crown Equipment",
    "wof:placetype":"venue"
},
  "geometry": {"coordinates":[150.916381836,-31.0869140625],"type":"Point"}
}