{
  "type": "Feature",
  "properties": {
    "addr:full":"20 Carrington St Kalgoorlie WA 6430",
    "addr:housenumber":"20",
    "addr:postcode":"6430",
    "addr:street":"Carrington St",
    "iso:country":"AU",
    "sg:address":"20 Carrington St",
    "sg:city":"Kalgoorlie",
    "sg:classifiers":[
        {
            "category":"Social Services",
            "subcategory":"Child Care",
            "type":"Services"
        }
    ],
    "sg:phone":"+61 8 9091 6619",
    "sg:postcode":"6430",
    "sg:province":"WA",
    "wof:name":"ABC Learning Centres",
    "wof:placetype":"venue"
},
  "geometry": {"coordinates":[121.478111267,-30.7583236694],"type":"Point"}
}