{
  "type": "Feature",
  "properties": {
    "addr:full":"Unit 1/ 16 Boag Pl Morley WA 6062",
    "addr:housenumber":"16",
    "addr:postcode":"6062",
    "addr:street":"Boag Pl",
    "iso:country":"AU",
    "sg:address":"Unit 1/ 16 Boag Pl",
    "sg:city":"Morley",
    "sg:classifiers":[
        {
            "category":"Professional",
            "type":"Services"
        }
    ],
    "sg:phone":"+61 8 9276 3487",
    "sg:postcode":"6062",
    "sg:province":"WA",
    "sg:tags":[
        "overlocking",
        "rug",
        "carpet"
    ],
    "wof:name":"Kens Carpet Overlocking & Fringing Service",
    "wof:placetype":"venue"
},
  "geometry": {"coordinates":[115.894859314,-31.8991127014],"type":"Point"}
}