{
  "type": "Feature",
  "properties": {
    "addr:full":"48 Whysall Rd Greenacres SA 5086",
    "addr:housenumber":"48",
    "addr:postcode":"5086",
    "addr:street":"Whysall Rd",
    "iso:country":"AU",
    "sg:address":"48 Whysall Rd",
    "sg:city":"Greenacres",
    "sg:classifiers":[
        {
            "category":"Manufacturing",
            "subcategory":"Food",
            "type":"Manufacturing & Wholesale Goods"
        }
    ],
    "sg:phone":"+61 8 8365 9261",
    "sg:postcode":"5086",
    "sg:province":"SA",
    "sg:tags":[
        "product",
        "nut",
        "edible"
    ],
    "wof:name":"King Kong Macadamias",
    "wof:placetype":"venue"
},
  "geometry": {"coordinates":[138.63101196299999,-34.866268158],"type":"Point"}
}