{
  "type": "Feature",
  "properties": {
    "addr:full":"Shop 2 67 Elder St Alice Springs NT 0870",
    "addr:housenumber":"shop;67",
    "addr:postcode":"nt 0870",
    "addr:street":"Elder St",
    "iso:country":"AU",
    "sg:address":"Shop 2 67 Elder St",
    "sg:city":"Alice Springs",
    "sg:classifiers":[
        {
            "category":"Shopping",
            "subcategory":"Bicycles & Sporting Goods",
            "type":"Retail Goods"
        }
    ],
    "sg:phone":"+61 8 8952 3638",
    "sg:postcode":"0870",
    "sg:province":"NT",
    "sg:tags":[
        "chemical",
        "equipment",
        "pool",
        "swimming"
    ],
    "wof:name":"Pool Poppits",
    "wof:placetype":"venue"
},
  "geometry": {"coordinates":[133.86349487300001,-23.6948604584],"type":"Point"}
}