{
  "type": "Feature",
  "properties": {
    "addr:full":"2C/ 6-8 Flagstaff St Gladesville NSW 2111",
    "addr:housenumber":"/ 6-8",
    "addr:postcode":"2111",
    "addr:street":"Flagstaff St",
    "iso:country":"AU",
    "sg:address":"2C/ 6-8 Flagstaff St",
    "sg:city":"Gladesville",
    "sg:classifiers":[
        {
            "category":"Health Services",
            "subcategory":"Dentist",
            "type":"Services"
        }
    ],
    "sg:phone":"+61 2 9817 2700",
    "sg:postcode":"2111",
    "sg:province":"NSW",
    "wof:name":"Heng Philip C C",
    "wof:placetype":"venue"
},
  "geometry": {"coordinates":[151.12852477999999,-33.8316230774],"type":"Point"}
}