{
  "type": "Feature",
  "properties": {
    "iso:country":"AU",
    "sg:address":"18 Park Rd",
    "sg:city":"Vineyard",
    "sg:classifiers":[
        {
            "category":"Home & Garden",
            "subcategory":"Carpets & Floor Coverings",
            "type":"Retail Goods"
        }
    ],
    "sg:phone":"+61 2 9624 8999",
    "sg:postcode":"2765",
    "sg:province":"NSW",
    "sg:tags":[
        "tile",
        "wall"
    ],
    "wof:name":"Slate Centres The",
    "wof:placetype":"venue"
},
  "geometry": {"coordinates":[150.84184265100001,-33.6325073242],"type":"Point"}
}