{
  "type": "Feature",
  "properties": {
    "iso:country":"AU",
    "sg:address":"PO Box 224",
    "sg:city":"Belmore",
    "sg:classifiers":[
        {
            "category":"Social Services",
            "subcategory":"Job Training",
            "type":"Services"
        }
    ],
    "sg:phone":"+61 407 410 709",
    "sg:postcode":"2192",
    "sg:province":"NSW",
    "sg:tags":[
        "interpreter"
    ],
    "wof:name":"Indonesian Interpreter",
    "wof:placetype":"venue"
},
  "geometry": {"coordinates":[151.088242,-33.91946],"type":"Point"}
}