{
  "type": "Feature",
  "properties": {
    "iso:country":"AU",
    "sg:address":"129 Manning Point Rd",
    "sg:city":"Old Bar",
    "sg:classifiers":[
        {
            "category":"Building & Trades",
            "subcategory":"Construction",
            "type":"Services"
        }
    ],
    "sg:phone":"+61 414 274 010",
    "sg:postcode":"2430",
    "sg:province":"NSW",
    "sg:tags":[
        "contractor"
    ],
    "wof:name":"Garry Addison Building Pty Ltd",
    "wof:placetype":"venue"
},
  "geometry": {"coordinates":[152.56137100000001,-31.950909],"type":"Point"}
}