{
  "type": "Feature",
  "properties": {
    "addr:full":"22 Atkins Rd Pakenham VIC 3810",
    "addr:housenumber":"22",
    "addr:postcode":"3810",
    "addr:street":"Atkins Rd",
    "iso:country":"AU",
    "sg:address":"22 Atkins Rd",
    "sg:city":"Pakenham",
    "sg:classifiers":[
        {
            "category":"Building & Trades",
            "subcategory":"Construction",
            "type":"Services"
        }
    ],
    "sg:phone":"+61 409 001 572",
    "sg:postcode":"3810",
    "sg:province":"VIC",
    "sg:tags":[
        "concrete",
        "contractor"
    ],
    "wof:name":"Tek Concreting",
    "wof:placetype":"venue"
},
  "geometry": {"coordinates":[145.48820499999999,-38.068096],"type":"Point"}
}