{
  "type": "Feature",
  "properties": {
    "iso:country":"AU",
    "sg:address":"353A Barrenjoey Rd",
    "sg:city":"Newport",
    "sg:classifiers":[
        {
            "category":"Food & Beverages",
            "subcategory":"Bakery",
            "type":"Retail Goods"
        }
    ],
    "sg:phone":"+61 2 9979 4487",
    "sg:postcode":"2106",
    "sg:province":"NSW",
    "sg:tags":[
        "baker"
    ],
    "wof:name":"Bakers Delight Ltd",
    "wof:placetype":"venue"
},
  "geometry": {"coordinates":[151.32032775900001,-33.6549263],"type":"Point"}
}