{
  "type": "Feature",
  "properties": {
    "addr:full":"10 Three Chain Rd Lismore NSW 2480",
    "addr:housenumber":"10",
    "addr:postcode":"2480",
    "addr:street":"Three Chain Rd",
    "iso:country":"AU",
    "sg:address":"10 Three Chain Rd",
    "sg:city":"Lismore",
    "sg:classifiers":[
        {
            "category":"Arts & Performance",
            "subcategory":"Music",
            "type":"Entertainment"
        }
    ],
    "sg:phone":"+61 2 6622 3099",
    "sg:postcode":"2480",
    "sg:province":"NSW",
    "sg:tags":[
        "hi-fi",
        "equipment"
    ],
    "wof:name":"Sky Electronics",
    "wof:placetype":"venue"
},
  "geometry": {"coordinates":[153.262741089,-28.8205547333],"type":"Point"}
}