{
  "type": "Feature",
  "properties": {
    "addr:full":"67 Uralba St Lismore NSW 2480",
    "addr:housenumber":"67",
    "addr:postcode":"2480",
    "addr:street":"Uralba St",
    "iso:country":"AU",
    "sg:address":"67 Uralba St",
    "sg:city":"Lismore",
    "sg:classifiers":[
        {
            "category":"Health Services",
            "subcategory":"Doctor",
            "type":"Services"
        }
    ],
    "sg:phone":"+61 2 6621 2567",
    "sg:postcode":"2480",
    "sg:province":"NSW",
    "sg:tags":[
        "medical",
        "practitioner"
    ],
    "wof:name":"O&#039;Sullivan B T",
    "wof:placetype":"venue"
},
  "geometry": {"coordinates":[153.291946411,-28.8096466064],"type":"Point"}
}