{
  "type": "Feature",
  "properties": {
    "addr:full":"3 Bangalow Rd Ballina NSW 2478",
    "addr:housenumber":"3",
    "addr:postcode":"2478",
    "addr:street":"Bangalow Rd",
    "iso:country":"AU",
    "sg:address":"3 Bangalow Rd",
    "sg:city":"Ballina",
    "sg:classifiers":[
        {
            "category":"Professional",
            "type":"Services"
        }
    ],
    "sg:phone":"+61 2 6686 4434",
    "sg:postcode":"2478",
    "sg:province":"NSW",
    "sg:tags":[
        "transport"
    ],
    "wof:name":"Ballina Table Top Crane Hire",
    "wof:placetype":"venue"
},
  "geometry": {"coordinates":[153.56578064000001,-28.8626689911],"type":"Point"}
}