{
  "type": "Feature",
  "properties": {
    "iso:country":"AU",
    "sg:address":"Bambra Rd",
    "sg:city":"Caulfield",
    "sg:classifiers":[
        {
            "category":"Building & Trades",
            "subcategory":"Cleaning & Sanitation",
            "type":"Services"
        }
    ],
    "sg:phone":"+61 417 307 903",
    "sg:postcode":"3162",
    "sg:province":"VIC",
    "sg:tags":[
        "cleaner",
        "repairer",
        "roof"
    ],
    "wof:name":"Phoenix Guttering",
    "wof:placetype":"venue"
},
  "geometry": {"coordinates":[145.03018188499999,-37.8801803589],"type":"Point"}
}