{
  "type": "Feature",
  "properties": {
    "addr:full":"14 Estelle St Sunshine VIC 3020",
    "addr:housenumber":"14",
    "addr:postcode":"3020",
    "addr:street":"Estelle St",
    "iso:country":"AU",
    "sg:address":"14 Estelle St",
    "sg:city":"Sunshine",
    "sg:classifiers":[
        {
            "category":"Arts & Performance",
            "subcategory":"Music",
            "type":"Entertainment"
        }
    ],
    "sg:phone":"+61 413 525 566",
    "sg:postcode":"3020",
    "sg:province":"VIC",
    "sg:tags":[
        "mobile",
        "jockey",
        "disc"
    ],
    "wof:name":"DJ Gidz",
    "wof:placetype":"venue"
},
  "geometry": {"coordinates":[144.811127,-37.787109],"type":"Point"}
}