{
  "type": "Feature",
  "properties": {
    "addr:full":"Wyan Rd Rappville NSW 2469",
    "addr:postcode":"2469",
    "addr:street":"Wyan Rd",
    "iso:country":"AU",
    "sg:address":"Wyan Rd",
    "sg:city":"Rappville",
    "sg:classifiers":[
        {
            "category":"Farming",
            "subcategory":"Farm",
            "type":"Manufacturing & Wholesale Goods"
        }
    ],
    "sg:phone":"+61 2 6661 7182",
    "sg:postcode":"2469",
    "sg:province":"NSW",
    "sg:tags":[
        "farmer"
    ],
    "wof:name":"Cole K",
    "wof:placetype":"venue"
},
  "geometry": {"coordinates":[152.95091247600001,-29.0892467499],"type":"Point"}
}