{
  "type": "Feature",
  "properties": {
    "iso:country":"AU",
    "sg:address":"Overport Rd",
    "sg:city":"Frankston",
    "sg:classifiers":[
        {
            "category":"Education",
            "subcategory":"School",
            "type":"Public Place"
        }
    ],
    "sg:phone":"+61 3 9787 3633",
    "sg:postcode":"3199",
    "sg:province":"VIC",
    "sg:tags":[
        "state",
        "except",
        "nsw"
    ],
    "wof:name":"Derinya Primary",
    "wof:placetype":"venue"
},
  "geometry": {"coordinates":[145.125274658,-38.1629486084],"type":"Point"}
}