{
  "type": "Feature",
  "properties": {
    "addr:full":"13 Marine Pde Ocean Grove VIC 3226",
    "addr:housenumber":"13",
    "addr:postcode":"3226",
    "addr:street":"Marine Pde",
    "iso:country":"AU",
    "sg:address":"13 Marine Pde",
    "sg:city":"Ocean Grove",
    "sg:classifiers":[
        {
            "category":"Shopping",
            "subcategory":"Baby Store",
            "type":"Retail Goods"
        }
    ],
    "sg:phone":"+61 3 5255 4095",
    "sg:postcode":"3226",
    "sg:province":"VIC",
    "sg:tags":[
        "wear"
    ],
    "wof:name":"Little Darlings",
    "wof:placetype":"venue"
},
  "geometry": {"coordinates":[144.53825399999999,-38.25135],"type":"Point"}
}