{
  "type": "Feature",
  "properties": {
    "addr:full":"11 Harwell Rd Ferntree Gully VIC 3156",
    "addr:housenumber":"11",
    "addr:postcode":"3156",
    "addr:street":"Harwell Rd",
    "iso:country":"AU",
    "sg:address":"11 Harwell Rd",
    "sg:city":"Ferntree Gully",
    "sg:classifiers":[
        {
            "category":"Education",
            "subcategory":"Kindergarten",
            "type":"Public Place"
        }
    ],
    "sg:phone":"+61 3 9758 3541",
    "sg:postcode":"3156",
    "sg:province":"VIC",
    "sg:tags":[
        "pre-schools"
    ],
    "wof:name":"Alexander Magit Pre-School",
    "wof:placetype":"venue"
},
  "geometry": {"coordinates":[145.27023315400001,-37.8865127563],"type":"Point"}
}