{
  "type": "Feature",
  "properties": {
    "iso:country":"AU",
    "sg:address":"Townhse45/ 15 Jugan St",
    "sg:city":"Glendalough",
    "sg:classifiers":[
        {
            "category":"Banks & Credit Unions",
            "subcategory":"Investment Brokerage",
            "type":"Services"
        }
    ],
    "sg:phone":"+61 8 9242 5026",
    "sg:postcode":"6016",
    "sg:province":"WA",
    "sg:tags":[
        "management",
        "property"
    ],
    "wof:name":"Octant Pty Ltd",
    "wof:placetype":"venue"
},
  "geometry": {"coordinates":[115.8253479,-31.9156913757],"type":"Point"}
}