{
  "type": "Feature",
  "properties": {
    "iso:country":"AU",
    "sg:address":"13 Fenton Ave",
    "sg:city":"Campbells Creek",
    "sg:classifiers":[
        {
            "category":"Professional",
            "subcategory":"Accounting & Tax Preparation",
            "type":"Services"
        }
    ],
    "sg:phone":"+61 3 5470 6994",
    "sg:postcode":"3451",
    "sg:province":"VIC",
    "sg:tags":[
        "bookkeeping"
    ],
    "wof:name":"Navigator Office Support",
    "wof:placetype":"venue"
},
  "geometry": {"coordinates":[144.19886779800001,-37.0896263123],"type":"Point"}
}