{
  "type": "Feature",
  "properties": {
    "iso:country":"AU",
    "sg:address":"Penrhyn Rd",
    "sg:city":"Botany",
    "sg:classifiers":[
        {
            "category":"Transit Center",
            "subcategory":"Freight",
            "type":"Transportation"
        }
    ],
    "sg:phone":"+61 2 9394 0000",
    "sg:postcode":"2019",
    "sg:province":"NSW",
    "sg:tags":[
        "stevedore"
    ],
    "wof:name":"PATRICK The Australian Stevedore",
    "wof:placetype":"venue"
},
  "geometry": {"coordinates":[151.21461486800001,-33.961933136],"type":"Point"}
}