{
  "type": "Feature",
  "properties": {
    "addr:full":"273 Camboon Rd Malaga WA 6090",
    "addr:housenumber":"273",
    "addr:postcode":"6090",
    "addr:street":"Camboon Rd",
    "iso:country":"AU",
    "sg:address":"273 Camboon Rd",
    "sg:city":"Malaga",
    "sg:classifiers":[
        {
            "category":"Manufacturing",
            "subcategory":"Paper Products",
            "type":"Manufacturing & Wholesale Goods"
        }
    ],
    "sg:phone":"+61 8 9248 5077",
    "sg:postcode":"6090",
    "sg:province":"WA",
    "sg:tags":[
        "metal",
        "non-ferrous",
        "foundry"
    ],
    "wof:name":"Ausco Products",
    "wof:placetype":"venue"
},
  "geometry": {"coordinates":[115.886993408,-31.8564147949],"type":"Point"}
}