{
  "type": "Feature",
  "properties": {
    "iso:country":"AU",
    "sg:address":"2/ 12 Commercial Drv",
    "sg:city":"Ashmore",
    "sg:classifiers":[
        {
            "category":"Professional",
            "subcategory":"Detective & Security Services",
            "type":"Services"
        }
    ],
    "sg:phone":"+61 7 5503 1555",
    "sg:postcode":"4214",
    "sg:province":"QLD",
    "sg:tags":[
        "equipment",
        "window",
        "doors"
    ],
    "wof:name":"Central Insect Screens",
    "wof:placetype":"venue"
},
  "geometry": {"coordinates":[153.39056396500001,-27.980676651],"type":"Point"}
}