{
  "type": "Feature",
  "properties": {
    "addr:full":"75 Central Ave Sherwood QLD 4075",
    "addr:housenumber":"75",
    "addr:postcode":"4075",
    "addr:street":"Central Ave",
    "iso:country":"AU",
    "sg:address":"75 Central Ave",
    "sg:city":"Sherwood",
    "sg:classifiers":[
        {
            "category":"Personal",
            "subcategory":"Massage",
            "type":"Services"
        }
    ],
    "sg:phone":"+61 7 3379 7019",
    "sg:postcode":"4075",
    "sg:province":"QLD",
    "sg:tags":[
        "therapy"
    ],
    "wof:name":"Body Balance",
    "wof:placetype":"venue"
},
  "geometry": {"coordinates":[152.98550415,-27.526550293],"type":"Point"}
}