{
  "type": "Feature",
  "properties": {
    "addr:full":"Shop 2 70 Bloomfield St Cleveland QLD 4163",
    "addr:housenumber":"shop;70",
    "addr:postcode":"4163",
    "addr:street":"Bloomfield St",
    "iso:country":"AU",
    "sg:address":"Shop 2 70 Bloomfield St",
    "sg:city":"Cleveland",
    "sg:classifiers":[
        {
            "category":"Cafe",
            "type":"Food & Drink"
        }
    ],
    "sg:phone":"+61 7 3821 2744",
    "sg:postcode":"4163",
    "sg:province":"QLD",
    "wof:name":"Penny Lane Coffee",
    "wof:placetype":"venue"
},
  "geometry": {"coordinates":[153.267211914,-27.5270290375],"type":"Point"}
}