{
  "type": "Feature",
  "properties": {
    "iso:country":"AU",
    "sg:address":"PO Box 2039",
    "sg:city":"North Ipswich",
    "sg:classifiers":[
        {
            "category":"Recreation",
            "subcategory":"Fishing",
            "type":"Entertainment"
        }
    ],
    "sg:phone":"+61 1300 887 614",
    "sg:postcode":"4305",
    "sg:province":"QLD",
    "sg:tags":[
        "tackle"
    ],
    "wof:name":"Hook-Eze",
    "wof:placetype":"venue"
},
  "geometry": {"coordinates":[152.76356506400001,-27.5974407196],"type":"Point"}
}