{
  "type": "Feature",
  "properties": {
    "iso:country":"AU",
    "sg:address":"21- 23 East St",
    "sg:city":"Rockhampton",
    "sg:classifiers":[
        {
            "category":"Shopping",
            "subcategory":"Bridal",
            "type":"Retail Goods"
        }
    ],
    "sg:phone":"+61 7 4922 7088",
    "sg:postcode":"4700",
    "sg:province":"QLD",
    "sg:tags":[
        "hire",
        "wear"
    ],
    "wof:name":"Razzle Dazzle",
    "wof:placetype":"venue"
},
  "geometry": {"coordinates":[150.52107238799999,-23.3888206482],"type":"Point"}
}