{
  "type": "Feature",
  "properties": {
    "addr:full":"20 Seeana Crt Byron Bay NSW 2481",
    "addr:housenumber":"20",
    "addr:postcode":"2481",
    "addr:street":"Seeana Crt",
    "iso:country":"AU",
    "sg:address":"20 Seeana Crt",
    "sg:city":"Byron Bay",
    "sg:classifiers":[
        {
            "category":"Real Estate",
            "subcategory":"Architect",
            "type":"Services"
        }
    ],
    "sg:phone":"+61 2 6685 6984",
    "sg:postcode":"2481",
    "sg:province":"NSW",
    "wof:name":"Byron Bay Architecture",
    "wof:placetype":"venue"
},
  "geometry": {"coordinates":[153.612823486,-28.6468906403],"type":"Point"}
}