{
  "type": "Feature",
  "properties": {
    "iso:country":"AU",
    "sg:address":"PO Box 101",
    "sg:city":"Rosanna",
    "sg:classifiers":[
        {
            "category":"Professional",
            "subcategory":"Management & Consulting",
            "type":"Services"
        }
    ],
    "sg:phone":"+61 411 730 948",
    "sg:postcode":"3084",
    "sg:province":"VIC",
    "sg:tags":[
        "consultant",
        "migration"
    ],
    "wof:name":"IBIS Immigration Specialists 93928",
    "wof:placetype":"venue"
},
  "geometry": {"coordinates":[145.065307617,-37.7427215576],"type":"Point"}
}