{
  "type": "Feature",
  "properties": {
    "addr:full":"Shp2/ 7 Clarke St Crows Nest NSW 2065",
    "addr:housenumber":"7",
    "addr:postcode":"2065",
    "addr:street":"Clarke St",
    "iso:country":"AU",
    "sg:address":"Shp2/ 7 Clarke St",
    "sg:city":"Crows Nest",
    "sg:classifiers":[
        {
            "category":"Shopping",
            "subcategory":"Bicycles & Sporting Goods",
            "type":"Retail Goods"
        }
    ],
    "sg:phone":"+61 2 9438 2644",
    "sg:postcode":"2065",
    "sg:province":"NSW",
    "sg:tags":[
        "dance",
        "accessory",
        "wear",
        "supply"
    ],
    "wof:name":"Dune Bugs",
    "wof:placetype":"venue"
},
  "geometry": {"coordinates":[151.20033264200001,-33.8257713318],"type":"Point"}
}