{
  "type": "Feature",
  "properties": {
    "addr:full":"Princess Hwy Munro VIC 3862",
    "addr:postcode":"3862",
    "addr:street":"Princess Hwy",
    "iso:country":"AU",
    "sg:address":"Princess Hwy",
    "sg:city":"Munro",
    "sg:classifiers":[
        {
            "category":"Building & Trades",
            "subcategory":"Construction",
            "type":"Services"
        }
    ],
    "sg:phone":"+61 3 5145 8286",
    "sg:postcode":"3862",
    "sg:province":"VIC",
    "sg:tags":[
        "fencing",
        "contractor"
    ],
    "wof:name":"CBL Fencing",
    "wof:placetype":"venue"
},
  "geometry": {"coordinates":[147.204025269,-37.92943573],"type":"Point"}
}