{
  "type": "Feature",
  "properties": {
    "addr:full":"9B Blacksmith Crt Childers QLD 4660",
    "addr:housenumber":"9b",
    "addr:postcode":"4660",
    "addr:street":"Blacksmith Crt",
    "iso:country":"AU",
    "sg:address":"9B Blacksmith Crt",
    "sg:city":"Childers",
    "sg:classifiers":[
        {
            "category":"Home & Garden",
            "subcategory":"Carpets & Floor Coverings",
            "type":"Retail Goods"
        }
    ],
    "sg:phone":"+61 7 4126 2066",
    "sg:postcode":"4660",
    "sg:province":"QLD",
    "wof:name":"Accent Floor Coverings",
    "wof:placetype":"venue"
},
  "geometry": {"coordinates":[152.295684814,-25.2378635406],"type":"Point"}
}