{
  "type": "Feature",
  "properties": {
    "addr:full":"155 Ford Rd Rochedale QLD 4123",
    "addr:housenumber":"155",
    "addr:postcode":"4123",
    "addr:street":"Ford Rd",
    "iso:country":"AU",
    "sg:address":"155 Ford Rd",
    "sg:city":"Rochedale",
    "sg:phone":"+61 7 3440 9000",
    "sg:postcode":"4123",
    "sg:province":"QLD",
    "wof:name":"Highgate Engineers",
    "wof:placetype":"venue"
},
  "geometry": {"coordinates":[153.12968444800001,-27.5715389252],"type":"Point"}
}