{
  "type": "Feature",
  "properties": {
    "addr:full":"2/ 11 Industrial Drv Coffs Harbour NSW 2450",
    "addr:housenumber":"/ 11",
    "addr:postcode":"2450",
    "addr:street":"Industrial Drv",
    "iso:country":"AU",
    "sg:address":"2/ 11 Industrial Drv",
    "sg:city":"Coffs Harbour",
    "sg:classifiers":[
        {
            "category":"Professional",
            "subcategory":"Printing & Photocopies",
            "type":"Services"
        }
    ],
    "sg:phone":"+61 2 6652 8860",
    "sg:postcode":"2450",
    "sg:province":"NSW",
    "sg:tags":[
        "photocopying"
    ],
    "wof:name":"X - Press Printing Coffs Harbour",
    "wof:placetype":"venue"
},
  "geometry": {"coordinates":[153.08764600000001,-30.313799],"type":"Point"}
}