{
  "type": "Feature",
  "properties": {
    "iso:country":"AU",
    "sg:address":"31b Dava Drv",
    "sg:city":"Mornington",
    "sg:classifiers":[
        {
            "category":"Food & Beverages",
            "subcategory":"Groceries & Convenience Stores",
            "type":"Retail Goods"
        }
    ],
    "sg:phone":"+61 3 5975 5804",
    "sg:postcode":"3931",
    "sg:province":"VIC",
    "wof:name":"Jo Jo Milk Bar",
    "wof:placetype":"venue"
},
  "geometry": {"coordinates":[145.03213500999999,-38.2405853271],"type":"Point"}
}