{
  "type": "Feature",
  "properties": {
    "addr:full":"108-110 Gertrude St Fitzroy VIC 3065",
    "addr:housenumber":"108-110",
    "addr:postcode":"3065",
    "addr:street":"Gertrude St",
    "iso:country":"AU",
    "sg:address":"108-110 Gertrude St",
    "sg:city":"Fitzroy",
    "sg:classifiers":[
        {
            "category":"Arts & Performance",
            "subcategory":"Art Gallery",
            "type":"Entertainment"
        }
    ],
    "sg:phone":"+61 3 9416 3956",
    "sg:postcode":"3065",
    "sg:province":"VIC",
    "wof:name":"Dianne Tanzer Gallery",
    "wof:placetype":"venue"
},
  "geometry": {"coordinates":[144.97787475600001,-37.8059272766],"type":"Point"}
}