{
  "type": "Feature",
  "properties": {
    "addr:full":"93 - 99 Maroondah Hwy Ringwood VIC 3134",
    "addr:housenumber":"99",
    "addr:postcode":"3134",
    "addr:street":"Maroondah Hwy",
    "iso:country":"AU",
    "sg:address":"93 - 99 Maroondah Hwy",
    "sg:city":"Ringwood",
    "sg:classifiers":[
        {
            "category":"Sports & Exercise",
            "subcategory":"Gym",
            "type":"Entertainment"
        }
    ],
    "sg:phone":"+61 3 9870 1666",
    "sg:postcode":"3134",
    "sg:province":"VIC",
    "sg:tags":[
        "health",
        "fitness"
    ],
    "wof:name":"Genesis Fitness Clubs",
    "wof:placetype":"venue"
},
  "geometry": {"coordinates":[145.225067139,-37.8164024353],"type":"Point"}
}