{
  "type": "Feature",
  "properties": {
    "iso:country":"AU",
    "sg:address":"5 Kinsel Ave",
    "sg:city":"Kingsgrove",
    "sg:classifiers":[
        {
            "category":"Professional",
            "subcategory":"Art Services",
            "type":"Services"
        }
    ],
    "sg:phone":"+61 2 9150 7042",
    "sg:postcode":"2208",
    "sg:province":"NSW",
    "sg:tags":[
        "decorator",
        "painter"
    ],
    "wof:name":"Alan Sullivan",
    "wof:placetype":"venue"
},
  "geometry": {"coordinates":[151.09373500000001,-33.949223],"type":"Point"}
}