{
  "type": "Feature",
  "properties": {
    "addr:full":"Reedmans Rd Ormeau QLD 4208",
    "addr:postcode":"4208",
    "addr:street":"Reedmans Rd",
    "iso:country":"AU",
    "sg:address":"Reedmans Rd",
    "sg:city":"Ormeau",
    "sg:classifiers":[
        {
            "category":"Education",
            "subcategory":"School",
            "type":"Public Place"
        }
    ],
    "sg:phone":"+61 7 5547 5866",
    "sg:postcode":"4208",
    "sg:province":"QLD",
    "wof:name":"The Toogoolawa School",
    "wof:placetype":"venue"
},
  "geometry": {"coordinates":[153.25991821299999,-27.7907371521],"type":"Point"}
}