{
  "type": "Feature",
  "properties": {
    "addr:full":"4 Astley St Wynnum QLD 4178",
    "addr:housenumber":"4",
    "addr:postcode":"4178",
    "addr:street":"Astley St",
    "iso:country":"AU",
    "sg:address":"4 Astley St",
    "sg:city":"Wynnum",
    "sg:classifiers":[
        {
            "category":"Professional",
            "subcategory":"Art Services",
            "type":"Services"
        }
    ],
    "sg:phone":"+61 7 3893 1976",
    "sg:postcode":"4178",
    "sg:province":"QLD",
    "sg:tags":[
        "artist"
    ],
    "wof:name":"Graham. W. Smith",
    "wof:placetype":"venue"
},
  "geometry": {"coordinates":[153.16003418,-27.4491977692],"type":"Point"}
}