{
  "type": "Feature",
  "properties": {
    "addr:full":"Unit 13, 2 Burrows Rd South St Peters NSW 2044",
    "addr:housenumber":"2",
    "addr:postcode":"2044",
    "addr:street":"Burrows Rd South",
    "iso:country":"AU",
    "sg:address":"Unit 13, 2 Burrows Rd South St",
    "sg:city":"Peters",
    "sg:classifiers":[
        {
            "category":"Manufacturing",
            "subcategory":"Metals",
            "type":"Manufacturing & Wholesale Goods"
        }
    ],
    "sg:phone":"+61 2 9557 5350",
    "sg:postcode":"2044",
    "sg:province":"NSW",
    "sg:tags":[
        "steel",
        "fabricator",
        "mfrs"
    ],
    "wof:name":"Stainweld Fabrication Pty Ltd",
    "wof:placetype":"venue"
},
  "geometry": {"coordinates":[151.178055,-33.919846],"type":"Point"}
}