{
  "type": "Feature",
  "properties": {
    "iso:country":"AU",
    "sg:address":"Cambus Rd",
    "sg:city":"Yering",
    "sg:classifiers":[
        {
            "category":"Farming",
            "subcategory":"Orchard",
            "type":"Manufacturing & Wholesale Goods"
        }
    ],
    "sg:phone":"+61 3 9739 1570",
    "sg:postcode":"3770",
    "sg:province":"VIC",
    "sg:tags":[
        "pear",
        "apple",
        "grower"
    ],
    "wof:name":"G. Johns Orchards",
    "wof:placetype":"venue"
},
  "geometry": {"coordinates":[145.38833600000001,-37.697002],"type":"Point"}
}