{
  "type": "Feature",
  "properties": {
    "addr:full":"57 Kenthurst Rd Kenthurst NSW 2156",
    "addr:housenumber":"57",
    "addr:postcode":"2156",
    "addr:street":"Kenthurst Rd",
    "iso:country":"AU",
    "sg:address":"57 Kenthurst Rd",
    "sg:city":"Kenthurst",
    "sg:classifiers":[
        {
            "category":"Retail",
            "subcategory":"Auto Repair",
            "type":"Services"
        }
    ],
    "sg:phone":"+61 2 9654 1880",
    "sg:postcode":"2156",
    "sg:province":"NSW",
    "sg:tags":[
        "repairer",
        "motor",
        "engineer"
    ],
    "wof:name":"Cali SA Mechanical Repairs Pty Ltd",
    "wof:placetype":"venue"
},
  "geometry": {"coordinates":[151.011062622,-33.6809768677],"type":"Point"}
}