{
  "type": "Feature",
  "properties": {
    "addr:full":"212 High St Maryborough VIC 3465",
    "addr:housenumber":"212",
    "addr:postcode":"3465",
    "addr:street":"High St",
    "iso:country":"AU",
    "sg:address":"212 High St",
    "sg:city":"Maryborough",
    "sg:classifiers":[
        {
            "category":"Fast Food",
            "type":"Food & Drink"
        }
    ],
    "sg:phone":"+61 3 5461 3724",
    "sg:postcode":"3465",
    "sg:province":"VIC",
    "sg:tags":[
        "away",
        "take"
    ],
    "wof:name":"Chicken Maryland",
    "wof:placetype":"venue"
},
  "geometry": {"coordinates":[143.73963928200001,-37.0455513],"type":"Point"}
}