{
  "type": "Feature",
  "properties": {
    "addr:full":"1767 Old Coast Rd Bouvard WA 6210",
    "addr:housenumber":"1767",
    "addr:postcode":"6210",
    "addr:street":"Old Coast Rd",
    "iso:country":"AU",
    "sg:address":"1767 Old Coast Rd",
    "sg:city":"Bouvard",
    "sg:classifiers":[
        {
            "category":"Real Estate",
            "subcategory":"Real Estate Agent",
            "type":"Services"
        }
    ],
    "sg:phone":"+61 8 9582 2379",
    "sg:postcode":"6210",
    "sg:province":"WA",
    "sg:tags":[
        "steel",
        "foundry",
        "iron"
    ],
    "wof:name":"Supreme Precision Castings",
    "wof:placetype":"venue"
},
  "geometry": {"coordinates":[115.714569,-32.537968],"type":"Point"}
}