{
  "type": "Feature",
  "properties": {
    "addr:full":"Unit 1/61 Walters Drv Herdsman Business Park Osborne Park WA 6017",
    "addr:housenumber":"61;business",
    "addr:postcode":"6017",
    "addr:street":"Walters Drv",
    "iso:country":"AU",
    "sg:address":"Unit 1/61 Walters Drv Herdsman Business Park",
    "sg:city":"Osborne Park",
    "sg:classifiers":[
        {
            "category":"Real Estate",
            "subcategory":"Surveying",
            "type":"Services"
        }
    ],
    "sg:phone":"+61 8 9443 2200",
    "sg:postcode":"6017",
    "sg:province":"WA",
    "sg:tags":[
        "surveyor",
        "land"
    ],
    "wof:name":"Town & Country Surveys",
    "wof:placetype":"venue"
},
  "geometry": {"coordinates":[115.817710877,-31.9038391113],"type":"Point"}
}