{
  "type": "Feature",
  "properties": {
    "iso:country":"AU",
    "sg:address":"Albert St",
    "sg:city":"Moruya",
    "sg:classifiers":[
        {
            "category":"Education",
            "subcategory":"School",
            "type":"Public Place"
        }
    ],
    "sg:phone":"+61 2 4474 2155",
    "sg:postcode":"2537",
    "sg:province":"NSW",
    "sg:tags":[
        "state",
        "-",
        "nsw"
    ],
    "wof:name":"Moruya High School",
    "wof:placetype":"venue"
},
  "geometry": {"coordinates":[150.078582764,-35.9179840088],"type":"Point"}
}