{
  "type": "Feature",
  "properties": {
    "addr:full":"1 Littleton St Crows Nest QLD 4355",
    "addr:housenumber":"1",
    "addr:postcode":"4355",
    "addr:street":"Littleton St",
    "iso:country":"AU",
    "sg:address":"1 Littleton St",
    "sg:city":"Crows Nest",
    "sg:classifiers":[
        {
            "category":"Education",
            "subcategory":"School",
            "type":"Public Place"
        }
    ],
    "sg:phone":"+61 7 4698 1271",
    "sg:postcode":"4355",
    "sg:province":"QLD",
    "sg:tags":[
        "state",
        "except",
        "nsw"
    ],
    "wof:name":"Crows Nest Preschool",
    "wof:placetype":"venue"
},
  "geometry": {"coordinates":[152.05174299999999,-27.263647],"type":"Point"}
}