{
  "type": "Feature",
  "properties": {
    "iso:country":"AU",
    "sg:address":"18 Lee Ave",
    "sg:city":"Jindabyne",
    "sg:classifiers":[
        {
            "category":"Food & Beverages",
            "subcategory":"Fruits & Vegetables",
            "type":"Retail Goods"
        }
    ],
    "sg:phone":"+61 2 6457 2224",
    "sg:postcode":"2627",
    "sg:province":"NSW",
    "sg:tags":[
        "wholesale"
    ],
    "wof:name":"Snowy Mountains Fresh Produce Pty Ltd",
    "wof:placetype":"venue"
},
  "geometry": {"coordinates":[148.60504150400001,-36.4357566833],"type":"Point"}
}