{
  "type": "Feature",
  "properties": {
    "addr:full":"Cnr White & Wentworth Rds Wonthaggi VIC 3995",
    "addr:postcode":"3995",
    "addr:street":"Cnr White &;Rds",
    "iso:country":"AU",
    "sg:address":"Cnr White & Wentworth Rds",
    "sg:city":"Wonthaggi",
    "sg:classifiers":[
        {
            "category":"Education",
            "subcategory":"School",
            "type":"Public Place"
        }
    ],
    "sg:phone":"+61 3 5672 4697",
    "sg:postcode":"3995",
    "sg:province":"VIC",
    "sg:tags":[
        "state",
        "except",
        "nsw"
    ],
    "wof:name":"Wonthaggi North Primary School",
    "wof:placetype":"venue"
},
  "geometry": {"coordinates":[145.59965500000001,-38.603649],"type":"Point"}
}