{
  "type": "Feature",
  "properties": {
    "addr:full":"2450 Albany Hwy Gosnells WA 6110",
    "addr:housenumber":"2450",
    "addr:postcode":"6110",
    "addr:street":"Albany Hwy",
    "iso:country":"AU",
    "sg:address":"2450 Albany Hwy",
    "sg:city":"Gosnells",
    "sg:classifiers":[
        {
            "category":"Autos & Motor Vehicles",
            "subcategory":"Fuel & Gas Station",
            "type":"Retail Goods"
        }
    ],
    "sg:phone":"+61 8 9398 2291",
    "sg:postcode":"6110",
    "sg:province":"WA",
    "wof:name":"Shell Seaforth",
    "wof:placetype":"venue"
},
  "geometry": {"coordinates":[115.998901367,-32.0676002502],"type":"Point"}
}