{
  "type": "Feature",
  "properties": {
    "iso:country":"AU",
    "sg:address":"419 Spencer St",
    "sg:city":"West Melbourne",
    "sg:classifiers":[
        {
            "category":"Restaurant",
            "type":"Food & Drink"
        }
    ],
    "sg:phone":"+61 3 9329 5712",
    "sg:postcode":"3003",
    "sg:province":"VIC",
    "sg:tags":[
        "theatre"
    ],
    "wof:name":"The Looney Bin Licenced Theatre Restaurant",
    "wof:placetype":"venue"
},
  "geometry": {"coordinates":[144.95013427699999,-37.8107185364],"type":"Point"}
}