{
  "type": "Feature",
  "properties": {
    "addr:full":"22 Nilson Ave Hillsdale NSW 2036",
    "addr:housenumber":"22",
    "addr:postcode":"2036",
    "addr:street":"Nilson Ave",
    "iso:country":"AU",
    "sg:address":"22 Nilson Ave",
    "sg:city":"Hillsdale",
    "sg:classifiers":[
        {
            "category":"Organizations",
            "subcategory":"Community Association",
            "type":"Services"
        }
    ],
    "sg:phone":"+61 2 9661 6942",
    "sg:postcode":"2036",
    "sg:province":"NSW",
    "sg:tags":[
        "organisation",
        "family",
        "welfare"
    ],
    "wof:name":"Maori Womens Welfare League",
    "wof:placetype":"venue"
},
  "geometry": {"coordinates":[151.22445678700001,-33.9534721375],"type":"Point"}
}