{
  "type": "Feature",
  "properties": {
    "iso:country":"AU",
    "sg:address":"centerway arcade shop 7 Queen St",
    "sg:city":"Bendigo",
    "sg:classifiers":[
        {
            "category":"Shopping",
            "subcategory":"Clothing, Apparel, & Fashions",
            "type":"Retail Goods"
        }
    ],
    "sg:phone":"+61 3 5443 0022",
    "sg:postcode":"3550",
    "sg:province":"VIC",
    "sg:tags":[
        "menswear"
    ],
    "wof:name":"Feisty",
    "wof:placetype":"venue"
},
  "geometry": {"coordinates":[144.281524658,-36.7606201172],"type":"Point"}
}