{
  "type": "Feature",
  "properties": {
    "iso:country":"AU",
    "sg:address":"PO Box 75",
    "sg:city":"Elwood",
    "sg:classifiers":[
        {
            "category":"Government",
            "subcategory":"Court House",
            "type":"Public Place"
        }
    ],
    "sg:phone":"+61 412 277 736",
    "sg:postcode":"3184",
    "sg:province":"VIC",
    "sg:tags":[
        "personal",
        "marriage",
        "family",
        "counselling"
    ],
    "wof:name":"Becher Judy",
    "wof:placetype":"venue"
},
  "geometry": {"coordinates":[144.98576355,-37.8810195923],"type":"Point"}
}