{
  "type": "Feature",
  "properties": {
    "addr:full":"103 Puckle St Moonee Ponds VIC 3039",
    "addr:housenumber":"103",
    "addr:postcode":"3039",
    "addr:street":"Puckle St",
    "iso:country":"AU",
    "sg:address":"103 Puckle St",
    "sg:city":"Moonee Ponds",
    "sg:classifiers":[
        {
            "category":"Cafe",
            "type":"Food & Drink"
        }
    ],
    "sg:phone":"+61 3 9370 0819",
    "sg:postcode":"3039",
    "sg:province":"VIC",
    "wof:name":"Tutto Deli",
    "wof:placetype":"venue"
},
  "geometry": {"coordinates":[144.921066,-37.766834],"type":"Point"}
}