{
  "type": "Feature",
  "properties": {
    "addr:full":"Unit 1 1 Hansen Crt West Lakes Shore SA 5020",
    "addr:housenumber":"1",
    "addr:postcode":"5020",
    "addr:street":"Hansen Crt",
    "iso:country":"AU",
    "sg:address":"Unit 1 1 Hansen Crt",
    "sg:city":"West Lakes Shore",
    "sg:classifiers":[
        {
            "category":"Building & Trades",
            "subcategory":"Construction",
            "type":"Services"
        }
    ],
    "sg:phone":"+61 401 335 910",
    "sg:postcode":"5020",
    "sg:province":"SA",
    "sg:tags":[
        "fencing",
        "contractor"
    ],
    "wof:name":"Waynes Fencing",
    "wof:placetype":"venue"
},
  "geometry": {"coordinates":[138.49400329599999,-34.8586158752],"type":"Point"}
}