{
  "type": "Feature",
  "properties": {
    "iso:country":"AU",
    "sg:address":"328 Grey St",
    "sg:city":"Glen Innes",
    "sg:classifiers":[
        {
            "category":"Professional",
            "subcategory":"Accounting & Tax Preparation",
            "type":"Services"
        }
    ],
    "sg:phone":"+61 2 6730 2900",
    "sg:postcode":"2370",
    "sg:province":"NSW",
    "sg:tags":[
        "accountant",
        "auditor"
    ],
    "wof:name":"Moore R",
    "wof:placetype":"venue"
},
  "geometry": {"coordinates":[151.73573303200001,-29.7366390228],"type":"Point"}
}