{
  "type": "Feature",
  "properties": {
    "addr:full":"501 Cross Keys Rd Cavan SA 5094",
    "addr:housenumber":"501",
    "addr:postcode":"5094",
    "addr:street":"Cross Keys Rd",
    "iso:country":"AU",
    "sg:address":"501 Cross Keys Rd",
    "sg:city":"Cavan",
    "sg:classifiers":[
        {
            "category":"Real Estate",
            "subcategory":"Real Estate Agent",
            "type":"Services"
        }
    ],
    "sg:phone":"+61 8 8262 6300",
    "sg:postcode":"5094",
    "sg:province":"SA",
    "sg:tags":[
        "handyman's",
        "equipment",
        "hire",
        "builders",
        "contractor"
    ],
    "wof:name":"Shorco Sykes Hire",
    "wof:placetype":"venue"
},
  "geometry": {"coordinates":[138.60038757300001,-34.8260536194],"type":"Point"}
}