{
  "type": "Feature",
  "properties": {
    "addr:full":"PO Box 8033 Mt Pritchard NSW 2170",
    "addr:postcode":"2170",
    "iso:country":"AU",
    "sg:address":"PO Box 8033",
    "sg:city":"Mt Pritchard",
    "sg:classifiers":[
        {
            "category":"Professional",
            "subcategory":"Advertising",
            "type":"Services"
        }
    ],
    "sg:phone":"+61 420 908 600",
    "sg:postcode":"2170",
    "sg:province":"NSW",
    "sg:tags":[
        "balloon",
        "novelty"
    ],
    "wof:name":"Inflatable Enterprises",
    "wof:placetype":"venue"
},
  "geometry": {"coordinates":[150.91192626899999,-33.9043617249],"type":"Point"}
}