{
  "type": "Feature",
  "properties": {
    "iso:country":"AU",
    "sg:address":"12 Dobra Rd",
    "sg:city":"Yangebup",
    "sg:phone":"+61 8 9418 4288",
    "sg:postcode":"6164",
    "sg:province":"WA",
    "wof:name":"Fibre Furn Tanks",
    "wof:placetype":"venue"
},
  "geometry": {"coordinates":[115.796288,-32.117016],"type":"Point"}
}