{
  "type": "Feature",
  "properties": {
    "iso:country":"AU",
    "sg:address":"2404 Logan Rd",
    "sg:city":"Eight Mile Plains",
    "sg:classifiers":[
        {
            "category":"Airport",
            "subcategory":"International",
            "type":"Transportation"
        }
    ],
    "sg:phone":"+61 7 3340 5192",
    "sg:postcode":"4113",
    "sg:province":"QLD",
    "sg:tags":[
        "diving",
        "commercial"
    ],
    "wof:name":"Ocean Marine Diving Contractors Pty Ltd",
    "wof:placetype":"venue"
},
  "geometry": {"coordinates":[153.091262817,-27.5732765198],"type":"Point"}
}