{
  "type": "Feature",
  "properties": {
    "addr:full":"377 Worongary Rd Tallai QLD 4213",
    "addr:housenumber":"377",
    "addr:postcode":"4213",
    "addr:street":"Worongary Rd",
    "iso:country":"AU",
    "sg:address":"377 Worongary Rd",
    "sg:city":"Tallai",
    "sg:classifiers":[
        {
            "category":"Professional",
            "subcategory":"Computer Services",
            "type":"Services"
        }
    ],
    "sg:phone":"+61 416 048 793",
    "sg:postcode":"4213",
    "sg:province":"QLD",
    "sg:tags":[
        "repairs",
        "upgrade",
        "equipment"
    ],
    "wof:name":"EDP Computing",
    "wof:placetype":"venue"
},
  "geometry": {"coordinates":[153.32083129899999,-28.0500106812],"type":"Point"}
}