{
  "type": "Feature",
  "properties": {
    "iso:country":"AU",
    "sg:address":"6-8 Berriman Drv",
    "sg:city":"Wangara",
    "sg:classifiers":[
        {
            "category":"Retail",
            "subcategory":"Auto Repair",
            "type":"Services"
        }
    ],
    "sg:phone":"+61 8 9409 9666",
    "sg:postcode":"6065",
    "sg:province":"WA",
    "sg:tags":[
        "repairer",
        "motor",
        "engineer"
    ],
    "wof:name":"Ford",
    "wof:placetype":"venue"
},
  "geometry": {"coordinates":[115.814781189,-31.7922534943],"type":"Point"}
}