{
  "type": "Feature",
  "properties": {
    "iso:country":"AU",
    "sg:address":"Ste 1204, Lvl 12, 227 Collins St",
    "sg:city":"Melbourne",
    "sg:classifiers":[
        {
            "category":"Recreation",
            "subcategory":"Sailing Club",
            "type":"Entertainment"
        }
    ],
    "sg:phone":"+61 3 9654 6695",
    "sg:postcode":"3000",
    "sg:province":"VIC",
    "sg:tags":[
        "merchant",
        "diamond"
    ],
    "wof:name":"Diamonco Australia Pty Ltd",
    "wof:placetype":"venue"
},
  "geometry": {"coordinates":[144.96644592300001,-37.8156509399],"type":"Point"}
}