{
  "type": "Feature",
  "properties": {
    "iso:country":"AU",
    "sg:address":"85b Avoca Drv",
    "sg:city":"Avoca Beach",
    "sg:classifiers":[
        {
            "category":"Fast Food",
            "type":"Food & Drink"
        }
    ],
    "sg:phone":"+61 2 4381 0600",
    "sg:postcode":"2251",
    "sg:province":"NSW",
    "sg:tags":[
        "away",
        "take"
    ],
    "wof:name":"Seafood Spot",
    "wof:placetype":"venue"
},
  "geometry": {"coordinates":[151.43568420400001,-33.4707603455],"type":"Point"}
}