{
  "type": "Feature",
  "properties": {
    "addr:full":"GPO Box 1896 Brisbane QLD 4001",
    "addr:postcode":"4001",
    "iso:country":"AU",
    "sg:address":"GPO Box 1896",
    "sg:city":"Brisbane",
    "sg:classifiers":[
        {
            "category":"Banks & Credit Unions",
            "subcategory":"Financial Services",
            "type":"Services"
        }
    ],
    "sg:phone":"+61 13 11 84",
    "sg:postcode":"4001",
    "sg:province":"QLD",
    "sg:tags":[
        "planning"
    ],
    "wof:name":"Sunsuper Financial Services",
    "wof:placetype":"venue"
},
  "geometry": {"coordinates":[152.88897705100001,-27.5976924896],"type":"Point"}
}