{
  "type": "Feature",
  "properties": {
    "addr:full":"Lvl 1, 63 Hay St Subiaco WA 6008",
    "addr:housenumber":"63",
    "addr:postcode":"6008",
    "addr:street":"Hay St",
    "iso:country":"AU",
    "sg:address":"Lvl 1, 63 Hay St",
    "sg:city":"Subiaco",
    "sg:classifiers":[
        {
            "category":"Professional",
            "subcategory":"Business Services",
            "type":"Services"
        }
    ],
    "sg:phone":"+61 8 6380 2555",
    "sg:postcode":"6008",
    "sg:province":"WA",
    "sg:tags":[
        "drafting"
    ],
    "wof:name":"Scribe Design Documentation Interiors",
    "wof:placetype":"venue"
},
  "geometry": {"coordinates":[115.835632324,-31.9472026825],"type":"Point"}
}