{
  "type": "Feature",
  "properties": {
    "iso:country":"AU",
    "sg:address":"PO Box 175",
    "sg:city":"Penola",
    "sg:classifiers":[
        {
            "category":"Manufacturing",
            "subcategory":"Furniture",
            "type":"Manufacturing & Wholesale Goods"
        }
    ],
    "sg:phone":"+61 8 8737 2095",
    "sg:postcode":"5277",
    "sg:province":"SA",
    "sg:tags":[
        "builder",
        "designer",
        "custom"
    ],
    "wof:name":"Krasni Park Redgum",
    "wof:placetype":"venue"
},
  "geometry": {"coordinates":[140.83673099999999,-37.377491],"type":"Point"}
}