{
  "type": "Feature",
  "properties": {
    "addr:full":"Halifax Rd Ingham QLD 4850",
    "addr:postcode":"4850",
    "addr:street":"Halifax Rd",
    "iso:country":"AU",
    "sg:address":"Halifax Rd",
    "sg:city":"Ingham",
    "sg:classifiers":[
        {
            "category":"Farming",
            "subcategory":"Crops",
            "type":"Manufacturing & Wholesale Goods"
        }
    ],
    "sg:phone":"+61 7 4776 2335",
    "sg:postcode":"4850",
    "sg:province":"QLD",
    "sg:tags":[
        "sugarcane",
        "mill",
        "grower"
    ],
    "wof:name":"Reinaudo Nelson & Vicki",
    "wof:placetype":"venue"
},
  "geometry": {"coordinates":[146.162185669,-18.6454849243],"type":"Point"}
}