{
  "type": "Feature",
  "properties": {
    "addr:full":"469 Mulgrave Rd Earlville QLD 4870",
    "addr:housenumber":"469",
    "addr:postcode":"4870",
    "addr:street":"Mulgrave Rd",
    "iso:country":"AU",
    "sg:address":"469 Mulgrave Rd",
    "sg:city":"Earlville",
    "sg:classifiers":[
        {
            "category":"Food & Beverages",
            "subcategory":"Bakery",
            "type":"Retail Goods"
        }
    ],
    "sg:phone":"+61 7 4033 1634",
    "sg:postcode":"4870",
    "sg:province":"QLD",
    "sg:tags":[
        "cake",
        "shop",
        "pastry"
    ],
    "wof:name":"Cairns Breadworks",
    "wof:placetype":"venue"
},
  "geometry": {"coordinates":[145.74148559599999,-16.9412689209],"type":"Point"}
}