{
  "type": "Feature",
  "properties": {
    "iso:country":"AU",
    "sg:address":"PO Box 266",
    "sg:city":"Canterbury",
    "sg:classifiers":[
        {
            "category":"Real Estate",
            "subcategory":"Architect",
            "type":"Services"
        }
    ],
    "sg:phone":"+61 3 9836 9743",
    "sg:postcode":"3126",
    "sg:province":"VIC",
    "sg:tags":[
        "building",
        "designer"
    ],
    "wof:name":"Robert Lawther Designs",
    "wof:placetype":"venue"
},
  "geometry": {"coordinates":[145.07310485799999,-37.8242492676],"type":"Point"}
}