{
  "type": "Feature",
  "properties": {
    "addr:full":"311/513- 519 Wattle St Ultimo NSW 2007",
    "addr:housenumber":"311 / 513 519",
    "addr:postcode":"2007",
    "addr:street":"Wattle St",
    "iso:country":"AU",
    "sg:address":"311/513- 519 Wattle St",
    "sg:city":"Ultimo",
    "sg:classifiers":[
        {
            "category":"Home & Garden",
            "subcategory":"Building Materials",
            "type":"Retail Goods"
        }
    ],
    "sg:phone":"+61 2 9211 3546",
    "sg:postcode":"2007",
    "sg:province":"NSW",
    "sg:tags":[
        "balustrading"
    ],
    "wof:name":"Platinum Glass Products",
    "wof:placetype":"venue"
},
  "geometry": {"coordinates":[151.1980896,-33.8835792542],"type":"Point"}
}