{
  "type": "Feature",
  "properties": {
    "addr:full":"Aspley Village Shopping Centre 3/591 Robinson Rd Aspley QLD 4034",
    "addr:housenumber":"3 / 591",
    "addr:postcode":"4034",
    "addr:street":"Robinson Rd",
    "iso:country":"AU",
    "sg:address":"Aspley Village Shopping Centre 3/591 Robinson Rd",
    "sg:city":"Aspley",
    "sg:classifiers":[
        {
            "category":"Health Services",
            "subcategory":"Health Practitioner",
            "type":"Services"
        }
    ],
    "sg:phone":"+61 7 3263 8121",
    "sg:postcode":"4034",
    "sg:province":"QLD",
    "sg:tags":[
        "acupuncture"
    ],
    "wof:name":"MacGinley Terry",
    "wof:placetype":"venue"
},
  "geometry": {"coordinates":[153.02499399999999,-27.364855],"type":"Point"}
}