{
  "type": "Feature",
  "properties": {
    "addr:full":"34 Francis St Port Adelaide SA 5015",
    "addr:housenumber":"34",
    "addr:postcode":"5015",
    "addr:street":"Francis St",
    "iso:country":"AU",
    "sg:address":"34 Francis St",
    "sg:city":"Port Adelaide",
    "sg:classifiers":[
        {
            "category":"Building & Trades",
            "subcategory":"Construction",
            "type":"Services"
        }
    ],
    "sg:phone":"+61 8 8447 5550",
    "sg:postcode":"5015",
    "sg:province":"SA",
    "sg:tags":[
        "scaffolding"
    ],
    "wof:name":"Waco Kwikform Limited",
    "wof:placetype":"venue"
},
  "geometry": {"coordinates":[138.517578125,-34.8402252197],"type":"Point"}
}