{
  "type": "Feature",
  "properties": {
    "addr:full":"450 Sheridan St Cairns North QLD 4870",
    "addr:housenumber":"450",
    "addr:postcode":"4870",
    "addr:street":"Sheridan St",
    "iso:country":"AU",
    "sg:address":"450 Sheridan St",
    "sg:city":"Cairns North",
    "sg:classifiers":[
        {
            "category":"Wholesale",
            "subcategory":"Furniture",
            "type":"Manufacturing & Wholesale Goods"
        }
    ],
    "sg:phone":"+61 7 4053 5255",
    "sg:postcode":"4870",
    "sg:province":"QLD",
    "sg:tags":[
        "wholesaler",
        "mfrs"
    ],
    "wof:name":"Pacific Outdoor Leisure Furniture",
    "wof:placetype":"venue"
},
  "geometry": {"coordinates":[145.75378418,-16.8939971924],"type":"Point"}
}