{
  "type": "Feature",
  "properties": {
    "iso:country":"AU",
    "sg:address":"136 William St",
    "sg:city":"Devonport",
    "sg:classifiers":[
        {
            "category":"Utilities",
            "subcategory":"Electric",
            "type":"Services"
        }
    ],
    "sg:phone":"+61 3 6423 3444",
    "sg:postcode":"7310",
    "sg:province":"TAS",
    "sg:tags":[
        "electrical",
        "contractor"
    ],
    "wof:name":"Shane Hill Electrical P/L",
    "wof:placetype":"venue"
},
  "geometry": {"coordinates":[146.351074219,-41.1772422791],"type":"Point"}
}