{
  "type": "Feature",
  "properties": {
    "addr:full":"Bayside Shopping Centre, G 82, Beach St Frankston VIC 3199",
    "addr:housenumber":"82",
    "addr:postcode":"3199",
    "addr:street":"Beach St",
    "iso:country":"AU",
    "sg:address":"Bayside Shopping Centre, G 82, Beach St",
    "sg:city":"Frankston",
    "sg:classifiers":[
        {
            "category":"Banks & Credit Unions",
            "subcategory":"Bureau De Change",
            "type":"Services"
        }
    ],
    "sg:phone":"+61 3 9781 4355",
    "sg:postcode":"3199",
    "sg:province":"VIC",
    "sg:tags":[
        "repairs",
        "part",
        "appliance",
        "electrical"
    ],
    "wof:name":"Shaver Shop",
    "wof:placetype":"venue"
},
  "geometry": {"coordinates":[145.135665894,-38.1624717712],"type":"Point"}
}