{
  "type": "Feature",
  "properties": {
    "addr:full":"59- 61 Inghan Rd Townsville QLD 4810",
    "addr:housenumber":"61",
    "addr:postcode":"4810",
    "addr:street":"Inghan Rd",
    "iso:country":"AU",
    "sg:address":"59- 61 Inghan Rd",
    "sg:city":"Townsville",
    "sg:classifiers":[
        {
            "category":"Retail",
            "subcategory":"Auto Repair",
            "type":"Services"
        }
    ],
    "sg:phone":"+61 7 4772 2267",
    "sg:postcode":"4810",
    "sg:province":"QLD",
    "sg:tags":[
        "automotive",
        "air conditioning"
    ],
    "wof:name":"Cooldrive Distribution",
    "wof:placetype":"venue"
},
  "geometry": {"coordinates":[146.80081200000001,-19.268166],"type":"Point"}
}