{
  "type": "Feature",
  "properties": {
    "iso:country":"AU",
    "sg:address":"Unit 1 / 9 Stanley St",
    "sg:city":"Peakhurst",
    "sg:classifiers":[
        {
            "category":"Manufacturing",
            "subcategory":"Motor Vehicles & Parts",
            "type":"Manufacturing & Wholesale Goods"
        }
    ],
    "sg:phone":"+61 2 9584 3877",
    "sg:postcode":"2210",
    "sg:province":"NSW",
    "sg:tags":[
        "replacement"
    ],
    "wof:name":"Go Parts",
    "wof:placetype":"venue"
},
  "geometry": {"coordinates":[151.06514,-33.961697],"type":"Point"}
}