{
  "type": "Feature",
  "properties": {
    "addr:full":"68 King William St Kent Town SA 5067",
    "addr:housenumber":"68",
    "addr:postcode":"5067",
    "addr:street":"King William St",
    "iso:country":"AU",
    "sg:address":"68 King William St",
    "sg:city":"Kent Town",
    "sg:classifiers":[
        {
            "category":"Professional",
            "subcategory":"Art Services",
            "type":"Services"
        }
    ],
    "sg:phone":"+61 8 8363 9920",
    "sg:postcode":"5067",
    "sg:province":"SA",
    "sg:tags":[
        "interior",
        "decorator"
    ],
    "wof:name":"Taylormade Interiors",
    "wof:placetype":"venue"
},
  "geometry": {"coordinates":[138.61935424800001,-34.9188575745],"type":"Point"}
}