{
  "type": "Feature",
  "properties": {
    "iso:country":"AU",
    "sg:address":"157- 161 Woodlands Drv",
    "sg:city":"Braeside",
    "sg:classifiers":[
        {
            "category":"Shopping",
            "subcategory":"Stationery & Office Supplies",
            "type":"Retail Goods"
        }
    ],
    "sg:phone":"+61 3 9588 0055",
    "sg:postcode":"3195",
    "sg:province":"VIC",
    "sg:tags":[
        "packaging",
        "material"
    ],
    "wof:name":"HR Rolls Packaging Pty Ltd",
    "wof:placetype":"venue"
},
  "geometry": {"coordinates":[145.11880493199999,-38.0004959106],"type":"Point"}
}