{
  "type": "Feature",
  "properties": {
    "iso:country":"AU",
    "sg:address":"Clarks Hill Rd",
    "sg:city":"Dean",
    "sg:classifiers":[
        {
            "category":"Farming",
            "subcategory":"Farm",
            "type":"Manufacturing & Wholesale Goods"
        }
    ],
    "sg:phone":"+61 3 5334 5253",
    "sg:postcode":"3352",
    "sg:province":"VIC",
    "sg:tags":[
        "farmer"
    ],
    "wof:name":"Guthrie K",
    "wof:placetype":"venue"
},
  "geometry": {"coordinates":[143.936279,-37.483776],"type":"Point"}
}