{
  "type": "Feature",
  "properties": {
    "addr:full":"238 Upper Heidelberg Rd Ivanhoe VIC 3079",
    "addr:housenumber":"238",
    "addr:postcode":"3079",
    "addr:street":"Upper Heidelberg Rd",
    "iso:country":"AU",
    "sg:address":"238 Upper Heidelberg Rd",
    "sg:city":"Ivanhoe",
    "sg:classifiers":[
        {
            "category":"Restaurant",
            "type":"Food & Drink"
        }
    ],
    "sg:phone":"+61 3 9497 1084",
    "sg:postcode":"3079",
    "sg:province":"VIC",
    "wof:name":"Cafe Saffron",
    "wof:placetype":"venue"
},
  "geometry": {"coordinates":[145.04563903799999,-37.7663803101],"type":"Point"}
}