{
  "type": "Feature",
  "properties": {
    "iso:country":"AU",
    "sg:address":"West Sands Centre,Ground Floor 44 Parliament Pl",
    "sg:city":"West Perth",
    "sg:classifiers":[
        {
            "category":"Health Services",
            "subcategory":"Doctor",
            "type":"Services"
        }
    ],
    "sg:phone":"+61 8 9321 1110",
    "sg:postcode":"6005",
    "sg:province":"WA",
    "sg:tags":[
        "medical",
        "practitioner"
    ],
    "wof:name":"Hair & Skin International",
    "wof:placetype":"venue"
},
  "geometry": {"coordinates":[115.846458435,-31.9512119293],"type":"Point"}
}