{
  "type": "Feature",
  "properties": {
    "iso:country":"AU",
    "sg:address":"410 Somerville Rd",
    "sg:city":"West Footscray",
    "sg:classifiers":[
        {
            "category":"Food & Beverages",
            "subcategory":"Fruits & Vegetables",
            "type":"Retail Goods"
        }
    ],
    "sg:phone":"+61 3 9314 9200",
    "sg:postcode":"3012",
    "sg:province":"VIC",
    "sg:tags":[
        "wholesale"
    ],
    "wof:name":"Tasty Chips Pty Ltd",
    "wof:placetype":"venue"
},
  "geometry": {"coordinates":[144.86062622099999,-37.8100776672],"type":"Point"}
}