{
  "type": "Feature",
  "properties": {
    "addr:full":"PO Box 443 Cherrybrook NSW 2126",
    "addr:postcode":"2126",
    "iso:country":"AU",
    "sg:address":"PO Box 443",
    "sg:city":"Cherrybrook",
    "sg:classifiers":[
        {
            "category":"Home & Garden",
            "subcategory":"Carpets & Floor Coverings",
            "type":"Retail Goods"
        }
    ],
    "sg:phone":"+61 1300 138 126",
    "sg:postcode":"2126",
    "sg:province":"NSW",
    "sg:tags":[
        "tile",
        "wall"
    ],
    "wof:name":"Warmtech Pty Ltd",
    "wof:placetype":"venue"
},
  "geometry": {"coordinates":[151.04136657699999,-33.7210006714],"type":"Point"}
}