{
  "type": "Feature",
  "properties": {
    "addr:full":"459 Pumicestone Rd Caboolture QLD 4510",
    "addr:housenumber":"459",
    "addr:postcode":"4510",
    "addr:street":"Pumicestone Rd",
    "iso:country":"AU",
    "sg:address":"459 Pumicestone Rd",
    "sg:city":"Caboolture",
    "sg:classifiers":[
        {
            "category":"Fast Food",
            "type":"Food & Drink"
        }
    ],
    "sg:phone":"+61 7 5428 3364",
    "sg:postcode":"4510",
    "sg:province":"QLD",
    "sg:tags":[
        "away",
        "take"
    ],
    "wof:name":"Humble Pie Co. Caboolture",
    "wof:placetype":"venue"
},
  "geometry": {"coordinates":[152.960342,-27.054665],"type":"Point"}
}