{
  "type": "Feature",
  "properties": {
    "addr:full":"Shop 174a Pacific Fair QLD 4218",
    "addr:housenumber":"174a",
    "addr:postcode":"4218",
    "addr:street":"Pacific Fair",
    "iso:country":"AU",
    "sg:address":"Shop 174a",
    "sg:city":"Pacific Fair",
    "sg:classifiers":[
        {
            "category":"Shopping",
            "subcategory":"Optical Goods",
            "type":"Retail Goods"
        }
    ],
    "sg:phone":"+61 7 5527 5561",
    "sg:postcode":"4218",
    "sg:province":"QLD",
    "sg:tags":[
        "dispenser",
        "prescription"
    ],
    "wof:name":"Axis Optical",
    "wof:placetype":"venue"
},
  "geometry": {"coordinates":[153.42666625999999,-28.0378303528],"type":"Point"}
}