{
  "type": "Feature",
  "properties": {
    "iso:country":"AU",
    "sg:address":"PO Box 53",
    "sg:city":"Landsborough",
    "sg:classifiers":[
        {
            "category":"Military Area",
            "subcategory":"Army Base",
            "type":"Public Place"
        }
    ],
    "sg:phone":"+61 7 5494 1921",
    "sg:postcode":"4550",
    "sg:province":"QLD",
    "sg:tags":[
        "concrete",
        "slab",
        "floor"
    ],
    "wof:name":"BA Owens Concreting",
    "wof:placetype":"venue"
},
  "geometry": {"coordinates":[152.96539306599999,-26.8091907501],"type":"Point"}
}