{
  "type": "Feature",
  "properties": {
    "iso:country":"AU",
    "sg:address":"182 Fulham Rd",
    "sg:city":"Gulliver",
    "sg:classifiers":[
        {
            "category":"Health Services",
            "subcategory":"Health Practitioner",
            "type":"Services"
        }
    ],
    "sg:phone":"+61 7 4775 5755",
    "sg:postcode":"4812",
    "sg:province":"QLD",
    "sg:tags":[
        "osteopath"
    ],
    "wof:name":"Finn Haylee",
    "wof:placetype":"venue"
},
  "geometry": {"coordinates":[146.769806,-19.288845],"type":"Point"}
}