{
  "type": "Feature",
  "properties": {
    "addr:full":"47- 49 Benowa Rd Southport QLD 4215",
    "addr:housenumber":"49",
    "addr:postcode":"4215",
    "addr:street":"Benowa Rd",
    "iso:country":"AU",
    "sg:address":"47- 49 Benowa Rd",
    "sg:city":"Southport",
    "sg:classifiers":[
        {
            "category":"Social Services",
            "subcategory":"Child Care",
            "type":"Services"
        }
    ],
    "sg:phone":"+61 7 5532 8788",
    "sg:postcode":"4215",
    "sg:province":"QLD",
    "wof:name":"Merryland Gardens Child Care & Learning Centre",
    "wof:placetype":"venue"
},
  "geometry": {"coordinates":[153.40507507300001,-27.9874305725],"type":"Point"}
}