{
  "type": "Feature",
  "properties": {
    "addr:full":"153 Marion Rd Richmond SA 5033",
    "addr:housenumber":"153",
    "addr:postcode":"5033",
    "addr:street":"Marion Rd",
    "iso:country":"AU",
    "sg:address":"153 Marion Rd",
    "sg:city":"Richmond",
    "sg:classifiers":[
        {
            "category":"Retail",
            "subcategory":"Auto Rental",
            "type":"Services"
        }
    ],
    "sg:phone":"+61 8 8152 0303",
    "sg:postcode":"5033",
    "sg:province":"SA",
    "sg:tags":[
        "car",
        "hire",
        "minibus"
    ],
    "wof:name":"Ace Rent A Car",
    "wof:placetype":"venue"
},
  "geometry": {"coordinates":[138.55311584500001,-34.9384651184],"type":"Point"}
}