{
  "type": "Feature",
  "properties": {
    "addr:full":"71- 75 Margaret St Launceston TAS 7250",
    "addr:housenumber":"75",
    "addr:postcode":"7250",
    "addr:street":"Margaret St",
    "iso:country":"AU",
    "sg:address":"71- 75 Margaret St",
    "sg:city":"Launceston",
    "sg:classifiers":[
        {
            "category":"Banks & Credit Unions",
            "subcategory":"Investment Brokerage",
            "type":"Services"
        }
    ],
    "sg:phone":"+61 3 6331 5114",
    "sg:postcode":"7250",
    "sg:province":"TAS",
    "sg:tags":[
        "equipment",
        "spray",
        "painting",
        "supply"
    ],
    "wof:name":"Spectrum Car Paints",
    "wof:placetype":"venue"
},
  "geometry": {"coordinates":[147.13865661599999,-41.4420700073],"type":"Point"}
}