{
  "type": "Feature",
  "properties": {
    "iso:country":"AU",
    "sg:address":"18 Carrington St",
    "sg:city":"Randwick",
    "sg:classifiers":[
        {
            "category":"Communications",
            "subcategory":"Film & Video Production",
            "type":"Services"
        }
    ],
    "sg:phone":"+61 2 9398 5509",
    "sg:postcode":"2031",
    "sg:province":"NSW",
    "sg:tags":[
        "dvd",
        "library"
    ],
    "wof:name":"Home Pics Video",
    "wof:placetype":"venue"
},
  "geometry": {"coordinates":[151.25253295900001,-33.9047241211],"type":"Point"}
}