{
  "type": "Feature",
  "properties": {
    "addr:full":"Old Bunbury Rd Coolup WA 6214",
    "addr:postcode":"6214",
    "addr:street":"Bunbury Rd",
    "iso:country":"AU",
    "sg:address":"Old Bunbury Rd",
    "sg:city":"Coolup",
    "sg:classifiers":[
        {
            "category":"Farming",
            "subcategory":"Farm",
            "type":"Manufacturing & Wholesale Goods"
        }
    ],
    "sg:phone":"+61 8 9530 3279",
    "sg:postcode":"6214",
    "sg:province":"WA",
    "sg:tags":[
        "farmer"
    ],
    "wof:name":"Richter G A & S L E",
    "wof:placetype":"venue"
},
  "geometry": {"coordinates":[115.831383,-32.714928],"type":"Point"}
}