{
  "type": "Feature",
  "properties": {
    "iso:country":"AU",
    "sg:address":"Raglan St",
    "sg:city":"Roma",
    "sg:classifiers":[
        {
            "category":"Home & Garden",
            "subcategory":"Building Materials",
            "type":"Retail Goods"
        }
    ],
    "sg:phone":"+61 7 4622 2733",
    "sg:postcode":"4455",
    "sg:province":"QLD",
    "sg:tags":[
        "pre-mixed",
        "concrete"
    ],
    "wof:name":"Hanson",
    "wof:placetype":"venue"
},
  "geometry": {"coordinates":[148.78468322800001,-26.5810146332],"type":"Point"}
}