{
  "type": "Feature",
  "properties": {
    "addr:full":"191 Botany Rd Alexandria NSW 2015",
    "addr:housenumber":"191",
    "addr:postcode":"2015",
    "addr:street":"Botany Rd",
    "iso:country":"AU",
    "sg:address":"191 Botany Rd",
    "sg:city":"Alexandria",
    "sg:classifiers":[
        {
            "category":"Government",
            "subcategory":"Customs House",
            "type":"Public Place"
        }
    ],
    "sg:phone":"+61 2 8303 2000",
    "sg:postcode":"2015",
    "sg:province":"NSW",
    "sg:tags":[
        "title",
        "management",
        "stratum"
    ],
    "sg:website":"http://www.strataassociates.com.au",
    "wof:name":"Strata Associates Pty Ltd",
    "wof:placetype":"venue"
},
  "geometry": {"coordinates":[151.20150756800001,-33.9018173218],"type":"Point"}
}