{
  "type": "Feature",
  "properties": {
    "addr:full":"58a Bogalara Rd Old Toongabbie NSW 2146",
    "addr:housenumber":"58a",
    "addr:postcode":"2146",
    "addr:street":"Bogalara Rd",
    "iso:country":"AU",
    "sg:address":"58a Bogalara Rd",
    "sg:city":"Old Toongabbie",
    "sg:classifiers":[
        {
            "category":"Food & Beverages",
            "subcategory":"Groceries & Convenience Stores",
            "type":"Retail Goods"
        }
    ],
    "sg:phone":"+61 2 9896 0407",
    "sg:postcode":"2146",
    "sg:province":"NSW",
    "wof:name":"Pips Pantry",
    "wof:placetype":"venue"
},
  "geometry": {"coordinates":[150.96871948200001,-33.7936401367],"type":"Point"}
}