{
  "type": "Feature",
  "properties": {
    "addr:full":"19 Gill St Charters Towers QLD 4820",
    "addr:housenumber":"19",
    "addr:postcode":"4820",
    "addr:street":"Gill St",
    "iso:country":"AU",
    "sg:address":"19 Gill St",
    "sg:city":"Charters Towers",
    "sg:classifiers":[
        {
            "category":"Banks & Credit Unions",
            "subcategory":"Bank",
            "type":"Services"
        }
    ],
    "sg:phone":"+61 13 20 32",
    "sg:postcode":"4820",
    "sg:province":"QLD",
    "wof:name":"Westpac",
    "wof:placetype":"venue"
},
  "geometry": {"coordinates":[146.257904,-20.075939],"type":"Point"}
}