{
  "type": "Feature",
  "properties": {
    "iso:country":"AU",
    "sg:address":"Nowland Ave",
    "sg:city":"Quirindi",
    "sg:classifiers":[
        {
            "category":"Education",
            "subcategory":"School",
            "type":"Public Place"
        }
    ],
    "sg:phone":"+61 2 6746 1565",
    "sg:postcode":"2343",
    "sg:province":"NSW",
    "sg:tags":[
        "state",
        "-",
        "nsw"
    ],
    "wof:name":"Quirindi Primary School",
    "wof:placetype":"venue"
},
  "geometry": {"coordinates":[150.679977417,-31.4999523163],"type":"Point"}
}