{
  "type": "Feature",
  "properties": {
    "addr:full":"37 Nicholson Ave St Ives NSW 2075",
    "addr:housenumber":"37",
    "addr:postcode":"2075",
    "addr:street":"Nicholson Ave",
    "iso:country":"AU",
    "sg:address":"37 Nicholson Ave St",
    "sg:city":"Ives",
    "sg:classifiers":[
        {
            "category":"Education",
            "subcategory":"Special Training",
            "type":"Public Place"
        }
    ],
    "sg:phone":"+61 2 9144 2390",
    "sg:postcode":"2075",
    "sg:province":"NSW",
    "sg:tags":[
        "tuition-educational"
    ],
    "wof:name":"Three K Project",
    "wof:placetype":"venue"
},
  "geometry": {"coordinates":[151.17347717300001,-33.7492675781],"type":"Point"}
}