{
  "type": "Feature",
  "properties": {
    "addr:full":"3 Kathleen St Lurnea NSW 2170",
    "addr:housenumber":"3",
    "addr:postcode":"2170",
    "addr:street":"Kathleen St",
    "iso:country":"AU",
    "sg:address":"3 Kathleen St",
    "sg:city":"Lurnea",
    "sg:classifiers":[
        {
            "category":"Professional",
            "subcategory":"Business Services",
            "type":"Services"
        }
    ],
    "sg:phone":"+61 412 247 829",
    "sg:postcode":"2170",
    "sg:province":"NSW",
    "sg:tags":[
        "drafting"
    ],
    "wof:name":"Elmir Design & Drafting Services",
    "wof:placetype":"venue"
},
  "geometry": {"coordinates":[150.894622803,-33.9369049072],"type":"Point"}
}