{
  "type": "Feature",
  "properties": {
    "addr:full":"155 Martin St Gardenvale VIC 3185",
    "addr:housenumber":"155",
    "addr:postcode":"3185",
    "addr:street":"Martin St",
    "iso:country":"AU",
    "sg:address":"155 Martin St",
    "sg:city":"Gardenvale",
    "sg:classifiers":[
        {
            "category":"Fast Food",
            "type":"Food & Drink"
        }
    ],
    "sg:phone":"+61 3 9596 6714",
    "sg:postcode":"3185",
    "sg:province":"VIC",
    "sg:tags":[
        "away",
        "take"
    ],
    "wof:name":"Yummy Sticks",
    "wof:placetype":"venue"
},
  "geometry": {"coordinates":[145.00387573200001,-37.8972358704],"type":"Point"}
}