{
  "type": "Feature",
  "properties": {
    "addr:full":"PO Box 376 Burnside SA 5066",
    "addr:postcode":"5066",
    "iso:country":"AU",
    "sg:address":"PO Box 376",
    "sg:city":"Burnside",
    "sg:classifiers":[
        {
            "category":"Building & Trades",
            "subcategory":"Cleaning & Sanitation",
            "type":"Services"
        }
    ],
    "sg:phone":"+61 411 625 606",
    "sg:postcode":"5066",
    "sg:province":"SA",
    "sg:tags":[
        "industrial",
        "commercial",
        "contractor"
    ],
    "wof:name":"Fusspot Cleaning",
    "wof:placetype":"venue"
},
  "geometry": {"coordinates":[138.65997314399999,-34.9359016418],"type":"Point"}
}