{
  "type": "Feature",
  "properties": {
    "addr:full":"630 Mooroduc Hwy Mornington VIC 3931",
    "addr:housenumber":"630",
    "addr:postcode":"3931",
    "addr:street":"Mooroduc Hwy",
    "iso:country":"AU",
    "sg:address":"630 Mooroduc Hwy",
    "sg:city":"Mornington",
    "sg:classifiers":[
        {
            "category":"Farming",
            "subcategory":"Nursery",
            "type":"Manufacturing & Wholesale Goods"
        }
    ],
    "sg:phone":"+61 405 411 522",
    "sg:postcode":"3931",
    "sg:province":"VIC",
    "wof:name":"Farmers Advanced Trees",
    "wof:placetype":"venue"
},
  "geometry": {"coordinates":[145.097381592,-38.2262229919],"type":"Point"}
}