{
  "type": "Feature",
  "properties": {
    "iso:country":"AU",
    "sg:address":"17 Moores Rd",
    "sg:city":"Monbulk",
    "sg:classifiers":[
        {
            "category":"Social Services",
            "subcategory":"Child Care",
            "type":"Services"
        }
    ],
    "sg:phone":"+61 3 9756 6459",
    "sg:postcode":"3793",
    "sg:province":"VIC",
    "wof:name":"Monbulk Childcare Centre",
    "wof:placetype":"venue"
},
  "geometry": {"coordinates":[145.410842895,-37.8733940125],"type":"Point"}
}