{
  "type": "Feature",
  "properties": {
    "iso:country":"AU",
    "sg:address":"60 Kings Cross Rd",
    "sg:city":"Potts Point",
    "sg:classifiers":[
        {
            "category":"Cafe",
            "type":"Food & Drink"
        }
    ],
    "sg:phone":"+61 2 9331 2343",
    "sg:postcode":"2011",
    "sg:province":"NSW",
    "wof:name":"Cafe Hernandez",
    "wof:placetype":"venue"
},
  "geometry": {"coordinates":[151.22564697300001,-33.8759841919],"type":"Point"}
}