{
  "type": "Feature",
  "properties": {
    "addr:full":"16 Wood St South Geelong VIC 3220",
    "addr:housenumber":"16",
    "addr:postcode":"3220",
    "addr:street":"Wood St",
    "iso:country":"AU",
    "sg:address":"16 Wood St",
    "sg:city":"South Geelong",
    "sg:classifiers":[
        {
            "category":"Wholesale",
            "subcategory":"Metals & Minerals",
            "type":"Manufacturing & Wholesale Goods"
        }
    ],
    "sg:phone":"+61 3 5222 3733",
    "sg:postcode":"3220",
    "sg:province":"VIC",
    "sg:tags":[
        "steel",
        "stainless",
        "product",
        "equipment"
    ],
    "wof:name":"Nicro Engineering",
    "wof:placetype":"venue"
},
  "geometry": {"coordinates":[144.368774,-38.168575],"type":"Point"}
}