{
  "type": "Feature",
  "properties": {
    "addr:full":"97- 101 Poole St Welshpool WA 6106",
    "addr:housenumber":"101",
    "addr:postcode":"6106",
    "addr:street":"97;Poole St",
    "iso:country":"AU",
    "sg:address":"97- 101 Poole St",
    "sg:city":"Welshpool",
    "sg:classifiers":[
        {
            "category":"Bars & Pubs",
            "subcategory":"Sports Bar",
            "type":"Food & Drink"
        }
    ],
    "sg:phone":"+61 8 9351 9463",
    "sg:postcode":"6106",
    "sg:province":"WA",
    "sg:tags":[
        "rolling",
        "forming",
        "metal"
    ],
    "wof:name":"Pedco Engineering",
    "wof:placetype":"venue"
},
  "geometry": {"coordinates":[115.945549011,-31.9936084747],"type":"Point"}
}