{
  "type": "Feature",
  "properties": {
    "addr:full":"Waratah St Gunning NSW 2581",
    "addr:postcode":"2581",
    "addr:street":"Waratah St",
    "iso:country":"AU",
    "sg:address":"Waratah St",
    "sg:city":"Gunning",
    "sg:classifiers":[
        {
            "category":"Social Services",
            "subcategory":"Child Care",
            "type":"Services"
        }
    ],
    "sg:phone":"+61 2 4845 1126",
    "sg:postcode":"2581",
    "sg:province":"NSW",
    "sg:tags":[
        "support",
        "health"
    ],
    "wof:name":"Early Childhood Centres",
    "wof:placetype":"venue"
},
  "geometry": {"coordinates":[149.26678466800001,-34.7826805115],"type":"Point"}
}