{
  "type": "Feature",
  "properties": {
    "iso:country":"AU",
    "sg:address":"PO Box 1916",
    "sg:city":"West Perth",
    "sg:classifiers":[
        {
            "category":"Manufacturing",
            "subcategory":"Glass & Minerals",
            "type":"Manufacturing & Wholesale Goods"
        }
    ],
    "sg:phone":"+61 8 9211 5777",
    "sg:postcode":"6872",
    "sg:province":"WA",
    "sg:tags":[
        "exploration"
    ],
    "wof:name":"Jackson Gold Limited",
    "wof:placetype":"venue"
},
  "geometry": {"coordinates":[115.843826,-31.95055],"type":"Point"}
}