{
  "type": "Feature",
  "properties": {
    "iso:country":"AU",
    "sg:address":"22 Tillinga St",
    "sg:city":"Balcatta",
    "sg:classifiers":[
        {
            "category":"Transit Center",
            "subcategory":"Freight",
            "type":"Transportation"
        }
    ],
    "sg:phone":"+61 412 984 259",
    "sg:postcode":"6021",
    "sg:province":"WA",
    "sg:tags":[
        "forklift",
        "truck"
    ],
    "wof:name":"CNA Forklifts",
    "wof:placetype":"venue"
},
  "geometry": {"coordinates":[115.827438355,-31.8717708588],"type":"Point"}
}