{
  "type": "Feature",
  "properties": {
    "iso:country":"AU",
    "sg:address":"PO Box 345",
    "sg:city":"Roseville",
    "sg:classifiers":[
        {
            "category":"Retail",
            "subcategory":"Veterinary Services",
            "type":"Services"
        }
    ],
    "sg:phone":"+61 2 9411 3848",
    "sg:postcode":"2069",
    "sg:province":"NSW",
    "sg:tags":[
        "surgeon"
    ],
    "wof:name":"Ark Veterinarian",
    "wof:placetype":"venue"
},
  "geometry": {"coordinates":[151.17579650900001,-33.7836799622],"type":"Point"}
}