{
  "type": "Feature",
  "properties": {
    "addr:full":"175 Sydney Rd Brunswick VIC 3056",
    "addr:housenumber":"175",
    "addr:postcode":"3056",
    "addr:street":"Sydney Rd",
    "iso:country":"AU",
    "sg:address":"175 Sydney Rd",
    "sg:city":"Brunswick",
    "sg:classifiers":[
        {
            "category":"Professional",
            "subcategory":"Employment Agencies",
            "type":"Services"
        }
    ],
    "sg:phone":"+61 3 9388 0044",
    "sg:postcode":"3056",
    "sg:province":"VIC",
    "wof:name":"Job Co/Job Futures",
    "wof:placetype":"venue"
},
  "geometry": {"coordinates":[144.96095275900001,-37.7730255127],"type":"Point"}
}