{
  "type": "Feature",
  "properties": {
    "addr:full":"Shp 8 16-18 Church St Morwell VIC 3840",
    "addr:housenumber":"8 16-18",
    "addr:postcode":"3840",
    "addr:street":"Church St",
    "iso:country":"AU",
    "sg:address":"Shp 8 16-18 Church St",
    "sg:city":"Morwell",
    "sg:classifiers":[
        {
            "category":"Personal",
            "subcategory":"Beauty Salon",
            "type":"Services"
        }
    ],
    "sg:phone":"+61 3 5134 4888",
    "sg:postcode":"3840",
    "sg:province":"VIC",
    "sg:tags":[
        "hairdresser"
    ],
    "wof:name":"Shellbeez Hair Relm",
    "wof:placetype":"venue"
},
  "geometry": {"coordinates":[146.39921569800001,-38.2360115051],"type":"Point"}
}