{
  "type": "Feature",
  "properties": {
    "iso:country":"AU",
    "sg:address":"23 High St",
    "sg:city":"Epping",
    "sg:classifiers":[
        {
            "category":"Insurance",
            "subcategory":"Insurance Agent",
            "type":"Services"
        }
    ],
    "sg:phone":"+61 412 678 144",
    "sg:postcode":"3076",
    "sg:province":"VIC",
    "wof:name":"The Coverdale Group",
    "wof:placetype":"venue"
},
  "geometry": {"coordinates":[145.011886597,-37.6907310486],"type":"Point"}
}