{
  "type": "Feature",
  "properties": {
    "addr:full":"4 Stanton Rd Seven Hills NSW 2147",
    "addr:housenumber":"4",
    "addr:postcode":"2147",
    "addr:street":"Stanton Rd",
    "iso:country":"AU",
    "sg:address":"4 Stanton Rd",
    "sg:city":"Seven Hills",
    "sg:classifiers":[
        {
            "category":"Education",
            "subcategory":"Special Training",
            "type":"Public Place"
        }
    ],
    "sg:phone":"+61 1300 130 666",
    "sg:postcode":"2147",
    "sg:province":"NSW",
    "sg:tags":[
        "development"
    ],
    "wof:name":"Lennox Institute",
    "wof:placetype":"venue"
},
  "geometry": {"coordinates":[150.94943237300001,-33.7690353394],"type":"Point"}
}