{
  "type": "Feature",
  "properties": {
    "addr:full":"27B Burlington St Crows Nest NSW 2065",
    "addr:housenumber":"27b",
    "addr:postcode":"2065",
    "addr:street":"Burlington St",
    "iso:country":"AU",
    "sg:address":"27B Burlington St",
    "sg:city":"Crows Nest",
    "sg:classifiers":[
        {
            "category":"Professional",
            "subcategory":"Art Services",
            "type":"Services"
        }
    ],
    "sg:phone":"+61 2 9439 8860",
    "sg:postcode":"2065",
    "sg:province":"NSW",
    "sg:tags":[
        "graphic",
        "designer"
    ],
    "wof:name":"McPherson Ian Studio Pty Ltd",
    "wof:placetype":"venue"
},
  "geometry": {"coordinates":[151.20274352999999,-33.8270568848],"type":"Point"}
}