{
  "type": "Feature",
  "properties": {
    "iso:country":"AU",
    "sg:address":"Mill Rd",
    "sg:city":"Smithton",
    "sg:classifiers":[
        {
            "category":"Education",
            "subcategory":"School",
            "type":"Public Place"
        }
    ],
    "sg:phone":"+61 3 6452 1376",
    "sg:postcode":"7330",
    "sg:province":"TAS",
    "sg:tags":[
        "state",
        "except",
        "nsw"
    ],
    "wof:name":"Smithton High School",
    "wof:placetype":"venue"
},
  "geometry": {"coordinates":[145.11738600000001,-40.839001],"type":"Point"}
}