{
  "type": "Feature",
  "properties": {
    "iso:country":"AU",
    "sg:address":"12 Noolinga Rd",
    "sg:city":"Bayview",
    "sg:classifiers":[
        {
            "category":"Health Services",
            "subcategory":"Doctor",
            "type":"Services"
        }
    ],
    "sg:phone":"+61 2 9940 2088",
    "sg:postcode":"2104",
    "sg:province":"NSW",
    "sg:tags":[
        "reflexology"
    ],
    "wof:name":"Christine Eagle",
    "wof:placetype":"venue"
},
  "geometry": {"coordinates":[151.291977,-33.655491],"type":"Point"}
}