{
  "type": "Feature",
  "properties": {
    "addr:full":"4/ 95 Dorset Rd Ferntree Gully VIC 3156",
    "addr:housenumber":"/ 95",
    "addr:postcode":"3156",
    "addr:street":"Dorset Rd",
    "iso:country":"AU",
    "sg:address":"4/ 95 Dorset Rd",
    "sg:city":"Ferntree Gully",
    "sg:classifiers":[
        {
            "category":"Professional",
            "type":"Services"
        }
    ],
    "sg:phone":"+61 3 9755 6168",
    "sg:postcode":"3156",
    "sg:province":"VIC",
    "sg:tags":[
        "spray",
        "painting"
    ],
    "wof:name":"Glass Flex",
    "wof:placetype":"venue"
},
  "geometry": {"coordinates":[145.28480529800001,-37.8744049072],"type":"Point"}
}