{
  "type": "Feature",
  "properties": {
    "addr:full":"Maryvale Rd Morwell VIC 3840",
    "addr:postcode":"3840",
    "addr:street":"Maryvale Rd",
    "iso:country":"AU",
    "sg:address":"Maryvale Rd",
    "sg:city":"Morwell",
    "sg:classifiers":[
        {
            "category":"Farming",
            "subcategory":"Poultry Farm",
            "type":"Manufacturing & Wholesale Goods"
        }
    ],
    "sg:phone":"+61 3 5134 4335",
    "sg:postcode":"3840",
    "sg:province":"VIC",
    "sg:tags":[
        "farmer"
    ],
    "wof:name":"Lyndale Poultry Farm",
    "wof:placetype":"venue"
},
  "geometry": {"coordinates":[146.40957641599999,-38.2302513123],"type":"Point"}
}