{
  "type": "Feature",
  "properties": {
    "iso:country":"AU",
    "sg:address":"188 Commercial Rd",
    "sg:city":"Prahran",
    "sg:classifiers":[
        {
            "category":"Travel",
            "subcategory":"Travel Agent",
            "type":"Entertainment"
        }
    ],
    "sg:phone":"+61 3 9533 6166",
    "sg:postcode":"3181",
    "sg:province":"VIC",
    "sg:tags":[
        "consultant"
    ],
    "wof:name":"Jetset",
    "wof:placetype":"venue"
},
  "geometry": {"coordinates":[144.99205017099999,-37.846698761],"type":"Point"}
}