{
  "type": "Feature",
  "properties": {
    "iso:country":"AU",
    "sg:address":"62 Whiting St",
    "sg:city":"Artarmon",
    "sg:classifiers":[
        {
            "category":"Real Estate",
            "subcategory":"Real Estate Agent",
            "type":"Services"
        }
    ],
    "sg:phone":"+61 2 9310 3100",
    "sg:postcode":"2064",
    "sg:province":"NSW",
    "sg:tags":[
        "handyman's",
        "equipment",
        "hire",
        "builders",
        "contractor"
    ],
    "wof:name":"Active Hire Group",
    "wof:placetype":"venue"
},
  "geometry": {"coordinates":[151.181442261,-33.8162612915],"type":"Point"}
}