{
  "type": "Feature",
  "properties": {
    "addr:full":"28 Dellar Drv Bibra Lake WA 6163",
    "addr:housenumber":"28",
    "addr:postcode":"6163",
    "addr:street":"Dellar Drv",
    "iso:country":"AU",
    "sg:address":"28 Dellar Drv",
    "sg:city":"Bibra Lake",
    "sg:classifiers":[
        {
            "category":"Home & Garden",
            "subcategory":"Household Appliances",
            "type":"Retail Goods"
        }
    ],
    "sg:phone":"+61 8 9418 8717",
    "sg:postcode":"6163",
    "sg:province":"WA",
    "sg:tags":[
        "equipment",
        "gas"
    ],
    "wof:name":"Hollands George & E",
    "wof:placetype":"venue"
},
  "geometry": {"coordinates":[115.803162,-32.090984],"type":"Point"}
}