{
  "type": "Feature",
  "properties": {
    "addr:full":"253 Torrens Rd West Croydon SA 5008",
    "addr:housenumber":"253",
    "addr:postcode":"5008",
    "addr:street":"Torrens Rd",
    "iso:country":"AU",
    "sg:address":"253 Torrens Rd",
    "sg:city":"West Croydon",
    "sg:classifiers":[
        {
            "category":"Education",
            "subcategory":"School",
            "type":"Public Place"
        }
    ],
    "sg:phone":"+61 8 8340 3733",
    "sg:postcode":"5008",
    "sg:province":"SA",
    "sg:tags":[
        "state",
        "except",
        "nsw"
    ],
    "wof:name":"Adelaide Secondary School Of English",
    "wof:placetype":"venue"
},
  "geometry": {"coordinates":[138.56579600000001,-34.885841],"type":"Point"}
}