{
  "type": "Feature",
  "properties": {
    "addr:full":"26 Julian Rocks Drv Byron Bay NSW 2481",
    "addr:housenumber":"26",
    "addr:postcode":"2481",
    "addr:street":"Julian Rocks Drv",
    "iso:country":"AU",
    "sg:address":"26 Julian Rocks Drv",
    "sg:city":"Byron Bay",
    "sg:classifiers":[
        {
            "category":"Personal",
            "subcategory":"Beauty Salon",
            "type":"Services"
        }
    ],
    "sg:phone":"+61 411 479 914",
    "sg:postcode":"2481",
    "sg:province":"NSW",
    "sg:tags":[
        "supply",
        "artist",
        "make-up"
    ],
    "wof:name":"Pout",
    "wof:placetype":"venue"
},
  "geometry": {"coordinates":[153.5859375,-28.6320495605],"type":"Point"}
}