{
  "type": "Feature",
  "properties": {
    "addr:full":"4/ 1 Mornington-Tyabb Rd Mornington VIC 3931",
    "addr:housenumber":"/ 1",
    "addr:postcode":"3931",
    "addr:street":"Mornington-Tyabb Rd",
    "iso:country":"AU",
    "sg:address":"4/ 1 Mornington-Tyabb Rd",
    "sg:city":"Mornington",
    "sg:classifiers":[
        {
            "category":"Shopping",
            "subcategory":"Music",
            "type":"Retail Goods"
        }
    ],
    "sg:phone":"+61 3 5975 0293",
    "sg:postcode":"3931",
    "sg:province":"VIC",
    "sg:tags":[
        "instrument",
        "musical"
    ],
    "wof:name":"Nepean Music Centre",
    "wof:placetype":"venue"
},
  "geometry": {"coordinates":[145.04573059099999,-38.2306060791],"type":"Point"}
}