{
  "type": "Feature",
  "properties": {
    "addr:full":"46 St Albans St Abbotsford NSW 2046",
    "addr:housenumber":"46",
    "addr:postcode":"2046",
    "addr:street":"St",
    "iso:country":"AU",
    "sg:address":"46 St Albans St",
    "sg:city":"Abbotsford",
    "sg:classifiers":[
        {
            "category":"Building & Trades",
            "subcategory":"Cleaning & Sanitation",
            "type":"Services"
        }
    ],
    "sg:phone":"+61 2 9712 7327",
    "sg:postcode":"2046",
    "sg:province":"NSW",
    "sg:tags":[
        "window"
    ],
    "wof:name":"Draper C B",
    "wof:placetype":"venue"
},
  "geometry": {"coordinates":[151.12690699999999,-33.850658],"type":"Point"}
}