{
  "type": "Feature",
  "properties": {
    "addr:full":"159 Ingham Rd West End QLD 4810",
    "addr:housenumber":"159",
    "addr:postcode":"4810",
    "addr:street":"Ingham Rd",
    "iso:country":"AU",
    "sg:address":"159 Ingham Rd",
    "sg:city":"West End",
    "sg:classifiers":[
        {
            "category":"Food & Beverages",
            "subcategory":"Meat & Fish",
            "type":"Retail Goods"
        }
    ],
    "sg:phone":"+61 7 4721 1464",
    "sg:postcode":"4810",
    "sg:province":"QLD",
    "sg:tags":[
        "seafood"
    ],
    "wof:name":"Ingham Road Seafood",
    "wof:placetype":"venue"
},
  "geometry": {"coordinates":[146.79129,-19.267138],"type":"Point"}
}