{
  "type": "Feature",
  "properties": {
    "iso:country":"AU",
    "sg:address":"Factory 2 23 Runway Drv",
    "sg:city":"Mudjimba",
    "sg:classifiers":[
        {
            "category":"Manufacturing",
            "subcategory":"Aerospace",
            "type":"Manufacturing & Wholesale Goods"
        }
    ],
    "sg:phone":"+61 7 5448 9737",
    "sg:postcode":"4564",
    "sg:province":"QLD",
    "sg:tags":[
        "equipment",
        "aircraft",
        "maintenance"
    ],
    "wof:name":"Integral Component Overhaul",
    "wof:placetype":"venue"
},
  "geometry": {"coordinates":[153.085037231,-26.6083717346],"type":"Point"}
}