{
  "type": "Feature",
  "properties": {
    "iso:country":"AU",
    "sg:address":"Shed 1/ 17 Brewer St",
    "sg:city":"Clontarf",
    "sg:classifiers":[
        {
            "category":"Retail",
            "subcategory":"Car Wash",
            "type":"Services"
        }
    ],
    "sg:phone":"+61 7 3883 2080",
    "sg:postcode":"4019",
    "sg:province":"QLD",
    "sg:tags":[
        "truck",
        "cleaning"
    ],
    "wof:name":"Clean Image The Car Cleaning Co",
    "wof:placetype":"venue"
},
  "geometry": {"coordinates":[153.08291625999999,-27.2394638062],"type":"Point"}
}