{
  "type": "Feature",
  "properties": {
    "addr:full":"13 Gate St Kootingal NSW 2352",
    "addr:housenumber":"13",
    "addr:postcode":"2352",
    "addr:street":"Gate St",
    "iso:country":"AU",
    "sg:address":"13 Gate St",
    "sg:city":"Kootingal",
    "sg:classifiers":[
        {
            "category":"Real Estate",
            "subcategory":"Developer",
            "type":"Services"
        }
    ],
    "sg:phone":"+61 2 6760 3755",
    "sg:postcode":"2352",
    "sg:province":"NSW",
    "sg:tags":[
        "development"
    ],
    "wof:name":"Kootingal Real Estate",
    "wof:placetype":"venue"
},
  "geometry": {"coordinates":[151.05413818400001,-31.0574493408],"type":"Point"}
}