{
  "type": "Feature",
  "properties": {
    "addr:full":"158 Gill St Charters Towers QLD 4820",
    "addr:housenumber":"158",
    "addr:postcode":"4820",
    "addr:street":"Gill St",
    "iso:country":"AU",
    "sg:address":"158 Gill St",
    "sg:city":"Charters Towers",
    "sg:classifiers":[
        {
            "category":"Shopping",
            "type":"Retail Goods"
        }
    ],
    "sg:phone":"+61 7 4787 4000",
    "sg:postcode":"4820",
    "sg:province":"QLD",
    "sg:tags":[
        "agent",
        "stock"
    ],
    "wof:name":"Geaneys",
    "wof:placetype":"venue"
},
  "geometry": {"coordinates":[146.26182600000001,-20.076729],"type":"Point"}
}