{
  "type": "Feature",
  "properties": {
    "addr:full":"20 Pioneer Rd Corrimal NSW 2518",
    "addr:housenumber":"20",
    "addr:postcode":"2518",
    "addr:street":"Pioneer Rd",
    "iso:country":"AU",
    "sg:address":"20 Pioneer Rd",
    "sg:city":"Corrimal",
    "sg:classifiers":[
        {
            "category":"Social Services",
            "subcategory":"Child Care",
            "type":"Services"
        }
    ],
    "sg:phone":"+61 2 4285 8170",
    "sg:postcode":"2518",
    "sg:province":"NSW",
    "wof:name":"Pioneer Rd Long Day Care Centre",
    "wof:placetype":"venue"
},
  "geometry": {"coordinates":[150.90997300000001,-34.369282],"type":"Point"}
}