{
  "type": "Feature",
  "properties": {
    "addr:full":"Suite 17 Buderim Central 17 Lindsay Rd Buderim QLD 4556",
    "addr:housenumber":"17",
    "addr:postcode":"4556",
    "addr:street":"Lindsay Rd",
    "iso:country":"AU",
    "sg:address":"Suite 17 Buderim Central 17 Lindsay Rd",
    "sg:city":"Buderim",
    "sg:classifiers":[
        {
            "category":"Health Services",
            "subcategory":"Health Practitioner",
            "type":"Services"
        }
    ],
    "sg:phone":"+61 7 5476 8835",
    "sg:postcode":"4556",
    "sg:province":"QLD",
    "sg:tags":[
        "naturopath"
    ],
    "wof:name":"Buderim Clinic of Herbal Medicine",
    "wof:placetype":"venue"
},
  "geometry": {"coordinates":[153.050323486,-26.6843261719],"type":"Point"}
}