{
  "type": "Feature",
  "properties": {
    "iso:country":"AU",
    "sg:address":"14 Kalulu Rd",
    "sg:city":"Belgrave",
    "sg:classifiers":[
        {
            "category":"Professional",
            "subcategory":"Art Services",
            "type":"Services"
        }
    ],
    "sg:phone":"+61 3 9754 2423",
    "sg:postcode":"3160",
    "sg:province":"VIC",
    "sg:tags":[
        "graphic",
        "designer"
    ],
    "wof:name":"Kenneday Graham",
    "wof:placetype":"venue"
},
  "geometry": {"coordinates":[145.34971618599999,-37.9053993225],"type":"Point"}
}