{
  "type": "Feature",
  "properties": {
    "iso:country":"AU",
    "sg:address":"200 Cordeaux Rd",
    "sg:city":"Mt Kembla",
    "sg:classifiers":[
        {
            "category":"Shopping",
            "subcategory":"Antiques",
            "type":"Retail Goods"
        }
    ],
    "sg:phone":"+61 2 4271 2883",
    "sg:postcode":"2526",
    "sg:province":"NSW",
    "wof:name":"Mt Kembla Collectables & Old Wares",
    "wof:placetype":"venue"
},
  "geometry": {"coordinates":[150.828216553,-34.430809021],"type":"Point"}
}