{
  "type": "Feature",
  "properties": {
    "iso:country":"AU",
    "sg:address":"344 Findon Rd",
    "sg:city":"Kidman Park",
    "sg:classifiers":[
        {
            "category":"Wholesale",
            "subcategory":"Stationery",
            "type":"Manufacturing & Wholesale Goods"
        }
    ],
    "sg:phone":"+61 1800 624 521",
    "sg:postcode":"5025",
    "sg:province":"SA",
    "sg:tags":[
        "mfrg"
    ],
    "wof:name":"Esselte Australia Pty Ltd",
    "wof:placetype":"venue"
},
  "geometry": {"coordinates":[138.533294678,-34.9099617004],"type":"Point"}
}