{
  "type": "Feature",
  "properties": {
    "addr:full":"Blk 373 Red Cliffs VIC 3496",
    "addr:housenumber":"373",
    "addr:postcode":"3496",
    "iso:country":"AU",
    "sg:address":"Blk 373",
    "sg:city":"Red Cliffs",
    "sg:classifiers":[
        {
            "category":"Farming",
            "subcategory":"Berry Farm",
            "type":"Manufacturing & Wholesale Goods"
        }
    ],
    "sg:phone":"+61 3 5024 1748",
    "sg:postcode":"3496",
    "sg:province":"VIC",
    "sg:tags":[
        "fruit",
        "grower"
    ],
    "wof:name":"Sergi D & T",
    "wof:placetype":"venue"
},
  "geometry": {"coordinates":[142.18652343799999,-34.3077087402],"type":"Point"}
}