{
  "type": "Feature",
  "properties": {
    "addr:full":"17 Smith Rd Goodna QLD 4300",
    "addr:housenumber":"17",
    "addr:postcode":"4300",
    "addr:street":"Smith Rd",
    "iso:country":"AU",
    "sg:address":"17 Smith Rd",
    "sg:city":"Goodna",
    "sg:classifiers":[
        {
            "category":"Autos & Motor Vehicles",
            "subcategory":"Auto Supplies",
            "type":"Retail Goods"
        }
    ],
    "sg:phone":"+61 7 3818 0855",
    "sg:postcode":"4300",
    "sg:province":"QLD",
    "sg:tags":[
        "tyre"
    ],
    "wof:name":"Waynes Tyre & Mechanical",
    "wof:placetype":"venue"
},
  "geometry": {"coordinates":[152.87266540499999,-27.5925197601],"type":"Point"}
}