{
  "type": "Feature",
  "properties": {
    "iso:country":"AU",
    "sg:address":"126 Darby St",
    "sg:city":"Cooks Hill",
    "sg:classifiers":[
        {
            "category":"Fast Food",
            "type":"Food & Drink"
        }
    ],
    "sg:phone":"+61 2 4929 4394",
    "sg:postcode":"2300",
    "sg:province":"NSW",
    "sg:tags":[
        "away",
        "take"
    ],
    "wof:name":"Oasis Kebabs & Takeaways",
    "wof:placetype":"venue"
},
  "geometry": {"coordinates":[151.771286,-32.931694],"type":"Point"}
}