{
  "type": "Feature",
  "properties": {
    "addr:full":"1a/24 Carnarvon St (Cnr Silverwater Rd) Silverwater NSW 2128",
    "addr:housenumber":"1a / 24",
    "addr:postcode":"2128",
    "addr:street":"Carnarvon St Cnr Silverwater Rd",
    "iso:country":"AU",
    "sg:address":"1a/24 Carnarvon St (Cnr Silverwater Rd)",
    "sg:city":"Silverwater",
    "sg:classifiers":[
        {
            "category":"Professional",
            "subcategory":"Printing & Photocopies",
            "type":"Services"
        }
    ],
    "sg:phone":"+61 2 9648 5844",
    "sg:postcode":"2128",
    "sg:province":"NSW",
    "sg:tags":[
        "photocopying"
    ],
    "wof:name":"Kopy Kolor",
    "wof:placetype":"venue"
},
  "geometry": {"coordinates":[151.04554748499999,-33.8397407532],"type":"Point"}
}