{
  "type": "Feature",
  "properties": {
    "addr:full":"Yaamba Rd Rockhampton QLD 4700",
    "addr:postcode":"4700",
    "addr:street":"Yaamba Rd",
    "iso:country":"AU",
    "sg:address":"Yaamba Rd",
    "sg:city":"Rockhampton",
    "sg:classifiers":[
        {
            "category":"Insurance",
            "subcategory":"Hazard Insurance",
            "type":"Services"
        }
    ],
    "sg:phone":"+61 13 11 75",
    "sg:postcode":"4700",
    "sg:province":"QLD",
    "sg:tags":[
        "fire",
        "accident",
        "marine"
    ],
    "wof:name":"Suncorp",
    "wof:placetype":"venue"
},
  "geometry": {"coordinates":[150.52415466299999,-23.3513832092],"type":"Point"}
}