{
  "type": "Feature",
  "properties": {
    "iso:country":"AU",
    "sg:address":"10 Gladstone St",
    "sg:city":"Gladstone",
    "sg:classifiers":[
        {
            "category":"Social Services",
            "type":"Services"
        }
    ],
    "sg:phone":"+61 8 8662 2622",
    "sg:postcode":"5473",
    "sg:province":"SA",
    "sg:tags":[
        "kinesiology"
    ],
    "wof:name":"White Lilly Centre For Health & Harmony",
    "wof:placetype":"venue"
},
  "geometry": {"coordinates":[138.356598,-33.267441],"type":"Point"}
}