{
  "type": "Feature",
  "properties": {
    "addr:full":"Seventh Rd York WA 6302",
    "addr:postcode":"6302",
    "addr:street":"Seventh Rd",
    "iso:country":"AU",
    "sg:address":"Seventh Rd",
    "sg:city":"York",
    "sg:classifiers":[
        {
            "category":"Arena",
            "subcategory":"Sports Club",
            "type":"Entertainment"
        }
    ],
    "sg:phone":"+61 8 9641 1131",
    "sg:postcode":"6302",
    "sg:province":"WA",
    "sg:tags":[
        "hunt",
        "racing"
    ],
    "wof:name":"York Beverley Turf Club",
    "wof:placetype":"venue"
},
  "geometry": {"coordinates":[116.768379211,-31.8880996704],"type":"Point"}
}