{
  "type": "Feature",
  "properties": {
    "addr:full":"PO Box 422 Southport QLD 4215",
    "addr:postcode":"4215",
    "iso:country":"AU",
    "sg:address":"PO Box 422",
    "sg:city":"Southport",
    "sg:classifiers":[
        {
            "category":"Organizations",
            "subcategory":"Professional Association",
            "type":"Services"
        }
    ],
    "sg:phone":"+61 7 5532 4544",
    "sg:postcode":"4215",
    "sg:province":"QLD",
    "sg:tags":[
        "organisation",
        "business"
    ],
    "wof:name":"Southport Chamber Of Commerce & Industry Inc.",
    "wof:placetype":"venue"
},
  "geometry": {"coordinates":[153.415618897,-27.9665660858],"type":"Point"}
}