{
  "type": "Feature",
  "properties": {
    "addr:full":"283 Alfred St North Sydney NSW 2060",
    "addr:housenumber":"283",
    "addr:postcode":"2060",
    "addr:street":"Alfred St",
    "iso:country":"AU",
    "sg:address":"283 Alfred St",
    "sg:city":"North Sydney",
    "sg:classifiers":[
        {
            "category":"Banks & Credit Unions",
            "subcategory":"Investment Brokerage",
            "type":"Services"
        }
    ],
    "sg:phone":"+61 2 9955 7506",
    "sg:postcode":"2060",
    "sg:province":"NSW",
    "wof:name":"Family Financial Centre",
    "wof:placetype":"venue"
},
  "geometry": {"coordinates":[151.21136474599999,-33.8400726318],"type":"Point"}
}