{
  "type": "Feature",
  "properties": {
    "iso:country":"AU",
    "sg:address":"44 Sunshine Pde",
    "sg:city":"Miami",
    "sg:classifiers":[
        {
            "category":"Real Estate",
            "subcategory":"Architect",
            "type":"Services"
        }
    ],
    "sg:phone":"+61 7 5576 2108",
    "sg:postcode":"4220",
    "sg:province":"QLD",
    "sg:tags":[
        "building",
        "designer"
    ],
    "wof:name":"Hooker John",
    "wof:placetype":"venue"
},
  "geometry": {"coordinates":[153.442962647,-28.0729866028],"type":"Point"}
}