{
  "type": "Feature",
  "properties": {
    "addr:full":"80 Corunna Rd Stanmore NSW 2048",
    "addr:housenumber":"80",
    "addr:postcode":"2048",
    "addr:street":"Corunna Rd",
    "iso:country":"AU",
    "sg:address":"80 Corunna Rd",
    "sg:city":"Stanmore",
    "sg:classifiers":[
        {
            "category":"Health Services",
            "subcategory":"Health Practitioner",
            "type":"Services"
        }
    ],
    "sg:phone":"+61 2 9569 5337",
    "sg:postcode":"2048",
    "sg:province":"NSW",
    "sg:tags":[
        "psychologist"
    ],
    "wof:name":"Donaldson Sandra E",
    "wof:placetype":"venue"
},
  "geometry": {"coordinates":[151.16679400000001,-33.888779],"type":"Point"}
}