{
  "type": "Feature",
  "properties": {
    "iso:country":"AU",
    "sg:address":"56 Raleigh Rd",
    "sg:city":"Milperra",
    "sg:classifiers":[
        {
            "category":"Retail",
            "subcategory":"Driving School",
            "type":"Services"
        }
    ],
    "sg:phone":"+61 2 9774 2063",
    "sg:postcode":"2214",
    "sg:province":"NSW",
    "wof:name":"Keith Safe Driver Training",
    "wof:placetype":"venue"
},
  "geometry": {"coordinates":[150.97569300000001,-33.937935],"type":"Point"}
}