{
  "type": "Feature",
  "properties": {
    "iso:country":"AU",
    "sg:address":"46 Theobald St",
    "sg:city":"Thornbury",
    "sg:classifiers":[
        {
            "category":"Wholesale",
            "subcategory":"Painting Supplies",
            "type":"Manufacturing & Wholesale Goods"
        }
    ],
    "sg:phone":"+61 3 9480 0636",
    "sg:postcode":"3071",
    "sg:province":"VIC",
    "sg:tags":[
        "product",
        "cleaning"
    ],
    "wof:name":"Technichem Pty Ltd",
    "wof:placetype":"venue"
},
  "geometry": {"coordinates":[145.029693603,-37.7564468384],"type":"Point"}
}