{
  "type": "Feature",
  "properties": {
    "addr:full":"Shopng Cntr 38 May Gibbs Cl Richardson ACT 2905",
    "addr:housenumber":"38",
    "addr:postcode":"2905",
    "addr:street":"May Gibbs Cl",
    "iso:country":"AU",
    "sg:address":"Shopng Cntr 38",
    "sg:city":"May Gibbs Cl Richardson",
    "sg:classifiers":[
        {
            "category":"Health Services",
            "subcategory":"Doctor",
            "type":"Services"
        }
    ],
    "sg:phone":"+61 2 6291 7950",
    "sg:postcode":"2905",
    "sg:province":"ACT",
    "sg:tags":[
        "medical",
        "practitioner"
    ],
    "wof:name":"Stevenson N F",
    "wof:placetype":"venue"
},
  "geometry": {"coordinates":[149.20866394000001,-35.3902397156],"type":"Point"}
}