{
  "type": "Feature",
  "properties": {
    "addr:full":"263 Hay St Subiaco WA 6008",
    "addr:housenumber":"263",
    "addr:postcode":"6008",
    "addr:street":"Hay St",
    "iso:country":"AU",
    "sg:address":"263 Hay St",
    "sg:city":"Subiaco",
    "sg:classifiers":[
        {
            "category":"Personal",
            "type":"Services"
        }
    ],
    "sg:phone":"+61 8 9388 8844",
    "sg:postcode":"6008",
    "sg:province":"WA",
    "sg:tags":[
        "gift"
    ],
    "sg:website":"http://www.stannesflorist.com.au",
    "wof:name":"St Annes Florist and Gift Baskets",
    "wof:placetype":"venue"
},
  "geometry": {"coordinates":[115.829650879,-31.9471702576],"type":"Point"}
}