{
  "type": "Feature",
  "properties": {
    "addr:full":"Glenrowan Rd Denmark WA 6333",
    "addr:postcode":"6333",
    "addr:street":"Glenrowan Rd",
    "iso:country":"AU",
    "sg:address":"Glenrowan Rd",
    "sg:city":"Denmark",
    "sg:classifiers":[
        {
            "category":"Farming",
            "subcategory":"Vineyard",
            "type":"Manufacturing & Wholesale Goods"
        }
    ],
    "sg:phone":"+61 8 9840 9218",
    "sg:postcode":"6333",
    "sg:province":"WA",
    "sg:tags":[
        "winery"
    ],
    "wof:name":"Tingle-Wood Wines",
    "wof:placetype":"venue"
},
  "geometry": {"coordinates":[117.32148742699999,-34.9503555298],"type":"Point"}
}