{
  "type": "Feature",
  "properties": {
    "addr:full":"7/ 15 Rogilla Cl Maryland NSW 2287",
    "addr:housenumber":"/ 15",
    "addr:postcode":"2287",
    "addr:street":"Rogilla Cl",
    "iso:country":"AU",
    "sg:address":"7/ 15 Rogilla Cl",
    "sg:city":"Maryland",
    "sg:classifiers":[
        {
            "category":"Retail",
            "subcategory":"Auto Repair",
            "type":"Services"
        }
    ],
    "sg:phone":"+61 2 4950 1155",
    "sg:postcode":"2287",
    "sg:province":"NSW",
    "sg:tags":[
        "electrical"
    ],
    "wof:name":"Frames Auto Electrics",
    "wof:placetype":"venue"
},
  "geometry": {"coordinates":[151.66252136200001,-32.8816184998],"type":"Point"}
}