{
  "type": "Feature",
  "properties": {
    "iso:country":"AU",
    "sg:address":"22 Fairscene Crs",
    "sg:city":"Avoca Beach",
    "sg:classifiers":[
        {
            "category":"Real Estate",
            "subcategory":"Architect",
            "type":"Services"
        }
    ],
    "sg:phone":"+61 2 4382 2604",
    "sg:postcode":"2251",
    "sg:province":"NSW",
    "sg:tags":[
        "building",
        "designer"
    ],
    "wof:name":"Ledell McHugh Building Design",
    "wof:placetype":"venue"
},
  "geometry": {"coordinates":[151.43377685600001,-33.4669303894],"type":"Point"}
}