{
  "type": "Feature",
  "properties": {
    "iso:country":"AU",
    "sg:address":"114 Fitzmaurice St",
    "sg:city":"Wagga Wagga",
    "sg:classifiers":[
        {
            "category":"Arena",
            "subcategory":"Sports Club",
            "type":"Entertainment"
        }
    ],
    "sg:phone":"+61 2 6921 6244",
    "sg:postcode":"2650",
    "sg:province":"NSW",
    "sg:tags":[
        "hunt",
        "racing"
    ],
    "wof:name":"Southern District Racing Association",
    "wof:placetype":"venue"
},
  "geometry": {"coordinates":[147.369049072,-35.1046981812],"type":"Point"}
}