{
  "type": "Feature",
  "properties": {
    "addr:full":"92 Central St Labrador QLD 4215",
    "addr:housenumber":"92",
    "addr:postcode":"4215",
    "addr:street":"Central St",
    "iso:country":"AU",
    "sg:address":"92 Central St",
    "sg:city":"Labrador",
    "sg:classifiers":[
        {
            "category":"Recreation",
            "type":"Entertainment"
        }
    ],
    "sg:phone":"+61 412 514 022",
    "sg:postcode":"4215",
    "sg:province":"QLD",
    "sg:tags":[
        "recreational",
        "diver"
    ],
    "wof:name":"Atlantis Scuba Academy",
    "wof:placetype":"venue"
},
  "geometry": {"coordinates":[153.40135192899999,-27.9484500885],"type":"Point"}
}