{
  "type": "Feature",
  "properties": {
    "addr:full":"Shop 4, Parker Arcade, 474 High St Penrith NSW 2750",
    "addr:housenumber":"shop 4;474",
    "addr:postcode":"2750",
    "addr:street":"Parker Arcade;High St",
    "iso:country":"AU",
    "sg:address":"Shop 4, Parker Arcade, 474 High St",
    "sg:city":"Penrith",
    "sg:classifiers":[
        {
            "category":"Shopping",
            "subcategory":"Jewelry",
            "type":"Retail Goods"
        }
    ],
    "sg:phone":"+61 2 4732 3464",
    "sg:postcode":"2750",
    "sg:province":"NSW",
    "sg:tags":[
        "jeweller"
    ],
    "wof:name":"Gem-Mart Jewellers",
    "wof:placetype":"venue"
},
  "geometry": {"coordinates":[150.915557861,-33.8949661255],"type":"Point"}
}