{
  "type": "Feature",
  "properties": {
    "addr:full":"T207 Erina Fair, 620-658 Terrigal Drv Erina NSW 2250",
    "addr:postcode":"620-658;2250",
    "addr:street":"Terrigal Drv",
    "iso:country":"AU",
    "sg:address":"T207 Erina Fair, 620-658 Terrigal Drv",
    "sg:city":"Erina",
    "sg:classifiers":[
        {
            "category":"Transit Center",
            "subcategory":"Passenger",
            "type":"Transportation"
        }
    ],
    "sg:phone":"+61 2 4365 6351",
    "sg:postcode":"2250",
    "sg:province":"NSW",
    "sg:tags":[
        "retail",
        "toiletry",
        "perfume"
    ],
    "wof:name":"Luxury Perfumes",
    "wof:placetype":"venue"
},
  "geometry": {"coordinates":[151.347412109,-33.4256591797],"type":"Point"}
}