{
  "type": "Feature",
  "properties": {
    "iso:country":"AU",
    "sg:address":"95 Grandview St",
    "sg:city":"Pymble",
    "sg:classifiers":[
        {
            "category":"Personal",
            "subcategory":"Skin Care",
            "type":"Services"
        }
    ],
    "sg:phone":"+61 2 9144 6434",
    "sg:postcode":"2073",
    "sg:province":"NSW",
    "sg:tags":[
        "treatment"
    ],
    "wof:name":"Skin Vision",
    "wof:placetype":"venue"
},
  "geometry": {"coordinates":[151.141723633,-33.7442321777],"type":"Point"}
}