{
  "type": "Feature",
  "properties": {
    "iso:country":"AU",
    "sg:address":"West Tamar Rd",
    "sg:city":"Riverside",
    "sg:classifiers":[
        {
            "category":"Education",
            "subcategory":"School",
            "type":"Public Place"
        }
    ],
    "sg:phone":"+61 3 6327 3969",
    "sg:postcode":"7250",
    "sg:province":"TAS",
    "sg:tags":[
        "state",
        "except",
        "nsw"
    ],
    "wof:name":"Riverside High School",
    "wof:placetype":"venue"
},
  "geometry": {"coordinates":[147.09283447300001,-41.4066352844],"type":"Point"}
}