{
  "type": "Feature",
  "properties": {
    "addr:full":"94 Queen Victoria St Fremantle WA 6160",
    "addr:housenumber":"94",
    "addr:postcode":"6160",
    "addr:street":"Queen Victoria St",
    "iso:country":"AU",
    "sg:address":"94 Queen Victoria St",
    "sg:city":"Fremantle",
    "sg:classifiers":[
        {
            "category":"Autos & Motor Vehicles",
            "subcategory":"Automobile Sales",
            "type":"Retail Goods"
        }
    ],
    "sg:phone":"+61 8 9335 6035",
    "sg:postcode":"6160",
    "sg:province":"WA",
    "sg:tags":[
        "car",
        "used"
    ],
    "wof:name":"Fremantle City Auto Wholesale",
    "wof:placetype":"venue"
},
  "geometry": {"coordinates":[115.750793,-32.048019],"type":"Point"}
}