{
  "type": "Feature",
  "properties": {
    "addr:full":"Shop 5 Dorset Arcade 260 Dorset Rd Boronia VIC 3155",
    "addr:housenumber":"shop 5;260",
    "addr:postcode":"3155",
    "addr:street":"Dorset Arcade;Dorset Rd",
    "iso:country":"AU",
    "sg:address":"Shop 5 Dorset Arcade 260 Dorset Rd",
    "sg:city":"Boronia",
    "sg:classifiers":[
        {
            "category":"Health Services",
            "subcategory":"Podiatrist",
            "type":"Services"
        }
    ],
    "sg:phone":"+61 3 9762 7033",
    "sg:postcode":"3155",
    "sg:province":"VIC",
    "sg:tags":[
        "cap",
        "hat",
        "renovation",
        "retail"
    ],
    "wof:name":"Wool N' Bull Boronia",
    "wof:placetype":"venue"
},
  "geometry": {"coordinates":[145.28590393100001,-37.8602294922],"type":"Point"}
}