{
  "type": "Feature",
  "properties": {
    "iso:country":"AU",
    "sg:address":"32 Marton St",
    "sg:city":"Shortland",
    "sg:classifiers":[
        {
            "category":"Structure",
            "subcategory":"Office Building",
            "type":"Public Place"
        }
    ],
    "sg:phone":"+61 2 4950 1667",
    "sg:postcode":"2307",
    "sg:province":"NSW",
    "sg:tags":[
        "slater",
        "tiler",
        "roof"
    ],
    "wof:name":"Hall Michael",
    "wof:placetype":"venue"
},
  "geometry": {"coordinates":[151.693192,-32.879925],"type":"Point"}
}