{
  "type": "Feature",
  "properties": {
    "iso:country":"AU",
    "sg:address":"Suite 2 / 2 Old Cleveland Rd",
    "sg:city":"Stones Corner",
    "sg:classifiers":[
        {
            "category":"Health Services",
            "subcategory":"Dentist",
            "type":"Services"
        }
    ],
    "sg:phone":"+61 7 3397 2016",
    "sg:postcode":"4120",
    "sg:province":"QLD",
    "sg:website":"http://www.nodecay.net",
    "wof:name":"Dr Abdul Azam",
    "wof:placetype":"venue"
},
  "geometry": {"coordinates":[153.047164917,-27.4987487793],"type":"Point"}
}