{
  "type": "Feature",
  "properties": {
    "addr:full":"292 Peel St Tamworth NSW 2340",
    "addr:housenumber":"292",
    "addr:postcode":"2340",
    "addr:street":"Peel St",
    "iso:country":"AU",
    "sg:address":"292 Peel St",
    "sg:city":"Tamworth",
    "sg:classifiers":[
        {
            "category":"Home & Garden",
            "subcategory":"Home Furnishings",
            "type":"Retail Goods"
        }
    ],
    "sg:phone":"+61 2 6762 7700",
    "sg:postcode":"2340",
    "sg:province":"NSW",
    "sg:tags":[
        "wicker",
        "cane",
        "furniture"
    ],
    "wof:name":"The Vast Interior",
    "wof:placetype":"venue"
},
  "geometry": {"coordinates":[150.92857360799999,-31.089006424],"type":"Point"}
}