{
  "type": "Feature",
  "properties": {
    "addr:full":"Cnr Glenelg & Merivale Sts South Brisbane QLD 4101",
    "addr:postcode":"4101",
    "addr:street":"Cnr Glenelg & Merivale Sts",
    "iso:country":"AU",
    "sg:address":"Cnr Glenelg & Merivale Sts",
    "sg:city":"South Brisbane",
    "sg:classifiers":[
        {
            "category":"Shopping",
            "subcategory":"Computers & Home Electronics",
            "type":"Retail Goods"
        }
    ],
    "sg:phone":"+61 7 3844 5675",
    "sg:postcode":"4101",
    "sg:province":"QLD",
    "sg:tags":[
        "equipment",
        "part",
        "electronic"
    ],
    "wof:name":"Electronic Warehouse",
    "wof:placetype":"venue"
},
  "geometry": {"coordinates":[153.01832580600001,-27.4787425995],"type":"Point"}
}