{
  "type": "Feature",
  "properties": {
    "addr:full":"380 Grand Junction Rd Mansfield Park SA 5012",
    "addr:housenumber":"380",
    "addr:postcode":"5012",
    "addr:street":"Grand Junction Rd",
    "iso:country":"AU",
    "sg:address":"380 Grand Junction Rd",
    "sg:city":"Mansfield Park",
    "sg:classifiers":[
        {
            "category":"Shopping",
            "subcategory":"Clothing, Apparel, & Fashions",
            "type":"Retail Goods"
        }
    ],
    "sg:phone":"+61 8 8268 6763",
    "sg:postcode":"5012",
    "sg:province":"SA",
    "sg:tags":[
        "jean"
    ],
    "wof:name":"Karob Jeans",
    "wof:placetype":"venue"
},
  "geometry": {"coordinates":[138.547775269,-34.8507194519],"type":"Point"}
}