{
  "type": "Feature",
  "properties": {
    "iso:country":"AU",
    "sg:address":"19 Ferris St",
    "sg:city":"Annandale",
    "sg:classifiers":[
        {
            "category":"Real Estate",
            "subcategory":"Real Estate Services",
            "type":"Services"
        }
    ],
    "sg:phone":"+61 2 9550 0883",
    "sg:postcode":"2038",
    "sg:province":"NSW",
    "sg:tags":[
        "valuer"
    ],
    "wof:name":"Waratah Property Services",
    "wof:placetype":"venue"
},
  "geometry": {"coordinates":[151.16517639200001,-33.8860282898],"type":"Point"}
}