{
  "type": "Feature",
  "properties": {
    "addr:full":"12 Stewart St Daintree QLD 4873",
    "addr:housenumber":"12",
    "addr:postcode":"4873",
    "addr:street":"Stewart St",
    "iso:country":"AU",
    "sg:address":"12 Stewart St",
    "sg:city":"Daintree",
    "sg:classifiers":[
        {
            "category":"Communications",
            "subcategory":"News Services",
            "type":"Services"
        }
    ],
    "sg:phone":"+61 7 4098 6103",
    "sg:postcode":"4873",
    "sg:province":"QLD",
    "sg:tags":[
        "information",
        "tourist",
        "attractions"
    ],
    "wof:name":"Electric Boat Cruises",
    "wof:placetype":"venue"
},
  "geometry": {"coordinates":[145.318237305,-16.2502536774],"type":"Point"}
}