{
  "type": "Feature",
  "properties": {
    "addr:full":"42 Manning St Kingswood NSW 2747",
    "addr:housenumber":"42",
    "addr:postcode":"2747",
    "addr:street":"Manning St",
    "iso:country":"AU",
    "sg:address":"42 Manning St",
    "sg:city":"Kingswood",
    "sg:classifiers":[
        {
            "category":"Shopping",
            "subcategory":"Computers & Home Electronics",
            "type":"Retail Goods"
        }
    ],
    "sg:phone":"+61 2 4736 8055",
    "sg:postcode":"2747",
    "sg:province":"NSW",
    "sg:tags":[
        "small",
        "equipment",
        "business"
    ],
    "wof:name":"MotherBoard Computer Systems",
    "wof:placetype":"venue"
},
  "geometry": {"coordinates":[150.72535705600001,-33.767162323],"type":"Point"}
}