{
  "type": "Feature",
  "properties": {
    "addr:full":"35 Enmore Rd Newtown NSW 2042",
    "addr:housenumber":"35",
    "addr:postcode":"2042",
    "addr:street":"Enmore Rd",
    "iso:country":"AU",
    "sg:address":"35 Enmore Rd",
    "sg:city":"Newtown",
    "sg:classifiers":[
        {
            "category":"Personal",
            "subcategory":"Beauty Salon",
            "type":"Services"
        }
    ],
    "sg:phone":"+61 2 9557 2331",
    "sg:postcode":"2042",
    "sg:province":"NSW",
    "wof:name":"Aquarius Beauty Salon",
    "wof:placetype":"venue"
},
  "geometry": {"coordinates":[151.175735,-33.898739],"type":"Point"}
}