{
  "type": "Feature",
  "properties": {
    "iso:country":"AU",
    "sg:address":"Corbery St",
    "sg:city":"Rockhampton",
    "sg:classifiers":[
        {
            "category":"Social Services",
            "subcategory":"Retirement Home",
            "type":"Services"
        }
    ],
    "sg:phone":"+61 7 4921 1981",
    "sg:postcode":"4700",
    "sg:province":"QLD",
    "sg:tags":[
        "village"
    ],
    "wof:name":"The Range Village",
    "wof:placetype":"venue"
},
  "geometry": {"coordinates":[150.49848938,-23.3920154572],"type":"Point"}
}