{
  "type": "Feature",
  "properties": {
    "iso:country":"AU",
    "sg:address":"159 Dickward Drive (Woollies Complex, Nightcliff Shopping Centre)",
    "sg:city":"Nightcliff",
    "sg:classifiers":[
        {
            "category":"Health Services",
            "subcategory":"Doctor",
            "type":"Services"
        }
    ],
    "sg:phone":"+61 8 8948 4333",
    "sg:postcode":"0810",
    "sg:province":"NT",
    "sg:tags":[
        "medical",
        "practitioner"
    ],
    "wof:name":"Nightcliff Medical Centre",
    "wof:placetype":"venue"
},
  "geometry": {"coordinates":[130.852127075,-12.3893470764],"type":"Point"}
}