{
  "type": "Feature",
  "properties": {
    "addr:full":"Shop 22 Mt Ommaney Cntr Mt Ommaney QLD 4074",
    "addr:housenumber":"shop 22",
    "addr:postcode":"4074",
    "addr:street":"Mt Ommaney Cntr Mt Ommaney",
    "iso:country":"AU",
    "sg:address":"Shop 22 Mt Ommaney Cntr",
    "sg:city":"Mt Ommaney",
    "sg:classifiers":[
        {
            "category":"Health Services",
            "subcategory":"Optometrist",
            "type":"Services"
        }
    ],
    "sg:phone":"+61 7 3376 5307",
    "sg:postcode":"4074",
    "sg:province":"QLD",
    "wof:name":"Laubman & Pank",
    "wof:placetype":"venue"
},
  "geometry": {"coordinates":[152.936737061,-27.5287322998],"type":"Point"}
}