{
  "type": "Feature",
  "properties": {
    "addr:full":"PO Box 24 Claremont TAS 7011",
    "addr:postcode":"7011",
    "iso:country":"AU",
    "sg:address":"PO Box 24",
    "sg:city":"Claremont",
    "sg:classifiers":[
        {
            "category":"Building & Trades",
            "subcategory":"Construction",
            "type":"Services"
        }
    ],
    "sg:phone":"+61 448 910 503",
    "sg:postcode":"7011",
    "sg:province":"TAS",
    "sg:tags":[
        "contractor"
    ],
    "wof:name":"Cre8ive Constructions",
    "wof:placetype":"venue"
},
  "geometry": {"coordinates":[147.250534058,-42.77602005],"type":"Point"}
}