{
  "type": "Feature",
  "properties": {
    "addr:full":"5 Cobbler Crt Leda WA 6170",
    "addr:housenumber":"5",
    "addr:postcode":"6170",
    "addr:street":"Cobbler Crt",
    "iso:country":"AU",
    "sg:address":"5 Cobbler Crt",
    "sg:city":"Leda",
    "sg:classifiers":[
        {
            "category":"Professional",
            "subcategory":"Detective & Security Services",
            "type":"Services"
        }
    ],
    "sg:phone":"+61 8 9419 5519",
    "sg:postcode":"6170",
    "sg:province":"WA",
    "sg:tags":[
        "domestic",
        "alarm",
        "commercial",
        "burglar"
    ],
    "wof:name":"Coastal Alarm Systems",
    "wof:placetype":"venue"
},
  "geometry": {"coordinates":[115.835182,-32.271015],"type":"Point"}
}