{
  "type": "Feature",
  "properties": {
    "addr:full":"791- 793 Nepean Hwy Moorabbin VIC 3189",
    "addr:housenumber":"793",
    "addr:postcode":"3189",
    "addr:street":"Nepean Hwy",
    "iso:country":"AU",
    "sg:address":"791- 793 Nepean Hwy",
    "sg:city":"Moorabbin",
    "sg:classifiers":[
        {
            "category":"Retail",
            "subcategory":"Auto Repair",
            "type":"Services"
        }
    ],
    "sg:phone":"+61 3 9524 9200",
    "sg:postcode":"3189",
    "sg:province":"VIC",
    "sg:tags":[
        "repairer",
        "motor",
        "engineer"
    ],
    "wof:name":"Southern Automobiles Volkswagen",
    "wof:placetype":"venue"
},
  "geometry": {"coordinates":[145.02394104000001,-37.9215126038],"type":"Point"}
}