{
  "type": "Feature",
  "properties": {
    "addr:full":"6A Conifer St Daisy Hill QLD 4127",
    "addr:housenumber":"6a",
    "addr:postcode":"4127",
    "addr:street":"Conifer St",
    "iso:country":"AU",
    "sg:address":"6A Conifer St",
    "sg:city":"Daisy Hill",
    "sg:classifiers":[
        {
            "category":"Bus Charters",
            "type":"Transportation"
        }
    ],
    "sg:phone":"+61 7 3208 8539",
    "sg:postcode":"4127",
    "sg:province":"QLD",
    "sg:tags":[
        "builder"
    ],
    "wof:name":"Springwood Flooring Pty Ltd",
    "wof:placetype":"venue"
},
  "geometry": {"coordinates":[153.16033935600001,-27.6456565857],"type":"Point"}
}