{
  "type": "Feature",
  "properties": {
    "iso:country":"AU",
    "sg:address":"112 Griffith St",
    "sg:city":"Coolangatta",
    "sg:classifiers":[
        {
            "category":"Real Estate",
            "subcategory":"Real Estate Agent",
            "type":"Services"
        }
    ],
    "sg:phone":"+61 7 5536 9369",
    "sg:postcode":"4225",
    "sg:province":"QLD",
    "wof:name":"Signatures Real Estate",
    "wof:placetype":"venue"
},
  "geometry": {"coordinates":[153.54000854500001,-28.1689186096],"type":"Point"}
}