{
  "type": "Feature",
  "properties": {
    "iso:country":"AU",
    "sg:address":"198 Paynes Rd",
    "sg:city":"Alloway",
    "sg:classifiers":[
        {
            "category":"Manufacturing",
            "subcategory":"Tools & Machinery",
            "type":"Manufacturing & Wholesale Goods"
        }
    ],
    "sg:phone":"+61 7 4159 7800",
    "sg:postcode":"4670",
    "sg:province":"QLD",
    "sg:tags":[
        "earth",
        "excavating",
        "moving",
        "equipment"
    ],
    "wof:name":"Budgie's Backhoe Hire",
    "wof:placetype":"venue"
},
  "geometry": {"coordinates":[152.36231994600001,-24.8951396942],"type":"Point"}
}