{
  "type": "Feature",
  "properties": {
    "iso:country":"AU",
    "sg:address":"11 Flinders St",
    "sg:city":"Coburg",
    "sg:classifiers":[
        {
            "category":"Retail",
            "subcategory":"Repair Shop",
            "type":"Services"
        }
    ],
    "sg:phone":"+61 3 9350 5283",
    "sg:postcode":"3058",
    "sg:province":"VIC",
    "sg:tags":[
        "leadlights"
    ],
    "wof:name":"Kon's Glass Repairs",
    "wof:placetype":"venue"
},
  "geometry": {"coordinates":[144.95335388199999,-37.73695755],"type":"Point"}
}