{
  "type": "Feature",
  "properties": {
    "addr:full":"53A Royce St Greystanes NSW 2145",
    "addr:housenumber":"53a",
    "addr:postcode":"2145",
    "addr:street":"Royce St",
    "iso:country":"AU",
    "sg:address":"53A Royce St",
    "sg:city":"Greystanes",
    "sg:classifiers":[
        {
            "category":"Professional",
            "subcategory":"Art Services",
            "type":"Services"
        }
    ],
    "sg:phone":"+61 2 9631 3150",
    "sg:postcode":"2145",
    "sg:province":"NSW",
    "sg:tags":[
        "decorator",
        "painter"
    ],
    "wof:name":"Luxury Design Painting Pty Ltd",
    "wof:placetype":"venue"
},
  "geometry": {"coordinates":[150.951416016,-33.8302841187],"type":"Point"}
}