{
  "type": "Feature",
  "properties": {
    "addr:full":"127 Centre St Casino NSW 2470",
    "addr:housenumber":"127",
    "addr:postcode":"2470",
    "addr:street":"Centre St",
    "iso:country":"AU",
    "sg:address":"127 Centre St",
    "sg:city":"Casino",
    "sg:classifiers":[
        {
            "category":"Building & Trades",
            "subcategory":"Construction",
            "type":"Services"
        }
    ],
    "sg:phone":"+61 2 6662 4381",
    "sg:postcode":"2470",
    "sg:province":"NSW",
    "sg:tags":[
        "stonework",
        "stone",
        "mason"
    ],
    "wof:name":"F.J. McKey Jnr. Monumental Masonry Pty Ltd",
    "wof:placetype":"venue"
},
  "geometry": {"coordinates":[153.04690551799999,-28.8579521179],"type":"Point"}
}