{
  "type": "Feature",
  "properties": {
    "addr:full":"PO Box 501 Balcatta WA 6021",
    "addr:postcode":"6021",
    "iso:country":"AU",
    "sg:address":"PO Box 501",
    "sg:city":"Balcatta",
    "sg:classifiers":[
        {
            "category":"Home & Garden",
            "subcategory":"Building Materials",
            "type":"Retail Goods"
        }
    ],
    "sg:phone":"+61 8 9247 3465",
    "sg:postcode":"6021",
    "sg:province":"WA",
    "sg:tags":[
        "merchant",
        "glass",
        "glazier"
    ],
    "wof:name":"Bonefish Glass",
    "wof:placetype":"venue"
},
  "geometry": {"coordinates":[115.82837677000001,-31.8731803894],"type":"Point"}
}