{
  "type": "Feature",
  "properties": {
    "addr:full":"6 Pignot Pl Goonellabah NSW 2480",
    "addr:housenumber":"6",
    "addr:postcode":"2480",
    "addr:street":"Pignot Pl",
    "iso:country":"AU",
    "sg:address":"6 Pignot Pl",
    "sg:city":"Goonellabah",
    "sg:classifiers":[
        {
            "category":"Manufacturing",
            "subcategory":"Motor Vehicles & Parts",
            "type":"Manufacturing & Wholesale Goods"
        }
    ],
    "sg:phone":"+61 2 6624 5283",
    "sg:postcode":"2480",
    "sg:province":"NSW",
    "sg:tags":[
        "wholesaler",
        "cycle",
        "mfrs",
        "accessory"
    ],
    "wof:name":"JCM Motorcycles Pty Ltd",
    "wof:placetype":"venue"
},
  "geometry": {"coordinates":[153.347457886,-28.8147735596],"type":"Point"}
}