{
  "type": "Feature",
  "properties": {
    "addr:full":"163 Stephensons Rd Mt Waverley VIC 3149",
    "addr:housenumber":"163",
    "addr:postcode":"3149",
    "addr:street":"Stephensons Rd",
    "iso:country":"AU",
    "sg:address":"163 Stephensons Rd",
    "sg:city":"Mt Waverley",
    "sg:classifiers":[
        {
            "category":"Social Services",
            "type":"Services"
        }
    ],
    "sg:phone":"+61 3 9809 4333",
    "sg:postcode":"3149",
    "sg:province":"VIC",
    "sg:tags":[
        "domestic",
        "help"
    ],
    "wof:name":"A Alma Rays",
    "wof:placetype":"venue"
},
  "geometry": {"coordinates":[145.12977600100001,-37.8707542419],"type":"Point"}
}