{
  "type": "Feature",
  "properties": {
    "addr:full":"Lot 11 Colston Rd Winton QLD 4735",
    "addr:postcode":"4735",
    "addr:street":"Colston Rd",
    "iso:country":"AU",
    "sg:address":"Lot 11 Colston Rd",
    "sg:city":"Winton",
    "sg:classifiers":[
        {
            "category":"Building & Trades",
            "subcategory":"Construction",
            "type":"Services"
        }
    ],
    "sg:phone":"+61 7 4657 1899",
    "sg:postcode":"4735",
    "sg:province":"QLD",
    "sg:tags":[
        "earth",
        "excavating",
        "moving",
        "contractor"
    ],
    "wof:name":"Phil Doolan Earthmoving",
    "wof:placetype":"venue"
},
  "geometry": {"coordinates":[143.040527,-22.391609],"type":"Point"}
}