{
  "type": "Feature",
  "properties": {
    "iso:country":"AU",
    "sg:address":"Lillian St",
    "sg:city":"Berala",
    "sg:classifiers":[
        {
            "category":"Building & Trades",
            "subcategory":"Construction",
            "type":"Services"
        }
    ],
    "sg:phone":"+61 2 9649 1556",
    "sg:postcode":"2141",
    "sg:province":"NSW",
    "sg:tags":[
        "earth",
        "excavating",
        "moving",
        "contractor"
    ],
    "wof:name":"Deehan Excavations",
    "wof:placetype":"venue"
},
  "geometry": {"coordinates":[151.036911011,-33.8729972839],"type":"Point"}
}