{
  "type": "Feature",
  "properties": {
    "addr:full":"Shop 4/ 7 Hillcrest Rd Pennant Hills NSW 2120",
    "addr:housenumber":"shop 4 / 7",
    "addr:postcode":"2120",
    "addr:street":"Hillcrest Rd",
    "iso:country":"AU",
    "sg:address":"Shop 4/ 7 Hillcrest Rd",
    "sg:city":"Pennant Hills",
    "sg:classifiers":[
        {
            "category":"Health Services",
            "subcategory":"Doctor",
            "type":"Services"
        }
    ],
    "sg:phone":"+61 2 9481 8672",
    "sg:postcode":"2120",
    "sg:province":"NSW",
    "sg:tags":[
        "medical",
        "practitioner"
    ],
    "wof:name":"Douglass Hanly Moir Pathology",
    "wof:placetype":"venue"
},
  "geometry": {"coordinates":[151.070602417,-33.7382469177],"type":"Point"}
}