{
  "type": "Feature",
  "properties": {
    "addr:full":"302 Anzac Ave Kippa-Ring QLD 4021",
    "addr:housenumber":"302",
    "addr:postcode":"4021",
    "addr:street":"Anzac Ave",
    "iso:country":"AU",
    "sg:address":"302 Anzac Ave",
    "sg:city":"Kippa-Ring",
    "sg:classifiers":[
        {
            "category":"Shopping",
            "subcategory":"Pawn Shop",
            "type":"Retail Goods"
        }
    ],
    "sg:phone":"+61 7 3283 6457",
    "sg:postcode":"4021",
    "sg:province":"QLD",
    "sg:tags":[
        "pawnbroker"
    ],
    "wof:name":"Cash Converters Redcliffe",
    "wof:placetype":"venue"
},
  "geometry": {"coordinates":[153.084824,-27.226152],"type":"Point"}
}