{
  "type": "Feature",
  "properties": {
    "addr:full":"49 Hampshire Rd Doncaster VIC 3108",
    "addr:housenumber":"49",
    "addr:postcode":"3108",
    "addr:street":"Hampshire Rd",
    "iso:country":"AU",
    "sg:address":"49 Hampshire Rd",
    "sg:city":"Doncaster",
    "sg:classifiers":[
        {
            "category":"Manufacturing",
            "subcategory":"Tools & Machinery",
            "type":"Manufacturing & Wholesale Goods"
        }
    ],
    "sg:phone":"+61 3 9848 2852",
    "sg:postcode":"3108",
    "sg:province":"VIC",
    "sg:tags":[
        "manufactured",
        "specially",
        "designed"
    ],
    "wof:name":"Arlos Engineering",
    "wof:placetype":"venue"
},
  "geometry": {"coordinates":[145.140457153,-37.7959213257],"type":"Point"}
}