{
  "type": "Feature",
  "properties": {
    "addr:full":"18 View St Peakhurst NSW 2210",
    "addr:housenumber":"18",
    "addr:postcode":"2210",
    "addr:street":"View St",
    "iso:country":"AU",
    "sg:address":"18 View St",
    "sg:city":"Peakhurst",
    "sg:classifiers":[
        {
            "category":"Professional",
            "subcategory":"Management & Consulting",
            "type":"Services"
        }
    ],
    "sg:phone":"+61 2 9584 2989",
    "sg:postcode":"2210",
    "sg:province":"NSW",
    "sg:tags":[
        "consultant"
    ],
    "wof:name":"ASPIN Marketing & Promotions",
    "wof:placetype":"venue"
},
  "geometry": {"coordinates":[151.05183400000001,-33.980488],"type":"Point"}
}