{
  "type": "Feature",
  "properties": {
    "iso:country":"AU",
    "sg:address":"31 Roslyn St",
    "sg:city":"Lane Cove",
    "sg:classifiers":[
        {
            "category":"Education",
            "subcategory":"Kindergarten",
            "type":"Public Place"
        }
    ],
    "sg:phone":"+61 2 9427 8587",
    "sg:postcode":"2066",
    "sg:province":"NSW",
    "sg:tags":[
        "pre-schools"
    ],
    "wof:name":"Little Rascals Child Care",
    "wof:placetype":"venue"
},
  "geometry": {"coordinates":[151.16763305699999,-33.8080596924],"type":"Point"}
}