{
  "type": "Feature",
  "properties": {
    "iso:country":"AU",
    "sg:address":"32 Jarvisfield Rd",
    "sg:city":"Picton",
    "sg:classifiers":[
        {
            "category":"Building & Trades",
            "subcategory":"Construction",
            "type":"Services"
        }
    ],
    "sg:phone":"+61 2 4677 2482",
    "sg:postcode":"2571",
    "sg:province":"NSW",
    "sg:tags":[
        "road",
        "contractor"
    ],
    "wof:name":"Fabemo Pty Ltd",
    "wof:placetype":"venue"
},
  "geometry": {"coordinates":[150.61561584500001,-34.1624832153],"type":"Point"}
}