{
  "type": "Feature",
  "properties": {
    "addr:full":"Ritchie St Penshurst VIC 3289",
    "addr:postcode":"3289",
    "addr:street":"Ritchie St",
    "iso:country":"AU",
    "sg:address":"Ritchie St",
    "sg:city":"Penshurst",
    "sg:classifiers":[
        {
            "category":"Education",
            "subcategory":"School",
            "type":"Public Place"
        }
    ],
    "sg:phone":"+61 3 5576 5433",
    "sg:postcode":"3289",
    "sg:province":"VIC",
    "sg:tags":[
        "state",
        "except",
        "nsw"
    ],
    "wof:name":"Penshurst Primary School",
    "wof:placetype":"venue"
},
  "geometry": {"coordinates":[142.28880310100001,-37.8790092468],"type":"Point"}
}