{
  "type": "Feature",
  "properties": {
    "addr:full":"Unit 1, 51 Farrall Rd Midvale WA 6056",
    "addr:housenumber":"51",
    "addr:postcode":"6056",
    "addr:street":"Farrall Rd",
    "iso:country":"AU",
    "sg:address":"Unit 1, 51 Farrall Rd",
    "sg:city":"Midvale",
    "sg:classifiers":[
        {
            "category":"Organizations",
            "subcategory":"Professional Association",
            "type":"Services"
        }
    ],
    "sg:phone":"+61 8 9274 6670",
    "sg:postcode":"6056",
    "sg:province":"WA",
    "sg:tags":[
        "web",
        "internet"
    ],
    "wof:name":"Hambo Design",
    "wof:placetype":"venue"
},
  "geometry": {"coordinates":[116.033241272,-31.889333725],"type":"Point"}
}