{
  "type": "Feature",
  "properties": {
    "addr:full":"336 Orrong Rd Caulfield North VIC 3161",
    "addr:housenumber":"336",
    "addr:postcode":"3161",
    "addr:street":"Orrong Rd",
    "iso:country":"AU",
    "sg:address":"336 Orrong Rd",
    "sg:city":"Caulfield North",
    "sg:classifiers":[
        {
            "category":"Personal",
            "subcategory":"Beauty Salon",
            "type":"Services"
        }
    ],
    "sg:phone":"+61 3 9527 2713",
    "sg:postcode":"3161",
    "sg:province":"VIC",
    "sg:tags":[
        "hairdresser"
    ],
    "wof:name":"Milicic Anton Hair Style For Men",
    "wof:placetype":"venue"
},
  "geometry": {"coordinates":[145.00994873100001,-37.8642654419],"type":"Point"}
}