{
  "type": "Feature",
  "properties": {
    "addr:full":"Brownells La Moonah TAS 7009",
    "addr:postcode":"7009",
    "iso:country":"AU",
    "sg:address":"Brownells La",
    "sg:city":"Moonah",
    "sg:classifiers":[
        {
            "category":"Banks & Credit Unions",
            "subcategory":"Investment Brokerage",
            "type":"Services"
        }
    ],
    "sg:phone":"+61 3 6278 2736",
    "sg:postcode":"7009",
    "sg:province":"TAS",
    "sg:tags":[
        "radiator",
        "motor"
    ],
    "wof:name":"Aherne Pat",
    "wof:placetype":"venue"
},
  "geometry": {"coordinates":[147.298339844,-42.8502731323],"type":"Point"}
}