{
  "type": "Feature",
  "properties": {
    "iso:country":"AU",
    "sg:address":"PO Box 546",
    "sg:city":"Heathcote",
    "sg:classifiers":[
        {
            "category":"Farming",
            "subcategory":"Poultry Farm",
            "type":"Manufacturing & Wholesale Goods"
        }
    ],
    "sg:phone":"+61 3 5439 1286",
    "sg:postcode":"3523",
    "sg:province":"VIC",
    "sg:tags":[
        "farmer"
    ],
    "wof:name":"IM & JA Littlejohn",
    "wof:placetype":"venue"
},
  "geometry": {"coordinates":[144.700333,-36.91436],"type":"Point"}
}