{
  "type": "Feature",
  "properties": {
    "addr:full":"St Oswald's Anglican Church 100 High St Glen Iris VIC 3146",
    "addr:housenumber":"100",
    "addr:postcode":"3146",
    "addr:street":"High St",
    "iso:country":"AU",
    "sg:address":"St Oswald's Anglican Church 100 High St",
    "sg:city":"Glen Iris",
    "sg:classifiers":[
        {
            "category":"Arts & Performance",
            "subcategory":"Dance",
            "type":"Entertainment"
        }
    ],
    "sg:phone":"+61 412 252 506",
    "sg:postcode":"3146",
    "sg:province":"VIC",
    "sg:tags":[
        "theatrical",
        "ballet",
        "tuition"
    ],
    "wof:name":"La Petite Ballet",
    "wof:placetype":"venue"
},
  "geometry": {"coordinates":[145.07066345199999,-37.8624649048],"type":"Point"}
}