{
  "type": "Feature",
  "properties": {
    "iso:country":"AU",
    "sg:address":"372 Hampton St",
    "sg:city":"Hampton",
    "sg:classifiers":[
        {
            "category":"Health Services",
            "subcategory":"Dentist",
            "type":"Services"
        }
    ],
    "sg:phone":"+61 407 814 024",
    "sg:postcode":"3188",
    "sg:province":"VIC",
    "wof:name":"Harnick Douglas Dr",
    "wof:placetype":"venue"
},
  "geometry": {"coordinates":[145.00221252399999,-37.9399108887],"type":"Point"}
}