{
  "type": "Feature",
  "properties": {
    "iso:country":"AU",
    "sg:address":"42 High St",
    "sg:city":"Swan Hill",
    "sg:classifiers":[
        {
            "category":"Health Services",
            "subcategory":"Dentist",
            "type":"Services"
        }
    ],
    "sg:phone":"+61 3 5033 1788",
    "sg:postcode":"3585",
    "sg:province":"VIC",
    "sg:tags":[
        "technician",
        "dental"
    ],
    "wof:name":"Stacey's Dental Laboratory",
    "wof:placetype":"venue"
},
  "geometry": {"coordinates":[143.555496,-35.341068],"type":"Point"}
}