{
  "type": "Feature",
  "properties": {
    "iso:country":"AU",
    "sg:address":"40 Pettigrew St",
    "sg:city":"Mt Gravatt",
    "sg:classifiers":[
        {
            "category":"Retail",
            "subcategory":"Driving School",
            "type":"Services"
        }
    ],
    "sg:phone":"+61 7 3849 2052",
    "sg:postcode":"4122",
    "sg:province":"QLD",
    "wof:name":"Scotia Driving School & Instructor Services",
    "wof:placetype":"venue"
},
  "geometry": {"coordinates":[153.08523559599999,-27.5405807495],"type":"Point"}
}