{
  "type": "Feature",
  "properties": {
    "addr:full":"20 Federal St Narrogin WA 6312",
    "addr:housenumber":"20",
    "addr:postcode":"6312",
    "addr:street":"Federal St",
    "iso:country":"AU",
    "sg:address":"20 Federal St",
    "sg:city":"Narrogin",
    "sg:classifiers":[
        {
            "category":"Insurance",
            "subcategory":"Hazard Insurance",
            "type":"Services"
        }
    ],
    "sg:phone":"+61 8 9881 2086",
    "sg:postcode":"6312",
    "sg:province":"WA",
    "sg:tags":[
        "fire",
        "accident",
        "marine"
    ],
    "wof:name":"Wesfarmers Federation Insurance",
    "wof:placetype":"venue"
},
  "geometry": {"coordinates":[117.178207398,-32.9314994812],"type":"Point"}
}