{
  "type": "Feature",
  "properties": {
    "iso:country":"AU",
    "sg:address":"45 Dunn Rd",
    "sg:city":"Rocklea",
    "sg:classifiers":[
        {
            "category":"Building & Trades",
            "subcategory":"Construction",
            "type":"Services"
        }
    ],
    "sg:phone":"+61 7 3277 8944",
    "sg:postcode":"4106",
    "sg:province":"QLD",
    "sg:tags":[
        "equipment",
        "balancing"
    ],
    "wof:name":"Engine Engineering",
    "wof:placetype":"venue"
},
  "geometry": {"coordinates":[152.99562072800001,-27.5553455353],"type":"Point"}
}