{
  "type": "Feature",
  "properties": {
    "addr:full":"21 Park Rd Cheltenham VIC 3192",
    "addr:housenumber":"21",
    "addr:postcode":"3192",
    "addr:street":"Park Rd",
    "iso:country":"AU",
    "sg:address":"21 Park Rd",
    "sg:city":"Cheltenham",
    "sg:classifiers":[
        {
            "category":"Home & Garden",
            "subcategory":"Building Materials",
            "type":"Retail Goods"
        }
    ],
    "sg:phone":"+61 3 9584 8855",
    "sg:postcode":"3192",
    "sg:province":"VIC",
    "sg:tags":[
        "supply"
    ],
    "wof:name":"A. Park Road Timber & Hardware Pty Ltd",
    "wof:placetype":"venue"
},
  "geometry": {"coordinates":[145.039962769,-37.9633026123],"type":"Point"}
}