{
  "type": "Feature",
  "properties": {
    "addr:full":"Lynch's Crossing Rd Glenthompson VIC 3293",
    "addr:postcode":"3293",
    "addr:street":"Crossing Rd",
    "iso:country":"AU",
    "sg:address":"Lynch's Crossing Rd",
    "sg:city":"Glenthompson",
    "sg:classifiers":[
        {
            "category":"Retail",
            "subcategory":"Animal Services",
            "type":"Services"
        }
    ],
    "sg:phone":"+61 3 5577 4331",
    "sg:postcode":"3293",
    "sg:province":"VIC",
    "sg:tags":[
        "breeder",
        "sheep",
        "stud",
        "cattle"
    ],
    "wof:name":"Cleverlie Coopworth Stud",
    "wof:placetype":"venue"
},
  "geometry": {"coordinates":[142.550506592,-37.5932044983],"type":"Point"}
}