{
  "type": "Feature",
  "properties": {
    "addr:full":"Cnr Woodstock & Willis St Newman WA 6753",
    "addr:postcode":"6753",
    "addr:street":"Cnr;St",
    "iso:country":"AU",
    "sg:address":"Cnr Woodstock & Willis St",
    "sg:city":"Newman",
    "sg:classifiers":[
        {
            "category":"Building & Trades",
            "subcategory":"Construction",
            "type":"Services"
        }
    ],
    "sg:phone":"+61 8 9175 1193",
    "sg:postcode":"6753",
    "sg:province":"WA",
    "sg:tags":[
        "earth",
        "excavating",
        "moving",
        "contractor"
    ],
    "wof:name":"N R W Pty Ltd",
    "wof:placetype":"venue"
},
  "geometry": {"coordinates":[119.73184967,-23.3686332703],"type":"Point"}
}