{
  "type": "Feature",
  "properties": {
    "addr:full":"Gr Flr 99 King St Melbourne VIC 3000",
    "addr:postcode":"3000",
    "addr:street":"Gr;King St",
    "iso:country":"AU",
    "sg:address":"Gr Flr 99 King St",
    "sg:city":"Melbourne",
    "sg:classifiers":[
        {
            "category":"Banks & Credit Unions",
            "subcategory":"Bank",
            "type":"Services"
        }
    ],
    "sg:phone":"+61 3 9629 4484",
    "sg:postcode":"3000",
    "sg:province":"VIC",
    "sg:tags":[
        "society"
    ],
    "wof:name":"Transcomm Credit Co-Operative Ltd",
    "wof:placetype":"venue"
},
  "geometry": {"coordinates":[144.95611572300001,-37.817527771],"type":"Point"}
}