{
  "type": "Feature",
  "properties": {
    "addr:full":"20 Virginia St Mornington VIC 3931",
    "addr:housenumber":"20",
    "addr:postcode":"3931",
    "addr:street":"Virginia St",
    "iso:country":"AU",
    "sg:address":"20 Virginia St",
    "sg:city":"Mornington",
    "sg:classifiers":[
        {
            "category":"Home & Garden",
            "subcategory":"Carpets & Floor Coverings",
            "type":"Retail Goods"
        }
    ],
    "sg:phone":"+61 3 5973 6936",
    "sg:postcode":"3931",
    "sg:province":"VIC",
    "sg:tags":[
        "wood"
    ],
    "wof:name":"Master Plus Timber Floors",
    "wof:placetype":"venue"
},
  "geometry": {"coordinates":[145.049026489,-38.2321014404],"type":"Point"}
}