{
  "type": "Feature",
  "properties": {
    "iso:country":"AU",
    "sg:address":"16 Oldaker St",
    "sg:city":"Devonport",
    "sg:classifiers":[
        {
            "category":"Retail",
            "subcategory":"Auto Repair",
            "type":"Services"
        }
    ],
    "sg:phone":"+61 3 6424 7222",
    "sg:postcode":"7310",
    "sg:province":"TAS",
    "sg:tags":[
        "repairer",
        "motor",
        "engineer"
    ],
    "wof:name":"Bob Jane T-Marts",
    "wof:placetype":"venue"
},
  "geometry": {"coordinates":[146.359832764,-41.1763420105],"type":"Point"}
}