{
  "type": "Feature",
  "properties": {
    "iso:country":"AU",
    "sg:address":"Shop 1 115 Pakington St",
    "sg:city":"Geelong West",
    "sg:classifiers":[
        {
            "category":"Shopping",
            "subcategory":"Clothing, Apparel, & Fashions",
            "type":"Retail Goods"
        }
    ],
    "sg:phone":"+61 3 5243 7686",
    "sg:postcode":"3218",
    "sg:province":"VIC",
    "sg:tags":[
        "menswear"
    ],
    "wof:name":"Pakington Men's Outfitters Pty Ltd",
    "wof:placetype":"venue"
},
  "geometry": {"coordinates":[144.34852600100001,-38.1387176514],"type":"Point"}
}