{
  "type": "Feature",
  "properties": {
    "addr:full":"6 Chapman St Swan Hill VIC 3585",
    "addr:housenumber":"6",
    "addr:postcode":"3585",
    "addr:street":"Chapman St",
    "iso:country":"AU",
    "sg:address":"6 Chapman St",
    "sg:city":"Swan Hill",
    "sg:classifiers":[
        {
            "category":"Utilities",
            "type":"Services"
        }
    ],
    "sg:phone":"+61 3 5032 2772",
    "sg:postcode":"3585",
    "sg:province":"VIC",
    "sg:tags":[
        "equipment",
        "towing"
    ],
    "wof:name":"Swan Hill Off Road",
    "wof:placetype":"venue"
},
  "geometry": {"coordinates":[143.557861,-35.333427],"type":"Point"}
}