{
  "type": "Feature",
  "properties": {
    "addr:full":"Shop 67 Westfield Shopping Centre Warrawong NSW 2502",
    "addr:housenumber":"shop 67",
    "addr:postcode":"2502",
    "addr:street":"Westfield Shopping",
    "iso:country":"AU",
    "sg:address":"Shop 67 Westfield Shopping Centre",
    "sg:city":"Warrawong",
    "sg:classifiers":[
        {
            "category":"Shopping",
            "subcategory":"Clothing, Apparel, & Fashions",
            "type":"Retail Goods"
        }
    ],
    "sg:phone":"+61 2 4274 4966",
    "sg:postcode":"2502",
    "sg:province":"NSW",
    "sg:tags":[
        "lady",
        "wear"
    ],
    "wof:name":"Sussan Lingerie & Sportswear",
    "wof:placetype":"venue"
},
  "geometry": {"coordinates":[150.88755800000001,-34.484859],"type":"Point"}
}