{
  "type": "Feature",
  "properties": {
    "iso:country":"AU",
    "sg:address":"5 Fenton Way",
    "sg:city":"Kew",
    "sg:classifiers":[
        {
            "category":"Personal",
            "subcategory":"Beauty Salon",
            "type":"Services"
        }
    ],
    "sg:phone":"+61 3 9853 5110",
    "sg:postcode":"3101",
    "sg:province":"VIC",
    "sg:website":"http://www.chicwaxing.com.au",
    "wof:name":"Chic Waxing",
    "wof:placetype":"venue"
},
  "geometry": {"coordinates":[145.030426025,-37.8070487976],"type":"Point"}
}