{
  "type": "Feature",
  "properties": {
    "addr:full":"97 Old Toombul Rd Northgate QLD 4013",
    "addr:housenumber":"97",
    "addr:postcode":"4013",
    "addr:street":"Old Toombul Rd",
    "iso:country":"AU",
    "sg:address":"97 Old Toombul Rd",
    "sg:city":"Northgate",
    "sg:classifiers":[
        {
            "category":"Professional",
            "subcategory":"Testing Lab",
            "type":"Services"
        }
    ],
    "sg:phone":"+61 7 3260 6371",
    "sg:postcode":"4013",
    "sg:province":"QLD",
    "sg:tags":[
        "soil",
        "investigation"
    ],
    "sg:website":"http://www.structerreqld.com.au",
    "wof:name":"Structerre Consulting Engineers",
    "wof:placetype":"venue"
},
  "geometry": {"coordinates":[153.071365356,-27.3913078308],"type":"Point"}
}