{
  "type": "Feature",
  "properties": {
    "iso:country":"AU",
    "sg:address":"5/18- 20 Whyalla Pl",
    "sg:city":"Prestons",
    "sg:classifiers":[
        {
            "category":"Manufacturing",
            "subcategory":"Tools & Machinery",
            "type":"Manufacturing & Wholesale Goods"
        }
    ],
    "sg:phone":"+61 2 9608 3999",
    "sg:postcode":"2170",
    "sg:province":"NSW",
    "sg:tags":[
        "toolmaker"
    ],
    "wof:name":"Lomar Tooling Pty Limited",
    "wof:placetype":"venue"
},
  "geometry": {"coordinates":[150.87890625,-33.9315338135],"type":"Point"}
}