{
  "type": "Feature",
  "properties": {
    "iso:country":"AU",
    "sg:address":"Banyan View Lodge, 119 Mitchell St",
    "sg:city":"Larrakeyah",
    "sg:classifiers":[
        {
            "category":"Government",
            "subcategory":"Post Office",
            "type":"Public Place"
        }
    ],
    "sg:phone":"+61 8 8985 5731",
    "sg:postcode":"0820",
    "sg:province":"NT",
    "sg:tags":[
        "yoga"
    ],
    "wof:name":"City Yoga Zone",
    "wof:placetype":"venue"
},
  "geometry": {"coordinates":[130.834350586,-12.4579553604],"type":"Point"}
}