{
  "type": "Feature",
  "properties": {
    "iso:country":"AU",
    "sg:address":"66 Frances Bay Drv",
    "sg:city":"Darwin",
    "sg:classifiers":[
        {
            "category":"Train Station",
            "subcategory":"Rail",
            "type":"Transportation"
        }
    ],
    "sg:phone":"+61 8 8981 9625",
    "sg:postcode":"0800",
    "sg:province":"NT",
    "sg:tags":[
        "ship",
        "chandler"
    ],
    "wof:name":"Sadgroves Quay",
    "wof:placetype":"venue"
},
  "geometry": {"coordinates":[130.84806823700001,-12.4529485703],"type":"Point"}
}