{
  "type": "Feature",
  "properties": {
    "addr:full":"73 Boyd St Kelso NSW 2795",
    "addr:housenumber":"73",
    "addr:postcode":"2795",
    "addr:street":"Boyd St",
    "iso:country":"AU",
    "sg:address":"73 Boyd St",
    "sg:city":"Kelso",
    "sg:classifiers":[
        {
            "category":"Personal",
            "subcategory":"Massage",
            "type":"Services"
        }
    ],
    "sg:phone":"+61 2 6331 7307",
    "sg:postcode":"2795",
    "sg:province":"NSW",
    "sg:tags":[
        "therapy"
    ],
    "wof:name":"Sweetnam Christine",
    "wof:placetype":"venue"
},
  "geometry": {"coordinates":[149.613006592,-33.4134254456],"type":"Point"}
}