{
  "type": "Feature",
  "properties": {
    "iso:country":"AU",
    "sg:address":"5/55 Willarong Rd",
    "sg:city":"Caringbah",
    "sg:classifiers":[
        {
            "category":"Shopping",
            "subcategory":"Stationery & Office Supplies",
            "type":"Retail Goods"
        }
    ],
    "sg:phone":"+61 2 9525 7626",
    "sg:postcode":"2229",
    "sg:province":"NSW",
    "sg:tags":[
        "equipment",
        "sailboarding"
    ],
    "wof:name":"Barracouta Sails",
    "wof:placetype":"venue"
},
  "geometry": {"coordinates":[151.1222229,-34.030380249],"type":"Point"}
}