{
  "type": "Feature",
  "properties": {
    "iso:country":"AU",
    "sg:address":"1 Ford St",
    "sg:city":"Wangaratta",
    "sg:classifiers":[
        {
            "category":"Government",
            "subcategory":"Court House",
            "type":"Public Place"
        }
    ],
    "sg:phone":"+61 3 5721 2341",
    "sg:postcode":"3676",
    "sg:province":"VIC",
    "sg:tags":[
        "personal",
        "marriage",
        "family",
        "counselling"
    ],
    "wof:name":"Centacare",
    "wof:placetype":"venue"
},
  "geometry": {"coordinates":[146.324326,-36.356522],"type":"Point"}
}