{
  "type": "Feature",
  "properties": {
    "addr:full":"333 Hawkesbury Rd Winmalee NSW 2777",
    "addr:housenumber":"333",
    "addr:postcode":"2777",
    "addr:street":"Hawkesbury Rd",
    "iso:country":"AU",
    "sg:address":"333 Hawkesbury Rd",
    "sg:city":"Winmalee",
    "sg:classifiers":[
        {
            "category":"Government",
            "subcategory":"Post Office",
            "type":"Public Place"
        }
    ],
    "sg:phone":"+61 411 428 441",
    "sg:postcode":"2777",
    "sg:province":"NSW",
    "sg:tags":[
        "silo"
    ],
    "wof:name":"Cougar Silo Clean Out & Bulk Product Removal",
    "wof:placetype":"venue"
},
  "geometry": {"coordinates":[150.60310363799999,-33.6791229248],"type":"Point"}
}