{
  "type": "Feature",
  "properties": {
    "iso:country":"AU",
    "sg:address":"Shop 17",
    "sg:city":"Mirrabooka Square Shopng Cntr Mirrabooka",
    "sg:classifiers":[
        {
            "category":"Shopping",
            "subcategory":"Clothing, Apparel, & Fashions",
            "type":"Retail Goods"
        }
    ],
    "sg:phone":"+61 8 9344 1595",
    "sg:postcode":"6061",
    "sg:province":"WA",
    "sg:tags":[
        "lady",
        "wear"
    ],
    "wof:name":"Sussan Lingerie & Sportswear",
    "wof:placetype":"venue"
},
  "geometry": {"coordinates":[115.854911804,-31.8537921906],"type":"Point"}
}