{
  "type": "Feature",
  "properties": {
    "iso:country":"AU",
    "sg:address":"McCrae St",
    "sg:city":"Longwarry",
    "sg:classifiers":[
        {
            "category":"Education",
            "subcategory":"School",
            "type":"Public Place"
        }
    ],
    "sg:phone":"+61 3 5629 9376",
    "sg:postcode":"3816",
    "sg:province":"VIC",
    "sg:tags":[
        "state",
        "except",
        "nsw"
    ],
    "wof:name":"Longwarry Primary School",
    "wof:placetype":"venue"
},
  "geometry": {"coordinates":[145.769714,-38.113579],"type":"Point"}
}