{
  "type": "Feature",
  "properties": {
    "iso:country":"AU",
    "sg:address":"Unit 1/ 10 Fitzgerald Rd",
    "sg:city":"Laverton North",
    "sg:classifiers":[
        {
            "category":"Shopping",
            "subcategory":"Stationery & Office Supplies",
            "type":"Retail Goods"
        }
    ],
    "sg:phone":"+61 3 9369 0711",
    "sg:postcode":"3026",
    "sg:province":"VIC",
    "sg:tags":[
        "packaging",
        "material"
    ],
    "wof:name":"Cyklop Secura Pty Ltd",
    "wof:placetype":"venue"
},
  "geometry": {"coordinates":[144.791718,-37.782707],"type":"Point"}
}