{
  "type": "Feature",
  "properties": {
    "iso:country":"AU",
    "sg:address":"114b Nepean Hwy",
    "sg:city":"Seaford",
    "sg:classifiers":[
        {
            "category":"Personal",
            "subcategory":"Beauty Salon",
            "type":"Services"
        }
    ],
    "sg:phone":"+61 3 9786 0292",
    "sg:postcode":"3198",
    "sg:province":"VIC",
    "sg:tags":[
        "hairdresser"
    ],
    "wof:name":"Here For Hair",
    "wof:placetype":"venue"
},
  "geometry": {"coordinates":[145.12612915,-38.1019630432],"type":"Point"}
}