{
  "type": "Feature",
  "properties": {
    "iso:country":"AU",
    "sg:address":"354 Burwood Hwy",
    "sg:city":"Burwood",
    "sg:classifiers":[
        {
            "category":"Health Services",
            "subcategory":"Health Practitioner",
            "type":"Services"
        }
    ],
    "sg:phone":"+61 3 9808 9555",
    "sg:postcode":"3125",
    "sg:province":"VIC",
    "sg:tags":[
        "osteopath"
    ],
    "wof:name":"Burwood Musculo-Skeletal",
    "wof:placetype":"venue"
},
  "geometry": {"coordinates":[145.16558837900001,-37.8546295166],"type":"Point"}
}