{
  "type": "Feature",
  "properties": {
    "addr:full":"715 Glenhuntly Rd Caulfield South VIC 3162",
    "addr:housenumber":"715",
    "addr:postcode":"3162",
    "addr:street":"Glenhuntly Rd",
    "iso:country":"AU",
    "sg:address":"715 Glenhuntly Rd",
    "sg:city":"Caulfield South",
    "sg:classifiers":[
        {
            "category":"Building & Trades",
            "subcategory":"Construction",
            "type":"Services"
        }
    ],
    "sg:phone":"+61 3 9544 5325",
    "sg:postcode":"3162",
    "sg:province":"VIC",
    "sg:tags":[
        "rendering",
        "cement"
    ],
    "wof:name":"Solidtex Rendering Pty Ltd",
    "wof:placetype":"venue"
},
  "geometry": {"coordinates":[145.01951599099999,-37.8864402771],"type":"Point"}
}