{
  "type": "Feature",
  "properties": {
    "addr:full":"Unit 2/ 11 Stoddart Rd Prospect NSW 2148",
    "addr:housenumber":"11",
    "addr:postcode":"2148",
    "addr:street":"Stoddart Rd",
    "iso:country":"AU",
    "sg:address":"Unit 2/ 11 Stoddart Rd",
    "sg:city":"Prospect",
    "sg:classifiers":[
        {
            "category":"Retail",
            "subcategory":"Auto Repair",
            "type":"Services"
        }
    ],
    "sg:phone":"+61 2 9896 1343",
    "sg:postcode":"2148",
    "sg:province":"NSW",
    "sg:tags":[
        "electrical"
    ],
    "wof:name":"A B M Automotive Repairs",
    "wof:placetype":"venue"
},
  "geometry": {"coordinates":[150.92198181099999,-33.8001785278],"type":"Point"}
}