{
  "type": "Feature",
  "properties": {
    "iso:country":"AU",
    "sg:address":"8 Elizabeth St",
    "sg:city":"Kensington",
    "sg:classifiers":[
        {
            "category":"Manufacturing",
            "subcategory":"Furniture",
            "type":"Manufacturing & Wholesale Goods"
        }
    ],
    "sg:phone":"+61 3 9372 1427",
    "sg:postcode":"3031",
    "sg:province":"VIC",
    "sg:tags":[
        "builder",
        "designer",
        "custom"
    ],
    "wof:name":"Deep in the Woods",
    "wof:placetype":"venue"
},
  "geometry": {"coordinates":[144.93211400000001,-37.796501],"type":"Point"}
}