{
  "type": "Feature",
  "properties": {
    "addr:full":"10 Hunter St North Balgowlah NSW 2093",
    "addr:housenumber":"10",
    "addr:postcode":"2093",
    "addr:street":"Hunter St",
    "iso:country":"AU",
    "sg:address":"10 Hunter St",
    "sg:city":"North Balgowlah",
    "sg:classifiers":[
        {
            "category":"Building & Trades",
            "subcategory":"Construction",
            "type":"Services"
        }
    ],
    "sg:phone":"+61 408 166 424",
    "sg:postcode":"2093",
    "sg:province":"NSW",
    "sg:tags":[
        "renovation",
        "alterations",
        "extension",
        "contractor"
    ],
    "wof:name":"Integrity Building & Pest Inspections",
    "wof:placetype":"venue"
},
  "geometry": {"coordinates":[151.24974060100001,-33.7888755798],"type":"Point"}
}