{
  "type": "Feature",
  "properties": {
    "addr:full":"2 Quartz Quarry Rd South Hedland WA 6722",
    "addr:housenumber":"2",
    "addr:postcode":"6722",
    "addr:street":"Quartz Quarry Rd",
    "iso:country":"AU",
    "sg:address":"2 Quartz Quarry Rd",
    "sg:city":"South Hedland",
    "sg:classifiers":[
        {
            "category":"Building & Trades",
            "subcategory":"Construction",
            "type":"Services"
        }
    ],
    "sg:phone":"+61 8 9172 5659",
    "sg:postcode":"6722",
    "sg:province":"WA",
    "sg:tags":[
        "earth",
        "excavating",
        "moving",
        "contractor"
    ],
    "wof:name":"Pilbara Earthmoving",
    "wof:placetype":"venue"
},
  "geometry": {"coordinates":[118.575286865,-20.423374176],"type":"Point"}
}