{
  "type": "Feature",
  "properties": {
    "addr:full":"PO Box 148 Eudunda SA 5374",
    "addr:postcode":"5374",
    "iso:country":"AU",
    "sg:address":"PO Box 148",
    "sg:city":"Eudunda",
    "sg:classifiers":[
        {
            "category":"Building & Trades",
            "subcategory":"Construction",
            "type":"Services"
        }
    ],
    "sg:phone":"+61 8 8581 1840",
    "sg:postcode":"5374",
    "sg:province":"SA",
    "sg:tags":[
        "spouting",
        "guttering"
    ],
    "wof:name":"Turn-Rite Engineering",
    "wof:placetype":"venue"
},
  "geometry": {"coordinates":[139.08688354500001,-34.1767807007],"type":"Point"}
}