{
  "type": "Feature",
  "properties": {
    "addr:full":"8 Barnes St Mt Isa QLD 4825",
    "addr:housenumber":"8",
    "addr:postcode":"4825",
    "addr:street":"Barnes St",
    "iso:country":"AU",
    "sg:address":"8 Barnes St",
    "sg:city":"Mt Isa",
    "sg:classifiers":[
        {
            "category":"Retail",
            "subcategory":"Auto Repair",
            "type":"Services"
        }
    ],
    "sg:phone":"+61 7 4743 4807",
    "sg:postcode":"4825",
    "sg:province":"QLD",
    "sg:tags":[
        "repairer",
        "motor",
        "engineer"
    ],
    "wof:name":"Brogden Kevin",
    "wof:placetype":"venue"
},
  "geometry": {"coordinates":[139.497604,-20.69698],"type":"Point"}
}