{
  "type": "Feature",
  "properties": {
    "addr:full":"Sth Gippsland Hwy Koonwarra VIC 3954",
    "addr:postcode":"3954",
    "addr:street":"Sth Gippsland Hwy Koonwarra",
    "iso:country":"AU",
    "sg:address":"Sth Gippsland Hwy",
    "sg:city":"Koonwarra",
    "sg:classifiers":[
        {
            "category":"Travel",
            "subcategory":"Hotels & Motels",
            "type":"Entertainment"
        }
    ],
    "sg:phone":"+61 3 5664 2488",
    "sg:postcode":"3954",
    "sg:province":"VIC",
    "wof:name":"Koonwarra Cottages",
    "wof:placetype":"venue"
},
  "geometry": {"coordinates":[145.949783325,-38.5595436096],"type":"Point"}
}