{
  "type": "Feature",
  "properties": {
    "addr:full":"137 Mornington Rd Mornington TAS 7018",
    "addr:housenumber":"137",
    "addr:postcode":"7018",
    "addr:street":"Mornington Rd",
    "iso:country":"AU",
    "sg:address":"137 Mornington Rd",
    "sg:city":"Mornington",
    "sg:classifiers":[
        {
            "category":"Retail",
            "subcategory":"Repair Shop",
            "type":"Services"
        }
    ],
    "sg:phone":"+61 3 6244 5210",
    "sg:postcode":"7018",
    "sg:province":"TAS",
    "sg:tags":[
        "upholsterer"
    ],
    "wof:name":"McPhersons Auto & Marine Trimmers",
    "wof:placetype":"venue"
},
  "geometry": {"coordinates":[147.40408325199999,-42.8603363037],"type":"Point"}
}