{
  "type": "Feature",
  "properties": {
    "iso:country":"AU",
    "sg:address":"467a North East Rd",
    "sg:city":"Hillcrest",
    "sg:classifiers":[
        {
            "category":"Autos & Motor Vehicles",
            "subcategory":"Auto Supplies",
            "type":"Retail Goods"
        }
    ],
    "sg:phone":"+61 8 8266 7969",
    "sg:postcode":"5086",
    "sg:province":"SA",
    "sg:tags":[
        "accessory"
    ],
    "wof:name":"Hilltop Crash Repairs",
    "wof:placetype":"venue"
},
  "geometry": {"coordinates":[138.64855957,-34.8621864319],"type":"Point"}
}