{
  "type": "Feature",
  "properties": {
    "iso:country":"AU",
    "sg:address":"Level 2, 60 Stirling St",
    "sg:city":"Perth",
    "sg:classifiers":[
        {
            "category":"Personal",
            "subcategory":"Beauty Salon",
            "type":"Services"
        }
    ],
    "sg:phone":"+61 8 9228 4611",
    "sg:postcode":"6000",
    "sg:province":"WA",
    "wof:name":"Australian College of Beauty Therapy",
    "wof:placetype":"venue"
},
  "geometry": {"coordinates":[115.86370086700001,-31.9499111176],"type":"Point"}
}