{
  "type": "Feature",
  "properties": {
    "iso:country":"AU",
    "sg:address":"116 Mossfiel Drv",
    "sg:city":"Hoppers Crossing",
    "sg:classifiers":[
        {
            "category":"Sports & Exercise",
            "subcategory":"Gym",
            "type":"Entertainment"
        }
    ],
    "sg:phone":"+61 3 9749 6422",
    "sg:postcode":"3029",
    "sg:province":"VIC",
    "sg:tags":[
        "health",
        "fitness"
    ],
    "wof:name":"Genesis Fitness Club",
    "wof:placetype":"venue"
},
  "geometry": {"coordinates":[144.690903,-37.869228],"type":"Point"}
}