{
  "type": "Feature",
  "properties": {
    "addr:full":"15 Meadowgate Drv Chirnside Park VIC 3116",
    "addr:housenumber":"15",
    "addr:postcode":"3116",
    "addr:street":"Meadowgate Drv",
    "iso:country":"AU",
    "sg:address":"15 Meadowgate Drv",
    "sg:city":"Chirnside Park",
    "sg:classifiers":[
        {
            "category":"Professional",
            "subcategory":"Accounting & Tax Preparation",
            "type":"Services"
        }
    ],
    "sg:phone":"+61 3 9727 5480",
    "sg:postcode":"3116",
    "sg:province":"VIC",
    "sg:tags":[
        "bookkeeping"
    ],
    "wof:name":"Dolphin Bookkeeping & Secretarial Services",
    "wof:placetype":"venue"
},
  "geometry": {"coordinates":[145.32518005399999,-37.757232666],"type":"Point"}
}