{
  "type": "Feature",
  "properties": {
    "addr:full":"1 Wilkins St Newport VIC 3015",
    "addr:housenumber":"1",
    "addr:postcode":"3015",
    "addr:street":"Wilkins St",
    "iso:country":"AU",
    "sg:address":"1 Wilkins St",
    "sg:city":"Newport",
    "sg:classifiers":[
        {
            "category":"Building & Trades",
            "subcategory":"Landscaping Services",
            "type":"Services"
        }
    ],
    "sg:phone":"+61 3 9398 0609",
    "sg:postcode":"3015",
    "sg:province":"VIC",
    "sg:tags":[
        "forestry",
        "consultant"
    ],
    "wof:name":"Arianda Pty Ltd",
    "wof:placetype":"venue"
},
  "geometry": {"coordinates":[144.89176940900001,-37.8470954895],"type":"Point"}
}