{
  "type": "Feature",
  "properties": {
    "iso:country":"AU",
    "sg:address":"52 Kendall Rd",
    "sg:city":"Kendall",
    "sg:classifiers":[
        {
            "category":"Retail",
            "subcategory":"Auto Repair",
            "type":"Services"
        }
    ],
    "sg:phone":"+61 2 6559 0147",
    "sg:postcode":"2439",
    "sg:province":"NSW",
    "sg:tags":[
        "repairer",
        "motor",
        "engineer"
    ],
    "wof:name":"G.T.H Automotive",
    "wof:placetype":"venue"
},
  "geometry": {"coordinates":[152.72389200000001,-31.634041],"type":"Point"}
}