{
  "type": "Feature",
  "properties": {
    "iso:country":"AU",
    "sg:address":"Shop 3 118 Prince St",
    "sg:city":"Clarence Town",
    "sg:classifiers":[
        {
            "category":"Banks & Credit Unions",
            "subcategory":"Financial Services",
            "type":"Services"
        }
    ],
    "sg:phone":"+61 13 19 87",
    "sg:postcode":"2321",
    "sg:province":"NSW",
    "sg:tags":[
        "building",
        "society"
    ],
    "wof:name":"Newcastle Permanent Building Society Ltd",
    "wof:placetype":"venue"
},
  "geometry": {"coordinates":[151.77792358400001,-32.586101532],"type":"Point"}
}