{
  "type": "Feature",
  "properties": {
    "addr:full":"28 Bowra St Nambucca Heads NSW 2448",
    "addr:housenumber":"28",
    "addr:postcode":"2448",
    "addr:street":"Bowra St",
    "iso:country":"AU",
    "sg:address":"28 Bowra St",
    "sg:city":"Nambucca Heads",
    "sg:classifiers":[
        {
            "category":"Food & Beverages",
            "subcategory":"Groceries & Convenience Stores",
            "type":"Retail Goods"
        }
    ],
    "sg:phone":"+61 2 6568 6266",
    "sg:postcode":"2448",
    "sg:province":"NSW",
    "wof:name":"5 Star Handimarket",
    "wof:placetype":"venue"
},
  "geometry": {"coordinates":[153.00199900000001,-30.641392],"type":"Point"}
}