{
  "type": "Feature",
  "properties": {
    "addr:full":"Queens Park Goleby St Ipswich QLD 4305",
    "addr:postcode":"4305",
    "addr:street":"St",
    "iso:country":"AU",
    "sg:address":"Queens Park Goleby St",
    "sg:city":"Ipswich",
    "sg:classifiers":[
        {
            "category":"Manufacturing",
            "subcategory":"Furniture",
            "type":"Manufacturing & Wholesale Goods"
        }
    ],
    "sg:phone":"+61 7 3202 2882",
    "sg:postcode":"4305",
    "sg:province":"QLD",
    "sg:tags":[
        "builder",
        "designer",
        "custom"
    ],
    "wof:name":"Design for Production",
    "wof:placetype":"venue"
},
  "geometry": {"coordinates":[152.766921997,-27.6183795929],"type":"Point"}
}