{
  "type": "Feature",
  "properties": {
    "addr:full":"408 Scarborough Beach Rd Osborne Park WA 6017",
    "addr:housenumber":"408",
    "addr:postcode":"6017",
    "addr:street":"Scarborough Beach Rd",
    "iso:country":"AU",
    "sg:address":"408 Scarborough Beach Rd",
    "sg:city":"Osborne Park",
    "sg:classifiers":[
        {
            "category":"Manufacturing",
            "subcategory":"Apparel",
            "type":"Manufacturing & Wholesale Goods"
        }
    ],
    "sg:phone":"+61 8 9444 6344",
    "sg:postcode":"6017",
    "sg:province":"WA",
    "sg:tags":[
        "makers-up",
        "clothing"
    ],
    "wof:name":"Sunset Coast Leisure Wear",
    "wof:placetype":"venue"
},
  "geometry": {"coordinates":[115.813621521,-31.9097099304],"type":"Point"}
}