{
  "type": "Feature",
  "properties": {
    "addr:full":"8 Franklin St Swansea TAS 7190",
    "addr:housenumber":"8",
    "addr:postcode":"7190",
    "addr:street":"Franklin St",
    "iso:country":"AU",
    "sg:address":"8 Franklin St",
    "sg:city":"Swansea",
    "sg:classifiers":[
        {
            "category":"Food & Beverages",
            "subcategory":"Supermarket",
            "type":"Retail Goods"
        }
    ],
    "sg:phone":"+61 3 6257 8118",
    "sg:postcode":"7190",
    "sg:province":"TAS",
    "sg:tags":[
        "grocery",
        "store"
    ],
    "wof:name":"Swansea Corner Store",
    "wof:placetype":"venue"
},
  "geometry": {"coordinates":[148.07725500000001,-42.124687],"type":"Point"}
}