{
  "type": "Feature",
  "properties": {
    "addr:full":"Suite 1 / 519 Pacific Hwy Mt Colah NSW 2079",
    "addr:housenumber":"/ 519",
    "addr:postcode":"2079",
    "addr:street":"Pacific Hwy Mt Colah",
    "iso:country":"AU",
    "sg:address":"Suite 1 / 519 Pacific Hwy",
    "sg:city":"Mt Colah",
    "sg:classifiers":[
        {
            "category":"Health Services",
            "subcategory":"Doctor",
            "type":"Services"
        }
    ],
    "sg:phone":"+61 2 9482 2227",
    "sg:postcode":"2079",
    "sg:province":"NSW",
    "sg:tags":[
        "podiatrist"
    ],
    "wof:name":"Hornsby & Asquith Podiatry",
    "wof:placetype":"venue"
},
  "geometry": {"coordinates":[151.111724853,-33.6779785156],"type":"Point"}
}