{
  "type": "Feature",
  "properties": {
    "addr:full":"8a Concorde Crs Werribee VIC 3030",
    "addr:housenumber":"8a",
    "addr:postcode":"3030",
    "addr:street":"Concorde Crs",
    "iso:country":"AU",
    "sg:address":"8a Concorde Crs",
    "sg:city":"Werribee",
    "sg:classifiers":[
        {
            "category":"Building & Trades",
            "subcategory":"Construction",
            "type":"Services"
        }
    ],
    "sg:phone":"+61 3 9742 7700",
    "sg:postcode":"3030",
    "sg:province":"VIC",
    "sg:tags":[
        "welding"
    ],
    "wof:name":"Domestic & Industrial Welding Services",
    "wof:placetype":"venue"
},
  "geometry": {"coordinates":[144.659637,-37.903702],"type":"Point"}
}