{
  "type": "Feature",
  "properties": {
    "iso:country":"AU",
    "sg:address":"351 Riley St",
    "sg:city":"Surry Hills",
    "sg:classifiers":[
        {
            "category":"Personal",
            "subcategory":"Beauty Salon",
            "type":"Services"
        }
    ],
    "sg:phone":"+61 2 9212 6647",
    "sg:postcode":"2010",
    "sg:province":"NSW",
    "sg:tags":[
        "hairdresser"
    ],
    "wof:name":"Topiary Haircutters",
    "wof:placetype":"venue"
},
  "geometry": {"coordinates":[151.21273803700001,-33.8841705322],"type":"Point"}
}