{
  "type": "Feature",
  "properties": {
    "iso:country":"AU",
    "sg:address":"1 Nepean Pl",
    "sg:city":"Sylvania Waters",
    "sg:classifiers":[
        {
            "category":"Professional",
            "subcategory":"Employment Agencies",
            "type":"Services"
        }
    ],
    "sg:phone":"+61 408 009 376",
    "sg:postcode":"2224",
    "sg:province":"NSW",
    "sg:tags":[
        "provider",
        "internet"
    ],
    "wof:name":"Digital Home Page",
    "wof:placetype":"venue"
},
  "geometry": {"coordinates":[151.11273193400001,-34.0126953125],"type":"Point"}
}