{
  "type": "Feature",
  "properties": {
    "addr:full":"1862 Albany Hwy Maddington WA 6109",
    "addr:housenumber":"1862",
    "addr:postcode":"6109",
    "addr:street":"Albany Hwy",
    "iso:country":"AU",
    "sg:address":"1862 Albany Hwy",
    "sg:city":"Maddington",
    "sg:classifiers":[
        {
            "category":"Building & Trades",
            "subcategory":"Construction",
            "type":"Services"
        }
    ],
    "sg:phone":"+61 13 84 68",
    "sg:postcode":"6109",
    "sg:province":"WA",
    "sg:tags":[
        "window",
        "tinting"
    ],
    "wof:name":"Tint.A.Car",
    "wof:placetype":"venue"
},
  "geometry": {"coordinates":[115.98034668,-32.0494422913],"type":"Point"}
}