{
  "type": "Feature",
  "properties": {
    "addr:full":"Berrigan Rd Monaro Vale NSW 2712",
    "addr:postcode":"2712",
    "addr:street":"Berrigan Rd",
    "iso:country":"AU",
    "sg:address":"Berrigan Rd",
    "sg:city":"Monaro Vale",
    "sg:classifiers":[
        {
            "category":"Farming",
            "subcategory":"Farm",
            "type":"Manufacturing & Wholesale Goods"
        }
    ],
    "sg:phone":"+61 3 5885 8225",
    "sg:postcode":"2712",
    "sg:province":"NSW",
    "sg:tags":[
        "farmer"
    ],
    "wof:name":"Lee G J",
    "wof:placetype":"venue"
},
  "geometry": {"coordinates":[145.78828430199999,-35.7472457886],"type":"Point"}
}