{
  "type": "Feature",
  "properties": {
    "iso:country":"AU",
    "sg:address":"50 George St",
    "sg:city":"Thebarton",
    "sg:classifiers":[
        {
            "category":"Home & Garden",
            "subcategory":"Hardware",
            "type":"Retail Goods"
        }
    ],
    "sg:phone":"+61 8 8234 0444",
    "sg:postcode":"5031",
    "sg:province":"SA",
    "sg:tags":[
        "trolley",
        "truck",
        "hand"
    ],
    "wof:name":"Team Teamstar Trolleys",
    "wof:placetype":"venue"
},
  "geometry": {"coordinates":[138.57545471200001,-34.9186134338],"type":"Point"}
}