{
  "type": "Feature",
  "properties": {
    "addr:full":"272 Redbank Plains Rd Bellbird Park QLD 4300",
    "addr:housenumber":"272",
    "addr:postcode":"4300",
    "addr:street":"Redbank Plains Rd",
    "iso:country":"AU",
    "sg:address":"272 Redbank Plains Rd",
    "sg:city":"Bellbird Park",
    "sg:classifiers":[
        {
            "category":"Home & Garden",
            "subcategory":"Building Materials",
            "type":"Retail Goods"
        }
    ],
    "sg:phone":"+61 408 870 264",
    "sg:postcode":"4300",
    "sg:province":"QLD",
    "sg:tags":[
        "retaining",
        "wall"
    ],
    "sg:website":"http://www.samssandstone.com.au",
    "wof:name":"Sams Sandstone Rocks",
    "wof:placetype":"venue"
},
  "geometry": {"coordinates":[152.872146606,-27.6428661346],"type":"Point"}
}