{
  "type": "Feature",
  "properties": {
    "addr:full":"Reid St Strahan TAS 7468",
    "addr:postcode":"7468",
    "addr:street":"Reid St",
    "iso:country":"AU",
    "sg:address":"Reid St",
    "sg:city":"Strahan",
    "sg:classifiers":[
        {
            "category":"Autos & Motor Vehicles",
            "subcategory":"Fuel & Gas Station",
            "type":"Retail Goods"
        }
    ],
    "sg:phone":"+61 3 6471 7218",
    "sg:postcode":"7468",
    "sg:province":"TAS",
    "wof:name":"BP Australia Limited",
    "wof:placetype":"venue"
},
  "geometry": {"coordinates":[145.32800293,-42.1507263184],"type":"Point"}
}