{
  "type": "Feature",
  "properties": {
    "addr:full":"PO Box 2287 Clovelly West NSW 2031",
    "addr:postcode":"2031",
    "iso:country":"AU",
    "sg:address":"PO Box 2287",
    "sg:city":"Clovelly West",
    "sg:classifiers":[
        {
            "category":"Shopping",
            "subcategory":"Party Supplies",
            "type":"Retail Goods"
        }
    ],
    "sg:phone":"+61 2 9665 0498",
    "sg:postcode":"2031",
    "sg:province":"NSW",
    "wof:name":"Celebrate Special Events",
    "wof:placetype":"venue"
},
  "geometry": {"coordinates":[151.25686645499999,-33.9094581604],"type":"Point"}
}