{
  "type": "Feature",
  "properties": {
    "iso:country":"AU",
    "sg:address":"11 Killarney Ave",
    "sg:city":"Manly West",
    "sg:classifiers":[
        {
            "category":"Sports & Exercise",
            "subcategory":"Gym",
            "type":"Entertainment"
        }
    ],
    "sg:phone":"+61 412 217 735",
    "sg:postcode":"4179",
    "sg:province":"QLD",
    "sg:tags":[
        "personal",
        "trainer",
        "fitness"
    ],
    "wof:name":"Personal Challenge Fitness Training",
    "wof:placetype":"venue"
},
  "geometry": {"coordinates":[153.178497314,-27.4626789093],"type":"Point"}
}