{
  "type": "Feature",
  "properties": {
    "addr:full":"10 Louise Simon Crt Leongatha VIC 3953",
    "addr:housenumber":"10",
    "addr:postcode":"3953",
    "addr:street":"Louise Simon Crt",
    "iso:country":"AU",
    "sg:address":"10 Louise Simon Crt",
    "sg:city":"Leongatha",
    "sg:classifiers":[
        {
            "category":"Building & Trades",
            "subcategory":"Construction",
            "type":"Services"
        }
    ],
    "sg:phone":"+61 3 5662 2117",
    "sg:postcode":"3953",
    "sg:province":"VIC",
    "sg:tags":[
        "contractor"
    ],
    "wof:name":"Heppell Bros.Construction Pty.Ltd.",
    "wof:placetype":"venue"
},
  "geometry": {"coordinates":[145.960571289,-38.4804916382],"type":"Point"}
}