{
  "type": "Feature",
  "properties": {
    "addr:full":"Arnold St (Cnr Dijon St) Katanning WA 6317",
    "addr:postcode":"6317",
    "addr:street":"Arnold St Cnr Dijon St",
    "iso:country":"AU",
    "sg:address":"Arnold St",
    "sg:city":"(Cnr Dijon St) Katanning",
    "sg:classifiers":[
        {
            "category":"Wholesale",
            "subcategory":"Auto Parts",
            "type":"Manufacturing & Wholesale Goods"
        }
    ],
    "sg:phone":"+61 8 9821 1733",
    "sg:postcode":"6317",
    "sg:province":"WA",
    "sg:tags":[
        "recyclers"
    ],
    "wof:name":"Katanning Wreckers",
    "wof:placetype":"venue"
},
  "geometry": {"coordinates":[117.566329956,-33.6983718872],"type":"Point"}
}