{
  "type": "Feature",
  "properties": {
    "iso:country":"AU",
    "sg:address":"Cnr Old Bathurst Rd",
    "sg:city":"Emu Plains",
    "sg:classifiers":[
        {
            "category":"Autos & Motor Vehicles",
            "subcategory":"Auto Supplies",
            "type":"Retail Goods"
        }
    ],
    "sg:phone":"+61 2 4735 2044",
    "sg:postcode":"2750",
    "sg:province":"NSW",
    "sg:tags":[
        "camper-trailers",
        "caravan",
        "equipment"
    ],
    "wof:name":"Sydney Caravans",
    "wof:placetype":"venue"
},
  "geometry": {"coordinates":[150.65948486299999,-33.7425689697],"type":"Point"}
}