{
  "type": "Feature",
  "properties": {
    "addr:full":"20A Kanowna St Hastings VIC 3915",
    "addr:housenumber":"20a",
    "addr:postcode":"3915",
    "addr:street":"Kanowna St",
    "iso:country":"AU",
    "sg:address":"20A Kanowna St",
    "sg:city":"Hastings",
    "sg:classifiers":[
        {
            "category":"Utilities",
            "subcategory":"Refuse",
            "type":"Services"
        }
    ],
    "sg:phone":"+61 1300 304 944",
    "sg:postcode":"3915",
    "sg:province":"VIC",
    "sg:tags":[
        "remover",
        "rubbish"
    ],
    "sg:website":"http://www.binsmart.net",
    "wof:name":"Bin Smart",
    "wof:placetype":"venue"
},
  "geometry": {"coordinates":[145.187423706,-38.2857322693],"type":"Point"}
}