{
  "type": "Feature",
  "properties": {
    "iso:country":"AU",
    "sg:address":"40 Murray St",
    "sg:city":"Colac",
    "sg:classifiers":[
        {
            "category":"Shopping",
            "type":"Retail Goods"
        }
    ],
    "sg:phone":"+61 3 5232 1800",
    "sg:postcode":"3250",
    "sg:province":"VIC",
    "sg:tags":[
        "agent",
        "stock"
    ],
    "wof:name":"Richardson H F & Co",
    "wof:placetype":"venue"
},
  "geometry": {"coordinates":[143.589905,-38.339741],"type":"Point"}
}