{
  "type": "Feature",
  "properties": {
    "iso:country":"AU",
    "sg:address":"40 Briant Rd",
    "sg:city":"Magill",
    "sg:classifiers":[
        {
            "category":"Personal",
            "type":"Services"
        }
    ],
    "sg:phone":"+61 8 8331 0811",
    "sg:postcode":"5072",
    "sg:province":"SA",
    "sg:tags":[
        "counselling",
        "alcohol",
        "drug"
    ],
    "wof:name":"Kahlyn Day Care",
    "wof:placetype":"venue"
},
  "geometry": {"coordinates":[138.66966247600001,-34.9169120789],"type":"Point"}
}