{
  "type": "Feature",
  "properties": {
    "iso:country":"AU",
    "sg:address":"69 Herries St",
    "sg:city":"Toowoomba",
    "sg:classifiers":[
        {
            "category":"Shopping",
            "subcategory":"Clothing, Apparel, & Fashions",
            "type":"Retail Goods"
        }
    ],
    "sg:phone":"+61 421 656 473",
    "sg:postcode":"4350",
    "sg:province":"QLD",
    "sg:tags":[
        "hire",
        "men's",
        "wear",
        "formal"
    ],
    "wof:name":"FormalWear Express Mobile Suit Hire",
    "wof:placetype":"venue"
},
  "geometry": {"coordinates":[151.93838500000001,-27.562307],"type":"Point"}
}