{
  "type": "Feature",
  "properties": {
    "addr:full":"131 Coromandel Rd Ebenezer NSW 2756",
    "addr:housenumber":"131",
    "addr:postcode":"2756",
    "addr:street":"Coromandel Rd",
    "iso:country":"AU",
    "sg:address":"131 Coromandel Rd",
    "sg:city":"Ebenezer",
    "sg:classifiers":[
        {
            "category":"Building & Trades",
            "subcategory":"Construction",
            "type":"Services"
        }
    ],
    "sg:phone":"+61 2 4579 9457",
    "sg:postcode":"2756",
    "sg:province":"NSW",
    "sg:tags":[
        "home",
        "air conditioning"
    ],
    "wof:name":"Rodney Pace Air",
    "wof:placetype":"venue"
},
  "geometry": {"coordinates":[150.89207458499999,-33.5360412598],"type":"Point"}
}