{
  "type": "Feature",
  "properties": {
    "addr:full":"PO Box 1058 Mt Gambier SA 5290",
    "addr:postcode":"5290",
    "iso:country":"AU",
    "sg:address":"PO Box 1058",
    "sg:city":"Mt Gambier",
    "sg:classifiers":[
        {
            "category":"Professional",
            "subcategory":"Business Services",
            "type":"Services"
        }
    ],
    "sg:phone":"+61 8 8725 7184",
    "sg:postcode":"5290",
    "sg:province":"SA",
    "sg:tags":[
        "livestock",
        "transport"
    ],
    "wof:name":"Crouch Richard J Livestock Carrier",
    "wof:placetype":"venue"
},
  "geometry": {"coordinates":[140.78329500000001,-37.826321],"type":"Point"}
}