{
  "type": "Feature",
  "properties": {
    "addr:full":"470 David St Albury NSW 2640",
    "addr:housenumber":"470",
    "addr:postcode":"2640",
    "addr:street":"David St",
    "iso:country":"AU",
    "sg:address":"470 David St",
    "sg:city":"Albury",
    "sg:classifiers":[
        {
            "category":"Banks & Credit Unions",
            "subcategory":"Financial Services",
            "type":"Services"
        }
    ],
    "sg:phone":"+61 2 6021 8552",
    "sg:postcode":"2640",
    "sg:province":"NSW",
    "sg:tags":[
        "planning"
    ],
    "wof:name":"Taskis Financial Planning Services",
    "wof:placetype":"venue"
},
  "geometry": {"coordinates":[146.92056274399999,-36.0829696655],"type":"Point"}
}