{
  "type": "Feature",
  "properties": {
    "addr:full":"PO Box 85 Gosnells PLB WA 6990",
    "addr:postcode":"6990",
    "iso:country":"AU",
    "sg:address":"PO Box 85",
    "sg:city":"Gosnells PLB",
    "sg:classifiers":[
        {
            "category":"Building & Trades",
            "subcategory":"Construction",
            "type":"Services"
        }
    ],
    "sg:phone":"+61 402 274 150",
    "sg:postcode":"6990",
    "sg:province":"WA",
    "sg:tags":[
        "fencing",
        "contractor"
    ],
    "wof:name":"Eiffler SA",
    "wof:placetype":"venue"
},
  "geometry": {"coordinates":[116.002357,-32.07201],"type":"Point"}
}