{
  "type": "Feature",
  "properties": {
    "addr:full":"180 Herries St Toowoomba QLD 4350",
    "addr:housenumber":"180",
    "addr:postcode":"4350",
    "addr:street":"Herries St",
    "iso:country":"AU",
    "sg:address":"180 Herries St",
    "sg:city":"Toowoomba",
    "sg:classifiers":[
        {
            "category":"Wholesale",
            "subcategory":"Painting Supplies",
            "type":"Manufacturing & Wholesale Goods"
        }
    ],
    "sg:phone":"+61 7 4632 4811",
    "sg:postcode":"4350",
    "sg:province":"QLD",
    "sg:tags":[
        "painter"
    ],
    "wof:name":"Wattyl (Queensland)",
    "wof:placetype":"venue"
},
  "geometry": {"coordinates":[151.935913,-27.562004],"type":"Point"}
}