{
  "type": "Feature",
  "properties": {
    "addr:full":"Retail Pastry Shop 7/2705 Main Place, Gold Coast Hwy Broadbeach QLD 4218",
    "addr:housenumber":"7 / 2705",
    "addr:postcode":"4218",
    "addr:street":"Main Place Gold Coast Hwy",
    "iso:country":"AU",
    "sg:address":"Retail Pastry Shop 7/2705 Main Place, Gold Coast Hwy",
    "sg:city":"Broadbeach",
    "sg:classifiers":[
        {
            "category":"Food & Beverages",
            "subcategory":"Bakery",
            "type":"Retail Goods"
        }
    ],
    "sg:phone":"+61 7 5570 2207",
    "sg:postcode":"4218",
    "sg:province":"QLD",
    "sg:tags":[
        "cake",
        "shop",
        "pastry"
    ],
    "wof:name":"Yenmart Pastry Art",
    "wof:placetype":"venue"
},
  "geometry": {"coordinates":[153.429412842,-28.0263671875],"type":"Point"}
}