{
  "type": "Feature",
  "properties": {
    "addr:full":"Suite 7 (upstairs) 41 Sunshine Beach Rd Noosa Junction QLD 4567",
    "addr:housenumber":"41",
    "addr:postcode":"4567",
    "addr:street":"Sunshine Beach Rd",
    "iso:country":"AU",
    "sg:address":"Suite 7 (upstairs) 41 Sunshine Beach Rd",
    "sg:city":"Noosa Junction",
    "sg:classifiers":[
        {
            "category":"Personal",
            "type":"Services"
        }
    ],
    "sg:phone":"+61 7 5448 0059",
    "sg:postcode":"4567",
    "sg:province":"QLD",
    "sg:tags":[
        "reducing",
        "treatment",
        "weight"
    ],
    "wof:name":"The Transformation Clinic",
    "wof:placetype":"venue"
},
  "geometry": {"coordinates":[153.09327697800001,-26.3989963531],"type":"Point"}
}