{
  "type": "Feature",
  "properties": {
    "addr:full":"15 Morrow St Cnr Moggill Rd Taringa QLD 4068",
    "addr:housenumber":"15",
    "addr:postcode":"4068",
    "addr:street":"Morrow St Cnr Moggill Rd",
    "iso:country":"AU",
    "sg:address":"15 Morrow St Cnr Moggill Rd",
    "sg:city":"Taringa",
    "sg:classifiers":[
        {
            "category":"Health Services",
            "subcategory":"Doctor",
            "type":"Services"
        }
    ],
    "sg:phone":"+61 7 3870 7239",
    "sg:postcode":"4068",
    "sg:province":"QLD",
    "sg:tags":[
        "medical",
        "practitioner"
    ],
    "wof:name":"Taringa 7 Day Medical Practice",
    "wof:placetype":"venue"
},
  "geometry": {"coordinates":[152.981323242,-27.4917469025],"type":"Point"}
}