{
  "type": "Feature",
  "properties": {
    "iso:country":"AU",
    "sg:address":"28 Murphy St",
    "sg:city":"Invermay",
    "sg:classifiers":[
        {
            "category":"Professional",
            "type":"Services"
        }
    ],
    "sg:phone":"+61 3 6334 7577",
    "sg:postcode":"7248",
    "sg:province":"TAS",
    "sg:tags":[
        "courier"
    ],
    "wof:name":"Fastway Couriers Tasmania",
    "wof:placetype":"venue"
},
  "geometry": {"coordinates":[147.12513732900001,-41.4248847961],"type":"Point"}
}