{
  "type": "Feature",
  "properties": {
    "addr:full":"8 Regatta Rd Five Dock NSW 2046",
    "addr:housenumber":"8",
    "addr:postcode":"2046",
    "addr:street":"Regatta Rd",
    "iso:country":"AU",
    "sg:address":"8 Regatta Rd",
    "sg:city":"Five Dock",
    "sg:classifiers":[
        {
            "category":"Retail",
            "subcategory":"Auto Repair",
            "type":"Services"
        }
    ],
    "sg:phone":"+61 2 9745 3173",
    "sg:postcode":"2046",
    "sg:province":"NSW",
    "sg:tags":[
        "repairer",
        "motor",
        "engineer"
    ],
    "wof:name":"Ciano Motor Engineers",
    "wof:placetype":"venue"
},
  "geometry": {"coordinates":[151.116074,-33.86977],"type":"Point"}
}