{
  "type": "Feature",
  "properties": {
    "addr:full":"Shop 2, 102 Alfred St Milsons Point NSW 2061",
    "addr:housenumber":"shop 2 102",
    "addr:postcode":"2061",
    "addr:street":"Alfred St",
    "iso:country":"AU",
    "sg:address":"Shop 2, 102 Alfred St",
    "sg:city":"Milsons Point",
    "sg:classifiers":[
        {
            "category":"Cafe",
            "type":"Food & Drink"
        }
    ],
    "sg:phone":"+61 2 9955 4406",
    "sg:postcode":"2061",
    "sg:province":"NSW",
    "wof:name":"Cafe Impromptu",
    "wof:placetype":"venue"
},
  "geometry": {"coordinates":[151.21058654800001,-33.8443183899],"type":"Point"}
}