{
  "type": "Feature",
  "properties": {
    "addr:full":"3 Buckingham Drv Wangara WA 6065",
    "addr:housenumber":"3",
    "addr:postcode":"6065",
    "addr:street":"Buckingham Drv",
    "iso:country":"AU",
    "sg:address":"3 Buckingham Drv",
    "sg:city":"Wangara",
    "sg:classifiers":[
        {
            "category":"Autos & Motor Vehicles",
            "subcategory":"Motorcycle Sales",
            "type":"Retail Goods"
        }
    ],
    "sg:phone":"+61 8 9409 7707",
    "sg:postcode":"6065",
    "sg:province":"WA",
    "sg:tags":[
        "outboard"
    ],
    "wof:name":"Access Boating & Leisure",
    "wof:placetype":"venue"
},
  "geometry": {"coordinates":[115.812973023,-31.7875041962],"type":"Point"}
}