{
  "type": "Feature",
  "properties": {
    "addr:full":"632 Bourke St Surry Hills NSW 2010",
    "addr:housenumber":"632",
    "addr:postcode":"2010",
    "addr:street":"Bourke St",
    "iso:country":"AU",
    "sg:address":"632 Bourke St",
    "sg:city":"Surry Hills",
    "sg:classifiers":[
        {
            "category":"Real Estate",
            "subcategory":"Architect",
            "type":"Services"
        }
    ],
    "sg:phone":"+61 2 9699 3322",
    "sg:postcode":"2010",
    "sg:province":"NSW",
    "wof:name":"Pohio Adams Architects",
    "wof:placetype":"venue"
},
  "geometry": {"coordinates":[151.21472168,-33.891330719],"type":"Point"}
}