{
  "type": "Feature",
  "properties": {
    "addr:full":"25 Wimbourne Rd Mt Waverley VIC 3149",
    "addr:housenumber":"25",
    "addr:postcode":"3149",
    "addr:street":"Wimbourne Rd",
    "iso:country":"AU",
    "sg:address":"25 Wimbourne Rd",
    "sg:city":"Mt Waverley",
    "sg:classifiers":[
        {
            "category":"Organizations",
            "subcategory":"Membership Organization",
            "type":"Services"
        }
    ],
    "sg:phone":"+61 3 9807 1826",
    "sg:postcode":"3149",
    "sg:province":"VIC",
    "sg:tags":[
        "club",
        "car"
    ],
    "wof:name":"Ford Four Car Club",
    "wof:placetype":"venue"
},
  "geometry": {"coordinates":[145.12307739299999,-37.8766517639],"type":"Point"}
}