{
  "type": "Feature",
  "properties": {
    "addr:full":"U4/ 150 Terrigal Drv Terrigal NSW 2260",
    "addr:housenumber":"150",
    "addr:postcode":"2260",
    "addr:street":"U4 /;Terrigal Drv",
    "iso:country":"AU",
    "sg:address":"U4/ 150 Terrigal Drv",
    "sg:city":"Terrigal",
    "sg:classifiers":[
        {
            "category":"Shopping",
            "subcategory":"Antiques",
            "type":"Retail Goods"
        }
    ],
    "sg:phone":"+61 2 4384 7781",
    "sg:postcode":"2260",
    "sg:province":"NSW",
    "wof:name":"Stuff Sales Company The",
    "wof:placetype":"venue"
},
  "geometry": {"coordinates":[151.44125399999999,-33.442863],"type":"Point"}
}