{
  "type": "Feature",
  "properties": {
    "addr:full":"51 Cox St Hamilton VIC 3300",
    "addr:housenumber":"51",
    "addr:postcode":"3300",
    "addr:street":"Cox St",
    "iso:country":"AU",
    "sg:address":"51 Cox St",
    "sg:city":"Hamilton",
    "sg:classifiers":[
        {
            "category":"Autos & Motor Vehicles",
            "subcategory":"Auto Supplies",
            "type":"Retail Goods"
        }
    ],
    "sg:phone":"+61 3 5572 2622",
    "sg:postcode":"3300",
    "sg:province":"VIC",
    "sg:tags":[
        "battery",
        "automotive"
    ],
    "wof:name":"Beaurepaires",
    "wof:placetype":"venue"
},
  "geometry": {"coordinates":[142.02845764200001,-37.7431983948],"type":"Point"}
}