{
  "type": "Feature",
  "properties": {
    "addr:full":"PO Box 4313 Knox City Centre VIC 3152",
    "addr:postcode":"3152",
    "iso:country":"AU",
    "sg:address":"PO Box 4313",
    "sg:city":"Knox City Centre",
    "sg:classifiers":[
        {
            "category":"Professional",
            "subcategory":"Accounting & Tax Preparation",
            "type":"Services"
        }
    ],
    "sg:phone":"+61 421 089 979",
    "sg:postcode":"3152",
    "sg:province":"VIC",
    "sg:tags":[
        "consultant",
        "taxation"
    ],
    "wof:name":"Integral Business Management",
    "wof:placetype":"venue"
},
  "geometry": {"coordinates":[145.24118042000001,-37.8691291809],"type":"Point"}
}