{
  "type": "Feature",
  "properties": {
    "addr:full":"3 Bardwell St Holbrook NSW 2644",
    "addr:housenumber":"3",
    "addr:postcode":"2644",
    "addr:street":"Bardwell St",
    "iso:country":"AU",
    "sg:address":"3 Bardwell St",
    "sg:city":"Holbrook",
    "sg:classifiers":[
        {
            "category":"Real Estate",
            "subcategory":"Real Estate Agent",
            "type":"Services"
        }
    ],
    "sg:phone":"+61 2 6036 2040",
    "sg:postcode":"2644",
    "sg:province":"NSW",
    "sg:tags":[
        "handyman's",
        "equipment",
        "hire",
        "builders",
        "contractor"
    ],
    "wof:name":"Grunow Plant Hire",
    "wof:placetype":"venue"
},
  "geometry": {"coordinates":[147.31784057600001,-35.730556488],"type":"Point"}
}