{
  "type": "Feature",
  "properties": {
    "addr:full":"Shop 4 379 Scarborough Beach Rd Metro Cntr Innaloo WA 6018",
    "addr:housenumber":"shop 4 379",
    "addr:postcode":"6018",
    "addr:street":"Scarborough Beach Rd",
    "iso:country":"AU",
    "sg:address":"Shop 4 379 Scarborough Beach Rd",
    "sg:city":"Metro Cntr Innaloo",
    "sg:classifiers":[
        {
            "category":"Banks & Credit Unions",
            "subcategory":"Financial Services",
            "type":"Services"
        }
    ],
    "sg:phone":"+61 8 9244 2264",
    "sg:postcode":"6018",
    "sg:province":"WA",
    "sg:tags":[
        "settlement",
        "nt",
        "agent",
        "wa"
    ],
    "wof:name":"Consolidated Settlements",
    "wof:placetype":"venue"
},
  "geometry": {"coordinates":[115.797042847,-31.9025268555],"type":"Point"}
}