{
  "type": "Feature",
  "properties": {
    "addr:full":"24 Gardiner Rd Notting Hill VIC 3168",
    "addr:housenumber":"24",
    "addr:postcode":"3168",
    "addr:street":"Gardiner Rd",
    "iso:country":"AU",
    "sg:address":"24 Gardiner Rd",
    "sg:city":"Notting Hill",
    "sg:classifiers":[
        {
            "category":"Professional",
            "type":"Services"
        }
    ],
    "sg:phone":"+61 13 13 22",
    "sg:postcode":"3168",
    "sg:province":"VIC",
    "sg:tags":[
        "courier"
    ],
    "wof:name":"Kings Transport",
    "wof:placetype":"venue"
},
  "geometry": {"coordinates":[145.13137817399999,-37.8999519348],"type":"Point"}
}