{
  "type": "Feature",
  "properties": {
    "addr:full":"56 Stud Rd Dandenong VIC 3175",
    "addr:housenumber":"56",
    "addr:postcode":"3175",
    "addr:street":"Stud Rd",
    "iso:country":"AU",
    "sg:address":"56 Stud Rd",
    "sg:city":"Dandenong",
    "sg:classifiers":[
        {
            "category":"Health Services",
            "subcategory":"Health Practitioner",
            "type":"Services"
        }
    ],
    "sg:phone":"+61 3 9791 8864",
    "sg:postcode":"3175",
    "sg:province":"VIC",
    "sg:tags":[
        "naturopath"
    ],
    "wof:name":"Blake Tammy-Natures Cure Clinic Pty Ltd",
    "wof:placetype":"venue"
},
  "geometry": {"coordinates":[145.22187805199999,-37.9800567627],"type":"Point"}
}