{
  "type": "Feature",
  "properties": {
    "addr:full":"242 Baylis St Wagga Wagga NSW 2650",
    "addr:housenumber":"242",
    "addr:postcode":"2650",
    "addr:street":"Baylis St",
    "iso:country":"AU",
    "sg:address":"242 Baylis St",
    "sg:city":"Wagga Wagga",
    "sg:classifiers":[
        {
            "category":"Shopping",
            "subcategory":"Crafts & Fabrics",
            "type":"Retail Goods"
        }
    ],
    "sg:phone":"+61 2 6921 5100",
    "sg:postcode":"2650",
    "sg:province":"NSW",
    "sg:tags":[
        "material",
        "dress"
    ],
    "wof:name":"Special Occasion Fabrics",
    "wof:placetype":"venue"
},
  "geometry": {"coordinates":[147.37028503400001,-35.1102561951],"type":"Point"}
}