{
  "type": "Feature",
  "properties": {
    "addr:full":"Suite 302, 16- 18 Cambridge St Epping NSW 2121",
    "addr:housenumber":"18",
    "addr:postcode":"2121",
    "addr:street":"16;Cambridge St",
    "iso:country":"AU",
    "sg:address":"Suite 302, 16- 18 Cambridge St",
    "sg:city":"Epping",
    "sg:classifiers":[
        {
            "category":"Insurance",
            "subcategory":"Insurance Agent",
            "type":"Services"
        }
    ],
    "sg:phone":"+61 2 9876 8199",
    "sg:postcode":"2121",
    "sg:province":"NSW",
    "sg:tags":[
        "broker"
    ],
    "wof:name":"Endeavour Insurance Broking Group Pty Ltd",
    "wof:placetype":"venue"
},
  "geometry": {"coordinates":[151.08200073200001,-33.7702217102],"type":"Point"}
}