{
  "type": "Feature",
  "properties": {
    "addr:full":"4/ 39 Campbell St Taringa QLD 4068",
    "addr:housenumber":"/ 39",
    "addr:postcode":"4068",
    "addr:street":"Campbell St",
    "iso:country":"AU",
    "sg:address":"4/ 39 Campbell St",
    "sg:city":"Taringa",
    "sg:classifiers":[
        {
            "category":"Professional",
            "subcategory":"Detective & Security Services",
            "type":"Services"
        }
    ],
    "sg:phone":"+61 7 3870 8446",
    "sg:postcode":"4068",
    "sg:province":"QLD",
    "sg:tags":[
        "consultant",
        "system"
    ],
    "wof:name":"Morrison Electrical",
    "wof:placetype":"venue"
},
  "geometry": {"coordinates":[152.98815918,-27.4907588959],"type":"Point"}
}