{
  "type": "Feature",
  "properties": {
    "addr:full":"Shop 24, Surfers International Arcade, Hanlan St Surfers Paradise QLD 4217",
    "addr:housenumber":"shop 24 surfers international",
    "addr:postcode":"4217",
    "addr:street":"Hanlan St",
    "iso:country":"AU",
    "sg:address":"Shop 24, Surfers International Arcade, Hanlan St",
    "sg:city":"Surfers Paradise",
    "sg:classifiers":[
        {
            "category":"Personal",
            "subcategory":"Piercing",
            "type":"Services"
        }
    ],
    "sg:phone":"+61 7 5538 0220",
    "sg:postcode":"4217",
    "sg:province":"QLD",
    "sg:tags":[
        "body",
        "ear"
    ],
    "wof:name":"U.V. Blacklight Reflective Tattooing & Pleasurable Body Modifications",
    "wof:placetype":"venue"
},
  "geometry": {"coordinates":[153.42984008799999,-28.0031414032],"type":"Point"}
}