{
  "type": "Feature",
  "properties": {
    "addr:full":"11 Wilgra Ave Ashburton VIC 3147",
    "addr:housenumber":"11",
    "addr:postcode":"3147",
    "addr:street":"Wilgra Ave",
    "iso:country":"AU",
    "sg:address":"11 Wilgra Ave",
    "sg:city":"Ashburton",
    "sg:classifiers":[
        {
            "category":"Social Services",
            "subcategory":"Child Care",
            "type":"Services"
        }
    ],
    "sg:phone":"+61 3 9885 2380",
    "sg:postcode":"3147",
    "sg:province":"VIC",
    "wof:name":"Ashburton Child Care Centre & Kindergarten",
    "wof:placetype":"venue"
},
  "geometry": {"coordinates":[145.08924865700001,-37.8620758057],"type":"Point"}
}