{
  "type": "Feature",
  "properties": {
    "addr:full":"135 Katoomba St Katoomba NSW 2780",
    "addr:housenumber":"135",
    "addr:postcode":"2780",
    "addr:street":"Katoomba St",
    "iso:country":"AU",
    "sg:address":"135 Katoomba St",
    "sg:city":"Katoomba",
    "sg:classifiers":[
        {
            "category":"Food & Beverages",
            "subcategory":"Bakery",
            "type":"Retail Goods"
        }
    ],
    "sg:phone":"+61 2 4782 4820",
    "sg:postcode":"2780",
    "sg:province":"NSW",
    "sg:tags":[
        "baker"
    ],
    "wof:name":"Katoomba French Hot Bread",
    "wof:placetype":"venue"
},
  "geometry": {"coordinates":[150.31114196799999,-33.715511322],"type":"Point"}
}