{
  "type": "Feature",
  "properties": {
    "addr:full":"10 Isle Of Bags Rd Nelson VIC 3292",
    "addr:housenumber":"10",
    "addr:postcode":"3292",
    "addr:street":"Isle;Rd",
    "iso:country":"AU",
    "sg:address":"10 Isle Of Bags Rd",
    "sg:city":"Nelson",
    "sg:classifiers":[
        {
            "category":"Cafe",
            "type":"Food & Drink"
        }
    ],
    "sg:phone":"+61 8 8738 4378",
    "sg:postcode":"3292",
    "sg:province":"VIC",
    "wof:name":"Ambience Licensed Gallery Cafe",
    "wof:placetype":"venue"
},
  "geometry": {"coordinates":[141.007126,-38.040432],"type":"Point"}
}