{
  "type": "Feature",
  "properties": {
    "addr:full":"1 Ballanda St Frenchs Forest NSW 2086",
    "addr:housenumber":"1",
    "addr:postcode":"2086",
    "addr:street":"Ballanda St",
    "iso:country":"AU",
    "sg:address":"1 Ballanda St",
    "sg:city":"Frenchs Forest",
    "sg:classifiers":[
        {
            "category":"Banks & Credit Unions",
            "subcategory":"Bank",
            "type":"Services"
        }
    ],
    "sg:phone":"+61 1300 739 113",
    "sg:postcode":"2086",
    "sg:province":"NSW",
    "sg:tags":[
        "equipment",
        "sale",
        "point"
    ],
    "wof:name":"Head Office Solutions",
    "wof:placetype":"venue"
},
  "geometry": {"coordinates":[151.22352600100001,-33.7570457458],"type":"Point"}
}