{
  "type": "Feature",
  "properties": {
    "addr:full":"Harry Graham Drv Kembla Heights NSW 2526",
    "addr:postcode":"2526",
    "addr:street":"Graham Drv",
    "iso:country":"AU",
    "sg:address":"Harry Graham Drv",
    "sg:city":"Kembla Heights",
    "sg:classifiers":[
        {
            "category":"Government",
            "subcategory":"City Hall",
            "type":"Public Place"
        }
    ],
    "sg:phone":"+61 2 4272 1029",
    "sg:postcode":"2526",
    "sg:province":"NSW",
    "wof:name":"Kembla Heights Community Hall",
    "wof:placetype":"venue"
},
  "geometry": {"coordinates":[150.80609130900001,-34.4321479797],"type":"Point"}
}