{
  "type": "Feature",
  "properties": {
    "addr:full":"2/ 22 Govetts Leap Rd Blackheath NSW 2785",
    "addr:housenumber":"/ 22",
    "addr:postcode":"2785",
    "addr:street":"Govetts Leap Rd",
    "iso:country":"AU",
    "sg:address":"2/ 22 Govetts Leap Rd",
    "sg:city":"Blackheath",
    "sg:classifiers":[
        {
            "category":"Professional",
            "subcategory":"Accounting & Tax Preparation",
            "type":"Services"
        }
    ],
    "sg:phone":"+61 2 4787 8902",
    "sg:postcode":"2785",
    "sg:province":"NSW",
    "sg:tags":[
        "consultant",
        "taxation"
    ],
    "wof:name":"Hoffman & Co Accountants",
    "wof:placetype":"venue"
},
  "geometry": {"coordinates":[150.28579711899999,-33.6357269287],"type":"Point"}
}