{
  "type": "Feature",
  "properties": {
    "addr:full":"PO Box 2469 Malaga WA 6090",
    "addr:postcode":"6090",
    "iso:country":"AU",
    "sg:address":"PO Box 2469",
    "sg:city":"Malaga",
    "sg:classifiers":[
        {
            "category":"Building & Trades",
            "subcategory":"Cleaning & Sanitation",
            "type":"Services"
        }
    ],
    "sg:phone":"+61 8 9276 6939",
    "sg:postcode":"6090",
    "sg:province":"WA",
    "sg:tags":[
        "industrial",
        "commercial",
        "contractor"
    ],
    "wof:name":"Style Clean",
    "wof:placetype":"venue"
},
  "geometry": {"coordinates":[115.897476196,-31.8568401337],"type":"Point"}
}