{
  "type": "Feature",
  "properties": {
    "addr:full":"53 Hawthorn Rd Caulfield North VIC 3161",
    "addr:housenumber":"53",
    "addr:postcode":"3161",
    "addr:street":"Hawthorn Rd",
    "iso:country":"AU",
    "sg:address":"53 Hawthorn Rd",
    "sg:city":"Caulfield North",
    "sg:classifiers":[
        {
            "category":"Cafe",
            "type":"Food & Drink"
        }
    ],
    "sg:phone":"+61 3 9528 2544",
    "sg:postcode":"3161",
    "sg:province":"VIC",
    "wof:name":"Caffe Uffizi",
    "wof:placetype":"venue"
},
  "geometry": {"coordinates":[145.02366638199999,-37.8708114624],"type":"Point"}
}