{
  "type": "Feature",
  "properties": {
    "iso:country":"AU",
    "sg:address":"4 Barnsbury Crt",
    "sg:city":"Deepdene",
    "sg:classifiers":[
        {
            "category":"Banks & Credit Unions",
            "subcategory":"Financial Services",
            "type":"Services"
        }
    ],
    "sg:phone":"+61 3 9606 0123",
    "sg:postcode":"3103",
    "sg:province":"VIC",
    "sg:tags":[
        "planning"
    ],
    "wof:name":"T Scott Investments P/L",
    "wof:placetype":"venue"
},
  "geometry": {"coordinates":[145.064163208,-37.8143310547],"type":"Point"}
}