{
  "type": "Feature",
  "properties": {
    "addr:full":"Factory 18/38- 44 Dandenong St Dandenong VIC 3175",
    "addr:housenumber":"18 / 38 44",
    "addr:postcode":"3175",
    "addr:street":"Dandenong St",
    "iso:country":"AU",
    "sg:address":"Factory 18/38- 44 Dandenong St",
    "sg:city":"Dandenong",
    "sg:classifiers":[
        {
            "category":"Communications",
            "subcategory":"Film & Video Production",
            "type":"Services"
        }
    ],
    "sg:phone":"+61 1300 668 896",
    "sg:postcode":"3175",
    "sg:province":"VIC",
    "sg:tags":[
        "shutter",
        "window",
        "roller"
    ],
    "wof:name":"Ultra Shutters",
    "wof:placetype":"venue"
},
  "geometry": {"coordinates":[145.19909668,-37.9951210022],"type":"Point"}
}