{
  "type": "Feature",
  "properties": {
    "iso:country":"AU",
    "sg:address":"191 Walnut Ave",
    "sg:city":"Mildura",
    "sg:classifiers":[
        {
            "category":"Personal",
            "subcategory":"Massage",
            "type":"Services"
        }
    ],
    "sg:phone":"+61 3 5023 4853",
    "sg:postcode":"3500",
    "sg:province":"VIC",
    "sg:tags":[
        "therapy"
    ],
    "wof:name":"Heather Hurley",
    "wof:placetype":"venue"
},
  "geometry": {"coordinates":[142.15072631800001,-34.1864204407],"type":"Point"}
}