{
  "type": "Feature",
  "properties": {
    "addr:full":"192 Station St Port Melbourne VIC 3207",
    "addr:housenumber":"192",
    "addr:postcode":"3207",
    "addr:street":"Station St",
    "iso:country":"AU",
    "sg:address":"192 Station St",
    "sg:city":"Port Melbourne",
    "sg:classifiers":[
        {
            "category":"Travel",
            "subcategory":"Hotels & Motels",
            "type":"Entertainment"
        }
    ],
    "sg:phone":"+61 3 9646 2746",
    "sg:postcode":"3207",
    "sg:province":"VIC",
    "sg:tags":[
        "pub"
    ],
    "wof:name":"Swallows Hotel Of Port Melbourne",
    "wof:placetype":"venue"
},
  "geometry": {"coordinates":[144.945694,-37.832687],"type":"Point"}
}