{
  "type": "Feature",
  "properties": {
    "addr:full":"7 Trebor Rd Pennant Hills NSW 2120",
    "addr:housenumber":"7",
    "addr:postcode":"2120",
    "addr:street":"Trebor Rd",
    "iso:country":"AU",
    "sg:address":"7 Trebor Rd",
    "sg:city":"Pennant Hills",
    "sg:classifiers":[
        {
            "category":"Social Services",
            "subcategory":"Child Care",
            "type":"Services"
        }
    ],
    "sg:phone":"+61 2 9980 7139",
    "sg:postcode":"2120",
    "sg:province":"NSW",
    "wof:name":"Trebor Road Out of School Hours Care",
    "wof:placetype":"venue"
},
  "geometry": {"coordinates":[151.06758117699999,-33.73878479],"type":"Point"}
}