{
  "type": "Feature",
  "properties": {
    "iso:country":"AU",
    "sg:address":"13 Main St",
    "sg:city":"North Tamborine",
    "sg:classifiers":[
        {
            "category":"Fast Food",
            "type":"Food & Drink"
        }
    ],
    "sg:phone":"+61 7 5545 1056",
    "sg:postcode":"4272",
    "sg:province":"QLD",
    "sg:tags":[
        "away",
        "take"
    ],
    "wof:name":"Pinnacle Pizza's",
    "wof:placetype":"venue"
},
  "geometry": {"coordinates":[153.18533325199999,-27.9262866974],"type":"Point"}
}