{
  "type": "Feature",
  "properties": {
    "addr:full":"674 Macquarie Drv Eleebana NSW 2282",
    "addr:housenumber":"674",
    "addr:postcode":"2282",
    "addr:street":"Macquarie Drv",
    "iso:country":"AU",
    "sg:address":"674 Macquarie Drv",
    "sg:city":"Eleebana",
    "sg:classifiers":[
        {
            "category":"Professional",
            "subcategory":"Engineering",
            "type":"Services"
        }
    ],
    "sg:phone":"+61 412 402 632",
    "sg:postcode":"2282",
    "sg:province":"NSW",
    "sg:tags":[
        "electrical",
        "engineer"
    ],
    "wof:name":"TWL Electrical-Industrial Engineering Pty Ltd",
    "wof:placetype":"venue"
},
  "geometry": {"coordinates":[151.63778686500001,-32.9919700623],"type":"Point"}
}