{
  "type": "Feature",
  "properties": {
    "iso:country":"AU",
    "sg:address":"176 Christmas St",
    "sg:city":"Fairfield",
    "sg:classifiers":[
        {
            "category":"Utilities",
            "subcategory":"Electric",
            "type":"Services"
        }
    ],
    "sg:phone":"+61 3 9489 9255",
    "sg:postcode":"3078",
    "sg:province":"VIC",
    "sg:tags":[
        "electrical",
        "contractor"
    ],
    "wof:name":"Melco Milec Victoria",
    "wof:placetype":"venue"
},
  "geometry": {"coordinates":[145.02503967300001,-37.7680435181],"type":"Point"}
}