{
  "type": "Feature",
  "properties": {
    "iso:country":"AU",
    "sg:address":"130 Royal St",
    "sg:city":"East Perth",
    "sg:classifiers":[
        {
            "category":"Professional",
            "subcategory":"Art Services",
            "type":"Services"
        }
    ],
    "sg:phone":"+61 8 9322 9733",
    "sg:postcode":"6004",
    "sg:province":"WA",
    "sg:tags":[
        "graphic",
        "designer"
    ],
    "wof:name":"Integrated Concept",
    "wof:placetype":"venue"
},
  "geometry": {"coordinates":[115.874229431,-31.9524707794],"type":"Point"}
}