{
  "type": "Feature",
  "properties": {
    "addr:full":"PO Box 2049 Bendigo MC VIC 3554",
    "addr:postcode":"3554",
    "iso:country":"AU",
    "sg:address":"PO Box 2049",
    "sg:city":"Bendigo MC",
    "sg:classifiers":[
        {
            "category":"Building & Trades",
            "subcategory":"Construction",
            "type":"Services"
        }
    ],
    "sg:phone":"+61 417 535 108",
    "sg:postcode":"3554",
    "sg:province":"VIC",
    "sg:tags":[
        "pool",
        "swimming"
    ],
    "wof:name":"Pure - Pools",
    "wof:placetype":"venue"
},
  "geometry": {"coordinates":[144.28007507300001,-36.7584915161],"type":"Point"}
}