{
  "type": "Feature",
  "properties": {
    "addr:full":"Hinkler Drv Nerang QLD 4211",
    "addr:postcode":"4211",
    "addr:street":"Hinkler Drv",
    "iso:country":"AU",
    "sg:address":"Hinkler Drv",
    "sg:city":"Nerang",
    "sg:classifiers":[
        {
            "category":"Food & Beverages",
            "subcategory":"Liquor & Beverages",
            "type":"Retail Goods"
        }
    ],
    "sg:phone":"+61 7 5596 6155",
    "sg:postcode":"4211",
    "sg:province":"QLD",
    "sg:tags":[
        "store"
    ],
    "wof:name":"Wazza's Nerang South Cellars",
    "wof:placetype":"venue"
},
  "geometry": {"coordinates":[153.34527587900001,-28.0112037659],"type":"Point"}
}