{
  "type": "Feature",
  "properties": {
    "addr:full":"129 Burnett St Buderim QLD 4556",
    "addr:housenumber":"129",
    "addr:postcode":"4556",
    "addr:street":"Burnett St",
    "iso:country":"AU",
    "sg:address":"129 Burnett St",
    "sg:city":"Buderim",
    "sg:classifiers":[
        {
            "category":"Utilities",
            "subcategory":"Natural Gas",
            "type":"Services"
        }
    ],
    "sg:phone":"+61 7 5445 1218",
    "sg:postcode":"4556",
    "sg:province":"QLD",
    "sg:tags":[
        "pressing",
        "metal",
        "stamping"
    ],
    "wof:name":"Mercury Mufflers (Aust) Pty Ltd",
    "wof:placetype":"venue"
},
  "geometry": {"coordinates":[153.046386719,-26.6897125244],"type":"Point"}
}