{
  "type": "Feature",
  "properties": {
    "iso:country":"AU",
    "sg:address":"15 Mitchell St",
    "sg:city":"Camden",
    "sg:classifiers":[
        {
            "category":"Insurance",
            "subcategory":"Life Insurance",
            "type":"Services"
        }
    ],
    "sg:phone":"+61 2 4655 7310",
    "sg:postcode":"2570",
    "sg:province":"NSW",
    "wof:name":"John L. Maher Insurance Brokers Pty Ltd",
    "wof:placetype":"venue"
},
  "geometry": {"coordinates":[150.69731140100001,-34.0517463684],"type":"Point"}
}