{
  "type": "Feature",
  "properties": {
    "addr:full":"138 Gilles St Adelaide SA 5000",
    "addr:housenumber":"138",
    "addr:postcode":"5000",
    "addr:street":"Gilles St",
    "iso:country":"AU",
    "sg:address":"138 Gilles St",
    "sg:city":"Adelaide",
    "sg:classifiers":[
        {
            "category":"Professional",
            "subcategory":"Employment Agencies",
            "type":"Services"
        }
    ],
    "sg:phone":"+61 8 8418 6666",
    "sg:postcode":"5000",
    "sg:province":"SA",
    "sg:tags":[
        "provider",
        "internet"
    ],
    "wof:name":"Kanga Internet Services",
    "wof:placetype":"venue"
},
  "geometry": {"coordinates":[138.60540771500001,-34.9339103699],"type":"Point"}
}