{
  "type": "Feature",
  "properties": {
    "addr:full":"111 Forest Rd Ferntree Gully VIC 3156",
    "addr:housenumber":"111",
    "addr:postcode":"3156",
    "addr:street":"Forest Rd",
    "iso:country":"AU",
    "sg:address":"111 Forest Rd",
    "sg:city":"Ferntree Gully",
    "sg:classifiers":[
        {
            "category":"Education",
            "subcategory":"School",
            "type":"Public Place"
        }
    ],
    "sg:phone":"+61 3 9758 1662",
    "sg:postcode":"3156",
    "sg:province":"VIC",
    "sg:tags":[
        "state",
        "except",
        "nsw"
    ],
    "wof:name":"Ferntree Gully North Primary",
    "wof:placetype":"venue"
},
  "geometry": {"coordinates":[145.299484253,-37.8746833801],"type":"Point"}
}