{
  "type": "Feature",
  "properties": {
    "addr:full":"PO Box 746 Gordon NSW 2072",
    "addr:postcode":"2072",
    "iso:country":"AU",
    "sg:address":"PO Box 746",
    "sg:city":"Gordon",
    "sg:classifiers":[
        {
            "category":"Building & Trades",
            "subcategory":"Construction",
            "type":"Services"
        }
    ],
    "sg:phone":"+61 2 9488 9577",
    "sg:postcode":"2072",
    "sg:province":"NSW",
    "sg:tags":[
        "renovation",
        "alterations",
        "extension",
        "contractor"
    ],
    "wof:name":"Spinners Building Services Gordon",
    "wof:placetype":"venue"
},
  "geometry": {"coordinates":[151.155685425,-33.7573509216],"type":"Point"}
}