{
  "type": "Feature",
  "properties": {
    "addr:full":"1230 Sydney Rd Fawkner VIC 3060",
    "addr:housenumber":"1230",
    "addr:postcode":"3060",
    "addr:street":"Sydney Rd",
    "iso:country":"AU",
    "sg:address":"1230 Sydney Rd",
    "sg:city":"Fawkner",
    "sg:classifiers":[
        {
            "category":"Retail",
            "subcategory":"Auto Repair",
            "type":"Services"
        }
    ],
    "sg:phone":"+61 3 9359 1855",
    "sg:postcode":"3060",
    "sg:province":"VIC",
    "sg:tags":[
        "electrical"
    ],
    "wof:name":"A Melbourne Auto Electrics",
    "wof:placetype":"venue"
},
  "geometry": {"coordinates":[144.96092224099999,-37.7047958374],"type":"Point"}
}