{
  "type": "Feature",
  "properties": {
    "addr:full":"2/ 25 McCauley St Alexandria NSW 2015",
    "addr:housenumber":"/ 25",
    "addr:postcode":"2015",
    "addr:street":"Mccauley St",
    "iso:country":"AU",
    "sg:address":"2/ 25 McCauley St",
    "sg:city":"Alexandria",
    "sg:classifiers":[
        {
            "category":"Professional",
            "subcategory":"Detective & Security Services",
            "type":"Services"
        }
    ],
    "sg:phone":"+61 2 9699 7771",
    "sg:postcode":"2015",
    "sg:province":"NSW",
    "sg:tags":[
        "domestic",
        "alarm",
        "commercial",
        "burglar"
    ],
    "wof:name":"Soundfreq Pty Ltd",
    "wof:placetype":"venue"
},
  "geometry": {"coordinates":[151.19883727999999,-33.9037971497],"type":"Point"}
}