{
  "type": "Feature",
  "properties": {
    "iso:country":"AU",
    "sg:address":"1A Bullecourt Ave",
    "sg:city":"Milperra",
    "sg:classifiers":[
        {
            "category":"Building & Trades",
            "subcategory":"Plumbing",
            "type":"Services"
        }
    ],
    "sg:phone":"+61 2 9792 8928",
    "sg:postcode":"2214",
    "sg:province":"NSW",
    "sg:tags":[
        "equipment",
        "valves"
    ],
    "wof:name":"Flangecast Pipe Supplies",
    "wof:placetype":"venue"
},
  "geometry": {"coordinates":[150.98912,-33.937592],"type":"Point"}
}