{
  "type": "Feature",
  "properties": {
    "addr:full":"6 Bendsten Pl Balcatta WA 6021",
    "addr:housenumber":"6",
    "addr:postcode":"6021",
    "addr:street":"Bendsten Pl",
    "iso:country":"AU",
    "sg:address":"6 Bendsten Pl",
    "sg:city":"Balcatta",
    "sg:classifiers":[
        {
            "category":"Home & Garden",
            "subcategory":"Hardware",
            "type":"Retail Goods"
        }
    ],
    "sg:phone":"+61 8 9345 3155",
    "sg:postcode":"6021",
    "sg:province":"WA",
    "sg:tags":[
        "plumber",
        "supply"
    ],
    "wof:name":"Tradelink Plumbing Centres",
    "wof:placetype":"venue"
},
  "geometry": {"coordinates":[115.806503296,-31.8587093353],"type":"Point"}
}