{
  "type": "Feature",
  "properties": {
    "addr:full":"360 Shute Harbour Rd Airlie Beach QLD 4802",
    "addr:housenumber":"360",
    "addr:postcode":"4802",
    "addr:street":"Shute Harbour Rd",
    "iso:country":"AU",
    "sg:address":"360 Shute Harbour Rd",
    "sg:city":"Airlie Beach",
    "sg:classifiers":[
        {
            "category":"Shopping",
            "subcategory":"Clothing, Apparel, & Fashions",
            "type":"Retail Goods"
        }
    ],
    "sg:phone":"+61 7 4946 4888",
    "sg:postcode":"4802",
    "sg:province":"QLD",
    "sg:tags":[
        "boutique"
    ],
    "wof:name":"Reef Goddess Boutique",
    "wof:placetype":"venue"
},
  "geometry": {"coordinates":[148.71893310600001,-20.2690181732],"type":"Point"}
}