{
  "type": "Feature",
  "properties": {
    "iso:country":"AU",
    "sg:address":"Level 2 242 Sheridan St",
    "sg:city":"Cairns",
    "sg:classifiers":[
        {
            "category":"Building & Trades",
            "subcategory":"Construction",
            "type":"Services"
        }
    ],
    "sg:phone":"+61 1300 136 774",
    "sg:postcode":"4870",
    "sg:province":"QLD",
    "sg:tags":[
        "home",
        "air conditioning"
    ],
    "wof:name":"C.C.S Climate Control Specialists",
    "wof:placetype":"venue"
},
  "geometry": {"coordinates":[145.76296997099999,-16.9107627869],"type":"Point"}
}