{
  "type": "Feature",
  "properties": {
    "addr:full":"146 Lambton Rd Broadmeadow NSW 2292",
    "addr:housenumber":"146",
    "addr:postcode":"2292",
    "addr:street":"Lambton Rd",
    "iso:country":"AU",
    "sg:address":"146 Lambton Rd",
    "sg:city":"Broadmeadow",
    "sg:classifiers":[
        {
            "category":"Education",
            "subcategory":"Special Training",
            "type":"Public Place"
        }
    ],
    "sg:phone":"+61 2 4956 4333",
    "sg:postcode":"2292",
    "sg:province":"NSW",
    "sg:tags":[
        "development"
    ],
    "wof:name":"International Child Care College",
    "wof:placetype":"venue"
},
  "geometry": {"coordinates":[151.724853516,-32.9231987],"type":"Point"}
}