{
  "type": "Feature",
  "properties": {
    "iso:country":"AU",
    "sg:address":"1 Belledale Cl St",
    "sg:city":"Clair",
    "sg:classifiers":[
        {
            "category":"Wholesale",
            "subcategory":"Music Publishers",
            "type":"Manufacturing & Wholesale Goods"
        }
    ],
    "sg:phone":"+61 2 9670 2795",
    "sg:postcode":"2759",
    "sg:province":"NSW",
    "sg:tags":[
        "wholesaler",
        "dvd",
        "mfrs",
        "cd"
    ],
    "wof:name":"Repeat Performance Disc Duplication Services",
    "wof:placetype":"venue"
},
  "geometry": {"coordinates":[150.77980041500001,-33.7973594666],"type":"Point"}
}