{
  "type": "Feature",
  "properties": {
    "addr:full":"7 Glenmore Crt Alexandra Hills QLD 4161",
    "addr:housenumber":"7",
    "addr:postcode":"4161",
    "addr:street":"Glenmore Crt",
    "iso:country":"AU",
    "sg:address":"7 Glenmore Crt",
    "sg:city":"Alexandra Hills",
    "sg:classifiers":[
        {
            "category":"Shopping",
            "subcategory":"Baby Store",
            "type":"Retail Goods"
        }
    ],
    "sg:phone":"+61 7 3824 5216",
    "sg:postcode":"4161",
    "sg:province":"QLD",
    "sg:tags":[
        "children's",
        "wear"
    ],
    "wof:name":"Natural Story Design",
    "wof:placetype":"venue"
},
  "geometry": {"coordinates":[153.22767639200001,-27.5441513062],"type":"Point"}
}