{
  "type": "Feature",
  "properties": {
    "iso:country":"AU",
    "sg:address":"6 Bloomsbury St",
    "sg:city":"Goodwood",
    "sg:classifiers":[
        {
            "category":"Building & Trades",
            "subcategory":"Construction",
            "type":"Services"
        }
    ],
    "sg:phone":"+61 412 713 844",
    "sg:postcode":"5034",
    "sg:province":"SA",
    "sg:tags":[
        "contractor"
    ],
    "wof:name":"Karas Constructions",
    "wof:placetype":"venue"
},
  "geometry": {"coordinates":[138.59910583499999,-34.9519996643],"type":"Point"}
}