{
  "type": "Feature",
  "properties": {
    "iso:country":"AU",
    "sg:address":"66 Brooker Ave",
    "sg:city":"Beacon Hill",
    "sg:classifiers":[
        {
            "category":"Shopping",
            "subcategory":"Bicycles & Sporting Goods",
            "type":"Retail Goods"
        }
    ],
    "sg:phone":"+61 2 9975 4630",
    "sg:postcode":"2100",
    "sg:province":"NSW",
    "sg:tags":[
        "dance",
        "accessory",
        "wear",
        "supply"
    ],
    "wof:name":"Kilkenny Irish Dance Wear",
    "wof:placetype":"venue"
},
  "geometry": {"coordinates":[151.254806519,-33.7474021912],"type":"Point"}
}