{
  "type": "Feature",
  "properties": {
    "addr:full":"Suite 4, 150 Chestnut St Richmond VIC 3121",
    "addr:housenumber":"150",
    "addr:postcode":"3121",
    "addr:street":"Chestnut St",
    "iso:country":"AU",
    "sg:address":"Suite 4, 150 Chestnut St",
    "sg:city":"Richmond",
    "sg:classifiers":[
        {
            "category":"Banks & Credit Unions",
            "subcategory":"Financial Services",
            "type":"Services"
        }
    ],
    "sg:phone":"+61 3 9428 5455",
    "sg:postcode":"3121",
    "sg:province":"VIC",
    "sg:tags":[
        "planning"
    ],
    "wof:name":"T. Ikraan Financial Services Pty Ltd",
    "wof:placetype":"venue"
},
  "geometry": {"coordinates":[144.994796753,-37.8311233521],"type":"Point"}
}