{
  "type": "Feature",
  "properties": {
    "addr:full":"North St Mulwala NSW 2647",
    "addr:postcode":"2647",
    "addr:street":"North St",
    "iso:country":"AU",
    "sg:address":"North St",
    "sg:city":"Mulwala",
    "sg:classifiers":[
        {
            "category":"Banks & Credit Unions",
            "subcategory":"Investment Brokerage",
            "type":"Services"
        }
    ],
    "sg:phone":"+61 3 5744 3616",
    "sg:postcode":"2647",
    "sg:province":"NSW",
    "sg:tags":[
        "electricity",
        "supplier"
    ],
    "wof:name":"Electricity Commission Of NSW The",
    "wof:placetype":"venue"
},
  "geometry": {"coordinates":[146.00721740700001,-35.9777565002],"type":"Point"}
}