{
  "type": "Feature",
  "properties": {
    "iso:country":"AU",
    "sg:address":"2135 Frankston-Flinders Rd",
    "sg:city":"Hastings",
    "sg:classifiers":[
        {
            "category":"Home & Garden",
            "subcategory":"Building Materials",
            "type":"Retail Goods"
        }
    ],
    "sg:phone":"+61 3 5979 7108",
    "sg:postcode":"3915",
    "sg:province":"VIC",
    "sg:tags":[
        "balustrading"
    ],
    "wof:name":"W.G. Ford Stainless Products",
    "wof:placetype":"venue"
},
  "geometry": {"coordinates":[145.184326172,-38.3110427856],"type":"Point"}
}