{
  "type": "Feature",
  "properties": {
    "addr:full":"69a Semaphore Rd Semaphore SA 5019",
    "addr:housenumber":"69a",
    "addr:postcode":"5019",
    "addr:street":"Semaphore Rd",
    "iso:country":"AU",
    "sg:address":"69a Semaphore Rd",
    "sg:city":"Semaphore",
    "sg:classifiers":[
        {
            "category":"Shopping",
            "subcategory":"Music",
            "type":"Retail Goods"
        }
    ],
    "sg:phone":"+61 8 8341 5234",
    "sg:postcode":"5019",
    "sg:province":"SA",
    "sg:tags":[
        "store"
    ],
    "wof:name":"Mr V Music",
    "wof:placetype":"venue"
},
  "geometry": {"coordinates":[138.48492431599999,-34.8388710022],"type":"Point"}
}