{
  "type": "Feature",
  "properties": {
    "iso:country":"AU",
    "sg:address":"Unit 2/ 371 Canterbury Rd",
    "sg:city":"Campsie",
    "sg:classifiers":[
        {
            "category":"Shopping",
            "subcategory":"Computers & Home Electronics",
            "type":"Retail Goods"
        }
    ],
    "sg:phone":"+61 2 9787 1314",
    "sg:postcode":"2194",
    "sg:province":"NSW",
    "sg:tags":[
        "hardware",
        "equipment"
    ],
    "wof:name":"MStation Technology Co.",
    "wof:placetype":"venue"
},
  "geometry": {"coordinates":[151.110596,-33.915539],"type":"Point"}
}