{
  "type": "Feature",
  "properties": {
    "iso:country":"AU",
    "sg:address":"31 Alexandra Ave",
    "sg:city":"Sunshine",
    "sg:classifiers":[
        {
            "category":"Social Services",
            "subcategory":"Child Care",
            "type":"Services"
        }
    ],
    "sg:phone":"+61 3 9310 2845",
    "sg:postcode":"3020",
    "sg:province":"VIC",
    "wof:name":"Alexandra Ave Childrens Centre Inc",
    "wof:placetype":"venue"
},
  "geometry": {"coordinates":[144.83874499999999,-37.782825],"type":"Point"}
}