{
  "type": "Feature",
  "properties": {
    "addr:full":"PO Box 8044 + Northland Centre VIC 3072",
    "addr:housenumber":"+",
    "addr:postcode":"3072",
    "addr:street":"Centre",
    "iso:country":"AU",
    "sg:address":"PO Box 8044",
    "sg:city":"+ Northland Centre",
    "sg:classifiers":[
        {
            "category":"Professional",
            "subcategory":"Testing Lab",
            "type":"Services"
        }
    ],
    "sg:phone":"+61 3 9442 2009",
    "sg:postcode":"3072",
    "sg:province":"VIC",
    "sg:tags":[
        "inspection"
    ],
    "wof:name":"Lonsdale Assist",
    "wof:placetype":"venue"
},
  "geometry": {"coordinates":[145.001785278,-37.7489204407],"type":"Point"}
}