{
  "type": "Feature",
  "properties": {
    "addr:full":"10 Adams St Preston VIC 3072",
    "addr:housenumber":"10",
    "addr:postcode":"3072",
    "addr:street":"Adams St",
    "iso:country":"AU",
    "sg:address":"10 Adams St",
    "sg:city":"Preston",
    "sg:classifiers":[
        {
            "category":"Train Station",
            "subcategory":"Light Rail",
            "type":"Transportation"
        }
    ],
    "sg:phone":"+61 3 9484 6002",
    "sg:postcode":"3072",
    "sg:province":"VIC",
    "sg:tags":[
        "survey",
        "traffic"
    ],
    "wof:name":"CFE Traffic Surveys",
    "wof:placetype":"venue"
},
  "geometry": {"coordinates":[145.019165039,-37.7531967163],"type":"Point"}
}