{
  "type": "Feature",
  "properties": {
    "iso:country":"AU",
    "sg:address":"Ground Floor, 1/150 King St",
    "sg:city":"Newcastle",
    "sg:classifiers":[
        {
            "category":"Health Services",
            "subcategory":"Doctor",
            "type":"Services"
        }
    ],
    "sg:phone":"+61 2 4979 3222",
    "sg:postcode":"2300",
    "sg:province":"NSW",
    "sg:tags":[
        "nurse",
        "nursing"
    ],
    "wof:name":"Drake Australia",
    "wof:placetype":"venue"
},
  "geometry": {"coordinates":[151.769516,-32.928211],"type":"Point"}
}