{
  "type": "Feature",
  "properties": {
    "addr:full":"363 High St, Kew VIC 3101",
    "addr:housenumber":"363",
    "addr:postcode":"3101",
    "addr:street":"High St",
    "iso:country":"AU",
    "sg:address":"363 High St,",
    "sg:city":"Kew",
    "sg:classifiers":[
        {
            "category":"Retail",
            "subcategory":"Repair Shop",
            "type":"Services"
        }
    ],
    "sg:phone":"+61 3 9855 1651",
    "sg:postcode":"3101",
    "sg:province":"VIC",
    "sg:tags":[
        "repairing",
        "piano",
        "tuning"
    ],
    "wof:name":"Hunters Pianoworks",
    "wof:placetype":"venue"
},
  "geometry": {"coordinates":[145.037765503,-37.8041343689],"type":"Point"}
}