{
  "type": "Feature",
  "properties": {
    "addr:full":"143 Francisco St Belmont WA 6104",
    "addr:housenumber":"143",
    "addr:postcode":"6104",
    "addr:street":"Francisco St",
    "iso:country":"AU",
    "sg:address":"143 Francisco St",
    "sg:city":"Belmont",
    "sg:classifiers":[
        {
            "category":"Home & Garden",
            "subcategory":"Furniture",
            "type":"Retail Goods"
        }
    ],
    "sg:phone":"+61 8 9477 6911",
    "sg:postcode":"6104",
    "sg:province":"WA",
    "sg:tags":[
        "business"
    ],
    "wof:name":"Office2U",
    "wof:placetype":"venue"
},
  "geometry": {"coordinates":[115.923027039,-31.9538249969],"type":"Point"}
}