{
  "type": "Feature",
  "properties": {
    "addr:full":"19 May St Parkes NSW 2870",
    "addr:housenumber":"19",
    "addr:postcode":"2870",
    "addr:street":"May St",
    "iso:country":"AU",
    "sg:address":"19 May St",
    "sg:city":"Parkes",
    "sg:classifiers":[
        {
            "category":"Home & Garden",
            "subcategory":"Garden Supply",
            "type":"Retail Goods"
        }
    ],
    "sg:phone":"+61 2 6862 5355",
    "sg:postcode":"2870",
    "sg:province":"NSW",
    "sg:tags":[
        "landscape"
    ],
    "wof:name":"Dirt Dr's Yard",
    "wof:placetype":"venue"
},
  "geometry": {"coordinates":[148.17550700000001,-33.141983],"type":"Point"}
}