{
  "type": "Feature",
  "properties": {
    "addr:full":"Unit 1/ 8 Blackmore Rd Smeaton Grange NSW 2567",
    "addr:housenumber":"8",
    "addr:postcode":"2567",
    "addr:street":"Blackmore Rd",
    "iso:country":"AU",
    "sg:address":"Unit 1/ 8 Blackmore Rd",
    "sg:city":"Smeaton Grange",
    "sg:classifiers":[
        {
            "category":"Building & Trades",
            "subcategory":"Construction",
            "type":"Services"
        }
    ],
    "sg:phone":"+61 2 4647 1155",
    "sg:postcode":"2567",
    "sg:province":"NSW",
    "sg:tags":[
        "welding"
    ],
    "wof:name":"Camden engineering",
    "wof:placetype":"venue"
},
  "geometry": {"coordinates":[150.75177001899999,-34.0385932922],"type":"Point"}
}