{
  "type": "Feature",
  "properties": {
    "iso:country":"AU",
    "sg:address":"33 Griffin Ave",
    "sg:city":"Tamworth",
    "sg:classifiers":[
        {
            "category":"Shopping",
            "subcategory":"Antiques",
            "type":"Retail Goods"
        }
    ],
    "sg:phone":"+61 2 6766 9920",
    "sg:postcode":"2340",
    "sg:province":"NSW",
    "sg:tags":[
        "restoration",
        "reproduction"
    ],
    "wof:name":"Howard Products (Aust)",
    "wof:placetype":"venue"
},
  "geometry": {"coordinates":[150.92887878400001,-31.0845432281],"type":"Point"}
}