{
  "type": "Feature",
  "properties": {
    "iso:country":"AU",
    "sg:address":"121 Bannister Rd",
    "sg:city":"Canning Vale",
    "sg:classifiers":[
        {
            "category":"Building & Trades",
            "subcategory":"Construction",
            "type":"Services"
        }
    ],
    "sg:phone":"+61 8 9334 4688",
    "sg:postcode":"6155",
    "sg:province":"WA",
    "sg:tags":[
        "roof"
    ],
    "wof:name":"BGC Metal Roofing",
    "wof:placetype":"venue"
},
  "geometry": {"coordinates":[115.915878,-32.057583],"type":"Point"}
}