{
  "type": "Feature",
  "properties": {
    "addr:full":"Uniting Church Hall 132 Keilor Rd Essendon North VIC 3041",
    "addr:housenumber":"132",
    "addr:postcode":"3041",
    "addr:street":"Keilor Rd",
    "iso:country":"AU",
    "sg:address":"Uniting Church Hall 132 Keilor Rd",
    "sg:city":"Essendon North",
    "sg:classifiers":[
        {
            "category":"Education",
            "subcategory":"Dance Studio",
            "type":"Public Place"
        }
    ],
    "sg:phone":"+61 3 9306 5851",
    "sg:postcode":"3041",
    "sg:province":"VIC",
    "sg:tags":[
        "venue",
        "tuition"
    ],
    "wof:name":"Western Academy Of Dance",
    "wof:placetype":"venue"
},
  "geometry": {"coordinates":[144.901977539,-37.7410392761],"type":"Point"}
}