{
  "type": "Feature",
  "properties": {
    "addr:full":"Unit 2/ 46- 50 Hugh Ryan Drv Garbutt QLD 4814",
    "addr:housenumber":"50",
    "addr:postcode":"4814",
    "addr:street":"Hugh Ryan Drv",
    "iso:country":"AU",
    "sg:address":"Unit 2/ 46- 50 Hugh Ryan Drv",
    "sg:city":"Garbutt",
    "sg:classifiers":[
        {
            "category":"Wholesale",
            "subcategory":"Machinery & Supplies",
            "type":"Manufacturing & Wholesale Goods"
        }
    ],
    "sg:phone":"+61 7 4725 2977",
    "sg:postcode":"4814",
    "sg:province":"QLD",
    "sg:tags":[
        "process",
        "instrument",
        "control"
    ],
    "wof:name":"Transmark FCX",
    "wof:placetype":"venue"
},
  "geometry": {"coordinates":[146.761124,-19.271149],"type":"Point"}
}