{
  "type": "Feature",
  "properties": {
    "addr:full":"8 Doree Pl Dora Creek NSW 2264",
    "addr:housenumber":"8",
    "addr:postcode":"2264",
    "addr:street":"Doree Pl Dora",
    "iso:country":"AU",
    "sg:address":"8 Doree Pl",
    "sg:city":"Dora Creek",
    "sg:classifiers":[
        {
            "category":"Health Services",
            "subcategory":"Doctor",
            "type":"Services"
        }
    ],
    "sg:phone":"+61 2 4973 1877",
    "sg:postcode":"2264",
    "sg:province":"NSW",
    "sg:tags":[
        "medical",
        "practitioner"
    ],
    "wof:name":"Shean W T",
    "wof:placetype":"venue"
},
  "geometry": {"coordinates":[151.50332599999999,-33.085274],"type":"Point"}
}