{
  "type": "Feature",
  "properties": {
    "addr:full":"244 Union Rd Ascot Vale VIC 3032",
    "addr:housenumber":"244",
    "addr:postcode":"3032",
    "addr:street":"Union Rd",
    "iso:country":"AU",
    "sg:address":"244 Union Rd",
    "sg:city":"Ascot Vale",
    "sg:classifiers":[
        {
            "category":"Health Services",
            "subcategory":"Dentist",
            "type":"Services"
        }
    ],
    "sg:phone":"+61 3 9375 1829",
    "sg:postcode":"3032",
    "sg:province":"VIC",
    "wof:name":"Ho Michael T L Dr",
    "wof:placetype":"venue"
},
  "geometry": {"coordinates":[144.91627500000001,-37.772141],"type":"Point"}
}