{
  "type": "Feature",
  "properties": {
    "addr:full":"Rooms 4 & 5, 108 Railway St Corrimal NSW 2518",
    "addr:housenumber":"4 & 5 108",
    "addr:postcode":"2518",
    "addr:street":"Railway St",
    "iso:country":"AU",
    "sg:address":"Rooms 4 & 5, 108 Railway St",
    "sg:city":"Corrimal",
    "sg:classifiers":[
        {
            "category":"Health Services",
            "subcategory":"Health Practitioner",
            "type":"Services"
        }
    ],
    "sg:phone":"+61 425 210 835",
    "sg:postcode":"2518",
    "sg:province":"NSW",
    "sg:tags":[
        "psychologist"
    ],
    "wof:name":"Kuter Paul",
    "wof:placetype":"venue"
},
  "geometry": {"coordinates":[150.89709500000001,-34.373047],"type":"Point"}
}