{
  "type": "Feature",
  "properties": {
    "addr:full":"105 Main St Stawell VIC 3380",
    "addr:housenumber":"105",
    "addr:postcode":"3380",
    "addr:street":"Main St",
    "iso:country":"AU",
    "sg:address":"105 Main St",
    "sg:city":"Stawell",
    "sg:classifiers":[
        {
            "category":"Casinos & Gambling",
            "type":"Entertainment"
        }
    ],
    "sg:phone":"+61 3 5358 1709",
    "sg:postcode":"3380",
    "sg:province":"VIC",
    "sg:tags":[
        "lottery",
        "agent"
    ],
    "wof:name":"Stawell Lotto",
    "wof:placetype":"venue"
},
  "geometry": {"coordinates":[142.78558349599999,-37.0525588989],"type":"Point"}
}