{
  "type": "Feature",
  "properties": {
    "addr:full":"Shp236/ 270 Canterbury Forest Hill VIC 3131",
    "addr:housenumber":"270",
    "addr:postcode":"3131",
    "addr:street":"Canterbury",
    "iso:country":"AU",
    "sg:address":"Shp236/ 270 Canterbury",
    "sg:city":"Forest Hill",
    "sg:classifiers":[
        {
            "category":"Personal",
            "subcategory":"Shoe Repair & Shine",
            "type":"Services"
        }
    ],
    "sg:phone":"+61 3 9894 1272",
    "sg:postcode":"3131",
    "sg:province":"VIC",
    "sg:tags":[
        "footwear"
    ],
    "wof:name":"Petro's Shoe Repairs",
    "wof:placetype":"venue"
},
  "geometry": {"coordinates":[145.173065186,-37.8350105286],"type":"Point"}
}