{
  "type": "Feature",
  "properties": {
    "addr:full":"10 Endeavour St Finley NSW 2713",
    "addr:housenumber":"10",
    "addr:postcode":"2713",
    "addr:street":"Endeavour St",
    "iso:country":"AU",
    "sg:address":"10 Endeavour St",
    "sg:city":"Finley",
    "sg:classifiers":[
        {
            "category":"Retail",
            "subcategory":"Auto Repair",
            "type":"Services"
        }
    ],
    "sg:phone":"+61 3 5883 1434",
    "sg:postcode":"2713",
    "sg:province":"NSW",
    "sg:tags":[
        "beater",
        "painter",
        "panel"
    ],
    "wof:name":"Agosta Panel Works",
    "wof:placetype":"venue"
},
  "geometry": {"coordinates":[145.57957458499999,-35.6407470703],"type":"Point"}
}