{
  "type": "Feature",
  "properties": {
    "iso:country":"AU",
    "sg:address":"188 Peel St",
    "sg:city":"North Melbourne",
    "sg:classifiers":[
        {
            "category":"Autos & Motor Vehicles",
            "subcategory":"Automobile Sales",
            "type":"Retail Goods"
        }
    ],
    "sg:phone":"+61 3 9329 9909",
    "sg:postcode":"3051",
    "sg:province":"VIC",
    "sg:tags":[
        "car",
        "new"
    ],
    "wof:name":"Citroen Melbourne",
    "wof:placetype":"venue"
},
  "geometry": {"coordinates":[144.956787109,-37.8028488159],"type":"Point"}
}