{
  "type": "Feature",
  "properties": {
    "addr:full":"Shp12/ 77 Hallam Rd Hampton Park VIC 3976",
    "addr:housenumber":"77",
    "addr:postcode":"3976",
    "addr:street":"Hallam Rd",
    "iso:country":"AU",
    "sg:address":"Shp12/ 77 Hallam Rd",
    "sg:city":"Hampton Park",
    "sg:classifiers":[
        {
            "category":"Food & Beverages",
            "subcategory":"Supermarket",
            "type":"Retail Goods"
        }
    ],
    "sg:phone":"+61 3 9799 1302",
    "sg:postcode":"3976",
    "sg:province":"VIC",
    "sg:tags":[
        "grocery",
        "store"
    ],
    "wof:name":"Pacific Mart",
    "wof:placetype":"venue"
},
  "geometry": {"coordinates":[145.26702880900001,-38.0352973938],"type":"Point"}
}