{
  "type": "Feature",
  "properties": {
    "addr:full":"253a Belmore Rd Balwyn North VIC 3104",
    "addr:housenumber":"253a",
    "addr:postcode":"3104",
    "addr:street":"Belmore Rd",
    "iso:country":"AU",
    "sg:address":"253a Belmore Rd",
    "sg:city":"Balwyn North",
    "sg:classifiers":[
        {
            "category":"Manufacturing",
            "subcategory":"Food",
            "type":"Manufacturing & Wholesale Goods"
        }
    ],
    "sg:phone":"+61 3 9816 3737",
    "sg:postcode":"3104",
    "sg:province":"VIC",
    "sg:tags":[
        "function",
        "catering"
    ],
    "wof:name":"FoodClews Fine Food & Catering",
    "wof:placetype":"venue"
},
  "geometry": {"coordinates":[145.08377075199999,-37.8033943176],"type":"Point"}
}