{
  "type": "Feature",
  "properties": {
    "addr:full":"152 Blues Point Rd McMahons Point NSW 2060",
    "addr:housenumber":"152",
    "addr:postcode":"2060",
    "addr:street":"Blues Point Rd",
    "iso:country":"AU",
    "sg:address":"152 Blues Point Rd",
    "sg:city":"McMahons Point",
    "sg:classifiers":[
        {
            "category":"Professional",
            "subcategory":"Business Services",
            "type":"Services"
        }
    ],
    "sg:phone":"+61 2 9922 3424",
    "sg:postcode":"2060",
    "sg:province":"NSW",
    "sg:tags":[
        "broker"
    ],
    "wof:name":"Peter O'Brien Business Agent",
    "wof:placetype":"venue"
},
  "geometry": {"coordinates":[151.20428466800001,-33.8441123962],"type":"Point"}
}