{
  "type": "Feature",
  "properties": {
    "iso:country":"AU",
    "sg:address":"1/ 2 Riedell St",
    "sg:city":"Wagga Wagga",
    "sg:classifiers":[
        {
            "category":"Utilities",
            "type":"Services"
        }
    ],
    "sg:phone":"+61 418 693 139",
    "sg:postcode":"2650",
    "sg:province":"NSW",
    "sg:tags":[
        "refrigeration",
        "industrial",
        "commercial",
        "retail"
    ],
    "wof:name":"Bowyer Refrigeration & Airconditioning",
    "wof:placetype":"venue"
},
  "geometry": {"coordinates":[147.344116211,-35.1184692383],"type":"Point"}
}