{
  "type": "Feature",
  "properties": {
    "addr:full":"Capital Ave Glen Waverley VIC 3150",
    "addr:postcode":"3150",
    "addr:street":"Capital Ave",
    "iso:country":"AU",
    "sg:address":"Capital Ave",
    "sg:city":"Glen Waverley",
    "sg:classifiers":[
        {
            "category":"Education",
            "subcategory":"School",
            "type":"Public Place"
        }
    ],
    "sg:phone":"+61 3 9803 5144",
    "sg:postcode":"3150",
    "sg:province":"VIC",
    "sg:tags":[
        "state",
        "except",
        "nsw"
    ],
    "wof:name":"Highvale Secondary College",
    "wof:placetype":"venue"
},
  "geometry": {"coordinates":[145.181442261,-37.871383667],"type":"Point"}
}