{
  "type": "Feature",
  "properties": {
    "addr:full":"11 Briarty Rd Coldstream VIC 3770",
    "addr:housenumber":"11",
    "addr:postcode":"3770",
    "addr:street":"Briarty Rd",
    "iso:country":"AU",
    "sg:address":"11 Briarty Rd",
    "sg:city":"Coldstream",
    "sg:classifiers":[
        {
            "category":"Farming",
            "subcategory":"Vineyard",
            "type":"Manufacturing & Wholesale Goods"
        }
    ],
    "sg:phone":"+61 3 5964 9266",
    "sg:postcode":"3770",
    "sg:province":"VIC",
    "sg:tags":[
        "winery"
    ],
    "wof:name":"Murrummong Vineyard",
    "wof:placetype":"venue"
},
  "geometry": {"coordinates":[145.47555500000001,-37.711594],"type":"Point"}
}