{
  "type": "Feature",
  "properties": {
    "addr:full":"603- 611 Whitehorse Rd Mitcham VIC 3132",
    "addr:housenumber":"603 611",
    "addr:postcode":"3132",
    "addr:street":"Whitehorse Rd",
    "iso:country":"AU",
    "sg:address":"603- 611 Whitehorse Rd",
    "sg:city":"Mitcham",
    "sg:classifiers":[
        {
            "category":"Autos & Motor Vehicles",
            "subcategory":"Boat Sales",
            "type":"Retail Goods"
        }
    ],
    "sg:phone":"+61 13 13 08",
    "sg:postcode":"3132",
    "sg:province":"VIC",
    "sg:tags":[
        "machine",
        "dishwashing"
    ],
    "wof:name":"Kleenmaid",
    "wof:placetype":"venue"
},
  "geometry": {"coordinates":[145.20367431599999,-37.8159103394],"type":"Point"}
}