{
  "type": "Feature",
  "properties": {
    "iso:country":"AU",
    "sg:address":"67 Sentry Drv",
    "sg:city":"Stanhope Gardens",
    "sg:classifiers":[
        {
            "category":"Social Services",
            "subcategory":"Child Care",
            "type":"Services"
        }
    ],
    "sg:phone":"+61 2 8883 2222",
    "sg:postcode":"2768",
    "sg:province":"NSW",
    "wof:name":"Abacus Kindergarden And Learning Centre Pty Ltd",
    "wof:placetype":"venue"
},
  "geometry": {"coordinates":[150.91850299999999,-33.723568],"type":"Point"}
}