{
  "type": "Feature",
  "properties": {
    "addr:full":"110, Cromwell St Collingwood VIC 3066",
    "addr:housenumber":"110",
    "addr:postcode":"3066",
    "addr:street":"Cromwell St",
    "iso:country":"AU",
    "sg:address":"110, Cromwell St",
    "sg:city":"Collingwood",
    "sg:classifiers":[
        {
            "category":"Wholesale",
            "subcategory":"Apparel",
            "type":"Manufacturing & Wholesale Goods"
        }
    ],
    "sg:phone":"+61 3 9419 6855",
    "sg:postcode":"3066",
    "sg:province":"VIC",
    "sg:tags":[
        "wholesaler",
        "mfrs",
        "uniform"
    ],
    "wof:name":"Bizwear Pty Ltd",
    "wof:placetype":"venue"
},
  "geometry": {"coordinates":[144.990356445,-37.8049468994],"type":"Point"}
}