{
  "type": "Feature",
  "properties": {
    "addr:full":"Purnong Rd Mannum SA 5238",
    "addr:postcode":"5238",
    "addr:street":"Purnong Rd",
    "iso:country":"AU",
    "sg:address":"Purnong Rd",
    "sg:city":"Mannum",
    "sg:classifiers":[
        {
            "category":"Commercial Area",
            "type":"Public Place"
        }
    ],
    "sg:phone":"+61 8 8569 1670",
    "sg:postcode":"5238",
    "sg:province":"SA",
    "sg:tags":[
        "heavy",
        "carrier"
    ],
    "wof:name":"Gowling N W",
    "wof:placetype":"venue"
},
  "geometry": {"coordinates":[139.31646728499999,-34.9099617004],"type":"Point"}
}