{
  "type": "Feature",
  "properties": {
    "iso:country":"AU",
    "sg:address":"176a Raglan St",
    "sg:city":"Mosman",
    "sg:classifiers":[
        {
            "category":"Real Estate",
            "subcategory":"Architect",
            "type":"Services"
        }
    ],
    "sg:phone":"+61 2 9969 7797",
    "sg:postcode":"2088",
    "sg:province":"NSW",
    "wof:name":"Murcutt G M",
    "wof:placetype":"venue"
},
  "geometry": {"coordinates":[151.24237060600001,-33.8320083618],"type":"Point"}
}