{
  "type": "Feature",
  "properties": {
    "addr:full":"56 Falvey St Ripley QLD 4306",
    "addr:housenumber":"56",
    "addr:postcode":"4306",
    "addr:street":"Falvey St",
    "iso:country":"AU",
    "sg:address":"56 Falvey St",
    "sg:city":"Ripley",
    "sg:classifiers":[
        {
            "category":"Utilities",
            "subcategory":"Electric",
            "type":"Services"
        }
    ],
    "sg:phone":"+61 7 3288 8418",
    "sg:postcode":"4306",
    "sg:province":"QLD",
    "sg:tags":[
        "electrical",
        "contractor"
    ],
    "wof:name":"Graig Hohenhaus",
    "wof:placetype":"venue"
},
  "geometry": {"coordinates":[152.78793335,-27.6649570465],"type":"Point"}
}