{
  "type": "Feature",
  "properties": {
    "iso:country":"AU",
    "sg:address":"28 William Angliss Drv",
    "sg:city":"Laverton North",
    "sg:classifiers":[
        {
            "category":"Autos & Motor Vehicles",
            "subcategory":"Auto Supplies",
            "type":"Retail Goods"
        }
    ],
    "sg:phone":"+61 3 9369 9209",
    "sg:postcode":"3026",
    "sg:province":"VIC",
    "sg:tags":[
        "equipment",
        "part",
        "truck"
    ],
    "wof:name":"Anteo Tail Lifts",
    "wof:placetype":"venue"
},
  "geometry": {"coordinates":[144.777283,-37.82288],"type":"Point"}
}