{
  "type": "Feature",
  "properties": {
    "addr:full":"56 Kent Rd North Ryde NSW 2113",
    "addr:housenumber":"56",
    "addr:postcode":"2113",
    "addr:street":"Kent Rd",
    "iso:country":"AU",
    "sg:address":"56 Kent Rd",
    "sg:city":"North Ryde",
    "sg:classifiers":[
        {
            "category":"Retail",
            "subcategory":"Auto Repair",
            "type":"Services"
        }
    ],
    "sg:phone":"+61 419 558 058",
    "sg:postcode":"2113",
    "sg:province":"NSW",
    "sg:tags":[
        "clutch",
        "brake"
    ],
    "wof:name":"Speedy On Car Disc Brake Machining",
    "wof:placetype":"venue"
},
  "geometry": {"coordinates":[151.1146698,-33.7904815674],"type":"Point"}
}