{
  "type": "Feature",
  "properties": {
    "addr:full":"55 East Pde Sutherland NSW 2232",
    "addr:housenumber":"55",
    "addr:postcode":"2232",
    "addr:street":"East Pde",
    "iso:country":"AU",
    "sg:address":"55 East Pde",
    "sg:city":"Sutherland",
    "sg:classifiers":[
        {
            "category":"Arena",
            "subcategory":"Sports Club",
            "type":"Entertainment"
        }
    ],
    "sg:phone":"+61 2 9589 0400",
    "sg:postcode":"2232",
    "sg:province":"NSW",
    "sg:tags":[
        "defence",
        "supply",
        "self",
        "instruction",
        "martial art"
    ],
    "wof:name":"Double Dragon Martial Arts Gym",
    "wof:placetype":"venue"
},
  "geometry": {"coordinates":[151.05619812,-34.0322036743],"type":"Point"}
}