{
  "type": "Feature",
  "properties": {
    "addr:full":"Shop 2 200 The Boulevarde Punchbowl NSW 2196",
    "addr:housenumber":"shop 2 200",
    "addr:postcode":"2196",
    "addr:street":"The Boulevarde",
    "iso:country":"AU",
    "sg:address":"Shop 2 200 The Boulevarde",
    "sg:city":"Punchbowl",
    "sg:classifiers":[
        {
            "category":"Shopping",
            "subcategory":"Clothing, Apparel, & Fashions",
            "type":"Retail Goods"
        }
    ],
    "sg:phone":"+61 2 9750 3276",
    "sg:postcode":"2196",
    "sg:province":"NSW",
    "sg:tags":[
        "uniform"
    ],
    "wof:name":"Saouma's School & Childrens Wear",
    "wof:placetype":"venue"
},
  "geometry": {"coordinates":[151.05737300000001,-33.925797],"type":"Point"}
}