{
  "type": "Feature",
  "properties": {
    "addr:full":"37 Sunderland Drv Banksia Beach QLD 4507",
    "addr:housenumber":"37",
    "addr:postcode":"4507",
    "addr:street":"Sunderland Drv",
    "iso:country":"AU",
    "sg:address":"37 Sunderland Drv",
    "sg:city":"Banksia Beach",
    "sg:classifiers":[
        {
            "category":"Professional",
            "subcategory":"Accounting & Tax Preparation",
            "type":"Services"
        }
    ],
    "sg:phone":"+61 7 3408 9644",
    "sg:postcode":"4507",
    "sg:province":"QLD",
    "sg:tags":[
        "accountant",
        "auditor"
    ],
    "wof:name":"Obt Accounting & Tax Pty Ltd",
    "wof:placetype":"venue"
},
  "geometry": {"coordinates":[153.13963317899999,-27.0448570251],"type":"Point"}
}