{
  "type": "Feature",
  "properties": {
    "addr:full":"635 Glenferrie Rd Hawthorn VIC 3122",
    "addr:housenumber":"635",
    "addr:postcode":"3122",
    "addr:street":"Glenferrie Rd",
    "iso:country":"AU",
    "sg:address":"635 Glenferrie Rd",
    "sg:city":"Hawthorn",
    "sg:classifiers":[
        {
            "category":"Health Services",
            "subcategory":"Chiropractor",
            "type":"Services"
        }
    ],
    "sg:phone":"+61 412 132 878",
    "sg:postcode":"3122",
    "sg:province":"VIC",
    "wof:name":"Dixon Joel A S",
    "wof:placetype":"venue"
},
  "geometry": {"coordinates":[145.03512573200001,-37.8229293823],"type":"Point"}
}