{
  "type": "Feature",
  "properties": {
    "addr:full":"Gertrude Healing Centre 202 Gertrude St Fitzroy VIC 3065",
    "addr:housenumber":"202",
    "addr:postcode":"3065",
    "addr:street":"Gertrude St",
    "iso:country":"AU",
    "sg:address":"Gertrude Healing Centre 202 Gertrude St",
    "sg:city":"Fitzroy",
    "sg:classifiers":[
        {
            "category":"Health Services",
            "subcategory":"Health Practitioner",
            "type":"Services"
        }
    ],
    "sg:phone":"+61 3 9417 7266",
    "sg:postcode":"3065",
    "sg:province":"VIC",
    "sg:tags":[
        "naturopath"
    ],
    "wof:name":"Gregory Cathcart",
    "wof:placetype":"venue"
},
  "geometry": {"coordinates":[144.98147582999999,-37.8063087463],"type":"Point"}
}