{
  "type": "Feature",
  "properties": {
    "addr:full":"1 Davey St Frankston VIC 3199",
    "addr:housenumber":"1",
    "addr:postcode":"3199",
    "addr:street":"Davey St",
    "iso:country":"AU",
    "sg:address":"1 Davey St",
    "sg:city":"Frankston",
    "sg:classifiers":[
        {
            "category":"Bars & Pubs",
            "subcategory":"Nightclub",
            "type":"Food & Drink"
        }
    ],
    "sg:phone":"+61 3 9783 7311",
    "sg:postcode":"3199",
    "sg:province":"VIC",
    "sg:tags":[
        "discotheque"
    ],
    "wof:name":"21st Century Dance Club",
    "wof:placetype":"venue"
},
  "geometry": {"coordinates":[145.087356567,-37.9985809326],"type":"Point"}
}