{
  "type": "Feature",
  "properties": {
    "iso:country":"AU",
    "sg:address":"PO Box 164",
    "sg:city":"Murgon",
    "sg:classifiers":[
        {
            "category":"Building & Trades",
            "subcategory":"Construction",
            "type":"Services"
        }
    ],
    "sg:phone":"+61 418 186 074",
    "sg:postcode":"4605",
    "sg:province":"QLD",
    "sg:tags":[
        "concrete",
        "contractor"
    ],
    "wof:name":"Beck Mark",
    "wof:placetype":"venue"
},
  "geometry": {"coordinates":[151.941757,-26.24209],"type":"Point"}
}