{
  "type": "Feature",
  "properties": {
    "addr:full":"4 Butler Pl Berrimah NT 0828",
    "addr:housenumber":"4",
    "addr:postcode":"nt 0828",
    "addr:street":"Butler Pl",
    "iso:country":"AU",
    "sg:address":"4 Butler Pl",
    "sg:city":"Berrimah",
    "sg:classifiers":[
        {
            "category":"Manufacturing",
            "subcategory":"Building Materials",
            "type":"Manufacturing & Wholesale Goods"
        }
    ],
    "sg:phone":"+61 8 8932 3111",
    "sg:postcode":"0828",
    "sg:province":"NT",
    "sg:tags":[
        "equipment",
        "handling"
    ],
    "wof:name":"Splice Line",
    "wof:placetype":"venue"
},
  "geometry": {"coordinates":[130.96817016599999,-12.4562473297],"type":"Point"}
}