{
  "type": "Feature",
  "properties": {
    "addr:full":"735 Heidelberg Rd Alphington VIC 3078",
    "addr:housenumber":"735",
    "addr:postcode":"3078",
    "addr:street":"Heidelberg Rd",
    "iso:country":"AU",
    "sg:address":"735 Heidelberg Rd",
    "sg:city":"Alphington",
    "sg:classifiers":[
        {
            "category":"Restaurant",
            "type":"Food & Drink"
        }
    ],
    "sg:phone":"+61 3 9499 1273",
    "sg:postcode":"3078",
    "sg:province":"VIC",
    "sg:website":"http://www.tastebudstjsrestcafe.com.au",
    "wof:name":"Tastebuds Courtyard & Caf\ufffd Restaurant",
    "wof:placetype":"venue"
},
  "geometry": {"coordinates":[145.03091430699999,-37.780670166],"type":"Point"}
}