{
  "type": "Feature",
  "properties": {
    "iso:country":"AU",
    "sg:address":"PO Box 648",
    "sg:city":"Ashgrove",
    "sg:classifiers":[
        {
            "category":"Professional",
            "subcategory":"Business Services",
            "type":"Services"
        }
    ],
    "sg:phone":"+61 7 3311 4451",
    "sg:postcode":"4060",
    "sg:province":"QLD",
    "sg:tags":[
        "processing",
        "word"
    ],
    "wof:name":"A Freelance Secretary",
    "wof:placetype":"venue"
},
  "geometry": {"coordinates":[152.99197387699999,-27.4456806183],"type":"Point"}
}