{
  "type": "Feature",
  "properties": {
    "iso:country":"AU",
    "sg:address":"8 Hoffman St",
    "sg:city":"Brunswick West",
    "sg:classifiers":[
        {
            "category":"Banks & Credit Unions",
            "subcategory":"Bank",
            "type":"Services"
        }
    ],
    "sg:phone":"+61 3 9388 9984",
    "sg:postcode":"3055",
    "sg:province":"VIC",
    "sg:tags":[
        "broker",
        "mortgage"
    ],
    "wof:name":"T N G Marketing",
    "wof:placetype":"venue"
},
  "geometry": {"coordinates":[144.94041442899999,-37.7665901184],"type":"Point"}
}