{
  "type": "Feature",
  "properties": {
    "addr:full":"1 Francis St East Sydney NSW 2010",
    "addr:housenumber":"1",
    "addr:postcode":"2010",
    "addr:street":"Francis St East",
    "iso:country":"AU",
    "sg:address":"1 Francis St",
    "sg:city":"East Sydney",
    "sg:classifiers":[
        {
            "category":"Insurance",
            "subcategory":"Insurance Agent",
            "type":"Services"
        }
    ],
    "sg:phone":"+61 2 9360 2244",
    "sg:postcode":"2010",
    "sg:province":"NSW",
    "sg:tags":[
        "broker"
    ],
    "wof:name":"B A C Insurance Brokers Pty Ltd",
    "wof:placetype":"venue"
},
  "geometry": {"coordinates":[151.21315002399999,-33.876121521],"type":"Point"}
}