{
  "type": "Feature",
  "properties": {
    "addr:full":"56 Kariboe St Biloela QLD 4715",
    "addr:housenumber":"56",
    "addr:postcode":"4715",
    "addr:street":"Kariboe St",
    "iso:country":"AU",
    "sg:address":"56 Kariboe St",
    "sg:city":"Biloela",
    "sg:classifiers":[
        {
            "category":"Travel",
            "subcategory":"Travel Agent",
            "type":"Entertainment"
        }
    ],
    "sg:phone":"+61 7 4992 1966",
    "sg:postcode":"4715",
    "sg:province":"QLD",
    "sg:tags":[
        "consultant"
    ],
    "wof:name":"Harvey World Travel",
    "wof:placetype":"venue"
},
  "geometry": {"coordinates":[150.51278686500001,-24.4011631012],"type":"Point"}
}