{
  "type": "Feature",
  "properties": {
    "iso:country":"AU",
    "sg:address":"28 Yambla St",
    "sg:city":"Clifton Hill",
    "sg:classifiers":[
        {
            "category":"Shopping",
            "subcategory":"Antiques",
            "type":"Retail Goods"
        }
    ],
    "sg:phone":"+61 3 9489 0713",
    "sg:postcode":"3068",
    "sg:province":"VIC",
    "sg:tags":[
        "restoration",
        "reproduction"
    ],
    "wof:name":"Clifton Upholstery",
    "wof:placetype":"venue"
},
  "geometry": {"coordinates":[145.00114440900001,-37.7918281555],"type":"Point"}
}