{
  "type": "Feature",
  "properties": {
    "addr:full":"16 Church St Corowa NSW 2646",
    "addr:housenumber":"16",
    "addr:postcode":"2646",
    "addr:street":"Church St",
    "iso:country":"AU",
    "sg:address":"16 Church St",
    "sg:city":"Corowa",
    "sg:classifiers":[
        {
            "category":"Banks & Credit Unions",
            "subcategory":"Bureau De Change",
            "type":"Services"
        }
    ],
    "sg:phone":"+61 2 6033 3360",
    "sg:postcode":"2646",
    "sg:province":"NSW",
    "sg:tags":[
        "repairs",
        "part",
        "appliance",
        "electrical"
    ],
    "wof:name":"Godde Electrical Appliance Repairs",
    "wof:placetype":"venue"
},
  "geometry": {"coordinates":[146.39085388199999,-35.9978179932],"type":"Point"}
}