{
  "type": "Feature",
  "properties": {
    "iso:country":"AU",
    "sg:address":"18 Torquata Crt",
    "sg:city":"Hoppers Crossing",
    "sg:classifiers":[
        {
            "category":"Professional",
            "subcategory":"Employment Agencies",
            "type":"Services"
        }
    ],
    "sg:phone":"+61 3 9749 3789",
    "sg:postcode":"3029",
    "sg:province":"VIC",
    "sg:tags":[
        "hire",
        "labour",
        "contractor"
    ],
    "wof:name":"Statewide Labour Hire Pty Ltd",
    "wof:placetype":"venue"
},
  "geometry": {"coordinates":[144.710342,-37.858528],"type":"Point"}
}