{
  "type": "Feature",
  "properties": {
    "addr:full":"PO Box 275, Dnsbro, 6281 Dunsborough WA 6281",
    "addr:housenumber":"6281",
    "addr:postcode":"6281",
    "addr:street":"Dnsbro",
    "iso:country":"AU",
    "sg:address":"PO Box 275, Dnsbro, 6281",
    "sg:city":"Dunsborough",
    "sg:classifiers":[
        {
            "category":"Home & Garden",
            "subcategory":"Building Materials",
            "type":"Retail Goods"
        }
    ],
    "sg:phone":"+61 8 9756 8678",
    "sg:postcode":"6281",
    "sg:province":"WA",
    "sg:tags":[
        "balustrading"
    ],
    "wof:name":"Steel Stile Stainless Steel Wire Balustrade",
    "wof:placetype":"venue"
},
  "geometry": {"coordinates":[115.107513428,-33.6170043945],"type":"Point"}
}