{
  "type": "Feature",
  "properties": {
    "iso:country":"AU",
    "sg:address":"Level 2, 454 - 456 Peel St",
    "sg:city":"Tamworth",
    "sg:classifiers":[
        {
            "category":"Shopping",
            "subcategory":"Computers & Home Electronics",
            "type":"Retail Goods"
        }
    ],
    "sg:phone":"+61 2 6766 3233",
    "sg:postcode":"2340",
    "sg:province":"NSW",
    "sg:tags":[
        "hardware",
        "equipment"
    ],
    "sg:website":"http://www.tamworthit.com.au",
    "wof:name":"Tamworth I.T. Solutions",
    "wof:placetype":"venue"
},
  "geometry": {"coordinates":[150.93263244600001,-31.0935153961],"type":"Point"}
}