{
  "type": "Feature",
  "properties": {
    "iso:country":"AU",
    "sg:address":"Shop 5, 2012 Logan Rd",
    "sg:city":"Upper Mt Gravatt",
    "sg:classifiers":[
        {
            "category":"Health Services",
            "subcategory":"Health Practitioner",
            "type":"Services"
        }
    ],
    "sg:phone":"+61 7 3420 0300",
    "sg:postcode":"4122",
    "sg:province":"QLD",
    "sg:tags":[
        "acupuncture"
    ],
    "wof:name":"Hung Yuan Chi (Jackie)",
    "wof:placetype":"venue"
},
  "geometry": {"coordinates":[153.08085632300001,-27.5587615967],"type":"Point"}
}