{
  "type": "Feature",
  "properties": {
    "iso:country":"AU",
    "sg:address":"28 Heaths Rd",
    "sg:city":"Hoppers Crossing",
    "sg:classifiers":[
        {
            "category":"Retail",
            "subcategory":"Auto Repair",
            "type":"Services"
        }
    ],
    "sg:phone":"+61 3 9974 5666",
    "sg:postcode":"3029",
    "sg:province":"VIC",
    "sg:tags":[
        "repairer",
        "motor",
        "engineer"
    ],
    "wof:name":"Werribee Mazda",
    "wof:placetype":"venue"
},
  "geometry": {"coordinates":[144.703293,-37.879333],"type":"Point"}
}