{
  "type": "Feature",
  "properties": {
    "addr:full":"202 Tena Rd Highclere TAS 7321",
    "addr:housenumber":"202",
    "addr:postcode":"7321",
    "addr:street":"Tena Rd",
    "iso:country":"AU",
    "sg:address":"202 Tena Rd",
    "sg:city":"Highclere",
    "sg:classifiers":[
        {
            "category":"Wholesale",
            "subcategory":"Meat",
            "type":"Manufacturing & Wholesale Goods"
        }
    ],
    "sg:phone":"+61 3 6435 7324",
    "sg:postcode":"7321",
    "sg:province":"TAS",
    "sg:tags":[
        "abattoir"
    ],
    "wof:name":"Highclere Abattoirs & Butchery",
    "wof:placetype":"venue"
},
  "geometry": {"coordinates":[145.79289199999999,-41.212517],"type":"Point"}
}