{
  "type": "Feature",
  "properties": {
    "addr:full":"Shop 4/ 1 Diment St Hurstville NSW 2220",
    "addr:housenumber":"shop 4 / 1",
    "addr:postcode":"2220",
    "addr:street":"Diment St",
    "iso:country":"AU",
    "sg:address":"Shop 4/ 1 Diment St",
    "sg:city":"Hurstville",
    "sg:classifiers":[
        {
            "category":"Cafe",
            "type":"Food & Drink"
        }
    ],
    "sg:phone":"+61 2 9579 1311",
    "sg:postcode":"2220",
    "sg:province":"NSW",
    "wof:name":"Espresso Lane Cafe",
    "wof:placetype":"venue"
},
  "geometry": {"coordinates":[151.10293579099999,-33.9665336609],"type":"Point"}
}