{
  "type": "Feature",
  "properties": {
    "iso:country":"AU",
    "sg:address":"Shop 3/ 16 Cliff Rd",
    "sg:city":"North Wollongong",
    "sg:classifiers":[
        {
            "category":"Personal",
            "subcategory":"Beauty Salon",
            "type":"Services"
        }
    ],
    "sg:phone":"+61 2 4226 1213",
    "sg:postcode":"2500",
    "sg:province":"NSW",
    "sg:tags":[
        "hairdresser"
    ],
    "wof:name":"Colours at North Beach",
    "wof:placetype":"venue"
},
  "geometry": {"coordinates":[150.900665,-34.415241],"type":"Point"}
}