{
  "type": "Feature",
  "properties": {
    "iso:country":"AU",
    "sg:address":"15 Glen Eira Rd",
    "sg:city":"Balaclava",
    "sg:classifiers":[
        {
            "category":"Health Services",
            "subcategory":"Dentist",
            "type":"Services"
        }
    ],
    "sg:phone":"+61 3 9532 4828",
    "sg:postcode":"3183",
    "sg:province":"VIC",
    "sg:tags":[
        "dental",
        "prosthetist"
    ],
    "wof:name":"Glen Eira Denture Clinic",
    "wof:placetype":"venue"
},
  "geometry": {"coordinates":[144.99586486800001,-37.8765258789],"type":"Point"}
}