{
  "type": "Feature",
  "properties": {
    "addr:full":"PO Box 211 Altona North VIC 3025",
    "addr:postcode":"3025",
    "iso:country":"AU",
    "sg:address":"PO Box 211",
    "sg:city":"Altona North",
    "sg:classifiers":[
        {
            "category":"Manufacturing",
            "subcategory":"Food",
            "type":"Manufacturing & Wholesale Goods"
        }
    ],
    "sg:phone":"+61 1800 677 233",
    "sg:postcode":"3025",
    "sg:province":"VIC",
    "sg:tags":[
        "function",
        "catering"
    ],
    "wof:name":"Fabulous Feast",
    "wof:placetype":"venue"
},
  "geometry": {"coordinates":[144.84158300000001,-37.830509],"type":"Point"}
}