{
  "type": "Feature",
  "properties": {
    "iso:country":"AU",
    "sg:address":"Shp5/ 2 Elizabeth St",
    "sg:city":"Melbourne",
    "sg:classifiers":[
        {
            "category":"Cafe",
            "type":"Food & Drink"
        }
    ],
    "sg:phone":"+61 3 9650 6545",
    "sg:postcode":"3000",
    "sg:province":"VIC",
    "wof:name":"Box Coffee",
    "wof:placetype":"venue"
},
  "geometry": {"coordinates":[144.965087891,-37.8180389404],"type":"Point"}
}