{
  "type": "Feature",
  "properties": {
    "iso:country":"AU",
    "sg:address":"219 Bannister Rd",
    "sg:city":"Canning Vale",
    "sg:classifiers":[
        {
            "category":"Transit Center",
            "subcategory":"Freight",
            "type":"Transportation"
        }
    ],
    "sg:phone":"+61 8 9311 5200",
    "sg:postcode":"6155",
    "sg:province":"WA",
    "sg:tags":[
        "forklift",
        "truck"
    ],
    "wof:name":"Toyota Material Handling (WA) Pty Ltd",
    "wof:placetype":"venue"
},
  "geometry": {"coordinates":[115.90368700000001,-32.062656],"type":"Point"}
}