{
  "type": "Feature",
  "properties": {
    "addr:full":"3/ 252 New Line Rd Dural NSW 2158",
    "addr:housenumber":"/ 252",
    "addr:postcode":"2158",
    "addr:street":"New Line Rd",
    "iso:country":"AU",
    "sg:address":"3/ 252 New Line Rd",
    "sg:city":"Dural",
    "sg:classifiers":[
        {
            "category":"Manufacturing",
            "subcategory":"Motor Vehicles & Parts",
            "type":"Manufacturing & Wholesale Goods"
        }
    ],
    "sg:phone":"+61 2 9651 7144",
    "sg:postcode":"2158",
    "sg:province":"NSW",
    "sg:tags":[
        "replacement"
    ],
    "wof:name":"Autobarn Pty Ltd",
    "wof:placetype":"venue"
},
  "geometry": {"coordinates":[151.03053283700001,-33.6961898804],"type":"Point"}
}