{
  "type": "Feature",
  "properties": {
    "addr:full":"Suite 2, Enfield Plaza 449 Main North Rd Enfield SA 5085",
    "addr:housenumber":"449",
    "addr:postcode":"5085",
    "addr:street":"Main North Rd",
    "iso:country":"AU",
    "sg:address":"Suite 2, Enfield Plaza 449 Main North Rd",
    "sg:city":"Enfield",
    "sg:classifiers":[
        {
            "category":"Health Services",
            "subcategory":"Doctor",
            "type":"Services"
        }
    ],
    "sg:phone":"+61 1300 665 337",
    "sg:postcode":"5085",
    "sg:province":"SA",
    "sg:tags":[
        "medical",
        "practitioner"
    ],
    "wof:name":"Molescan",
    "wof:placetype":"venue"
},
  "geometry": {"coordinates":[138.600875855,-34.8544998169],"type":"Point"}
}