{
  "type": "Feature",
  "properties": {
    "addr:full":"29 South Western Hwy Picton WA 6229",
    "addr:housenumber":"29",
    "addr:postcode":"6229",
    "addr:street":"South Western Hwy",
    "iso:country":"AU",
    "sg:address":"29 South Western Hwy",
    "sg:city":"Picton",
    "sg:classifiers":[
        {
            "category":"Professional",
            "type":"Services"
        }
    ],
    "sg:phone":"+61 8 9725 4484",
    "sg:postcode":"6229",
    "sg:province":"WA",
    "sg:tags":[
        "industrial",
        "commercial",
        "catering"
    ],
    "wof:name":"Marges Place & Snack Bar",
    "wof:placetype":"venue"
},
  "geometry": {"coordinates":[115.69967699999999,-33.349293],"type":"Point"}
}