{
  "type": "Feature",
  "properties": {
    "iso:country":"AU",
    "sg:address":"227 River St",
    "sg:city":"Ballina",
    "sg:classifiers":[
        {
            "category":"Travel",
            "subcategory":"Hotels & Motels",
            "type":"Entertainment"
        }
    ],
    "sg:phone":"+61 2 6686 9100",
    "sg:postcode":"2478",
    "sg:province":"NSW",
    "wof:name":"Golden Chain Richmond Motor Inn",
    "wof:placetype":"venue"
},
  "geometry": {"coordinates":[153.55743408199999,-28.8690986633],"type":"Point"}
}