{
  "type": "Feature",
  "properties": {
    "addr:full":"302 Hobart Rd Kings Meadows TAS 7249",
    "addr:housenumber":"302",
    "addr:postcode":"7249",
    "addr:street":"Hobart Rd",
    "iso:country":"AU",
    "sg:address":"302 Hobart Rd",
    "sg:city":"Kings Meadows",
    "sg:classifiers":[
        {
            "category":"Food & Beverages",
            "subcategory":"Supermarket",
            "type":"Retail Goods"
        }
    ],
    "sg:phone":"+61 3 6344 6435",
    "sg:postcode":"7249",
    "sg:province":"TAS",
    "sg:tags":[
        "grocery",
        "store"
    ],
    "wof:name":"Southside Village Supermarket & Newsagency",
    "wof:placetype":"venue"
},
  "geometry": {"coordinates":[147.167205811,-41.4804649353],"type":"Point"}
}