{
  "type": "Feature",
  "properties": {
    "addr:full":"89 Princess St Urana NSW 2645",
    "addr:housenumber":"89",
    "addr:postcode":"2645",
    "addr:street":"Princess St",
    "iso:country":"AU",
    "sg:address":"89 Princess St",
    "sg:city":"Urana",
    "sg:classifiers":[
        {
            "category":"Farming",
            "subcategory":"Farm & Veterinary Services",
            "type":"Manufacturing & Wholesale Goods"
        }
    ],
    "sg:phone":"+61 2 6920 8265",
    "sg:postcode":"2645",
    "sg:province":"NSW",
    "sg:tags":[
        "shearing",
        "contractor"
    ],
    "wof:name":"Hanlon Les",
    "wof:placetype":"venue"
},
  "geometry": {"coordinates":[146.26560974099999,-35.3231391907],"type":"Point"}
}