{
  "type": "Feature",
  "properties": {
    "addr:full":"164 Beechboro Rd Bayswater WA 6053",
    "addr:housenumber":"164",
    "addr:postcode":"6053",
    "addr:street":"Beechboro Rd",
    "iso:country":"AU",
    "sg:address":"164 Beechboro Rd",
    "sg:city":"Bayswater",
    "sg:classifiers":[
        {
            "category":"Utilities",
            "subcategory":"Water",
            "type":"Services"
        }
    ],
    "sg:phone":"+61 8 9272 4100",
    "sg:postcode":"6053",
    "sg:province":"WA",
    "sg:tags":[
        "equipment",
        "treatment"
    ],
    "wof:name":"Chatoyer Water Treatment",
    "wof:placetype":"venue"
},
  "geometry": {"coordinates":[115.919952393,-31.9003372192],"type":"Point"}
}