{
  "type": "Feature",
  "properties": {
    "addr:full":"Cnr Pangeza & Quill Sts, 19 Quill Street, Stafford Heights QLD 4053",
    "addr:housenumber":"19",
    "addr:postcode":"4053",
    "addr:street":"Cnr Pangeza & Quill Sts;Quill Street",
    "iso:country":"AU",
    "sg:address":"Cnr Pangeza & Quill Sts, 19",
    "sg:city":"Quill Street, Stafford Heights",
    "sg:classifiers":[
        {
            "category":"Health Services",
            "subcategory":"Medical Lab",
            "type":"Services"
        }
    ],
    "sg:phone":"+61 7 3359 6667",
    "sg:postcode":"4053",
    "sg:province":"QLD",
    "sg:tags":[
        "laboratory",
        "dental"
    ],
    "wof:name":"Graham Hannam",
    "wof:placetype":"venue"
},
  "geometry": {"coordinates":[153.018112183,-27.3986701965],"type":"Point"}
}