{
  "type": "Feature",
  "properties": {
    "addr:full":"Merino Arcade 118a Eagle St Longreach QLD 4730",
    "addr:housenumber":"118a",
    "addr:postcode":"4730",
    "addr:street":"Eagle St",
    "iso:country":"AU",
    "sg:address":"Merino Arcade 118a Eagle St",
    "sg:city":"Longreach",
    "sg:classifiers":[
        {
            "category":"Personal",
            "subcategory":"Beauty Salon",
            "type":"Services"
        }
    ],
    "sg:phone":"+61 7 4658 1451",
    "sg:postcode":"4730",
    "sg:province":"QLD",
    "sg:tags":[
        "hairdresser"
    ],
    "wof:name":"Gaby's Unisex Hair Design",
    "wof:placetype":"venue"
},
  "geometry": {"coordinates":[144.24877900000001,-23.442669],"type":"Point"}
}