{
  "type": "Feature",
  "properties": {
    "iso:country":"AU",
    "sg:address":"Cnr Shafton Ave & Rawlins St",
    "sg:city":"Kangaroo Point",
    "sg:classifiers":[
        {
            "category":"Building & Trades",
            "subcategory":"Locksmith",
            "type":"Services"
        }
    ],
    "sg:phone":"+61 1800 806 067",
    "sg:postcode":"4169",
    "sg:province":"QLD",
    "sg:tags":[
        "lock"
    ],
    "wof:name":"Mobile Locksmiths",
    "wof:placetype":"venue"
},
  "geometry": {"coordinates":[153.03872680699999,-27.4782276154],"type":"Point"}
}