{
  "type": "Feature",
  "properties": {
    "addr:full":"Shp1/ 148 Railway Pde Kogarah NSW 2217",
    "addr:housenumber":"148",
    "addr:postcode":"2217",
    "addr:street":"Railway Pde",
    "iso:country":"AU",
    "sg:address":"Shp1/ 148 Railway Pde",
    "sg:city":"Kogarah",
    "sg:classifiers":[
        {
            "category":"Restaurant",
            "type":"Food & Drink"
        }
    ],
    "sg:phone":"+61 2 9553 0501",
    "sg:postcode":"2217",
    "sg:province":"NSW",
    "wof:name":"Alanya Turkish Pizza",
    "wof:placetype":"venue"
},
  "geometry": {"coordinates":[151.13185100000001,-33.96537],"type":"Point"}
}