{
  "type": "Feature",
  "properties": {
    "addr:full":"Suite 3/40 Reid St Wangaratta VIC 3677",
    "addr:housenumber":"40",
    "addr:postcode":"3677",
    "addr:street":"Reid St",
    "iso:country":"AU",
    "sg:address":"Suite 3/40 Reid St",
    "sg:city":"Wangaratta",
    "sg:classifiers":[
        {
            "category":"Health Services",
            "subcategory":"Health Practitioner",
            "type":"Services"
        }
    ],
    "sg:phone":"+61 3 5721 2885",
    "sg:postcode":"3677",
    "sg:province":"VIC",
    "sg:tags":[
        "psychologist"
    ],
    "wof:name":"Matrix Psychology Services",
    "wof:placetype":"venue"
},
  "geometry": {"coordinates":[146.32664489699999,-36.3551330566],"type":"Point"}
}