{
  "type": "Feature",
  "properties": {
    "iso:country":"AU",
    "sg:address":"PO Box 853",
    "sg:city":"Kensington Private Bxs",
    "sg:classifiers":[
        {
            "category":"Education",
            "subcategory":"Dance Studio",
            "type":"Public Place"
        }
    ],
    "sg:phone":"+61 2 9385 0339",
    "sg:postcode":"1465",
    "sg:province":"NSW",
    "sg:tags":[
        "instruction",
        "language"
    ],
    "wof:name":"University of New South Wales, Institute of Languages",
    "wof:placetype":"venue"
},
  "geometry": {"coordinates":[151.223419189,-33.9090003967],"type":"Point"}
}