{
  "type": "Feature",
  "properties": {
    "addr:full":"161 Alison Rd Randwick NSW 2031",
    "addr:housenumber":"161",
    "addr:postcode":"2031",
    "addr:street":"Alison Rd",
    "iso:country":"AU",
    "sg:address":"161 Alison Rd",
    "sg:city":"Randwick",
    "sg:classifiers":[
        {
            "category":"Education",
            "subcategory":"Dance Studio",
            "type":"Public Place"
        }
    ],
    "sg:phone":"+61 2 9398 8658",
    "sg:postcode":"2031",
    "sg:province":"NSW",
    "sg:tags":[
        "venue",
        "tuition"
    ],
    "wof:name":"Logan Dance Sydney",
    "wof:placetype":"venue"
},
  "geometry": {"coordinates":[151.239135742,-33.9128341675],"type":"Point"}
}