{
  "type": "Feature",
  "properties": {
    "iso:country":"AU",
    "sg:address":"Shop 5/ 149 Waterloo Rd",
    "sg:city":"Greenacre",
    "sg:classifiers":[
        {
            "category":"Personal",
            "subcategory":"Beauty Salon",
            "type":"Services"
        }
    ],
    "sg:phone":"+61 2 9740 6371",
    "sg:postcode":"2190",
    "sg:province":"NSW",
    "sg:tags":[
        "hairdresser"
    ],
    "wof:name":"E.L. Masri Barber Salon",
    "wof:placetype":"venue"
},
  "geometry": {"coordinates":[151.058792,-33.898537],"type":"Point"}
}