{
  "type": "Feature",
  "properties": {
    "addr:full":"124- 128 De Fredricks La Yarrambat VIC 3091",
    "addr:housenumber":"124 128",
    "addr:postcode":"3091",
    "addr:street":"De Fredricks La",
    "iso:country":"AU",
    "sg:address":"124- 128 De Fredricks La",
    "sg:city":"Yarrambat",
    "sg:classifiers":[
        {
            "category":"Professional",
            "subcategory":"Accounting & Tax Preparation",
            "type":"Services"
        }
    ],
    "sg:phone":"+61 3 9436 2121",
    "sg:postcode":"3091",
    "sg:province":"VIC",
    "sg:tags":[
        "insulation",
        "wholesaler",
        "material",
        "mfrs"
    ],
    "wof:name":"Reflecta Batts Pty Ltd",
    "wof:placetype":"venue"
},
  "geometry": {"coordinates":[145.14649963400001,-37.6368560791],"type":"Point"}
}