{
  "type": "Feature",
  "properties": {
    "iso:country":"AU",
    "sg:address":"Lewis St",
    "sg:city":"Coolamon",
    "sg:classifiers":[
        {
            "category":"Sports & Exercise",
            "subcategory":"Golf",
            "type":"Entertainment"
        }
    ],
    "sg:phone":"+61 2 6927 3178",
    "sg:postcode":"2701",
    "sg:province":"NSW",
    "sg:tags":[
        "club"
    ],
    "wof:name":"Coolamon Golf Club",
    "wof:placetype":"venue"
},
  "geometry": {"coordinates":[147.20533752399999,-34.8161697388],"type":"Point"}
}