{
  "type": "Feature",
  "properties": {
    "addr:full":"405 Sydenham St Belmont WA 6104",
    "addr:housenumber":"405",
    "addr:postcode":"6104",
    "addr:street":"Sydenham St",
    "iso:country":"AU",
    "sg:address":"405 Sydenham St",
    "sg:city":"Belmont",
    "sg:classifiers":[
        {
            "category":"Banks & Credit Unions",
            "subcategory":"Financial Services",
            "type":"Services"
        }
    ],
    "sg:phone":"+61 8 9479 4467",
    "sg:postcode":"6104",
    "sg:province":"WA",
    "sg:tags":[
        "settlement",
        "nt",
        "agent",
        "wa"
    ],
    "wof:name":"Precise Settlements",
    "wof:placetype":"venue"
},
  "geometry": {"coordinates":[115.946472168,-31.949174881],"type":"Point"}
}