{
  "type": "Feature",
  "properties": {
    "addr:full":"Level 1, 176 Cumberland St The Rocks The Rocks NSW 2000",
    "addr:housenumber":"176",
    "addr:postcode":"2000",
    "addr:street":"Cumberland St",
    "iso:country":"AU",
    "sg:address":"Level 1, 176 Cumberland St The Rocks",
    "sg:city":"The Rocks",
    "sg:classifiers":[
        {
            "category":"Restaurant",
            "type":"Food & Drink"
        }
    ],
    "sg:phone":"+61 2 9250 6206",
    "sg:postcode":"2000",
    "sg:province":"NSW",
    "wof:name":"Cafe Mix",
    "wof:placetype":"venue"
},
  "geometry": {"coordinates":[151.20628356899999,-33.8611831665],"type":"Point"}
}