{
  "type": "Feature",
  "properties": {
    "addr:full":"Shop 6 20 Howard Ave Dee Why NSW 2099",
    "addr:housenumber":"shop;20",
    "addr:postcode":"2099",
    "addr:street":"Howard Ave",
    "iso:country":"AU",
    "sg:address":"Shop 6 20 Howard Ave",
    "sg:city":"Dee Why",
    "sg:classifiers":[
        {
            "category":"Personal",
            "subcategory":"Day Spa",
            "type":"Services"
        }
    ],
    "sg:phone":"+61 2 9982 5332",
    "sg:postcode":"2099",
    "sg:province":"NSW",
    "wof:name":"Street Retreat Beauty Spa",
    "wof:placetype":"venue"
},
  "geometry": {"coordinates":[151.28848266599999,-33.7525672913],"type":"Point"}
}