{
  "type": "Feature",
  "properties": {
    "iso:country":"AU",
    "sg:address":"Shop 8 Big Top Shopping Cntr, 1230 Logan Rd",
    "sg:city":"Mt Gravatt",
    "sg:classifiers":[
        {
            "category":"Shopping",
            "subcategory":"Computers & Home Electronics",
            "type":"Retail Goods"
        }
    ],
    "sg:phone":"+61 7 3849 7655",
    "sg:postcode":"4122",
    "sg:province":"QLD",
    "sg:tags":[
        "equipment",
        "supply"
    ],
    "wof:name":"CY Computermart",
    "wof:placetype":"venue"
},
  "geometry": {"coordinates":[153.072433472,-27.5300540924],"type":"Point"}
}