{
  "type": "Feature",
  "properties": {
    "iso:country":"AU",
    "sg:address":"Unit 17",
    "sg:city":"Pearcedale Village Shopping Centre Pearcedale",
    "sg:classifiers":[
        {
            "category":"Autos & Motor Vehicles",
            "subcategory":"Fuel & Gas Station",
            "type":"Retail Goods"
        }
    ],
    "sg:phone":"+61 3 5978 7244",
    "sg:postcode":"3912",
    "sg:province":"VIC",
    "wof:name":"Shell Federation Motor Garage",
    "wof:placetype":"venue"
},
  "geometry": {"coordinates":[145.23358154300001,-38.2103157043],"type":"Point"}
}