{
  "type": "Feature",
  "properties": {
    "iso:country":"AU",
    "sg:address":"22 Northcott Ave",
    "sg:city":"Wyong",
    "sg:classifiers":[
        {
            "category":"Building & Trades",
            "subcategory":"Construction",
            "type":"Services"
        }
    ],
    "sg:phone":"+61 2 4352 2389",
    "sg:postcode":"2259",
    "sg:province":"NSW",
    "sg:tags":[
        "joinery"
    ],
    "wof:name":"Lou Borg Joinery",
    "wof:placetype":"venue"
},
  "geometry": {"coordinates":[151.427825928,-33.2740707397],"type":"Point"}
}