{
  "type": "Feature",
  "properties": {
    "addr:full":"6 Strickland St Rose Bay NSW 2029",
    "addr:housenumber":"6",
    "addr:postcode":"2029",
    "addr:street":"Strickland St",
    "iso:country":"AU",
    "sg:address":"6 Strickland St",
    "sg:city":"Rose Bay",
    "sg:classifiers":[
        {
            "category":"Banks & Credit Unions",
            "subcategory":"Financial Services",
            "type":"Services"
        }
    ],
    "sg:phone":"+61 2 9388 2815",
    "sg:postcode":"2029",
    "sg:province":"NSW",
    "sg:tags":[
        "loan",
        "finance",
        "mortgage"
    ],
    "wof:name":"Pacific Finance Group Pty Ltd",
    "wof:placetype":"venue"
},
  "geometry": {"coordinates":[151.27487182600001,-33.8725204468],"type":"Point"}
}