{
  "type": "Feature",
  "properties": {
    "addr:full":"Whitehead St Corowa NSW 2646",
    "addr:postcode":"2646",
    "addr:street":"Whitehead St",
    "iso:country":"AU",
    "sg:address":"Whitehead St",
    "sg:city":"Corowa",
    "sg:classifiers":[
        {
            "category":"Home & Garden",
            "subcategory":"Building Materials",
            "type":"Retail Goods"
        }
    ],
    "sg:phone":"+61 2 6033 1899",
    "sg:postcode":"2646",
    "sg:province":"NSW",
    "sg:tags":[
        "supply"
    ],
    "wof:name":"Maclean Max & Co Pty Ltd",
    "wof:placetype":"venue"
},
  "geometry": {"coordinates":[146.387405395,-35.9914627075],"type":"Point"}
}