{
  "type": "Feature",
  "properties": {
    "iso:country":"AU",
    "sg:address":"136 Main Rd",
    "sg:city":"Moonah",
    "sg:classifiers":[
        {
            "category":"Home & Garden",
            "subcategory":"Garden Supply",
            "type":"Retail Goods"
        }
    ],
    "sg:phone":"+61 3 6278 9210",
    "sg:postcode":"7009",
    "sg:province":"TAS",
    "sg:tags":[
        "equipment"
    ],
    "wof:name":"Tool Market The",
    "wof:placetype":"venue"
},
  "geometry": {"coordinates":[147.29339599599999,-42.8449516296],"type":"Point"}
}