{
  "type": "Feature",
  "properties": {
    "iso:country":"AU",
    "sg:address":"Lot 2 Bohle Rd",
    "sg:city":"Rasmussen",
    "sg:classifiers":[
        {
            "category":"Home & Garden",
            "subcategory":"Garden Supply",
            "type":"Retail Goods"
        }
    ],
    "sg:phone":"+61 414 490 735",
    "sg:postcode":"4815",
    "sg:province":"QLD",
    "sg:tags":[
        "turf",
        "lawn"
    ],
    "wof:name":"Bohle Grass Turf Farm",
    "wof:placetype":"venue"
},
  "geometry": {"coordinates":[146.702896,-19.342276],"type":"Point"}
}