{
  "type": "Feature",
  "properties": {
    "iso:country":"AU",
    "sg:address":"PO Box 201",
    "sg:city":"Bright",
    "sg:classifiers":[
        {
            "category":"Personal",
            "subcategory":"Massage",
            "type":"Services"
        }
    ],
    "sg:phone":"+61 3 5756 2050",
    "sg:postcode":"3741",
    "sg:province":"VIC",
    "sg:tags":[
        "therapy"
    ],
    "wof:name":"Hall, Paula D, C.M.T.",
    "wof:placetype":"venue"
},
  "geometry": {"coordinates":[146.960129,-36.72739],"type":"Point"}
}