{
  "type": "Feature",
  "properties": {
    "addr:full":"Unit 4 118 Connaught St Sandgate QLD 4017",
    "addr:housenumber":"118",
    "addr:postcode":"4017",
    "addr:street":"Connaught St",
    "iso:country":"AU",
    "sg:address":"Unit 4 118 Connaught St",
    "sg:city":"Sandgate",
    "sg:classifiers":[
        {
            "category":"Shopping",
            "subcategory":"Stationery & Office Supplies",
            "type":"Retail Goods"
        }
    ],
    "sg:phone":"+61 7 3869 2255",
    "sg:postcode":"4017",
    "sg:province":"QLD",
    "sg:tags":[
        "packaging",
        "material"
    ],
    "wof:name":"Precision Packaging",
    "wof:placetype":"venue"
},
  "geometry": {"coordinates":[153.056732178,-27.3186511993],"type":"Point"}
}