{
  "type": "Feature",
  "properties": {
    "iso:country":"AU",
    "sg:address":"7 Vida Ave",
    "sg:city":"Redwood Park",
    "sg:classifiers":[
        {
            "category":"Health Services",
            "subcategory":"Health Practitioner",
            "type":"Services"
        }
    ],
    "sg:phone":"+61 8 8395 9295",
    "sg:postcode":"5097",
    "sg:province":"SA",
    "sg:tags":[
        "naturopath"
    ],
    "wof:name":"Daniela Nita MD(Ro)Dip.Hom.",
    "wof:placetype":"venue"
},
  "geometry": {"coordinates":[138.707107544,-34.809337616],"type":"Point"}
}