{
  "type": "Feature",
  "properties": {
    "addr:full":"U3/ 5 Rose St Hawthorn East VIC 3123",
    "addr:housenumber":"5",
    "addr:postcode":"3123",
    "addr:street":"U3 /;Rose St",
    "iso:country":"AU",
    "sg:address":"U3/ 5 Rose St",
    "sg:city":"Hawthorn East",
    "sg:classifiers":[
        {
            "category":"Wholesale",
            "subcategory":"Non-durable Goods",
            "type":"Manufacturing & Wholesale Goods"
        }
    ],
    "sg:phone":"+61 3 9882 2845",
    "sg:postcode":"3123",
    "sg:province":"VIC",
    "sg:tags":[
        "wholesaler",
        "mfrs",
        "cosmetic"
    ],
    "wof:name":"Apivita Natural Products",
    "wof:placetype":"venue"
},
  "geometry": {"coordinates":[145.05203247099999,-37.8297767639],"type":"Point"}
}