{
  "type": "Feature",
  "properties": {
    "addr:full":"361 Newbridge Rd Moorebank NSW 2170",
    "addr:housenumber":"361",
    "addr:postcode":"2170",
    "addr:street":"Newbridge Rd",
    "iso:country":"AU",
    "sg:address":"361 Newbridge Rd",
    "sg:city":"Moorebank",
    "sg:classifiers":[
        {
            "category":"Retail",
            "subcategory":"Auto Repair",
            "type":"Services"
        }
    ],
    "sg:phone":"+61 2 9601 3155",
    "sg:postcode":"2170",
    "sg:province":"NSW",
    "sg:tags":[
        "recapping",
        "repairing",
        "retreading",
        "tyre"
    ],
    "wof:name":"Tyre Distributors",
    "wof:placetype":"venue"
},
  "geometry": {"coordinates":[150.935745239,-33.9296607971],"type":"Point"}
}