{
  "type": "Feature",
  "properties": {
    "addr:full":"126 Callan Ave Maryland NSW 2287",
    "addr:housenumber":"126",
    "addr:postcode":"2287",
    "addr:street":"Callan Ave",
    "iso:country":"AU",
    "sg:address":"126 Callan Ave",
    "sg:city":"Maryland",
    "sg:classifiers":[
        {
            "category":"Personal",
            "type":"Services"
        }
    ],
    "sg:phone":"+61 2 9502 0031",
    "sg:postcode":"2287",
    "sg:province":"NSW",
    "sg:tags":[
        "reducing",
        "treatment",
        "weight"
    ],
    "wof:name":"Herbalife Australasia Pty Ltd",
    "wof:placetype":"venue"
},
  "geometry": {"coordinates":[151.65733337399999,-32.8719863892],"type":"Point"}
}