{
  "type": "Feature",
  "properties": {
    "iso:country":"AU",
    "sg:address":"Centenary Ave",
    "sg:city":"Wandiligong",
    "sg:classifiers":[
        {
            "category":"Building & Trades",
            "subcategory":"Construction",
            "type":"Services"
        }
    ],
    "sg:phone":"+61 3 5755 2389",
    "sg:postcode":"3744",
    "sg:province":"VIC",
    "sg:tags":[
        "brick",
        "paving"
    ],
    "wof:name":"Eric & S. de Carheil",
    "wof:placetype":"venue"
},
  "geometry": {"coordinates":[146.97846999999999,-36.780388],"type":"Point"}
}