{
  "type": "Feature",
  "properties": {
    "addr:full":"13 Port St Port Sorell TAS 7307",
    "addr:housenumber":"13",
    "addr:postcode":"7307",
    "addr:street":"Port St",
    "iso:country":"AU",
    "sg:address":"13 Port St",
    "sg:city":"Port Sorell",
    "sg:classifiers":[
        {
            "category":"Building & Trades",
            "subcategory":"Construction",
            "type":"Services"
        }
    ],
    "sg:phone":"+61 3 6428 6357",
    "sg:postcode":"7307",
    "sg:province":"TAS",
    "sg:tags":[
        "contractor"
    ],
    "wof:name":"Templar Brian",
    "wof:placetype":"venue"
},
  "geometry": {"coordinates":[146.55836500000001,-41.170868],"type":"Point"}
}