{
  "type": "Feature",
  "properties": {
    "addr:full":"23 Boulder Rd Kalgoorlie WA 6430",
    "addr:housenumber":"23",
    "addr:postcode":"6430",
    "addr:street":"Boulder Rd",
    "iso:country":"AU",
    "sg:address":"23 Boulder Rd",
    "sg:city":"Kalgoorlie",
    "sg:classifiers":[
        {
            "category":"Fast Food",
            "type":"Food & Drink"
        }
    ],
    "sg:phone":"+61 8 9021 3555",
    "sg:postcode":"6430",
    "sg:province":"WA",
    "sg:tags":[
        "away",
        "take"
    ],
    "wof:name":"Hungry Jacks Pty Ltd",
    "wof:placetype":"venue"
},
  "geometry": {"coordinates":[121.47651672400001,-30.7479496002],"type":"Point"}
}