{
  "type": "Feature",
  "properties": {
    "addr:full":"17a Fourth St Booragul NSW 2284",
    "addr:housenumber":"17a",
    "addr:postcode":"2284",
    "addr:street":"Fourth St",
    "iso:country":"AU",
    "sg:address":"17a Fourth St",
    "sg:city":"Booragul",
    "sg:classifiers":[
        {
            "category":"Retail",
            "subcategory":"Driving School",
            "type":"Services"
        }
    ],
    "sg:phone":"+61 2 4954 8333",
    "sg:postcode":"2284",
    "sg:province":"NSW",
    "wof:name":"Holdings Driver Training",
    "wof:placetype":"venue"
},
  "geometry": {"coordinates":[151.60850524899999,-32.9710006714],"type":"Point"}
}