{
  "type": "Feature",
  "properties": {
    "addr:full":"200- 202 High St Northcote VIC 3070",
    "addr:housenumber":"202",
    "addr:postcode":"3070",
    "addr:street":"High St",
    "iso:country":"AU",
    "sg:address":"200- 202 High St",
    "sg:city":"Northcote",
    "sg:classifiers":[
        {
            "category":"Retail",
            "subcategory":"Auto Repair",
            "type":"Services"
        }
    ],
    "sg:phone":"+61 3 9482 5169",
    "sg:postcode":"3070",
    "sg:province":"VIC",
    "sg:tags":[
        "clutch",
        "brake"
    ],
    "wof:name":"Motafit Service Centres",
    "wof:placetype":"venue"
},
  "geometry": {"coordinates":[144.99818400000001,-37.774212],"type":"Point"}
}