{
  "type": "Feature",
  "properties": {
    "addr:full":"4 Derby Rd Caulfield East VIC 3145",
    "addr:housenumber":"4",
    "addr:postcode":"3145",
    "addr:street":"Derby Rd",
    "iso:country":"AU",
    "sg:address":"4 Derby Rd",
    "sg:city":"Caulfield East",
    "sg:classifiers":[
        {
            "category":"Restaurant",
            "type":"Food & Drink"
        }
    ],
    "sg:phone":"+61 3 9571 1306",
    "sg:postcode":"3145",
    "sg:province":"VIC",
    "wof:name":"Derby Thai",
    "wof:placetype":"venue"
},
  "geometry": {"coordinates":[145.04193115199999,-37.8763504028],"type":"Point"}
}