{
  "type": "Feature",
  "properties": {
    "iso:country":"AU",
    "sg:address":"21 Wragg St",
    "sg:city":"Somerset",
    "sg:classifiers":[
        {
            "category":"Retail",
            "subcategory":"Auto Repair",
            "type":"Services"
        }
    ],
    "sg:phone":"+61 3 6435 1740",
    "sg:postcode":"7322",
    "sg:province":"TAS",
    "sg:tags":[
        "repairer",
        "motor",
        "engineer"
    ],
    "wof:name":"Cam Filling Station",
    "wof:placetype":"venue"
},
  "geometry": {"coordinates":[145.833496,-41.042553],"type":"Point"}
}