{
  "type": "Feature",
  "properties": {
    "addr:full":"PO Box 3007 Central Park VIC 3145",
    "addr:postcode":"3145",
    "addr:street":"Park",
    "iso:country":"AU",
    "sg:address":"PO Box 3007",
    "sg:city":"Central Park",
    "sg:classifiers":[
        {
            "category":"Professional",
            "subcategory":"Employment Agencies",
            "type":"Services"
        }
    ],
    "sg:phone":"+61 3 9885 3388",
    "sg:postcode":"3145",
    "sg:province":"VIC",
    "sg:tags":[
        "model"
    ],
    "wof:name":"Bubblegum Casting",
    "wof:placetype":"venue"
},
  "geometry": {"coordinates":[145.04893493599999,-37.867641449],"type":"Point"}
}