{
  "type": "Feature",
  "properties": {
    "addr:full":"Unit 6/ 7 Brentham St Leederville WA 6007",
    "addr:housenumber":"7",
    "addr:postcode":"6007",
    "addr:street":"Brentham St",
    "iso:country":"AU",
    "sg:address":"Unit 6/ 7 Brentham St",
    "sg:city":"Leederville",
    "sg:classifiers":[
        {
            "category":"Real Estate",
            "subcategory":"Architect",
            "type":"Services"
        }
    ],
    "sg:phone":"+61 8 9201 0495",
    "sg:postcode":"6007",
    "sg:province":"WA",
    "wof:name":"Penka Parova Architects",
    "wof:placetype":"venue"
},
  "geometry": {"coordinates":[115.838661194,-31.9299221039],"type":"Point"}
}