{
  "type": "Feature",
  "properties": {
    "addr:full":"2 Dickson St Avondale Heights VIC 3034",
    "addr:housenumber":"2",
    "addr:postcode":"3034",
    "addr:street":"Dickson St",
    "iso:country":"AU",
    "sg:address":"2 Dickson St",
    "sg:city":"Avondale Heights",
    "sg:classifiers":[
        {
            "category":"Building & Trades",
            "subcategory":"Construction",
            "type":"Services"
        }
    ],
    "sg:phone":"+61 3 9337 0279",
    "sg:postcode":"3034",
    "sg:province":"VIC",
    "sg:tags":[
        "contractor"
    ],
    "wof:name":"Leander Constructions Pty Ltd",
    "wof:placetype":"venue"
},
  "geometry": {"coordinates":[144.87411499999999,-37.753098],"type":"Point"}
}