{
  "type": "Feature",
  "properties": {
    "addr:full":"Lower Paper Mill Rd Fyansford VIC 3221",
    "addr:postcode":"3221",
    "addr:street":"Paper Mill Rd",
    "iso:country":"AU",
    "sg:address":"Lower Paper Mill Rd",
    "sg:city":"Fyansford",
    "sg:classifiers":[
        {
            "category":"Home & Garden",
            "subcategory":"Building Materials",
            "type":"Retail Goods"
        }
    ],
    "sg:phone":"+61 1300 360 082",
    "sg:postcode":"3221",
    "sg:province":"VIC",
    "sg:tags":[
        "fencing"
    ],
    "wof:name":"Emu Wire Industries",
    "wof:placetype":"venue"
},
  "geometry": {"coordinates":[144.30711400000001,-38.144211],"type":"Point"}
}