{
  "type": "Feature",
  "properties": {
    "addr:full":"44 Woodhill St Castle Hill NSW 2154",
    "addr:housenumber":"44",
    "addr:postcode":"2154",
    "addr:street":"Woodhill St",
    "iso:country":"AU",
    "sg:address":"44 Woodhill St",
    "sg:city":"Castle Hill",
    "sg:classifiers":[
        {
            "category":"Professional",
            "subcategory":"Art Services",
            "type":"Services"
        }
    ],
    "sg:phone":"+61 2 9899 4266",
    "sg:postcode":"2154",
    "sg:province":"NSW",
    "sg:tags":[
        "graphic",
        "designer"
    ],
    "wof:name":"Composer Art Studio",
    "wof:placetype":"venue"
},
  "geometry": {"coordinates":[151.00379943900001,-33.7432746887],"type":"Point"}
}