{
  "type": "Feature",
  "properties": {
    "iso:country":"AU",
    "sg:address":"200 Elder St",
    "sg:city":"Greensborough",
    "sg:classifiers":[
        {
            "category":"Retail",
            "subcategory":"Veterinary Services",
            "type":"Services"
        }
    ],
    "sg:phone":"+61 3 9434 7155",
    "sg:postcode":"3088",
    "sg:province":"VIC",
    "sg:tags":[
        "surgeon"
    ],
    "wof:name":"Cat Protection Society Of Victoria",
    "wof:placetype":"venue"
},
  "geometry": {"coordinates":[145.103317261,-37.7170410156],"type":"Point"}
}