{
  "type": "Feature",
  "properties": {
    "iso:country":"AU",
    "sg:address":"326 Church St",
    "sg:city":"Richmond",
    "sg:classifiers":[
        {
            "category":"Government",
            "subcategory":"City Hall",
            "type":"Public Place"
        }
    ],
    "sg:phone":"+61 3 8420 6789",
    "sg:postcode":"3121",
    "sg:province":"VIC",
    "wof:name":"St Ignatius Meeting Room",
    "wof:placetype":"venue"
},
  "geometry": {"coordinates":[144.99845886200001,-37.821762085],"type":"Point"}
}