{
  "type": "Feature",
  "properties": {
    "addr:full":"25 Kirkaldy St Bathurst NSW 2795",
    "addr:housenumber":"25",
    "addr:postcode":"2795",
    "addr:street":"Kirkaldy St",
    "iso:country":"AU",
    "sg:address":"25 Kirkaldy St",
    "sg:city":"Bathurst",
    "sg:classifiers":[
        {
            "category":"Manufacturing",
            "subcategory":"Motor Vehicles & Parts",
            "type":"Manufacturing & Wholesale Goods"
        }
    ],
    "sg:phone":"+61 2 6332 2331",
    "sg:postcode":"2795",
    "sg:province":"NSW",
    "sg:tags":[
        "replacement"
    ],
    "wof:name":"Bathurst Auto Parts",
    "wof:placetype":"venue"
},
  "geometry": {"coordinates":[149.57963562,-33.4368667603],"type":"Point"}
}