{
  "type": "Feature",
  "properties": {
    "addr:full":"Cnr George & Webster Rds Deception Bay QLD 4508",
    "addr:postcode":"4508",
    "addr:street":"Cnr George &;Rds",
    "iso:country":"AU",
    "sg:address":"Cnr George & Webster Rds",
    "sg:city":"Deception Bay",
    "sg:classifiers":[
        {
            "category":"Social Services",
            "subcategory":"Retirement Home",
            "type":"Services"
        }
    ],
    "sg:phone":"+61 7 3385 9900",
    "sg:postcode":"4508",
    "sg:province":"QLD",
    "sg:tags":[
        "village"
    ],
    "wof:name":"Palm Lake Resort",
    "wof:placetype":"venue"
},
  "geometry": {"coordinates":[153.011276245,-27.187543869],"type":"Point"}
}