{
  "type": "Feature",
  "properties": {
    "addr:full":"99 Sutton St Redcliffe QLD 4020",
    "addr:housenumber":"99",
    "addr:postcode":"4020",
    "addr:street":"Sutton St",
    "iso:country":"AU",
    "sg:address":"99 Sutton St",
    "sg:city":"Redcliffe",
    "sg:classifiers":[
        {
            "category":"Professional",
            "subcategory":"Accounting & Tax Preparation",
            "type":"Services"
        }
    ],
    "sg:phone":"+61 7 3284 0444",
    "sg:postcode":"4020",
    "sg:province":"QLD",
    "sg:tags":[
        "consultant",
        "taxation"
    ],
    "wof:name":"Liddy, Kennelly",
    "wof:placetype":"venue"
},
  "geometry": {"coordinates":[153.11563100000001,-27.231392],"type":"Point"}
}