{
  "type": "Feature",
  "properties": {
    "addr:full":"8 Benwerrin Rd Loganholme QLD 4129",
    "addr:housenumber":"8",
    "addr:postcode":"4129",
    "addr:street":"Benwerrin Rd",
    "iso:country":"AU",
    "sg:address":"8 Benwerrin Rd",
    "sg:city":"Loganholme",
    "sg:classifiers":[
        {
            "category":"Personal",
            "subcategory":"Beauty Salon",
            "type":"Services"
        }
    ],
    "sg:phone":"+61 7 3801 1965",
    "sg:postcode":"4129",
    "sg:province":"QLD",
    "sg:tags":[
        "hair",
        "wedding"
    ],
    "wof:name":"Nye Shelly",
    "wof:placetype":"venue"
},
  "geometry": {"coordinates":[153.18327331500001,-27.6790523529],"type":"Point"}
}