{
  "type": "Feature",
  "properties": {
    "addr:full":"92 Okinja Rd Alexandra Headland QLD 4572",
    "addr:housenumber":"92",
    "addr:postcode":"4572",
    "addr:street":"Okinja Rd",
    "iso:country":"AU",
    "sg:address":"92 Okinja Rd",
    "sg:city":"Alexandra Headland",
    "sg:classifiers":[
        {
            "category":"Autos & Motor Vehicles",
            "subcategory":"Automobile Sales",
            "type":"Retail Goods"
        }
    ],
    "sg:phone":"+61 7 5443 6152",
    "sg:postcode":"4572",
    "sg:province":"QLD",
    "sg:tags":[
        "equipment",
        "trailer"
    ],
    "wof:name":"Everlast Trailers",
    "wof:placetype":"venue"
},
  "geometry": {"coordinates":[153.09875500000001,-26.66823],"type":"Point"}
}