{
  "type": "Feature",
  "properties": {
    "addr:full":"McIntosh Ave Glossop SA 5344",
    "addr:postcode":"5344",
    "addr:street":"Mcintosh Ave",
    "iso:country":"AU",
    "sg:address":"McIntosh Ave",
    "sg:city":"Glossop",
    "sg:classifiers":[
        {
            "category":"Farming",
            "subcategory":"Berry Farm",
            "type":"Manufacturing & Wholesale Goods"
        }
    ],
    "sg:phone":"+61 8 8583 2245",
    "sg:postcode":"5344",
    "sg:province":"SA",
    "sg:tags":[
        "fruit",
        "grower"
    ],
    "wof:name":"Kypreos A",
    "wof:placetype":"venue"
},
  "geometry": {"coordinates":[140.53640747099999,-34.2812576294],"type":"Point"}
}