{
  "type": "Feature",
  "properties": {
    "iso:country":"AU",
    "sg:address":"139 Silverwater Rd",
    "sg:city":"Silverwater",
    "sg:classifiers":[
        {
            "category":"Home & Garden",
            "subcategory":"Furniture",
            "type":"Retail Goods"
        }
    ],
    "sg:phone":"+61 2 9648 3183",
    "sg:postcode":"2128",
    "sg:province":"NSW",
    "sg:tags":[
        "business"
    ],
    "wof:name":"Atom Welders",
    "wof:placetype":"venue"
},
  "geometry": {"coordinates":[151.048217773,-33.8345985413],"type":"Point"}
}