{
  "type": "Feature",
  "properties": {
    "addr:full":"410 Nepean Hwy Chelsea VIC 3196",
    "addr:housenumber":"410",
    "addr:postcode":"3196",
    "addr:street":"Nepean Hwy",
    "iso:country":"AU",
    "sg:address":"410 Nepean Hwy",
    "sg:city":"Chelsea",
    "sg:classifiers":[
        {
            "category":"Real Estate",
            "subcategory":"Real Estate Agent",
            "type":"Services"
        }
    ],
    "sg:phone":"+61 3 9772 9600",
    "sg:postcode":"3196",
    "sg:province":"VIC",
    "wof:name":"Brad Hollingworth First National",
    "wof:placetype":"venue"
},
  "geometry": {"coordinates":[145.116455078,-38.0537147522],"type":"Point"}
}