{
  "type": "Feature",
  "properties": {
    "addr:full":"PO Box 299 Nanango QLD 4615",
    "addr:postcode":"4615",
    "iso:country":"AU",
    "sg:address":"PO Box 299",
    "sg:city":"Nanango",
    "sg:classifiers":[
        {
            "category":"Retail",
            "subcategory":"Auto Repair",
            "type":"Services"
        }
    ],
    "sg:phone":"+61 417 631 899",
    "sg:postcode":"4615",
    "sg:province":"QLD",
    "sg:tags":[
        "automotive",
        "air conditioning"
    ],
    "wof:name":"Eddies",
    "wof:placetype":"venue"
},
  "geometry": {"coordinates":[152.00094604500001,-26.6758708954],"type":"Point"}
}