{
  "type": "Feature",
  "properties": {
    "addr:full":"1112 Tathra Rd Jellat Jellat NSW 2550",
    "addr:housenumber":"1112",
    "addr:postcode":"2550",
    "addr:street":"Tathra Rd",
    "iso:country":"AU",
    "sg:address":"1112 Tathra Rd",
    "sg:city":"Jellat Jellat",
    "sg:classifiers":[
        {
            "category":"Building & Trades",
            "subcategory":"Construction",
            "type":"Services"
        }
    ],
    "sg:phone":"+61 2 6492 0022",
    "sg:postcode":"2550",
    "sg:province":"NSW",
    "sg:tags":[
        "contractor"
    ],
    "wof:name":"Mark Roberts Building Design & Construction",
    "wof:placetype":"venue"
},
  "geometry": {"coordinates":[149.8828125,-36.7157821655],"type":"Point"}
}