{
  "type": "Feature",
  "properties": {
    "iso:country":"AU",
    "sg:address":"Unit 2 49 Heron Ave",
    "sg:city":"Mermaid Beach",
    "sg:classifiers":[
        {
            "category":"Building & Trades",
            "subcategory":"Construction",
            "type":"Services"
        }
    ],
    "sg:phone":"+61 416 195 731",
    "sg:postcode":"4218",
    "sg:province":"QLD",
    "sg:tags":[
        "joiner",
        "carpenter"
    ],
    "wof:name":"Ben Johnston Carpenter",
    "wof:placetype":"venue"
},
  "geometry": {"coordinates":[153.43655395499999,-28.0536346436],"type":"Point"}
}