{
  "type": "Feature",
  "properties": {
    "addr:full":"279 Hannan St Kalgoorlie WA 6430",
    "addr:housenumber":"279",
    "addr:postcode":"6430",
    "addr:street":"Hannan St",
    "iso:country":"AU",
    "sg:address":"279 Hannan St",
    "sg:city":"Kalgoorlie",
    "sg:classifiers":[
        {
            "category":"Food & Beverages",
            "subcategory":"Specialty",
            "type":"Retail Goods"
        }
    ],
    "sg:phone":"+61 8 9021 8509",
    "sg:postcode":"6430",
    "sg:province":"WA",
    "sg:tags":[
        "product",
        "health"
    ],
    "wof:name":"Go Vita Kalgoorlie",
    "wof:placetype":"venue"
},
  "geometry": {"coordinates":[121.46926879900001,-30.7502212524],"type":"Point"}
}