{
  "type": "Feature",
  "properties": {
    "addr:full":"7 Radovick St Korumburra VIC 3950",
    "addr:housenumber":"7",
    "addr:postcode":"3950",
    "addr:street":"Radovick St",
    "iso:country":"AU",
    "sg:address":"7 Radovick St",
    "sg:city":"Korumburra",
    "sg:classifiers":[
        {
            "category":"Retail",
            "subcategory":"Auto Repair",
            "type":"Services"
        }
    ],
    "sg:phone":"+61 3 5655 1522",
    "sg:postcode":"3950",
    "sg:province":"VIC",
    "sg:tags":[
        "repairer",
        "motor",
        "engineer"
    ],
    "wof:name":"Boston's Garage",
    "wof:placetype":"venue"
},
  "geometry": {"coordinates":[145.82281494099999,-38.4323501587],"type":"Point"}
}