{
  "type": "Feature",
  "properties": {
    "addr:full":"11 Carisbrook Crs Lower Plenty VIC 3093",
    "addr:housenumber":"11",
    "addr:postcode":"3093",
    "addr:street":"Carisbrook Crs",
    "iso:country":"AU",
    "sg:address":"11 Carisbrook Crs",
    "sg:city":"Lower Plenty",
    "sg:classifiers":[
        {
            "category":"Building & Trades",
            "subcategory":"Plumbing",
            "type":"Services"
        }
    ],
    "sg:phone":"+61 3 9435 2830",
    "sg:postcode":"3093",
    "sg:province":"VIC",
    "sg:tags":[
        "plumber",
        "gasfitters"
    ],
    "wof:name":"Simondson W A",
    "wof:placetype":"venue"
},
  "geometry": {"coordinates":[145.16569519000001,-37.7867355347],"type":"Point"}
}