{
  "type": "Feature",
  "properties": {
    "addr:full":"637 Ipswich Rd Annerley QLD 4103",
    "addr:housenumber":"637",
    "addr:postcode":"4103",
    "addr:street":"Ipswich Rd",
    "iso:country":"AU",
    "sg:address":"637 Ipswich Rd",
    "sg:city":"Annerley",
    "sg:classifiers":[
        {
            "category":"Banks & Credit Unions",
            "subcategory":"Investment Brokerage",
            "type":"Services"
        }
    ],
    "sg:phone":"+61 1300 556 638",
    "sg:postcode":"4103",
    "sg:province":"QLD",
    "sg:tags":[
        "finance",
        "broker"
    ],
    "wof:name":"Cyber Mortgage",
    "wof:placetype":"venue"
},
  "geometry": {"coordinates":[153.029495239,-27.5175018311],"type":"Point"}
}