{
  "type": "Feature",
  "properties": {
    "iso:country":"AU",
    "sg:address":"340 Lake Rd",
    "sg:city":"Glendale",
    "sg:classifiers":[
        {
            "category":"Retail",
            "subcategory":"Auto Rental",
            "type":"Services"
        }
    ],
    "sg:phone":"+61 1800 736 825",
    "sg:postcode":"2285",
    "sg:province":"NSW",
    "sg:tags":[
        "car",
        "hire",
        "minibus"
    ],
    "wof:name":"Network Car & Truck Rentals",
    "wof:placetype":"venue"
},
  "geometry": {"coordinates":[151.643676758,-32.9282417297],"type":"Point"}
}