{
  "type": "Feature",
  "properties": {
    "iso:country":"AU",
    "sg:address":"PO Box 323",
    "sg:city":"Rozelle",
    "sg:classifiers":[
        {
            "category":"Personal",
            "type":"Services"
        }
    ],
    "sg:phone":"+61 2 9560 9366",
    "sg:postcode":"2039",
    "sg:province":"NSW",
    "sg:tags":[
        "introduction",
        "social"
    ],
    "wof:name":"Rave Guzzle & Gorge",
    "wof:placetype":"venue"
},
  "geometry": {"coordinates":[151.17036438,-33.8634414673],"type":"Point"}
}