{
  "type": "Feature",
  "properties": {
    "addr:full":"5 Wellington Crs Torquay QLD 4655",
    "addr:housenumber":"5",
    "addr:postcode":"4655",
    "addr:street":"Wellington Crs",
    "iso:country":"AU",
    "sg:address":"5 Wellington Crs",
    "sg:city":"Torquay",
    "sg:classifiers":[
        {
            "category":"Education",
            "subcategory":"Special Training",
            "type":"Public Place"
        }
    ],
    "sg:phone":"+61 7 4125 3340",
    "sg:postcode":"4655",
    "sg:province":"QLD",
    "sg:tags":[
        "drama",
        "tuition"
    ],
    "wof:name":"Helen Ogrady Childrens Drama Academy Wide Bay",
    "wof:placetype":"venue"
},
  "geometry": {"coordinates":[152.86926299999999,-25.291929],"type":"Point"}
}