{
  "type": "Feature",
  "properties": {
    "iso:country":"AU",
    "sg:address":"5 Wellington Crs",
    "sg:city":"Torquay",
    "sg:classifiers":[
        {
            "category":"Education",
            "subcategory":"Special Training",
            "type":"Public Place"
        }
    ],
    "sg:phone":"+61 7 4125 3340",
    "sg:postcode":"4655",
    "sg:province":"QLD",
    "sg:tags":[
        "drama",
        "tuition"
    ],
    "wof:name":"Helen Ogrady Childrens Drama Academy Wide Bay",
    "wof:placetype":"venue"
},
  "geometry": {"coordinates":[152.869263,-25.291929],"type":"Point"}
}