{
  "type": "Feature",
  "properties": {
    "addr:full":"Wentworth Ave Wentworthville NSW 2145",
    "addr:postcode":"2145",
    "addr:street":"Wentworth Ave",
    "iso:country":"AU",
    "sg:address":"Wentworth Ave",
    "sg:city":"Wentworthville",
    "sg:classifiers":[
        {
            "category":"Building & Trades",
            "subcategory":"Construction",
            "type":"Services"
        }
    ],
    "sg:phone":"+61 2 9636 5999",
    "sg:postcode":"2145",
    "sg:province":"NSW",
    "sg:tags":[
        "home",
        "air conditioning"
    ],
    "wof:name":"Answer Group Australia",
    "wof:placetype":"venue"
},
  "geometry": {"coordinates":[150.96983337399999,-33.8057174683],"type":"Point"}
}