{
  "type": "Feature",
  "properties": {
    "addr:full":"13 Abelia St Doncaster East VIC 3109",
    "addr:housenumber":"13",
    "addr:postcode":"3109",
    "addr:street":"Abelia St",
    "iso:country":"AU",
    "sg:address":"13 Abelia St",
    "sg:city":"Doncaster East",
    "sg:classifiers":[
        {
            "category":"Wholesale",
            "subcategory":"Painting Supplies",
            "type":"Manufacturing & Wholesale Goods"
        }
    ],
    "sg:phone":"+61 3 9841 9901",
    "sg:postcode":"3109",
    "sg:province":"VIC",
    "sg:tags":[
        "product",
        "cleaning"
    ],
    "wof:name":"Chemical Essentials Pty. Ltd.",
    "wof:placetype":"venue"
},
  "geometry": {"coordinates":[145.169067383,-37.784526825],"type":"Point"}
}