{
  "type": "Feature",
  "properties": {
    "iso:country":"AU",
    "sg:address":"Unit c- 274 Henley Beach Rd",
    "sg:city":"Underdale",
    "sg:classifiers":[
        {
            "category":"Professional",
            "subcategory":"Employment Agencies",
            "type":"Services"
        }
    ],
    "sg:phone":"+61 418 857 583",
    "sg:postcode":"5032",
    "sg:province":"SA",
    "sg:tags":[
        "hire",
        "labour",
        "contractor"
    ],
    "wof:name":"Area Construction Labour Services Pty Ltd",
    "wof:placetype":"venue"
},
  "geometry": {"coordinates":[138.54747009299999,-34.9246902466],"type":"Point"}
}