{
  "type": "Feature",
  "properties": {
    "iso:country":"AU",
    "sg:address":"25 Airds Rd",
    "sg:city":"Minto",
    "sg:classifiers":[
        {
            "category":"Retail",
            "subcategory":"Auto Repair",
            "type":"Services"
        }
    ],
    "sg:phone":"+61 2 9603 8999",
    "sg:postcode":"2566",
    "sg:province":"NSW",
    "sg:tags":[
        "repairer",
        "motor",
        "engineer"
    ],
    "wof:name":"Pauls Automotive Pty Ltd",
    "wof:placetype":"venue"
},
  "geometry": {"coordinates":[150.84016418499999,-34.024055481],"type":"Point"}
}