{
  "type": "Feature",
  "properties": {
    "addr:full":"23 Harley St Knoxfield VIC 3180",
    "addr:housenumber":"23",
    "addr:postcode":"3180",
    "addr:street":"Harley St",
    "iso:country":"AU",
    "sg:address":"23 Harley St",
    "sg:city":"Knoxfield",
    "sg:classifiers":[
        {
            "category":"Education",
            "subcategory":"Junior College",
            "type":"Public Place"
        }
    ],
    "sg:phone":"+61 3 9764 8797",
    "sg:postcode":"3180",
    "sg:province":"VIC",
    "sg:tags":[
        "wholesaler",
        "school",
        "mfrs",
        "uniform"
    ],
    "wof:name":"Party & Play Childrens Wear & School Uniforms",
    "wof:placetype":"venue"
},
  "geometry": {"coordinates":[145.24546814000001,-37.8946876526],"type":"Point"}
}