{
  "type": "Feature",
  "properties": {
    "addr:full":"8 Evans St Collie WA 6225",
    "addr:housenumber":"8",
    "addr:postcode":"6225",
    "addr:street":"Evans St",
    "iso:country":"AU",
    "sg:address":"8 Evans St",
    "sg:city":"Collie",
    "sg:classifiers":[
        {
            "category":"Taxi",
            "type":"Transportation"
        }
    ],
    "sg:phone":"+61 8 9734 1428",
    "sg:postcode":"6225",
    "sg:province":"WA",
    "sg:tags":[
        "cab"
    ],
    "wof:name":"Mario's Taxi Service",
    "wof:placetype":"venue"
},
  "geometry": {"coordinates":[116.170326,-33.351341],"type":"Point"}
}