{
  "type": "Feature",
  "properties": {
    "addr:full":"Cnr Keppel & William St Bathurst NSW 2795",
    "addr:postcode":"2795",
    "addr:street":"Cnr;St",
    "iso:country":"AU",
    "sg:address":"Cnr Keppel & William St",
    "sg:city":"Bathurst",
    "sg:classifiers":[
        {
            "category":"Professional",
            "subcategory":"Accounting & Tax Preparation",
            "type":"Services"
        }
    ],
    "sg:phone":"+61 2 6332 2960",
    "sg:postcode":"2795",
    "sg:province":"NSW",
    "sg:tags":[
        "consultant",
        "taxation"
    ],
    "wof:name":"Business Development Solutions",
    "wof:placetype":"venue"
},
  "geometry": {"coordinates":[149.58261108400001,-33.4250221252],"type":"Point"}
}