{
  "type": "Feature",
  "properties": {
    "addr:full":"120 Gardeners Rd Kingsford NSW 2032",
    "addr:housenumber":"120",
    "addr:postcode":"2032",
    "addr:street":"Gardeners Rd",
    "iso:country":"AU",
    "sg:address":"120 Gardeners Rd",
    "sg:city":"Kingsford",
    "sg:classifiers":[
        {
            "category":"Retail",
            "subcategory":"Funeral Services",
            "type":"Services"
        }
    ],
    "sg:phone":"+61 2 9697 3199",
    "sg:postcode":"2032",
    "sg:province":"NSW",
    "sg:tags":[
        "director"
    ],
    "wof:name":"Acropolis Funeral Services",
    "wof:placetype":"venue"
},
  "geometry": {"coordinates":[151.222579956,-33.9253387451],"type":"Point"}
}