{
  "type": "Feature",
  "properties": {
    "addr:full":"Factory 1/ 9-10 Carl Crt Hallam VIC 3803",
    "addr:housenumber":"/ 9-10",
    "addr:postcode":"3803",
    "addr:street":"Carl Crt",
    "iso:country":"AU",
    "sg:address":"Factory 1/ 9-10 Carl Crt",
    "sg:city":"Hallam",
    "sg:classifiers":[
        {
            "category":"Landmark",
            "subcategory":"Scenic View",
            "type":"Public Place"
        }
    ],
    "sg:phone":"+61 3 9702 3493",
    "sg:postcode":"3803",
    "sg:province":"VIC",
    "sg:tags":[
        "staircase",
        "handrail"
    ],
    "wof:name":"Ionart Pty Ltd",
    "wof:placetype":"venue"
},
  "geometry": {"coordinates":[145.26779174800001,-38.0087509155],"type":"Point"}
}