{
  "type": "Feature",
  "properties": {
    "addr:full":"L10, Como Tower 644 Chapel St South Yarra VIC 3141",
    "addr:housenumber":"l10;644",
    "addr:postcode":"3141",
    "addr:street":"Como;Chapel St",
    "iso:country":"AU",
    "sg:address":"L10, Como Tower 644 Chapel St",
    "sg:city":"South Yarra",
    "sg:classifiers":[
        {
            "category":"Professional",
            "subcategory":"Research",
            "type":"Services"
        }
    ],
    "sg:phone":"+61 3 9289 9599",
    "sg:postcode":"3141",
    "sg:province":"VIC",
    "sg:tags":[
        "market"
    ],
    "wof:name":"Quantum Market Research",
    "wof:placetype":"venue"
},
  "geometry": {"coordinates":[145.002563477,-37.8389930725],"type":"Point"}
}