{
  "type": "Feature",
  "properties": {
    "iso:country":"AU",
    "sg:address":"Shop 8 309 Morrison Rd",
    "sg:city":"Swan View",
    "sg:classifiers":[
        {
            "category":"Communications",
            "subcategory":"Film & Video Production",
            "type":"Services"
        }
    ],
    "sg:phone":"+61 8 9255 1790",
    "sg:postcode":"6056",
    "sg:province":"WA",
    "sg:tags":[
        "dvd",
        "library"
    ],
    "wof:name":"Civic Video Swan View",
    "wof:placetype":"venue"
},
  "geometry": {"coordinates":[116.04245758099999,-31.8857822418],"type":"Point"}
}