{
  "type": "Feature",
  "properties": {
    "addr:full":"3/ 38 Ailsa St Mansfield VIC 3722",
    "addr:housenumber":"/ 38",
    "addr:postcode":"3722",
    "addr:street":"Ailsa St",
    "iso:country":"AU",
    "sg:address":"3/ 38 Ailsa St",
    "sg:city":"Mansfield",
    "sg:classifiers":[
        {
            "category":"Professional",
            "subcategory":"Computer Services",
            "type":"Services"
        }
    ],
    "sg:phone":"+61 429 796 991",
    "sg:postcode":"3722",
    "sg:province":"VIC",
    "sg:tags":[
        "equipment",
        "networking",
        "installation"
    ],
    "wof:name":"TST IT",
    "wof:placetype":"venue"
},
  "geometry": {"coordinates":[146.091674805,-37.0548820496],"type":"Point"}
}