{
  "type": "Feature",
  "properties": {
    "addr:full":"18 Middle St Labrador QLD 4215",
    "addr:housenumber":"18",
    "addr:postcode":"4215",
    "addr:street":"Middle St",
    "iso:country":"AU",
    "sg:address":"18 Middle St",
    "sg:city":"Labrador",
    "sg:classifiers":[
        {
            "category":"Manufacturing",
            "subcategory":"Pottery",
            "type":"Manufacturing & Wholesale Goods"
        }
    ],
    "sg:phone":"+61 7 5537 4284",
    "sg:postcode":"4215",
    "sg:province":"QLD",
    "wof:name":"Bluebell Pottery & Party Plan",
    "wof:placetype":"venue"
},
  "geometry": {"coordinates":[153.404495239,-27.939874649],"type":"Point"}
}