{
  "type": "Feature",
  "properties": {
    "addr:full":"Wheelers La Dubbo NSW 2830",
    "addr:postcode":"2830",
    "iso:country":"AU",
    "sg:address":"Wheelers La",
    "sg:city":"Dubbo",
    "sg:classifiers":[
        {
            "category":"Landmark",
            "subcategory":"Fountain",
            "type":"Public Place"
        }
    ],
    "sg:phone":"+61 2 6882 1008",
    "sg:postcode":"2830",
    "sg:province":"NSW",
    "sg:tags":[
        "wholesaler",
        "spring",
        "mfrs"
    ],
    "wof:name":"Honeysett Spring Repairs",
    "wof:placetype":"venue"
},
  "geometry": {"coordinates":[148.62989807100001,-32.2528152466],"type":"Point"}
}