{
  "type": "Feature",
  "properties": {
    "addr:full":"128 Woodlands Rd Taren Point NSW 2229",
    "addr:housenumber":"128",
    "addr:postcode":"2229",
    "addr:street":"Woodlands Rd",
    "iso:country":"AU",
    "sg:address":"128 Woodlands Rd",
    "sg:city":"Taren Point",
    "sg:classifiers":[
        {
            "category":"Building & Trades",
            "subcategory":"Landscaping Services",
            "type":"Services"
        }
    ],
    "sg:phone":"+61 2 9524 4282",
    "sg:postcode":"2229",
    "sg:province":"NSW",
    "sg:tags":[
        "consultant"
    ],
    "wof:name":"Windowmakers Pty Ltd",
    "wof:placetype":"venue"
},
  "geometry": {"coordinates":[151.123336792,-34.0189819336],"type":"Point"}
}