{
  "type": "Feature",
  "properties": {
    "addr:full":"64 Norma Rd Myaree WA 6154",
    "addr:housenumber":"64",
    "addr:postcode":"6154",
    "addr:street":"Norma Rd",
    "iso:country":"AU",
    "sg:address":"64 Norma Rd",
    "sg:city":"Myaree",
    "sg:classifiers":[
        {
            "category":"Utilities",
            "subcategory":"Water",
            "type":"Services"
        }
    ],
    "sg:phone":"+61 8 9330 5600",
    "sg:postcode":"6154",
    "sg:province":"WA",
    "sg:tags":[
        "hot",
        "system"
    ],
    "wof:name":"Pratt Plumbers",
    "wof:placetype":"venue"
},
  "geometry": {"coordinates":[115.82215100000001,-32.040062],"type":"Point"}
}