{
  "type": "Feature",
  "properties": {
    "addr:full":"59 Johnston St Southport QLD 4215",
    "addr:housenumber":"59",
    "addr:postcode":"4215",
    "addr:street":"Johnston St",
    "iso:country":"AU",
    "sg:address":"59 Johnston St",
    "sg:city":"Southport",
    "sg:classifiers":[
        {
            "category":"Retail",
            "subcategory":"Auto Rental",
            "type":"Services"
        }
    ],
    "sg:phone":"+61 7 5531 2578",
    "sg:postcode":"4215",
    "sg:province":"QLD",
    "sg:tags":[
        "camper-trailers",
        "caravan",
        "hire"
    ],
    "wof:name":"Down 2 Earth Campers",
    "wof:placetype":"venue"
},
  "geometry": {"coordinates":[153.404373169,-27.9651985168],"type":"Point"}
}