{
  "type": "Feature",
  "properties": {
    "addr:full":"111 Musgrave Rd Red Hill QLD 4059",
    "addr:housenumber":"111",
    "addr:postcode":"4059",
    "addr:street":"Musgrave Rd",
    "iso:country":"AU",
    "sg:address":"111 Musgrave Rd",
    "sg:city":"Red Hill",
    "sg:classifiers":[
        {
            "category":"Health Services",
            "subcategory":"Health Practitioner",
            "type":"Services"
        }
    ],
    "sg:phone":"+61 7 3369 9866",
    "sg:postcode":"4059",
    "sg:province":"QLD",
    "sg:tags":[
        "naturopath"
    ],
    "wof:name":"Trowbridge Patricia",
    "wof:placetype":"venue"
},
  "geometry": {"coordinates":[153.00880432100001,-27.456451416],"type":"Point"}
}