{
  "type": "Feature",
  "properties": {
    "iso:country":"AU",
    "sg:address":"151 Royal St",
    "sg:city":"East Perth",
    "sg:classifiers":[
        {
            "category":"Education",
            "subcategory":"Kindergarten",
            "type":"Public Place"
        }
    ],
    "sg:phone":"+61 8 9264 4111",
    "sg:postcode":"6004",
    "sg:province":"WA",
    "sg:tags":[
        "pre-schools"
    ],
    "wof:name":"Schools Government (Public)",
    "wof:placetype":"venue"
},
  "geometry": {"coordinates":[115.872161865,-31.9522171021],"type":"Point"}
}