{
  "type": "Feature",
  "properties": {
    "addr:full":"182 Osborne St Nowra NSW 2541",
    "addr:housenumber":"182",
    "addr:postcode":"2541",
    "addr:street":"Osborne St",
    "iso:country":"AU",
    "sg:address":"182 Osborne St",
    "sg:city":"Nowra",
    "sg:classifiers":[
        {
            "category":"Professional",
            "subcategory":"Art Services",
            "type":"Services"
        }
    ],
    "sg:phone":"+61 2 4421 3629",
    "sg:postcode":"2541",
    "sg:province":"NSW",
    "sg:tags":[
        "decorator",
        "painter"
    ],
    "wof:name":"Byrnes Paul",
    "wof:placetype":"venue"
},
  "geometry": {"coordinates":[150.59555053700001,-34.8877410889],"type":"Point"}
}