{
  "type": "Feature",
  "properties": {
    "addr:full":"77 Raglan St Daylesford VIC 3460",
    "addr:housenumber":"77",
    "addr:postcode":"3460",
    "addr:street":"Raglan St",
    "iso:country":"AU",
    "sg:address":"77 Raglan St",
    "sg:city":"Daylesford",
    "sg:classifiers":[
        {
            "category":"Retail",
            "subcategory":"Veterinary Services",
            "type":"Services"
        }
    ],
    "sg:phone":"+61 3 5348 1088",
    "sg:postcode":"3460",
    "sg:province":"VIC",
    "sg:tags":[
        "surgeon"
    ],
    "wof:name":"Hitchman A.G.",
    "wof:placetype":"venue"
},
  "geometry": {"coordinates":[144.14335632300001,-37.3393173218],"type":"Point"}
}