{
  "type": "Feature",
  "properties": {
    "addr:full":"U 1/ 4 Leach Crs Rockingham WA 6168",
    "addr:housenumber":"4",
    "addr:postcode":"6168",
    "addr:street":"Leach Crs",
    "iso:country":"AU",
    "sg:address":"U 1/ 4 Leach Crs",
    "sg:city":"Rockingham",
    "sg:classifiers":[
        {
            "category":"Professional",
            "subcategory":"Computer Services",
            "type":"Services"
        }
    ],
    "sg:phone":"+61 8 9529 1733",
    "sg:postcode":"6168",
    "sg:province":"WA",
    "sg:tags":[
        "repairs",
        "upgrade",
        "equipment"
    ],
    "wof:name":"Pc Class",
    "wof:placetype":"venue"
},
  "geometry": {"coordinates":[115.741028,-32.280399],"type":"Point"}
}