{
  "type": "Feature",
  "properties": {
    "iso:country":"AU",
    "sg:address":"2 Stuart St",
    "sg:city":"Padstow",
    "sg:classifiers":[
        {
            "category":"Retail",
            "subcategory":"Car Wash",
            "type":"Services"
        }
    ],
    "sg:phone":"+61 2 9792 4811",
    "sg:postcode":"2211",
    "sg:province":"NSW",
    "sg:tags":[
        "truck",
        "cleaning"
    ],
    "wof:name":"Prince Car Detailing",
    "wof:placetype":"venue"
},
  "geometry": {"coordinates":[151.037857,-33.944229],"type":"Point"}
}