{
  "type": "Feature",
  "properties": {
    "addr:full":"Unit 1, 101 Winton Rd Joondalup WA 6027",
    "addr:housenumber":"101",
    "addr:postcode":"6027",
    "addr:street":"Winton Rd",
    "iso:country":"AU",
    "sg:address":"Unit 1, 101 Winton Rd",
    "sg:city":"Joondalup",
    "sg:classifiers":[
        {
            "category":"Building & Trades",
            "subcategory":"Construction",
            "type":"Services"
        }
    ],
    "sg:phone":"+61 8 9301 2401",
    "sg:postcode":"6027",
    "sg:province":"WA",
    "sg:tags":[
        "home",
        "air conditioning"
    ],
    "wof:name":"Aussie Air",
    "wof:placetype":"venue"
},
  "geometry": {"coordinates":[115.759498596,-31.743024826],"type":"Point"}
}