{
  "type": "Feature",
  "properties": {
    "iso:country":"AU",
    "sg:address":"92 Elizabeth St",
    "sg:city":"Hobart",
    "sg:classifiers":[
        {
            "category":"Retail",
            "subcategory":"Repair Shop",
            "type":"Services"
        }
    ],
    "sg:phone":"+61 3 6234 4633",
    "sg:postcode":"7000",
    "sg:province":"TAS",
    "sg:tags":[
        "machine",
        "sewing"
    ],
    "wof:name":"Elizabeth Sewing Centre",
    "wof:placetype":"venue"
},
  "geometry": {"coordinates":[147.325683594,-42.8806648254],"type":"Point"}
}