{
  "type": "Feature",
  "properties": {
    "addr:full":"57 Bagot Rd Subiaco WA 6008",
    "addr:housenumber":"57",
    "addr:postcode":"6008",
    "addr:street":"Bagot Rd",
    "iso:country":"AU",
    "sg:address":"57 Bagot Rd",
    "sg:city":"Subiaco",
    "sg:classifiers":[
        {
            "category":"Professional",
            "subcategory":"Art Services",
            "type":"Services"
        }
    ],
    "sg:phone":"+61 8 9381 3836",
    "sg:postcode":"6008",
    "sg:province":"WA",
    "wof:name":"Macha Mary",
    "wof:placetype":"venue"
},
  "geometry": {"coordinates":[115.830841065,-31.9506149292],"type":"Point"}
}