{
  "type": "Feature",
  "properties": {
    "addr:full":"Shop 2- 113 The Glen Shopping Cntr Glen Waverley VIC 3150",
    "addr:housenumber":"shop 2 113",
    "addr:postcode":"3150",
    "addr:street":"The Glen Shopping Cntr",
    "iso:country":"AU",
    "sg:address":"Shop 2- 113 The Glen Shopping Cntr",
    "sg:city":"Glen Waverley",
    "sg:classifiers":[
        {
            "category":"Fast Food",
            "type":"Food & Drink"
        }
    ],
    "sg:phone":"+61 3 9802 1028",
    "sg:postcode":"3150",
    "sg:province":"VIC",
    "sg:tags":[
        "away",
        "take"
    ],
    "wof:name":"Sushi Sushi",
    "wof:placetype":"venue"
},
  "geometry": {"coordinates":[145.16778564399999,-37.8688812256],"type":"Point"}
}