{
  "type": "Feature",
  "properties": {
    "iso:country":"AU",
    "sg:address":"80 Flemington St",
    "sg:city":"Flemington",
    "sg:classifiers":[
        {
            "category":"Social Services",
            "subcategory":"Child Care",
            "type":"Services"
        }
    ],
    "sg:phone":"+61 3 9372 6834",
    "sg:postcode":"3031",
    "sg:province":"VIC",
    "wof:name":"Flemington St Childrens Centre",
    "wof:placetype":"venue"
},
  "geometry": {"coordinates":[144.932877,-37.781261],"type":"Point"}
}