{
  "type": "Feature",
  "properties": {
    "addr:full":"University Drv Robina QLD 4226",
    "addr:postcode":"4226",
    "addr:street":"University Drv",
    "iso:country":"AU",
    "sg:address":"University Drv",
    "sg:city":"Robina",
    "sg:classifiers":[
        {
            "category":"Education",
            "subcategory":"University",
            "type":"Public Place"
        }
    ],
    "sg:phone":"+61 7 5595 1111",
    "sg:postcode":"4226",
    "sg:province":"QLD",
    "sg:tags":[
        "college",
        "tertiary"
    ],
    "wof:name":"Bond University",
    "wof:placetype":"venue"
},
  "geometry": {"coordinates":[153.40423584000001,-28.0799980164],"type":"Point"}
}