{
  "type": "Feature",
  "properties": {
    "addr:full":"Manns Rd Mullumbimby NSW 2482",
    "addr:postcode":"2482",
    "addr:street":"Manns Rd",
    "iso:country":"AU",
    "sg:address":"Manns Rd",
    "sg:city":"Mullumbimby",
    "sg:classifiers":[
        {
            "category":"Retail",
            "subcategory":"Storage",
            "type":"Services"
        }
    ],
    "sg:phone":"+61 2 6684 2198",
    "sg:postcode":"2482",
    "sg:province":"NSW",
    "sg:tags":[
        "removal",
        "furniture"
    ],
    "wof:name":"Robinson Stan Removals",
    "wof:placetype":"venue"
},
  "geometry": {"coordinates":[153.513916016,-28.5556793213],"type":"Point"}
}