{
  "type": "Feature",
  "properties": {
    "iso:country":"AU",
    "sg:address":"33a Wentworth Drv",
    "sg:city":"Taylors Lakes",
    "sg:classifiers":[
        {
            "category":"Professional",
            "subcategory":"Accounting & Tax Preparation",
            "type":"Services"
        }
    ],
    "sg:phone":"+61 3 9390 9020",
    "sg:postcode":"3038",
    "sg:province":"VIC",
    "sg:tags":[
        "accountant",
        "auditor"
    ],
    "wof:name":"Santomartino Carmine",
    "wof:placetype":"venue"
},
  "geometry": {"coordinates":[144.776123,-37.694305],"type":"Point"}
}