{
  "type": "Feature",
  "properties": {
    "addr:full":"Unit 39, 22 Pennant St Castle Hill NSW 2154",
    "addr:housenumber":"22",
    "addr:postcode":"2154",
    "addr:street":"Pennant St",
    "iso:country":"AU",
    "sg:address":"Unit 39, 22 Pennant St",
    "sg:city":"Castle Hill",
    "sg:classifiers":[
        {
            "category":"Health Services",
            "subcategory":"Doctor",
            "type":"Services"
        }
    ],
    "sg:phone":"+61 411 282 256",
    "sg:postcode":"2154",
    "sg:province":"NSW",
    "sg:tags":[
        "reflexology"
    ],
    "wof:name":"Melanie Parsons",
    "wof:placetype":"venue"
},
  "geometry": {"coordinates":[151.00433349599999,-33.7308692932],"type":"Point"}
}