{
  "type": "Feature",
  "properties": {
    "iso:country":"AU",
    "sg:address":"12 Chateau St",
    "sg:city":"Calamvale",
    "sg:classifiers":[
        {
            "category":"Manufacturing",
            "subcategory":"Food",
            "type":"Manufacturing & Wholesale Goods"
        }
    ],
    "sg:phone":"+61 7 3273 7852",
    "sg:postcode":"4116",
    "sg:province":"QLD",
    "sg:tags":[
        "function",
        "catering"
    ],
    "wof:name":"Weekend Catering",
    "wof:placetype":"venue"
},
  "geometry": {"coordinates":[153.058395386,-27.6132335663],"type":"Point"}
}