{
  "type": "Feature",
  "properties": {
    "addr:full":"Unit 3/ 40 Lawson St Blayney NSW 2799",
    "addr:housenumber":"40",
    "addr:postcode":"2799",
    "addr:street":"Lawson St",
    "iso:country":"AU",
    "sg:address":"Unit 3/ 40 Lawson St",
    "sg:city":"Blayney",
    "sg:classifiers":[
        {
            "category":"Landmark",
            "subcategory":"Scenic View",
            "type":"Public Place"
        }
    ],
    "sg:phone":"+61 2 6368 2570",
    "sg:postcode":"2799",
    "sg:province":"NSW",
    "sg:tags":[
        "staircase",
        "handrail"
    ],
    "wof:name":"Access Stairways",
    "wof:placetype":"venue"
},
  "geometry": {"coordinates":[149.25614899999999,-33.51366],"type":"Point"}
}