{
  "type": "Feature",
  "properties": {
    "addr:full":"28 Michaelangelo Drv Redlynch QLD 4870",
    "addr:housenumber":"28",
    "addr:postcode":"4870",
    "addr:street":"Michaelangelo Drv",
    "iso:country":"AU",
    "sg:address":"28 Michaelangelo Drv",
    "sg:city":"Redlynch",
    "sg:classifiers":[
        {
            "category":"Food & Beverages",
            "subcategory":"Supermarket",
            "type":"Retail Goods"
        }
    ],
    "sg:phone":"+61 7 4039 2055",
    "sg:postcode":"4870",
    "sg:province":"QLD",
    "sg:tags":[
        "grocery",
        "store"
    ],
    "wof:name":"Michaelangelo Mini Mart",
    "wof:placetype":"venue"
},
  "geometry": {"coordinates":[145.695556641,-16.9038505554],"type":"Point"}
}