{
  "type": "Feature",
  "properties": {
    "addr:full":"3/ 22 Main Drv Kawana Waters QLD 4575",
    "addr:housenumber":"/ 22",
    "addr:postcode":"4575",
    "addr:street":"Main Drv",
    "iso:country":"AU",
    "sg:address":"3/ 22 Main Drv",
    "sg:city":"Kawana Waters",
    "sg:classifiers":[
        {
            "category":"Autos & Motor Vehicles",
            "subcategory":"Auto Supplies",
            "type":"Retail Goods"
        }
    ],
    "sg:phone":"+61 13 61 30",
    "sg:postcode":"4575",
    "sg:province":"QLD",
    "sg:tags":[
        "battery",
        "automotive"
    ],
    "wof:name":"Marshall Batteries",
    "wof:placetype":"venue"
},
  "geometry": {"coordinates":[153.125427,-26.730955],"type":"Point"}
}