{
  "type": "Feature",
  "properties": {
    "addr:full":"90b High St Boonah QLD 4310",
    "addr:housenumber":"90b",
    "addr:postcode":"4310",
    "addr:street":"High St",
    "iso:country":"AU",
    "sg:address":"90b High St",
    "sg:city":"Boonah",
    "sg:classifiers":[
        {
            "category":"Personal",
            "subcategory":"Beauty Salon",
            "type":"Services"
        }
    ],
    "sg:phone":"+61 7 5463 1191",
    "sg:postcode":"4310",
    "sg:province":"QLD",
    "sg:tags":[
        "hairdresser"
    ],
    "wof:name":"Lyn Quade Hair",
    "wof:placetype":"venue"
},
  "geometry": {"coordinates":[152.68261718799999,-27.996011734],"type":"Point"}
}