{
  "type": "Feature",
  "properties": {
    "addr:full":"164 Bald Hills Rd Bald Hills QLD 4036",
    "addr:housenumber":"164",
    "addr:postcode":"4036",
    "addr:street":"Bald Hills Rd",
    "iso:country":"AU",
    "sg:address":"164 Bald Hills Rd",
    "sg:city":"Bald Hills",
    "sg:classifiers":[
        {
            "category":"Education",
            "subcategory":"Special Training",
            "type":"Public Place"
        }
    ],
    "sg:phone":"+61 7 3261 2140",
    "sg:postcode":"4036",
    "sg:province":"QLD",
    "sg:tags":[
        "development"
    ],
    "wof:name":"Trischel",
    "wof:placetype":"venue"
},
  "geometry": {"coordinates":[153.011337,-27.31072],"type":"Point"}
}