{
  "type": "Feature",
  "properties": {
    "addr:full":"Unit 7, 20 Kenworth Pl Brendale QLD 4500",
    "addr:housenumber":"20",
    "addr:postcode":"4500",
    "addr:street":"Kenworth Pl",
    "iso:country":"AU",
    "sg:address":"Unit 7, 20 Kenworth Pl",
    "sg:city":"Brendale",
    "sg:classifiers":[
        {
            "category":"Shopping",
            "subcategory":"Mobile Phones",
            "type":"Retail Goods"
        }
    ],
    "sg:phone":"+61 7 3205 7388",
    "sg:postcode":"4500",
    "sg:province":"QLD",
    "sg:tags":[
        "wholesaler",
        "mfrs",
        "electrical",
        "switchboard"
    ],
    "sg:website":"http://www.gbelectrics.com.au",
    "wof:name":"G B Electrics Pty Ltd",
    "wof:placetype":"venue"
},
  "geometry": {"coordinates":[152.988449097,-27.3249778748],"type":"Point"}
}