{
  "type": "Feature",
  "properties": {
    "addr:full":"359 Queen St Concord West NSW 2138",
    "addr:housenumber":"359",
    "addr:postcode":"2138",
    "addr:street":"Queen St",
    "iso:country":"AU",
    "sg:address":"359 Queen St",
    "sg:city":"Concord West",
    "sg:classifiers":[
        {
            "category":"Professional",
            "subcategory":"Art Services",
            "type":"Services"
        }
    ],
    "sg:phone":"+61 2 9743 1154",
    "sg:postcode":"2138",
    "sg:province":"NSW",
    "sg:tags":[
        "graphic",
        "designer"
    ],
    "wof:name":"Design Takes Form",
    "wof:placetype":"venue"
},
  "geometry": {"coordinates":[151.08653259299999,-33.8387336731],"type":"Point"}
}