{
  "type": "Feature",
  "properties": {
    "iso:country":"AU",
    "sg:address":"95 Ledger Rd",
    "sg:city":"Beverley",
    "sg:classifiers":[
        {
            "category":"Landmark",
            "subcategory":"City Walls",
            "type":"Public Place"
        }
    ],
    "sg:phone":"+61 8 8345 1200",
    "sg:postcode":"5009",
    "sg:province":"SA",
    "sg:tags":[
        "board",
        "particle"
    ],
    "wof:name":"Tasmania Wood Panels",
    "wof:placetype":"venue"
},
  "geometry": {"coordinates":[138.54142761200001,-34.8935317993],"type":"Point"}
}