{
  "type": "Feature",
  "properties": {
    "addr:full":"286 Samsonvale Rd Strathpine QLD 4500",
    "addr:housenumber":"286",
    "addr:postcode":"4500",
    "addr:street":"Samsonvale Rd",
    "iso:country":"AU",
    "sg:address":"286 Samsonvale Rd",
    "sg:city":"Strathpine",
    "sg:classifiers":[
        {
            "category":"Utilities",
            "subcategory":"Electric",
            "type":"Services"
        }
    ],
    "sg:phone":"+61 418 730 651",
    "sg:postcode":"4500",
    "sg:province":"QLD",
    "sg:tags":[
        "electrical",
        "contractor"
    ],
    "wof:name":"Peter Hulbert",
    "wof:placetype":"venue"
},
  "geometry": {"coordinates":[152.963623047,-27.294260025],"type":"Point"}
}