{
  "type": "Feature",
  "properties": {
    "addr:full":"189 Wyreema Rd Toowoomba QLD 4350",
    "addr:housenumber":"189",
    "addr:postcode":"4350",
    "addr:street":"Wyreema Rd",
    "iso:country":"AU",
    "sg:address":"189 Wyreema Rd",
    "sg:city":"Toowoomba",
    "sg:classifiers":[
        {
            "category":"Food & Beverages",
            "subcategory":"Fruits & Vegetables",
            "type":"Retail Goods"
        }
    ],
    "sg:phone":"+61 7 4630 1725",
    "sg:postcode":"4350",
    "sg:province":"QLD",
    "sg:tags":[
        "grower"
    ],
    "wof:name":"Westview Gardens",
    "wof:placetype":"venue"
},
  "geometry": {"coordinates":[151.89660599999999,-27.605274],"type":"Point"}
}