{
  "type": "Feature",
  "properties": {
    "addr:full":"Bellambi La Bellambi NSW 2518",
    "addr:postcode":"2518",
    "addr:street":"Bellambi",
    "iso:country":"AU",
    "sg:address":"Bellambi La",
    "sg:city":"Bellambi",
    "sg:classifiers":[
        {
            "category":"Travel",
            "subcategory":"Hotels & Motels",
            "type":"Entertainment"
        }
    ],
    "sg:phone":"+61 2 4284 1691",
    "sg:postcode":"2518",
    "sg:province":"NSW",
    "sg:tags":[
        "accommodation"
    ],
    "wof:name":"Bellambi Hotel",
    "wof:placetype":"venue"
},
  "geometry": {"coordinates":[150.88789399999999,-34.37236],"type":"Point"}
}