{
  "type": "Feature",
  "properties": {
    "iso:country":"AU",
    "sg:address":"Room 3, 1",
    "sg:city":"st Floor, London Court, Hay Street Mall Perth",
    "sg:classifiers":[
        {
            "category":"Health Services",
            "subcategory":"Doctor",
            "type":"Services"
        }
    ],
    "sg:phone":"+61 8 9325 2265",
    "sg:postcode":"6000",
    "sg:province":"WA",
    "sg:tags":[
        "podiatrist"
    ],
    "wof:name":"City & Lakeside Podiatry",
    "wof:placetype":"venue"
},
  "geometry": {"coordinates":[115.853813171,-31.9525032043],"type":"Point"}
}