{
  "type": "Feature",
  "properties": {
    "addr:full":"18 Bulletin Pl Sydney NSW 2000",
    "addr:housenumber":"18",
    "addr:postcode":"2000",
    "addr:street":"Bulletin Pl",
    "iso:country":"AU",
    "sg:address":"18 Bulletin Pl",
    "sg:city":"Sydney",
    "sg:classifiers":[
        {
            "category":"Banks & Credit Unions",
            "subcategory":"Financial Services",
            "type":"Services"
        }
    ],
    "sg:phone":"+61 2 9238 6623",
    "sg:postcode":"2000",
    "sg:province":"NSW",
    "sg:tags":[
        "planning"
    ],
    "wof:name":"Count Wealth Accountants",
    "wof:placetype":"venue"
},
  "geometry": {"coordinates":[151.20997619600001,-33.86277771],"type":"Point"}
}