{
  "type": "Feature",
  "properties": {
    "addr:full":"32 Marine Pde Bucasia QLD 4750",
    "addr:housenumber":"32",
    "addr:postcode":"4750",
    "addr:street":"Marine Pde",
    "iso:country":"AU",
    "sg:address":"32 Marine Pde",
    "sg:city":"Bucasia",
    "sg:classifiers":[
        {
            "category":"Home & Garden",
            "subcategory":"Building Materials",
            "type":"Retail Goods"
        }
    ],
    "sg:phone":"+61 7 4954 7667",
    "sg:postcode":"4750",
    "sg:province":"QLD",
    "sg:tags":[
        "ventilating",
        "equipment",
        "system"
    ],
    "wof:name":"Access Insulation",
    "wof:placetype":"venue"
},
  "geometry": {"coordinates":[149.15052800000001,-21.023697],"type":"Point"}
}