{
  "type": "Feature",
  "properties": {
    "iso:country":"AU",
    "sg:address":"104 Penola Rd",
    "sg:city":"Mt Gambier",
    "sg:classifiers":[
        {
            "category":"Autos & Motor Vehicles",
            "subcategory":"Automobile Sales",
            "type":"Retail Goods"
        }
    ],
    "sg:phone":"+61 8 8725 7700",
    "sg:postcode":"5290",
    "sg:province":"SA",
    "sg:tags":[
        "equipment",
        "trailer"
    ],
    "wof:name":"Baxter Hire",
    "wof:placetype":"venue"
},
  "geometry": {"coordinates":[140.786423,-37.817486],"type":"Point"}
}