{
  "type": "Feature",
  "properties": {
    "addr:full":"PO Box 426 Maffra VIC 3860",
    "addr:postcode":"3860",
    "iso:country":"AU",
    "sg:address":"PO Box 426",
    "sg:city":"Maffra",
    "sg:classifiers":[
        {
            "category":"Utilities",
            "subcategory":"Electric",
            "type":"Services"
        }
    ],
    "sg:phone":"+61 3 5147 3367",
    "sg:postcode":"3860",
    "sg:province":"VIC",
    "sg:tags":[
        "electrical",
        "contractor"
    ],
    "wof:name":"DA & PA Bennett",
    "wof:placetype":"venue"
},
  "geometry": {"coordinates":[146.98373413100001,-37.971698761],"type":"Point"}
}