{
  "type": "Feature",
  "properties": {
    "addr:full":"4 Keppel Ave Concord NSW 2137",
    "addr:housenumber":"4",
    "addr:postcode":"2137",
    "addr:street":"Keppel Ave",
    "iso:country":"AU",
    "sg:address":"4 Keppel Ave",
    "sg:city":"Concord",
    "sg:classifiers":[
        {
            "category":"Health Services",
            "subcategory":"Health Practitioner",
            "type":"Services"
        }
    ],
    "sg:phone":"+61 403 898 805",
    "sg:postcode":"2137",
    "sg:province":"NSW",
    "sg:tags":[
        "pathologist",
        "speech"
    ],
    "wof:name":"Frederick Patchell & Cecile Patchell.",
    "wof:placetype":"venue"
},
  "geometry": {"coordinates":[151.095993042,-33.8638267517],"type":"Point"}
}