{
  "type": "Feature",
  "properties": {
    "iso:country":"AU",
    "sg:address":"32 May Rd",
    "sg:city":"Lalor",
    "sg:classifiers":[
        {
            "category":"Personal",
            "subcategory":"Beauty Salon",
            "type":"Services"
        }
    ],
    "sg:phone":"+61 3 9465 3031",
    "sg:postcode":"3075",
    "sg:province":"VIC",
    "sg:tags":[
        "hairdresser"
    ],
    "wof:name":"Hair Trivia",
    "wof:placetype":"venue"
},
  "geometry": {"coordinates":[145.00498962399999,-37.8474578857],"type":"Point"}
}