{
  "type": "Feature",
  "properties": {
    "iso:country":"AU",
    "sg:address":"3 Mt Ousley Rd",
    "sg:city":"Fairy Meadow",
    "sg:classifiers":[
        {
            "category":"Recreation",
            "type":"Entertainment"
        }
    ],
    "sg:phone":"+61 2 4228 5962",
    "sg:postcode":"2519",
    "sg:province":"NSW",
    "sg:tags":[
        "recreational",
        "diver"
    ],
    "sg:website":"http://www.uniteddivers.com.au",
    "wof:name":"United Divers",
    "wof:placetype":"venue"
},
  "geometry": {"coordinates":[150.890457,-34.403111],"type":"Point"}
}