{
  "type": "Feature",
  "properties": {
    "addr:full":"87 Oates Ave Holland Park QLD 4121",
    "addr:housenumber":"87",
    "addr:postcode":"4121",
    "addr:street":"Oates Ave",
    "iso:country":"AU",
    "sg:address":"87 Oates Ave",
    "sg:city":"Holland Park",
    "sg:classifiers":[
        {
            "category":"Building & Trades",
            "subcategory":"Cleaning & Sanitation",
            "type":"Services"
        }
    ],
    "sg:phone":"+61 7 3343 6827",
    "sg:postcode":"4121",
    "sg:province":"QLD",
    "sg:tags":[
        "window"
    ],
    "wof:name":"\"Pane\" Fully Clear Windows & Housewash",
    "wof:placetype":"venue"
},
  "geometry": {"coordinates":[153.074127197,-27.5250587463],"type":"Point"}
}