{
  "type": "Feature",
  "properties": {
    "addr:full":"16 Donald St Ashburton VIC 3147",
    "addr:housenumber":"16",
    "addr:postcode":"3147",
    "addr:street":"Donald St",
    "iso:country":"AU",
    "sg:address":"16 Donald St",
    "sg:city":"Ashburton",
    "sg:classifiers":[
        {
            "category":"Building & Trades",
            "subcategory":"Plumbing",
            "type":"Services"
        }
    ],
    "sg:phone":"+61 3 9885 1442",
    "sg:postcode":"3147",
    "sg:province":"VIC",
    "sg:tags":[
        "plumber",
        "gasfitters"
    ],
    "wof:name":"Jackson W F & Sons Pty Ltd",
    "wof:placetype":"venue"
},
  "geometry": {"coordinates":[145.06866455100001,-37.8701057434],"type":"Point"}
}