{
  "type": "Feature",
  "properties": {
    "iso:country":"AU",
    "sg:address":"110 Musgrave St",
    "sg:city":"North Rockhampton",
    "sg:classifiers":[
        {
            "category":"Real Estate",
            "subcategory":"Real Estate Agent",
            "type":"Services"
        }
    ],
    "sg:phone":"+61 7 4921 0655",
    "sg:postcode":"4701",
    "sg:province":"QLD",
    "wof:name":"Raine & Horne Rockhampton",
    "wof:placetype":"venue"
},
  "geometry": {"coordinates":[150.52235412600001,-23.366689682],"type":"Point"}
}