{
  "type": "Feature",
  "properties": {
    "iso:country":"AU",
    "sg:address":"63 Wells St",
    "sg:city":"Frankston",
    "sg:classifiers":[
        {
            "category":"Banks & Credit Unions",
            "subcategory":"Investment Brokerage",
            "type":"Services"
        }
    ],
    "sg:phone":"+61 3 9770 5376",
    "sg:postcode":"3199",
    "sg:province":"VIC",
    "sg:tags":[
        "money",
        "term",
        "short",
        "finance",
        "market"
    ],
    "wof:name":"Cheque Exchange",
    "wof:placetype":"venue"
},
  "geometry": {"coordinates":[144.96887207,-37.8275489807],"type":"Point"}
}