{
  "type": "Feature",
  "properties": {
    "iso:country":"AU",
    "sg:address":"PO Box 4073",
    "sg:city":"Kingsway West",
    "sg:classifiers":[
        {
            "category":"Retail",
            "subcategory":"Storage",
            "type":"Services"
        }
    ],
    "sg:phone":"+61 2 9150 0788",
    "sg:postcode":"2208",
    "sg:province":"NSW",
    "sg:tags":[
        "removal",
        "furniture"
    ],
    "wof:name":"Kraut Removals",
    "wof:placetype":"venue"
},
  "geometry": {"coordinates":[151.093506,-33.950161],"type":"Point"}
}