{
  "type": "Feature",
  "properties": {
    "addr:full":"1349 Teviot Rd Jimboomba QLD 4280",
    "addr:housenumber":"1349",
    "addr:postcode":"4280",
    "addr:street":"Teviot Rd",
    "iso:country":"AU",
    "sg:address":"1349 Teviot Rd",
    "sg:city":"Jimboomba",
    "sg:classifiers":[
        {
            "category":"Home & Garden",
            "subcategory":"Building Materials",
            "type":"Retail Goods"
        }
    ],
    "sg:phone":"+61 7 5547 7256",
    "sg:postcode":"4280",
    "sg:province":"QLD",
    "sg:tags":[
        "concrete",
        "panel",
        "pre-cast"
    ],
    "wof:name":"G J Gibson Constructions Pty Ltd",
    "wof:placetype":"venue"
},
  "geometry": {"coordinates":[152.97088600000001,-27.81702],"type":"Point"}
}