{
  "type": "Feature",
  "properties": {
    "addr:full":"7 Stapleton Ave Sutherland NSW 2232",
    "addr:housenumber":"7",
    "addr:postcode":"2232",
    "addr:street":"Stapleton Ave",
    "iso:country":"AU",
    "sg:address":"7 Stapleton Ave",
    "sg:city":"Sutherland",
    "sg:classifiers":[
        {
            "category":"Government",
            "subcategory":"Court House",
            "type":"Public Place"
        }
    ],
    "sg:phone":"+61 2 9521 2933",
    "sg:postcode":"2232",
    "sg:province":"NSW",
    "sg:tags":[
        "personal",
        "marriage",
        "family",
        "counselling"
    ],
    "wof:name":"SHIRELIVE //",
    "wof:placetype":"venue"
},
  "geometry": {"coordinates":[151.06033325199999,-34.0307846069],"type":"Point"}
}