{
  "type": "Feature",
  "properties": {
    "addr:full":"RSD 20 Weetulta SA 5573",
    "addr:housenumber":"20",
    "addr:postcode":"5573",
    "addr:street":"Weetulta",
    "iso:country":"AU",
    "sg:address":"RSD 20",
    "sg:city":"Weetulta",
    "sg:classifiers":[
        {
            "category":"Farming",
            "subcategory":"Farm",
            "type":"Manufacturing & Wholesale Goods"
        }
    ],
    "sg:phone":"+61 8 8835 2229",
    "sg:postcode":"5573",
    "sg:province":"SA",
    "sg:tags":[
        "farmer"
    ],
    "wof:name":"Wicks L R & M G",
    "wof:placetype":"venue"
},
  "geometry": {"coordinates":[137.639892578,-34.2190208435],"type":"Point"}
}