{
  "type": "Feature",
  "properties": {
    "addr:full":"Cnr Kessels Rd & Springfield St MacGregor QLD 4109",
    "addr:postcode":"4109",
    "addr:street":"Cnr Kessels Rd & Springfield St",
    "iso:country":"AU",
    "sg:address":"Cnr Kessels Rd & Springfield St",
    "sg:city":"MacGregor",
    "sg:classifiers":[
        {
            "category":"Autos & Motor Vehicles",
            "subcategory":"Fuel & Gas Station",
            "type":"Retail Goods"
        }
    ],
    "sg:phone":"+61 7 3343 6591",
    "sg:postcode":"4109",
    "sg:province":"QLD",
    "wof:name":"Plus Petrol",
    "wof:placetype":"venue"
},
  "geometry": {"coordinates":[153.07455444300001,-27.5619907379],"type":"Point"}
}