{
  "type": "Feature",
  "properties": {
    "addr:full":"35 Foston Drv Duncraig WA 6023",
    "addr:housenumber":"35",
    "addr:postcode":"6023",
    "addr:street":"Foston Drv",
    "iso:country":"AU",
    "sg:address":"35 Foston Drv",
    "sg:city":"Duncraig",
    "sg:classifiers":[
        {
            "category":"Farming",
            "subcategory":"Farm & Veterinary Services",
            "type":"Manufacturing & Wholesale Goods"
        }
    ],
    "sg:phone":"+61 8 9448 5062",
    "sg:postcode":"6023",
    "sg:province":"WA",
    "sg:tags":[
        "irrigation",
        "reticulation",
        "system"
    ],
    "wof:name":"Atlas Electrical Service",
    "wof:placetype":"venue"
},
  "geometry": {"coordinates":[115.782676697,-31.8241233826],"type":"Point"}
}