{
  "type": "Feature",
  "properties": {
    "iso:country":"AU",
    "sg:address":"U2/ 42 Global Drv",
    "sg:city":"Westmeadows",
    "sg:classifiers":[
        {
            "category":"Professional",
            "subcategory":"Employment Agencies",
            "type":"Services"
        }
    ],
    "sg:phone":"+61 3 9339 6000",
    "sg:postcode":"3049",
    "sg:province":"VIC",
    "sg:tags":[
        "broker",
        "custom"
    ],
    "wof:name":"LR International Pty Ltd",
    "wof:placetype":"venue"
},
  "geometry": {"coordinates":[144.877365,-37.68354],"type":"Point"}
}