{
  "type": "Feature",
  "properties": {
    "addr:full":"21 Kylie Crs Batemans Bay NSW 2536",
    "addr:housenumber":"21",
    "addr:postcode":"2536",
    "addr:street":"Kylie Crs",
    "iso:country":"AU",
    "sg:address":"21 Kylie Crs",
    "sg:city":"Batemans Bay",
    "sg:classifiers":[
        {
            "category":"Utilities",
            "subcategory":"Natural Gas",
            "type":"Services"
        }
    ],
    "sg:phone":"+61 1300 366 116",
    "sg:postcode":"2536",
    "sg:province":"NSW",
    "sg:tags":[
        "supplier"
    ],
    "wof:name":"Gorilla Gas",
    "wof:placetype":"venue"
},
  "geometry": {"coordinates":[150.17732238799999,-35.7084007263],"type":"Point"}
}