{
  "type": "Feature",
  "properties": {
    "iso:country":"AU",
    "sg:address":"10 Warren Ave",
    "sg:city":"Bankstown",
    "sg:classifiers":[
        {
            "category":"Professional",
            "subcategory":"Detective & Security Services",
            "type":"Services"
        }
    ],
    "sg:phone":"+61 2 9708 4488",
    "sg:postcode":"2200",
    "sg:province":"NSW",
    "sg:tags":[
        "guard",
        "patrol"
    ],
    "sg:website":"http://www.reliablesecurity.com.au",
    "wof:name":"Reliable Protective Services",
    "wof:placetype":"venue"
},
  "geometry": {"coordinates":[151.036209,-33.932903],"type":"Point"}
}