{
  "type": "Feature",
  "properties": {
    "iso:country":"AU",
    "sg:address":"171 Sheridan St",
    "sg:city":"Gundagai",
    "sg:classifiers":[
        {
            "category":"Banks & Credit Unions",
            "subcategory":"Bank",
            "type":"Services"
        }
    ],
    "sg:phone":"+61 13 20 32",
    "sg:postcode":"2722",
    "sg:province":"NSW",
    "wof:name":"Westpac",
    "wof:placetype":"venue"
},
  "geometry": {"coordinates":[148.099625,-35.062149],"type":"Point"}
}