{
  "type": "Feature",
  "properties": {
    "addr:full":"57 Mosman St Charters Towers QLD 4820",
    "addr:housenumber":"57",
    "addr:postcode":"4820",
    "addr:street":"Mosman St",
    "iso:country":"AU",
    "sg:address":"57 Mosman St",
    "sg:city":"Charters Towers",
    "sg:classifiers":[
        {
            "category":"Autos & Motor Vehicles",
            "subcategory":"Automobile Sales",
            "type":"Retail Goods"
        }
    ],
    "sg:phone":"+61 7 4787 1177",
    "sg:postcode":"4820",
    "sg:province":"QLD",
    "sg:tags":[
        "car",
        "new"
    ],
    "wof:name":"Tony Ireland Holden",
    "wof:placetype":"venue"
},
  "geometry": {"coordinates":[146.25787399999999,-20.074095],"type":"Point"}
}