{
  "type": "Feature",
  "properties": {
    "addr:full":"33 Thomas St Cardiff NSW 2285",
    "addr:housenumber":"33",
    "addr:postcode":"2285",
    "addr:street":"Thomas St",
    "iso:country":"AU",
    "sg:address":"33 Thomas St",
    "sg:city":"Cardiff",
    "sg:classifiers":[
        {
            "category":"Building & Trades",
            "subcategory":"Construction",
            "type":"Services"
        }
    ],
    "sg:phone":"+61 2 4954 8166",
    "sg:postcode":"2285",
    "sg:province":"NSW",
    "sg:tags":[
        "window",
        "timber"
    ],
    "wof:name":"Cardiff Joinery",
    "wof:placetype":"venue"
},
  "geometry": {"coordinates":[151.660552978,-32.9413452148],"type":"Point"}
}