{
  "type": "Feature",
  "properties": {
    "iso:country":"AU",
    "sg:address":"37- 43 McLachlan St",
    "sg:city":"Apollo Bay",
    "sg:classifiers":[
        {
            "category":"Social Services",
            "subcategory":"Child Care",
            "type":"Services"
        }
    ],
    "sg:phone":"+61 3 5237 8560",
    "sg:postcode":"3233",
    "sg:province":"VIC",
    "wof:name":"Apollo Bay Child Care Centre",
    "wof:placetype":"venue"
},
  "geometry": {"coordinates":[143.66456604000001,-38.7540664673],"type":"Point"}
}