{
  "type": "Feature",
  "properties": {
    "addr:full":"86 Malibar St Fairfield NSW 2165",
    "addr:housenumber":"86",
    "addr:postcode":"2165",
    "addr:street":"Malibar St",
    "iso:country":"AU",
    "sg:address":"86 Malibar St",
    "sg:city":"Fairfield",
    "sg:classifiers":[
        {
            "category":"Social Services",
            "subcategory":"Adult Care",
            "type":"Services"
        }
    ],
    "sg:phone":"+61 421 742 092",
    "sg:postcode":"2165",
    "sg:province":"NSW",
    "sg:tags":[
        "towing"
    ],
    "wof:name":"A5 Fairfield Towing",
    "wof:placetype":"venue"
},
  "geometry": {"coordinates":[150.93978881800001,-33.877494812],"type":"Point"}
}