{
  "type": "Feature",
  "properties": {
    "addr:full":"17a Breakfast Rd Marayong NSW 2148",
    "addr:housenumber":"17a",
    "addr:postcode":"2148",
    "addr:street":"Breakfast Rd",
    "iso:country":"AU",
    "sg:address":"17a Breakfast Rd",
    "sg:city":"Marayong",
    "sg:classifiers":[
        {
            "category":"Personal",
            "subcategory":"Beauty Salon",
            "type":"Services"
        }
    ],
    "sg:phone":"+61 416 051 660",
    "sg:postcode":"2148",
    "sg:province":"NSW",
    "sg:tags":[
        "supply",
        "artist",
        "make-up"
    ],
    "wof:name":"Pucker Up",
    "wof:placetype":"venue"
},
  "geometry": {"coordinates":[150.89288330100001,-33.7465438843],"type":"Point"}
}