{
  "type": "Feature",
  "properties": {
    "iso:country":"AU",
    "sg:address":"Kalinga St",
    "sg:city":"Ballina",
    "sg:classifiers":[
        {
            "category":"Arena",
            "subcategory":"Sports Club",
            "type":"Entertainment"
        }
    ],
    "sg:phone":"+61 2 6686 6380",
    "sg:postcode":"2478",
    "sg:province":"NSW",
    "sg:tags":[
        "league",
        "rugby"
    ],
    "wof:name":"Ballina Rugby Club",
    "wof:placetype":"venue"
},
  "geometry": {"coordinates":[153.54377746599999,-28.8641262054],"type":"Point"}
}