{
  "type": "Feature",
  "properties": {
    "addr:full":"Unit 1, 27 Econo Pl Silverdale NSW 2752",
    "addr:housenumber":"27",
    "addr:postcode":"2752",
    "addr:street":"Econo Pl",
    "iso:country":"AU",
    "sg:address":"Unit 1, 27 Econo Pl",
    "sg:city":"Silverdale",
    "sg:classifiers":[
        {
            "category":"Transit Center",
            "subcategory":"Freight",
            "type":"Transportation"
        }
    ],
    "sg:phone":"+61 2 4774 2154",
    "sg:postcode":"2752",
    "sg:province":"NSW",
    "sg:tags":[
        "turner",
        "wood"
    ],
    "wof:name":"Better Building Products",
    "wof:placetype":"venue"
},
  "geometry": {"coordinates":[150.613723755,-33.8903846741],"type":"Point"}
}