{
  "type": "Feature",
  "properties": {
    "addr:full":"48 Leichardt St Mundubbera QLD 4626",
    "addr:housenumber":"48",
    "addr:postcode":"4626",
    "addr:street":"Leichardt St",
    "iso:country":"AU",
    "sg:address":"48 Leichardt St",
    "sg:city":"Mundubbera",
    "sg:classifiers":[
        {
            "category":"Organizations",
            "subcategory":"Non-profit Organization",
            "type":"Services"
        }
    ],
    "sg:phone":"+61 7 4165 4163",
    "sg:postcode":"4626",
    "sg:province":"QLD",
    "sg:tags":[
        "support",
        "disability",
        "organisation"
    ],
    "wof:name":"Blue Care",
    "wof:placetype":"venue"
},
  "geometry": {"coordinates":[151.304337,-25.590166],"type":"Point"}
}