{
  "type": "Feature",
  "properties": {
    "iso:country":"AU",
    "sg:address":"PO Box 90",
    "sg:city":"Kurrajong",
    "sg:classifiers":[
        {
            "category":"Building & Trades",
            "subcategory":"Construction",
            "type":"Services"
        }
    ],
    "sg:phone":"+61 2 4571 3881",
    "sg:postcode":"2758",
    "sg:province":"NSW",
    "sg:tags":[
        "renovation",
        "alterations",
        "extension",
        "contractor"
    ],
    "wof:name":"Kurrajong Constructions (Aust) Pty Limited",
    "wof:placetype":"venue"
},
  "geometry": {"coordinates":[150.674850464,-33.5483703613],"type":"Point"}
}