{
  "type": "Feature",
  "properties": {
    "addr:full":"Lot 1, Cnr Port Wakefield & Ryans Rds Parafield Gardens SA 5107",
    "addr:housenumber":"cnr",
    "addr:postcode":"5107",
    "addr:street":"Port",
    "iso:country":"AU",
    "sg:address":"Lot 1, Cnr Port Wakefield & Ryans Rds",
    "sg:city":"Parafield Gardens",
    "sg:classifiers":[
        {
            "category":"Home & Garden",
            "subcategory":"Garden Supply",
            "type":"Retail Goods"
        }
    ],
    "sg:phone":"+61 8 8250 9988",
    "sg:postcode":"5107",
    "sg:province":"SA",
    "sg:tags":[
        "shed"
    ],
    "wof:name":"Galeprufe Constructions Pty Ltd",
    "wof:placetype":"venue"
},
  "geometry": {"coordinates":[138.59591674800001,-34.7816314697],"type":"Point"}
}