{
  "type": "Feature",
  "properties": {
    "addr:full":"Algoma Rd Mutchilba QLD 4872",
    "addr:postcode":"4872",
    "addr:street":"Algoma Rd",
    "iso:country":"AU",
    "sg:address":"Algoma Rd",
    "sg:city":"Mutchilba",
    "sg:classifiers":[
        {
            "category":"Farming",
            "subcategory":"Farm",
            "type":"Manufacturing & Wholesale Goods"
        }
    ],
    "sg:phone":"+61 7 4093 1132",
    "sg:postcode":"4872",
    "sg:province":"QLD",
    "sg:tags":[
        "farmer"
    ],
    "wof:name":"Palmeri A",
    "wof:placetype":"venue"
},
  "geometry": {"coordinates":[145.23138427699999,-17.1393871307],"type":"Point"}
}