{
  "type": "Feature",
  "properties": {
    "iso:country":"AU",
    "sg:address":"198 Carrington St",
    "sg:city":"Hilton",
    "sg:classifiers":[
        {
            "category":"Professional",
            "subcategory":"Detective & Security Services",
            "type":"Services"
        }
    ],
    "sg:phone":"+61 8 9337 3852",
    "sg:postcode":"6163",
    "sg:province":"WA",
    "sg:tags":[
        "consultant",
        "system"
    ],
    "wof:name":"Get Smart Electronics",
    "wof:placetype":"venue"
},
  "geometry": {"coordinates":[115.779579,-32.063499],"type":"Point"}
}