{
  "type": "Feature",
  "properties": {
    "addr:full":"59-61 Victoria Pde Fitzroy VIC 3065",
    "addr:housenumber":"59-61",
    "addr:postcode":"3065",
    "addr:street":"Victoria Pde",
    "iso:country":"AU",
    "sg:address":"59-61 Victoria Pde",
    "sg:city":"Fitzroy",
    "sg:classifiers":[
        {
            "category":"Health Services",
            "subcategory":"Doctor",
            "type":"Services"
        }
    ],
    "sg:phone":"+61 3 9419 5138",
    "sg:postcode":"3065",
    "sg:province":"VIC",
    "sg:tags":[
        "medical",
        "practitioner"
    ],
    "wof:name":"Di Quinzio Dr Megan K.W.",
    "wof:placetype":"venue"
},
  "geometry": {"coordinates":[144.97915649399999,-37.8009185791],"type":"Point"}
}