{
  "type": "Feature",
  "properties": {
    "iso:country":"AU",
    "sg:address":"PO Box 254",
    "sg:city":"Glenorie",
    "sg:classifiers":[
        {
            "category":"Building & Trades",
            "subcategory":"Pest Control",
            "type":"Services"
        }
    ],
    "sg:phone":"+61 2 9652 1547",
    "sg:postcode":"2157",
    "sg:province":"NSW",
    "wof:name":"McLarty Jim Pest Control",
    "wof:placetype":"venue"
},
  "geometry": {"coordinates":[151.024047852,-33.6238288879],"type":"Point"}
}