{
  "type": "Feature",
  "properties": {
    "addr:full":"695A Princes Hwy Tempe NSW 2044",
    "addr:housenumber":"695a",
    "addr:postcode":"2044",
    "addr:street":"Princes Hwy",
    "iso:country":"AU",
    "sg:address":"695A Princes Hwy",
    "sg:city":"Tempe",
    "sg:classifiers":[
        {
            "category":"Education",
            "subcategory":"Dance Studio",
            "type":"Public Place"
        }
    ],
    "sg:phone":"+61 403 397 474",
    "sg:postcode":"2044",
    "sg:province":"NSW",
    "sg:tags":[
        "venue",
        "tuition"
    ],
    "wof:name":"Alhambra Latin-Arabic Dance",
    "wof:placetype":"venue"
},
  "geometry": {"coordinates":[151.16197199999999,-33.923561],"type":"Point"}
}