{
  "type": "Feature",
  "properties": {
    "iso:country":"AU",
    "sg:address":"135 Harold St",
    "sg:city":"Holland Park",
    "sg:classifiers":[
        {
            "category":"Professional",
            "subcategory":"Art Services",
            "type":"Services"
        }
    ],
    "sg:phone":"+61 7 3397 4936",
    "sg:postcode":"4121",
    "sg:province":"QLD",
    "sg:tags":[
        "conservation",
        "restoration"
    ],
    "wof:name":"All Antique Art Restoration & Gilding By Karel Kellner",
    "wof:placetype":"venue"
},
  "geometry": {"coordinates":[153.06512451200001,-27.5148181915],"type":"Point"}
}