{
  "type": "Feature",
  "properties": {
    "addr:full":"42 Meeks Rd Marrickville NSW 2204",
    "addr:housenumber":"42",
    "addr:postcode":"2204",
    "addr:street":"Meeks Rd",
    "iso:country":"AU",
    "sg:address":"42 Meeks Rd",
    "sg:city":"Marrickville",
    "sg:classifiers":[
        {
            "category":"Cafe",
            "type":"Food & Drink"
        }
    ],
    "sg:phone":"+61 2 9565 1299",
    "sg:postcode":"2204",
    "sg:province":"NSW",
    "wof:name":"Premier Packaging Supplies",
    "wof:placetype":"venue"
},
  "geometry": {"coordinates":[151.161652,-33.911682],"type":"Point"}
}