{
  "type": "Feature",
  "properties": {
    "addr:full":"Shop 16, Wallsend Plaza 24 Kokera St Wallsend NSW 2287",
    "addr:housenumber":"shop 16;24",
    "addr:postcode":"2287",
    "addr:street":"Wallsend Plaza;St",
    "iso:country":"AU",
    "sg:address":"Shop 16, Wallsend Plaza 24 Kokera St",
    "sg:city":"Wallsend",
    "sg:classifiers":[
        {
            "category":"Health Services",
            "subcategory":"Optometrist",
            "type":"Services"
        }
    ],
    "sg:phone":"+61 2 4950 1098",
    "sg:postcode":"2287",
    "sg:province":"NSW",
    "wof:name":"Simon Watson Optometrist",
    "wof:placetype":"venue"
},
  "geometry": {"coordinates":[151.66595459000001,-32.9030838013],"type":"Point"}
}