{
  "type": "Feature",
  "properties": {
    "addr:full":"Princes Hwy Panmure VIC 3265",
    "addr:postcode":"3265",
    "addr:street":"Princes Hwy",
    "iso:country":"AU",
    "sg:address":"Princes Hwy",
    "sg:city":"Panmure",
    "sg:classifiers":[
        {
            "category":"Food & Beverages",
            "subcategory":"Groceries & Convenience Stores",
            "type":"Retail Goods"
        }
    ],
    "sg:phone":"+61 3 5567 6281",
    "sg:postcode":"3265",
    "sg:province":"VIC",
    "wof:name":"Panmure General Store",
    "wof:placetype":"venue"
},
  "geometry": {"coordinates":[142.724441528,-38.3376502991],"type":"Point"}
}