{
  "type": "Feature",
  "properties": {
    "iso:country":"AU",
    "sg:address":"Suite 1 Bell Place The Linkway",
    "sg:city":"Mudgeeraba",
    "sg:classifiers":[
        {
            "category":"Health Services",
            "subcategory":"Doctor",
            "type":"Services"
        }
    ],
    "sg:phone":"+61 7 5525 2588",
    "sg:postcode":"4213",
    "sg:province":"QLD",
    "sg:tags":[
        "medical",
        "practitioner"
    ],
    "wof:name":"Badawy Maryse Dr",
    "wof:placetype":"venue"
},
  "geometry": {"coordinates":[153.365768433,-28.0802936554],"type":"Point"}
}