{
  "type": "Feature",
  "properties": {
    "addr:full":"Shed 7, Lot 6 MacPeak Crs Smithfield QLD 4878",
    "addr:housenumber":"7 lot 6",
    "addr:postcode":"4878",
    "addr:street":"Macpeak Crs",
    "iso:country":"AU",
    "sg:address":"Shed 7, Lot 6 MacPeak Crs",
    "sg:city":"Smithfield",
    "sg:classifiers":[
        {
            "category":"Retail",
            "subcategory":"Auto Repair",
            "type":"Services"
        }
    ],
    "sg:phone":"+61 7 4057 6797",
    "sg:postcode":"4878",
    "sg:province":"QLD",
    "sg:tags":[
        "repairer",
        "motor",
        "engineer"
    ],
    "wof:name":"Smithfield Automotive",
    "wof:placetype":"venue"
},
  "geometry": {"coordinates":[145.68907165499999,-16.83852005],"type":"Point"}
}