{
  "type": "Feature",
  "properties": {
    "iso:country":"AU",
    "sg:address":"135 Noble St",
    "sg:city":"Newtown",
    "sg:classifiers":[
        {
            "category":"Building & Trades",
            "subcategory":"Construction",
            "type":"Services"
        }
    ],
    "sg:phone":"+61 3 5221 0413",
    "sg:postcode":"3220",
    "sg:province":"VIC",
    "sg:tags":[
        "contractor"
    ],
    "wof:name":"M.I.B. Developments Pty Ltd",
    "wof:placetype":"venue"
},
  "geometry": {"coordinates":[144.337006,-38.153065],"type":"Point"}
}