{
  "type": "Feature",
  "properties": {
    "addr:full":"10 David Muir St Slade Point QLD 4740",
    "addr:housenumber":"10",
    "addr:postcode":"4740",
    "addr:street":"David Muir St",
    "iso:country":"AU",
    "sg:address":"10 David Muir St",
    "sg:city":"Slade Point",
    "sg:phone":"+61 7 4955 4149",
    "sg:postcode":"4740",
    "sg:province":"QLD",
    "wof:name":"North Queensland Independant Fuel Services Pty Ltd",
    "wof:placetype":"venue"
},
  "geometry": {"coordinates":[149.21258499999999,-21.090885],"type":"Point"}
}