{
  "type": "Feature",
  "properties": {
    "iso:country":"AU",
    "sg:address":"10 David Muir St",
    "sg:city":"Slade Point",
    "sg:phone":"+61 7 4955 4149",
    "sg:postcode":"4740",
    "sg:province":"QLD",
    "wof:name":"North Queensland Independant Fuel Services Pty Ltd",
    "wof:placetype":"venue"
},
  "geometry": {"coordinates":[149.212585,-21.090885],"type":"Point"}
}