{
  "type": "Feature",
  "properties": {
    "iso:country":"AU",
    "sg:address":"90 Harrington St",
    "sg:city":"Cabramatta West",
    "sg:classifiers":[
        {
            "category":"Personal",
            "subcategory":"Beauty Salon",
            "type":"Services"
        }
    ],
    "sg:phone":"+61 2 9711 3222",
    "sg:postcode":"2166",
    "sg:province":"NSW",
    "wof:name":"Beauty Buzz",
    "wof:placetype":"venue"
},
  "geometry": {"coordinates":[150.90907287600001,-33.893825531],"type":"Point"}
}