{
  "type": "Feature",
  "properties": {
    "addr:full":"PO Box 31 Bentleigh VIC 3204",
    "addr:postcode":"3204",
    "iso:country":"AU",
    "sg:address":"PO Box 31",
    "sg:city":"Bentleigh",
    "sg:classifiers":[
        {
            "category":"Health Services",
            "subcategory":"Health Practitioner",
            "type":"Services"
        }
    ],
    "sg:phone":"+61 409 578 526",
    "sg:postcode":"3204",
    "sg:province":"VIC",
    "sg:tags":[
        "alternative"
    ],
    "wof:name":"South Eastern Health Education Programs",
    "wof:placetype":"venue"
},
  "geometry": {"coordinates":[145.026962,-37.91193],"type":"Point"}
}