{
  "type": "Feature",
  "properties": {
    "iso:country":"AU",
    "sg:address":"1 Arrigo St",
    "sg:city":"Wanneroo",
    "sg:classifiers":[
        {
            "category":"Farming",
            "subcategory":"Farm & Veterinary Services",
            "type":"Manufacturing & Wholesale Goods"
        }
    ],
    "sg:phone":"+61 8 9409 9129",
    "sg:postcode":"6065",
    "sg:province":"WA",
    "sg:tags":[
        "seedsman"
    ],
    "wof:name":"Mirco Bros Pty Ltd",
    "wof:placetype":"venue"
},
  "geometry": {"coordinates":[115.817863464,-31.7875576019],"type":"Point"}
}