{
  "type": "Feature",
  "properties": {
    "addr:full":"25 Greenknoll Ave Rostrevor SA 5073",
    "addr:housenumber":"25",
    "addr:postcode":"5073",
    "addr:street":"Greenknoll Ave",
    "iso:country":"AU",
    "sg:address":"25 Greenknoll Ave",
    "sg:city":"Rostrevor",
    "sg:classifiers":[
        {
            "category":"Building & Trades",
            "subcategory":"Cleaning & Sanitation",
            "type":"Services"
        }
    ],
    "sg:phone":"+61 418 829 348",
    "sg:postcode":"5073",
    "sg:province":"SA",
    "sg:tags":[
        "commercial",
        "maintenance"
    ],
    "wof:name":"5star Property Maintenance & Services",
    "wof:placetype":"venue"
},
  "geometry": {"coordinates":[138.69583129899999,-34.8870697021],"type":"Point"}
}