{
  "type": "Feature",
  "properties": {
    "iso:country":"AU",
    "sg:address":"627 Sydney Rd",
    "sg:city":"Brunswick",
    "sg:classifiers":[
        {
            "category":"Cafe",
            "type":"Food & Drink"
        }
    ],
    "sg:phone":"+61 3 9386 5400",
    "sg:postcode":"3056",
    "sg:province":"VIC",
    "wof:name":"Sahara Pizza",
    "wof:placetype":"venue"
},
  "geometry": {"coordinates":[144.962966919,-37.762878418],"type":"Point"}
}