{
  "type": "Feature",
  "properties": {
    "addr:full":"732 New South Head Rd Rose Bay NSW 2029",
    "addr:housenumber":"732",
    "addr:postcode":"2029",
    "addr:street":"New South Head Rd",
    "iso:country":"AU",
    "sg:address":"732 New South Head Rd",
    "sg:city":"Rose Bay",
    "sg:classifiers":[
        {
            "category":"Fast Food",
            "type":"Food & Drink"
        }
    ],
    "sg:phone":"+61 2 9371 0045",
    "sg:postcode":"2029",
    "sg:province":"NSW",
    "sg:tags":[
        "away",
        "take"
    ],
    "wof:name":"Charcoal Chickens Rose Bay",
    "wof:placetype":"venue"
},
  "geometry": {"coordinates":[151.269927978,-33.8693237305],"type":"Point"}
}