{
  "type": "Feature",
  "properties": {
    "addr:full":"3B, 211 Montague Rd West End (Brisbane) QLD 4101",
    "addr:housenumber":"3b 211",
    "addr:postcode":"4101",
    "addr:street":"Montague Rd",
    "iso:country":"AU",
    "sg:address":"3B, 211 Montague Rd",
    "sg:city":"West End (Brisbane)",
    "sg:classifiers":[
        {
            "category":"Professional",
            "subcategory":"Printing & Photocopies",
            "type":"Services"
        }
    ],
    "sg:phone":"+61 7 3217 2288",
    "sg:postcode":"4101",
    "sg:province":"QLD",
    "sg:tags":[
        "screen",
        "printer"
    ],
    "wof:name":"Adval Brisbane",
    "wof:placetype":"venue"
},
  "geometry": {"coordinates":[153.008056641,-27.4767074585],"type":"Point"}
}