{
  "type": "Feature",
  "properties": {
    "addr:full":"PO Box 214 Traralgon VIC 3844",
    "addr:postcode":"3844",
    "iso:country":"AU",
    "sg:address":"PO Box 214",
    "sg:city":"Traralgon",
    "sg:classifiers":[
        {
            "category":"Building & Trades",
            "subcategory":"Plumbing",
            "type":"Services"
        }
    ],
    "sg:phone":"+61 418 513 942",
    "sg:postcode":"3844",
    "sg:province":"VIC",
    "sg:tags":[
        "plumber",
        "gasfitters"
    ],
    "wof:name":"R & D Goddard Plumbing",
    "wof:placetype":"venue"
},
  "geometry": {"coordinates":[146.53814697300001,-38.1949501038],"type":"Point"}
}