{
  "type": "Feature",
  "properties": {
    "addr:full":"176 Raymond St Sale VIC 3850",
    "addr:housenumber":"176",
    "addr:postcode":"3850",
    "addr:street":"Raymond St",
    "iso:country":"AU",
    "sg:address":"176 Raymond St",
    "sg:city":"Sale",
    "sg:classifiers":[
        {
            "category":"Health Services",
            "subcategory":"Doctor",
            "type":"Services"
        }
    ],
    "sg:phone":"+61 3 5143 2432",
    "sg:postcode":"3850",
    "sg:province":"VIC",
    "sg:tags":[
        "reflexology"
    ],
    "wof:name":"Andrea Hall",
    "wof:placetype":"venue"
},
  "geometry": {"coordinates":[147.06588745100001,-38.1090774536],"type":"Point"}
}