{
  "type": "Feature",
  "properties": {
    "iso:country":"AU",
    "sg:address":"PO Box 228",
    "sg:city":"Hunter Region Mail Centre",
    "sg:classifiers":[
        {
            "category":"Education",
            "subcategory":"Special Training",
            "type":"Public Place"
        }
    ],
    "sg:phone":"+61 2 4983 1129",
    "sg:postcode":"2310",
    "sg:province":"NSW",
    "sg:tags":[
        "development"
    ],
    "wof:name":"OTR Training",
    "wof:placetype":"venue"
},
  "geometry": {"coordinates":[151.907242,-32.788738],"type":"Point"}
}