{
  "type": "Feature",
  "properties": {
    "iso:country":"AU",
    "sg:address":"24 Blakesley St",
    "sg:city":"Chatswood",
    "sg:classifiers":[
        {
            "category":"Professional",
            "subcategory":"Management & Consulting",
            "type":"Services"
        }
    ],
    "sg:phone":"+61 413 312 134",
    "sg:postcode":"2067",
    "sg:province":"NSW",
    "sg:tags":[
        "consultant"
    ],
    "wof:name":"Huon Strategic Management",
    "wof:placetype":"venue"
},
  "geometry": {"coordinates":[151.18847656200001,-33.793762207],"type":"Point"}
}