{
  "type": "Feature",
  "properties": {
    "addr:full":"80 Explorer Drv Thornlie WA 6108",
    "addr:housenumber":"80",
    "addr:postcode":"6108",
    "addr:street":"Explorer Drv",
    "iso:country":"AU",
    "sg:address":"80 Explorer Drv",
    "sg:city":"Thornlie",
    "sg:classifiers":[
        {
            "category":"Home & Garden",
            "subcategory":"Garden Supply",
            "type":"Retail Goods"
        }
    ],
    "sg:phone":"+61 8 9493 2725",
    "sg:postcode":"6108",
    "sg:province":"WA",
    "sg:tags":[
        "equipment"
    ],
    "wof:name":"Garden Goodies (Parkers)",
    "wof:placetype":"venue"
},
  "geometry": {"coordinates":[115.960510254,-32.0736961365],"type":"Point"}
}