{
  "type": "Feature",
  "properties": {
    "addr:full":"49 Derrimut Rd Werribee VIC 3030",
    "addr:housenumber":"49",
    "addr:postcode":"3030",
    "addr:street":"Derrimut Rd",
    "iso:country":"AU",
    "sg:address":"49 Derrimut Rd",
    "sg:city":"Werribee",
    "sg:classifiers":[
        {
            "category":"Health Services",
            "subcategory":"Health Practitioner",
            "type":"Services"
        }
    ],
    "sg:phone":"+61 3 9734 1225",
    "sg:postcode":"3030",
    "sg:province":"VIC",
    "sg:tags":[
        "acupuncture"
    ],
    "wof:name":"Screen Daniel",
    "wof:placetype":"venue"
},
  "geometry": {"coordinates":[144.680725,-37.888668],"type":"Point"}
}