{
  "type": "Feature",
  "properties": {
    "addr:full":"Shop 6 Cnr Day & Carpenter Sts Colyton NSW 2760",
    "addr:housenumber":"shop 6",
    "addr:postcode":"2760",
    "addr:street":"Cnr Day & Carpenter Sts",
    "iso:country":"AU",
    "sg:address":"Shop 6 Cnr Day & Carpenter Sts",
    "sg:city":"Colyton",
    "sg:classifiers":[
        {
            "category":"Real Estate",
            "subcategory":"Real Estate Agent",
            "type":"Services"
        }
    ],
    "sg:phone":"+61 2 9623 4435",
    "sg:postcode":"2760",
    "sg:province":"NSW",
    "wof:name":"Australian Real Estate",
    "wof:placetype":"venue"
},
  "geometry": {"coordinates":[150.79200744600001,-33.7783088684],"type":"Point"}
}