{
  "type": "Feature",
  "properties": {
    "addr:full":"10 Church St Castle Hill NSW 2154",
    "addr:housenumber":"10",
    "addr:postcode":"2154",
    "addr:street":"Church St",
    "iso:country":"AU",
    "sg:address":"10 Church St",
    "sg:city":"Castle Hill",
    "sg:classifiers":[
        {
            "category":"Professional",
            "subcategory":"Business Services",
            "type":"Services"
        }
    ],
    "sg:phone":"+61 2 9680 8886",
    "sg:postcode":"2154",
    "sg:province":"NSW",
    "sg:tags":[
        "drafting"
    ],
    "wof:name":"All House Plans Drafting Services",
    "wof:placetype":"venue"
},
  "geometry": {"coordinates":[151.001495361,-33.7388343811],"type":"Point"}
}