{
  "type": "Feature",
  "properties": {
    "iso:country":"AU",
    "sg:address":"PO Box 522",
    "sg:city":"Essendon",
    "sg:classifiers":[
        {
            "category":"Organizations",
            "subcategory":"Professional Association",
            "type":"Services"
        }
    ],
    "sg:phone":"+61 422 887 998",
    "sg:postcode":"3040",
    "sg:province":"VIC",
    "sg:tags":[
        "web",
        "internet"
    ],
    "wof:name":"UC Web Design",
    "wof:placetype":"venue"
},
  "geometry": {"coordinates":[144.90951538100001,-37.7515411377],"type":"Point"}
}