{
  "type": "Feature",
  "properties": {
    "iso:country":"AU",
    "sg:address":"461 Liverpool Rd",
    "sg:city":"South Strathfield",
    "sg:classifiers":[
        {
            "category":"Shopping",
            "subcategory":"Computers & Home Electronics",
            "type":"Retail Goods"
        }
    ],
    "sg:phone":"+61 2 9642 0885",
    "sg:postcode":"2136",
    "sg:province":"NSW",
    "sg:tags":[
        "hi-fi",
        "equipment"
    ],
    "wof:name":"Zero One Digital",
    "wof:placetype":"venue"
},
  "geometry": {"coordinates":[151.083862305,-33.8917274475],"type":"Point"}
}