{
  "type": "Feature",
  "properties": {
    "addr:full":"Suite 9 44 Beach St Frankston VIC 3199",
    "addr:housenumber":"44",
    "addr:postcode":"3199",
    "addr:street":"Beach St",
    "iso:country":"AU",
    "sg:address":"Suite 9 44 Beach St",
    "sg:city":"Frankston",
    "sg:classifiers":[
        {
            "category":"Retail",
            "subcategory":"Laundry & Dry Cleaning",
            "type":"Services"
        }
    ],
    "sg:phone":"+61 3 9781 5593",
    "sg:postcode":"3199",
    "sg:province":"VIC",
    "sg:tags":[
        "manicurist"
    ],
    "wof:name":"Frankston Epilation Centre",
    "wof:placetype":"venue"
},
  "geometry": {"coordinates":[144.93754577600001,-37.8427886963],"type":"Point"}
}