{
  "type": "Feature",
  "properties": {
    "addr:full":"110 Greaves St Werribee VIC 3030",
    "addr:housenumber":"110",
    "addr:postcode":"3030",
    "addr:street":"Greaves St",
    "iso:country":"AU",
    "sg:address":"110 Greaves St",
    "sg:city":"Werribee",
    "sg:classifiers":[
        {
            "category":"Education",
            "subcategory":"School",
            "type":"Public Place"
        }
    ],
    "sg:phone":"+61 3 9741 3686",
    "sg:postcode":"3030",
    "sg:province":"VIC",
    "sg:tags":[
        "co-educational"
    ],
    "wof:name":"St Andrew's Primary",
    "wof:placetype":"venue"
},
  "geometry": {"coordinates":[144.65057400000001,-37.901699],"type":"Point"}
}