{
  "type": "Feature",
  "properties": {
    "addr:full":"Ground Floor 156- 158 King St Newtown NSW 2042",
    "addr:housenumber":"156 158",
    "addr:postcode":"2042",
    "addr:street":"King St",
    "iso:country":"AU",
    "sg:address":"Ground Floor 156- 158 King St",
    "sg:city":"Newtown",
    "sg:classifiers":[
        {
            "category":"Cafe",
            "type":"Food & Drink"
        }
    ],
    "sg:phone":"+61 2 9550 3884",
    "sg:postcode":"2042",
    "sg:province":"NSW",
    "wof:name":"Gloria Jean's Coffees",
    "wof:placetype":"venue"
},
  "geometry": {"coordinates":[151.183334,-33.893837],"type":"Point"}
}