{
  "type": "Feature",
  "properties": {
    "addr:full":"Suite 1 Level 3/ 171 Bigge St Liverpool NSW 2170",
    "addr:housenumber":"/ 171",
    "addr:postcode":"2170",
    "addr:street":"Bigge St",
    "iso:country":"AU",
    "sg:address":"Suite 1 Level 3/ 171 Bigge St",
    "sg:city":"Liverpool",
    "sg:classifiers":[
        {
            "category":"Health Services",
            "subcategory":"Doctor",
            "type":"Services"
        }
    ],
    "sg:phone":"+61 2 9822 8133",
    "sg:postcode":"2170",
    "sg:province":"NSW",
    "sg:tags":[
        "medical",
        "practitioner"
    ],
    "wof:name":"Abi-Hanna D Dr",
    "wof:placetype":"venue"
},
  "geometry": {"coordinates":[150.9269104,-33.9218521118],"type":"Point"}
}