{
  "type": "Feature",
  "properties": {
    "iso:country":"AU",
    "sg:address":"Suite 2, 119 Lonsdale St",
    "sg:city":"Dandenong",
    "sg:classifiers":[
        {
            "category":"Professional",
            "subcategory":"Employment Agencies",
            "type":"Services"
        }
    ],
    "sg:phone":"+61 1300 888 728",
    "sg:postcode":"3175",
    "sg:province":"VIC",
    "sg:tags":[
        "provider",
        "internet"
    ],
    "wof:name":"Netlink Communications Services",
    "wof:placetype":"venue"
},
  "geometry": {"coordinates":[145.21479797399999,-37.9913291931],"type":"Point"}
}