{
  "type": "Feature",
  "properties": {
    "iso:country":"AU",
    "sg:address":"37 Columbine Ave",
    "sg:city":"Bankstown",
    "sg:classifiers":[
        {
            "category":"Building & Trades",
            "subcategory":"Construction",
            "type":"Services"
        }
    ],
    "sg:phone":"+61 411 455 554",
    "sg:postcode":"2200",
    "sg:province":"NSW",
    "sg:tags":[
        "contractor"
    ],
    "wof:name":"Komplete Constructions Pty Ltd",
    "wof:placetype":"venue"
},
  "geometry": {"coordinates":[151.042587,-33.925175],"type":"Point"}
}