{
  "type": "Feature",
  "properties": {
    "addr:full":"56 Cattley St Burnie TAS 7320",
    "addr:housenumber":"56",
    "addr:postcode":"7320",
    "addr:street":"Cattley St",
    "iso:country":"AU",
    "sg:address":"56 Cattley St",
    "sg:city":"Burnie",
    "sg:classifiers":[
        {
            "category":"Health Services",
            "subcategory":"Doctor",
            "type":"Services"
        }
    ],
    "sg:phone":"+61 3 6430 6697",
    "sg:postcode":"7320",
    "sg:province":"TAS",
    "sg:tags":[
        "medical",
        "practitioner"
    ],
    "wof:name":"McMahon A, Paech P F, Mykytowycz M, Shulman J M",
    "wof:placetype":"venue"
},
  "geometry": {"coordinates":[145.90394599999999,-41.05201],"type":"Point"}
}