{
  "type": "Feature",
  "properties": {
    "iso:country":"AU",
    "sg:address":"1131 Sandgate Rd",
    "sg:city":"Nundah",
    "sg:classifiers":[
        {
            "category":"Arena",
            "subcategory":"Sports Club",
            "type":"Entertainment"
        }
    ],
    "sg:phone":"+61 7 3256 7100",
    "sg:postcode":"4012",
    "sg:province":"QLD",
    "sg:tags":[
        "defence",
        "supply",
        "self",
        "instruction",
        "martial art"
    ],
    "wof:name":"Wing Chun Do Kung Fu",
    "wof:placetype":"venue"
},
  "geometry": {"coordinates":[153.06053161599999,-27.4040813446],"type":"Point"}
}