{
  "type": "Feature",
  "properties": {
    "iso:country":"AU",
    "sg:address":"7 Headland Crs",
    "sg:city":"Woodcroft",
    "sg:classifiers":[
        {
            "category":"Recreation",
            "subcategory":"Boat Charter",
            "type":"Entertainment"
        }
    ],
    "sg:phone":"+61 407 040 758",
    "sg:postcode":"5162",
    "sg:province":"SA",
    "wof:name":"Paradise Cove Boat Charter",
    "wof:placetype":"venue"
},
  "geometry": {"coordinates":[138.55705261200001,-35.1035385132],"type":"Point"}
}