{
  "type": "Feature",
  "properties": {
    "addr:full":"Shp7/ 476 South Arm Rd Lauderdale TAS 7021",
    "addr:housenumber":"476",
    "addr:postcode":"7021",
    "addr:street":"South Arm Rd",
    "iso:country":"AU",
    "sg:address":"Shp7/ 476 South Arm Rd",
    "sg:city":"Lauderdale",
    "sg:classifiers":[
        {
            "category":"Food & Beverages",
            "subcategory":"Groceries & Convenience Stores",
            "type":"Retail Goods"
        }
    ],
    "sg:phone":"+61 3 6248 7488",
    "sg:postcode":"7021",
    "sg:province":"TAS",
    "wof:name":"Asian Gourmet Food",
    "wof:placetype":"venue"
},
  "geometry": {"coordinates":[147.48257446299999,-42.9082450867],"type":"Point"}
}