{
  "type": "Feature",
  "properties": {
    "addr:full":"43 Havilah Rd Long Gully VIC 3550",
    "addr:housenumber":"43",
    "addr:postcode":"3550",
    "addr:street":"Havilah Rd",
    "iso:country":"AU",
    "sg:address":"43 Havilah Rd",
    "sg:city":"Long Gully",
    "sg:classifiers":[
        {
            "category":"Professional",
            "subcategory":"Detective & Security Services",
            "type":"Services"
        }
    ],
    "sg:phone":"+61 3 5442 1562",
    "sg:postcode":"3550",
    "sg:province":"VIC",
    "sg:tags":[
        "protective",
        "rustproofing"
    ],
    "wof:name":"Bendigo Electroplating & Metal Polishers",
    "wof:placetype":"venue"
},
  "geometry": {"coordinates":[144.263793945,-36.74401474],"type":"Point"}
}