{
  "type": "Feature",
  "properties": {
    "addr:full":"3 Bean Rd Bruce Rock WA 6418",
    "addr:housenumber":"3",
    "addr:postcode":"6418",
    "addr:street":"Bean Rd",
    "iso:country":"AU",
    "sg:address":"3 Bean Rd",
    "sg:city":"Bruce Rock",
    "sg:classifiers":[
        {
            "category":"Social Services",
            "subcategory":"Child Care",
            "type":"Services"
        }
    ],
    "sg:phone":"+61 8 9061 1195",
    "sg:postcode":"6418",
    "sg:province":"WA",
    "wof:name":"Bruce Rock Day Care Centre",
    "wof:placetype":"venue"
},
  "geometry": {"coordinates":[118.14723205599999,-31.872133255],"type":"Point"}
}