{
  "type": "Feature",
  "properties": {
    "iso:country":"AU",
    "sg:address":"Shop 22, 219 Hampton Rd",
    "sg:city":"South Fremantle",
    "sg:classifiers":[
        {
            "category":"Real Estate",
            "subcategory":"Real Estate Agent",
            "type":"Services"
        }
    ],
    "sg:phone":"+61 8 9430 9907",
    "sg:postcode":"6162",
    "sg:province":"WA",
    "wof:name":"Loreden Estates",
    "wof:placetype":"venue"
},
  "geometry": {"coordinates":[115.760132,-32.074459],"type":"Point"}
}