{
  "type": "Feature",
  "properties": {
    "addr:full":"115 Radium St Welshpool WA 6106",
    "addr:housenumber":"115",
    "addr:postcode":"6106",
    "addr:street":"Radium St",
    "iso:country":"AU",
    "sg:address":"115 Radium St",
    "sg:city":"Welshpool",
    "sg:classifiers":[
        {
            "category":"Communications",
            "subcategory":"Television Station",
            "type":"Services"
        }
    ],
    "sg:phone":"+61 8 9350 9933",
    "sg:postcode":"6106",
    "sg:province":"WA",
    "sg:tags":[
        "screening",
        "machinery",
        "grading"
    ],
    "wof:name":"Screenex Australia Pty Ltd",
    "wof:placetype":"venue"
},
  "geometry": {"coordinates":[115.933792114,-31.9979400635],"type":"Point"}
}