{
  "type": "Feature",
  "properties": {
    "iso:country":"AU",
    "sg:address":"30 Main Rd",
    "sg:city":"Derby",
    "sg:classifiers":[
        {
            "category":"Social Services",
            "subcategory":"Adult Care",
            "type":"Services"
        }
    ],
    "sg:phone":"+61 3 6354 2477",
    "sg:postcode":"7264",
    "sg:province":"TAS",
    "sg:tags":[
        "towing"
    ],
    "wof:name":"Caltex Service Station Derby",
    "wof:placetype":"venue"
},
  "geometry": {"coordinates":[147.93141199999999,-41.083179],"type":"Point"}
}