{
  "type": "Feature",
  "properties": {
    "addr:full":"24 Coventry St Montmorency VIC 3094",
    "addr:housenumber":"24",
    "addr:postcode":"3094",
    "addr:street":"Coventry St",
    "iso:country":"AU",
    "sg:address":"24 Coventry St",
    "sg:city":"Montmorency",
    "sg:classifiers":[
        {
            "category":"Professional",
            "subcategory":"Computer Services",
            "type":"Services"
        }
    ],
    "sg:phone":"+61 400 147 106",
    "sg:postcode":"3094",
    "sg:province":"VIC",
    "sg:tags":[
        "repairs",
        "upgrade",
        "equipment"
    ],
    "wof:name":"Steve Murphy Computer Support Services",
    "wof:placetype":"venue"
},
  "geometry": {"coordinates":[145.11882019000001,-37.7222366333],"type":"Point"}
}