{
  "type": "Feature",
  "properties": {
    "addr:full":"14 Finchley St Milton QLD 4064",
    "addr:housenumber":"14",
    "addr:postcode":"4064",
    "addr:street":"Finchley St",
    "iso:country":"AU",
    "sg:address":"14 Finchley St",
    "sg:city":"Milton",
    "sg:classifiers":[
        {
            "category":"Building & Trades",
            "subcategory":"Equipment Rental",
            "type":"Services"
        }
    ],
    "sg:phone":"+61 1800 064 431",
    "sg:postcode":"4064",
    "sg:province":"QLD",
    "sg:tags":[
        "supply",
        "catering"
    ],
    "wof:name":"Silver Chef Ltd",
    "wof:placetype":"venue"
},
  "geometry": {"coordinates":[153.005737305,-27.4654216766],"type":"Point"}
}