{
  "type": "Feature",
  "properties": {
    "addr:full":"31 - 33 Keppler Cct Seaford VIC 3198",
    "addr:housenumber":"33",
    "addr:postcode":"3198",
    "addr:street":"Keppler Cct",
    "iso:country":"AU",
    "sg:address":"31 - 33 Keppler Cct",
    "sg:city":"Seaford",
    "sg:classifiers":[
        {
            "category":"Building & Trades",
            "subcategory":"Construction",
            "type":"Services"
        }
    ],
    "sg:phone":"+61 428 567 008",
    "sg:postcode":"3198",
    "sg:province":"VIC",
    "sg:tags":[
        "earth",
        "excavating",
        "moving",
        "contractor"
    ],
    "wof:name":"Pearcedale Plant Hire Pty Ltd",
    "wof:placetype":"venue"
},
  "geometry": {"coordinates":[145.151657105,-38.0966110229],"type":"Point"}
}