{
  "type": "Feature",
  "properties": {
    "iso:country":"AU",
    "sg:address":"187 James St",
    "sg:city":"New Farm",
    "sg:classifiers":[
        {
            "category":"Health Services",
            "subcategory":"Chiropractor",
            "type":"Services"
        }
    ],
    "sg:phone":"+61 7 3358 2982",
    "sg:postcode":"4005",
    "sg:province":"QLD",
    "wof:name":"Chiropractic on James",
    "wof:placetype":"venue"
},
  "geometry": {"coordinates":[153.047164917,-27.4625854492],"type":"Point"}
}