{
  "type": "Feature",
  "properties": {
    "addr:full":"46 Roseberry St Hawthorn East VIC 3123",
    "addr:housenumber":"46",
    "addr:postcode":"3123",
    "addr:street":"Roseberry St",
    "iso:country":"AU",
    "sg:address":"46 Roseberry St",
    "sg:city":"Hawthorn East",
    "sg:classifiers":[
        {
            "category":"Building & Trades",
            "subcategory":"Construction",
            "type":"Services"
        }
    ],
    "sg:phone":"+61 3 9813 2390",
    "sg:postcode":"3123",
    "sg:province":"VIC",
    "sg:tags":[
        "roof"
    ],
    "wof:name":"Rhino Clad Pty Ltd",
    "wof:placetype":"venue"
},
  "geometry": {"coordinates":[145.048583984,-37.8267440796],"type":"Point"}
}