{
  "type": "Feature",
  "properties": {
    "addr:full":"45 Hickman St Winnellie NT 0820",
    "addr:housenumber":"45",
    "addr:postcode":"nt 0820",
    "addr:street":"Hickman St",
    "iso:country":"AU",
    "sg:address":"45 Hickman St",
    "sg:city":"Winnellie",
    "sg:classifiers":[
        {
            "category":"Professional",
            "subcategory":"Art Services",
            "type":"Services"
        }
    ],
    "sg:phone":"+61 8 8984 3394",
    "sg:postcode":"0820",
    "sg:province":"NT",
    "sg:tags":[
        "interior",
        "decorator"
    ],
    "wof:name":"Bill Warren Painting Service",
    "wof:placetype":"venue"
},
  "geometry": {"coordinates":[130.870727539,-12.4291620255],"type":"Point"}
}