{
  "type": "Feature",
  "properties": {
    "addr:full":"426 Winter St Ballarat VIC 3350",
    "addr:housenumber":"426",
    "addr:postcode":"3350",
    "addr:street":"Winter St",
    "iso:country":"AU",
    "sg:address":"426 Winter St",
    "sg:city":"Ballarat",
    "sg:classifiers":[
        {
            "category":"Recreation",
            "subcategory":"Dog Park",
            "type":"Entertainment"
        }
    ],
    "sg:phone":"+61 3 5334 2114",
    "sg:postcode":"3350",
    "sg:province":"VIC",
    "sg:tags":[
        "jack"
    ],
    "wof:name":"J & B WADE - JACK SALES & SERVICE",
    "wof:placetype":"venue"
},
  "geometry": {"coordinates":[143.811768,-37.567932],"type":"Point"}
}