{
  "type": "Feature",
  "properties": {
    "addr:full":"U3/ 62 Collingwood St Osborne Park WA 6017",
    "addr:housenumber":"62",
    "addr:postcode":"6017",
    "addr:street":"U3 /;Collingwood St",
    "iso:country":"AU",
    "sg:address":"U3/ 62 Collingwood St",
    "sg:city":"Osborne Park",
    "sg:classifiers":[
        {
            "category":"Autos & Motor Vehicles",
            "subcategory":"Auto Supplies",
            "type":"Retail Goods"
        }
    ],
    "sg:phone":"+61 8 9445 8299",
    "sg:postcode":"6017",
    "sg:province":"WA",
    "sg:tags":[
        "part",
        "cycles",
        "accessory"
    ],
    "wof:name":"Motomax",
    "wof:placetype":"venue"
},
  "geometry": {"coordinates":[115.816993713,-31.9045906067],"type":"Point"}
}