{
  "type": "Feature",
  "properties": {
    "addr:full":"157 Nalleys Creek Rd Millers Forest NSW 2324",
    "addr:housenumber":"157",
    "addr:postcode":"2324",
    "addr:street":"Nalleys Creek Rd",
    "iso:country":"AU",
    "sg:address":"157 Nalleys Creek Rd",
    "sg:city":"Millers Forest",
    "sg:classifiers":[
        {
            "category":"Building & Trades",
            "subcategory":"Electrical",
            "type":"Services"
        }
    ],
    "sg:phone":"+61 2 4983 1800",
    "sg:postcode":"2324",
    "sg:province":"NSW",
    "sg:tags":[
        "repair",
        "generator",
        "electric",
        "motor"
    ],
    "wof:name":"ALN Controls Pty Ltd",
    "wof:placetype":"venue"
},
  "geometry": {"coordinates":[151.713912964,-32.7765045166],"type":"Point"}
}