{
  "type": "Feature",
  "properties": {
    "addr:full":"Box Hill Hospital, Nelson Rd Box Hill VIC 3128",
    "addr:postcode":"3128",
    "addr:street":"Nelson Rd",
    "iso:country":"AU",
    "sg:address":"Box Hill Hospital, Nelson Rd",
    "sg:city":"Box Hill",
    "sg:classifiers":[
        {
            "category":"Health Services",
            "subcategory":"Doctor",
            "type":"Services"
        }
    ],
    "sg:phone":"+61 3 9895 3359",
    "sg:postcode":"3128",
    "sg:province":"VIC",
    "sg:tags":[
        "medical",
        "practitioner"
    ],
    "wof:name":"Kovacs Gabor T",
    "wof:placetype":"venue"
},
  "geometry": {"coordinates":[145.119598389,-37.81590271],"type":"Point"}
}