{
  "type": "Feature",
  "properties": {
    "iso:country":"AU",
    "sg:address":"168 Goodna Rd",
    "sg:city":"Greenbank",
    "sg:classifiers":[
        {
            "category":"Utilities",
            "subcategory":"Electric",
            "type":"Services"
        }
    ],
    "sg:phone":"+61 7 3297 5294",
    "sg:postcode":"4124",
    "sg:province":"QLD",
    "sg:tags":[
        "electrical",
        "contractor"
    ],
    "wof:name":"J F & L M Rose",
    "wof:placetype":"venue"
},
  "geometry": {"coordinates":[152.971969605,-27.7052898407],"type":"Point"}
}