{
  "type": "Feature",
  "properties": {
    "iso:country":"AU",
    "sg:address":"Old Pacific Hwy",
    "sg:city":"Brunswick Heads",
    "sg:classifiers":[
        {
            "category":"Fast Food",
            "type":"Food & Drink"
        }
    ],
    "sg:phone":"+61 2 6685 1755",
    "sg:postcode":"2483",
    "sg:province":"NSW",
    "sg:tags":[
        "away",
        "take"
    ],
    "wof:name":"Pizza Shop The",
    "wof:placetype":"venue"
},
  "geometry": {"coordinates":[153.54791259800001,-28.536737442],"type":"Point"}
}