{
  "type": "Feature",
  "properties": {
    "addr:full":"1 Argent Pl Ringwood VIC 3134",
    "addr:housenumber":"1",
    "addr:postcode":"3134",
    "addr:street":"Argent Pl",
    "iso:country":"AU",
    "sg:address":"1 Argent Pl",
    "sg:city":"Ringwood",
    "sg:classifiers":[
        {
            "category":"Professional",
            "subcategory":"Printing & Photocopies",
            "type":"Services"
        }
    ],
    "sg:phone":"+61 3 9873 5144",
    "sg:postcode":"3134",
    "sg:province":"VIC",
    "sg:tags":[
        "publishing",
        "desktop"
    ],
    "wof:name":"FSG-Creative Design & Print",
    "wof:placetype":"venue"
},
  "geometry": {"coordinates":[145.21351623499999,-37.8276176453],"type":"Point"}
}