{
  "type": "Feature",
  "properties": {
    "iso:country":"AU",
    "sg:address":"Shop 1, 53 James St",
    "sg:city":"Burleigh Heads",
    "sg:classifiers":[
        {
            "category":"Travel",
            "subcategory":"Travel Agent",
            "type":"Entertainment"
        }
    ],
    "sg:phone":"+61 7 5535 8355",
    "sg:postcode":"4220",
    "sg:province":"QLD",
    "sg:tags":[
        "consultant"
    ],
    "wof:name":"Cruise Escapes",
    "wof:placetype":"venue"
},
  "geometry": {"coordinates":[153.449874878,-28.0890426636],"type":"Point"}
}