{
  "type": "Feature",
  "properties": {
    "addr:full":"50 Hortense St Glen Iris VIC 3146",
    "addr:housenumber":"50",
    "addr:postcode":"3146",
    "addr:street":"Hortense St",
    "iso:country":"AU",
    "sg:address":"50 Hortense St",
    "sg:city":"Glen Iris",
    "sg:classifiers":[
        {
            "category":"Health Services",
            "subcategory":"Health Practitioner",
            "type":"Services"
        }
    ],
    "sg:phone":"+61 3 9889 2773",
    "sg:postcode":"3146",
    "sg:province":"VIC",
    "sg:tags":[
        "technique",
        "alexander"
    ],
    "wof:name":"Alexander Technique Australian Society Of Teachers Of The (Austat)",
    "wof:placetype":"venue"
},
  "geometry": {"coordinates":[145.08012390100001,-37.8570861816],"type":"Point"}
}