{
  "type": "Feature",
  "properties": {
    "addr:full":"12B/ 29 Queens Rd Melbourne VIC 3000",
    "addr:housenumber":"12b / 29",
    "addr:postcode":"3000",
    "addr:street":"Queens Rd",
    "iso:country":"AU",
    "sg:address":"12B/ 29 Queens Rd",
    "sg:city":"Melbourne",
    "sg:classifiers":[
        {
            "category":"Professional",
            "subcategory":"Business Services",
            "type":"Services"
        }
    ],
    "sg:phone":"+61 3 9866 2818",
    "sg:postcode":"3000",
    "sg:province":"VIC",
    "sg:tags":[
        "small",
        "advisory"
    ],
    "wof:name":"Robert E. Ramsay FCA",
    "wof:placetype":"venue"
},
  "geometry": {"coordinates":[144.97578430199999,-37.8428268433],"type":"Point"}
}