{
  "type": "Feature",
  "properties": {
    "addr:full":"344 Bay Rd Cheltenham VIC 3192",
    "addr:housenumber":"344",
    "addr:postcode":"3192",
    "addr:street":"Bay Rd",
    "iso:country":"AU",
    "sg:address":"344 Bay Rd",
    "sg:city":"Cheltenham",
    "sg:classifiers":[
        {
            "category":"Professional",
            "subcategory":"Engineering",
            "type":"Services"
        }
    ],
    "sg:phone":"+61 3 9583 9061",
    "sg:postcode":"3192",
    "sg:province":"VIC",
    "sg:tags":[
        "engineer",
        "structural"
    ],
    "wof:name":"J S C Consulting Engineers Pty Ltd",
    "wof:placetype":"venue"
},
  "geometry": {"coordinates":[145.04371643100001,-37.9565505981],"type":"Point"}
}