{
  "type": "Feature",
  "properties": {
    "addr:full":"333 Illawarra Rd Marrickville NSW 2204",
    "addr:housenumber":"333",
    "addr:postcode":"2204",
    "addr:street":"Illawarra Rd",
    "iso:country":"AU",
    "sg:address":"333 Illawarra Rd",
    "sg:city":"Marrickville",
    "sg:classifiers":[
        {
            "category":"Health Services",
            "subcategory":"Doctor",
            "type":"Services"
        }
    ],
    "sg:phone":"+61 2 9558 4112",
    "sg:postcode":"2204",
    "sg:province":"NSW",
    "sg:tags":[
        "medical",
        "practitioner"
    ],
    "wof:name":"Mai Van Sinh",
    "wof:placetype":"venue"
},
  "geometry": {"coordinates":[151.154617,-33.91243],"type":"Point"}
}