{
  "type": "Feature",
  "properties": {
    "iso:country":"AU",
    "sg:address":"4 Frazer St",
    "sg:city":"Lakemba",
    "sg:classifiers":[
        {
            "category":"Manufacturing",
            "subcategory":"Motor Vehicles & Parts",
            "type":"Manufacturing & Wholesale Goods"
        }
    ],
    "sg:phone":"+61 2 9758 1966",
    "sg:postcode":"2195",
    "sg:province":"NSW",
    "sg:tags":[
        "replacement"
    ],
    "wof:name":"Fabre Australia",
    "wof:placetype":"venue"
},
  "geometry": {"coordinates":[151.076019,-33.911289],"type":"Point"}
}