{
  "type": "Feature",
  "properties": {
    "addr:full":"Shp3/ 456 Cooper Rd Yagoona NSW 2199",
    "addr:housenumber":"456",
    "addr:postcode":"2199",
    "addr:street":"Cooper Rd",
    "iso:country":"AU",
    "sg:address":"Shp3/ 456 Cooper Rd",
    "sg:city":"Yagoona",
    "sg:classifiers":[
        {
            "category":"Personal",
            "subcategory":"Beauty Salon",
            "type":"Services"
        }
    ],
    "sg:phone":"+61 2 9709 5239",
    "sg:postcode":"2199",
    "sg:province":"NSW",
    "sg:tags":[
        "hairdresser"
    ],
    "wof:name":"Ultimate In Hair Design",
    "wof:placetype":"venue"
},
  "geometry": {"coordinates":[151.02586400000001,-33.907249],"type":"Point"}
}