{
  "type": "Feature",
  "properties": {
    "iso:country":"AU",
    "sg:address":"12 Harris St",
    "sg:city":"Middlemount",
    "sg:classifiers":[
        {
            "category":"Social Services",
            "subcategory":"Child Care",
            "type":"Services"
        }
    ],
    "sg:phone":"+61 7 4985 9549",
    "sg:postcode":"4746",
    "sg:province":"QLD",
    "sg:tags":[
        "shearer"
    ],
    "wof:name":"Eickhoff Australia",
    "wof:placetype":"venue"
},
  "geometry": {"coordinates":[148.708893,-22.815916],"type":"Point"}
}