{
  "type": "Feature",
  "properties": {
    "iso:country":"AU",
    "sg:address":"593 Englehardt St",
    "sg:city":"Albury",
    "sg:classifiers":[
        {
            "category":"Health Services",
            "subcategory":"Dentist",
            "type":"Services"
        }
    ],
    "sg:phone":"+61 2 6021 4192",
    "sg:postcode":"2640",
    "sg:province":"NSW",
    "wof:name":"Poyner J E",
    "wof:placetype":"venue"
},
  "geometry": {"coordinates":[146.91281127900001,-36.0780296326],"type":"Point"}
}