{
  "type": "Feature",
  "properties": {
    "addr:full":"33 Melville St Numurkah VIC 3636",
    "addr:housenumber":"33",
    "addr:postcode":"3636",
    "addr:street":"Melville St",
    "iso:country":"AU",
    "sg:address":"33 Melville St",
    "sg:city":"Numurkah",
    "sg:classifiers":[
        {
            "category":"Shopping",
            "subcategory":"Optical Goods",
            "type":"Retail Goods"
        }
    ],
    "sg:phone":"+61 3 5862 3066",
    "sg:postcode":"3636",
    "sg:province":"VIC",
    "sg:tags":[
        "dispenser",
        "prescription"
    ],
    "wof:name":"Shepparton Optical Services Pty Ltd",
    "wof:placetype":"venue"
},
  "geometry": {"coordinates":[145.44256591800001,-36.0895881653],"type":"Point"}
}