{
  "type": "Feature",
  "properties": {
    "addr:full":"Cnr Pitt St & Angel Pl Sydney NSW 2000",
    "addr:postcode":"2000",
    "addr:street":"Cnr Pitt St & Angel Pl",
    "iso:country":"AU",
    "sg:address":"Cnr Pitt St & Angel Pl",
    "sg:city":"Sydney",
    "sg:classifiers":[
        {
            "category":"Health Services",
            "subcategory":"Chiropractor",
            "type":"Services"
        }
    ],
    "sg:phone":"+61 2 9264 7959",
    "sg:postcode":"2000",
    "sg:province":"NSW",
    "wof:name":"Limboro Hance",
    "wof:placetype":"venue"
},
  "geometry": {"coordinates":[151.20826721200001,-33.8694496155],"type":"Point"}
}