{
  "type": "Feature",
  "properties": {
    "addr:full":"Kiewa Valley Hwy Mt Beauty VIC 3699",
    "addr:postcode":"3699",
    "addr:street":"Valley Hwy",
    "iso:country":"AU",
    "sg:address":"Kiewa Valley Hwy",
    "sg:city":"Mt Beauty",
    "sg:classifiers":[
        {
            "category":"Building & Trades",
            "subcategory":"Landscaping Services",
            "type":"Services"
        }
    ],
    "sg:phone":"+61 3 5754 4572",
    "sg:postcode":"3699",
    "sg:province":"VIC",
    "sg:tags":[
        "gardener"
    ],
    "wof:name":"Ghirardello Mark",
    "wof:placetype":"venue"
},
  "geometry": {"coordinates":[147.16761779800001,-36.7428894043],"type":"Point"}
}