{
  "type": "Feature",
  "properties": {
    "addr:full":"5 Angle Vale Rd Angle Vale SA 5117",
    "addr:housenumber":"5",
    "addr:postcode":"5117",
    "addr:street":"Angle Vale Rd",
    "iso:country":"AU",
    "sg:address":"5 Angle Vale Rd",
    "sg:city":"Angle Vale",
    "sg:classifiers":[
        {
            "category":"Education",
            "subcategory":"Kindergarten",
            "type":"Public Place"
        }
    ],
    "sg:phone":"+61 8 8284 7573",
    "sg:postcode":"5117",
    "sg:province":"SA",
    "sg:tags":[
        "pre-schools"
    ],
    "wof:name":"Angle Vale KindyCare",
    "wof:placetype":"venue"
},
  "geometry": {"coordinates":[138.64645385700001,-34.6409645081],"type":"Point"}
}