{
  "type": "Feature",
  "properties": {
    "addr:full":"439 Yan Yean Rd Yarrambat VIC 3091",
    "addr:housenumber":"439",
    "addr:postcode":"3091",
    "addr:street":"Yan Yean Rd",
    "iso:country":"AU",
    "sg:address":"439 Yan Yean Rd",
    "sg:city":"Yarrambat",
    "sg:classifiers":[
        {
            "category":"Building & Trades",
            "subcategory":"Construction",
            "type":"Services"
        }
    ],
    "sg:phone":"+61 418 359 106",
    "sg:postcode":"3091",
    "sg:province":"VIC",
    "sg:tags":[
        "joiner",
        "carpenter"
    ],
    "wof:name":"R & A Carpentry",
    "wof:placetype":"venue"
},
  "geometry": {"coordinates":[145.125244141,-37.6487693787],"type":"Point"}
}