{
  "type": "Feature",
  "properties": {
    "addr:full":"Francis St Marble Bar WA 6760",
    "addr:postcode":"6760",
    "addr:street":"Francis St",
    "iso:country":"AU",
    "sg:address":"Francis St",
    "sg:city":"Marble Bar",
    "sg:classifiers":[
        {
            "category":"Autos & Motor Vehicles",
            "subcategory":"Fuel & Gas Station",
            "type":"Retail Goods"
        }
    ],
    "sg:phone":"+61 8 9176 1041",
    "sg:postcode":"6760",
    "sg:province":"WA",
    "wof:name":"BP Australia Limited",
    "wof:placetype":"venue"
},
  "geometry": {"coordinates":[119.74756600000001,-21.173651],"type":"Point"}
}