{
  "type": "Feature",
  "properties": {
    "addr:full":"Lot 42, Delmarco Drive, Picton Bunbury WA 6230",
    "addr:postcode":"6230",
    "addr:street":"Delmarco Drive",
    "iso:country":"AU",
    "sg:address":"Lot 42, Delmarco Drive, Picton",
    "sg:city":"Bunbury",
    "sg:classifiers":[
        {
            "category":"Retail",
            "subcategory":"Storage",
            "type":"Services"
        }
    ],
    "sg:phone":"+61 8 9726 0010",
    "sg:postcode":"6230",
    "sg:province":"WA",
    "wof:name":"Affordable Removals & Picton Storage",
    "wof:placetype":"venue"
},
  "geometry": {"coordinates":[115.65454099999999,-33.338879],"type":"Point"}
}