{
  "type": "Feature",
  "properties": {
    "iso:country":"AU",
    "sg:address":"22 Mary Ann St",
    "sg:city":"Ultimo",
    "sg:classifiers":[
        {
            "category":"Fast Food",
            "type":"Food & Drink"
        }
    ],
    "sg:phone":"+61 2 9212 7350",
    "sg:postcode":"2007",
    "sg:province":"NSW",
    "sg:tags":[
        "away",
        "take"
    ],
    "wof:name":"Mary Ann Gourmet Foods",
    "wof:placetype":"venue"
},
  "geometry": {"coordinates":[151.19917297399999,-33.8814277649],"type":"Point"}
}