{
  "type": "Feature",
  "properties": {
    "addr:full":"38 High St Texas QLD 4385",
    "addr:housenumber":"38",
    "addr:postcode":"qld 4385",
    "addr:street":"High St",
    "iso:country":"AU",
    "sg:address":"38 High St",
    "sg:city":"Texas",
    "sg:classifiers":[
        {
            "category":"Shopping",
            "type":"Retail Goods"
        }
    ],
    "sg:phone":"+61 7 4653 1488",
    "sg:postcode":"4385",
    "sg:province":"QLD",
    "sg:tags":[
        "agent",
        "stock"
    ],
    "wof:name":"Border Merchandise",
    "wof:placetype":"venue"
},
  "geometry": {"coordinates":[151.17158499999999,-28.855373],"type":"Point"}
}