{
  "type": "Feature",
  "properties": {
    "addr:full":"Cnr Cooyong & Mort Sts Braddon ACT 2612",
    "addr:postcode":"2612",
    "addr:street":"Cnr Cooyong & Mort Sts",
    "iso:country":"AU",
    "sg:address":"Cnr Cooyong & Mort Sts",
    "sg:city":"Braddon",
    "sg:classifiers":[
        {
            "category":"Fast Food",
            "type":"Food & Drink"
        }
    ],
    "sg:phone":"+61 2 6247 9533",
    "sg:postcode":"2612",
    "sg:province":"ACT",
    "sg:tags":[
        "away",
        "take"
    ],
    "wof:name":"McDonald's Family Restaurants",
    "wof:placetype":"venue"
},
  "geometry": {"coordinates":[149.13380432100001,-35.2763175964],"type":"Point"}
}