{
  "type": "Feature",
  "properties": {
    "addr:full":"3/ 13 Fuller Rd Ripponlea VIC 3185",
    "addr:housenumber":"/ 13",
    "addr:postcode":"3185",
    "addr:street":"Fuller Rd",
    "iso:country":"AU",
    "sg:address":"3/ 13 Fuller Rd",
    "sg:city":"Ripponlea",
    "sg:classifiers":[
        {
            "category":"Personal",
            "type":"Services"
        }
    ],
    "sg:phone":"+61 425 812 398",
    "sg:postcode":"3185",
    "sg:province":"VIC",
    "sg:tags":[
        "gift"
    ],
    "sg:website":"http://www.finepoint.com.au",
    "wof:name":"Finepoint Embroidery",
    "wof:placetype":"venue"
},
  "geometry": {"coordinates":[144.99531555199999,-37.8776245117],"type":"Point"}
}