{
  "type": "Feature",
  "properties": {
    "addr:full":"3 Jardine St Kingston ACT 2604",
    "addr:housenumber":"3",
    "addr:postcode":"2604",
    "addr:street":"Jardine St",
    "iso:country":"AU",
    "sg:address":"3 Jardine St",
    "sg:city":"Kingston",
    "sg:classifiers":[
        {
            "category":"Fast Food",
            "type":"Food & Drink"
        }
    ],
    "sg:phone":"+61 2 6295 9182",
    "sg:postcode":"2604",
    "sg:province":"ACT",
    "sg:tags":[
        "away",
        "take"
    ],
    "wof:name":"Highgate Snack Bar",
    "wof:placetype":"venue"
},
  "geometry": {"coordinates":[149.140335083,-35.3134117126],"type":"Point"}
}