{
  "type": "Feature",
  "properties": {
    "addr:full":"374 Punt Rd South Yarra VIC 3141",
    "addr:housenumber":"374",
    "addr:postcode":"3141",
    "addr:street":"Punt Rd",
    "iso:country":"AU",
    "sg:address":"374 Punt Rd",
    "sg:city":"South Yarra",
    "sg:classifiers":[
        {
            "category":"Health Services",
            "subcategory":"Doctor",
            "type":"Services"
        }
    ],
    "sg:phone":"+61 3 9867 1413",
    "sg:postcode":"3141",
    "sg:province":"VIC",
    "sg:tags":[
        "medical",
        "practitioner"
    ],
    "wof:name":"Miach A L Dr",
    "wof:placetype":"venue"
},
  "geometry": {"coordinates":[144.98626709000001,-37.8403892517],"type":"Point"}
}