{
  "type": "Feature",
  "properties": {
    "addr:full":"10 View St Upwey VIC 3158",
    "addr:housenumber":"10",
    "addr:postcode":"3158",
    "addr:street":"View St",
    "iso:country":"AU",
    "sg:address":"10 View St",
    "sg:city":"Upwey",
    "sg:classifiers":[
        {
            "category":"Health Services",
            "subcategory":"Health Practitioner",
            "type":"Services"
        }
    ],
    "sg:phone":"+61 3 9754 3089",
    "sg:postcode":"3158",
    "sg:province":"VIC",
    "sg:tags":[
        "naturopath"
    ],
    "wof:name":"David Russell",
    "wof:placetype":"venue"
},
  "geometry": {"coordinates":[145.330810547,-37.9059066772],"type":"Point"}
}