{
  "type": "Feature",
  "properties": {
    "iso:country":"AU",
    "sg:address":"184 Gilles St",
    "sg:city":"Adelaide",
    "sg:classifiers":[
        {
            "category":"Professional",
            "subcategory":"Management & Consulting",
            "type":"Services"
        }
    ],
    "sg:phone":"+61 8 8223 1337",
    "sg:postcode":"5000",
    "sg:province":"SA",
    "sg:tags":[
        "consultant",
        "business"
    ],
    "wof:name":"Versace Business Services Pty Ltd",
    "wof:placetype":"venue"
},
  "geometry": {"coordinates":[138.607345581,-34.9338226318],"type":"Point"}
}