{
  "type": "Feature",
  "properties": {
    "addr:full":"898 Stuart Hwy Pinelands NT 0829",
    "addr:housenumber":"898",
    "addr:postcode":"nt 0829",
    "addr:street":"Stuart Hwy",
    "iso:country":"AU",
    "sg:address":"898 Stuart Hwy",
    "sg:city":"Pinelands",
    "sg:classifiers":[
        {
            "category":"Education",
            "subcategory":"Special Training",
            "type":"Public Place"
        }
    ],
    "sg:phone":"+61 417 851 430",
    "sg:postcode":"0829",
    "sg:province":"NT",
    "sg:tags":[
        "development"
    ],
    "wof:name":"Territory On-Site Training",
    "wof:placetype":"venue"
},
  "geometry": {"coordinates":[130.96864318900001,-12.4579563141],"type":"Point"}
}