{
  "type": "Feature",
  "properties": {
    "addr:full":"151 River St Maclean NSW 2463",
    "addr:housenumber":"151",
    "addr:postcode":"2463",
    "addr:street":"River St",
    "iso:country":"AU",
    "sg:address":"151 River St",
    "sg:city":"Maclean",
    "sg:classifiers":[
        {
            "category":"Shopping",
            "subcategory":"Antiques",
            "type":"Retail Goods"
        }
    ],
    "sg:phone":"+61 2 6645 2317",
    "sg:postcode":"2463",
    "sg:province":"NSW",
    "wof:name":"Penny Farthing Old Wares & Collectables",
    "wof:placetype":"venue"
},
  "geometry": {"coordinates":[153.19847106899999,-29.4525260925],"type":"Point"}
}