{
  "type": "Feature",
  "properties": {
    "addr:full":"192- 194 New Canterbury Rd Petersham NSW 2049",
    "addr:housenumber":"194",
    "addr:postcode":"2049",
    "addr:street":"New Canterbury Rd",
    "iso:country":"AU",
    "sg:address":"192- 194 New Canterbury Rd",
    "sg:city":"Petersham",
    "sg:classifiers":[
        {
            "category":"Building & Trades",
            "subcategory":"Construction",
            "type":"Services"
        }
    ],
    "sg:phone":"+61 2 9560 4100",
    "sg:postcode":"2049",
    "sg:province":"NSW",
    "sg:tags":[
        "window",
        "timber"
    ],
    "wof:name":"Broadview",
    "wof:placetype":"venue"
},
  "geometry": {"coordinates":[151.149719,-33.897079],"type":"Point"}
}