{
  "type": "Feature",
  "properties": {
    "addr:full":"41 Hunter St Parramatta NSW 2150",
    "addr:housenumber":"41",
    "addr:postcode":"2150",
    "addr:street":"Hunter St",
    "iso:country":"AU",
    "sg:address":"41 Hunter St",
    "sg:city":"Parramatta",
    "sg:classifiers":[
        {
            "category":"Banks & Credit Unions",
            "subcategory":"Investment Brokerage",
            "type":"Services"
        }
    ],
    "sg:phone":"+61 2 9633 4797",
    "sg:postcode":"2150",
    "sg:province":"NSW",
    "sg:tags":[
        "finance",
        "broker"
    ],
    "wof:name":"Centrepoint Alliance Limited",
    "wof:placetype":"venue"
},
  "geometry": {"coordinates":[150.94900512699999,-33.8710327148],"type":"Point"}
}