{
  "type": "Feature",
  "properties": {
    "iso:country":"AU",
    "sg:address":"154 Goodwood Rd",
    "sg:city":"Goodwood",
    "sg:classifiers":[
        {
            "category":"Personal",
            "subcategory":"Hair Removal",
            "type":"Services"
        }
    ],
    "sg:phone":"+61 8 8271 9869",
    "sg:postcode":"5034",
    "sg:province":"SA",
    "wof:name":"Kings & Queens",
    "wof:placetype":"venue"
},
  "geometry": {"coordinates":[138.589569092,-34.952507019],"type":"Point"}
}