{
  "type": "Feature",
  "properties": {
    "iso:country":"AU",
    "sg:address":"1084 High St",
    "sg:city":"Armadale",
    "sg:classifiers":[
        {
            "category":"Cafe",
            "type":"Food & Drink"
        }
    ],
    "sg:phone":"+61 3 9509 5601",
    "sg:postcode":"3143",
    "sg:province":"VIC",
    "wof:name":"La Macino Cafe",
    "wof:placetype":"venue"
},
  "geometry": {"coordinates":[145.02349853499999,-37.85597229],"type":"Point"}
}