{
  "type": "Feature",
  "properties": {
    "addr:full":"PO Box 1013G Greythorn VIC 3104",
    "addr:postcode":"3104",
    "iso:country":"AU",
    "sg:address":"PO Box 1013G",
    "sg:city":"Greythorn",
    "sg:classifiers":[
        {
            "category":"Education",
            "subcategory":"Music School",
            "type":"Public Place"
        }
    ],
    "sg:phone":"+61 3 9858 2598",
    "sg:postcode":"3104",
    "sg:province":"VIC",
    "sg:tags":[
        "choir",
        "bands",
        "orchestra"
    ],
    "wof:name":"The Fitzgerald Brothers",
    "wof:placetype":"venue"
},
  "geometry": {"coordinates":[145.091262817,-37.792388916],"type":"Point"}
}