{
  "type": "Feature",
  "properties": {
    "addr:full":"Lvl 1/ 302 Chapel Rd Bankstown NSW 2200",
    "addr:housenumber":"/ 302",
    "addr:postcode":"2200",
    "addr:street":"Chapel Rd",
    "iso:country":"AU",
    "sg:address":"Lvl 1/ 302 Chapel Rd",
    "sg:city":"Bankstown",
    "sg:classifiers":[
        {
            "category":"Health Services",
            "subcategory":"Doctor",
            "type":"Services"
        }
    ],
    "sg:phone":"+61 2 9796 8679",
    "sg:postcode":"2200",
    "sg:province":"NSW",
    "sg:tags":[
        "medical",
        "practitioner"
    ],
    "wof:name":"Lam Andrew",
    "wof:placetype":"venue"
},
  "geometry": {"coordinates":[151.031586,-33.919312],"type":"Point"}
}