{
  "type": "Feature",
  "properties": {
    "addr:full":"47 McLachlan St Fortitude Valley QLD 4006",
    "addr:housenumber":"47",
    "addr:postcode":"4006",
    "addr:street":"Mclachlan St",
    "iso:country":"AU",
    "sg:address":"47 McLachlan St",
    "sg:city":"Fortitude Valley",
    "sg:classifiers":[
        {
            "category":"Retail",
            "subcategory":"Auto Repair",
            "type":"Services"
        }
    ],
    "sg:phone":"+61 7 3252 9339",
    "sg:postcode":"4006",
    "sg:province":"QLD",
    "sg:tags":[
        "repairer",
        "motor",
        "engineer"
    ],
    "wof:name":"Auto Safe-T-Check Pty Ltd",
    "wof:placetype":"venue"
},
  "geometry": {"coordinates":[153.03663635300001,-27.45835495],"type":"Point"}
}