{
  "type": "Feature",
  "properties": {
    "iso:country":"AU",
    "sg:address":"41 Riley St",
    "sg:city":"Woolloomooloo",
    "sg:classifiers":[
        {
            "category":"Professional",
            "subcategory":"Computer Services",
            "type":"Services"
        }
    ],
    "sg:phone":"+61 2 9380 7111",
    "sg:postcode":"2011",
    "sg:province":"NSW",
    "sg:tags":[
        "consultant",
        "system"
    ],
    "wof:name":"TrakHealth Pty Ltd",
    "wof:placetype":"venue"
},
  "geometry": {"coordinates":[151.21542358400001,-33.873260498],"type":"Point"}
}