{
  "type": "Feature",
  "properties": {
    "addr:full":"Shop 3, 8 Hume Hwy Warwick Farm NSW 2170",
    "addr:housenumber":"shop;8",
    "addr:postcode":"2170",
    "addr:street":"Hume Hwy",
    "iso:country":"AU",
    "sg:address":"Shop 3, 8 Hume Hwy",
    "sg:city":"Warwick Farm",
    "sg:classifiers":[
        {
            "category":"Food & Beverages",
            "subcategory":"Bakery",
            "type":"Retail Goods"
        }
    ],
    "sg:phone":"+61 2 9824 2038",
    "sg:postcode":"2170",
    "sg:province":"NSW",
    "sg:tags":[
        "baker"
    ],
    "wof:name":"L & Q Hotbread",
    "wof:placetype":"venue"
},
  "geometry": {"coordinates":[150.930786133,-33.9141921997],"type":"Point"}
}