{
  "type": "Feature",
  "properties": {
    "addr:full":"132 Burgundy St Heidelberg VIC 3084",
    "addr:housenumber":"132",
    "addr:postcode":"3084",
    "addr:street":"Burgundy St",
    "iso:country":"AU",
    "sg:address":"132 Burgundy St",
    "sg:city":"Heidelberg",
    "sg:classifiers":[
        {
            "category":"Health Services",
            "subcategory":"Dentist",
            "type":"Services"
        }
    ],
    "sg:phone":"+61 3 9459 4297",
    "sg:postcode":"3084",
    "sg:province":"VIC",
    "wof:name":"Papli Rain",
    "wof:placetype":"venue"
},
  "geometry": {"coordinates":[145.065750122,-37.7559890747],"type":"Point"}
}