{
  "type": "Feature",
  "properties": {
    "addr:full":"unit 10 3 Roma Rd Valentine NSW 2280",
    "addr:housenumber":"3",
    "addr:postcode":"2280",
    "addr:street":"Roma Rd",
    "iso:country":"AU",
    "sg:address":"unit 10 3 Roma Rd",
    "sg:city":"Valentine",
    "sg:classifiers":[
        {
            "category":"Professional",
            "subcategory":"Art Services",
            "type":"Services"
        }
    ],
    "sg:phone":"+61 408 673 775",
    "sg:postcode":"2280",
    "sg:province":"NSW",
    "sg:tags":[
        "decorator",
        "painter"
    ],
    "wof:name":"Chris Mulligan",
    "wof:placetype":"venue"
},
  "geometry": {"coordinates":[151.635375977,-33.014465332],"type":"Point"}
}