{
  "type": "Feature",
  "properties": {
    "addr:full":"62 Queen St Campbelltown NSW 2560",
    "addr:housenumber":"62",
    "addr:postcode":"2560",
    "addr:street":"Queen St",
    "iso:country":"AU",
    "sg:address":"62 Queen St",
    "sg:city":"Campbelltown",
    "sg:classifiers":[
        {
            "category":"Retail",
            "subcategory":"Auto Repair",
            "type":"Services"
        }
    ],
    "sg:phone":"+61 2 4627 2055",
    "sg:postcode":"2560",
    "sg:province":"NSW",
    "sg:tags":[
        "wheel",
        "balancing",
        "alignment"
    ],
    "wof:name":"Bridgestone Tyre Centres",
    "wof:placetype":"venue"
},
  "geometry": {"coordinates":[150.81922912600001,-34.0614204407],"type":"Point"}
}