{
  "type": "Feature",
  "properties": {
    "iso:country":"AU",
    "sg:address":"16 Australia 2 Ave",
    "sg:city":"North Haven",
    "sg:classifiers":[
        {
            "category":"Building & Trades",
            "subcategory":"Construction",
            "type":"Services"
        }
    ],
    "sg:phone":"+61 8 8248 5332",
    "sg:postcode":"5018",
    "sg:province":"SA",
    "sg:tags":[
        "contractor"
    ],
    "wof:name":"Gardiner P J & B A",
    "wof:placetype":"venue"
},
  "geometry": {"coordinates":[138.48611450199999,-34.7831878662],"type":"Point"}
}