{
  "type": "Feature",
  "properties": {
    "addr:full":"213 Botany Rd Waterloo NSW 2017",
    "addr:housenumber":"213",
    "addr:postcode":"2017",
    "addr:street":"Botany Rd",
    "iso:country":"AU",
    "sg:address":"213 Botany Rd",
    "sg:city":"Waterloo",
    "sg:classifiers":[
        {
            "category":"Cafe",
            "type":"Food & Drink"
        }
    ],
    "sg:phone":"+61 2 9699 4702",
    "sg:postcode":"2017",
    "sg:province":"NSW",
    "wof:name":"Verde Cafe",
    "wof:placetype":"venue"
},
  "geometry": {"coordinates":[151.202026367,-33.9028816223],"type":"Point"}
}