{
  "type": "Feature",
  "properties": {
    "iso:country":"AU",
    "sg:address":"103 Tapleys Hill Rd",
    "sg:city":"Glenelg North",
    "sg:classifiers":[
        {
            "category":"Wholesale",
            "subcategory":"Machinery & Supplies",
            "type":"Manufacturing & Wholesale Goods"
        }
    ],
    "sg:phone":"+61 8 8295 6622",
    "sg:postcode":"5045",
    "sg:province":"SA",
    "sg:tags":[
        "equipment",
        "hydraulic"
    ],
    "wof:name":"B J Inns Pty Ltd",
    "wof:placetype":"venue"
},
  "geometry": {"coordinates":[138.516556,-34.96619],"type":"Point"}
}