{
  "type": "Feature",
  "properties": {
    "iso:country":"AU",
    "sg:address":"1/ 22 Rattray Rd",
    "sg:city":"Montmorency",
    "sg:classifiers":[
        {
            "category":"Social Services",
            "type":"Services"
        }
    ],
    "sg:phone":"+61 409 148 585",
    "sg:postcode":"3094",
    "sg:province":"VIC",
    "sg:tags":[
        "domestic",
        "help"
    ],
    "wof:name":"My Right Hand",
    "wof:placetype":"venue"
},
  "geometry": {"coordinates":[145.116653442,-37.7188568115],"type":"Point"}
}