{
  "type": "Feature",
  "properties": {
    "iso:country":"AU",
    "sg:address":"9 Princeton Crt",
    "sg:city":"Buderim",
    "sg:classifiers":[
        {
            "category":"Professional",
            "subcategory":"Art Services",
            "type":"Services"
        }
    ],
    "sg:phone":"+61 414 626 211",
    "sg:postcode":"4556",
    "sg:province":"QLD",
    "sg:tags":[
        "interior",
        "decorator"
    ],
    "wof:name":"Margie Robertson Creative Decor",
    "wof:placetype":"venue"
},
  "geometry": {"coordinates":[153.055252075,-26.7181224823],"type":"Point"}
}