{
  "type": "Feature",
  "properties": {
    "iso:country":"AU",
    "sg:address":"33 Piper St",
    "sg:city":"Caboolture",
    "sg:classifiers":[
        {
            "category":"Home & Garden",
            "subcategory":"Building Materials",
            "type":"Retail Goods"
        }
    ],
    "sg:phone":"+61 7 5498 9516",
    "sg:postcode":"4510",
    "sg:province":"QLD",
    "sg:tags":[
        "fencing"
    ],
    "wof:name":"A. B. Steel Supplies",
    "wof:placetype":"venue"
},
  "geometry": {"coordinates":[152.984756,-27.083185],"type":"Point"}
}