{
  "type": "Feature",
  "properties": {
    "iso:country":"AU",
    "sg:address":"Shop 2/ 13 Milligan St",
    "sg:city":"Taree",
    "sg:classifiers":[
        {
            "category":"Personal",
            "subcategory":"Beauty Salon",
            "type":"Services"
        }
    ],
    "sg:phone":"+61 2 6552 1038",
    "sg:postcode":"2430",
    "sg:province":"NSW",
    "sg:tags":[
        "hairdresser"
    ],
    "wof:name":"Bravissimo Hair Studio",
    "wof:placetype":"venue"
},
  "geometry": {"coordinates":[152.472946,-31.90106],"type":"Point"}
}