{
  "type": "Feature",
  "properties": {
    "addr:full":"45-57 Antimony St (Cnr Emery St) Carole Park QLD 4300",
    "addr:housenumber":"45-57",
    "addr:postcode":"4300",
    "addr:street":"Antimony St Cnr Emery St",
    "iso:country":"AU",
    "sg:address":"45-57 Antimony St (Cnr Emery St)",
    "sg:city":"Carole Park",
    "sg:classifiers":[
        {
            "category":"Manufacturing",
            "subcategory":"Paper Products",
            "type":"Manufacturing & Wholesale Goods"
        }
    ],
    "sg:phone":"+61 7 3331 2100",
    "sg:postcode":"4300",
    "sg:province":"QLD",
    "sg:tags":[
        "wholesaler",
        "toilet",
        "mfrs"
    ],
    "wof:name":"Queensland Tissue Products Pty Ltd",
    "wof:placetype":"venue"
},
  "geometry": {"coordinates":[152.93658447300001,-27.6188774109],"type":"Point"}
}