{
  "type": "Feature",
  "properties": {
    "iso:country":"AU",
    "sg:address":"6 Stennett Rd",
    "sg:city":"Ingleburn",
    "sg:classifiers":[
        {
            "category":"Manufacturing",
            "subcategory":"Metals",
            "type":"Manufacturing & Wholesale Goods"
        }
    ],
    "sg:phone":"+61 2 9618 3203",
    "sg:postcode":"2565",
    "sg:province":"NSW",
    "sg:tags":[
        "steel",
        "fabricator",
        "mfrs"
    ],
    "wof:name":"J.A. Glenn Engineering Pty Ltd",
    "wof:placetype":"venue"
},
  "geometry": {"coordinates":[150.85504150400001,-34.0003700256],"type":"Point"}
}