{
  "type": "Feature",
  "properties": {
    "addr:full":"17 Chelsea Drv Canley Heights NSW 2166",
    "addr:housenumber":"17",
    "addr:postcode":"2166",
    "addr:street":"Chelsea Drv",
    "iso:country":"AU",
    "sg:address":"17 Chelsea Drv",
    "sg:city":"Canley Heights",
    "sg:classifiers":[
        {
            "category":"Utilities",
            "subcategory":"Telephone",
            "type":"Services"
        }
    ],
    "sg:phone":"+61 2 9729 1999",
    "sg:postcode":"2166",
    "sg:province":"NSW",
    "sg:tags":[
        "installation",
        "system",
        "maintenance"
    ],
    "wof:name":"Auscom Communications",
    "wof:placetype":"venue"
},
  "geometry": {"coordinates":[150.92404174800001,-33.8771247864],"type":"Point"}
}