{
  "type": "Feature",
  "properties": {
    "iso:country":"AU",
    "sg:address":"9 Melody Hill Crt",
    "sg:city":"Dandenong North",
    "sg:classifiers":[
        {
            "category":"Shopping",
            "type":"Retail Goods"
        }
    ],
    "sg:phone":"+61 3 9790 1871",
    "sg:postcode":"3175",
    "sg:province":"VIC",
    "sg:tags":[
        "produce",
        "grain"
    ],
    "wof:name":"Scollo J",
    "wof:placetype":"venue"
},
  "geometry": {"coordinates":[145.209716797,-37.9426841736],"type":"Point"}
}