{
  "type": "Feature",
  "properties": {
    "addr:full":"121 Oxford Street St Bondi Junction NSW 2022",
    "addr:housenumber":"121",
    "addr:postcode":"2022",
    "addr:street":"Oxford Street St",
    "iso:country":"AU",
    "sg:address":"121 Oxford Street St",
    "sg:city":"Bondi Junction",
    "sg:classifiers":[
        {
            "category":"Fast Food",
            "type":"Food & Drink"
        }
    ],
    "sg:phone":"+61 2 9387 3833",
    "sg:postcode":"2022",
    "sg:province":"NSW",
    "sg:tags":[
        "away",
        "take"
    ],
    "wof:name":"BJ Prestige Kebab",
    "wof:placetype":"venue"
},
  "geometry": {"coordinates":[151.247314453,-33.8918685913],"type":"Point"}
}