{
  "type": "Feature",
  "properties": {
    "iso:country":"AU",
    "sg:address":"5 Richmond Ave",
    "sg:city":"Fairbairn",
    "sg:classifiers":[
        {
            "category":"Building & Trades",
            "subcategory":"Construction",
            "type":"Services"
        }
    ],
    "sg:phone":"+61 2 6257 9999",
    "sg:postcode":"2609",
    "sg:province":"ACT",
    "sg:tags":[
        "sun",
        "product",
        "protection"
    ],
    "wof:name":"Cancer Council ACT The",
    "wof:placetype":"venue"
},
  "geometry": {"coordinates":[149.179443359,-35.298625946],"type":"Point"}
}