{
  "type": "Feature",
  "properties": {
    "iso:country":"AU",
    "sg:address":"238 Macquarie Rd",
    "sg:city":"Springwood",
    "sg:classifiers":[
        {
            "category":"Fast Food",
            "type":"Food & Drink"
        }
    ],
    "sg:phone":"+61 2 4751 5187",
    "sg:postcode":"2777",
    "sg:province":"NSW",
    "sg:tags":[
        "away",
        "take"
    ],
    "wof:name":"Springwood Pizza",
    "wof:placetype":"venue"
},
  "geometry": {"coordinates":[150.563919067,-33.6992950439],"type":"Point"}
}