{
  "type": "Feature",
  "properties": {
    "addr:full":"4 - 3 Acacia St Byron Bay NSW 2481",
    "addr:housenumber":"3",
    "addr:postcode":"2481",
    "addr:street":"Acacia St",
    "iso:country":"AU",
    "sg:address":"4 - 3 Acacia St",
    "sg:city":"Byron Bay",
    "sg:classifiers":[
        {
            "category":"Home & Garden",
            "subcategory":"Garden Supply",
            "type":"Retail Goods"
        }
    ],
    "sg:phone":"+61 2 6685 6366",
    "sg:postcode":"2481",
    "sg:province":"NSW",
    "sg:tags":[
        "equipment"
    ],
    "wof:name":"Byron Mowers",
    "wof:placetype":"venue"
},
  "geometry": {"coordinates":[153.584594727,-28.6346111298],"type":"Point"}
}