{
  "type": "Feature",
  "properties": {
    "iso:country":"AU",
    "sg:address":"125 Clarinda St",
    "sg:city":"Parkes",
    "sg:classifiers":[
        {
            "category":"Utilities",
            "subcategory":"Water",
            "type":"Services"
        }
    ],
    "sg:phone":"+61 2 6862 3342",
    "sg:postcode":"2870",
    "sg:province":"NSW",
    "sg:tags":[
        "hot",
        "system"
    ],
    "wof:name":"Parkes Paint & Heating",
    "wof:placetype":"venue"
},
  "geometry": {"coordinates":[148.17572000000001,-33.139919],"type":"Point"}
}