{
  "type": "Feature",
  "properties": {
    "iso:country":"AU",
    "sg:address":"37 Queen St",
    "sg:city":"Fingal Head",
    "sg:classifiers":[
        {
            "category":"Home & Garden",
            "subcategory":"Building Materials",
            "type":"Retail Goods"
        }
    ],
    "sg:phone":"+61 402 570 470",
    "sg:postcode":"2487",
    "sg:province":"QLD",
    "sg:tags":[
        "merchant",
        "glass",
        "glazier"
    ],
    "wof:name":"Tweed Valley Glass",
    "wof:placetype":"venue"
},
  "geometry": {"coordinates":[153.56707763700001,-28.2008838654],"type":"Point"}
}