{
  "type": "Feature",
  "properties": {
    "addr:full":"Shop 22A, Bellbowrie Shopping Plaza Bellbowrie QLD 4070",
    "addr:housenumber":"22a bellbowrie shopping",
    "addr:postcode":"4070",
    "iso:country":"AU",
    "sg:address":"Shop 22A, Bellbowrie Shopping Plaza",
    "sg:city":"Bellbowrie",
    "sg:classifiers":[
        {
            "category":"Personal",
            "type":"Services"
        }
    ],
    "sg:phone":"+61 7 3202 8773",
    "sg:postcode":"4070",
    "sg:province":"QLD",
    "sg:tags":[
        "gift"
    ],
    "wof:name":"Bellbowrie Florist",
    "wof:placetype":"venue"
},
  "geometry": {"coordinates":[152.886108398,-27.5629997253],"type":"Point"}
}