{
  "type": "Feature",
  "properties": {
    "iso:country":"AU",
    "sg:address":"1 Berry St",
    "sg:city":"Essendon North",
    "sg:classifiers":[
        {
            "category":"Arts & Performance",
            "subcategory":"Dance",
            "type":"Entertainment"
        }
    ],
    "sg:phone":"+61 419 230 180",
    "sg:postcode":"3041",
    "sg:province":"VIC",
    "sg:tags":[
        "theatrical",
        "ballet",
        "tuition"
    ],
    "wof:name":"Shimmerz Dance Studio",
    "wof:placetype":"venue"
},
  "geometry": {"coordinates":[144.90463256800001,-37.7420387268],"type":"Point"}
}