{
  "type": "Feature",
  "properties": {
    "iso:country":"AU",
    "sg:address":"192 Glebe Rd",
    "sg:city":"Merewether",
    "sg:classifiers":[
        {
            "category":"Retail",
            "subcategory":"Veterinary Services",
            "type":"Services"
        }
    ],
    "sg:phone":"+61 2 4969 2694",
    "sg:postcode":"2291",
    "sg:province":"NSW",
    "sg:tags":[
        "surgeon"
    ],
    "wof:name":"Holland Chris",
    "wof:placetype":"venue"
},
  "geometry": {"coordinates":[151.75108337399999,-32.9379768372],"type":"Point"}
}