{
  "type": "Feature",
  "properties": {
    "iso:country":"AU",
    "sg:address":"PO Box 407",
    "sg:city":"Drummoyne",
    "sg:classifiers":[
        {
            "category":"Building & Trades",
            "subcategory":"Construction",
            "type":"Services"
        }
    ],
    "sg:phone":"+61 419 993 489",
    "sg:postcode":"2047",
    "sg:province":"NSW",
    "sg:tags":[
        "plasterboard",
        "plasterer",
        "fixer"
    ],
    "wof:name":"Interior Works Pty Ltd",
    "wof:placetype":"venue"
},
  "geometry": {"coordinates":[151.15353400000001,-33.8521],"type":"Point"}
}