{
  "type": "Feature",
  "properties": {
    "addr:full":"Honeysuckle Wine Centre, Workshop Wy Newcastle NSW 2300",
    "addr:postcode":"2300",
    "addr:street":"Wy",
    "iso:country":"AU",
    "sg:address":"Honeysuckle Wine Centre, Workshop Wy",
    "sg:city":"Newcastle",
    "sg:classifiers":[
        {
            "category":"Farming",
            "subcategory":"Vineyard",
            "type":"Manufacturing & Wholesale Goods"
        }
    ],
    "sg:phone":"+61 2 4941 3000",
    "sg:postcode":"2300",
    "sg:province":"NSW",
    "sg:tags":[
        "winery"
    ],
    "wof:name":"Hunter Valley Wine Society",
    "wof:placetype":"venue"
},
  "geometry": {"coordinates":[151.780136,-32.930859],"type":"Point"}
}