{
  "type": "Feature",
  "properties": {
    "addr:full":"U1/ 27 Dorset St Lonsdale SA 5160",
    "addr:housenumber":"27",
    "addr:postcode":"5160",
    "addr:street":"U1 /;Dorset St",
    "iso:country":"AU",
    "sg:address":"U1/ 27 Dorset St",
    "sg:city":"Lonsdale",
    "sg:classifiers":[
        {
            "category":"Airport",
            "subcategory":"International",
            "type":"Transportation"
        }
    ],
    "sg:phone":"+61 8 8186 5543",
    "sg:postcode":"5160",
    "sg:province":"SA",
    "sg:tags":[
        "diving",
        "commercial"
    ],
    "wof:name":"Dive Dynamix",
    "wof:placetype":"venue"
},
  "geometry": {"coordinates":[138.507080078,-35.1149177551],"type":"Point"}
}