{
  "type": "Feature",
  "properties": {
    "addr:full":"13 Burlington St Oakleigh VIC 3166",
    "addr:housenumber":"13",
    "addr:postcode":"3166",
    "addr:street":"Burlington St",
    "iso:country":"AU",
    "sg:address":"13 Burlington St",
    "sg:city":"Oakleigh",
    "sg:classifiers":[
        {
            "category":"Organizations",
            "subcategory":"Non-profit Organization",
            "type":"Services"
        }
    ],
    "sg:phone":"+61 3 9530 9550",
    "sg:postcode":"3166",
    "sg:province":"VIC",
    "sg:tags":[
        "support",
        "disability",
        "organisation"
    ],
    "wof:name":"AGAPI Care",
    "wof:placetype":"venue"
},
  "geometry": {"coordinates":[145.092987061,-37.9017601013],"type":"Point"}
}