{
  "type": "Feature",
  "properties": {
    "addr:full":"151 Samuel St Camp Hill QLD 4152",
    "addr:housenumber":"151",
    "addr:postcode":"4152",
    "addr:street":"Samuel St",
    "iso:country":"AU",
    "sg:address":"151 Samuel St",
    "sg:city":"Camp Hill",
    "sg:classifiers":[
        {
            "category":"Insurance",
            "subcategory":"Hazard Insurance",
            "type":"Services"
        }
    ],
    "sg:phone":"+61 7 3395 1222",
    "sg:postcode":"4152",
    "sg:province":"QLD",
    "sg:tags":[
        "loss",
        "adjuster",
        "assessor"
    ],
    "wof:name":"Barry Wallace C.A.P",
    "wof:placetype":"venue"
},
  "geometry": {"coordinates":[153.08396911599999,-27.5025787354],"type":"Point"}
}