{
  "type": "Feature",
  "properties": {
    "iso:country":"AU",
    "sg:address":"10 Parsons Ave",
    "sg:city":"Springvale",
    "sg:classifiers":[
        {
            "category":"Manufacturing",
            "subcategory":"Food",
            "type":"Manufacturing & Wholesale Goods"
        }
    ],
    "sg:phone":"+61 3 9548 4066",
    "sg:postcode":"3171",
    "sg:province":"VIC",
    "sg:tags":[
        "function",
        "catering"
    ],
    "wof:name":"Nautilus Catering",
    "wof:placetype":"venue"
},
  "geometry": {"coordinates":[145.15109252900001,-37.9451904297],"type":"Point"}
}