{
  "type": "Feature",
  "properties": {
    "addr:full":"19/ 25 Khartoum Rd Macquarie Park NSW 2113",
    "addr:housenumber":"19 / 25",
    "addr:postcode":"2113",
    "addr:street":"Khartoum Rd",
    "iso:country":"AU",
    "sg:address":"19/ 25 Khartoum Rd",
    "sg:city":"Macquarie Park",
    "sg:classifiers":[
        {
            "category":"Professional",
            "subcategory":"Research",
            "type":"Services"
        }
    ],
    "sg:phone":"+61 2 9870 8788",
    "sg:postcode":"2113",
    "sg:province":"NSW",
    "sg:tags":[
        "industrial",
        "scientific"
    ],
    "wof:name":"Peptech Limited",
    "wof:placetype":"venue"
},
  "geometry": {"coordinates":[151.1275177,-33.776802063],"type":"Point"}
}