{
  "type": "Feature",
  "properties": {
    "addr:full":"Knox Towerpoint Cntr Shp 2205, Burwood Hwy Knox VIC 3180",
    "addr:housenumber":"2205",
    "addr:postcode":"3180",
    "addr:street":"Burwood Hwy",
    "iso:country":"AU",
    "sg:address":"Knox Towerpoint Cntr Shp 2205, Burwood Hwy",
    "sg:city":"Knox",
    "sg:classifiers":[
        {
            "category":"Home & Garden",
            "subcategory":"Furniture",
            "type":"Retail Goods"
        }
    ],
    "sg:phone":"+61 3 9801 7722",
    "sg:postcode":"3180",
    "sg:province":"VIC",
    "sg:tags":[
        "outdoor"
    ],
    "wof:name":"Barbeques Galore",
    "wof:placetype":"venue"
},
  "geometry": {"coordinates":[145.25296020499999,-37.8748283386],"type":"Point"}
}