{
  "type": "Feature",
  "properties": {
    "addr:full":"77 Victoria Ave Albert Park VIC 3206",
    "addr:housenumber":"77",
    "addr:postcode":"3206",
    "addr:street":"Victoria Ave",
    "iso:country":"AU",
    "sg:address":"77 Victoria Ave",
    "sg:city":"Albert Park",
    "sg:classifiers":[
        {
            "category":"Personal",
            "subcategory":"Beauty Salon",
            "type":"Services"
        }
    ],
    "sg:phone":"+61 3 9690 4095",
    "sg:postcode":"3206",
    "sg:province":"VIC",
    "sg:tags":[
        "hairdresser"
    ],
    "wof:name":"Fashion Waves Hair Design",
    "wof:placetype":"venue"
},
  "geometry": {"coordinates":[144.951324,-37.844265],"type":"Point"}
}