{
  "type": "Feature",
  "properties": {
    "iso:country":"AU",
    "sg:address":"2 Blamey St",
    "sg:city":"Revesby",
    "sg:classifiers":[
        {
            "category":"Fast Food",
            "type":"Food & Drink"
        }
    ],
    "sg:phone":"+61 2 9792 3339",
    "sg:postcode":"2212",
    "sg:province":"NSW",
    "sg:tags":[
        "away",
        "take"
    ],
    "wof:name":"Sals Ozrock Cafe",
    "wof:placetype":"venue"
},
  "geometry": {"coordinates":[151.016266,-33.952839],"type":"Point"}
}