{
  "type": "Feature",
  "properties": {
    "addr:full":"492 - 494 Clayton Rd Clayton VIC 3168",
    "addr:housenumber":"494",
    "addr:postcode":"3168",
    "addr:street":"Clayton Rd",
    "iso:country":"AU",
    "sg:address":"492 - 494 Clayton Rd",
    "sg:city":"Clayton",
    "sg:classifiers":[
        {
            "category":"Retail",
            "subcategory":"Auto Repair",
            "type":"Services"
        }
    ],
    "sg:phone":"+61 3 9544 7044",
    "sg:postcode":"3168",
    "sg:province":"VIC",
    "sg:tags":[
        "testing",
        "inspection",
        "motor",
        "vehicle"
    ],
    "wof:name":"Serv Group (AUST)",
    "wof:placetype":"venue"
},
  "geometry": {"coordinates":[145.12440490700001,-37.899684906],"type":"Point"}
}