{
  "type": "Feature",
  "properties": {
    "addr:full":"Lot 5/ Old Gunnedah Rd Narrabri NSW 2390",
    "addr:housenumber":"5 /",
    "addr:postcode":"2390",
    "addr:street":"Old Gunnedah Rd",
    "iso:country":"AU",
    "sg:address":"Lot 5/ Old Gunnedah Rd",
    "sg:city":"Narrabri",
    "sg:classifiers":[
        {
            "category":"Building & Trades",
            "subcategory":"Construction",
            "type":"Services"
        }
    ],
    "sg:phone":"+61 407 456 925",
    "sg:postcode":"2390",
    "sg:province":"NSW",
    "sg:tags":[
        "contractor"
    ],
    "wof:name":"Paul Newton Constructions",
    "wof:placetype":"venue"
},
  "geometry": {"coordinates":[149.78918457,-30.3356132507],"type":"Point"}
}