{
  "type": "Feature",
  "properties": {
    "iso:country":"AU",
    "sg:address":"Colwill Place 188 Albion Rd",
    "sg:city":"Windsor",
    "sg:classifiers":[
        {
            "category":"Professional",
            "subcategory":"Accounting & Tax Preparation",
            "type":"Services"
        }
    ],
    "sg:phone":"+61 7 3357 9833",
    "sg:postcode":"4030",
    "sg:province":"QLD",
    "sg:tags":[
        "accountant",
        "auditor"
    ],
    "wof:name":"Sinclair J H & Co",
    "wof:placetype":"venue"
},
  "geometry": {"coordinates":[153.033005,-27.42886],"type":"Point"}
}