{
  "type": "Feature",
  "properties": {
    "addr:full":"17 O'Brien St Bondi NSW 2026",
    "addr:housenumber":"17",
    "addr:postcode":"2026",
    "addr:street":"O'Brien St",
    "iso:country":"AU",
    "sg:address":"17 O'Brien St",
    "sg:city":"Bondi",
    "sg:classifiers":[
        {
            "category":"Farming",
            "subcategory":"Fish & Marine Products",
            "type":"Manufacturing & Wholesale Goods"
        }
    ],
    "sg:phone":"+61 2 9365 4904",
    "sg:postcode":"2026",
    "sg:province":"NSW",
    "sg:tags":[
        "kosher"
    ],
    "wof:name":"Eilat At Hadassa",
    "wof:placetype":"venue"
},
  "geometry": {"coordinates":[151.26873779300001,-33.8888702393],"type":"Point"}
}