{
  "type": "Feature",
  "properties": {
    "addr:full":"7 Lydiard St South Ballarat VIC 3350",
    "addr:housenumber":"7",
    "addr:postcode":"3350",
    "addr:street":"Lydiard St South",
    "iso:country":"AU",
    "sg:address":"7 Lydiard St South",
    "sg:city":"Ballarat",
    "sg:classifiers":[
        {
            "category":"Shopping",
            "subcategory":"Stationery & Office Supplies",
            "type":"Retail Goods"
        }
    ],
    "sg:phone":"+61 3 5333 2295",
    "sg:postcode":"3350",
    "sg:province":"VIC",
    "sg:tags":[
        "stocktaker"
    ],
    "wof:name":"Salter J H & B A",
    "wof:placetype":"venue"
},
  "geometry": {"coordinates":[143.857834,-37.562401],"type":"Point"}
}