{
  "type": "Feature",
  "properties": {
    "iso:country":"AU",
    "sg:address":"1024 Botany Rd",
    "sg:city":"Mascot",
    "sg:classifiers":[
        {
            "category":"Retail",
            "subcategory":"Auto Repair",
            "type":"Services"
        }
    ],
    "sg:phone":"+61 2 9666 5544",
    "sg:postcode":"2020",
    "sg:province":"NSW",
    "sg:tags":[
        "repairer",
        "motor",
        "engineer"
    ],
    "wof:name":"Ford",
    "wof:placetype":"venue"
},
  "geometry": {"coordinates":[151.19354248100001,-33.9341621399],"type":"Point"}
}