{
  "type": "Feature",
  "properties": {
    "addr:full":"Unit 1 156 Main St Blacktown NSW 2148",
    "addr:housenumber":"156",
    "addr:postcode":"2148",
    "addr:street":"Main St",
    "iso:country":"AU",
    "sg:address":"Unit 1 156 Main St",
    "sg:city":"Blacktown",
    "sg:classifiers":[
        {
            "category":"Internet Cafe",
            "subcategory":"None",
            "type":"Food & Drink"
        }
    ],
    "sg:phone":"+61 418 289 160",
    "sg:postcode":"2148",
    "sg:province":"NSW",
    "wof:name":"Sydwest Cyber",
    "wof:placetype":"venue"
},
  "geometry": {"coordinates":[150.913528442,-33.7730026245],"type":"Point"}
}