{
  "type": "Feature",
  "properties": {
    "iso:country":"AU",
    "sg:address":"175 Excelsior St",
    "sg:city":"Guildford",
    "sg:classifiers":[
        {
            "category":"Health Services",
            "subcategory":"Doctor",
            "type":"Services"
        }
    ],
    "sg:phone":"+61 2 9681 4056",
    "sg:postcode":"2161",
    "sg:province":"NSW",
    "sg:tags":[
        "medical",
        "practitioner"
    ],
    "wof:name":"Bhatt B & S Drs",
    "wof:placetype":"venue"
},
  "geometry": {"coordinates":[150.99049377399999,-33.8548812866],"type":"Point"}
}