{
  "type": "Feature",
  "properties": {
    "addr:full":"29 Harle St Abermain NSW 2326",
    "addr:housenumber":"29",
    "addr:postcode":"2326",
    "addr:street":"Harle St",
    "iso:country":"AU",
    "sg:address":"29 Harle St",
    "sg:city":"Abermain",
    "sg:classifiers":[
        {
            "category":"Home & Garden",
            "subcategory":"Building Materials",
            "type":"Retail Goods"
        }
    ],
    "sg:phone":"+61 438 702 772",
    "sg:postcode":"2326",
    "sg:province":"NSW",
    "sg:tags":[
        "lawn",
        "cutting",
        "maintenance"
    ],
    "wof:name":"The Gardening Professionals",
    "wof:placetype":"venue"
},
  "geometry": {"coordinates":[151.439529419,-32.8109893799],"type":"Point"}
}