{
  "type": "Feature",
  "properties": {
    "addr:full":"Shop 2 Parkinson Plaza 441 Algester & Nottingham R Algester QLD 4115",
    "addr:housenumber":"shop 2;441",
    "addr:postcode":"4115",
    "addr:street":"Parkinson Plaza;&;R Algester",
    "iso:country":"AU",
    "sg:address":"Shop 2 Parkinson Plaza 441 Algester & Nottingham R",
    "sg:city":"Algester",
    "sg:classifiers":[
        {
            "category":"Food & Beverages",
            "subcategory":"Liquor & Beverages",
            "type":"Retail Goods"
        }
    ],
    "sg:phone":"+61 7 3711 9188",
    "sg:postcode":"4115",
    "sg:province":"QLD",
    "sg:tags":[
        "store"
    ],
    "wof:name":"BWS Liquor Stores",
    "wof:placetype":"venue"
},
  "geometry": {"coordinates":[153.04075622600001,-27.6385936737],"type":"Point"}
}