{
  "type": "Feature",
  "properties": {
    "addr:full":"128b Canning Hwy South Perth WA 6151",
    "addr:housenumber":"128b",
    "addr:postcode":"6151",
    "addr:street":"Canning Hwy South",
    "iso:country":"AU",
    "sg:address":"128b Canning Hwy",
    "sg:city":"South Perth",
    "sg:classifiers":[
        {
            "category":"Fast Food",
            "type":"Food & Drink"
        }
    ],
    "sg:phone":"+61 8 9367 8868",
    "sg:postcode":"6151",
    "sg:province":"WA",
    "sg:tags":[
        "away",
        "take"
    ],
    "wof:name":"Delicious Chinese Restaurant & Take Away",
    "wof:placetype":"venue"
},
  "geometry": {"coordinates":[115.876312,-31.982189],"type":"Point"}
}