{
  "type": "Feature",
  "properties": {
    "addr:full":"Galah St Churchill QLD 4305",
    "addr:postcode":"4305",
    "addr:street":"Galah St",
    "iso:country":"AU",
    "sg:address":"Galah St",
    "sg:city":"Churchill",
    "sg:classifiers":[
        {
            "category":"Retail",
            "subcategory":"Car Wash",
            "type":"Services"
        }
    ],
    "sg:phone":"+61 7 3281 4904",
    "sg:postcode":"4305",
    "sg:province":"QLD",
    "sg:tags":[
        "truck",
        "cleaning"
    ],
    "wof:name":"Finer Details",
    "wof:placetype":"venue"
},
  "geometry": {"coordinates":[152.75360107399999,-27.6390686035],"type":"Point"}
}