{
  "type": "Feature",
  "properties": {
    "iso:country":"AU",
    "sg:address":"Suite 19, 18 Stirling Hwy",
    "sg:city":"Nedlands",
    "sg:classifiers":[
        {
            "category":"Professional",
            "subcategory":"Management & Consulting",
            "type":"Services"
        }
    ],
    "sg:phone":"+61 8 9386 9155",
    "sg:postcode":"6009",
    "sg:province":"WA",
    "sg:tags":[
        "consultant"
    ],
    "wof:name":"McIntyre Management & Marketing",
    "wof:placetype":"venue"
},
  "geometry": {"coordinates":[115.81398,-31.977015],"type":"Point"}
}