{
  "type": "Feature",
  "properties": {
    "iso:country":"AU",
    "sg:address":"44 Clarke St",
    "sg:city":"Koroit",
    "sg:classifiers":[
        {
            "category":"Home & Garden",
            "subcategory":"Carpets & Floor Coverings",
            "type":"Retail Goods"
        }
    ],
    "sg:phone":"+61 418 658 540",
    "sg:postcode":"3282",
    "sg:province":"VIC",
    "sg:tags":[
        "layer",
        "planner"
    ],
    "wof:name":"Bushell Brendan",
    "wof:placetype":"venue"
},
  "geometry": {"coordinates":[142.35838317899999,-38.2444992065],"type":"Point"}
}