{
  "type": "Feature",
  "properties": {
    "addr:full":"25 Chief St Welland SA 5007",
    "addr:housenumber":"25",
    "addr:postcode":"5007",
    "addr:street":"Chief St",
    "iso:country":"AU",
    "sg:address":"25 Chief St",
    "sg:city":"Welland",
    "sg:classifiers":[
        {
            "category":"Organizations",
            "subcategory":"Labor Organization",
            "type":"Services"
        }
    ],
    "sg:phone":"+61 8 8346 8423",
    "sg:postcode":"5007",
    "sg:province":"SA",
    "sg:tags":[
        "union"
    ],
    "wof:name":"Textile Clothing & Footwear Union",
    "wof:placetype":"venue"
},
  "geometry": {"coordinates":[138.57583618199999,-34.9019889832],"type":"Point"}
}