{
  "type": "Feature",
  "properties": {
    "iso:country":"AU",
    "sg:address":"Appartment 11 10 Crawford Rd",
    "sg:city":"Brighton-le-Sands",
    "sg:classifiers":[
        {
            "category":"Building & Trades",
            "subcategory":"Construction",
            "type":"Services"
        }
    ],
    "sg:phone":"+61 414 559 970",
    "sg:postcode":"2216",
    "sg:province":"NSW",
    "sg:tags":[
        "joiner",
        "carpenter"
    ],
    "wof:name":"Add More Renovations",
    "wof:placetype":"venue"
},
  "geometry": {"coordinates":[151.152176,-33.95993],"type":"Point"}
}