{
  "type": "Feature",
  "properties": {
    "addr:full":"End of Laidlaw Rd Woombye QLD 4559",
    "addr:postcode":"4559",
    "addr:street":"Rd",
    "iso:country":"AU",
    "sg:address":"End of Laidlaw Rd",
    "sg:city":"Woombye",
    "sg:classifiers":[
        {
            "category":"Farming",
            "subcategory":"Nursery",
            "type":"Manufacturing & Wholesale Goods"
        }
    ],
    "sg:phone":"+61 7 5442 1339",
    "sg:postcode":"4559",
    "sg:province":"QLD",
    "wof:name":"Florabunda Bushcare",
    "wof:placetype":"venue"
},
  "geometry": {"coordinates":[152.95390319800001,-26.6519889832],"type":"Point"}
}