{
  "type": "Feature",
  "properties": {
    "addr:full":"42 Cardiff Rd Elermore Vale NSW 2287",
    "addr:housenumber":"42",
    "addr:postcode":"2287",
    "addr:street":"Cardiff Rd",
    "iso:country":"AU",
    "sg:address":"42 Cardiff Rd",
    "sg:city":"Elermore Vale",
    "sg:classifiers":[
        {
            "category":"Retail",
            "subcategory":"Auto Repair",
            "type":"Services"
        }
    ],
    "sg:phone":"+61 2 4951 8288",
    "sg:postcode":"2287",
    "sg:province":"NSW",
    "sg:tags":[
        "repairer",
        "motor",
        "engineer"
    ],
    "wof:name":"Kaiser Mechanical Repairs",
    "wof:placetype":"venue"
},
  "geometry": {"coordinates":[151.67257690400001,-32.9140663147],"type":"Point"}
}