{
  "type": "Feature",
  "properties": {
    "addr:full":"29 Criterion St Hobart TAS 7000",
    "addr:housenumber":"29",
    "addr:postcode":"7000",
    "addr:street":"Criterion St",
    "iso:country":"AU",
    "sg:address":"29 Criterion St",
    "sg:city":"Hobart",
    "sg:classifiers":[
        {
            "category":"Professional",
            "subcategory":"Accounting & Tax Preparation",
            "type":"Services"
        }
    ],
    "sg:phone":"+61 3 6234 4377",
    "sg:postcode":"7000",
    "sg:province":"TAS",
    "sg:tags":[
        "consultant",
        "taxation"
    ],
    "sg:website":"http://www.itp.com.au",
    "wof:name":"ITP The Income Tax Professionals",
    "wof:placetype":"venue"
},
  "geometry": {"coordinates":[147.32533264200001,-42.8812942505],"type":"Point"}
}