{
  "type": "Feature",
  "properties": {
    "addr:full":"Suite 299, 2nd Floor, St Andrew's Place, 33 North Street Spring Hill QLD 4004",
    "addr:housenumber":"33",
    "addr:postcode":"4004",
    "addr:street":"North Street",
    "iso:country":"AU",
    "sg:address":"Suite 299, 2nd Floor, St Andrew's Place, 33 North Street",
    "sg:city":"Spring Hill",
    "sg:classifiers":[
        {
            "category":"Health Services",
            "subcategory":"Doctor",
            "type":"Services"
        }
    ],
    "sg:phone":"+61 7 3831 7238",
    "sg:postcode":"4004",
    "sg:province":"QLD",
    "sg:tags":[
        "medical",
        "practitioner"
    ],
    "wof:name":"Bryant Andrew",
    "wof:placetype":"venue"
},
  "geometry": {"coordinates":[153.021606445,-27.4612216949],"type":"Point"}
}