{
  "type": "Feature",
  "properties": {
    "iso:country":"AU",
    "sg:address":"597 Glen Huntly Rd",
    "sg:city":"Elsternwick",
    "sg:classifiers":[
        {
            "category":"Health Services",
            "subcategory":"Chiropractor",
            "type":"Services"
        }
    ],
    "sg:phone":"+61 3 9523 1911",
    "sg:postcode":"3185",
    "sg:province":"VIC",
    "wof:name":"Nemeth Chiropractic",
    "wof:placetype":"venue"
},
  "geometry": {"coordinates":[145.01414489699999,-37.8857803345],"type":"Point"}
}