{
  "type": "Feature",
  "properties": {
    "addr:full":"75 / 77 Mooney St Gulliver QLD 4812",
    "addr:housenumber":"75 / 77",
    "addr:postcode":"4812",
    "addr:street":"Mooney St",
    "iso:country":"AU",
    "sg:address":"75 / 77 Mooney St",
    "sg:city":"Gulliver",
    "sg:classifiers":[
        {
            "category":"Personal",
            "subcategory":"Beauty Salon",
            "type":"Services"
        }
    ],
    "sg:phone":"+61 7 4779 1256",
    "sg:postcode":"4812",
    "sg:province":"QLD",
    "sg:tags":[
        "hairdresser"
    ],
    "wof:name":"Salon Capri",
    "wof:placetype":"venue"
},
  "geometry": {"coordinates":[146.77145400000001,-19.282581],"type":"Point"}
}