{
  "type": "Feature",
  "properties": {
    "addr:full":"11 Cochrane St West Kempsey NSW 2440",
    "addr:housenumber":"11",
    "addr:postcode":"2440",
    "addr:street":"Cochrane St West",
    "iso:country":"AU",
    "sg:address":"11 Cochrane St",
    "sg:city":"West Kempsey",
    "sg:classifiers":[
        {
            "category":"Building & Trades",
            "subcategory":"Construction",
            "type":"Services"
        }
    ],
    "sg:phone":"+61 2 6563 1522",
    "sg:postcode":"2440",
    "sg:province":"NSW",
    "sg:tags":[
        "concrete",
        "contractor"
    ],
    "wof:name":"Borger Mark Stamp & Stencil Concrete Service",
    "wof:placetype":"venue"
},
  "geometry": {"coordinates":[152.832672,-31.065346],"type":"Point"}
}