{
  "type": "Feature",
  "properties": {
    "iso:country":"AU",
    "sg:address":"3 Marshall St",
    "sg:city":"Earlville",
    "sg:classifiers":[
        {
            "category":"Communications",
            "subcategory":"News Services",
            "type":"Services"
        }
    ],
    "sg:phone":"+61 7 4051 4328",
    "sg:postcode":"4870",
    "sg:province":"QLD",
    "sg:tags":[
        "information",
        "tourist",
        "attractions"
    ],
    "wof:name":"Trek North Safaris",
    "wof:placetype":"venue"
},
  "geometry": {"coordinates":[145.732345581,-16.9371776581],"type":"Point"}
}