{
  "type": "Feature",
  "properties": {
    "addr:full":"37 Allens Pde Bondi Junction NSW 2022",
    "addr:housenumber":"37",
    "addr:postcode":"2022",
    "addr:street":"Allens Pde",
    "iso:country":"AU",
    "sg:address":"37 Allens Pde",
    "sg:city":"Bondi Junction",
    "sg:classifiers":[
        {
            "category":"Professional",
            "subcategory":"Computer Services",
            "type":"Services"
        }
    ],
    "sg:phone":"+61 2 9387 1559",
    "sg:postcode":"2022",
    "sg:province":"NSW",
    "sg:tags":[
        "consultant",
        "system"
    ],
    "wof:name":"ZEN IT Pty Ltd",
    "wof:placetype":"venue"
},
  "geometry": {"coordinates":[151.25387573200001,-33.8950767517],"type":"Point"}
}