{
  "type": "Feature",
  "properties": {
    "addr:full":"Pheasant St Mackay QLD 4740",
    "addr:postcode":"4740",
    "addr:street":"Pheasant St",
    "iso:country":"AU",
    "sg:address":"Pheasant St",
    "sg:city":"Mackay",
    "sg:classifiers":[
        {
            "category":"Education",
            "subcategory":"School",
            "type":"Public Place"
        }
    ],
    "sg:phone":"+61 7 4965 7355",
    "sg:postcode":"4740",
    "sg:province":"QLD",
    "sg:tags":[
        "state",
        "except",
        "nsw"
    ],
    "wof:name":"Slade Point Preschool",
    "wof:placetype":"venue"
},
  "geometry": {"coordinates":[149.215057,-21.074692],"type":"Point"}
}