{
  "type": "Feature",
  "properties": {
    "addr:full":"337 Logan Rd Stones Corner QLD 4120",
    "addr:housenumber":"337",
    "addr:postcode":"4120",
    "addr:street":"Logan Rd",
    "iso:country":"AU",
    "sg:address":"337 Logan Rd",
    "sg:city":"Stones Corner",
    "sg:classifiers":[
        {
            "category":"Sports & Exercise",
            "subcategory":"Gym",
            "type":"Entertainment"
        }
    ],
    "sg:phone":"+61 7 3394 2344",
    "sg:postcode":"4120",
    "sg:province":"QLD",
    "sg:tags":[
        "personal",
        "trainer",
        "fitness"
    ],
    "wof:name":"Australian Institute of Applied Sciences",
    "wof:placetype":"venue"
},
  "geometry": {"coordinates":[153.044723511,-27.4977588654],"type":"Point"}
}