{
  "type": "Feature",
  "properties": {
    "iso:country":"AU",
    "sg:address":"43 Railway Pde",
    "sg:city":"Mt Lawley",
    "sg:classifiers":[
        {
            "category":"Professional",
            "subcategory":"Computer Services",
            "type":"Services"
        }
    ],
    "sg:phone":"+61 8 9473 1800",
    "sg:postcode":"6050",
    "sg:province":"WA",
    "sg:tags":[
        "equipment",
        "networking",
        "installation"
    ],
    "wof:name":"The Net Effect",
    "wof:placetype":"venue"
},
  "geometry": {"coordinates":[115.878616333,-31.9368076324],"type":"Point"}
}