{
  "type": "Feature",
  "properties": {
    "addr:full":"Shp3/ 100b King William Rd Goodwood SA 5034",
    "addr:housenumber":"100b",
    "addr:postcode":"5034",
    "addr:street":"King William Rd",
    "iso:country":"AU",
    "sg:address":"Shp3/ 100b King William Rd",
    "sg:city":"Goodwood",
    "sg:classifiers":[
        {
            "category":"Shopping",
            "subcategory":"Clothing, Apparel, & Fashions",
            "type":"Retail Goods"
        }
    ],
    "sg:phone":"+61 8 8272 0088",
    "sg:postcode":"5034",
    "sg:province":"SA",
    "sg:tags":[
        "lady",
        "wear"
    ],
    "wof:name":"China Image",
    "wof:placetype":"venue"
},
  "geometry": {"coordinates":[138.599685669,-34.9517936707],"type":"Point"}
}