{
  "type": "Feature",
  "properties": {
    "addr:full":"1 Nepean Hwy Mentone VIC 3194",
    "addr:housenumber":"1",
    "addr:postcode":"3194",
    "addr:street":"Nepean Hwy",
    "iso:country":"AU",
    "sg:address":"1 Nepean Hwy",
    "sg:city":"Mentone",
    "sg:classifiers":[
        {
            "category":"Autos & Motor Vehicles",
            "subcategory":"Automobile Sales",
            "type":"Retail Goods"
        }
    ],
    "sg:phone":"+61 3 8586 8888",
    "sg:postcode":"3194",
    "sg:province":"VIC",
    "sg:tags":[
        "car",
        "new"
    ],
    "wof:name":"Barloworld Volkswagon",
    "wof:placetype":"venue"
},
  "geometry": {"coordinates":[145.06517028799999,-37.9742546082],"type":"Point"}
}