{
  "type": "Feature",
  "properties": {
    "addr:full":"1 Callaghan Cl Charmhaven NSW 2263",
    "addr:housenumber":"1",
    "addr:postcode":"2263",
    "addr:street":"Callaghan Cl Charmhaven",
    "iso:country":"AU",
    "sg:address":"1 Callaghan Cl",
    "sg:city":"Charmhaven",
    "sg:classifiers":[
        {
            "category":"Personal",
            "subcategory":"Massage",
            "type":"Services"
        }
    ],
    "sg:phone":"+61 1300 931 200",
    "sg:postcode":"2263",
    "sg:province":"NSW",
    "sg:tags":[
        "therapy"
    ],
    "sg:website":"http://www.massageschool.com.au",
    "wof:name":"Lake Spa Healing Therapy & Education Centre",
    "wof:placetype":"venue"
},
  "geometry": {"coordinates":[151.497131,-33.237801],"type":"Point"}
}