{
  "type": "Feature",
  "properties": {
    "addr:full":"PO Box 1728 Moree NSW 2400",
    "addr:postcode":"2400",
    "iso:country":"AU",
    "sg:address":"PO Box 1728",
    "sg:city":"Moree",
    "sg:classifiers":[
        {
            "category":"Personal",
            "subcategory":"Adult",
            "type":"Services"
        }
    ],
    "sg:phone":"+61 428 531 453",
    "sg:postcode":"2400",
    "sg:province":"NSW",
    "sg:tags":[
        "vic",
        "except",
        "state",
        "escort",
        "social",
        "qld"
    ],
    "wof:name":"Sweethearts",
    "wof:placetype":"venue"
},
  "geometry": {"coordinates":[149.841598511,-29.4661998749],"type":"Point"}
}