{
  "type": "Feature",
  "properties": {
    "addr:full":"47 Burns Rd Altona VIC 3018",
    "addr:housenumber":"47",
    "addr:postcode":"3018",
    "addr:street":"Burns Rd",
    "iso:country":"AU",
    "sg:address":"47 Burns Rd",
    "sg:city":"Altona",
    "sg:classifiers":[
        {
            "category":"Bars & Pubs",
            "subcategory":"Biergarten",
            "type":"Food & Drink"
        }
    ],
    "sg:phone":"+61 3 8368 2522",
    "sg:postcode":"3018",
    "sg:province":"VIC",
    "sg:tags":[
        "eucalyptus",
        "oil",
        "tree",
        "essential",
        "tea"
    ],
    "wof:name":"Lighting Products Pty Ltd",
    "wof:placetype":"venue"
},
  "geometry": {"coordinates":[144.78994750999999,-37.8498306274],"type":"Point"}
}