{
  "type": "Feature",
  "properties": {
    "iso:country":"AU",
    "sg:address":"Cnr Metcalfe & High Rds",
    "sg:city":"Parkwood",
    "sg:classifiers":[
        {
            "category":"Education",
            "subcategory":"School",
            "type":"Public Place"
        }
    ],
    "sg:phone":"+61 8 9457 1222",
    "sg:postcode":"6147",
    "sg:province":"WA",
    "sg:tags":[
        "state",
        "except",
        "nsw"
    ],
    "wof:name":"Lynwood Senior High School",
    "wof:placetype":"venue"
},
  "geometry": {"coordinates":[115.917137,-32.043007],"type":"Point"}
}