{
  "type": "Feature",
  "properties": {
    "iso:country":"AU",
    "sg:address":"Fcty 5/ 156 High St",
    "sg:city":"Melton",
    "sg:classifiers":[
        {
            "category":"Professional",
            "subcategory":"Art Services",
            "type":"Services"
        }
    ],
    "sg:phone":"+61 3 9746 6003",
    "sg:postcode":"3337",
    "sg:province":"VIC",
    "sg:tags":[
        "picture",
        "frame",
        "framing"
    ],
    "wof:name":"B & S Picture Framing & Engraving",
    "wof:placetype":"venue"
},
  "geometry": {"coordinates":[144.58674600000001,-37.682816],"type":"Point"}
}