{
  "type": "Feature",
  "properties": {
    "addr:full":"U3/ 15 Truck City Drv Campbellfield VIC 3061",
    "addr:postcode":"3061",
    "addr:street":"U3 / 15 Truck City Drv",
    "iso:country":"AU",
    "sg:address":"U3/ 15 Truck City Drv",
    "sg:city":"Campbellfield",
    "sg:classifiers":[
        {
            "category":"Military Area",
            "subcategory":"Army Base",
            "type":"Public Place"
        }
    ],
    "sg:phone":"+61 3 9308 9616",
    "sg:postcode":"3061",
    "sg:province":"VIC",
    "sg:tags":[
        "wholesaler",
        "clutch",
        "brake",
        "mfrs",
        "equipment"
    ],
    "sg:website":"http://www.justbrakes.com.au",
    "wof:name":"Just Brakes",
    "wof:placetype":"venue"
},
  "geometry": {"coordinates":[144.94833374000001,-37.6479415894],"type":"Point"}
}