{
  "type": "Feature",
  "properties": {
    "addr:full":"1072 Glenhuntly Rd Glen Huntly VIC 3163",
    "addr:housenumber":"1072",
    "addr:postcode":"3163",
    "addr:street":"Glenhuntly Rd",
    "iso:country":"AU",
    "sg:address":"1072 Glenhuntly Rd",
    "sg:city":"Glen Huntly",
    "sg:classifiers":[
        {
            "category":"Retail",
            "subcategory":"Auto Repair",
            "type":"Services"
        }
    ],
    "sg:phone":"+61 3 9563 6133",
    "sg:postcode":"3163",
    "sg:province":"VIC",
    "sg:tags":[
        "fuel",
        "petrol",
        "injection"
    ],
    "wof:name":"New Life Carburettors",
    "wof:placetype":"venue"
},
  "geometry": {"coordinates":[145.03797912600001,-37.8890190125],"type":"Point"}
}