{
  "type": "Feature",
  "properties": {
    "addr:full":"1 Daveyduke Drv Mitchell Park VIC 3352",
    "addr:housenumber":"1",
    "addr:postcode":"3352",
    "addr:street":"Daveyduke Drv",
    "iso:country":"AU",
    "sg:address":"1 Daveyduke Drv",
    "sg:city":"Mitchell Park",
    "sg:classifiers":[
        {
            "category":"Autos & Motor Vehicles",
            "subcategory":"Automobile Sales",
            "type":"Retail Goods"
        }
    ],
    "sg:phone":"+61 3 5339 9339",
    "sg:postcode":"3352",
    "sg:province":"VIC",
    "sg:tags":[
        "car",
        "new"
    ],
    "wof:name":"Ballarat VW",
    "wof:placetype":"venue"
},
  "geometry": {"coordinates":[143.80508399999999,-37.513718],"type":"Point"}
}