{
  "type": "Feature",
  "properties": {
    "addr:full":"30 O'Sullivan St Higgins ACT 2615",
    "addr:housenumber":"30",
    "addr:postcode":"2615",
    "addr:street":"O'Sullivan St",
    "iso:country":"AU",
    "sg:address":"30 O'Sullivan St",
    "sg:city":"Higgins",
    "sg:classifiers":[
        {
            "category":"Building & Trades",
            "subcategory":"Construction",
            "type":"Services"
        }
    ],
    "sg:phone":"+61 2 6254 9953",
    "sg:postcode":"2615",
    "sg:province":"ACT",
    "sg:tags":[
        "brick",
        "paving"
    ],
    "wof:name":"Burgess Landscaping",
    "wof:placetype":"venue"
},
  "geometry": {"coordinates":[149.028839111,-35.2399520874],"type":"Point"}
}