{
  "type": "Feature",
  "properties": {
    "iso:country":"AU",
    "sg:address":"67 Standish St",
    "sg:city":"Myrtleford",
    "sg:classifiers":[
        {
            "category":"Travel",
            "subcategory":"Hotels & Motels",
            "type":"Entertainment"
        }
    ],
    "sg:phone":"+61 3 5752 1001",
    "sg:postcode":"3737",
    "sg:province":"VIC",
    "sg:tags":[
        "accommodation"
    ],
    "wof:name":"Myrtleford Hotel Motel",
    "wof:placetype":"venue"
},
  "geometry": {"coordinates":[146.724334717,-36.5601959229],"type":"Point"}
}