{
  "type": "Feature",
  "properties": {
    "iso:country":"AU",
    "sg:address":"12 Dib Crt",
    "sg:city":"Tullamarine",
    "sg:classifiers":[
        {
            "category":"Organizations",
            "subcategory":"Professional Association",
            "type":"Services"
        }
    ],
    "sg:phone":"+61 3 9338 3471",
    "sg:postcode":"3043",
    "sg:province":"VIC",
    "sg:tags":[
        "cloth",
        "spreading",
        "cutting",
        "machinery"
    ],
    "wof:name":"Pathfinder Australia Pty Ltd",
    "wof:placetype":"venue"
},
  "geometry": {"coordinates":[144.866577148,-37.7199516296],"type":"Point"}
}