{
  "type": "Feature",
  "properties": {
    "addr:full":"88 Gawler Pl Adelaide SA 5000",
    "addr:housenumber":"88",
    "addr:postcode":"5000",
    "addr:street":"Gawler Pl",
    "iso:country":"AU",
    "sg:address":"88 Gawler Pl",
    "sg:city":"Adelaide",
    "sg:classifiers":[
        {
            "category":"Cafe",
            "type":"Food & Drink"
        }
    ],
    "sg:phone":"+61 8 8232 1256",
    "sg:postcode":"5000",
    "sg:province":"SA",
    "wof:name":"Latte Fix",
    "wof:placetype":"venue"
},
  "geometry": {"coordinates":[138.60214233400001,-34.924446106],"type":"Point"}
}