{
  "type": "Feature",
  "properties": {
    "iso:country":"AU",
    "sg:address":"26 Johnson Drv",
    "sg:city":"Lockrose",
    "sg:classifiers":[
        {
            "category":"Communications",
            "type":"Services"
        }
    ],
    "sg:phone":"+61 412 246 723",
    "sg:postcode":"4342",
    "sg:province":"QLD",
    "sg:tags":[
        "public",
        "system",
        "address"
    ],
    "wof:name":"R. & K. Hancock",
    "wof:placetype":"venue"
},
  "geometry": {"coordinates":[152.45930480999999,-27.500421524],"type":"Point"}
}