{
  "type": "Feature",
  "properties": {
    "addr:full":"15 Lawson St Mudgee NSW 2850",
    "addr:housenumber":"15",
    "addr:postcode":"2850",
    "addr:street":"Lawson St",
    "iso:country":"AU",
    "sg:address":"15 Lawson St",
    "sg:city":"Mudgee",
    "sg:classifiers":[
        {
            "category":"Juice Bar",
            "subcategory":"None",
            "type":"Food & Drink"
        }
    ],
    "sg:phone":"+61 1800 650 036",
    "sg:postcode":"2850",
    "sg:province":"NSW",
    "sg:tags":[
        "merchant",
        "fruit",
        "processor"
    ],
    "wof:name":"Bevco Quality Drinks",
    "wof:placetype":"venue"
},
  "geometry": {"coordinates":[149.59300200000001,-32.594921],"type":"Point"}
}