{
  "type": "Feature",
  "properties": {
    "iso:country":"AU",
    "sg:address":"10 Macquarie St",
    "sg:city":"Swansea",
    "sg:classifiers":[
        {
            "category":"Retail",
            "subcategory":"Repair Shop",
            "type":"Services"
        }
    ],
    "sg:phone":"+61 2 4971 4871",
    "sg:postcode":"2281",
    "sg:province":"NSW",
    "sg:tags":[
        "leadlights"
    ],
    "wof:name":"Ray's Leadlighting",
    "wof:placetype":"venue"
},
  "geometry": {"coordinates":[151.63659668,-33.0863685608],"type":"Point"}
}