{
  "type": "Feature",
  "properties": {
    "iso:country":"AU",
    "sg:address":"31 Longstaff Ave",
    "sg:city":"Chipping Norton",
    "sg:classifiers":[
        {
            "category":"Wholesale",
            "subcategory":"Machinery & Supplies",
            "type":"Manufacturing & Wholesale Goods"
        }
    ],
    "sg:phone":"+61 2 9601 2209",
    "sg:postcode":"2170",
    "sg:province":"NSW",
    "sg:tags":[
        "equipment",
        "pneumatic"
    ],
    "wof:name":"Celcor Pty Ltd",
    "wof:placetype":"venue"
},
  "geometry": {"coordinates":[150.94822692899999,-33.9262580872],"type":"Point"}
}