{
  "type": "Feature",
  "properties": {
    "addr:full":"Cnr Leeson & Princes Hwy Traralgon VIC 3844",
    "addr:postcode":"3844",
    "addr:street":"Hwy",
    "iso:country":"AU",
    "sg:address":"Cnr Leeson & Princes Hwy",
    "sg:city":"Traralgon",
    "sg:classifiers":[
        {
            "category":"Home & Garden",
            "subcategory":"Building Materials",
            "type":"Retail Goods"
        }
    ],
    "sg:phone":"+61 1800 666 437",
    "sg:postcode":"3844",
    "sg:province":"VIC",
    "sg:tags":[
        "tile",
        "roofing"
    ],
    "wof:name":"Monier Wunderlich",
    "wof:placetype":"venue"
},
  "geometry": {"coordinates":[146.541107178,-38.1958122253],"type":"Point"}
}