{
  "type": "Feature",
  "properties": {
    "addr:full":"Unit G8/ 2a Victoria Ave Castle Hill NSW 2154",
    "addr:housenumber":"g8 / 2a",
    "addr:postcode":"2154",
    "addr:street":"Victoria Ave",
    "iso:country":"AU",
    "sg:address":"Unit G8/ 2a Victoria Ave",
    "sg:city":"Castle Hill",
    "sg:classifiers":[
        {
            "category":"Utilities",
            "subcategory":"Water",
            "type":"Services"
        }
    ],
    "sg:phone":"+61 2 8850 2522",
    "sg:postcode":"2154",
    "sg:province":"NSW",
    "sg:tags":[
        "equipment",
        "treatment"
    ],
    "wof:name":"Hydrotech Scientific Services Pty Ltd",
    "wof:placetype":"venue"
},
  "geometry": {"coordinates":[150.981323242,-33.7354278564],"type":"Point"}
}