{
  "type": "Feature",
  "properties": {
    "addr:full":"184 Spencer St Bunbury WA 6230",
    "addr:housenumber":"184",
    "addr:postcode":"6230",
    "addr:street":"Spencer St",
    "iso:country":"AU",
    "sg:address":"184 Spencer St",
    "sg:city":"Bunbury",
    "sg:classifiers":[
        {
            "category":"Personal",
            "subcategory":"Beauty Salon",
            "type":"Services"
        }
    ],
    "sg:phone":"+61 8 9721 3039",
    "sg:postcode":"6230",
    "sg:province":"WA",
    "sg:tags":[
        "hairdresser"
    ],
    "wof:name":"Lucy's Hair Design",
    "wof:placetype":"venue"
},
  "geometry": {"coordinates":[115.641487,-33.346172],"type":"Point"}
}