{
  "type": "Feature",
  "properties": {
    "addr:full":"425 Fallon St Albury NSW 2640",
    "addr:housenumber":"425",
    "addr:postcode":"2640",
    "addr:street":"Fallon St",
    "iso:country":"AU",
    "sg:address":"425 Fallon St",
    "sg:city":"Albury",
    "sg:classifiers":[
        {
            "category":"Utilities",
            "subcategory":"Electric",
            "type":"Services"
        }
    ],
    "sg:phone":"+61 418 578 545",
    "sg:postcode":"2640",
    "sg:province":"NSW",
    "sg:tags":[
        "electrical",
        "contractor"
    ],
    "wof:name":"Daniel Muller Electrical",
    "wof:placetype":"venue"
},
  "geometry": {"coordinates":[146.926834106,-36.0624847412],"type":"Point"}
}