{
  "type": "Feature",
  "properties": {
    "addr:full":"Cnr Parramatta Rd & Glebe Point Rd Glebe NSW 2037",
    "addr:postcode":"2037",
    "addr:street":"Parramatta Rd & Glebe Point Rd",
    "iso:country":"AU",
    "sg:address":"Cnr Parramatta Rd & Glebe Point Rd",
    "sg:city":"Glebe",
    "sg:classifiers":[
        {
            "category":"Restaurant",
            "type":"Food & Drink"
        }
    ],
    "sg:phone":"+61 2 9660 7830",
    "sg:postcode":"2037",
    "sg:province":"NSW",
    "wof:name":"Attica Brasserie & Bar",
    "wof:placetype":"venue"
},
  "geometry": {"coordinates":[151.192504883,-33.8846130371],"type":"Point"}
}