{
  "type": "Feature",
  "properties": {
    "addr:full":"Grnd Flr, 70 Hindmarsh St Adelaide SA 5000",
    "addr:postcode":"5000",
    "addr:street":"Grnd;Hindmarsh St",
    "iso:country":"AU",
    "sg:address":"Grnd Flr, 70 Hindmarsh St",
    "sg:city":"Adelaide",
    "sg:classifiers":[
        {
            "category":"Banks & Credit Unions",
            "subcategory":"Financial Services",
            "type":"Services"
        }
    ],
    "sg:phone":"+61 8 8223 6899",
    "sg:postcode":"5000",
    "sg:province":"SA",
    "sg:tags":[
        "planning"
    ],
    "wof:name":"Genesys Wealth Advisers",
    "wof:placetype":"venue"
},
  "geometry": {"coordinates":[138.6065979,-34.9244499207],"type":"Point"}
}