{
  "type": "Feature",
  "properties": {
    "iso:country":"AU",
    "sg:address":"Level 1 251 Malvern Rd",
    "sg:city":"South Yarra",
    "sg:classifiers":[
        {
            "category":"Insurance",
            "subcategory":"Insurance Agent",
            "type":"Services"
        }
    ],
    "sg:phone":"+61 3 9827 5955",
    "sg:postcode":"3141",
    "sg:province":"VIC",
    "sg:tags":[
        "broker"
    ],
    "wof:name":"IMC Insurance Brokers",
    "wof:placetype":"venue"
},
  "geometry": {"coordinates":[144.994598389,-37.8467826843],"type":"Point"}
}