{
  "type": "Feature",
  "properties": {
    "addr:full":"Shop 1 Inala Town Cntr, Inala Ave Inala QLD 4077",
    "addr:housenumber":"shop 1",
    "addr:postcode":"4077",
    "addr:street":"Inala Town Cntr Inala Ave Inala",
    "iso:country":"AU",
    "sg:address":"Shop 1 Inala Town Cntr, Inala Ave",
    "sg:city":"Inala",
    "sg:classifiers":[
        {
            "category":"Health Services",
            "subcategory":"Medical Lab",
            "type":"Services"
        }
    ],
    "sg:phone":"+61 7 3278 7811",
    "sg:postcode":"4077",
    "sg:province":"QLD",
    "sg:tags":[
        "laboratory",
        "pathology"
    ],
    "wof:name":"Sullivan Nicolaides Pathology",
    "wof:placetype":"venue"
},
  "geometry": {"coordinates":[152.97158813499999,-27.5963191986],"type":"Point"}
}