{
  "type": "Feature",
  "properties": {
    "addr:full":"4 Shields St Cairns QLD 4870",
    "addr:housenumber":"4",
    "addr:postcode":"4870",
    "addr:street":"Shields St",
    "iso:country":"AU",
    "sg:address":"4 Shields St",
    "sg:city":"Cairns",
    "sg:classifiers":[
        {
            "category":"Shopping",
            "subcategory":"Clothing, Apparel, & Fashions",
            "type":"Retail Goods"
        }
    ],
    "sg:phone":"+61 7 4051 2202",
    "sg:postcode":"4870",
    "sg:province":"QLD",
    "sg:tags":[
        "menswear"
    ],
    "wof:name":"Curtin Danny Menswear",
    "wof:placetype":"venue"
},
  "geometry": {"coordinates":[145.776977539,-16.9212875366],"type":"Point"}
}