{
  "type": "Feature",
  "properties": {
    "addr:full":"Murat Rd Exmouth WA 6707",
    "addr:postcode":"6707",
    "addr:street":"Murat Rd",
    "iso:country":"AU",
    "sg:address":"Murat Rd",
    "sg:city":"Exmouth",
    "sg:classifiers":[
        {
            "category":"Travel",
            "subcategory":"Hotels & Motels",
            "type":"Entertainment"
        }
    ],
    "sg:phone":"+61 8 9949 1200",
    "sg:postcode":"6707",
    "sg:province":"WA",
    "wof:name":"Potshot Hotel Resort",
    "wof:placetype":"venue"
},
  "geometry": {"coordinates":[114.13329315199999,-21.946231842],"type":"Point"}
}