{
  "type": "Feature",
  "properties": {
    "addr:full":"4 Pridmore Rd Glen Osmond SA 5064",
    "addr:housenumber":"4",
    "addr:postcode":"5064",
    "addr:street":"Pridmore Rd",
    "iso:country":"AU",
    "sg:address":"4 Pridmore Rd",
    "sg:city":"Glen Osmond",
    "sg:classifiers":[
        {
            "category":"Real Estate",
            "subcategory":"Real Estate Agent",
            "type":"Services"
        }
    ],
    "sg:phone":"+61 412 671 352",
    "sg:postcode":"5064",
    "sg:province":"SA",
    "wof:name":"Mittiga Mary",
    "wof:placetype":"venue"
},
  "geometry": {"coordinates":[138.64466857900001,-34.9628410339],"type":"Point"}
}