{
  "type": "Feature",
  "properties": {
    "addr:full":"16 Maple St Moonah TAS 7009",
    "addr:housenumber":"16",
    "addr:postcode":"7009",
    "addr:street":"Maple St",
    "iso:country":"AU",
    "sg:address":"16 Maple St",
    "sg:city":"Moonah",
    "sg:classifiers":[
        {
            "category":"Social Services",
            "subcategory":"Adult Care",
            "type":"Services"
        }
    ],
    "sg:phone":"+61 3 6272 9332",
    "sg:postcode":"7009",
    "sg:province":"TAS",
    "sg:tags":[
        "towing"
    ],
    "wof:name":"Elite Towing & Cartage",
    "wof:placetype":"venue"
},
  "geometry": {"coordinates":[147.30291748100001,-42.8417892456],"type":"Point"}
}