{
  "type": "Feature",
  "properties": {
    "addr:full":"9 Toronto St Kelso NSW 2795",
    "addr:housenumber":"9",
    "addr:postcode":"2795",
    "addr:street":"Toronto St",
    "iso:country":"AU",
    "sg:address":"9 Toronto St",
    "sg:city":"Kelso",
    "sg:classifiers":[
        {
            "category":"Home & Garden",
            "subcategory":"Building Materials",
            "type":"Retail Goods"
        }
    ],
    "sg:phone":"+61 2 6331 2488",
    "sg:postcode":"2795",
    "sg:province":"NSW",
    "sg:tags":[
        "fencing"
    ],
    "wof:name":"A & A Wilding Pty Ltd",
    "wof:placetype":"venue"
},
  "geometry": {"coordinates":[149.605834961,-33.4242019653],"type":"Point"}
}