{
  "type": "Feature",
  "properties": {
    "iso:country":"AU",
    "sg:address":"Caravan St",
    "sg:city":"Wendouree",
    "sg:classifiers":[
        {
            "category":"Commercial Area",
            "type":"Public Place"
        }
    ],
    "sg:phone":"+61 3 5338 2187",
    "sg:postcode":"3355",
    "sg:province":"VIC",
    "sg:tags":[
        "heavy",
        "carrier"
    ],
    "wof:name":"K. T. Preston Pty. Ltd.",
    "wof:placetype":"venue"
},
  "geometry": {"coordinates":[143.814789,-37.530979],"type":"Point"}
}