{
  "type": "Feature",
  "properties": {
    "iso:country":"AU",
    "sg:address":"Unit 6, Cavehill Industrial Gardens, Cavehill Road",
    "sg:city":"Lilydale",
    "sg:classifiers":[
        {
            "category":"Retail",
            "subcategory":"Auto Repair",
            "type":"Services"
        }
    ],
    "sg:phone":"+61 3 9739 4999",
    "sg:postcode":"3140",
    "sg:province":"VIC",
    "sg:tags":[
        "gas",
        "conversion",
        "natural",
        "lp",
        "vehicle"
    ],
    "wof:name":"AG Auto Gas Conversions",
    "wof:placetype":"venue"
},
  "geometry": {"coordinates":[144.91778564399999,-37.6749191284],"type":"Point"}
}