{
  "type": "Feature",
  "properties": {
    "iso:country":"AU",
    "sg:address":"Cnr Gatton & Newton Sts",
    "sg:city":"Cairns",
    "sg:classifiers":[
        {
            "category":"Health Services",
            "subcategory":"Optometrist",
            "type":"Services"
        }
    ],
    "sg:phone":"+61 7 4031 1360",
    "sg:postcode":"4870",
    "sg:province":"QLD",
    "wof:name":"ProVision Optometrists",
    "wof:placetype":"venue"
},
  "geometry": {"coordinates":[145.74717712399999,-16.930513382],"type":"Point"}
}