{
  "type": "Feature",
  "properties": {
    "iso:country":"AU",
    "sg:address":"1 Markey St",
    "sg:city":"Eastwood",
    "sg:classifiers":[
        {
            "category":"Banks & Credit Unions",
            "subcategory":"Investment Brokerage",
            "type":"Services"
        }
    ],
    "sg:phone":"+61 8 8357 7824",
    "sg:postcode":"5063",
    "sg:province":"SA",
    "sg:tags":[
        "finance",
        "broker"
    ],
    "wof:name":"A A A Adelaide Finance Agency Pty Ltd",
    "wof:placetype":"venue"
},
  "geometry": {"coordinates":[138.622802734,-34.9447135925],"type":"Point"}
}