{
  "type": "Feature",
  "properties": {
    "iso:country":"AU",
    "sg:address":"8/ 97 Jijaws St",
    "sg:city":"Sumner Park",
    "sg:classifiers":[
        {
            "category":"Home & Garden",
            "subcategory":"Building Materials",
            "type":"Retail Goods"
        }
    ],
    "sg:phone":"+61 1800 240 766",
    "sg:postcode":"4074",
    "sg:province":"QLD",
    "sg:tags":[
        "shutter",
        "roller",
        "grille"
    ],
    "wof:name":"Sound & Safe Shutters",
    "wof:placetype":"venue"
},
  "geometry": {"coordinates":[152.93661499000001,-27.5611057281],"type":"Point"}
}