{
  "type": "Feature",
  "properties": {
    "iso:country":"AU",
    "sg:address":"Unit 103/ 781 Pacific Hwy",
    "sg:city":"Chatswood",
    "sg:classifiers":[
        {
            "category":"Education",
            "subcategory":"Special Training",
            "type":"Public Place"
        }
    ],
    "sg:phone":"+61 2 9884 9055",
    "sg:postcode":"2067",
    "sg:province":"NSW",
    "sg:tags":[
        "development"
    ],
    "wof:name":"ATS Training Systems",
    "wof:placetype":"venue"
},
  "geometry": {"coordinates":[151.17814636200001,-33.7962226868],"type":"Point"}
}