{
  "type": "Feature",
  "properties": {
    "addr:full":"\"Willendon\" 45 Grandview St Pymble NSW 2073",
    "addr:housenumber":"45",
    "addr:postcode":"2073",
    "addr:street":"Grandview St",
    "iso:country":"AU",
    "sg:address":"\"Willendon\" 45 Grandview St",
    "sg:city":"Pymble",
    "sg:classifiers":[
        {
            "category":"Health Services",
            "subcategory":"Dentist",
            "type":"Services"
        }
    ],
    "sg:phone":"+61 2 9449 6344",
    "sg:postcode":"2073",
    "sg:province":"NSW",
    "wof:name":"Iredale Stephen",
    "wof:placetype":"venue"
},
  "geometry": {"coordinates":[151.14454650900001,-33.7453155518],"type":"Point"}
}