{
  "type": "Feature",
  "properties": {
    "addr:full":"Shed 10, 110 Reichardt Rd Winnellie NT 0820",
    "addr:housenumber":"110",
    "addr:postcode":"nt 0820",
    "addr:street":"Reichardt Rd",
    "iso:country":"AU",
    "sg:address":"Shed 10, 110 Reichardt Rd",
    "sg:city":"Winnellie",
    "sg:classifiers":[
        {
            "category":"Retail",
            "subcategory":"Car Wash",
            "type":"Services"
        }
    ],
    "sg:phone":"+61 8 8947 1722",
    "sg:postcode":"0820",
    "sg:province":"NT",
    "sg:tags":[
        "truck",
        "cleaning"
    ],
    "wof:name":"T.T.S. Mobile Detailing",
    "wof:placetype":"venue"
},
  "geometry": {"coordinates":[130.869537353,-12.4287242889],"type":"Point"}
}