{
  "type": "Feature",
  "properties": {
    "addr:full":"298 Princes Hwy Dapto NSW 2530",
    "addr:housenumber":"298",
    "addr:postcode":"2530",
    "addr:street":"Princes Hwy",
    "iso:country":"AU",
    "sg:address":"298 Princes Hwy",
    "sg:city":"Dapto",
    "sg:classifiers":[
        {
            "category":"Home & Garden",
            "subcategory":"Building Materials",
            "type":"Retail Goods"
        }
    ],
    "sg:phone":"+61 2 4261 7295",
    "sg:postcode":"2530",
    "sg:province":"NSW",
    "sg:tags":[
        "merchant",
        "glass",
        "glazier"
    ],
    "wof:name":"Haines Glass & Glazing",
    "wof:placetype":"venue"
},
  "geometry": {"coordinates":[150.7862854,-34.5063362122],"type":"Point"}
}