{
  "type": "Feature",
  "properties": {
    "addr:full":"69 Seebeck Rd Rowville VIC 3178",
    "addr:housenumber":"69",
    "addr:postcode":"3178",
    "addr:street":"Seebeck Rd",
    "iso:country":"AU",
    "sg:address":"69 Seebeck Rd",
    "sg:city":"Rowville",
    "sg:classifiers":[
        {
            "category":"Personal",
            "subcategory":"Beauty Salon",
            "type":"Services"
        }
    ],
    "sg:phone":"+61 3 9795 6664",
    "sg:postcode":"3178",
    "sg:province":"VIC",
    "wof:name":"Sandys Beauty Clinic",
    "wof:placetype":"venue"
},
  "geometry": {"coordinates":[145.225372314,-37.9385948181],"type":"Point"}
}