{
  "type": "Feature",
  "properties": {
    "addr:full":"40 Clapham Rd Sefton NSW 2162",
    "addr:housenumber":"40",
    "addr:postcode":"2162",
    "addr:street":"Clapham Rd",
    "iso:country":"AU",
    "sg:address":"40 Clapham Rd",
    "sg:city":"Sefton",
    "sg:classifiers":[
        {
            "category":"Retail",
            "subcategory":"Auto Repair",
            "type":"Services"
        }
    ],
    "sg:phone":"+61 2 9645 4377",
    "sg:postcode":"2162",
    "sg:province":"NSW",
    "sg:tags":[
        "beater",
        "painter",
        "panel"
    ],
    "wof:name":"Hi Quality Smash Repairs",
    "wof:placetype":"venue"
},
  "geometry": {"coordinates":[151.01451110799999,-33.8838996887],"type":"Point"}
}