{
  "type": "Feature",
  "properties": {
    "addr:full":"Shop 29 Rhodes Waterside Shopping Centre, 1 Rider Blvd Rhodes NSW 2138",
    "addr:housenumber":"shop 29;1",
    "addr:postcode":"2138",
    "addr:street":"Rider Blvd",
    "iso:country":"AU",
    "sg:address":"Shop 29 Rhodes Waterside Shopping Centre, 1 Rider Blvd",
    "sg:city":"Rhodes",
    "sg:classifiers":[
        {
            "category":"Travel",
            "subcategory":"Travel Agent",
            "type":"Entertainment"
        }
    ],
    "sg:phone":"+61 2 8765 0088",
    "sg:postcode":"2138",
    "sg:province":"NSW",
    "sg:tags":[
        "consultant"
    ],
    "wof:name":"Escape Travel",
    "wof:placetype":"venue"
},
  "geometry": {"coordinates":[151.085327148,-33.8340110779],"type":"Point"}
}