{
  "type": "Feature",
  "properties": {
    "addr:full":"72 Capital Link Drv Campbellfield VIC 3061",
    "addr:housenumber":"72",
    "addr:postcode":"3061",
    "addr:street":"Capital Link Drv",
    "iso:country":"AU",
    "sg:address":"72 Capital Link Drv",
    "sg:city":"Campbellfield",
    "sg:classifiers":[
        {
            "category":"Home & Garden",
            "subcategory":"Hardware",
            "type":"Retail Goods"
        }
    ],
    "sg:phone":"+61 3 9357 9932",
    "sg:postcode":"3061",
    "sg:province":"VIC",
    "sg:tags":[
        "nut",
        "bolt"
    ],
    "wof:name":"Maptco Fasteners Aust Pty Ltd",
    "wof:placetype":"venue"
},
  "geometry": {"coordinates":[144.959884644,-37.6525154114],"type":"Point"}
}