{
  "type": "Feature",
  "properties": {
    "addr:full":"Shp16/ 353 Beaconsfield Tce Brighton QLD 4017",
    "addr:housenumber":"353",
    "addr:postcode":"4017",
    "addr:street":"Beaconsfield Tce",
    "iso:country":"AU",
    "sg:address":"Shp16/ 353",
    "sg:city":"Beaconsfield Tce Brighton",
    "sg:classifiers":[
        {
            "category":"Personal",
            "subcategory":"Beauty Salon",
            "type":"Services"
        }
    ],
    "sg:phone":"+61 7 3269 9422",
    "sg:postcode":"4017",
    "sg:province":"QLD",
    "wof:name":"Bright On Beauty",
    "wof:placetype":"venue"
},
  "geometry": {"coordinates":[153.06234741200001,-27.2929058075],"type":"Point"}
}