{
  "type": "Feature",
  "properties": {
    "iso:country":"AU",
    "sg:address":"19 Cattley St",
    "sg:city":"Burnie",
    "sg:classifiers":[
        {
            "category":"Banks & Credit Unions",
            "subcategory":"Financial Services",
            "type":"Services"
        }
    ],
    "sg:phone":"+61 3 6431 5703",
    "sg:postcode":"7320",
    "sg:province":"TAS",
    "sg:tags":[
        "finance",
        "motor",
        "vehicle"
    ],
    "wof:name":"SMA Finance Burnie",
    "wof:placetype":"venue"
},
  "geometry": {"coordinates":[145.907486,-41.050926],"type":"Point"}
}