{
  "type": "Feature",
  "properties": {
    "iso:country":"AU",
    "sg:address":"7 Panoramic Pl",
    "sg:city":"Whitfield",
    "sg:classifiers":[
        {
            "category":"Real Estate",
            "subcategory":"Surveying",
            "type":"Services"
        }
    ],
    "sg:phone":"+61 7 4032 1004",
    "sg:postcode":"4870",
    "sg:province":"QLD",
    "sg:tags":[
        "map",
        "mapping"
    ],
    "wof:name":"Panorama Publications",
    "wof:placetype":"venue"
},
  "geometry": {"coordinates":[145.72369384800001,-16.9051589966],"type":"Point"}
}