{
  "type": "Feature",
  "properties": {
    "addr:full":"Mail Service 1000 Maleny QLD 4552",
    "addr:postcode":"4552",
    "iso:country":"AU",
    "sg:address":"Mail Service 1000",
    "sg:city":"Maleny",
    "sg:classifiers":[
        {
            "category":"Professional",
            "subcategory":"Art Services",
            "type":"Services"
        }
    ],
    "sg:phone":"+61 7 5494 1845",
    "sg:postcode":"4552",
    "sg:province":"QLD",
    "sg:tags":[
        "commercial",
        "artist"
    ],
    "wof:name":"Cary Davies",
    "wof:placetype":"venue"
},
  "geometry": {"coordinates":[152.85955810600001,-26.7518482208],"type":"Point"}
}