{
  "type": "Feature",
  "properties": {
    "addr:full":"Shop 2/ 203 Pacific Hwy Charmhaven NSW 2263",
    "addr:housenumber":"shop 2 / 203",
    "addr:postcode":"2263",
    "addr:street":"Pacific Hwy",
    "iso:country":"AU",
    "sg:address":"Shop 2/ 203 Pacific Hwy",
    "sg:city":"Charmhaven",
    "sg:classifiers":[
        {
            "category":"Personal",
            "subcategory":"Beauty Salon",
            "type":"Services"
        }
    ],
    "sg:phone":"+61 2 4393 0981",
    "sg:postcode":"2263",
    "sg:province":"NSW",
    "sg:tags":[
        "hairdresser"
    ],
    "wof:name":"Swish Hair Design",
    "wof:placetype":"venue"
},
  "geometry": {"coordinates":[151.503174,-33.227802],"type":"Point"}
}