{
  "type": "Feature",
  "properties": {
    "iso:country":"AU",
    "sg:address":"Kanangra Drv",
    "sg:city":"Taree",
    "sg:classifiers":[
        {
            "category":"Arena",
            "subcategory":"Sports Club",
            "type":"Entertainment"
        }
    ],
    "sg:phone":"+61 2 6552 2082",
    "sg:postcode":"2430",
    "sg:province":"NSW",
    "sg:tags":[
        "hunt",
        "racing"
    ],
    "wof:name":"Taree Greyhound Racing Club Ltd",
    "wof:placetype":"venue"
},
  "geometry": {"coordinates":[152.465744,-31.901623],"type":"Point"}
}