{
  "type": "Feature",
  "properties": {
    "addr:full":"PO Box 257 South Melbourne VIC 8867",
    "addr:postcode":"8867",
    "iso:country":"AU",
    "sg:address":"PO Box 257",
    "sg:city":"South Melbourne",
    "sg:classifiers":[
        {
            "category":"Building & Trades",
            "subcategory":"Cleaning & Sanitation",
            "type":"Services"
        }
    ],
    "sg:phone":"+61 412 353 006",
    "sg:postcode":"8867",
    "sg:province":"VIC",
    "sg:tags":[
        "cleaner",
        "repairer",
        "roof"
    ],
    "wof:name":"Larkin Plumbing Services Pty Ltd",
    "wof:placetype":"venue"
},
  "geometry": {"coordinates":[144.960174561,-37.8345489502],"type":"Point"}
}