{
  "type": "Feature",
  "properties": {
    "addr:full":"14 Howard St Warners Bay NSW 2282",
    "addr:housenumber":"14",
    "addr:postcode":"2282",
    "addr:street":"Howard St",
    "iso:country":"AU",
    "sg:address":"14 Howard St",
    "sg:city":"Warners Bay",
    "sg:classifiers":[
        {
            "category":"Health Services",
            "subcategory":"Health Practitioner",
            "type":"Services"
        }
    ],
    "sg:phone":"+61 2 4947 2910",
    "sg:postcode":"2282",
    "sg:province":"NSW",
    "sg:tags":[
        "psychologist"
    ],
    "wof:name":"EDUCARE",
    "wof:placetype":"venue"
},
  "geometry": {"coordinates":[151.64596557600001,-32.9766273499],"type":"Point"}
}