{
  "type": "Feature",
  "properties": {
    "addr:full":"2nd Level 65 Murray St Hobart TAS 7000",
    "addr:housenumber":"65",
    "addr:postcode":"7000",
    "addr:street":"Murray St",
    "iso:country":"AU",
    "sg:address":"2nd Level 65 Murray St",
    "sg:city":"Hobart",
    "sg:classifiers":[
        {
            "category":"Education",
            "subcategory":"Special Training",
            "type":"Public Place"
        }
    ],
    "sg:phone":"+61 3 6234 1433",
    "sg:postcode":"7000",
    "sg:province":"TAS",
    "sg:tags":[
        "development"
    ],
    "wof:name":"Jenard Training & Personnel",
    "wof:placetype":"venue"
},
  "geometry": {"coordinates":[147.32594299300001,-42.882598877],"type":"Point"}
}