{
  "type": "Feature",
  "properties": {
    "addr:full":"11 McIntosh Drv Cannonvale QLD 4802",
    "addr:housenumber":"11",
    "addr:postcode":"4802",
    "addr:street":"Mcintosh Drv",
    "iso:country":"AU",
    "sg:address":"11 McIntosh Drv",
    "sg:city":"Cannonvale",
    "sg:classifiers":[
        {
            "category":"Manufacturing",
            "subcategory":"Building Materials",
            "type":"Manufacturing & Wholesale Goods"
        }
    ],
    "sg:phone":"+61 7 4946 4611",
    "sg:postcode":"4802",
    "sg:province":"QLD",
    "sg:tags":[
        "concrete",
        "product"
    ],
    "wof:name":"Airlie Concrete",
    "wof:placetype":"venue"
},
  "geometry": {"coordinates":[148.682250977,-20.2847557068],"type":"Point"}
}