{
  "type": "Feature",
  "properties": {
    "addr:full":"Garden Sq 643 Kessels Rd Upper Mt Gravatt QLD 4122",
    "addr:housenumber":"643",
    "addr:postcode":"4122",
    "addr:street":"Garden;Kessels Rd Upper",
    "iso:country":"AU",
    "sg:address":"Garden Sq 643 Kessels Rd",
    "sg:city":"Upper Mt Gravatt",
    "sg:classifiers":[
        {
            "category":"Banks & Credit Unions",
            "subcategory":"Investment Brokerage",
            "type":"Services"
        }
    ],
    "sg:phone":"+61 7 3340 3888",
    "sg:postcode":"4122",
    "sg:province":"QLD",
    "wof:name":"Insight Investment Services",
    "wof:placetype":"venue"
},
  "geometry": {"coordinates":[153.07606506400001,-27.5616912842],"type":"Point"}
}