{
  "type": "Feature",
  "properties": {
    "addr:full":"9 Aldenhoven Rd Lonsdale SA 5160",
    "addr:housenumber":"9",
    "addr:postcode":"5160",
    "addr:street":"Aldenhoven Rd",
    "iso:country":"AU",
    "sg:address":"9 Aldenhoven Rd",
    "sg:city":"Lonsdale",
    "sg:classifiers":[
        {
            "category":"Home & Garden",
            "subcategory":"Garden Supply",
            "type":"Retail Goods"
        }
    ],
    "sg:phone":"+61 8 8384 4374",
    "sg:postcode":"5160",
    "sg:province":"SA",
    "sg:tags":[
        "nursery"
    ],
    "wof:name":"Austwan Enterprise",
    "wof:placetype":"venue"
},
  "geometry": {"coordinates":[138.49667358400001,-35.1115760803],"type":"Point"}
}