{
  "type": "Feature",
  "properties": {
    "iso:country":"AU",
    "sg:address":"395 Station St",
    "sg:city":"Carlton North",
    "sg:classifiers":[
        {
            "category":"Health Services",
            "subcategory":"Health Practitioner",
            "type":"Services"
        }
    ],
    "sg:phone":"+61 3 9347 5083",
    "sg:postcode":"3054",
    "sg:province":"VIC",
    "sg:tags":[
        "psychologist"
    ],
    "wof:name":"McIndoe Rosemary",
    "wof:placetype":"venue"
},
  "geometry": {"coordinates":[144.975509644,-37.7875938416],"type":"Point"}
}