{
  "type": "Feature",
  "properties": {
    "iso:country":"AU",
    "sg:address":"68 Denham St",
    "sg:city":"Rockhampton",
    "sg:classifiers":[
        {
            "category":"Personal",
            "subcategory":"Beauty Salon",
            "type":"Services"
        }
    ],
    "sg:phone":"+61 7 4922 7227",
    "sg:postcode":"4700",
    "sg:province":"QLD",
    "sg:tags":[
        "hairdresser"
    ],
    "wof:name":"Maree Crow's Hairdressing",
    "wof:placetype":"venue"
},
  "geometry": {"coordinates":[150.498657227,-23.3876018524],"type":"Point"}
}