{
  "type": "Feature",
  "properties": {
    "addr:full":"15 Yao St Kingscliff NSW 2487",
    "addr:housenumber":"15",
    "addr:postcode":"2487",
    "addr:street":"Yao St",
    "iso:country":"AU",
    "sg:address":"15 Yao St",
    "sg:city":"Kingscliff",
    "sg:classifiers":[
        {
            "category":"Utilities",
            "subcategory":"Electric",
            "type":"Services"
        }
    ],
    "sg:phone":"+61 2 6674 1366",
    "sg:postcode":"2487",
    "sg:province":"NSW",
    "sg:tags":[
        "electrical",
        "contractor"
    ],
    "wof:name":"Peter Quinlivan Electrical Service",
    "wof:placetype":"venue"
},
  "geometry": {"coordinates":[153.565719605,-28.2420711517],"type":"Point"}
}