{
  "type": "Feature",
  "properties": {
    "addr:full":"26 Victoria St Bunbury WA 6230",
    "addr:housenumber":"26",
    "addr:postcode":"6230",
    "addr:street":"Victoria St",
    "iso:country":"AU",
    "sg:address":"26 Victoria St",
    "sg:city":"Bunbury",
    "sg:classifiers":[
        {
            "category":"Professional",
            "subcategory":"Printing & Photocopies",
            "type":"Services"
        }
    ],
    "sg:phone":"+61 8 9721 4543",
    "sg:postcode":"6230",
    "sg:province":"WA",
    "sg:tags":[
        "trophy"
    ],
    "wof:name":"Trophies West",
    "wof:placetype":"venue"
},
  "geometry": {"coordinates":[115.637123,-33.322376],"type":"Point"}
}