{
  "type": "Feature",
  "properties": {
    "addr:full":"Maroochydore Rd Buderim QLD 4556",
    "addr:postcode":"4556",
    "addr:street":"Maroochydore Rd",
    "iso:country":"AU",
    "sg:address":"Maroochydore Rd",
    "sg:city":"Buderim",
    "sg:classifiers":[
        {
            "category":"Farming",
            "subcategory":"Nursery",
            "type":"Manufacturing & Wholesale Goods"
        }
    ],
    "sg:phone":"+61 7 5445 4283",
    "sg:postcode":"4556",
    "sg:province":"QLD",
    "wof:name":"Martins Creek Tree Farm",
    "wof:placetype":"venue"
},
  "geometry": {"coordinates":[153.06132507300001,-26.6629047394],"type":"Point"}
}