{
  "type": "Feature",
  "properties": {
    "iso:country":"AU",
    "sg:address":"18a Miller St",
    "sg:city":"Gilgandra",
    "sg:classifiers":[
        {
            "category":"Food & Beverages",
            "subcategory":"Bakery",
            "type":"Retail Goods"
        }
    ],
    "sg:phone":"+61 2 6847 1774",
    "sg:postcode":"2827",
    "sg:province":"NSW",
    "sg:tags":[
        "cake",
        "shop",
        "pastry"
    ],
    "wof:name":"Rock Cake Bakery",
    "wof:placetype":"venue"
},
  "geometry": {"coordinates":[148.66531372099999,-31.7130699158],"type":"Point"}
}