{
  "type": "Feature",
  "properties": {
    "addr:full":"2A Brisbane St Harris Park NSW 2150",
    "addr:housenumber":"2a",
    "addr:postcode":"2150",
    "addr:street":"Brisbane St",
    "iso:country":"AU",
    "sg:address":"2A Brisbane St",
    "sg:city":"Harris Park",
    "sg:classifiers":[
        {
            "category":"Professional",
            "subcategory":"Art Services",
            "type":"Services"
        }
    ],
    "sg:phone":"+61 2 9760 2178",
    "sg:postcode":"2150",
    "sg:province":"NSW",
    "sg:tags":[
        "graphic",
        "designer"
    ],
    "wof:name":"Silence Design",
    "wof:placetype":"venue"
},
  "geometry": {"coordinates":[151.01333618199999,-33.8242797852],"type":"Point"}
}