{
  "type": "Feature",
  "properties": {
    "iso:country":"AU",
    "sg:address":"17 Bonville St",
    "sg:city":"Urunga",
    "sg:classifiers":[
        {
            "category":"Real Estate",
            "subcategory":"Real Estate Agent",
            "type":"Services"
        }
    ],
    "sg:phone":"+61 2 6655 6616",
    "sg:postcode":"2455",
    "sg:province":"NSW",
    "wof:name":"Kilbornes First National",
    "wof:placetype":"venue"
},
  "geometry": {"coordinates":[153.02058400000001,-30.496817],"type":"Point"}
}