{
  "type": "Feature",
  "properties": {
    "iso:country":"AU",
    "sg:address":"783- 787 Sydney Rd",
    "sg:city":"Brunswick",
    "sg:classifiers":[
        {
            "category":"Shopping",
            "type":"Retail Goods"
        }
    ],
    "sg:phone":"+61 3 9383 4144",
    "sg:postcode":"3056",
    "sg:province":"VIC",
    "sg:tags":[
        "clearance",
        "factory",
        "outlet"
    ],
    "wof:name":"Holeproof Clearance Outlets",
    "wof:placetype":"venue"
},
  "geometry": {"coordinates":[144.96348571799999,-37.7581863403],"type":"Point"}
}