{
  "type": "Feature",
  "properties": {
    "addr:full":"3/42- 44 Albemarle St Williamstown VIC 3016",
    "addr:housenumber":"/;44",
    "addr:postcode":"3016",
    "addr:street":"42;Albemarle St",
    "iso:country":"AU",
    "sg:address":"3/42- 44 Albemarle St",
    "sg:city":"Williamstown",
    "sg:classifiers":[
        {
            "category":"Retail",
            "subcategory":"Auto Repair",
            "type":"Services"
        }
    ],
    "sg:phone":"+61 3 9397 1185",
    "sg:postcode":"3016",
    "sg:province":"VIC",
    "sg:tags":[
        "repairer",
        "motor",
        "engineer"
    ],
    "wof:name":"Williamstown Motors",
    "wof:placetype":"venue"
},
  "geometry": {"coordinates":[144.86155700699999,-37.8505134583],"type":"Point"}
}