{
  "type": "Feature",
  "properties": {
    "addr:full":"25 Ryde Rd Pymble NSW 2073",
    "addr:housenumber":"25",
    "addr:postcode":"2073",
    "addr:street":"Ryde Rd",
    "iso:country":"AU",
    "sg:address":"25 Ryde Rd",
    "sg:city":"Pymble",
    "sg:classifiers":[
        {
            "category":"Professional",
            "subcategory":"Computer Services",
            "type":"Services"
        }
    ],
    "sg:phone":"+61 2 9418 2900",
    "sg:postcode":"2073",
    "sg:province":"NSW",
    "sg:tags":[
        "consultant",
        "system"
    ],
    "wof:name":"Strategic Software",
    "wof:placetype":"venue"
},
  "geometry": {"coordinates":[151.14353942899999,-33.752204895],"type":"Point"}
}