{
  "type": "Feature",
  "properties": {
    "addr:full":"108 Morrison Rd Gladesville NSW 2111",
    "addr:housenumber":"108",
    "addr:postcode":"2111",
    "addr:street":"Morrison Rd",
    "iso:country":"AU",
    "sg:address":"108 Morrison Rd",
    "sg:city":"Gladesville",
    "sg:classifiers":[
        {
            "category":"Education",
            "subcategory":"Special Training",
            "type":"Public Place"
        }
    ],
    "sg:phone":"+61 2 9817 4036",
    "sg:postcode":"2111",
    "sg:province":"NSW",
    "sg:tags":[
        "development"
    ],
    "wof:name":"WildHiland Communications",
    "wof:placetype":"venue"
},
  "geometry": {"coordinates":[151.11843872099999,-33.8285675049],"type":"Point"}
}