{
  "type": "Feature",
  "properties": {
    "iso:country":"AU",
    "sg:address":"50 Hambleton St (Cnr Mills )",
    "sg:city":"Albert Park",
    "sg:classifiers":[
        {
            "category":"Health Services",
            "subcategory":"Health Practitioner",
            "type":"Services"
        }
    ],
    "sg:phone":"+61 3 9699 7798",
    "sg:postcode":"3206",
    "sg:province":"VIC",
    "sg:tags":[
        "osteopath"
    ],
    "wof:name":"Galinas John Dr",
    "wof:placetype":"venue"
},
  "geometry": {"coordinates":[144.958557,-37.846432],"type":"Point"}
}