{
  "type": "Feature",
  "properties": {
    "addr:full":"33c Blythe Ave Yokine WA 6060",
    "addr:housenumber":"33c",
    "addr:postcode":"6060",
    "addr:street":"Blythe Ave",
    "iso:country":"AU",
    "sg:address":"33c Blythe Ave",
    "sg:city":"Yokine",
    "sg:classifiers":[
        {
            "category":"Fast Food",
            "type":"Food & Drink"
        }
    ],
    "sg:phone":"+61 8 9444 2855",
    "sg:postcode":"6060",
    "sg:province":"WA",
    "sg:tags":[
        "away",
        "take"
    ],
    "wof:name":"Blythe Ave Fish Supply",
    "wof:placetype":"venue"
},
  "geometry": {"coordinates":[115.85088348399999,-31.9016456604],"type":"Point"}
}