{
  "type": "Feature",
  "properties": {
    "iso:country":"AU",
    "sg:address":"1 / 1 Burton St",
    "sg:city":"Vincentia",
    "sg:classifiers":[
        {
            "category":"Real Estate",
            "subcategory":"Real Estate Agent",
            "type":"Services"
        }
    ],
    "sg:phone":"+61 2 4441 6400",
    "sg:postcode":"2540",
    "sg:province":"NSW",
    "wof:name":"Ray White Jervis Bay",
    "wof:placetype":"venue"
},
  "geometry": {"coordinates":[150.67489624000001,-35.070690155],"type":"Point"}
}