{
  "type": "Feature",
  "properties": {
    "addr:full":"43 Mornington Tyabb Rd Mornington VIC 3931",
    "addr:housenumber":"43",
    "addr:postcode":"3931",
    "addr:street":"Mornington Tyabb Rd",
    "iso:country":"AU",
    "sg:address":"43 Mornington Tyabb Rd",
    "sg:city":"Mornington",
    "sg:classifiers":[
        {
            "category":"Autos & Motor Vehicles",
            "subcategory":"Auto Supplies",
            "type":"Retail Goods"
        }
    ],
    "sg:phone":"+61 3 5975 6023",
    "sg:postcode":"3931",
    "sg:province":"VIC",
    "sg:tags":[
        "tyre"
    ],
    "wof:name":"Kettle's Discount Tyres",
    "wof:placetype":"venue"
},
  "geometry": {"coordinates":[145.048461914,-38.2336807251],"type":"Point"}
}