{
  "type": "Feature",
  "properties": {
    "addr:full":"180 Hogan St Tatura VIC 3616",
    "addr:housenumber":"180",
    "addr:postcode":"3616",
    "addr:street":"Hogan St",
    "iso:country":"AU",
    "sg:address":"180 Hogan St",
    "sg:city":"Tatura",
    "sg:classifiers":[
        {
            "category":"Retail",
            "subcategory":"Auto Repair",
            "type":"Services"
        }
    ],
    "sg:phone":"+61 3 5824 1945",
    "sg:postcode":"3616",
    "sg:province":"VIC",
    "sg:tags":[
        "repairer",
        "motor",
        "engineer"
    ],
    "wof:name":"Mobil Service Centre",
    "wof:placetype":"venue"
},
  "geometry": {"coordinates":[145.23104858400001,-36.4399757385],"type":"Point"}
}