{
  "type": "Feature",
  "properties": {
    "addr:full":"Sydney Rd Bathurst NSW 2795",
    "addr:postcode":"2795",
    "addr:street":"Sydney Rd",
    "iso:country":"AU",
    "sg:address":"Sydney Rd",
    "sg:city":"Bathurst",
    "sg:classifiers":[
        {
            "category":"Professional",
            "subcategory":"Engineering",
            "type":"Services"
        }
    ],
    "sg:phone":"+61 2 6332 7800",
    "sg:postcode":"2795",
    "sg:province":"NSW",
    "sg:tags":[
        "engineer"
    ],
    "wof:name":"Edi Rail",
    "wof:placetype":"venue"
},
  "geometry": {"coordinates":[149.58589172399999,-33.4180145264],"type":"Point"}
}