{
  "type": "Feature",
  "properties": {
    "iso:country":"AU",
    "sg:address":"667 Pascoe Vale Rd",
    "sg:city":"Oak Park",
    "sg:classifiers":[
        {
            "category":"Social Services",
            "subcategory":"Child Care",
            "type":"Services"
        }
    ],
    "sg:phone":"+61 3 9304 2922",
    "sg:postcode":"3046",
    "sg:province":"VIC",
    "wof:name":"Oak Park Children's Centre",
    "wof:placetype":"venue"
},
  "geometry": {"coordinates":[144.917236328,-37.7138366699],"type":"Point"}
}