{
  "type": "Feature",
  "properties": {
    "addr:full":"2 Kangerong Rd Box Hill VIC 3128",
    "addr:housenumber":"2",
    "addr:postcode":"3128",
    "addr:street":"Kangerong Rd",
    "iso:country":"AU",
    "sg:address":"2 Kangerong Rd",
    "sg:city":"Box Hill",
    "sg:classifiers":[
        {
            "category":"Health Services",
            "subcategory":"Dentist",
            "type":"Services"
        }
    ],
    "sg:phone":"+61 3 9898 6701",
    "sg:postcode":"3128",
    "sg:province":"VIC",
    "wof:name":"Soh L L",
    "wof:placetype":"venue"
},
  "geometry": {"coordinates":[145.12759399399999,-37.8182144165],"type":"Point"}
}