{
  "type": "Feature",
  "properties": {
    "iso:country":"AU",
    "sg:address":"98 Commercial Rd",
    "sg:city":"Port Adelaide",
    "sg:classifiers":[
        {
            "category":"Food & Beverages",
            "subcategory":"Bakery",
            "type":"Retail Goods"
        }
    ],
    "sg:phone":"+61 8 8241 1311",
    "sg:postcode":"5015",
    "sg:province":"SA",
    "sg:tags":[
        "baker"
    ],
    "wof:name":"Filipino Bakehaus & Asian Groceries",
    "wof:placetype":"venue"
},
  "geometry": {"coordinates":[138.505767822,-34.8453292847],"type":"Point"}
}