{
  "type": "Feature",
  "properties": {
    "addr:full":"22 Stephenson St Crookwell NSW 2583",
    "addr:housenumber":"22",
    "addr:postcode":"2583",
    "addr:street":"Stephenson St",
    "iso:country":"AU",
    "sg:address":"22 Stephenson St",
    "sg:city":"Crookwell",
    "sg:classifiers":[
        {
            "category":"Professional",
            "subcategory":"Business Services",
            "type":"Services"
        }
    ],
    "sg:phone":"+61 2 4832 2192",
    "sg:postcode":"2583",
    "sg:province":"NSW",
    "sg:tags":[
        "livestock",
        "transport"
    ],
    "wof:name":"Thorn Andrew",
    "wof:placetype":"venue"
},
  "geometry": {"coordinates":[149.455734253,-34.4587554932],"type":"Point"}
}