{
  "type": "Feature",
  "properties": {
    "addr:full":"499 Bridge St Toowoomba QLD 4350",
    "addr:housenumber":"499",
    "addr:postcode":"4350",
    "addr:street":"Bridge St",
    "iso:country":"AU",
    "sg:address":"499 Bridge St",
    "sg:city":"Toowoomba",
    "sg:classifiers":[
        {
            "category":"Building & Trades",
            "subcategory":"Cleaning & Sanitation",
            "type":"Services"
        }
    ],
    "sg:phone":"+61 1800 807 057",
    "sg:postcode":"4350",
    "sg:province":"QLD",
    "sg:tags":[
        "industrial",
        "commercial",
        "contractor"
    ],
    "wof:name":"Eaton Services Group",
    "wof:placetype":"venue"
},
  "geometry": {"coordinates":[151.89845299999999,-27.532795],"type":"Point"}
}