{
  "type": "Feature",
  "properties": {
    "addr:full":"7 Terminus St Grange SA 5022",
    "addr:housenumber":"7",
    "addr:postcode":"5022",
    "addr:street":"Terminus St",
    "iso:country":"AU",
    "sg:address":"7 Terminus St",
    "sg:city":"Grange",
    "sg:classifiers":[
        {
            "category":"Personal",
            "type":"Services"
        }
    ],
    "sg:phone":"+61 407 868 433",
    "sg:postcode":"5022",
    "sg:province":"SA",
    "sg:tags":[
        "reducing",
        "treatment",
        "weight"
    ],
    "wof:name":"Herbalife Australasia Grange",
    "wof:placetype":"venue"
},
  "geometry": {"coordinates":[138.492477417,-34.8998718262],"type":"Point"}
}