{
  "type": "Feature",
  "properties": {
    "addr:full":"Shop 4 /188- 192 Margaret St Toowoomba QLD 4350",
    "addr:housenumber":"shop 4 / 188 192",
    "addr:postcode":"4350",
    "addr:street":"Margaret St",
    "iso:country":"AU",
    "sg:address":"Shop 4 /188- 192 Margaret St",
    "sg:city":"Toowoomba",
    "sg:classifiers":[
        {
            "category":"Shopping",
            "subcategory":"Clothing, Apparel, & Fashions",
            "type":"Retail Goods"
        }
    ],
    "sg:phone":"+61 7 4638 5400",
    "sg:postcode":"4350",
    "sg:province":"QLD",
    "sg:tags":[
        "maternity",
        "wear"
    ],
    "wof:name":"My Bump Maternity",
    "wof:placetype":"venue"
},
  "geometry": {"coordinates":[151.953934,-27.561209],"type":"Point"}
}