{
  "type": "Feature",
  "properties": {
    "addr:full":"129 Bentinck St Bathurst NSW 2795",
    "addr:housenumber":"129",
    "addr:postcode":"2795",
    "addr:street":"Bentinck St",
    "iso:country":"AU",
    "sg:address":"129 Bentinck St",
    "sg:city":"Bathurst",
    "sg:classifiers":[
        {
            "category":"Communications",
            "subcategory":"Film & Video Production",
            "type":"Services"
        }
    ],
    "sg:phone":"+61 2 6332 6266",
    "sg:postcode":"2795",
    "sg:province":"NSW",
    "sg:tags":[
        "dvd",
        "library"
    ],
    "wof:name":"Video Ezy Bathurst",
    "wof:placetype":"venue"
},
  "geometry": {"coordinates":[149.58001709000001,-33.4210662842],"type":"Point"}
}