{
  "type": "Feature",
  "properties": {
    "iso:country":"AU",
    "sg:address":"648 Pascoe Vale Rd",
    "sg:city":"Oak Park",
    "sg:classifiers":[
        {
            "category":"Health Services",
            "subcategory":"Chiropractor",
            "type":"Services"
        }
    ],
    "sg:phone":"+61 3 9306 7581",
    "sg:postcode":"3046",
    "sg:province":"VIC",
    "wof:name":"Oak Park Chiropractic Clinic",
    "wof:placetype":"venue"
},
  "geometry": {"coordinates":[144.919998169,-37.717830658],"type":"Point"}
}