{
  "type": "Feature",
  "properties": {
    "iso:country":"AU",
    "sg:address":"122 Kelly St",
    "sg:city":"Scone",
    "sg:classifiers":[
        {
            "category":"Structure",
            "subcategory":"Office Building",
            "type":"Public Place"
        }
    ],
    "sg:phone":"+61 2 6544 3000",
    "sg:postcode":"2337",
    "sg:province":"NSW",
    "sg:tags":[
        "serviced"
    ],
    "wof:name":"The Office Group Pty Ltd",
    "wof:placetype":"venue"
},
  "geometry": {"coordinates":[150.86813354500001,-32.0487709045],"type":"Point"}
}