{
  "type": "Feature",
  "properties": {
    "iso:country":"AU",
    "sg:address":"40 Blenheim St",
    "sg:city":"Chermside West",
    "sg:classifiers":[
        {
            "category":"Professional",
            "subcategory":"Art Services",
            "type":"Services"
        }
    ],
    "sg:phone":"+61 7 3256 3330",
    "sg:postcode":"4032",
    "sg:province":"QLD",
    "sg:tags":[
        "decorator",
        "painter"
    ],
    "wof:name":"Pezzimenti Painters",
    "wof:placetype":"venue"
},
  "geometry": {"coordinates":[153.016464,-27.391506],"type":"Point"}
}