{
  "type": "Feature",
  "properties": {
    "iso:country":"AU",
    "sg:address":"13 Buckland Crt",
    "sg:city":"Endeavour Hills",
    "sg:classifiers":[
        {
            "category":"Retail",
            "subcategory":"Car Wash",
            "type":"Services"
        }
    ],
    "sg:phone":"+61 13 15 46",
    "sg:postcode":"3802",
    "sg:province":"VIC",
    "sg:tags":[
        "truck",
        "cleaning"
    ],
    "wof:name":"Jims Car Cleaning",
    "wof:placetype":"venue"
},
  "geometry": {"coordinates":[145.249725342,-37.9677963257],"type":"Point"}
}