{
  "type": "Feature",
  "properties": {
    "addr:full":"Shop 28, Stockland Supercentre Glendale NSW 2285",
    "addr:housenumber":"shop 28",
    "addr:postcode":"2285",
    "iso:country":"AU",
    "sg:address":"Shop 28, Stockland Supercentre",
    "sg:city":"Glendale",
    "sg:classifiers":[
        {
            "category":"Banks & Credit Unions",
            "subcategory":"Financial Services",
            "type":"Services"
        }
    ],
    "sg:phone":"+61 2 4921 9982",
    "sg:postcode":"2285",
    "sg:province":"NSW",
    "sg:tags":[
        "building",
        "society"
    ],
    "wof:name":"Greater Building Society Ltd",
    "wof:placetype":"venue"
},
  "geometry": {"coordinates":[151.651443481,-32.927406311],"type":"Point"}
}