{
  "type": "Feature",
  "properties": {
    "addr:full":"47 Whitbread St Taree NSW 2430",
    "addr:housenumber":"47",
    "addr:postcode":"2430",
    "addr:street":"Whitbread St",
    "iso:country":"AU",
    "sg:address":"47 Whitbread St",
    "sg:city":"Taree",
    "sg:classifiers":[
        {
            "category":"Shopping",
            "subcategory":"Pets & Pet Supplies",
            "type":"Retail Goods"
        }
    ],
    "sg:phone":"+61 2 6552 5381",
    "sg:postcode":"2430",
    "sg:province":"NSW",
    "sg:tags":[
        "equipment",
        "ceramic"
    ],
    "wof:name":"Taree Hobby Ceramics",
    "wof:placetype":"venue"
},
  "geometry": {"coordinates":[152.459305,-31.906721],"type":"Point"}
}