{
  "type": "Feature",
  "properties": {
    "iso:country":"AU",
    "sg:address":"Ridge Rd",
    "sg:city":"Tilba Tilba",
    "sg:classifiers":[
        {
            "category":"Retail",
            "subcategory":"Laundry & Dry Cleaning",
            "type":"Services"
        }
    ],
    "sg:phone":"+61 2 4473 7401",
    "sg:postcode":"2546",
    "sg:province":"NSW",
    "sg:tags":[
        "wholesaler",
        "underclothing",
        "mfrs"
    ],
    "wof:name":"Downunders Pty Ltd",
    "wof:placetype":"venue"
},
  "geometry": {"coordinates":[150.063400269,-36.2826919556],"type":"Point"}
}