{
  "type": "Feature",
  "properties": {
    "iso:country":"AU",
    "sg:address":"Morrison Rd",
    "sg:city":"Gladesville",
    "sg:classifiers":[
        {
            "category":"Banks & Credit Unions",
            "subcategory":"Investment Brokerage",
            "type":"Services"
        }
    ],
    "sg:phone":"+61 2 9802 7666",
    "sg:postcode":"2111",
    "sg:province":"NSW",
    "sg:tags":[
        "shutter",
        "louvre"
    ],
    "wof:name":"AA. Allstar Timber Shutters & Blinds",
    "wof:placetype":"venue"
},
  "geometry": {"coordinates":[151.124633789,-33.8337783813],"type":"Point"}
}