{
  "type": "Feature",
  "properties": {
    "iso:country":"AU",
    "sg:address":"5 Torio Pl",
    "sg:city":"Runaway Bay",
    "sg:classifiers":[
        {
            "category":"Building & Trades",
            "subcategory":"Cleaning & Sanitation",
            "type":"Services"
        }
    ],
    "sg:phone":"+61 408 448 528",
    "sg:postcode":"4216",
    "sg:province":"QLD",
    "sg:tags":[
        "commercial",
        "maintenance"
    ],
    "wof:name":"Bill Bugelli Plasterer",
    "wof:placetype":"venue"
},
  "geometry": {"coordinates":[153.40583801299999,-27.9055843353],"type":"Point"}
}