{
  "type": "Feature",
  "properties": {
    "addr:full":"923 Bourke Rd Waterloo NSW 1440",
    "addr:housenumber":"923",
    "addr:postcode":"1440",
    "addr:street":"Bourke Rd",
    "iso:country":"AU",
    "sg:address":"923 Bourke Rd",
    "sg:city":"Waterloo",
    "sg:classifiers":[
        {
            "category":"Retail",
            "subcategory":"Auto Repair",
            "type":"Services"
        }
    ],
    "sg:phone":"+61 2 9358 5444",
    "sg:postcode":"1440",
    "sg:province":"NSW",
    "sg:tags":[
        "wheel",
        "balancing",
        "alignment"
    ],
    "wof:name":"Spinning Wheel Tyres",
    "wof:placetype":"venue"
},
  "geometry": {"coordinates":[151.20614624000001,-33.9003982544],"type":"Point"}
}