{
  "type": "Feature",
  "properties": {
    "iso:country":"AU",
    "sg:address":"Unit 5/ 101 Spencer St",
    "sg:city":"Bunbury",
    "sg:classifiers":[
        {
            "category":"Social Services",
            "type":"Services"
        }
    ],
    "sg:phone":"+61 8 9791 2255",
    "sg:postcode":"6230",
    "sg:province":"WA",
    "sg:tags":[
        "kinesiology"
    ],
    "wof:name":"Blue Sky Therapy & Training",
    "wof:placetype":"venue"
},
  "geometry": {"coordinates":[115.641571,-33.346577],"type":"Point"}
}