{
  "type": "Feature",
  "properties": {
    "addr:full":"33 Reid Rd Perth Airport WA 6105",
    "addr:housenumber":"33",
    "addr:postcode":"6105",
    "addr:street":"Reid Rd",
    "iso:country":"AU",
    "sg:address":"33 Reid Rd",
    "sg:city":"Perth Airport",
    "sg:classifiers":[
        {
            "category":"Mining & Drilling",
            "type":"Manufacturing & Wholesale Goods"
        }
    ],
    "sg:phone":"+61 8 9262 9700",
    "sg:postcode":"6105",
    "sg:province":"WA",
    "sg:tags":[
        "equipment",
        "quarrying",
        "supply"
    ],
    "wof:name":"Atlas Copco Construction & Mining Australia",
    "wof:placetype":"venue"
},
  "geometry": {"coordinates":[115.964370727,-31.9693336487],"type":"Point"}
}