{
  "type": "Feature",
  "properties": {
    "addr:full":"4 Cameron St Lidcombe NSW 2141",
    "addr:housenumber":"4",
    "addr:postcode":"2141",
    "addr:street":"Cameron St",
    "iso:country":"AU",
    "sg:address":"4 Cameron St",
    "sg:city":"Lidcombe",
    "sg:classifiers":[
        {
            "category":"Professional",
            "subcategory":"Art Services",
            "type":"Services"
        }
    ],
    "sg:phone":"+61 2 9702 1808",
    "sg:postcode":"2141",
    "sg:province":"NSW",
    "sg:tags":[
        "decorator",
        "painter"
    ],
    "wof:name":"J L Master Painters",
    "wof:placetype":"venue"
},
  "geometry": {"coordinates":[151.037109375,-33.865562439],"type":"Point"}
}