{
  "type": "Feature",
  "properties": {
    "iso:country":"AU",
    "sg:address":"615 Wooroora Rd",
    "sg:city":"Ravenshoe",
    "sg:classifiers":[
        {
            "category":"Building & Trades",
            "subcategory":"Construction",
            "type":"Services"
        }
    ],
    "sg:phone":"+61 7 4097 7011",
    "sg:postcode":"4872",
    "sg:province":"QLD",
    "sg:tags":[
        "fitting",
        "line",
        "electric",
        "power"
    ],
    "wof:name":"Millstream Electrical",
    "wof:placetype":"venue"
},
  "geometry": {"coordinates":[145.44342040999999,-17.6592884064],"type":"Point"}
}