{
  "type": "Feature",
  "properties": {
    "addr:full":"9 King St Stuart Park NT 0820",
    "addr:housenumber":"9",
    "addr:postcode":"0820",
    "addr:street":"King St",
    "iso:country":"AU",
    "sg:address":"9 King St",
    "sg:city":"Stuart Park",
    "sg:classifiers":[
        {
            "category":"Mining & Drilling",
            "type":"Manufacturing & Wholesale Goods"
        }
    ],
    "sg:phone":"+61 8 8981 8964",
    "sg:postcode":"0820",
    "sg:province":"NT",
    "sg:tags":[
        "geologist"
    ],
    "wof:name":"Rocksearch Australia",
    "wof:placetype":"venue"
},
  "geometry": {"coordinates":[130.842697144,-12.4490919113],"type":"Point"}
}