{
  "type": "Feature",
  "properties": {
    "addr:full":"Melbourne Depot Railroad Transport 1 Cawley Road Brooklyn VIC 3012",
    "addr:housenumber":"1",
    "addr:postcode":"3012",
    "addr:street":"Cawley Road",
    "iso:country":"AU",
    "sg:address":"Melbourne Depot Railroad Transport 1 Cawley Road",
    "sg:city":"Brooklyn",
    "sg:classifiers":[
        {
            "category":"Professional",
            "type":"Services"
        }
    ],
    "sg:phone":"+61 3 9314 9322",
    "sg:postcode":"3012",
    "sg:province":"VIC",
    "sg:tags":[
        "transport"
    ],
    "wof:name":"Aray Transport",
    "wof:placetype":"venue"
},
  "geometry": {"coordinates":[144.86033630399999,-37.8202285767],"type":"Point"}
}