{
  "type": "Feature",
  "properties": {
    "addr:full":"12 McKay Ave Leeton NSW 2705",
    "addr:housenumber":"12",
    "addr:postcode":"2705",
    "addr:street":"Mckay Ave",
    "iso:country":"AU",
    "sg:address":"12 McKay Ave",
    "sg:city":"Leeton",
    "sg:classifiers":[
        {
            "category":"Commercial Area",
            "type":"Public Place"
        }
    ],
    "sg:phone":"+61 2 6953 5099",
    "sg:postcode":"2705",
    "sg:province":"NSW",
    "sg:tags":[
        "heavy",
        "carrier"
    ],
    "wof:name":"George DePaoli Transport",
    "wof:placetype":"venue"
},
  "geometry": {"coordinates":[146.38877868599999,-34.55052948],"type":"Point"}
}