{
  "type": "Feature",
  "properties": {
    "iso:country":"AU",
    "sg:address":"18 Violet St",
    "sg:city":"Chatswood",
    "sg:classifiers":[
        {
            "category":"Professional",
            "subcategory":"Employment Agencies",
            "type":"Services"
        }
    ],
    "sg:phone":"+61 2 9411 1682",
    "sg:postcode":"2067",
    "sg:province":"NSW",
    "sg:tags":[
        "provider",
        "internet"
    ],
    "wof:name":"John Yu",
    "wof:placetype":"venue"
},
  "geometry": {"coordinates":[151.182983398,-33.7915000916],"type":"Point"}
}