{
  "type": "Feature",
  "properties": {
    "iso:country":"AU",
    "sg:address":"49 Joslin St",
    "sg:city":"Kotara South",
    "sg:classifiers":[
        {
            "category":"Fast Food",
            "type":"Food & Drink"
        }
    ],
    "sg:phone":"+61 2 4965 5677",
    "sg:postcode":"2289",
    "sg:province":"NSW",
    "sg:tags":[
        "away",
        "take"
    ],
    "wof:name":"Fish &#039;N&#039; Bits",
    "wof:placetype":"venue"
},
  "geometry": {"coordinates":[151.698944092,-32.944858551],"type":"Point"}
}