{
  "type": "Feature",
  "properties": {
    "iso:country":"AU",
    "sg:address":"Sunshine Hospital 176 Furlong Rd",
    "sg:city":"St Albans",
    "sg:classifiers":[
        {
            "category":"Health Services",
            "subcategory":"Doctor",
            "type":"Services"
        }
    ],
    "sg:phone":"+61 3 8345 1662",
    "sg:postcode":"3021",
    "sg:province":"VIC",
    "sg:tags":[
        "medical",
        "practitioner"
    ],
    "wof:name":"Bell Imaging Group",
    "wof:placetype":"venue"
},
  "geometry": {"coordinates":[144.815826,-37.760647],"type":"Point"}
}