{
  "type": "Feature",
  "properties": {
    "iso:country":"AU",
    "sg:address":"Level 1, Unit 2, 32 Bougainville St",
    "sg:city":"Manuka",
    "sg:classifiers":[
        {
            "category":"Travel",
            "subcategory":"Travel Agent",
            "type":"Entertainment"
        }
    ],
    "sg:phone":"+61 1800 739 288",
    "sg:postcode":"2603",
    "sg:province":"ACT",
    "sg:tags":[
        "consultant"
    ],
    "wof:name":"Pagonis & James Travel Associates",
    "wof:placetype":"venue"
},
  "geometry": {"coordinates":[149.13148498499999,-35.320400238],"type":"Point"}
}