{
  "type": "Feature",
  "properties": {
    "addr:full":"Balmoral Ave Bundoora VIC 3083",
    "addr:postcode":"3083",
    "addr:street":"Balmoral Ave",
    "iso:country":"AU",
    "sg:address":"Balmoral Ave",
    "sg:city":"Bundoora",
    "sg:classifiers":[
        {
            "category":"Education",
            "subcategory":"School",
            "type":"Public Place"
        }
    ],
    "sg:phone":"+61 3 9467 2601",
    "sg:postcode":"3083",
    "sg:province":"VIC",
    "sg:tags":[
        "state",
        "except",
        "nsw"
    ],
    "wof:name":"Greenwood Primary",
    "wof:placetype":"venue"
},
  "geometry": {"coordinates":[145.06625366200001,-37.7071914673],"type":"Point"}
}