{
  "type": "Feature",
  "properties": {
    "addr:full":"Shp 22a Northpark Shopng Cntr 258-264 Main North R Prospect SA 5082",
    "addr:housenumber":"22a;258-264",
    "addr:postcode":"5082",
    "addr:street":"Main North R Prospect",
    "iso:country":"AU",
    "sg:address":"Shp 22a Northpark Shopng Cntr 258-264 Main North R",
    "sg:city":"Prospect",
    "sg:classifiers":[
        {
            "category":"Travel",
            "subcategory":"Travel Agent",
            "type":"Entertainment"
        }
    ],
    "sg:phone":"+61 8 8344 8255",
    "sg:postcode":"5082",
    "sg:province":"SA",
    "sg:tags":[
        "consultant"
    ],
    "wof:name":"Harvey World Travel",
    "wof:placetype":"venue"
},
  "geometry": {"coordinates":[138.602386475,-34.8823623657],"type":"Point"}
}