{
  "type": "Feature",
  "properties": {
    "iso:country":"AU",
    "sg:address":"107 Distillary Rd",
    "sg:city":"Yatala",
    "sg:classifiers":[
        {
            "category":"Building & Trades",
            "subcategory":"Construction",
            "type":"Services"
        }
    ],
    "sg:phone":"+61 7 3807 7200",
    "sg:postcode":"4207",
    "sg:province":"QLD",
    "sg:tags":[
        "fencing",
        "contractor"
    ],
    "wof:name":"Australian Temporary Fencing",
    "wof:placetype":"venue"
},
  "geometry": {"coordinates":[153.218063355,-27.7215976715],"type":"Point"}
}