{
  "type": "Feature",
  "properties": {
    "addr:full":"110 Shortbeach Rd Bremer Bay WA 6338",
    "addr:housenumber":"110",
    "addr:postcode":"6338",
    "addr:street":"Shortbeach Rd",
    "iso:country":"AU",
    "sg:address":"110 Shortbeach Rd",
    "sg:city":"Bremer Bay",
    "sg:classifiers":[
        {
            "category":"Real Estate",
            "subcategory":"Architect",
            "type":"Services"
        }
    ],
    "sg:phone":"+61 417 950 061",
    "sg:postcode":"6338",
    "sg:province":"WA",
    "wof:name":"Siero G?rard",
    "wof:placetype":"venue"
},
  "geometry": {"coordinates":[119.394096374,-34.4428596497],"type":"Point"}
}