{
  "type": "Feature",
  "properties": {
    "addr:full":"Ann St Applethorpe QLD 4378",
    "addr:postcode":"4378",
    "addr:street":"Ann St",
    "iso:country":"AU",
    "sg:address":"Ann St",
    "sg:city":"Applethorpe",
    "sg:classifiers":[
        {
            "category":"Farming",
            "subcategory":"Orchard",
            "type":"Manufacturing & Wholesale Goods"
        }
    ],
    "sg:phone":"+61 7 4683 2293",
    "sg:postcode":"4378",
    "sg:province":"QLD",
    "sg:tags":[
        "pear",
        "apple",
        "grower"
    ],
    "wof:name":"Brisotto I & R",
    "wof:placetype":"venue"
},
  "geometry": {"coordinates":[151.95452880900001,-28.6174106598],"type":"Point"}
}