{
  "type": "Feature",
  "properties": {
    "iso:country":"AU",
    "sg:address":"207 Northstead St",
    "sg:city":"Scarborough",
    "sg:classifiers":[
        {
            "category":"Banks & Credit Unions",
            "subcategory":"Bank",
            "type":"Services"
        }
    ],
    "sg:phone":"+61 416 392 700",
    "sg:postcode":"6019",
    "sg:province":"WA",
    "sg:tags":[
        "broker",
        "mortgage"
    ],
    "wof:name":"What Mortgage Pty Ltd",
    "wof:placetype":"venue"
},
  "geometry": {"coordinates":[115.772621155,-31.8969669342],"type":"Point"}
}