{
  "type": "Feature",
  "properties": {
    "addr:full":"137 High Rd Wanneroo WA 6065",
    "addr:housenumber":"137",
    "addr:postcode":"6065",
    "addr:street":"High Rd",
    "iso:country":"AU",
    "sg:address":"137 High Rd",
    "sg:city":"Wanneroo",
    "sg:classifiers":[
        {
            "category":"Building & Trades",
            "subcategory":"Equipment Rental",
            "type":"Services"
        }
    ],
    "sg:phone":"+61 8 9408 0851",
    "sg:postcode":"6065",
    "sg:province":"WA",
    "sg:tags":[
        "demolition",
        "contractor"
    ],
    "wof:name":"Murphy Plant Hire",
    "wof:placetype":"venue"
},
  "geometry": {"coordinates":[115.82762146,-31.7575931549],"type":"Point"}
}