{
  "type": "Feature",
  "properties": {
    "iso:country":"AU",
    "sg:address":"51 Denison St",
    "sg:city":"Hamilton",
    "sg:classifiers":[
        {
            "category":"Health Services",
            "subcategory":"Doctor",
            "type":"Services"
        }
    ],
    "sg:phone":"+61 2 4961 4411",
    "sg:postcode":"2303",
    "sg:province":"NSW",
    "sg:tags":[
        "podiatrist"
    ],
    "sg:website":"http://www.healthyfeet.com.au",
    "wof:name":"Newcastle Family & Sports Podiatry",
    "wof:placetype":"venue"
},
  "geometry": {"coordinates":[151.738953,-32.925156],"type":"Point"}
}