{
  "type": "Feature",
  "properties": {
    "iso:country":"AU",
    "sg:address":"76 Wyndham St",
    "sg:city":"Shepparton",
    "sg:classifiers":[
        {
            "category":"Organizations",
            "subcategory":"Membership Organization",
            "type":"Services"
        }
    ],
    "sg:phone":"+61 3 5831 5399",
    "sg:postcode":"3630",
    "sg:province":"VIC",
    "sg:tags":[
        "support",
        "health",
        "organisation"
    ],
    "wof:name":"G.V.G.P.'s A Division of General Practice Ltd",
    "wof:placetype":"venue"
},
  "geometry": {"coordinates":[145.400634766,-36.3733482361],"type":"Point"}
}