{
  "type": "Feature",
  "properties": {
    "addr:full":"280 Bourke St Mall Melbourne VIC 3000",
    "addr:housenumber":"280",
    "addr:postcode":"3000",
    "addr:street":"Bourke St Mall",
    "iso:country":"AU",
    "sg:address":"280 Bourke St",
    "sg:city":"Mall Melbourne",
    "sg:classifiers":[
        {
            "category":"Shopping",
            "subcategory":"Shoes",
            "type":"Retail Goods"
        }
    ],
    "sg:phone":"+61 3 9650 3336",
    "sg:postcode":"3000",
    "sg:province":"VIC",
    "sg:tags":[
        "footwear"
    ],
    "wof:name":"Emporio The",
    "wof:placetype":"venue"
},
  "geometry": {"coordinates":[144.96525573700001,-37.8135070801],"type":"Point"}
}