{
  "type": "Feature",
  "properties": {
    "addr:full":"10 Station St Wentworth Falls NSW 2782",
    "addr:housenumber":"10",
    "addr:postcode":"2782",
    "addr:street":"Station St",
    "iso:country":"AU",
    "sg:address":"10 Station St",
    "sg:city":"Wentworth Falls",
    "sg:classifiers":[
        {
            "category":"Professional",
            "subcategory":"Art Services",
            "type":"Services"
        }
    ],
    "sg:phone":"+61 2 4757 4044",
    "sg:postcode":"2782",
    "sg:province":"NSW",
    "sg:tags":[
        "picture",
        "frame",
        "framing"
    ],
    "wof:name":"Jakeman's Framing & Art Supplies",
    "wof:placetype":"venue"
},
  "geometry": {"coordinates":[150.375762939,-33.7100105286],"type":"Point"}
}