{
  "type": "Feature",
  "properties": {
    "addr:full":"Adelaide Rd Millicent SA 5280",
    "addr:postcode":"5280",
    "addr:street":"Adelaide Rd",
    "iso:country":"AU",
    "sg:address":"Adelaide Rd",
    "sg:city":"Millicent",
    "sg:classifiers":[
        {
            "category":"Sports & Exercise",
            "subcategory":"Sports Center",
            "type":"Entertainment"
        }
    ],
    "sg:phone":"+61 8 8733 4884",
    "sg:postcode":"5280",
    "sg:province":"SA",
    "sg:tags":[
        "ground"
    ],
    "wof:name":"Millicent Youth Centre Incorporated",
    "wof:placetype":"venue"
},
  "geometry": {"coordinates":[140.35218800000001,-37.591656],"type":"Point"}
}