{
  "type": "Feature",
  "properties": {
    "iso:country":"AU",
    "sg:address":"93 Market St",
    "sg:city":"Balranald",
    "sg:classifiers":[
        {
            "category":"Banks & Credit Unions",
            "subcategory":"Bank",
            "type":"Services"
        }
    ],
    "sg:phone":"+61 13 20 32",
    "sg:postcode":"2715",
    "sg:province":"NSW",
    "wof:name":"Westpac",
    "wof:placetype":"venue"
},
  "geometry": {"coordinates":[143.56947326700001,-34.6443214417],"type":"Point"}
}