{
  "type": "Feature",
  "properties": {
    "iso:country":"AU",
    "sg:address":"2/ 219 Glynburn Rd",
    "sg:city":"St Morris",
    "sg:classifiers":[
        {
            "category":"Personal",
            "subcategory":"Beauty Salon",
            "type":"Services"
        }
    ],
    "sg:phone":"+61 8 8361 2600",
    "sg:postcode":"5068",
    "sg:province":"SA",
    "wof:name":"Bella Donna Skin & Body",
    "wof:placetype":"venue"
},
  "geometry": {"coordinates":[138.657714844,-34.908203125],"type":"Point"}
}