{
  "type": "Feature",
  "properties": {
    "addr:full":"3/ 176 South Creek Rd Dee Why NSW 2099",
    "addr:housenumber":"/ 176",
    "addr:postcode":"2099",
    "addr:street":"South Creek Rd",
    "iso:country":"AU",
    "sg:address":"3/ 176 South Creek Rd",
    "sg:city":"Dee Why",
    "sg:classifiers":[
        {
            "category":"Building & Trades",
            "subcategory":"Construction",
            "type":"Services"
        }
    ],
    "sg:phone":"+61 2 9972 4778",
    "sg:postcode":"2099",
    "sg:province":"NSW",
    "sg:tags":[
        "window",
        "timber"
    ],
    "wof:name":"JM Joinery",
    "wof:placetype":"venue"
},
  "geometry": {"coordinates":[151.279663086,-33.7342834473],"type":"Point"}
}