{
  "type": "Feature",
  "properties": {
    "iso:country":"AU",
    "sg:address":"Cnr Marabou Drv & Yolanda Drv",
    "sg:city":"Annandale",
    "sg:classifiers":[
        {
            "category":"Retail",
            "subcategory":"Veterinary Services",
            "type":"Services"
        }
    ],
    "sg:phone":"+61 7 4775 6377",
    "sg:postcode":"4814",
    "sg:province":"QLD",
    "sg:tags":[
        "surgeon"
    ],
    "wof:name":"Edwards Eleanor",
    "wof:placetype":"venue"
},
  "geometry": {"coordinates":[146.782776,-19.313601],"type":"Point"}
}