{
  "type": "Feature",
  "properties": {
    "iso:country":"AU",
    "sg:address":"32 Aldea Pl",
    "sg:city":"Stretton",
    "sg:classifiers":[
        {
            "category":"Utilities",
            "subcategory":"Electric",
            "type":"Services"
        }
    ],
    "sg:phone":"+61 404 940 163",
    "sg:postcode":"4116",
    "sg:province":"QLD",
    "sg:tags":[
        "electrical",
        "contractor"
    ],
    "wof:name":"Jag Electricals",
    "wof:placetype":"venue"
},
  "geometry": {"coordinates":[153.05870056099999,-27.6332511902],"type":"Point"}
}