{
  "type": "Feature",
  "properties": {
    "iso:country":"AU",
    "sg:address":"25 Leighton Pl",
    "sg:city":"Hornsby",
    "sg:classifiers":[
        {
            "category":"Professional",
            "subcategory":"Accounting & Tax Preparation",
            "type":"Services"
        }
    ],
    "sg:phone":"+61 2 9477 4095",
    "sg:postcode":"2077",
    "sg:province":"NSW",
    "sg:tags":[
        "insulation",
        "wholesaler",
        "material",
        "mfrs"
    ],
    "wof:name":"Lehmann Pacific Solar Pty Ltd",
    "wof:placetype":"venue"
},
  "geometry": {"coordinates":[151.114379883,-33.6956100464],"type":"Point"}
}