{
  "type": "Feature",
  "properties": {
    "addr:full":"Logans Crossing Rd Kendall NSW 2439",
    "addr:postcode":"2439",
    "addr:street":"Crossing Rd",
    "iso:country":"AU",
    "sg:address":"Logans Crossing Rd",
    "sg:city":"Kendall",
    "sg:classifiers":[
        {
            "category":"Home & Garden",
            "subcategory":"Garden Supply",
            "type":"Retail Goods"
        }
    ],
    "sg:phone":"+61 419 464 907",
    "sg:postcode":"2439",
    "sg:province":"NSW",
    "sg:tags":[
        "turf",
        "lawn"
    ],
    "wof:name":"Port City Turf Supplies",
    "wof:placetype":"venue"
},
  "geometry": {"coordinates":[152.70095800000001,-31.625172],"type":"Point"}
}