{
  "type": "Feature",
  "properties": {
    "iso:country":"AU",
    "sg:address":"Blocksidge & Ferguson Arcade 144 Adelaide St",
    "sg:city":"Brisbane City",
    "sg:classifiers":[
        {
            "category":"Shopping",
            "subcategory":"Clothing, Apparel, & Fashions",
            "type":"Retail Goods"
        }
    ],
    "sg:phone":"+61 7 3229 6428",
    "sg:postcode":"4000",
    "sg:province":"QLD",
    "sg:tags":[
        "recycled",
        "clothing"
    ],
    "wof:name":"Lifeline Clothing Shops",
    "wof:placetype":"venue"
},
  "geometry": {"coordinates":[153.02542114299999,-27.4679546356],"type":"Point"}
}