{
  "type": "Feature",
  "properties": {
    "addr:full":"Old Chittaway Rd Fountaindale NSW 2259",
    "addr:postcode":"2259",
    "addr:street":"Chittaway Rd",
    "iso:country":"AU",
    "sg:address":"Old Chittaway Rd",
    "sg:city":"Fountaindale",
    "sg:classifiers":[
        {
            "category":"Health Services",
            "subcategory":"Doctor",
            "type":"Services"
        }
    ],
    "sg:phone":"+61 2 4362 3456",
    "sg:postcode":"2259",
    "sg:province":"NSW",
    "sg:tags":[
        "nurse",
        "nursing"
    ],
    "wof:name":"Quantica Consultants Pty Ltd",
    "wof:placetype":"venue"
},
  "geometry": {"coordinates":[151.408691406,-33.3259887695],"type":"Point"}
}