{
  "type": "Feature",
  "properties": {
    "iso:country":"AU",
    "sg:address":"23 Haversham Ave",
    "sg:city":"Glen Waverley",
    "sg:classifiers":[
        {
            "category":"Food & Beverages",
            "subcategory":"Fruits & Vegetables",
            "type":"Retail Goods"
        }
    ],
    "sg:phone":"+61 3 9587 3799",
    "sg:postcode":"3150",
    "sg:province":"VIC",
    "sg:tags":[
        "consultant",
        "catering"
    ],
    "wof:name":"Down Under Catering",
    "wof:placetype":"venue"
},
  "geometry": {"coordinates":[145.19903564399999,-37.9114761353],"type":"Point"}
}