{
  "type": "Feature",
  "properties": {
    "addr:full":"432 Rockingham Rd Spearwood WA 6163",
    "addr:housenumber":"432",
    "addr:postcode":"6163",
    "addr:street":"Rockingham Rd",
    "iso:country":"AU",
    "sg:address":"432 Rockingham Rd",
    "sg:city":"Spearwood",
    "sg:classifiers":[
        {
            "category":"Food & Beverages",
            "subcategory":"Fruits & Vegetables",
            "type":"Retail Goods"
        }
    ],
    "sg:phone":"+61 8 9418 6035",
    "sg:postcode":"6163",
    "sg:province":"WA",
    "sg:tags":[
        "greengrocer",
        "fruiterer"
    ],
    "wof:name":"Spearwood Fresh",
    "wof:placetype":"venue"
},
  "geometry": {"coordinates":[115.78257000000001,-32.114445],"type":"Point"}
}