{
  "type": "Feature",
  "properties": {
    "iso:country":"AU",
    "sg:address":"70 Holbrooks Rd",
    "sg:city":"Flinders Park",
    "sg:classifiers":[
        {
            "category":"Education",
            "subcategory":"School",
            "type":"Public Place"
        }
    ],
    "sg:phone":"+61 8 8443 9356",
    "sg:postcode":"5025",
    "sg:province":"SA",
    "sg:tags":[
        "state",
        "except",
        "nsw"
    ],
    "wof:name":"Flinders Park Primary",
    "wof:placetype":"venue"
},
  "geometry": {"coordinates":[138.548706055,-34.9109725952],"type":"Point"}
}