{
  "type": "Feature",
  "properties": {
    "addr:full":"4 Rakeevan Rd Graceville QLD 4075",
    "addr:housenumber":"4",
    "addr:postcode":"4075",
    "addr:street":"Rakeevan Rd",
    "iso:country":"AU",
    "sg:address":"4 Rakeevan Rd",
    "sg:city":"Graceville",
    "sg:classifiers":[
        {
            "category":"Professional",
            "subcategory":"Lawyer & Legal Services",
            "type":"Services"
        }
    ],
    "sg:phone":"+61 7 3278 2109",
    "sg:postcode":"4075",
    "sg:province":"QLD",
    "sg:tags":[
        "wills",
        "probate",
        "estate"
    ],
    "wof:name":"Williamson & Associates",
    "wof:placetype":"venue"
},
  "geometry": {"coordinates":[152.97549438499999,-27.5210456848],"type":"Point"}
}