{
  "type": "Feature",
  "properties": {
    "addr:full":"12 Fairway St Frankston VIC 3199",
    "addr:housenumber":"12",
    "addr:postcode":"3199",
    "addr:street":"Fairway St",
    "iso:country":"AU",
    "sg:address":"12 Fairway St",
    "sg:city":"Frankston",
    "sg:classifiers":[
        {
            "category":"Manufacturing",
            "subcategory":"Food",
            "type":"Manufacturing & Wholesale Goods"
        }
    ],
    "sg:phone":"+61 3 9781 4603",
    "sg:postcode":"3199",
    "sg:province":"VIC",
    "sg:tags":[
        "function",
        "catering"
    ],
    "wof:name":"Gourmet Classic Catering",
    "wof:placetype":"venue"
},
  "geometry": {"coordinates":[145.13267517099999,-38.1357803345],"type":"Point"}
}