{
  "type": "Feature",
  "properties": {
    "addr:full":"Unit 5 26- 34 Dunning Av Roseberry NSW 2474",
    "addr:housenumber":"26 34",
    "addr:postcode":"2474",
    "addr:street":"Dunning Av",
    "iso:country":"AU",
    "sg:address":"Unit 5 26- 34",
    "sg:city":"Dunning Av Roseberry",
    "sg:classifiers":[
        {
            "category":"Wholesale",
            "subcategory":"Drugs",
            "type":"Manufacturing & Wholesale Goods"
        }
    ],
    "sg:phone":"+61 1800 252 325",
    "sg:postcode":"2474",
    "sg:province":"NSW",
    "sg:tags":[
        "wholesaler",
        "pharmaceutical",
        "product",
        "mfrs"
    ],
    "wof:name":"Regional Pharmaceuticals",
    "wof:placetype":"venue"
},
  "geometry": {"coordinates":[152.91421508799999,-28.4815502167],"type":"Point"}
}