{
  "type": "Feature",
  "properties": {
    "addr:full":"121- 125 Newton Rd Wetherill Park NSW 2164",
    "addr:housenumber":"125",
    "addr:postcode":"2164",
    "addr:street":"121;Newton Rd",
    "iso:country":"AU",
    "sg:address":"121- 125 Newton Rd",
    "sg:city":"Wetherill Park",
    "sg:classifiers":[
        {
            "category":"Education",
            "subcategory":"Special Training",
            "type":"Public Place"
        }
    ],
    "sg:phone":"+61 2 9756 5050",
    "sg:postcode":"2164",
    "sg:province":"NSW",
    "sg:tags":[
        "development"
    ],
    "wof:name":"Independent Licenced Heavy Vehicle & Dangerous Goods Training",
    "wof:placetype":"venue"
},
  "geometry": {"coordinates":[150.89353942899999,-33.843624115],"type":"Point"}
}