{
  "type": "Feature",
  "properties": {
    "addr:full":"U1/ 33 Ella Gr Chelsea VIC 3196",
    "addr:housenumber":"33",
    "addr:postcode":"3196",
    "addr:street":"U1 /;Ella Gr",
    "iso:country":"AU",
    "sg:address":"U1/ 33",
    "sg:city":"Ella Gr Chelsea",
    "sg:classifiers":[
        {
            "category":"Professional",
            "subcategory":"Art Services",
            "type":"Services"
        }
    ],
    "sg:phone":"+61 3 9773 2688",
    "sg:postcode":"3196",
    "sg:province":"VIC",
    "sg:tags":[
        "decorator",
        "painter"
    ],
    "wof:name":"Flair Painting & Maintenance",
    "wof:placetype":"venue"
},
  "geometry": {"coordinates":[145.121185303,-38.04322052],"type":"Point"}
}