{
  "type": "Feature",
  "properties": {
    "addr:full":"83 Lakeview St Speers Point NSW 2284",
    "addr:housenumber":"83",
    "addr:postcode":"2284",
    "addr:street":"Lakeview St",
    "iso:country":"AU",
    "sg:address":"83 Lakeview St",
    "sg:city":"Speers Point",
    "sg:classifiers":[
        {
            "category":"Arts & Performance",
            "subcategory":"Theater",
            "type":"Entertainment"
        }
    ],
    "sg:phone":"+61 2 4958 5244",
    "sg:postcode":"2284",
    "sg:province":"NSW",
    "sg:tags":[
        "theatre"
    ],
    "wof:name":"Freewheels Theatre",
    "wof:placetype":"venue"
},
  "geometry": {"coordinates":[151.623977661,-32.9607925415],"type":"Point"}
}