{
  "type": "Feature",
  "properties": {
    "addr:full":"38- 40 Ralph St Alexandria NSW 2015",
    "addr:housenumber":"40",
    "addr:postcode":"2015",
    "addr:street":"Ralph St",
    "iso:country":"AU",
    "sg:address":"38- 40 Ralph St",
    "sg:city":"Alexandria",
    "sg:classifiers":[
        {
            "category":"Social Services",
            "subcategory":"Retirement Home",
            "type":"Services"
        }
    ],
    "sg:phone":"+61 2 9667 1888",
    "sg:postcode":"2015",
    "sg:province":"NSW",
    "sg:tags":[
        "t-shirt",
        "supplier"
    ],
    "wof:name":"Blue Pacific Clothing",
    "wof:placetype":"venue"
},
  "geometry": {"coordinates":[151.19731140100001,-33.9188117981],"type":"Point"}
}