{
  "type": "Feature",
  "properties": {
    "addr:full":"Shop 104, Centre Colonnades Shopng Cntr,Cnr Goldsmith Dr & Beach Rd Noarlunga SA 5168",
    "addr:housenumber":"104",
    "addr:postcode":"5168",
    "addr:street":"Centre Colonnades Shopng Cntr Cnr Goldsmith Dr & Beach Rd",
    "iso:country":"AU",
    "sg:address":"Shop 104, Centre Colonnades Shopng Cntr,Cnr Goldsmith Dr & Beach Rd",
    "sg:city":"Noarlunga",
    "sg:classifiers":[
        {
            "category":"Wholesale",
            "subcategory":"Medical Equipment & Supplies",
            "type":"Manufacturing & Wholesale Goods"
        }
    ],
    "sg:phone":"+61 8 8186 0900",
    "sg:postcode":"5168",
    "sg:province":"SA",
    "sg:tags":[
        "aids",
        "hearing"
    ],
    "wof:name":"National Hearing Care",
    "wof:placetype":"venue"
},
  "geometry": {"coordinates":[138.49700927699999,-35.1446685791],"type":"Point"}
}