{
  "type": "Feature",
  "properties": {
    "addr:full":"508 Anzac Pde Kingsford NSW 2032",
    "addr:housenumber":"508",
    "addr:postcode":"2032",
    "addr:street":"Anzac Pde",
    "iso:country":"AU",
    "sg:address":"508 Anzac Pde",
    "sg:city":"Kingsford",
    "sg:classifiers":[
        {
            "category":"Fast Food",
            "type":"Food & Drink"
        }
    ],
    "sg:phone":"+61 2 9663 2518",
    "sg:postcode":"2032",
    "sg:province":"NSW",
    "sg:tags":[
        "away",
        "take"
    ],
    "wof:name":"Warung Surabaya",
    "wof:placetype":"venue"
},
  "geometry": {"coordinates":[151.22755432100001,-33.923248291],"type":"Point"}
}