{
  "type": "Feature",
  "properties": {
    "addr:full":"378 Shannon Ave Newtown VIC 3220",
    "addr:housenumber":"378",
    "addr:postcode":"3220",
    "addr:street":"Shannon Ave",
    "iso:country":"AU",
    "sg:address":"378 Shannon Ave",
    "sg:city":"Newtown",
    "sg:classifiers":[
        {
            "category":"Professional",
            "subcategory":"Business Services",
            "type":"Services"
        }
    ],
    "sg:phone":"+61 3 5222 4553",
    "sg:postcode":"3220",
    "sg:province":"VIC",
    "sg:tags":[
        "drafting"
    ],
    "wof:name":"C & L Drafting Services",
    "wof:placetype":"venue"
},
  "geometry": {"coordinates":[144.33371,-38.155819],"type":"Point"}
}