{
  "type": "Feature",
  "properties": {
    "addr:full":"142 Main Rd McLaren Vale SA 5171",
    "addr:housenumber":"142",
    "addr:postcode":"5171",
    "addr:street":"Main Rd",
    "iso:country":"AU",
    "sg:address":"142 Main Rd",
    "sg:city":"McLaren Vale",
    "sg:classifiers":[
        {
            "category":"Utilities",
            "subcategory":"Fuel Oil & Lpg",
            "type":"Services"
        }
    ],
    "sg:phone":"+61 8 8323 9231",
    "sg:postcode":"5171",
    "sg:province":"SA",
    "sg:tags":[
        "olive"
    ],
    "wof:name":"Brian's Olive Shop",
    "wof:placetype":"venue"
},
  "geometry": {"coordinates":[138.537277222,-35.2150535583],"type":"Point"}
}