{
  "type": "Feature",
  "properties": {
    "iso:country":"AU",
    "sg:address":"208 Dyson Rd",
    "sg:city":"Lonsdale",
    "sg:classifiers":[
        {
            "category":"Manufacturing",
            "subcategory":"Glass & Minerals",
            "type":"Manufacturing & Wholesale Goods"
        }
    ],
    "sg:phone":"+61 8 8326 0877",
    "sg:postcode":"5160",
    "sg:province":"SA",
    "sg:tags":[
        "repair",
        "fibreglass",
        "product"
    ],
    "wof:name":"Fibreglass Factory",
    "wof:placetype":"venue"
},
  "geometry": {"coordinates":[138.491577148,-35.1174354553],"type":"Point"}
}