{
  "type": "Feature",
  "properties": {
    "addr:full":"U3/ 62 Rose St Fitzroy VIC 3065",
    "addr:housenumber":"62",
    "addr:postcode":"3065",
    "addr:street":"U3 /;Rose St",
    "iso:country":"AU",
    "sg:address":"U3/ 62 Rose St",
    "sg:city":"Fitzroy",
    "sg:classifiers":[
        {
            "category":"Building & Trades",
            "subcategory":"Locksmith",
            "type":"Services"
        }
    ],
    "sg:phone":"+61 3 9416 4448",
    "sg:postcode":"3065",
    "sg:province":"VIC",
    "sg:tags":[
        "steeplejack"
    ],
    "wof:name":"United Rope Access",
    "wof:placetype":"venue"
},
  "geometry": {"coordinates":[144.97755432100001,-37.795917511],"type":"Point"}
}