{
  "type": "Feature",
  "properties": {
    "iso:country":"AU",
    "sg:address":"Crawford St",
    "sg:city":"Jindabyne",
    "sg:classifiers":[
        {
            "category":"Home & Garden",
            "subcategory":"Building Materials",
            "type":"Retail Goods"
        }
    ],
    "sg:phone":"+61 2 6456 1066",
    "sg:postcode":"2627",
    "sg:province":"NSW",
    "sg:tags":[
        "pre-mixed",
        "concrete"
    ],
    "wof:name":"Boral Country-Concrete & Quarries",
    "wof:placetype":"venue"
},
  "geometry": {"coordinates":[148.60235595699999,-36.4375305176],"type":"Point"}
}