{
  "type": "Feature",
  "properties": {
    "addr:full":"194 Payneham Rd Evandale SA 5069",
    "addr:housenumber":"194",
    "addr:postcode":"5069",
    "addr:street":"Payneham Rd",
    "iso:country":"AU",
    "sg:address":"194 Payneham Rd",
    "sg:city":"Evandale",
    "sg:classifiers":[
        {
            "category":"Personal",
            "subcategory":"Skin Care",
            "type":"Services"
        }
    ],
    "sg:phone":"+61 8 8362 2394",
    "sg:postcode":"5069",
    "sg:province":"SA",
    "sg:tags":[
        "treatment"
    ],
    "wof:name":"Psoriasis & Skin Clinic",
    "wof:placetype":"venue"
},
  "geometry": {"coordinates":[138.632156372,-34.9047355652],"type":"Point"}
}