{
  "type": "Feature",
  "properties": {
    "addr:full":"410 Ipswich Rd Annerley QLD 4103",
    "addr:housenumber":"410",
    "addr:postcode":"4103",
    "addr:street":"Ipswich Rd",
    "iso:country":"AU",
    "sg:address":"410 Ipswich Rd",
    "sg:city":"Annerley",
    "sg:classifiers":[
        {
            "category":"Food & Beverages",
            "subcategory":"Fruits & Vegetables",
            "type":"Retail Goods"
        }
    ],
    "sg:phone":"+61 7 3391 2933",
    "sg:postcode":"4103",
    "sg:province":"QLD",
    "sg:tags":[
        "greengrocer",
        "fruiterer"
    ],
    "wof:name":"Annerley Fruit Barn",
    "wof:placetype":"venue"
},
  "geometry": {"coordinates":[153.034255981,-27.507724762],"type":"Point"}
}