{
  "type": "Feature",
  "properties": {
    "addr:full":"2 / 29 Hi Tech Drv Kunda Park QLD 4556",
    "addr:housenumber":"/ 29",
    "addr:postcode":"4556",
    "addr:street":"Hi Tech Drv",
    "iso:country":"AU",
    "sg:address":"2 / 29 Hi Tech Drv",
    "sg:city":"Kunda Park",
    "sg:classifiers":[
        {
            "category":"Shopping",
            "subcategory":"Crafts & Fabrics",
            "type":"Retail Goods"
        }
    ],
    "sg:phone":"+61 413 334 767",
    "sg:postcode":"4556",
    "sg:province":"QLD",
    "sg:tags":[
        "synthetic",
        "canvas",
        "product"
    ],
    "wof:name":"Cutting Edge Canvas",
    "wof:placetype":"venue"
},
  "geometry": {"coordinates":[153.03021240199999,-26.6696052551],"type":"Point"}
}