{
  "type": "Feature",
  "properties": {
    "addr:full":"Shop 4 West Mall Plaza Rutherford Shopping Centre Ru NSW 2320",
    "addr:housenumber":"shop 4",
    "addr:postcode":"nsw 2320",
    "addr:street":"West Mall",
    "iso:country":"AU",
    "sg:address":"Shop 4",
    "sg:city":"West Mall Plaza Rutherford Shopping Centre Ru",
    "sg:classifiers":[
        {
            "category":"Personal",
            "subcategory":"Beauty Salon",
            "type":"Services"
        }
    ],
    "sg:phone":"+61 2 4932 8614",
    "sg:postcode":"2320",
    "sg:province":"NSW",
    "sg:tags":[
        "hairdresser"
    ],
    "wof:name":"Sandies Salon",
    "wof:placetype":"venue"
},
  "geometry": {"coordinates":[151.52746582,-32.7152938843],"type":"Point"}
}