{
  "type": "Feature",
  "properties": {
    "addr:full":"63 High St Altona Meadows VIC 3028",
    "addr:housenumber":"63",
    "addr:postcode":"3028",
    "addr:street":"High St",
    "iso:country":"AU",
    "sg:address":"63 High St",
    "sg:city":"Altona Meadows",
    "sg:classifiers":[
        {
            "category":"Shopping",
            "subcategory":"Pets & Pet Supplies",
            "type":"Retail Goods"
        }
    ],
    "sg:phone":"+61 1300 308 950",
    "sg:postcode":"3028",
    "sg:province":"VIC",
    "sg:tags":[
        "food"
    ],
    "wof:name":"Proud Pets",
    "wof:placetype":"venue"
},
  "geometry": {"coordinates":[144.77340699999999,-37.86985],"type":"Point"}
}