{
  "type": "Feature",
  "properties": {
    "addr:full":"638 Chant St Lavington NSW 2641",
    "addr:housenumber":"638",
    "addr:postcode":"2641",
    "addr:street":"Chant St",
    "iso:country":"AU",
    "sg:address":"638 Chant St",
    "sg:city":"Lavington",
    "sg:classifiers":[
        {
            "category":"Building & Trades",
            "subcategory":"Construction",
            "type":"Services"
        }
    ],
    "sg:phone":"+61 2 6025 4427",
    "sg:postcode":"2641",
    "sg:province":"NSW",
    "sg:tags":[
        "contractor"
    ],
    "wof:name":"Jeff Jones",
    "wof:placetype":"venue"
},
  "geometry": {"coordinates":[146.92059326200001,-36.0273284912],"type":"Point"}
}