{
  "type": "Feature",
  "properties": {
    "addr:full":"Briggs St Warwick QLD 4370",
    "addr:postcode":"4370",
    "addr:street":"Briggs St",
    "iso:country":"AU",
    "sg:address":"Briggs St",
    "sg:city":"Warwick",
    "sg:classifiers":[
        {
            "category":"Building & Trades",
            "subcategory":"Plumbing",
            "type":"Services"
        }
    ],
    "sg:phone":"+61 418 193 980",
    "sg:postcode":"4370",
    "sg:province":"QLD",
    "sg:tags":[
        "drainers"
    ],
    "wof:name":"Jacklin J F & J D",
    "wof:placetype":"venue"
},
  "geometry": {"coordinates":[152.04315185600001,-28.2080535889],"type":"Point"}
}