{
  "type": "Feature",
  "properties": {
    "addr:full":"200 Newmarket Rd Wilston QLD 4051",
    "addr:housenumber":"200",
    "addr:postcode":"4051",
    "addr:street":"Newmarket Rd",
    "iso:country":"AU",
    "sg:address":"200 Newmarket Rd",
    "sg:city":"Wilston",
    "sg:classifiers":[
        {
            "category":"Wholesale",
            "subcategory":"Apparel",
            "type":"Manufacturing & Wholesale Goods"
        }
    ],
    "sg:phone":"+61 7 3311 4263",
    "sg:postcode":"4051",
    "sg:province":"QLD",
    "sg:tags":[
        "wholesaler",
        "mfrs",
        "dress"
    ],
    "wof:name":"Prom Queen",
    "wof:placetype":"venue"
},
  "geometry": {"coordinates":[153.019897461,-27.4365692139],"type":"Point"}
}