{
  "type": "Feature",
  "properties": {
    "addr:full":"67 Rosslyn St West Melbourne VIC 3003",
    "addr:housenumber":"67",
    "addr:postcode":"3003",
    "addr:street":"Rosslyn St",
    "iso:country":"AU",
    "sg:address":"67 Rosslyn St",
    "sg:city":"West Melbourne",
    "sg:classifiers":[
        {
            "category":"Professional",
            "type":"Services"
        }
    ],
    "sg:phone":"+61 3 9326 5001",
    "sg:postcode":"3003",
    "sg:province":"VIC",
    "sg:tags":[
        "transport"
    ],
    "wof:name":"Melbourne Budget Limousine Pty Ltd",
    "wof:placetype":"venue"
},
  "geometry": {"coordinates":[144.952270508,-37.8080177307],"type":"Point"}
}