{
  "type": "Feature",
  "properties": {
    "addr:full":"384 Main Rd Wellington Point QLD 4160",
    "addr:housenumber":"384",
    "addr:postcode":"4160",
    "addr:street":"Main Rd",
    "iso:country":"AU",
    "sg:address":"384 Main Rd",
    "sg:city":"Wellington Point",
    "sg:classifiers":[
        {
            "category":"Shopping",
            "subcategory":"Clothing, Apparel, & Fashions",
            "type":"Retail Goods"
        }
    ],
    "sg:phone":"+61 7 3822 9462",
    "sg:postcode":"4160",
    "sg:province":"QLD",
    "sg:tags":[
        "recycled",
        "clothing"
    ],
    "wof:name":"Lifeline Clothing Shops",
    "wof:placetype":"venue"
},
  "geometry": {"coordinates":[153.23823547399999,-27.4860668182],"type":"Point"}
}