{
  "type": "Feature",
  "properties": {
    "iso:country":"AU",
    "sg:address":"1223 Canterbury Rd",
    "sg:city":"Punchbowl",
    "sg:classifiers":[
        {
            "category":"Manufacturing",
            "subcategory":"Apparel",
            "type":"Manufacturing & Wholesale Goods"
        }
    ],
    "sg:phone":"+61 2 9740 7950",
    "sg:postcode":"2196",
    "sg:province":"NSW",
    "sg:tags":[
        "wholesaler",
        "mfrs",
        "footwear"
    ],
    "wof:name":"Carnivale Shoes Co Pty Ltd",
    "wof:placetype":"venue"
},
  "geometry": {"coordinates":[151.05371099999999,-33.931808],"type":"Point"}
}