{
  "type": "Feature",
  "properties": {
    "iso:country":"AU",
    "sg:address":"357 Darebin Rd",
    "sg:city":"Thornbury",
    "sg:classifiers":[
        {
            "category":"Retail",
            "subcategory":"Auto Repair",
            "type":"Services"
        }
    ],
    "sg:phone":"+61 3 9497 4200",
    "sg:postcode":"3071",
    "sg:province":"VIC",
    "sg:tags":[
        "beater",
        "painter",
        "panel"
    ],
    "wof:name":"Super Tek Collision Repairs",
    "wof:placetype":"venue"
},
  "geometry": {"coordinates":[145.03102111800001,-37.7664527893],"type":"Point"}
}