{
  "type": "Feature",
  "properties": {
    "addr:full":"189 Barkly St St Kilda VIC 3182",
    "addr:housenumber":"189",
    "addr:postcode":"3182",
    "addr:street":"Barkly St",
    "iso:country":"AU",
    "sg:address":"189 Barkly St St",
    "sg:city":"Kilda",
    "sg:classifiers":[
        {
            "category":"Food & Beverages",
            "subcategory":"Liquor & Beverages",
            "type":"Retail Goods"
        }
    ],
    "sg:phone":"+61 3 9525 3311",
    "sg:postcode":"3182",
    "sg:province":"VIC",
    "sg:tags":[
        "store"
    ],
    "wof:name":"Barkly Cellars",
    "wof:placetype":"venue"
},
  "geometry": {"coordinates":[144.98080444300001,-37.8685646057],"type":"Point"}
}