{
  "type": "Feature",
  "properties": {
    "addr:full":"Suite 22, 152 - 156 Shore St Cleveland QLD 4163",
    "addr:housenumber":"152 156",
    "addr:postcode":"4163",
    "addr:street":"Shore St",
    "iso:country":"AU",
    "sg:address":"Suite 22, 152 - 156 Shore St",
    "sg:city":"Cleveland",
    "sg:classifiers":[
        {
            "category":"Personal",
            "subcategory":"Massage",
            "type":"Services"
        }
    ],
    "sg:phone":"+61 7 3821 2955",
    "sg:postcode":"4163",
    "sg:province":"QLD",
    "sg:tags":[
        "therapy"
    ],
    "wof:name":"Harbour Day Spa & Salon",
    "wof:placetype":"venue"
},
  "geometry": {"coordinates":[153.268997192,-27.5245494843],"type":"Point"}
}