{
  "type": "Feature",
  "properties": {
    "addr:full":"125 Grey St West Albany WA 6330",
    "addr:housenumber":"125",
    "addr:postcode":"6330",
    "addr:street":"Grey St",
    "iso:country":"AU",
    "sg:address":"125 Grey St",
    "sg:city":"West Albany",
    "sg:classifiers":[
        {
            "category":"Social Services",
            "subcategory":"Child Care",
            "type":"Services"
        }
    ],
    "sg:phone":"+61 8 9841 8244",
    "sg:postcode":"6330",
    "sg:province":"WA",
    "sg:tags":[
        "support",
        "health"
    ],
    "wof:name":"Community & Child Health Services",
    "wof:placetype":"venue"
},
  "geometry": {"coordinates":[117.884307861,-35.023979187],"type":"Point"}
}