{
  "type": "Feature",
  "properties": {
    "iso:country":"AU",
    "sg:address":"215 George Dr",
    "sg:city":"Liverpool",
    "sg:classifiers":[
        {
            "category":"Professional",
            "subcategory":"Employment Agencies",
            "type":"Services"
        }
    ],
    "sg:phone":"+61 2 8209 3894",
    "sg:postcode":"2170",
    "sg:province":"NSW",
    "wof:name":"Xtreme Personnel Products & Services",
    "wof:placetype":"venue"
},
  "geometry": {"coordinates":[150.92451477,-33.9239006042],"type":"Point"}
}