{
  "type": "Feature",
  "properties": {
    "addr:full":"31 Harcourt Pde Rosebery NSW 2018",
    "addr:housenumber":"31",
    "addr:postcode":"2018",
    "addr:street":"Harcourt Pde",
    "iso:country":"AU",
    "sg:address":"31 Harcourt Pde",
    "sg:city":"Rosebery",
    "sg:classifiers":[
        {
            "category":"Professional",
            "subcategory":"Management & Consulting",
            "type":"Services"
        }
    ],
    "sg:phone":"+61 2 9667 1199",
    "sg:postcode":"2018",
    "sg:province":"NSW",
    "sg:tags":[
        "consultant"
    ],
    "wof:name":"Ndarala Group",
    "wof:placetype":"venue"
},
  "geometry": {"coordinates":[151.201461792,-33.9202232361],"type":"Point"}
}