{
  "type": "Feature",
  "properties": {
    "addr:full":"224 Springvale Rd Springvale VIC 3171",
    "addr:housenumber":"224",
    "addr:postcode":"3171",
    "addr:street":"Springvale Rd",
    "iso:country":"AU",
    "sg:address":"224 Springvale Rd",
    "sg:city":"Springvale",
    "sg:classifiers":[
        {
            "category":"Personal",
            "subcategory":"Beauty Salon",
            "type":"Services"
        }
    ],
    "sg:phone":"+61 3 9546 0977",
    "sg:postcode":"3171",
    "sg:province":"VIC",
    "sg:tags":[
        "hairdresser"
    ],
    "wof:name":"African Haircare & Beauty Salon",
    "wof:placetype":"venue"
},
  "geometry": {"coordinates":[145.15248107900001,-37.949836731],"type":"Point"}
}