{
  "type": "Feature",
  "properties": {
    "iso:country":"AU",
    "sg:address":"Shop 3 Burns St",
    "sg:city":"Kawana",
    "sg:classifiers":[
        {
            "category":"Personal",
            "subcategory":"Beauty Salon",
            "type":"Services"
        }
    ],
    "sg:phone":"+61 7 5444 4122",
    "sg:postcode":"4701",
    "sg:province":"QLD",
    "sg:tags":[
        "hairdresser"
    ],
    "wof:name":"Kreative Hair Studio Kawana",
    "wof:placetype":"venue"
},
  "geometry": {"coordinates":[150.548339844,-23.3450775146],"type":"Point"}
}