{
  "type": "Feature",
  "properties": {
    "addr:full":"3 Kent St Minto NSW 2566",
    "addr:housenumber":"3",
    "addr:postcode":"2566",
    "addr:street":"Kent St",
    "iso:country":"AU",
    "sg:address":"3 Kent St",
    "sg:city":"Minto",
    "sg:classifiers":[
        {
            "category":"Wholesale",
            "subcategory":"Machinery & Supplies",
            "type":"Manufacturing & Wholesale Goods"
        }
    ],
    "sg:phone":"+61 2 9603 5817",
    "sg:postcode":"2566",
    "sg:province":"NSW",
    "sg:tags":[
        "engineer"
    ],
    "wof:name":"D E K Tooling Supplies Pty Ltd",
    "wof:placetype":"venue"
},
  "geometry": {"coordinates":[150.8465271,-34.0287475586],"type":"Point"}
}