{
  "type": "Feature",
  "properties": {
    "addr:full":"Unit 16, 34 King St Newcastle NSW 2300",
    "addr:housenumber":"34",
    "addr:postcode":"2300",
    "addr:street":"King St",
    "iso:country":"AU",
    "sg:address":"Unit 16, 34 King St",
    "sg:city":"Newcastle",
    "sg:classifiers":[
        {
            "category":"Train Station",
            "subcategory":"Light Rail",
            "type":"Transportation"
        }
    ],
    "sg:phone":"+61 414 185 890",
    "sg:postcode":"2300",
    "sg:province":"NSW",
    "sg:tags":[
        "equipment",
        "energy",
        "solar"
    ],
    "wof:name":"Solartech",
    "wof:placetype":"venue"
},
  "geometry": {"coordinates":[151.783188,-32.928467],"type":"Point"}
}