{
  "type": "Feature",
  "properties": {
    "iso:country":"AU",
    "sg:address":"PO Box 238",
    "sg:city":"Red Hill South",
    "sg:classifiers":[
        {
            "category":"Health Services",
            "subcategory":"Doctor",
            "type":"Services"
        }
    ],
    "sg:phone":"+61 3 9483 0999",
    "sg:postcode":"3937",
    "sg:province":"VIC",
    "sg:tags":[
        "occupational",
        "safety"
    ],
    "wof:name":"PWS Proper Work Safety",
    "wof:placetype":"venue"
},
  "geometry": {"coordinates":[145.043655395,-38.3980789185],"type":"Point"}
}