{
  "type": "Feature",
  "properties": {
    "addr:full":"6 Molly Morgan Drv East Maitland NSW 2323",
    "addr:housenumber":"6",
    "addr:postcode":"2323",
    "addr:street":"Molly Morgan Drv",
    "iso:country":"AU",
    "sg:address":"6 Molly Morgan Drv",
    "sg:city":"East Maitland",
    "sg:classifiers":[
        {
            "category":"Health Services",
            "subcategory":"Doctor",
            "type":"Services"
        }
    ],
    "sg:phone":"+61 2 4939 4777",
    "sg:postcode":"2323",
    "sg:province":"NSW",
    "sg:tags":[
        "medical",
        "practitioner"
    ],
    "wof:name":"Good Health GreenHills",
    "wof:placetype":"venue"
},
  "geometry": {"coordinates":[151.59378051799999,-32.7620048523],"type":"Point"}
}