{
  "type": "Feature",
  "properties": {
    "addr:full":"2051 Moggill Rd Kenmore QLD 4069",
    "addr:housenumber":"2051",
    "addr:postcode":"4069",
    "addr:street":"Moggill Rd",
    "iso:country":"AU",
    "sg:address":"2051 Moggill Rd",
    "sg:city":"Kenmore",
    "sg:classifiers":[
        {
            "category":"Manufacturing",
            "subcategory":"Chemicals & Compounds",
            "type":"Manufacturing & Wholesale Goods"
        }
    ],
    "sg:phone":"+61 7 3878 4011",
    "sg:postcode":"4069",
    "sg:province":"QLD",
    "sg:tags":[
        "agricultural"
    ],
    "wof:name":"Dow AgroSciences Australia Ltd",
    "wof:placetype":"venue"
},
  "geometry": {"coordinates":[152.93864440900001,-27.5076637268],"type":"Point"}
}