{
  "type": "Feature",
  "properties": {
    "addr:full":"Brush Rd Ourimbah NSW 2258",
    "addr:postcode":"2258",
    "addr:street":"Brush Rd",
    "iso:country":"AU",
    "sg:address":"Brush Rd",
    "sg:city":"Ourimbah",
    "sg:classifiers":[
        {
            "category":"Education",
            "subcategory":"University",
            "type":"Public Place"
        }
    ],
    "sg:phone":"+61 2 4348 4000",
    "sg:postcode":"2258",
    "sg:province":"NSW",
    "sg:tags":[
        "college",
        "tertiary"
    ],
    "wof:name":"University Of Newcastle Central Coast Campus",
    "wof:placetype":"venue"
},
  "geometry": {"coordinates":[151.37098693900001,-33.3585586548],"type":"Point"}
}