{
  "type": "Feature",
  "properties": {
    "addr:full":"62- 64 Switchback Rd Churchill VIC 3842",
    "addr:housenumber":"64",
    "addr:postcode":"3842",
    "addr:street":"Switchback Rd",
    "iso:country":"AU",
    "sg:address":"62- 64 Switchback Rd",
    "sg:city":"Churchill",
    "sg:classifiers":[
        {
            "category":"Home & Garden",
            "subcategory":"Building Materials",
            "type":"Retail Goods"
        }
    ],
    "sg:phone":"+61 3 5122 1077",
    "sg:postcode":"3842",
    "sg:province":"VIC",
    "sg:tags":[
        "supply"
    ],
    "wof:name":"Woody's Churchill Timber & Hardware",
    "wof:placetype":"venue"
},
  "geometry": {"coordinates":[146.40805053700001,-38.30651474],"type":"Point"}
}