{
  "type": "Feature",
  "properties": {
    "addr:full":"1-7 Reeves St Clifton Hill VIC 3068",
    "addr:housenumber":"1-7",
    "addr:postcode":"3068",
    "addr:street":"Reeves St",
    "iso:country":"AU",
    "sg:address":"1-7 Reeves St",
    "sg:city":"Clifton Hill",
    "sg:classifiers":[
        {
            "category":"Wholesale",
            "subcategory":"Apparel",
            "type":"Manufacturing & Wholesale Goods"
        }
    ],
    "sg:phone":"+61 3 9489 0333",
    "sg:postcode":"3068",
    "sg:province":"VIC",
    "sg:tags":[
        "wholesaler",
        "mfrs",
        "sportswear",
        "women's"
    ],
    "wof:name":"R?hnisch Sportwear Women Only",
    "wof:placetype":"venue"
},
  "geometry": {"coordinates":[144.986129761,-37.7931480408],"type":"Point"}
}