{
  "type": "Feature",
  "properties": {
    "addr:full":"27 Allan St Camira QLD 4300",
    "addr:housenumber":"27",
    "addr:postcode":"4300",
    "addr:street":"Allan St",
    "iso:country":"AU",
    "sg:address":"27 Allan St",
    "sg:city":"Camira",
    "sg:classifiers":[
        {
            "category":"Professional",
            "subcategory":"Art Services",
            "type":"Services"
        }
    ],
    "sg:phone":"+61 7 3288 5751",
    "sg:postcode":"4300",
    "sg:province":"QLD",
    "sg:tags":[
        "graphic",
        "designer"
    ],
    "wof:name":"Holloway Georgette",
    "wof:placetype":"venue"
},
  "geometry": {"coordinates":[152.90399169899999,-27.6169223785],"type":"Point"}
}