{
  "type": "Feature",
  "properties": {
    "iso:country":"AU",
    "sg:address":"24 Bowman St",
    "sg:city":"Crystal Brook",
    "sg:classifiers":[
        {
            "category":"Travel",
            "subcategory":"Hotels & Motels",
            "type":"Entertainment"
        }
    ],
    "sg:phone":"+61 8 8636 2018",
    "sg:postcode":"5523",
    "sg:province":"SA",
    "sg:tags":[
        "accommodation"
    ],
    "wof:name":"Royal Hotel",
    "wof:placetype":"venue"
},
  "geometry": {"coordinates":[138.20625305199999,-33.3526687622],"type":"Point"}
}