{
  "type": "Feature",
  "properties": {
    "addr:full":"8a/ 30 Erindale Rd Balcatta WA 6021",
    "addr:housenumber":"8a / 30",
    "addr:postcode":"6021",
    "addr:street":"Erindale Rd",
    "iso:country":"AU",
    "sg:address":"8a/ 30 Erindale Rd",
    "sg:city":"Balcatta",
    "sg:classifiers":[
        {
            "category":"Building & Trades",
            "subcategory":"Equipment Rental",
            "type":"Services"
        }
    ],
    "sg:phone":"+61 8 9240 7555",
    "sg:postcode":"6021",
    "sg:province":"WA",
    "sg:tags":[
        "party",
        "hire"
    ],
    "wof:name":"Lights&#039;n&#039;Vibes",
    "wof:placetype":"venue"
},
  "geometry": {"coordinates":[115.803497315,-31.8671760559],"type":"Point"}
}