{
  "type": "Feature",
  "properties": {
    "iso:country":"AU",
    "sg:address":"Lot 35 Smith Rd",
    "sg:city":"Gawler",
    "sg:classifiers":[
        {
            "category":"Professional",
            "type":"Services"
        }
    ],
    "sg:phone":"+61 8 8523 3077",
    "sg:postcode":"5118",
    "sg:province":"SA",
    "sg:tags":[
        "shop",
        "fitting"
    ],
    "wof:name":"Gawler Custom Cabinet Makers",
    "wof:placetype":"venue"
},
  "geometry": {"coordinates":[138.746506,-34.570034],"type":"Point"}
}