{
  "type": "Feature",
  "properties": {
    "addr:full":"508 Warringah Rd Frenchs Forest NSW 2086",
    "addr:housenumber":"508",
    "addr:postcode":"2086",
    "addr:street":"Warringah Rd",
    "iso:country":"AU",
    "sg:address":"508 Warringah Rd",
    "sg:city":"Frenchs Forest",
    "sg:classifiers":[
        {
            "category":"Professional",
            "subcategory":"Computer Services",
            "type":"Services"
        }
    ],
    "sg:phone":"+61 2 9451 1929",
    "sg:postcode":"2086",
    "sg:province":"NSW",
    "sg:tags":[
        "package",
        "software"
    ],
    "wof:name":"Uniloc Corporation Pty Ltd",
    "wof:placetype":"venue"
},
  "geometry": {"coordinates":[151.240768433,-33.7533454895],"type":"Point"}
}