{
  "type": "Feature",
  "properties": {
    "addr:full":"84 Katoomba St Katoomba NSW 2780",
    "addr:housenumber":"84",
    "addr:postcode":"2780",
    "addr:street":"Katoomba St",
    "iso:country":"AU",
    "sg:address":"84 Katoomba St",
    "sg:city":"Katoomba",
    "sg:classifiers":[
        {
            "category":"Utilities",
            "subcategory":"Water",
            "type":"Services"
        }
    ],
    "sg:phone":"+61 2 4782 1722",
    "sg:postcode":"2780",
    "sg:province":"NSW",
    "sg:tags":[
        "hot",
        "system"
    ],
    "wof:name":"Macarthurs Retravision",
    "wof:placetype":"venue"
},
  "geometry": {"coordinates":[150.311767578,-33.7139472961],"type":"Point"}
}