{
  "type": "Feature",
  "properties": {
    "addr:full":"477 Balcombe Rd Beaumaris VIC 3193",
    "addr:housenumber":"477",
    "addr:postcode":"3193",
    "addr:street":"Balcombe Rd",
    "iso:country":"AU",
    "sg:address":"477 Balcombe Rd",
    "sg:city":"Beaumaris",
    "sg:classifiers":[
        {
            "category":"Professional",
            "subcategory":"Accounting & Tax Preparation",
            "type":"Services"
        }
    ],
    "sg:phone":"+61 3 9589 3521",
    "sg:postcode":"3193",
    "sg:province":"VIC",
    "sg:tags":[
        "consultant",
        "taxation"
    ],
    "wof:name":"Hermann & Associates",
    "wof:placetype":"venue"
},
  "geometry": {"coordinates":[145.03027343799999,-37.9772415161],"type":"Point"}
}