{
  "type": "Feature",
  "properties": {
    "iso:country":"AU",
    "sg:address":"200 Middleton Rd",
    "sg:city":"Albany",
    "sg:classifiers":[
        {
            "category":"Health Services",
            "subcategory":"Dentist",
            "type":"Services"
        }
    ],
    "sg:phone":"+61 8 9841 5653",
    "sg:postcode":"6330",
    "sg:province":"WA",
    "wof:name":"Lyons Michael Dr",
    "wof:placetype":"venue"
},
  "geometry": {"coordinates":[117.897438049,-35.0176429749],"type":"Point"}
}