{
  "type": "Feature",
  "properties": {
    "addr:full":"10 Gina Pl Ayr QLD 4807",
    "addr:housenumber":"10",
    "addr:postcode":"4807",
    "addr:street":"Gina Pl",
    "iso:country":"AU",
    "sg:address":"10 Gina Pl",
    "sg:city":"Ayr",
    "sg:classifiers":[
        {
            "category":"Military Area",
            "subcategory":"Air Force Base",
            "type":"Public Place"
        }
    ],
    "sg:phone":"+61 7 4783 3148",
    "sg:postcode":"4807",
    "sg:province":"QLD",
    "sg:tags":[
        "conditioner",
        "treatment",
        "soil"
    ],
    "wof:name":"Inkerman Lime & Gypsum",
    "wof:placetype":"venue"
},
  "geometry": {"coordinates":[147.418869019,-19.5320167542],"type":"Point"}
}