{
  "type": "Feature",
  "properties": {
    "addr:full":"11- 17 Pearl St Derwent Park TAS 7009",
    "addr:housenumber":"17",
    "addr:postcode":"7009",
    "addr:street":"Pearl St",
    "iso:country":"AU",
    "sg:address":"11- 17 Pearl St",
    "sg:city":"Derwent Park",
    "sg:classifiers":[
        {
            "category":"Professional",
            "subcategory":"Detective & Security Services",
            "type":"Services"
        }
    ],
    "sg:phone":"+61 3 6272 0211",
    "sg:postcode":"7009",
    "sg:province":"TAS",
    "sg:tags":[
        "consultant",
        "system"
    ],
    "wof:name":"Pacific Communications",
    "wof:placetype":"venue"
},
  "geometry": {"coordinates":[147.29852294899999,-42.837928772],"type":"Point"}
}