{
  "type": "Feature",
  "properties": {
    "iso:country":"AU",
    "sg:address":"98 Balmoral St",
    "sg:city":"Hornsby",
    "sg:classifiers":[
        {
            "category":"Health Services",
            "subcategory":"Doctor",
            "type":"Services"
        }
    ],
    "sg:phone":"+61 2 9476 3644",
    "sg:postcode":"2077",
    "sg:province":"NSW",
    "sg:tags":[
        "medical",
        "practitioner"
    ],
    "wof:name":"Hadgis Christopher Dr",
    "wof:placetype":"venue"
},
  "geometry": {"coordinates":[151.110275269,-33.7027168274],"type":"Point"}
}