{
  "type": "Feature",
  "properties": {
    "addr:full":"Glen Bold Rd Mylor SA 5153",
    "addr:postcode":"5153",
    "addr:street":"Bold Rd",
    "iso:country":"AU",
    "sg:address":"Glen Bold Rd",
    "sg:city":"Mylor",
    "sg:classifiers":[
        {
            "category":"Farming",
            "subcategory":"Livestock Farm",
            "type":"Manufacturing & Wholesale Goods"
        }
    ],
    "sg:phone":"+61 8 8388 5228",
    "sg:postcode":"5153",
    "sg:province":"SA",
    "sg:tags":[
        "breeder",
        "horse",
        "stud"
    ],
    "wof:name":"Glenrose Park Stud",
    "wof:placetype":"venue"
},
  "geometry": {"coordinates":[138.76890564000001,-35.0652046204],"type":"Point"}
}