{
  "type": "Feature",
  "properties": {
    "addr:full":"Unit 6/ 20 Vale St Malaga WA 6090",
    "addr:housenumber":"20",
    "addr:postcode":"6090",
    "addr:street":"Vale St",
    "iso:country":"AU",
    "sg:address":"Unit 6/ 20 Vale St",
    "sg:city":"Malaga",
    "sg:classifiers":[
        {
            "category":"Home & Garden",
            "subcategory":"Building Materials",
            "type":"Retail Goods"
        }
    ],
    "sg:phone":"+61 8 9249 5334",
    "sg:postcode":"6090",
    "sg:province":"WA",
    "sg:tags":[
        "shutter",
        "roller",
        "grille"
    ],
    "wof:name":"Roller Shutter Guard",
    "wof:placetype":"venue"
},
  "geometry": {"coordinates":[115.89173126199999,-31.848405838],"type":"Point"}
}