{
  "type": "Feature",
  "properties": {
    "iso:country":"AU",
    "sg:address":"137 Haig Rd",
    "sg:city":"Auchenflower",
    "sg:classifiers":[
        {
            "category":"Real Estate",
            "subcategory":"Architect",
            "type":"Services"
        }
    ],
    "sg:phone":"+61 7 3217 7550",
    "sg:postcode":"4066",
    "sg:province":"QLD",
    "wof:name":"Jeremy Salmon - Architect",
    "wof:placetype":"venue"
},
  "geometry": {"coordinates":[152.99522399899999,-27.471654892],"type":"Point"}
}