{
  "type": "Feature",
  "properties": {
    "iso:country":"AU",
    "sg:address":"19 Grevillia Drv",
    "sg:city":"Mackay",
    "sg:classifiers":[
        {
            "category":"Building & Trades",
            "subcategory":"Construction",
            "type":"Services"
        }
    ],
    "sg:phone":"+61 7 4942 2030",
    "sg:postcode":"4740",
    "sg:province":"QLD",
    "sg:tags":[
        "contractor"
    ],
    "wof:name":"Buchbach PA & DE",
    "wof:placetype":"venue"
},
  "geometry": {"coordinates":[149.149277,-21.113916],"type":"Point"}
}