{
  "type": "Feature",
  "properties": {
    "iso:country":"AU",
    "sg:address":"20 Memorial Ave",
    "sg:city":"Ingleburn",
    "sg:classifiers":[
        {
            "category":"Autos & Motor Vehicles",
            "subcategory":"Auto Supplies",
            "type":"Retail Goods"
        }
    ],
    "sg:phone":"+61 2 9605 9490",
    "sg:postcode":"2565",
    "sg:province":"NSW",
    "sg:tags":[
        "tyre"
    ],
    "wof:name":"Ingleburn Alignment Mechanical & Tyres",
    "wof:placetype":"venue"
},
  "geometry": {"coordinates":[150.86158752399999,-33.9952735901],"type":"Point"}
}