{
  "type": "Feature",
  "properties": {
    "addr:full":"Unit 25/ 7- 13, Victoria Ave Castle Hill NSW 2154",
    "addr:housenumber":"/ 7 13",
    "addr:postcode":"2154",
    "addr:street":"Victoria Ave",
    "iso:country":"AU",
    "sg:address":"Unit 25/ 7- 13, Victoria Ave",
    "sg:city":"Castle Hill",
    "sg:classifiers":[
        {
            "category":"Autos & Motor Vehicles",
            "subcategory":"Auto Supplies",
            "type":"Retail Goods"
        }
    ],
    "sg:phone":"+61 2 9894 5949",
    "sg:postcode":"2154",
    "sg:province":"NSW",
    "sg:tags":[
        "car",
        "alarm"
    ],
    "wof:name":"T & K Security Pty Ltd",
    "wof:placetype":"venue"
},
  "geometry": {"coordinates":[150.98016357399999,-33.7314300537],"type":"Point"}
}