{
  "type": "Feature",
  "properties": {
    "addr:full":"U20/ 176 Sunnyholt Rd Blacktown NSW 2148",
    "addr:postcode":"2148",
    "addr:street":"/ 176 Sunnyholt Rd",
    "iso:country":"AU",
    "sg:address":"U20/ 176 Sunnyholt Rd",
    "sg:city":"Blacktown",
    "sg:classifiers":[
        {
            "category":"Shopping",
            "subcategory":"Pets & Pet Supplies",
            "type":"Retail Goods"
        }
    ],
    "sg:phone":"+61 2 9676 1755",
    "sg:postcode":"2148",
    "sg:province":"NSW",
    "sg:tags":[
        "food"
    ],
    "wof:name":"Well Being 4 Pets",
    "wof:placetype":"venue"
},
  "geometry": {"coordinates":[150.91563415499999,-33.7503852844],"type":"Point"}
}