{
  "type": "Feature",
  "properties": {
    "addr:full":"2102 The Forum Tower 1 Sergents La St Leonards NSW 2065",
    "addr:housenumber":"2102;forum;1",
    "addr:postcode":"2065",
    "addr:street":"The;Sergents La",
    "iso:country":"AU",
    "sg:address":"2102 The Forum Tower 1 Sergents La St",
    "sg:city":"Leonards",
    "sg:classifiers":[
        {
            "category":"Professional",
            "subcategory":"Employment Agencies",
            "type":"Services"
        }
    ],
    "sg:phone":"+61 415 606 610",
    "sg:postcode":"2065",
    "sg:province":"NSW",
    "sg:tags":[
        "provider",
        "internet"
    ],
    "wof:name":"A1 Plus Web Design Nu-Line",
    "wof:placetype":"venue"
},
  "geometry": {"coordinates":[151.19468689000001,-33.822303772],"type":"Point"}
}