{
  "type": "Feature",
  "properties": {
    "iso:country":"AU",
    "sg:address":"152 Elanora Rd",
    "sg:city":"Elanora Heights",
    "sg:classifiers":[
        {
            "category":"Real Estate",
            "subcategory":"Real Estate Agent",
            "type":"Services"
        }
    ],
    "sg:phone":"+61 2 9970 7070",
    "sg:postcode":"2101",
    "sg:province":"NSW",
    "wof:name":"Sue Morgan Real Estate",
    "wof:placetype":"venue"
},
  "geometry": {"coordinates":[151.276535,-33.698597],"type":"Point"}
}