{
  "type": "Feature",
  "properties": {
    "addr:full":"Cnr Hester Ave & Merriwa St Merriwa WA 6030",
    "addr:postcode":"6030",
    "addr:street":"Hester Ave & Merriwa St",
    "iso:country":"AU",
    "sg:address":"Cnr Hester Ave & Merriwa St",
    "sg:city":"Merriwa",
    "sg:classifiers":[
        {
            "category":"Autos & Motor Vehicles",
            "subcategory":"Fuel & Gas Station",
            "type":"Retail Goods"
        }
    ],
    "sg:phone":"+61 8 9305 8531",
    "sg:postcode":"6030",
    "sg:province":"WA",
    "wof:name":"BP",
    "wof:placetype":"venue"
},
  "geometry": {"coordinates":[115.715827942,-31.6741371155],"type":"Point"}
}