{
  "type": "Feature",
  "properties": {
    "addr:full":"PO Box 167 Essendon VIC 3040",
    "addr:postcode":"3040",
    "iso:country":"AU",
    "sg:address":"PO Box 167",
    "sg:city":"Essendon",
    "sg:classifiers":[
        {
            "category":"Retail",
            "subcategory":"Laundry & Dry Cleaning",
            "type":"Services"
        }
    ],
    "sg:phone":"+61 3 9336 0147",
    "sg:postcode":"3040",
    "sg:province":"VIC",
    "sg:tags":[
        "cloth",
        "supply"
    ],
    "wof:name":"AAAA Ragman Products",
    "wof:placetype":"venue"
},
  "geometry": {"coordinates":[144.90951538100001,-37.7515411377],"type":"Point"}
}