{
  "type": "Feature",
  "properties": {
    "iso:country":"AU",
    "sg:address":"198 Edith St",
    "sg:city":"Innisfail",
    "sg:classifiers":[
        {
            "category":"Food & Beverages",
            "subcategory":"Bakery",
            "type":"Retail Goods"
        }
    ],
    "sg:phone":"+61 7 4061 8601",
    "sg:postcode":"4860",
    "sg:province":"QLD",
    "sg:tags":[
        "baker"
    ],
    "wof:name":"Goondi Hill Bakery",
    "wof:placetype":"venue"
},
  "geometry": {"coordinates":[146.020355225,-17.5241127014],"type":"Point"}
}