{
  "type": "Feature",
  "properties": {
    "addr:full":"11 Kelvin Grove St Maryborough QLD 4650",
    "addr:housenumber":"11",
    "addr:postcode":"4650",
    "addr:street":"Kelvin Grove St",
    "iso:country":"AU",
    "sg:address":"11 Kelvin Grove St",
    "sg:city":"Maryborough",
    "sg:classifiers":[
        {
            "category":"Professional",
            "subcategory":"Printing & Photocopies",
            "type":"Services"
        }
    ],
    "sg:phone":"+61 7 4121 4587",
    "sg:postcode":"4650",
    "sg:province":"QLD",
    "sg:tags":[
        "screen",
        "printer"
    ],
    "wof:name":"Klein Signs",
    "wof:placetype":"venue"
},
  "geometry": {"coordinates":[152.67484999999999,-25.552513],"type":"Point"}
}