{
  "type": "Feature",
  "properties": {
    "addr:full":"Shp 18 BKK Shopng Cntr Cnr Evan & Barber Ave Eastlakes NSW 2018",
    "addr:housenumber":"18",
    "addr:postcode":"2018",
    "addr:street":"Bkk Shopng Cntr Cnr Evan;Ave",
    "iso:country":"AU",
    "sg:address":"Shp 18 BKK Shopng Cntr Cnr Evan & Barber Ave",
    "sg:city":"Eastlakes",
    "sg:classifiers":[
        {
            "category":"Food & Beverages",
            "subcategory":"Meat & Fish",
            "type":"Retail Goods"
        }
    ],
    "sg:phone":"+61 2 9317 3218",
    "sg:postcode":"2018",
    "sg:province":"NSW",
    "sg:tags":[
        "seafood"
    ],
    "wof:name":"Hai Loi Fish Market",
    "wof:placetype":"venue"
},
  "geometry": {"coordinates":[151.211959839,-33.9257888794],"type":"Point"}
}