{
  "type": "Feature",
  "properties": {
    "addr:full":"93 Kent Rd Pascoe Vale VIC 3044",
    "addr:housenumber":"93",
    "addr:postcode":"3044",
    "addr:street":"Kent Rd",
    "iso:country":"AU",
    "sg:address":"93 Kent Rd",
    "sg:city":"Pascoe Vale",
    "sg:classifiers":[
        {
            "category":"Communications",
            "subcategory":"News Services",
            "type":"Services"
        }
    ],
    "sg:phone":"+61 3 9354 7599",
    "sg:postcode":"3044",
    "sg:province":"VIC",
    "sg:tags":[
        "information",
        "tourist",
        "attractions"
    ],
    "wof:name":"Country Victoria",
    "wof:placetype":"venue"
},
  "geometry": {"coordinates":[144.941864014,-37.7203598022],"type":"Point"}
}