{
  "type": "Feature",
  "properties": {
    "addr:full":"Auckland St Bega NSW 2550",
    "addr:postcode":"2550",
    "addr:street":"St",
    "iso:country":"AU",
    "sg:address":"Auckland St",
    "sg:city":"Bega",
    "sg:classifiers":[
        {
            "category":"Professional",
            "type":"Services"
        }
    ],
    "sg:phone":"+61 2 6492 1005",
    "sg:postcode":"2550",
    "sg:province":"NSW",
    "sg:tags":[
        "auctioneer"
    ],
    "wof:name":"Gowing A J",
    "wof:placetype":"venue"
},
  "geometry": {"coordinates":[149.69883727999999,-36.7651786804],"type":"Point"}
}