{
  "type": "Feature",
  "properties": {
    "addr:full":"21 Wells Rd Mordialloc VIC 3195",
    "addr:housenumber":"21",
    "addr:postcode":"3195",
    "addr:street":"Wells Rd",
    "iso:country":"AU",
    "sg:address":"21 Wells Rd",
    "sg:city":"Mordialloc",
    "sg:classifiers":[
        {
            "category":"Farming",
            "subcategory":"Fish & Marine Products",
            "type":"Manufacturing & Wholesale Goods"
        }
    ],
    "sg:phone":"+61 3 9586 8900",
    "sg:postcode":"3195",
    "sg:province":"VIC",
    "sg:tags":[
        "production",
        "seafood",
        "processing"
    ],
    "wof:name":"Moyston Fisheries Ltd",
    "wof:placetype":"venue"
},
  "geometry": {"coordinates":[145.10115051299999,-38.0107917786],"type":"Point"}
}