{
  "type": "Feature",
  "properties": {
    "addr:full":"10 Birdwood St Box Hill VIC 3128",
    "addr:housenumber":"10",
    "addr:postcode":"3128",
    "addr:street":"Birdwood St",
    "iso:country":"AU",
    "sg:address":"10 Birdwood St",
    "sg:city":"Box Hill",
    "sg:classifiers":[
        {
            "category":"Building & Trades",
            "subcategory":"Equipment Rental",
            "type":"Services"
        }
    ],
    "sg:phone":"+61 418 336 697",
    "sg:postcode":"3128",
    "sg:province":"VIC",
    "sg:tags":[
        "supply",
        "catering"
    ],
    "wof:name":"Bar-Quip Beverage Systems",
    "wof:placetype":"venue"
},
  "geometry": {"coordinates":[145.125656128,-37.8301925659],"type":"Point"}
}