{
  "type": "Feature",
  "properties": {
    "addr:full":"3 Norton St Wagga Wagga NSW 2650",
    "addr:housenumber":"3",
    "addr:postcode":"2650",
    "addr:street":"Norton St",
    "iso:country":"AU",
    "sg:address":"3 Norton St",
    "sg:city":"Wagga Wagga",
    "sg:classifiers":[
        {
            "category":"Banks & Credit Unions",
            "subcategory":"Investment Brokerage",
            "type":"Services"
        }
    ],
    "sg:phone":"+61 2 6921 4206",
    "sg:postcode":"2650",
    "sg:province":"NSW",
    "sg:tags":[
        "shutter",
        "louvre"
    ],
    "wof:name":"LouverShield Pty Ltd",
    "wof:placetype":"venue"
},
  "geometry": {"coordinates":[147.38160705600001,-35.1212158203],"type":"Point"}
}