{
  "type": "Feature",
  "properties": {
    "iso:country":"AU",
    "sg:address":"6 Ledbury Crt",
    "sg:city":"Toorak",
    "sg:classifiers":[
        {
            "category":"Health Services",
            "subcategory":"Doctor",
            "type":"Services"
        }
    ],
    "sg:phone":"+61 3 9822 7326",
    "sg:postcode":"3142",
    "sg:province":"VIC",
    "sg:tags":[
        "medical",
        "practitioner"
    ],
    "wof:name":"Hadley Hugh",
    "wof:placetype":"venue"
},
  "geometry": {"coordinates":[145.029464722,-37.8469543457],"type":"Point"}
}