{
  "type": "Feature",
  "properties": {
    "iso:country":"AU",
    "sg:address":"207 Maitland Rd",
    "sg:city":"Tighes Hill",
    "sg:classifiers":[
        {
            "category":"Travel",
            "subcategory":"Hotels & Motels",
            "type":"Entertainment"
        }
    ],
    "sg:phone":"+61 2 4961 1977",
    "sg:postcode":"2297",
    "sg:province":"NSW",
    "sg:tags":[
        "accommodation"
    ],
    "wof:name":"Royal Oak Hotel",
    "wof:placetype":"venue"
},
  "geometry": {"coordinates":[151.74766540499999,-32.9064712524],"type":"Point"}
}