{
  "type": "Feature",
  "properties": {
    "iso:country":"AU",
    "sg:address":"5 Hamill St",
    "sg:city":"Garbutt",
    "sg:classifiers":[
        {
            "category":"Building & Trades",
            "subcategory":"Pest Control",
            "type":"Services"
        }
    ],
    "sg:phone":"+61 7 4779 6376",
    "sg:postcode":"4814",
    "sg:province":"QLD",
    "sg:tags":[
        "controller",
        "automatic"
    ],
    "wof:name":"Stan Agencies Pty Ltd",
    "wof:placetype":"venue"
},
  "geometry": {"coordinates":[146.75990300000001,-19.265795],"type":"Point"}
}