{
  "type": "Feature",
  "properties": {
    "addr:full":"Factory 1 / 10 Clarice Rd Box Hill South VIC 3128",
    "addr:housenumber":"/ 10",
    "addr:postcode":"3128",
    "addr:street":"Clarice Rd",
    "iso:country":"AU",
    "sg:address":"Factory 1 / 10 Clarice Rd",
    "sg:city":"Box Hill South",
    "sg:classifiers":[
        {
            "category":"Building & Trades",
            "subcategory":"Cleaning & Sanitation",
            "type":"Services"
        }
    ],
    "sg:phone":"+61 418 319 509",
    "sg:postcode":"3128",
    "sg:province":"VIC",
    "sg:tags":[
        "commercial",
        "maintenance"
    ],
    "wof:name":"All Clear Drain Cleaning Pty Ltd",
    "wof:placetype":"venue"
},
  "geometry": {"coordinates":[145.133636475,-37.8356895447],"type":"Point"}
}