{
  "type": "Feature",
  "properties": {
    "iso:country":"AU",
    "sg:address":"Suite 20, 119 Camooweal St",
    "sg:city":"Mt Isa",
    "sg:classifiers":[
        {
            "category":"Professional",
            "subcategory":"Engineering",
            "type":"Services"
        }
    ],
    "sg:phone":"+61 7 4749 2355",
    "sg:postcode":"4825",
    "sg:province":"QLD",
    "sg:tags":[
        "installation",
        "maintenance",
        "engineer"
    ],
    "wof:name":"Transfield Services (Australia)",
    "wof:placetype":"venue"
},
  "geometry": {"coordinates":[139.493622,-20.722235],"type":"Point"}
}