{
  "type": "Feature",
  "properties": {
    "iso:country":"AU",
    "sg:address":"U3/ 416 Church Rd",
    "sg:city":"Templestowe",
    "sg:classifiers":[
        {
            "category":"Building & Trades",
            "subcategory":"Construction",
            "type":"Services"
        }
    ],
    "sg:phone":"+61 411 743 203",
    "sg:postcode":"3106",
    "sg:province":"VIC",
    "sg:tags":[
        "roof"
    ],
    "wof:name":"D K L Roofing Service",
    "wof:placetype":"venue"
},
  "geometry": {"coordinates":[145.14382934599999,-37.7552032471],"type":"Point"}
}