{
  "type": "Feature",
  "properties": {
    "addr:full":"Arthur St Rosebery TAS 7470",
    "addr:postcode":"7470",
    "addr:street":"Arthur St",
    "iso:country":"AU",
    "sg:address":"Arthur St",
    "sg:city":"Rosebery",
    "sg:classifiers":[
        {
            "category":"Health Services",
            "subcategory":"Dentist",
            "type":"Services"
        }
    ],
    "sg:phone":"+61 3 6473 1311",
    "sg:postcode":"7470",
    "sg:province":"TAS",
    "wof:name":"Jay N Kotay Dr",
    "wof:placetype":"venue"
},
  "geometry": {"coordinates":[145.54916381800001,-42.0773773193],"type":"Point"}
}