{
  "type": "Feature",
  "properties": {
    "iso:country":"AU",
    "sg:address":"32 Highfield Rd",
    "sg:city":"Quakers Hill",
    "sg:classifiers":[
        {
            "category":"Government",
            "subcategory":"Court House",
            "type":"Public Place"
        }
    ],
    "sg:phone":"+61 2 9626 6620",
    "sg:postcode":"2763",
    "sg:province":"NSW",
    "sg:tags":[
        "personal",
        "marriage",
        "family",
        "counselling"
    ],
    "wof:name":"Quakers Hill Family Services",
    "wof:placetype":"venue"
},
  "geometry": {"coordinates":[150.89166259800001,-33.7294464111],"type":"Point"}
}