{
  "type": "Feature",
  "properties": {
    "iso:country":"AU",
    "sg:address":"1/ 276 Charters Towers Rd",
    "sg:city":"Hermit Park",
    "sg:classifiers":[
        {
            "category":"Sports & Exercise",
            "subcategory":"Sports Center",
            "type":"Entertainment"
        }
    ],
    "sg:phone":"+61 412 843 798",
    "sg:postcode":"4812",
    "sg:province":"QLD",
    "sg:tags":[
        "physiologist"
    ],
    "wof:name":"Brent Goriss",
    "wof:placetype":"venue"
},
  "geometry": {"coordinates":[146.796402,-19.29027],"type":"Point"}
}