{
  "type": "Feature",
  "properties": {
    "iso:country":"AU",
    "sg:address":"383 High St Rd",
    "sg:city":"Mt Waverley",
    "sg:classifiers":[
        {
            "category":"Education",
            "subcategory":"University",
            "type":"Public Place"
        }
    ],
    "sg:phone":"+61 3 9807 4755",
    "sg:postcode":"3149",
    "sg:province":"VIC",
    "sg:tags":[
        "educational",
        "organisation",
        "cultural"
    ],
    "wof:name":"Universities Of The Third Age (U3A) - Victorian Network",
    "wof:placetype":"venue"
},
  "geometry": {"coordinates":[145.134002686,-37.8703193665],"type":"Point"}
}