{
  "type": "Feature",
  "properties": {
    "iso:country":"AU",
    "sg:address":"Shop 1 15 Anglo Rd",
    "sg:city":"Campsie",
    "sg:classifiers":[
        {
            "category":"Personal",
            "subcategory":"Beauty Salon",
            "type":"Services"
        }
    ],
    "sg:phone":"+61 2 9787 2800",
    "sg:postcode":"2194",
    "sg:province":"NSW",
    "wof:name":"Katherine Facial & Body Skin Care",
    "wof:placetype":"venue"
},
  "geometry": {"coordinates":[151.102844,-33.911163],"type":"Point"}
}