{
  "type": "Feature",
  "properties": {
    "iso:country":"AU",
    "sg:address":"21 Parsonage Rd",
    "sg:city":"Castle Hill",
    "sg:classifiers":[
        {
            "category":"Professional",
            "subcategory":"Art Services",
            "type":"Services"
        }
    ],
    "sg:phone":"+61 2 9560 8701",
    "sg:postcode":"2154",
    "sg:province":"NSW",
    "sg:tags":[
        "decorator",
        "painter"
    ],
    "wof:name":"Holdforth David",
    "wof:placetype":"venue"
},
  "geometry": {"coordinates":[150.99838256800001,-33.7367553711],"type":"Point"}
}