{
  "type": "Feature",
  "properties": {
    "iso:country":"AU",
    "sg:address":"7 Brazel Crt",
    "sg:city":"Loganholme",
    "sg:classifiers":[
        {
            "category":"Building & Trades",
            "subcategory":"Construction",
            "type":"Services"
        }
    ],
    "sg:phone":"+61 7 3287 7128",
    "sg:postcode":"4129",
    "sg:province":"QLD",
    "sg:tags":[
        "installation",
        "air conditioning"
    ],
    "wof:name":"All Type Airconditioning",
    "wof:placetype":"venue"
},
  "geometry": {"coordinates":[153.202270508,-27.6764125824],"type":"Point"}
}