{
  "type": "Feature",
  "properties": {
    "iso:country":"AU",
    "sg:address":"355 Great Western Hwy",
    "sg:city":"Blackheath",
    "sg:classifiers":[
        {
            "category":"Home & Garden",
            "subcategory":"Garden Supply",
            "type":"Retail Goods"
        }
    ],
    "sg:phone":"+61 2 4787 8339",
    "sg:postcode":"2785",
    "sg:province":"NSW",
    "sg:tags":[
        "equipment"
    ],
    "wof:name":"Mt Boyce Garden Centre Pty. Ltd. Landscape Supplies",
    "wof:placetype":"venue"
},
  "geometry": {"coordinates":[150.29017639200001,-33.7007446289],"type":"Point"}
}