{
  "type": "Feature",
  "properties": {
    "addr:full":"Shp 3, 47 East Pde Buxton NSW 2571",
    "addr:housenumber":"47",
    "addr:postcode":"2571",
    "addr:street":"East Pde",
    "iso:country":"AU",
    "sg:address":"Shp 3, 47 East Pde",
    "sg:city":"Buxton",
    "sg:classifiers":[
        {
            "category":"Fast Food",
            "type":"Food & Drink"
        }
    ],
    "sg:phone":"+61 2 4683 1555",
    "sg:postcode":"2571",
    "sg:province":"NSW",
    "sg:tags":[
        "away",
        "take"
    ],
    "wof:name":"Brons Place",
    "wof:placetype":"venue"
},
  "geometry": {"coordinates":[150.53460693400001,-34.2547111511],"type":"Point"}
}