{
  "type": "Feature",
  "properties": {
    "iso:country":"AU",
    "sg:address":"Lillypilly Rd",
    "sg:city":"Leeton",
    "sg:classifiers":[
        {
            "category":"Farming",
            "subcategory":"Vineyard",
            "type":"Manufacturing & Wholesale Goods"
        }
    ],
    "sg:phone":"+61 2 6953 4069",
    "sg:postcode":"2705",
    "sg:province":"NSW",
    "sg:tags":[
        "winery"
    ],
    "wof:name":"Lillypilly Estate Winery",
    "wof:placetype":"venue"
},
  "geometry": {"coordinates":[146.41282653799999,-34.5715789795],"type":"Point"}
}