{
  "type": "Feature",
  "properties": {
    "iso:country":"AU",
    "sg:address":"461 Bronte Rd",
    "sg:city":"Bronte",
    "sg:classifiers":[
        {
            "category":"Building & Trades",
            "subcategory":"Cleaning & Sanitation",
            "type":"Services"
        }
    ],
    "sg:phone":"+61 408 004 900",
    "sg:postcode":"2024",
    "sg:province":"NSW",
    "sg:tags":[
        "window"
    ],
    "wof:name":"G James Glass Cleaning",
    "wof:placetype":"venue"
},
  "geometry": {"coordinates":[151.26678466800001,-33.9047584534],"type":"Point"}
}