{
  "type": "Feature",
  "properties": {
    "iso:country":"AU",
    "sg:address":"234 Welshpool Rd",
    "sg:city":"Welshpool",
    "sg:classifiers":[
        {
            "category":"Professional",
            "subcategory":"Art Services",
            "type":"Services"
        }
    ],
    "sg:phone":"+61 8 9458 5759",
    "sg:postcode":"6106",
    "sg:province":"WA",
    "sg:tags":[
        "medical",
        "industrial",
        "gas"
    ],
    "wof:name":"BOC",
    "wof:placetype":"venue"
},
  "geometry": {"coordinates":[115.97386169400001,-32.0032348633],"type":"Point"}
}