{
  "type": "Feature",
  "properties": {
    "iso:country":"AU",
    "sg:address":"142 Old Gympie Rd",
    "sg:city":"Caboolture",
    "sg:classifiers":[
        {
            "category":"Fast Food",
            "type":"Food & Drink"
        }
    ],
    "sg:phone":"+61 407 767 444",
    "sg:postcode":"4510",
    "sg:province":"QLD",
    "sg:tags":[
        "away",
        "take"
    ],
    "wof:name":"Mobile Dutch Pancake House",
    "wof:placetype":"venue"
},
  "geometry": {"coordinates":[152.94186400000001,-27.059069],"type":"Point"}
}