{
  "type": "Feature",
  "properties": {
    "addr:full":"Level 1 Suite 3, 12 Laycock Ave Cronulla NSW 2230",
    "addr:housenumber":"12",
    "addr:postcode":"2230",
    "addr:street":"Laycock Ave",
    "iso:country":"AU",
    "sg:address":"Level 1 Suite 3, 12 Laycock Ave",
    "sg:city":"Cronulla",
    "sg:classifiers":[
        {
            "category":"Personal",
            "subcategory":"Hair Removal",
            "type":"Services"
        }
    ],
    "sg:phone":"+61 2 9527 7600",
    "sg:postcode":"2230",
    "sg:province":"NSW",
    "wof:name":"Evolve (Visual Transformations)",
    "wof:placetype":"venue"
},
  "geometry": {"coordinates":[151.15238952600001,-34.0568962097],"type":"Point"}
}