{
  "type": "Feature",
  "properties": {
    "addr:full":"Shp 1/ 528 Ashmore Rd Ashmore QLD 4214",
    "addr:housenumber":"/ 528",
    "addr:postcode":"4214",
    "addr:street":"Ashmore Rd",
    "iso:country":"AU",
    "sg:address":"Shp 1/ 528 Ashmore Rd",
    "sg:city":"Ashmore",
    "sg:classifiers":[
        {
            "category":"Food & Beverages",
            "subcategory":"Supermarket",
            "type":"Retail Goods"
        }
    ],
    "sg:phone":"+61 7 5539 5940",
    "sg:postcode":"4214",
    "sg:province":"QLD",
    "sg:tags":[
        "grocery",
        "store"
    ],
    "wof:name":"IGA Express Ashmore",
    "wof:placetype":"venue"
},
  "geometry": {"coordinates":[153.36686706500001,-27.9881362915],"type":"Point"}
}