{
  "type": "Feature",
  "properties": {
    "addr:full":"PO Box 857 Ulladulla NSW 2539",
    "addr:postcode":"2539",
    "iso:country":"AU",
    "sg:address":"PO Box 857",
    "sg:city":"Ulladulla",
    "sg:classifiers":[
        {
            "category":"Professional",
            "subcategory":"Computer Services",
            "type":"Services"
        }
    ],
    "sg:phone":"+61 405 231 690",
    "sg:postcode":"2539",
    "sg:province":"NSW",
    "sg:tags":[
        "technical",
        "support"
    ],
    "wof:name":"Grant's Computer Solutions",
    "wof:placetype":"venue"
},
  "geometry": {"coordinates":[150.475631714,-35.3509788513],"type":"Point"}
}