{
  "type": "Feature",
  "properties": {
    "iso:country":"AU",
    "sg:address":"59 Troughton Rd",
    "sg:city":"Sunnybank",
    "sg:classifiers":[
        {
            "category":"Building & Trades",
            "subcategory":"Construction",
            "type":"Services"
        }
    ],
    "sg:phone":"+61 7 3345 1654",
    "sg:postcode":"4109",
    "sg:province":"QLD",
    "sg:tags":[
        "contractor"
    ],
    "wof:name":"Linwood Homes",
    "wof:placetype":"venue"
},
  "geometry": {"coordinates":[153.04826355,-27.5727291107],"type":"Point"}
}