{
  "type": "Feature",
  "properties": {
    "addr:full":"Unit 2/ 12 Salisbury Rd Hornsby NSW 2077",
    "addr:housenumber":"12",
    "addr:postcode":"2077",
    "addr:street":"Salisbury Rd",
    "iso:country":"AU",
    "sg:address":"Unit 2/ 12 Salisbury Rd",
    "sg:city":"Hornsby",
    "sg:classifiers":[
        {
            "category":"Professional",
            "subcategory":"Testing Lab",
            "type":"Services"
        }
    ],
    "sg:phone":"+61 2 9477 7757",
    "sg:postcode":"2077",
    "sg:province":"NSW",
    "sg:tags":[
        "inspection"
    ],
    "wof:name":"International Compliance Testing",
    "wof:placetype":"venue"
},
  "geometry": {"coordinates":[151.11135864299999,-33.6965789795],"type":"Point"}
}