{
  "type": "Feature",
  "properties": {
    "addr:full":"Wallaroo Rd Hall ACT 2618",
    "addr:postcode":"2618",
    "addr:street":"Wallaroo Rd",
    "iso:country":"AU",
    "sg:address":"Wallaroo Rd",
    "sg:city":"Hall",
    "sg:classifiers":[
        {
            "category":"Building & Trades",
            "subcategory":"Construction",
            "type":"Services"
        }
    ],
    "sg:phone":"+61 2 6230 2772",
    "sg:postcode":"2618",
    "sg:province":"ACT",
    "sg:tags":[
        "contractor"
    ],
    "wof:name":"Randolph R H",
    "wof:placetype":"venue"
},
  "geometry": {"coordinates":[149.06175231899999,-35.173614502],"type":"Point"}
}