{
  "type": "Feature",
  "properties": {
    "iso:country":"AU",
    "sg:address":"53 Lookout Rd",
    "sg:city":"New Lambton",
    "sg:classifiers":[
        {
            "category":"Real Estate",
            "subcategory":"Real Estate Services",
            "type":"Services"
        }
    ],
    "sg:phone":"+61 2 4952 8771",
    "sg:postcode":"2305",
    "sg:province":"NSW",
    "sg:tags":[
        "listing"
    ],
    "wof:name":"Killala Kids",
    "wof:placetype":"venue"
},
  "geometry": {"coordinates":[151.696732,-32.925617],"type":"Point"}
}