{
  "type": "Feature",
  "properties": {
    "addr:full":"327 Peel St Tamworth NSW 2340",
    "addr:housenumber":"327",
    "addr:postcode":"2340",
    "addr:street":"Peel St",
    "iso:country":"AU",
    "sg:address":"327 Peel St",
    "sg:city":"Tamworth",
    "sg:classifiers":[
        {
            "category":"Travel",
            "subcategory":"Hotels & Motels",
            "type":"Entertainment"
        }
    ],
    "sg:phone":"+61 2 6766 2930",
    "sg:postcode":"2340",
    "sg:province":"NSW",
    "sg:tags":[
        "accommodation"
    ],
    "wof:name":"Tudor Hotel",
    "wof:placetype":"venue"
},
  "geometry": {"coordinates":[150.92950439399999,-31.0904216766],"type":"Point"}
}