{
  "type": "Feature",
  "properties": {
    "iso:country":"AU",
    "sg:address":"U6/ 70 Buderim Pines Drv",
    "sg:city":"Buderim",
    "sg:classifiers":[
        {
            "category":"Professional",
            "subcategory":"Detective & Security Services",
            "type":"Services"
        }
    ],
    "sg:phone":"+61 418 740 634",
    "sg:postcode":"4556",
    "sg:province":"QLD",
    "sg:tags":[
        "equipment",
        "window",
        "doors"
    ],
    "wof:name":"Micks Security Screens",
    "wof:placetype":"venue"
},
  "geometry": {"coordinates":[153.08244323700001,-26.684835434],"type":"Point"}
}