{
  "type": "Feature",
  "properties": {
    "addr:full":"4 Halls Rd Cedar Creek (Beenleigh) QLD 4520",
    "addr:housenumber":"4",
    "addr:postcode":"4520",
    "addr:street":"Halls Rd",
    "iso:country":"AU",
    "sg:address":"4 Halls Rd",
    "sg:city":"Cedar Creek (Beenleigh)",
    "sg:classifiers":[
        {
            "category":"Professional",
            "type":"Services"
        }
    ],
    "sg:phone":"+61 7 3289 4420",
    "sg:postcode":"4520",
    "sg:province":"QLD",
    "sg:tags":[
        "shop",
        "fitting"
    ],
    "wof:name":"Accent Systems",
    "wof:placetype":"venue"
},
  "geometry": {"coordinates":[152.88664199999999,-27.373671],"type":"Point"}
}