{
  "type": "Feature",
  "properties": {
    "addr:full":"14- 20 King St Melbourne VIC 3000",
    "addr:housenumber":"20",
    "addr:postcode":"3000",
    "addr:street":"King St",
    "iso:country":"AU",
    "sg:address":"14- 20 King St",
    "sg:city":"Melbourne",
    "sg:classifiers":[
        {
            "category":"Recreation",
            "subcategory":"Amusement Park",
            "type":"Entertainment"
        }
    ],
    "sg:phone":"+61 1300 131 916",
    "sg:postcode":"3000",
    "sg:province":"VIC",
    "wof:name":"Barcode",
    "wof:placetype":"venue"
},
  "geometry": {"coordinates":[144.957427978,-37.8196754456],"type":"Point"}
}