{
  "type": "Feature",
  "properties": {
    "addr:full":"210 Kruger Pde Redbank Plains QLD 4301",
    "addr:housenumber":"210",
    "addr:postcode":"4301",
    "addr:street":"Kruger Pde",
    "iso:country":"AU",
    "sg:address":"210 Kruger Pde",
    "sg:city":"Redbank Plains",
    "sg:classifiers":[
        {
            "category":"Home & Garden",
            "subcategory":"Carpets & Floor Coverings",
            "type":"Retail Goods"
        }
    ],
    "sg:phone":"+61 7 3814 2839",
    "sg:postcode":"4301",
    "sg:province":"QLD",
    "sg:tags":[
        "tile",
        "wall",
        "layer"
    ],
    "wof:name":"M. Pesic Tiling Specialists",
    "wof:placetype":"venue"
},
  "geometry": {"coordinates":[152.87449645999999,-27.6309108734],"type":"Point"}
}