{
  "type": "Feature",
  "properties": {
    "addr:full":"142 Princes Hwy Ulladulla NSW 2539",
    "addr:housenumber":"142",
    "addr:postcode":"2539",
    "addr:street":"Princes Hwy",
    "iso:country":"AU",
    "sg:address":"142 Princes Hwy",
    "sg:city":"Ulladulla",
    "sg:classifiers":[
        {
            "category":"Home & Garden",
            "subcategory":"Carpets & Floor Coverings",
            "type":"Retail Goods"
        }
    ],
    "sg:phone":"+61 2 4455 4849",
    "sg:postcode":"2539",
    "sg:province":"NSW",
    "sg:tags":[
        "tile",
        "wall"
    ],
    "wof:name":"Harbourside Tiles",
    "wof:placetype":"venue"
},
  "geometry": {"coordinates":[150.473556519,-35.3615951538],"type":"Point"}
}