{
  "type": "Feature",
  "properties": {
    "addr:full":"185 Vermont Rd Mowbray TAS 7248",
    "addr:housenumber":"185",
    "addr:postcode":"7248",
    "addr:street":"Vermont Rd",
    "iso:country":"AU",
    "sg:address":"185 Vermont Rd",
    "sg:city":"Mowbray",
    "sg:classifiers":[
        {
            "category":"Utilities",
            "subcategory":"Fuel Oil & Lpg",
            "type":"Services"
        }
    ],
    "sg:phone":"+61 3 6326 1025",
    "sg:postcode":"7248",
    "sg:province":"TAS",
    "sg:tags":[
        "merchant"
    ],
    "wof:name":"Northern Wood Supplies",
    "wof:placetype":"venue"
},
  "geometry": {"coordinates":[147.154464722,-41.4104728699],"type":"Point"}
}