{
  "type": "Feature",
  "properties": {
    "addr:full":"54 Portman St Oakleigh VIC 3166",
    "addr:housenumber":"54",
    "addr:postcode":"3166",
    "addr:street":"Portman St",
    "iso:country":"AU",
    "sg:address":"54 Portman St",
    "sg:city":"Oakleigh",
    "sg:classifiers":[
        {
            "category":"Arena",
            "subcategory":"Sports Club",
            "type":"Entertainment"
        }
    ],
    "sg:phone":"+61 3 9791 2700",
    "sg:postcode":"3166",
    "sg:province":"VIC",
    "sg:tags":[
        "defence",
        "supply",
        "self",
        "instruction",
        "martial art"
    ],
    "wof:name":"Wing Chung Kung Fu",
    "wof:placetype":"venue"
},
  "geometry": {"coordinates":[145.09080505399999,-37.9003295898],"type":"Point"}
}