{
  "type": "Feature",
  "properties": {
    "addr:full":"PO Box 279 Halls Creek WA 6770",
    "addr:postcode":"6770",
    "iso:country":"AU",
    "sg:address":"PO Box 279",
    "sg:city":"Halls Creek",
    "sg:classifiers":[
        {
            "category":"Airline",
            "type":"Transportation"
        }
    ],
    "sg:phone":"+61 8 9168 5100",
    "sg:postcode":"6770",
    "sg:province":"WA",
    "sg:tags":[
        "aircraft",
        "rental",
        "charter"
    ],
    "wof:name":"Northern Air Charter",
    "wof:placetype":"venue"
},
  "geometry": {"coordinates":[127.66699218799999,-18.2247505188],"type":"Point"}
}