{
  "type": "Feature",
  "properties": {
    "addr:full":"6/ 15 Grafton Crs Dee Why NSW 2099",
    "addr:housenumber":"/ 15",
    "addr:postcode":"2099",
    "addr:street":"Grafton Crs",
    "iso:country":"AU",
    "sg:address":"6/ 15 Grafton Crs",
    "sg:city":"Dee Why",
    "sg:classifiers":[
        {
            "category":"Personal",
            "subcategory":"Massage",
            "type":"Services"
        }
    ],
    "sg:phone":"+61 2 9972 1939",
    "sg:postcode":"2099",
    "sg:province":"NSW",
    "sg:tags":[
        "therapy"
    ],
    "wof:name":"Rejuvenation Enterprises",
    "wof:placetype":"venue"
},
  "geometry": {"coordinates":[151.285232544,-33.7537498474],"type":"Point"}
}