{
  "type": "Feature",
  "properties": {
    "addr:full":"491a Portrush Rd Glenunga SA 5064",
    "addr:housenumber":"491a",
    "addr:postcode":"5064",
    "addr:street":"Portrush Rd",
    "iso:country":"AU",
    "sg:address":"491a Portrush Rd",
    "sg:city":"Glenunga",
    "sg:classifiers":[
        {
            "category":"Health Services",
            "subcategory":"Doctor",
            "type":"Services"
        }
    ],
    "sg:phone":"+61 8 8379 0009",
    "sg:postcode":"5064",
    "sg:province":"SA",
    "sg:tags":[
        "podiatrist"
    ],
    "wof:name":"Burns Andrew",
    "wof:placetype":"venue"
},
  "geometry": {"coordinates":[138.642852783,-34.9466133118],"type":"Point"}
}