{
  "type": "Feature",
  "properties": {
    "addr:full":"131 Chester Pass Rd Albany WA 6330",
    "addr:housenumber":"131",
    "addr:postcode":"6330",
    "addr:street":"Chester Pass Rd",
    "iso:country":"AU",
    "sg:address":"131 Chester Pass Rd",
    "sg:city":"Albany",
    "sg:classifiers":[
        {
            "category":"Professional",
            "subcategory":"Accounting & Tax Preparation",
            "type":"Services"
        }
    ],
    "sg:phone":"+61 8 9841 7222",
    "sg:postcode":"6330",
    "sg:province":"WA",
    "sg:tags":[
        "insulation",
        "wholesaler",
        "material",
        "mfrs"
    ],
    "wof:name":"Albany Insulation",
    "wof:placetype":"venue"
},
  "geometry": {"coordinates":[117.872131348,-34.9921836853],"type":"Point"}
}