{
  "type": "Feature",
  "properties": {
    "addr:full":"12 Birchgrove Drv Orange NSW 2800",
    "addr:housenumber":"12",
    "addr:postcode":"2800",
    "addr:street":"Birchgrove Drv",
    "iso:country":"AU",
    "sg:address":"12 Birchgrove Drv",
    "sg:city":"Orange",
    "sg:classifiers":[
        {
            "category":"Professional",
            "subcategory":"Printing & Photocopies",
            "type":"Services"
        }
    ],
    "sg:phone":"+61 2 6362 2061",
    "sg:postcode":"2800",
    "sg:province":"NSW",
    "sg:tags":[
        "trophy"
    ],
    "wof:name":"Malleo Trophies",
    "wof:placetype":"venue"
},
  "geometry": {"coordinates":[149.07737731899999,-33.2725868225],"type":"Point"}
}