{
  "type": "Feature",
  "properties": {
    "addr:full":"833 Logan Rd Holland Park QLD 4121",
    "addr:housenumber":"833",
    "addr:postcode":"4121",
    "addr:street":"Logan Rd",
    "iso:country":"AU",
    "sg:address":"833 Logan Rd",
    "sg:city":"Holland Park",
    "sg:classifiers":[
        {
            "category":"Professional",
            "subcategory":"Accounting & Tax Preparation",
            "type":"Services"
        }
    ],
    "sg:phone":"+61 7 3394 2711",
    "sg:postcode":"4121",
    "sg:province":"QLD",
    "sg:tags":[
        "accountant",
        "auditor"
    ],
    "wof:name":"Lowe Tony & Co",
    "wof:placetype":"venue"
},
  "geometry": {"coordinates":[153.056732178,-27.5157814026],"type":"Point"}
}