{
  "type": "Feature",
  "properties": {
    "iso:country":"AU",
    "sg:address":"12- 14 Grandview Drv",
    "sg:city":"Mt Pleasant",
    "sg:classifiers":[
        {
            "category":"Banks & Credit Unions",
            "subcategory":"Bank",
            "type":"Services"
        }
    ],
    "sg:phone":"+61 13 20 32",
    "sg:postcode":"4521",
    "sg:province":"QLD",
    "wof:name":"Westpac Banking Corporation",
    "wof:placetype":"venue"
},
  "geometry": {"coordinates":[152.767487,-27.127399],"type":"Point"}
}