{
  "type": "Feature",
  "properties": {
    "addr:full":"266- 268 Forest Rd Hurstville NSW 2220",
    "addr:housenumber":"268",
    "addr:postcode":"2220",
    "addr:street":"Forest Rd",
    "iso:country":"AU",
    "sg:address":"266- 268 Forest Rd",
    "sg:city":"Hurstville",
    "sg:classifiers":[
        {
            "category":"Fast Food",
            "type":"Food & Drink"
        }
    ],
    "sg:phone":"+61 2 9570 9661",
    "sg:postcode":"2220",
    "sg:province":"NSW",
    "sg:tags":[
        "away",
        "take"
    ],
    "wof:name":"Hungry Jacks Pty Ltd",
    "wof:placetype":"venue"
},
  "geometry": {"coordinates":[151.103424072,-33.9670219421],"type":"Point"}
}