{
  "type": "Feature",
  "properties": {
    "addr:full":"Level 9, 533 Little Lonsdale St Melbourne VIC 3000",
    "addr:housenumber":"533",
    "addr:postcode":"3000",
    "addr:street":"Little Lonsdale St",
    "iso:country":"AU",
    "sg:address":"Level 9, 533 Little Lonsdale St",
    "sg:city":"Melbourne",
    "sg:classifiers":[
        {
            "category":"Education",
            "subcategory":"Special Training",
            "type":"Public Place"
        }
    ],
    "sg:phone":"+61 3 9926 4698",
    "sg:postcode":"3000",
    "sg:province":"VIC",
    "sg:tags":[
        "development"
    ],
    "wof:name":"AMES Consulting",
    "wof:placetype":"venue"
},
  "geometry": {"coordinates":[144.956176758,-37.8130645752],"type":"Point"}
}