{
  "type": "Feature",
  "properties": {
    "addr:full":"44 Panfield Ave Ringwood North VIC 3134",
    "addr:housenumber":"44",
    "addr:postcode":"3134",
    "addr:street":"Panfield Ave",
    "iso:country":"AU",
    "sg:address":"44 Panfield Ave",
    "sg:city":"Ringwood North",
    "sg:classifiers":[
        {
            "category":"Food & Beverages",
            "subcategory":"Groceries & Convenience Stores",
            "type":"Retail Goods"
        }
    ],
    "sg:phone":"+61 3 9870 2118",
    "sg:postcode":"3134",
    "sg:province":"VIC",
    "wof:name":"Jones Milkbar",
    "wof:placetype":"venue"
},
  "geometry": {"coordinates":[145.24082946799999,-37.7986335754],"type":"Point"}
}