{
  "type": "Feature",
  "properties": {
    "addr:full":"Unit 9 16 Ledger Rd Balcatta WA 6021",
    "addr:housenumber":"16",
    "addr:postcode":"6021",
    "addr:street":"Ledger Rd",
    "iso:country":"AU",
    "sg:address":"Unit 9 16 Ledger Rd",
    "sg:city":"Balcatta",
    "sg:classifiers":[
        {
            "category":"Building & Trades",
            "subcategory":"Construction",
            "type":"Services"
        }
    ],
    "sg:phone":"+61 418 920 896",
    "sg:postcode":"6021",
    "sg:province":"WA",
    "sg:tags":[
        "joiner",
        "carpenter"
    ],
    "wof:name":"Kingsley Construction",
    "wof:placetype":"venue"
},
  "geometry": {"coordinates":[115.80342865,-31.8649215698],"type":"Point"}
}