{
  "type": "Feature",
  "properties": {
    "iso:country":"AU",
    "sg:address":"Peachy Rd",
    "sg:city":"Ormeau",
    "sg:classifiers":[
        {
            "category":"Building & Trades",
            "subcategory":"Pest Control",
            "type":"Services"
        }
    ],
    "sg:phone":"+61 7 5546 7199",
    "sg:postcode":"4208",
    "sg:province":"QLD",
    "sg:tags":[
        "technical",
        "consultant"
    ],
    "wof:name":"Readymix Technical Services & Quarries",
    "wof:placetype":"venue"
},
  "geometry": {"coordinates":[153.23666381800001,-27.7798137665],"type":"Point"}
}