{
  "type": "Feature",
  "properties": {
    "addr:full":"Suite 7, 4 Plaza Crcle Highfields QLD 4352",
    "addr:housenumber":"4",
    "addr:postcode":"4352",
    "addr:street":"Plaza Crcle",
    "iso:country":"AU",
    "sg:address":"Suite 7, 4 Plaza Crcle",
    "sg:city":"Highfields",
    "sg:classifiers":[
        {
            "category":"Health Services",
            "subcategory":"Dentist",
            "type":"Services"
        }
    ],
    "sg:phone":"+61 7 4698 7222",
    "sg:postcode":"4352",
    "sg:province":"QLD",
    "wof:name":"Robert Mark J",
    "wof:placetype":"venue"
},
  "geometry": {"coordinates":[151.95332300000001,-27.464439],"type":"Point"}
}