{
  "type": "Feature",
  "properties": {
    "addr:full":"PO Box 328 Chirnside Park VIC 3116",
    "addr:postcode":"3116",
    "iso:country":"AU",
    "sg:address":"PO Box 328",
    "sg:city":"Chirnside Park",
    "sg:classifiers":[
        {
            "category":"Transit Center",
            "subcategory":"Passenger",
            "type":"Transportation"
        }
    ],
    "sg:phone":"+61 3 9727 2337",
    "sg:postcode":"3116",
    "sg:province":"VIC",
    "sg:tags":[
        "retail",
        "toiletry",
        "perfume"
    ],
    "wof:name":"The Fragrance Gallery",
    "wof:placetype":"venue"
},
  "geometry": {"coordinates":[145.31483459500001,-37.7397918701],"type":"Point"}
}