{
  "type": "Feature",
  "properties": {
    "addr:full":"Unit 1/ 6 London Drv Bayswater VIC 3153",
    "addr:postcode":"3153",
    "addr:street":"London Drv",
    "iso:country":"AU",
    "sg:address":"Unit 1/ 6 London Drv",
    "sg:city":"Bayswater",
    "sg:classifiers":[
        {
            "category":"Building & Trades",
            "subcategory":"Equipment Rental",
            "type":"Services"
        }
    ],
    "sg:phone":"+61 3 9762 9966",
    "sg:postcode":"3153",
    "sg:province":"VIC",
    "sg:tags":[
        "supply",
        "catering"
    ],
    "wof:name":"SDL Appliance Service Pty Ltd",
    "wof:placetype":"venue"
},
  "geometry": {"coordinates":[145.285232544,-37.8451538086],"type":"Point"}
}