{
  "type": "Feature",
  "properties": {
    "iso:country":"AU",
    "sg:address":"50 McLarty Rd",
    "sg:city":"Halls Head",
    "sg:classifiers":[
        {
            "category":"Social Services",
            "subcategory":"Child Care",
            "type":"Services"
        }
    ],
    "sg:phone":"+61 8 9581 2903",
    "sg:postcode":"6210",
    "sg:province":"WA",
    "wof:name":"Cuddles Halls Head",
    "wof:placetype":"venue"
},
  "geometry": {"coordinates":[115.70591,-32.53981],"type":"Point"}
}