{
  "type": "Feature",
  "properties": {
    "addr:full":"299 Old Northern Rd Castle Hill NSW 2154",
    "addr:housenumber":"299",
    "addr:postcode":"2154",
    "addr:street":"Old Northern Rd",
    "iso:country":"AU",
    "sg:address":"299 Old Northern Rd",
    "sg:city":"Castle Hill",
    "sg:classifiers":[
        {
            "category":"Education",
            "subcategory":"Junior College",
            "type":"Public Place"
        }
    ],
    "sg:phone":"+61 2 9659 4699",
    "sg:postcode":"2154",
    "sg:province":"NSW",
    "sg:tags":[
        "business"
    ],
    "wof:name":"Australian College of Professionals",
    "wof:placetype":"venue"
},
  "geometry": {"coordinates":[151.00619506800001,-33.7323608398],"type":"Point"}
}