{
  "type": "Feature",
  "properties": {
    "addr:full":"126 High St East Maitland NSW 2323",
    "addr:housenumber":"126",
    "addr:postcode":"2323",
    "addr:street":"High St",
    "iso:country":"AU",
    "sg:address":"126 High St",
    "sg:city":"East Maitland",
    "sg:classifiers":[
        {
            "category":"Real Estate",
            "subcategory":"Surveying",
            "type":"Services"
        }
    ],
    "sg:phone":"+61 2 4933 5631",
    "sg:postcode":"2323",
    "sg:province":"NSW",
    "sg:tags":[
        "surveyor",
        "land"
    ],
    "wof:name":"Scott, Crisp & Dilley Surveyors",
    "wof:placetype":"venue"
},
  "geometry": {"coordinates":[151.58758544899999,-32.7527122498],"type":"Point"}
}