{
  "type": "Feature",
  "properties": {
    "addr:full":"59 Hobart St Riverstone NSW 2765",
    "addr:housenumber":"59",
    "addr:postcode":"2765",
    "addr:street":"Hobart St",
    "iso:country":"AU",
    "sg:address":"59 Hobart St",
    "sg:city":"Riverstone",
    "sg:classifiers":[
        {
            "category":"Building & Trades",
            "subcategory":"Landscaping Services",
            "type":"Services"
        }
    ],
    "sg:phone":"+61 417 022 455",
    "sg:postcode":"2765",
    "sg:province":"NSW",
    "sg:tags":[
        "designer",
        "landscape",
        "contractor"
    ],
    "wof:name":"Ring Us Group",
    "wof:placetype":"venue"
},
  "geometry": {"coordinates":[150.86146545400001,-33.6672859192],"type":"Point"}
}