{
  "type": "Feature",
  "properties": {
    "addr:full":"4A Industrial Ave Mudgee NSW 2850",
    "addr:housenumber":"4a",
    "addr:postcode":"2850",
    "addr:street":"Industrial Ave",
    "iso:country":"AU",
    "sg:address":"4A Industrial Ave",
    "sg:city":"Mudgee",
    "sg:classifiers":[
        {
            "category":"Retail",
            "subcategory":"Auto Repair",
            "type":"Services"
        }
    ],
    "sg:phone":"+61 428 753 836",
    "sg:postcode":"2850",
    "sg:province":"NSW",
    "sg:tags":[
        "beater",
        "painter",
        "panel"
    ],
    "wof:name":"Dent Addict",
    "wof:placetype":"venue"
},
  "geometry": {"coordinates":[149.60029599999999,-32.608158],"type":"Point"}
}