{
  "type": "Feature",
  "properties": {
    "addr:full":"18 Ferguson St Underwood QLD 4119",
    "addr:housenumber":"18",
    "addr:postcode":"4119",
    "addr:street":"Ferguson St",
    "iso:country":"AU",
    "sg:address":"18 Ferguson St",
    "sg:city":"Underwood",
    "sg:classifiers":[
        {
            "category":"Government",
            "subcategory":"Department Of Motor Vehicles",
            "type":"Public Place"
        }
    ],
    "sg:phone":"+61 7 3341 4899",
    "sg:postcode":"4119",
    "sg:province":"QLD",
    "sg:tags":[
        "body",
        "supply",
        "trimmer"
    ],
    "wof:name":"Queensland Moulded Car Carpets",
    "wof:placetype":"venue"
},
  "geometry": {"coordinates":[153.11415100100001,-27.6116523743],"type":"Point"}
}