{
  "type": "Feature",
  "properties": {
    "iso:country":"AU",
    "sg:address":"Shp 14",
    "sg:city":"Tillegerry Plaza Tanilba Bay",
    "sg:classifiers":[
        {
            "category":"Communications",
            "subcategory":"News Services",
            "type":"Services"
        }
    ],
    "sg:phone":"+61 2 4982 4441",
    "sg:postcode":"2319",
    "sg:province":"NSW",
    "sg:tags":[
        "information",
        "tourist",
        "attractions"
    ],
    "wof:name":"Tilligerry Habitat Gallery & Information Centre",
    "wof:placetype":"venue"
},
  "geometry": {"coordinates":[151.99705499999999,-32.736843],"type":"Point"}
}