{
  "type": "Feature",
  "properties": {
    "iso:country":"AU",
    "sg:address":"1 Smillie St",
    "sg:city":"Robe",
    "sg:classifiers":[
        {
            "category":"Health Services",
            "subcategory":"Doctor",
            "type":"Services"
        }
    ],
    "sg:phone":"+61 8 8768 2012",
    "sg:postcode":"5276",
    "sg:province":"SA",
    "sg:tags":[
        "medical",
        "practitioner"
    ],
    "wof:name":"Senior David P",
    "wof:placetype":"venue"
},
  "geometry": {"coordinates":[139.75796500000001,-37.16349],"type":"Point"}
}