{
  "type": "Feature",
  "properties": {
    "iso:country":"AU",
    "sg:address":"44-60 McDonald Rd",
    "sg:city":"Brooklyn",
    "sg:classifiers":[
        {
            "category":"Manufacturing",
            "subcategory":"Metals",
            "type":"Manufacturing & Wholesale Goods"
        }
    ],
    "sg:phone":"+61 3 9314 0844",
    "sg:postcode":"3025",
    "sg:province":"VIC",
    "sg:tags":[
        "steel",
        "tube"
    ],
    "wof:name":"SimsMetal",
    "wof:placetype":"venue"
},
  "geometry": {"coordinates":[144.848251,-37.809246],"type":"Point"}
}