{
  "type": "Feature",
  "properties": {
    "addr:full":"67 Hesse St Queenscliff VIC 3225",
    "addr:housenumber":"67",
    "addr:postcode":"3225",
    "addr:street":"Hesse St",
    "iso:country":"AU",
    "sg:address":"67 Hesse St",
    "sg:city":"Queenscliff",
    "sg:classifiers":[
        {
            "category":"Restaurant",
            "type":"Food & Drink"
        }
    ],
    "sg:phone":"+61 3 5258 1977",
    "sg:postcode":"3225",
    "sg:province":"VIC",
    "wof:name":"Cafe 67on Hesse",
    "wof:placetype":"venue"
},
  "geometry": {"coordinates":[144.660721,-38.268368],"type":"Point"}
}