{
  "type": "Feature",
  "properties": {
    "iso:country":"AU",
    "sg:address":"676 Gympie Rd",
    "sg:city":"Chermside",
    "sg:classifiers":[
        {
            "category":"Personal",
            "subcategory":"Beauty Salon",
            "type":"Services"
        }
    ],
    "sg:phone":"+61 7 3359 9365",
    "sg:postcode":"4032",
    "sg:province":"QLD",
    "sg:tags":[
        "hairdresser"
    ],
    "wof:name":"Hair Perfect",
    "wof:placetype":"venue"
},
  "geometry": {"coordinates":[153.03117399999999,-27.38994],"type":"Point"}
}