{
  "type": "Feature",
  "properties": {
    "addr:full":"Harry Mac Crt Narangba QLD 4504",
    "addr:postcode":"4504",
    "addr:street":"Crt",
    "iso:country":"AU",
    "sg:address":"Harry Mac Crt",
    "sg:city":"Narangba",
    "sg:classifiers":[
        {
            "category":"Health Services",
            "subcategory":"Health Practitioner",
            "type":"Services"
        }
    ],
    "sg:phone":"+61 7 3886 6403",
    "sg:postcode":"4504",
    "sg:province":"QLD",
    "sg:tags":[
        "naturopath"
    ],
    "wof:name":"Cunningham Patricia",
    "wof:placetype":"venue"
},
  "geometry": {"coordinates":[152.93513488799999,-27.1894512177],"type":"Point"}
}