{
  "type": "Feature",
  "properties": {
    "iso:country":"AU",
    "sg:address":"62 Northbourne Ave",
    "sg:city":"Canberra City",
    "sg:classifiers":[
        {
            "category":"Cafe",
            "type":"Food & Drink"
        }
    ],
    "sg:phone":"+61 2 6257 4407",
    "sg:postcode":"2601",
    "sg:province":"ACT",
    "wof:name":"Cafe Picasso",
    "wof:placetype":"venue"
},
  "geometry": {"coordinates":[149.12974548299999,-35.2777900696],"type":"Point"}
}