{
  "type": "Feature",
  "properties": {
    "iso:country":"AU",
    "sg:address":"175 Bonds Rd",
    "sg:city":"Riverwood",
    "sg:classifiers":[
        {
            "category":"Retail",
            "subcategory":"Repair Shop",
            "type":"Services"
        }
    ],
    "sg:phone":"+61 2 9717 2358",
    "sg:postcode":"2210",
    "sg:province":"NSW",
    "sg:tags":[
        "machine",
        "repairs",
        "part",
        "dryer",
        "washing"
    ],
    "wof:name":"Electrolux Home Products Pty Ltd",
    "wof:placetype":"venue"
},
  "geometry": {"coordinates":[151.060242,-33.943802],"type":"Point"}
}