{
  "type": "Feature",
  "properties": {
    "addr:full":"319 Wyreema-Cambooya Rd Wyreema QLD 4352",
    "addr:housenumber":"319",
    "addr:postcode":"4352",
    "addr:street":"Wyreema-Cambooya Rd",
    "iso:country":"AU",
    "sg:address":"319 Wyreema-Cambooya Rd",
    "sg:city":"Wyreema",
    "sg:classifiers":[
        {
            "category":"Cafe",
            "type":"Food & Drink"
        }
    ],
    "sg:phone":"+61 7 4696 1033",
    "sg:postcode":"4352",
    "sg:province":"QLD",
    "wof:name":"Glenworth Cottage Teahouse",
    "wof:placetype":"venue"
},
  "geometry": {"coordinates":[151.89866599999999,-27.60652],"type":"Point"}
}