{
  "type": "Feature",
  "properties": {
    "iso:country":"AU",
    "sg:address":"1 Emerald St",
    "sg:city":"Kirwan",
    "sg:classifiers":[
        {
            "category":"Social Services",
            "subcategory":"Adult Care",
            "type":"Services"
        }
    ],
    "sg:phone":"+61 7 4773 1155",
    "sg:postcode":"4817",
    "sg:province":"QLD",
    "sg:tags":[
        "aged"
    ],
    "wof:name":"Masonic Village (NQ) Ltd",
    "wof:placetype":"venue"
},
  "geometry": {"coordinates":[146.737335,-19.307592],"type":"Point"}
}