{
  "type": "Feature",
  "properties": {
    "addr:full":"Building 5, 2404 Logan Rd Upper Mt Gravatt Delivery Cen QLD 4122",
    "addr:housenumber":"2404",
    "addr:postcode":"4122",
    "addr:street":"Logan Rd Upper",
    "iso:country":"AU",
    "sg:address":"Building 5, 2404 Logan Rd",
    "sg:city":"Upper Mt Gravatt Delivery Cen",
    "sg:classifiers":[
        {
            "category":"Banks & Credit Unions",
            "subcategory":"Investment Brokerage",
            "type":"Services"
        }
    ],
    "sg:phone":"+61 408 522 652",
    "sg:postcode":"4122",
    "sg:province":"QLD",
    "sg:tags":[
        "finance",
        "broker"
    ],
    "wof:name":"Capitalcorp Financial Services",
    "wof:placetype":"venue"
},
  "geometry": {"coordinates":[153.07940673799999,-27.5489883423],"type":"Point"}
}