{
  "type": "Feature",
  "properties": {
    "addr:full":"PO Box 743 Virginia QLD 4014",
    "addr:postcode":"4014",
    "iso:country":"AU",
    "sg:address":"PO Box 743",
    "sg:city":"Virginia",
    "sg:classifiers":[
        {
            "category":"Autos & Motor Vehicles",
            "subcategory":"Auto Supplies",
            "type":"Retail Goods"
        }
    ],
    "sg:phone":"+61 7 3265 5000",
    "sg:postcode":"4014",
    "sg:province":"QLD",
    "sg:tags":[
        "transmission",
        "equipment",
        "power"
    ],
    "wof:name":"Power Transmission Drives Australia",
    "wof:placetype":"venue"
},
  "geometry": {"coordinates":[153.06463623100001,-27.3816890717],"type":"Point"}
}