{
  "type": "Feature",
  "properties": {
    "addr:full":"Grose Rd Faulconbridge NSW 2776",
    "addr:postcode":"2776",
    "addr:street":"Grose Rd",
    "iso:country":"AU",
    "sg:address":"Grose Rd",
    "sg:city":"Faulconbridge",
    "sg:classifiers":[
        {
            "category":"Education",
            "subcategory":"School",
            "type":"Public Place"
        }
    ],
    "sg:phone":"+61 2 4751 2208",
    "sg:postcode":"2776",
    "sg:province":"NSW",
    "sg:tags":[
        "state",
        "-",
        "nsw"
    ],
    "wof:name":"Faulconbridge Public School",
    "wof:placetype":"venue"
},
  "geometry": {"coordinates":[150.549224853,-33.6849899292],"type":"Point"}
}