{
  "type": "Feature",
  "properties": {
    "addr:full":"Shop 5, 19 Essington St Mitchell ACT 2911",
    "addr:housenumber":"shop;19",
    "addr:postcode":"2911",
    "addr:street":"Essington St",
    "iso:country":"AU",
    "sg:address":"Shop 5, 19 Essington St",
    "sg:city":"Mitchell",
    "sg:classifiers":[
        {
            "category":"Retail",
            "subcategory":"Auto Repair",
            "type":"Services"
        }
    ],
    "sg:phone":"+61 2 6241 7029",
    "sg:postcode":"2911",
    "sg:province":"ACT",
    "sg:tags":[
        "repairer",
        "motor",
        "engineer"
    ],
    "wof:name":"Metro Car Care",
    "wof:placetype":"venue"
},
  "geometry": {"coordinates":[149.14126586899999,-35.2132606506],"type":"Point"}
}