{
  "type": "Feature",
  "properties": {
    "addr:full":"59 White Rd Landsborough QLD 4550",
    "addr:housenumber":"59",
    "addr:postcode":"4550",
    "addr:street":"White Rd",
    "iso:country":"AU",
    "sg:address":"59 White Rd",
    "sg:city":"Landsborough",
    "sg:classifiers":[
        {
            "category":"Education",
            "subcategory":"Junior College",
            "type":"Public Place"
        }
    ],
    "sg:phone":"+61 7 5494 8895",
    "sg:postcode":"4550",
    "sg:province":"QLD",
    "sg:tags":[
        "wholesaler",
        "school",
        "mfrs",
        "uniform"
    ],
    "wof:name":"Contract Cutting",
    "wof:placetype":"venue"
},
  "geometry": {"coordinates":[152.95016479500001,-26.8085021973],"type":"Point"}
}