{
  "type": "Feature",
  "properties": {
    "addr:full":"80 Magazine St Stratford QLD 4870",
    "addr:housenumber":"80",
    "addr:postcode":"4870",
    "addr:street":"Magazine St",
    "iso:country":"AU",
    "sg:address":"80 Magazine St",
    "sg:city":"Stratford",
    "sg:classifiers":[
        {
            "category":"Home & Garden",
            "subcategory":"Building Materials",
            "type":"Retail Goods"
        }
    ],
    "sg:phone":"+61 7 4055 1031",
    "sg:postcode":"4870",
    "sg:province":"QLD",
    "sg:tags":[
        "fencing"
    ],
    "wof:name":"Rankine Timber & Truss",
    "wof:placetype":"venue"
},
  "geometry": {"coordinates":[145.74310302699999,-16.8773651123],"type":"Point"}
}