{
  "type": "Feature",
  "properties": {
    "iso:country":"AU",
    "sg:address":"627 Rode Rd",
    "sg:city":"Chermside",
    "sg:classifiers":[
        {
            "category":"Health Services",
            "subcategory":"Doctor",
            "type":"Services"
        }
    ],
    "sg:phone":"+61 7 3230 5455",
    "sg:postcode":"4032",
    "sg:province":"QLD",
    "sg:tags":[
        "medical",
        "practitioner"
    ],
    "wof:name":"English Hugh Dr",
    "wof:placetype":"venue"
},
  "geometry": {"coordinates":[153.02018699999999,-27.392399],"type":"Point"}
}