{
  "type": "Feature",
  "properties": {
    "iso:country":"AU",
    "sg:address":"19 Kitchener St",
    "sg:city":"Hughes",
    "sg:classifiers":[
        {
            "category":"Education",
            "subcategory":"Music School",
            "type":"Public Place"
        }
    ],
    "sg:phone":"+61 2 6281 3554",
    "sg:postcode":"2605",
    "sg:province":"ACT",
    "sg:tags":[
        "choir",
        "bands",
        "orchestra"
    ],
    "wof:name":"Woden Valley Youth Choir",
    "wof:placetype":"venue"
},
  "geometry": {"coordinates":[149.09649658199999,-35.3334350586],"type":"Point"}
}