{
  "type": "Feature",
  "properties": {
    "addr:full":"23 Queen St Croydon NSW 2132",
    "addr:housenumber":"23",
    "addr:postcode":"2132",
    "addr:street":"Queen St",
    "iso:country":"AU",
    "sg:address":"23 Queen St",
    "sg:city":"Croydon",
    "sg:classifiers":[
        {
            "category":"Building & Trades",
            "subcategory":"Landscaping Services",
            "type":"Services"
        }
    ],
    "sg:phone":"+61 2 9744 3245",
    "sg:postcode":"2132",
    "sg:province":"NSW",
    "sg:tags":[
        "stump",
        "tree",
        "felling",
        "removal"
    ],
    "wof:name":"Cheapest Tree Lopping",
    "wof:placetype":"venue"
},
  "geometry": {"coordinates":[151.11686706500001,-33.876373291],"type":"Point"}
}