{
  "type": "Feature",
  "properties": {
    "addr:full":"56 Cahills Rd Yarrawonga VIC 3730",
    "addr:housenumber":"56",
    "addr:postcode":"3730",
    "addr:street":"Cahills Rd",
    "iso:country":"AU",
    "sg:address":"56 Cahills Rd",
    "sg:city":"Yarrawonga",
    "sg:classifiers":[
        {
            "category":"Wholesale",
            "subcategory":"Drugs",
            "type":"Manufacturing & Wholesale Goods"
        }
    ],
    "sg:phone":"+61 3 5743 1996",
    "sg:postcode":"3730",
    "sg:province":"VIC",
    "sg:tags":[
        "wholesaler",
        "pharmaceutical",
        "product",
        "mfrs"
    ],
    "wof:name":"Chempak PharmaSystems",
    "wof:placetype":"venue"
},
  "geometry": {"coordinates":[146.020095825,-36.0262641907],"type":"Point"}
}