{
  "type": "Feature",
  "properties": {
    "iso:country":"AU",
    "sg:address":"Pollocksford Rd",
    "sg:city":"Stonehaven",
    "sg:classifiers":[
        {
            "category":"Building & Trades",
            "subcategory":"Construction",
            "type":"Services"
        }
    ],
    "sg:phone":"+61 3 5271 1245",
    "sg:postcode":"3221",
    "sg:province":"VIC",
    "sg:tags":[
        "earth",
        "excavating",
        "moving",
        "contractor"
    ],
    "wof:name":"Hucker N J & H J",
    "wof:placetype":"venue"
},
  "geometry": {"coordinates":[144.199173,-38.134903],"type":"Point"}
}