{
  "type": "Feature",
  "properties": {
    "addr:full":"38 Hoskins St Mitchell ACT 2911",
    "addr:housenumber":"38",
    "addr:postcode":"2911",
    "addr:street":"Hoskins St",
    "iso:country":"AU",
    "sg:address":"38 Hoskins St",
    "sg:city":"Mitchell",
    "sg:classifiers":[
        {
            "category":"Retail",
            "subcategory":"Auto Repair",
            "type":"Services"
        }
    ],
    "sg:phone":"+61 2 6241 8777",
    "sg:postcode":"2911",
    "sg:province":"ACT",
    "sg:tags":[
        "clutch",
        "brake"
    ],
    "wof:name":"Canberra Motor Works",
    "wof:placetype":"venue"
},
  "geometry": {"coordinates":[149.13714599599999,-35.2184753418],"type":"Point"}
}