{
  "type": "Feature",
  "properties": {
    "addr:full":"995 Ipswich Rd Moorooka QLD 4105",
    "addr:housenumber":"995",
    "addr:postcode":"4105",
    "addr:street":"Ipswich Rd",
    "iso:country":"AU",
    "sg:address":"995 Ipswich Rd",
    "sg:city":"Moorooka",
    "sg:classifiers":[
        {
            "category":"Autos & Motor Vehicles",
            "subcategory":"Automobile Sales",
            "type":"Retail Goods"
        }
    ],
    "sg:phone":"+61 7 3848 0822",
    "sg:postcode":"4105",
    "sg:province":"QLD",
    "sg:tags":[
        "car",
        "used"
    ],
    "wof:name":"Instant Wholesale Cars",
    "wof:placetype":"venue"
},
  "geometry": {"coordinates":[153.01817321799999,-27.5301494598],"type":"Point"}
}