{
  "type": "Feature",
  "properties": {
    "iso:country":"AU",
    "sg:address":"16- 20 Third Ave",
    "sg:city":"Sunshine",
    "sg:classifiers":[
        {
            "category":"Professional",
            "subcategory":"Detective & Security Services",
            "type":"Services"
        }
    ],
    "sg:phone":"+61 3 9300 9390",
    "sg:postcode":"3020",
    "sg:province":"VIC",
    "sg:tags":[
        "consultant",
        "system"
    ],
    "wof:name":"IR Security & Safety",
    "wof:placetype":"venue"
},
  "geometry": {"coordinates":[144.836533,-37.799664],"type":"Point"}
}