{
  "type": "Feature",
  "properties": {
    "addr:full":"458 South Rd Marleston SA 5033",
    "addr:housenumber":"458",
    "addr:postcode":"5033",
    "addr:street":"South Rd",
    "iso:country":"AU",
    "sg:address":"458 South Rd",
    "sg:city":"Marleston",
    "sg:classifiers":[
        {
            "category":"Insurance",
            "subcategory":"Hazard Insurance",
            "type":"Services"
        }
    ],
    "sg:phone":"+61 8 8404 3000",
    "sg:postcode":"5033",
    "sg:province":"SA",
    "sg:tags":[
        "loss",
        "adjuster",
        "assessor"
    ],
    "wof:name":"Riedel Fox Loss Adjusters",
    "wof:placetype":"venue"
},
  "geometry": {"coordinates":[138.571136475,-34.9455795288],"type":"Point"}
}