{
  "type": "Feature",
  "properties": {
    "iso:country":"AU",
    "sg:address":"PO Box 201",
    "sg:city":"Olinda",
    "sg:classifiers":[
        {
            "category":"Autos & Motor Vehicles",
            "subcategory":"Auto Supplies",
            "type":"Retail Goods"
        }
    ],
    "sg:phone":"+61 419 955 466",
    "sg:postcode":"3788",
    "sg:province":"VIC",
    "sg:tags":[
        "accessory"
    ],
    "wof:name":"Australian Car Cover Company",
    "wof:placetype":"venue"
},
  "geometry": {"coordinates":[145.35876500000001,-37.841629],"type":"Point"}
}