{
  "type": "Feature",
  "properties": {
    "addr:full":"406 Rode Rd Chermside QLD 4032",
    "addr:postcode":"qld 4032",
    "addr:street":"Rode Rd",
    "iso:country":"AU",
    "sg:address":"406 Rode Rd",
    "sg:city":"Chermside",
    "sg:classifiers":[
        {
            "category":"Professional",
            "subcategory":"Computer Services",
            "type":"Services"
        }
    ],
    "sg:phone":"+61 7 3359 3776",
    "sg:postcode":"4032",
    "sg:province":"QLD",
    "sg:tags":[
        "package",
        "software"
    ],
    "wof:name":"Highcove Pty Ltd",
    "wof:placetype":"venue"
},
  "geometry": {"coordinates":[153.032623,-27.39378],"type":"Point"}
}