{
  "type": "Feature",
  "properties": {
    "addr:full":"4 Schofield St Riverwood NSW 2210",
    "addr:housenumber":"4",
    "addr:postcode":"2210",
    "addr:street":"Schofield St",
    "iso:country":"AU",
    "sg:address":"4 Schofield St",
    "sg:city":"Riverwood",
    "sg:classifiers":[
        {
            "category":"Government",
            "subcategory":"Post Office",
            "type":"Public Place"
        }
    ],
    "sg:phone":"+61 2 9584 9028",
    "sg:postcode":"2210",
    "sg:province":"NSW",
    "sg:tags":[
        "chair",
        "manufacturer"
    ],
    "wof:name":"Deson's Furniture Pty Ltd",
    "wof:placetype":"venue"
},
  "geometry": {"coordinates":[151.04884300000001,-33.940166],"type":"Point"}
}