{
  "type": "Feature",
  "properties": {
    "addr:full":"83 Kingman St Sunnybank Hills QLD 4109",
    "addr:housenumber":"83",
    "addr:postcode":"4109",
    "addr:street":"Kingman St",
    "iso:country":"AU",
    "sg:address":"83 Kingman St",
    "sg:city":"Sunnybank Hills",
    "sg:classifiers":[
        {
            "category":"Government",
            "subcategory":"Court House",
            "type":"Public Place"
        }
    ],
    "sg:phone":"+61 7 3273 2049",
    "sg:postcode":"4109",
    "sg:province":"QLD",
    "sg:tags":[
        "personal",
        "marriage",
        "family",
        "counselling"
    ],
    "wof:name":"Parent Effectiveness Training Sunnybank",
    "wof:placetype":"venue"
},
  "geometry": {"coordinates":[153.05020141599999,-27.5945854187],"type":"Point"}
}