{
  "type": "Feature",
  "properties": {
    "addr:full":"181 Scarborough Beach Rd Doubleview WA 6018",
    "addr:housenumber":"181",
    "addr:postcode":"6018",
    "addr:street":"Scarborough Beach Rd",
    "iso:country":"AU",
    "sg:address":"181 Scarborough Beach Rd",
    "sg:city":"Doubleview",
    "sg:classifiers":[
        {
            "category":"Food & Beverages",
            "subcategory":"Bakery",
            "type":"Retail Goods"
        }
    ],
    "sg:phone":"+61 8 9244 8822",
    "sg:postcode":"6018",
    "sg:province":"WA",
    "sg:tags":[
        "baker"
    ],
    "wof:name":"Brumbys WA & NT",
    "wof:placetype":"venue"
},
  "geometry": {"coordinates":[115.77670288100001,-31.8940868378],"type":"Point"}
}