{
  "type": "Feature",
  "properties": {
    "addr:full":"49 Park Rd Cabramatta NSW 2166",
    "addr:housenumber":"49",
    "addr:postcode":"2166",
    "addr:street":"Park Rd",
    "iso:country":"AU",
    "sg:address":"49 Park Rd",
    "sg:city":"Cabramatta",
    "sg:classifiers":[
        {
            "category":"Food & Beverages",
            "subcategory":"Fruits & Vegetables",
            "type":"Retail Goods"
        }
    ],
    "sg:phone":"+61 2 9724 0098",
    "sg:postcode":"2166",
    "sg:province":"NSW",
    "sg:tags":[
        "wholesale"
    ],
    "wof:name":"Win Minh Fruit Market",
    "wof:placetype":"venue"
},
  "geometry": {"coordinates":[150.936889648,-33.8939704895],"type":"Point"}
}