{
  "type": "Feature",
  "properties": {
    "addr:full":"Shop 33c, Centrepoint Shopping Centre Bunbury WA 6230",
    "addr:housenumber":"33c",
    "addr:postcode":"6230",
    "addr:street":"Shop",
    "iso:country":"AU",
    "sg:address":"Shop 33c, Centrepoint Shopping Centre",
    "sg:city":"Bunbury",
    "sg:classifiers":[
        {
            "category":"Utilities",
            "subcategory":"Mobile Phone",
            "type":"Services"
        }
    ],
    "sg:phone":"+61 8 9721 4567",
    "sg:postcode":"6230",
    "sg:province":"WA",
    "sg:tags":[
        "repair",
        "telephone"
    ],
    "wof:name":"Phone Frenzy",
    "wof:placetype":"venue"
},
  "geometry": {"coordinates":[115.645348,-33.380112],"type":"Point"}
}