{
  "type": "Feature",
  "properties": {
    "addr:full":"34- 36 Railway St Dirranbandi QLD 4486",
    "addr:housenumber":"36",
    "addr:postcode":"4486",
    "addr:street":"Railway St",
    "iso:country":"AU",
    "sg:address":"34- 36 Railway St",
    "sg:city":"Dirranbandi",
    "sg:classifiers":[
        {
            "category":"Wholesale",
            "subcategory":"Farm Supplies",
            "type":"Manufacturing & Wholesale Goods"
        }
    ],
    "sg:phone":"+61 7 4625 8999",
    "sg:postcode":"4486",
    "sg:province":"QLD",
    "sg:tags":[
        "equipment"
    ],
    "wof:name":"Dirran Ag Spares",
    "wof:placetype":"venue"
},
  "geometry": {"coordinates":[148.226394653,-28.5854797363],"type":"Point"}
}