{
  "type": "Feature",
  "properties": {
    "addr:full":"GPO Box 4257 Sydney NSW 2001",
    "addr:postcode":"2001",
    "iso:country":"AU",
    "sg:address":"GPO Box 4257",
    "sg:city":"Sydney",
    "sg:classifiers":[
        {
            "category":"Insurance",
            "subcategory":"Title Insurance",
            "type":"Services"
        }
    ],
    "sg:phone":"+61 1300 739 472",
    "sg:postcode":"2001",
    "sg:province":"NSW",
    "sg:tags":[
        "reinsurance"
    ],
    "wof:name":"HSB AUSTRALIA",
    "wof:placetype":"venue"
},
  "geometry": {"coordinates":[151.207107544,-33.8671417236],"type":"Point"}
}