{
  "type": "Feature",
  "properties": {
    "addr:full":"Shop 4, 284 Bronte Rd Waverley NSW 2024",
    "addr:housenumber":"shop 4 284",
    "addr:postcode":"2024",
    "addr:street":"Bronte Rd",
    "iso:country":"AU",
    "sg:address":"Shop 4, 284 Bronte Rd",
    "sg:city":"Waverley",
    "sg:classifiers":[
        {
            "category":"Health Services",
            "subcategory":"Chiropractor",
            "type":"Services"
        }
    ],
    "sg:phone":"+61 2 8198 4434",
    "sg:postcode":"2024",
    "sg:province":"NSW",
    "sg:website":"http://www.chiropractors.asn.au",
    "wof:name":"Get Well Chiropractic",
    "wof:placetype":"venue"
},
  "geometry": {"coordinates":[151.25428772000001,-33.9011955261],"type":"Point"}
}