{
  "type": "Feature",
  "properties": {
    "iso:country":"AU",
    "sg:address":"Midway Rd",
    "sg:city":"Elizabeth Downs",
    "sg:classifiers":[
        {
            "category":"Arena",
            "subcategory":"Sports Club",
            "type":"Entertainment"
        }
    ],
    "sg:phone":"+61 8 8255 6146",
    "sg:postcode":"5113",
    "sg:province":"SA",
    "sg:tags":[
        "australian",
        "football",
        "rule"
    ],
    "wof:name":"Elizabeth Football Club Incorporated",
    "wof:placetype":"venue"
},
  "geometry": {"coordinates":[138.69053649899999,-34.7029418945],"type":"Point"}
}