{
  "type": "Feature",
  "properties": {
    "addr:full":"4 Avoca St South Yarra VIC 3141",
    "addr:housenumber":"4",
    "addr:postcode":"3141",
    "addr:street":"Avoca St",
    "iso:country":"AU",
    "sg:address":"4 Avoca St",
    "sg:city":"South Yarra",
    "sg:classifiers":[
        {
            "category":"Professional",
            "subcategory":"Accounting & Tax Preparation",
            "type":"Services"
        }
    ],
    "sg:phone":"+61 3 9867 3977",
    "sg:postcode":"3141",
    "sg:province":"VIC",
    "sg:tags":[
        "accountant",
        "auditor"
    ],
    "wof:name":"Wilson Robert W & Co",
    "wof:placetype":"venue"
},
  "geometry": {"coordinates":[144.989303589,-37.8383102417],"type":"Point"}
}