{
  "type": "Feature",
  "properties": {
    "iso:country":"AU",
    "sg:address":"PO Box 1127",
    "sg:city":"Joondalup DC",
    "sg:classifiers":[
        {
            "category":"Professional",
            "subcategory":"Detective & Security Services",
            "type":"Services"
        }
    ],
    "sg:phone":"+61 8 9304 7122",
    "sg:postcode":"6919",
    "sg:province":"WA",
    "sg:tags":[
        "guard",
        "patrol"
    ],
    "wof:name":"Seth Security",
    "wof:placetype":"venue"
},
  "geometry": {"coordinates":[115.769889831,-31.7465190887],"type":"Point"}
}