{
  "type": "Feature",
  "properties": {
    "addr:full":"PO Box 7016 Banyule VIC 3084",
    "addr:postcode":"3084",
    "iso:country":"AU",
    "sg:address":"PO Box 7016",
    "sg:city":"Banyule",
    "sg:classifiers":[
        {
            "category":"Building & Trades",
            "subcategory":"Construction",
            "type":"Services"
        }
    ],
    "sg:phone":"+61 3 9432 1445",
    "sg:postcode":"3084",
    "sg:province":"VIC",
    "sg:tags":[
        "earth",
        "excavating",
        "moving",
        "contractor"
    ],
    "wof:name":"Mitre Excavations",
    "wof:placetype":"venue"
},
  "geometry": {"coordinates":[145.07305908199999,-37.7228889465],"type":"Point"}
}