{
  "type": "Feature",
  "properties": {
    "addr:full":"7 Lewis St Glenroy VIC 3046",
    "addr:housenumber":"7",
    "addr:postcode":"3046",
    "addr:street":"Lewis St",
    "iso:country":"AU",
    "sg:address":"7 Lewis St",
    "sg:city":"Glenroy",
    "sg:classifiers":[
        {
            "category":"Health Services",
            "subcategory":"Nursing And Care Facility",
            "type":"Services"
        }
    ],
    "sg:phone":"+61 3 8311 0000",
    "sg:postcode":"3046",
    "sg:province":"VIC",
    "sg:tags":[
        "home"
    ],
    "wof:name":"Craigcare",
    "wof:placetype":"venue"
},
  "geometry": {"coordinates":[144.92117309599999,-37.7089042664],"type":"Point"}
}