{
  "type": "Feature",
  "properties": {
    "addr:full":"46a Hurst St Walkervale QLD 4670",
    "addr:housenumber":"46a",
    "addr:postcode":"4670",
    "addr:street":"Hurst St",
    "iso:country":"AU",
    "sg:address":"46a Hurst St",
    "sg:city":"Walkervale",
    "sg:classifiers":[
        {
            "category":"Education",
            "subcategory":"School",
            "type":"Public Place"
        }
    ],
    "sg:phone":"+61 7 4151 4800",
    "sg:postcode":"4670",
    "sg:province":"QLD",
    "sg:tags":[
        "state",
        "except",
        "nsw"
    ],
    "wof:name":"Walkervale Primary",
    "wof:placetype":"venue"
},
  "geometry": {"coordinates":[152.359832764,-24.8847637177],"type":"Point"}
}