{
  "type": "Feature",
  "properties": {
    "iso:country":"AU",
    "sg:address":"48 Thomas St",
    "sg:city":"Unley",
    "sg:classifiers":[
        {
            "category":"Professional",
            "subcategory":"Art Services",
            "type":"Services"
        }
    ],
    "sg:phone":"+61 8 8271 5539",
    "sg:postcode":"5061",
    "sg:province":"SA",
    "sg:tags":[
        "interior",
        "designer"
    ],
    "wof:name":"Hosking Interior Design",
    "wof:placetype":"venue"
},
  "geometry": {"coordinates":[138.60299682600001,-34.9522132874],"type":"Point"}
}