{
  "type": "Feature",
  "properties": {
    "addr:full":"Bay C/ 10 Ray McCarthy Drv Coffs Harbour NSW 2450",
    "addr:housenumber":"10",
    "addr:postcode":"2450",
    "addr:street":"C /;Mccarthy Drv",
    "iso:country":"AU",
    "sg:address":"Bay C/ 10 Ray McCarthy Drv",
    "sg:city":"Coffs Harbour",
    "sg:classifiers":[
        {
            "category":"Building & Trades",
            "subcategory":"Construction",
            "type":"Services"
        }
    ],
    "sg:phone":"+61 2 6650 9477",
    "sg:postcode":"2450",
    "sg:province":"NSW",
    "sg:tags":[
        "renovation",
        "alterations",
        "extension",
        "contractor"
    ],
    "wof:name":"Stoddart Building Products",
    "wof:placetype":"venue"
},
  "geometry": {"coordinates":[153.100739,-30.309565],"type":"Point"}
}