{
  "type": "Feature",
  "properties": {
    "iso:country":"AU",
    "sg:address":"17 Southern Blv",
    "sg:city":"Narre Warren South",
    "sg:classifiers":[
        {
            "category":"Autos & Motor Vehicles",
            "subcategory":"Auto Supplies",
            "type":"Retail Goods"
        }
    ],
    "sg:phone":"+61 407 875 225",
    "sg:postcode":"3805",
    "sg:province":"VIC",
    "sg:tags":[
        "tyre"
    ],
    "wof:name":"Air Anywhere",
    "wof:placetype":"venue"
},
  "geometry": {"coordinates":[145.305634,-38.06226],"type":"Point"}
}