{
  "type": "Feature",
  "properties": {
    "addr:full":"43- 45 Spensley Clifton Hill VIC 3068",
    "addr:housenumber":"45",
    "addr:postcode":"3068",
    "addr:street":"Spensley",
    "iso:country":"AU",
    "sg:address":"43- 45 Spensley",
    "sg:city":"Clifton Hill",
    "sg:classifiers":[
        {
            "category":"Cafe",
            "type":"Food & Drink"
        }
    ],
    "sg:phone":"+61 3 9482 4180",
    "sg:postcode":"3068",
    "sg:province":"VIC",
    "wof:name":"Cafe Quince",
    "wof:placetype":"venue"
},
  "geometry": {"coordinates":[144.997879028,-37.7886962891],"type":"Point"}
}