{
  "type": "Feature",
  "properties": {
    "addr:full":"43 Cambridge Rd Mooroolbark VIC 3138",
    "addr:housenumber":"43",
    "addr:postcode":"3138",
    "addr:street":"Cambridge Rd",
    "iso:country":"AU",
    "sg:address":"43 Cambridge Rd",
    "sg:city":"Mooroolbark",
    "sg:classifiers":[
        {
            "category":"Health Services",
            "subcategory":"Health Practitioner",
            "type":"Services"
        }
    ],
    "sg:phone":"+61 3 9723 2595",
    "sg:postcode":"3138",
    "sg:province":"VIC",
    "sg:tags":[
        "homoeopath"
    ],
    "wof:name":"Williams Robyn A",
    "wof:placetype":"venue"
},
  "geometry": {"coordinates":[145.313552856,-37.7911682129],"type":"Point"}
}