{
  "type": "Feature",
  "properties": {
    "addr:full":"Bowen St Burketown QLD 4830",
    "addr:postcode":"4830",
    "addr:street":"Bowen St",
    "iso:country":"AU",
    "sg:address":"Bowen St",
    "sg:city":"Burketown",
    "sg:classifiers":[
        {
            "category":"Communications",
            "subcategory":"Film & Video Production",
            "type":"Services"
        }
    ],
    "sg:phone":"+61 7 4745 5135",
    "sg:postcode":"4830",
    "sg:province":"QLD",
    "sg:tags":[
        "society",
        "housing",
        "co-operative"
    ],
    "wof:name":"Moungibi Housing Co-op Society Ltd",
    "wof:placetype":"venue"
},
  "geometry": {"coordinates":[139.546753,-17.74428],"type":"Point"}
}