{
  "type": "Feature",
  "properties": {
    "iso:country":"AU",
    "sg:address":"4/ 15 Overlord Pl",
    "sg:city":"Acacia Ridge",
    "sg:classifiers":[
        {
            "category":"Home & Garden",
            "subcategory":"Garden Supply",
            "type":"Retail Goods"
        }
    ],
    "sg:phone":"+61 7 3273 6457",
    "sg:postcode":"4110",
    "sg:province":"QLD",
    "sg:tags":[
        "equipment"
    ],
    "wof:name":"Acacia Mower Centre",
    "wof:placetype":"venue"
},
  "geometry": {"coordinates":[153.03706359899999,-27.5954666138],"type":"Point"}
}