{
  "type": "Feature",
  "properties": {
    "addr:full":"Lathlain Primary School 120 Howick St Lathlain WA 6100",
    "addr:housenumber":"120",
    "addr:postcode":"6100",
    "addr:street":"Howick St",
    "iso:country":"AU",
    "sg:address":"Lathlain Primary School 120 Howick St",
    "sg:city":"Lathlain",
    "sg:classifiers":[
        {
            "category":"Education",
            "subcategory":"School",
            "type":"Public Place"
        }
    ],
    "sg:phone":"+61 8 9361 1265",
    "sg:postcode":"6100",
    "sg:province":"WA",
    "sg:tags":[
        "state",
        "except",
        "nsw"
    ],
    "wof:name":"Schools Government (Public)",
    "wof:placetype":"venue"
},
  "geometry": {"coordinates":[115.90857696499999,-31.970205307],"type":"Point"}
}