{
  "type": "Feature",
  "properties": {
    "addr:full":"Unit 4/ 2 Brown St Kiama NSW 2533",
    "addr:housenumber":"2",
    "addr:postcode":"2533",
    "addr:street":"Brown St",
    "iso:country":"AU",
    "sg:address":"Unit 4/ 2 Brown St",
    "sg:city":"Kiama",
    "sg:classifiers":[
        {
            "category":"Retail",
            "subcategory":"Auto Repair",
            "type":"Services"
        }
    ],
    "sg:phone":"+61 2 4232 2971",
    "sg:postcode":"2533",
    "sg:province":"NSW",
    "sg:tags":[
        "electrical"
    ],
    "wof:name":"Kiama Auto Electrical",
    "wof:placetype":"venue"
},
  "geometry": {"coordinates":[150.84780883799999,-34.6656112671],"type":"Point"}
}