{
  "type": "Feature",
  "properties": {
    "iso:country":"AU",
    "sg:address":"240 Ipswich Rd",
    "sg:city":"Buranda",
    "sg:classifiers":[
        {
            "category":"Professional",
            "subcategory":"Employment Agencies",
            "type":"Services"
        }
    ],
    "sg:phone":"+61 7 3391 1880",
    "sg:postcode":"4102",
    "sg:province":"QLD",
    "sg:tags":[
        "hire",
        "labour",
        "contractor"
    ],
    "sg:website":"http://www.rexco.com.au",
    "wof:name":"Rexco People",
    "wof:placetype":"venue"
},
  "geometry": {"coordinates":[153.03570556599999,-27.4994754791],"type":"Point"}
}