{
  "type": "Feature",
  "properties": {
    "iso:country":"AU",
    "sg:address":"Shop 5 264 Bazaar St",
    "sg:city":"Maryborough",
    "sg:classifiers":[
        {
            "category":"Health Services",
            "subcategory":"Doctor",
            "type":"Services"
        }
    ],
    "sg:phone":"+61 7 4123 1200",
    "sg:postcode":"4650",
    "sg:province":"QLD",
    "sg:tags":[
        "medical",
        "practitioner"
    ],
    "wof:name":"Isles M K",
    "wof:placetype":"venue"
},
  "geometry": {"coordinates":[152.704544,-25.536987],"type":"Point"}
}