{
  "type": "Feature",
  "properties": {
    "addr:full":"6 King Pl Eden NSW 2551",
    "addr:housenumber":"6",
    "addr:postcode":"2551",
    "addr:street":"King Pl",
    "iso:country":"AU",
    "sg:address":"6 King Pl",
    "sg:city":"Eden",
    "sg:classifiers":[
        {
            "category":"Retail",
            "subcategory":"Repair Shop",
            "type":"Services"
        }
    ],
    "sg:phone":"+61 429 963 306",
    "sg:postcode":"2551",
    "sg:province":"NSW",
    "sg:tags":[
        "upholsterer"
    ],
    "wof:name":"Eden Upholstery",
    "wof:placetype":"venue"
},
  "geometry": {"coordinates":[149.90382385300001,-37.0499725342],"type":"Point"}
}