{
  "type": "Feature",
  "properties": {
    "addr:full":"246 Grand Junction Rd Athol Park SA 5012",
    "addr:housenumber":"246",
    "addr:postcode":"5012",
    "addr:street":"Grand Junction Rd",
    "iso:country":"AU",
    "sg:address":"246 Grand Junction Rd",
    "sg:city":"Athol Park",
    "sg:classifiers":[
        {
            "category":"Wholesale",
            "subcategory":"Machinery & Supplies",
            "type":"Manufacturing & Wholesale Goods"
        }
    ],
    "sg:phone":"+61 8 8341 0177",
    "sg:postcode":"5012",
    "sg:province":"SA",
    "sg:tags":[
        "equipment",
        "hydraulic"
    ],
    "sg:website":"http://www.torquehydraulics.com",
    "wof:name":"Torque Hydraulics",
    "wof:placetype":"venue"
},
  "geometry": {"coordinates":[138.53936767600001,-34.8511352539],"type":"Point"}
}