{
  "type": "Feature",
  "properties": {
    "addr:full":"Unit 6/ 52 Mileham St Windsor NSW 2756",
    "addr:housenumber":"52",
    "addr:postcode":"2756",
    "addr:street":"Mileham St",
    "iso:country":"AU",
    "sg:address":"Unit 6/ 52 Mileham St",
    "sg:city":"Windsor",
    "sg:classifiers":[
        {
            "category":"Professional",
            "type":"Services"
        }
    ],
    "sg:phone":"+61 2 4577 3511",
    "sg:postcode":"2756",
    "sg:province":"NSW",
    "sg:tags":[
        "spray",
        "painting"
    ],
    "wof:name":"Kustom Classic Spray Painting",
    "wof:placetype":"venue"
},
  "geometry": {"coordinates":[150.814453125,-33.6146774292],"type":"Point"}
}