{
  "type": "Feature",
  "properties": {
    "addr:full":"Cnr Stock & French Rds Melville WA 6156",
    "addr:postcode":"6156",
    "iso:country":"AU",
    "sg:address":"Cnr Stock & French Rds",
    "sg:city":"Melville",
    "sg:classifiers":[
        {
            "category":"Social Services",
            "subcategory":"Retirement Home",
            "type":"Services"
        }
    ],
    "sg:phone":"+61 8 9330 1911",
    "sg:postcode":"6156",
    "sg:province":"WA",
    "sg:tags":[
        "village"
    ],
    "wof:name":"Craigville Gardens Village",
    "wof:placetype":"venue"
},
  "geometry": {"coordinates":[115.80201,-32.042488],"type":"Point"}
}