{
  "type": "Feature",
  "properties": {
    "addr:full":"37 Mount View St Aspendale VIC 3195",
    "addr:housenumber":"37",
    "addr:postcode":"3195",
    "addr:street":"Mount View St",
    "iso:country":"AU",
    "sg:address":"37 Mount View St",
    "sg:city":"Aspendale",
    "sg:classifiers":[
        {
            "category":"Professional",
            "subcategory":"Business Services",
            "type":"Services"
        }
    ],
    "sg:phone":"+61 3 9580 6708",
    "sg:postcode":"3195",
    "sg:province":"VIC",
    "sg:tags":[
        "drafting"
    ],
    "wof:name":"Somme Drafting Services Pty Ltd",
    "wof:placetype":"venue"
},
  "geometry": {"coordinates":[145.09483337399999,-38.0139465332],"type":"Point"}
}