{
  "type": "Feature",
  "properties": {
    "addr:full":"Ste3/ 5 Belmore St Burwood NSW 2134",
    "addr:housenumber":"5",
    "addr:postcode":"2134",
    "addr:street":"Belmore St",
    "iso:country":"AU",
    "sg:address":"Ste3/ 5 Belmore St",
    "sg:city":"Burwood",
    "sg:classifiers":[
        {
            "category":"Banks & Credit Unions",
            "subcategory":"Investment Brokerage",
            "type":"Services"
        }
    ],
    "sg:phone":"+61 2 9701 0672",
    "sg:postcode":"2134",
    "sg:province":"NSW",
    "sg:tags":[
        "finance",
        "broker"
    ],
    "wof:name":"Slc Sydney",
    "wof:placetype":"venue"
},
  "geometry": {"coordinates":[151.105957031,-33.8791046143],"type":"Point"}
}