{
  "type": "Feature",
  "properties": {
    "iso:country":"AU",
    "sg:address":"200 Hartley St",
    "sg:city":"Cairns",
    "sg:classifiers":[
        {
            "category":"Building & Trades",
            "subcategory":"Pest Control",
            "type":"Services"
        }
    ],
    "sg:phone":"+61 7 4035 1533",
    "sg:postcode":"4870",
    "sg:province":"QLD",
    "wof:name":"All Pest & Weed Control",
    "wof:placetype":"venue"
},
  "geometry": {"coordinates":[145.75416564899999,-16.9451541901],"type":"Point"}
}