{
  "type": "Feature",
  "properties": {
    "addr:full":"Waterview St Ganmain NSW 2702",
    "addr:postcode":"2702",
    "addr:street":"Waterview St",
    "iso:country":"AU",
    "sg:address":"Waterview St",
    "sg:city":"Ganmain",
    "sg:classifiers":[
        {
            "category":"Arena",
            "subcategory":"Sports Club",
            "type":"Entertainment"
        }
    ],
    "sg:phone":"+61 2 6927 6212",
    "sg:postcode":"2702",
    "sg:province":"NSW",
    "sg:tags":[
        "australian",
        "football",
        "rule"
    ],
    "wof:name":"Ganmain Grong Grong Matong Football Club",
    "wof:placetype":"venue"
},
  "geometry": {"coordinates":[147.037384033,-34.7947006226],"type":"Point"}
}