{
  "type": "Feature",
  "properties": {
    "addr:full":"239 Dundas St Preston VIC 3072",
    "addr:housenumber":"239",
    "addr:postcode":"3072",
    "addr:street":"Dundas St",
    "iso:country":"AU",
    "sg:address":"239 Dundas St",
    "sg:city":"Preston",
    "sg:classifiers":[
        {
            "category":"Manufacturing",
            "subcategory":"Metals",
            "type":"Manufacturing & Wholesale Goods"
        }
    ],
    "sg:phone":"+61 3 9480 6959",
    "sg:postcode":"3072",
    "sg:province":"VIC",
    "sg:tags":[
        "polisher"
    ],
    "wof:name":"Australian Metal Polishing Co",
    "wof:placetype":"venue"
},
  "geometry": {"coordinates":[145.025314331,-37.7547874451],"type":"Point"}
}