{
  "type": "Feature",
  "properties": {
    "addr:full":"233 Fryar Rd Eagleby QLD 4207",
    "addr:housenumber":"233",
    "addr:postcode":"4207",
    "addr:street":"Fryar Rd",
    "iso:country":"AU",
    "sg:address":"233 Fryar Rd",
    "sg:city":"Eagleby",
    "sg:classifiers":[
        {
            "category":"Social Services",
            "subcategory":"Child Care",
            "type":"Services"
        }
    ],
    "sg:phone":"+61 439 781 390",
    "sg:postcode":"4207",
    "sg:province":"QLD",
    "wof:name":"All About Kids",
    "wof:placetype":"venue"
},
  "geometry": {"coordinates":[153.214553833,-27.6950626373],"type":"Point"}
}