{
  "type": "Feature",
  "properties": {
    "iso:country":"AU",
    "sg:address":"Lot 7 Maison Dieu Rd",
    "sg:city":"Singleton",
    "sg:classifiers":[
        {
            "category":"Communications",
            "type":"Services"
        }
    ],
    "sg:phone":"+61 2 6571 1717",
    "sg:postcode":"2330",
    "sg:province":"NSW",
    "sg:tags":[
        "equipment",
        "radio"
    ],
    "wof:name":"Novacom Communications",
    "wof:placetype":"venue"
},
  "geometry": {"coordinates":[151.13342299999999,-32.549263],"type":"Point"}
}