{
  "type": "Feature",
  "properties": {
    "addr:full":"54 Press Rd Brooklyn Park SA 5032",
    "addr:housenumber":"54",
    "addr:postcode":"5032",
    "addr:street":"Press Rd",
    "iso:country":"AU",
    "sg:address":"54 Press Rd",
    "sg:city":"Brooklyn Park",
    "sg:classifiers":[
        {
            "category":"Retail",
            "subcategory":"Auto Repair",
            "type":"Services"
        }
    ],
    "sg:phone":"+61 8 8234 9116",
    "sg:postcode":"5032",
    "sg:province":"SA",
    "sg:tags":[
        "repairer",
        "motor",
        "engineer"
    ],
    "wof:name":"Automotive Industry Consultancy",
    "wof:placetype":"venue"
},
  "geometry": {"coordinates":[138.54624939000001,-34.9348297119],"type":"Point"}
}