{
  "type": "Feature",
  "properties": {
    "iso:country":"AU",
    "sg:address":"49 Thomas Drv",
    "sg:city":"Chevron Island",
    "sg:classifiers":[
        {
            "category":"Shopping",
            "subcategory":"Jewelry",
            "type":"Retail Goods"
        }
    ],
    "sg:phone":"+61 7 5538 4849",
    "sg:postcode":"4217",
    "sg:province":"QLD",
    "sg:tags":[
        "jeweller"
    ],
    "wof:name":"J.R. Woodley",
    "wof:placetype":"venue"
},
  "geometry": {"coordinates":[153.419464111,-27.9977855682],"type":"Point"}
}