{
  "type": "Feature",
  "properties": {
    "addr:full":"First Floor 92 Victoria St Mackay QLD 4740",
    "addr:housenumber":"92",
    "addr:postcode":"4740",
    "addr:street":"Floor;Victoria St",
    "iso:country":"AU",
    "sg:address":"First Floor 92 Victoria St",
    "sg:city":"Mackay",
    "sg:classifiers":[
        {
            "category":"Organizations",
            "subcategory":"Professional Association",
            "type":"Services"
        }
    ],
    "sg:phone":"+61 7 4953 3609",
    "sg:postcode":"4740",
    "sg:province":"QLD",
    "sg:tags":[
        "web",
        "internet"
    ],
    "wof:name":"www.weddings-mackay.com.au",
    "wof:placetype":"venue"
},
  "geometry": {"coordinates":[149.18675200000001,-21.141136],"type":"Point"}
}