{
  "type": "Feature",
  "properties": {
    "iso:country":"AU",
    "sg:address":"68 Rawson St",
    "sg:city":"Haberfield",
    "sg:classifiers":[
        {
            "category":"Professional",
            "subcategory":"Employment Agencies",
            "type":"Services"
        }
    ],
    "sg:phone":"+61 427 689 963",
    "sg:postcode":"2045",
    "sg:province":"NSW",
    "sg:tags":[
        "occupational",
        "therapist"
    ],
    "wof:name":"Kids on top",
    "wof:placetype":"venue"
},
  "geometry": {"coordinates":[151.142349,-33.875057],"type":"Point"}
}