{
  "type": "Feature",
  "properties": {
    "iso:country":"AU",
    "sg:address":"Fcty57/ 36 Barku Crt",
    "sg:city":"Hemmant",
    "sg:classifiers":[
        {
            "category":"Autos & Motor Vehicles",
            "subcategory":"Boat Sales",
            "type":"Retail Goods"
        }
    ],
    "sg:phone":"+61 7 3393 6742",
    "sg:postcode":"4174",
    "sg:province":"QLD",
    "sg:tags":[
        "builder",
        "yacht",
        "repairer"
    ],
    "wof:name":"Smart Marine Services",
    "wof:placetype":"venue"
},
  "geometry": {"coordinates":[153.131988525,-27.4301586151],"type":"Point"}
}