{
  "type": "Feature",
  "properties": {
    "addr:full":"2/ 1401 Logan Rd Mt Gravatt QLD 4122",
    "addr:housenumber":"/ 1401",
    "addr:postcode":"4122",
    "addr:street":"Logan Rd",
    "iso:country":"AU",
    "sg:address":"2/ 1401 Logan Rd",
    "sg:city":"Mt Gravatt",
    "sg:classifiers":[
        {
            "category":"Shopping",
            "subcategory":"Bridal",
            "type":"Retail Goods"
        }
    ],
    "sg:phone":"+61 7 3219 1418",
    "sg:postcode":"4122",
    "sg:province":"QLD",
    "sg:tags":[
        "hire",
        "wear"
    ],
    "wof:name":"La Bella Moda",
    "wof:placetype":"venue"
},
  "geometry": {"coordinates":[153.079223633,-27.5384540558],"type":"Point"}
}