{
  "type": "Feature",
  "properties": {
    "addr:full":"3/ 31 Mary St Noosaville QLD 4566",
    "addr:housenumber":"/ 31",
    "addr:postcode":"4566",
    "addr:street":"Mary St",
    "iso:country":"AU",
    "sg:address":"3/ 31 Mary St",
    "sg:city":"Noosaville",
    "sg:classifiers":[
        {
            "category":"Real Estate",
            "subcategory":"Architect",
            "type":"Services"
        }
    ],
    "sg:phone":"+61 7 5474 0408",
    "sg:postcode":"4566",
    "sg:province":"QLD",
    "wof:name":"Greg Gibbs Architects",
    "wof:placetype":"venue"
},
  "geometry": {"coordinates":[153.06507873499999,-26.400346756],"type":"Point"}
}