{
  "type": "Feature",
  "properties": {
    "iso:country":"AU",
    "sg:address":"PO Box 353",
    "sg:city":"Millicent",
    "sg:classifiers":[
        {
            "category":"Farming",
            "subcategory":"Farm",
            "type":"Manufacturing & Wholesale Goods"
        }
    ],
    "sg:phone":"+61 8 8733 4488",
    "sg:postcode":"5280",
    "sg:province":"SA",
    "sg:tags":[
        "farmer"
    ],
    "wof:name":"Bell G N & P B",
    "wof:placetype":"venue"
},
  "geometry": {"coordinates":[140.351334,-37.593342],"type":"Point"}
}