{
  "type": "Feature",
  "properties": {
    "addr:full":"Shop 7 Robinlee Ave Burwood East VIC 3151",
    "addr:housenumber":"shop 7",
    "addr:postcode":"3151",
    "addr:street":"Robinlee Ave",
    "iso:country":"AU",
    "sg:address":"Shop 7 Robinlee Ave",
    "sg:city":"Burwood East",
    "sg:classifiers":[
        {
            "category":"Shopping",
            "subcategory":"News",
            "type":"Retail Goods"
        }
    ],
    "sg:phone":"+61 3 9886 1710",
    "sg:postcode":"3151",
    "sg:province":"VIC",
    "sg:tags":[
        "magazine",
        "periodical"
    ],
    "wof:name":"Computer Trader",
    "wof:placetype":"venue"
},
  "geometry": {"coordinates":[145.159225464,-37.8464622498],"type":"Point"}
}