{
  "type": "Feature",
  "properties": {
    "iso:country":"AU",
    "sg:address":"210 Walsh St",
    "sg:city":"Mareeba",
    "sg:classifiers":[
        {
            "category":"Health Services",
            "subcategory":"Health Practitioner",
            "type":"Services"
        }
    ],
    "sg:phone":"+61 7 4092 7711",
    "sg:postcode":"4880",
    "sg:province":"QLD",
    "sg:tags":[
        "physiotherapist"
    ],
    "wof:name":"Tableland Physiotherapy",
    "wof:placetype":"venue"
},
  "geometry": {"coordinates":[145.424118042,-16.9994812012],"type":"Point"}
}