{
  "type": "Feature",
  "properties": {
    "addr:full":"&#034;Yarrabee&#034;+ 1913 Cudgewa Bluff Rd Walwa VIC 3709",
    "addr:postcode":"3709",
    "addr:street":"Bluff Rd",
    "iso:country":"AU",
    "sg:address":"&#034;Yarrabee&#034;+ 1913 Cudgewa Bluff Rd",
    "sg:city":"Walwa",
    "sg:classifiers":[
        {
            "category":"Shopping",
            "type":"Retail Goods"
        }
    ],
    "sg:phone":"+61 428 233 472",
    "sg:postcode":"3709",
    "sg:province":"VIC",
    "sg:tags":[
        "agent",
        "stock"
    ],
    "wof:name":"Drummond K G",
    "wof:placetype":"venue"
},
  "geometry": {"coordinates":[147.735198975,-36.0046386719],"type":"Point"}
}