{
  "type": "Feature",
  "properties": {
    "addr:full":"11 Mason Ave Parkhurst QLD 4702",
    "addr:housenumber":"11",
    "addr:postcode":"4702",
    "addr:street":"Mason Ave",
    "iso:country":"AU",
    "sg:address":"11 Mason Ave",
    "sg:city":"Parkhurst",
    "sg:classifiers":[
        {
            "category":"Education",
            "subcategory":"School",
            "type":"Public Place"
        }
    ],
    "sg:phone":"+61 7 4924 6514",
    "sg:postcode":"4702",
    "sg:province":"QLD",
    "sg:tags":[
        "state",
        "except",
        "nsw"
    ],
    "wof:name":"Parkhurst Preschool",
    "wof:placetype":"venue"
},
  "geometry": {"coordinates":[150.51278686500001,-23.2959442139],"type":"Point"}
}