{
  "type": "Feature",
  "properties": {
    "addr:full":"27 Alexander St Port Pirie SA 5540",
    "addr:housenumber":"27",
    "addr:postcode":"5540",
    "addr:street":"Alexander St",
    "iso:country":"AU",
    "sg:address":"27 Alexander St",
    "sg:city":"Port Pirie",
    "sg:classifiers":[
        {
            "category":"Shopping",
            "subcategory":"Mobile Phones",
            "type":"Retail Goods"
        }
    ],
    "sg:phone":"+61 8 8633 3000",
    "sg:postcode":"5540",
    "sg:province":"SA",
    "sg:tags":[
        "telephone",
        "accessory"
    ],
    "wof:name":"Phone Xpress",
    "wof:placetype":"venue"
},
  "geometry": {"coordinates":[138.009033203,-33.1773986816],"type":"Point"}
}