{
  "type": "Feature",
  "properties": {
    "iso:country":"AU",
    "sg:address":"646 Bridge Rd",
    "sg:city":"Richmond",
    "sg:classifiers":[
        {
            "category":"Retail",
            "subcategory":"Repair Shop",
            "type":"Services"
        }
    ],
    "sg:phone":"+61 3 9429 2459",
    "sg:postcode":"3121",
    "sg:province":"VIC",
    "sg:tags":[
        "machine",
        "repairs",
        "part",
        "dryer",
        "washing"
    ],
    "wof:name":"Toms Appliance Spares",
    "wof:placetype":"venue"
},
  "geometry": {"coordinates":[145.01361084000001,-37.8201980591],"type":"Point"}
}