{
  "type": "Feature",
  "properties": {
    "addr:full":"194 Lakedge Ave Berkeley Vale NSW 2261",
    "addr:housenumber":"194",
    "addr:postcode":"2261",
    "addr:street":"Lakedge Ave",
    "iso:country":"AU",
    "sg:address":"194 Lakedge Ave",
    "sg:city":"Berkeley Vale",
    "sg:classifiers":[
        {
            "category":"Utilities",
            "subcategory":"Electric",
            "type":"Services"
        }
    ],
    "sg:phone":"+61 2 4389 1801",
    "sg:postcode":"2261",
    "sg:province":"NSW",
    "sg:tags":[
        "electrical",
        "contractor"
    ],
    "wof:name":"Pocknall M A",
    "wof:placetype":"venue"
},
  "geometry": {"coordinates":[151.43850699999999,-33.344765],"type":"Point"}
}