{
  "type": "Feature",
  "properties": {
    "addr:full":"11 Roslyn St Liverpool NSW 2170",
    "addr:housenumber":"11",
    "addr:postcode":"2170",
    "addr:street":"Roslyn St",
    "iso:country":"AU",
    "sg:address":"11 Roslyn St",
    "sg:city":"Liverpool",
    "sg:classifiers":[
        {
            "category":"Health Services",
            "subcategory":"Doctor",
            "type":"Services"
        }
    ],
    "sg:phone":"+61 2 9602 5243",
    "sg:postcode":"2170",
    "sg:province":"NSW",
    "sg:tags":[
        "medical",
        "practitioner"
    ],
    "wof:name":"Yap Robert",
    "wof:placetype":"venue"
},
  "geometry": {"coordinates":[150.91038513199999,-33.9169769287],"type":"Point"}
}