{
  "type": "Feature",
  "properties": {
    "addr:full":"23 Plimsoll St Sans Souci NSW 2219",
    "addr:housenumber":"23",
    "addr:postcode":"2219",
    "addr:street":"Plimsoll St",
    "iso:country":"AU",
    "sg:address":"23 Plimsoll St",
    "sg:city":"Sans Souci",
    "sg:classifiers":[
        {
            "category":"Building & Trades",
            "subcategory":"Construction",
            "type":"Services"
        }
    ],
    "sg:phone":"+61 2 9283 3446",
    "sg:postcode":"2219",
    "sg:province":"NSW",
    "sg:tags":[
        "contractor"
    ],
    "wof:name":"TBAMS PTY LTD",
    "wof:placetype":"venue"
},
  "geometry": {"coordinates":[151.125274658,-33.9981803894],"type":"Point"}
}