{
  "type": "Feature",
  "properties": {
    "addr:full":"12 A Howitt St South Yarra VIC 3141",
    "addr:housenumber":"12 a",
    "addr:postcode":"3141",
    "addr:street":"Howitt St",
    "iso:country":"AU",
    "sg:address":"12 A Howitt St",
    "sg:city":"South Yarra",
    "sg:classifiers":[
        {
            "category":"Health Services",
            "subcategory":"Health Practitioner",
            "type":"Services"
        }
    ],
    "sg:phone":"+61 3 9827 1725",
    "sg:postcode":"3141",
    "sg:province":"VIC",
    "sg:tags":[
        "naturopath"
    ],
    "wof:name":"Moontides Womens Health Centre Pty Ltd",
    "wof:placetype":"venue"
},
  "geometry": {"coordinates":[145.000854492,-37.8467903137],"type":"Point"}
}