{
  "type": "Feature",
  "properties": {
    "addr:full":"41 Freelander Ave Katoomba NSW 2780",
    "addr:housenumber":"41",
    "addr:postcode":"2780",
    "addr:street":"Freelander Ave",
    "iso:country":"AU",
    "sg:address":"41 Freelander Ave",
    "sg:city":"Katoomba",
    "sg:classifiers":[
        {
            "category":"Shopping",
            "subcategory":"Stationery & Office Supplies",
            "type":"Retail Goods"
        }
    ],
    "sg:phone":"+61 2 4782 4822",
    "sg:postcode":"2780",
    "sg:province":"NSW",
    "sg:tags":[
        "pottery",
        "equipment"
    ],
    "wof:name":"Potters At Work",
    "wof:placetype":"venue"
},
  "geometry": {"coordinates":[150.31260681099999,-33.7063331604],"type":"Point"}
}