{
  "type": "Feature",
  "properties": {
    "addr:full":"51 Roberts Ave Horsham VIC 3400",
    "addr:housenumber":"51",
    "addr:postcode":"3400",
    "addr:street":"Roberts Ave",
    "iso:country":"AU",
    "sg:address":"51 Roberts Ave",
    "sg:city":"Horsham",
    "sg:classifiers":[
        {
            "category":"Personal",
            "type":"Services"
        }
    ],
    "sg:phone":"+61 1300 885 917",
    "sg:postcode":"3400",
    "sg:province":"VIC",
    "sg:tags":[
        "gift"
    ],
    "wof:name":"Horsham Florist",
    "wof:placetype":"venue"
},
  "geometry": {"coordinates":[142.19790649399999,-36.7144126892],"type":"Point"}
}