{
  "type": "Feature",
  "properties": {
    "addr:full":"363 Allan St Kyabram VIC 3620",
    "addr:housenumber":"363",
    "addr:postcode":"3620",
    "addr:street":"Allan St",
    "iso:country":"AU",
    "sg:address":"363 Allan St",
    "sg:city":"Kyabram",
    "sg:classifiers":[
        {
            "category":"Travel",
            "subcategory":"Hotels & Motels",
            "type":"Entertainment"
        }
    ],
    "sg:phone":"+61 3 5852 3577",
    "sg:postcode":"3620",
    "sg:province":"VIC",
    "wof:name":"Ky Country Roads Motor Inn",
    "wof:placetype":"venue"
},
  "geometry": {"coordinates":[145.05455017099999,-36.3133125305],"type":"Point"}
}