{
  "type": "Feature",
  "properties": {
    "iso:country":"AU",
    "sg:address":"161 Main St",
    "sg:city":"West Wyalong",
    "sg:classifiers":[
        {
            "category":"Personal",
            "subcategory":"Beauty Salon",
            "type":"Services"
        }
    ],
    "sg:phone":"+61 2 6972 2620",
    "sg:postcode":"2671",
    "sg:province":"NSW",
    "sg:tags":[
        "hairdresser"
    ],
    "wof:name":"Coelli Joan",
    "wof:placetype":"venue"
},
  "geometry": {"coordinates":[147.201416016,-33.9222717285],"type":"Point"}
}