{
  "type": "Feature",
  "properties": {
    "addr:full":"Level 1 600 Collins St Melbourne VIC 3000",
    "addr:housenumber":"600",
    "addr:postcode":"3000",
    "addr:street":"Collins St",
    "iso:country":"AU",
    "sg:address":"Level 1 600 Collins St",
    "sg:city":"Melbourne",
    "sg:classifiers":[
        {
            "category":"Banks & Credit Unions",
            "subcategory":"Bank",
            "type":"Services"
        }
    ],
    "sg:phone":"+61 3 9615 0675",
    "sg:postcode":"3000",
    "sg:province":"VIC",
    "sg:tags":[
        "society"
    ],
    "wof:name":"Advantage Financial Planning",
    "wof:placetype":"venue"
},
  "geometry": {"coordinates":[144.95474243199999,-37.8187675476],"type":"Point"}
}