{
  "type": "Feature",
  "properties": {
    "addr:full":"Shop 5, 15 - 21 Smith St Mooloolaba QLD 4557",
    "addr:housenumber":"shop;15 21",
    "addr:postcode":"4557",
    "addr:street":"Smith St",
    "iso:country":"AU",
    "sg:address":"Shop 5, 15 - 21 Smith St",
    "sg:city":"Mooloolaba",
    "sg:classifiers":[
        {
            "category":"Banks & Credit Unions",
            "subcategory":"Bank",
            "type":"Services"
        }
    ],
    "sg:phone":"+61 7 5477 7267",
    "sg:postcode":"4557",
    "sg:province":"QLD",
    "sg:tags":[
        "broker",
        "mortgage"
    ],
    "wof:name":"RAMS Home Loans",
    "wof:placetype":"venue"
},
  "geometry": {"coordinates":[153.11805725100001,-26.6811981201],"type":"Point"}
}