{
  "type": "Feature",
  "properties": {
    "addr:full":"Suite 2 Ground Floor 4- 6 Watt St Gosford NSW 2250",
    "addr:housenumber":"6",
    "addr:postcode":"2250",
    "addr:street":"Watt St",
    "iso:country":"AU",
    "sg:address":"Suite 2 Ground Floor 4- 6 Watt St",
    "sg:city":"Gosford",
    "sg:classifiers":[
        {
            "category":"Health Services",
            "subcategory":"Doctor",
            "type":"Services"
        }
    ],
    "sg:phone":"+61 2 4322 8810",
    "sg:postcode":"2250",
    "sg:province":"NSW",
    "sg:tags":[
        "medical",
        "practitioner"
    ],
    "wof:name":"Resmed Centre for Healthy Sleep",
    "wof:placetype":"venue"
},
  "geometry": {"coordinates":[151.343994141,-33.4215621948],"type":"Point"}
}