{
  "type": "Feature",
  "properties": {
    "iso:country":"AU",
    "sg:address":"Suites 2 & 5/ 6 Railway Pde",
    "sg:city":"Burwood",
    "sg:classifiers":[
        {
            "category":"Health Services",
            "subcategory":"Doctor",
            "type":"Services"
        }
    ],
    "sg:phone":"+61 2 9747 2688",
    "sg:postcode":"2134",
    "sg:province":"NSW",
    "sg:tags":[
        "medical",
        "practitioner"
    ],
    "wof:name":"Yiannikas Con",
    "wof:placetype":"venue"
},
  "geometry": {"coordinates":[151.106567383,-33.8781394958],"type":"Point"}
}