{
  "type": "Feature",
  "properties": {
    "iso:country":"AU",
    "sg:address":"115a Pt Cartwright Drv",
    "sg:city":"Buddina",
    "sg:classifiers":[
        {
            "category":"Fast Food",
            "type":"Food & Drink"
        }
    ],
    "sg:phone":"+61 7 5444 0988",
    "sg:postcode":"4575",
    "sg:province":"QLD",
    "sg:tags":[
        "away",
        "take"
    ],
    "wof:name":"All&#039;Antica",
    "wof:placetype":"venue"
},
  "geometry": {"coordinates":[153.129913,-26.701279],"type":"Point"}
}