{
  "type": "Feature",
  "properties": {
    "iso:country":"AU",
    "sg:address":"PO Box 134",
    "sg:city":"Ramsgate",
    "sg:classifiers":[
        {
            "category":"Arts & Performance",
            "subcategory":"Theater",
            "type":"Entertainment"
        }
    ],
    "sg:phone":"+61 2 9547 2722",
    "sg:postcode":"2217",
    "sg:province":"NSW",
    "sg:tags":[
        "agency",
        "booking",
        "theatre"
    ],
    "wof:name":"Onstage Productions Warren Kermonds",
    "wof:placetype":"venue"
},
  "geometry": {"coordinates":[151.13807700000001,-33.984421],"type":"Point"}
}