{
  "type": "Feature",
  "properties": {
    "addr:full":"26 Royal Crs Kinglake VIC 3763",
    "addr:housenumber":"26",
    "addr:postcode":"3763",
    "addr:street":"Royal Crs Kinglake",
    "iso:country":"AU",
    "sg:address":"26 Royal Crs",
    "sg:city":"Kinglake",
    "sg:classifiers":[
        {
            "category":"Building & Trades",
            "subcategory":"Construction",
            "type":"Services"
        }
    ],
    "sg:phone":"+61 3 5786 1984",
    "sg:postcode":"3763",
    "sg:province":"VIC",
    "sg:tags":[
        "stonework",
        "stone",
        "mason"
    ],
    "wof:name":"Mountain Stone Constructions",
    "wof:placetype":"venue"
},
  "geometry": {"coordinates":[145.34014892600001,-37.5305786133],"type":"Point"}
}