{
  "type": "Feature",
  "properties": {
    "iso:country":"AU",
    "sg:address":"PO Box 543",
    "sg:city":"Benalla",
    "sg:classifiers":[
        {
            "category":"Retail",
            "subcategory":"Storage",
            "type":"Services"
        }
    ],
    "sg:phone":"+61 3 5762 2707",
    "sg:postcode":"3671",
    "sg:province":"VIC",
    "sg:tags":[
        "removal",
        "furniture"
    ],
    "wof:name":"Symes Transport Operations",
    "wof:placetype":"venue"
},
  "geometry": {"coordinates":[145.988327,-36.550659],"type":"Point"}
}