{
  "type": "Feature",
  "properties": {
    "iso:country":"AU",
    "sg:address":"500 Great Eastern Hwy",
    "sg:city":"Redcliffe",
    "sg:classifiers":[
        {
            "category":"Retail",
            "subcategory":"Auto Repair",
            "type":"Services"
        }
    ],
    "sg:phone":"+61 8 9479 4575",
    "sg:postcode":"6104",
    "sg:province":"WA",
    "sg:tags":[
        "body",
        "builder",
        "motor"
    ],
    "wof:name":"W A Transport Spares & Repairs",
    "wof:placetype":"venue"
},
  "geometry": {"coordinates":[115.95482635499999,-31.9230957031],"type":"Point"}
}