{
  "type": "Feature",
  "properties": {
    "iso:country":"AU",
    "sg:address":"756 Stud Rd",
    "sg:city":"Scoresby",
    "sg:classifiers":[
        {
            "category":"Professional",
            "subcategory":"Engineering",
            "type":"Services"
        }
    ],
    "sg:phone":"+61 3 9764 0411",
    "sg:postcode":"3179",
    "sg:province":"VIC",
    "sg:tags":[
        "engineer"
    ],
    "wof:name":"TechEng Pty Ltd",
    "wof:placetype":"venue"
},
  "geometry": {"coordinates":[145.232696533,-37.8980827332],"type":"Point"}
}