{
  "type": "Feature",
  "properties": {
    "addr:full":"U3/ 274 Unley Rd Hyde Park SA 5061",
    "addr:housenumber":"274",
    "addr:postcode":"5061",
    "addr:street":"U3 /;Unley Rd",
    "iso:country":"AU",
    "sg:address":"U3/ 274 Unley Rd",
    "sg:city":"Hyde Park",
    "sg:classifiers":[
        {
            "category":"Banks & Credit Unions",
            "subcategory":"Investment Brokerage",
            "type":"Services"
        }
    ],
    "sg:phone":"+61 8 8274 8000",
    "sg:postcode":"5061",
    "sg:province":"SA",
    "sg:tags":[
        "finance",
        "broker"
    ],
    "wof:name":"Money Advisers Unley",
    "wof:placetype":"venue"
},
  "geometry": {"coordinates":[138.60772705100001,-34.9552154541],"type":"Point"}
}