{
  "type": "Feature",
  "properties": {
    "iso:country":"AU",
    "sg:address":"109 Maribyrnong Rd",
    "sg:city":"Ascot Vale",
    "sg:classifiers":[
        {
            "category":"Home & Garden",
            "subcategory":"Building Materials",
            "type":"Retail Goods"
        }
    ],
    "sg:phone":"+61 3 9375 4047",
    "sg:postcode":"3032",
    "sg:province":"VIC",
    "sg:tags":[
        "fencing"
    ],
    "wof:name":"Minh Metal",
    "wof:placetype":"venue"
},
  "geometry": {"coordinates":[144.91589400000001,-37.771549],"type":"Point"}
}