{
  "type": "Feature",
  "properties": {
    "addr:full":"PO Box 5751 Clare SA 5453",
    "addr:postcode":"5453",
    "iso:country":"AU",
    "sg:address":"PO Box 5751",
    "sg:city":"Clare",
    "sg:classifiers":[
        {
            "category":"Home & Garden",
            "subcategory":"Carpets & Floor Coverings",
            "type":"Retail Goods"
        }
    ],
    "sg:phone":"+61 428 942 186",
    "sg:postcode":"5453",
    "sg:province":"SA",
    "sg:tags":[
        "tile",
        "wall",
        "layer"
    ],
    "wof:name":"S M & T M Degenhardt",
    "wof:placetype":"venue"
},
  "geometry": {"coordinates":[138.61077900000001,-33.83239],"type":"Point"}
}