{
  "type": "Feature",
  "properties": {
    "addr:full":"2099 Malvern Rd Malvern East VIC 3145",
    "addr:housenumber":"2099",
    "addr:postcode":"3145",
    "addr:street":"Malvern Rd",
    "iso:country":"AU",
    "sg:address":"2099 Malvern Rd",
    "sg:city":"Malvern East",
    "sg:classifiers":[
        {
            "category":"Building & Trades",
            "subcategory":"Plumbing",
            "type":"Services"
        }
    ],
    "sg:phone":"+61 418 400 777",
    "sg:postcode":"3145",
    "sg:province":"VIC",
    "sg:tags":[
        "plumber",
        "gasfitters"
    ],
    "wof:name":"Derry Plumbing",
    "wof:placetype":"venue"
},
  "geometry": {"coordinates":[145.067749023,-37.8778038025],"type":"Point"}
}