{
  "type": "Feature",
  "properties": {
    "addr:full":"41 High St Walkerston QLD 4751",
    "addr:housenumber":"41",
    "addr:postcode":"4751",
    "addr:street":"High St",
    "iso:country":"AU",
    "sg:address":"41 High St",
    "sg:city":"Walkerston",
    "sg:classifiers":[
        {
            "category":"Building & Trades",
            "subcategory":"Construction",
            "type":"Services"
        }
    ],
    "sg:phone":"+61 7 4959 2260",
    "sg:postcode":"4751",
    "sg:province":"QLD",
    "sg:tags":[
        "earth",
        "excavating",
        "moving",
        "contractor"
    ],
    "wof:name":"Youngs Excavations",
    "wof:placetype":"venue"
},
  "geometry": {"coordinates":[149.06982400000001,-21.162498],"type":"Point"}
}