{
  "type": "Feature",
  "properties": {
    "addr:full":"27 Westralia St Stuart Park NT 0820",
    "addr:housenumber":"27",
    "addr:postcode":"0820",
    "addr:street":"Westralia St",
    "iso:country":"AU",
    "sg:address":"27 Westralia St",
    "sg:city":"Stuart Park",
    "sg:classifiers":[
        {
            "category":"Building & Trades",
            "subcategory":"Plumbing",
            "type":"Services"
        }
    ],
    "sg:phone":"+61 8 8941 0201",
    "sg:postcode":"0820",
    "sg:province":"NT",
    "sg:tags":[
        "plumber",
        "gasfitters"
    ],
    "wof:name":"Carodale Pty Ltd",
    "wof:placetype":"venue"
},
  "geometry": {"coordinates":[130.844360352,-12.4448547363],"type":"Point"}
}