{
  "type": "Feature",
  "properties": {
    "iso:country":"AU",
    "sg:address":"PO Box 524",
    "sg:city":"Cleveland",
    "sg:classifiers":[
        {
            "category":"Food & Beverages",
            "subcategory":"Specialty",
            "type":"Retail Goods"
        }
    ],
    "sg:phone":"+61 416 121 450",
    "sg:postcode":"4163",
    "sg:province":"QLD",
    "sg:tags":[
        "product",
        "health"
    ],
    "wof:name":"About Alternatives",
    "wof:placetype":"venue"
},
  "geometry": {"coordinates":[153.26710510300001,-27.5265293121],"type":"Point"}
}