{
  "type": "Feature",
  "properties": {
    "addr:full":"33 Richard St Lota QLD 4179",
    "addr:housenumber":"33",
    "addr:postcode":"4179",
    "addr:street":"Richard St",
    "iso:country":"AU",
    "sg:address":"33 Richard St",
    "sg:city":"Lota",
    "sg:classifiers":[
        {
            "category":"Professional",
            "subcategory":"Art Services",
            "type":"Services"
        }
    ],
    "sg:phone":"+61 7 3396 6378",
    "sg:postcode":"4179",
    "sg:province":"QLD",
    "sg:tags":[
        "conservation",
        "restoration"
    ],
    "wof:name":"Atelier Fine Art Restoration",
    "wof:placetype":"venue"
},
  "geometry": {"coordinates":[153.186447144,-27.4682865143],"type":"Point"}
}