{
  "type": "Feature",
  "properties": {
    "addr:full":"GPO Box 2756 Brisbane QLD 9000",
    "addr:postcode":"9000",
    "iso:country":"AU",
    "sg:address":"GPO Box 2756",
    "sg:city":"Brisbane",
    "sg:classifiers":[
        {
            "category":"Professional",
            "subcategory":"Employment Agencies",
            "type":"Services"
        }
    ],
    "sg:phone":"+61 7 3221 2177",
    "sg:postcode":"9000",
    "sg:province":"QLD",
    "wof:name":"Executive People",
    "wof:placetype":"venue"
},
  "geometry": {"coordinates":[152.888595581,-27.5975894928],"type":"Point"}
}