{
  "type": "Feature",
  "properties": {
    "addr:full":"20 Coondoo St Kuranda QLD 4881",
    "addr:housenumber":"20",
    "addr:postcode":"4881",
    "addr:street":"Coondoo St",
    "iso:country":"AU",
    "sg:address":"20 Coondoo St",
    "sg:city":"Kuranda",
    "sg:classifiers":[
        {
            "category":"Shopping",
            "subcategory":"Crafts & Fabrics",
            "type":"Retail Goods"
        }
    ],
    "sg:phone":"+61 407 224 459",
    "sg:postcode":"4881",
    "sg:province":"QLD",
    "sg:tags":[
        "silk"
    ],
    "wof:name":"Didi La Baysee",
    "wof:placetype":"venue"
},
  "geometry": {"coordinates":[145.635498047,-16.8196792603],"type":"Point"}
}