{
  "type": "Feature",
  "properties": {
    "addr:full":"227 Maryborough/Hervey Bay Rd Hervey Bay QLD 4655",
    "addr:housenumber":"227",
    "addr:postcode":"4655",
    "addr:street":"Hervey Bay Rd",
    "iso:country":"AU",
    "sg:address":"227 Maryborough/Hervey Bay Rd",
    "sg:city":"Hervey Bay",
    "sg:classifiers":[
        {
            "category":"Communications",
            "subcategory":"News Services",
            "type":"Services"
        }
    ],
    "sg:phone":"+61 7 4125 9855",
    "sg:postcode":"4655",
    "sg:province":"QLD",
    "sg:tags":[
        "information",
        "tourist",
        "attractions"
    ],
    "sg:website":"http://www.visitherveybay.info",
    "wof:name":"Tourism Hervey Bay",
    "wof:placetype":"venue"
},
  "geometry": {"coordinates":[152.809662,-25.302574],"type":"Point"}
}