{
  "type": "Feature",
  "properties": {
    "iso:country":"AU",
    "sg:address":"24 A Phillips St",
    "sg:city":"Thebarton",
    "sg:classifiers":[
        {
            "category":"Government",
            "subcategory":"Police Station",
            "type":"Public Place"
        }
    ],
    "sg:phone":"+61 8 8352 7771",
    "sg:postcode":"5031",
    "sg:province":"SA",
    "sg:tags":[
        "steering",
        "power"
    ],
    "wof:name":"Active Power Steering",
    "wof:placetype":"venue"
},
  "geometry": {"coordinates":[138.577072144,-34.9134368896],"type":"Point"}
}