{
  "type": "Feature",
  "properties": {
    "iso:country":"AU",
    "sg:address":"Oberon District Hospital North St",
    "sg:city":"Oberon",
    "sg:classifiers":[
        {
            "category":"Social Services",
            "type":"Services"
        }
    ],
    "sg:phone":"+61 2 6336 1300",
    "sg:postcode":"2787",
    "sg:province":"NSW",
    "sg:tags":[
        "disabled",
        "person",
        "equipment"
    ],
    "wof:name":"Oberon District Car Committee",
    "wof:placetype":"venue"
},
  "geometry": {"coordinates":[149.854171753,-33.7040100098],"type":"Point"}
}