{
  "type": "Feature",
  "properties": {
    "addr:full":"17 Selwyn St Paddington NSW 2021",
    "addr:housenumber":"17",
    "addr:postcode":"2021",
    "addr:street":"Selwyn St",
    "iso:country":"AU",
    "sg:address":"17 Selwyn St",
    "sg:city":"Paddington",
    "sg:classifiers":[
        {
            "category":"Professional",
            "subcategory":"Art Services",
            "type":"Services"
        }
    ],
    "sg:phone":"+61 2 9331 6722",
    "sg:postcode":"2021",
    "sg:province":"NSW",
    "sg:tags":[
        "artist"
    ],
    "wof:name":"Mary Pinnock Art & Design",
    "wof:placetype":"venue"
},
  "geometry": {"coordinates":[151.219573975,-33.8839035034],"type":"Point"}
}