{
  "type": "Feature",
  "properties": {
    "addr:full":"35 McPherson St Woodenbong NSW 2476",
    "addr:housenumber":"35",
    "addr:postcode":"2476",
    "addr:street":"Mcpherson St",
    "iso:country":"AU",
    "sg:address":"35 McPherson St",
    "sg:city":"Woodenbong",
    "sg:classifiers":[
        {
            "category":"Personal",
            "subcategory":"Beauty Salon",
            "type":"Services"
        }
    ],
    "sg:phone":"+61 2 6635 1239",
    "sg:postcode":"2476",
    "sg:province":"NSW",
    "sg:tags":[
        "hairdresser"
    ],
    "wof:name":"Woodenbong Hair Design",
    "wof:placetype":"venue"
},
  "geometry": {"coordinates":[152.61207580600001,-28.3896064758],"type":"Point"}
}