{
  "type": "Feature",
  "properties": {
    "addr:full":"24 Tarina St Noosa Heads QLD 4567",
    "addr:housenumber":"24",
    "addr:postcode":"4567",
    "addr:street":"Tarina St",
    "iso:country":"AU",
    "sg:address":"24 Tarina St",
    "sg:city":"Noosa Heads",
    "sg:classifiers":[
        {
            "category":"Personal",
            "subcategory":"Massage",
            "type":"Services"
        }
    ],
    "sg:phone":"+61 411 554 318",
    "sg:postcode":"4567",
    "sg:province":"QLD",
    "sg:tags":[
        "therapy"
    ],
    "wof:name":"Jurgen Schiffers",
    "wof:placetype":"venue"
},
  "geometry": {"coordinates":[153.087966919,-26.405834198],"type":"Point"}
}