{
  "type": "Feature",
  "properties": {
    "addr:full":"12 High St Drysdale VIC 3222",
    "addr:housenumber":"12",
    "addr:postcode":"3222",
    "addr:street":"High St",
    "iso:country":"AU",
    "sg:address":"12 High St",
    "sg:city":"Drysdale",
    "sg:classifiers":[
        {
            "category":"Food & Beverages",
            "subcategory":"Fruits & Vegetables",
            "type":"Retail Goods"
        }
    ],
    "sg:phone":"+61 3 5251 2401",
    "sg:postcode":"3222",
    "sg:province":"VIC",
    "sg:tags":[
        "greengrocer",
        "fruiterer"
    ],
    "wof:name":"Drysdale Convenience Store",
    "wof:placetype":"venue"
},
  "geometry": {"coordinates":[144.57032775900001,-38.1732788086],"type":"Point"}
}