{
  "type": "Feature",
  "properties": {
    "addr:full":"Unit 7/ 30 Foundry Rd Seven Hills NSW 2147",
    "addr:housenumber":"30",
    "addr:postcode":"2147",
    "addr:street":"Foundry Rd",
    "iso:country":"AU",
    "sg:address":"Unit 7/ 30 Foundry Rd",
    "sg:city":"Seven Hills",
    "sg:classifiers":[
        {
            "category":"Building & Trades",
            "subcategory":"Construction",
            "type":"Services"
        }
    ],
    "sg:phone":"+61 2 8824 2600",
    "sg:postcode":"2147",
    "sg:province":"NSW",
    "sg:tags":[
        "contractor"
    ],
    "wof:name":"Devine Homes",
    "wof:placetype":"venue"
},
  "geometry": {"coordinates":[150.95512390100001,-33.7702865601],"type":"Point"}
}