{
  "type": "Feature",
  "properties": {
    "addr:full":"1a Quirk Rd Balgowlah NSW 2093",
    "addr:housenumber":"1a",
    "addr:postcode":"2093",
    "addr:street":"Quirk Rd",
    "iso:country":"AU",
    "sg:address":"1a Quirk Rd",
    "sg:city":"Balgowlah",
    "sg:classifiers":[
        {
            "category":"Retail",
            "subcategory":"Auto Repair",
            "type":"Services"
        }
    ],
    "sg:phone":"+61 2 9949 5788",
    "sg:postcode":"2093",
    "sg:province":"NSW",
    "sg:tags":[
        "camper-trailers",
        "caravan",
        "servicing"
    ],
    "wof:name":"The Camec Group",
    "wof:placetype":"venue"
},
  "geometry": {"coordinates":[151.26974487300001,-33.7878799438],"type":"Point"}
}