{
  "type": "Feature",
  "properties": {
    "iso:country":"AU",
    "sg:address":"2A Murray St",
    "sg:city":"Hamilton",
    "sg:classifiers":[
        {
            "category":"Personal",
            "subcategory":"Massage",
            "type":"Services"
        }
    ],
    "sg:phone":"+61 425 211 039",
    "sg:postcode":"2303",
    "sg:province":"NSW",
    "sg:tags":[
        "therapy"
    ],
    "wof:name":"Body Lee Balance",
    "wof:placetype":"venue"
},
  "geometry": {"coordinates":[151.748077,-32.922188],"type":"Point"}
}