{
  "type": "Feature",
  "properties": {
    "addr:full":"106 Hammond St Hervey Bay QLD 4655",
    "addr:housenumber":"106",
    "addr:postcode":"4655",
    "addr:street":"Hammond St",
    "iso:country":"AU",
    "sg:address":"106 Hammond St",
    "sg:city":"Hervey Bay",
    "sg:classifiers":[
        {
            "category":"Building & Trades",
            "subcategory":"Plumbing",
            "type":"Services"
        }
    ],
    "sg:phone":"+61 7 4125 3510",
    "sg:postcode":"4655",
    "sg:province":"QLD",
    "sg:tags":[
        "consultant"
    ],
    "wof:name":"Water Wise Design",
    "wof:placetype":"venue"
},
  "geometry": {"coordinates":[152.887497,-25.293606],"type":"Point"}
}