{
  "type": "Feature",
  "properties": {
    "addr:full":"45 Brodie Rd (North) Lonsdale SA 5160",
    "addr:housenumber":"45",
    "addr:postcode":"5160",
    "addr:street":"Brodie Rd",
    "iso:country":"AU",
    "sg:address":"45 Brodie Rd (North)",
    "sg:city":"Lonsdale",
    "sg:classifiers":[
        {
            "category":"Home & Garden",
            "subcategory":"Building Materials",
            "type":"Retail Goods"
        }
    ],
    "sg:phone":"+61 8 8329 2800",
    "sg:postcode":"5160",
    "sg:province":"SA",
    "sg:tags":[
        "laminate",
        "laminated",
        "panel"
    ],
    "wof:name":"KT3 Benchtops To The Trade",
    "wof:placetype":"venue"
},
  "geometry": {"coordinates":[138.50907898,-35.1040115356],"type":"Point"}
}