{
  "type": "Feature",
  "properties": {
    "addr:full":"460 Princes Hwy Rockdale NSW 2216",
    "addr:housenumber":"460",
    "addr:postcode":"2216",
    "addr:street":"Princes Hwy",
    "iso:country":"AU",
    "sg:address":"460 Princes Hwy",
    "sg:city":"Rockdale",
    "sg:classifiers":[
        {
            "category":"Travel",
            "subcategory":"Travel Agent",
            "type":"Entertainment"
        }
    ],
    "sg:phone":"+61 2 9556 2665",
    "sg:postcode":"2216",
    "sg:province":"NSW",
    "sg:tags":[
        "consultant"
    ],
    "wof:name":"United World Travel",
    "wof:placetype":"venue"
},
  "geometry": {"coordinates":[151.13864100000001,-33.951077],"type":"Point"}
}