{
  "type": "Feature",
  "properties": {
    "addr:full":"Unit 1, 63 Burnside Rd Stapylton QLD 4207",
    "addr:housenumber":"63",
    "addr:postcode":"4207",
    "addr:street":"Burnside Rd",
    "iso:country":"AU",
    "sg:address":"Unit 1, 63 Burnside Rd",
    "sg:city":"Stapylton",
    "sg:classifiers":[
        {
            "category":"Utilities",
            "subcategory":"Water",
            "type":"Services"
        }
    ],
    "sg:phone":"+61 7 3804 7119",
    "sg:postcode":"4207",
    "sg:province":"QLD",
    "sg:tags":[
        "equipment",
        "treatment"
    ],
    "wof:name":"Aqua Dyne Australia Pty Ltd",
    "wof:placetype":"venue"
},
  "geometry": {"coordinates":[153.253616333,-27.7496623993],"type":"Point"}
}