{
  "type": "Feature",
  "properties": {
    "addr:full":"P O Box 6362 Parramatta Bus Centre 2150 Parramatta NSW 2124",
    "addr:housenumber":"2150",
    "addr:postcode":"2124",
    "iso:country":"AU",
    "sg:address":"P O Box 6362 Parramatta Bus Centre 2150",
    "sg:city":"Parramatta",
    "sg:classifiers":[
        {
            "category":"Education",
            "subcategory":"Dance Studio",
            "type":"Public Place"
        }
    ],
    "sg:phone":"+61 2 9683 4551",
    "sg:postcode":"2124",
    "sg:province":"NSW",
    "sg:tags":[
        "venue",
        "tuition"
    ],
    "wof:name":"Australian National Dance Association",
    "wof:placetype":"venue"
},
  "geometry": {"coordinates":[151.00668335,-33.81483078],"type":"Point"}
}