{
  "type": "Feature",
  "properties": {
    "addr:full":"48 MacAlister St Mackay QLD 4740",
    "addr:housenumber":"48",
    "addr:postcode":"4740",
    "addr:street":"Macalister St",
    "iso:country":"AU",
    "sg:address":"48 MacAlister St",
    "sg:city":"Mackay",
    "sg:classifiers":[
        {
            "category":"Personal",
            "subcategory":"Beauty Salon",
            "type":"Services"
        }
    ],
    "sg:phone":"+61 7 4953 2930",
    "sg:postcode":"4740",
    "sg:province":"QLD",
    "sg:tags":[
        "hairdresser"
    ],
    "wof:name":"Barbers On MacAlister St",
    "wof:placetype":"venue"
},
  "geometry": {"coordinates":[149.183044,-21.142338],"type":"Point"}
}