{
  "type": "Feature",
  "properties": {
    "iso:country":"AU",
    "sg:address":"Cnr Albert Rd & St Kilda Rd",
    "sg:city":"Melbourne",
    "sg:classifiers":[
        {
            "category":"Retail",
            "subcategory":"Event Space",
            "type":"Services"
        }
    ],
    "sg:phone":"+61 3 9820 5656",
    "sg:postcode":"3000",
    "sg:province":"VIC",
    "sg:tags":[
        "function",
        "organiser"
    ],
    "wof:name":"The Domain",
    "wof:placetype":"venue"
},
  "geometry": {"coordinates":[144.97198486299999,-37.8327522278],"type":"Point"}
}