{
  "type": "Feature",
  "properties": {
    "iso:country":"AU",
    "sg:address":"372 Reserve Rd",
    "sg:city":"Cheltenham",
    "sg:classifiers":[
        {
            "category":"Retail",
            "subcategory":"Auto Repair",
            "type":"Services"
        }
    ],
    "sg:phone":"+61 3 9583 0500",
    "sg:postcode":"3192",
    "sg:province":"VIC",
    "sg:tags":[
        "repairer",
        "motor",
        "engineer"
    ],
    "wof:name":"Cheltenham Service Centre Pty Ltd",
    "wof:placetype":"venue"
},
  "geometry": {"coordinates":[145.03863525400001,-37.9578933716],"type":"Point"}
}