{
  "type": "Feature",
  "properties": {
    "addr:full":"Captain Cook Drv Kurnell NSW 2231",
    "addr:postcode":"2231",
    "addr:street":"Captain Cook Drv",
    "iso:country":"AU",
    "sg:address":"Captain Cook Drv",
    "sg:city":"Kurnell",
    "sg:classifiers":[
        {
            "category":"Social Services",
            "subcategory":"Child Care",
            "type":"Services"
        }
    ],
    "sg:phone":"+61 2 9668 9119",
    "sg:postcode":"2231",
    "sg:province":"NSW",
    "sg:tags":[
        "support",
        "health"
    ],
    "wof:name":"Marton Community Hall",
    "wof:placetype":"venue"
},
  "geometry": {"coordinates":[151.21469116200001,-34.0098609924],"type":"Point"}
}