{
  "type": "Feature",
  "properties": {
    "iso:country":"AU",
    "sg:address":"42 Wickham St",
    "sg:city":"East Perth",
    "sg:classifiers":[
        {
            "category":"Professional",
            "subcategory":"Printing & Photocopies",
            "type":"Services"
        }
    ],
    "sg:phone":"+61 8 9221 1640",
    "sg:postcode":"6004",
    "sg:province":"WA",
    "sg:tags":[
        "plaque"
    ],
    "wof:name":"Plaque Enterprises",
    "wof:placetype":"venue"
},
  "geometry": {"coordinates":[115.876731873,-31.9548492432],"type":"Point"}
}