{
  "type": "Feature",
  "properties": {
    "addr:full":"4 Homan Crt Warrandyte VIC 3113",
    "addr:housenumber":"4",
    "addr:postcode":"3113",
    "addr:street":"Homan Crt",
    "iso:country":"AU",
    "sg:address":"4 Homan Crt",
    "sg:city":"Warrandyte",
    "sg:classifiers":[
        {
            "category":"Building & Trades",
            "subcategory":"Plumbing",
            "type":"Services"
        }
    ],
    "sg:phone":"+61 3 9844 2868",
    "sg:postcode":"3113",
    "sg:province":"VIC",
    "sg:tags":[
        "plumber",
        "gasfitters"
    ],
    "wof:name":"Aquaworks Plumbing Pty Ltd",
    "wof:placetype":"venue"
},
  "geometry": {"coordinates":[145.237915039,-37.7702865601],"type":"Point"}
}