{
  "type": "Feature",
  "properties": {
    "iso:country":"AU",
    "sg:address":"2 Fetherstone St",
    "sg:city":"Bankstown",
    "sg:classifiers":[
        {
            "category":"Government",
            "subcategory":"Court House",
            "type":"Public Place"
        }
    ],
    "sg:phone":"+61 2 9793 1500",
    "sg:postcode":"2200",
    "sg:province":"NSW",
    "sg:tags":[
        "personal",
        "marriage",
        "family",
        "counselling"
    ],
    "wof:name":"Social Work Assessment Team",
    "wof:placetype":"venue"
},
  "geometry": {"coordinates":[151.034042,-33.917274],"type":"Point"}
}