{
  "type": "Feature",
  "properties": {
    "addr:full":"Cnr Buckley & Russell Sts Essendon VIC 3040",
    "addr:postcode":"3040",
    "addr:street":"Cnr",
    "iso:country":"AU",
    "sg:address":"Cnr Buckley & Russell Sts",
    "sg:city":"Essendon",
    "sg:classifiers":[
        {
            "category":"Shopping",
            "subcategory":"Clothing, Apparel, & Fashions",
            "type":"Retail Goods"
        }
    ],
    "sg:phone":"+61 3 9370 7769",
    "sg:postcode":"3040",
    "sg:province":"VIC",
    "sg:tags":[
        "uniform"
    ],
    "wof:name":"Buckleys Store",
    "wof:placetype":"venue"
},
  "geometry": {"coordinates":[144.908737183,-37.7560958862],"type":"Point"}
}