{
  "type": "Feature",
  "properties": {
    "addr:full":"Cowwarr Weir Rd Toongabbie VIC 3856",
    "addr:postcode":"3856",
    "addr:street":"Weir Rd",
    "iso:country":"AU",
    "sg:address":"Cowwarr Weir Rd",
    "sg:city":"Toongabbie",
    "sg:classifiers":[
        {
            "category":"Manufacturing",
            "subcategory":"Pottery",
            "type":"Manufacturing & Wholesale Goods"
        }
    ],
    "sg:phone":"+61 3 5192 4598",
    "sg:postcode":"3856",
    "sg:province":"VIC",
    "wof:name":"Toongabbie Pottery",
    "wof:placetype":"venue"
},
  "geometry": {"coordinates":[146.500396728,-38.0080718994],"type":"Point"}
}