{
  "type": "Feature",
  "properties": {
    "addr:full":"44 Begonia St Inala QLD 4077",
    "addr:housenumber":"44",
    "addr:postcode":"4077",
    "addr:street":"Begonia St",
    "iso:country":"AU",
    "sg:address":"44 Begonia St",
    "sg:city":"Inala",
    "sg:classifiers":[
        {
            "category":"Food & Beverages",
            "subcategory":"Supermarket",
            "type":"Retail Goods"
        }
    ],
    "sg:phone":"+61 7 3372 5233",
    "sg:postcode":"4077",
    "sg:province":"QLD",
    "sg:tags":[
        "grocery",
        "store"
    ],
    "wof:name":"Sunway Convenient Store",
    "wof:placetype":"venue"
},
  "geometry": {"coordinates":[152.97171020499999,-27.5798454285],"type":"Point"}
}