{
  "type": "Feature",
  "properties": {
    "addr:full":"Menindee St Menindee NSW 2879",
    "addr:postcode":"2879",
    "addr:street":"Menindee St",
    "iso:country":"AU",
    "sg:address":"Menindee St",
    "sg:city":"Menindee",
    "sg:classifiers":[
        {
            "category":"Travel",
            "subcategory":"Hotels & Motels",
            "type":"Entertainment"
        }
    ],
    "sg:phone":"+61 8 8091 4212",
    "sg:postcode":"2879",
    "sg:province":"NSW",
    "sg:tags":[
        "accommodation"
    ],
    "wof:name":"Albemarle Hotel",
    "wof:placetype":"venue"
},
  "geometry": {"coordinates":[142.41665599999999,-32.392796],"type":"Point"}
}