{
  "type": "Feature",
  "properties": {
    "addr:full":"70 Jacaranda Pl Coogee NSW 2034",
    "addr:housenumber":"70",
    "addr:postcode":"2034",
    "addr:street":"Jacaranda Pl",
    "iso:country":"AU",
    "sg:address":"70 Jacaranda Pl",
    "sg:city":"Coogee",
    "sg:classifiers":[
        {
            "category":"Health Services",
            "subcategory":"Health Practitioner",
            "type":"Services"
        }
    ],
    "sg:phone":"+61 2 9314 3893",
    "sg:postcode":"2034",
    "sg:province":"NSW",
    "sg:tags":[
        "alternative"
    ],
    "wof:name":"Coogee Remedial Therapies",
    "wof:placetype":"venue"
},
  "geometry": {"coordinates":[151.25267028799999,-33.9320793152],"type":"Point"}
}