{
  "type": "Feature",
  "properties": {
    "addr:full":"6 Cowper St Nabiac NSW 2312",
    "addr:housenumber":"6",
    "addr:postcode":"2312",
    "addr:street":"Cowper St",
    "iso:country":"AU",
    "sg:address":"6 Cowper St",
    "sg:city":"Nabiac",
    "sg:classifiers":[
        {
            "category":"Wholesale",
            "subcategory":"Scrap",
            "type":"Manufacturing & Wholesale Goods"
        }
    ],
    "sg:phone":"+61 417 203 591",
    "sg:postcode":"2312",
    "sg:province":"NSW",
    "sg:tags":[
        "merchant",
        "metal"
    ],
    "wof:name":"Minidigs",
    "wof:placetype":"venue"
},
  "geometry": {"coordinates":[152.384445,-32.099052],"type":"Point"}
}