{
  "type": "Feature",
  "properties": {
    "addr:full":"Shops 5A & 5B, 127 Macquarie Rd Springwood NSW 2777",
    "addr:housenumber":"5a & 5b 127",
    "addr:postcode":"2777",
    "addr:street":"Macquarie Rd",
    "iso:country":"AU",
    "sg:address":"Shops 5A & 5B, 127 Macquarie Rd",
    "sg:city":"Springwood",
    "sg:classifiers":[
        {
            "category":"Professional",
            "subcategory":"Accounting & Tax Preparation",
            "type":"Services"
        }
    ],
    "sg:phone":"+61 2 4751 9199",
    "sg:postcode":"2777",
    "sg:province":"NSW",
    "sg:tags":[
        "consultant",
        "taxation"
    ],
    "wof:name":"H&R Block",
    "wof:placetype":"venue"
},
  "geometry": {"coordinates":[150.56739807100001,-33.6989402771],"type":"Point"}
}