{
  "type": "Feature",
  "properties": {
    "addr:full":"Unit 14-15, 108 Old Pittwater Rd Brookvale NSW 2100",
    "addr:housenumber":"108",
    "addr:postcode":"2100",
    "addr:street":"Old Pittwater Rd",
    "iso:country":"AU",
    "sg:address":"Unit 14-15, 108 Old Pittwater Rd",
    "sg:city":"Brookvale",
    "sg:classifiers":[
        {
            "category":"Retail",
            "subcategory":"Auto Repair",
            "type":"Services"
        }
    ],
    "sg:phone":"+61 2 9905 5186",
    "sg:postcode":"2100",
    "sg:province":"NSW",
    "sg:tags":[
        "repairer",
        "motor",
        "engineer"
    ],
    "wof:name":"Berriman Frank G.",
    "wof:placetype":"venue"
},
  "geometry": {"coordinates":[151.261795044,-33.764541626],"type":"Point"}
}