{
  "type": "Feature",
  "properties": {
    "addr:full":"Level 1, 3 Bennett St East Perth WA 6004",
    "addr:housenumber":"3",
    "addr:postcode":"6004",
    "addr:street":"Bennett St East",
    "iso:country":"AU",
    "sg:address":"Level 1, 3 Bennett St",
    "sg:city":"East Perth",
    "sg:classifiers":[
        {
            "category":"Education",
            "subcategory":"University",
            "type":"Public Place"
        }
    ],
    "sg:phone":"+61 8 9325 4533",
    "sg:postcode":"6004",
    "sg:province":"WA",
    "sg:tags":[
        "college",
        "tertiary"
    ],
    "wof:name":"SAE College",
    "wof:placetype":"venue"
},
  "geometry": {"coordinates":[115.87409210200001,-31.9531421661],"type":"Point"}
}