{
  "type": "Feature",
  "properties": {
    "iso:country":"AU",
    "sg:address":"Amity House 101 Welsby St",
    "sg:city":"New Farm",
    "sg:classifiers":[
        {
            "category":"Real Estate",
            "subcategory":"Architect",
            "type":"Services"
        }
    ],
    "sg:phone":"+61 418 888 500",
    "sg:postcode":"4005",
    "sg:province":"QLD",
    "wof:name":"Dempseys Architects Pty Ltd",
    "wof:placetype":"venue"
},
  "geometry": {"coordinates":[153.05081176799999,-27.4642276764],"type":"Point"}
}