{
  "type": "Feature",
  "properties": {
    "addr:full":"Lot 1 Hassell Hwy King River WA 6330",
    "addr:postcode":"6330",
    "addr:street":"Hassell Hwy",
    "iso:country":"AU",
    "sg:address":"Lot 1 Hassell Hwy",
    "sg:city":"King River",
    "sg:classifiers":[
        {
            "category":"Restaurant",
            "type":"Food & Drink"
        }
    ],
    "sg:phone":"+61 8 9844 3340",
    "sg:postcode":"6330",
    "sg:province":"WA",
    "sg:tags":[
        "roadhouse"
    ],
    "wof:name":"Bakers Junction Road House",
    "wof:placetype":"venue"
},
  "geometry": {"coordinates":[117.730308533,-35.007938385],"type":"Point"}
}