{
  "type": "Feature",
  "properties": {
    "addr:full":"Suite 7 21 Wanneroo Rd Joondanna WA 6060",
    "addr:housenumber":"21",
    "addr:postcode":"6060",
    "addr:street":"Wanneroo Rd",
    "iso:country":"AU",
    "sg:address":"Suite 7 21 Wanneroo Rd",
    "sg:city":"Joondanna",
    "sg:classifiers":[
        {
            "category":"Retail",
            "subcategory":"Auto Repair",
            "type":"Services"
        }
    ],
    "sg:phone":"+61 8 9444 3188",
    "sg:postcode":"6060",
    "sg:province":"WA",
    "sg:tags":[
        "sport",
        "motor"
    ],
    "wof:name":"CAMS- Confederation of Australian Motor Sport Ltd",
    "wof:placetype":"venue"
},
  "geometry": {"coordinates":[115.84455871599999,-31.9080581665],"type":"Point"}
}