{
  "type": "Feature",
  "properties": {
    "addr:full":"10 Morecambe Crt Templestowe VIC 3106",
    "addr:housenumber":"10",
    "addr:postcode":"3106",
    "addr:street":"Morecambe Crt",
    "iso:country":"AU",
    "sg:address":"10 Morecambe Crt",
    "sg:city":"Templestowe",
    "sg:classifiers":[
        {
            "category":"Wholesale",
            "subcategory":"Machinery & Supplies",
            "type":"Manufacturing & Wholesale Goods"
        }
    ],
    "sg:phone":"+61 3 9846 1863",
    "sg:postcode":"3106",
    "sg:province":"VIC",
    "wof:name":"Colbern Agricultural Machinery",
    "wof:placetype":"venue"
},
  "geometry": {"coordinates":[145.13340759299999,-37.7544403076],"type":"Point"}
}