{
  "type": "Feature",
  "properties": {
    "iso:country":"AU",
    "sg:address":"2 Pickwick St",
    "sg:city":"Cannon Hill",
    "sg:classifiers":[
        {
            "category":"Retail",
            "subcategory":"Auto Repair",
            "type":"Services"
        }
    ],
    "sg:phone":"+61 7 3395 9100",
    "sg:postcode":"4170",
    "sg:province":"QLD",
    "sg:tags":[
        "repairer",
        "motor",
        "engineer"
    ],
    "wof:name":"Autocare Workshops",
    "wof:placetype":"venue"
},
  "geometry": {"coordinates":[153.09564209000001,-27.4709682465],"type":"Point"}
}