{
  "type": "Feature",
  "properties": {
    "addr:full":"906- 908 Doncaster Rd Doncaster East VIC 3109",
    "addr:housenumber":"908",
    "addr:postcode":"3109",
    "addr:street":"Doncaster Rd",
    "iso:country":"AU",
    "sg:address":"906- 908 Doncaster Rd",
    "sg:city":"Doncaster East",
    "sg:classifiers":[
        {
            "category":"Real Estate",
            "subcategory":"Real Estate Agent",
            "type":"Services"
        }
    ],
    "sg:phone":"+61 3 9840 1111",
    "sg:postcode":"3109",
    "sg:province":"VIC",
    "wof:name":"Parkes Property Group Pty Ltd",
    "wof:placetype":"venue"
},
  "geometry": {"coordinates":[145.149993897,-37.787902832],"type":"Point"}
}