{
  "type": "Feature",
  "properties": {
    "iso:country":"AU",
    "sg:address":"471 Glenferrie Rd",
    "sg:city":"Kooyong",
    "sg:classifiers":[
        {
            "category":"Health Services",
            "subcategory":"Dentist",
            "type":"Services"
        }
    ],
    "sg:phone":"+61 1300 661 158",
    "sg:postcode":"3144",
    "sg:province":"VIC",
    "wof:name":"A Whiter Smiley",
    "wof:placetype":"venue"
},
  "geometry": {"coordinates":[145.031982422,-37.8403091431],"type":"Point"}
}