{
  "type": "Feature",
  "properties": {
    "addr:full":"9 Pearce Rd Kanwal NSW 2259",
    "addr:housenumber":"9",
    "addr:postcode":"2259",
    "addr:street":"Pearce Rd",
    "iso:country":"AU",
    "sg:address":"9 Pearce Rd",
    "sg:city":"Kanwal",
    "sg:classifiers":[
        {
            "category":"Building & Trades",
            "subcategory":"Construction",
            "type":"Services"
        }
    ],
    "sg:phone":"+61 408 116 681",
    "sg:postcode":"2259",
    "sg:province":"NSW",
    "sg:tags":[
        "earth",
        "excavating",
        "moving",
        "contractor"
    ],
    "wof:name":"Harris Steven",
    "wof:placetype":"venue"
},
  "geometry": {"coordinates":[151.48190307600001,-33.2677192688],"type":"Point"}
}