{
  "type": "Feature",
  "properties": {
    "iso:country":"AU",
    "sg:address":"171 St Pauls Tce",
    "sg:city":"Fortitude Valley",
    "sg:classifiers":[
        {
            "category":"Travel",
            "subcategory":"Hostel",
            "type":"Entertainment"
        }
    ],
    "sg:phone":"+61 7 3835 8100",
    "sg:postcode":"4006",
    "sg:province":"QLD",
    "sg:tags":[
        "home"
    ],
    "wof:name":"Villa Maria Centre",
    "wof:placetype":"venue"
},
  "geometry": {"coordinates":[153.029495239,-27.4583835602],"type":"Point"}
}