{
  "type": "Feature",
  "properties": {
    "iso:country":"AU",
    "sg:address":"509 Main Rd",
    "sg:city":"Ballarat",
    "sg:classifiers":[
        {
            "category":"Food & Beverages",
            "subcategory":"Bakery",
            "type":"Retail Goods"
        }
    ],
    "sg:phone":"+61 3 5332 4415",
    "sg:postcode":"3350",
    "sg:province":"VIC",
    "sg:tags":[
        "cake",
        "shop",
        "pastry"
    ],
    "wof:name":"Peter Pope's Pies",
    "wof:placetype":"venue"
},
  "geometry": {"coordinates":[143.868729,-37.576084],"type":"Point"}
}