{
  "type": "Feature",
  "properties": {
    "iso:country":"AU",
    "sg:address":"60 Jijaws St",
    "sg:city":"Sumner Park",
    "sg:classifiers":[
        {
            "category":"Banks & Credit Unions",
            "subcategory":"Financial Services",
            "type":"Services"
        }
    ],
    "sg:phone":"+61 7 3376 0111",
    "sg:postcode":"4074",
    "sg:province":"QLD",
    "sg:tags":[
        "wholesaler",
        "mfrs",
        "gear"
    ],
    "wof:name":"Gear Concern",
    "wof:placetype":"venue"
},
  "geometry": {"coordinates":[152.93856811500001,-27.5616340637],"type":"Point"}
}