{
  "type": "Feature",
  "properties": {
    "iso:country":"AU",
    "sg:address":"3 Adina Crt",
    "sg:city":"Tullamarine",
    "sg:classifiers":[
        {
            "category":"Home & Garden",
            "subcategory":"Furniture",
            "type":"Retail Goods"
        }
    ],
    "sg:phone":"+61 3 9335 2177",
    "sg:postcode":"3043",
    "sg:province":"VIC",
    "sg:tags":[
        "business"
    ],
    "wof:name":"Vinfra Office Furniture (Aust) Pty Ltd",
    "wof:placetype":"venue"
},
  "geometry": {"coordinates":[144.87640380900001,-37.711315155],"type":"Point"}
}