{
  "type": "Feature",
  "properties": {
    "addr:full":"12 Salerno Pl St Ives NSW 2075",
    "addr:housenumber":"12",
    "addr:postcode":"2075",
    "addr:street":"Salerno Pl",
    "iso:country":"AU",
    "sg:address":"12 Salerno Pl",
    "sg:city":"St Ives",
    "sg:classifiers":[
        {
            "category":"Professional",
            "subcategory":"Management & Consulting",
            "type":"Services"
        }
    ],
    "sg:phone":"+61 2 9983 0861",
    "sg:postcode":"2075",
    "sg:province":"NSW",
    "sg:tags":[
        "consultant"
    ],
    "wof:name":"Raspass Consultancy The",
    "wof:placetype":"venue"
},
  "geometry": {"coordinates":[151.157745361,-33.7134552002],"type":"Point"}
}