{
  "type": "Feature",
  "properties": {
    "addr:full":"7 Louis St Granville NSW 2142",
    "addr:housenumber":"7",
    "addr:postcode":"2142",
    "addr:street":"Louis St",
    "iso:country":"AU",
    "sg:address":"7 Louis St",
    "sg:city":"Granville",
    "sg:classifiers":[
        {
            "category":"Professional",
            "subcategory":"Accounting & Tax Preparation",
            "type":"Services"
        }
    ],
    "sg:phone":"+61 2 9682 7968",
    "sg:postcode":"2142",
    "sg:province":"NSW",
    "sg:tags":[
        "accountant",
        "auditor"
    ],
    "wof:name":"T Taktak & Associates",
    "wof:placetype":"venue"
},
  "geometry": {"coordinates":[151.009933472,-33.8411560059],"type":"Point"}
}