{
  "type": "Feature",
  "properties": {
    "iso:country":"AU",
    "sg:address":"147 Bathurst St",
    "sg:city":"Hobart",
    "sg:classifiers":[
        {
            "category":"Education",
            "subcategory":"School",
            "type":"Public Place"
        }
    ],
    "sg:phone":"+61 3 6234 2122",
    "sg:postcode":"7000",
    "sg:province":"TAS",
    "sg:tags":[
        "supply"
    ],
    "wof:name":"Birchalls",
    "wof:placetype":"venue"
},
  "geometry": {"coordinates":[147.322509766,-42.8829727173],"type":"Point"}
}