{
  "type": "Feature",
  "properties": {
    "addr:full":"Suite 3/ 4 Wisteria Pde Edgewater WA 6027",
    "addr:housenumber":"4",
    "addr:postcode":"6027",
    "addr:street":"Wisteria Pde",
    "iso:country":"AU",
    "sg:address":"Suite 3/ 4 Wisteria Pde",
    "sg:city":"Edgewater",
    "sg:classifiers":[
        {
            "category":"Health Services",
            "subcategory":"Doctor",
            "type":"Services"
        }
    ],
    "sg:phone":"+61 8 9306 1899",
    "sg:postcode":"6027",
    "sg:province":"WA",
    "sg:tags":[
        "medical",
        "practitioner"
    ],
    "wof:name":"Hernaman Peter",
    "wof:placetype":"venue"
},
  "geometry": {"coordinates":[115.78904724100001,-31.772146225],"type":"Point"}
}