{
  "type": "Feature",
  "properties": {
    "iso:country":"AU",
    "sg:address":"Suite 1",
    "sg:city":"Level 1 Harrington Plaza Harrington Park",
    "sg:classifiers":[
        {
            "category":"Health Services",
            "subcategory":"Health Practitioner",
            "type":"Services"
        }
    ],
    "sg:phone":"+61 2 4648 4200",
    "sg:postcode":"2567",
    "sg:province":"NSW",
    "sg:tags":[
        "bowen",
        "therapy"
    ],
    "wof:name":"Bowen At Smile Within",
    "wof:placetype":"venue"
},
  "geometry": {"coordinates":[150.73606872600001,-34.0287590027],"type":"Point"}
}