{
  "type": "Feature",
  "properties": {
    "iso:country":"AU",
    "sg:address":"Shop 2 171 Abernethy Rd",
    "sg:city":"Belmont",
    "sg:classifiers":[
        {
            "category":"Shopping",
            "subcategory":"Pawn Shop",
            "type":"Retail Goods"
        }
    ],
    "sg:phone":"+61 8 9475 0500",
    "sg:postcode":"6104",
    "sg:province":"WA",
    "sg:tags":[
        "pawnbroker"
    ],
    "wof:name":"Cash City Belmont",
    "wof:placetype":"venue"
},
  "geometry": {"coordinates":[115.92890930199999,-31.9559326172],"type":"Point"}
}