{
  "type": "Feature",
  "properties": {
    "addr:full":"21 Roger Crs Mt Riverview NSW 2774",
    "addr:housenumber":"21",
    "addr:postcode":"2774",
    "addr:street":"Roger Crs Mt",
    "iso:country":"AU",
    "sg:address":"21 Roger Crs",
    "sg:city":"Mt Riverview",
    "sg:classifiers":[
        {
            "category":"Building & Trades",
            "subcategory":"Landscaping Services",
            "type":"Services"
        }
    ],
    "sg:phone":"+61 2 4739 1588",
    "sg:postcode":"2774",
    "sg:province":"NSW",
    "sg:tags":[
        "stump",
        "tree",
        "felling",
        "removal"
    ],
    "wof:name":"Blue Mountains Area Tree Lopping Pty Ltd",
    "wof:placetype":"venue"
},
  "geometry": {"coordinates":[150.63380432100001,-33.729549408],"type":"Point"}
}