{
  "type": "Feature",
  "properties": {
    "addr:full":"415A Albany Hwy Victoria Park WA 6100",
    "addr:housenumber":"415a",
    "addr:postcode":"6100",
    "addr:street":"Albany Hwy Victoria",
    "iso:country":"AU",
    "sg:address":"415A Albany Hwy",
    "sg:city":"Victoria Park",
    "sg:classifiers":[
        {
            "category":"Arts & Performance",
            "subcategory":"Music",
            "type":"Entertainment"
        }
    ],
    "sg:phone":"+61 8 9472 4444",
    "sg:postcode":"6100",
    "sg:province":"WA",
    "sg:tags":[
        "mobile",
        "jockey",
        "disc"
    ],
    "wof:name":"A Bit Of Class",
    "wof:placetype":"venue"
},
  "geometry": {"coordinates":[115.897506714,-31.9748935699],"type":"Point"}
}