{
  "type": "Feature",
  "properties": {
    "iso:country":"AU",
    "sg:address":"Factory 4, 6 Pendrey Crt",
    "sg:city":"Woodridge",
    "sg:classifiers":[
        {
            "category":"Wholesale",
            "subcategory":"Furniture",
            "type":"Manufacturing & Wholesale Goods"
        }
    ],
    "sg:phone":"+61 7 3808 7483",
    "sg:postcode":"4114",
    "sg:province":"QLD",
    "sg:tags":[
        "wholesaler",
        "mfrs"
    ],
    "wof:name":"Yolanda Designs",
    "wof:placetype":"venue"
},
  "geometry": {"coordinates":[153.11390685999999,-27.6207065582],"type":"Point"}
}