{
  "type": "Feature",
  "properties": {
    "addr:full":"1445 Main North Rd Para Hills West SA 5096",
    "addr:housenumber":"1445",
    "addr:postcode":"5096",
    "addr:street":"Main North Rd Para Hills West",
    "iso:country":"AU",
    "sg:address":"1445 Main North Rd",
    "sg:city":"Para Hills West",
    "sg:classifiers":[
        {
            "category":"Wholesale",
            "subcategory":"Machinery & Supplies",
            "type":"Manufacturing & Wholesale Goods"
        }
    ],
    "sg:phone":"+61 8 8258 2955",
    "sg:postcode":"5096",
    "sg:province":"SA",
    "sg:tags":[
        "bearing",
        "bushing"
    ],
    "wof:name":"Consolidated Bearing Co (S.A.) Pty Ltd",
    "wof:placetype":"venue"
},
  "geometry": {"coordinates":[138.64579773,-34.7936439514],"type":"Point"}
}