{
  "type": "Feature",
  "properties": {
    "iso:country":"AU",
    "sg:address":"8/385- 389 Pacific Hwy",
    "sg:city":"Crows Nest",
    "sg:classifiers":[
        {
            "category":"Retail",
            "subcategory":"Funeral Services",
            "type":"Services"
        }
    ],
    "sg:phone":"+61 2 9955 6121",
    "sg:postcode":"2065",
    "sg:province":"NSW",
    "sg:tags":[
        "director"
    ],
    "wof:name":"Guardian Funerals",
    "wof:placetype":"venue"
},
  "geometry": {"coordinates":[151.198654175,-33.8252677917],"type":"Point"}
}