{
  "type": "Feature",
  "properties": {
    "iso:country":"AU",
    "sg:address":"Factory 1, 18 Deblin Drv",
    "sg:city":"Narre Warren",
    "sg:classifiers":[
        {
            "category":"Retail",
            "subcategory":"Auto Repair",
            "type":"Services"
        }
    ],
    "sg:phone":"+61 412 852 292",
    "sg:postcode":"3805",
    "sg:province":"VIC",
    "sg:tags":[
        "camper-trailers",
        "caravan",
        "servicing"
    ],
    "wof:name":"Advance Camper & Caravan Repairs",
    "wof:placetype":"venue"
},
  "geometry": {"coordinates":[145.30041499999999,-38.026783],"type":"Point"}
}