{
  "type": "Feature",
  "properties": {
    "addr:full":"466 Brighton Rd Brighton SA 5048",
    "addr:housenumber":"466",
    "addr:postcode":"5048",
    "addr:street":"Brighton Rd",
    "iso:country":"AU",
    "sg:address":"466 Brighton Rd",
    "sg:city":"Brighton",
    "sg:classifiers":[
        {
            "category":"Travel",
            "subcategory":"Hotels & Motels",
            "type":"Entertainment"
        }
    ],
    "sg:phone":"+61 8 8358 3288",
    "sg:postcode":"5048",
    "sg:province":"SA",
    "sg:tags":[
        "accommodation"
    ],
    "wof:name":"Brighton Metro Hotel",
    "wof:placetype":"venue"
},
  "geometry": {"coordinates":[138.52328499999999,-35.018757],"type":"Point"}
}