{
  "type": "Feature",
  "properties": {
    "iso:country":"AU",
    "sg:address":"Level 1/ 121 Wharf St",
    "sg:city":"Spring Hill",
    "sg:classifiers":[
        {
            "category":"Organizations",
            "subcategory":"Community Association",
            "type":"Services"
        }
    ],
    "sg:phone":"+61 7 3016 1800",
    "sg:postcode":"4000",
    "sg:province":"QLD",
    "sg:tags":[
        "organisation",
        "family",
        "welfare"
    ],
    "wof:name":"Muscular Dystrophy Association Of Queensland Inc",
    "wof:placetype":"venue"
},
  "geometry": {"coordinates":[153.02801513700001,-27.4631462097],"type":"Point"}
}