{
  "type": "Feature",
  "properties": {
    "addr:full":"202 Hay St Subiaco WA 6008",
    "addr:housenumber":"202",
    "addr:postcode":"6008",
    "addr:street":"Hay St",
    "iso:country":"AU",
    "sg:address":"202 Hay St",
    "sg:city":"Subiaco",
    "sg:classifiers":[
        {
            "category":"Shopping",
            "subcategory":"Gifts & Souvenirs",
            "type":"Retail Goods"
        }
    ],
    "sg:phone":"+61 8 9381 2511",
    "sg:postcode":"6008",
    "sg:province":"WA",
    "sg:tags":[
        "print",
        "poster",
        "pictures"
    ],
    "wof:name":"Art Heritage",
    "wof:placetype":"venue"
},
  "geometry": {"coordinates":[115.831672669,-31.9469337463],"type":"Point"}
}