{
  "type": "Feature",
  "properties": {
    "addr:full":"231 Hutt St Adelaide SA 5000",
    "addr:housenumber":"231",
    "addr:postcode":"5000",
    "addr:street":"Hutt St",
    "iso:country":"AU",
    "sg:address":"231 Hutt St",
    "sg:city":"Adelaide",
    "sg:classifiers":[
        {
            "category":"Personal",
            "type":"Services"
        }
    ],
    "sg:phone":"+61 8 8232 2321",
    "sg:postcode":"5000",
    "sg:province":"SA",
    "sg:tags":[
        "gift"
    ],
    "sg:website":"http://www.executiveflowers.com.au",
    "wof:name":"Executive Gifts",
    "wof:placetype":"venue"
},
  "geometry": {"coordinates":[138.6121521,-34.9334259033],"type":"Point"}
}