{
  "type": "Feature",
  "properties": {
    "addr:full":"1754 Albany Hwy Kenwick WA 6107",
    "addr:housenumber":"1754",
    "addr:postcode":"6107",
    "addr:street":"Albany Hwy",
    "iso:country":"AU",
    "sg:address":"1754 Albany Hwy",
    "sg:city":"Kenwick",
    "sg:classifiers":[
        {
            "category":"Building & Trades",
            "subcategory":"Construction",
            "type":"Services"
        }
    ],
    "sg:phone":"+61 8 9493 2022",
    "sg:postcode":"6107",
    "sg:province":"WA",
    "sg:tags":[
        "pool",
        "swimming"
    ],
    "wof:name":"Sapphire Pools",
    "wof:placetype":"venue"
},
  "geometry": {"coordinates":[115.972091675,-32.0414657593],"type":"Point"}
}