{
  "type": "Feature",
  "properties": {
    "iso:country":"AU",
    "sg:address":"89 McDowall St",
    "sg:city":"Roma",
    "sg:classifiers":[
        {
            "category":"Banks & Credit Unions",
            "subcategory":"Bureau De Change",
            "type":"Services"
        }
    ],
    "sg:phone":"+61 7 4622 1744",
    "sg:postcode":"4455",
    "sg:province":"QLD",
    "sg:tags":[
        "repairs",
        "part",
        "appliance",
        "electrical"
    ],
    "wof:name":"Dore's Elect-Air Pty Ltd",
    "wof:placetype":"venue"
},
  "geometry": {"coordinates":[148.78855895999999,-26.5713653564],"type":"Point"}
}