{
  "type": "Feature",
  "properties": {
    "addr:full":"Penrith Showground Station St Penrith NSW 2750",
    "addr:postcode":"2750",
    "addr:street":"Station St",
    "iso:country":"AU",
    "sg:address":"Penrith Showground Station St",
    "sg:city":"Penrith",
    "sg:classifiers":[
        {
            "category":"Arena",
            "subcategory":"Sports Club",
            "type":"Entertainment"
        }
    ],
    "sg:phone":"+61 2 4721 2375",
    "sg:postcode":"2750",
    "sg:province":"NSW",
    "sg:tags":[
        "hunt",
        "racing"
    ],
    "wof:name":"Penrith Paceway",
    "wof:placetype":"venue"
},
  "geometry": {"coordinates":[150.673065186,-33.7462005615],"type":"Point"}
}