{
  "type": "Feature",
  "properties": {
    "iso:country":"AU",
    "sg:address":"4 Brunsdon St",
    "sg:city":"Bayswater",
    "sg:classifiers":[
        {
            "category":"Professional",
            "subcategory":"Art Services",
            "type":"Services"
        }
    ],
    "sg:phone":"+61 3 9720 3322",
    "sg:postcode":"3153",
    "sg:province":"VIC",
    "sg:tags":[
        "picture",
        "frame",
        "framing"
    ],
    "wof:name":"National Art Materials Pty Ltd",
    "wof:placetype":"venue"
},
  "geometry": {"coordinates":[145.276580811,-37.8477325439],"type":"Point"}
}