{
  "type": "Feature",
  "properties": {
    "addr:full":"11 Tamboura Crt The Gap QLD 4061",
    "addr:housenumber":"11",
    "addr:postcode":"4061",
    "addr:street":"Tamboura Crt",
    "iso:country":"AU",
    "sg:address":"11 Tamboura Crt",
    "sg:city":"The Gap",
    "sg:classifiers":[
        {
            "category":"Real Estate",
            "subcategory":"Architect",
            "type":"Services"
        }
    ],
    "sg:phone":"+61 7 3300 2021",
    "sg:postcode":"4061",
    "sg:province":"QLD",
    "sg:tags":[
        "building",
        "designer"
    ],
    "wof:name":"Mechielsen L C & Co Pty Ltd",
    "wof:placetype":"venue"
},
  "geometry": {"coordinates":[152.944656372,-27.4360427856],"type":"Point"}
}