{
  "type": "Feature",
  "properties": {
    "addr:full":"44 Walton St Blakehurst NSW 2221",
    "addr:housenumber":"44",
    "addr:postcode":"2221",
    "addr:street":"Walton St",
    "iso:country":"AU",
    "sg:address":"44 Walton St",
    "sg:city":"Blakehurst",
    "sg:classifiers":[
        {
            "category":"Professional",
            "subcategory":"Computer Services",
            "type":"Services"
        }
    ],
    "sg:phone":"+61 2 9546 1729",
    "sg:postcode":"2221",
    "sg:province":"NSW",
    "sg:tags":[
        "consultant",
        "system"
    ],
    "wof:name":"Meridian Consulting Services Pty Ltd",
    "wof:placetype":"venue"
},
  "geometry": {"coordinates":[151.10598754899999,-33.9852790833],"type":"Point"}
}