{
  "type": "Feature",
  "properties": {
    "iso:country":"AU",
    "sg:address":"32 Meninya St",
    "sg:city":"Moama",
    "sg:classifiers":[
        {
            "category":"Building & Trades",
            "subcategory":"Construction",
            "type":"Services"
        }
    ],
    "sg:phone":"+61 3 5482 1380",
    "sg:postcode":"2731",
    "sg:province":"NSW",
    "sg:tags":[
        "home",
        "air conditioning"
    ],
    "wof:name":"Moama Electrical Service",
    "wof:placetype":"venue"
},
  "geometry": {"coordinates":[144.754623,-36.111275],"type":"Point"}
}