{
  "type": "Feature",
  "properties": {
    "addr:full":"135 Cobra St Dubbo NSW 2830",
    "addr:housenumber":"135",
    "addr:postcode":"2830",
    "addr:street":"Cobra St",
    "iso:country":"AU",
    "sg:address":"135 Cobra St",
    "sg:city":"Dubbo",
    "sg:classifiers":[
        {
            "category":"Health Services",
            "subcategory":"Health Practitioner",
            "type":"Services"
        }
    ],
    "sg:phone":"+61 2 6885 3177",
    "sg:postcode":"2830",
    "sg:province":"NSW",
    "sg:tags":[
        "psychologist"
    ],
    "wof:name":"Michelle Clarke",
    "wof:placetype":"venue"
},
  "geometry": {"coordinates":[148.61293029800001,-32.2549514771],"type":"Point"}
}