{
  "type": "Feature",
  "properties": {
    "iso:country":"AU",
    "sg:address":"213 Crawford St",
    "sg:city":"Queanbeyan",
    "sg:classifiers":[
        {
            "category":"Health Services",
            "subcategory":"Dentist",
            "type":"Services"
        }
    ],
    "sg:phone":"+61 2 6299 4812",
    "sg:postcode":"2620",
    "sg:province":"ACT",
    "wof:name":"Fricker Dr John P",
    "wof:placetype":"venue"
},
  "geometry": {"coordinates":[149.23379516599999,-35.3527984619],"type":"Point"}
}