{
  "type": "Feature",
  "properties": {
    "addr:full":"246 Adelaide Tce Perth WA 6000",
    "addr:housenumber":"246",
    "addr:postcode":"6000",
    "addr:street":"Adelaide Tce",
    "iso:country":"AU",
    "sg:address":"246 Adelaide Tce",
    "sg:city":"Perth",
    "sg:classifiers":[
        {
            "category":"Banks & Credit Unions",
            "subcategory":"Financial Services",
            "type":"Services"
        }
    ],
    "sg:phone":"+61 13 25 77",
    "sg:postcode":"6000",
    "sg:province":"WA",
    "sg:tags":[
        "planning"
    ],
    "wof:name":"Police & Nurses Credit Society",
    "wof:placetype":"venue"
},
  "geometry": {"coordinates":[115.866523743,-31.9579029083],"type":"Point"}
}