{
  "type": "Feature",
  "properties": {
    "addr:full":"Shop 4 Deepwater Plaza Woy Woy NSW 2256",
    "addr:housenumber":"shop 4",
    "addr:postcode":"2256",
    "addr:street":"Deepwater Plaza",
    "iso:country":"AU",
    "sg:address":"Shop 4",
    "sg:city":"Deepwater Plaza Woy Woy",
    "sg:classifiers":[
        {
            "category":"Personal",
            "subcategory":"Beauty Salon",
            "type":"Services"
        }
    ],
    "sg:phone":"+61 2 4342 8814",
    "sg:postcode":"2256",
    "sg:province":"NSW",
    "sg:tags":[
        "hairdresser"
    ],
    "wof:name":"Just Cuts",
    "wof:placetype":"venue"
},
  "geometry": {"coordinates":[151.327468872,-33.4929008484],"type":"Point"}
}