{
  "type": "Feature",
  "properties": {
    "iso:country":"AU",
    "sg:address":"PO Box 170",
    "sg:city":"Dulwich Hill",
    "sg:classifiers":[
        {
            "category":"Sports & Exercise",
            "subcategory":"Sports Center",
            "type":"Entertainment"
        }
    ],
    "sg:phone":"+61 411 158 669",
    "sg:postcode":"2203",
    "sg:province":"NSW",
    "sg:tags":[
        "coach",
        "tennis"
    ],
    "wof:name":"Australian Tennis Professional Coaches Association",
    "wof:placetype":"venue"
},
  "geometry": {"coordinates":[151.13876300000001,-33.90469],"type":"Point"}
}