{
  "type": "Feature",
  "properties": {
    "iso:country":"AU",
    "sg:address":"Suite 2, 734 Albany Hwy",
    "sg:city":"Victoria Park",
    "sg:classifiers":[
        {
            "category":"Health Services",
            "subcategory":"Dentist",
            "type":"Services"
        }
    ],
    "sg:phone":"+61 8 9355 1474",
    "sg:postcode":"6100",
    "sg:province":"WA",
    "sg:tags":[
        "dental",
        "prosthetist"
    ],
    "wof:name":"Denture Professionals",
    "wof:placetype":"venue"
},
  "geometry": {"coordinates":[115.897903442,-31.975112915],"type":"Point"}
}