{
  "type": "Feature",
  "properties": {
    "addr:full":"Pacific Hwy Woolgoolga NSW 2456",
    "addr:postcode":"2456",
    "addr:street":"Pacific Hwy",
    "iso:country":"AU",
    "sg:address":"Pacific Hwy",
    "sg:city":"Woolgoolga",
    "sg:classifiers":[
        {
            "category":"Autos & Motor Vehicles",
            "subcategory":"Fuel & Gas Station",
            "type":"Retail Goods"
        }
    ],
    "sg:phone":"+61 2 6654 1537",
    "sg:postcode":"2456",
    "sg:province":"NSW",
    "wof:name":"BP Australia Limited",
    "wof:placetype":"venue"
},
  "geometry": {"coordinates":[153.19035299999999,-30.111889],"type":"Point"}
}