{
  "type": "Feature",
  "properties": {
    "addr:full":"350 Church St Hay NSW 2711",
    "addr:housenumber":"350",
    "addr:postcode":"2711",
    "addr:street":"Church St",
    "iso:country":"AU",
    "sg:address":"350 Church St",
    "sg:city":"Hay",
    "sg:classifiers":[
        {
            "category":"Education",
            "subcategory":"Kindergarten",
            "type":"Public Place"
        }
    ],
    "sg:phone":"+61 2 6993 3059",
    "sg:postcode":"2711",
    "sg:province":"NSW",
    "sg:tags":[
        "pre-schools"
    ],
    "wof:name":"Hay Mobile Resources Unit",
    "wof:placetype":"venue"
},
  "geometry": {"coordinates":[144.850738525,-34.5037536621],"type":"Point"}
}