{
  "type": "Feature",
  "properties": {
    "iso:country":"AU",
    "sg:address":"145a Beaumont St",
    "sg:city":"Hamilton",
    "sg:classifiers":[
        {
            "category":"Arena",
            "subcategory":"Horse Racetrack",
            "type":"Entertainment"
        }
    ],
    "sg:phone":"+61 2 4961 6804",
    "sg:postcode":"2303",
    "sg:province":"NSW",
    "sg:tags":[
        "retail",
        "swimwear"
    ],
    "wof:name":"Cozzies-swimwear",
    "wof:placetype":"venue"
},
  "geometry": {"coordinates":[151.746826,-32.925068],"type":"Point"}
}