{
  "type": "Feature",
  "properties": {
    "addr:full":"2 Roslyn St Potts Point NSW 2011",
    "addr:housenumber":"2",
    "addr:postcode":"2011",
    "addr:street":"Roslyn St",
    "iso:country":"AU",
    "sg:address":"2 Roslyn St",
    "sg:city":"Potts Point",
    "sg:classifiers":[
        {
            "category":"Travel",
            "subcategory":"Hotels & Motels",
            "type":"Entertainment"
        }
    ],
    "sg:phone":"+61 2 8354 0956",
    "sg:postcode":"2011",
    "sg:province":"NSW",
    "wof:name":"Leisure Inn Suites",
    "wof:placetype":"venue"
},
  "geometry": {"coordinates":[151.224533081,-33.8735542297],"type":"Point"}
}