{
  "type": "Feature",
  "properties": {
    "addr:full":"9 Church St Brighton VIC 3186",
    "addr:housenumber":"9",
    "addr:postcode":"3186",
    "addr:street":"Church St",
    "iso:country":"AU",
    "sg:address":"9 Church St",
    "sg:city":"Brighton",
    "sg:classifiers":[
        {
            "category":"Fast Food",
            "type":"Food & Drink"
        }
    ],
    "sg:phone":"+61 3 9591 0633",
    "sg:postcode":"3186",
    "sg:province":"VIC",
    "sg:tags":[
        "away",
        "take"
    ],
    "wof:name":"Omuro Japanese Take Away & Grocery",
    "wof:placetype":"venue"
},
  "geometry": {"coordinates":[144.99316406200001,-37.9125938416],"type":"Point"}
}