{
  "type": "Feature",
  "properties": {
    "addr:full":"47 Kangaroo St Lawson NSW 2783",
    "addr:housenumber":"47",
    "addr:postcode":"2783",
    "addr:street":"Kangaroo St",
    "iso:country":"AU",
    "sg:address":"47 Kangaroo St",
    "sg:city":"Lawson",
    "sg:classifiers":[
        {
            "category":"Health Services",
            "subcategory":"Health Practitioner",
            "type":"Services"
        }
    ],
    "sg:phone":"+61 2 4759 1118",
    "sg:postcode":"2783",
    "sg:province":"NSW",
    "sg:tags":[
        "naturopath"
    ],
    "wof:name":"de Haan Helen",
    "wof:placetype":"venue"
},
  "geometry": {"coordinates":[150.440841675,-33.7149047852],"type":"Point"}
}