{
  "type": "Feature",
  "properties": {
    "addr:full":"88 Eucalypt Drv Lilydale VIC 3140",
    "addr:housenumber":"88",
    "addr:postcode":"3140",
    "addr:street":"Eucalypt Drv",
    "iso:country":"AU",
    "sg:address":"88 Eucalypt Drv",
    "sg:city":"Lilydale",
    "sg:classifiers":[
        {
            "category":"Utilities",
            "subcategory":"Water",
            "type":"Services"
        }
    ],
    "sg:phone":"+61 3 9735 9175",
    "sg:postcode":"3140",
    "sg:province":"VIC",
    "sg:tags":[
        "cartage"
    ],
    "wof:name":"Phils Water Cartage",
    "wof:placetype":"venue"
},
  "geometry": {"coordinates":[145.34605407699999,-37.7729377747],"type":"Point"}
}