{
  "type": "Feature",
  "properties": {
    "iso:country":"AU",
    "sg:address":"33 Patterson Rd",
    "sg:city":"Bentleigh",
    "sg:classifiers":[
        {
            "category":"Personal",
            "subcategory":"Massage",
            "type":"Services"
        }
    ],
    "sg:phone":"+61 3 9557 1720",
    "sg:postcode":"3204",
    "sg:province":"VIC",
    "sg:tags":[
        "therapy"
    ],
    "wof:name":"Zen Zone Health and Beauty",
    "wof:placetype":"venue"
},
  "geometry": {"coordinates":[145.033875,-37.925316],"type":"Point"}
}