{
  "type": "Feature",
  "properties": {
    "addr:full":"200 Melrose Drv Tullamarine VIC 3043",
    "addr:housenumber":"200",
    "addr:postcode":"3043",
    "addr:street":"Melrose Drv",
    "iso:country":"AU",
    "sg:address":"200 Melrose Drv",
    "sg:city":"Tullamarine",
    "sg:classifiers":[
        {
            "category":"Professional",
            "subcategory":"Computer Services",
            "type":"Services"
        }
    ],
    "sg:phone":"+61 3 9335 1121",
    "sg:postcode":"3043",
    "sg:province":"VIC",
    "sg:tags":[
        "consultant",
        "system"
    ],
    "wof:name":"Aus-Tech Consulting",
    "wof:placetype":"venue"
},
  "geometry": {"coordinates":[144.87977600100001,-37.6985931396],"type":"Point"}
}