{
  "type": "Feature",
  "properties": {
    "iso:country":"AU",
    "sg:address":"680 Bruce Crs",
    "sg:city":"Wallarah",
    "sg:classifiers":[
        {
            "category":"Building & Trades",
            "subcategory":"Construction",
            "type":"Services"
        }
    ],
    "sg:phone":"+61 2 4392 6905",
    "sg:postcode":"2259",
    "sg:province":"NSW",
    "sg:tags":[
        "renovation",
        "alterations",
        "extension",
        "contractor"
    ],
    "wof:name":"Mick Harvey",
    "wof:placetype":"venue"
},
  "geometry": {"coordinates":[151.45008850100001,-33.2426109314],"type":"Point"}
}