{
  "type": "Feature",
  "properties": {
    "addr:full":"High St Boonah QLD 4310",
    "addr:postcode":"4310",
    "addr:street":"High St",
    "iso:country":"AU",
    "sg:address":"High St",
    "sg:city":"Boonah",
    "sg:classifiers":[
        {
            "category":"Professional",
            "subcategory":"Accounting & Tax Preparation",
            "type":"Services"
        }
    ],
    "sg:phone":"+61 7 5463 2199",
    "sg:postcode":"4310",
    "sg:province":"QLD",
    "sg:tags":[
        "consultant",
        "taxation"
    ],
    "wof:name":"Ramsey R W & Co Pty Ltd",
    "wof:placetype":"venue"
},
  "geometry": {"coordinates":[152.682571411,-27.9953708649],"type":"Point"}
}