{
  "type": "Feature",
  "properties": {
    "addr:full":"527 Sandy Bay Rd Sandy Bay TAS 7005",
    "addr:housenumber":"527",
    "addr:postcode":"7005",
    "addr:street":"Sandy Bay Rd",
    "iso:country":"AU",
    "sg:address":"527 Sandy Bay Rd",
    "sg:city":"Sandy Bay",
    "sg:classifiers":[
        {
            "category":"Deli",
            "type":"Food & Drink"
        }
    ],
    "sg:phone":"+61 3 6225 1135",
    "sg:postcode":"7005",
    "sg:province":"TAS",
    "sg:tags":[
        "delicatessen"
    ],
    "wof:name":"Lipscombe Larder",
    "wof:placetype":"venue"
},
  "geometry": {"coordinates":[147.34684753400001,-42.9090957642],"type":"Point"}
}