{
  "type": "Feature",
  "properties": {
    "iso:country":"AU",
    "sg:address":"Shop 1 34 Tank St",
    "sg:city":"Gladstone",
    "sg:classifiers":[
        {
            "category":"Professional",
            "subcategory":"Printing & Photocopies",
            "type":"Services"
        }
    ],
    "sg:phone":"+61 7 4972 4270",
    "sg:postcode":"4680",
    "sg:province":"QLD",
    "sg:tags":[
        "photocopier"
    ],
    "wof:name":"CQ Digital Solutions",
    "wof:placetype":"venue"
},
  "geometry": {"coordinates":[151.260528564,-23.84815979],"type":"Point"}
}