{
  "type": "Feature",
  "properties": {
    "addr:full":"Shop 42 The Pines Shopping Centre Guineas Creek Rd Elanora QLD 4221",
    "addr:housenumber":"shop 42",
    "addr:postcode":"4221",
    "addr:street":"The;Guineas Creek Rd",
    "iso:country":"AU",
    "sg:address":"Shop 42 The Pines Shopping Centre Guineas Creek Rd",
    "sg:city":"Elanora",
    "sg:classifiers":[
        {
            "category":"Shopping",
            "subcategory":"Shoes",
            "type":"Retail Goods"
        }
    ],
    "sg:phone":"+61 7 5534 4623",
    "sg:postcode":"4221",
    "sg:province":"QLD",
    "sg:tags":[
        "footwear"
    ],
    "wof:name":"Mathers Shoes",
    "wof:placetype":"venue"
},
  "geometry": {"coordinates":[153.454177856,-28.1367073059],"type":"Point"}
}