{
  "type": "Feature",
  "properties": {
    "addr:full":"34 Ozone St Victor Harbor SA 5211",
    "addr:housenumber":"34",
    "addr:postcode":"5211",
    "addr:street":"Ozone St",
    "iso:country":"AU",
    "sg:address":"34 Ozone St",
    "sg:city":"Victor Harbor",
    "sg:classifiers":[
        {
            "category":"Building & Trades",
            "subcategory":"Construction",
            "type":"Services"
        }
    ],
    "sg:phone":"+61 8 8552 3142",
    "sg:postcode":"5211",
    "sg:province":"SA",
    "sg:tags":[
        "roof"
    ],
    "wof:name":"McKenzie's Roofing",
    "wof:placetype":"venue"
},
  "geometry": {"coordinates":[138.615432739,-35.5481414795],"type":"Point"}
}