{
  "type": "Feature",
  "properties": {
    "iso:country":"AU",
    "sg:address":"2/ 172 Boat Harbour Drv",
    "sg:city":"Hervey Bay",
    "sg:classifiers":[
        {
            "category":"Shopping",
            "subcategory":"Crafts & Fabrics",
            "type":"Retail Goods"
        }
    ],
    "sg:phone":"+61 7 4124 2022",
    "sg:postcode":"4655",
    "sg:province":"QLD",
    "sg:tags":[
        "supply"
    ],
    "wof:name":"Crazy Crafts Warehouse",
    "wof:placetype":"venue"
},
  "geometry": {"coordinates":[152.83781400000001,-25.287924],"type":"Point"}
}