{
  "type": "Feature",
  "properties": {
    "addr:full":"Shop 55 Chute St Diamond Creek VIC 3089",
    "addr:housenumber":"shop 55",
    "addr:postcode":"3089",
    "addr:street":"Chute St",
    "iso:country":"AU",
    "sg:address":"Shop 55 Chute St",
    "sg:city":"Diamond Creek",
    "sg:classifiers":[
        {
            "category":"Shopping",
            "subcategory":"Clothing, Apparel, & Fashions",
            "type":"Retail Goods"
        }
    ],
    "sg:phone":"+61 3 9438 5464",
    "sg:postcode":"3089",
    "sg:province":"VIC",
    "sg:tags":[
        "maternity",
        "wear"
    ],
    "wof:name":"Mango Jam Maternity",
    "wof:placetype":"venue"
},
  "geometry": {"coordinates":[145.15237400000001,-37.672897],"type":"Point"}
}