{
  "type": "Feature",
  "properties": {
    "iso:country":"AU",
    "sg:address":"Trade Centre Shed 15/ 66A Smith St",
    "sg:city":"Alice Springs",
    "sg:classifiers":[
        {
            "category":"Professional",
            "subcategory":"Engineering",
            "type":"Services"
        }
    ],
    "sg:phone":"+61 8 8953 2355",
    "sg:postcode":"0870",
    "sg:province":"NT",
    "sg:tags":[
        "engineer"
    ],
    "wof:name":"Tranthem Engineering Pty Ltd",
    "wof:placetype":"venue"
},
  "geometry": {"coordinates":[133.86436462399999,-23.6903629303],"type":"Point"}
}