{
  "type": "Feature",
  "properties": {
    "addr:full":"250 Blaxland Rd Ryde NSW 2112",
    "addr:housenumber":"250",
    "addr:postcode":"2112",
    "addr:street":"Blaxland Rd",
    "iso:country":"AU",
    "sg:address":"250 Blaxland Rd",
    "sg:city":"Ryde",
    "sg:classifiers":[
        {
            "category":"Education",
            "subcategory":"Junior College",
            "type":"Public Place"
        }
    ],
    "sg:phone":"+61 1800 064 802",
    "sg:postcode":"2112",
    "sg:province":"NSW",
    "sg:tags":[
        "business"
    ],
    "wof:name":"Le Cordon Bleu",
    "wof:placetype":"venue"
},
  "geometry": {"coordinates":[151.10462951700001,-33.8070983887],"type":"Point"}
}