{
  "type": "Feature",
  "properties": {
    "addr:full":"114 Hoare St Manunda QLD 4870",
    "addr:housenumber":"114",
    "addr:postcode":"4870",
    "addr:street":"Hoare St",
    "iso:country":"AU",
    "sg:address":"114 Hoare St",
    "sg:city":"Manunda",
    "sg:classifiers":[
        {
            "category":"Fast Food",
            "type":"Food & Drink"
        }
    ],
    "sg:phone":"+61 7 4032 0790",
    "sg:postcode":"4870",
    "sg:province":"QLD",
    "sg:tags":[
        "away",
        "take"
    ],
    "wof:name":"Daeng's Thai Takeaway",
    "wof:placetype":"venue"
},
  "geometry": {"coordinates":[145.745605469,-16.923116684],"type":"Point"}
}