{
  "type": "Feature",
  "properties": {
    "addr:full":"26 Como Rd Oyster Bay NSW 2225",
    "addr:housenumber":"26",
    "addr:postcode":"2225",
    "addr:street":"Como Rd",
    "iso:country":"AU",
    "sg:address":"26 Como Rd",
    "sg:city":"Oyster Bay",
    "sg:classifiers":[
        {
            "category":"Real Estate",
            "subcategory":"Surveying",
            "type":"Services"
        }
    ],
    "sg:phone":"+61 412 909 126",
    "sg:postcode":"2225",
    "sg:province":"NSW",
    "sg:tags":[
        "surveyor",
        "land"
    ],
    "wof:name":"A Allen Consulting Surveyors Pty Ltd",
    "wof:placetype":"venue"
},
  "geometry": {"coordinates":[151.085006714,-34.0023727417],"type":"Point"}
}