{
  "type": "Feature",
  "properties": {
    "addr:full":"PO Box 161 Geraldton Private Boxes WA 6531",
    "addr:postcode":"6531",
    "iso:country":"AU",
    "sg:address":"PO Box 161",
    "sg:city":"Geraldton Private Boxes",
    "sg:classifiers":[
        {
            "category":"Building & Trades",
            "subcategory":"Landscaping Services",
            "type":"Services"
        }
    ],
    "sg:phone":"+61 8 9964 4563",
    "sg:postcode":"6531",
    "sg:province":"WA",
    "sg:tags":[
        "control",
        "weed"
    ],
    "wof:name":"Central West Pest Control",
    "wof:placetype":"venue"
},
  "geometry": {"coordinates":[114.61126709,-28.7730693817],"type":"Point"}
}