{
  "type": "Feature",
  "properties": {
    "iso:country":"AU",
    "sg:address":"5/ 104 Botany Strs",
    "sg:city":"Randwick",
    "sg:classifiers":[
        {
            "category":"Building & Trades",
            "subcategory":"Construction",
            "type":"Services"
        }
    ],
    "sg:phone":"+61 418 474 663",
    "sg:postcode":"2031",
    "sg:province":"NSW",
    "sg:tags":[
        "polishing",
        "sanding",
        "floor"
    ],
    "wof:name":"Add Perfect Shining",
    "wof:placetype":"venue"
},
  "geometry": {"coordinates":[151.23455810600001,-33.9238967896],"type":"Point"}
}