{
  "type": "Feature",
  "properties": {
    "addr:full":"41 Belgrave St Manly NSW 2095",
    "addr:housenumber":"41",
    "addr:postcode":"2095",
    "addr:street":"Belgrave St",
    "iso:country":"AU",
    "sg:address":"41 Belgrave St",
    "sg:city":"Manly",
    "sg:classifiers":[
        {
            "category":"Social Services",
            "subcategory":"Retirement Home",
            "type":"Services"
        }
    ],
    "sg:phone":"+61 2 9976 2842",
    "sg:postcode":"2095",
    "sg:province":"NSW",
    "sg:tags":[
        "environmental",
        "consultant",
        "pollution"
    ],
    "wof:name":"Manly Environment Centre",
    "wof:placetype":"venue"
},
  "geometry": {"coordinates":[151.28541564899999,-33.7958717346],"type":"Point"}
}