{
  "type": "Feature",
  "properties": {
    "iso:country":"AU",
    "sg:address":"\"The Village\" Lord St Whiteman Park",
    "sg:city":"Whiteman",
    "sg:classifiers":[
        {
            "category":"Cafe",
            "type":"Food & Drink"
        }
    ],
    "sg:phone":"+61 8 9249 3552",
    "sg:postcode":"6068",
    "sg:province":"WA",
    "wof:name":"Whiteman Park Country Kitchen",
    "wof:placetype":"venue"
},
  "geometry": {"coordinates":[115.968948364,-31.8552093506],"type":"Point"}
}