{
  "type": "Feature",
  "properties": {
    "addr:full":"Shop 4 121 The Cove Rd Hallett Cove SA 5158",
    "addr:housenumber":"shop 4 121",
    "addr:postcode":"5158",
    "addr:street":"The Cove Rd",
    "iso:country":"AU",
    "sg:address":"Shop 4 121 The Cove Rd",
    "sg:city":"Hallett Cove",
    "sg:classifiers":[
        {
            "category":"Health Services",
            "subcategory":"Doctor",
            "type":"Services"
        }
    ],
    "sg:phone":"+61 8 8414 8414",
    "sg:postcode":"5158",
    "sg:province":"SA",
    "sg:tags":[
        "medical",
        "practitioner"
    ],
    "wof:name":"Tobias Otto H",
    "wof:placetype":"venue"
},
  "geometry": {"coordinates":[138.505584717,-35.0650024414],"type":"Point"}
}