{
  "type": "Feature",
  "properties": {
    "iso:country":"AU",
    "sg:address":"11 MacIntosh St",
    "sg:city":"Mascot",
    "sg:classifiers":[
        {
            "category":"Shopping",
            "subcategory":"Stationery & Office Supplies",
            "type":"Retail Goods"
        }
    ],
    "sg:phone":"+61 418 227 988",
    "sg:postcode":"2020",
    "sg:province":"NSW",
    "sg:tags":[
        "partition"
    ],
    "wof:name":"Maybury Interiors Pty Ltd",
    "wof:placetype":"venue"
},
  "geometry": {"coordinates":[151.19410705600001,-33.927406311],"type":"Point"}
}