{
  "type": "Feature",
  "properties": {
    "iso:country":"AU",
    "sg:address":"164 Marius St",
    "sg:city":"Tamworth",
    "sg:classifiers":[
        {
            "category":"Health Services",
            "subcategory":"Doctor",
            "type":"Services"
        }
    ],
    "sg:phone":"+61 2 6766 5288",
    "sg:postcode":"2340",
    "sg:province":"NSW",
    "sg:tags":[
        "medical",
        "practitioner"
    ],
    "wof:name":"On Clinic",
    "wof:placetype":"venue"
},
  "geometry": {"coordinates":[150.93260192899999,-31.0898265839],"type":"Point"}
}