{
  "type": "Feature",
  "properties": {
    "iso:country":"AU",
    "sg:address":"Webb Dock Terminal Williamstown Rd",
    "sg:city":"Port Melbourne",
    "sg:classifiers":[
        {
            "category":"Transit Center",
            "subcategory":"Freight",
            "type":"Transportation"
        }
    ],
    "sg:phone":"+61 3 9647 8777",
    "sg:postcode":"3207",
    "sg:province":"VIC",
    "sg:tags":[
        "stevedore"
    ],
    "wof:name":"Patrick Stevedores",
    "wof:placetype":"venue"
},
  "geometry": {"coordinates":[144.92358400000001,-37.835239],"type":"Point"}
}