{
  "type": "Feature",
  "properties": {
    "addr:full":"Shop 50 Bass Hill Plaza 735 Hume Highway Bass Hill NSW 2197",
    "addr:housenumber":"shop 50;735",
    "addr:postcode":"2197",
    "addr:street":"Hume Highway",
    "iso:country":"AU",
    "sg:address":"Shop 50 Bass Hill Plaza 735",
    "sg:city":"Hume Highway Bass Hill",
    "sg:classifiers":[
        {
            "category":"Personal",
            "subcategory":"Beauty Salon",
            "type":"Services"
        }
    ],
    "sg:phone":"+61 2 9728 2758",
    "sg:postcode":"2197",
    "sg:province":"NSW",
    "sg:tags":[
        "hairdresser"
    ],
    "wof:name":"Rubette Hairdressing",
    "wof:placetype":"venue"
},
  "geometry": {"coordinates":[150.99525499999999,-33.898571],"type":"Point"}
}