{
  "type": "Feature",
  "properties": {
    "addr:full":"Cnr Church & Market Sts Parramatta NSW 2150",
    "addr:postcode":"2150",
    "iso:country":"AU",
    "sg:address":"Cnr Church & Market Sts",
    "sg:city":"Parramatta",
    "sg:classifiers":[
        {
            "category":"Retail",
            "subcategory":"Event Space",
            "type":"Services"
        }
    ],
    "sg:phone":"+61 2 9630 0511",
    "sg:postcode":"2150",
    "sg:province":"NSW",
    "sg:tags":[
        "venue",
        "reception",
        "wedding"
    ],
    "wof:name":"Amadeus Catering Pty Ltd.",
    "wof:placetype":"venue"
},
  "geometry": {"coordinates":[151.00668335,-33.81483078],"type":"Point"}
}