{
  "type": "Feature",
  "properties": {
    "iso:country":"AU",
    "sg:address":"16 Nandina St",
    "sg:city":"Forest Hill",
    "sg:classifiers":[
        {
            "category":"Real Estate",
            "subcategory":"Architect",
            "type":"Services"
        }
    ],
    "sg:phone":"+61 3 9874 5250",
    "sg:postcode":"3131",
    "sg:province":"VIC",
    "wof:name":"Zalk George",
    "wof:placetype":"venue"
},
  "geometry": {"coordinates":[145.18205261200001,-37.8331184387],"type":"Point"}
}