{
  "type": "Feature",
  "properties": {
    "iso:country":"AU",
    "sg:address":"23 Jasmine Drv",
    "sg:city":"Bomaderry",
    "sg:classifiers":[
        {
            "category":"Building & Trades",
            "subcategory":"Construction",
            "type":"Services"
        }
    ],
    "sg:phone":"+61 2 4423 1314",
    "sg:postcode":"2541",
    "sg:province":"NSW",
    "sg:tags":[
        "earth",
        "excavating",
        "moving",
        "contractor"
    ],
    "wof:name":"Bomaderry Mini Excavations",
    "wof:placetype":"venue"
},
  "geometry": {"coordinates":[150.59832763700001,-34.8414115906],"type":"Point"}
}