{
  "type": "Feature",
  "properties": {
    "addr:full":"155 Navigator Rd Ballarat VIC 3352",
    "addr:housenumber":"155",
    "addr:postcode":"3352",
    "addr:street":"Navigator Rd",
    "iso:country":"AU",
    "sg:address":"155 Navigator Rd",
    "sg:city":"Ballarat",
    "sg:classifiers":[
        {
            "category":"Building & Trades",
            "subcategory":"Construction",
            "type":"Services"
        }
    ],
    "sg:phone":"+61 412 221 799",
    "sg:postcode":"3352",
    "sg:province":"VIC",
    "sg:tags":[
        "earth",
        "excavating",
        "moving",
        "contractor"
    ],
    "wof:name":"MH Bobcat & Tipper Services",
    "wof:placetype":"venue"
},
  "geometry": {"coordinates":[143.89198300000001,-37.435986],"type":"Point"}
}