{
  "type": "Feature",
  "properties": {
    "addr:full":"2/ 16 Sundercombe St Osborne Park WA 6017",
    "addr:housenumber":"/ 16",
    "addr:postcode":"6017",
    "addr:street":"Sundercombe St",
    "iso:country":"AU",
    "sg:address":"2/ 16 Sundercombe St",
    "sg:city":"Osborne Park",
    "sg:classifiers":[
        {
            "category":"Professional",
            "subcategory":"Printing & Photocopies",
            "type":"Services"
        }
    ],
    "sg:phone":"+61 8 9244 9000",
    "sg:postcode":"6017",
    "sg:province":"WA",
    "sg:tags":[
        "screen",
        "printer"
    ],
    "sg:website":"http://www.fabricprinter.com.au",
    "wof:name":"Fabric Printer The",
    "wof:placetype":"venue"
},
  "geometry": {"coordinates":[115.81288146999999,-31.9036808014],"type":"Point"}
}