{
  "type": "Feature",
  "properties": {
    "addr:full":"PO Box 209 Glenbrook NSW 2773",
    "addr:postcode":"2773",
    "iso:country":"AU",
    "sg:address":"PO Box 209",
    "sg:city":"Glenbrook",
    "sg:classifiers":[
        {
            "category":"Health Services",
            "subcategory":"Doctor",
            "type":"Services"
        }
    ],
    "sg:phone":"+61 2 4739 5211",
    "sg:postcode":"2773",
    "sg:province":"NSW",
    "sg:tags":[
        "nurse",
        "nursing"
    ],
    "wof:name":"Complete Care Team",
    "wof:placetype":"venue"
},
  "geometry": {"coordinates":[150.621170044,-33.7665481567],"type":"Point"}
}