{
  "type": "Feature",
  "properties": {
    "iso:country":"AU",
    "sg:address":"70 East Boundary Rd",
    "sg:city":"Bentleigh East",
    "sg:classifiers":[
        {
            "category":"Social Services",
            "subcategory":"Child Care",
            "type":"Services"
        }
    ],
    "sg:phone":"+61 3 9579 4547",
    "sg:postcode":"3165",
    "sg:province":"VIC",
    "wof:name":"East Bentleigh Child Care Centre",
    "wof:placetype":"venue"
},
  "geometry": {"coordinates":[145.057769775,-37.9288101196],"type":"Point"}
}