{
  "type": "Feature",
  "properties": {
    "addr:full":"59 Meehan La Osbornes Flat NSW 3749",
    "addr:housenumber":"59",
    "addr:postcode":"3749",
    "addr:street":"Meehan La Osbornes",
    "iso:country":"AU",
    "sg:address":"59 Meehan La",
    "sg:city":"Osbornes Flat",
    "sg:classifiers":[
        {
            "category":"Building & Trades",
            "subcategory":"Construction",
            "type":"Services"
        }
    ],
    "sg:phone":"+61 2 6027 0955",
    "sg:postcode":"3749",
    "sg:province":"NSW",
    "sg:tags":[
        "contractor"
    ],
    "wof:name":"Marjen Homes P/L",
    "wof:placetype":"venue"
},
  "geometry": {"coordinates":[146.86291499999999,-36.327293],"type":"Point"}
}