{
  "type": "Feature",
  "properties": {
    "iso:country":"AU",
    "sg:address":"48 Denbigh St",
    "sg:city":"Moolap",
    "sg:classifiers":[
        {
            "category":"Building & Trades",
            "subcategory":"Construction",
            "type":"Services"
        }
    ],
    "sg:phone":"+61 1300 133 922",
    "sg:postcode":"3221",
    "sg:province":"VIC",
    "sg:tags":[
        "scaffolding"
    ],
    "wof:name":"Access Scaffolding Hire",
    "wof:placetype":"venue"
},
  "geometry": {"coordinates":[144.415466,-38.168156],"type":"Point"}
}