{
  "type": "Feature",
  "properties": {
    "iso:country":"AU",
    "sg:address":"6 Vivienne Ave",
    "sg:city":"Mt Gambier",
    "sg:classifiers":[
        {
            "category":"Personal",
            "subcategory":"Massage",
            "type":"Services"
        }
    ],
    "sg:phone":"+61 409 330 701",
    "sg:postcode":"5290",
    "sg:province":"SA",
    "sg:tags":[
        "therapy"
    ],
    "wof:name":"Kathy Nunn",
    "wof:placetype":"venue"
},
  "geometry": {"coordinates":[140.78945899999999,-37.803455],"type":"Point"}
}