{
  "type": "Feature",
  "properties": {
    "iso:country":"AU",
    "sg:address":"206 Gertrude St",
    "sg:city":"Fitzroy",
    "sg:classifiers":[
        {
            "category":"Retail",
            "subcategory":"Storage",
            "type":"Services"
        }
    ],
    "sg:phone":"+61 3 9417 6518",
    "sg:postcode":"3065",
    "sg:province":"VIC",
    "wof:name":"Harry Evans & Sons (Vic) Pty Ltd",
    "wof:placetype":"venue"
},
  "geometry": {"coordinates":[144.98162841800001,-37.8063278198],"type":"Point"}
}