{
  "type": "Feature",
  "properties": {
    "addr:full":"38 Johnston St Collingwood VIC 3066",
    "addr:housenumber":"38",
    "addr:postcode":"3066",
    "addr:street":"Johnston St",
    "iso:country":"AU",
    "sg:address":"38 Johnston St",
    "sg:city":"Collingwood",
    "sg:classifiers":[
        {
            "category":"Home & Garden",
            "subcategory":"Hardware",
            "type":"Retail Goods"
        }
    ],
    "sg:phone":"+61 3 9417 5828",
    "sg:postcode":"3066",
    "sg:province":"VIC",
    "sg:tags":[
        "compressor",
        "air"
    ],
    "wof:name":"Dinatale John Engineering",
    "wof:placetype":"venue"
},
  "geometry": {"coordinates":[144.986038208,-37.7989845276],"type":"Point"}
}