{
  "type": "Feature",
  "properties": {
    "addr:full":"21 Railway Ave Bundanoon NSW 2578",
    "addr:housenumber":"21",
    "addr:postcode":"2578",
    "addr:street":"Railway Ave",
    "iso:country":"AU",
    "sg:address":"21 Railway Ave",
    "sg:city":"Bundanoon",
    "sg:classifiers":[
        {
            "category":"Restaurant",
            "type":"Food & Drink"
        }
    ],
    "sg:phone":"+61 2 4883 6368",
    "sg:postcode":"2578",
    "sg:province":"NSW",
    "wof:name":"Bundanoon Chinese Restaurant",
    "wof:placetype":"venue"
},
  "geometry": {"coordinates":[150.30076599099999,-34.6561050415],"type":"Point"}
}