{
  "type": "Feature",
  "properties": {
    "addr:full":"359 Commercial St (West) Mt Gambier SA 5290",
    "addr:housenumber":"359",
    "addr:postcode":"5290",
    "addr:street":"Commercial St West",
    "iso:country":"AU",
    "sg:address":"359 Commercial St (West)",
    "sg:city":"Mt Gambier",
    "sg:classifiers":[
        {
            "category":"Building & Trades",
            "subcategory":"Landscaping Services",
            "type":"Services"
        }
    ],
    "sg:phone":"+61 448 686 144",
    "sg:postcode":"5290",
    "sg:province":"SA",
    "sg:tags":[
        "designer",
        "landscape",
        "contractor"
    ],
    "wof:name":"Easy Spread",
    "wof:placetype":"venue"
},
  "geometry": {"coordinates":[140.74920700000001,-37.818398],"type":"Point"}
}