{
  "type": "Feature",
  "properties": {
    "iso:country":"AU",
    "sg:address":"334 Keilor Rd",
    "sg:city":"Niddrie",
    "sg:classifiers":[
        {
            "category":"Shopping",
            "subcategory":"Hobbies, Toys, & Games",
            "type":"Retail Goods"
        }
    ],
    "sg:phone":"+61 3 9379 5777",
    "sg:postcode":"3042",
    "sg:province":"VIC",
    "sg:tags":[
        "stamp"
    ],
    "wof:name":"O&#039;Brien P & J",
    "wof:placetype":"venue"
},
  "geometry": {"coordinates":[144.89158630399999,-37.7368507385],"type":"Point"}
}