{
  "type": "Feature",
  "properties": {
    "addr:full":"243 Maroubra Rd Maroubra NSW 2035",
    "addr:housenumber":"243",
    "addr:postcode":"2035",
    "addr:street":"Maroubra Rd",
    "iso:country":"AU",
    "sg:address":"243 Maroubra Rd",
    "sg:city":"Maroubra",
    "sg:classifiers":[
        {
            "category":"Personal",
            "subcategory":"Beauty Salon",
            "type":"Services"
        }
    ],
    "sg:phone":"+61 2 9344 0996",
    "sg:postcode":"2035",
    "sg:province":"NSW",
    "wof:name":"Shiner Hair Salon",
    "wof:placetype":"venue"
},
  "geometry": {"coordinates":[151.24110412600001,-33.9419364929],"type":"Point"}
}