{
  "type": "Feature",
  "properties": {
    "addr:full":"11 Coverdale St Carlingford NSW 2118",
    "addr:housenumber":"11",
    "addr:postcode":"2118",
    "addr:street":"Coverdale St",
    "iso:country":"AU",
    "sg:address":"11 Coverdale St",
    "sg:city":"Carlingford",
    "sg:classifiers":[
        {
            "category":"Health Services",
            "subcategory":"Dentist",
            "type":"Services"
        }
    ],
    "sg:phone":"+61 2 9871 1215",
    "sg:postcode":"2118",
    "sg:province":"NSW",
    "wof:name":"Irvin E J",
    "wof:placetype":"venue"
},
  "geometry": {"coordinates":[151.059616089,-33.7654838562],"type":"Point"}
}