{
  "type": "Feature",
  "properties": {
    "addr:full":"18- 20 Baillieu Crt Mitchell ACT 2911",
    "addr:housenumber":"20",
    "addr:postcode":"2911",
    "addr:street":"Baillieu Crt",
    "iso:country":"AU",
    "sg:address":"18- 20 Baillieu Crt",
    "sg:city":"Mitchell",
    "sg:classifiers":[
        {
            "category":"Retail",
            "subcategory":"Storage",
            "type":"Services"
        }
    ],
    "sg:phone":"+61 2 6255 7333",
    "sg:postcode":"2911",
    "sg:province":"ACT",
    "sg:tags":[
        "removal",
        "furniture"
    ],
    "wof:name":"Australian Vanlines",
    "wof:placetype":"venue"
},
  "geometry": {"coordinates":[149.14224243199999,-35.2172012329],"type":"Point"}
}