{
  "type": "Feature",
  "properties": {
    "addr:full":"Shop 2a Wentworth Hotel Sydney NSW 2000",
    "addr:housenumber":"shop 2a",
    "addr:postcode":"2000",
    "iso:country":"AU",
    "sg:address":"Shop 2a Wentworth Hotel",
    "sg:city":"Sydney",
    "sg:classifiers":[
        {
            "category":"Shopping",
            "subcategory":"Antiques",
            "type":"Retail Goods"
        }
    ],
    "sg:phone":"+61 2 9233 2515",
    "sg:postcode":"2000",
    "sg:province":"NSW",
    "wof:name":"Laveen's Antiques",
    "wof:placetype":"venue"
},
  "geometry": {"coordinates":[151.21211242699999,-33.8772621155],"type":"Point"}
}