{
  "type": "Feature",
  "properties": {
    "iso:country":"AU",
    "sg:address":"322 Crown St",
    "sg:city":"Wollongong",
    "sg:classifiers":[
        {
            "category":"Personal",
            "subcategory":"Beauty Salon",
            "type":"Services"
        }
    ],
    "sg:phone":"+61 2 4229 2353",
    "sg:postcode":"2500",
    "sg:province":"NSW",
    "sg:tags":[
        "hairdresser"
    ],
    "wof:name":"Peter Stutz Hairdresser",
    "wof:placetype":"venue"
},
  "geometry": {"coordinates":[150.881317,-34.425903],"type":"Point"}
}