{
  "type": "Feature",
  "properties": {
    "addr:full":"Suite 3 93 Bulcock St Caloundra QLD 4551",
    "addr:housenumber":"93",
    "addr:postcode":"4551",
    "addr:street":"Bulcock St",
    "iso:country":"AU",
    "sg:address":"Suite 3 93 Bulcock St",
    "sg:city":"Caloundra",
    "sg:classifiers":[
        {
            "category":"Professional",
            "subcategory":"Business Services",
            "type":"Services"
        }
    ],
    "sg:phone":"+61 7 5491 2393",
    "sg:postcode":"4551",
    "sg:province":"QLD",
    "sg:tags":[
        "drafting"
    ],
    "wof:name":"Caloundra Design & Drafting",
    "wof:placetype":"venue"
},
  "geometry": {"coordinates":[153.12867736800001,-26.804599762],"type":"Point"}
}