{
  "type": "Feature",
  "properties": {
    "iso:country":"AU",
    "sg:address":"9 Smythe St",
    "sg:city":"Shepparton",
    "sg:classifiers":[
        {
            "category":"Wholesale",
            "subcategory":"Metals & Minerals",
            "type":"Manufacturing & Wholesale Goods"
        }
    ],
    "sg:phone":"+61 3 5831 2330",
    "sg:postcode":"3630",
    "sg:province":"VIC",
    "sg:tags":[
        "steel",
        "merchant"
    ],
    "wof:name":"Challenge Steel",
    "wof:placetype":"venue"
},
  "geometry": {"coordinates":[145.41755676299999,-36.3854675293],"type":"Point"}
}