{
  "type": "Feature",
  "properties": {
    "addr:full":"113/ 396 Scarborough Beach Rd Osborne Park WA 6017",
    "addr:housenumber":"113 / 396",
    "addr:postcode":"6017",
    "addr:street":"Scarborough Beach Rd",
    "iso:country":"AU",
    "sg:address":"113/ 396 Scarborough Beach Rd",
    "sg:city":"Osborne Park",
    "sg:classifiers":[
        {
            "category":"Professional",
            "subcategory":"Art Services",
            "type":"Services"
        }
    ],
    "sg:phone":"+61 8 9242 1992",
    "sg:postcode":"6017",
    "sg:province":"WA",
    "sg:tags":[
        "graphic",
        "designer"
    ],
    "wof:name":"Style Graphics",
    "wof:placetype":"venue"
},
  "geometry": {"coordinates":[115.814582825,-31.9106483459],"type":"Point"}
}