{
  "type": "Feature",
  "properties": {
    "iso:country":"AU",
    "sg:address":"79 Old Station Rd",
    "sg:city":"Coningham",
    "sg:classifiers":[
        {
            "category":"Building & Trades",
            "subcategory":"Construction",
            "type":"Services"
        }
    ],
    "sg:phone":"+61 3 6267 9348",
    "sg:postcode":"7054",
    "sg:province":"TAS",
    "sg:tags":[
        "renovation",
        "alterations",
        "extension",
        "contractor"
    ],
    "wof:name":"Ims S R & L A",
    "wof:placetype":"venue"
},
  "geometry": {"coordinates":[147.265045,-43.075043],"type":"Point"}
}