{
  "type": "Feature",
  "properties": {
    "addr:full":"Shop S133 Elizabeth Shopping Centre, 50 Elizabeth Way, Elizabeth SA 5112",
    "addr:housenumber":"s133;50",
    "addr:postcode":"5112",
    "addr:street":"Elizabeth Way",
    "iso:country":"AU",
    "sg:address":"Shop S133 Elizabeth Shopping Centre, 50",
    "sg:city":"Elizabeth Way, Elizabeth",
    "sg:classifiers":[
        {
            "category":"Travel",
            "subcategory":"Travel Agent",
            "type":"Entertainment"
        }
    ],
    "sg:phone":"+61 8 8307 4177",
    "sg:postcode":"5112",
    "sg:province":"SA",
    "sg:tags":[
        "consultant"
    ],
    "wof:name":"Escape Travel",
    "wof:placetype":"venue"
},
  "geometry": {"coordinates":[138.66700744600001,-34.7156982422],"type":"Point"}
}