{
  "type": "Feature",
  "properties": {
    "addr:full":"81 Edinburgh Rd Castle Cove NSW 2069",
    "addr:housenumber":"81",
    "addr:postcode":"2069",
    "addr:street":"Edinburgh Rd",
    "iso:country":"AU",
    "sg:address":"81 Edinburgh Rd",
    "sg:city":"Castle Cove",
    "sg:classifiers":[
        {
            "category":"Real Estate",
            "subcategory":"Real Estate Agent",
            "type":"Services"
        }
    ],
    "sg:phone":"+61 2 9417 1376",
    "sg:postcode":"2069",
    "sg:province":"NSW",
    "wof:name":"Richardson & Wrench Pty Ltd",
    "wof:placetype":"venue"
},
  "geometry": {"coordinates":[151.20173645,-33.7819900513],"type":"Point"}
}