{
  "type": "Feature",
  "properties": {
    "iso:country":"AU",
    "sg:address":"10 Mallett Rd",
    "sg:city":"Tullamarine",
    "sg:classifiers":[
        {
            "category":"Banks & Credit Unions",
            "subcategory":"Investment Brokerage",
            "type":"Services"
        }
    ],
    "sg:phone":"+61 3 9338 0054",
    "sg:postcode":"3043",
    "sg:province":"VIC",
    "sg:tags":[
        "pulverising",
        "machinery",
        "grinding"
    ],
    "wof:name":"Rudolph Muller Pty Ltd",
    "wof:placetype":"venue"
},
  "geometry": {"coordinates":[144.849777222,-37.7068328857],"type":"Point"}
}