{
  "type": "Feature",
  "properties": {
    "addr:full":"8 Folini Ave Northmead NSW 2152",
    "addr:housenumber":"8",
    "addr:postcode":"2152",
    "addr:street":"Folini Ave",
    "iso:country":"AU",
    "sg:address":"8 Folini Ave",
    "sg:city":"Northmead",
    "sg:classifiers":[
        {
            "category":"Home & Garden",
            "subcategory":"Building Materials",
            "type":"Retail Goods"
        }
    ],
    "sg:phone":"+61 439 434 723",
    "sg:postcode":"2152",
    "sg:province":"NSW",
    "sg:tags":[
        "lawn",
        "cutting",
        "maintenance"
    ],
    "wof:name":"Snappy Home and Garden Care",
    "wof:placetype":"venue"
},
  "geometry": {"coordinates":[150.99940490700001,-33.7769165039],"type":"Point"}
}