{
  "type": "Feature",
  "properties": {
    "addr:full":"121 MacKay St Cootamundra NSW 2590",
    "addr:housenumber":"121",
    "addr:postcode":"2590",
    "addr:street":"Mackay St",
    "iso:country":"AU",
    "sg:address":"121 MacKay St",
    "sg:city":"Cootamundra",
    "sg:classifiers":[
        {
            "category":"Health Services",
            "subcategory":"Nursing And Care Facility",
            "type":"Services"
        }
    ],
    "sg:phone":"+61 2 6942 3511",
    "sg:postcode":"2590",
    "sg:province":"NSW",
    "sg:tags":[
        "home"
    ],
    "wof:name":"Cootamundra Nursing Home",
    "wof:placetype":"venue"
},
  "geometry": {"coordinates":[148.013793945,-34.6346511841],"type":"Point"}
}