{
  "type": "Feature",
  "properties": {
    "addr:full":"12 Denise Crt Langwarrin VIC 3910",
    "addr:housenumber":"12",
    "addr:postcode":"3910",
    "addr:street":"Denise Crt",
    "iso:country":"AU",
    "sg:address":"12 Denise Crt",
    "sg:city":"Langwarrin",
    "sg:classifiers":[
        {
            "category":"Building & Trades",
            "subcategory":"Construction",
            "type":"Services"
        }
    ],
    "sg:phone":"+61 408 516 248",
    "sg:postcode":"3910",
    "sg:province":"VIC",
    "sg:tags":[
        "window",
        "aluminium"
    ],
    "wof:name":"Dynamic Window Systems",
    "wof:placetype":"venue"
},
  "geometry": {"coordinates":[145.20857238799999,-38.1463127136],"type":"Point"}
}