{
  "type": "Feature",
  "properties": {
    "addr:full":"16A King St Blackburn VIC 3130",
    "addr:housenumber":"16a",
    "addr:postcode":"3130",
    "addr:street":"King St",
    "iso:country":"AU",
    "sg:address":"16A King St",
    "sg:city":"Blackburn",
    "sg:classifiers":[
        {
            "category":"Fast Food",
            "type":"Food & Drink"
        }
    ],
    "sg:phone":"+61 3 9877 7965",
    "sg:postcode":"3130",
    "sg:province":"VIC",
    "sg:tags":[
        "away",
        "take"
    ],
    "wof:name":"Food Cage The",
    "wof:placetype":"venue"
},
  "geometry": {"coordinates":[145.16418457,-37.8196640015],"type":"Point"}
}