{
  "type": "Feature",
  "properties": {
    "addr:full":"93 Elder St Lambton NSW 2299",
    "addr:housenumber":"93",
    "addr:postcode":"2299",
    "addr:street":"Elder St",
    "iso:country":"AU",
    "sg:address":"93 Elder St",
    "sg:city":"Lambton",
    "sg:classifiers":[
        {
            "category":"Health Services",
            "subcategory":"Doctor",
            "type":"Services"
        }
    ],
    "sg:phone":"+61 2 4957 3401",
    "sg:postcode":"2299",
    "sg:province":"NSW",
    "sg:tags":[
        "medical",
        "practitioner"
    ],
    "wof:name":"Tarrant Michael",
    "wof:placetype":"venue"
},
  "geometry": {"coordinates":[151.70863342300001,-32.9117126465],"type":"Point"}
}