{
  "type": "Feature",
  "properties": {
    "addr:full":"Level 3, 87 Wickham Tce Brisbane QLD 4001",
    "addr:housenumber":"87",
    "addr:postcode":"4001",
    "addr:street":"Wickham Tce",
    "iso:country":"AU",
    "sg:address":"Level 3, 87",
    "sg:city":"Wickham Tce Brisbane",
    "sg:classifiers":[
        {
            "category":"Professional",
            "subcategory":"Engineering",
            "type":"Services"
        }
    ],
    "sg:phone":"+61 7 3839 5370",
    "sg:postcode":"4001",
    "sg:province":"QLD",
    "sg:tags":[
        "consulting",
        "engineer"
    ],
    "wof:name":"Harrington Construction Consultants",
    "wof:placetype":"venue"
},
  "geometry": {"coordinates":[153.047561645,-27.3007793427],"type":"Point"}
}