{
  "type": "Feature",
  "properties": {
    "addr:full":"32 Pavilion St Queenscliff NSW 2096",
    "addr:housenumber":"32",
    "addr:postcode":"2096",
    "addr:street":"Pavilion St",
    "iso:country":"AU",
    "sg:address":"32 Pavilion St",
    "sg:city":"Queenscliff",
    "sg:classifiers":[
        {
            "category":"Professional",
            "subcategory":"Engineering",
            "type":"Services"
        }
    ],
    "sg:phone":"+61 2 9939 2786",
    "sg:postcode":"2096",
    "sg:province":"NSW",
    "sg:tags":[
        "consulting",
        "engineer"
    ],
    "wof:name":"Peleng",
    "wof:placetype":"venue"
},
  "geometry": {"coordinates":[151.288696289,-33.7836761475],"type":"Point"}
}