{
  "type": "Feature",
  "properties": {
    "addr:full":"Head Office 20 Shields St Cairns QLD 4870",
    "addr:housenumber":"20",
    "addr:postcode":"4870",
    "addr:street":"Shields St",
    "iso:country":"AU",
    "sg:address":"Head Office 20 Shields St",
    "sg:city":"Cairns",
    "sg:classifiers":[
        {
            "category":"Arts & Performance",
            "subcategory":"Art Gallery",
            "type":"Entertainment"
        }
    ],
    "sg:phone":"+61 7 4031 9877",
    "sg:postcode":"4870",
    "sg:province":"QLD",
    "wof:name":"Peter Jarver Gallery",
    "wof:placetype":"venue"
},
  "geometry": {"coordinates":[145.77560424800001,-16.9223918915],"type":"Point"}
}