{
  "type": "Feature",
  "properties": {
    "iso:country":"AU",
    "sg:address":"5 View Crt",
    "sg:city":"Aberfoyle Park",
    "sg:classifiers":[
        {
            "category":"Health Services",
            "subcategory":"Health Practitioner",
            "type":"Services"
        }
    ],
    "sg:phone":"+61 8 8370 5751",
    "sg:postcode":"5159",
    "sg:province":"SA",
    "sg:tags":[
        "naturopath"
    ],
    "wof:name":"Bandiera S",
    "wof:placetype":"venue"
},
  "geometry": {"coordinates":[138.59992980999999,-35.0746116638],"type":"Point"}
}