{
  "type": "Feature",
  "properties": {
    "addr:full":"635 Brunswick St Fitzroy North VIC 3068",
    "addr:housenumber":"635",
    "addr:postcode":"3068",
    "addr:street":"Brunswick St",
    "iso:country":"AU",
    "sg:address":"635 Brunswick St",
    "sg:city":"Fitzroy North",
    "sg:classifiers":[
        {
            "category":"Shopping",
            "subcategory":"Jewelry",
            "type":"Retail Goods"
        }
    ],
    "sg:phone":"+61 3 9497 8121",
    "sg:postcode":"3068",
    "sg:province":"VIC",
    "sg:tags":[
        "jeweller"
    ],
    "wof:name":"Pieces Of Eight",
    "wof:placetype":"venue"
},
  "geometry": {"coordinates":[144.980026245,-37.7880210876],"type":"Point"}
}