{
  "type": "Feature",
  "properties": {
    "iso:country":"AU",
    "sg:address":"104 Havannah St",
    "sg:city":"Bathurst",
    "sg:classifiers":[
        {
            "category":"Home & Garden",
            "subcategory":"Garden Supply",
            "type":"Retail Goods"
        }
    ],
    "sg:phone":"+61 2 6332 3111",
    "sg:postcode":"2795",
    "sg:province":"NSW",
    "sg:tags":[
        "landscape"
    ],
    "wof:name":"Hothams Sand, Soil & Gravel Supplies",
    "wof:placetype":"venue"
},
  "geometry": {"coordinates":[149.565063477,-33.4371643066],"type":"Point"}
}