{
  "type": "Feature",
  "properties": {
    "addr:full":"69A Korong Rd cnr Northern Rd, Heidelberg VIC 3084",
    "addr:housenumber":"69a",
    "addr:postcode":"3084",
    "addr:street":"Korong Rd Cnr Northern Rd",
    "iso:country":"AU",
    "sg:address":"69A Korong Rd",
    "sg:city":"cnr Northern Rd, Heidelberg",
    "sg:classifiers":[
        {
            "category":"Retail",
            "subcategory":"Auto Repair",
            "type":"Services"
        }
    ],
    "sg:phone":"+61 3 9459 6127",
    "sg:postcode":"3084",
    "sg:province":"VIC",
    "sg:tags":[
        "beater",
        "painter",
        "panel"
    ],
    "wof:name":"Complete Collision Group - Heidelberg",
    "wof:placetype":"venue"
},
  "geometry": {"coordinates":[145.05987548799999,-37.7305870056],"type":"Point"}
}