{
  "type": "Feature",
  "properties": {
    "addr:full":"PO Box 102 Ballajura WA 6066",
    "addr:postcode":"6066",
    "iso:country":"AU",
    "sg:address":"PO Box 102",
    "sg:city":"Ballajura",
    "sg:classifiers":[
        {
            "category":"Real Estate",
            "subcategory":"Real Estate Agent",
            "type":"Services"
        }
    ],
    "sg:phone":"+61 412 191 988",
    "sg:postcode":"6066",
    "sg:province":"WA",
    "wof:name":"Major Realty",
    "wof:placetype":"venue"
},
  "geometry": {"coordinates":[115.897216797,-31.8382892609],"type":"Point"}
}