{
  "type": "Feature",
  "properties": {
    "addr:full":"Lot 97 Barnes Rd Wubin WA 6612",
    "addr:postcode":"6612",
    "addr:street":"Barnes Rd",
    "iso:country":"AU",
    "sg:address":"Lot 97 Barnes Rd",
    "sg:city":"Wubin",
    "sg:classifiers":[
        {
            "category":"Farming",
            "subcategory":"Farm",
            "type":"Manufacturing & Wholesale Goods"
        }
    ],
    "sg:phone":"+61 8 9668 1032",
    "sg:postcode":"6612",
    "sg:province":"WA",
    "sg:tags":[
        "farmer"
    ],
    "wof:name":"Barnes A J & J A",
    "wof:placetype":"venue"
},
  "geometry": {"coordinates":[116.507949829,-30.1397857666],"type":"Point"}
}