{
  "type": "Feature",
  "properties": {
    "iso:country":"AU",
    "sg:address":"147a King St",
    "sg:city":"Sydney",
    "sg:classifiers":[
        {
            "category":"Health Services",
            "subcategory":"Doctor",
            "type":"Services"
        }
    ],
    "sg:phone":"+61 2 9223 2991",
    "sg:postcode":"2000",
    "sg:province":"NSW",
    "sg:tags":[
        "occupational",
        "safety"
    ],
    "wof:name":"Work To Health and Safety",
    "wof:placetype":"venue"
},
  "geometry": {"coordinates":[151.20930480999999,-33.8691215515],"type":"Point"}
}