{
  "type": "Feature",
  "properties": {
    "addr:full":"PO Box 3137 Erina NSW 2250",
    "addr:postcode":"2250",
    "iso:country":"AU",
    "sg:address":"PO Box 3137",
    "sg:city":"Erina",
    "sg:classifiers":[
        {
            "category":"Professional",
            "subcategory":"Secretarial Services",
            "type":"Services"
        }
    ],
    "sg:phone":"+61 2 4367 2664",
    "sg:postcode":"2250",
    "sg:province":"NSW",
    "sg:tags":[
        "typing"
    ],
    "wof:name":"Accounts On Call",
    "wof:placetype":"venue"
},
  "geometry": {"coordinates":[151.395217895,-33.4346389771],"type":"Point"}
}