{
  "type": "Feature",
  "properties": {
    "iso:country":"AU",
    "sg:address":"373 Glen Osmond Rd",
    "sg:city":"Glen Osmond",
    "sg:classifiers":[
        {
            "category":"Travel",
            "subcategory":"Hotels & Motels",
            "type":"Entertainment"
        }
    ],
    "sg:phone":"+61 8 8379 1601",
    "sg:postcode":"5064",
    "sg:province":"SA",
    "wof:name":"Jacksons Motor Inn",
    "wof:placetype":"venue"
},
  "geometry": {"coordinates":[138.64169311500001,-34.9602966309],"type":"Point"}
}