{
  "type": "Feature",
  "properties": {
    "addr:full":"91 Wood St White Gum Valley WA 6162",
    "addr:housenumber":"91",
    "addr:postcode":"6162",
    "addr:street":"Wood St",
    "iso:country":"AU",
    "sg:address":"91 Wood St",
    "sg:city":"White Gum Valley",
    "sg:classifiers":[
        {
            "category":"Building & Trades",
            "subcategory":"Construction",
            "type":"Services"
        }
    ],
    "sg:phone":"+61 418 920 259",
    "sg:postcode":"6162",
    "sg:province":"WA",
    "sg:tags":[
        "joiner",
        "carpenter"
    ],
    "wof:name":"Sink Or Swim",
    "wof:placetype":"venue"
},
  "geometry": {"coordinates":[115.763741,-32.063126],"type":"Point"}
}