{
  "type": "Feature",
  "properties": {
    "iso:country":"AU",
    "sg:address":"Havana Rd (East)",
    "sg:city":"Coolum Beach",
    "sg:classifiers":[
        {
            "category":"Education",
            "subcategory":"School",
            "type":"Public Place"
        }
    ],
    "sg:phone":"+61 7 5471 5333",
    "sg:postcode":"4573",
    "sg:province":"QLD",
    "sg:tags":[
        "state",
        "except",
        "nsw"
    ],
    "wof:name":"Coolum High School",
    "wof:placetype":"venue"
},
  "geometry": {"coordinates":[153.07545500000001,-26.53541],"type":"Point"}
}