{
  "type": "Feature",
  "properties": {
    "iso:country":"AU",
    "sg:address":"8/ 53 Prindiville Drv",
    "sg:city":"Wangara",
    "sg:classifiers":[
        {
            "category":"Home & Garden",
            "subcategory":"Furniture",
            "type":"Retail Goods"
        }
    ],
    "sg:phone":"+61 8 9309 6124",
    "sg:postcode":"6065",
    "sg:province":"WA",
    "sg:tags":[
        "outdoor"
    ],
    "wof:name":"E & S Enterprises",
    "wof:placetype":"venue"
},
  "geometry": {"coordinates":[115.82469940199999,-31.7909412384],"type":"Point"}
}