{
  "type": "Feature",
  "properties": {
    "iso:country":"AU",
    "sg:address":"29 Belmore Rd",
    "sg:city":"Randwick",
    "sg:classifiers":[
        {
            "category":"Health Services",
            "subcategory":"Dentist",
            "type":"Services"
        }
    ],
    "sg:phone":"+61 2 9398 5251",
    "sg:postcode":"2031",
    "sg:province":"NSW",
    "wof:name":"Urwand Daniel Dr",
    "wof:placetype":"venue"
},
  "geometry": {"coordinates":[151.23992919899999,-33.9136123657],"type":"Point"}
}