{
  "type": "Feature",
  "properties": {
    "iso:country":"AU",
    "sg:address":"5 Linda Crs",
    "sg:city":"Ferntree Gully",
    "sg:classifiers":[
        {
            "category":"Personal",
            "subcategory":"Beauty Salon",
            "type":"Services"
        }
    ],
    "sg:phone":"+61 408 627 818",
    "sg:postcode":"3156",
    "sg:province":"VIC",
    "sg:tags":[
        "supply",
        "artist",
        "make-up"
    ],
    "wof:name":"All Dolled Up Make-Up Services",
    "wof:placetype":"venue"
},
  "geometry": {"coordinates":[145.29524230999999,-37.8827018738],"type":"Point"}
}