{
  "type": "Feature",
  "properties": {
    "iso:country":"AU",
    "sg:address":"65 Jennings St",
    "sg:city":"Curtin",
    "sg:classifiers":[
        {
            "category":"Banks & Credit Unions",
            "subcategory":"Investment Brokerage",
            "type":"Services"
        }
    ],
    "sg:phone":"+61 412 473 182",
    "sg:postcode":"2605",
    "sg:province":"ACT",
    "sg:tags":[
        "debt",
        "collection"
    ],
    "wof:name":"Harleys Collection Services",
    "wof:placetype":"venue"
},
  "geometry": {"coordinates":[149.074310303,-35.3247642517],"type":"Point"}
}