{
  "type": "Feature",
  "properties": {
    "iso:country":"AU",
    "sg:address":"Jenkins St",
    "sg:city":"Port Pirie",
    "sg:classifiers":[
        {
            "category":"Education",
            "subcategory":"School",
            "type":"Public Place"
        }
    ],
    "sg:phone":"+61 8 8632 3172",
    "sg:postcode":"5540",
    "sg:province":"SA",
    "wof:name":"St Marks College Infant School",
    "wof:placetype":"venue"
},
  "geometry": {"coordinates":[137.996582031,-33.195980072],"type":"Point"}
}