{
  "type": "Feature",
  "properties": {
    "addr:full":"Unit 2, 15 Garema Cct Kingsgrove NSW 2208",
    "addr:housenumber":"15",
    "addr:postcode":"2208",
    "addr:street":"Garema Cct",
    "iso:country":"AU",
    "sg:address":"Unit 2, 15",
    "sg:city":"Garema Cct Kingsgrove",
    "sg:classifiers":[
        {
            "category":"Professional",
            "subcategory":"Detective & Security Services",
            "type":"Services"
        }
    ],
    "sg:phone":"+61 2 9750 7355",
    "sg:postcode":"2208",
    "sg:province":"NSW",
    "sg:tags":[
        "equipment",
        "window",
        "doors"
    ],
    "wof:name":"Alexandria Wrought Iron Works",
    "wof:placetype":"venue"
},
  "geometry": {"coordinates":[151.09435999999999,-33.937416],"type":"Point"}
}