{
  "type": "Feature",
  "properties": {
    "addr:full":"Norwest Business Park Suite 6 04, Level 6 Baulkham Hills NSW 2153",
    "addr:housenumber":"04 level 6",
    "addr:postcode":"2153",
    "iso:country":"AU",
    "sg:address":"Norwest Business Park Suite 6",
    "sg:city":"04, Level 6 Baulkham Hills",
    "sg:classifiers":[
        {
            "category":"Professional",
            "subcategory":"Employment Agencies",
            "type":"Services"
        }
    ],
    "sg:phone":"+61 2 9659 0255",
    "sg:postcode":"2153",
    "sg:province":"NSW",
    "wof:name":"Hudson",
    "wof:placetype":"venue"
},
  "geometry": {"coordinates":[150.97525024399999,-33.7621879578],"type":"Point"}
}