{
  "type": "Feature",
  "properties": {
    "addr:full":"292 Great Eastern Hwy Ascot WA 6104",
    "addr:housenumber":"292",
    "addr:postcode":"6104",
    "addr:street":"Great Eastern Hwy",
    "iso:country":"AU",
    "sg:address":"292 Great Eastern Hwy",
    "sg:city":"Ascot",
    "sg:classifiers":[
        {
            "category":"Retail",
            "subcategory":"Auto Rental",
            "type":"Services"
        }
    ],
    "sg:phone":"+61 8 9277 9404",
    "sg:postcode":"6104",
    "sg:province":"WA",
    "sg:tags":[
        "car",
        "hire",
        "minibus"
    ],
    "wof:name":"Cheapy Car Rental",
    "wof:placetype":"venue"
},
  "geometry": {"coordinates":[115.94566345200001,-31.9292793274],"type":"Point"}
}