{
  "type": "Feature",
  "properties": {
    "iso:country":"AU",
    "sg:address":"Mulga St",
    "sg:city":"Mt Gambier",
    "sg:classifiers":[
        {
            "category":"Education",
            "subcategory":"School",
            "type":"Public Place"
        }
    ],
    "sg:phone":"+61 8 8725 9955",
    "sg:postcode":"5290",
    "sg:province":"SA",
    "sg:tags":[
        "state",
        "except",
        "nsw"
    ],
    "wof:name":"Mulga St Primary School",
    "wof:placetype":"venue"
},
  "geometry": {"coordinates":[140.761047,-37.813046],"type":"Point"}
}