{
  "type": "Feature",
  "properties": {
    "iso:country":"AU",
    "sg:address":"PO Box 323",
    "sg:city":"Belmont",
    "sg:classifiers":[
        {
            "category":"Mining & Drilling",
            "type":"Manufacturing & Wholesale Goods"
        }
    ],
    "sg:phone":"+61 8 9477 3344",
    "sg:postcode":"6984",
    "sg:province":"WA",
    "sg:tags":[
        "concrete",
        "breaking",
        "grinding",
        "sawing"
    ],
    "wof:name":"Mr Cut Concrete Cutting And Core Drilling",
    "wof:placetype":"venue"
},
  "geometry": {"coordinates":[115.921379,-31.955561],"type":"Point"}
}