{
  "type": "Feature",
  "properties": {
    "iso:country":"AU",
    "sg:address":"22 South St",
    "sg:city":"Allora",
    "sg:classifiers":[
        {
            "category":"Wholesale",
            "subcategory":"Apparel",
            "type":"Manufacturing & Wholesale Goods"
        }
    ],
    "sg:phone":"+61 7 4666 3266",
    "sg:postcode":"4362",
    "sg:province":"QLD",
    "sg:tags":[
        "wholesaler",
        "mfrs",
        "silo"
    ],
    "wof:name":"Denny's Engineering & Welding Pty Ltd",
    "wof:placetype":"venue"
},
  "geometry": {"coordinates":[151.98078918499999,-28.0405502319],"type":"Point"}
}