{
  "type": "Feature",
  "properties": {
    "addr:full":"Princes Hwy Dapto NSW 2530",
    "addr:postcode":"2530",
    "addr:street":"Princes Hwy",
    "iso:country":"AU",
    "sg:address":"Princes Hwy",
    "sg:city":"Dapto",
    "sg:classifiers":[
        {
            "category":"Shopping",
            "subcategory":"Clothing, Apparel, & Fashions",
            "type":"Retail Goods"
        }
    ],
    "sg:phone":"+61 2 4262 8102",
    "sg:postcode":"2530",
    "sg:province":"NSW",
    "sg:tags":[
        "recycled",
        "clothing"
    ],
    "wof:name":"Salvos Stores",
    "wof:placetype":"venue"
},
  "geometry": {"coordinates":[150.791671753,-34.4977264404],"type":"Point"}
}