{
  "type": "Feature",
  "properties": {
    "addr:full":"160 Main St West Wyalong NSW 2671",
    "addr:housenumber":"160",
    "addr:postcode":"2671",
    "addr:street":"Main St West",
    "iso:country":"AU",
    "sg:address":"160 Main St",
    "sg:city":"West Wyalong",
    "sg:classifiers":[
        {
            "category":"Shopping",
            "subcategory":"Crafts & Fabrics",
            "type":"Retail Goods"
        }
    ],
    "sg:phone":"+61 2 6972 0252",
    "sg:postcode":"2671",
    "sg:province":"NSW",
    "sg:tags":[
        "supply"
    ],
    "wof:name":"Bland Bizarre Incorporated",
    "wof:placetype":"venue"
},
  "geometry": {"coordinates":[147.201416016,-33.9222717285],"type":"Point"}
}