{
  "type": "Feature",
  "properties": {
    "addr:full":"72 Mickle Crs Warrnambool VIC 3280",
    "addr:housenumber":"72",
    "addr:postcode":"3280",
    "addr:street":"Mickle Crs",
    "iso:country":"AU",
    "sg:address":"72 Mickle Crs",
    "sg:city":"Warrnambool",
    "sg:classifiers":[
        {
            "category":"Building & Trades",
            "subcategory":"Construction",
            "type":"Services"
        }
    ],
    "sg:phone":"+61 3 5561 7117",
    "sg:postcode":"3280",
    "sg:province":"VIC",
    "sg:tags":[
        "contractor"
    ],
    "wof:name":"Carlin D J & S A Builders",
    "wof:placetype":"venue"
},
  "geometry": {"coordinates":[142.49148559599999,-38.374912262],"type":"Point"}
}