{
  "type": "Feature",
  "properties": {
    "addr:full":"30 Rowes Rd Geeveston TAS 7116",
    "addr:housenumber":"30",
    "addr:postcode":"7116",
    "addr:street":"Rowes Rd",
    "iso:country":"AU",
    "sg:address":"30 Rowes Rd",
    "sg:city":"Geeveston",
    "sg:classifiers":[
        {
            "category":"Building & Trades",
            "subcategory":"Plumbing",
            "type":"Services"
        }
    ],
    "sg:phone":"+61 408 054 055",
    "sg:postcode":"7116",
    "sg:province":"TAS",
    "sg:tags":[
        "plumber",
        "gasfitters"
    ],
    "wof:name":"Andrew Carr",
    "wof:placetype":"venue"
},
  "geometry": {"coordinates":[146.92930602999999,-43.1763725281],"type":"Point"}
}