{
  "type": "Feature",
  "properties": {
    "addr:full":"Cnr Corporation & Dominions Rds Ashmore QLD 4214",
    "addr:postcode":"4214",
    "iso:country":"AU",
    "sg:address":"Cnr Corporation & Dominions Rds",
    "sg:city":"Ashmore",
    "sg:classifiers":[
        {
            "category":"Health Services",
            "subcategory":"Health Practitioner",
            "type":"Services"
        }
    ],
    "sg:phone":"+61 7 5539 5998",
    "sg:postcode":"4214",
    "sg:province":"QLD",
    "sg:tags":[
        "physiotherapist"
    ],
    "wof:name":"A All Sports Natural Healing Clinic",
    "wof:placetype":"venue"
},
  "geometry": {"coordinates":[153.383636475,-27.9818649292],"type":"Point"}
}