{
  "type": "Feature",
  "properties": {
    "addr:full":"Unit 3, 1 Aitken Way Kewdale WA 6105",
    "addr:housenumber":"1",
    "addr:postcode":"6105",
    "addr:street":"Aitken Way",
    "iso:country":"AU",
    "sg:address":"Unit 3, 1 Aitken Way",
    "sg:city":"Kewdale",
    "sg:classifiers":[
        {
            "category":"Retail",
            "subcategory":"Auto Rental",
            "type":"Services"
        }
    ],
    "sg:phone":"+61 8 9353 1044",
    "sg:postcode":"6105",
    "sg:province":"WA",
    "sg:tags":[
        "bus",
        "truck"
    ],
    "wof:name":"Jaspals Rentals",
    "wof:placetype":"venue"
},
  "geometry": {"coordinates":[115.96421814,-31.9766540527],"type":"Point"}
}