{
  "type": "Feature",
  "properties": {
    "addr:full":"Shop 8/ 727 Nicklin Way Currimundi QLD 4551",
    "addr:housenumber":"shop 8 / 727",
    "addr:postcode":"4551",
    "addr:street":"Nicklin Way",
    "iso:country":"AU",
    "sg:address":"Shop 8/ 727 Nicklin Way",
    "sg:city":"Currimundi",
    "sg:classifiers":[
        {
            "category":"Building & Trades",
            "subcategory":"Locksmith",
            "type":"Services"
        }
    ],
    "sg:phone":"+61 7 5493 4844",
    "sg:postcode":"4551",
    "sg:province":"QLD",
    "sg:tags":[
        "strongroom",
        "safe",
        "door"
    ],
    "wof:name":"Winston Quality Locksmiths",
    "wof:placetype":"venue"
},
  "geometry": {"coordinates":[153.122970581,-26.7699356079],"type":"Point"}
}