{
  "type": "Feature",
  "properties": {
    "addr:full":"491 Warrigal Rd Moorabbin VIC 3189",
    "addr:housenumber":"491",
    "addr:postcode":"3189",
    "addr:street":"Warrigal Rd",
    "iso:country":"AU",
    "sg:address":"491 Warrigal Rd",
    "sg:city":"Moorabbin",
    "sg:classifiers":[
        {
            "category":"Autos & Motor Vehicles",
            "subcategory":"Automobile Sales",
            "type":"Retail Goods"
        }
    ],
    "sg:phone":"+61 3 9555 9188",
    "sg:postcode":"3189",
    "sg:province":"VIC",
    "sg:tags":[
        "car",
        "used"
    ],
    "wof:name":"Tony Taranto Motors",
    "wof:placetype":"venue"
},
  "geometry": {"coordinates":[145.078567505,-37.9429016113],"type":"Point"}
}