{
  "type": "Feature",
  "properties": {
    "addr:full":"135 Queen St Woollahra NSW 2025",
    "addr:housenumber":"135",
    "addr:postcode":"2025",
    "addr:street":"Queen St",
    "iso:country":"AU",
    "sg:address":"135 Queen St",
    "sg:city":"Woollahra",
    "sg:classifiers":[
        {
            "category":"Government",
            "subcategory":"Fire Station",
            "type":"Public Place"
        }
    ],
    "sg:phone":"+61 2 9362 4922",
    "sg:postcode":"2025",
    "sg:province":"NSW",
    "sg:tags":[
        "cooling",
        "tower"
    ],
    "wof:name":"Water Control Services",
    "wof:placetype":"venue"
},
  "geometry": {"coordinates":[151.23945617699999,-33.8881454468],"type":"Point"}
}