{
  "type": "Feature",
  "properties": {
    "addr:full":"7 Millet St Joondanna WA 6060",
    "addr:housenumber":"7",
    "addr:postcode":"6060",
    "addr:street":"Millet St",
    "iso:country":"AU",
    "sg:address":"7 Millet St",
    "sg:city":"Joondanna",
    "sg:classifiers":[
        {
            "category":"Health Services",
            "subcategory":"Health Practitioner",
            "type":"Services"
        }
    ],
    "sg:phone":"+61 431 907 965",
    "sg:postcode":"6060",
    "sg:province":"WA",
    "sg:tags":[
        "pathologist",
        "speech"
    ],
    "wof:name":"Lyn Goodwin Speech Pathology",
    "wof:placetype":"venue"
},
  "geometry": {"coordinates":[115.843360901,-31.9117412567],"type":"Point"}
}