{
  "type": "Feature",
  "properties": {
    "addr:full":"Lvl2/ 55 Norton St Leichhardt NSW 2040",
    "addr:housenumber":"55",
    "addr:postcode":"2040",
    "addr:street":"Norton St",
    "iso:country":"AU",
    "sg:address":"Lvl2/ 55 Norton St",
    "sg:city":"Leichhardt",
    "sg:classifiers":[
        {
            "category":"Professional",
            "subcategory":"Computer Services",
            "type":"Services"
        }
    ],
    "sg:phone":"+61 2 9564 3663",
    "sg:postcode":"2040",
    "sg:province":"NSW",
    "sg:tags":[
        "consultant",
        "system"
    ],
    "wof:name":"Sicab Computer Services Pty Ltd",
    "wof:placetype":"venue"
},
  "geometry": {"coordinates":[151.15739400000001,-33.887421],"type":"Point"}
}