{
  "type": "Feature",
  "properties": {
    "addr:full":"73 Langson Ave Figtree NSW 2525",
    "addr:housenumber":"73",
    "addr:postcode":"2525",
    "addr:street":"Langson Ave",
    "iso:country":"AU",
    "sg:address":"73 Langson Ave",
    "sg:city":"Figtree",
    "sg:classifiers":[
        {
            "category":"Education",
            "subcategory":"Special Training",
            "type":"Public Place"
        }
    ],
    "sg:phone":"+61 411 203 409",
    "sg:postcode":"2525",
    "sg:province":"NSW",
    "sg:tags":[
        "development"
    ],
    "wof:name":"Beneficial Training Services",
    "wof:placetype":"venue"
},
  "geometry": {"coordinates":[150.85708618199999,-34.4213981628],"type":"Point"}
}