{
  "type": "Feature",
  "properties": {
    "iso:country":"AU",
    "sg:address":"175 Grattan St",
    "sg:city":"Carlton",
    "sg:classifiers":[
        {
            "category":"Professional",
            "subcategory":"Management & Consulting",
            "type":"Services"
        }
    ],
    "sg:phone":"+61 3 9349 4077",
    "sg:postcode":"3053",
    "sg:province":"VIC",
    "sg:tags":[
        "consultant",
        "migration"
    ],
    "wof:name":"immigrate OZ",
    "wof:placetype":"venue"
},
  "geometry": {"coordinates":[144.963134766,-37.8004455566],"type":"Point"}
}