{
  "type": "Feature",
  "properties": {
    "addr:full":"35 Gunn St Wentworth NSW 2648",
    "addr:housenumber":"35",
    "addr:postcode":"2648",
    "addr:street":"Gunn St",
    "iso:country":"AU",
    "sg:address":"35 Gunn St",
    "sg:city":"Wentworth",
    "sg:classifiers":[
        {
            "category":"Building & Trades",
            "subcategory":"Construction",
            "type":"Services"
        }
    ],
    "sg:phone":"+61 407 272 532",
    "sg:postcode":"2648",
    "sg:province":"NSW",
    "sg:tags":[
        "window",
        "tinting"
    ],
    "wof:name":"Shady Tinting",
    "wof:placetype":"venue"
},
  "geometry": {"coordinates":[141.92562899999999,-34.103058],"type":"Point"}
}