{
  "type": "Feature",
  "properties": {
    "addr:full":"4 Council St Wallsend NSW 2287",
    "addr:housenumber":"4",
    "addr:postcode":"2287",
    "addr:street":"Council St",
    "iso:country":"AU",
    "sg:address":"4 Council St",
    "sg:city":"Wallsend",
    "sg:classifiers":[
        {
            "category":"Health Services",
            "subcategory":"Doctor",
            "type":"Services"
        }
    ],
    "sg:phone":"+61 2 4950 0600",
    "sg:postcode":"2287",
    "sg:province":"NSW",
    "sg:tags":[
        "medical",
        "practitioner"
    ],
    "wof:name":"Laycock Lee",
    "wof:placetype":"venue"
},
  "geometry": {"coordinates":[151.66859435999999,-32.9027824402],"type":"Point"}
}