{
  "type": "Feature",
  "properties": {
    "addr:full":"1/ 143 Point Nepean Rd Dromana VIC 3936",
    "addr:housenumber":"/ 143",
    "addr:postcode":"3936",
    "addr:street":"Nepean Rd",
    "iso:country":"AU",
    "sg:address":"1/ 143 Point Nepean Rd",
    "sg:city":"Dromana",
    "sg:classifiers":[
        {
            "category":"Health Services",
            "subcategory":"Optometrist",
            "type":"Services"
        }
    ],
    "sg:phone":"+61 3 5981 0701",
    "sg:postcode":"3936",
    "sg:province":"VIC",
    "wof:name":"Eyes On",
    "wof:placetype":"venue"
},
  "geometry": {"coordinates":[144.96286010700001,-38.3338012695],"type":"Point"}
}