{
  "type": "Feature",
  "properties": {
    "addr:full":"940 Centre Rd Oakleigh South VIC 3167",
    "addr:housenumber":"940",
    "addr:postcode":"3167",
    "addr:street":"Centre Rd",
    "iso:country":"AU",
    "sg:address":"940 Centre Rd",
    "sg:city":"Oakleigh South",
    "sg:classifiers":[
        {
            "category":"Manufacturing",
            "subcategory":"Musical Instruments",
            "type":"Manufacturing & Wholesale Goods"
        }
    ],
    "sg:phone":"+61 3 9563 8711",
    "sg:postcode":"3167",
    "sg:province":"VIC",
    "sg:tags":[
        "repair",
        "maker"
    ],
    "wof:name":"Adbend Pty Ltd",
    "wof:placetype":"venue"
},
  "geometry": {"coordinates":[145.08273315400001,-37.9240837097],"type":"Point"}
}