{
  "type": "Feature",
  "properties": {
    "addr:full":"PO Box 939 Sandy Bay TAS 7006",
    "addr:postcode":"7006",
    "iso:country":"AU",
    "sg:address":"PO Box 939",
    "sg:city":"Sandy Bay",
    "sg:classifiers":[
        {
            "category":"Wholesale",
            "subcategory":"Drugs",
            "type":"Manufacturing & Wholesale Goods"
        }
    ],
    "sg:phone":"+61 3 6227 8382",
    "sg:postcode":"7006",
    "sg:province":"TAS",
    "sg:tags":[
        "wholesaler",
        "pharmaceutical",
        "product",
        "mfrs"
    ],
    "wof:name":"Snore Stopper P/L",
    "wof:placetype":"venue"
},
  "geometry": {"coordinates":[147.35438537600001,-42.9128265381],"type":"Point"}
}