{
  "type": "Feature",
  "properties": {
    "addr:full":"5 Horizon Drv Salamander Bay NSW 2317",
    "addr:housenumber":"5",
    "addr:postcode":"2317",
    "addr:street":"Horizon Drv",
    "iso:country":"AU",
    "sg:address":"5 Horizon Drv",
    "sg:city":"Salamander Bay",
    "sg:classifiers":[
        {
            "category":"Sports & Exercise",
            "subcategory":"Golf",
            "type":"Entertainment"
        }
    ],
    "sg:phone":"+61 2 4982 0188",
    "sg:postcode":"2317",
    "sg:province":"NSW",
    "sg:tags":[
        "club"
    ],
    "wof:name":"Horizons Golf Club",
    "wof:placetype":"venue"
},
  "geometry": {"coordinates":[152.09103400000001,-32.738911],"type":"Point"}
}