{
  "type": "Feature",
  "properties": {
    "addr:full":"21 Brierly St Weston ACT 2611",
    "addr:housenumber":"21",
    "addr:postcode":"2611",
    "addr:street":"Brierly St",
    "iso:country":"AU",
    "sg:address":"21 Brierly St",
    "sg:city":"Weston",
    "sg:classifiers":[
        {
            "category":"Retail",
            "subcategory":"Event Space",
            "type":"Services"
        }
    ],
    "sg:phone":"+61 2 6288 9563",
    "sg:postcode":"2611",
    "sg:province":"ACT",
    "sg:tags":[
        "function",
        "organiser"
    ],
    "wof:name":"Portellies Trattoria",
    "wof:placetype":"venue"
},
  "geometry": {"coordinates":[149.052124023,-35.3416213989],"type":"Point"}
}