{
  "type": "Feature",
  "properties": {
    "addr:full":"6 Cawdor Farm Rd Camden NSW 2570",
    "addr:housenumber":"6",
    "addr:postcode":"2570",
    "addr:street":"Cawdor Farm Rd",
    "iso:country":"AU",
    "sg:address":"6 Cawdor Farm Rd",
    "sg:city":"Camden",
    "sg:classifiers":[
        {
            "category":"Organizations",
            "subcategory":"Professional Association",
            "type":"Services"
        }
    ],
    "sg:phone":"+61 2 4655 5886",
    "sg:postcode":"2570",
    "sg:province":"NSW",
    "sg:tags":[
        "web",
        "internet"
    ],
    "wof:name":"Swallow Computer Solutions",
    "wof:placetype":"venue"
},
  "geometry": {"coordinates":[150.663406372,-34.0549468994],"type":"Point"}
}