{
  "type": "Feature",
  "properties": {
    "addr:full":"1/ 31 Ern Harley Drv Burleigh Heads QLD 4220",
    "addr:housenumber":"/ 31",
    "addr:postcode":"4220",
    "addr:street":"Ern Harley Drv",
    "iso:country":"AU",
    "sg:address":"1/ 31 Ern Harley Drv",
    "sg:city":"Burleigh Heads",
    "sg:classifiers":[
        {
            "category":"Manufacturing",
            "subcategory":"Glass & Minerals",
            "type":"Manufacturing & Wholesale Goods"
        }
    ],
    "sg:phone":"+61 7 5522 0350",
    "sg:postcode":"4220",
    "sg:province":"QLD",
    "sg:tags":[
        "fabricator",
        "fibreglass"
    ],
    "wof:name":"M & C Fiberglass",
    "wof:placetype":"venue"
},
  "geometry": {"coordinates":[153.414886475,-28.1025447845],"type":"Point"}
}