{
  "type": "Feature",
  "properties": {
    "addr:full":"Shop 33, Hedland Shopping Cntr South Hedland WA 6722",
    "addr:housenumber":"shop 33",
    "addr:postcode":"6722",
    "addr:street":"Shopping",
    "iso:country":"AU",
    "sg:address":"Shop 33, Hedland Shopping Cntr",
    "sg:city":"South Hedland",
    "sg:classifiers":[
        {
            "category":"Professional",
            "type":"Services"
        }
    ],
    "sg:phone":"+61 1800 801 294",
    "sg:postcode":"6722",
    "sg:province":"WA",
    "sg:tags":[
        "courier"
    ],
    "wof:name":"Greyhound Pioneer",
    "wof:placetype":"venue"
},
  "geometry": {"coordinates":[118.60131072999999,-20.4081993103],"type":"Point"}
}