{
  "type": "Feature",
  "properties": {
    "addr:full":"First Floor 19 Aplin St Cairns QLD 4870",
    "addr:housenumber":"19",
    "addr:postcode":"4870",
    "addr:street":"Floor;St",
    "iso:country":"AU",
    "sg:address":"First Floor 19 Aplin St",
    "sg:city":"Cairns",
    "sg:classifiers":[
        {
            "category":"Travel",
            "subcategory":"Travel Agent",
            "type":"Entertainment"
        }
    ],
    "sg:phone":"+61 7 4031 1551",
    "sg:postcode":"4870",
    "sg:province":"QLD",
    "sg:tags":[
        "consultant"
    ],
    "wof:name":"Kintetsu International Express",
    "wof:placetype":"venue"
},
  "geometry": {"coordinates":[145.77276611299999,-16.9218101501],"type":"Point"}
}