{
  "type": "Feature",
  "properties": {
    "iso:country":"AU",
    "sg:address":"8 Centrepoint Mall Denny St",
    "sg:city":"Berri",
    "sg:classifiers":[
        {
            "category":"Professional",
            "subcategory":"Accounting & Tax Preparation",
            "type":"Services"
        }
    ],
    "sg:phone":"+61 8 8582 3320",
    "sg:postcode":"5343",
    "sg:province":"SA",
    "sg:tags":[
        "consultant",
        "taxation"
    ],
    "wof:name":"Nagy Ron",
    "wof:placetype":"venue"
},
  "geometry": {"coordinates":[140.601486206,-34.2867431641],"type":"Point"}
}