{
  "type": "Feature",
  "properties": {
    "addr:full":"186 Springvale Rd Glen Waverley VIC 3150",
    "addr:housenumber":"186",
    "addr:postcode":"3150",
    "addr:street":"Springvale Rd",
    "iso:country":"AU",
    "sg:address":"186 Springvale Rd",
    "sg:city":"Glen Waverley",
    "sg:classifiers":[
        {
            "category":"Travel",
            "subcategory":"Hotels & Motels",
            "type":"Entertainment"
        }
    ],
    "sg:phone":"+61 3 9802 6511",
    "sg:postcode":"3150",
    "sg:province":"VIC",
    "sg:tags":[
        "pub"
    ],
    "wof:name":"Mountain View Hotel",
    "wof:placetype":"venue"
},
  "geometry": {"coordinates":[145.16612243599999,-37.8794746399],"type":"Point"}
}