{
  "type": "Feature",
  "properties": {
    "addr:full":"PO Box 771 Bunbury Private Boxes WA 6231",
    "addr:postcode":"6231",
    "iso:country":"AU",
    "sg:address":"PO Box 771",
    "sg:city":"Bunbury Private Boxes",
    "sg:classifiers":[
        {
            "category":"Professional",
            "subcategory":"Detective & Security Services",
            "type":"Services"
        }
    ],
    "sg:phone":"+61 8 9795 9955",
    "sg:postcode":"6231",
    "sg:province":"WA",
    "sg:tags":[
        "domestic",
        "alarm",
        "commercial",
        "burglar"
    ],
    "wof:name":"Knight Security Systems",
    "wof:placetype":"venue"
},
  "geometry": {"coordinates":[115.636993,-33.32711],"type":"Point"}
}