{
  "type": "Feature",
  "properties": {
    "iso:country":"AU",
    "sg:address":"GPO Laneway 261 Queen St",
    "sg:city":"Brisbane",
    "sg:classifiers":[
        {
            "category":"Organizations",
            "subcategory":"Membership Organization",
            "type":"Services"
        }
    ],
    "sg:phone":"+61 7 3872 8465",
    "sg:postcode":"4000",
    "sg:province":"QLD",
    "sg:tags":[
        "club",
        "car"
    ],
    "wof:name":"RACQ",
    "wof:placetype":"venue"
},
  "geometry": {"coordinates":[153.02784729000001,-27.4677715302],"type":"Point"}
}