{
  "type": "Feature",
  "properties": {
    "addr:full":"1691 Tehan Rd Koyuga VIC 3622",
    "addr:housenumber":"1691",
    "addr:postcode":"3622",
    "addr:street":"Tehan Rd",
    "iso:country":"AU",
    "sg:address":"1691 Tehan Rd",
    "sg:city":"Koyuga",
    "sg:classifiers":[
        {
            "category":"Wholesale",
            "subcategory":"Machinery & Supplies",
            "type":"Manufacturing & Wholesale Goods"
        }
    ],
    "sg:phone":"+61 3 5859 2239",
    "sg:postcode":"3622",
    "sg:province":"VIC",
    "sg:tags":[
        "agricultural"
    ],
    "wof:name":"Tongala Farm Services",
    "wof:placetype":"venue"
},
  "geometry": {"coordinates":[144.868240356,-36.2111167908],"type":"Point"}
}