{
  "type": "Feature",
  "properties": {
    "iso:country":"AU",
    "sg:address":"38Km Arnhem Hwy",
    "sg:city":"Humpty Doo",
    "sg:classifiers":[
        {
            "category":"Building & Trades",
            "subcategory":"Landscaping Services",
            "type":"Services"
        }
    ],
    "sg:phone":"+61 8 8978 8944",
    "sg:postcode":"0836",
    "sg:province":"NT",
    "sg:tags":[
        "firebreak",
        "clearing",
        "land",
        "contractor"
    ],
    "wof:name":"Agtracts",
    "wof:placetype":"venue"
},
  "geometry": {"coordinates":[131.109894,-12.57359],"type":"Point"}
}