{
  "type": "Feature",
  "properties": {
    "iso:country":"AU",
    "sg:address":"Unit 1/ 61 Nepean Hwy",
    "sg:city":"Aspendale",
    "sg:classifiers":[
        {
            "category":"Utilities",
            "subcategory":"Electric",
            "type":"Services"
        }
    ],
    "sg:phone":"+61 418 342 036",
    "sg:postcode":"3195",
    "sg:province":"VIC",
    "sg:tags":[
        "electrical",
        "contractor"
    ],
    "wof:name":"Savage Greg Electrics",
    "wof:placetype":"venue"
},
  "geometry": {"coordinates":[145.09503173799999,-38.0176620483],"type":"Point"}
}