{
  "type": "Feature",
  "properties": {
    "addr:full":"Lot 28 Cranbourne - Franskton Rd Langwarrin VIC 3910",
    "addr:postcode":"3910",
    "addr:street":"Franskton Rd",
    "iso:country":"AU",
    "sg:address":"Lot 28 Cranbourne - Franskton Rd",
    "sg:city":"Langwarrin",
    "sg:classifiers":[
        {
            "category":"Autos & Motor Vehicles",
            "subcategory":"Fuel & Gas Station",
            "type":"Retail Goods"
        }
    ],
    "sg:phone":"+61 3 9789 4887",
    "sg:postcode":"3910",
    "sg:province":"VIC",
    "wof:name":"BP Australia Pty Ltd",
    "wof:placetype":"venue"
},
  "geometry": {"coordinates":[145.173065186,-38.1562728882],"type":"Point"}
}