{
  "type": "Feature",
  "properties": {
    "addr:full":"151 Mostyn St Castlemaine VIC 3450",
    "addr:housenumber":"151",
    "addr:postcode":"3450",
    "addr:street":"Mostyn St",
    "iso:country":"AU",
    "sg:address":"151 Mostyn St",
    "sg:city":"Castlemaine",
    "sg:classifiers":[
        {
            "category":"Professional",
            "subcategory":"Art Services",
            "type":"Services"
        }
    ],
    "sg:phone":"+61 3 5472 3377",
    "sg:postcode":"3450",
    "sg:province":"VIC",
    "sg:tags":[
        "graphic",
        "designer"
    ],
    "wof:name":"Meg Norris Design",
    "wof:placetype":"venue"
},
  "geometry": {"coordinates":[144.22268676799999,-37.0660934448],"type":"Point"}
}