{
  "type": "Feature",
  "properties": {
    "iso:country":"AU",
    "sg:address":"Unit 5/6 30 Sustainable Ave",
    "sg:city":"Bibra Lake",
    "sg:classifiers":[
        {
            "category":"Wholesale",
            "subcategory":"Stationery",
            "type":"Manufacturing & Wholesale Goods"
        }
    ],
    "sg:phone":"+61 8 9434 3588",
    "sg:postcode":"6163",
    "sg:province":"WA",
    "sg:tags":[
        "mfrg"
    ],
    "wof:name":"Candor Stationery Manufacturers Pty Ltd",
    "wof:placetype":"venue"
},
  "geometry": {"coordinates":[115.81240099999999,-32.08992],"type":"Point"}
}