{
  "type": "Feature",
  "properties": {
    "addr:full":"88 Delifield Drv Templestowe VIC 3106",
    "addr:housenumber":"88",
    "addr:postcode":"3106",
    "addr:street":"Delifield Drv",
    "iso:country":"AU",
    "sg:address":"88 Delifield Drv",
    "sg:city":"Templestowe",
    "sg:classifiers":[
        {
            "category":"Food & Beverages",
            "subcategory":"Fruits & Vegetables",
            "type":"Retail Goods"
        }
    ],
    "sg:phone":"+61 3 9846 2538",
    "sg:postcode":"3106",
    "sg:province":"VIC",
    "sg:tags":[
        "greengrocer",
        "fruiterer"
    ],
    "wof:name":"Tasmanian Fruit Wholesalers Pty Ltd",
    "wof:placetype":"venue"
},
  "geometry": {"coordinates":[145.12681579599999,-37.7601623535],"type":"Point"}
}