{
  "type": "Feature",
  "properties": {
    "addr:full":"Shop 6 Hosking Crs Glenfield NSW 2167",
    "addr:housenumber":"shop 6",
    "addr:postcode":"2167",
    "addr:street":"Hosking Crs",
    "iso:country":"AU",
    "sg:address":"Shop 6 Hosking Crs",
    "sg:city":"Glenfield",
    "sg:classifiers":[
        {
            "category":"Structure",
            "subcategory":"Bridge",
            "type":"Public Place"
        }
    ],
    "sg:phone":"+61 2 9605 3176",
    "sg:postcode":"2167",
    "sg:province":"NSW",
    "sg:tags":[
        "chainsaw",
        "brushcutters"
    ],
    "wof:name":"Fields Mower Centre",
    "wof:placetype":"venue"
},
  "geometry": {"coordinates":[150.83886718799999,-33.9315338135],"type":"Point"}
}