{
  "type": "Feature",
  "properties": {
    "iso:country":"AU",
    "sg:address":"181 Victoria St",
    "sg:city":"Taree",
    "sg:classifiers":[
        {
            "category":"Health Services",
            "subcategory":"Optometrist",
            "type":"Services"
        }
    ],
    "sg:phone":"+61 2 6552 5044",
    "sg:postcode":"2430",
    "sg:province":"NSW",
    "wof:name":"McKay Peter",
    "wof:placetype":"venue"
},
  "geometry": {"coordinates":[152.46032700000001,-31.913679],"type":"Point"}
}