{
  "type": "Feature",
  "properties": {
    "addr:full":"1621 Ferntree Gully Rd Knoxfield VIC 3180",
    "addr:housenumber":"1621",
    "addr:postcode":"3180",
    "addr:street":"Ferntree Gully Rd",
    "iso:country":"AU",
    "sg:address":"1621 Ferntree Gully Rd",
    "sg:city":"Knoxfield",
    "sg:classifiers":[
        {
            "category":"Health Services",
            "subcategory":"Health Practitioner",
            "type":"Services"
        }
    ],
    "sg:phone":"+61 3 9764 9359",
    "sg:postcode":"3180",
    "sg:province":"VIC",
    "sg:tags":[
        "physiotherapist"
    ],
    "wof:name":"Edwards Trish",
    "wof:placetype":"venue"
},
  "geometry": {"coordinates":[145.252441406,-37.8936080933],"type":"Point"}
}