{
  "type": "Feature",
  "properties": {
    "addr:full":"Unit9/ 170 Boundary Rd Braeside VIC 3195",
    "addr:housenumber":"170",
    "addr:postcode":"3195",
    "addr:street":"Boundary Rd",
    "iso:country":"AU",
    "sg:address":"Unit9/ 170 Boundary Rd",
    "sg:city":"Braeside",
    "sg:classifiers":[
        {
            "category":"Retail",
            "subcategory":"Storage",
            "type":"Services"
        }
    ],
    "sg:phone":"+61 414 223 750",
    "sg:postcode":"3195",
    "sg:province":"VIC",
    "sg:tags":[
        "removal",
        "furniture"
    ],
    "sg:website":"http://www.movingprofessionals.com.au",
    "wof:name":"Mr Moving Man",
    "wof:placetype":"venue"
},
  "geometry": {"coordinates":[145.105743408,-37.999835968],"type":"Point"}
}