{
  "type": "Feature",
  "properties": {
    "addr:full":"6 Bond St Richmond SA 5033",
    "addr:housenumber":"6",
    "addr:postcode":"5033",
    "addr:street":"Bond St",
    "iso:country":"AU",
    "sg:address":"6 Bond St",
    "sg:city":"Richmond",
    "sg:classifiers":[
        {
            "category":"Transit Center",
            "subcategory":"Passenger",
            "type":"Transportation"
        }
    ],
    "sg:phone":"+61 8 8351 8757",
    "sg:postcode":"5033",
    "sg:province":"SA",
    "sg:tags":[
        "wholesaler",
        "mfrs",
        "toiletry",
        "perfume"
    ],
    "wof:name":"Lever J H & Co Pty Ltd",
    "wof:placetype":"venue"
},
  "geometry": {"coordinates":[138.568634033,-34.9414291382],"type":"Point"}
}