{
  "type": "Feature",
  "properties": {
    "addr:full":"226 Moggill Rd Taringa QLD 4068",
    "addr:housenumber":"226",
    "addr:postcode":"4068",
    "addr:street":"Moggill Rd",
    "iso:country":"AU",
    "sg:address":"226 Moggill Rd",
    "sg:city":"Taringa",
    "sg:classifiers":[
        {
            "category":"Health Services",
            "subcategory":"Health Practitioner",
            "type":"Services"
        }
    ],
    "sg:phone":"+61 7 3870 0771",
    "sg:postcode":"4068",
    "sg:province":"QLD",
    "sg:tags":[
        "psychologist"
    ],
    "wof:name":"Dugan Jan",
    "wof:placetype":"venue"
},
  "geometry": {"coordinates":[152.977783203,-27.4932880402],"type":"Point"}
}