{
  "type": "Feature",
  "properties": {
    "addr:full":"Shop 5/ 44 The Horsley Drv Carramar NSW 2163",
    "addr:housenumber":"shop 5 / 44",
    "addr:postcode":"2163",
    "addr:street":"The Horsley Drv",
    "iso:country":"AU",
    "sg:address":"Shop 5/ 44 The Horsley Drv",
    "sg:city":"Carramar",
    "sg:classifiers":[
        {
            "category":"Food & Beverages",
            "subcategory":"Bakery",
            "type":"Retail Goods"
        }
    ],
    "sg:phone":"+61 2 9728 4858",
    "sg:postcode":"2163",
    "sg:province":"NSW",
    "sg:tags":[
        "baker"
    ],
    "wof:name":"Sapori Di Pane",
    "wof:placetype":"venue"
},
  "geometry": {"coordinates":[150.967407227,-33.8850135803],"type":"Point"}
}