{
  "type": "Feature",
  "properties": {
    "addr:full":"383 Port Hacking Rd South Caringbah NSW 2229",
    "addr:housenumber":"383",
    "addr:postcode":"2229",
    "addr:street":"Port Hacking Rd South",
    "iso:country":"AU",
    "sg:address":"383 Port Hacking Rd",
    "sg:city":"South Caringbah",
    "sg:classifiers":[
        {
            "category":"Health Services",
            "subcategory":"Health Practitioner",
            "type":"Services"
        }
    ],
    "sg:phone":"+61 2 9531 2600",
    "sg:postcode":"2229",
    "sg:province":"NSW",
    "sg:tags":[
        "physiotherapist"
    ],
    "wof:name":"Hardman & McCarthy",
    "wof:placetype":"venue"
},
  "geometry": {"coordinates":[151.12307739299999,-34.0451774597],"type":"Point"}
}