{
  "type": "Feature",
  "properties": {
    "iso:country":"AU",
    "sg:address":"113 Reservoir St",
    "sg:city":"Surry Hills",
    "sg:classifiers":[
        {
            "category":"Bagels",
            "subcategory":"None",
            "type":"Food & Drink"
        }
    ],
    "sg:phone":"+61 2 9211 1186",
    "sg:postcode":"2010",
    "sg:province":"NSW",
    "sg:tags":[
        "pleaters"
    ],
    "wof:name":"Rado-Pleating Pty Ltd",
    "wof:placetype":"venue"
},
  "geometry": {"coordinates":[151.21244812,-33.8814964294],"type":"Point"}
}