{
  "type": "Feature",
  "properties": {
    "addr:full":"Lvl 5/ 111 Collins St Melbourne VIC 3000",
    "addr:housenumber":"/ 111",
    "addr:postcode":"3000",
    "addr:street":"Collins St",
    "iso:country":"AU",
    "sg:address":"Lvl 5/ 111 Collins St",
    "sg:city":"Melbourne",
    "sg:classifiers":[
        {
            "category":"Banks & Credit Unions",
            "subcategory":"Investment Brokerage",
            "type":"Services"
        }
    ],
    "sg:phone":"+61 3 9654 5933",
    "sg:postcode":"3000",
    "sg:province":"VIC",
    "wof:name":"Affinity Funds Management Ltd",
    "wof:placetype":"venue"
},
  "geometry": {"coordinates":[144.97018432600001,-37.8145484924],"type":"Point"}
}