{
  "type": "Feature",
  "properties": {
    "addr:full":"10 Boyd St Gayndah QLD 4625",
    "addr:housenumber":"10",
    "addr:postcode":"4625",
    "addr:street":"Boyd St",
    "iso:country":"AU",
    "sg:address":"10 Boyd St",
    "sg:city":"Gayndah",
    "sg:classifiers":[
        {
            "category":"Retail",
            "subcategory":"Auto Repair",
            "type":"Services"
        }
    ],
    "sg:phone":"+61 7 4161 1401",
    "sg:postcode":"4625",
    "sg:province":"QLD",
    "sg:tags":[
        "repairer",
        "motor",
        "engineer"
    ],
    "wof:name":"Pigram R J & J I",
    "wof:placetype":"venue"
},
  "geometry": {"coordinates":[151.61134338400001,-25.6208763123],"type":"Point"}
}