{
  "type": "Feature",
  "properties": {
    "addr:full":"83 Terrara Rd Vermont South VIC 3133",
    "addr:housenumber":"83",
    "addr:postcode":"3133",
    "addr:street":"Terrara Rd",
    "iso:country":"AU",
    "sg:address":"83 Terrara Rd",
    "sg:city":"Vermont South",
    "sg:classifiers":[
        {
            "category":"Education",
            "subcategory":"Special Training",
            "type":"Public Place"
        }
    ],
    "sg:phone":"+61 3 9887 5801",
    "sg:postcode":"3133",
    "sg:province":"VIC",
    "sg:tags":[
        "tuition-educational"
    ],
    "wof:name":"Economics Specialist Tutoring",
    "wof:placetype":"venue"
},
  "geometry": {"coordinates":[145.189254761,-37.8474006653],"type":"Point"}
}