{
  "type": "Feature",
  "properties": {
    "addr:full":"308 Great Eastern Hwy Midland WA 6056",
    "addr:housenumber":"308",
    "addr:postcode":"6056",
    "addr:street":"Great Eastern Hwy",
    "iso:country":"AU",
    "sg:address":"308 Great Eastern Hwy",
    "sg:city":"Midland",
    "sg:classifiers":[
        {
            "category":"Retail",
            "subcategory":"Repair Shop",
            "type":"Services"
        }
    ],
    "sg:phone":"+61 8 9274 2366",
    "sg:postcode":"6056",
    "sg:province":"WA",
    "sg:tags":[
        "machine",
        "sewing"
    ],
    "wof:name":"Classic Sewing Centre",
    "wof:placetype":"venue"
},
  "geometry": {"coordinates":[116.01235199,-31.8918037415],"type":"Point"}
}