{
  "type": "Feature",
  "properties": {
    "addr:full":"3 New St Lawson NSW 2783",
    "addr:housenumber":"3",
    "addr:postcode":"2783",
    "addr:street":"New St",
    "iso:country":"AU",
    "sg:address":"3 New St",
    "sg:city":"Lawson",
    "sg:classifiers":[
        {
            "category":"Social Services",
            "subcategory":"Child Care",
            "type":"Services"
        }
    ],
    "sg:phone":"+61 2 4758 6833",
    "sg:postcode":"2783",
    "sg:province":"NSW",
    "wof:name":"Mountains Mobile Minders",
    "wof:placetype":"venue"
},
  "geometry": {"coordinates":[150.429443359,-33.7203636169],"type":"Point"}
}