{
  "type": "Feature",
  "properties": {
    "addr:full":"8 Freeman St Yarraville VIC 3013",
    "addr:housenumber":"8",
    "addr:postcode":"3013",
    "addr:street":"Freeman St",
    "iso:country":"AU",
    "sg:address":"8 Freeman St",
    "sg:city":"Yarraville",
    "sg:classifiers":[
        {
            "category":"Building & Trades",
            "subcategory":"Construction",
            "type":"Services"
        }
    ],
    "sg:phone":"+61 418 365 067",
    "sg:postcode":"3013",
    "sg:province":"VIC",
    "sg:tags":[
        "joiner",
        "carpenter"
    ],
    "wof:name":"Bonsai Boy Carpentry",
    "wof:placetype":"venue"
},
  "geometry": {"coordinates":[144.87405395499999,-37.8165245056],"type":"Point"}
}