{
  "type": "Feature",
  "properties": {
    "addr:full":"103 Central Ave Moonah TAS 7009",
    "addr:housenumber":"103",
    "addr:postcode":"7009",
    "addr:street":"Central Ave",
    "iso:country":"AU",
    "sg:address":"103 Central Ave",
    "sg:city":"Moonah",
    "sg:classifiers":[
        {
            "category":"Home & Garden",
            "subcategory":"Building Materials",
            "type":"Retail Goods"
        }
    ],
    "sg:phone":"+61 407 627 212",
    "sg:postcode":"7009",
    "sg:province":"TAS",
    "sg:tags":[
        "concrete",
        "gutter",
        "kerb"
    ],
    "wof:name":"Kwik Kerb",
    "wof:placetype":"venue"
},
  "geometry": {"coordinates":[147.30210876500001,-42.8393516541],"type":"Point"}
}