{
  "type": "Feature",
  "properties": {
    "iso:country":"AU",
    "sg:address":"100 Great North Rd",
    "sg:city":"Five Dock",
    "sg:classifiers":[
        {
            "category":"Food & Beverages",
            "subcategory":"Liquor & Beverages",
            "type":"Retail Goods"
        }
    ],
    "sg:phone":"+61 2 9713 4141",
    "sg:postcode":"2046",
    "sg:province":"NSW",
    "sg:tags":[
        "store"
    ],
    "wof:name":"BWS Liquor",
    "wof:placetype":"venue"
},
  "geometry": {"coordinates":[151.130127,-33.867085],"type":"Point"}
}