{
  "type": "Feature",
  "properties": {
    "addr:full":"100 Great North Rd Five Dock NSW 2046",
    "addr:housenumber":"100",
    "addr:postcode":"2046",
    "addr:street":"Great North Rd",
    "iso:country":"AU",
    "sg:address":"100 Great North Rd",
    "sg:city":"Five Dock",
    "sg:classifiers":[
        {
            "category":"Food & Beverages",
            "subcategory":"Liquor & Beverages",
            "type":"Retail Goods"
        }
    ],
    "sg:phone":"+61 2 9713 4141",
    "sg:postcode":"2046",
    "sg:province":"NSW",
    "sg:tags":[
        "store"
    ],
    "wof:name":"BWS Liquor",
    "wof:placetype":"venue"
},
  "geometry": {"coordinates":[151.13012699999999,-33.867085],"type":"Point"}
}