{
  "type": "Feature",
  "properties": {
    "addr:full":"7 Greensill La Samsonvale QLD 4520",
    "addr:housenumber":"7",
    "addr:postcode":"4520",
    "addr:street":"Greensill La Samsonvale",
    "iso:country":"AU",
    "sg:address":"7 Greensill La",
    "sg:city":"Samsonvale",
    "sg:classifiers":[
        {
            "category":"Shopping",
            "type":"Retail Goods"
        }
    ],
    "sg:phone":"+61 7 3289 9777",
    "sg:postcode":"4520",
    "sg:province":"QLD",
    "sg:tags":[
        "equipment",
        "safety",
        "accessory"
    ],
    "wof:name":"Vertical Safety Australia",
    "wof:placetype":"venue"
},
  "geometry": {"coordinates":[152.84255999999999,-27.252872],"type":"Point"}
}