{
  "type": "Feature",
  "properties": {
    "iso:country":"AU",
    "sg:address":"7 Greensill La",
    "sg:city":"Samsonvale",
    "sg:classifiers":[
        {
            "category":"Shopping",
            "type":"Retail Goods"
        }
    ],
    "sg:phone":"+61 7 3289 9777",
    "sg:postcode":"4520",
    "sg:province":"QLD",
    "sg:tags":[
        "equipment",
        "safety",
        "accessory"
    ],
    "wof:name":"Vertical Safety Australia",
    "wof:placetype":"venue"
},
  "geometry": {"coordinates":[152.84256,-27.252872],"type":"Point"}
}