{
  "type": "Feature",
  "properties": {
    "addr:full":"Factory 1/ 35 Churchill Park Drv Invermay TAS 7248",
    "addr:housenumber":"/ 35",
    "addr:postcode":"7248",
    "addr:street":"Churchill Park Drv",
    "iso:country":"AU",
    "sg:address":"Factory 1/ 35 Churchill Park Drv",
    "sg:city":"Invermay",
    "sg:classifiers":[
        {
            "category":"Retail",
            "subcategory":"Auto Repair",
            "type":"Services"
        }
    ],
    "sg:phone":"+61 3 6331 5473",
    "sg:postcode":"7248",
    "sg:province":"TAS",
    "sg:tags":[
        "repairer",
        "motor",
        "engineer"
    ],
    "wof:name":"Roger Lutwyche Automotives",
    "wof:placetype":"venue"
},
  "geometry": {"coordinates":[147.14355468799999,-41.4173278809],"type":"Point"}
}