{
  "type": "Feature",
  "properties": {
    "addr:full":"Cnr South Rd & Susan St Hindmarsh SA 5007",
    "addr:postcode":"5007",
    "addr:street":"Cnr South Rd & Susan St",
    "iso:country":"AU",
    "sg:address":"Cnr South Rd & Susan St",
    "sg:city":"Hindmarsh",
    "sg:classifiers":[
        {
            "category":"Wholesale",
            "subcategory":"Electrical",
            "type":"Manufacturing & Wholesale Goods"
        }
    ],
    "sg:phone":"+61 8 8340 9255",
    "sg:postcode":"5007",
    "sg:province":"SA",
    "sg:tags":[
        "wholesaler"
    ],
    "wof:name":"Middendorp Electric Co Pty Ltd",
    "wof:placetype":"venue"
},
  "geometry": {"coordinates":[138.56562805199999,-34.90574646],"type":"Point"}
}