{
  "type": "Feature",
  "properties": {
    "iso:country":"AU",
    "sg:address":"433 Buckingham St",
    "sg:city":"North Albury",
    "sg:classifiers":[
        {
            "category":"Building & Trades",
            "subcategory":"Landscaping Services",
            "type":"Services"
        }
    ],
    "sg:phone":"+61 416 556 379",
    "sg:postcode":"2640",
    "sg:province":"NSW",
    "sg:tags":[
        "designer",
        "landscape",
        "contractor"
    ],
    "wof:name":"Ben Turner",
    "wof:placetype":"venue"
},
  "geometry": {"coordinates":[146.92616272000001,-36.0636672974],"type":"Point"}
}