{
  "type": "Feature",
  "properties": {
    "addr:full":"32 Ramu Pde Heidelberg VIC 3084",
    "addr:housenumber":"32",
    "addr:postcode":"3084",
    "addr:street":"Ramu Pde",
    "iso:country":"AU",
    "sg:address":"32 Ramu Pde",
    "sg:city":"Heidelberg",
    "sg:classifiers":[
        {
            "category":"Personal",
            "subcategory":"Beauty Salon",
            "type":"Services"
        }
    ],
    "sg:phone":"+61 438 323 766",
    "sg:postcode":"3084",
    "sg:province":"VIC",
    "wof:name":"Jolenes Mobile Beauty",
    "wof:placetype":"venue"
},
  "geometry": {"coordinates":[145.06935119600001,-37.7580184937],"type":"Point"}
}