{
  "type": "Feature",
  "properties": {
    "addr:full":"87 St Johns Rd Busby NSW 2168",
    "addr:housenumber":"87",
    "addr:postcode":"2168",
    "addr:street":"St Johns Rd",
    "iso:country":"AU",
    "sg:address":"87 St Johns Rd",
    "sg:city":"Busby",
    "sg:classifiers":[
        {
            "category":"Social Services",
            "subcategory":"Child Care",
            "type":"Services"
        }
    ],
    "sg:phone":"+61 2 9608 3435",
    "sg:postcode":"2168",
    "sg:province":"NSW",
    "wof:name":"Busby Long Day Care Centre",
    "wof:placetype":"venue"
},
  "geometry": {"coordinates":[150.884597778,-33.9117927551],"type":"Point"}
}