{
  "type": "Feature",
  "properties": {
    "addr:full":"2 Yardie Crt Lower Plenty VIC 3093",
    "addr:housenumber":"2",
    "addr:postcode":"3093",
    "addr:street":"Yardie Crt",
    "iso:country":"AU",
    "sg:address":"2 Yardie Crt",
    "sg:city":"Lower Plenty",
    "sg:classifiers":[
        {
            "category":"Building & Trades",
            "subcategory":"Construction",
            "type":"Services"
        }
    ],
    "sg:phone":"+61 412 801 657",
    "sg:postcode":"3093",
    "sg:province":"VIC",
    "sg:tags":[
        "renovation",
        "alterations",
        "extension",
        "contractor"
    ],
    "wof:name":"Vancor Maintenance & Renovations",
    "wof:placetype":"venue"
},
  "geometry": {"coordinates":[145.13185119600001,-37.733543396],"type":"Point"}
}