{
  "type": "Feature",
  "properties": {
    "addr:full":"Gipp St Bega NSW 2550",
    "addr:postcode":"2550",
    "addr:street":"St",
    "iso:country":"AU",
    "sg:address":"Gipp St",
    "sg:city":"Bega",
    "sg:classifiers":[
        {
            "category":"Education",
            "subcategory":"School",
            "type":"Public Place"
        }
    ],
    "sg:phone":"+61 2 6492 5500",
    "sg:postcode":"2550",
    "sg:province":"NSW",
    "wof:name":"St Patrick's School",
    "wof:placetype":"venue"
},
  "geometry": {"coordinates":[149.69696044899999,-36.7635612488],"type":"Point"}
}