{
  "type": "Feature",
  "properties": {
    "addr:full":"156 Moray St South Melbourne VIC 3205",
    "addr:housenumber":"156",
    "addr:postcode":"3205",
    "addr:street":"Moray St",
    "iso:country":"AU",
    "sg:address":"156 Moray St",
    "sg:city":"South Melbourne",
    "sg:classifiers":[
        {
            "category":"Shopping",
            "subcategory":"Computers & Home Electronics",
            "type":"Retail Goods"
        }
    ],
    "sg:phone":"+61 1800 060 643",
    "sg:postcode":"3205",
    "sg:province":"VIC",
    "sg:tags":[
        "equipment",
        "multimedia"
    ],
    "wof:name":"Innographics",
    "wof:placetype":"venue"
},
  "geometry": {"coordinates":[144.962265,-37.830917],"type":"Point"}
}