{
  "type": "Feature",
  "properties": {
    "iso:country":"AU",
    "sg:address":"Clint St",
    "sg:city":"Kelso",
    "sg:classifiers":[
        {
            "category":"Arena",
            "subcategory":"Sports Club",
            "type":"Entertainment"
        }
    ],
    "sg:phone":"+61 7 4789 2262",
    "sg:postcode":"4815",
    "sg:province":"QLD",
    "sg:tags":[
        "league",
        "rugby"
    ],
    "wof:name":"Upper Ross Junior Rugby League Club",
    "wof:placetype":"venue"
},
  "geometry": {"coordinates":[146.72972100000001,-19.385],"type":"Point"}
}