{
  "type": "Feature",
  "properties": {
    "iso:country":"AU",
    "sg:address":"93 Loughnan Rd",
    "sg:city":"Ringwood",
    "sg:classifiers":[
        {
            "category":"Food & Beverages",
            "subcategory":"Groceries & Convenience Stores",
            "type":"Retail Goods"
        }
    ],
    "sg:phone":"+61 3 9870 1679",
    "sg:postcode":"3134",
    "sg:province":"VIC",
    "wof:name":"Chmait A & S",
    "wof:placetype":"venue"
},
  "geometry": {"coordinates":[145.21905517600001,-37.8087882996],"type":"Point"}
}