{
  "type": "Feature",
  "properties": {
    "addr:full":"131 George St Beenleigh QLD 4207",
    "addr:housenumber":"131",
    "addr:postcode":"4207",
    "addr:street":"George St",
    "iso:country":"AU",
    "sg:address":"131 George St",
    "sg:city":"Beenleigh",
    "sg:classifiers":[
        {
            "category":"Manufacturing",
            "subcategory":"Motor Vehicles & Parts",
            "type":"Manufacturing & Wholesale Goods"
        }
    ],
    "sg:phone":"+61 7 3807 9822",
    "sg:postcode":"4207",
    "sg:province":"QLD",
    "sg:tags":[
        "replacement"
    ],
    "wof:name":"Autobarn Pty Ltd",
    "wof:placetype":"venue"
},
  "geometry": {"coordinates":[153.20390319800001,-27.7162094116],"type":"Point"}
}