{
  "type": "Feature",
  "properties": {
    "addr:full":"U5/ 12 to 14 Cranbrook Rd Batemans Bay NSW 2536",
    "addr:housenumber":"12 to 14",
    "addr:postcode":"2536",
    "addr:street":"U5 /;Cranbrook Rd",
    "iso:country":"AU",
    "sg:address":"U5/ 12 to 14 Cranbrook Rd",
    "sg:city":"Batemans Bay",
    "sg:classifiers":[
        {
            "category":"Retail",
            "subcategory":"Auto Repair",
            "type":"Services"
        }
    ],
    "sg:phone":"+61 2 4472 3334",
    "sg:postcode":"2536",
    "sg:province":"NSW",
    "sg:tags":[
        "repairer",
        "motor",
        "engineer"
    ],
    "wof:name":"Doc Ford Auto Clinic",
    "wof:placetype":"venue"
},
  "geometry": {"coordinates":[150.173339844,-35.7202186584],"type":"Point"}
}