{
  "type": "Feature",
  "properties": {
    "iso:country":"AU",
    "sg:address":"3 Charlotte Pl St",
    "sg:city":"Kilda",
    "sg:classifiers":[
        {
            "category":"Building & Trades",
            "subcategory":"Landscaping Services",
            "type":"Services"
        }
    ],
    "sg:phone":"+61 3 9529 1083",
    "sg:postcode":"3182",
    "sg:province":"VIC",
    "sg:tags":[
        "designer",
        "landscape",
        "contractor"
    ],
    "wof:name":"Jon Houghton Garden Productions",
    "wof:placetype":"venue"
},
  "geometry": {"coordinates":[144.99081420900001,-37.858417511],"type":"Point"}
}