{
  "type": "Feature",
  "properties": {
    "addr:full":"Unit 10, 120 Gilba Rd Girraween NSW 2145",
    "addr:housenumber":"120",
    "addr:postcode":"2145",
    "addr:street":"Gilba Rd",
    "iso:country":"AU",
    "sg:address":"Unit 10, 120 Gilba Rd",
    "sg:city":"Girraween",
    "sg:classifiers":[
        {
            "category":"Retail",
            "subcategory":"Auto Repair",
            "type":"Services"
        }
    ],
    "sg:phone":"+61 2 9631 5264",
    "sg:postcode":"2145",
    "sg:province":"NSW",
    "sg:tags":[
        "repairer",
        "motor",
        "engineer"
    ],
    "wof:name":"Teuma Louis Mechanical Repairs",
    "wof:placetype":"venue"
},
  "geometry": {"coordinates":[150.94314575199999,-33.7979545593],"type":"Point"}
}