{
  "type": "Feature",
  "properties": {
    "iso:country":"AU",
    "sg:address":"Warburton Hwy",
    "sg:city":"Woori Yallock",
    "sg:classifiers":[
        {
            "category":"Fast Food",
            "type":"Food & Drink"
        }
    ],
    "sg:phone":"+61 3 5964 6343",
    "sg:postcode":"3139",
    "sg:province":"VIC",
    "sg:tags":[
        "away",
        "take"
    ],
    "wof:name":"Woori's Pizza",
    "wof:placetype":"venue"
},
  "geometry": {"coordinates":[145.52960205100001,-37.7796516418],"type":"Point"}
}