{
  "type": "Feature",
  "properties": {
    "addr:full":"Stuart St Melrose SA 5483",
    "addr:postcode":"5483",
    "addr:street":"Stuart St",
    "iso:country":"AU",
    "sg:address":"Stuart St",
    "sg:city":"Melrose",
    "sg:classifiers":[
        {
            "category":"Government",
            "subcategory":"Post Office",
            "type":"Public Place"
        }
    ],
    "sg:phone":"+61 8 8666 2123",
    "sg:postcode":"5483",
    "sg:province":"SA",
    "sg:tags":[
        "postal"
    ],
    "wof:name":"Australia Post",
    "wof:placetype":"venue"
},
  "geometry": {"coordinates":[138.191131592,-32.821308136],"type":"Point"}
}