{
  "type": "Feature",
  "properties": {
    "addr:full":"4 Stewart St Dowerin WA 6461",
    "addr:housenumber":"4",
    "addr:postcode":"6461",
    "addr:street":"Stewart St",
    "iso:country":"AU",
    "sg:address":"4 Stewart St",
    "sg:city":"Dowerin",
    "sg:classifiers":[
        {
            "category":"Travel",
            "subcategory":"Hotels & Motels",
            "type":"Entertainment"
        }
    ],
    "sg:phone":"+61 8 9631 1206",
    "sg:postcode":"6461",
    "sg:province":"WA",
    "sg:tags":[
        "accommodation"
    ],
    "wof:name":"Dowerin Hotel",
    "wof:placetype":"venue"
},
  "geometry": {"coordinates":[117.0311203,-31.1955375671],"type":"Point"}
}