{
  "type": "Feature",
  "properties": {
    "addr:full":"13 Bedford St Queanbeyan NSW 2620",
    "addr:housenumber":"13",
    "addr:postcode":"2620",
    "addr:street":"Bedford St",
    "iso:country":"AU",
    "sg:address":"13 Bedford St",
    "sg:city":"Queanbeyan",
    "sg:classifiers":[
        {
            "category":"Building & Trades",
            "subcategory":"Plumbing",
            "type":"Services"
        }
    ],
    "sg:phone":"+61 2 6297 2022",
    "sg:postcode":"2620",
    "sg:province":"NSW",
    "sg:tags":[
        "plumber",
        "gasfitters"
    ],
    "wof:name":"O'Neill & Brown Plumbing Co Pty Ltd",
    "wof:placetype":"venue"
},
  "geometry": {"coordinates":[149.20484924300001,-35.3505363464],"type":"Point"}
}