{
  "type": "Feature",
  "properties": {
    "addr:full":"142 Union Rd Ascot Vale VIC 3032",
    "addr:housenumber":"142",
    "addr:postcode":"3032",
    "addr:street":"Union Rd",
    "iso:country":"AU",
    "sg:address":"142 Union Rd",
    "sg:city":"Ascot Vale",
    "sg:classifiers":[
        {
            "category":"Sports & Exercise",
            "subcategory":"Gym",
            "type":"Entertainment"
        }
    ],
    "sg:phone":"+61 3 9326 2688",
    "sg:postcode":"3032",
    "sg:province":"VIC",
    "sg:tags":[
        "health",
        "fitness"
    ],
    "wof:name":"Paramount Health & Fitness Centre",
    "wof:placetype":"venue"
},
  "geometry": {"coordinates":[144.91575599999999,-37.775455],"type":"Point"}
}