{
  "type": "Feature",
  "properties": {
    "addr:full":"The Royal Botanic Gardens, Mrs Macquaries Rd Sydney NSW 2000",
    "addr:postcode":"2000",
    "addr:street":"Macquaries Rd",
    "iso:country":"AU",
    "sg:address":"The Royal Botanic Gardens, Mrs Macquaries Rd",
    "sg:city":"Sydney",
    "sg:classifiers":[
        {
            "category":"Restaurant",
            "type":"Food & Drink"
        }
    ],
    "sg:phone":"+61 2 9241 2419",
    "sg:postcode":"2000",
    "sg:province":"NSW",
    "wof:name":"Botanic Gardens Restaurant",
    "wof:placetype":"venue"
},
  "geometry": {"coordinates":[151.21922302199999,-33.8663101196],"type":"Point"}
}