{
  "type": "Feature",
  "properties": {
    "iso:country":"AU",
    "sg:address":"1120 Sydney Rd",
    "sg:city":"Fawkner",
    "sg:classifiers":[
        {
            "category":"Building & Trades",
            "subcategory":"Construction",
            "type":"Services"
        }
    ],
    "sg:phone":"+61 3 9357 4040",
    "sg:postcode":"3060",
    "sg:province":"VIC",
    "sg:tags":[
        "monumental",
        "mason"
    ],
    "wof:name":"George Dawe",
    "wof:placetype":"venue"
},
  "geometry": {"coordinates":[144.962402344,-37.7136611938],"type":"Point"}
}