{
  "type": "Feature",
  "properties": {
    "addr:full":"4 Howard St Lindfield NSW 2070",
    "addr:housenumber":"4",
    "addr:postcode":"2070",
    "addr:street":"Howard St",
    "iso:country":"AU",
    "sg:address":"4 Howard St",
    "sg:city":"Lindfield",
    "sg:classifiers":[
        {
            "category":"Shopping",
            "subcategory":"Computers & Home Electronics",
            "type":"Retail Goods"
        }
    ],
    "sg:phone":"+61 2 9416 4500",
    "sg:postcode":"2070",
    "sg:province":"NSW",
    "sg:tags":[
        "equipment",
        "part",
        "electronic"
    ],
    "wof:name":"Australian Great Enterprises",
    "wof:placetype":"venue"
},
  "geometry": {"coordinates":[151.17576599099999,-33.774394989],"type":"Point"}
}