{
  "type": "Feature",
  "properties": {
    "iso:country":"AU",
    "sg:address":"7 Finniss St",
    "sg:city":"Gawler",
    "sg:classifiers":[
        {
            "category":"Wholesale",
            "subcategory":"Electrical",
            "type":"Manufacturing & Wholesale Goods"
        }
    ],
    "sg:phone":"+61 8 8522 4299",
    "sg:postcode":"5118",
    "sg:province":"SA",
    "sg:tags":[
        "wholesaler"
    ],
    "wof:name":"P & R Electrical Wholesalers Pty Ltd",
    "wof:placetype":"venue"
},
  "geometry": {"coordinates":[138.743607,-34.597858],"type":"Point"}
}