{
  "type": "Feature",
  "properties": {
    "addr:full":"Suite 3, 329 Canning Hwy Palmyra WA 6157",
    "addr:housenumber":"329",
    "addr:postcode":"6157",
    "addr:street":"Canning Hwy",
    "iso:country":"AU",
    "sg:address":"Suite 3, 329 Canning Hwy",
    "sg:city":"Palmyra",
    "sg:classifiers":[
        {
            "category":"Professional",
            "subcategory":"Accounting & Tax Preparation",
            "type":"Services"
        }
    ],
    "sg:phone":"+61 8 9339 3297",
    "sg:postcode":"6157",
    "sg:province":"WA",
    "sg:tags":[
        "consultant",
        "taxation"
    ],
    "wof:name":"ITP The Income Tax Professionals",
    "wof:placetype":"venue"
},
  "geometry": {"coordinates":[115.78340900000001,-32.036667],"type":"Point"}
}