{
  "type": "Feature",
  "properties": {
    "iso:country":"AU",
    "sg:address":"21 Grenfell St",
    "sg:city":"West Wyalong",
    "sg:classifiers":[
        {
            "category":"Utilities",
            "subcategory":"Electric",
            "type":"Services"
        }
    ],
    "sg:phone":"+61 2 6972 2808",
    "sg:postcode":"2671",
    "sg:province":"NSW",
    "sg:tags":[
        "electrical",
        "contractor"
    ],
    "wof:name":"Mrowka P & L",
    "wof:placetype":"venue"
},
  "geometry": {"coordinates":[147.206756592,-33.918800354],"type":"Point"}
}