{
  "type": "Feature",
  "properties": {
    "addr:full":"13 Sassafrass Crs Burnie TAS 7320",
    "addr:housenumber":"13",
    "addr:postcode":"7320",
    "addr:street":"Sassafrass Crs",
    "iso:country":"AU",
    "sg:address":"13 Sassafrass Crs",
    "sg:city":"Burnie",
    "sg:classifiers":[
        {
            "category":"Building & Trades",
            "subcategory":"Pest Control",
            "type":"Services"
        }
    ],
    "sg:phone":"+61 3 6433 0220",
    "sg:postcode":"7320",
    "sg:province":"TAS",
    "wof:name":"Franks Neville",
    "wof:placetype":"venue"
},
  "geometry": {"coordinates":[145.89825400000001,-41.075859],"type":"Point"}
}