{
  "type": "Feature",
  "properties": {
    "addr:full":"Shop 6/ 109 James St Northbridge WA 6003",
    "addr:housenumber":"shop 6 / 109",
    "addr:postcode":"6003",
    "addr:street":"James St",
    "iso:country":"AU",
    "sg:address":"Shop 6/ 109 James St",
    "sg:city":"Northbridge",
    "sg:classifiers":[
        {
            "category":"Airline",
            "type":"Transportation"
        }
    ],
    "sg:phone":"+61 8 9328 6868",
    "sg:postcode":"6003",
    "sg:province":"WA",
    "sg:tags":[
        "agent"
    ],
    "wof:name":"Ausworld Travel",
    "wof:placetype":"venue"
},
  "geometry": {"coordinates":[115.857788086,-31.9481697083],"type":"Point"}
}