{
  "type": "Feature",
  "properties": {
    "iso:country":"AU",
    "sg:address":"114 Rothchild Ave",
    "sg:city":"Rosebery",
    "sg:classifiers":[
        {
            "category":"Wholesale",
            "subcategory":"Apparel",
            "type":"Manufacturing & Wholesale Goods"
        }
    ],
    "sg:phone":"+61 2 9317 5866",
    "sg:postcode":"2018",
    "sg:province":"NSW",
    "sg:tags":[
        "wholesaler",
        "mfrs",
        "uniform"
    ],
    "wof:name":"Ranier Pty Ltd",
    "wof:placetype":"venue"
},
  "geometry": {"coordinates":[151.203582764,-33.9184989929],"type":"Point"}
}