{
  "type": "Feature",
  "properties": {
    "addr:full":"306 Bent St South Grafton NSW 2460",
    "addr:housenumber":"306",
    "addr:postcode":"2460",
    "addr:street":"Bent St",
    "iso:country":"AU",
    "sg:address":"306 Bent St",
    "sg:city":"South Grafton",
    "sg:classifiers":[
        {
            "category":"Building & Trades",
            "subcategory":"Construction",
            "type":"Services"
        }
    ],
    "sg:phone":"+61 2 6643 2826",
    "sg:postcode":"2460",
    "sg:province":"NSW",
    "sg:tags":[
        "joiner",
        "carpenter"
    ],
    "wof:name":"Carl Boulton Carpenter & Joiner",
    "wof:placetype":"venue"
},
  "geometry": {"coordinates":[152.930221558,-29.7250862122],"type":"Point"}
}