{
  "type": "Feature",
  "properties": {
    "addr:full":"38 Oriole St Stirling WA 6021",
    "addr:housenumber":"38",
    "addr:postcode":"6021",
    "addr:street":"Oriole St",
    "iso:country":"AU",
    "sg:address":"38 Oriole St",
    "sg:city":"Stirling",
    "sg:classifiers":[
        {
            "category":"Home & Garden",
            "subcategory":"Carpets & Floor Coverings",
            "type":"Retail Goods"
        }
    ],
    "sg:phone":"+61 418 488 806",
    "sg:postcode":"6021",
    "sg:province":"WA",
    "sg:tags":[
        "tile",
        "wall",
        "layer"
    ],
    "wof:name":"Vince's Tiling Service",
    "wof:placetype":"venue"
},
  "geometry": {"coordinates":[115.810981751,-31.8852138519],"type":"Point"}
}