{
  "type": "Feature",
  "properties": {
    "addr:full":"1st Floor/ 349 Elizabeth St Melbourne VIC 3000",
    "addr:housenumber":"/ 349",
    "addr:postcode":"3000",
    "addr:street":"Elizabeth St",
    "iso:country":"AU",
    "sg:address":"1st Floor/ 349 Elizabeth St",
    "sg:city":"Melbourne",
    "sg:classifiers":[
        {
            "category":"Shopping",
            "subcategory":"Music",
            "type":"Retail Goods"
        }
    ],
    "sg:phone":"+61 3 9640 0304",
    "sg:postcode":"3000",
    "sg:province":"VIC",
    "sg:tags":[
        "store"
    ],
    "wof:name":"Inferno DVD Video & CD",
    "wof:placetype":"venue"
},
  "geometry": {"coordinates":[144.96127319300001,-37.8104820251],"type":"Point"}
}