{
  "type": "Feature",
  "properties": {
    "addr:full":"12 Naranganah Ave Gymea Bay NSW 2227",
    "addr:housenumber":"12",
    "addr:postcode":"2227",
    "addr:street":"Naranganah Ave",
    "iso:country":"AU",
    "sg:address":"12 Naranganah Ave",
    "sg:city":"Gymea Bay",
    "sg:classifiers":[
        {
            "category":"Farming",
            "subcategory":"Fish & Marine Products",
            "type":"Manufacturing & Wholesale Goods"
        }
    ],
    "sg:phone":"+61 2 9525 6995",
    "sg:postcode":"2227",
    "sg:province":"NSW",
    "sg:tags":[
        "wholesaler",
        "mfrs",
        "swimwear"
    ],
    "wof:name":"Simply Swimming",
    "wof:placetype":"venue"
},
  "geometry": {"coordinates":[151.08822631800001,-34.054977417],"type":"Point"}
}