{
  "type": "Feature",
  "properties": {
    "addr:full":"4/ 49 Townsville St Fyshwick ACT 2609",
    "addr:housenumber":"/ 49",
    "addr:postcode":"2609",
    "addr:street":"Townsville St",
    "iso:country":"AU",
    "sg:address":"4/ 49 Townsville St",
    "sg:city":"Fyshwick",
    "sg:classifiers":[
        {
            "category":"Retail",
            "subcategory":"Funeral Services",
            "type":"Services"
        }
    ],
    "sg:phone":"+61 2 6239 2355",
    "sg:postcode":"2609",
    "sg:province":"ACT",
    "sg:tags":[
        "supply"
    ],
    "wof:name":"A & S Printers",
    "wof:placetype":"venue"
},
  "geometry": {"coordinates":[149.18356323200001,-35.3305397034],"type":"Point"}
}