{
  "type": "Feature",
  "properties": {
    "iso:country":"AU",
    "sg:address":"Suites 12-13, 38",
    "sg:city":"East Esp Manly",
    "sg:classifiers":[
        {
            "category":"Health Services",
            "subcategory":"Health Practitioner",
            "type":"Services"
        }
    ],
    "sg:phone":"+61 2 9977 3800",
    "sg:postcode":"2095",
    "sg:province":"NSW",
    "sg:tags":[
        "psychologist"
    ],
    "wof:name":"Clark Dianne C",
    "wof:placetype":"venue"
},
  "geometry": {"coordinates":[151.28590393100001,-33.7999572754],"type":"Point"}
}