{
  "type": "Feature",
  "properties": {
    "iso:country":"AU",
    "sg:address":"17 Dittmar Crt",
    "sg:city":"Goolwa",
    "sg:classifiers":[
        {
            "category":"Utilities",
            "subcategory":"Electric",
            "type":"Services"
        }
    ],
    "sg:phone":"+61 409 552 937",
    "sg:postcode":"5214",
    "sg:province":"SA",
    "sg:tags":[
        "electrical",
        "contractor"
    ],
    "wof:name":"Goolwa & South Coast Electrical",
    "wof:placetype":"venue"
},
  "geometry": {"coordinates":[138.77005004899999,-35.5077285767],"type":"Point"}
}