{
  "type": "Feature",
  "properties": {
    "iso:country":"AU",
    "sg:address":"82 Monsants Rd",
    "sg:city":"Maiden Gully",
    "sg:classifiers":[
        {
            "category":"Train Station",
            "subcategory":"Rail",
            "type":"Transportation"
        }
    ],
    "sg:phone":"+61 408 343 248",
    "sg:postcode":"3551",
    "sg:province":"VIC",
    "sg:tags":[
        "wallboard"
    ],
    "wof:name":"Flora Hill Plaster",
    "wof:placetype":"venue"
},
  "geometry": {"coordinates":[144.19973754899999,-36.7572364807],"type":"Point"}
}