{
  "type": "Feature",
  "properties": {
    "addr:full":"631 South Rd Everard Park SA 5035",
    "addr:housenumber":"631",
    "addr:postcode":"5035",
    "addr:street":"South Rd",
    "iso:country":"AU",
    "sg:address":"631 South Rd",
    "sg:city":"Everard Park",
    "sg:classifiers":[
        {
            "category":"Travel",
            "subcategory":"Hostel",
            "type":"Entertainment"
        }
    ],
    "sg:phone":"+61 8 8293 1975",
    "sg:postcode":"5035",
    "sg:province":"SA",
    "sg:tags":[
        "home"
    ],
    "wof:name":"Aveo Ackland Park",
    "wof:placetype":"venue"
},
  "geometry": {"coordinates":[138.57240295400001,-34.9565391541],"type":"Point"}
}