{
  "type": "Feature",
  "properties": {
    "iso:country":"AU",
    "sg:address":"77 Silver St",
    "sg:city":"Marrickville",
    "sg:classifiers":[
        {
            "category":"Health Services",
            "subcategory":"Doctor",
            "type":"Services"
        }
    ],
    "sg:phone":"+61 2 9560 3154",
    "sg:postcode":"2204",
    "sg:province":"NSW",
    "sg:tags":[
        "medical",
        "practitioner"
    ],
    "wof:name":"Criticos J C Dr",
    "wof:placetype":"venue"
},
  "geometry": {"coordinates":[151.156937,-33.911419],"type":"Point"}
}