{
  "type": "Feature",
  "properties": {
    "addr:full":"Unit 4 / 45 4th Ave Blacktown NSW 2148",
    "addr:housenumber":"45",
    "addr:postcode":"2148",
    "addr:street":"4Th Ave",
    "iso:country":"AU",
    "sg:address":"Unit 4 / 45 4th Ave",
    "sg:city":"Blacktown",
    "sg:classifiers":[
        {
            "category":"Retail",
            "subcategory":"Auto Repair",
            "type":"Services"
        }
    ],
    "sg:phone":"+61 2 9671 5140",
    "sg:postcode":"2148",
    "sg:province":"NSW",
    "sg:tags":[
        "repairer",
        "motor",
        "engineer"
    ],
    "wof:name":"Rods Mechanical Repairs",
    "wof:placetype":"venue"
},
  "geometry": {"coordinates":[150.909988403,-33.7639579773],"type":"Point"}
}