{
  "type": "Feature",
  "properties": {
    "addr:full":"Suite 3/ 3 Oxford St Paddington NSW 2021",
    "addr:housenumber":"3",
    "addr:postcode":"2021",
    "addr:street":"Oxford St",
    "iso:country":"AU",
    "sg:address":"Suite 3/ 3 Oxford St",
    "sg:city":"Paddington",
    "sg:classifiers":[
        {
            "category":"Building & Trades",
            "subcategory":"Landscaping Services",
            "type":"Services"
        }
    ],
    "sg:phone":"+61 2 9361 4549",
    "sg:postcode":"2021",
    "sg:province":"NSW",
    "sg:tags":[
        "architect",
        "landscape"
    ],
    "wof:name":"Spackman & Mossop Pty Ltd",
    "wof:placetype":"venue"
},
  "geometry": {"coordinates":[151.22892761200001,-33.8862419128],"type":"Point"}
}