{
  "type": "Feature",
  "properties": {
    "addr:full":"167 Magnesium Drv Crestmead QLD 4132",
    "addr:housenumber":"167",
    "addr:postcode":"4132",
    "addr:street":"Magnesium Drv",
    "iso:country":"AU",
    "sg:address":"167 Magnesium Drv",
    "sg:city":"Crestmead",
    "sg:classifiers":[
        {
            "category":"Home & Garden",
            "subcategory":"Carpets & Floor Coverings",
            "type":"Retail Goods"
        }
    ],
    "sg:phone":"+61 7 3803 6262",
    "sg:postcode":"4132",
    "sg:province":"QLD",
    "sg:tags":[
        "wood"
    ],
    "wof:name":"Auswood",
    "wof:placetype":"venue"
},
  "geometry": {"coordinates":[153.078399658,-27.6824607849],"type":"Point"}
}