{
  "type": "Feature",
  "properties": {
    "addr:full":"292 Oxley Ave Margate QLD 4019",
    "addr:housenumber":"292",
    "addr:postcode":"4019",
    "addr:street":"Oxley Ave",
    "iso:country":"AU",
    "sg:address":"292 Oxley Ave",
    "sg:city":"Margate",
    "sg:classifiers":[
        {
            "category":"Banks & Credit Unions",
            "subcategory":"Financial Services",
            "type":"Services"
        }
    ],
    "sg:phone":"+61 7 3283 6399",
    "sg:postcode":"4019",
    "sg:province":"QLD",
    "sg:tags":[
        "loan",
        "finance",
        "mortgage"
    ],
    "wof:name":"RAMS Home Loans",
    "wof:placetype":"venue"
},
  "geometry": {"coordinates":[153.10728454599999,-27.2432155609],"type":"Point"}
}