{
  "type": "Feature",
  "properties": {
    "addr:full":"189 Lawrence St Alexandria NSW 2015",
    "addr:housenumber":"189",
    "addr:postcode":"2015",
    "addr:street":"Lawrence St",
    "iso:country":"AU",
    "sg:address":"189 Lawrence St",
    "sg:city":"Alexandria",
    "sg:classifiers":[
        {
            "category":"Real Estate",
            "subcategory":"Architect",
            "type":"Services"
        }
    ],
    "sg:phone":"+61 2 9516 1177",
    "sg:postcode":"2015",
    "sg:province":"NSW",
    "wof:name":"Aitken David",
    "wof:placetype":"venue"
},
  "geometry": {"coordinates":[151.19117736800001,-33.905380249],"type":"Point"}
}