{
  "type": "Feature",
  "properties": {
    "iso:country":"AU",
    "sg:address":"1/ 44 Eddie Rd",
    "sg:city":"Minchinbury",
    "sg:classifiers":[
        {
            "category":"Recreation",
            "type":"Entertainment"
        }
    ],
    "sg:phone":"+61 2 9625 5372",
    "sg:postcode":"2770",
    "sg:province":"NSW",
    "sg:tags":[
        "children's",
        "play",
        "programme"
    ],
    "wof:name":"Kidz Fun Factory",
    "wof:placetype":"venue"
},
  "geometry": {"coordinates":[150.81712341299999,-33.7849884033],"type":"Point"}
}