{
  "type": "Feature",
  "properties": {
    "iso:country":"AU",
    "sg:address":"U 29/ 398 Marion St",
    "sg:city":"Condell Park",
    "sg:classifiers":[
        {
            "category":"Manufacturing",
            "subcategory":"Apparel",
            "type":"Manufacturing & Wholesale Goods"
        }
    ],
    "sg:phone":"+61 2 9708 0127",
    "sg:postcode":"2200",
    "sg:province":"NSW",
    "sg:tags":[
        "makers-up",
        "clothing"
    ],
    "wof:name":"La Mode Clothing",
    "wof:placetype":"venue"
},
  "geometry": {"coordinates":[151.00176999999999,-33.916405],"type":"Point"}
}