{
  "type": "Feature",
  "properties": {
    "iso:country":"AU",
    "sg:address":"James Pl",
    "sg:city":"Tanunda",
    "sg:classifiers":[
        {
            "category":"Home & Garden",
            "subcategory":"Building Materials",
            "type":"Retail Goods"
        }
    ],
    "sg:phone":"+61 8 8563 0153",
    "sg:postcode":"5352",
    "sg:province":"SA",
    "sg:tags":[
        "wall",
        "frame",
        "truss",
        "roof"
    ],
    "wof:name":"Nomadic Enterprises Pty Ltd",
    "wof:placetype":"venue"
},
  "geometry": {"coordinates":[138.96934509299999,-34.5168304443],"type":"Point"}
}