{
  "type": "Feature",
  "properties": {
    "addr:full":"296 McKillop St East Geelong VIC 3219",
    "addr:housenumber":"296",
    "addr:postcode":"3219",
    "addr:street":"Mckillop St East",
    "iso:country":"AU",
    "sg:address":"296 McKillop St",
    "sg:city":"East Geelong",
    "sg:classifiers":[
        {
            "category":"Personal",
            "subcategory":"Massage",
            "type":"Services"
        }
    ],
    "sg:phone":"+61 3 5224 2126",
    "sg:postcode":"3219",
    "sg:province":"VIC",
    "sg:tags":[
        "therapy"
    ],
    "wof:name":"Elizabeth A Smith",
    "wof:placetype":"venue"
},
  "geometry": {"coordinates":[144.37982177699999,-38.1597938538],"type":"Point"}
}