{
  "type": "Feature",
  "properties": {
    "iso:country":"AU",
    "sg:address":"526 Kingsway St",
    "sg:city":"Miranda",
    "sg:classifiers":[
        {
            "category":"Autos & Motor Vehicles",
            "subcategory":"Fuel & Gas Station",
            "type":"Retail Goods"
        }
    ],
    "sg:phone":"+61 2 9525 6971",
    "sg:postcode":"2228",
    "sg:province":"NSW",
    "wof:name":"Caltex Ampol Service Station",
    "wof:placetype":"venue"
},
  "geometry": {"coordinates":[151.10406494099999,-34.0345191956],"type":"Point"}
}