{
  "type": "Feature",
  "properties": {
    "addr:full":"40 Balonne St Runcorn QLD 4113",
    "addr:housenumber":"40",
    "addr:postcode":"4113",
    "addr:street":"Balonne St",
    "iso:country":"AU",
    "sg:address":"40 Balonne St",
    "sg:city":"Runcorn",
    "sg:classifiers":[
        {
            "category":"Education",
            "subcategory":"Music School",
            "type":"Public Place"
        }
    ],
    "sg:phone":"+61 7 3273 8377",
    "sg:postcode":"4113",
    "sg:province":"QLD",
    "sg:tags":[
        "teacher"
    ],
    "wof:name":"Narelle Close",
    "wof:placetype":"venue"
},
  "geometry": {"coordinates":[153.066314697,-27.6058616638],"type":"Point"}
}