{
  "type": "Feature",
  "properties": {
    "addr:full":"78a Glebe Rd The Junction NSW 2291",
    "addr:housenumber":"78a",
    "addr:postcode":"2291",
    "addr:street":"Glebe Rd",
    "iso:country":"AU",
    "sg:address":"78a Glebe Rd",
    "sg:city":"The Junction",
    "sg:classifiers":[
        {
            "category":"Deli",
            "type":"Food & Drink"
        }
    ],
    "sg:phone":"+61 2 4969 6846",
    "sg:postcode":"2291",
    "sg:province":"NSW",
    "sg:tags":[
        "delicatessen"
    ],
    "wof:name":"Gourmet Kitchen",
    "wof:placetype":"venue"
},
  "geometry": {"coordinates":[151.75880432100001,-32.938533783],"type":"Point"}
}