{
  "type": "Feature",
  "properties": {
    "iso:country":"AU",
    "sg:address":"510 Irish Town Rd",
    "sg:city":"Irish Town",
    "sg:classifiers":[
        {
            "category":"Home & Garden",
            "subcategory":"Building Materials",
            "type":"Retail Goods"
        }
    ],
    "sg:phone":"+61 3 6456 1331",
    "sg:postcode":"7330",
    "sg:province":"TAS",
    "sg:tags":[
        "merchant",
        "glass",
        "glazier"
    ],
    "wof:name":"Smithton Glass",
    "wof:placetype":"venue"
},
  "geometry": {"coordinates":[145.14541600000001,-40.904167],"type":"Point"}
}