{
  "type": "Feature",
  "properties": {
    "iso:country":"AU",
    "sg:address":"19a Ethel Ave",
    "sg:city":"Brookvale",
    "sg:classifiers":[
        {
            "category":"Retail",
            "subcategory":"Auto Repair",
            "type":"Services"
        }
    ],
    "sg:phone":"+61 2 9939 1742",
    "sg:postcode":"2100",
    "sg:province":"NSW",
    "sg:tags":[
        "beater",
        "painter",
        "panel"
    ],
    "wof:name":"Straightline Paint & Panel Pty Ltd",
    "wof:placetype":"venue"
},
  "geometry": {"coordinates":[151.27812194800001,-33.7666854858],"type":"Point"}
}