{
  "type": "Feature",
  "properties": {
    "addr:full":"Armadale Primary School 1 Carradine Rd Armadale WA 6112",
    "addr:housenumber":"1",
    "addr:postcode":"6112",
    "addr:street":"Carradine Rd",
    "iso:country":"AU",
    "sg:address":"Armadale Primary School 1 Carradine Rd",
    "sg:city":"Armadale",
    "sg:classifiers":[
        {
            "category":"Education",
            "subcategory":"School",
            "type":"Public Place"
        }
    ],
    "sg:phone":"+61 8 9399 2200",
    "sg:postcode":"6112",
    "sg:province":"WA",
    "sg:tags":[
        "state",
        "except",
        "nsw"
    ],
    "wof:name":"Schools Government (Public)",
    "wof:placetype":"venue"
},
  "geometry": {"coordinates":[116.030700684,-32.1432189941],"type":"Point"}
}