{
  "type": "Feature",
  "properties": {
    "iso:country":"AU",
    "sg:address":"3/ 38 Station St",
    "sg:city":"Wentworth Falls",
    "sg:classifiers":[
        {
            "category":"Personal",
            "subcategory":"Massage",
            "type":"Services"
        }
    ],
    "sg:phone":"+61 439 900 550",
    "sg:postcode":"2782",
    "sg:province":"NSW",
    "sg:tags":[
        "therapy"
    ],
    "wof:name":"Mountain Massage Matters",
    "wof:placetype":"venue"
},
  "geometry": {"coordinates":[150.375686645,-33.7084846497],"type":"Point"}
}