{
  "type": "Feature",
  "properties": {
    "iso:country":"AU",
    "sg:address":"Gate 3 Verdun St",
    "sg:city":"Nedlands",
    "sg:classifiers":[
        {
            "category":"Health Services",
            "subcategory":"Doctor",
            "type":"Services"
        }
    ],
    "sg:phone":"+61 8 9386 6211",
    "sg:postcode":"6009",
    "sg:province":"WA",
    "sg:tags":[
        "medical",
        "practitioner"
    ],
    "wof:name":"Wood D.J. Prof",
    "wof:placetype":"venue"
},
  "geometry": {"coordinates":[115.807678,-31.967211],"type":"Point"}
}