{
  "type": "Feature",
  "properties": {
    "addr:full":"2/8A Craftsman Ave Berkeley Vale NSW 2261",
    "addr:housenumber":"/ 8a",
    "addr:postcode":"2261",
    "addr:street":"Craftsman Ave",
    "iso:country":"AU",
    "sg:address":"2/8A Craftsman Ave",
    "sg:city":"Berkeley Vale",
    "sg:classifiers":[
        {
            "category":"Shopping",
            "subcategory":"Crafts & Fabrics",
            "type":"Retail Goods"
        }
    ],
    "sg:phone":"+61 2 4389 4755",
    "sg:postcode":"2261",
    "sg:province":"NSW",
    "sg:tags":[
        "synthetic",
        "canvas",
        "product"
    ],
    "wof:name":"Great Rugs",
    "wof:placetype":"venue"
},
  "geometry": {"coordinates":[151.42245500000001,-33.328217],"type":"Point"}
}