{
  "type": "Feature",
  "properties": {
    "addr:full":"12 Beaumont St Hamilton NSW 2303",
    "addr:housenumber":"12",
    "addr:postcode":"2303",
    "addr:street":"Beaumont St",
    "iso:country":"AU",
    "sg:address":"12 Beaumont St",
    "sg:city":"Hamilton",
    "sg:classifiers":[
        {
            "category":"Restaurant",
            "type":"Food & Drink"
        }
    ],
    "sg:phone":"+61 2 4940 8050",
    "sg:postcode":"2303",
    "sg:province":"NSW",
    "sg:tags":[
        "theatre"
    ],
    "wof:name":"Kavon Theme Restaurant",
    "wof:placetype":"venue"
},
  "geometry": {"coordinates":[151.74735999999999,-32.920998],"type":"Point"}
}