{
  "type": "Feature",
  "properties": {
    "iso:country":"AU",
    "sg:address":"38 McKechnie St St",
    "sg:city":"Albans",
    "sg:classifiers":[
        {
            "category":"Travel",
            "subcategory":"Hotels & Motels",
            "type":"Entertainment"
        }
    ],
    "sg:phone":"+61 3 9366 2066",
    "sg:postcode":"3021",
    "sg:province":"VIC",
    "sg:tags":[
        "pub"
    ],
    "wof:name":"St Albans Hotel",
    "wof:placetype":"venue"
},
  "geometry": {"coordinates":[144.79948400000001,-37.747398],"type":"Point"}
}