{
  "type": "Feature",
  "properties": {
    "addr:full":"16- 18 Powers Rd Seven Hills NSW 1730",
    "addr:housenumber":"18",
    "addr:postcode":"1730",
    "addr:street":"Powers Rd",
    "iso:country":"AU",
    "sg:address":"16- 18 Powers Rd",
    "sg:city":"Seven Hills",
    "sg:classifiers":[
        {
            "category":"Government",
            "subcategory":"Post Office",
            "type":"Public Place"
        }
    ],
    "sg:phone":"+61 2 9955 7580",
    "sg:postcode":"1730",
    "sg:province":"NSW",
    "sg:tags":[
        "chair",
        "manufacturer"
    ],
    "wof:name":"Australian Made Office Chairs",
    "wof:placetype":"venue"
},
  "geometry": {"coordinates":[150.94413757300001,-33.7740516663],"type":"Point"}
}