{
  "type": "Feature",
  "properties": {
    "addr:full":"206 The Entrance Rd Erina NSW 2250",
    "addr:housenumber":"206",
    "addr:postcode":"2250",
    "addr:street":"The Entrance Rd",
    "iso:country":"AU",
    "sg:address":"206 The Entrance Rd",
    "sg:city":"Erina",
    "sg:classifiers":[
        {
            "category":"Professional",
            "subcategory":"Accounting & Tax Preparation",
            "type":"Services"
        }
    ],
    "sg:phone":"+61 2 4367 6263",
    "sg:postcode":"2250",
    "sg:province":"NSW",
    "sg:tags":[
        "accountant",
        "auditor"
    ],
    "wof:name":"Richmond G A & Co",
    "wof:placetype":"venue"
},
  "geometry": {"coordinates":[151.390792847,-33.4333229065],"type":"Point"}
}