{
  "type": "Feature",
  "properties": {
    "addr:full":"Shop 3/25- 35a Park Rd Hurstville NSW 2220",
    "addr:housenumber":"shop 3 / 25 35a",
    "addr:postcode":"2220",
    "addr:street":"Park Rd",
    "iso:country":"AU",
    "sg:address":"Shop 3/25- 35a Park Rd",
    "sg:city":"Hurstville",
    "sg:classifiers":[
        {
            "category":"Real Estate",
            "subcategory":"Real Estate Agent",
            "type":"Services"
        }
    ],
    "sg:phone":"+61 2 9585 1088",
    "sg:postcode":"2220",
    "sg:province":"NSW",
    "wof:name":"Centaline International Properties",
    "wof:placetype":"venue"
},
  "geometry": {"coordinates":[151.10467529300001,-33.9654121399],"type":"Point"}
}