{
  "type": "Feature",
  "properties": {
    "addr:full":"61 Boundary Rd North Melbourne VIC 3051",
    "addr:housenumber":"61",
    "addr:postcode":"3051",
    "addr:street":"Boundary Rd",
    "iso:country":"AU",
    "sg:address":"61 Boundary Rd",
    "sg:city":"North Melbourne",
    "sg:classifiers":[
        {
            "category":"Home & Garden",
            "subcategory":"Hardware",
            "type":"Retail Goods"
        }
    ],
    "sg:phone":"+61 3 9348 9099",
    "sg:postcode":"3051",
    "sg:province":"VIC",
    "sg:tags":[
        "plumber",
        "supply"
    ],
    "wof:name":"Tradelink Plumbing Centres",
    "wof:placetype":"venue"
},
  "geometry": {"coordinates":[144.93907165499999,-37.7935447693],"type":"Point"}
}