{
  "type": "Feature",
  "properties": {
    "addr:full":"186 Baylis St Wagga Wagga NSW 2650",
    "addr:housenumber":"186",
    "addr:postcode":"2650",
    "addr:street":"Baylis St",
    "iso:country":"AU",
    "sg:address":"186 Baylis St",
    "sg:city":"Wagga Wagga",
    "sg:classifiers":[
        {
            "category":"Banks & Credit Unions",
            "subcategory":"Bank",
            "type":"Services"
        }
    ],
    "sg:phone":"+61 2 6921 9163",
    "sg:postcode":"2650",
    "sg:province":"NSW",
    "wof:name":"St. George Bank Rural & Business Banking",
    "wof:placetype":"venue"
},
  "geometry": {"coordinates":[147.37002563499999,-35.1117668152],"type":"Point"}
}