{
  "type": "Feature",
  "properties": {
    "addr:full":"13 Rendle St Aitkenvale QLD 4814",
    "addr:housenumber":"13",
    "addr:postcode":"4814",
    "addr:street":"Rendle St",
    "iso:country":"AU",
    "sg:address":"13 Rendle St",
    "sg:city":"Aitkenvale",
    "sg:classifiers":[
        {
            "category":"Professional",
            "subcategory":"Detective & Security Services",
            "type":"Services"
        }
    ],
    "sg:phone":"+61 7 4725 6044",
    "sg:postcode":"4814",
    "sg:province":"QLD",
    "sg:tags":[
        "equipment",
        "window",
        "doors"
    ],
    "wof:name":"Townsville Windows & Screens",
    "wof:placetype":"venue"
},
  "geometry": {"coordinates":[146.767944,-19.292519],"type":"Point"}
}