{
  "type": "Feature",
  "properties": {
    "addr:full":"27 Princeton Ave Cape Woolamai VIC 3925",
    "addr:housenumber":"27",
    "addr:postcode":"3925",
    "addr:street":"Princeton Ave",
    "iso:country":"AU",
    "sg:address":"27 Princeton Ave",
    "sg:city":"Cape Woolamai",
    "sg:classifiers":[
        {
            "category":"Building & Trades",
            "subcategory":"Plumbing",
            "type":"Services"
        }
    ],
    "sg:phone":"+61 418 347 969",
    "sg:postcode":"3925",
    "sg:province":"VIC",
    "sg:tags":[
        "plumber",
        "gasfitters"
    ],
    "wof:name":"Scott Lagler Plumbing Services",
    "wof:placetype":"venue"
},
  "geometry": {"coordinates":[145.333084106,-38.5288581848],"type":"Point"}
}