{
  "type": "Feature",
  "properties": {
    "addr:full":"30 Coulson Way Canning Vale WA 6155",
    "addr:housenumber":"30",
    "addr:postcode":"6155",
    "addr:street":"Coulson Way",
    "iso:country":"AU",
    "sg:address":"30 Coulson Way",
    "sg:city":"Canning Vale",
    "sg:classifiers":[
        {
            "category":"Manufacturing",
            "subcategory":"Tools & Machinery",
            "type":"Manufacturing & Wholesale Goods"
        }
    ],
    "sg:phone":"+61 8 9459 9100",
    "sg:postcode":"6155",
    "sg:province":"WA",
    "sg:tags":[
        "earth",
        "excavating",
        "moving",
        "equipment"
    ],
    "wof:name":"B & J Breaker Hire",
    "wof:placetype":"venue"
},
  "geometry": {"coordinates":[115.931511,-32.057533],"type":"Point"}
}