{
  "type": "Feature",
  "properties": {
    "iso:country":"AU",
    "sg:address":"Stall 20",
    "sg:city":"Preston Market Preston",
    "sg:classifiers":[
        {
            "category":"Professional",
            "subcategory":"Art Services",
            "type":"Services"
        }
    ],
    "sg:phone":"+61 3 9459 5125",
    "sg:postcode":"3072",
    "sg:province":"VIC",
    "sg:tags":[
        "picture",
        "frame",
        "framing"
    ],
    "wof:name":"Art, Frames & Graphix",
    "wof:placetype":"venue"
},
  "geometry": {"coordinates":[145.003829956,-37.7411155701],"type":"Point"}
}