{
  "type": "Feature",
  "properties": {
    "addr:full":"2/ 18-20 Redland Drv Mitcham VIC 3132",
    "addr:housenumber":"/ 18-20",
    "addr:postcode":"3132",
    "addr:street":"Redland Drv",
    "iso:country":"AU",
    "sg:address":"2/ 18-20 Redland Drv",
    "sg:city":"Mitcham",
    "sg:classifiers":[
        {
            "category":"Wholesale",
            "subcategory":"Medical Equipment & Supplies",
            "type":"Manufacturing & Wholesale Goods"
        }
    ],
    "sg:phone":"+61 3 9874 3993",
    "sg:postcode":"3132",
    "sg:province":"VIC",
    "sg:tags":[
        "dental"
    ],
    "wof:name":"Maestro Dental & Cosmetics Pty Ltd",
    "wof:placetype":"venue"
},
  "geometry": {"coordinates":[145.19065856899999,-37.8301353455],"type":"Point"}
}