{
  "type": "Feature",
  "properties": {
    "iso:country":"AU",
    "sg:address":"10 Railway St",
    "sg:city":"Gatton",
    "sg:classifiers":[
        {
            "category":"Shopping",
            "subcategory":"Bicycles & Sporting Goods",
            "type":"Retail Goods"
        }
    ],
    "sg:phone":"+61 7 5462 1476",
    "sg:postcode":"4343",
    "sg:province":"QLD",
    "sg:tags":[
        "trampoline"
    ],
    "wof:name":"Toyworld Gatton",
    "wof:placetype":"venue"
},
  "geometry": {"coordinates":[152.276977539,-27.5571594238],"type":"Point"}
}