{
  "type": "Feature",
  "properties": {
    "iso:country":"AU",
    "sg:address":"PO Box 1086",
    "sg:city":"Flinders Park",
    "sg:classifiers":[
        {
            "category":"Building & Trades",
            "subcategory":"Construction",
            "type":"Services"
        }
    ],
    "sg:phone":"+61 411 631 757",
    "sg:postcode":"5025",
    "sg:province":"SA",
    "sg:tags":[
        "polishing",
        "sanding",
        "floor"
    ],
    "wof:name":"Timber Flooring Association Of S.A. Inc",
    "wof:placetype":"venue"
},
  "geometry": {"coordinates":[138.53338623100001,-34.9096412659],"type":"Point"}
}