{
  "type": "Feature",
  "properties": {
    "addr:full":"72 Beaufort Rd Croydon VIC 3136",
    "addr:housenumber":"72",
    "addr:postcode":"3136",
    "addr:street":"Beaufort Rd",
    "iso:country":"AU",
    "sg:address":"72 Beaufort Rd",
    "sg:city":"Croydon",
    "sg:classifiers":[
        {
            "category":"Education",
            "subcategory":"Vocational School",
            "type":"Public Place"
        }
    ],
    "sg:phone":"+61 3 9894 0388",
    "sg:postcode":"3136",
    "sg:province":"VIC",
    "sg:tags":[
        "beauty"
    ],
    "wof:name":"International School of Health & Beauty Pty Ltd",
    "wof:placetype":"venue"
},
  "geometry": {"coordinates":[145.25765991200001,-37.7965049744],"type":"Point"}
}