{
  "type": "Feature",
  "properties": {
    "addr:full":"Shop 4 62 May Rd Narraweena NSW 2099",
    "addr:housenumber":"shop;62",
    "addr:postcode":"2099",
    "addr:street":"May Rd",
    "iso:country":"AU",
    "sg:address":"Shop 4 62 May Rd",
    "sg:city":"Narraweena",
    "sg:classifiers":[
        {
            "category":"Food & Beverages",
            "subcategory":"Groceries & Convenience Stores",
            "type":"Retail Goods"
        }
    ],
    "sg:phone":"+61 2 9981 3889",
    "sg:postcode":"2099",
    "sg:province":"NSW",
    "wof:name":"Lucy's Mixed Business",
    "wof:placetype":"venue"
},
  "geometry": {"coordinates":[151.27577209500001,-33.755355835],"type":"Point"}
}