{
  "type": "Feature",
  "properties": {
    "iso:country":"AU",
    "sg:address":"Shp7/ 1 Mansbridge St",
    "sg:city":"Leinster",
    "sg:classifiers":[
        {
            "category":"Personal",
            "subcategory":"Beauty Salon",
            "type":"Services"
        }
    ],
    "sg:phone":"+61 438 962 894",
    "sg:postcode":"6437",
    "sg:province":"WA",
    "sg:tags":[
        "hairdresser"
    ],
    "wof:name":"Superfx Hair Designs",
    "wof:placetype":"venue"
},
  "geometry": {"coordinates":[120.69526672400001,-27.9378890991],"type":"Point"}
}