{
  "type": "Feature",
  "properties": {
    "iso:country":"AU",
    "sg:address":"Mt Seaview Oxley Hwy Via",
    "sg:city":"Wauchope",
    "sg:classifiers":[
        {
            "category":"Building & Trades",
            "subcategory":"Landscaping Services",
            "type":"Services"
        }
    ],
    "sg:phone":"+61 2 6587 7133",
    "sg:postcode":"2446",
    "sg:province":"NSW",
    "sg:tags":[
        "grazier"
    ],
    "wof:name":"Clissold E M & R L",
    "wof:placetype":"venue"
},
  "geometry": {"coordinates":[152.733734,-31.457371],"type":"Point"}
}