{
  "type": "Feature",
  "properties": {
    "iso:country":"AU",
    "sg:address":"424 Bellevue St",
    "sg:city":"Albury",
    "sg:classifiers":[
        {
            "category":"Professional",
            "subcategory":"Business Services",
            "type":"Services"
        }
    ],
    "sg:phone":"+61 428 933 723",
    "sg:postcode":"2640",
    "sg:province":"NSW",
    "sg:tags":[
        "drafting"
    ],
    "wof:name":"Yanden Pty Ltd",
    "wof:placetype":"venue"
},
  "geometry": {"coordinates":[146.92686462399999,-36.065612793],"type":"Point"}
}