{
  "type": "Feature",
  "properties": {
    "addr:full":"Lot 3129 Muramats Rd Berrimah NT 0828",
    "addr:housenumber":"3129",
    "addr:postcode":"nt 0828",
    "addr:street":"Muramats Rd",
    "iso:country":"AU",
    "sg:address":"Lot 3129 Muramats Rd",
    "sg:city":"Berrimah",
    "sg:classifiers":[
        {
            "category":"Parking",
            "subcategory":"Bicycle",
            "type":"Transportation"
        }
    ],
    "sg:phone":"+61 8 8947 0744",
    "sg:postcode":"0828",
    "sg:province":"NT",
    "sg:tags":[
        "consultant",
        "shipping"
    ],
    "wof:name":"QAL Shipping & Specialised Transport",
    "wof:placetype":"venue"
},
  "geometry": {"coordinates":[130.92489624000001,-12.4796762466],"type":"Point"}
}