{
  "type": "Feature",
  "properties": {
    "iso:country":"AU",
    "sg:address":"2 Cade Pl",
    "sg:city":"Greenwood",
    "sg:classifiers":[
        {
            "category":"Building & Trades",
            "subcategory":"Construction",
            "type":"Services"
        }
    ],
    "sg:phone":"+61 8 9447 9439",
    "sg:postcode":"6024",
    "sg:province":"WA",
    "sg:tags":[
        "contractor"
    ],
    "wof:name":"Cade Constructions",
    "wof:placetype":"venue"
},
  "geometry": {"coordinates":[115.806808472,-31.8254451752],"type":"Point"}
}