{
  "type": "Feature",
  "properties": {
    "iso:country":"AU",
    "sg:address":"8 Moreau Mews",
    "sg:city":"Applecross",
    "sg:classifiers":[
        {
            "category":"Building & Trades",
            "subcategory":"Landscaping Services",
            "type":"Services"
        }
    ],
    "sg:phone":"+61 8 9315 9421",
    "sg:postcode":"6153",
    "sg:province":"WA",
    "sg:tags":[
        "gardener"
    ],
    "wof:name":"Jansen's Gardening Services",
    "wof:placetype":"venue"
},
  "geometry": {"coordinates":[115.849197,-32.010616],"type":"Point"}
}