{
  "type": "Feature",
  "properties": {
    "addr:full":"Memorial Drv Granville NSW 2142",
    "addr:postcode":"2142",
    "addr:street":"Memorial Drv",
    "iso:country":"AU",
    "sg:address":"Memorial Drv",
    "sg:city":"Granville",
    "sg:classifiers":[
        {
            "category":"Retail",
            "subcategory":"Event Space",
            "type":"Services"
        }
    ],
    "sg:phone":"+61 2 9637 7888",
    "sg:postcode":"2142",
    "sg:province":"NSW",
    "sg:tags":[
        "venue",
        "reception",
        "wedding"
    ],
    "wof:name":"Granville RSL Sub-Branch Club Ltd",
    "wof:placetype":"venue"
},
  "geometry": {"coordinates":[151.01072692899999,-33.8323287964],"type":"Point"}
}