{
  "type": "Feature",
  "properties": {
    "addr:full":"220 Coogee Bay Rd Coogee NSW 2034",
    "addr:housenumber":"220",
    "addr:postcode":"2034",
    "addr:street":"Coogee Bay Rd",
    "iso:country":"AU",
    "sg:address":"220 Coogee Bay Rd",
    "sg:city":"Coogee",
    "sg:classifiers":[
        {
            "category":"Shopping",
            "subcategory":"Shoes",
            "type":"Retail Goods"
        }
    ],
    "sg:phone":"+61 2 9664 6462",
    "sg:postcode":"2034",
    "sg:province":"NSW",
    "sg:tags":[
        "footwear"
    ],
    "wof:name":"By San Sebastian",
    "wof:placetype":"venue"
},
  "geometry": {"coordinates":[151.25506591800001,-33.9204101562],"type":"Point"}
}