{
  "type": "Feature",
  "properties": {
    "addr:full":"Neighbourhood Centre Hayden Brook Rd Woodrising NSW 2284",
    "addr:postcode":"2284",
    "addr:street":"Hayden Brook Rd",
    "iso:country":"AU",
    "sg:address":"Neighbourhood Centre Hayden Brook Rd",
    "sg:city":"Woodrising",
    "sg:classifiers":[
        {
            "category":"Social Services",
            "subcategory":"Child Care",
            "type":"Services"
        }
    ],
    "sg:phone":"+61 2 4959 1762",
    "sg:postcode":"2284",
    "sg:province":"NSW",
    "sg:tags":[
        "support",
        "health"
    ],
    "wof:name":"Child Health Centres",
    "wof:placetype":"venue"
},
  "geometry": {"coordinates":[151.60534668,-32.982170105],"type":"Point"}
}