{
  "type": "Feature",
  "properties": {
    "iso:country":"AU",
    "sg:address":"4 McMullen Ave",
    "sg:city":"Castle Hill",
    "sg:classifiers":[
        {
            "category":"Social Services",
            "subcategory":"Child Care",
            "type":"Services"
        }
    ],
    "sg:phone":"+61 2 9634 2658",
    "sg:postcode":"2154",
    "sg:province":"NSW",
    "sg:tags":[
        "support",
        "health"
    ],
    "wof:name":"Early Childhood Health Centres",
    "wof:placetype":"venue"
},
  "geometry": {"coordinates":[151.00953674300001,-33.7306442261],"type":"Point"}
}