{
  "type": "Feature",
  "properties": {
    "iso:country":"AU",
    "sg:address":"16 St. Cloud St",
    "sg:city":"Novar Gardens",
    "sg:classifiers":[
        {
            "category":"Utilities",
            "subcategory":"Electric",
            "type":"Services"
        }
    ],
    "sg:phone":"+61 415 358 250",
    "sg:postcode":"5040",
    "sg:province":"SA",
    "sg:tags":[
        "electrical",
        "contractor"
    ],
    "wof:name":"Jason Newberry Electrical",
    "wof:placetype":"venue"
},
  "geometry": {"coordinates":[138.530777,-34.963573],"type":"Point"}
}