{
  "type": "Feature",
  "properties": {
    "iso:country":"AU",
    "sg:address":"90A Murphy St",
    "sg:city":"Wangaratta",
    "sg:classifiers":[
        {
            "category":"Fast Food",
            "type":"Food & Drink"
        }
    ],
    "sg:phone":"+61 3 5723 4800",
    "sg:postcode":"3676",
    "sg:province":"VIC",
    "sg:tags":[
        "away",
        "take"
    ],
    "wof:name":"Domino's Pizza",
    "wof:placetype":"venue"
},
  "geometry": {"coordinates":[146.32756000000001,-36.354881],"type":"Point"}
}