{
  "type": "Feature",
  "properties": {
    "addr:full":"Caves Rd Busselton WA 6280",
    "addr:postcode":"6280",
    "addr:street":"Caves Rd",
    "iso:country":"AU",
    "sg:address":"Caves Rd",
    "sg:city":"Busselton",
    "sg:classifiers":[
        {
            "category":"Building & Trades",
            "subcategory":"Construction",
            "type":"Services"
        }
    ],
    "sg:phone":"+61 419 847 142",
    "sg:postcode":"6280",
    "sg:province":"WA",
    "sg:tags":[
        "joiner",
        "carpenter"
    ],
    "wof:name":"Eggemann J Carpentry",
    "wof:placetype":"venue"
},
  "geometry": {"coordinates":[115.25710296600001,-33.6605148315],"type":"Point"}
}