{
  "type": "Feature",
  "properties": {
    "iso:country":"AU",
    "sg:address":"141 Bamfield Rd",
    "sg:city":"Heidelberg West",
    "sg:classifiers":[
        {
            "category":"Manufacturing",
            "subcategory":"Building Materials",
            "type":"Manufacturing & Wholesale Goods"
        }
    ],
    "sg:phone":"+61 3 9457 7611",
    "sg:postcode":"3081",
    "sg:province":"VIC",
    "sg:tags":[
        "equipment",
        "handling"
    ],
    "wof:name":"Control Automation Pty Ltd",
    "wof:placetype":"venue"
},
  "geometry": {"coordinates":[145.05679321299999,-37.733215332],"type":"Point"}
}