{
  "type": "Feature",
  "properties": {
    "iso:country":"AU",
    "sg:address":"Shop 1 242 -246 Edmondson Ave",
    "sg:city":"Austral",
    "sg:classifiers":[
        {
            "category":"Fast Food",
            "type":"Food & Drink"
        }
    ],
    "sg:phone":"+61 2 9606 9873",
    "sg:postcode":"2179",
    "sg:province":"NSW",
    "sg:tags":[
        "away",
        "take"
    ],
    "wof:name":"Oasis Take Away Australia",
    "wof:placetype":"venue"
},
  "geometry": {"coordinates":[150.81192016599999,-33.9326896667],"type":"Point"}
}