{
  "type": "Feature",
  "properties": {
    "iso:country":"AU",
    "sg:address":"2/ 12 Candlebark Crt",
    "sg:city":"Research",
    "sg:classifiers":[
        {
            "category":"Retail",
            "subcategory":"Auto Repair",
            "type":"Services"
        }
    ],
    "sg:phone":"+61 3 9437 1922",
    "sg:postcode":"3095",
    "sg:province":"VIC",
    "sg:tags":[
        "beater",
        "painter",
        "panel"
    ],
    "wof:name":"Research Smash Repairs",
    "wof:placetype":"venue"
},
  "geometry": {"coordinates":[145.186676025,-37.6994361877],"type":"Point"}
}