{
  "type": "Feature",
  "properties": {
    "addr:full":"1284 Lytton Rd Hemmant QLD 4174",
    "addr:housenumber":"1284",
    "addr:postcode":"4174",
    "addr:street":"Lytton Rd",
    "iso:country":"AU",
    "sg:address":"1284 Lytton Rd",
    "sg:city":"Hemmant",
    "sg:classifiers":[
        {
            "category":"Manufacturing",
            "subcategory":"Paper Products",
            "type":"Manufacturing & Wholesale Goods"
        }
    ],
    "sg:phone":"+61 7 3390 4022",
    "sg:postcode":"4174",
    "sg:province":"QLD",
    "sg:tags":[
        "metal",
        "non-ferrous",
        "foundry"
    ],
    "wof:name":"Rogers Industries",
    "wof:placetype":"venue"
},
  "geometry": {"coordinates":[153.12159729000001,-27.4447288513],"type":"Point"}
}