{
  "type": "Feature",
  "properties": {
    "addr:full":"525 Stirling Hwy (Cnr Forrest Rd) Cottesloe WA 6011",
    "addr:housenumber":"525",
    "addr:postcode":"6011",
    "addr:street":"Stirling Hwy Cnr Forrest Rd",
    "iso:country":"AU",
    "sg:address":"525 Stirling Hwy (Cnr Forrest Rd)",
    "sg:city":"Cottesloe",
    "sg:classifiers":[
        {
            "category":"Health Services",
            "subcategory":"Dentist",
            "type":"Services"
        }
    ],
    "sg:phone":"+61 8 9384 5866",
    "sg:postcode":"6011",
    "sg:province":"WA",
    "wof:name":"LifeCare Cottesloe (Dental)",
    "wof:placetype":"venue"
},
  "geometry": {"coordinates":[115.760269165,-32.0032272339],"type":"Point"}
}