{
  "type": "Feature",
  "properties": {
    "addr:full":"184 High St Maryborough VIC 3465",
    "addr:housenumber":"184",
    "addr:postcode":"3465",
    "addr:street":"High St",
    "iso:country":"AU",
    "sg:address":"184 High St",
    "sg:city":"Maryborough",
    "sg:classifiers":[
        {
            "category":"Food & Beverages",
            "subcategory":"Bakery",
            "type":"Retail Goods"
        }
    ],
    "sg:phone":"+61 3 5461 1113",
    "sg:postcode":"3465",
    "sg:province":"VIC",
    "sg:tags":[
        "baker"
    ],
    "wof:name":"Red House Bakery",
    "wof:placetype":"venue"
},
  "geometry": {"coordinates":[143.73866272000001,-37.0463523865],"type":"Point"}
}