{
  "type": "Feature",
  "properties": {
    "iso:country":"AU",
    "sg:address":"360 Murray St",
    "sg:city":"Perth",
    "sg:classifiers":[
        {
            "category":"Industrial Area",
            "type":"Public Place"
        }
    ],
    "sg:phone":"+61 8 9322 5900",
    "sg:postcode":"6000",
    "sg:province":"WA",
    "sg:tags":[
        "protective",
        "clothing"
    ],
    "wof:name":"Midland Disposals Stores",
    "wof:placetype":"venue"
},
  "geometry": {"coordinates":[115.854919434,-31.9514484406],"type":"Point"}
}