{
  "type": "Feature",
  "properties": {
    "addr:full":"18 Reid St Wodonga NSW 3690",
    "addr:housenumber":"18",
    "addr:postcode":"3690",
    "addr:street":"Reid St",
    "iso:country":"AU",
    "sg:address":"18 Reid St",
    "sg:city":"Wodonga",
    "sg:classifiers":[
        {
            "category":"Utilities",
            "type":"Services"
        }
    ],
    "sg:phone":"+61 2 6056 1866",
    "sg:postcode":"3690",
    "sg:province":"NSW",
    "sg:tags":[
        "equipment",
        "towing"
    ],
    "wof:name":"Bobs Exhaust Centre",
    "wof:placetype":"venue"
},
  "geometry": {"coordinates":[146.895187378,-36.1236152649],"type":"Point"}
}