{
  "type": "Feature",
  "properties": {
    "addr:full":"81 Rushdale St Knoxfield VIC 3180",
    "addr:housenumber":"81",
    "addr:postcode":"3180",
    "addr:street":"Rushdale St",
    "iso:country":"AU",
    "sg:address":"81 Rushdale St",
    "sg:city":"Knoxfield",
    "sg:classifiers":[
        {
            "category":"Personal",
            "subcategory":"Beauty Salon",
            "type":"Services"
        }
    ],
    "sg:phone":"+61 1300 854 484",
    "sg:postcode":"3180",
    "sg:province":"VIC",
    "sg:tags":[
        "hairdresser"
    ],
    "wof:name":"Price Attack",
    "wof:placetype":"venue"
},
  "geometry": {"coordinates":[145.255615234,-37.895275116],"type":"Point"}
}