{
  "type": "Feature",
  "properties": {
    "iso:country":"AU",
    "sg:address":"140 Creek St",
    "sg:city":"Brisbane",
    "sg:classifiers":[
        {
            "category":"Sports & Exercise",
            "subcategory":"Gym",
            "type":"Entertainment"
        }
    ],
    "sg:phone":"+61 7 3211 9970",
    "sg:postcode":"4000",
    "sg:province":"QLD",
    "sg:tags":[
        "health",
        "fitness"
    ],
    "wof:name":"Brisbane Fitness Centre",
    "wof:placetype":"venue"
},
  "geometry": {"coordinates":[153.02746582,-27.4659996033],"type":"Point"}
}