{
  "type": "Feature",
  "properties": {
    "iso:country":"AU",
    "sg:address":"1 Opal Pl",
    "sg:city":"Gymea",
    "sg:classifiers":[
        {
            "category":"Manufacturing",
            "subcategory":"Tools & Machinery",
            "type":"Manufacturing & Wholesale Goods"
        }
    ],
    "sg:phone":"+61 2 9525 4738",
    "sg:postcode":"2227",
    "sg:province":"NSW",
    "sg:tags":[
        "supplier",
        "diamond"
    ],
    "wof:name":"National Diamond Tools",
    "wof:placetype":"venue"
},
  "geometry": {"coordinates":[151.08685302699999,-34.0265693665],"type":"Point"}
}