{
  "type": "Feature",
  "properties": {
    "iso:country":"AU",
    "sg:address":"169 Morley Drv",
    "sg:city":"Nollamara",
    "sg:classifiers":[
        {
            "category":"Social Services",
            "subcategory":"Retirement Home",
            "type":"Services"
        }
    ],
    "sg:phone":"+61 417 186 338",
    "sg:postcode":"6061",
    "sg:province":"WA",
    "sg:tags":[
        "decoration",
        "supplier",
        "contractor"
    ],
    "wof:name":"The Wedding Decorator",
    "wof:placetype":"venue"
},
  "geometry": {"coordinates":[115.847160339,-31.8887443542],"type":"Point"}
}