{
  "type": "Feature",
  "properties": {
    "addr:full":"PO Box 63 North Perth WA 6906",
    "addr:postcode":"6906",
    "iso:country":"AU",
    "sg:address":"PO Box 63",
    "sg:city":"North Perth",
    "sg:classifiers":[
        {
            "category":"Building & Trades",
            "subcategory":"Construction",
            "type":"Services"
        }
    ],
    "sg:phone":"+61 8 9242 8725",
    "sg:postcode":"6906",
    "sg:province":"WA",
    "sg:tags":[
        "roof"
    ],
    "wof:name":"Advanced Metal Roofing",
    "wof:placetype":"venue"
},
  "geometry": {"coordinates":[115.85684204099999,-31.9317092896],"type":"Point"}
}