{
  "type": "Feature",
  "properties": {
    "iso:country":"AU",
    "sg:address":"Blk 96",
    "sg:city":"c Robinvale",
    "sg:classifiers":[
        {
            "category":"Farming",
            "subcategory":"Berry Farm",
            "type":"Manufacturing & Wholesale Goods"
        }
    ],
    "sg:phone":"+61 3 5026 1486",
    "sg:postcode":"3549",
    "sg:province":"VIC",
    "sg:tags":[
        "fruit",
        "grower"
    ],
    "wof:name":"O&#039;Brien P W & P M",
    "wof:placetype":"venue"
},
  "geometry": {"coordinates":[142.770065308,-34.5829200745],"type":"Point"}
}