{
  "type": "Feature",
  "properties": {
    "addr:full":"1st Flr 89- 91 Burwood Rd Burwood NSW 2134",
    "addr:housenumber":"89 91",
    "addr:postcode":"2134",
    "addr:street":"Burwood Rd",
    "iso:country":"AU",
    "sg:address":"1st Flr 89- 91 Burwood Rd",
    "sg:city":"Burwood",
    "sg:classifiers":[
        {
            "category":"Health Services",
            "subcategory":"Clinic",
            "type":"Services"
        }
    ],
    "sg:phone":"+61 2 9744 5143",
    "sg:postcode":"2134",
    "sg:province":"NSW",
    "sg:tags":[
        "aromatherapy"
    ],
    "wof:name":"Aromatherapists, International Federation Of",
    "wof:placetype":"venue"
},
  "geometry": {"coordinates":[151.10383605999999,-33.8758583069],"type":"Point"}
}