{
  "type": "Feature",
  "properties": {
    "iso:country":"AU",
    "sg:address":"115 Baylis St",
    "sg:city":"Wagga Wagga",
    "sg:classifiers":[
        {
            "category":"Real Estate",
            "subcategory":"Real Estate Agent",
            "type":"Services"
        }
    ],
    "sg:phone":"+61 2 6923 3555",
    "sg:postcode":"2650",
    "sg:province":"NSW",
    "sg:website":"http://www.prdwagga.com.au",
    "wof:name":"PRDnationwide Wagga Wagga",
    "wof:placetype":"venue"
},
  "geometry": {"coordinates":[147.369796753,-35.1144866943],"type":"Point"}
}