{
  "type": "Feature",
  "properties": {
    "iso:country":"AU",
    "sg:address":"24 Prince St",
    "sg:city":"Grafton",
    "sg:classifiers":[
        {
            "category":"Insurance",
            "subcategory":"Hazard Insurance",
            "type":"Services"
        }
    ],
    "sg:phone":"+61 2 6642 1061",
    "sg:postcode":"2460",
    "sg:province":"NSW",
    "sg:tags":[
        "fire",
        "accident",
        "marine"
    ],
    "wof:name":"Stephen Donnelly Financial Services",
    "wof:placetype":"venue"
},
  "geometry": {"coordinates":[152.933135986,-29.6916770935],"type":"Point"}
}