{
  "type": "Feature",
  "properties": {
    "addr:full":"Shop 11, Forest Shopping Centre, Cnr Beeville & Fr Petrie QLD 4502",
    "addr:housenumber":"shop 11",
    "addr:postcode":"4502",
    "addr:street":"Forest Shopping;Cnr",
    "iso:country":"AU",
    "sg:address":"Shop 11, Forest Shopping Centre, Cnr Beeville & Fr",
    "sg:city":"Petrie",
    "sg:classifiers":[
        {
            "category":"Food & Beverages",
            "subcategory":"Liquor & Beverages",
            "type":"Retail Goods"
        }
    ],
    "sg:phone":"+61 7 3285 1599",
    "sg:postcode":"4502",
    "sg:province":"QLD",
    "sg:tags":[
        "store"
    ],
    "wof:name":"Frenchs Forest",
    "wof:placetype":"venue"
},
  "geometry": {"coordinates":[152.96617126500001,-27.263879776],"type":"Point"}
}