{
  "type": "Feature",
  "properties": {
    "addr:full":"13 Chestnut St Logan Central QLD 4114",
    "addr:housenumber":"13",
    "addr:postcode":"4114",
    "addr:street":"Chestnut St",
    "iso:country":"AU",
    "sg:address":"13 Chestnut St",
    "sg:city":"Logan Central",
    "sg:classifiers":[
        {
            "category":"Manufacturing",
            "subcategory":"Metals",
            "type":"Manufacturing & Wholesale Goods"
        }
    ],
    "sg:phone":"+61 422 836 825",
    "sg:postcode":"4114",
    "sg:province":"QLD",
    "sg:tags":[
        "sheet",
        "worker"
    ],
    "wof:name":"Mc Master Metal Works",
    "wof:placetype":"venue"
},
  "geometry": {"coordinates":[153.10003662099999,-27.6506061554],"type":"Point"}
}