{
  "type": "Feature",
  "properties": {
    "addr:full":"35 Grandview Drv Tea Tree Gully SA 5091",
    "addr:housenumber":"35",
    "addr:postcode":"5091",
    "addr:street":"Grandview Drv",
    "iso:country":"AU",
    "sg:address":"35 Grandview Drv",
    "sg:city":"Tea Tree Gully",
    "sg:classifiers":[
        {
            "category":"Building & Trades",
            "subcategory":"Construction",
            "type":"Services"
        }
    ],
    "sg:phone":"+61 8 8414 1960",
    "sg:postcode":"5091",
    "sg:province":"SA",
    "sg:tags":[
        "industrial",
        "commercial",
        "air conditioning"
    ],
    "wof:name":"Chenoweth Martin Electrical",
    "wof:placetype":"venue"
},
  "geometry": {"coordinates":[138.72438049300001,-34.831161499],"type":"Point"}
}