{
  "type": "Feature",
  "properties": {
    "iso:country":"AU",
    "sg:address":"4 First Ave St",
    "sg:city":"Morris",
    "sg:classifiers":[
        {
            "category":"Building & Trades",
            "subcategory":"Construction",
            "type":"Services"
        }
    ],
    "sg:phone":"+61 413 000 777",
    "sg:postcode":"5068",
    "sg:province":"SA",
    "sg:tags":[
        "renovation",
        "alterations",
        "extension",
        "contractor"
    ],
    "wof:name":"United Carpentry & Builders",
    "wof:placetype":"venue"
},
  "geometry": {"coordinates":[138.651885986,-34.9134559631],"type":"Point"}
}