{
  "type": "Feature",
  "properties": {
    "addr:full":"Suite 205, City Plaza (Opp Canb Centre) 222 City Walk Canberra ACT 2600",
    "addr:housenumber":"222",
    "addr:postcode":"2600",
    "addr:street":"Opp Canb;City Walk",
    "iso:country":"AU",
    "sg:address":"Suite 205, City Plaza (Opp Canb Centre) 222",
    "sg:city":"City Walk Canberra",
    "sg:classifiers":[
        {
            "category":"Health Services",
            "subcategory":"Dentist",
            "type":"Services"
        }
    ],
    "sg:phone":"+61 2 6257 1638",
    "sg:postcode":"2600",
    "sg:province":"ACT",
    "wof:name":"Tatumaru Denisa Dr",
    "wof:placetype":"venue"
},
  "geometry": {"coordinates":[149.13351440400001,-35.2820205688],"type":"Point"}
}