{
  "type": "Feature",
  "properties": {
    "iso:country":"AU",
    "sg:address":"343 Somerville Rd",
    "sg:city":"Yarraville",
    "sg:classifiers":[
        {
            "category":"Fast Food",
            "type":"Food & Drink"
        }
    ],
    "sg:phone":"+61 3 9314 3996",
    "sg:postcode":"3013",
    "sg:province":"VIC",
    "sg:tags":[
        "away",
        "take"
    ],
    "wof:name":"Pizza Del Sole",
    "wof:placetype":"venue"
},
  "geometry": {"coordinates":[144.870529175,-37.8114547729],"type":"Point"}
}