{
  "type": "Feature",
  "properties": {
    "addr:full":"1/ 19 Woodbine Ave Normanhurst NSW 2076",
    "addr:housenumber":"/ 19",
    "addr:postcode":"2076",
    "addr:street":"Woodbine Ave",
    "iso:country":"AU",
    "sg:address":"1/ 19 Woodbine Ave",
    "sg:city":"Normanhurst",
    "sg:classifiers":[
        {
            "category":"Real Estate",
            "subcategory":"Architect",
            "type":"Services"
        }
    ],
    "sg:phone":"+61 2 9487 4900",
    "sg:postcode":"2076",
    "sg:province":"NSW",
    "wof:name":"Edmiston Robin & Assoc Pty Ltd",
    "wof:placetype":"venue"
},
  "geometry": {"coordinates":[151.098266602,-33.7178115845],"type":"Point"}
}