{
  "type": "Feature",
  "properties": {
    "iso:country":"AU",
    "sg:address":"58 Abercrombie St",
    "sg:city":"Chippendale",
    "sg:classifiers":[
        {
            "category":"Building & Trades",
            "subcategory":"Equipment Rental",
            "type":"Services"
        }
    ],
    "sg:phone":"+61 2 9699 6137",
    "sg:postcode":"2008",
    "sg:province":"NSW",
    "sg:tags":[
        "ironing"
    ],
    "wof:name":"Broven Ironing Board Cover Supply Co Pty Ltd",
    "wof:placetype":"venue"
},
  "geometry": {"coordinates":[151.19889831500001,-33.8863525391],"type":"Point"}
}