{
  "type": "Feature",
  "properties": {
    "addr:full":"57 Leah St Forestville SA 5035",
    "addr:housenumber":"57",
    "addr:postcode":"5035",
    "addr:street":"Leah St",
    "iso:country":"AU",
    "sg:address":"57 Leah St",
    "sg:city":"Forestville",
    "sg:classifiers":[
        {
            "category":"Home & Garden",
            "subcategory":"Carpets & Floor Coverings",
            "type":"Retail Goods"
        }
    ],
    "sg:phone":"+61 413 084 026",
    "sg:postcode":"5035",
    "sg:province":"SA",
    "sg:tags":[
        "tile",
        "wall",
        "layer"
    ],
    "wof:name":"Angelo Katsikas",
    "wof:placetype":"venue"
},
  "geometry": {"coordinates":[138.581573486,-34.9535102844],"type":"Point"}
}