{
  "type": "Feature",
  "properties": {
    "addr:full":"25 Bennett St Dee Why NSW 2099",
    "addr:housenumber":"25",
    "addr:postcode":"2099",
    "addr:street":"Bennett St",
    "iso:country":"AU",
    "sg:address":"25 Bennett St",
    "sg:city":"Dee Why",
    "sg:classifiers":[
        {
            "category":"Utilities",
            "subcategory":"Electric",
            "type":"Services"
        }
    ],
    "sg:phone":"+61 2 9981 3659",
    "sg:postcode":"2099",
    "sg:province":"NSW",
    "sg:tags":[
        "electrical",
        "contractor"
    ],
    "wof:name":"Smiles Steven",
    "wof:placetype":"venue"
},
  "geometry": {"coordinates":[151.28309631400001,-33.7487297058],"type":"Point"}
}