{
  "type": "Feature",
  "properties": {
    "addr:full":"2 Scottsdale Drv Robina QLD 4226",
    "addr:housenumber":"2",
    "addr:postcode":"4226",
    "addr:street":"Scottsdale Drv",
    "iso:country":"AU",
    "sg:address":"2 Scottsdale Drv",
    "sg:city":"Robina",
    "sg:classifiers":[
        {
            "category":"Restaurant",
            "type":"Food & Drink"
        }
    ],
    "sg:phone":"+61 7 5575 7955",
    "sg:postcode":"4226",
    "sg:province":"QLD",
    "wof:name":"Dog & Parrot Tavern",
    "wof:placetype":"venue"
},
  "geometry": {"coordinates":[153.38949585,-28.079580307],"type":"Point"}
}