{
  "type": "Feature",
  "properties": {
    "iso:country":"AU",
    "sg:address":"Suite 8/ 10 Eastbrook Tce",
    "sg:city":"East Perth",
    "sg:classifiers":[
        {
            "category":"Shopping",
            "subcategory":"Mobile Phones",
            "type":"Retail Goods"
        }
    ],
    "sg:phone":"+61 8 9325 1007",
    "sg:postcode":"6004",
    "sg:province":"WA",
    "sg:tags":[
        "telephone",
        "accessory"
    ],
    "wof:name":"Merc Technology- East Perth",
    "wof:placetype":"venue"
},
  "geometry": {"coordinates":[115.87670135499999,-31.9527664185],"type":"Point"}
}