{
  "type": "Feature",
  "properties": {
    "addr:full":"286 Rainbow St Coogee NSW 2034",
    "addr:housenumber":"286",
    "addr:postcode":"2034",
    "addr:street":"Rainbow St",
    "iso:country":"AU",
    "sg:address":"286 Rainbow St",
    "sg:city":"Coogee",
    "sg:classifiers":[
        {
            "category":"Real Estate",
            "subcategory":"Surveying",
            "type":"Services"
        }
    ],
    "sg:phone":"+61 417 889 939",
    "sg:postcode":"2034",
    "sg:province":"NSW",
    "sg:tags":[
        "surveyor",
        "land"
    ],
    "wof:name":"Cornish Peter",
    "wof:placetype":"venue"
},
  "geometry": {"coordinates":[151.25402832,-33.9274597168],"type":"Point"}
}