{
  "type": "Feature",
  "properties": {
    "addr:full":"89 Edwin St Croydon NSW 2132",
    "addr:housenumber":"89",
    "addr:postcode":"2132",
    "addr:street":"Edwin St",
    "iso:country":"AU",
    "sg:address":"89 Edwin St",
    "sg:city":"Croydon",
    "sg:classifiers":[
        {
            "category":"Fast Food",
            "type":"Food & Drink"
        }
    ],
    "sg:phone":"+61 2 9798 9685",
    "sg:postcode":"2132",
    "sg:province":"NSW",
    "sg:tags":[
        "away",
        "take"
    ],
    "wof:name":"Croydon Chinese Takeaway",
    "wof:placetype":"venue"
},
  "geometry": {"coordinates":[151.11705017099999,-33.8831138611],"type":"Point"}
}