{
  "type": "Feature",
  "properties": {
    "addr:full":"819 Burke St Surry Hills NSW 2010",
    "addr:housenumber":"819",
    "addr:postcode":"2010",
    "addr:street":"Burke St",
    "iso:country":"AU",
    "sg:address":"819 Burke St",
    "sg:city":"Surry Hills",
    "sg:classifiers":[
        {
            "category":"Professional",
            "type":"Services"
        }
    ],
    "sg:phone":"+61 405 093 089",
    "sg:postcode":"2010",
    "sg:province":"NSW",
    "sg:tags":[
        "transport"
    ],
    "wof:name":"Moving Pro",
    "wof:placetype":"venue"
},
  "geometry": {"coordinates":[151.21693420400001,-33.8800697327],"type":"Point"}
}