{
  "type": "Feature",
  "properties": {
    "addr:full":"341 Hampton Rd Hampton VIC 3188",
    "addr:housenumber":"341",
    "addr:postcode":"3188",
    "addr:street":"Hampton Rd",
    "iso:country":"AU",
    "sg:address":"341 Hampton Rd",
    "sg:city":"Hampton",
    "sg:classifiers":[
        {
            "category":"Food & Beverages",
            "subcategory":"Bakery",
            "type":"Retail Goods"
        }
    ],
    "sg:phone":"+61 3 9521 8196",
    "sg:postcode":"3188",
    "sg:province":"VIC",
    "sg:tags":[
        "baker"
    ],
    "wof:name":"Browns Bakers of Distinction",
    "wof:placetype":"venue"
},
  "geometry": {"coordinates":[145.002319336,-37.9375419617],"type":"Point"}
}