{
  "type": "Feature",
  "properties": {
    "addr:full":"49 Filbert St Caulfield South VIC 3162",
    "addr:housenumber":"49",
    "addr:postcode":"3162",
    "addr:street":"Filbert St",
    "iso:country":"AU",
    "sg:address":"49 Filbert St",
    "sg:city":"Caulfield South",
    "sg:classifiers":[
        {
            "category":"Retail",
            "subcategory":"Repair Shop",
            "type":"Services"
        }
    ],
    "sg:phone":"+61 3 9523 9126",
    "sg:postcode":"3162",
    "sg:province":"VIC",
    "sg:tags":[
        "upholsterer"
    ],
    "wof:name":"Marie Martin Sewing Service Upholstry",
    "wof:placetype":"venue"
},
  "geometry": {"coordinates":[145.02606201200001,-37.8911514282],"type":"Point"}
}