{
  "type": "Feature",
  "properties": {
    "addr:full":"333 Belmore Rd Narwee NSW 2209",
    "addr:housenumber":"333",
    "addr:postcode":"2209",
    "addr:street":"Belmore Rd",
    "iso:country":"AU",
    "sg:address":"333 Belmore Rd",
    "sg:city":"Narwee",
    "sg:classifiers":[
        {
            "category":"Fast Food",
            "type":"Food & Drink"
        }
    ],
    "sg:phone":"+61 2 9533 9699",
    "sg:postcode":"2209",
    "sg:province":"NSW",
    "sg:tags":[
        "away",
        "take"
    ],
    "wof:name":"Brighton Pizzeria",
    "wof:placetype":"venue"
},
  "geometry": {"coordinates":[151.071045,-33.94841],"type":"Point"}
}