{
  "type": "Feature",
  "properties": {
    "addr:full":"418 Church St Richmond VIC 3121",
    "addr:housenumber":"418",
    "addr:postcode":"3121",
    "addr:street":"Church St",
    "iso:country":"AU",
    "sg:address":"418 Church St",
    "sg:city":"Richmond",
    "sg:classifiers":[
        {
            "category":"Shopping",
            "subcategory":"Jewelry",
            "type":"Retail Goods"
        }
    ],
    "sg:phone":"+61 3 9428 2877",
    "sg:postcode":"3121",
    "sg:province":"VIC",
    "sg:tags":[
        "jeweller"
    ],
    "wof:name":"Carat Club Jewellery",
    "wof:placetype":"venue"
},
  "geometry": {"coordinates":[144.997924805,-37.8247795105],"type":"Point"}
}