{
  "type": "Feature",
  "properties": {
    "addr:full":"15 Ross Pl Wakerley QLD 4154",
    "addr:housenumber":"15",
    "addr:postcode":"4154",
    "addr:street":"Ross Pl",
    "iso:country":"AU",
    "sg:address":"15 Ross Pl",
    "sg:city":"Wakerley",
    "sg:classifiers":[
        {
            "category":"Education",
            "subcategory":"Music School",
            "type":"Public Place"
        }
    ],
    "sg:phone":"+61 7 3390 5487",
    "sg:postcode":"4154",
    "sg:province":"QLD",
    "sg:tags":[
        "choir",
        "bands",
        "orchestra"
    ],
    "sg:website":"http://www.paradisecityjazz.com.au",
    "wof:name":"Paradise City Jazz Band",
    "wof:placetype":"venue"
},
  "geometry": {"coordinates":[153.15042114299999,-27.4887371063],"type":"Point"}
}