{
  "type": "Feature",
  "properties": {
    "iso:country":"AU",
    "sg:address":"100 Bolsover St",
    "sg:city":"Rockhampton",
    "sg:classifiers":[
        {
            "category":"Building & Trades",
            "subcategory":"Electrical",
            "type":"Services"
        }
    ],
    "sg:phone":"+61 7 4927 2066",
    "sg:postcode":"4700",
    "sg:province":"QLD",
    "sg:tags":[
        "wholesaler",
        "mfrs",
        "appliance"
    ],
    "wof:name":"Lawrence & Hanson",
    "wof:placetype":"venue"
},
  "geometry": {"coordinates":[150.51640319800001,-23.384645462],"type":"Point"}
}