{
  "type": "Feature",
  "properties": {
    "addr:full":"542 Footscray Rd West Melbourne VIC 3003",
    "addr:housenumber":"542",
    "addr:postcode":"3003",
    "addr:street":"Footscray Rd",
    "iso:country":"AU",
    "sg:address":"542 Footscray Rd",
    "sg:city":"West Melbourne",
    "sg:classifiers":[
        {
            "category":"Home & Garden",
            "subcategory":"Garden Supply",
            "type":"Retail Goods"
        }
    ],
    "sg:phone":"+61 3 9687 6836",
    "sg:postcode":"3003",
    "sg:province":"VIC",
    "sg:tags":[
        "fertilizer"
    ],
    "wof:name":"Muir E E & Sons Pty Ltd",
    "wof:placetype":"venue"
},
  "geometry": {"coordinates":[144.92155456500001,-37.8076972961],"type":"Point"}
}