{
  "type": "Feature",
  "properties": {
    "addr:full":"2 Talofa Crs Port Macquarie NSW 2444",
    "addr:housenumber":"2",
    "addr:postcode":"2444",
    "addr:street":"Talofa Crs",
    "iso:country":"AU",
    "sg:address":"2 Talofa Crs",
    "sg:city":"Port Macquarie",
    "sg:classifiers":[
        {
            "category":"Utilities",
            "subcategory":"Electric",
            "type":"Services"
        }
    ],
    "sg:phone":"+61 2 6582 6858",
    "sg:postcode":"2444",
    "sg:province":"NSW",
    "sg:tags":[
        "electrical",
        "contractor"
    ],
    "wof:name":"Lecsafe",
    "wof:placetype":"venue"
},
  "geometry": {"coordinates":[152.90817300000001,-31.4296],"type":"Point"}
}