{
  "type": "Feature",
  "properties": {
    "addr:full":"1B. 128 Fullarton Rd Norwood SA 5067",
    "addr:housenumber":"1b 128",
    "addr:postcode":"5067",
    "addr:street":"Fullarton Rd",
    "iso:country":"AU",
    "sg:address":"1B. 128 Fullarton Rd",
    "sg:city":"Norwood",
    "sg:classifiers":[
        {
            "category":"Professional",
            "subcategory":"Employment Agencies",
            "type":"Services"
        }
    ],
    "sg:phone":"+61 1800 882 287",
    "sg:postcode":"5067",
    "sg:province":"SA",
    "wof:name":"Lucas Group Pty Ltd The",
    "wof:placetype":"venue"
},
  "geometry": {"coordinates":[138.623779297,-34.9270401001],"type":"Point"}
}