{
  "type": "Feature",
  "properties": {
    "addr:full":"7 Parkes St Parramatta NSW 2150",
    "addr:housenumber":"7",
    "addr:postcode":"2150",
    "addr:street":"Parkes St",
    "iso:country":"AU",
    "sg:address":"7 Parkes St",
    "sg:city":"Parramatta",
    "sg:classifiers":[
        {
            "category":"Real Estate",
            "subcategory":"Architect",
            "type":"Services"
        }
    ],
    "sg:phone":"+61 2 9635 6922",
    "sg:postcode":"2150",
    "sg:province":"NSW",
    "wof:name":"Sector 7G Architects Interiors",
    "wof:placetype":"venue"
},
  "geometry": {"coordinates":[150.972564697,-33.8489112854],"type":"Point"}
}