{
  "type": "Feature",
  "properties": {
    "addr:full":"2 Bird St Springvale VIC 3171",
    "addr:housenumber":"2",
    "addr:postcode":"3171",
    "addr:street":"Bird St",
    "iso:country":"AU",
    "sg:address":"2 Bird St",
    "sg:city":"Springvale",
    "sg:classifiers":[
        {
            "category":"Banks & Credit Unions",
            "subcategory":"Investment Brokerage",
            "type":"Services"
        }
    ],
    "sg:phone":"+61 3 9547 7277",
    "sg:postcode":"3171",
    "sg:province":"VIC",
    "sg:tags":[
        "directory",
        "notice",
        "board"
    ],
    "wof:name":"Forbo Cork Sales",
    "wof:placetype":"venue"
},
  "geometry": {"coordinates":[145.16148376500001,-37.9481239319],"type":"Point"}
}