{
  "type": "Feature",
  "properties": {
    "addr:full":"1 Campbell St Artarmon NSW 2064",
    "addr:housenumber":"1",
    "addr:postcode":"2064",
    "addr:street":"Campbell St",
    "iso:country":"AU",
    "sg:address":"1 Campbell St",
    "sg:city":"Artarmon",
    "sg:classifiers":[
        {
            "category":"Retail",
            "subcategory":"Auto Rental",
            "type":"Services"
        }
    ],
    "sg:phone":"+61 2 9200 2650",
    "sg:postcode":"2064",
    "sg:province":"NSW",
    "sg:tags":[
        "car",
        "hire",
        "minibus"
    ],
    "wof:name":"Europcar",
    "wof:placetype":"venue"
},
  "geometry": {"coordinates":[151.185012817,-33.8179321289],"type":"Point"}
}