{
  "type": "Feature",
  "properties": {
    "addr:full":"Level 1, 307 Bay St Brighton VIC 3186",
    "addr:housenumber":"307",
    "addr:postcode":"3186",
    "addr:street":"Bay St",
    "iso:country":"AU",
    "sg:address":"Level 1, 307 Bay St",
    "sg:city":"Brighton",
    "sg:classifiers":[
        {
            "category":"Professional",
            "subcategory":"Accounting & Tax Preparation",
            "type":"Services"
        }
    ],
    "sg:phone":"+61 3 9596 5466",
    "sg:postcode":"3186",
    "sg:province":"VIC",
    "sg:tags":[
        "bookkeeping"
    ],
    "wof:name":"Award Bookkeeping Company (Brighton)",
    "wof:placetype":"venue"
},
  "geometry": {"coordinates":[145.00265502900001,-37.9054069519],"type":"Point"}
}