{
  "type": "Feature",
  "properties": {
    "addr:full":"96 Yarra St Geelong VIC 3220",
    "addr:housenumber":"96",
    "addr:postcode":"3220",
    "addr:street":"Yarra St",
    "iso:country":"AU",
    "sg:address":"96 Yarra St",
    "sg:city":"Geelong",
    "sg:classifiers":[
        {
            "category":"Farming",
            "subcategory":"Farm & Veterinary Services",
            "type":"Manufacturing & Wholesale Goods"
        }
    ],
    "sg:phone":"+61 3 5224 2663",
    "sg:postcode":"3220",
    "sg:province":"VIC",
    "sg:tags":[
        "agricultural",
        "advisory"
    ],
    "wof:name":"Ashby R G & Co Pty Ltd",
    "wof:placetype":"venue"
},
  "geometry": {"coordinates":[144.361908,-38.150536],"type":"Point"}
}