{
  "type": "Feature",
  "properties": {
    "addr:full":"442 Racecourse Rd Flemington VIC 3031",
    "addr:housenumber":"442",
    "addr:postcode":"3031",
    "addr:street":"Racecourse Rd",
    "iso:country":"AU",
    "sg:address":"442 Racecourse Rd",
    "sg:city":"Flemington",
    "sg:classifiers":[
        {
            "category":"Social Services",
            "subcategory":"Child Care",
            "type":"Services"
        }
    ],
    "sg:phone":"+61 3 9376 5500",
    "sg:postcode":"3031",
    "sg:province":"VIC",
    "wof:name":"Melbourne Child Care & Kindergarten Centre Pty Ltd",
    "wof:placetype":"venue"
},
  "geometry": {"coordinates":[144.925735,-37.787598],"type":"Point"}
}