{
  "type": "Feature",
  "properties": {
    "iso:country":"AU",
    "sg:address":"91 Latrobe Rd",
    "sg:city":"Railton",
    "sg:classifiers":[
        {
            "category":"Shopping",
            "subcategory":"Antiques",
            "type":"Retail Goods"
        }
    ],
    "sg:phone":"+61 3 6496 1002",
    "sg:postcode":"7305",
    "sg:province":"TAS",
    "sg:tags":[
        "restoration",
        "reproduction"
    ],
    "wof:name":"AJ & KM Restorations",
    "wof:placetype":"venue"
},
  "geometry": {"coordinates":[146.42390399999999,-41.335133],"type":"Point"}
}