{
  "type": "Feature",
  "properties": {
    "addr:full":"2875 Cowle Rd Karratha WA 6714",
    "addr:housenumber":"2875",
    "addr:postcode":"6714",
    "addr:street":"Cowle Rd",
    "iso:country":"AU",
    "sg:address":"2875 Cowle Rd",
    "sg:city":"Karratha",
    "sg:classifiers":[
        {
            "category":"Professional",
            "subcategory":"Detective & Security Services",
            "type":"Services"
        }
    ],
    "sg:phone":"+61 8 9143 1600",
    "sg:postcode":"6714",
    "sg:province":"WA",
    "sg:tags":[
        "guard",
        "patrol"
    ],
    "wof:name":"Think Security",
    "wof:placetype":"venue"
},
  "geometry": {"coordinates":[116.843971252,-20.7356300354],"type":"Point"}
}