{
  "type": "Feature",
  "properties": {
    "iso:country":"AU",
    "sg:address":"Taplan Rd",
    "sg:city":"Loxton East",
    "sg:classifiers":[
        {
            "category":"Farming",
            "subcategory":"Farm",
            "type":"Manufacturing & Wholesale Goods"
        }
    ],
    "sg:phone":"+61 8 8584 6962",
    "sg:postcode":"5333",
    "sg:province":"SA",
    "sg:tags":[
        "farmer"
    ],
    "wof:name":"Vowles B K & M",
    "wof:placetype":"venue"
},
  "geometry": {"coordinates":[140.61895751899999,-34.4794006348],"type":"Point"}
}