{
  "type": "Feature",
  "properties": {
    "addr:full":"Regents Park Rd Joondalup WA 6027",
    "addr:postcode":"6027",
    "addr:street":"Regents Park Rd",
    "iso:country":"AU",
    "sg:address":"Regents Park Rd",
    "sg:city":"Joondalup",
    "sg:classifiers":[
        {
            "category":"Social Services",
            "subcategory":"Child Care",
            "type":"Services"
        }
    ],
    "sg:phone":"+61 8 9400 9533",
    "sg:postcode":"6027",
    "sg:province":"WA",
    "sg:tags":[
        "support",
        "health"
    ],
    "wof:name":"Child Health Services",
    "wof:placetype":"venue"
},
  "geometry": {"coordinates":[115.77037811300001,-31.7378101349],"type":"Point"}
}