{
  "type": "Feature",
  "properties": {
    "iso:country":"AU",
    "sg:address":"99 Adams St",
    "sg:city":"Wentworth",
    "sg:classifiers":[
        {
            "category":"Farming",
            "subcategory":"Orchard",
            "type":"Manufacturing & Wholesale Goods"
        }
    ],
    "sg:phone":"+61 3 5027 3416",
    "sg:postcode":"2648",
    "sg:province":"VIC",
    "sg:tags":[
        "citrus",
        "fruit",
        "grower"
    ],
    "wof:name":"Fasolino J",
    "wof:placetype":"venue"
},
  "geometry": {"coordinates":[141.918182,-34.108444],"type":"Point"}
}