{
  "type": "Feature",
  "properties": {
    "addr:full":"126 Gilles St Adelaide SA 5000",
    "addr:housenumber":"126",
    "addr:postcode":"5000",
    "addr:street":"Gilles St",
    "iso:country":"AU",
    "sg:address":"126 Gilles St",
    "sg:city":"Adelaide",
    "sg:classifiers":[
        {
            "category":"Home & Garden",
            "subcategory":"Household Appliances",
            "type":"Retail Goods"
        }
    ],
    "sg:phone":"+61 8 8224 0911",
    "sg:postcode":"5000",
    "sg:province":"SA",
    "sg:tags":[
        "chemical",
        "equipment",
        "steam",
        "cleaning",
        "pressure"
    ],
    "wof:name":"City Car Detailers",
    "wof:placetype":"venue"
},
  "geometry": {"coordinates":[138.604934692,-34.9339256287],"type":"Point"}
}