{
  "type": "Feature",
  "properties": {
    "iso:country":"AU",
    "sg:address":"2 / 11 Neutron Pl",
    "sg:city":"Rowville",
    "sg:classifiers":[
        {
            "category":"Home & Garden",
            "subcategory":"Hardware",
            "type":"Retail Goods"
        }
    ],
    "sg:phone":"+61 3 9763 8563",
    "sg:postcode":"3178",
    "sg:province":"VIC",
    "sg:tags":[
        "compressor",
        "air"
    ],
    "sg:website":"http://www.industair.com",
    "wof:name":"Industair",
    "wof:placetype":"venue"
},
  "geometry": {"coordinates":[145.24690246599999,-37.9066314697],"type":"Point"}
}