{
  "type": "Feature",
  "properties": {
    "addr:full":"11 Glenshee Pl St Andrews NSW 2566",
    "addr:housenumber":"11",
    "addr:postcode":"2566",
    "addr:street":"Glenshee Pl",
    "iso:country":"AU",
    "sg:address":"11 Glenshee Pl",
    "sg:city":"St Andrews",
    "sg:classifiers":[
        {
            "category":"Building & Trades",
            "subcategory":"Construction",
            "type":"Services"
        }
    ],
    "sg:phone":"+61 415 964 460",
    "sg:postcode":"2566",
    "sg:province":"NSW",
    "sg:tags":[
        "earth",
        "excavating",
        "moving",
        "contractor"
    ],
    "wof:name":"R P Anthony Excavations Pty Ltd",
    "wof:placetype":"venue"
},
  "geometry": {"coordinates":[150.82679748499999,-34.0357208252],"type":"Point"}
}