{
  "type": "Feature",
  "properties": {
    "iso:country":"AU",
    "sg:address":"36a Langston Pl",
    "sg:city":"Epping",
    "sg:classifiers":[
        {
            "category":"Arts & Performance",
            "subcategory":"Theater",
            "type":"Entertainment"
        }
    ],
    "sg:phone":"+61 1300 666 900",
    "sg:postcode":"2121",
    "sg:province":"NSW",
    "sg:tags":[
        "theatrical",
        "supply"
    ],
    "wof:name":"Theatricalities",
    "wof:placetype":"venue"
},
  "geometry": {"coordinates":[151.082687378,-33.772895813],"type":"Point"}
}