{
  "type": "Feature",
  "properties": {
    "iso:country":"AU",
    "sg:address":"53-63 Raglan Pde",
    "sg:city":"Warrnambool",
    "sg:classifiers":[
        {
            "category":"Travel",
            "subcategory":"Hotels & Motels",
            "type":"Entertainment"
        }
    ],
    "sg:phone":"+61 3 5561 1000",
    "sg:postcode":"3280",
    "sg:province":"VIC",
    "wof:name":"Southern Right Motor Inn",
    "wof:placetype":"venue"
},
  "geometry": {"coordinates":[142.525390625,-38.3843307495],"type":"Point"}
}