{
  "type": "Feature",
  "properties": {
    "addr:full":"Margaret St Palmwoods QLD 4555",
    "addr:postcode":"4555",
    "addr:street":"Margaret St",
    "iso:country":"AU",
    "sg:address":"Margaret St",
    "sg:city":"Palmwoods",
    "sg:classifiers":[
        {
            "category":"Fast Food",
            "type":"Food & Drink"
        }
    ],
    "sg:phone":"+61 7 5445 9585",
    "sg:postcode":"4555",
    "sg:province":"QLD",
    "sg:tags":[
        "away",
        "take"
    ],
    "wof:name":"Palmwoods Take Away",
    "wof:placetype":"venue"
},
  "geometry": {"coordinates":[152.956207275,-26.6875495911],"type":"Point"}
}