{
  "type": "Feature",
  "properties": {
    "iso:country":"AU",
    "sg:address":"1/ 3 Eurobin Ave",
    "sg:city":"Manly",
    "sg:classifiers":[
        {
            "category":"Professional",
            "subcategory":"Art Services",
            "type":"Services"
        }
    ],
    "sg:phone":"+61 2 9977 7767",
    "sg:postcode":"2095",
    "sg:province":"NSW",
    "sg:tags":[
        "graphic",
        "designer"
    ],
    "wof:name":"Broad Concepts Pty Ltd",
    "wof:placetype":"venue"
},
  "geometry": {"coordinates":[151.281326294,-33.7857894897],"type":"Point"}
}