{
  "type": "Feature",
  "properties": {
    "iso:country":"AU",
    "sg:address":"4 Woodlands Crt",
    "sg:city":"Castle Hill",
    "sg:classifiers":[
        {
            "category":"Building & Trades",
            "subcategory":"Construction",
            "type":"Services"
        }
    ],
    "sg:phone":"+61 7 4772 0350",
    "sg:postcode":"4810",
    "sg:province":"QLD",
    "sg:tags":[
        "ceiling"
    ],
    "wof:name":"Kinsella Plastering Pty Ltd",
    "wof:placetype":"venue"
},
  "geometry": {"coordinates":[146.795624,-19.249466],"type":"Point"}
}