{
  "type": "Feature",
  "properties": {
    "addr:full":"34 Brisbane Rd Redbank QLD 4301",
    "addr:housenumber":"34",
    "addr:postcode":"4301",
    "addr:street":"Brisbane Rd",
    "iso:country":"AU",
    "sg:address":"34 Brisbane Rd",
    "sg:city":"Redbank",
    "sg:classifiers":[
        {
            "category":"Shopping",
            "subcategory":"Antiques",
            "type":"Retail Goods"
        }
    ],
    "sg:phone":"+61 7 3288 1711",
    "sg:postcode":"4301",
    "sg:province":"QLD",
    "wof:name":"Antiques At Redbank",
    "wof:placetype":"venue"
},
  "geometry": {"coordinates":[152.865524292,-27.6022605896],"type":"Point"}
}