{
  "type": "Feature",
  "properties": {
    "addr:full":"147 King St Caboolture QLD 4510",
    "addr:housenumber":"147",
    "addr:postcode":"4510",
    "addr:street":"King St",
    "iso:country":"AU",
    "sg:address":"147 King St",
    "sg:city":"Caboolture",
    "sg:classifiers":[
        {
            "category":"Wholesale",
            "subcategory":"Machinery & Supplies",
            "type":"Manufacturing & Wholesale Goods"
        }
    ],
    "sg:phone":"+61 7 5495 1533",
    "sg:postcode":"4510",
    "sg:province":"QLD",
    "sg:tags":[
        "agricultural"
    ],
    "wof:name":"John Page Motors",
    "wof:placetype":"venue"
},
  "geometry": {"coordinates":[152.94047499999999,-27.084759],"type":"Point"}
}