{
  "type": "Feature",
  "properties": {
    "addr:full":"117 Kingaroy St Kingaroy QLD 4610",
    "addr:housenumber":"117",
    "addr:postcode":"4610",
    "addr:street":"Kingaroy St",
    "iso:country":"AU",
    "sg:address":"117 Kingaroy St",
    "sg:city":"Kingaroy",
    "sg:classifiers":[
        {
            "category":"Fast Food",
            "type":"Food & Drink"
        }
    ],
    "sg:phone":"+61 7 4162 7777",
    "sg:postcode":"4610",
    "sg:province":"QLD",
    "sg:tags":[
        "away",
        "take"
    ],
    "wof:name":"Aussies Pizza Cafe Kingaroy",
    "wof:placetype":"venue"
},
  "geometry": {"coordinates":[151.83888244600001,-26.5425605774],"type":"Point"}
}