{
  "type": "Feature",
  "properties": {
    "addr:full":"4 Burrendong Pl Avalon NSW 2107",
    "addr:housenumber":"4",
    "addr:postcode":"2107",
    "addr:street":"Burrendong Pl",
    "iso:country":"AU",
    "sg:address":"4 Burrendong Pl",
    "sg:city":"Avalon",
    "sg:classifiers":[
        {
            "category":"Retail",
            "subcategory":"Laundry & Dry Cleaning",
            "type":"Services"
        }
    ],
    "sg:phone":"+61 2 9918 5524",
    "sg:postcode":"2107",
    "sg:province":"NSW",
    "sg:tags":[
        "ironing"
    ],
    "wof:name":"Onboard Services",
    "wof:placetype":"venue"
},
  "geometry": {"coordinates":[151.32220459000001,-33.6300849915],"type":"Point"}
}