{
  "type": "Feature",
  "properties": {
    "addr:full":"84 Newman Ave Camp Hill QLD 4152",
    "addr:housenumber":"84",
    "addr:postcode":"4152",
    "addr:street":"Newman Ave",
    "iso:country":"AU",
    "sg:address":"84 Newman Ave",
    "sg:city":"Camp Hill",
    "sg:classifiers":[
        {
            "category":"Professional",
            "subcategory":"Computer Services",
            "type":"Services"
        }
    ],
    "sg:phone":"+61 7 3843 0069",
    "sg:postcode":"4152",
    "sg:province":"QLD",
    "sg:tags":[
        "package",
        "software"
    ],
    "wof:name":"Datablue",
    "wof:placetype":"venue"
},
  "geometry": {"coordinates":[153.07403564399999,-27.498588562],"type":"Point"}
}