{
  "type": "Feature",
  "properties": {
    "addr:full":"Kiosk 2.4 Armadale S/C Jull St Armadale WA 6112",
    "addr:housenumber":"/ c",
    "addr:postcode":"6112",
    "addr:street":"Armadale;Jull St",
    "iso:country":"AU",
    "sg:address":"Kiosk 2.4 Armadale S/C Jull St",
    "sg:city":"Armadale",
    "sg:classifiers":[
        {
            "category":"Shopping",
            "subcategory":"Mobile Phones",
            "type":"Retail Goods"
        }
    ],
    "sg:phone":"+61 8 9497 2777",
    "sg:postcode":"6112",
    "sg:province":"WA",
    "sg:tags":[
        "telephone",
        "accessory"
    ],
    "wof:name":"TeleChoice",
    "wof:placetype":"venue"
},
  "geometry": {"coordinates":[115.957138062,-32.1477928162],"type":"Point"}
}