{
  "type": "Feature",
  "properties": {
    "iso:country":"AU",
    "sg:address":"6 Macdonnell St",
    "sg:city":"Kingston SE",
    "sg:classifiers":[
        {
            "category":"Commercial Area",
            "type":"Public Place"
        }
    ],
    "sg:phone":"+61 8 8767 2452",
    "sg:postcode":"5275",
    "sg:province":"SA",
    "sg:tags":[
        "heavy",
        "carrier"
    ],
    "wof:name":"Dicker H F & Son Pty Ltd",
    "wof:placetype":"venue"
},
  "geometry": {"coordinates":[139.854614,-36.834618],"type":"Point"}
}