{
  "type": "Feature",
  "properties": {
    "addr:full":"Lot 211 Kelvin Vickery Ave Narrabri NSW 2390",
    "addr:postcode":"2390",
    "addr:street":"Kelvin Vickery Ave",
    "iso:country":"AU",
    "sg:address":"Lot 211 Kelvin Vickery Ave",
    "sg:city":"Narrabri",
    "sg:classifiers":[
        {
            "category":"Wholesale",
            "subcategory":"Home Furnishings",
            "type":"Manufacturing & Wholesale Goods"
        }
    ],
    "sg:phone":"+61 2 6792 5334",
    "sg:postcode":"2390",
    "sg:province":"NSW",
    "sg:tags":[
        "wholesaler",
        "mfrs",
        "manchester"
    ],
    "wof:name":"Kozmen 1 Nsw",
    "wof:placetype":"venue"
},
  "geometry": {"coordinates":[149.754959106,-30.3455734253],"type":"Point"}
}