{
  "type": "Feature",
  "properties": {
    "iso:country":"AU",
    "sg:address":"9b Tenth St",
    "sg:city":"Hepburn Springs",
    "sg:classifiers":[
        {
            "category":"Building & Trades",
            "subcategory":"Landscaping Services",
            "type":"Services"
        }
    ],
    "sg:phone":"+61 3 5348 1632",
    "sg:postcode":"3461",
    "sg:province":"VIC",
    "sg:tags":[
        "designer",
        "landscape",
        "contractor"
    ],
    "wof:name":"Richmond Hill Garden Designs",
    "wof:placetype":"venue"
},
  "geometry": {"coordinates":[144.137374878,-37.3116493225],"type":"Point"}
}