{
  "type": "Feature",
  "properties": {
    "addr:full":"1/ 69 Normanby Rd Caulfield North VIC 3161",
    "addr:housenumber":"/ 69",
    "addr:postcode":"3161",
    "addr:street":"Normanby Rd",
    "iso:country":"AU",
    "sg:address":"1/ 69 Normanby Rd",
    "sg:city":"Caulfield North",
    "sg:classifiers":[
        {
            "category":"Professional",
            "subcategory":"Art Services",
            "type":"Services"
        }
    ],
    "sg:phone":"+61 409 668 812",
    "sg:postcode":"3161",
    "sg:province":"VIC",
    "sg:tags":[
        "graphic",
        "designer"
    ],
    "wof:name":"Bayside Graphics & Consulting",
    "wof:placetype":"venue"
},
  "geometry": {"coordinates":[145.035400391,-37.8721542358],"type":"Point"}
}