{
  "type": "Feature",
  "properties": {
    "addr:full":"3 Cobden St Bright VIC 3741",
    "addr:housenumber":"3",
    "addr:postcode":"3741",
    "addr:street":"Cobden St",
    "iso:country":"AU",
    "sg:address":"3 Cobden St",
    "sg:city":"Bright",
    "sg:classifiers":[
        {
            "category":"Autos & Motor Vehicles",
            "subcategory":"Automobile Sales",
            "type":"Retail Goods"
        }
    ],
    "sg:phone":"+61 3 5755 1418",
    "sg:postcode":"3741",
    "sg:province":"VIC",
    "sg:tags":[
        "car",
        "used"
    ],
    "wof:name":"High Country Motors",
    "wof:placetype":"venue"
},
  "geometry": {"coordinates":[146.96255500000001,-36.730316],"type":"Point"}
}