{
  "type": "Feature",
  "properties": {
    "addr:full":"Great Northern Hwy De Grey WA 6723",
    "addr:postcode":"6723",
    "addr:street":"Northern Hwy De",
    "iso:country":"AU",
    "sg:address":"Great Northern Hwy",
    "sg:city":"De Grey",
    "sg:classifiers":[
        {
            "category":"Autos & Motor Vehicles",
            "subcategory":"Fuel & Gas Station",
            "type":"Retail Goods"
        }
    ],
    "sg:phone":"+61 8 9176 4916",
    "sg:postcode":"6723",
    "sg:province":"WA",
    "wof:name":"Pardoo Roadhouse & Tavern",
    "wof:placetype":"venue"
},
  "geometry": {"coordinates":[119.478660584,-20.2993888855],"type":"Point"}
}