{
  "type": "Feature",
  "properties": {
    "addr:full":"1 Mario Crt Lesmurdie WA 6076",
    "addr:housenumber":"1",
    "addr:postcode":"6076",
    "addr:street":"Mario Crt",
    "iso:country":"AU",
    "sg:address":"1 Mario Crt",
    "sg:city":"Lesmurdie",
    "sg:classifiers":[
        {
            "category":"Shopping",
            "subcategory":"Party Supplies",
            "type":"Retail Goods"
        }
    ],
    "sg:phone":"+61 8 9291 9009",
    "sg:postcode":"6076",
    "sg:province":"WA",
    "sg:tags":[
        "children's"
    ],
    "wof:name":"Conny-Grams",
    "wof:placetype":"venue"
},
  "geometry": {"coordinates":[116.05317688,-32.0080757141],"type":"Point"}
}