{
  "type": "Feature",
  "properties": {
    "addr:full":"2/ 410 Churchill Rd Kilburn SA 5084",
    "addr:housenumber":"/ 410",
    "addr:postcode":"5084",
    "addr:street":"Churchill Rd",
    "iso:country":"AU",
    "sg:address":"2/ 410 Churchill Rd",
    "sg:city":"Kilburn",
    "sg:classifiers":[
        {
            "category":"Home & Garden",
            "subcategory":"Household Appliances",
            "type":"Retail Goods"
        }
    ],
    "sg:phone":"+61 8 8262 4222",
    "sg:postcode":"5084",
    "sg:province":"SA",
    "sg:tags":[
        "chemical",
        "equipment",
        "steam",
        "cleaning",
        "pressure"
    ],
    "wof:name":"Clean- Machine",
    "wof:placetype":"venue"
},
  "geometry": {"coordinates":[138.583053589,-34.8611755371],"type":"Point"}
}