{
  "type": "Feature",
  "properties": {
    "addr:full":"Kiosk 17 Westfield Shopng Twn Arndale Cnr Torrens & Hanson Rds Kilkenny SA 5009",
    "addr:housenumber":"17",
    "addr:postcode":"5009",
    "addr:street":"Westfield Shopng;Arndale Cnr Torrens",
    "iso:country":"AU",
    "sg:address":"Kiosk 17 Westfield Shopng Twn Arndale Cnr Torrens & Hanson Rds",
    "sg:city":"Kilkenny",
    "sg:classifiers":[
        {
            "category":"Cafe",
            "type":"Food & Drink"
        }
    ],
    "sg:phone":"+61 8 8244 3535",
    "sg:postcode":"5009",
    "sg:province":"SA",
    "wof:name":"Gloria Jean's Coffees",
    "wof:placetype":"venue"
},
  "geometry": {"coordinates":[138.55354309099999,-34.8782424927],"type":"Point"}
}