{
  "type": "Feature",
  "properties": {
    "addr:full":"59 Hart St Dundas NSW 2117",
    "addr:housenumber":"59",
    "addr:postcode":"2117",
    "addr:street":"Hart St",
    "iso:country":"AU",
    "sg:address":"59 Hart St",
    "sg:city":"Dundas",
    "sg:classifiers":[
        {
            "category":"Sports & Exercise",
            "subcategory":"Sports Center",
            "type":"Entertainment"
        }
    ],
    "sg:phone":"+61 2 9872 1357",
    "sg:postcode":"2117",
    "sg:province":"NSW",
    "sg:tags":[
        "coach",
        "tennis"
    ],
    "wof:name":"Brennan Ray Tennis Schools",
    "wof:placetype":"venue"
},
  "geometry": {"coordinates":[151.05368042000001,-33.7871665955],"type":"Point"}
}