{
  "type": "Feature",
  "properties": {
    "iso:country":"AU",
    "sg:address":"356 Brunswick St",
    "sg:city":"Fitzroy",
    "sg:classifiers":[
        {
            "category":"Cafe",
            "type":"Food & Drink"
        }
    ],
    "sg:phone":"+61 3 9419 2482",
    "sg:postcode":"3065",
    "sg:province":"VIC",
    "wof:name":"Idibidi Pty Ltd",
    "wof:placetype":"venue"
},
  "geometry": {"coordinates":[144.978881836,-37.7966575623],"type":"Point"}
}