{
  "type": "Feature",
  "properties": {
    "addr:full":"1140 Albany Hwy Bentley WA 6102",
    "addr:housenumber":"1140",
    "addr:postcode":"6102",
    "addr:street":"Albany Hwy",
    "iso:country":"AU",
    "sg:address":"1140 Albany Hwy",
    "sg:city":"Bentley",
    "sg:classifiers":[
        {
            "category":"Personal",
            "subcategory":"Day Spa",
            "type":"Services"
        }
    ],
    "sg:phone":"+61 8 9258 4811",
    "sg:postcode":"6102",
    "sg:province":"WA",
    "wof:name":"Inspired Day Spa",
    "wof:placetype":"venue"
},
  "geometry": {"coordinates":[115.92073822,-32.003993988],"type":"Point"}
}