{
  "type": "Feature",
  "properties": {
    "addr:full":"10 Jade Crt Alexandra Hills QLD 4161",
    "addr:housenumber":"10",
    "addr:postcode":"4161",
    "addr:street":"Jade Crt",
    "iso:country":"AU",
    "sg:address":"10 Jade Crt",
    "sg:city":"Alexandra Hills",
    "sg:classifiers":[
        {
            "category":"Utilities",
            "subcategory":"Telephone",
            "type":"Services"
        }
    ],
    "sg:phone":"+61 7 3824 7500",
    "sg:postcode":"4161",
    "sg:province":"QLD",
    "sg:tags":[
        "equipment",
        "system"
    ],
    "wof:name":"Phoenix Telephone &#039;n&#039; Data Services",
    "wof:placetype":"venue"
},
  "geometry": {"coordinates":[153.23406982399999,-27.5181732178],"type":"Point"}
}