{
  "type": "Feature",
  "properties": {
    "iso:country":"AU",
    "sg:address":"Lake Rd",
    "sg:city":"Port Macquarie",
    "sg:classifiers":[
        {
            "category":"Health Services",
            "subcategory":"Doctor",
            "type":"Services"
        }
    ],
    "sg:phone":"+61 2 6586 6140",
    "sg:postcode":"2444",
    "sg:province":"NSW",
    "sg:tags":[
        "medical",
        "practitioner"
    ],
    "wof:name":"Briscoe P J",
    "wof:placetype":"venue"
},
  "geometry": {"coordinates":[152.91146900000001,-31.434656],"type":"Point"}
}