{
  "type": "Feature",
  "properties": {
    "iso:country":"AU",
    "sg:address":"Nareena Hills Tennis Club Uralba St",
    "sg:city":"Figtree",
    "sg:classifiers":[
        {
            "category":"Sports & Exercise",
            "subcategory":"Sports Center",
            "type":"Entertainment"
        }
    ],
    "sg:phone":"+61 2 4225 7065",
    "sg:postcode":"2525",
    "sg:province":"NSW",
    "sg:tags":[
        "coach",
        "tennis"
    ],
    "wof:name":"Linda Bayly Tennis Coaching",
    "wof:placetype":"venue"
},
  "geometry": {"coordinates":[150.85435485799999,-34.4267044067],"type":"Point"}
}