{
  "type": "Feature",
  "properties": {
    "iso:country":"AU",
    "sg:address":"Cnr Victoria Hwy",
    "sg:city":"& Messmate Way Kununurra",
    "sg:classifiers":[
        {
            "category":"Travel",
            "subcategory":"Hotels & Motels",
            "type":"Entertainment"
        }
    ],
    "sg:phone":"+61 8 9168 4000",
    "sg:postcode":"6743",
    "sg:province":"WA",
    "wof:name":"All Seasons Kununurra",
    "wof:placetype":"venue"
},
  "geometry": {"coordinates":[128.742385864,-15.778719902],"type":"Point"}
}