{
  "type": "Feature",
  "properties": {
    "addr:full":"Unit 1/ 64 Prince St Busselton WA 6280",
    "addr:housenumber":"64",
    "addr:postcode":"6280",
    "addr:street":"Prince St",
    "iso:country":"AU",
    "sg:address":"Unit 1/ 64 Prince St",
    "sg:city":"Busselton",
    "sg:classifiers":[
        {
            "category":"Real Estate",
            "subcategory":"Real Estate Agent",
            "type":"Services"
        }
    ],
    "sg:phone":"+61 8 9754 0200",
    "sg:postcode":"6280",
    "sg:province":"WA",
    "wof:name":"Harvey Grey & Associates",
    "wof:placetype":"venue"
},
  "geometry": {"coordinates":[115.346557617,-33.6507949829],"type":"Point"}
}