{
  "type": "Feature",
  "properties": {
    "iso:country":"AU",
    "sg:address":"Level 5, 68 St Georges Tce",
    "sg:city":"Perth",
    "sg:classifiers":[
        {
            "category":"Professional",
            "subcategory":"Employment Agencies",
            "type":"Services"
        }
    ],
    "sg:phone":"+61 8 9324 1411",
    "sg:postcode":"6000",
    "sg:province":"WA",
    "wof:name":"GEL Group Pty Ltd",
    "wof:placetype":"venue"
},
  "geometry": {"coordinates":[115.85836792000001,-31.9551715851],"type":"Point"}
}