{
  "type": "Feature",
  "properties": {
    "iso:country":"AU",
    "sg:address":"Cnr Queen & Sargood St",
    "sg:city":"Altona",
    "sg:classifiers":[
        {
            "category":"Health Services",
            "subcategory":"Doctor",
            "type":"Services"
        }
    ],
    "sg:phone":"+61 3 9398 8800",
    "sg:postcode":"3018",
    "sg:province":"VIC",
    "sg:tags":[
        "medical",
        "practitioner"
    ],
    "wof:name":"Hobsons Bay Endoscopy Centre",
    "wof:placetype":"venue"
},
  "geometry": {"coordinates":[144.82937622099999,-37.865650177],"type":"Point"}
}