{
  "type": "Feature",
  "properties": {
    "addr:full":"Unit 12, 543 Churchill Rd Kilburn SA 5084",
    "addr:housenumber":"543",
    "addr:postcode":"5084",
    "addr:street":"Churchill Rd",
    "iso:country":"AU",
    "sg:address":"Unit 12, 543 Churchill Rd",
    "sg:city":"Kilburn",
    "sg:classifiers":[
        {
            "category":"Communications",
            "subcategory":"Television Station",
            "type":"Services"
        }
    ],
    "sg:phone":"+61 8 8260 7888",
    "sg:postcode":"5084",
    "sg:province":"SA",
    "sg:tags":[
        "equipment",
        "laser"
    ],
    "wof:name":"Ross Instruments",
    "wof:placetype":"venue"
},
  "geometry": {"coordinates":[138.58273315400001,-34.852016449],"type":"Point"}
}