{
  "type": "Feature",
  "properties": {
    "iso:country":"AU",
    "sg:address":"28 Chamberlain St",
    "sg:city":"Campbelltown",
    "sg:phone":"+61 2 4627 4055",
    "sg:postcode":"2560",
    "sg:province":"NSW",
    "wof:name":"Truline Heritage Roofing",
    "wof:placetype":"venue"
},
  "geometry": {"coordinates":[150.82244873100001,-34.0625572205],"type":"Point"}
}