{
  "type": "Feature",
  "properties": {
    "iso:country":"AU",
    "sg:address":"81 Kootingal St",
    "sg:city":"Greystanes",
    "sg:classifiers":[
        {
            "category":"Professional",
            "subcategory":"Computer Services",
            "type":"Services"
        }
    ],
    "sg:phone":"+61 2 9896 6424",
    "sg:postcode":"2145",
    "sg:province":"NSW",
    "sg:tags":[
        "consultant",
        "system"
    ],
    "wof:name":"Objectco Pty Ltd",
    "wof:placetype":"venue"
},
  "geometry": {"coordinates":[150.94793701200001,-33.8231315613],"type":"Point"}
}