{
  "type": "Feature",
  "properties": {
    "addr:full":"8 Woolshed St Bordertown SA 5268",
    "addr:housenumber":"8",
    "addr:postcode":"5268",
    "addr:street":"Woolshed St",
    "iso:country":"AU",
    "sg:address":"8 Woolshed St",
    "sg:city":"Bordertown",
    "sg:classifiers":[
        {
            "category":"Shopping",
            "subcategory":"Computers & Home Electronics",
            "type":"Retail Goods"
        }
    ],
    "sg:phone":"+61 8 8752 0007",
    "sg:postcode":"5268",
    "sg:province":"SA",
    "sg:tags":[
        "small",
        "equipment",
        "business"
    ],
    "wof:name":"Bordertown Computer Supplies",
    "wof:placetype":"venue"
},
  "geometry": {"coordinates":[140.773697,-36.311249],"type":"Point"}
}