{
  "type": "Feature",
  "properties": {
    "addr:full":"104 Beaudesert Rd Moorooka QLD 4105",
    "addr:housenumber":"104",
    "addr:postcode":"4105",
    "addr:street":"Beaudesert Rd",
    "iso:country":"AU",
    "sg:address":"104 Beaudesert Rd",
    "sg:city":"Moorooka",
    "sg:classifiers":[
        {
            "category":"Health Services",
            "subcategory":"Dentist",
            "type":"Services"
        }
    ],
    "sg:phone":"+61 7 3848 2761",
    "sg:postcode":"4105",
    "sg:province":"QLD",
    "wof:name":"Camp M J",
    "wof:placetype":"venue"
},
  "geometry": {"coordinates":[153.023880005,-27.5301399231],"type":"Point"}
}