{
  "type": "Feature",
  "properties": {
    "iso:country":"AU",
    "sg:address":"Shop 3, Stargate Shopping Centre, 129",
    "sg:city":"Lydon Blvd Atwell",
    "sg:classifiers":[
        {
            "category":"Shopping",
            "subcategory":"Bridal",
            "type":"Retail Goods"
        }
    ],
    "sg:phone":"+61 8 9498 6227",
    "sg:postcode":"6164",
    "sg:province":"WA",
    "sg:tags":[
        "hire",
        "wear"
    ],
    "wof:name":"Tranquility Hair & Body Studio",
    "wof:placetype":"venue"
},
  "geometry": {"coordinates":[115.867203,-32.13633],"type":"Point"}
}