{
  "type": "Feature",
  "properties": {
    "iso:country":"AU",
    "sg:address":"Shop 1 126 Collins Ave",
    "sg:city":"Edge Hill",
    "sg:classifiers":[
        {
            "category":"Personal",
            "subcategory":"Beauty Salon",
            "type":"Services"
        }
    ],
    "sg:phone":"+61 7 4053 4617",
    "sg:postcode":"4870",
    "sg:province":"QLD",
    "sg:tags":[
        "hairdresser"
    ],
    "wof:name":"Snipz Hair Salon Of Cairns",
    "wof:placetype":"venue"
},
  "geometry": {"coordinates":[145.74229431099999,-16.9008903503],"type":"Point"}
}