{
  "type": "Feature",
  "properties": {
    "addr:full":"20 John St Hunters Hill NSW 2110",
    "addr:housenumber":"20",
    "addr:postcode":"2110",
    "addr:street":"John St",
    "iso:country":"AU",
    "sg:address":"20 John St",
    "sg:city":"Hunters Hill",
    "sg:classifiers":[
        {
            "category":"Professional",
            "subcategory":"Accounting & Tax Preparation",
            "type":"Services"
        }
    ],
    "sg:phone":"+61 2 9879 7078",
    "sg:postcode":"2110",
    "sg:province":"NSW",
    "sg:tags":[
        "consultant",
        "taxation"
    ],
    "wof:name":"Davis Peter Taxation & Accounting Services",
    "wof:placetype":"venue"
},
  "geometry": {"coordinates":[151.134857178,-33.8311576843],"type":"Point"}
}