{
  "type": "Feature",
  "properties": {
    "addr:full":"12 Warwick St Hobart TAS 7000",
    "addr:housenumber":"12",
    "addr:postcode":"7000",
    "addr:street":"Warwick St",
    "iso:country":"AU",
    "sg:address":"12 Warwick St",
    "sg:city":"Hobart",
    "sg:classifiers":[
        {
            "category":"Commercial Area",
            "type":"Public Place"
        }
    ],
    "sg:phone":"+61 407 036 603",
    "sg:postcode":"7000",
    "sg:province":"TAS",
    "sg:tags":[
        "heavy",
        "carrier"
    ],
    "wof:name":"Jackson's Transport Services Pty Ltd",
    "wof:placetype":"venue"
},
  "geometry": {"coordinates":[147.32379150400001,-42.8744888306],"type":"Point"}
}