{
  "type": "Feature",
  "properties": {
    "iso:country":"AU",
    "sg:address":"16 Hill St",
    "sg:city":"Burnside",
    "sg:classifiers":[
        {
            "category":"Building & Trades",
            "subcategory":"Plumbing",
            "type":"Services"
        }
    ],
    "sg:phone":"+61 418 843 383",
    "sg:postcode":"5066",
    "sg:province":"SA",
    "sg:tags":[
        "plumber",
        "gasfitters"
    ],
    "wof:name":"Burnside Plumbing Service",
    "wof:placetype":"venue"
},
  "geometry": {"coordinates":[138.66331481899999,-34.9392280579],"type":"Point"}
}