{
  "type": "Feature",
  "properties": {
    "iso:country":"AU",
    "sg:address":"136 Clontarf St",
    "sg:city":"Seaforth",
    "sg:classifiers":[
        {
            "category":"Personal",
            "type":"Services"
        }
    ],
    "sg:phone":"+61 2 9949 1873",
    "sg:postcode":"2092",
    "sg:province":"NSW",
    "sg:tags":[
        "wallpapering",
        "wallcovering"
    ],
    "wof:name":"Alexander R & W Pty Ltd",
    "wof:placetype":"venue"
},
  "geometry": {"coordinates":[151.24273681599999,-33.7824134827],"type":"Point"}
}