{
  "type": "Feature",
  "properties": {
    "addr:full":"280 Comur St Yass NSW 2582",
    "addr:housenumber":"280",
    "addr:postcode":"2582",
    "addr:street":"Comur St",
    "iso:country":"AU",
    "sg:address":"280 Comur St",
    "sg:city":"Yass",
    "sg:classifiers":[
        {
            "category":"Autos & Motor Vehicles",
            "subcategory":"Automobile Sales",
            "type":"Retail Goods"
        }
    ],
    "sg:phone":"+61 2 6226 1122",
    "sg:postcode":"2582",
    "sg:province":"NSW",
    "sg:tags":[
        "car",
        "used"
    ],
    "wof:name":"Luff Motors",
    "wof:placetype":"venue"
},
  "geometry": {"coordinates":[148.915817261,-34.8470573425],"type":"Point"}
}