{
  "type": "Feature",
  "properties": {
    "iso:country":"AU",
    "sg:address":"35 Edgar St",
    "sg:city":"Portland",
    "sg:classifiers":[
        {
            "category":"Retail",
            "subcategory":"Car Wash",
            "type":"Services"
        }
    ],
    "sg:phone":"+61 3 5521 7316",
    "sg:postcode":"3305",
    "sg:province":"VIC",
    "sg:tags":[
        "truck",
        "cleaning"
    ],
    "wof:name":"Greenys Car Detailing",
    "wof:placetype":"venue"
},
  "geometry": {"coordinates":[141.62059020999999,-38.3622932434],"type":"Point"}
}