{
  "type": "Feature",
  "properties": {
    "addr:full":"179 Drummond St Dennington VIC 3280",
    "addr:housenumber":"179",
    "addr:postcode":"3280",
    "addr:street":"Drummond St",
    "iso:country":"AU",
    "sg:address":"179 Drummond St",
    "sg:city":"Dennington",
    "sg:classifiers":[
        {
            "category":"Retail",
            "subcategory":"Storage",
            "type":"Services"
        }
    ],
    "sg:phone":"+61 3 5562 5707",
    "sg:postcode":"3280",
    "sg:province":"VIC",
    "sg:tags":[
        "cold"
    ],
    "wof:name":"Warrnambool Cool Stores",
    "wof:placetype":"venue"
},
  "geometry": {"coordinates":[142.449707031,-38.358581543],"type":"Point"}
}