{
  "type": "Feature",
  "properties": {
    "iso:country":"AU",
    "sg:address":"626 Hawthorn Rd",
    "sg:city":"Brighton East",
    "sg:classifiers":[
        {
            "category":"Professional",
            "subcategory":"Art Services",
            "type":"Services"
        }
    ],
    "sg:phone":"+61 3 9596 8511",
    "sg:postcode":"3187",
    "sg:province":"VIC",
    "sg:tags":[
        "graphic",
        "designer"
    ],
    "wof:name":"Sarn Potter Graphics",
    "wof:placetype":"venue"
},
  "geometry": {"coordinates":[145.018798828,-37.9024124146],"type":"Point"}
}