{
  "type": "Feature",
  "properties": {
    "addr:full":"169 Canterbury Rd Kilsyth VIC 3137",
    "addr:housenumber":"169",
    "addr:postcode":"3137",
    "addr:street":"Canterbury Rd",
    "iso:country":"AU",
    "sg:address":"169 Canterbury Rd",
    "sg:city":"Kilsyth",
    "sg:classifiers":[
        {
            "category":"Home & Garden",
            "subcategory":"Furniture",
            "type":"Retail Goods"
        }
    ],
    "sg:phone":"+61 3 9761 4245",
    "sg:postcode":"3137",
    "sg:province":"VIC",
    "sg:tags":[
        "outdoor"
    ],
    "wof:name":"Elite Metals Pty Ltd",
    "wof:placetype":"venue"
},
  "geometry": {"coordinates":[145.30487060600001,-37.8212051392],"type":"Point"}
}