{
  "type": "Feature",
  "properties": {
    "addr:full":"19 Days Rd Grange QLD 4051",
    "addr:housenumber":"19",
    "addr:postcode":"4051",
    "addr:street":"Days Rd",
    "iso:country":"AU",
    "sg:address":"19 Days Rd",
    "sg:city":"Grange",
    "sg:classifiers":[
        {
            "category":"Professional",
            "subcategory":"Art Services",
            "type":"Services"
        }
    ],
    "sg:phone":"+61 7 3856 4463",
    "sg:postcode":"4051",
    "sg:province":"QLD",
    "sg:tags":[
        "graphic",
        "designer"
    ],
    "wof:name":"CMA Creative & Design",
    "wof:placetype":"venue"
},
  "geometry": {"coordinates":[153.022613525,-27.4269428253],"type":"Point"}
}