{
  "type": "Feature",
  "properties": {
    "iso:country":"AU",
    "sg:address":"Shop 8b Queens Rd",
    "sg:city":"Scarness",
    "sg:classifiers":[
        {
            "category":"Personal",
            "type":"Services"
        }
    ],
    "sg:phone":"+61 7 4128 1114",
    "sg:postcode":"4655",
    "sg:province":"QLD",
    "sg:tags":[
        "gift"
    ],
    "wof:name":"Scarness Florist",
    "wof:placetype":"venue"
},
  "geometry": {"coordinates":[152.853928,-25.284222],"type":"Point"}
}