{
  "type": "Feature",
  "properties": {
    "addr:full":"Kiosk 7 Westfield Tuggerah Shopping Centre, Cnr Cobbs & Gavenlock Rds Tuggerah NSW 2259",
    "addr:postcode":"2259",
    "addr:street":"Cnr",
    "iso:country":"AU",
    "sg:address":"Kiosk 7 Westfield Tuggerah Shopping Centre, Cnr Cobbs & Gavenlock Rds",
    "sg:city":"Tuggerah",
    "sg:classifiers":[
        {
            "category":"Building & Trades",
            "subcategory":"Locksmith",
            "type":"Services"
        }
    ],
    "sg:phone":"+61 2 4353 4305",
    "sg:postcode":"2259",
    "sg:province":"NSW",
    "sg:tags":[
        "lock"
    ],
    "wof:name":"Mister Minit",
    "wof:placetype":"venue"
},
  "geometry": {"coordinates":[151.417205811,-33.307674408],"type":"Point"}
}