{
  "type": "Feature",
  "properties": {
    "iso:country":"AU",
    "sg:address":"Brolga Pl",
    "sg:city":"Coleambally",
    "sg:classifiers":[
        {
            "category":"Travel",
            "subcategory":"Hotels & Motels",
            "type":"Entertainment"
        }
    ],
    "sg:phone":"+61 2 6954 4009",
    "sg:postcode":"2707",
    "sg:province":"NSW",
    "wof:name":"Brolga Hotel",
    "wof:placetype":"venue"
},
  "geometry": {"coordinates":[145.88035583499999,-34.806476593],"type":"Point"}
}