{
  "type": "Feature",
  "properties": {
    "addr:full":"379 Belgravia St Cloverdale WA 6105",
    "addr:housenumber":"379",
    "addr:postcode":"6105",
    "addr:street":"Belgravia St",
    "iso:country":"AU",
    "sg:address":"379 Belgravia St",
    "sg:city":"Cloverdale",
    "sg:classifiers":[
        {
            "category":"Deli",
            "type":"Food & Drink"
        }
    ],
    "sg:phone":"+61 8 9277 6145",
    "sg:postcode":"6105",
    "sg:province":"WA",
    "sg:tags":[
        "delicatessen"
    ],
    "wof:name":"Belgravia Fine Foods",
    "wof:placetype":"venue"
},
  "geometry": {"coordinates":[115.945648193,-31.9629554749],"type":"Point"}
}