{
  "type": "Feature",
  "properties": {
    "iso:country":"AU",
    "sg:address":"202 Charters Towers Rd",
    "sg:city":"Hermit Park",
    "sg:classifiers":[
        {
            "category":"Health Services",
            "subcategory":"Dentist",
            "type":"Services"
        }
    ],
    "sg:phone":"+61 7 4725 3366",
    "sg:postcode":"4812",
    "sg:province":"QLD",
    "sg:tags":[
        "dental",
        "prosthetist"
    ],
    "wof:name":"Courtney Bernie & Brett",
    "wof:placetype":"venue"
},
  "geometry": {"coordinates":[146.797882,-19.28373],"type":"Point"}
}