{
  "type": "Feature",
  "properties": {
    "iso:country":"AU",
    "sg:address":"410 Regency Rd",
    "sg:city":"Prospect",
    "sg:classifiers":[
        {
            "category":"Professional",
            "subcategory":"Detective & Security Services",
            "type":"Services"
        }
    ],
    "sg:phone":"+61 418 825 943",
    "sg:postcode":"5082",
    "sg:province":"SA",
    "sg:tags":[
        "consultant",
        "laser"
    ],
    "wof:name":"Multi Shape Profile Routing",
    "wof:placetype":"venue"
},
  "geometry": {"coordinates":[138.59286499000001,-34.8739585876],"type":"Point"}
}