{
  "type": "Feature",
  "properties": {
    "iso:country":"AU",
    "sg:address":"Ferntree Gully Rd",
    "sg:city":"Notting Hill",
    "sg:classifiers":[
        {
            "category":"Education",
            "subcategory":"Dance Studio",
            "type":"Public Place"
        }
    ],
    "sg:phone":"+61 3 9753 3401",
    "sg:postcode":"3168",
    "sg:province":"VIC",
    "sg:tags":[
        "square",
        "caller",
        "dancing"
    ],
    "wof:name":"Jaybee Square Wheelers",
    "wof:placetype":"venue"
},
  "geometry": {"coordinates":[145.14271545400001,-37.9011993408],"type":"Point"}
}