{
  "type": "Feature",
  "properties": {
    "addr:full":"540 Port Rd Allenby Gardens SA 5009",
    "addr:housenumber":"540",
    "addr:postcode":"5009",
    "addr:street":"Port Rd",
    "iso:country":"AU",
    "sg:address":"540 Port Rd",
    "sg:city":"Allenby Gardens",
    "sg:classifiers":[
        {
            "category":"Travel",
            "subcategory":"Hotels & Motels",
            "type":"Entertainment"
        }
    ],
    "sg:phone":"+61 8 8346 2838",
    "sg:postcode":"5009",
    "sg:province":"SA",
    "sg:tags":[
        "pub"
    ],
    "wof:name":"Tavern 540",
    "wof:placetype":"venue"
},
  "geometry": {"coordinates":[138.55592346200001,-34.8950271606],"type":"Point"}
}