{
  "type": "Feature",
  "properties": {
    "addr:full":"82 Grose Rd Faulconbridge NSW 2776",
    "addr:housenumber":"82",
    "addr:postcode":"2776",
    "addr:street":"Grose Rd",
    "iso:country":"AU",
    "sg:address":"82 Grose Rd",
    "sg:city":"Faulconbridge",
    "sg:classifiers":[
        {
            "category":"Professional",
            "subcategory":"Management & Consulting",
            "type":"Services"
        }
    ],
    "sg:phone":"+61 2 4751 2475",
    "sg:postcode":"2776",
    "sg:province":"NSW",
    "sg:tags":[
        "consultant"
    ],
    "wof:name":"Altitude Consulting",
    "wof:placetype":"venue"
},
  "geometry": {"coordinates":[150.54881286599999,-33.6860542297],"type":"Point"}
}