{
  "type": "Feature",
  "properties": {
    "addr:full":"172 Bridport St Albert Park VIC 3206",
    "addr:housenumber":"172",
    "addr:postcode":"3206",
    "addr:street":"Bridport St",
    "iso:country":"AU",
    "sg:address":"172 Bridport St",
    "sg:city":"Albert Park",
    "sg:classifiers":[
        {
            "category":"Shopping",
            "subcategory":"Clothing, Apparel, & Fashions",
            "type":"Retail Goods"
        }
    ],
    "sg:phone":"+61 3 9690 4021",
    "sg:postcode":"3206",
    "sg:province":"VIC",
    "sg:tags":[
        "menswear"
    ],
    "wof:name":"Mike Treloar Investments Pty Ltd",
    "wof:placetype":"venue"
},
  "geometry": {"coordinates":[144.95472699999999,-37.840828],"type":"Point"}
}