{
  "type": "Feature",
  "properties": {
    "iso:country":"AU",
    "sg:address":"380 Chapel Rd",
    "sg:city":"Bankstown",
    "sg:classifiers":[
        {
            "category":"Health Services",
            "subcategory":"Dentist",
            "type":"Services"
        }
    ],
    "sg:phone":"+61 2 9709 5806",
    "sg:postcode":"2200",
    "sg:province":"NSW",
    "wof:name":"McCrystal S M Munroe W J",
    "wof:placetype":"venue"
},
  "geometry": {"coordinates":[151.032913,-33.916843],"type":"Point"}
}