{
  "type": "Feature",
  "properties": {
    "iso:country":"AU",
    "sg:address":"3 Carbost Crt",
    "sg:city":"Macleod",
    "sg:classifiers":[
        {
            "category":"Shopping",
            "type":"Retail Goods"
        }
    ],
    "sg:phone":"+61 3 9458 3390",
    "sg:postcode":"3085",
    "sg:province":"VIC",
    "sg:tags":[
        "equipment",
        "safety",
        "accessory"
    ],
    "wof:name":"Halson Enterprises Pty Ltd",
    "wof:placetype":"venue"
},
  "geometry": {"coordinates":[145.06933593799999,-37.7201538086],"type":"Point"}
}