{
  "type": "Feature",
  "properties": {
    "addr:full":"Shp2/ 183 Union St The Junction NSW 2291",
    "addr:housenumber":"183",
    "addr:postcode":"2291",
    "addr:street":"Union St",
    "iso:country":"AU",
    "sg:address":"Shp2/ 183 Union St",
    "sg:city":"The Junction",
    "sg:classifiers":[
        {
            "category":"Fast Food",
            "type":"Food & Drink"
        }
    ],
    "sg:phone":"+61 2 4961 5882",
    "sg:postcode":"2291",
    "sg:province":"NSW",
    "sg:tags":[
        "away",
        "take"
    ],
    "wof:name":"Enjoy The Different Taste",
    "wof:placetype":"venue"
},
  "geometry": {"coordinates":[151.75970459000001,-32.9376525879],"type":"Point"}
}