{
  "type": "Feature",
  "properties": {
    "iso:country":"AU",
    "sg:address":"Unit 5/ 90 Jervious St",
    "sg:city":"Torrensville",
    "sg:classifiers":[
        {
            "category":"Wholesale",
            "subcategory":"Home Furnishings",
            "type":"Manufacturing & Wholesale Goods"
        }
    ],
    "sg:phone":"+61 1800 142 737",
    "sg:postcode":"5031",
    "sg:province":"SA",
    "sg:tags":[
        "tile",
        "wholesaler",
        "mfrs",
        "carpet"
    ],
    "wof:name":"Redbook Carpets",
    "wof:placetype":"venue"
},
  "geometry": {"coordinates":[138.560745239,-34.9140396118],"type":"Point"}
}