{
  "type": "Feature",
  "properties": {
    "addr:full":"Unit 1, 15 Overlord Pl Acacia Ridge QLD 4110",
    "addr:housenumber":"15",
    "addr:postcode":"4110",
    "addr:street":"Overlord Pl",
    "iso:country":"AU",
    "sg:address":"Unit 1, 15 Overlord Pl",
    "sg:city":"Acacia Ridge",
    "sg:classifiers":[
        {
            "category":"Home & Garden",
            "subcategory":"Hardware",
            "type":"Retail Goods"
        }
    ],
    "sg:phone":"+61 7 3272 2377",
    "sg:postcode":"4110",
    "sg:province":"QLD",
    "sg:tags":[
        "battery",
        "dry",
        "rechargeable",
        "cell"
    ],
    "wof:name":"Australian Battery Distributors Pty. Ltd.",
    "wof:placetype":"venue"
},
  "geometry": {"coordinates":[153.03706359899999,-27.5954666138],"type":"Point"}
}