{
  "type": "Feature",
  "properties": {
    "iso:country":"AU",
    "sg:address":"30 Nerang St",
    "sg:city":"Southport",
    "sg:classifiers":[
        {
            "category":"Shopping",
            "subcategory":"Beauty & Cosmetics",
            "type":"Retail Goods"
        }
    ],
    "sg:phone":"+61 7 5528 1044",
    "sg:postcode":"4215",
    "sg:province":"QLD",
    "wof:name":"Cosmetic Girl Pty Ltd",
    "wof:placetype":"venue"
},
  "geometry": {"coordinates":[153.414825439,-27.9672546387],"type":"Point"}
}