{
  "type": "Feature",
  "properties": {
    "iso:country":"AU",
    "sg:address":"Cnr Coglin Rd & Philip Hwy",
    "sg:city":"Elizabeth South",
    "sg:classifiers":[
        {
            "category":"Government",
            "subcategory":"Department Of Motor Vehicles",
            "type":"Public Place"
        }
    ],
    "sg:phone":"+61 8 8252 4044",
    "sg:postcode":"5112",
    "sg:province":"SA",
    "sg:tags":[
        "container",
        "recycling",
        "beverage",
        "sa",
        "depot"
    ],
    "wof:name":"Elizabeth Bottle & Wood Yard",
    "wof:placetype":"venue"
},
  "geometry": {"coordinates":[138.659500122,-34.7489891052],"type":"Point"}
}