{
  "type": "Feature",
  "properties": {
    "iso:country":"AU",
    "sg:address":"Unit 56/ 249 Chalmers St",
    "sg:city":"Redfern",
    "sg:classifiers":[
        {
            "category":"Communications",
            "subcategory":"Film & Video Production",
            "type":"Services"
        }
    ],
    "sg:phone":"+61 2 9698 8321",
    "sg:postcode":"2016",
    "sg:province":"NSW",
    "sg:tags":[
        "yacht",
        "transport",
        "boat"
    ],
    "wof:name":"Sydney Gondolas Pty Ltd",
    "wof:placetype":"venue"
},
  "geometry": {"coordinates":[151.20501709000001,-33.8942260742],"type":"Point"}
}