{
  "type": "Feature",
  "properties": {
    "addr:full":"11 Westbrook Ave Wahroonga NSW 2076",
    "addr:housenumber":"11",
    "addr:postcode":"2076",
    "addr:street":"Westbrook Ave",
    "iso:country":"AU",
    "sg:address":"11 Westbrook Ave",
    "sg:city":"Wahroonga",
    "sg:classifiers":[
        {
            "category":"Professional",
            "subcategory":"Management & Consulting",
            "type":"Services"
        }
    ],
    "sg:phone":"+61 2 9989 8000",
    "sg:postcode":"2076",
    "sg:province":"NSW",
    "sg:tags":[
        "consultant"
    ],
    "wof:name":"New Business Evolution",
    "wof:placetype":"venue"
},
  "geometry": {"coordinates":[151.135421753,-33.7146263123],"type":"Point"}
}