{
  "type": "Feature",
  "properties": {
    "iso:country":"AU",
    "sg:address":"Lot 1 Temby Rd",
    "sg:city":"Two Wells",
    "sg:classifiers":[
        {
            "category":"Professional",
            "subcategory":"Business Services",
            "type":"Services"
        }
    ],
    "sg:phone":"+61 424 876 421",
    "sg:postcode":"5501",
    "sg:province":"SA",
    "sg:tags":[
        "management",
        "event"
    ],
    "wof:name":"The Magic Fairy",
    "wof:placetype":"venue"
},
  "geometry": {"coordinates":[138.54054300000001,-34.571121],"type":"Point"}
}