{
  "type": "Feature",
  "properties": {
    "addr:full":"6/ 1 Almondbury Rd Mt Lawley WA 6050",
    "addr:housenumber":"/ 1",
    "addr:postcode":"6050",
    "addr:street":"Almondbury Rd",
    "iso:country":"AU",
    "sg:address":"6/ 1 Almondbury Rd",
    "sg:city":"Mt Lawley",
    "sg:classifiers":[
        {
            "category":"Banks & Credit Unions",
            "subcategory":"Financial Services",
            "type":"Services"
        }
    ],
    "sg:phone":"+61 8 9471 8433",
    "sg:postcode":"6050",
    "sg:province":"WA",
    "sg:tags":[
        "loan",
        "finance",
        "mortgage"
    ],
    "wof:name":"Complete Financial Services Australia Pty Ltd",
    "wof:placetype":"venue"
},
  "geometry": {"coordinates":[115.879089355,-31.9356975555],"type":"Point"}
}