{
  "type": "Feature",
  "properties": {
    "addr:full":"Unit C, 55- 61 Talavera Rd North Ryde NSW 2113",
    "addr:housenumber":"61",
    "addr:postcode":"2113",
    "addr:street":"C 55;Talavera Rd",
    "iso:country":"AU",
    "sg:address":"Unit C, 55- 61 Talavera Rd",
    "sg:city":"North Ryde",
    "sg:classifiers":[
        {
            "category":"Professional",
            "subcategory":"Detective & Security Services",
            "type":"Services"
        }
    ],
    "sg:phone":"+61 2 8875 0201",
    "sg:postcode":"2113",
    "sg:province":"NSW",
    "sg:tags":[
        "identification",
        "system"
    ],
    "wof:name":"Symbol Technologies",
    "wof:placetype":"venue"
},
  "geometry": {"coordinates":[151.12220764200001,-33.7760505676],"type":"Point"}
}