{
  "type": "Feature",
  "properties": {
    "iso:country":"AU",
    "sg:address":"3400 Warburton Hwy",
    "sg:city":"Warburton",
    "sg:classifiers":[
        {
            "category":"Communications",
            "subcategory":"News Services",
            "type":"Services"
        }
    ],
    "sg:phone":"+61 3 5966 9600",
    "sg:postcode":"3799",
    "sg:province":"VIC",
    "sg:tags":[
        "information",
        "tourist",
        "attractions"
    ],
    "wof:name":"Warburton Water Wheel Visitor Information Centre",
    "wof:placetype":"venue"
},
  "geometry": {"coordinates":[145.69866943400001,-37.7531318665],"type":"Point"}
}