{
  "type": "Feature",
  "properties": {
    "addr:full":"Un 2, 22 London Drv Bayswater VIC 3153",
    "addr:housenumber":"22",
    "addr:postcode":"3153",
    "addr:street":"London Drv",
    "iso:country":"AU",
    "sg:address":"Un 2, 22 London Drv",
    "sg:city":"Bayswater",
    "sg:classifiers":[
        {
            "category":"Retail",
            "subcategory":"Auto Repair",
            "type":"Services"
        }
    ],
    "sg:phone":"+61 3 9762 2600",
    "sg:postcode":"3153",
    "sg:province":"VIC",
    "sg:tags":[
        "repairer",
        "motor",
        "engineer"
    ],
    "wof:name":"All Ranges 4wd Services",
    "wof:placetype":"venue"
},
  "geometry": {"coordinates":[145.28262329099999,-37.8447990417],"type":"Point"}
}