{
  "type": "Feature",
  "properties": {
    "addr:full":"8 Teal Crt Wurtulla QLD 4575",
    "addr:housenumber":"8",
    "addr:postcode":"4575",
    "addr:street":"Teal Crt",
    "iso:country":"AU",
    "sg:address":"8 Teal Crt",
    "sg:city":"Wurtulla",
    "sg:classifiers":[
        {
            "category":"Professional",
            "subcategory":"Management & Consulting",
            "type":"Services"
        }
    ],
    "sg:phone":"+61 7 5493 1099",
    "sg:postcode":"4575",
    "sg:province":"QLD",
    "sg:tags":[
        "consultant"
    ],
    "wof:name":"Curd Management Group",
    "wof:placetype":"venue"
},
  "geometry": {"coordinates":[153.132904,-26.755053],"type":"Point"}
}