{
  "type": "Feature",
  "properties": {
    "addr:full":"316 Carlisle St Balaclava VIC 3183",
    "addr:housenumber":"316",
    "addr:postcode":"3183",
    "addr:street":"Carlisle St",
    "iso:country":"AU",
    "sg:address":"316 Carlisle St",
    "sg:city":"Balaclava",
    "sg:classifiers":[
        {
            "category":"Food & Beverages",
            "subcategory":"Supermarket",
            "type":"Retail Goods"
        }
    ],
    "sg:phone":"+61 3 9727 3237",
    "sg:postcode":"3183",
    "sg:province":"VIC",
    "sg:tags":[
        "grocery",
        "store"
    ],
    "wof:name":"Sunrise Fruits Pty. Ltd.",
    "wof:placetype":"venue"
},
  "geometry": {"coordinates":[144.995040894,-37.8688011169],"type":"Point"}
}