{
  "type": "Feature",
  "properties": {
    "addr:full":"22a Norseman Rd Esperance WA 6450",
    "addr:housenumber":"22a",
    "addr:postcode":"6450",
    "addr:street":"Norseman Rd",
    "iso:country":"AU",
    "sg:address":"22a Norseman Rd",
    "sg:city":"Esperance",
    "sg:classifiers":[
        {
            "category":"Manufacturing",
            "subcategory":"Motor Vehicles & Parts",
            "type":"Manufacturing & Wholesale Goods"
        }
    ],
    "sg:phone":"+61 8 9071 6688",
    "sg:postcode":"6450",
    "sg:province":"WA",
    "sg:tags":[
        "replacement"
    ],
    "wof:name":"Auto One Parts & Accessories",
    "wof:placetype":"venue"
},
  "geometry": {"coordinates":[121.90003967299999,-33.8439331055],"type":"Point"}
}