{
  "type": "Feature",
  "properties": {
    "iso:country":"AU",
    "sg:address":"81 Saints Rd",
    "sg:city":"Salisbury Plain",
    "sg:classifiers":[
        {
            "category":"Autos & Motor Vehicles",
            "subcategory":"Automobile Sales",
            "type":"Retail Goods"
        }
    ],
    "sg:phone":"+61 8 8283 2233",
    "sg:postcode":"5109",
    "sg:province":"SA",
    "sg:tags":[
        "car",
        "used"
    ],
    "wof:name":"Gurney's Cheaper Car Centre",
    "wof:placetype":"venue"
},
  "geometry": {"coordinates":[138.667114258,-34.764919281],"type":"Point"}
}