{
  "type": "Feature",
  "properties": {
    "addr:full":"10 Valiant St Rochedale South QLD 4123",
    "addr:housenumber":"10",
    "addr:postcode":"4123",
    "addr:street":"Valiant St",
    "iso:country":"AU",
    "sg:address":"10 Valiant St",
    "sg:city":"Rochedale South",
    "sg:classifiers":[
        {
            "category":"Building & Trades",
            "subcategory":"Construction",
            "type":"Services"
        }
    ],
    "sg:phone":"+61 402 521 961",
    "sg:postcode":"4123",
    "sg:province":"QLD",
    "sg:tags":[
        "polishing",
        "sanding",
        "floor"
    ],
    "wof:name":"George Cassar Floor Sanding",
    "wof:placetype":"venue"
},
  "geometry": {"coordinates":[153.12663269000001,-27.6028385162],"type":"Point"}
}