{
  "type": "Feature",
  "properties": {
    "iso:country":"AU",
    "sg:address":"29 Production Ave",
    "sg:city":"Kogarah",
    "sg:classifiers":[
        {
            "category":"Utilities",
            "type":"Services"
        }
    ],
    "sg:phone":"+61 2 9553 9988",
    "sg:postcode":"2217",
    "sg:province":"NSW",
    "sg:tags":[
        "refrigeration",
        "industrial",
        "commercial",
        "retail"
    ],
    "wof:name":"J A Metalworks",
    "wof:placetype":"venue"
},
  "geometry": {"coordinates":[151.13931299999999,-33.97847],"type":"Point"}
}