{
  "type": "Feature",
  "properties": {
    "iso:country":"AU",
    "sg:address":"24 Frederick St",
    "sg:city":"Oatley",
    "sg:classifiers":[
        {
            "category":"Shopping",
            "subcategory":"Clothing, Apparel, & Fashions",
            "type":"Retail Goods"
        }
    ],
    "sg:phone":"+61 2 9580 6972",
    "sg:postcode":"2223",
    "sg:province":"NSW",
    "sg:tags":[
        "lady",
        "wear"
    ],
    "wof:name":"Emma James",
    "wof:placetype":"venue"
},
  "geometry": {"coordinates":[151.081130981,-33.9810447693],"type":"Point"}
}