{
  "type": "Feature",
  "properties": {
    "addr:full":"Suite 8a 11 Beach St Port Melbourne VIC 3207",
    "addr:housenumber":"11",
    "addr:postcode":"3207",
    "addr:street":"Beach St",
    "iso:country":"AU",
    "sg:address":"Suite 8a 11 Beach St",
    "sg:city":"Port Melbourne",
    "sg:classifiers":[
        {
            "category":"Professional",
            "subcategory":"Engineering",
            "type":"Services"
        }
    ],
    "sg:phone":"+61 3 9646 5277",
    "sg:postcode":"3207",
    "sg:province":"VIC",
    "sg:tags":[
        "consulting",
        "engineer"
    ],
    "wof:name":"Robert Read & Associates",
    "wof:placetype":"venue"
},
  "geometry": {"coordinates":[144.93962099999999,-37.843758],"type":"Point"}
}