{
  "type": "Feature",
  "properties": {
    "addr:full":"PO Box 89 Gogango QLD 4702",
    "addr:postcode":"4702",
    "iso:country":"AU",
    "sg:address":"PO Box 89",
    "sg:city":"Gogango",
    "sg:classifiers":[
        {
            "category":"Building & Trades",
            "subcategory":"Landscaping Services",
            "type":"Services"
        }
    ],
    "sg:phone":"+61 7 4934 7593",
    "sg:postcode":"4702",
    "sg:province":"QLD",
    "sg:tags":[
        "grazier"
    ],
    "wof:name":"Dunphy J E",
    "wof:placetype":"venue"
},
  "geometry": {"coordinates":[150.03758239699999,-23.6680793762],"type":"Point"}
}