{
  "type": "Feature",
  "properties": {
    "addr:full":"106 Harris St Harris Park NSW 2150",
    "addr:housenumber":"106",
    "addr:postcode":"2150",
    "addr:street":"Harris St",
    "iso:country":"AU",
    "sg:address":"106 Harris St",
    "sg:city":"Harris Park",
    "sg:classifiers":[
        {
            "category":"Health Services",
            "subcategory":"Dentist",
            "type":"Services"
        }
    ],
    "sg:phone":"+61 2 9891 4099",
    "sg:postcode":"2150",
    "sg:province":"NSW",
    "sg:tags":[
        "technician",
        "dental"
    ],
    "wof:name":"Sydney Oral Design",
    "wof:placetype":"venue"
},
  "geometry": {"coordinates":[151.011154175,-33.8188705444],"type":"Point"}
}