{
  "type": "Feature",
  "properties": {
    "iso:country":"AU",
    "sg:address":"16a Pembroke Rd",
    "sg:city":"Ocean Grove",
    "sg:classifiers":[
        {
            "category":"Personal",
            "subcategory":"Massage",
            "type":"Services"
        }
    ],
    "sg:phone":"+61 3 5255 4445",
    "sg:postcode":"3226",
    "sg:province":"VIC",
    "sg:tags":[
        "therapy"
    ],
    "wof:name":"Pembroke Massage",
    "wof:placetype":"venue"
},
  "geometry": {"coordinates":[144.54747,-38.266037],"type":"Point"}
}