{
  "type": "Feature",
  "properties": {
    "addr:full":"Shop P37-P39 Greenwood Plaza Blue St North Sydney NSW 2060",
    "addr:housenumber":"p37-p39",
    "addr:postcode":"2060",
    "addr:street":"Greenwood Plaza Blue St",
    "iso:country":"AU",
    "sg:address":"Shop P37-P39 Greenwood Plaza Blue St",
    "sg:city":"North Sydney",
    "sg:classifiers":[
        {
            "category":"Shopping",
            "subcategory":"Clothing, Apparel, & Fashions",
            "type":"Retail Goods"
        }
    ],
    "sg:phone":"+61 2 9956 6926",
    "sg:postcode":"2060",
    "sg:province":"NSW",
    "sg:tags":[
        "lady",
        "wear"
    ],
    "wof:name":"Esprit Retail Pty Ltd",
    "wof:placetype":"venue"
},
  "geometry": {"coordinates":[151.20603942899999,-33.8407440186],"type":"Point"}
}