{
  "type": "Feature",
  "properties": {
    "addr:full":"290 Wolseley Pl Thomastown VIC 3074",
    "addr:housenumber":"290",
    "addr:postcode":"3074",
    "addr:street":"Wolseley Pl",
    "iso:country":"AU",
    "sg:address":"290 Wolseley Pl",
    "sg:city":"Thomastown",
    "sg:classifiers":[
        {
            "category":"Building & Trades",
            "subcategory":"Construction",
            "type":"Services"
        }
    ],
    "sg:phone":"+61 418 319 329",
    "sg:postcode":"3074",
    "sg:province":"VIC",
    "sg:tags":[
        "contractor"
    ],
    "wof:name":"Apex Constructions Builders & Developers",
    "wof:placetype":"venue"
},
  "geometry": {"coordinates":[145.000854492,-37.689617157],"type":"Point"}
}