{
  "type": "Feature",
  "properties": {
    "iso:country":"AU",
    "sg:address":"Maitland Rd",
    "sg:city":"Paskeville",
    "sg:classifiers":[
        {
            "category":"Education",
            "subcategory":"School",
            "type":"Public Place"
        }
    ],
    "sg:phone":"+61 8 8827 2161",
    "sg:postcode":"5552",
    "sg:province":"SA",
    "sg:tags":[
        "state",
        "except",
        "nsw"
    ],
    "wof:name":"Paskeville District Primary School",
    "wof:placetype":"venue"
},
  "geometry": {"coordinates":[137.86000060999999,-34.0208511353],"type":"Point"}
}