{
  "type": "Feature",
  "properties": {
    "iso:country":"AU",
    "sg:address":"60 Clovelly Rd",
    "sg:city":"Randwick",
    "sg:classifiers":[
        {
            "category":"Education",
            "subcategory":"Music School",
            "type":"Public Place"
        }
    ],
    "sg:phone":"+61 2 9665 9713",
    "sg:postcode":"2031",
    "sg:province":"NSW",
    "sg:tags":[
        "teacher"
    ],
    "wof:name":"Music & Movement For Young Children",
    "wof:placetype":"venue"
},
  "geometry": {"coordinates":[151.25015258799999,-33.9099121094],"type":"Point"}
}