{
  "type": "Feature",
  "properties": {
    "iso:country":"AU",
    "sg:address":"High School Drv",
    "sg:city":"Winmalee",
    "sg:classifiers":[
        {
            "category":"Education",
            "subcategory":"School",
            "type":"Public Place"
        }
    ],
    "sg:phone":"+61 2 4754 2822",
    "sg:postcode":"2777",
    "sg:province":"NSW",
    "sg:tags":[
        "state",
        "-",
        "nsw"
    ],
    "wof:name":"Winmalee High",
    "wof:placetype":"venue"
},
  "geometry": {"coordinates":[150.61520385700001,-33.6734237671],"type":"Point"}
}