{
  "type": "Feature",
  "properties": {
    "iso:country":"AU",
    "sg:address":"Factory 4 2- 10 Hallam Rd",
    "sg:city":"Hallam",
    "sg:classifiers":[
        {
            "category":"Retail",
            "subcategory":"Auto Repair",
            "type":"Services"
        }
    ],
    "sg:phone":"+61 3 9702 4696",
    "sg:postcode":"3803",
    "sg:province":"VIC",
    "sg:tags":[
        "repairer",
        "motor",
        "engineer"
    ],
    "wof:name":"Denva Brake & Mechanical Services",
    "wof:placetype":"venue"
},
  "geometry": {"coordinates":[145.273345947,-38.0072479248],"type":"Point"}
}