{
  "type": "Feature",
  "properties": {
    "addr:full":"8/ 6 Chaplin Drv Lane Cove NSW 2066",
    "addr:housenumber":"/ 6",
    "addr:postcode":"2066",
    "addr:street":"Chaplin Drv",
    "iso:country":"AU",
    "sg:address":"8/ 6 Chaplin Drv",
    "sg:city":"Lane Cove",
    "sg:classifiers":[
        {
            "category":"Social Services",
            "subcategory":"Retirement Home",
            "type":"Services"
        }
    ],
    "sg:phone":"+61 2 9427 2000",
    "sg:postcode":"2066",
    "sg:province":"NSW",
    "sg:tags":[
        "t-shirt",
        "supplier"
    ],
    "wof:name":"Adimage Promotions Pty. Ltd.",
    "wof:placetype":"venue"
},
  "geometry": {"coordinates":[151.147949219,-33.809803009],"type":"Point"}
}