{
  "type": "Feature",
  "properties": {
    "addr:full":"6 Lealt Pl Ardross WA 6153",
    "addr:housenumber":"6",
    "addr:postcode":"6153",
    "addr:street":"Lealt Pl",
    "iso:country":"AU",
    "sg:address":"6 Lealt Pl",
    "sg:city":"Ardross",
    "sg:classifiers":[
        {
            "category":"Organizations",
            "subcategory":"Membership Organization",
            "type":"Services"
        }
    ],
    "sg:phone":"+61 8 9364 5663",
    "sg:postcode":"6153",
    "sg:province":"WA",
    "sg:tags":[
        "club",
        "car"
    ],
    "wof:name":"BMW Club WA Inc",
    "wof:placetype":"venue"
},
  "geometry": {"coordinates":[115.837051,-32.031578],"type":"Point"}
}