{
  "type": "Feature",
  "properties": {
    "addr:full":"805 Armstrong St North Ballarat VIC 3350",
    "addr:housenumber":"805",
    "addr:postcode":"3350",
    "addr:street":"Armstrong St North",
    "iso:country":"AU",
    "sg:address":"805 Armstrong St North",
    "sg:city":"Ballarat",
    "sg:classifiers":[
        {
            "category":"Building & Trades",
            "subcategory":"Construction",
            "type":"Services"
        }
    ],
    "sg:phone":"+61 3 5331 7685",
    "sg:postcode":"3350",
    "sg:province":"VIC",
    "sg:tags":[
        "contractor"
    ],
    "wof:name":"Doyle Anthony J.",
    "wof:placetype":"venue"
},
  "geometry": {"coordinates":[143.85922199999999,-37.545059],"type":"Point"}
}