{
  "type": "Feature",
  "properties": {
    "iso:country":"AU",
    "sg:address":"1/ 83 Princes Hwy",
    "sg:city":"Fairy Meadow",
    "sg:classifiers":[
        {
            "category":"Home & Garden",
            "subcategory":"Carpets & Floor Coverings",
            "type":"Retail Goods"
        }
    ],
    "sg:phone":"+61 2 4225 0900",
    "sg:postcode":"2519",
    "sg:province":"NSW",
    "sg:tags":[
        "wood"
    ],
    "wof:name":"Wollongong Carpet Choice",
    "wof:placetype":"venue"
},
  "geometry": {"coordinates":[150.891769,-34.399601],"type":"Point"}
}