{
  "type": "Feature",
  "properties": {
    "addr:full":"48A Alexander Ave Taren Point NSW 2229",
    "addr:housenumber":"48a",
    "addr:postcode":"2229",
    "addr:street":"Alexander Ave",
    "iso:country":"AU",
    "sg:address":"48A Alexander Ave",
    "sg:city":"Taren Point",
    "sg:classifiers":[
        {
            "category":"Professional",
            "type":"Services"
        }
    ],
    "sg:phone":"+61 2 9531 6646",
    "sg:postcode":"2229",
    "sg:province":"NSW",
    "sg:tags":[
        "shop",
        "fitting"
    ],
    "sg:website":"http://www.displaywise.com.au",
    "wof:name":"DisplayWise Design & Production",
    "wof:placetype":"venue"
},
  "geometry": {"coordinates":[151.12408447300001,-34.0214385986],"type":"Point"}
}