{
  "type": "Feature",
  "properties": {
    "addr:full":"12 Lake St Windale NSW 2306",
    "addr:housenumber":"12",
    "addr:postcode":"2306",
    "addr:street":"Lake St",
    "iso:country":"AU",
    "sg:address":"12 Lake St",
    "sg:city":"Windale",
    "sg:classifiers":[
        {
            "category":"Education",
            "subcategory":"School",
            "type":"Public Place"
        }
    ],
    "sg:phone":"+61 2 4948 8467",
    "sg:postcode":"2306",
    "sg:province":"NSW",
    "wof:name":"Schools Catholic",
    "wof:placetype":"venue"
},
  "geometry": {"coordinates":[151.681747,-32.993111],"type":"Point"}
}