{
  "type": "Feature",
  "properties": {
    "addr:full":"174 Onkaparinga Valley Rd Woodside SA 5244",
    "addr:housenumber":"174",
    "addr:postcode":"5244",
    "addr:street":"Onkaparinga Valley Rd",
    "iso:country":"AU",
    "sg:address":"174 Onkaparinga Valley Rd",
    "sg:city":"Woodside",
    "sg:classifiers":[
        {
            "category":"Personal",
            "type":"Services"
        }
    ],
    "sg:phone":"+61 8 8389 9400",
    "sg:postcode":"5244",
    "sg:province":"SA",
    "sg:tags":[
        "reducing",
        "treatment",
        "weight"
    ],
    "wof:name":"Herbalife Australasia Pty Ltd",
    "wof:placetype":"venue"
},
  "geometry": {"coordinates":[138.87792968799999,-34.9472236633],"type":"Point"}
}