{
  "type": "Feature",
  "properties": {
    "iso:country":"AU",
    "sg:address":"13 Denny St",
    "sg:city":"Berri",
    "sg:classifiers":[
        {
            "category":"Personal",
            "subcategory":"Beauty Salon",
            "type":"Services"
        }
    ],
    "sg:phone":"+61 8 8582 2740",
    "sg:postcode":"5343",
    "sg:province":"SA",
    "wof:name":"Pure Skin Beauty Therapy",
    "wof:placetype":"venue"
},
  "geometry": {"coordinates":[140.601119995,-34.2870101929],"type":"Point"}
}