{
  "type": "Feature",
  "properties": {
    "iso:country":"AU",
    "sg:address":"Level 3/ 21 May St",
    "sg:city":"Surry Hills",
    "sg:classifiers":[
        {
            "category":"Professional",
            "subcategory":"Accounting & Tax Preparation",
            "type":"Services"
        }
    ],
    "sg:phone":"+61 2 9211 5000",
    "sg:postcode":"2010",
    "sg:province":"NSW",
    "sg:tags":[
        "accountant",
        "auditor"
    ],
    "wof:name":"Management & Accountancy Service Pty Ltd",
    "wof:placetype":"venue"
},
  "geometry": {"coordinates":[151.20999145499999,-33.8811569214],"type":"Point"}
}