{
  "type": "Feature",
  "properties": {
    "addr:full":"Yoku Rd Ashgrove QLD 4060",
    "addr:postcode":"4060",
    "addr:street":"Yoku Rd",
    "iso:country":"AU",
    "sg:address":"Yoku Rd",
    "sg:city":"Ashgrove",
    "sg:classifiers":[
        {
            "category":"Arena",
            "subcategory":"Sports Club",
            "type":"Entertainment"
        }
    ],
    "sg:phone":"+61 7 3366 1266",
    "sg:postcode":"4060",
    "sg:province":"QLD",
    "sg:tags":[
        "union",
        "rugby"
    ],
    "wof:name":"G.P.S. Old Boys Rugby Union Club",
    "wof:placetype":"venue"
},
  "geometry": {"coordinates":[152.97755432100001,-27.444896698],"type":"Point"}
}