{
  "type": "Feature",
  "properties": {
    "addr:full":"153 Browning St Portland VIC 3305",
    "addr:housenumber":"153",
    "addr:postcode":"3305",
    "addr:street":"Browning St",
    "iso:country":"AU",
    "sg:address":"153 Browning St",
    "sg:city":"Portland",
    "sg:classifiers":[
        {
            "category":"Manufacturing",
            "subcategory":"Motor Vehicles & Parts",
            "type":"Manufacturing & Wholesale Goods"
        }
    ],
    "sg:phone":"+61 3 5523 6615",
    "sg:postcode":"3305",
    "sg:province":"VIC",
    "sg:tags":[
        "replacement"
    ],
    "wof:name":"Westvic Auto Salvage",
    "wof:placetype":"venue"
},
  "geometry": {"coordinates":[141.592407227,-38.330329895],"type":"Point"}
}