{
  "type": "Feature",
  "properties": {
    "addr:full":"Ground Floor, 18 Woolley Street Dickson ACT 2602",
    "addr:housenumber":"18",
    "addr:postcode":"2602",
    "addr:street":"Woolley Street",
    "iso:country":"AU",
    "sg:address":"Ground Floor, 18 Woolley Street",
    "sg:city":"Dickson",
    "sg:classifiers":[
        {
            "category":"Fast Food",
            "type":"Food & Drink"
        }
    ],
    "sg:phone":"+61 2 6249 8849",
    "sg:postcode":"2602",
    "sg:province":"ACT",
    "sg:tags":[
        "away",
        "take"
    ],
    "wof:name":"Ruby Chinese Restaurant",
    "wof:placetype":"venue"
},
  "geometry": {"coordinates":[149.13682556099999,-35.25025177],"type":"Point"}
}