{
  "type": "Feature",
  "properties": {
    "iso:country":"AU",
    "sg:address":"225 Karinie St",
    "sg:city":"Swan Hill",
    "sg:classifiers":[
        {
            "category":"Manufacturing",
            "subcategory":"Building Materials",
            "type":"Manufacturing & Wholesale Goods"
        }
    ],
    "sg:phone":"+61 3 5033 1414",
    "sg:postcode":"3585",
    "sg:province":"VIC",
    "sg:tags":[
        "concrete",
        "product"
    ],
    "wof:name":"Swan Crete irrigation & Garden Supplies",
    "wof:placetype":"venue"
},
  "geometry": {"coordinates":[143.53566,-35.325367],"type":"Point"}
}