{
  "type": "Feature",
  "properties": {
    "addr:full":"1204 Great Northern Hwy Upper Swan WA 6069",
    "addr:housenumber":"1204",
    "addr:postcode":"6069",
    "addr:street":"Great Northern Hwy Upper",
    "iso:country":"AU",
    "sg:address":"1204 Great Northern Hwy",
    "sg:city":"Upper Swan",
    "sg:classifiers":[
        {
            "category":"Education",
            "subcategory":"School",
            "type":"Public Place"
        }
    ],
    "sg:phone":"+61 8 9296 4622",
    "sg:postcode":"6069",
    "sg:province":"WA",
    "sg:tags":[
        "state",
        "except",
        "nsw"
    ],
    "wof:name":"Upper Swan Primary School",
    "wof:placetype":"venue"
},
  "geometry": {"coordinates":[116.02987670900001,-31.7697868347],"type":"Point"}
}