{
  "type": "Feature",
  "properties": {
    "iso:country":"AU",
    "sg:address":"Shop 332, Warringah Mall Condamine St",
    "sg:city":"Brookvale",
    "sg:classifiers":[
        {
            "category":"Shopping",
            "subcategory":"Shoes",
            "type":"Retail Goods"
        }
    ],
    "sg:phone":"+61 2 9938 2192",
    "sg:postcode":"2100",
    "sg:province":"NSW",
    "sg:tags":[
        "footwear"
    ],
    "wof:name":"Payless Shoes Pty Limited",
    "wof:placetype":"venue"
},
  "geometry": {"coordinates":[151.26707458499999,-33.7689933777],"type":"Point"}
}