{
  "type": "Feature",
  "properties": {
    "addr:full":"RMB 571 Kojonup WA 6395",
    "addr:postcode":"6395",
    "iso:country":"AU",
    "sg:address":"RMB 571",
    "sg:city":"Kojonup",
    "sg:classifiers":[
        {
            "category":"Farming",
            "subcategory":"Farm",
            "type":"Manufacturing & Wholesale Goods"
        }
    ],
    "sg:phone":"+61 8 9832 8020",
    "sg:postcode":"6395",
    "sg:province":"WA",
    "sg:tags":[
        "farmer"
    ],
    "wof:name":"Mathwin Tim",
    "wof:placetype":"venue"
},
  "geometry": {"coordinates":[117.159866333,-33.8369293213],"type":"Point"}
}