{
  "type": "Feature",
  "properties": {
    "addr:full":"St Agnes Campus Evans Rd Rooty Hill NSW 2766",
    "addr:postcode":"2766",
    "addr:street":"Evans Rd",
    "iso:country":"AU",
    "sg:address":"St Agnes Campus Evans Rd",
    "sg:city":"Rooty Hill",
    "sg:classifiers":[
        {
            "category":"Education",
            "subcategory":"School",
            "type":"Public Place"
        }
    ],
    "sg:phone":"+61 2 9675 2422",
    "sg:postcode":"2766",
    "sg:province":"NSW",
    "sg:tags":[
        "co-educational"
    ],
    "wof:name":"Christ Catholic College St Annes Campus",
    "wof:placetype":"venue"
},
  "geometry": {"coordinates":[150.84605407699999,-33.7819404602],"type":"Point"}
}