{
  "type": "Feature",
  "properties": {
    "addr:full":"833 Frenchman Bay Rd Little Grove WA 6330",
    "addr:housenumber":"833",
    "addr:postcode":"6330",
    "addr:street":"Frenchman Bay Rd",
    "iso:country":"AU",
    "sg:address":"833 Frenchman Bay Rd",
    "sg:city":"Little Grove",
    "sg:classifiers":[
        {
            "category":"Building & Trades",
            "subcategory":"Construction",
            "type":"Services"
        }
    ],
    "sg:phone":"+61 8 9844 4075",
    "sg:postcode":"6330",
    "sg:province":"WA",
    "sg:tags":[
        "renovation",
        "alterations",
        "extension",
        "contractor"
    ],
    "wof:name":"King MD & DI",
    "wof:placetype":"venue"
},
  "geometry": {"coordinates":[117.862213135,-35.0684432983],"type":"Point"}
}