{
  "type": "Feature",
  "properties": {
    "addr:full":"Suite 605 253 Oxford St Bondi Junction NSW 2022",
    "addr:housenumber":"253",
    "addr:postcode":"2022",
    "addr:street":"Oxford St",
    "iso:country":"AU",
    "sg:address":"Suite 605 253 Oxford St",
    "sg:city":"Bondi Junction",
    "sg:classifiers":[
        {
            "category":"Health Services",
            "subcategory":"Dentist",
            "type":"Services"
        }
    ],
    "sg:phone":"+61 2 9369 2706",
    "sg:postcode":"2022",
    "sg:province":"NSW",
    "sg:tags":[
        "dental",
        "prosthetist"
    ],
    "wof:name":"Vajda Leslie",
    "wof:placetype":"venue"
},
  "geometry": {"coordinates":[151.252563477,-33.8913955688],"type":"Point"}
}