{
  "type": "Feature",
  "properties": {
    "addr:full":"192 Queen St St Marys NSW 2760",
    "addr:housenumber":"192",
    "addr:postcode":"2760",
    "addr:street":"Queen St",
    "iso:country":"AU",
    "sg:address":"192 Queen St",
    "sg:city":"St Marys",
    "sg:classifiers":[
        {
            "category":"Shopping",
            "subcategory":"Bicycles & Sporting Goods",
            "type":"Retail Goods"
        }
    ],
    "sg:phone":"+61 2 9673 1842",
    "sg:postcode":"2760",
    "sg:province":"NSW",
    "sg:tags":[
        "dance",
        "accessory",
        "wear",
        "supply"
    ],
    "wof:name":"Dancing Delight",
    "wof:placetype":"venue"
},
  "geometry": {"coordinates":[150.773925781,-33.7682151794],"type":"Point"}
}