{
  "type": "Feature",
  "properties": {
    "addr:full":"25 The Gully Rd Berowra NSW 2081",
    "addr:housenumber":"25",
    "addr:postcode":"2081",
    "addr:street":"The Gully Rd",
    "iso:country":"AU",
    "sg:address":"25 The Gully Rd",
    "sg:city":"Berowra",
    "sg:classifiers":[
        {
            "category":"Professional",
            "subcategory":"Secretarial Services",
            "type":"Services"
        }
    ],
    "sg:phone":"+61 2 9456 4448",
    "sg:postcode":"2081",
    "sg:province":"NSW",
    "sg:tags":[
        "typing"
    ],
    "wof:name":"Tudor Office Services",
    "wof:placetype":"venue"
},
  "geometry": {"coordinates":[151.15463256800001,-33.6186676025],"type":"Point"}
}