{
  "type": "Feature",
  "properties": {
    "iso:country":"AU",
    "sg:address":"Unit 10/ 56 Industrial Drv",
    "sg:city":"Mayfield",
    "sg:classifiers":[
        {
            "category":"Professional",
            "subcategory":"Testing Lab",
            "type":"Services"
        }
    ],
    "sg:phone":"+61 2 4960 8833",
    "sg:postcode":"2304",
    "sg:province":"NSW",
    "sg:tags":[
        "equipment"
    ],
    "wof:name":"Combustion Instrumentation Pty Ltd",
    "wof:placetype":"venue"
},
  "geometry": {"coordinates":[151.74206543,-32.891254425],"type":"Point"}
}