{
  "type": "Feature",
  "properties": {
    "addr:full":"65 Hobart St Mt Hawthorn WA 6016",
    "addr:housenumber":"65",
    "addr:postcode":"6016",
    "addr:street":"Hobart St Mt",
    "iso:country":"AU",
    "sg:address":"65 Hobart St",
    "sg:city":"Mt Hawthorn",
    "sg:classifiers":[
        {
            "category":"Building & Trades",
            "subcategory":"Plumbing",
            "type":"Services"
        }
    ],
    "sg:phone":"+61 1800 102 888",
    "sg:postcode":"6016",
    "sg:province":"WA",
    "sg:tags":[
        "plumber",
        "gasfitters"
    ],
    "wof:name":"A.AAA.ABA & AMP Plumbing, Gas & Hot Water",
    "wof:placetype":"venue"
},
  "geometry": {"coordinates":[115.84485626199999,-31.9221153259],"type":"Point"}
}