{
  "type": "Feature",
  "properties": {
    "addr:full":"1/ 193 Margaret St Orange NSW 2800",
    "addr:housenumber":"/ 193",
    "addr:postcode":"2800",
    "addr:street":"Margaret St",
    "iso:country":"AU",
    "sg:address":"1/ 193 Margaret St",
    "sg:city":"Orange",
    "sg:classifiers":[
        {
            "category":"Wholesale",
            "subcategory":"Farm Supplies",
            "type":"Manufacturing & Wholesale Goods"
        }
    ],
    "sg:phone":"+61 2 6362 3785",
    "sg:postcode":"2800",
    "sg:province":"NSW",
    "sg:tags":[
        "equipment"
    ],
    "wof:name":"Orange Farm Hardware Pty Ltd",
    "wof:placetype":"venue"
},
  "geometry": {"coordinates":[149.10783386200001,-33.2719688416],"type":"Point"}
}