{
  "type": "Feature",
  "properties": {
    "addr:full":"6c Robert St Atherton QLD 4883",
    "addr:housenumber":"6c",
    "addr:postcode":"4883",
    "addr:street":"Robert St",
    "iso:country":"AU",
    "sg:address":"6c Robert St",
    "sg:city":"Atherton",
    "sg:classifiers":[
        {
            "category":"Professional",
            "subcategory":"Accounting & Tax Preparation",
            "type":"Services"
        }
    ],
    "sg:phone":"+61 7 4091 3500",
    "sg:postcode":"4883",
    "sg:province":"QLD",
    "sg:tags":[
        "bookkeeping"
    ],
    "wof:name":"Tableland Secretarial Services",
    "wof:placetype":"venue"
},
  "geometry": {"coordinates":[145.47558593799999,-17.2683582306],"type":"Point"}
}