{
  "type": "Feature",
  "properties": {
    "iso:country":"AU",
    "sg:address":"15 Freighter Ave",
    "sg:city":"Toowoomba",
    "sg:classifiers":[
        {
            "category":"Building & Trades",
            "subcategory":"Construction",
            "type":"Services"
        }
    ],
    "sg:phone":"+61 7 4633 2511",
    "sg:postcode":"4350",
    "sg:province":"QLD",
    "sg:tags":[
        "window",
        "aluminium"
    ],
    "sg:website":"http://www.scopeonline.com.au",
    "wof:name":"Scope Doors & Windows",
    "wof:placetype":"venue"
},
  "geometry": {"coordinates":[151.908905,-27.538492],"type":"Point"}
}