{
  "type": "Feature",
  "properties": {
    "iso:country":"AU",
    "sg:address":"10 Lorna St",
    "sg:city":"Pelican",
    "sg:classifiers":[
        {
            "category":"Utilities",
            "type":"Services"
        }
    ],
    "sg:phone":"+61 1800 028 968",
    "sg:postcode":"2281",
    "sg:province":"NSW",
    "sg:tags":[
        "refrigeration",
        "industrial",
        "commercial",
        "retail"
    ],
    "wof:name":"Coolroom Cleaning Service",
    "wof:placetype":"venue"
},
  "geometry": {"coordinates":[151.643234253,-33.0690727234],"type":"Point"}
}