{
  "type": "Feature",
  "properties": {
    "iso:country":"AU",
    "sg:address":"PO Box 4195",
    "sg:city":"Richmond East",
    "sg:classifiers":[
        {
            "category":"Professional",
            "subcategory":"Detective & Security Services",
            "type":"Services"
        }
    ],
    "sg:phone":"+61 411 555 551",
    "sg:postcode":"3121",
    "sg:province":"VIC",
    "sg:tags":[
        "investigator"
    ],
    "wof:name":"Strict Security",
    "wof:placetype":"venue"
},
  "geometry": {"coordinates":[145.00813293499999,-37.8220596313],"type":"Point"}
}