{
  "type": "Feature",
  "properties": {
    "addr:full":"2/ 10 Rodborough Rd Frenchs Forest NSW 2086",
    "addr:housenumber":"/ 10",
    "addr:postcode":"2086",
    "addr:street":"Rodborough Rd",
    "iso:country":"AU",
    "sg:address":"2/ 10 Rodborough Rd",
    "sg:city":"Frenchs Forest",
    "sg:classifiers":[
        {
            "category":"Shopping",
            "subcategory":"Baby Store",
            "type":"Retail Goods"
        }
    ],
    "sg:phone":"+61 2 9935 2107",
    "sg:postcode":"2086",
    "sg:province":"NSW",
    "sg:tags":[
        "children's",
        "wear"
    ],
    "wof:name":"Pumpkin Patch",
    "wof:placetype":"venue"
},
  "geometry": {"coordinates":[151.24407959000001,-33.7535209656],"type":"Point"}
}