{
  "type": "Feature",
  "properties": {
    "addr:full":"PO Box 677 Maroochydore QLD 4558",
    "addr:postcode":"4558",
    "iso:country":"AU",
    "sg:address":"PO Box 677",
    "sg:city":"Maroochydore",
    "sg:classifiers":[
        {
            "category":"Real Estate",
            "subcategory":"Surveying",
            "type":"Services"
        }
    ],
    "sg:phone":"+61 7 5443 4265",
    "sg:postcode":"4558",
    "sg:province":"QLD",
    "sg:tags":[
        "surveyor",
        "quantity"
    ],
    "wof:name":"Graham Lukins Partnership Pty Ltd",
    "wof:placetype":"venue"
},
  "geometry": {"coordinates":[153.06553649899999,-26.6553192139],"type":"Point"}
}