{
  "type": "Feature",
  "properties": {
    "iso:country":"AU",
    "sg:address":"Carawatha Drv",
    "sg:city":"Mypolonga",
    "sg:classifiers":[
        {
            "category":"Parking",
            "subcategory":"Lot",
            "type":"Transportation"
        }
    ],
    "sg:phone":"+61 8 8535 4011",
    "sg:postcode":"5254",
    "sg:province":"SA",
    "sg:tags":[
        "vegetable",
        "packing",
        "fruit",
        "pack"
    ],
    "wof:name":"Luscious Orchards Pty Ltd",
    "wof:placetype":"venue"
},
  "geometry": {"coordinates":[139.33505249000001,-35.029258728],"type":"Point"}
}