{
  "type": "Feature",
  "properties": {
    "iso:country":"AU",
    "sg:address":"10 Dean St",
    "sg:city":"Tamworth",
    "sg:classifiers":[
        {
            "category":"Health Services",
            "subcategory":"Doctor",
            "type":"Services"
        }
    ],
    "sg:phone":"+61 2 6766 9970",
    "sg:postcode":"2340",
    "sg:province":"NSW",
    "sg:tags":[
        "occupational",
        "safety"
    ],
    "wof:name":"Moore Options",
    "wof:placetype":"venue"
},
  "geometry": {"coordinates":[150.92251586899999,-31.0768032074],"type":"Point"}
}