{
  "type": "Feature",
  "properties": {
    "addr:full":"Shp1/ 138 Main Rd McLaren Vale SA 5171",
    "addr:housenumber":"138",
    "addr:postcode":"5171",
    "addr:street":"Main Rd",
    "iso:country":"AU",
    "sg:address":"Shp1/ 138 Main Rd",
    "sg:city":"McLaren Vale",
    "sg:classifiers":[
        {
            "category":"Food & Beverages",
            "subcategory":"Meat & Fish",
            "type":"Retail Goods"
        }
    ],
    "sg:phone":"+61 8 8323 9133",
    "sg:postcode":"5171",
    "sg:province":"SA",
    "sg:tags":[
        "seafood"
    ],
    "wof:name":"McLaren Vale Seafoods",
    "wof:placetype":"venue"
},
  "geometry": {"coordinates":[138.53724670400001,-35.2150382996],"type":"Point"}
}