{
  "type": "Feature",
  "properties": {
    "addr:full":"Level 2, 36 Victoria St Burwood NSW 2134",
    "addr:housenumber":"36",
    "addr:postcode":"2134",
    "addr:street":"Victoria St",
    "iso:country":"AU",
    "sg:address":"Level 2, 36 Victoria St",
    "sg:city":"Burwood",
    "sg:classifiers":[
        {
            "category":"Insurance",
            "subcategory":"Insurance Agent",
            "type":"Services"
        }
    ],
    "sg:phone":"+61 2 9744 0400",
    "sg:postcode":"2134",
    "sg:province":"NSW",
    "sg:tags":[
        "broker"
    ],
    "wof:name":"OAMPS Insurance Brokers Ltd",
    "wof:placetype":"venue"
},
  "geometry": {"coordinates":[151.106002808,-33.8753089905],"type":"Point"}
}