{
  "type": "Feature",
  "properties": {
    "addr:full":"7 Mason St Ferntree Gully VIC 3156",
    "addr:housenumber":"7",
    "addr:postcode":"3156",
    "addr:street":"Mason St",
    "iso:country":"AU",
    "sg:address":"7 Mason St",
    "sg:city":"Ferntree Gully",
    "sg:classifiers":[
        {
            "category":"Personal",
            "subcategory":"Massage",
            "type":"Services"
        }
    ],
    "sg:phone":"+61 3 9758 2264",
    "sg:postcode":"3156",
    "sg:province":"VIC",
    "sg:tags":[
        "therapy"
    ],
    "wof:name":"Angelo Mazzone",
    "wof:placetype":"venue"
},
  "geometry": {"coordinates":[145.29437255900001,-37.8953170776],"type":"Point"}
}