{
  "type": "Feature",
  "properties": {
    "iso:country":"AU",
    "sg:address":"14 Speed St",
    "sg:city":"Cooee",
    "sg:classifiers":[
        {
            "category":"Professional",
            "subcategory":"Computer Services",
            "type":"Services"
        }
    ],
    "sg:phone":"+61 3 6432 3681",
    "sg:postcode":"7320",
    "sg:province":"TAS",
    "sg:tags":[
        "repairs",
        "upgrade",
        "equipment"
    ],
    "wof:name":"GAFS Mobile Computer Services",
    "wof:placetype":"venue"
},
  "geometry": {"coordinates":[145.876495,-41.0424],"type":"Point"}
}