{
  "type": "Feature",
  "properties": {
    "addr:full":"142 Nebo Rd Mackay QLD 4740",
    "addr:housenumber":"142",
    "addr:postcode":"4740",
    "addr:street":"Nebo Rd",
    "iso:country":"AU",
    "sg:address":"142 Nebo Rd",
    "sg:city":"Mackay",
    "sg:classifiers":[
        {
            "category":"Professional",
            "subcategory":"Employment Agencies",
            "type":"Services"
        }
    ],
    "sg:phone":"+61 7 4957 4766",
    "sg:postcode":"4740",
    "sg:province":"QLD",
    "sg:tags":[
        "hire",
        "labour",
        "contractor"
    ],
    "sg:website":"http://www.extremegroup.com.au",
    "wof:name":"Extreme Workforce & Employment",
    "wof:placetype":"venue"
},
  "geometry": {"coordinates":[149.166245,-21.153816],"type":"Point"}
}