{
  "type": "Feature",
  "properties": {
    "addr:full":"25 Belina Ave Wyoming NSW 2250",
    "addr:housenumber":"25",
    "addr:postcode":"2250",
    "addr:street":"Belina Ave",
    "iso:country":"AU",
    "sg:address":"25 Belina Ave",
    "sg:city":"Wyoming",
    "sg:classifiers":[
        {
            "category":"Commercial Area",
            "type":"Public Place"
        }
    ],
    "sg:phone":"+61 419 988 536",
    "sg:postcode":"2250",
    "sg:province":"NSW",
    "sg:tags":[
        "heavy",
        "carrier"
    ],
    "wof:name":"Terrigal Taxi Trucks",
    "wof:placetype":"venue"
},
  "geometry": {"coordinates":[151.362823486,-33.395740509],"type":"Point"}
}