{
  "type": "Feature",
  "properties": {
    "addr:full":"107 Lake Bunga Beach Rd Lakes Entrance VIC 3909",
    "addr:housenumber":"107",
    "addr:postcode":"3909",
    "addr:street":"Lake Bunga Beach Rd Lakes",
    "iso:country":"AU",
    "sg:address":"107 Lake Bunga Beach Rd",
    "sg:city":"Lakes Entrance",
    "sg:classifiers":[
        {
            "category":"Retail",
            "subcategory":"Repair Shop",
            "type":"Services"
        }
    ],
    "sg:phone":"+61 3 5155 1759",
    "sg:postcode":"3909",
    "sg:province":"VIC",
    "sg:tags":[
        "machine",
        "repairs",
        "part",
        "dryer",
        "washing"
    ],
    "wof:name":"Lakes Washing Machine Service",
    "wof:placetype":"venue"
},
  "geometry": {"coordinates":[148.03941345199999,-37.8647346497],"type":"Point"}
}