{
  "type": "Feature",
  "properties": {
    "addr:full":"34 Munro St Babinda QLD 4861",
    "addr:housenumber":"34",
    "addr:postcode":"4861",
    "addr:street":"Munro St",
    "iso:country":"AU",
    "sg:address":"34 Munro St",
    "sg:city":"Babinda",
    "sg:classifiers":[
        {
            "category":"Wholesale",
            "subcategory":"Machinery & Supplies",
            "type":"Manufacturing & Wholesale Goods"
        }
    ],
    "sg:phone":"+61 7 4067 1315",
    "sg:postcode":"4861",
    "sg:province":"QLD",
    "sg:tags":[
        "equipment",
        "hydraulic"
    ],
    "wof:name":"Babinda Automotive Pty Ltd",
    "wof:placetype":"venue"
},
  "geometry": {"coordinates":[145.922042847,-17.3438777924],"type":"Point"}
}