{
  "type": "Feature",
  "properties": {
    "addr:full":"Ste3/ 10 Prospect Hill Rd Camberwell VIC 3124",
    "addr:housenumber":"10",
    "addr:postcode":"3124",
    "addr:street":"Prospect Hill Rd",
    "iso:country":"AU",
    "sg:address":"Ste3/ 10 Prospect Hill Rd",
    "sg:city":"Camberwell",
    "sg:classifiers":[
        {
            "category":"Professional",
            "subcategory":"Management & Consulting",
            "type":"Services"
        }
    ],
    "sg:phone":"+61 3 9813 0161",
    "sg:postcode":"3124",
    "sg:province":"VIC",
    "sg:tags":[
        "consultant"
    ],
    "wof:name":"Management Group Australia Pty Ltd",
    "wof:placetype":"venue"
},
  "geometry": {"coordinates":[145.05848693900001,-37.8284111023],"type":"Point"}
}