{
  "type": "Feature",
  "properties": {
    "addr:full":"Unit 1, 461- 463 The Boulevarde Kirrawee NSW 2232",
    "addr:housenumber":"461 463",
    "addr:postcode":"2232",
    "addr:street":"The Boulevarde",
    "iso:country":"AU",
    "sg:address":"Unit 1, 461- 463 The Boulevarde",
    "sg:city":"Kirrawee",
    "sg:classifiers":[
        {
            "category":"Utilities",
            "subcategory":"Sewage",
            "type":"Services"
        }
    ],
    "sg:phone":"+61 2 9545 2811",
    "sg:postcode":"2232",
    "sg:province":"NSW",
    "sg:tags":[
        "water",
        "waste",
        "treatment"
    ],
    "wof:name":"Facet Plate Separators",
    "wof:placetype":"venue"
},
  "geometry": {"coordinates":[151.07110595699999,-34.0342292786],"type":"Point"}
}