{
  "type": "Feature",
  "properties": {
    "iso:country":"AU",
    "sg:address":"10 Cameron Pde",
    "sg:city":"Broadford",
    "sg:classifiers":[
        {
            "category":"Autos & Motor Vehicles",
            "subcategory":"Automobile Sales",
            "type":"Retail Goods"
        }
    ],
    "sg:phone":"+61 3 5784 2360",
    "sg:postcode":"3658",
    "sg:province":"VIC",
    "sg:tags":[
        "car",
        "used"
    ],
    "wof:name":"Broadford Car Sales",
    "wof:placetype":"venue"
},
  "geometry": {"coordinates":[145.059524536,-37.2100448608],"type":"Point"}
}