{
  "type": "Feature",
  "properties": {
    "iso:country":"AU",
    "sg:address":"20 Ensign Ave",
    "sg:city":"Annerley",
    "sg:classifiers":[
        {
            "category":"Home & Garden",
            "subcategory":"Kitchen Supply",
            "type":"Retail Goods"
        }
    ],
    "sg:phone":"+61 7 3891 3555",
    "sg:postcode":"4103",
    "sg:province":"QLD",
    "sg:tags":[
        "vegetable",
        "fruit",
        "grain",
        "exporter"
    ],
    "wof:name":"Grainex International Pty Ltd",
    "wof:placetype":"venue"
},
  "geometry": {"coordinates":[153.02932739299999,-27.505865097],"type":"Point"}
}