{
  "type": "Feature",
  "properties": {
    "addr:full":"10 Finnerty St Karrinyup WA 6018",
    "addr:housenumber":"10",
    "addr:postcode":"6018",
    "addr:street":"Finnerty St",
    "iso:country":"AU",
    "sg:address":"10 Finnerty St",
    "sg:city":"Karrinyup",
    "sg:classifiers":[
        {
            "category":"Building & Trades",
            "subcategory":"Construction",
            "type":"Services"
        }
    ],
    "sg:phone":"+61 419 959 188",
    "sg:postcode":"6018",
    "sg:province":"WA",
    "sg:tags":[
        "contractor"
    ],
    "wof:name":"Alinga Building Pty Ltd",
    "wof:placetype":"venue"
},
  "geometry": {"coordinates":[115.786880493,-31.8712749481],"type":"Point"}
}