{
  "type": "Feature",
  "properties": {
    "addr:full":"202 Glebe Rd Merewether NSW 2291",
    "addr:housenumber":"202",
    "addr:postcode":"2291",
    "addr:street":"Glebe Rd",
    "iso:country":"AU",
    "sg:address":"202 Glebe Rd",
    "sg:city":"Merewether",
    "sg:classifiers":[
        {
            "category":"Health Services",
            "subcategory":"Dentist",
            "type":"Services"
        }
    ],
    "sg:phone":"+61 2 4961 6300",
    "sg:postcode":"2291",
    "sg:province":"NSW",
    "wof:name":"Reed Maria Dr",
    "wof:placetype":"venue"
},
  "geometry": {"coordinates":[151.75094604500001,-32.9379577637],"type":"Point"}
}