{
  "type": "Feature",
  "properties": {
    "addr:full":"Shop 132, Lake Haven Shopping Cntr Goobarabah Ave Lake Haven NSW 2263",
    "addr:housenumber":"132",
    "addr:postcode":"2263",
    "addr:street":"Lake Haven;Ave Lake",
    "iso:country":"AU",
    "sg:address":"Shop 132, Lake Haven Shopping Cntr Goobarabah Ave",
    "sg:city":"Lake Haven",
    "sg:classifiers":[
        {
            "category":"Banks & Credit Unions",
            "subcategory":"Financial Services",
            "type":"Services"
        }
    ],
    "sg:phone":"+61 2 4393 3494",
    "sg:postcode":"2263",
    "sg:province":"NSW",
    "sg:tags":[
        "loan",
        "finance",
        "mortgage"
    ],
    "wof:name":"RAMS Home Loans",
    "wof:placetype":"venue"
},
  "geometry": {"coordinates":[151.50245699999999,-33.243011],"type":"Point"}
}