{
  "type": "Feature",
  "properties": {
    "addr:full":"366 Scarborough Beach Rd Osborne Park WA 6017",
    "addr:housenumber":"366",
    "addr:postcode":"6017",
    "addr:street":"Scarborough Beach Rd",
    "iso:country":"AU",
    "sg:address":"366 Scarborough Beach Rd",
    "sg:city":"Osborne Park",
    "sg:classifiers":[
        {
            "category":"Building & Trades",
            "subcategory":"Construction",
            "type":"Services"
        }
    ],
    "sg:phone":"+61 8 9201 0500",
    "sg:postcode":"6017",
    "sg:province":"WA",
    "sg:tags":[
        "contractor"
    ],
    "wof:name":"Ross Griffin Quality Homes",
    "wof:placetype":"venue"
},
  "geometry": {"coordinates":[115.80783081,-31.905172348],"type":"Point"}
}