{
  "type": "Feature",
  "properties": {
    "addr:full":"200 Beavers Rd Northcote VIC 3070",
    "addr:housenumber":"200",
    "addr:postcode":"3070",
    "addr:street":"Beavers Rd",
    "iso:country":"AU",
    "sg:address":"200 Beavers Rd",
    "sg:city":"Northcote",
    "sg:classifiers":[
        {
            "category":"Wholesale",
            "subcategory":"Music Publishers",
            "type":"Manufacturing & Wholesale Goods"
        }
    ],
    "sg:phone":"+61 3 9014 0200",
    "sg:postcode":"3070",
    "sg:province":"VIC",
    "sg:tags":[
        "wholesaler",
        "dvd",
        "mfrs",
        "cd"
    ],
    "wof:name":"Shock Records Pty Ltd",
    "wof:placetype":"venue"
},
  "geometry": {"coordinates":[144.985016,-37.765003],"type":"Point"}
}