{
  "type": "Feature",
  "properties": {
    "addr:full":"96 Beerburrum St Caloundra QLD 4551",
    "addr:housenumber":"96",
    "addr:postcode":"4551",
    "addr:street":"Beerburrum St",
    "iso:country":"AU",
    "sg:address":"96 Beerburrum St",
    "sg:city":"Caloundra",
    "sg:classifiers":[
        {
            "category":"Health Services",
            "subcategory":"Doctor",
            "type":"Services"
        }
    ],
    "sg:phone":"+61 7 5492 0280",
    "sg:postcode":"4551",
    "sg:province":"QLD",
    "sg:tags":[
        "medical",
        "practitioner"
    ],
    "wof:name":"Lane Daniel",
    "wof:placetype":"venue"
},
  "geometry": {"coordinates":[153.126586914,-26.7818336487],"type":"Point"}
}