{
  "type": "Feature",
  "properties": {
    "addr:full":"Bavin Rd Broadmeadow NSW 2292",
    "addr:postcode":"2292",
    "addr:street":"Bavin Rd",
    "iso:country":"AU",
    "sg:address":"Bavin Rd",
    "sg:city":"Broadmeadow",
    "sg:classifiers":[
        {
            "category":"Airport",
            "subcategory":"General Aviation",
            "type":"Transportation"
        }
    ],
    "sg:phone":"+61 2 4952 0000",
    "sg:postcode":"2292",
    "sg:province":"NSW",
    "sg:tags":[
        "helicopter"
    ],
    "wof:name":"Hunter Region S.L.S.A. Helicopter Rescue Service Ltd",
    "wof:placetype":"venue"
},
  "geometry": {"coordinates":[151.72909545900001,-32.9235076904],"type":"Point"}
}