{
  "type": "Feature",
  "properties": {
    "iso:country":"AU",
    "sg:address":"Newton Village/ 60- 64 Gorge Rd",
    "sg:city":"Newton",
    "sg:classifiers":[
        {
            "category":"Manufacturing",
            "subcategory":"Jewelry",
            "type":"Manufacturing & Wholesale Goods"
        }
    ],
    "sg:phone":"+61 8 8365 1577",
    "sg:postcode":"5074",
    "sg:province":"SA",
    "sg:tags":[
        "designer",
        "jewellery"
    ],
    "wof:name":"Polgold Jewellery",
    "wof:placetype":"venue"
},
  "geometry": {"coordinates":[138.672042847,-34.8765487671],"type":"Point"}
}