{
  "type": "Feature",
  "properties": {
    "addr:full":"231 Up Heidelberg Rd Ivanhoe VIC 3079",
    "addr:housenumber":"231",
    "addr:postcode":"3079",
    "addr:street":"Up Heidelberg Rd",
    "iso:country":"AU",
    "sg:address":"231 Up Heidelberg Rd",
    "sg:city":"Ivanhoe",
    "sg:classifiers":[
        {
            "category":"Shopping",
            "subcategory":"Antiques",
            "type":"Retail Goods"
        }
    ],
    "sg:phone":"+61 3 9497 1935",
    "sg:postcode":"3079",
    "sg:province":"VIC",
    "wof:name":"Ivanhoe Antiques Collectibles Corner",
    "wof:placetype":"venue"
},
  "geometry": {"coordinates":[145.04066467300001,-37.7727622986],"type":"Point"}
}