{
  "type": "Feature",
  "properties": {
    "addr:full":"74 Main St Brinkworth SA 5464",
    "addr:housenumber":"74",
    "addr:postcode":"5464",
    "addr:street":"Main St",
    "iso:country":"AU",
    "sg:address":"74 Main St",
    "sg:city":"Brinkworth",
    "sg:classifiers":[
        {
            "category":"Travel",
            "subcategory":"Hotels & Motels",
            "type":"Entertainment"
        }
    ],
    "sg:phone":"+61 8 8846 2152",
    "sg:postcode":"5464",
    "sg:province":"SA",
    "sg:tags":[
        "accommodation"
    ],
    "wof:name":"Junction Hotel",
    "wof:placetype":"venue"
},
  "geometry": {"coordinates":[138.403564453,-33.6916618347],"type":"Point"}
}