{
  "type": "Feature",
  "properties": {
    "addr:full":"Shop 3 / 188 The Entrance Rd Erina NSW 2250",
    "addr:housenumber":"shop 3 / 188",
    "addr:postcode":"2250",
    "addr:street":"The Entrance Rd",
    "iso:country":"AU",
    "sg:address":"Shop 3 / 188 The Entrance Rd",
    "sg:city":"Erina",
    "sg:classifiers":[
        {
            "category":"Home & Garden",
            "subcategory":"Carpets & Floor Coverings",
            "type":"Retail Goods"
        }
    ],
    "sg:phone":"+61 2 4367 7329",
    "sg:postcode":"2250",
    "sg:province":"NSW",
    "wof:name":"Carpet Choice",
    "wof:placetype":"venue"
},
  "geometry": {"coordinates":[151.385375977,-33.4359664917],"type":"Point"}
}