{
  "type": "Feature",
  "properties": {
    "addr:full":"Shop 2, 10 South St Wodonga VIC 3690",
    "addr:housenumber":"shop;10",
    "addr:postcode":"3690",
    "addr:street":"South St",
    "iso:country":"AU",
    "sg:address":"Shop 2, 10 South St",
    "sg:city":"Wodonga",
    "sg:classifiers":[
        {
            "category":"Shopping",
            "subcategory":"Computers & Home Electronics",
            "type":"Retail Goods"
        }
    ],
    "sg:phone":"+61 2 6056 5746",
    "sg:postcode":"3690",
    "sg:province":"VIC",
    "sg:tags":[
        "equipment",
        "part",
        "electronic"
    ],
    "wof:name":"Exact Computers & Home Entertainment",
    "wof:placetype":"venue"
},
  "geometry": {"coordinates":[146.89077758799999,-36.1191902161],"type":"Point"}
}