{
  "type": "Feature",
  "properties": {
    "iso:country":"AU",
    "sg:address":"139 Fitzgerald St",
    "sg:city":"Geraldton",
    "sg:classifiers":[
        {
            "category":"Health Services",
            "subcategory":"Dentist",
            "type":"Services"
        }
    ],
    "sg:phone":"+61 8 9921 4795",
    "sg:postcode":"6530",
    "sg:province":"WA",
    "wof:name":"Thompson Barry Dr",
    "wof:placetype":"venue"
},
  "geometry": {"coordinates":[114.60774231000001,-28.7829036713],"type":"Point"}
}