{
  "type": "Feature",
  "properties": {
    "addr:full":"Shop 4, 128 South St Ulladulla NSW 2539",
    "addr:housenumber":"shop 4 128",
    "addr:postcode":"2539",
    "addr:street":"South St",
    "iso:country":"AU",
    "sg:address":"Shop 4, 128 South St",
    "sg:city":"Ulladulla",
    "sg:classifiers":[
        {
            "category":"Fast Food",
            "type":"Food & Drink"
        }
    ],
    "sg:phone":"+61 2 4455 1943",
    "sg:postcode":"2539",
    "sg:province":"NSW",
    "sg:tags":[
        "away",
        "take"
    ],
    "wof:name":"Ulladulla Chinese Restaurant",
    "wof:placetype":"venue"
},
  "geometry": {"coordinates":[150.478439331,-35.3610992432],"type":"Point"}
}