{
  "type": "Feature",
  "properties": {
    "addr:full":"215 Place Rd Geraldton WA 6530",
    "addr:housenumber":"215",
    "addr:postcode":"6530",
    "addr:street":"Place Rd",
    "iso:country":"AU",
    "sg:address":"215 Place Rd",
    "sg:city":"Geraldton",
    "sg:classifiers":[
        {
            "category":"Wholesale",
            "subcategory":"Painting Supplies",
            "type":"Manufacturing & Wholesale Goods"
        }
    ],
    "sg:phone":"+61 8 9964 2167",
    "sg:postcode":"6530",
    "sg:province":"WA",
    "sg:tags":[
        "product",
        "cleaning"
    ],
    "wof:name":"Midwest Chemical & Paper Distributors",
    "wof:placetype":"venue"
},
  "geometry": {"coordinates":[114.626861572,-28.7590637207],"type":"Point"}
}