{
  "type": "Feature",
  "properties": {
    "iso:country":"AU",
    "sg:address":"Unit 26/ 175 Cathedral St",
    "sg:city":"Woolloomooloo",
    "sg:classifiers":[
        {
            "category":"Professional",
            "subcategory":"Detective & Security Services",
            "type":"Services"
        }
    ],
    "sg:phone":"+61 2 9356 2455",
    "sg:postcode":"2011",
    "sg:province":"NSW",
    "sg:tags":[
        "consultant",
        "system"
    ],
    "wof:name":"GPS Security",
    "wof:placetype":"venue"
},
  "geometry": {"coordinates":[151.22001648,-33.8730125427],"type":"Point"}
}