{
  "type": "Feature",
  "properties": {
    "iso:country":"AU",
    "sg:address":"328 Cowlong Rd",
    "sg:city":"McLeans Ridges",
    "sg:classifiers":[
        {
            "category":"Farming",
            "subcategory":"Nursery",
            "type":"Manufacturing & Wholesale Goods"
        }
    ],
    "sg:phone":"+61 2 6628 1289",
    "sg:postcode":"2480",
    "sg:province":"NSW",
    "wof:name":"Pearce's Nurseries",
    "wof:placetype":"venue"
},
  "geometry": {"coordinates":[153.393844605,-28.791633606],"type":"Point"}
}