{
  "type": "Feature",
  "properties": {
    "addr:full":"Sydney St Mackay QLD 4740",
    "addr:postcode":"4740",
    "addr:street":"Sydney St",
    "iso:country":"AU",
    "sg:address":"Sydney St",
    "sg:city":"Mackay",
    "sg:classifiers":[
        {
            "category":"Shopping",
            "type":"Retail Goods"
        }
    ],
    "sg:phone":"+61 7 4957 2343",
    "sg:postcode":"4740",
    "sg:province":"QLD",
    "sg:tags":[
        "supply",
        "religious",
        "church"
    ],
    "wof:name":"Christian Reformed Bookshop",
    "wof:placetype":"venue"
},
  "geometry": {"coordinates":[149.185608,-21.1514],"type":"Point"}
}