{
  "type": "Feature",
  "properties": {
    "addr:full":"Shp3/ 50 Maple St Maleny QLD 4552",
    "addr:housenumber":"50",
    "addr:postcode":"4552",
    "addr:street":"Maple St",
    "iso:country":"AU",
    "sg:address":"Shp3/ 50 Maple St",
    "sg:city":"Maleny",
    "sg:classifiers":[
        {
            "category":"Shopping",
            "subcategory":"Shoes",
            "type":"Retail Goods"
        }
    ],
    "sg:phone":"+61 7 5499 9622",
    "sg:postcode":"4552",
    "sg:province":"QLD",
    "sg:tags":[
        "footwear"
    ],
    "wof:name":"Imelda's On Maple",
    "wof:placetype":"venue"
},
  "geometry": {"coordinates":[152.84909057600001,-26.7579441071],"type":"Point"}
}