{
  "type": "Feature",
  "properties": {
    "addr:full":"Cnr Ipswich Rd & Douglas St Oxley QLD 4075",
    "addr:postcode":"4075",
    "addr:street":"Ipswich Rd & Douglas St",
    "iso:country":"AU",
    "sg:address":"Cnr Ipswich Rd & Douglas St",
    "sg:city":"Oxley",
    "sg:classifiers":[
        {
            "category":"Manufacturing",
            "subcategory":"Tools & Machinery",
            "type":"Manufacturing & Wholesale Goods"
        }
    ],
    "sg:phone":"+61 7 3375 3555",
    "sg:postcode":"4075",
    "sg:province":"QLD",
    "sg:tags":[
        "earth",
        "excavating",
        "moving",
        "equipment"
    ],
    "wof:name":"Oxley Plant Sales Pty Ltd",
    "wof:placetype":"venue"
},
  "geometry": {"coordinates":[152.97508239699999,-27.5669803619],"type":"Point"}
}