{
  "type": "Feature",
  "properties": {
    "iso:country":"AU",
    "sg:address":"135 Riverview St",
    "sg:city":"Riverview",
    "sg:classifiers":[
        {
            "category":"Building & Trades",
            "subcategory":"Landscaping Services",
            "type":"Services"
        }
    ],
    "sg:phone":"+61 2 9418 9257",
    "sg:postcode":"2066",
    "sg:province":"NSW",
    "sg:tags":[
        "consultant"
    ],
    "wof:name":"G.L. Zakos & Associates Pty Ltd",
    "wof:placetype":"venue"
},
  "geometry": {"coordinates":[151.15620422399999,-33.8205375671],"type":"Point"}
}