{
  "type": "Feature",
  "properties": {
    "iso:country":"AU",
    "sg:address":"70 Commercial Pl",
    "sg:city":"Eltham",
    "sg:classifiers":[
        {
            "category":"Professional",
            "subcategory":"Accounting & Tax Preparation",
            "type":"Services"
        }
    ],
    "sg:phone":"+61 3 9431 4482",
    "sg:postcode":"3095",
    "sg:province":"VIC",
    "sg:tags":[
        "consultant",
        "taxation"
    ],
    "wof:name":"H & R Block",
    "wof:placetype":"venue"
},
  "geometry": {"coordinates":[145.14941406200001,-37.7125205994],"type":"Point"}
}