{
  "type": "Feature",
  "properties": {
    "addr:full":"K6 Level 2 Westpoint Shopping Centre Blacktown NSW 2148",
    "addr:postcode":"2148",
    "iso:country":"AU",
    "sg:address":"K6 Level 2 Westpoint Shopping Centre",
    "sg:city":"Blacktown",
    "sg:classifiers":[
        {
            "category":"Cafe",
            "type":"Food & Drink"
        }
    ],
    "sg:phone":"+61 2 9671 2018",
    "sg:postcode":"2148",
    "sg:province":"NSW",
    "wof:name":"Nadia's Cafe",
    "wof:placetype":"venue"
},
  "geometry": {"coordinates":[150.90814209000001,-33.7725982666],"type":"Point"}
}