{
  "type": "Feature",
  "properties": {
    "addr:full":"16 Pavitt Crs Wyong NSW 2259",
    "addr:housenumber":"16",
    "addr:postcode":"2259",
    "addr:street":"Pavitt Crs",
    "iso:country":"AU",
    "sg:address":"16 Pavitt Crs",
    "sg:city":"Wyong",
    "sg:classifiers":[
        {
            "category":"Home & Garden",
            "subcategory":"Building Materials",
            "type":"Retail Goods"
        }
    ],
    "sg:phone":"+61 2 4353 0036",
    "sg:postcode":"2259",
    "sg:province":"NSW",
    "sg:tags":[
        "retaining",
        "wall"
    ],
    "wof:name":"Stone Masonry (NSW) Pty Ltd",
    "wof:placetype":"venue"
},
  "geometry": {"coordinates":[151.42552185100001,-33.2829093933],"type":"Point"}
}