{
  "type": "Feature",
  "properties": {
    "addr:full":"15 Beechmount Ave Hazelbrook NSW 2779",
    "addr:housenumber":"15",
    "addr:postcode":"2779",
    "addr:street":"Beechmount Ave",
    "iso:country":"AU",
    "sg:address":"15 Beechmount Ave",
    "sg:city":"Hazelbrook",
    "sg:classifiers":[
        {
            "category":"Building & Trades",
            "subcategory":"Construction",
            "type":"Services"
        }
    ],
    "sg:phone":"+61 415 400 119",
    "sg:postcode":"2779",
    "sg:province":"NSW",
    "sg:tags":[
        "contractor"
    ],
    "wof:name":"Dynamic Home Improvements",
    "wof:placetype":"venue"
},
  "geometry": {"coordinates":[150.45848083499999,-33.7253608704],"type":"Point"}
}