{
  "type": "Feature",
  "properties": {
    "addr:full":"Fcty1/ 16 Sir Laurence Drv Seaford VIC 3198",
    "addr:housenumber":"16",
    "addr:postcode":"3198",
    "addr:street":"Sir Laurence Drv",
    "iso:country":"AU",
    "sg:address":"Fcty1/ 16 Sir Laurence Drv",
    "sg:city":"Seaford",
    "sg:phone":"+61 3 9773 5744",
    "sg:postcode":"3198",
    "sg:province":"VIC",
    "wof:name":"Melbourne Rotomould",
    "wof:placetype":"venue"
},
  "geometry": {"coordinates":[145.143875122,-38.1156692505],"type":"Point"}
}