{
  "type": "Feature",
  "properties": {
    "addr:full":"3 Oak Pl Mt Pritchard NSW 2170",
    "addr:housenumber":"3",
    "addr:postcode":"2170",
    "addr:street":"Oak Pl;Pritchard",
    "iso:country":"AU",
    "sg:address":"3 Oak Pl",
    "sg:city":"Mt Pritchard",
    "sg:classifiers":[
        {
            "category":"Professional",
            "subcategory":"Engineering",
            "type":"Services"
        }
    ],
    "sg:phone":"+61 2 8786 0656",
    "sg:postcode":"2170",
    "sg:province":"NSW",
    "sg:tags":[
        "engineer"
    ],
    "wof:name":"Spot On Rebores",
    "wof:placetype":"venue"
},
  "geometry": {"coordinates":[150.897338867,-33.9015388489],"type":"Point"}
}