{
  "type": "Feature",
  "properties": {
    "iso:country":"AU",
    "sg:address":"185 Main South Rd",
    "sg:city":"Morphett Vale",
    "sg:classifiers":[
        {
            "category":"Professional",
            "subcategory":"Accounting & Tax Preparation",
            "type":"Services"
        }
    ],
    "sg:phone":"+61 8 8326 7222",
    "sg:postcode":"5162",
    "sg:province":"SA",
    "sg:tags":[
        "consultant",
        "taxation"
    ],
    "wof:name":"ITP Income Tax Professionals",
    "wof:placetype":"venue"
},
  "geometry": {"coordinates":[138.52288818400001,-35.1199874878],"type":"Point"}
}