{
  "type": "Feature",
  "properties": {
    "addr:full":"265 Castlereagh St Sydney NSW 2000",
    "addr:housenumber":"265",
    "addr:postcode":"2000",
    "addr:street":"Castlereagh St",
    "iso:country":"AU",
    "sg:address":"265 Castlereagh St",
    "sg:city":"Sydney",
    "sg:classifiers":[
        {
            "category":"Professional",
            "subcategory":"Management & Consulting",
            "type":"Services"
        }
    ],
    "sg:phone":"+61 2 9267 2224",
    "sg:postcode":"2000",
    "sg:province":"NSW",
    "sg:tags":[
        "consultant"
    ],
    "wof:name":"McRae Carol & Associates",
    "wof:placetype":"venue"
},
  "geometry": {"coordinates":[151.20855712900001,-33.8772392273],"type":"Point"}
}