{
  "type": "Feature",
  "properties": {
    "iso:country":"AU",
    "sg:address":"204 Albert St",
    "sg:city":"Sebastopol",
    "sg:classifiers":[
        {
            "category":"Fast Food",
            "type":"Food & Drink"
        }
    ],
    "sg:phone":"+61 3 5335 7882",
    "sg:postcode":"3356",
    "sg:province":"VIC",
    "sg:tags":[
        "away",
        "take"
    ],
    "wof:name":"Chickens R Us",
    "wof:placetype":"venue"
},
  "geometry": {"coordinates":[143.840912,-37.598518],"type":"Point"}
}