{
  "type": "Feature",
  "properties": {
    "addr:full":"15 Elvin St Macleod VIC 3085",
    "addr:housenumber":"15",
    "addr:postcode":"3085",
    "addr:street":"Elvin St",
    "iso:country":"AU",
    "sg:address":"15 Elvin St",
    "sg:city":"Macleod",
    "sg:classifiers":[
        {
            "category":"Arts & Performance",
            "subcategory":"Music",
            "type":"Entertainment"
        }
    ],
    "sg:phone":"+61 419 908 494",
    "sg:postcode":"3085",
    "sg:province":"VIC",
    "sg:tags":[
        "mobile",
        "jockey",
        "disc"
    ],
    "wof:name":"Dj Tony Boyd",
    "wof:placetype":"venue"
},
  "geometry": {"coordinates":[145.084350586,-37.7184028625],"type":"Point"}
}