{
  "type": "Feature",
  "properties": {
    "addr:full":"3056 Albany Hwy Armadale WA 6112",
    "addr:housenumber":"3056",
    "addr:postcode":"6112",
    "addr:street":"Albany Hwy",
    "iso:country":"AU",
    "sg:address":"3056 Albany Hwy",
    "sg:city":"Armadale",
    "sg:classifiers":[
        {
            "category":"Cafe",
            "type":"Food & Drink"
        }
    ],
    "sg:phone":"+61 8 9498 1910",
    "sg:postcode":"6112",
    "sg:province":"WA",
    "wof:name":"Thyme Out Cafe",
    "wof:placetype":"venue"
},
  "geometry": {"coordinates":[116.017753601,-32.1389656067],"type":"Point"}
}