{
  "type": "Feature",
  "properties": {
    "iso:country":"AU",
    "sg:address":"2/ 106 William St",
    "sg:city":"Port Macquarie",
    "sg:classifiers":[
        {
            "category":"Insurance",
            "subcategory":"Hazard Insurance",
            "type":"Services"
        }
    ],
    "sg:phone":"+61 2 6584 2144",
    "sg:postcode":"2444",
    "sg:province":"NSW",
    "sg:tags":[
        "fire",
        "accident",
        "marine"
    ],
    "wof:name":"Elders",
    "wof:placetype":"venue"
},
  "geometry": {"coordinates":[152.909409,-31.431307],"type":"Point"}
}