{
  "type": "Feature",
  "properties": {
    "addr:full":"3 Second Ave Loftus NSW 2232",
    "addr:housenumber":"3",
    "addr:postcode":"2232",
    "addr:street":"Second Ave",
    "iso:country":"AU",
    "sg:address":"3 Second Ave",
    "sg:city":"Loftus",
    "sg:classifiers":[
        {
            "category":"Building & Trades",
            "subcategory":"Plumbing",
            "type":"Services"
        }
    ],
    "sg:phone":"+61 418 253 018",
    "sg:postcode":"2232",
    "sg:province":"NSW",
    "sg:tags":[
        "plumber",
        "gasfitters"
    ],
    "wof:name":"Gersback B & S Plumbing",
    "wof:placetype":"venue"
},
  "geometry": {"coordinates":[151.05162048299999,-34.0377578735],"type":"Point"}
}