{
  "type": "Feature",
  "properties": {
    "addr:full":"52 Main St St Marys TAS 7215",
    "addr:housenumber":"52",
    "addr:postcode":"7215",
    "addr:street":"Main St",
    "iso:country":"AU",
    "sg:address":"52 Main St",
    "sg:city":"St Marys",
    "sg:classifiers":[
        {
            "category":"Food & Beverages",
            "subcategory":"Bakery",
            "type":"Retail Goods"
        }
    ],
    "sg:phone":"+61 3 6372 2131",
    "sg:postcode":"7215",
    "sg:province":"TAS",
    "sg:tags":[
        "baker"
    ],
    "wof:name":"St Marys Bakery",
    "wof:placetype":"venue"
},
  "geometry": {"coordinates":[148.187073,-41.579384],"type":"Point"}
}