{
  "type": "Feature",
  "properties": {
    "addr:full":"140 Maddox Rd Williamstown VIC 3016",
    "addr:housenumber":"140",
    "addr:postcode":"3016",
    "addr:street":"Maddox Rd",
    "iso:country":"AU",
    "sg:address":"140 Maddox Rd",
    "sg:city":"Williamstown",
    "sg:classifiers":[
        {
            "category":"Home & Garden",
            "subcategory":"Building Materials",
            "type":"Retail Goods"
        }
    ],
    "sg:phone":"+61 3 9397 0998",
    "sg:postcode":"3016",
    "sg:province":"VIC",
    "sg:tags":[
        "concrete",
        "panel",
        "pre-cast"
    ],
    "wof:name":"National Precast Pty Ltd",
    "wof:placetype":"venue"
},
  "geometry": {"coordinates":[144.866943359,-37.856262207],"type":"Point"}
}