{
  "type": "Feature",
  "properties": {
    "iso:country":"AU",
    "sg:address":"3 Blakesley Rd",
    "sg:city":"Hurstville South",
    "sg:classifiers":[
        {
            "category":"Building & Trades",
            "subcategory":"Construction",
            "type":"Services"
        }
    ],
    "sg:phone":"+61 400 663 066",
    "sg:postcode":"2221",
    "sg:province":"NSW",
    "sg:tags":[
        "polishing",
        "sanding",
        "floor"
    ],
    "wof:name":"A Grain Timber Floors",
    "wof:placetype":"venue"
},
  "geometry": {"coordinates":[151.11155700699999,-33.978427887],"type":"Point"}
}