{
  "type": "Feature",
  "properties": {
    "addr:full":"14 Erskine Rd Caringbah NSW 2229",
    "addr:housenumber":"14",
    "addr:postcode":"2229",
    "addr:street":"Erskine Rd",
    "iso:country":"AU",
    "sg:address":"14 Erskine Rd",
    "sg:city":"Caringbah",
    "sg:classifiers":[
        {
            "category":"Building & Trades",
            "subcategory":"Construction",
            "type":"Services"
        }
    ],
    "sg:phone":"+61 2 9525 3358",
    "sg:postcode":"2229",
    "sg:province":"NSW",
    "sg:tags":[
        "brick",
        "paving"
    ],
    "wof:name":"Jolly Rogers Concrete Products",
    "wof:placetype":"venue"
},
  "geometry": {"coordinates":[151.12223815900001,-34.0255393982],"type":"Point"}
}