{
  "type": "Feature",
  "properties": {
    "addr:full":"PO Box 422 Balgowlah NSW 2093",
    "addr:postcode":"2093",
    "iso:country":"AU",
    "sg:address":"PO Box 422",
    "sg:city":"Balgowlah",
    "sg:classifiers":[
        {
            "category":"Building & Trades",
            "subcategory":"Landscaping Services",
            "type":"Services"
        }
    ],
    "sg:phone":"+61 418 997 317",
    "sg:postcode":"2093",
    "sg:province":"NSW",
    "sg:tags":[
        "designer",
        "landscape",
        "contractor"
    ],
    "wof:name":"Jardine Art Landscape Design and Construction",
    "wof:placetype":"venue"
},
  "geometry": {"coordinates":[151.26158142099999,-33.7939300537],"type":"Point"}
}