{
  "type": "Feature",
  "properties": {
    "iso:country":"AU",
    "sg:address":"Punchbowl Rd",
    "sg:city":"Punchbowl",
    "sg:classifiers":[
        {
            "category":"Education",
            "subcategory":"School",
            "type":"Public Place"
        }
    ],
    "sg:phone":"+61 3 6344 1382",
    "sg:postcode":"7249",
    "sg:province":"TAS",
    "sg:tags":[
        "state",
        "except",
        "nsw"
    ],
    "wof:name":"Punchbowl Primary School",
    "wof:placetype":"venue"
},
  "geometry": {"coordinates":[147.163665772,-41.4582099915],"type":"Point"}
}