{
  "type": "Feature",
  "properties": {
    "addr:full":"PO Box 1141 Nairne SA 5252",
    "addr:postcode":"5252",
    "iso:country":"AU",
    "sg:address":"PO Box 1141",
    "sg:city":"Nairne",
    "sg:classifiers":[
        {
            "category":"Professional",
            "subcategory":"Art Services",
            "type":"Services"
        }
    ],
    "sg:phone":"+61 8 8388 6283",
    "sg:postcode":"5252",
    "sg:province":"SA",
    "sg:tags":[
        "graphic",
        "designer"
    ],
    "wof:name":"Cannon Michael",
    "wof:placetype":"venue"
},
  "geometry": {"coordinates":[138.91746520999999,-35.0379714966],"type":"Point"}
}