{
  "type": "Feature",
  "properties": {
    "iso:country":"AU",
    "sg:address":"29 Hammond St",
    "sg:city":"Altona",
    "sg:classifiers":[
        {
            "category":"Education",
            "subcategory":"Music School",
            "type":"Public Place"
        }
    ],
    "sg:phone":"+61 438 818 668",
    "sg:postcode":"3018",
    "sg:province":"VIC",
    "sg:tags":[
        "teacher"
    ],
    "wof:name":"Tim Canning",
    "wof:placetype":"venue"
},
  "geometry": {"coordinates":[144.82052612300001,-37.8579978943],"type":"Point"}
}