{
  "type": "Feature",
  "properties": {
    "addr:full":"206 Montague Rd West End QLD 4101",
    "addr:housenumber":"206",
    "addr:postcode":"4101",
    "addr:street":"Montague Rd",
    "iso:country":"AU",
    "sg:address":"206 Montague Rd",
    "sg:city":"West End",
    "sg:classifiers":[
        {
            "category":"Shopping",
            "subcategory":"Clothing, Apparel, & Fashions",
            "type":"Retail Goods"
        }
    ],
    "sg:phone":"+61 7 3217 2488",
    "sg:postcode":"4101",
    "sg:province":"QLD",
    "sg:tags":[
        "wholesaler",
        "children's",
        "mfrs",
        "wear"
    ],
    "wof:name":"Kaper Kidz Warehouse",
    "wof:placetype":"venue"
},
  "geometry": {"coordinates":[153.008544922,-27.4766387939],"type":"Point"}
}