{
  "type": "Feature",
  "properties": {
    "addr:full":"43 Mountain St Broadway NSW 2007",
    "addr:housenumber":"43",
    "addr:postcode":"2007",
    "addr:street":"Mountain St",
    "iso:country":"AU",
    "sg:address":"43 Mountain St",
    "sg:city":"Broadway",
    "sg:classifiers":[
        {
            "category":"Banks & Credit Unions",
            "subcategory":"Bank",
            "type":"Services"
        }
    ],
    "sg:phone":"+61 2 9211 3322",
    "sg:postcode":"2007",
    "sg:province":"NSW",
    "wof:name":"National Australia Bank Ltd",
    "wof:placetype":"venue"
},
  "geometry": {"coordinates":[151.19662475600001,-33.8840446472],"type":"Point"}
}