{
  "type": "Feature",
  "properties": {
    "addr:full":"High St Sydney University NSW 2006",
    "addr:postcode":"2006",
    "addr:street":"High St",
    "iso:country":"AU",
    "sg:address":"High St",
    "sg:city":"Sydney University",
    "sg:classifiers":[
        {
            "category":"Education",
            "subcategory":"University",
            "type":"Public Place"
        }
    ],
    "sg:phone":"+61 2 9385 3175",
    "sg:postcode":"2006",
    "sg:province":"NSW",
    "sg:tags":[
        "college",
        "tertiary"
    ],
    "wof:name":"Professional Education",
    "wof:placetype":"venue"
},
  "geometry": {"coordinates":[151.18692016599999,-33.8879203796],"type":"Point"}
}