{
  "type": "Feature",
  "properties": {
    "addr:full":"23 Slough Rd Altona VIC 3018",
    "addr:housenumber":"23",
    "addr:postcode":"3018",
    "addr:street":"Slough Rd",
    "iso:country":"AU",
    "sg:address":"23 Slough Rd",
    "sg:city":"Altona",
    "sg:classifiers":[
        {
            "category":"Building & Trades",
            "subcategory":"Plumbing",
            "type":"Services"
        }
    ],
    "sg:phone":"+61 3 9398 3611",
    "sg:postcode":"3018",
    "sg:province":"VIC",
    "sg:tags":[
        "plumber",
        "gasfitters"
    ],
    "wof:name":"A-Bright Plumbing Services Pty Ltd",
    "wof:placetype":"venue"
},
  "geometry": {"coordinates":[144.80667114299999,-37.8590393066],"type":"Point"}
}