{
  "type": "Feature",
  "properties": {
    "addr:full":"65 Wentworth St Vaucluse NSW 2030",
    "addr:housenumber":"65",
    "addr:postcode":"2030",
    "addr:street":"Wentworth St",
    "iso:country":"AU",
    "sg:address":"65 Wentworth St",
    "sg:city":"Vaucluse",
    "sg:classifiers":[
        {
            "category":"Real Estate",
            "subcategory":"Real Estate Services",
            "type":"Services"
        }
    ],
    "sg:phone":"+61 2 9337 6039",
    "sg:postcode":"2030",
    "sg:province":"NSW",
    "sg:tags":[
        "valuer"
    ],
    "wof:name":"Gardner K C",
    "wof:placetype":"venue"
},
  "geometry": {"coordinates":[151.282958984,-33.8816184998],"type":"Point"}
}