{
  "type": "Feature",
  "properties": {
    "addr:full":"186 Lachlan St Hay NSW 2711",
    "addr:housenumber":"186",
    "addr:postcode":"2711",
    "addr:street":"Lachlan St",
    "iso:country":"AU",
    "sg:address":"186 Lachlan St",
    "sg:city":"Hay",
    "sg:classifiers":[
        {
            "category":"Shopping",
            "subcategory":"Clothing, Apparel, & Fashions",
            "type":"Retail Goods"
        }
    ],
    "sg:phone":"+61 2 6993 1220",
    "sg:postcode":"2711",
    "sg:province":"NSW",
    "sg:tags":[
        "boutique"
    ],
    "wof:name":"Dy's Boutique",
    "wof:placetype":"venue"
},
  "geometry": {"coordinates":[144.84507751500001,-34.4994812012],"type":"Point"}
}