{
  "type": "Feature",
  "properties": {
    "addr:full":"The Wash House 6/193 Hartley St Portsmith QLD 4870",
    "addr:housenumber":"6 / 193",
    "addr:postcode":"4870",
    "addr:street":"Hartley St Portsmith",
    "iso:country":"AU",
    "sg:address":"The Wash House 6/193 Hartley St",
    "sg:city":"Portsmith",
    "sg:classifiers":[
        {
            "category":"Retail",
            "subcategory":"Laundry & Dry Cleaning",
            "type":"Services"
        }
    ],
    "sg:phone":"+61 7 4035 5900",
    "sg:postcode":"4870",
    "sg:province":"QLD",
    "wof:name":"Your Laundry",
    "wof:placetype":"venue"
},
  "geometry": {"coordinates":[145.762252808,-16.93907547],"type":"Point"}
}