{
  "type": "Feature",
  "properties": {
    "addr:full":"513 Princes Drv Morwell VIC 3840",
    "addr:housenumber":"513",
    "addr:postcode":"3840",
    "addr:street":"Princes Drv",
    "iso:country":"AU",
    "sg:address":"513 Princes Drv",
    "sg:city":"Morwell",
    "sg:classifiers":[
        {
            "category":"Industrial Area",
            "type":"Public Place"
        }
    ],
    "sg:phone":"+61 3 5133 6911",
    "sg:postcode":"3840",
    "sg:province":"VIC",
    "sg:tags":[
        "rural",
        "shed"
    ],
    "wof:name":"Aspire Garages",
    "wof:placetype":"venue"
},
  "geometry": {"coordinates":[146.408203125,-38.2395515442],"type":"Point"}
}