{
  "type": "Feature",
  "properties": {
    "iso:country":"AU",
    "sg:address":"18 Main Western Rd",
    "sg:city":"North Tamborine",
    "sg:classifiers":[
        {
            "category":"Health Services",
            "subcategory":"Optometrist",
            "type":"Services"
        }
    ],
    "sg:phone":"+61 7 5545 0277",
    "sg:postcode":"4272",
    "sg:province":"QLD",
    "wof:name":"Waldron Colin",
    "wof:placetype":"venue"
},
  "geometry": {"coordinates":[153.184204102,-27.9303092957],"type":"Point"}
}