{
  "type": "Feature",
  "properties": {
    "addr:full":"2/71 Seven Hills Rd Seven Hills NSW 2147",
    "addr:housenumber":"/ 71",
    "addr:postcode":"2147",
    "addr:street":"Seven Hills Rd",
    "iso:country":"AU",
    "sg:address":"2/71 Seven Hills Rd",
    "sg:city":"Seven Hills",
    "sg:classifiers":[
        {
            "category":"Train Station",
            "subcategory":"Rail",
            "type":"Transportation"
        }
    ],
    "sg:phone":"+61 2 9621 7135",
    "sg:postcode":"2147",
    "sg:province":"NSW",
    "sg:tags":[
        "goat",
        "farmer"
    ],
    "wof:name":"Rhoseberg Dairy Goat Toggenburg Stud",
    "wof:placetype":"venue"
},
  "geometry": {"coordinates":[150.93165588400001,-33.7786064148],"type":"Point"}
}