{
  "type": "Feature",
  "properties": {
    "addr:full":"72 Sarah St Ashmore QLD 4214",
    "addr:housenumber":"72",
    "addr:postcode":"4214",
    "addr:street":"Sarah St",
    "iso:country":"AU",
    "sg:address":"72 Sarah St",
    "sg:city":"Ashmore",
    "sg:classifiers":[
        {
            "category":"Banks & Credit Unions",
            "subcategory":"Bureau De Change",
            "type":"Services"
        }
    ],
    "sg:phone":"+61 7 5597 5687",
    "sg:postcode":"4214",
    "sg:province":"QLD",
    "sg:tags":[
        "rodent",
        "trap",
        "animal"
    ],
    "wof:name":"A Aaanimals & Pests",
    "wof:placetype":"venue"
},
  "geometry": {"coordinates":[153.343185425,-27.9847660065],"type":"Point"}
}