{
  "type": "Feature",
  "properties": {
    "addr:full":"\"Karith\" Dammans Road (Riverturn Lane) Warburton VIC 3799",
    "addr:postcode":"3799",
    "addr:street":"Dammans Road Riverturn Lane",
    "iso:country":"AU",
    "sg:address":"\"Karith\" Dammans Road (Riverturn Lane)",
    "sg:city":"Warburton",
    "sg:classifiers":[
        {
            "category":"Sports & Exercise",
            "subcategory":"Gym",
            "type":"Entertainment"
        }
    ],
    "sg:phone":"+61 3 5966 2120",
    "sg:postcode":"3799",
    "sg:province":"VIC",
    "sg:tags":[
        "meditation"
    ],
    "wof:name":"Sancta Sophia Meditation Community",
    "wof:placetype":"venue"
},
  "geometry": {"coordinates":[145.691696167,-37.7524452209],"type":"Point"}
}