{
  "type": "Feature",
  "properties": {
    "addr:full":"73 Devon St North Epping NSW 2121",
    "addr:housenumber":"73",
    "addr:postcode":"2121",
    "addr:street":"Devon St",
    "iso:country":"AU",
    "sg:address":"73 Devon St",
    "sg:city":"North Epping",
    "sg:classifiers":[
        {
            "category":"Professional",
            "subcategory":"Secretarial Services",
            "type":"Services"
        }
    ],
    "sg:phone":"+61 2 9869 4617",
    "sg:postcode":"2121",
    "sg:province":"NSW",
    "sg:tags":[
        "typing"
    ],
    "wof:name":"Rodgers & Rodgers Professional Support Services",
    "wof:placetype":"venue"
},
  "geometry": {"coordinates":[151.092193603,-33.7633476257],"type":"Point"}
}