{
  "type": "Feature",
  "properties": {
    "iso:country":"AU",
    "sg:address":"112 Rothschild Ave",
    "sg:city":"Rosebery",
    "sg:classifiers":[
        {
            "category":"Shopping",
            "subcategory":"Antiques",
            "type":"Retail Goods"
        }
    ],
    "sg:phone":"+61 2 9663 2997",
    "sg:postcode":"2018",
    "sg:province":"NSW",
    "sg:tags":[
        "restoration",
        "reproduction"
    ],
    "wof:name":"R.V. Rothschild Interiors",
    "wof:placetype":"venue"
},
  "geometry": {"coordinates":[151.20364379899999,-33.9182853699],"type":"Point"}
}