{
  "type": "Feature",
  "properties": {
    "iso:country":"AU",
    "sg:address":"640 Barkly St",
    "sg:city":"Ballarat",
    "sg:classifiers":[
        {
            "category":"Retail",
            "subcategory":"Auto Repair",
            "type":"Services"
        }
    ],
    "sg:phone":"+61 3 5332 4020",
    "sg:postcode":"3350",
    "sg:province":"VIC",
    "sg:tags":[
        "repairer",
        "motor",
        "engineer"
    ],
    "wof:name":"Paul Wilson Motors",
    "wof:placetype":"venue"
},
  "geometry": {"coordinates":[143.857834,-37.573578],"type":"Point"}
}