{
  "type": "Feature",
  "properties": {
    "iso:country":"AU",
    "sg:address":"20 Campbell St",
    "sg:city":"Gerringong",
    "sg:classifiers":[
        {
            "category":"Building & Trades",
            "subcategory":"Construction",
            "type":"Services"
        }
    ],
    "sg:phone":"+61 412 136 221",
    "sg:postcode":"2534",
    "sg:province":"NSW",
    "sg:tags":[
        "joiner",
        "carpenter"
    ],
    "wof:name":"D & R Kelly Services",
    "wof:placetype":"venue"
},
  "geometry": {"coordinates":[150.81869506800001,-34.7491493225],"type":"Point"}
}