{
  "type": "Feature",
  "properties": {
    "addr:full":"Cnr Evans Ave & Harvey St North Mackay QLD 4740",
    "addr:postcode":"4740",
    "addr:street":"Cnr Evans Ave & Harvey St",
    "iso:country":"AU",
    "sg:address":"Cnr Evans Ave & Harvey St",
    "sg:city":"North Mackay",
    "sg:classifiers":[
        {
            "category":"Education",
            "subcategory":"School",
            "type":"Public Place"
        }
    ],
    "sg:phone":"+61 7 4940 0333",
    "sg:postcode":"4740",
    "sg:province":"QLD",
    "sg:tags":[
        "state",
        "except",
        "nsw"
    ],
    "wof:name":"Mackay North Primary School",
    "wof:placetype":"venue"
},
  "geometry": {"coordinates":[149.184494,-21.121769],"type":"Point"}
}