{
  "type": "Feature",
  "properties": {
    "addr:full":"2 Angle Rd Deepdene VIC 3103",
    "addr:housenumber":"2",
    "addr:postcode":"3103",
    "addr:street":"Angle Rd",
    "iso:country":"AU",
    "sg:address":"2 Angle Rd",
    "sg:city":"Deepdene",
    "sg:classifiers":[
        {
            "category":"Professional",
            "subcategory":"Management & Consulting",
            "type":"Services"
        }
    ],
    "sg:phone":"+61 3 9817 3103",
    "sg:postcode":"3103",
    "sg:province":"VIC",
    "sg:tags":[
        "consultant"
    ],
    "wof:name":"Grand Central Investments Pty Ltd",
    "wof:placetype":"venue"
},
  "geometry": {"coordinates":[145.060623169,-37.8153381348],"type":"Point"}
}