{
  "type": "Feature",
  "properties": {
    "iso:country":"AU",
    "sg:address":"3 Coolbarro La",
    "sg:city":"Redcliffe",
    "sg:classifiers":[
        {
            "category":"Professional",
            "subcategory":"Engineering",
            "type":"Services"
        }
    ],
    "sg:phone":"+61 412 955 620",
    "sg:postcode":"6104",
    "sg:province":"WA",
    "sg:tags":[
        "diesel",
        "engineer"
    ],
    "wof:name":"Emergency Mechanical Service",
    "wof:placetype":"venue"
},
  "geometry": {"coordinates":[115.952392578,-31.9498710632],"type":"Point"}
}