{
  "type": "Feature",
  "properties": {
    "addr:full":"42 Panorama Drv Eumundi QLD 4562",
    "addr:housenumber":"42",
    "addr:postcode":"4562",
    "addr:street":"Panorama Drv",
    "iso:country":"AU",
    "sg:address":"42 Panorama Drv",
    "sg:city":"Eumundi",
    "sg:classifiers":[
        {
            "category":"Building & Trades",
            "subcategory":"Construction",
            "type":"Services"
        }
    ],
    "sg:phone":"+61 7 5449 1284",
    "sg:postcode":"4562",
    "sg:province":"QLD",
    "sg:tags":[
        "contractor"
    ],
    "wof:name":"David Palmer Homes",
    "wof:placetype":"venue"
},
  "geometry": {"coordinates":[152.97813415499999,-26.448633194],"type":"Point"}
}