{
  "type": "Feature",
  "properties": {
    "iso:country":"AU",
    "sg:address":"28 Tantitha St",
    "sg:city":"Bundaberg",
    "sg:classifiers":[
        {
            "category":"Insurance",
            "subcategory":"Hazard Insurance",
            "type":"Services"
        }
    ],
    "sg:phone":"+61 7 4151 3772",
    "sg:postcode":"4670",
    "sg:province":"QLD",
    "sg:tags":[
        "motor",
        "vehicle"
    ],
    "wof:name":"McLarens Young International",
    "wof:placetype":"venue"
},
  "geometry": {"coordinates":[152.35395813,-24.8666172028],"type":"Point"}
}