{
  "type": "Feature",
  "properties": {
    "addr:full":"8 Tower Drv Briar Hill VIC 3088",
    "addr:housenumber":"8",
    "addr:postcode":"3088",
    "addr:street":"Tower Drv",
    "iso:country":"AU",
    "sg:address":"8 Tower Drv",
    "sg:city":"Briar Hill",
    "sg:classifiers":[
        {
            "category":"Professional",
            "subcategory":"Business Services",
            "type":"Services"
        }
    ],
    "sg:phone":"+61 3 9432 1999",
    "sg:postcode":"3088",
    "sg:province":"VIC",
    "sg:tags":[
        "drafting"
    ],
    "wof:name":"N & B Smith Drafting Services",
    "wof:placetype":"venue"
},
  "geometry": {"coordinates":[145.11932373100001,-37.702003479],"type":"Point"}
}