{
  "type": "Feature",
  "properties": {
    "addr:full":"PO Box 173 Northcliffe WA 6262",
    "addr:postcode":"6262",
    "iso:country":"AU",
    "sg:address":"PO Box 173",
    "sg:city":"Northcliffe",
    "sg:classifiers":[
        {
            "category":"Building & Trades",
            "subcategory":"Construction",
            "type":"Services"
        }
    ],
    "sg:phone":"+61 429 900 330",
    "sg:postcode":"6262",
    "sg:province":"WA",
    "sg:tags":[
        "earth",
        "excavating",
        "moving",
        "contractor"
    ],
    "wof:name":"Mal Armstrong Contracting",
    "wof:placetype":"venue"
},
  "geometry": {"coordinates":[116.115196228,-34.6328086853],"type":"Point"}
}