{
  "type": "Feature",
  "properties": {
    "addr:full":"65- 67 Thomas Drv Chevron Island QLD 4217",
    "addr:housenumber":"67",
    "addr:postcode":"4217",
    "addr:street":"Thomas Drv Chevron",
    "iso:country":"AU",
    "sg:address":"65- 67 Thomas Drv",
    "sg:city":"Chevron Island",
    "sg:classifiers":[
        {
            "category":"Banks & Credit Unions",
            "subcategory":"Investment Brokerage",
            "type":"Services"
        }
    ],
    "sg:phone":"+61 7 5592 5777",
    "sg:postcode":"4217",
    "sg:province":"QLD",
    "sg:tags":[
        "share",
        "broker",
        "stock"
    ],
    "sg:website":"http://www.abnamromorgans.com.au",
    "wof:name":"ABN AMRO Morgans",
    "wof:placetype":"venue"
},
  "geometry": {"coordinates":[153.41798400900001,-27.9976043701],"type":"Point"}
}