{
  "type": "Feature",
  "properties": {
    "addr:full":"Workshop 7, 2B Holmes St Ballarat VIC 3350",
    "addr:housenumber":"2b",
    "addr:postcode":"3350",
    "addr:street":"Holmes St",
    "iso:country":"AU",
    "sg:address":"Workshop 7, 2B Holmes St",
    "sg:city":"Ballarat",
    "sg:classifiers":[
        {
            "category":"Personal",
            "type":"Services"
        }
    ],
    "sg:phone":"+61 3 5331 5808",
    "sg:postcode":"3350",
    "sg:province":"VIC",
    "sg:tags":[
        "dressmaker"
    ],
    "wof:name":"Ellium Jane",
    "wof:placetype":"venue"
},
  "geometry": {"coordinates":[143.856033,-37.555088],"type":"Point"}
}