{
  "type": "Feature",
  "properties": {
    "iso:country":"AU",
    "sg:address":"First Floor, 71 Racecourse Rd",
    "sg:city":"Ascot",
    "sg:classifiers":[
        {
            "category":"Health Services",
            "subcategory":"Health Practitioner",
            "type":"Services"
        }
    ],
    "sg:phone":"+61 411 242 982",
    "sg:postcode":"4007",
    "sg:province":"QLD",
    "sg:tags":[
        "acupuncture"
    ],
    "wof:name":"Maria Berry",
    "wof:placetype":"venue"
},
  "geometry": {"coordinates":[153.064957,-27.436169],"type":"Point"}
}