{
  "type": "Feature",
  "properties": {
    "addr:full":"40 Butler Drv Kuranda QLD 4872",
    "addr:housenumber":"40",
    "addr:postcode":"4872",
    "addr:street":"Butler Drv",
    "iso:country":"AU",
    "sg:address":"40 Butler Drv",
    "sg:city":"Kuranda",
    "sg:classifiers":[
        {
            "category":"Banks & Credit Unions",
            "subcategory":"Bureau De Change",
            "type":"Services"
        }
    ],
    "sg:phone":"+61 7 4093 8886",
    "sg:postcode":"4872",
    "sg:province":"QLD",
    "sg:tags":[
        "gas",
        "natural",
        "lp",
        "equipment"
    ],
    "wof:name":"Doreian Tony",
    "wof:placetype":"venue"
},
  "geometry": {"coordinates":[145.71351623499999,-16.9049224854],"type":"Point"}
}