{
  "type": "Feature",
  "properties": {
    "addr:full":"Shop 7 1 Edmunds St Darwin NT 0800",
    "addr:housenumber":"shop;1",
    "addr:postcode":"nt 0800",
    "addr:street":"Edmunds St",
    "iso:country":"AU",
    "sg:address":"Shop 7 1 Edmunds St",
    "sg:city":"Darwin",
    "sg:classifiers":[
        {
            "category":"Professional",
            "subcategory":"Printing & Photocopies",
            "type":"Services"
        }
    ],
    "sg:phone":"+61 8 8981 6805",
    "sg:postcode":"0800",
    "sg:province":"NT",
    "sg:tags":[
        "laminating"
    ],
    "wof:name":"Art Decor Picture Framing",
    "wof:placetype":"venue"
},
  "geometry": {"coordinates":[130.840942383,-12.462015152],"type":"Point"}
}