{
  "type": "Feature",
  "properties": {
    "iso:country":"AU",
    "sg:address":"2/ 36 Griffey St",
    "sg:city":"Bohle",
    "sg:classifiers":[
        {
            "category":"Utilities",
            "subcategory":"Natural Gas",
            "type":"Services"
        }
    ],
    "sg:phone":"+61 7 4774 6616",
    "sg:postcode":"4818",
    "sg:province":"QLD",
    "sg:tags":[
        "solid",
        "plasterer"
    ],
    "wof:name":"A & S Texture Coating",
    "wof:placetype":"venue"
},
  "geometry": {"coordinates":[146.686935,-19.245609],"type":"Point"}
}