{
  "type": "Feature",
  "properties": {
    "addr:full":"2/ 21 Hospital Rd Emerald QLD 4720",
    "addr:housenumber":"/ 21",
    "addr:postcode":"4720",
    "addr:street":"Hospital Rd",
    "iso:country":"AU",
    "sg:address":"2/ 21 Hospital Rd",
    "sg:city":"Emerald",
    "sg:classifiers":[
        {
            "category":"Insurance",
            "subcategory":"Hazard Insurance",
            "type":"Services"
        }
    ],
    "sg:phone":"+61 7 4987 5811",
    "sg:postcode":"4720",
    "sg:province":"QLD",
    "sg:tags":[
        "fire",
        "accident",
        "marine"
    ],
    "wof:name":"Regional Insurance Brokers",
    "wof:placetype":"venue"
},
  "geometry": {"coordinates":[148.15841699999999,-23.524158],"type":"Point"}
}