{
  "type": "Feature",
  "properties": {
    "iso:country":"AU",
    "sg:address":"Lvel 11, 135 King St",
    "sg:city":"Sydney",
    "sg:classifiers":[
        {
            "category":"Banks & Credit Unions",
            "subcategory":"Bank",
            "type":"Services"
        }
    ],
    "sg:phone":"+61 2 9238 6400",
    "sg:postcode":"2000",
    "sg:province":"NSW",
    "wof:name":"Bank of Queensland Limited",
    "wof:placetype":"venue"
},
  "geometry": {"coordinates":[151.208908081,-33.8690719604],"type":"Point"}
}