{
  "type": "Feature",
  "properties": {
    "addr:full":"290 Botany Rd Alexandria NSW 2015",
    "addr:housenumber":"290",
    "addr:postcode":"2015",
    "addr:street":"Botany Rd",
    "iso:country":"AU",
    "sg:address":"290 Botany Rd",
    "sg:city":"Alexandria",
    "sg:classifiers":[
        {
            "category":"Social Services",
            "subcategory":"Retirement Home",
            "type":"Services"
        }
    ],
    "sg:phone":"+61 2 9699 8166",
    "sg:postcode":"2015",
    "sg:province":"NSW",
    "sg:tags":[
        "t-shirt",
        "supplier"
    ],
    "wof:name":"Aushen Corporate Clothing Pty Ltd",
    "wof:placetype":"venue"
},
  "geometry": {"coordinates":[151.20242309599999,-33.9043159485],"type":"Point"}
}