{
  "type": "Feature",
  "properties": {
    "addr:full":"1/ 75 Hunter St Hornsby NSW 2077",
    "addr:housenumber":"/ 75",
    "addr:postcode":"2077",
    "addr:street":"Hunter St",
    "iso:country":"AU",
    "sg:address":"1/ 75 Hunter St",
    "sg:city":"Hornsby",
    "sg:classifiers":[
        {
            "category":"Home & Garden",
            "subcategory":"Furniture",
            "type":"Retail Goods"
        }
    ],
    "sg:phone":"+61 2 9476 3880",
    "sg:postcode":"2077",
    "sg:province":"NSW",
    "sg:tags":[
        "repair",
        "restoration"
    ],
    "wof:name":"All Furniture Repair Co.",
    "wof:placetype":"venue"
},
  "geometry": {"coordinates":[151.10104370100001,-33.7008323669],"type":"Point"}
}