{
  "type": "Feature",
  "properties": {
    "iso:country":"AU",
    "sg:address":"1/ 4 Canterbury Rd",
    "sg:city":"Braeside",
    "sg:classifiers":[
        {
            "category":"Manufacturing",
            "subcategory":"Soap",
            "type":"Manufacturing & Wholesale Goods"
        }
    ],
    "sg:phone":"+61 3 9587 8515",
    "sg:postcode":"3195",
    "sg:province":"VIC",
    "sg:tags":[
        "detergent"
    ],
    "wof:name":"DBJ Chemicals",
    "wof:placetype":"venue"
},
  "geometry": {"coordinates":[145.105392456,-38.0099220276],"type":"Point"}
}