{
  "type": "Feature",
  "properties": {
    "addr:full":"Shop 6, 37- 41 Victoria St Hastings VIC 3915",
    "addr:housenumber":"shop;37 41",
    "addr:postcode":"3915",
    "addr:street":"Victoria St",
    "iso:country":"AU",
    "sg:address":"Shop 6, 37- 41 Victoria St",
    "sg:city":"Hastings",
    "sg:classifiers":[
        {
            "category":"Professional",
            "subcategory":"Accounting & Tax Preparation",
            "type":"Services"
        }
    ],
    "sg:phone":"+61 3 5979 3096",
    "sg:postcode":"3915",
    "sg:province":"VIC",
    "sg:tags":[
        "consultant",
        "taxation"
    ],
    "wof:name":"Block H&R",
    "wof:placetype":"venue"
},
  "geometry": {"coordinates":[145.19065856899999,-38.30727005],"type":"Point"}
}