{
  "type": "Feature",
  "properties": {
    "iso:country":"AU",
    "sg:address":"15 Milgate St",
    "sg:city":"Oakleigh South",
    "sg:classifiers":[
        {
            "category":"Home & Garden",
            "subcategory":"Building Materials",
            "type":"Retail Goods"
        }
    ],
    "sg:phone":"+61 3 9544 4325",
    "sg:postcode":"3167",
    "sg:province":"VIC",
    "sg:tags":[
        "laminate",
        "laminated",
        "panel"
    ],
    "wof:name":"James A Wilson",
    "wof:placetype":"venue"
},
  "geometry": {"coordinates":[145.10902404800001,-37.9147071838],"type":"Point"}
}