{
  "type": "Feature",
  "properties": {
    "iso:country":"AU",
    "sg:address":"53 B Byrnes St",
    "sg:city":"Mareeba",
    "sg:classifiers":[
        {
            "category":"Retail",
            "subcategory":"Self-service Laundry",
            "type":"Services"
        }
    ],
    "sg:phone":"+61 7 4092 6703",
    "sg:postcode":"4880",
    "sg:province":"QLD",
    "wof:name":"Mareeba Laundromat",
    "wof:placetype":"venue"
},
  "geometry": {"coordinates":[145.424957275,-17.0126361847],"type":"Point"}
}