{
  "type": "Feature",
  "properties": {
    "iso:country":"AU",
    "sg:address":"7076 Pacific Hwy",
    "sg:city":"Ormeau",
    "sg:classifiers":[
        {
            "category":"Autos & Motor Vehicles",
            "subcategory":"Fuel & Gas Station",
            "type":"Retail Goods"
        }
    ],
    "sg:phone":"+61 7 5546 6255",
    "sg:postcode":"4208",
    "sg:province":"QLD",
    "wof:name":"Mobil Oil Aust Ltd",
    "wof:placetype":"venue"
},
  "geometry": {"coordinates":[153.24998474099999,-27.7675533295],"type":"Point"}
}