{
  "type": "Feature",
  "properties": {
    "addr:full":"32 Groves Ave Mulgrave NSW 2756",
    "addr:housenumber":"32",
    "addr:postcode":"2756",
    "addr:street":"Groves Ave",
    "iso:country":"AU",
    "sg:address":"32 Groves Ave",
    "sg:city":"Mulgrave",
    "sg:classifiers":[
        {
            "category":"Manufacturing",
            "subcategory":"Motor Vehicles & Parts",
            "type":"Manufacturing & Wholesale Goods"
        }
    ],
    "sg:phone":"+61 2 4587 7807",
    "sg:postcode":"2756",
    "sg:province":"NSW",
    "sg:tags":[
        "replacement"
    ],
    "wof:name":"British Motor Imports",
    "wof:placetype":"venue"
},
  "geometry": {"coordinates":[150.834884644,-33.6275024414],"type":"Point"}
}