{
  "type": "Feature",
  "properties": {
    "addr:full":"4 Ancilla St Mullaloo WA 6027",
    "addr:housenumber":"4",
    "addr:postcode":"6027",
    "addr:street":"Ancilla St",
    "iso:country":"AU",
    "sg:address":"4 Ancilla St",
    "sg:city":"Mullaloo",
    "sg:classifiers":[
        {
            "category":"Food & Beverages",
            "subcategory":"Specialty",
            "type":"Retail Goods"
        }
    ],
    "sg:phone":"+61 415 591 764",
    "sg:postcode":"6027",
    "sg:province":"WA",
    "sg:tags":[
        "product",
        "health"
    ],
    "wof:name":"Juice Plus",
    "wof:placetype":"venue"
},
  "geometry": {"coordinates":[115.742782593,-31.7736625671],"type":"Point"}
}