{
  "type": "Feature",
  "properties": {
    "addr:full":"89 Wilkins St Newport VIC 3015",
    "addr:housenumber":"89",
    "addr:postcode":"3015",
    "addr:street":"Wilkins St",
    "iso:country":"AU",
    "sg:address":"89 Wilkins St",
    "sg:city":"Newport",
    "sg:classifiers":[
        {
            "category":"Retail",
            "subcategory":"Auto Repair",
            "type":"Services"
        }
    ],
    "sg:phone":"+61 3 9399 2977",
    "sg:postcode":"3015",
    "sg:province":"VIC",
    "sg:tags":[
        "repairer",
        "motor",
        "engineer"
    ],
    "wof:name":"Pace Motors",
    "wof:placetype":"venue"
},
  "geometry": {"coordinates":[144.886520386,-37.846534729],"type":"Point"}
}