{
  "type": "Feature",
  "properties": {
    "iso:country":"AU",
    "sg:address":"14 Bernborough Crt",
    "sg:city":"Toowoomba",
    "sg:classifiers":[
        {
            "category":"Manufacturing",
            "subcategory":"Tools & Machinery",
            "type":"Manufacturing & Wholesale Goods"
        }
    ],
    "sg:phone":"+61 7 4634 0055",
    "sg:postcode":"4350",
    "sg:province":"QLD",
    "sg:tags":[
        "earth",
        "excavating",
        "moving",
        "equipment"
    ],
    "wof:name":"Gregs Kerbs & Paths",
    "wof:placetype":"venue"
},
  "geometry": {"coordinates":[151.914597,-27.556059],"type":"Point"}
}