{
  "type": "Feature",
  "properties": {
    "addr:full":"44 Victor Ave Panania NSW 2213",
    "addr:housenumber":"44",
    "addr:postcode":"2213",
    "addr:street":"Victor Ave",
    "iso:country":"AU",
    "sg:address":"44 Victor Ave",
    "sg:city":"Panania",
    "sg:classifiers":[
        {
            "category":"Building & Trades",
            "subcategory":"Construction",
            "type":"Services"
        }
    ],
    "sg:phone":"+61 2 9773 1122",
    "sg:postcode":"2213",
    "sg:province":"NSW",
    "sg:tags":[
        "contractor"
    ],
    "wof:name":"C J V Constructions",
    "wof:placetype":"venue"
},
  "geometry": {"coordinates":[151.00668300000001,-33.964314],"type":"Point"}
}