{
  "type": "Feature",
  "properties": {
    "addr:full":"28 Middle St Chinchilla QLD 4413",
    "addr:housenumber":"28",
    "addr:postcode":"4413",
    "addr:street":"Middle St",
    "iso:country":"AU",
    "sg:address":"28 Middle St",
    "sg:city":"Chinchilla",
    "sg:classifiers":[
        {
            "category":"Education",
            "subcategory":"School",
            "type":"Public Place"
        }
    ],
    "sg:phone":"+61 7 4662 7726",
    "sg:postcode":"4413",
    "sg:province":"QLD",
    "sg:tags":[
        "state",
        "except",
        "nsw"
    ],
    "wof:name":"Chinchilla Preschool",
    "wof:placetype":"venue"
},
  "geometry": {"coordinates":[150.62652587900001,-26.7429351807],"type":"Point"}
}