{
  "type": "Feature",
  "properties": {
    "addr:full":"95 Milton St Mackay QLD 4740",
    "addr:housenumber":"95",
    "addr:postcode":"4740",
    "addr:street":"Milton St",
    "iso:country":"AU",
    "sg:address":"95 Milton St",
    "sg:city":"Mackay",
    "sg:classifiers":[
        {
            "category":"Food & Beverages",
            "subcategory":"Supermarket",
            "type":"Retail Goods"
        }
    ],
    "sg:phone":"+61 7 4957 8763",
    "sg:postcode":"4740",
    "sg:province":"QLD",
    "sg:tags":[
        "grocery",
        "store"
    ],
    "wof:name":"De Campo's Mini Market",
    "wof:placetype":"venue"
},
  "geometry": {"coordinates":[149.175522,-21.159891],"type":"Point"}
}