{
  "type": "Feature",
  "properties": {
    "iso:country":"AU",
    "sg:address":"PO Box 14155",
    "sg:city":"Mt Sheridan",
    "sg:classifiers":[
        {
            "category":"Professional",
            "type":"Services"
        }
    ],
    "sg:phone":"+61 403 424 547",
    "sg:postcode":"4868",
    "sg:province":"QLD",
    "sg:tags":[
        "shop",
        "fitting"
    ],
    "wof:name":"Dickinson Painting Contractors",
    "wof:placetype":"venue"
},
  "geometry": {"coordinates":[145.74195861800001,-16.9764003754],"type":"Point"}
}