{
  "type": "Feature",
  "properties": {
    "iso:country":"AU",
    "sg:address":"246 Pullenvale Rd",
    "sg:city":"Pullenvale",
    "sg:classifiers":[
        {
            "category":"Home & Garden",
            "subcategory":"Building Materials",
            "type":"Retail Goods"
        }
    ],
    "sg:phone":"+61 7 3818 0882",
    "sg:postcode":"4069",
    "sg:province":"QLD",
    "sg:tags":[
        "merchant",
        "glass",
        "glazier"
    ],
    "wof:name":"Quick Glaze Group",
    "wof:placetype":"venue"
},
  "geometry": {"coordinates":[152.90153503400001,-27.5180644989],"type":"Point"}
}