{
  "type": "Feature",
  "properties": {
    "addr:full":"(Yarra Vly Living Cntre) Rayner Crt Yarra Junction VIC 3797",
    "addr:postcode":"3797",
    "addr:street":"Rayner Crt",
    "iso:country":"AU",
    "sg:address":"(Yarra Vly Living Cntre) Rayner Crt",
    "sg:city":"Yarra Junction",
    "sg:classifiers":[
        {
            "category":"Organizations",
            "subcategory":"Membership Organization",
            "type":"Services"
        }
    ],
    "sg:phone":"+61 3 5967 1730",
    "sg:postcode":"3797",
    "sg:province":"VIC",
    "sg:tags":[
        "support",
        "health",
        "organisation"
    ],
    "wof:name":"Gawler Foundation",
    "wof:placetype":"venue"
},
  "geometry": {"coordinates":[145.64010620100001,-37.8062171936],"type":"Point"}
}