{
  "type": "Feature",
  "properties": {
    "iso:country":"AU",
    "sg:address":"212 Victoria St",
    "sg:city":"Mackay",
    "sg:classifiers":[
        {
            "category":"Autos & Motor Vehicles",
            "subcategory":"Auto Supplies",
            "type":"Retail Goods"
        }
    ],
    "sg:phone":"+61 7 4951 1488",
    "sg:postcode":"4740",
    "sg:province":"QLD",
    "sg:tags":[
        "accessory"
    ],
    "wof:name":"Direct Auto Supply",
    "wof:placetype":"venue"
},
  "geometry": {"coordinates":[149.181534,-21.140442],"type":"Point"}
}