{
  "type": "Feature",
  "properties": {
    "addr:full":"19c Activity Crs Molendinar QLD 4214",
    "addr:housenumber":"19c",
    "addr:postcode":"4214",
    "addr:street":"Activity Crs",
    "iso:country":"AU",
    "sg:address":"19c Activity Crs",
    "sg:city":"Molendinar",
    "sg:classifiers":[
        {
            "category":"Manufacturing",
            "subcategory":"Motor Vehicles & Parts",
            "type":"Manufacturing & Wholesale Goods"
        }
    ],
    "sg:phone":"+61 412 667 022",
    "sg:postcode":"4214",
    "sg:province":"QLD",
    "sg:tags":[
        "equipment",
        "cushion",
        "air"
    ],
    "wof:name":"Innovative Developments Pty Ltd",
    "wof:placetype":"venue"
},
  "geometry": {"coordinates":[153.36187744099999,-27.9781703949],"type":"Point"}
}