{
  "type": "Feature",
  "properties": {
    "addr:full":"8 Binney Rd Marayong NSW 2148",
    "addr:housenumber":"8",
    "addr:postcode":"2148",
    "addr:street":"Binney Rd",
    "iso:country":"AU",
    "sg:address":"8 Binney Rd",
    "sg:city":"Marayong",
    "sg:classifiers":[
        {
            "category":"Building & Trades",
            "subcategory":"Plumbing",
            "type":"Services"
        }
    ],
    "sg:phone":"+61 2 8822 7122",
    "sg:postcode":"2148",
    "sg:province":"NSW",
    "sg:tags":[
        "equipment",
        "valves"
    ],
    "wof:name":"Flowserve Australia Pty Ltd",
    "wof:placetype":"venue"
},
  "geometry": {"coordinates":[150.908294678,-33.7435150146],"type":"Point"}
}