{
  "type": "Feature",
  "properties": {
    "iso:country":"AU",
    "sg:address":"97 Franklin St",
    "sg:city":"Melbourne",
    "sg:classifiers":[
        {
            "category":"Professional",
            "subcategory":"Computer Services",
            "type":"Services"
        }
    ],
    "sg:phone":"+61 3 9929 9744",
    "sg:postcode":"3000",
    "sg:province":"VIC",
    "sg:tags":[
        "technical",
        "support"
    ],
    "wof:name":"Phoenix IT Tech Support",
    "wof:placetype":"venue"
},
  "geometry": {"coordinates":[144.96112060600001,-37.8080863953],"type":"Point"}
}