{
  "type": "Feature",
  "properties": {
    "iso:country":"AU",
    "sg:address":"84 LaFrantz Drv",
    "sg:city":"Tinana",
    "sg:classifiers":[
        {
            "category":"Personal",
            "subcategory":"Nail Salon",
            "type":"Services"
        }
    ],
    "sg:phone":"+61 7 4123 3626",
    "sg:postcode":"4650",
    "sg:province":"QLD",
    "sg:tags":[
        "artificial"
    ],
    "wof:name":"Funky Nailz",
    "wof:placetype":"venue"
},
  "geometry": {"coordinates":[152.68034399999999,-25.542809],"type":"Point"}
}