{
  "type": "Feature",
  "properties": {
    "addr:full":"108 Weld St Beaconsfield TAS 7270",
    "addr:housenumber":"108",
    "addr:postcode":"7270",
    "addr:street":"Weld St",
    "iso:country":"AU",
    "sg:address":"108 Weld St",
    "sg:city":"Beaconsfield",
    "sg:classifiers":[
        {
            "category":"Government",
            "subcategory":"Post Office",
            "type":"Public Place"
        }
    ],
    "sg:phone":"+61 13 13 18",
    "sg:postcode":"7270",
    "sg:province":"TAS",
    "sg:tags":[
        "postal"
    ],
    "wof:name":"Australia Post",
    "wof:placetype":"venue"
},
  "geometry": {"coordinates":[146.81698608400001,-41.2010879517],"type":"Point"}
}