{
  "type": "Feature",
  "properties": {
    "addr:full":"108a Langtree Ave Mildura VIC 3500",
    "addr:housenumber":"108a",
    "addr:postcode":"3500",
    "addr:street":"Langtree Ave",
    "iso:country":"AU",
    "sg:address":"108a Langtree Ave",
    "sg:city":"Mildura",
    "sg:classifiers":[
        {
            "category":"Shopping",
            "subcategory":"Clothing, Apparel, & Fashions",
            "type":"Retail Goods"
        }
    ],
    "sg:phone":"+61 3 5023 2733",
    "sg:postcode":"3500",
    "sg:province":"VIC",
    "sg:tags":[
        "lady",
        "wear"
    ],
    "wof:name":"Di Lyn Fashions",
    "wof:placetype":"venue"
},
  "geometry": {"coordinates":[142.15890502900001,-34.1865844727],"type":"Point"}
}