{
  "type": "Feature",
  "properties": {
    "addr:full":"16 Lily St Coburg North VIC 3058",
    "addr:housenumber":"16",
    "addr:postcode":"3058",
    "addr:street":"Lily St",
    "iso:country":"AU",
    "sg:address":"16 Lily St",
    "sg:city":"Coburg North",
    "sg:classifiers":[
        {
            "category":"Taxi",
            "type":"Transportation"
        }
    ],
    "sg:phone":"+61 3 9354 9918",
    "sg:postcode":"3058",
    "sg:province":"VIC",
    "sg:tags":[
        "cab"
    ],
    "wof:name":"V & A Nominees Pty Ltd",
    "wof:placetype":"venue"
},
  "geometry": {"coordinates":[144.952224731,-37.7236747742],"type":"Point"}
}