{
  "type": "Feature",
  "properties": {
    "iso:country":"AU",
    "sg:address":"Shop 6/ 306 Great Eastern Hwy",
    "sg:city":"Midland",
    "sg:classifiers":[
        {
            "category":"Shopping",
            "subcategory":"Baby Store",
            "type":"Retail Goods"
        }
    ],
    "sg:phone":"+61 8 9274 8854",
    "sg:postcode":"6056",
    "sg:province":"WA",
    "sg:tags":[
        "wear"
    ],
    "wof:name":"Cheeky Monkeys",
    "wof:placetype":"venue"
},
  "geometry": {"coordinates":[116.012336731,-31.8918018341],"type":"Point"}
}