{
  "type": "Feature",
  "properties": {
    "iso:country":"AU",
    "sg:address":"PO Box 204",
    "sg:city":"Howard Springs",
    "sg:classifiers":[
        {
            "category":"Wholesale",
            "subcategory":"Machinery & Supplies",
            "type":"Manufacturing & Wholesale Goods"
        }
    ],
    "sg:phone":"+61 417 825 707",
    "sg:postcode":"0835",
    "sg:province":"NT",
    "sg:tags":[
        "rigging",
        "equipment",
        "hoisting"
    ],
    "wof:name":"Atko Mechanical Engineering Pty Ltd",
    "wof:placetype":"venue"
},
  "geometry": {"coordinates":[131.045792,-12.49626],"type":"Point"}
}