{
  "type": "Feature",
  "properties": {
    "addr:full":"PO Box 204 Howard Springs NT 0835",
    "addr:postcode":"nt 0835",
    "iso:country":"AU",
    "sg:address":"PO Box 204",
    "sg:city":"Howard Springs",
    "sg:classifiers":[
        {
            "category":"Wholesale",
            "subcategory":"Machinery & Supplies",
            "type":"Manufacturing & Wholesale Goods"
        }
    ],
    "sg:phone":"+61 417 825 707",
    "sg:postcode":"0835",
    "sg:province":"NT",
    "sg:tags":[
        "rigging",
        "equipment",
        "hoisting"
    ],
    "wof:name":"Atko Mechanical Engineering Pty Ltd",
    "wof:placetype":"venue"
},
  "geometry": {"coordinates":[131.04579200000001,-12.49626],"type":"Point"}
}