{
  "type": "Feature",
  "properties": {
    "iso:country":"AU",
    "sg:address":"Shop 7 Parry Ave Village Shopng Cntr",
    "sg:city":"Bullcreek",
    "sg:classifiers":[
        {
            "category":"Food & Beverages",
            "subcategory":"Groceries & Convenience Stores",
            "type":"Retail Goods"
        }
    ],
    "sg:phone":"+61 8 9310 4572",
    "sg:postcode":"6149",
    "sg:province":"WA",
    "wof:name":"Bullcreek Oriental Supplies",
    "wof:placetype":"venue"
},
  "geometry": {"coordinates":[115.84573399999999,-32.054337],"type":"Point"}
}