{
  "type": "Feature",
  "properties": {
    "addr:full":"102 West St The Range QLD 4700",
    "addr:housenumber":"102",
    "addr:postcode":"4700",
    "addr:street":"West St The",
    "iso:country":"AU",
    "sg:address":"102 West St",
    "sg:city":"The Range",
    "sg:classifiers":[
        {
            "category":"Professional",
            "subcategory":"Accounting & Tax Preparation",
            "type":"Services"
        }
    ],
    "sg:phone":"+61 7 4922 5108",
    "sg:postcode":"4700",
    "sg:province":"QLD",
    "sg:tags":[
        "consultant",
        "taxation"
    ],
    "wof:name":"Yorke Peter R",
    "wof:placetype":"venue"
},
  "geometry": {"coordinates":[150.503662109,-23.3827171326],"type":"Point"}
}