{
  "type": "Feature",
  "properties": {
    "iso:country":"AU",
    "sg:address":"53 Harrick Rd",
    "sg:city":"Keilor Park",
    "sg:classifiers":[
        {
            "category":"Professional",
            "subcategory":"Employment Agencies",
            "type":"Services"
        }
    ],
    "sg:phone":"+61 3 9933 1300",
    "sg:postcode":"3042",
    "sg:province":"VIC",
    "sg:tags":[
        "broker",
        "custom"
    ],
    "wof:name":"Pacific Network",
    "wof:placetype":"venue"
},
  "geometry": {"coordinates":[144.846160889,-37.7207679749],"type":"Point"}
}