{
  "type": "Feature",
  "properties": {
    "addr:full":"22 Goldfinch Crt Carrum Downs VIC 3201",
    "addr:housenumber":"22",
    "addr:postcode":"3201",
    "addr:street":"Goldfinch Crt",
    "iso:country":"AU",
    "sg:address":"22 Goldfinch Crt",
    "sg:city":"Carrum Downs",
    "sg:classifiers":[
        {
            "category":"Building & Trades",
            "subcategory":"Construction",
            "type":"Services"
        }
    ],
    "sg:phone":"+61 3 9776 9874",
    "sg:postcode":"3201",
    "sg:province":"VIC",
    "sg:tags":[
        "polishing",
        "sanding",
        "floor"
    ],
    "wof:name":"Quality Floors",
    "wof:placetype":"venue"
},
  "geometry": {"coordinates":[145.169647,-38.106659],"type":"Point"}
}