{
  "type": "Feature",
  "properties": {
    "addr:full":"49 Lee-Steere Drv Mariginiup WA 6065",
    "addr:housenumber":"49",
    "addr:postcode":"6065",
    "addr:street":"Lee-Steere Drv",
    "iso:country":"AU",
    "sg:address":"49 Lee-Steere Drv",
    "sg:city":"Mariginiup",
    "sg:classifiers":[
        {
            "category":"Retail",
            "subcategory":"Repair Shop",
            "type":"Services"
        }
    ],
    "sg:phone":"+61 8 9306 3066",
    "sg:postcode":"6065",
    "sg:province":"WA",
    "sg:tags":[
        "maintenance",
        "pool",
        "swimming"
    ],
    "wof:name":"Atlantic Pools",
    "wof:placetype":"venue"
},
  "geometry": {"coordinates":[115.816268921,-31.7024288177],"type":"Point"}
}