{
  "type": "Feature",
  "properties": {
    "addr:full":"589 South Western Hwy Byford WA 6122",
    "addr:housenumber":"589",
    "addr:postcode":"6122",
    "addr:street":"South Western Hwy",
    "iso:country":"AU",
    "sg:address":"589 South Western Hwy",
    "sg:city":"Byford",
    "sg:classifiers":[
        {
            "category":"Building & Trades",
            "subcategory":"Construction",
            "type":"Services"
        }
    ],
    "sg:phone":"+61 417 186 149",
    "sg:postcode":"6122",
    "sg:province":"WA",
    "sg:tags":[
        "fencing",
        "contractor"
    ],
    "wof:name":"Byford Fencing",
    "wof:placetype":"venue"
},
  "geometry": {"coordinates":[116.008300781,-32.2232322693],"type":"Point"}
}