{
  "type": "Feature",
  "properties": {
    "addr:full":"34 - 36 Bassendean Rd Bayswater WA 6053",
    "addr:housenumber":"36",
    "addr:postcode":"6053",
    "addr:street":"Bassendean Rd",
    "iso:country":"AU",
    "sg:address":"34 - 36 Bassendean Rd",
    "sg:city":"Bayswater",
    "sg:classifiers":[
        {
            "category":"Wholesale",
            "subcategory":"Auto Parts",
            "type":"Manufacturing & Wholesale Goods"
        }
    ],
    "sg:phone":"+61 8 9471 1588",
    "sg:postcode":"6053",
    "sg:province":"WA",
    "sg:tags":[
        "recyclers"
    ],
    "wof:name":"Wright Auto Wrecking",
    "wof:placetype":"venue"
},
  "geometry": {"coordinates":[115.921546936,-31.914899826],"type":"Point"}
}