{
  "type": "Feature",
  "properties": {
    "addr:full":"28 Libya Crs Allambie Heights NSW 2100",
    "addr:housenumber":"28",
    "addr:postcode":"2100",
    "addr:street":"Libya Crs",
    "iso:country":"AU",
    "sg:address":"28 Libya Crs",
    "sg:city":"Allambie Heights",
    "sg:classifiers":[
        {
            "category":"Education",
            "subcategory":"Kindergarten",
            "type":"Public Place"
        }
    ],
    "sg:phone":"+61 2 9905 4896",
    "sg:postcode":"2100",
    "sg:province":"NSW",
    "sg:tags":[
        "pre-schools"
    ],
    "wof:name":"Allambie Heights Kindergarten",
    "wof:placetype":"venue"
},
  "geometry": {"coordinates":[151.251556397,-33.7655906677],"type":"Point"}
}