{
  "type": "Feature",
  "properties": {
    "addr:full":"Carindale Shopping Centre Cnr Creek & Old Clevelan Carindale QLD 4152",
    "addr:postcode":"4152",
    "addr:street":"Cnr",
    "iso:country":"AU",
    "sg:address":"Carindale Shopping Centre Cnr Creek & Old Clevelan",
    "sg:city":"Carindale",
    "sg:classifiers":[
        {
            "category":"Health Services",
            "subcategory":"Doctor",
            "type":"Services"
        }
    ],
    "sg:phone":"+61 7 3398 9798",
    "sg:postcode":"4152",
    "sg:province":"QLD",
    "sg:tags":[
        "podiatrist"
    ],
    "wof:name":"Cox & Nielsen Podiatry Group",
    "wof:placetype":"venue"
},
  "geometry": {"coordinates":[153.10421752900001,-27.5004520416],"type":"Point"}
}