{
  "type": "Feature",
  "properties": {
    "addr:full":"Shop F110, 1st Floor, Karrinyup Shopng Cntr Karrinyup WA 6018",
    "addr:housenumber":"f110;floor karrinyup",
    "addr:postcode":"6018",
    "iso:country":"AU",
    "sg:address":"Shop F110, 1st Floor, Karrinyup Shopng Cntr",
    "sg:city":"Karrinyup",
    "sg:classifiers":[
        {
            "category":"Shopping",
            "subcategory":"Jewelry",
            "type":"Retail Goods"
        }
    ],
    "sg:phone":"+61 8 9244 3638",
    "sg:postcode":"6018",
    "sg:province":"WA",
    "sg:tags":[
        "jeweller"
    ],
    "wof:name":"Showcase Jewellers Karrinyup",
    "wof:placetype":"venue"
},
  "geometry": {"coordinates":[115.77133178699999,-31.8735256195],"type":"Point"}
}