{
  "type": "Feature",
  "properties": {
    "iso:country":"AU",
    "sg:address":"32 Melba Pl",
    "sg:city":"St Helens Park",
    "sg:classifiers":[
        {
            "category":"Professional",
            "subcategory":"Accounting & Tax Preparation",
            "type":"Services"
        }
    ],
    "sg:phone":"+61 2 4621 3542",
    "sg:postcode":"2560",
    "sg:province":"NSW",
    "sg:tags":[
        "bookkeeping"
    ],
    "wof:name":"Bongoo Pty Ltd",
    "wof:placetype":"venue"
},
  "geometry": {"coordinates":[150.80848693900001,-34.1011390686],"type":"Point"}
}