{
  "type": "Feature",
  "properties": {
    "iso:country":"AU",
    "sg:address":"55 Montague St",
    "sg:city":"North Wollongong",
    "sg:classifiers":[
        {
            "category":"Retail",
            "subcategory":"Auto Repair",
            "type":"Services"
        }
    ],
    "sg:phone":"+61 2 4226 4911",
    "sg:postcode":"2500",
    "sg:province":"NSW",
    "sg:tags":[
        "clutch",
        "brake"
    ],
    "wof:name":"Brake Smart",
    "wof:placetype":"venue"
},
  "geometry": {"coordinates":[150.895554,-34.401203],"type":"Point"}
}