{
  "type": "Feature",
  "properties": {
    "addr:full":"24a Dudley St Tamarama NSW 2026",
    "addr:housenumber":"24a",
    "addr:postcode":"2026",
    "addr:street":"Dudley St",
    "iso:country":"AU",
    "sg:address":"24a Dudley St",
    "sg:city":"Tamarama",
    "sg:classifiers":[
        {
            "category":"Professional",
            "subcategory":"Art Services",
            "type":"Services"
        }
    ],
    "sg:phone":"+61 2 9660 4066",
    "sg:postcode":"2026",
    "sg:province":"NSW",
    "sg:tags":[
        "arranger",
        "music",
        "composer"
    ],
    "wof:name":"Fresh Music Pty Ltd",
    "wof:placetype":"venue"
},
  "geometry": {"coordinates":[151.271194458,-33.8961906433],"type":"Point"}
}