{
  "type": "Feature",
  "properties": {
    "iso:country":"AU",
    "sg:address":"102 Reservoir Rd",
    "sg:city":"Modbury",
    "sg:classifiers":[
        {
            "category":"Health Services",
            "subcategory":"Dentist",
            "type":"Services"
        }
    ],
    "sg:phone":"+61 8 8265 3220",
    "sg:postcode":"5092",
    "sg:province":"SA",
    "wof:name":"Verco Bill Dr",
    "wof:placetype":"venue"
},
  "geometry": {"coordinates":[138.688034058,-34.8336868286],"type":"Point"}
}