{
  "type": "Feature",
  "properties": {
    "iso:country":"AU",
    "sg:address":"25 Lawley St",
    "sg:city":"Dicky Beach",
    "sg:classifiers":[
        {
            "category":"Professional",
            "subcategory":"Art Services",
            "type":"Services"
        }
    ],
    "sg:phone":"+61 7 5492 7749",
    "sg:postcode":"4551",
    "sg:province":"QLD",
    "sg:tags":[
        "decorator",
        "painter"
    ],
    "wof:name":"Mastro Painting Service",
    "wof:placetype":"venue"
},
  "geometry": {"coordinates":[153.133544922,-26.7874317169],"type":"Point"}
}