{
  "type": "Feature",
  "properties": {
    "addr:full":"Shop 2 Gaymark La Penrith NSW 2750",
    "addr:housenumber":"shop 2",
    "addr:postcode":"2750",
    "addr:street":"Gaymark La",
    "iso:country":"AU",
    "sg:address":"Shop 2 Gaymark La",
    "sg:city":"Penrith",
    "sg:classifiers":[
        {
            "category":"Personal",
            "subcategory":"Beauty Salon",
            "type":"Services"
        }
    ],
    "sg:phone":"+61 2 4731 6090",
    "sg:postcode":"2750",
    "sg:province":"NSW",
    "sg:tags":[
        "hairdresser"
    ],
    "wof:name":"Penrith Perfects Hair & Beauty",
    "wof:placetype":"venue"
},
  "geometry": {"coordinates":[150.69656372099999,-33.7523193359],"type":"Point"}
}