{
  "type": "Feature",
  "properties": {
    "addr:full":"11 Upper Rosemount Rd Nambour QLD 4560",
    "addr:housenumber":"11",
    "addr:postcode":"4560",
    "addr:street":"Upper Rosemount Rd",
    "iso:country":"AU",
    "sg:address":"11 Upper Rosemount Rd",
    "sg:city":"Nambour",
    "sg:classifiers":[
        {
            "category":"Building & Trades",
            "subcategory":"Construction",
            "type":"Services"
        }
    ],
    "sg:phone":"+61 414 986 053",
    "sg:postcode":"4560",
    "sg:province":"QLD",
    "sg:tags":[
        "contractor"
    ],
    "wof:name":"N C Whitney",
    "wof:placetype":"venue"
},
  "geometry": {"coordinates":[152.98971557600001,-26.6264266968],"type":"Point"}
}