{
  "type": "Feature",
  "properties": {
    "addr:full":"Unit 2/ 218 Crown St Darlinghurst NSW 2010",
    "addr:housenumber":"/ 218",
    "addr:postcode":"2010",
    "addr:street":"Crown St",
    "iso:country":"AU",
    "sg:address":"Unit 2/ 218 Crown St",
    "sg:city":"Darlinghurst",
    "sg:classifiers":[
        {
            "category":"Professional",
            "subcategory":"Research",
            "type":"Services"
        }
    ],
    "sg:phone":"+61 2 9332 4399",
    "sg:postcode":"2010",
    "sg:province":"NSW",
    "sg:tags":[
        "market"
    ],
    "wof:name":"Instinct & Reason",
    "wof:placetype":"venue"
},
  "geometry": {"coordinates":[151.215744019,-33.8776130676],"type":"Point"}
}