{
  "type": "Feature",
  "properties": {
    "addr:full":"189 Vienna Rd Alexandra Hills QLD 4161",
    "addr:housenumber":"189",
    "addr:postcode":"4161",
    "addr:street":"Vienna Rd",
    "iso:country":"AU",
    "sg:address":"189 Vienna Rd",
    "sg:city":"Alexandra Hills",
    "sg:classifiers":[
        {
            "category":"Health Services",
            "subcategory":"Doctor",
            "type":"Services"
        }
    ],
    "sg:phone":"+61 7 3824 3882",
    "sg:postcode":"4161",
    "sg:province":"QLD",
    "sg:tags":[
        "medical",
        "practitioner"
    ],
    "wof:name":"Best Ruth Dr",
    "wof:placetype":"venue"
},
  "geometry": {"coordinates":[153.22425842300001,-27.5432281494],"type":"Point"}
}