{
  "type": "Feature",
  "properties": {
    "addr:full":"32 Ashover Rd Rocklea QLD 4106",
    "addr:housenumber":"32",
    "addr:postcode":"4106",
    "addr:street":"Ashover Rd",
    "iso:country":"AU",
    "sg:address":"32 Ashover Rd",
    "sg:city":"Rocklea",
    "sg:classifiers":[
        {
            "category":"Building & Trades",
            "subcategory":"Cleaning & Sanitation",
            "type":"Services"
        }
    ],
    "sg:phone":"+61 7 3277 8961",
    "sg:postcode":"4106",
    "sg:province":"QLD",
    "sg:tags":[
        "abrasive",
        "blasting"
    ],
    "sg:website":"http://www.rgmmaintenance.com.au",
    "wof:name":"Archerfield Sandblasting",
    "wof:placetype":"venue"
},
  "geometry": {"coordinates":[153.00813293499999,-27.56001091],"type":"Point"}
}