{
  "type": "Feature",
  "properties": {
    "addr:full":"Hamilton Rd Warwick QLD 4370",
    "addr:postcode":"4370",
    "addr:street":"Hamilton Rd",
    "iso:country":"AU",
    "sg:address":"Hamilton Rd",
    "sg:city":"Warwick",
    "sg:classifiers":[
        {
            "category":"Building & Trades",
            "subcategory":"Cleaning & Sanitation",
            "type":"Services"
        }
    ],
    "sg:phone":"+61 423 463 565",
    "sg:postcode":"4370",
    "sg:province":"QLD",
    "sg:tags":[
        "abrasive",
        "blasting"
    ],
    "wof:name":"Lightening Fast Mobile Sandblast",
    "wof:placetype":"venue"
},
  "geometry": {"coordinates":[152.041915894,-28.2191314697],"type":"Point"}
}