{
  "type": "Feature",
  "properties": {
    "addr:full":"Burke Ward Hall Gypsum St Broken Hill NSW 2880",
    "addr:postcode":"2880",
    "addr:street":"Gypsum St",
    "iso:country":"AU",
    "sg:address":"Burke Ward Hall Gypsum St",
    "sg:city":"Broken Hill",
    "sg:classifiers":[
        {
            "category":"Health Services",
            "subcategory":"Health Practitioner",
            "type":"Services"
        }
    ],
    "sg:phone":"+61 8 8088 2228",
    "sg:postcode":"2880",
    "sg:province":"NSW",
    "sg:tags":[
        "consultant",
        "conservation",
        "hearing"
    ],
    "wof:name":"Broken Hill & District Hearing Resource Centre Inc",
    "wof:placetype":"venue"
},
  "geometry": {"coordinates":[141.44674682600001,-31.9690208435],"type":"Point"}
}