{
  "type": "Feature",
  "properties": {
    "addr:full":"Unit 4, 44 Hector St Osborne Park WA 6017",
    "addr:housenumber":"44",
    "addr:postcode":"6017",
    "addr:street":"Hector St",
    "iso:country":"AU",
    "sg:address":"Unit 4, 44 Hector St",
    "sg:city":"Osborne Park",
    "sg:classifiers":[
        {
            "category":"Retail",
            "subcategory":"Auto Repair",
            "type":"Services"
        }
    ],
    "sg:phone":"+61 8 9244 4904",
    "sg:postcode":"6017",
    "sg:province":"WA",
    "sg:tags":[
        "beater",
        "painter",
        "panel"
    ],
    "wof:name":"BP Panel & Paint",
    "wof:placetype":"venue"
},
  "geometry": {"coordinates":[115.822532654,-31.9043045044],"type":"Point"}
}