{
  "type": "Feature",
  "properties": {
    "addr:full":"42 Princes Hwy Nowa Nowa VIC 3887",
    "addr:housenumber":"42",
    "addr:postcode":"3887",
    "addr:street":"Princes Hwy",
    "iso:country":"AU",
    "sg:address":"42 Princes Hwy",
    "sg:city":"Nowa Nowa",
    "sg:classifiers":[
        {
            "category":"Arts & Performance",
            "subcategory":"Art Gallery",
            "type":"Entertainment"
        }
    ],
    "sg:phone":"+61 3 5155 7247",
    "sg:postcode":"3887",
    "sg:province":"VIC",
    "wof:name":"Ramsdell Gallery",
    "wof:placetype":"venue"
},
  "geometry": {"coordinates":[148.10418701200001,-37.7326202393],"type":"Point"}
}