{
  "type": "Feature",
  "properties": {
    "iso:country":"AU",
    "sg:address":"Rockingham Shopping Centre Council Ave",
    "sg:city":"Rockingham",
    "sg:classifiers":[
        {
            "category":"Shopping",
            "subcategory":"Shoes",
            "type":"Retail Goods"
        }
    ],
    "sg:phone":"+61 8 9527 3502",
    "sg:postcode":"6168",
    "sg:province":"WA",
    "sg:tags":[
        "footwear"
    ],
    "wof:name":"Betts",
    "wof:placetype":"venue"
},
  "geometry": {"coordinates":[115.744003,-32.291077],"type":"Point"}
}