{
  "type": "Feature",
  "properties": {
    "addr:full":"Parkers Rd Parkdale VIC 3195",
    "addr:postcode":"3195",
    "addr:street":"Parkers Rd",
    "iso:country":"AU",
    "sg:address":"Parkers Rd",
    "sg:city":"Parkdale",
    "sg:classifiers":[
        {
            "category":"Professional",
            "subcategory":"Detective & Security Services",
            "type":"Services"
        }
    ],
    "sg:phone":"+61 3 9580 9411",
    "sg:postcode":"3195",
    "sg:province":"VIC",
    "sg:tags":[
        "consultant",
        "system"
    ],
    "wof:name":"Crowded House Security Pty Ltd",
    "wof:placetype":"venue"
},
  "geometry": {"coordinates":[145.080154419,-37.9914207458],"type":"Point"}
}