{
  "type": "Feature",
  "properties": {
    "addr:full":"Princes Hwy Monarto SA 5254",
    "addr:postcode":"5254",
    "addr:street":"Princes Hwy",
    "iso:country":"AU",
    "sg:address":"Princes Hwy",
    "sg:city":"Monarto",
    "sg:classifiers":[
        {
            "category":"Park",
            "subcategory":"County",
            "type":"Public Place"
        }
    ],
    "sg:phone":"+61 8 8267 3255",
    "sg:postcode":"5254",
    "sg:province":"SA",
    "sg:tags":[
        "sanctuary",
        "zoos",
        "animal"
    ],
    "wof:name":"Monarto Zoological Park",
    "wof:placetype":"venue"
},
  "geometry": {"coordinates":[139.056884766,-35.1109848022],"type":"Point"}
}