{
  "type": "Feature",
  "properties": {
    "addr:full":"Shop 9, 129 Pakington St Geelong West VIC 3218",
    "addr:housenumber":"shop 9",
    "addr:postcode":"129;3218",
    "addr:street":"Pakington St",
    "iso:country":"AU",
    "sg:address":"Shop 9, 129 Pakington St",
    "sg:city":"Geelong West",
    "sg:classifiers":[
        {
            "category":"Personal",
            "subcategory":"Beauty Salon",
            "type":"Services"
        }
    ],
    "sg:phone":"+61 3 5222 1242",
    "sg:postcode":"3218",
    "sg:province":"VIC",
    "sg:tags":[
        "hairdresser"
    ],
    "wof:name":"Better Trends For Hair",
    "wof:placetype":"venue"
},
  "geometry": {"coordinates":[144.34840393100001,-38.1393585205],"type":"Point"}
}