{
  "type": "Feature",
  "properties": {
    "iso:country":"AU",
    "sg:address":"Hainsworth St",
    "sg:city":"Westmead",
    "sg:classifiers":[
        {
            "category":"Health Services",
            "subcategory":"Health Practitioner",
            "type":"Services"
        }
    ],
    "sg:phone":"+61 2 9845 0793",
    "sg:postcode":"2145",
    "sg:province":"NSW",
    "sg:tags":[
        "pathologist",
        "speech"
    ],
    "wof:name":"Speech-Language-Learning Centre",
    "wof:placetype":"venue"
},
  "geometry": {"coordinates":[150.99269104000001,-33.8024177551],"type":"Point"}
}