{
  "type": "Feature",
  "properties": {
    "addr:full":"Lvl 5, 385 Bourke Melbourne VIC 3000",
    "addr:housenumber":"385",
    "addr:postcode":"3000",
    "addr:street":"Bourke",
    "iso:country":"AU",
    "sg:address":"Lvl 5, 385",
    "sg:city":"Bourke Melbourne",
    "sg:classifiers":[
        {
            "category":"Banks & Credit Unions",
            "subcategory":"Financial Services",
            "type":"Services"
        }
    ],
    "sg:phone":"+61 1800 811 446",
    "sg:postcode":"3000",
    "sg:province":"VIC",
    "sg:tags":[
        "financier"
    ],
    "wof:name":"CBFC Limited",
    "wof:placetype":"venue"
},
  "geometry": {"coordinates":[144.963134766,-37.8143882751],"type":"Point"}
}