{
  "type": "Feature",
  "properties": {
    "iso:country":"AU",
    "sg:address":"PO Box 356",
    "sg:city":"Ormeau",
    "sg:classifiers":[
        {
            "category":"Government",
            "subcategory":"Fire Station",
            "type":"Public Place"
        }
    ],
    "sg:phone":"+61 1300 731 800",
    "sg:postcode":"4208",
    "sg:province":"QLD",
    "sg:tags":[
        "equipment",
        "protection",
        "consultant"
    ],
    "wof:name":"Pacific Helmets Australia Pty Ltd",
    "wof:placetype":"venue"
},
  "geometry": {"coordinates":[153.244216919,-27.7652397156],"type":"Point"}
}