{
  "type": "Feature",
  "properties": {
    "iso:country":"AU",
    "sg:address":"Shop 17a Riverton Forum Shopping Centre",
    "sg:city":"Riverton",
    "sg:classifiers":[
        {
            "category":"Personal",
            "subcategory":"Beauty Salon",
            "type":"Services"
        }
    ],
    "sg:phone":"+61 8 9259 0001",
    "sg:postcode":"6148",
    "sg:province":"WA",
    "sg:tags":[
        "hairdresser"
    ],
    "wof:name":"Players Mens Hair Stylists",
    "wof:placetype":"venue"
},
  "geometry": {"coordinates":[115.862396,-32.042229],"type":"Point"}
}