{
  "type": "Feature",
  "properties": {
    "addr:full":"Cnr Ring Rd & Trewin St Ballarat VIC 3350",
    "addr:postcode":"3350",
    "addr:street":"Cnr Ring Rd & Trewin St",
    "iso:country":"AU",
    "sg:address":"Cnr Ring Rd & Trewin St",
    "sg:city":"Ballarat",
    "sg:classifiers":[
        {
            "category":"Building & Trades",
            "subcategory":"Construction",
            "type":"Services"
        }
    ],
    "sg:phone":"+61 3 5338 2011",
    "sg:postcode":"3350",
    "sg:province":"VIC",
    "sg:tags":[
        "joinery"
    ],
    "wof:name":"McEldrew's Joinery Pty Ltd",
    "wof:placetype":"venue"
},
  "geometry": {"coordinates":[143.797012,-37.546509],"type":"Point"}
}