{
  "type": "Feature",
  "properties": {
    "addr:full":"PO Box 414 Kyogle NSW 2474",
    "addr:postcode":"2474",
    "iso:country":"AU",
    "sg:address":"PO Box 414",
    "sg:city":"Kyogle",
    "sg:classifiers":[
        {
            "category":"Arena",
            "subcategory":"Sports Club",
            "type":"Entertainment"
        }
    ],
    "sg:phone":"+61 1300 888 469",
    "sg:postcode":"2474",
    "sg:province":"NSW",
    "sg:tags":[
        "tour",
        "holiday"
    ],
    "wof:name":"Mazzers Coaches Pty Ltd",
    "wof:placetype":"venue"
},
  "geometry": {"coordinates":[153.03839111299999,-28.8555545807],"type":"Point"}
}