{
  "type": "Feature",
  "properties": {
    "addr:full":"West Busselton Shopng Cntr 170 Bussell Hwy Busselton WA 6280",
    "addr:housenumber":"170",
    "addr:postcode":"6280",
    "addr:street":"West;Bussell Hwy",
    "iso:country":"AU",
    "sg:address":"West Busselton Shopng Cntr 170 Bussell Hwy",
    "sg:city":"Busselton",
    "sg:classifiers":[
        {
            "category":"Food & Beverages",
            "subcategory":"Specialty",
            "type":"Retail Goods"
        }
    ],
    "sg:phone":"+61 8 9752 3394",
    "sg:postcode":"6280",
    "sg:province":"WA",
    "sg:tags":[
        "delicacy"
    ],
    "wof:name":"Wraggs Quality Butchers",
    "wof:placetype":"venue"
},
  "geometry": {"coordinates":[115.258460998,-33.6625404358],"type":"Point"}
}