{
  "type": "Feature",
  "properties": {
    "iso:country":"AU",
    "sg:address":"Camp Rd",
    "sg:city":"Campbellfield",
    "sg:classifiers":[
        {
            "category":"Personal",
            "subcategory":"Massage",
            "type":"Services"
        }
    ],
    "sg:phone":"+61 416 273 452",
    "sg:postcode":"3061",
    "sg:province":"VIC",
    "sg:tags":[
        "therapy"
    ],
    "wof:name":"Bella Donna Massage & Beauty",
    "wof:placetype":"venue"
},
  "geometry": {"coordinates":[144.956268311,-37.6661987305],"type":"Point"}
}