{
  "type": "Feature",
  "properties": {
    "addr:full":"8 Campbell St Trangie NSW 2823",
    "addr:housenumber":"8",
    "addr:postcode":"2823",
    "addr:street":"Campbell St",
    "iso:country":"AU",
    "sg:address":"8 Campbell St",
    "sg:city":"Trangie",
    "sg:classifiers":[
        {
            "category":"Retail",
            "subcategory":"Auto Repair",
            "type":"Services"
        }
    ],
    "sg:phone":"+61 2 6888 7799",
    "sg:postcode":"2823",
    "sg:province":"NSW",
    "sg:tags":[
        "automotive",
        "air conditioning"
    ],
    "wof:name":"Des Davey Automotive & Farm Machinery Air Conditioning",
    "wof:placetype":"venue"
},
  "geometry": {"coordinates":[147.98240661599999,-32.0349388123],"type":"Point"}
}