{
  "type": "Feature",
  "properties": {
    "addr:full":"99 Wallpark Ave Blacktown NSW 2148",
    "addr:housenumber":"99",
    "addr:postcode":"2148",
    "addr:street":"Wallpark Ave",
    "iso:country":"AU",
    "sg:address":"99 Wallpark Ave",
    "sg:city":"Blacktown",
    "sg:classifiers":[
        {
            "category":"Professional",
            "subcategory":"Management & Consulting",
            "type":"Services"
        }
    ],
    "sg:phone":"+61 2 9622 7152",
    "sg:postcode":"2148",
    "sg:province":"NSW",
    "sg:tags":[
        "consultant"
    ],
    "wof:name":"Auto-Qual Pty Ltd",
    "wof:placetype":"venue"
},
  "geometry": {"coordinates":[150.92153930699999,-33.7757606506],"type":"Point"}
}