{
  "type": "Feature",
  "properties": {
    "addr:full":"Ste 3/ 1a Knox La Double Bay NSW 2028",
    "addr:housenumber":"/ 1a",
    "addr:postcode":"2028",
    "addr:street":"La",
    "iso:country":"AU",
    "sg:address":"Ste 3/ 1a Knox La",
    "sg:city":"Double Bay",
    "sg:classifiers":[
        {
            "category":"Health Services",
            "subcategory":"Health Practitioner",
            "type":"Services"
        }
    ],
    "sg:phone":"+61 417 468 035",
    "sg:postcode":"2028",
    "sg:province":"NSW",
    "sg:tags":[
        "psychologist"
    ],
    "wof:name":"Bentley Gabriella",
    "wof:placetype":"venue"
},
  "geometry": {"coordinates":[151.24282836899999,-33.8772506714],"type":"Point"}
}