{
  "type": "Feature",
  "properties": {
    "addr:full":"Ste3a/ 350 High St Maitland NSW 2320",
    "addr:housenumber":"350",
    "addr:postcode":"2320",
    "addr:street":"High St",
    "iso:country":"AU",
    "sg:address":"Ste3a/ 350 High St",
    "sg:city":"Maitland",
    "sg:classifiers":[
        {
            "category":"Building & Trades",
            "subcategory":"Construction",
            "type":"Services"
        }
    ],
    "sg:phone":"+61 2 4933 0001",
    "sg:postcode":"2320",
    "sg:province":"NSW",
    "sg:tags":[
        "contractor"
    ],
    "wof:name":"Capital Homes",
    "wof:placetype":"venue"
},
  "geometry": {"coordinates":[151.553466797,-32.7311286926],"type":"Point"}
}