{
  "type": "Feature",
  "properties": {
    "addr:full":"11th Floor Suite 6 141 Queen St Brisbane QLD 4001",
    "addr:housenumber":"141",
    "addr:postcode":"4001",
    "addr:street":"Queen St",
    "iso:country":"AU",
    "sg:address":"11th Floor Suite 6 141 Queen St",
    "sg:city":"Brisbane",
    "sg:classifiers":[
        {
            "category":"Health Services",
            "subcategory":"Dentist",
            "type":"Services"
        }
    ],
    "sg:phone":"+61 7 3221 8611",
    "sg:postcode":"4001",
    "sg:province":"QLD",
    "wof:name":"MacMillan Andrew",
    "wof:placetype":"venue"
},
  "geometry": {"coordinates":[153.02565002399999,-27.4694957733],"type":"Point"}
}