{
  "type": "Feature",
  "properties": {
    "iso:country":"AU",
    "sg:address":"William St",
    "sg:city":"Gol Gol",
    "sg:classifiers":[
        {
            "category":"Education",
            "subcategory":"School",
            "type":"Public Place"
        }
    ],
    "sg:phone":"+61 3 5024 8401",
    "sg:postcode":"2738",
    "sg:province":"NSW",
    "sg:tags":[
        "state",
        "except",
        "nsw"
    ],
    "wof:name":"Gol Gol Public School",
    "wof:placetype":"venue"
},
  "geometry": {"coordinates":[142.226837,-34.179508],"type":"Point"}
}