{
  "type": "Feature",
  "properties": {
    "iso:country":"AU",
    "sg:address":"Tristania St",
    "sg:city":"Doveton",
    "sg:classifiers":[
        {
            "category":"Professional",
            "subcategory":"Art Services",
            "type":"Services"
        }
    ],
    "sg:phone":"+61 412 737 462",
    "sg:postcode":"3177",
    "sg:province":"VIC",
    "sg:tags":[
        "decorator",
        "painter"
    ],
    "wof:name":"Ian Wickson Painter & Decorator",
    "wof:placetype":"venue"
},
  "geometry": {"coordinates":[145.24307250999999,-37.9889831543],"type":"Point"}
}