{
  "type": "Feature",
  "properties": {
    "iso:country":"AU",
    "sg:address":"21 Church St",
    "sg:city":"Traralgon",
    "sg:classifiers":[
        {
            "category":"Personal",
            "subcategory":"Beauty Salon",
            "type":"Services"
        }
    ],
    "sg:phone":"+61 3 5174 3580",
    "sg:postcode":"3844",
    "sg:province":"VIC",
    "sg:tags":[
        "hairdresser"
    ],
    "wof:name":"Lorralee Salon",
    "wof:placetype":"venue"
},
  "geometry": {"coordinates":[146.535064697,-38.1969337463],"type":"Point"}
}