{
  "type": "Feature",
  "properties": {
    "addr:full":"28 Carlow Crs Killarney Heights NSW 2087",
    "addr:housenumber":"28",
    "addr:postcode":"2087",
    "addr:street":"Carlow Crs",
    "iso:country":"AU",
    "sg:address":"28 Carlow Crs",
    "sg:city":"Killarney Heights",
    "sg:classifiers":[
        {
            "category":"Building & Trades",
            "subcategory":"Landscaping Services",
            "type":"Services"
        }
    ],
    "sg:phone":"+61 2 9452 3909",
    "sg:postcode":"2087",
    "sg:province":"NSW",
    "sg:tags":[
        "gardener"
    ],
    "wof:name":"Priority One Gardens",
    "wof:placetype":"venue"
},
  "geometry": {"coordinates":[151.217453003,-33.7729492188],"type":"Point"}
}