{
  "type": "Feature",
  "properties": {
    "iso:country":"AU",
    "sg:address":"270 Devonshire St",
    "sg:city":"Surry Hills",
    "sg:classifiers":[
        {
            "category":"Arts & Performance",
            "subcategory":"Art Gallery",
            "type":"Entertainment"
        }
    ],
    "sg:phone":"+61 2 9698 3200",
    "sg:postcode":"2010",
    "sg:province":"NSW",
    "wof:name":"Hughes Ray Gallery",
    "wof:placetype":"venue"
},
  "geometry": {"coordinates":[151.21403503400001,-33.8890266418],"type":"Point"}
}