{
  "type": "Feature",
  "properties": {
    "addr:full":"17 Ribblesdale Crt Joyner QLD 4500",
    "addr:housenumber":"17",
    "addr:postcode":"4500",
    "addr:street":"Ribblesdale Crt",
    "iso:country":"AU",
    "sg:address":"17 Ribblesdale Crt",
    "sg:city":"Joyner",
    "sg:classifiers":[
        {
            "category":"Utilities",
            "subcategory":"Electric",
            "type":"Services"
        }
    ],
    "sg:phone":"+61 419 660 433",
    "sg:postcode":"4500",
    "sg:province":"QLD",
    "sg:tags":[
        "electrical",
        "contractor"
    ],
    "wof:name":"Ross Electrics",
    "wof:placetype":"venue"
},
  "geometry": {"coordinates":[152.93504333499999,-27.2832584381],"type":"Point"}
}