{
  "type": "Feature",
  "properties": {
    "iso:country":"AU",
    "sg:address":"16 Cheshire St",
    "sg:city":"Wagga Wagga",
    "sg:classifiers":[
        {
            "category":"Retail",
            "subcategory":"Auto Repair",
            "type":"Services"
        }
    ],
    "sg:phone":"+61 2 6925 6101",
    "sg:postcode":"2650",
    "sg:province":"NSW",
    "sg:tags":[
        "beater",
        "painter",
        "panel"
    ],
    "wof:name":"Craig Keys Automotive Centre",
    "wof:placetype":"venue"
},
  "geometry": {"coordinates":[147.34681701700001,-35.1243095398],"type":"Point"}
}