{
  "type": "Feature",
  "properties": {
    "iso:country":"AU",
    "sg:address":"suit 29/ 1a Coulson St",
    "sg:city":"Erskineville",
    "sg:classifiers":[
        {
            "category":"Organizations",
            "subcategory":"Professional Association",
            "type":"Services"
        }
    ],
    "sg:phone":"+61 1300 135 426",
    "sg:postcode":"2043",
    "sg:province":"NSW",
    "sg:tags":[
        "web",
        "internet"
    ],
    "wof:name":"Atomic IT Web Solutions",
    "wof:placetype":"venue"
},
  "geometry": {"coordinates":[151.185501,-33.905586],"type":"Point"}
}