{
  "type": "Feature",
  "properties": {
    "iso:country":"AU",
    "sg:address":"92 Queen St",
    "sg:city":"Busselton",
    "sg:classifiers":[
        {
            "category":"Wholesale",
            "subcategory":"Medical Equipment & Supplies",
            "type":"Manufacturing & Wholesale Goods"
        }
    ],
    "sg:phone":"+61 8 9752 1824",
    "sg:postcode":"6280",
    "sg:province":"WA",
    "sg:tags":[
        "aid",
        "care",
        "health",
        "home"
    ],
    "wof:name":"Busselton Pharmacy",
    "wof:placetype":"venue"
},
  "geometry": {"coordinates":[115.344833374,-33.6514778137],"type":"Point"}
}