{
  "type": "Feature",
  "properties": {
    "addr:full":"13 King St Claremont WA 6010",
    "addr:housenumber":"13",
    "addr:postcode":"6010",
    "addr:street":"King St",
    "iso:country":"AU",
    "sg:address":"13 King St",
    "sg:city":"Claremont",
    "sg:classifiers":[
        {
            "category":"Bars & Pubs",
            "subcategory":"Biergarten",
            "type":"Food & Drink"
        }
    ],
    "sg:phone":"+61 8 9385 1541",
    "sg:postcode":"6010",
    "sg:province":"WA",
    "sg:tags":[
        "eucalyptus",
        "oil",
        "tree",
        "essential",
        "tea"
    ],
    "wof:name":"The Paperbark Co",
    "wof:placetype":"venue"
},
  "geometry": {"coordinates":[115.789466858,-31.9852218628],"type":"Point"}
}