{
  "type": "Feature",
  "properties": {
    "addr:full":"29 Princess Hwy Littlehampton SA 5250",
    "addr:housenumber":"29",
    "addr:postcode":"5250",
    "addr:street":"Princess Hwy",
    "iso:country":"AU",
    "sg:address":"29 Princess Hwy",
    "sg:city":"Littlehampton",
    "sg:classifiers":[
        {
            "category":"Personal",
            "subcategory":"Day Spa",
            "type":"Services"
        }
    ],
    "sg:phone":"+61 8 8398 3664",
    "sg:postcode":"5250",
    "sg:province":"SA",
    "wof:name":"Adelaide Hills Natural Health & Beauty Centre",
    "wof:placetype":"venue"
},
  "geometry": {"coordinates":[138.876754761,-35.0446548462],"type":"Point"}
}