{
  "type": "Feature",
  "properties": {
    "addr:full":"304- 306 Main North Rd Prospect SA 5082",
    "addr:housenumber":"306",
    "addr:postcode":"5082",
    "addr:street":"Main North Rd",
    "iso:country":"AU",
    "sg:address":"304- 306 Main North Rd",
    "sg:city":"Prospect",
    "sg:classifiers":[
        {
            "category":"Social Services",
            "subcategory":"Child Care",
            "type":"Services"
        }
    ],
    "sg:phone":"+61 8 8342 1929",
    "sg:postcode":"5082",
    "sg:province":"SA",
    "wof:name":"Prospect Early Learning Child Care",
    "wof:placetype":"venue"
},
  "geometry": {"coordinates":[138.6015625,-34.8712615967],"type":"Point"}
}