{
  "type": "Feature",
  "properties": {
    "addr:full":"67 Maynard St Woolloongabba QLD 4102",
    "addr:housenumber":"67",
    "addr:postcode":"4102",
    "addr:street":"Maynard St",
    "iso:country":"AU",
    "sg:address":"67 Maynard St",
    "sg:city":"Woolloongabba",
    "sg:classifiers":[
        {
            "category":"Building & Trades",
            "subcategory":"Construction",
            "type":"Services"
        }
    ],
    "sg:phone":"+61 7 3844 9040",
    "sg:postcode":"4102",
    "sg:province":"QLD",
    "sg:tags":[
        "contractor"
    ],
    "sg:website":"http://www.cutulibuilding.com.au",
    "wof:name":"Cutuli Building And Carpentry Pty Ltd",
    "wof:placetype":"venue"
},
  "geometry": {"coordinates":[153.04640197800001,-27.4948577881],"type":"Point"}
}