{
  "type": "Feature",
  "properties": {
    "addr:full":"68 Cassilis St Coonabarabran NSW 2357",
    "addr:housenumber":"68",
    "addr:postcode":"2357",
    "addr:street":"Cassilis St",
    "iso:country":"AU",
    "sg:address":"68 Cassilis St",
    "sg:city":"Coonabarabran",
    "sg:classifiers":[
        {
            "category":"Professional",
            "subcategory":"Accounting & Tax Preparation",
            "type":"Services"
        }
    ],
    "sg:phone":"+61 2 6842 1744",
    "sg:postcode":"2357",
    "sg:province":"NSW",
    "sg:tags":[
        "accountant",
        "auditor"
    ],
    "wof:name":"Redman Stafford & Partners",
    "wof:placetype":"venue"
},
  "geometry": {"coordinates":[149.27914428700001,-31.2752227783],"type":"Point"}
}