{
  "type": "Feature",
  "properties": {
    "addr:full":"PO Box 4187 Croydon Hills VIC 3136",
    "addr:postcode":"3136",
    "iso:country":"AU",
    "sg:address":"PO Box 4187",
    "sg:city":"Croydon Hills",
    "sg:classifiers":[
        {
            "category":"Building & Trades",
            "subcategory":"Landscaping Services",
            "type":"Services"
        }
    ],
    "sg:phone":"+61 417 381 925",
    "sg:postcode":"3136",
    "sg:province":"VIC",
    "sg:tags":[
        "designer",
        "landscape",
        "contractor"
    ],
    "wof:name":"Enright & Thompson Landscapes",
    "wof:placetype":"venue"
},
  "geometry": {"coordinates":[145.274856567,-37.7743110657],"type":"Point"}
}