{
  "type": "Feature",
  "properties": {
    "iso:country":"AU",
    "sg:address":"Unit 2, 33 Stockton St",
    "sg:city":"Nelson Bay",
    "sg:classifiers":[
        {
            "category":"Health Services",
            "subcategory":"Doctor",
            "type":"Services"
        }
    ],
    "sg:phone":"+61 2 4984 3675",
    "sg:postcode":"2315",
    "sg:province":"NSW",
    "sg:tags":[
        "medical",
        "practitioner"
    ],
    "wof:name":"Mayne Laverty Pathology Collection Centres",
    "wof:placetype":"venue"
},
  "geometry": {"coordinates":[152.143341,-32.723328],"type":"Point"}
}