{
  "type": "Feature",
  "properties": {
    "addr:full":"21 Main Rd Penguin TAS 7316",
    "addr:housenumber":"21",
    "addr:postcode":"7316",
    "addr:street":"Main Rd",
    "iso:country":"AU",
    "sg:address":"21 Main Rd",
    "sg:city":"Penguin",
    "sg:classifiers":[
        {
            "category":"Retail",
            "subcategory":"Auto Repair",
            "type":"Services"
        }
    ],
    "sg:phone":"+61 3 6437 2408",
    "sg:postcode":"7316",
    "sg:province":"TAS",
    "sg:tags":[
        "repairer",
        "motor",
        "engineer"
    ],
    "wof:name":"Jupps Auto Centre",
    "wof:placetype":"venue"
},
  "geometry": {"coordinates":[146.067626953,-41.1088867188],"type":"Point"}
}