{
  "type": "Feature",
  "properties": {
    "addr:full":"1 19 Copeland St Kingswood NSW 2747",
    "addr:housenumber":"19",
    "addr:postcode":"2747",
    "addr:street":"1;Copeland St",
    "iso:country":"AU",
    "sg:address":"1 19 Copeland St",
    "sg:city":"Kingswood",
    "sg:classifiers":[
        {
            "category":"Professional",
            "type":"Services"
        }
    ],
    "sg:phone":"+61 2 4724 7633",
    "sg:postcode":"2747",
    "sg:province":"NSW",
    "sg:tags":[
        "forwarding",
        "agent",
        "transport"
    ],
    "wof:name":"Rex J Andrews Pty Ltd",
    "wof:placetype":"venue"
},
  "geometry": {"coordinates":[150.71702575699999,-33.7547645569],"type":"Point"}
}