{
  "type": "Feature",
  "properties": {
    "addr:full":"37 Newfield St Sunrise Beach QLD 4567",
    "addr:housenumber":"37",
    "addr:postcode":"4567",
    "addr:street":"Newfield St",
    "iso:country":"AU",
    "sg:address":"37 Newfield St",
    "sg:city":"Sunrise Beach",
    "sg:classifiers":[
        {
            "category":"Personal",
            "type":"Services"
        }
    ],
    "sg:phone":"+61 7 5447 3734",
    "sg:postcode":"4567",
    "sg:province":"QLD",
    "sg:tags":[
        "dressmaker"
    ],
    "wof:name":"Powell Denise Dressmaking",
    "wof:placetype":"venue"
},
  "geometry": {"coordinates":[153.10253906200001,-26.4168720245],"type":"Point"}
}