{
  "type": "Feature",
  "properties": {
    "addr:full":"Mt Lindesay Hwy Jimboomba QLD 4280",
    "addr:postcode":"4280",
    "addr:street":"Lindesay Hwy",
    "iso:country":"AU",
    "sg:address":"Mt Lindesay Hwy",
    "sg:city":"Jimboomba",
    "sg:classifiers":[
        {
            "category":"Personal",
            "subcategory":"Beauty Salon",
            "type":"Services"
        }
    ],
    "sg:phone":"+61 7 5546 9665",
    "sg:postcode":"4280",
    "sg:province":"QLD",
    "sg:tags":[
        "hairdresser"
    ],
    "wof:name":"Dyes Hair & Beauty",
    "wof:placetype":"venue"
},
  "geometry": {"coordinates":[153.02891500000001,-27.813429],"type":"Point"}
}