{
  "type": "Feature",
  "properties": {
    "addr:full":"139 Nelson St Wallsend NSW 2287",
    "addr:housenumber":"139",
    "addr:postcode":"2287",
    "addr:street":"Nelson St",
    "iso:country":"AU",
    "sg:address":"139 Nelson St",
    "sg:city":"Wallsend",
    "sg:classifiers":[
        {
            "category":"Travel",
            "subcategory":"Travel Agent",
            "type":"Entertainment"
        }
    ],
    "sg:phone":"+61 2 4951 5444",
    "sg:postcode":"2287",
    "sg:province":"NSW",
    "sg:tags":[
        "consultant"
    ],
    "wof:name":"Harvey World Travel",
    "wof:placetype":"venue"
},
  "geometry": {"coordinates":[151.6693573,-32.9017562866],"type":"Point"}
}