{
  "type": "Feature",
  "properties": {
    "addr:full":"31 Cahors Rd Padstow NSW 2211",
    "addr:housenumber":"31",
    "addr:postcode":"2211",
    "addr:street":"Cahors Rd",
    "iso:country":"AU",
    "sg:address":"31 Cahors Rd",
    "sg:city":"Padstow",
    "sg:classifiers":[
        {
            "category":"Food & Beverages",
            "subcategory":"Bakery",
            "type":"Retail Goods"
        }
    ],
    "sg:phone":"+61 2 9773 5917",
    "sg:postcode":"2211",
    "sg:province":"NSW",
    "sg:tags":[
        "cake",
        "shop",
        "pastry"
    ],
    "wof:name":"Cheesecake Shop The",
    "wof:placetype":"venue"
},
  "geometry": {"coordinates":[151.02723700000001,-33.94735],"type":"Point"}
}