{
  "type": "Feature",
  "properties": {
    "iso:country":"AU",
    "sg:address":"444 Oxley Ave",
    "sg:city":"Redcliffe",
    "sg:classifiers":[
        {
            "category":"Autos & Motor Vehicles",
            "subcategory":"Automobile Sales",
            "type":"Retail Goods"
        }
    ],
    "sg:phone":"+61 7 3000 1000",
    "sg:postcode":"4020",
    "sg:province":"QLD",
    "sg:tags":[
        "car",
        "new"
    ],
    "wof:name":"Torque Ford",
    "wof:placetype":"venue"
},
  "geometry": {"coordinates":[153.109924,-27.229769],"type":"Point"}
}