{
  "type": "Feature",
  "properties": {
    "addr:full":"Lot E19 Nolans Rd Cambrian Hill VIC 3352",
    "addr:housenumber":"e19",
    "addr:postcode":"3352",
    "addr:street":"Nolans Rd",
    "iso:country":"AU",
    "sg:address":"Lot E19 Nolans Rd",
    "sg:city":"Cambrian Hill",
    "sg:classifiers":[
        {
            "category":"Professional",
            "subcategory":"Engineering",
            "type":"Services"
        }
    ],
    "sg:phone":"+61 3 5341 3763",
    "sg:postcode":"3352",
    "sg:province":"VIC",
    "sg:tags":[
        "installation",
        "maintenance",
        "engineer"
    ],
    "wof:name":"Tuddys Engineering",
    "wof:placetype":"venue"
},
  "geometry": {"coordinates":[143.83566300000001,-37.662056],"type":"Point"}
}