{
  "type": "Feature",
  "properties": {
    "addr:full":"Level 4/The Arts Exchange 18 Hickson Rd The Rocks NSW 2000",
    "addr:housenumber":"18",
    "addr:postcode":"2000",
    "addr:street":"Hickson Rd",
    "iso:country":"AU",
    "sg:address":"Level 4/The Arts Exchange 18 Hickson Rd",
    "sg:city":"The Rocks",
    "sg:classifiers":[
        {
            "category":"Shopping",
            "subcategory":"Music",
            "type":"Retail Goods"
        }
    ],
    "sg:phone":"+61 2 9247 4677",
    "sg:postcode":"2000",
    "sg:province":"NSW",
    "sg:tags":[
        "store"
    ],
    "wof:name":"Australian Music Centre Ltd",
    "wof:placetype":"venue"
},
  "geometry": {"coordinates":[151.20570373499999,-33.8565406799],"type":"Point"}
}