{
  "type": "Feature",
  "properties": {
    "iso:country":"AU",
    "sg:address":"27 Hutchinson St",
    "sg:city":"Mt Barker",
    "sg:classifiers":[
        {
            "category":"Education",
            "subcategory":"Junior College",
            "type":"Public Place"
        }
    ],
    "sg:phone":"+61 8 8398 3983",
    "sg:postcode":"5251",
    "sg:province":"SA",
    "sg:tags":[
        "wholesaler",
        "school",
        "mfrs",
        "uniform"
    ],
    "wof:name":"The Uniform Shop Manufacturer & Supplier Of Uniforms",
    "wof:placetype":"venue"
},
  "geometry": {"coordinates":[138.85972595199999,-35.0658760071],"type":"Point"}
}