{
  "type": "Feature",
  "properties": {
    "addr:full":"31 Vasey St Bentleigh East VIC 3165",
    "addr:housenumber":"31",
    "addr:postcode":"3165",
    "addr:street":"Vasey St",
    "iso:country":"AU",
    "sg:address":"31 Vasey St",
    "sg:city":"Bentleigh East",
    "sg:classifiers":[
        {
            "category":"Building & Trades",
            "subcategory":"Construction",
            "type":"Services"
        }
    ],
    "sg:phone":"+61 418 506 261",
    "sg:postcode":"3165",
    "sg:province":"VIC",
    "sg:tags":[
        "bricklayer"
    ],
    "wof:name":"All Level Bricklaying",
    "wof:placetype":"venue"
},
  "geometry": {"coordinates":[145.06559753400001,-37.9347076416],"type":"Point"}
}