{
  "type": "Feature",
  "properties": {
    "addr:full":"105 Bangalow Rd Byron Bay NSW 2481",
    "addr:housenumber":"105",
    "addr:postcode":"2481",
    "addr:street":"Bangalow Rd",
    "iso:country":"AU",
    "sg:address":"105 Bangalow Rd",
    "sg:city":"Byron Bay",
    "sg:classifiers":[
        {
            "category":"Shopping",
            "subcategory":"Clothing, Apparel, & Fashions",
            "type":"Retail Goods"
        }
    ],
    "sg:phone":"+61 2 6685 8313",
    "sg:postcode":"2481",
    "sg:province":"NSW",
    "sg:tags":[
        "wholesaler",
        "children's",
        "mfrs",
        "wear"
    ],
    "wof:name":"Zannie",
    "wof:placetype":"venue"
},
  "geometry": {"coordinates":[153.61534118599999,-28.6604194641],"type":"Point"}
}