{
  "type": "Feature",
  "properties": {
    "addr:full":"2154 Mt Glorious Rd Mt Glorious QLD 4520",
    "addr:housenumber":"2154",
    "addr:postcode":"4520",
    "addr:street":"Mt Glorious Rd;Glorious",
    "iso:country":"AU",
    "sg:address":"2154 Mt Glorious Rd",
    "sg:city":"Mt Glorious",
    "sg:classifiers":[
        {
            "category":"Building & Trades",
            "subcategory":"Landscaping Services",
            "type":"Services"
        }
    ],
    "sg:phone":"+61 7 3289 0292",
    "sg:postcode":"4520",
    "sg:province":"QLD",
    "sg:tags":[
        "designer",
        "landscape",
        "contractor"
    ],
    "wof:name":"A Wise Design Sculptures and Features",
    "wof:placetype":"venue"
},
  "geometry": {"coordinates":[152.88621499999999,-27.373358],"type":"Point"}
}