{
  "type": "Feature",
  "properties": {
    "addr:full":"8 Taylors St Yarraville VIC 3013",
    "addr:housenumber":"8",
    "addr:postcode":"3013",
    "addr:street":"Taylors St",
    "iso:country":"AU",
    "sg:address":"8 Taylors St",
    "sg:city":"Yarraville",
    "sg:classifiers":[
        {
            "category":"Government",
            "subcategory":"Fire Station",
            "type":"Public Place"
        }
    ],
    "sg:phone":"+61 1300 131 557",
    "sg:postcode":"3013",
    "sg:province":"VIC",
    "sg:tags":[
        "equipment",
        "protection",
        "consultant"
    ],
    "wof:name":"Barricade Fire Protection Pty Ltd",
    "wof:placetype":"venue"
},
  "geometry": {"coordinates":[144.896606445,-37.8211326599],"type":"Point"}
}