{
  "type": "Feature",
  "properties": {
    "iso:country":"AU",
    "sg:address":"205 Rocky Point Rd",
    "sg:city":"Ramsgate",
    "sg:classifiers":[
        {
            "category":"Professional",
            "subcategory":"Engineering",
            "type":"Services"
        }
    ],
    "sg:phone":"+61 2 9529 5188",
    "sg:postcode":"2217",
    "sg:province":"NSW",
    "sg:tags":[
        "consulting",
        "engineer"
    ],
    "wof:name":"Barry Smith Engineers Pty Ltd",
    "wof:placetype":"venue"
},
  "geometry": {"coordinates":[151.136185,-33.983849],"type":"Point"}
}