{
  "type": "Feature",
  "properties": {
    "addr:full":"25 Prescott St Toowoomba QLD 4350",
    "addr:housenumber":"25",
    "addr:postcode":"4350",
    "addr:street":"Prescott St",
    "iso:country":"AU",
    "sg:address":"25 Prescott St",
    "sg:city":"Toowoomba",
    "sg:classifiers":[
        {
            "category":"Home & Garden",
            "subcategory":"Furniture",
            "type":"Retail Goods"
        }
    ],
    "sg:phone":"+61 7 4638 0525",
    "sg:postcode":"4350",
    "sg:province":"QLD",
    "sg:tags":[
        "business"
    ],
    "wof:name":"Capricorn Office Furniture",
    "wof:placetype":"venue"
},
  "geometry": {"coordinates":[151.94734199999999,-27.566162],"type":"Point"}
}