{
  "type": "Feature",
  "properties": {
    "addr:full":"PO Box 220 Holland Park QLD 4121",
    "addr:postcode":"4121",
    "iso:country":"AU",
    "sg:address":"PO Box 220",
    "sg:city":"Holland Park",
    "sg:classifiers":[
        {
            "category":"Communications",
            "subcategory":"Film & Video Production",
            "type":"Services"
        }
    ],
    "sg:phone":"+61 7 3847 9900",
    "sg:postcode":"4121",
    "sg:province":"QLD",
    "sg:tags":[
        "information",
        "recorded",
        "telephone"
    ],
    "wof:name":"Now Hear This!",
    "wof:placetype":"venue"
},
  "geometry": {"coordinates":[153.07435607900001,-27.517780304],"type":"Point"}
}