{
  "type": "Feature",
  "properties": {
    "addr:full":"378 Napier St White Hills VIC 3550",
    "addr:housenumber":"378",
    "addr:postcode":"3550",
    "addr:street":"Napier St",
    "iso:country":"AU",
    "sg:address":"378 Napier St",
    "sg:city":"White Hills",
    "sg:classifiers":[
        {
            "category":"Wholesale",
            "subcategory":"Auto Parts",
            "type":"Manufacturing & Wholesale Goods"
        }
    ],
    "sg:phone":"+61 3 5444 1448",
    "sg:postcode":"3550",
    "sg:province":"VIC",
    "sg:tags":[
        "recyclers"
    ],
    "wof:name":"All Premium Parts",
    "wof:placetype":"venue"
},
  "geometry": {"coordinates":[144.29847717300001,-36.739982605],"type":"Point"}
}