{
  "type": "Feature",
  "properties": {
    "addr:full":"14 Perry St Matraville NSW 2036",
    "addr:housenumber":"14",
    "addr:postcode":"2036",
    "addr:street":"Perry St",
    "iso:country":"AU",
    "sg:address":"14 Perry St",
    "sg:city":"Matraville",
    "sg:classifiers":[
        {
            "category":"Manufacturing",
            "subcategory":"Furniture",
            "type":"Manufacturing & Wholesale Goods"
        }
    ],
    "sg:phone":"+61 2 9316 9755",
    "sg:postcode":"2036",
    "sg:province":"NSW",
    "sg:tags":[
        "builder",
        "designer",
        "custom"
    ],
    "wof:name":"Lewis & Lewis",
    "wof:placetype":"venue"
},
  "geometry": {"coordinates":[151.22268676799999,-33.9592247009],"type":"Point"}
}