{
  "type": "Feature",
  "properties": {
    "addr:full":"144 McCredie Rd Smithfield NSW 2164",
    "addr:housenumber":"144",
    "addr:postcode":"2164",
    "addr:street":"Mccredie Rd",
    "iso:country":"AU",
    "sg:address":"144 McCredie Rd",
    "sg:city":"Smithfield",
    "sg:classifiers":[
        {
            "category":"Manufacturing",
            "subcategory":"Paper Products",
            "type":"Manufacturing & Wholesale Goods"
        }
    ],
    "sg:phone":"+61 2 9681 5500",
    "sg:postcode":"2164",
    "sg:province":"NSW",
    "sg:tags":[
        "box",
        "fibre",
        "carton",
        "cardboard"
    ],
    "wof:name":"Carter Holt Harvey",
    "wof:placetype":"venue"
},
  "geometry": {"coordinates":[150.957885742,-33.8498687744],"type":"Point"}
}