{
  "type": "Feature",
  "properties": {
    "iso:country":"AU",
    "sg:address":"17 National Park St",
    "sg:city":"Newcastle West",
    "sg:classifiers":[
        {
            "category":"Arena",
            "subcategory":"Sports Club",
            "type":"Entertainment"
        }
    ],
    "sg:phone":"+61 2 4929 3257",
    "sg:postcode":"2302",
    "sg:province":"NSW",
    "sg:tags":[
        "league",
        "rugby"
    ],
    "wof:name":"Newcastle Rugby League Ltd",
    "wof:placetype":"venue"
},
  "geometry": {"coordinates":[151.761124,-32.927139],"type":"Point"}
}