{
  "type": "Feature",
  "properties": {
    "iso:country":"AU",
    "sg:address":"7 Glendon St",
    "sg:city":"Kingaroy",
    "sg:classifiers":[
        {
            "category":"Professional",
            "subcategory":"Employment Agencies",
            "type":"Services"
        }
    ],
    "sg:phone":"+61 7 4162 7200",
    "sg:postcode":"4610",
    "sg:province":"QLD",
    "wof:name":"South Burnett Jobmatch Association Incorporated",
    "wof:placetype":"venue"
},
  "geometry": {"coordinates":[151.839279175,-26.5399150848],"type":"Point"}
}