{
  "type": "Feature",
  "properties": {
    "addr:full":"43- 63 Lyndhurst Drv Bomaderry NSW 2541",
    "addr:housenumber":"63",
    "addr:postcode":"2541",
    "addr:street":"Lyndhurst Drv",
    "iso:country":"AU",
    "sg:address":"43- 63 Lyndhurst Drv",
    "sg:city":"Bomaderry",
    "sg:classifiers":[
        {
            "category":"Social Services",
            "subcategory":"Child Care",
            "type":"Services"
        }
    ],
    "sg:phone":"+61 2 4423 6230",
    "sg:postcode":"2541",
    "sg:province":"NSW",
    "wof:name":"Lyndhurst Preschool",
    "wof:placetype":"venue"
},
  "geometry": {"coordinates":[150.605377197,-34.8410110474],"type":"Point"}
}