{
  "type": "Feature",
  "properties": {
    "addr:full":"4/ 38 Tennyson Memorial Ave Yeerongpilly QLD 4105",
    "addr:housenumber":"/ 38",
    "addr:postcode":"4105",
    "addr:street":"Memorial Ave",
    "iso:country":"AU",
    "sg:address":"4/ 38 Tennyson Memorial Ave",
    "sg:city":"Yeerongpilly",
    "sg:classifiers":[
        {
            "category":"Professional",
            "subcategory":"Art Services",
            "type":"Services"
        }
    ],
    "sg:phone":"+61 7 3278 1122",
    "sg:postcode":"4105",
    "sg:province":"QLD",
    "sg:tags":[
        "decorator",
        "painter"
    ],
    "wof:name":"Corporate Painting & Maintenance Pty Ltd",
    "wof:placetype":"venue"
},
  "geometry": {"coordinates":[153.01101684599999,-27.5270233154],"type":"Point"}
}