{
  "type": "Feature",
  "properties": {
    "iso:country":"AU",
    "sg:address":"PO Box 4163",
    "sg:city":"Kingston",
    "sg:classifiers":[
        {
            "category":"Building & Trades",
            "subcategory":"Landscaping Services",
            "type":"Services"
        }
    ],
    "sg:phone":"+61 410 900 450",
    "sg:postcode":"2604",
    "sg:province":"ACT",
    "sg:tags":[
        "designer",
        "landscape",
        "contractor"
    ],
    "wof:name":"Caribbean Pools",
    "wof:placetype":"venue"
},
  "geometry": {"coordinates":[149.14822387699999,-35.3175086975],"type":"Point"}
}