{
  "type": "Feature",
  "properties": {
    "addr:full":"596 Geelong Rd Brooklyn VIC 3025",
    "addr:housenumber":"596",
    "addr:postcode":"3025",
    "addr:street":"Geelong Rd",
    "iso:country":"AU",
    "sg:address":"596 Geelong Rd",
    "sg:city":"Brooklyn",
    "sg:classifiers":[
        {
            "category":"Home & Garden",
            "subcategory":"Hardware",
            "type":"Retail Goods"
        }
    ],
    "sg:phone":"+61 3 9318 9888",
    "sg:postcode":"3025",
    "sg:province":"VIC",
    "sg:tags":[
        "pumping",
        "contractor"
    ],
    "wof:name":"Coates Shorco",
    "wof:placetype":"venue"
},
  "geometry": {"coordinates":[144.83758499999999,-37.819733],"type":"Point"}
}