{
  "type": "Feature",
  "properties": {
    "addr:full":"1 Macquarie St Hobart TAS 7000",
    "addr:housenumber":"1",
    "addr:postcode":"7000",
    "addr:street":"Macquarie St",
    "iso:country":"AU",
    "sg:address":"1 Macquarie St",
    "sg:city":"Hobart",
    "sg:classifiers":[
        {
            "category":"Travel",
            "subcategory":"Hotels & Motels",
            "type":"Entertainment"
        }
    ],
    "sg:phone":"+61 3 6235 5355",
    "sg:postcode":"7000",
    "sg:province":"TAS",
    "wof:name":"The Old Woolstore Apartment Hotel",
    "wof:placetype":"venue"
},
  "geometry": {"coordinates":[147.334182739,-42.8791236877],"type":"Point"}
}