{
  "type": "Feature",
  "properties": {
    "addr:full":"20 Darling St Woodend QLD 4305",
    "addr:housenumber":"20",
    "addr:postcode":"4305",
    "addr:street":"Darling St",
    "iso:country":"AU",
    "sg:address":"20 Darling St",
    "sg:city":"Woodend",
    "sg:classifiers":[
        {
            "category":"Professional",
            "subcategory":"Computer Services",
            "type":"Services"
        }
    ],
    "sg:phone":"+61 7 3281 9539",
    "sg:postcode":"4305",
    "sg:province":"QLD",
    "sg:tags":[
        "package",
        "software"
    ],
    "wof:name":"Manufacturing & Management Systems(QLD)",
    "wof:placetype":"venue"
},
  "geometry": {"coordinates":[152.751708984,-27.6146087646],"type":"Point"}
}