{
  "type": "Feature",
  "properties": {
    "addr:full":"63 Lucerne Crs Frankston VIC 3199",
    "addr:housenumber":"63",
    "addr:postcode":"3199",
    "addr:street":"Lucerne Crs",
    "iso:country":"AU",
    "sg:address":"63 Lucerne Crs",
    "sg:city":"Frankston",
    "sg:classifiers":[
        {
            "category":"Building & Trades",
            "subcategory":"Construction",
            "type":"Services"
        }
    ],
    "sg:phone":"+61 412 760 550",
    "sg:postcode":"3199",
    "sg:province":"VIC",
    "sg:tags":[
        "contractor"
    ],
    "sg:website":"http://www.mbav.com.au",
    "wof:name":"Bobbin Constructions",
    "wof:placetype":"venue"
},
  "geometry": {"coordinates":[145.12179565400001,-38.1415710449],"type":"Point"}
}