{
  "type": "Feature",
  "properties": {
    "addr:full":"20 Cordyline Drv Reedy Creek QLD 4227",
    "addr:housenumber":"20",
    "addr:postcode":"4227",
    "addr:street":"Cordyline Drv",
    "iso:country":"AU",
    "sg:address":"20 Cordyline Drv",
    "sg:city":"Reedy Creek",
    "sg:classifiers":[
        {
            "category":"Banks & Credit Unions",
            "subcategory":"Financial Services",
            "type":"Services"
        }
    ],
    "sg:phone":"+61 7 5593 5248",
    "sg:postcode":"4227",
    "sg:province":"QLD",
    "sg:tags":[
        "loan",
        "finance",
        "mortgage"
    ],
    "wof:name":"Harts Consultancy",
    "wof:placetype":"venue"
},
  "geometry": {"coordinates":[153.406936645,-28.1108627319],"type":"Point"}
}