{
  "type": "Feature",
  "properties": {
    "iso:country":"AU",
    "sg:address":"122 Maitland Rd",
    "sg:city":"Islington",
    "sg:classifiers":[
        {
            "category":"Autos & Motor Vehicles",
            "subcategory":"Automobile Sales",
            "type":"Retail Goods"
        }
    ],
    "sg:phone":"+61 2 4969 1722",
    "sg:postcode":"2296",
    "sg:province":"NSW",
    "sg:tags":[
        "equipment",
        "trailer"
    ],
    "wof:name":"ISP",
    "wof:placetype":"venue"
},
  "geometry": {"coordinates":[151.748535156,-32.9157752991],"type":"Point"}
}