{
  "type": "Feature",
  "properties": {
    "iso:country":"AU",
    "sg:address":"12 Trade Pl",
    "sg:city":"Coburg",
    "sg:classifiers":[
        {
            "category":"Building & Trades",
            "subcategory":"Construction",
            "type":"Services"
        }
    ],
    "sg:phone":"+61 450 794 989",
    "sg:postcode":"3058",
    "sg:province":"VIC",
    "sg:tags":[
        "concrete",
        "contractor"
    ],
    "wof:name":"Mascitti Concrete Developments",
    "wof:placetype":"venue"
},
  "geometry": {"coordinates":[144.97369384800001,-37.7244148254],"type":"Point"}
}