{
  "type": "Feature",
  "properties": {
    "iso:country":"AU",
    "sg:address":"136 Bromley Rd",
    "sg:city":"Robinvale",
    "sg:classifiers":[
        {
            "category":"Retail",
            "subcategory":"Auto Repair",
            "type":"Services"
        }
    ],
    "sg:phone":"+61 3 5026 3274",
    "sg:postcode":"3549",
    "sg:province":"VIC",
    "sg:tags":[
        "wheel",
        "balancing",
        "alignment"
    ],
    "wof:name":"Tyrepower",
    "wof:placetype":"venue"
},
  "geometry": {"coordinates":[142.77090454099999,-34.584690094],"type":"Point"}
}