{
  "type": "Feature",
  "properties": {
    "iso:country":"AU",
    "sg:address":"213 Fullarton Rd",
    "sg:city":"Eastwood",
    "sg:classifiers":[
        {
            "category":"Health Services",
            "subcategory":"Health Practitioner",
            "type":"Services"
        }
    ],
    "sg:phone":"+61 8 8373 6634",
    "sg:postcode":"5063",
    "sg:province":"SA",
    "sg:tags":[
        "pathologist",
        "speech"
    ],
    "wof:name":"Buckman Jane",
    "wof:placetype":"venue"
},
  "geometry": {"coordinates":[138.62452697800001,-34.9425315857],"type":"Point"}
}