{
  "type": "Feature",
  "properties": {
    "addr:full":"3 Dalgarno St Williamstown VIC 3016",
    "addr:housenumber":"3",
    "addr:postcode":"3016",
    "addr:street":"Dalgarno St",
    "iso:country":"AU",
    "sg:address":"3 Dalgarno St",
    "sg:city":"Williamstown",
    "sg:classifiers":[
        {
            "category":"Professional",
            "subcategory":"Management & Consulting",
            "type":"Services"
        }
    ],
    "sg:phone":"+61 3 9397 2777",
    "sg:postcode":"3016",
    "sg:province":"VIC",
    "sg:tags":[
        "consultant"
    ],
    "wof:name":"Comad Consulting Pty Ltd",
    "wof:placetype":"venue"
},
  "geometry": {"coordinates":[144.89732360799999,-37.8526153564],"type":"Point"}
}