{
  "type": "Feature",
  "properties": {
    "addr:full":"Shop 3 Sawyers Valley Shopping Centre Sawyers Valley WA 6074",
    "addr:housenumber":"shop 3",
    "addr:postcode":"6074",
    "addr:street":"Sawyers Valley",
    "iso:country":"AU",
    "sg:address":"Shop 3",
    "sg:city":"Sawyers Valley Shopping Centre Sawyers Valley",
    "sg:classifiers":[
        {
            "category":"Fast Food",
            "type":"Food & Drink"
        }
    ],
    "sg:phone":"+61 8 9295 6535",
    "sg:postcode":"6074",
    "sg:province":"WA",
    "sg:tags":[
        "away",
        "take"
    ],
    "wof:name":"Authentic Italian Pizza",
    "wof:placetype":"venue"
},
  "geometry": {"coordinates":[116.204742432,-31.8926029205],"type":"Point"}
}