{
  "type": "Feature",
  "properties": {
    "iso:country":"AU",
    "sg:address":"110 Edward St",
    "sg:city":"Perth",
    "sg:classifiers":[
        {
            "category":"Organizations",
            "subcategory":"Membership Organization",
            "type":"Services"
        }
    ],
    "sg:phone":"+61 8 9228 0200",
    "sg:postcode":"6000",
    "sg:province":"WA",
    "sg:tags":[
        "support",
        "health",
        "organisation"
    ],
    "wof:name":"Mental Illness Fellowship of WA Inc",
    "wof:placetype":"venue"
},
  "geometry": {"coordinates":[115.86888885499999,-31.9472980499],"type":"Point"}
}