{
  "type": "Feature",
  "properties": {
    "addr:full":"14 Lemnos St Nundah QLD 4012",
    "addr:housenumber":"14",
    "addr:postcode":"4012",
    "addr:street":"Lemnos St",
    "iso:country":"AU",
    "sg:address":"14 Lemnos St",
    "sg:city":"Nundah",
    "sg:classifiers":[
        {
            "category":"Shopping",
            "type":"Retail Goods"
        }
    ],
    "sg:phone":"+61 428 441 152",
    "sg:postcode":"4012",
    "sg:province":"QLD",
    "sg:tags":[
        "equipment",
        "safety",
        "accessory"
    ],
    "wof:name":"Logistics & Trading",
    "wof:placetype":"venue"
},
  "geometry": {"coordinates":[153.04884338400001,-27.3999881744],"type":"Point"}
}