{
  "type": "Feature",
  "properties": {
    "addr:full":"3/ 461 Ipswich Rd Annerley QLD 4103",
    "addr:housenumber":"/ 461",
    "addr:postcode":"4103",
    "addr:street":"Ipswich Rd",
    "iso:country":"AU",
    "sg:address":"3/ 461 Ipswich Rd",
    "sg:city":"Annerley",
    "sg:classifiers":[
        {
            "category":"Real Estate",
            "subcategory":"Real Estate Agent",
            "type":"Services"
        }
    ],
    "sg:phone":"+61 7 3892 1555",
    "sg:postcode":"4103",
    "sg:province":"QLD",
    "wof:name":"Professionals- Annerley",
    "wof:placetype":"venue"
},
  "geometry": {"coordinates":[153.03155517600001,-27.5117683411],"type":"Point"}
}