{
  "type": "Feature",
  "properties": {
    "addr:full":"Cnr Nicklin Way & Bellara Drv Currimundi QLD 4551",
    "addr:postcode":"4551",
    "addr:street":"Cnr Nicklin Way & Bellara Drv",
    "iso:country":"AU",
    "sg:address":"Cnr Nicklin Way & Bellara Drv",
    "sg:city":"Currimundi",
    "sg:classifiers":[
        {
            "category":"Food & Beverages",
            "subcategory":"Bakery",
            "type":"Retail Goods"
        }
    ],
    "sg:phone":"+61 7 5493 5459",
    "sg:postcode":"4551",
    "sg:province":"QLD",
    "sg:tags":[
        "baker"
    ],
    "wof:name":"Bakers Delight",
    "wof:placetype":"venue"
},
  "geometry": {"coordinates":[153.12217712399999,-26.7688045502],"type":"Point"}
}