{
  "type": "Feature",
  "properties": {
    "addr:full":"66- 74 Brice Ave Mooroolbark VIC 3138",
    "addr:housenumber":"74",
    "addr:postcode":"3138",
    "addr:street":"Brice Ave",
    "iso:country":"AU",
    "sg:address":"66- 74 Brice Ave",
    "sg:city":"Mooroolbark",
    "sg:classifiers":[
        {
            "category":"Food & Beverages",
            "subcategory":"Supermarket",
            "type":"Retail Goods"
        }
    ],
    "sg:phone":"+61 3 9726 7266",
    "sg:postcode":"3138",
    "sg:province":"VIC",
    "sg:tags":[
        "grocery",
        "store"
    ],
    "wof:name":"Mooroolbark I G A",
    "wof:placetype":"venue"
},
  "geometry": {"coordinates":[145.31208801299999,-37.7852745056],"type":"Point"}
}