{
  "type": "Feature",
  "properties": {
    "iso:country":"AU",
    "sg:address":"Cnr Wynne & Beenleigh Rds",
    "sg:city":"Sunnybank Hills",
    "sg:classifiers":[
        {
            "category":"Health Services",
            "subcategory":"Health Practitioner",
            "type":"Services"
        }
    ],
    "sg:phone":"+61 7 3344 6696",
    "sg:postcode":"4109",
    "sg:province":"QLD",
    "sg:tags":[
        "dietitian"
    ],
    "wof:name":"K.J.' s Weight Loss Centre",
    "wof:placetype":"venue"
},
  "geometry": {"coordinates":[153.05619812,-27.5917282104],"type":"Point"}
}