{
  "type": "Feature",
  "properties": {
    "addr:full":"700 Main Rd Eltham VIC 3095",
    "addr:housenumber":"700",
    "addr:postcode":"3095",
    "addr:street":"Main Rd",
    "iso:country":"AU",
    "sg:address":"700 Main Rd",
    "sg:city":"Eltham",
    "sg:classifiers":[
        {
            "category":"Health Services",
            "subcategory":"Doctor",
            "type":"Services"
        }
    ],
    "sg:phone":"+61 3 9431 0644",
    "sg:postcode":"3095",
    "sg:province":"VIC",
    "sg:tags":[
        "medical",
        "practitioner"
    ],
    "wof:name":"Hall Caroline",
    "wof:placetype":"venue"
},
  "geometry": {"coordinates":[145.146240234,-37.7244033813],"type":"Point"}
}