{
  "type": "Feature",
  "properties": {
    "iso:country":"AU",
    "sg:address":"27b Bruce St",
    "sg:city":"Nedlands",
    "sg:classifiers":[
        {
            "category":"Home & Garden",
            "subcategory":"Carpets & Floor Coverings",
            "type":"Retail Goods"
        }
    ],
    "sg:phone":"+61 8 9386 8433",
    "sg:postcode":"6009",
    "sg:province":"WA",
    "sg:tags":[
        "flooring",
        "parquet"
    ],
    "wof:name":"Metro Sanding Co",
    "wof:placetype":"venue"
},
  "geometry": {"coordinates":[115.810944,-31.981173],"type":"Point"}
}