{
  "type": "Feature",
  "properties": {
    "addr:full":"480 Princes Hwy Nowra NSW 2541",
    "addr:housenumber":"480",
    "addr:postcode":"2541",
    "addr:street":"Princes Hwy",
    "iso:country":"AU",
    "sg:address":"480 Princes Hwy",
    "sg:city":"Nowra",
    "sg:classifiers":[
        {
            "category":"Fast Food",
            "type":"Food & Drink"
        }
    ],
    "sg:phone":"+61 2 4421 8558",
    "sg:postcode":"2541",
    "sg:province":"NSW",
    "sg:tags":[
        "away",
        "take"
    ],
    "wof:name":"Nowra Bridge Seafoods",
    "wof:placetype":"venue"
},
  "geometry": {"coordinates":[150.602050781,-34.8659706116],"type":"Point"}
}