{
  "type": "Feature",
  "properties": {
    "addr:full":"Glenvale Rd Toowoomba QLD 4350",
    "addr:postcode":"4350",
    "addr:street":"Glenvale Rd",
    "iso:country":"AU",
    "sg:address":"Glenvale Rd",
    "sg:city":"Toowoomba",
    "sg:classifiers":[
        {
            "category":"Food & Beverages",
            "subcategory":"Groceries & Convenience Stores",
            "type":"Retail Goods"
        }
    ],
    "sg:phone":"+61 7 4633 3886",
    "sg:postcode":"4350",
    "sg:province":"QLD",
    "wof:name":"Glenvale Convenience Plus",
    "wof:placetype":"venue"
},
  "geometry": {"coordinates":[151.88623000000001,-27.560198],"type":"Point"}
}