{
  "type": "Feature",
  "properties": {
    "addr:full":"5 Carpenters La Mardi NSW 2259",
    "addr:housenumber":"5",
    "addr:postcode":"2259",
    "addr:street":"Carpenters La Mardi",
    "iso:country":"AU",
    "sg:address":"5 Carpenters La",
    "sg:city":"Mardi",
    "sg:classifiers":[
        {
            "category":"Home & Garden",
            "subcategory":"Building Materials",
            "type":"Retail Goods"
        }
    ],
    "sg:phone":"+61 2 4353 0033",
    "sg:postcode":"2259",
    "sg:province":"NSW",
    "sg:tags":[
        "retaining",
        "wall"
    ],
    "wof:name":"B.N.T. Concreting",
    "wof:placetype":"venue"
},
  "geometry": {"coordinates":[151.39503479000001,-33.3071403503],"type":"Point"}
}