{
  "type": "Feature",
  "properties": {
    "addr:full":"1 Cullen Pl Smithfield NSW 2164",
    "addr:housenumber":"1",
    "addr:postcode":"2164",
    "addr:street":"Cullen Pl",
    "iso:country":"AU",
    "sg:address":"1 Cullen Pl",
    "sg:city":"Smithfield",
    "sg:classifiers":[
        {
            "category":"Manufacturing",
            "subcategory":"Metals",
            "type":"Manufacturing & Wholesale Goods"
        }
    ],
    "sg:phone":"+61 2 9609 2655",
    "sg:postcode":"2164",
    "sg:province":"NSW",
    "sg:tags":[
        "steel",
        "fabricator",
        "mfrs"
    ],
    "wof:name":"F & E Moulds Pty Ltd",
    "wof:placetype":"venue"
},
  "geometry": {"coordinates":[150.95018005399999,-33.8416938782],"type":"Point"}
}