{
  "type": "Feature",
  "properties": {
    "addr:full":"Retreat Rd Newtown VIC 3220",
    "addr:postcode":"3220",
    "addr:street":"Retreat Rd",
    "iso:country":"AU",
    "sg:address":"Retreat Rd",
    "sg:city":"Newtown",
    "sg:classifiers":[
        {
            "category":"Education",
            "subcategory":"School",
            "type":"Public Place"
        }
    ],
    "sg:phone":"+61 3 5221 4211",
    "sg:postcode":"3220",
    "sg:province":"VIC",
    "sg:tags":[
        "girl"
    ],
    "wof:name":"Sacred Heart College",
    "wof:placetype":"venue"
},
  "geometry": {"coordinates":[144.345596,-38.150131],"type":"Point"}
}