{
  "type": "Feature",
  "properties": {
    "addr:full":"11 O&#039;Driscol Crt Highton VIC 3216",
    "addr:housenumber":"11",
    "addr:postcode":"3216",
    "addr:street":"O &;Crt",
    "iso:country":"AU",
    "sg:address":"11 O&#039;Driscol Crt",
    "sg:city":"Highton",
    "sg:classifiers":[
        {
            "category":"Structure",
            "subcategory":"Office Building",
            "type":"Public Place"
        }
    ],
    "sg:phone":"+61 3 5244 2194",
    "sg:postcode":"3216",
    "sg:province":"VIC",
    "sg:tags":[
        "slater",
        "tiler",
        "roof"
    ],
    "wof:name":"Barwon Roofing",
    "wof:placetype":"venue"
},
  "geometry": {"coordinates":[144.312042236,-38.188949585],"type":"Point"}
}