{
  "type": "Feature",
  "properties": {
    "iso:country":"AU",
    "sg:address":"6 - 8",
    "sg:city":"Flower Injune",
    "sg:classifiers":[
        {
            "category":"Professional",
            "subcategory":"Engineering",
            "type":"Services"
        }
    ],
    "sg:phone":"+61 7 4626 1116",
    "sg:postcode":"4454",
    "sg:province":"QLD",
    "sg:tags":[
        "diesel",
        "engineer"
    ],
    "wof:name":"Injune Diesel Service",
    "wof:placetype":"venue"
},
  "geometry": {"coordinates":[148.56834411599999,-25.8409290314],"type":"Point"}
}