{
  "type": "Feature",
  "properties": {
    "addr:full":"Suite 6a 235 New South Head Rd Edgecliff NSW 2027",
    "addr:housenumber":"235",
    "addr:postcode":"2027",
    "addr:street":"New South Head Rd",
    "iso:country":"AU",
    "sg:address":"Suite 6a 235 New South Head Rd",
    "sg:city":"Edgecliff",
    "sg:classifiers":[
        {
            "category":"Health Services",
            "subcategory":"Doctor",
            "type":"Services"
        }
    ],
    "sg:phone":"+61 2 9363 5932",
    "sg:postcode":"2027",
    "sg:province":"NSW",
    "sg:tags":[
        "podiatrist"
    ],
    "wof:name":"Edgecliff Podiatry Pty Ltd",
    "wof:placetype":"venue"
},
  "geometry": {"coordinates":[151.23599243199999,-33.8788261414],"type":"Point"}
}