{
  "type": "Feature",
  "properties": {
    "iso:country":"AU",
    "sg:address":"2 Madden Ave",
    "sg:city":"Carnegie",
    "sg:classifiers":[
        {
            "category":"Education",
            "subcategory":"Special Training",
            "type":"Public Place"
        }
    ],
    "sg:phone":"+61 3 9569 2622",
    "sg:postcode":"3163",
    "sg:province":"VIC",
    "sg:tags":[
        "development"
    ],
    "wof:name":"Delta Consulting",
    "wof:placetype":"venue"
},
  "geometry": {"coordinates":[145.05101013199999,-37.8906517029],"type":"Point"}
}