{
  "type": "Feature",
  "properties": {
    "addr:full":"136 Cromwell St Collingwood VIC 3066",
    "addr:housenumber":"136",
    "addr:postcode":"3066",
    "addr:street":"Cromwell St",
    "iso:country":"AU",
    "sg:address":"136 Cromwell St",
    "sg:city":"Collingwood",
    "sg:classifiers":[
        {
            "category":"Wholesale",
            "subcategory":"Non-durable Goods",
            "type":"Manufacturing & Wholesale Goods"
        }
    ],
    "sg:phone":"+61 3 9417 0052",
    "sg:postcode":"3066",
    "sg:province":"VIC",
    "sg:tags":[
        "wholesaler",
        "craft",
        "mfrs"
    ],
    "wof:name":"M & S Textiles Australia",
    "wof:placetype":"venue"
},
  "geometry": {"coordinates":[144.99057006800001,-37.8037796021],"type":"Point"}
}