{
  "type": "Feature",
  "properties": {
    "addr:full":"354 Fitzgerald St Northam WA 6401",
    "addr:housenumber":"354",
    "addr:postcode":"6401",
    "addr:street":"Fitzgerald St",
    "iso:country":"AU",
    "sg:address":"354 Fitzgerald St",
    "sg:city":"Northam",
    "sg:classifiers":[
        {
            "category":"Deli",
            "type":"Food & Drink"
        }
    ],
    "sg:phone":"+61 8 9622 3855",
    "sg:postcode":"6401",
    "sg:province":"WA",
    "sg:tags":[
        "delicatessen"
    ],
    "wof:name":"Westend Store",
    "wof:placetype":"venue"
},
  "geometry": {"coordinates":[116.67391204800001,-31.6485691071],"type":"Point"}
}