{
  "type": "Feature",
  "properties": {
    "addr:full":"21 Kootenai Drv North Tamborine QLD 4272",
    "addr:housenumber":"21",
    "addr:postcode":"4272",
    "addr:street":"Kootenai Drv North",
    "iso:country":"AU",
    "sg:address":"21 Kootenai Drv",
    "sg:city":"North Tamborine",
    "sg:classifiers":[
        {
            "category":"Autos & Motor Vehicles",
            "subcategory":"Auto Supplies",
            "type":"Retail Goods"
        }
    ],
    "sg:phone":"+61 7 5545 4228",
    "sg:postcode":"4272",
    "sg:province":"QLD",
    "sg:tags":[
        "part",
        "cycles",
        "accessory"
    ],
    "wof:name":"Australian Motorcycle Headlight Protectors",
    "wof:placetype":"venue"
},
  "geometry": {"coordinates":[153.174102783,-27.9238395691],"type":"Point"}
}