{
  "type": "Feature",
  "properties": {
    "iso:country":"AU",
    "sg:address":"17 Boreen Crt",
    "sg:city":"Helensvale",
    "sg:classifiers":[
        {
            "category":"Shopping",
            "subcategory":"Stationery & Office Supplies",
            "type":"Retail Goods"
        }
    ],
    "sg:phone":"+61 7 5573 0704",
    "sg:postcode":"4212",
    "sg:province":"QLD",
    "sg:tags":[
        "partition"
    ],
    "wof:name":"Ace Plasterboard Repairs & Renovations",
    "wof:placetype":"venue"
},
  "geometry": {"coordinates":[153.34405517600001,-27.9070396423],"type":"Point"}
}