{
  "type": "Feature",
  "properties": {
    "addr:full":"2c Staley St Brunswick VIC 3056",
    "addr:housenumber":"2c",
    "addr:postcode":"3056",
    "addr:street":"Staley St",
    "iso:country":"AU",
    "sg:address":"2c Staley St",
    "sg:city":"Brunswick",
    "sg:classifiers":[
        {
            "category":"Professional",
            "subcategory":"Employment Agencies",
            "type":"Services"
        }
    ],
    "sg:phone":"+61 3 9380 8444",
    "sg:postcode":"3056",
    "sg:province":"VIC",
    "sg:tags":[
        "theatrical",
        "managers",
        "agent",
        "producer"
    ],
    "wof:name":"Centre Stage Agency",
    "wof:placetype":"venue"
},
  "geometry": {"coordinates":[144.962966919,-37.7664794922],"type":"Point"}
}