{
  "type": "Feature",
  "properties": {
    "iso:country":"AU",
    "sg:address":"116 Alfred Rd",
    "sg:city":"Chipping Norton",
    "sg:classifiers":[
        {
            "category":"Autos & Motor Vehicles",
            "subcategory":"Motorcycle Sales",
            "type":"Retail Goods"
        }
    ],
    "sg:phone":"+61 428 962 538",
    "sg:postcode":"2170",
    "sg:province":"NSW",
    "sg:tags":[
        "outboard"
    ],
    "wof:name":"Bonnette's Mobile Boating Services",
    "wof:placetype":"venue"
},
  "geometry": {"coordinates":[150.95640564000001,-33.9234580994],"type":"Point"}
}