{
  "type": "Feature",
  "properties": {
    "addr:full":"43 William St Bowen QLD 4805",
    "addr:housenumber":"43",
    "addr:postcode":"4805",
    "addr:street":"William St",
    "iso:country":"AU",
    "sg:address":"43 William St",
    "sg:city":"Bowen",
    "sg:classifiers":[
        {
            "category":"Personal",
            "subcategory":"Beauty Salon",
            "type":"Services"
        }
    ],
    "sg:phone":"+61 7 4786 2868",
    "sg:postcode":"4805",
    "sg:province":"QLD",
    "sg:tags":[
        "hairdresser"
    ],
    "wof:name":"Ros-Lea House Of Beauty & Hair",
    "wof:placetype":"venue"
},
  "geometry": {"coordinates":[148.24375915499999,-20.0152263641],"type":"Point"}
}