{
  "type": "Feature",
  "properties": {
    "addr:full":"Delta Rd (off Cooloolabin Rd Yandina QLD 4561",
    "addr:postcode":"4561",
    "addr:street":"Delta Rd Off Cooloolabin Rd",
    "iso:country":"AU",
    "sg:address":"Delta Rd (off Cooloolabin Rd",
    "sg:city":"Yandina",
    "sg:classifiers":[
        {
            "category":"Farming",
            "subcategory":"Nursery",
            "type":"Manufacturing & Wholesale Goods"
        }
    ],
    "sg:phone":"+61 7 5446 8355",
    "sg:postcode":"4561",
    "sg:province":"QLD",
    "wof:name":"Schonrock Nurseries",
    "wof:placetype":"venue"
},
  "geometry": {"coordinates":[152.956344605,-26.5604496002],"type":"Point"}
}