{
  "type": "Feature",
  "properties": {
    "iso:country":"AU",
    "sg:address":"PO Box 654",
    "sg:city":"Oxenford",
    "sg:classifiers":[
        {
            "category":"Professional",
            "subcategory":"Accounting & Tax Preparation",
            "type":"Services"
        }
    ],
    "sg:phone":"+61 417 712 734",
    "sg:postcode":"4210",
    "sg:province":"QLD",
    "sg:tags":[
        "bookkeeping"
    ],
    "wof:name":"Cashin Bookkeeping Pty Ltd",
    "wof:placetype":"venue"
},
  "geometry": {"coordinates":[153.31413269000001,-27.9020309448],"type":"Point"}
}