{
  "type": "Feature",
  "properties": {
    "addr:full":"51 Cross St Double Bay NSW 2028",
    "addr:housenumber":"51",
    "addr:postcode":"2028",
    "addr:street":"Cross St",
    "iso:country":"AU",
    "sg:address":"51 Cross St",
    "sg:city":"Double Bay",
    "sg:classifiers":[
        {
            "category":"Banks & Credit Unions",
            "subcategory":"Financial Services",
            "type":"Services"
        }
    ],
    "sg:phone":"+61 2 9327 7756",
    "sg:postcode":"2028",
    "sg:province":"NSW",
    "sg:tags":[
        "loan",
        "finance",
        "mortgage"
    ],
    "wof:name":"George St Property Finance Co Pty Ltd",
    "wof:placetype":"venue"
},
  "geometry": {"coordinates":[151.24223327600001,-33.8757476807],"type":"Point"}
}