{
  "type": "Feature",
  "properties": {
    "iso:country":"AU",
    "sg:address":"40 Camp St",
    "sg:city":"Beechworth",
    "sg:classifiers":[
        {
            "category":"Shopping",
            "subcategory":"Antiques",
            "type":"Retail Goods"
        }
    ],
    "sg:phone":"+61 3 5728 1861",
    "sg:postcode":"3747",
    "sg:province":"VIC",
    "sg:tags":[
        "collectable",
        "memorabilia"
    ],
    "wof:name":"Beechworth Antiques",
    "wof:placetype":"venue"
},
  "geometry": {"coordinates":[146.68634,-36.358627],"type":"Point"}
}