{
  "type": "Feature",
  "properties": {
    "addr:full":"444 West Botany St Rockdale NSW 2216",
    "addr:housenumber":"444",
    "addr:postcode":"2216",
    "addr:street":"West Botany St",
    "iso:country":"AU",
    "sg:address":"444 West Botany St",
    "sg:city":"Rockdale",
    "sg:classifiers":[
        {
            "category":"Fast Food",
            "type":"Food & Drink"
        }
    ],
    "sg:phone":"+61 2 9597 5406",
    "sg:postcode":"2216",
    "sg:province":"NSW",
    "sg:tags":[
        "away",
        "take"
    ],
    "wof:name":"R & J Sandwich Shop",
    "wof:placetype":"venue"
},
  "geometry": {"coordinates":[151.145599,-33.959835],"type":"Point"}
}