{
  "type": "Feature",
  "properties": {
    "iso:country":"AU",
    "sg:address":"189 Bullumwaal Rd",
    "sg:city":"Wy Yung",
    "sg:classifiers":[
        {
            "category":"Real Estate",
            "subcategory":"Real Estate Agent",
            "type":"Services"
        }
    ],
    "sg:phone":"+61 429 111 085",
    "sg:postcode":"3875",
    "sg:province":"VIC",
    "wof:name":"Dennis Hall",
    "wof:placetype":"venue"
},
  "geometry": {"coordinates":[147.61442565900001,-37.8016204834],"type":"Point"}
}