{
  "type": "Feature",
  "properties": {
    "iso:country":"AU",
    "sg:address":"10 Middlebrook Crt",
    "sg:city":"Woodcroft",
    "sg:classifiers":[
        {
            "category":"Professional",
            "subcategory":"Art Services",
            "type":"Services"
        }
    ],
    "sg:phone":"+61 8 8325 3805",
    "sg:postcode":"5162",
    "sg:province":"SA",
    "sg:tags":[
        "decorator",
        "painter"
    ],
    "wof:name":"Brushstrokes Painting & Decorating",
    "wof:placetype":"venue"
},
  "geometry": {"coordinates":[138.55174255399999,-35.1191520691],"type":"Point"}
}