{
  "type": "Feature",
  "properties": {
    "addr:full":"PO Box 364 Maitland NSW 2320",
    "addr:postcode":"2320",
    "iso:country":"AU",
    "sg:address":"PO Box 364",
    "sg:city":"Maitland",
    "sg:classifiers":[
        {
            "category":"Professional",
            "subcategory":"Detective & Security Services",
            "type":"Services"
        }
    ],
    "sg:phone":"+61 2 4934 1813",
    "sg:postcode":"2320",
    "sg:province":"NSW",
    "sg:tags":[
        "consultant",
        "system"
    ],
    "wof:name":"Maitland Security Services",
    "wof:placetype":"venue"
},
  "geometry": {"coordinates":[151.570114136,-32.7078857422],"type":"Point"}
}