{
  "type": "Feature",
  "properties": {
    "iso:country":"AU",
    "sg:address":"85 Main St",
    "sg:city":"Blacktown",
    "sg:classifiers":[
        {
            "category":"Health Services",
            "subcategory":"Optometrist",
            "type":"Services"
        }
    ],
    "sg:phone":"+61 2 9621 6564",
    "sg:postcode":"2148",
    "sg:province":"NSW",
    "wof:name":"Allen John A",
    "wof:placetype":"venue"
},
  "geometry": {"coordinates":[150.909881592,-33.7704086304],"type":"Point"}
}