{
  "type": "Feature",
  "properties": {
    "iso:country":"AU",
    "sg:address":"127 Church St",
    "sg:city":"Parramatta",
    "sg:classifiers":[
        {
            "category":"Shopping",
            "subcategory":"Antiques",
            "type":"Retail Goods"
        }
    ],
    "sg:phone":"+61 2 9893 9056",
    "sg:postcode":"2150",
    "sg:province":"NSW",
    "sg:tags":[
        "collectable",
        "memorabilia"
    ],
    "wof:name":"Sherriff's Mini Cars",
    "wof:placetype":"venue"
},
  "geometry": {"coordinates":[151.11984252900001,-33.8753585815],"type":"Point"}
}