{
  "type": "Feature",
  "properties": {
    "addr:full":"Unit 12, 41- 43 Higginbotham Rd Gladesville NSW 2111",
    "addr:housenumber":"41 43",
    "addr:postcode":"2111",
    "addr:street":"Higginbotham Rd",
    "iso:country":"AU",
    "sg:address":"Unit 12, 41- 43 Higginbotham Rd",
    "sg:city":"Gladesville",
    "sg:classifiers":[
        {
            "category":"Building & Trades",
            "subcategory":"Construction",
            "type":"Services"
        }
    ],
    "sg:phone":"+61 2 9807 8400",
    "sg:postcode":"2111",
    "sg:province":"NSW",
    "sg:tags":[
        "home",
        "air conditioning"
    ],
    "wof:name":"Carrier Showroom Sales",
    "wof:placetype":"venue"
},
  "geometry": {"coordinates":[151.12319946299999,-33.8159255981],"type":"Point"}
}