{
  "type": "Feature",
  "properties": {
    "addr:full":"PO Box 317 Hillarys WA 6923",
    "addr:postcode":"6923",
    "iso:country":"AU",
    "sg:address":"PO Box 317",
    "sg:city":"Hillarys",
    "sg:classifiers":[
        {
            "category":"Recreation",
            "subcategory":"Boat Charter",
            "type":"Entertainment"
        }
    ],
    "sg:phone":"+61 417 957 870",
    "sg:postcode":"6923",
    "sg:province":"WA",
    "wof:name":"Image Charter",
    "wof:placetype":"venue"
},
  "geometry": {"coordinates":[115.741539002,-31.809419632],"type":"Point"}
}