{
  "type": "Feature",
  "properties": {
    "addr:full":"106 Pateena St Stafford QLD 4053",
    "addr:housenumber":"106",
    "addr:postcode":"4053",
    "addr:street":"Pateena St",
    "iso:country":"AU",
    "sg:address":"106 Pateena St",
    "sg:city":"Stafford",
    "sg:classifiers":[
        {
            "category":"Personal",
            "subcategory":"Massage",
            "type":"Services"
        }
    ],
    "sg:phone":"+61 7 3352 5334",
    "sg:postcode":"4053",
    "sg:province":"QLD",
    "sg:tags":[
        "therapy"
    ],
    "wof:name":"Hands From Heaven",
    "wof:placetype":"venue"
},
  "geometry": {"coordinates":[153.01159668,-27.4069023132],"type":"Point"}
}