{
  "type": "Feature",
  "properties": {
    "addr:full":"117A Turpin Rd Labrador QLD 4215",
    "addr:housenumber":"117a",
    "addr:postcode":"4215",
    "addr:street":"Turpin Rd",
    "iso:country":"AU",
    "sg:address":"117A Turpin Rd",
    "sg:city":"Labrador",
    "sg:classifiers":[
        {
            "category":"Real Estate",
            "subcategory":"Real Estate Agent",
            "type":"Services"
        }
    ],
    "sg:phone":"+61 7 5532 8880",
    "sg:postcode":"4215",
    "sg:province":"QLD",
    "wof:name":"Intercom Commercial Property Sales",
    "wof:placetype":"venue"
},
  "geometry": {"coordinates":[153.40257263199999,-27.9473209381],"type":"Point"}
}