{
  "type": "Feature",
  "properties": {
    "iso:country":"AU",
    "sg:address":"43 Clarence St",
    "sg:city":"Coorparoo",
    "sg:classifiers":[
        {
            "category":"Home & Garden",
            "subcategory":"Garden Supply",
            "type":"Retail Goods"
        }
    ],
    "sg:phone":"+61 7 3394 3324",
    "sg:postcode":"4151",
    "sg:province":"QLD",
    "sg:tags":[
        "equipment",
        "hydroponics"
    ],
    "wof:name":"Advance Profile Tech",
    "wof:placetype":"venue"
},
  "geometry": {"coordinates":[153.05380249000001,-27.4897708893],"type":"Point"}
}