{
  "type": "Feature",
  "properties": {
    "addr:full":"183c Forest Rd Hurstville NSW 2220",
    "addr:housenumber":"183c",
    "addr:postcode":"2220",
    "addr:street":"Forest Rd",
    "iso:country":"AU",
    "sg:address":"183c Forest Rd",
    "sg:city":"Hurstville",
    "sg:classifiers":[
        {
            "category":"Shopping",
            "subcategory":"Clothing, Apparel, & Fashions",
            "type":"Retail Goods"
        }
    ],
    "sg:phone":"+61 2 9580 2459",
    "sg:postcode":"2220",
    "sg:province":"NSW",
    "sg:tags":[
        "recycled",
        "clothing"
    ],
    "wof:name":"St Vincent De Paul Society",
    "wof:placetype":"venue"
},
  "geometry": {"coordinates":[151.103149414,-33.9671783447],"type":"Point"}
}