{
  "type": "Feature",
  "properties": {
    "addr:full":"Homemaker City Jindalee QLD 4074",
    "addr:postcode":"4074",
    "iso:country":"AU",
    "sg:address":"Homemaker City",
    "sg:city":"Jindalee",
    "sg:classifiers":[
        {
            "category":"Home & Garden",
            "subcategory":"Furniture",
            "type":"Retail Goods"
        }
    ],
    "sg:phone":"+61 7 3279 3522",
    "sg:postcode":"4074",
    "sg:province":"QLD",
    "sg:tags":[
        "outdoor"
    ],
    "wof:name":"The Outdoor Furniture Specialists",
    "wof:placetype":"venue"
},
  "geometry": {"coordinates":[152.948974609,-27.5351352692],"type":"Point"}
}