{
  "type": "Feature",
  "properties": {
    "addr:full":"173 Narracan Drv Moe VIC 3825",
    "addr:housenumber":"173",
    "addr:postcode":"3825",
    "addr:street":"Narracan Drv",
    "iso:country":"AU",
    "sg:address":"173 Narracan Drv",
    "sg:city":"Moe",
    "sg:classifiers":[
        {
            "category":"Autos & Motor Vehicles",
            "subcategory":"Fuel & Gas Station",
            "type":"Retail Goods"
        }
    ],
    "sg:phone":"+61 3 5127 6266",
    "sg:postcode":"3825",
    "sg:province":"VIC",
    "wof:name":"B P Australia Ltd",
    "wof:placetype":"venue"
},
  "geometry": {"coordinates":[146.28353899999999,-38.187054],"type":"Point"}
}