{
  "type": "Feature",
  "properties": {
    "iso:country":"AU",
    "sg:address":"300 Como Pde West",
    "sg:city":"Parkdale",
    "sg:classifiers":[
        {
            "category":"Professional",
            "subcategory":"Accounting & Tax Preparation",
            "type":"Services"
        }
    ],
    "sg:phone":"+61 3 9580 9008",
    "sg:postcode":"3195",
    "sg:province":"VIC",
    "sg:tags":[
        "accountant",
        "auditor"
    ],
    "wof:name":"Lewis Neil R & Co",
    "wof:placetype":"venue"
},
  "geometry": {"coordinates":[145.07760620100001,-37.9946632385],"type":"Point"}
}