{
  "type": "Feature",
  "properties": {
    "addr:full":"Unit 3 / 43 Burnett St Bundaberg QLD 4670",
    "addr:housenumber":"43",
    "addr:postcode":"4670",
    "addr:street":"Burnett St",
    "iso:country":"AU",
    "sg:address":"Unit 3 / 43 Burnett St",
    "sg:city":"Bundaberg",
    "sg:classifiers":[
        {
            "category":"Building & Trades",
            "subcategory":"Pest Control",
            "type":"Services"
        }
    ],
    "sg:phone":"+61 7 4153 5653",
    "sg:postcode":"4670",
    "sg:province":"QLD",
    "wof:name":"Natraspray Pest Control",
    "wof:placetype":"venue"
},
  "geometry": {"coordinates":[152.35661315900001,-24.8733386993],"type":"Point"}
}