{
  "type": "Feature",
  "properties": {
    "addr:full":"52 Corrigan Rd Noble Park VIC 3174",
    "addr:housenumber":"52",
    "addr:postcode":"3174",
    "addr:street":"Corrigan Rd",
    "iso:country":"AU",
    "sg:address":"52 Corrigan Rd",
    "sg:city":"Noble Park",
    "sg:classifiers":[
        {
            "category":"Food & Beverages",
            "subcategory":"Groceries & Convenience Stores",
            "type":"Retail Goods"
        }
    ],
    "sg:phone":"+61 3 9546 5868",
    "sg:postcode":"3174",
    "sg:province":"VIC",
    "wof:name":"Chwn Yan Zhang Milk Bar",
    "wof:placetype":"venue"
},
  "geometry": {"coordinates":[145.169723511,-37.9573135376],"type":"Point"}
}