{
  "type": "Feature",
  "properties": {
    "addr:full":"15 Wilson St Newtown NSW 2042",
    "addr:housenumber":"15",
    "addr:postcode":"2042",
    "addr:street":"Wilson St",
    "iso:country":"AU",
    "sg:address":"15 Wilson St",
    "sg:city":"Newtown",
    "sg:classifiers":[
        {
            "category":"Shopping",
            "subcategory":"Crafts & Fabrics",
            "type":"Retail Goods"
        }
    ],
    "sg:phone":"+61 2 9516 2339",
    "sg:postcode":"2042",
    "sg:province":"NSW",
    "sg:tags":[
        "supply"
    ],
    "wof:name":"Newtown Art Supplies",
    "wof:placetype":"venue"
},
  "geometry": {"coordinates":[151.180115,-33.897064],"type":"Point"}
}