{
  "type": "Feature",
  "properties": {
    "iso:country":"AU",
    "sg:address":"4a Dib Crt",
    "sg:city":"Tullamarine",
    "sg:classifiers":[
        {
            "category":"Social Services",
            "subcategory":"Adult Care",
            "type":"Services"
        }
    ],
    "sg:phone":"+61 3 9330 0770",
    "sg:postcode":"3043",
    "sg:province":"VIC",
    "sg:tags":[
        "towing"
    ],
    "wof:name":"C & A Towing",
    "wof:placetype":"venue"
},
  "geometry": {"coordinates":[144.86640930199999,-37.7191696167],"type":"Point"}
}