{
  "type": "Feature",
  "properties": {
    "addr:full":"71 Victoria St Potts Point NSW 2011",
    "addr:housenumber":"71",
    "addr:postcode":"2011",
    "addr:street":"Victoria St",
    "iso:country":"AU",
    "sg:address":"71 Victoria St",
    "sg:city":"Potts Point",
    "sg:classifiers":[
        {
            "category":"Shopping",
            "subcategory":"Clothing, Apparel, & Fashions",
            "type":"Retail Goods"
        }
    ],
    "sg:phone":"+61 2 9368 0989",
    "sg:postcode":"2011",
    "sg:province":"NSW",
    "sg:tags":[
        "textile",
        "designer"
    ],
    "wof:name":"Sue Smithers Style",
    "wof:placetype":"venue"
},
  "geometry": {"coordinates":[151.22297668499999,-33.8702201843],"type":"Point"}
}