{
  "type": "Feature",
  "properties": {
    "addr:full":"326 Melbourne Rd Newport VIC 3015",
    "addr:housenumber":"326",
    "addr:postcode":"3015",
    "addr:street":"Melbourne Rd",
    "iso:country":"AU",
    "sg:address":"326 Melbourne Rd",
    "sg:city":"Newport",
    "sg:classifiers":[
        {
            "category":"Fast Food",
            "type":"Food & Drink"
        }
    ],
    "sg:phone":"+61 13 11 66",
    "sg:postcode":"3015",
    "sg:province":"VIC",
    "sg:tags":[
        "away",
        "take"
    ],
    "wof:name":"Pizza Hut Delivery",
    "wof:placetype":"venue"
},
  "geometry": {"coordinates":[144.88551330600001,-37.8456840515],"type":"Point"}
}