{
  "type": "Feature",
  "properties": {
    "addr:full":"Cnr Perry Rd/Tyers La Keysborough VIC 3173",
    "addr:postcode":"3173",
    "addr:street":"Cnr Perry Rd / Tyers La",
    "iso:country":"AU",
    "sg:address":"Cnr Perry Rd/Tyers La",
    "sg:city":"Keysborough",
    "sg:classifiers":[
        {
            "category":"Farming",
            "subcategory":"Poultry Farm",
            "type":"Manufacturing & Wholesale Goods"
        }
    ],
    "sg:phone":"+61 3 9798 1037",
    "sg:postcode":"3173",
    "sg:province":"VIC",
    "sg:tags":[
        "farmer"
    ],
    "wof:name":"Keysborough Egg Farm",
    "wof:placetype":"venue"
},
  "geometry": {"coordinates":[145.17166137699999,-38.0094184875],"type":"Point"}
}