{
  "type": "Feature",
  "properties": {
    "iso:country":"AU",
    "sg:address":"444 Forest Rd",
    "sg:city":"Sutherland",
    "sg:classifiers":[
        {
            "category":"Health Services",
            "subcategory":"Health Practitioner",
            "type":"Services"
        }
    ],
    "sg:phone":"+61 2 9545 3636",
    "sg:postcode":"2232",
    "sg:province":"NSW",
    "sg:tags":[
        "osteopath"
    ],
    "wof:name":"Sutherland Osteopathic Centre",
    "wof:placetype":"venue"
},
  "geometry": {"coordinates":[151.05921935999999,-34.0381126404],"type":"Point"}
}