{
  "type": "Feature",
  "properties": {
    "addr:full":"Unit 2 320 Selby St Osborne Park WA 6017",
    "addr:housenumber":"320",
    "addr:postcode":"6017",
    "addr:street":"Selby St",
    "iso:country":"AU",
    "sg:address":"Unit 2 320 Selby St",
    "sg:city":"Osborne Park",
    "sg:classifiers":[
        {
            "category":"Shopping",
            "subcategory":"Clothing, Apparel, & Fashions",
            "type":"Retail Goods"
        }
    ],
    "sg:phone":"+61 8 9244 1979",
    "sg:postcode":"6017",
    "sg:province":"WA",
    "sg:tags":[
        "recycled",
        "clothing"
    ],
    "wof:name":"Salvation Army Family Stores",
    "wof:placetype":"venue"
},
  "geometry": {"coordinates":[115.80393219,-31.9055633545],"type":"Point"}
}