{
  "type": "Feature",
  "properties": {
    "addr:full":"PO Box 414 Albany Creek QLD 4035",
    "addr:postcode":"4035",
    "iso:country":"AU",
    "sg:address":"PO Box 414",
    "sg:city":"Albany Creek",
    "sg:classifiers":[
        {
            "category":"Retail",
            "subcategory":"Auto Repair",
            "type":"Services"
        }
    ],
    "sg:phone":"+61 416 114 215",
    "sg:postcode":"4035",
    "sg:province":"QLD",
    "sg:tags":[
        "clutch",
        "brake"
    ],
    "wof:name":"B.C.A.S",
    "wof:placetype":"venue"
},
  "geometry": {"coordinates":[152.96537799999999,-27.34589],"type":"Point"}
}