{
  "type": "Feature",
  "properties": {
    "addr:full":"308 St Georges Rd Thornbury VIC 3071",
    "addr:housenumber":"308",
    "addr:postcode":"3071",
    "addr:street":"St Georges Rd",
    "iso:country":"AU",
    "sg:address":"308 St Georges Rd",
    "sg:city":"Thornbury",
    "sg:classifiers":[
        {
            "category":"Retail",
            "subcategory":"Repair Shop",
            "type":"Services"
        }
    ],
    "sg:phone":"+61 3 9480 3688",
    "sg:postcode":"3071",
    "sg:province":"VIC",
    "sg:tags":[
        "upholsterer"
    ],
    "wof:name":"Upholstery Direct",
    "wof:placetype":"venue"
},
  "geometry": {"coordinates":[144.99342346200001,-37.7602806091],"type":"Point"}
}