{
  "type": "Feature",
  "properties": {
    "addr:full":"41 Godfrey Ave St Kilda VIC 3182",
    "addr:housenumber":"41",
    "addr:postcode":"3182",
    "addr:street":"Godfrey Ave",
    "iso:country":"AU",
    "sg:address":"41 Godfrey Ave",
    "sg:city":"St Kilda",
    "sg:classifiers":[
        {
            "category":"Building & Trades",
            "subcategory":"Construction",
            "type":"Services"
        }
    ],
    "sg:phone":"+61 3 9867 1511",
    "sg:postcode":"3182",
    "sg:province":"VIC",
    "sg:tags":[
        "plasterboard",
        "plasterer",
        "fixer"
    ],
    "wof:name":"Zone Plastering",
    "wof:placetype":"venue"
},
  "geometry": {"coordinates":[144.992279053,-37.86328125],"type":"Point"}
}