{
  "type": "Feature",
  "properties": {
    "addr:full":"1st Flr, 17- 21 Bronte Rd Bondi Junction NSW 2022",
    "addr:housenumber":"17 21",
    "addr:postcode":"2022",
    "addr:street":"Bronte Rd",
    "iso:country":"AU",
    "sg:address":"1st Flr, 17- 21 Bronte Rd",
    "sg:city":"Bondi Junction",
    "sg:classifiers":[
        {
            "category":"Personal",
            "subcategory":"Massage",
            "type":"Services"
        }
    ],
    "sg:phone":"+61 2 9389 6955",
    "sg:postcode":"2022",
    "sg:province":"NSW",
    "sg:tags":[
        "therapy"
    ],
    "wof:name":"Catherine Tiney",
    "wof:placetype":"venue"
},
  "geometry": {"coordinates":[151.24949645999999,-33.8928794861],"type":"Point"}
}