{
  "type": "Feature",
  "properties": {
    "addr:full":"Granite Belt Drv The Summit QLD 4377",
    "addr:postcode":"4377",
    "addr:street":"Belt Drv",
    "iso:country":"AU",
    "sg:address":"Granite Belt Drv",
    "sg:city":"The Summit",
    "sg:classifiers":[
        {
            "category":"Shopping",
            "type":"Retail Goods"
        }
    ],
    "sg:phone":"+61 7 4683 2491",
    "sg:postcode":"4377",
    "sg:province":"QLD",
    "sg:tags":[
        "produce",
        "grain"
    ],
    "wof:name":"The Summit Produce Co",
    "wof:placetype":"venue"
},
  "geometry": {"coordinates":[151.95120239299999,-28.5775299072],"type":"Point"}
}