{
  "type": "Feature",
  "properties": {
    "addr:full":"11 Myer St Lakes Entrance VIC 3909",
    "addr:housenumber":"11",
    "addr:postcode":"3909",
    "addr:street":"Myer St",
    "iso:country":"AU",
    "sg:address":"11 Myer St",
    "sg:city":"Lakes Entrance",
    "sg:classifiers":[
        {
            "category":"Banks & Credit Unions",
            "subcategory":"Financial Services",
            "type":"Services"
        }
    ],
    "sg:phone":"+61 3 5155 1800",
    "sg:postcode":"3909",
    "sg:province":"VIC",
    "sg:tags":[
        "loan",
        "finance",
        "mortgage"
    ],
    "wof:name":"ANZ",
    "wof:placetype":"venue"
},
  "geometry": {"coordinates":[147.99345398,-37.8790588379],"type":"Point"}
}