{
  "type": "Feature",
  "properties": {
    "addr:full":"Lvl 9/ 50 Clarence St Sydney NSW 2000",
    "addr:housenumber":"/ 50",
    "addr:postcode":"2000",
    "addr:street":"Clarence St",
    "iso:country":"AU",
    "sg:address":"Lvl 9/ 50 Clarence St",
    "sg:city":"Sydney",
    "sg:classifiers":[
        {
            "category":"Professional",
            "subcategory":"Business Services",
            "type":"Services"
        }
    ],
    "sg:phone":"+61 2 9299 7044",
    "sg:postcode":"2000",
    "sg:province":"NSW",
    "sg:tags":[
        "broker"
    ],
    "wof:name":"Lockwood Business Sale",
    "wof:placetype":"venue"
},
  "geometry": {"coordinates":[151.20504760700001,-33.8654823303],"type":"Point"}
}