{
  "type": "Feature",
  "properties": {
    "iso:country":"AU",
    "sg:address":"105 Old Dookie Rd",
    "sg:city":"Shepparton",
    "sg:classifiers":[
        {
            "category":"Autos & Motor Vehicles",
            "subcategory":"Auto Supplies",
            "type":"Retail Goods"
        }
    ],
    "sg:phone":"+61 417 510 317",
    "sg:postcode":"3630",
    "sg:province":"VIC",
    "sg:tags":[
        "battery",
        "automotive"
    ],
    "wof:name":"Supercharge Batteries",
    "wof:placetype":"venue"
},
  "geometry": {"coordinates":[145.42820739699999,-36.3774528503],"type":"Point"}
}