{
  "type": "Feature",
  "properties": {
    "iso:country":"AU",
    "sg:address":"5 McCoy St",
    "sg:city":"Naracoorte",
    "sg:classifiers":[
        {
            "category":"Professional",
            "subcategory":"Detective & Security Services",
            "type":"Services"
        }
    ],
    "sg:phone":"+61 8 8762 2660",
    "sg:postcode":"5271",
    "sg:province":"SA",
    "sg:tags":[
        "consultant",
        "system"
    ],
    "wof:name":"Limestone Coast Security",
    "wof:placetype":"venue"
},
  "geometry": {"coordinates":[140.737686,-36.958862],"type":"Point"}
}