{
  "type": "Feature",
  "properties": {
    "iso:country":"AU",
    "sg:address":"Suite 204/ 66 Berry St",
    "sg:city":"North Sydney",
    "sg:classifiers":[
        {
            "category":"Health Services",
            "subcategory":"Dentist",
            "type":"Services"
        }
    ],
    "sg:phone":"+61 2 8920 1888",
    "sg:postcode":"2060",
    "sg:province":"NSW",
    "wof:name":"Ho Ken Dr",
    "wof:placetype":"venue"
},
  "geometry": {"coordinates":[151.20744323700001,-33.8366394043],"type":"Point"}
}