{
  "type": "Feature",
  "properties": {
    "addr:full":"248 Wickham Rd Highett VIC 3190",
    "addr:housenumber":"248",
    "addr:postcode":"3190",
    "addr:street":"Wickham Rd",
    "iso:country":"AU",
    "sg:address":"248 Wickham Rd",
    "sg:city":"Highett",
    "sg:classifiers":[
        {
            "category":"Retail",
            "subcategory":"Veterinary Services",
            "type":"Services"
        }
    ],
    "sg:phone":"+61 3 9532 5261",
    "sg:postcode":"3190",
    "sg:province":"VIC",
    "sg:tags":[
        "surgeon"
    ],
    "wof:name":"Southern Animal Emergency Centre",
    "wof:placetype":"venue"
},
  "geometry": {"coordinates":[145.05435180699999,-37.9467315674],"type":"Point"}
}