{
  "type": "Feature",
  "properties": {
    "iso:country":"AU",
    "sg:address":"39 Fairview St",
    "sg:city":"Springvale",
    "sg:classifiers":[
        {
            "category":"Home & Garden",
            "subcategory":"Carpets & Floor Coverings",
            "type":"Retail Goods"
        }
    ],
    "sg:phone":"+61 3 9547 8988",
    "sg:postcode":"3171",
    "sg:province":"VIC",
    "sg:tags":[
        "mattress"
    ],
    "wof:name":"Mattresses-r-us.com",
    "wof:placetype":"venue"
},
  "geometry": {"coordinates":[145.15054321299999,-37.9341163635],"type":"Point"}
}