{
  "type": "Feature",
  "properties": {
    "iso:country":"AU",
    "sg:address":"75 Islander Rd",
    "sg:city":"Pialba",
    "sg:classifiers":[
        {
            "category":"Wholesale",
            "subcategory":"Farm Supplies",
            "type":"Manufacturing & Wholesale Goods"
        }
    ],
    "sg:phone":"+61 7 4124 6711",
    "sg:postcode":"4655",
    "sg:province":"QLD",
    "sg:tags":[
        "equipment"
    ],
    "wof:name":"Hervey Bay Rural Supplies",
    "wof:placetype":"venue"
},
  "geometry": {"coordinates":[152.82815600000001,-25.284945],"type":"Point"}
}