{
  "type": "Feature",
  "properties": {
    "addr:full":"19 Sydney St Mackay QLD 4740",
    "addr:housenumber":"19",
    "addr:postcode":"4740",
    "addr:street":"Sydney St",
    "iso:country":"AU",
    "sg:address":"19 Sydney St",
    "sg:city":"Mackay",
    "sg:classifiers":[
        {
            "category":"Professional",
            "subcategory":"Accounting & Tax Preparation",
            "type":"Services"
        }
    ],
    "sg:phone":"+61 7 4951 2377",
    "sg:postcode":"4740",
    "sg:province":"QLD",
    "sg:tags":[
        "accountant",
        "auditor"
    ],
    "wof:name":"Stephens Glenn",
    "wof:placetype":"venue"
},
  "geometry": {"coordinates":[149.186035,-21.149591],"type":"Point"}
}