{
  "type": "Feature",
  "properties": {
    "iso:country":"AU",
    "sg:address":"277 Excelsior St",
    "sg:city":"South Granville",
    "sg:classifiers":[
        {
            "category":"Home & Garden",
            "subcategory":"Building Materials",
            "type":"Retail Goods"
        }
    ],
    "sg:phone":"+61 2 9721 0177",
    "sg:postcode":"2142",
    "sg:province":"NSW",
    "sg:tags":[
        "supply"
    ],
    "wof:name":"P R Pool",
    "wof:placetype":"venue"
},
  "geometry": {"coordinates":[150.999908447,-33.8589744568],"type":"Point"}
}