{
  "type": "Feature",
  "properties": {
    "addr:full":"5 Powdrill Rd Prestons NSW 2170",
    "addr:housenumber":"5",
    "addr:postcode":"2170",
    "addr:street":"Powdrill Rd",
    "iso:country":"AU",
    "sg:address":"5 Powdrill Rd",
    "sg:city":"Prestons",
    "sg:classifiers":[
        {
            "category":"Retail",
            "subcategory":"Repair Shop",
            "type":"Services"
        }
    ],
    "sg:phone":"+61 2 9825 9000",
    "sg:postcode":"2170",
    "sg:province":"NSW",
    "sg:tags":[
        "maintenance",
        "pool",
        "swimming"
    ],
    "wof:name":"Stroud Pool & Spa Equipment",
    "wof:placetype":"venue"
},
  "geometry": {"coordinates":[150.889572144,-33.9343147278],"type":"Point"}
}