{
  "type": "Feature",
  "properties": {
    "addr:full":"323- 329 Bell St Preston VIC 3072",
    "addr:housenumber":"329",
    "addr:postcode":"3072",
    "addr:street":"Bell St",
    "iso:country":"AU",
    "sg:address":"323- 329 Bell St",
    "sg:city":"Preston",
    "sg:classifiers":[
        {
            "category":"Home & Garden",
            "subcategory":"Carpets & Floor Coverings",
            "type":"Retail Goods"
        }
    ],
    "sg:phone":"+61 3 9484 3434",
    "sg:postcode":"3072",
    "sg:province":"VIC",
    "sg:tags":[
        "mattress"
    ],
    "wof:name":"Becks Bedding",
    "wof:placetype":"venue"
},
  "geometry": {"coordinates":[145.00209045400001,-37.745262146],"type":"Point"}
}