{
  "type": "Feature",
  "properties": {
    "addr:full":"5/ 10 Chetwynd St Merrylands NSW 2160",
    "addr:housenumber":"/ 10",
    "addr:postcode":"2160",
    "addr:street":"Chetwynd St",
    "iso:country":"AU",
    "sg:address":"5/ 10 Chetwynd St",
    "sg:city":"Merrylands",
    "sg:classifiers":[
        {
            "category":"Professional",
            "subcategory":"Art Services",
            "type":"Services"
        }
    ],
    "sg:phone":"+61 421 913 593",
    "sg:postcode":"2160",
    "sg:province":"NSW",
    "sg:tags":[
        "decorator",
        "painter"
    ],
    "wof:name":"B & R Painting & Decorating",
    "wof:placetype":"venue"
},
  "geometry": {"coordinates":[150.98245239299999,-33.8362922668],"type":"Point"}
}