{
  "type": "Feature",
  "properties": {
    "addr:full":"Lvl 27, 101 Collins St Melbourne VIC 3000",
    "addr:housenumber":"101",
    "addr:postcode":"3000",
    "addr:street":"Collins St",
    "iso:country":"AU",
    "sg:address":"Lvl 27, 101 Collins St",
    "sg:city":"Melbourne",
    "sg:classifiers":[
        {
            "category":"Structure",
            "subcategory":"Office Building",
            "type":"Public Place"
        }
    ],
    "sg:phone":"+61 3 9653 7444",
    "sg:postcode":"3000",
    "sg:province":"VIC",
    "sg:tags":[
        "serviced"
    ],
    "wof:name":"Servcorp",
    "wof:placetype":"venue"
},
  "geometry": {"coordinates":[144.97036743199999,-37.8144950867],"type":"Point"}
}