{
  "type": "Feature",
  "properties": {
    "addr:full":"1 Lea Ave Willoughby North NSW 2068",
    "addr:housenumber":"1",
    "addr:postcode":"2068",
    "addr:street":"Lea Ave",
    "iso:country":"AU",
    "sg:address":"1 Lea Ave",
    "sg:city":"Willoughby North",
    "sg:classifiers":[
        {
            "category":"Retail",
            "subcategory":"Storage",
            "type":"Services"
        }
    ],
    "sg:phone":"+61 2 9410 0404",
    "sg:postcode":"2068",
    "sg:province":"NSW",
    "sg:tags":[
        "removal",
        "furniture"
    ],
    "wof:name":"Hardwick Removals",
    "wof:placetype":"venue"
},
  "geometry": {"coordinates":[151.198608398,-33.799369812],"type":"Point"}
}