{
  "type": "Feature",
  "properties": {
    "addr:full":"27- 29 Lakewood Blv Braeside VIC 3195",
    "addr:housenumber":"29",
    "addr:postcode":"3195",
    "addr:street":"Lakewood Blv",
    "iso:country":"AU",
    "sg:address":"27- 29",
    "sg:city":"Lakewood Blv Braeside",
    "sg:classifiers":[
        {
            "category":"Building & Trades",
            "subcategory":"Pest Control",
            "type":"Services"
        }
    ],
    "sg:phone":"+61 3 9540 4600",
    "sg:postcode":"3195",
    "sg:province":"VIC",
    "sg:tags":[
        "part",
        "radio",
        "distributors"
    ],
    "wof:name":"Techaudio",
    "wof:placetype":"venue"
},
  "geometry": {"coordinates":[145.117477417,-38.0042610168],"type":"Point"}
}