{
  "type": "Feature",
  "properties": {
    "addr:full":"153 Lime Ave Mildura VIC 3500",
    "addr:housenumber":"153",
    "addr:postcode":"3500",
    "addr:street":"Lime Ave",
    "iso:country":"AU",
    "sg:address":"153 Lime Ave",
    "sg:city":"Mildura",
    "sg:classifiers":[
        {
            "category":"Health Services",
            "subcategory":"Health Practitioner",
            "type":"Services"
        }
    ],
    "sg:phone":"+61 3 5021 3142",
    "sg:postcode":"3500",
    "sg:province":"VIC",
    "sg:tags":[
        "physiotherapist"
    ],
    "wof:name":"Marcus Rawlings",
    "wof:placetype":"venue"
},
  "geometry": {"coordinates":[142.15554809599999,-34.1872406006],"type":"Point"}
}