{
  "type": "Feature",
  "properties": {
    "addr:full":"PO Box 1066 Merrylands NSW 2160",
    "addr:postcode":"2160",
    "iso:country":"AU",
    "sg:address":"PO Box 1066",
    "sg:city":"Merrylands",
    "sg:classifiers":[
        {
            "category":"Building & Trades",
            "subcategory":"Construction",
            "type":"Services"
        }
    ],
    "sg:phone":"+61 412 554 476",
    "sg:postcode":"2160",
    "sg:province":"NSW",
    "sg:tags":[
        "concrete",
        "contractor"
    ],
    "wof:name":"Form Concrete Pty Ltd",
    "wof:placetype":"venue"
},
  "geometry": {"coordinates":[150.98817443900001,-33.83618927],"type":"Point"}
}