{
  "type": "Feature",
  "properties": {
    "addr:full":"113 Exhibition St Melbourne VIC 3000",
    "addr:housenumber":"113",
    "addr:postcode":"3000",
    "addr:street":"Exhibition St",
    "iso:country":"AU",
    "sg:address":"113 Exhibition St",
    "sg:city":"Melbourne",
    "sg:classifiers":[
        {
            "category":"Professional",
            "subcategory":"Business Services",
            "type":"Services"
        }
    ],
    "sg:phone":"+61 13 22 15",
    "sg:postcode":"3000",
    "sg:province":"VIC",
    "sg:tags":[
        "small",
        "advisory"
    ],
    "wof:name":"Victorian Business Line",
    "wof:placetype":"venue"
},
  "geometry": {"coordinates":[144.970825195,-37.8129615784],"type":"Point"}
}