{
  "type": "Feature",
  "properties": {
    "iso:country":"AU",
    "sg:address":"112 Dales Rd",
    "sg:city":"Chevallum",
    "sg:classifiers":[
        {
            "category":"Building & Trades",
            "subcategory":"Construction",
            "type":"Services"
        }
    ],
    "sg:phone":"+61 413 943 480",
    "sg:postcode":"4555",
    "sg:province":"QLD",
    "sg:tags":[
        "scaffolding"
    ],
    "wof:name":"Access Guard",
    "wof:placetype":"venue"
},
  "geometry": {"coordinates":[152.98298645,-26.7069206238],"type":"Point"}
}