{
  "type": "Feature",
  "properties": {
    "addr:full":"6 Forth Rd Don TAS 7310",
    "addr:housenumber":"6",
    "addr:postcode":"7310",
    "addr:street":"Forth Rd",
    "iso:country":"AU",
    "sg:address":"6 Forth Rd",
    "sg:city":"Don",
    "sg:classifiers":[
        {
            "category":"Government",
            "subcategory":"Post Office",
            "type":"Public Place"
        }
    ],
    "sg:phone":"+61 3 6424 1425",
    "sg:postcode":"7310",
    "sg:province":"TAS",
    "sg:tags":[
        "postal"
    ],
    "wof:name":"Australia Post",
    "wof:placetype":"venue"
},
  "geometry": {"coordinates":[146.31837463400001,-41.1823768616],"type":"Point"}
}