{
  "type": "Feature",
  "properties": {
    "addr:full":"5/ 17 Katanning St Bayswater WA 6053",
    "addr:housenumber":"/ 17",
    "addr:postcode":"6053",
    "addr:street":"Katanning St",
    "iso:country":"AU",
    "sg:address":"5/ 17 Katanning St",
    "sg:city":"Bayswater",
    "sg:classifiers":[
        {
            "category":"Professional",
            "subcategory":"Detective & Security Services",
            "type":"Services"
        }
    ],
    "sg:phone":"+61 8 9377 3129",
    "sg:postcode":"6053",
    "sg:province":"WA",
    "sg:tags":[
        "equipment",
        "window",
        "doors"
    ],
    "wof:name":"Character Gatemakers",
    "wof:placetype":"venue"
},
  "geometry": {"coordinates":[115.929588318,-31.919298172],"type":"Point"}
}