{
  "type": "Feature",
  "properties": {
    "iso:country":"AU",
    "sg:address":"25 Mudjimba Beach Rd",
    "sg:city":"Mudjimba",
    "sg:classifiers":[
        {
            "category":"Health Services",
            "subcategory":"Chiropractor",
            "type":"Services"
        }
    ],
    "sg:phone":"+61 7 5448 9544",
    "sg:postcode":"4564",
    "sg:province":"QLD",
    "wof:name":"Linda Power Dr",
    "wof:placetype":"venue"
},
  "geometry": {"coordinates":[153.09759521500001,-26.6156024933],"type":"Point"}
}