{
  "type": "Feature",
  "properties": {
    "addr:full":"PO Box 784 Wangaratta VIC 3677",
    "addr:postcode":"3677",
    "iso:country":"AU",
    "sg:address":"PO Box 784",
    "sg:city":"Wangaratta",
    "sg:classifiers":[
        {
            "category":"Shopping",
            "subcategory":"News",
            "type":"Retail Goods"
        }
    ],
    "sg:phone":"+61 3 5722 1250",
    "sg:postcode":"3677",
    "sg:province":"VIC",
    "sg:tags":[
        "magazine",
        "periodical"
    ],
    "wof:name":"Australian Rallysport News",
    "wof:placetype":"venue"
},
  "geometry": {"coordinates":[146.318527222,-36.3704109192],"type":"Point"}
}