{
  "type": "Feature",
  "properties": {
    "addr:full":"1 Cuddihy Crt Lovely Banks VIC 3221",
    "addr:housenumber":"1",
    "addr:postcode":"3221",
    "addr:street":"Cuddihy Crt",
    "iso:country":"AU",
    "sg:address":"1 Cuddihy Crt",
    "sg:city":"Lovely Banks",
    "sg:classifiers":[
        {
            "category":"Building & Trades",
            "subcategory":"Cleaning & Sanitation",
            "type":"Services"
        }
    ],
    "sg:phone":"+61 3 5274 9600",
    "sg:postcode":"3221",
    "sg:province":"VIC",
    "sg:tags":[
        "cleaner",
        "repairer",
        "roof"
    ],
    "wof:name":"Cockerell R.J.",
    "wof:placetype":"venue"
},
  "geometry": {"coordinates":[144.32440199999999,-38.075333],"type":"Point"}
}