{
  "type": "Feature",
  "properties": {
    "addr:full":"Cnr Centre & Richmond Sts Casino NSW 2470",
    "addr:postcode":"2470",
    "iso:country":"AU",
    "sg:address":"Cnr Centre & Richmond Sts",
    "sg:city":"Casino",
    "sg:classifiers":[
        {
            "category":"Fast Food",
            "type":"Food & Drink"
        }
    ],
    "sg:phone":"+61 2 6662 4488",
    "sg:postcode":"2470",
    "sg:province":"NSW",
    "sg:tags":[
        "away",
        "take"
    ],
    "wof:name":"Chicken Express",
    "wof:placetype":"venue"
},
  "geometry": {"coordinates":[153.04786682100001,-28.8585395813],"type":"Point"}
}