{
  "type": "Feature",
  "properties": {
    "iso:country":"AU",
    "sg:address":"19 South St",
    "sg:city":"Wodonga",
    "sg:classifiers":[
        {
            "category":"Home & Garden",
            "subcategory":"Building Materials",
            "type":"Retail Goods"
        }
    ],
    "sg:phone":"+61 2 6024 7399",
    "sg:postcode":"3690",
    "sg:province":"VIC",
    "sg:tags":[
        "fitting",
        "door"
    ],
    "wof:name":"Wodonga Joinery",
    "wof:placetype":"venue"
},
  "geometry": {"coordinates":[146.88832092300001,-36.1183395386],"type":"Point"}
}