{
  "type": "Feature",
  "properties": {
    "addr:full":"7 Wynyard St Sydney NSW 2000",
    "addr:housenumber":"7",
    "addr:postcode":"2000",
    "addr:street":"Wynyard St",
    "iso:country":"AU",
    "sg:address":"7 Wynyard St",
    "sg:city":"Sydney",
    "sg:classifiers":[
        {
            "category":"Banks & Credit Unions",
            "subcategory":"Bank",
            "type":"Services"
        }
    ],
    "sg:phone":"+61 2 9299 2764",
    "sg:postcode":"2000",
    "sg:province":"NSW",
    "wof:name":"Banks ' Clearing House",
    "wof:placetype":"venue"
},
  "geometry": {"coordinates":[151.20690918,-33.8671035767],"type":"Point"}
}