{
  "type": "Feature",
  "properties": {
    "iso:country":"AU",
    "sg:address":"Unit 5, 32 Robinson Ave",
    "sg:city":"Belmont",
    "sg:classifiers":[
        {
            "category":"Wholesale",
            "subcategory":"Auto Parts",
            "type":"Manufacturing & Wholesale Goods"
        }
    ],
    "sg:phone":"+61 8 9479 3222",
    "sg:postcode":"6104",
    "sg:province":"WA",
    "sg:tags":[
        "transmission",
        "automotive",
        "truck"
    ],
    "wof:name":"Independent Automatics (W.A)",
    "wof:placetype":"venue"
},
  "geometry": {"coordinates":[115.922607422,-31.9538116455],"type":"Point"}
}