{
  "type": "Feature",
  "properties": {
    "addr:full":"6/ 11 Nerrima Crt Cooloongup WA 6168",
    "addr:housenumber":"/ 11",
    "addr:postcode":"6168",
    "addr:street":"Nerrima Crt",
    "iso:country":"AU",
    "sg:address":"6/ 11 Nerrima Crt",
    "sg:city":"Cooloongup",
    "sg:classifiers":[
        {
            "category":"Autos & Motor Vehicles",
            "subcategory":"Boat Sales",
            "type":"Retail Goods"
        }
    ],
    "sg:phone":"+61 413 774 739",
    "sg:postcode":"6168",
    "sg:province":"WA",
    "sg:tags":[
        "builder",
        "yacht",
        "repairer"
    ],
    "wof:name":"RVH Solutions",
    "wof:placetype":"venue"
},
  "geometry": {"coordinates":[115.752769,-32.296822],"type":"Point"}
}