{
  "type": "Feature",
  "properties": {
    "addr:full":"Osbornes Rd Bunbartha VIC 3634",
    "addr:postcode":"3634",
    "addr:street":"Osbornes Rd",
    "iso:country":"AU",
    "sg:address":"Osbornes Rd",
    "sg:city":"Bunbartha",
    "sg:classifiers":[
        {
            "category":"Food & Beverages",
            "subcategory":"Fruits & Vegetables",
            "type":"Retail Goods"
        }
    ],
    "sg:phone":"+61 3 5826 9468",
    "sg:postcode":"3634",
    "sg:province":"VIC",
    "sg:tags":[
        "wholesale"
    ],
    "wof:name":"Bunbartha (Fruit Packers) Pty Ltd",
    "wof:placetype":"venue"
},
  "geometry": {"coordinates":[145.34327697800001,-36.1760406494],"type":"Point"}
}