{
  "type": "Feature",
  "properties": {
    "addr:full":"19 Lawrence Drv Nerang QLD 4211",
    "addr:housenumber":"19",
    "addr:postcode":"4211",
    "addr:street":"Lawrence Drv",
    "iso:country":"AU",
    "sg:address":"19 Lawrence Drv",
    "sg:city":"Nerang",
    "sg:classifiers":[
        {
            "category":"Building & Trades",
            "subcategory":"Construction",
            "type":"Services"
        }
    ],
    "sg:phone":"+61 7 5527 2577",
    "sg:postcode":"4211",
    "sg:province":"QLD",
    "sg:tags":[
        "welding"
    ],
    "wof:name":"ASAP Welding Repairs",
    "wof:placetype":"venue"
},
  "geometry": {"coordinates":[153.347045898,-27.9967327118],"type":"Point"}
}