{
  "type": "Feature",
  "properties": {
    "iso:country":"AU",
    "sg:address":"3 / 114 Bent St",
    "sg:city":"Northcote",
    "sg:classifiers":[
        {
            "category":"Professional",
            "subcategory":"Employment Agencies",
            "type":"Services"
        }
    ],
    "sg:phone":"+61 3 9486 4445",
    "sg:postcode":"3070",
    "sg:province":"VIC",
    "sg:tags":[
        "entertainer",
        "agent"
    ],
    "wof:name":"Magic Unlimited",
    "wof:placetype":"venue"
},
  "geometry": {"coordinates":[144.991394,-37.766396],"type":"Point"}
}