{
  "type": "Feature",
  "properties": {
    "iso:country":"AU",
    "sg:address":"34 Glenrose Crt",
    "sg:city":"Belrose",
    "sg:classifiers":[
        {
            "category":"Health Services",
            "subcategory":"Optometrist",
            "type":"Services"
        }
    ],
    "sg:phone":"+61 1300 797 975",
    "sg:postcode":"2085",
    "sg:province":"NSW",
    "wof:name":"Eyecare Plus Optometrists",
    "wof:placetype":"venue"
},
  "geometry": {"coordinates":[151.209259033,-33.7398033142],"type":"Point"}
}