{
  "type": "Feature",
  "properties": {
    "addr:full":"15a Ridge St Nambucca Heads NSW 2448",
    "addr:housenumber":"15a",
    "addr:postcode":"2448",
    "addr:street":"Ridge St",
    "iso:country":"AU",
    "sg:address":"15a Ridge St",
    "sg:city":"Nambucca Heads",
    "sg:classifiers":[
        {
            "category":"Shopping",
            "subcategory":"Clothing, Apparel, & Fashions",
            "type":"Retail Goods"
        }
    ],
    "sg:phone":"+61 2 6569 4489",
    "sg:postcode":"2448",
    "sg:province":"NSW",
    "sg:tags":[
        "recycled",
        "clothing"
    ],
    "wof:name":"D\ufffdj\ufffd Vu Clothing & Accessories",
    "wof:placetype":"venue"
},
  "geometry": {"coordinates":[153.003052,-30.642149],"type":"Point"}
}