{
  "type": "Feature",
  "properties": {
    "addr:full":"23B Badham St Dickson ACT 2602",
    "addr:housenumber":"23b",
    "addr:postcode":"2602",
    "addr:street":"Badham St",
    "iso:country":"AU",
    "sg:address":"23B Badham St",
    "sg:city":"Dickson",
    "sg:classifiers":[
        {
            "category":"Personal",
            "subcategory":"Beauty Salon",
            "type":"Services"
        }
    ],
    "sg:phone":"+61 2 6257 9822",
    "sg:postcode":"2602",
    "sg:province":"ACT",
    "sg:tags":[
        "hairdresser"
    ],
    "wof:name":"Michelle's Hair & Beauty",
    "wof:placetype":"venue"
},
  "geometry": {"coordinates":[149.13763427699999,-35.2504920959],"type":"Point"}
}