{
  "type": "Feature",
  "properties": {
    "iso:country":"AU",
    "sg:address":"14 Church St",
    "sg:city":"Greensborough",
    "sg:classifiers":[
        {
            "category":"Shopping",
            "type":"Retail Goods"
        }
    ],
    "sg:phone":"+61 3 9435 5762",
    "sg:postcode":"3088",
    "sg:province":"VIC",
    "sg:tags":[
        "supply",
        "religious",
        "church"
    ],
    "wof:name":"Christian Book Centre Greensborough",
    "wof:placetype":"venue"
},
  "geometry": {"coordinates":[145.10226440400001,-37.7034606934],"type":"Point"}
}