{
  "type": "Feature",
  "properties": {
    "addr:full":"19/ 20 Thurston St Tingalpa QLD 4173",
    "addr:housenumber":"19 / 20",
    "addr:postcode":"4173",
    "addr:street":"Thurston St",
    "iso:country":"AU",
    "sg:address":"19/ 20 Thurston St",
    "sg:city":"Tingalpa",
    "sg:classifiers":[
        {
            "category":"School Buses",
            "type":"Transportation"
        }
    ],
    "sg:phone":"+61 7 3890 3368",
    "sg:postcode":"4173",
    "sg:province":"QLD",
    "sg:tags":[
        "nanny"
    ],
    "wof:name":"JCR Nannies Abroad",
    "wof:placetype":"venue"
},
  "geometry": {"coordinates":[153.129806519,-27.4828052521],"type":"Point"}
}