{
  "type": "Feature",
  "properties": {
    "addr:full":"Warringah Mall Shopping Centre 327a Old Pitwater Rd Brookvale NSW 2100",
    "addr:housenumber":"327a",
    "addr:postcode":"2100",
    "addr:street":"Centre;Old Pitwater Rd",
    "iso:country":"AU",
    "sg:address":"Warringah Mall Shopping Centre 327a Old Pitwater Rd",
    "sg:city":"Brookvale",
    "sg:classifiers":[
        {
            "category":"Shopping",
            "subcategory":"Clothing, Apparel, & Fashions",
            "type":"Retail Goods"
        }
    ],
    "sg:phone":"+61 2 9939 3544",
    "sg:postcode":"2100",
    "sg:province":"NSW",
    "sg:tags":[
        "accessory"
    ],
    "wof:name":"Equip",
    "wof:placetype":"venue"
},
  "geometry": {"coordinates":[151.26588439899999,-33.7702178955],"type":"Point"}
}