{
  "type": "Feature",
  "properties": {
    "iso:country":"AU",
    "sg:address":"Warialda St",
    "sg:city":"Yetman",
    "sg:classifiers":[
        {
            "category":"Education",
            "subcategory":"School",
            "type":"Public Place"
        }
    ],
    "sg:phone":"+61 7 4675 3150",
    "sg:postcode":"2410",
    "sg:province":"NSW",
    "sg:tags":[
        "state",
        "except",
        "nsw"
    ],
    "wof:name":"Yetman Primary School",
    "wof:placetype":"venue"
},
  "geometry": {"coordinates":[150.78016662600001,-28.9052906036],"type":"Point"}
}