{
  "type": "Feature",
  "properties": {
    "iso:country":"AU",
    "sg:address":"Celeber Drv",
    "sg:city":"North Mackay",
    "sg:classifiers":[
        {
            "category":"Education",
            "subcategory":"School",
            "type":"Public Place"
        }
    ],
    "sg:phone":"+61 7 4969 2000",
    "sg:postcode":"4740",
    "sg:province":"QLD",
    "sg:website":"http://www.was.qld.edu.au",
    "wof:name":"Whitsunday Anglican School",
    "wof:placetype":"venue"
},
  "geometry": {"coordinates":[149.173157,-21.101654],"type":"Point"}
}