{
  "type": "Feature",
  "properties": {
    "addr:full":"3/ 14 Blackwood St Townsville QLD 4810",
    "addr:housenumber":"/ 14",
    "addr:postcode":"4810",
    "addr:street":"Blackwood St",
    "iso:country":"AU",
    "sg:address":"3/ 14 Blackwood St",
    "sg:city":"Townsville",
    "sg:classifiers":[
        {
            "category":"Professional",
            "subcategory":"Art Services",
            "type":"Services"
        }
    ],
    "sg:phone":"+61 7 4721 2488",
    "sg:postcode":"4810",
    "sg:province":"QLD",
    "sg:tags":[
        "interior",
        "decorator"
    ],
    "wof:name":"Urbanite Design",
    "wof:placetype":"venue"
},
  "geometry": {"coordinates":[146.81279000000001,-19.261705],"type":"Point"}
}