{
  "type": "Feature",
  "properties": {
    "iso:country":"AU",
    "sg:address":"3 Wakool St",
    "sg:city":"Barham",
    "sg:classifiers":[
        {
            "category":"Shopping",
            "type":"Retail Goods"
        }
    ],
    "sg:phone":"+61 3 5453 2019",
    "sg:postcode":"2732",
    "sg:province":"VIC",
    "sg:tags":[
        "agent",
        "stock"
    ],
    "wof:name":"Bernard M Ryan & Co",
    "wof:placetype":"venue"
},
  "geometry": {"coordinates":[144.128464,-35.627995],"type":"Point"}
}