{
  "type": "Feature",
  "properties": {
    "addr:full":"5 Anglo Rd Greenwich NSW 2065",
    "addr:housenumber":"5",
    "addr:postcode":"2065",
    "addr:street":"Anglo Rd",
    "iso:country":"AU",
    "sg:address":"5 Anglo Rd",
    "sg:city":"Greenwich",
    "sg:classifiers":[
        {
            "category":"Health Services",
            "subcategory":"Health Practitioner",
            "type":"Services"
        }
    ],
    "sg:phone":"+61 2 9966 8863",
    "sg:postcode":"2065",
    "sg:province":"NSW",
    "sg:tags":[
        "physiotherapist"
    ],
    "wof:name":"Stillness Centre",
    "wof:placetype":"venue"
},
  "geometry": {"coordinates":[151.18882751500001,-33.8256912231],"type":"Point"}
}