{
  "type": "Feature",
  "properties": {
    "addr:full":"PO Box 412 Leederville WA 6903",
    "addr:postcode":"6903",
    "iso:country":"AU",
    "sg:address":"PO Box 412",
    "sg:city":"Leederville",
    "sg:classifiers":[
        {
            "category":"Home & Garden",
            "subcategory":"Building Materials",
            "type":"Retail Goods"
        }
    ],
    "sg:phone":"+61 1300 727 336",
    "sg:postcode":"6903",
    "sg:province":"WA",
    "sg:tags":[
        "insect",
        "screen"
    ],
    "wof:name":"Freedom Retractable Screens",
    "wof:placetype":"venue"
},
  "geometry": {"coordinates":[115.8412323,-31.9364795685],"type":"Point"}
}