{
  "type": "Feature",
  "properties": {
    "addr:full":"133 Alexander St Crows Nest NSW 2065",
    "addr:housenumber":"133",
    "addr:postcode":"2065",
    "addr:street":"Alexander St",
    "iso:country":"AU",
    "sg:address":"133 Alexander St",
    "sg:city":"Crows Nest",
    "sg:classifiers":[
        {
            "category":"Home & Garden",
            "subcategory":"Carpets & Floor Coverings",
            "type":"Retail Goods"
        }
    ],
    "sg:phone":"+61 2 9965 7221",
    "sg:postcode":"2065",
    "sg:province":"NSW",
    "sg:tags":[
        "tile",
        "wall"
    ],
    "wof:name":"Australian Building Ceramics Pty Ltd",
    "wof:placetype":"venue"
},
  "geometry": {"coordinates":[151.202835083,-33.8244018555],"type":"Point"}
}