{
  "type": "Feature",
  "properties": {
    "addr:full":"Level 19, 201 Kent St Sydney NSW 2000",
    "addr:housenumber":"201",
    "addr:postcode":"2000",
    "addr:street":"Kent St",
    "iso:country":"AU",
    "sg:address":"Level 19, 201 Kent St",
    "sg:city":"Sydney",
    "sg:classifiers":[
        {
            "category":"Health Services",
            "subcategory":"Nursing And Care Facility",
            "type":"Services"
        }
    ],
    "sg:phone":"+61 1300 302 350",
    "sg:postcode":"2000",
    "sg:province":"NSW",
    "sg:tags":[
        "home"
    ],
    "wof:name":"Amity Group Pty Ltd",
    "wof:placetype":"venue"
},
  "geometry": {"coordinates":[151.20382690400001,-33.8636398315],"type":"Point"}
}