{
  "type": "Feature",
  "properties": {
    "iso:country":"AU",
    "sg:address":"St Agnes Shopping Shp 9 North East Rd",
    "sg:city":"St Agnes",
    "sg:classifiers":[
        {
            "category":"Food & Beverages",
            "subcategory":"Fruits & Vegetables",
            "type":"Retail Goods"
        }
    ],
    "sg:phone":"+61 8 8264 5483",
    "sg:postcode":"5097",
    "sg:province":"SA",
    "sg:tags":[
        "greengrocer",
        "fruiterer"
    ],
    "wof:name":"Sam's Fruit Market",
    "wof:placetype":"venue"
},
  "geometry": {"coordinates":[138.70928955100001,-34.8247947693],"type":"Point"}
}