{
  "type": "Feature",
  "properties": {
    "addr:full":"16 Elsey St Hawker ACT 2614",
    "addr:housenumber":"16",
    "addr:postcode":"2614",
    "addr:street":"Elsey St",
    "iso:country":"AU",
    "sg:address":"16 Elsey St",
    "sg:city":"Hawker",
    "sg:classifiers":[
        {
            "category":"Building & Trades",
            "subcategory":"Construction",
            "type":"Services"
        }
    ],
    "sg:phone":"+61 2 6254 7512",
    "sg:postcode":"2614",
    "sg:province":"ACT",
    "sg:tags":[
        "roof"
    ],
    "wof:name":"Petherbridge Roofing",
    "wof:placetype":"venue"
},
  "geometry": {"coordinates":[149.02989196799999,-35.2486572266],"type":"Point"}
}