{
  "type": "Feature",
  "properties": {
    "addr:full":"Shop 6, 20 Macquarie St Parramatta NSW 2150",
    "addr:housenumber":"shop;20",
    "addr:postcode":"2150",
    "addr:street":"Macquarie St",
    "iso:country":"AU",
    "sg:address":"Shop 6, 20 Macquarie St",
    "sg:city":"Parramatta",
    "sg:classifiers":[
        {
            "category":"Professional",
            "subcategory":"Employment Agencies",
            "type":"Services"
        }
    ],
    "sg:phone":"+61 2 9687 1033",
    "sg:postcode":"2150",
    "sg:province":"NSW",
    "wof:name":"Jobfind Centre",
    "wof:placetype":"venue"
},
  "geometry": {"coordinates":[150.94453430199999,-33.8707733154],"type":"Point"}
}