{
  "type": "Feature",
  "properties": {
    "iso:country":"AU",
    "sg:address":"2500 Gold Coast Hwy",
    "sg:city":"Mermaid Beach",
    "sg:classifiers":[
        {
            "category":"Travel",
            "subcategory":"Hotels & Motels",
            "type":"Entertainment"
        }
    ],
    "sg:phone":"+61 7 5526 6944",
    "sg:postcode":"4218",
    "sg:province":"QLD",
    "sg:tags":[
        "accommodation"
    ],
    "wof:name":"Mermaid Beach Tavern",
    "wof:placetype":"venue"
},
  "geometry": {"coordinates":[153.434204102,-28.0429401398],"type":"Point"}
}