{
  "type": "Feature",
  "properties": {
    "addr:full":"Shop 6 Fountain Crt Bendigo VIC 3550",
    "addr:housenumber":"shop 6",
    "addr:postcode":"3550",
    "addr:street":"Fountain Crt",
    "iso:country":"AU",
    "sg:address":"Shop 6 Fountain Crt",
    "sg:city":"Bendigo",
    "sg:classifiers":[
        {
            "category":"Ice Cream",
            "type":"Food & Drink"
        }
    ],
    "sg:phone":"+61 3 5442 4800",
    "sg:postcode":"3550",
    "sg:province":"VIC",
    "sg:tags":[
        "retail"
    ],
    "wof:name":"Bendigo Ice Creamery Cafe",
    "wof:placetype":"venue"
},
  "geometry": {"coordinates":[144.281692505,-36.7581253052],"type":"Point"}
}