{
  "type": "Feature",
  "properties": {
    "addr:full":"144 Northbourne Rd Campbellfield VIC 3061",
    "addr:housenumber":"144",
    "addr:postcode":"3061",
    "addr:street":"Northbourne Rd",
    "iso:country":"AU",
    "sg:address":"144 Northbourne Rd",
    "sg:city":"Campbellfield",
    "sg:classifiers":[
        {
            "category":"Home & Garden",
            "subcategory":"Building Materials",
            "type":"Retail Goods"
        }
    ],
    "sg:phone":"+61 3 9217 3888",
    "sg:postcode":"3061",
    "sg:province":"VIC",
    "sg:tags":[
        "wall",
        "frame",
        "truss",
        "roof"
    ],
    "sg:website":"http://www.designertruss.com",
    "wof:name":"Designer Truss Pty Ltd",
    "wof:placetype":"venue"
},
  "geometry": {"coordinates":[144.96678161599999,-37.6520767212],"type":"Point"}
}