{
  "type": "Feature",
  "properties": {
    "iso:country":"AU",
    "sg:address":"133 Middle Rd",
    "sg:city":"Devonport",
    "sg:classifiers":[
        {
            "category":"Organizations",
            "subcategory":"Non-profit Organization",
            "type":"Services"
        }
    ],
    "sg:phone":"+61 3 6424 6133",
    "sg:postcode":"7310",
    "sg:province":"TAS",
    "sg:tags":[
        "support",
        "disability",
        "organisation"
    ],
    "wof:name":"Devonfield Hawley Lodge",
    "wof:placetype":"venue"
},
  "geometry": {"coordinates":[146.344970703,-41.1936225891],"type":"Point"}
}