{
  "type": "Feature",
  "properties": {
    "addr:full":"Omeo Hwy Mitta Mitta VIC 3701",
    "addr:postcode":"3701",
    "addr:street":"Omeo Hwy",
    "iso:country":"AU",
    "sg:address":"Omeo Hwy",
    "sg:city":"Mitta Mitta",
    "sg:classifiers":[
        {
            "category":"Food & Beverages",
            "subcategory":"Groceries & Convenience Stores",
            "type":"Retail Goods"
        }
    ],
    "sg:phone":"+61 2 6072 3591",
    "sg:postcode":"3701",
    "sg:province":"VIC",
    "wof:name":"Mitta General Store",
    "wof:placetype":"venue"
},
  "geometry": {"coordinates":[147.37411499000001,-36.5378189087],"type":"Point"}
}