{
  "type": "Feature",
  "properties": {
    "addr:full":"8 Korina Crt Langwarrin VIC 3910",
    "addr:housenumber":"8",
    "addr:postcode":"3910",
    "addr:street":"Korina Crt",
    "iso:country":"AU",
    "sg:address":"8 Korina Crt",
    "sg:city":"Langwarrin",
    "sg:classifiers":[
        {
            "category":"Building & Trades",
            "subcategory":"Construction",
            "type":"Services"
        }
    ],
    "sg:phone":"+61 409 148 466",
    "sg:postcode":"3910",
    "sg:province":"VIC",
    "sg:tags":[
        "concrete",
        "contractor"
    ],
    "wof:name":"Allcrete Concepts",
    "wof:placetype":"venue"
},
  "geometry": {"coordinates":[145.18605041500001,-38.1643218994],"type":"Point"}
}