{
  "type": "Feature",
  "properties": {
    "addr:full":"17 John St Kew VIC 3101",
    "addr:housenumber":"17",
    "addr:postcode":"3101",
    "addr:street":"John St",
    "iso:country":"AU",
    "sg:address":"17 John St",
    "sg:city":"Kew",
    "sg:classifiers":[
        {
            "category":"Real Estate",
            "subcategory":"Real Estate Agent",
            "type":"Services"
        }
    ],
    "sg:phone":"+61 3 9817 1454",
    "sg:postcode":"3101",
    "sg:province":"VIC",
    "wof:name":"Nicholls Gledhill & Co",
    "wof:placetype":"venue"
},
  "geometry": {"coordinates":[145.051971436,-37.8108100891],"type":"Point"}
}