{
  "type": "Feature",
  "properties": {
    "addr:full":"9a Production Ave Molendinar QLD 4214",
    "addr:housenumber":"9a",
    "addr:postcode":"4214",
    "addr:street":"Production Ave",
    "iso:country":"AU",
    "sg:address":"9a Production Ave",
    "sg:city":"Molendinar",
    "sg:classifiers":[
        {
            "category":"Autos & Motor Vehicles",
            "subcategory":"Boat Sales",
            "type":"Retail Goods"
        }
    ],
    "sg:phone":"+61 7 5571 5277",
    "sg:postcode":"4214",
    "sg:province":"QLD",
    "sg:tags":[
        "builder",
        "yacht",
        "repairer"
    ],
    "wof:name":"Blue Fin Boat",
    "wof:placetype":"venue"
},
  "geometry": {"coordinates":[153.36203002900001,-27.9680957794],"type":"Point"}
}