{
  "type": "Feature",
  "properties": {
    "addr:full":"Lot 2 Ipswich-Boonah Rd Boonah QLD 4310",
    "addr:postcode":"4310",
    "addr:street":"Ipswich-Boonah Rd",
    "iso:country":"AU",
    "sg:address":"Lot 2 Ipswich-Boonah Rd",
    "sg:city":"Boonah",
    "sg:classifiers":[
        {
            "category":"Travel",
            "subcategory":"Hotels & Motels",
            "type":"Entertainment"
        }
    ],
    "sg:phone":"+61 7 5463 4738",
    "sg:postcode":"4310",
    "sg:province":"QLD",
    "sg:tags":[
        "accommodation"
    ],
    "wof:name":"Boonah Valley Motel",
    "wof:placetype":"venue"
},
  "geometry": {"coordinates":[152.70806884800001,-27.9793586731],"type":"Point"}
}