{
  "type": "Feature",
  "properties": {
    "iso:country":"AU",
    "sg:address":"157 Paradise St",
    "sg:city":"Mackay",
    "sg:classifiers":[
        {
            "category":"Building & Trades",
            "subcategory":"Construction",
            "type":"Services"
        }
    ],
    "sg:phone":"+61 7 4952 5135",
    "sg:postcode":"4740",
    "sg:province":"QLD",
    "sg:tags":[
        "concrete",
        "contractor"
    ],
    "wof:name":"QCCS Qld Complete Contracting Services",
    "wof:placetype":"venue"
},
  "geometry": {"coordinates":[149.16250600000001,-21.16695],"type":"Point"}
}