{
  "type": "Feature",
  "properties": {
    "addr:full":"PO Box 433 Narooma NSW 2546",
    "addr:postcode":"2546",
    "iso:country":"AU",
    "sg:address":"PO Box 433",
    "sg:city":"Narooma",
    "sg:classifiers":[
        {
            "category":"Retail",
            "subcategory":"Auto Repair",
            "type":"Services"
        }
    ],
    "sg:phone":"+61 2 4476 1670",
    "sg:postcode":"2546",
    "sg:province":"NSW",
    "sg:tags":[
        "electrical"
    ],
    "wof:name":"Narooma Mobile Auto Electrical",
    "wof:placetype":"venue"
},
  "geometry": {"coordinates":[150.132324219,-36.2188415527],"type":"Point"}
}