{
  "type": "Feature",
  "properties": {
    "iso:country":"AU",
    "sg:address":"1/ 160 Hampstead Rd",
    "sg:city":"Broadview",
    "sg:classifiers":[
        {
            "category":"Farming",
            "subcategory":"Fish & Marine Products",
            "type":"Manufacturing & Wholesale Goods"
        }
    ],
    "sg:phone":"+61 8 8261 3027",
    "sg:postcode":"5083",
    "sg:province":"SA",
    "sg:tags":[
        "organic"
    ],
    "wof:name":"It's Organic",
    "wof:placetype":"venue"
},
  "geometry": {"coordinates":[138.61871337900001,-34.867816925],"type":"Point"}
}