{
  "type": "Feature",
  "properties": {
    "addr:full":"14 Ridgewood Crt Burleigh Waters QLD 4220",
    "addr:housenumber":"14",
    "addr:postcode":"4220",
    "addr:street":"Ridgewood Crt",
    "iso:country":"AU",
    "sg:address":"14 Ridgewood Crt",
    "sg:city":"Burleigh Waters",
    "sg:classifiers":[
        {
            "category":"Building & Trades",
            "subcategory":"Construction",
            "type":"Services"
        }
    ],
    "sg:phone":"+61 7 5576 1856",
    "sg:postcode":"4220",
    "sg:province":"QLD",
    "sg:tags":[
        "concrete",
        "contractor"
    ],
    "wof:name":"Budget Concreting",
    "wof:placetype":"venue"
},
  "geometry": {"coordinates":[153.42349243199999,-28.0913105011],"type":"Point"}
}