{
  "type": "Feature",
  "properties": {
    "addr:full":"71 Railway Rd Quakers Hill NSW 2763",
    "addr:housenumber":"71",
    "addr:postcode":"2763",
    "addr:street":"Railway Rd",
    "iso:country":"AU",
    "sg:address":"71 Railway Rd",
    "sg:city":"Quakers Hill",
    "sg:classifiers":[
        {
            "category":"Freight",
            "type":"Transportation"
        }
    ],
    "sg:phone":"+61 412 181 535",
    "sg:postcode":"2763",
    "sg:province":"NSW",
    "sg:tags":[
        "car",
        "carrier",
        "transporting"
    ],
    "wof:name":"Stapley's Car Carrying",
    "wof:placetype":"venue"
},
  "geometry": {"coordinates":[150.888671875,-33.730758667],"type":"Point"}
}