{
  "type": "Feature",
  "properties": {
    "iso:country":"AU",
    "sg:address":"Bligh Pl",
    "sg:city":"Randwick",
    "sg:classifiers":[
        {
            "category":"Building & Trades",
            "subcategory":"Cleaning & Sanitation",
            "type":"Services"
        }
    ],
    "sg:phone":"+61 2 9399 6048",
    "sg:postcode":"2031",
    "sg:province":"NSW",
    "sg:tags":[
        "window"
    ],
    "wof:name":"Best Prices Window Cleaning",
    "wof:placetype":"venue"
},
  "geometry": {"coordinates":[151.248336792,-33.9092521667],"type":"Point"}
}