{
  "type": "Feature",
  "properties": {
    "addr:full":"94 McLeod St Cairns QLD 4870",
    "addr:housenumber":"94",
    "addr:postcode":"4870",
    "addr:street":"Mcleod St",
    "iso:country":"AU",
    "sg:address":"94 McLeod St",
    "sg:city":"Cairns",
    "sg:classifiers":[
        {
            "category":"Autos & Motor Vehicles",
            "subcategory":"Automobile Sales",
            "type":"Retail Goods"
        }
    ],
    "sg:phone":"+61 7 4031 3000",
    "sg:postcode":"4870",
    "sg:province":"QLD",
    "sg:tags":[
        "car",
        "new"
    ],
    "wof:name":"Broadley Hyundai",
    "wof:placetype":"venue"
},
  "geometry": {"coordinates":[145.76890564000001,-16.9197807312],"type":"Point"}
}