{
  "type": "Feature",
  "properties": {
    "addr:full":"25 Forth Rd Don TAS 7310",
    "addr:housenumber":"25",
    "addr:postcode":"7310",
    "addr:street":"Forth Rd",
    "iso:country":"AU",
    "sg:address":"25 Forth Rd",
    "sg:city":"Don",
    "sg:classifiers":[
        {
            "category":"Building & Trades",
            "subcategory":"Cleaning & Sanitation",
            "type":"Services"
        }
    ],
    "sg:phone":"+61 3 6424 5551",
    "sg:postcode":"7310",
    "sg:province":"TAS",
    "sg:tags":[
        "window"
    ],
    "wof:name":"Mirror Like Cleaners",
    "wof:placetype":"venue"
},
  "geometry": {"coordinates":[146.3152771,-41.1835021973],"type":"Point"}
}