{
  "type": "Feature",
  "properties": {
    "iso:country":"AU",
    "sg:address":"440 Goodwood Rd",
    "sg:city":"Cumberland Park",
    "sg:classifiers":[
        {
            "category":"Professional",
            "subcategory":"Accounting & Tax Preparation",
            "type":"Services"
        }
    ],
    "sg:phone":"+61 8 8272 9851",
    "sg:postcode":"5041",
    "sg:province":"SA",
    "sg:tags":[
        "accountant",
        "auditor"
    ],
    "wof:name":"Evans Partners",
    "wof:placetype":"venue"
},
  "geometry": {"coordinates":[138.591156,-34.972965],"type":"Point"}
}