{
  "type": "Feature",
  "properties": {
    "addr:full":"196 Maitland Rd Islington NSW 2296",
    "addr:housenumber":"196",
    "addr:postcode":"2296",
    "addr:street":"Maitland Rd",
    "iso:country":"AU",
    "sg:address":"196 Maitland Rd",
    "sg:city":"Islington",
    "sg:classifiers":[
        {
            "category":"Retail",
            "subcategory":"Car Wash",
            "type":"Services"
        }
    ],
    "sg:phone":"+61 2 4962 5778",
    "sg:postcode":"2296",
    "sg:province":"NSW",
    "sg:tags":[
        "truck",
        "cleaning"
    ],
    "wof:name":"Classic Hand Car Wash",
    "wof:placetype":"venue"
},
  "geometry": {"coordinates":[151.74707031200001,-32.9135475159],"type":"Point"}
}