{
  "type": "Feature",
  "properties": {
    "addr:full":"Cnr Beaufort & Salisbury Sts Inglewood WA 6052",
    "addr:postcode":"6052",
    "addr:street":"Cnr",
    "iso:country":"AU",
    "sg:address":"Cnr Beaufort & Salisbury Sts",
    "sg:city":"Inglewood",
    "sg:classifiers":[
        {
            "category":"Communications",
            "subcategory":"Film & Video Production",
            "type":"Services"
        }
    ],
    "sg:phone":"+61 8 9371 6699",
    "sg:postcode":"6052",
    "sg:province":"WA",
    "sg:tags":[
        "dvd",
        "library"
    ],
    "wof:name":"Video Ezy",
    "wof:placetype":"venue"
},
  "geometry": {"coordinates":[115.886863709,-31.9205932617],"type":"Point"}
}