{
  "type": "Feature",
  "properties": {
    "addr:full":"1370 Toorak Rd Burwood VIC 3125",
    "addr:housenumber":"1370",
    "addr:postcode":"3125",
    "addr:street":"Toorak Rd",
    "iso:country":"AU",
    "sg:address":"1370 Toorak Rd",
    "sg:city":"Burwood",
    "sg:classifiers":[
        {
            "category":"Restaurant",
            "type":"Food & Drink"
        }
    ],
    "sg:phone":"+61 3 9889 7722",
    "sg:postcode":"3125",
    "sg:province":"VIC",
    "wof:name":"Dragon Phoenix Restaurant",
    "wof:placetype":"venue"
},
  "geometry": {"coordinates":[145.09312439000001,-37.8502502441],"type":"Point"}
}