{
  "type": "Feature",
  "properties": {
    "iso:country":"AU",
    "sg:address":"207 James St",
    "sg:city":"Toowoomba",
    "sg:classifiers":[
        {
            "category":"Autos & Motor Vehicles",
            "subcategory":"Automobile Sales",
            "type":"Retail Goods"
        }
    ],
    "sg:phone":"+61 7 4632 4257",
    "sg:postcode":"4350",
    "sg:province":"QLD",
    "sg:tags":[
        "equipment",
        "trailer"
    ],
    "wof:name":"Whitleys Welding Works",
    "wof:placetype":"venue"
},
  "geometry": {"coordinates":[151.950195,-27.568327],"type":"Point"}
}