{
  "type": "Feature",
  "properties": {
    "addr:full":"Unit 7, 71A Rhodes St Hillsdale NSW 2036",
    "addr:housenumber":"71a",
    "addr:postcode":"2036",
    "addr:street":"Rhodes St",
    "iso:country":"AU",
    "sg:address":"Unit 7, 71A Rhodes St",
    "sg:city":"Hillsdale",
    "sg:classifiers":[
        {
            "category":"Commercial Area",
            "type":"Public Place"
        }
    ],
    "sg:phone":"+61 2 9661 1380",
    "sg:postcode":"2036",
    "sg:province":"NSW",
    "sg:tags":[
        "clothing",
        "label"
    ],
    "wof:name":"Superb Labels",
    "wof:placetype":"venue"
},
  "geometry": {"coordinates":[151.226287842,-33.950378418],"type":"Point"}
}