{
  "type": "Feature",
  "properties": {
    "addr:full":"25 Ninth St Mildura VIC 3500",
    "addr:housenumber":"25",
    "addr:postcode":"3500",
    "addr:street":"Ninth St",
    "iso:country":"AU",
    "sg:address":"25 Ninth St",
    "sg:city":"Mildura",
    "sg:classifiers":[
        {
            "category":"Professional",
            "type":"Services"
        }
    ],
    "sg:phone":"+61 1300 366 684",
    "sg:postcode":"3500",
    "sg:province":"VIC",
    "sg:tags":[
        "transport"
    ],
    "wof:name":"Toll IPEC",
    "wof:placetype":"venue"
},
  "geometry": {"coordinates":[142.16900634800001,-34.1938438416],"type":"Point"}
}