{
  "type": "Feature",
  "properties": {
    "addr:full":"80 Benowa Rd Southport QLD 4215",
    "addr:housenumber":"80",
    "addr:postcode":"4215",
    "addr:street":"Benowa Rd",
    "iso:country":"AU",
    "sg:address":"80 Benowa Rd",
    "sg:city":"Southport",
    "sg:classifiers":[
        {
            "category":"Home & Garden",
            "subcategory":"Carpets & Floor Coverings",
            "type":"Retail Goods"
        }
    ],
    "sg:phone":"+61 7 5526 4599",
    "sg:postcode":"4215",
    "sg:province":"QLD",
    "wof:name":"Mark Green Consultants Pty Ltd",
    "wof:placetype":"venue"
},
  "geometry": {"coordinates":[153.402633667,-27.9891433716],"type":"Point"}
}