{
  "type": "Feature",
  "properties": {
    "addr:full":"73 Grattan St Carlton VIC 3053",
    "addr:housenumber":"73",
    "addr:postcode":"3053",
    "addr:street":"Grattan St",
    "iso:country":"AU",
    "sg:address":"73 Grattan St",
    "sg:city":"Carlton",
    "sg:classifiers":[
        {
            "category":"Professional",
            "subcategory":"Accounting & Tax Preparation",
            "type":"Services"
        }
    ],
    "sg:phone":"+61 3 9663 6952",
    "sg:postcode":"3053",
    "sg:province":"VIC",
    "sg:tags":[
        "accountant",
        "auditor"
    ],
    "wof:name":"Pearson Bernard",
    "wof:placetype":"venue"
},
  "geometry": {"coordinates":[144.96705627399999,-37.8008728027],"type":"Point"}
}