{
  "type": "Feature",
  "properties": {
    "iso:country":"AU",
    "sg:address":"Shop 2 152 Griffith St",
    "sg:city":"Coolangatta",
    "sg:classifiers":[
        {
            "category":"Internet Cafe",
            "subcategory":"None",
            "type":"Food & Drink"
        }
    ],
    "sg:phone":"+61 7 5599 4536",
    "sg:postcode":"4225",
    "sg:province":"QLD",
    "wof:name":"PBs Oz Internet Cafe",
    "wof:placetype":"venue"
},
  "geometry": {"coordinates":[153.54119873100001,-28.1687412262],"type":"Point"}
}