{
  "type": "Feature",
  "properties": {
    "iso:country":"AU",
    "sg:address":"11 Dalrymple Drv",
    "sg:city":"Gladstone",
    "sg:classifiers":[
        {
            "category":"Professional",
            "subcategory":"Engineering",
            "type":"Services"
        }
    ],
    "sg:phone":"+61 7 4979 3022",
    "sg:postcode":"4680",
    "sg:province":"QLD",
    "sg:tags":[
        "engineer"
    ],
    "wof:name":"Ribca Engineering Pty Ltd",
    "wof:placetype":"venue"
},
  "geometry": {"coordinates":[151.27064514200001,-23.8810844421],"type":"Point"}
}