{
  "type": "Feature",
  "properties": {
    "addr:full":"55 Queen St Busselton WA 6280",
    "addr:housenumber":"55",
    "addr:postcode":"6280",
    "addr:street":"Queen St",
    "iso:country":"AU",
    "sg:address":"55 Queen St",
    "sg:city":"Busselton",
    "sg:classifiers":[
        {
            "category":"Restaurant",
            "type":"Food & Drink"
        }
    ],
    "sg:phone":"+61 8 9754 7222",
    "sg:postcode":"6280",
    "sg:province":"WA",
    "wof:name":"Dee Samer Thai Restaurant",
    "wof:placetype":"venue"
},
  "geometry": {"coordinates":[115.34459686300001,-33.6495399475],"type":"Point"}
}