{
  "type": "Feature",
  "properties": {
    "addr:full":"1- 7 Francis Rd Wingfield SA 5013",
    "addr:housenumber":"7",
    "addr:postcode":"5013",
    "addr:street":"Francis Rd",
    "iso:country":"AU",
    "sg:address":"1- 7 Francis Rd",
    "sg:city":"Wingfield",
    "sg:classifiers":[
        {
            "category":"Home & Garden",
            "subcategory":"Building Materials",
            "type":"Retail Goods"
        }
    ],
    "sg:phone":"+61 1800 648 304",
    "sg:postcode":"5013",
    "sg:province":"SA",
    "sg:tags":[
        "fencing"
    ],
    "wof:name":"Rally DIY Fencing",
    "wof:placetype":"venue"
},
  "geometry": {"coordinates":[138.550323486,-34.8456687927],"type":"Point"}
}