{
  "type": "Feature",
  "properties": {
    "addr:full":"Market St Community Centre, 5 Market St Lismore NSW 2480",
    "addr:housenumber":"5",
    "addr:postcode":"2480",
    "addr:street":"Market;Market St",
    "iso:country":"AU",
    "sg:address":"Market St Community Centre, 5 Market St",
    "sg:city":"Lismore",
    "sg:classifiers":[
        {
            "category":"Government",
            "subcategory":"Court House",
            "type":"Public Place"
        }
    ],
    "sg:phone":"+61 2 6622 7003",
    "sg:postcode":"2480",
    "sg:province":"NSW",
    "sg:tags":[
        "personal",
        "marriage",
        "family",
        "counselling"
    ],
    "wof:name":"Lismore Family Relationship Centre",
    "wof:placetype":"venue"
},
  "geometry": {"coordinates":[153.27377319300001,-28.8111629486],"type":"Point"}
}