{
  "type": "Feature",
  "properties": {
    "iso:country":"AU",
    "sg:address":"22 Wireless Rd",
    "sg:city":"East Mt Gambier",
    "sg:classifiers":[
        {
            "category":"Manufacturing",
            "subcategory":"Motor Vehicles & Parts",
            "type":"Manufacturing & Wholesale Goods"
        }
    ],
    "sg:phone":"+61 8 8724 9500",
    "sg:postcode":"5290",
    "sg:province":"SA",
    "sg:tags":[
        "engine",
        "equipment",
        "diesel"
    ],
    "wof:name":"Hage Tractors & Implements Pty Ltd",
    "wof:placetype":"venue"
},
  "geometry": {"coordinates":[140.790985,-37.814751],"type":"Point"}
}