{
  "type": "Feature",
  "properties": {
    "addr:full":"10 Tokay La The Vines WA 6069",
    "addr:housenumber":"10",
    "addr:postcode":"6069",
    "addr:street":"Tokay La The",
    "iso:country":"AU",
    "sg:address":"10 Tokay La",
    "sg:city":"The Vines",
    "sg:classifiers":[
        {
            "category":"Professional",
            "subcategory":"Art Services",
            "type":"Services"
        }
    ],
    "sg:phone":"+61 412 255 981",
    "sg:postcode":"6069",
    "sg:province":"WA",
    "sg:tags":[
        "decorator",
        "painter"
    ],
    "wof:name":"R Peppiatt & Sons",
    "wof:placetype":"venue"
},
  "geometry": {"coordinates":[116.001296997,-31.7694816589],"type":"Point"}
}