{
  "type": "Feature",
  "properties": {
    "iso:country":"AU",
    "sg:address":"Unit 1, 36 Waverley Drv",
    "sg:city":"Unanderra",
    "sg:classifiers":[
        {
            "category":"Building & Trades",
            "subcategory":"Cleaning & Sanitation",
            "type":"Services"
        }
    ],
    "sg:phone":"+61 2 4272 3733",
    "sg:postcode":"2526",
    "sg:province":"NSW",
    "sg:tags":[
        "cleaner",
        "repairer",
        "roof"
    ],
    "wof:name":"The Leaf It To Me Group Pty Ltd",
    "wof:placetype":"venue"
},
  "geometry": {"coordinates":[150.844039917,-34.4587593079],"type":"Point"}
}