{
  "type": "Feature",
  "properties": {
    "iso:country":"AU",
    "sg:address":"16 Masons Drv",
    "sg:city":"North Parramatta",
    "sg:classifiers":[
        {
            "category":"Farming",
            "subcategory":"Livestock Farm",
            "type":"Manufacturing & Wholesale Goods"
        }
    ],
    "sg:phone":"+61 2 9683 3655",
    "sg:postcode":"2151",
    "sg:province":"NSW",
    "sg:tags":[
        "school",
        "theological"
    ],
    "wof:name":"United Theological College",
    "wof:placetype":"venue"
},
  "geometry": {"coordinates":[151.017303467,-33.7917442322],"type":"Point"}
}