{
  "type": "Feature",
  "properties": {
    "addr:full":"1 Karana St Tugun QLD 4224",
    "addr:housenumber":"1",
    "addr:postcode":"4224",
    "addr:street":"Karana St",
    "iso:country":"AU",
    "sg:address":"1 Karana St",
    "sg:city":"Tugun",
    "sg:classifiers":[
        {
            "category":"Health Services",
            "subcategory":"Dentist",
            "type":"Services"
        }
    ],
    "sg:phone":"+61 7 5534 7033",
    "sg:postcode":"4224",
    "sg:province":"QLD",
    "wof:name":"Providental",
    "wof:placetype":"venue"
},
  "geometry": {"coordinates":[153.49237060600001,-28.1429710388],"type":"Point"}
}