{
  "type": "Feature",
  "properties": {
    "addr:full":"Shp 3/ 505 Old South Head Rd Rose Bay NSW 2029",
    "addr:housenumber":"/ 505",
    "addr:postcode":"2029",
    "addr:street":"Old South Head Rd",
    "iso:country":"AU",
    "sg:address":"Shp 3/ 505 Old South Head Rd",
    "sg:city":"Rose Bay",
    "sg:classifiers":[
        {
            "category":"Health Services",
            "subcategory":"Health Practitioner",
            "type":"Services"
        }
    ],
    "sg:phone":"+61 2 9371 0993",
    "sg:postcode":"2029",
    "sg:province":"NSW",
    "sg:tags":[
        "osteopath"
    ],
    "wof:name":"Smith Lisa",
    "wof:placetype":"venue"
},
  "geometry": {"coordinates":[151.272903442,-33.8747520447],"type":"Point"}
}