{
  "type": "Feature",
  "properties": {
    "addr:full":"Suite 208 234 Queensberry St Carlton VIC 3053",
    "addr:housenumber":"234",
    "addr:postcode":"3053",
    "addr:street":"Queensberry St",
    "iso:country":"AU",
    "sg:address":"Suite 208 234 Queensberry St",
    "sg:city":"Carlton",
    "sg:classifiers":[
        {
            "category":"Professional",
            "subcategory":"Research",
            "type":"Services"
        }
    ],
    "sg:phone":"+61 3 9349 3994",
    "sg:postcode":"3053",
    "sg:province":"VIC",
    "sg:tags":[
        "market"
    ],
    "wof:name":"Denis Muller & Associates",
    "wof:placetype":"venue"
},
  "geometry": {"coordinates":[144.96092224099999,-37.8040885925],"type":"Point"}
}