{
  "type": "Feature",
  "properties": {
    "iso:country":"AU",
    "sg:address":"2- 12 Council St",
    "sg:city":"Doncaster",
    "sg:classifiers":[
        {
            "category":"Education",
            "subcategory":"School",
            "type":"Public Place"
        }
    ],
    "sg:phone":"+61 3 9848 1122",
    "sg:postcode":"3108",
    "sg:province":"VIC",
    "sg:tags":[
        "state",
        "except",
        "nsw"
    ],
    "wof:name":"Doncaster Primary School",
    "wof:placetype":"venue"
},
  "geometry": {"coordinates":[145.12971496599999,-37.7861747742],"type":"Point"}
}