{
  "type": "Feature",
  "properties": {
    "addr:full":"2/ 80 City Rd Beenleigh QLD 4207",
    "addr:housenumber":"/ 80",
    "addr:postcode":"4207",
    "addr:street":"City Rd",
    "iso:country":"AU",
    "sg:address":"2/ 80 City Rd",
    "sg:city":"Beenleigh",
    "sg:classifiers":[
        {
            "category":"Social Services",
            "subcategory":"Job Training",
            "type":"Services"
        }
    ],
    "sg:phone":"+61 7 3807 9366",
    "sg:postcode":"4207",
    "sg:province":"QLD",
    "sg:tags":[
        "hire",
        "computer",
        "leasing"
    ],
    "wof:name":"Rent To Own",
    "wof:placetype":"venue"
},
  "geometry": {"coordinates":[153.20254516599999,-27.7140922546],"type":"Point"}
}