{
  "type": "Feature",
  "properties": {
    "addr:full":"114 Napier St St Arnaud VIC 3478",
    "addr:housenumber":"114",
    "addr:postcode":"3478",
    "addr:street":"Napier St",
    "iso:country":"AU",
    "sg:address":"114 Napier St",
    "sg:city":"St Arnaud",
    "sg:classifiers":[
        {
            "category":"Shopping",
            "subcategory":"Optical Goods",
            "type":"Retail Goods"
        }
    ],
    "sg:phone":"+61 3 5495 2564",
    "sg:postcode":"3478",
    "sg:province":"VIC",
    "sg:tags":[
        "dispenser",
        "prescription"
    ],
    "wof:name":"Blizzard & Assoc.",
    "wof:placetype":"venue"
},
  "geometry": {"coordinates":[142.98953247099999,-36.3740768433],"type":"Point"}
}