{
  "type": "Feature",
  "properties": {
    "iso:country":"AU",
    "sg:address":"Unit 18, 16- 17 Mahogany Crt",
    "sg:city":"Willawong",
    "sg:classifiers":[
        {
            "category":"Retail",
            "subcategory":"Auto Repair",
            "type":"Services"
        }
    ],
    "sg:phone":"+61 1300 767 040",
    "sg:postcode":"4110",
    "sg:province":"QLD",
    "sg:tags":[
        "engine",
        "reconditioning"
    ],
    "wof:name":"HM Gem Engines Pty Ltd",
    "wof:placetype":"venue"
},
  "geometry": {"coordinates":[153.03146362300001,-27.6053104401],"type":"Point"}
}