{
  "type": "Feature",
  "properties": {
    "iso:country":"AU",
    "sg:address":"Unit 8/ 61 Buckingham Drv",
    "sg:city":"Wangara",
    "sg:classifiers":[
        {
            "category":"Professional",
            "type":"Services"
        }
    ],
    "sg:phone":"+61 8 9309 3270",
    "sg:postcode":"6065",
    "sg:province":"WA",
    "sg:tags":[
        "coating",
        "powder"
    ],
    "wof:name":"B & D Powdercoaters",
    "wof:placetype":"venue"
},
  "geometry": {"coordinates":[115.82417297400001,-31.7872219086],"type":"Point"}
}