{
  "type": "Feature",
  "properties": {
    "addr:full":"389 Canterbury Rd Surrey Hills VIC 3127",
    "addr:housenumber":"389",
    "addr:postcode":"3127",
    "addr:street":"Canterbury Rd",
    "iso:country":"AU",
    "sg:address":"389 Canterbury Rd",
    "sg:city":"Surrey Hills",
    "sg:classifiers":[
        {
            "category":"Professional",
            "subcategory":"Accounting & Tax Preparation",
            "type":"Services"
        }
    ],
    "sg:phone":"+61 3 9836 2499",
    "sg:postcode":"3127",
    "sg:province":"VIC",
    "sg:tags":[
        "accountant",
        "auditor"
    ],
    "wof:name":"GJM & Associates Pty Ltd",
    "wof:placetype":"venue"
},
  "geometry": {"coordinates":[145.10086059599999,-37.8262405396],"type":"Point"}
}