{
  "type": "Feature",
  "properties": {
    "iso:country":"AU",
    "sg:address":"6 Fleisher St",
    "sg:city":"Paynesville",
    "sg:classifiers":[
        {
            "category":"Health Services",
            "subcategory":"Medical Lab",
            "type":"Services"
        }
    ],
    "sg:phone":"+61 3 5156 6866",
    "sg:postcode":"3880",
    "sg:province":"VIC",
    "sg:tags":[
        "laboratory",
        "pathology"
    ],
    "wof:name":"Gippsland Pathology",
    "wof:placetype":"venue"
},
  "geometry": {"coordinates":[147.72369384800001,-37.9191360474],"type":"Point"}
}