{
  "type": "Feature",
  "properties": {
    "addr:full":"Fcty1 40 Healey Rd Dandenong VIC 3175",
    "addr:housenumber":"40",
    "addr:postcode":"3175",
    "addr:street":"Healey Rd",
    "iso:country":"AU",
    "sg:address":"Fcty1 40 Healey Rd",
    "sg:city":"Dandenong",
    "sg:classifiers":[
        {
            "category":"Transit Center",
            "subcategory":"Freight",
            "type":"Transportation"
        }
    ],
    "sg:phone":"+61 3 9706 6701",
    "sg:postcode":"3175",
    "sg:province":"VIC",
    "sg:tags":[
        "equipment",
        "truck",
        "transport",
        "refrigerated"
    ],
    "wof:name":"Conlock Refrigerated Transport Repairs",
    "wof:placetype":"venue"
},
  "geometry": {"coordinates":[145.225997925,-38.0299263],"type":"Point"}
}