{
  "type": "Feature",
  "properties": {
    "iso:country":"AU",
    "sg:address":"Shop 24 Stocklands Molly Morgan Drv",
    "sg:city":"Greenhills",
    "sg:classifiers":[
        {
            "category":"Personal",
            "subcategory":"Beauty Salon",
            "type":"Services"
        }
    ],
    "sg:phone":"+61 2 4933 0300",
    "sg:postcode":"2323",
    "sg:province":"NSW",
    "sg:tags":[
        "hairdresser"
    ],
    "wof:name":"Just Cuts",
    "wof:placetype":"venue"
},
  "geometry": {"coordinates":[151.589187622,-32.7621192932],"type":"Point"}
}