{
  "type": "Feature",
  "properties": {
    "addr:full":"1350 Barkers Lodge Rd Picton NSW 2571",
    "addr:housenumber":"1350",
    "addr:postcode":"2571",
    "addr:street":"Barkers Lodge Rd",
    "iso:country":"AU",
    "sg:address":"1350 Barkers Lodge Rd",
    "sg:city":"Picton",
    "sg:classifiers":[
        {
            "category":"Farming",
            "subcategory":"Livestock Farm",
            "type":"Manufacturing & Wholesale Goods"
        }
    ],
    "sg:phone":"+61 2 4680 9090",
    "sg:postcode":"2571",
    "sg:province":"NSW",
    "sg:tags":[
        "agistment"
    ],
    "wof:name":"Green Oak Lodge",
    "wof:placetype":"venue"
},
  "geometry": {"coordinates":[150.50950622600001,-34.1257629395],"type":"Point"}
}