{
  "type": "Feature",
  "properties": {
    "addr:full":"11 Silkhorn Crs Mt Martha VIC 3934",
    "addr:housenumber":"11",
    "addr:postcode":"3934",
    "addr:street":"Silkhorn Crs Mt Martha",
    "iso:country":"AU",
    "sg:address":"11 Silkhorn Crs",
    "sg:city":"Mt Martha",
    "sg:classifiers":[
        {
            "category":"Personal",
            "subcategory":"Hair Removal",
            "type":"Services"
        }
    ],
    "sg:phone":"+61 3 5974 4700",
    "sg:postcode":"3934",
    "sg:province":"VIC",
    "wof:name":"Hennie's Skin & Beauty Care Centre",
    "wof:placetype":"venue"
},
  "geometry": {"coordinates":[145.030853272,-38.2737808228],"type":"Point"}
}