{
  "type": "Feature",
  "properties": {
    "iso:country":"AU",
    "sg:address":"38 Gordon St",
    "sg:city":"Coffs Harbour",
    "sg:classifiers":[
        {
            "category":"Education",
            "subcategory":"School",
            "type":"Public Place"
        }
    ],
    "sg:phone":"+61 2 6652 1899",
    "sg:postcode":"2450",
    "sg:province":"NSW",
    "sg:tags":[
        "state",
        "-",
        "nsw"
    ],
    "wof:name":"School Dental Clinic",
    "wof:placetype":"venue"
},
  "geometry": {"coordinates":[153.118164,-30.296297],"type":"Point"}
}