{
  "type": "Feature",
  "properties": {
    "addr:full":"28 Loretta Ave Wheelers Hill VIC 3150",
    "addr:housenumber":"28",
    "addr:postcode":"3150",
    "addr:street":"Loretta Ave",
    "iso:country":"AU",
    "sg:address":"28 Loretta Ave",
    "sg:city":"Wheelers Hill",
    "sg:classifiers":[
        {
            "category":"Communications",
            "type":"Services"
        }
    ],
    "sg:phone":"+61 3 9511 4362",
    "sg:postcode":"3150",
    "sg:province":"VIC",
    "sg:tags":[
        "equipment",
        "radio"
    ],
    "wof:name":"Long Distance Communications",
    "wof:placetype":"venue"
},
  "geometry": {"coordinates":[145.19888305699999,-37.9069404602],"type":"Point"}
}