{
  "type": "Feature",
  "properties": {
    "iso:country":"AU",
    "sg:address":"33 Northcote St",
    "sg:city":"Brighton",
    "sg:classifiers":[
        {
            "category":"Building & Trades",
            "subcategory":"Construction",
            "type":"Services"
        }
    ],
    "sg:phone":"+61 7 3869 0051",
    "sg:postcode":"4017",
    "sg:province":"QLD",
    "sg:tags":[
        "waterproofing",
        "contractor"
    ],
    "wof:name":"Aquatight Water Proofing Pty Ltd",
    "wof:placetype":"venue"
},
  "geometry": {"coordinates":[153.05592346200001,-27.3070697784],"type":"Point"}
}