{
  "type": "Feature",
  "properties": {
    "addr:full":"21 Byres St Newstead QLD 4006",
    "addr:housenumber":"21",
    "addr:postcode":"4006",
    "addr:street":"Byres St",
    "iso:country":"AU",
    "sg:address":"21 Byres St",
    "sg:city":"Newstead",
    "sg:classifiers":[
        {
            "category":"Cafe",
            "type":"Food & Drink"
        }
    ],
    "sg:phone":"+61 7 3252 4852",
    "sg:postcode":"4006",
    "sg:province":"QLD",
    "wof:name":"Tucker Time",
    "wof:placetype":"venue"
},
  "geometry": {"coordinates":[153.04394531200001,-27.4471931458],"type":"Point"}
}