{
  "type": "Feature",
  "properties": {
    "addr:full":"Level 38/ 88 Phillip St Sydney NSW 2000",
    "addr:housenumber":"/ 88",
    "addr:postcode":"2000",
    "addr:street":"Phillip St",
    "iso:country":"AU",
    "sg:address":"Level 38/ 88 Phillip St",
    "sg:city":"Sydney",
    "sg:classifiers":[
        {
            "category":"Banks & Credit Unions",
            "subcategory":"Investment Brokerage",
            "type":"Services"
        }
    ],
    "sg:phone":"+61 2 9240 7600",
    "sg:postcode":"2000",
    "sg:province":"NSW",
    "wof:name":"State Street Global Advisors Aust Ltd",
    "wof:placetype":"venue"
},
  "geometry": {"coordinates":[151.211791992,-33.8648147583],"type":"Point"}
}