{
  "type": "Feature",
  "properties": {
    "addr:full":"Facty 10 9-11 Clare St Bayswater VIC 3153",
    "addr:housenumber":"10 9-11",
    "addr:postcode":"3153",
    "addr:street":"Facty;Clare St",
    "iso:country":"AU",
    "sg:address":"Facty 10 9-11 Clare St",
    "sg:city":"Bayswater",
    "sg:classifiers":[
        {
            "category":"Manufacturing",
            "subcategory":"Tools & Machinery",
            "type":"Manufacturing & Wholesale Goods"
        }
    ],
    "sg:phone":"+61 438 313 036",
    "sg:postcode":"3153",
    "sg:province":"VIC",
    "sg:tags":[
        "machine",
        "industrial",
        "sewing"
    ],
    "wof:name":"G.K. Sewing Service",
    "wof:placetype":"venue"
},
  "geometry": {"coordinates":[145.28184509299999,-37.8431892395],"type":"Point"}
}