{
  "type": "Feature",
  "properties": {
    "addr:full":"Chullora Market Place Shopng Cntr Waterloo Rd Chullora NSW 2190",
    "addr:postcode":"2190",
    "addr:street":"Market Place Shopng Cntr Waterloo Rd",
    "iso:country":"AU",
    "sg:address":"Chullora Market Place Shopng Cntr Waterloo Rd",
    "sg:city":"Chullora",
    "sg:classifiers":[
        {
            "category":"Health Services",
            "subcategory":"Doctor",
            "type":"Services"
        }
    ],
    "sg:phone":"+61 2 9758 8311",
    "sg:postcode":"2190",
    "sg:province":"NSW",
    "sg:tags":[
        "medical",
        "practitioner"
    ],
    "wof:name":"Chullora Medical Centre",
    "wof:placetype":"venue"
},
  "geometry": {"coordinates":[151.05853300000001,-33.899025],"type":"Point"}
}