{
  "type": "Feature",
  "properties": {
    "iso:country":"AU",
    "sg:address":"616 Old Northern Rd",
    "sg:city":"Dural",
    "sg:classifiers":[
        {
            "category":"Ice Cream",
            "type":"Food & Drink"
        }
    ],
    "sg:phone":"+61 2 9651 5445",
    "sg:postcode":"2158",
    "sg:province":"NSW",
    "sg:tags":[
        "specialised",
        "fitting",
        "lady",
        "wear"
    ],
    "wof:name":"Four All Clothing Pty Ltd",
    "wof:placetype":"venue"
},
  "geometry": {"coordinates":[151.030883789,-33.6902770996],"type":"Point"}
}