{
  "type": "Feature",
  "properties": {
    "addr:full":"58 Redruth Rd Alexandra Hills QLD 4161",
    "addr:housenumber":"58",
    "addr:postcode":"4161",
    "addr:street":"Redruth Rd",
    "iso:country":"AU",
    "sg:address":"58 Redruth Rd",
    "sg:city":"Alexandra Hills",
    "sg:classifiers":[
        {
            "category":"Professional",
            "subcategory":"Computer Services",
            "type":"Services"
        }
    ],
    "sg:phone":"+61 7 3824 0652",
    "sg:postcode":"4161",
    "sg:province":"QLD",
    "sg:tags":[
        "repairs",
        "upgrade",
        "equipment"
    ],
    "wof:name":"RP Computer Support",
    "wof:placetype":"venue"
},
  "geometry": {"coordinates":[153.21768188499999,-27.5363712311],"type":"Point"}
}