{
  "type": "Feature",
  "properties": {
    "iso:country":"AU",
    "sg:address":"1 Council Drv",
    "sg:city":"Eaton",
    "sg:classifiers":[
        {
            "category":"Government",
            "subcategory":"Department Of Motor Vehicles",
            "type":"Public Place"
        }
    ],
    "sg:phone":"+61 8 9724 0000",
    "sg:postcode":"6232",
    "sg:province":"WA",
    "sg:tags":[
        "organisation",
        "local"
    ],
    "wof:name":"Dardanup Shire Of",
    "wof:placetype":"venue"
},
  "geometry": {"coordinates":[115.718513,-33.318954],"type":"Point"}
}