{
  "type": "Feature",
  "properties": {
    "iso:country":"AU",
    "sg:address":"36 Mt. Dandenong Rd",
    "sg:city":"Ringwood East",
    "sg:classifiers":[
        {
            "category":"Health Services",
            "subcategory":"Dentist",
            "type":"Services"
        }
    ],
    "sg:phone":"+61 3 9347 3788",
    "sg:postcode":"3135",
    "sg:province":"VIC",
    "wof:name":"Probert Timothy CS",
    "wof:placetype":"venue"
},
  "geometry": {"coordinates":[145.24893188499999,-37.8090934753],"type":"Point"}
}