{
  "type": "Feature",
  "properties": {
    "addr:full":"79 Watkins Rd Wangi Wangi NSW 2267",
    "addr:housenumber":"79",
    "addr:postcode":"2267",
    "addr:street":"Watkins Rd",
    "iso:country":"AU",
    "sg:address":"79 Watkins Rd",
    "sg:city":"Wangi Wangi",
    "sg:classifiers":[
        {
            "category":"Professional",
            "subcategory":"Employment Agencies",
            "type":"Services"
        }
    ],
    "sg:phone":"+61 2 4973 4119",
    "sg:postcode":"2267",
    "sg:province":"NSW",
    "sg:tags":[
        "entertainer",
        "agent"
    ],
    "wof:name":"Another Face - The Face Painters",
    "wof:placetype":"venue"
},
  "geometry": {"coordinates":[151.602814,-33.072998],"type":"Point"}
}