{
  "type": "Feature",
  "properties": {
    "addr:full":"30 Victoria St Eugowra NSW 2806",
    "addr:housenumber":"30",
    "addr:postcode":"2806",
    "addr:street":"Victoria St",
    "iso:country":"AU",
    "sg:address":"30 Victoria St",
    "sg:city":"Eugowra",
    "sg:classifiers":[
        {
            "category":"Building & Trades",
            "subcategory":"Construction",
            "type":"Services"
        }
    ],
    "sg:phone":"+61 2 6859 2482",
    "sg:postcode":"2806",
    "sg:province":"NSW",
    "sg:tags":[
        "contractor"
    ],
    "wof:name":"Howell A L",
    "wof:placetype":"venue"
},
  "geometry": {"coordinates":[148.36831665,-33.4236030579],"type":"Point"}
}