{
  "type": "Feature",
  "properties": {
    "iso:country":"AU",
    "sg:address":"Shop 57 & 58, Ettalong Markets",
    "sg:city":"Ettalong",
    "sg:classifiers":[
        {
            "category":"Shopping",
            "subcategory":"Crafts & Fabrics",
            "type":"Retail Goods"
        }
    ],
    "sg:phone":"+61 2 4344 6565",
    "sg:postcode":"2257",
    "sg:province":"NSW",
    "sg:tags":[
        "supply"
    ],
    "wof:name":"Creative Focus",
    "wof:placetype":"venue"
},
  "geometry": {"coordinates":[151.34234619099999,-33.5241317749],"type":"Point"}
}