{
  "type": "Feature",
  "properties": {
    "iso:country":"AU",
    "sg:address":"57 Port Hacking Rd",
    "sg:city":"Sylvania",
    "sg:classifiers":[
        {
            "category":"Structure",
            "subcategory":"Bridge",
            "type":"Public Place"
        }
    ],
    "sg:phone":"+61 2 9522 5244",
    "sg:postcode":"2224",
    "sg:province":"NSW",
    "sg:tags":[
        "chainsaw",
        "brushcutters"
    ],
    "wof:name":"Sylvania Mowers Pty Ltd",
    "wof:placetype":"venue"
},
  "geometry": {"coordinates":[151.10432434099999,-34.0134773254],"type":"Point"}
}