{
  "type": "Feature",
  "properties": {
    "iso:country":"AU",
    "sg:address":"11 Rosebery St",
    "sg:city":"Altona Meadows",
    "sg:classifiers":[
        {
            "category":"Home & Garden",
            "subcategory":"Building Materials",
            "type":"Retail Goods"
        }
    ],
    "sg:phone":"+61 3 9369 5032",
    "sg:postcode":"3028",
    "sg:province":"VIC",
    "sg:tags":[
        "lawn",
        "cutting",
        "maintenance"
    ],
    "wof:name":"All West Mowing",
    "wof:placetype":"venue"
},
  "geometry": {"coordinates":[144.784012,-37.866871],"type":"Point"}
}