{
  "type": "Feature",
  "properties": {
    "addr:full":"Berry St Consulting Rooms, 37 Berry St Nowra NSW 2541",
    "addr:housenumber":"37",
    "addr:postcode":"2541",
    "addr:street":"Berry;Berry St",
    "iso:country":"AU",
    "sg:address":"Berry St Consulting Rooms, 37 Berry St",
    "sg:city":"Nowra",
    "sg:classifiers":[
        {
            "category":"Health Services",
            "subcategory":"Health Practitioner",
            "type":"Services"
        }
    ],
    "sg:phone":"+61 2 4423 2500",
    "sg:postcode":"2541",
    "sg:province":"NSW",
    "sg:tags":[
        "psychologist"
    ],
    "wof:name":"Helen Rutland & Associates",
    "wof:placetype":"venue"
},
  "geometry": {"coordinates":[150.60017395,-34.8757171631],"type":"Point"}
}