{
  "type": "Feature",
  "properties": {
    "iso:country":"AU",
    "sg:address":"197 Murray St",
    "sg:city":"Colac",
    "sg:classifiers":[
        {
            "category":"Shopping",
            "subcategory":"Mobile Phones",
            "type":"Retail Goods"
        }
    ],
    "sg:phone":"+61 3 5232 1504",
    "sg:postcode":"3250",
    "sg:province":"VIC",
    "sg:tags":[
        "telephone",
        "accessory"
    ],
    "wof:name":"B M Tronics",
    "wof:placetype":"venue"
},
  "geometry": {"coordinates":[143.584564,-38.3396],"type":"Point"}
}