{
  "type": "Feature",
  "properties": {
    "iso:country":"AU",
    "sg:address":"Suite 4 24 Albert Rd",
    "sg:city":"Melbourne",
    "sg:classifiers":[
        {
            "category":"Professional",
            "subcategory":"Detective & Security Services",
            "type":"Services"
        }
    ],
    "sg:phone":"+61 3 9866 4884",
    "sg:postcode":"3004",
    "sg:province":"VIC",
    "sg:tags":[
        "investigator"
    ],
    "wof:name":"Lawtrack Pty Ltd",
    "wof:placetype":"venue"
},
  "geometry": {"coordinates":[144.971557617,-37.8332595825],"type":"Point"}
}