{
  "type": "Feature",
  "properties": {
    "addr:full":"4/ 400 Newman Rd Geebung QLD 4034",
    "addr:housenumber":"/ 400",
    "addr:postcode":"4034",
    "addr:street":"Newman Rd",
    "iso:country":"AU",
    "sg:address":"4/ 400 Newman Rd",
    "sg:city":"Geebung",
    "sg:classifiers":[
        {
            "category":"Shopping Center",
            "type":"Public Place"
        }
    ],
    "sg:phone":"+61 7 3865 2898",
    "sg:postcode":"4034",
    "sg:province":"QLD",
    "sg:tags":[
        "riveting",
        "equipment",
        "rivet"
    ],
    "sg:website":"http://www.henrob.co.uk",
    "wof:name":"Henrob (UK) Pty Ltd",
    "wof:placetype":"venue"
},
  "geometry": {"coordinates":[153.048203,-27.366526],"type":"Point"}
}