{
  "type": "Feature",
  "properties": {
    "addr:full":"162 Wakaden St Griffith NSW 2680",
    "addr:housenumber":"162",
    "addr:postcode":"2680",
    "addr:street":"Wakaden St",
    "iso:country":"AU",
    "sg:address":"162 Wakaden St",
    "sg:city":"Griffith",
    "sg:classifiers":[
        {
            "category":"Commercial Area",
            "type":"Public Place"
        }
    ],
    "sg:phone":"+61 2 6962 6005",
    "sg:postcode":"2680",
    "sg:province":"NSW",
    "sg:tags":[
        "heavy",
        "carrier"
    ],
    "wof:name":"MIA Freighters",
    "wof:placetype":"venue"
},
  "geometry": {"coordinates":[146.05183400000001,-34.286018],"type":"Point"}
}