{
  "type": "Feature",
  "properties": {
    "addr:full":"147 San Fernando Drv Worongary QLD 4213",
    "addr:housenumber":"147",
    "addr:postcode":"4213",
    "addr:street":"San Fernando Drv",
    "iso:country":"AU",
    "sg:address":"147 San Fernando Drv",
    "sg:city":"Worongary",
    "sg:classifiers":[
        {
            "category":"Building & Trades",
            "subcategory":"Cleaning & Sanitation",
            "type":"Services"
        }
    ],
    "sg:phone":"+61 7 5530 6834",
    "sg:postcode":"4213",
    "sg:province":"QLD",
    "sg:tags":[
        "industrial",
        "commercial",
        "contractor"
    ],
    "wof:name":"Nolans Cleaning Service",
    "wof:placetype":"venue"
},
  "geometry": {"coordinates":[153.34474182100001,-28.0332489014],"type":"Point"}
}