{
  "type": "Feature",
  "properties": {
    "iso:country":"AU",
    "sg:address":"205 Darling Rd",
    "sg:city":"Malvern East",
    "sg:classifiers":[
        {
            "category":"Personal",
            "subcategory":"Beauty Salon",
            "type":"Services"
        }
    ],
    "sg:phone":"+61 3 9505 6567",
    "sg:postcode":"3145",
    "sg:province":"VIC",
    "sg:tags":[
        "hairdresser"
    ],
    "wof:name":"Helmut Salon",
    "wof:placetype":"venue"
},
  "geometry": {"coordinates":[145.06059265100001,-37.8697090149],"type":"Point"}
}