{
  "type": "Feature",
  "properties": {
    "addr:full":"1766 Ipswich Rd Rocklea QLD 4106",
    "addr:housenumber":"1766",
    "addr:postcode":"4106",
    "addr:street":"Ipswich Rd",
    "iso:country":"AU",
    "sg:address":"1766 Ipswich Rd",
    "sg:city":"Rocklea",
    "sg:classifiers":[
        {
            "category":"Autos & Motor Vehicles",
            "subcategory":"Motorcycle Sales",
            "type":"Retail Goods"
        }
    ],
    "sg:phone":"+61 7 3875 1600",
    "sg:postcode":"4106",
    "sg:province":"QLD",
    "sg:tags":[
        "outboard"
    ],
    "wof:name":"Karee Marine",
    "wof:placetype":"venue"
},
  "geometry": {"coordinates":[152.996551514,-27.5603370667],"type":"Point"}
}