{
  "type": "Feature",
  "properties": {
    "addr:full":"Carngham Rd Ballarat West VIC 3352",
    "addr:postcode":"3352",
    "addr:street":"Carngham Rd",
    "iso:country":"AU",
    "sg:address":"Carngham Rd",
    "sg:city":"Ballarat West",
    "sg:phone":"+61 1800 065 356",
    "sg:postcode":"3352",
    "sg:province":"VIC",
    "wof:name":"Icon Industries (Ballarat) P/L",
    "wof:placetype":"venue"
},
  "geometry": {"coordinates":[143.89198300000001,-37.435986],"type":"Point"}
}