{
  "type": "Feature",
  "properties": {
    "addr:full":"11 Mercer St Geelong VIC 3220",
    "addr:housenumber":"11",
    "addr:postcode":"3220",
    "addr:street":"Mercer St",
    "iso:country":"AU",
    "sg:address":"11 Mercer St",
    "sg:city":"Geelong",
    "sg:classifiers":[
        {
            "category":"Retail",
            "subcategory":"Auto Repair",
            "type":"Services"
        }
    ],
    "sg:phone":"+61 3 5221 1155",
    "sg:postcode":"3220",
    "sg:province":"VIC",
    "sg:tags":[
        "muffler",
        "exhaust",
        "system"
    ],
    "wof:name":"Muffler & Tube Bending",
    "wof:placetype":"venue"
},
  "geometry": {"coordinates":[144.35479699999999,-38.138916],"type":"Point"}
}