{
  "type": "Feature",
  "properties": {
    "addr:full":"4b Kempling St Car Park, 4 Ways Devonport TAS 7310",
    "addr:housenumber":"4b",
    "addr:postcode":"7310",
    "addr:street":"Kempling St",
    "iso:country":"AU",
    "sg:address":"4b Kempling St Car Park, 4 Ways",
    "sg:city":"Devonport",
    "sg:classifiers":[
        {
            "category":"Personal",
            "subcategory":"Beauty Salon",
            "type":"Services"
        }
    ],
    "sg:phone":"+61 3 6424 3624",
    "sg:postcode":"7310",
    "sg:province":"TAS",
    "sg:tags":[
        "hairdresser"
    ],
    "wof:name":"Divine Hairdressing",
    "wof:placetype":"venue"
},
  "geometry": {"coordinates":[146.35002136200001,-41.1763725281],"type":"Point"}
}