{
  "type": "Feature",
  "properties": {
    "iso:country":"AU",
    "sg:address":"1 Minora Pl",
    "sg:city":"Rivervale",
    "sg:classifiers":[
        {
            "category":"Travel",
            "subcategory":"Hotels & Motels",
            "type":"Entertainment"
        }
    ],
    "sg:phone":"+61 8 9472 3411",
    "sg:postcode":"6103",
    "sg:province":"WA",
    "wof:name":"Burswood Lodge",
    "wof:placetype":"venue"
},
  "geometry": {"coordinates":[115.907592773,-31.9546394348],"type":"Point"}
}