{
  "type": "Feature",
  "properties": {
    "addr:full":"7 Glenelg Ave Corio VIC 3214",
    "addr:housenumber":"7",
    "addr:postcode":"3214",
    "addr:street":"Glenelg Ave",
    "iso:country":"AU",
    "sg:address":"7 Glenelg Ave",
    "sg:city":"Corio",
    "sg:classifiers":[
        {
            "category":"Wholesale",
            "subcategory":"Home Furnishings",
            "type":"Manufacturing & Wholesale Goods"
        }
    ],
    "sg:phone":"+61 3 5275 2386",
    "sg:postcode":"3214",
    "sg:province":"VIC",
    "wof:name":"Specialty Interiors",
    "wof:placetype":"venue"
},
  "geometry": {"coordinates":[144.353607178,-38.0754089355],"type":"Point"}
}