{
  "type": "Feature",
  "properties": {
    "addr:full":"26 Chifley Rd Morisset Park NSW 2264",
    "addr:housenumber":"26",
    "addr:postcode":"2264",
    "addr:street":"Chifley Rd",
    "iso:country":"AU",
    "sg:address":"26 Chifley Rd",
    "sg:city":"Morisset Park",
    "sg:classifiers":[
        {
            "category":"Health Services",
            "subcategory":"Health Practitioner",
            "type":"Services"
        }
    ],
    "sg:phone":"+61 407 227 957",
    "sg:postcode":"2264",
    "sg:province":"NSW",
    "sg:tags":[
        "alternative"
    ],
    "wof:name":"Wise Management Pty Ltd",
    "wof:placetype":"venue"
},
  "geometry": {"coordinates":[151.531387,-33.119019],"type":"Point"}
}