{
  "type": "Feature",
  "properties": {
    "addr:full":"41 North Valley Rd Highton VIC 3216",
    "addr:housenumber":"41",
    "addr:postcode":"3216",
    "addr:street":"North Valley Rd",
    "iso:country":"AU",
    "sg:address":"41 North Valley Rd",
    "sg:city":"Highton",
    "sg:classifiers":[
        {
            "category":"Education",
            "subcategory":"Junior College",
            "type":"Public Place"
        }
    ],
    "sg:phone":"+61 3 5244 2910",
    "sg:postcode":"3216",
    "sg:province":"VIC",
    "sg:tags":[
        "wholesaler",
        "school",
        "mfrs",
        "uniform"
    ],
    "wof:name":"Dinkum Sweats",
    "wof:placetype":"venue"
},
  "geometry": {"coordinates":[144.31877136200001,-38.1721725464],"type":"Point"}
}