{
  "type": "Feature",
  "properties": {
    "addr:full":"2a Pindari Ave St Ives NSW 2075",
    "addr:housenumber":"2a",
    "addr:postcode":"2075",
    "addr:street":"Pindari Ave",
    "iso:country":"AU",
    "sg:address":"2a Pindari Ave",
    "sg:city":"St Ives",
    "sg:classifiers":[
        {
            "category":"Arts & Performance",
            "subcategory":"Dance",
            "type":"Entertainment"
        }
    ],
    "sg:phone":"+61 2 9449 2965",
    "sg:postcode":"2075",
    "sg:province":"NSW",
    "sg:tags":[
        "theatrical",
        "ballet",
        "tuition"
    ],
    "wof:name":"Robyn Ross School Of Ballet",
    "wof:placetype":"venue"
},
  "geometry": {"coordinates":[151.16447448700001,-33.741897583],"type":"Point"}
}