{
  "type": "Feature",
  "properties": {
    "addr:full":"2 George St Gladesville NSW 2111",
    "addr:housenumber":"2",
    "addr:postcode":"2111",
    "addr:street":"George St",
    "iso:country":"AU",
    "sg:address":"2 George St",
    "sg:city":"Gladesville",
    "sg:classifiers":[
        {
            "category":"Government",
            "subcategory":"Court House",
            "type":"Public Place"
        }
    ],
    "sg:phone":"+61 2 9879 4865",
    "sg:postcode":"2111",
    "sg:province":"NSW",
    "sg:tags":[
        "personal",
        "marriage",
        "family",
        "counselling"
    ],
    "wof:name":"Hicks Shirley",
    "wof:placetype":"venue"
},
  "geometry": {"coordinates":[151.124343872,-33.8349990845],"type":"Point"}
}