{
  "type": "Feature",
  "properties": {
    "addr:full":"Bush Pilot Ave Cairns QLD 4870",
    "addr:postcode":"4870",
    "addr:street":"Ave",
    "iso:country":"AU",
    "sg:address":"Bush Pilot Ave",
    "sg:city":"Cairns",
    "sg:classifiers":[
        {
            "category":"Airport",
            "subcategory":"General Aviation",
            "type":"Transportation"
        }
    ],
    "sg:phone":"+61 7 4040 0300",
    "sg:postcode":"4870",
    "sg:province":"QLD",
    "sg:tags":[
        "helicopter"
    ],
    "wof:name":"GBR Helicopter Group",
    "wof:placetype":"venue"
},
  "geometry": {"coordinates":[145.66958618199999,-17.0185699463],"type":"Point"}
}