{
  "type": "Feature",
  "properties": {
    "addr:full":"Shop 2 Quadrant Plaza Arc Launceston TAS 7250",
    "addr:housenumber":"shop 2",
    "addr:postcode":"7250",
    "addr:street":"Quadrant Plaza Arc",
    "iso:country":"AU",
    "sg:address":"Shop 2",
    "sg:city":"Quadrant Plaza Arc Launceston",
    "sg:classifiers":[
        {
            "category":"Health Services",
            "subcategory":"Health Practitioner",
            "type":"Services"
        }
    ],
    "sg:phone":"+61 419 004 461",
    "sg:postcode":"7250",
    "sg:province":"TAS",
    "sg:tags":[
        "naturopath"
    ],
    "wof:name":"JAN VAN NEK",
    "wof:placetype":"venue"
},
  "geometry": {"coordinates":[147.138504028,-41.4452018738],"type":"Point"}
}