{
  "type": "Feature",
  "properties": {
    "addr:full":"53 Wynyard Ramp St Sydney NSW 2000",
    "addr:housenumber":"53",
    "addr:postcode":"2000",
    "addr:street":"Wynyard Ramp St",
    "iso:country":"AU",
    "sg:address":"53 Wynyard Ramp St",
    "sg:city":"Sydney",
    "sg:classifiers":[
        {
            "category":"Fast Food",
            "type":"Food & Drink"
        }
    ],
    "sg:phone":"+61 2 9290 1216",
    "sg:postcode":"2000",
    "sg:province":"NSW",
    "sg:tags":[
        "away",
        "take"
    ],
    "wof:name":"Wynyard Salad Bar",
    "wof:placetype":"venue"
},
  "geometry": {"coordinates":[151.20690918,-33.8671035767],"type":"Point"}
}