{
  "type": "Feature",
  "properties": {
    "addr:full":"197 Shead Rd Tolga QLD 4882",
    "addr:housenumber":"197",
    "addr:postcode":"4882",
    "addr:street":"Shead Rd",
    "iso:country":"AU",
    "sg:address":"197 Shead Rd",
    "sg:city":"Tolga",
    "sg:classifiers":[
        {
            "category":"Shopping",
            "subcategory":"Bridal",
            "type":"Retail Goods"
        }
    ],
    "sg:phone":"+61 7 4095 8680",
    "sg:postcode":"4882",
    "sg:province":"QLD",
    "sg:tags":[
        "hire",
        "wear"
    ],
    "wof:name":"Irene Costa's Bridal Fashions",
    "wof:placetype":"venue"
},
  "geometry": {"coordinates":[145.49549865700001,-17.2014713287],"type":"Point"}
}