{
  "type": "Feature",
  "properties": {
    "iso:country":"AU",
    "sg:address":"Ferguson-Lowden Rd",
    "sg:city":"Donnybrook",
    "sg:classifiers":[
        {
            "category":"Home & Garden",
            "subcategory":"Building Materials",
            "type":"Retail Goods"
        }
    ],
    "sg:phone":"+61 8 9732 1212",
    "sg:postcode":"6239",
    "sg:province":"WA",
    "sg:tags":[
        "retaining",
        "wall"
    ],
    "wof:name":"Donnybrook Bricklaying",
    "wof:placetype":"venue"
},
  "geometry": {"coordinates":[115.823013,-33.570419],"type":"Point"}
}