{
  "type": "Feature",
  "properties": {
    "addr:full":"Shop 1/ 344 Peel St Tamworth NSW 2340",
    "addr:housenumber":"shop 1 / 344",
    "addr:postcode":"2340",
    "addr:street":"Peel St",
    "iso:country":"AU",
    "sg:address":"Shop 1/ 344 Peel St",
    "sg:city":"Tamworth",
    "sg:classifiers":[
        {
            "category":"Food & Beverages",
            "subcategory":"Groceries & Convenience Stores",
            "type":"Retail Goods"
        }
    ],
    "sg:phone":"+61 2 6766 5462",
    "sg:postcode":"2340",
    "sg:province":"NSW",
    "wof:name":"Sandwich Box The",
    "wof:placetype":"venue"
},
  "geometry": {"coordinates":[150.92973327600001,-31.0902385712],"type":"Point"}
}