{
  "type": "Feature",
  "properties": {
    "addr:full":"109- 111 McFees Rd Dandenong VIC 3175",
    "addr:housenumber":"111",
    "addr:postcode":"3175",
    "addr:street":"Mcfees Rd",
    "iso:country":"AU",
    "sg:address":"109- 111 McFees Rd",
    "sg:city":"Dandenong",
    "sg:classifiers":[
        {
            "category":"Social Services",
            "subcategory":"Retirement Home",
            "type":"Services"
        }
    ],
    "sg:phone":"+61 3 9792 5305",
    "sg:postcode":"3175",
    "sg:province":"VIC",
    "sg:tags":[
        "accommodation",
        "special"
    ],
    "wof:name":"Bahilda Lodge Special Accommodation",
    "wof:placetype":"venue"
},
  "geometry": {"coordinates":[145.22142028799999,-37.9646835327],"type":"Point"}
}