{
  "type": "Feature",
  "properties": {
    "iso:country":"AU",
    "sg:address":"Shop K1, Northpark Shopping Centre, 264 Main North Rd",
    "sg:city":"Prospect",
    "sg:classifiers":[
        {
            "category":"Building & Trades",
            "subcategory":"Locksmith",
            "type":"Services"
        }
    ],
    "sg:phone":"+61 8 8344 7207",
    "sg:postcode":"5082",
    "sg:province":"SA",
    "sg:tags":[
        "lock"
    ],
    "wof:name":"Mister Minit",
    "wof:placetype":"venue"
},
  "geometry": {"coordinates":[138.602386475,-34.8825378418],"type":"Point"}
}