{
  "type": "Feature",
  "properties": {
    "addr:full":"210 Warrandyte Rd Ringwood North VIC 3134",
    "addr:housenumber":"210",
    "addr:postcode":"3134",
    "addr:street":"Warrandyte Rd",
    "iso:country":"AU",
    "sg:address":"210 Warrandyte Rd",
    "sg:city":"Ringwood North",
    "sg:classifiers":[
        {
            "category":"Health Services",
            "subcategory":"Doctor",
            "type":"Services"
        }
    ],
    "sg:phone":"+61 3 9876 2222",
    "sg:postcode":"3134",
    "sg:province":"VIC",
    "sg:tags":[
        "medical",
        "practitioner"
    ],
    "wof:name":"Moodie Christopher J Dr",
    "wof:placetype":"venue"
},
  "geometry": {"coordinates":[145.236328125,-37.7889480591],"type":"Point"}
}