{
  "type": "Feature",
  "properties": {
    "addr:full":"13 Oban Crt Greenvale VIC 3059",
    "addr:housenumber":"13",
    "addr:postcode":"3059",
    "addr:street":"Oban Crt",
    "iso:country":"AU",
    "sg:address":"13 Oban Crt",
    "sg:city":"Greenvale",
    "sg:classifiers":[
        {
            "category":"Professional",
            "subcategory":"Business Services",
            "type":"Services"
        }
    ],
    "sg:phone":"+61 3 9333 1972",
    "sg:postcode":"3059",
    "sg:province":"VIC",
    "sg:tags":[
        "drafting"
    ],
    "wof:name":"Talifax Pty Ltd",
    "wof:placetype":"venue"
},
  "geometry": {"coordinates":[144.89903259299999,-37.6451797485],"type":"Point"}
}