{
  "type": "Feature",
  "properties": {
    "addr:full":"6 Hakea Crt Hove SA 5048",
    "addr:housenumber":"6",
    "addr:postcode":"5048",
    "addr:street":"Hakea Crt",
    "iso:country":"AU",
    "sg:address":"6 Hakea Crt",
    "sg:city":"Hove",
    "sg:classifiers":[
        {
            "category":"Education",
            "subcategory":"Special Training",
            "type":"Public Place"
        }
    ],
    "sg:phone":"+61 8 8358 4604",
    "sg:postcode":"5048",
    "sg:province":"SA",
    "sg:tags":[
        "tuition-educational"
    ],
    "wof:name":"Kumon Maths & English",
    "wof:placetype":"venue"
},
  "geometry": {"coordinates":[138.516876,-35.010777],"type":"Point"}
}