{
  "type": "Feature",
  "properties": {
    "addr:full":"23 Lanaghan St Lavington NSW 2641",
    "addr:housenumber":"23",
    "addr:postcode":"2641",
    "addr:street":"Lanaghan St",
    "iso:country":"AU",
    "sg:address":"23 Lanaghan St",
    "sg:city":"Lavington",
    "sg:classifiers":[
        {
            "category":"Building & Trades",
            "subcategory":"Cleaning & Sanitation",
            "type":"Services"
        }
    ],
    "sg:phone":"+61 412 761 788",
    "sg:postcode":"2641",
    "sg:province":"NSW",
    "sg:tags":[
        "cleaner",
        "repairer",
        "roof"
    ],
    "wof:name":"Advanced Roof Restoration",
    "wof:placetype":"venue"
},
  "geometry": {"coordinates":[146.91563415499999,-36.0441055298],"type":"Point"}
}