{
  "type": "Feature",
  "properties": {
    "addr:full":"89 Litzows Rd Tarampa QLD 4311",
    "addr:housenumber":"89",
    "addr:postcode":"4311",
    "addr:street":"Litzows Rd",
    "iso:country":"AU",
    "sg:address":"89 Litzows Rd",
    "sg:city":"Tarampa",
    "sg:classifiers":[
        {
            "category":"Shopping",
            "subcategory":"Bridal",
            "type":"Retail Goods"
        }
    ],
    "sg:phone":"+61 7 5426 1197",
    "sg:postcode":"4311",
    "sg:province":"QLD",
    "sg:tags":[
        "hire",
        "wear"
    ],
    "wof:name":"Lorelle &#034;D&#034; Bridal Centre",
    "wof:placetype":"venue"
},
  "geometry": {"coordinates":[152.567459106,-27.4894237518],"type":"Point"}
}