{
  "type": "Feature",
  "properties": {
    "addr:full":"12 Carson Rd Malaga WA 6090",
    "addr:housenumber":"12",
    "addr:postcode":"6090",
    "addr:street":"Carson Rd",
    "iso:country":"AU",
    "sg:address":"12 Carson Rd",
    "sg:city":"Malaga",
    "sg:classifiers":[
        {
            "category":"Professional",
            "subcategory":"Computer Services",
            "type":"Services"
        }
    ],
    "sg:phone":"+61 8 9249 4545",
    "sg:postcode":"6090",
    "sg:province":"WA",
    "sg:tags":[
        "repairs",
        "upgrade",
        "equipment"
    ],
    "wof:name":"Chernic Pty Ltd",
    "wof:placetype":"venue"
},
  "geometry": {"coordinates":[115.880310059,-31.8555488586],"type":"Point"}
}