{
  "type": "Feature",
  "properties": {
    "addr:full":"108 Drummond St North Ballarat VIC 3350",
    "addr:housenumber":"108",
    "addr:postcode":"3350",
    "addr:street":"Drummond St North",
    "iso:country":"AU",
    "sg:address":"108 Drummond St North",
    "sg:city":"Ballarat",
    "sg:classifiers":[
        {
            "category":"Health Services",
            "subcategory":"Doctor",
            "type":"Services"
        }
    ],
    "sg:phone":"+61 3 5331 8289",
    "sg:postcode":"3350",
    "sg:province":"VIC",
    "sg:tags":[
        "medical",
        "practitioner"
    ],
    "wof:name":"Stewart Bruce Mr",
    "wof:placetype":"venue"
},
  "geometry": {"coordinates":[143.84823600000001,-37.557308],"type":"Point"}
}