{
  "type": "Feature",
  "properties": {
    "addr:full":"Unit 7, 229 Wilson St Newtown NSW 2042",
    "addr:housenumber":"229",
    "addr:postcode":"2042",
    "addr:street":"Wilson St",
    "iso:country":"AU",
    "sg:address":"Unit 7, 229 Wilson St",
    "sg:city":"Newtown",
    "sg:classifiers":[
        {
            "category":"Retail",
            "subcategory":"Storage",
            "type":"Services"
        }
    ],
    "sg:phone":"+61 2 9550 6555",
    "sg:postcode":"2042",
    "sg:province":"NSW",
    "wof:name":"All Car Storage",
    "wof:placetype":"venue"
},
  "geometry": {"coordinates":[151.188187,-33.894554],"type":"Point"}
}