{
  "type": "Feature",
  "properties": {
    "iso:country":"AU",
    "sg:address":"36 Watton St",
    "sg:city":"Werribee",
    "sg:classifiers":[
        {
            "category":"Shopping",
            "subcategory":"Bridal",
            "type":"Retail Goods"
        }
    ],
    "sg:phone":"+61 3 9742 3670",
    "sg:postcode":"3030",
    "sg:province":"VIC",
    "sg:tags":[
        "hire",
        "wear"
    ],
    "wof:name":"KJ's Fashions",
    "wof:placetype":"venue"
},
  "geometry": {"coordinates":[144.66037,-37.901676],"type":"Point"}
}