{
  "type": "Feature",
  "properties": {
    "addr:full":"500 Mt Dandenong Tourist Rd Olinda VIC 3788",
    "addr:housenumber":"500",
    "addr:postcode":"3788",
    "addr:street":"Mt Dandenong Tourist Rd",
    "iso:country":"AU",
    "sg:address":"500 Mt Dandenong Tourist Rd",
    "sg:city":"Olinda",
    "sg:classifiers":[
        {
            "category":"Professional",
            "subcategory":"Computer Services",
            "type":"Services"
        }
    ],
    "sg:phone":"+61 3 9751 2780",
    "sg:postcode":"3788",
    "sg:province":"VIC",
    "sg:tags":[
        "consultant",
        "system"
    ],
    "wof:name":"Mountain Ash Computer Solutions",
    "wof:placetype":"venue"
},
  "geometry": {"coordinates":[145.369156,-37.858761],"type":"Point"}
}