{
  "type": "Feature",
  "properties": {
    "addr:full":"Newington Pl Kingsley WA 6026",
    "addr:postcode":"6026",
    "addr:street":"Pl",
    "iso:country":"AU",
    "sg:address":"Newington Pl",
    "sg:city":"Kingsley",
    "sg:classifiers":[
        {
            "category":"Utilities",
            "subcategory":"Recycling",
            "type":"Services"
        }
    ],
    "sg:phone":"+61 8 9324 4038",
    "sg:postcode":"6026",
    "sg:province":"WA",
    "wof:name":"Mallaway Holdings",
    "wof:placetype":"venue"
},
  "geometry": {"coordinates":[115.791549683,-31.8071231842],"type":"Point"}
}