{
  "type": "Feature",
  "properties": {
    "addr:full":"PO Box 4 Nemingha NSW 2340",
    "addr:postcode":"2340",
    "iso:country":"AU",
    "sg:address":"PO Box 4",
    "sg:city":"Nemingha",
    "sg:classifiers":[
        {
            "category":"Building & Trades",
            "subcategory":"Plumbing",
            "type":"Services"
        }
    ],
    "sg:phone":"+61 2 6760 9089",
    "sg:postcode":"2340",
    "sg:province":"NSW",
    "sg:tags":[
        "plumber",
        "gasfitters"
    ],
    "wof:name":"Halcroft Tim Plumbing",
    "wof:placetype":"venue"
},
  "geometry": {"coordinates":[150.989334106,-31.1237201691],"type":"Point"}
}