{
  "type": "Feature",
  "properties": {
    "addr:full":"Lee St Kelso NSW 2795",
    "addr:postcode":"2795",
    "addr:street":"Lee St",
    "iso:country":"AU",
    "sg:address":"Lee St",
    "sg:city":"Kelso",
    "sg:classifiers":[
        {
            "category":"Sports & Exercise",
            "subcategory":"Sports Center",
            "type":"Entertainment"
        }
    ],
    "sg:phone":"+61 2 6332 3175",
    "sg:postcode":"2795",
    "sg:province":"NSW",
    "sg:tags":[
        "ground"
    ],
    "wof:name":"Bathurst 75 Soccer Club",
    "wof:placetype":"venue"
},
  "geometry": {"coordinates":[149.606002808,-33.4201087952],"type":"Point"}
}