{
  "type": "Feature",
  "properties": {
    "addr:full":"16 Centre Rd Morwell VIC 3840",
    "addr:housenumber":"16",
    "addr:postcode":"3840",
    "addr:street":"Centre Rd",
    "iso:country":"AU",
    "sg:address":"16 Centre Rd",
    "sg:city":"Morwell",
    "sg:classifiers":[
        {
            "category":"Professional",
            "type":"Services"
        }
    ],
    "sg:phone":"+61 3 5133 9051",
    "sg:postcode":"3840",
    "sg:province":"VIC",
    "sg:tags":[
        "transport"
    ],
    "wof:name":"Sherritt & Sons Tilt Trays & Crane Truck Hire",
    "wof:placetype":"venue"
},
  "geometry": {"coordinates":[146.44073486299999,-38.2273139954],"type":"Point"}
}