{
  "type": "Feature",
  "properties": {
    "addr:full":"PO Box 1019 Burwood North NSW 2134",
    "addr:postcode":"2134",
    "iso:country":"AU",
    "sg:address":"PO Box 1019",
    "sg:city":"Burwood North",
    "sg:classifiers":[
        {
            "category":"Utilities",
            "subcategory":"Refuse",
            "type":"Services"
        }
    ],
    "sg:phone":"+61 2 8765 0250",
    "sg:postcode":"2134",
    "sg:province":"NSW",
    "sg:tags":[
        "remover",
        "rubbish"
    ],
    "wof:name":"Bargain Bins & Rubbish Removals Pty Ltd",
    "wof:placetype":"venue"
},
  "geometry": {"coordinates":[151.10392761200001,-33.8761482239],"type":"Point"}
}