{
  "type": "Feature",
  "properties": {
    "addr:full":"29 Ivanhoe Pde Ivanhoe VIC 3079",
    "addr:housenumber":"29",
    "addr:postcode":"3079",
    "addr:street":"Ivanhoe Pde",
    "iso:country":"AU",
    "sg:address":"29 Ivanhoe Pde",
    "sg:city":"Ivanhoe",
    "sg:classifiers":[
        {
            "category":"Health Services",
            "subcategory":"Doctor",
            "type":"Services"
        }
    ],
    "sg:phone":"+61 3 9497 4359",
    "sg:postcode":"3079",
    "sg:province":"VIC",
    "sg:tags":[
        "podiatrist"
    ],
    "wof:name":"Italia Michelle",
    "wof:placetype":"venue"
},
  "geometry": {"coordinates":[145.04450988799999,-37.7663917542],"type":"Point"}
}