{
  "type": "Feature",
  "properties": {
    "iso:country":"AU",
    "sg:address":"Aeroclub Building Airport Rd",
    "sg:city":"Narrabri",
    "sg:classifiers":[
        {
            "category":"Education",
            "subcategory":"Special Training",
            "type":"Public Place"
        }
    ],
    "sg:phone":"+61 427 924 200",
    "sg:postcode":"2390",
    "sg:province":"NSW",
    "sg:tags":[
        "school",
        "flying"
    ],
    "wof:name":"Kaputar Aviation Pty Ltd",
    "wof:placetype":"venue"
},
  "geometry": {"coordinates":[149.766845703,-30.3389701843],"type":"Point"}
}