{
  "type": "Feature",
  "properties": {
    "addr:full":"254 Gilbert Rd Preston West VIC 3072",
    "addr:housenumber":"254",
    "addr:postcode":"3072",
    "addr:street":"Gilbert Rd",
    "iso:country":"AU",
    "sg:address":"254 Gilbert Rd",
    "sg:city":"Preston West",
    "sg:classifiers":[
        {
            "category":"Health Services",
            "subcategory":"Doctor",
            "type":"Services"
        }
    ],
    "sg:phone":"+61 3 9416 8122",
    "sg:postcode":"3072",
    "sg:province":"VIC",
    "sg:tags":[
        "medical",
        "practitioner"
    ],
    "wof:name":"Samuel-John Daisy Dr.",
    "wof:placetype":"venue"
},
  "geometry": {"coordinates":[144.98959350600001,-37.7421875],"type":"Point"}
}