{
  "type": "Feature",
  "properties": {
    "iso:country":"AU",
    "sg:address":"5 Augusta Rd",
    "sg:city":"The Basin",
    "sg:classifiers":[
        {
            "category":"Wholesale",
            "subcategory":"Machinery & Supplies",
            "type":"Manufacturing & Wholesale Goods"
        }
    ],
    "sg:phone":"+61 419 115 193",
    "sg:postcode":"3154",
    "sg:province":"VIC",
    "sg:tags":[
        "equipment",
        "welding"
    ],
    "wof:name":"Spotweld Services",
    "wof:placetype":"venue"
},
  "geometry": {"coordinates":[145.31341552699999,-37.8549194336],"type":"Point"}
}