{
  "type": "Feature",
  "properties": {
    "addr:full":"62 Claremont Ave Greenacre NSW 2190",
    "addr:housenumber":"62",
    "addr:postcode":"2190",
    "addr:street":"Claremont Ave",
    "iso:country":"AU",
    "sg:address":"62 Claremont Ave",
    "sg:city":"Greenacre",
    "sg:classifiers":[
        {
            "category":"Manufacturing",
            "subcategory":"Motor Vehicles & Parts",
            "type":"Manufacturing & Wholesale Goods"
        }
    ],
    "sg:phone":"+61 2 9708 5474",
    "sg:postcode":"2190",
    "sg:province":"NSW",
    "sg:tags":[
        "replacement"
    ],
    "wof:name":"Jaw smash repairs",
    "wof:placetype":"venue"
},
  "geometry": {"coordinates":[151.03839099999999,-33.901981],"type":"Point"}
}