{
  "type": "Feature",
  "properties": {
    "addr:full":"59 Emmett St Smithton TAS 7330",
    "addr:housenumber":"59",
    "addr:postcode":"7330",
    "addr:street":"Emmett St",
    "iso:country":"AU",
    "sg:address":"59 Emmett St",
    "sg:city":"Smithton",
    "sg:classifiers":[
        {
            "category":"Food & Beverages",
            "subcategory":"Supermarket",
            "type":"Retail Goods"
        }
    ],
    "sg:phone":"+61 3 6452 1668",
    "sg:postcode":"7330",
    "sg:province":"TAS",
    "sg:tags":[
        "grocery",
        "store"
    ],
    "wof:name":"Friendly Grocer IGA Stores",
    "wof:placetype":"venue"
},
  "geometry": {"coordinates":[145.12614400000001,-40.840942],"type":"Point"}
}