{
  "type": "Feature",
  "properties": {
    "iso:country":"AU",
    "sg:address":"41 North Rd",
    "sg:city":"Brighton",
    "sg:classifiers":[
        {
            "category":"Professional",
            "subcategory":"Engineering",
            "type":"Services"
        }
    ],
    "sg:phone":"+61 3 9596 1576",
    "sg:postcode":"3186",
    "sg:province":"VIC",
    "sg:tags":[
        "consulting",
        "engineer"
    ],
    "wof:name":"All Crane & Hoist Consulting & Inspection Services",
    "wof:placetype":"venue"
},
  "geometry": {"coordinates":[144.99180602999999,-37.8978538513],"type":"Point"}
}