{
  "type": "Feature",
  "properties": {
    "addr:full":"48 Sheehan St Pearce ACT 2607",
    "addr:housenumber":"48",
    "addr:postcode":"2607",
    "addr:street":"Sheehan St",
    "iso:country":"AU",
    "sg:address":"48 Sheehan St",
    "sg:city":"Pearce",
    "sg:classifiers":[
        {
            "category":"Education",
            "subcategory":"Special Training",
            "type":"Public Place"
        }
    ],
    "sg:phone":"+61 2 6290 1961",
    "sg:postcode":"2607",
    "sg:province":"ACT",
    "sg:tags":[
        "tuition-educational"
    ],
    "wof:name":"Dawn Hill",
    "wof:placetype":"venue"
},
  "geometry": {"coordinates":[149.07853698700001,-35.3662452698],"type":"Point"}
}