{
  "type": "Feature",
  "properties": {
    "addr:full":"17 Market St Woolgoolga NSW 2456",
    "addr:housenumber":"17",
    "addr:postcode":"2456",
    "addr:street":"Market St",
    "iso:country":"AU",
    "sg:address":"17 Market St",
    "sg:city":"Woolgoolga",
    "sg:classifiers":[
        {
            "category":"Health Services",
            "subcategory":"Health Practitioner",
            "type":"Services"
        }
    ],
    "sg:phone":"+61 2 6654 2477",
    "sg:postcode":"2456",
    "sg:province":"NSW",
    "sg:tags":[
        "physiotherapist"
    ],
    "wof:name":"Lynn Wright",
    "wof:placetype":"venue"
},
  "geometry": {"coordinates":[153.202133,-30.111284],"type":"Point"}
}