{
  "type": "Feature",
  "properties": {
    "addr:full":"U2/ 30 Achievement Way Wangara WA 6065",
    "addr:housenumber":"30",
    "addr:postcode":"6065",
    "addr:street":"U2 /;Achievement Way",
    "iso:country":"AU",
    "sg:address":"U2/ 30",
    "sg:city":"Achievement Way Wangara",
    "sg:classifiers":[
        {
            "category":"Home & Garden",
            "subcategory":"Building Materials",
            "type":"Retail Goods"
        }
    ],
    "sg:phone":"+61 411 420 349",
    "sg:postcode":"6065",
    "sg:province":"WA",
    "sg:tags":[
        "balustrading"
    ],
    "wof:name":"Ozwest Steel Fabricators Pty Ltd",
    "wof:placetype":"venue"
},
  "geometry": {"coordinates":[115.830337524,-31.7884025574],"type":"Point"}
}