{
  "type": "Feature",
  "properties": {
    "addr:full":"2 Station St Seymour VIC 3660",
    "addr:housenumber":"2",
    "addr:postcode":"3660",
    "addr:street":"Station St",
    "iso:country":"AU",
    "sg:address":"2 Station St",
    "sg:city":"Seymour",
    "sg:classifiers":[
        {
            "category":"Personal",
            "subcategory":"Beauty Salon",
            "type":"Services"
        }
    ],
    "sg:phone":"+61 3 5799 0200",
    "sg:postcode":"3660",
    "sg:province":"VIC",
    "sg:tags":[
        "hairdresser"
    ],
    "wof:name":"Paul Sterry Hairdressing",
    "wof:placetype":"venue"
},
  "geometry": {"coordinates":[145.13948059099999,-37.0233764648],"type":"Point"}
}