{
  "type": "Feature",
  "properties": {
    "addr:full":"184- 186 Lords Pl Orange NSW 2800",
    "addr:housenumber":"186",
    "addr:postcode":"2800",
    "addr:street":"Lords Pl",
    "iso:country":"AU",
    "sg:address":"184- 186 Lords Pl",
    "sg:city":"Orange",
    "sg:classifiers":[
        {
            "category":"Government",
            "subcategory":"Department Of Motor Vehicles",
            "type":"Public Place"
        }
    ],
    "sg:phone":"+61 13 32 20",
    "sg:postcode":"2800",
    "sg:province":"NSW",
    "sg:tags":[
        "organisation",
        "local"
    ],
    "wof:name":"Fair Trading, Office of",
    "wof:placetype":"venue"
},
  "geometry": {"coordinates":[149.101074219,-33.2850456238],"type":"Point"}
}