{
  "type": "Feature",
  "properties": {
    "addr:full":"81 Churchill St Childers QLD 4660",
    "addr:housenumber":"81",
    "addr:postcode":"4660",
    "addr:street":"Churchill St",
    "iso:country":"AU",
    "sg:address":"81 Churchill St",
    "sg:city":"Childers",
    "sg:classifiers":[
        {
            "category":"Personal",
            "subcategory":"Beauty Salon",
            "type":"Services"
        }
    ],
    "sg:phone":"+61 7 4126 2009",
    "sg:postcode":"4660",
    "sg:province":"QLD",
    "wof:name":"Amazon Babe Nails & Beauty",
    "wof:placetype":"venue"
},
  "geometry": {"coordinates":[152.27590942399999,-25.2361698151],"type":"Point"}
}