{
  "type": "Feature",
  "properties": {
    "iso:country":"AU",
    "sg:address":"Toowoomba Specialist Centre Suite 6",
    "sg:city":"/9 Scott Street Toowoomba",
    "sg:classifiers":[
        {
            "category":"Health Services",
            "subcategory":"Doctor",
            "type":"Services"
        }
    ],
    "sg:phone":"+61 7 4632 2800",
    "sg:postcode":"4350",
    "sg:province":"QLD",
    "sg:tags":[
        "medical",
        "practitioner"
    ],
    "wof:name":"Venugopalan V Dr",
    "wof:placetype":"venue"
},
  "geometry": {"coordinates":[151.973587,-27.565733],"type":"Point"}
}