{
  "type": "Feature",
  "properties": {
    "iso:country":"AU",
    "sg:address":"Shop 15b Kingsway Plaza Barton St",
    "sg:city":"Kurri Kurri",
    "sg:classifiers":[
        {
            "category":"Professional",
            "subcategory":"Art Services",
            "type":"Services"
        }
    ],
    "sg:phone":"+61 2 4937 4499",
    "sg:postcode":"2327",
    "sg:province":"NSW",
    "sg:tags":[
        "picture",
        "frame",
        "framing"
    ],
    "wof:name":"Frameworks The",
    "wof:placetype":"venue"
},
  "geometry": {"coordinates":[151.480560303,-32.8195533752],"type":"Point"}
}