{
  "type": "Feature",
  "properties": {
    "iso:country":"AU",
    "sg:address":"20 Ninth St",
    "sg:city":"Wingfield",
    "sg:classifiers":[
        {
            "category":"Building & Trades",
            "subcategory":"Construction",
            "type":"Services"
        }
    ],
    "sg:phone":"+61 8 8244 7000",
    "sg:postcode":"5013",
    "sg:province":"SA",
    "sg:tags":[
        "welding"
    ],
    "wof:name":"Alysteel Fabricators",
    "wof:placetype":"venue"
},
  "geometry": {"coordinates":[138.55607605,-34.8381919861],"type":"Point"}
}