{
  "type": "Feature",
  "properties": {
    "addr:full":"8 Spoonbill Pl Sale VIC 3850",
    "addr:housenumber":"8",
    "addr:postcode":"3850",
    "addr:street":"Spoonbill Pl",
    "iso:country":"AU",
    "sg:address":"8 Spoonbill Pl",
    "sg:city":"Sale",
    "sg:classifiers":[
        {
            "category":"Shopping",
            "subcategory":"Stationery & Office Supplies",
            "type":"Retail Goods"
        }
    ],
    "sg:phone":"+61 3 5144 7889",
    "sg:postcode":"3850",
    "sg:province":"VIC",
    "sg:tags":[
        "equipment",
        "dairy"
    ],
    "wof:name":"Glover R J & K M",
    "wof:placetype":"venue"
},
  "geometry": {"coordinates":[147.088088989,-38.104724884],"type":"Point"}
}