{
  "type": "Feature",
  "properties": {
    "addr:full":"4 Bergin St West Ryde NSW 2114",
    "addr:housenumber":"4",
    "addr:postcode":"2114",
    "addr:street":"Bergin St",
    "iso:country":"AU",
    "sg:address":"4 Bergin St",
    "sg:city":"West Ryde",
    "sg:classifiers":[
        {
            "category":"Utilities",
            "subcategory":"Electric",
            "type":"Services"
        }
    ],
    "sg:phone":"+61 2 9011 7757",
    "sg:postcode":"2114",
    "sg:province":"NSW",
    "sg:tags":[
        "electrical",
        "contractor"
    ],
    "wof:name":"Slattery Security Services",
    "wof:placetype":"venue"
},
  "geometry": {"coordinates":[151.074295044,-33.7991752625],"type":"Point"}
}