{
  "type": "Feature",
  "properties": {
    "iso:country":"AU",
    "sg:address":"10- 14 Railway Ave",
    "sg:city":"Ringwood East",
    "sg:classifiers":[
        {
            "category":"Cafe",
            "type":"Food & Drink"
        }
    ],
    "sg:phone":"+61 3 9879 2855",
    "sg:postcode":"3135",
    "sg:province":"VIC",
    "wof:name":"All Smiles Cafe Function Centre",
    "wof:placetype":"venue"
},
  "geometry": {"coordinates":[145.25198364299999,-37.8117141724],"type":"Point"}
}