{
  "type": "Feature",
  "properties": {
    "addr:full":"2 Danbury Crs Girrawheen WA 6064",
    "addr:housenumber":"2",
    "addr:postcode":"6064",
    "addr:street":"Danbury Crs",
    "iso:country":"AU",
    "sg:address":"2 Danbury Crs",
    "sg:city":"Girrawheen",
    "sg:classifiers":[
        {
            "category":"Building & Trades",
            "subcategory":"Cleaning & Sanitation",
            "type":"Services"
        }
    ],
    "sg:phone":"+61 8 9343 2325",
    "sg:postcode":"6064",
    "sg:province":"WA",
    "sg:tags":[
        "window"
    ],
    "wof:name":"Magic Touch Window Cleaning",
    "wof:placetype":"venue"
},
  "geometry": {"coordinates":[115.831481934,-31.8418102264],"type":"Point"}
}