{
  "type": "Feature",
  "properties": {
    "iso:country":"AU",
    "sg:address":"d&#039;arenberg Wines Osborn Rd",
    "sg:city":"McLaren Vale",
    "sg:classifiers":[
        {
            "category":"Restaurant",
            "type":"Food & Drink"
        }
    ],
    "sg:phone":"+61 8 8323 8710",
    "sg:postcode":"5171",
    "sg:province":"SA",
    "wof:name":"d&#039;Arrys Verandah",
    "wof:placetype":"venue"
},
  "geometry": {"coordinates":[138.54524230999999,-35.1983718872],"type":"Point"}
}