{
  "type": "Feature",
  "properties": {
    "addr:full":"4 Heslop Rd Lesmurdie WA 6076",
    "addr:housenumber":"4",
    "addr:postcode":"6076",
    "addr:street":"Heslop Rd",
    "iso:country":"AU",
    "sg:address":"4 Heslop Rd",
    "sg:city":"Lesmurdie",
    "sg:classifiers":[
        {
            "category":"Building & Trades",
            "subcategory":"Construction",
            "type":"Services"
        }
    ],
    "sg:phone":"+61 417 096 614",
    "sg:postcode":"6076",
    "sg:province":"WA",
    "sg:tags":[
        "earth",
        "excavating",
        "moving",
        "contractor"
    ],
    "wof:name":"DW Cartage Pty Ltd",
    "wof:placetype":"venue"
},
  "geometry": {"coordinates":[116.05960082999999,-31.9954681396],"type":"Point"}
}