{
  "type": "Feature",
  "properties": {
    "iso:country":"AU",
    "sg:address":"45 Poole St",
    "sg:city":"Deer Park",
    "sg:classifiers":[
        {
            "category":"Building & Trades",
            "subcategory":"Construction",
            "type":"Services"
        }
    ],
    "sg:phone":"+61 407 512 876",
    "sg:postcode":"3023",
    "sg:province":"VIC",
    "sg:tags":[
        "joiner",
        "carpenter"
    ],
    "wof:name":"Brincats Carpentry & Handyman Service",
    "wof:placetype":"venue"
},
  "geometry": {"coordinates":[144.76902799999999,-37.773643],"type":"Point"}
}