{
  "type": "Feature",
  "properties": {
    "addr:full":"6 Dungara Crs Parklea NSW 2768",
    "addr:housenumber":"6",
    "addr:postcode":"2768",
    "addr:street":"Dungara Crs",
    "iso:country":"AU",
    "sg:address":"6 Dungara Crs",
    "sg:city":"Parklea",
    "sg:classifiers":[
        {
            "category":"Transit Center",
            "subcategory":"Freight",
            "type":"Transportation"
        }
    ],
    "sg:phone":"+61 2 9629 8391",
    "sg:postcode":"2768",
    "sg:province":"NSW",
    "sg:tags":[
        "agent",
        "shipping"
    ],
    "wof:name":"Icepack Pty Ltd",
    "wof:placetype":"venue"
},
  "geometry": {"coordinates":[150.918137,-33.725399],"type":"Point"}
}