{
  "type": "Feature",
  "properties": {
    "iso:country":"AU",
    "sg:address":"17 Keston Ave",
    "sg:city":"Mosman",
    "sg:classifiers":[
        {
            "category":"Utilities",
            "subcategory":"Electric",
            "type":"Services"
        }
    ],
    "sg:phone":"+61 2 9968 3337",
    "sg:postcode":"2088",
    "sg:province":"NSW",
    "sg:tags":[
        "electrical",
        "contractor"
    ],
    "wof:name":"Michael Ryan",
    "wof:placetype":"venue"
},
  "geometry": {"coordinates":[151.24240112300001,-33.8296737671],"type":"Point"}
}