{
  "type": "Feature",
  "properties": {
    "addr:full":"485 Warburton Hwy Seville VIC 3139",
    "addr:housenumber":"485",
    "addr:postcode":"3139",
    "addr:street":"Warburton Hwy",
    "iso:country":"AU",
    "sg:address":"485 Warburton Hwy",
    "sg:city":"Seville",
    "sg:classifiers":[
        {
            "category":"Education",
            "subcategory":"Special Training",
            "type":"Public Place"
        }
    ],
    "sg:phone":"+61 3 5964 4161",
    "sg:postcode":"3139",
    "sg:province":"VIC",
    "sg:tags":[
        "tuition-educational"
    ],
    "wof:name":"Eastern Literacy Services",
    "wof:placetype":"venue"
},
  "geometry": {"coordinates":[145.44866943400001,-37.7790298462],"type":"Point"}
}