{
  "type": "Feature",
  "properties": {
    "iso:country":"AU",
    "sg:address":"Grattan Crt",
    "sg:city":"Wanniassa",
    "sg:classifiers":[
        {
            "category":"Health Services",
            "subcategory":"Doctor",
            "type":"Services"
        }
    ],
    "sg:phone":"+61 2 6296 1966",
    "sg:postcode":"2903",
    "sg:province":"ACT",
    "sg:tags":[
        "medical",
        "practitioner"
    ],
    "wof:name":"Erindale Medical Practice",
    "wof:placetype":"venue"
},
  "geometry": {"coordinates":[149.09779357900001,-35.4032440186],"type":"Point"}
}