{
  "type": "Feature",
  "properties": {
    "iso:country":"AU",
    "sg:address":"Shop 4, 6- 12 Hurtle Pde",
    "sg:city":"Mawson Lakes",
    "sg:classifiers":[
        {
            "category":"Personal",
            "subcategory":"Beauty Salon",
            "type":"Services"
        }
    ],
    "sg:phone":"+61 8 8349 9115",
    "sg:postcode":"5095",
    "sg:province":"SA",
    "sg:tags":[
        "hairdresser"
    ],
    "wof:name":"Ark Hair & Beauty",
    "wof:placetype":"venue"
},
  "geometry": {"coordinates":[138.616821289,-34.8082618713],"type":"Point"}
}