{
  "type": "Feature",
  "properties": {
    "addr:full":"33 Front St Mossman QLD 4873",
    "addr:housenumber":"33",
    "addr:postcode":"4873",
    "addr:street":"Front St",
    "iso:country":"AU",
    "sg:address":"33 Front St",
    "sg:city":"Mossman",
    "sg:classifiers":[
        {
            "category":"Food & Beverages",
            "subcategory":"Fruits & Vegetables",
            "type":"Retail Goods"
        }
    ],
    "sg:phone":"+61 7 4098 1118",
    "sg:postcode":"4873",
    "sg:province":"QLD",
    "sg:tags":[
        "greengrocer",
        "fruiterer"
    ],
    "wof:name":"Goodies The Goodfood Store",
    "wof:placetype":"venue"
},
  "geometry": {"coordinates":[145.373413086,-16.4617385864],"type":"Point"}
}