{
  "type": "Feature",
  "properties": {
    "addr:full":"Unit 2, 79 Wheatley Drv Bull Creek WA 6149",
    "addr:housenumber":"79",
    "addr:postcode":"6149",
    "addr:street":"Wheatley Drv",
    "iso:country":"AU",
    "sg:address":"Unit 2, 79 Wheatley Drv",
    "sg:city":"Bull Creek",
    "sg:classifiers":[
        {
            "category":"Health Services",
            "subcategory":"Doctor",
            "type":"Services"
        }
    ],
    "sg:phone":"+61 8 9332 0488",
    "sg:postcode":"6149",
    "sg:province":"WA",
    "sg:tags":[
        "medical",
        "practitioner"
    ],
    "wof:name":"Bullcreek Medical Centre",
    "wof:placetype":"venue"
},
  "geometry": {"coordinates":[115.865891,-32.057892],"type":"Point"}
}