{
  "type": "Feature",
  "properties": {
    "addr:full":"Focal Point, 18 Second Ave Maroochydore QLD 4558",
    "addr:housenumber":"18",
    "addr:postcode":"4558",
    "addr:street":"Second Ave",
    "iso:country":"AU",
    "sg:address":"Focal Point, 18 Second Ave",
    "sg:city":"Maroochydore",
    "sg:classifiers":[
        {
            "category":"Health Services",
            "subcategory":"Optometrist",
            "type":"Services"
        }
    ],
    "sg:phone":"+61 7 5443 3211",
    "sg:postcode":"4558",
    "sg:province":"QLD",
    "wof:name":"ProVision",
    "wof:placetype":"venue"
},
  "geometry": {"coordinates":[153.09555053700001,-26.6559753418],"type":"Point"}
}