{
  "type": "Feature",
  "properties": {
    "addr:full":"1824 Argyle St The Rocks NSW 2000",
    "addr:housenumber":"1824",
    "addr:postcode":"2000",
    "addr:street":"Argyle St",
    "iso:country":"AU",
    "sg:address":"1824 Argyle St",
    "sg:city":"The Rocks",
    "sg:classifiers":[
        {
            "category":"Shopping",
            "subcategory":"Jewelry",
            "type":"Retail Goods"
        }
    ],
    "sg:phone":"+61 2 9241 3164",
    "sg:postcode":"2000",
    "sg:province":"NSW",
    "sg:tags":[
        "jeweller"
    ],
    "wof:name":"Duo Clothing & Jewellery Pty Ltd",
    "wof:placetype":"venue"
},
  "geometry": {"coordinates":[151.208084106,-33.8591423035],"type":"Point"}
}