{
  "type": "Feature",
  "properties": {
    "addr:full":"531 Sandy Bay Rd Sandy Bay TAS 7005",
    "addr:housenumber":"531",
    "addr:postcode":"7005",
    "addr:street":"Sandy Bay Rd",
    "iso:country":"AU",
    "sg:address":"531 Sandy Bay Rd",
    "sg:city":"Sandy Bay",
    "sg:classifiers":[
        {
            "category":"Real Estate",
            "subcategory":"Real Estate Agent",
            "type":"Services"
        }
    ],
    "sg:phone":"+61 3 6225 4666",
    "sg:postcode":"7005",
    "sg:province":"TAS",
    "wof:name":"L.J. Hooker",
    "wof:placetype":"venue"
},
  "geometry": {"coordinates":[147.347290039,-42.9092674255],"type":"Point"}
}