{
  "type": "Feature",
  "properties": {
    "iso:country":"AU",
    "sg:address":"25 Dyer Crt",
    "sg:city":"West Lakes",
    "sg:classifiers":[
        {
            "category":"Shopping",
            "subcategory":"Beauty & Cosmetics",
            "type":"Retail Goods"
        }
    ],
    "sg:phone":"+61 8 8449 5253",
    "sg:postcode":"5021",
    "sg:province":"SA",
    "sg:tags":[
        "equipment",
        "salon",
        "supply"
    ],
    "wof:name":"Thalgo Australia",
    "wof:placetype":"venue"
},
  "geometry": {"coordinates":[138.495925903,-34.860080719],"type":"Point"}
}