{
  "type": "Feature",
  "properties": {
    "addr:full":"55 Blackabys Rd Boat Harbour TAS 7321",
    "addr:housenumber":"55",
    "addr:postcode":"7321",
    "addr:street":"Blackabys Rd",
    "iso:country":"AU",
    "sg:address":"55 Blackabys Rd",
    "sg:city":"Boat Harbour",
    "sg:classifiers":[
        {
            "category":"Mining & Drilling",
            "type":"Manufacturing & Wholesale Goods"
        }
    ],
    "sg:phone":"+61 3 6445 1232",
    "sg:postcode":"7321",
    "sg:province":"TAS",
    "sg:tags":[
        "concrete",
        "breaking",
        "grinding",
        "sawing"
    ],
    "wof:name":"Concrete Cutting Services",
    "wof:placetype":"venue"
},
  "geometry": {"coordinates":[145.62178,-40.954884],"type":"Point"}
}