{
  "type": "Feature",
  "properties": {
    "addr:full":"Unit 1, Woodvale Commercial Cntr, 923 Whitfords Av Woodvale WA 6026",
    "addr:housenumber":"923",
    "addr:postcode":"6026",
    "addr:street":"Commercial Cntr;Av",
    "iso:country":"AU",
    "sg:address":"Unit 1, Woodvale Commercial Cntr, 923 Whitfords Av",
    "sg:city":"Woodvale",
    "sg:classifiers":[
        {
            "category":"Banks & Credit Unions",
            "subcategory":"Financial Services",
            "type":"Services"
        }
    ],
    "sg:phone":"+61 8 9309 1911",
    "sg:postcode":"6026",
    "sg:province":"WA",
    "sg:tags":[
        "loan",
        "finance",
        "mortgage"
    ],
    "wof:name":"Wizard",
    "wof:placetype":"venue"
},
  "geometry": {"coordinates":[115.79387664799999,-31.8001995087],"type":"Point"}
}