{
  "type": "Feature",
  "properties": {
    "addr:full":"108 Miles St Bald Hills QLD 4036",
    "addr:housenumber":"108",
    "addr:postcode":"4036",
    "addr:street":"Miles St",
    "iso:country":"AU",
    "sg:address":"108 Miles St",
    "sg:city":"Bald Hills",
    "sg:classifiers":[
        {
            "category":"Building & Trades",
            "subcategory":"Plumbing",
            "type":"Services"
        }
    ],
    "sg:phone":"+61 7 3312 7065",
    "sg:postcode":"4036",
    "sg:province":"QLD",
    "sg:tags":[
        "plumber",
        "gasfitters"
    ],
    "wof:name":"J K & J Plumbing",
    "wof:placetype":"venue"
},
  "geometry": {"coordinates":[153.01205400000001,-27.323252],"type":"Point"}
}