{
  "type": "Feature",
  "properties": {
    "addr:full":"Suite 5/ 26 Joseph St Blackburn North VIC 3130",
    "addr:housenumber":"26",
    "addr:postcode":"3130",
    "addr:street":"Joseph St",
    "iso:country":"AU",
    "sg:address":"Suite 5/ 26 Joseph St",
    "sg:city":"Blackburn North",
    "sg:classifiers":[
        {
            "category":"Professional",
            "subcategory":"Printing & Photocopies",
            "type":"Services"
        }
    ],
    "sg:phone":"+61 3 9890 6460",
    "sg:postcode":"3130",
    "sg:province":"VIC",
    "sg:tags":[
        "embroidery"
    ],
    "wof:name":"Mosmo Embroidery Design",
    "wof:placetype":"venue"
},
  "geometry": {"coordinates":[145.14437866200001,-37.8001708984],"type":"Point"}
}