{
  "type": "Feature",
  "properties": {
    "addr:full":"Great Southern Hwy Popanyinning WA 6309",
    "addr:postcode":"6309",
    "addr:street":"Great Southern Hwy",
    "iso:country":"AU",
    "sg:address":"Great Southern Hwy",
    "sg:city":"Popanyinning",
    "sg:classifiers":[
        {
            "category":"Farming",
            "subcategory":"Farm",
            "type":"Manufacturing & Wholesale Goods"
        }
    ],
    "sg:phone":"+61 8 9887 5062",
    "sg:postcode":"6309",
    "sg:province":"WA",
    "sg:tags":[
        "farmer"
    ],
    "wof:name":"K A & S L Lansdell",
    "wof:placetype":"venue"
},
  "geometry": {"coordinates":[117.12448883099999,-32.6395835876],"type":"Point"}
}