{
  "type": "Feature",
  "properties": {
    "addr:full":"64 Gilbert St Dover Heights NSW 2030",
    "addr:housenumber":"64",
    "addr:postcode":"2030",
    "addr:street":"Gilbert St Dover",
    "iso:country":"AU",
    "sg:address":"64 Gilbert St",
    "sg:city":"Dover Heights",
    "sg:classifiers":[
        {
            "category":"Professional",
            "subcategory":"Accounting & Tax Preparation",
            "type":"Services"
        }
    ],
    "sg:phone":"+61 2 9371 6436",
    "sg:postcode":"2030",
    "sg:province":"NSW",
    "sg:tags":[
        "accountant",
        "auditor"
    ],
    "wof:name":"Savona S",
    "wof:placetype":"venue"
},
  "geometry": {"coordinates":[151.27842712399999,-33.8721122742],"type":"Point"}
}