{
  "type": "Feature",
  "properties": {
    "addr:full":"436 Maitland Rd Mayfield West NSW 2304",
    "addr:housenumber":"436",
    "addr:postcode":"2304",
    "addr:street":"Maitland Rd",
    "iso:country":"AU",
    "sg:address":"436 Maitland Rd",
    "sg:city":"Mayfield West",
    "sg:classifiers":[
        {
            "category":"Fast Food",
            "type":"Food & Drink"
        }
    ],
    "sg:phone":"+61 2 4960 0191",
    "sg:postcode":"2304",
    "sg:province":"NSW",
    "sg:tags":[
        "away",
        "take"
    ],
    "wof:name":"Mega Burgers Takeaway",
    "wof:placetype":"venue"
},
  "geometry": {"coordinates":[151.728225708,-32.8912315369],"type":"Point"}
}