{
  "type": "Feature",
  "properties": {
    "addr:full":"111 Morayfield Rd Caboolture QLD 4510",
    "addr:housenumber":"111",
    "addr:postcode":"4510",
    "addr:street":"Morayfield Rd",
    "iso:country":"AU",
    "sg:address":"111 Morayfield Rd",
    "sg:city":"Caboolture",
    "sg:classifiers":[
        {
            "category":"Health Services",
            "subcategory":"Doctor",
            "type":"Services"
        }
    ],
    "sg:phone":"+61 7 5495 8755",
    "sg:postcode":"4510",
    "sg:province":"QLD",
    "sg:tags":[
        "medical",
        "practitioner"
    ],
    "wof:name":"Queensland Diagnostic Imaging",
    "wof:placetype":"venue"
},
  "geometry": {"coordinates":[152.94931,-27.097281],"type":"Point"}
}