{
  "type": "Feature",
  "properties": {
    "iso:country":"AU",
    "sg:address":"116 Panatana Drv",
    "sg:city":"Port Sorell",
    "sg:classifiers":[
        {
            "category":"Building & Trades",
            "subcategory":"Construction",
            "type":"Services"
        }
    ],
    "sg:phone":"+61 438 287 041",
    "sg:postcode":"7307",
    "sg:province":"TAS",
    "sg:tags":[
        "concrete",
        "contractor"
    ],
    "wof:name":"Curb-Fast",
    "wof:placetype":"venue"
},
  "geometry": {"coordinates":[146.551422,-41.173405],"type":"Point"}
}