{
  "type": "Feature",
  "properties": {
    "iso:country":"AU",
    "sg:address":"14 Bungaree Rd",
    "sg:city":"Wilson",
    "sg:classifiers":[
        {
            "category":"Health Services",
            "subcategory":"Chiropractor",
            "type":"Services"
        }
    ],
    "sg:phone":"+61 8 9356 1051",
    "sg:postcode":"6107",
    "sg:province":"WA",
    "wof:name":"Hellemons Pamela M",
    "wof:placetype":"venue"
},
  "geometry": {"coordinates":[115.90586853000001,-32.0145187378],"type":"Point"}
}