{
  "type": "Feature",
  "properties": {
    "iso:country":"AU",
    "sg:address":"Reynard St",
    "sg:city":"Pascoe Vale South",
    "sg:classifiers":[
        {
            "category":"Education",
            "subcategory":"School",
            "type":"Public Place"
        }
    ],
    "sg:phone":"+61 3 9386 4301",
    "sg:postcode":"3044",
    "sg:province":"VIC",
    "sg:tags":[
        "state",
        "except",
        "nsw"
    ],
    "wof:name":"Pascoe Vale South Primary",
    "wof:placetype":"venue"
},
  "geometry": {"coordinates":[144.93821716299999,-37.745677948],"type":"Point"}
}