{
  "type": "Feature",
  "properties": {
    "addr:full":"9 Dell Rd Gosford West NSW 2250",
    "addr:housenumber":"9",
    "addr:postcode":"2250",
    "addr:street":"Dell Rd",
    "iso:country":"AU",
    "sg:address":"9 Dell Rd",
    "sg:city":"Gosford West",
    "sg:classifiers":[
        {
            "category":"Retail",
            "subcategory":"Auto Repair",
            "type":"Services"
        }
    ],
    "sg:phone":"+61 2 4323 3000",
    "sg:postcode":"2250",
    "sg:province":"NSW",
    "sg:tags":[
        "bus",
        "truck"
    ],
    "wof:name":"Scania Australia Pty Ltd",
    "wof:placetype":"venue"
},
  "geometry": {"coordinates":[151.3306427,-33.4136352539],"type":"Point"}
}