{
  "type": "Feature",
  "properties": {
    "iso:country":"AU",
    "sg:address":"PO Box 888",
    "sg:city":"Hurstville",
    "sg:classifiers":[
        {
            "category":"Retail",
            "subcategory":"Driving School",
            "type":"Services"
        }
    ],
    "sg:phone":"+61 2 9588 7766",
    "sg:postcode":"2220",
    "sg:province":"NSW",
    "wof:name":"Drive Safe Australia",
    "wof:placetype":"venue"
},
  "geometry": {"coordinates":[151.10104370100001,-33.9671897888],"type":"Point"}
}