{
  "type": "Feature",
  "properties": {
    "addr:full":"170 Queen St Woollahra NSW 2025",
    "addr:housenumber":"170",
    "addr:postcode":"2025",
    "addr:street":"Queen St",
    "iso:country":"AU",
    "sg:address":"170 Queen St",
    "sg:city":"Woollahra",
    "sg:classifiers":[
        {
            "category":"Shopping",
            "subcategory":"Antiques",
            "type":"Retail Goods"
        }
    ],
    "sg:phone":"+61 2 9362 1733",
    "sg:postcode":"2025",
    "sg:province":"NSW",
    "wof:name":"Sally Beresford",
    "wof:placetype":"venue"
},
  "geometry": {"coordinates":[151.240509033,-33.8876876831],"type":"Point"}
}