{
  "type": "Feature",
  "properties": {
    "addr:full":"16 Murray St Merrylands NSW 2160",
    "addr:housenumber":"16",
    "addr:postcode":"2160",
    "addr:street":"Murray St",
    "iso:country":"AU",
    "sg:address":"16 Murray St",
    "sg:city":"Merrylands",
    "sg:classifiers":[
        {
            "category":"Building & Trades",
            "subcategory":"Construction",
            "type":"Services"
        }
    ],
    "sg:phone":"+61 405 323 233",
    "sg:postcode":"2160",
    "sg:province":"NSW",
    "sg:tags":[
        "rendering",
        "cement"
    ],
    "wof:name":"Nooris Advanced Cement Rendering",
    "wof:placetype":"venue"
},
  "geometry": {"coordinates":[150.988845825,-33.8260955811],"type":"Point"}
}