{
  "type": "Feature",
  "properties": {
    "addr:full":"Sporing Ave Kings Langley NSW 2147",
    "addr:postcode":"2147",
    "addr:street":"Sporing Ave",
    "iso:country":"AU",
    "sg:address":"Sporing Ave",
    "sg:city":"Kings Langley",
    "sg:classifiers":[
        {
            "category":"Wholesale",
            "subcategory":"Machinery & Supplies",
            "type":"Manufacturing & Wholesale Goods"
        }
    ],
    "sg:phone":"+61 2 9674 7222",
    "sg:postcode":"2147",
    "sg:province":"NSW",
    "sg:tags":[
        "equipment",
        "laboratory"
    ],
    "wof:name":"AMYL Media Pty Ltd",
    "wof:placetype":"venue"
},
  "geometry": {"coordinates":[150.934204102,-33.747543335],"type":"Point"}
}