{
  "type": "Feature",
  "properties": {
    "addr:full":"Cnr Harold St & Victoria Rd Macquarie Fields NSW 2564",
    "addr:postcode":"2564",
    "addr:street":"Harold St & Victoria Rd",
    "iso:country":"AU",
    "sg:address":"Cnr Harold St & Victoria Rd",
    "sg:city":"Macquarie Fields",
    "sg:classifiers":[
        {
            "category":"Autos & Motor Vehicles",
            "subcategory":"Fuel & Gas Station",
            "type":"Retail Goods"
        }
    ],
    "sg:phone":"+61 2 9618 2685",
    "sg:postcode":"2564",
    "sg:province":"NSW",
    "wof:name":"BP Australia Pty Ltd",
    "wof:placetype":"venue"
},
  "geometry": {"coordinates":[150.89372253400001,-33.985660553],"type":"Point"}
}