{
  "type": "Feature",
  "properties": {
    "addr:full":"131 Chester Pass Rd Albany WA 6330",
    "addr:housenumber":"131",
    "addr:postcode":"6330",
    "addr:street":"Chester Pass Rd",
    "iso:country":"AU",
    "sg:address":"131 Chester Pass Rd",
    "sg:city":"Albany",
    "sg:classifiers":[
        {
            "category":"Wholesale",
            "subcategory":"Auto Parts",
            "type":"Manufacturing & Wholesale Goods"
        }
    ],
    "sg:phone":"+61 8 9841 5298",
    "sg:postcode":"6330",
    "sg:province":"WA",
    "sg:tags":[
        "recyclers"
    ],
    "wof:name":"Hills Auto Wreckers",
    "wof:placetype":"venue"
},
  "geometry": {"coordinates":[117.87361145,-34.993347168],"type":"Point"}
}