{
  "type": "Feature",
  "properties": {
    "iso:country":"AU",
    "sg:address":"St Vincents Private Hospital 59-61 Victoria Pde",
    "sg:city":"Fitzroy",
    "sg:classifiers":[
        {
            "category":"Health Services",
            "subcategory":"Doctor",
            "type":"Services"
        }
    ],
    "sg:phone":"+61 3 9417 1055",
    "sg:postcode":"3065",
    "sg:province":"VIC",
    "sg:tags":[
        "medical",
        "practitioner"
    ],
    "wof:name":"Carroll Lawrence",
    "wof:placetype":"venue"
},
  "geometry": {"coordinates":[144.97615051299999,-37.8079299927],"type":"Point"}
}