{
  "type": "Feature",
  "properties": {
    "iso:country":"AU",
    "sg:address":"Medici on Scott 4/ 15 Scott St",
    "sg:city":"Toowoomba",
    "sg:classifiers":[
        {
            "category":"Manufacturing",
            "subcategory":"Food",
            "type":"Manufacturing & Wholesale Goods"
        }
    ],
    "sg:phone":"+61 7 4638 1723",
    "sg:postcode":"4350",
    "sg:province":"QLD",
    "sg:tags":[
        "function",
        "catering"
    ],
    "wof:name":"Pink Peppercorn Deli Cafe",
    "wof:placetype":"venue"
},
  "geometry": {"coordinates":[151.97283899999999,-27.565639],"type":"Point"}
}