{
  "type": "Feature",
  "properties": {
    "iso:country":"AU",
    "sg:address":"5 Fitzgerald Rd",
    "sg:city":"Pasadena",
    "sg:classifiers":[
        {
            "category":"Organizations",
            "subcategory":"Non-profit Organization",
            "type":"Services"
        }
    ],
    "sg:phone":"+61 8 8372 0182",
    "sg:postcode":"5042",
    "sg:province":"SA",
    "sg:tags":[
        "environmental",
        "organisation",
        "conservation"
    ],
    "wof:name":"Pasadena Natural Resource Centre",
    "wof:placetype":"venue"
},
  "geometry": {"coordinates":[138.590317,-35.000031],"type":"Point"}
}