{
  "type": "Feature",
  "properties": {
    "iso:country":"AU",
    "sg:address":"341 Gresford Rd",
    "sg:city":"Paterson",
    "sg:classifiers":[
        {
            "category":"Farming",
            "subcategory":"Fish & Marine Products",
            "type":"Manufacturing & Wholesale Goods"
        }
    ],
    "sg:phone":"+61 2 4938 5596",
    "sg:postcode":"2421",
    "sg:province":"NSW",
    "sg:tags":[
        "organic"
    ],
    "wof:name":"Paterson Valley Biodynamic Beef",
    "wof:placetype":"venue"
},
  "geometry": {"coordinates":[151.597382,-32.574482],"type":"Point"}
}