{
  "type": "Feature",
  "properties": {
    "addr:full":"16 Stokes St Townsville QLD 4810",
    "addr:housenumber":"16",
    "addr:postcode":"4810",
    "addr:street":"Stokes St",
    "iso:country":"AU",
    "sg:address":"16 Stokes St",
    "sg:city":"Townsville",
    "sg:classifiers":[
        {
            "category":"Banks & Credit Unions",
            "subcategory":"Bank",
            "type":"Services"
        }
    ],
    "sg:phone":"+61 7 4761 8460",
    "sg:postcode":"4810",
    "sg:province":"QLD",
    "wof:name":"Bank of Queensland",
    "wof:placetype":"venue"
},
  "geometry": {"coordinates":[146.81651299999999,-19.259544],"type":"Point"}
}