{
  "type": "Feature",
  "properties": {
    "addr:full":"Level 1/ 225 Bay St Brighton VIC 3186",
    "addr:housenumber":"/ 225",
    "addr:postcode":"3186",
    "addr:street":"Bay St",
    "iso:country":"AU",
    "sg:address":"Level 1/ 225 Bay St",
    "sg:city":"Brighton",
    "sg:classifiers":[
        {
            "category":"Professional",
            "subcategory":"Computer Services",
            "type":"Services"
        }
    ],
    "sg:phone":"+61 3 9596 6522",
    "sg:postcode":"3186",
    "sg:province":"VIC",
    "sg:tags":[
        "equipment",
        "networking",
        "installation"
    ],
    "wof:name":"Datasphere Pty Ltd",
    "wof:placetype":"venue"
},
  "geometry": {"coordinates":[144.99948120100001,-37.9049568176],"type":"Point"}
}