{
  "type": "Feature",
  "properties": {
    "addr:full":"PO Box 220 Mt Lawley WA 6050",
    "addr:postcode":"6050",
    "iso:country":"AU",
    "sg:address":"PO Box 220",
    "sg:city":"Mt Lawley",
    "sg:classifiers":[
        {
            "category":"Real Estate",
            "subcategory":"Surveying",
            "type":"Services"
        }
    ],
    "sg:phone":"+61 8 9272 1736",
    "sg:postcode":"6050",
    "sg:province":"WA",
    "sg:tags":[
        "surveyor",
        "land"
    ],
    "wof:name":"Geographe Surveys",
    "wof:placetype":"venue"
},
  "geometry": {"coordinates":[115.870262146,-31.9267730713],"type":"Point"}
}