{
  "type": "Feature",
  "properties": {
    "addr:full":"78-81 Willesden Rd Oakleigh VIC 3166",
    "addr:housenumber":"78-81",
    "addr:postcode":"3166",
    "addr:street":"Willesden Rd",
    "iso:country":"AU",
    "sg:address":"78-81 Willesden Rd",
    "sg:city":"Oakleigh",
    "sg:classifiers":[
        {
            "category":"Education",
            "subcategory":"School",
            "type":"Public Place"
        }
    ],
    "sg:phone":"+61 3 9569 6128",
    "sg:postcode":"3166",
    "sg:province":"VIC",
    "sg:tags":[
        "co-educational"
    ],
    "wof:name":"Oakleigh Greek Orthodox College",
    "wof:placetype":"venue"
},
  "geometry": {"coordinates":[145.082763672,-37.8962860107],"type":"Point"}
}