{
  "type": "Feature",
  "properties": {
    "addr:full":"Shp 68/ 166 Somerville Rd Hampton Park VIC 3976",
    "addr:housenumber":"68 / 166",
    "addr:postcode":"3976",
    "addr:street":"Somerville Rd",
    "iso:country":"AU",
    "sg:address":"Shp 68/ 166 Somerville Rd",
    "sg:city":"Hampton Park",
    "sg:classifiers":[
        {
            "category":"Sports & Exercise",
            "subcategory":"Gym",
            "type":"Entertainment"
        }
    ],
    "sg:phone":"+61 3 8787 8400",
    "sg:postcode":"3976",
    "sg:province":"VIC",
    "sg:tags":[
        "health",
        "fitness"
    ],
    "wof:name":"Curves Hampton Park",
    "wof:placetype":"venue"
},
  "geometry": {"coordinates":[145.26556396500001,-38.0320281982],"type":"Point"}
}