{
  "type": "Feature",
  "properties": {
    "addr:full":"8 Goyder St Erindale SA 5066",
    "addr:housenumber":"8",
    "addr:postcode":"5066",
    "addr:street":"Goyder St",
    "iso:country":"AU",
    "sg:address":"8 Goyder St",
    "sg:city":"Erindale",
    "sg:classifiers":[
        {
            "category":"Professional",
            "subcategory":"Engineering",
            "type":"Services"
        }
    ],
    "sg:phone":"+61 8 8364 2208",
    "sg:postcode":"5066",
    "sg:province":"SA",
    "sg:tags":[
        "engineer",
        "structural"
    ],
    "wof:name":"Peter H Cox & Associates",
    "wof:placetype":"venue"
},
  "geometry": {"coordinates":[138.66653442399999,-34.9277496338],"type":"Point"}
}