{
  "type": "Feature",
  "properties": {
    "iso:country":"AU",
    "sg:address":"107 Miles Platting Rd",
    "sg:city":"Eight Mile Plains",
    "sg:classifiers":[
        {
            "category":"Airline",
            "type":"Transportation"
        }
    ],
    "sg:phone":"+61 7 3340 9700",
    "sg:postcode":"4113",
    "sg:province":"QLD",
    "sg:tags":[
        "surveyor",
        "aerial"
    ],
    "wof:name":"Cottrell Cameron & Steen Surveys Pty Ltd",
    "wof:placetype":"venue"
},
  "geometry": {"coordinates":[153.098556519,-27.5768604279],"type":"Point"}
}