{
  "type": "Feature",
  "properties": {
    "addr:full":"3/ 47 Palm Ave Surfers Paradise QLD 4217",
    "addr:housenumber":"/ 47",
    "addr:postcode":"4217",
    "addr:street":"Palm Ave",
    "iso:country":"AU",
    "sg:address":"3/ 47 Palm Ave",
    "sg:city":"Surfers Paradise",
    "sg:classifiers":[
        {
            "category":"Recreation",
            "type":"Entertainment"
        }
    ],
    "sg:phone":"+61 409 635 708",
    "sg:postcode":"4217",
    "sg:province":"QLD",
    "sg:tags":[
        "recreational",
        "diver"
    ],
    "sg:website":"http://www.scubasteve.com.au",
    "wof:name":"Scuba Steve's Diving Adventures",
    "wof:placetype":"venue"
},
  "geometry": {"coordinates":[153.425613403,-27.9954051971],"type":"Point"}
}