{
  "type": "Feature",
  "properties": {
    "addr:full":"Suite 204/Lvl 2, 443 Victoria Ave Chatswood NSW 2067",
    "addr:housenumber":"443",
    "addr:postcode":"2067",
    "addr:street":"Victoria Ave",
    "iso:country":"AU",
    "sg:address":"Suite 204/Lvl 2, 443 Victoria Ave",
    "sg:city":"Chatswood",
    "sg:classifiers":[
        {
            "category":"Health Services",
            "subcategory":"Doctor",
            "type":"Services"
        }
    ],
    "sg:phone":"+61 2 9411 7747",
    "sg:postcode":"2067",
    "sg:province":"NSW",
    "sg:tags":[
        "medical",
        "practitioner"
    ],
    "wof:name":"Park Gordon Dr",
    "wof:placetype":"venue"
},
  "geometry": {"coordinates":[151.18260192899999,-33.7962303162],"type":"Point"}
}