{
  "type": "Feature",
  "properties": {
    "iso:country":"AU",
    "sg:address":"40 Church St",
    "sg:city":"Ryde",
    "sg:classifiers":[
        {
            "category":"Real Estate",
            "subcategory":"Real Estate Agent",
            "type":"Services"
        }
    ],
    "sg:phone":"+61 2 9808 3200",
    "sg:postcode":"2112",
    "sg:province":"NSW",
    "wof:name":"Ray White Ryde",
    "wof:placetype":"venue"
},
  "geometry": {"coordinates":[151.105072022,-33.8146324158],"type":"Point"}
}