{
  "type": "Feature",
  "properties": {
    "addr:full":"492 Townsend St Albury NSW 2640",
    "addr:housenumber":"492",
    "addr:postcode":"2640",
    "addr:street":"Townsend St",
    "iso:country":"AU",
    "sg:address":"492 Townsend St",
    "sg:city":"Albury",
    "sg:classifiers":[
        {
            "category":"Home & Garden",
            "subcategory":"Building Materials",
            "type":"Retail Goods"
        }
    ],
    "sg:phone":"+61 2 6040 6740",
    "sg:postcode":"2640",
    "sg:province":"NSW",
    "sg:tags":[
        "gate"
    ],
    "wof:name":"Gerard Percy Electrics Pty Ltd",
    "wof:placetype":"venue"
},
  "geometry": {"coordinates":[146.91317749000001,-36.080745697],"type":"Point"}
}