{
  "type": "Feature",
  "properties": {
    "addr:full":"520 King Georges Rd Beverly Hills NSW 2209",
    "addr:housenumber":"520",
    "addr:postcode":"2209",
    "addr:street":"King Georges Rd",
    "iso:country":"AU",
    "sg:address":"520 King Georges Rd",
    "sg:city":"Beverly Hills",
    "sg:classifiers":[
        {
            "category":"Fast Food",
            "type":"Food & Drink"
        }
    ],
    "sg:phone":"+61 2 9580 9229",
    "sg:postcode":"2209",
    "sg:province":"NSW",
    "sg:tags":[
        "away",
        "take"
    ],
    "wof:name":"Beverley Hills Kebabs",
    "wof:placetype":"venue"
},
  "geometry": {"coordinates":[151.08215300000001,-33.950634],"type":"Point"}
}