{
  "type": "Feature",
  "properties": {
    "iso:country":"AU",
    "sg:address":"Shop2/ 60 Liverpool St",
    "sg:city":"Port Lincoln",
    "sg:classifiers":[
        {
            "category":"Shopping",
            "subcategory":"Computers & Home Electronics",
            "type":"Retail Goods"
        }
    ],
    "sg:phone":"+61 8 8683 1233",
    "sg:postcode":"5606",
    "sg:province":"SA",
    "sg:tags":[
        "small",
        "equipment",
        "business"
    ],
    "wof:name":"Paragon Computer World",
    "wof:placetype":"venue"
},
  "geometry": {"coordinates":[135.861313,-34.723274],"type":"Point"}
}