{
  "type": "Feature",
  "properties": {
    "addr:full":"203 Margaret St Toowoomba QLD 4350",
    "addr:housenumber":"203",
    "addr:postcode":"4350",
    "addr:street":"Margaret St",
    "iso:country":"AU",
    "sg:address":"203 Margaret St",
    "sg:city":"Toowoomba",
    "sg:classifiers":[
        {
            "category":"Personal",
            "subcategory":"Beauty Salon",
            "type":"Services"
        }
    ],
    "sg:phone":"+61 7 4691 0145",
    "sg:postcode":"4350",
    "sg:province":"QLD",
    "sg:tags":[
        "supply",
        "artist",
        "make-up"
    ],
    "wof:name":"Amanda McLennan-Dehnert",
    "wof:placetype":"venue"
},
  "geometry": {"coordinates":[151.95422400000001,-27.560986],"type":"Point"}
}