{
  "type": "Feature",
  "properties": {
    "iso:country":"AU",
    "sg:address":"PO Box 456",
    "sg:city":"Wodonga",
    "sg:classifiers":[
        {
            "category":"Communications",
            "subcategory":"News Services",
            "type":"Services"
        }
    ],
    "sg:phone":"+61 2 6056 2266",
    "sg:postcode":"3690",
    "sg:province":"VIC",
    "sg:tags":[
        "information",
        "tourist",
        "attractions"
    ],
    "wof:name":"Wodonga Charter Specialists Pty Ltd",
    "wof:placetype":"venue"
},
  "geometry": {"coordinates":[146.84840393100001,-36.1168785095],"type":"Point"}
}