{
  "type": "Feature",
  "properties": {
    "addr:full":"Forest Lakes Shopping Centre, Forest Lakes Rd Thornlie WA 6108",
    "addr:postcode":"6108",
    "addr:street":"Forest Lakes Rd",
    "iso:country":"AU",
    "sg:address":"Forest Lakes Shopping Centre, Forest Lakes Rd",
    "sg:city":"Thornlie",
    "sg:classifiers":[
        {
            "category":"Health Services",
            "subcategory":"Chiropractor",
            "type":"Services"
        }
    ],
    "sg:phone":"+61 8 9493 5655",
    "sg:postcode":"6108",
    "sg:province":"WA",
    "wof:name":"Forest Lakes Chiropractic Health Centre",
    "wof:placetype":"venue"
},
  "geometry": {"coordinates":[115.952407837,-32.0700950623],"type":"Point"}
}