{
  "type": "Feature",
  "properties": {
    "addr:full":"280 Bay Rd Cheltenham VIC 3192",
    "addr:housenumber":"280",
    "addr:postcode":"3192",
    "addr:street":"Bay Rd",
    "iso:country":"AU",
    "sg:address":"280 Bay Rd",
    "sg:city":"Cheltenham",
    "sg:classifiers":[
        {
            "category":"Home & Garden",
            "subcategory":"Hardware",
            "type":"Retail Goods"
        }
    ],
    "sg:phone":"+61 3 9581 6150",
    "sg:postcode":"3192",
    "sg:province":"VIC",
    "sg:tags":[
        "tarpaulin"
    ],
    "wof:name":"Structureflex Pacific",
    "wof:placetype":"venue"
},
  "geometry": {"coordinates":[145.03370666500001,-37.9553909302],"type":"Point"}
}