{
  "type": "Feature",
  "properties": {
    "iso:country":"AU",
    "sg:address":"6 Chapel St",
    "sg:city":"Glen Waverley",
    "sg:classifiers":[
        {
            "category":"Professional",
            "subcategory":"Detective & Security Services",
            "type":"Services"
        }
    ],
    "sg:phone":"+61 3 8802 8073",
    "sg:postcode":"3150",
    "sg:province":"VIC",
    "sg:tags":[
        "consultant",
        "system"
    ],
    "wof:name":"Transcam Concepts Pty Ltd",
    "wof:placetype":"venue"
},
  "geometry": {"coordinates":[145.17466735799999,-37.8714561462],"type":"Point"}
}