{
  "type": "Feature",
  "properties": {
    "iso:country":"AU",
    "sg:address":"22 Lily St",
    "sg:city":"Cairns North",
    "sg:classifiers":[
        {
            "category":"Food & Beverages",
            "subcategory":"Bakery",
            "type":"Retail Goods"
        }
    ],
    "sg:phone":"+61 7 4041 3178",
    "sg:postcode":"4870",
    "sg:province":"QLD",
    "sg:tags":[
        "cake",
        "shop",
        "pastry"
    ],
    "wof:name":"Joey's Bakery",
    "wof:placetype":"venue"
},
  "geometry": {"coordinates":[145.75819397000001,-16.9045639038],"type":"Point"}
}