{
  "type": "Feature",
  "properties": {
    "addr:full":"104- 110 Talbragar St Dubbo NSW 2830",
    "addr:housenumber":"110",
    "addr:postcode":"2830",
    "addr:street":"Talbragar St",
    "iso:country":"AU",
    "sg:address":"104- 110 Talbragar St",
    "sg:city":"Dubbo",
    "sg:classifiers":[
        {
            "category":"Home & Garden",
            "subcategory":"Furniture",
            "type":"Retail Goods"
        }
    ],
    "sg:phone":"+61 13 26 44",
    "sg:postcode":"2830",
    "sg:province":"NSW",
    "sg:tags":[
        "business"
    ],
    "wof:name":"Corporate Express",
    "wof:placetype":"venue"
},
  "geometry": {"coordinates":[148.605178833,-32.2451400757],"type":"Point"}
}