{
  "type": "Feature",
  "properties": {
    "addr:full":"PO Box 331 Sorrento VIC 3943",
    "addr:postcode":"3943",
    "iso:country":"AU",
    "sg:address":"PO Box 331",
    "sg:city":"Sorrento",
    "sg:classifiers":[
        {
            "category":"Building & Trades",
            "subcategory":"Construction",
            "type":"Services"
        }
    ],
    "sg:phone":"+61 3 5988 9986",
    "sg:postcode":"3943",
    "sg:province":"VIC",
    "sg:tags":[
        "contractor"
    ],
    "wof:name":"Rob Gaffney Constructions Pty Ltd",
    "wof:placetype":"venue"
},
  "geometry": {"coordinates":[144.742431641,-38.3386688232],"type":"Point"}
}