{
  "type": "Feature",
  "properties": {
    "addr:full":"30 Simpson St Sale VIC 3850",
    "addr:housenumber":"30",
    "addr:postcode":"3850",
    "addr:street":"Simpson St",
    "iso:country":"AU",
    "sg:address":"30 Simpson St",
    "sg:city":"Sale",
    "sg:classifiers":[
        {
            "category":"Building & Trades",
            "subcategory":"Construction",
            "type":"Services"
        }
    ],
    "sg:phone":"+61 3 5144 3397",
    "sg:postcode":"3850",
    "sg:province":"VIC",
    "sg:tags":[
        "contractor"
    ],
    "wof:name":"Stephenson R A & I",
    "wof:placetype":"venue"
},
  "geometry": {"coordinates":[147.06288147000001,-38.0991668701],"type":"Point"}
}