{
  "type": "Feature",
  "properties": {
    "addr:full":"Industrial Ave Goombungee QLD 4354",
    "addr:postcode":"4354",
    "addr:street":"Industrial Ave",
    "iso:country":"AU",
    "sg:address":"Industrial Ave",
    "sg:city":"Goombungee",
    "sg:classifiers":[
        {
            "category":"Building & Trades",
            "subcategory":"Construction",
            "type":"Services"
        }
    ],
    "sg:phone":"+61 7 4696 5200",
    "sg:postcode":"4354",
    "sg:province":"QLD",
    "sg:tags":[
        "welding"
    ],
    "wof:name":"Leicht's Welding Industries",
    "wof:placetype":"venue"
},
  "geometry": {"coordinates":[151.85313400000001,-27.301399],"type":"Point"}
}