{
  "type": "Feature",
  "properties": {
    "addr:full":"PO Box 210 Korumburra VIC 3950",
    "addr:postcode":"3950",
    "iso:country":"AU",
    "sg:address":"PO Box 210",
    "sg:city":"Korumburra",
    "sg:classifiers":[
        {
            "category":"Professional",
            "type":"Services"
        }
    ],
    "sg:phone":"+61 408 380 627",
    "sg:postcode":"3950",
    "sg:province":"VIC",
    "sg:tags":[
        "courier"
    ],
    "wof:name":"Burra Couriers",
    "wof:placetype":"venue"
},
  "geometry": {"coordinates":[145.82281494099999,-38.4323501587],"type":"Point"}
}