{
  "type": "Feature",
  "properties": {
    "addr:full":"1- 3 Lakewood Blv Braeside VIC 3195",
    "addr:housenumber":"3",
    "addr:postcode":"3195",
    "addr:street":"Lakewood Blv",
    "iso:country":"AU",
    "sg:address":"1- 3",
    "sg:city":"Lakewood Blv Braeside",
    "sg:classifiers":[
        {
            "category":"Wholesale",
            "subcategory":"Machinery & Supplies",
            "type":"Manufacturing & Wholesale Goods"
        }
    ],
    "sg:phone":"+61 3 9580 4366",
    "sg:postcode":"3195",
    "sg:province":"VIC",
    "sg:tags":[
        "process",
        "instrument",
        "control"
    ],
    "wof:name":"Davidson Measurement Pty Ltd",
    "wof:placetype":"venue"
},
  "geometry": {"coordinates":[145.11587524399999,-38.0027999878],"type":"Point"}
}