{
  "type": "Feature",
  "properties": {
    "iso:country":"AU",
    "sg:address":"72 Dawson Hwy",
    "sg:city":"Moura",
    "sg:classifiers":[
        {
            "category":"Arts & Performance",
            "subcategory":"Dance",
            "type":"Entertainment"
        }
    ],
    "sg:phone":"+61 7 4997 2164",
    "sg:postcode":"4718",
    "sg:province":"QLD",
    "sg:tags":[
        "theatrical",
        "ballet",
        "tuition"
    ],
    "wof:name":"Moura Ballet & Dance Appreciation Group Incorporated",
    "wof:placetype":"venue"
},
  "geometry": {"coordinates":[149.96981811500001,-24.5708026886],"type":"Point"}
}