{
  "type": "Feature",
  "properties": {
    "addr:full":"GPO Box 1127 Brisbane QLD 4001",
    "addr:postcode":"4001",
    "iso:country":"AU",
    "sg:address":"GPO Box 1127",
    "sg:city":"Brisbane",
    "sg:classifiers":[
        {
            "category":"Manufacturing",
            "subcategory":"Jewelry",
            "type":"Manufacturing & Wholesale Goods"
        }
    ],
    "sg:phone":"+61 7 3229 3271",
    "sg:postcode":"4001",
    "sg:province":"QLD",
    "sg:tags":[
        "mfrg",
        "jeweller"
    ],
    "wof:name":"Avery Wallace Ltd",
    "wof:placetype":"venue"
},
  "geometry": {"coordinates":[152.88931274399999,-27.5977859497],"type":"Point"}
}