{
  "type": "Feature",
  "properties": {
    "iso:country":"AU",
    "sg:address":"7 Demand Ave",
    "sg:city":"Arundel",
    "sg:classifiers":[
        {
            "category":"Home & Garden",
            "subcategory":"Mobile Homes",
            "type":"Retail Goods"
        }
    ],
    "sg:phone":"+61 7 5597 4400",
    "sg:postcode":"4214",
    "sg:province":"QLD",
    "sg:tags":[
        "motor",
        "campervans"
    ],
    "wof:name":"Paradise Motor Homes",
    "wof:placetype":"venue"
},
  "geometry": {"coordinates":[153.35848999000001,-27.9864196777],"type":"Point"}
}