{
  "type": "Feature",
  "properties": {
    "addr:full":"Bookmark Ave Renmark SA 5341",
    "addr:postcode":"5341",
    "addr:street":"Bookmark Ave",
    "iso:country":"AU",
    "sg:address":"Bookmark Ave",
    "sg:city":"Renmark",
    "sg:classifiers":[
        {
            "category":"Building & Trades",
            "subcategory":"Construction",
            "type":"Services"
        }
    ],
    "sg:phone":"+61 8 8595 1489",
    "sg:postcode":"5341",
    "sg:province":"SA",
    "sg:tags":[
        "fencing",
        "contractor"
    ],
    "wof:name":"Mitchell Fencing",
    "wof:placetype":"venue"
},
  "geometry": {"coordinates":[140.730911255,-34.1673431396],"type":"Point"}
}