{
  "type": "Feature",
  "properties": {
    "addr:full":"12 Kinkaid Ave North Plympton SA 5037",
    "addr:housenumber":"12",
    "addr:postcode":"5037",
    "addr:street":"Kinkaid Ave North",
    "iso:country":"AU",
    "sg:address":"12 Kinkaid Ave",
    "sg:city":"North Plympton",
    "sg:classifiers":[
        {
            "category":"Food & Beverages",
            "subcategory":"Groceries & Convenience Stores",
            "type":"Retail Goods"
        }
    ],
    "sg:phone":"+61 8 8293 7789",
    "sg:postcode":"5037",
    "sg:province":"SA",
    "sg:tags":[
        "merchant",
        "egg"
    ],
    "wof:name":"Adelaide Eggs",
    "wof:placetype":"venue"
},
  "geometry": {"coordinates":[138.54298400900001,-34.9582557678],"type":"Point"}
}