{
  "type": "Feature",
  "properties": {
    "addr:full":"6 Roxburgh Rd Wights Mountain QLD 4520",
    "addr:housenumber":"6",
    "addr:postcode":"4520",
    "addr:street":"Roxburgh Rd",
    "iso:country":"AU",
    "sg:address":"6 Roxburgh Rd",
    "sg:city":"Wights Mountain",
    "sg:classifiers":[
        {
            "category":"Building & Trades",
            "subcategory":"Construction",
            "type":"Services"
        }
    ],
    "sg:phone":"+61 417 790 045",
    "sg:postcode":"4520",
    "sg:province":"QLD",
    "sg:tags":[
        "contractor"
    ],
    "wof:name":"Tropicool Homes - Queensland",
    "wof:placetype":"venue"
},
  "geometry": {"coordinates":[152.85243199999999,-27.382574],"type":"Point"}
}