{
  "type": "Feature",
  "properties": {
    "iso:country":"AU",
    "sg:address":"PO Box 698",
    "sg:city":"Stones Corner",
    "sg:classifiers":[
        {
            "category":"Professional",
            "subcategory":"Employment Agencies",
            "type":"Services"
        }
    ],
    "sg:phone":"+61 411 517 265",
    "sg:postcode":"4120",
    "sg:province":"QLD",
    "sg:tags":[
        "entertainer",
        "agent"
    ],
    "wof:name":"Caribbean Kings",
    "wof:placetype":"venue"
},
  "geometry": {"coordinates":[153.046340942,-27.5013694763],"type":"Point"}
}