{
  "type": "Feature",
  "properties": {
    "addr:full":"603a Glebe Rd Adamstown NSW 2289",
    "addr:housenumber":"603a",
    "addr:postcode":"2289",
    "addr:street":"Glebe Rd",
    "iso:country":"AU",
    "sg:address":"603a Glebe Rd",
    "sg:city":"Adamstown",
    "sg:classifiers":[
        {
            "category":"Personal",
            "subcategory":"Beauty Salon",
            "type":"Services"
        }
    ],
    "sg:phone":"+61 2 4957 3268",
    "sg:postcode":"2289",
    "sg:province":"NSW",
    "sg:tags":[
        "hairdresser"
    ],
    "wof:name":"Simply Unique Hair Design",
    "wof:placetype":"venue"
},
  "geometry": {"coordinates":[151.725662231,-32.9343185425],"type":"Point"}
}