{
  "type": "Feature",
  "properties": {
    "iso:country":"AU",
    "sg:address":"3 Hunter St",
    "sg:city":"Tatura",
    "sg:classifiers":[
        {
            "category":"Building & Trades",
            "subcategory":"Construction",
            "type":"Services"
        }
    ],
    "sg:phone":"+61 418 577 325",
    "sg:postcode":"3616",
    "sg:province":"VIC",
    "sg:tags":[
        "earth",
        "excavating",
        "moving",
        "contractor"
    ],
    "wof:name":"ADA Excavations",
    "wof:placetype":"venue"
},
  "geometry": {"coordinates":[145.22288513199999,-36.4381980896],"type":"Point"}
}