{
  "type": "Feature",
  "properties": {
    "iso:country":"AU",
    "sg:address":"53 Jessie Wadsworth St",
    "sg:city":"Cowan Cowan",
    "sg:classifiers":[
        {
            "category":"Real Estate",
            "subcategory":"Real Estate Agent",
            "type":"Services"
        }
    ],
    "sg:phone":"+61 7 3410 0041",
    "sg:postcode":"4025",
    "sg:province":"QLD",
    "wof:name":"Ray White Moreton Island",
    "wof:placetype":"venue"
},
  "geometry": {"coordinates":[153.365814,-27.126011],"type":"Point"}
}