{
  "type": "Feature",
  "properties": {
    "addr:full":"56 Kilkenny Pde Berkeley Vale NSW 2261",
    "addr:housenumber":"56",
    "addr:postcode":"2261",
    "addr:street":"Kilkenny Pde",
    "iso:country":"AU",
    "sg:address":"56 Kilkenny Pde",
    "sg:city":"Berkeley Vale",
    "sg:classifiers":[
        {
            "category":"Professional",
            "subcategory":"Art Services",
            "type":"Services"
        }
    ],
    "sg:phone":"+61 409 838 875",
    "sg:postcode":"2261",
    "sg:province":"NSW",
    "sg:tags":[
        "decorator",
        "painter"
    ],
    "wof:name":"Garry Walsh",
    "wof:placetype":"venue"
},
  "geometry": {"coordinates":[151.43699599999999,-33.344994],"type":"Point"}
}