{
  "type": "Feature",
  "properties": {
    "addr:full":"35 Mary St Brisbane QLD 4000",
    "addr:housenumber":"35",
    "addr:postcode":"4000",
    "addr:street":"Mary St",
    "iso:country":"AU",
    "sg:address":"35 Mary St",
    "sg:city":"Brisbane",
    "sg:classifiers":[
        {
            "category":"Banks & Credit Unions",
            "subcategory":"Investment Brokerage",
            "type":"Services"
        }
    ],
    "sg:phone":"+61 7 3808 8016",
    "sg:postcode":"4000",
    "sg:province":"QLD",
    "sg:tags":[
        "shutter",
        "louvre"
    ],
    "wof:name":"Guardian Screens Pty Ltd",
    "wof:placetype":"venue"
},
  "geometry": {"coordinates":[153.026687622,-27.4727210999],"type":"Point"}
}