{
  "type": "Feature",
  "properties": {
    "addr:full":"8 King St Rockdale NSW 2216",
    "addr:housenumber":"8",
    "addr:postcode":"2216",
    "addr:street":"King St",
    "iso:country":"AU",
    "sg:address":"8 King St",
    "sg:city":"Rockdale",
    "sg:classifiers":[
        {
            "category":"Cafe",
            "type":"Food & Drink"
        }
    ],
    "sg:phone":"+61 2 9567 1230",
    "sg:postcode":"2216",
    "sg:province":"NSW",
    "wof:name":"J Cafe The",
    "wof:placetype":"venue"
},
  "geometry": {"coordinates":[151.138824,-33.952343],"type":"Point"}
}