{
  "type": "Feature",
  "properties": {
    "iso:country":"AU",
    "sg:address":"480 Mahoneys Rd",
    "sg:city":"Campbellfield",
    "sg:classifiers":[
        {
            "category":"Home & Garden",
            "subcategory":"Carpets & Floor Coverings",
            "type":"Retail Goods"
        }
    ],
    "sg:phone":"+61 3 9359 5711",
    "sg:postcode":"3061",
    "sg:province":"VIC",
    "sg:tags":[
        "wood"
    ],
    "sg:website":"http://www.mahoneystimber.com.au",
    "wof:name":"Mahoneys Timber & Hardware",
    "wof:placetype":"venue"
},
  "geometry": {"coordinates":[144.96478271500001,-37.6900177002],"type":"Point"}
}