{
  "type": "Feature",
  "properties": {
    "addr:full":"PO Box 1454 Ashfield NSW 2131",
    "addr:postcode":"2131",
    "iso:country":"AU",
    "sg:address":"PO Box 1454",
    "sg:city":"Ashfield",
    "sg:classifiers":[
        {
            "category":"Professional",
            "subcategory":"Management & Consulting",
            "type":"Services"
        }
    ],
    "sg:phone":"+61 2 9799 4829",
    "sg:postcode":"2131",
    "sg:province":"NSW",
    "sg:tags":[
        "consultant",
        "educational"
    ],
    "wof:name":"Delta Education",
    "wof:placetype":"venue"
},
  "geometry": {"coordinates":[151.127441406,-33.8894996643],"type":"Point"}
}