{
  "type": "Feature",
  "properties": {
    "addr:full":"22 Padstum Ave Lalor VIC 3075",
    "addr:housenumber":"22",
    "addr:postcode":"3075",
    "addr:street":"Padstum Ave",
    "iso:country":"AU",
    "sg:address":"22 Padstum Ave",
    "sg:city":"Lalor",
    "sg:classifiers":[
        {
            "category":"Retail",
            "subcategory":"Laundry & Dry Cleaning",
            "type":"Services"
        }
    ],
    "sg:phone":"+61 3 9466 4961",
    "sg:postcode":"3075",
    "sg:province":"VIC",
    "sg:tags":[
        "truck",
        "tip",
        "contractor"
    ],
    "wof:name":"Becvinovski Z",
    "wof:placetype":"venue"
},
  "geometry": {"coordinates":[144.990234375,-37.6691932678],"type":"Point"}
}