{
  "type": "Feature",
  "properties": {
    "addr:full":"U2/ 17 Elmsfield Rd Midvale WA 6056",
    "addr:postcode":"6056",
    "addr:street":"U2 / 17 Elmsfield Rd",
    "iso:country":"AU",
    "sg:address":"U2/ 17 Elmsfield Rd",
    "sg:city":"Midvale",
    "sg:classifiers":[
        {
            "category":"Recreation",
            "subcategory":"Dog Park",
            "type":"Entertainment"
        }
    ],
    "sg:phone":"+61 8 9250 1455",
    "sg:postcode":"6056",
    "sg:province":"WA",
    "sg:tags":[
        "jack"
    ],
    "wof:name":"Hyjack",
    "wof:placetype":"venue"
},
  "geometry": {"coordinates":[116.034667969,-31.8921165466],"type":"Point"}
}