{
  "type": "Feature",
  "properties": {
    "addr:full":"0 Melbourne Rd Shepparton VIC 3630",
    "addr:housenumber":"0",
    "addr:postcode":"3630",
    "addr:street":"Melbourne Rd",
    "iso:country":"AU",
    "sg:address":"0 Melbourne Rd",
    "sg:city":"Shepparton",
    "sg:classifiers":[
        {
            "category":"Professional",
            "subcategory":"Business Services",
            "type":"Services"
        }
    ],
    "sg:phone":"+61 3 5823 1800",
    "sg:postcode":"3630",
    "sg:province":"VIC",
    "sg:tags":[
        "consultant",
        "promoter",
        "entertainment"
    ],
    "wof:name":"The Peppermill Inn",
    "wof:placetype":"venue"
},
  "geometry": {"coordinates":[145.390136719,-36.4269676208],"type":"Point"}
}