{
  "type": "Feature",
  "properties": {
    "addr:full":"PO Box 1720 Aitkenvale QLD 4814",
    "addr:postcode":"4814",
    "iso:country":"AU",
    "sg:address":"PO Box 1720",
    "sg:city":"Aitkenvale",
    "sg:classifiers":[
        {
            "category":"Professional",
            "type":"Services"
        }
    ],
    "sg:phone":"+61 7 4725 1458",
    "sg:postcode":"4814",
    "sg:province":"QLD",
    "sg:tags":[
        "shop",
        "fitting"
    ],
    "wof:name":"Phoenix Constructions (Queensland) Pty. Ltd",
    "wof:placetype":"venue"
},
  "geometry": {"coordinates":[146.76745600000001,-19.2953],"type":"Point"}
}