{
  "type": "Feature",
  "properties": {
    "addr:full":"Sailors Gully Rd Myers Flat VIC 3556",
    "addr:postcode":"3556",
    "addr:street":"Gully Rd",
    "iso:country":"AU",
    "sg:address":"Sailors Gully Rd",
    "sg:city":"Myers Flat",
    "sg:classifiers":[
        {
            "category":"Professional",
            "subcategory":"Computer Services",
            "type":"Services"
        }
    ],
    "sg:phone":"+61 500 500 609",
    "sg:postcode":"3556",
    "sg:province":"VIC",
    "sg:tags":[
        "package",
        "software"
    ],
    "wof:name":"Regional Technology",
    "wof:placetype":"venue"
},
  "geometry": {"coordinates":[144.22215270999999,-36.7070770264],"type":"Point"}
}