{
  "type": "Feature",
  "properties": {
    "iso:country":"AU",
    "sg:address":"142 Kentucky St",
    "sg:city":"Armidale",
    "sg:classifiers":[
        {
            "category":"Commercial Area",
            "type":"Public Place"
        }
    ],
    "sg:phone":"+61 408 668 520",
    "sg:postcode":"2350",
    "sg:province":"NSW",
    "sg:tags":[
        "heavy",
        "carrier"
    ],
    "wof:name":"Forrester Ian Pty Ltd Super Service",
    "wof:placetype":"venue"
},
  "geometry": {"coordinates":[151.66716003400001,-30.5257053375],"type":"Point"}
}