{
  "type": "Feature",
  "properties": {
    "addr:full":"Unit 1 Chandlers Hill Shopping Centre 194 Chandlers Hill Rd Happy Valley SA 5159",
    "addr:housenumber":"194",
    "addr:postcode":"5159",
    "addr:street":"Chandlers Hill Rd",
    "iso:country":"AU",
    "sg:address":"Unit 1 Chandlers Hill Shopping Centre 194 Chandlers Hill Rd",
    "sg:city":"Happy Valley",
    "sg:classifiers":[
        {
            "category":"Health Services",
            "subcategory":"Health Practitioner",
            "type":"Services"
        }
    ],
    "sg:phone":"+61 8 8381 8777",
    "sg:postcode":"5159",
    "sg:province":"SA",
    "sg:tags":[
        "physiotherapist"
    ],
    "wof:name":"Anton Karatassas",
    "wof:placetype":"venue"
},
  "geometry": {"coordinates":[138.58744812,-35.0868606567],"type":"Point"}
}