{
  "type": "Feature",
  "properties": {
    "addr:full":"276 Russell St Melbourne VIC 3000",
    "addr:housenumber":"276",
    "addr:postcode":"3000",
    "addr:street":"Russell St",
    "iso:country":"AU",
    "sg:address":"276 Russell St",
    "sg:city":"Melbourne",
    "sg:classifiers":[
        {
            "category":"Sports & Exercise",
            "subcategory":"Gym",
            "type":"Entertainment"
        }
    ],
    "sg:phone":"+61 1300 556 654",
    "sg:postcode":"3000",
    "sg:province":"VIC",
    "sg:tags":[
        "personal",
        "trainer",
        "fitness"
    ],
    "wof:name":"Lifestyle Fitness",
    "wof:placetype":"venue"
},
  "geometry": {"coordinates":[144.96694946299999,-37.8098907471],"type":"Point"}
}