{
  "type": "Feature",
  "properties": {
    "addr:full":"57 division St Welshpool WA 6106",
    "addr:housenumber":"57",
    "addr:postcode":"6106",
    "addr:street":"Division St",
    "iso:country":"AU",
    "sg:address":"57 division St",
    "sg:city":"Welshpool",
    "sg:classifiers":[
        {
            "category":"Wholesale",
            "subcategory":"Machinery & Supplies",
            "type":"Manufacturing & Wholesale Goods"
        }
    ],
    "sg:phone":"+61 8 9258 8411",
    "sg:postcode":"6106",
    "sg:province":"WA",
    "sg:tags":[
        "equipment",
        "laboratory"
    ],
    "wof:name":"Scot Scientific Pty Ltd",
    "wof:placetype":"venue"
},
  "geometry": {"coordinates":[115.93466949499999,-31.9899616241],"type":"Point"}
}