{
  "type": "Feature",
  "properties": {
    "addr:full":"Koongarra Crt Magill SA 5072",
    "addr:postcode":"5072",
    "addr:street":"Koongarra Crt",
    "iso:country":"AU",
    "sg:address":"Koongarra Crt",
    "sg:city":"Magill",
    "sg:classifiers":[
        {
            "category":"Education",
            "subcategory":"Dance Studio",
            "type":"Public Place"
        }
    ],
    "sg:phone":"+61 8 8364 2419",
    "sg:postcode":"5072",
    "sg:province":"SA",
    "sg:tags":[
        "venue",
        "tuition"
    ],
    "wof:name":"Christina Sherwood Academy Of Dance",
    "wof:placetype":"venue"
},
  "geometry": {"coordinates":[138.68336486800001,-34.9049530029],"type":"Point"}
}