{
  "type": "Feature",
  "properties": {
    "addr:full":"253- 255 Oxford St Leederville WA 6007",
    "addr:housenumber":"255",
    "addr:postcode":"6007",
    "addr:street":"Oxford St",
    "iso:country":"AU",
    "sg:address":"253- 255 Oxford St",
    "sg:city":"Leederville",
    "sg:classifiers":[
        {
            "category":"Personal",
            "subcategory":"Day Spa",
            "type":"Services"
        }
    ],
    "sg:phone":"+61 8 9201 1088",
    "sg:postcode":"6007",
    "sg:province":"WA",
    "wof:name":"Blush Day Spa",
    "wof:placetype":"venue"
},
  "geometry": {"coordinates":[115.841072083,-31.9320602417],"type":"Point"}
}