{
  "type": "Feature",
  "properties": {
    "iso:country":"AU",
    "sg:address":"13- 15 Victoria St",
    "sg:city":"Gerringong",
    "sg:classifiers":[
        {
            "category":"Retail",
            "subcategory":"Auto Rental",
            "type":"Services"
        }
    ],
    "sg:phone":"+61 2 4233 1888",
    "sg:postcode":"2534",
    "sg:province":"NSW",
    "sg:tags":[
        "bus",
        "truck"
    ],
    "wof:name":"Rentquip",
    "wof:placetype":"venue"
},
  "geometry": {"coordinates":[150.81918335,-34.7447052002],"type":"Point"}
}