{
  "type": "Feature",
  "properties": {
    "iso:country":"AU",
    "sg:address":"15 Pidding Rd",
    "sg:city":"Ryde",
    "sg:classifiers":[
        {
            "category":"Utilities",
            "subcategory":"Refuse",
            "type":"Services"
        }
    ],
    "sg:phone":"+61 412 414 422",
    "sg:postcode":"2112",
    "sg:province":"NSW",
    "sg:tags":[
        "disposal",
        "reduction",
        "waste"
    ],
    "wof:name":"Aulco Pty Ltd",
    "wof:placetype":"venue"
},
  "geometry": {"coordinates":[151.12173461899999,-33.8132858276],"type":"Point"}
}