{
  "type": "Feature",
  "properties": {
    "iso:country":"AU",
    "sg:address":"Lot 2 Shellharbour Rd",
    "sg:city":"Port Kembla",
    "sg:classifiers":[
        {
            "category":"Bus Stop",
            "subcategory":"None",
            "type":"Transportation"
        }
    ],
    "sg:phone":"+61 2 4275 8888",
    "sg:postcode":"2505",
    "sg:province":"NSW",
    "sg:tags":[
        "galvanising",
        "tinning"
    ],
    "wof:name":"Industrial Galvanizers",
    "wof:placetype":"venue"
},
  "geometry": {"coordinates":[150.89305100000001,-34.486938],"type":"Point"}
}