{
  "type": "Feature",
  "properties": {
    "iso:country":"AU",
    "sg:address":"15 Richmond Ave",
    "sg:city":"Padstow",
    "sg:classifiers":[
        {
            "category":"Building & Trades",
            "subcategory":"Construction",
            "type":"Services"
        }
    ],
    "sg:phone":"+61 2 9773 9333",
    "sg:postcode":"2211",
    "sg:province":"NSW",
    "sg:tags":[
        "contractor"
    ],
    "wof:name":"Bevan D & A",
    "wof:placetype":"venue"
},
  "geometry": {"coordinates":[151.039444,-33.965771],"type":"Point"}
}