{
  "type": "Feature",
  "properties": {
    "addr:full":"298 New South Head Rd Double Bay NSW 2028",
    "addr:housenumber":"298",
    "addr:postcode":"2028",
    "addr:street":"New South Head Rd",
    "iso:country":"AU",
    "sg:address":"298 New South Head Rd",
    "sg:city":"Double Bay",
    "sg:classifiers":[
        {
            "category":"Health Services",
            "subcategory":"Doctor",
            "type":"Services"
        }
    ],
    "sg:phone":"+61 2 9328 1200",
    "sg:postcode":"2028",
    "sg:province":"NSW",
    "sg:tags":[
        "podiatrist"
    ],
    "sg:website":"http://www.sportslab.com.au",
    "wof:name":"Sports-Lab Podiatry",
    "wof:placetype":"venue"
},
  "geometry": {"coordinates":[151.24114990199999,-33.8782997131],"type":"Point"}
}