{
  "type": "Feature",
  "properties": {
    "addr:full":"69 Tiverton Drv Mulgrave VIC 3170",
    "addr:housenumber":"69",
    "addr:postcode":"3170",
    "addr:street":"Tiverton Drv",
    "iso:country":"AU",
    "sg:address":"69 Tiverton Drv",
    "sg:city":"Mulgrave",
    "sg:classifiers":[
        {
            "category":"Home & Garden",
            "subcategory":"Carpets & Floor Coverings",
            "type":"Retail Goods"
        }
    ],
    "sg:phone":"+61 408 059 734",
    "sg:postcode":"3170",
    "sg:province":"VIC",
    "sg:tags":[
        "tile",
        "wall",
        "layer"
    ],
    "wof:name":"Imperial Tiling",
    "wof:placetype":"venue"
},
  "geometry": {"coordinates":[145.181106567,-37.9273529053],"type":"Point"}
}