{
  "type": "Feature",
  "properties": {
    "addr:full":"8 Tyrone Pl Erskine Park NSW 2759",
    "addr:housenumber":"8",
    "addr:postcode":"2759",
    "addr:street":"Pl",
    "iso:country":"AU",
    "sg:address":"8 Tyrone Pl",
    "sg:city":"Erskine Park",
    "sg:classifiers":[
        {
            "category":"Manufacturing",
            "subcategory":"Metals",
            "type":"Manufacturing & Wholesale Goods"
        }
    ],
    "sg:phone":"+61 2 8887 2888",
    "sg:postcode":"2759",
    "sg:province":"NSW",
    "sg:tags":[
        "wholesaler",
        "aluminium",
        "mfrs"
    ],
    "wof:name":"Darley Aluminium Trading Pty Ltd",
    "wof:placetype":"venue"
},
  "geometry": {"coordinates":[150.80580139200001,-33.8040390015],"type":"Point"}
}