{
  "type": "Feature",
  "properties": {
    "addr:full":"Unit 1 / 15 Gibbs St Labrador QLD 4215",
    "addr:housenumber":"15",
    "addr:postcode":"4215",
    "addr:street":"Gibbs St",
    "iso:country":"AU",
    "sg:address":"Unit 1 / 15 Gibbs St",
    "sg:city":"Labrador",
    "sg:classifiers":[
        {
            "category":"Retail",
            "subcategory":"Auto Repair",
            "type":"Services"
        }
    ],
    "sg:phone":"+61 7 5528 9188",
    "sg:postcode":"4215",
    "sg:province":"QLD",
    "sg:tags":[
        "repairer",
        "motor",
        "engineer"
    ],
    "wof:name":"Ross Automotive Group",
    "wof:placetype":"venue"
},
  "geometry": {"coordinates":[153.411819458,-27.9736366272],"type":"Point"}
}