{
  "type": "Feature",
  "properties": {
    "addr:full":"18 Valentine Crs Valentine NSW 2280",
    "addr:housenumber":"18",
    "addr:postcode":"2280",
    "addr:street":"Valentine Crs",
    "iso:country":"AU",
    "sg:address":"18 Valentine Crs",
    "sg:city":"Valentine",
    "sg:classifiers":[
        {
            "category":"Banks & Credit Unions",
            "subcategory":"Investment Brokerage",
            "type":"Services"
        }
    ],
    "sg:phone":"+61 2 4946 7107",
    "sg:postcode":"2280",
    "sg:province":"NSW",
    "sg:tags":[
        "mechanical",
        "oil",
        "seal"
    ],
    "wof:name":"Eneco Pty Ltd",
    "wof:placetype":"venue"
},
  "geometry": {"coordinates":[151.644287109,-33.0118789673],"type":"Point"}
}