{
  "type": "Feature",
  "properties": {
    "iso:country":"AU",
    "sg:address":"5 School Rd",
    "sg:city":"Nowa Nowa",
    "sg:classifiers":[
        {
            "category":"Travel",
            "subcategory":"Travel Agent",
            "type":"Entertainment"
        }
    ],
    "sg:phone":"+61 3 5155 7423",
    "sg:postcode":"3887",
    "sg:province":"VIC",
    "sg:tags":[
        "tour",
        "holiday",
        "adventure"
    ],
    "wof:name":"Wild Won Adventure Caving Tours",
    "wof:placetype":"venue"
},
  "geometry": {"coordinates":[148.09475707999999,-37.7305488586],"type":"Point"}
}