{
  "type": "Feature",
  "properties": {
    "addr:full":"5/ 14 Brendan Drv Nerang QLD 4211",
    "addr:housenumber":"/ 14",
    "addr:postcode":"4211",
    "addr:street":"Brendan Drv",
    "iso:country":"AU",
    "sg:address":"5/ 14 Brendan Drv",
    "sg:city":"Nerang",
    "sg:classifiers":[
        {
            "category":"Retail",
            "subcategory":"Auto Repair",
            "type":"Services"
        }
    ],
    "sg:phone":"+61 7 5578 3483",
    "sg:postcode":"4211",
    "sg:province":"QLD",
    "sg:tags":[
        "repairer",
        "motor",
        "engineer"
    ],
    "wof:name":"Brendan Drive Motors",
    "wof:placetype":"venue"
},
  "geometry": {"coordinates":[153.34231567399999,-27.9982719421],"type":"Point"}
}