{
  "type": "Feature",
  "properties": {
    "addr:full":"1 Marly St Highgate Hill QLD 4101",
    "addr:housenumber":"1",
    "addr:postcode":"4101",
    "addr:street":"Marly St",
    "iso:country":"AU",
    "sg:address":"1 Marly St",
    "sg:city":"Highgate Hill",
    "sg:classifiers":[
        {
            "category":"Manufacturing",
            "subcategory":"Food",
            "type":"Manufacturing & Wholesale Goods"
        }
    ],
    "sg:phone":"+61 7 3844 0874",
    "sg:postcode":"4101",
    "sg:province":"QLD",
    "sg:tags":[
        "function",
        "catering"
    ],
    "wof:name":"Affairs With Food",
    "wof:placetype":"venue"
},
  "geometry": {"coordinates":[153.01524352999999,-27.482213974],"type":"Point"}
}