{
  "type": "Feature",
  "properties": {
    "addr:full":"55 Fulham Rd Pimlico QLD 4812",
    "addr:housenumber":"55",
    "addr:postcode":"4812",
    "addr:street":"Fulham Rd",
    "iso:country":"AU",
    "sg:address":"55 Fulham Rd",
    "sg:city":"Pimlico",
    "sg:classifiers":[
        {
            "category":"Professional",
            "subcategory":"Computer Services",
            "type":"Services"
        }
    ],
    "sg:phone":"+61 7 4775 6965",
    "sg:postcode":"4812",
    "sg:province":"QLD",
    "sg:tags":[
        "consultant",
        "system"
    ],
    "wof:name":"Evolution IT Pty Ltd",
    "wof:placetype":"venue"
},
  "geometry": {"coordinates":[146.78419500000001,-19.288853],"type":"Point"}
}