{
  "type": "Feature",
  "properties": {
    "addr:full":"67 McKell Ave Sunbury VIC 3429",
    "addr:housenumber":"67",
    "addr:postcode":"3429",
    "addr:street":"Mckell Ave",
    "iso:country":"AU",
    "sg:address":"67 McKell Ave",
    "sg:city":"Sunbury",
    "sg:classifiers":[
        {
            "category":"Utilities",
            "subcategory":"Cable",
            "type":"Services"
        }
    ],
    "sg:phone":"+61 1800 639 841",
    "sg:postcode":"3429",
    "sg:province":"VIC",
    "sg:tags":[
        "headset"
    ],
    "wof:name":"Telset Technologies",
    "wof:placetype":"venue"
},
  "geometry": {"coordinates":[144.724807739,-37.5718841553],"type":"Point"}
}