{
  "type": "Feature",
  "properties": {
    "addr:full":"80 Hawthorne St Roma QLD 4455",
    "addr:housenumber":"80",
    "addr:postcode":"4455",
    "addr:street":"Hawthorne St",
    "iso:country":"AU",
    "sg:address":"80 Hawthorne St",
    "sg:city":"Roma",
    "sg:classifiers":[
        {
            "category":"Industrial Area",
            "type":"Public Place"
        }
    ],
    "sg:phone":"+61 7 4622 2065",
    "sg:postcode":"4455",
    "sg:province":"QLD",
    "sg:tags":[
        "rural",
        "shed"
    ],
    "wof:name":"Ken Sallur",
    "wof:placetype":"venue"
},
  "geometry": {"coordinates":[148.787277222,-26.5790367126],"type":"Point"}
}