{
  "type": "Feature",
  "properties": {
    "iso:country":"AU",
    "sg:address":"Office 2, 163 Aukland St",
    "sg:city":"Bega",
    "sg:classifiers":[
        {
            "category":"Communications",
            "subcategory":"News Services",
            "type":"Services"
        }
    ],
    "sg:phone":"+61 1800 672 009",
    "sg:postcode":"2550",
    "sg:province":"NSW",
    "sg:tags":[
        "information",
        "tourist",
        "attractions"
    ],
    "wof:name":"South Coast Regional Tourism Organisation Incorp",
    "wof:placetype":"venue"
},
  "geometry": {"coordinates":[149.69696044899999,-36.7635612488],"type":"Point"}
}