{
  "type": "Feature",
  "properties": {
    "iso:country":"AU",
    "sg:address":"167 Grey St",
    "sg:city":"Glen Innes",
    "sg:classifiers":[
        {
            "category":"Retail",
            "subcategory":"Auto Repair",
            "type":"Services"
        }
    ],
    "sg:phone":"+61 2 6732 2888",
    "sg:postcode":"2370",
    "sg:province":"NSW",
    "sg:tags":[
        "repairer",
        "motor",
        "engineer"
    ],
    "wof:name":"Holden",
    "wof:placetype":"venue"
},
  "geometry": {"coordinates":[151.736083984,-29.736371994],"type":"Point"}
}