{
  "type": "Feature",
  "properties": {
    "addr:full":"Mt Berriman Rd Laidley QLD 4341",
    "addr:postcode":"4341",
    "addr:street":"Berriman Rd",
    "iso:country":"AU",
    "sg:address":"Mt Berriman Rd",
    "sg:city":"Laidley",
    "sg:classifiers":[
        {
            "category":"Farming",
            "subcategory":"Livestock Farm",
            "type":"Manufacturing & Wholesale Goods"
        }
    ],
    "sg:phone":"+61 7 5466 4240",
    "sg:postcode":"4341",
    "sg:province":"QLD",
    "sg:tags":[
        "breeder",
        "horse",
        "stud"
    ],
    "wof:name":"Jaybee Farm Stud & Equestrian Centre",
    "wof:placetype":"venue"
},
  "geometry": {"coordinates":[152.32716369600001,-27.6531391144],"type":"Point"}
}