{
  "type": "Feature",
  "properties": {
    "addr:full":"4/ 80 Grand Blv Joondalup WA 6027",
    "addr:housenumber":"/ 80",
    "addr:postcode":"6027",
    "addr:street":"Grand Blv",
    "iso:country":"AU",
    "sg:address":"4/ 80",
    "sg:city":"Grand Blv Joondalup",
    "sg:classifiers":[
        {
            "category":"Real Estate",
            "subcategory":"Real Estate Agent",
            "type":"Services"
        }
    ],
    "sg:phone":"+61 8 9300 2283",
    "sg:postcode":"6027",
    "sg:province":"WA",
    "wof:name":"L.J. Hooker Joondalup",
    "wof:placetype":"venue"
},
  "geometry": {"coordinates":[115.767501831,-31.7523231506],"type":"Point"}
}