{
  "type": "Feature",
  "properties": {
    "addr:full":"Saunders St Wynyard TAS 7325",
    "addr:postcode":"7325",
    "addr:street":"Saunders St",
    "iso:country":"AU",
    "sg:address":"Saunders St",
    "sg:city":"Wynyard",
    "sg:classifiers":[
        {
            "category":"Professional",
            "subcategory":"Employment Agencies",
            "type":"Services"
        }
    ],
    "sg:phone":"+61 3 6442 4499",
    "sg:postcode":"7325",
    "sg:province":"TAS",
    "sg:tags":[
        "provider",
        "internet"
    ],
    "wof:name":"Online Access Centres",
    "wof:placetype":"venue"
},
  "geometry": {"coordinates":[145.725281,-40.989128],"type":"Point"}
}