{
  "type": "Feature",
  "properties": {
    "addr:full":"83 York St Sydney NSW 2000",
    "addr:housenumber":"83",
    "addr:postcode":"2000",
    "addr:street":"York St",
    "iso:country":"AU",
    "sg:address":"83 York St",
    "sg:city":"Sydney",
    "sg:classifiers":[
        {
            "category":"Sports & Exercise",
            "subcategory":"Ski Slope",
            "type":"Entertainment"
        }
    ],
    "sg:phone":"+61 2 9262 3398",
    "sg:postcode":"2000",
    "sg:province":"NSW",
    "sg:tags":[
        "equipment",
        "hire",
        "retail",
        "snow"
    ],
    "sg:website":"http://www.paulreader.com.au",
    "wof:name":"Paul Reader Snow & Mountain Sports",
    "wof:placetype":"venue"
},
  "geometry": {"coordinates":[151.20594787600001,-33.8691291809],"type":"Point"}
}