{
  "type": "Feature",
  "properties": {
    "addr:full":"6- 8 Harris St Condell Park NSW 2200",
    "addr:housenumber":"8",
    "addr:postcode":"2200",
    "addr:street":"Harris St",
    "iso:country":"AU",
    "sg:address":"6- 8 Harris St",
    "sg:city":"Condell Park",
    "sg:classifiers":[
        {
            "category":"Retail",
            "subcategory":"Auto Repair",
            "type":"Services"
        }
    ],
    "sg:phone":"+61 2 9792 3688",
    "sg:postcode":"2200",
    "sg:province":"NSW",
    "sg:tags":[
        "beater",
        "painter",
        "panel"
    ],
    "wof:name":"Padstow Smash & Mechanical Services",
    "wof:placetype":"venue"
},
  "geometry": {"coordinates":[151.01391599999999,-33.9319],"type":"Point"}
}