{
  "type": "Feature",
  "properties": {
    "addr:full":"18 Collie St Fyshwick ACT 2609",
    "addr:housenumber":"18",
    "addr:postcode":"2609",
    "addr:street":"Collie St",
    "iso:country":"AU",
    "sg:address":"18 Collie St",
    "sg:city":"Fyshwick",
    "sg:classifiers":[
        {
            "category":"Building & Trades",
            "subcategory":"Construction",
            "type":"Services"
        }
    ],
    "sg:phone":"+61 402 923 361",
    "sg:postcode":"2609",
    "sg:province":"ACT",
    "sg:tags":[
        "joinery"
    ],
    "wof:name":"Platinum",
    "wof:placetype":"venue"
},
  "geometry": {"coordinates":[149.180175781,-35.3269233704],"type":"Point"}
}