{
  "type": "Feature",
  "properties": {
    "iso:country":"AU",
    "sg:address":"PO Box 2305",
    "sg:city":"Toowong",
    "sg:classifiers":[
        {
            "category":"Professional",
            "subcategory":"Art Services",
            "type":"Services"
        }
    ],
    "sg:phone":"+61 7 3871 1459",
    "sg:postcode":"4066",
    "sg:province":"QLD",
    "sg:tags":[
        "interior",
        "decorator"
    ],
    "wof:name":"Jacqueline's Interiors",
    "wof:placetype":"venue"
},
  "geometry": {"coordinates":[152.98562622099999,-27.4785194397],"type":"Point"}
}