{
  "type": "Feature",
  "properties": {
    "addr:full":"379 Princes Hwy St Peters NSW 2044",
    "addr:housenumber":"379",
    "addr:postcode":"2044",
    "addr:street":"Princes Hwy",
    "iso:country":"AU",
    "sg:address":"379 Princes Hwy",
    "sg:city":"St Peters",
    "sg:classifiers":[
        {
            "category":"Retail",
            "subcategory":"Car Wash",
            "type":"Services"
        }
    ],
    "sg:phone":"+61 2 9557 1007",
    "sg:postcode":"2044",
    "sg:province":"NSW",
    "sg:tags":[
        "truck",
        "cleaning"
    ],
    "wof:name":"Citiwash Hand Carwash Cafe",
    "wof:placetype":"venue"
},
  "geometry": {"coordinates":[151.17147800000001,-33.917389],"type":"Point"}
}