{
  "type": "Feature",
  "properties": {
    "addr:full":"2 Thomas St Laidley QLD 4341",
    "addr:housenumber":"2",
    "addr:postcode":"4341",
    "addr:street":"Thomas St",
    "iso:country":"AU",
    "sg:address":"2 Thomas St",
    "sg:city":"Laidley",
    "sg:classifiers":[
        {
            "category":"Building & Trades",
            "subcategory":"Plumbing",
            "type":"Services"
        }
    ],
    "sg:phone":"+61 7 5465 1538",
    "sg:postcode":"4341",
    "sg:province":"QLD",
    "sg:tags":[
        "plumber",
        "gasfitters"
    ],
    "wof:name":"Lee & Sons",
    "wof:placetype":"venue"
},
  "geometry": {"coordinates":[152.39859008799999,-27.6337661743],"type":"Point"}
}