{
  "type": "Feature",
  "properties": {
    "addr:full":"1 Simes St Barmera SA 5345",
    "addr:housenumber":"1",
    "addr:postcode":"5345",
    "addr:street":"Simes St",
    "iso:country":"AU",
    "sg:address":"1 Simes St",
    "sg:city":"Barmera",
    "sg:classifiers":[
        {
            "category":"Retail",
            "subcategory":"Auto Repair",
            "type":"Services"
        }
    ],
    "sg:phone":"+61 8 8588 2522",
    "sg:postcode":"5345",
    "sg:province":"SA",
    "sg:tags":[
        "repairer",
        "motor",
        "engineer"
    ],
    "wof:name":"Riverland Auto Repairs",
    "wof:placetype":"venue"
},
  "geometry": {"coordinates":[140.46612548799999,-34.2564086914],"type":"Point"}
}