{
  "type": "Feature",
  "properties": {
    "addr:full":"Export Drv Darwin Business Park Berrimah NT 0828",
    "addr:postcode":"nt 0828",
    "addr:street":"Export Drv Darwin Business",
    "iso:country":"AU",
    "sg:address":"Export Drv",
    "sg:city":"Darwin Business Park Berrimah",
    "sg:classifiers":[
        {
            "category":"Wholesale",
            "subcategory":"Electrical",
            "type":"Manufacturing & Wholesale Goods"
        }
    ],
    "sg:phone":"+61 8 8947 2141",
    "sg:postcode":"0828",
    "sg:province":"NT",
    "sg:tags":[
        "control",
        "equipment",
        "switch"
    ],
    "wof:name":"Rowanco Switchboards Pty Ltd",
    "wof:placetype":"venue"
},
  "geometry": {"coordinates":[130.92274475100001,-12.4695053101],"type":"Point"}
}