{
  "type": "Feature",
  "properties": {
    "addr:full":"Karratha Village (Medical Centre) Suite 28/ 2608 Sharpe Ave Karratha WA 6714",
    "addr:housenumber":"28 / 2608",
    "addr:postcode":"6714",
    "addr:street":"Sharpe Ave",
    "iso:country":"AU",
    "sg:address":"Karratha Village (Medical Centre) Suite 28/ 2608 Sharpe Ave",
    "sg:city":"Karratha",
    "sg:classifiers":[
        {
            "category":"Health Services",
            "subcategory":"Dentist",
            "type":"Services"
        }
    ],
    "sg:phone":"+61 8 9144 1470",
    "sg:postcode":"6714",
    "sg:province":"WA",
    "wof:name":"Nickol Bay Dental Clinic",
    "wof:placetype":"venue"
},
  "geometry": {"coordinates":[116.84449768099999,-20.7355613708],"type":"Point"}
}