{
  "type": "Feature",
  "properties": {
    "iso:country":"AU",
    "sg:address":"29 Rishon Ave",
    "sg:city":"Blackburn South",
    "sg:classifiers":[
        {
            "category":"Building & Trades",
            "subcategory":"Construction",
            "type":"Services"
        }
    ],
    "sg:phone":"+61 419 538 145",
    "sg:postcode":"3130",
    "sg:province":"VIC",
    "sg:tags":[
        "renovation",
        "alterations",
        "extension",
        "contractor"
    ],
    "wof:name":"Tarra Constructions Pty Ltd",
    "wof:placetype":"venue"
},
  "geometry": {"coordinates":[145.151290894,-37.8451347351],"type":"Point"}
}