{
  "type": "Feature",
  "properties": {
    "iso:country":"AU",
    "sg:address":"175 Hawkesbury Rd",
    "sg:city":"Westmead",
    "sg:classifiers":[
        {
            "category":"Travel",
            "subcategory":"Hotels & Motels",
            "type":"Entertainment"
        }
    ],
    "sg:phone":"+61 2 9635 1233",
    "sg:postcode":"2145",
    "sg:province":"NSW",
    "sg:website":"http://www.wesleylodge.com.au",
    "wof:name":"Best Western Wesley Lodge",
    "wof:placetype":"venue"
},
  "geometry": {"coordinates":[150.98968505900001,-33.8053703308],"type":"Point"}
}