{
  "type": "Feature",
  "properties": {
    "iso:country":"AU",
    "sg:address":"Shop 3/ 3A Takalvan St",
    "sg:city":"Bundaberg",
    "sg:classifiers":[
        {
            "category":"Banks & Credit Unions",
            "subcategory":"Investment Brokerage",
            "type":"Services"
        }
    ],
    "sg:phone":"+61 7 4151 7400",
    "sg:postcode":"4670",
    "sg:province":"QLD",
    "sg:tags":[
        "management",
        "property"
    ],
    "wof:name":"Professional Property Services (Bundaberg) Pty Ltd",
    "wof:placetype":"venue"
},
  "geometry": {"coordinates":[152.33479309099999,-24.8714160919],"type":"Point"}
}