{
  "type": "Feature",
  "properties": {
    "addr:full":"712 Creek Rd Mt Gravatt QLD 4122",
    "addr:housenumber":"712",
    "addr:postcode":"4122",
    "addr:street":"Creek Rd",
    "iso:country":"AU",
    "sg:address":"712 Creek Rd",
    "sg:city":"Mt Gravatt",
    "sg:classifiers":[
        {
            "category":"Travel",
            "subcategory":"Hostel",
            "type":"Entertainment"
        }
    ],
    "sg:phone":"+61 7 3343 2277",
    "sg:postcode":"4122",
    "sg:province":"QLD",
    "sg:tags":[
        "home"
    ],
    "wof:name":"Green Meadow Court",
    "wof:placetype":"venue"
},
  "geometry": {"coordinates":[153.096755981,-27.5192203522],"type":"Point"}
}