{
  "type": "Feature",
  "properties": {
    "addr:full":"Shop 9B Phillip Mall Kendall St West Pymble NSW 2073",
    "addr:housenumber":"shop 9b",
    "addr:postcode":"2073",
    "addr:street":"Phillip Mall Kendall St",
    "iso:country":"AU",
    "sg:address":"Shop 9B Phillip Mall Kendall St",
    "sg:city":"West Pymble",
    "sg:classifiers":[
        {
            "category":"Health Services",
            "subcategory":"Health Practitioner",
            "type":"Services"
        }
    ],
    "sg:phone":"+61 2 9418 2926",
    "sg:postcode":"2073",
    "sg:province":"NSW",
    "sg:tags":[
        "physiotherapist"
    ],
    "wof:name":"McKenna Christopher",
    "wof:placetype":"venue"
},
  "geometry": {"coordinates":[151.13059997600001,-33.7608108521],"type":"Point"}
}