{
  "type": "Feature",
  "properties": {
    "addr:full":"Suite 1, 65 Palmer St South Townsville QLD 4810",
    "addr:housenumber":"65",
    "addr:postcode":"4810",
    "addr:street":"Palmer St",
    "iso:country":"AU",
    "sg:address":"Suite 1, 65 Palmer St",
    "sg:city":"South Townsville",
    "sg:classifiers":[
        {
            "category":"Organizations",
            "subcategory":"Non-profit Organization",
            "type":"Services"
        }
    ],
    "sg:phone":"+61 7 4721 4322",
    "sg:postcode":"4810",
    "sg:province":"QLD",
    "sg:tags":[
        "environmental",
        "organisation",
        "conservation"
    ],
    "wof:name":"Townsville Thuringowa Landcare Association",
    "wof:placetype":"venue"
},
  "geometry": {"coordinates":[146.82441700000001,-19.259378],"type":"Point"}
}