{
  "type": "Feature",
  "properties": {
    "addr:full":"U 9/ 398 Marion St Bankstown NSW 2200",
    "addr:housenumber":"/ 398",
    "addr:postcode":"2200",
    "addr:street":"Marion St",
    "iso:country":"AU",
    "sg:address":"U 9/ 398 Marion St",
    "sg:city":"Bankstown",
    "sg:classifiers":[
        {
            "category":"Shopping",
            "subcategory":"Mobile Phones",
            "type":"Retail Goods"
        }
    ],
    "sg:phone":"+61 2 9791 0563",
    "sg:postcode":"2200",
    "sg:province":"NSW",
    "sg:tags":[
        "wholesaler",
        "mfrs",
        "electrical",
        "switchboard"
    ],
    "wof:name":"Echo Metal Products Pty Ltd",
    "wof:placetype":"venue"
},
  "geometry": {"coordinates":[151.00176999999999,-33.916405],"type":"Point"}
}