{
  "type": "Feature",
  "properties": {
    "iso:country":"AU",
    "sg:address":"744 Waverley Rd",
    "sg:city":"Chadstone",
    "sg:classifiers":[
        {
            "category":"Education",
            "subcategory":"School",
            "type":"Public Place"
        }
    ],
    "sg:phone":"+61 3 9568 8181",
    "sg:postcode":"3148",
    "sg:province":"VIC",
    "sg:tags":[
        "teaching",
        "aid"
    ],
    "wof:name":"The Parent Teacher Shop",
    "wof:placetype":"venue"
},
  "geometry": {"coordinates":[145.09002685600001,-37.8799552917],"type":"Point"}
}