{
  "type": "Feature",
  "properties": {
    "addr:full":"63 Eucalyptus Rd Eltham VIC 3095",
    "addr:housenumber":"63",
    "addr:postcode":"3095",
    "addr:street":"Eucalyptus Rd",
    "iso:country":"AU",
    "sg:address":"63 Eucalyptus Rd",
    "sg:city":"Eltham",
    "sg:classifiers":[
        {
            "category":"Education",
            "subcategory":"Special Training",
            "type":"Public Place"
        }
    ],
    "sg:phone":"+61 3 9439 1503",
    "sg:postcode":"3095",
    "sg:province":"VIC",
    "sg:tags":[
        "drama",
        "tuition"
    ],
    "wof:name":"Helen O&#039;Grady Childrens Drama Academy",
    "wof:placetype":"venue"
},
  "geometry": {"coordinates":[145.16545105,-37.7141456604],"type":"Point"}
}