{
  "type": "Feature",
  "properties": {
    "addr:full":"27 Goode Rd Port Pirie West SA 5540",
    "addr:housenumber":"27",
    "addr:postcode":"5540",
    "addr:street":"Goode Rd",
    "iso:country":"AU",
    "sg:address":"27 Goode Rd",
    "sg:city":"Port Pirie West",
    "sg:classifiers":[
        {
            "category":"Fast Food",
            "type":"Food & Drink"
        }
    ],
    "sg:phone":"+61 8 8632 4142",
    "sg:postcode":"5540",
    "sg:province":"SA",
    "sg:tags":[
        "away",
        "take"
    ],
    "wof:name":"Goode Road Deli & Takeaway",
    "wof:placetype":"venue"
},
  "geometry": {"coordinates":[138.00115966800001,-33.1814117432],"type":"Point"}
}