{
  "type": "Feature",
  "properties": {
    "addr:full":"Nowra Rd Fitzroy Falls NSW 2577",
    "addr:postcode":"2577",
    "addr:street":"Nowra Rd",
    "iso:country":"AU",
    "sg:address":"Nowra Rd",
    "sg:city":"Fitzroy Falls",
    "sg:classifiers":[
        {
            "category":"Communications",
            "subcategory":"News Services",
            "type":"Services"
        }
    ],
    "sg:phone":"+61 2 4887 7270",
    "sg:postcode":"2577",
    "sg:province":"NSW",
    "sg:tags":[
        "information",
        "tourist",
        "attractions"
    ],
    "wof:name":"National Parks & Wildlife Service",
    "wof:placetype":"venue"
},
  "geometry": {"coordinates":[150.47999572800001,-34.6450538635],"type":"Point"}
}