{
  "type": "Feature",
  "properties": {
    "iso:country":"AU",
    "sg:address":"260 Sirl Rd",
    "sg:city":"Woodford",
    "sg:classifiers":[
        {
            "category":"Retail",
            "subcategory":"Laundry & Dry Cleaning",
            "type":"Services"
        }
    ],
    "sg:phone":"+61 7 5496 1840",
    "sg:postcode":"4514",
    "sg:province":"QLD",
    "sg:tags":[
        "breeder",
        "alpaca",
        "llama"
    ],
    "wof:name":"Durundur Alpaca Stud",
    "wof:placetype":"venue"
},
  "geometry": {"coordinates":[152.718384,-26.945456],"type":"Point"}
}