{
  "type": "Feature",
  "properties": {
    "addr:full":"96 Cunningham St Dalby QLD 4405",
    "addr:housenumber":"96",
    "addr:postcode":"4405",
    "addr:street":"Cunningham St",
    "iso:country":"AU",
    "sg:address":"96 Cunningham St",
    "sg:city":"Dalby",
    "sg:classifiers":[
        {
            "category":"Professional",
            "subcategory":"Accounting & Tax Preparation",
            "type":"Services"
        }
    ],
    "sg:phone":"+61 7 4662 4855",
    "sg:postcode":"4405",
    "sg:province":"QLD",
    "sg:tags":[
        "consultant",
        "taxation"
    ],
    "wof:name":"Maipbas",
    "wof:placetype":"venue"
},
  "geometry": {"coordinates":[151.264602661,-27.1824417114],"type":"Point"}
}