{
  "type": "Feature",
  "properties": {
    "addr:full":"90 Maxwell Rd Fingal VIC 3939",
    "addr:housenumber":"90",
    "addr:postcode":"3939",
    "addr:street":"Maxwell Rd",
    "iso:country":"AU",
    "sg:address":"90 Maxwell Rd",
    "sg:city":"Fingal",
    "sg:classifiers":[
        {
            "category":"Education",
            "subcategory":"School",
            "type":"Public Place"
        }
    ],
    "sg:phone":"+61 3 5988 5347",
    "sg:postcode":"3939",
    "sg:province":"VIC",
    "sg:tags":[
        "teaching",
        "aid"
    ],
    "wof:name":"Teewah Time",
    "wof:placetype":"venue"
},
  "geometry": {"coordinates":[144.88607788100001,-38.4202041626],"type":"Point"}
}