{
  "type": "Feature",
  "properties": {
    "addr:full":"Level 3, 480 Collins St Melbourne VIC 3000",
    "addr:housenumber":"480",
    "addr:postcode":"3000",
    "addr:street":"Collins St",
    "iso:country":"AU",
    "sg:address":"Level 3, 480 Collins St",
    "sg:city":"Melbourne",
    "sg:classifiers":[
        {
            "category":"Banks & Credit Unions",
            "subcategory":"Investment Brokerage",
            "type":"Services"
        }
    ],
    "sg:phone":"+61 1300 368 939",
    "sg:postcode":"3000",
    "sg:province":"VIC",
    "sg:tags":[
        "share",
        "broker",
        "stock"
    ],
    "wof:name":"OneTrade Stockbroking Pty Ltd",
    "wof:placetype":"venue"
},
  "geometry": {"coordinates":[144.95797729500001,-37.8178253174],"type":"Point"}
}