{
  "type": "Feature",
  "properties": {
    "addr:full":"126 Reesville Rd Maleny QLD 4552",
    "addr:housenumber":"126",
    "addr:postcode":"4552",
    "addr:street":"Reesville Rd",
    "iso:country":"AU",
    "sg:address":"126 Reesville Rd",
    "sg:city":"Maleny",
    "sg:classifiers":[
        {
            "category":"Building & Trades",
            "subcategory":"Construction",
            "type":"Services"
        }
    ],
    "sg:phone":"+61 7 5499 9066",
    "sg:postcode":"4552",
    "sg:province":"QLD",
    "sg:tags":[
        "fencing",
        "contractor"
    ],
    "wof:name":"Lanhams Rural Fencing",
    "wof:placetype":"venue"
},
  "geometry": {"coordinates":[152.81736755399999,-26.7585544586],"type":"Point"}
}