{
  "type": "Feature",
  "properties": {
    "addr:full":"UA5/ 15 Narabang Way Belrose NSW 2085",
    "addr:postcode":"2085",
    "addr:street":"Narabang Way",
    "iso:country":"AU",
    "sg:address":"UA5/ 15",
    "sg:city":"Narabang Way Belrose",
    "sg:classifiers":[
        {
            "category":"Building & Trades",
            "subcategory":"Plumbing",
            "type":"Services"
        }
    ],
    "sg:phone":"+61 2 9986 1234",
    "sg:postcode":"2085",
    "sg:province":"NSW",
    "sg:tags":[
        "plumber",
        "gasfitters"
    ],
    "wof:name":"Terrey Hills Plumbing",
    "wof:placetype":"venue"
},
  "geometry": {"coordinates":[151.212432861,-33.7053451538],"type":"Point"}
}