{
  "type": "Feature",
  "properties": {
    "addr:full":"Shp 33/ 695 Punchbowl Rd Punchbowl NSW 2196",
    "addr:housenumber":"33 / 695",
    "addr:postcode":"2196",
    "addr:street":"Punchbowl Rd",
    "iso:country":"AU",
    "sg:address":"Shp 33/ 695 Punchbowl Rd",
    "sg:city":"Punchbowl",
    "sg:classifiers":[
        {
            "category":"Health Services",
            "subcategory":"Optometrist",
            "type":"Services"
        }
    ],
    "sg:phone":"+61 2 9750 0443",
    "sg:postcode":"2196",
    "sg:province":"NSW",
    "wof:name":"Central Eyecare",
    "wof:placetype":"venue"
},
  "geometry": {"coordinates":[151.055969,-33.924606],"type":"Point"}
}