{
  "type": "Feature",
  "properties": {
    "addr:full":"65 Holmes Rd Moonee Ponds VIC 3039",
    "addr:housenumber":"65",
    "addr:postcode":"3039",
    "addr:street":"Holmes Rd",
    "iso:country":"AU",
    "sg:address":"65 Holmes Rd",
    "sg:city":"Moonee Ponds",
    "sg:classifiers":[
        {
            "category":"Health Services",
            "subcategory":"Doctor",
            "type":"Services"
        }
    ],
    "sg:phone":"+61 3 9370 3904",
    "sg:postcode":"3039",
    "sg:province":"VIC",
    "sg:tags":[
        "medical",
        "practitioner"
    ],
    "wof:name":"Drentin Joseph Dr",
    "wof:placetype":"venue"
},
  "geometry": {"coordinates":[144.91546600000001,-37.766273],"type":"Point"}
}