{
  "type": "Feature",
  "properties": {
    "addr:full":"40 Ridgeway St The Gap QLD 4061",
    "addr:housenumber":"40",
    "addr:postcode":"4061",
    "addr:street":"Ridgeway St",
    "iso:country":"AU",
    "sg:address":"40 Ridgeway St",
    "sg:city":"The Gap",
    "sg:classifiers":[
        {
            "category":"Professional",
            "subcategory":"Engineering",
            "type":"Services"
        }
    ],
    "sg:phone":"+61 7 3300 3564",
    "sg:postcode":"4061",
    "sg:province":"QLD",
    "sg:tags":[
        "consulting",
        "engineer"
    ],
    "wof:name":"Bleakly C J",
    "wof:placetype":"venue"
},
  "geometry": {"coordinates":[152.94944763199999,-27.4561576843],"type":"Point"}
}