{
  "type": "Feature",
  "properties": {
    "addr:full":"152 Brisbane Rd Booval QLD 4304",
    "addr:housenumber":"152",
    "addr:postcode":"4304",
    "addr:street":"Brisbane Rd",
    "iso:country":"AU",
    "sg:address":"152 Brisbane Rd",
    "sg:city":"Booval",
    "sg:classifiers":[
        {
            "category":"Real Estate",
            "subcategory":"Real Estate Agent",
            "type":"Services"
        }
    ],
    "sg:phone":"+61 7 3816 2088",
    "sg:postcode":"4304",
    "sg:province":"QLD",
    "wof:name":"Realogy Property Agents",
    "wof:placetype":"venue"
},
  "geometry": {"coordinates":[152.79029846200001,-27.6138248444],"type":"Point"}
}