{
  "type": "Feature",
  "properties": {
    "iso:country":"AU",
    "sg:address":"97a Argus St",
    "sg:city":"Cheltenham",
    "sg:classifiers":[
        {
            "category":"Wholesale",
            "subcategory":"Stationery",
            "type":"Manufacturing & Wholesale Goods"
        }
    ],
    "sg:phone":"+61 3 9583 0935",
    "sg:postcode":"3192",
    "sg:province":"VIC",
    "sg:tags":[
        "mfrg"
    ],
    "wof:name":"Atsco Australia Pty Ltd",
    "wof:placetype":"venue"
},
  "geometry": {"coordinates":[145.074615478,-37.9600372314],"type":"Point"}
}