{
  "type": "Feature",
  "properties": {
    "addr:full":"68 Beaudesert Rd Moorooka QLD 4105",
    "addr:housenumber":"68",
    "addr:postcode":"4105",
    "addr:street":"Beaudesert Rd",
    "iso:country":"AU",
    "sg:address":"68 Beaudesert Rd",
    "sg:city":"Moorooka",
    "sg:classifiers":[
        {
            "category":"Shopping",
            "subcategory":"Clothing, Apparel, & Fashions",
            "type":"Retail Goods"
        }
    ],
    "sg:phone":"+61 7 3392 9390",
    "sg:postcode":"4105",
    "sg:province":"QLD",
    "sg:tags":[
        "recycled",
        "clothing"
    ],
    "wof:name":"RSPCA - Moorooka Bargain Barn",
    "wof:placetype":"venue"
},
  "geometry": {"coordinates":[153.023269653,-27.5279998779],"type":"Point"}
}