{
  "type": "Feature",
  "properties": {
    "addr:full":"Cnr North & King Sts Oberon NSW 2787",
    "addr:postcode":"2787",
    "addr:street":"Cnr",
    "iso:country":"AU",
    "sg:address":"Cnr North & King Sts",
    "sg:city":"Oberon",
    "sg:classifiers":[
        {
            "category":"Education",
            "subcategory":"Kindergarten",
            "type":"Public Place"
        }
    ],
    "sg:phone":"+61 2 6336 1310",
    "sg:postcode":"2787",
    "sg:province":"NSW",
    "sg:tags":[
        "pre-schools"
    ],
    "wof:name":"Oberon Childrens Centre Incorporated",
    "wof:placetype":"venue"
},
  "geometry": {"coordinates":[149.87123107900001,-33.7060317993],"type":"Point"}
}