{
  "type": "Feature",
  "properties": {
    "addr:full":"89 Rammond St Sale VIC 3850",
    "addr:housenumber":"89",
    "addr:postcode":"3850",
    "addr:street":"Rammond St",
    "iso:country":"AU",
    "sg:address":"89 Rammond St",
    "sg:city":"Sale",
    "sg:classifiers":[
        {
            "category":"Home & Garden",
            "subcategory":"Carpets & Floor Coverings",
            "type":"Retail Goods"
        }
    ],
    "sg:phone":"+61 402 120 670",
    "sg:postcode":"3850",
    "sg:province":"VIC",
    "wof:name":"Lazzaro Floor & Wall",
    "wof:placetype":"venue"
},
  "geometry": {"coordinates":[147.06562805199999,-38.1112861633],"type":"Point"}
}