{
  "type": "Feature",
  "properties": {
    "addr:full":"200 Gravelly Beach Rd Gravelly Beach TAS 7276",
    "addr:housenumber":"200",
    "addr:postcode":"7276",
    "addr:street":"Gravelly Beach Rd",
    "iso:country":"AU",
    "sg:address":"200 Gravelly Beach Rd",
    "sg:city":"Gravelly Beach",
    "sg:classifiers":[
        {
            "category":"Building & Trades",
            "subcategory":"Construction",
            "type":"Services"
        }
    ],
    "sg:phone":"+61 3 6394 4271",
    "sg:postcode":"7276",
    "sg:province":"TAS",
    "sg:tags":[
        "mooring",
        "contractor"
    ],
    "wof:name":"Gravelly Beach Marine",
    "wof:placetype":"venue"
},
  "geometry": {"coordinates":[146.96879577600001,-41.2948875427],"type":"Point"}
}