{
  "type": "Feature",
  "properties": {
    "addr:full":"182 Star St Carlisle WA 6101",
    "addr:housenumber":"182",
    "addr:postcode":"6101",
    "addr:street":"Star St",
    "iso:country":"AU",
    "sg:address":"182 Star St",
    "sg:city":"Carlisle",
    "sg:classifiers":[
        {
            "category":"Retail",
            "subcategory":"Laundry & Dry Cleaning",
            "type":"Services"
        }
    ],
    "sg:phone":"+61 8 9361 6555",
    "sg:postcode":"6101",
    "sg:province":"WA",
    "sg:tags":[
        "machine",
        "commercial",
        "industrial",
        "washing"
    ],
    "wof:name":"Veeco",
    "wof:placetype":"venue"
},
  "geometry": {"coordinates":[115.921630859,-31.9807186127],"type":"Point"}
}