{
  "type": "Feature",
  "properties": {
    "addr:full":"159 Oakmont Ave Meadow Springs WA 6210",
    "addr:housenumber":"159",
    "addr:postcode":"6210",
    "addr:street":"Oakmont Ave",
    "iso:country":"AU",
    "sg:address":"159 Oakmont Ave",
    "sg:city":"Meadow Springs",
    "sg:classifiers":[
        {
            "category":"Personal",
            "subcategory":"Beauty Salon",
            "type":"Services"
        }
    ],
    "sg:phone":"+61 8 9581 8757",
    "sg:postcode":"6210",
    "sg:province":"WA",
    "sg:tags":[
        "hairdresser"
    ],
    "wof:name":"Anita Bailey",
    "wof:placetype":"venue"
},
  "geometry": {"coordinates":[115.743622,-32.508568],"type":"Point"}
}