{
  "type": "Feature",
  "properties": {
    "addr:full":"17 Talgai St Bracken Ridge QLD 4017",
    "addr:housenumber":"17",
    "addr:postcode":"4017",
    "addr:street":"Talgai St",
    "iso:country":"AU",
    "sg:address":"17 Talgai St",
    "sg:city":"Bracken Ridge",
    "sg:classifiers":[
        {
            "category":"Building & Trades",
            "subcategory":"Pest Control",
            "type":"Services"
        }
    ],
    "sg:phone":"+61 7 3269 1969",
    "sg:postcode":"4017",
    "sg:province":"QLD",
    "wof:name":"Bracken Ridge Pest Control",
    "wof:placetype":"venue"
},
  "geometry": {"coordinates":[153.04142761200001,-27.3267860413],"type":"Point"}
}