{
  "type": "Feature",
  "properties": {
    "iso:country":"AU",
    "sg:address":"99 Whites Rd",
    "sg:city":"Manly",
    "sg:classifiers":[
        {
            "category":"Shopping",
            "subcategory":"Clothing, Apparel, & Fashions",
            "type":"Retail Goods"
        }
    ],
    "sg:phone":"+61 7 3393 5370",
    "sg:postcode":"4179",
    "sg:province":"QLD",
    "sg:tags":[
        "recycled",
        "clothing"
    ],
    "wof:name":"Save The Children Fund (QLD)",
    "wof:placetype":"venue"
},
  "geometry": {"coordinates":[153.18000793499999,-27.4626941681],"type":"Point"}
}