{
  "type": "Feature",
  "properties": {
    "addr:full":"Mersey Rd Spreyton TAS 7310",
    "addr:postcode":"7310",
    "addr:street":"Mersey Rd",
    "iso:country":"AU",
    "sg:address":"Mersey Rd",
    "sg:city":"Spreyton",
    "sg:classifiers":[
        {
            "category":"Home & Garden",
            "subcategory":"Garden Supply",
            "type":"Retail Goods"
        }
    ],
    "sg:phone":"+61 3 6427 2067",
    "sg:postcode":"7310",
    "sg:province":"TAS",
    "sg:tags":[
        "nursery"
    ],
    "wof:name":"Defender Peat Products Pty Ltd",
    "wof:placetype":"venue"
},
  "geometry": {"coordinates":[146.352981567,-41.1867980957],"type":"Point"}
}