{
  "type": "Feature",
  "properties": {
    "addr:full":"1 William Street Melbourne VIC 3000",
    "addr:housenumber":"1",
    "addr:postcode":"3000",
    "addr:street":"William Street",
    "iso:country":"AU",
    "sg:address":"1 William Street",
    "sg:city":"Melbourne",
    "sg:classifiers":[
        {
            "category":"Restaurant",
            "type":"Food & Drink"
        }
    ],
    "sg:phone":"+61 3 9296 8862",
    "sg:postcode":"3000",
    "sg:province":"VIC",
    "wof:name":"Williams Bar & Cafe",
    "wof:placetype":"venue"
},
  "geometry": {"coordinates":[144.95980835,-37.8194236755],"type":"Point"}
}