{
  "type": "Feature",
  "properties": {
    "iso:country":"AU",
    "sg:address":"Charters Towers Showgrounds Clarke St",
    "sg:city":"Charters Towers",
    "sg:classifiers":[
        {
            "category":"Organizations",
            "subcategory":"Professional Association",
            "type":"Services"
        }
    ],
    "sg:phone":"+61 7 4787 7292",
    "sg:postcode":"4820",
    "sg:province":"QLD",
    "sg:tags":[
        "rural",
        "organisation",
        "production",
        "primary"
    ],
    "wof:name":"Towers Pastoral Agricultural & Mining Association Inc",
    "wof:placetype":"venue"
},
  "geometry": {"coordinates":[146.255493,-20.071157],"type":"Point"}
}