{
  "type": "Feature",
  "properties": {
    "addr:full":"520 Orange Grove Rd Booker Bay NSW 2257",
    "addr:housenumber":"520",
    "addr:postcode":"2257",
    "addr:street":"Orange Grove Rd",
    "iso:country":"AU",
    "sg:address":"520 Orange Grove Rd",
    "sg:city":"Booker Bay",
    "sg:classifiers":[
        {
            "category":"Banks & Credit Unions",
            "subcategory":"Financial Services",
            "type":"Services"
        }
    ],
    "sg:phone":"+61 2 4344 1638",
    "sg:postcode":"2257",
    "sg:province":"NSW",
    "sg:tags":[
        "financier"
    ],
    "wof:name":"Huntington Properties Pty Ltd",
    "wof:placetype":"venue"
},
  "geometry": {"coordinates":[151.34580993599999,-33.5081253052],"type":"Point"}
}