{
  "type": "Feature",
  "properties": {
    "iso:country":"AU",
    "sg:address":"10 Keates Rd",
    "sg:city":"Armadale",
    "sg:classifiers":[
        {
            "category":"Home & Garden",
            "subcategory":"Building Materials",
            "type":"Retail Goods"
        }
    ],
    "sg:phone":"+61 8 9399 8336",
    "sg:postcode":"6112",
    "sg:province":"WA",
    "sg:tags":[
        "wall",
        "frame",
        "truss",
        "roof"
    ],
    "wof:name":"A G Trusses",
    "wof:placetype":"venue"
},
  "geometry": {"coordinates":[116.012840271,-32.1717224121],"type":"Point"}
}