{
  "type": "Feature",
  "properties": {
    "addr:full":"Unit 24/ 94 Bryant St Padstow NSW 2211",
    "addr:housenumber":"/ 94",
    "addr:postcode":"2211",
    "addr:street":"Bryant St",
    "iso:country":"AU",
    "sg:address":"Unit 24/ 94 Bryant St",
    "sg:city":"Padstow",
    "sg:classifiers":[
        {
            "category":"Manufacturing",
            "subcategory":"Food",
            "type":"Manufacturing & Wholesale Goods"
        }
    ],
    "sg:phone":"+61 2 9773 6191",
    "sg:postcode":"2211",
    "sg:province":"NSW",
    "sg:tags":[
        "function",
        "catering"
    ],
    "wof:name":"Cosmos Catering",
    "wof:placetype":"venue"
},
  "geometry": {"coordinates":[151.03509500000001,-33.941059],"type":"Point"}
}