{
  "type": "Feature",
  "properties": {
    "addr:full":"Elizabeth St Eumundi QLD 4562",
    "addr:postcode":"4562",
    "addr:street":"Elizabeth St",
    "iso:country":"AU",
    "sg:address":"Elizabeth St",
    "sg:city":"Eumundi",
    "sg:classifiers":[
        {
            "category":"Home & Garden",
            "subcategory":"Carpets & Floor Coverings",
            "type":"Retail Goods"
        }
    ],
    "sg:phone":"+61 412 370 590",
    "sg:postcode":"4562",
    "sg:province":"QLD",
    "sg:tags":[
        "layer",
        "planner"
    ],
    "wof:name":"Hudson Floor Covering Service",
    "wof:placetype":"venue"
},
  "geometry": {"coordinates":[152.94807434099999,-26.4717750549],"type":"Point"}
}