{
  "type": "Feature",
  "properties": {
    "iso:country":"AU",
    "sg:address":"5 Hall St",
    "sg:city":"Castlemaine",
    "sg:classifiers":[
        {
            "category":"Wholesale",
            "subcategory":"Machinery & Supplies",
            "type":"Manufacturing & Wholesale Goods"
        }
    ],
    "sg:phone":"+61 3 5472 4370",
    "sg:postcode":"3450",
    "sg:province":"VIC",
    "sg:tags":[
        "equipment",
        "hydraulic"
    ],
    "wof:name":"Castlemaine Hydraulics",
    "wof:placetype":"venue"
},
  "geometry": {"coordinates":[144.218185425,-37.0536346436],"type":"Point"}
}