{
  "type": "Feature",
  "properties": {
    "iso:country":"AU",
    "sg:address":"63 Nicholson St",
    "sg:city":"Orbost",
    "sg:classifiers":[
        {
            "category":"Travel",
            "subcategory":"Hotels & Motels",
            "type":"Entertainment"
        }
    ],
    "sg:phone":"+61 3 5154 1003",
    "sg:postcode":"3888",
    "sg:province":"VIC",
    "sg:tags":[
        "accommodation"
    ],
    "wof:name":"Club Hotel",
    "wof:placetype":"venue"
},
  "geometry": {"coordinates":[148.45851135300001,-37.6923179626],"type":"Point"}
}