{
  "type": "Feature",
  "properties": {
    "addr:full":"30 Stradbroke St Heathwood QLD 4110",
    "addr:housenumber":"30",
    "addr:postcode":"4110",
    "addr:street":"Stradbroke St",
    "iso:country":"AU",
    "sg:address":"30 Stradbroke St",
    "sg:city":"Heathwood",
    "sg:classifiers":[
        {
            "category":"Professional",
            "subcategory":"Accounting & Tax Preparation",
            "type":"Services"
        }
    ],
    "sg:phone":"+61 1300 728 985",
    "sg:postcode":"4110",
    "sg:province":"QLD",
    "sg:tags":[
        "insulation",
        "wholesaler",
        "material",
        "mfrs"
    ],
    "wof:name":"Fat Batts Insulation",
    "wof:placetype":"venue"
},
  "geometry": {"coordinates":[152.98141479500001,-27.6430473328],"type":"Point"}
}