{
  "type": "Feature",
  "properties": {
    "addr:full":"117 Jessie St Armidale NSW 2350",
    "addr:housenumber":"117",
    "addr:postcode":"2350",
    "addr:street":"Jessie St",
    "iso:country":"AU",
    "sg:address":"117 Jessie St",
    "sg:city":"Armidale",
    "sg:classifiers":[
        {
            "category":"Personal",
            "subcategory":"Beauty Salon",
            "type":"Services"
        }
    ],
    "sg:phone":"+61 2 6772 3659",
    "sg:postcode":"2350",
    "sg:province":"NSW",
    "sg:tags":[
        "hairdresser"
    ],
    "wof:name":"Kristies Hair & Beauty Boutique",
    "wof:placetype":"venue"
},
  "geometry": {"coordinates":[151.663604736,-30.5130653381],"type":"Point"}
}