{
  "type": "Feature",
  "properties": {
    "addr:full":"11 Production Drv Campbellfield VIC 3061",
    "addr:housenumber":"11",
    "addr:postcode":"3061",
    "addr:street":"Production Drv",
    "iso:country":"AU",
    "sg:address":"11 Production Drv",
    "sg:city":"Campbellfield",
    "sg:classifiers":[
        {
            "category":"Wholesale",
            "subcategory":"Non-durable Goods",
            "type":"Manufacturing & Wholesale Goods"
        }
    ],
    "sg:phone":"+61 3 9357 7188",
    "sg:postcode":"3061",
    "sg:province":"VIC",
    "sg:tags":[
        "textile"
    ],
    "wof:name":"Melbourne Fabrics",
    "wof:placetype":"venue"
},
  "geometry": {"coordinates":[144.96998596200001,-37.6654205322],"type":"Point"}
}