{
  "type": "Feature",
  "properties": {
    "iso:country":"AU",
    "sg:address":"Level 3/ 549 Queen St",
    "sg:city":"Brisbane",
    "sg:classifiers":[
        {
            "category":"Professional",
            "subcategory":"Accounting & Tax Preparation",
            "type":"Services"
        }
    ],
    "sg:phone":"+61 7 3839 9733",
    "sg:postcode":"4000",
    "sg:province":"QLD",
    "sg:tags":[
        "accountant",
        "auditor"
    ],
    "wof:name":"Lawler Hacketts Chartered Accountants",
    "wof:placetype":"venue"
},
  "geometry": {"coordinates":[153.03138732900001,-27.462808609],"type":"Point"}
}