{
  "type": "Feature",
  "properties": {
    "addr:full":"Suite 9 115 Darby St Newcastle NSW 2300",
    "addr:housenumber":"115",
    "addr:postcode":"2300",
    "addr:street":"Darby St",
    "iso:country":"AU",
    "sg:address":"Suite 9 115 Darby St",
    "sg:city":"Newcastle",
    "sg:classifiers":[
        {
            "category":"Communications",
            "subcategory":"Television Station",
            "type":"Services"
        }
    ],
    "sg:phone":"+61 2 4929 2990",
    "sg:postcode":"2300",
    "sg:province":"NSW",
    "sg:tags":[
        "wholesaler",
        "wire",
        "mfrs",
        "electric",
        "cable"
    ],
    "wof:name":"Olex",
    "wof:placetype":"venue"
},
  "geometry": {"coordinates":[151.772186,-32.931137],"type":"Point"}
}