{
  "type": "Feature",
  "properties": {
    "iso:country":"AU",
    "sg:address":"Shop 20, South Shore Plaza 85",
    "sg:city":"The Esplanade South Perth",
    "sg:classifiers":[
        {
            "category":"Travel",
            "subcategory":"Travel Agent",
            "type":"Entertainment"
        }
    ],
    "sg:phone":"+61 13 18 66",
    "sg:postcode":"6151",
    "sg:province":"WA",
    "sg:tags":[
        "consultant"
    ],
    "wof:name":"Flight Centre",
    "wof:placetype":"venue"
},
  "geometry": {"coordinates":[115.85019699999999,-32.012627],"type":"Point"}
}