{
  "type": "Feature",
  "properties": {
    "addr:full":"Shop 61 Logan Central Plaza Logan QLD 4114",
    "addr:housenumber":"shop 61",
    "addr:postcode":"4114",
    "iso:country":"AU",
    "sg:address":"Shop 61 Logan Central Plaza",
    "sg:city":"Logan",
    "sg:classifiers":[
        {
            "category":"Shopping",
            "subcategory":"Music",
            "type":"Retail Goods"
        }
    ],
    "sg:phone":"+61 7 3208 0252",
    "sg:postcode":"4114",
    "sg:province":"QLD",
    "sg:tags":[
        "store"
    ],
    "wof:name":"Woody's Music Store",
    "wof:placetype":"venue"
},
  "geometry": {"coordinates":[153.10911560100001,-27.598077774],"type":"Point"}
}