{
  "type": "Feature",
  "properties": {
    "addr:full":"3 Humble Crt Kambah ACT 2902",
    "addr:housenumber":"3",
    "addr:postcode":"2902",
    "addr:street":"Humble Crt",
    "iso:country":"AU",
    "sg:address":"3 Humble Crt",
    "sg:city":"Kambah",
    "sg:classifiers":[
        {
            "category":"Building & Trades",
            "subcategory":"Landscaping Services",
            "type":"Services"
        }
    ],
    "sg:phone":"+61 2 6231 8213",
    "sg:postcode":"2902",
    "sg:province":"ACT",
    "sg:tags":[
        "architect",
        "landscape"
    ],
    "wof:name":"Area Design Consultants",
    "wof:placetype":"venue"
},
  "geometry": {"coordinates":[149.07760620100001,-35.3834037781],"type":"Point"}
}