{
  "type": "Feature",
  "properties": {
    "addr:full":"Unit 12/ 398 The Boulevarde Kirrawee NSW 2232",
    "addr:housenumber":"/ 398",
    "addr:postcode":"2232",
    "addr:street":"The Boulevarde",
    "iso:country":"AU",
    "sg:address":"Unit 12/ 398 The Boulevarde",
    "sg:city":"Kirrawee",
    "sg:classifiers":[
        {
            "category":"Wholesale",
            "subcategory":"Painting Supplies",
            "type":"Manufacturing & Wholesale Goods"
        }
    ],
    "sg:phone":"+61 2 8536 9000",
    "sg:postcode":"2232",
    "sg:province":"NSW",
    "sg:tags":[
        "product",
        "cleaning"
    ],
    "wof:name":"Multimaster Australia Pty Ltd",
    "wof:placetype":"venue"
},
  "geometry": {"coordinates":[151.07110595699999,-34.0342292786],"type":"Point"}
}