{
  "type": "Feature",
  "properties": {
    "addr:full":"Kings La Wujal Wujal QLD 4871",
    "addr:postcode":"4871",
    "addr:street":"Kings",
    "iso:country":"AU",
    "sg:address":"Kings La",
    "sg:city":"Wujal Wujal",
    "sg:classifiers":[
        {
            "category":"Autos & Motor Vehicles",
            "subcategory":"Fuel & Gas Station",
            "type":"Retail Goods"
        }
    ],
    "sg:phone":"+61 7 4060 8290",
    "sg:postcode":"4871",
    "sg:province":"QLD",
    "wof:name":"Wujal Wujal Service Station",
    "wof:placetype":"venue"
},
  "geometry": {"coordinates":[143.27737426799999,-16.0666408539],"type":"Point"}
}