{
  "type": "Feature",
  "properties": {
    "addr:full":"122 Sparkes Rd Norlane VIC 3214",
    "addr:housenumber":"122",
    "addr:postcode":"3214",
    "addr:street":"Sparkes Rd",
    "iso:country":"AU",
    "sg:address":"122 Sparkes Rd",
    "sg:city":"Norlane",
    "sg:classifiers":[
        {
            "category":"Retail",
            "subcategory":"Auto Repair",
            "type":"Services"
        }
    ],
    "sg:phone":"+61 418 521 552",
    "sg:postcode":"3214",
    "sg:province":"VIC",
    "sg:tags":[
        "clutch",
        "brake"
    ],
    "wof:name":"Geelong Mobile Brakes",
    "wof:placetype":"venue"
},
  "geometry": {"coordinates":[144.35887145999999,-38.0915603638],"type":"Point"}
}