{
  "type": "Feature",
  "properties": {
    "iso:country":"AU",
    "sg:address":"U6/ 1 Oswald St",
    "sg:city":"Mosman",
    "sg:classifiers":[
        {
            "category":"Professional",
            "subcategory":"Art Services",
            "type":"Services"
        }
    ],
    "sg:phone":"+61 2 9953 7902",
    "sg:postcode":"2088",
    "sg:province":"NSW",
    "sg:tags":[
        "arranger",
        "music",
        "composer"
    ],
    "wof:name":"Ian Laurence Music",
    "wof:placetype":"venue"
},
  "geometry": {"coordinates":[151.23210144000001,-33.833568573],"type":"Point"}
}