{
  "type": "Feature",
  "properties": {
    "addr:full":"132 Manningham Rd Bulleen VIC 3105",
    "addr:housenumber":"132",
    "addr:postcode":"3105",
    "addr:street":"Manningham Rd",
    "iso:country":"AU",
    "sg:address":"132 Manningham Rd",
    "sg:city":"Bulleen",
    "sg:classifiers":[
        {
            "category":"Health Services",
            "subcategory":"Chiropractor",
            "type":"Services"
        }
    ],
    "sg:phone":"+61 3 9852 0055",
    "sg:postcode":"3105",
    "sg:province":"VIC",
    "wof:name":"Emergency At All Hours Chiropractic Clinic",
    "wof:placetype":"venue"
},
  "geometry": {"coordinates":[145.09629821799999,-37.768447876],"type":"Point"}
}