{
  "type": "Feature",
  "properties": {
    "iso:country":"AU",
    "sg:address":"160 Finch St",
    "sg:city":"Glen Iris",
    "sg:classifiers":[
        {
            "category":"Communications",
            "type":"Services"
        }
    ],
    "sg:phone":"+61 3 9509 5229",
    "sg:postcode":"3146",
    "sg:province":"VIC",
    "sg:tags":[
        "translation"
    ],
    "wof:name":"Vietnamese Intertrans",
    "wof:placetype":"venue"
},
  "geometry": {"coordinates":[145.04515075699999,-37.8623809814],"type":"Point"}
}