{
  "type": "Feature",
  "properties": {
    "iso:country":"AU",
    "sg:address":"Bussell Hwy",
    "sg:city":"Gelorup",
    "sg:classifiers":[
        {
            "category":"Autos & Motor Vehicles",
            "subcategory":"Fuel & Gas Station",
            "type":"Retail Goods"
        }
    ],
    "sg:phone":"+61 8 9795 7002",
    "sg:postcode":"6230",
    "sg:province":"WA",
    "wof:name":"Caltex",
    "wof:placetype":"venue"
},
  "geometry": {"coordinates":[115.632248,-33.408077],"type":"Point"}
}