{
  "type": "Feature",
  "properties": {
    "addr:full":"10 Addison Rd Marrickville NSW 2204",
    "addr:housenumber":"10",
    "addr:postcode":"2204",
    "addr:street":"Addison Rd",
    "iso:country":"AU",
    "sg:address":"10 Addison Rd",
    "sg:city":"Marrickville",
    "sg:classifiers":[
        {
            "category":"Real Estate",
            "subcategory":"Architect",
            "type":"Services"
        }
    ],
    "sg:phone":"+61 2 9557 8733",
    "sg:postcode":"2204",
    "sg:province":"NSW",
    "wof:name":"FMJM Partnership Pty Ltd",
    "wof:placetype":"venue"
},
  "geometry": {"coordinates":[151.16795300000001,-33.904102],"type":"Point"}
}