{
  "type": "Feature",
  "properties": {
    "addr:full":"103 Gray St Hamilton VIC 3300",
    "addr:housenumber":"103",
    "addr:postcode":"3300",
    "addr:street":"Gray St",
    "iso:country":"AU",
    "sg:address":"103 Gray St",
    "sg:city":"Hamilton",
    "sg:classifiers":[
        {
            "category":"Personal",
            "type":"Services"
        }
    ],
    "sg:phone":"+61 3 5572 3474",
    "sg:postcode":"3300",
    "sg:province":"VIC",
    "sg:tags":[
        "gift"
    ],
    "wof:name":"Hamilton Florist",
    "wof:placetype":"venue"
},
  "geometry": {"coordinates":[142.02330017099999,-37.743560791],"type":"Point"}
}