{
  "type": "Feature",
  "properties": {
    "addr:full":"2/ 93-95 Grand Plaza Drv Browns Plains QLD 4118",
    "addr:housenumber":"/ 93-95",
    "addr:postcode":"4118",
    "addr:street":"Grand Plaza Drv",
    "iso:country":"AU",
    "sg:address":"2/ 93-95 Grand Plaza Drv",
    "sg:city":"Browns Plains",
    "sg:classifiers":[
        {
            "category":"Shopping",
            "subcategory":"Pawn Shop",
            "type":"Retail Goods"
        }
    ],
    "sg:phone":"+61 7 3800 7308",
    "sg:postcode":"4118",
    "sg:province":"QLD",
    "sg:tags":[
        "pawnbroker"
    ],
    "wof:name":"Browns Plains Pawnbrokers & Jewellery",
    "wof:placetype":"venue"
},
  "geometry": {"coordinates":[153.04318237300001,-27.6625595093],"type":"Point"}
}