{
  "type": "Feature",
  "properties": {
    "iso:country":"AU",
    "sg:address":"388- 390 Barkly St",
    "sg:city":"Brunswick",
    "sg:classifiers":[
        {
            "category":"Shopping",
            "subcategory":"Gifts & Souvenirs",
            "type":"Retail Goods"
        }
    ],
    "sg:phone":"+61 3 9388 1484",
    "sg:postcode":"3056",
    "sg:province":"VIC",
    "sg:tags":[
        "shop",
        "supply"
    ],
    "wof:name":"Arton Giftware",
    "wof:placetype":"venue"
},
  "geometry": {"coordinates":[144.956542969,-37.7756881714],"type":"Point"}
}