{
  "type": "Feature",
  "properties": {
    "iso:country":"AU",
    "sg:address":"80 John St",
    "sg:city":"Yeppoon",
    "sg:classifiers":[
        {
            "category":"Education",
            "subcategory":"Special Training",
            "type":"Public Place"
        }
    ],
    "sg:phone":"+61 7 4935 4165",
    "sg:postcode":"4703",
    "sg:province":"QLD",
    "sg:tags":[
        "tuition-educational"
    ],
    "wof:name":"Access Literacy & Learning",
    "wof:placetype":"venue"
},
  "geometry": {"coordinates":[150.741729736,-23.1310367584],"type":"Point"}
}