{
  "type": "Feature",
  "properties": {
    "addr:full":"145 Browns Plains Rd Browns Plains QLD 4118",
    "addr:housenumber":"145",
    "addr:postcode":"4118",
    "addr:street":"Browns Plains Rd",
    "iso:country":"AU",
    "sg:address":"145 Browns Plains Rd",
    "sg:city":"Browns Plains",
    "sg:classifiers":[
        {
            "category":"Shopping",
            "subcategory":"Bicycles & Sporting Goods",
            "type":"Retail Goods"
        }
    ],
    "sg:phone":"+61 7 3806 6911",
    "sg:postcode":"4118",
    "sg:province":"QLD",
    "sg:tags":[
        "chemical",
        "equipment",
        "pool",
        "swimming"
    ],
    "wof:name":"Clark Pools & Spas",
    "wof:placetype":"venue"
},
  "geometry": {"coordinates":[153.05267334000001,-27.6625957489],"type":"Point"}
}