{
  "type": "Feature",
  "properties": {
    "iso:country":"AU",
    "sg:address":"Shaws Rd",
    "sg:city":"Kanumbra",
    "sg:classifiers":[
        {
            "category":"Building & Trades",
            "subcategory":"Landscaping Services",
            "type":"Services"
        }
    ],
    "sg:phone":"+61 3 5773 4272",
    "sg:postcode":"3719",
    "sg:province":"VIC",
    "sg:tags":[
        "grazier"
    ],
    "wof:name":"Lane C F",
    "wof:placetype":"venue"
},
  "geometry": {"coordinates":[145.63432312,-36.9851875305],"type":"Point"}
}