{
  "type": "Feature",
  "properties": {
    "iso:country":"AU",
    "sg:address":"52 Savoy St",
    "sg:city":"Port Macquarie",
    "sg:classifiers":[
        {
            "category":"Personal",
            "subcategory":"Massage",
            "type":"Services"
        }
    ],
    "sg:phone":"+61 2 6584 1166",
    "sg:postcode":"2444",
    "sg:province":"NSW",
    "sg:tags":[
        "therapy"
    ],
    "wof:name":"Wendy Millis",
    "wof:placetype":"venue"
},
  "geometry": {"coordinates":[152.913376,-31.443287],"type":"Point"}
}