{
  "type": "Feature",
  "properties": {
    "addr:full":"10 Baker St St Kilda VIC 3182",
    "addr:housenumber":"10",
    "addr:postcode":"3182",
    "addr:street":"Baker St",
    "iso:country":"AU",
    "sg:address":"10 Baker St St",
    "sg:city":"Kilda",
    "sg:classifiers":[
        {
            "category":"Professional",
            "subcategory":"Art Services",
            "type":"Services"
        }
    ],
    "sg:phone":"+61 3 9593 9322",
    "sg:postcode":"3182",
    "sg:province":"VIC",
    "sg:tags":[
        "product",
        "industrial",
        "designer"
    ],
    "wof:name":"Blend Colour Marketing & Design Pty Ltd",
    "wof:placetype":"venue"
},
  "geometry": {"coordinates":[144.97850036599999,-37.8733863831],"type":"Point"}
}