{
  "type": "Feature",
  "properties": {
    "addr:full":"67 Maluka Drv Gunn NT 0832",
    "addr:housenumber":"67",
    "addr:postcode":"nt 0832",
    "addr:street":"Maluka Drv",
    "iso:country":"AU",
    "sg:address":"67 Maluka Drv",
    "sg:city":"Gunn",
    "sg:classifiers":[
        {
            "category":"Communications",
            "type":"Services"
        }
    ],
    "sg:phone":"+61 8 8932 9355",
    "sg:postcode":"0832",
    "sg:province":"NT",
    "sg:tags":[
        "data"
    ],
    "wof:name":"Darwin Data Cablers Pty Ltd",
    "wof:placetype":"venue"
},
  "geometry": {"coordinates":[130.99279799999999,-12.485482],"type":"Point"}
}