{
  "type": "Feature",
  "properties": {
    "iso:country":"AU",
    "sg:address":"31 Forest St",
    "sg:city":"Whittlesea",
    "sg:classifiers":[
        {
            "category":"Wholesale",
            "subcategory":"Farm Supplies",
            "type":"Manufacturing & Wholesale Goods"
        }
    ],
    "sg:phone":"+61 3 9716 2459",
    "sg:postcode":"3757",
    "sg:province":"VIC",
    "sg:tags":[
        "feed",
        "supplement",
        "stock"
    ],
    "wof:name":"Whittlesea Produce",
    "wof:placetype":"venue"
},
  "geometry": {"coordinates":[145.120773,-37.510445],"type":"Point"}
}