{
  "type": "Feature",
  "properties": {
    "iso:country":"AU",
    "sg:address":"Unit 5/ 46 Burgess Rd",
    "sg:city":"Bayswater North",
    "sg:classifiers":[
        {
            "category":"Wholesale",
            "subcategory":"Machinery & Supplies",
            "type":"Manufacturing & Wholesale Goods"
        }
    ],
    "sg:phone":"+61 3 9761 6846",
    "sg:postcode":"3153",
    "sg:province":"VIC",
    "sg:tags":[
        "instrument"
    ],
    "wof:name":"Integrated Analytical Systems Pty Ltd",
    "wof:placetype":"venue"
},
  "geometry": {"coordinates":[145.29441833499999,-37.8237457275],"type":"Point"}
}