{
  "type": "Feature",
  "properties": {
    "iso:country":"AU",
    "sg:address":"3 Palina Rd",
    "sg:city":"Smithfield",
    "sg:classifiers":[
        {
            "category":"Building & Trades",
            "subcategory":"Construction",
            "type":"Services"
        }
    ],
    "sg:phone":"+61 8 8284 1847",
    "sg:postcode":"5114",
    "sg:province":"SA",
    "sg:tags":[
        "welding"
    ],
    "wof:name":"Gant & Sons Pty Ltd",
    "wof:placetype":"venue"
},
  "geometry": {"coordinates":[138.68780517600001,-34.6765823364],"type":"Point"}
}