{
  "type": "Feature",
  "properties": {
    "addr:full":"Lot 11 588 Waterloo Cnr Rd Burton SA 5110",
    "addr:housenumber":"588",
    "addr:postcode":"5110",
    "addr:street":"Waterloo Cnr Rd",
    "iso:country":"AU",
    "sg:address":"Lot 11 588 Waterloo Cnr Rd",
    "sg:city":"Burton",
    "sg:classifiers":[
        {
            "category":"Retail",
            "subcategory":"Auto Repair",
            "type":"Services"
        }
    ],
    "sg:phone":"+61 8 8280 9569",
    "sg:postcode":"5110",
    "sg:province":"SA",
    "sg:tags":[
        "beater",
        "painter",
        "panel"
    ],
    "wof:name":"Burton Paint & Panel",
    "wof:placetype":"venue"
},
  "geometry": {"coordinates":[138.60757446299999,-34.7416687012],"type":"Point"}
}