{
  "type": "Feature",
  "properties": {
    "iso:country":"AU",
    "sg:address":"22 Hadfield St",
    "sg:city":"Windsor",
    "sg:classifiers":[
        {
            "category":"Building & Trades",
            "subcategory":"Plumbing",
            "type":"Services"
        }
    ],
    "sg:phone":"+61 7 3857 2605",
    "sg:postcode":"4030",
    "sg:province":"QLD",
    "sg:tags":[
        "plumber",
        "gasfitters"
    ],
    "wof:name":"Gary Starr Plumbing",
    "wof:placetype":"venue"
},
  "geometry": {"coordinates":[153.034607,-27.430658],"type":"Point"}
}