{
  "type": "Feature",
  "properties": {
    "iso:country":"AU",
    "sg:address":"PO Box 6759",
    "sg:city":"Gold Coast Mail Centre",
    "sg:classifiers":[
        {
            "category":"Building & Trades",
            "subcategory":"Equipment Rental",
            "type":"Services"
        }
    ],
    "sg:phone":"+61 7 5533 7991",
    "sg:postcode":"9726",
    "sg:province":"QLD",
    "sg:tags":[
        "party",
        "hire"
    ],
    "wof:name":"Leaves N Things",
    "wof:placetype":"venue"
},
  "geometry": {"coordinates":[153.44924926799999,-28.0854701996],"type":"Point"}
}