{
  "type": "Feature",
  "properties": {
    "addr:full":"16- 22 Cullen Pl Smithfield NSW 2164",
    "addr:housenumber":"22",
    "addr:postcode":"2164",
    "addr:street":"Cullen Pl",
    "iso:country":"AU",
    "sg:address":"16- 22 Cullen Pl",
    "sg:city":"Smithfield",
    "sg:classifiers":[
        {
            "category":"Professional",
            "subcategory":"Detective & Security Services",
            "type":"Services"
        }
    ],
    "sg:phone":"+61 1800 472 654",
    "sg:postcode":"2164",
    "sg:province":"NSW",
    "sg:tags":[
        "equipment",
        "window",
        "doors"
    ],
    "wof:name":"Gramline Colorbond Fencing",
    "wof:placetype":"venue"
},
  "geometry": {"coordinates":[150.949493408,-33.8415794373],"type":"Point"}
}