{
  "type": "Feature",
  "properties": {
    "iso:country":"AU",
    "sg:address":"Unit 7, 77-85 Pasturage Rd",
    "sg:city":"Caboolture",
    "sg:classifiers":[
        {
            "category":"Professional",
            "subcategory":"Detective & Security Services",
            "type":"Services"
        }
    ],
    "sg:phone":"+61 7 5495 7533",
    "sg:postcode":"4510",
    "sg:province":"QLD",
    "sg:tags":[
        "equipment",
        "window",
        "doors"
    ],
    "wof:name":"Lockout",
    "wof:placetype":"venue"
},
  "geometry": {"coordinates":[152.978088,-27.083626],"type":"Point"}
}