{
  "type": "Feature",
  "properties": {
    "iso:country":"AU",
    "sg:address":"120 Old Maryborough Rd",
    "sg:city":"Gympie",
    "sg:classifiers":[
        {
            "category":"Education",
            "subcategory":"Music School",
            "type":"Public Place"
        }
    ],
    "sg:phone":"+61 7 5483 9419",
    "sg:postcode":"4570",
    "sg:province":"QLD",
    "sg:tags":[
        "teacher"
    ],
    "wof:name":"Elizabeth Young",
    "wof:placetype":"venue"
},
  "geometry": {"coordinates":[152.671676636,-26.1741199493],"type":"Point"}
}