{
  "type": "Feature",
  "properties": {
    "addr:full":"4 Kipling Crt Burwood East VIC 3151",
    "addr:housenumber":"4",
    "addr:postcode":"3151",
    "addr:street":"Kipling Crt",
    "iso:country":"AU",
    "sg:address":"4 Kipling Crt",
    "sg:city":"Burwood East",
    "sg:classifiers":[
        {
            "category":"Building & Trades",
            "subcategory":"Cleaning & Sanitation",
            "type":"Services"
        }
    ],
    "sg:phone":"+61 3 9887 9604",
    "sg:postcode":"3151",
    "sg:province":"VIC",
    "sg:tags":[
        "industrial",
        "commercial",
        "contractor"
    ],
    "wof:name":"Sealpoint Cleaning Services",
    "wof:placetype":"venue"
},
  "geometry": {"coordinates":[145.16253662099999,-37.850528717],"type":"Point"}
}