{
  "type": "Feature",
  "properties": {
    "iso:country":"AU",
    "sg:address":"12a Marton St",
    "sg:city":"Shortland",
    "sg:classifiers":[
        {
            "category":"Retail",
            "subcategory":"Repair Shop",
            "type":"Services"
        }
    ],
    "sg:phone":"+61 2 4955 8076",
    "sg:postcode":"2307",
    "sg:province":"NSW",
    "sg:tags":[
        "mending",
        "clothing",
        "alteration"
    ],
    "wof:name":"Barrack Nola",
    "wof:placetype":"venue"
},
  "geometry": {"coordinates":[151.69508400000001,-32.879059],"type":"Point"}
}