{
  "type": "Feature",
  "properties": {
    "iso:country":"AU",
    "sg:address":"21 Dingley Ave",
    "sg:city":"Dandenong",
    "sg:classifiers":[
        {
            "category":"Retail",
            "subcategory":"Auto Repair",
            "type":"Services"
        }
    ],
    "sg:phone":"+61 3 9708 5226",
    "sg:postcode":"3175",
    "sg:province":"VIC",
    "sg:tags":[
        "repairer",
        "motor",
        "engineer"
    ],
    "wof:name":"G & J Differential Services Pty Ltd",
    "wof:placetype":"venue"
},
  "geometry": {"coordinates":[145.19598388700001,-37.9938430786],"type":"Point"}
}