{
  "type": "Feature",
  "properties": {
    "addr:full":"204 Main Rd Monbulk VIC 3793",
    "addr:housenumber":"204",
    "addr:postcode":"3793",
    "addr:street":"Main Rd",
    "iso:country":"AU",
    "sg:address":"204 Main Rd",
    "sg:city":"Monbulk",
    "sg:classifiers":[
        {
            "category":"Health Services",
            "subcategory":"Health Practitioner",
            "type":"Services"
        }
    ],
    "sg:phone":"+61 3 9752 1198",
    "sg:postcode":"3793",
    "sg:province":"VIC",
    "sg:tags":[
        "physiotherapist"
    ],
    "wof:name":"Monbulk & District Physiotherapy Greg Murphy",
    "wof:placetype":"venue"
},
  "geometry": {"coordinates":[145.40544128400001,-37.873336792],"type":"Point"}
}