{
  "type": "Feature",
  "properties": {
    "addr:full":"Pasteur St Jericho QLD 4702",
    "addr:postcode":"4702",
    "addr:street":"Pasteur St",
    "iso:country":"AU",
    "sg:address":"Pasteur St",
    "sg:city":"Jericho",
    "sg:classifiers":[
        {
            "category":"Education",
            "subcategory":"School",
            "type":"Public Place"
        }
    ],
    "sg:phone":"+61 7 4651 4162",
    "sg:postcode":"4702",
    "sg:province":"QLD",
    "sg:tags":[
        "state",
        "except",
        "nsw"
    ],
    "wof:name":"Jericho Primary",
    "wof:placetype":"venue"
},
  "geometry": {"coordinates":[146.12997436500001,-23.6038322449],"type":"Point"}
}