{
  "type": "Feature",
  "properties": {
    "iso:country":"AU",
    "sg:address":"221 High St",
    "sg:city":"Fremantle",
    "sg:classifiers":[
        {
            "category":"Real Estate",
            "subcategory":"Real Estate Agent",
            "type":"Services"
        }
    ],
    "sg:phone":"+61 8 9430 8155",
    "sg:postcode":"6160",
    "sg:province":"WA",
    "wof:name":"Edinger Real Estate",
    "wof:placetype":"venue"
},
  "geometry": {"coordinates":[115.753281,-32.052467],"type":"Point"}
}