{
  "type": "Feature",
  "properties": {
    "addr:full":"2/ 3 Treharne Cl Marsfield NSW 2122",
    "addr:housenumber":"/ 3",
    "addr:postcode":"2122",
    "addr:street":"Treharne Cl",
    "iso:country":"AU",
    "sg:address":"2/ 3 Treharne Cl",
    "sg:city":"Marsfield",
    "sg:classifiers":[
        {
            "category":"Utilities",
            "subcategory":"Electric",
            "type":"Services"
        }
    ],
    "sg:phone":"+61 2 9888 3566",
    "sg:postcode":"2122",
    "sg:province":"NSW",
    "sg:tags":[
        "electrical",
        "contractor"
    ],
    "wof:name":"Thor Electrics Pty Ltd",
    "wof:placetype":"venue"
},
  "geometry": {"coordinates":[151.102325439,-33.7803497314],"type":"Point"}
}