{
  "type": "Feature",
  "properties": {
    "iso:country":"AU",
    "sg:address":"2 Park St",
    "sg:city":"Bacchus Marsh",
    "sg:classifiers":[
        {
            "category":"Home & Garden",
            "subcategory":"Building Materials",
            "type":"Retail Goods"
        }
    ],
    "sg:phone":"+61 3 5367 3025",
    "sg:postcode":"3340",
    "sg:province":"VIC",
    "sg:tags":[
        "pre-mixed",
        "concrete"
    ],
    "wof:name":"Alsafe Pre-Mix Concrete",
    "wof:placetype":"venue"
},
  "geometry": {"coordinates":[144.43985,-37.686588],"type":"Point"}
}