{
  "type": "Feature",
  "properties": {
    "iso:country":"AU",
    "sg:address":"22 Seventh Ave",
    "sg:city":"Windsor",
    "sg:classifiers":[
        {
            "category":"Farming",
            "subcategory":"Farm & Veterinary Services",
            "type":"Manufacturing & Wholesale Goods"
        }
    ],
    "sg:phone":"+61 7 3315 6311",
    "sg:postcode":"4030",
    "sg:province":"QLD",
    "sg:tags":[
        "agricultural",
        "advisory"
    ],
    "wof:name":"Stur Werner Dr International Agricultural R & D Consultant",
    "wof:placetype":"venue"
},
  "geometry": {"coordinates":[153.02702300000001,-27.434814],"type":"Point"}
}