{
  "type": "Feature",
  "properties": {
    "iso:country":"AU",
    "sg:address":"57 Walter Rd",
    "sg:city":"Dianella",
    "sg:classifiers":[
        {
            "category":"Personal",
            "subcategory":"Barber",
            "type":"Services"
        }
    ],
    "sg:phone":"+61 8 9271 0928",
    "sg:postcode":"6059",
    "sg:province":"WA",
    "wof:name":"Sopranos Mens Hair Salon",
    "wof:placetype":"venue"
},
  "geometry": {"coordinates":[115.93502807599999,-31.8946151733],"type":"Point"}
}