{
  "type": "Feature",
  "properties": {
    "iso:country":"AU",
    "sg:address":"60- 64 Bromley St",
    "sg:city":"Cornubia",
    "sg:classifiers":[
        {
            "category":"Professional",
            "subcategory":"Art Services",
            "type":"Services"
        }
    ],
    "sg:phone":"+61 7 3287 6189",
    "sg:postcode":"4130",
    "sg:province":"QLD",
    "sg:tags":[
        "decorator",
        "painter"
    ],
    "wof:name":"Top 2 Bottom",
    "wof:placetype":"venue"
},
  "geometry": {"coordinates":[153.207473755,-27.6708278656],"type":"Point"}
}