{
  "type": "Feature",
  "properties": {
    "addr:full":"51 Holland St Northgate QLD 4013",
    "addr:housenumber":"51",
    "addr:postcode":"4013",
    "addr:street":"Holland St",
    "iso:country":"AU",
    "sg:address":"51 Holland St",
    "sg:city":"Northgate",
    "sg:classifiers":[
        {
            "category":"Professional",
            "subcategory":"Detective & Security Services",
            "type":"Services"
        }
    ],
    "sg:phone":"+61 7 3266 7400",
    "sg:postcode":"4013",
    "sg:province":"QLD",
    "sg:tags":[
        "equipment",
        "window",
        "doors"
    ],
    "wof:name":"PanAsia Aluminium (Brisbane) Pty Ltd",
    "wof:placetype":"venue"
},
  "geometry": {"coordinates":[153.07037353499999,-27.3927364349],"type":"Point"}
}