{
  "type": "Feature",
  "properties": {
    "iso:country":"AU",
    "sg:address":"8 Arnott St",
    "sg:city":"Newcastle West",
    "sg:classifiers":[
        {
            "category":"Retail",
            "subcategory":"Auto Repair",
            "type":"Services"
        }
    ],
    "sg:phone":"+61 2 4926 1718",
    "sg:postcode":"2302",
    "sg:province":"NSW",
    "sg:tags":[
        "repairer",
        "motor",
        "engineer"
    ],
    "wof:name":"Denstoj Auto Centre",
    "wof:placetype":"venue"
},
  "geometry": {"coordinates":[151.764679,-32.930546],"type":"Point"}
}