{
  "type": "Feature",
  "properties": {
    "addr:full":"141 Brougham St Woolloomooloo NSW 2011",
    "addr:housenumber":"141",
    "addr:postcode":"2011",
    "addr:street":"Brougham St",
    "iso:country":"AU",
    "sg:address":"141 Brougham St",
    "sg:city":"Woolloomooloo",
    "sg:classifiers":[
        {
            "category":"Real Estate",
            "subcategory":"Real Estate Agent",
            "type":"Services"
        }
    ],
    "sg:phone":"+61 2 9380 2236",
    "sg:postcode":"2011",
    "sg:province":"NSW",
    "sg:tags":[
        "export"
    ],
    "wof:name":"Duke & Duchess Pty Ltd",
    "wof:placetype":"venue"
},
  "geometry": {"coordinates":[151.2215271,-33.8736381531],"type":"Point"}
}