{
  "type": "Feature",
  "properties": {
    "addr:full":"430 Rode Rd Chermside QLD 4032",
    "addr:housenumber":"430",
    "addr:postcode":"qld 4032",
    "addr:street":"Rode Rd",
    "iso:country":"AU",
    "sg:address":"430 Rode Rd",
    "sg:city":"Chermside",
    "sg:classifiers":[
        {
            "category":"Professional",
            "subcategory":"Art Services",
            "type":"Services"
        }
    ],
    "sg:phone":"+61 7 3359 1386",
    "sg:postcode":"4032",
    "sg:province":"QLD",
    "sg:tags":[
        "picture",
        "frame",
        "framing"
    ],
    "wof:name":"Peter Gardiner Picture Framing",
    "wof:placetype":"venue"
},
  "geometry": {"coordinates":[153.03118900000001,-27.393637],"type":"Point"}
}