{
  "type": "Feature",
  "properties": {
    "iso:country":"AU",
    "sg:address":"5 Birrakay Crt",
    "sg:city":"Greensborough",
    "sg:classifiers":[
        {
            "category":"Personal",
            "subcategory":"Massage",
            "type":"Services"
        }
    ],
    "sg:phone":"+61 3 9435 0238",
    "sg:postcode":"3088",
    "sg:province":"VIC",
    "sg:tags":[
        "therapy"
    ],
    "wof:name":"James Sumarac",
    "wof:placetype":"venue"
},
  "geometry": {"coordinates":[145.10304260300001,-37.6939964294],"type":"Point"}
}