{
  "type": "Feature",
  "properties": {
    "addr:full":"192 Great Western Hwy Hazelbrook NSW 2779",
    "addr:housenumber":"192",
    "addr:postcode":"2779",
    "addr:street":"Great Western Hwy",
    "iso:country":"AU",
    "sg:address":"192 Great Western Hwy",
    "sg:city":"Hazelbrook",
    "sg:classifiers":[
        {
            "category":"Food & Beverages",
            "subcategory":"Fruits & Vegetables",
            "type":"Retail Goods"
        }
    ],
    "sg:phone":"+61 2 4758 6739",
    "sg:postcode":"2779",
    "sg:province":"NSW",
    "sg:tags":[
        "greengrocer",
        "fruiterer"
    ],
    "wof:name":"Hazelbrook Fruit & Vegetables",
    "wof:placetype":"venue"
},
  "geometry": {"coordinates":[150.453201294,-33.722328186],"type":"Point"}
}