{
  "type": "Feature",
  "properties": {
    "iso:country":"AU",
    "sg:address":"33 Sir Joseph Banks St",
    "sg:city":"Botany",
    "sg:classifiers":[
        {
            "category":"Home & Garden",
            "subcategory":"Building Materials",
            "type":"Retail Goods"
        }
    ],
    "sg:phone":"+61 2 9316 8378",
    "sg:postcode":"2019",
    "sg:province":"NSW",
    "sg:tags":[
        "supply"
    ],
    "wof:name":"Donovan Chemicals Pty Ltd",
    "wof:placetype":"venue"
},
  "geometry": {"coordinates":[151.202102661,-33.9494514465],"type":"Point"}
}