{
  "type": "Feature",
  "properties": {
    "addr:full":"26 High St Beechworth VIC 3747",
    "addr:housenumber":"26",
    "addr:postcode":"3747",
    "addr:street":"High St",
    "iso:country":"AU",
    "sg:address":"26 High St",
    "sg:city":"Beechworth",
    "sg:classifiers":[
        {
            "category":"Professional",
            "type":"Services"
        }
    ],
    "sg:phone":"+61 408 691 484",
    "sg:postcode":"3747",
    "sg:province":"VIC",
    "sg:tags":[
        "courier"
    ],
    "wof:name":"Beechworth Couriers",
    "wof:placetype":"venue"
},
  "geometry": {"coordinates":[146.68443300000001,-36.363148],"type":"Point"}
}