{
  "type": "Feature",
  "properties": {
    "iso:country":"AU",
    "sg:address":"Unit 2, 1 Gordon St",
    "sg:city":"Camperdown",
    "sg:classifiers":[
        {
            "category":"Wholesale",
            "subcategory":"Photographic Equipment",
            "type":"Manufacturing & Wholesale Goods"
        }
    ],
    "sg:phone":"+61 2 9550 5833",
    "sg:postcode":"2050",
    "sg:province":"NSW",
    "sg:tags":[
        "wholesaler",
        "mfrs",
        "supply"
    ],
    "wof:name":"Vanbar Photographic Supplies",
    "wof:placetype":"venue"
},
  "geometry": {"coordinates":[151.173889,-33.886055],"type":"Point"}
}