{
  "type": "Feature",
  "properties": {
    "addr:full":"Unit 508/ 3 Kings Cross Rd Kings Cross NSW 2011",
    "addr:housenumber":"/ 3",
    "addr:postcode":"2011",
    "addr:street":"Kings Cross Rd",
    "iso:country":"AU",
    "sg:address":"Unit 508/ 3 Kings Cross Rd",
    "sg:city":"Kings Cross",
    "sg:classifiers":[
        {
            "category":"Home & Garden",
            "subcategory":"Garden Supply",
            "type":"Retail Goods"
        }
    ],
    "sg:phone":"+61 413 650 410",
    "sg:postcode":"2011",
    "sg:province":"NSW",
    "sg:tags":[
        "statuary",
        "fountains",
        "sundial"
    ],
    "wof:name":"A La Belle Epoque",
    "wof:placetype":"venue"
},
  "geometry": {"coordinates":[151.22267150900001,-33.8755760193],"type":"Point"}
}