{
  "type": "Feature",
  "properties": {
    "addr:full":"18 Twynam St Narrandera NSW 2700",
    "addr:housenumber":"18",
    "addr:postcode":"2700",
    "addr:street":"Twynam St",
    "iso:country":"AU",
    "sg:address":"18 Twynam St",
    "sg:city":"Narrandera",
    "sg:classifiers":[
        {
            "category":"Retail",
            "subcategory":"Veterinary Services",
            "type":"Services"
        }
    ],
    "sg:phone":"+61 2 6959 2039",
    "sg:postcode":"2700",
    "sg:province":"NSW",
    "sg:tags":[
        "surgeon"
    ],
    "wof:name":"Narrandera Veterinary Clinic",
    "wof:placetype":"venue"
},
  "geometry": {"coordinates":[146.55137634299999,-34.7468605042],"type":"Point"}
}