{
  "type": "Feature",
  "properties": {
    "addr:full":"Unit 6, 92 Killara Rd Campbellfield VIC 3061",
    "addr:housenumber":"92",
    "addr:postcode":"3061",
    "addr:street":"Killara Rd",
    "iso:country":"AU",
    "sg:address":"Unit 6, 92 Killara Rd",
    "sg:city":"Campbellfield",
    "sg:classifiers":[
        {
            "category":"Wholesale",
            "subcategory":"Farm Supplies",
            "type":"Manufacturing & Wholesale Goods"
        }
    ],
    "sg:phone":"+61 1300 721 099",
    "sg:postcode":"3061",
    "sg:province":"VIC",
    "sg:tags":[
        "equipment"
    ],
    "wof:name":"Bainbridge Veterinary Instrument",
    "wof:placetype":"venue"
},
  "geometry": {"coordinates":[144.96510314899999,-37.6607551575],"type":"Point"}
}