{
  "type": "Feature",
  "properties": {
    "addr:full":"22 Sinnamon Rd Seventeen Mile Rocks QLD 4073",
    "addr:housenumber":"22",
    "addr:postcode":"4073",
    "addr:street":"Sinnamon Rd",
    "iso:country":"AU",
    "sg:address":"22 Sinnamon Rd",
    "sg:city":"Seventeen Mile Rocks",
    "sg:classifiers":[
        {
            "category":"Utilities",
            "subcategory":"Natural Gas",
            "type":"Services"
        }
    ],
    "sg:phone":"+61 7 3376 6955",
    "sg:postcode":"4073",
    "sg:province":"QLD",
    "sg:tags":[
        "pontoon"
    ],
    "wof:name":"Bellingham Marine",
    "wof:placetype":"venue"
},
  "geometry": {"coordinates":[152.95773315400001,-27.5378417969],"type":"Point"}
}