{
  "type": "Feature",
  "properties": {
    "addr:full":"26 Rogers St Roselands NSW 2196",
    "addr:housenumber":"26",
    "addr:postcode":"2196",
    "addr:street":"Rogers St",
    "iso:country":"AU",
    "sg:address":"26 Rogers St",
    "sg:city":"Roselands",
    "sg:classifiers":[
        {
            "category":"Utilities",
            "type":"Services"
        }
    ],
    "sg:phone":"+61 419 999 799",
    "sg:postcode":"2196",
    "sg:province":"NSW",
    "sg:tags":[
        "refrigeration",
        "industrial",
        "commercial",
        "retail"
    ],
    "wof:name":"Paragon Refrigeration",
    "wof:placetype":"venue"
},
  "geometry": {"coordinates":[151.080307,-33.936069],"type":"Point"}
}