{
  "type": "Feature",
  "properties": {
    "addr:full":"221- 223 Main South Rd Morphett Vale SA 5162",
    "addr:housenumber":"221 223",
    "addr:postcode":"5162",
    "addr:street":"Main South Rd",
    "iso:country":"AU",
    "sg:address":"221- 223 Main South Rd",
    "sg:city":"Morphett Vale",
    "sg:classifiers":[
        {
            "category":"Health Services",
            "subcategory":"Doctor",
            "type":"Services"
        }
    ],
    "sg:phone":"+61 8 8326 2111",
    "sg:postcode":"5162",
    "sg:province":"SA",
    "sg:tags":[
        "medical",
        "practitioner"
    ],
    "wof:name":"Sawyer Bridget Dr",
    "wof:placetype":"venue"
},
  "geometry": {"coordinates":[138.52276611299999,-35.117893219],"type":"Point"}
}