{
  "type": "Feature",
  "properties": {
    "iso:country":"AU",
    "sg:address":"Shop 6 Railway Arcade 255 Dorset Rd",
    "sg:city":"Boronia",
    "sg:classifiers":[
        {
            "category":"Personal",
            "subcategory":"Beauty Salon",
            "type":"Services"
        }
    ],
    "sg:phone":"+61 3 9762 3146",
    "sg:postcode":"3155",
    "sg:province":"VIC",
    "sg:tags":[
        "hairdresser"
    ],
    "wof:name":"Brush & Cut",
    "wof:placetype":"venue"
},
  "geometry": {"coordinates":[145.28556823700001,-37.8604660034],"type":"Point"}
}