{
  "type": "Feature",
  "properties": {
    "iso:country":"AU",
    "sg:address":"60 Owen St",
    "sg:city":"Glendenning",
    "sg:classifiers":[
        {
            "category":"Utilities",
            "type":"Services"
        }
    ],
    "sg:phone":"+61 2 9675 4456",
    "sg:postcode":"2761",
    "sg:province":"NSW",
    "sg:tags":[
        "refrigeration",
        "industrial",
        "commercial",
        "retail"
    ],
    "wof:name":"Arneg Oceania Pty Ltd",
    "wof:placetype":"venue"
},
  "geometry": {"coordinates":[150.858276,-33.748638],"type":"Point"}
}