{
  "type": "Feature",
  "properties": {
    "iso:country":"AU",
    "sg:address":"285 Melton Rd",
    "sg:city":"Gisborne",
    "sg:classifiers":[
        {
            "category":"Utilities",
            "subcategory":"Water",
            "type":"Services"
        }
    ],
    "sg:phone":"+61 3 5428 4830",
    "sg:postcode":"3437",
    "sg:province":"VIC",
    "sg:tags":[
        "cartage"
    ],
    "wof:name":"Gisborne & District Water Cartage",
    "wof:placetype":"venue"
},
  "geometry": {"coordinates":[144.59135437,-37.4869995117],"type":"Point"}
}