{
  "type": "Feature",
  "properties": {
    "addr:full":"49 Burswood Rd Burswood WA 6100",
    "addr:housenumber":"49",
    "addr:postcode":"6100",
    "addr:street":"Burswood Rd",
    "iso:country":"AU",
    "sg:address":"49 Burswood Rd",
    "sg:city":"Burswood",
    "sg:classifiers":[
        {
            "category":"Retail",
            "subcategory":"Auto Repair",
            "type":"Services"
        }
    ],
    "sg:phone":"+61 8 9311 7555",
    "sg:postcode":"6100",
    "sg:province":"WA",
    "sg:tags":[
        "repairer",
        "motor",
        "engineer"
    ],
    "wof:name":"Burswood Honda",
    "wof:placetype":"venue"
},
  "geometry": {"coordinates":[115.892272949,-31.967798233],"type":"Point"}
}