{
  "type": "Feature",
  "properties": {
    "addr:full":"Cnr Shute Harbour Rd & Coconut Gr Airlie Beach QLD 4802",
    "addr:postcode":"4802",
    "addr:street":"Cnr Shute Harbour Rd & Coconut Gr",
    "iso:country":"AU",
    "sg:address":"Cnr Shute Harbour Rd",
    "sg:city":"& Coconut Gr Airlie Beach",
    "sg:classifiers":[
        {
            "category":"Bars & Pubs",
            "subcategory":"Nightclub",
            "type":"Food & Drink"
        }
    ],
    "sg:phone":"+61 7 4946 6905",
    "sg:postcode":"4802",
    "sg:province":"QLD",
    "sg:tags":[
        "discotheque"
    ],
    "wof:name":"Legends Bar & Grill",
    "wof:placetype":"venue"
},
  "geometry": {"coordinates":[148.71969604500001,-20.2692375183],"type":"Point"}
}