{
  "type": "Feature",
  "properties": {
    "addr:full":"Cnr Lewington & Hereford Sts Bomen NSW 2650",
    "addr:postcode":"2650",
    "addr:street":"Cnr Lewington & Hereford Sts",
    "iso:country":"AU",
    "sg:address":"Cnr Lewington & Hereford Sts",
    "sg:city":"Bomen",
    "sg:classifiers":[
        {
            "category":"Wholesale",
            "subcategory":"Machinery & Supplies",
            "type":"Manufacturing & Wholesale Goods"
        }
    ],
    "sg:phone":"+61 2 6971 0755",
    "sg:postcode":"2650",
    "sg:province":"NSW",
    "sg:tags":[
        "agricultural"
    ],
    "wof:name":"K & S Machinery",
    "wof:placetype":"venue"
},
  "geometry": {"coordinates":[147.40977477999999,-35.071849823],"type":"Point"}
}