{
  "type": "Feature",
  "properties": {
    "iso:country":"AU",
    "sg:address":"1st Floor, 152 Marsden St",
    "sg:city":"Parramatta",
    "sg:classifiers":[
        {
            "category":"Health Services",
            "subcategory":"Doctor",
            "type":"Services"
        }
    ],
    "sg:phone":"+61 2 9635 6964",
    "sg:postcode":"2150",
    "sg:province":"NSW",
    "sg:tags":[
        "medical",
        "practitioner"
    ],
    "wof:name":"Chong Robert Dr",
    "wof:placetype":"venue"
},
  "geometry": {"coordinates":[151.00190734899999,-33.8137702942],"type":"Point"}
}