{
  "type": "Feature",
  "properties": {
    "addr:full":"2/ 449 Mitcham Rd Mitcham VIC 3132",
    "addr:housenumber":"/ 449",
    "addr:postcode":"3132",
    "addr:street":"Mitcham Rd",
    "iso:country":"AU",
    "sg:address":"2/ 449 Mitcham Rd",
    "sg:city":"Mitcham",
    "sg:classifiers":[
        {
            "category":"Professional",
            "subcategory":"Engineering",
            "type":"Services"
        }
    ],
    "sg:phone":"+61 3 9874 2663",
    "sg:postcode":"3132",
    "sg:province":"VIC",
    "sg:tags":[
        "consulting",
        "engineer"
    ],
    "wof:name":"Winkfield Pty Ltd",
    "wof:placetype":"venue"
},
  "geometry": {"coordinates":[145.19453430199999,-37.8249893188],"type":"Point"}
}