{
  "type": "Feature",
  "properties": {
    "addr:full":"Suite 302, Level 3, 137-139 Bathurst St Sydney NSW 2000",
    "addr:housenumber":"302 level 3",
    "addr:postcode":"137-139;2000",
    "addr:street":"Bathurst St",
    "iso:country":"AU",
    "sg:address":"Suite 302, Level 3, 137-139 Bathurst St",
    "sg:city":"Sydney",
    "sg:classifiers":[
        {
            "category":"Professional",
            "subcategory":"Management & Consulting",
            "type":"Services"
        }
    ],
    "sg:phone":"+61 1300 764 727",
    "sg:postcode":"2000",
    "sg:province":"NSW",
    "sg:tags":[
        "consultant",
        "migration"
    ],
    "wof:name":"Advocate Immigration Lawyers & Agents",
    "wof:placetype":"venue"
},
  "geometry": {"coordinates":[151.20857238799999,-33.8746376038],"type":"Point"}
}