{
  "type": "Feature",
  "properties": {
    "addr:full":"Shop 50 Burnside Village 447 Portrush Rd Glenside SA 5065",
    "addr:housenumber":"shop 50;447",
    "addr:postcode":"5065",
    "addr:street":"Burnside Village;Portrush Rd",
    "iso:country":"AU",
    "sg:address":"Shop 50 Burnside Village 447 Portrush Rd",
    "sg:city":"Glenside",
    "sg:classifiers":[
        {
            "category":"Food & Beverages",
            "subcategory":"Specialty",
            "type":"Retail Goods"
        }
    ],
    "sg:phone":"+61 8 8379 6806",
    "sg:postcode":"5065",
    "sg:province":"SA",
    "sg:tags":[
        "delicacy"
    ],
    "wof:name":"Viva Gourmet Fine Foods",
    "wof:placetype":"venue"
},
  "geometry": {"coordinates":[138.64247131400001,-34.9413871765],"type":"Point"}
}