{
  "type": "Feature",
  "properties": {
    "addr:full":"16 Helena St Midland WA 6056",
    "addr:housenumber":"16",
    "addr:postcode":"6056",
    "addr:street":"Helena St",
    "iso:country":"AU",
    "sg:address":"16 Helena St",
    "sg:city":"Midland",
    "sg:classifiers":[
        {
            "category":"Health Services",
            "subcategory":"Dentist",
            "type":"Services"
        }
    ],
    "sg:phone":"+61 8 9250 3100",
    "sg:postcode":"6056",
    "sg:province":"WA",
    "wof:name":"Helena Street Dental Clinic",
    "wof:placetype":"venue"
},
  "geometry": {"coordinates":[116.003013611,-31.8903656006],"type":"Point"}
}