{
  "type": "Feature",
  "properties": {
    "addr:full":"4 Juandah St Wandoan QLD 4419",
    "addr:housenumber":"4",
    "addr:postcode":"4419",
    "addr:street":"Juandah St",
    "iso:country":"AU",
    "sg:address":"4 Juandah St",
    "sg:city":"Wandoan",
    "sg:classifiers":[
        {
            "category":"Commercial Area",
            "type":"Public Place"
        }
    ],
    "sg:phone":"+61 7 4627 4188",
    "sg:postcode":"4419",
    "sg:province":"QLD",
    "sg:tags":[
        "heavy",
        "carrier"
    ],
    "wof:name":"Kurtz Transport Pty Ltd",
    "wof:placetype":"venue"
},
  "geometry": {"coordinates":[149.964385986,-26.1237545013],"type":"Point"}
}