{
  "type": "Feature",
  "properties": {
    "iso:country":"AU",
    "sg:address":"60 Beaumont St",
    "sg:city":"Hamilton",
    "sg:classifiers":[
        {
            "category":"Shopping",
            "subcategory":"Crafts & Fabrics",
            "type":"Retail Goods"
        }
    ],
    "sg:phone":"+61 2 4961 6016",
    "sg:postcode":"2303",
    "sg:province":"NSW",
    "sg:tags":[
        "supply"
    ],
    "wof:name":"Anne's Glory Box",
    "wof:placetype":"venue"
},
  "geometry": {"coordinates":[151.747238,-32.921543],"type":"Point"}
}