{
  "type": "Feature",
  "properties": {
    "iso:country":"AU",
    "sg:address":"Shop1/ 5 Nash St",
    "sg:city":"Paddington",
    "sg:classifiers":[
        {
            "category":"Fast Food",
            "type":"Food & Drink"
        }
    ],
    "sg:phone":"+61 7 3511 6511",
    "sg:postcode":"4064",
    "sg:province":"QLD",
    "sg:tags":[
        "away",
        "take"
    ],
    "wof:name":"Sing's Asian Kitchen",
    "wof:placetype":"venue"
},
  "geometry": {"coordinates":[152.99713134800001,-27.465883255],"type":"Point"}
}