{
  "type": "Feature",
  "properties": {
    "addr:full":"PO Box 1673 Macquarie Centre NSW 2113",
    "addr:postcode":"2113",
    "iso:country":"AU",
    "sg:address":"PO Box 1673",
    "sg:city":"Macquarie Centre",
    "sg:classifiers":[
        {
            "category":"Arena",
            "subcategory":"Indoor Arena",
            "type":"Entertainment"
        }
    ],
    "sg:phone":"+61 419 629 771",
    "sg:postcode":"2113",
    "sg:province":"NSW",
    "sg:tags":[
        "modelmakers"
    ],
    "wof:name":"Kewiz Graphics Services",
    "wof:placetype":"venue"
},
  "geometry": {"coordinates":[151.13319397000001,-33.7892303467],"type":"Point"}
}