{
  "type": "Feature",
  "properties": {
    "addr:full":"715 Pechey Rd Swan View WA 6056",
    "addr:housenumber":"715",
    "addr:postcode":"6056",
    "addr:street":"Pechey Rd",
    "iso:country":"AU",
    "sg:address":"715 Pechey Rd",
    "sg:city":"Swan View",
    "sg:classifiers":[
        {
            "category":"Building & Trades",
            "subcategory":"Construction",
            "type":"Services"
        }
    ],
    "sg:phone":"+61 419 952 043",
    "sg:postcode":"6056",
    "sg:province":"WA",
    "sg:tags":[
        "contractor"
    ],
    "wof:name":"Ramseys Construction",
    "wof:placetype":"venue"
},
  "geometry": {"coordinates":[116.064308166,-31.8789424896],"type":"Point"}
}