{
  "type": "Feature",
  "properties": {
    "addr:full":"Saint Rd Ningi QLD 4511",
    "addr:postcode":"4511",
    "addr:street":"Saint Rd",
    "iso:country":"AU",
    "sg:address":"Saint Rd",
    "sg:city":"Ningi",
    "sg:classifiers":[
        {
            "category":"Farming",
            "subcategory":"Nursery",
            "type":"Manufacturing & Wholesale Goods"
        }
    ],
    "sg:phone":"+61 408 767 554",
    "sg:postcode":"4511",
    "sg:province":"QLD",
    "wof:name":"Ningi Bamboo",
    "wof:placetype":"venue"
},
  "geometry": {"coordinates":[153.03334000000001,-27.053474],"type":"Point"}
}