{
  "type": "Feature",
  "properties": {
    "iso:country":"AU",
    "sg:address":"155 Karaak Flat Rd",
    "sg:city":"Karaak Flat",
    "sg:classifiers":[
        {
            "category":"Professional",
            "subcategory":"Accounting & Tax Preparation",
            "type":"Services"
        }
    ],
    "sg:phone":"+61 2 6553 0931",
    "sg:postcode":"2429",
    "sg:province":"NSW",
    "sg:tags":[
        "consultant",
        "taxation"
    ],
    "wof:name":"Leanne George, CPA",
    "wof:placetype":"venue"
},
  "geometry": {"coordinates":[152.286224,-31.92621],"type":"Point"}
}