{
  "type": "Feature",
  "properties": {
    "addr:full":"1a 270 Mann St Armidale NSW 2350",
    "addr:housenumber":"1a 270",
    "addr:postcode":"2350",
    "addr:street":"Mann St",
    "iso:country":"AU",
    "sg:address":"1a 270 Mann St",
    "sg:city":"Armidale",
    "sg:classifiers":[
        {
            "category":"Retail",
            "subcategory":"Auto Repair",
            "type":"Services"
        }
    ],
    "sg:phone":"+61 2 6771 1535",
    "sg:postcode":"2350",
    "sg:province":"NSW",
    "sg:tags":[
        "repairer",
        "motor",
        "engineer"
    ],
    "wof:name":"Yates Ian Service Centre",
    "wof:placetype":"venue"
},
  "geometry": {"coordinates":[151.64216613799999,-30.5146026611],"type":"Point"}
}