{
  "type": "Feature",
  "properties": {
    "iso:country":"AU",
    "sg:address":"139 Wilson St",
    "sg:city":"Burnie",
    "sg:classifiers":[
        {
            "category":"Retail",
            "subcategory":"Auto Rental",
            "type":"Services"
        }
    ],
    "sg:phone":"+61 3 6434 4466",
    "sg:postcode":"7320",
    "sg:province":"TAS",
    "sg:tags":[
        "car",
        "hire",
        "minibus"
    ],
    "wof:name":"Avis Car Rental",
    "wof:placetype":"venue"
},
  "geometry": {"coordinates":[145.905151,-41.059944],"type":"Point"}
}