{
  "type": "Feature",
  "properties": {
    "addr:full":"240 Brown St Armidale NSW 2350",
    "addr:housenumber":"240",
    "addr:postcode":"2350",
    "addr:street":"Brown St",
    "iso:country":"AU",
    "sg:address":"240 Brown St",
    "sg:city":"Armidale",
    "sg:classifiers":[
        {
            "category":"Home & Garden",
            "subcategory":"Garden Supply",
            "type":"Retail Goods"
        }
    ],
    "sg:phone":"+61 2 6771 4711",
    "sg:postcode":"2350",
    "sg:province":"NSW",
    "sg:tags":[
        "landscape"
    ],
    "wof:name":"Terra Firma * New England",
    "wof:placetype":"venue"
},
  "geometry": {"coordinates":[151.67732238799999,-30.5222244263],"type":"Point"}
}