{
  "type": "Feature",
  "properties": {
    "addr:full":"481 Watson Rd Golden Hill WA 6333",
    "addr:housenumber":"481",
    "addr:postcode":"6333",
    "addr:street":"Watson Rd",
    "iso:country":"AU",
    "sg:address":"481 Watson Rd",
    "sg:city":"Golden Hill",
    "sg:classifiers":[
        {
            "category":"Farming",
            "subcategory":"Vineyard",
            "type":"Manufacturing & Wholesale Goods"
        }
    ],
    "sg:phone":"+61 8 9840 9381",
    "sg:postcode":"6333",
    "sg:province":"WA",
    "sg:tags":[
        "winery"
    ],
    "wof:name":"Karriview Wines",
    "wof:placetype":"venue"
},
  "geometry": {"coordinates":[117.26200103799999,-34.925567627],"type":"Point"}
}