{
  "type": "Feature",
  "properties": {
    "addr:full":"Unit 1 21 Duntroon St Brendale QLD 4500",
    "addr:housenumber":"21",
    "addr:postcode":"4500",
    "addr:street":"Duntroon St",
    "iso:country":"AU",
    "sg:address":"Unit 1 21 Duntroon St",
    "sg:city":"Brendale",
    "sg:classifiers":[
        {
            "category":"Professional",
            "subcategory":"Detective & Security Services",
            "type":"Services"
        }
    ],
    "sg:phone":"+61 7 3283 7166",
    "sg:postcode":"4500",
    "sg:province":"QLD",
    "sg:tags":[
        "equipment",
        "window",
        "doors"
    ],
    "wof:name":"B J Securities Wholesalers",
    "wof:placetype":"venue"
},
  "geometry": {"coordinates":[152.98359680199999,-27.3216934204],"type":"Point"}
}