{
  "type": "Feature",
  "properties": {
    "iso:country":"AU",
    "sg:address":"217 Argyle St",
    "sg:city":"Hobart",
    "sg:classifiers":[
        {
            "category":"Professional",
            "type":"Services"
        }
    ],
    "sg:phone":"+61 3 6234 4122",
    "sg:postcode":"7000",
    "sg:province":"TAS",
    "sg:tags":[
        "valuer"
    ],
    "wof:name":"Banks-Smith Wayne",
    "wof:placetype":"venue"
},
  "geometry": {"coordinates":[147.31582641599999,-42.8697662354],"type":"Point"}
}