{
  "type": "Feature",
  "properties": {
    "iso:country":"AU",
    "sg:address":"Jannali Rd",
    "sg:city":"Dubbo",
    "sg:classifiers":[
        {
            "category":"Freight",
            "type":"Transportation"
        }
    ],
    "sg:phone":"+61 2 6884 4245",
    "sg:postcode":"2830",
    "sg:province":"NSW",
    "sg:tags":[
        "light",
        "carrier"
    ],
    "wof:name":"Tamex Transport Pty Ltd",
    "wof:placetype":"venue"
},
  "geometry": {"coordinates":[148.58244323700001,-32.2414093018],"type":"Point"}
}