{
  "type": "Feature",
  "properties": {
    "iso:country":"AU",
    "sg:address":"227 Ewings Rd",
    "sg:city":"Avenel",
    "sg:classifiers":[
        {
            "category":"Professional",
            "subcategory":"Detective & Security Services",
            "type":"Services"
        }
    ],
    "sg:phone":"+61 409 164 046",
    "sg:postcode":"3664",
    "sg:province":"VIC",
    "sg:tags":[
        "consultant",
        "system"
    ],
    "wof:name":"Storm Security",
    "wof:placetype":"venue"
},
  "geometry": {"coordinates":[145.21844482399999,-36.8960762024],"type":"Point"}
}