{
  "type": "Feature",
  "properties": {
    "iso:country":"AU",
    "sg:address":"23a Cook Drv",
    "sg:city":"Coffs Harbour",
    "sg:classifiers":[
        {
            "category":"Building & Trades",
            "subcategory":"Construction",
            "type":"Services"
        }
    ],
    "sg:phone":"+61 2 6652 7771",
    "sg:postcode":"2450",
    "sg:province":"NSW",
    "sg:tags":[
        "renovation",
        "alterations",
        "extension",
        "contractor"
    ],
    "wof:name":"Jims Add-A-Room",
    "wof:placetype":"venue"
},
  "geometry": {"coordinates":[153.088455,-30.315775],"type":"Point"}
}