{
  "type": "Feature",
  "properties": {
    "addr:full":"141 Pacific Hwy Charlestown NSW 2290",
    "addr:housenumber":"141",
    "addr:postcode":"2290",
    "addr:street":"Pacific Hwy",
    "iso:country":"AU",
    "sg:address":"141 Pacific Hwy",
    "sg:city":"Charlestown",
    "sg:classifiers":[
        {
            "category":"Real Estate",
            "subcategory":"Real Estate Agent",
            "type":"Services"
        }
    ],
    "sg:phone":"+61 2 4943 3155",
    "sg:postcode":"2290",
    "sg:province":"NSW",
    "wof:name":"Professionals",
    "wof:placetype":"venue"
},
  "geometry": {"coordinates":[151.69610595699999,-32.9633750916],"type":"Point"}
}