{
  "type": "Feature",
  "properties": {
    "iso:country":"AU",
    "sg:address":"L2- 472 New Canterbury Rd",
    "sg:city":"Dulwich Hill",
    "sg:classifiers":[
        {
            "category":"Professional",
            "subcategory":"Detective & Security Services",
            "type":"Services"
        }
    ],
    "sg:phone":"+61 2 9569 4800",
    "sg:postcode":"2203",
    "sg:province":"NSW",
    "sg:tags":[
        "consultant",
        "system"
    ],
    "wof:name":"Parkom Electronic Security",
    "wof:placetype":"venue"
},
  "geometry": {"coordinates":[151.13964799999999,-33.90451],"type":"Point"}
}