{
  "type": "Feature",
  "properties": {
    "iso:country":"AU",
    "sg:address":"26 London Drv",
    "sg:city":"Bayswater",
    "sg:classifiers":[
        {
            "category":"Wholesale",
            "subcategory":"Painting Supplies",
            "type":"Manufacturing & Wholesale Goods"
        }
    ],
    "sg:phone":"+61 3 9761 1400",
    "sg:postcode":"3153",
    "sg:province":"VIC",
    "sg:tags":[
        "product",
        "polyurethane"
    ],
    "wof:name":"Australian Rubber Rollers",
    "wof:placetype":"venue"
},
  "geometry": {"coordinates":[145.28222656200001,-37.8447608948],"type":"Point"}
}