{
  "type": "Feature",
  "properties": {
    "addr:full":"689 Boundary Rd Coopers Plains QLD 4108",
    "addr:housenumber":"689",
    "addr:postcode":"4108",
    "addr:street":"Boundary Rd",
    "iso:country":"AU",
    "sg:address":"689 Boundary Rd",
    "sg:city":"Coopers Plains",
    "sg:classifiers":[
        {
            "category":"Wholesale",
            "subcategory":"Auto Parts",
            "type":"Manufacturing & Wholesale Goods"
        }
    ],
    "sg:phone":"+61 7 3277 9755",
    "sg:postcode":"4108",
    "sg:province":"QLD",
    "sg:tags":[
        "tyre"
    ],
    "wof:name":"Toyo Tyre & Rubber Aust. Ltd.",
    "wof:placetype":"venue"
},
  "geometry": {"coordinates":[153.02491760300001,-27.5683193207],"type":"Point"}
}