{
  "type": "Feature",
  "properties": {
    "addr:full":"119-121 Pinjarra Rd Mandurah WA 6210",
    "addr:postcode":"119-121;6210",
    "addr:street":"Pinjarra Rd",
    "iso:country":"AU",
    "sg:address":"119-121 Pinjarra Rd",
    "sg:city":"Mandurah",
    "sg:classifiers":[
        {
            "category":"Autos & Motor Vehicles",
            "subcategory":"Automobile Sales",
            "type":"Retail Goods"
        }
    ],
    "sg:phone":"+61 8 9535 6555",
    "sg:postcode":"6210",
    "sg:province":"WA",
    "sg:tags":[
        "car",
        "new"
    ],
    "wof:name":"Mandurah Hyundai",
    "wof:placetype":"venue"
},
  "geometry": {"coordinates":[115.773033,-32.547134],"type":"Point"}
}