{
  "type": "Feature",
  "properties": {
    "addr:full":"12 Malcolm Rd Maddington WA 6109",
    "addr:housenumber":"12",
    "addr:postcode":"6109",
    "addr:street":"Malcolm Rd",
    "iso:country":"AU",
    "sg:address":"12 Malcolm Rd",
    "sg:city":"Maddington",
    "sg:classifiers":[
        {
            "category":"Government",
            "subcategory":"Department Of Motor Vehicles",
            "type":"Public Place"
        }
    ],
    "sg:phone":"+61 8 9493 3551",
    "sg:postcode":"6109",
    "sg:province":"WA",
    "sg:tags":[
        "wholesaler",
        "mfrs",
        "accessory"
    ],
    "wof:name":"Street Quick Performance Centre",
    "wof:placetype":"venue"
},
  "geometry": {"coordinates":[115.985076904,-32.0418014526],"type":"Point"}
}