{
  "type": "Feature",
  "properties": {
    "addr:full":"PO Box 242 Stratford QLD 4870",
    "addr:postcode":"4870",
    "iso:country":"AU",
    "sg:address":"PO Box 242",
    "sg:city":"Stratford",
    "sg:classifiers":[
        {
            "category":"Shopping",
            "subcategory":"Musical Instruments",
            "type":"Retail Goods"
        }
    ],
    "sg:phone":"+61 7 4032 1124",
    "sg:postcode":"4870",
    "sg:province":"QLD",
    "sg:tags":[
        "musician",
        "agent"
    ],
    "wof:name":"In The Mood",
    "wof:placetype":"venue"
},
  "geometry": {"coordinates":[145.73246765100001,-16.8754291534],"type":"Point"}
}