{
  "type": "Feature",
  "properties": {
    "addr:full":"Shed 1, 305 Morayfield Rd Morayfield QLD 4506",
    "addr:housenumber":"1",
    "addr:postcode":"305;4506",
    "addr:street":"Morayfield Rd",
    "iso:country":"AU",
    "sg:address":"Shed 1, 305 Morayfield Rd",
    "sg:city":"Morayfield",
    "sg:classifiers":[
        {
            "category":"Building & Trades",
            "subcategory":"Construction",
            "type":"Services"
        }
    ],
    "sg:phone":"+61 7 5428 6066",
    "sg:postcode":"4506",
    "sg:province":"QLD",
    "sg:tags":[
        "insulation",
        "contractor"
    ],
    "wof:name":"Smart Insulation",
    "wof:placetype":"venue"
},
  "geometry": {"coordinates":[152.95280456500001,-27.1151065826],"type":"Point"}
}