{
  "type": "Feature",
  "properties": {
    "addr:full":"Grnd Flr 318 Pacific Hwy Lindfield NSW 2070",
    "addr:housenumber":"318",
    "addr:postcode":"2070",
    "addr:street":"Grnd Flr;Pacific Hwy",
    "iso:country":"AU",
    "sg:address":"Grnd Flr 318 Pacific Hwy",
    "sg:city":"Lindfield",
    "sg:classifiers":[
        {
            "category":"Travel",
            "subcategory":"Travel Agent",
            "type":"Entertainment"
        }
    ],
    "sg:phone":"+61 2 9416 7811",
    "sg:postcode":"2070",
    "sg:province":"NSW",
    "sg:tags":[
        "consultant"
    ],
    "wof:name":"American Express International Inc",
    "wof:placetype":"venue"
},
  "geometry": {"coordinates":[151.168624878,-33.7754592896],"type":"Point"}
}