{
  "type": "Feature",
  "properties": {
    "addr:full":"5 Mulga Pl Carrum Downs VIC 3201",
    "addr:housenumber":"5",
    "addr:postcode":"3201",
    "addr:street":"Mulga Pl",
    "iso:country":"AU",
    "sg:address":"5 Mulga Pl",
    "sg:city":"Carrum Downs",
    "sg:classifiers":[
        {
            "category":"Personal",
            "subcategory":"Beauty Salon",
            "type":"Services"
        }
    ],
    "sg:phone":"+61 3 9782 0144",
    "sg:postcode":"3201",
    "sg:province":"VIC",
    "wof:name":"Nails Ago-Go",
    "wof:placetype":"venue"
},
  "geometry": {"coordinates":[145.196136,-38.097557],"type":"Point"}
}