{
  "type": "Feature",
  "properties": {
    "iso:country":"AU",
    "sg:address":"327a Belmore Rd",
    "sg:city":"Riverwood",
    "sg:classifiers":[
        {
            "category":"Personal",
            "subcategory":"Massage",
            "type":"Services"
        }
    ],
    "sg:phone":"+61 2 9584 2751",
    "sg:postcode":"2210",
    "sg:province":"NSW",
    "sg:tags":[
        "therapy"
    ],
    "wof:name":"Health Body Massage",
    "wof:placetype":"venue"
},
  "geometry": {"coordinates":[151.052368,-33.949608],"type":"Point"}
}