{
  "type": "Feature",
  "properties": {
    "iso:country":"AU",
    "sg:address":"2 Alderley Crt",
    "sg:city":"Hamlyn Heights",
    "sg:classifiers":[
        {
            "category":"Home & Garden",
            "subcategory":"Household Appliances",
            "type":"Retail Goods"
        }
    ],
    "sg:phone":"+61 419 595 905",
    "sg:postcode":"3215",
    "sg:province":"VIC",
    "sg:tags":[
        "equipment",
        "gas"
    ],
    "wof:name":"City Gas Services",
    "wof:placetype":"venue"
},
  "geometry": {"coordinates":[144.322097778,-38.1103515625],"type":"Point"}
}