{
  "type": "Feature",
  "properties": {
    "iso:country":"AU",
    "sg:address":"99 Hyatts Rd",
    "sg:city":"Oakhurst",
    "sg:classifiers":[
        {
            "category":"Social Services",
            "subcategory":"Child Care",
            "type":"Services"
        }
    ],
    "sg:phone":"+61 2 9832 0378",
    "sg:postcode":"2761",
    "sg:province":"NSW",
    "wof:name":"St Marks Child Care Centre",
    "wof:placetype":"venue"
},
  "geometry": {"coordinates":[150.835663,-33.740765],"type":"Point"}
}