{
  "type": "Feature",
  "properties": {
    "addr:full":"Unit 3 62 Albert St Berry NSW 2535",
    "addr:housenumber":"62",
    "addr:postcode":"2535",
    "addr:street":"Albert St",
    "iso:country":"AU",
    "sg:address":"Unit 3 62 Albert St",
    "sg:city":"Berry",
    "sg:classifiers":[
        {
            "category":"Cafe",
            "type":"Food & Drink"
        }
    ],
    "sg:phone":"+61 2 4464 3650",
    "sg:postcode":"2535",
    "sg:province":"NSW",
    "wof:name":"Delicious Food by Lisa",
    "wof:placetype":"venue"
},
  "geometry": {"coordinates":[150.69691467300001,-34.7746315002],"type":"Point"}
}