{
  "type": "Feature",
  "properties": {
    "iso:country":"AU",
    "sg:address":"Shop 1/ 11 Manning St",
    "sg:city":"Tuncurry",
    "sg:classifiers":[
        {
            "category":"Professional",
            "subcategory":"Printing & Photocopies",
            "type":"Services"
        }
    ],
    "sg:phone":"+61 2 6555 5629",
    "sg:postcode":"2428",
    "sg:province":"NSW",
    "sg:tags":[
        "trophy"
    ],
    "wof:name":"MJ Sports",
    "wof:placetype":"venue"
},
  "geometry": {"coordinates":[152.500153,-32.17606],"type":"Point"}
}