{
  "type": "Feature",
  "properties": {
    "addr:full":"11 Wran St Goulburn NSW 2580",
    "addr:housenumber":"11",
    "addr:postcode":"2580",
    "addr:street":"Wran St",
    "iso:country":"AU",
    "sg:address":"11 Wran St",
    "sg:city":"Goulburn",
    "sg:classifiers":[
        {
            "category":"Professional",
            "subcategory":"Art Services",
            "type":"Services"
        }
    ],
    "sg:phone":"+61 2 4821 5978",
    "sg:postcode":"2580",
    "sg:province":"NSW",
    "sg:tags":[
        "decorator",
        "painter"
    ],
    "wof:name":"D.F. White",
    "wof:placetype":"venue"
},
  "geometry": {"coordinates":[149.742843628,-34.7192878723],"type":"Point"}
}