{
  "type": "Feature",
  "properties": {
    "addr:full":"338 Balaclava Rd Caulfield North VIC 3161",
    "addr:housenumber":"338",
    "addr:postcode":"3161",
    "addr:street":"Balaclava Rd",
    "iso:country":"AU",
    "sg:address":"338 Balaclava Rd",
    "sg:city":"Caulfield North",
    "sg:classifiers":[
        {
            "category":"Shopping",
            "subcategory":"Optical Goods",
            "type":"Retail Goods"
        }
    ],
    "sg:phone":"+61 3 9509 9991",
    "sg:postcode":"3161",
    "sg:province":"VIC",
    "sg:tags":[
        "dispenser",
        "prescription"
    ],
    "wof:name":"Contax",
    "wof:placetype":"venue"
},
  "geometry": {"coordinates":[145.03573608400001,-37.8741455078],"type":"Point"}
}