{
  "type": "Feature",
  "properties": {
    "iso:country":"AU",
    "sg:address":"39a Cornelia Rd",
    "sg:city":"Toongabbie",
    "sg:classifiers":[
        {
            "category":"Social Services",
            "subcategory":"Adult Care",
            "type":"Services"
        }
    ],
    "sg:phone":"+61 2 9874 8822",
    "sg:postcode":"2146",
    "sg:province":"NSW",
    "sg:tags":[
        "disadvantaged",
        "aid",
        "organisation",
        "group"
    ],
    "wof:name":"Adele Dundas Inc",
    "wof:placetype":"venue"
},
  "geometry": {"coordinates":[150.94471740700001,-33.7862510681],"type":"Point"}
}