{
  "type": "Feature",
  "properties": {
    "addr:full":"5 Couchman Crs Chisholm ACT 2905",
    "addr:housenumber":"5",
    "addr:postcode":"2905",
    "addr:street":"Couchman Crs",
    "iso:country":"AU",
    "sg:address":"5 Couchman Crs",
    "sg:city":"Chisholm",
    "sg:classifiers":[
        {
            "category":"Professional",
            "subcategory":"Computer Services",
            "type":"Services"
        }
    ],
    "sg:phone":"+61 2 6112 8852",
    "sg:postcode":"2905",
    "sg:province":"ACT",
    "sg:tags":[
        "consultant",
        "system"
    ],
    "wof:name":"WP & VL Damm Consulting",
    "wof:placetype":"venue"
},
  "geometry": {"coordinates":[149.124176025,-35.4190483093],"type":"Point"}
}