{
  "type": "Feature",
  "properties": {
    "addr:full":"Shop 150 C, Pacific Fair, Hooker Blvd Broadbeach QLD 4218",
    "addr:housenumber":"150",
    "addr:postcode":"4218",
    "addr:street":"C Pacific;Hooker Blvd",
    "iso:country":"AU",
    "sg:address":"Shop 150",
    "sg:city":"C, Pacific Fair, Hooker Blvd Broadbeach",
    "sg:classifiers":[
        {
            "category":"Shopping",
            "subcategory":"Music",
            "type":"Retail Goods"
        }
    ],
    "sg:phone":"+61 7 5575 6840",
    "sg:postcode":"4218",
    "sg:province":"QLD",
    "sg:tags":[
        "store"
    ],
    "wof:name":"HMV Australia",
    "wof:placetype":"venue"
},
  "geometry": {"coordinates":[153.43081665,-28.034198761],"type":"Point"}
}