{
  "type": "Feature",
  "properties": {
    "addr:full":"19 Harbury St Reservoir VIC 3073",
    "addr:housenumber":"19",
    "addr:postcode":"3073",
    "addr:street":"Harbury St",
    "iso:country":"AU",
    "sg:address":"19 Harbury St",
    "sg:city":"Reservoir",
    "sg:classifiers":[
        {
            "category":"Professional",
            "subcategory":"Computer Services",
            "type":"Services"
        }
    ],
    "sg:phone":"+61 3 9460 9000",
    "sg:postcode":"3073",
    "sg:province":"VIC",
    "sg:tags":[
        "repairs",
        "upgrade",
        "equipment"
    ],
    "wof:name":"Megacom Electronics Pty Ltd",
    "wof:placetype":"venue"
},
  "geometry": {"coordinates":[144.999710083,-37.7140541077],"type":"Point"}
}