{
  "type": "Feature",
  "properties": {
    "addr:full":"60 Robinson St Murchison VIC 3610",
    "addr:housenumber":"60",
    "addr:postcode":"3610",
    "addr:street":"Robinson St",
    "iso:country":"AU",
    "sg:address":"60 Robinson St",
    "sg:city":"Murchison",
    "sg:classifiers":[
        {
            "category":"Autos & Motor Vehicles",
            "subcategory":"Fuel & Gas Station",
            "type":"Retail Goods"
        }
    ],
    "sg:phone":"+61 3 5826 2433",
    "sg:postcode":"3610",
    "sg:province":"VIC",
    "wof:name":"Ashley Motors",
    "wof:placetype":"venue"
},
  "geometry": {"coordinates":[145.21539306599999,-36.6222496033],"type":"Point"}
}