{
  "type": "Feature",
  "properties": {
    "iso:country":"AU",
    "sg:address":"765 Port Rd",
    "sg:city":"Woodville",
    "sg:classifiers":[
        {
            "category":"Health Services",
            "subcategory":"Health Practitioner",
            "type":"Services"
        }
    ],
    "sg:phone":"+61 8 8445 9344",
    "sg:postcode":"5011",
    "sg:province":"SA",
    "sg:tags":[
        "physiotherapist"
    ],
    "wof:name":"Physio One",
    "wof:placetype":"venue"
},
  "geometry": {"coordinates":[138.53721618599999,-34.8816566467],"type":"Point"}
}