{
  "type": "Feature",
  "properties": {
    "addr:full":"Lot 61 Brookton Hwy Roleystone WA 6111",
    "addr:postcode":"6111",
    "addr:street":"Brookton Hwy",
    "iso:country":"AU",
    "sg:address":"Lot 61 Brookton Hwy",
    "sg:city":"Roleystone",
    "sg:classifiers":[
        {
            "category":"Home & Garden",
            "subcategory":"Building Materials",
            "type":"Retail Goods"
        }
    ],
    "sg:phone":"+61 412 509 526",
    "sg:postcode":"6111",
    "sg:province":"WA",
    "sg:tags":[
        "lawn",
        "cutting",
        "maintenance"
    ],
    "wof:name":"Bee Jay's Garden & Lawn Maintenance",
    "wof:placetype":"venue"
},
  "geometry": {"coordinates":[116.062538147,-32.1258468628],"type":"Point"}
}