{
  "type": "Feature",
  "properties": {
    "addr:full":"86 Main Rd Lower Plenty VIC 3093",
    "addr:housenumber":"86",
    "addr:postcode":"3093",
    "addr:street":"Main Rd",
    "iso:country":"AU",
    "sg:address":"86 Main Rd",
    "sg:city":"Lower Plenty",
    "sg:classifiers":[
        {
            "category":"Organizations",
            "subcategory":"Community Association",
            "type":"Services"
        }
    ],
    "sg:phone":"+61 3 9435 8583",
    "sg:postcode":"3093",
    "sg:province":"VIC",
    "sg:tags":[
        "club",
        "senior",
        "citizen"
    ],
    "wof:name":"Lower Plenty Senior Citizen's Centre Inc",
    "wof:placetype":"venue"
},
  "geometry": {"coordinates":[145.11286926299999,-37.7277107239],"type":"Point"}
}