{
  "type": "Feature",
  "properties": {
    "addr:full":"44 Corsair Ave Inala QLD 4077",
    "addr:housenumber":"44",
    "addr:postcode":"4077",
    "addr:street":"Corsair Ave Inala",
    "iso:country":"AU",
    "sg:address":"44 Corsair Ave",
    "sg:city":"Inala",
    "sg:classifiers":[
        {
            "category":"Health Services",
            "subcategory":"Doctor",
            "type":"Services"
        }
    ],
    "sg:phone":"+61 7 3372 3383",
    "sg:postcode":"4077",
    "sg:province":"QLD",
    "sg:tags":[
        "medical",
        "practitioner"
    ],
    "wof:name":"Boothroyd J G",
    "wof:placetype":"venue"
},
  "geometry": {"coordinates":[152.975006103,-27.599899292],"type":"Point"}
}