{
  "type": "Feature",
  "properties": {
    "addr:full":"13 Tinderbox Rd Blackmans Bay TAS 7052",
    "addr:housenumber":"13",
    "addr:postcode":"7052",
    "addr:street":"Tinderbox Rd",
    "iso:country":"AU",
    "sg:address":"13 Tinderbox Rd",
    "sg:city":"Blackmans Bay",
    "sg:classifiers":[
        {
            "category":"Home & Garden",
            "subcategory":"Carpets & Floor Coverings",
            "type":"Retail Goods"
        }
    ],
    "sg:phone":"+61 427 303 223",
    "sg:postcode":"7052",
    "sg:province":"TAS",
    "sg:tags":[
        "double",
        "window",
        "glazed"
    ],
    "wof:name":"Clark Windows Pty Ltd",
    "wof:placetype":"venue"
},
  "geometry": {"coordinates":[147.31767300000001,-43.008778],"type":"Point"}
}