{
  "type": "Feature",
  "properties": {
    "addr:full":"32 Service St Bairnsdale VIC 3875",
    "addr:housenumber":"32",
    "addr:postcode":"3875",
    "addr:street":"Service St",
    "iso:country":"AU",
    "sg:address":"32 Service St",
    "sg:city":"Bairnsdale",
    "sg:classifiers":[
        {
            "category":"Shopping",
            "subcategory":"Party Supplies",
            "type":"Retail Goods"
        }
    ],
    "sg:phone":"+61 3 5152 1666",
    "sg:postcode":"3875",
    "sg:province":"VIC",
    "wof:name":"O2party",
    "wof:placetype":"venue"
},
  "geometry": {"coordinates":[147.62901306099999,-37.8258399963],"type":"Point"}
}