{
  "type": "Feature",
  "properties": {
    "iso:country":"AU",
    "sg:address":"PO Box 1591",
    "sg:city":"Hornsby Northgate",
    "sg:classifiers":[
        {
            "category":"Building & Trades",
            "subcategory":"Landscaping Services",
            "type":"Services"
        }
    ],
    "sg:phone":"+61 2 9482 2741",
    "sg:postcode":"2077",
    "sg:province":"NSW",
    "sg:tags":[
        "market"
    ],
    "wof:name":"Rowan's Market Line",
    "wof:placetype":"venue"
},
  "geometry": {"coordinates":[151.09991455100001,-33.7072372437],"type":"Point"}
}