{
  "type": "Feature",
  "properties": {
    "addr:full":"85- 87 John St Coonabarabran NSW 2357",
    "addr:housenumber":"87",
    "addr:postcode":"2357",
    "addr:street":"John St",
    "iso:country":"AU",
    "sg:address":"85- 87 John St",
    "sg:city":"Coonabarabran",
    "sg:classifiers":[
        {
            "category":"Autos & Motor Vehicles",
            "subcategory":"Fuel & Gas Station",
            "type":"Retail Goods"
        }
    ],
    "sg:phone":"+61 2 6842 1340",
    "sg:postcode":"2357",
    "sg:province":"NSW",
    "wof:name":"Bogas",
    "wof:placetype":"venue"
},
  "geometry": {"coordinates":[149.27748107900001,-31.273979187],"type":"Point"}
}