{
  "type": "Feature",
  "properties": {
    "addr:full":"39 Merino Drv Shepparton VIC 3630",
    "addr:housenumber":"39",
    "addr:postcode":"3630",
    "addr:street":"Merino Drv",
    "iso:country":"AU",
    "sg:address":"39 Merino Drv",
    "sg:city":"Shepparton",
    "sg:classifiers":[
        {
            "category":"Professional",
            "subcategory":"Art Services",
            "type":"Services"
        }
    ],
    "sg:phone":"+61 421 563 939",
    "sg:postcode":"3630",
    "sg:province":"VIC",
    "sg:tags":[
        "interior",
        "decorator"
    ],
    "wof:name":"Allure Interior Decorators",
    "wof:placetype":"venue"
},
  "geometry": {"coordinates":[145.412200928,-36.3493652344],"type":"Point"}
}