{
  "type": "Feature",
  "properties": {
    "addr:full":"135 St Georges Rd Fitzroy North VIC 3068",
    "addr:housenumber":"135",
    "addr:postcode":"3068",
    "addr:street":"St Georges Rd",
    "iso:country":"AU",
    "sg:address":"135 St Georges Rd",
    "sg:city":"Fitzroy North",
    "sg:classifiers":[
        {
            "category":"Real Estate",
            "subcategory":"Architect",
            "type":"Services"
        }
    ],
    "sg:phone":"+61 3 9482 3504",
    "sg:postcode":"3068",
    "sg:province":"VIC",
    "wof:name":"Zen Architects",
    "wof:placetype":"venue"
},
  "geometry": {"coordinates":[144.981002808,-37.7863121033],"type":"Point"}
}