{
  "type": "Feature",
  "properties": {
    "addr:full":"7 Bright St Campbellfield VIC 3061",
    "addr:housenumber":"7",
    "addr:postcode":"3061",
    "addr:street":"Bright St",
    "iso:country":"AU",
    "sg:address":"7 Bright St",
    "sg:city":"Campbellfield",
    "sg:classifiers":[
        {
            "category":"Building & Trades",
            "subcategory":"Cleaning & Sanitation",
            "type":"Services"
        }
    ],
    "sg:phone":"+61 3 9357 7646",
    "sg:postcode":"3061",
    "sg:province":"VIC",
    "sg:tags":[
        "chemical",
        "pressure",
        "steam",
        "contractor"
    ],
    "wof:name":"Tamgul Cleaning Services",
    "wof:placetype":"venue"
},
  "geometry": {"coordinates":[144.95140075699999,-37.6673583984],"type":"Point"}
}