{
  "type": "Feature",
  "properties": {
    "addr:full":"7 Edward St Bendigo VIC 3550",
    "addr:housenumber":"7",
    "addr:postcode":"3550",
    "addr:street":"Edward St",
    "iso:country":"AU",
    "sg:address":"7 Edward St",
    "sg:city":"Bendigo",
    "sg:classifiers":[
        {
            "category":"Shopping",
            "subcategory":"Shoes",
            "type":"Retail Goods"
        }
    ],
    "sg:phone":"+61 3 5443 8680",
    "sg:postcode":"3550",
    "sg:province":"VIC",
    "sg:tags":[
        "footwear"
    ],
    "wof:name":"Footwear Solutions",
    "wof:placetype":"venue"
},
  "geometry": {"coordinates":[144.28013610799999,-36.7641029358],"type":"Point"}
}