{
  "type": "Feature",
  "properties": {
    "addr:full":"205-207 Ballarat Rd Maidstone VIC 3012",
    "addr:housenumber":"205-207",
    "addr:postcode":"3012",
    "addr:street":"Ballarat Rd",
    "iso:country":"AU",
    "sg:address":"205-207 Ballarat Rd",
    "sg:city":"Maidstone",
    "sg:classifiers":[
        {
            "category":"Autos & Motor Vehicles",
            "subcategory":"Automobile Sales",
            "type":"Retail Goods"
        }
    ],
    "sg:phone":"+61 3 9318 1444",
    "sg:postcode":"3012",
    "sg:province":"VIC",
    "sg:tags":[
        "car",
        "used"
    ],
    "wof:name":"Simon's Car Sales Pty Ltd",
    "wof:placetype":"venue"
},
  "geometry": {"coordinates":[144.865631103,-37.7816123962],"type":"Point"}
}