{
  "type": "Feature",
  "properties": {
    "addr:full":"Cnr Church & Harold Sts Parramatta NSW 2150",
    "addr:postcode":"2150",
    "iso:country":"AU",
    "sg:address":"Cnr Church & Harold Sts",
    "sg:city":"Parramatta",
    "sg:classifiers":[
        {
            "category":"Fast Food",
            "type":"Food & Drink"
        }
    ],
    "sg:phone":"+61 2 9481 1111",
    "sg:postcode":"2150",
    "sg:province":"NSW",
    "sg:tags":[
        "away",
        "take"
    ],
    "wof:name":"Pizza Hut",
    "wof:placetype":"venue"
},
  "geometry": {"coordinates":[151.00668335,-33.81483078],"type":"Point"}
}