{
  "type": "Feature",
  "properties": {
    "addr:full":"13 Treforest Drv Clayton VIC 3168",
    "addr:housenumber":"13",
    "addr:postcode":"3168",
    "addr:street":"Treforest Drv",
    "iso:country":"AU",
    "sg:address":"13 Treforest Drv",
    "sg:city":"Clayton",
    "sg:classifiers":[
        {
            "category":"Manufacturing",
            "subcategory":"Metals",
            "type":"Manufacturing & Wholesale Goods"
        }
    ],
    "sg:phone":"+61 3 9544 6605",
    "sg:postcode":"3168",
    "sg:province":"VIC",
    "sg:tags":[
        "steel",
        "fabricator",
        "mfrs"
    ],
    "wof:name":"J.M.G. Engineering",
    "wof:placetype":"venue"
},
  "geometry": {"coordinates":[145.131988525,-37.9215049744],"type":"Point"}
}