{
  "type": "Feature",
  "properties": {
    "addr:full":"41 King Edward Rd Osborne Park WA 6017",
    "addr:housenumber":"41",
    "addr:postcode":"6017",
    "addr:street":"King Edward Rd",
    "iso:country":"AU",
    "sg:address":"41 King Edward Rd",
    "sg:city":"Osborne Park",
    "sg:classifiers":[
        {
            "category":"Wholesale",
            "subcategory":"Electrical",
            "type":"Manufacturing & Wholesale Goods"
        }
    ],
    "sg:phone":"+61 8 9244 2346",
    "sg:postcode":"6017",
    "sg:province":"WA",
    "sg:tags":[
        "control",
        "equipment",
        "switch"
    ],
    "wof:name":"Almos Systems Pty Ltd",
    "wof:placetype":"venue"
},
  "geometry": {"coordinates":[115.809310913,-31.9000988007],"type":"Point"}
}