{
  "type": "Feature",
  "properties": {
    "addr:full":"Albert St Wickham NSW 2293",
    "addr:postcode":"2293",
    "addr:street":"Albert St",
    "iso:country":"AU",
    "sg:address":"Albert St",
    "sg:city":"Wickham",
    "sg:classifiers":[
        {
            "category":"Sports & Exercise",
            "subcategory":"Tennis Court",
            "type":"Entertainment"
        }
    ],
    "sg:phone":"+61 2 4961 6535",
    "sg:postcode":"2293",
    "sg:province":"NSW",
    "sg:tags":[
        "badminton"
    ],
    "wof:name":"Badminton Hunter",
    "wof:placetype":"venue"
},
  "geometry": {"coordinates":[151.757354736,-32.9184074402],"type":"Point"}
}