{
  "type": "Feature",
  "properties": {
    "addr:full":"Shop 7, BiLo Shopping Centre Bucasia Rd Nindaroo QLD 4740",
    "addr:housenumber":"shop 7",
    "addr:postcode":"4740",
    "addr:street":"Bilo Shopping;Bucasia Rd",
    "iso:country":"AU",
    "sg:address":"Shop 7, BiLo Shopping Centre Bucasia Rd",
    "sg:city":"Nindaroo",
    "sg:classifiers":[
        {
            "category":"Food & Beverages",
            "subcategory":"Liquor & Beverages",
            "type":"Retail Goods"
        }
    ],
    "sg:phone":"+61 7 4954 7644",
    "sg:postcode":"4740",
    "sg:province":"QLD",
    "sg:tags":[
        "store"
    ],
    "wof:name":"Northern Beaches Cellars",
    "wof:placetype":"venue"
},
  "geometry": {"coordinates":[149.132462,-21.06847],"type":"Point"}
}