{
  "type": "Feature",
  "properties": {
    "addr:full":"403 Marion Rd Plympton SA 5038",
    "addr:housenumber":"403",
    "addr:postcode":"5038",
    "addr:street":"Marion Rd",
    "iso:country":"AU",
    "sg:address":"403 Marion Rd",
    "sg:city":"Plympton",
    "sg:classifiers":[
        {
            "category":"Real Estate",
            "subcategory":"Real Estate Agent",
            "type":"Services"
        }
    ],
    "sg:phone":"+61 8 8271 8117",
    "sg:postcode":"5038",
    "sg:province":"SA",
    "wof:name":"Laycock John R Real Estate",
    "wof:placetype":"venue"
},
  "geometry": {"coordinates":[138.55502319300001,-34.965133667],"type":"Point"}
}