{
  "type": "Feature",
  "properties": {
    "addr:full":"31 Ormond St Ascot QLD 4007",
    "addr:housenumber":"31",
    "addr:postcode":"4007",
    "addr:street":"Ormond St",
    "iso:country":"AU",
    "sg:address":"31 Ormond St",
    "sg:city":"Ascot",
    "sg:classifiers":[
        {
            "category":"Manufacturing",
            "subcategory":"Rubber & Plastics",
            "type":"Manufacturing & Wholesale Goods"
        }
    ],
    "sg:phone":"+61 7 3314 8338",
    "sg:postcode":"4007",
    "sg:province":"QLD",
    "sg:tags":[
        "equipment",
        "card"
    ],
    "wof:name":"Xpress Plastic Cards Aust",
    "wof:placetype":"venue"
},
  "geometry": {"coordinates":[153.059494,-27.428644],"type":"Point"}
}