{
  "type": "Feature",
  "properties": {
    "iso:country":"AU",
    "sg:address":"Factory 7 61 Russell St",
    "sg:city":"Werribee",
    "sg:classifiers":[
        {
            "category":"Landmark",
            "subcategory":"Scenic View",
            "type":"Public Place"
        }
    ],
    "sg:phone":"+61 3 9749 7100",
    "sg:postcode":"3030",
    "sg:province":"VIC",
    "sg:tags":[
        "staircase",
        "handrail"
    ],
    "wof:name":"D & C Staircases",
    "wof:placetype":"venue"
},
  "geometry": {"coordinates":[144.66012599999999,-37.911362],"type":"Point"}
}