{
  "type": "Feature",
  "properties": {
    "addr:full":"U20/ 191 Parramatta Rd Auburn NSW 2144",
    "addr:housenumber":"191",
    "addr:postcode":"2144",
    "addr:street":"/;Parramatta Rd",
    "iso:country":"AU",
    "sg:address":"U20/ 191 Parramatta Rd",
    "sg:city":"Auburn",
    "sg:classifiers":[
        {
            "category":"Shopping",
            "subcategory":"Computers & Home Electronics",
            "type":"Retail Goods"
        }
    ],
    "sg:phone":"+61 2 9737 8809",
    "sg:postcode":"2144",
    "sg:province":"NSW",
    "sg:tags":[
        "hardware",
        "equipment"
    ],
    "wof:name":"Peridyme Pty Ltd",
    "wof:placetype":"venue"
},
  "geometry": {"coordinates":[151.03492736800001,-33.8406944275],"type":"Point"}
}