{
  "type": "Feature",
  "properties": {
    "addr:full":"332 Napoleon Reef Rd Walang NSW 2795",
    "addr:housenumber":"332",
    "addr:postcode":"2795",
    "addr:street":"Napoleon Reef Rd",
    "iso:country":"AU",
    "sg:address":"332 Napoleon Reef Rd",
    "sg:city":"Walang",
    "sg:classifiers":[
        {
            "category":"Professional",
            "subcategory":"Business Services",
            "type":"Services"
        }
    ],
    "sg:phone":"+61 2 6337 5153",
    "sg:postcode":"2795",
    "sg:province":"NSW",
    "sg:tags":[
        "drafting"
    ],
    "wof:name":"MoeMac Design & Drafting",
    "wof:placetype":"venue"
},
  "geometry": {"coordinates":[149.75880432100001,-33.4367103577],"type":"Point"}
}