{
  "type": "Feature",
  "properties": {
    "addr:full":"PO Box 1780 Noosaville DC QLD 4566",
    "addr:postcode":"4566",
    "iso:country":"AU",
    "sg:address":"PO Box 1780",
    "sg:city":"Noosaville DC",
    "sg:classifiers":[
        {
            "category":"Professional",
            "subcategory":"Detective & Security Services",
            "type":"Services"
        }
    ],
    "sg:phone":"+61 417 744 625",
    "sg:postcode":"4566",
    "sg:province":"QLD",
    "sg:tags":[
        "consultant",
        "system"
    ],
    "wof:name":"Noosa Protective Services",
    "wof:placetype":"venue"
},
  "geometry": {"coordinates":[153.05848693900001,-26.4247493744],"type":"Point"}
}