{
  "type": "Feature",
  "properties": {
    "addr:full":"First Floor, 100 Collins St Melbourne VIC 3000",
    "addr:housenumber":"100",
    "addr:postcode":"3000",
    "addr:street":"First Floor;Collins St",
    "iso:country":"AU",
    "sg:address":"First Floor, 100 Collins St",
    "sg:city":"Melbourne",
    "sg:classifiers":[
        {
            "category":"Health Services",
            "subcategory":"Dentist",
            "type":"Services"
        }
    ],
    "sg:phone":"+61 3 9654 8977",
    "sg:postcode":"3000",
    "sg:province":"VIC",
    "sg:tags":[
        "dental",
        "prosthetist"
    ],
    "wof:name":"Dental Clinic",
    "wof:placetype":"venue"
},
  "geometry": {"coordinates":[144.97006225600001,-37.8143196106],"type":"Point"}
}