{
  "type": "Feature",
  "properties": {
    "addr:full":"2/ 13 Neutron Pl Rowville VIC 3178",
    "addr:housenumber":"/ 13",
    "addr:postcode":"3178",
    "addr:street":"Neutron Pl",
    "iso:country":"AU",
    "sg:address":"2/ 13 Neutron Pl",
    "sg:city":"Rowville",
    "sg:classifiers":[
        {
            "category":"Structure",
            "subcategory":"Building",
            "type":"Public Place"
        }
    ],
    "sg:phone":"+61 3 9763 3444",
    "sg:postcode":"3178",
    "sg:province":"VIC",
    "sg:tags":[
        "sail",
        "shade"
    ],
    "wof:name":"Life-Style Canvass Goods Pty Ltd",
    "wof:placetype":"venue"
},
  "geometry": {"coordinates":[145.24688720699999,-37.906791687],"type":"Point"}
}