{
  "type": "Feature",
  "properties": {
    "iso:country":"AU",
    "sg:address":"3/ 251 Princess Hwy",
    "sg:city":"Unanderra",
    "sg:classifiers":[
        {
            "category":"Building & Trades",
            "subcategory":"Construction",
            "type":"Services"
        }
    ],
    "sg:phone":"+61 2 4271 1585",
    "sg:postcode":"2526",
    "sg:province":"NSW",
    "sg:tags":[
        "contractor"
    ],
    "wof:name":"Banfield Builders",
    "wof:placetype":"venue"
},
  "geometry": {"coordinates":[150.830154419,-34.4674568176],"type":"Point"}
}