{
  "type": "Feature",
  "properties": {
    "addr:full":"2/ 483 Dean St Albury NSW 2640",
    "addr:housenumber":"/ 483",
    "addr:postcode":"2640",
    "addr:street":"Dean St",
    "iso:country":"AU",
    "sg:address":"2/ 483 Dean St",
    "sg:city":"Albury",
    "sg:classifiers":[
        {
            "category":"Shopping",
            "subcategory":"Gifts & Souvenirs",
            "type":"Retail Goods"
        }
    ],
    "sg:phone":"+61 2 6021 3050",
    "sg:postcode":"2640",
    "sg:province":"NSW",
    "sg:tags":[
        "print",
        "poster",
        "pictures"
    ],
    "wof:name":"Get Framed",
    "wof:placetype":"venue"
},
  "geometry": {"coordinates":[146.91212463400001,-36.080368042],"type":"Point"}
}