{
  "type": "Feature",
  "properties": {
    "addr:full":"41 Lawson St Warren NSW 2824",
    "addr:housenumber":"41",
    "addr:postcode":"2824",
    "addr:street":"Lawson St",
    "iso:country":"AU",
    "sg:address":"41 Lawson St",
    "sg:city":"Warren",
    "sg:classifiers":[
        {
            "category":"Personal",
            "subcategory":"Beauty Salon",
            "type":"Services"
        }
    ],
    "sg:phone":"+61 2 6847 4418",
    "sg:postcode":"2824",
    "sg:province":"NSW",
    "sg:tags":[
        "hairdresser"
    ],
    "wof:name":"Comb N Cutter Hair Salon",
    "wof:placetype":"venue"
},
  "geometry": {"coordinates":[147.83619689899999,-31.69830513],"type":"Point"}
}