{
  "type": "Feature",
  "properties": {
    "iso:country":"AU",
    "sg:address":"2/ 341 Great Western Hwy",
    "sg:city":"St Marys",
    "sg:classifiers":[
        {
            "category":"Banks & Credit Unions",
            "subcategory":"Bureau De Change",
            "type":"Services"
        }
    ],
    "sg:phone":"+61 2 9833 2700",
    "sg:postcode":"2760",
    "sg:province":"NSW",
    "sg:tags":[
        "repairs",
        "part",
        "appliance",
        "electrical"
    ],
    "wof:name":"Australian Hot Water & Stove Service",
    "wof:placetype":"venue"
},
  "geometry": {"coordinates":[150.77117919899999,-33.769443512],"type":"Point"}
}