{
  "type": "Feature",
  "properties": {
    "iso:country":"AU",
    "sg:address":"102c Charters Towers Rd",
    "sg:city":"Hermit Park",
    "sg:classifiers":[
        {
            "category":"Fast Food",
            "type":"Food & Drink"
        }
    ],
    "sg:phone":"+61 7 4771 5975",
    "sg:postcode":"4812",
    "sg:province":"QLD",
    "sg:tags":[
        "away",
        "take"
    ],
    "wof:name":"Hermit Park Munchies",
    "wof:placetype":"venue"
},
  "geometry": {"coordinates":[146.80105599999999,-19.276005],"type":"Point"}
}