{
  "type": "Feature",
  "properties": {
    "addr:full":"96 Haven Rd Pullenvale QLD 4069",
    "addr:housenumber":"96",
    "addr:postcode":"4069",
    "addr:street":"Haven Rd",
    "iso:country":"AU",
    "sg:address":"96 Haven Rd",
    "sg:city":"Pullenvale",
    "sg:classifiers":[
        {
            "category":"Professional",
            "subcategory":"Detective & Security Services",
            "type":"Services"
        }
    ],
    "sg:phone":"+61 7 3374 2854",
    "sg:postcode":"4069",
    "sg:province":"QLD",
    "sg:tags":[
        "consultant",
        "system"
    ],
    "wof:name":"Mondami Pty Ltd",
    "wof:placetype":"venue"
},
  "geometry": {"coordinates":[152.89065551799999,-27.509185791],"type":"Point"}
}