{
  "type": "Feature",
  "properties": {
    "iso:country":"AU",
    "sg:address":"PO Box 13",
    "sg:city":"Hamilton",
    "sg:classifiers":[
        {
            "category":"Retail",
            "subcategory":"Repair Shop",
            "type":"Services"
        }
    ],
    "sg:phone":"+61 402 223 133",
    "sg:postcode":"2303",
    "sg:province":"NSW",
    "sg:tags":[
        "windscreen"
    ],
    "wof:name":"GT Glass Technology",
    "wof:placetype":"venue"
},
  "geometry": {"coordinates":[151.746994,-32.923489],"type":"Point"}
}