{
  "type": "Feature",
  "properties": {
    "iso:country":"AU",
    "sg:address":"405- 409 Upper Heidelberg Rd",
    "sg:city":"Heidelberg",
    "sg:classifiers":[
        {
            "category":"Social Services",
            "subcategory":"Retirement Home",
            "type":"Services"
        }
    ],
    "sg:phone":"+61 3 9458 4619",
    "sg:postcode":"3084",
    "sg:province":"VIC",
    "sg:tags":[
        "accommodation",
        "special"
    ],
    "wof:name":"Third Age Consultants",
    "wof:placetype":"venue"
},
  "geometry": {"coordinates":[145.054321289,-37.7570991516],"type":"Point"}
}