{
  "type": "Feature",
  "properties": {
    "iso:country":"AU",
    "sg:address":"U4/ 18-20 Chapel St",
    "sg:city":"Rockdale",
    "sg:classifiers":[
        {
            "category":"Building & Trades",
            "subcategory":"Equipment Rental",
            "type":"Services"
        }
    ],
    "sg:phone":"+61 412 034 654",
    "sg:postcode":"2216",
    "sg:province":"NSW",
    "sg:tags":[
        "supply",
        "catering"
    ],
    "wof:name":"Bioplates",
    "wof:placetype":"venue"
},
  "geometry": {"coordinates":[151.14016699999999,-33.954945],"type":"Point"}
}