{
  "type": "Feature",
  "properties": {
    "iso:country":"AU",
    "sg:address":"Pavilion A Centennial Parklands Equestrian Centre Lang Rd",
    "sg:city":"Centennial Park",
    "sg:classifiers":[
        {
            "category":"Communications",
            "subcategory":"News Services",
            "type":"Services"
        }
    ],
    "sg:phone":"+61 2 9360 8747",
    "sg:postcode":"2021",
    "sg:province":"NSW",
    "sg:tags":[
        "information",
        "tourist",
        "attractions"
    ],
    "wof:name":"Moore Park Stables",
    "wof:placetype":"venue"
},
  "geometry": {"coordinates":[151.230667114,-33.8945121765],"type":"Point"}
}