{
  "type": "Feature",
  "properties": {
    "addr:full":"Shop 3, 23 Quondola St Pambula NSW 2549",
    "addr:housenumber":"shop;23",
    "addr:postcode":"2549",
    "addr:street":"Quondola St",
    "iso:country":"AU",
    "sg:address":"Shop 3, 23 Quondola St",
    "sg:city":"Pambula",
    "sg:classifiers":[
        {
            "category":"Personal",
            "subcategory":"Beauty Salon",
            "type":"Services"
        }
    ],
    "sg:phone":"+61 2 6495 6007",
    "sg:postcode":"2549",
    "sg:province":"NSW",
    "sg:tags":[
        "hairdresser"
    ],
    "wof:name":"Pambula Hair & Beauty",
    "wof:placetype":"venue"
},
  "geometry": {"coordinates":[149.87448120100001,-36.929775238],"type":"Point"}
}