{
  "type": "Feature",
  "properties": {
    "addr:full":"90 Olives La St Andrews VIC 3761",
    "addr:housenumber":"90",
    "addr:postcode":"3761",
    "addr:street":"Olives La",
    "iso:country":"AU",
    "sg:address":"90 Olives La St",
    "sg:city":"Andrews",
    "sg:classifiers":[
        {
            "category":"Professional",
            "subcategory":"Computer Services",
            "type":"Services"
        }
    ],
    "sg:phone":"+61 3 9710 1884",
    "sg:postcode":"3761",
    "sg:province":"VIC",
    "sg:tags":[
        "consultant",
        "system"
    ],
    "wof:name":"QTM",
    "wof:placetype":"venue"
},
  "geometry": {"coordinates":[145.30287170400001,-37.5788536072],"type":"Point"}
}