{
  "type": "Feature",
  "properties": {
    "addr:full":"31 Production Ave Molendinar QLD 4214",
    "addr:housenumber":"31",
    "addr:postcode":"4214",
    "addr:street":"Production Ave",
    "iso:country":"AU",
    "sg:address":"31 Production Ave",
    "sg:city":"Molendinar",
    "sg:phone":"+61 7 5574 4411",
    "sg:postcode":"4214",
    "sg:province":"QLD",
    "wof:name":"Filter Tech Sales",
    "wof:placetype":"venue"
},
  "geometry": {"coordinates":[153.367721558,-27.9651489258],"type":"Point"}
}