{
  "type": "Feature",
  "properties": {
    "iso:country":"AU",
    "sg:address":"PO Box 29",
    "sg:city":"Vinifera",
    "sg:classifiers":[
        {
            "category":"Building & Trades",
            "subcategory":"Cleaning & Sanitation",
            "type":"Services"
        }
    ],
    "sg:phone":"+61 408 325 664",
    "sg:postcode":"3591",
    "sg:province":"VIC",
    "sg:tags":[
        "tank",
        "septic"
    ],
    "wof:name":"Vernons Plumbing",
    "wof:placetype":"venue"
},
  "geometry": {"coordinates":[143.40153503400001,-35.2126197815],"type":"Point"}
}