{
  "type": "Feature",
  "properties": {
    "addr:full":"82 Doggett St Newstead QLD 4006",
    "addr:housenumber":"82",
    "addr:postcode":"4006",
    "addr:street":"Doggett St",
    "iso:country":"AU",
    "sg:address":"82 Doggett St",
    "sg:city":"Newstead",
    "sg:classifiers":[
        {
            "category":"Home & Garden",
            "subcategory":"Kitchen Supply",
            "type":"Retail Goods"
        }
    ],
    "sg:phone":"+61 7 3257 4969",
    "sg:postcode":"4006",
    "sg:province":"QLD",
    "sg:tags":[
        "equipment",
        "diving"
    ],
    "wof:name":"Custom Wetsuit Designs",
    "wof:placetype":"venue"
},
  "geometry": {"coordinates":[153.04364013700001,-27.4515380859],"type":"Point"}
}