{
  "type": "Feature",
  "properties": {
    "addr:full":"54 Tiarri Ave Terrey Hills NSW 2084",
    "addr:housenumber":"54",
    "addr:postcode":"2084",
    "addr:street":"Tiarri Ave",
    "iso:country":"AU",
    "sg:address":"54 Tiarri Ave",
    "sg:city":"Terrey Hills",
    "sg:classifiers":[
        {
            "category":"Education",
            "subcategory":"School",
            "type":"Public Place"
        }
    ],
    "sg:phone":"+61 2 9450 1697",
    "sg:postcode":"2084",
    "sg:province":"NSW",
    "sg:tags":[
        "supply"
    ],
    "wof:name":"By Jingo Design & Computer Consulting",
    "wof:placetype":"venue"
},
  "geometry": {"coordinates":[151.22067260700001,-33.683391571],"type":"Point"}
}