{
  "type": "Feature",
  "properties": {
    "addr:full":"1244 North East Rd St Agnes SA 5097",
    "addr:housenumber":"1244",
    "addr:postcode":"5097",
    "addr:street":"North East Rd",
    "iso:country":"AU",
    "sg:address":"1244 North East Rd St",
    "sg:city":"Agnes",
    "sg:classifiers":[
        {
            "category":"Cafe",
            "type":"Food & Drink"
        }
    ],
    "sg:phone":"+61 8 8264 5562",
    "sg:postcode":"5097",
    "sg:province":"SA",
    "wof:name":"St Agnes Gourmet Foods",
    "wof:placetype":"venue"
},
  "geometry": {"coordinates":[138.71531677199999,-34.8213806152],"type":"Point"}
}