{
  "type": "Feature",
  "properties": {
    "addr:full":"Unit 10/ 70 Holbeche Rd Arndell Park NSW 2148",
    "addr:housenumber":"/ 70",
    "addr:postcode":"2148",
    "addr:street":"Holbeche Rd",
    "iso:country":"AU",
    "sg:address":"Unit 10/ 70 Holbeche Rd",
    "sg:city":"Arndell Park",
    "sg:classifiers":[
        {
            "category":"Autos & Motor Vehicles",
            "subcategory":"Auto Supplies",
            "type":"Retail Goods"
        }
    ],
    "sg:phone":"+61 2 9679 8644",
    "sg:postcode":"2148",
    "sg:province":"NSW",
    "sg:tags":[
        "accessory"
    ],
    "wof:name":"V-Sport Australia",
    "wof:placetype":"venue"
},
  "geometry": {"coordinates":[150.893875122,-33.7959785461],"type":"Point"}
}