{
  "type": "Feature",
  "properties": {
    "iso:country":"AU",
    "sg:address":"123 Aberdeen St",
    "sg:city":"Northbridge",
    "sg:classifiers":[
        {
            "category":"Building & Trades",
            "subcategory":"Locksmith",
            "type":"Services"
        }
    ],
    "sg:phone":"+61 8 9227 1163",
    "sg:postcode":"6003",
    "sg:province":"WA",
    "sg:tags":[
        "lock"
    ],
    "wof:name":"Master Locksmiths",
    "wof:placetype":"venue"
},
  "geometry": {"coordinates":[115.857078552,-31.9457550049],"type":"Point"}
}