{
  "type": "Feature",
  "properties": {
    "addr:full":"10 Pickford St Prahran VIC 3181",
    "addr:housenumber":"10",
    "addr:postcode":"3181",
    "addr:street":"Pickford St",
    "iso:country":"AU",
    "sg:address":"10 Pickford St",
    "sg:city":"Prahran",
    "sg:classifiers":[
        {
            "category":"Education",
            "subcategory":"Special Training",
            "type":"Public Place"
        }
    ],
    "sg:phone":"+61 3 9529 8905",
    "sg:postcode":"3181",
    "sg:province":"VIC",
    "sg:tags":[
        "development"
    ],
    "sg:website":"http://www.corporatemediaservices.com.au",
    "wof:name":"Corporate Media Services",
    "wof:placetype":"venue"
},
  "geometry": {"coordinates":[145.00677490199999,-37.8569717407],"type":"Point"}
}