{
  "type": "Feature",
  "properties": {
    "addr:full":"30 Talbragar St Dubbo NSW 2830",
    "addr:housenumber":"30",
    "addr:postcode":"2830",
    "addr:street":"Talbragar St",
    "iso:country":"AU",
    "sg:address":"30 Talbragar St",
    "sg:city":"Dubbo",
    "sg:classifiers":[
        {
            "category":"Health Services",
            "subcategory":"Optometrist",
            "type":"Services"
        }
    ],
    "sg:phone":"+61 2 6884 3011",
    "sg:postcode":"2830",
    "sg:province":"NSW",
    "wof:name":"Bemrose Colin J",
    "wof:placetype":"venue"
},
  "geometry": {"coordinates":[148.602584839,-32.2448120117],"type":"Point"}
}