{
  "type": "Feature",
  "properties": {
    "addr:full":"Unit 10, Kiama Court 8 Kiama St Bowral NSW 2576",
    "addr:housenumber":"8",
    "addr:postcode":"2576",
    "addr:street":"Kiama;Kiama St",
    "iso:country":"AU",
    "sg:address":"Unit 10, Kiama Court 8 Kiama St",
    "sg:city":"Bowral",
    "sg:classifiers":[
        {
            "category":"Retail",
            "subcategory":"Repair Shop",
            "type":"Services"
        }
    ],
    "sg:phone":"+61 422 129 123",
    "sg:postcode":"2576",
    "sg:province":"NSW",
    "sg:tags":[
        "upholsterer"
    ],
    "wof:name":"Richos Marine Trim",
    "wof:placetype":"venue"
},
  "geometry": {"coordinates":[150.40864563,-34.4858627319],"type":"Point"}
}