{
  "type": "Feature",
  "properties": {
    "iso:country":"AU",
    "sg:address":"29- 31 Scoresby St",
    "sg:city":"Kerang",
    "sg:classifiers":[
        {
            "category":"Wholesale",
            "subcategory":"Medical Equipment & Supplies",
            "type":"Manufacturing & Wholesale Goods"
        }
    ],
    "sg:phone":"+61 3 5452 2555",
    "sg:postcode":"3579",
    "sg:province":"VIC",
    "sg:tags":[
        "scooter",
        "mobility"
    ],
    "wof:name":"Bolwell Mobility",
    "wof:placetype":"venue"
},
  "geometry": {"coordinates":[143.91929626500001,-35.73279953],"type":"Point"}
}