{
  "type": "Feature",
  "properties": {
    "addr:full":"66 Mountford Ave Guildford NSW 2161",
    "addr:housenumber":"66",
    "addr:postcode":"2161",
    "addr:street":"Mountford Ave",
    "iso:country":"AU",
    "sg:address":"66 Mountford Ave",
    "sg:city":"Guildford",
    "sg:classifiers":[
        {
            "category":"Professional",
            "subcategory":"Printing & Photocopies",
            "type":"Services"
        }
    ],
    "sg:phone":"+61 2 9721 1464",
    "sg:postcode":"2161",
    "sg:province":"NSW",
    "sg:tags":[
        "photocopier"
    ],
    "wof:name":"Black & White Office Services",
    "wof:placetype":"venue"
},
  "geometry": {"coordinates":[150.988647461,-33.8523483276],"type":"Point"}
}