{
  "type": "Feature",
  "properties": {
    "addr:full":"Lvl1/ Park Rd Hurstville NSW 2220",
    "addr:postcode":"2220",
    "addr:street":"Rd",
    "iso:country":"AU",
    "sg:address":"Lvl1/ Park Rd",
    "sg:city":"Hurstville",
    "sg:classifiers":[
        {
            "category":"Personal",
            "subcategory":"Beauty Salon",
            "type":"Services"
        }
    ],
    "sg:phone":"+61 2 9570 4543",
    "sg:postcode":"2220",
    "sg:province":"NSW",
    "wof:name":"Care Ceuticals Medi Spa",
    "wof:placetype":"venue"
},
  "geometry": {"coordinates":[151.10104370100001,-33.9671897888],"type":"Point"}
}