{
  "type": "Feature",
  "properties": {
    "addr:full":"3 Development Crt Caloundra QLD 4551",
    "addr:housenumber":"3",
    "addr:postcode":"4551",
    "addr:street":"Development Crt",
    "iso:country":"AU",
    "sg:address":"3 Development Crt",
    "sg:city":"Caloundra",
    "sg:classifiers":[
        {
            "category":"Building & Trades",
            "subcategory":"Construction",
            "type":"Services"
        }
    ],
    "sg:phone":"+61 7 5492 8801",
    "sg:postcode":"4551",
    "sg:province":"QLD",
    "sg:tags":[
        "contractor"
    ],
    "wof:name":"Chadmont Pty.Ltd.",
    "wof:placetype":"venue"
},
  "geometry": {"coordinates":[153.116653442,-26.7962799072],"type":"Point"}
}