{
  "type": "Feature",
  "properties": {
    "addr:full":"Suite 4, City West Business Cntr, Railway Pde West Perth WA 6005",
    "addr:postcode":"6005",
    "addr:street":"Railway Pde",
    "iso:country":"AU",
    "sg:address":"Suite 4, City West Business Cntr, Railway Pde",
    "sg:city":"West Perth",
    "sg:classifiers":[
        {
            "category":"Professional",
            "subcategory":"Accounting & Tax Preparation",
            "type":"Services"
        }
    ],
    "sg:phone":"+61 1300 306 301",
    "sg:postcode":"6005",
    "sg:province":"WA",
    "sg:tags":[
        "accountant",
        "auditor"
    ],
    "wof:name":"Accounting For Small Business",
    "wof:placetype":"venue"
},
  "geometry": {"coordinates":[115.841667175,-31.943271637],"type":"Point"}
}