{
  "type": "Feature",
  "properties": {
    "iso:country":"AU",
    "sg:address":"Harbours Rd",
    "sg:city":"Yendon",
    "sg:classifiers":[
        {
            "category":"Mining & Drilling",
            "type":"Manufacturing & Wholesale Goods"
        }
    ],
    "sg:phone":"+61 3 5341 7728",
    "sg:postcode":"3352",
    "sg:province":"VIC",
    "sg:tags":[
        "boring",
        "contractor"
    ],
    "wof:name":"Davies Backhoe Services Pty Ltd",
    "wof:placetype":"venue"
},
  "geometry": {"coordinates":[143.974213,-37.638325],"type":"Point"}
}