{
  "type": "Feature",
  "properties": {
    "addr:full":"PO Box 6203 South Lismore NSW 2480",
    "addr:postcode":"2480",
    "addr:street":"South",
    "iso:country":"AU",
    "sg:address":"PO Box 6203",
    "sg:city":"South Lismore",
    "sg:classifiers":[
        {
            "category":"Home & Garden",
            "subcategory":"Carpets & Floor Coverings",
            "type":"Retail Goods"
        }
    ],
    "sg:phone":"+61 412 706 697",
    "sg:postcode":"2480",
    "sg:province":"NSW",
    "sg:tags":[
        "tile",
        "wall",
        "layer"
    ],
    "wof:name":"Nick Lainchbury Tiling",
    "wof:placetype":"venue"
},
  "geometry": {"coordinates":[153.17547607399999,-28.7682113647],"type":"Point"}
}