{
  "type": "Feature",
  "properties": {
    "addr:full":"36 Duntroon St Brendale QLD 4500",
    "addr:housenumber":"36",
    "addr:postcode":"4500",
    "addr:street":"Duntroon St",
    "iso:country":"AU",
    "sg:address":"36 Duntroon St",
    "sg:city":"Brendale",
    "sg:classifiers":[
        {
            "category":"Manufacturing",
            "subcategory":"Metals",
            "type":"Manufacturing & Wholesale Goods"
        }
    ],
    "sg:phone":"+61 7 3205 3529",
    "sg:postcode":"4500",
    "sg:province":"QLD",
    "sg:tags":[
        "steel",
        "fabricator",
        "mfrs"
    ],
    "wof:name":"B & L Steel Pty Ltd",
    "wof:placetype":"venue"
},
  "geometry": {"coordinates":[152.982696533,-27.3220710754],"type":"Point"}
}