{
  "type": "Feature",
  "properties": {
    "addr:full":"1/49 Stuart St Manly NSW 2095",
    "addr:housenumber":"/ 49",
    "addr:postcode":"2095",
    "addr:street":"Stuart St",
    "iso:country":"AU",
    "sg:address":"1/49 Stuart St",
    "sg:city":"Manly",
    "sg:classifiers":[
        {
            "category":"Health Services",
            "subcategory":"Medical Lab",
            "type":"Services"
        }
    ],
    "sg:phone":"+61 2 9976 2440",
    "sg:postcode":"2095",
    "sg:province":"NSW",
    "sg:tags":[
        "laboratory",
        "pathology"
    ],
    "wof:name":"Metametrix Clinical Laboratory",
    "wof:placetype":"venue"
},
  "geometry": {"coordinates":[151.28732299800001,-33.805973053],"type":"Point"}
}