{
  "type": "Feature",
  "properties": {
    "addr:full":"Unit 1, 2150 Castlereagh Rd Penrith NSW 2750",
    "addr:housenumber":"2150",
    "addr:postcode":"2750",
    "addr:street":"Castlereagh Rd",
    "iso:country":"AU",
    "sg:address":"Unit 1, 2150 Castlereagh Rd",
    "sg:city":"Penrith",
    "sg:classifiers":[
        {
            "category":"Autos & Motor Vehicles",
            "subcategory":"Automobile Sales",
            "type":"Retail Goods"
        }
    ],
    "sg:phone":"+61 2 4722 9242",
    "sg:postcode":"2750",
    "sg:province":"NSW",
    "sg:tags":[
        "car",
        "new"
    ],
    "wof:name":"Col Wallis",
    "wof:placetype":"venue"
},
  "geometry": {"coordinates":[150.68887329099999,-33.748664856],"type":"Point"}
}