{
  "type": "Feature",
  "properties": {
    "addr:full":"10 Nowra Pl Kelmscott WA 6111",
    "addr:housenumber":"10",
    "addr:postcode":"6111",
    "addr:street":"Pl",
    "iso:country":"AU",
    "sg:address":"10 Nowra Pl",
    "sg:city":"Kelmscott",
    "sg:classifiers":[
        {
            "category":"Building & Trades",
            "subcategory":"Construction",
            "type":"Services"
        }
    ],
    "sg:phone":"+61 8 9390 3783",
    "sg:postcode":"6111",
    "sg:province":"WA",
    "sg:tags":[
        "plasterboard",
        "plasterer",
        "fixer"
    ],
    "wof:name":"de Graaf Gary",
    "wof:placetype":"venue"
},
  "geometry": {"coordinates":[116.026756287,-32.1067962646],"type":"Point"}
}