{
  "type": "Feature",
  "properties": {
    "addr:full":"50 Sutton St Chelmer QLD 4068",
    "addr:housenumber":"50",
    "addr:postcode":"4068",
    "addr:street":"Sutton St",
    "iso:country":"AU",
    "sg:address":"50 Sutton St",
    "sg:city":"Chelmer",
    "sg:classifiers":[
        {
            "category":"Wholesale",
            "subcategory":"Painting Supplies",
            "type":"Manufacturing & Wholesale Goods"
        }
    ],
    "sg:phone":"+61 7 3278 2953",
    "sg:postcode":"4068",
    "sg:province":"QLD",
    "sg:tags":[
        "product",
        "cleaning"
    ],
    "sg:website":"http://www.envirochemicals.com.au",
    "wof:name":"Enviroclean Distributors",
    "wof:placetype":"venue"
},
  "geometry": {"coordinates":[152.96890258799999,-27.5130405426],"type":"Point"}
}