{
  "type": "Feature",
  "properties": {
    "iso:country":"AU",
    "sg:address":"Suite 8 266 Trower Rd",
    "sg:city":"Casuarina",
    "sg:classifiers":[
        {
            "category":"Health Services",
            "subcategory":"Dentist",
            "type":"Services"
        }
    ],
    "sg:phone":"+61 8 8945 4022",
    "sg:postcode":"0810",
    "sg:province":"NT",
    "wof:name":"Raets Hans",
    "wof:placetype":"venue"
},
  "geometry": {"coordinates":[130.88343810999999,-12.3743743896],"type":"Point"}
}