{
  "type": "Feature",
  "properties": {
    "iso:country":"AU",
    "sg:address":"29a Chapple St",
    "sg:city":"Gladstone",
    "sg:classifiers":[
        {
            "category":"Wholesale",
            "subcategory":"Machinery & Supplies",
            "type":"Manufacturing & Wholesale Goods"
        }
    ],
    "sg:phone":"+61 7 4976 9551",
    "sg:postcode":"4680",
    "sg:province":"QLD",
    "sg:tags":[
        "process",
        "instrument",
        "control"
    ],
    "wof:name":"Transmark FCX",
    "wof:placetype":"venue"
},
  "geometry": {"coordinates":[151.24055480999999,-23.8425865173],"type":"Point"}
}