{
  "type": "Feature",
  "properties": {
    "addr:full":"Unit 31 Anthony St West End (Brisbane) QLD 4101",
    "addr:postcode":"4101",
    "addr:street":"Anthony St",
    "iso:country":"AU",
    "sg:address":"Unit 31 Anthony St",
    "sg:city":"West End (Brisbane)",
    "sg:classifiers":[
        {
            "category":"Professional",
            "subcategory":"Business Services",
            "type":"Services"
        }
    ],
    "sg:phone":"+61 7 3844 5751",
    "sg:postcode":"4101",
    "sg:province":"QLD",
    "sg:tags":[
        "fashion",
        "agent"
    ],
    "wof:name":"Associated Fashion Distributors Pty Ltd",
    "wof:placetype":"venue"
},
  "geometry": {"coordinates":[153.00747680699999,-27.4766311646],"type":"Point"}
}