{
  "type": "Feature",
  "properties": {
    "addr:full":"PO Box 479 Narrabri NSW 2390",
    "addr:postcode":"2390",
    "iso:country":"AU",
    "sg:address":"PO Box 479",
    "sg:city":"Narrabri",
    "sg:classifiers":[
        {
            "category":"Building & Trades",
            "subcategory":"Landscaping Services",
            "type":"Services"
        }
    ],
    "sg:phone":"+61 2 6792 2709",
    "sg:postcode":"2390",
    "sg:province":"NSW",
    "sg:tags":[
        "inspection"
    ],
    "wof:name":"Rose Pest Control",
    "wof:placetype":"venue"
},
  "geometry": {"coordinates":[149.766845703,-30.3389701843],"type":"Point"}
}