{
  "type": "Feature",
  "properties": {
    "addr:full":"Reiby Rd Hunters Hill NSW 2110",
    "addr:postcode":"2110",
    "addr:street":"Reiby Rd",
    "iso:country":"AU",
    "sg:address":"Reiby Rd",
    "sg:city":"Hunters Hill",
    "sg:classifiers":[
        {
            "category":"Education",
            "subcategory":"School",
            "type":"Public Place"
        }
    ],
    "sg:phone":"+61 2 9817 4565",
    "sg:postcode":"2110",
    "sg:province":"NSW",
    "sg:tags":[
        "state",
        "-",
        "nsw"
    ],
    "wof:name":"Hunters Hill High School",
    "wof:placetype":"venue"
},
  "geometry": {"coordinates":[151.147216797,-33.8322677612],"type":"Point"}
}