{
  "type": "Feature",
  "properties": {
    "iso:country":"AU",
    "sg:address":"59 Boronia Rd",
    "sg:city":"Boronia",
    "sg:classifiers":[
        {
            "category":"Arts & Performance",
            "subcategory":"Dance",
            "type":"Entertainment"
        }
    ],
    "sg:phone":"+61 3 9729 0420",
    "sg:postcode":"3155",
    "sg:province":"VIC",
    "sg:tags":[
        "theatrical",
        "ballet",
        "tuition"
    ],
    "wof:name":"Audrey Nicholls-Eve King School Of Ballet",
    "wof:placetype":"venue"
},
  "geometry": {"coordinates":[145.29139709500001,-37.8630485535],"type":"Point"}
}