{
  "type": "Feature",
  "properties": {
    "addr:full":"56 Boyanda St Wishart QLD 4122",
    "addr:housenumber":"56",
    "addr:postcode":"4122",
    "addr:street":"Boyanda St",
    "iso:country":"AU",
    "sg:address":"56 Boyanda St",
    "sg:city":"Wishart",
    "sg:classifiers":[
        {
            "category":"Professional",
            "subcategory":"Accounting & Tax Preparation",
            "type":"Services"
        }
    ],
    "sg:phone":"+61 7 3849 5227",
    "sg:postcode":"4122",
    "sg:province":"QLD",
    "sg:tags":[
        "accountant",
        "auditor"
    ],
    "wof:name":"Tomlin Accounting",
    "wof:placetype":"venue"
},
  "geometry": {"coordinates":[153.10606384299999,-27.5550823212],"type":"Point"}
}