{
  "type": "Feature",
  "properties": {
    "addr:full":"Luriston Drv Coldstream VIC 3770",
    "addr:postcode":"3770",
    "addr:street":"Luriston Drv",
    "iso:country":"AU",
    "sg:address":"Luriston Drv",
    "sg:city":"Coldstream",
    "sg:classifiers":[
        {
            "category":"Retail",
            "subcategory":"Repair Shop",
            "type":"Services"
        }
    ],
    "sg:phone":"+61 3 9739 1353",
    "sg:postcode":"3770",
    "sg:province":"VIC",
    "sg:tags":[
        "machine",
        "repairs",
        "part",
        "dryer",
        "washing"
    ],
    "wof:name":"A & B Washing Machine Service",
    "wof:placetype":"venue"
},
  "geometry": {"coordinates":[145.38583399999999,-37.724846],"type":"Point"}
}