{
  "type": "Feature",
  "properties": {
    "addr:full":"5 Phillips Drv Kangaroo Flat VIC 3555",
    "addr:housenumber":"5",
    "addr:postcode":"3555",
    "addr:street":"Phillips Drv",
    "iso:country":"AU",
    "sg:address":"5 Phillips Drv",
    "sg:city":"Kangaroo Flat",
    "sg:classifiers":[
        {
            "category":"Real Estate",
            "subcategory":"Real Estate Agent",
            "type":"Services"
        }
    ],
    "sg:phone":"+61 3 5447 7866",
    "sg:postcode":"3555",
    "sg:province":"VIC",
    "sg:tags":[
        "handyman's",
        "equipment",
        "hire",
        "builders",
        "contractor"
    ],
    "wof:name":"Wreckair",
    "wof:placetype":"venue"
},
  "geometry": {"coordinates":[144.24168395999999,-36.8075828552],"type":"Point"}
}