{
  "type": "Feature",
  "properties": {
    "addr:full":"Boonderoo Rd Tom Price WA 6751",
    "addr:postcode":"6751",
    "addr:street":"Boonderoo Rd",
    "iso:country":"AU",
    "sg:address":"Boonderoo Rd",
    "sg:city":"Tom Price",
    "sg:classifiers":[
        {
            "category":"Wholesale",
            "subcategory":"Machinery & Supplies",
            "type":"Manufacturing & Wholesale Goods"
        }
    ],
    "sg:phone":"+61 8 9188 1885",
    "sg:postcode":"6751",
    "sg:province":"WA",
    "sg:tags":[
        "equipment",
        "hydraulic"
    ],
    "wof:name":"Enzed Pilbara",
    "wof:placetype":"venue"
},
  "geometry": {"coordinates":[117.78600311300001,-22.6878852844],"type":"Point"}
}