{
  "type": "Feature",
  "properties": {
    "addr:full":"PO Box 6105 Tweed Heads South NSW 2486",
    "addr:postcode":"2486",
    "iso:country":"AU",
    "sg:address":"PO Box 6105",
    "sg:city":"Tweed Heads South",
    "sg:classifiers":[
        {
            "category":"Wholesale",
            "subcategory":"Home Furnishings",
            "type":"Manufacturing & Wholesale Goods"
        }
    ],
    "sg:phone":"+61 7 5524 1871",
    "sg:postcode":"2486",
    "sg:province":"NSW",
    "sg:tags":[
        "wholesaler",
        "bedding",
        "mfrs",
        "bed"
    ],
    "wof:name":"Mr Cabinets",
    "wof:placetype":"venue"
},
  "geometry": {"coordinates":[153.491744995,-28.213344574],"type":"Point"}
}