{
  "type": "Feature",
  "properties": {
    "addr:full":"96 Tingal Rd Wynnum QLD 4178",
    "addr:housenumber":"96",
    "addr:postcode":"4178",
    "addr:street":"Tingal Rd",
    "iso:country":"AU",
    "sg:address":"96 Tingal Rd",
    "sg:city":"Wynnum",
    "sg:classifiers":[
        {
            "category":"Communications",
            "subcategory":"Film & Video Production",
            "type":"Services"
        }
    ],
    "sg:phone":"+61 7 3396 9944",
    "sg:postcode":"4178",
    "sg:province":"QLD",
    "sg:tags":[
        "dvd",
        "library"
    ],
    "wof:name":"Blockbuster",
    "wof:placetype":"venue"
},
  "geometry": {"coordinates":[153.17181396500001,-27.446428299],"type":"Point"}
}