{
  "type": "Feature",
  "properties": {
    "addr:full":"Shp LG 11, Homemaker Centre, 18 Victoria Ave Castle Hill NSW 2154",
    "addr:housenumber":"11;18",
    "addr:postcode":"2154",
    "addr:street":"Homemaker Centre;Victoria Ave",
    "iso:country":"AU",
    "sg:address":"Shp LG 11, Homemaker Centre, 18 Victoria Ave",
    "sg:city":"Castle Hill",
    "sg:classifiers":[
        {
            "category":"Retail",
            "subcategory":"Repair Shop",
            "type":"Services"
        }
    ],
    "sg:phone":"+61 2 9894 8150",
    "sg:postcode":"2154",
    "sg:province":"NSW",
    "sg:tags":[
        "cleaner",
        "part",
        "vacuum"
    ],
    "wof:name":"Godfreys",
    "wof:placetype":"venue"
},
  "geometry": {"coordinates":[150.97825622600001,-33.7280044556],"type":"Point"}
}