{
  "type": "Feature",
  "properties": {
    "addr:full":"138 Carlisle St Glanville SA 5015",
    "addr:housenumber":"138",
    "addr:postcode":"5015",
    "addr:street":"Carlisle St",
    "iso:country":"AU",
    "sg:address":"138 Carlisle St",
    "sg:city":"Glanville",
    "sg:classifiers":[
        {
            "category":"Professional",
            "subcategory":"Engineering",
            "type":"Services"
        }
    ],
    "sg:phone":"+61 8 8449 7544",
    "sg:postcode":"5015",
    "sg:province":"SA",
    "sg:tags":[
        "engineer"
    ],
    "wof:name":"Clutterham C H Pty Ltd",
    "wof:placetype":"venue"
},
  "geometry": {"coordinates":[138.492355347,-34.8440437317],"type":"Point"}
}