{
  "type": "Feature",
  "properties": {
    "iso:country":"AU",
    "sg:address":"1003 Fairview Drv",
    "sg:city":"Albury",
    "sg:classifiers":[
        {
            "category":"Education",
            "subcategory":"Music School",
            "type":"Public Place"
        }
    ],
    "sg:phone":"+61 419 572 858",
    "sg:postcode":"2640",
    "sg:province":"NSW",
    "sg:tags":[
        "teacher"
    ],
    "wof:name":"Powell Bronwyn",
    "wof:placetype":"venue"
},
  "geometry": {"coordinates":[146.922897339,-36.0564460754],"type":"Point"}
}