{
  "type": "Feature",
  "properties": {
    "addr:full":"North St Wandoan QLD 4419",
    "addr:postcode":"4419",
    "addr:street":"North St",
    "iso:country":"AU",
    "sg:address":"North St",
    "sg:city":"Wandoan",
    "sg:classifiers":[
        {
            "category":"Real Estate",
            "subcategory":"Real Estate Agent",
            "type":"Services"
        }
    ],
    "sg:phone":"+61 7 4627 4433",
    "sg:postcode":"4419",
    "sg:province":"QLD",
    "wof:name":"Landmark Operations Limited",
    "wof:placetype":"venue"
},
  "geometry": {"coordinates":[149.96029663100001,-26.1180534363],"type":"Point"}
}