{
  "type": "Feature",
  "properties": {
    "addr:full":"80- 86 Buckhurst St South Melbourne VIC 3205",
    "addr:housenumber":"86",
    "addr:postcode":"3205",
    "addr:street":"Buckhurst St",
    "iso:country":"AU",
    "sg:address":"80- 86 Buckhurst St",
    "sg:city":"South Melbourne",
    "sg:classifiers":[
        {
            "category":"Building & Trades",
            "subcategory":"Pest Control",
            "type":"Services"
        }
    ],
    "sg:phone":"+61 3 8696 9000",
    "sg:postcode":"3205",
    "sg:province":"VIC",
    "wof:name":"Exopest",
    "wof:placetype":"venue"
},
  "geometry": {"coordinates":[144.95053100000001,-37.830715],"type":"Point"}
}