{
  "type": "Feature",
  "properties": {
    "iso:country":"AU",
    "sg:address":"40 Alexander St",
    "sg:city":"Wembley",
    "sg:classifiers":[
        {
            "category":"Health Services",
            "subcategory":"Doctor",
            "type":"Services"
        }
    ],
    "sg:phone":"+61 8 9383 9412",
    "sg:postcode":"6014",
    "sg:province":"WA",
    "sg:tags":[
        "podiatrist"
    ],
    "wof:name":"Hartman Mark",
    "wof:placetype":"venue"
},
  "geometry": {"coordinates":[115.81056213399999,-31.9358577728],"type":"Point"}
}