{
  "type": "Feature",
  "properties": {
    "iso:country":"AU",
    "sg:address":"257 Princes Hwy",
    "sg:city":"Bulli",
    "sg:classifiers":[
        {
            "category":"Retail",
            "subcategory":"Funeral Services",
            "type":"Services"
        }
    ],
    "sg:phone":"+61 2 4284 3103",
    "sg:postcode":"2516",
    "sg:province":"NSW",
    "sg:tags":[
        "director"
    ],
    "wof:name":"Hansen & Cole Funerals",
    "wof:placetype":"venue"
},
  "geometry": {"coordinates":[150.910263,-34.337505],"type":"Point"}
}