{
  "type": "Feature",
  "properties": {
    "addr:full":"9 Simcock St Somerville VIC 3912",
    "addr:housenumber":"9",
    "addr:postcode":"3912",
    "addr:street":"Simcock St",
    "iso:country":"AU",
    "sg:address":"9 Simcock St",
    "sg:city":"Somerville",
    "sg:classifiers":[
        {
            "category":"Retail",
            "subcategory":"Storage",
            "type":"Services"
        }
    ],
    "sg:phone":"+61 3 5977 7800",
    "sg:postcode":"3912",
    "sg:province":"VIC",
    "wof:name":"Somerville Self Storage",
    "wof:placetype":"venue"
},
  "geometry": {"coordinates":[145.17831420900001,-38.221446991],"type":"Point"}
}