{
  "type": "Feature",
  "properties": {
    "addr:full":"Suite 1/ 112 Francis St Richmond NSW 2753",
    "addr:housenumber":"/ 112",
    "addr:postcode":"2753",
    "addr:street":"Francis St",
    "iso:country":"AU",
    "sg:address":"Suite 1/ 112 Francis St",
    "sg:city":"Richmond",
    "sg:classifiers":[
        {
            "category":"Shopping",
            "subcategory":"Optical Goods",
            "type":"Retail Goods"
        }
    ],
    "sg:phone":"+61 2 4578 1915",
    "sg:postcode":"2753",
    "sg:province":"NSW",
    "sg:tags":[
        "dispenser",
        "prescription"
    ],
    "wof:name":"Peards&#039; Optical",
    "wof:placetype":"venue"
},
  "geometry": {"coordinates":[150.74940490700001,-33.5943031311],"type":"Point"}
}