{
  "type": "Feature",
  "properties": {
    "addr:full":"59 Carr St Coogee NSW 2034",
    "addr:housenumber":"59",
    "addr:postcode":"2034",
    "addr:street":"Carr St",
    "iso:country":"AU",
    "sg:address":"59 Carr St",
    "sg:city":"Coogee",
    "sg:classifiers":[
        {
            "category":"Health Services",
            "subcategory":"Dentist",
            "type":"Services"
        }
    ],
    "sg:phone":"+61 2 9315 7420",
    "sg:postcode":"2034",
    "sg:province":"NSW",
    "wof:name":"Anthony J Stewart",
    "wof:placetype":"venue"
},
  "geometry": {"coordinates":[151.25502014200001,-33.9224586487],"type":"Point"}
}