{
  "type": "Feature",
  "properties": {
    "iso:country":"AU",
    "sg:address":"44 Mt Pleasant Rd",
    "sg:city":"Belmont",
    "sg:classifiers":[
        {
            "category":"Government",
            "subcategory":"Court House",
            "type":"Public Place"
        }
    ],
    "sg:phone":"+61 3 5241 6011",
    "sg:postcode":"3216",
    "sg:province":"VIC",
    "sg:tags":[
        "personal",
        "marriage",
        "family",
        "counselling"
    ],
    "wof:name":"Lyn Bruscella",
    "wof:placetype":"venue"
},
  "geometry": {"coordinates":[144.34397888199999,-38.1706161499],"type":"Point"}
}