{
  "type": "Feature",
  "properties": {
    "addr:full":"Level 16 140 St. Georges Tce Perth WA 6000",
    "addr:housenumber":"140",
    "addr:postcode":"6000",
    "addr:street":"St. Georges Tce",
    "iso:country":"AU",
    "sg:address":"Level 16 140",
    "sg:city":"St. Georges Tce Perth",
    "sg:classifiers":[
        {
            "category":"Banks & Credit Unions",
            "subcategory":"Financial Services",
            "type":"Services"
        }
    ],
    "sg:phone":"+61 8 9215 7300",
    "sg:postcode":"6000",
    "sg:province":"WA",
    "sg:tags":[
        "planning"
    ],
    "wof:name":"Financial Partnerships",
    "wof:placetype":"venue"
},
  "geometry": {"coordinates":[115.856391907,-31.954492569],"type":"Point"}
}