{
  "type": "Feature",
  "properties": {
    "addr:full":"8 Albion St Warwick QLD 4370",
    "addr:housenumber":"8",
    "addr:postcode":"4370",
    "addr:street":"Albion St",
    "iso:country":"AU",
    "sg:address":"8 Albion St",
    "sg:city":"Warwick",
    "sg:classifiers":[
        {
            "category":"Cafe",
            "type":"Food & Drink"
        }
    ],
    "sg:phone":"+61 7 4661 9022",
    "sg:postcode":"4370",
    "sg:province":"QLD",
    "wof:name":"The Bramble Patch Cafe",
    "wof:placetype":"venue"
},
  "geometry": {"coordinates":[152.036178589,-28.2105941772],"type":"Point"}
}