{
  "type": "Feature",
  "properties": {
    "iso:country":"AU",
    "sg:address":"1 Bye St",
    "sg:city":"Wagga Wagga",
    "sg:phone":"+61 2 6925 4455",
    "sg:postcode":"2650",
    "sg:province":"NSW",
    "wof:name":"Solar Tinting Centre",
    "wof:placetype":"venue"
},
  "geometry": {"coordinates":[147.34455871599999,-35.1182632446],"type":"Point"}
}