{
  "type": "Feature",
  "properties": {
    "iso:country":"AU",
    "sg:address":"486 Lysterfield Rd",
    "sg:city":"Lysterfield",
    "sg:classifiers":[
        {
            "category":"Utilities",
            "subcategory":"Electric",
            "type":"Services"
        }
    ],
    "sg:phone":"+61 3 9752 2284",
    "sg:postcode":"3156",
    "sg:province":"VIC",
    "sg:tags":[
        "electrical",
        "contractor"
    ],
    "wof:name":"Nash A A",
    "wof:placetype":"venue"
},
  "geometry": {"coordinates":[145.30314636200001,-37.925037384],"type":"Point"}
}