{
  "type": "Feature",
  "properties": {
    "addr:full":"207 Banyula Drv Gaven QLD 4211",
    "addr:housenumber":"207",
    "addr:postcode":"4211",
    "addr:street":"Banyula Drv",
    "iso:country":"AU",
    "sg:address":"207 Banyula Drv",
    "sg:city":"Gaven",
    "sg:classifiers":[
        {
            "category":"Professional",
            "type":"Services"
        }
    ],
    "sg:phone":"+61 7 5596 0817",
    "sg:postcode":"4211",
    "sg:province":"QLD",
    "sg:tags":[
        "transport"
    ],
    "wof:name":"Plant Delivery Services",
    "wof:placetype":"venue"
},
  "geometry": {"coordinates":[153.343505859,-27.9588489532],"type":"Point"}
}