{
  "type": "Feature",
  "properties": {
    "addr:full":"PO Box 1236 Hobart TAS 7000",
    "addr:postcode":"7000",
    "iso:country":"AU",
    "sg:address":"PO Box 1236",
    "sg:city":"Hobart",
    "sg:classifiers":[
        {
            "category":"Building & Trades",
            "subcategory":"Construction",
            "type":"Services"
        }
    ],
    "sg:phone":"+61 3 6229 4447",
    "sg:postcode":"7000",
    "sg:province":"TAS",
    "sg:tags":[
        "contractor"
    ],
    "wof:name":"Sunrise Homes",
    "wof:placetype":"venue"
},
  "geometry": {"coordinates":[147.31495666500001,-42.8748512268],"type":"Point"}
}