{
  "type": "Feature",
  "properties": {
    "addr:full":"72- 80 Wells St Frankston VIC 3199",
    "addr:housenumber":"80",
    "addr:postcode":"3199",
    "addr:street":"Wells St",
    "iso:country":"AU",
    "sg:address":"72- 80 Wells St",
    "sg:city":"Frankston",
    "sg:classifiers":[
        {
            "category":"Shopping",
            "subcategory":"Computers & Home Electronics",
            "type":"Retail Goods"
        }
    ],
    "sg:phone":"+61 3 9783 9144",
    "sg:postcode":"3199",
    "sg:province":"VIC",
    "sg:tags":[
        "small",
        "equipment",
        "business"
    ],
    "wof:name":"Dick Smith Electronics",
    "wof:placetype":"venue"
},
  "geometry": {"coordinates":[144.968475342,-37.8277816772],"type":"Point"}
}