{
  "type": "Feature",
  "properties": {
    "addr:full":"2/ 13-15 Paul St Croydon VIC 3136",
    "addr:housenumber":"/ 13-15",
    "addr:postcode":"3136",
    "addr:street":"Paul St",
    "iso:country":"AU",
    "sg:address":"2/ 13-15 Paul St",
    "sg:city":"Croydon",
    "sg:classifiers":[
        {
            "category":"Professional",
            "subcategory":"Engineering",
            "type":"Services"
        }
    ],
    "sg:phone":"+61 3 9725 2725",
    "sg:postcode":"3136",
    "sg:province":"VIC",
    "sg:tags":[
        "electronic",
        "engineer"
    ],
    "wof:name":"CSE Pty Ltd",
    "wof:placetype":"venue"
},
  "geometry": {"coordinates":[145.307739258,-37.7899589539],"type":"Point"}
}