{
  "type": "Feature",
  "properties": {
    "addr:full":"6 Short St Plz Manly NSW 2095",
    "addr:housenumber":"6",
    "addr:postcode":"2095",
    "addr:street":"Short St Plz",
    "iso:country":"AU",
    "sg:address":"6 Short St Plz",
    "sg:city":"Manly",
    "sg:classifiers":[
        {
            "category":"Personal",
            "subcategory":"Beauty Salon",
            "type":"Services"
        }
    ],
    "sg:phone":"+61 2 9977 6704",
    "sg:postcode":"2095",
    "sg:province":"NSW",
    "sg:tags":[
        "hairdresser"
    ],
    "wof:name":"Plaza Barber Shop",
    "wof:placetype":"venue"
},
  "geometry": {"coordinates":[151.286056519,-33.7967338562],"type":"Point"}
}