{
  "type": "Feature",
  "properties": {
    "addr:full":"21 Longford St Roseville NSW 2069",
    "addr:housenumber":"21",
    "addr:postcode":"2069",
    "addr:street":"Longford St",
    "iso:country":"AU",
    "sg:address":"21 Longford St",
    "sg:city":"Roseville",
    "sg:classifiers":[
        {
            "category":"Shopping",
            "subcategory":"Clothing, Apparel, & Fashions",
            "type":"Retail Goods"
        }
    ],
    "sg:phone":"+61 2 9416 8916",
    "sg:postcode":"2069",
    "sg:province":"NSW",
    "sg:tags":[
        "wholesaler",
        "children's",
        "mfrs",
        "wear"
    ],
    "wof:name":"Little Witchetty",
    "wof:placetype":"venue"
},
  "geometry": {"coordinates":[151.16549682600001,-33.7879562378],"type":"Point"}
}