{
  "type": "Feature",
  "properties": {
    "iso:country":"AU",
    "sg:address":"186 Corio St",
    "sg:city":"Shepparton",
    "sg:classifiers":[
        {
            "category":"Personal",
            "subcategory":"Beauty Salon",
            "type":"Services"
        }
    ],
    "sg:phone":"+61 3 5821 2485",
    "sg:postcode":"3630",
    "sg:province":"VIC",
    "sg:tags":[
        "hairdresser"
    ],
    "wof:name":"Kevins Barber Shop",
    "wof:placetype":"venue"
},
  "geometry": {"coordinates":[145.40306091299999,-36.3816986084],"type":"Point"}
}