{
  "type": "Feature",
  "properties": {
    "iso:country":"AU",
    "sg:address":"458 Whitehorse Rd",
    "sg:city":"Surrey Hills",
    "sg:classifiers":[
        {
            "category":"Sports & Exercise",
            "subcategory":"Gym",
            "type":"Entertainment"
        }
    ],
    "sg:phone":"+61 3 9836 6961",
    "sg:postcode":"3127",
    "sg:province":"VIC",
    "sg:tags":[
        "health",
        "fitness"
    ],
    "wof:name":"Jack Lim Qigong Academy Australia",
    "wof:placetype":"venue"
},
  "geometry": {"coordinates":[145.093994141,-37.8144569397],"type":"Point"}
}