{
  "type": "Feature",
  "properties": {
    "addr:full":"101 Breimba St Grafton NSW 2460",
    "addr:housenumber":"101",
    "addr:postcode":"2460",
    "addr:street":"Breimba St",
    "iso:country":"AU",
    "sg:address":"101 Breimba St",
    "sg:city":"Grafton",
    "sg:classifiers":[
        {
            "category":"Banks & Credit Unions",
            "subcategory":"Bank",
            "type":"Services"
        }
    ],
    "sg:phone":"+61 2 6642 1800",
    "sg:postcode":"2460",
    "sg:province":"NSW",
    "sg:tags":[
        "broker",
        "mortgage"
    ],
    "wof:name":"Northern Lending",
    "wof:placetype":"venue"
},
  "geometry": {"coordinates":[152.931915283,-29.6927318573],"type":"Point"}
}