{
  "type": "Feature",
  "properties": {
    "addr:full":"31 Vivian St Boulder WA 6432",
    "addr:housenumber":"31",
    "addr:postcode":"6432",
    "addr:street":"Vivian St",
    "iso:country":"AU",
    "sg:address":"31 Vivian St",
    "sg:city":"Boulder",
    "sg:classifiers":[
        {
            "category":"Building & Trades",
            "subcategory":"Cleaning & Sanitation",
            "type":"Services"
        }
    ],
    "sg:phone":"+61 8 9093 2747",
    "sg:postcode":"6432",
    "sg:province":"WA",
    "sg:tags":[
        "grease",
        "trap"
    ],
    "wof:name":"The Grime Fighters",
    "wof:placetype":"venue"
},
  "geometry": {"coordinates":[121.49581146200001,-30.7902851105],"type":"Point"}
}