{
  "type": "Feature",
  "properties": {
    "addr:full":"848 Hampton St Brighton VIC 3186",
    "addr:housenumber":"848",
    "addr:postcode":"3186",
    "addr:street":"Hampton St",
    "iso:country":"AU",
    "sg:address":"848 Hampton St",
    "sg:city":"Brighton",
    "sg:classifiers":[
        {
            "category":"Building & Trades",
            "subcategory":"Construction",
            "type":"Services"
        }
    ],
    "sg:phone":"+61 3 9592 6495",
    "sg:postcode":"3186",
    "sg:province":"VIC",
    "sg:tags":[
        "contractor"
    ],
    "wof:name":"Thompson R P & J Pty Ltd",
    "wof:placetype":"venue"
},
  "geometry": {"coordinates":[145.007446289,-37.9121055603],"type":"Point"}
}