{
  "type": "Feature",
  "properties": {
    "addr:full":"4/ 3 Torca Tce Mornington VIC 3931",
    "addr:housenumber":"/ 3",
    "addr:postcode":"3931",
    "addr:street":"Torca Tce",
    "iso:country":"AU",
    "sg:address":"4/ 3",
    "sg:city":"Torca Tce Mornington",
    "sg:classifiers":[
        {
            "category":"Wholesale",
            "subcategory":"Medical Equipment & Supplies",
            "type":"Manufacturing & Wholesale Goods"
        }
    ],
    "sg:phone":"+61 3 5975 6107",
    "sg:postcode":"3931",
    "sg:province":"VIC",
    "sg:tags":[
        "scooter",
        "mobility"
    ],
    "wof:name":"Coastcare Medical Equipment Hire & Sales Pty Ltd",
    "wof:placetype":"venue"
},
  "geometry": {"coordinates":[145.05595398,-38.2347335815],"type":"Point"}
}