{
  "type": "Feature",
  "properties": {
    "iso:country":"AU",
    "sg:address":"156 Sixth Ave",
    "sg:city":"Royston Park",
    "sg:classifiers":[
        {
            "category":"Health Services",
            "subcategory":"Dentist",
            "type":"Services"
        }
    ],
    "sg:phone":"+61 8 8362 3228",
    "sg:postcode":"5070",
    "sg:province":"SA",
    "wof:name":"Alexander V & Karin J",
    "wof:placetype":"venue"
},
  "geometry": {"coordinates":[138.62954711899999,-34.896030426],"type":"Point"}
}