{
  "type": "Feature",
  "properties": {
    "iso:country":"AU",
    "sg:address":"76 Cove Hill Rd",
    "sg:city":"Bridgewater",
    "sg:classifiers":[
        {
            "category":"Manufacturing",
            "subcategory":"Building Materials",
            "type":"Manufacturing & Wholesale Goods"
        }
    ],
    "sg:phone":"+61 3 6263 5533",
    "sg:postcode":"7030",
    "sg:province":"TAS",
    "sg:tags":[
        "concrete",
        "product"
    ],
    "wof:name":"Precast Tasmania Pty Ltd",
    "wof:placetype":"venue"
},
  "geometry": {"coordinates":[147.24349975600001,-42.7342720032],"type":"Point"}
}