{
  "type": "Feature",
  "properties": {
    "iso:country":"AU",
    "sg:address":"151 Boundary St",
    "sg:city":"Port Melbourne",
    "sg:classifiers":[
        {
            "category":"Farming",
            "subcategory":"Poultry Farm",
            "type":"Manufacturing & Wholesale Goods"
        }
    ],
    "sg:phone":"+61 3 8645 1200",
    "sg:postcode":"3207",
    "sg:province":"VIC",
    "sg:tags":[
        "farmer"
    ],
    "wof:name":"Luv-A-Duck Pty Ltd",
    "wof:placetype":"venue"
},
  "geometry": {"coordinates":[144.941223,-37.826889],"type":"Point"}
}