{
  "type": "Feature",
  "properties": {
    "addr:full":"899 High St Armadale VIC 3143",
    "addr:housenumber":"899",
    "addr:postcode":"3143",
    "addr:street":"High St",
    "iso:country":"AU",
    "sg:address":"899 High St",
    "sg:city":"Armadale",
    "sg:classifiers":[
        {
            "category":"Shopping",
            "subcategory":"Antiques",
            "type":"Retail Goods"
        }
    ],
    "sg:phone":"+61 3 9509 7322",
    "sg:postcode":"3143",
    "sg:province":"VIC",
    "wof:name":"Gary Kay",
    "wof:placetype":"venue"
},
  "geometry": {"coordinates":[145.01736450199999,-37.8549118042],"type":"Point"}
}