{
  "type": "Feature",
  "properties": {
    "addr:full":"Shop 4/ 82 Victoria St Werrington NSW 2747",
    "addr:housenumber":"shop 4 / 82",
    "addr:postcode":"2747",
    "addr:street":"Victoria St",
    "iso:country":"AU",
    "sg:address":"Shop 4/ 82 Victoria St",
    "sg:city":"Werrington",
    "sg:classifiers":[
        {
            "category":"Fast Food",
            "type":"Food & Drink"
        }
    ],
    "sg:phone":"+61 2 9623 0010",
    "sg:postcode":"2747",
    "sg:province":"NSW",
    "sg:tags":[
        "away",
        "take"
    ],
    "wof:name":"Latitudes Takeaway Cafe",
    "wof:placetype":"venue"
},
  "geometry": {"coordinates":[150.738845825,-33.7579231262],"type":"Point"}
}