{
  "type": "Feature",
  "properties": {
    "addr:full":"76a Bass Hwy Cooee TAS 7320",
    "addr:housenumber":"76a",
    "addr:postcode":"7320",
    "addr:street":"Bass Hwy",
    "iso:country":"AU",
    "sg:address":"76a Bass Hwy",
    "sg:city":"Cooee",
    "sg:classifiers":[
        {
            "category":"Retail",
            "subcategory":"Repair Shop",
            "type":"Services"
        }
    ],
    "sg:phone":"+61 3 6431 9470",
    "sg:postcode":"7320",
    "sg:province":"TAS",
    "sg:tags":[
        "mending",
        "clothing",
        "alteration"
    ],
    "wof:name":"All Sewn Up",
    "wof:placetype":"venue"
},
  "geometry": {"coordinates":[145.87402299999999,-41.040329],"type":"Point"}
}