{
  "type": "Feature",
  "properties": {
    "iso:country":"AU",
    "sg:address":"40a Oxford St",
    "sg:city":"Paddington",
    "sg:classifiers":[
        {
            "category":"Personal",
            "subcategory":"Beauty Salon",
            "type":"Services"
        }
    ],
    "sg:phone":"+61 2 9331 3220",
    "sg:postcode":"2021",
    "sg:province":"NSW",
    "sg:tags":[
        "hairdresser"
    ],
    "wof:name":"Ardino Hair Face Body",
    "wof:placetype":"venue"
},
  "geometry": {"coordinates":[151.220169067,-33.8822555542],"type":"Point"}
}