{
  "type": "Feature",
  "properties": {
    "addr:full":"R.P.A.H. Medical Centre 100 Carillon Ave Newtown NSW 2042",
    "addr:housenumber":"100",
    "addr:postcode":"2042",
    "addr:street":"Carillon Ave",
    "iso:country":"AU",
    "sg:address":"R.P.A.H. Medical Centre 100 Carillon Ave",
    "sg:city":"Newtown",
    "sg:classifiers":[
        {
            "category":"Health Services",
            "subcategory":"Doctor",
            "type":"Services"
        }
    ],
    "sg:phone":"+61 2 9517 1330",
    "sg:postcode":"2042",
    "sg:province":"NSW",
    "sg:tags":[
        "medical",
        "practitioner"
    ],
    "wof:name":"James Con A Dr",
    "wof:placetype":"venue"
},
  "geometry": {"coordinates":[151.17581200000001,-33.89859],"type":"Point"}
}