{
  "type": "Feature",
  "properties": {
    "iso:country":"AU",
    "sg:address":"38 Belmont Ave",
    "sg:city":"Rivervale",
    "sg:classifiers":[
        {
            "category":"Mining & Drilling",
            "type":"Manufacturing & Wholesale Goods"
        }
    ],
    "sg:phone":"+61 8 9277 1777",
    "sg:postcode":"6103",
    "sg:province":"WA",
    "sg:tags":[
        "equipment",
        "quarrying",
        "supply"
    ],
    "wof:name":"NHP Electrical Engineering Products Pty Ltd",
    "wof:placetype":"venue"
},
  "geometry": {"coordinates":[115.919960022,-31.9544143677],"type":"Point"}
}