{
  "type": "Feature",
  "properties": {
    "iso:country":"AU",
    "sg:address":"St Leonards Road Wahgunyah (VIC)",
    "sg:city":"Wahgunyah",
    "sg:classifiers":[
        {
            "category":"Farming",
            "subcategory":"Vineyard",
            "type":"Manufacturing & Wholesale Goods"
        }
    ],
    "sg:phone":"+61 2 6033 1004",
    "sg:postcode":"3687",
    "sg:province":"VIC",
    "sg:tags":[
        "winery"
    ],
    "wof:name":"St Leonards Vineyard",
    "wof:placetype":"venue"
},
  "geometry": {"coordinates":[146.417923,-35.991062],"type":"Point"}
}