{
  "type": "Feature",
  "properties": {
    "addr:full":"50 Rosebery St Bayswater WA 6053",
    "addr:housenumber":"50",
    "addr:postcode":"6053",
    "addr:street":"Rosebery St",
    "iso:country":"AU",
    "sg:address":"50 Rosebery St",
    "sg:city":"Bayswater",
    "sg:classifiers":[
        {
            "category":"Shopping",
            "subcategory":"Stationery & Office Supplies",
            "type":"Retail Goods"
        }
    ],
    "sg:phone":"+61 8 9471 9122",
    "sg:postcode":"6053",
    "sg:province":"WA",
    "sg:tags":[
        "packaging",
        "material"
    ],
    "wof:name":"Impacked Pty Ltd",
    "wof:placetype":"venue"
},
  "geometry": {"coordinates":[115.895812988,-31.9188861847],"type":"Point"}
}