{
  "type": "Feature",
  "properties": {
    "iso:country":"AU",
    "sg:address":"280 Main Rd",
    "sg:city":"Cardiff",
    "sg:classifiers":[
        {
            "category":"Shopping",
            "subcategory":"Optical Goods",
            "type":"Retail Goods"
        }
    ],
    "sg:phone":"+61 2 4954 0288",
    "sg:postcode":"2285",
    "sg:province":"NSW",
    "sg:tags":[
        "dispenser",
        "prescription"
    ],
    "wof:name":"Cardiff Pharmacy Soulvision",
    "wof:placetype":"venue"
},
  "geometry": {"coordinates":[151.65994262699999,-32.9399604797],"type":"Point"}
}