{
  "type": "Feature",
  "properties": {
    "addr:full":"2065 Princes Hwy Clayton VIC 3168",
    "addr:housenumber":"2065",
    "addr:postcode":"3168",
    "addr:street":"Princes Hwy",
    "iso:country":"AU",
    "sg:address":"2065 Princes Hwy",
    "sg:city":"Clayton",
    "sg:classifiers":[
        {
            "category":"Retail",
            "subcategory":"Storage",
            "type":"Services"
        }
    ],
    "sg:phone":"+61 3 9544 3444",
    "sg:postcode":"3168",
    "sg:province":"VIC",
    "sg:tags":[
        "shelving",
        "system"
    ],
    "wof:name":"Southern Storage Systems",
    "wof:placetype":"venue"
},
  "geometry": {"coordinates":[145.13630676299999,-37.9196891785],"type":"Point"}
}