{
  "type": "Feature",
  "properties": {
    "addr:full":"Unit 2/ 25 Preston St Como WA 6152",
    "addr:housenumber":"25",
    "addr:postcode":"6152",
    "addr:street":"Preston St",
    "iso:country":"AU",
    "sg:address":"Unit 2/ 25 Preston St",
    "sg:city":"Como",
    "sg:classifiers":[
        {
            "category":"Communications",
            "subcategory":"Film & Video Production",
            "type":"Services"
        }
    ],
    "sg:phone":"+61 8 9367 7017",
    "sg:postcode":"6152",
    "sg:province":"WA",
    "sg:tags":[
        "dvd",
        "library"
    ],
    "wof:name":"Lally Videos",
    "wof:placetype":"venue"
},
  "geometry": {"coordinates":[115.85923,-31.993877],"type":"Point"}
}