{
  "type": "Feature",
  "properties": {
    "addr:full":"31 Rimfire Drv Hallam VIC 3803",
    "addr:housenumber":"31",
    "addr:postcode":"3803",
    "addr:street":"Rimfire Drv",
    "iso:country":"AU",
    "sg:address":"31 Rimfire Drv",
    "sg:city":"Hallam",
    "sg:classifiers":[
        {
            "category":"Home & Garden",
            "subcategory":"Building Materials",
            "type":"Retail Goods"
        }
    ],
    "sg:phone":"+61 3 8795 7304",
    "sg:postcode":"3803",
    "sg:province":"VIC",
    "sg:tags":[
        "tile",
        "roofing"
    ],
    "wof:name":"Tip Top Roofing Pty Ltd",
    "wof:placetype":"venue"
},
  "geometry": {"coordinates":[145.275314331,-38.01902771],"type":"Point"}
}