{
  "type": "Feature",
  "properties": {
    "addr:full":"29 Main St Lobethal SA 5241",
    "addr:housenumber":"29",
    "addr:postcode":"5241",
    "addr:street":"Main St",
    "iso:country":"AU",
    "sg:address":"29 Main St",
    "sg:city":"Lobethal",
    "sg:classifiers":[
        {
            "category":"Personal",
            "subcategory":"Beauty Salon",
            "type":"Services"
        }
    ],
    "sg:phone":"+61 8 8389 6444",
    "sg:postcode":"5241",
    "sg:province":"SA",
    "sg:tags":[
        "hairdresser"
    ],
    "wof:name":"Foster Pingel Hairdressing",
    "wof:placetype":"venue"
},
  "geometry": {"coordinates":[138.87440490700001,-34.905708313],"type":"Point"}
}