{
  "type": "Feature",
  "properties": {
    "addr:full":"Christine Crs Lalor Park NSW 2147",
    "addr:postcode":"2147",
    "addr:street":"Christine Crs",
    "iso:country":"AU",
    "sg:address":"Christine Crs",
    "sg:city":"Lalor Park",
    "sg:classifiers":[
        {
            "category":"Professional",
            "type":"Services"
        }
    ],
    "sg:phone":"+61 424 183 676",
    "sg:postcode":"2147",
    "sg:province":"NSW",
    "sg:tags":[
        "courier"
    ],
    "wof:name":"Couriers R Us",
    "wof:placetype":"venue"
},
  "geometry": {"coordinates":[150.93145751899999,-33.7619895935],"type":"Point"}
}