{
  "type": "Feature",
  "properties": {
    "iso:country":"AU",
    "sg:address":"Jarrah Rd Shopping Centre",
    "sg:city":"Roleystone",
    "sg:classifiers":[
        {
            "category":"Real Estate",
            "subcategory":"Real Estate Agent",
            "type":"Services"
        }
    ],
    "sg:phone":"+61 8 9397 5400",
    "sg:postcode":"6111",
    "sg:province":"WA",
    "wof:name":"Fidock & Co Real Estate",
    "wof:placetype":"venue"
},
  "geometry": {"coordinates":[116.069740295,-32.114315033],"type":"Point"}
}