{
  "type": "Feature",
  "properties": {
    "iso:country":"AU",
    "sg:address":"Unit 2 109 Union Rd",
    "sg:city":"Surrey Hills",
    "sg:classifiers":[
        {
            "category":"Health Services",
            "subcategory":"Dentist",
            "type":"Services"
        }
    ],
    "sg:phone":"+61 3 9898 0100",
    "sg:postcode":"3127",
    "sg:province":"VIC",
    "wof:name":"Poulos Georgia Dr",
    "wof:placetype":"venue"
},
  "geometry": {"coordinates":[145.09753418,-37.8252105713],"type":"Point"}
}