{
  "type": "Feature",
  "properties": {
    "addr:full":"170 Albert St Brunswick VIC 3056",
    "addr:housenumber":"170",
    "addr:postcode":"3056",
    "addr:street":"Albert St",
    "iso:country":"AU",
    "sg:address":"170 Albert St",
    "sg:city":"Brunswick",
    "sg:classifiers":[
        {
            "category":"Arena",
            "subcategory":"Sports Club",
            "type":"Entertainment"
        }
    ],
    "sg:phone":"+61 3 9620 5433",
    "sg:postcode":"3056",
    "sg:province":"VIC",
    "sg:tags":[
        "defence",
        "supply",
        "self",
        "instruction",
        "martial art"
    ],
    "wof:name":"Brunswick Kickboxing",
    "wof:placetype":"venue"
},
  "geometry": {"coordinates":[144.96879577600001,-37.7696647644],"type":"Point"}
}