{
  "type": "Feature",
  "properties": {
    "addr:full":"Market Sq Shopng Cntr Moorabool St Geelong VIC 3220",
    "addr:postcode":"3220",
    "addr:street":"Market Sq Shopng Cntr Moorabool St",
    "iso:country":"AU",
    "sg:address":"Market Sq Shopng Cntr Moorabool St",
    "sg:city":"Geelong",
    "sg:classifiers":[
        {
            "category":"Communications",
            "subcategory":"News Services",
            "type":"Services"
        }
    ],
    "sg:phone":"+61 3 5222 6126",
    "sg:postcode":"3220",
    "sg:province":"VIC",
    "sg:tags":[
        "information",
        "tourist",
        "attractions"
    ],
    "wof:name":"Geelong Otway Tourism",
    "wof:placetype":"venue"
},
  "geometry": {"coordinates":[144.35479699999999,-38.160118],"type":"Point"}
}