{
  "type": "Feature",
  "properties": {
    "addr:full":"54 Maroondah Hwy Ringwood VIC 3134",
    "addr:housenumber":"54",
    "addr:postcode":"3134",
    "addr:street":"Maroondah Hwy",
    "iso:country":"AU",
    "sg:address":"54 Maroondah Hwy",
    "sg:city":"Ringwood",
    "sg:classifiers":[
        {
            "category":"Retail",
            "subcategory":"Auto Rental",
            "type":"Services"
        }
    ],
    "sg:phone":"+61 3 9870 5649",
    "sg:postcode":"3134",
    "sg:province":"VIC",
    "sg:tags":[
        "bus",
        "truck"
    ],
    "wof:name":"Delta Car & Truck Rentals",
    "wof:placetype":"venue"
},
  "geometry": {"coordinates":[145.22105407699999,-37.8172454834],"type":"Point"}
}