{
  "type": "Feature",
  "properties": {
    "iso:country":"AU",
    "sg:address":"212 Gnangara Rd",
    "sg:city":"Landsdale",
    "sg:classifiers":[
        {
            "category":"Fast Food",
            "type":"Food & Drink"
        }
    ],
    "sg:phone":"+61 8 9309 2900",
    "sg:postcode":"6065",
    "sg:province":"WA",
    "sg:tags":[
        "away",
        "take"
    ],
    "wof:name":"Landsdale Supa Lunch Bar",
    "wof:placetype":"venue"
},
  "geometry": {"coordinates":[115.84055328399999,-31.8013916016],"type":"Point"}
}