{
  "type": "Feature",
  "properties": {
    "addr:full":"Lvl 1/ 597 Military Rd Mosman NSW 2088",
    "addr:housenumber":"/ 597",
    "addr:postcode":"2088",
    "addr:street":"Military Rd",
    "iso:country":"AU",
    "sg:address":"Lvl 1/ 597 Military Rd",
    "sg:city":"Mosman",
    "sg:classifiers":[
        {
            "category":"Real Estate",
            "subcategory":"Surveying",
            "type":"Services"
        }
    ],
    "sg:phone":"+61 2 9969 9997",
    "sg:postcode":"2088",
    "sg:province":"NSW",
    "sg:tags":[
        "surveyor",
        "land"
    ],
    "wof:name":"Theodore Mossel",
    "wof:placetype":"venue"
},
  "geometry": {"coordinates":[151.241912842,-33.8251037598],"type":"Point"}
}