{
  "type": "Feature",
  "properties": {
    "addr:full":"29 Seaview Ave Newport NSW 2106",
    "addr:housenumber":"29",
    "addr:postcode":"2106",
    "addr:street":"Seaview Ave",
    "iso:country":"AU",
    "sg:address":"29 Seaview Ave",
    "sg:city":"Newport",
    "sg:classifiers":[
        {
            "category":"Building & Trades",
            "subcategory":"Construction",
            "type":"Services"
        }
    ],
    "sg:phone":"+61 2 9997 8840",
    "sg:postcode":"2106",
    "sg:province":"NSW",
    "sg:tags":[
        "concrete",
        "paving"
    ],
    "wof:name":"Barrie Bree",
    "wof:placetype":"venue"
},
  "geometry": {"coordinates":[151.31867980999999,-33.6528549194],"type":"Point"}
}