{
  "type": "Feature",
  "properties": {
    "addr:full":"165 Clovelly Rd Clovelly NSW 2031",
    "addr:housenumber":"165",
    "addr:postcode":"2031",
    "addr:street":"Clovelly Rd",
    "iso:country":"AU",
    "sg:address":"165 Clovelly Rd",
    "sg:city":"Clovelly",
    "sg:classifiers":[
        {
            "category":"Retail",
            "subcategory":"Repair Shop",
            "type":"Services"
        }
    ],
    "sg:phone":"+61 2 9399 8356",
    "sg:postcode":"2031",
    "sg:province":"NSW",
    "sg:tags":[
        "mending",
        "clothing",
        "alteration"
    ],
    "wof:name":"Just Casual",
    "wof:placetype":"venue"
},
  "geometry": {"coordinates":[151.251876831,-33.9100074768],"type":"Point"}
}