{
  "type": "Feature",
  "properties": {
    "addr:full":"684 Sackville Ferry Rd Sackville North NSW 2756",
    "addr:housenumber":"684",
    "addr:postcode":"2756",
    "addr:street":"Sackville Ferry Rd",
    "iso:country":"AU",
    "sg:address":"684 Sackville Ferry Rd",
    "sg:city":"Sackville North",
    "sg:classifiers":[
        {
            "category":"Building & Trades",
            "subcategory":"Construction",
            "type":"Services"
        }
    ],
    "sg:phone":"+61 2 4579 0414",
    "sg:postcode":"2756",
    "sg:province":"NSW",
    "sg:tags":[
        "tennis court",
        "repair"
    ],
    "wof:name":"Ogden Concrete Contractors",
    "wof:placetype":"venue"
},
  "geometry": {"coordinates":[150.895584106,-33.480430603],"type":"Point"}
}