{
  "type": "Feature",
  "properties": {
    "iso:country":"AU",
    "sg:address":"1/ 62 Woodlands Rd",
    "sg:city":"Katoomba",
    "sg:classifiers":[
        {
            "category":"Retail",
            "subcategory":"Auto Repair",
            "type":"Services"
        }
    ],
    "sg:phone":"+61 2 4782 3530",
    "sg:postcode":"2780",
    "sg:province":"NSW",
    "sg:tags":[
        "beater",
        "painter",
        "panel"
    ],
    "wof:name":"Eds Body Shop",
    "wof:placetype":"venue"
},
  "geometry": {"coordinates":[150.320510864,-33.7053794861],"type":"Point"}
}