{
  "type": "Feature",
  "properties": {
    "addr:full":"134 White St Mordialloc VIC 3195",
    "addr:housenumber":"134",
    "addr:postcode":"3195",
    "addr:street":"White St",
    "iso:country":"AU",
    "sg:address":"134 White St",
    "sg:city":"Mordialloc",
    "sg:classifiers":[
        {
            "category":"Professional",
            "subcategory":"Engineering",
            "type":"Services"
        }
    ],
    "sg:phone":"+61 3 9587 6341",
    "sg:postcode":"3195",
    "sg:province":"VIC",
    "sg:tags":[
        "engineer",
        "mechanical"
    ],
    "wof:name":"Heatco Sales Pty Ltd",
    "wof:placetype":"venue"
},
  "geometry": {"coordinates":[145.10188293499999,-38.0005836487],"type":"Point"}
}