{
  "type": "Feature",
  "properties": {
    "addr:full":"62 Secam St Mansfield QLD 4122",
    "addr:housenumber":"62",
    "addr:postcode":"4122",
    "addr:street":"Secam St",
    "iso:country":"AU",
    "sg:address":"62 Secam St",
    "sg:city":"Mansfield",
    "sg:classifiers":[
        {
            "category":"Shopping",
            "subcategory":"Party Supplies",
            "type":"Retail Goods"
        }
    ],
    "sg:phone":"+61 7 3849 1077",
    "sg:postcode":"4122",
    "sg:province":"QLD",
    "sg:tags":[
        "equipment",
        "ultrasonic"
    ],
    "wof:name":"Sterilizing Equipment Sales & Service",
    "wof:placetype":"venue"
},
  "geometry": {"coordinates":[153.09863281200001,-27.529094696],"type":"Point"}
}