{
  "type": "Feature",
  "properties": {
    "addr:full":"258 Hyde St Yarraville VIC 3013",
    "addr:housenumber":"258",
    "addr:postcode":"3013",
    "addr:street":"Hyde St",
    "iso:country":"AU",
    "sg:address":"258 Hyde St",
    "sg:city":"Yarraville",
    "sg:classifiers":[
        {
            "category":"Building & Trades",
            "subcategory":"Cleaning & Sanitation",
            "type":"Services"
        }
    ],
    "sg:phone":"+61 3 9689 9999",
    "sg:postcode":"3013",
    "sg:province":"VIC",
    "sg:tags":[
        "chemical",
        "pressure",
        "steam",
        "contractor"
    ],
    "wof:name":"Kirwan Industrial Services",
    "wof:placetype":"venue"
},
  "geometry": {"coordinates":[144.89590454099999,-37.8205375671],"type":"Point"}
}