{
  "type": "Feature",
  "properties": {
    "iso:country":"AU",
    "sg:address":"Cnr Railway & East Sts",
    "sg:city":"Lidcombe",
    "sg:classifiers":[
        {
            "category":"Building & Trades",
            "subcategory":"Construction",
            "type":"Services"
        }
    ],
    "sg:phone":"+61 2 9643 8096",
    "sg:postcode":"2141",
    "sg:province":"NSW",
    "sg:tags":[
        "monumental",
        "mason"
    ],
    "wof:name":"Sydney Stone Art",
    "wof:placetype":"venue"
},
  "geometry": {"coordinates":[151.04447937,-33.8638534546],"type":"Point"}
}