{
  "type": "Feature",
  "properties": {
    "iso:country":"AU",
    "sg:address":"2/ 610 Great Western Hwy",
    "sg:city":"Girraween",
    "sg:classifiers":[
        {
            "category":"Building & Trades",
            "subcategory":"Construction",
            "type":"Services"
        }
    ],
    "sg:phone":"+61 2 9631 4468",
    "sg:postcode":"2145",
    "sg:province":"NSW",
    "sg:tags":[
        "decking",
        "contractor"
    ],
    "wof:name":"G & K Lattice",
    "wof:placetype":"venue"
},
  "geometry": {"coordinates":[150.94143676799999,-33.8083496094],"type":"Point"}
}