{
  "type": "Feature",
  "properties": {
    "addr:full":"8 Kamarooka St Sunshine VIC 3020",
    "addr:housenumber":"8",
    "addr:postcode":"3020",
    "addr:street":"Kamarooka St",
    "iso:country":"AU",
    "sg:address":"8 Kamarooka St",
    "sg:city":"Sunshine",
    "sg:classifiers":[
        {
            "category":"Building & Trades",
            "subcategory":"Construction",
            "type":"Services"
        }
    ],
    "sg:phone":"+61 412 530 607",
    "sg:postcode":"3020",
    "sg:province":"VIC",
    "sg:tags":[
        "plasterboard",
        "plasterer",
        "fixer"
    ],
    "wof:name":"Summit Plastering",
    "wof:placetype":"venue"
},
  "geometry": {"coordinates":[144.82145700000001,-37.780582],"type":"Point"}
}