{
  "type": "Feature",
  "properties": {
    "iso:country":"AU",
    "sg:address":"2/ 55 Piper Drv",
    "sg:city":"Ballina",
    "sg:classifiers":[
        {
            "category":"Banks & Credit Unions",
            "subcategory":"Bank",
            "type":"Services"
        }
    ],
    "sg:phone":"+61 2 6686 6291",
    "sg:postcode":"2478",
    "sg:province":"NSW",
    "sg:tags":[
        "broker",
        "mortgage"
    ],
    "wof:name":"East Coast Mortgage Solutions",
    "wof:placetype":"venue"
},
  "geometry": {"coordinates":[153.55540466299999,-28.8467082977],"type":"Point"}
}