{
  "type": "Feature",
  "properties": {
    "addr:full":"571 Yalangur/ Lilyvale Rd Lilyvale QLD 4352",
    "addr:housenumber":"571;/ lilyvale",
    "addr:postcode":"4352",
    "addr:street":"Yalangur;Rd",
    "iso:country":"AU",
    "sg:address":"571 Yalangur/ Lilyvale Rd",
    "sg:city":"Lilyvale",
    "sg:classifiers":[
        {
            "category":"Health Services",
            "subcategory":"Health Practitioner",
            "type":"Services"
        }
    ],
    "sg:phone":"+61 402 070 058",
    "sg:postcode":"4352",
    "sg:province":"QLD",
    "sg:tags":[
        "psychologist"
    ],
    "wof:name":"Baker Warren",
    "wof:placetype":"venue"
},
  "geometry": {"coordinates":[151.87681599999999,-27.427549],"type":"Point"}
}