{
  "type": "Feature",
  "properties": {
    "addr:full":"3 Hector St Osborne Park WA 6017",
    "addr:housenumber":"3",
    "addr:postcode":"6017",
    "addr:street":"Hector St",
    "iso:country":"AU",
    "sg:address":"3 Hector St",
    "sg:city":"Osborne Park",
    "sg:classifiers":[
        {
            "category":"Shopping",
            "subcategory":"Computers & Home Electronics",
            "type":"Retail Goods"
        }
    ],
    "sg:phone":"+61 8 9242 7288",
    "sg:postcode":"6017",
    "sg:province":"WA",
    "sg:tags":[
        "hardware",
        "equipment"
    ],
    "wof:name":"Netplus Micro Computers",
    "wof:placetype":"venue"
},
  "geometry": {"coordinates":[115.81333923299999,-31.8979969025],"type":"Point"}
}