{
  "type": "Feature",
  "properties": {
    "addr:full":"499 Nicholson St Carlton North VIC 3054",
    "addr:housenumber":"499",
    "addr:postcode":"3054",
    "addr:street":"Nicholson St",
    "iso:country":"AU",
    "sg:address":"499 Nicholson St",
    "sg:city":"Carlton North",
    "sg:classifiers":[
        {
            "category":"Communications",
            "type":"Services"
        }
    ],
    "sg:phone":"+61 3 9348 2876",
    "sg:postcode":"3054",
    "sg:province":"VIC",
    "sg:tags":[
        "translation"
    ],
    "wof:name":"Medio-Legal Communications Pty Ltd",
    "wof:placetype":"venue"
},
  "geometry": {"coordinates":[144.97645568900001,-37.7877845764],"type":"Point"}
}