{
  "type": "Feature",
  "properties": {
    "iso:country":"AU",
    "sg:address":"65 South Centre Rd",
    "sg:city":"Melbourne Airport",
    "sg:classifiers":[
        {
            "category":"Professional",
            "subcategory":"Employment Agencies",
            "type":"Services"
        }
    ],
    "sg:phone":"+61 3 9335 7111",
    "sg:postcode":"3045",
    "sg:province":"VIC",
    "sg:tags":[
        "broker",
        "custom"
    ],
    "wof:name":"BAX Global (Aust) Pty Ltd",
    "wof:placetype":"venue"
},
  "geometry": {"coordinates":[144.85505676299999,-37.6874694824],"type":"Point"}
}