{
  "type": "Feature",
  "properties": {
    "addr:full":"132 Hoddle St Collingwood VIC 3066",
    "addr:housenumber":"132",
    "addr:postcode":"3066",
    "addr:street":"Hoddle St",
    "iso:country":"AU",
    "sg:address":"132 Hoddle St",
    "sg:city":"Collingwood",
    "sg:classifiers":[
        {
            "category":"Retail",
            "subcategory":"Auto Repair",
            "type":"Services"
        }
    ],
    "sg:phone":"+61 3 9419 2233",
    "sg:postcode":"3066",
    "sg:province":"VIC",
    "sg:tags":[
        "camper-trailers",
        "caravan",
        "servicing"
    ],
    "wof:name":"ABS Auto Brake Service",
    "wof:placetype":"venue"
},
  "geometry": {"coordinates":[144.99250793499999,-37.8043441772],"type":"Point"}
}