{
  "type": "Feature",
  "properties": {
    "addr:full":"Suite 14 Forster Tower Wallis St Forster NSW 2428",
    "addr:postcode":"2428",
    "addr:street":"Wallis St",
    "iso:country":"AU",
    "sg:address":"Suite 14 Forster Tower Wallis St",
    "sg:city":"Forster",
    "sg:classifiers":[
        {
            "category":"Health Services",
            "subcategory":"Dentist",
            "type":"Services"
        }
    ],
    "sg:phone":"+61 2 6554 8821",
    "sg:postcode":"2428",
    "sg:province":"NSW",
    "sg:tags":[
        "technician",
        "dental"
    ],
    "wof:name":"Middlecoat Michael",
    "wof:placetype":"venue"
},
  "geometry": {"coordinates":[152.51724200000001,-32.181564],"type":"Point"}
}