{
  "type": "Feature",
  "properties": {
    "addr:full":"Unit 15/ 662 Stuart Hwy Berrimah NT 0828",
    "addr:housenumber":"/ 662",
    "addr:postcode":"nt 0828",
    "addr:street":"Stuart Hwy",
    "iso:country":"AU",
    "sg:address":"Unit 15/ 662 Stuart Hwy",
    "sg:city":"Berrimah",
    "sg:classifiers":[
        {
            "category":"Communications",
            "subcategory":"Newspaper",
            "type":"Services"
        }
    ],
    "sg:phone":"+61 8 8947 1157",
    "sg:postcode":"0828",
    "sg:province":"NT",
    "sg:tags":[
        "whiteboards",
        "chalkboard"
    ],
    "wof:name":"Corporate Design Floors N.T.",
    "wof:placetype":"venue"
},
  "geometry": {"coordinates":[130.92024230999999,-12.4325389862],"type":"Point"}
}