{
  "type": "Feature",
  "properties": {
    "addr:full":"152 Pacific Hwy Swansea NSW 2281",
    "addr:housenumber":"152",
    "addr:postcode":"2281",
    "addr:street":"Pacific Hwy",
    "iso:country":"AU",
    "sg:address":"152 Pacific Hwy",
    "sg:city":"Swansea",
    "sg:classifiers":[
        {
            "category":"Food & Beverages",
            "subcategory":"Liquor & Beverages",
            "type":"Retail Goods"
        }
    ],
    "sg:phone":"+61 2 4971 1787",
    "sg:postcode":"2281",
    "sg:province":"NSW",
    "sg:tags":[
        "store"
    ],
    "wof:name":"BWS Liquor Stores",
    "wof:placetype":"venue"
},
  "geometry": {"coordinates":[151.63763427699999,-33.0916938782],"type":"Point"}
}