{
  "type": "Feature",
  "properties": {
    "addr:full":"7 Exchange Drv Pakenham VIC 3810",
    "addr:housenumber":"7",
    "addr:postcode":"3810",
    "addr:street":"Exchange Drv",
    "iso:country":"AU",
    "sg:address":"7 Exchange Drv",
    "sg:city":"Pakenham",
    "sg:classifiers":[
        {
            "category":"Utilities",
            "subcategory":"Refuse",
            "type":"Services"
        }
    ],
    "sg:phone":"+61 409 232 286",
    "sg:postcode":"3810",
    "sg:province":"VIC",
    "sg:tags":[
        "disposal",
        "reduction",
        "waste"
    ],
    "wof:name":"PAK Bin Hire",
    "wof:placetype":"venue"
},
  "geometry": {"coordinates":[145.464584,-38.058754],"type":"Point"}
}