{
  "type": "Feature",
  "properties": {
    "addr:full":"26 Curry Rd Gympie QLD 4570",
    "addr:housenumber":"26",
    "addr:postcode":"4570",
    "addr:street":"Curry Rd",
    "iso:country":"AU",
    "sg:address":"26 Curry Rd",
    "sg:city":"Gympie",
    "sg:classifiers":[
        {
            "category":"Education",
            "subcategory":"Junior College",
            "type":"Public Place"
        }
    ],
    "sg:phone":"+61 7 5482 7445",
    "sg:postcode":"4570",
    "sg:province":"QLD",
    "sg:tags":[
        "wholesaler",
        "school",
        "mfrs",
        "uniform"
    ],
    "wof:name":"Overtops",
    "wof:placetype":"venue"
},
  "geometry": {"coordinates":[152.59939575199999,-26.1748428345],"type":"Point"}
}