{
  "type": "Feature",
  "properties": {
    "iso:country":"AU",
    "sg:address":"5 Willshire Pl",
    "sg:city":"Runcorn",
    "sg:classifiers":[
        {
            "category":"Professional",
            "subcategory":"Computer Services",
            "type":"Services"
        }
    ],
    "sg:phone":"+61 7 3276 1372",
    "sg:postcode":"4113",
    "sg:province":"QLD",
    "sg:tags":[
        "package",
        "software"
    ],
    "wof:name":"ACT Software",
    "wof:placetype":"venue"
},
  "geometry": {"coordinates":[153.06893920900001,-27.6108093262],"type":"Point"}
}