{
  "type": "Feature",
  "properties": {
    "addr:full":"20 Bond St Sale VIC 3850",
    "addr:housenumber":"20",
    "addr:postcode":"3850",
    "addr:street":"Bond St",
    "iso:country":"AU",
    "sg:address":"20 Bond St",
    "sg:city":"Sale",
    "sg:classifiers":[
        {
            "category":"Structure",
            "subcategory":"Factory",
            "type":"Public Place"
        }
    ],
    "sg:phone":"+61 3 5144 3043",
    "sg:postcode":"3850",
    "sg:province":"VIC",
    "sg:tags":[
        "seating",
        "system"
    ],
    "wof:name":"Gippsland Gas & Automotive",
    "wof:placetype":"venue"
},
  "geometry": {"coordinates":[147.06655883799999,-38.1104812622],"type":"Point"}
}