{
  "type": "Feature",
  "properties": {
    "addr:full":"54 Barnett Ave Glynde SA 5070",
    "addr:housenumber":"54",
    "addr:postcode":"5070",
    "addr:street":"Barnett Ave",
    "iso:country":"AU",
    "sg:address":"54 Barnett Ave",
    "sg:city":"Glynde",
    "sg:classifiers":[
        {
            "category":"Building & Trades",
            "subcategory":"Construction",
            "type":"Services"
        }
    ],
    "sg:phone":"+61 8 8336 4888",
    "sg:postcode":"5070",
    "sg:province":"SA",
    "sg:tags":[
        "excavation",
        "foundation"
    ],
    "wof:name":"Saccardo Constructions (SA) Pty Ltd",
    "wof:placetype":"venue"
},
  "geometry": {"coordinates":[138.65472412099999,-34.8965148926],"type":"Point"}
}