{
  "type": "Feature",
  "properties": {
    "addr:full":"72a New Beach Rd Darling Point NSW 2027",
    "addr:housenumber":"72a",
    "addr:postcode":"2027",
    "addr:street":"New Beach Rd",
    "iso:country":"AU",
    "sg:address":"72a New Beach Rd",
    "sg:city":"Darling Point",
    "sg:classifiers":[
        {
            "category":"Professional",
            "subcategory":"Art Services",
            "type":"Services"
        }
    ],
    "sg:phone":"+61 2 9327 8383",
    "sg:postcode":"2027",
    "sg:province":"NSW",
    "sg:tags":[
        "interior",
        "designer"
    ],
    "wof:name":"Love Michael Interior Design Pty Ltd",
    "wof:placetype":"venue"
},
  "geometry": {"coordinates":[151.23590087900001,-33.8695755005],"type":"Point"}
}