{
  "type": "Feature",
  "properties": {
    "iso:country":"AU",
    "sg:address":"498 Miller St",
    "sg:city":"Cammeray",
    "sg:classifiers":[
        {
            "category":"Shopping",
            "subcategory":"Clothing, Apparel, & Fashions",
            "type":"Retail Goods"
        }
    ],
    "sg:phone":"+61 2 9955 4965",
    "sg:postcode":"2062",
    "sg:province":"NSW",
    "sg:tags":[
        "lady",
        "wear"
    ],
    "wof:name":"Betty Annette Ladies And Childrens Wear",
    "wof:placetype":"venue"
},
  "geometry": {"coordinates":[151.21014404300001,-33.8226280212],"type":"Point"}
}