{
  "type": "Feature",
  "properties": {
    "addr:full":"PO Box 436 Cobram VIC 3644",
    "addr:postcode":"3644",
    "iso:country":"AU",
    "sg:address":"PO Box 436",
    "sg:city":"Cobram",
    "sg:classifiers":[
        {
            "category":"Building & Trades",
            "subcategory":"Plumbing",
            "type":"Services"
        }
    ],
    "sg:phone":"+61 429 352 084",
    "sg:postcode":"3644",
    "sg:province":"VIC",
    "sg:tags":[
        "plumber",
        "gasfitters"
    ],
    "wof:name":"Bob's Plumbing Pty Ltd",
    "wof:placetype":"venue"
},
  "geometry": {"coordinates":[145.663696289,-35.885181427],"type":"Point"}
}