{
  "type": "Feature",
  "properties": {
    "addr:full":"Shop 6 116 Diment Rd Salisbury North SA 5108",
    "addr:housenumber":"shop 6",
    "addr:postcode":"116;5108",
    "addr:street":"Diment Rd",
    "iso:country":"AU",
    "sg:address":"Shop 6 116 Diment Rd",
    "sg:city":"Salisbury North",
    "sg:classifiers":[
        {
            "category":"Personal",
            "subcategory":"Tattoo Parlor",
            "type":"Services"
        }
    ],
    "sg:phone":"+61 8 8285 4411",
    "sg:postcode":"5108",
    "sg:province":"SA",
    "sg:tags":[
        "tattooing"
    ],
    "wof:name":"Lords Of Ink Tattoo Studio",
    "wof:placetype":"venue"
},
  "geometry": {"coordinates":[138.62652587900001,-34.740196228],"type":"Point"}
}