{
  "type": "Feature",
  "properties": {
    "addr:full":"53 Maryann St Golden Beach QLD 4551",
    "addr:housenumber":"53",
    "addr:postcode":"4551",
    "addr:street":"Maryann St",
    "iso:country":"AU",
    "sg:address":"53 Maryann St",
    "sg:city":"Golden Beach",
    "sg:classifiers":[
        {
            "category":"Banks & Credit Unions",
            "subcategory":"Bank",
            "type":"Services"
        }
    ],
    "sg:phone":"+61 418 712 483",
    "sg:postcode":"4551",
    "sg:province":"QLD",
    "sg:tags":[
        "concrete",
        "reinforcement"
    ],
    "wof:name":"Civic Steelfixing",
    "wof:placetype":"venue"
},
  "geometry": {"coordinates":[153.11567688,-26.8377590179],"type":"Point"}
}