{
  "type": "Feature",
  "properties": {
    "addr:full":"Suite 201, 189 Queens St Melbourne VIC 3000",
    "addr:housenumber":"189",
    "addr:postcode":"3000",
    "addr:street":"Queens St",
    "iso:country":"AU",
    "sg:address":"Suite 201, 189 Queens St",
    "sg:city":"Melbourne",
    "sg:classifiers":[
        {
            "category":"Building & Trades",
            "subcategory":"Cleaning & Sanitation",
            "type":"Services"
        }
    ],
    "sg:phone":"+61 1800 114 400",
    "sg:postcode":"3000",
    "sg:province":"VIC",
    "sg:tags":[
        "industrial",
        "commercial",
        "contractor"
    ],
    "wof:name":"Service Alliance Group",
    "wof:placetype":"venue"
},
  "geometry": {"coordinates":[144.960174561,-37.8141365051],"type":"Point"}
}