{
  "type": "Feature",
  "properties": {
    "addr:full":"Beach Rd Nelson VIC 3292",
    "addr:postcode":"3292",
    "addr:street":"Beach Rd",
    "iso:country":"AU",
    "sg:address":"Beach Rd",
    "sg:city":"Nelson",
    "sg:classifiers":[
        {
            "category":"Recreation",
            "subcategory":"Boat Charter",
            "type":"Entertainment"
        }
    ],
    "sg:phone":"+61 8 8738 4191",
    "sg:postcode":"3292",
    "sg:province":"VIC",
    "wof:name":"Nelson Endeavour",
    "wof:placetype":"venue"
},
  "geometry": {"coordinates":[141.01681500000001,-38.062187],"type":"Point"}
}