{
  "type": "Feature",
  "properties": {
    "addr:full":"PO Box 419 Hampton Park VIC 3976",
    "addr:postcode":"3976",
    "iso:country":"AU",
    "sg:address":"PO Box 419",
    "sg:city":"Hampton Park",
    "sg:classifiers":[
        {
            "category":"Professional",
            "subcategory":"Business Services",
            "type":"Services"
        }
    ],
    "sg:phone":"+61 3 9799 6260",
    "sg:postcode":"3976",
    "sg:province":"VIC",
    "sg:tags":[
        "drafting"
    ],
    "wof:name":"Creative Living Designs",
    "wof:placetype":"venue"
},
  "geometry": {"coordinates":[145.26762390100001,-38.0422897339],"type":"Point"}
}