{
  "type": "Feature",
  "properties": {
    "addr:full":"Hudsons Rd Kuttabul QLD 4741",
    "addr:postcode":"4741",
    "addr:street":"Hudsons Rd",
    "iso:country":"AU",
    "sg:address":"Hudsons Rd",
    "sg:city":"Kuttabul",
    "sg:classifiers":[
        {
            "category":"Building & Trades",
            "subcategory":"Plumbing",
            "type":"Services"
        }
    ],
    "sg:phone":"+61 7 4954 0288",
    "sg:postcode":"4741",
    "sg:province":"QLD",
    "sg:tags":[
        "plumber",
        "gasfitters"
    ],
    "wof:name":"Findlay's G & J Drainage & Plumbing Co",
    "wof:placetype":"venue"
},
  "geometry": {"coordinates":[148.90725699999999,-21.048519],"type":"Point"}
}