{
  "type": "Feature",
  "properties": {
    "iso:country":"AU",
    "sg:address":"132 Hare St",
    "sg:city":"Echuca",
    "sg:classifiers":[
        {
            "category":"Building & Trades",
            "subcategory":"Equipment Rental",
            "type":"Services"
        }
    ],
    "sg:phone":"+61 3 5482 6661",
    "sg:postcode":"3564",
    "sg:province":"VIC",
    "sg:tags":[
        "fitness"
    ],
    "wof:name":"Bennett's Sports",
    "wof:placetype":"venue"
},
  "geometry": {"coordinates":[144.750091553,-36.1294212341],"type":"Point"}
}