{
  "type": "Feature",
  "properties": {
    "addr:full":"6/ 9 Almondbury Rd Mt Lawley WA 6050",
    "addr:housenumber":"/ 9",
    "addr:postcode":"6050",
    "addr:street":"Almondbury Rd",
    "iso:country":"AU",
    "sg:address":"6/ 9 Almondbury Rd",
    "sg:city":"Mt Lawley",
    "sg:classifiers":[
        {
            "category":"Banks & Credit Unions",
            "subcategory":"Bank",
            "type":"Services"
        }
    ],
    "sg:phone":"+61 1300 663 877",
    "sg:postcode":"6050",
    "sg:province":"WA",
    "sg:tags":[
        "broker",
        "mortgage"
    ],
    "sg:website":"http://www.completefinancial.com.au",
    "wof:name":"Complete Financial Services",
    "wof:placetype":"venue"
},
  "geometry": {"coordinates":[115.87779998800001,-31.9346199036],"type":"Point"}
}