{
  "type": "Feature",
  "properties": {
    "iso:country":"AU",
    "sg:address":"15 Rickmann Pl",
    "sg:city":"Wangara",
    "sg:classifiers":[
        {
            "category":"Retail",
            "subcategory":"Auto Repair",
            "type":"Services"
        }
    ],
    "sg:phone":"+61 417 181 465",
    "sg:postcode":"6065",
    "sg:province":"WA",
    "sg:tags":[
        "clutch",
        "brake"
    ],
    "wof:name":"Adaptable Mobile Mechanics",
    "wof:placetype":"venue"
},
  "geometry": {"coordinates":[115.84925842299999,-31.8318843842],"type":"Point"}
}