{
  "type": "Feature",
  "properties": {
    "addr:full":"Unit N4, Regents Park Estate, 391 Park Rd Regents Park NSW 2143",
    "addr:housenumber":"391",
    "addr:postcode":"2143",
    "addr:street":"Park Rd",
    "iso:country":"AU",
    "sg:address":"Unit N4, Regents Park Estate, 391 Park Rd",
    "sg:city":"Regents Park",
    "sg:classifiers":[
        {
            "category":"Wholesale",
            "subcategory":"Home Furnishings",
            "type":"Manufacturing & Wholesale Goods"
        }
    ],
    "sg:phone":"+61 2 9738 9999",
    "sg:postcode":"2143",
    "sg:province":"NSW",
    "sg:tags":[
        "wholesaler",
        "mfrs",
        "manchester"
    ],
    "wof:name":"Juslink (Aust) Pty Ltd",
    "wof:placetype":"venue"
},
  "geometry": {"coordinates":[151.023925781,-33.881942749],"type":"Point"}
}