{
  "type": "Feature",
  "properties": {
    "iso:country":"AU",
    "sg:address":"Memorial Drv",
    "sg:city":"Forster",
    "sg:classifiers":[
        {
            "category":"Recreation",
            "subcategory":"Boat Charter",
            "type":"Entertainment"
        }
    ],
    "sg:phone":"+61 419 333 445",
    "sg:postcode":"2428",
    "sg:province":"NSW",
    "wof:name":"Amaroo Dolphin Watch",
    "wof:placetype":"venue"
},
  "geometry": {"coordinates":[152.510864,-32.180775],"type":"Point"}
}