{
  "type": "Feature",
  "properties": {
    "iso:country":"AU",
    "sg:address":"14 Wilton Ave",
    "sg:city":"Somerton Park",
    "sg:classifiers":[
        {
            "category":"Building & Trades",
            "subcategory":"Equipment Rental",
            "type":"Services"
        }
    ],
    "sg:phone":"+61 8 8358 0011",
    "sg:postcode":"5044",
    "sg:province":"SA",
    "sg:tags":[
        "saw"
    ],
    "wof:name":"Giben Australia Pty Ltd",
    "wof:placetype":"venue"
},
  "geometry": {"coordinates":[138.521942,-34.999928],"type":"Point"}
}