{
  "type": "Feature",
  "properties": {
    "iso:country":"AU",
    "sg:address":"1/ 5 Callan St",
    "sg:city":"Mitchell",
    "sg:classifiers":[
        {
            "category":"Home & Garden",
            "subcategory":"Building Materials",
            "type":"Retail Goods"
        }
    ],
    "sg:phone":"+61 2 6255 4122",
    "sg:postcode":"2911",
    "sg:province":"ACT",
    "sg:tags":[
        "supply"
    ],
    "wof:name":"Commercial Building Centre",
    "wof:placetype":"venue"
},
  "geometry": {"coordinates":[149.143341064,-35.2142906189],"type":"Point"}
}