{
  "type": "Feature",
  "properties": {
    "addr:full":"91 Florence Rd Nedlands WA 6009",
    "addr:housenumber":"91",
    "addr:postcode":"6009",
    "addr:street":"Florence Rd",
    "iso:country":"AU",
    "sg:address":"91 Florence Rd",
    "sg:city":"Nedlands",
    "sg:classifiers":[
        {
            "category":"Professional",
            "subcategory":"Computer Services",
            "type":"Services"
        }
    ],
    "sg:phone":"+61 8 9386 3026",
    "sg:postcode":"6009",
    "sg:province":"WA",
    "sg:tags":[
        "consultant",
        "system"
    ],
    "wof:name":"Rees C & IT Pty Ltd",
    "wof:placetype":"venue"
},
  "geometry": {"coordinates":[115.80384100000001,-31.989033],"type":"Point"}
}