{
  "type": "Feature",
  "properties": {
    "addr:full":"Wharf Rd Port Hedland WA 6721",
    "addr:postcode":"6721",
    "addr:street":"Wharf Rd",
    "iso:country":"AU",
    "sg:address":"Wharf Rd",
    "sg:city":"Port Hedland",
    "sg:classifiers":[
        {
            "category":"Real Estate",
            "subcategory":"Surveying",
            "type":"Services"
        }
    ],
    "sg:phone":"+61 8 9173 2310",
    "sg:postcode":"6721",
    "sg:province":"WA",
    "sg:tags":[
        "surveyor",
        "marine",
        "cargo"
    ],
    "wof:name":"Intertek Testing Services",
    "wof:placetype":"venue"
},
  "geometry": {"coordinates":[118.46824646,-20.7532691956],"type":"Point"}
}