{
  "type": "Feature",
  "properties": {
    "addr:full":"25 Puckle St Moonee Ponds VIC 3039",
    "addr:housenumber":"25",
    "addr:postcode":"3039",
    "addr:street":"Puckle St",
    "iso:country":"AU",
    "sg:address":"25 Puckle St",
    "sg:city":"Moonee Ponds",
    "sg:classifiers":[
        {
            "category":"Cafe",
            "type":"Food & Drink"
        }
    ],
    "sg:phone":"+61 3 9372 7030",
    "sg:postcode":"3039",
    "sg:province":"VIC",
    "wof:name":"Gloria Jean's Coffees",
    "wof:placetype":"venue"
},
  "geometry": {"coordinates":[144.923599,-37.767082],"type":"Point"}
}