{
  "type": "Feature",
  "properties": {
    "iso:country":"AU",
    "sg:address":"Ford St",
    "sg:city":"Moruya",
    "sg:classifiers":[
        {
            "category":"Manufacturing",
            "subcategory":"Retail Goods",
            "type":"Manufacturing & Wholesale Goods"
        }
    ],
    "sg:phone":"+61 2 4474 3322",
    "sg:postcode":"2537",
    "sg:province":"NSW",
    "sg:tags":[
        "merchant",
        "pump",
        "mfrs"
    ],
    "wof:name":"Moruya Mower & Chainsaw Centre",
    "wof:placetype":"venue"
},
  "geometry": {"coordinates":[150.08314514200001,-35.911026001],"type":"Point"}
}