{
  "type": "Feature",
  "properties": {
    "iso:country":"AU",
    "sg:address":"20 Clare St",
    "sg:city":"New Town",
    "sg:classifiers":[
        {
            "category":"Organizations",
            "subcategory":"Community Association",
            "type":"Services"
        }
    ],
    "sg:phone":"+61 3 6211 4050",
    "sg:postcode":"7008",
    "sg:province":"TAS",
    "sg:tags":[
        "organisation",
        "family",
        "welfare"
    ],
    "wof:name":"Separation Mediation",
    "wof:placetype":"venue"
},
  "geometry": {"coordinates":[147.30874633799999,-42.8656387329],"type":"Point"}
}