{
  "type": "Feature",
  "properties": {
    "addr:full":"12 Shephards La Raywood VIC 3570",
    "addr:housenumber":"12",
    "addr:postcode":"3570",
    "addr:street":"Shephards La",
    "iso:country":"AU",
    "sg:address":"12 Shephards La",
    "sg:city":"Raywood",
    "sg:classifiers":[
        {
            "category":"Building & Trades",
            "subcategory":"Construction",
            "type":"Services"
        }
    ],
    "sg:phone":"+61 3 5436 1279",
    "sg:postcode":"3570",
    "sg:province":"VIC",
    "sg:tags":[
        "concrete",
        "contractor"
    ],
    "wof:name":"Warwick Higgins Concreter",
    "wof:placetype":"venue"
},
  "geometry": {"coordinates":[144.24330139200001,-36.5607795715],"type":"Point"}
}