{
  "type": "Feature",
  "properties": {
    "iso:country":"AU",
    "sg:address":"56 North Rd",
    "sg:city":"Newport",
    "sg:classifiers":[
        {
            "category":"Professional",
            "subcategory":"Art Services",
            "type":"Services"
        }
    ],
    "sg:phone":"+61 3 9391 9192",
    "sg:postcode":"3015",
    "sg:province":"VIC",
    "sg:tags":[
        "decorator",
        "painter"
    ],
    "wof:name":"Fresco Painting",
    "wof:placetype":"venue"
},
  "geometry": {"coordinates":[144.890228272,-37.8447265625],"type":"Point"}
}