{
  "type": "Feature",
  "properties": {
    "addr:full":"256 Hoods Rd Bundaberg QLD 4670",
    "addr:housenumber":"256",
    "addr:postcode":"4670",
    "addr:street":"Hoods Rd",
    "iso:country":"AU",
    "sg:address":"256 Hoods Rd",
    "sg:city":"Bundaberg",
    "sg:classifiers":[
        {
            "category":"Commercial Area",
            "type":"Public Place"
        }
    ],
    "sg:phone":"+61 7 4159 9751",
    "sg:postcode":"4670",
    "sg:province":"QLD",
    "sg:tags":[
        "heavy",
        "carrier"
    ],
    "wof:name":"DJ & MD Erb",
    "wof:placetype":"venue"
},
  "geometry": {"coordinates":[152.274993897,-24.8154830933],"type":"Point"}
}