{
  "type": "Feature",
  "properties": {
    "addr:full":"68 Ariah St Ardlethan NSW 2665",
    "addr:housenumber":"68",
    "addr:postcode":"2665",
    "addr:street":"Ariah St",
    "iso:country":"AU",
    "sg:address":"68 Ariah St",
    "sg:city":"Ardlethan",
    "sg:classifiers":[
        {
            "category":"Personal",
            "subcategory":"Beauty Salon",
            "type":"Services"
        }
    ],
    "sg:phone":"+61 2 6978 2119",
    "sg:postcode":"2665",
    "sg:province":"NSW",
    "sg:tags":[
        "hairdresser"
    ],
    "wof:name":"Ardlethan Hair & Beauty",
    "wof:placetype":"venue"
},
  "geometry": {"coordinates":[146.904907227,-34.3581123352],"type":"Point"}
}