{
  "type": "Feature",
  "properties": {
    "iso:country":"AU",
    "sg:address":"1 Nicholson St",
    "sg:city":"Toronto",
    "sg:classifiers":[
        {
            "category":"Social Services",
            "subcategory":"Adult Care",
            "type":"Services"
        }
    ],
    "sg:phone":"+61 2 4950 4600",
    "sg:postcode":"2283",
    "sg:province":"NSW",
    "sg:tags":[
        "towing"
    ],
    "wof:name":"Toronto Towing Service",
    "wof:placetype":"venue"
},
  "geometry": {"coordinates":[151.57344055199999,-33.0016708374],"type":"Point"}
}