{
  "type": "Feature",
  "properties": {
    "addr:full":"Unit 22/ 140 Addison Rd Manly NSW 2095",
    "addr:housenumber":"/ 140",
    "addr:postcode":"2095",
    "addr:street":"Addison Rd",
    "iso:country":"AU",
    "sg:address":"Unit 22/ 140 Addison Rd",
    "sg:city":"Manly",
    "sg:classifiers":[
        {
            "category":"Sports & Exercise",
            "subcategory":"Ski Resort",
            "type":"Entertainment"
        }
    ],
    "sg:phone":"+61 2 9976 3192",
    "sg:postcode":"2095",
    "sg:province":"NSW",
    "sg:tags":[
        "tour",
        "centres"
    ],
    "wof:name":"Dulmison Ski Club Ltd",
    "wof:placetype":"venue"
},
  "geometry": {"coordinates":[151.29173278799999,-33.8015289307],"type":"Point"}
}