{
  "type": "Feature",
  "properties": {
    "iso:country":"AU",
    "sg:address":"2a Ramsay Ave",
    "sg:city":"Mt Gambier",
    "sg:classifiers":[
        {
            "category":"Freight",
            "type":"Transportation"
        }
    ],
    "sg:phone":"+61 13 15 31",
    "sg:postcode":"5290",
    "sg:province":"SA",
    "sg:tags":[
        "light",
        "carrier"
    ],
    "wof:name":"Wards Skyroad",
    "wof:placetype":"venue"
},
  "geometry": {"coordinates":[140.803314,-37.834171],"type":"Point"}
}