{
  "type": "Feature",
  "properties": {
    "addr:full":"6 bundoran Pde Mont Albert North VIC 3129",
    "addr:housenumber":"6",
    "addr:postcode":"3129",
    "addr:street":"Bundoran Pde",
    "iso:country":"AU",
    "sg:address":"6 bundoran Pde",
    "sg:city":"Mont Albert North",
    "sg:classifiers":[
        {
            "category":"Building & Trades",
            "subcategory":"Construction",
            "type":"Services"
        }
    ],
    "sg:phone":"+61 414 310 521",
    "sg:postcode":"3129",
    "sg:province":"VIC",
    "sg:tags":[
        "joiner",
        "carpenter"
    ],
    "wof:name":"Ardent Carpentry",
    "wof:placetype":"venue"
},
  "geometry": {"coordinates":[145.10403442399999,-37.8094596863],"type":"Point"}
}