{
  "type": "Feature",
  "properties": {
    "addr:full":"42 Galston Rd Hornsby NSW 2077",
    "addr:housenumber":"42",
    "addr:postcode":"2077",
    "addr:street":"Galston Rd",
    "iso:country":"AU",
    "sg:address":"42 Galston Rd",
    "sg:city":"Hornsby",
    "sg:classifiers":[
        {
            "category":"Banks & Credit Unions",
            "subcategory":"Financial Services",
            "type":"Services"
        }
    ],
    "sg:phone":"+61 2 9477 5541",
    "sg:postcode":"2077",
    "sg:province":"NSW",
    "sg:tags":[
        "financier"
    ],
    "wof:name":"Nextpay Finance Pty Ltd",
    "wof:placetype":"venue"
},
  "geometry": {"coordinates":[151.09611511200001,-33.6860084534],"type":"Point"}
}