{
  "type": "Feature",
  "properties": {
    "addr:full":"8 Homburg Drv Murray Bridge SA 5253",
    "addr:housenumber":"8",
    "addr:postcode":"5253",
    "addr:street":"Homburg Drv",
    "iso:country":"AU",
    "sg:address":"8 Homburg Drv",
    "sg:city":"Murray Bridge",
    "sg:classifiers":[
        {
            "category":"Health Services",
            "subcategory":"Doctor",
            "type":"Services"
        }
    ],
    "sg:phone":"+61 8 8532 4500",
    "sg:postcode":"5253",
    "sg:province":"SA",
    "sg:tags":[
        "medical",
        "practitioner"
    ],
    "wof:name":"Bridge Clinic",
    "wof:placetype":"venue"
},
  "geometry": {"coordinates":[139.28176879899999,-35.1357574463],"type":"Point"}
}