{
  "type": "Feature",
  "properties": {
    "addr:full":"Level 2, 120 Erina St Gosford NSW 2250",
    "addr:housenumber":"120",
    "addr:postcode":"2250",
    "addr:street":"Erina St",
    "iso:country":"AU",
    "sg:address":"Level 2, 120 Erina St",
    "sg:city":"Gosford",
    "sg:classifiers":[
        {
            "category":"Professional",
            "subcategory":"Art Services",
            "type":"Services"
        }
    ],
    "sg:phone":"+61 2 4323 4331",
    "sg:postcode":"2250",
    "sg:province":"NSW",
    "sg:tags":[
        "graphic",
        "designer"
    ],
    "wof:name":"Anthouse Communications",
    "wof:placetype":"venue"
},
  "geometry": {"coordinates":[151.34370422399999,-33.4250144958],"type":"Point"}
}