{
  "type": "Feature",
  "properties": {
    "addr:full":"191- 193 Newcastle St Jesmond NSW 2299",
    "addr:housenumber":"193",
    "addr:postcode":"2299",
    "addr:street":"Newcastle St",
    "iso:country":"AU",
    "sg:address":"191- 193 Newcastle St",
    "sg:city":"Jesmond",
    "sg:classifiers":[
        {
            "category":"Travel",
            "subcategory":"Hotels & Motels",
            "type":"Entertainment"
        }
    ],
    "sg:phone":"+61 2 4929 6677",
    "sg:postcode":"2299",
    "sg:province":"NSW",
    "wof:name":"Bimet Executive Lodge",
    "wof:placetype":"venue"
},
  "geometry": {"coordinates":[151.69158935600001,-32.9053878784],"type":"Point"}
}