{
  "type": "Feature",
  "properties": {
    "addr:full":"21/ 55 Salvado Rd Subiaco WA 6008",
    "addr:housenumber":"21 / 55",
    "addr:postcode":"6008",
    "addr:street":"Salvado Rd",
    "iso:country":"AU",
    "sg:address":"21/ 55 Salvado Rd",
    "sg:city":"Subiaco",
    "sg:classifiers":[
        {
            "category":"Building & Trades",
            "subcategory":"Construction",
            "type":"Services"
        }
    ],
    "sg:phone":"+61 8 9381 4411",
    "sg:postcode":"6008",
    "sg:province":"WA",
    "sg:tags":[
        "home",
        "air conditioning"
    ],
    "sg:website":"http://www.needhamair.com.au",
    "wof:name":"Needhamair",
    "wof:placetype":"venue"
},
  "geometry": {"coordinates":[115.820007324,-31.9419345856],"type":"Point"}
}