{
  "type": "Feature",
  "properties": {
    "iso:country":"AU",
    "sg:address":"239b Victoria St",
    "sg:city":"Ballarat",
    "sg:classifiers":[
        {
            "category":"Bars & Pubs",
            "subcategory":"Nightclub",
            "type":"Food & Drink"
        }
    ],
    "sg:phone":"+61 3 5334 4408",
    "sg:postcode":"3350",
    "sg:province":"VIC",
    "sg:tags":[
        "karaoke"
    ],
    "wof:name":"Redwood Entertainment",
    "wof:placetype":"venue"
},
  "geometry": {"coordinates":[143.88400300000001,-37.558685],"type":"Point"}
}