{
  "type": "Feature",
  "properties": {
    "addr:full":"Shop 3, 132 Wyong Rd Killarney Vale NSW 2261",
    "addr:housenumber":"shop 3",
    "addr:postcode":"132;2261",
    "addr:street":"Wyong Rd",
    "iso:country":"AU",
    "sg:address":"Shop 3, 132 Wyong Rd",
    "sg:city":"Killarney Vale",
    "sg:classifiers":[
        {
            "category":"Shopping",
            "subcategory":"Computers & Home Electronics",
            "type":"Retail Goods"
        }
    ],
    "sg:phone":"+61 2 4334 1855",
    "sg:postcode":"2261",
    "sg:province":"NSW",
    "sg:tags":[
        "equipment",
        "supply"
    ],
    "wof:name":"Cartridge World",
    "wof:placetype":"venue"
},
  "geometry": {"coordinates":[151.462616,-33.366055],"type":"Point"}
}