{
  "type": "Feature",
  "properties": {
    "iso:country":"AU",
    "sg:address":"Shop 3- 143 Old Pacific Hwy",
    "sg:city":"Oxenford",
    "sg:classifiers":[
        {
            "category":"Utilities",
            "subcategory":"Electric",
            "type":"Services"
        }
    ],
    "sg:phone":"+61 7 5580 5790",
    "sg:postcode":"4210",
    "sg:province":"QLD",
    "sg:tags":[
        "electrical",
        "contractor"
    ],
    "wof:name":"Broad Electrical & Air Conditioning",
    "wof:placetype":"venue"
},
  "geometry": {"coordinates":[153.31350707999999,-27.8899822235],"type":"Point"}
}