{
  "type": "Feature",
  "properties": {
    "addr:full":"S7 Westfield Pl Blacktown NSW 2148",
    "addr:housenumber":"s7",
    "addr:postcode":"2148",
    "addr:street":"Westfield Pl",
    "iso:country":"AU",
    "sg:address":"S7 Westfield Pl",
    "sg:city":"Blacktown",
    "sg:classifiers":[
        {
            "category":"Personal",
            "subcategory":"Beauty Salon",
            "type":"Services"
        }
    ],
    "sg:phone":"+61 2 9671 4121",
    "sg:postcode":"2148",
    "sg:province":"NSW",
    "sg:tags":[
        "hairdresser"
    ],
    "wof:name":"Rainbow Hairstyle",
    "wof:placetype":"venue"
},
  "geometry": {"coordinates":[150.90826415999999,-33.7700996399],"type":"Point"}
}