{
  "type": "Feature",
  "properties": {
    "addr:full":"42 - 46 Tarnard Drv Braeside VIC 3195",
    "addr:housenumber":"46",
    "addr:postcode":"3195",
    "addr:street":"Tarnard Drv",
    "iso:country":"AU",
    "sg:address":"42 - 46 Tarnard Drv",
    "sg:city":"Braeside",
    "sg:classifiers":[
        {
            "category":"Industrial Area",
            "type":"Public Place"
        }
    ],
    "sg:phone":"+61 1800 133 098",
    "sg:postcode":"3195",
    "sg:province":"VIC",
    "sg:tags":[
        "rural",
        "shed"
    ],
    "sg:website":"http://www.trubilt.com.au",
    "wof:name":"Tru-Bilt Fabrications Pty Ltd",
    "wof:placetype":"venue"
},
  "geometry": {"coordinates":[145.11408996599999,-37.9895324707],"type":"Point"}
}