{
  "type": "Feature",
  "properties": {
    "iso:country":"AU",
    "sg:address":"46 Northumberland Drv",
    "sg:city":"Epping",
    "sg:classifiers":[
        {
            "category":"Professional",
            "subcategory":"Engineering",
            "type":"Services"
        }
    ],
    "sg:phone":"+61 3 9401 3765",
    "sg:postcode":"3076",
    "sg:province":"VIC",
    "sg:tags":[
        "engineer"
    ],
    "wof:name":"Epping Engineering",
    "wof:placetype":"venue"
},
  "geometry": {"coordinates":[145.03651428200001,-37.6416473389],"type":"Point"}
}