{
  "type": "Feature",
  "properties": {
    "addr:full":"31 Glen Eira Rd Ripponlea VIC 3185",
    "addr:housenumber":"31",
    "addr:postcode":"3185",
    "addr:street":"Glen Eira Rd",
    "iso:country":"AU",
    "sg:address":"31 Glen Eira Rd",
    "sg:city":"Ripponlea",
    "sg:classifiers":[
        {
            "category":"Shopping",
            "subcategory":"Clothing, Apparel, & Fashions",
            "type":"Retail Goods"
        }
    ],
    "sg:phone":"+61 3 9523 7482",
    "sg:postcode":"3185",
    "sg:province":"VIC",
    "sg:tags":[
        "accessory"
    ],
    "wof:name":"Riva Caffe Della Moda",
    "wof:placetype":"venue"
},
  "geometry": {"coordinates":[144.99621582,-37.8765602112],"type":"Point"}
}