{
  "type": "Feature",
  "properties": {
    "iso:country":"AU",
    "sg:address":"66 Ryan St",
    "sg:city":"Footscray",
    "sg:classifiers":[
        {
            "category":"Health Services",
            "subcategory":"Doctor",
            "type":"Services"
        }
    ],
    "sg:phone":"+61 3 9689 8852",
    "sg:postcode":"3011",
    "sg:province":"VIC",
    "sg:tags":[
        "medical",
        "practitioner"
    ],
    "wof:name":"Thai D B",
    "wof:placetype":"venue"
},
  "geometry": {"coordinates":[144.90139770499999,-37.7984352112],"type":"Point"}
}