{
  "type": "Feature",
  "properties": {
    "addr:full":"16 Fig St Yungaburra QLD 4884",
    "addr:housenumber":"16",
    "addr:postcode":"4884",
    "addr:street":"Fig St",
    "iso:country":"AU",
    "sg:address":"16 Fig St",
    "sg:city":"Yungaburra",
    "sg:classifiers":[
        {
            "category":"Banks & Credit Unions",
            "subcategory":"Bureau De Change",
            "type":"Services"
        }
    ],
    "sg:phone":"+61 7 4095 3737",
    "sg:postcode":"4884",
    "sg:province":"QLD",
    "sg:tags":[
        "archaeology"
    ],
    "wof:name":"Gordon Grimwade & Associates",
    "wof:placetype":"venue"
},
  "geometry": {"coordinates":[145.58428955100001,-17.270362854],"type":"Point"}
}