{
  "type": "Feature",
  "properties": {
    "addr:full":"406 Blessington Rd White Hills TAS 7258",
    "addr:housenumber":"406",
    "addr:postcode":"7258",
    "addr:street":"Blessington Rd",
    "iso:country":"AU",
    "sg:address":"406 Blessington Rd",
    "sg:city":"White Hills",
    "sg:classifiers":[
        {
            "category":"Building & Trades",
            "subcategory":"Construction",
            "type":"Services"
        }
    ],
    "sg:phone":"+61 417 319 924",
    "sg:postcode":"7258",
    "sg:province":"TAS",
    "sg:tags":[
        "contractor"
    ],
    "wof:name":"Aaron Chugg Building Contractors",
    "wof:placetype":"venue"
},
  "geometry": {"coordinates":[147.240234375,-41.4939460754],"type":"Point"}
}