{
  "type": "Feature",
  "properties": {
    "addr:full":"&#034;Marrambang&#034; Redground Heights Rd Laggan NSW 2583",
    "addr:postcode":"2583",
    "addr:street":"Heights Rd",
    "iso:country":"AU",
    "sg:address":"&#034;Marrambang&#034; Redground Heights Rd",
    "sg:city":"Laggan",
    "sg:classifiers":[
        {
            "category":"Train Station",
            "subcategory":"Rail",
            "type":"Transportation"
        }
    ],
    "sg:phone":"+61 2 4837 3327",
    "sg:postcode":"2583",
    "sg:province":"NSW",
    "sg:tags":[
        "goat",
        "farmer"
    ],
    "wof:name":"Cady W.R. & L.A.",
    "wof:placetype":"venue"
},
  "geometry": {"coordinates":[149.47807312,-34.4063148499],"type":"Point"}
}