{
  "type": "Feature",
  "properties": {
    "iso:country":"AU",
    "sg:address":"61 Blaxland Rd",
    "sg:city":"Campbelltown",
    "sg:classifiers":[
        {
            "category":"Home & Garden",
            "subcategory":"Carpets & Floor Coverings",
            "type":"Retail Goods"
        }
    ],
    "sg:phone":"+61 2 4628 8465",
    "sg:postcode":"2560",
    "sg:province":"NSW",
    "sg:tags":[
        "tile",
        "wall"
    ],
    "wof:name":"Bargain Tile Market",
    "wof:placetype":"venue"
},
  "geometry": {"coordinates":[150.810714722,-34.0612945557],"type":"Point"}
}