{
  "type": "Feature",
  "properties": {
    "addr:full":"47 Panalatinga Rd Woodcroft SA 5162",
    "addr:housenumber":"47",
    "addr:postcode":"5162",
    "addr:street":"Panalatinga Rd",
    "iso:country":"AU",
    "sg:address":"47 Panalatinga Rd",
    "sg:city":"Woodcroft",
    "sg:classifiers":[
        {
            "category":"Building & Trades",
            "subcategory":"Construction",
            "type":"Services"
        }
    ],
    "sg:phone":"+61 409 322 414",
    "sg:postcode":"5162",
    "sg:province":"SA",
    "sg:tags":[
        "fencing",
        "contractor"
    ],
    "wof:name":"Lochness Fencing",
    "wof:placetype":"venue"
},
  "geometry": {"coordinates":[138.54791259800001,-35.1061248779],"type":"Point"}
}