{
  "type": "Feature",
  "properties": {
    "addr:full":"Cnr Hepburn Ave & Wanaroo Rd Landsdale WA 6065",
    "addr:postcode":"6065",
    "addr:street":"Cnr Hepburn Ave & Wanaroo Rd",
    "iso:country":"AU",
    "sg:address":"Cnr Hepburn Ave & Wanaroo Rd",
    "sg:city":"Landsdale",
    "sg:classifiers":[
        {
            "category":"Health Services",
            "subcategory":"Health Practitioner",
            "type":"Services"
        }
    ],
    "sg:phone":"+61 8 9409 3993",
    "sg:postcode":"6065",
    "sg:province":"WA",
    "sg:tags":[
        "physiotherapist"
    ],
    "wof:name":"Stuart White",
    "wof:placetype":"venue"
},
  "geometry": {"coordinates":[115.86859893800001,-31.8209400177],"type":"Point"}
}