{
  "type": "Feature",
  "properties": {
    "addr:full":"294 Albury St Murrumburrah NSW 2587",
    "addr:housenumber":"294",
    "addr:postcode":"2587",
    "addr:street":"Albury St",
    "iso:country":"AU",
    "sg:address":"294 Albury St",
    "sg:city":"Murrumburrah",
    "sg:classifiers":[
        {
            "category":"Autos & Motor Vehicles",
            "subcategory":"Fuel & Gas Station",
            "type":"Retail Goods"
        }
    ],
    "sg:phone":"+61 2 6386 2652",
    "sg:postcode":"2587",
    "sg:province":"NSW",
    "wof:name":"R & B Partners",
    "wof:placetype":"venue"
},
  "geometry": {"coordinates":[148.35157775900001,-34.5498046875],"type":"Point"}
}