{
  "type": "Feature",
  "properties": {
    "iso:country":"AU",
    "sg:address":"17 Counihan Rd",
    "sg:city":"Seventeen Mile Rocks",
    "sg:classifiers":[
        {
            "category":"Manufacturing",
            "subcategory":"Metals",
            "type":"Manufacturing & Wholesale Goods"
        }
    ],
    "sg:phone":"+61 7 3376 2723",
    "sg:postcode":"4073",
    "sg:province":"QLD",
    "sg:tags":[
        "steel",
        "fabricator",
        "mfrs"
    ],
    "wof:name":"Brewer Doug Pty Ltd",
    "wof:placetype":"venue"
},
  "geometry": {"coordinates":[152.957519531,-27.5408267975],"type":"Point"}
}