{
  "type": "Feature",
  "properties": {
    "addr:full":"PO Box 928 Warners Bay NSW 2282",
    "addr:postcode":"2282",
    "iso:country":"AU",
    "sg:address":"PO Box 928",
    "sg:city":"Warners Bay",
    "sg:classifiers":[
        {
            "category":"Professional",
            "subcategory":"Testing Lab",
            "type":"Services"
        }
    ],
    "sg:phone":"+61 407 258 128",
    "sg:postcode":"2282",
    "sg:province":"NSW",
    "sg:tags":[
        "inspection"
    ],
    "wof:name":"Just Testin & Taggin",
    "wof:placetype":"venue"
},
  "geometry": {"coordinates":[151.64869689899999,-32.973110199],"type":"Point"}
}