{
  "type": "Feature",
  "properties": {
    "addr:full":"Level 1 North Bldg 34 Glenferrie Dr Robina QLD 4226",
    "addr:housenumber":"34",
    "addr:postcode":"4226",
    "addr:street":"Glenferrie Dr",
    "iso:country":"AU",
    "sg:address":"Level 1 North Bldg 34 Glenferrie Dr",
    "sg:city":"Robina",
    "sg:classifiers":[
        {
            "category":"Professional",
            "subcategory":"Accounting & Tax Preparation",
            "type":"Services"
        }
    ],
    "sg:phone":"+61 7 5575 7400",
    "sg:postcode":"4226",
    "sg:province":"QLD",
    "sg:tags":[
        "consultant",
        "taxation"
    ],
    "wof:name":"Core Group The",
    "wof:placetype":"venue"
},
  "geometry": {"coordinates":[153.40196227999999,-28.064289093],"type":"Point"}
}