{
  "type": "Feature",
  "properties": {
    "addr:full":"104a Canterbury Rd Blackburn South VIC 3130",
    "addr:housenumber":"104a",
    "addr:postcode":"3130",
    "addr:street":"Canterbury Rd",
    "iso:country":"AU",
    "sg:address":"104a Canterbury Rd",
    "sg:city":"Blackburn South",
    "sg:classifiers":[
        {
            "category":"Fast Food",
            "type":"Food & Drink"
        }
    ],
    "sg:phone":"+61 3 9878 4169",
    "sg:postcode":"3130",
    "sg:province":"VIC",
    "sg:tags":[
        "away",
        "take"
    ],
    "wof:name":"Con's Fish & Chips",
    "wof:placetype":"venue"
},
  "geometry": {"coordinates":[145.14649963400001,-37.8318328857],"type":"Point"}
}