{
  "type": "Feature",
  "properties": {
    "addr:full":"Level 1 & 2 Wallace Bishop Building, 117 Queen St Mall Brisbane City QLD 4000",
    "addr:housenumber":"& 2;117",
    "addr:postcode":"4000",
    "addr:street":"Wallace;Queen St Mall",
    "iso:country":"AU",
    "sg:address":"Level 1 & 2 Wallace Bishop Building, 117 Queen St",
    "sg:city":"Mall Brisbane City",
    "sg:classifiers":[
        {
            "category":"Personal",
            "subcategory":"Piercing",
            "type":"Services"
        }
    ],
    "sg:phone":"+61 7 3229 5149",
    "sg:postcode":"4000",
    "sg:province":"QLD",
    "sg:tags":[
        "body",
        "ear"
    ],
    "wof:name":"The Piercing Shop",
    "wof:placetype":"venue"
},
  "geometry": {"coordinates":[153.024993897,-27.4699859619],"type":"Point"}
}