{
  "type": "Feature",
  "properties": {
    "addr:full":"2/ 25 Allens Pde Lennox Head NSW 2478",
    "addr:housenumber":"/ 25",
    "addr:postcode":"2478",
    "addr:street":"Allens Pde",
    "iso:country":"AU",
    "sg:address":"2/ 25 Allens Pde",
    "sg:city":"Lennox Head",
    "sg:classifiers":[
        {
            "category":"Personal",
            "subcategory":"Massage",
            "type":"Services"
        }
    ],
    "sg:phone":"+61 2 6687 6662",
    "sg:postcode":"2478",
    "sg:province":"NSW",
    "sg:tags":[
        "therapy"
    ],
    "wof:name":"Thea Woznitza-Soothing Touch",
    "wof:placetype":"venue"
},
  "geometry": {"coordinates":[153.594116211,-28.7999000549],"type":"Point"}
}