{
  "type": "Feature",
  "properties": {
    "iso:country":"AU",
    "sg:address":"151 Chapel St",
    "sg:city":"St Kilda",
    "sg:classifiers":[
        {
            "category":"Professional",
            "subcategory":"Accounting & Tax Preparation",
            "type":"Services"
        }
    ],
    "sg:phone":"+61 3 9534 6969",
    "sg:postcode":"3182",
    "sg:province":"VIC",
    "sg:tags":[
        "consultant",
        "taxation"
    ],
    "wof:name":"Gnieslaw Isaac",
    "wof:placetype":"venue"
},
  "geometry": {"coordinates":[144.99026489299999,-37.8679962158],"type":"Point"}
}