{
  "type": "Feature",
  "properties": {
    "addr:full":"9 Pandanus St Noosa Heads QLD 4567",
    "addr:housenumber":"9",
    "addr:postcode":"4567",
    "addr:street":"Pandanus St",
    "iso:country":"AU",
    "sg:address":"9 Pandanus St",
    "sg:city":"Noosa Heads",
    "sg:classifiers":[
        {
            "category":"Personal",
            "subcategory":"Massage",
            "type":"Services"
        }
    ],
    "sg:phone":"+61 421 285 858",
    "sg:postcode":"4567",
    "sg:province":"QLD",
    "sg:tags":[
        "therapy"
    ],
    "wof:name":"Tatyana Pozar-Burgar",
    "wof:placetype":"venue"
},
  "geometry": {"coordinates":[153.09654235799999,-26.3849582672],"type":"Point"}
}