{
  "type": "Feature",
  "properties": {
    "addr:full":"132 Fairfield St Mt Hawthorn WA 6016",
    "addr:housenumber":"132",
    "addr:postcode":"6016",
    "addr:street":"Fairfield St Mt",
    "iso:country":"AU",
    "sg:address":"132 Fairfield St",
    "sg:city":"Mt Hawthorn",
    "sg:classifiers":[
        {
            "category":"Building & Trades",
            "subcategory":"Construction",
            "type":"Services"
        }
    ],
    "sg:phone":"+61 408 385 357",
    "sg:postcode":"6016",
    "sg:province":"WA",
    "sg:tags":[
        "renovation",
        "alterations",
        "extension",
        "contractor"
    ],
    "wof:name":"Finial Home Services",
    "wof:placetype":"venue"
},
  "geometry": {"coordinates":[115.840118408,-31.9243335724],"type":"Point"}
}