{
  "type": "Feature",
  "properties": {
    "addr:full":"521 Tomago Rd Tomago NSW 2322",
    "addr:housenumber":"521",
    "addr:postcode":"2322",
    "addr:street":"Tomago Rd",
    "iso:country":"AU",
    "sg:address":"521 Tomago Rd",
    "sg:city":"Tomago",
    "sg:classifiers":[
        {
            "category":"Manufacturing",
            "subcategory":"Metals",
            "type":"Manufacturing & Wholesale Goods"
        }
    ],
    "sg:phone":"+61 2 4964 8300",
    "sg:postcode":"2322",
    "sg:province":"NSW",
    "sg:tags":[
        "steel",
        "fabricator",
        "mfrs"
    ],
    "sg:website":"http://www.twwoods.com.au",
    "wof:name":"T. W. Woods Construction Pty. Ltd.",
    "wof:placetype":"venue"
},
  "geometry": {"coordinates":[151.70884704599999,-32.8268013],"type":"Point"}
}