{
  "type": "Feature",
  "properties": {
    "addr:full":"442 Cambridge St Floreat WA 6014",
    "addr:housenumber":"442",
    "addr:postcode":"6014",
    "addr:street":"Cambridge St",
    "iso:country":"AU",
    "sg:address":"442 Cambridge St",
    "sg:city":"Floreat",
    "sg:classifiers":[
        {
            "category":"Deli",
            "type":"Food & Drink"
        }
    ],
    "sg:phone":"+61 8 9387 4046",
    "sg:postcode":"6014",
    "sg:province":"WA",
    "sg:tags":[
        "delicatessen"
    ],
    "wof:name":"Floreat Mini-Mart",
    "wof:placetype":"venue"
},
  "geometry": {"coordinates":[115.801139831,-31.9406452179],"type":"Point"}
}