{
  "type": "Feature",
  "properties": {
    "iso:country":"AU",
    "sg:address":"Jindabyne Rd",
    "sg:city":"Berridale",
    "sg:classifiers":[
        {
            "category":"Fast Food",
            "type":"Food & Drink"
        }
    ],
    "sg:phone":"+61 2 6456 3552",
    "sg:postcode":"2628",
    "sg:province":"NSW",
    "sg:tags":[
        "away",
        "take"
    ],
    "wof:name":"Tasty Takeaway",
    "wof:placetype":"venue"
},
  "geometry": {"coordinates":[148.825897217,-36.3664627075],"type":"Point"}
}