{
  "type": "Feature",
  "properties": {
    "addr:full":"Unit 1002/ 6 Crestridge Cres Oxenford QLD 4210",
    "addr:housenumber":"1002 / 6",
    "addr:postcode":"4210",
    "addr:street":"Crestridge Cres",
    "iso:country":"AU",
    "sg:address":"Unit 1002/ 6",
    "sg:city":"Crestridge Cres Oxenford",
    "sg:classifiers":[
        {
            "category":"Banks & Credit Unions",
            "subcategory":"Investment Brokerage",
            "type":"Services"
        }
    ],
    "sg:phone":"+61 7 5573 7779",
    "sg:postcode":"4210",
    "sg:province":"QLD",
    "sg:tags":[
        "management",
        "property"
    ],
    "wof:name":"Terraces On The Park",
    "wof:placetype":"venue"
},
  "geometry": {"coordinates":[153.31111145,-27.9195766449],"type":"Point"}
}