{
  "type": "Feature",
  "properties": {
    "iso:country":"AU",
    "sg:address":"PO Box 1227",
    "sg:city":"+ Mildura Centre Plaza",
    "sg:classifiers":[
        {
            "category":"Retail",
            "subcategory":"Storage",
            "type":"Services"
        }
    ],
    "sg:phone":"+61 3 5024 3848",
    "sg:postcode":"3501",
    "sg:province":"VIC",
    "sg:tags":[
        "removal",
        "furniture"
    ],
    "wof:name":"Sunraysia Furniture Removals & Caravan Towing",
    "wof:placetype":"venue"
},
  "geometry": {"coordinates":[142.13630676299999,-34.2071113586],"type":"Point"}
}