{
  "type": "Feature",
  "properties": {
    "addr:full":"3 Nagle Ave Maroubra NSW 2035",
    "addr:housenumber":"3",
    "addr:postcode":"2035",
    "addr:street":"Nagle Ave",
    "iso:country":"AU",
    "sg:address":"3 Nagle Ave",
    "sg:city":"Maroubra",
    "sg:classifiers":[
        {
            "category":"Personal",
            "subcategory":"Beauty Salon",
            "type":"Services"
        }
    ],
    "sg:phone":"+61 2 9344 0638",
    "sg:postcode":"2035",
    "sg:province":"NSW",
    "sg:tags":[
        "supply",
        "artist",
        "make-up"
    ],
    "wof:name":"Creative Faces Make-Up",
    "wof:placetype":"venue"
},
  "geometry": {"coordinates":[151.236816406,-33.9431724548],"type":"Point"}
}