{
  "type": "Feature",
  "properties": {
    "iso:country":"AU",
    "sg:address":"21 Hudson Rd",
    "sg:city":"Albion",
    "sg:classifiers":[
        {
            "category":"Building & Trades",
            "subcategory":"Locksmith",
            "type":"Services"
        }
    ],
    "sg:phone":"+61 7 3262 7777",
    "sg:postcode":"4010",
    "sg:province":"QLD",
    "sg:tags":[
        "strongroom",
        "safe",
        "door"
    ],
    "wof:name":"J. Larsen Pty. Ltd.",
    "wof:placetype":"venue"
},
  "geometry": {"coordinates":[153.041015625,-27.4316921234],"type":"Point"}
}