{
  "type": "Feature",
  "properties": {
    "addr:full":"2/ 25 Brendan Drv Nerang QLD 4211",
    "addr:housenumber":"/ 25",
    "addr:postcode":"4211",
    "addr:street":"Brendan Drv",
    "iso:country":"AU",
    "sg:address":"2/ 25 Brendan Drv",
    "sg:city":"Nerang",
    "sg:classifiers":[
        {
            "category":"Farming",
            "subcategory":"Fish & Marine Products",
            "type":"Manufacturing & Wholesale Goods"
        }
    ],
    "sg:phone":"+61 7 5596 2856",
    "sg:postcode":"4211",
    "sg:province":"QLD",
    "sg:tags":[
        "wholesaler",
        "mfrs",
        "swimwear"
    ],
    "wof:name":"Nova Sportswear",
    "wof:placetype":"venue"
},
  "geometry": {"coordinates":[153.34413147000001,-27.9986686707],"type":"Point"}
}