{
  "type": "Feature",
  "properties": {
    "addr:full":"10 Baretta Rd Wangara WA 6065",
    "addr:housenumber":"10",
    "addr:postcode":"6065",
    "addr:street":"Baretta Rd",
    "iso:country":"AU",
    "sg:address":"10 Baretta Rd",
    "sg:city":"Wangara",
    "sg:classifiers":[
        {
            "category":"Farming",
            "subcategory":"Farm & Veterinary Services",
            "type":"Manufacturing & Wholesale Goods"
        }
    ],
    "sg:phone":"+61 8 9409 4804",
    "sg:postcode":"6065",
    "sg:province":"WA",
    "sg:tags":[
        "poultry",
        "processing",
        "supply"
    ],
    "wof:name":"Select Poultry (WA)",
    "wof:placetype":"venue"
},
  "geometry": {"coordinates":[115.81764984100001,-31.7922401428],"type":"Point"}
}