{
  "type": "Feature",
  "properties": {
    "addr:full":"Beaury St Urbenville NSW 2475",
    "addr:postcode":"2475",
    "iso:country":"AU",
    "sg:address":"Beaury St",
    "sg:city":"Urbenville",
    "sg:classifiers":[
        {
            "category":"Health Services",
            "subcategory":"Doctor",
            "type":"Services"
        }
    ],
    "sg:phone":"+61 2 6634 1275",
    "sg:postcode":"2475",
    "sg:province":"NSW",
    "sg:tags":[
        "medical",
        "practitioner"
    ],
    "wof:name":"Lee H L",
    "wof:placetype":"venue"
},
  "geometry": {"coordinates":[152.547073364,-28.472612381],"type":"Point"}
}