{
  "type": "Feature",
  "properties": {
    "addr:full":"13 Bindley Crt Kilmore VIC 3764",
    "addr:housenumber":"13",
    "addr:postcode":"3764",
    "addr:street":"Bindley Crt",
    "iso:country":"AU",
    "sg:address":"13 Bindley Crt",
    "sg:city":"Kilmore",
    "sg:classifiers":[
        {
            "category":"Retail",
            "subcategory":"Repair Shop",
            "type":"Services"
        }
    ],
    "sg:phone":"+61 3 5781 1822",
    "sg:postcode":"3764",
    "sg:province":"VIC",
    "sg:tags":[
        "leadlights"
    ],
    "wof:name":"Kilmore Leadlights",
    "wof:placetype":"venue"
},
  "geometry": {"coordinates":[144.94238281200001,-37.3203544617],"type":"Point"}
}