{
  "type": "Feature",
  "properties": {
    "addr:full":"The Walk Building, 2 Edgeworth David Av, Hornsby NSW 2077",
    "addr:postcode":"2077",
    "addr:street":"Av",
    "iso:country":"AU",
    "sg:address":"The Walk Building, 2",
    "sg:city":"Edgeworth David Av, Hornsby",
    "sg:classifiers":[
        {
            "category":"Banks & Credit Unions",
            "subcategory":"Financial Services",
            "type":"Services"
        }
    ],
    "sg:phone":"+61 2 9482 8333",
    "sg:postcode":"2077",
    "sg:province":"NSW",
    "sg:tags":[
        "financier"
    ],
    "wof:name":"The Small Loan Company North Shore",
    "wof:placetype":"venue"
},
  "geometry": {"coordinates":[151.104705811,-33.7062721252],"type":"Point"}
}