{
  "type": "Feature",
  "properties": {
    "addr:full":"104 Balwyn Rd Balwyn VIC 3103",
    "addr:housenumber":"104",
    "addr:postcode":"3103",
    "addr:street":"Balwyn Rd",
    "iso:country":"AU",
    "sg:address":"104 Balwyn Rd",
    "sg:city":"Balwyn",
    "sg:classifiers":[
        {
            "category":"Social Services",
            "subcategory":"Child Care",
            "type":"Services"
        }
    ],
    "sg:phone":"+61 3 9836 5928",
    "sg:postcode":"3103",
    "sg:province":"VIC",
    "wof:name":"3 Apples Childcare Centre & Kindergarten",
    "wof:placetype":"venue"
},
  "geometry": {"coordinates":[145.081756592,-37.8114204407],"type":"Point"}
}