{
  "type": "Feature",
  "properties": {
    "iso:country":"AU",
    "sg:address":"49 Adelphi St",
    "sg:city":"Rouse Hill",
    "sg:classifiers":[
        {
            "category":"Health Services",
            "subcategory":"Chiropractor",
            "type":"Services"
        }
    ],
    "sg:phone":"+61 416 087 418",
    "sg:postcode":"2155",
    "sg:province":"NSW",
    "wof:name":"Advanced Chiropractic Care",
    "wof:placetype":"venue"
},
  "geometry": {"coordinates":[150.91563415499999,-33.6793289185],"type":"Point"}
}