{
  "type": "Feature",
  "properties": {
    "addr:full":"GPO Box 689 Kalamunda WA 6076",
    "addr:postcode":"6076",
    "iso:country":"AU",
    "sg:address":"GPO Box 689",
    "sg:city":"Kalamunda",
    "sg:classifiers":[
        {
            "category":"Home & Garden",
            "subcategory":"Carpets & Floor Coverings",
            "type":"Retail Goods"
        }
    ],
    "sg:phone":"+61 418 946 616",
    "sg:postcode":"6076",
    "sg:province":"WA",
    "sg:tags":[
        "flooring",
        "parquet"
    ],
    "wof:name":"Floor Restore",
    "wof:placetype":"venue"
},
  "geometry": {"coordinates":[116.04212951700001,-31.9614639282],"type":"Point"}
}