{
  "type": "Feature",
  "properties": {
    "addr:full":"370 Elamo Rd Healesville VIC 3777",
    "addr:housenumber":"370",
    "addr:postcode":"3777",
    "addr:street":"Elamo Rd",
    "iso:country":"AU",
    "sg:address":"370 Elamo Rd",
    "sg:city":"Healesville",
    "sg:classifiers":[
        {
            "category":"Retail",
            "subcategory":"Auto Rental",
            "type":"Services"
        }
    ],
    "sg:phone":"+61 3 5962 5694",
    "sg:postcode":"3777",
    "sg:province":"VIC",
    "sg:tags":[
        "car",
        "hire",
        "minibus"
    ],
    "wof:name":"Yarra Valley Discovery Minibus Hire",
    "wof:placetype":"venue"
},
  "geometry": {"coordinates":[145.52726699999999,-37.650864],"type":"Point"}
}