{
  "type": "Feature",
  "properties": {
    "addr:full":"Douglas St Toorak VIC 3142",
    "addr:postcode":"3142",
    "addr:street":"Douglas St",
    "iso:country":"AU",
    "sg:address":"Douglas St",
    "sg:city":"Toorak",
    "sg:classifiers":[
        {
            "category":"Utilities",
            "subcategory":"Refuse",
            "type":"Services"
        }
    ],
    "sg:phone":"+61 435 091 950",
    "sg:postcode":"3142",
    "sg:province":"VIC",
    "sg:tags":[
        "remover",
        "rubbish"
    ],
    "wof:name":"A1 Rubbish",
    "wof:placetype":"venue"
},
  "geometry": {"coordinates":[145.00933837900001,-37.8391647339],"type":"Point"}
}