{
  "type": "Feature",
  "properties": {
    "addr:full":"Suite 1 Labour Centre 82 Beaufort St Perth WA 6000",
    "addr:housenumber":"82",
    "addr:postcode":"6000",
    "addr:street":"Beaufort St",
    "iso:country":"AU",
    "sg:address":"Suite 1 Labour Centre 82 Beaufort St",
    "sg:city":"Perth",
    "sg:classifiers":[
        {
            "category":"Organizations",
            "subcategory":"Non-profit Organization",
            "type":"Services"
        }
    ],
    "sg:phone":"+61 8 9328 3169",
    "sg:postcode":"6000",
    "sg:province":"WA",
    "sg:tags":[
        "support",
        "disability",
        "organisation"
    ],
    "wof:name":"Disabled Workers Union",
    "wof:placetype":"venue"
},
  "geometry": {"coordinates":[115.862747192,-31.9496097565],"type":"Point"}
}