{
  "type": "Feature",
  "properties": {
    "iso:country":"AU",
    "sg:address":"133 King St",
    "sg:city":"Newcastle",
    "sg:classifiers":[
        {
            "category":"Health Services",
            "subcategory":"Health Practitioner",
            "type":"Services"
        }
    ],
    "sg:phone":"+61 414 923 479",
    "sg:postcode":"2300",
    "sg:province":"NSW",
    "sg:tags":[
        "hypnotherapy"
    ],
    "wof:name":"Colleen Wilson",
    "wof:placetype":"venue"
},
  "geometry": {"coordinates":[151.769577,-32.928207],"type":"Point"}
}