{
  "type": "Feature",
  "properties": {
    "addr:full":"20 Pauline St Tarragindi QLD 4121",
    "addr:housenumber":"20",
    "addr:postcode":"4121",
    "addr:street":"Pauline St",
    "iso:country":"AU",
    "sg:address":"20 Pauline St",
    "sg:city":"Tarragindi",
    "sg:classifiers":[
        {
            "category":"Professional",
            "subcategory":"Engineering",
            "type":"Services"
        }
    ],
    "sg:phone":"+61 7 3848 4902",
    "sg:postcode":"4121",
    "sg:province":"QLD",
    "sg:tags":[
        "consulting",
        "engineer"
    ],
    "wof:name":"Holding Ralph & Associates Pty Ltd",
    "wof:placetype":"venue"
},
  "geometry": {"coordinates":[153.03921508799999,-27.5173110962],"type":"Point"}
}