{
  "type": "Feature",
  "properties": {
    "addr:full":"34 Hawkesbury Rd Springwood NSW 2777",
    "addr:housenumber":"34",
    "addr:postcode":"2777",
    "addr:street":"Hawkesbury Rd",
    "iso:country":"AU",
    "sg:address":"34 Hawkesbury Rd",
    "sg:city":"Springwood",
    "sg:classifiers":[
        {
            "category":"Sports & Exercise",
            "subcategory":"Gym",
            "type":"Entertainment"
        }
    ],
    "sg:phone":"+61 2 4751 8200",
    "sg:postcode":"2777",
    "sg:province":"NSW",
    "sg:tags":[
        "health",
        "fitness"
    ],
    "wof:name":"Mannatech Independent Associates",
    "wof:placetype":"venue"
},
  "geometry": {"coordinates":[150.57426452600001,-33.6954498291],"type":"Point"}
}