{
  "type": "Feature",
  "properties": {
    "iso:country":"AU",
    "sg:address":"Shop 4, Luxford Rd",
    "sg:city":"Shalvey",
    "sg:classifiers":[
        {
            "category":"Food & Beverages",
            "subcategory":"Liquor & Beverages",
            "type":"Retail Goods"
        }
    ],
    "sg:phone":"+61 2 9628 5199",
    "sg:postcode":"2770",
    "sg:province":"NSW",
    "sg:tags":[
        "store"
    ],
    "wof:name":"Shalvey Liquor Supplies",
    "wof:placetype":"venue"
},
  "geometry": {"coordinates":[150.809448242,-33.7291297913],"type":"Point"}
}