{
  "type": "Feature",
  "properties": {
    "addr:full":"129 Main St Cressy TAS 7302",
    "addr:housenumber":"129",
    "addr:postcode":"7302",
    "addr:street":"Main St",
    "iso:country":"AU",
    "sg:address":"129 Main St",
    "sg:city":"Cressy",
    "sg:classifiers":[
        {
            "category":"Professional",
            "subcategory":"Art Services",
            "type":"Services"
        }
    ],
    "sg:phone":"+61 3 6397 6252",
    "sg:postcode":"7302",
    "sg:province":"TAS",
    "sg:tags":[
        "decorator",
        "painter"
    ],
    "wof:name":"Brian Cotton Painting Service",
    "wof:placetype":"venue"
},
  "geometry": {"coordinates":[147.079055786,-41.6924285889],"type":"Point"}
}