{
  "type": "Feature",
  "properties": {
    "addr:full":"16 Lr Dandenong Rd Mentone VIC 3194",
    "addr:housenumber":"16",
    "addr:postcode":"3194",
    "addr:street":"Dandenong Rd",
    "iso:country":"AU",
    "sg:address":"16 Lr Dandenong Rd",
    "sg:city":"Mentone",
    "sg:classifiers":[
        {
            "category":"Shopping",
            "subcategory":"Clothing, Apparel, & Fashions",
            "type":"Retail Goods"
        }
    ],
    "sg:phone":"+61 3 9583 6671",
    "sg:postcode":"3194",
    "sg:province":"VIC",
    "sg:tags":[
        "boutique"
    ],
    "wof:name":"Middle Of The Road Fashions",
    "wof:placetype":"venue"
},
  "geometry": {"coordinates":[145.07673645,-37.9827194214],"type":"Point"}
}