{
  "type": "Feature",
  "properties": {
    "iso:country":"AU",
    "sg:address":"7 Samdon St",
    "sg:city":"Hamilton",
    "sg:classifiers":[
        {
            "category":"Professional",
            "subcategory":"Printing & Photocopies",
            "type":"Services"
        }
    ],
    "sg:phone":"+61 2 4922 1111",
    "sg:postcode":"2303",
    "sg:province":"NSW",
    "sg:tags":[
        "photocopier"
    ],
    "wof:name":"Ricoh Business Centre",
    "wof:placetype":"venue"
},
  "geometry": {"coordinates":[151.74205000000001,-32.922924],"type":"Point"}
}