{
  "type": "Feature",
  "properties": {
    "addr:full":"Unit 1/ 102 Racecourse Rd Rutherford NSW 2320",
    "addr:housenumber":"/ 102",
    "addr:postcode":"2320",
    "addr:street":"Racecourse Rd",
    "iso:country":"AU",
    "sg:address":"Unit 1/ 102 Racecourse Rd",
    "sg:city":"Rutherford",
    "sg:classifiers":[
        {
            "category":"Wholesale",
            "subcategory":"Machinery & Supplies",
            "type":"Manufacturing & Wholesale Goods"
        }
    ],
    "sg:phone":"+61 2 4932 4555",
    "sg:postcode":"2320",
    "sg:province":"NSW",
    "sg:tags":[
        "bearing",
        "bushing"
    ],
    "wof:name":"Bearing Dynamics Pty Ltd",
    "wof:placetype":"venue"
},
  "geometry": {"coordinates":[151.51568603499999,-32.7120323181],"type":"Point"}
}