{
  "type": "Feature",
  "properties": {
    "addr:full":"5 Rupert Drv Mulgrave VIC 3170",
    "addr:housenumber":"5",
    "addr:postcode":"3170",
    "addr:street":"Rupert Drv",
    "iso:country":"AU",
    "sg:address":"5 Rupert Drv",
    "sg:city":"Mulgrave",
    "sg:classifiers":[
        {
            "category":"Insurance",
            "subcategory":"Insurance Agent",
            "type":"Services"
        }
    ],
    "sg:phone":"+61 3 9558 5555",
    "sg:postcode":"3170",
    "sg:province":"VIC",
    "wof:name":"Foley Charles & Associates",
    "wof:placetype":"venue"
},
  "geometry": {"coordinates":[145.177642822,-37.9297218323],"type":"Point"}
}