{
  "type": "Feature",
  "properties": {
    "iso:country":"AU",
    "sg:address":"23 Anderson St",
    "sg:city":"Cairns",
    "sg:classifiers":[
        {
            "category":"Shopping",
            "subcategory":"Pets & Pet Supplies",
            "type":"Retail Goods"
        }
    ],
    "sg:phone":"+61 7 4041 1415",
    "sg:postcode":"4870",
    "sg:province":"QLD",
    "sg:tags":[
        "food"
    ],
    "wof:name":"Pet Cafe The",
    "wof:placetype":"venue"
},
  "geometry": {"coordinates":[145.75320434599999,-16.9135932922],"type":"Point"}
}