{
  "type": "Feature",
  "properties": {
    "addr:full":"St Helen St Isisford QLD 4731",
    "addr:postcode":"4731",
    "addr:street":"St Isisford",
    "iso:country":"AU",
    "sg:address":"St Helen St",
    "sg:city":"Isisford",
    "sg:classifiers":[
        {
            "category":"Education",
            "subcategory":"School",
            "type":"Public Place"
        }
    ],
    "sg:phone":"+61 7 4658 8186",
    "sg:postcode":"4731",
    "sg:province":"QLD",
    "sg:tags":[
        "state",
        "except",
        "nsw"
    ],
    "wof:name":"Isisford Primary School",
    "wof:placetype":"venue"
},
  "geometry": {"coordinates":[144.439987,-24.261658],"type":"Point"}
}