{
  "type": "Feature",
  "properties": {
    "addr:full":"10 Princes Hwy Lakes Entrance VIC 3909",
    "addr:housenumber":"10",
    "addr:postcode":"3909",
    "addr:street":"Princes Hwy",
    "iso:country":"AU",
    "sg:address":"10 Princes Hwy",
    "sg:city":"Lakes Entrance",
    "sg:classifiers":[
        {
            "category":"Travel",
            "subcategory":"Hotels & Motels",
            "type":"Entertainment"
        }
    ],
    "sg:phone":"+61 3 5155 2841",
    "sg:postcode":"3909",
    "sg:province":"VIC",
    "wof:name":"Golden Chain Lakes Waterfront Motel",
    "wof:placetype":"venue"
},
  "geometry": {"coordinates":[148.007125855,-37.8754005432],"type":"Point"}
}