{
  "type": "Feature",
  "properties": {
    "addr:full":"Unit 7, 270 Pacific Hwy Artarmon NSW 2064",
    "addr:housenumber":"270",
    "addr:postcode":"2064",
    "addr:street":"Pacific Hwy",
    "iso:country":"AU",
    "sg:address":"Unit 7, 270 Pacific Hwy",
    "sg:city":"Artarmon",
    "sg:classifiers":[
        {
            "category":"Professional",
            "subcategory":"Computer Services",
            "type":"Services"
        }
    ],
    "sg:phone":"+61 407 245 169",
    "sg:postcode":"2064",
    "sg:province":"NSW",
    "sg:tags":[
        "consultant",
        "system"
    ],
    "wof:name":"ByteWise Solutions Pty Ltd",
    "wof:placetype":"venue"
},
  "geometry": {"coordinates":[151.180343628,-33.8174476624],"type":"Point"}
}