{
  "type": "Feature",
  "properties": {
    "addr:full":"PO Box 1227 Tully QLD 4854",
    "addr:postcode":"4854",
    "iso:country":"AU",
    "sg:address":"PO Box 1227",
    "sg:city":"Tully",
    "sg:classifiers":[
        {
            "category":"Recreation",
            "subcategory":"Fishing",
            "type":"Entertainment"
        }
    ],
    "sg:phone":"+61 408 871 849",
    "sg:postcode":"4854",
    "sg:province":"QLD",
    "sg:tags":[
        "trip"
    ],
    "wof:name":"Hinchinbrook Explorer Fishing",
    "wof:placetype":"venue"
},
  "geometry": {"coordinates":[145.93263244600001,-17.933889389],"type":"Point"}
}