{
  "type": "Feature",
  "properties": {
    "addr:full":"184 Welshpool Rd Welshpool WA 6106",
    "addr:housenumber":"184",
    "addr:postcode":"6106",
    "addr:street":"Welshpool Rd",
    "iso:country":"AU",
    "sg:address":"184 Welshpool Rd",
    "sg:city":"Welshpool",
    "sg:classifiers":[
        {
            "category":"Retail",
            "subcategory":"Auto Rental",
            "type":"Services"
        }
    ],
    "sg:phone":"+61 8 9458 6222",
    "sg:postcode":"6106",
    "sg:province":"WA",
    "sg:tags":[
        "car",
        "hire",
        "minibus"
    ],
    "wof:name":"Avis",
    "wof:placetype":"venue"
},
  "geometry": {"coordinates":[115.938751221,-31.9955368042],"type":"Point"}
}