{
  "type": "Feature",
  "properties": {
    "addr:full":"33 Market St Merimbula NSW 2548",
    "addr:housenumber":"33",
    "addr:postcode":"2548",
    "addr:street":"Market St",
    "iso:country":"AU",
    "sg:address":"33 Market St",
    "sg:city":"Merimbula",
    "sg:classifiers":[
        {
            "category":"Insurance",
            "subcategory":"Insurance Agent",
            "type":"Services"
        }
    ],
    "sg:phone":"+61 2 6495 9643",
    "sg:postcode":"2548",
    "sg:province":"NSW",
    "sg:tags":[
        "broker"
    ],
    "wof:name":"M&F Agencies Pty Ltd",
    "wof:placetype":"venue"
},
  "geometry": {"coordinates":[149.91046142600001,-36.8886489868],"type":"Point"}
}