{
  "type": "Feature",
  "properties": {
    "addr:full":"24 Temple Drv Thomastown VIC 3074",
    "addr:housenumber":"24",
    "addr:postcode":"3074",
    "addr:street":"Temple Drv",
    "iso:country":"AU",
    "sg:address":"24 Temple Drv",
    "sg:city":"Thomastown",
    "sg:classifiers":[
        {
            "category":"Wholesale",
            "subcategory":"Metals & Minerals",
            "type":"Manufacturing & Wholesale Goods"
        }
    ],
    "sg:phone":"+61 3 9465 6488",
    "sg:postcode":"3074",
    "sg:province":"VIC",
    "sg:tags":[
        "steel",
        "stainless",
        "product",
        "equipment"
    ],
    "wof:name":"Tubesales (Vic) Pty Ltd",
    "wof:placetype":"venue"
},
  "geometry": {"coordinates":[145.01658630399999,-37.6902313232],"type":"Point"}
}