{
  "type": "Feature",
  "properties": {
    "iso:country":"AU",
    "sg:address":"81 Adelaide St",
    "sg:city":"Maryborough",
    "sg:classifiers":[
        {
            "category":"Professional",
            "subcategory":"Accounting & Tax Preparation",
            "type":"Services"
        }
    ],
    "sg:phone":"+61 7 4123 1931",
    "sg:postcode":"4650",
    "sg:province":"QLD",
    "sg:tags":[
        "consultant",
        "taxation"
    ],
    "wof:name":"Lewis, Lynton, Accountant",
    "wof:placetype":"venue"
},
  "geometry": {"coordinates":[152.700409,-25.540262],"type":"Point"}
}