{
  "type": "Feature",
  "properties": {
    "addr:full":"194 Henry Lawson Drv Mudgee NSW 2850",
    "addr:housenumber":"194",
    "addr:postcode":"2850",
    "addr:street":"Henry Lawson Drv",
    "iso:country":"AU",
    "sg:address":"194 Henry Lawson Drv",
    "sg:city":"Mudgee",
    "sg:classifiers":[
        {
            "category":"Farming",
            "subcategory":"Vineyard",
            "type":"Manufacturing & Wholesale Goods"
        }
    ],
    "sg:phone":"+61 2 6372 2461",
    "sg:postcode":"2850",
    "sg:province":"NSW",
    "sg:tags":[
        "winery"
    ],
    "wof:name":"Vinifera Wines",
    "wof:placetype":"venue"
},
  "geometry": {"coordinates":[149.60644500000001,-32.559864],"type":"Point"}
}