{
  "type": "Feature",
  "properties": {
    "iso:country":"AU",
    "sg:address":"15 Tweed Crt",
    "sg:city":"Langwarrin",
    "sg:classifiers":[
        {
            "category":"Retail",
            "subcategory":"Auto Repair",
            "type":"Services"
        }
    ],
    "sg:phone":"+61 3 9775 5710",
    "sg:postcode":"3910",
    "sg:province":"VIC",
    "sg:tags":[
        "beater",
        "painter",
        "panel"
    ],
    "wof:name":"Touch Up Panels",
    "wof:placetype":"venue"
},
  "geometry": {"coordinates":[145.182403564,-38.1586608887],"type":"Point"}
}