{
  "type": "Feature",
  "properties": {
    "addr:full":"5 Read St Canton Beach NSW 2263",
    "addr:housenumber":"5",
    "addr:postcode":"2263",
    "addr:street":"Read St",
    "iso:country":"AU",
    "sg:address":"5 Read St",
    "sg:city":"Canton Beach",
    "sg:classifiers":[
        {
            "category":"Professional",
            "subcategory":"Art Services",
            "type":"Services"
        }
    ],
    "sg:phone":"+61 2 4396 3978",
    "sg:postcode":"2263",
    "sg:province":"NSW",
    "sg:tags":[
        "graphic",
        "designer"
    ],
    "wof:name":"F2 Graphics",
    "wof:placetype":"venue"
},
  "geometry": {"coordinates":[151.54800399999999,-33.271149],"type":"Point"}
}