{
  "type": "Feature",
  "properties": {
    "addr:full":"231 A Miller Rd Bass Hill NSW 2197",
    "addr:housenumber":"231",
    "addr:postcode":"2197",
    "addr:street":"A Miller Rd",
    "iso:country":"AU",
    "sg:address":"231 A Miller Rd",
    "sg:city":"Bass Hill",
    "sg:classifiers":[
        {
            "category":"Education",
            "subcategory":"University",
            "type":"Public Place"
        }
    ],
    "sg:phone":"+61 2 9786 4495",
    "sg:postcode":"2197",
    "sg:province":"NSW",
    "sg:tags":[
        "educational",
        "organisation",
        "cultural"
    ],
    "wof:name":"Platypy Collective Art Group",
    "wof:placetype":"venue"
},
  "geometry": {"coordinates":[150.99288899999999,-33.900612],"type":"Point"}
}