{
  "type": "Feature",
  "properties": {
    "iso:country":"AU",
    "sg:address":"PO Box 75",
    "sg:city":"Parndana",
    "sg:classifiers":[
        {
            "category":"Building & Trades",
            "subcategory":"Construction",
            "type":"Services"
        }
    ],
    "sg:phone":"+61 8 8553 9030",
    "sg:postcode":"5220",
    "sg:province":"SA",
    "sg:tags":[
        "contractor"
    ],
    "wof:name":"Nic Flynn Building",
    "wof:placetype":"venue"
},
  "geometry": {"coordinates":[137.25697326700001,-35.7837905884],"type":"Point"}
}