{
  "type": "Feature",
  "properties": {
    "addr:full":"Shop 5/ 66 Jessica Blv Minyama QLD 4575",
    "addr:housenumber":"shop 5 / 66",
    "addr:postcode":"4575",
    "addr:street":"Jessica Blv",
    "iso:country":"AU",
    "sg:address":"Shop 5/ 66 Jessica Blv",
    "sg:city":"Minyama",
    "sg:classifiers":[
        {
            "category":"Personal",
            "subcategory":"Skin Care",
            "type":"Services"
        }
    ],
    "sg:phone":"+61 7 5444 0099",
    "sg:postcode":"4575",
    "sg:province":"QLD",
    "sg:tags":[
        "treatment"
    ],
    "wof:name":"Jardin Salon De Beaute^A",
    "wof:placetype":"venue"
},
  "geometry": {"coordinates":[153.1241,-26.698917],"type":"Point"}
}