{
  "type": "Feature",
  "properties": {
    "addr:full":"30 Oak St Brightview QLD 4311",
    "addr:housenumber":"30",
    "addr:postcode":"4311",
    "addr:street":"Oak St",
    "iso:country":"AU",
    "sg:address":"30 Oak St",
    "sg:city":"Brightview",
    "sg:classifiers":[
        {
            "category":"Farming",
            "subcategory":"Fish & Marine Products",
            "type":"Manufacturing & Wholesale Goods"
        }
    ],
    "sg:phone":"+61 7 5427 9522",
    "sg:postcode":"4311",
    "sg:province":"QLD",
    "sg:tags":[
        "organic"
    ],
    "wof:name":"Jiedy Pty Ltd",
    "wof:placetype":"venue"
},
  "geometry": {"coordinates":[152.48875427199999,-27.5193023682],"type":"Point"}
}