{
  "type": "Feature",
  "properties": {
    "addr:full":"Lot 57 Cooke St Kingston SE SA 5275",
    "addr:postcode":"5275",
    "addr:street":"Cooke St",
    "iso:country":"AU",
    "sg:address":"Lot 57 Cooke St",
    "sg:city":"Kingston SE",
    "sg:classifiers":[
        {
            "category":"Utilities",
            "subcategory":"Fuel Oil & Lpg",
            "type":"Services"
        }
    ],
    "sg:phone":"+61 8 8767 2602",
    "sg:postcode":"5275",
    "sg:province":"SA",
    "sg:tags":[
        "merchant"
    ],
    "wof:name":"Barrett Distributors",
    "wof:placetype":"venue"
},
  "geometry": {"coordinates":[139.85127299999999,-36.829933],"type":"Point"}
}