{
  "type": "Feature",
  "properties": {
    "addr:full":"23 Marlborough St Fulham Gardens SA 5024",
    "addr:housenumber":"23",
    "addr:postcode":"5024",
    "addr:street":"Marlborough St",
    "iso:country":"AU",
    "sg:address":"23 Marlborough St",
    "sg:city":"Fulham Gardens",
    "sg:classifiers":[
        {
            "category":"Professional",
            "subcategory":"Art Services",
            "type":"Services"
        }
    ],
    "sg:phone":"+61 8 8353 5007",
    "sg:postcode":"5024",
    "sg:province":"SA",
    "sg:tags":[
        "decorator",
        "painter"
    ],
    "wof:name":"Theo's Painting Service",
    "wof:placetype":"venue"
},
  "geometry": {"coordinates":[138.51017761200001,-34.9129981995],"type":"Point"}
}