{
  "type": "Feature",
  "properties": {
    "addr:full":"72 Edmund Ave Unley SA 5061",
    "addr:housenumber":"72",
    "addr:postcode":"5061",
    "addr:street":"Edmund Ave",
    "iso:country":"AU",
    "sg:address":"72 Edmund Ave",
    "sg:city":"Unley",
    "sg:classifiers":[
        {
            "category":"Arts & Performance",
            "subcategory":"Theater",
            "type":"Entertainment"
        }
    ],
    "sg:phone":"+61 8 8272 3036",
    "sg:postcode":"5061",
    "sg:province":"SA",
    "sg:tags":[
        "theatre"
    ],
    "wof:name":"Urban Myth Theatre Of Youth",
    "wof:placetype":"venue"
},
  "geometry": {"coordinates":[138.60931396500001,-34.9514694214],"type":"Point"}
}