{
  "type": "Feature",
  "properties": {
    "addr:full":"Mudlo Rd Kilkivan QLD 4600",
    "addr:postcode":"4600",
    "addr:street":"Mudlo Rd",
    "iso:country":"AU",
    "sg:address":"Mudlo Rd",
    "sg:city":"Kilkivan",
    "sg:classifiers":[
        {
            "category":"Building & Trades",
            "subcategory":"Landscaping Services",
            "type":"Services"
        }
    ],
    "sg:phone":"+61 7 5484 1157",
    "sg:postcode":"4600",
    "sg:province":"QLD",
    "sg:tags":[
        "grazier"
    ],
    "wof:name":"Lawlor R W",
    "wof:placetype":"venue"
},
  "geometry": {"coordinates":[152.23999000000001,-26.076166],"type":"Point"}
}