{
  "type": "Feature",
  "properties": {
    "addr:full":"PO Box 609 Greenacre NSW 2190",
    "addr:postcode":"2190",
    "iso:country":"AU",
    "sg:address":"PO Box 609",
    "sg:city":"Greenacre",
    "sg:classifiers":[
        {
            "category":"Home & Garden",
            "subcategory":"Carpets & Floor Coverings",
            "type":"Retail Goods"
        }
    ],
    "sg:phone":"+61 2 9596 4466",
    "sg:postcode":"2190",
    "sg:province":"NSW",
    "sg:tags":[
        "wood"
    ],
    "wof:name":"GM Flooring Services Pty Ltd",
    "wof:placetype":"venue"
},
  "geometry": {"coordinates":[151.06634500000001,-33.895401],"type":"Point"}
}