{
  "type": "Feature",
  "properties": {
    "addr:full":"77 Parry St Newcastle West NSW 2302",
    "addr:housenumber":"77",
    "addr:postcode":"2302",
    "addr:street":"Parry St",
    "iso:country":"AU",
    "sg:address":"77 Parry St",
    "sg:city":"Newcastle West",
    "sg:classifiers":[
        {
            "category":"Retail",
            "subcategory":"Auto Repair",
            "type":"Services"
        }
    ],
    "sg:phone":"+61 2 4962 5430",
    "sg:postcode":"2302",
    "sg:province":"NSW",
    "sg:tags":[
        "electrical"
    ],
    "wof:name":"Absolute Auto Excellence",
    "wof:placetype":"venue"
},
  "geometry": {"coordinates":[151.75869800000001,-32.927399],"type":"Point"}
}