{
  "type": "Feature",
  "properties": {
    "addr:full":"10 Mingara Ave Stonyfell SA 5066",
    "addr:housenumber":"10",
    "addr:postcode":"5066",
    "addr:street":"Mingara Ave",
    "iso:country":"AU",
    "sg:address":"10 Mingara Ave",
    "sg:city":"Stonyfell",
    "sg:classifiers":[
        {
            "category":"Professional",
            "subcategory":"Computer Services",
            "type":"Services"
        }
    ],
    "sg:phone":"+61 8 8431 1408",
    "sg:postcode":"5066",
    "sg:province":"SA",
    "sg:tags":[
        "consultant",
        "system"
    ],
    "wof:name":"Stratavis Corporation Pty Ltd",
    "wof:placetype":"venue"
},
  "geometry": {"coordinates":[138.674026489,-34.9329605103],"type":"Point"}
}