{
  "type": "Feature",
  "properties": {
    "addr:full":"25 David St Horsham VIC 3400",
    "addr:housenumber":"25",
    "addr:postcode":"3400",
    "addr:street":"David St",
    "iso:country":"AU",
    "sg:address":"25 David St",
    "sg:city":"Horsham",
    "sg:classifiers":[
        {
            "category":"Personal",
            "type":"Services"
        }
    ],
    "sg:phone":"+61 3 5381 1062",
    "sg:postcode":"3400",
    "sg:province":"VIC",
    "sg:tags":[
        "counselling",
        "alcohol",
        "drug"
    ],
    "wof:name":"Palm Lodge Centre Inc. Counselling Outreach & Support Services",
    "wof:placetype":"venue"
},
  "geometry": {"coordinates":[142.19830322300001,-36.7083244324],"type":"Point"}
}