{
  "type": "Feature",
  "properties": {
    "addr:full":"388a South St Toowoomba QLD 4350",
    "addr:housenumber":"388a",
    "addr:postcode":"4350",
    "addr:street":"South St",
    "iso:country":"AU",
    "sg:address":"388a South St",
    "sg:city":"Toowoomba",
    "sg:classifiers":[
        {
            "category":"Farming",
            "subcategory":"Poultry Farm",
            "type":"Manufacturing & Wholesale Goods"
        }
    ],
    "sg:phone":"+61 7 4635 9211",
    "sg:postcode":"4350",
    "sg:province":"QLD",
    "sg:tags":[
        "breeder",
        "bird"
    ],
    "wof:name":"Aquabird Pet Centre",
    "wof:placetype":"venue"
},
  "geometry": {"coordinates":[151.91128499999999,-27.57254],"type":"Point"}
}