{
  "type": "Feature",
  "properties": {
    "addr:full":"Shop 1, 65 Wynyard St Tumut NSW 2720",
    "addr:housenumber":"shop;65",
    "addr:postcode":"2720",
    "addr:street":"Wynyard St",
    "iso:country":"AU",
    "sg:address":"Shop 1, 65 Wynyard St",
    "sg:city":"Tumut",
    "sg:classifiers":[
        {
            "category":"Travel",
            "subcategory":"Travel Agent",
            "type":"Entertainment"
        }
    ],
    "sg:phone":"+61 2 6947 1111",
    "sg:postcode":"2720",
    "sg:province":"NSW",
    "sg:tags":[
        "consultant"
    ],
    "wof:name":"Travelscene Tumut",
    "wof:placetype":"venue"
},
  "geometry": {"coordinates":[148.224594,-35.300671],"type":"Point"}
}