{
  "type": "Feature",
  "properties": {
    "iso:country":"AU",
    "sg:address":"340 Gore St",
    "sg:city":"Fitzroy",
    "sg:classifiers":[
        {
            "category":"Social Services",
            "subcategory":"Retirement Home",
            "type":"Services"
        }
    ],
    "sg:phone":"+61 3 9416 2994",
    "sg:postcode":"3065",
    "sg:province":"VIC",
    "sg:tags":[
        "environmental",
        "consultant",
        "pollution"
    ],
    "wof:name":"Environment Training Company Ltd",
    "wof:placetype":"venue"
},
  "geometry": {"coordinates":[144.98330688499999,-37.7984733582],"type":"Point"}
}