{
  "type": "Feature",
  "properties": {
    "iso:country":"AU",
    "sg:address":"Shop 3",
    "sg:city":"Nepean Square Penrith",
    "sg:classifiers":[
        {
            "category":"Farming",
            "subcategory":"Farm & Veterinary Services",
            "type":"Manufacturing & Wholesale Goods"
        }
    ],
    "sg:phone":"+61 2 4721 2802",
    "sg:postcode":"2750",
    "sg:province":"NSW",
    "sg:tags":[
        "poultry",
        "processing",
        "supply"
    ],
    "wof:name":"Penrith Poultry",
    "wof:placetype":"venue"
},
  "geometry": {"coordinates":[150.66632080100001,-33.7532310486],"type":"Point"}
}