{
  "type": "Feature",
  "properties": {
    "iso:country":"AU",
    "sg:address":"Unit 3 153 High Rd",
    "sg:city":"Willetton",
    "sg:classifiers":[
        {
            "category":"Building & Trades",
            "subcategory":"Construction",
            "type":"Services"
        }
    ],
    "sg:phone":"+61 8 9457 3977",
    "sg:postcode":"6155",
    "sg:province":"WA",
    "sg:tags":[
        "road",
        "contractor"
    ],
    "wof:name":"Capricorn Roads",
    "wof:placetype":"venue"
},
  "geometry": {"coordinates":[115.88215599999999,-32.038845],"type":"Point"}
}