{
  "type": "Feature",
  "properties": {
    "iso:country":"AU",
    "sg:address":"2/ 10 Salisbury Rd",
    "sg:city":"Castle Hill",
    "sg:classifiers":[
        {
            "category":"Home & Garden",
            "subcategory":"Hardware",
            "type":"Retail Goods"
        }
    ],
    "sg:phone":"+61 2 9899 8900",
    "sg:postcode":"2154",
    "sg:province":"NSW",
    "sg:tags":[
        "tarpaulin"
    ],
    "wof:name":"Castle Hill Party Hire Marquee & Tarp",
    "wof:placetype":"venue"
},
  "geometry": {"coordinates":[150.97886657699999,-33.728225708],"type":"Point"}
}