{
  "type": "Feature",
  "properties": {
    "addr:full":"165 Smart St Fairfield NSW 2165",
    "addr:housenumber":"165",
    "addr:postcode":"2165",
    "addr:street":"Smart St",
    "iso:country":"AU",
    "sg:address":"165 Smart St",
    "sg:city":"Fairfield",
    "sg:classifiers":[
        {
            "category":"Organizations",
            "subcategory":"Community Association",
            "type":"Services"
        }
    ],
    "sg:phone":"+61 2 9725 7077",
    "sg:postcode":"2165",
    "sg:province":"NSW",
    "sg:tags":[
        "organisation",
        "family",
        "welfare"
    ],
    "wof:name":"Centacare Disability Program Direct Employment",
    "wof:placetype":"venue"
},
  "geometry": {"coordinates":[150.94647216800001,-33.8642044067],"type":"Point"}
}