{
  "type": "Feature",
  "properties": {
    "addr:full":"384a Waverley Rd Malvern East VIC 3145",
    "addr:housenumber":"384a",
    "addr:postcode":"3145",
    "addr:street":"Waverley Rd",
    "iso:country":"AU",
    "sg:address":"384a Waverley Rd",
    "sg:city":"Malvern East",
    "sg:classifiers":[
        {
            "category":"Education",
            "subcategory":"Special Training",
            "type":"Public Place"
        }
    ],
    "sg:phone":"+61 402 093 600",
    "sg:postcode":"3145",
    "sg:province":"VIC",
    "sg:tags":[
        "drama",
        "speech",
        "speaking",
        "tuition"
    ],
    "wof:name":"Skyring Vicki (ATCL.LTCL London, BA/Ed",
    "wof:placetype":"venue"
},
  "geometry": {"coordinates":[145.06124877900001,-37.8776702881],"type":"Point"}
}