{
  "type": "Feature",
  "properties": {
    "addr:full":"Shop 8, Manuka Village Manuka ACT 2603",
    "addr:housenumber":"shop 8",
    "addr:postcode":"2603",
    "addr:street":"Village",
    "iso:country":"AU",
    "sg:address":"Shop 8, Manuka Village",
    "sg:city":"Manuka",
    "sg:classifiers":[
        {
            "category":"Shopping",
            "subcategory":"Bridal",
            "type":"Retail Goods"
        }
    ],
    "sg:phone":"+61 2 6239 4930",
    "sg:postcode":"2603",
    "sg:province":"ACT",
    "sg:tags":[
        "hire",
        "wear"
    ],
    "wof:name":"Brides Of Manuka",
    "wof:placetype":"venue"
},
  "geometry": {"coordinates":[149.13372802699999,-35.3202018738],"type":"Point"}
}