{
  "type": "Feature",
  "properties": {
    "addr:full":"PO Box 1142 Doncaster East VIC 3109",
    "addr:postcode":"3109",
    "iso:country":"AU",
    "sg:address":"PO Box 1142",
    "sg:city":"Doncaster East",
    "sg:classifiers":[
        {
            "category":"Professional",
            "type":"Services"
        }
    ],
    "sg:phone":"+61 3 9848 7951",
    "sg:postcode":"3109",
    "sg:province":"VIC",
    "sg:tags":[
        "auctioneer"
    ],
    "wof:name":"AAA Australian Antiques Arms Auctions",
    "wof:placetype":"venue"
},
  "geometry": {"coordinates":[145.16328430199999,-37.7757987976],"type":"Point"}
}