{
  "type": "Feature",
  "properties": {
    "addr:full":"Woodcroft Town Centre Suite 6, 185-191 Bains Rd Woodcroft SA 5162",
    "addr:housenumber":"185-191",
    "addr:postcode":"5162",
    "addr:street":"Bains Rd",
    "iso:country":"AU",
    "sg:address":"Woodcroft Town Centre Suite 6, 185-191 Bains Rd",
    "sg:city":"Woodcroft",
    "sg:classifiers":[
        {
            "category":"Health Services",
            "subcategory":"Health Practitioner",
            "type":"Services"
        }
    ],
    "sg:phone":"+61 8 8325 1500",
    "sg:postcode":"5162",
    "sg:province":"SA",
    "sg:tags":[
        "physiotherapist"
    ],
    "wof:name":"Lagos Nick",
    "wof:placetype":"venue"
},
  "geometry": {"coordinates":[138.55165100100001,-35.1141700745],"type":"Point"}
}