{
  "type": "Feature",
  "properties": {
    "iso:country":"AU",
    "sg:address":"193- 199 McDougall St",
    "sg:city":"Toowoomba",
    "sg:classifiers":[
        {
            "category":"Manufacturing",
            "subcategory":"Food",
            "type":"Manufacturing & Wholesale Goods"
        }
    ],
    "sg:phone":"+61 7 4699 9444",
    "sg:postcode":"4350",
    "sg:province":"QLD",
    "sg:tags":[
        "product",
        "nut",
        "edible"
    ],
    "wof:name":"Stahmanns",
    "wof:placetype":"venue"
},
  "geometry": {"coordinates":[151.907455,-27.560163],"type":"Point"}
}