{
  "type": "Feature",
  "properties": {
    "iso:country":"AU",
    "sg:address":"27 Parraweena Rd",
    "sg:city":"Taren Point",
    "sg:classifiers":[
        {
            "category":"Shopping Center",
            "type":"Public Place"
        }
    ],
    "sg:phone":"+61 2 9525 4777",
    "sg:postcode":"2229",
    "sg:province":"NSW",
    "sg:tags":[
        "riveting",
        "equipment",
        "rivet"
    ],
    "wof:name":"Cold Forged Products",
    "wof:placetype":"venue"
},
  "geometry": {"coordinates":[151.12620544399999,-34.0259437561],"type":"Point"}
}