{
  "type": "Feature",
  "properties": {
    "iso:country":"AU",
    "sg:address":"17 Winthrop Drv",
    "sg:city":"Winthrop",
    "sg:classifiers":[
        {
            "category":"Health Services",
            "subcategory":"Dentist",
            "type":"Services"
        }
    ],
    "sg:phone":"+61 8 9310 8828",
    "sg:postcode":"6150",
    "sg:province":"WA",
    "wof:name":"Dental Orthodontic Centre",
    "wof:placetype":"venue"
},
  "geometry": {"coordinates":[115.825462,-32.048447],"type":"Point"}
}