{
  "type": "Feature",
  "properties": {
    "addr:full":"11 Whitehaven Ave Quakers Hill NSW 2763",
    "addr:housenumber":"11",
    "addr:postcode":"2763",
    "addr:street":"Whitehaven Ave",
    "iso:country":"AU",
    "sg:address":"11 Whitehaven Ave",
    "sg:city":"Quakers Hill",
    "sg:classifiers":[
        {
            "category":"Building & Trades",
            "subcategory":"Construction",
            "type":"Services"
        }
    ],
    "sg:phone":"+61 2 9837 1045",
    "sg:postcode":"2763",
    "sg:province":"NSW",
    "sg:tags":[
        "contractor"
    ],
    "wof:name":"Haddock J.C. & Associates",
    "wof:placetype":"venue"
},
  "geometry": {"coordinates":[150.88772582999999,-33.7183914185],"type":"Point"}
}