{
  "type": "Feature",
  "properties": {
    "addr:full":"Sycamore St Melbourne VIC 3000",
    "addr:postcode":"3000",
    "addr:street":"Sycamore St",
    "iso:country":"AU",
    "sg:address":"Sycamore St",
    "sg:city":"Melbourne",
    "sg:classifiers":[
        {
            "category":"Building & Trades",
            "subcategory":"Equipment Rental",
            "type":"Services"
        }
    ],
    "sg:phone":"+61 1300 738 666",
    "sg:postcode":"3000",
    "sg:province":"VIC",
    "sg:tags":[
        "fitness"
    ],
    "wof:name":"BeFit Sales & Hire",
    "wof:placetype":"venue"
},
  "geometry": {"coordinates":[144.97027587900001,-37.8145599365],"type":"Point"}
}