{
  "type": "Feature",
  "properties": {
    "iso:country":"AU",
    "sg:address":"72 Black St",
    "sg:city":"Brighton",
    "sg:classifiers":[
        {
            "category":"Professional",
            "subcategory":"Engineering",
            "type":"Services"
        }
    ],
    "sg:phone":"+61 3 9592 8734",
    "sg:postcode":"3186",
    "sg:province":"VIC",
    "sg:tags":[
        "consulting",
        "engineer"
    ],
    "wof:name":"Pratt R D & Associates Pty Ltd",
    "wof:placetype":"venue"
},
  "geometry": {"coordinates":[145.000366211,-37.9170188904],"type":"Point"}
}