{
  "type": "Feature",
  "properties": {
    "iso:country":"AU",
    "sg:address":"Pioneer Drv",
    "sg:city":"Mole Creek",
    "sg:classifiers":[
        {
            "category":"Professional",
            "subcategory":"Employment Agencies",
            "type":"Services"
        }
    ],
    "sg:phone":"+61 3 6363 2030",
    "sg:postcode":"7304",
    "sg:province":"TAS",
    "sg:tags":[
        "provider",
        "internet"
    ],
    "wof:name":"Online Access Centres",
    "wof:placetype":"venue"
},
  "geometry": {"coordinates":[146.40785199999999,-41.556877],"type":"Point"}
}