{
  "type": "Feature",
  "properties": {
    "iso:country":"AU",
    "sg:address":"Level 1\\\\ 498 Princes Hwy",
    "sg:city":"Rockdale",
    "sg:classifiers":[
        {
            "category":"Professional",
            "subcategory":"Accounting & Tax Preparation",
            "type":"Services"
        }
    ],
    "sg:phone":"+61 403 063 673",
    "sg:postcode":"2216",
    "sg:province":"NSW",
    "sg:tags":[
        "consultant",
        "taxation"
    ],
    "wof:name":"Perdikaris J",
    "wof:placetype":"venue"
},
  "geometry": {"coordinates":[151.138016,-33.952259],"type":"Point"}
}