{
  "type": "Feature",
  "properties": {
    "addr:full":"75A Belgrave - Hallam Rd Hallam VIC 3803",
    "addr:housenumber":"75a",
    "addr:postcode":"3803",
    "addr:street":"Belgrave Hallam Rd",
    "iso:country":"AU",
    "sg:address":"75A Belgrave - Hallam Rd",
    "sg:city":"Hallam",
    "sg:classifiers":[
        {
            "category":"Personal",
            "subcategory":"Beauty Salon",
            "type":"Services"
        }
    ],
    "sg:phone":"+61 3 9796 5100",
    "sg:postcode":"3803",
    "sg:province":"VIC",
    "sg:tags":[
        "supply",
        "artist",
        "make-up"
    ],
    "wof:name":"Exclusive Hair Make Up Studio",
    "wof:placetype":"venue"
},
  "geometry": {"coordinates":[145.276046753,-37.9930419922],"type":"Point"}
}