{
  "type": "Feature",
  "properties": {
    "iso:country":"AU",
    "sg:address":"37 Woodland Ave",
    "sg:city":"Croydon",
    "sg:classifiers":[
        {
            "category":"Insurance",
            "subcategory":"Hazard Insurance",
            "type":"Services"
        }
    ],
    "sg:phone":"+61 3 9722 9461",
    "sg:postcode":"3136",
    "sg:province":"VIC",
    "sg:tags":[
        "loss",
        "adjuster",
        "assessor"
    ],
    "wof:name":"Safe-T-First Risk Solution Pty Ltd",
    "wof:placetype":"venue"
},
  "geometry": {"coordinates":[145.26713562,-37.7943725586],"type":"Point"}
}