{
  "type": "Feature",
  "properties": {
    "addr:full":"76 South Western Hwy Yarloop WA 6218",
    "addr:housenumber":"76",
    "addr:postcode":"6218",
    "addr:street":"South Western Hwy",
    "iso:country":"AU",
    "sg:address":"76 South Western Hwy",
    "sg:city":"Yarloop",
    "sg:classifiers":[
        {
            "category":"Autos & Motor Vehicles",
            "subcategory":"Fuel & Gas Station",
            "type":"Retail Goods"
        }
    ],
    "sg:phone":"+61 8 9733 5078",
    "sg:postcode":"6218",
    "sg:province":"WA",
    "wof:name":"Ampol",
    "wof:placetype":"venue"
},
  "geometry": {"coordinates":[115.91113300000001,-32.950478],"type":"Point"}
}