{
  "type": "Feature",
  "properties": {
    "iso:country":"AU",
    "sg:address":"6 Grenfell St",
    "sg:city":"Kent Town",
    "sg:classifiers":[
        {
            "category":"Professional",
            "subcategory":"Employment Agencies",
            "type":"Services"
        }
    ],
    "sg:phone":"+61 8 8363 0906",
    "sg:postcode":"5067",
    "sg:province":"SA",
    "wof:name":"MRC Management Resource Consulting",
    "wof:placetype":"venue"
},
  "geometry": {"coordinates":[138.620895386,-34.9206466675],"type":"Point"}
}