{
  "type": "Feature",
  "properties": {
    "iso:country":"AU",
    "sg:address":"U2/ 17 Sorrett Ave",
    "sg:city":"Malvern",
    "sg:classifiers":[
        {
            "category":"Health Services",
            "subcategory":"Health Practitioner",
            "type":"Services"
        }
    ],
    "sg:phone":"+61 3 9822 9884",
    "sg:postcode":"3144",
    "sg:province":"VIC",
    "sg:tags":[
        "pathologist",
        "speech"
    ],
    "wof:name":"Jansen Penny",
    "wof:placetype":"venue"
},
  "geometry": {"coordinates":[145.03179931599999,-37.8546905518],"type":"Point"}
}