{
  "type": "Feature",
  "properties": {
    "addr:full":"Un 5b, 2021 Wynnum Rd Wynnum QLD 4178",
    "addr:housenumber":"2021",
    "addr:postcode":"4178",
    "addr:street":"Wynnum Rd",
    "iso:country":"AU",
    "sg:address":"Un 5b, 2021 Wynnum Rd",
    "sg:city":"Wynnum",
    "sg:classifiers":[
        {
            "category":"Personal",
            "subcategory":"Massage",
            "type":"Services"
        }
    ],
    "sg:phone":"+61 7 3348 5652",
    "sg:postcode":"4178",
    "sg:province":"QLD",
    "sg:tags":[
        "therapy"
    ],
    "wof:name":"Essence Complete Health",
    "wof:placetype":"venue"
},
  "geometry": {"coordinates":[153.15374755900001,-27.4566802979],"type":"Point"}
}