{
  "type": "Feature",
  "properties": {
    "iso:country":"AU",
    "sg:address":"15 Arno Bay Rd",
    "sg:city":"Cleve",
    "sg:classifiers":[
        {
            "category":"Building & Trades",
            "subcategory":"Equipment Rental",
            "type":"Services"
        }
    ],
    "sg:phone":"+61 429 423 101",
    "sg:postcode":"5640",
    "sg:province":"SA",
    "sg:tags":[
        "party",
        "hire"
    ],
    "wof:name":"Dunrite Sales & Hire",
    "wof:placetype":"venue"
},
  "geometry": {"coordinates":[136.494064331,-33.7059020996],"type":"Point"}
}