{
  "type": "Feature",
  "properties": {
    "addr:full":"2/ 38 Fitzroy St St Kilda VIC 3182",
    "addr:housenumber":"/ 38",
    "addr:postcode":"3182",
    "addr:street":"Fitzroy St",
    "iso:country":"AU",
    "sg:address":"2/ 38 Fitzroy St St",
    "sg:city":"Kilda",
    "sg:classifiers":[
        {
            "category":"Health Services",
            "subcategory":"Health Practitioner",
            "type":"Services"
        }
    ],
    "sg:phone":"+61 1300 797 793",
    "sg:postcode":"3182",
    "sg:province":"VIC",
    "sg:tags":[
        "physiotherapist"
    ],
    "wof:name":"TJW Physio",
    "wof:placetype":"venue"
},
  "geometry": {"coordinates":[144.97601318400001,-37.8603973389],"type":"Point"}
}