{
  "type": "Feature",
  "properties": {
    "iso:country":"AU",
    "sg:address":"139 Collins Ave",
    "sg:city":"Edge Hill",
    "sg:classifiers":[
        {
            "category":"Autos & Motor Vehicles",
            "subcategory":"Recreational Vehicle Sales",
            "type":"Retail Goods"
        }
    ],
    "sg:phone":"+61 7 4032 0222",
    "sg:postcode":"4870",
    "sg:province":"QLD",
    "sg:tags":[
        "confectionery"
    ],
    "wof:name":"Biscotti",
    "wof:placetype":"venue"
},
  "geometry": {"coordinates":[145.742462158,-16.9010810852],"type":"Point"}
}