{
  "type": "Feature",
  "properties": {
    "iso:country":"AU",
    "sg:address":"172 Avoca Drv",
    "sg:city":"Avoca Beach",
    "sg:classifiers":[
        {
            "category":"Restaurant",
            "type":"Food & Drink"
        }
    ],
    "sg:phone":"+61 2 4382 3506",
    "sg:postcode":"2251",
    "sg:province":"NSW",
    "wof:name":"Avoca Beach Pizzeria & Restaurant",
    "wof:placetype":"venue"
},
  "geometry": {"coordinates":[151.43307495100001,-33.4653053284],"type":"Point"}
}