{
  "type": "Feature",
  "properties": {
    "addr:full":"62 Beafield Rd Para Hills West SA 5096",
    "addr:housenumber":"62",
    "addr:postcode":"5096",
    "addr:street":"Beafield Rd Para Hills West",
    "iso:country":"AU",
    "sg:address":"62 Beafield Rd",
    "sg:city":"Para Hills West",
    "sg:classifiers":[
        {
            "category":"Retail",
            "subcategory":"Auto Repair",
            "type":"Services"
        }
    ],
    "sg:phone":"+61 8 8182 4247",
    "sg:postcode":"5096",
    "sg:province":"SA",
    "sg:tags":[
        "repairer",
        "motor",
        "engineer"
    ],
    "wof:name":"All Suburbs Mechanical",
    "wof:placetype":"venue"
},
  "geometry": {"coordinates":[138.64796447800001,-34.7995033264],"type":"Point"}
}