{
  "type": "Feature",
  "properties": {
    "addr:full":"86- 88 Conadilly St Gunnedah NSW 2380",
    "addr:housenumber":"88",
    "addr:postcode":"2380",
    "addr:street":"Conadilly St",
    "iso:country":"AU",
    "sg:address":"86- 88 Conadilly St",
    "sg:city":"Gunnedah",
    "sg:classifiers":[
        {
            "category":"Banks & Credit Unions",
            "subcategory":"Investment Brokerage",
            "type":"Services"
        }
    ],
    "sg:phone":"+61 2 6742 4615",
    "sg:postcode":"2380",
    "sg:province":"NSW",
    "sg:tags":[
        "debt",
        "collection"
    ],
    "wof:name":"Lloyd Collection Services Pty Ltd",
    "wof:placetype":"venue"
},
  "geometry": {"coordinates":[150.24873352,-30.9753608704],"type":"Point"}
}