{
  "type": "Feature",
  "properties": {
    "addr:full":"1 Bay Rd Mt Martha VIC 3934",
    "addr:housenumber":"1",
    "addr:postcode":"3934",
    "addr:street":"Bay Rd",
    "iso:country":"AU",
    "sg:address":"1 Bay Rd",
    "sg:city":"Mt Martha",
    "sg:classifiers":[
        {
            "category":"Communications",
            "subcategory":"Film & Video Production",
            "type":"Services"
        }
    ],
    "sg:phone":"+61 3 5974 3577",
    "sg:postcode":"3934",
    "sg:province":"VIC",
    "sg:tags":[
        "dvd",
        "library"
    ],
    "wof:name":"Network Video Mt Martha",
    "wof:placetype":"venue"
},
  "geometry": {"coordinates":[145.012329102,-38.2680168152],"type":"Point"}
}