{
  "type": "Feature",
  "properties": {
    "iso:country":"AU",
    "sg:address":"Shp 12/ 414 Milne Rd",
    "sg:city":"Redwood Park",
    "sg:classifiers":[
        {
            "category":"Fast Food",
            "type":"Food & Drink"
        }
    ],
    "sg:phone":"+61 8 8395 8725",
    "sg:postcode":"5097",
    "sg:province":"SA",
    "sg:tags":[
        "away",
        "take"
    ],
    "wof:name":"Pizza Bite",
    "wof:placetype":"venue"
},
  "geometry": {"coordinates":[138.705612183,-34.8167686462],"type":"Point"}
}