{
  "type": "Feature",
  "properties": {
    "iso:country":"AU",
    "sg:address":"Cnr Chatswood & Magellon Rds",
    "sg:city":"Springwood",
    "sg:classifiers":[
        {
            "category":"Real Estate",
            "subcategory":"Real Estate Agent",
            "type":"Services"
        }
    ],
    "sg:phone":"+61 7 3208 4455",
    "sg:postcode":"4127",
    "sg:province":"QLD",
    "wof:name":"Ray White Springwood at Chatswood Hills",
    "wof:placetype":"venue"
},
  "geometry": {"coordinates":[153.13471984899999,-27.6332588196],"type":"Point"}
}