{
  "type": "Feature",
  "properties": {
    "iso:country":"AU",
    "sg:address":"27 Mcdonald St",
    "sg:city":"Numurkah",
    "sg:classifiers":[
        {
            "category":"Retail",
            "subcategory":"Storage",
            "type":"Services"
        }
    ],
    "sg:phone":"+61 3 5862 1077",
    "sg:postcode":"3636",
    "sg:province":"VIC",
    "wof:name":"Central Numurkah Self Storage",
    "wof:placetype":"venue"
},
  "geometry": {"coordinates":[145.439376831,-36.091003418],"type":"Point"}
}