{
  "type": "Feature",
  "properties": {
    "addr:full":"130 Russell St Melbourne VIC 3000",
    "addr:housenumber":"130",
    "addr:postcode":"3000",
    "addr:street":"Russell St",
    "iso:country":"AU",
    "sg:address":"130 Russell St",
    "sg:city":"Melbourne",
    "sg:classifiers":[
        {
            "category":"Shopping",
            "subcategory":"Jewelry",
            "type":"Retail Goods"
        }
    ],
    "sg:phone":"+61 3 9650 3561",
    "sg:postcode":"3000",
    "sg:province":"VIC",
    "sg:tags":[
        "jeweller"
    ],
    "wof:name":"Golden Casket Jewellery & Gifts",
    "wof:placetype":"venue"
},
  "geometry": {"coordinates":[144.96849060100001,-37.8132553101],"type":"Point"}
}