{
  "type": "Feature",
  "properties": {
    "addr:full":"31 Foxlease Ave Traralgon VIC 3844",
    "addr:housenumber":"31",
    "addr:postcode":"3844",
    "addr:street":"Foxlease Ave",
    "iso:country":"AU",
    "sg:address":"31 Foxlease Ave",
    "sg:city":"Traralgon",
    "sg:classifiers":[
        {
            "category":"Professional",
            "subcategory":"Art Services",
            "type":"Services"
        }
    ],
    "sg:phone":"+61 3 5174 2158",
    "sg:postcode":"3844",
    "sg:province":"VIC",
    "sg:tags":[
        "decorator",
        "painter"
    ],
    "wof:name":"Dyes Painting Service",
    "wof:placetype":"venue"
},
  "geometry": {"coordinates":[146.531539917,-38.1876678467],"type":"Point"}
}