{
  "type": "Feature",
  "properties": {
    "iso:country":"AU",
    "sg:address":"69 Strcikland St",
    "sg:city":"Denmark",
    "sg:classifiers":[
        {
            "category":"Arts & Performance",
            "subcategory":"Art Gallery",
            "type":"Entertainment"
        }
    ],
    "sg:phone":"+61 8 9848 1281",
    "sg:postcode":"6333",
    "sg:province":"WA",
    "wof:name":"Michael Cartwright",
    "wof:placetype":"venue"
},
  "geometry": {"coordinates":[117.322799683,-34.9531555176],"type":"Point"}
}