{
  "type": "Feature",
  "properties": {
    "addr:full":"Shop 15/ 655 Sydney Rd Brunswick VIC 3056",
    "addr:housenumber":"shop 15 / 655",
    "addr:postcode":"3056",
    "addr:street":"Sydney Rd",
    "iso:country":"AU",
    "sg:address":"Shop 15/ 655 Sydney Rd",
    "sg:city":"Brunswick",
    "sg:classifiers":[
        {
            "category":"Deli",
            "type":"Food & Drink"
        }
    ],
    "sg:phone":"+61 3 9386 8074",
    "sg:postcode":"3056",
    "sg:province":"VIC",
    "sg:tags":[
        "delicatessen"
    ],
    "wof:name":"Brunswick Delicatessen & Wholesaler",
    "wof:placetype":"venue"
},
  "geometry": {"coordinates":[144.96307373100001,-37.7622261047],"type":"Point"}
}