{
  "type": "Feature",
  "properties": {
    "addr:full":"15 Swan St Marks Point NSW 2280",
    "addr:housenumber":"15",
    "addr:postcode":"2280",
    "addr:street":"Swan St",
    "iso:country":"AU",
    "sg:address":"15 Swan St",
    "sg:city":"Marks Point",
    "sg:classifiers":[
        {
            "category":"Building & Trades",
            "subcategory":"Construction",
            "type":"Services"
        }
    ],
    "sg:phone":"+61 419 618 441",
    "sg:postcode":"2280",
    "sg:province":"NSW",
    "sg:tags":[
        "renovation",
        "alterations",
        "extension",
        "contractor"
    ],
    "wof:name":"J. Oakey Building Pty Ltd",
    "wof:placetype":"venue"
},
  "geometry": {"coordinates":[151.646972656,-33.0569381714],"type":"Point"}
}