{
  "type": "Feature",
  "properties": {
    "iso:country":"AU",
    "sg:address":"Grand Central Shop 21 Margaret St",
    "sg:city":"Toowoomba",
    "sg:classifiers":[
        {
            "category":"Shopping",
            "subcategory":"Jewelry",
            "type":"Retail Goods"
        }
    ],
    "sg:phone":"+61 7 4632 2677",
    "sg:postcode":"4350",
    "sg:province":"QLD",
    "sg:tags":[
        "jeweller"
    ],
    "wof:name":"Central Jewellers",
    "wof:placetype":"venue"
},
  "geometry": {"coordinates":[151.941757,-27.560299],"type":"Point"}
}