{
  "type": "Feature",
  "properties": {
    "iso:country":"AU",
    "sg:address":"34 King Edward St",
    "sg:city":"Penguin",
    "sg:classifiers":[
        {
            "category":"Education",
            "subcategory":"Dance Studio",
            "type":"Public Place"
        }
    ],
    "sg:phone":"+61 3 6437 1234",
    "sg:postcode":"7316",
    "sg:province":"TAS",
    "sg:tags":[
        "venue",
        "tuition"
    ],
    "wof:name":"Myra Di Maria Dancers",
    "wof:placetype":"venue"
},
  "geometry": {"coordinates":[146.07420349099999,-41.1161994934],"type":"Point"}
}