{
  "type": "Feature",
  "properties": {
    "addr:full":"20 Yareen Rd Cooma NSW 2630",
    "addr:housenumber":"20",
    "addr:postcode":"2630",
    "addr:street":"Yareen Rd",
    "iso:country":"AU",
    "sg:address":"20 Yareen Rd",
    "sg:city":"Cooma",
    "sg:classifiers":[
        {
            "category":"Professional",
            "type":"Services"
        }
    ],
    "sg:phone":"+61 1300 366 684",
    "sg:postcode":"2630",
    "sg:province":"NSW",
    "sg:tags":[
        "transport"
    ],
    "wof:name":"Toll IPEC",
    "wof:placetype":"venue"
},
  "geometry": {"coordinates":[149.13601684599999,-36.2268638611],"type":"Point"}
}