{
  "type": "Feature",
  "properties": {
    "addr:full":"37 Blackbutt St Lyneham ACT 2602",
    "addr:housenumber":"37",
    "addr:postcode":"2602",
    "addr:street":"Blackbutt St",
    "iso:country":"AU",
    "sg:address":"37 Blackbutt St",
    "sg:city":"Lyneham",
    "sg:classifiers":[
        {
            "category":"Home & Garden",
            "subcategory":"Building Materials",
            "type":"Retail Goods"
        }
    ],
    "sg:phone":"+61 432 697 511",
    "sg:postcode":"2602",
    "sg:province":"ACT",
    "sg:tags":[
        "lawn",
        "cutting",
        "maintenance"
    ],
    "wof:name":"Avant Garden Horticultural Services",
    "wof:placetype":"venue"
},
  "geometry": {"coordinates":[149.119750977,-35.2462501526],"type":"Point"}
}