{
  "type": "Feature",
  "properties": {
    "addr:full":"1/17- 19 Florence St Mall Hornsby NSW 1630",
    "addr:housenumber":"/;19",
    "addr:postcode":"1630",
    "addr:street":"17;Florence St Mall",
    "iso:country":"AU",
    "sg:address":"1/17- 19 Florence St Mall",
    "sg:city":"Hornsby",
    "sg:classifiers":[
        {
            "category":"Shopping",
            "subcategory":"Clothing, Apparel, & Fashions",
            "type":"Retail Goods"
        }
    ],
    "sg:phone":"+61 2 9477 3076",
    "sg:postcode":"1630",
    "sg:province":"NSW",
    "sg:tags":[
        "menswear"
    ],
    "wof:name":"Anthony Weiss Menswear & Formal Hire",
    "wof:placetype":"venue"
},
  "geometry": {"coordinates":[151.099685669,-33.7037124634],"type":"Point"}
}