{
  "type": "Feature",
  "properties": {
    "iso:country":"AU",
    "sg:address":"Cnr Crescent Ave & Railway Pde",
    "sg:city":"Taree",
    "sg:classifiers":[
        {
            "category":"Autos & Motor Vehicles",
            "subcategory":"Automobile Sales",
            "type":"Retail Goods"
        }
    ],
    "sg:phone":"+61 2 6552 3999",
    "sg:postcode":"2430",
    "sg:province":"NSW",
    "sg:tags":[
        "car",
        "new"
    ],
    "wof:name":"Taree Subaru",
    "wof:placetype":"venue"
},
  "geometry": {"coordinates":[152.470886,-31.90737],"type":"Point"}
}