{
  "type": "Feature",
  "properties": {
    "iso:country":"AU",
    "sg:address":"Top Gawler Rd",
    "sg:city":"Ulverstone",
    "sg:classifiers":[
        {
            "category":"Building & Trades",
            "subcategory":"Construction",
            "type":"Services"
        }
    ],
    "sg:phone":"+61 419 707 102",
    "sg:postcode":"7315",
    "sg:province":"TAS",
    "sg:tags":[
        "contractor"
    ],
    "wof:name":"PA & MA Beswick",
    "wof:placetype":"venue"
},
  "geometry": {"coordinates":[146.160522461,-41.1834945679],"type":"Point"}
}