{
  "type": "Feature",
  "properties": {
    "addr:full":"Units 6 & 7 18 Rudloc St Morley WA 6062",
    "addr:housenumber":"units 6 &;18",
    "addr:postcode":"6062",
    "addr:street":"7;St",
    "iso:country":"AU",
    "sg:address":"Units 6 & 7 18 Rudloc St",
    "sg:city":"Morley",
    "sg:classifiers":[
        {
            "category":"Retail",
            "subcategory":"Auto Repair",
            "type":"Services"
        }
    ],
    "sg:phone":"+61 419 832 070",
    "sg:postcode":"6062",
    "sg:province":"WA",
    "sg:tags":[
        "beater",
        "painter",
        "panel"
    ],
    "wof:name":"CA Spray Painter",
    "wof:placetype":"venue"
},
  "geometry": {"coordinates":[115.896751404,-31.9019737244],"type":"Point"}
}