{
  "type": "Feature",
  "properties": {
    "addr:full":"275 Macquarie St Liverpool NSW 2170",
    "addr:housenumber":"275",
    "addr:postcode":"2170",
    "addr:street":"Macquarie St",
    "iso:country":"AU",
    "sg:address":"275 Macquarie St",
    "sg:city":"Liverpool",
    "sg:classifiers":[
        {
            "category":"Food & Beverages",
            "subcategory":"Bakery",
            "type":"Retail Goods"
        }
    ],
    "sg:phone":"+61 2 9602 9922",
    "sg:postcode":"2170",
    "sg:province":"NSW",
    "sg:tags":[
        "baker"
    ],
    "wof:name":"Haney Bakery",
    "wof:placetype":"venue"
},
  "geometry": {"coordinates":[150.923217773,-33.9243507385],"type":"Point"}
}