{
  "type": "Feature",
  "properties": {
    "iso:country":"AU",
    "sg:address":"90 Crown St",
    "sg:city":"Wollongong",
    "sg:classifiers":[
        {
            "category":"Bars & Pubs",
            "subcategory":"Nightclub",
            "type":"Food & Drink"
        }
    ],
    "sg:phone":"+61 2 4226 4305",
    "sg:postcode":"2500",
    "sg:province":"NSW",
    "sg:tags":[
        "discotheque"
    ],
    "wof:name":"Glass House Tavern",
    "wof:placetype":"venue"
},
  "geometry": {"coordinates":[150.89793399999999,-34.425465],"type":"Point"}
}