{
  "type": "Feature",
  "properties": {
    "addr:full":"148 Smart Rd St Agnes SA 5097",
    "addr:housenumber":"148",
    "addr:postcode":"5097",
    "addr:street":"Smart Rd",
    "iso:country":"AU",
    "sg:address":"148 Smart Rd St",
    "sg:city":"Agnes",
    "sg:classifiers":[
        {
            "category":"Retail",
            "subcategory":"Repair Shop",
            "type":"Services"
        }
    ],
    "sg:phone":"+61 8 8265 3953",
    "sg:postcode":"5097",
    "sg:province":"SA",
    "sg:tags":[
        "machine",
        "repairs",
        "part",
        "dryer",
        "washing"
    ],
    "wof:name":"Abram Appliances",
    "wof:placetype":"venue"
},
  "geometry": {"coordinates":[138.71192932100001,-34.8320045471],"type":"Point"}
}