{
  "type": "Feature",
  "properties": {
    "addr:full":"965 Bourke St Waterloo NSW 2017",
    "addr:housenumber":"965",
    "addr:postcode":"2017",
    "addr:street":"Bourke St",
    "iso:country":"AU",
    "sg:address":"965 Bourke St",
    "sg:city":"Waterloo",
    "sg:classifiers":[
        {
            "category":"Education",
            "subcategory":"School",
            "type":"Public Place"
        }
    ],
    "sg:phone":"+61 2 8303 9700",
    "sg:postcode":"2017",
    "sg:province":"NSW",
    "wof:name":"Taylors College - Sydney Campus",
    "wof:placetype":"venue"
},
  "geometry": {"coordinates":[151.207717895,-33.9024543762],"type":"Point"}
}