{
  "type": "Feature",
  "properties": {
    "addr:full":"19 George St Kandos NSW 2848",
    "addr:housenumber":"19",
    "addr:postcode":"2848",
    "addr:street":"George St",
    "iso:country":"AU",
    "sg:address":"19 George St",
    "sg:city":"Kandos",
    "sg:classifiers":[
        {
            "category":"Home & Garden",
            "subcategory":"Building Materials",
            "type":"Retail Goods"
        }
    ],
    "sg:phone":"+61 2 6379 4293",
    "sg:postcode":"2848",
    "sg:province":"NSW",
    "sg:tags":[
        "pre-mixed",
        "concrete"
    ],
    "wof:name":"Kuchta J & S K Pty Ltd",
    "wof:placetype":"venue"
},
  "geometry": {"coordinates":[149.98318499999999,-32.851452],"type":"Point"}
}