{
  "type": "Feature",
  "properties": {
    "addr:full":"Unit 3, 45 Heffernan St Mitchell ACT 2911",
    "addr:housenumber":"45",
    "addr:postcode":"2911",
    "addr:street":"Heffernan St",
    "iso:country":"AU",
    "sg:address":"Unit 3, 45 Heffernan St",
    "sg:city":"Mitchell",
    "sg:classifiers":[
        {
            "category":"Retail",
            "subcategory":"Auto Repair",
            "type":"Services"
        }
    ],
    "sg:phone":"+61 2 6241 0005",
    "sg:postcode":"2911",
    "sg:province":"ACT",
    "sg:tags":[
        "repairer",
        "motor",
        "engineer"
    ],
    "wof:name":"Custom Mechanix",
    "wof:placetype":"venue"
},
  "geometry": {"coordinates":[149.14158630399999,-35.2184524536],"type":"Point"}
}