{
  "type": "Feature",
  "properties": {
    "addr:full":"74 Webster Rd Stafford QLD 4053",
    "addr:housenumber":"74",
    "addr:postcode":"4053",
    "addr:street":"Webster Rd",
    "iso:country":"AU",
    "sg:address":"74 Webster Rd",
    "sg:city":"Stafford",
    "sg:classifiers":[
        {
            "category":"Bars & Pubs",
            "subcategory":"Lounge",
            "type":"Food & Drink"
        }
    ],
    "sg:phone":"+61 7 3352 5944",
    "sg:postcode":"4053",
    "sg:province":"QLD",
    "sg:tags":[
        "water",
        "filter",
        "drinking"
    ],
    "wof:name":"Challenger Filtration",
    "wof:placetype":"venue"
},
  "geometry": {"coordinates":[153.007720947,-27.4093284607],"type":"Point"}
}