{
  "type": "Feature",
  "properties": {
    "addr:full":"77 Monaro Station Rd Royalla ACT 2620",
    "addr:housenumber":"77",
    "addr:postcode":"2620",
    "addr:street":"Monaro Station Rd",
    "iso:country":"AU",
    "sg:address":"77 Monaro Station Rd",
    "sg:city":"Royalla",
    "sg:classifiers":[
        {
            "category":"Building & Trades",
            "subcategory":"Construction",
            "type":"Services"
        }
    ],
    "sg:phone":"+61 413 994 588",
    "sg:postcode":"2620",
    "sg:province":"ACT",
    "sg:tags":[
        "home",
        "air conditioning"
    ],
    "wof:name":"Twin Air - Air Conditioning",
    "wof:placetype":"venue"
},
  "geometry": {"coordinates":[149.16104125999999,-35.473941803],"type":"Point"}
}