{
  "type": "Feature",
  "properties": {
    "iso:country":"AU",
    "sg:address":"435 Bourke St",
    "sg:city":"Darlinghurst",
    "sg:classifiers":[
        {
            "category":"Health Services",
            "subcategory":"Doctor",
            "type":"Services"
        }
    ],
    "sg:phone":"+61 2 9333 4000",
    "sg:postcode":"2010",
    "sg:province":"NSW",
    "sg:tags":[
        "medical",
        "practitioner"
    ],
    "wof:name":"Paul C W Chay",
    "wof:placetype":"venue"
},
  "geometry": {"coordinates":[151.21617126500001,-33.8825721741],"type":"Point"}
}