{
  "type": "Feature",
  "properties": {
    "iso:country":"AU",
    "sg:address":"U1/ 179 Coombabah Rd",
    "sg:city":"Runaway Bay",
    "sg:classifiers":[
        {
            "category":"Banks & Credit Unions",
            "subcategory":"Investment Brokerage",
            "type":"Services"
        }
    ],
    "sg:phone":"+61 7 5537 4299",
    "sg:postcode":"4216",
    "sg:province":"QLD",
    "sg:tags":[
        "management",
        "property"
    ],
    "wof:name":"Harbour Landing",
    "wof:placetype":"venue"
},
  "geometry": {"coordinates":[153.38534545900001,-27.9224395752],"type":"Point"}
}