{
  "type": "Feature",
  "properties": {
    "addr:full":"82 Claremont Ave Malvern VIC 3144",
    "addr:housenumber":"82",
    "addr:postcode":"3144",
    "addr:street":"Claremont Ave",
    "iso:country":"AU",
    "sg:address":"82 Claremont Ave",
    "sg:city":"Malvern",
    "sg:classifiers":[
        {
            "category":"Real Estate",
            "subcategory":"Architect",
            "type":"Services"
        }
    ],
    "sg:phone":"+61 417 010 885",
    "sg:postcode":"3144",
    "sg:province":"VIC",
    "wof:name":"Tapsall Diana",
    "wof:placetype":"venue"
},
  "geometry": {"coordinates":[145.03695678700001,-37.8668479919],"type":"Point"}
}