{
  "type": "Feature",
  "properties": {
    "addr:full":"Cyril Road Hall High Wycombe WA 6057",
    "addr:postcode":"6057",
    "addr:street":"Cyril Road",
    "iso:country":"AU",
    "sg:address":"Cyril Road Hall",
    "sg:city":"High Wycombe",
    "sg:classifiers":[
        {
            "category":"Education",
            "subcategory":"Dance Studio",
            "type":"Public Place"
        }
    ],
    "sg:phone":"+61 8 9294 2066",
    "sg:postcode":"6057",
    "sg:province":"WA",
    "sg:tags":[
        "venue",
        "tuition"
    ],
    "wof:name":"Kalamunda Performers",
    "wof:placetype":"venue"
},
  "geometry": {"coordinates":[116.009109497,-31.9384689331],"type":"Point"}
}