{
  "type": "Feature",
  "properties": {
    "addr:full":"27 Ivanhoe Pl North Ryde NSW 2113",
    "addr:housenumber":"27",
    "addr:postcode":"2113",
    "addr:street":"Ivanhoe Pl",
    "iso:country":"AU",
    "sg:address":"27 Ivanhoe Pl",
    "sg:city":"North Ryde",
    "sg:classifiers":[
        {
            "category":"Social Services",
            "subcategory":"Child Care",
            "type":"Services"
        }
    ],
    "sg:phone":"+61 2 9878 5969",
    "sg:postcode":"2113",
    "sg:province":"NSW",
    "wof:name":"Macquarie Park Childcare Centre",
    "wof:placetype":"venue"
},
  "geometry": {"coordinates":[151.116363525,-33.7821083069],"type":"Point"}
}