{
  "type": "Feature",
  "properties": {
    "iso:country":"AU",
    "sg:address":"Shop 1&2, 321 Pakington St (In Nicholas St)",
    "sg:city":"Newtown",
    "sg:classifiers":[
        {
            "category":"Shopping",
            "subcategory":"Clothing, Apparel, & Fashions",
            "type":"Retail Goods"
        }
    ],
    "sg:phone":"+61 3 5222 7727",
    "sg:postcode":"3220",
    "sg:province":"VIC",
    "sg:tags":[
        "lady",
        "wear"
    ],
    "wof:name":"Urban Chic",
    "wof:placetype":"venue"
},
  "geometry": {"coordinates":[144.345245,-38.155945],"type":"Point"}
}