{
  "type": "Feature",
  "properties": {
    "iso:country":"AU",
    "sg:address":"1/72- 74 Chifley Drv",
    "sg:city":"Preston",
    "sg:classifiers":[
        {
            "category":"Shopping",
            "subcategory":"Computers & Home Electronics",
            "type":"Retail Goods"
        }
    ],
    "sg:phone":"+61 3 9480 6411",
    "sg:postcode":"3072",
    "sg:province":"VIC",
    "sg:tags":[
        "equipment",
        "multimedia"
    ],
    "wof:name":"Evan Evans Flags And Banners",
    "wof:placetype":"venue"
},
  "geometry": {"coordinates":[145.02981567399999,-37.7486991882],"type":"Point"}
}