{
  "type": "Feature",
  "properties": {
    "iso:country":"AU",
    "sg:address":"242 York St",
    "sg:city":"Sale",
    "sg:classifiers":[
        {
            "category":"Retail",
            "subcategory":"Auto Repair",
            "type":"Services"
        }
    ],
    "sg:phone":"+61 3 5144 3262",
    "sg:postcode":"3850",
    "sg:province":"VIC",
    "sg:tags":[
        "beater",
        "painter",
        "panel"
    ],
    "wof:name":"Sale T & M Auto Repairs",
    "wof:placetype":"venue"
},
  "geometry": {"coordinates":[147.06829834000001,-38.1041755676],"type":"Point"}
}