{
  "type": "Feature",
  "properties": {
    "addr:full":"Cnr Barkly & Blessington Sts St Kilda VIC 3182",
    "addr:postcode":"3182",
    "addr:street":"Cnr Barkly & Blessington Sts",
    "iso:country":"AU",
    "sg:address":"Cnr Barkly & Blessington Sts St",
    "sg:city":"Kilda",
    "sg:classifiers":[
        {
            "category":"Food & Beverages",
            "subcategory":"Groceries & Convenience Stores",
            "type":"Retail Goods"
        }
    ],
    "sg:phone":"+61 3 9534 5192",
    "sg:postcode":"3182",
    "sg:province":"VIC",
    "wof:name":"7-Eleven Stores Pty Ltd",
    "wof:placetype":"venue"
},
  "geometry": {"coordinates":[144.982666016,-37.8592605591],"type":"Point"}
}