{
  "type": "Feature",
  "properties": {
    "addr:full":"25 Wood St Dalby QLD 4405",
    "addr:housenumber":"25",
    "addr:postcode":"4405",
    "addr:street":"Wood St",
    "iso:country":"AU",
    "sg:address":"25 Wood St",
    "sg:city":"Dalby",
    "sg:classifiers":[
        {
            "category":"Education",
            "subcategory":"Music School",
            "type":"Public Place"
        }
    ],
    "sg:phone":"+61 7 4662 1895",
    "sg:postcode":"4405",
    "sg:province":"QLD",
    "sg:tags":[
        "teacher"
    ],
    "wof:name":"Johnston N M",
    "wof:placetype":"venue"
},
  "geometry": {"coordinates":[151.255950928,-27.1856842041],"type":"Point"}
}