{
  "type": "Feature",
  "properties": {
    "addr:full":"2 Bryce Crt Redcliffe QLD 4020",
    "addr:housenumber":"2",
    "addr:postcode":"4020",
    "addr:street":"Bryce Crt",
    "iso:country":"AU",
    "sg:address":"2 Bryce Crt",
    "sg:city":"Redcliffe",
    "sg:classifiers":[
        {
            "category":"Personal",
            "subcategory":"Beauty Salon",
            "type":"Services"
        }
    ],
    "sg:phone":"+61 409 761 128",
    "sg:postcode":"4020",
    "sg:province":"QLD",
    "sg:tags":[
        "hairdresser"
    ],
    "wof:name":"Ladies Mobile Hair & Beauty",
    "wof:placetype":"venue"
},
  "geometry": {"coordinates":[153.102158,-27.217266],"type":"Point"}
}