{
  "type": "Feature",
  "properties": {
    "iso:country":"AU",
    "sg:address":"Unit 7 63 Ourimbah Rd",
    "sg:city":"Tweed Heads",
    "sg:classifiers":[
        {
            "category":"Retail",
            "subcategory":"Storage",
            "type":"Services"
        }
    ],
    "sg:phone":"+61 1800 028 390",
    "sg:postcode":"2485",
    "sg:province":"NSW",
    "sg:tags":[
        "removal",
        "furniture"
    ],
    "wof:name":"Kirkham Family The",
    "wof:placetype":"venue"
},
  "geometry": {"coordinates":[153.528106689,-28.1762065887],"type":"Point"}
}