{
  "type": "Feature",
  "properties": {
    "addr:full":"Suite 1208, Level 12, 370 Pitt St Sydney NSW 2000",
    "addr:housenumber":"1208 level 12 370",
    "addr:postcode":"2000",
    "addr:street":"Pitt St",
    "iso:country":"AU",
    "sg:address":"Suite 1208, Level 12, 370 Pitt St",
    "sg:city":"Sydney",
    "sg:classifiers":[
        {
            "category":"Health Services",
            "subcategory":"Doctor",
            "type":"Services"
        }
    ],
    "sg:phone":"+61 2 9264 7511",
    "sg:postcode":"2000",
    "sg:province":"NSW",
    "sg:tags":[
        "medical",
        "practitioner"
    ],
    "wof:name":"Parmegiani Enrico Dr",
    "wof:placetype":"venue"
},
  "geometry": {"coordinates":[151.207794189,-33.8773345947],"type":"Point"}
}