{
  "type": "Feature",
  "properties": {
    "addr:full":"83 Wyndora Ave Harbord NSW 2096",
    "addr:housenumber":"83",
    "addr:postcode":"2096",
    "addr:street":"Wyndora Ave",
    "iso:country":"AU",
    "sg:address":"83 Wyndora Ave",
    "sg:city":"Harbord",
    "sg:classifiers":[
        {
            "category":"Professional",
            "subcategory":"Computer Services",
            "type":"Services"
        }
    ],
    "sg:phone":"+61 2 9938 3873",
    "sg:postcode":"2096",
    "sg:province":"NSW",
    "sg:tags":[
        "consultant",
        "system"
    ],
    "wof:name":"Hague Consultants",
    "wof:placetype":"venue"
},
  "geometry": {"coordinates":[151.285064697,-33.7747383118],"type":"Point"}
}