{
  "type": "Feature",
  "properties": {
    "addr:full":"Heidke Rd Kalkie QLD 4670",
    "addr:postcode":"4670",
    "addr:street":"Heidke Rd",
    "iso:country":"AU",
    "sg:address":"Heidke Rd",
    "sg:city":"Kalkie",
    "sg:classifiers":[
        {
            "category":"Farming",
            "subcategory":"Crops",
            "type":"Manufacturing & Wholesale Goods"
        }
    ],
    "sg:phone":"+61 7 4159 3291",
    "sg:postcode":"4670",
    "sg:province":"QLD",
    "sg:tags":[
        "sugarcane",
        "mill",
        "grower"
    ],
    "wof:name":"Heidke A C & W F & B E",
    "wof:placetype":"venue"
},
  "geometry": {"coordinates":[152.319290161,-24.8863449097],"type":"Point"}
}