{
  "type": "Feature",
  "properties": {
    "addr:full":"30 Ware St Fairfield NSW 2165",
    "addr:housenumber":"30",
    "addr:postcode":"2165",
    "addr:street":"Ware St",
    "iso:country":"AU",
    "sg:address":"30 Ware St",
    "sg:city":"Fairfield",
    "sg:classifiers":[
        {
            "category":"Health Services",
            "subcategory":"Doctor",
            "type":"Services"
        }
    ],
    "sg:phone":"+61 2 9726 1183",
    "sg:postcode":"2165",
    "sg:province":"NSW",
    "sg:tags":[
        "medical",
        "practitioner"
    ],
    "wof:name":"Atto John Dr",
    "wof:placetype":"venue"
},
  "geometry": {"coordinates":[150.95513915999999,-33.8712348938],"type":"Point"}
}