{
  "type": "Feature",
  "properties": {
    "addr:full":"19 Limestone St Ipswich QLD 4305",
    "addr:housenumber":"19",
    "addr:postcode":"4305",
    "addr:street":"Limestone St",
    "iso:country":"AU",
    "sg:address":"19 Limestone St",
    "sg:city":"Ipswich",
    "sg:classifiers":[
        {
            "category":"Fast Food",
            "type":"Food & Drink"
        }
    ],
    "sg:phone":"+61 7 3282 7444",
    "sg:postcode":"4305",
    "sg:province":"QLD",
    "sg:tags":[
        "away",
        "take"
    ],
    "wof:name":"Tomato Brothers Restaurant",
    "wof:placetype":"venue"
},
  "geometry": {"coordinates":[152.763839722,-27.6159934998],"type":"Point"}
}