{
  "type": "Feature",
  "properties": {
    "addr:full":"401 Redland Bay Rd Capalaba QLD 4157",
    "addr:housenumber":"401",
    "addr:postcode":"4157",
    "addr:street":"Redland Bay Rd",
    "iso:country":"AU",
    "sg:address":"401 Redland Bay Rd",
    "sg:city":"Capalaba",
    "sg:classifiers":[
        {
            "category":"Home & Garden",
            "subcategory":"Garden Supply",
            "type":"Retail Goods"
        }
    ],
    "sg:phone":"+61 7 3206 4166",
    "sg:postcode":"4157",
    "sg:province":"QLD",
    "sg:tags":[
        "equipment"
    ],
    "wof:name":"Colonial Landscape Supplies",
    "wof:placetype":"venue"
},
  "geometry": {"coordinates":[153.21339416500001,-27.5399875641],"type":"Point"}
}