{
  "type": "Feature",
  "properties": {
    "addr:full":"74 Amherst St Cammeray NSW 2062",
    "addr:housenumber":"74",
    "addr:postcode":"2062",
    "addr:street":"Amherst St",
    "iso:country":"AU",
    "sg:address":"74 Amherst St",
    "sg:city":"Cammeray",
    "sg:classifiers":[
        {
            "category":"Professional",
            "subcategory":"Employment Agencies",
            "type":"Services"
        }
    ],
    "sg:phone":"+61 2 9929 5022",
    "sg:postcode":"2062",
    "sg:province":"NSW",
    "sg:tags":[
        "theatrical",
        "managers",
        "agent",
        "producer"
    ],
    "wof:name":"Telecast Theatrical & Television Agents",
    "wof:placetype":"venue"
},
  "geometry": {"coordinates":[151.211593628,-33.8230438232],"type":"Point"}
}