{
  "type": "Feature",
  "properties": {
    "addr:full":"22 Fitzroy St St Kilda VIC 3182",
    "addr:housenumber":"22",
    "addr:postcode":"3182",
    "addr:street":"Fitzroy St",
    "iso:country":"AU",
    "sg:address":"22 Fitzroy St St",
    "sg:city":"Kilda",
    "sg:classifiers":[
        {
            "category":"Education",
            "subcategory":"University",
            "type":"Public Place"
        }
    ],
    "sg:phone":"+61 3 9536 3109",
    "sg:postcode":"3182",
    "sg:province":"VIC",
    "sg:tags":[
        "college",
        "tertiary"
    ],
    "wof:name":"Graduate Management Association Of Australia Inc.",
    "wof:placetype":"venue"
},
  "geometry": {"coordinates":[144.974884033,-37.8610801697],"type":"Point"}
}