{
  "type": "Feature",
  "properties": {
    "addr:full":"Links Rd Giru QLD 4809",
    "addr:postcode":"4809",
    "addr:street":"Links Rd",
    "iso:country":"AU",
    "sg:address":"Links Rd",
    "sg:city":"Giru",
    "sg:classifiers":[
        {
            "category":"Farming",
            "subcategory":"Farm",
            "type":"Manufacturing & Wholesale Goods"
        }
    ],
    "sg:phone":"+61 7 4782 9177",
    "sg:postcode":"4809",
    "sg:province":"QLD",
    "sg:tags":[
        "farmer"
    ],
    "wof:name":"Scarabel Algie",
    "wof:placetype":"venue"
},
  "geometry": {"coordinates":[147.06246948200001,-19.5331134796],"type":"Point"}
}