{
  "type": "Feature",
  "properties": {
    "iso:country":"AU",
    "sg:address":"9 Nells Rd",
    "sg:city":"Gosford West",
    "sg:classifiers":[
        {
            "category":"Building & Trades",
            "subcategory":"Construction",
            "type":"Services"
        }
    ],
    "sg:phone":"+61 2 4324 7077",
    "sg:postcode":"2250",
    "sg:province":"NSW",
    "sg:tags":[
        "joinery"
    ],
    "wof:name":"Deamer's Traditional Joinery",
    "wof:placetype":"venue"
},
  "geometry": {"coordinates":[151.320678711,-33.4181632996],"type":"Point"}
}