{
  "type": "Feature",
  "properties": {
    "addr:full":"Shop 1 Charles St Plaza Charles St Adelaide SA 5000",
    "addr:housenumber":"shop 1",
    "addr:postcode":"5000",
    "addr:street":"Charles St Plaza Charles St",
    "iso:country":"AU",
    "sg:address":"Shop 1 Charles St Plaza Charles St",
    "sg:city":"Adelaide",
    "sg:classifiers":[
        {
            "category":"Retail",
            "subcategory":"Repair Shop",
            "type":"Services"
        }
    ],
    "sg:phone":"+61 8 8223 1244",
    "sg:postcode":"5000",
    "sg:province":"SA",
    "sg:tags":[
        "mending",
        "clothing",
        "alteration"
    ],
    "wof:name":"Final Stitch",
    "wof:placetype":"venue"
},
  "geometry": {"coordinates":[138.60354614299999,-34.9225502014],"type":"Point"}
}