{
  "type": "Feature",
  "properties": {
    "addr:full":"Unit 5-6, 99 Lysaght St Mitchell ACT 2911",
    "addr:housenumber":"99",
    "addr:postcode":"2911",
    "addr:street":"Lysaght St",
    "iso:country":"AU",
    "sg:address":"Unit 5-6, 99 Lysaght St",
    "sg:city":"Mitchell",
    "sg:classifiers":[
        {
            "category":"Home & Garden",
            "subcategory":"Carpets & Floor Coverings",
            "type":"Retail Goods"
        }
    ],
    "sg:phone":"+61 2 6241 0811",
    "sg:postcode":"2911",
    "sg:province":"ACT",
    "sg:tags":[
        "tile",
        "wall"
    ],
    "wof:name":"Actiles",
    "wof:placetype":"venue"
},
  "geometry": {"coordinates":[149.14109802199999,-35.2156028748],"type":"Point"}
}