{
  "type": "Feature",
  "properties": {
    "iso:country":"AU",
    "sg:address":"33 Welbeck Rd",
    "sg:city":"Canning Vale",
    "sg:classifiers":[
        {
            "category":"Government",
            "subcategory":"Court House",
            "type":"Public Place"
        }
    ],
    "sg:phone":"+61 8 9456 4414",
    "sg:postcode":"6155",
    "sg:province":"WA",
    "sg:tags":[
        "personal",
        "marriage",
        "family",
        "counselling"
    ],
    "wof:name":"Canning Vale Counselling Centre",
    "wof:placetype":"venue"
},
  "geometry": {"coordinates":[115.941849,-32.09079],"type":"Point"}
}