{
  "type": "Feature",
  "properties": {
    "addr:full":"7 Liali Crt Point Cook VIC 3030",
    "addr:housenumber":"7",
    "addr:postcode":"3030",
    "addr:street":"Liali Crt",
    "iso:country":"AU",
    "sg:address":"7 Liali Crt",
    "sg:city":"Point Cook",
    "sg:classifiers":[
        {
            "category":"Professional",
            "subcategory":"Accounting & Tax Preparation",
            "type":"Services"
        }
    ],
    "sg:phone":"+61 416 110 629",
    "sg:postcode":"3030",
    "sg:province":"VIC",
    "sg:tags":[
        "bookkeeping"
    ],
    "wof:name":"TRW Business Services",
    "wof:placetype":"venue"
},
  "geometry": {"coordinates":[144.738235,-37.896435],"type":"Point"}
}