{
  "type": "Feature",
  "properties": {
    "addr:full":"80 Mount St North Sydney NSW 2060",
    "addr:housenumber":"80",
    "addr:postcode":"2060",
    "addr:street":"Mount St",
    "iso:country":"AU",
    "sg:address":"80 Mount St",
    "sg:city":"North Sydney",
    "sg:classifiers":[
        {
            "category":"Food & Beverages",
            "subcategory":"Specialty",
            "type":"Retail Goods"
        }
    ],
    "sg:phone":"+61 2 8904 0348",
    "sg:postcode":"2060",
    "sg:province":"NSW",
    "sg:tags":[
        "product",
        "health"
    ],
    "wof:name":"Daily Squeeze",
    "wof:placetype":"venue"
},
  "geometry": {"coordinates":[151.20817565900001,-33.8388671875],"type":"Point"}
}