{
  "type": "Feature",
  "properties": {
    "iso:country":"AU",
    "sg:address":"31 Post Office Rd",
    "sg:city":"Glenorie",
    "sg:classifiers":[
        {
            "category":"Real Estate",
            "subcategory":"Surveying",
            "type":"Services"
        }
    ],
    "sg:phone":"+61 2 9652 1488",
    "sg:postcode":"2157",
    "sg:province":"NSW",
    "sg:tags":[
        "surveyor",
        "quantity"
    ],
    "wof:name":"H.J.L. Constructions Pty Ltd",
    "wof:placetype":"venue"
},
  "geometry": {"coordinates":[151.008056641,-33.6048545837],"type":"Point"}
}