{
  "type": "Feature",
  "properties": {
    "addr:full":"37 Victoria Rd Camberwell VIC 3124",
    "addr:housenumber":"37",
    "addr:postcode":"3124",
    "addr:street":"Victoria Rd",
    "iso:country":"AU",
    "sg:address":"37 Victoria Rd",
    "sg:city":"Camberwell",
    "sg:classifiers":[
        {
            "category":"Health Services",
            "subcategory":"Dentist",
            "type":"Services"
        }
    ],
    "sg:phone":"+61 3 9882 7546",
    "sg:postcode":"3124",
    "sg:province":"VIC",
    "wof:name":"Braham Derek D Dr",
    "wof:placetype":"venue"
},
  "geometry": {"coordinates":[145.062408447,-37.8238334656],"type":"Point"}
}