{
  "type": "Feature",
  "properties": {
    "addr:full":"69 Albion Rd Albion QLD 4010",
    "addr:housenumber":"69",
    "addr:postcode":"4010",
    "addr:street":"Albion Rd",
    "iso:country":"AU",
    "sg:address":"69 Albion Rd",
    "sg:city":"Albion",
    "sg:classifiers":[
        {
            "category":"Personal",
            "subcategory":"Beauty Salon",
            "type":"Services"
        }
    ],
    "sg:phone":"+61 7 3357 9090",
    "sg:postcode":"4010",
    "sg:province":"QLD",
    "wof:name":"Patricia Skin & Electrolysis Therapy",
    "wof:placetype":"venue"
},
  "geometry": {"coordinates":[153.038452148,-27.4293251038],"type":"Point"}
}