{
  "type": "Feature",
  "properties": {
    "iso:country":"AU",
    "sg:address":"6 Ingham Rd",
    "sg:city":"Townsville",
    "sg:classifiers":[
        {
            "category":"Education",
            "subcategory":"Junior College",
            "type":"Public Place"
        }
    ],
    "sg:phone":"+61 7 4771 2091",
    "sg:postcode":"4810",
    "sg:province":"QLD",
    "sg:tags":[
        "wholesaler",
        "school",
        "mfrs",
        "uniform"
    ],
    "wof:name":"Fourex Clothing Pty Ltd",
    "wof:placetype":"venue"
},
  "geometry": {"coordinates":[146.75500500000001,-19.262217],"type":"Point"}
}