{
  "type": "Feature",
  "properties": {
    "iso:country":"AU",
    "sg:address":"14 Gouldson Drv",
    "sg:city":"Toowoomba",
    "sg:classifiers":[
        {
            "category":"Building & Trades",
            "subcategory":"Construction",
            "type":"Services"
        }
    ],
    "sg:phone":"+61 7 4635 7350",
    "sg:postcode":"4350",
    "sg:province":"QLD",
    "sg:tags":[
        "contractor"
    ],
    "wof:name":"Trevor Miller Builder Pty Ltd",
    "wof:placetype":"venue"
},
  "geometry": {"coordinates":[151.94885300000001,-27.604092],"type":"Point"}
}