{
  "type": "Feature",
  "properties": {
    "addr:full":"171 Clarendon St South Melbourne VIC 3205",
    "addr:housenumber":"171",
    "addr:postcode":"3205",
    "addr:street":"Clarendon St",
    "iso:country":"AU",
    "sg:address":"171 Clarendon St",
    "sg:city":"South Melbourne",
    "sg:classifiers":[
        {
            "category":"Professional",
            "subcategory":"Printing & Photocopies",
            "type":"Services"
        }
    ],
    "sg:phone":"+61 3 9682 3330",
    "sg:postcode":"3205",
    "sg:province":"VIC",
    "sg:tags":[
        "laminating"
    ],
    "wof:name":"Qasco Vic",
    "wof:placetype":"venue"
},
  "geometry": {"coordinates":[144.96270799999999,-37.835869],"type":"Point"}
}