{
  "type": "Feature",
  "properties": {
    "addr:full":"Shop 3, Gerringong Plaza, Blackwood Street Gerringong NSW 2534",
    "addr:housenumber":"shop 3",
    "addr:postcode":"2534",
    "addr:street":"Gerringong Plaza Blackwood Street",
    "iso:country":"AU",
    "sg:address":"Shop 3, Gerringong Plaza, Blackwood Street",
    "sg:city":"Gerringong",
    "sg:classifiers":[
        {
            "category":"Communications",
            "subcategory":"Film & Video Production",
            "type":"Services"
        }
    ],
    "sg:phone":"+61 2 4234 1013",
    "sg:postcode":"2534",
    "sg:province":"NSW",
    "sg:tags":[
        "dvd",
        "library"
    ],
    "wof:name":"Gerringong Top Video",
    "wof:placetype":"venue"
},
  "geometry": {"coordinates":[150.82594299300001,-34.7449913025],"type":"Point"}
}