{
  "type": "Feature",
  "properties": {
    "addr:full":"4 Azalea St Colo Vale NSW 2575",
    "addr:housenumber":"4",
    "addr:postcode":"2575",
    "addr:street":"Azalea St",
    "iso:country":"AU",
    "sg:address":"4 Azalea St",
    "sg:city":"Colo Vale",
    "sg:classifiers":[
        {
            "category":"Building & Trades",
            "subcategory":"Plumbing",
            "type":"Services"
        }
    ],
    "sg:phone":"+61 2 4889 4770",
    "sg:postcode":"2575",
    "sg:province":"NSW",
    "sg:tags":[
        "plumber",
        "gasfitters"
    ],
    "wof:name":"Bruce Richardson Plumbing & Excavations",
    "wof:placetype":"venue"
},
  "geometry": {"coordinates":[150.48068237300001,-34.4048805237],"type":"Point"}
}