{
  "type": "Feature",
  "properties": {
    "iso:country":"AU",
    "sg:address":"6 Currunghi Crt St",
    "sg:city":"Albans",
    "sg:classifiers":[
        {
            "category":"Building & Trades",
            "subcategory":"Construction",
            "type":"Services"
        }
    ],
    "sg:phone":"+61 1300 360 521",
    "sg:postcode":"3021",
    "sg:province":"VIC",
    "sg:tags":[
        "fencing",
        "contractor"
    ],
    "wof:name":"Stagg Industries Pty Ltd",
    "wof:placetype":"venue"
},
  "geometry": {"coordinates":[144.82768200000001,-37.751766],"type":"Point"}
}