{
  "type": "Feature",
  "properties": {
    "addr:full":"292 Maroondah Hwy Healesville VIC 3777",
    "addr:housenumber":"292",
    "addr:postcode":"3777",
    "addr:street":"Maroondah Hwy",
    "iso:country":"AU",
    "sg:address":"292 Maroondah Hwy",
    "sg:city":"Healesville",
    "sg:classifiers":[
        {
            "category":"Professional",
            "subcategory":"Art Services",
            "type":"Services"
        }
    ],
    "sg:phone":"+61 3 5962 2929",
    "sg:postcode":"3777",
    "sg:province":"VIC",
    "sg:tags":[
        "interior",
        "decorator"
    ],
    "wof:name":"Elly Milner - The Finishing Touch Interiors",
    "wof:placetype":"venue"
},
  "geometry": {"coordinates":[145.51817299999999,-37.653656],"type":"Point"}
}