{
  "type": "Feature",
  "properties": {
    "iso:country":"AU",
    "sg:address":"1108 High St",
    "sg:city":"Armadale",
    "sg:classifiers":[
        {
            "category":"Shopping",
            "subcategory":"Clothing, Apparel, & Fashions",
            "type":"Retail Goods"
        }
    ],
    "sg:phone":"+61 3 9500 0833",
    "sg:postcode":"3143",
    "sg:province":"VIC",
    "sg:tags":[
        "lady",
        "wear"
    ],
    "wof:name":"John Cavill",
    "wof:placetype":"venue"
},
  "geometry": {"coordinates":[145.02418518100001,-37.8560676575],"type":"Point"}
}