{
  "type": "Feature",
  "properties": {
    "addr:full":"1 Gallant Crt Midvale WA 6056",
    "addr:housenumber":"1",
    "addr:postcode":"6056",
    "addr:street":"Gallant Crt",
    "iso:country":"AU",
    "sg:address":"1 Gallant Crt",
    "sg:city":"Midvale",
    "sg:classifiers":[
        {
            "category":"Manufacturing",
            "subcategory":"Rubber & Plastics",
            "type":"Manufacturing & Wholesale Goods"
        }
    ],
    "sg:phone":"+61 8 9250 3777",
    "sg:postcode":"6056",
    "sg:province":"WA",
    "sg:tags":[
        "wholesaler",
        "product",
        "mfrs"
    ],
    "wof:name":"ARP",
    "wof:placetype":"venue"
},
  "geometry": {"coordinates":[116.03315734900001,-31.8915538788],"type":"Point"}
}