{
  "type": "Feature",
  "properties": {
    "addr:full":"2 Lockington Rd Lockington VIC 3563",
    "addr:housenumber":"2",
    "addr:postcode":"3563",
    "addr:street":"Lockington Rd",
    "iso:country":"AU",
    "sg:address":"2 Lockington Rd",
    "sg:city":"Lockington",
    "sg:classifiers":[
        {
            "category":"Food & Beverages",
            "subcategory":"Supermarket",
            "type":"Retail Goods"
        }
    ],
    "sg:phone":"+61 3 5486 2200",
    "sg:postcode":"3563",
    "sg:province":"VIC",
    "sg:tags":[
        "grocery",
        "store"
    ],
    "wof:name":"Pentreath's Lockington",
    "wof:placetype":"venue"
},
  "geometry": {"coordinates":[144.53581199999999,-36.271576],"type":"Point"}
}