{
  "type": "Feature",
  "properties": {
    "addr:full":"19 Blackstone Rd Prospect TAS 7250",
    "addr:housenumber":"19",
    "addr:postcode":"7250",
    "addr:street":"Blackstone Rd",
    "iso:country":"AU",
    "sg:address":"19 Blackstone Rd",
    "sg:city":"Prospect",
    "sg:classifiers":[
        {
            "category":"Professional",
            "subcategory":"Art Services",
            "type":"Services"
        }
    ],
    "sg:phone":"+61 3 6343 0251",
    "sg:postcode":"7250",
    "sg:province":"TAS",
    "sg:tags":[
        "decorator",
        "painter"
    ],
    "wof:name":"Anderson J",
    "wof:placetype":"venue"
},
  "geometry": {"coordinates":[147.084274292,-41.4692077637],"type":"Point"}
}