{
  "type": "Feature",
  "properties": {
    "iso:country":"AU",
    "sg:address":"15 Mary St",
    "sg:city":"Granville",
    "sg:classifiers":[
        {
            "category":"Health Services",
            "subcategory":"Doctor",
            "type":"Services"
        }
    ],
    "sg:phone":"+61 2 9637 7973",
    "sg:postcode":"2142",
    "sg:province":"NSW",
    "sg:tags":[
        "medical",
        "practitioner"
    ],
    "wof:name":"Sivaguru Ahila Dr",
    "wof:placetype":"venue"
},
  "geometry": {"coordinates":[151.010223389,-33.8336715698],"type":"Point"}
}