{
  "type": "Feature",
  "properties": {
    "addr:full":"1a Boronia St Belfield NSW 2191",
    "addr:housenumber":"1a",
    "addr:postcode":"2191",
    "addr:street":"Boronia St",
    "iso:country":"AU",
    "sg:address":"1a Boronia St",
    "sg:city":"Belfield",
    "sg:classifiers":[
        {
            "category":"Professional",
            "subcategory":"Computer Services",
            "type":"Services"
        }
    ],
    "sg:phone":"+61 419 237 182",
    "sg:postcode":"2191",
    "sg:province":"NSW",
    "sg:tags":[
        "technical",
        "support"
    ],
    "wof:name":"Caravelle I.T. Services",
    "wof:placetype":"venue"
},
  "geometry": {"coordinates":[151.08111600000001,-33.906967],"type":"Point"}
}