{
  "type": "Feature",
  "properties": {
    "iso:country":"AU",
    "sg:address":"2 Techno Park Drv",
    "sg:city":"Williamstown",
    "sg:classifiers":[
        {
            "category":"Professional",
            "subcategory":"Secretarial Services",
            "type":"Services"
        }
    ],
    "sg:phone":"+61 3 9397 5520",
    "sg:postcode":"3016",
    "sg:province":"VIC",
    "sg:tags":[
        "typing"
    ],
    "wof:name":"Lisa Carson Secretarial Services",
    "wof:placetype":"venue"
},
  "geometry": {"coordinates":[144.85873413100001,-37.8545455933],"type":"Point"}
}