{
  "type": "Feature",
  "properties": {
    "addr:full":"106 Hammond Ave Wagga Wagga NSW 2650",
    "addr:housenumber":"106",
    "addr:postcode":"2650",
    "addr:street":"Hammond Ave",
    "iso:country":"AU",
    "sg:address":"106 Hammond Ave",
    "sg:city":"Wagga Wagga",
    "sg:classifiers":[
        {
            "category":"Utilities",
            "subcategory":"Telephone",
            "type":"Services"
        }
    ],
    "sg:phone":"+61 2 6921 2125",
    "sg:postcode":"2650",
    "sg:province":"NSW",
    "sg:tags":[
        "accessory"
    ],
    "wof:name":"Rivercom",
    "wof:placetype":"venue"
},
  "geometry": {"coordinates":[147.395584106,-35.1227073669],"type":"Point"}
}