{
  "type": "Feature",
  "properties": {
    "iso:country":"AU",
    "sg:address":"68 Quinlan Ave St",
    "sg:city":"Marys",
    "sg:classifiers":[
        {
            "category":"Professional",
            "subcategory":"Art Services",
            "type":"Services"
        }
    ],
    "sg:phone":"+61 8 8276 1680",
    "sg:postcode":"5042",
    "sg:province":"SA",
    "sg:tags":[
        "decorator",
        "painter"
    ],
    "wof:name":"Chateau Property Services",
    "wof:placetype":"venue"
},
  "geometry": {"coordinates":[138.583755,-35.005569],"type":"Point"}
}