{
  "type": "Feature",
  "properties": {
    "addr:full":"Stirling House 155 Mount Barker Rd Stirling SA 5152",
    "addr:housenumber":"155",
    "addr:postcode":"5152",
    "addr:street":"Mount Barker Rd",
    "iso:country":"AU",
    "sg:address":"Stirling House 155 Mount Barker Rd",
    "sg:city":"Stirling",
    "sg:classifiers":[
        {
            "category":"Personal",
            "subcategory":"Massage",
            "type":"Services"
        }
    ],
    "sg:phone":"+61 414 317 414",
    "sg:postcode":"5152",
    "sg:province":"SA",
    "sg:tags":[
        "therapy"
    ],
    "wof:name":"Jennifer Doubell",
    "wof:placetype":"venue"
},
  "geometry": {"coordinates":[138.72276306099999,-35.0082511902],"type":"Point"}
}