{
  "type": "Feature",
  "properties": {
    "addr:full":"43 Phillip St Goonellabah NSW 2480",
    "addr:housenumber":"43",
    "addr:postcode":"2480",
    "addr:street":"Phillip St",
    "iso:country":"AU",
    "sg:address":"43 Phillip St",
    "sg:city":"Goonellabah",
    "sg:classifiers":[
        {
            "category":"Social Services",
            "subcategory":"Adult Care",
            "type":"Services"
        }
    ],
    "sg:phone":"+61 2 6624 6711",
    "sg:postcode":"2480",
    "sg:province":"NSW",
    "sg:tags":[
        "aged"
    ],
    "wof:name":"Caroona Community Aged Care Packages",
    "wof:placetype":"venue"
},
  "geometry": {"coordinates":[153.32362365700001,-28.8258152008],"type":"Point"}
}