{
  "type": "Feature",
  "properties": {
    "addr:full":"10 Carlyle St Springwood QLD 4127",
    "addr:housenumber":"10",
    "addr:postcode":"4127",
    "addr:street":"Carlyle St",
    "iso:country":"AU",
    "sg:address":"10 Carlyle St",
    "sg:city":"Springwood",
    "sg:classifiers":[
        {
            "category":"Manufacturing",
            "subcategory":"Motor Vehicles & Parts",
            "type":"Manufacturing & Wholesale Goods"
        }
    ],
    "sg:phone":"+61 7 3290 7888",
    "sg:postcode":"4127",
    "sg:province":"QLD",
    "sg:tags":[
        "replacement"
    ],
    "wof:name":"Nissan Highway",
    "wof:placetype":"venue"
},
  "geometry": {"coordinates":[153.13087463400001,-27.6320648193],"type":"Point"}
}