{
  "type": "Feature",
  "properties": {
    "addr:full":"254 Princes Hwy Sylvania NSW 2224",
    "addr:housenumber":"254",
    "addr:postcode":"2224",
    "addr:street":"Princes Hwy",
    "iso:country":"AU",
    "sg:address":"254 Princes Hwy",
    "sg:city":"Sylvania",
    "sg:classifiers":[
        {
            "category":"Food & Beverages",
            "subcategory":"Fruits & Vegetables",
            "type":"Retail Goods"
        }
    ],
    "sg:phone":"+61 2 9522 9088",
    "sg:postcode":"2224",
    "sg:province":"NSW",
    "sg:tags":[
        "greengrocer",
        "fruiterer"
    ],
    "wof:name":"Vella T",
    "wof:placetype":"venue"
},
  "geometry": {"coordinates":[151.09454345699999,-34.0133705139],"type":"Point"}
}