{
  "type": "Feature",
  "properties": {
    "addr:full":"33 Livingstone St South West Rocks NSW 2431",
    "addr:housenumber":"33",
    "addr:postcode":"2431",
    "addr:street":"Livingstone St South West Rocks",
    "iso:country":"AU",
    "sg:address":"33 Livingstone St",
    "sg:city":"South West Rocks",
    "sg:classifiers":[
        {
            "category":"Fast Food",
            "type":"Food & Drink"
        }
    ],
    "sg:phone":"+61 2 6566 7703",
    "sg:postcode":"2431",
    "sg:province":"NSW",
    "sg:tags":[
        "away",
        "take"
    ],
    "wof:name":"South West Rocks Seafood",
    "wof:placetype":"venue"
},
  "geometry": {"coordinates":[153.041336,-30.884632],"type":"Point"}
}