{
  "type": "Feature",
  "properties": {
    "addr:full":"Unit 1/ 17 Anzac Rd Tuggerah NSW 2259",
    "addr:housenumber":"17",
    "addr:postcode":"2259",
    "addr:street":"Anzac Rd",
    "iso:country":"AU",
    "sg:address":"Unit 1/ 17 Anzac Rd",
    "sg:city":"Tuggerah",
    "sg:classifiers":[
        {
            "category":"Health Services",
            "subcategory":"Health Practitioner",
            "type":"Services"
        }
    ],
    "sg:phone":"+61 2 4353 5077",
    "sg:postcode":"2259",
    "sg:province":"NSW",
    "sg:tags":[
        "physiotherapist"
    ],
    "wof:name":"Holmes Trish",
    "wof:placetype":"venue"
},
  "geometry": {"coordinates":[151.41766357399999,-33.3067970276],"type":"Point"}
}