{
  "type": "Feature",
  "properties": {
    "addr:full":"27 Lake Albert Rd Wagga Wagga NSW 2650",
    "addr:housenumber":"27",
    "addr:postcode":"2650",
    "addr:street":"Lake Albert Rd",
    "iso:country":"AU",
    "sg:address":"27 Lake Albert Rd",
    "sg:city":"Wagga Wagga",
    "sg:classifiers":[
        {
            "category":"Travel",
            "subcategory":"Travel Agent",
            "type":"Entertainment"
        }
    ],
    "sg:phone":"+61 2 6971 9255",
    "sg:postcode":"2650",
    "sg:province":"NSW",
    "sg:tags":[
        "consultant"
    ],
    "wof:name":"Makeham's Coach & Bus Service",
    "wof:placetype":"venue"
},
  "geometry": {"coordinates":[147.371917725,-35.1490364075],"type":"Point"}
}