{
  "type": "Feature",
  "properties": {
    "iso:country":"AU",
    "sg:address":"8/ 11 Lancaster St",
    "sg:city":"Ingleburn",
    "sg:classifiers":[
        {
            "category":"Organizations",
            "subcategory":"Non-profit Organization",
            "type":"Services"
        }
    ],
    "sg:phone":"+61 2 9829 7940",
    "sg:postcode":"2565",
    "sg:province":"NSW",
    "sg:tags":[
        "support",
        "disability",
        "organisation"
    ],
    "wof:name":"The Australian Help! Programme",
    "wof:placetype":"venue"
},
  "geometry": {"coordinates":[150.865966797,-33.990852356],"type":"Point"}
}