{
  "type": "Feature",
  "properties": {
    "addr:full":"58 Coleman St Wagga Wagga NSW 2650",
    "addr:housenumber":"58",
    "addr:postcode":"2650",
    "addr:street":"Coleman St",
    "iso:country":"AU",
    "sg:address":"58 Coleman St",
    "sg:city":"Wagga Wagga",
    "sg:classifiers":[
        {
            "category":"Building & Trades",
            "subcategory":"Construction",
            "type":"Services"
        }
    ],
    "sg:phone":"+61 421 600 978",
    "sg:postcode":"2650",
    "sg:province":"NSW",
    "sg:tags":[
        "joiner",
        "carpenter"
    ],
    "wof:name":"Finemore's Home Maintenance & Repairs",
    "wof:placetype":"venue"
},
  "geometry": {"coordinates":[147.36196899399999,-35.1228904724],"type":"Point"}
}