{
  "type": "Feature",
  "properties": {
    "iso:country":"AU",
    "sg:address":"Scotsdale Rd",
    "sg:city":"Denmark",
    "sg:classifiers":[
        {
            "category":"Farming",
            "subcategory":"Farm",
            "type":"Manufacturing & Wholesale Goods"
        }
    ],
    "sg:phone":"+61 8 9840 9375",
    "sg:postcode":"6333",
    "sg:province":"WA",
    "sg:tags":[
        "farmer"
    ],
    "wof:name":"Howard M R & L J",
    "wof:placetype":"venue"
},
  "geometry": {"coordinates":[117.35299682599999,-34.9578781128],"type":"Point"}
}