{
  "type": "Feature",
  "properties": {
    "addr:full":"25 Yarraman Pl Virginia QLD 4014",
    "addr:housenumber":"25",
    "addr:postcode":"4014",
    "addr:street":"Yarraman Pl",
    "iso:country":"AU",
    "sg:address":"25 Yarraman Pl",
    "sg:city":"Virginia",
    "sg:classifiers":[
        {
            "category":"Building & Trades",
            "subcategory":"Construction",
            "type":"Services"
        }
    ],
    "sg:phone":"+61 7 3265 3055",
    "sg:postcode":"4014",
    "sg:province":"QLD",
    "sg:tags":[
        "earth",
        "excavating",
        "moving",
        "contractor"
    ],
    "wof:name":"J.D. Earthmoving",
    "wof:placetype":"venue"
},
  "geometry": {"coordinates":[153.05807495100001,-27.375743866],"type":"Point"}
}