{
  "type": "Feature",
  "properties": {
    "addr:full":"288 Crown St Wollongong NSW 2500",
    "addr:housenumber":"288",
    "addr:postcode":"2500",
    "addr:street":"Crown St",
    "iso:country":"AU",
    "sg:address":"288 Crown St",
    "sg:city":"Wollongong",
    "sg:classifiers":[
        {
            "category":"Shopping",
            "subcategory":"Party Supplies",
            "type":"Retail Goods"
        }
    ],
    "sg:phone":"+61 2 4229 7788",
    "sg:postcode":"2500",
    "sg:province":"NSW",
    "sg:tags":[
        "hire",
        "costume"
    ],
    "wof:name":"Capers Costumes",
    "wof:placetype":"venue"
},
  "geometry": {"coordinates":[150.89039600000001,-34.425385],"type":"Point"}
}