{
  "type": "Feature",
  "properties": {
    "addr:full":"PO Box 57 Timboon VIC 3268",
    "addr:postcode":"3268",
    "iso:country":"AU",
    "sg:address":"PO Box 57",
    "sg:city":"Timboon",
    "sg:classifiers":[
        {
            "category":"Commercial Area",
            "type":"Public Place"
        }
    ],
    "sg:phone":"+61 409 593 221",
    "sg:postcode":"3268",
    "sg:province":"VIC",
    "sg:tags":[
        "heavy",
        "carrier"
    ],
    "wof:name":"Dance Port Pty Ltd",
    "wof:placetype":"venue"
},
  "geometry": {"coordinates":[142.97679138199999,-38.4794006348],"type":"Point"}
}