{
  "type": "Feature",
  "properties": {
    "addr:full":"PO Box 350 Avoca Beach NSW 2251",
    "addr:postcode":"2251",
    "iso:country":"AU",
    "sg:address":"PO Box 350",
    "sg:city":"Avoca Beach",
    "sg:classifiers":[
        {
            "category":"Real Estate",
            "subcategory":"Real Estate Agent",
            "type":"Services"
        }
    ],
    "sg:phone":"+61 2 4382 6366",
    "sg:postcode":"2251",
    "sg:province":"NSW",
    "wof:name":"Compass Plus",
    "wof:placetype":"venue"
},
  "geometry": {"coordinates":[151.42500305199999,-33.4733924866],"type":"Point"}
}