{
  "type": "Feature",
  "properties": {
    "addr:full":"66 Dudley St West Melbourne VIC 3003",
    "addr:housenumber":"66",
    "addr:postcode":"3003",
    "addr:street":"Dudley St",
    "iso:country":"AU",
    "sg:address":"66 Dudley St",
    "sg:city":"West Melbourne",
    "sg:classifiers":[
        {
            "category":"Real Estate",
            "subcategory":"Architect",
            "type":"Services"
        }
    ],
    "sg:phone":"+61 3 9329 2233",
    "sg:postcode":"3003",
    "sg:province":"VIC",
    "wof:name":"Castles, Stephenson & Turner Pty Ltd",
    "wof:placetype":"venue"
},
  "geometry": {"coordinates":[144.95300293,-37.8088645935],"type":"Point"}
}