{
  "type": "Feature",
  "properties": {
    "iso:country":"AU",
    "sg:address":"5 Salandra St",
    "sg:city":"Mansfield",
    "sg:classifiers":[
        {
            "category":"Travel",
            "subcategory":"Travel Agent",
            "type":"Entertainment"
        }
    ],
    "sg:phone":"+61 7 3349 0577",
    "sg:postcode":"4122",
    "sg:province":"QLD",
    "sg:tags":[
        "consultant"
    ],
    "wof:name":"Auz Travel",
    "wof:placetype":"venue"
},
  "geometry": {"coordinates":[153.09916687,-27.5419082642],"type":"Point"}
}