{
  "type": "Feature",
  "properties": {
    "addr:full":"3 Grant St Bairnsdale VIC 3875",
    "addr:housenumber":"3",
    "addr:postcode":"3875",
    "addr:street":"Grant St",
    "iso:country":"AU",
    "sg:address":"3 Grant St",
    "sg:city":"Bairnsdale",
    "sg:classifiers":[
        {
            "category":"Home & Garden",
            "subcategory":"Carpets & Floor Coverings",
            "type":"Retail Goods"
        }
    ],
    "sg:phone":"+61 3 5152 2868",
    "sg:postcode":"3875",
    "sg:province":"VIC",
    "sg:tags":[
        "flooring",
        "parquet"
    ],
    "wof:name":"C & D Weir",
    "wof:placetype":"venue"
},
  "geometry": {"coordinates":[147.61993408199999,-37.8219795227],"type":"Point"}
}