{
  "type": "Feature",
  "properties": {
    "addr:full":"86 Marshall Rd Holland Park QLD 4121",
    "addr:housenumber":"86",
    "addr:postcode":"4121",
    "addr:street":"Marshall Rd",
    "iso:country":"AU",
    "sg:address":"86 Marshall Rd",
    "sg:city":"Holland Park",
    "sg:classifiers":[
        {
            "category":"Social Services",
            "subcategory":"Child Care",
            "type":"Services"
        }
    ],
    "sg:phone":"+61 7 3397 1400",
    "sg:postcode":"4121",
    "sg:province":"QLD",
    "wof:name":"Holland Park West Kindergarten & Child Care Centre",
    "wof:placetype":"venue"
},
  "geometry": {"coordinates":[153.063354492,-27.5209674835],"type":"Point"}
}