{
  "type": "Feature",
  "properties": {
    "addr:full":"Unit 2A, 4 Rocklea Drive Port Melbourne VIC 3207",
    "addr:housenumber":"unit 2a 4",
    "addr:postcode":"3207",
    "addr:street":"Rocklea Drive",
    "iso:country":"AU",
    "sg:address":"Unit 2A, 4 Rocklea Drive",
    "sg:city":"Port Melbourne",
    "sg:classifiers":[
        {
            "category":"Professional",
            "subcategory":"Computer Services",
            "type":"Services"
        }
    ],
    "sg:phone":"+61 3 9646 1099",
    "sg:postcode":"3207",
    "sg:province":"VIC",
    "sg:tags":[
        "equipment",
        "networking",
        "installation"
    ],
    "wof:name":"MGE Ups Systems",
    "wof:placetype":"venue"
},
  "geometry": {"coordinates":[144.92146299999999,-37.831596],"type":"Point"}
}