{
  "type": "Feature",
  "properties": {
    "addr:full":"Unit 2, 91 Guthrie St Osborne Park WA 6017",
    "addr:housenumber":"91",
    "addr:postcode":"6017",
    "addr:street":"Guthrie St",
    "iso:country":"AU",
    "sg:address":"Unit 2, 91 Guthrie St",
    "sg:city":"Osborne Park",
    "sg:classifiers":[
        {
            "category":"Home & Garden",
            "subcategory":"Kitchen Supply",
            "type":"Retail Goods"
        }
    ],
    "sg:phone":"+61 8 9446 4399",
    "sg:postcode":"6017",
    "sg:province":"WA",
    "sg:tags":[
        "sharpening"
    ],
    "wof:name":"Crown Sharpening Service",
    "wof:placetype":"venue"
},
  "geometry": {"coordinates":[115.817092895,-31.9070510864],"type":"Point"}
}