{
  "type": "Feature",
  "properties": {
    "addr:full":"U6/ 151 Brisbane St Perth WA 6000",
    "addr:housenumber":"151",
    "addr:postcode":"6000",
    "addr:street":"U6 /;Brisbane St",
    "iso:country":"AU",
    "sg:address":"U6/ 151 Brisbane St",
    "sg:city":"Perth",
    "sg:classifiers":[
        {
            "category":"Professional",
            "subcategory":"Accounting & Tax Preparation",
            "type":"Services"
        }
    ],
    "sg:phone":"+61 8 9386 3234",
    "sg:postcode":"6000",
    "sg:province":"WA",
    "sg:tags":[
        "accountant",
        "auditor"
    ],
    "wof:name":"Banister-Jones & Campbell",
    "wof:placetype":"venue"
},
  "geometry": {"coordinates":[115.861091614,-31.9420547485],"type":"Point"}
}