{
  "type": "Feature",
  "properties": {
    "addr:full":"Winston Hills Mall Caroline Chisholm Drv Winston Hills NSW 2153",
    "addr:postcode":"2153",
    "addr:street":"Chisholm Drv",
    "iso:country":"AU",
    "sg:address":"Winston Hills Mall Caroline Chisholm Drv",
    "sg:city":"Winston Hills",
    "sg:classifiers":[
        {
            "category":"Shopping",
            "subcategory":"Clothing, Apparel, & Fashions",
            "type":"Retail Goods"
        }
    ],
    "sg:phone":"+61 2 9674 4237",
    "sg:postcode":"2153",
    "sg:province":"NSW",
    "sg:tags":[
        "menswear"
    ],
    "wof:name":"Mike Samson Clothier",
    "wof:placetype":"venue"
},
  "geometry": {"coordinates":[150.97398376500001,-33.7760925293],"type":"Point"}
}