{
  "type": "Feature",
  "properties": {
    "addr:full":"1 Jubilee Ave Mullumbimby NSW 2482",
    "addr:housenumber":"1",
    "addr:postcode":"2482",
    "addr:street":"Jubilee Ave",
    "iso:country":"AU",
    "sg:address":"1 Jubilee Ave",
    "sg:city":"Mullumbimby",
    "sg:classifiers":[
        {
            "category":"Wholesale",
            "subcategory":"Farm Supplies",
            "type":"Manufacturing & Wholesale Goods"
        }
    ],
    "sg:phone":"+61 2 6684 2239",
    "sg:postcode":"2482",
    "sg:province":"NSW",
    "sg:tags":[
        "equipment"
    ],
    "wof:name":"Mullumbimby Rural Co-Op Socy Ltd",
    "wof:placetype":"venue"
},
  "geometry": {"coordinates":[153.49882507300001,-28.5558891296],"type":"Point"}
}