{
  "type": "Feature",
  "properties": {
    "addr:full":"Shops 9 & 10, Mirrabooka Ave Moruya NSW 2537",
    "addr:housenumber":"shops 9 & 10",
    "addr:postcode":"2537",
    "addr:street":"Mirrabooka Ave",
    "iso:country":"AU",
    "sg:address":"Shops 9 & 10, Mirrabooka Ave",
    "sg:city":"Moruya",
    "sg:classifiers":[
        {
            "category":"Home & Garden",
            "subcategory":"Furniture",
            "type":"Retail Goods"
        }
    ],
    "sg:phone":"+61 2 4474 4044",
    "sg:postcode":"2537",
    "sg:province":"NSW",
    "sg:tags":[
        "business"
    ],
    "wof:name":"Sapphire Office Services",
    "wof:placetype":"venue"
},
  "geometry": {"coordinates":[150.079544067,-35.911151886],"type":"Point"}
}