{
  "type": "Feature",
  "properties": {
    "addr:full":"11 Greenup St Texas QLD 4385",
    "addr:housenumber":"11",
    "addr:postcode":"qld 4385",
    "addr:street":"Greenup St",
    "iso:country":"AU",
    "sg:address":"11 Greenup St",
    "sg:city":"Texas",
    "sg:classifiers":[
        {
            "category":"Food & Beverages",
            "subcategory":"Groceries & Convenience Stores",
            "type":"Retail Goods"
        }
    ],
    "sg:phone":"+61 7 4653 1238",
    "sg:postcode":"4385",
    "sg:province":"QLD",
    "wof:name":"Fords Store",
    "wof:placetype":"venue"
},
  "geometry": {"coordinates":[151.16383400000001,-28.848537],"type":"Point"}
}