{
  "type": "Feature",
  "properties": {
    "addr:full":"Fact 2 130 Maddox Rd Williamstown VIC 3016",
    "addr:housenumber":"2",
    "addr:postcode":"130;3016",
    "addr:street":"Fact;Maddox Rd",
    "iso:country":"AU",
    "sg:address":"Fact 2 130 Maddox Rd",
    "sg:city":"Williamstown",
    "sg:classifiers":[
        {
            "category":"Building & Trades",
            "subcategory":"Construction",
            "type":"Services"
        }
    ],
    "sg:phone":"+61 3 9397 6077",
    "sg:postcode":"3016",
    "sg:province":"VIC",
    "sg:tags":[
        "fencing",
        "contractor"
    ],
    "wof:name":"Hobsons Bay Pickets",
    "wof:placetype":"venue"
},
  "geometry": {"coordinates":[144.866622925,-37.8580551147],"type":"Point"}
}