{
  "type": "Feature",
  "properties": {
    "addr:full":"54 Wade St Dungog NSW 2420",
    "addr:housenumber":"54",
    "addr:postcode":"2420",
    "addr:street":"Wade St",
    "iso:country":"AU",
    "sg:address":"54 Wade St",
    "sg:city":"Dungog",
    "sg:classifiers":[
        {
            "category":"Building & Trades",
            "subcategory":"Construction",
            "type":"Services"
        }
    ],
    "sg:phone":"+61 427 753 565",
    "sg:postcode":"2420",
    "sg:province":"NSW",
    "sg:tags":[
        "contractor"
    ],
    "wof:name":"Stewart Mark Building Services",
    "wof:placetype":"venue"
},
  "geometry": {"coordinates":[151.75796500000001,-32.400139],"type":"Point"}
}