{
  "type": "Feature",
  "properties": {
    "addr:full":"213 Wappa Falls Rd Yandina QLD 4561",
    "addr:housenumber":"213",
    "addr:postcode":"4561",
    "addr:street":"Wappa Falls Rd",
    "iso:country":"AU",
    "sg:address":"213 Wappa Falls Rd",
    "sg:city":"Yandina",
    "sg:classifiers":[
        {
            "category":"Wholesale",
            "subcategory":"Farm Supplies",
            "type":"Manufacturing & Wholesale Goods"
        }
    ],
    "sg:phone":"+61 7 5446 8227",
    "sg:postcode":"4561",
    "sg:province":"QLD",
    "sg:tags":[
        "material",
        "filtering"
    ],
    "wof:name":"4M Filters & Maintenance Systems",
    "wof:placetype":"venue"
},
  "geometry": {"coordinates":[152.95130920400001,-26.5702381134],"type":"Point"}
}