{
  "type": "Feature",
  "properties": {
    "addr:full":"Montgomery Ave Mt Waverley VIC 3149",
    "addr:postcode":"3149",
    "addr:street":"Montgomery Ave Mt",
    "iso:country":"AU",
    "sg:address":"Montgomery Ave",
    "sg:city":"Mt Waverley",
    "sg:classifiers":[
        {
            "category":"Arena",
            "subcategory":"Sports Club",
            "type":"Entertainment"
        }
    ],
    "sg:phone":"+61 408 881 186",
    "sg:postcode":"3149",
    "sg:province":"VIC",
    "sg:tags":[
        "defence",
        "supply",
        "self",
        "instruction",
        "martial art"
    ],
    "wof:name":"Chinkon - Kishin Aikido",
    "wof:placetype":"venue"
},
  "geometry": {"coordinates":[145.14166259800001,-37.8787879944],"type":"Point"}
}