{
  "type": "Feature",
  "properties": {
    "addr:full":"1117 Raglan Pde Warrnambool VIC 3280",
    "addr:housenumber":"1117",
    "addr:postcode":"3280",
    "addr:street":"Raglan Pde",
    "iso:country":"AU",
    "sg:address":"1117 Raglan Pde",
    "sg:city":"Warrnambool",
    "sg:classifiers":[
        {
            "category":"Autos & Motor Vehicles",
            "subcategory":"Boat Sales",
            "type":"Retail Goods"
        }
    ],
    "sg:phone":"+61 3 5561 4354",
    "sg:postcode":"3280",
    "sg:province":"VIC",
    "sg:tags":[
        "equipment",
        "yacht"
    ],
    "wof:name":"Russell Cairns Marine & 4X4",
    "wof:placetype":"venue"
},
  "geometry": {"coordinates":[142.46116638199999,-38.3656082153],"type":"Point"}
}