{
  "type": "Feature",
  "properties": {
    "iso:country":"AU",
    "sg:address":"2/ 567 Kingsway",
    "sg:city":"Miranda",
    "sg:classifiers":[
        {
            "category":"Personal",
            "type":"Services"
        }
    ],
    "sg:phone":"+61 2 9525 8402",
    "sg:postcode":"2228",
    "sg:province":"NSW",
    "sg:tags":[
        "dressmaker"
    ],
    "wof:name":"Chloe's Bridal Boutique",
    "wof:placetype":"venue"
},
  "geometry": {"coordinates":[151.10264587399999,-34.034034729],"type":"Point"}
}