{
  "type": "Feature",
  "properties": {
    "addr:full":"Shop 7 East Mall Cmplx Armidale NSW 2350",
    "addr:housenumber":"shop 7",
    "addr:postcode":"2350",
    "addr:street":"East Mall Cmplx",
    "iso:country":"AU",
    "sg:address":"Shop 7",
    "sg:city":"East Mall Cmplx Armidale",
    "sg:classifiers":[
        {
            "category":"Shopping",
            "subcategory":"Computers & Home Electronics",
            "type":"Retail Goods"
        }
    ],
    "sg:phone":"+61 2 6772 0600",
    "sg:postcode":"2350",
    "sg:province":"NSW",
    "sg:tags":[
        "small",
        "equipment",
        "business"
    ],
    "wof:name":"McDonagh Computer Services",
    "wof:placetype":"venue"
},
  "geometry": {"coordinates":[151.74203491200001,-30.6037902832],"type":"Point"}
}