{
  "type": "Feature",
  "properties": {
    "addr:full":"5 Davies Drv Shepparton East VIC 3631",
    "addr:housenumber":"5",
    "addr:postcode":"3631",
    "addr:street":"Davies Drv",
    "iso:country":"AU",
    "sg:address":"5 Davies Drv",
    "sg:city":"Shepparton East",
    "sg:classifiers":[
        {
            "category":"Health Services",
            "subcategory":"Health Practitioner",
            "type":"Services"
        }
    ],
    "sg:phone":"+61 3 5829 2399",
    "sg:postcode":"3631",
    "sg:province":"VIC",
    "sg:tags":[
        "acupuncture"
    ],
    "wof:name":"Chinese Medicine Clinic",
    "wof:placetype":"venue"
},
  "geometry": {"coordinates":[145.44108581500001,-36.3894233704],"type":"Point"}
}