{
  "type": "Feature",
  "properties": {
    "iso:country":"AU",
    "sg:address":"50 Hamilton Rd",
    "sg:city":"Horsham",
    "sg:classifiers":[
        {
            "category":"Professional",
            "type":"Services"
        }
    ],
    "sg:phone":"+61 407 553 804",
    "sg:postcode":"3400",
    "sg:province":"VIC",
    "sg:tags":[
        "buyer",
        "merchant",
        "wool"
    ],
    "wof:name":"South West Wools",
    "wof:placetype":"venue"
},
  "geometry": {"coordinates":[142.20347595199999,-36.7179336548],"type":"Point"}
}