{
  "type": "Feature",
  "properties": {
    "addr:full":"54 Victoria St Dubbo NSW 2830",
    "addr:housenumber":"54",
    "addr:postcode":"2830",
    "addr:street":"Victoria St",
    "iso:country":"AU",
    "sg:address":"54 Victoria St",
    "sg:city":"Dubbo",
    "sg:classifiers":[
        {
            "category":"Home & Garden",
            "subcategory":"Garden Supply",
            "type":"Retail Goods"
        }
    ],
    "sg:phone":"+61 2 6882 7728",
    "sg:postcode":"2830",
    "sg:province":"NSW",
    "sg:tags":[
        "nursery"
    ],
    "wof:name":"The Olive Bay Cafe & Nursery",
    "wof:placetype":"venue"
},
  "geometry": {"coordinates":[148.59625244099999,-32.2509803772],"type":"Point"}
}