{
  "type": "Feature",
  "properties": {
    "addr:full":"16 Meager St Deer Park VIC 3023",
    "addr:housenumber":"16",
    "addr:postcode":"3023",
    "addr:street":"Meager St",
    "iso:country":"AU",
    "sg:address":"16 Meager St",
    "sg:city":"Deer Park",
    "sg:classifiers":[
        {
            "category":"Manufacturing",
            "subcategory":"Tools & Machinery",
            "type":"Manufacturing & Wholesale Goods"
        }
    ],
    "sg:phone":"+61 3 9363 4926",
    "sg:postcode":"3023",
    "sg:province":"VIC",
    "sg:tags":[
        "machine",
        "industrial",
        "sewing"
    ],
    "wof:name":"D.A.L. Contract Engineering Pty Ltd",
    "wof:placetype":"venue"
},
  "geometry": {"coordinates":[144.767807,-37.771397],"type":"Point"}
}