{
  "type": "Feature",
  "properties": {
    "addr:full":"47 South St Kempsey NSW 2440",
    "addr:housenumber":"47",
    "addr:postcode":"2440",
    "addr:street":"South St",
    "iso:country":"AU",
    "sg:address":"47 South St",
    "sg:city":"Kempsey",
    "sg:classifiers":[
        {
            "category":"Home & Garden",
            "subcategory":"Building Materials",
            "type":"Retail Goods"
        }
    ],
    "sg:phone":"+61 2 6562 2088",
    "sg:postcode":"2440",
    "sg:province":"NSW",
    "sg:tags":[
        "supply"
    ],
    "wof:name":"Point Plumbing Warehouse",
    "wof:placetype":"venue"
},
  "geometry": {"coordinates":[152.825806,-31.100039],"type":"Point"}
}