{
  "type": "Feature",
  "properties": {
    "addr:full":"8 Ada St Canley Vale NSW 2166",
    "addr:housenumber":"8",
    "addr:postcode":"2166",
    "addr:street":"Ada St",
    "iso:country":"AU",
    "sg:address":"8 Ada St",
    "sg:city":"Canley Vale",
    "sg:classifiers":[
        {
            "category":"Banks & Credit Unions",
            "subcategory":"Financial Services",
            "type":"Services"
        }
    ],
    "sg:phone":"+61 425 362 211",
    "sg:postcode":"2166",
    "sg:province":"NSW",
    "sg:tags":[
        "planning"
    ],
    "wof:name":"D2D Group Financial Education",
    "wof:placetype":"venue"
},
  "geometry": {"coordinates":[150.95376586899999,-33.8835830688],"type":"Point"}
}