{
  "type": "Feature",
  "properties": {
    "addr:full":"21 Lock Ave Werribee VIC 3030",
    "addr:housenumber":"21",
    "addr:postcode":"3030",
    "addr:street":"Lock Ave",
    "iso:country":"AU",
    "sg:address":"21 Lock Ave",
    "sg:city":"Werribee",
    "sg:classifiers":[
        {
            "category":"Manufacturing",
            "subcategory":"Wood Products",
            "type":"Manufacturing & Wholesale Goods"
        }
    ],
    "sg:phone":"+61 3 9731 0255",
    "sg:postcode":"3030",
    "sg:province":"VIC",
    "sg:tags":[
        "pallet",
        "platform"
    ],
    "wof:name":"All Timber Packaging",
    "wof:placetype":"venue"
},
  "geometry": {"coordinates":[144.66154499999999,-37.910862],"type":"Point"}
}