{
  "type": "Feature",
  "properties": {
    "addr:full":"1 George St Sydney NSW 2000",
    "addr:housenumber":"1",
    "addr:postcode":"2000",
    "addr:street":"George St",
    "iso:country":"AU",
    "sg:address":"1 George St",
    "sg:city":"Sydney",
    "sg:classifiers":[
        {
            "category":"Shopping",
            "subcategory":"Computers & Home Electronics",
            "type":"Retail Goods"
        }
    ],
    "sg:phone":"+61 2 9966 7544",
    "sg:postcode":"2000",
    "sg:province":"NSW",
    "sg:tags":[
        "hardware",
        "equipment"
    ],
    "wof:name":"Dial a PC",
    "wof:placetype":"venue"
},
  "geometry": {"coordinates":[151.20820617699999,-33.8568916321],"type":"Point"}
}