{
  "type": "Feature",
  "properties": {
    "addr:full":"Unit 13/ 27 Childs Rd Chipping Norton NSW 2170",
    "addr:housenumber":"/ 27",
    "addr:postcode":"2170",
    "addr:street":"Childs Rd",
    "iso:country":"AU",
    "sg:address":"Unit 13/ 27 Childs Rd",
    "sg:city":"Chipping Norton",
    "sg:classifiers":[
        {
            "category":"Sports & Exercise",
            "subcategory":"Ski Resort",
            "type":"Entertainment"
        }
    ],
    "sg:phone":"+61 2 9755 3334",
    "sg:postcode":"2170",
    "sg:province":"NSW",
    "sg:tags":[
        "repair",
        "lift",
        "maintenance"
    ],
    "wof:name":"P K Metal Polishing",
    "wof:placetype":"venue"
},
  "geometry": {"coordinates":[150.96217346200001,-33.9188423157],"type":"Point"}
}