{
  "type": "Feature",
  "properties": {
    "iso:country":"AU",
    "sg:address":"158 Pacific Pde",
    "sg:city":"Dee Why",
    "sg:classifiers":[
        {
            "category":"Fast Food",
            "type":"Food & Drink"
        }
    ],
    "sg:phone":"+61 2 9982 4056",
    "sg:postcode":"2099",
    "sg:province":"NSW",
    "sg:tags":[
        "away",
        "take"
    ],
    "wof:name":"Kahani Indian Restaurant",
    "wof:placetype":"venue"
},
  "geometry": {"coordinates":[151.295776367,-33.7558135986],"type":"Point"}
}