{
  "type": "Feature",
  "properties": {
    "iso:country":"AU",
    "sg:address":"1537 Pacific Hwy",
    "sg:city":"Wahroonga",
    "sg:classifiers":[
        {
            "category":"Health Services",
            "subcategory":"Optometrist",
            "type":"Services"
        }
    ],
    "sg:phone":"+61 2 9489 9901",
    "sg:postcode":"2076",
    "sg:province":"NSW",
    "wof:name":"Rodney Gary Optometrist",
    "wof:placetype":"venue"
},
  "geometry": {"coordinates":[151.11813354500001,-33.7218971252],"type":"Point"}
}