{
  "type": "Feature",
  "properties": {
    "addr:full":"36- 40 Northern Rd Heidelberg West VIC 3081",
    "addr:housenumber":"40",
    "addr:postcode":"3081",
    "addr:street":"Northern Rd",
    "iso:country":"AU",
    "sg:address":"36- 40 Northern Rd",
    "sg:city":"Heidelberg West",
    "sg:classifiers":[
        {
            "category":"Building & Trades",
            "subcategory":"Construction",
            "type":"Services"
        }
    ],
    "sg:phone":"+61 3 9455 2311",
    "sg:postcode":"3081",
    "sg:province":"VIC",
    "sg:tags":[
        "fencing",
        "contractor"
    ],
    "wof:name":"Temporary Fencing Direct Sales Pty Ltd",
    "wof:placetype":"venue"
},
  "geometry": {"coordinates":[145.047363281,-37.7293968201],"type":"Point"}
}