{
  "type": "Feature",
  "properties": {
    "addr:full":"Shp 15a/ 15 Marine Pde St Kilda VIC 3182",
    "addr:housenumber":"15a / 15",
    "addr:postcode":"3182",
    "addr:street":"Marine Pde",
    "iso:country":"AU",
    "sg:address":"Shp 15a/ 15 Marine Pde",
    "sg:city":"St Kilda",
    "sg:classifiers":[
        {
            "category":"Cafe",
            "type":"Food & Drink"
        }
    ],
    "sg:phone":"+61 3 9534 9988",
    "sg:postcode":"3182",
    "sg:province":"VIC",
    "wof:name":"Cafe Racer",
    "wof:placetype":"venue"
},
  "geometry": {"coordinates":[144.976654053,-37.8718070984],"type":"Point"}
}