{
  "type": "Feature",
  "properties": {
    "addr:full":"6 Dolphin St Randwick NSW 2031",
    "addr:housenumber":"6",
    "addr:postcode":"2031",
    "addr:street":"Dolphin St",
    "iso:country":"AU",
    "sg:address":"6 Dolphin St",
    "sg:city":"Randwick",
    "sg:classifiers":[
        {
            "category":"Real Estate",
            "subcategory":"Architect",
            "type":"Services"
        }
    ],
    "sg:phone":"+61 2 9398 4509",
    "sg:postcode":"2031",
    "sg:province":"NSW",
    "wof:name":"Cox Thomas & Carolyn Architects-Residential & Human Scale Architecture",
    "wof:placetype":"venue"
},
  "geometry": {"coordinates":[151.24482727,-33.9169845581],"type":"Point"}
}