{
  "type": "Feature",
  "properties": {
    "addr:full":"16 Pine Rd Bayswater VIC 3153",
    "addr:housenumber":"16",
    "addr:postcode":"3153",
    "addr:street":"Pine Rd",
    "iso:country":"AU",
    "sg:address":"16 Pine Rd",
    "sg:city":"Bayswater",
    "sg:classifiers":[
        {
            "category":"Home & Garden",
            "subcategory":"Hardware",
            "type":"Retail Goods"
        }
    ],
    "sg:phone":"+61 407 548 345",
    "sg:postcode":"3153",
    "sg:province":"VIC",
    "sg:tags":[
        "nut",
        "bolt"
    ],
    "wof:name":"T.M.M. Fasteners",
    "wof:placetype":"venue"
},
  "geometry": {"coordinates":[145.26640319800001,-37.8457145691],"type":"Point"}
}