{
  "type": "Feature",
  "properties": {
    "addr:full":"170- 172 Parramatta Rd Auburn NSW 2144",
    "addr:housenumber":"172",
    "addr:postcode":"2144",
    "addr:street":"Parramatta Rd",
    "iso:country":"AU",
    "sg:address":"170- 172 Parramatta Rd",
    "sg:city":"Auburn",
    "sg:classifiers":[
        {
            "category":"Shopping",
            "subcategory":"Luggage & Leather Goods",
            "type":"Retail Goods"
        }
    ],
    "sg:phone":"+61 2 9748 1867",
    "sg:postcode":"2144",
    "sg:province":"NSW",
    "wof:name":"Gypsy Leather & Suede",
    "wof:placetype":"venue"
},
  "geometry": {"coordinates":[151.03799438499999,-33.8425369263],"type":"Point"}
}