{
  "type": "Feature",
  "properties": {
    "addr:full":"4th Floor, 3-5 Bennett St East Perth WA 6004",
    "addr:housenumber":"3-5",
    "addr:postcode":"6004",
    "addr:street":"Bennett St East",
    "iso:country":"AU",
    "sg:address":"4th Floor, 3-5 Bennett St",
    "sg:city":"East Perth",
    "sg:classifiers":[
        {
            "category":"Professional",
            "subcategory":"Accounting & Tax Preparation",
            "type":"Services"
        }
    ],
    "sg:phone":"+61 8 9421 1722",
    "sg:postcode":"6004",
    "sg:province":"WA",
    "sg:tags":[
        "consultant",
        "taxation"
    ],
    "wof:name":"Thornton Partners Pty Ltd",
    "wof:placetype":"venue"
},
  "geometry": {"coordinates":[115.87068176299999,-31.9607467651],"type":"Point"}
}