{
  "type": "Feature",
  "properties": {
    "iso:country":"AU",
    "sg:address":"1349 Burke Rd",
    "sg:city":"Kew",
    "sg:classifiers":[
        {
            "category":"Health Services",
            "subcategory":"Dentist",
            "type":"Services"
        }
    ],
    "sg:phone":"+61 3 9817 7123",
    "sg:postcode":"3101",
    "sg:province":"VIC",
    "wof:name":"Emery Luke Dr",
    "wof:placetype":"venue"
},
  "geometry": {"coordinates":[145.06228637699999,-37.8012123108],"type":"Point"}
}