{
  "type": "Feature",
  "properties": {
    "iso:country":"AU",
    "sg:address":"289 West St",
    "sg:city":"Umina",
    "sg:classifiers":[
        {
            "category":"Banks & Credit Unions",
            "subcategory":"Bank",
            "type":"Services"
        }
    ],
    "sg:phone":"+61 2 4344 3211",
    "sg:postcode":"2257",
    "sg:province":"NSW",
    "wof:name":"St.George Bank Limited",
    "wof:placetype":"venue"
},
  "geometry": {"coordinates":[151.319625855,-33.5213813782],"type":"Point"}
}