{
  "type": "Feature",
  "properties": {
    "addr:full":"Paradigm Business Park, 2 Newman Rd Geebung QLD 4034",
    "addr:housenumber":"2",
    "addr:postcode":"4034",
    "addr:street":"Newman Rd",
    "iso:country":"AU",
    "sg:address":"Paradigm Business Park, 2 Newman Rd",
    "sg:city":"Geebung",
    "sg:classifiers":[
        {
            "category":"Banks & Credit Unions",
            "subcategory":"Bank",
            "type":"Services"
        }
    ],
    "sg:phone":"+61 1800 804 665",
    "sg:postcode":"4034",
    "sg:province":"QLD",
    "sg:tags":[
        "equipment",
        "sale",
        "point"
    ],
    "wof:name":"Trion Industries (Aust) Pty Ltd",
    "wof:placetype":"venue"
},
  "geometry": {"coordinates":[153.047867,-27.369242],"type":"Point"}
}