{
  "type": "Feature",
  "properties": {
    "addr:full":"Factory 5/ 4 Collins Rd Melton VIC 3337",
    "addr:housenumber":"/ 4",
    "addr:postcode":"3337",
    "addr:street":"Collins Rd",
    "iso:country":"AU",
    "sg:address":"Factory 5/ 4 Collins Rd",
    "sg:city":"Melton",
    "sg:classifiers":[
        {
            "category":"Professional",
            "subcategory":"Engineering",
            "type":"Services"
        }
    ],
    "sg:phone":"+61 408 367 799",
    "sg:postcode":"3337",
    "sg:province":"VIC",
    "sg:tags":[
        "diesel",
        "engineer"
    ],
    "wof:name":"Skec J I",
    "wof:placetype":"venue"
},
  "geometry": {"coordinates":[144.60142500000001,-37.690113],"type":"Point"}
}