{
  "type": "Feature",
  "properties": {
    "iso:country":"AU",
    "sg:address":"Unit 5, 31 Enterprise St",
    "sg:city":"Kunda Park",
    "sg:classifiers":[
        {
            "category":"Professional",
            "type":"Services"
        }
    ],
    "sg:phone":"+61 7 5445 8733",
    "sg:postcode":"4556",
    "sg:province":"QLD",
    "sg:tags":[
        "spray",
        "painting"
    ],
    "wof:name":"KP Spray",
    "wof:placetype":"venue"
},
  "geometry": {"coordinates":[153.030197144,-26.666437149],"type":"Point"}
}