{
  "type": "Feature",
  "properties": {
    "addr:full":"300 Great Eastern Hwy Midland WA 6056",
    "addr:housenumber":"300",
    "addr:postcode":"6056",
    "addr:street":"Great Eastern Hwy",
    "iso:country":"AU",
    "sg:address":"300 Great Eastern Hwy",
    "sg:city":"Midland",
    "sg:classifiers":[
        {
            "category":"Shopping",
            "subcategory":"Clothing, Apparel, & Fashions",
            "type":"Retail Goods"
        }
    ],
    "sg:phone":"+61 8 9250 8877",
    "sg:postcode":"6056",
    "sg:province":"WA",
    "sg:tags":[
        "lady",
        "wear"
    ],
    "wof:name":"20 Plus",
    "wof:placetype":"venue"
},
  "geometry": {"coordinates":[116.012306213,-31.8917961121],"type":"Point"}
}