{
  "type": "Feature",
  "properties": {
    "addr:full":"Suite 3/ 75 Ryedale Rd West Ryde NSW 2114",
    "addr:housenumber":"75",
    "addr:postcode":"2114",
    "addr:street":"Ryedale Rd",
    "iso:country":"AU",
    "sg:address":"Suite 3/ 75 Ryedale Rd",
    "sg:city":"West Ryde",
    "sg:classifiers":[
        {
            "category":"Real Estate",
            "subcategory":"Surveying",
            "type":"Services"
        }
    ],
    "sg:phone":"+61 2 9808 6854",
    "sg:postcode":"2114",
    "sg:province":"NSW",
    "sg:tags":[
        "surveyor",
        "land"
    ],
    "wof:name":"ATS Land & Engineering Surveyors Pty Ltd",
    "wof:placetype":"venue"
},
  "geometry": {"coordinates":[151.09141540499999,-33.8063392639],"type":"Point"}
}