{
  "type": "Feature",
  "properties": {
    "addr:full":"12 Bellana Pl Queens Park WA 6107",
    "addr:housenumber":"12",
    "addr:postcode":"6107",
    "addr:street":"Bellana Pl Queens",
    "iso:country":"AU",
    "sg:address":"12 Bellana Pl",
    "sg:city":"Queens Park",
    "sg:classifiers":[
        {
            "category":"Real Estate",
            "subcategory":"Real Estate Agent",
            "type":"Services"
        }
    ],
    "sg:phone":"+61 413 417 684",
    "sg:postcode":"6107",
    "sg:province":"WA",
    "wof:name":"Investment & Residential Sales & Service (WA)",
    "wof:placetype":"venue"
},
  "geometry": {"coordinates":[115.991790772,-32.0339851379],"type":"Point"}
}