{
  "type": "Feature",
  "properties": {
    "iso:country":"AU",
    "sg:address":"52 Dawson Rd",
    "sg:city":"Gladstone",
    "sg:classifiers":[
        {
            "category":"Fast Food",
            "type":"Food & Drink"
        }
    ],
    "sg:phone":"+61 7 4972 1131",
    "sg:postcode":"4680",
    "sg:province":"QLD",
    "sg:tags":[
        "away",
        "take"
    ],
    "wof:name":"KFC",
    "wof:placetype":"venue"
},
  "geometry": {"coordinates":[151.24859619099999,-23.8564147949],"type":"Point"}
}