{
  "type": "Feature",
  "properties": {
    "addr:full":"49 Erin St Richmond VIC 3121",
    "addr:housenumber":"49",
    "addr:postcode":"3121",
    "addr:street":"Erin St",
    "iso:country":"AU",
    "sg:address":"49 Erin St",
    "sg:city":"Richmond",
    "sg:classifiers":[
        {
            "category":"Health Services",
            "subcategory":"Health Practitioner",
            "type":"Services"
        }
    ],
    "sg:phone":"+61 3 9427 0032",
    "sg:postcode":"3121",
    "sg:province":"VIC",
    "sg:tags":[
        "psychotherapist"
    ],
    "wof:name":"Francesca Levine",
    "wof:placetype":"venue"
},
  "geometry": {"coordinates":[144.99305725100001,-37.8164787292],"type":"Point"}
}