{
  "type": "Feature",
  "properties": {
    "addr:full":"Farrington Shopng Cntr Cnr Farrington & Findlay Rds Leeming WA 6149",
    "addr:postcode":"6149",
    "addr:street":"Cnr",
    "iso:country":"AU",
    "sg:address":"Farrington Shopng Cntr Cnr Farrington & Findlay Rds",
    "sg:city":"Leeming",
    "sg:classifiers":[
        {
            "category":"Fast Food",
            "type":"Food & Drink"
        }
    ],
    "sg:phone":"+61 8 9310 3255",
    "sg:postcode":"6149",
    "sg:province":"WA",
    "sg:tags":[
        "away",
        "take"
    ],
    "wof:name":"Chicken Treat",
    "wof:placetype":"venue"
},
  "geometry": {"coordinates":[115.85984000000001,-32.079472],"type":"Point"}
}