{
  "type": "Feature",
  "properties": {
    "iso:country":"AU",
    "sg:address":"2/251- 253 St Georges St",
    "sg:city":"Northcote",
    "sg:classifiers":[
        {
            "category":"Personal",
            "subcategory":"Massage",
            "type":"Services"
        }
    ],
    "sg:phone":"+61 416 207 077",
    "sg:postcode":"3070",
    "sg:province":"VIC",
    "sg:tags":[
        "therapy"
    ],
    "wof:name":"Loose as a Goose Massage Therapy",
    "wof:placetype":"venue"
},
  "geometry": {"coordinates":[144.991821,-37.764355],"type":"Point"}
}