{
  "type": "Feature",
  "properties": {
    "iso:country":"AU",
    "sg:address":"Cnr Lake and Central Rds",
    "sg:city":"Port Macquarie",
    "sg:classifiers":[
        {
            "category":"Home & Garden",
            "subcategory":"Carpets & Floor Coverings",
            "type":"Retail Goods"
        }
    ],
    "sg:phone":"+61 2 6581 0100",
    "sg:postcode":"2444",
    "sg:province":"NSW",
    "sg:tags":[
        "tile",
        "wall"
    ],
    "sg:website":"http://www.colortile.com.au",
    "wof:name":"ColorTile Port Macquarie",
    "wof:placetype":"venue"
},
  "geometry": {"coordinates":[152.911469,-31.434656],"type":"Point"}
}