{
  "type": "Feature",
  "properties": {
    "iso:country":"AU",
    "sg:address":"Shop 71 Morayfield Shopping Centre",
    "sg:city":"Morayfield",
    "sg:classifiers":[
        {
            "category":"Shopping",
            "subcategory":"Clothing, Apparel, & Fashions",
            "type":"Retail Goods"
        }
    ],
    "sg:phone":"+61 7 5499 3799",
    "sg:postcode":"4506",
    "sg:province":"QLD",
    "sg:tags":[
        "lady",
        "wear"
    ],
    "wof:name":"Miller's Fashion Club",
    "wof:placetype":"venue"
},
  "geometry": {"coordinates":[152.94973754899999,-27.1099243164],"type":"Point"}
}