{
  "type": "Feature",
  "properties": {
    "addr:full":"144 Main St Bairnsdale VIC 3875",
    "addr:housenumber":"144",
    "addr:postcode":"3875",
    "addr:street":"Main St",
    "iso:country":"AU",
    "sg:address":"144 Main St",
    "sg:city":"Bairnsdale",
    "sg:classifiers":[
        {
            "category":"Deli",
            "type":"Food & Drink"
        }
    ],
    "sg:phone":"+61 3 5152 1544",
    "sg:postcode":"3875",
    "sg:province":"VIC",
    "sg:tags":[
        "delicatessen"
    ],
    "wof:name":"Bairnsdale Gourmet Deli",
    "wof:placetype":"venue"
},
  "geometry": {"coordinates":[147.827224731,-37.7086296082],"type":"Point"}
}