{
  "type": "Feature",
  "properties": {
    "addr:full":"359 Main South Rd Morphett Vale SA 5162",
    "addr:housenumber":"359",
    "addr:postcode":"5162",
    "addr:street":"Main South Rd",
    "iso:country":"AU",
    "sg:address":"359 Main South Rd",
    "sg:city":"Morphett Vale",
    "sg:classifiers":[
        {
            "category":"Industrial Area",
            "type":"Public Place"
        }
    ],
    "sg:phone":"+61 1300 135 291",
    "sg:postcode":"5162",
    "sg:province":"SA",
    "sg:tags":[
        "rural",
        "shed"
    ],
    "wof:name":"Shed King The",
    "wof:placetype":"venue"
},
  "geometry": {"coordinates":[138.52537536599999,-35.1068611145],"type":"Point"}
}