{
  "type": "Feature",
  "properties": {
    "addr:full":"PO Box 356 Bega NSW 2550",
    "addr:postcode":"2550",
    "iso:country":"AU",
    "sg:address":"PO Box 356",
    "sg:city":"Bega",
    "sg:phone":"+61 1800 241 246",
    "sg:postcode":"2550",
    "sg:province":"NSW",
    "wof:name":"Bega Concrete Tanks",
    "wof:placetype":"venue"
},
  "geometry": {"coordinates":[149.84138488799999,-36.6739883423],"type":"Point"}
}