{
  "type": "Feature",
  "properties": {
    "addr:full":"Unit 2/ 9 Travers St Coconut Grove NT 0810",
    "addr:housenumber":"9",
    "addr:postcode":"0810",
    "addr:street":"Travers St",
    "iso:country":"AU",
    "sg:address":"Unit 2/ 9 Travers St",
    "sg:city":"Coconut Grove",
    "sg:classifiers":[
        {
            "category":"Shopping",
            "subcategory":"Antiques",
            "type":"Retail Goods"
        }
    ],
    "sg:phone":"+61 8 8948 1666",
    "sg:postcode":"0810",
    "sg:province":"NT",
    "sg:tags":[
        "restoration",
        "reproduction"
    ],
    "wof:name":"Unique Antiques Furniture & Gifts",
    "wof:placetype":"venue"
},
  "geometry": {"coordinates":[130.853683472,-12.4009752274],"type":"Point"}
}