{
  "type": "Feature",
  "properties": {
    "addr:full":"Crispe St Deniliquin NSW 2710",
    "addr:postcode":"2710",
    "addr:street":"Crispe St",
    "iso:country":"AU",
    "sg:address":"Crispe St",
    "sg:city":"Deniliquin",
    "sg:classifiers":[
        {
            "category":"Autos & Motor Vehicles",
            "subcategory":"Fuel & Gas Station",
            "type":"Retail Goods"
        }
    ],
    "sg:phone":"+61 3 5881 1932",
    "sg:postcode":"2710",
    "sg:province":"NSW",
    "wof:name":"Shell Australia Limited",
    "wof:placetype":"venue"
},
  "geometry": {"coordinates":[144.965133667,-35.5377998352],"type":"Point"}
}