{
  "type": "Feature",
  "properties": {
    "addr:full":"13 Phillips Kangaroo Flat VIC 3555",
    "addr:housenumber":"13",
    "addr:postcode":"3555",
    "addr:street":"Phillips",
    "iso:country":"AU",
    "sg:address":"13 Phillips",
    "sg:city":"Kangaroo Flat",
    "sg:classifiers":[
        {
            "category":"Retail",
            "subcategory":"Auto Repair",
            "type":"Services"
        }
    ],
    "sg:phone":"+61 3 5447 0009",
    "sg:postcode":"3555",
    "sg:province":"VIC",
    "sg:tags":[
        "wheel",
        "balancing",
        "alignment"
    ],
    "wof:name":"Pedders Suspension",
    "wof:placetype":"venue"
},
  "geometry": {"coordinates":[144.24418640100001,-36.7957687378],"type":"Point"}
}