{
  "type": "Feature",
  "properties": {
    "iso:country":"AU",
    "sg:address":"27 Giles Rd",
    "sg:city":"Willunga",
    "sg:classifiers":[
        {
            "category":"Real Estate",
            "subcategory":"Real Estate Services",
            "type":"Services"
        }
    ],
    "sg:phone":"+61 8 8556 2417",
    "sg:postcode":"5172",
    "sg:province":"SA",
    "sg:tags":[
        "valuer"
    ],
    "wof:name":"David Wright",
    "wof:placetype":"venue"
},
  "geometry": {"coordinates":[138.54815673799999,-35.2751312256],"type":"Point"}
}