{
  "type": "Feature",
  "properties": {
    "addr:full":"Suite 1a 60-64 Reservoir St Surry Hills NSW 2010",
    "addr:housenumber":"60-64",
    "addr:postcode":"2010",
    "addr:street":"Reservoir St",
    "iso:country":"AU",
    "sg:address":"Suite 1a 60-64 Reservoir St",
    "sg:city":"Surry Hills",
    "sg:classifiers":[
        {
            "category":"Professional",
            "subcategory":"Computer Services",
            "type":"Services"
        }
    ],
    "sg:phone":"+61 2 9212 2160",
    "sg:postcode":"2010",
    "sg:province":"NSW",
    "sg:tags":[
        "on-line",
        "provider"
    ],
    "wof:name":"Reading Room Sydney",
    "wof:placetype":"venue"
},
  "geometry": {"coordinates":[151.20965576200001,-33.881111145],"type":"Point"}
}