{
  "type": "Feature",
  "properties": {
    "addr:full":"3 Birdwood Ave Umina NSW 2257",
    "addr:housenumber":"3",
    "addr:postcode":"2257",
    "addr:street":"Birdwood Ave",
    "iso:country":"AU",
    "sg:address":"3 Birdwood Ave",
    "sg:city":"Umina",
    "sg:classifiers":[
        {
            "category":"Manufacturing",
            "subcategory":"Glass & Minerals",
            "type":"Manufacturing & Wholesale Goods"
        }
    ],
    "sg:phone":"+61 2 4342 5052",
    "sg:postcode":"2257",
    "sg:province":"NSW",
    "sg:tags":[
        "repair",
        "fibreglass",
        "product"
    ],
    "wof:name":"Grant Peterson",
    "wof:placetype":"venue"
},
  "geometry": {"coordinates":[151.31674194300001,-33.5157966614],"type":"Point"}
}