{
  "type": "Feature",
  "properties": {
    "addr:full":"Unit 17/ 7 Anela Ave Castle Hill NSW 2154",
    "addr:housenumber":"/ 7",
    "addr:postcode":"2154",
    "addr:street":"Anela Ave",
    "iso:country":"AU",
    "sg:address":"Unit 17/ 7 Anela Ave",
    "sg:city":"Castle Hill",
    "sg:classifiers":[
        {
            "category":"Education",
            "subcategory":"University",
            "type":"Public Place"
        }
    ],
    "sg:phone":"+61 2 9680 1117",
    "sg:postcode":"2154",
    "sg:province":"NSW",
    "sg:tags":[
        "college",
        "tertiary"
    ],
    "wof:name":"Northwest Community College",
    "wof:placetype":"venue"
},
  "geometry": {"coordinates":[150.97848510700001,-33.7265663147],"type":"Point"}
}