{
  "type": "Feature",
  "properties": {
    "addr:full":"202 - 204 Minchin Drv Minchinbury NSW 2770",
    "addr:housenumber":"204",
    "addr:postcode":"2770",
    "addr:street":"Minchin Drv",
    "iso:country":"AU",
    "sg:address":"202 - 204 Minchin Drv",
    "sg:city":"Minchinbury",
    "sg:classifiers":[
        {
            "category":"Social Services",
            "subcategory":"Child Care",
            "type":"Services"
        }
    ],
    "sg:phone":"+61 2 9832 1119",
    "sg:postcode":"2770",
    "sg:province":"NSW",
    "wof:name":"White Bunny Pre-School & Childcare Centre",
    "wof:placetype":"venue"
},
  "geometry": {"coordinates":[150.83412170400001,-33.787563324],"type":"Point"}
}