{
  "type": "Feature",
  "properties": {
    "addr:full":"152 Byrnes St Mareeba QLD 4880",
    "addr:housenumber":"152",
    "addr:postcode":"4880",
    "addr:street":"Byrnes St",
    "iso:country":"AU",
    "sg:address":"152 Byrnes St",
    "sg:city":"Mareeba",
    "sg:classifiers":[
        {
            "category":"Personal",
            "subcategory":"Piercing",
            "type":"Services"
        }
    ],
    "sg:phone":"+61 7 4092 4163",
    "sg:postcode":"4880",
    "sg:province":"QLD",
    "sg:tags":[
        "body",
        "ear"
    ],
    "wof:name":"Blue Lagoon Swimwear & Beauty",
    "wof:placetype":"venue"
},
  "geometry": {"coordinates":[145.42027282699999,-16.9870605469],"type":"Point"}
}