{
  "type": "Feature",
  "properties": {
    "addr:full":"Bagshaw St Harcourt VIC 3453",
    "addr:postcode":"3453",
    "addr:street":"Bagshaw St",
    "iso:country":"AU",
    "sg:address":"Bagshaw St",
    "sg:city":"Harcourt",
    "sg:classifiers":[
        {
            "category":"Professional",
            "subcategory":"Engineering",
            "type":"Services"
        }
    ],
    "sg:phone":"+61 3 5474 2321",
    "sg:postcode":"3453",
    "sg:province":"VIC",
    "sg:tags":[
        "manufacturing",
        "engineer"
    ],
    "wof:name":"Diecrest Engineering",
    "wof:placetype":"venue"
},
  "geometry": {"coordinates":[144.26176452600001,-37.0009040833],"type":"Point"}
}