{
  "type": "Feature",
  "properties": {
    "iso:country":"AU",
    "sg:address":"38 Blossom Drv",
    "sg:city":"Doveton",
    "sg:classifiers":[
        {
            "category":"Professional",
            "subcategory":"Detective & Security Services",
            "type":"Services"
        }
    ],
    "sg:phone":"+61 3 9794 9194",
    "sg:postcode":"3177",
    "sg:province":"VIC",
    "sg:tags":[
        "equipment",
        "window",
        "doors"
    ],
    "wof:name":"Insul Quote Security Doors & Fly Screens",
    "wof:placetype":"venue"
},
  "geometry": {"coordinates":[145.231765747,-37.9906425476],"type":"Point"}
}