{
  "type": "Feature",
  "properties": {
    "addr:full":"16 Pike St Oakbank SA 5243",
    "addr:housenumber":"16",
    "addr:postcode":"5243",
    "addr:street":"Pike St",
    "iso:country":"AU",
    "sg:address":"16 Pike St",
    "sg:city":"Oakbank",
    "sg:classifiers":[
        {
            "category":"Building & Trades",
            "subcategory":"Landscaping Services",
            "type":"Services"
        }
    ],
    "sg:phone":"+61 8 8339 8333",
    "sg:postcode":"5243",
    "sg:province":"SA",
    "sg:tags":[
        "inspection"
    ],
    "wof:name":"Blue Chip Building Consultants",
    "wof:placetype":"venue"
},
  "geometry": {"coordinates":[138.84349060100001,-34.9857177734],"type":"Point"}
}