{
  "type": "Feature",
  "properties": {
    "addr:full":"86 Granite Drv Langwarrin VIC 3910",
    "addr:housenumber":"86",
    "addr:postcode":"3910",
    "addr:street":"Granite Drv",
    "iso:country":"AU",
    "sg:address":"86 Granite Drv",
    "sg:city":"Langwarrin",
    "sg:classifiers":[
        {
            "category":"Shopping",
            "subcategory":"Stationery & Office Supplies",
            "type":"Retail Goods"
        }
    ],
    "sg:phone":"+61 3 9775 6433",
    "sg:postcode":"3910",
    "sg:province":"VIC",
    "sg:tags":[
        "packaging",
        "material"
    ],
    "wof:name":"Bantec International Pty Ltd",
    "wof:placetype":"venue"
},
  "geometry": {"coordinates":[145.211227417,-38.1387863159],"type":"Point"}
}