{
  "type": "Feature",
  "properties": {
    "addr:full":"20 Brisbane Rd Mooloolaba QLD 4557",
    "addr:housenumber":"20",
    "addr:postcode":"4557",
    "addr:street":"Brisbane Rd",
    "iso:country":"AU",
    "sg:address":"20 Brisbane Rd",
    "sg:city":"Mooloolaba",
    "sg:classifiers":[
        {
            "category":"Building & Trades",
            "subcategory":"Construction",
            "type":"Services"
        }
    ],
    "sg:phone":"+61 7 5444 7877",
    "sg:postcode":"4557",
    "sg:province":"QLD",
    "sg:tags":[
        "contractor"
    ],
    "wof:name":"Engineered Aggregates Australia Pty Ltd",
    "wof:placetype":"venue"
},
  "geometry": {"coordinates":[153.11892700199999,-26.6816310883],"type":"Point"}
}