{
  "type": "Feature",
  "properties": {
    "iso:country":"AU",
    "sg:address":"724 Plenty Rd",
    "sg:city":"Reservoir East",
    "sg:classifiers":[
        {
            "category":"Health Services",
            "subcategory":"Medical Lab",
            "type":"Services"
        }
    ],
    "sg:phone":"+61 3 9471 0933",
    "sg:postcode":"3073",
    "sg:province":"VIC",
    "sg:tags":[
        "laboratory",
        "dental"
    ],
    "wof:name":"Snelling W J & A J",
    "wof:placetype":"venue"
},
  "geometry": {"coordinates":[145.01475524899999,-37.7309303284],"type":"Point"}
}