{
  "type": "Feature",
  "properties": {
    "addr:full":"Belgravia Rd Molong NSW 2866",
    "addr:postcode":"2866",
    "addr:street":"Belgravia Rd",
    "iso:country":"AU",
    "sg:address":"Belgravia Rd",
    "sg:city":"Molong",
    "sg:classifiers":[
        {
            "category":"Building & Trades",
            "subcategory":"Landscaping Services",
            "type":"Services"
        }
    ],
    "sg:phone":"+61 2 6366 8855",
    "sg:postcode":"2866",
    "sg:province":"NSW",
    "sg:tags":[
        "fertilizer",
        "spreading",
        "insecticide"
    ],
    "wof:name":"Centrespread Pty Ltd Ground Spreading",
    "wof:placetype":"venue"
},
  "geometry": {"coordinates":[148.900452,-33.081818],"type":"Point"}
}