{
  "type": "Feature",
  "properties": {
    "addr:full":"32 Alice St Wellington Point QLD 4160",
    "addr:housenumber":"32",
    "addr:postcode":"4160",
    "addr:street":"Alice St",
    "iso:country":"AU",
    "sg:address":"32 Alice St",
    "sg:city":"Wellington Point",
    "sg:classifiers":[
        {
            "category":"Government",
            "subcategory":"Court House",
            "type":"Public Place"
        }
    ],
    "sg:phone":"+61 7 3207 5532",
    "sg:postcode":"4160",
    "sg:province":"QLD",
    "sg:tags":[
        "personal",
        "marriage",
        "family",
        "counselling"
    ],
    "wof:name":"Restoration Ministries",
    "wof:placetype":"venue"
},
  "geometry": {"coordinates":[153.24253845199999,-27.4959506989],"type":"Point"}
}