{
  "type": "Feature",
  "properties": {
    "iso:country":"AU",
    "sg:address":"129 Bangalee St",
    "sg:city":"Lauderdale",
    "sg:classifiers":[
        {
            "category":"Building & Trades",
            "subcategory":"Construction",
            "type":"Services"
        }
    ],
    "sg:phone":"+61 3 6248 7639",
    "sg:postcode":"7021",
    "sg:province":"TAS",
    "sg:tags":[
        "contractor"
    ],
    "wof:name":"J & D Russell Pty Ltd",
    "wof:placetype":"venue"
},
  "geometry": {"coordinates":[147.49745178200001,-42.895160675],"type":"Point"}
}