{
  "type": "Feature",
  "properties": {
    "iso:country":"AU",
    "sg:address":"PO Box 408",
    "sg:city":"Henley Beach",
    "sg:classifiers":[
        {
            "category":"Building & Trades",
            "subcategory":"Construction",
            "type":"Services"
        }
    ],
    "sg:phone":"+61 408 480 982",
    "sg:postcode":"5022",
    "sg:province":"SA",
    "sg:tags":[
        "spouting",
        "guttering"
    ],
    "wof:name":"The Handyman No Job Too Small",
    "wof:placetype":"venue"
},
  "geometry": {"coordinates":[138.49435424800001,-34.9197387695],"type":"Point"}
}