{
  "type": "Feature",
  "properties": {
    "iso:country":"AU",
    "sg:address":"25A Blessington St",
    "sg:city":"St Kilda",
    "sg:classifiers":[
        {
            "category":"Cafe",
            "type":"Food & Drink"
        }
    ],
    "sg:phone":"+61 3 9593 9889",
    "sg:postcode":"3182",
    "sg:province":"VIC",
    "wof:name":"Blessington Corner Cafe & Bar",
    "wof:placetype":"venue"
},
  "geometry": {"coordinates":[144.980270386,-37.8707084656],"type":"Point"}
}