{
  "type": "Feature",
  "properties": {
    "iso:country":"AU",
    "sg:address":"Suite 6/ 621 Coronation Drv",
    "sg:city":"Toowong",
    "sg:classifiers":[
        {
            "category":"Banks & Credit Unions",
            "subcategory":"Financial Services",
            "type":"Services"
        }
    ],
    "sg:phone":"+61 7 3720 9811",
    "sg:postcode":"4066",
    "sg:province":"QLD",
    "sg:tags":[
        "planning"
    ],
    "wof:name":"Solutions Unlimited Financial Planning",
    "wof:placetype":"venue"
},
  "geometry": {"coordinates":[152.993743897,-27.4845523834],"type":"Point"}
}