{
  "type": "Feature",
  "properties": {
    "iso:country":"AU",
    "sg:address":"Office 5, F Block TAFE Campus 91 Poinsettia St",
    "sg:city":"Richlands",
    "sg:classifiers":[
        {
            "category":"Health Services",
            "subcategory":"Doctor",
            "type":"Services"
        }
    ],
    "sg:phone":"+61 7 3372 0459",
    "sg:postcode":"4077",
    "sg:province":"QLD",
    "sg:tags":[
        "occupational",
        "safety"
    ],
    "wof:name":"Molliwell Pty Ltd",
    "wof:placetype":"venue"
},
  "geometry": {"coordinates":[152.965896606,-27.5973720551],"type":"Point"}
}