{
  "type": "Feature",
  "properties": {
    "iso:country":"AU",
    "sg:address":"1- 4 Carlyle St",
    "sg:city":"Mackay",
    "sg:classifiers":[
        {
            "category":"Home & Garden",
            "subcategory":"Hardware",
            "type":"Retail Goods"
        }
    ],
    "sg:phone":"+61 7 4957 4894",
    "sg:postcode":"4740",
    "sg:province":"QLD",
    "sg:tags":[
        "plumber",
        "supply"
    ],
    "wof:name":"Reece Pty Ltd",
    "wof:placetype":"venue"
},
  "geometry": {"coordinates":[149.18987999999999,-21.140764],"type":"Point"}
}