{
  "type": "Feature",
  "properties": {
    "iso:country":"AU",
    "sg:address":"7 Ballantyne Rd",
    "sg:city":"Kewdale",
    "sg:classifiers":[
        {
            "category":"Professional",
            "subcategory":"Accounting & Tax Preparation",
            "type":"Services"
        }
    ],
    "sg:phone":"+61 8 9451 6309",
    "sg:postcode":"6105",
    "sg:province":"WA",
    "sg:tags":[
        "insulation",
        "wholesaler",
        "material",
        "mfrs"
    ],
    "wof:name":"Applied Insulation Pty Ltd",
    "wof:placetype":"venue"
},
  "geometry": {"coordinates":[115.93675994900001,-31.9854431152],"type":"Point"}
}