{
  "type": "Feature",
  "properties": {
    "addr:full":"146d Boronia Rd Boronia VIC 3155",
    "addr:housenumber":"146d",
    "addr:postcode":"3155",
    "addr:street":"Boronia Rd",
    "iso:country":"AU",
    "sg:address":"146d Boronia Rd",
    "sg:city":"Boronia",
    "sg:classifiers":[
        {
            "category":"Retail",
            "subcategory":"Repair Shop",
            "type":"Services"
        }
    ],
    "sg:phone":"+61 3 9739 8586",
    "sg:postcode":"3155",
    "sg:province":"VIC",
    "sg:tags":[
        "upholsterer"
    ],
    "wof:name":"B.N. Upholstery",
    "wof:placetype":"venue"
},
  "geometry": {"coordinates":[145.283477783,-37.8626556396],"type":"Point"}
}