{
  "type": "Feature",
  "properties": {
    "iso:country":"AU",
    "sg:address":"1 Armour Ave",
    "sg:city":"Underdale",
    "sg:classifiers":[
        {
            "category":"Building & Trades",
            "subcategory":"Construction",
            "type":"Services"
        }
    ],
    "sg:phone":"+61 8 8443 3975",
    "sg:postcode":"5032",
    "sg:province":"SA",
    "sg:tags":[
        "joinery"
    ],
    "wof:name":"South Australian Joinery Works Pty Ltd",
    "wof:placetype":"venue"
},
  "geometry": {"coordinates":[138.54864501899999,-34.91664505],"type":"Point"}
}