{
  "type": "Feature",
  "properties": {
    "iso:country":"AU",
    "sg:address":"Cnr The Grand Pde & Princess St",
    "sg:city":"Brighton-le-Sands",
    "sg:classifiers":[
        {
            "category":"Restaurant",
            "type":"Food & Drink"
        }
    ],
    "sg:phone":"+61 2 9597 7111",
    "sg:postcode":"2216",
    "sg:province":"NSW",
    "wof:name":"Brannigans Tavern",
    "wof:placetype":"venue"
},
  "geometry": {"coordinates":[151.15649400000001,-33.960484],"type":"Point"}
}