{
  "type": "Feature",
  "properties": {
    "addr:full":"7A Bay Rd Mt Martha VIC 3934",
    "addr:housenumber":"7a",
    "addr:postcode":"3934",
    "addr:street":"Bay Rd",
    "iso:country":"AU",
    "sg:address":"7A Bay Rd",
    "sg:city":"Mt Martha",
    "sg:classifiers":[
        {
            "category":"Real Estate",
            "subcategory":"Real Estate Agent",
            "type":"Services"
        }
    ],
    "sg:phone":"+61 3 5974 1544",
    "sg:postcode":"3934",
    "sg:province":"VIC",
    "wof:name":"Pro-Active Real Estate",
    "wof:placetype":"venue"
},
  "geometry": {"coordinates":[145.01280212399999,-38.2681236267],"type":"Point"}
}