{
  "type": "Feature",
  "properties": {
    "addr:full":"9 Brex Crt Reservoir VIC 3073",
    "addr:housenumber":"9",
    "addr:postcode":"3073",
    "addr:street":"Brex Crt",
    "iso:country":"AU",
    "sg:address":"9 Brex Crt",
    "sg:city":"Reservoir",
    "sg:classifiers":[
        {
            "category":"Manufacturing",
            "subcategory":"Tools & Machinery",
            "type":"Manufacturing & Wholesale Goods"
        }
    ],
    "sg:phone":"+61 3 9462 6194",
    "sg:postcode":"3073",
    "sg:province":"VIC",
    "sg:tags":[
        "earth",
        "excavating",
        "moving",
        "equipment"
    ],
    "wof:name":"Gayters Spares & Repairs",
    "wof:placetype":"venue"
},
  "geometry": {"coordinates":[144.98036193900001,-37.70860672],"type":"Point"}
}