{
  "type": "Feature",
  "properties": {
    "addr:full":"PO Box 316 Hunters Hill NSW 2110",
    "addr:postcode":"2110",
    "iso:country":"AU",
    "sg:address":"PO Box 316",
    "sg:city":"Hunters Hill",
    "sg:classifiers":[
        {
            "category":"Recreation",
            "subcategory":"Boat Charter",
            "type":"Entertainment"
        }
    ],
    "sg:phone":"+61 2 9879 7647",
    "sg:postcode":"2110",
    "sg:province":"NSW",
    "wof:name":"Solquest Harbour Charters",
    "wof:placetype":"venue"
},
  "geometry": {"coordinates":[151.15332031200001,-33.8347091675],"type":"Point"}
}