{
  "type": "Feature",
  "properties": {
    "iso:country":"AU",
    "sg:address":"Under The Bunya Pines, Winmalee Shopping Village, Whitecross Rd",
    "sg:city":"Winmalee",
    "sg:classifiers":[
        {
            "category":"Retail",
            "subcategory":"Veterinary Services",
            "type":"Services"
        }
    ],
    "sg:phone":"+61 2 4754 4333",
    "sg:postcode":"2777",
    "sg:province":"NSW",
    "sg:tags":[
        "surgeon"
    ],
    "sg:website":"http://www.winmaleevets.com.au",
    "wof:name":"Winmalee Veterinary Clinic",
    "wof:placetype":"venue"
},
  "geometry": {"coordinates":[150.59963989299999,-33.725605011],"type":"Point"}
}