{
  "type": "Feature",
  "properties": {
    "addr:full":"Lot 93 William St Linville QLD 4306",
    "addr:housenumber":"93",
    "addr:postcode":"4306",
    "addr:street":"William St",
    "iso:country":"AU",
    "sg:address":"Lot 93 William St",
    "sg:city":"Linville",
    "sg:classifiers":[
        {
            "category":"Organizations",
            "subcategory":"Professional Association",
            "type":"Services"
        }
    ],
    "sg:phone":"+61 7 5424 7241",
    "sg:postcode":"4306",
    "sg:province":"QLD",
    "sg:tags":[
        "web",
        "internet"
    ],
    "wof:name":"Splot Web Development",
    "wof:placetype":"venue"
},
  "geometry": {"coordinates":[152.27784729000001,-26.8400535583],"type":"Point"}
}