{
  "type": "Feature",
  "properties": {
    "iso:country":"AU",
    "sg:address":"84 Trawalla Ave",
    "sg:city":"Thomastown",
    "sg:classifiers":[
        {
            "category":"Building & Trades",
            "subcategory":"Equipment Rental",
            "type":"Services"
        }
    ],
    "sg:phone":"+61 3 9359 1122",
    "sg:postcode":"3074",
    "sg:province":"VIC",
    "sg:tags":[
        "platform",
        "hire",
        "work",
        "elevating"
    ],
    "wof:name":"Northern Access Pty Ltd",
    "wof:placetype":"venue"
},
  "geometry": {"coordinates":[144.97279357900001,-37.6865463257],"type":"Point"}
}