{
  "type": "Feature",
  "properties": {
    "iso:country":"AU",
    "sg:address":"228 Beatty Rd",
    "sg:city":"Archerfield",
    "sg:classifiers":[
        {
            "category":"Retail",
            "subcategory":"Repair Shop",
            "type":"Services"
        }
    ],
    "sg:phone":"+61 7 3277 4400",
    "sg:postcode":"4108",
    "sg:province":"QLD",
    "sg:tags":[
        "upholsterer"
    ],
    "wof:name":"Brisbane Auto Trimming",
    "wof:placetype":"venue"
},
  "geometry": {"coordinates":[153.015457153,-27.5662078857],"type":"Point"}
}