{
  "type": "Feature",
  "properties": {
    "addr:full":"Level 5, 100 Pirie St Adelaide SA 5000",
    "addr:housenumber":"100",
    "addr:postcode":"5000",
    "addr:street":"Pirie St",
    "iso:country":"AU",
    "sg:address":"Level 5, 100 Pirie St",
    "sg:city":"Adelaide",
    "sg:classifiers":[
        {
            "category":"Professional",
            "subcategory":"Management & Consulting",
            "type":"Services"
        }
    ],
    "sg:phone":"+61 8 8232 6088",
    "sg:postcode":"5000",
    "sg:province":"SA",
    "sg:tags":[
        "consultant"
    ],
    "wof:name":"Right Management Consultants Pty Ltd",
    "wof:placetype":"venue"
},
  "geometry": {"coordinates":[138.60346984899999,-34.9254455566],"type":"Point"}
}