{
  "type": "Feature",
  "properties": {
    "addr:full":"946 Main Rd Hurstbridge VIC 3099",
    "addr:housenumber":"946",
    "addr:postcode":"3099",
    "addr:street":"Main Rd",
    "iso:country":"AU",
    "sg:address":"946 Main Rd",
    "sg:city":"Hurstbridge",
    "sg:classifiers":[
        {
            "category":"Communications",
            "subcategory":"Film & Video Production",
            "type":"Services"
        }
    ],
    "sg:phone":"+61 3 9718 1441",
    "sg:postcode":"3099",
    "sg:province":"VIC",
    "sg:tags":[
        "dvd",
        "library"
    ],
    "wof:name":"Hurstbridge Video",
    "wof:placetype":"venue"
},
  "geometry": {"coordinates":[145.19639587399999,-37.6369819641],"type":"Point"}
}