{
  "type": "Feature",
  "properties": {
    "addr:full":"66 Porter Rd Heidelberg Heights VIC 3081",
    "addr:housenumber":"66",
    "addr:postcode":"3081",
    "addr:street":"Porter Rd",
    "iso:country":"AU",
    "sg:address":"66 Porter Rd",
    "sg:city":"Heidelberg Heights",
    "sg:classifiers":[
        {
            "category":"Banks & Credit Unions",
            "subcategory":"Investment Brokerage",
            "type":"Services"
        }
    ],
    "sg:phone":"+61 3 9440 8222",
    "sg:postcode":"3081",
    "sg:province":"VIC",
    "sg:tags":[
        "finance",
        "broker"
    ],
    "wof:name":"AMH Vehicle & Equipment Finance",
    "wof:placetype":"venue"
},
  "geometry": {"coordinates":[145.057693481,-37.7397079468],"type":"Point"}
}