{
  "type": "Feature",
  "properties": {
    "addr:full":"76 Barker St Casino NSW 2470",
    "addr:housenumber":"76",
    "addr:postcode":"2470",
    "addr:street":"Barker St",
    "iso:country":"AU",
    "sg:address":"76 Barker St",
    "sg:city":"Casino",
    "sg:classifiers":[
        {
            "category":"Health Services",
            "subcategory":"Optometrist",
            "type":"Services"
        }
    ],
    "sg:phone":"+61 2 6662 1655",
    "sg:postcode":"2470",
    "sg:province":"NSW",
    "wof:name":"Anthony J Hogan Optometrist",
    "wof:placetype":"venue"
},
  "geometry": {"coordinates":[153.045166016,-28.8643436432],"type":"Point"}
}