{
  "type": "Feature",
  "properties": {
    "addr:full":"John St Rosewood QLD 4340",
    "addr:postcode":"4340",
    "addr:street":"John St",
    "iso:country":"AU",
    "sg:address":"John St",
    "sg:city":"Rosewood",
    "sg:classifiers":[
        {
            "category":"Shopping",
            "subcategory":"Clothing, Apparel, & Fashions",
            "type":"Retail Goods"
        }
    ],
    "sg:phone":"+61 7 5464 1155",
    "sg:postcode":"4340",
    "sg:province":"QLD",
    "sg:tags":[
        "lady",
        "wear"
    ],
    "wof:name":"Kaysuelle Fashions",
    "wof:placetype":"venue"
},
  "geometry": {"coordinates":[152.59071350100001,-27.6357765198],"type":"Point"}
}