{
  "type": "Feature",
  "properties": {
    "addr:full":"174a Warrigal Rd Oakleigh VIC 3166",
    "addr:housenumber":"174a",
    "addr:postcode":"3166",
    "addr:street":"Warrigal Rd",
    "iso:country":"AU",
    "sg:address":"174a Warrigal Rd",
    "sg:city":"Oakleigh",
    "sg:classifiers":[
        {
            "category":"Restaurant",
            "type":"Food & Drink"
        }
    ],
    "sg:phone":"+61 3 9579 2870",
    "sg:postcode":"3166",
    "sg:province":"VIC",
    "sg:tags":[
        "pizza"
    ],
    "wof:name":"Rafas Pizzeria",
    "wof:placetype":"venue"
},
  "geometry": {"coordinates":[145.085449219,-37.9083786011],"type":"Point"}
}