{
  "type": "Feature",
  "properties": {
    "addr:full":"54 King Arthur Drv Glen Waverley VIC 3150",
    "addr:housenumber":"54",
    "addr:postcode":"3150",
    "addr:street":"King Arthur Drv",
    "iso:country":"AU",
    "sg:address":"54 King Arthur Drv",
    "sg:city":"Glen Waverley",
    "sg:classifiers":[
        {
            "category":"Health Services",
            "subcategory":"Doctor",
            "type":"Services"
        }
    ],
    "sg:phone":"+61 3 9527 7452",
    "sg:postcode":"3150",
    "sg:province":"VIC",
    "sg:tags":[
        "medical",
        "practitioner"
    ],
    "wof:name":"Korbi G",
    "wof:placetype":"venue"
},
  "geometry": {"coordinates":[145.187988281,-37.8682632446],"type":"Point"}
}