{
  "type": "Feature",
  "properties": {
    "addr:full":"30 Bundella Ave Lake Cathie NSW 2445",
    "addr:housenumber":"30",
    "addr:postcode":"2445",
    "addr:street":"Bundella Ave",
    "iso:country":"AU",
    "sg:address":"30 Bundella Ave",
    "sg:city":"Lake Cathie",
    "sg:classifiers":[
        {
            "category":"Recreation",
            "subcategory":"Fishing",
            "type":"Entertainment"
        }
    ],
    "sg:phone":"+61 2 6585 5257",
    "sg:postcode":"2445",
    "sg:province":"NSW",
    "sg:tags":[
        "tackle"
    ],
    "wof:name":"Lakeside Tackle Shack",
    "wof:placetype":"venue"
},
  "geometry": {"coordinates":[152.856155,-31.548704],"type":"Point"}
}