{
  "type": "Feature",
  "properties": {
    "iso:country":"AU",
    "sg:address":"Lot 1 Nildottie Rd",
    "sg:city":"Swan Reach",
    "sg:classifiers":[
        {
            "category":"Sports & Exercise",
            "subcategory":"Golf",
            "type":"Entertainment"
        }
    ],
    "sg:phone":"+61 8 8570 2340",
    "sg:postcode":"5354",
    "sg:province":"SA",
    "sg:tags":[
        "club"
    ],
    "wof:name":"Swan Reach Golf Club Incorporated",
    "wof:placetype":"venue"
},
  "geometry": {"coordinates":[139.59669494600001,-34.5688056946],"type":"Point"}
}