{
  "type": "Feature",
  "properties": {
    "iso:country":"AU",
    "sg:address":"PO Box 1858",
    "sg:city":"Gawler",
    "sg:classifiers":[
        {
            "category":"Government",
            "subcategory":"Post Office",
            "type":"Public Place"
        }
    ],
    "sg:phone":"+61 417 841 978",
    "sg:postcode":"5118",
    "sg:province":"SA",
    "sg:tags":[
        "equipment",
        "hole",
        "contractor"
    ],
    "wof:name":"Brooklyn Contracting",
    "wof:placetype":"venue"
},
  "geometry": {"coordinates":[138.72822600000001,-34.596329],"type":"Point"}
}