{
  "type": "Feature",
  "properties": {
    "addr:full":"5 Gonzales St Amity Point QLD 4183",
    "addr:housenumber":"5",
    "addr:postcode":"4183",
    "addr:street":"Gonzales St",
    "iso:country":"AU",
    "sg:address":"5 Gonzales St",
    "sg:city":"Amity Point",
    "sg:classifiers":[
        {
            "category":"Building & Trades",
            "subcategory":"Construction",
            "type":"Services"
        }
    ],
    "sg:phone":"+61 7 3409 7008",
    "sg:postcode":"4183",
    "sg:province":"QLD",
    "sg:tags":[
        "fencing",
        "contractor"
    ],
    "wof:name":"W & K Davey Fencing",
    "wof:placetype":"venue"
},
  "geometry": {"coordinates":[153.44081115700001,-27.3964996338],"type":"Point"}
}