{
  "type": "Feature",
  "properties": {
    "addr:full":"Turner St Bacchus Marsh VIC 3340",
    "addr:postcode":"3340",
    "addr:street":"Turner St",
    "iso:country":"AU",
    "sg:address":"Turner St",
    "sg:city":"Bacchus Marsh",
    "sg:classifiers":[
        {
            "category":"Health Services",
            "subcategory":"Doctor",
            "type":"Services"
        }
    ],
    "sg:phone":"+61 3 5367 3333",
    "sg:postcode":"3340",
    "sg:province":"VIC",
    "sg:tags":[
        "medical",
        "practitioner"
    ],
    "wof:name":"Sooknandan S",
    "wof:placetype":"venue"
},
  "geometry": {"coordinates":[144.43367000000001,-37.67733],"type":"Point"}
}