{
  "type": "Feature",
  "properties": {
    "iso:country":"AU",
    "sg:address":"91A William St",
    "sg:city":"Bathurst",
    "sg:classifiers":[
        {
            "category":"Shopping",
            "subcategory":"Clothing, Apparel, & Fashions",
            "type":"Retail Goods"
        }
    ],
    "sg:phone":"+61 2 6332 6565",
    "sg:postcode":"2795",
    "sg:province":"NSW",
    "sg:tags":[
        "lady",
        "wear"
    ],
    "wof:name":"Xquizit Boutique",
    "wof:placetype":"venue"
},
  "geometry": {"coordinates":[149.57911682100001,-33.4192733765],"type":"Point"}
}