{
  "type": "Feature",
  "properties": {
    "iso:country":"AU",
    "sg:address":"24- 26 Drynan St",
    "sg:city":"Bayswater",
    "sg:classifiers":[
        {
            "category":"Manufacturing",
            "subcategory":"Building Materials",
            "type":"Manufacturing & Wholesale Goods"
        }
    ],
    "sg:phone":"+61 1300 888 607",
    "sg:postcode":"6053",
    "sg:province":"WA",
    "sg:tags":[
        "stone",
        "product",
        "supply"
    ],
    "wof:name":"Smartstone",
    "wof:placetype":"venue"
},
  "geometry": {"coordinates":[115.912239075,-31.9089031219],"type":"Point"}
}