{
  "type": "Feature",
  "properties": {
    "addr:full":"Wright St Busselton WA 6280",
    "addr:postcode":"6280",
    "addr:street":"Wright St",
    "iso:country":"AU",
    "sg:address":"Wright St",
    "sg:city":"Busselton",
    "sg:classifiers":[
        {
            "category":"Home & Garden",
            "subcategory":"Building Materials",
            "type":"Retail Goods"
        }
    ],
    "sg:phone":"+61 8 9754 2822",
    "sg:postcode":"6280",
    "sg:province":"WA",
    "sg:tags":[
        "supply"
    ],
    "wof:name":"Busselton Steel",
    "wof:placetype":"venue"
},
  "geometry": {"coordinates":[115.347488403,-33.6637687683],"type":"Point"}
}