{
  "type": "Feature",
  "properties": {
    "addr:full":"U14/ 25 Power Ave Alexandria NSW 2015",
    "addr:postcode":"2015",
    "addr:street":"/ 25 Power Ave",
    "iso:country":"AU",
    "sg:address":"U14/ 25 Power Ave",
    "sg:city":"Alexandria",
    "sg:classifiers":[
        {
            "category":"Manufacturing",
            "subcategory":"Printing",
            "type":"Manufacturing & Wholesale Goods"
        }
    ],
    "sg:phone":"+61 2 9319 5933",
    "sg:postcode":"2015",
    "sg:province":"NSW",
    "sg:tags":[
        "wholesaler",
        "mfrs",
        "greeting",
        "card"
    ],
    "wof:name":"Card & Paper House",
    "wof:placetype":"venue"
},
  "geometry": {"coordinates":[151.19842529300001,-33.9008407593],"type":"Point"}
}