{
  "type": "Feature",
  "properties": {
    "addr:full":"Century Chambers Church St Dubbo NSW 2830",
    "addr:postcode":"2830",
    "addr:street":"Church St",
    "iso:country":"AU",
    "sg:address":"Century Chambers Church St",
    "sg:city":"Dubbo",
    "sg:classifiers":[
        {
            "category":"Health Services",
            "subcategory":"Dentist",
            "type":"Services"
        }
    ],
    "sg:phone":"+61 2 6882 4142",
    "sg:postcode":"2830",
    "sg:province":"NSW",
    "wof:name":"McKay W R",
    "wof:placetype":"venue"
},
  "geometry": {"coordinates":[148.600708008,-32.2468032837],"type":"Point"}
}