{
  "type": "Feature",
  "properties": {
    "iso:country":"AU",
    "sg:address":"123 Watsons Rd",
    "sg:city":"Glen Waverley",
    "sg:classifiers":[
        {
            "category":"Health Services",
            "subcategory":"Health Practitioner",
            "type":"Services"
        }
    ],
    "sg:phone":"+61 3 9560 3334",
    "sg:postcode":"3150",
    "sg:province":"VIC",
    "sg:tags":[
        "naturopath"
    ],
    "wof:name":"Jim Kontsimanis",
    "wof:placetype":"venue"
},
  "geometry": {"coordinates":[145.16786193900001,-37.901966095],"type":"Point"}
}