{
  "type": "Feature",
  "properties": {
    "addr:full":"5/ 86 Nile St Orange NSW 2800",
    "addr:housenumber":"/ 86",
    "addr:postcode":"2800",
    "addr:street":"Nile St",
    "iso:country":"AU",
    "sg:address":"5/ 86 Nile St",
    "sg:city":"Orange",
    "sg:classifiers":[
        {
            "category":"Education",
            "subcategory":"Music School",
            "type":"Public Place"
        }
    ],
    "sg:phone":"+61 408 622 819",
    "sg:postcode":"2800",
    "sg:province":"NSW",
    "sg:tags":[
        "teacher"
    ],
    "wof:name":"Central West Drum Tuition",
    "wof:placetype":"venue"
},
  "geometry": {"coordinates":[149.113555908,-33.2782402039],"type":"Point"}
}