{
  "type": "Feature",
  "properties": {
    "addr:full":"&#034;Glen Douglas&#034; Golf Course Rd St George QLD 4487",
    "addr:postcode":"4487",
    "addr:street":"Glen;Golf Course Rd",
    "iso:country":"AU",
    "sg:address":"&#034;Glen Douglas&#034; Golf Course Rd St",
    "sg:city":"George",
    "sg:classifiers":[
        {
            "category":"Farming",
            "subcategory":"Farm",
            "type":"Manufacturing & Wholesale Goods"
        }
    ],
    "sg:phone":"+61 7 4625 4116",
    "sg:postcode":"4487",
    "sg:province":"QLD",
    "sg:tags":[
        "farmer"
    ],
    "wof:name":"Knights J C & E S",
    "wof:placetype":"venue"
},
  "geometry": {"coordinates":[148.58096313499999,-28.0376491547],"type":"Point"}
}