{
  "type": "Feature",
  "properties": {
    "iso:country":"AU",
    "sg:address":"160 Stoney Creek Rd",
    "sg:city":"Beverly Hills",
    "sg:classifiers":[
        {
            "category":"Professional",
            "subcategory":"Accounting & Tax Preparation",
            "type":"Services"
        }
    ],
    "sg:phone":"+61 2 9580 9200",
    "sg:postcode":"2209",
    "sg:province":"NSW",
    "sg:tags":[
        "accountant",
        "auditor"
    ],
    "wof:name":"P R Carson & Co",
    "wof:placetype":"venue"
},
  "geometry": {"coordinates":[151.084229,-33.952263],"type":"Point"}
}