{
  "type": "Feature",
  "properties": {
    "iso:country":"AU",
    "sg:address":"U1/ 31 Coral St",
    "sg:city":"The Entrance",
    "sg:classifiers":[
        {
            "category":"Food & Beverages",
            "subcategory":"Supermarket",
            "type":"Retail Goods"
        }
    ],
    "sg:phone":"+61 2 4333 7472",
    "sg:postcode":"2261",
    "sg:province":"NSW",
    "sg:tags":[
        "grocery",
        "store"
    ],
    "wof:name":"The Entrance Supermarket",
    "wof:placetype":"venue"
},
  "geometry": {"coordinates":[151.497467,-33.341068],"type":"Point"}
}