{
  "type": "Feature",
  "properties": {
    "addr:full":"Barrack St Merredin WA 6415",
    "addr:postcode":"6415",
    "addr:street":"Barrack St",
    "iso:country":"AU",
    "sg:address":"Barrack St",
    "sg:city":"Merredin",
    "sg:classifiers":[
        {
            "category":"Landmark",
            "subcategory":"Tourist Information",
            "type":"Public Place"
        }
    ],
    "sg:phone":"+61 8 9041 1666",
    "sg:postcode":"6415",
    "sg:province":"WA",
    "sg:tags":[
        "bureau"
    ],
    "wof:name":"Merredin Tourist & Information Centre",
    "wof:placetype":"venue"
},
  "geometry": {"coordinates":[118.272369385,-31.4820613861],"type":"Point"}
}