{
  "type": "Feature",
  "properties": {
    "iso:country":"AU",
    "sg:address":"26 May Rd",
    "sg:city":"Eden Hill",
    "sg:classifiers":[
        {
            "category":"Personal",
            "subcategory":"Beauty Salon",
            "type":"Services"
        }
    ],
    "sg:phone":"+61 408 915 863",
    "sg:postcode":"6054",
    "sg:province":"WA",
    "sg:tags":[
        "supply",
        "artist",
        "make-up"
    ],
    "wof:name":"Katie Hair & Make-Up Artist",
    "wof:placetype":"venue"
},
  "geometry": {"coordinates":[115.942321777,-31.8889961243],"type":"Point"}
}