{
  "type": "Feature",
  "properties": {
    "addr:full":"6 Hilda St Waikiki WA 6169",
    "addr:housenumber":"6",
    "addr:postcode":"6169",
    "addr:street":"Hilda St",
    "iso:country":"AU",
    "sg:address":"6 Hilda St",
    "sg:city":"Waikiki",
    "sg:classifiers":[
        {
            "category":"Recreation",
            "subcategory":"Fishing",
            "type":"Entertainment"
        }
    ],
    "sg:phone":"+61 413 959 265",
    "sg:postcode":"6169",
    "sg:province":"WA",
    "sg:tags":[
        "trip"
    ],
    "wof:name":"Western Waters Aquatic Adventures",
    "wof:placetype":"venue"
},
  "geometry": {"coordinates":[115.742722,-32.323486],"type":"Point"}
}