{
  "type": "Feature",
  "properties": {
    "iso:country":"AU",
    "sg:address":"280 Mitchell Rd",
    "sg:city":"Alexandria",
    "sg:classifiers":[
        {
            "category":"Retail",
            "subcategory":"Auto Repair",
            "type":"Services"
        }
    ],
    "sg:phone":"+61 2 9557 3338",
    "sg:postcode":"2015",
    "sg:province":"NSW",
    "sg:tags":[
        "beater",
        "painter",
        "panel"
    ],
    "wof:name":"Alexandria Bodyworks",
    "wof:placetype":"venue"
},
  "geometry": {"coordinates":[151.18960571299999,-33.9050178528],"type":"Point"}
}