{
  "type": "Feature",
  "properties": {
    "iso:country":"AU",
    "sg:address":"Cnr Amherst & Blinco St",
    "sg:city":"Fremantle",
    "sg:classifiers":[
        {
            "category":"Professional",
            "type":"Services"
        }
    ],
    "sg:phone":"+61 8 9336 1322",
    "sg:postcode":"6160",
    "sg:province":"WA",
    "sg:tags":[
        "auctioneer"
    ],
    "wof:name":"Fremantle Auctioneers",
    "wof:placetype":"venue"
},
  "geometry": {"coordinates":[115.762321,-32.052433],"type":"Point"}
}