{
  "type": "Feature",
  "properties": {
    "iso:country":"AU",
    "sg:address":"291 Clyde St",
    "sg:city":"Granville",
    "sg:classifiers":[
        {
            "category":"Food & Beverages",
            "subcategory":"Supermarket",
            "type":"Retail Goods"
        }
    ],
    "sg:phone":"+61 2 9897 0014",
    "sg:postcode":"2142",
    "sg:province":"NSW",
    "sg:tags":[
        "grocery",
        "store"
    ],
    "wof:name":"Aboul Ibrahim Market",
    "wof:placetype":"venue"
},
  "geometry": {"coordinates":[151.010986328,-33.8575210571],"type":"Point"}
}