{
  "type": "Feature",
  "properties": {
    "addr:full":"93 River St Earlwood NSW 2206",
    "addr:housenumber":"93",
    "addr:postcode":"2206",
    "addr:street":"River St",
    "iso:country":"AU",
    "sg:address":"93 River St",
    "sg:city":"Earlwood",
    "sg:classifiers":[
        {
            "category":"Building & Trades",
            "subcategory":"Construction",
            "type":"Services"
        }
    ],
    "sg:phone":"+61 2 9718 7165",
    "sg:postcode":"2206",
    "sg:province":"NSW",
    "sg:tags":[
        "pool",
        "swimming"
    ],
    "wof:name":"Poolform Construction Pty Ltd",
    "wof:placetype":"venue"
},
  "geometry": {"coordinates":[151.12048300000001,-33.923367],"type":"Point"}
}