{
  "type": "Feature",
  "properties": {
    "addr:full":"Shop 6 & 7 64 Wallarah Rd Gorokan NSW 2263",
    "addr:housenumber":"shop 6 &;64",
    "addr:postcode":"2263",
    "addr:street":"7;Wallarah Rd",
    "iso:country":"AU",
    "sg:address":"Shop 6 & 7 64 Wallarah Rd",
    "sg:city":"Gorokan",
    "sg:classifiers":[
        {
            "category":"Real Estate",
            "subcategory":"Real Estate Agent",
            "type":"Services"
        }
    ],
    "sg:phone":"+61 2 4393 1255",
    "sg:postcode":"2263",
    "sg:province":"NSW",
    "wof:name":"Ray White Real Estate",
    "wof:placetype":"venue"
},
  "geometry": {"coordinates":[151.51130699999999,-33.258026],"type":"Point"}
}