{
  "type": "Feature",
  "properties": {
    "iso:country":"AU",
    "sg:address":"34 Cowper St",
    "sg:city":"Granville",
    "sg:classifiers":[
        {
            "category":"Retail",
            "subcategory":"Auto Repair",
            "type":"Services"
        }
    ],
    "sg:phone":"+61 2 9637 6465",
    "sg:postcode":"2142",
    "sg:province":"NSW",
    "sg:tags":[
        "repairer",
        "motor",
        "engineer"
    ],
    "wof:name":"Bob Drive Shaft",
    "wof:placetype":"venue"
},
  "geometry": {"coordinates":[151.01260375999999,-33.83177948],"type":"Point"}
}