{
  "type": "Feature",
  "properties": {
    "addr:full":"137 Faunce St Gosford NSW 2250",
    "addr:housenumber":"137",
    "addr:postcode":"2250",
    "addr:street":"Faunce St",
    "iso:country":"AU",
    "sg:address":"137 Faunce St",
    "sg:city":"Gosford",
    "sg:classifiers":[
        {
            "category":"Health Services",
            "subcategory":"Doctor",
            "type":"Services"
        }
    ],
    "sg:phone":"+61 2 4325 5665",
    "sg:postcode":"2250",
    "sg:province":"NSW",
    "sg:tags":[
        "medical",
        "practitioner"
    ],
    "wof:name":"Walton John",
    "wof:placetype":"venue"
},
  "geometry": {"coordinates":[151.343383789,-33.4231910706],"type":"Point"}
}