{
  "type": "Feature",
  "properties": {
    "addr:full":"Casa d'Italia 67 Norton St Leichhardt NSW 2040",
    "addr:housenumber":"67",
    "addr:postcode":"2040",
    "addr:street":"Norton St",
    "iso:country":"AU",
    "sg:address":"Casa d'Italia 67 Norton St",
    "sg:city":"Leichhardt",
    "sg:classifiers":[
        {
            "category":"Organizations",
            "subcategory":"Community Association",
            "type":"Services"
        }
    ],
    "sg:phone":"+61 2 9564 0744",
    "sg:postcode":"2040",
    "sg:province":"NSW",
    "sg:tags":[
        "organisation",
        "family",
        "welfare"
    ],
    "wof:name":"Co. As. It. Italian Association of Assistance",
    "wof:placetype":"venue"
},
  "geometry": {"coordinates":[151.15742499999999,-33.885242],"type":"Point"}
}