{
  "type": "Feature",
  "properties": {
    "addr:full":"204 South St Thornlands QLD 4164",
    "addr:housenumber":"204",
    "addr:postcode":"4164",
    "addr:street":"South St",
    "iso:country":"AU",
    "sg:address":"204 South St",
    "sg:city":"Thornlands",
    "sg:classifiers":[
        {
            "category":"Building & Trades",
            "subcategory":"Construction",
            "type":"Services"
        }
    ],
    "sg:phone":"+61 411 320 619",
    "sg:postcode":"4164",
    "sg:province":"QLD",
    "sg:tags":[
        "concrete",
        "contractor"
    ],
    "wof:name":"Superb Kerb",
    "wof:placetype":"venue"
},
  "geometry": {"coordinates":[153.255004883,-27.5477409363],"type":"Point"}
}