{
  "type": "Feature",
  "properties": {
    "addr:full":"Strand Hotel 12 The Terrace Ipswich QLD 4305",
    "addr:housenumber":"12",
    "addr:postcode":"4305",
    "addr:street":"The Terrace",
    "iso:country":"AU",
    "sg:address":"Strand Hotel 12 The Terrace",
    "sg:city":"Ipswich",
    "sg:classifiers":[
        {
            "category":"Food & Beverages",
            "subcategory":"Liquor & Beverages",
            "type":"Retail Goods"
        }
    ],
    "sg:phone":"+61 7 3281 1090",
    "sg:postcode":"4305",
    "sg:province":"QLD",
    "sg:tags":[
        "store"
    ],
    "wof:name":"Liquorwise",
    "wof:placetype":"venue"
},
  "geometry": {"coordinates":[152.76324462900001,-27.6090526581],"type":"Point"}
}