{
  "type": "Feature",
  "properties": {
    "addr:full":"243 Princes Hwy Albion Park NSW 2527",
    "addr:housenumber":"243",
    "addr:postcode":"2527",
    "addr:street":"Princes Hwy Albion Park",
    "iso:country":"AU",
    "sg:address":"243 Princes Hwy",
    "sg:city":"Albion Park",
    "sg:classifiers":[
        {
            "category":"Recreation",
            "subcategory":"Fishing",
            "type":"Entertainment"
        }
    ],
    "sg:phone":"+61 2 4256 6600",
    "sg:postcode":"2527",
    "sg:province":"NSW",
    "sg:tags":[
        "tackle"
    ],
    "wof:name":"Hellraiser Tackle & Electronics",
    "wof:placetype":"venue"
},
  "geometry": {"coordinates":[150.801239014,-34.5664520264],"type":"Point"}
}