{
  "type": "Feature",
  "properties": {
    "addr:full":"214 Balaclava Rd Caulfield North VIC 3161",
    "addr:housenumber":"214",
    "addr:postcode":"3161",
    "addr:street":"Balaclava Rd",
    "iso:country":"AU",
    "sg:address":"214 Balaclava Rd",
    "sg:city":"Caulfield North",
    "sg:classifiers":[
        {
            "category":"Professional",
            "subcategory":"Art Services",
            "type":"Services"
        }
    ],
    "sg:phone":"+61 3 9576 2229",
    "sg:postcode":"3161",
    "sg:province":"VIC",
    "sg:tags":[
        "interior",
        "designer"
    ],
    "wof:name":"Cohen Rina Interiors",
    "wof:placetype":"venue"
},
  "geometry": {"coordinates":[145.02311706500001,-37.8723144531],"type":"Point"}
}