{
  "type": "Feature",
  "properties": {
    "addr:full":"675 High St Preston VIC 3072",
    "addr:housenumber":"675",
    "addr:postcode":"3072",
    "addr:street":"High St",
    "iso:country":"AU",
    "sg:address":"675 High St",
    "sg:city":"Preston",
    "sg:classifiers":[
        {
            "category":"Cafe",
            "type":"Food & Drink"
        }
    ],
    "sg:phone":"+61 3 9471 2377",
    "sg:postcode":"3072",
    "sg:province":"VIC",
    "wof:name":"Cuppa Cafe",
    "wof:placetype":"venue"
},
  "geometry": {"coordinates":[145.004806519,-37.7321662903],"type":"Point"}
}