{
  "type": "Feature",
  "properties": {
    "addr:full":"Grimwade Rd Lowden WA 6240",
    "addr:postcode":"6240",
    "addr:street":"Grimwade Rd",
    "iso:country":"AU",
    "sg:address":"Grimwade Rd",
    "sg:city":"Lowden",
    "sg:classifiers":[
        {
            "category":"Professional",
            "subcategory":"Engineering",
            "type":"Services"
        }
    ],
    "sg:phone":"+61 428 925 084",
    "sg:postcode":"6240",
    "sg:province":"WA",
    "sg:tags":[
        "diesel",
        "engineer"
    ],
    "wof:name":"Allanson Engineering",
    "wof:placetype":"venue"
},
  "geometry": {"coordinates":[115.96542358400001,-33.5324707031],"type":"Point"}
}