{
  "type": "Feature",
  "properties": {
    "addr:full":"1844 Albany Hwy Maddington WA 6109",
    "addr:housenumber":"1844",
    "addr:postcode":"6109",
    "addr:street":"Albany Hwy",
    "iso:country":"AU",
    "sg:address":"1844 Albany Hwy",
    "sg:city":"Maddington",
    "sg:classifiers":[
        {
            "category":"Retail",
            "subcategory":"Storage",
            "type":"Services"
        }
    ],
    "sg:phone":"+61 8 9493 2888",
    "sg:postcode":"6109",
    "sg:province":"WA",
    "wof:name":"Maddington Storage",
    "wof:placetype":"venue"
},
  "geometry": {"coordinates":[115.98033905,-32.0494384766],"type":"Point"}
}