{
  "type": "Feature",
  "properties": {
    "iso:country":"AU",
    "sg:address":"2a Harriet St",
    "sg:city":"Croydon",
    "sg:classifiers":[
        {
            "category":"Health Services",
            "subcategory":"Health Practitioner",
            "type":"Services"
        }
    ],
    "sg:phone":"+61 8 8346 8138",
    "sg:postcode":"5008",
    "sg:province":"SA",
    "sg:tags":[
        "physiotherapist"
    ],
    "wof:name":"Woodville Physiotherapy & Sports Injury Clinic",
    "wof:placetype":"venue"
},
  "geometry": {"coordinates":[138.56723,-34.892979],"type":"Point"}
}