{
  "type": "Feature",
  "properties": {
    "iso:country":"AU",
    "sg:address":"10 Market St",
    "sg:city":"Nunawading",
    "sg:classifiers":[
        {
            "category":"Professional",
            "subcategory":"Business Services",
            "type":"Services"
        }
    ],
    "sg:phone":"+61 3 9877 5644",
    "sg:postcode":"3131",
    "sg:province":"VIC",
    "sg:tags":[
        "consultant",
        "system"
    ],
    "wof:name":"Twenty Seventh Y",
    "wof:placetype":"venue"
},
  "geometry": {"coordinates":[145.17648315400001,-37.8210945129],"type":"Point"}
}