{
  "type": "Feature",
  "properties": {
    "iso:country":"AU",
    "sg:address":"9 Boyd St",
    "sg:city":"Richmond",
    "sg:classifiers":[
        {
            "category":"Communications",
            "subcategory":"Film & Video Production",
            "type":"Services"
        }
    ],
    "sg:phone":"+61 3 9429 6883",
    "sg:postcode":"3121",
    "sg:province":"VIC",
    "sg:tags":[
        "cost",
        "estimator"
    ],
    "wof:name":"N.C. Cost Planning Pty Ltd",
    "wof:placetype":"venue"
},
  "geometry": {"coordinates":[145.00485229500001,-37.8230552673],"type":"Point"}
}