{
  "type": "Feature",
  "properties": {
    "iso:country":"AU",
    "sg:address":"Shp6/ 354 Pennant Hills Rd",
    "sg:city":"Pennant Hills",
    "sg:classifiers":[
        {
            "category":"Personal",
            "subcategory":"Nail Salon",
            "type":"Services"
        }
    ],
    "sg:phone":"+61 2 9980 2425",
    "sg:postcode":"2120",
    "sg:province":"NSW",
    "sg:tags":[
        "artificial"
    ],
    "wof:name":"Creative Nails",
    "wof:placetype":"venue"
},
  "geometry": {"coordinates":[151.07034301799999,-33.7390632629],"type":"Point"}
}