{
  "type": "Feature",
  "properties": {
    "addr:full":"27 Stephen St New Norfolk TAS 7140",
    "addr:housenumber":"27",
    "addr:postcode":"7140",
    "addr:street":"Stephen St",
    "iso:country":"AU",
    "sg:address":"27 Stephen St",
    "sg:city":"New Norfolk",
    "sg:classifiers":[
        {
            "category":"Building & Trades",
            "subcategory":"Locksmith",
            "type":"Services"
        }
    ],
    "sg:phone":"+61 3 6261 3444",
    "sg:postcode":"7140",
    "sg:province":"TAS",
    "sg:tags":[
        "strongroom",
        "safe",
        "door"
    ],
    "wof:name":"New Norfolk Gun Shop",
    "wof:placetype":"venue"
},
  "geometry": {"coordinates":[147.06564299999999,-42.780945],"type":"Point"}
}