{
  "type": "Feature",
  "properties": {
    "addr:full":"14 Louisa St Goodwood SA 5034",
    "addr:housenumber":"14",
    "addr:postcode":"5034",
    "addr:street":"Louisa St",
    "iso:country":"AU",
    "sg:address":"14 Louisa St",
    "sg:city":"Goodwood",
    "sg:classifiers":[
        {
            "category":"Wholesale",
            "subcategory":"Machinery & Supplies",
            "type":"Manufacturing & Wholesale Goods"
        }
    ],
    "sg:phone":"+61 8 8357 7525",
    "sg:postcode":"5034",
    "sg:province":"SA",
    "sg:tags":[
        "machine",
        "tool",
        "engineer"
    ],
    "wof:name":"ALLTIME CNC MACHINES (SA)",
    "wof:placetype":"venue"
},
  "geometry": {"coordinates":[138.59573364299999,-34.9528770447],"type":"Point"}
}