{
  "type": "Feature",
  "properties": {
    "addr:full":"U 7/ 8 Kerta Rd Kincumber NSW 2251",
    "addr:postcode":"2251",
    "addr:street":"Kerta Rd",
    "iso:country":"AU",
    "sg:address":"U 7/ 8 Kerta Rd",
    "sg:city":"Kincumber",
    "sg:classifiers":[
        {
            "category":"Autos & Motor Vehicles",
            "subcategory":"Auto Supplies",
            "type":"Retail Goods"
        }
    ],
    "sg:phone":"+61 2 4368 3444",
    "sg:postcode":"2251",
    "sg:province":"NSW",
    "sg:tags":[
        "accessory"
    ],
    "wof:name":"Automotive Discount Roof Racks",
    "wof:placetype":"venue"
},
  "geometry": {"coordinates":[151.392944336,-33.4739532471],"type":"Point"}
}