{
  "type": "Feature",
  "properties": {
    "iso:country":"AU",
    "sg:address":"Lvl1/ 259 Victoria Rd",
    "sg:city":"Gladesville",
    "sg:classifiers":[
        {
            "category":"Banks & Credit Unions",
            "subcategory":"Bank",
            "type":"Services"
        }
    ],
    "sg:phone":"+61 2 9816 4844",
    "sg:postcode":"2111",
    "sg:province":"NSW",
    "sg:tags":[
        "equipment",
        "sale",
        "point"
    ],
    "wof:name":"ATPOS Solutions",
    "wof:placetype":"venue"
},
  "geometry": {"coordinates":[151.126953125,-33.8304138184],"type":"Point"}
}