{
  "type": "Feature",
  "properties": {
    "addr:full":"28 Greenway Ave Camden NSW 2570",
    "addr:housenumber":"28",
    "addr:postcode":"2570",
    "addr:street":"Greenway Ave",
    "iso:country":"AU",
    "sg:address":"28 Greenway Ave",
    "sg:city":"Camden",
    "sg:classifiers":[
        {
            "category":"Building & Trades",
            "subcategory":"Landscaping Services",
            "type":"Services"
        }
    ],
    "sg:phone":"+61 409 559 435",
    "sg:postcode":"2570",
    "sg:province":"NSW",
    "sg:tags":[
        "designer",
        "landscape",
        "contractor"
    ],
    "wof:name":"Tech Scapes Australia Pty Ltd",
    "wof:placetype":"venue"
},
  "geometry": {"coordinates":[150.69944763199999,-34.0754966736],"type":"Point"}
}