{
  "type": "Feature",
  "properties": {
    "addr:full":"PO Box 326 Castle Hill NSW 1765",
    "addr:postcode":"1765",
    "iso:country":"AU",
    "sg:address":"PO Box 326",
    "sg:city":"Castle Hill",
    "sg:classifiers":[
        {
            "category":"Building & Trades",
            "subcategory":"Construction",
            "type":"Services"
        }
    ],
    "sg:phone":"+61 2 9680 8080",
    "sg:postcode":"1765",
    "sg:province":"NSW",
    "sg:tags":[
        "contractor"
    ],
    "wof:name":"Caliber Homes",
    "wof:placetype":"venue"
},
  "geometry": {"coordinates":[151.01724200000001,-33.730858],"type":"Point"}
}