{
  "type": "Feature",
  "properties": {
    "addr:full":"155 Doolong Rd Pialba QLD 4655",
    "addr:housenumber":"155",
    "addr:postcode":"4655",
    "addr:street":"Doolong Rd",
    "iso:country":"AU",
    "sg:address":"155 Doolong Rd",
    "sg:city":"Pialba",
    "sg:classifiers":[
        {
            "category":"Building & Trades",
            "subcategory":"Construction",
            "type":"Services"
        }
    ],
    "sg:phone":"+61 417 781 044",
    "sg:postcode":"4655",
    "sg:province":"QLD",
    "sg:tags":[
        "excavation",
        "foundation"
    ],
    "wof:name":"Bay City Bobcat & Tipper Hire",
    "wof:placetype":"venue"
},
  "geometry": {"coordinates":[152.837051,-25.304531],"type":"Point"}
}