{
  "type": "Feature",
  "properties": {
    "addr:full":"7 Elizabeth St Flying Fish Point QLD 4860",
    "addr:housenumber":"7",
    "addr:postcode":"4860",
    "addr:street":"Elizabeth St",
    "iso:country":"AU",
    "sg:address":"7 Elizabeth St",
    "sg:city":"Flying Fish Point",
    "sg:classifiers":[
        {
            "category":"Real Estate",
            "subcategory":"Real Estate Services",
            "type":"Services"
        }
    ],
    "sg:phone":"+61 7 4061 7782",
    "sg:postcode":"4860",
    "sg:province":"QLD",
    "sg:tags":[
        "consultant",
        "property"
    ],
    "wof:name":"Oasis Sunshine Developments Pty Ltd",
    "wof:placetype":"venue"
},
  "geometry": {"coordinates":[146.075805664,-17.5020027161],"type":"Point"}
}