{
  "type": "Feature",
  "properties": {
    "iso:country":"AU",
    "sg:address":"443 King St",
    "sg:city":"Moodlu",
    "sg:classifiers":[
        {
            "category":"Education",
            "subcategory":"Music School",
            "type":"Public Place"
        }
    ],
    "sg:phone":"+61 7 5495 3393",
    "sg:postcode":"4510",
    "sg:province":"QLD",
    "sg:tags":[
        "teacher"
    ],
    "wof:name":"Caboolture College of Music",
    "wof:placetype":"venue"
},
  "geometry": {"coordinates":[152.931732,-27.078075],"type":"Point"}
}