{
  "type": "Feature",
  "properties": {
    "addr:full":"179 Foote St Templestowe VIC 3106",
    "addr:housenumber":"179",
    "addr:postcode":"3106",
    "addr:street":"Foote St",
    "iso:country":"AU",
    "sg:address":"179 Foote St",
    "sg:city":"Templestowe",
    "sg:classifiers":[
        {
            "category":"Health Services",
            "subcategory":"Doctor",
            "type":"Services"
        }
    ],
    "sg:phone":"+61 3 9846 1777",
    "sg:postcode":"3106",
    "sg:province":"VIC",
    "sg:tags":[
        "medical",
        "practitioner"
    ],
    "wof:name":"Zeng Ge Dr",
    "wof:placetype":"venue"
},
  "geometry": {"coordinates":[145.13150024399999,-37.7591323853],"type":"Point"}
}