{
  "type": "Feature",
  "properties": {
    "iso:country":"AU",
    "sg:address":"47 Irving St",
    "sg:city":"Footscray",
    "sg:classifiers":[
        {
            "category":"Utilities",
            "subcategory":"Mobile Phone",
            "type":"Services"
        }
    ],
    "sg:phone":"+61 3 9689 0400",
    "sg:postcode":"3011",
    "sg:province":"VIC",
    "sg:tags":[
        "repair",
        "telephone"
    ],
    "wof:name":"Mobilelink",
    "wof:placetype":"venue"
},
  "geometry": {"coordinates":[144.901245117,-37.8015403748],"type":"Point"}
}