{
  "type": "Feature",
  "properties": {
    "addr:full":"4 Station Ave Darra QLD 4076",
    "addr:housenumber":"4",
    "addr:postcode":"4076",
    "addr:street":"Station Ave",
    "iso:country":"AU",
    "sg:address":"4 Station Ave",
    "sg:city":"Darra",
    "sg:classifiers":[
        {
            "category":"Home & Garden",
            "subcategory":"Building Materials",
            "type":"Retail Goods"
        }
    ],
    "sg:phone":"+61 7 3375 0588",
    "sg:postcode":"4076",
    "sg:province":"QLD",
    "sg:tags":[
        "pre-mixed",
        "concrete"
    ],
    "wof:name":"Excel Concrete",
    "wof:placetype":"venue"
},
  "geometry": {"coordinates":[152.95112609899999,-27.5645637512],"type":"Point"}
}