{
  "type": "Feature",
  "properties": {
    "addr:full":"Lot 11 McDougall St Jerilderie NSW 2716",
    "addr:postcode":"2716",
    "addr:street":"Mcdougall St",
    "iso:country":"AU",
    "sg:address":"Lot 11 McDougall St",
    "sg:city":"Jerilderie",
    "sg:classifiers":[
        {
            "category":"Building & Trades",
            "subcategory":"Landscaping Services",
            "type":"Services"
        }
    ],
    "sg:phone":"+61 3 5886 1359",
    "sg:postcode":"2716",
    "sg:province":"NSW",
    "sg:tags":[
        "stump",
        "tree",
        "felling",
        "removal"
    ],
    "wof:name":"Linelop Contracting Services",
    "wof:placetype":"venue"
},
  "geometry": {"coordinates":[145.72865295400001,-35.3507957458],"type":"Point"}
}