{
  "type": "Feature",
  "properties": {
    "addr:full":"28 Hannah St Beecroft NSW 2119",
    "addr:housenumber":"28",
    "addr:postcode":"2119",
    "addr:street":"Hannah St",
    "iso:country":"AU",
    "sg:address":"28 Hannah St",
    "sg:city":"Beecroft",
    "sg:classifiers":[
        {
            "category":"Health Services",
            "subcategory":"Doctor",
            "type":"Services"
        }
    ],
    "sg:phone":"+61 2 9481 9417",
    "sg:postcode":"2119",
    "sg:province":"NSW",
    "sg:tags":[
        "medical",
        "practitioner"
    ],
    "wof:name":"Beecroft Dental & Medical Centre",
    "wof:placetype":"venue"
},
  "geometry": {"coordinates":[151.06466674800001,-33.7493743896],"type":"Point"}
}