{
  "type": "Feature",
  "properties": {
    "iso:country":"AU",
    "sg:address":"58 Cimitiere St",
    "sg:city":"Launceston",
    "sg:classifiers":[
        {
            "category":"Home & Garden",
            "subcategory":"Carpets & Floor Coverings",
            "type":"Retail Goods"
        }
    ],
    "sg:phone":"+61 3 6335 5201",
    "sg:postcode":"7250",
    "sg:province":"TAS",
    "sg:tags":[
        "wood"
    ],
    "wof:name":"Gunns Limited",
    "wof:placetype":"venue"
},
  "geometry": {"coordinates":[147.145065308,-41.4308547974],"type":"Point"}
}