{
  "type": "Feature",
  "properties": {
    "addr:full":"6 Glyde Crt Malaga WA 6090",
    "addr:housenumber":"6",
    "addr:postcode":"6090",
    "addr:street":"Glyde Crt",
    "iso:country":"AU",
    "sg:address":"6 Glyde Crt",
    "sg:city":"Malaga",
    "sg:classifiers":[
        {
            "category":"Home & Garden",
            "subcategory":"Building Materials",
            "type":"Retail Goods"
        }
    ],
    "sg:phone":"+61 8 9249 6122",
    "sg:postcode":"6090",
    "sg:province":"WA",
    "sg:tags":[
        "concrete",
        "panel",
        "pre-cast"
    ],
    "wof:name":"Unique Concrete",
    "wof:placetype":"venue"
},
  "geometry": {"coordinates":[115.906478882,-31.8651828766],"type":"Point"}
}