{
  "type": "Feature",
  "properties": {
    "iso:country":"AU",
    "sg:address":"17 Pitt St",
    "sg:city":"Mortdale",
    "sg:classifiers":[
        {
            "category":"Real Estate",
            "subcategory":"Real Estate Agent",
            "type":"Services"
        }
    ],
    "sg:phone":"+61 2 9570 2777",
    "sg:postcode":"2223",
    "sg:province":"NSW",
    "wof:name":"Richardson & Wrench Mortdale",
    "wof:placetype":"venue"
},
  "geometry": {"coordinates":[151.07972717300001,-33.9719200134],"type":"Point"}
}