{
  "type": "Feature",
  "properties": {
    "addr:full":"11 Wotton St Aitkenvale QLD 4814",
    "addr:housenumber":"11",
    "addr:postcode":"4814",
    "addr:street":"Wotton St",
    "iso:country":"AU",
    "sg:address":"11 Wotton St",
    "sg:city":"Aitkenvale",
    "sg:classifiers":[
        {
            "category":"Health Services",
            "subcategory":"Nursing And Care Facility",
            "type":"Services"
        }
    ],
    "sg:phone":"+61 7 4775 7700",
    "sg:postcode":"4814",
    "sg:province":"QLD",
    "sg:tags":[
        "home"
    ],
    "wof:name":"Wotton Lodge",
    "wof:placetype":"venue"
},
  "geometry": {"coordinates":[146.76925700000001,-19.295322],"type":"Point"}
}