{
  "type": "Feature",
  "properties": {
    "addr:full":"Cnr Chapel & Commercial Rd Prahran VIC 3181",
    "addr:postcode":"3181",
    "iso:country":"AU",
    "sg:address":"Cnr Chapel & Commercial Rd",
    "sg:city":"Prahran",
    "sg:classifiers":[
        {
            "category":"Personal",
            "type":"Services"
        }
    ],
    "sg:phone":"+61 3 9509 7622",
    "sg:postcode":"3181",
    "sg:province":"VIC",
    "sg:tags":[
        "reducing",
        "treatment",
        "weight"
    ],
    "wof:name":"Re-Creation Health Clubs",
    "wof:placetype":"venue"
},
  "geometry": {"coordinates":[144.99400329599999,-37.8468322754],"type":"Point"}
}