{
  "type": "Feature",
  "properties": {
    "iso:country":"AU",
    "sg:address":"5/ 6 Duntroon St",
    "sg:city":"Brendale",
    "sg:classifiers":[
        {
            "category":"Home & Garden",
            "subcategory":"Building Materials",
            "type":"Retail Goods"
        }
    ],
    "sg:phone":"+61 7 3889 9133",
    "sg:postcode":"4500",
    "sg:province":"QLD",
    "sg:tags":[
        "merchant",
        "glass",
        "glazier"
    ],
    "wof:name":"Star Mirrors Qld",
    "wof:placetype":"venue"
},
  "geometry": {"coordinates":[152.9871521,-27.3210926056],"type":"Point"}
}