{
  "type": "Feature",
  "properties": {
    "iso:country":"AU",
    "sg:address":"302- 304 Bay St",
    "sg:city":"Port Melbourne",
    "sg:classifiers":[
        {
            "category":"Banks & Credit Unions",
            "subcategory":"Bank",
            "type":"Services"
        }
    ],
    "sg:phone":"+61 13 20 32",
    "sg:postcode":"3207",
    "sg:province":"VIC",
    "wof:name":"Westpac",
    "wof:placetype":"venue"
},
  "geometry": {"coordinates":[144.943817,-37.837185],"type":"Point"}
}