{
  "type": "Feature",
  "properties": {
    "addr:full":"5 Addison St Shellharbour NSW 2529",
    "addr:housenumber":"5",
    "addr:postcode":"2529",
    "addr:street":"Addison St",
    "iso:country":"AU",
    "sg:address":"5 Addison St",
    "sg:city":"Shellharbour",
    "sg:classifiers":[
        {
            "category":"Fast Food",
            "type":"Food & Drink"
        }
    ],
    "sg:phone":"+61 2 4296 5640",
    "sg:postcode":"2529",
    "sg:province":"NSW",
    "sg:tags":[
        "away",
        "take"
    ],
    "wof:name":"Shellharbour Fish & Chips",
    "wof:placetype":"venue"
},
  "geometry": {"coordinates":[150.867843628,-34.579208374],"type":"Point"}
}