{
  "type": "Feature",
  "properties": {
    "iso:country":"AU",
    "sg:address":"4 Seymour St",
    "sg:city":"Traralgon",
    "sg:classifiers":[
        {
            "category":"Personal",
            "subcategory":"Beauty Salon",
            "type":"Services"
        }
    ],
    "sg:phone":"+61 3 5174 1105",
    "sg:postcode":"3844",
    "sg:province":"VIC",
    "sg:tags":[
        "hairdresser"
    ],
    "wof:name":"Winston Brown Unisex Salon",
    "wof:placetype":"venue"
},
  "geometry": {"coordinates":[146.54043579099999,-38.1963005066],"type":"Point"}
}