{
  "type": "Feature",
  "properties": {
    "iso:country":"AU",
    "sg:address":"300 West St",
    "sg:city":"Toowoomba",
    "sg:classifiers":[
        {
            "category":"Food & Beverages",
            "subcategory":"Liquor & Beverages",
            "type":"Retail Goods"
        }
    ],
    "sg:phone":"+61 7 4635 2366",
    "sg:postcode":"4350",
    "sg:province":"QLD",
    "sg:tags":[
        "store"
    ],
    "wof:name":"West Ridge Bottle Shop",
    "wof:placetype":"venue"
},
  "geometry": {"coordinates":[151.937164,-27.596003],"type":"Point"}
}