{
  "type": "Feature",
  "properties": {
    "addr:full":"1 Nash Pl Yass NSW 2582",
    "addr:housenumber":"1",
    "addr:postcode":"2582",
    "addr:street":"Nash Pl",
    "iso:country":"AU",
    "sg:address":"1 Nash Pl",
    "sg:city":"Yass",
    "sg:classifiers":[
        {
            "category":"Farming",
            "subcategory":"Farm & Veterinary Services",
            "type":"Manufacturing & Wholesale Goods"
        }
    ],
    "sg:phone":"+61 2 6226 2250",
    "sg:postcode":"2582",
    "sg:province":"NSW",
    "sg:tags":[
        "blacksmith",
        "farrier"
    ],
    "wof:name":"Peter Seddon",
    "wof:placetype":"venue"
},
  "geometry": {"coordinates":[148.921051025,-34.8495788574],"type":"Point"}
}