{
  "type": "Feature",
  "properties": {
    "iso:country":"AU",
    "sg:address":"174 Cavan Rd",
    "sg:city":"Dry Creek",
    "sg:classifiers":[
        {
            "category":"Wholesale",
            "subcategory":"Construction Materials",
            "type":"Manufacturing & Wholesale Goods"
        }
    ],
    "sg:phone":"+61 8 8368 0222",
    "sg:postcode":"5094",
    "sg:province":"SA",
    "sg:tags":[
        "protective",
        "coating"
    ],
    "wof:name":"BIZ-Fine Pty Ltd",
    "wof:placetype":"venue"
},
  "geometry": {"coordinates":[138.596832275,-34.8368644714],"type":"Point"}
}