{
  "type": "Feature",
  "properties": {
    "iso:country":"AU",
    "sg:address":"Clunes Rd",
    "sg:city":"Clunes",
    "sg:classifiers":[
        {
            "category":"Building & Trades",
            "subcategory":"Cleaning & Sanitation",
            "type":"Services"
        }
    ],
    "sg:phone":"+61 413 307 607",
    "sg:postcode":"2480",
    "sg:province":"NSW",
    "sg:tags":[
        "cleaner",
        "repairer",
        "roof"
    ],
    "wof:name":"Update Roofing",
    "wof:placetype":"venue"
},
  "geometry": {"coordinates":[153.34684753400001,-28.7626209259],"type":"Point"}
}