{
  "type": "Feature",
  "properties": {
    "addr:full":"Jubilee Central, Lvl 2, 1 Erromango Drv Jubilee Pocket QLD 4802",
    "addr:housenumber":"1",
    "addr:postcode":"4802",
    "addr:street":"Erromango Drv",
    "iso:country":"AU",
    "sg:address":"Jubilee Central, Lvl 2, 1 Erromango Drv",
    "sg:city":"Jubilee Pocket",
    "sg:classifiers":[
        {
            "category":"Professional",
            "subcategory":"Accounting & Tax Preparation",
            "type":"Services"
        }
    ],
    "sg:phone":"+61 7 4948 4444",
    "sg:postcode":"4802",
    "sg:province":"QLD",
    "sg:tags":[
        "consultant",
        "taxation"
    ],
    "wof:name":"Accountancy Plus Whitsunday Pty Ltd",
    "wof:placetype":"venue"
},
  "geometry": {"coordinates":[148.73245239299999,-20.2815628052],"type":"Point"}
}