{
  "type": "Feature",
  "properties": {
    "iso:country":"AU",
    "sg:address":"11 Wales St",
    "sg:city":"Brunswick West",
    "sg:classifiers":[
        {
            "category":"Professional",
            "subcategory":"Employment Agencies",
            "type":"Services"
        }
    ],
    "sg:phone":"+61 3 9384 1082",
    "sg:postcode":"3055",
    "sg:province":"VIC",
    "sg:tags":[
        "entertainer",
        "agent"
    ],
    "wof:name":"Rohan Clark",
    "wof:placetype":"venue"
},
  "geometry": {"coordinates":[144.94221496599999,-37.7571792603],"type":"Point"}
}