{
  "type": "Feature",
  "properties": {
    "addr:full":"63 King Edward Rd Osborne Park WA 6017",
    "addr:housenumber":"63",
    "addr:postcode":"6017",
    "addr:street":"King Edward Rd",
    "iso:country":"AU",
    "sg:address":"63 King Edward Rd",
    "sg:city":"Osborne Park",
    "sg:classifiers":[
        {
            "category":"Building & Trades",
            "subcategory":"Construction",
            "type":"Services"
        }
    ],
    "sg:phone":"+61 8 9446 6655",
    "sg:postcode":"6017",
    "sg:province":"WA",
    "sg:tags":[
        "concrete",
        "contractor"
    ],
    "wof:name":"Seabreeze Concrete Construction",
    "wof:placetype":"venue"
},
  "geometry": {"coordinates":[115.812049866,-31.8980045319],"type":"Point"}
}