{
  "type": "Feature",
  "properties": {
    "iso:country":"AU",
    "sg:address":"27 Badila Crt",
    "sg:city":"Mackay",
    "sg:classifiers":[
        {
            "category":"Building & Trades",
            "subcategory":"Landscaping Services",
            "type":"Services"
        }
    ],
    "sg:phone":"+61 7 4942 1316",
    "sg:postcode":"4740",
    "sg:province":"QLD",
    "sg:tags":[
        "consultant"
    ],
    "wof:name":"Place Designs",
    "wof:placetype":"venue"
},
  "geometry": {"coordinates":[149.16232299999999,-21.119081],"type":"Point"}
}