{
  "type": "Feature",
  "properties": {
    "addr:full":"23 Earl St Canley Vale NSW 2166",
    "addr:housenumber":"23",
    "addr:postcode":"2166",
    "addr:street":"Earl St",
    "iso:country":"AU",
    "sg:address":"23 Earl St",
    "sg:city":"Canley Vale",
    "sg:classifiers":[
        {
            "category":"Building & Trades",
            "subcategory":"Cleaning & Sanitation",
            "type":"Services"
        }
    ],
    "sg:phone":"+61 407 200 508",
    "sg:postcode":"2166",
    "sg:province":"NSW",
    "sg:tags":[
        "chemical",
        "pressure",
        "steam",
        "contractor"
    ],
    "wof:name":"Yang Brick Cleaning Services",
    "wof:placetype":"venue"
},
  "geometry": {"coordinates":[150.93641662600001,-33.8836898804],"type":"Point"}
}