{
  "type": "Feature",
  "properties": {
    "iso:country":"AU",
    "sg:address":"131 Margaret St",
    "sg:city":"Toowoomba",
    "sg:classifiers":[
        {
            "category":"Restaurant",
            "type":"Food & Drink"
        }
    ],
    "sg:phone":"+61 7 4632 2623",
    "sg:postcode":"4350",
    "sg:province":"QLD",
    "wof:name":"Amigos Bar & Grill",
    "wof:placetype":"venue"
},
  "geometry": {"coordinates":[151.954666,-27.561029],"type":"Point"}
}