{
  "type": "Feature",
  "properties": {
    "addr:full":"149 Beach St Frankston VIC 3199",
    "addr:housenumber":"149",
    "addr:postcode":"3199",
    "addr:street":"Beach St",
    "iso:country":"AU",
    "sg:address":"149 Beach St",
    "sg:city":"Frankston",
    "sg:classifiers":[
        {
            "category":"Professional",
            "subcategory":"Computer Services",
            "type":"Services"
        }
    ],
    "sg:phone":"+61 417 330 168",
    "sg:postcode":"3199",
    "sg:province":"VIC",
    "sg:tags":[
        "equipment",
        "networking",
        "installation"
    ],
    "wof:name":"Pacific Traders",
    "wof:placetype":"venue"
},
  "geometry": {"coordinates":[144.92655944800001,-37.8394584656],"type":"Point"}
}