{
  "type": "Feature",
  "properties": {
    "addr:full":"Princes Hwy Bairnsdale VIC 3875",
    "addr:postcode":"3875",
    "addr:street":"Princes Hwy",
    "iso:country":"AU",
    "sg:address":"Princes Hwy",
    "sg:city":"Bairnsdale",
    "sg:classifiers":[
        {
            "category":"Wholesale",
            "subcategory":"Farm Supplies",
            "type":"Manufacturing & Wholesale Goods"
        }
    ],
    "sg:phone":"+61 3 5156 8808",
    "sg:postcode":"3875",
    "sg:province":"VIC",
    "sg:tags":[
        "feed",
        "supplement",
        "stock"
    ],
    "wof:name":"Bairnsdale Stockfeeds",
    "wof:placetype":"venue"
},
  "geometry": {"coordinates":[147.61001586899999,-37.8316841125],"type":"Point"}
}