{
  "type": "Feature",
  "properties": {
    "iso:country":"AU",
    "sg:address":"565 High St",
    "sg:city":"Penrith",
    "sg:classifiers":[
        {
            "category":"Real Estate",
            "subcategory":"Real Estate Agent",
            "type":"Services"
        }
    ],
    "sg:phone":"+61 2 4731 4731",
    "sg:postcode":"2751",
    "sg:province":"NSW",
    "wof:name":"Pullman & Williams",
    "wof:placetype":"venue"
},
  "geometry": {"coordinates":[150.91554260300001,-33.8950843811],"type":"Point"}
}