{
  "type": "Feature",
  "properties": {
    "addr:full":"53a Seventh St Mildura East VIC 3500",
    "addr:housenumber":"53a",
    "addr:postcode":"3500",
    "addr:street":"Seventh St",
    "iso:country":"AU",
    "sg:address":"53a Seventh St",
    "sg:city":"Mildura East",
    "sg:classifiers":[
        {
            "category":"Building & Trades",
            "subcategory":"Construction",
            "type":"Services"
        }
    ],
    "sg:phone":"+61 3 5021 0917",
    "sg:postcode":"3500",
    "sg:province":"VIC",
    "sg:tags":[
        "welding"
    ],
    "wof:name":"Markandea Engineering & Construction Pty Ltd",
    "wof:placetype":"venue"
},
  "geometry": {"coordinates":[142.153244019,-34.1758880615],"type":"Point"}
}