{
  "type": "Feature",
  "properties": {
    "iso:country":"AU",
    "sg:address":"67a High St",
    "sg:city":"New Norfolk",
    "sg:classifiers":[
        {
            "category":"Fast Food",
            "type":"Food & Drink"
        }
    ],
    "sg:phone":"+61 3 6261 2150",
    "sg:postcode":"7140",
    "sg:province":"TAS",
    "sg:tags":[
        "away",
        "take"
    ],
    "wof:name":"Martin Cash Pizza",
    "wof:placetype":"venue"
},
  "geometry": {"coordinates":[147.064529,-42.780537],"type":"Point"}
}