{
  "type": "Feature",
  "properties": {
    "iso:country":"AU",
    "sg:address":"148 Canterbury Rd",
    "sg:city":"Bankstown",
    "sg:classifiers":[
        {
            "category":"Manufacturing",
            "subcategory":"Rubber & Plastics",
            "type":"Manufacturing & Wholesale Goods"
        }
    ],
    "sg:phone":"+61 2 9793 8944",
    "sg:postcode":"2200",
    "sg:province":"NSW",
    "sg:tags":[
        "fabricator"
    ],
    "wof:name":"The Plastix Centre",
    "wof:placetype":"venue"
},
  "geometry": {"coordinates":[151.02874800000001,-33.933994],"type":"Point"}
}