{
  "type": "Feature",
  "properties": {
    "addr:full":"1/ 38 Tank St Gladstone QLD 4680",
    "addr:housenumber":"/ 38",
    "addr:postcode":"4680",
    "addr:street":"Tank St",
    "iso:country":"AU",
    "sg:address":"1/ 38 Tank St",
    "sg:city":"Gladstone",
    "sg:classifiers":[
        {
            "category":"Building & Trades",
            "subcategory":"Construction",
            "type":"Services"
        }
    ],
    "sg:phone":"+61 7 4972 6177",
    "sg:postcode":"4680",
    "sg:province":"QLD",
    "sg:tags":[
        "contractor"
    ],
    "wof:name":"G.J. Gardner. Homes",
    "wof:placetype":"venue"
},
  "geometry": {"coordinates":[151.25990295400001,-23.848482132],"type":"Point"}
}