{
  "type": "Feature",
  "properties": {
    "iso:country":"AU",
    "sg:address":"Rosebud; Cnr Nepean Hwy & Forth Ave",
    "sg:city":"Rosebud",
    "sg:classifiers":[
        {
            "category":"Fast Food",
            "type":"Food & Drink"
        }
    ],
    "sg:phone":"+61 3 5981 1688",
    "sg:postcode":"3939",
    "sg:province":"VIC",
    "sg:tags":[
        "away",
        "take"
    ],
    "wof:name":"McDonald's Family Restaurants",
    "wof:placetype":"venue"
},
  "geometry": {"coordinates":[144.89884948700001,-38.3572654724],"type":"Point"}
}