{
  "type": "Feature",
  "properties": {
    "iso:country":"AU",
    "sg:address":"Lipson Ave",
    "sg:city":"Kadina",
    "sg:classifiers":[
        {
            "category":"Education",
            "subcategory":"School",
            "type":"Public Place"
        }
    ],
    "sg:phone":"+61 8 8821 1988",
    "sg:postcode":"5554",
    "sg:province":"SA",
    "sg:tags":[
        "state",
        "except",
        "nsw"
    ],
    "wof:name":"Wallaroo Mines Primary School",
    "wof:placetype":"venue"
},
  "geometry": {"coordinates":[137.706375122,-33.9650421143],"type":"Point"}
}