{
  "type": "Feature",
  "properties": {
    "addr:full":"4/ 20 Loyalty Rd North Rocks NSW 2151",
    "addr:housenumber":"/ 20",
    "addr:postcode":"2151",
    "addr:street":"Loyalty Rd",
    "iso:country":"AU",
    "sg:address":"4/ 20 Loyalty Rd",
    "sg:city":"North Rocks",
    "sg:classifiers":[
        {
            "category":"Parking",
            "type":"Transportation"
        }
    ],
    "sg:phone":"+61 2 9630 6722",
    "sg:postcode":"2151",
    "sg:province":"NSW",
    "sg:tags":[
        "equipment",
        "system"
    ],
    "wof:name":"S & B Parking Services Pty Ltd",
    "wof:placetype":"venue"
},
  "geometry": {"coordinates":[151.008666992,-33.7749443054],"type":"Point"}
}