{
  "type": "Feature",
  "properties": {
    "addr:full":"115 Tamar St Ballina NSW 2478",
    "addr:housenumber":"115",
    "addr:postcode":"2478",
    "addr:street":"Tamar St",
    "iso:country":"AU",
    "sg:address":"115 Tamar St",
    "sg:city":"Ballina",
    "sg:classifiers":[
        {
            "category":"Wholesale",
            "subcategory":"Medical Equipment & Supplies",
            "type":"Manufacturing & Wholesale Goods"
        }
    ],
    "sg:phone":"+61 1800 653 336",
    "sg:postcode":"2478",
    "sg:province":"NSW",
    "sg:tags":[
        "aids",
        "hearing"
    ],
    "wof:name":"King Hearing Centres",
    "wof:placetype":"venue"
},
  "geometry": {"coordinates":[153.55732727,-28.86759758],"type":"Point"}
}