{
  "type": "Feature",
  "properties": {
    "addr:full":"Suite G3/ 62 Wellington Pde East Melbourne VIC 3002",
    "addr:housenumber":"/ 62",
    "addr:postcode":"3002",
    "addr:street":"Wellington Pde",
    "iso:country":"AU",
    "sg:address":"Suite G3/ 62 Wellington Pde",
    "sg:city":"East Melbourne",
    "sg:classifiers":[
        {
            "category":"Health Services",
            "subcategory":"Health Practitioner",
            "type":"Services"
        }
    ],
    "sg:phone":"+61 3 9419 4990",
    "sg:postcode":"3002",
    "sg:province":"VIC",
    "sg:tags":[
        "acupuncture"
    ],
    "wof:name":"Frackowiak Acupuncture & Natural Therapy Centre",
    "wof:placetype":"venue"
},
  "geometry": {"coordinates":[144.98823547399999,-37.8165283203],"type":"Point"}
}