{
  "type": "Feature",
  "properties": {
    "addr:full":"Level 3 North Tower Chatswood Central Chatswood NSW 2067",
    "addr:postcode":"2067",
    "iso:country":"AU",
    "sg:address":"Level 3 North Tower Chatswood Central",
    "sg:city":"Chatswood",
    "sg:classifiers":[
        {
            "category":"Wholesale",
            "subcategory":"Fruits & Vegetables",
            "type":"Manufacturing & Wholesale Goods"
        }
    ],
    "sg:phone":"+61 2 9904 6699",
    "sg:postcode":"2067",
    "sg:province":"NSW",
    "sg:tags":[
        "produce",
        "grain"
    ],
    "wof:name":"Bartlett Grain Pty Ltd",
    "wof:placetype":"venue"
},
  "geometry": {"coordinates":[151.19012451200001,-33.7924385071],"type":"Point"}
}