{
  "type": "Feature",
  "properties": {
    "iso:country":"AU",
    "sg:address":"166A Bridge Rd",
    "sg:city":"Richmond",
    "sg:classifiers":[
        {
            "category":"Health Services",
            "subcategory":"Health Practitioner",
            "type":"Services"
        }
    ],
    "sg:phone":"+61 3 9429 2168",
    "sg:postcode":"3121",
    "sg:province":"VIC",
    "sg:tags":[
        "naturopath"
    ],
    "wof:name":"Illingworth, Jan",
    "wof:placetype":"venue"
},
  "geometry": {"coordinates":[144.99594116200001,-37.8183403015],"type":"Point"}
}