{
  "type": "Feature",
  "properties": {
    "iso:country":"AU",
    "sg:address":"PO Box 21",
    "sg:city":"Kingsford",
    "sg:classifiers":[
        {
            "category":"Professional",
            "subcategory":"Art Services",
            "type":"Services"
        }
    ],
    "sg:phone":"+61 411 170 353",
    "sg:postcode":"2032",
    "sg:province":"NSW",
    "sg:tags":[
        "graphic",
        "designer"
    ],
    "wof:name":"Eons Creations",
    "wof:placetype":"venue"
},
  "geometry": {"coordinates":[151.227493286,-33.9234886169],"type":"Point"}
}