{
  "type": "Feature",
  "properties": {
    "addr:full":"Building 2 Block 1, 1b Unwin St Rosehill NSW 2142",
    "addr:housenumber":"block;1b",
    "addr:postcode":"2142",
    "addr:street":"Unwin St",
    "iso:country":"AU",
    "sg:address":"Building 2 Block 1, 1b Unwin St",
    "sg:city":"Rosehill",
    "sg:classifiers":[
        {
            "category":"Shopping",
            "subcategory":"Stationery & Office Supplies",
            "type":"Retail Goods"
        }
    ],
    "sg:phone":"+61 2 9682 4555",
    "sg:postcode":"2142",
    "sg:province":"NSW",
    "sg:tags":[
        "partition"
    ],
    "wof:name":"Australian Office Group Design Partners",
    "wof:placetype":"venue"
},
  "geometry": {"coordinates":[151.021774292,-33.8271408081],"type":"Point"}
}