{
  "type": "Feature",
  "properties": {
    "addr:full":"12 Gateway Blv Epping VIC 3076",
    "addr:housenumber":"12",
    "addr:postcode":"3076",
    "addr:street":"Gateway Blv",
    "iso:country":"AU",
    "sg:address":"12 Gateway Blv",
    "sg:city":"Epping",
    "sg:classifiers":[
        {
            "category":"Professional",
            "subcategory":"Business Services",
            "type":"Services"
        }
    ],
    "sg:phone":"+61 1300 808 808",
    "sg:postcode":"3076",
    "sg:province":"VIC",
    "sg:tags":[
        "record",
        "management",
        "storage"
    ],
    "sg:website":"http://www.apsolutions.com.au",
    "wof:name":"Australian Packaging Solutions",
    "wof:placetype":"venue"
},
  "geometry": {"coordinates":[145.20521545400001,-37.9735832214],"type":"Point"}
}