{
  "type": "Feature",
  "properties": {
    "iso:country":"AU",
    "sg:address":"17 Mayo St",
    "sg:city":"McDowall",
    "sg:classifiers":[
        {
            "category":"Professional",
            "subcategory":"Computer Services",
            "type":"Services"
        }
    ],
    "sg:phone":"+61 7 3353 4474",
    "sg:postcode":"4053",
    "sg:province":"QLD",
    "sg:tags":[
        "package",
        "software"
    ],
    "wof:name":"Frosting Software",
    "wof:placetype":"venue"
},
  "geometry": {"coordinates":[152.99351501500001,-27.3841724396],"type":"Point"}
}