{
  "type": "Feature",
  "properties": {
    "addr:full":"Shop 7B Sunbury Sq S/C, 2- 24 Evans St Sunbury VIC 3429",
    "addr:housenumber":"shop 7b;24",
    "addr:postcode":"3429",
    "addr:street":"Sunbury Sq S / C 2;Evans St",
    "iso:country":"AU",
    "sg:address":"Shop 7B Sunbury Sq S/C, 2- 24 Evans St",
    "sg:city":"Sunbury",
    "sg:classifiers":[
        {
            "category":"Travel",
            "subcategory":"Travel Agent",
            "type":"Entertainment"
        }
    ],
    "sg:phone":"+61 3 9744 4544",
    "sg:postcode":"3429",
    "sg:province":"VIC",
    "sg:tags":[
        "consultant"
    ],
    "wof:name":"Harvey World Travel",
    "wof:placetype":"venue"
},
  "geometry": {"coordinates":[144.728515625,-37.5805931091],"type":"Point"}
}