{
  "type": "Feature",
  "properties": {
    "iso:country":"AU",
    "sg:address":"215 Elizabeth St",
    "sg:city":"Melbourne",
    "sg:classifiers":[
        {
            "category":"Health Services",
            "subcategory":"Optometrist",
            "type":"Services"
        }
    ],
    "sg:phone":"+61 3 9670 6955",
    "sg:postcode":"3000",
    "sg:province":"VIC",
    "wof:name":"A.P. Optometrists Pty Ltd",
    "wof:placetype":"venue"
},
  "geometry": {"coordinates":[144.962615967,-37.8134155273],"type":"Point"}
}