{
  "type": "Feature",
  "properties": {
    "iso:country":"AU",
    "sg:address":"32a Greeves St St",
    "sg:city":"Kilda",
    "sg:classifiers":[
        {
            "category":"Real Estate",
            "subcategory":"Architect",
            "type":"Services"
        }
    ],
    "sg:phone":"+61 3 9525 3780",
    "sg:postcode":"3182",
    "sg:province":"VIC",
    "wof:name":"BP Architects",
    "wof:placetype":"venue"
},
  "geometry": {"coordinates":[144.98341369600001,-37.8657188416],"type":"Point"}
}