{
  "type": "Feature",
  "properties": {
    "iso:country":"AU",
    "sg:address":"48 Park St",
    "sg:city":"Peakhurst",
    "sg:classifiers":[
        {
            "category":"Organizations",
            "subcategory":"Non-profit Organization",
            "type":"Services"
        }
    ],
    "sg:phone":"+61 2 9584 0110",
    "sg:postcode":"2210",
    "sg:province":"NSW",
    "sg:tags":[
        "support",
        "disability",
        "organisation"
    ],
    "wof:name":"St George Area Intellectual Disability Services Ltd",
    "wof:placetype":"venue"
},
  "geometry": {"coordinates":[151.05188000000001,-33.963085],"type":"Point"}
}