{
  "type": "Feature",
  "properties": {
    "addr:full":"44 Cavan Rd Dry Creek SA 5094",
    "addr:housenumber":"44",
    "addr:postcode":"5094",
    "addr:street":"Cavan Rd Dry",
    "iso:country":"AU",
    "sg:address":"44 Cavan Rd",
    "sg:city":"Dry Creek",
    "sg:classifiers":[
        {
            "category":"Shopping",
            "subcategory":"Clothing, Apparel, & Fashions",
            "type":"Retail Goods"
        }
    ],
    "sg:phone":"+61 8 8202 5071",
    "sg:postcode":"5094",
    "sg:province":"SA",
    "sg:tags":[
        "recycled",
        "clothing"
    ],
    "wof:name":"Goodwill",
    "wof:placetype":"venue"
},
  "geometry": {"coordinates":[138.589187622,-34.8427619934],"type":"Point"}
}