{
  "type": "Feature",
  "properties": {
    "iso:country":"AU",
    "sg:address":"Cnr Bay & Stuart Sts",
    "sg:city":"Tweed Heads",
    "sg:classifiers":[
        {
            "category":"Structure",
            "subcategory":"Tunnel",
            "type":"Public Place"
        }
    ],
    "sg:phone":"+61 7 5536 6057",
    "sg:postcode":"2485",
    "sg:province":"NSW",
    "sg:tags":[
        "cleaner",
        "industrial",
        "vacuum"
    ],
    "wof:name":"Tweed Vacuum Cleaners",
    "wof:placetype":"venue"
},
  "geometry": {"coordinates":[153.54087829599999,-28.1707725525],"type":"Point"}
}