{
  "type": "Feature",
  "properties": {
    "addr:full":"Shop 1, 499 Beechboro Rd Beechboro WA 6063",
    "addr:housenumber":"shop 1",
    "addr:postcode":"499;6063",
    "addr:street":"Beechboro Rd",
    "iso:country":"AU",
    "sg:address":"Shop 1, 499 Beechboro Rd",
    "sg:city":"Beechboro",
    "sg:classifiers":[
        {
            "category":"Food & Beverages",
            "subcategory":"Liquor & Beverages",
            "type":"Retail Goods"
        }
    ],
    "sg:phone":"+61 8 9317 2433",
    "sg:postcode":"6063",
    "sg:province":"WA",
    "sg:tags":[
        "store"
    ],
    "wof:name":"Western Cellars",
    "wof:placetype":"venue"
},
  "geometry": {"coordinates":[115.924621582,-31.8684425354],"type":"Point"}
}