{
  "type": "Feature",
  "properties": {
    "iso:country":"AU",
    "sg:address":"70 Frank St",
    "sg:city":"Caboolture",
    "sg:classifiers":[
        {
            "category":"Banks & Credit Unions",
            "subcategory":"Bank",
            "type":"Services"
        }
    ],
    "sg:phone":"+61 412 068 063",
    "sg:postcode":"4510",
    "sg:province":"QLD",
    "wof:name":"Alternative Loans",
    "wof:placetype":"venue"
},
  "geometry": {"coordinates":[152.944946,-27.095055],"type":"Point"}
}