{
  "type": "Feature",
  "properties": {
    "iso:country":"AU",
    "sg:address":"1084 Grand Junction Rd",
    "sg:city":"Holden Hill",
    "sg:classifiers":[
        {
            "category":"Sports & Exercise",
            "subcategory":"Gym",
            "type":"Entertainment"
        }
    ],
    "sg:phone":"+61 8 8396 4229",
    "sg:postcode":"5088",
    "sg:province":"SA",
    "sg:tags":[
        "health",
        "fitness"
    ],
    "wof:name":"Barry's Health Centre",
    "wof:placetype":"venue"
},
  "geometry": {"coordinates":[138.68484497099999,-34.8443260193],"type":"Point"}
}