{
  "type": "Feature",
  "properties": {
    "iso:country":"AU",
    "sg:address":"141 George St",
    "sg:city":"Liverpool",
    "sg:classifiers":[
        {
            "category":"Shopping",
            "subcategory":"Optical Goods",
            "type":"Retail Goods"
        }
    ],
    "sg:phone":"+61 2 9601 8898",
    "sg:postcode":"2170",
    "sg:province":"NSW",
    "sg:tags":[
        "dispenser",
        "prescription"
    ],
    "wof:name":"Elegance Eyewear Boutique",
    "wof:placetype":"venue"
},
  "geometry": {"coordinates":[150.92457580600001,-33.9236297607],"type":"Point"}
}