{
  "type": "Feature",
  "properties": {
    "iso:country":"AU",
    "sg:address":"3/ 20 Broadhurst Rd",
    "sg:city":"Ingleburn",
    "sg:classifiers":[
        {
            "category":"Retail",
            "subcategory":"Auto Repair",
            "type":"Services"
        }
    ],
    "sg:phone":"+61 2 9618 7858",
    "sg:postcode":"2565",
    "sg:province":"NSW",
    "sg:tags":[
        "bus",
        "truck"
    ],
    "wof:name":"Direct Power Steering Service",
    "wof:placetype":"venue"
},
  "geometry": {"coordinates":[150.85440063499999,-34.0047416687],"type":"Point"}
}