{
  "type": "Feature",
  "properties": {
    "addr:full":"Lot 2 , Williams Cct Dubbo NSW 2830",
    "addr:postcode":"2830",
    "addr:street":"Williams Cct",
    "iso:country":"AU",
    "sg:address":"Lot 2",
    "sg:city":", Williams Cct Dubbo",
    "sg:classifiers":[
        {
            "category":"Wholesale",
            "subcategory":"Metals & Minerals",
            "type":"Manufacturing & Wholesale Goods"
        }
    ],
    "sg:phone":"+61 2 6882 8111",
    "sg:postcode":"2830",
    "sg:province":"NSW",
    "sg:tags":[
        "steel",
        "merchant"
    ],
    "wof:name":"Smorgon Steel Distribution",
    "wof:placetype":"venue"
},
  "geometry": {"coordinates":[148.60118102999999,-32.2478713989],"type":"Point"}
}