{
  "type": "Feature",
  "properties": {
    "iso:country":"AU",
    "sg:address":"267 Burke Rd",
    "sg:city":"Glen Iris",
    "sg:classifiers":[
        {
            "category":"Education",
            "subcategory":"Special Training",
            "type":"Public Place"
        }
    ],
    "sg:phone":"+61 3 9813 8722",
    "sg:postcode":"3146",
    "sg:province":"VIC",
    "sg:tags":[
        "diving",
        "school",
        "scuba"
    ],
    "wof:name":"Academy Of Scuba",
    "wof:placetype":"venue"
},
  "geometry": {"coordinates":[145.05215454099999,-37.8540840149],"type":"Point"}
}