{
  "type": "Feature",
  "properties": {
    "addr:full":"3/ 74 Clarence St Port Macquarie NSW 2444",
    "addr:housenumber":"/ 74",
    "addr:postcode":"2444",
    "addr:street":"Clarence St",
    "iso:country":"AU",
    "sg:address":"3/ 74 Clarence St",
    "sg:city":"Port Macquarie",
    "sg:classifiers":[
        {
            "category":"Recreation",
            "subcategory":"Boat Charter",
            "type":"Entertainment"
        }
    ],
    "sg:phone":"+61 1300 555 890",
    "sg:postcode":"2444",
    "sg:province":"NSW",
    "wof:name":"Clarence Street Booking Office",
    "wof:placetype":"venue"
},
  "geometry": {"coordinates":[152.906128,-31.429422],"type":"Point"}
}