{
  "type": "Feature",
  "properties": {
    "addr:full":"29 Lawrence Drv Nerang QLD 4211",
    "addr:housenumber":"29",
    "addr:postcode":"4211",
    "addr:street":"Lawrence Drv",
    "iso:country":"AU",
    "sg:address":"29 Lawrence Drv",
    "sg:city":"Nerang",
    "sg:classifiers":[
        {
            "category":"Shopping",
            "subcategory":"Crafts & Fabrics",
            "type":"Retail Goods"
        }
    ],
    "sg:phone":"+61 7 5596 1400",
    "sg:postcode":"4211",
    "sg:province":"QLD",
    "sg:tags":[
        "synthetic",
        "canvas",
        "product"
    ],
    "wof:name":"Dolomite Awnings",
    "wof:placetype":"venue"
},
  "geometry": {"coordinates":[153.346923828,-27.9969558716],"type":"Point"}
}