{
  "type": "Feature",
  "properties": {
    "addr:full":"418- 422 Maitland Rd Mayfield NSW 2304",
    "addr:housenumber":"422",
    "addr:postcode":"2304",
    "addr:street":"Maitland Rd",
    "iso:country":"AU",
    "sg:address":"418- 422 Maitland Rd",
    "sg:city":"Mayfield",
    "sg:classifiers":[
        {
            "category":"Restaurant",
            "type":"Food & Drink"
        }
    ],
    "sg:phone":"+61 2 4967 1977",
    "sg:postcode":"2304",
    "sg:province":"NSW",
    "wof:name":"Comfort Inn Hospitality",
    "wof:placetype":"venue"
},
  "geometry": {"coordinates":[151.72929382300001,-32.8920669556],"type":"Point"}
}