{
  "type": "Feature",
  "properties": {
    "iso:country":"AU",
    "sg:address":"72 Ervatamia St",
    "sg:city":"Runcorn",
    "sg:classifiers":[
        {
            "category":"Personal",
            "subcategory":"Massage",
            "type":"Services"
        }
    ],
    "sg:phone":"+61 7 3345 7643",
    "sg:postcode":"4113",
    "sg:province":"QLD",
    "sg:tags":[
        "therapy"
    ],
    "wof:name":"Fernantzen Sylvia",
    "wof:placetype":"venue"
},
  "geometry": {"coordinates":[153.071502686,-27.603427887],"type":"Point"}
}