{
  "type": "Feature",
  "properties": {
    "iso:country":"AU",
    "sg:address":"15 Celtis St",
    "sg:city":"Acacia Ridge",
    "sg:classifiers":[
        {
            "category":"Utilities",
            "subcategory":"Electric",
            "type":"Services"
        }
    ],
    "sg:phone":"+61 7 3277 8323",
    "sg:postcode":"4110",
    "sg:province":"QLD",
    "sg:tags":[
        "electrical",
        "contractor"
    ],
    "wof:name":"Total Mechanical Service Qld Pty Ltd",
    "wof:placetype":"venue"
},
  "geometry": {"coordinates":[153.011642456,-27.5799617767],"type":"Point"}
}