{
  "type": "Feature",
  "properties": {
    "addr:full":"Shop 16 Kalamunda Central Shopng Cntr Cnr Haynes & Kalamunda WA 6076",
    "addr:housenumber":"shop 16",
    "addr:postcode":"6076",
    "addr:street":"Cnr",
    "iso:country":"AU",
    "sg:address":"Shop 16 Kalamunda Central Shopng Cntr Cnr Haynes &",
    "sg:city":"Kalamunda",
    "sg:classifiers":[
        {
            "category":"Travel",
            "subcategory":"Travel Agent",
            "type":"Entertainment"
        }
    ],
    "sg:phone":"+61 13 18 66",
    "sg:postcode":"6076",
    "sg:province":"WA",
    "sg:tags":[
        "consultant"
    ],
    "wof:name":"Flight Centre",
    "wof:placetype":"venue"
},
  "geometry": {"coordinates":[116.05911254900001,-31.9713001251],"type":"Point"}
}