{
  "type": "Feature",
  "properties": {
    "addr:full":"126 Long St Smithfield NSW 2164",
    "addr:housenumber":"126",
    "addr:postcode":"2164",
    "addr:street":"Long St",
    "iso:country":"AU",
    "sg:address":"126 Long St",
    "sg:city":"Smithfield",
    "sg:classifiers":[
        {
            "category":"Wholesale",
            "subcategory":"Chemicals & Plastics",
            "type":"Manufacturing & Wholesale Goods"
        }
    ],
    "sg:phone":"+61 2 9725 4688",
    "sg:postcode":"2164",
    "sg:province":"NSW",
    "sg:tags":[
        "bag"
    ],
    "sg:website":"http://www.plasticbag.com.au",
    "wof:name":"The Plastic Bag Company Pty Ltd",
    "wof:placetype":"venue"
},
  "geometry": {"coordinates":[150.932769775,-33.8410758972],"type":"Point"}
}