{
  "type": "Feature",
  "properties": {
    "addr:full":"Willcox Ave Prospect SA 5082",
    "addr:postcode":"5082",
    "addr:street":"Willcox Ave",
    "iso:country":"AU",
    "sg:address":"Willcox Ave",
    "sg:city":"Prospect",
    "sg:classifiers":[
        {
            "category":"Retail",
            "subcategory":"Event Space",
            "type":"Services"
        }
    ],
    "sg:phone":"+61 8 8260 1114",
    "sg:postcode":"5082",
    "sg:province":"SA",
    "sg:tags":[
        "venue",
        "reception",
        "wedding"
    ],
    "wof:name":"Prospect R.S.L. Memorial Hall",
    "wof:placetype":"venue"
},
  "geometry": {"coordinates":[138.595245361,-34.8850212097],"type":"Point"}
}