{
  "type": "Feature",
  "properties": {
    "addr:full":"Firle Plaza Shopping Centre 171 Glynburn Rd Firle SA 5070",
    "addr:housenumber":"171",
    "addr:postcode":"5070",
    "addr:street":"Glynburn Rd",
    "iso:country":"AU",
    "sg:address":"Firle Plaza Shopping Centre 171 Glynburn Rd",
    "sg:city":"Firle",
    "sg:classifiers":[
        {
            "category":"Health Services",
            "subcategory":"Dentist",
            "type":"Services"
        }
    ],
    "sg:phone":"+61 8 8378 7939",
    "sg:postcode":"5070",
    "sg:province":"SA",
    "wof:name":"AAA Emergency Dental",
    "wof:placetype":"venue"
},
  "geometry": {"coordinates":[138.65751648,-34.9053230286],"type":"Point"}
}