{
  "type": "Feature",
  "properties": {
    "addr:full":"50 Skarratt St North Silverwater NSW 2128",
    "addr:housenumber":"50",
    "addr:postcode":"2128",
    "addr:street":"Skarratt St North",
    "iso:country":"AU",
    "sg:address":"50 Skarratt St",
    "sg:city":"North Silverwater",
    "sg:classifiers":[
        {
            "category":"Wholesale",
            "subcategory":"Machinery & Supplies",
            "type":"Manufacturing & Wholesale Goods"
        }
    ],
    "sg:phone":"+61 2 9748 4505",
    "sg:postcode":"2128",
    "sg:province":"NSW",
    "sg:tags":[
        "rigging",
        "equipment",
        "hoisting"
    ],
    "wof:name":"John L. Robertson Pty Ltd",
    "wof:placetype":"venue"
},
  "geometry": {"coordinates":[151.03794860799999,-33.8339614868],"type":"Point"}
}