{
  "type": "Feature",
  "properties": {
    "iso:country":"AU",
    "sg:address":"Unit 4/ 41 Northville Drv",
    "sg:city":"Barnsley",
    "sg:classifiers":[
        {
            "category":"Communications",
            "subcategory":"Film & Video Production",
            "type":"Services"
        }
    ],
    "sg:phone":"+61 2 4953 1999",
    "sg:postcode":"2278",
    "sg:province":"NSW",
    "sg:tags":[
        "television",
        "system",
        "circuit",
        "closed"
    ],
    "wof:name":"Quantic Security Pty Ltd",
    "wof:placetype":"venue"
},
  "geometry": {"coordinates":[151.591003,-32.932404],"type":"Point"}
}