{
  "type": "Feature",
  "properties": {
    "iso:country":"AU",
    "sg:address":"Pyrmont House 110 Serpentine Rd",
    "sg:city":"Albany",
    "sg:classifiers":[
        {
            "category":"Organizations",
            "subcategory":"Professional Association",
            "type":"Services"
        }
    ],
    "sg:phone":"+61 8 9842 4888",
    "sg:postcode":"6330",
    "sg:province":"WA",
    "sg:tags":[
        "organisation",
        "business"
    ],
    "wof:name":"Great Southern Development Commission",
    "wof:placetype":"venue"
},
  "geometry": {"coordinates":[117.882110596,-35.0219726562],"type":"Point"}
}