{
  "type": "Feature",
  "properties": {
    "addr:full":"Studio 6, Level 3/ 35 Buckingham St Surry Hills NSW 2010",
    "addr:housenumber":"/ 35",
    "addr:postcode":"2010",
    "addr:street":"Buckingham St",
    "iso:country":"AU",
    "sg:address":"Studio 6, Level 3/ 35 Buckingham St",
    "sg:city":"Surry Hills",
    "sg:classifiers":[
        {
            "category":"Professional",
            "subcategory":"Art Services",
            "type":"Services"
        }
    ],
    "sg:phone":"+61 2 8399 2103",
    "sg:postcode":"2010",
    "sg:province":"NSW",
    "sg:tags":[
        "interior",
        "designer"
    ],
    "wof:name":"Greg Natale Interior Design",
    "wof:placetype":"venue"
},
  "geometry": {"coordinates":[151.20736694300001,-33.8871803284],"type":"Point"}
}