{
  "type": "Feature",
  "properties": {
    "addr:full":"PO Box 603 Everton Park QLD 4053",
    "addr:postcode":"4053",
    "iso:country":"AU",
    "sg:address":"PO Box 603",
    "sg:city":"Everton Park",
    "sg:classifiers":[
        {
            "category":"Arena",
            "subcategory":"Sports Club",
            "type":"Entertainment"
        }
    ],
    "sg:phone":"+61 7 3263 6557",
    "sg:postcode":"4053",
    "sg:province":"QLD",
    "sg:tags":[
        "defence",
        "supply",
        "self",
        "instruction",
        "martial art"
    ],
    "wof:name":"Pacific International Taekwondo",
    "wof:placetype":"venue"
},
  "geometry": {"coordinates":[152.98692321799999,-27.3994598389],"type":"Point"}
}