{
  "type": "Feature",
  "properties": {
    "addr:full":"Unit 5/ 22 Cecil Ave Cannington WA 6107",
    "addr:housenumber":"22",
    "addr:postcode":"6107",
    "addr:street":"Cecil Ave",
    "iso:country":"AU",
    "sg:address":"Unit 5/ 22 Cecil Ave",
    "sg:city":"Cannington",
    "sg:classifiers":[
        {
            "category":"Health Services",
            "subcategory":"Doctor",
            "type":"Services"
        }
    ],
    "sg:phone":"+61 8 9258 5999",
    "sg:postcode":"6107",
    "sg:province":"WA",
    "sg:tags":[
        "medical",
        "practitioner"
    ],
    "wof:name":"Canning Eye Clinic",
    "wof:placetype":"venue"
},
  "geometry": {"coordinates":[115.937232971,-32.0164451599],"type":"Point"}
}