{
  "type": "Feature",
  "properties": {
    "iso:country":"AU",
    "sg:address":"26 Ironbark Crs",
    "sg:city":"Raceview",
    "sg:classifiers":[
        {
            "category":"Home & Garden",
            "subcategory":"Building Materials",
            "type":"Retail Goods"
        }
    ],
    "sg:phone":"+61 407 577 039",
    "sg:postcode":"4305",
    "sg:province":"QLD",
    "sg:tags":[
        "lawn",
        "cutting",
        "maintenance"
    ],
    "wof:name":"Smiths Outdoor Services",
    "wof:placetype":"venue"
},
  "geometry": {"coordinates":[152.786834717,-27.6423206329],"type":"Point"}
}