{
  "type": "Feature",
  "properties": {
    "addr:full":"488 Lutwyche Rd Lutwyche QLD 4030",
    "addr:housenumber":"488",
    "addr:postcode":"4030",
    "addr:street":"Lutwyche Rd",
    "iso:country":"AU",
    "sg:address":"488 Lutwyche Rd",
    "sg:city":"Lutwyche",
    "sg:classifiers":[
        {
            "category":"Banks & Credit Unions",
            "subcategory":"Bank",
            "type":"Services"
        }
    ],
    "sg:phone":"+61 7 3866 4777",
    "sg:postcode":"4030",
    "sg:province":"QLD",
    "sg:tags":[
        "broker",
        "mortgage"
    ],
    "wof:name":"Aussie Home Loans",
    "wof:placetype":"venue"
},
  "geometry": {"coordinates":[153.03341699999999,-27.423376],"type":"Point"}
}