{
  "type": "Feature",
  "properties": {
    "addr:full":"71 Berkshire Rd Sunshine North VIC 3020",
    "addr:housenumber":"71",
    "addr:postcode":"3020",
    "addr:street":"Berkshire Rd",
    "iso:country":"AU",
    "sg:address":"71 Berkshire Rd",
    "sg:city":"Sunshine North",
    "sg:classifiers":[
        {
            "category":"Fast Food",
            "type":"Food & Drink"
        }
    ],
    "sg:phone":"+61 3 9312 5976",
    "sg:postcode":"3020",
    "sg:province":"VIC",
    "sg:tags":[
        "away",
        "take"
    ],
    "wof:name":"Tonys Tucker",
    "wof:placetype":"venue"
},
  "geometry": {"coordinates":[144.839066,-37.765305],"type":"Point"}
}