{
  "type": "Feature",
  "properties": {
    "addr:full":"23 Groom St Clifton Hill VIC 3068",
    "addr:housenumber":"23",
    "addr:postcode":"3068",
    "addr:street":"Groom St",
    "iso:country":"AU",
    "sg:address":"23 Groom St",
    "sg:city":"Clifton Hill",
    "sg:classifiers":[
        {
            "category":"Cafe",
            "type":"Food & Drink"
        }
    ],
    "sg:phone":"+61 3 9481 4798",
    "sg:postcode":"3068",
    "sg:province":"VIC",
    "wof:name":"Cafe Chill",
    "wof:placetype":"venue"
},
  "geometry": {"coordinates":[144.99818420400001,-37.7942619324],"type":"Point"}
}