{
  "type": "Feature",
  "properties": {
    "iso:country":"AU",
    "sg:address":"1 Simpson Rd",
    "sg:city":"Proserpine",
    "sg:classifiers":[
        {
            "category":"Home & Garden",
            "subcategory":"Garden Supply",
            "type":"Retail Goods"
        }
    ],
    "sg:phone":"+61 7 4947 1022",
    "sg:postcode":"4800",
    "sg:province":"QLD",
    "sg:tags":[
        "landscape"
    ],
    "wof:name":"Hillside Turf",
    "wof:placetype":"venue"
},
  "geometry": {"coordinates":[148.58497619600001,-20.30717659],"type":"Point"}
}