{
  "type": "Feature",
  "properties": {
    "addr:full":"103 Flinders La Melbourne VIC 3000",
    "addr:housenumber":"103",
    "addr:postcode":"3000",
    "addr:street":"Flinders La",
    "iso:country":"AU",
    "sg:address":"103 Flinders La",
    "sg:city":"Melbourne",
    "sg:classifiers":[
        {
            "category":"Bars & Pubs",
            "subcategory":"Wine Bar",
            "type":"Food & Drink"
        }
    ],
    "sg:phone":"+61 3 9639 8122",
    "sg:postcode":"3000",
    "sg:province":"VIC",
    "wof:name":"Cherry",
    "wof:placetype":"venue"
},
  "geometry": {"coordinates":[144.970977783,-37.8154373169],"type":"Point"}
}