{
  "type": "Feature",
  "properties": {
    "iso:country":"AU",
    "sg:address":"560 David St",
    "sg:city":"Albury",
    "sg:classifiers":[
        {
            "category":"Health Services",
            "subcategory":"Doctor",
            "type":"Services"
        }
    ],
    "sg:phone":"+61 2 6021 1590",
    "sg:postcode":"2640",
    "sg:province":"NSW",
    "sg:tags":[
        "occupational",
        "safety"
    ],
    "wof:name":"Wills Injury Management",
    "wof:placetype":"venue"
},
  "geometry": {"coordinates":[146.921417236,-36.0784187317],"type":"Point"}
}