{
  "type": "Feature",
  "properties": {
    "addr:full":"Unit 2/ 136 Balcatta Rd Balcatta WA 6021",
    "addr:housenumber":"/ 136",
    "addr:postcode":"6021",
    "addr:street":"Balcatta Rd",
    "iso:country":"AU",
    "sg:address":"Unit 2/ 136 Balcatta Rd",
    "sg:city":"Balcatta",
    "sg:classifiers":[
        {
            "category":"Building & Trades",
            "subcategory":"Construction",
            "type":"Services"
        }
    ],
    "sg:phone":"+61 8 9345 4001",
    "sg:postcode":"6021",
    "sg:province":"WA",
    "sg:tags":[
        "contractor"
    ],
    "wof:name":"Rokbuild Pty Ltd",
    "wof:placetype":"venue"
},
  "geometry": {"coordinates":[115.816383362,-31.8622283936],"type":"Point"}
}