{
  "type": "Feature",
  "properties": {
    "addr:full":"2 Taylors La Rowville VIC 3178",
    "addr:housenumber":"2",
    "addr:postcode":"3178",
    "addr:street":"Taylors La",
    "iso:country":"AU",
    "sg:address":"2 Taylors La",
    "sg:city":"Rowville",
    "sg:classifiers":[
        {
            "category":"Education",
            "subcategory":"School",
            "type":"Public Place"
        }
    ],
    "sg:phone":"+61 3 9755 4222",
    "sg:postcode":"3178",
    "sg:province":"VIC",
    "sg:tags":[
        "co-educational"
    ],
    "wof:name":"St Simons Primary",
    "wof:placetype":"venue"
},
  "geometry": {"coordinates":[145.24432373100001,-37.9265594482],"type":"Point"}
}