{
  "type": "Feature",
  "properties": {
    "iso:country":"AU",
    "sg:address":"William St",
    "sg:city":"Cabarita",
    "sg:classifiers":[
        {
            "category":"Education",
            "subcategory":"Kindergarten",
            "type":"Public Place"
        }
    ],
    "sg:phone":"+61 2 9743 4446",
    "sg:postcode":"2137",
    "sg:province":"NSW",
    "sg:tags":[
        "pre-schools"
    ],
    "wof:name":"Cabarita-Mortlake Kindergarten",
    "wof:placetype":"venue"
},
  "geometry": {"coordinates":[151.108840942,-33.8486862183],"type":"Point"}
}