{
  "type": "Feature",
  "properties": {
    "addr:full":"337 High St Golden Square VIC 3555",
    "addr:housenumber":"337",
    "addr:postcode":"3555",
    "addr:street":"High St",
    "iso:country":"AU",
    "sg:address":"337 High St",
    "sg:city":"Golden Square",
    "sg:classifiers":[
        {
            "category":"Structure",
            "subcategory":"Tunnel",
            "type":"Public Place"
        }
    ],
    "sg:phone":"+61 3 5441 7750",
    "sg:postcode":"3555",
    "sg:province":"VIC",
    "sg:tags":[
        "cleaner",
        "industrial",
        "vacuum"
    ],
    "wof:name":"Coola's Cleaning Supplies",
    "wof:placetype":"venue"
},
  "geometry": {"coordinates":[144.25448608400001,-36.7757835388],"type":"Point"}
}