{
  "type": "Feature",
  "properties": {
    "addr:full":"1 Park St Clovelly NSW 2031",
    "addr:housenumber":"1",
    "addr:postcode":"2031",
    "addr:street":"Park St",
    "iso:country":"AU",
    "sg:address":"1 Park St",
    "sg:city":"Clovelly",
    "sg:classifiers":[
        {
            "category":"Communications",
            "subcategory":"News Services",
            "type":"Services"
        }
    ],
    "sg:phone":"+61 2 9664 6819",
    "sg:postcode":"2031",
    "sg:province":"NSW",
    "sg:tags":[
        "information",
        "tourist",
        "attractions"
    ],
    "wof:name":"Sydney By Bike",
    "wof:placetype":"venue"
},
  "geometry": {"coordinates":[151.26620483400001,-33.9126663208],"type":"Point"}
}