{
  "type": "Feature",
  "properties": {
    "addr:full":"232 Mickleham Rd Tullamarine VIC 3043",
    "addr:housenumber":"232",
    "addr:postcode":"3043",
    "addr:street":"Mickleham Rd",
    "iso:country":"AU",
    "sg:address":"232 Mickleham Rd",
    "sg:city":"Tullamarine",
    "sg:classifiers":[
        {
            "category":"Health Services",
            "subcategory":"Doctor",
            "type":"Services"
        }
    ],
    "sg:phone":"+61 3 9330 2533",
    "sg:postcode":"3043",
    "sg:province":"VIC",
    "sg:tags":[
        "medical",
        "practitioner"
    ],
    "wof:name":"McCarthy Sarah Dr.",
    "wof:placetype":"venue"
},
  "geometry": {"coordinates":[144.88328552199999,-37.6849899292],"type":"Point"}
}