{
  "type": "Feature",
  "properties": {
    "addr:full":"101 Lonsdale St Dandenong VIC 3175",
    "addr:housenumber":"101",
    "addr:postcode":"3175",
    "addr:street":"Lonsdale St",
    "iso:country":"AU",
    "sg:address":"101 Lonsdale St",
    "sg:city":"Dandenong",
    "sg:classifiers":[
        {
            "category":"Autos & Motor Vehicles",
            "subcategory":"Auto Supplies",
            "type":"Retail Goods"
        }
    ],
    "sg:phone":"+61 3 9791 6322",
    "sg:postcode":"3175",
    "sg:province":"VIC",
    "sg:tags":[
        "tyre"
    ],
    "sg:website":"http://www.beaurepaires.com.au",
    "wof:name":"Beaurepaires",
    "wof:placetype":"venue"
},
  "geometry": {"coordinates":[145.21473693900001,-37.9911956787],"type":"Point"}
}