{
  "type": "Feature",
  "properties": {
    "addr:full":"9a Lackey St Summer Hill NSW 2130",
    "addr:housenumber":"9a",
    "addr:postcode":"2130",
    "addr:street":"Lackey St",
    "iso:country":"AU",
    "sg:address":"9a Lackey St",
    "sg:city":"Summer Hill",
    "sg:classifiers":[
        {
            "category":"Personal",
            "subcategory":"Beauty Salon",
            "type":"Services"
        }
    ],
    "sg:phone":"+61 2 9799 3989",
    "sg:postcode":"2130",
    "sg:province":"NSW",
    "sg:tags":[
        "hairdresser"
    ],
    "wof:name":"Absolutely Fabulous Hair Therapy",
    "wof:placetype":"venue"
},
  "geometry": {"coordinates":[151.138305664,-33.8905677795],"type":"Point"}
}