{
  "type": "Feature",
  "properties": {
    "addr:full":"51 Berkeley Rd Glenning Valley NSW 2261",
    "addr:housenumber":"51",
    "addr:postcode":"2261",
    "addr:street":"Berkeley Rd",
    "iso:country":"AU",
    "sg:address":"51 Berkeley Rd",
    "sg:city":"Glenning Valley",
    "sg:classifiers":[
        {
            "category":"Retail",
            "subcategory":"Driving School",
            "type":"Services"
        }
    ],
    "sg:phone":"+61 2 4388 9245",
    "sg:postcode":"2261",
    "sg:province":"NSW",
    "wof:name":"GAF Driving Services",
    "wof:placetype":"venue"
},
  "geometry": {"coordinates":[151.42146299999999,-33.341694],"type":"Point"}
}