{
  "type": "Feature",
  "properties": {
    "iso:country":"AU",
    "sg:address":"Unit 1/ 10 Thornley St",
    "sg:city":"Leichhardt",
    "sg:classifiers":[
        {
            "category":"Manufacturing",
            "subcategory":"Paper Products",
            "type":"Manufacturing & Wholesale Goods"
        }
    ],
    "sg:phone":"+61 418 549 996",
    "sg:postcode":"2040",
    "sg:province":"NSW",
    "sg:tags":[
        "wholesaler",
        "brassware",
        "mfrs"
    ],
    "wof:name":"Bronzeworks .com.au",
    "wof:placetype":"venue"
},
  "geometry": {"coordinates":[151.15567,-33.887444],"type":"Point"}
}