{
  "type": "Feature",
  "properties": {
    "addr:full":"69 Anderson St Yarraville VIC 3013",
    "addr:housenumber":"69",
    "addr:postcode":"3013",
    "addr:street":"Anderson St",
    "iso:country":"AU",
    "sg:address":"69 Anderson St",
    "sg:city":"Yarraville",
    "sg:classifiers":[
        {
            "category":"Personal",
            "subcategory":"Tanning Parlor",
            "type":"Services"
        }
    ],
    "sg:phone":"+61 3 9314 9878",
    "sg:postcode":"3013",
    "sg:province":"VIC",
    "sg:tags":[
        "solarium"
    ],
    "wof:name":"Body Bronze",
    "wof:placetype":"venue"
},
  "geometry": {"coordinates":[144.88778686500001,-37.8161582947],"type":"Point"}
}