{
  "type": "Feature",
  "properties": {
    "addr:full":"Unit 36, Gold Coast City Marina, 76 Waterway Drive Coomera QLD 4209",
    "addr:housenumber":"76",
    "addr:postcode":"4209",
    "addr:street":"Waterway Drive",
    "iso:country":"AU",
    "sg:address":"Unit 36, Gold Coast City Marina, 76 Waterway Drive",
    "sg:city":"Coomera",
    "sg:classifiers":[
        {
            "category":"Autos & Motor Vehicles",
            "subcategory":"Boat Sales",
            "type":"Retail Goods"
        }
    ],
    "sg:phone":"+61 7 5502 7782",
    "sg:postcode":"4209",
    "sg:province":"QLD",
    "sg:tags":[
        "equipment",
        "yacht"
    ],
    "wof:name":"Classic Marine Trimming",
    "wof:placetype":"venue"
},
  "geometry": {"coordinates":[153.331832886,-27.8310909271],"type":"Point"}
}