{
  "type": "Feature",
  "properties": {
    "addr:full":"21 Mayda St Shailer Park QLD 4128",
    "addr:housenumber":"21",
    "addr:postcode":"4128",
    "addr:street":"Mayda St",
    "iso:country":"AU",
    "sg:address":"21 Mayda St",
    "sg:city":"Shailer Park",
    "sg:classifiers":[
        {
            "category":"Real Estate",
            "subcategory":"Real Estate Agent",
            "type":"Services"
        }
    ],
    "sg:phone":"+61 7 3290 2522",
    "sg:postcode":"4128",
    "sg:province":"QLD",
    "wof:name":"Commercial Real Estate",
    "wof:placetype":"venue"
},
  "geometry": {"coordinates":[153.16412353499999,-27.6444244385],"type":"Point"}
}