{
  "type": "Feature",
  "properties": {
    "iso:country":"AU",
    "sg:address":"Suite 12/ 21 Hunter St",
    "sg:city":"Hornsby",
    "sg:classifiers":[
        {
            "category":"Health Services",
            "subcategory":"Dentist",
            "type":"Services"
        }
    ],
    "sg:phone":"+61 2 9476 2736",
    "sg:postcode":"2077",
    "sg:province":"NSW",
    "wof:name":"Treloar D C",
    "wof:placetype":"venue"
},
  "geometry": {"coordinates":[151.10047912600001,-33.7036094666],"type":"Point"}
}