{
  "type": "Feature",
  "properties": {
    "addr:full":"Foreshore St Hastings VIC 3915",
    "addr:postcode":"3915",
    "addr:street":"Foreshore St",
    "iso:country":"AU",
    "sg:address":"Foreshore St",
    "sg:city":"Hastings",
    "sg:classifiers":[
        {
            "category":"Recreation",
            "subcategory":"Sailing Club",
            "type":"Entertainment"
        }
    ],
    "sg:phone":"+61 3 5979 1891",
    "sg:postcode":"3915",
    "sg:province":"VIC",
    "sg:tags":[
        "yacht"
    ],
    "wof:name":"Hastings Yacht Club",
    "wof:placetype":"venue"
},
  "geometry": {"coordinates":[145.20962524399999,-38.3030166626],"type":"Point"}
}