{
  "type": "Feature",
  "properties": {
    "addr:full":"Shop 2, 223 Calam Rd Sunnybank Hills QLD 4109",
    "addr:housenumber":"shop 2",
    "addr:postcode":"223;4109",
    "addr:street":"Calam Rd",
    "iso:country":"AU",
    "sg:address":"Shop 2, 223 Calam Rd",
    "sg:city":"Sunnybank Hills",
    "sg:classifiers":[
        {
            "category":"Manufacturing",
            "subcategory":"Food",
            "type":"Manufacturing & Wholesale Goods"
        }
    ],
    "sg:phone":"+61 7 3273 8884",
    "sg:postcode":"4109",
    "sg:province":"QLD",
    "sg:tags":[
        "function",
        "catering"
    ],
    "wof:name":"Azu Cafe & Bistro",
    "wof:placetype":"venue"
},
  "geometry": {"coordinates":[153.054397583,-27.609708786],"type":"Point"}
}