{
  "type": "Feature",
  "properties": {
    "iso:country":"AU",
    "sg:address":"216 South St",
    "sg:city":"Beaconsfield",
    "sg:classifiers":[
        {
            "category":"Communications",
            "subcategory":"Film & Video Production",
            "type":"Services"
        }
    ],
    "sg:phone":"+61 8 9335 6522",
    "sg:postcode":"6162",
    "sg:province":"WA",
    "sg:tags":[
        "dvd",
        "library"
    ],
    "wof:name":"Starland Video",
    "wof:placetype":"venue"
},
  "geometry": {"coordinates":[115.77175099999999,-32.063236],"type":"Point"}
}