{
  "type": "Feature",
  "properties": {
    "addr:full":"University Of NSW, Gate 4, High St Kensington NSW 2033",
    "addr:housenumber":"4",
    "addr:postcode":"2033",
    "addr:street":"Gate;High St",
    "iso:country":"AU",
    "sg:address":"University Of NSW, Gate 4, High St",
    "sg:city":"Kensington",
    "sg:classifiers":[
        {
            "category":"Arts & Performance",
            "subcategory":"Theater",
            "type":"Entertainment"
        }
    ],
    "sg:phone":"+61 2 9385 7600",
    "sg:postcode":"2033",
    "sg:province":"NSW",
    "sg:tags":[
        "theatre"
    ],
    "wof:name":"Fig Tree Theatre",
    "wof:placetype":"venue"
},
  "geometry": {"coordinates":[151.220474,-33.912968],"type":"Point"}
}