{
  "type": "Feature",
  "properties": {
    "iso:country":"AU",
    "sg:address":"131 Edward St",
    "sg:city":"Ayr",
    "sg:classifiers":[
        {
            "category":"Retail",
            "subcategory":"Laundry & Dry Cleaning",
            "type":"Services"
        }
    ],
    "sg:phone":"+61 7 4783 3347",
    "sg:postcode":"4807",
    "sg:province":"QLD",
    "sg:tags":[
        "manicurist"
    ],
    "wof:name":"Kellys Perfect Touch Nailz",
    "wof:placetype":"venue"
},
  "geometry": {"coordinates":[147.40567016599999,-19.5738945007],"type":"Point"}
}