{
  "type": "Feature",
  "properties": {
    "addr:full":"65 - 67 Beach St Frankston VIC 3199",
    "addr:housenumber":"67",
    "addr:postcode":"3199",
    "addr:street":"Beach St",
    "iso:country":"AU",
    "sg:address":"65 - 67 Beach St",
    "sg:city":"Frankston",
    "sg:classifiers":[
        {
            "category":"Health Services",
            "subcategory":"Health Practitioner",
            "type":"Services"
        }
    ],
    "sg:phone":"+61 3 9781 4088",
    "sg:postcode":"3199",
    "sg:province":"VIC",
    "sg:tags":[
        "pathologist",
        "speech"
    ],
    "wof:name":"Frankston Speech Pathology Clinic",
    "wof:placetype":"venue"
},
  "geometry": {"coordinates":[144.93621826200001,-37.8419837952],"type":"Point"}
}