{
  "type": "Feature",
  "properties": {
    "addr:full":"10 Strain St Bicton WA 6157",
    "addr:housenumber":"10",
    "addr:postcode":"6157",
    "addr:street":"Strain St",
    "iso:country":"AU",
    "sg:address":"10 Strain St",
    "sg:city":"Bicton",
    "sg:classifiers":[
        {
            "category":"Professional",
            "subcategory":"Printing & Photocopies",
            "type":"Services"
        }
    ],
    "sg:phone":"+61 8 9339 4790",
    "sg:postcode":"6157",
    "sg:province":"WA",
    "sg:tags":[
        "embroidery"
    ],
    "wof:name":"Perth School Of Creative Needleart",
    "wof:placetype":"venue"
},
  "geometry": {"coordinates":[115.786247,-32.021225],"type":"Point"}
}