{
  "type": "Feature",
  "properties": {
    "addr:full":"Factory 1, 205 Abbotts Rd Dandenong South VIC 3164",
    "addr:housenumber":"205",
    "addr:postcode":"3164",
    "addr:street":"Abbotts Rd",
    "iso:country":"AU",
    "sg:address":"Factory 1, 205 Abbotts Rd",
    "sg:city":"Dandenong South",
    "sg:classifiers":[
        {
            "category":"Manufacturing",
            "subcategory":"Building Materials",
            "type":"Manufacturing & Wholesale Goods"
        }
    ],
    "sg:phone":"+61 1300 669 010",
    "sg:postcode":"3164",
    "sg:province":"VIC",
    "sg:tags":[
        "equipment",
        "handling"
    ],
    "wof:name":"BT Lift Trucks Pty Ltd",
    "wof:placetype":"venue"
},
  "geometry": {"coordinates":[145.23280334500001,-38.0339622498],"type":"Point"}
}