{
  "type": "Feature",
  "properties": {
    "addr:full":"1/ 10 Ivan St Arundel QLD 4214",
    "addr:housenumber":"/ 10",
    "addr:postcode":"4214",
    "addr:street":"Ivan St",
    "iso:country":"AU",
    "sg:address":"1/ 10 Ivan St",
    "sg:city":"Arundel",
    "sg:classifiers":[
        {
            "category":"Retail",
            "subcategory":"Repair Shop",
            "type":"Services"
        }
    ],
    "sg:phone":"+61 403 545 946",
    "sg:postcode":"4214",
    "sg:province":"QLD",
    "sg:tags":[
        "upholsterer"
    ],
    "wof:name":"Deluxe Trimming",
    "wof:placetype":"venue"
},
  "geometry": {"coordinates":[153.35932922399999,-27.9664154053],"type":"Point"}
}