{
  "type": "Feature",
  "properties": {
    "addr:full":"327 Maroubra Rd Maroubra NSW 2035",
    "addr:housenumber":"327",
    "addr:postcode":"2035",
    "addr:street":"Maroubra Rd",
    "iso:country":"AU",
    "sg:address":"327 Maroubra Rd",
    "sg:city":"Maroubra",
    "sg:classifiers":[
        {
            "category":"Professional",
            "subcategory":"Advertising",
            "type":"Services"
        }
    ],
    "sg:phone":"+61 2 9130 5042",
    "sg:postcode":"2035",
    "sg:province":"NSW",
    "sg:tags":[
        "balloon",
        "novelty"
    ],
    "wof:name":"Ballooning Around",
    "wof:placetype":"venue"
},
  "geometry": {"coordinates":[151.24746704099999,-33.9428710938],"type":"Point"}
}