{
  "type": "Feature",
  "properties": {
    "addr:full":"98 Radford Rd Reservoir VIC 3073",
    "addr:housenumber":"98",
    "addr:postcode":"3073",
    "addr:street":"Radford Rd",
    "iso:country":"AU",
    "sg:address":"98 Radford Rd",
    "sg:city":"Reservoir",
    "sg:classifiers":[
        {
            "category":"Retail",
            "subcategory":"Car Wash",
            "type":"Services"
        }
    ],
    "sg:phone":"+61 411 257 063",
    "sg:postcode":"3073",
    "sg:province":"VIC",
    "sg:tags":[
        "truck",
        "cleaning"
    ],
    "wof:name":"Supa Clean Auto Detailing",
    "wof:placetype":"venue"
},
  "geometry": {"coordinates":[144.984649658,-37.7021408081],"type":"Point"}
}