{
  "type": "Feature",
  "properties": {
    "iso:country":"AU",
    "sg:address":"PO Box 102",
    "sg:city":"Tully",
    "sg:classifiers":[
        {
            "category":"Farming",
            "subcategory":"Farm",
            "type":"Manufacturing & Wholesale Goods"
        }
    ],
    "sg:phone":"+61 7 4068 6138",
    "sg:postcode":"4854",
    "sg:province":"QLD",
    "sg:tags":[
        "farmer"
    ],
    "wof:name":"Frazer W T",
    "wof:placetype":"venue"
},
  "geometry": {"coordinates":[145.93263244600001,-17.933889389],"type":"Point"}
}