{
  "type": "Feature",
  "properties": {
    "addr:full":"18 Wridgeway Ave Burwood VIC 3125",
    "addr:housenumber":"18",
    "addr:postcode":"3125",
    "addr:street":"Wridgeway Ave",
    "iso:country":"AU",
    "sg:address":"18 Wridgeway Ave",
    "sg:city":"Burwood",
    "sg:classifiers":[
        {
            "category":"Health Services",
            "subcategory":"Dentist",
            "type":"Services"
        }
    ],
    "sg:phone":"+61 3 9808 4159",
    "sg:postcode":"3125",
    "sg:province":"VIC",
    "sg:tags":[
        "dental",
        "prosthetist"
    ],
    "wof:name":"Just Ceramics",
    "wof:placetype":"venue"
},
  "geometry": {"coordinates":[145.12086486800001,-37.8526153564],"type":"Point"}
}