{
  "type": "Feature",
  "properties": {
    "addr:full":"PO Box 660 Bundaberg QLD 4670",
    "addr:postcode":"4670",
    "iso:country":"AU",
    "sg:address":"PO Box 660",
    "sg:city":"Bundaberg",
    "sg:classifiers":[
        {
            "category":"Building & Trades",
            "subcategory":"Landscaping Services",
            "type":"Services"
        }
    ],
    "sg:phone":"+61 400 484 101",
    "sg:postcode":"4670",
    "sg:province":"QLD",
    "sg:tags":[
        "designer",
        "landscape",
        "contractor"
    ],
    "wof:name":"Exterior Magic",
    "wof:placetype":"venue"
},
  "geometry": {"coordinates":[152.34669494600001,-24.8670501709],"type":"Point"}
}