{
  "type": "Feature",
  "properties": {
    "addr:full":"53 Finch St Beechworth VIC 3747",
    "addr:housenumber":"53",
    "addr:postcode":"3747",
    "addr:street":"Finch St",
    "iso:country":"AU",
    "sg:address":"53 Finch St",
    "sg:city":"Beechworth",
    "sg:classifiers":[
        {
            "category":"Government",
            "subcategory":"Court House",
            "type":"Public Place"
        }
    ],
    "sg:phone":"+61 3 5728 2889",
    "sg:postcode":"3747",
    "sg:province":"VIC",
    "sg:tags":[
        "personal",
        "marriage",
        "family",
        "counselling"
    ],
    "wof:name":"Counselling & Education Services",
    "wof:placetype":"venue"
},
  "geometry": {"coordinates":[146.688309,-36.355118],"type":"Point"}
}