{
  "type": "Feature",
  "properties": {
    "iso:country":"AU",
    "sg:address":"654 Bourke Rd",
    "sg:city":"Camberwell",
    "sg:classifiers":[
        {
            "category":"Wholesale",
            "subcategory":"Apparel",
            "type":"Manufacturing & Wholesale Goods"
        }
    ],
    "sg:phone":"+61 3 9882 4800",
    "sg:postcode":"3124",
    "sg:province":"VIC",
    "sg:tags":[
        "wholesaler",
        "mfrs",
        "uniform"
    ],
    "wof:name":"Motto",
    "wof:placetype":"venue"
},
  "geometry": {"coordinates":[145.057373047,-37.8286972046],"type":"Point"}
}