{
  "type": "Feature",
  "properties": {
    "iso:country":"AU",
    "sg:address":"57 Patrick St",
    "sg:city":"Portland",
    "sg:classifiers":[
        {
            "category":"Building & Trades",
            "subcategory":"Cleaning & Sanitation",
            "type":"Services"
        }
    ],
    "sg:phone":"+61 3 5523 2370",
    "sg:postcode":"3305",
    "sg:province":"VIC",
    "sg:tags":[
        "window"
    ],
    "wof:name":"Portland Cleaning Service",
    "wof:placetype":"venue"
},
  "geometry": {"coordinates":[141.60859680199999,-38.3634490967],"type":"Point"}
}