{
  "type": "Feature",
  "properties": {
    "addr:full":"Showroom 7, 938 South Rd Edwardstown SA 5039",
    "addr:housenumber":"938",
    "addr:postcode":"5039",
    "addr:street":"South Rd",
    "iso:country":"AU",
    "sg:address":"Showroom 7, 938 South Rd",
    "sg:city":"Edwardstown",
    "sg:classifiers":[
        {
            "category":"Manufacturing",
            "subcategory":"Building Materials",
            "type":"Manufacturing & Wholesale Goods"
        }
    ],
    "sg:phone":"+61 1800 100 050",
    "sg:postcode":"5039",
    "sg:province":"SA",
    "sg:tags":[
        "equipment",
        "handling"
    ],
    "wof:name":"Dexion (Australia) Pty Limited",
    "wof:placetype":"venue"
},
  "geometry": {"coordinates":[138.57455444300001,-34.9913673401],"type":"Point"}
}