{
  "type": "Feature",
  "properties": {
    "addr:full":"2 Rosella Crs Old Beach TAS 7017",
    "addr:housenumber":"2",
    "addr:postcode":"7017",
    "addr:street":"Rosella Crs Old Beach",
    "iso:country":"AU",
    "sg:address":"2 Rosella Crs",
    "sg:city":"Old Beach",
    "sg:classifiers":[
        {
            "category":"Building & Trades",
            "subcategory":"Construction",
            "type":"Services"
        }
    ],
    "sg:phone":"+61 408 123 279",
    "sg:postcode":"7017",
    "sg:province":"TAS",
    "sg:tags":[
        "tennis court",
        "repair"
    ],
    "wof:name":"Hickman Holloway Constructions",
    "wof:placetype":"venue"
},
  "geometry": {"coordinates":[147.26918029800001,-42.7747497559],"type":"Point"}
}