{
  "type": "Feature",
  "properties": {
    "addr:full":"5 Lexington Ave St Clair NSW 2759",
    "addr:housenumber":"5",
    "addr:postcode":"2759",
    "addr:street":"Lexington Ave St",
    "iso:country":"AU",
    "sg:address":"5 Lexington Ave St",
    "sg:city":"Clair",
    "sg:classifiers":[
        {
            "category":"Building & Trades",
            "subcategory":"Cleaning & Sanitation",
            "type":"Services"
        }
    ],
    "sg:phone":"+61 401 000 679",
    "sg:postcode":"2759",
    "sg:province":"NSW",
    "sg:tags":[
        "industrial",
        "commercial",
        "contractor"
    ],
    "wof:name":"Platinum Commercial Cleaning Services",
    "wof:placetype":"venue"
},
  "geometry": {"coordinates":[150.80241394000001,-33.797088623],"type":"Point"}
}