{
  "type": "Feature",
  "properties": {
    "addr:full":"Brompton Rd City Beach WA 6015",
    "addr:postcode":"6015",
    "addr:street":"Brompton Rd",
    "iso:country":"AU",
    "sg:address":"Brompton Rd",
    "sg:city":"City Beach",
    "sg:classifiers":[
        {
            "category":"Education",
            "subcategory":"School",
            "type":"Public Place"
        }
    ],
    "sg:phone":"+61 8 9245 4840",
    "sg:postcode":"6015",
    "sg:province":"WA",
    "wof:name":"Holy Spirit School City Beach",
    "wof:placetype":"venue"
},
  "geometry": {"coordinates":[115.766059876,-31.9215164185],"type":"Point"}
}