{
  "type": "Feature",
  "properties": {
    "iso:country":"AU",
    "sg:address":"Shp 3/ 12",
    "sg:city":"Seaview Tce Caloundra",
    "sg:classifiers":[
        {
            "category":"Fast Food",
            "type":"Food & Drink"
        }
    ],
    "sg:phone":"+61 7 5491 3435",
    "sg:postcode":"4551",
    "sg:province":"QLD",
    "sg:tags":[
        "away",
        "take"
    ],
    "wof:name":"Fish At Moffat Beach The",
    "wof:placetype":"venue"
},
  "geometry": {"coordinates":[153.14169311500001,-26.7916259766],"type":"Point"}
}