{
  "type": "Feature",
  "properties": {
    "iso:country":"AU",
    "sg:address":"968 Anzac Pde",
    "sg:city":"Maroubra",
    "sg:classifiers":[
        {
            "category":"Personal",
            "subcategory":"Beauty Salon",
            "type":"Services"
        }
    ],
    "sg:phone":"+61 2 9349 8915",
    "sg:postcode":"2035",
    "sg:province":"NSW",
    "wof:name":"Glen Sharon Specialized Electrolysis Clinic B.A.UNSW A.A.B.TH .SCME",
    "wof:placetype":"venue"
},
  "geometry": {"coordinates":[151.24058532699999,-33.9451217651],"type":"Point"}
}