{
  "type": "Feature",
  "properties": {
    "iso:country":"AU",
    "sg:address":"612 Oxley Ave",
    "sg:city":"Scarborough",
    "sg:classifiers":[
        {
            "category":"Autos & Motor Vehicles",
            "subcategory":"Auto Supplies",
            "type":"Retail Goods"
        }
    ],
    "sg:phone":"+61 7 3880 0373",
    "sg:postcode":"4020",
    "sg:province":"QLD",
    "sg:tags":[
        "automotive",
        "stereo",
        "radio"
    ],
    "wof:name":"Qld Audio Repairs",
    "wof:placetype":"venue"
},
  "geometry": {"coordinates":[153.113785,-27.206673],"type":"Point"}
}