{
  "type": "Feature",
  "properties": {
    "iso:country":"AU",
    "sg:address":"1 Barnes St",
    "sg:city":"Tamworth",
    "sg:classifiers":[
        {
            "category":"Retail",
            "subcategory":"Auto Repair",
            "type":"Services"
        }
    ],
    "sg:phone":"+61 2 6765 5634",
    "sg:postcode":"2340",
    "sg:province":"NSW",
    "sg:tags":[
        "body",
        "motor",
        "trimmer"
    ],
    "wof:name":"Mang's Automotive Interiors",
    "wof:placetype":"venue"
},
  "geometry": {"coordinates":[150.917144775,-31.0891456604],"type":"Point"}
}