{
  "type": "Feature",
  "properties": {
    "iso:country":"AU",
    "sg:address":"Great Southern Hwy",
    "sg:city":"Broomehill",
    "sg:classifiers":[
        {
            "category":"Autos & Motor Vehicles",
            "subcategory":"Fuel & Gas Station",
            "type":"Retail Goods"
        }
    ],
    "sg:phone":"+61 8 9824 1234",
    "sg:postcode":"6318",
    "sg:province":"WA",
    "wof:name":"Shell Co Of Australia Ltd The",
    "wof:placetype":"venue"
},
  "geometry": {"coordinates":[117.63905334499999,-33.8440628052],"type":"Point"}
}