{
  "type": "Feature",
  "properties": {
    "iso:country":"AU",
    "sg:address":"212 Albert St",
    "sg:city":"Brunswick",
    "sg:classifiers":[
        {
            "category":"Professional",
            "subcategory":"Computer Services",
            "type":"Services"
        }
    ],
    "sg:phone":"+61 3 9380 1855",
    "sg:postcode":"3056",
    "sg:province":"VIC",
    "sg:tags":[
        "consultant",
        "system"
    ],
    "wof:name":"Applecations",
    "wof:placetype":"venue"
},
  "geometry": {"coordinates":[144.967285156,-37.7695541382],"type":"Point"}
}