{
  "type": "Feature",
  "properties": {
    "addr:full":"Jetty Park Fern Rd Wilson WA 6107",
    "addr:postcode":"6107",
    "addr:street":"Fern Rd",
    "iso:country":"AU",
    "sg:address":"Jetty Park Fern Rd",
    "sg:city":"Wilson",
    "sg:classifiers":[
        {
            "category":"Fast Food",
            "type":"Food & Drink"
        }
    ],
    "sg:phone":"+61 8 9451 1062",
    "sg:postcode":"6107",
    "sg:province":"WA",
    "sg:tags":[
        "away",
        "take"
    ],
    "wof:name":"Riverton Kiosk",
    "wof:placetype":"venue"
},
  "geometry": {"coordinates":[115.913887024,-32.0209922791],"type":"Point"}
}