{
  "type": "Feature",
  "properties": {
    "addr:full":"25- 29 Colley Tce Glenelg SA 5045",
    "addr:housenumber":"29",
    "addr:postcode":"5045",
    "addr:street":"Colley Tce",
    "iso:country":"AU",
    "sg:address":"25- 29 Colley Tce",
    "sg:city":"Glenelg",
    "sg:classifiers":[
        {
            "category":"Travel",
            "subcategory":"Hotels & Motels",
            "type":"Entertainment"
        }
    ],
    "sg:phone":"+61 1300 721 801",
    "sg:postcode":"5045",
    "sg:province":"SA",
    "sg:tags":[
        "accommodation"
    ],
    "wof:name":"Oaks Liberty Towers",
    "wof:placetype":"venue"
},
  "geometry": {"coordinates":[138.51246599999999,-34.97868],"type":"Point"}
}