{
  "type": "Feature",
  "properties": {
    "addr:full":"96 Sumners Rd Middle Park QLD 4074",
    "addr:housenumber":"96",
    "addr:postcode":"4074",
    "addr:street":"Sumners Rd",
    "iso:country":"AU",
    "sg:address":"96 Sumners Rd",
    "sg:city":"Middle Park",
    "sg:classifiers":[
        {
            "category":"Travel",
            "subcategory":"Hotels & Motels",
            "type":"Entertainment"
        }
    ],
    "sg:phone":"+61 7 3376 8111",
    "sg:postcode":"4074",
    "sg:province":"QLD",
    "sg:tags":[
        "pub"
    ],
    "wof:name":"Centenary Hotel",
    "wof:placetype":"venue"
},
  "geometry": {"coordinates":[152.93208313,-27.5619373322],"type":"Point"}
}