{
  "type": "Feature",
  "properties": {
    "addr:full":"Unit 1 237 Main Rd McLaren Vale SA 5171",
    "addr:housenumber":"237",
    "addr:postcode":"5171",
    "addr:street":"Main Rd",
    "iso:country":"AU",
    "sg:address":"Unit 1 237 Main Rd",
    "sg:city":"McLaren Vale",
    "sg:classifiers":[
        {
            "category":"Wholesale",
            "subcategory":"Machinery & Supplies",
            "type":"Manufacturing & Wholesale Goods"
        }
    ],
    "sg:phone":"+61 8 8323 7833",
    "sg:postcode":"5171",
    "sg:province":"SA",
    "sg:tags":[
        "agricultural"
    ],
    "wof:name":"Oliver Engineers Pty Ltd",
    "wof:placetype":"venue"
},
  "geometry": {"coordinates":[138.53028869600001,-35.2098083496],"type":"Point"}
}