{
  "type": "Feature",
  "properties": {
    "iso:country":"AU",
    "sg:address":"32 Clark St",
    "sg:city":"North Sydney",
    "sg:classifiers":[
        {
            "category":"Banks & Credit Unions",
            "subcategory":"Financial Services",
            "type":"Services"
        }
    ],
    "sg:phone":"+61 2 9676 2400",
    "sg:postcode":"2055",
    "sg:province":"NSW",
    "sg:tags":[
        "loan",
        "finance",
        "mortgage"
    ],
    "wof:name":"Flashfinance",
    "wof:placetype":"venue"
},
  "geometry": {"coordinates":[151.21452300000001,-33.840435],"type":"Point"}
}