{
  "type": "Feature",
  "properties": {
    "iso:country":"AU",
    "sg:address":"795 Thompsons Rd",
    "sg:city":"Lyndhurst",
    "sg:classifiers":[
        {
            "category":"Farming",
            "subcategory":"Livestock Farm",
            "type":"Manufacturing & Wholesale Goods"
        }
    ],
    "sg:phone":"+61 3 9799 2710",
    "sg:postcode":"3975",
    "sg:province":"VIC",
    "sg:tags":[
        "agistment"
    ],
    "wof:name":"Silverdene Warmblood Stud & Dressage Centre",
    "wof:placetype":"venue"
},
  "geometry": {"coordinates":[145.22346496599999,-38.0754318237],"type":"Point"}
}