{
  "type": "Feature",
  "properties": {
    "addr:full":"2-4 Fitzroy St Kerang VIC 3579",
    "addr:housenumber":"2-4",
    "addr:postcode":"3579",
    "addr:street":"Fitzroy St",
    "iso:country":"AU",
    "sg:address":"2-4 Fitzroy St",
    "sg:city":"Kerang",
    "sg:classifiers":[
        {
            "category":"Professional",
            "subcategory":"Accounting & Tax Preparation",
            "type":"Services"
        }
    ],
    "sg:phone":"+61 3 5452 1155",
    "sg:postcode":"3579",
    "sg:province":"VIC",
    "sg:tags":[
        "consultant",
        "taxation"
    ],
    "wof:name":"May Partners Pty Ltd",
    "wof:placetype":"venue"
},
  "geometry": {"coordinates":[143.91868591299999,-35.7349319458],"type":"Point"}
}