{
  "type": "Feature",
  "properties": {
    "addr:full":"Booth Rd Oak Valley QLD 4811",
    "addr:postcode":"4811",
    "addr:street":"Booth Rd",
    "iso:country":"AU",
    "sg:address":"Booth Rd",
    "sg:city":"Oak Valley",
    "sg:classifiers":[
        {
            "category":"Organizations",
            "subcategory":"Professional Association",
            "type":"Services"
        }
    ],
    "sg:phone":"+61 7 4778 4188",
    "sg:postcode":"4811",
    "sg:province":"QLD",
    "sg:tags":[
        "rural",
        "organisation",
        "production",
        "primary"
    ],
    "wof:name":"Livestock Transporters Association of Qld Inc",
    "wof:placetype":"venue"
},
  "geometry": {"coordinates":[146.843414,-19.414116],"type":"Point"}
}