{
  "type": "Feature",
  "properties": {
    "addr:full":"15 Kamala St Redlynch QLD 4870",
    "addr:housenumber":"15",
    "addr:postcode":"4870",
    "addr:street":"Kamala St",
    "iso:country":"AU",
    "sg:address":"15 Kamala St",
    "sg:city":"Redlynch",
    "sg:classifiers":[
        {
            "category":"Home & Garden",
            "subcategory":"Building Materials",
            "type":"Retail Goods"
        }
    ],
    "sg:phone":"+61 7 4039 3433",
    "sg:postcode":"4870",
    "sg:province":"QLD",
    "sg:tags":[
        "lawn",
        "cutting",
        "maintenance"
    ],
    "wof:name":"Lawns Limbs & Cleaning Services",
    "wof:placetype":"venue"
},
  "geometry": {"coordinates":[145.69534301799999,-16.9021453857],"type":"Point"}
}