{
  "type": "Feature",
  "properties": {
    "addr:full":"200 Gilmore Rd Queanbeyan NSW 2620",
    "addr:housenumber":"200",
    "addr:postcode":"2620",
    "addr:street":"Gilmore Rd",
    "iso:country":"AU",
    "sg:address":"200 Gilmore Rd",
    "sg:city":"Queanbeyan",
    "sg:classifiers":[
        {
            "category":"Professional",
            "type":"Services"
        }
    ],
    "sg:phone":"+61 2 6284 2544",
    "sg:postcode":"2620",
    "sg:province":"NSW",
    "sg:tags":[
        "transport"
    ],
    "wof:name":"DAS Distribution",
    "wof:placetype":"venue"
},
  "geometry": {"coordinates":[149.20631408700001,-35.3483695984],"type":"Point"}
}