{
  "type": "Feature",
  "properties": {
    "addr:full":"Shepherd St St Marys NSW 2760",
    "addr:postcode":"2760",
    "addr:street":"Shepherd St",
    "iso:country":"AU",
    "sg:address":"Shepherd St St",
    "sg:city":"Marys",
    "sg:classifiers":[
        {
            "category":"Building & Trades",
            "subcategory":"Construction",
            "type":"Services"
        }
    ],
    "sg:phone":"+61 2 9623 6748",
    "sg:postcode":"2760",
    "sg:province":"NSW",
    "sg:tags":[
        "joiner",
        "carpenter"
    ],
    "wof:name":"Celeban E",
    "wof:placetype":"venue"
},
  "geometry": {"coordinates":[150.777786255,-33.7828941345],"type":"Point"}
}