{
  "type": "Feature",
  "properties": {
    "iso:country":"AU",
    "sg:address":"50 Maribyrnong Rd",
    "sg:city":"Moonee Ponds",
    "sg:classifiers":[
        {
            "category":"Health Services",
            "subcategory":"Doctor",
            "type":"Services"
        }
    ],
    "sg:phone":"+61 3 9372 0499",
    "sg:postcode":"3039",
    "sg:province":"VIC",
    "sg:tags":[
        "medical",
        "practitioner"
    ],
    "wof:name":"Moonee Ponds Mind Body Health Centre",
    "wof:placetype":"venue"
},
  "geometry": {"coordinates":[144.923187,-37.772312],"type":"Point"}
}