{
  "type": "Feature",
  "properties": {
    "addr:full":"3 Crick St Dubbo NSW 2830",
    "addr:housenumber":"3",
    "addr:postcode":"2830",
    "addr:street":"Crick St",
    "iso:country":"AU",
    "sg:address":"3 Crick St",
    "sg:city":"Dubbo",
    "sg:classifiers":[
        {
            "category":"Professional",
            "type":"Services"
        }
    ],
    "sg:phone":"+61 2 6882 0793",
    "sg:postcode":"2830",
    "sg:province":"NSW",
    "sg:tags":[
        "industrial",
        "commercial",
        "catering"
    ],
    "wof:name":"Central West Stainless Steel",
    "wof:placetype":"venue"
},
  "geometry": {"coordinates":[148.61770629899999,-32.2395172119],"type":"Point"}
}