{
  "type": "Feature",
  "properties": {
    "addr:full":"520 Redland Bay Rd Capalaba QLD 4157",
    "addr:housenumber":"520",
    "addr:postcode":"4157",
    "addr:street":"Redland Bay Rd",
    "iso:country":"AU",
    "sg:address":"520 Redland Bay Rd",
    "sg:city":"Capalaba",
    "sg:classifiers":[
        {
            "category":"Social Services",
            "subcategory":"Adult Care",
            "type":"Services"
        }
    ],
    "sg:phone":"+61 7 3206 2217",
    "sg:postcode":"4157",
    "sg:province":"QLD",
    "sg:tags":[
        "towing"
    ],
    "wof:name":"Redlands Towing Service",
    "wof:placetype":"venue"
},
  "geometry": {"coordinates":[153.20671081500001,-27.535112381],"type":"Point"}
}