{
  "type": "Feature",
  "properties": {
    "iso:country":"AU",
    "sg:address":"5 Lewis St",
    "sg:city":"Coburg",
    "sg:classifiers":[
        {
            "category":"Manufacturing",
            "subcategory":"Glass & Minerals",
            "type":"Manufacturing & Wholesale Goods"
        }
    ],
    "sg:phone":"+61 3 9354 1171",
    "sg:postcode":"3058",
    "sg:province":"VIC",
    "sg:tags":[
        "repair",
        "fibreglass",
        "product"
    ],
    "wof:name":"Ezi-Glass Pty Ltd",
    "wof:placetype":"venue"
},
  "geometry": {"coordinates":[144.961593628,-37.7328987122],"type":"Point"}
}