{
  "type": "Feature",
  "properties": {
    "addr:full":"201 High St Willoughby NSW 2068",
    "addr:housenumber":"201",
    "addr:postcode":"2068",
    "addr:street":"High St",
    "iso:country":"AU",
    "sg:address":"201 High St",
    "sg:city":"Willoughby",
    "sg:classifiers":[
        {
            "category":"Food & Beverages",
            "subcategory":"Bakery",
            "type":"Retail Goods"
        }
    ],
    "sg:phone":"+61 2 9958 4781",
    "sg:postcode":"2068",
    "sg:province":"NSW",
    "sg:tags":[
        "baker"
    ],
    "wof:name":"Highs Bakery",
    "wof:placetype":"venue"
},
  "geometry": {"coordinates":[151.20075988799999,-33.796005249],"type":"Point"}
}