{
  "type": "Feature",
  "properties": {
    "addr:full":"3 Bonnefin Rd Hunters Hill NSW 2110",
    "addr:housenumber":"3",
    "addr:postcode":"2110",
    "addr:street":"Bonnefin Rd",
    "iso:country":"AU",
    "sg:address":"3 Bonnefin Rd",
    "sg:city":"Hunters Hill",
    "sg:classifiers":[
        {
            "category":"Manufacturing",
            "subcategory":"Wood Products",
            "type":"Manufacturing & Wholesale Goods"
        }
    ],
    "sg:phone":"+61 2 9817 4080",
    "sg:postcode":"2110",
    "sg:province":"NSW",
    "sg:tags":[
        "polisher",
        "french"
    ],
    "wof:name":"Palfrey J N & Son",
    "wof:placetype":"venue"
},
  "geometry": {"coordinates":[151.14390564000001,-33.8301887512],"type":"Point"}
}