{
  "type": "Feature",
  "properties": {
    "addr:full":"4th Floor 301 Flinders La Melbourne VIC 3000",
    "addr:housenumber":"301",
    "addr:postcode":"3000",
    "addr:street":"Flinders La",
    "iso:country":"AU",
    "sg:address":"4th Floor 301 Flinders La",
    "sg:city":"Melbourne",
    "sg:classifiers":[
        {
            "category":"Health Services",
            "subcategory":"Health Practitioner",
            "type":"Services"
        }
    ],
    "sg:phone":"+61 3 9919 1111",
    "sg:postcode":"3000",
    "sg:province":"VIC",
    "sg:tags":[
        "alternative"
    ],
    "wof:name":"Victoria University Osteopathic Medicine Clinic",
    "wof:placetype":"venue"
},
  "geometry": {"coordinates":[144.964080811,-37.8174514771],"type":"Point"}
}