{
  "type": "Feature",
  "properties": {
    "iso:country":"AU",
    "sg:address":"9 Westerway St",
    "sg:city":"Springwood",
    "sg:classifiers":[
        {
            "category":"Industrial Area",
            "type":"Public Place"
        }
    ],
    "sg:phone":"+61 7 3808 8133",
    "sg:postcode":"4127",
    "sg:province":"QLD",
    "sg:tags":[
        "floor"
    ],
    "wof:name":"Mastershield Polymer Flooring",
    "wof:placetype":"venue"
},
  "geometry": {"coordinates":[153.129562378,-27.6311683655],"type":"Point"}
}