{
  "type": "Feature",
  "properties": {
    "addr:full":"42 Allpike Rd Darlington WA 6070",
    "addr:housenumber":"42",
    "addr:postcode":"6070",
    "addr:street":"Allpike Rd",
    "iso:country":"AU",
    "sg:address":"42 Allpike Rd",
    "sg:city":"Darlington",
    "sg:classifiers":[
        {
            "category":"Professional",
            "type":"Services"
        }
    ],
    "sg:phone":"+61 428 911 795",
    "sg:postcode":"6070",
    "sg:province":"WA",
    "sg:tags":[
        "transport"
    ],
    "wof:name":"Browning Transport",
    "wof:placetype":"venue"
},
  "geometry": {"coordinates":[116.085876465,-31.9229469299],"type":"Point"}
}