{
  "type": "Feature",
  "properties": {
    "addr:full":"Level 28 MLC Centre 239 George St Brisbane QLD 4000",
    "addr:housenumber":"239",
    "addr:postcode":"4000",
    "addr:street":"George St",
    "iso:country":"AU",
    "sg:address":"Level 28 MLC Centre 239 George St",
    "sg:city":"Brisbane",
    "sg:classifiers":[
        {
            "category":"Professional",
            "subcategory":"Engineering",
            "type":"Services"
        }
    ],
    "sg:phone":"+61 7 3334 8600",
    "sg:postcode":"4000",
    "sg:province":"QLD",
    "sg:tags":[
        "installation",
        "maintenance",
        "engineer"
    ],
    "wof:name":"Transfield Maintenance",
    "wof:placetype":"venue"
},
  "geometry": {"coordinates":[153.02322387699999,-27.4703712463],"type":"Point"}
}