{
  "type": "Feature",
  "properties": {
    "iso:country":"AU",
    "sg:address":"209 Maroubra Rd",
    "sg:city":"Maroubra",
    "sg:classifiers":[
        {
            "category":"Personal",
            "type":"Services"
        }
    ],
    "sg:phone":"+61 2 9349 1197",
    "sg:postcode":"2035",
    "sg:province":"NSW",
    "sg:tags":[
        "gift"
    ],
    "wof:name":"A. Amethyst Florist",
    "wof:placetype":"venue"
},
  "geometry": {"coordinates":[151.23982238799999,-33.9417800903],"type":"Point"}
}