{
  "type": "Feature",
  "properties": {
    "iso:country":"AU",
    "sg:address":"Hugh King Drv",
    "sg:city":"Mildura",
    "sg:classifiers":[
        {
            "category":"Retail",
            "subcategory":"Event Space",
            "type":"Services"
        }
    ],
    "sg:phone":"+61 3 5023 7307",
    "sg:postcode":"3500",
    "sg:province":"VIC",
    "sg:tags":[
        "function",
        "organiser"
    ],
    "wof:name":"Mildura Lawn Tennis Club",
    "wof:placetype":"venue"
},
  "geometry": {"coordinates":[142.16571044899999,-34.1844139099],"type":"Point"}
}