{
  "type": "Feature",
  "properties": {
    "addr:full":"4/ 35 Merrigal Rd Port Macquarie NSW 2444",
    "addr:housenumber":"/ 35",
    "addr:postcode":"2444",
    "addr:street":"Merrigal Rd",
    "iso:country":"AU",
    "sg:address":"4/ 35 Merrigal Rd",
    "sg:city":"Port Macquarie",
    "sg:classifiers":[
        {
            "category":"Professional",
            "subcategory":"Art Services",
            "type":"Services"
        }
    ],
    "sg:phone":"+61 2 6581 1611",
    "sg:postcode":"2444",
    "sg:province":"NSW",
    "sg:tags":[
        "graphic",
        "designer"
    ],
    "wof:name":"Bago Graphics",
    "wof:placetype":"venue"
},
  "geometry": {"coordinates":[152.88157699999999,-31.45541],"type":"Point"}
}