{
  "type": "Feature",
  "properties": {
    "addr:full":"64 Mount Druitt Rd Mt Druitt NSW 2770",
    "addr:housenumber":"64",
    "addr:postcode":"2770",
    "addr:street":"Mount Druitt Rd",
    "iso:country":"AU",
    "sg:address":"64 Mount Druitt Rd",
    "sg:city":"Mt Druitt",
    "sg:classifiers":[
        {
            "category":"Travel",
            "subcategory":"Hotels & Motels",
            "type":"Entertainment"
        }
    ],
    "sg:phone":"+61 2 9625 8863",
    "sg:postcode":"2770",
    "sg:province":"NSW",
    "wof:name":"Mt Druitt Inn",
    "wof:placetype":"venue"
},
  "geometry": {"coordinates":[150.81185913100001,-33.7718238831],"type":"Point"}
}