{
  "type": "Feature",
  "properties": {
    "addr:full":"Exchange House Level 6 68 St Georges Tce Perth WA 6000",
    "addr:housenumber":"68",
    "addr:postcode":"6000",
    "addr:street":"St Georges Tce",
    "iso:country":"AU",
    "sg:address":"Exchange House Level 6 68 St Georges Tce",
    "sg:city":"Perth",
    "sg:classifiers":[
        {
            "category":"Health Services",
            "subcategory":"Dentist",
            "type":"Services"
        }
    ],
    "sg:phone":"+61 8 9321 7075",
    "sg:postcode":"6000",
    "sg:province":"WA",
    "wof:name":"Bartley Andrew",
    "wof:placetype":"venue"
},
  "geometry": {"coordinates":[115.85836792000001,-31.9551715851],"type":"Point"}
}