{
  "type": "Feature",
  "properties": {
    "iso:country":"AU",
    "sg:address":"Belmore River Rd",
    "sg:city":"Smithtown",
    "sg:classifiers":[
        {
            "category":"Building & Trades",
            "subcategory":"Landscaping Services",
            "type":"Services"
        }
    ],
    "sg:phone":"+61 2 6567 4393",
    "sg:postcode":"2440",
    "sg:province":"NSW",
    "sg:tags":[
        "grazier"
    ],
    "wof:name":"Fraser R E & B E",
    "wof:placetype":"venue"
},
  "geometry": {"coordinates":[152.969803,-31.117664],"type":"Point"}
}