{
  "type": "Feature",
  "properties": {
    "iso:country":"AU",
    "sg:address":"284 Anzac Ave",
    "sg:city":"Kippa-Ring",
    "sg:classifiers":[
        {
            "category":"Shopping",
            "subcategory":"Clothing, Apparel, & Fashions",
            "type":"Retail Goods"
        }
    ],
    "sg:phone":"+61 7 3284 4873",
    "sg:postcode":"4021",
    "sg:province":"QLD",
    "sg:tags":[
        "recycled",
        "clothing"
    ],
    "wof:name":"Australian Red Cross",
    "wof:placetype":"venue"
},
  "geometry": {"coordinates":[153.08644100000001,-27.226435],"type":"Point"}
}