{
  "type": "Feature",
  "properties": {
    "addr:full":"17 Conway St Lismore NSW 2480",
    "addr:housenumber":"17",
    "addr:postcode":"2480",
    "addr:street":"Conway St",
    "iso:country":"AU",
    "sg:address":"17 Conway St",
    "sg:city":"Lismore",
    "sg:classifiers":[
        {
            "category":"Health Services",
            "subcategory":"Doctor",
            "type":"Services"
        }
    ],
    "sg:phone":"+61 2 6622 3466",
    "sg:postcode":"2480",
    "sg:province":"NSW",
    "sg:tags":[
        "occupational",
        "safety"
    ],
    "wof:name":"Interact Injury Management",
    "wof:placetype":"venue"
},
  "geometry": {"coordinates":[153.31541442899999,-28.8146877289],"type":"Point"}
}