{
  "type": "Feature",
  "properties": {
    "iso:country":"AU",
    "sg:address":"8/3 Roma Rd",
    "sg:city":"Valentine",
    "sg:classifiers":[
        {
            "category":"Sports & Exercise",
            "subcategory":"Gym",
            "type":"Entertainment"
        }
    ],
    "sg:phone":"+61 2 4946 1551",
    "sg:postcode":"2280",
    "sg:province":"NSW",
    "sg:tags":[
        "personal",
        "trainer",
        "fitness"
    ],
    "wof:name":"Paul Fyvie: Personal Trainer",
    "wof:placetype":"venue"
},
  "geometry": {"coordinates":[151.635375977,-33.014465332],"type":"Point"}
}