{
  "type": "Feature",
  "properties": {
    "addr:full":"471 Oxley Rd Sherwood QLD 4075",
    "addr:housenumber":"471",
    "addr:postcode":"4075",
    "addr:street":"Oxley Rd",
    "iso:country":"AU",
    "sg:address":"471 Oxley Rd",
    "sg:city":"Sherwood",
    "sg:classifiers":[
        {
            "category":"Professional",
            "subcategory":"Accounting & Tax Preparation",
            "type":"Services"
        }
    ],
    "sg:phone":"+61 7 3379 1284",
    "sg:postcode":"4075",
    "sg:province":"QLD",
    "sg:tags":[
        "consultant",
        "taxation"
    ],
    "wof:name":"ITP Income Tax Professionals",
    "wof:placetype":"venue"
},
  "geometry": {"coordinates":[152.98298645,-27.5315742493],"type":"Point"}
}