{
  "type": "Feature",
  "properties": {
    "iso:country":"AU",
    "sg:address":"Lot 4, Jones Rd",
    "sg:city":"Morwell",
    "sg:classifiers":[
        {
            "category":"Wholesale",
            "subcategory":"Metals & Minerals",
            "type":"Manufacturing & Wholesale Goods"
        }
    ],
    "sg:phone":"+61 3 5134 6266",
    "sg:postcode":"3840",
    "sg:province":"VIC",
    "sg:tags":[
        "steel",
        "merchant"
    ],
    "wof:name":"Smorgon Steel Distribution",
    "wof:placetype":"venue"
},
  "geometry": {"coordinates":[146.447433472,-38.2365188599],"type":"Point"}
}