{
  "type": "Feature",
  "properties": {
    "iso:country":"AU",
    "sg:address":"17 Wetherill St South",
    "sg:city":"Lidcombe",
    "sg:classifiers":[
        {
            "category":"Manufacturing",
            "subcategory":"Tobacco Products",
            "type":"Manufacturing & Wholesale Goods"
        }
    ],
    "sg:phone":"+61 2 9648 0011",
    "sg:postcode":"2141",
    "sg:province":"NSW",
    "sg:tags":[
        "car",
        "truck",
        "cleaning",
        "equipment"
    ],
    "wof:name":"S B N Car Detailing",
    "wof:placetype":"venue"
},
  "geometry": {"coordinates":[151.045455933,-33.8447914124],"type":"Point"}
}