{
  "type": "Feature",
  "properties": {
    "addr:full":"Shop 1 375 The Entrance Rd Erina NSW 2250",
    "addr:housenumber":"shop 1 375",
    "addr:postcode":"2250",
    "addr:street":"The Entrance Rd",
    "iso:country":"AU",
    "sg:address":"Shop 1 375 The Entrance Rd",
    "sg:city":"Erina",
    "sg:classifiers":[
        {
            "category":"Food & Beverages",
            "subcategory":"Liquor & Beverages",
            "type":"Retail Goods"
        }
    ],
    "sg:phone":"+61 2 4365 4255",
    "sg:postcode":"2250",
    "sg:province":"NSW",
    "sg:tags":[
        "store"
    ],
    "wof:name":"Erina Heights Cellars",
    "wof:placetype":"venue"
},
  "geometry": {"coordinates":[151.42930602999999,-33.4240150452],"type":"Point"}
}