{
  "type": "Feature",
  "properties": {
    "iso:country":"AU",
    "sg:address":"Shop 14B, Logan Central Plaza 38-74 Wembley Rd",
    "sg:city":"Logan Central",
    "sg:classifiers":[
        {
            "category":"Shopping",
            "subcategory":"Clothing, Apparel, & Fashions",
            "type":"Retail Goods"
        }
    ],
    "sg:phone":"+61 7 3299 3690",
    "sg:postcode":"4114",
    "sg:province":"QLD",
    "sg:tags":[
        "accessory"
    ],
    "wof:name":"Style 66",
    "wof:placetype":"venue"
},
  "geometry": {"coordinates":[153.11012268100001,-27.6415176392],"type":"Point"}
}