{
  "type": "Feature",
  "properties": {
    "iso:country":"AU",
    "sg:address":"18 Lismore Ave",
    "sg:city":"Dee Why",
    "sg:classifiers":[
        {
            "category":"Professional",
            "subcategory":"Secretarial Services",
            "type":"Services"
        }
    ],
    "sg:phone":"+61 2 9972 0263",
    "sg:postcode":"2099",
    "sg:province":"NSW",
    "sg:tags":[
        "typing"
    ],
    "wof:name":"Friendly Secretarial Services",
    "wof:placetype":"venue"
},
  "geometry": {"coordinates":[151.288406372,-33.7472457886],"type":"Point"}
}