{
  "type": "Feature",
  "properties": {
    "addr:full":"Shop 37 Unit 16 Vermonth South Shopng Cntr, Cnr Burwood Hwy & Hanover Rd Vermont South VIC 3133",
    "addr:housenumber":"shop;16",
    "addr:postcode":"3133",
    "addr:street":"Vermonth South Shopng Cntr Cnr Burwood Hwy & Hanover Rd",
    "iso:country":"AU",
    "sg:address":"Shop 37 Unit 16 Vermonth South Shopng Cntr, Cnr Burwood Hwy & Hanover Rd",
    "sg:city":"Vermont South",
    "sg:classifiers":[
        {
            "category":"Health Services",
            "subcategory":"Optometrist",
            "type":"Services"
        }
    ],
    "sg:phone":"+61 3 9802 4407",
    "sg:postcode":"3133",
    "sg:province":"VIC",
    "wof:name":"Merringtons Optometrists",
    "wof:placetype":"venue"
},
  "geometry": {"coordinates":[145.18536376899999,-37.8566627502],"type":"Point"}
}