{
  "type": "Feature",
  "properties": {
    "iso:country":"AU",
    "sg:address":"275 Hyde St",
    "sg:city":"Yarraville",
    "sg:classifiers":[
        {
            "category":"Shopping",
            "subcategory":"Mobile Phones",
            "type":"Retail Goods"
        }
    ],
    "sg:phone":"+61 3 9689 8822",
    "sg:postcode":"3013",
    "sg:province":"VIC",
    "sg:tags":[
        "telephone",
        "accessory"
    ],
    "wof:name":"C & A Tele-Communications",
    "wof:placetype":"venue"
},
  "geometry": {"coordinates":[144.89610290499999,-37.8213691711],"type":"Point"}
}