{
  "type": "Feature",
  "properties": {
    "addr:full":"89 Glebe Point Rd Glebe NSW 2037",
    "addr:housenumber":"89",
    "addr:postcode":"2037",
    "addr:street":"Glebe Point Rd",
    "iso:country":"AU",
    "sg:address":"89 Glebe Point Rd",
    "sg:city":"Glebe",
    "sg:classifiers":[
        {
            "category":"Fast Food",
            "type":"Food & Drink"
        }
    ],
    "sg:phone":"+61 2 9692 9784",
    "sg:postcode":"2037",
    "sg:province":"NSW",
    "sg:tags":[
        "away",
        "take"
    ],
    "wof:name":"Ecco La Pasta",
    "wof:placetype":"venue"
},
  "geometry": {"coordinates":[151.19042968799999,-33.8824386597],"type":"Point"}
}