{
  "type": "Feature",
  "properties": {
    "addr:full":"3 / 13 Tradelink Rd Browns Plains QLD 4118",
    "addr:housenumber":"/ 13",
    "addr:postcode":"4118",
    "addr:street":"Tradelink Rd",
    "iso:country":"AU",
    "sg:address":"3 / 13 Tradelink Rd",
    "sg:city":"Browns Plains",
    "sg:classifiers":[
        {
            "category":"Retail",
            "subcategory":"Auto Repair",
            "type":"Services"
        }
    ],
    "sg:phone":"+61 7 3800 9400",
    "sg:postcode":"4118",
    "sg:province":"QLD",
    "sg:tags":[
        "repairer",
        "motor",
        "engineer"
    ],
    "wof:name":"Toyo Serv",
    "wof:placetype":"venue"
},
  "geometry": {"coordinates":[153.03408813499999,-27.6648254395],"type":"Point"}
}