{
  "type": "Feature",
  "properties": {
    "iso:country":"AU",
    "sg:address":"Karinie St",
    "sg:city":"Swan Hill",
    "sg:classifiers":[
        {
            "category":"Home & Garden",
            "subcategory":"Building Materials",
            "type":"Retail Goods"
        }
    ],
    "sg:phone":"+61 3 5032 9322",
    "sg:postcode":"3585",
    "sg:province":"NSW",
    "sg:tags":[
        "fitting",
        "door"
    ],
    "wof:name":"Dahlsens Swan Hill",
    "wof:placetype":"venue"
},
  "geometry": {"coordinates":[143.553604,-35.327419],"type":"Point"}
}