{
  "type": "Feature",
  "properties": {
    "iso:country":"AU",
    "sg:address":"G7/ 2 Beattie St",
    "sg:city":"Balmain",
    "sg:classifiers":[
        {
            "category":"Social Services",
            "subcategory":"Adult Care",
            "type":"Services"
        }
    ],
    "sg:phone":"+61 1300 767 616",
    "sg:postcode":"2041",
    "sg:province":"NSW",
    "sg:tags":[
        "aged"
    ],
    "wof:name":"Doctors Safety Line",
    "wof:placetype":"venue"
},
  "geometry": {"coordinates":[151.180771,-33.857929],"type":"Point"}
}