{
  "type": "Feature",
  "properties": {
    "addr:full":"253 Crown St Darlinghurst NSW 2010",
    "addr:housenumber":"253",
    "addr:postcode":"2010",
    "addr:street":"Crown St",
    "iso:country":"AU",
    "sg:address":"253 Crown St",
    "sg:city":"Darlinghurst",
    "sg:classifiers":[
        {
            "category":"Food & Beverages",
            "subcategory":"Fruits & Vegetables",
            "type":"Retail Goods"
        }
    ],
    "sg:phone":"+61 2 9357 6690",
    "sg:postcode":"2010",
    "sg:province":"NSW",
    "sg:tags":[
        "consultant",
        "catering"
    ],
    "wof:name":"The Goods Organic",
    "wof:placetype":"venue"
},
  "geometry": {"coordinates":[151.214935303,-33.8798789978],"type":"Point"}
}