{
  "type": "Feature",
  "properties": {
    "iso:country":"AU",
    "sg:address":"91 Coventry St",
    "sg:city":"South Melbourne",
    "sg:classifiers":[
        {
            "category":"Fast Food",
            "type":"Food & Drink"
        }
    ],
    "sg:phone":"+61 3 9690 7571",
    "sg:postcode":"3205",
    "sg:province":"VIC",
    "sg:tags":[
        "away",
        "take"
    ],
    "wof:name":"The Gables Food Bar",
    "wof:placetype":"venue"
},
  "geometry": {"coordinates":[144.954056,-37.832985],"type":"Point"}
}