{
  "type": "Feature",
  "properties": {
    "addr:full":"21 Tecoma St Southport QLD 4215",
    "addr:housenumber":"21",
    "addr:postcode":"4215",
    "addr:street":"Tecoma St",
    "iso:country":"AU",
    "sg:address":"21 Tecoma St",
    "sg:city":"Southport",
    "sg:classifiers":[
        {
            "category":"Building & Trades",
            "subcategory":"Construction",
            "type":"Services"
        }
    ],
    "sg:phone":"+61 7 5571 1915",
    "sg:postcode":"4215",
    "sg:province":"QLD",
    "sg:tags":[
        "fencing",
        "contractor"
    ],
    "sg:website":"http://www.exclusiveglass.com.au",
    "wof:name":"Exclusive Glass Pool Fencing",
    "wof:placetype":"venue"
},
  "geometry": {"coordinates":[153.39552307100001,-27.9902439117],"type":"Point"}
}