{
  "type": "Feature",
  "properties": {
    "addr:full":"Shop 4/ 495 Dean St Albury NSW 2640",
    "addr:housenumber":"shop 4 / 495",
    "addr:postcode":"2640",
    "addr:street":"Dean St",
    "iso:country":"AU",
    "sg:address":"Shop 4/ 495 Dean St",
    "sg:city":"Albury",
    "sg:classifiers":[
        {
            "category":"Arena",
            "subcategory":"Horse Racetrack",
            "type":"Entertainment"
        }
    ],
    "sg:phone":"+61 2 6021 7998",
    "sg:postcode":"2640",
    "sg:province":"NSW",
    "sg:tags":[
        "retail",
        "swimwear"
    ],
    "wof:name":"Robisons Sports & Leisurewear",
    "wof:placetype":"venue"
},
  "geometry": {"coordinates":[146.91215515100001,-36.0803718567],"type":"Point"}
}