{
  "type": "Feature",
  "properties": {
    "addr:full":"2/ 12 Aileen Ave Heidelberg VIC 3084",
    "addr:housenumber":"/ 12",
    "addr:postcode":"3084",
    "addr:street":"Aileen Ave",
    "iso:country":"AU",
    "sg:address":"2/ 12 Aileen Ave",
    "sg:city":"Heidelberg",
    "sg:classifiers":[
        {
            "category":"Arts & Performance",
            "subcategory":"Art Gallery",
            "type":"Entertainment"
        }
    ],
    "sg:phone":"+61 3 9458 5911",
    "sg:postcode":"3084",
    "sg:province":"VIC",
    "wof:name":"Red River Gallery",
    "wof:placetype":"venue"
},
  "geometry": {"coordinates":[145.052825928,-37.730846405],"type":"Point"}
}