{
  "type": "Feature",
  "properties": {
    "iso:country":"AU",
    "sg:address":"1922 Albany Hwy",
    "sg:city":"Maddington",
    "sg:classifiers":[
        {
            "category":"Autos & Motor Vehicles",
            "subcategory":"Auto Supplies",
            "type":"Retail Goods"
        }
    ],
    "sg:phone":"+61 8 9452 2017",
    "sg:postcode":"6109",
    "sg:province":"WA",
    "sg:tags":[
        "camper-trailers",
        "caravan",
        "equipment"
    ],
    "sg:website":"http://www.freedomcaravans.com.au",
    "wof:name":"Freedom Caravans",
    "wof:placetype":"venue"
},
  "geometry": {"coordinates":[115.98516082800001,-32.0516242981],"type":"Point"}
}