{
  "type": "Feature",
  "properties": {
    "addr:full":"164 Invermay Rd Invermay TAS 7248",
    "addr:housenumber":"164",
    "addr:postcode":"7248",
    "addr:street":"Invermay Rd",
    "iso:country":"AU",
    "sg:address":"164 Invermay Rd",
    "sg:city":"Invermay",
    "sg:classifiers":[
        {
            "category":"Industrial Area",
            "type":"Public Place"
        }
    ],
    "sg:phone":"+61 3 6326 4666",
    "sg:postcode":"7248",
    "sg:province":"TAS",
    "sg:tags":[
        "protective",
        "clothing"
    ],
    "wof:name":"BOC",
    "wof:placetype":"venue"
},
  "geometry": {"coordinates":[147.13287353499999,-41.411857605],"type":"Point"}
}