{
  "type": "Feature",
  "properties": {
    "addr:full":"44b Guthrie St Osborne Park WA 6017",
    "addr:housenumber":"44b",
    "addr:postcode":"6017",
    "addr:street":"Guthrie St",
    "iso:country":"AU",
    "sg:address":"44b Guthrie St",
    "sg:city":"Osborne Park",
    "sg:classifiers":[
        {
            "category":"Retail",
            "subcategory":"Auto Repair",
            "type":"Services"
        }
    ],
    "sg:phone":"+61 8 9446 4744",
    "sg:postcode":"6017",
    "sg:province":"WA",
    "sg:tags":[
        "beater",
        "painter",
        "panel"
    ],
    "wof:name":"E & W Lawrence (1981) Pty Ltd",
    "wof:placetype":"venue"
},
  "geometry": {"coordinates":[115.81301879900001,-31.9034748077],"type":"Point"}
}