{
  "type": "Feature",
  "properties": {
    "iso:country":"AU",
    "sg:address":"191 Carp St",
    "sg:city":"Bega",
    "sg:classifiers":[
        {
            "category":"Shopping",
            "subcategory":"Clothing, Apparel, & Fashions",
            "type":"Retail Goods"
        }
    ],
    "sg:phone":"+61 2 6492 1517",
    "sg:postcode":"2550",
    "sg:province":"NSW",
    "sg:tags":[
        "accessory"
    ],
    "wof:name":"2 Sassy Boutique",
    "wof:placetype":"venue"
},
  "geometry": {"coordinates":[149.84515380900001,-36.6743392944],"type":"Point"}
}