{
  "type": "Feature",
  "properties": {
    "addr:full":"PO Box 288 Epping Private Boxes NSW 1710",
    "addr:postcode":"1710",
    "addr:street":"Epping",
    "iso:country":"AU",
    "sg:address":"PO Box 288",
    "sg:city":"Epping Private Boxes",
    "sg:classifiers":[
        {
            "category":"Bars & Pubs",
            "subcategory":"Biergarten",
            "type":"Food & Drink"
        }
    ],
    "sg:phone":"+61 2 9832 4366",
    "sg:postcode":"1710",
    "sg:province":"NSW",
    "sg:tags":[
        "eucalyptus",
        "oil",
        "tree",
        "essential",
        "tea"
    ],
    "wof:name":"Bush Treat",
    "wof:placetype":"venue"
},
  "geometry": {"coordinates":[151.08236694300001,-33.7725486755],"type":"Point"}
}