{
  "type": "Feature",
  "properties": {
    "iso:country":"AU",
    "sg:address":"148 Queen St St",
    "sg:city":"Marys",
    "sg:classifiers":[
        {
            "category":"Personal",
            "subcategory":"Beauty Salon",
            "type":"Services"
        }
    ],
    "sg:phone":"+61 2 9623 5613",
    "sg:postcode":"2760",
    "sg:province":"NSW",
    "sg:tags":[
        "hairdresser"
    ],
    "wof:name":"Magic Touch Hair Design St Marys",
    "wof:placetype":"venue"
},
  "geometry": {"coordinates":[150.77413940400001,-33.7670669556],"type":"Point"}
}