{
  "type": "Feature",
  "properties": {
    "iso:country":"AU",
    "sg:address":"17 Headland Rd",
    "sg:city":"Arrawarra Headland",
    "sg:classifiers":[
        {
            "category":"Utilities",
            "subcategory":"Electric",
            "type":"Services"
        }
    ],
    "sg:phone":"+61 2 6654 0364",
    "sg:postcode":"2456",
    "sg:province":"NSW",
    "sg:tags":[
        "electrical",
        "contractor"
    ],
    "wof:name":"Swan T.W",
    "wof:placetype":"venue"
},
  "geometry": {"coordinates":[153.201904,-30.06806],"type":"Point"}
}