{
  "type": "Feature",
  "properties": {
    "addr:full":"Humpty Back Rd McLeans Ridges NSW 2480",
    "addr:postcode":"2480",
    "addr:street":"Back Rd",
    "iso:country":"AU",
    "sg:address":"Humpty Back Rd",
    "sg:city":"McLeans Ridges",
    "sg:classifiers":[
        {
            "category":"Building & Trades",
            "subcategory":"Landscaping Services",
            "type":"Services"
        }
    ],
    "sg:phone":"+61 2 6628 0936",
    "sg:postcode":"2480",
    "sg:province":"NSW",
    "sg:tags":[
        "designer",
        "landscape",
        "contractor"
    ],
    "wof:name":"Amaroo Wholesale Nursery",
    "wof:placetype":"venue"
},
  "geometry": {"coordinates":[153.40266418499999,-28.7925109863],"type":"Point"}
}