{
  "type": "Feature",
  "properties": {
    "iso:country":"AU",
    "sg:address":"105 River St",
    "sg:city":"Maclean",
    "sg:classifiers":[
        {
            "category":"Home & Garden",
            "subcategory":"Building Materials",
            "type":"Retail Goods"
        }
    ],
    "sg:phone":"+61 2 6645 2100",
    "sg:postcode":"2463",
    "sg:province":"NSW",
    "sg:tags":[
        "shutter",
        "roller",
        "grille"
    ],
    "wof:name":"Big River Garage Doors",
    "wof:placetype":"venue"
},
  "geometry": {"coordinates":[153.20562744099999,-29.4455890656],"type":"Point"}
}