{
  "type": "Feature",
  "properties": {
    "addr:full":"Cnr Cribb St & Maleny Rd Landsborough QLD 4550",
    "addr:postcode":"4550",
    "addr:street":"Cnr Cribb St & Maleny Rd",
    "iso:country":"AU",
    "sg:address":"Cnr Cribb St & Maleny Rd",
    "sg:city":"Landsborough",
    "sg:classifiers":[
        {
            "category":"Fast Food",
            "type":"Food & Drink"
        }
    ],
    "sg:phone":"+61 7 5494 1349",
    "sg:postcode":"4550",
    "sg:province":"QLD",
    "sg:tags":[
        "away",
        "take"
    ],
    "wof:name":"Mellum Munchies",
    "wof:placetype":"venue"
},
  "geometry": {"coordinates":[152.96571350100001,-26.8085289001],"type":"Point"}
}