{
  "type": "Feature",
  "properties": {
    "iso:country":"AU",
    "sg:address":"PO Box 256",
    "sg:city":"Beaudesert",
    "sg:classifiers":[
        {
            "category":"Professional",
            "subcategory":"Business Services",
            "type":"Services"
        }
    ],
    "sg:phone":"+61 7 5541 4355",
    "sg:postcode":"4285",
    "sg:province":"QLD",
    "sg:tags":[
        "consultant",
        "promoter",
        "entertainment"
    ],
    "wof:name":"Beaudesert Country & Horse Festival",
    "wof:placetype":"venue"
},
  "geometry": {"coordinates":[152.995819,-27.98781],"type":"Point"}
}