{
  "type": "Feature",
  "properties": {
    "addr:full":"PO Box 6018 Halifax St Adelaide SA 5001",
    "addr:postcode":"5001",
    "addr:street":"St",
    "iso:country":"AU",
    "sg:address":"PO Box 6018 Halifax St",
    "sg:city":"Adelaide",
    "sg:classifiers":[
        {
            "category":"Professional",
            "subcategory":"Detective & Security Services",
            "type":"Services"
        }
    ],
    "sg:phone":"+61 8 8352 4333",
    "sg:postcode":"5001",
    "sg:province":"SA",
    "sg:tags":[
        "investigator"
    ],
    "wof:name":"Precise Investigations",
    "wof:placetype":"venue"
},
  "geometry": {"coordinates":[138.599731445,-34.9257698059],"type":"Point"}
}