{
  "type": "Feature",
  "properties": {
    "iso:country":"AU",
    "sg:address":"2 Prindiville Drv",
    "sg:city":"Wangara",
    "sg:classifiers":[
        {
            "category":"Professional",
            "subcategory":"Accounting & Tax Preparation",
            "type":"Services"
        }
    ],
    "sg:phone":"+61 8 9309 3580",
    "sg:postcode":"6065",
    "sg:province":"WA",
    "sg:tags":[
        "consultant",
        "taxation"
    ],
    "wof:name":"Block H & R",
    "wof:placetype":"venue"
},
  "geometry": {"coordinates":[115.81417083700001,-31.7913589478],"type":"Point"}
}