{
  "type": "Feature",
  "properties": {
    "addr:full":"314 Albany Hwy Albany WA 6330",
    "addr:housenumber":"314",
    "addr:postcode":"6330",
    "addr:street":"Albany Hwy",
    "iso:country":"AU",
    "sg:address":"314 Albany Hwy",
    "sg:city":"Albany",
    "sg:classifiers":[
        {
            "category":"Travel",
            "subcategory":"Hotels & Motels",
            "type":"Entertainment"
        }
    ],
    "sg:phone":"+61 8 9841 2911",
    "sg:postcode":"6330",
    "sg:province":"WA",
    "wof:name":"Ace Motor Inn",
    "wof:placetype":"venue"
},
  "geometry": {"coordinates":[117.8670578,-35.0049133301],"type":"Point"}
}