{
  "type": "Feature",
  "properties": {
    "addr:full":"7 Macauley St Leichhardt NSW 2040",
    "addr:housenumber":"7",
    "addr:postcode":"2040",
    "addr:street":"Macauley St",
    "iso:country":"AU",
    "sg:address":"7 Macauley St",
    "sg:city":"Leichhardt",
    "sg:classifiers":[
        {
            "category":"Real Estate",
            "subcategory":"Architect",
            "type":"Services"
        }
    ],
    "sg:phone":"+61 407 973 733",
    "sg:postcode":"2040",
    "sg:province":"NSW",
    "wof:name":"One Plus Pty Ltd",
    "wof:placetype":"venue"
},
  "geometry": {"coordinates":[151.156296,-33.880817],"type":"Point"}
}