{
  "type": "Feature",
  "properties": {
    "iso:country":"AU",
    "sg:address":"13 West St",
    "sg:city":"Forster",
    "sg:classifiers":[
        {
            "category":"Health Services",
            "subcategory":"Health Practitioner",
            "type":"Services"
        }
    ],
    "sg:phone":"+61 2 6554 6556",
    "sg:postcode":"2428",
    "sg:province":"NSW",
    "sg:tags":[
        "physiotherapist"
    ],
    "wof:name":"Robertson Janet",
    "wof:placetype":"venue"
},
  "geometry": {"coordinates":[152.513992,-32.180382],"type":"Point"}
}