{
  "type": "Feature",
  "properties": {
    "addr:full":"71 Oxford St Smithfield NSW 2164",
    "addr:housenumber":"71",
    "addr:postcode":"2164",
    "addr:street":"Oxford St",
    "iso:country":"AU",
    "sg:address":"71 Oxford St",
    "sg:city":"Smithfield",
    "sg:classifiers":[
        {
            "category":"Social Services",
            "subcategory":"Child Care",
            "type":"Services"
        }
    ],
    "sg:phone":"+61 2 9604 0226",
    "sg:postcode":"2164",
    "sg:province":"NSW",
    "wof:name":"Smithfield Child Care Centre",
    "wof:placetype":"venue"
},
  "geometry": {"coordinates":[150.93977355999999,-33.8559455872],"type":"Point"}
}