{
  "type": "Feature",
  "properties": {
    "addr:full":"9 Leanyer Drv Leanyer NT 0812",
    "addr:housenumber":"9",
    "addr:postcode":"nt 0812",
    "addr:street":"Leanyer Drv",
    "iso:country":"AU",
    "sg:address":"9 Leanyer Drv",
    "sg:city":"Leanyer",
    "sg:classifiers":[
        {
            "category":"Health Services",
            "subcategory":"Doctor",
            "type":"Services"
        }
    ],
    "sg:phone":"+61 8 8927 7756",
    "sg:postcode":"0812",
    "sg:province":"NT",
    "sg:tags":[
        "medical",
        "practitioner"
    ],
    "wof:name":"Glynatsis Philip",
    "wof:placetype":"venue"
},
  "geometry": {"coordinates":[130.89541600000001,-12.377002],"type":"Point"}
}