{
  "type": "Feature",
  "properties": {
    "addr:full":"126 Olympic Pde Kangaroo Flat VIC 3555",
    "addr:housenumber":"126",
    "addr:postcode":"3555",
    "addr:street":"Olympic Pde",
    "iso:country":"AU",
    "sg:address":"126 Olympic Pde",
    "sg:city":"Kangaroo Flat",
    "sg:classifiers":[
        {
            "category":"Arena",
            "subcategory":"Bull Ring",
            "type":"Entertainment"
        }
    ],
    "sg:phone":"+61 3 5447 8156",
    "sg:postcode":"3555",
    "sg:province":"VIC",
    "sg:tags":[
        "club",
        "bushwalking"
    ],
    "wof:name":"Bendigo Outdoor Club Inc",
    "wof:placetype":"venue"
},
  "geometry": {"coordinates":[144.230865478,-36.7836036682],"type":"Point"}
}