{
  "type": "Feature",
  "properties": {
    "addr:full":"20 McClean St Goondiwindi QLD 4390",
    "addr:housenumber":"20",
    "addr:postcode":"4390",
    "addr:street":"Mcclean St",
    "iso:country":"AU",
    "sg:address":"20 McClean St",
    "sg:city":"Goondiwindi",
    "sg:classifiers":[
        {
            "category":"Autos & Motor Vehicles",
            "subcategory":"Automobile Sales",
            "type":"Retail Goods"
        }
    ],
    "sg:phone":"+61 7 4671 3044",
    "sg:postcode":"4390",
    "sg:province":"QLD",
    "sg:tags":[
        "car",
        "new"
    ],
    "wof:name":"Nissan",
    "wof:placetype":"venue"
},
  "geometry": {"coordinates":[150.307907105,-28.5460567474],"type":"Point"}
}