{
  "type": "Feature",
  "properties": {
    "iso:country":"AU",
    "sg:address":"17 Mayne St",
    "sg:city":"North Rothbury",
    "sg:classifiers":[
        {
            "category":"Home & Garden",
            "subcategory":"Building Materials",
            "type":"Retail Goods"
        }
    ],
    "sg:phone":"+61 2 4938 1167",
    "sg:postcode":"2335",
    "sg:province":"NSW",
    "sg:tags":[
        "retaining",
        "wall"
    ],
    "wof:name":"Graham Duncan Concreting",
    "wof:placetype":"venue"
},
  "geometry": {"coordinates":[151.34669494600001,-32.6823425293],"type":"Point"}
}