{
  "type": "Feature",
  "properties": {
    "addr:full":"Un 1/ 77 Connells Point Rd South Hurstville NSW 2221",
    "addr:housenumber":"77",
    "addr:postcode":"2221",
    "addr:street":"Connells Point Rd",
    "iso:country":"AU",
    "sg:address":"Un 1/ 77 Connells Point Rd",
    "sg:city":"South Hurstville",
    "sg:classifiers":[
        {
            "category":"Health Services",
            "subcategory":"Dentist",
            "type":"Services"
        }
    ],
    "sg:phone":"+61 2 9547 0400",
    "sg:postcode":"2221",
    "sg:province":"NSW",
    "sg:tags":[
        "dental",
        "prosthetist"
    ],
    "wof:name":"Denture Creations Pty Ltd",
    "wof:placetype":"venue"
},
  "geometry": {"coordinates":[151.10394287099999,-33.9787254333],"type":"Point"}
}