{
  "type": "Feature",
  "properties": {
    "iso:country":"AU",
    "sg:address":"10 Hansen Crt",
    "sg:city":"Deeragun",
    "sg:classifiers":[
        {
            "category":"Utilities",
            "subcategory":"Telephone",
            "type":"Services"
        }
    ],
    "sg:phone":"+61 7 4751 5522",
    "sg:postcode":"4818",
    "sg:province":"QLD",
    "sg:tags":[
        "installation",
        "system",
        "maintenance"
    ],
    "wof:name":"Vatsonic Communications Pty Ltd",
    "wof:placetype":"venue"
},
  "geometry": {"coordinates":[146.668396,-19.24402],"type":"Point"}
}