{
  "type": "Feature",
  "properties": {
    "iso:country":"AU",
    "sg:address":"505 Brooking Rd",
    "sg:city":"Mahogany Creek",
    "sg:classifiers":[
        {
            "category":"Social Services",
            "subcategory":"Child Care",
            "type":"Services"
        }
    ],
    "sg:phone":"+61 8 9298 8336",
    "sg:postcode":"6072",
    "sg:province":"WA",
    "wof:name":"Mundaring Child Care Centre",
    "wof:placetype":"venue"
},
  "geometry": {"coordinates":[116.13043999999999,-31.90074],"type":"Point"}
}