{
  "type": "Feature",
  "properties": {
    "iso:country":"AU",
    "sg:address":"Unit 6/ 176 Forrester Rd",
    "sg:city":"St Marys",
    "sg:classifiers":[
        {
            "category":"Retail",
            "subcategory":"Auto Repair",
            "type":"Services"
        }
    ],
    "sg:phone":"+61 2 9833 7995",
    "sg:postcode":"2760",
    "sg:province":"NSW",
    "sg:tags":[
        "repairer",
        "motor",
        "engineer"
    ],
    "wof:name":"Mobile One Auto Repairs",
    "wof:placetype":"venue"
},
  "geometry": {"coordinates":[150.7762146,-33.7515335083],"type":"Point"}
}