{
  "type": "Feature",
  "properties": {
    "addr:full":"19 Yennora Ave Yennora NSW 2161",
    "addr:housenumber":"19",
    "addr:postcode":"2161",
    "addr:street":"Yennora Ave",
    "iso:country":"AU",
    "sg:address":"19 Yennora Ave",
    "sg:city":"Yennora",
    "sg:classifiers":[
        {
            "category":"Home & Garden",
            "subcategory":"Building Materials",
            "type":"Retail Goods"
        }
    ],
    "sg:phone":"+61 2 9892 2300",
    "sg:postcode":"2161",
    "sg:province":"NSW",
    "sg:tags":[
        "merchant",
        "glass",
        "glazier"
    ],
    "wof:name":"Foster Plastics Industries Pty Ltd",
    "wof:placetype":"venue"
},
  "geometry": {"coordinates":[150.97137451200001,-33.8618278503],"type":"Point"}
}