{
  "type": "Feature",
  "properties": {
    "addr:full":"&#034;Guide Hall&#034; 41 Kauri Pde Seacliff SA 5049",
    "addr:housenumber":"41",
    "addr:postcode":"5049",
    "addr:street":"Kauri Pde",
    "iso:country":"AU",
    "sg:address":"&#034;Guide Hall&#034; 41 Kauri Pde",
    "sg:city":"Seacliff",
    "sg:classifiers":[
        {
            "category":"Education",
            "subcategory":"School",
            "type":"Public Place"
        }
    ],
    "sg:phone":"+61 8 8358 1066",
    "sg:postcode":"5049",
    "sg:province":"SA",
    "sg:tags":[
        "co-educational"
    ],
    "wof:name":"Montessori Childrens Centre Pty Ltd",
    "wof:placetype":"venue"
},
  "geometry": {"coordinates":[138.521759,-35.031918],"type":"Point"}
}