{
  "type": "Feature",
  "properties": {
    "addr:full":"Lister St Monto QLD 4630",
    "addr:postcode":"4630",
    "addr:street":"Lister St",
    "iso:country":"AU",
    "sg:address":"Lister St",
    "sg:city":"Monto",
    "sg:classifiers":[
        {
            "category":"Building & Trades",
            "subcategory":"Plumbing",
            "type":"Services"
        }
    ],
    "sg:phone":"+61 7 4166 1677",
    "sg:postcode":"4630",
    "sg:province":"QLD",
    "sg:tags":[
        "plumber",
        "gasfitters"
    ],
    "wof:name":"Midstate Plumbing & Building",
    "wof:placetype":"venue"
},
  "geometry": {"coordinates":[151.11985778799999,-24.8656959534],"type":"Point"}
}