{
  "type": "Feature",
  "properties": {
    "addr:full":"40 Brice Ave Mooroolbark VIC 3138",
    "addr:housenumber":"40",
    "addr:postcode":"3138",
    "addr:street":"Brice Ave",
    "iso:country":"AU",
    "sg:address":"40 Brice Ave",
    "sg:city":"Mooroolbark",
    "sg:classifiers":[
        {
            "category":"Shopping",
            "type":"Retail Goods"
        }
    ],
    "sg:phone":"+61 3 9726 5544",
    "sg:postcode":"3138",
    "sg:province":"VIC",
    "sg:tags":[
        "new age",
        "product"
    ],
    "wof:name":"Balanced Harmony",
    "wof:placetype":"venue"
},
  "geometry": {"coordinates":[145.31271362300001,-37.7852172852],"type":"Point"}
}