{
  "type": "Feature",
  "properties": {
    "addr:full":"3A 27 Corporation Cct Currumbin QLD 4223",
    "addr:housenumber":"27",
    "addr:postcode":"4223",
    "addr:street":"Corporation Cct",
    "iso:country":"AU",
    "sg:address":"3A 27",
    "sg:city":"Corporation Cct Currumbin",
    "sg:classifiers":[
        {
            "category":"Health Services",
            "subcategory":"Doctor",
            "type":"Services"
        }
    ],
    "sg:phone":"+61 1300 361 238",
    "sg:postcode":"4223",
    "sg:province":"QLD",
    "sg:tags":[
        "podiatrist"
    ],
    "wof:name":"Foot Analysis Centre",
    "wof:placetype":"venue"
},
  "geometry": {"coordinates":[153.47454834000001,-28.1377792358],"type":"Point"}
}