{
  "type": "Feature",
  "properties": {
    "addr:full":"Level 4, 600 George St Sydney NSW 2000",
    "addr:housenumber":"600",
    "addr:postcode":"2000",
    "addr:street":"George St",
    "iso:country":"AU",
    "sg:address":"Level 4, 600 George St",
    "sg:city":"Sydney",
    "sg:classifiers":[
        {
            "category":"Professional",
            "subcategory":"Accounting & Tax Preparation",
            "type":"Services"
        }
    ],
    "sg:phone":"+61 2 9283 1111",
    "sg:postcode":"2000",
    "sg:province":"NSW",
    "sg:tags":[
        "accountant",
        "auditor"
    ],
    "wof:name":"BPO Consulting Pty. Ltd",
    "wof:placetype":"venue"
},
  "geometry": {"coordinates":[151.206832886,-33.8750152588],"type":"Point"}
}