{
  "type": "Feature",
  "properties": {
    "addr:full":"3 Staughton Pl Wanniassa ACT 2903",
    "addr:housenumber":"3",
    "addr:postcode":"2903",
    "addr:street":"Staughton Pl",
    "iso:country":"AU",
    "sg:address":"3 Staughton Pl",
    "sg:city":"Wanniassa",
    "sg:classifiers":[
        {
            "category":"Government",
            "subcategory":"Fire Station",
            "type":"Public Place"
        }
    ],
    "sg:phone":"+61 2 6231 3883",
    "sg:postcode":"2903",
    "sg:province":"ACT",
    "sg:tags":[
        "equipment",
        "protection",
        "consultant"
    ],
    "wof:name":"Canberra Fire Stopping",
    "wof:placetype":"venue"
},
  "geometry": {"coordinates":[149.08357238799999,-35.4056968689],"type":"Point"}
}