{
  "type": "Feature",
  "properties": {
    "addr:full":"143 Powell St Geelong VIC 3220",
    "addr:housenumber":"143",
    "addr:postcode":"3220",
    "addr:street":"Powell St",
    "iso:country":"AU",
    "sg:address":"143 Powell St",
    "sg:city":"Geelong",
    "sg:classifiers":[
        {
            "category":"Building & Trades",
            "subcategory":"Construction",
            "type":"Services"
        }
    ],
    "sg:phone":"+61 438 538 610",
    "sg:postcode":"3220",
    "sg:province":"VIC",
    "sg:tags":[
        "rendering",
        "cement"
    ],
    "wof:name":"R.A.L. Rendering",
    "wof:placetype":"venue"
},
  "geometry": {"coordinates":[144.364105,-38.149105],"type":"Point"}
}