{
  "type": "Feature",
  "properties": {
    "addr:full":"23 Mackenzie St Concord West NSW 2138",
    "addr:housenumber":"23",
    "addr:postcode":"2138",
    "addr:street":"Mackenzie St",
    "iso:country":"AU",
    "sg:address":"23 Mackenzie St",
    "sg:city":"Concord West",
    "sg:classifiers":[
        {
            "category":"Real Estate",
            "subcategory":"Architect",
            "type":"Services"
        }
    ],
    "sg:phone":"+61 2 9743 1717",
    "sg:postcode":"2138",
    "sg:province":"NSW",
    "wof:name":"Zenere A D",
    "wof:placetype":"venue"
},
  "geometry": {"coordinates":[151.090011597,-33.8540229797],"type":"Point"}
}