{
  "type": "Feature",
  "properties": {
    "addr:full":"96 Unley Rd Unley SA 5061",
    "addr:housenumber":"96",
    "addr:postcode":"5061",
    "addr:street":"Unley Rd",
    "iso:country":"AU",
    "sg:address":"96 Unley Rd",
    "sg:city":"Unley",
    "sg:classifiers":[
        {
            "category":"Health Services",
            "subcategory":"Doctor",
            "type":"Services"
        }
    ],
    "sg:phone":"+61 8 8373 2422",
    "sg:postcode":"5061",
    "sg:province":"SA",
    "sg:tags":[
        "medical",
        "practitioner"
    ],
    "wof:name":"Kette Frank E",
    "wof:placetype":"venue"
},
  "geometry": {"coordinates":[138.60699462900001,-34.9462509155],"type":"Point"}
}