{
  "type": "Feature",
  "properties": {
    "addr:full":"457 Swan St Richmond VIC 3121",
    "addr:housenumber":"457",
    "addr:postcode":"3121",
    "addr:street":"Swan St",
    "iso:country":"AU",
    "sg:address":"457 Swan St",
    "sg:city":"Richmond",
    "sg:classifiers":[
        {
            "category":"Personal",
            "subcategory":"Massage",
            "type":"Services"
        }
    ],
    "sg:phone":"+61 3 9428 8341",
    "sg:postcode":"3121",
    "sg:province":"VIC",
    "sg:tags":[
        "therapy"
    ],
    "wof:name":"H.M.Swan Relaxation & Health Centre",
    "wof:placetype":"venue"
},
  "geometry": {"coordinates":[145.00918579099999,-37.8267593384],"type":"Point"}
}