{
  "type": "Feature",
  "properties": {
    "iso:country":"AU",
    "sg:address":"23 Ellengowan St",
    "sg:city":"Urangan",
    "sg:classifiers":[
        {
            "category":"Utilities",
            "subcategory":"Cable",
            "type":"Services"
        }
    ],
    "sg:phone":"+61 7 4124 9029",
    "sg:postcode":"4655",
    "sg:province":"QLD",
    "sg:tags":[
        "equipment",
        "meters"
    ],
    "wof:name":"Skilltech Consulting Services Pty Ltd",
    "wof:placetype":"venue"
},
  "geometry": {"coordinates":[152.889725,-25.315966],"type":"Point"}
}