{
  "type": "Feature",
  "properties": {
    "addr:full":"48- 50 Box Forest Rd Glenroy VIC 3046",
    "addr:housenumber":"50",
    "addr:postcode":"3046",
    "addr:street":"Box Forest Rd",
    "iso:country":"AU",
    "sg:address":"48- 50 Box Forest Rd",
    "sg:city":"Glenroy",
    "sg:classifiers":[
        {
            "category":"Education",
            "subcategory":"School",
            "type":"Public Place"
        }
    ],
    "sg:phone":"+61 3 9359 9266",
    "sg:postcode":"3046",
    "sg:province":"VIC",
    "sg:tags":[
        "state",
        "except",
        "nsw"
    ],
    "wof:name":"Glenroy Specialist School",
    "wof:placetype":"venue"
},
  "geometry": {"coordinates":[144.952392578,-37.7036476135],"type":"Point"}
}