{
  "type": "Feature",
  "properties": {
    "addr:full":"Edward St Currie TAS 7256",
    "addr:postcode":"7256",
    "addr:street":"Edward St",
    "iso:country":"AU",
    "sg:address":"Edward St",
    "sg:city":"Currie",
    "sg:classifiers":[
        {
            "category":"Landmark",
            "subcategory":"Tourist Information",
            "type":"Public Place"
        }
    ],
    "sg:phone":"+61 1800 645 014",
    "sg:postcode":"7256",
    "sg:province":"TAS",
    "sg:tags":[
        "bureau"
    ],
    "wof:name":"King Island Tourism Information",
    "wof:placetype":"venue"
},
  "geometry": {"coordinates":[143.85357665999999,-39.9312896729],"type":"Point"}
}