{
  "type": "Feature",
  "properties": {
    "addr:full":"29 Triholm Ave Laverton VIC 3028",
    "addr:housenumber":"29",
    "addr:postcode":"3028",
    "addr:street":"Triholm Ave",
    "iso:country":"AU",
    "sg:address":"29 Triholm Ave",
    "sg:city":"Laverton",
    "sg:classifiers":[
        {
            "category":"Autos & Motor Vehicles",
            "subcategory":"Auto Supplies",
            "type":"Retail Goods"
        }
    ],
    "sg:phone":"+61 3 9369 1711",
    "sg:postcode":"3028",
    "sg:province":"VIC",
    "sg:tags":[
        "tyre"
    ],
    "wof:name":"Stevens Tyre Service Pty Ltd",
    "wof:placetype":"venue"
},
  "geometry": {"coordinates":[144.75886499999999,-37.867756],"type":"Point"}
}