{
  "type": "Feature",
  "properties": {
    "addr:full":"1190 Old Port Rd Royal Park SA 5014",
    "addr:housenumber":"1190",
    "addr:postcode":"5014",
    "addr:street":"Old Port Rd",
    "iso:country":"AU",
    "sg:address":"1190 Old Port Rd",
    "sg:city":"Royal Park",
    "sg:classifiers":[
        {
            "category":"Retail",
            "subcategory":"Auto Repair",
            "type":"Services"
        }
    ],
    "sg:phone":"+61 8 8241 0688",
    "sg:postcode":"5014",
    "sg:province":"SA",
    "sg:tags":[
        "beater",
        "painter",
        "panel"
    ],
    "wof:name":"Royal City Autos",
    "wof:placetype":"venue"
},
  "geometry": {"coordinates":[138.507522583,-34.8627548218],"type":"Point"}
}