{
  "type": "Feature",
  "properties": {
    "iso:country":"AU",
    "sg:address":"8a Grafton St",
    "sg:city":"Naremburn",
    "sg:classifiers":[
        {
            "category":"Professional",
            "subcategory":"Employment Agencies",
            "type":"Services"
        }
    ],
    "sg:phone":"+61 2 9436 3798",
    "sg:postcode":"2065",
    "sg:province":"NSW",
    "sg:tags":[
        "entertainer",
        "agent"
    ],
    "wof:name":"A Accordion A-La-Carte Entertainment",
    "wof:placetype":"venue"
},
  "geometry": {"coordinates":[151.20800781200001,-33.8172950745],"type":"Point"}
}