{
  "type": "Feature",
  "properties": {
    "addr:full":"8 Heinrich Crt Mackay QLD 4740",
    "addr:housenumber":"8",
    "addr:postcode":"4740",
    "addr:street":"Heinrich Crt",
    "iso:country":"AU",
    "sg:address":"8 Heinrich Crt",
    "sg:city":"Mackay",
    "sg:classifiers":[
        {
            "category":"Transit Center",
            "subcategory":"Freight",
            "type":"Transportation"
        }
    ],
    "sg:phone":"+61 7 4952 5687",
    "sg:postcode":"4740",
    "sg:province":"QLD",
    "sg:tags":[
        "agent",
        "shipping"
    ],
    "wof:name":"Allied Pickfords",
    "wof:placetype":"venue"
},
  "geometry": {"coordinates":[149.17318700000001,-21.170584],"type":"Point"}
}