{
  "type": "Feature",
  "properties": {
    "addr:full":"Shop 3 Ebert Pde Lawnton QLD 4501",
    "addr:housenumber":"shop 3",
    "addr:postcode":"4501",
    "addr:street":"Ebert Pde",
    "iso:country":"AU",
    "sg:address":"Shop 3 Ebert Pde",
    "sg:city":"Lawnton",
    "sg:classifiers":[
        {
            "category":"Food & Beverages",
            "subcategory":"Bakery",
            "type":"Retail Goods"
        }
    ],
    "sg:phone":"+61 7 3285 3642",
    "sg:postcode":"4501",
    "sg:province":"QLD",
    "sg:tags":[
        "baker"
    ],
    "wof:name":"Lawnton Bakery",
    "wof:placetype":"venue"
},
  "geometry": {"coordinates":[152.98052978499999,-27.2826766968],"type":"Point"}
}