{
  "type": "Feature",
  "properties": {
    "iso:country":"AU",
    "sg:address":"74 Surrey Rd",
    "sg:city":"Blackburn North",
    "sg:classifiers":[
        {
            "category":"Health Services",
            "subcategory":"Health Practitioner",
            "type":"Services"
        }
    ],
    "sg:phone":"+61 3 9877 7304",
    "sg:postcode":"3130",
    "sg:province":"VIC",
    "sg:tags":[
        "physiotherapist"
    ],
    "wof:name":"Lee Arthur",
    "wof:placetype":"venue"
},
  "geometry": {"coordinates":[145.158569336,-37.8058319092],"type":"Point"}
}