{
  "type": "Feature",
  "properties": {
    "addr:full":"12 Shannon Crt Dingley VIC 3172",
    "addr:housenumber":"12",
    "addr:postcode":"3172",
    "addr:street":"Shannon Crt",
    "iso:country":"AU",
    "sg:address":"12 Shannon Crt",
    "sg:city":"Dingley",
    "sg:classifiers":[
        {
            "category":"Building & Trades",
            "subcategory":"Construction",
            "type":"Services"
        }
    ],
    "sg:phone":"+61 418 666 652",
    "sg:postcode":"3172",
    "sg:province":"VIC",
    "sg:tags":[
        "fencing",
        "contractor"
    ],
    "wof:name":"T F H-Temporary Fence Hire Pty Ltd",
    "wof:placetype":"venue"
},
  "geometry": {"coordinates":[145.119903564,-37.9746932983],"type":"Point"}
}