{
  "type": "Feature",
  "properties": {
    "iso:country":"AU",
    "sg:address":"95 Pascoe St",
    "sg:city":"Karrinyup",
    "sg:classifiers":[
        {
            "category":"Building & Trades",
            "subcategory":"Plumbing",
            "type":"Services"
        }
    ],
    "sg:phone":"+61 8 9445 7575",
    "sg:postcode":"6018",
    "sg:province":"WA",
    "sg:tags":[
        "plumber",
        "gasfitters"
    ],
    "wof:name":"A. ABA & AMP Plumbing & Gas",
    "wof:placetype":"venue"
},
  "geometry": {"coordinates":[115.781539917,-31.870891571],"type":"Point"}
}