{
  "type": "Feature",
  "properties": {
    "addr:full":"128 South Seas Drv Ashtonfield NSW 2323",
    "addr:housenumber":"128",
    "addr:postcode":"2323",
    "addr:street":"South Seas Drv",
    "iso:country":"AU",
    "sg:address":"128 South Seas Drv",
    "sg:city":"Ashtonfield",
    "sg:classifiers":[
        {
            "category":"Health Services",
            "subcategory":"Dentist",
            "type":"Services"
        }
    ],
    "sg:phone":"+61 2 4934 2603",
    "sg:postcode":"2323",
    "sg:province":"NSW",
    "sg:tags":[
        "dental",
        "prosthetist"
    ],
    "wof:name":"Robinson Scott",
    "wof:placetype":"venue"
},
  "geometry": {"coordinates":[151.59373474099999,-32.769618988],"type":"Point"}
}