{
  "type": "Feature",
  "properties": {
    "iso:country":"AU",
    "sg:address":"24 Tracey Rd",
    "sg:city":"Healy",
    "sg:classifiers":[
        {
            "category":"Airline",
            "type":"Transportation"
        }
    ],
    "sg:phone":"+61 7 4743 8434",
    "sg:postcode":"4825",
    "sg:province":"QLD",
    "sg:tags":[
        "agent"
    ],
    "wof:name":"A.A. Co Pty Ltd",
    "wof:placetype":"venue"
},
  "geometry": {"coordinates":[139.50396728499999,-20.748134613],"type":"Point"}
}