{
  "type": "Feature",
  "properties": {
    "addr:full":"Tuggeranong Health Centre Cnr Anketell & Pitman Sts Tuggeranong ACT 2900",
    "addr:postcode":"2900",
    "addr:street":"Cnr Anketell & Pitman",
    "iso:country":"AU",
    "sg:address":"Tuggeranong Health Centre Cnr Anketell & Pitman Sts",
    "sg:city":"Tuggeranong",
    "sg:classifiers":[
        {
            "category":"Health Services",
            "subcategory":"Doctor",
            "type":"Services"
        }
    ],
    "sg:phone":"+61 2 6293 3111",
    "sg:postcode":"2900",
    "sg:province":"ACT",
    "sg:tags":[
        "medical",
        "practitioner"
    ],
    "wof:name":"Ng Anthony",
    "wof:placetype":"venue"
},
  "geometry": {"coordinates":[149.06768798799999,-35.4157333374],"type":"Point"}
}