{
  "type": "Feature",
  "properties": {
    "addr:full":"42 Welten Drv Coldstream VIC 3770",
    "addr:housenumber":"42",
    "addr:postcode":"3770",
    "addr:street":"Welten Drv",
    "iso:country":"AU",
    "sg:address":"42 Welten Drv",
    "sg:city":"Coldstream",
    "sg:classifiers":[
        {
            "category":"Professional",
            "subcategory":"Accounting & Tax Preparation",
            "type":"Services"
        }
    ],
    "sg:phone":"+61 3 9739 0866",
    "sg:postcode":"3770",
    "sg:province":"VIC",
    "sg:tags":[
        "bookkeeping"
    ],
    "wof:name":"Taylor & Moore",
    "wof:placetype":"venue"
},
  "geometry": {"coordinates":[145.382553,-37.727325],"type":"Point"}
}