{
  "type": "Feature",
  "properties": {
    "addr:full":"288 Marrickville Rd Marrickville NSW 2204",
    "addr:housenumber":"288",
    "addr:postcode":"2204",
    "addr:street":"Marrickville Rd",
    "iso:country":"AU",
    "sg:address":"288 Marrickville Rd",
    "sg:city":"Marrickville",
    "sg:classifiers":[
        {
            "category":"Insurance",
            "subcategory":"Health Insurance",
            "type":"Services"
        }
    ],
    "sg:phone":"+61 2 9560 2222",
    "sg:postcode":"2204",
    "sg:province":"NSW",
    "wof:name":"HCF",
    "wof:placetype":"venue"
},
  "geometry": {"coordinates":[151.156631,-33.910778],"type":"Point"}
}