{
  "type": "Feature",
  "properties": {
    "addr:full":"1 Patterson St Petrie QLD 4502",
    "addr:housenumber":"1",
    "addr:postcode":"4502",
    "addr:street":"Patterson St",
    "iso:country":"AU",
    "sg:address":"1 Patterson St",
    "sg:city":"Petrie",
    "sg:classifiers":[
        {
            "category":"Manufacturing",
            "subcategory":"Tools & Machinery",
            "type":"Manufacturing & Wholesale Goods"
        }
    ],
    "sg:phone":"+61 438 851 911",
    "sg:postcode":"4502",
    "sg:province":"QLD",
    "sg:tags":[
        "earth",
        "excavating",
        "moving",
        "equipment"
    ],
    "wof:name":"All Class Earthmoving Pty Ltd",
    "wof:placetype":"venue"
},
  "geometry": {"coordinates":[152.977005005,-27.2690544128],"type":"Point"}
}