{
  "type": "Feature",
  "properties": {
    "iso:country":"AU",
    "sg:address":"2 Hillard St",
    "sg:city":"Wiley Park",
    "sg:classifiers":[
        {
            "category":"Health Services",
            "subcategory":"Doctor",
            "type":"Services"
        }
    ],
    "sg:phone":"+61 2 9759 7493",
    "sg:postcode":"2195",
    "sg:province":"NSW",
    "sg:tags":[
        "medical",
        "practitioner"
    ],
    "wof:name":"Amin Rachel Dr",
    "wof:placetype":"venue"
},
  "geometry": {"coordinates":[151.067825,-33.921417],"type":"Point"}
}