{
  "type": "Feature",
  "properties": {
    "addr:full":"901 Doland St Albury NSW 2640",
    "addr:housenumber":"901",
    "addr:postcode":"2640",
    "addr:street":"Doland St",
    "iso:country":"AU",
    "sg:address":"901 Doland St",
    "sg:city":"Albury",
    "sg:classifiers":[
        {
            "category":"Building & Trades",
            "subcategory":"Construction",
            "type":"Services"
        }
    ],
    "sg:phone":"+61 2 6041 2757",
    "sg:postcode":"2640",
    "sg:province":"NSW",
    "sg:tags":[
        "tennis court",
        "repair"
    ],
    "wof:name":"Riverina Sporting Services Pty Ltd",
    "wof:placetype":"venue"
},
  "geometry": {"coordinates":[146.89523315400001,-36.0790176392],"type":"Point"}
}