{
  "type": "Feature",
  "properties": {
    "addr:full":"10 Victoria St Warragul VIC 3820",
    "addr:housenumber":"10",
    "addr:postcode":"3820",
    "addr:street":"Victoria St",
    "iso:country":"AU",
    "sg:address":"10 Victoria St",
    "sg:city":"Warragul",
    "sg:classifiers":[
        {
            "category":"Shopping",
            "subcategory":"Jewelry",
            "type":"Retail Goods"
        }
    ],
    "sg:phone":"+61 3 5623 2104",
    "sg:postcode":"3820",
    "sg:province":"VIC",
    "sg:tags":[
        "jeweller"
    ],
    "wof:name":"Callander's Fine Jewellery",
    "wof:placetype":"venue"
},
  "geometry": {"coordinates":[145.930679,-38.162651],"type":"Point"}
}