{
  "type": "Feature",
  "properties": {
    "addr:full":"Unit 5/ 2 Commerce Drv Warilla NSW 2528",
    "addr:postcode":"2528",
    "addr:street":"Commerce Drv",
    "iso:country":"AU",
    "sg:address":"Unit 5/ 2 Commerce Drv",
    "sg:city":"Warilla",
    "sg:classifiers":[
        {
            "category":"Building & Trades",
            "subcategory":"Construction",
            "type":"Services"
        }
    ],
    "sg:phone":"+61 2 4295 3661",
    "sg:postcode":"2528",
    "sg:province":"NSW",
    "sg:tags":[
        "joinery"
    ],
    "wof:name":"Ultimate Kitchens & Joinery",
    "wof:placetype":"venue"
},
  "geometry": {"coordinates":[150.866577148,-34.547542572],"type":"Point"}
}