{
  "type": "Feature",
  "properties": {
    "addr:full":"800 Beaudesert Rd Coopers Plains QLD 4108",
    "addr:housenumber":"800",
    "addr:postcode":"4108",
    "addr:street":"Beaudesert Rd",
    "iso:country":"AU",
    "sg:address":"800 Beaudesert Rd",
    "sg:city":"Coopers Plains",
    "sg:classifiers":[
        {
            "category":"Manufacturing",
            "subcategory":"Tools & Machinery",
            "type":"Manufacturing & Wholesale Goods"
        }
    ],
    "sg:phone":"+61 13 63 36",
    "sg:postcode":"4108",
    "sg:province":"QLD",
    "sg:tags":[
        "earth",
        "excavating",
        "moving",
        "equipment"
    ],
    "wof:name":"National Hire",
    "wof:placetype":"venue"
},
  "geometry": {"coordinates":[153.021194458,-27.5587234497],"type":"Point"}
}