{
  "type": "Feature",
  "properties": {
    "addr:full":"10 Beetson Pl Millner NT 0810",
    "addr:housenumber":"10",
    "addr:postcode":"nt 0810",
    "addr:street":"Beetson Pl",
    "iso:country":"AU",
    "sg:address":"10 Beetson Pl",
    "sg:city":"Millner",
    "sg:classifiers":[
        {
            "category":"Utilities",
            "subcategory":"Electric",
            "type":"Services"
        }
    ],
    "sg:phone":"+61 417 856 593",
    "sg:postcode":"0810",
    "sg:province":"NT",
    "sg:tags":[
        "electrical",
        "contractor"
    ],
    "wof:name":"Ross Martin Electrics",
    "wof:placetype":"venue"
},
  "geometry": {"coordinates":[130.864379883,-12.3935937881],"type":"Point"}
}