{
  "type": "Feature",
  "properties": {
    "addr:full":"3 Grenfell St Adelaide SA 5000",
    "addr:housenumber":"3",
    "addr:postcode":"5000",
    "addr:street":"Grenfell St",
    "iso:country":"AU",
    "sg:address":"3 Grenfell St",
    "sg:city":"Adelaide",
    "sg:classifiers":[
        {
            "category":"Travel",
            "subcategory":"Travel Agent",
            "type":"Entertainment"
        }
    ],
    "sg:phone":"+61 8 8410 1587",
    "sg:postcode":"5000",
    "sg:province":"SA",
    "sg:tags":[
        "consultant"
    ],
    "wof:name":"Saunders Travel Services",
    "wof:placetype":"venue"
},
  "geometry": {"coordinates":[138.60023498499999,-34.9241409302],"type":"Point"}
}