{
  "type": "Feature",
  "properties": {
    "addr:full":"101 Best St Wagga Wagga NSW 2650",
    "addr:housenumber":"101",
    "addr:postcode":"2650",
    "addr:street":"Best St",
    "iso:country":"AU",
    "sg:address":"101 Best St",
    "sg:city":"Wagga Wagga",
    "sg:classifiers":[
        {
            "category":"Personal",
            "subcategory":"Massage",
            "type":"Services"
        }
    ],
    "sg:phone":"+61 403 586 748",
    "sg:postcode":"2650",
    "sg:province":"NSW",
    "sg:tags":[
        "therapy"
    ],
    "wof:name":"Aleasha Ball",
    "wof:placetype":"venue"
},
  "geometry": {"coordinates":[147.367095947,-35.1126022339],"type":"Point"}
}