{
  "type": "Feature",
  "properties": {
    "iso:country":"AU",
    "sg:address":"Level 1/ 264 Crown St",
    "sg:city":"Wollongong",
    "sg:classifiers":[
        {
            "category":"Personal",
            "subcategory":"Massage",
            "type":"Services"
        }
    ],
    "sg:phone":"+61 2 4228 3151",
    "sg:postcode":"2500",
    "sg:province":"NSW",
    "sg:tags":[
        "therapy"
    ],
    "wof:name":"Bua Tong Thai Traditional Massage",
    "wof:placetype":"venue"
},
  "geometry": {"coordinates":[150.89132699999999,-34.425171],"type":"Point"}
}