{
  "type": "Feature",
  "properties": {
    "addr:full":"Fcty4/ 123 Chesterville Rd Highett VIC 3190",
    "addr:housenumber":"123",
    "addr:postcode":"3190",
    "addr:street":"Chesterville Rd",
    "iso:country":"AU",
    "sg:address":"Fcty4/ 123 Chesterville Rd",
    "sg:city":"Highett",
    "sg:classifiers":[
        {
            "category":"Building & Trades",
            "subcategory":"Equipment Rental",
            "type":"Services"
        }
    ],
    "sg:phone":"+61 3 9555 1116",
    "sg:postcode":"3190",
    "sg:province":"VIC",
    "sg:tags":[
        "platform",
        "hire",
        "work",
        "elevating"
    ],
    "wof:name":"Vic Access",
    "wof:placetype":"venue"
},
  "geometry": {"coordinates":[145.05833435100001,-37.9502487183],"type":"Point"}
}