{
  "type": "Feature",
  "properties": {
    "iso:country":"AU",
    "sg:address":"6 Ross Rd",
    "sg:city":"Hectorville",
    "sg:classifiers":[
        {
            "category":"Building & Trades",
            "subcategory":"Construction",
            "type":"Services"
        }
    ],
    "sg:phone":"+61 8 8337 0989",
    "sg:postcode":"5073",
    "sg:province":"SA",
    "sg:tags":[
        "concrete",
        "contractor"
    ],
    "wof:name":"Sciarrone P",
    "wof:placetype":"venue"
},
  "geometry": {"coordinates":[138.66418457,-34.8935394287],"type":"Point"}
}