{
  "type": "Feature",
  "properties": {
    "addr:full":"55 Newman Crs Airport West VIC 3042",
    "addr:housenumber":"55",
    "addr:postcode":"3042",
    "addr:street":"Newman Crs",
    "iso:country":"AU",
    "sg:address":"55 Newman Crs",
    "sg:city":"Airport West",
    "sg:classifiers":[
        {
            "category":"Building & Trades",
            "subcategory":"Construction",
            "type":"Services"
        }
    ],
    "sg:phone":"+61 3 9374 2027",
    "sg:postcode":"3042",
    "sg:province":"VIC",
    "sg:tags":[
        "contractor"
    ],
    "wof:name":"Bastiaan J T",
    "wof:placetype":"venue"
},
  "geometry": {"coordinates":[144.882904053,-37.7343826294],"type":"Point"}
}