{
  "type": "Feature",
  "properties": {
    "addr:full":"103 Firebrace St Horsham VIC 3400",
    "addr:housenumber":"103",
    "addr:postcode":"3400",
    "addr:street":"Firebrace St",
    "iso:country":"AU",
    "sg:address":"103 Firebrace St",
    "sg:city":"Horsham",
    "sg:classifiers":[
        {
            "category":"Autos & Motor Vehicles",
            "subcategory":"Auto Supplies",
            "type":"Retail Goods"
        }
    ],
    "sg:phone":"+61 3 5382 0041",
    "sg:postcode":"3400",
    "sg:province":"VIC",
    "sg:tags":[
        "battery",
        "automotive"
    ],
    "wof:name":"Beaurepaires",
    "wof:placetype":"venue"
},
  "geometry": {"coordinates":[142.199905395,-36.7171897888],"type":"Point"}
}