{
  "type": "Feature",
  "properties": {
    "iso:country":"AU",
    "sg:address":"Shop 2, 1892 Beach Rd",
    "sg:city":"Malaga",
    "sg:classifiers":[
        {
            "category":"Personal",
            "subcategory":"Barber",
            "type":"Services"
        }
    ],
    "sg:phone":"+61 8 9249 6132",
    "sg:postcode":"6090",
    "sg:province":"WA",
    "wof:name":"Tania's Barber Shop",
    "wof:placetype":"venue"
},
  "geometry": {"coordinates":[115.887252808,-31.8555850983],"type":"Point"}
}