{
  "type": "Feature",
  "properties": {
    "iso:country":"AU",
    "sg:address":"32 Herbert St",
    "sg:city":"Innisfail",
    "sg:classifiers":[
        {
            "category":"Professional",
            "type":"Services"
        }
    ],
    "sg:phone":"+61 7 4061 4268",
    "sg:postcode":"4860",
    "sg:province":"QLD",
    "sg:tags":[
        "shop",
        "fitting"
    ],
    "wof:name":"Beare Building",
    "wof:placetype":"venue"
},
  "geometry": {"coordinates":[146.03669738799999,-17.5221271515],"type":"Point"}
}