{
  "type": "Feature",
  "properties": {
    "iso:country":"AU",
    "sg:address":"155 Monbulk-Seville Rd",
    "sg:city":"Silvan",
    "sg:classifiers":[
        {
            "category":"Professional",
            "subcategory":"Art Services",
            "type":"Services"
        }
    ],
    "sg:phone":"+61 3 9737 9327",
    "sg:postcode":"3795",
    "sg:province":"VIC",
    "sg:tags":[
        "graphic",
        "designer"
    ],
    "wof:name":"Chanter Design Pty Ltd",
    "wof:placetype":"venue"
},
  "geometry": {"coordinates":[145.43809509299999,-37.8417739868],"type":"Point"}
}