{
  "type": "Feature",
  "properties": {
    "addr:full":"12c Louise Ave Ingleburn NSW 2565",
    "addr:housenumber":"12c",
    "addr:postcode":"2565",
    "addr:street":"Louise Ave",
    "iso:country":"AU",
    "sg:address":"12c Louise Ave",
    "sg:city":"Ingleburn",
    "sg:classifiers":[
        {
            "category":"Farming",
            "subcategory":"Farm & Veterinary Services",
            "type":"Manufacturing & Wholesale Goods"
        }
    ],
    "sg:phone":"+61 2 9829 1334",
    "sg:postcode":"2565",
    "sg:province":"NSW",
    "sg:tags":[
        "irrigation",
        "reticulation",
        "system"
    ],
    "wof:name":"C & M Innovations",
    "wof:placetype":"venue"
},
  "geometry": {"coordinates":[150.86590576200001,-33.9952812195],"type":"Point"}
}