{
  "type": "Feature",
  "properties": {
    "iso:country":"AU",
    "sg:address":"33 Darley St",
    "sg:city":"Forestville",
    "sg:classifiers":[
        {
            "category":"Retail",
            "subcategory":"Auto Repair",
            "type":"Services"
        }
    ],
    "sg:phone":"+61 2 9451 6773",
    "sg:postcode":"2087",
    "sg:province":"NSW",
    "sg:tags":[
        "repairer",
        "motor",
        "engineer"
    ],
    "wof:name":"Webber Neville Automotive Engineering Consultancy",
    "wof:placetype":"venue"
},
  "geometry": {"coordinates":[151.21347045900001,-33.7641792297],"type":"Point"}
}