{
  "type": "Feature",
  "properties": {
    "addr:full":"358 East St Albury NSW 2640",
    "addr:housenumber":"358",
    "addr:postcode":"2640",
    "addr:street":"East St",
    "iso:country":"AU",
    "sg:address":"358 East St",
    "sg:city":"Albury",
    "sg:classifiers":[
        {
            "category":"Mining & Drilling",
            "type":"Manufacturing & Wholesale Goods"
        }
    ],
    "sg:phone":"+61 2 6021 1047",
    "sg:postcode":"2640",
    "sg:province":"NSW",
    "sg:tags":[
        "geologist"
    ],
    "wof:name":"B Hochwimmer & Associates",
    "wof:placetype":"venue"
},
  "geometry": {"coordinates":[146.9347229,-36.0896911621],"type":"Point"}
}