{
  "type": "Feature",
  "properties": {
    "addr:full":"67/ 2- 6 Market St Rockdale NSW 2216",
    "addr:housenumber":"67 / 2 6",
    "addr:postcode":"2216",
    "addr:street":"Market St",
    "iso:country":"AU",
    "sg:address":"67/ 2- 6 Market St",
    "sg:city":"Rockdale",
    "sg:classifiers":[
        {
            "category":"Health Services",
            "subcategory":"Doctor",
            "type":"Services"
        }
    ],
    "sg:phone":"+61 2 9567 7077",
    "sg:postcode":"2216",
    "sg:province":"NSW",
    "sg:tags":[
        "medical",
        "practitioner"
    ],
    "wof:name":"Rockdale Family Health Clinic",
    "wof:placetype":"venue"
},
  "geometry": {"coordinates":[151.13992300000001,-33.951172],"type":"Point"}
}