{
  "type": "Feature",
  "properties": {
    "addr:full":"7 Appleton St Carlisle WA 6101",
    "addr:housenumber":"7",
    "addr:postcode":"6101",
    "addr:street":"Appleton St",
    "iso:country":"AU",
    "sg:address":"7 Appleton St",
    "sg:city":"Carlisle",
    "sg:classifiers":[
        {
            "category":"Building & Trades",
            "subcategory":"Plumbing",
            "type":"Services"
        }
    ],
    "sg:phone":"+61 407 194 857",
    "sg:postcode":"6101",
    "sg:province":"WA",
    "sg:tags":[
        "plumber",
        "gasfitters"
    ],
    "wof:name":"A O.K. Plumbing",
    "wof:placetype":"venue"
},
  "geometry": {"coordinates":[115.92582702599999,-31.9804439545],"type":"Point"}
}