{
  "type": "Feature",
  "properties": {
    "addr:full":"281 Byron St Inverell NSW 2360",
    "addr:housenumber":"281",
    "addr:postcode":"2360",
    "addr:street":"Byron St",
    "iso:country":"AU",
    "sg:address":"281 Byron St",
    "sg:city":"Inverell",
    "sg:classifiers":[
        {
            "category":"Retail",
            "subcategory":"Auto Rental",
            "type":"Services"
        }
    ],
    "sg:phone":"+61 2 6722 2244",
    "sg:postcode":"2360",
    "sg:province":"NSW",
    "sg:tags":[
        "car",
        "hire",
        "minibus"
    ],
    "wof:name":"Thrifty",
    "wof:placetype":"venue"
},
  "geometry": {"coordinates":[151.12104797399999,-29.7672252655],"type":"Point"}
}