{
  "type": "Feature",
  "properties": {
    "addr:full":"29 Fulton St Oakleigh South VIC 3167",
    "addr:housenumber":"29",
    "addr:postcode":"3167",
    "addr:street":"Fulton St",
    "iso:country":"AU",
    "sg:address":"29 Fulton St",
    "sg:city":"Oakleigh South",
    "sg:classifiers":[
        {
            "category":"Autos & Motor Vehicles",
            "subcategory":"Automobile Sales",
            "type":"Retail Goods"
        }
    ],
    "sg:phone":"+61 3 9544 3880",
    "sg:postcode":"3167",
    "sg:province":"VIC",
    "sg:tags":[
        "equipment",
        "trailer"
    ],
    "wof:name":"Bentleigh Trailers",
    "wof:placetype":"venue"
},
  "geometry": {"coordinates":[145.11210632300001,-37.9134864807],"type":"Point"}
}