{
  "type": "Feature",
  "properties": {
    "iso:country":"AU",
    "sg:address":"Suite 7/ 650 Pittwater Rd",
    "sg:city":"Brookvale",
    "sg:classifiers":[
        {
            "category":"Real Estate",
            "subcategory":"Real Estate Services",
            "type":"Services"
        }
    ],
    "sg:phone":"+61 2 9938 1805",
    "sg:postcode":"2100",
    "sg:province":"NSW",
    "sg:tags":[
        "valuer"
    ],
    "wof:name":"Anthony Eldridge-Smith A.A.P.I",
    "wof:placetype":"venue"
},
  "geometry": {"coordinates":[151.27076721200001,-33.7649765015],"type":"Point"}
}