{
  "type": "Feature",
  "properties": {
    "addr:full":"4/ 33 Seymour Gr Camberwell VIC 3124",
    "addr:housenumber":"/ 33",
    "addr:postcode":"3124",
    "addr:street":"Seymour Gr",
    "iso:country":"AU",
    "sg:address":"4/ 33",
    "sg:city":"Seymour Gr Camberwell",
    "sg:classifiers":[
        {
            "category":"Education",
            "subcategory":"Special Training",
            "type":"Public Place"
        }
    ],
    "sg:phone":"+61 500 555 401",
    "sg:postcode":"3124",
    "sg:province":"VIC",
    "sg:tags":[
        "drama",
        "tuition"
    ],
    "wof:name":"Bel Foster",
    "wof:placetype":"venue"
},
  "geometry": {"coordinates":[145.058227539,-37.8357200623],"type":"Point"}
}