{
  "type": "Feature",
  "properties": {
    "addr:full":"235 Basford Rd Lake Munmorah NSW 2259",
    "addr:housenumber":"235",
    "addr:postcode":"2259",
    "addr:street":"Basford Rd",
    "iso:country":"AU",
    "sg:address":"235 Basford Rd",
    "sg:city":"Lake Munmorah",
    "sg:classifiers":[
        {
            "category":"Real Estate",
            "subcategory":"Real Estate Operator",
            "type":"Services"
        }
    ],
    "sg:phone":"+61 2 4358 8275",
    "sg:postcode":"2259",
    "sg:province":"NSW",
    "sg:tags":[
        "concrete",
        "pumping"
    ],
    "wof:name":"In & Out Concrete Pumping",
    "wof:placetype":"venue"
},
  "geometry": {"coordinates":[151.54852294899999,-33.1878089905],"type":"Point"}
}