{
  "type": "Feature",
  "properties": {
    "addr:full":"Gate 3 Fairbairn Rd Brooklyn VIC 3025",
    "addr:housenumber":"3",
    "addr:postcode":"3025",
    "addr:street":"Gate;Fairbairn Rd",
    "iso:country":"AU",
    "sg:address":"Gate 3 Fairbairn Rd",
    "sg:city":"Brooklyn",
    "sg:classifiers":[
        {
            "category":"Building & Trades",
            "subcategory":"Equipment Rental",
            "type":"Services"
        }
    ],
    "sg:phone":"+61 3 9314 2500",
    "sg:postcode":"3025",
    "sg:province":"VIC",
    "sg:tags":[
        "renting",
        "trailer"
    ],
    "wof:name":"T.E.H. Pty Ltd",
    "wof:placetype":"venue"
},
  "geometry": {"coordinates":[144.818893,-37.793198],"type":"Point"}
}