{
  "type": "Feature",
  "properties": {
    "addr:full":"130 Cumberland St The Rocks NSW 2000",
    "addr:housenumber":"130",
    "addr:postcode":"2000",
    "addr:street":"Cumberland St",
    "iso:country":"AU",
    "sg:address":"130 Cumberland St",
    "sg:city":"The Rocks",
    "sg:classifiers":[
        {
            "category":"Shopping",
            "subcategory":"Computers & Home Electronics",
            "type":"Retail Goods"
        }
    ],
    "sg:phone":"+61 2 9241 7069",
    "sg:postcode":"2000",
    "sg:province":"NSW",
    "sg:tags":[
        "equipment",
        "multimedia"
    ],
    "wof:name":"Hurricane Media Pty Ltd.",
    "wof:placetype":"venue"
},
  "geometry": {"coordinates":[151.20660400400001,-33.860534668],"type":"Point"}
}