{
  "type": "Feature",
  "properties": {
    "addr:full":"Shop 10/ 83 Wharf St Tweed Heads NSW 2485",
    "addr:housenumber":"shop 10 / 83",
    "addr:postcode":"2485",
    "addr:street":"Wharf St",
    "iso:country":"AU",
    "sg:address":"Shop 10/ 83 Wharf St",
    "sg:city":"Tweed Heads",
    "sg:classifiers":[
        {
            "category":"Shopping",
            "subcategory":"Clothing, Apparel, & Fashions",
            "type":"Retail Goods"
        }
    ],
    "sg:phone":"+61 7 5599 1981",
    "sg:postcode":"2485",
    "sg:province":"NSW",
    "sg:tags":[
        "lady",
        "wear"
    ],
    "wof:name":"Essence of La Lunar",
    "wof:placetype":"venue"
},
  "geometry": {"coordinates":[153.54273986800001,-28.1731777191],"type":"Point"}
}