{
  "type": "Feature",
  "properties": {
    "addr:full":"36 Allied Drv Tullamarine VIC 3043",
    "addr:housenumber":"36",
    "addr:postcode":"3043",
    "addr:street":"Allied Drv",
    "iso:country":"AU",
    "sg:address":"36 Allied Drv",
    "sg:city":"Tullamarine",
    "sg:classifiers":[
        {
            "category":"Transit Center",
            "subcategory":"Freight",
            "type":"Transportation"
        }
    ],
    "sg:phone":"+61 3 9330 0090",
    "sg:postcode":"3043",
    "sg:province":"VIC",
    "sg:tags":[
        "agent",
        "shipping"
    ],
    "wof:name":"Tradelanes Global Solutions",
    "wof:placetype":"venue"
},
  "geometry": {"coordinates":[144.886352539,-37.699924469],"type":"Point"}
}