{
  "type": "Feature",
  "properties": {
    "iso:country":"AU",
    "sg:address":"4/ 67 Araluen St",
    "sg:city":"Kedron",
    "sg:classifiers":[
        {
            "category":"Home & Garden",
            "subcategory":"Carpets & Floor Coverings",
            "type":"Retail Goods"
        }
    ],
    "sg:phone":"+61 7 3861 4422",
    "sg:postcode":"4031",
    "sg:province":"QLD",
    "sg:tags":[
        "wood"
    ],
    "wof:name":"Trojan Timbers Pty Ltd",
    "wof:placetype":"venue"
},
  "geometry": {"coordinates":[153.022552,-27.397465],"type":"Point"}
}