{
  "type": "Feature",
  "properties": {
    "addr:full":"Upper Level, Towns Centre Arcade, 81-83 Katoomba St Katoomba NSW 2780",
    "addr:housenumber":"81-83",
    "addr:postcode":"2780",
    "addr:street":"Katoomba St",
    "iso:country":"AU",
    "sg:address":"Upper Level, Towns Centre Arcade, 81-83 Katoomba St",
    "sg:city":"Katoomba",
    "sg:classifiers":[
        {
            "category":"Professional",
            "subcategory":"Business Services",
            "type":"Services"
        }
    ],
    "sg:phone":"+61 2 4782 5944",
    "sg:postcode":"2780",
    "sg:province":"NSW",
    "sg:tags":[
        "small",
        "advisory"
    ],
    "wof:name":"Blue Mountains Business Advisory Centre",
    "wof:placetype":"venue"
},
  "geometry": {"coordinates":[150.311737061,-33.7132949829],"type":"Point"}
}