{
  "type": "Feature",
  "properties": {
    "addr:full":"3 Vaughan Drv Ormeau QLD 4208",
    "addr:housenumber":"3",
    "addr:postcode":"4208",
    "addr:street":"Vaughan Drv",
    "iso:country":"AU",
    "sg:address":"3 Vaughan Drv",
    "sg:city":"Ormeau",
    "sg:classifiers":[
        {
            "category":"Personal",
            "subcategory":"Massage",
            "type":"Services"
        }
    ],
    "sg:phone":"+61 7 5547 5666",
    "sg:postcode":"4208",
    "sg:province":"QLD",
    "sg:tags":[
        "therapy"
    ],
    "wof:name":"P J Lynskey",
    "wof:placetype":"venue"
},
  "geometry": {"coordinates":[153.250534058,-27.7856864929],"type":"Point"}
}