{
  "type": "Feature",
  "properties": {
    "addr:full":"PO Box 1485 Mt Isa QLD 4825",
    "addr:postcode":"4825",
    "iso:country":"AU",
    "sg:address":"PO Box 1485",
    "sg:city":"Mt Isa",
    "sg:classifiers":[
        {
            "category":"Building & Trades",
            "subcategory":"Construction",
            "type":"Services"
        }
    ],
    "sg:phone":"+61 412 607 660",
    "sg:postcode":"4825",
    "sg:province":"QLD",
    "sg:tags":[
        "contractor"
    ],
    "wof:name":"Will Fedder Builder",
    "wof:placetype":"venue"
},
  "geometry": {"coordinates":[139.48582500000001,-20.727293],"type":"Point"}
}