{
  "type": "Feature",
  "properties": {
    "addr:full":"205 Main Rd Lower Plenty VIC 3093",
    "addr:housenumber":"205",
    "addr:postcode":"3093",
    "addr:street":"Main Rd",
    "iso:country":"AU",
    "sg:address":"205 Main Rd",
    "sg:city":"Lower Plenty",
    "sg:classifiers":[
        {
            "category":"Health Services",
            "subcategory":"Health Practitioner",
            "type":"Services"
        }
    ],
    "sg:phone":"+61 3 9439 0828",
    "sg:postcode":"3093",
    "sg:province":"VIC",
    "sg:tags":[
        "myotherapy"
    ],
    "wof:name":"Andrew Knight",
    "wof:placetype":"venue"
},
  "geometry": {"coordinates":[145.122314453,-37.7251319885],"type":"Point"}
}