{
  "type": "Feature",
  "properties": {
    "addr:full":"46 Glencairn St Mulgrave VIC 3170",
    "addr:housenumber":"46",
    "addr:postcode":"3170",
    "addr:street":"Glencairn St",
    "iso:country":"AU",
    "sg:address":"46 Glencairn St",
    "sg:city":"Mulgrave",
    "sg:classifiers":[
        {
            "category":"Building & Trades",
            "subcategory":"Construction",
            "type":"Services"
        }
    ],
    "sg:phone":"+61 3 9547 4700",
    "sg:postcode":"3170",
    "sg:province":"VIC",
    "sg:tags":[
        "fencing",
        "contractor"
    ],
    "wof:name":"Webster's Fencing",
    "wof:placetype":"venue"
},
  "geometry": {"coordinates":[145.16532898,-37.9311447144],"type":"Point"}
}