{
  "type": "Feature",
  "properties": {
    "addr:full":"20 Toodyay Rd Middle Swan WA 6056",
    "addr:housenumber":"20",
    "addr:postcode":"6056",
    "addr:street":"Toodyay Rd",
    "iso:country":"AU",
    "sg:address":"20 Toodyay Rd",
    "sg:city":"Middle Swan",
    "sg:classifiers":[
        {
            "category":"Education",
            "subcategory":"School",
            "type":"Public Place"
        }
    ],
    "sg:phone":"+61 8 9250 1592",
    "sg:postcode":"6056",
    "sg:province":"WA",
    "wof:name":"St Brigid's Primary School",
    "wof:placetype":"venue"
},
  "geometry": {"coordinates":[116.015159607,-31.873134613],"type":"Point"}
}