{
  "type": "Feature",
  "properties": {
    "addr:full":"PO Box 310 Ringwood VIC 3134",
    "addr:postcode":"3134",
    "iso:country":"AU",
    "sg:address":"PO Box 310",
    "sg:city":"Ringwood",
    "sg:classifiers":[
        {
            "category":"Professional",
            "subcategory":"Computer Services",
            "type":"Services"
        }
    ],
    "sg:phone":"+61 1300 725 632",
    "sg:postcode":"3134",
    "sg:province":"VIC",
    "sg:tags":[
        "tele-communications",
        "consultant"
    ],
    "wof:name":"E-Select Solutions",
    "wof:placetype":"venue"
},
  "geometry": {"coordinates":[145.22752380399999,-37.8157196045],"type":"Point"}
}