{
  "type": "Feature",
  "properties": {
    "iso:country":"AU",
    "sg:address":"PO Box 457",
    "sg:city":"Edgecliff",
    "sg:classifiers":[
        {
            "category":"Real Estate",
            "subcategory":"Real Estate Agent",
            "type":"Services"
        }
    ],
    "sg:phone":"+61 2 9363 9436",
    "sg:postcode":"2027",
    "sg:province":"NSW",
    "wof:name":"Akkerman Property Consultants",
    "wof:placetype":"venue"
},
  "geometry": {"coordinates":[151.237792969,-33.8803787231],"type":"Point"}
}