{
  "type": "Feature",
  "properties": {
    "addr:full":"90a Gordon St Footscray VIC 3011",
    "addr:housenumber":"90a",
    "addr:postcode":"3011",
    "addr:street":"Gordon St",
    "iso:country":"AU",
    "sg:address":"90a Gordon St",
    "sg:city":"Footscray",
    "sg:classifiers":[
        {
            "category":"Personal",
            "subcategory":"Beauty Salon",
            "type":"Services"
        }
    ],
    "sg:phone":"+61 1800 035 302",
    "sg:postcode":"3011",
    "sg:province":"VIC",
    "wof:name":"Winning Nails Professional Nail Products",
    "wof:placetype":"venue"
},
  "geometry": {"coordinates":[144.88999939000001,-37.7880210876],"type":"Point"}
}