{
  "type": "Feature",
  "properties": {
    "iso:country":"AU",
    "sg:address":"138 Main Rd East",
    "sg:city":"St Albans",
    "sg:classifiers":[
        {
            "category":"Health Services",
            "subcategory":"Doctor",
            "type":"Services"
        }
    ],
    "sg:phone":"+61 3 9367 1088",
    "sg:postcode":"3021",
    "sg:province":"VIC",
    "sg:tags":[
        "medical",
        "practitioner"
    ],
    "wof:name":"Chew P S",
    "wof:placetype":"venue"
},
  "geometry": {"coordinates":[144.818634,-37.746296],"type":"Point"}
}