{
  "type": "Feature",
  "properties": {
    "iso:country":"AU",
    "sg:address":"PO Box 66",
    "sg:city":"Curtin",
    "sg:classifiers":[
        {
            "category":"Professional",
            "subcategory":"Employment Agencies",
            "type":"Services"
        }
    ],
    "sg:phone":"+61 2 6281 7887",
    "sg:postcode":"2605",
    "sg:province":"ACT",
    "wof:name":"Tall Poppies Act",
    "wof:placetype":"venue"
},
  "geometry": {"coordinates":[149.081298828,-35.3241615295],"type":"Point"}
}