{
  "type": "Feature",
  "properties": {
    "addr:full":"St Vincents Hospital Scott St Toowoomba QLD 4350",
    "addr:postcode":"4350",
    "addr:street":"St;Scott St",
    "iso:country":"AU",
    "sg:address":"St Vincents Hospital Scott St",
    "sg:city":"Toowoomba",
    "sg:classifiers":[
        {
            "category":"Health Services",
            "subcategory":"Health Practitioner",
            "type":"Services"
        }
    ],
    "sg:phone":"+61 7 4632 6672",
    "sg:postcode":"4350",
    "sg:province":"QLD",
    "sg:tags":[
        "physiotherapist"
    ],
    "wof:name":"Gosden Kristine",
    "wof:placetype":"venue"
},
  "geometry": {"coordinates":[151.86923200000001,-27.603662],"type":"Point"}
}