{
  "type": "Feature",
  "properties": {
    "addr:full":"44 Progress Drv Nightcliff NT 0810",
    "addr:housenumber":"44",
    "addr:postcode":"nt 0810",
    "addr:street":"Progress Drv",
    "iso:country":"AU",
    "sg:address":"44 Progress Drv",
    "sg:city":"Nightcliff",
    "sg:classifiers":[
        {
            "category":"Government",
            "subcategory":"Post Office",
            "type":"Public Place"
        }
    ],
    "sg:phone":"+61 8 8985 1255",
    "sg:postcode":"0810",
    "sg:province":"NT",
    "sg:tags":[
        "postal"
    ],
    "wof:name":"Australia Post",
    "wof:placetype":"venue"
},
  "geometry": {"coordinates":[130.85043335,-12.3876285553],"type":"Point"}
}