{
  "type": "Feature",
  "properties": {
    "addr:full":"PO BOX 2439 Burnside 5066 Echunga SA 5153",
    "addr:postcode":"5066;5153",
    "iso:country":"AU",
    "sg:address":"PO BOX 2439 Burnside 5066",
    "sg:city":"Echunga",
    "sg:classifiers":[
        {
            "category":"Education",
            "subcategory":"Special Training",
            "type":"Public Place"
        }
    ],
    "sg:phone":"+61 8 8379 2373",
    "sg:postcode":"5153",
    "sg:province":"SA",
    "sg:tags":[
        "feldenkrais"
    ],
    "wof:name":"Abilities Awareness",
    "wof:placetype":"venue"
},
  "geometry": {"coordinates":[138.66989135700001,-34.9461402893],"type":"Point"}
}