{
  "type": "Feature",
  "properties": {
    "addr:full":"9 Tennant Pl Jerrabomberra NSW 2619",
    "addr:housenumber":"9",
    "addr:postcode":"2619",
    "addr:street":"Tennant Pl",
    "iso:country":"AU",
    "sg:address":"9 Tennant Pl",
    "sg:city":"Jerrabomberra",
    "sg:classifiers":[
        {
            "category":"Professional",
            "subcategory":"Accounting & Tax Preparation",
            "type":"Services"
        }
    ],
    "sg:phone":"+61 2 6255 9999",
    "sg:postcode":"2619",
    "sg:province":"NSW",
    "sg:tags":[
        "bookkeeping"
    ],
    "wof:name":"Gems Bookkeeping Services",
    "wof:placetype":"venue"
},
  "geometry": {"coordinates":[149.200119019,-35.3764686584],"type":"Point"}
}