{
  "type": "Feature",
  "properties": {
    "iso:country":"AU",
    "sg:address":"Henderson Drv",
    "sg:city":"Pin Gin Hill",
    "sg:classifiers":[
        {
            "category":"Farming",
            "subcategory":"Farm",
            "type":"Manufacturing & Wholesale Goods"
        }
    ],
    "sg:phone":"+61 7 4064 4192",
    "sg:postcode":"4860",
    "sg:province":"QLD",
    "sg:tags":[
        "farmer"
    ],
    "wof:name":"Binder G J & C M",
    "wof:placetype":"venue"
},
  "geometry": {"coordinates":[145.950881958,-17.5642719269],"type":"Point"}
}