{
  "type": "Feature",
  "properties": {
    "addr:full":"16 Gillespie Rd St Albans VIC 3021",
    "addr:housenumber":"16",
    "addr:postcode":"3021",
    "addr:street":"Gillespie Rd",
    "iso:country":"AU",
    "sg:address":"16 Gillespie Rd",
    "sg:city":"St Albans",
    "sg:classifiers":[
        {
            "category":"Building & Trades",
            "subcategory":"Equipment Rental",
            "type":"Services"
        }
    ],
    "sg:phone":"+61 3 9382 7550",
    "sg:postcode":"3021",
    "sg:province":"VIC",
    "sg:tags":[
        "demolition",
        "contractor"
    ],
    "wof:name":"Ed's Demolitions",
    "wof:placetype":"venue"
},
  "geometry": {"coordinates":[144.78797900000001,-37.734821],"type":"Point"}
}