{
  "type": "Feature",
  "properties": {
    "iso:country":"AU",
    "sg:address":"Shop 106 Malop St",
    "sg:city":"Geelong",
    "sg:classifiers":[
        {
            "category":"Shopping",
            "subcategory":"Mobile Phones",
            "type":"Retail Goods"
        }
    ],
    "sg:phone":"+61 3 5222 6288",
    "sg:postcode":"3220",
    "sg:province":"VIC",
    "sg:tags":[
        "telephone",
        "accessory"
    ],
    "wof:name":"Speedy Link Communications",
    "wof:placetype":"venue"
},
  "geometry": {"coordinates":[144.36087000000001,-38.147385],"type":"Point"}
}