{
  "type": "Feature",
  "properties": {
    "addr:full":"1 Glenhaven Rd Glenhaven NSW 2156",
    "addr:housenumber":"1",
    "addr:postcode":"2156",
    "addr:street":"Glenhaven Rd",
    "iso:country":"AU",
    "sg:address":"1 Glenhaven Rd",
    "sg:city":"Glenhaven",
    "sg:classifiers":[
        {
            "category":"Education",
            "subcategory":"Kindergarten",
            "type":"Public Place"
        }
    ],
    "sg:phone":"+61 2 9894 0455",
    "sg:postcode":"2156",
    "sg:province":"NSW",
    "sg:tags":[
        "pre-schools"
    ],
    "wof:name":"Kindalin Child Care Centres",
    "wof:placetype":"venue"
},
  "geometry": {"coordinates":[151.01048278799999,-33.7050437927],"type":"Point"}
}