{
  "type": "Feature",
  "properties": {
    "iso:country":"AU",
    "sg:address":"21 Commercial Rd",
    "sg:city":"Alstonville",
    "sg:classifiers":[
        {
            "category":"Banks & Credit Unions",
            "subcategory":"Financial Services",
            "type":"Services"
        }
    ],
    "sg:phone":"+61 2 6628 0688",
    "sg:postcode":"2477",
    "sg:province":"NSW",
    "sg:tags":[
        "planning"
    ],
    "wof:name":"Staruiala Ehrich CFP (BComm)",
    "wof:placetype":"venue"
},
  "geometry": {"coordinates":[153.440109253,-28.8404312134],"type":"Point"}
}