{
  "type": "Feature",
  "properties": {
    "iso:country":"AU",
    "sg:address":"12 Lawrence St",
    "sg:city":"Toowoomba",
    "sg:classifiers":[
        {
            "category":"Education",
            "subcategory":"School",
            "type":"Public Place"
        }
    ],
    "sg:phone":"+61 7 4637 1699",
    "sg:postcode":"4350",
    "sg:province":"QLD",
    "sg:tags":[
        "girl"
    ],
    "wof:name":"St Saviours Boarding School",
    "wof:placetype":"venue"
},
  "geometry": {"coordinates":[151.953476,-27.570873],"type":"Point"}
}