{
  "type": "Feature",
  "properties": {
    "addr:full":"2 Justin Rd Brooklyn VIC 3012",
    "addr:housenumber":"2",
    "addr:postcode":"3012",
    "addr:street":"Justin Rd",
    "iso:country":"AU",
    "sg:address":"2 Justin Rd",
    "sg:city":"Brooklyn",
    "sg:classifiers":[
        {
            "category":"Manufacturing",
            "subcategory":"Motor Vehicles & Parts",
            "type":"Manufacturing & Wholesale Goods"
        }
    ],
    "sg:phone":"+61 3 9314 6796",
    "sg:postcode":"3012",
    "sg:province":"VIC",
    "sg:tags":[
        "replacement"
    ],
    "wof:name":"Niss Truck Salvage Pty Ltd",
    "wof:placetype":"venue"
},
  "geometry": {"coordinates":[144.84963989299999,-37.8031921387],"type":"Point"}
}