{
  "type": "Feature",
  "properties": {
    "addr:full":"42a Spencer St Bunbury WA 6230",
    "addr:housenumber":"42a",
    "addr:postcode":"6230",
    "addr:street":"Spencer St",
    "iso:country":"AU",
    "sg:address":"42a Spencer St",
    "sg:city":"Bunbury",
    "sg:classifiers":[
        {
            "category":"Professional",
            "subcategory":"Art Services",
            "type":"Services"
        }
    ],
    "sg:phone":"+61 8 9721 6166",
    "sg:postcode":"6230",
    "sg:province":"WA",
    "sg:tags":[
        "picture",
        "frame",
        "framing"
    ],
    "wof:name":"Southern Picture Framers",
    "wof:placetype":"venue"
},
  "geometry": {"coordinates":[115.641548,-33.346897],"type":"Point"}
}