{
  "type": "Feature",
  "properties": {
    "addr:full":"3 Acushla Crt Sandy Bay TAS 7005",
    "addr:housenumber":"3",
    "addr:postcode":"7005",
    "addr:street":"Acushla Crt",
    "iso:country":"AU",
    "sg:address":"3 Acushla Crt",
    "sg:city":"Sandy Bay",
    "sg:classifiers":[
        {
            "category":"Health Services",
            "subcategory":"Doctor",
            "type":"Services"
        }
    ],
    "sg:phone":"+61 3 6225 2102",
    "sg:postcode":"7005",
    "sg:province":"TAS",
    "sg:tags":[
        "medical",
        "practitioner"
    ],
    "wof:name":"Epari S R Dr",
    "wof:placetype":"venue"
},
  "geometry": {"coordinates":[147.33436584500001,-42.9150924683],"type":"Point"}
}