{
  "type": "Feature",
  "properties": {
    "addr:full":"Cleveland St Surry Hills NSW 2010",
    "addr:postcode":"2010",
    "addr:street":"Cleveland St",
    "iso:country":"AU",
    "sg:address":"Cleveland St",
    "sg:city":"Surry Hills",
    "sg:classifiers":[
        {
            "category":"Building & Trades",
            "subcategory":"Locksmith",
            "type":"Services"
        }
    ],
    "sg:phone":"+61 1800 640 651",
    "sg:postcode":"2010",
    "sg:province":"NSW",
    "sg:tags":[
        "lock"
    ],
    "wof:name":"Darlinghurst-Surry Hills Locksmiths (24 Hour Mobile Service)",
    "wof:placetype":"venue"
},
  "geometry": {"coordinates":[151.20767211899999,-33.8898773193],"type":"Point"}
}