{
  "type": "Feature",
  "properties": {
    "addr:full":"49- 53 Capital Link Drv Campbellfield VIC 3061",
    "addr:housenumber":"53",
    "addr:postcode":"3061",
    "addr:street":"Capital Link Drv",
    "iso:country":"AU",
    "sg:address":"49- 53 Capital Link Drv",
    "sg:city":"Campbellfield",
    "sg:classifiers":[
        {
            "category":"Wholesale",
            "subcategory":"Farm Supplies",
            "type":"Manufacturing & Wholesale Goods"
        }
    ],
    "sg:phone":"+61 3 9357 8110",
    "sg:postcode":"3061",
    "sg:province":"VIC",
    "sg:tags":[
        "feed",
        "supplement",
        "stock"
    ],
    "wof:name":"Peters Pure Animal Foods",
    "wof:placetype":"venue"
},
  "geometry": {"coordinates":[144.96090698200001,-37.6528663635],"type":"Point"}
}