{
  "type": "Feature",
  "properties": {
    "addr:full":"69 Spencer St Bunbury WA 6230",
    "addr:housenumber":"69",
    "addr:postcode":"6230",
    "addr:street":"Spencer St",
    "iso:country":"AU",
    "sg:address":"69 Spencer St",
    "sg:city":"Bunbury",
    "sg:classifiers":[
        {
            "category":"Train Station",
            "subcategory":"Light Rail",
            "type":"Transportation"
        }
    ],
    "sg:phone":"+61 8 9791 5377",
    "sg:postcode":"6230",
    "sg:province":"WA",
    "sg:tags":[
        "equipment",
        "energy",
        "solar"
    ],
    "wof:name":"Exact Air",
    "wof:placetype":"venue"
},
  "geometry": {"coordinates":[115.641571,-33.346764],"type":"Point"}
}