{
  "type": "Feature",
  "properties": {
    "addr:full":"Cossia St Dee Why NSW 2099",
    "addr:postcode":"2099",
    "addr:street":"Cossia St",
    "iso:country":"AU",
    "sg:address":"Cossia St",
    "sg:city":"Dee Why",
    "sg:classifiers":[
        {
            "category":"Health Services",
            "subcategory":"Health Practitioner",
            "type":"Services"
        }
    ],
    "sg:phone":"+61 2 9984 7020",
    "sg:postcode":"2099",
    "sg:province":"NSW",
    "sg:tags":[
        "naturopath"
    ],
    "wof:name":"McIntosh Linda",
    "wof:placetype":"venue"
},
  "geometry": {"coordinates":[151.29510498100001,-33.7564468384],"type":"Point"}
}