{
  "type": "Feature",
  "properties": {
    "addr:full":"600 Bourke St Melbourne VIC 3000",
    "addr:housenumber":"600",
    "addr:postcode":"3000",
    "addr:street":"Bourke St",
    "iso:country":"AU",
    "sg:address":"600 Bourke St",
    "sg:city":"Melbourne",
    "sg:classifiers":[
        {
            "category":"Fast Food",
            "type":"Food & Drink"
        }
    ],
    "sg:phone":"+61 3 9670 1880",
    "sg:postcode":"3000",
    "sg:province":"VIC",
    "sg:tags":[
        "away",
        "take"
    ],
    "wof:name":"Bento Place",
    "wof:placetype":"venue"
},
  "geometry": {"coordinates":[144.956497192,-37.8160324097],"type":"Point"}
}