{
  "type": "Feature",
  "properties": {
    "iso:country":"AU",
    "sg:address":"18 Torrington St",
    "sg:city":"Canterbury",
    "sg:classifiers":[
        {
            "category":"Personal",
            "subcategory":"Beauty Salon",
            "type":"Services"
        }
    ],
    "sg:phone":"+61 3 9882 1161",
    "sg:postcode":"3126",
    "sg:province":"VIC",
    "sg:tags":[
        "supply",
        "artist",
        "make-up"
    ],
    "wof:name":"Musq",
    "wof:placetype":"venue"
},
  "geometry": {"coordinates":[145.062774658,-37.8189125061],"type":"Point"}
}