{
  "type": "Feature",
  "properties": {
    "addr:full":"6 Rossell St Port MacDonnell SA 5291",
    "addr:housenumber":"6",
    "addr:postcode":"5291",
    "addr:street":"Rossell St",
    "iso:country":"AU",
    "sg:address":"6 Rossell St",
    "sg:city":"Port MacDonnell",
    "sg:classifiers":[
        {
            "category":"Farming",
            "subcategory":"Fish & Marine Products",
            "type":"Manufacturing & Wholesale Goods"
        }
    ],
    "sg:phone":"+61 8 8738 2381",
    "sg:postcode":"5291",
    "sg:province":"SA",
    "sg:tags":[
        "fisherman"
    ],
    "wof:name":"Coutts T J",
    "wof:placetype":"venue"
},
  "geometry": {"coordinates":[140.692474,-38.055298],"type":"Point"}
}