{
  "type": "Feature",
  "properties": {
    "addr:full":"8 Greenstone Pl Bundoora VIC 3083",
    "addr:housenumber":"8",
    "addr:postcode":"3083",
    "addr:street":"Pl",
    "iso:country":"AU",
    "sg:address":"8 Greenstone Pl",
    "sg:city":"Bundoora",
    "sg:classifiers":[
        {
            "category":"Building & Trades",
            "subcategory":"Plumbing",
            "type":"Services"
        }
    ],
    "sg:phone":"+61 418 340 501",
    "sg:postcode":"3083",
    "sg:province":"VIC",
    "sg:tags":[
        "plumber",
        "gasfitters"
    ],
    "wof:name":"Kovele Plumbing",
    "wof:placetype":"venue"
},
  "geometry": {"coordinates":[145.05398559599999,-37.7126235962],"type":"Point"}
}