{
  "type": "Feature",
  "properties": {
    "addr:full":"Swansea General Practice Wellington St Swansea TAS 7190",
    "addr:postcode":"7190",
    "addr:street":"Wellington St",
    "iso:country":"AU",
    "sg:address":"Swansea General Practice Wellington St",
    "sg:city":"Swansea",
    "sg:classifiers":[
        {
            "category":"Health Services",
            "subcategory":"Optometrist",
            "type":"Services"
        }
    ],
    "sg:phone":"+61 3 6257 8205",
    "sg:postcode":"7190",
    "sg:province":"TAS",
    "wof:name":"Youd Rebecca",
    "wof:placetype":"venue"
},
  "geometry": {"coordinates":[148.075638,-42.126129],"type":"Point"}
}