{
  "type": "Feature",
  "properties": {
    "iso:country":"AU",
    "sg:address":"130 Wellington St",
    "sg:city":"Banyo",
    "sg:classifiers":[
        {
            "category":"Retail",
            "subcategory":"Auto Repair",
            "type":"Services"
        }
    ],
    "sg:phone":"+61 7 3830 4060",
    "sg:postcode":"4014",
    "sg:province":"QLD",
    "sg:tags":[
        "repairer",
        "motor",
        "engineer"
    ],
    "wof:name":"At Your Door Car Services",
    "wof:placetype":"venue"
},
  "geometry": {"coordinates":[153.072631836,-27.3760986328],"type":"Point"}
}