{
  "type": "Feature",
  "properties": {
    "iso:country":"AU",
    "sg:address":"4 Mort La",
    "sg:city":"Shortland",
    "sg:classifiers":[
        {
            "category":"Professional",
            "subcategory":"Printing & Photocopies",
            "type":"Services"
        }
    ],
    "sg:phone":"+61 2 4950 1293",
    "sg:postcode":"2307",
    "sg:province":"NSW",
    "sg:tags":[
        "screen",
        "printer"
    ],
    "wof:name":"Impressions Screenprinting",
    "wof:placetype":"venue"
},
  "geometry": {"coordinates":[151.689346,-32.874516],"type":"Point"}
}