{
  "type": "Feature",
  "properties": {
    "addr:full":"25-29 Cookson St Camberwell VIC 3124",
    "addr:housenumber":"25-29",
    "addr:postcode":"3124",
    "addr:street":"Cookson St",
    "iso:country":"AU",
    "sg:address":"25-29 Cookson St",
    "sg:city":"Camberwell",
    "sg:classifiers":[
        {
            "category":"Shopping",
            "subcategory":"Antiques",
            "type":"Retail Goods"
        }
    ],
    "sg:phone":"+61 3 9882 2028",
    "sg:postcode":"3124",
    "sg:province":"VIC",
    "wof:name":"Melbourne Antique Prints & Maps",
    "wof:placetype":"venue"
},
  "geometry": {"coordinates":[145.058685303,-37.8261451721],"type":"Point"}
}