{
  "type": "Feature",
  "properties": {
    "addr:full":"Bards Crt Nerang QLD 4211",
    "addr:postcode":"4211",
    "addr:street":"Bards Crt",
    "iso:country":"AU",
    "sg:address":"Bards Crt",
    "sg:city":"Nerang",
    "sg:classifiers":[
        {
            "category":"Social Services",
            "subcategory":"Child Care",
            "type":"Services"
        }
    ],
    "sg:phone":"+61 413 555 145",
    "sg:postcode":"4211",
    "sg:province":"QLD",
    "sg:tags":[
        "baby",
        "sitter"
    ],
    "wof:name":"Daily Sitters",
    "wof:placetype":"venue"
},
  "geometry": {"coordinates":[153.320770264,-28.0012321472],"type":"Point"}
}