{
  "type": "Feature",
  "properties": {
    "iso:country":"AU",
    "sg:address":"Lot 8 Elder St",
    "sg:city":"Heatherton",
    "sg:classifiers":[
        {
            "category":"Utilities",
            "subcategory":"Refuse",
            "type":"Services"
        }
    ],
    "sg:phone":"+61 3 9558 2477",
    "sg:postcode":"3202",
    "sg:province":"VIC",
    "sg:tags":[
        "remover",
        "rubbish"
    ],
    "wof:name":"Whelan Kartaway Pty Ltd",
    "wof:placetype":"venue"
},
  "geometry": {"coordinates":[145.104507,-37.927853],"type":"Point"}
}