{
  "type": "Feature",
  "properties": {
    "addr:full":"162 Gladstone St Mudgee NSW 2850",
    "addr:housenumber":"162",
    "addr:postcode":"2850",
    "addr:street":"Gladstone St",
    "iso:country":"AU",
    "sg:address":"162 Gladstone St",
    "sg:city":"Mudgee",
    "sg:classifiers":[
        {
            "category":"Professional",
            "type":"Services"
        }
    ],
    "sg:phone":"+61 2 6372 3755",
    "sg:postcode":"2850",
    "sg:province":"NSW",
    "sg:tags":[
        "courier"
    ],
    "wof:name":"Mudgee Courier Services",
    "wof:placetype":"venue"
},
  "geometry": {"coordinates":[149.574265,-32.591259],"type":"Point"}
}