{
  "type": "Feature",
  "properties": {
    "addr:full":"28 Samford Rd Alderley QLD 4051",
    "addr:housenumber":"28",
    "addr:postcode":"4051",
    "addr:street":"Samford Rd",
    "iso:country":"AU",
    "sg:address":"28 Samford Rd",
    "sg:city":"Alderley",
    "sg:classifiers":[
        {
            "category":"Banks & Credit Unions",
            "subcategory":"Investment Brokerage",
            "type":"Services"
        }
    ],
    "sg:phone":"+61 7 3352 5656",
    "sg:postcode":"4051",
    "sg:province":"QLD",
    "sg:tags":[
        "repairer",
        "typewriter"
    ],
    "wof:name":"Office Zone",
    "wof:placetype":"venue"
},
  "geometry": {"coordinates":[152.99998474099999,-27.4251499176],"type":"Point"}
}