{
  "type": "Feature",
  "properties": {
    "addr:full":"Shp51/ 235 Forest Lake Blv Forest Lake QLD 4078",
    "addr:housenumber":"235",
    "addr:postcode":"4078",
    "addr:street":"Forest Lake Blv",
    "iso:country":"AU",
    "sg:address":"Shp51/ 235 Forest Lake Blv",
    "sg:city":"Forest Lake",
    "sg:classifiers":[
        {
            "category":"Personal",
            "subcategory":"Nail Salon",
            "type":"Services"
        }
    ],
    "sg:phone":"+61 7 3879 6975",
    "sg:postcode":"4078",
    "sg:province":"QLD",
    "sg:tags":[
        "artificial"
    ],
    "wof:name":"Australia Nails",
    "wof:placetype":"venue"
},
  "geometry": {"coordinates":[152.96864318900001,-27.6256027222],"type":"Point"}
}