{
  "type": "Feature",
  "properties": {
    "addr:full":"Rickard Rd Bankstown NSW 2200",
    "addr:postcode":"2200",
    "addr:street":"Rickard Rd",
    "iso:country":"AU",
    "sg:address":"Rickard Rd",
    "sg:city":"Bankstown",
    "sg:classifiers":[
        {
            "category":"Retail",
            "subcategory":"Auto Repair",
            "type":"Services"
        }
    ],
    "sg:phone":"+61 2 9707 4993",
    "sg:postcode":"2200",
    "sg:province":"NSW",
    "sg:tags":[
        "repairer",
        "motor",
        "engineer"
    ],
    "wof:name":"K. Mart Tyre & Auto Service Centres",
    "wof:placetype":"venue"
},
  "geometry": {"coordinates":[151.03201300000001,-33.914204],"type":"Point"}
}