{
  "type": "Feature",
  "properties": {
    "addr:full":"38 Violet St Eagle Farm QLD 4009",
    "addr:housenumber":"38",
    "addr:postcode":"4009",
    "addr:street":"Violet St",
    "iso:country":"AU",
    "sg:address":"38 Violet St",
    "sg:city":"Eagle Farm",
    "sg:classifiers":[
        {
            "category":"Shopping",
            "subcategory":"Computers & Home Electronics",
            "type":"Retail Goods"
        }
    ],
    "sg:phone":"+61 7 3268 4699",
    "sg:postcode":"4009",
    "sg:province":"QLD",
    "sg:tags":[
        "hardware",
        "equipment"
    ],
    "wof:name":"Auto-Quote Qld",
    "wof:placetype":"venue"
},
  "geometry": {"coordinates":[153.084274292,-27.4304046631],"type":"Point"}
}