{
  "type": "Feature",
  "properties": {
    "iso:country":"AU",
    "sg:address":"Suite 9/ 50 Angove St",
    "sg:city":"North Perth",
    "sg:classifiers":[
        {
            "category":"Organizations",
            "subcategory":"Professional Association",
            "type":"Services"
        }
    ],
    "sg:phone":"+61 8 9228 1770",
    "sg:postcode":"6006",
    "sg:province":"WA",
    "sg:tags":[
        "web",
        "internet"
    ],
    "wof:name":"Infinite Logic",
    "wof:placetype":"venue"
},
  "geometry": {"coordinates":[115.857292175,-31.9296531677],"type":"Point"}
}