{
  "type": "Feature",
  "properties": {
    "iso:country":"AU",
    "sg:address":"Level 1 21 Bedford St",
    "sg:city":"North Melbourne",
    "sg:classifiers":[
        {
            "category":"Professional",
            "subcategory":"Management & Consulting",
            "type":"Services"
        }
    ],
    "sg:phone":"+61 3 9326 7577",
    "sg:postcode":"3051",
    "sg:province":"VIC",
    "sg:tags":[
        "consultant"
    ],
    "wof:name":"Dawson Consulting (International) Pty Ltd",
    "wof:placetype":"venue"
},
  "geometry": {"coordinates":[144.95588684099999,-37.8021392822],"type":"Point"}
}