{
  "type": "Feature",
  "properties": {
    "addr:full":"19 Wandella Ave Northmead NSW 2152",
    "addr:housenumber":"19",
    "addr:postcode":"2152",
    "addr:street":"Wandella Ave",
    "iso:country":"AU",
    "sg:address":"19 Wandella Ave",
    "sg:city":"Northmead",
    "sg:classifiers":[
        {
            "category":"Utilities",
            "type":"Services"
        }
    ],
    "sg:phone":"+61 2 9639 0241",
    "sg:postcode":"2152",
    "sg:province":"NSW",
    "sg:tags":[
        "refrigeration",
        "industrial",
        "commercial",
        "retail"
    ],
    "wof:name":"B.R. Refrigeration",
    "wof:placetype":"venue"
},
  "geometry": {"coordinates":[151.00312805199999,-33.7763557434],"type":"Point"}
}