{
  "type": "Feature",
  "properties": {
    "addr:full":"62 Old Maitland Rd Wyee NSW 2259",
    "addr:housenumber":"62",
    "addr:postcode":"2259",
    "addr:street":"Old Maitland Rd",
    "iso:country":"AU",
    "sg:address":"62 Old Maitland Rd",
    "sg:city":"Wyee",
    "sg:classifiers":[
        {
            "category":"Commercial Area",
            "type":"Public Place"
        }
    ],
    "sg:phone":"+61 2 4357 1900",
    "sg:postcode":"2259",
    "sg:province":"NSW",
    "sg:tags":[
        "heavy",
        "carrier"
    ],
    "wof:name":"Wyee Transport",
    "wof:placetype":"venue"
},
  "geometry": {"coordinates":[151.394241333,-33.285369873],"type":"Point"}
}