{
  "type": "Feature",
  "properties": {
    "addr:full":"86 Liverpool St Hobart TAS 7000",
    "addr:housenumber":"86",
    "addr:postcode":"7000",
    "addr:street":"Liverpool St",
    "iso:country":"AU",
    "sg:address":"86 Liverpool St",
    "sg:city":"Hobart",
    "sg:classifiers":[
        {
            "category":"Shopping",
            "subcategory":"Jewelry",
            "type":"Retail Goods"
        }
    ],
    "sg:phone":"+61 3 6231 2240",
    "sg:postcode":"7000",
    "sg:province":"TAS",
    "sg:tags":[
        "jeweller"
    ],
    "wof:name":"Indulge Contemporary Silver Jewellery",
    "wof:placetype":"venue"
},
  "geometry": {"coordinates":[147.327072144,-42.8815994263],"type":"Point"}
}