{
  "type": "Feature",
  "properties": {
    "addr:full":"PO Box 142 Braddon ACT 2612",
    "addr:postcode":"2612",
    "iso:country":"AU",
    "sg:address":"PO Box 142",
    "sg:city":"Braddon",
    "sg:classifiers":[
        {
            "category":"Professional",
            "subcategory":"Art Services",
            "type":"Services"
        }
    ],
    "sg:phone":"+61 419 159 408",
    "sg:postcode":"2612",
    "sg:province":"ACT",
    "sg:tags":[
        "interior",
        "designer"
    ],
    "wof:name":"Simone Interior Design",
    "wof:placetype":"venue"
},
  "geometry": {"coordinates":[149.13766479500001,-35.2748718262],"type":"Point"}
}