{
  "type": "Feature",
  "properties": {
    "addr:full":"Coolamon Rd Wagga Wagga NSW 2650",
    "addr:postcode":"2650",
    "addr:street":"Coolamon Rd",
    "iso:country":"AU",
    "sg:address":"Coolamon Rd",
    "sg:city":"Wagga Wagga",
    "sg:classifiers":[
        {
            "category":"Education",
            "subcategory":"University",
            "type":"Public Place"
        }
    ],
    "sg:phone":"+61 2 6939 5000",
    "sg:postcode":"2650",
    "sg:province":"NSW",
    "sg:tags":[
        "college",
        "tertiary"
    ],
    "wof:name":"TAFE NSW Riverina Institute",
    "wof:placetype":"venue"
},
  "geometry": {"coordinates":[147.379562378,-35.0692558289],"type":"Point"}
}