{
  "type": "Feature",
  "properties": {
    "addr:full":"Cnr Kwinana Beach & Patterson Rds Kwinana WA 6167",
    "addr:postcode":"6167",
    "addr:street":"Cnr",
    "iso:country":"AU",
    "sg:address":"Cnr Kwinana Beach & Patterson Rds",
    "sg:city":"Kwinana",
    "sg:classifiers":[
        {
            "category":"Manufacturing",
            "subcategory":"Chemicals & Compounds",
            "type":"Manufacturing & Wholesale Goods"
        }
    ],
    "sg:phone":"+61 8 9439 8200",
    "sg:postcode":"6167",
    "sg:province":"WA",
    "sg:tags":[
        "industrial"
    ],
    "wof:name":"Coogee Chemicals Pty Ltd",
    "wof:placetype":"venue"
},
  "geometry": {"coordinates":[115.77504,-32.244576],"type":"Point"}
}