{
  "type": "Feature",
  "properties": {
    "iso:country":"AU",
    "sg:address":"Cnr Bolsover & William Sts",
    "sg:city":"Rockhampton",
    "sg:classifiers":[
        {
            "category":"Fast Food",
            "type":"Food & Drink"
        }
    ],
    "sg:phone":"+61 7 4922 1255",
    "sg:postcode":"4700",
    "sg:province":"QLD",
    "sg:tags":[
        "away",
        "take"
    ],
    "wof:name":"Thai Tanee Restaurant",
    "wof:placetype":"venue"
},
  "geometry": {"coordinates":[150.52244567899999,-23.3927211761],"type":"Point"}
}