{
  "type": "Feature",
  "properties": {
    "iso:country":"AU",
    "sg:address":"424 Canterbury Rd",
    "sg:city":"Surrey Hills",
    "sg:classifiers":[
        {
            "category":"Retail",
            "subcategory":"Auto Repair",
            "type":"Services"
        }
    ],
    "sg:phone":"+61 3 9830 0223",
    "sg:postcode":"3127",
    "sg:province":"VIC",
    "sg:tags":[
        "testing",
        "inspection",
        "motor",
        "vehicle"
    ],
    "wof:name":"Surrey Hills Automotive Repairs",
    "wof:placetype":"venue"
},
  "geometry": {"coordinates":[145.09954834000001,-37.8263664246],"type":"Point"}
}