{
  "type": "Feature",
  "properties": {
    "addr:full":"6/ 611 Robinson Rd Aspley QLD 4034",
    "addr:housenumber":"/ 611",
    "addr:postcode":"4034",
    "addr:street":"Robinson Rd",
    "iso:country":"AU",
    "sg:address":"6/ 611 Robinson Rd",
    "sg:city":"Aspley",
    "sg:classifiers":[
        {
            "category":"Professional",
            "subcategory":"Management & Consulting",
            "type":"Services"
        }
    ],
    "sg:phone":"+61 7 3862 9300",
    "sg:postcode":"4034",
    "sg:province":"QLD",
    "sg:tags":[
        "consultant"
    ],
    "wof:name":"Workcover Consultancy Services",
    "wof:placetype":"venue"
},
  "geometry": {"coordinates":[153.02290300000001,-27.364565],"type":"Point"}
}