{
  "type": "Feature",
  "properties": {
    "addr:full":"Badger Creek Rd Healesville VIC 3777",
    "addr:postcode":"3777",
    "addr:street":"Badger Creek Rd",
    "iso:country":"AU",
    "sg:address":"Badger Creek Rd",
    "sg:city":"Healesville",
    "sg:classifiers":[
        {
            "category":"Education",
            "subcategory":"School",
            "type":"Public Place"
        }
    ],
    "sg:phone":"+61 3 5962 4019",
    "sg:postcode":"3777",
    "sg:province":"VIC",
    "sg:tags":[
        "state",
        "except",
        "nsw"
    ],
    "wof:name":"Badger Creek Primary School",
    "wof:placetype":"venue"
},
  "geometry": {"coordinates":[145.52247600000001,-37.654617],"type":"Point"}
}