{
  "type": "Feature",
  "properties": {
    "iso:country":"AU",
    "sg:address":"Suite 1, 2 Shepherd St",
    "sg:city":"Darwin",
    "sg:classifiers":[
        {
            "category":"Insurance",
            "subcategory":"Insurance Agent",
            "type":"Services"
        }
    ],
    "sg:phone":"+61 8 8941 0049",
    "sg:postcode":"0800",
    "sg:province":"NT",
    "sg:tags":[
        "broker"
    ],
    "wof:name":"Insurance Advisernet Australia Pty Limited",
    "wof:placetype":"venue"
},
  "geometry": {"coordinates":[130.839477539,-12.458571434],"type":"Point"}
}