{
  "type": "Feature",
  "properties": {
    "addr:full":"225 Charman Rd Cheltenham VIC 3192",
    "addr:housenumber":"225",
    "addr:postcode":"3192",
    "addr:street":"Charman Rd",
    "iso:country":"AU",
    "sg:address":"225 Charman Rd",
    "sg:city":"Cheltenham",
    "sg:classifiers":[
        {
            "category":"Health Services",
            "subcategory":"Doctor",
            "type":"Services"
        }
    ],
    "sg:phone":"+61 3 9583 2003",
    "sg:postcode":"3192",
    "sg:province":"VIC",
    "sg:tags":[
        "medical",
        "practitioner"
    ],
    "wof:name":"Pras Janette",
    "wof:placetype":"venue"
},
  "geometry": {"coordinates":[145.054763794,-37.9694213867],"type":"Point"}
}