{
  "type": "Feature",
  "properties": {
    "addr:full":"88 Koonoona Ave Villawood NSW 2163",
    "addr:housenumber":"88",
    "addr:postcode":"2163",
    "addr:street":"Koonoona Ave",
    "iso:country":"AU",
    "sg:address":"88 Koonoona Ave",
    "sg:city":"Villawood",
    "sg:classifiers":[
        {
            "category":"Home & Garden",
            "subcategory":"Carpets & Floor Coverings",
            "type":"Retail Goods"
        }
    ],
    "sg:phone":"+61 403 030 990",
    "sg:postcode":"2163",
    "sg:province":"NSW",
    "wof:name":"Allan Floor Covering",
    "wof:placetype":"venue"
},
  "geometry": {"coordinates":[150.96807861299999,-33.8846473694],"type":"Point"}
}