{
  "type": "Feature",
  "properties": {
    "iso:country":"AU",
    "sg:address":"Ormadale Rd",
    "sg:city":"Yeronga",
    "sg:classifiers":[
        {
            "category":"Home & Garden",
            "subcategory":"Building Materials",
            "type":"Retail Goods"
        }
    ],
    "sg:phone":"+61 7 3848 8459",
    "sg:postcode":"4104",
    "sg:province":"QLD",
    "sg:tags":[
        "tile",
        "roofing"
    ],
    "wof:name":"High-N-Dry Roofing Pty Ltd",
    "wof:placetype":"venue"
},
  "geometry": {"coordinates":[153.00218200699999,-27.5100860596],"type":"Point"}
}