{
  "type": "Feature",
  "properties": {
    "addr:full":"55/ 3 Harbourview Crs Abbotsford NSW 2046",
    "addr:housenumber":"55 / 3",
    "addr:postcode":"2046",
    "addr:street":"Harbourview Crs",
    "iso:country":"AU",
    "sg:address":"55/ 3 Harbourview Crs",
    "sg:city":"Abbotsford",
    "sg:classifiers":[
        {
            "category":"Arts & Performance",
            "subcategory":"Dance",
            "type":"Entertainment"
        }
    ],
    "sg:phone":"+61 419 483 108",
    "sg:postcode":"2046",
    "sg:province":"NSW",
    "sg:tags":[
        "theatrical",
        "ballet",
        "tuition"
    ],
    "wof:name":"Malone Sandra Dance Centre",
    "wof:placetype":"venue"
},
  "geometry": {"coordinates":[151.12855500000001,-33.850632],"type":"Point"}
}