{
  "type": "Feature",
  "properties": {
    "iso:country":"AU",
    "sg:address":"Seventh Ave",
    "sg:city":"South Townsville",
    "sg:classifiers":[
        {
            "category":"Wholesale",
            "subcategory":"Machinery & Supplies",
            "type":"Manufacturing & Wholesale Goods"
        }
    ],
    "sg:phone":"+61 7 4772 4799",
    "sg:postcode":"4810",
    "sg:province":"QLD",
    "sg:tags":[
        "rigging",
        "equipment",
        "hoisting"
    ],
    "wof:name":"All-Rig Lifting & Engineering Supplies Pty Ltd",
    "wof:placetype":"venue"
},
  "geometry": {"coordinates":[146.830536,-19.268295],"type":"Point"}
}