{
  "type": "Feature",
  "properties": {
    "iso:country":"AU",
    "sg:address":"Shp1/ 525 Box Rd",
    "sg:city":"Jannali",
    "sg:classifiers":[
        {
            "category":"Shopping",
            "type":"Retail Goods"
        }
    ],
    "sg:phone":"+61 2 9528 6816",
    "sg:postcode":"2226",
    "sg:province":"NSW",
    "sg:tags":[
        "new age",
        "product"
    ],
    "wof:name":"Shire Crystal",
    "wof:placetype":"venue"
},
  "geometry": {"coordinates":[151.066574097,-34.0161972046],"type":"Point"}
}