{
  "type": "Feature",
  "properties": {
    "addr:full":"24 Wentworth Ave Rowville VIC 3178",
    "addr:housenumber":"24",
    "addr:postcode":"3178",
    "addr:street":"Wentworth Ave",
    "iso:country":"AU",
    "sg:address":"24 Wentworth Ave",
    "sg:city":"Rowville",
    "sg:classifiers":[
        {
            "category":"Professional",
            "subcategory":"Business Services",
            "type":"Services"
        }
    ],
    "sg:phone":"+61 3 9752 7758",
    "sg:postcode":"3178",
    "sg:province":"VIC",
    "sg:tags":[
        "processing",
        "word"
    ],
    "wof:name":"A1 Wordprocessing",
    "wof:placetype":"venue"
},
  "geometry": {"coordinates":[145.26173400900001,-37.9176750183],"type":"Point"}
}