{
  "type": "Feature",
  "properties": {
    "addr:full":"4d/ 5 Belmore St Burwood NSW 2134",
    "addr:housenumber":"4d / 5",
    "addr:postcode":"2134",
    "addr:street":"Belmore St",
    "iso:country":"AU",
    "sg:address":"4d/ 5 Belmore St",
    "sg:city":"Burwood",
    "sg:classifiers":[
        {
            "category":"Social Services",
            "subcategory":"Retirement Home",
            "type":"Services"
        }
    ],
    "sg:phone":"+61 2 8746 5000",
    "sg:postcode":"2134",
    "sg:province":"NSW",
    "sg:tags":[
        "environmental",
        "consultant",
        "pollution"
    ],
    "wof:name":"Waste Management Association Of Australia",
    "wof:placetype":"venue"
},
  "geometry": {"coordinates":[151.105957031,-33.8791046143],"type":"Point"}
}