{
  "type": "Feature",
  "properties": {
    "addr:full":"Suite 5, Level 6 550 Stanley St South Brisbane QLD 4101",
    "addr:housenumber":"550",
    "addr:postcode":"4101",
    "addr:street":"Stanley St",
    "iso:country":"AU",
    "sg:address":"Suite 5, Level 6 550 Stanley St",
    "sg:city":"South Brisbane",
    "sg:classifiers":[
        {
            "category":"Personal",
            "type":"Services"
        }
    ],
    "sg:phone":"+61 7 3840 2847",
    "sg:postcode":"4101",
    "sg:province":"QLD",
    "sg:tags":[
        "reducing",
        "treatment",
        "weight"
    ],
    "wof:name":"Medically Supervised Weight Loss Programs",
    "wof:placetype":"venue"
},
  "geometry": {"coordinates":[153.02854919399999,-27.4848499298],"type":"Point"}
}