{
  "type": "Feature",
  "properties": {
    "iso:country":"AU",
    "sg:address":"7 Blamey Rd",
    "sg:city":"Wattlegrove",
    "sg:classifiers":[
        {
            "category":"Building & Trades",
            "subcategory":"Construction",
            "type":"Services"
        }
    ],
    "sg:phone":"+61 419 422 917",
    "sg:postcode":"2625",
    "sg:province":"NSW",
    "sg:tags":[
        "ceiling"
    ],
    "wof:name":"Andcor Interiors Pty Ltd",
    "wof:placetype":"venue"
},
  "geometry": {"coordinates":[148.30847168,-36.5016517639],"type":"Point"}
}