{
  "type": "Feature",
  "properties": {
    "addr:full":"Shp 4 a Belridge Shopng Cntr Beldon WA 6027",
    "addr:housenumber":"4",
    "addr:postcode":"6027",
    "addr:street":"A Belridge Shopng Cntr",
    "iso:country":"AU",
    "sg:address":"Shp 4",
    "sg:city":"a Belridge Shopng Cntr Beldon",
    "sg:classifiers":[
        {
            "category":"Professional",
            "subcategory":"Accounting & Tax Preparation",
            "type":"Services"
        }
    ],
    "sg:phone":"+61 8 9401 0603",
    "sg:postcode":"6027",
    "sg:province":"WA",
    "sg:tags":[
        "accountant",
        "auditor"
    ],
    "wof:name":"H&R Block",
    "wof:placetype":"venue"
},
  "geometry": {"coordinates":[115.76348877,-31.774520874],"type":"Point"}
}