{
  "type": "Feature",
  "properties": {
    "addr:full":"9 River St Springfield NSW 2250",
    "addr:housenumber":"9",
    "addr:postcode":"2250",
    "addr:street":"River St",
    "iso:country":"AU",
    "sg:address":"9 River St",
    "sg:city":"Springfield",
    "sg:classifiers":[
        {
            "category":"Commercial Area",
            "type":"Public Place"
        }
    ],
    "sg:phone":"+61 439 670 092",
    "sg:postcode":"2250",
    "sg:province":"NSW",
    "sg:tags":[
        "heavy",
        "carrier"
    ],
    "wof:name":"Johnstone Transport Services Pty Ltd",
    "wof:placetype":"venue"
},
  "geometry": {"coordinates":[151.38348388700001,-33.4303855896],"type":"Point"}
}