{
  "type": "Feature",
  "properties": {
    "addr:full":"Myer Sydney City Level 6 436 George St Sydney NSW 2000",
    "addr:housenumber":"436",
    "addr:postcode":"2000",
    "addr:street":"George St",
    "iso:country":"AU",
    "sg:address":"Myer Sydney City Level 6 436 George St",
    "sg:city":"Sydney",
    "sg:classifiers":[
        {
            "category":"Building & Trades",
            "subcategory":"Equipment Rental",
            "type":"Services"
        }
    ],
    "sg:phone":"+61 2 9238 9801",
    "sg:postcode":"2000",
    "sg:province":"NSW",
    "sg:tags":[
        "fitness"
    ],
    "wof:name":"Elite Fitness Equipment",
    "wof:placetype":"venue"
},
  "geometry": {"coordinates":[151.20713806099999,-33.870262146],"type":"Point"}
}