{
  "type": "Feature",
  "properties": {
    "addr:full":"44 Bantry Bay Rd Frenchs Forest NSW 2086",
    "addr:housenumber":"44",
    "addr:postcode":"2086",
    "addr:street":"Bantry Bay Rd",
    "iso:country":"AU",
    "sg:address":"44 Bantry Bay Rd",
    "sg:city":"Frenchs Forest",
    "sg:classifiers":[
        {
            "category":"Health Services",
            "subcategory":"Doctor",
            "type":"Services"
        }
    ],
    "sg:phone":"+61 2 9452 2133",
    "sg:postcode":"2086",
    "sg:province":"NSW",
    "sg:tags":[
        "medical",
        "practitioner"
    ],
    "wof:name":"Dr James O&#039;Brien",
    "wof:placetype":"venue"
},
  "geometry": {"coordinates":[151.23298645,-33.751739502],"type":"Point"}
}