{
  "type": "Feature",
  "properties": {
    "iso:country":"AU",
    "sg:address":"1 Hancock St",
    "sg:city":"Vermont South",
    "sg:classifiers":[
        {
            "category":"Building & Trades",
            "subcategory":"Cleaning & Sanitation",
            "type":"Services"
        }
    ],
    "sg:phone":"+61 3 9803 8796",
    "sg:postcode":"3133",
    "sg:province":"VIC",
    "sg:tags":[
        "industrial",
        "commercial",
        "contractor"
    ],
    "wof:name":"Box Hill Cleaning Service",
    "wof:placetype":"venue"
},
  "geometry": {"coordinates":[145.184783936,-37.8479804993],"type":"Point"}
}