{
  "type": "Feature",
  "properties": {
    "iso:country":"AU",
    "sg:address":"159 Bundall Rd",
    "sg:city":"Bundall",
    "sg:classifiers":[
        {
            "category":"Farming",
            "subcategory":"Crops",
            "type":"Manufacturing & Wholesale Goods"
        }
    ],
    "sg:phone":"+61 7 5591 7588",
    "sg:postcode":"4217",
    "sg:province":"QLD",
    "sg:tags":[
        "club",
        "rowing"
    ],
    "wof:name":"Surfers Paradise Rowing Club",
    "wof:placetype":"venue"
},
  "geometry": {"coordinates":[153.41444397000001,-28.0007686615],"type":"Point"}
}