{
  "type": "Feature",
  "properties": {
    "addr:full":"1/ 122 Pitt Town Dural Rd Pitt Town NSW 2756",
    "addr:housenumber":"/ 122",
    "addr:postcode":"2756",
    "addr:street":"Dural Rd",
    "iso:country":"AU",
    "sg:address":"1/ 122 Pitt Town Dural Rd",
    "sg:city":"Pitt Town",
    "sg:classifiers":[
        {
            "category":"Wholesale",
            "subcategory":"Home Furnishings",
            "type":"Manufacturing & Wholesale Goods"
        }
    ],
    "sg:phone":"+61 2 4580 9399",
    "sg:postcode":"2756",
    "sg:province":"NSW",
    "sg:tags":[
        "wholesaler",
        "mfrs",
        "kitchenware"
    ],
    "wof:name":"Stutech Pty Ltd",
    "wof:placetype":"venue"
},
  "geometry": {"coordinates":[150.87620544399999,-33.5808029175],"type":"Point"}
}