{
  "type": "Feature",
  "properties": {
    "addr:full":"114 Queen St Ayr QLD 4807",
    "addr:housenumber":"114",
    "addr:postcode":"4807",
    "addr:street":"Queen St",
    "iso:country":"AU",
    "sg:address":"114 Queen St",
    "sg:city":"Ayr",
    "sg:classifiers":[
        {
            "category":"Shopping",
            "subcategory":"Clothing, Apparel, & Fashions",
            "type":"Retail Goods"
        }
    ],
    "sg:phone":"+61 7 4783 1615",
    "sg:postcode":"4807",
    "sg:province":"QLD",
    "sg:tags":[
        "lady",
        "wear"
    ],
    "wof:name":"Glen-Dell",
    "wof:placetype":"venue"
},
  "geometry": {"coordinates":[147.40643310600001,-19.5749282837],"type":"Point"}
}