{
  "type": "Feature",
  "properties": {
    "addr:full":"255 Kangaroo Ground- Warrand Rd Kangaroo Ground VIC 3097",
    "addr:housenumber":"255",
    "addr:postcode":"3097",
    "addr:street":"Kangaroo Ground Warrand Rd",
    "iso:country":"AU",
    "sg:address":"255 Kangaroo Ground- Warrand Rd",
    "sg:city":"Kangaroo Ground",
    "sg:classifiers":[
        {
            "category":"Building & Trades",
            "subcategory":"Construction",
            "type":"Services"
        }
    ],
    "sg:phone":"+61 3 9712 0432",
    "sg:postcode":"3097",
    "sg:province":"VIC",
    "sg:tags":[
        "contractor"
    ],
    "wof:name":"Versteegen Joseph",
    "wof:placetype":"venue"
},
  "geometry": {"coordinates":[145.215667725,-37.6913490295],"type":"Point"}
}