{
  "type": "Feature",
  "properties": {
    "iso:country":"AU",
    "sg:address":"195 Kings Rd",
    "sg:city":"New Lambton",
    "sg:classifiers":[
        {
            "category":"Health Services",
            "subcategory":"Clinic",
            "type":"Services"
        }
    ],
    "sg:phone":"+61 2 4957 2825",
    "sg:postcode":"2305",
    "sg:province":"NSW",
    "sg:tags":[
        "aromatherapy"
    ],
    "wof:name":"New Lambton Aromatherapy Clinic",
    "wof:placetype":"venue"
},
  "geometry": {"coordinates":[151.717148,-32.934593],"type":"Point"}
}