{
  "type": "Feature",
  "properties": {
    "iso:country":"AU",
    "sg:address":"Cnr Smith & George Sts",
    "sg:city":"Longford",
    "sg:classifiers":[
        {
            "category":"Health Services",
            "subcategory":"Doctor",
            "type":"Services"
        }
    ],
    "sg:phone":"+61 3 6391 1170",
    "sg:postcode":"7301",
    "sg:province":"TAS",
    "sg:tags":[
        "medical",
        "practitioner"
    ],
    "wof:name":"Joske F",
    "wof:placetype":"venue"
},
  "geometry": {"coordinates":[147.117142,-41.585522],"type":"Point"}
}