{
  "type": "Feature",
  "properties": {
    "addr:full":"Smithfield Centre, Cnr Kennedy St & Cook Hwy Smithfield QLD 4350",
    "addr:postcode":"4350",
    "addr:street":"Cnr Kennedy St & Cook Hwy",
    "iso:country":"AU",
    "sg:address":"Smithfield Centre, Cnr Kennedy St & Cook Hwy",
    "sg:city":"Smithfield",
    "sg:classifiers":[
        {
            "category":"Shopping",
            "subcategory":"Mobile Phones",
            "type":"Retail Goods"
        }
    ],
    "sg:phone":"+61 7 4038 2077",
    "sg:postcode":"4350",
    "sg:province":"QLD",
    "sg:tags":[
        "telephone",
        "accessory"
    ],
    "wof:name":"Fone Zone",
    "wof:placetype":"venue"
},
  "geometry": {"coordinates":[151.962234,-27.55242],"type":"Point"}
}