{
  "type": "Feature",
  "properties": {
    "addr:full":"Heysen St Weston ACT 2611",
    "addr:postcode":"2611",
    "addr:street":"St",
    "iso:country":"AU",
    "sg:address":"Heysen St",
    "sg:city":"Weston",
    "sg:classifiers":[
        {
            "category":"Education",
            "subcategory":"University",
            "type":"Public Place"
        }
    ],
    "sg:phone":"+61 2 6288 0760",
    "sg:postcode":"2611",
    "sg:province":"ACT",
    "sg:tags":[
        "educational",
        "organisation",
        "cultural"
    ],
    "wof:name":"Nature & Society Forum",
    "wof:placetype":"venue"
},
  "geometry": {"coordinates":[149.05976867699999,-35.3320922852],"type":"Point"}
}