{
  "type": "Feature",
  "properties": {
    "iso:country":"AU",
    "sg:address":"Cnr King St & Shellharbour Rd",
    "sg:city":"Warrawong",
    "sg:classifiers":[
        {
            "category":"Utilities",
            "subcategory":"Water",
            "type":"Services"
        }
    ],
    "sg:phone":"+61 2 4274 1111",
    "sg:postcode":"2502",
    "sg:province":"NSW",
    "sg:tags":[
        "hot",
        "system"
    ],
    "wof:name":"De Wit Hot Water Services",
    "wof:placetype":"venue"
},
  "geometry": {"coordinates":[150.887604,-34.484882],"type":"Point"}
}