{
  "type": "Feature",
  "properties": {
    "addr:full":"Lot 9 Louise Crt Bundaberg QLD 4670",
    "addr:housenumber":"9",
    "addr:postcode":"4670",
    "addr:street":"Louise Crt",
    "iso:country":"AU",
    "sg:address":"Lot 9 Louise Crt",
    "sg:city":"Bundaberg",
    "sg:classifiers":[
        {
            "category":"Building & Trades",
            "subcategory":"Construction",
            "type":"Services"
        }
    ],
    "sg:phone":"+61 7 4155 2844",
    "sg:postcode":"4670",
    "sg:province":"QLD",
    "sg:tags":[
        "pool",
        "swimming"
    ],
    "wof:name":"Aqualine Pools",
    "wof:placetype":"venue"
},
  "geometry": {"coordinates":[152.27398681599999,-24.907535553],"type":"Point"}
}