{
  "type": "Feature",
  "properties": {
    "iso:country":"AU",
    "sg:address":"35 Torwood Rd",
    "sg:city":"Warrimoo",
    "sg:classifiers":[
        {
            "category":"Retail",
            "subcategory":"Driving School",
            "type":"Services"
        }
    ],
    "sg:phone":"+61 2 4753 6260",
    "sg:postcode":"2774",
    "sg:province":"NSW",
    "wof:name":"Instructor The",
    "wof:placetype":"venue"
},
  "geometry": {"coordinates":[150.59661865199999,-33.7166442871],"type":"Point"}
}