{
  "type": "Feature",
  "properties": {
    "iso:country":"AU",
    "sg:address":"Cnr Hume Hwy & Rookwood Rd",
    "sg:city":"Bankstown",
    "sg:classifiers":[
        {
            "category":"Home & Garden",
            "subcategory":"Carpets & Floor Coverings",
            "type":"Retail Goods"
        }
    ],
    "sg:phone":"+61 2 9709 6022",
    "sg:postcode":"2200",
    "sg:province":"NSW",
    "sg:tags":[
        "tile",
        "wall"
    ],
    "wof:name":"Versatile Ceramics",
    "wof:placetype":"venue"
},
  "geometry": {"coordinates":[151.03602599999999,-33.906391],"type":"Point"}
}