{
  "type": "Feature",
  "properties": {
    "addr:full":"1/ 13 Penny Pl Arndell Park NSW 2148",
    "addr:housenumber":"/ 13",
    "addr:postcode":"2148",
    "addr:street":"Penny Pl",
    "iso:country":"AU",
    "sg:address":"1/ 13 Penny Pl",
    "sg:city":"Arndell Park",
    "sg:classifiers":[
        {
            "category":"Wholesale",
            "subcategory":"Machinery & Supplies",
            "type":"Manufacturing & Wholesale Goods"
        }
    ],
    "sg:phone":"+61 2 9671 5011",
    "sg:postcode":"2148",
    "sg:province":"NSW",
    "sg:tags":[
        "machine",
        "tool",
        "engineer"
    ],
    "wof:name":"Doall Aust Pty Ltd",
    "wof:placetype":"venue"
},
  "geometry": {"coordinates":[150.89503479000001,-33.7961196899],"type":"Point"}
}