{
  "type": "Feature",
  "properties": {
    "iso:country":"AU",
    "sg:address":"125 Sherbourne Rd",
    "sg:city":"Montmorency",
    "sg:classifiers":[
        {
            "category":"Education",
            "subcategory":"Special Training",
            "type":"Public Place"
        }
    ],
    "sg:phone":"+61 3 9434 5622",
    "sg:postcode":"3094",
    "sg:province":"VIC",
    "sg:tags":[
        "development"
    ],
    "wof:name":"Aldridge Neville",
    "wof:placetype":"venue"
},
  "geometry": {"coordinates":[145.132644653,-37.7127418518],"type":"Point"}
}