{
  "type": "Feature",
  "properties": {
    "iso:country":"AU",
    "sg:address":"13a Church St",
    "sg:city":"Traralgon",
    "sg:classifiers":[
        {
            "category":"Professional",
            "subcategory":"Engineering",
            "type":"Services"
        }
    ],
    "sg:phone":"+61 3 5174 9911",
    "sg:postcode":"3844",
    "sg:province":"VIC",
    "sg:tags":[
        "consulting",
        "engineer"
    ],
    "wof:name":"Chris O&#039;Brien & Company Pty Ltd",
    "wof:placetype":"venue"
},
  "geometry": {"coordinates":[146.53492736800001,-38.1979026794],"type":"Point"}
}