{
  "type": "Feature",
  "properties": {
    "addr:full":"Lvl 13, Macquarie House 167 Macquarie St Sydney NSW 2000",
    "addr:housenumber":"167",
    "addr:postcode":"2000",
    "addr:street":"Macquarie St",
    "iso:country":"AU",
    "sg:address":"Lvl 13, Macquarie House 167 Macquarie St",
    "sg:city":"Sydney",
    "sg:classifiers":[
        {
            "category":"Professional",
            "subcategory":"Accounting & Tax Preparation",
            "type":"Services"
        }
    ],
    "sg:phone":"+61 2 8667 3200",
    "sg:postcode":"2000",
    "sg:province":"NSW",
    "sg:tags":[
        "accountant",
        "auditor"
    ],
    "wof:name":"Guardian Partners",
    "wof:placetype":"venue"
},
  "geometry": {"coordinates":[151.21234130900001,-33.8663597107],"type":"Point"}
}