{
  "type": "Feature",
  "properties": {
    "addr:full":"PO Box 114 Ballarat VIC 3352",
    "addr:postcode":"3352",
    "iso:country":"AU",
    "sg:address":"PO Box 114",
    "sg:city":"Ballarat",
    "sg:classifiers":[
        {
            "category":"Retail",
            "subcategory":"Auto Rental",
            "type":"Services"
        }
    ],
    "sg:phone":"+61 3 5334 6352",
    "sg:postcode":"3352",
    "sg:province":"VIC",
    "sg:tags":[
        "car",
        "wedding"
    ],
    "wof:name":"Camelot Carriage Hire",
    "wof:placetype":"venue"
},
  "geometry": {"coordinates":[143.89198300000001,-37.435986],"type":"Point"}
}