{
  "type": "Feature",
  "properties": {
    "addr:full":"216 Nicholson Rd Subiaco WA 6008",
    "addr:housenumber":"216",
    "addr:postcode":"6008",
    "addr:street":"Nicholson Rd",
    "iso:country":"AU",
    "sg:address":"216 Nicholson Rd",
    "sg:city":"Subiaco",
    "sg:classifiers":[
        {
            "category":"Shopping",
            "subcategory":"Music",
            "type":"Retail Goods"
        }
    ],
    "sg:phone":"+61 8 9388 1380",
    "sg:postcode":"6008",
    "sg:province":"WA",
    "sg:tags":[
        "instrument",
        "musical"
    ],
    "sg:website":"http://www.collegebrassandstrings.com.au",
    "wof:name":"College Brass & Strings",
    "wof:placetype":"venue"
},
  "geometry": {"coordinates":[115.81452179,-31.9561595917],"type":"Point"}
}