{
  "type": "Feature",
  "properties": {
    "addr:full":"2064 Gold Coast Hwy Miami QLD 4220",
    "addr:housenumber":"2064",
    "addr:postcode":"4220",
    "addr:street":"Gold Coast Hwy",
    "iso:country":"AU",
    "sg:address":"2064 Gold Coast Hwy",
    "sg:city":"Miami",
    "sg:classifiers":[
        {
            "category":"Retail",
            "subcategory":"Auto Rental",
            "type":"Services"
        }
    ],
    "sg:phone":"+61 7 5572 3533",
    "sg:postcode":"4220",
    "sg:province":"QLD",
    "sg:tags":[
        "bus",
        "truck"
    ],
    "wof:name":"Brian's Auto Hire",
    "wof:placetype":"venue"
},
  "geometry": {"coordinates":[153.44119262699999,-28.0683689117],"type":"Point"}
}