{
  "type": "Feature",
  "properties": {
    "iso:country":"AU",
    "sg:address":"13 Lowan Ave",
    "sg:city":"Glenalta",
    "sg:classifiers":[
        {
            "category":"Food & Beverages",
            "subcategory":"Specialty",
            "type":"Retail Goods"
        }
    ],
    "sg:phone":"+61 401 997 557",
    "sg:postcode":"5052",
    "sg:province":"SA",
    "sg:tags":[
        "product",
        "health"
    ],
    "wof:name":"Tahitian Noni Juice Morinda Distributor: Cecile Horsefall",
    "wof:placetype":"venue"
},
  "geometry": {"coordinates":[138.629425,-35.013004],"type":"Point"}
}