{
  "type": "Feature",
  "properties": {
    "iso:country":"AU",
    "sg:address":"Level 2, 382 Pacific Hwy",
    "sg:city":"Crows Nest",
    "sg:classifiers":[
        {
            "category":"Professional",
            "subcategory":"Computer Services",
            "type":"Services"
        }
    ],
    "sg:phone":"+61 2 9437 4277",
    "sg:postcode":"2065",
    "sg:province":"NSW",
    "sg:tags":[
        "package",
        "software"
    ],
    "wof:name":"Business Professionals Pty Ltd",
    "wof:placetype":"venue"
},
  "geometry": {"coordinates":[151.198928833,-33.8259468079],"type":"Point"}
}