{
  "type": "Feature",
  "properties": {
    "addr:full":"Larapinta Drv Alice Springs NT 0870",
    "addr:postcode":"nt 0870",
    "addr:street":"Larapinta Drv",
    "iso:country":"AU",
    "sg:address":"Larapinta Drv",
    "sg:city":"Alice Springs",
    "sg:classifiers":[
        {
            "category":"Communications",
            "subcategory":"News Services",
            "type":"Services"
        }
    ],
    "sg:phone":"+61 8 8951 5686",
    "sg:postcode":"0870",
    "sg:province":"NT",
    "sg:tags":[
        "information",
        "tourist",
        "attractions"
    ],
    "wof:name":"Central Australia Aviation Museum",
    "wof:placetype":"venue"
},
  "geometry": {"coordinates":[133.83323669399999,-23.6817703247],"type":"Point"}
}