{
  "type": "Feature",
  "properties": {
    "addr:full":"25 Scribner Ave Forestdale QLD 4118",
    "addr:housenumber":"25",
    "addr:postcode":"4118",
    "addr:street":"Scribner Ave",
    "iso:country":"AU",
    "sg:address":"25 Scribner Ave",
    "sg:city":"Forestdale",
    "sg:classifiers":[
        {
            "category":"Utilities",
            "subcategory":"Electric",
            "type":"Services"
        }
    ],
    "sg:phone":"+61 421 690 802",
    "sg:postcode":"4118",
    "sg:province":"QLD",
    "sg:tags":[
        "electrical",
        "contractor"
    ],
    "wof:name":"De Vita J & M Electrical",
    "wof:placetype":"venue"
},
  "geometry": {"coordinates":[153.01683044399999,-27.6683692932],"type":"Point"}
}