{
  "type": "Feature",
  "properties": {
    "addr:full":"Albany Hwy Narrakine WA 6391",
    "addr:postcode":"6391",
    "addr:street":"Albany Hwy Narrakine",
    "iso:country":"AU",
    "sg:address":"Albany Hwy",
    "sg:city":"Narrakine",
    "sg:classifiers":[
        {
            "category":"Farming",
            "subcategory":"Farm",
            "type":"Manufacturing & Wholesale Goods"
        }
    ],
    "sg:phone":"+61 8 9885 6042",
    "sg:postcode":"6391",
    "sg:province":"WA",
    "sg:tags":[
        "farmer"
    ],
    "wof:name":"Williamson P H & H G",
    "wof:placetype":"venue"
},
  "geometry": {"coordinates":[116.73248291,-32.923915863],"type":"Point"}
}