{
  "type": "Feature",
  "properties": {
    "iso:country":"AU",
    "sg:address":"11- 13 Belah St",
    "sg:city":"Leeton",
    "sg:classifiers":[
        {
            "category":"Building & Trades",
            "subcategory":"Equipment Rental",
            "type":"Services"
        }
    ],
    "sg:phone":"+61 2 6953 6976",
    "sg:postcode":"2705",
    "sg:province":"NSW",
    "sg:tags":[
        "builder",
        "contractor"
    ],
    "wof:name":"Arnold Bill Pty Ltd",
    "wof:placetype":"venue"
},
  "geometry": {"coordinates":[146.40061950699999,-34.5530433655],"type":"Point"}
}