{
  "type": "Feature",
  "properties": {
    "addr:full":"PO Box 36130 Winnellie NT 0821",
    "addr:postcode":"nt 0821",
    "iso:country":"AU",
    "sg:address":"PO Box 36130",
    "sg:city":"Winnellie",
    "sg:classifiers":[
        {
            "category":"School Buses",
            "type":"Transportation"
        }
    ],
    "sg:phone":"+61 8 8984 4336",
    "sg:postcode":"0821",
    "sg:province":"NT",
    "sg:tags":[
        "brick"
    ],
    "wof:name":"Quality Exteriors",
    "wof:placetype":"venue"
},
  "geometry": {"coordinates":[130.87991332999999,-12.4266233444],"type":"Point"}
}