{
  "type": "Feature",
  "properties": {
    "addr:full":"83 Kathryn Rd Knoxfield VIC 3180",
    "addr:housenumber":"83",
    "addr:postcode":"3180",
    "addr:street":"Kathryn Rd",
    "iso:country":"AU",
    "sg:address":"83 Kathryn Rd",
    "sg:city":"Knoxfield",
    "sg:classifiers":[
        {
            "category":"Health Services",
            "subcategory":"Dentist",
            "type":"Services"
        }
    ],
    "sg:phone":"+61 3 9778 6383",
    "sg:postcode":"3180",
    "sg:province":"VIC",
    "sg:tags":[
        "dental",
        "prosthetist"
    ],
    "wof:name":"Monahan Dental Prosthetics",
    "wof:placetype":"venue"
},
  "geometry": {"coordinates":[145.24891662600001,-37.8863677979],"type":"Point"}
}