{
  "type": "Feature",
  "properties": {
    "addr:full":"Days Rd Grange QLD 4051",
    "addr:postcode":"4051",
    "addr:street":"Days Rd",
    "iso:country":"AU",
    "sg:address":"Days Rd",
    "sg:city":"Grange",
    "sg:classifiers":[
        {
            "category":"Insurance",
            "subcategory":"Insurance Agent",
            "type":"Services"
        }
    ],
    "sg:phone":"+61 7 3352 6355",
    "sg:postcode":"4051",
    "sg:province":"QLD",
    "sg:tags":[
        "broker"
    ],
    "wof:name":"IT Computer Insurance Brokers",
    "wof:placetype":"venue"
},
  "geometry": {"coordinates":[153.01556396500001,-27.4260673523],"type":"Point"}
}