{
  "type": "Feature",
  "properties": {
    "addr:full":"562 Spencer St West Melbourne VIC 3003",
    "addr:housenumber":"562",
    "addr:postcode":"3003",
    "addr:street":"Spencer St",
    "iso:country":"AU",
    "sg:address":"562 Spencer St",
    "sg:city":"West Melbourne",
    "sg:classifiers":[
        {
            "category":"Shopping",
            "subcategory":"Computers & Home Electronics",
            "type":"Retail Goods"
        }
    ],
    "sg:phone":"+61 3 9321 8300",
    "sg:postcode":"3003",
    "sg:province":"VIC",
    "sg:tags":[
        "equipment",
        "part",
        "electronic"
    ],
    "wof:name":"Radio Parts Group",
    "wof:placetype":"venue"
},
  "geometry": {"coordinates":[144.94715881400001,-37.8070716858],"type":"Point"}
}