{
  "type": "Feature",
  "properties": {
    "addr:full":"2 Tooronga Ave Edwardstown SA 5039",
    "addr:housenumber":"2",
    "addr:postcode":"5039",
    "addr:street":"Tooronga Ave",
    "iso:country":"AU",
    "sg:address":"2 Tooronga Ave",
    "sg:city":"Edwardstown",
    "sg:classifiers":[
        {
            "category":"Building & Trades",
            "subcategory":"Construction",
            "type":"Services"
        }
    ],
    "sg:phone":"+61 8 8276 2488",
    "sg:postcode":"5039",
    "sg:province":"SA",
    "sg:tags":[
        "equipment",
        "system",
        "automation"
    ],
    "wof:name":"PV Technologies Pty Ltd",
    "wof:placetype":"venue"
},
  "geometry": {"coordinates":[138.57127380399999,-34.9927253723],"type":"Point"}
}