{
  "type": "Feature",
  "properties": {
    "addr:full":"62 Hudson Rd Spotswood VIC 3015",
    "addr:housenumber":"62",
    "addr:postcode":"3015",
    "addr:street":"Hudson Rd",
    "iso:country":"AU",
    "sg:address":"62 Hudson Rd",
    "sg:city":"Spotswood",
    "sg:classifiers":[
        {
            "category":"Travel",
            "subcategory":"Hotels & Motels",
            "type":"Entertainment"
        }
    ],
    "sg:phone":"+61 3 9391 1056",
    "sg:postcode":"3015",
    "sg:province":"VIC",
    "sg:tags":[
        "accommodation"
    ],
    "wof:name":"Spotswood Hotel",
    "wof:placetype":"venue"
},
  "geometry": {"coordinates":[144.886444092,-37.8299369812],"type":"Point"}
}