{
  "type": "Feature",
  "properties": {
    "iso:country":"AU",
    "sg:address":"PO Box 1318",
    "sg:city":"Caloundra",
    "sg:classifiers":[
        {
            "category":"Arts & Performance",
            "subcategory":"Comedy Club",
            "type":"Entertainment"
        }
    ],
    "sg:phone":"+61 419 679 085",
    "sg:postcode":"4551",
    "sg:province":"QLD",
    "sg:tags":[
        "piano",
        "removal"
    ],
    "wof:name":"Queensland Furniture Transport",
    "wof:placetype":"venue"
},
  "geometry": {"coordinates":[153.124755859,-26.7936191559],"type":"Point"}
}