{
  "type": "Feature",
  "properties": {
    "addr:full":"Hillend Road Child Care Centre, 209 Hillend Rd, Doonside NSW 2767",
    "addr:housenumber":"209",
    "addr:postcode":"2767",
    "addr:street":"Hillend;Hillend Rd",
    "iso:country":"AU",
    "sg:address":"Hillend Road",
    "sg:city":"Child Care Centre, 209 Hillend Rd, Doonside",
    "sg:classifiers":[
        {
            "category":"Banks & Credit Unions",
            "subcategory":"Investment Brokerage",
            "type":"Services"
        }
    ],
    "sg:phone":"+61 2 9626 7001",
    "sg:postcode":"2767",
    "sg:province":"NSW",
    "sg:tags":[
        "care",
        "day",
        "family",
        "child"
    ],
    "wof:name":"Blacktown City Council",
    "wof:placetype":"venue"
},
  "geometry": {"coordinates":[150.87237548799999,-33.7489204407],"type":"Point"}
}