{
  "type": "Feature",
  "properties": {
    "addr:full":"425 Werombi Rd Camden NSW 2570",
    "addr:housenumber":"425",
    "addr:postcode":"2570",
    "addr:street":"Werombi Rd",
    "iso:country":"AU",
    "sg:address":"425 Werombi Rd",
    "sg:city":"Camden",
    "sg:classifiers":[
        {
            "category":"Education",
            "subcategory":"University",
            "type":"Public Place"
        }
    ],
    "sg:phone":"+61 2 4655 0611",
    "sg:postcode":"2570",
    "sg:province":"NSW",
    "sg:tags":[
        "college",
        "tertiary"
    ],
    "wof:name":"The Uni of Sydney-Faculty of Vet.Science",
    "wof:placetype":"venue"
},
  "geometry": {"coordinates":[150.607696533,-33.9900474548],"type":"Point"}
}