{
  "type": "Feature",
  "properties": {
    "addr:full":"Heugh St Tamworth NSW 2340",
    "addr:postcode":"2340",
    "addr:street":"St",
    "iso:country":"AU",
    "sg:address":"Heugh St",
    "sg:city":"Tamworth",
    "sg:classifiers":[
        {
            "category":"Building & Trades",
            "subcategory":"Construction",
            "type":"Services"
        }
    ],
    "sg:phone":"+61 412 259 588",
    "sg:postcode":"2340",
    "sg:province":"NSW",
    "sg:tags":[
        "concrete",
        "contractor"
    ],
    "wof:name":"Classic Patterned Concrete",
    "wof:placetype":"venue"
},
  "geometry": {"coordinates":[150.918045044,-31.111869812],"type":"Point"}
}