{
  "type": "Feature",
  "properties": {
    "addr:full":"Footscray Markets Hopkins St Footscray VIC 3011",
    "addr:postcode":"3011",
    "addr:street":"Hopkins St",
    "iso:country":"AU",
    "sg:address":"Footscray Markets Hopkins St",
    "sg:city":"Footscray",
    "sg:classifiers":[
        {
            "category":"Food & Beverages",
            "subcategory":"Meat & Fish",
            "type":"Retail Goods"
        }
    ],
    "sg:phone":"+61 3 9689 0672",
    "sg:postcode":"3011",
    "sg:province":"VIC",
    "sg:tags":[
        "seafood"
    ],
    "wof:name":"Best Kay Seafood Pty Ltd",
    "wof:placetype":"venue"
},
  "geometry": {"coordinates":[144.89970398,-37.7997970581],"type":"Point"}
}