{
  "type": "Feature",
  "properties": {
    "addr:full":"1267 South Rd St Marys SA 5042",
    "addr:housenumber":"1267",
    "addr:postcode":"5042",
    "addr:street":"South Rd",
    "iso:country":"AU",
    "sg:address":"1267 South Rd",
    "sg:city":"St Marys",
    "sg:classifiers":[
        {
            "category":"Recreation",
            "subcategory":"Fishing",
            "type":"Entertainment"
        }
    ],
    "sg:phone":"+61 8 8374 4788",
    "sg:postcode":"5042",
    "sg:province":"SA",
    "sg:tags":[
        "tackle"
    ],
    "wof:name":"Got One Fishing & Outdoor Leisure",
    "wof:placetype":"venue"
},
  "geometry": {"coordinates":[138.57591199999999,-35.003967],"type":"Point"}
}