{
  "type": "Feature",
  "properties": {
    "addr:full":"13 Coral St Maleny QLD 4552",
    "addr:housenumber":"13",
    "addr:postcode":"4552",
    "addr:street":"Coral St",
    "iso:country":"AU",
    "sg:address":"13 Coral St",
    "sg:city":"Maleny",
    "sg:classifiers":[
        {
            "category":"Social Services",
            "subcategory":"Adult Care",
            "type":"Services"
        }
    ],
    "sg:phone":"+61 7 5494 3855",
    "sg:postcode":"4552",
    "sg:province":"QLD",
    "sg:tags":[
        "towing"
    ],
    "wof:name":"Maleny Autocare",
    "wof:placetype":"venue"
},
  "geometry": {"coordinates":[152.85244750999999,-26.7595157623],"type":"Point"}
}