{
  "type": "Feature",
  "properties": {
    "addr:full":"32 Flinders St Wollongong NSW 2500",
    "addr:housenumber":"32",
    "addr:postcode":"2500",
    "addr:street":"Flinders St",
    "iso:country":"AU",
    "sg:address":"32 Flinders St",
    "sg:city":"Wollongong",
    "sg:classifiers":[
        {
            "category":"Building & Trades",
            "subcategory":"Locksmith",
            "type":"Services"
        }
    ],
    "sg:phone":"+61 2 4226 6644",
    "sg:postcode":"2500",
    "sg:province":"NSW",
    "sg:tags":[
        "strongroom",
        "safe",
        "door"
    ],
    "wof:name":"ADC Security Engineers",
    "wof:placetype":"venue"
},
  "geometry": {"coordinates":[150.89259300000001,-34.415878],"type":"Point"}
}