{
  "type": "Feature",
  "properties": {
    "iso:country":"AU",
    "sg:address":"29 Rubery St",
    "sg:city":"Moe",
    "sg:classifiers":[
        {
            "category":"Organizations",
            "subcategory":"Community Association",
            "type":"Services"
        }
    ],
    "sg:phone":"+61 3 5127 4755",
    "sg:postcode":"3825",
    "sg:province":"VIC",
    "sg:tags":[
        "shiatsu",
        "therapy"
    ],
    "wof:name":"Moe Shiatsu Centre",
    "wof:placetype":"venue"
},
  "geometry": {"coordinates":[146.245514,-38.184216],"type":"Point"}
}