{
  "type": "Feature",
  "properties": {
    "addr:full":"29 Rubery St Moe VIC 3825",
    "addr:housenumber":"29",
    "addr:postcode":"3825",
    "addr:street":"Rubery St",
    "iso:country":"AU",
    "sg:address":"29 Rubery St",
    "sg:city":"Moe",
    "sg:classifiers":[
        {
            "category":"Organizations",
            "subcategory":"Community Association",
            "type":"Services"
        }
    ],
    "sg:phone":"+61 3 5127 4755",
    "sg:postcode":"3825",
    "sg:province":"VIC",
    "sg:tags":[
        "shiatsu",
        "therapy"
    ],
    "wof:name":"Moe Shiatsu Centre",
    "wof:placetype":"venue"
},
  "geometry": {"coordinates":[146.24551399999999,-38.184216],"type":"Point"}
}