{
  "type": "Feature",
  "properties": {
    "iso:country":"AU",
    "sg:address":"Shop 5, 1708 Gold Coast Hwy",
    "sg:city":"Burleigh Heads",
    "sg:classifiers":[
        {
            "category":"Personal",
            "subcategory":"Beauty Salon",
            "type":"Services"
        }
    ],
    "sg:phone":"+61 7 5535 3352",
    "sg:postcode":"4220",
    "sg:province":"QLD",
    "sg:tags":[
        "hairdresser"
    ],
    "wof:name":"Burleigh Hair Design",
    "wof:placetype":"venue"
},
  "geometry": {"coordinates":[153.451705933,-28.0887393951],"type":"Point"}
}