{
  "type": "Feature",
  "properties": {
    "iso:country":"AU",
    "sg:address":"76 Stanley St",
    "sg:city":"East Sydney",
    "sg:classifiers":[
        {
            "category":"Restaurant",
            "type":"Food & Drink"
        }
    ],
    "sg:phone":"+61 2 9361 4437",
    "sg:postcode":"2010",
    "sg:province":"NSW",
    "sg:website":"http://www.trovatarestaurant.com.au",
    "wof:name":"Trovata Mediterranean Restaurant",
    "wof:placetype":"venue"
},
  "geometry": {"coordinates":[151.215576172,-33.8756752014],"type":"Point"}
}