{
  "type": "Feature",
  "properties": {
    "addr:full":"43 Ogilvie St Essendon VIC 3040",
    "addr:housenumber":"43",
    "addr:postcode":"3040",
    "addr:street":"Ogilvie St",
    "iso:country":"AU",
    "sg:address":"43 Ogilvie St",
    "sg:city":"Essendon",
    "sg:classifiers":[
        {
            "category":"Professional",
            "subcategory":"Art Services",
            "type":"Services"
        }
    ],
    "sg:phone":"+61 3 9337 2944",
    "sg:postcode":"3040",
    "sg:province":"VIC",
    "sg:tags":[
        "decorator",
        "painter"
    ],
    "wof:name":"Kelly G & M",
    "wof:placetype":"venue"
},
  "geometry": {"coordinates":[144.892303467,-37.7503623962],"type":"Point"}
}