{
  "type": "Feature",
  "properties": {
    "addr:full":"57- 59 Coronation St Nambour QLD 4560",
    "addr:housenumber":"59",
    "addr:postcode":"4560",
    "addr:street":"Coronation St",
    "iso:country":"AU",
    "sg:address":"57- 59 Coronation St",
    "sg:city":"Nambour",
    "sg:classifiers":[
        {
            "category":"Retail",
            "subcategory":"Auto Repair",
            "type":"Services"
        }
    ],
    "sg:phone":"+61 407 033 341",
    "sg:postcode":"4560",
    "sg:province":"QLD",
    "sg:tags":[
        "car",
        "restoration",
        "supply"
    ],
    "wof:name":"Ryan's Auto Salon",
    "wof:placetype":"venue"
},
  "geometry": {"coordinates":[152.96531677199999,-26.6204929352],"type":"Point"}
}