{
  "type": "Feature",
  "properties": {
    "addr:full":"128 Carradine Rd Bedfordale WA 6112",
    "addr:housenumber":"128",
    "addr:postcode":"6112",
    "addr:street":"Carradine Rd",
    "iso:country":"AU",
    "sg:address":"128 Carradine Rd",
    "sg:city":"Bedfordale",
    "sg:classifiers":[
        {
            "category":"Health Services",
            "subcategory":"Doctor",
            "type":"Services"
        }
    ],
    "sg:phone":"+61 8 9497 7727",
    "sg:postcode":"6112",
    "sg:province":"WA",
    "sg:tags":[
        "medical",
        "practitioner"
    ],
    "wof:name":"Waterford Health",
    "wof:placetype":"venue"
},
  "geometry": {"coordinates":[116.042877197,-32.1479263306],"type":"Point"}
}