{
  "type": "Feature",
  "properties": {
    "iso:country":"AU",
    "sg:address":"Factory 1, 7 Dunstans Crt",
    "sg:city":"Keon Park",
    "sg:classifiers":[
        {
            "category":"Retail",
            "subcategory":"Auto Repair",
            "type":"Services"
        }
    ],
    "sg:phone":"+61 3 9469 4011",
    "sg:postcode":"3073",
    "sg:province":"VIC",
    "sg:tags":[
        "repairer",
        "motor",
        "engineer"
    ],
    "wof:name":"Car Start Automotive",
    "wof:placetype":"venue"
},
  "geometry": {"coordinates":[145.02090454099999,-37.6944656372],"type":"Point"}
}