{
  "type": "Feature",
  "properties": {
    "addr:full":"1126 Sydney Rd Fawkner VIC 3060",
    "addr:housenumber":"1126",
    "addr:postcode":"3060",
    "addr:street":"Sydney Rd",
    "iso:country":"AU",
    "sg:address":"1126 Sydney Rd",
    "sg:city":"Fawkner",
    "sg:classifiers":[
        {
            "category":"Shopping",
            "subcategory":"Stationery & Office Supplies",
            "type":"Retail Goods"
        }
    ],
    "sg:phone":"+61 3 9358 2478",
    "sg:postcode":"3060",
    "sg:province":"VIC",
    "sg:tags":[
        "packaging",
        "material"
    ],
    "wof:name":"Cryovac Shrink Films",
    "wof:placetype":"venue"
},
  "geometry": {"coordinates":[144.96232605,-37.7130851746],"type":"Point"}
}