{
  "type": "Feature",
  "properties": {
    "addr:full":"PO Box 96 Endeavour Hills VIC 3802",
    "addr:postcode":"3802",
    "iso:country":"AU",
    "sg:address":"PO Box 96",
    "sg:city":"Endeavour Hills",
    "sg:classifiers":[
        {
            "category":"Building & Trades",
            "subcategory":"Construction",
            "type":"Services"
        }
    ],
    "sg:phone":"+61 418 566 246",
    "sg:postcode":"3802",
    "sg:province":"VIC",
    "sg:tags":[
        "contractor"
    ],
    "wof:name":"Profine Construction",
    "wof:placetype":"venue"
},
  "geometry": {"coordinates":[145.25584411599999,-37.96900177],"type":"Point"}
}