{
  "type": "Feature",
  "properties": {
    "addr:full":"114 Bellarine Hwy Newcomb VIC 3219",
    "addr:housenumber":"114",
    "addr:postcode":"3219",
    "addr:street":"Bellarine Hwy",
    "iso:country":"AU",
    "sg:address":"114 Bellarine Hwy",
    "sg:city":"Newcomb",
    "sg:classifiers":[
        {
            "category":"Building & Trades",
            "subcategory":"Landscaping Services",
            "type":"Services"
        }
    ],
    "sg:phone":"+61 3 5248 2390",
    "sg:postcode":"3219",
    "sg:province":"VIC",
    "sg:tags":[
        "market"
    ],
    "wof:name":"Mill Markets",
    "wof:placetype":"venue"
},
  "geometry": {"coordinates":[144.39756774899999,-38.1723480225],"type":"Point"}
}