{
  "type": "Feature",
  "properties": {
    "addr:full":"1 Pollard Pl Sunbury VIC 3429",
    "addr:housenumber":"1",
    "addr:postcode":"3429",
    "addr:street":"Pollard Pl",
    "iso:country":"AU",
    "sg:address":"1 Pollard Pl",
    "sg:city":"Sunbury",
    "sg:classifiers":[
        {
            "category":"Professional",
            "subcategory":"Art Services",
            "type":"Services"
        }
    ],
    "sg:phone":"+61 3 9744 2265",
    "sg:postcode":"3429",
    "sg:province":"VIC",
    "sg:tags":[
        "decorator",
        "painter"
    ],
    "wof:name":"Sunbury Decorating",
    "wof:placetype":"venue"
},
  "geometry": {"coordinates":[144.73008727999999,-37.570892334],"type":"Point"}
}