{
  "type": "Feature",
  "properties": {
    "iso:country":"AU",
    "sg:address":"8 Casuarina Ave",
    "sg:city":"Bellingen",
    "sg:classifiers":[
        {
            "category":"Professional",
            "subcategory":"Art Services",
            "type":"Services"
        }
    ],
    "sg:phone":"+61 413 997 402",
    "sg:postcode":"2454",
    "sg:province":"NSW",
    "sg:tags":[
        "interior",
        "designer"
    ],
    "wof:name":"inform styling",
    "wof:placetype":"venue"
},
  "geometry": {"coordinates":[152.899628,-30.443899],"type":"Point"}
}