{
  "type": "Feature",
  "properties": {
    "addr:full":"3/ 119 Welshpool Rd Welshpool WA 6106",
    "addr:housenumber":"/ 119",
    "addr:postcode":"6106",
    "addr:street":"Welshpool Rd",
    "iso:country":"AU",
    "sg:address":"3/ 119 Welshpool Rd",
    "sg:city":"Welshpool",
    "sg:classifiers":[
        {
            "category":"Wholesale",
            "subcategory":"Machinery & Supplies",
            "type":"Manufacturing & Wholesale Goods"
        }
    ],
    "sg:phone":"+61 1300 132 992",
    "sg:postcode":"6106",
    "sg:province":"WA",
    "sg:tags":[
        "instrument",
        "scientific"
    ],
    "wof:name":"Olympus Australia Pty Ltd",
    "wof:placetype":"venue"
},
  "geometry": {"coordinates":[115.930236816,-31.9946556091],"type":"Point"}
}