{
  "type": "Feature",
  "properties": {
    "iso:country":"AU",
    "sg:address":"211 Parramatta Rd",
    "sg:city":"Annandale",
    "sg:classifiers":[
        {
            "category":"Shopping",
            "subcategory":"Bridal",
            "type":"Retail Goods"
        }
    ],
    "sg:phone":"+61 2 9569 5977",
    "sg:postcode":"2038",
    "sg:province":"NSW",
    "sg:tags":[
        "hire",
        "wear"
    ],
    "wof:name":"Cash Palace Emporium Pty Ltd",
    "wof:placetype":"venue"
},
  "geometry": {"coordinates":[151.16390991200001,-33.8880958557],"type":"Point"}
}