{
  "type": "Feature",
  "properties": {
    "addr:full":"7 Hamilton St Bathurst NSW 2795",
    "addr:housenumber":"7",
    "addr:postcode":"2795",
    "addr:street":"Hamilton St",
    "iso:country":"AU",
    "sg:address":"7 Hamilton St",
    "sg:city":"Bathurst",
    "sg:classifiers":[
        {
            "category":"Social Services",
            "subcategory":"Child Care",
            "type":"Services"
        }
    ],
    "sg:phone":"+61 2 6331 2553",
    "sg:postcode":"2795",
    "sg:province":"NSW",
    "wof:name":"Hamilton St Childcare Centre",
    "wof:placetype":"venue"
},
  "geometry": {"coordinates":[149.54629516599999,-33.3800048828],"type":"Point"}
}