{
  "type": "Feature",
  "properties": {
    "iso:country":"AU",
    "sg:address":"1A/ 104 Newmarket Rd",
    "sg:city":"Windsor",
    "sg:classifiers":[
        {
            "category":"Real Estate",
            "subcategory":"Real Estate Agent",
            "type":"Services"
        }
    ],
    "sg:phone":"+61 7 3637 4444",
    "sg:postcode":"4030",
    "sg:province":"QLD",
    "wof:name":"L J Hooker",
    "wof:placetype":"venue"
},
  "geometry": {"coordinates":[153.025513,-27.437429],"type":"Point"}
}