{
  "type": "Feature",
  "properties": {
    "iso:country":"AU",
    "sg:address":"12 Charlton Crt",
    "sg:city":"Woolner",
    "sg:classifiers":[
        {
            "category":"Professional",
            "subcategory":"Accounting & Tax Preparation",
            "type":"Services"
        }
    ],
    "sg:phone":"+61 8 8942 2299",
    "sg:postcode":"0820",
    "sg:province":"NT",
    "sg:tags":[
        "bookkeeping"
    ],
    "wof:name":"Beancounter Australia",
    "wof:placetype":"venue"
},
  "geometry": {"coordinates":[130.85943603499999,-12.4316959381],"type":"Point"}
}