{
  "type": "Feature",
  "properties": {
    "addr:full":"Cnr Milton & Granzella Rd Milton QLD 4064",
    "addr:postcode":"4064",
    "addr:street":"Cnr;Rd",
    "iso:country":"AU",
    "sg:address":"Cnr Milton & Granzella Rd",
    "sg:city":"Milton",
    "sg:classifiers":[
        {
            "category":"Fast Food",
            "type":"Food & Drink"
        }
    ],
    "sg:phone":"+61 7 3876 2796",
    "sg:postcode":"4064",
    "sg:province":"QLD",
    "sg:tags":[
        "away",
        "take"
    ],
    "wof:name":"McDonald's Family Restaurants",
    "wof:placetype":"venue"
},
  "geometry": {"coordinates":[153.0052948,-27.4686031342],"type":"Point"}
}