{
  "type": "Feature",
  "properties": {
    "addr:full":"Level 1/ 98-100 Moore St Liverpool NSW 2170",
    "addr:housenumber":"/ 98-100",
    "addr:postcode":"2170",
    "addr:street":"Moore St",
    "iso:country":"AU",
    "sg:address":"Level 1/ 98-100 Moore St",
    "sg:city":"Liverpool",
    "sg:classifiers":[
        {
            "category":"Professional",
            "subcategory":"Employment Agencies",
            "type":"Services"
        }
    ],
    "sg:phone":"+61 2 9822 4440",
    "sg:postcode":"2170",
    "sg:province":"NSW",
    "wof:name":"Bowman Recruitment Specialists",
    "wof:placetype":"venue"
},
  "geometry": {"coordinates":[150.922897339,-33.9225158691],"type":"Point"}
}