{
  "type": "Feature",
  "properties": {
    "addr:full":"Shop 2, 152 Haly St Kingaroy QLD 4610",
    "addr:housenumber":"shop 2",
    "addr:postcode":"152;4610",
    "addr:street":"Haly St",
    "iso:country":"AU",
    "sg:address":"Shop 2, 152 Haly St",
    "sg:city":"Kingaroy",
    "sg:classifiers":[
        {
            "category":"Insurance",
            "subcategory":"Hazard Insurance",
            "type":"Services"
        }
    ],
    "sg:phone":"+61 7 4162 3422",
    "sg:postcode":"4610",
    "sg:province":"QLD",
    "sg:tags":[
        "fire",
        "accident",
        "marine"
    ],
    "wof:name":"AIS Insurance Pty Ltd",
    "wof:placetype":"venue"
},
  "geometry": {"coordinates":[151.838500977,-26.5390739441],"type":"Point"}
}