{
  "type": "Feature",
  "properties": {
    "addr:full":"Minjungbal Drv (cnr Shallow Bay Drv) Tweed Heads QLD 2485",
    "addr:postcode":"2485",
    "addr:street":"Minjungbal Drv Cnr Shallow Bay Drv",
    "iso:country":"AU",
    "sg:address":"Minjungbal Drv (cnr Shallow Bay Drv)",
    "sg:city":"Tweed Heads",
    "sg:classifiers":[
        {
            "category":"Fast Food",
            "type":"Food & Drink"
        }
    ],
    "sg:phone":"+61 7 5524 6799",
    "sg:postcode":"2485",
    "sg:province":"QLD",
    "sg:tags":[
        "away",
        "take"
    ],
    "wof:name":"KFC",
    "wof:placetype":"venue"
},
  "geometry": {"coordinates":[153.54066467300001,-28.179693222],"type":"Point"}
}