{
  "type": "Feature",
  "properties": {
    "iso:country":"AU",
    "sg:address":"Bass Hwy",
    "sg:city":"Cooee",
    "sg:classifiers":[
        {
            "category":"Autos & Motor Vehicles",
            "subcategory":"Automobile Sales",
            "type":"Retail Goods"
        }
    ],
    "sg:phone":"+61 3 6430 3150",
    "sg:postcode":"7320",
    "sg:province":"TAS",
    "sg:tags":[
        "car",
        "new"
    ],
    "wof:name":"Von Bibra Motors",
    "wof:placetype":"venue"
},
  "geometry": {"coordinates":[145.875763,-41.041069],"type":"Point"}
}