{
  "type": "Feature",
  "properties": {
    "addr:full":"36 Outram St West Perth WA 6005",
    "addr:housenumber":"36",
    "addr:postcode":"6005",
    "addr:street":"Outram St",
    "iso:country":"AU",
    "sg:address":"36 Outram St",
    "sg:city":"West Perth",
    "sg:classifiers":[
        {
            "category":"Health Services",
            "subcategory":"Doctor",
            "type":"Services"
        }
    ],
    "sg:phone":"+61 8 9481 2552",
    "sg:postcode":"6005",
    "sg:province":"WA",
    "sg:tags":[
        "medical",
        "practitioner"
    ],
    "wof:name":"Smith Graham E",
    "wof:placetype":"venue"
},
  "geometry": {"coordinates":[115.839447022,-31.9494609833],"type":"Point"}
}