{
  "type": "Feature",
  "properties": {
    "iso:country":"AU",
    "sg:address":"Factory 4/ 94 Princes Hwy",
    "sg:city":"Beaconsfield",
    "sg:classifiers":[
        {
            "category":"Retail",
            "subcategory":"Auto Repair",
            "type":"Services"
        }
    ],
    "sg:phone":"+61 3 9769 5200",
    "sg:postcode":"3807",
    "sg:province":"VIC",
    "sg:tags":[
        "beater",
        "painter",
        "panel"
    ],
    "wof:name":"Autoweld",
    "wof:placetype":"venue"
},
  "geometry": {"coordinates":[145.373046875,-38.0503845215],"type":"Point"}
}