{
  "type": "Feature",
  "properties": {
    "addr:full":"12 Gimlet Crt Forrestfield WA 6058",
    "addr:housenumber":"12",
    "addr:postcode":"6058",
    "addr:street":"Gimlet Crt",
    "iso:country":"AU",
    "sg:address":"12 Gimlet Crt",
    "sg:city":"Forrestfield",
    "sg:classifiers":[
        {
            "category":"Building & Trades",
            "subcategory":"Construction",
            "type":"Services"
        }
    ],
    "sg:phone":"+61 417 961 718",
    "sg:postcode":"6058",
    "sg:province":"WA",
    "sg:tags":[
        "earth",
        "excavating",
        "moving",
        "contractor"
    ],
    "wof:name":"Ace of Spades Mini Earthworks",
    "wof:placetype":"venue"
},
  "geometry": {"coordinates":[116.010986328,-31.981464386],"type":"Point"}
}