{
  "type": "Feature",
  "properties": {
    "addr:full":"Ladbroke St Milperra NSW 2214",
    "addr:postcode":"2214",
    "addr:street":"Ladbroke St",
    "iso:country":"AU",
    "sg:address":"Ladbroke St",
    "sg:city":"Milperra",
    "sg:classifiers":[
        {
            "category":"Building & Trades",
            "subcategory":"Landscaping Services",
            "type":"Services"
        }
    ],
    "sg:phone":"+61 2 9792 3757",
    "sg:postcode":"2214",
    "sg:province":"NSW",
    "sg:tags":[
        "designer",
        "landscape",
        "contractor"
    ],
    "wof:name":"Pain In The Grass",
    "wof:placetype":"venue"
},
  "geometry": {"coordinates":[150.99612400000001,-33.93359],"type":"Point"}
}