{
  "type": "Feature",
  "properties": {
    "addr:full":"PO Box 4126 Black Rock VIC 3193",
    "addr:postcode":"3193",
    "iso:country":"AU",
    "sg:address":"PO Box 4126",
    "sg:city":"Black Rock",
    "sg:classifiers":[
        {
            "category":"Farming",
            "subcategory":"Fish & Marine Products",
            "type":"Manufacturing & Wholesale Goods"
        }
    ],
    "sg:phone":"+61 3 9598 8224",
    "sg:postcode":"3193",
    "sg:province":"VIC",
    "sg:tags":[
        "wholesaler",
        "mfrs",
        "swimwear"
    ],
    "wof:name":"Rav Goggles & Accessories",
    "wof:placetype":"venue"
},
  "geometry": {"coordinates":[145.03004455600001,-37.9695014954],"type":"Point"}
}