{
  "type": "Feature",
  "properties": {
    "iso:country":"AU",
    "sg:address":"46 Broun Ave",
    "sg:city":"Embleton",
    "sg:classifiers":[
        {
            "category":"Health Services",
            "subcategory":"Nursing And Care Facility",
            "type":"Services"
        }
    ],
    "sg:phone":"+61 8 9471 0600",
    "sg:postcode":"6062",
    "sg:province":"WA",
    "sg:tags":[
        "home"
    ],
    "wof:name":"Embleton Care Facility",
    "wof:placetype":"venue"
},
  "geometry": {"coordinates":[115.904556274,-31.9018383026],"type":"Point"}
}