{
  "type": "Feature",
  "properties": {
    "addr:full":"PO Box 208 Avoca TAS 7213",
    "addr:postcode":"7213",
    "iso:country":"AU",
    "sg:address":"PO Box 208",
    "sg:city":"Avoca",
    "sg:classifiers":[
        {
            "category":"Retail",
            "subcategory":"Auto Rental",
            "type":"Services"
        }
    ],
    "sg:phone":"+61 407 085 499",
    "sg:postcode":"7213",
    "sg:province":"TAS",
    "sg:tags":[
        "car",
        "wedding"
    ],
    "wof:name":"Island Limousine Service",
    "wof:placetype":"venue"
},
  "geometry": {"coordinates":[147.72110000000001,-41.781818],"type":"Point"}
}