{
  "type": "Feature",
  "properties": {
    "addr:full":"22 Sutherland Pl Golden Grove SA 5125",
    "addr:housenumber":"22",
    "addr:postcode":"5125",
    "addr:street":"Sutherland Pl",
    "iso:country":"AU",
    "sg:address":"22 Sutherland Pl",
    "sg:city":"Golden Grove",
    "sg:classifiers":[
        {
            "category":"Retail",
            "subcategory":"Auto Rental",
            "type":"Services"
        }
    ],
    "sg:phone":"+61 8 8289 2026",
    "sg:postcode":"5125",
    "sg:province":"SA",
    "sg:tags":[
        "camper-trailers",
        "caravan",
        "hire"
    ],
    "wof:name":"Coolabah Camper Hire",
    "wof:placetype":"venue"
},
  "geometry": {"coordinates":[138.70268200000001,-34.788925],"type":"Point"}
}