{
  "type": "Feature",
  "properties": {
    "addr:full":"Hornsby St Maldon VIC 3463",
    "addr:postcode":"3463",
    "addr:street":"Hornsby St",
    "iso:country":"AU",
    "sg:address":"Hornsby St",
    "sg:city":"Maldon",
    "sg:classifiers":[
        {
            "category":"Communications",
            "subcategory":"News Services",
            "type":"Services"
        }
    ],
    "sg:phone":"+61 3 5470 6658",
    "sg:postcode":"3463",
    "sg:province":"VIC",
    "sg:tags":[
        "information",
        "tourist",
        "attractions"
    ],
    "wof:name":"Victorian Goldfields Railway",
    "wof:placetype":"venue"
},
  "geometry": {"coordinates":[144.080322266,-36.9924659729],"type":"Point"}
}