{
  "type": "Feature",
  "properties": {
    "addr:full":"721 Webster Rd Chermside QLD 4032",
    "addr:housenumber":"721",
    "addr:postcode":"qld 4032",
    "addr:street":"Webster Rd",
    "iso:country":"AU",
    "sg:address":"721 Webster Rd",
    "sg:city":"Chermside",
    "sg:classifiers":[
        {
            "category":"Retail",
            "subcategory":"Storage",
            "type":"Services"
        }
    ],
    "sg:phone":"+61 7 3630 5694",
    "sg:postcode":"4032",
    "sg:province":"QLD",
    "wof:name":"Kennards Self Storage",
    "wof:placetype":"venue"
},
  "geometry": {"coordinates":[153.02363600000001,-27.376154],"type":"Point"}
}