{
  "type": "Feature",
  "properties": {
    "iso:country":"AU",
    "sg:address":"24 Essex St",
    "sg:city":"Moolap",
    "sg:classifiers":[
        {
            "category":"Wholesale",
            "subcategory":"Machinery & Supplies",
            "type":"Manufacturing & Wholesale Goods"
        }
    ],
    "sg:phone":"+61 417 852 814",
    "sg:postcode":"3221",
    "sg:province":"VIC",
    "sg:tags":[
        "equipment",
        "hydraulic"
    ],
    "wof:name":"Ross Hydraulics & Pneumatics Pty. Ltd.",
    "wof:placetype":"venue"
},
  "geometry": {"coordinates":[144.410126,-38.16515],"type":"Point"}
}