{
  "type": "Feature",
  "properties": {
    "iso:country":"AU",
    "sg:address":"115 Marion St",
    "sg:city":"Bankstown",
    "sg:classifiers":[
        {
            "category":"Personal",
            "subcategory":"Beauty Salon",
            "type":"Services"
        }
    ],
    "sg:phone":"+61 2 9708 4901",
    "sg:postcode":"2200",
    "sg:province":"NSW",
    "sg:tags":[
        "hairdresser"
    ],
    "wof:name":"Rina's Finishing Touch Freelance Hairdresser",
    "wof:placetype":"venue"
},
  "geometry": {"coordinates":[151.024323,-33.917469],"type":"Point"}
}