{
  "type": "Feature",
  "properties": {
    "addr:full":"42 Walmsley St Esperance WA 6450",
    "addr:housenumber":"42",
    "addr:postcode":"6450",
    "addr:street":"Walmsley St",
    "iso:country":"AU",
    "sg:address":"42 Walmsley St",
    "sg:city":"Esperance",
    "sg:classifiers":[
        {
            "category":"Education",
            "subcategory":"Kindergarten",
            "type":"Public Place"
        }
    ],
    "sg:phone":"+61 8 9071 4930",
    "sg:postcode":"6450",
    "sg:province":"WA",
    "sg:tags":[
        "pre-schools"
    ],
    "wof:name":"Esperance Community Kindergarten",
    "wof:placetype":"venue"
},
  "geometry": {"coordinates":[121.912216187,-33.8351364136],"type":"Point"}
}