{
  "type": "Feature",
  "properties": {
    "addr:full":"Rear 484 Smith Street Collingwood VIC 3066",
    "addr:housenumber":"484",
    "addr:postcode":"3066",
    "addr:street":"Smith Street",
    "iso:country":"AU",
    "sg:address":"Rear 484 Smith Street",
    "sg:city":"Collingwood",
    "sg:classifiers":[
        {
            "category":"Building & Trades",
            "subcategory":"Cleaning & Sanitation",
            "type":"Services"
        }
    ],
    "sg:phone":"+61 3 9419 4411",
    "sg:postcode":"3066",
    "sg:province":"VIC",
    "sg:tags":[
        "industrial",
        "commercial",
        "contractor"
    ],
    "wof:name":"Master Cleaning Services",
    "wof:placetype":"venue"
},
  "geometry": {"coordinates":[144.985229492,-37.794216156],"type":"Point"}
}