{
  "type": "Feature",
  "properties": {
    "addr:full":"51 Haig St Bexley NSW 2207",
    "addr:housenumber":"51",
    "addr:postcode":"2207",
    "addr:street":"Haig St",
    "iso:country":"AU",
    "sg:address":"51 Haig St",
    "sg:city":"Bexley",
    "sg:classifiers":[
        {
            "category":"Taxi",
            "type":"Transportation"
        }
    ],
    "sg:phone":"+61 2 9587 0044",
    "sg:postcode":"2207",
    "sg:province":"NSW",
    "sg:tags":[
        "truck"
    ],
    "wof:name":"Dunrite Removals",
    "wof:placetype":"venue"
},
  "geometry": {"coordinates":[151.11201500000001,-33.956867],"type":"Point"}
}