{
  "type": "Feature",
  "properties": {
    "iso:country":"AU",
    "sg:address":"13 Fifteenth Ave",
    "sg:city":"Sawtell",
    "sg:classifiers":[
        {
            "category":"Building & Trades",
            "subcategory":"Cleaning & Sanitation",
            "type":"Services"
        }
    ],
    "sg:phone":"+61 2 6653 2132",
    "sg:postcode":"2452",
    "sg:province":"NSW",
    "sg:tags":[
        "industrial",
        "commercial",
        "contractor"
    ],
    "wof:name":"Coffs Contract Cleaners",
    "wof:placetype":"venue"
},
  "geometry": {"coordinates":[153.099716,-30.362068],"type":"Point"}
}