{
  "type": "Feature",
  "properties": {
    "addr:full":"35 Paget St Paget QLD 4740",
    "addr:housenumber":"35",
    "addr:postcode":"4740",
    "addr:street":"Paget St",
    "iso:country":"AU",
    "sg:address":"35 Paget St",
    "sg:city":"Paget",
    "sg:classifiers":[
        {
            "category":"Social Services",
            "subcategory":"Child Care",
            "type":"Services"
        }
    ],
    "sg:phone":"+61 7 4952 4466",
    "sg:postcode":"4740",
    "sg:province":"QLD",
    "wof:name":"Hot Tots Educational Centre",
    "wof:placetype":"venue"
},
  "geometry": {"coordinates":[149.16127,-21.167181],"type":"Point"}
}