{
  "type": "Feature",
  "properties": {
    "addr:full":"Shp4/ 288 Malton Rd North Epping NSW 2121",
    "addr:housenumber":"288",
    "addr:postcode":"2121",
    "addr:street":"Malton Rd",
    "iso:country":"AU",
    "sg:address":"Shp4/ 288 Malton Rd",
    "sg:city":"North Epping",
    "sg:classifiers":[
        {
            "category":"Personal",
            "subcategory":"Beauty Salon",
            "type":"Services"
        }
    ],
    "sg:phone":"+61 2 9868 5593",
    "sg:postcode":"2121",
    "sg:province":"NSW",
    "sg:tags":[
        "hairdresser"
    ],
    "wof:name":"Silver Spectrum Hair Design",
    "wof:placetype":"venue"
},
  "geometry": {"coordinates":[151.09344482399999,-33.7592849731],"type":"Point"}
}