{
  "type": "Feature",
  "properties": {
    "iso:country":"AU",
    "sg:address":"Shop 14, 600 Burke Rd",
    "sg:city":"Camberwell",
    "sg:classifiers":[
        {
            "category":"Personal",
            "subcategory":"Beauty Salon",
            "type":"Services"
        }
    ],
    "sg:phone":"+61 3 9813 5661",
    "sg:postcode":"3124",
    "sg:province":"VIC",
    "wof:name":"C T Nails",
    "wof:placetype":"venue"
},
  "geometry": {"coordinates":[145.05708313,-37.830116272],"type":"Point"}
}