{
  "type": "Feature",
  "properties": {
    "addr:full":"1 Cowper St Parramatta NSW 2150",
    "addr:housenumber":"1",
    "addr:postcode":"2150",
    "addr:street":"Cowper St",
    "iso:country":"AU",
    "sg:address":"1 Cowper St",
    "sg:city":"Parramatta",
    "sg:classifiers":[
        {
            "category":"Professional",
            "subcategory":"Accounting & Tax Preparation",
            "type":"Services"
        }
    ],
    "sg:phone":"+61 2 9893 9977",
    "sg:postcode":"2150",
    "sg:province":"NSW",
    "sg:tags":[
        "consultant",
        "taxation"
    ],
    "wof:name":"De Santis CPA",
    "wof:placetype":"venue"
},
  "geometry": {"coordinates":[151.015350342,-33.8326454163],"type":"Point"}
}