{
  "type": "Feature",
  "properties": {
    "addr:full":"57 Minninup Rd Bunbury WA 6230",
    "addr:housenumber":"57",
    "addr:postcode":"6230",
    "addr:street":"Minninup Rd",
    "iso:country":"AU",
    "sg:address":"57 Minninup Rd",
    "sg:city":"Bunbury",
    "sg:classifiers":[
        {
            "category":"Deli",
            "type":"Food & Drink"
        }
    ],
    "sg:phone":"+61 8 9721 4981",
    "sg:postcode":"6230",
    "sg:province":"WA",
    "sg:tags":[
        "delicatessen"
    ],
    "wof:name":"Mangles Corner Store & Home Videos",
    "wof:placetype":"venue"
},
  "geometry": {"coordinates":[115.633957,-33.348228],"type":"Point"}
}