{
  "type": "Feature",
  "properties": {
    "iso:country":"AU",
    "sg:address":"32 Murray St",
    "sg:city":"Gawler",
    "sg:classifiers":[
        {
            "category":"Food & Beverages",
            "subcategory":"Liquor & Beverages",
            "type":"Retail Goods"
        }
    ],
    "sg:phone":"+61 8 8522 1687",
    "sg:postcode":"5118",
    "sg:province":"SA",
    "sg:tags":[
        "store"
    ],
    "wof:name":"Liquorsmart Pty Ltd",
    "wof:placetype":"venue"
},
  "geometry": {"coordinates":[138.748886,-34.596291],"type":"Point"}
}