{
  "type": "Feature",
  "properties": {
    "addr:full":"Shop5/ 3 Shepherd Rd Mandurah WA 6210",
    "addr:housenumber":"3",
    "addr:postcode":"6210",
    "addr:street":"Shepherd Rd",
    "iso:country":"AU",
    "sg:address":"Shop5/ 3 Shepherd Rd",
    "sg:city":"Mandurah",
    "sg:classifiers":[
        {
            "category":"Cafe",
            "type":"Food & Drink"
        }
    ],
    "sg:phone":"+61 8 9581 6366",
    "sg:postcode":"6210",
    "sg:province":"WA",
    "wof:name":"Gordon Road Food & Drink",
    "wof:placetype":"venue"
},
  "geometry": {"coordinates":[115.73957799999999,-32.509888],"type":"Point"}
}