{
  "type": "Feature",
  "properties": {
    "iso:country":"AU",
    "sg:address":"25 Gorge Rd",
    "sg:city":"Morang South",
    "sg:classifiers":[
        {
            "category":"Personal",
            "subcategory":"Beauty Salon",
            "type":"Services"
        }
    ],
    "sg:phone":"+61 3 9436 0099",
    "sg:postcode":"3752",
    "sg:province":"VIC",
    "sg:tags":[
        "hairdresser"
    ],
    "wof:name":"Get The Look Hair Design",
    "wof:placetype":"venue"
},
  "geometry": {"coordinates":[145.08929443400001,-37.6514472961],"type":"Point"}
}