{
  "type": "Feature",
  "properties": {
    "addr:full":"582 Morayfield Rd Burpengary QLD 4505",
    "addr:housenumber":"582",
    "addr:postcode":"4505",
    "addr:street":"Morayfield Rd",
    "iso:country":"AU",
    "sg:address":"582 Morayfield Rd",
    "sg:city":"Burpengary",
    "sg:classifiers":[
        {
            "category":"Home & Garden",
            "subcategory":"Furniture",
            "type":"Retail Goods"
        }
    ],
    "sg:phone":"+61 409 262 326",
    "sg:postcode":"4505",
    "sg:province":"QLD",
    "sg:tags":[
        "repair",
        "restoration"
    ],
    "wof:name":"Norvic Upholstery",
    "wof:placetype":"venue"
},
  "geometry": {"coordinates":[152.977249145,-27.147403717],"type":"Point"}
}