{
  "type": "Feature",
  "properties": {
    "addr:full":"145 Park St Moonee Ponds VIC 3039",
    "addr:housenumber":"145",
    "addr:postcode":"3039",
    "addr:street":"Park St",
    "iso:country":"AU",
    "sg:address":"145 Park St",
    "sg:city":"Moonee Ponds",
    "sg:classifiers":[
        {
            "category":"Retail",
            "subcategory":"Driving School",
            "type":"Services"
        }
    ],
    "sg:phone":"+61 411 739 786",
    "sg:postcode":"3039",
    "sg:province":"VIC",
    "wof:name":"Apples Driving School",
    "wof:placetype":"venue"
},
  "geometry": {"coordinates":[144.907104492,-37.7607727051],"type":"Point"}
}