{
  "type": "Feature",
  "properties": {
    "addr:full":"66 High St Yea VIC 3717",
    "addr:housenumber":"66",
    "addr:postcode":"3717",
    "addr:street":"High St",
    "iso:country":"AU",
    "sg:address":"66 High St",
    "sg:city":"Yea",
    "sg:classifiers":[
        {
            "category":"Shopping",
            "type":"Retail Goods"
        }
    ],
    "sg:phone":"+61 3 5797 2086",
    "sg:postcode":"3717",
    "sg:province":"VIC",
    "sg:tags":[
        "agent",
        "stock"
    ],
    "wof:name":"Rodwells & Co Pty Ltd",
    "wof:placetype":"venue"
},
  "geometry": {"coordinates":[145.423370361,-37.2113304138],"type":"Point"}
}