{
  "type": "Feature",
  "properties": {
    "addr:full":"207 Miller Rd Villawood NSW 2163",
    "addr:housenumber":"207",
    "addr:postcode":"2163",
    "addr:street":"Miller Rd",
    "iso:country":"AU",
    "sg:address":"207 Miller Rd",
    "sg:city":"Villawood",
    "sg:classifiers":[
        {
            "category":"Food & Beverages",
            "subcategory":"Liquor & Beverages",
            "type":"Retail Goods"
        }
    ],
    "sg:phone":"+61 2 9726 9899",
    "sg:postcode":"2163",
    "sg:province":"NSW",
    "sg:tags":[
        "store"
    ],
    "wof:name":"Cellarbrations",
    "wof:placetype":"venue"
},
  "geometry": {"coordinates":[150.992721558,-33.8852424622],"type":"Point"}
}