{
  "type": "Feature",
  "properties": {
    "addr:full":"489 George St Windsor South NSW 2756",
    "addr:housenumber":"489",
    "addr:postcode":"2756",
    "addr:street":"George St",
    "iso:country":"AU",
    "sg:address":"489 George St",
    "sg:city":"Windsor South",
    "sg:classifiers":[
        {
            "category":"Health Services",
            "subcategory":"Doctor",
            "type":"Services"
        }
    ],
    "sg:phone":"+61 2 4577 4377",
    "sg:postcode":"2756",
    "sg:province":"NSW",
    "sg:tags":[
        "medical",
        "practitioner"
    ],
    "wof:name":"Stubbs R P",
    "wof:placetype":"venue"
},
  "geometry": {"coordinates":[150.80784606899999,-33.616973877],"type":"Point"}
}