{
  "type": "Feature",
  "properties": {
    "addr:full":"37 Wilson St Burnie TAS 7320",
    "addr:housenumber":"37",
    "addr:postcode":"7320",
    "addr:street":"Wilson St",
    "iso:country":"AU",
    "sg:address":"37 Wilson St",
    "sg:city":"Burnie",
    "sg:classifiers":[
        {
            "category":"Coffee & Tea",
            "type":"Food & Drink"
        }
    ],
    "sg:phone":"+61 3 6431 6500",
    "sg:postcode":"7320",
    "sg:province":"TAS",
    "sg:tags":[
        "kayak",
        "canoe"
    ],
    "wof:name":"Tassie Tackle & Outdoor",
    "wof:placetype":"venue"
},
  "geometry": {"coordinates":[145.906769,-41.051544],"type":"Point"}
}