{
  "type": "Feature",
  "properties": {
    "iso:country":"AU",
    "sg:address":"Lvl 5/ 793 George St",
    "sg:city":"Sydney",
    "sg:classifiers":[
        {
            "category":"Communications",
            "subcategory":"Film & Video Production",
            "type":"Services"
        }
    ],
    "sg:phone":"+61 2 9212 2669",
    "sg:postcode":"2000",
    "sg:province":"NSW",
    "sg:tags":[
        "made",
        "clothing",
        "custom"
    ],
    "wof:name":"People Like Us Pty Ltd",
    "wof:placetype":"venue"
},
  "geometry": {"coordinates":[151.20411682100001,-33.8826179504],"type":"Point"}
}