{
  "type": "Feature",
  "properties": {
    "addr:full":"Perth City Arcade 676 Hay St Perth WA 6000",
    "addr:housenumber":"676",
    "addr:postcode":"6000",
    "addr:street":"Hay St",
    "iso:country":"AU",
    "sg:address":"Perth City Arcade 676 Hay St",
    "sg:city":"Perth",
    "sg:classifiers":[
        {
            "category":"Shopping",
            "subcategory":"Jewelry",
            "type":"Retail Goods"
        }
    ],
    "sg:phone":"+61 8 9485 2127",
    "sg:postcode":"6000",
    "sg:province":"WA",
    "sg:tags":[
        "jeweller"
    ],
    "wof:name":"Mazzucchellis Jewellers",
    "wof:placetype":"venue"
},
  "geometry": {"coordinates":[115.855163574,-31.9530906677],"type":"Point"}
}