{
  "type": "Feature",
  "properties": {
    "addr:full":"149 Whithorse Rd Balwyn VIC 3103",
    "addr:housenumber":"149",
    "addr:postcode":"3103",
    "addr:street":"Whithorse Rd",
    "iso:country":"AU",
    "sg:address":"149 Whithorse Rd",
    "sg:city":"Balwyn",
    "sg:classifiers":[
        {
            "category":"Health Services",
            "subcategory":"Health Practitioner",
            "type":"Services"
        }
    ],
    "sg:phone":"+61 3 9888 9291",
    "sg:postcode":"3103",
    "sg:province":"VIC",
    "sg:tags":[
        "naturopath"
    ],
    "wof:name":"Helen Andros Naturopathy",
    "wof:placetype":"venue"
},
  "geometry": {"coordinates":[145.068115234,-37.8111038208],"type":"Point"}
}