{
  "type": "Feature",
  "properties": {
    "iso:country":"AU",
    "sg:address":"Unit 3/ 1 Garnet St",
    "sg:city":"Rockdale",
    "sg:classifiers":[
        {
            "category":"Building & Trades",
            "subcategory":"Cleaning & Sanitation",
            "type":"Services"
        }
    ],
    "sg:phone":"+61 2 9567 4779",
    "sg:postcode":"2216",
    "sg:province":"NSW",
    "sg:tags":[
        "industrial",
        "commercial",
        "contractor"
    ],
    "wof:name":"Glad Cleaning Services Pty Ltd",
    "wof:placetype":"venue"
},
  "geometry": {"coordinates":[151.144455,-33.956181],"type":"Point"}
}