{
  "type": "Feature",
  "properties": {
    "addr:full":"42 Water St Toowoomba QLD 4350",
    "addr:housenumber":"42",
    "addr:postcode":"4350",
    "addr:street":"Water St",
    "iso:country":"AU",
    "sg:address":"42 Water St",
    "sg:city":"Toowoomba",
    "sg:classifiers":[
        {
            "category":"Retail",
            "subcategory":"Auto Repair",
            "type":"Services"
        }
    ],
    "sg:phone":"+61 7 4632 4900",
    "sg:postcode":"4350",
    "sg:province":"QLD",
    "sg:tags":[
        "electrical"
    ],
    "wof:name":"Century Batteries",
    "wof:placetype":"venue"
},
  "geometry": {"coordinates":[151.949265,-27.567614],"type":"Point"}
}