{
  "type": "Feature",
  "properties": {
    "iso:country":"AU",
    "sg:address":"7 Mill St",
    "sg:city":"Proserpine",
    "sg:classifiers":[
        {
            "category":"Autos & Motor Vehicles",
            "subcategory":"Automobile Sales",
            "type":"Retail Goods"
        }
    ],
    "sg:phone":"+61 7 4945 1209",
    "sg:postcode":"4800",
    "sg:province":"QLD",
    "sg:tags":[
        "car",
        "new"
    ],
    "wof:name":"Rod Grittners Car Sales",
    "wof:placetype":"venue"
},
  "geometry": {"coordinates":[148.58160400400001,-20.3995609283],"type":"Point"}
}