{
  "type": "Feature",
  "properties": {
    "iso:country":"AU",
    "sg:address":"213a Mona Vale Rd",
    "sg:city":"St Ives",
    "sg:classifiers":[
        {
            "category":"Food & Beverages",
            "subcategory":"Meat & Fish",
            "type":"Retail Goods"
        }
    ],
    "sg:phone":"+61 2 9449 5021",
    "sg:postcode":"2075",
    "sg:province":"NSW",
    "sg:tags":[
        "seafood"
    ],
    "wof:name":"Olympia Quality Seafoods",
    "wof:placetype":"venue"
},
  "geometry": {"coordinates":[151.16036987300001,-33.7306594849],"type":"Point"}
}