{
  "type": "Feature",
  "properties": {
    "addr:full":"206 Warrenheip St Buninyong VIC 3357",
    "addr:housenumber":"206",
    "addr:postcode":"3357",
    "addr:street":"Warrenheip St",
    "iso:country":"AU",
    "sg:address":"206 Warrenheip St",
    "sg:city":"Buninyong",
    "sg:classifiers":[
        {
            "category":"Retail",
            "subcategory":"Auto Repair",
            "type":"Services"
        }
    ],
    "sg:phone":"+61 3 5341 3503",
    "sg:postcode":"3357",
    "sg:province":"VIC",
    "sg:tags":[
        "repairer",
        "motor",
        "engineer"
    ],
    "wof:name":"Vagg Automotive",
    "wof:placetype":"venue"
},
  "geometry": {"coordinates":[143.88516200000001,-37.646233],"type":"Point"}
}