{
  "type": "Feature",
  "properties": {
    "iso:country":"AU",
    "sg:address":"2 Geils Crt",
    "sg:city":"Deakin",
    "sg:classifiers":[
        {
            "category":"Health Services",
            "subcategory":"Doctor",
            "type":"Services"
        }
    ],
    "sg:phone":"+61 2 6282 2232",
    "sg:postcode":"2600",
    "sg:province":"ACT",
    "sg:tags":[
        "medical",
        "practitioner"
    ],
    "wof:name":"Brook Andrew Dr",
    "wof:placetype":"venue"
},
  "geometry": {"coordinates":[149.09715270999999,-35.3182144165],"type":"Point"}
}