{
  "type": "Feature",
  "properties": {
    "addr:full":"Cnr Luxford Rd & Mount St Mt Druitt NSW 2770",
    "addr:postcode":"2770",
    "addr:street":"Cnr Luxford Rd & Mount St Mt",
    "iso:country":"AU",
    "sg:address":"Cnr Luxford Rd & Mount St",
    "sg:city":"Mt Druitt",
    "sg:classifiers":[
        {
            "category":"Food & Beverages",
            "subcategory":"Supermarket",
            "type":"Retail Goods"
        }
    ],
    "sg:phone":"+61 2 9832 1367",
    "sg:postcode":"2770",
    "sg:province":"NSW",
    "sg:tags":[
        "grocery",
        "store"
    ],
    "wof:name":"Quix Food Stores",
    "wof:placetype":"venue"
},
  "geometry": {"coordinates":[150.81736755399999,-33.7643470764],"type":"Point"}
}