{
  "type": "Feature",
  "properties": {
    "addr:full":"58 Lawitta Rd New Norfolk TAS 7140",
    "addr:housenumber":"58",
    "addr:postcode":"7140",
    "addr:street":"Lawitta Rd",
    "iso:country":"AU",
    "sg:address":"58 Lawitta Rd",
    "sg:city":"New Norfolk",
    "sg:classifiers":[
        {
            "category":"Retail",
            "subcategory":"Storage",
            "type":"Services"
        }
    ],
    "sg:phone":"+61 418 552 763",
    "sg:postcode":"7140",
    "sg:province":"TAS",
    "sg:tags":[
        "removal",
        "furniture"
    ],
    "wof:name":"Birds Express",
    "wof:placetype":"venue"
},
  "geometry": {"coordinates":[147.031937,-42.76712],"type":"Point"}
}