{
  "type": "Feature",
  "properties": {
    "iso:country":"AU",
    "sg:address":"19b Gilbert St",
    "sg:city":"Torquay",
    "sg:classifiers":[
        {
            "category":"Cafe",
            "type":"Food & Drink"
        }
    ],
    "sg:phone":"+61 3 5264 7054",
    "sg:postcode":"3228",
    "sg:province":"VIC",
    "wof:name":"Munchies Torquay",
    "wof:placetype":"venue"
},
  "geometry": {"coordinates":[144.324341,-38.33223],"type":"Point"}
}