{
  "type": "Feature",
  "properties": {
    "addr:full":"F1/ 2 Palmerston St Melton VIC 3337",
    "addr:housenumber":"2",
    "addr:postcode":"3337",
    "addr:street":"/;Palmerston St",
    "iso:country":"AU",
    "sg:address":"F1/ 2 Palmerston St",
    "sg:city":"Melton",
    "sg:classifiers":[
        {
            "category":"Building & Trades",
            "subcategory":"Equipment Rental",
            "type":"Services"
        }
    ],
    "sg:phone":"+61 3 9747 0084",
    "sg:postcode":"3337",
    "sg:province":"VIC",
    "sg:tags":[
        "party",
        "hire"
    ],
    "wof:name":"Western Suburbs Party Hire & Sales",
    "wof:placetype":"venue"
},
  "geometry": {"coordinates":[144.59677099999999,-37.691666],"type":"Point"}
}