{
  "type": "Feature",
  "properties": {
    "addr:full":"32 Jubilee St Caboolture QLD 4510",
    "addr:housenumber":"32",
    "addr:postcode":"4510",
    "addr:street":"Jubilee St",
    "iso:country":"AU",
    "sg:address":"32 Jubilee St",
    "sg:city":"Caboolture",
    "sg:classifiers":[
        {
            "category":"Social Services",
            "subcategory":"Child Care",
            "type":"Services"
        }
    ],
    "sg:phone":"+61 7 5498 3355",
    "sg:postcode":"4510",
    "sg:province":"QLD",
    "wof:name":"Jubilee & Jubilee Tots Child Care Centre",
    "wof:placetype":"venue"
},
  "geometry": {"coordinates":[152.95486500000001,-27.075222],"type":"Point"}
}