{
  "type": "Feature",
  "properties": {
    "addr:full":"3 Kardinian Ave Cheltenham VIC 3192",
    "addr:housenumber":"3",
    "addr:postcode":"3192",
    "addr:street":"Kardinian Ave",
    "iso:country":"AU",
    "sg:address":"3 Kardinian Ave",
    "sg:city":"Cheltenham",
    "sg:classifiers":[
        {
            "category":"Professional",
            "subcategory":"Secretarial Services",
            "type":"Services"
        }
    ],
    "sg:phone":"+61 3 9584 5726",
    "sg:postcode":"3192",
    "sg:province":"VIC",
    "sg:tags":[
        "typing"
    ],
    "wof:name":"Excel Secretarial",
    "wof:placetype":"venue"
},
  "geometry": {"coordinates":[145.08076477,-37.9681510925],"type":"Point"}
}