{
  "type": "Feature",
  "properties": {
    "addr:full":"162 Colonial Drv Bligh Park NSW 2756",
    "addr:housenumber":"162",
    "addr:postcode":"2756",
    "addr:street":"Colonial Drv",
    "iso:country":"AU",
    "sg:address":"162 Colonial Drv",
    "sg:city":"Bligh Park",
    "sg:classifiers":[
        {
            "category":"Retail",
            "subcategory":"Driving School",
            "type":"Services"
        }
    ],
    "sg:phone":"+61 417 926 599",
    "sg:postcode":"2756",
    "sg:province":"NSW",
    "wof:name":"Australian Professional Driver Training Services Pty Ltd",
    "wof:placetype":"venue"
},
  "geometry": {"coordinates":[150.80064392099999,-33.6381225586],"type":"Point"}
}