{
  "type": "Feature",
  "properties": {
    "addr:full":"14 Conniston St Ballarat VIC 3350",
    "addr:housenumber":"14",
    "addr:postcode":"3350",
    "addr:street":"Conniston St",
    "iso:country":"AU",
    "sg:address":"14 Conniston St",
    "sg:city":"Ballarat",
    "sg:classifiers":[
        {
            "category":"Retail",
            "subcategory":"Auto Rental",
            "type":"Services"
        }
    ],
    "sg:phone":"+61 1800 285 621",
    "sg:postcode":"3350",
    "sg:province":"VIC",
    "sg:tags":[
        "chauffeur",
        "car",
        "hire",
        "driven",
        "limousine"
    ],
    "wof:name":"Begonia City Hire Cars",
    "wof:placetype":"venue"
},
  "geometry": {"coordinates":[143.83223000000001,-37.521519],"type":"Point"}
}