{
  "type": "Feature",
  "properties": {
    "addr:full":"113 Patrick St Laidley QLD 4341",
    "addr:housenumber":"113",
    "addr:postcode":"4341",
    "addr:street":"Patrick St",
    "iso:country":"AU",
    "sg:address":"113 Patrick St",
    "sg:city":"Laidley",
    "sg:classifiers":[
        {
            "category":"Professional",
            "subcategory":"Printing & Photocopies",
            "type":"Services"
        }
    ],
    "sg:phone":"+61 7 5465 3344",
    "sg:postcode":"4341",
    "sg:province":"QLD",
    "sg:tags":[
        "trophy"
    ],
    "wof:name":"Laidley Jewellers",
    "wof:placetype":"venue"
},
  "geometry": {"coordinates":[152.393844605,-27.6306724548],"type":"Point"}
}