{
  "type": "Feature",
  "properties": {
    "addr:full":"38 Piper St Kyneton VIC 3444",
    "addr:housenumber":"38",
    "addr:postcode":"3444",
    "addr:street":"Piper St",
    "iso:country":"AU",
    "sg:address":"38 Piper St",
    "sg:city":"Kyneton",
    "sg:classifiers":[
        {
            "category":"Professional",
            "subcategory":"Art Services",
            "type":"Services"
        }
    ],
    "sg:phone":"+61 3 5422 2369",
    "sg:postcode":"3444",
    "sg:province":"VIC",
    "sg:tags":[
        "interior",
        "decorator"
    ],
    "wof:name":"Klassik Elegance Interiors",
    "wof:placetype":"venue"
},
  "geometry": {"coordinates":[144.45059204099999,-37.2441596985],"type":"Point"}
}