{
  "type": "Feature",
  "properties": {
    "iso:country":"AU",
    "sg:address":"60 Palmerin St",
    "sg:city":"Warwick",
    "sg:classifiers":[
        {
            "category":"Shopping",
            "subcategory":"Crafts & Fabrics",
            "type":"Retail Goods"
        }
    ],
    "sg:phone":"+61 7 4661 4433",
    "sg:postcode":"4370",
    "sg:province":"QLD",
    "sg:tags":[
        "supply"
    ],
    "wof:name":"Majors Sewing Centre",
    "wof:placetype":"venue"
},
  "geometry": {"coordinates":[152.03306579599999,-28.2145786285],"type":"Point"}
}