{
  "type": "Feature",
  "properties": {
    "addr:full":"PO Box 4027 Lalor Park NSW 2147",
    "addr:postcode":"2147",
    "iso:country":"AU",
    "sg:address":"PO Box 4027",
    "sg:city":"Lalor Park",
    "sg:classifiers":[
        {
            "category":"Building & Trades",
            "subcategory":"Landscaping Services",
            "type":"Services"
        }
    ],
    "sg:phone":"+61 402 491 421",
    "sg:postcode":"2147",
    "sg:province":"NSW",
    "sg:tags":[
        "stump",
        "tree",
        "felling",
        "removal"
    ],
    "wof:name":"A-One Tree Services",
    "wof:placetype":"venue"
},
  "geometry": {"coordinates":[150.93145751899999,-33.7619895935],"type":"Point"}
}