{
  "type": "Feature",
  "properties": {
    "iso:country":"AU",
    "sg:address":"Shp2/ 987 Hume Hwy",
    "sg:city":"Carramar",
    "sg:classifiers":[
        {
            "category":"Autos & Motor Vehicles",
            "subcategory":"Auto Supplies",
            "type":"Retail Goods"
        }
    ],
    "sg:phone":"+61 2 9727 7521",
    "sg:postcode":"2163",
    "sg:province":"NSW",
    "sg:tags":[
        "tyre"
    ],
    "wof:name":"Hwy Tyres",
    "wof:placetype":"venue"
},
  "geometry": {"coordinates":[150.970779419,-33.8892021179],"type":"Point"}
}