{
  "type": "Feature",
  "properties": {
    "addr:full":"11 Higginbotham St Coburg VIC 3058",
    "addr:housenumber":"11",
    "addr:postcode":"3058",
    "addr:street":"Higginbotham St",
    "iso:country":"AU",
    "sg:address":"11 Higginbotham St",
    "sg:city":"Coburg",
    "sg:classifiers":[
        {
            "category":"Building & Trades",
            "subcategory":"Construction",
            "type":"Services"
        }
    ],
    "sg:phone":"+61 418 417 606",
    "sg:postcode":"3058",
    "sg:province":"VIC",
    "sg:tags":[
        "fencing",
        "contractor"
    ],
    "wof:name":"Hard Hammer Constructions",
    "wof:placetype":"venue"
},
  "geometry": {"coordinates":[144.95794677699999,-37.7360115051],"type":"Point"}
}