{
  "type": "Feature",
  "properties": {
    "addr:full":"May St Altona North VIC 3025",
    "addr:postcode":"3025",
    "addr:street":"May St",
    "iso:country":"AU",
    "sg:address":"May St",
    "sg:city":"Altona North",
    "sg:classifiers":[
        {
            "category":"Retail",
            "subcategory":"Auto Repair",
            "type":"Services"
        }
    ],
    "sg:phone":"+61 3 9399 2345",
    "sg:postcode":"3025",
    "sg:province":"VIC",
    "sg:tags":[
        "repairer",
        "motor",
        "engineer"
    ],
    "wof:name":"IRG Motors",
    "wof:placetype":"venue"
},
  "geometry": {"coordinates":[144.847992,-37.833004],"type":"Point"}
}