{
  "type": "Feature",
  "properties": {
    "addr:full":"1 Sunrise Drv Mulgrave VIC 3170",
    "addr:housenumber":"1",
    "addr:postcode":"3170",
    "addr:street":"Sunrise Drv",
    "iso:country":"AU",
    "sg:address":"1 Sunrise Drv",
    "sg:city":"Mulgrave",
    "sg:classifiers":[
        {
            "category":"Communications",
            "type":"Services"
        }
    ],
    "sg:phone":"+61 3 9560 4882",
    "sg:postcode":"3170",
    "sg:province":"VIC",
    "sg:tags":[
        "translation"
    ],
    "wof:name":"Louis Ternel",
    "wof:placetype":"venue"
},
  "geometry": {"coordinates":[145.173538208,-37.9271354675],"type":"Point"}
}