{
  "type": "Feature",
  "properties": {
    "addr:full":"1033 Centre Rd Oakleigh South VIC 3167",
    "addr:housenumber":"1033",
    "addr:postcode":"3167",
    "addr:street":"Centre Rd",
    "iso:country":"AU",
    "sg:address":"1033 Centre Rd",
    "sg:city":"Oakleigh South",
    "sg:classifiers":[
        {
            "category":"Real Estate",
            "subcategory":"Real Estate Agent",
            "type":"Services"
        }
    ],
    "sg:phone":"+61 3 9579 2722",
    "sg:postcode":"3167",
    "sg:province":"VIC",
    "sg:tags":[
        "handyman's",
        "equipment",
        "hire",
        "builders",
        "contractor"
    ],
    "wof:name":"Instant Hire",
    "wof:placetype":"venue"
},
  "geometry": {"coordinates":[145.084106445,-37.9240379333],"type":"Point"}
}