{
  "type": "Feature",
  "properties": {
    "iso:country":"AU",
    "sg:address":"PO Box 425",
    "sg:city":"Newcastle",
    "sg:classifiers":[
        {
            "category":"Professional",
            "subcategory":"Management & Consulting",
            "type":"Services"
        }
    ],
    "sg:phone":"+61 2 4926 1557",
    "sg:postcode":"2300",
    "sg:province":"NSW",
    "sg:tags":[
        "consultant",
        "business"
    ],
    "wof:name":"Business Diagnostics & Solutions",
    "wof:placetype":"venue"
},
  "geometry": {"coordinates":[151.780136,-32.930859],"type":"Point"}
}