{
  "type": "Feature",
  "properties": {
    "addr:full":"30 Coverley Drv Collie WA 6225",
    "addr:housenumber":"30",
    "addr:postcode":"6225",
    "addr:street":"Coverley Drv",
    "iso:country":"AU",
    "sg:address":"30 Coverley Drv",
    "sg:city":"Collie",
    "sg:classifiers":[
        {
            "category":"Building & Trades",
            "subcategory":"Construction",
            "type":"Services"
        }
    ],
    "sg:phone":"+61 8 9734 2992",
    "sg:postcode":"6225",
    "sg:province":"WA",
    "sg:tags":[
        "earth",
        "excavating",
        "moving",
        "contractor"
    ],
    "wof:name":"Carmichael Contractors",
    "wof:placetype":"venue"
},
  "geometry": {"coordinates":[116.148308,-33.34713],"type":"Point"}
}