{
  "type": "Feature",
  "properties": {
    "addr:full":"Dewar Rd Badgingarra WA 6521",
    "addr:postcode":"6521",
    "addr:street":"Dewar Rd",
    "iso:country":"AU",
    "sg:address":"Dewar Rd",
    "sg:city":"Badgingarra",
    "sg:classifiers":[
        {
            "category":"Farming",
            "subcategory":"Farm",
            "type":"Manufacturing & Wholesale Goods"
        }
    ],
    "sg:phone":"+61 8 9652 9110",
    "sg:postcode":"6521",
    "sg:province":"WA",
    "sg:tags":[
        "farmer"
    ],
    "wof:name":"Kenny A & G",
    "wof:placetype":"venue"
},
  "geometry": {"coordinates":[115.581840515,-30.3122615814],"type":"Point"}
}