{
  "type": "Feature",
  "properties": {
    "addr:full":"Ground Floor, Nth Shore Medical Cntr, 66 Pacific Highway St Leonards NSW 2065",
    "addr:housenumber":"66",
    "addr:postcode":"2065",
    "addr:street":"Nth;Pacific Highway",
    "iso:country":"AU",
    "sg:address":"Ground Floor, Nth Shore Medical Cntr, 66 Pacific Highway",
    "sg:city":"St Leonards",
    "sg:classifiers":[
        {
            "category":"Health Services",
            "subcategory":"Doctor",
            "type":"Services"
        }
    ],
    "sg:phone":"+61 2 9439 7761",
    "sg:postcode":"2065",
    "sg:province":"NSW",
    "sg:tags":[
        "medical",
        "practitioner"
    ],
    "wof:name":"Douglass Hanly Moir Pathology",
    "wof:placetype":"venue"
},
  "geometry": {"coordinates":[151.19915771500001,-33.8257675171],"type":"Point"}
}