{
  "type": "Feature",
  "properties": {
    "iso:country":"AU",
    "sg:address":"Room 18 1315 Forest St",
    "sg:city":"Bendigo",
    "sg:classifiers":[
        {
            "category":"Communications",
            "subcategory":"Film & Video Production",
            "type":"Services"
        }
    ],
    "sg:phone":"+61 3 5441 2131",
    "sg:postcode":"3550",
    "sg:province":"VIC",
    "sg:tags":[
        "society",
        "housing",
        "co-operative"
    ],
    "wof:name":"Common Equity Housing Pty Ltd",
    "wof:placetype":"venue"
},
  "geometry": {"coordinates":[144.27636718799999,-36.7594909668],"type":"Point"}
}