{
  "type": "Feature",
  "properties": {
    "iso:country":"AU",
    "sg:address":"Ann Findlay Pl",
    "sg:city":"Bateau Bay",
    "sg:classifiers":[
        {
            "category":"Social Services",
            "subcategory":"Retirement Home",
            "type":"Services"
        }
    ],
    "sg:phone":"+61 2 4332 0790",
    "sg:postcode":"2261",
    "sg:province":"NSW",
    "sg:tags":[
        "village"
    ],
    "wof:name":"Kiah Lodge Retirement Village",
    "wof:placetype":"venue"
},
  "geometry": {"coordinates":[151.47967499999999,-33.376686],"type":"Point"}
}