{
  "type": "Feature",
  "properties": {
    "addr:full":"Level 1/ 216 Glen Osmond Rd Fullarton SA 5063",
    "addr:housenumber":"/ 216",
    "addr:postcode":"5063",
    "addr:street":"Glen Osmond Rd",
    "iso:country":"AU",
    "sg:address":"Level 1/ 216 Glen Osmond Rd",
    "sg:city":"Fullarton",
    "sg:classifiers":[
        {
            "category":"Real Estate",
            "subcategory":"Architect",
            "type":"Services"
        }
    ],
    "sg:phone":"+61 8 8379 9803",
    "sg:postcode":"5063",
    "sg:province":"SA",
    "sg:tags":[
        "building",
        "designer"
    ],
    "wof:name":"Vartzokas Architects Pty Ltd",
    "wof:placetype":"venue"
},
  "geometry": {"coordinates":[138.63023376500001,-34.949420929],"type":"Point"}
}