{
  "type": "Feature",
  "properties": {
    "iso:country":"AU",
    "sg:address":"200 Mulgrave Rd",
    "sg:city":"Cairns",
    "sg:classifiers":[
        {
            "category":"Building & Trades",
            "subcategory":"Construction",
            "type":"Services"
        }
    ],
    "sg:phone":"+61 7 4050 5200",
    "sg:postcode":"4870",
    "sg:province":"QLD",
    "sg:tags":[
        "contractor"
    ],
    "wof:name":"Dixon Homes",
    "wof:placetype":"venue"
},
  "geometry": {"coordinates":[145.74693298299999,-16.9378185272],"type":"Point"}
}