{
  "type": "Feature",
  "properties": {
    "addr:full":"32 Intervale Drv Wyndham Vale VIC 3024",
    "addr:housenumber":"32",
    "addr:postcode":"3024",
    "addr:street":"Intervale Drv",
    "iso:country":"AU",
    "sg:address":"32 Intervale Drv",
    "sg:city":"Wyndham Vale",
    "sg:classifiers":[
        {
            "category":"Building & Trades",
            "subcategory":"Construction",
            "type":"Services"
        }
    ],
    "sg:phone":"+61 405 779 324",
    "sg:postcode":"3024",
    "sg:province":"VIC",
    "sg:tags":[
        "fencing",
        "contractor"
    ],
    "wof:name":"Chris Te Puni",
    "wof:placetype":"venue"
},
  "geometry": {"coordinates":[144.62619000000001,-37.895191],"type":"Point"}
}