{
  "type": "Feature",
  "properties": {
    "addr:full":"16 Janderra St Buderim QLD 4556",
    "addr:housenumber":"16",
    "addr:postcode":"4556",
    "addr:street":"Janderra St",
    "iso:country":"AU",
    "sg:address":"16 Janderra St",
    "sg:city":"Buderim",
    "sg:classifiers":[
        {
            "category":"Manufacturing",
            "subcategory":"Metals",
            "type":"Manufacturing & Wholesale Goods"
        }
    ],
    "sg:phone":"+61 7 5477 0202",
    "sg:postcode":"4556",
    "sg:province":"QLD",
    "sg:tags":[
        "steel",
        "fabricator",
        "mfrs"
    ],
    "wof:name":"Regent Fabrications",
    "wof:placetype":"venue"
},
  "geometry": {"coordinates":[153.080245972,-26.6919460297],"type":"Point"}
}