{
  "type": "Feature",
  "properties": {
    "iso:country":"AU",
    "sg:address":"5 Bouganville St",
    "sg:city":"Boronia",
    "sg:classifiers":[
        {
            "category":"Home & Garden",
            "subcategory":"Household Appliances",
            "type":"Retail Goods"
        }
    ],
    "sg:phone":"+61 3 9729 7734",
    "sg:postcode":"3155",
    "sg:province":"VIC",
    "sg:tags":[
        "heating",
        "system"
    ],
    "wof:name":"Floorheat Pty Ltd",
    "wof:placetype":"venue"
},
  "geometry": {"coordinates":[145.29116821299999,-37.8399543762],"type":"Point"}
}