{
  "type": "Feature",
  "properties": {
    "addr:full":"34 Thackeray St Norman Park QLD 4170",
    "addr:housenumber":"34",
    "addr:postcode":"4170",
    "addr:street":"Thackeray St",
    "iso:country":"AU",
    "sg:address":"34 Thackeray St",
    "sg:city":"Norman Park",
    "sg:classifiers":[
        {
            "category":"Education",
            "subcategory":"Special Training",
            "type":"Public Place"
        }
    ],
    "sg:phone":"+61 7 3395 6237",
    "sg:postcode":"4170",
    "sg:province":"QLD",
    "sg:tags":[
        "development"
    ],
    "wof:name":"Mischefski Paul",
    "wof:placetype":"venue"
},
  "geometry": {"coordinates":[153.0597229,-27.4782352448],"type":"Point"}
}