{
  "type": "Feature",
  "properties": {
    "iso:country":"AU",
    "sg:address":"15 White St",
    "sg:city":"Maribyrnong",
    "sg:classifiers":[
        {
            "category":"Wholesale",
            "subcategory":"Home Furnishings",
            "type":"Manufacturing & Wholesale Goods"
        }
    ],
    "sg:phone":"+61 3 9317 8122",
    "sg:postcode":"3032",
    "sg:province":"VIC",
    "sg:tags":[
        "wholesaler",
        "bedding",
        "mfrs",
        "bed"
    ],
    "wof:name":"Dreamworks Bedding",
    "wof:placetype":"venue"
},
  "geometry": {"coordinates":[144.883667,-37.773647],"type":"Point"}
}