{
  "type": "Feature",
  "properties": {
    "addr:full":"Shop 7-8 Fitzgerald Ave Springwood QLD 4127",
    "addr:housenumber":"shop 7-8",
    "addr:postcode":"4127",
    "addr:street":"Fitzgerald Ave",
    "iso:country":"AU",
    "sg:address":"Shop 7-8 Fitzgerald Ave",
    "sg:city":"Springwood",
    "sg:classifiers":[
        {
            "category":"Wholesale",
            "subcategory":"Medical Equipment & Supplies",
            "type":"Manufacturing & Wholesale Goods"
        }
    ],
    "sg:phone":"+61 7 3208 7591",
    "sg:postcode":"4127",
    "sg:province":"QLD",
    "sg:tags":[
        "aid",
        "care",
        "health",
        "home"
    ],
    "wof:name":"Springwood Shopping Centre Day & Night Pharmacy",
    "wof:placetype":"venue"
},
  "geometry": {"coordinates":[153.126220703,-27.6121501923],"type":"Point"}
}