{
  "type": "Feature",
  "properties": {
    "iso:country":"AU",
    "sg:address":"Unit 8/ 278 Camboon Rd",
    "sg:city":"Malaga",
    "sg:classifiers":[
        {
            "category":"Building & Trades",
            "subcategory":"Construction",
            "type":"Services"
        }
    ],
    "sg:phone":"+61 8 9209 3636",
    "sg:postcode":"6090",
    "sg:province":"WA",
    "sg:tags":[
        "contractor"
    ],
    "wof:name":"Jondor Constructions",
    "wof:placetype":"venue"
},
  "geometry": {"coordinates":[115.88723754900001,-31.8556880951],"type":"Point"}
}