{
  "type": "Feature",
  "properties": {
    "addr:full":"169 Wilshire Rd Londonderry NSW 2753",
    "addr:housenumber":"169",
    "addr:postcode":"2753",
    "addr:street":"Wilshire Rd",
    "iso:country":"AU",
    "sg:address":"169 Wilshire Rd",
    "sg:city":"Londonderry",
    "sg:classifiers":[
        {
            "category":"Professional",
            "subcategory":"Engineering",
            "type":"Services"
        }
    ],
    "sg:phone":"+61 2 4578 2785",
    "sg:postcode":"2753",
    "sg:province":"NSW",
    "sg:tags":[
        "installation",
        "maintenance",
        "engineer"
    ],
    "wof:name":"Jeylan Services Pty Ltd",
    "wof:placetype":"venue"
},
  "geometry": {"coordinates":[150.72067260700001,-33.628780365],"type":"Point"}
}