{
  "type": "Feature",
  "properties": {
    "addr:full":"11 Anzac Crs Loxton SA 5333",
    "addr:housenumber":"11",
    "addr:postcode":"5333",
    "addr:street":"Anzac Crs",
    "iso:country":"AU",
    "sg:address":"11 Anzac Crs",
    "sg:city":"Loxton",
    "sg:classifiers":[
        {
            "category":"Health Services",
            "subcategory":"Doctor",
            "type":"Services"
        }
    ],
    "sg:phone":"+61 8 8584 7321",
    "sg:postcode":"5333",
    "sg:province":"SA",
    "sg:tags":[
        "medical",
        "practitioner"
    ],
    "wof:name":"Hamilton P W Dr",
    "wof:placetype":"venue"
},
  "geometry": {"coordinates":[140.57780456500001,-34.4486694336],"type":"Point"}
}