{
  "type": "Feature",
  "properties": {
    "addr:full":"Masons Rd Forest Range SA 5139",
    "addr:postcode":"5139",
    "addr:street":"Masons Rd",
    "iso:country":"AU",
    "sg:address":"Masons Rd",
    "sg:city":"Forest Range",
    "sg:classifiers":[
        {
            "category":"Farming",
            "subcategory":"Orchard",
            "type":"Manufacturing & Wholesale Goods"
        }
    ],
    "sg:phone":"+61 8 8389 8386",
    "sg:postcode":"5139",
    "sg:province":"SA",
    "sg:tags":[
        "pear",
        "apple",
        "grower"
    ],
    "wof:name":"Mason AG & HC",
    "wof:placetype":"venue"
},
  "geometry": {"coordinates":[138.798461914,-34.9264297485],"type":"Point"}
}