{
  "type": "Feature",
  "properties": {
    "addr:full":"47 Billabirra Crs Nerang QLD 4211",
    "addr:housenumber":"47",
    "addr:postcode":"4211",
    "addr:street":"Billabirra Crs",
    "iso:country":"AU",
    "sg:address":"47 Billabirra Crs",
    "sg:city":"Nerang",
    "sg:classifiers":[
        {
            "category":"Building & Trades",
            "subcategory":"Construction",
            "type":"Services"
        }
    ],
    "sg:phone":"+61 412 758 968",
    "sg:postcode":"4211",
    "sg:province":"QLD",
    "sg:tags":[
        "management"
    ],
    "wof:name":"Black Rock (QLD) Pty Ltd",
    "wof:placetype":"venue"
},
  "geometry": {"coordinates":[153.336425781,-27.989440918],"type":"Point"}
}