{
  "type": "Feature",
  "properties": {
    "iso:country":"AU",
    "sg:address":"U4/ 577 Boundary Rd",
    "sg:city":"Archerfield",
    "sg:classifiers":[
        {
            "category":"Manufacturing",
            "subcategory":"Tools & Machinery",
            "type":"Manufacturing & Wholesale Goods"
        }
    ],
    "sg:phone":"+61 7 3277 4983",
    "sg:postcode":"4108",
    "sg:province":"QLD",
    "sg:tags":[
        "earth",
        "excavating",
        "moving",
        "equipment"
    ],
    "wof:name":"Southern Tool & Equipment",
    "wof:placetype":"venue"
},
  "geometry": {"coordinates":[153.01922607399999,-27.5677242279],"type":"Point"}
}