{
  "type": "Feature",
  "properties": {
    "addr:full":"Fcty 3/ 34 Berwick Rd Campbellfield VIC 3061",
    "addr:housenumber":"/ 34",
    "addr:postcode":"3061",
    "addr:street":"Berwick Rd",
    "iso:country":"AU",
    "sg:address":"Fcty 3/ 34 Berwick Rd",
    "sg:city":"Campbellfield",
    "sg:classifiers":[
        {
            "category":"Home & Garden",
            "subcategory":"Carpets & Floor Coverings",
            "type":"Retail Goods"
        }
    ],
    "sg:phone":"+61 3 9357 8955",
    "sg:postcode":"3061",
    "sg:province":"VIC",
    "sg:tags":[
        "tile",
        "wall"
    ],
    "wof:name":"Tiles &#039;N&#039; Things",
    "wof:placetype":"venue"
},
  "geometry": {"coordinates":[144.956100464,-37.671333313],"type":"Point"}
}