{
  "type": "Feature",
  "properties": {
    "addr:full":"117 Gordon St Balwyn VIC 3103",
    "addr:housenumber":"117",
    "addr:postcode":"3103",
    "addr:street":"Gordon St",
    "iso:country":"AU",
    "sg:address":"117 Gordon St",
    "sg:city":"Balwyn",
    "sg:classifiers":[
        {
            "category":"Building & Trades",
            "subcategory":"Construction",
            "type":"Services"
        }
    ],
    "sg:phone":"+61 3 9817 7077",
    "sg:postcode":"3103",
    "sg:province":"VIC",
    "sg:tags":[
        "contractor"
    ],
    "wof:name":"Boss Housing Developments Pty Ltd",
    "wof:placetype":"venue"
},
  "geometry": {"coordinates":[145.07537841800001,-37.808391571],"type":"Point"}
}