{
  "type": "Feature",
  "properties": {
    "addr:full":"13 Grandview Crt Crafers SA 5152",
    "addr:housenumber":"13",
    "addr:postcode":"5152",
    "addr:street":"Grandview Crt",
    "iso:country":"AU",
    "sg:address":"13 Grandview Crt",
    "sg:city":"Crafers",
    "sg:classifiers":[
        {
            "category":"Building & Trades",
            "subcategory":"Construction",
            "type":"Services"
        }
    ],
    "sg:phone":"+61 8 8370 8283",
    "sg:postcode":"5152",
    "sg:province":"SA",
    "sg:tags":[
        "ceiling"
    ],
    "wof:name":"Premier Ceilings Pty Ltd",
    "wof:placetype":"venue"
},
  "geometry": {"coordinates":[138.72698974599999,-34.9871902466],"type":"Point"}
}