{
  "type": "Feature",
  "properties": {
    "iso:country":"AU",
    "sg:address":"130 Bushby&#039;s Rd",
    "sg:city":"Barongarook",
    "sg:classifiers":[
        {
            "category":"Farming",
            "subcategory":"Nursery",
            "type":"Manufacturing & Wholesale Goods"
        }
    ],
    "sg:phone":"+61 3 5233 8357",
    "sg:postcode":"3249",
    "sg:province":"VIC",
    "wof:name":"Barongarook Nursery",
    "wof:placetype":"venue"
},
  "geometry": {"coordinates":[143.583694458,-38.4132995605],"type":"Point"}
}