{
  "type": "Feature",
  "properties": {
    "addr:full":"29 Wellington Rd Lysterfield VIC 3156",
    "addr:housenumber":"29",
    "addr:postcode":"3156",
    "addr:street":"Wellington Rd",
    "iso:country":"AU",
    "sg:address":"29 Wellington Rd",
    "sg:city":"Lysterfield",
    "sg:classifiers":[
        {
            "category":"Shopping",
            "subcategory":"Shoes",
            "type":"Retail Goods"
        }
    ],
    "sg:phone":"+61 3 9013 9307",
    "sg:postcode":"3156",
    "sg:province":"VIC",
    "sg:tags":[
        "footwear"
    ],
    "wof:name":"Kinky Boots",
    "wof:placetype":"venue"
},
  "geometry": {"coordinates":[145.278076172,-37.9267654419],"type":"Point"}
}