{
  "type": "Feature",
  "properties": {
    "addr:full":"68 Prince Regent Drv Heathridge WA 6027",
    "addr:housenumber":"68",
    "addr:postcode":"6027",
    "addr:street":"Prince Regent Drv",
    "iso:country":"AU",
    "sg:address":"68 Prince Regent Drv",
    "sg:city":"Heathridge",
    "sg:classifiers":[
        {
            "category":"Home & Garden",
            "subcategory":"Hardware",
            "type":"Retail Goods"
        }
    ],
    "sg:phone":"+61 8 9307 2080",
    "sg:postcode":"6027",
    "sg:province":"WA",
    "sg:tags":[
        "part",
        "air conditioning"
    ],
    "wof:name":"Air Conditioning Ancillaries",
    "wof:placetype":"venue"
},
  "geometry": {"coordinates":[115.750396728,-31.7589645386],"type":"Point"}
}