{
  "type": "Feature",
  "properties": {
    "addr:full":"56 Kendall Crs Bonny Hills NSW 2445",
    "addr:housenumber":"56",
    "addr:postcode":"2445",
    "addr:street":"Kendall Crs",
    "iso:country":"AU",
    "sg:address":"56 Kendall Crs",
    "sg:city":"Bonny Hills",
    "sg:classifiers":[
        {
            "category":"Building & Trades",
            "subcategory":"Construction",
            "type":"Services"
        }
    ],
    "sg:phone":"+61 438 654 994",
    "sg:postcode":"2445",
    "sg:province":"NSW",
    "sg:tags":[
        "renovation",
        "alterations",
        "extension",
        "contractor"
    ],
    "wof:name":"BMB Constructions",
    "wof:placetype":"venue"
},
  "geometry": {"coordinates":[152.836411,-31.588989],"type":"Point"}
}