{
  "type": "Feature",
  "properties": {
    "iso:country":"AU",
    "sg:address":"PO Box 360",
    "sg:city":"Enmore",
    "sg:classifiers":[
        {
            "category":"Shopping",
            "subcategory":"Computers & Home Electronics",
            "type":"Retail Goods"
        }
    ],
    "sg:phone":"+61 2 9560 3737",
    "sg:postcode":"2042",
    "sg:province":"NSW",
    "sg:tags":[
        "equipment",
        "multimedia"
    ],
    "wof:name":"Filmview Services",
    "wof:placetype":"venue"
},
  "geometry": {"coordinates":[151.171173,-33.899288],"type":"Point"}
}