{
  "type": "Feature",
  "properties": {
    "addr:full":"118 Coolart Rd Tuerong VIC 3933",
    "addr:housenumber":"118",
    "addr:postcode":"3933",
    "addr:street":"Coolart Rd",
    "iso:country":"AU",
    "sg:address":"118 Coolart Rd",
    "sg:city":"Tuerong",
    "sg:classifiers":[
        {
            "category":"Building & Trades",
            "subcategory":"Construction",
            "type":"Services"
        }
    ],
    "sg:phone":"+61 3 5979 1591",
    "sg:postcode":"3933",
    "sg:province":"VIC",
    "sg:tags":[
        "fencing",
        "contractor"
    ],
    "wof:name":"Donat Philippe",
    "wof:placetype":"venue"
},
  "geometry": {"coordinates":[145.156936645,-38.2088928223],"type":"Point"}
}