{
  "type": "Feature",
  "properties": {
    "addr:full":"Cnr High & Logan Sts Tenterfield NSW 2372",
    "addr:postcode":"2372",
    "iso:country":"AU",
    "sg:address":"Cnr High & Logan Sts",
    "sg:city":"Tenterfield",
    "sg:classifiers":[
        {
            "category":"Personal",
            "subcategory":"Massage",
            "type":"Services"
        }
    ],
    "sg:phone":"+61 429 436 756",
    "sg:postcode":"2372",
    "sg:province":"NSW",
    "sg:tags":[
        "therapy"
    ],
    "wof:name":"Rachel Kerr",
    "wof:placetype":"venue"
},
  "geometry": {"coordinates":[152.02116394000001,-29.0547866821],"type":"Point"}
}