{
  "type": "Feature",
  "properties": {
    "iso:country":"AU",
    "sg:address":"PO Box 67",
    "sg:city":"Morayfield",
    "sg:classifiers":[
        {
            "category":"Retail",
            "subcategory":"Repair Shop",
            "type":"Services"
        }
    ],
    "sg:phone":"+61 409 811 708",
    "sg:postcode":"4506",
    "sg:province":"QLD",
    "sg:tags":[
        "upholsterer"
    ],
    "wof:name":"S.F.R. Upholstery Services",
    "wof:placetype":"venue"
},
  "geometry": {"coordinates":[152.94992065400001,-27.1089096069],"type":"Point"}
}