{
  "type": "Feature",
  "properties": {
    "addr:full":"60 Best St Belgrave VIC 3160",
    "addr:housenumber":"60",
    "addr:postcode":"3160",
    "addr:street":"Best St",
    "iso:country":"AU",
    "sg:address":"60 Best St",
    "sg:city":"Belgrave",
    "sg:classifiers":[
        {
            "category":"Health Services",
            "subcategory":"Health Practitioner",
            "type":"Services"
        }
    ],
    "sg:phone":"+61 3 9752 5086",
    "sg:postcode":"3160",
    "sg:province":"VIC",
    "sg:tags":[
        "psychologist"
    ],
    "wof:name":"McKay Lucinda",
    "wof:placetype":"venue"
},
  "geometry": {"coordinates":[145.354049683,-37.9144477844],"type":"Point"}
}