{
  "type": "Feature",
  "properties": {
    "iso:country":"AU",
    "sg:address":"45 York St",
    "sg:city":"Glen Waverley",
    "sg:classifiers":[
        {
            "category":"Professional",
            "subcategory":"Employment Agencies",
            "type":"Services"
        }
    ],
    "sg:phone":"+61 3 9803 2424",
    "sg:postcode":"3150",
    "sg:province":"VIC",
    "sg:tags":[
        "entertainer",
        "agent"
    ],
    "wof:name":"de Moiser# MAGIC",
    "wof:placetype":"venue"
},
  "geometry": {"coordinates":[145.177444458,-37.8695335388],"type":"Point"}
}