{
  "type": "Feature",
  "properties": {
    "addr:full":"Level 3, Shop U091 Macarthur Square Ambarvale NSW 2560",
    "addr:housenumber":"shop u091",
    "addr:postcode":"2560",
    "addr:street":"Macarthur Square",
    "iso:country":"AU",
    "sg:address":"Level 3, Shop U091 Macarthur Square",
    "sg:city":"Ambarvale",
    "sg:classifiers":[
        {
            "category":"Shopping",
            "subcategory":"Computers & Home Electronics",
            "type":"Retail Goods"
        }
    ],
    "sg:phone":"+61 2 4626 5960",
    "sg:postcode":"2560",
    "sg:province":"NSW",
    "sg:tags":[
        "hire",
        "video",
        "game"
    ],
    "wof:name":"Games Wizards The",
    "wof:placetype":"venue"
},
  "geometry": {"coordinates":[150.80238342300001,-34.0839996338],"type":"Point"}
}