{
  "type": "Feature",
  "properties": {
    "addr:full":"378 Bridge Rd Richmond VIC 3121",
    "addr:housenumber":"378",
    "addr:postcode":"3121",
    "addr:street":"Bridge Rd",
    "iso:country":"AU",
    "sg:address":"378 Bridge Rd",
    "sg:city":"Richmond",
    "sg:classifiers":[
        {
            "category":"Travel",
            "subcategory":"Travel Agent",
            "type":"Entertainment"
        }
    ],
    "sg:phone":"+61 3 9428 5283",
    "sg:postcode":"3121",
    "sg:province":"VIC",
    "sg:tags":[
        "consultant"
    ],
    "wof:name":"R J Travel Pty Ltd",
    "wof:placetype":"venue"
},
  "geometry": {"coordinates":[145.004104614,-37.8191795349],"type":"Point"}
}