{
  "type": "Feature",
  "properties": {
    "addr:full":"3 Naweena Rd Regency Park SA 5010",
    "addr:housenumber":"3",
    "addr:postcode":"5010",
    "addr:street":"Naweena Rd",
    "iso:country":"AU",
    "sg:address":"3 Naweena Rd",
    "sg:city":"Regency Park",
    "sg:classifiers":[
        {
            "category":"Freight",
            "type":"Transportation"
        }
    ],
    "sg:phone":"+61 8 8346 3937",
    "sg:postcode":"5010",
    "sg:province":"SA",
    "sg:tags":[
        "light",
        "carrier"
    ],
    "wof:name":"R.E.D. Express Deliveries",
    "wof:placetype":"venue"
},
  "geometry": {"coordinates":[138.57420349099999,-34.8641891479],"type":"Point"}
}