{
  "type": "Feature",
  "properties": {
    "addr:full":"382 Pacific Hwy Crows Nest NSW 2065",
    "addr:housenumber":"382",
    "addr:postcode":"2065",
    "addr:street":"Pacific Hwy",
    "iso:country":"AU",
    "sg:address":"382 Pacific Hwy",
    "sg:city":"Crows Nest",
    "sg:classifiers":[
        {
            "category":"Restaurant",
            "type":"Food & Drink"
        }
    ],
    "sg:phone":"+61 2 9966 8855",
    "sg:postcode":"2065",
    "sg:province":"NSW",
    "wof:name":"E-UR-Do Korean Restaurant",
    "wof:placetype":"venue"
},
  "geometry": {"coordinates":[151.198928833,-33.8259468079],"type":"Point"}
}