{
  "type": "Feature",
  "properties": {
    "addr:full":"15 James St Clayton VIC 3168",
    "addr:housenumber":"15",
    "addr:postcode":"3168",
    "addr:street":"James St",
    "iso:country":"AU",
    "sg:address":"15 James St",
    "sg:city":"Clayton",
    "sg:classifiers":[
        {
            "category":"Retail",
            "subcategory":"Auto Repair",
            "type":"Services"
        }
    ],
    "sg:phone":"+61 3 9544 9018",
    "sg:postcode":"3168",
    "sg:province":"VIC",
    "sg:tags":[
        "repairer",
        "motor",
        "engineer"
    ],
    "wof:name":"Gulian Motors",
    "wof:placetype":"venue"
},
  "geometry": {"coordinates":[145.120635986,-37.9301986694],"type":"Point"}
}