{
  "type": "Feature",
  "properties": {
    "iso:country":"AU",
    "sg:address":"80 Daltons Rd",
    "sg:city":"Warrnambool",
    "sg:classifiers":[
        {
            "category":"Building & Trades",
            "subcategory":"Equipment Rental",
            "type":"Services"
        }
    ],
    "sg:phone":"+61 419 138 078",
    "sg:postcode":"3280",
    "sg:province":"VIC",
    "sg:tags":[
        "party",
        "hire"
    ],
    "wof:name":"Ensuites on the Move",
    "wof:placetype":"venue"
},
  "geometry": {"coordinates":[142.47605895999999,-38.3632278442],"type":"Point"}
}