{
  "type": "Feature",
  "properties": {
    "iso:country":"AU",
    "sg:address":"74 Minora Rd",
    "sg:city":"Dalkeith",
    "sg:classifiers":[
        {
            "category":"Professional",
            "subcategory":"Management & Consulting",
            "type":"Services"
        }
    ],
    "sg:phone":"+61 8 6389 0020",
    "sg:postcode":"6009",
    "sg:province":"WA",
    "sg:tags":[
        "consultant",
        "business"
    ],
    "wof:name":"McDonald & Company (Australasia) Pty Ltd",
    "wof:placetype":"venue"
},
  "geometry": {"coordinates":[115.79389999999999,-31.999283],"type":"Point"}
}