{
  "type": "Feature",
  "properties": {
    "addr:full":"Unit 7/ 628-630 Newcastle St Leederville WA 6007",
    "addr:housenumber":"/ 628-630",
    "addr:postcode":"6007",
    "addr:street":"Newcastle St",
    "iso:country":"AU",
    "sg:address":"Unit 7/ 628-630 Newcastle St",
    "sg:city":"Leederville",
    "sg:classifiers":[
        {
            "category":"Professional",
            "subcategory":"Management & Consulting",
            "type":"Services"
        }
    ],
    "sg:phone":"+61 8 9244 8897",
    "sg:postcode":"6007",
    "sg:province":"WA",
    "sg:tags":[
        "consultant",
        "business"
    ],
    "wof:name":"People Rich Pty Ltd",
    "wof:placetype":"venue"
},
  "geometry": {"coordinates":[115.844467163,-31.9384727478],"type":"Point"}
}