{
  "type": "Feature",
  "properties": {
    "iso:country":"AU",
    "sg:address":"106 Hampden St",
    "sg:city":"Artarmon",
    "sg:classifiers":[
        {
            "category":"Food & Beverages",
            "subcategory":"Fruits & Vegetables",
            "type":"Retail Goods"
        }
    ],
    "sg:phone":"+61 2 9411 1401",
    "sg:postcode":"2064",
    "sg:province":"NSW",
    "sg:tags":[
        "greengrocer",
        "fruiterer"
    ],
    "wof:name":"Artarmon Fruit Market",
    "wof:placetype":"venue"
},
  "geometry": {"coordinates":[151.18414306599999,-33.8086433411],"type":"Point"}
}