{
  "type": "Feature",
  "properties": {
    "iso:country":"AU",
    "sg:address":"185 Elizabeth St",
    "sg:city":"Sydney",
    "sg:classifiers":[
        {
            "category":"Health Services",
            "subcategory":"Dentist",
            "type":"Services"
        }
    ],
    "sg:phone":"+61 2 9267 8781",
    "sg:postcode":"2000",
    "sg:province":"NSW",
    "wof:name":"Graham Dr David A & Yanniotis Dr John",
    "wof:placetype":"venue"
},
  "geometry": {"coordinates":[151.20986938499999,-33.8726425171],"type":"Point"}
}