{
  "type": "Feature",
  "properties": {
    "iso:country":"AU",
    "sg:address":"22 Warren Park Pl",
    "sg:city":"Narre Warren",
    "sg:classifiers":[
        {
            "category":"Retail",
            "subcategory":"Repair Shop",
            "type":"Services"
        }
    ],
    "sg:phone":"+61 3 8794 8362",
    "sg:postcode":"3805",
    "sg:province":"VIC",
    "sg:tags":[
        "machine",
        "repairs",
        "part",
        "dryer",
        "washing"
    ],
    "wof:name":"Davez Washer and Dryer Repairs",
    "wof:placetype":"venue"
},
  "geometry": {"coordinates":[145.296936,-38.039375],"type":"Point"}
}