{
  "type": "Feature",
  "properties": {
    "iso:country":"AU",
    "sg:address":"Level 11, 1 Eagle St, Waterfront Pl",
    "sg:city":"Brisbane",
    "sg:classifiers":[
        {
            "category":"Banks & Credit Unions",
            "subcategory":"Investment Brokerage",
            "type":"Services"
        }
    ],
    "sg:phone":"+61 1800 000 369",
    "sg:postcode":"4001",
    "sg:province":"QLD",
    "sg:tags":[
        "share",
        "broker",
        "stock"
    ],
    "wof:name":"Freeman Fox Securities",
    "wof:placetype":"venue"
},
  "geometry": {"coordinates":[153.03047180199999,-27.4695243835],"type":"Point"}
}