{
  "type": "Feature",
  "properties": {
    "addr:full":"Level 2, 167 Gouger St Adelaide SA 5000",
    "addr:housenumber":"167",
    "addr:postcode":"5000",
    "addr:street":"Gouger St",
    "iso:country":"AU",
    "sg:address":"Level 2, 167 Gouger St",
    "sg:city":"Adelaide",
    "sg:classifiers":[
        {
            "category":"Professional",
            "subcategory":"Computer Services",
            "type":"Services"
        }
    ],
    "sg:phone":"+61 8 8410 9030",
    "sg:postcode":"5000",
    "sg:province":"SA",
    "sg:tags":[
        "repairs",
        "upgrade",
        "equipment"
    ],
    "wof:name":"Sotek Information Systems",
    "wof:placetype":"venue"
},
  "geometry": {"coordinates":[138.593017578,-34.9306144714],"type":"Point"}
}