{
  "type": "Feature",
  "properties": {
    "iso:country":"AU",
    "sg:address":"Shop 32, Castletown Shopping World, Cnr Kings Rd &",
    "sg:city":"Hyde Park",
    "sg:classifiers":[
        {
            "category":"Banks & Credit Unions",
            "subcategory":"Bank",
            "type":"Services"
        }
    ],
    "sg:phone":"+61 7 4772 1500",
    "sg:postcode":"4812",
    "sg:province":"QLD",
    "wof:name":"Credit Union Australia",
    "wof:placetype":"venue"
},
  "geometry": {"coordinates":[146.791824,-19.278521],"type":"Point"}
}