{
  "type": "Feature",
  "properties": {
    "iso:country":"AU",
    "sg:address":"Unit 4 5 Navigator Pl",
    "sg:city":"Hendra",
    "sg:classifiers":[
        {
            "category":"Sports & Exercise",
            "subcategory":"Gym",
            "type":"Entertainment"
        }
    ],
    "sg:phone":"+61 7 3268 6450",
    "sg:postcode":"4011",
    "sg:province":"QLD",
    "sg:tags":[
        "personal",
        "trainer",
        "fitness"
    ],
    "wof:name":"Flexfit",
    "wof:placetype":"venue"
},
  "geometry": {"coordinates":[153.075211,-27.414314],"type":"Point"}
}