{
  "type": "Feature",
  "properties": {
    "iso:country":"AU",
    "sg:address":"26 Iandra St",
    "sg:city":"Concord West",
    "sg:classifiers":[
        {
            "category":"Health Services",
            "subcategory":"Health Practitioner",
            "type":"Services"
        }
    ],
    "sg:phone":"+61 2 9736 1348",
    "sg:postcode":"2138",
    "sg:province":"NSW",
    "sg:tags":[
        "physiotherapist"
    ],
    "wof:name":"Barbara Furniss-Concord West Physiotherapy",
    "wof:placetype":"venue"
},
  "geometry": {"coordinates":[151.09266662600001,-33.8437232971],"type":"Point"}
}