{
  "type": "Feature",
  "properties": {
    "iso:country":"AU",
    "sg:address":"16B Wellesley Pl",
    "sg:city":"Green Valley",
    "sg:classifiers":[
        {
            "category":"Building & Trades",
            "subcategory":"Construction",
            "type":"Services"
        }
    ],
    "sg:phone":"+61 2 9826 9104",
    "sg:postcode":"2168",
    "sg:province":"NSW",
    "sg:tags":[
        "contractor"
    ],
    "wof:name":"MJJ Services Pty Ltd",
    "wof:placetype":"venue"
},
  "geometry": {"coordinates":[150.86180114699999,-33.8999710083],"type":"Point"}
}