{
  "type": "Feature",
  "properties": {
    "addr:full":"3 Loyalty Rd North Rocks NSW 2151",
    "addr:housenumber":"3",
    "addr:postcode":"2151",
    "addr:street":"Loyalty Rd",
    "iso:country":"AU",
    "sg:address":"3 Loyalty Rd",
    "sg:city":"North Rocks",
    "sg:classifiers":[
        {
            "category":"Professional",
            "type":"Services"
        }
    ],
    "sg:phone":"+61 2 9630 5649",
    "sg:postcode":"2151",
    "sg:province":"NSW",
    "sg:tags":[
        "packaging",
        "filling",
        "assembling"
    ],
    "wof:name":"Clyde Contract Fillers Pty Ltd",
    "wof:placetype":"venue"
},
  "geometry": {"coordinates":[151.01167297399999,-33.7770881653],"type":"Point"}
}