{
  "type": "Feature",
  "properties": {
    "addr:full":"54 Nicholson Rd Subiaco WA 6008",
    "addr:housenumber":"54",
    "addr:postcode":"6008",
    "addr:street":"Nicholson Rd",
    "iso:country":"AU",
    "sg:address":"54 Nicholson Rd",
    "sg:city":"Subiaco",
    "sg:classifiers":[
        {
            "category":"Shopping",
            "subcategory":"Antiques",
            "type":"Retail Goods"
        }
    ],
    "sg:phone":"+61 8 9382 1011",
    "sg:postcode":"6008",
    "sg:province":"WA",
    "wof:name":"Annabelle's Antiques",
    "wof:placetype":"venue"
},
  "geometry": {"coordinates":[115.821807861,-31.9565181732],"type":"Point"}
}