{
  "type": "Feature",
  "properties": {
    "addr:full":"17A Wheeler St Shepparton VIC 3630",
    "addr:housenumber":"17a",
    "addr:postcode":"3630",
    "addr:street":"Wheeler St",
    "iso:country":"AU",
    "sg:address":"17A Wheeler St",
    "sg:city":"Shepparton",
    "sg:classifiers":[
        {
            "category":"Commercial Area",
            "type":"Public Place"
        }
    ],
    "sg:phone":"+61 3 5831 2171",
    "sg:postcode":"3630",
    "sg:province":"VIC",
    "sg:tags":[
        "heavy",
        "carrier"
    ],
    "wof:name":"Shepparton Mobile Cranes",
    "wof:placetype":"venue"
},
  "geometry": {"coordinates":[145.41989135700001,-36.3761062622],"type":"Point"}
}