{
  "type": "Feature",
  "properties": {
    "addr:full":"23 Barley Crt Delahey VIC 3038",
    "addr:housenumber":"23",
    "addr:postcode":"3038",
    "addr:street":"Barley Crt",
    "iso:country":"AU",
    "sg:address":"23 Barley Crt",
    "sg:city":"Delahey",
    "sg:classifiers":[
        {
            "category":"Shopping",
            "subcategory":"Antiques",
            "type":"Retail Goods"
        }
    ],
    "sg:phone":"+61 413 766 481",
    "sg:postcode":"3038",
    "sg:province":"VIC",
    "sg:tags":[
        "collectable",
        "memorabilia"
    ],
    "wof:name":"Road Tags U.S.A.",
    "wof:placetype":"venue"
},
  "geometry": {"coordinates":[144.76712000000001,-37.718102],"type":"Point"}
}