{
  "type": "Feature",
  "properties": {
    "addr:full":"1 Baltimore Rd Mortdale NSW 2223",
    "addr:housenumber":"1",
    "addr:postcode":"2223",
    "addr:street":"Baltimore Rd",
    "iso:country":"AU",
    "sg:address":"1 Baltimore Rd",
    "sg:city":"Mortdale",
    "sg:classifiers":[
        {
            "category":"Building & Trades",
            "subcategory":"Plumbing",
            "type":"Services"
        }
    ],
    "sg:phone":"+61 2 9580 3015",
    "sg:postcode":"2223",
    "sg:province":"NSW",
    "sg:tags":[
        "plumber",
        "gasfitters"
    ],
    "wof:name":"Russell Dennis Plumbing Service Pty Ltd",
    "wof:placetype":"venue"
},
  "geometry": {"coordinates":[151.069381714,-33.9719009399],"type":"Point"}
}