{
  "type": "Feature",
  "properties": {
    "addr:full":"151 West Burleigh Rd Burleigh Heads QLD 4220",
    "addr:housenumber":"151",
    "addr:postcode":"4220",
    "addr:street":"West Burleigh Rd",
    "iso:country":"AU",
    "sg:address":"151 West Burleigh Rd",
    "sg:city":"Burleigh Heads",
    "sg:classifiers":[
        {
            "category":"Shopping",
            "subcategory":"Crafts & Fabrics",
            "type":"Retail Goods"
        }
    ],
    "sg:phone":"+61 7 5520 5598",
    "sg:postcode":"4220",
    "sg:province":"QLD",
    "sg:tags":[
        "supply"
    ],
    "wof:name":"The Scrapyard",
    "wof:placetype":"venue"
},
  "geometry": {"coordinates":[153.44236755399999,-28.1017856598],"type":"Point"}
}