{
  "type": "Feature",
  "properties": {
    "addr:full":"150 Commercial Rd Port Adelaide SA 5015",
    "addr:housenumber":"150",
    "addr:postcode":"5015",
    "addr:street":"Commercial Rd",
    "iso:country":"AU",
    "sg:address":"150 Commercial Rd",
    "sg:city":"Port Adelaide",
    "sg:classifiers":[
        {
            "category":"Sports & Exercise",
            "subcategory":"Gym",
            "type":"Entertainment"
        }
    ],
    "sg:phone":"+61 8 8447 6953",
    "sg:postcode":"5015",
    "sg:province":"SA",
    "sg:tags":[
        "health",
        "fitness"
    ],
    "wof:name":"Hydraslim",
    "wof:placetype":"venue"
},
  "geometry": {"coordinates":[138.50660705600001,-34.8466072083],"type":"Point"}
}