{
  "type": "Feature",
  "properties": {
    "addr:full":"2/ 20 Gibbs St Labrador QLD 4215",
    "addr:housenumber":"/ 20",
    "addr:postcode":"4215",
    "addr:street":"Gibbs St",
    "iso:country":"AU",
    "sg:address":"2/ 20 Gibbs St",
    "sg:city":"Labrador",
    "sg:classifiers":[
        {
            "category":"Home & Garden",
            "subcategory":"Building Materials",
            "type":"Retail Goods"
        }
    ],
    "sg:phone":"+61 7 5563 9244",
    "sg:postcode":"4215",
    "sg:province":"QLD",
    "sg:tags":[
        "supply"
    ],
    "wof:name":"Plumbers Hardware Distributors Pty Ltd",
    "wof:placetype":"venue"
},
  "geometry": {"coordinates":[153.38336181599999,-27.9352359772],"type":"Point"}
}