{
  "type": "Feature",
  "properties": {
    "iso:country":"AU",
    "sg:address":"Lvl 2, 100 Carillon Ave",
    "sg:city":"Camperdown",
    "sg:classifiers":[
        {
            "category":"Health Services",
            "subcategory":"Doctor",
            "type":"Services"
        }
    ],
    "sg:phone":"+61 2 9565 1137",
    "sg:postcode":"2050",
    "sg:province":"NSW",
    "sg:tags":[
        "medical",
        "practitioner"
    ],
    "wof:name":"Sleep Disorder & Respiratory Failure Consultative Clinic",
    "wof:placetype":"venue"
},
  "geometry": {"coordinates":[151.183304,-33.891499],"type":"Point"}
}