{
  "type": "Feature",
  "properties": {
    "addr:full":"737 Glen Huntly Rd Caulfield VIC 3162",
    "addr:housenumber":"737",
    "addr:postcode":"3162",
    "addr:street":"Glen Huntly Rd",
    "iso:country":"AU",
    "sg:address":"737 Glen Huntly Rd",
    "sg:city":"Caulfield",
    "sg:classifiers":[
        {
            "category":"Retail",
            "subcategory":"Laundry & Dry Cleaning",
            "type":"Services"
        }
    ],
    "sg:phone":"+61 3 9532 4104",
    "sg:postcode":"3162",
    "sg:province":"VIC",
    "sg:tags":[
        "manicurist"
    ],
    "wof:name":"Nails For Today",
    "wof:placetype":"venue"
},
  "geometry": {"coordinates":[145.02032470699999,-37.8865432739],"type":"Point"}
}