{
  "type": "Feature",
  "properties": {
    "addr:full":"52 Manning Rd Hunters Hill NSW 2110",
    "addr:housenumber":"52",
    "addr:postcode":"2110",
    "addr:street":"Manning Rd",
    "iso:country":"AU",
    "sg:address":"52 Manning Rd",
    "sg:city":"Hunters Hill",
    "sg:classifiers":[
        {
            "category":"Personal",
            "subcategory":"Massage",
            "type":"Services"
        }
    ],
    "sg:phone":"+61 2 9879 5722",
    "sg:postcode":"2110",
    "sg:province":"NSW",
    "sg:tags":[
        "therapy"
    ],
    "wof:name":"Tickner Lauren",
    "wof:placetype":"venue"
},
  "geometry": {"coordinates":[151.13693237300001,-33.8329162598],"type":"Point"}
}