{
  "type": "Feature",
  "properties": {
    "addr:full":"5 Textile Ave Maroochydore QLD 4558",
    "addr:housenumber":"5",
    "addr:postcode":"4558",
    "addr:street":"Textile Ave",
    "iso:country":"AU",
    "sg:address":"5 Textile Ave",
    "sg:city":"Maroochydore",
    "sg:classifiers":[
        {
            "category":"Sports & Exercise",
            "subcategory":"Gym",
            "type":"Entertainment"
        }
    ],
    "sg:phone":"+61 419 479 886",
    "sg:postcode":"4558",
    "sg:province":"QLD",
    "sg:tags":[
        "health",
        "fitness"
    ],
    "wof:name":"Brute Fitness",
    "wof:placetype":"venue"
},
  "geometry": {"coordinates":[153.06553649899999,-26.6553192139],"type":"Point"}
}