{
  "type": "Feature",
  "properties": {
    "addr:full":"Lvl 11/ 90 Arthur St North Sydney NSW 2060",
    "addr:housenumber":"/ 90",
    "addr:postcode":"2060",
    "addr:street":"Arthur St",
    "iso:country":"AU",
    "sg:address":"Lvl 11/ 90 Arthur St",
    "sg:city":"North Sydney",
    "sg:classifiers":[
        {
            "category":"Professional",
            "subcategory":"Computer Services",
            "type":"Services"
        }
    ],
    "sg:phone":"+61 2 9923 8000",
    "sg:postcode":"2060",
    "sg:province":"NSW",
    "sg:tags":[
        "package",
        "software"
    ],
    "wof:name":"ComOps Australia Pty Ltd",
    "wof:placetype":"venue"
},
  "geometry": {"coordinates":[151.20979309099999,-33.8397064209],"type":"Point"}
}