{
  "type": "Feature",
  "properties": {
    "addr:full":"15 George Young St Lidcombe NSW 2141",
    "addr:housenumber":"15",
    "addr:postcode":"2141",
    "addr:street":"George Young St",
    "iso:country":"AU",
    "sg:address":"15 George Young St",
    "sg:city":"Lidcombe",
    "sg:classifiers":[
        {
            "category":"Manufacturing",
            "subcategory":"Apparel",
            "type":"Manufacturing & Wholesale Goods"
        }
    ],
    "sg:phone":"+61 422 399 495",
    "sg:postcode":"2141",
    "sg:province":"NSW",
    "sg:tags":[
        "wholesaler",
        "mfrs",
        "footwear"
    ],
    "wof:name":"Victor Footwear Pty Ltd",
    "wof:placetype":"venue"
},
  "geometry": {"coordinates":[151.04083251899999,-33.8648490906],"type":"Point"}
}