{
  "type": "Feature",
  "properties": {
    "addr:full":"1/ 114 Station Rd Seven Hills NSW 2147",
    "addr:housenumber":"/ 114",
    "addr:postcode":"2147",
    "addr:street":"Station Rd",
    "iso:country":"AU",
    "sg:address":"1/ 114 Station Rd",
    "sg:city":"Seven Hills",
    "sg:classifiers":[
        {
            "category":"Military Area",
            "subcategory":"Air Force Base",
            "type":"Public Place"
        }
    ],
    "sg:phone":"+61 1300 139 181",
    "sg:postcode":"2147",
    "sg:province":"NSW",
    "sg:tags":[
        "equipment",
        "speed",
        "variation"
    ],
    "sg:website":"http://www.emtmotor.com.au",
    "wof:name":"EMT Pty Ltd",
    "wof:placetype":"venue"
},
  "geometry": {"coordinates":[150.94392395,-33.7726020813],"type":"Point"}
}