{
  "type": "Feature",
  "properties": {
    "addr:full":"Cnr Snow & Great Alpine Rds Myrtleford VIC 3737",
    "addr:postcode":"3737",
    "iso:country":"AU",
    "sg:address":"Cnr Snow & Great Alpine Rds",
    "sg:city":"Myrtleford",
    "sg:classifiers":[
        {
            "category":"Farming",
            "subcategory":"Vineyard",
            "type":"Manufacturing & Wholesale Goods"
        }
    ],
    "sg:phone":"+61 3 5751 1992",
    "sg:postcode":"3737",
    "sg:province":"VIC",
    "sg:tags":[
        "winery"
    ],
    "wof:name":"Vic Alps Winery",
    "wof:placetype":"venue"
},
  "geometry": {"coordinates":[146.715377808,-36.555644989],"type":"Point"}
}