{
  "type": "Feature",
  "properties": {
    "iso:country":"AU",
    "sg:address":"Bldg 3, 7A Gibbes St",
    "sg:city":"Chatswood",
    "sg:classifiers":[
        {
            "category":"Professional",
            "subcategory":"Employment Agencies",
            "type":"Services"
        }
    ],
    "sg:phone":"+61 2 9882 1022",
    "sg:postcode":"2057",
    "sg:province":"NSW",
    "sg:tags":[
        "provider",
        "internet"
    ],
    "wof:name":"Infotech Associates Pty Ltd",
    "wof:placetype":"venue"
},
  "geometry": {"coordinates":[151.200546,-33.790142],"type":"Point"}
}