{
  "type": "Feature",
  "properties": {
    "iso:country":"AU",
    "sg:address":"119 Malabar St",
    "sg:city":"Canley Vale",
    "sg:classifiers":[
        {
            "category":"Retail",
            "subcategory":"Auto Rental",
            "type":"Services"
        }
    ],
    "sg:phone":"+61 2 9754 2804",
    "sg:postcode":"2166",
    "sg:province":"NSW",
    "sg:tags":[
        "car",
        "wedding"
    ],
    "wof:name":"Cadillac Dreams Wedding Car",
    "wof:placetype":"venue"
},
  "geometry": {"coordinates":[150.93864440900001,-33.8771514893],"type":"Point"}
}