{
  "type": "Feature",
  "properties": {
    "iso:country":"AU",
    "sg:address":"64 Deloraine Drv",
    "sg:city":"Leonay",
    "sg:classifiers":[
        {
            "category":"Home & Garden",
            "subcategory":"Building Materials",
            "type":"Retail Goods"
        }
    ],
    "sg:phone":"+61 2 4735 5826",
    "sg:postcode":"2750",
    "sg:province":"NSW",
    "sg:tags":[
        "anti-corrosive",
        "composition",
        "flooring"
    ],
    "wof:name":"Riley Industries",
    "wof:placetype":"venue"
},
  "geometry": {"coordinates":[150.643997192,-33.7602310181],"type":"Point"}
}