{
  "type": "Feature",
  "properties": {
    "iso:country":"AU",
    "sg:address":"598 St Kilda Rd",
    "sg:city":"Melbourne",
    "sg:classifiers":[
        {
            "category":"Professional",
            "subcategory":"Business Services",
            "type":"Services"
        }
    ],
    "sg:phone":"+61 3 9510 5015",
    "sg:postcode":"3000",
    "sg:province":"VIC",
    "sg:tags":[
        "exporter"
    ],
    "wof:name":"Intrafix (Aust) Pty Ltd",
    "wof:placetype":"venue"
},
  "geometry": {"coordinates":[144.98028564399999,-37.8501243591],"type":"Point"}
}