{
  "type": "Feature",
  "properties": {
    "iso:country":"AU",
    "sg:address":"28 Boobook St",
    "sg:city":"Rocklea",
    "sg:classifiers":[
        {
            "category":"Professional",
            "subcategory":"Computer Services",
            "type":"Services"
        }
    ],
    "sg:phone":"+61 7 3277 3242",
    "sg:postcode":"4106",
    "sg:province":"QLD",
    "sg:tags":[
        "consultant",
        "system"
    ],
    "wof:name":"Drake Stuart",
    "wof:placetype":"venue"
},
  "geometry": {"coordinates":[153.014801025,-27.5488128662],"type":"Point"}
}