{
  "type": "Feature",
  "properties": {
    "addr:full":"PO Box 881 Dunsborough WA 6281",
    "addr:postcode":"6281",
    "iso:country":"AU",
    "sg:address":"PO Box 881",
    "sg:city":"Dunsborough",
    "sg:classifiers":[
        {
            "category":"Home & Garden",
            "subcategory":"Building Materials",
            "type":"Retail Goods"
        }
    ],
    "sg:phone":"+61 419 843 880",
    "sg:postcode":"6281",
    "sg:province":"WA",
    "sg:tags":[
        "lawn",
        "cutting",
        "maintenance"
    ],
    "wof:name":"Sussex Turf Control",
    "wof:placetype":"venue"
},
  "geometry": {"coordinates":[115.102020264,-33.6174812317],"type":"Point"}
}