{
  "type": "Feature",
  "properties": {
    "addr:full":"Lot 17, Coates Rd Hilltop NSW 2575",
    "addr:postcode":"2575",
    "addr:street":"Coates Rd",
    "iso:country":"AU",
    "sg:address":"Lot 17, Coates Rd",
    "sg:city":"Hilltop",
    "sg:classifiers":[
        {
            "category":"Home & Garden",
            "subcategory":"Building Materials",
            "type":"Retail Goods"
        }
    ],
    "sg:phone":"+61 2 4889 9461",
    "sg:postcode":"2575",
    "sg:province":"NSW",
    "sg:tags":[
        "lawn",
        "cutting",
        "maintenance"
    ],
    "wof:name":"Ian's TLC Gardening",
    "wof:placetype":"venue"
},
  "geometry": {"coordinates":[150.390716553,-34.3214492798],"type":"Point"}
}