{
  "type": "Feature",
  "properties": {
    "addr:full":"U 59/ 7 Percy St Auburn NSW 2144",
    "addr:housenumber":"59 / 7",
    "addr:postcode":"2144",
    "addr:street":"Percy St",
    "iso:country":"AU",
    "sg:address":"U 59/ 7 Percy St",
    "sg:city":"Auburn",
    "sg:classifiers":[
        {
            "category":"Building & Trades",
            "subcategory":"Construction",
            "type":"Services"
        }
    ],
    "sg:phone":"+61 2 9649 2249",
    "sg:postcode":"2144",
    "sg:province":"NSW",
    "sg:tags":[
        "contractor"
    ],
    "wof:name":"Sunshine Interior Services",
    "wof:placetype":"venue"
},
  "geometry": {"coordinates":[151.038894653,-33.8513717651],"type":"Point"}
}