{
  "type": "Feature",
  "properties": {
    "addr:full":"39 Susan Godfrey Drv Windaroo QLD 4207",
    "addr:housenumber":"39",
    "addr:postcode":"4207",
    "addr:street":"Susan Godfrey Drv",
    "iso:country":"AU",
    "sg:address":"39 Susan Godfrey Drv",
    "sg:city":"Windaroo",
    "sg:classifiers":[
        {
            "category":"Building & Trades",
            "subcategory":"Construction",
            "type":"Services"
        }
    ],
    "sg:phone":"+61 417 645 445",
    "sg:postcode":"4207",
    "sg:province":"QLD",
    "sg:tags":[
        "earth",
        "excavating",
        "moving",
        "contractor"
    ],
    "wof:name":"On-Site Earth-Moving Repairs Pty Ltd",
    "wof:placetype":"venue"
},
  "geometry": {"coordinates":[153.191864014,-27.7524547577],"type":"Point"}
}