{
  "type": "Feature",
  "properties": {
    "addr:full":"7 Wickepin Crt Elanora QLD 4221",
    "addr:housenumber":"7",
    "addr:postcode":"4221",
    "addr:street":"Wickepin Crt",
    "iso:country":"AU",
    "sg:address":"7 Wickepin Crt",
    "sg:city":"Elanora",
    "sg:classifiers":[
        {
            "category":"Home & Garden",
            "subcategory":"Building Materials",
            "type":"Retail Goods"
        }
    ],
    "sg:phone":"+61 422 881 899",
    "sg:postcode":"4221",
    "sg:province":"QLD",
    "sg:tags":[
        "lawn",
        "cutting",
        "maintenance"
    ],
    "wof:name":"Benns Maintenance & Garden Care",
    "wof:placetype":"venue"
},
  "geometry": {"coordinates":[153.45692443900001,-28.126707077],"type":"Point"}
}