{
  "type": "Feature",
  "properties": {
    "addr:full":"Suite 5, Level 3 450 St Kilda Rd Melbourne VIC 3000",
    "addr:housenumber":"450",
    "addr:postcode":"3000",
    "addr:street":"St Kilda Rd",
    "iso:country":"AU",
    "sg:address":"Suite 5, Level 3 450 St Kilda Rd",
    "sg:city":"Melbourne",
    "sg:classifiers":[
        {
            "category":"Banks & Credit Unions",
            "subcategory":"Investment Brokerage",
            "type":"Services"
        }
    ],
    "sg:phone":"+61 3 9820 4800",
    "sg:postcode":"3000",
    "sg:province":"VIC",
    "sg:tags":[
        "finance",
        "broker"
    ],
    "wof:name":"Australian Finance Group Ltd",
    "wof:placetype":"venue"
},
  "geometry": {"coordinates":[144.976119995,-37.8387718201],"type":"Point"}
}