{
  "type": "Feature",
  "properties": {
    "addr:full":"1 Peterbudge Ave Templestowe VIC 3106",
    "addr:housenumber":"1",
    "addr:postcode":"3106",
    "addr:street":"Peterbudge Ave",
    "iso:country":"AU",
    "sg:address":"1 Peterbudge Ave",
    "sg:city":"Templestowe",
    "sg:classifiers":[
        {
            "category":"Food & Beverages",
            "subcategory":"Fruits & Vegetables",
            "type":"Retail Goods"
        }
    ],
    "sg:phone":"+61 3 9840 2102",
    "sg:postcode":"3106",
    "sg:province":"VIC",
    "sg:tags":[
        "wholesale"
    ],
    "wof:name":"Chilli String",
    "wof:placetype":"venue"
},
  "geometry": {"coordinates":[145.14747619600001,-37.7703475952],"type":"Point"}
}