{
  "type": "Feature",
  "properties": {
    "addr:full":"Shp2/ 83 Station St Fairfield VIC 3078",
    "addr:housenumber":"83",
    "addr:postcode":"3078",
    "addr:street":"Station St",
    "iso:country":"AU",
    "sg:address":"Shp2/ 83 Station St",
    "sg:city":"Fairfield",
    "sg:classifiers":[
        {
            "category":"Restaurant",
            "type":"Food & Drink"
        }
    ],
    "sg:phone":"+61 3 9486 4466",
    "sg:postcode":"3078",
    "sg:province":"VIC",
    "sg:tags":[
        "pizza"
    ],
    "wof:name":"Basiles Pizza",
    "wof:placetype":"venue"
},
  "geometry": {"coordinates":[145.01824951200001,-37.7793502808],"type":"Point"}
}