{
  "type": "Feature",
  "properties": {
    "addr:full":"11 Balaclava St Woolloongabba QLD 4102",
    "addr:housenumber":"11",
    "addr:postcode":"4102",
    "addr:street":"Balaclava St",
    "iso:country":"AU",
    "sg:address":"11 Balaclava St",
    "sg:city":"Woolloongabba",
    "sg:classifiers":[
        {
            "category":"Retail",
            "subcategory":"Auto Repair",
            "type":"Services"
        }
    ],
    "sg:phone":"+61 7 3391 6360",
    "sg:postcode":"4102",
    "sg:province":"QLD",
    "sg:tags":[
        "repairer",
        "motor",
        "engineer"
    ],
    "wof:name":"Ryans Auto Repairs",
    "wof:placetype":"venue"
},
  "geometry": {"coordinates":[153.036743164,-27.490196228],"type":"Point"}
}