{
  "type": "Feature",
  "properties": {
    "addr:full":"40a Henry St Ravenswood TAS 7250",
    "addr:housenumber":"40a",
    "addr:postcode":"7250",
    "addr:street":"Henry St",
    "iso:country":"AU",
    "sg:address":"40a Henry St",
    "sg:city":"Ravenswood",
    "sg:classifiers":[
        {
            "category":"Building & Trades",
            "subcategory":"Construction",
            "type":"Services"
        }
    ],
    "sg:phone":"+61 3 6339 2465",
    "sg:postcode":"7250",
    "sg:province":"TAS",
    "sg:tags":[
        "brick",
        "paving"
    ],
    "wof:name":"Danny Shields",
    "wof:placetype":"venue"
},
  "geometry": {"coordinates":[147.16603088400001,-41.4218864441],"type":"Point"}
}