{
  "type": "Feature",
  "properties": {
    "addr:full":"5 Craiglee Drv Coromandel East SA 5051",
    "addr:housenumber":"5",
    "addr:postcode":"5051",
    "addr:street":"Craiglee Drv",
    "iso:country":"AU",
    "sg:address":"5 Craiglee Drv",
    "sg:city":"Coromandel East",
    "sg:classifiers":[
        {
            "category":"Building & Trades",
            "subcategory":"Construction",
            "type":"Services"
        }
    ],
    "sg:phone":"+61 424 282 330",
    "sg:postcode":"5051",
    "sg:province":"SA",
    "sg:tags":[
        "home",
        "air conditioning"
    ],
    "wof:name":"MJ Air Servicing",
    "wof:placetype":"venue"
},
  "geometry": {"coordinates":[138.616928,-35.044758],"type":"Point"}
}