{
  "type": "Feature",
  "properties": {
    "iso:country":"AU",
    "sg:address":"PO Box 254",
    "sg:city":"Wahroonga",
    "sg:classifiers":[
        {
            "category":"Building & Trades",
            "subcategory":"Landscaping Services",
            "type":"Services"
        }
    ],
    "sg:phone":"+61 409 093 346",
    "sg:postcode":"2076",
    "sg:province":"NSW",
    "sg:tags":[
        "designer",
        "landscape",
        "contractor"
    ],
    "wof:name":"Design It Landscapes Pty Ltd",
    "wof:placetype":"venue"
},
  "geometry": {"coordinates":[151.117385864,-33.7187194824],"type":"Point"}
}