{
  "type": "Feature",
  "properties": {
    "iso:country":"AU",
    "sg:address":"10 Central Park Drv",
    "sg:city":"Mackay",
    "sg:classifiers":[
        {
            "category":"Retail",
            "subcategory":"Storage",
            "type":"Services"
        }
    ],
    "sg:phone":"+61 13 25 54",
    "sg:postcode":"4740",
    "sg:province":"QLD",
    "sg:tags":[
        "removal",
        "furniture"
    ],
    "wof:name":"Allied Pickfords",
    "wof:placetype":"venue"
},
  "geometry": {"coordinates":[149.166077,-21.174231],"type":"Point"}
}