{
  "type": "Feature",
  "properties": {
    "addr:full":"10 Jamieson St Cheltenham VIC 3192",
    "addr:housenumber":"10",
    "addr:postcode":"3192",
    "addr:street":"Jamieson St",
    "iso:country":"AU",
    "sg:address":"10 Jamieson St",
    "sg:city":"Cheltenham",
    "sg:classifiers":[
        {
            "category":"Health Services",
            "subcategory":"Doctor",
            "type":"Services"
        }
    ],
    "sg:phone":"+61 3 9584 9576",
    "sg:postcode":"3192",
    "sg:province":"VIC",
    "sg:tags":[
        "medical",
        "practitioner"
    ],
    "wof:name":"McLean Iain",
    "wof:placetype":"venue"
},
  "geometry": {"coordinates":[145.05567932100001,-37.9604759216],"type":"Point"}
}