{
  "type": "Feature",
  "properties": {
    "iso:country":"AU",
    "sg:address":"7a Sweeney St",
    "sg:city":"Inverell",
    "sg:classifiers":[
        {
            "category":"Autos & Motor Vehicles",
            "subcategory":"Auto Supplies",
            "type":"Retail Goods"
        }
    ],
    "sg:phone":"+61 2 6721 4843",
    "sg:postcode":"2360",
    "sg:province":"NSW",
    "sg:tags":[
        "part",
        "cycles",
        "accessory"
    ],
    "wof:name":"Donks Bikes & Bits",
    "wof:placetype":"venue"
},
  "geometry": {"coordinates":[151.11236572300001,-29.7721004486],"type":"Point"}
}