{
  "type": "Feature",
  "properties": {
    "addr:full":"20 McLeod St Condong NSW 2484",
    "addr:housenumber":"20",
    "addr:postcode":"2484",
    "addr:street":"Mcleod St",
    "iso:country":"AU",
    "sg:address":"20 McLeod St",
    "sg:city":"Condong",
    "sg:classifiers":[
        {
            "category":"Education",
            "subcategory":"Kindergarten",
            "type":"Public Place"
        }
    ],
    "sg:phone":"+61 2 6672 4744",
    "sg:postcode":"2484",
    "sg:province":"NSW",
    "sg:tags":[
        "pre-schools"
    ],
    "wof:name":"Possums Community Pre-School Asscn",
    "wof:placetype":"venue"
},
  "geometry": {"coordinates":[153.43487548799999,-28.3127250671],"type":"Point"}
}