{
  "type": "Feature",
  "properties": {
    "iso:country":"AU",
    "sg:address":"13 Gray Rd",
    "sg:city":"St Marys",
    "sg:classifiers":[
        {
            "category":"Education",
            "subcategory":"School",
            "type":"Public Place"
        }
    ],
    "sg:phone":"+61 3 6372 3900",
    "sg:postcode":"7215",
    "sg:province":"TAS",
    "sg:tags":[
        "state",
        "except",
        "nsw"
    ],
    "wof:name":"St Marys District High School",
    "wof:placetype":"venue"
},
  "geometry": {"coordinates":[148.18713399999999,-41.585014],"type":"Point"}
}