{
  "type": "Feature",
  "properties": {
    "addr:full":"558 Pacific Hwy Belmont NSW 2280",
    "addr:housenumber":"558",
    "addr:postcode":"2280",
    "addr:street":"Pacific Hwy",
    "iso:country":"AU",
    "sg:address":"558 Pacific Hwy",
    "sg:city":"Belmont",
    "sg:classifiers":[
        {
            "category":"Real Estate",
            "subcategory":"Real Estate Agent",
            "type":"Services"
        }
    ],
    "sg:phone":"+61 2 4945 2121",
    "sg:postcode":"2280",
    "sg:province":"NSW",
    "wof:name":"Global Property International",
    "wof:placetype":"venue"
},
  "geometry": {"coordinates":[151.661254883,-33.0346450806],"type":"Point"}
}