{
  "type": "Feature",
  "properties": {
    "iso:country":"AU",
    "sg:address":"6a Thesiger Crt",
    "sg:city":"Deakin",
    "sg:classifiers":[
        {
            "category":"Professional",
            "subcategory":"Management & Consulting",
            "type":"Services"
        }
    ],
    "sg:phone":"+61 2 6282 7288",
    "sg:postcode":"2600",
    "sg:province":"ACT",
    "sg:tags":[
        "consultant"
    ],
    "wof:name":"IMCG Pty Ltd",
    "wof:placetype":"venue"
},
  "geometry": {"coordinates":[149.094436645,-35.3170623779],"type":"Point"}
}