{
  "type": "Feature",
  "properties": {
    "iso:country":"AU",
    "sg:address":"7 Suntop Plaza Sunshine Beach Rd",
    "sg:city":"Noosa Heads",
    "sg:classifiers":[
        {
            "category":"Sports & Exercise",
            "subcategory":"Gym",
            "type":"Entertainment"
        }
    ],
    "sg:phone":"+61 7 5447 3312",
    "sg:postcode":"4567",
    "sg:province":"QLD",
    "sg:tags":[
        "pilate",
        "method"
    ],
    "wof:name":"Pilates Studio The",
    "wof:placetype":"venue"
},
  "geometry": {"coordinates":[153.09002685600001,-26.3967170715],"type":"Point"}
}