{
  "type": "Feature",
  "properties": {
    "iso:country":"AU",
    "sg:address":"261 Grange Rd",
    "sg:city":"Findon",
    "sg:classifiers":[
        {
            "category":"Travel",
            "subcategory":"Hotels & Motels",
            "type":"Entertainment"
        }
    ],
    "sg:phone":"+61 8 8445 7909",
    "sg:postcode":"5023",
    "sg:province":"SA",
    "sg:tags":[
        "pub"
    ],
    "wof:name":"Topaz Bar & Restaurant",
    "wof:placetype":"venue"
},
  "geometry": {"coordinates":[138.53573608400001,-34.9051818848],"type":"Point"}
}