{
  "type": "Feature",
  "properties": {
    "iso:country":"AU",
    "sg:address":"73 Camooweal St",
    "sg:city":"Mt Isa",
    "sg:classifiers":[
        {
            "category":"Health Services",
            "subcategory":"Doctor",
            "type":"Services"
        }
    ],
    "sg:phone":"+61 407 495 300",
    "sg:postcode":"4825",
    "sg:province":"QLD",
    "sg:tags":[
        "medical",
        "practitioner"
    ],
    "wof:name":"Kemp Nick Dr",
    "wof:placetype":"venue"
},
  "geometry": {"coordinates":[139.492645,-20.727741],"type":"Point"}
}