{
  "type": "Feature",
  "properties": {
    "addr:full":"122 Old South Rd Bowral NSW 2576",
    "addr:housenumber":"122",
    "addr:postcode":"2576",
    "addr:street":"Old South Rd",
    "iso:country":"AU",
    "sg:address":"122 Old South Rd",
    "sg:city":"Bowral",
    "sg:classifiers":[
        {
            "category":"Retail",
            "subcategory":"Repair Shop",
            "type":"Services"
        }
    ],
    "sg:phone":"+61 2 4861 4633",
    "sg:postcode":"2576",
    "sg:province":"NSW",
    "sg:tags":[
        "leadlights"
    ],
    "wof:name":"Independent Stained Glass",
    "wof:placetype":"venue"
},
  "geometry": {"coordinates":[150.43997192399999,-34.487411499],"type":"Point"}
}