{
  "type": "Feature",
  "properties": {
    "iso:country":"AU",
    "sg:address":"12 Lytham Crt",
    "sg:city":"Mudjimba",
    "sg:classifiers":[
        {
            "category":"Banks & Credit Unions",
            "subcategory":"Financial Services",
            "type":"Services"
        }
    ],
    "sg:phone":"+61 7 5450 6566",
    "sg:postcode":"4564",
    "sg:province":"QLD",
    "sg:tags":[
        "loan",
        "finance",
        "mortgage"
    ],
    "wof:name":"Home Loan Connexion",
    "wof:placetype":"venue"
},
  "geometry": {"coordinates":[153.082122803,-26.6287536621],"type":"Point"}
}