{
  "type": "Feature",
  "properties": {
    "addr:full":"Cnr Fitzgibbon & Robertson Sts Toowoomba QLD 4350",
    "addr:postcode":"4350",
    "addr:street":"Cnr",
    "iso:country":"AU",
    "sg:address":"Cnr Fitzgibbon & Robertson Sts",
    "sg:city":"Toowoomba",
    "sg:classifiers":[
        {
            "category":"Wholesale",
            "subcategory":"Apparel",
            "type":"Manufacturing & Wholesale Goods"
        }
    ],
    "sg:phone":"+61 7 4639 4545",
    "sg:postcode":"4350",
    "sg:province":"QLD",
    "sg:tags":[
        "wholesaler",
        "mfrs",
        "glove"
    ],
    "wof:name":"Brady Industries Pty Ltd",
    "wof:placetype":"venue"
},
  "geometry": {"coordinates":[151.94906599999999,-27.569073],"type":"Point"}
}