{
  "type": "Feature",
  "properties": {
    "addr:full":"166 Murray St Perth WA 6000",
    "addr:housenumber":"166",
    "addr:postcode":"6000",
    "addr:street":"Murray St",
    "iso:country":"AU",
    "sg:address":"166 Murray St",
    "sg:city":"Perth",
    "sg:classifiers":[
        {
            "category":"Personal",
            "subcategory":"Beauty Salon",
            "type":"Services"
        }
    ],
    "sg:phone":"+61 8 9221 7522",
    "sg:postcode":"6000",
    "sg:province":"WA",
    "wof:name":"Treat Day Spa Perth",
    "wof:placetype":"venue"
},
  "geometry": {"coordinates":[115.85859680199999,-31.9526691437],"type":"Point"}
}