{
  "type": "Feature",
  "properties": {
    "addr:full":"Shed 1, 14 Swallow Rd South Grafton NSW 2460",
    "addr:housenumber":"14",
    "addr:postcode":"2460",
    "addr:street":"Swallow Rd",
    "iso:country":"AU",
    "sg:address":"Shed 1, 14 Swallow Rd",
    "sg:city":"South Grafton",
    "sg:classifiers":[
        {
            "category":"Freight",
            "type":"Transportation"
        }
    ],
    "sg:phone":"+61 2 6642 3670",
    "sg:postcode":"2460",
    "sg:province":"NSW",
    "sg:tags":[
        "light",
        "carrier"
    ],
    "wof:name":"Hills Transport",
    "wof:placetype":"venue"
},
  "geometry": {"coordinates":[152.94708251899999,-29.7207164764],"type":"Point"}
}