{
  "type": "Feature",
  "properties": {
    "addr:full":"90 Como Rd Leopold VIC 3224",
    "addr:housenumber":"90",
    "addr:postcode":"3224",
    "addr:street":"Como Rd",
    "iso:country":"AU",
    "sg:address":"90 Como Rd",
    "sg:city":"Leopold",
    "sg:classifiers":[
        {
            "category":"Military Area",
            "subcategory":"Army Base",
            "type":"Public Place"
        }
    ],
    "sg:phone":"+61 3 5250 2169",
    "sg:postcode":"3224",
    "sg:province":"VIC",
    "sg:tags":[
        "concrete",
        "slab",
        "floor"
    ],
    "wof:name":"Ciuffetelli Pty Ltd",
    "wof:placetype":"venue"
},
  "geometry": {"coordinates":[144.456177,-38.205399],"type":"Point"}
}