{
  "type": "Feature",
  "properties": {
    "iso:country":"AU",
    "sg:address":"24 Outram St",
    "sg:city":"West Perth",
    "sg:classifiers":[
        {
            "category":"Banks & Credit Unions",
            "subcategory":"Financial Services",
            "type":"Services"
        }
    ],
    "sg:phone":"+61 1300 721 128",
    "sg:postcode":"6005",
    "sg:province":"WA",
    "sg:tags":[
        "planning"
    ],
    "wof:name":"Accord Financial Planners",
    "wof:placetype":"venue"
},
  "geometry": {"coordinates":[115.838813782,-31.950176239],"type":"Point"}
}