{
  "type": "Feature",
  "properties": {
    "addr:full":"Cnr Lords Road & Flood St Leichhardt NSW 2040",
    "addr:postcode":"2040",
    "addr:street":"Cnr Lords Road;St",
    "iso:country":"AU",
    "sg:address":"Cnr Lords Road & Flood St",
    "sg:city":"Leichhardt",
    "sg:classifiers":[
        {
            "category":"Arena",
            "subcategory":"Sports Club",
            "type":"Entertainment"
        }
    ],
    "sg:phone":"+61 2 9568 4623",
    "sg:postcode":"2040",
    "sg:province":"NSW",
    "sg:tags":[
        "defence",
        "supply",
        "self",
        "instruction",
        "martial art"
    ],
    "sg:website":"http://www.jowgar.com.au",
    "wof:name":"Head Academy Jow Ga Kung Fu",
    "wof:placetype":"venue"
},
  "geometry": {"coordinates":[151.14913899999999,-33.885796],"type":"Point"}
}