{
  "type": "Feature",
  "properties": {
    "addr:full":"102 Station Rd Seven Hills NSW 2147",
    "addr:housenumber":"102",
    "addr:postcode":"2147",
    "addr:street":"Station Rd",
    "iso:country":"AU",
    "sg:address":"102 Station Rd",
    "sg:city":"Seven Hills",
    "sg:classifiers":[
        {
            "category":"Utilities",
            "subcategory":"Refuse",
            "type":"Services"
        }
    ],
    "sg:phone":"+61 414 415 035",
    "sg:postcode":"2147",
    "sg:province":"NSW",
    "sg:tags":[
        "remover",
        "rubbish"
    ],
    "wof:name":"Peakeys Skip Bins",
    "wof:placetype":"venue"
},
  "geometry": {"coordinates":[150.94453430199999,-33.7750167847],"type":"Point"}
}