{
  "type": "Feature",
  "properties": {
    "addr:full":"137 Bathurst St Brewarrina NSW 2839",
    "addr:housenumber":"137",
    "addr:postcode":"2839",
    "addr:street":"Bathurst St",
    "iso:country":"AU",
    "sg:address":"137 Bathurst St",
    "sg:city":"Brewarrina",
    "sg:classifiers":[
        {
            "category":"Shopping",
            "type":"Retail Goods"
        }
    ],
    "sg:phone":"+61 2 6839 2003",
    "sg:postcode":"2839",
    "sg:province":"NSW",
    "sg:tags":[
        "agent",
        "stock"
    ],
    "wof:name":"Elders Limited",
    "wof:placetype":"venue"
},
  "geometry": {"coordinates":[146.86424299999999,-29.963911],"type":"Point"}
}