{
  "type": "Feature",
  "properties": {
    "addr:full":"14 Main St Minlaton SA 5575",
    "addr:housenumber":"14",
    "addr:postcode":"5575",
    "addr:street":"Main St",
    "iso:country":"AU",
    "sg:address":"14 Main St",
    "sg:city":"Minlaton",
    "sg:classifiers":[
        {
            "category":"Food & Beverages",
            "subcategory":"Supermarket",
            "type":"Retail Goods"
        }
    ],
    "sg:phone":"+61 8 8853 2306",
    "sg:postcode":"5575",
    "sg:province":"SA",
    "sg:tags":[
        "grocery",
        "store"
    ],
    "wof:name":"IGA Everyday",
    "wof:placetype":"venue"
},
  "geometry": {"coordinates":[137.59608459500001,-34.7705802917],"type":"Point"}
}