{
  "type": "Feature",
  "properties": {
    "addr:full":"8 Collingwood St Albion QLD 4010",
    "addr:housenumber":"8",
    "addr:postcode":"4010",
    "addr:street":"Collingwood St",
    "iso:country":"AU",
    "sg:address":"8 Collingwood St",
    "sg:city":"Albion",
    "sg:classifiers":[
        {
            "category":"Autos & Motor Vehicles",
            "subcategory":"Automobile Sales",
            "type":"Retail Goods"
        }
    ],
    "sg:phone":"+61 7 3862 1015",
    "sg:postcode":"4010",
    "sg:province":"QLD",
    "sg:tags":[
        "car",
        "used"
    ],
    "wof:name":"ARC Wholesaler",
    "wof:placetype":"venue"
},
  "geometry": {"coordinates":[153.04348754899999,-27.4328708649],"type":"Point"}
}