{
  "type": "Feature",
  "properties": {
    "addr:full":"45 Garfield Rd Riverstone NSW 2765",
    "addr:housenumber":"45",
    "addr:postcode":"2765",
    "addr:street":"Garfield Rd",
    "iso:country":"AU",
    "sg:address":"45 Garfield Rd",
    "sg:city":"Riverstone",
    "sg:classifiers":[
        {
            "category":"Health Services",
            "subcategory":"Optometrist",
            "type":"Services"
        }
    ],
    "sg:phone":"+61 2 9627 1102",
    "sg:postcode":"2765",
    "sg:province":"NSW",
    "wof:name":"Everything In Sight",
    "wof:placetype":"venue"
},
  "geometry": {"coordinates":[150.863204956,-33.6783676147],"type":"Point"}
}