{
  "type": "Feature",
  "properties": {
    "iso:country":"AU",
    "sg:address":"28 Fishermans Rd",
    "sg:city":"Maroochydore",
    "sg:classifiers":[
        {
            "category":"Building & Trades",
            "subcategory":"Construction",
            "type":"Services"
        }
    ],
    "sg:phone":"+61 7 5443 3944",
    "sg:postcode":"4558",
    "sg:province":"QLD",
    "sg:tags":[
        "renovation",
        "alterations",
        "extension",
        "contractor"
    ],
    "wof:name":"Coastal Patios",
    "wof:placetype":"venue"
},
  "geometry": {"coordinates":[153.055252075,-26.654384613],"type":"Point"}
}