{
  "type": "Feature",
  "properties": {
    "addr:full":"2/ 64 Guthrie St Osborne Park WA 6017",
    "addr:housenumber":"/ 64",
    "addr:postcode":"6017",
    "addr:street":"Guthrie St",
    "iso:country":"AU",
    "sg:address":"2/ 64 Guthrie St",
    "sg:city":"Osborne Park",
    "sg:classifiers":[
        {
            "category":"Autos & Motor Vehicles",
            "subcategory":"Auto Supplies",
            "type":"Retail Goods"
        }
    ],
    "sg:phone":"+61 8 9242 8140",
    "sg:postcode":"6017",
    "sg:province":"WA",
    "sg:tags":[
        "wheel",
        "automotive",
        "rim"
    ],
    "sg:website":"http://www.alliancerimrepairs.com.au",
    "wof:name":"Alliance Rim Repairs",
    "wof:placetype":"venue"
},
  "geometry": {"coordinates":[115.81439209,-31.9048404694],"type":"Point"}
}