{
  "type": "Feature",
  "properties": {
    "iso:country":"AU",
    "sg:address":"U5/ 46 Allpass Pde",
    "sg:city":"Shorncliffe",
    "sg:classifiers":[
        {
            "category":"Wholesale",
            "subcategory":"Non-durable Goods",
            "type":"Manufacturing & Wholesale Goods"
        }
    ],
    "sg:phone":"+61 402 512 139",
    "sg:postcode":"4017",
    "sg:province":"QLD",
    "sg:tags":[
        "textile"
    ],
    "wof:name":"Exotic Lounge",
    "wof:placetype":"venue"
},
  "geometry": {"coordinates":[153.08514404300001,-27.3294754028],"type":"Point"}
}