{
  "type": "Feature",
  "properties": {
    "iso:country":"AU",
    "sg:address":"15 Church St",
    "sg:city":"Singleton",
    "sg:classifiers":[
        {
            "category":"Retail",
            "subcategory":"Repair Shop",
            "type":"Services"
        }
    ],
    "sg:phone":"+61 2 6572 2192",
    "sg:postcode":"2330",
    "sg:province":"NSW",
    "sg:tags":[
        "maintenance",
        "pool",
        "swimming"
    ],
    "wof:name":"MR & TB Heuston Pool Services",
    "wof:placetype":"venue"
},
  "geometry": {"coordinates":[151.171371,-32.570744],"type":"Point"}
}