{
  "type": "Feature",
  "properties": {
    "addr:full":"141 Dolphin St Coogee NSW 2034",
    "addr:housenumber":"141",
    "addr:postcode":"2034",
    "addr:street":"Dolphin St",
    "iso:country":"AU",
    "sg:address":"141 Dolphin St",
    "sg:city":"Coogee",
    "sg:classifiers":[
        {
            "category":"Deli",
            "type":"Food & Drink"
        }
    ],
    "sg:phone":"+61 2 9665 4403",
    "sg:postcode":"2034",
    "sg:province":"NSW",
    "sg:tags":[
        "delicatessen"
    ],
    "wof:name":"Deli On Dolphin",
    "wof:placetype":"venue"
},
  "geometry": {"coordinates":[151.25770568900001,-33.9188499451],"type":"Point"}
}