{
  "type": "Feature",
  "properties": {
    "addr:full":"Shop 4 Marine Pde Bellara Bribie Island QLD 4507",
    "addr:housenumber":"shop 4",
    "addr:postcode":"4507",
    "addr:street":"Marine Pde;Bribie",
    "iso:country":"AU",
    "sg:address":"Shop 4 Marine Pde Bellara",
    "sg:city":"Bribie Island",
    "sg:classifiers":[
        {
            "category":"Fast Food",
            "type":"Food & Drink"
        }
    ],
    "sg:phone":"+61 7 3408 8155",
    "sg:postcode":"4507",
    "sg:province":"QLD",
    "sg:tags":[
        "away",
        "take"
    ],
    "wof:name":"Sylvan Beach Fish Cafe",
    "wof:placetype":"venue"
},
  "geometry": {"coordinates":[153.14465332,-27.0647087097],"type":"Point"}
}