{
  "type": "Feature",
  "properties": {
    "addr:full":"Aerodrome Rd Gladstone QLD 4680",
    "addr:postcode":"4680",
    "addr:street":"Aerodrome Rd",
    "iso:country":"AU",
    "sg:address":"Aerodrome Rd",
    "sg:city":"Gladstone",
    "sg:classifiers":[
        {
            "category":"Cafe",
            "type":"Food & Drink"
        }
    ],
    "sg:phone":"+61 7 4978 3241",
    "sg:postcode":"4680",
    "sg:province":"QLD",
    "wof:name":"Cafe Espresso",
    "wof:placetype":"venue"
},
  "geometry": {"coordinates":[151.226104736,-23.8734359741],"type":"Point"}
}