{
  "type": "Feature",
  "properties": {
    "iso:country":"AU",
    "sg:address":"PO Box 154",
    "sg:city":"Ramsgate",
    "sg:classifiers":[
        {
            "category":"Building & Trades",
            "subcategory":"Plumbing",
            "type":"Services"
        }
    ],
    "sg:phone":"+61 2 9546 2004",
    "sg:postcode":"2217",
    "sg:province":"NSW",
    "sg:tags":[
        "plumber",
        "gasfitters"
    ],
    "wof:name":"Plumbing &#039;R&#039; Us Pty Ltd",
    "wof:placetype":"venue"
},
  "geometry": {"coordinates":[151.138077,-33.984421],"type":"Point"}
}