{
  "type": "Feature",
  "properties": {
    "iso:country":"AU",
    "sg:address":"194 Pacific Hwy",
    "sg:city":"St Leonards",
    "sg:classifiers":[
        {
            "category":"Retail",
            "subcategory":"Event Space",
            "type":"Services"
        }
    ],
    "sg:phone":"+61 2 9439 6000",
    "sg:postcode":"2065",
    "sg:province":"NSW",
    "sg:tags":[
        "venue",
        "reception",
        "wedding"
    ],
    "wof:name":"Bellevue Restaurant",
    "wof:placetype":"venue"
},
  "geometry": {"coordinates":[151.198974609,-33.8255691528],"type":"Point"}
}