{
  "type": "Feature",
  "properties": {
    "iso:country":"AU",
    "sg:address":"176 Katoomba St",
    "sg:city":"Katoomba",
    "sg:classifiers":[
        {
            "category":"Personal",
            "subcategory":"Beauty Salon",
            "type":"Services"
        }
    ],
    "sg:phone":"+61 2 4782 2042",
    "sg:postcode":"2780",
    "sg:province":"NSW",
    "sg:tags":[
        "hairdresser"
    ],
    "wof:name":"Kristine's His & Hers Hairdressing",
    "wof:placetype":"venue"
},
  "geometry": {"coordinates":[150.31149292000001,-33.7153511047],"type":"Point"}
}