{
  "type": "Feature",
  "properties": {
    "addr:full":"Terang Rd Ecklin VIC 3265",
    "addr:postcode":"3265",
    "addr:street":"Terang Rd",
    "iso:country":"AU",
    "sg:address":"Terang Rd",
    "sg:city":"Ecklin",
    "sg:classifiers":[
        {
            "category":"Farming",
            "subcategory":"Farm",
            "type":"Manufacturing & Wholesale Goods"
        }
    ],
    "sg:phone":"+61 3 5591 0240",
    "sg:postcode":"3265",
    "sg:province":"VIC",
    "sg:tags":[
        "farmer"
    ],
    "wof:name":"McKinnon Harry",
    "wof:placetype":"venue"
},
  "geometry": {"coordinates":[142.73173523,-38.2457084656],"type":"Point"}
}