{
  "type": "Feature",
  "properties": {
    "addr:full":"10 Coronation Pde Enfield NSW 2136",
    "addr:housenumber":"10",
    "addr:postcode":"2136",
    "addr:street":"Coronation Pde",
    "iso:country":"AU",
    "sg:address":"10 Coronation Pde",
    "sg:city":"Enfield",
    "sg:classifiers":[
        {
            "category":"Health Services",
            "subcategory":"Doctor",
            "type":"Services"
        }
    ],
    "sg:phone":"+61 2 9745 4448",
    "sg:postcode":"2136",
    "sg:province":"NSW",
    "sg:tags":[
        "medical",
        "practitioner"
    ],
    "wof:name":"Ho E",
    "wof:placetype":"venue"
},
  "geometry": {"coordinates":[151.091705322,-33.8880271912],"type":"Point"}
}