{
  "type": "Feature",
  "properties": {
    "addr:full":"89b Willoughby Rd Crows Nest NSW 2065",
    "addr:housenumber":"89b",
    "addr:postcode":"2065",
    "addr:street":"Willoughby Rd",
    "iso:country":"AU",
    "sg:address":"89b Willoughby Rd",
    "sg:city":"Crows Nest",
    "sg:classifiers":[
        {
            "category":"Shopping",
            "subcategory":"Clothing, Apparel, & Fashions",
            "type":"Retail Goods"
        }
    ],
    "sg:phone":"+61 2 9439 9345",
    "sg:postcode":"2065",
    "sg:province":"NSW",
    "sg:tags":[
        "lady",
        "wear"
    ],
    "wof:name":"Bagatelle De Paris",
    "wof:placetype":"venue"
},
  "geometry": {"coordinates":[151.20106506400001,-33.8242263794],"type":"Point"}
}