{
  "type": "Feature",
  "properties": {
    "iso:country":"AU",
    "sg:address":"279 Clarendon St",
    "sg:city":"South Melbourne",
    "sg:classifiers":[
        {
            "category":"Restaurant",
            "type":"Food & Drink"
        }
    ],
    "sg:phone":"+61 3 9699 4036",
    "sg:postcode":"3205",
    "sg:province":"VIC",
    "wof:name":"Blue Room Restaurant Bar Cafe",
    "wof:placetype":"venue"
},
  "geometry": {"coordinates":[144.96077,-37.833046],"type":"Point"}
}