{
  "type": "Feature",
  "properties": {
    "iso:country":"AU",
    "sg:address":"Level 1 / 68 Alfred St",
    "sg:city":"Milsons Point",
    "sg:classifiers":[
        {
            "category":"Professional",
            "subcategory":"Accounting & Tax Preparation",
            "type":"Services"
        }
    ],
    "sg:phone":"+61 2 9929 4177",
    "sg:postcode":"2061",
    "sg:province":"NSW",
    "sg:tags":[
        "consultant",
        "taxation"
    ],
    "wof:name":"Thomas Hopper & Partners",
    "wof:placetype":"venue"
},
  "geometry": {"coordinates":[151.21127319300001,-33.8465003967],"type":"Point"}
}