{
  "type": "Feature",
  "properties": {
    "addr:full":"28 Gordon St Mullumbimby NSW 2482",
    "addr:housenumber":"28",
    "addr:postcode":"2482",
    "addr:street":"Gordon St",
    "iso:country":"AU",
    "sg:address":"28 Gordon St",
    "sg:city":"Mullumbimby",
    "sg:classifiers":[
        {
            "category":"Home & Garden",
            "subcategory":"Hardware",
            "type":"Retail Goods"
        }
    ],
    "sg:phone":"+61 416 025 843",
    "sg:postcode":"2482",
    "sg:province":"NSW",
    "sg:tags":[
        "repair",
        "tool",
        "power"
    ],
    "wof:name":"Stokes Bay Elect Services",
    "wof:placetype":"venue"
},
  "geometry": {"coordinates":[153.498947144,-28.5511016846],"type":"Point"}
}