{
  "type": "Feature",
  "properties": {
    "addr:full":"256 Spring Flat Rd Wangoom VIC 3279",
    "addr:housenumber":"256",
    "addr:postcode":"3279",
    "addr:street":"Spring Flat Rd",
    "iso:country":"AU",
    "sg:address":"256 Spring Flat Rd",
    "sg:city":"Wangoom",
    "sg:classifiers":[
        {
            "category":"Commercial Area",
            "type":"Public Place"
        }
    ],
    "sg:phone":"+61 419 596 598",
    "sg:postcode":"3279",
    "sg:province":"VIC",
    "sg:tags":[
        "heavy",
        "carrier"
    ],
    "wof:name":"Buckley Bulk Transport",
    "wof:placetype":"venue"
},
  "geometry": {"coordinates":[142.53692626899999,-38.3288192749],"type":"Point"}
}