{
  "type": "Feature",
  "properties": {
    "iso:country":"AU",
    "sg:address":"Unit 3/ 62 Anderson Rd",
    "sg:city":"Hawthorn East",
    "sg:classifiers":[
        {
            "category":"Manufacturing",
            "subcategory":"Building Materials",
            "type":"Manufacturing & Wholesale Goods"
        }
    ],
    "sg:phone":"+61 3 9824 4071",
    "sg:postcode":"3123",
    "sg:province":"VIC",
    "sg:tags":[
        "equipment",
        "handling"
    ],
    "wof:name":"Enviro Kinetic Equipment",
    "wof:placetype":"venue"
},
  "geometry": {"coordinates":[145.05377197300001,-37.8417129517],"type":"Point"}
}