{
  "type": "Feature",
  "properties": {
    "iso:country":"AU",
    "sg:address":"Level 1, 102- 104 Longueville Rd",
    "sg:city":"Lane Cove",
    "sg:classifiers":[
        {
            "category":"Government",
            "subcategory":"Court House",
            "type":"Public Place"
        }
    ],
    "sg:phone":"+61 419 467 794",
    "sg:postcode":"2066",
    "sg:province":"NSW",
    "sg:tags":[
        "personal",
        "marriage",
        "family",
        "counselling"
    ],
    "wof:name":"Sue Gynther",
    "wof:placetype":"venue"
},
  "geometry": {"coordinates":[151.17007446299999,-33.8141059875],"type":"Point"}
}