{
  "type": "Feature",
  "properties": {
    "addr:full":"Uralla Rd Katherine NT 0850",
    "addr:postcode":"nt 0850",
    "addr:street":"Uralla Rd",
    "iso:country":"AU",
    "sg:address":"Uralla Rd",
    "sg:city":"Katherine",
    "sg:classifiers":[
        {
            "category":"Building & Trades",
            "subcategory":"Landscaping Services",
            "type":"Services"
        }
    ],
    "sg:phone":"+61 8 8972 1667",
    "sg:postcode":"0850",
    "sg:province":"NT",
    "sg:tags":[
        "stump",
        "tree",
        "felling",
        "removal"
    ],
    "wof:name":"Cav's Mowing & Treelopping Service Pty Ltd",
    "wof:placetype":"venue"
},
  "geometry": {"coordinates":[132.29603599999999,-14.489296],"type":"Point"}
}