{
  "type": "Feature",
  "properties": {
    "addr:full":"8 Dennis Rd Springwood QLD 4127",
    "addr:housenumber":"8",
    "addr:postcode":"4127",
    "addr:street":"Dennis Rd",
    "iso:country":"AU",
    "sg:address":"8 Dennis Rd",
    "sg:city":"Springwood",
    "sg:classifiers":[
        {
            "category":"Health Services",
            "subcategory":"Doctor",
            "type":"Services"
        }
    ],
    "sg:phone":"+61 7 3290 2922",
    "sg:postcode":"4127",
    "sg:province":"QLD",
    "sg:tags":[
        "medical",
        "practitioner"
    ],
    "wof:name":"Prowacki Steve",
    "wof:placetype":"venue"
},
  "geometry": {"coordinates":[153.127716064,-27.621301651],"type":"Point"}
}