{
  "type": "Feature",
  "properties": {
    "addr:full":"77 Howard Rd Sarsfield VIC 3875",
    "addr:housenumber":"77",
    "addr:postcode":"3875",
    "addr:street":"Howard Rd",
    "iso:country":"AU",
    "sg:address":"77 Howard Rd",
    "sg:city":"Sarsfield",
    "sg:classifiers":[
        {
            "category":"Professional",
            "subcategory":"Business Services",
            "type":"Services"
        }
    ],
    "sg:phone":"+61 3 5157 5586",
    "sg:postcode":"3875",
    "sg:province":"VIC",
    "sg:tags":[
        "drafting"
    ],
    "wof:name":"Bairnsdale Drafting Services",
    "wof:placetype":"venue"
},
  "geometry": {"coordinates":[147.61129760700001,-37.8314208984],"type":"Point"}
}