{
  "type": "Feature",
  "properties": {
    "addr:full":"60 Ricketts Rd Mt Waverley VIC 3149",
    "addr:housenumber":"60",
    "addr:postcode":"3149",
    "addr:street":"Ricketts Rd",
    "iso:country":"AU",
    "sg:address":"60 Ricketts Rd",
    "sg:city":"Mt Waverley",
    "sg:classifiers":[
        {
            "category":"Retail",
            "subcategory":"Auto Repair",
            "type":"Services"
        }
    ],
    "sg:phone":"+61 3 9540 0400",
    "sg:postcode":"3149",
    "sg:province":"VIC",
    "sg:tags":[
        "repairer",
        "motor",
        "engineer"
    ],
    "wof:name":"Ricketts Auto Centre",
    "wof:placetype":"venue"
},
  "geometry": {"coordinates":[145.132720947,-37.8947257996],"type":"Point"}
}