{
  "type": "Feature",
  "properties": {
    "addr:full":"31 Summerhayes Drv Karrinyup WA 6018",
    "addr:housenumber":"31",
    "addr:postcode":"6018",
    "addr:street":"Summerhayes Drv",
    "iso:country":"AU",
    "sg:address":"31 Summerhayes Drv",
    "sg:city":"Karrinyup",
    "sg:classifiers":[
        {
            "category":"Building & Trades",
            "subcategory":"Construction",
            "type":"Services"
        }
    ],
    "sg:phone":"+61 8 9448 9948",
    "sg:postcode":"6018",
    "sg:province":"WA",
    "sg:tags":[
        "contractor"
    ],
    "wof:name":"Daniel Ross S & D A",
    "wof:placetype":"venue"
},
  "geometry": {"coordinates":[115.782997131,-31.8676948547],"type":"Point"}
}