{
  "type": "Feature",
  "properties": {
    "iso:country":"AU",
    "sg:address":"PO Box 152",
    "sg:city":"Burwood",
    "sg:classifiers":[
        {
            "category":"Shopping",
            "type":"Retail Goods"
        }
    ],
    "sg:phone":"+61 3 9889 8166",
    "sg:postcode":"3125",
    "sg:province":"VIC",
    "sg:tags":[
        "equipment",
        "safety",
        "accessory"
    ],
    "wof:name":"Aearo Company",
    "wof:placetype":"venue"
},
  "geometry": {"coordinates":[145.11361694300001,-37.8485298157],"type":"Point"}
}