{
  "type": "Feature",
  "properties": {
    "addr:full":"PO Box 772 Smithfield (Cairns) QLD 4878",
    "addr:postcode":"4878",
    "iso:country":"AU",
    "sg:address":"PO Box 772",
    "sg:city":"Smithfield (Cairns)",
    "sg:classifiers":[
        {
            "category":"Building & Trades",
            "subcategory":"Construction",
            "type":"Services"
        }
    ],
    "sg:phone":"+61 408 982 830",
    "sg:postcode":"4878",
    "sg:province":"QLD",
    "sg:tags":[
        "concrete",
        "contractor"
    ],
    "wof:name":"David Henneker",
    "wof:placetype":"venue"
},
  "geometry": {"coordinates":[145.68907165499999,-16.83852005],"type":"Point"}
}