{
  "type": "Feature",
  "properties": {
    "addr:full":"47- 51 Little Boundary Rd Laverton North VIC 3026",
    "addr:housenumber":"51",
    "addr:postcode":"3026",
    "addr:street":"Little Boundary Rd",
    "iso:country":"AU",
    "sg:address":"47- 51 Little Boundary Rd",
    "sg:city":"Laverton North",
    "sg:classifiers":[
        {
            "category":"Real Estate",
            "subcategory":"Real Estate Agent",
            "type":"Services"
        }
    ],
    "sg:phone":"+61 3 8325 6888",
    "sg:postcode":"3026",
    "sg:province":"VIC",
    "wof:name":"Colliers International",
    "wof:placetype":"venue"
},
  "geometry": {"coordinates":[144.816956,-37.816681],"type":"Point"}
}