{
  "type": "Feature",
  "properties": {
    "iso:country":"AU",
    "sg:address":"Lvl 1/ 457 Malvern Rd",
    "sg:city":"South Yarra",
    "sg:classifiers":[
        {
            "category":"Professional",
            "subcategory":"Employment Agencies",
            "type":"Services"
        }
    ],
    "sg:phone":"+61 3 9827 6804",
    "sg:postcode":"3141",
    "sg:province":"VIC",
    "sg:tags":[
        "consultant",
        "casting"
    ],
    "wof:name":"LMC",
    "wof:placetype":"venue"
},
  "geometry": {"coordinates":[145.00163269000001,-37.8477401733],"type":"Point"}
}