{
  "type": "Feature",
  "properties": {
    "addr:full":"Palmerston Hwy Pin Gin Hill QLD 4860",
    "addr:postcode":"4860",
    "addr:street":"Palmerston Hwy Pin Gin",
    "iso:country":"AU",
    "sg:address":"Palmerston Hwy",
    "sg:city":"Pin Gin Hill",
    "sg:classifiers":[
        {
            "category":"Farming",
            "subcategory":"Farm",
            "type":"Manufacturing & Wholesale Goods"
        }
    ],
    "sg:phone":"+61 7 4064 4188",
    "sg:postcode":"4860",
    "sg:province":"QLD",
    "sg:tags":[
        "farmer"
    ],
    "wof:name":"Bertei R",
    "wof:placetype":"venue"
},
  "geometry": {"coordinates":[145.95062255900001,-17.5643386841],"type":"Point"}
}