{
  "type": "Feature",
  "properties": {
    "addr:full":"79 Main Rd McLaren Vale SA 5171",
    "addr:housenumber":"79",
    "addr:postcode":"5171",
    "addr:street":"Main Rd",
    "iso:country":"AU",
    "sg:address":"79 Main Rd",
    "sg:city":"McLaren Vale",
    "sg:classifiers":[
        {
            "category":"Health Services",
            "subcategory":"Health Practitioner",
            "type":"Services"
        }
    ],
    "sg:phone":"+61 8 8323 9990",
    "sg:postcode":"5171",
    "sg:province":"SA",
    "sg:tags":[
        "homoeopath"
    ],
    "wof:name":"Julie Walker",
    "wof:placetype":"venue"
},
  "geometry": {"coordinates":[138.53689575199999,-35.2148017883],"type":"Point"}
}