{
  "type": "Feature",
  "properties": {
    "iso:country":"AU",
    "sg:address":"32-38 Network Drv",
    "sg:city":"Port Melbourne",
    "sg:classifiers":[
        {
            "category":"Manufacturing",
            "subcategory":"Metals",
            "type":"Manufacturing & Wholesale Goods"
        }
    ],
    "sg:phone":"+61 3 8671 2300",
    "sg:postcode":"3207",
    "sg:province":"VIC",
    "sg:tags":[
        "cutting"
    ],
    "wof:name":"Aerostaff Australia Pty Ltd",
    "wof:placetype":"venue"
},
  "geometry": {"coordinates":[144.902481,-37.829983],"type":"Point"}
}