{
  "type": "Feature",
  "properties": {
    "iso:country":"AU",
    "sg:address":"Cnr Gordon & Meenan Sts",
    "sg:city":"Garbutt",
    "sg:classifiers":[
        {
            "category":"Building & Trades",
            "subcategory":"Locksmith",
            "type":"Services"
        }
    ],
    "sg:phone":"+61 7 4779 3122",
    "sg:postcode":"4814",
    "sg:province":"QLD",
    "sg:tags":[
        "lock"
    ],
    "wof:name":"Grimseys Hardware",
    "wof:placetype":"venue"
},
  "geometry": {"coordinates":[146.76686100000001,-19.292395],"type":"Point"}
}