{
  "type": "Feature",
  "properties": {
    "iso:country":"AU",
    "sg:address":"45 Anthony Drv",
    "sg:city":"Rosemeadow",
    "sg:classifiers":[
        {
            "category":"Professional",
            "subcategory":"Art Services",
            "type":"Services"
        }
    ],
    "sg:phone":"+61 2 4621 1280",
    "sg:postcode":"2560",
    "sg:province":"NSW",
    "sg:tags":[
        "graphic",
        "designer"
    ],
    "wof:name":"Graphicom",
    "wof:placetype":"venue"
},
  "geometry": {"coordinates":[150.79261779800001,-34.1028556824],"type":"Point"}
}