{
  "type": "Feature",
  "properties": {
    "addr:full":"23 Chamberlain St Campbelltown NSW 2560",
    "addr:housenumber":"23",
    "addr:postcode":"2560",
    "addr:street":"Chamberlain St",
    "iso:country":"AU",
    "sg:address":"23 Chamberlain St",
    "sg:city":"Campbelltown",
    "sg:classifiers":[
        {
            "category":"Health Services",
            "subcategory":"Doctor",
            "type":"Services"
        }
    ],
    "sg:phone":"+61 2 4626 8317",
    "sg:postcode":"2560",
    "sg:province":"NSW",
    "sg:tags":[
        "medical",
        "practitioner"
    ],
    "wof:name":"Chen Dr Joycelyn",
    "wof:placetype":"venue"
},
  "geometry": {"coordinates":[150.82164001500001,-34.0620498657],"type":"Point"}
}