{
  "type": "Feature",
  "properties": {
    "addr:full":"End Of Suakin Drv Mosman NSW 2088",
    "addr:postcode":"2088",
    "addr:street":"Drv",
    "iso:country":"AU",
    "sg:address":"End Of Suakin Drv",
    "sg:city":"Mosman",
    "sg:classifiers":[
        {
            "category":"Retail",
            "subcategory":"Event Space",
            "type":"Services"
        }
    ],
    "sg:phone":"+61 2 8962 5900",
    "sg:postcode":"2088",
    "sg:province":"NSW",
    "sg:tags":[
        "venue",
        "reception",
        "wedding"
    ],
    "wof:name":"The Tea Room Gunners Barracks",
    "wof:placetype":"venue"
},
  "geometry": {"coordinates":[151.25454711899999,-33.8343009949],"type":"Point"}
}