{
  "type": "Feature",
  "properties": {
    "addr:full":"13 Helles Ave Moorebank NSW 2170",
    "addr:housenumber":"13",
    "addr:postcode":"2170",
    "addr:street":"Helles Ave",
    "iso:country":"AU",
    "sg:address":"13 Helles Ave",
    "sg:city":"Moorebank",
    "sg:classifiers":[
        {
            "category":"Manufacturing",
            "subcategory":"Motor Vehicles & Parts",
            "type":"Manufacturing & Wholesale Goods"
        }
    ],
    "sg:phone":"+61 2 9601 6655",
    "sg:postcode":"2170",
    "sg:province":"NSW",
    "sg:tags":[
        "replacement"
    ],
    "wof:name":"Astra Motor Wreckers",
    "wof:placetype":"venue"
},
  "geometry": {"coordinates":[150.922897339,-33.9370384216],"type":"Point"}
}