{
  "type": "Feature",
  "properties": {
    "addr:full":"384 Adelaide Park Rd Yeppoon QLD 4703",
    "addr:housenumber":"384",
    "addr:postcode":"4703",
    "addr:street":"Adelaide Park Rd",
    "iso:country":"AU",
    "sg:address":"384 Adelaide Park Rd",
    "sg:city":"Yeppoon",
    "sg:classifiers":[
        {
            "category":"Building & Trades",
            "subcategory":"Cleaning & Sanitation",
            "type":"Services"
        }
    ],
    "sg:phone":"+61 7 4939 3215",
    "sg:postcode":"4703",
    "sg:province":"QLD",
    "sg:tags":[
        "industrial",
        "commercial",
        "contractor"
    ],
    "wof:name":"Campbell's Cleaning Services",
    "wof:placetype":"venue"
},
  "geometry": {"coordinates":[150.721755981,-23.1060142517],"type":"Point"}
}