{
  "type": "Feature",
  "properties": {
    "addr:full":"Unit 2/ 49 Raws Crs Hume ACT 2620",
    "addr:housenumber":"49",
    "addr:postcode":"2620",
    "addr:street":"Raws Crs",
    "iso:country":"AU",
    "sg:address":"Unit 2/ 49 Raws Crs",
    "sg:city":"Hume",
    "sg:classifiers":[
        {
            "category":"Manufacturing",
            "subcategory":"Tools & Machinery",
            "type":"Manufacturing & Wholesale Goods"
        }
    ],
    "sg:phone":"+61 2 6280 4182",
    "sg:postcode":"2620",
    "sg:province":"ACT",
    "sg:tags":[
        "earth",
        "excavating",
        "moving",
        "equipment"
    ],
    "wof:name":"Gough & Gilmore Holdings Pty Ltd",
    "wof:placetype":"venue"
},
  "geometry": {"coordinates":[149.162307739,-35.3929290771],"type":"Point"}
}