{
  "type": "Feature",
  "properties": {
    "addr:full":"Unit 9/ 10 Hudson Ave Castle Hill NSW 2154",
    "addr:postcode":"2154",
    "addr:street":"Hudson Ave",
    "iso:country":"AU",
    "sg:address":"Unit 9/ 10 Hudson Ave",
    "sg:city":"Castle Hill",
    "sg:classifiers":[
        {
            "category":"Recreation",
            "type":"Entertainment"
        }
    ],
    "sg:phone":"+61 2 9899 8228",
    "sg:postcode":"2154",
    "sg:province":"NSW",
    "sg:tags":[
        "supply",
        "outdoor",
        "adventure",
        "activity"
    ],
    "wof:name":"Edge Adventure Centre The",
    "wof:placetype":"venue"
},
  "geometry": {"coordinates":[150.97450256400001,-33.7294998169],"type":"Point"}
}