{
  "type": "Feature",
  "properties": {
    "addr:full":"109 Lindesay St Campbelltown NSW 2560",
    "addr:housenumber":"109",
    "addr:postcode":"2560",
    "addr:street":"Lindesay St",
    "iso:country":"AU",
    "sg:address":"109 Lindesay St",
    "sg:city":"Campbelltown",
    "sg:classifiers":[
        {
            "category":"Building & Trades",
            "subcategory":"Plumbing",
            "type":"Services"
        }
    ],
    "sg:phone":"+61 412 248 631",
    "sg:postcode":"2560",
    "sg:province":"NSW",
    "sg:tags":[
        "plumber",
        "gasfitters"
    ],
    "wof:name":"O'Flaherty Plumbing Services",
    "wof:placetype":"venue"
},
  "geometry": {"coordinates":[150.82533264200001,-34.0653381348],"type":"Point"}
}