{
  "type": "Feature",
  "properties": {
    "iso:country":"AU",
    "sg:address":"Unit 3/ 82 King Rd",
    "sg:city":"Bunbury",
    "sg:classifiers":[
        {
            "category":"Autos & Motor Vehicles",
            "subcategory":"Auto Supplies",
            "type":"Retail Goods"
        }
    ],
    "sg:phone":"+61 8 9791 9422",
    "sg:postcode":"6230",
    "sg:province":"WA",
    "sg:tags":[
        "part",
        "cycles",
        "accessory"
    ],
    "wof:name":"King Road Motorcycles",
    "wof:placetype":"venue"
},
  "geometry": {"coordinates":[115.65435,-33.3382],"type":"Point"}
}