{
  "type": "Feature",
  "properties": {
    "addr:full":"PO Box 267 Maroochydore QLD 4558",
    "addr:postcode":"4558",
    "iso:country":"AU",
    "sg:address":"PO Box 267",
    "sg:city":"Maroochydore",
    "sg:classifiers":[
        {
            "category":"Social Services",
            "subcategory":"Retirement Home",
            "type":"Services"
        }
    ],
    "sg:phone":"+61 1800 867 368",
    "sg:postcode":"4558",
    "sg:province":"QLD",
    "sg:tags":[
        "village"
    ],
    "wof:name":"SunnyCove Head Office",
    "wof:placetype":"venue"
},
  "geometry": {"coordinates":[153.06553649899999,-26.6553192139],"type":"Point"}
}