{
  "type": "Feature",
  "properties": {
    "addr:full":"Civic Centre Cnr Baylis & Morrow Sts Wagga Wagga NSW 2650",
    "addr:postcode":"2650",
    "addr:street":"Cnr",
    "iso:country":"AU",
    "sg:address":"Civic Centre Cnr Baylis & Morrow Sts",
    "sg:city":"Wagga Wagga",
    "sg:classifiers":[
        {
            "category":"Arts & Performance",
            "subcategory":"Art Gallery",
            "type":"Entertainment"
        }
    ],
    "sg:phone":"+61 2 6926 9660",
    "sg:postcode":"2650",
    "sg:province":"NSW",
    "wof:name":"Wagga Wagga Art Gallery",
    "wof:placetype":"venue"
},
  "geometry": {"coordinates":[147.36907959000001,-35.1174583435],"type":"Point"}
}