{
  "type": "Feature",
  "properties": {
    "addr:full":"Fcty3/ 252 Lower Dandenong Rd Mordialloc VIC 3195",
    "addr:housenumber":"252",
    "addr:postcode":"3195",
    "addr:street":"Lower Dandenong Rd",
    "iso:country":"AU",
    "sg:address":"Fcty3/ 252 Lower Dandenong Rd",
    "sg:city":"Mordialloc",
    "sg:classifiers":[
        {
            "category":"Retail",
            "subcategory":"Auto Repair",
            "type":"Services"
        }
    ],
    "sg:phone":"+61 3 9587 4192",
    "sg:postcode":"3195",
    "sg:province":"VIC",
    "sg:tags":[
        "repairer",
        "motor",
        "engineer"
    ],
    "wof:name":"T D Tyres & Automotive",
    "wof:placetype":"venue"
},
  "geometry": {"coordinates":[145.08534240700001,-38.0056800842],"type":"Point"}
}