{
  "type": "Feature",
  "properties": {
    "addr:full":"2/ 77 Scott St Bungalow QLD 4870",
    "addr:housenumber":"/ 77",
    "addr:postcode":"4870",
    "addr:street":"Scott St",
    "iso:country":"AU",
    "sg:address":"2/ 77 Scott St",
    "sg:city":"Bungalow",
    "sg:classifiers":[
        {
            "category":"Industrial Area",
            "type":"Public Place"
        }
    ],
    "sg:phone":"+61 7 4031 1317",
    "sg:postcode":"4870",
    "sg:province":"QLD",
    "sg:tags":[
        "protective",
        "clothing"
    ],
    "sg:website":"http://www.australasiansafety.com.au",
    "wof:name":"Australasian Safety Co. Pty Ltd",
    "wof:placetype":"venue"
},
  "geometry": {"coordinates":[145.76252746599999,-16.932264328],"type":"Point"}
}