{
  "type": "Feature",
  "properties": {
    "addr:full":"192b Mona Vale Rd St Ives NSW 2075",
    "addr:housenumber":"192b",
    "addr:postcode":"2075",
    "addr:street":"Mona Vale Rd",
    "iso:country":"AU",
    "sg:address":"192b Mona Vale Rd",
    "sg:city":"St Ives",
    "sg:classifiers":[
        {
            "category":"Health Services",
            "subcategory":"Optometrist",
            "type":"Services"
        }
    ],
    "sg:phone":"+61 2 9144 5515",
    "sg:postcode":"2075",
    "sg:province":"NSW",
    "wof:name":"Amanda Macknight",
    "wof:placetype":"venue"
},
  "geometry": {"coordinates":[151.16041564899999,-33.7301712036],"type":"Point"}
}