{
  "type": "Feature",
  "properties": {
    "addr:full":"Suite 4, 97- 103 Anzac Pde Kensington NSW 2033",
    "addr:housenumber":"97 103",
    "addr:postcode":"2033",
    "addr:street":"Anzac Pde",
    "iso:country":"AU",
    "sg:address":"Suite 4, 97- 103 Anzac Pde",
    "sg:city":"Kensington",
    "sg:classifiers":[
        {
            "category":"Manufacturing",
            "subcategory":"Food",
            "type":"Manufacturing & Wholesale Goods"
        }
    ],
    "sg:phone":"+61 2 9663 4840",
    "sg:postcode":"2033",
    "sg:province":"NSW",
    "sg:tags":[
        "function",
        "catering"
    ],
    "wof:name":"Gastronomy Australia Pty Ltd The Art and Science of Food",
    "wof:placetype":"venue"
},
  "geometry": {"coordinates":[151.22318999999999,-33.908848],"type":"Point"}
}