{
  "type": "Feature",
  "properties": {
    "addr:full":"3 Sheldon Ave Mooroolbark VIC 3138",
    "addr:housenumber":"3",
    "addr:postcode":"3138",
    "addr:street":"Sheldon Ave",
    "iso:country":"AU",
    "sg:address":"3 Sheldon Ave",
    "sg:city":"Mooroolbark",
    "sg:classifiers":[
        {
            "category":"Retail",
            "subcategory":"Auto Rental",
            "type":"Services"
        }
    ],
    "sg:phone":"+61 411 814 040",
    "sg:postcode":"3138",
    "sg:province":"VIC",
    "sg:tags":[
        "chauffeur",
        "car",
        "hire",
        "driven",
        "limousine"
    ],
    "wof:name":"D & L Limousines Pty Ltd",
    "wof:placetype":"venue"
},
  "geometry": {"coordinates":[145.32232665999999,-37.7893104553],"type":"Point"}
}