{
  "type": "Feature",
  "properties": {
    "addr:full":"59 Urana Rd Yarrawarrah NSW 2233",
    "addr:housenumber":"59",
    "addr:postcode":"2233",
    "addr:street":"Urana Rd",
    "iso:country":"AU",
    "sg:address":"59 Urana Rd",
    "sg:city":"Yarrawarrah",
    "sg:classifiers":[
        {
            "category":"Building & Trades",
            "subcategory":"Cleaning & Sanitation",
            "type":"Services"
        }
    ],
    "sg:phone":"+61 2 9548 2491",
    "sg:postcode":"2233",
    "sg:province":"NSW",
    "sg:tags":[
        "window"
    ],
    "wof:name":"Brad Harris",
    "wof:placetype":"venue"
},
  "geometry": {"coordinates":[151.02894592300001,-34.052822113],"type":"Point"}
}