{
  "type": "Feature",
  "properties": {
    "iso:country":"AU",
    "sg:address":"4938 Pacific Hwy",
    "sg:city":"Harwood Island",
    "sg:classifiers":[
        {
            "category":"Farming",
            "subcategory":"Farm",
            "type":"Manufacturing & Wholesale Goods"
        }
    ],
    "sg:phone":"+61 2 6646 4233",
    "sg:postcode":"2465",
    "sg:province":"NSW",
    "sg:tags":[
        "farmer"
    ],
    "wof:name":"Shannon A G & E J",
    "wof:placetype":"venue"
},
  "geometry": {"coordinates":[153.24183654800001,-29.4142875671],"type":"Point"}
}