{
  "type": "Feature",
  "properties": {
    "iso:country":"AU",
    "sg:address":"396 Ferrars St",
    "sg:city":"Albert Park",
    "sg:classifiers":[
        {
            "category":"Professional",
            "subcategory":"Employment Agencies",
            "type":"Services"
        }
    ],
    "sg:phone":"+61 3 9699 8544",
    "sg:postcode":"3206",
    "sg:province":"VIC",
    "sg:tags":[
        "model"
    ],
    "wof:name":"Panache Pty Ltd",
    "wof:placetype":"venue"
},
  "geometry": {"coordinates":[144.95910599999999,-37.842312],"type":"Point"}
}