{
  "type": "Feature",
  "properties": {
    "iso:country":"AU",
    "sg:address":"5 First St",
    "sg:city":"Booragul",
    "sg:classifiers":[
        {
            "category":"Building & Trades",
            "subcategory":"Landscaping Services",
            "type":"Services"
        }
    ],
    "sg:phone":"+61 415 710 109",
    "sg:postcode":"2284",
    "sg:province":"NSW",
    "sg:tags":[
        "designer",
        "landscape",
        "contractor"
    ],
    "wof:name":"In Natures Image",
    "wof:placetype":"venue"
},
  "geometry": {"coordinates":[151.61070251500001,-32.971496582],"type":"Point"}
}