{
  "type": "Feature",
  "properties": {
    "iso:country":"AU",
    "sg:address":"15 Violet St",
    "sg:city":"Balgowlah",
    "sg:classifiers":[
        {
            "category":"Professional",
            "subcategory":"Business Services",
            "type":"Services"
        }
    ],
    "sg:phone":"+61 412 241 514",
    "sg:postcode":"2093",
    "sg:province":"NSW",
    "sg:tags":[
        "drafting"
    ],
    "wof:name":"Carrick Paul & Associates",
    "wof:placetype":"venue"
},
  "geometry": {"coordinates":[151.25700378400001,-33.79712677],"type":"Point"}
}