{
  "type": "Feature",
  "properties": {
    "addr:full":"28 Fraser Road Gympie QLD 4570",
    "addr:housenumber":"28",
    "addr:postcode":"4570",
    "addr:street":"Fraser Road",
    "iso:country":"AU",
    "sg:address":"28 Fraser Road",
    "sg:city":"Gympie",
    "sg:classifiers":[
        {
            "category":"Conference Center",
            "type":"Public Place"
        }
    ],
    "sg:phone":"+61 7 5483 0000",
    "sg:postcode":"4570",
    "sg:province":"QLD",
    "sg:tags":[
        "venue",
        "convention"
    ],
    "wof:name":"Gympie Conference Centre",
    "wof:placetype":"venue"
},
  "geometry": {"coordinates":[152.645095825,-26.1618003845],"type":"Point"}
}