{
  "type": "Feature",
  "properties": {
    "addr:full":"69 Boorowa St Young NSW 2594",
    "addr:housenumber":"69",
    "addr:postcode":"2594",
    "addr:street":"Boorowa St",
    "iso:country":"AU",
    "sg:address":"69 Boorowa St",
    "sg:city":"Young",
    "sg:classifiers":[
        {
            "category":"Manufacturing",
            "subcategory":"Chemicals & Compounds",
            "type":"Manufacturing & Wholesale Goods"
        }
    ],
    "sg:phone":"+61 2 6382 5633",
    "sg:postcode":"2594",
    "sg:province":"NSW",
    "sg:tags":[
        "agricultural"
    ],
    "wof:name":"Thompson's Rural Supplies",
    "wof:placetype":"venue"
},
  "geometry": {"coordinates":[148.294647217,-34.3125610352],"type":"Point"}
}