{
  "type": "Feature",
  "properties": {
    "addr:full":"27 Collie St Fremantle WA 6160",
    "addr:housenumber":"27",
    "addr:postcode":"6160",
    "addr:street":"Collie St",
    "iso:country":"AU",
    "sg:address":"27 Collie St",
    "sg:city":"Fremantle",
    "sg:classifiers":[
        {
            "category":"Cafe",
            "type":"Food & Drink"
        }
    ],
    "sg:phone":"+61 8 9433 5668",
    "sg:postcode":"6160",
    "sg:province":"WA",
    "wof:name":"Chef Hans Cafe",
    "wof:placetype":"venue"
},
  "geometry": {"coordinates":[115.747299,-32.056122],"type":"Point"}
}