{
  "type": "Feature",
  "properties": {
    "addr:full":"173 Como Pde East Parkdale VIC 3195",
    "addr:housenumber":"173",
    "addr:postcode":"3195",
    "addr:street":"Como Pde East",
    "iso:country":"AU",
    "sg:address":"173 Como Pde East",
    "sg:city":"Parkdale",
    "sg:classifiers":[
        {
            "category":"Personal",
            "subcategory":"Beauty Salon",
            "type":"Services"
        }
    ],
    "sg:phone":"+61 3 9580 0422",
    "sg:postcode":"3195",
    "sg:province":"VIC",
    "sg:tags":[
        "hairdresser"
    ],
    "wof:name":"Waves Hair Cutting and Colour Salon",
    "wof:placetype":"venue"
},
  "geometry": {"coordinates":[145.07695007300001,-37.9931106567],"type":"Point"}
}