{
  "type": "Feature",
  "properties": {
    "addr:full":"307 Mann St Gosford NSW 2250",
    "addr:housenumber":"307",
    "addr:postcode":"2250",
    "addr:street":"Mann St",
    "iso:country":"AU",
    "sg:address":"307 Mann St",
    "sg:city":"Gosford",
    "sg:classifiers":[
        {
            "category":"Home & Garden",
            "subcategory":"Garden Supply",
            "type":"Retail Goods"
        }
    ],
    "sg:phone":"+61 2 4325 0291",
    "sg:postcode":"2250",
    "sg:province":"NSW",
    "sg:tags":[
        "fertilizer"
    ],
    "wof:name":"Gosford Packing House",
    "wof:placetype":"venue"
},
  "geometry": {"coordinates":[151.34332275400001,-33.4204483032],"type":"Point"}
}