{
  "type": "Feature",
  "properties": {
    "addr:full":"U 25/ 68 Liverpool Rd Summer Hill NSW 2130",
    "addr:housenumber":"25 / 68",
    "addr:postcode":"2130",
    "addr:street":"Liverpool Rd",
    "iso:country":"AU",
    "sg:address":"U 25/ 68 Liverpool Rd",
    "sg:city":"Summer Hill",
    "sg:classifiers":[
        {
            "category":"Shopping",
            "subcategory":"Computers & Home Electronics",
            "type":"Retail Goods"
        }
    ],
    "sg:phone":"+61 2 9716 5486",
    "sg:postcode":"2130",
    "sg:province":"NSW",
    "sg:tags":[
        "equipment",
        "part",
        "electronic"
    ],
    "wof:name":"Yulidigital",
    "wof:placetype":"venue"
},
  "geometry": {"coordinates":[151.10588073700001,-33.8871307373],"type":"Point"}
}