{
  "type": "Feature",
  "properties": {
    "addr:full":"Lvl 3 40 McDougall St Milton QLD 4064",
    "addr:housenumber":"40",
    "addr:postcode":"4064",
    "addr:street":"Mcdougall St",
    "iso:country":"AU",
    "sg:address":"Lvl 3 40 McDougall St",
    "sg:city":"Milton",
    "sg:classifiers":[
        {
            "category":"Professional",
            "subcategory":"Engineering",
            "type":"Services"
        }
    ],
    "sg:phone":"+61 7 3320 3333",
    "sg:postcode":"4064",
    "sg:province":"QLD",
    "sg:tags":[
        "engineer"
    ],
    "wof:name":"Bateman Engineering Pty Ltd",
    "wof:placetype":"venue"
},
  "geometry": {"coordinates":[153.006393433,-27.4711551666],"type":"Point"}
}