{
  "type": "Feature",
  "properties": {
    "addr:full":"Shop 12, Spotlight Plaza Mann St Gosford NSW 2250",
    "addr:housenumber":"shop 12",
    "addr:postcode":"2250",
    "addr:street":"Mann St",
    "iso:country":"AU",
    "sg:address":"Shop 12, Spotlight Plaza Mann St",
    "sg:city":"Gosford",
    "sg:classifiers":[
        {
            "category":"Personal",
            "subcategory":"Beauty Salon",
            "type":"Services"
        }
    ],
    "sg:phone":"+61 418 406 219",
    "sg:postcode":"2250",
    "sg:province":"NSW",
    "sg:tags":[
        "hair",
        "treatment",
        "replacement"
    ],
    "wof:name":"Anne-Maree Lynch I.A.T.",
    "wof:placetype":"venue"
},
  "geometry": {"coordinates":[151.34251403799999,-33.4237060547],"type":"Point"}
}