{
  "type": "Feature",
  "properties": {
    "addr:full":"18 Terrace Ave Sylvania NSW 2224",
    "addr:housenumber":"18",
    "addr:postcode":"2224",
    "addr:street":"Terrace Ave",
    "iso:country":"AU",
    "sg:address":"18 Terrace Ave",
    "sg:city":"Sylvania",
    "sg:classifiers":[
        {
            "category":"Wholesale",
            "subcategory":"Painting Supplies",
            "type":"Manufacturing & Wholesale Goods"
        }
    ],
    "sg:phone":"+61 2 9522 9750",
    "sg:postcode":"2224",
    "sg:province":"NSW",
    "sg:tags":[
        "product",
        "cleaning"
    ],
    "wof:name":"Amway Of Australia Pty Ltd",
    "wof:placetype":"venue"
},
  "geometry": {"coordinates":[151.09913635300001,-34.0137290955],"type":"Point"}
}