{
  "type": "Feature",
  "properties": {
    "addr:full":"5 Taroona Pl Somerset TAS 7322",
    "addr:housenumber":"5",
    "addr:postcode":"7322",
    "addr:street":"Taroona Pl",
    "iso:country":"AU",
    "sg:address":"5 Taroona Pl",
    "sg:city":"Somerset",
    "sg:classifiers":[
        {
            "category":"Building & Trades",
            "subcategory":"Pest Control",
            "type":"Services"
        }
    ],
    "sg:phone":"+61 3 6435 1676",
    "sg:postcode":"7322",
    "sg:province":"TAS",
    "wof:name":"Beaumont W A",
    "wof:placetype":"venue"
},
  "geometry": {"coordinates":[145.81706199999999,-41.044064],"type":"Point"}
}