{
  "type": "Feature",
  "properties": {
    "addr:full":"William St Gundagai NSW 2722",
    "addr:postcode":"2722",
    "addr:street":"William St",
    "iso:country":"AU",
    "sg:address":"William St",
    "sg:city":"Gundagai",
    "sg:classifiers":[
        {
            "category":"Education",
            "subcategory":"School",
            "type":"Public Place"
        }
    ],
    "sg:phone":"+61 2 6944 1811",
    "sg:postcode":"2722",
    "sg:province":"NSW",
    "sg:tags":[
        "state",
        "-",
        "nsw"
    ],
    "wof:name":"Gundagai Primary School",
    "wof:placetype":"venue"
},
  "geometry": {"coordinates":[148.10531599999999,-35.050117],"type":"Point"}
}