{
  "type": "Feature",
  "properties": {
    "addr:full":"56 Berry St Sydney NSW 2000",
    "addr:housenumber":"56",
    "addr:postcode":"2000",
    "addr:street":"Berry St",
    "iso:country":"AU",
    "sg:address":"56 Berry St",
    "sg:city":"Sydney",
    "sg:classifiers":[
        {
            "category":"Health Services",
            "subcategory":"Doctor",
            "type":"Services"
        }
    ],
    "sg:phone":"+61 1300 360 107",
    "sg:postcode":"2000",
    "sg:province":"NSW",
    "sg:tags":[
        "medical",
        "practitioner"
    ],
    "wof:name":"Peak Health Management",
    "wof:placetype":"venue"
},
  "geometry": {"coordinates":[151.207855225,-33.8367729187],"type":"Point"}
}