{
  "type": "Feature",
  "properties": {
    "iso:country":"AU",
    "sg:address":"Shp1/ 19 Marco Ave",
    "sg:city":"Revesby",
    "sg:classifiers":[
        {
            "category":"Restaurant",
            "type":"Food & Drink"
        }
    ],
    "sg:phone":"+61 2 9792 6866",
    "sg:postcode":"2212",
    "sg:province":"NSW",
    "sg:tags":[
        "pizza"
    ],
    "wof:name":"Alcatraz Cafe",
    "wof:placetype":"venue"
},
  "geometry": {"coordinates":[151.014053,-33.951897],"type":"Point"}
}