{
  "type": "Feature",
  "properties": {
    "addr:full":"71 East St Gatton QLD 4343",
    "addr:housenumber":"71",
    "addr:postcode":"4343",
    "addr:street":"East St",
    "iso:country":"AU",
    "sg:address":"71 East St",
    "sg:city":"Gatton",
    "sg:classifiers":[
        {
            "category":"Home & Garden",
            "subcategory":"Building Materials",
            "type":"Retail Goods"
        }
    ],
    "sg:phone":"+61 7 5462 5566",
    "sg:postcode":"4343",
    "sg:province":"QLD",
    "sg:tags":[
        "balustrading"
    ],
    "wof:name":"P & D Patios",
    "wof:placetype":"venue"
},
  "geometry": {"coordinates":[152.273147583,-27.5608882904],"type":"Point"}
}