{
  "type": "Feature",
  "properties": {
    "addr:full":"Alexander Ave South Yarra VIC 3141",
    "addr:postcode":"3141",
    "addr:street":"Alexander Ave",
    "iso:country":"AU",
    "sg:address":"Alexander Ave",
    "sg:city":"South Yarra",
    "sg:classifiers":[
        {
            "category":"Cafe",
            "type":"Food & Drink"
        }
    ],
    "sg:phone":"+61 3 9824 2500",
    "sg:postcode":"3141",
    "sg:province":"VIC",
    "wof:name":"Yarra Kiosk",
    "wof:placetype":"venue"
},
  "geometry": {"coordinates":[144.99111938499999,-37.8378791809],"type":"Point"}
}