{
  "type": "Feature",
  "properties": {
    "iso:country":"AU",
    "sg:address":"870-872 Maroondah Hwy",
    "sg:city":"Coldstream",
    "sg:classifiers":[
        {
            "category":"Farming",
            "subcategory":"Vineyard",
            "type":"Manufacturing & Wholesale Goods"
        }
    ],
    "sg:phone":"+61 3 5962 5760",
    "sg:postcode":"3770",
    "sg:province":"VIC",
    "sg:tags":[
        "winery"
    ],
    "wof:name":"Portet Wine Makers",
    "wof:placetype":"venue"
},
  "geometry": {"coordinates":[145.46646100000001,-37.68359],"type":"Point"}
}