{
  "type": "Feature",
  "properties": {
    "addr:full":"347 Ipswich Rd Annerley QLD 4103",
    "addr:housenumber":"347",
    "addr:postcode":"4103",
    "addr:street":"Ipswich Rd",
    "iso:country":"AU",
    "sg:address":"347 Ipswich Rd",
    "sg:city":"Annerley",
    "sg:classifiers":[
        {
            "category":"Manufacturing",
            "subcategory":"Furniture",
            "type":"Manufacturing & Wholesale Goods"
        }
    ],
    "sg:phone":"+61 7 3217 3002",
    "sg:postcode":"4103",
    "sg:province":"QLD",
    "sg:tags":[
        "builder",
        "designer",
        "custom"
    ],
    "sg:website":"http://www.antiques-online-shop.com",
    "wof:name":"Palliaer Antiques",
    "wof:placetype":"venue"
},
  "geometry": {"coordinates":[153.034423828,-27.506023407],"type":"Point"}
}