{
  "type": "Feature",
  "properties": {
    "iso:country":"AU",
    "sg:address":"Yackandandah Rd",
    "sg:city":"Staghorn Flat",
    "sg:classifiers":[
        {
            "category":"Professional",
            "subcategory":"Accounting & Tax Preparation",
            "type":"Services"
        }
    ],
    "sg:phone":"+61 2 6020 8703",
    "sg:postcode":"3691",
    "sg:province":"VIC",
    "sg:tags":[
        "bookkeeping"
    ],
    "wof:name":"Staghorn Enterprises",
    "wof:placetype":"venue"
},
  "geometry": {"coordinates":[146.95297199999999,-36.222321],"type":"Point"}
}