{
  "type": "Feature",
  "properties": {
    "iso:country":"AU",
    "sg:address":"21 Skinner St",
    "sg:city":"South Grafton",
    "sg:classifiers":[
        {
            "category":"Professional",
            "subcategory":"Computer Services",
            "type":"Services"
        }
    ],
    "sg:phone":"+61 2 6643 3980",
    "sg:postcode":"2460",
    "sg:province":"NSW",
    "sg:tags":[
        "repairs",
        "upgrade",
        "equipment"
    ],
    "wof:name":"The Computer Doctor",
    "wof:placetype":"venue"
},
  "geometry": {"coordinates":[152.93565368599999,-29.7018852234],"type":"Point"}
}