{
  "type": "Feature",
  "properties": {
    "addr:full":"469 Darling St Balmain NSW 2041",
    "addr:housenumber":"469",
    "addr:postcode":"2041",
    "addr:street":"Darling St",
    "iso:country":"AU",
    "sg:address":"469 Darling St",
    "sg:city":"Balmain",
    "sg:classifiers":[
        {
            "category":"Professional",
            "subcategory":"Computer Services",
            "type":"Services"
        }
    ],
    "sg:phone":"+61 2 9555 4777",
    "sg:postcode":"2041",
    "sg:province":"NSW",
    "sg:tags":[
        "package",
        "software"
    ],
    "wof:name":"OMNIS Australasia",
    "wof:placetype":"venue"
},
  "geometry": {"coordinates":[151.17321799999999,-33.856201],"type":"Point"}
}