{
  "type": "Feature",
  "properties": {
    "addr:full":"92- 94 Old Toombul Rd Northgate QLD 4013",
    "addr:housenumber":"94",
    "addr:postcode":"4013",
    "addr:street":"Old Toombul Rd",
    "iso:country":"AU",
    "sg:address":"92- 94 Old Toombul Rd",
    "sg:city":"Northgate",
    "sg:classifiers":[
        {
            "category":"Retail",
            "subcategory":"Auto Repair",
            "type":"Services"
        }
    ],
    "sg:phone":"+61 7 3266 1550",
    "sg:postcode":"4013",
    "sg:province":"QLD",
    "sg:tags":[
        "beater",
        "painter",
        "panel"
    ],
    "wof:name":"Toombul Road Auto Smash",
    "wof:placetype":"venue"
},
  "geometry": {"coordinates":[153.071365356,-27.3913078308],"type":"Point"}
}