{
  "type": "Feature",
  "properties": {
    "addr:full":"494- 496 Woolcock St Townsville QLD 4810",
    "addr:housenumber":"494 496",
    "addr:postcode":"4810",
    "addr:street":"Woolcock St",
    "iso:country":"AU",
    "sg:address":"494- 496 Woolcock St",
    "sg:city":"Townsville",
    "sg:classifiers":[
        {
            "category":"Manufacturing",
            "subcategory":"Building Materials",
            "type":"Manufacturing & Wholesale Goods"
        }
    ],
    "sg:phone":"+61 7 4728 9040",
    "sg:postcode":"4810",
    "sg:province":"QLD",
    "sg:tags":[
        "concrete",
        "product"
    ],
    "wof:name":"The Pot Factory",
    "wof:placetype":"venue"
},
  "geometry": {"coordinates":[146.753784,-19.268173],"type":"Point"}
}