{
  "type": "Feature",
  "properties": {
    "iso:country":"AU",
    "sg:address":"245 North Beach Drv",
    "sg:city":"Tuart Hill",
    "sg:classifiers":[
        {
            "category":"Personal",
            "subcategory":"Beauty Salon",
            "type":"Services"
        }
    ],
    "sg:phone":"+61 8 9344 2527",
    "sg:postcode":"6060",
    "sg:province":"WA",
    "sg:tags":[
        "hairdresser"
    ],
    "wof:name":"Kevin Mckenna Men's Hairstylist",
    "wof:placetype":"venue"
},
  "geometry": {"coordinates":[115.83373260499999,-31.8902053833],"type":"Point"}
}