{
  "type": "Feature",
  "properties": {
    "addr:full":"74 Keen St Lismore NSW 2480",
    "addr:housenumber":"74",
    "addr:postcode":"2480",
    "addr:street":"Keen St",
    "iso:country":"AU",
    "sg:address":"74 Keen St",
    "sg:city":"Lismore",
    "sg:classifiers":[
        {
            "category":"Building & Trades",
            "subcategory":"Equipment Rental",
            "type":"Services"
        }
    ],
    "sg:phone":"+61 2 6622 8008",
    "sg:postcode":"2480",
    "sg:province":"NSW",
    "sg:tags":[
        "supply",
        "catering"
    ],
    "wof:name":"The Kitchen Shelf",
    "wof:placetype":"venue"
},
  "geometry": {"coordinates":[153.27865600600001,-28.8090267181],"type":"Point"}
}