{
  "type": "Feature",
  "properties": {
    "addr:full":"PO Box 222 Ferntree Gully Bus Cntr VIC 3156",
    "addr:postcode":"3156",
    "iso:country":"AU",
    "sg:address":"PO Box 222",
    "sg:city":"Ferntree Gully Bus Cntr",
    "sg:classifiers":[
        {
            "category":"Professional",
            "subcategory":"Art Services",
            "type":"Services"
        }
    ],
    "sg:phone":"+61 417 527 284",
    "sg:postcode":"3156",
    "sg:province":"VIC",
    "sg:tags":[
        "decorator",
        "painter"
    ],
    "wof:name":"Dream Finishes Painting & Decorating",
    "wof:placetype":"venue"
},
  "geometry": {"coordinates":[145.261184692,-37.8898849487],"type":"Point"}
}