{
  "type": "Feature",
  "properties": {
    "addr:full":"4- 6 Leeds St Wingfield SA 5013",
    "addr:housenumber":"6",
    "addr:postcode":"5013",
    "addr:street":"Leeds St",
    "iso:country":"AU",
    "sg:address":"4- 6 Leeds St",
    "sg:city":"Wingfield",
    "sg:classifiers":[
        {
            "category":"Manufacturing",
            "subcategory":"Chemicals & Compounds",
            "type":"Manufacturing & Wholesale Goods"
        }
    ],
    "sg:phone":"+61 8 8262 2800",
    "sg:postcode":"5013",
    "sg:province":"SA",
    "sg:tags":[
        "electroplating"
    ],
    "wof:name":"Columbia Hardchrome",
    "wof:placetype":"venue"
},
  "geometry": {"coordinates":[138.56423950199999,-34.8381195068],"type":"Point"}
}