{
  "type": "Feature",
  "properties": {
    "addr:full":"Shop 27 24 Hughes St Cabramatta NSW 2166",
    "addr:housenumber":"shop 27 24",
    "addr:postcode":"2166",
    "addr:street":"Hughes St",
    "iso:country":"AU",
    "sg:address":"Shop 27 24 Hughes St",
    "sg:city":"Cabramatta",
    "sg:classifiers":[
        {
            "category":"Utilities",
            "subcategory":"Water",
            "type":"Services"
        }
    ],
    "sg:phone":"+61 2 9725 6227",
    "sg:postcode":"2166",
    "sg:province":"NSW",
    "sg:tags":[
        "equipment",
        "treatment"
    ],
    "wof:name":"Air & Water Purifier",
    "wof:placetype":"venue"
},
  "geometry": {"coordinates":[150.93606567399999,-33.8935394287],"type":"Point"}
}