{
  "type": "Feature",
  "properties": {
    "addr:full":"181 Conadilly St Gunnedah NSW 2380",
    "addr:housenumber":"181",
    "addr:postcode":"2380",
    "addr:street":"Conadilly St",
    "iso:country":"AU",
    "sg:address":"181 Conadilly St",
    "sg:city":"Gunnedah",
    "sg:classifiers":[
        {
            "category":"Shopping",
            "type":"Retail Goods"
        }
    ],
    "sg:phone":"+61 2 6742 1715",
    "sg:postcode":"2380",
    "sg:province":"NSW",
    "sg:tags":[
        "agent",
        "stock"
    ],
    "wof:name":"C. R. Ewing & Sons",
    "wof:placetype":"venue"
},
  "geometry": {"coordinates":[150.25233459500001,-30.9772491455],"type":"Point"}
}