{
  "type": "Feature",
  "properties": {
    "addr:full":"10 Station St Thornleigh NSW 2120",
    "addr:housenumber":"10",
    "addr:postcode":"2120",
    "addr:street":"Station St",
    "iso:country":"AU",
    "sg:address":"10 Station St",
    "sg:city":"Thornleigh",
    "sg:classifiers":[
        {
            "category":"Personal",
            "subcategory":"Beauty Salon",
            "type":"Services"
        }
    ],
    "sg:phone":"+61 2 9875 5113",
    "sg:postcode":"2120",
    "sg:province":"NSW",
    "wof:name":"Adele's Beauty & Bodyworks",
    "wof:placetype":"venue"
},
  "geometry": {"coordinates":[151.08300781200001,-33.7253723145],"type":"Point"}
}