{
  "type": "Feature",
  "properties": {
    "addr:full":"22/ 18 Bridges Rd Melville WA 6156",
    "addr:housenumber":"22 / 18",
    "addr:postcode":"6156",
    "addr:street":"Bridges Rd",
    "iso:country":"AU",
    "sg:address":"22/ 18 Bridges Rd",
    "sg:city":"Melville",
    "sg:classifiers":[
        {
            "category":"Utilities",
            "subcategory":"Telephone",
            "type":"Services"
        }
    ],
    "sg:phone":"+61 8 9317 1317",
    "sg:postcode":"6156",
    "sg:province":"WA",
    "sg:tags":[
        "installation",
        "system",
        "maintenance"
    ],
    "wof:name":"Lindsay's Telephone & Data Services",
    "wof:placetype":"venue"
},
  "geometry": {"coordinates":[115.799278,-32.034718],"type":"Point"}
}