{
  "type": "Feature",
  "properties": {
    "addr:full":"3522 Dekin Ave Koorlong VIC 3501",
    "addr:housenumber":"3522",
    "addr:postcode":"3501",
    "addr:street":"Dekin Ave",
    "iso:country":"AU",
    "sg:address":"3522 Dekin Ave",
    "sg:city":"Koorlong",
    "sg:classifiers":[
        {
            "category":"Building & Trades",
            "subcategory":"Construction",
            "type":"Services"
        }
    ],
    "sg:phone":"+61 3 5021 1707",
    "sg:postcode":"3501",
    "sg:province":"VIC",
    "sg:tags":[
        "installation",
        "air conditioning"
    ],
    "wof:name":"Brooks Real Refrigeration & Airconditioning",
    "wof:placetype":"venue"
},
  "geometry": {"coordinates":[142.08706665,-34.2474403381],"type":"Point"}
}