{
  "type": "Feature",
  "properties": {
    "iso:country":"AU",
    "sg:address":"7, 6 Steele St",
    "sg:city":"Winnellie",
    "sg:classifiers":[
        {
            "category":"Utilities",
            "subcategory":"Electric",
            "type":"Services"
        }
    ],
    "sg:phone":"+61 8 8947 1300",
    "sg:postcode":"0820",
    "sg:province":"NT",
    "sg:tags":[
        "electrical",
        "contractor"
    ],
    "wof:name":"Bruno Rinaldi",
    "wof:placetype":"venue"
},
  "geometry": {"coordinates":[130.86203002900001,-12.4292869568],"type":"Point"}
}