{
  "type": "Feature",
  "properties": {
    "iso:country":"AU",
    "sg:address":"10 Jubilee Ave",
    "sg:city":"Warriewood",
    "sg:classifiers":[
        {
            "category":"Professional",
            "subcategory":"Accounting & Tax Preparation",
            "type":"Services"
        }
    ],
    "sg:phone":"+61 2 9997 8753",
    "sg:postcode":"2102",
    "sg:province":"NSW",
    "sg:tags":[
        "accountant",
        "auditor"
    ],
    "wof:name":"Corkill Richard",
    "wof:placetype":"venue"
},
  "geometry": {"coordinates":[151.283844,-33.677391],"type":"Point"}
}