{
  "type": "Feature",
  "properties": {
    "addr:full":"283-285 Shannon Ave Geelong VIC 3220",
    "addr:housenumber":"283-285",
    "addr:postcode":"3220",
    "addr:street":"Shannon Ave",
    "iso:country":"AU",
    "sg:address":"283-285 Shannon Ave",
    "sg:city":"Geelong",
    "sg:classifiers":[
        {
            "category":"Travel",
            "subcategory":"Hotels & Motels",
            "type":"Entertainment"
        }
    ],
    "sg:phone":"+61 3 5222 4355",
    "sg:postcode":"3220",
    "sg:province":"VIC",
    "wof:name":"Shannon Motor Inn & Apartments",
    "wof:placetype":"venue"
},
  "geometry": {"coordinates":[144.335114,-38.146133],"type":"Point"}
}