{
  "type": "Feature",
  "properties": {
    "addr:full":"Factory 2 23 Orchard St Kilsyth VIC 3137",
    "addr:housenumber":"23",
    "addr:postcode":"3137",
    "addr:street":"Orchard St",
    "iso:country":"AU",
    "sg:address":"Factory 2 23 Orchard St",
    "sg:city":"Kilsyth",
    "sg:classifiers":[
        {
            "category":"Landmark",
            "subcategory":"Scenic View",
            "type":"Public Place"
        }
    ],
    "sg:phone":"+61 3 9725 2555",
    "sg:postcode":"3137",
    "sg:province":"VIC",
    "sg:tags":[
        "staircase",
        "handrail"
    ],
    "wof:name":"Active Stairs",
    "wof:placetype":"venue"
},
  "geometry": {"coordinates":[145.313034058,-37.8111381531],"type":"Point"}
}