{
  "type": "Feature",
  "properties": {
    "addr:full":"35 Macquarie Drv Cherrybrook NSW 2126",
    "addr:housenumber":"35",
    "addr:postcode":"2126",
    "addr:street":"Macquarie Drv",
    "iso:country":"AU",
    "sg:address":"35 Macquarie Drv",
    "sg:city":"Cherrybrook",
    "sg:classifiers":[
        {
            "category":"Building & Trades",
            "subcategory":"Cleaning & Sanitation",
            "type":"Services"
        }
    ],
    "sg:phone":"+61 2 9481 8800",
    "sg:postcode":"2126",
    "sg:province":"NSW",
    "sg:tags":[
        "industrial",
        "commercial",
        "contractor"
    ],
    "wof:name":"J M Asset Maintenance",
    "wof:placetype":"venue"
},
  "geometry": {"coordinates":[151.047164917,-33.7246170044],"type":"Point"}
}