{
  "type": "Feature",
  "properties": {
    "iso:country":"AU",
    "sg:address":"Suite 1, Level 1 Midway Arcade, 974-976 Main Road",
    "sg:city":"Eltham",
    "sg:classifiers":[
        {
            "category":"Professional",
            "subcategory":"Business Services",
            "type":"Services"
        }
    ],
    "sg:phone":"+61 3 9439 5201",
    "sg:postcode":"3095",
    "sg:province":"VIC",
    "sg:tags":[
        "broker"
    ],
    "wof:name":"Action International",
    "wof:placetype":"venue"
},
  "geometry": {"coordinates":[145.148803711,-37.7137107849],"type":"Point"}
}