{
  "type": "Feature",
  "properties": {
    "addr:full":"Great Western Hwy Girraween NSW 2145",
    "addr:postcode":"2145",
    "addr:street":"Great Western Hwy",
    "iso:country":"AU",
    "sg:address":"Great Western Hwy",
    "sg:city":"Girraween",
    "sg:classifiers":[
        {
            "category":"Home & Garden",
            "subcategory":"Hardware",
            "type":"Retail Goods"
        }
    ],
    "sg:phone":"+61 2 9636 3200",
    "sg:postcode":"2145",
    "sg:province":"NSW",
    "sg:tags":[
        "generating",
        "set",
        "generator"
    ],
    "wof:name":"Kennards Generator Hire",
    "wof:placetype":"venue"
},
  "geometry": {"coordinates":[150.93385314899999,-33.8072090149],"type":"Point"}
}