{
  "type": "Feature",
  "properties": {
    "iso:country":"AU",
    "sg:address":"U2/ 14 Provident Ave",
    "sg:city":"Glynde",
    "sg:classifiers":[
        {
            "category":"Professional",
            "subcategory":"Art Services",
            "type":"Services"
        }
    ],
    "sg:phone":"+61 8 8365 9542",
    "sg:postcode":"5070",
    "sg:province":"SA",
    "sg:tags":[
        "commercial",
        "artist"
    ],
    "wof:name":"Tamara Molloy",
    "wof:placetype":"venue"
},
  "geometry": {"coordinates":[138.65315246599999,-34.8947753906],"type":"Point"}
}