{
  "type": "Feature",
  "properties": {
    "iso:country":"AU",
    "sg:address":"Level 3",
    "sg:city":"International Terminal Mascot",
    "sg:classifiers":[
        {
            "category":"Health Services",
            "subcategory":"Doctor",
            "type":"Services"
        }
    ],
    "sg:phone":"+61 2 9667 4355",
    "sg:postcode":"2020",
    "sg:province":"NSW",
    "sg:tags":[
        "medical",
        "practitioner"
    ],
    "wof:name":"Travel Health Sydney Airport Medical Centre",
    "wof:placetype":"venue"
},
  "geometry": {"coordinates":[151.198486328,-33.9233589172],"type":"Point"}
}