{
  "type": "Feature",
  "properties": {
    "addr:full":"24 Cranfield St Sunnybank Hills QLD 4109",
    "addr:housenumber":"24",
    "addr:postcode":"4109",
    "addr:street":"Cranfield St",
    "iso:country":"AU",
    "sg:address":"24 Cranfield St",
    "sg:city":"Sunnybank Hills",
    "sg:classifiers":[
        {
            "category":"Building & Trades",
            "subcategory":"Plumbing",
            "type":"Services"
        }
    ],
    "sg:phone":"+61 7 3345 6042",
    "sg:postcode":"4109",
    "sg:province":"QLD",
    "sg:tags":[
        "plumber",
        "gasfitters"
    ],
    "wof:name":"Rivercity Plumbing",
    "wof:placetype":"venue"
},
  "geometry": {"coordinates":[153.047271728,-27.5878372192],"type":"Point"}
}