{
  "type": "Feature",
  "properties": {
    "addr:full":"Kiora Rd Miranda NSW 2228",
    "addr:postcode":"2228",
    "addr:street":"Kiora Rd",
    "iso:country":"AU",
    "sg:address":"Kiora Rd",
    "sg:city":"Miranda",
    "sg:classifiers":[
        {
            "category":"Shopping",
            "subcategory":"Clothing, Apparel, & Fashions",
            "type":"Retail Goods"
        }
    ],
    "sg:phone":"+61 2 9526 8760",
    "sg:postcode":"2228",
    "sg:province":"NSW",
    "sg:tags":[
        "sportswear"
    ],
    "wof:name":"Planet Unique",
    "wof:placetype":"venue"
},
  "geometry": {"coordinates":[151.102493286,-34.0339202881],"type":"Point"}
}