{
  "type": "Feature",
  "properties": {
    "iso:country":"AU",
    "sg:address":"112 Ramsay St",
    "sg:city":"Haberfield",
    "sg:classifiers":[
        {
            "category":"Health Services",
            "subcategory":"Doctor",
            "type":"Services"
        }
    ],
    "sg:phone":"+61 2 9799 5000",
    "sg:postcode":"2045",
    "sg:province":"NSW",
    "sg:tags":[
        "medical",
        "practitioner"
    ],
    "wof:name":"George Rebekah Dr",
    "wof:placetype":"venue"
},
  "geometry": {"coordinates":[151.138107,-33.879795],"type":"Point"}
}