{
  "type": "Feature",
  "properties": {
    "addr:full":"766 Ipswich Rd Annerley QLD 4103",
    "addr:housenumber":"766",
    "addr:postcode":"4103",
    "addr:street":"Ipswich Rd",
    "iso:country":"AU",
    "sg:address":"766 Ipswich Rd",
    "sg:city":"Annerley",
    "sg:classifiers":[
        {
            "category":"Sports & Exercise",
            "subcategory":"Gym",
            "type":"Entertainment"
        }
    ],
    "sg:phone":"+61 7 3848 8000",
    "sg:postcode":"4103",
    "sg:province":"QLD",
    "sg:tags":[
        "health",
        "fitness"
    ],
    "wof:name":"Hepburns Health & Fitness Centre",
    "wof:placetype":"venue"
},
  "geometry": {"coordinates":[153.02659606899999,-27.5212364197],"type":"Point"}
}