{
  "type": "Feature",
  "properties": {
    "addr:full":"Cnr. Quindus St & Spanns Rd Beenleigh QLD 4207",
    "addr:postcode":"4207",
    "addr:street":"Quindus St & Spanns Rd",
    "iso:country":"AU",
    "sg:address":"Cnr. Quindus St & Spanns Rd",
    "sg:city":"Beenleigh",
    "sg:classifiers":[
        {
            "category":"Home & Garden",
            "subcategory":"Building Materials",
            "type":"Retail Goods"
        }
    ],
    "sg:phone":"+61 7 3451 4200",
    "sg:postcode":"4207",
    "sg:province":"QLD",
    "sg:tags":[
        "supply"
    ],
    "sg:website":"http://www.peerindustries.com.au",
    "wof:name":"Peer Industries Pty Ltd",
    "wof:placetype":"venue"
},
  "geometry": {"coordinates":[153.188232422,-27.7127342224],"type":"Point"}
}