{
  "type": "Feature",
  "properties": {
    "addr:full":"385 Hargraves St Bendigo VIC 3550",
    "addr:housenumber":"385",
    "addr:postcode":"3550",
    "addr:street":"Hargraves St",
    "iso:country":"AU",
    "sg:address":"385 Hargraves St",
    "sg:city":"Bendigo",
    "sg:classifiers":[
        {
            "category":"Education",
            "subcategory":"School",
            "type":"Public Place"
        }
    ],
    "sg:phone":"+61 3 5442 3057",
    "sg:postcode":"3550",
    "sg:province":"VIC",
    "sg:tags":[
        "co-educational"
    ],
    "wof:name":"Australian Technical College",
    "wof:placetype":"venue"
},
  "geometry": {"coordinates":[144.27813720699999,-36.76171875],"type":"Point"}
}