{
  "type": "Feature",
  "properties": {
    "iso:country":"AU",
    "sg:address":"Purlewaugh Rd",
    "sg:city":"Coonabarabran",
    "sg:classifiers":[
        {
            "category":"Farming",
            "subcategory":"Berry Farm",
            "type":"Manufacturing & Wholesale Goods"
        }
    ],
    "sg:phone":"+61 2 6842 7894",
    "sg:postcode":"2357",
    "sg:province":"NSW",
    "sg:tags":[
        "fruit",
        "grower"
    ],
    "wof:name":"Treetop Projects Limited",
    "wof:placetype":"venue"
},
  "geometry": {"coordinates":[149.27748107900001,-31.273979187],"type":"Point"}
}