{
  "type": "Feature",
  "properties": {
    "addr:full":"PO Box 655 Bacchus Marsh VIC 3340",
    "addr:postcode":"3340",
    "iso:country":"AU",
    "sg:address":"PO Box 655",
    "sg:city":"Bacchus Marsh",
    "sg:classifiers":[
        {
            "category":"Manufacturing",
            "subcategory":"Petroleum Products",
            "type":"Manufacturing & Wholesale Goods"
        }
    ],
    "sg:phone":"+61 417 997 017",
    "sg:postcode":"3340",
    "sg:province":"VIC",
    "sg:tags":[
        "lubricant"
    ],
    "wof:name":"Industrial Lubrication & Maintenance Pty Ltd",
    "wof:placetype":"venue"
},
  "geometry": {"coordinates":[144.435562,-37.67474],"type":"Point"}
}