{
  "type": "Feature",
  "properties": {
    "addr:full":"32 Plummer Rd Laverton North VIC 3026",
    "addr:housenumber":"32",
    "addr:postcode":"3026",
    "addr:street":"Plummer Rd",
    "iso:country":"AU",
    "sg:address":"32 Plummer Rd",
    "sg:city":"Laverton North",
    "sg:classifiers":[
        {
            "category":"Professional",
            "subcategory":"Accounting & Tax Preparation",
            "type":"Services"
        }
    ],
    "sg:phone":"+61 3 9314 6007",
    "sg:postcode":"3026",
    "sg:province":"VIC",
    "sg:tags":[
        "record",
        "business",
        "destruction"
    ],
    "wof:name":"Fine Paper Recyclers Pty Ltd",
    "wof:placetype":"venue"
},
  "geometry": {"coordinates":[144.81431599999999,-37.818783],"type":"Point"}
}