{
  "type": "Feature",
  "properties": {
    "addr:full":"15 Oriel Rd Yeronga QLD 4104",
    "addr:housenumber":"15",
    "addr:postcode":"4104",
    "addr:street":"Oriel Rd",
    "iso:country":"AU",
    "sg:address":"15 Oriel Rd",
    "sg:city":"Yeronga",
    "sg:classifiers":[
        {
            "category":"Government",
            "subcategory":"Court House",
            "type":"Public Place"
        }
    ],
    "sg:phone":"+61 7 3848 4454",
    "sg:postcode":"4104",
    "sg:province":"QLD",
    "sg:tags":[
        "personal",
        "marriage",
        "family",
        "counselling"
    ],
    "wof:name":"Tracey Tighe",
    "wof:placetype":"venue"
},
  "geometry": {"coordinates":[153.00279235799999,-27.5104198456],"type":"Point"}
}