{
  "type": "Feature",
  "properties": {
    "iso:country":"AU",
    "sg:address":"130 North Rd",
    "sg:city":"Brighton",
    "sg:classifiers":[
        {
            "category":"Real Estate",
            "subcategory":"Developer",
            "type":"Services"
        }
    ],
    "sg:phone":"+61 500 888 277",
    "sg:postcode":"3186",
    "sg:province":"VIC",
    "sg:tags":[
        "development"
    ],
    "wof:name":"Westwater Corporation Pty Ltd",
    "wof:placetype":"venue"
},
  "geometry": {"coordinates":[145.00210571299999,-37.8993873596],"type":"Point"}
}