{
  "type": "Feature",
  "properties": {
    "iso:country":"AU",
    "sg:address":"Unit 1 35 Industrial Drv",
    "sg:city":"Braeside",
    "sg:classifiers":[
        {
            "category":"Autos & Motor Vehicles",
            "subcategory":"Auto Supplies",
            "type":"Retail Goods"
        }
    ],
    "sg:phone":"+61 3 9587 9889",
    "sg:postcode":"3195",
    "sg:province":"VIC",
    "sg:tags":[
        "wheel",
        "automotive",
        "rim"
    ],
    "wof:name":"Stonestar Australia",
    "wof:placetype":"venue"
},
  "geometry": {"coordinates":[145.11119079599999,-38.0052528381],"type":"Point"}
}