{
  "type": "Feature",
  "properties": {
    "addr:full":"Shp1/ 1567 Wynnum Rd Tingalpa QLD 4173",
    "addr:housenumber":"1567",
    "addr:postcode":"4173",
    "addr:street":"Wynnum Rd",
    "iso:country":"AU",
    "sg:address":"Shp1/ 1567 Wynnum Rd",
    "sg:city":"Tingalpa",
    "sg:classifiers":[
        {
            "category":"Fast Food",
            "type":"Food & Drink"
        }
    ],
    "sg:phone":"+61 7 3390 6688",
    "sg:postcode":"4173",
    "sg:province":"QLD",
    "sg:tags":[
        "away",
        "take"
    ],
    "wof:name":"Tingalpa Seafood & Takeaway",
    "wof:placetype":"venue"
},
  "geometry": {"coordinates":[153.127609253,-27.4748859406],"type":"Point"}
}