{
  "type": "Feature",
  "properties": {
    "addr:full":"87 Riding Rd Hawthorne QLD 4171",
    "addr:housenumber":"87",
    "addr:postcode":"4171",
    "addr:street":"Riding Rd",
    "iso:country":"AU",
    "sg:address":"87 Riding Rd",
    "sg:city":"Hawthorne",
    "sg:classifiers":[
        {
            "category":"Real Estate",
            "subcategory":"Real Estate Agent",
            "type":"Services"
        }
    ],
    "sg:phone":"+61 7 3414 6754",
    "sg:postcode":"4171",
    "sg:province":"QLD",
    "wof:name":"Coldwell Banker - APA",
    "wof:placetype":"venue"
},
  "geometry": {"coordinates":[153.064376831,-27.4652137756],"type":"Point"}
}