{
  "type": "Feature",
  "properties": {
    "addr:full":"42 Ayfield Rd Para Hills West SA 5096",
    "addr:housenumber":"42",
    "addr:postcode":"5096",
    "addr:street":"Ayfield Rd Para Hills West",
    "iso:country":"AU",
    "sg:address":"42 Ayfield Rd",
    "sg:city":"Para Hills West",
    "sg:classifiers":[
        {
            "category":"Wholesale",
            "subcategory":"Metals & Minerals",
            "type":"Manufacturing & Wholesale Goods"
        }
    ],
    "sg:phone":"+61 8 8281 2720",
    "sg:postcode":"5096",
    "sg:province":"SA",
    "sg:tags":[
        "steel",
        "merchant"
    ],
    "wof:name":"Titan Steel Supplies",
    "wof:placetype":"venue"
},
  "geometry": {"coordinates":[138.64979553200001,-34.7967033386],"type":"Point"}
}