{
  "type": "Feature",
  "properties": {
    "iso:country":"AU",
    "sg:address":"380 City Rd",
    "sg:city":"South Melbourne",
    "sg:classifiers":[
        {
            "category":"Autos & Motor Vehicles",
            "subcategory":"Automobile Sales",
            "type":"Retail Goods"
        }
    ],
    "sg:phone":"+61 3 9627 3333",
    "sg:postcode":"3205",
    "sg:province":"VIC",
    "sg:tags":[
        "car",
        "new"
    ],
    "wof:name":"HSV",
    "wof:placetype":"venue"
},
  "geometry": {"coordinates":[144.955994,-37.829212],"type":"Point"}
}