{
  "type": "Feature",
  "properties": {
    "iso:country":"AU",
    "sg:address":"Suite 2&3 123- 125 Willougby Rd",
    "sg:city":"Crows Nest",
    "sg:classifiers":[
        {
            "category":"Recreation",
            "subcategory":"Fishing",
            "type":"Entertainment"
        }
    ],
    "sg:phone":"+61 2 9438 4244",
    "sg:postcode":"2065",
    "sg:province":"NSW",
    "sg:tags":[
        "tackle"
    ],
    "wof:name":"Corico",
    "wof:placetype":"venue"
},
  "geometry": {"coordinates":[151.201080322,-33.822353363],"type":"Point"}
}