{
  "type": "Feature",
  "properties": {
    "addr:full":"Stockland Shopping Centre, West Burleigh Rd Burleigh Heads QLD 4220",
    "addr:postcode":"4220",
    "addr:street":"Burleigh Rd",
    "iso:country":"AU",
    "sg:address":"Stockland Shopping Centre, West Burleigh Rd",
    "sg:city":"Burleigh Heads",
    "sg:classifiers":[
        {
            "category":"Utilities",
            "subcategory":"Mobile Phone",
            "type":"Services"
        }
    ],
    "sg:phone":"+61 7 5520 6858",
    "sg:postcode":"4220",
    "sg:province":"QLD",
    "sg:tags":[
        "repair",
        "telephone"
    ],
    "wof:name":"Network Communications",
    "wof:placetype":"venue"
},
  "geometry": {"coordinates":[153.449752808,-28.0879230499],"type":"Point"}
}