{
  "type": "Feature",
  "properties": {
    "iso:country":"AU",
    "sg:address":"1/ 7 Ralph Black Drv",
    "sg:city":"Fairy Meadow",
    "sg:classifiers":[
        {
            "category":"Home & Garden",
            "subcategory":"Building Materials",
            "type":"Retail Goods"
        }
    ],
    "sg:phone":"+61 2 4225 1300",
    "sg:postcode":"2519",
    "sg:province":"NSW",
    "sg:tags":[
        "merchant",
        "glass",
        "glazier"
    ],
    "sg:website":"http://www.langsonglass.com.au",
    "wof:name":"Langson Glass Pty Ltd",
    "wof:placetype":"venue"
},
  "geometry": {"coordinates":[150.889267,-34.402676],"type":"Point"}
}