{
  "type": "Feature",
  "properties": {
    "iso:country":"AU",
    "sg:address":"Cnr Tebble & Darcy Sts",
    "sg:city":"Seymour",
    "sg:phone":"+61 3 5799 0133",
    "sg:postcode":"3660",
    "sg:province":"VIC",
    "wof:name":"Rural Tanks",
    "wof:placetype":"venue"
},
  "geometry": {"coordinates":[145.16995239299999,-37.0516166687],"type":"Point"}
}