{
  "type": "Feature",
  "properties": {
    "iso:country":"AU",
    "sg:address":"608 Laurie St",
    "sg:city":"Ballarat",
    "sg:classifiers":[
        {
            "category":"Wholesale",
            "subcategory":"Painting Supplies",
            "type":"Manufacturing & Wholesale Goods"
        }
    ],
    "sg:phone":"+61 3 5331 1581",
    "sg:postcode":"3350",
    "sg:province":"VIC",
    "sg:tags":[
        "product",
        "cleaning"
    ],
    "wof:name":"Dominant Home Products",
    "wof:placetype":"venue"
},
  "geometry": {"coordinates":[143.859695,-37.573105],"type":"Point"}
}