{
  "type": "Feature",
  "properties": {
    "addr:full":"Suite 1/ 247 Nolan St Unanderra NSW 2526",
    "addr:housenumber":"/ 247",
    "addr:postcode":"2526",
    "addr:street":"Nolan St",
    "iso:country":"AU",
    "sg:address":"Suite 1/ 247 Nolan St",
    "sg:city":"Unanderra",
    "sg:classifiers":[
        {
            "category":"Building & Trades",
            "subcategory":"Cleaning & Sanitation",
            "type":"Services"
        }
    ],
    "sg:phone":"+61 2 4271 5333",
    "sg:postcode":"2526",
    "sg:province":"NSW",
    "sg:tags":[
        "abrasive",
        "blasting"
    ],
    "wof:name":"Veolia Environmental Services",
    "wof:placetype":"venue"
},
  "geometry": {"coordinates":[150.843673706,-34.4636077881],"type":"Point"}
}