{
  "type": "Feature",
  "properties": {
    "iso:country":"AU",
    "sg:address":"23 Essington Lewis Ave",
    "sg:city":"Whyalla",
    "sg:classifiers":[
        {
            "category":"Travel",
            "subcategory":"Hotels & Motels",
            "type":"Entertainment"
        }
    ],
    "sg:phone":"+61 8 8644 2100",
    "sg:postcode":"5600",
    "sg:province":"SA",
    "wof:name":"Mirambeena Lodge Pty Ltd",
    "wof:placetype":"venue"
},
  "geometry": {"coordinates":[137.57588200000001,-33.034042],"type":"Point"}
}