{
  "type": "Feature",
  "properties": {
    "addr:full":"1 Whitbread St Taree NSW 2430",
    "addr:housenumber":"1",
    "addr:postcode":"2430",
    "addr:street":"Whitbread St",
    "iso:country":"AU",
    "sg:address":"1 Whitbread St",
    "sg:city":"Taree",
    "sg:classifiers":[
        {
            "category":"Manufacturing",
            "subcategory":"Retail Goods",
            "type":"Manufacturing & Wholesale Goods"
        }
    ],
    "sg:phone":"+61 2 6592 4755",
    "sg:postcode":"2430",
    "sg:province":"NSW",
    "sg:tags":[
        "merchant",
        "pump",
        "mfrs"
    ],
    "wof:name":"Town Plumbing Supplies",
    "wof:placetype":"venue"
},
  "geometry": {"coordinates":[152.45521500000001,-31.902821],"type":"Point"}
}