{
  "type": "Feature",
  "properties": {
    "addr:full":"4 Coombes Crt Rye VIC 3941",
    "addr:housenumber":"4",
    "addr:postcode":"3941",
    "addr:street":"Coombes Crt",
    "iso:country":"AU",
    "sg:address":"4 Coombes Crt",
    "sg:city":"Rye",
    "sg:classifiers":[
        {
            "category":"Shopping",
            "subcategory":"Computers & Home Electronics",
            "type":"Retail Goods"
        }
    ],
    "sg:phone":"+61 3 5985 1444",
    "sg:postcode":"3941",
    "sg:province":"VIC",
    "sg:tags":[
        "hardware",
        "equipment"
    ],
    "wof:name":"The Computer Surgeons",
    "wof:placetype":"venue"
},
  "geometry": {"coordinates":[144.82298278799999,-38.3770713806],"type":"Point"}
}