{
  "type": "Feature",
  "properties": {
    "addr:full":"54 Lipson St Port Adelaide SA 5015",
    "addr:housenumber":"54",
    "addr:postcode":"5015",
    "addr:street":"Lipson St",
    "iso:country":"AU",
    "sg:address":"54 Lipson St",
    "sg:city":"Port Adelaide",
    "sg:classifiers":[
        {
            "category":"Retail",
            "subcategory":"Auto Repair",
            "type":"Services"
        }
    ],
    "sg:phone":"+61 8 8400 7198",
    "sg:postcode":"5015",
    "sg:province":"SA",
    "sg:tags":[
        "beater",
        "painter",
        "panel"
    ],
    "wof:name":"Smiths Bodyshops",
    "wof:placetype":"venue"
},
  "geometry": {"coordinates":[138.50950622600001,-34.8480033875],"type":"Point"}
}