{
  "type": "Feature",
  "properties": {
    "addr:full":"6-8 Fryers St Shepparton VIC 3630",
    "addr:housenumber":"6-8",
    "addr:postcode":"3630",
    "addr:street":"Fryers St",
    "iso:country":"AU",
    "sg:address":"6-8 Fryers St",
    "sg:city":"Shepparton",
    "sg:classifiers":[
        {
            "category":"Professional",
            "subcategory":"Accounting & Tax Preparation",
            "type":"Services"
        }
    ],
    "sg:phone":"+61 3 5821 8114",
    "sg:postcode":"3630",
    "sg:province":"VIC",
    "sg:tags":[
        "consultant",
        "taxation"
    ],
    "wof:name":"H&R Block",
    "wof:placetype":"venue"
},
  "geometry": {"coordinates":[145.39874267600001,-36.3790512085],"type":"Point"}
}