{
  "type": "Feature",
  "properties": {
    "addr:full":"86 Darby St Cooks Hill NSW 2300",
    "addr:housenumber":"86",
    "addr:postcode":"2300",
    "addr:street":"Darby St",
    "iso:country":"AU",
    "sg:address":"86 Darby St",
    "sg:city":"Cooks Hill",
    "sg:classifiers":[
        {
            "category":"Real Estate",
            "subcategory":"Architect",
            "type":"Services"
        }
    ],
    "sg:phone":"+61 2 4929 7888",
    "sg:postcode":"2300",
    "sg:province":"NSW",
    "wof:name":"Schreiber Hamilton Architecture",
    "wof:placetype":"venue"
},
  "geometry": {"coordinates":[151.768585,-32.934654],"type":"Point"}
}