{
  "type": "Feature",
  "properties": {
    "addr:full":"68 Palmerin St Warwick QLD 4370",
    "addr:housenumber":"68",
    "addr:postcode":"4370",
    "addr:street":"Palmerin St",
    "iso:country":"AU",
    "sg:address":"68 Palmerin St",
    "sg:city":"Warwick",
    "sg:classifiers":[
        {
            "category":"Home & Garden",
            "subcategory":"Household Appliances",
            "type":"Retail Goods"
        }
    ],
    "sg:phone":"+61 7 4661 2222",
    "sg:postcode":"4370",
    "sg:province":"QLD",
    "sg:tags":[
        "equipment",
        "gas"
    ],
    "wof:name":"Warwick Heating & Cooling",
    "wof:placetype":"venue"
},
  "geometry": {"coordinates":[152.033004761,-28.2149124146],"type":"Point"}
}