{
  "type": "Feature",
  "properties": {
    "addr:full":"473 Forest Rd Bexley NSW 2207",
    "addr:housenumber":"473",
    "addr:postcode":"2207",
    "addr:street":"Forest Rd",
    "iso:country":"AU",
    "sg:address":"473 Forest Rd",
    "sg:city":"Bexley",
    "sg:classifiers":[
        {
            "category":"Health Services",
            "subcategory":"Health Practitioner",
            "type":"Services"
        }
    ],
    "sg:phone":"+61 2 9597 7969",
    "sg:postcode":"2207",
    "sg:province":"NSW",
    "sg:tags":[
        "naturopath"
    ],
    "wof:name":"Bexley Natural Therapies Centre",
    "wof:placetype":"venue"
},
  "geometry": {"coordinates":[151.12399300000001,-33.95192],"type":"Point"}
}