{
  "type": "Feature",
  "properties": {
    "addr:full":"7 Acacia St Moranbah QLD 4744",
    "addr:housenumber":"7",
    "addr:postcode":"4744",
    "addr:street":"Acacia St",
    "iso:country":"AU",
    "sg:address":"7 Acacia St",
    "sg:city":"Moranbah",
    "sg:classifiers":[
        {
            "category":"Building & Trades",
            "subcategory":"Construction",
            "type":"Services"
        }
    ],
    "sg:phone":"+61 7 4941 7807",
    "sg:postcode":"4744",
    "sg:province":"QLD",
    "sg:tags":[
        "earth",
        "excavating",
        "moving",
        "contractor"
    ],
    "wof:name":"Associated Plumbing Services",
    "wof:placetype":"venue"
},
  "geometry": {"coordinates":[148.036651611,-21.9937229156],"type":"Point"}
}