{
  "type": "Feature",
  "properties": {
    "addr:full":"Taylors Rd Aberfoyle Park SA 5159",
    "addr:postcode":"5159",
    "addr:street":"Taylors Rd",
    "iso:country":"AU",
    "sg:address":"Taylors Rd",
    "sg:city":"Aberfoyle Park",
    "sg:classifiers":[
        {
            "category":"Health Services",
            "subcategory":"Dentist",
            "type":"Services"
        }
    ],
    "sg:phone":"+61 8 8270 4911",
    "sg:postcode":"5159",
    "sg:province":"SA",
    "wof:name":"Waddell-Smith Iain",
    "wof:placetype":"venue"
},
  "geometry": {"coordinates":[138.591140747,-35.0733375549],"type":"Point"}
}