{
  "type": "Feature",
  "properties": {
    "addr:full":"PO Box 610 Moss Vale NSW 2577",
    "addr:postcode":"2577",
    "iso:country":"AU",
    "sg:address":"PO Box 610",
    "sg:city":"Moss Vale",
    "sg:classifiers":[
        {
            "category":"Real Estate",
            "subcategory":"Real Estate Services",
            "type":"Services"
        }
    ],
    "sg:phone":"+61 2 4878 9571",
    "sg:postcode":"2577",
    "sg:province":"NSW",
    "sg:tags":[
        "consultant",
        "property"
    ],
    "wof:name":"MC Building & Consultancy Pty Limited",
    "wof:placetype":"venue"
},
  "geometry": {"coordinates":[150.371170044,-34.5501289368],"type":"Point"}
}