{
  "type": "Feature",
  "properties": {
    "addr:full":"25 Bishop St Kelvin Grove QLD 4059",
    "addr:housenumber":"25",
    "addr:postcode":"4059",
    "addr:street":"Bishop St",
    "iso:country":"AU",
    "sg:address":"25 Bishop St",
    "sg:city":"Kelvin Grove",
    "sg:classifiers":[
        {
            "category":"Banks & Credit Unions",
            "subcategory":"Financial Services",
            "type":"Services"
        }
    ],
    "sg:phone":"+61 7 3356 0577",
    "sg:postcode":"4059",
    "sg:province":"QLD",
    "sg:tags":[
        "surge",
        "protection",
        "lightning"
    ],
    "wof:name":"Energy Correction Options Pty Ltd",
    "wof:placetype":"venue"
},
  "geometry": {"coordinates":[153.00885009800001,-27.4435176849],"type":"Point"}
}