{
  "type": "Feature",
  "properties": {
    "addr:full":"PO Box 3026 Norman Park QLD 4170",
    "addr:postcode":"4170",
    "iso:country":"AU",
    "sg:address":"PO Box 3026",
    "sg:city":"Norman Park",
    "sg:classifiers":[
        {
            "category":"Building & Trades",
            "subcategory":"Pest Control",
            "type":"Services"
        }
    ],
    "sg:phone":"+61 411 239 300",
    "sg:postcode":"4170",
    "sg:province":"QLD",
    "sg:tags":[
        "breastfeeding",
        "support"
    ],
    "wof:name":"Australian Lactation Consultants Association (QLD)",
    "wof:placetype":"venue"
},
  "geometry": {"coordinates":[153.05592346200001,-27.4741001129],"type":"Point"}
}