{
  "type": "Feature",
  "properties": {
    "addr:full":"73 Stirling St Perth WA 6001",
    "addr:housenumber":"73",
    "addr:postcode":"6001",
    "addr:street":"Stirling St",
    "iso:country":"AU",
    "sg:address":"73 Stirling St",
    "sg:city":"Perth",
    "sg:classifiers":[
        {
            "category":"Building & Trades",
            "subcategory":"Pest Control",
            "type":"Services"
        }
    ],
    "sg:phone":"+61 1800 230 125",
    "sg:postcode":"6001",
    "sg:province":"WA",
    "sg:tags":[
        "breastfeeding",
        "support"
    ],
    "wof:name":"Breast Feeding Support WA",
    "wof:placetype":"venue"
},
  "geometry": {"coordinates":[115.863831,-31.949686],"type":"Point"}
}