{
  "type": "Feature",
  "properties": {
    "addr:full":"Unit 3 Cottelsloe Chambers 136 Railway St Cottesloe WA 6011",
    "addr:housenumber":"136",
    "addr:postcode":"6011",
    "addr:street":"Railway St",
    "iso:country":"AU",
    "sg:address":"Unit 3 Cottelsloe Chambers 136 Railway St",
    "sg:city":"Cottesloe",
    "sg:classifiers":[
        {
            "category":"Health Services",
            "subcategory":"Doctor",
            "type":"Services"
        }
    ],
    "sg:phone":"+61 8 9384 7403",
    "sg:postcode":"6011",
    "sg:province":"WA",
    "sg:tags":[
        "podiatrist"
    ],
    "wof:name":"Adrian Davis",
    "wof:placetype":"venue"
},
  "geometry": {"coordinates":[115.765052795,-31.9881248474],"type":"Point"}
}