{
  "type": "Feature",
  "properties": {
    "addr:full":"PO Box 6632 Cairns QLD 4870",
    "addr:postcode":"4870",
    "iso:country":"AU",
    "sg:address":"PO Box 6632",
    "sg:city":"Cairns",
    "sg:classifiers":[
        {
            "category":"Social Services",
            "subcategory":"Child Care",
            "type":"Services"
        }
    ],
    "sg:phone":"+61 7 4041 9544",
    "sg:postcode":"4870",
    "sg:province":"QLD",
    "wof:name":"Hedley Childcare & Education Centres Pty Ltd",
    "wof:placetype":"venue"
},
  "geometry": {"coordinates":[145.66958618199999,-17.0185699463],"type":"Point"}
}