{
  "type": "Feature",
  "properties": {
    "addr:full":"Mackay Entertainment & Convention Centre Mackay QLD 4740",
    "addr:postcode":"4740",
    "iso:country":"AU",
    "sg:address":"Mackay Entertainment & Convention Centre",
    "sg:city":"Mackay",
    "sg:classifiers":[
        {
            "category":"Conference Center",
            "type":"Public Place"
        }
    ],
    "sg:phone":"+61 7 4942 9563",
    "sg:postcode":"4740",
    "sg:province":"QLD",
    "sg:tags":[
        "venue",
        "convention"
    ],
    "wof:name":"Grinders Corporate Catering",
    "wof:placetype":"venue"
},
  "geometry": {"coordinates":[149.17022700000001,-21.102386],"type":"Point"}
}