{
  "type": "Feature",
  "properties": {
    "addr:full":"300 Commercial Rd Port Adelaide SA 5015",
    "addr:housenumber":"300",
    "addr:postcode":"5015",
    "addr:street":"Commercial Rd",
    "iso:country":"AU",
    "sg:address":"300 Commercial Rd",
    "sg:city":"Port Adelaide",
    "sg:classifiers":[
        {
            "category":"Shopping",
            "subcategory":"Mobile Phones",
            "type":"Retail Goods"
        }
    ],
    "sg:phone":"+61 8 8241 1500",
    "sg:postcode":"5015",
    "sg:province":"SA",
    "sg:tags":[
        "telephone",
        "accessory"
    ],
    "wof:name":"Phone Xpress",
    "wof:placetype":"venue"
},
  "geometry": {"coordinates":[138.50889587399999,-34.8509254456],"type":"Point"}
}