{
  "type": "Feature",
  "properties": {
    "addr:full":"5 Shiel St North Melbourne VIC 3051",
    "addr:housenumber":"5",
    "addr:postcode":"3051",
    "addr:street":"Shiel St",
    "iso:country":"AU",
    "sg:address":"5 Shiel St",
    "sg:city":"North Melbourne",
    "sg:classifiers":[
        {
            "category":"Retail",
            "subcategory":"Auto Repair",
            "type":"Services"
        }
    ],
    "sg:phone":"+61 3 9328 3223",
    "sg:postcode":"3051",
    "sg:province":"VIC",
    "sg:tags":[
        "beater",
        "painter",
        "panel"
    ],
    "wof:name":"Woods Accident Repair Centres",
    "wof:placetype":"venue"
},
  "geometry": {"coordinates":[144.94392395,-37.7979545593],"type":"Point"}
}