{
  "type": "Feature",
  "properties": {
    "iso:country":"AU",
    "sg:address":"9/58 64 cook St",
    "sg:city":"Kurnell",
    "sg:classifiers":[
        {
            "category":"Professional",
            "subcategory":"Engineering",
            "type":"Services"
        }
    ],
    "sg:phone":"+61 2 9668 8800",
    "sg:postcode":"2231",
    "sg:province":"NSW",
    "sg:tags":[
        "engineer"
    ],
    "wof:name":"J & E Engineering",
    "wof:placetype":"venue"
},
  "geometry": {"coordinates":[151.21539306599999,-34.0116348267],"type":"Point"}
}