{
  "type": "Feature",
  "properties": {
    "addr:full":"Dry St Boorowa NSW 2586",
    "addr:postcode":"2586",
    "addr:street":"Dry St",
    "iso:country":"AU",
    "sg:address":"Dry St",
    "sg:city":"Boorowa",
    "sg:classifiers":[
        {
            "category":"Organizations",
            "subcategory":"Non-profit Organization",
            "type":"Services"
        }
    ],
    "sg:phone":"+61 2 6385 3004",
    "sg:postcode":"2586",
    "sg:province":"NSW",
    "sg:tags":[
        "support",
        "disability",
        "organisation"
    ],
    "wof:name":"Boorowa Community Transport",
    "wof:placetype":"venue"
},
  "geometry": {"coordinates":[148.72764587399999,-34.4352531433],"type":"Point"}
}