{
  "type": "Feature",
  "properties": {
    "addr:full":"63 Davis St Kew VIC 3101",
    "addr:housenumber":"63",
    "addr:postcode":"3101",
    "addr:street":"Davis St",
    "iso:country":"AU",
    "sg:address":"63 Davis St",
    "sg:city":"Kew",
    "sg:classifiers":[
        {
            "category":"Shopping",
            "subcategory":"Computers & Home Electronics",
            "type":"Retail Goods"
        }
    ],
    "sg:phone":"+61 3 9817 7099",
    "sg:postcode":"3101",
    "sg:province":"VIC",
    "sg:tags":[
        "equipment",
        "multimedia"
    ],
    "wof:name":"World Wide Interactive Group Pty Ltd",
    "wof:placetype":"venue"
},
  "geometry": {"coordinates":[145.04646301299999,-37.8100585938],"type":"Point"}
}