{
  "type": "Feature",
  "properties": {
    "addr:full":"6 Nelson St Ferntree Gully VIC 3156",
    "addr:housenumber":"6",
    "addr:postcode":"3156",
    "addr:street":"Nelson St",
    "iso:country":"AU",
    "sg:address":"6 Nelson St",
    "sg:city":"Ferntree Gully",
    "sg:classifiers":[
        {
            "category":"Building & Trades",
            "subcategory":"Cleaning & Sanitation",
            "type":"Services"
        }
    ],
    "sg:phone":"+61 3 9729 4827",
    "sg:postcode":"3156",
    "sg:province":"VIC",
    "sg:tags":[
        "chemical",
        "pressure",
        "steam",
        "contractor"
    ],
    "wof:name":"H & B Steam Cleaning Service",
    "wof:placetype":"venue"
},
  "geometry": {"coordinates":[145.29281616200001,-37.8988075256],"type":"Point"}
}