{
  "type": "Feature",
  "properties": {
    "addr:full":"12 Hinton St North Rockhampton QLD 4701",
    "addr:housenumber":"12",
    "addr:postcode":"4701",
    "addr:street":"Hinton St North",
    "iso:country":"AU",
    "sg:address":"12 Hinton St",
    "sg:city":"North Rockhampton",
    "sg:classifiers":[
        {
            "category":"Building & Trades",
            "subcategory":"Construction",
            "type":"Services"
        }
    ],
    "sg:phone":"+61 7 4926 1740",
    "sg:postcode":"4701",
    "sg:province":"QLD",
    "sg:tags":[
        "contractor"
    ],
    "wof:name":"Jenkins John",
    "wof:placetype":"venue"
},
  "geometry": {"coordinates":[150.54354858400001,-23.3595561981],"type":"Point"}
}