{
  "type": "Feature",
  "properties": {
    "iso:country":"AU",
    "sg:address":"Shp33/ 56 Glen St",
    "sg:city":"Belrose",
    "sg:classifiers":[
        {
            "category":"Shopping",
            "subcategory":"Clothing, Apparel, & Fashions",
            "type":"Retail Goods"
        }
    ],
    "sg:phone":"+61 2 9453 5002",
    "sg:postcode":"2085",
    "sg:province":"NSW",
    "sg:tags":[
        "lady",
        "wear"
    ],
    "wof:name":"Springfields Designer Labels On Sale",
    "wof:placetype":"venue"
},
  "geometry": {"coordinates":[151.212234497,-33.7392311096],"type":"Point"}
}