{
  "type": "Feature",
  "properties": {
    "addr:full":"Skylight Arcade Shop 3 17-19 Wallace St Macksville NSW 2447",
    "addr:housenumber":"3 17-19",
    "addr:postcode":"2447",
    "addr:street":"Wallace St",
    "iso:country":"AU",
    "sg:address":"Skylight Arcade Shop 3 17-19 Wallace St",
    "sg:city":"Macksville",
    "sg:classifiers":[
        {
            "category":"Personal",
            "subcategory":"Beauty Salon",
            "type":"Services"
        }
    ],
    "sg:phone":"+61 2 6568 4110",
    "sg:postcode":"2447",
    "sg:province":"NSW",
    "sg:tags":[
        "hairdresser"
    ],
    "wof:name":"Twin Scissors - Tanya",
    "wof:placetype":"venue"
},
  "geometry": {"coordinates":[152.91961699999999,-30.707092],"type":"Point"}
}