{
  "type": "Feature",
  "properties": {
    "addr:full":"Unit 21, 76 Hume Hwy Lansvale NSW 2166",
    "addr:housenumber":"76",
    "addr:postcode":"2166",
    "addr:street":"Hume Hwy",
    "iso:country":"AU",
    "sg:address":"Unit 21, 76 Hume Hwy",
    "sg:city":"Lansvale",
    "sg:classifiers":[
        {
            "category":"Manufacturing",
            "subcategory":"Furniture",
            "type":"Manufacturing & Wholesale Goods"
        }
    ],
    "sg:phone":"+61 2 9728 2158",
    "sg:postcode":"2166",
    "sg:province":"NSW",
    "sg:tags":[
        "builder",
        "designer",
        "custom"
    ],
    "wof:name":"Maison Paul Furniture Designs Pty Ltd",
    "wof:placetype":"venue"
},
  "geometry": {"coordinates":[150.96356201200001,-33.8922767639],"type":"Point"}
}