{
  "type": "Feature",
  "properties": {
    "addr:full":"265 Earnshaw Rd Northgate QLD 4013",
    "addr:housenumber":"265",
    "addr:postcode":"4013",
    "addr:street":"Earnshaw Rd",
    "iso:country":"AU",
    "sg:address":"265 Earnshaw Rd",
    "sg:city":"Northgate",
    "sg:classifiers":[
        {
            "category":"Retail",
            "subcategory":"Auto Repair",
            "type":"Services"
        }
    ],
    "sg:phone":"+61 7 3266 8527",
    "sg:postcode":"4013",
    "sg:province":"QLD",
    "sg:tags":[
        "electrical"
    ],
    "wof:name":"Absolute Auto Electrical",
    "wof:placetype":"venue"
},
  "geometry": {"coordinates":[153.07327270499999,-27.385219574],"type":"Point"}
}