{
  "type": "Feature",
  "properties": {
    "iso:country":"AU",
    "sg:address":"U4/ 133 Keen St",
    "sg:city":"Lismore",
    "sg:classifiers":[
        {
            "category":"Professional",
            "subcategory":"Computer Services",
            "type":"Services"
        }
    ],
    "sg:phone":"+61 2 8875 7948",
    "sg:postcode":"2480",
    "sg:province":"NSW",
    "sg:tags":[
        "consultant",
        "system"
    ],
    "wof:name":"Earth Science Information Systems",
    "wof:placetype":"venue"
},
  "geometry": {"coordinates":[153.27825927699999,-28.8096084595],"type":"Point"}
}