{
  "type": "Feature",
  "properties": {
    "iso:country":"AU",
    "sg:address":"7 Chartwell St",
    "sg:city":"Margate",
    "sg:classifiers":[
        {
            "category":"Professional",
            "subcategory":"Art Services",
            "type":"Services"
        }
    ],
    "sg:phone":"+61 403 308 192",
    "sg:postcode":"4019",
    "sg:province":"QLD",
    "sg:tags":[
        "decorator",
        "painter"
    ],
    "wof:name":"Jim & Mark Stewart",
    "wof:placetype":"venue"
},
  "geometry": {"coordinates":[153.096755981,-27.2373466492],"type":"Point"}
}