{
  "type": "Feature",
  "properties": {
    "addr:full":"1 Yarra St Warrandyte VIC 3113",
    "addr:housenumber":"1",
    "addr:postcode":"3113",
    "addr:street":"Yarra St",
    "iso:country":"AU",
    "sg:address":"1 Yarra St",
    "sg:city":"Warrandyte",
    "sg:classifiers":[
        {
            "category":"Professional",
            "subcategory":"Engineering",
            "type":"Services"
        }
    ],
    "sg:phone":"+61 3 9844 2069",
    "sg:postcode":"3113",
    "sg:province":"VIC",
    "sg:tags":[
        "engineer"
    ],
    "wof:name":"Bird Engineering",
    "wof:placetype":"venue"
},
  "geometry": {"coordinates":[145.20989990199999,-37.7470932007],"type":"Point"}
}