{
  "type": "Feature",
  "properties": {
    "addr:full":"98 Stanleys Rd Red Hill South VIC 3937",
    "addr:housenumber":"98",
    "addr:postcode":"3937",
    "addr:street":"Stanleys Rd",
    "iso:country":"AU",
    "sg:address":"98 Stanleys Rd",
    "sg:city":"Red Hill South",
    "sg:classifiers":[
        {
            "category":"Farming",
            "subcategory":"Vineyard",
            "type":"Manufacturing & Wholesale Goods"
        }
    ],
    "sg:phone":"+61 3 5989 2646",
    "sg:postcode":"3937",
    "sg:province":"VIC",
    "sg:tags":[
        "winery"
    ],
    "wof:name":"Wildcroft Estate",
    "wof:placetype":"venue"
},
  "geometry": {"coordinates":[145.054199219,-38.3738632202],"type":"Point"}
}