{
  "type": "Feature",
  "properties": {
    "addr:full":"33 Barringer St Conder ACT 2906",
    "addr:housenumber":"33",
    "addr:postcode":"2906",
    "addr:street":"Barringer St",
    "iso:country":"AU",
    "sg:address":"33 Barringer St",
    "sg:city":"Conder",
    "sg:classifiers":[
        {
            "category":"Building & Trades",
            "subcategory":"Construction",
            "type":"Services"
        }
    ],
    "sg:phone":"+61 2 6294 5665",
    "sg:postcode":"2906",
    "sg:province":"ACT",
    "sg:tags":[
        "pool",
        "swimming"
    ],
    "wof:name":"Brindabella Pools",
    "wof:placetype":"venue"
},
  "geometry": {"coordinates":[149.109283447,-35.4621162415],"type":"Point"}
}