{
  "type": "Feature",
  "properties": {
    "addr:full":"Cnr Creswick Rd & Norman St Ballarat VIC 3350",
    "addr:postcode":"3350",
    "addr:street":"Cnr Creswick Rd & Norman St",
    "iso:country":"AU",
    "sg:address":"Cnr Creswick Rd & Norman St",
    "sg:city":"Ballarat",
    "sg:classifiers":[
        {
            "category":"Structure",
            "subcategory":"Bridge",
            "type":"Public Place"
        }
    ],
    "sg:phone":"+61 3 5339 8113",
    "sg:postcode":"3350",
    "sg:province":"VIC",
    "sg:tags":[
        "chainsaw",
        "brushcutters"
    ],
    "wof:name":"Ballarat Mowers & Chainsaws",
    "wof:placetype":"venue"
},
  "geometry": {"coordinates":[143.85502600000001,-37.557148],"type":"Point"}
}