{
  "type": "Feature",
  "properties": {
    "addr:full":"395 Albert St Brunswick VIC 3056",
    "addr:housenumber":"395",
    "addr:postcode":"3056",
    "addr:street":"Albert St",
    "iso:country":"AU",
    "sg:address":"395 Albert St",
    "sg:city":"Brunswick",
    "sg:classifiers":[
        {
            "category":"Building & Trades",
            "subcategory":"Plumbing",
            "type":"Services"
        }
    ],
    "sg:phone":"+61 3 9387 1799",
    "sg:postcode":"3056",
    "sg:province":"VIC",
    "sg:tags":[
        "equipment",
        "valves"
    ],
    "wof:name":"Valve-Tech Engineering",
    "wof:placetype":"venue"
},
  "geometry": {"coordinates":[144.953369141,-37.7676200867],"type":"Point"}
}