{
  "type": "Feature",
  "properties": {
    "iso:country":"AU",
    "sg:address":"29 Laurie St",
    "sg:city":"Newport",
    "sg:classifiers":[
        {
            "category":"Professional",
            "subcategory":"Employment Agencies",
            "type":"Services"
        }
    ],
    "sg:phone":"+61 412 545 570",
    "sg:postcode":"3015",
    "sg:province":"VIC",
    "sg:tags":[
        "provider",
        "internet"
    ],
    "wof:name":"Cybersyte",
    "wof:placetype":"venue"
},
  "geometry": {"coordinates":[144.870483398,-37.8427314758],"type":"Point"}
}