{
  "type": "Feature",
  "properties": {
    "iso:country":"AU",
    "sg:address":"34a Park Ave",
    "sg:city":"Waitara",
    "sg:classifiers":[
        {
            "category":"Professional",
            "subcategory":"Engineering",
            "type":"Services"
        }
    ],
    "sg:phone":"+61 2 9489 8850",
    "sg:postcode":"2077",
    "sg:province":"NSW",
    "sg:tags":[
        "consulting",
        "engineer"
    ],
    "wof:name":"Edwards Traffic Consulting",
    "wof:placetype":"venue"
},
  "geometry": {"coordinates":[151.107620239,-33.7073173523],"type":"Point"}
}