{
  "type": "Feature",
  "properties": {
    "iso:country":"AU",
    "sg:address":"PO Box 7111",
    "sg:city":"Beaumaris",
    "sg:classifiers":[
        {
            "category":"Wholesale",
            "subcategory":"Auto Parts",
            "type":"Manufacturing & Wholesale Goods"
        }
    ],
    "sg:phone":"+61 3 9589 6888",
    "sg:postcode":"3193",
    "sg:province":"VIC",
    "sg:tags":[
        "watch"
    ],
    "wof:name":"ESGE Asia Pacific Pty Ltd",
    "wof:placetype":"venue"
},
  "geometry": {"coordinates":[145.05137634299999,-37.9860687256],"type":"Point"}
}