{
  "type": "Feature",
  "properties": {
    "iso:country":"AU",
    "sg:address":"Fair View 190 Cape Hawke Drv",
    "sg:city":"Forster",
    "sg:classifiers":[
        {
            "category":"Building & Trades",
            "subcategory":"Landscaping Services",
            "type":"Services"
        }
    ],
    "sg:phone":"+61 2 6554 6353",
    "sg:postcode":"2428",
    "sg:province":"NSW",
    "sg:tags":[
        "grazier"
    ],
    "wof:name":"McBride A F & E F",
    "wof:placetype":"venue"
},
  "geometry": {"coordinates":[152.53410299999999,-32.213398],"type":"Point"}
}