{
  "type": "Feature",
  "properties": {
    "iso:country":"AU",
    "sg:address":"790 Burwood Rd",
    "sg:city":"Hawthorn East",
    "sg:classifiers":[
        {
            "category":"Health Services",
            "subcategory":"Doctor",
            "type":"Services"
        }
    ],
    "sg:phone":"+61 3 9813 1144",
    "sg:postcode":"3123",
    "sg:province":"VIC",
    "sg:tags":[
        "medical",
        "practitioner"
    ],
    "wof:name":"Piperoglou Michael V",
    "wof:placetype":"venue"
},
  "geometry": {"coordinates":[145.05715942399999,-37.8253593445],"type":"Point"}
}