{
  "type": "Feature",
  "properties": {
    "addr:full":"Unit 1, 30 Walters Drv Osborne Park WA 6017",
    "addr:housenumber":"30",
    "addr:postcode":"6017",
    "addr:street":"Walters Drv",
    "iso:country":"AU",
    "sg:address":"Unit 1, 30 Walters Drv",
    "sg:city":"Osborne Park",
    "sg:classifiers":[
        {
            "category":"Communications",
            "type":"Services"
        }
    ],
    "sg:phone":"+61 8 9242 8344",
    "sg:postcode":"6017",
    "sg:province":"WA",
    "sg:tags":[
        "equipment",
        "radio"
    ],
    "sg:website":"http://www.tellusradio.com.au",
    "wof:name":"Tellus Radio",
    "wof:placetype":"venue"
},
  "geometry": {"coordinates":[115.80940246599999,-31.9097328186],"type":"Point"}
}