{
  "type": "Feature",
  "properties": {
    "addr:full":"12 Petrana Pl Henley Brook WA 6055",
    "addr:housenumber":"12",
    "addr:postcode":"6055",
    "addr:street":"Petrana Pl Henley",
    "iso:country":"AU",
    "sg:address":"12 Petrana Pl",
    "sg:city":"Henley Brook",
    "sg:classifiers":[
        {
            "category":"Organizations",
            "subcategory":"Membership Organization",
            "type":"Services"
        }
    ],
    "sg:phone":"+61 8 9296 0576",
    "sg:postcode":"6055",
    "sg:province":"WA",
    "sg:tags":[
        "club",
        "car"
    ],
    "wof:name":"Mini Owners Club Of WA Inc",
    "wof:placetype":"venue"
},
  "geometry": {"coordinates":[115.96736900000001,-31.798031],"type":"Point"}
}