{
  "type": "Feature",
  "properties": {
    "addr:full":"Specialist Medical Centre 2, Excelsior Pde Toronto NSW 2283",
    "addr:housenumber":"2",
    "addr:postcode":"2283",
    "addr:street":"Excelsior Pde",
    "iso:country":"AU",
    "sg:address":"Specialist Medical Centre 2, Excelsior Pde",
    "sg:city":"Toronto",
    "sg:classifiers":[
        {
            "category":"Health Services",
            "subcategory":"Health Practitioner",
            "type":"Services"
        }
    ],
    "sg:phone":"+61 2 4959 2111",
    "sg:postcode":"2283",
    "sg:province":"NSW",
    "sg:tags":[
        "physiotherapist"
    ],
    "wof:name":"Gonano Frank",
    "wof:placetype":"venue"
},
  "geometry": {"coordinates":[151.59608459500001,-33.0163078308],"type":"Point"}
}