{
  "type": "Feature",
  "properties": {
    "iso:country":"AU",
    "sg:address":"100 Church St",
    "sg:city":"Parramatta",
    "sg:classifiers":[
        {
            "category":"Sports & Exercise",
            "subcategory":"Gym",
            "type":"Entertainment"
        }
    ],
    "sg:phone":"+61 2 9687 1233",
    "sg:postcode":"2150",
    "sg:province":"NSW",
    "sg:tags":[
        "health",
        "fitness"
    ],
    "wof:name":"Ladies Sanctuary",
    "wof:placetype":"venue"
},
  "geometry": {"coordinates":[151.044433594,-33.8630256653],"type":"Point"}
}