{
  "type": "Feature",
  "properties": {
    "addr:full":"Woff St Sunnybank QLD 4109",
    "addr:postcode":"4109",
    "addr:street":"St",
    "iso:country":"AU",
    "sg:address":"Woff St",
    "sg:city":"Sunnybank",
    "sg:classifiers":[
        {
            "category":"Arena",
            "subcategory":"Sports Club",
            "type":"Entertainment"
        }
    ],
    "sg:phone":"+61 7 3345 6320",
    "sg:postcode":"4109",
    "sg:province":"QLD",
    "sg:tags":[
        "league",
        "rugby"
    ],
    "wof:name":"South Sunnybank Rugby League Club",
    "wof:placetype":"venue"
},
  "geometry": {"coordinates":[153.05816650400001,-27.5810089111],"type":"Point"}
}