{
  "type": "Feature",
  "properties": {
    "addr:full":"17 Bromley Rd Emu Plains NSW 2750",
    "addr:housenumber":"17",
    "addr:postcode":"2750",
    "addr:street":"Bromley Rd",
    "iso:country":"AU",
    "sg:address":"17 Bromley Rd",
    "sg:city":"Emu Plains",
    "sg:classifiers":[
        {
            "category":"Professional",
            "type":"Services"
        }
    ],
    "sg:phone":"+61 2 4735 4011",
    "sg:postcode":"2750",
    "sg:province":"NSW",
    "sg:tags":[
        "packaging",
        "filling",
        "assembling"
    ],
    "wof:name":"P & R Packaging",
    "wof:placetype":"venue"
},
  "geometry": {"coordinates":[150.64923095699999,-33.7438545227],"type":"Point"}
}