{
  "type": "Feature",
  "properties": {
    "iso:country":"AU",
    "sg:address":"No 18",
    "sg:city":"Wperfeld Cct Caroline Springs",
    "sg:classifiers":[
        {
            "category":"Building & Trades",
            "subcategory":"Cleaning & Sanitation",
            "type":"Services"
        }
    ],
    "sg:phone":"+61 418 554 455",
    "sg:postcode":"3023",
    "sg:province":"VIC",
    "sg:tags":[
        "industrial",
        "commercial",
        "contractor"
    ],
    "wof:name":"Aamys Cleaning Service",
    "wof:placetype":"venue"
},
  "geometry": {"coordinates":[144.735199,-37.744961],"type":"Point"}
}