{
  "type": "Feature",
  "properties": {
    "addr:full":"PO Box 106 Palmyra WA 6157",
    "addr:postcode":"6157",
    "iso:country":"AU",
    "sg:address":"PO Box 106",
    "sg:city":"Palmyra",
    "sg:classifiers":[
        {
            "category":"Health Services",
            "subcategory":"Doctor",
            "type":"Services"
        }
    ],
    "sg:phone":"+61 8 9430 4377",
    "sg:postcode":"6157",
    "sg:province":"WA",
    "sg:tags":[
        "occupational",
        "safety"
    ],
    "wof:name":"Emergency Support Network",
    "wof:placetype":"venue"
},
  "geometry": {"coordinates":[115.779427,-32.041969],"type":"Point"}
}