{
  "type": "Feature",
  "properties": {
    "addr:full":"5 Brougham Ave Fennell Bay NSW 2283",
    "addr:housenumber":"5",
    "addr:postcode":"2283",
    "addr:street":"Brougham Ave",
    "iso:country":"AU",
    "sg:address":"5 Brougham Ave",
    "sg:city":"Fennell Bay",
    "sg:classifiers":[
        {
            "category":"Autos & Motor Vehicles",
            "subcategory":"Boat Sales",
            "type":"Retail Goods"
        }
    ],
    "sg:phone":"+61 2 4975 3999",
    "sg:postcode":"2283",
    "sg:province":"NSW",
    "sg:tags":[
        "builder",
        "yacht",
        "repairer"
    ],
    "wof:name":"Gravity Downs Marine Service",
    "wof:placetype":"venue"
},
  "geometry": {"coordinates":[151.59362793,-32.9907112122],"type":"Point"}
}