{
  "type": "Feature",
  "properties": {
    "iso:country":"AU",
    "sg:address":"80 Moore St",
    "sg:city":"Liverpool",
    "sg:classifiers":[
        {
            "category":"Fast Food",
            "type":"Food & Drink"
        }
    ],
    "sg:phone":"+61 2 9602 7807",
    "sg:postcode":"2170",
    "sg:province":"NSW",
    "sg:tags":[
        "away",
        "take"
    ],
    "wof:name":"Quality Snacks",
    "wof:placetype":"venue"
},
  "geometry": {"coordinates":[150.92364501899999,-33.9223442078],"type":"Point"}
}