{
  "type": "Feature",
  "properties": {
    "addr:full":"28 William St Gosford NSW 2250",
    "addr:housenumber":"28",
    "addr:postcode":"2250",
    "addr:street":"William St",
    "iso:country":"AU",
    "sg:address":"28 William St",
    "sg:city":"Gosford",
    "sg:classifiers":[
        {
            "category":"Shopping",
            "subcategory":"Jewelry",
            "type":"Retail Goods"
        }
    ],
    "sg:phone":"+61 2 4321 0707",
    "sg:postcode":"2250",
    "sg:province":"NSW",
    "sg:tags":[
        "jeweller"
    ],
    "wof:name":"Milagras Shop",
    "wof:placetype":"venue"
},
  "geometry": {"coordinates":[151.343505859,-33.4260940552],"type":"Point"}
}