{
  "type": "Feature",
  "properties": {
    "iso:country":"AU",
    "sg:address":"473 Ruthven St",
    "sg:city":"Toowoomba",
    "sg:classifiers":[
        {
            "category":"Shopping",
            "subcategory":"Crafts & Fabrics",
            "type":"Retail Goods"
        }
    ],
    "sg:phone":"+61 7 4632 1358",
    "sg:postcode":"4350",
    "sg:province":"QLD",
    "sg:tags":[
        "material",
        "dress"
    ],
    "wof:name":"Sabas",
    "wof:placetype":"venue"
},
  "geometry": {"coordinates":[151.952301,-27.56818],"type":"Point"}
}