{
  "type": "Feature",
  "properties": {
    "addr:full":"9 Throsby St Moss Vale NSW 2577",
    "addr:housenumber":"9",
    "addr:postcode":"2577",
    "addr:street":"Throsby St",
    "iso:country":"AU",
    "sg:address":"9 Throsby St",
    "sg:city":"Moss Vale",
    "sg:classifiers":[
        {
            "category":"Building & Trades",
            "subcategory":"Construction",
            "type":"Services"
        }
    ],
    "sg:phone":"+61 2 4868 1173",
    "sg:postcode":"2577",
    "sg:province":"NSW",
    "sg:tags":[
        "ceiling"
    ],
    "wof:name":"Parsons T B & K L",
    "wof:placetype":"venue"
},
  "geometry": {"coordinates":[150.370193481,-34.5521240234],"type":"Point"}
}