{
  "type": "Feature",
  "properties": {
    "addr:full":"84 Main St Proserpine QLD 4800",
    "addr:housenumber":"84",
    "addr:postcode":"4800",
    "addr:street":"Main St",
    "iso:country":"AU",
    "sg:address":"84 Main St",
    "sg:city":"Proserpine",
    "sg:classifiers":[
        {
            "category":"Banks & Credit Unions",
            "subcategory":"Bank",
            "type":"Services"
        }
    ],
    "sg:phone":"+61 13 20 32",
    "sg:postcode":"4800",
    "sg:province":"QLD",
    "wof:name":"Westpac",
    "wof:placetype":"venue"
},
  "geometry": {"coordinates":[148.58334350600001,-20.4019069672],"type":"Point"}
}