{
  "type": "Feature",
  "properties": {
    "addr:full":"1a Lindfield Ave Lindfield NSW 2070",
    "addr:housenumber":"1a",
    "addr:postcode":"2070",
    "addr:street":"Lindfield Ave",
    "iso:country":"AU",
    "sg:address":"1a Lindfield Ave",
    "sg:city":"Lindfield",
    "sg:classifiers":[
        {
            "category":"Arts & Performance",
            "subcategory":"Dance",
            "type":"Entertainment"
        }
    ],
    "sg:phone":"+61 412 100 537",
    "sg:postcode":"2070",
    "sg:province":"NSW",
    "sg:tags":[
        "theatrical",
        "ballet",
        "tuition"
    ],
    "wof:name":"The Jazz Factory",
    "wof:placetype":"venue"
},
  "geometry": {"coordinates":[151.16966247600001,-33.7753410339],"type":"Point"}
}