{
  "type": "Feature",
  "properties": {
    "addr:full":"42 McCauley St Matraville NSW 2036",
    "addr:housenumber":"42",
    "addr:postcode":"2036",
    "addr:street":"Mccauley St",
    "iso:country":"AU",
    "sg:address":"42 McCauley St",
    "sg:city":"Matraville",
    "sg:classifiers":[
        {
            "category":"Home & Garden",
            "subcategory":"Building Materials",
            "type":"Retail Goods"
        }
    ],
    "sg:phone":"+61 403 164 924",
    "sg:postcode":"2036",
    "sg:province":"NSW",
    "sg:tags":[
        "supply"
    ],
    "wof:name":"Pro-Panel Building Products",
    "wof:placetype":"venue"
},
  "geometry": {"coordinates":[151.221801758,-33.9632759094],"type":"Point"}
}