{
  "type": "Feature",
  "properties": {
    "addr:full":"660 Main Rd Eltham VIC 3095",
    "addr:housenumber":"660",
    "addr:postcode":"3095",
    "addr:street":"Main Rd",
    "iso:country":"AU",
    "sg:address":"660 Main Rd",
    "sg:city":"Eltham",
    "sg:classifiers":[
        {
            "category":"Health Services",
            "subcategory":"Doctor",
            "type":"Services"
        }
    ],
    "sg:phone":"+61 3 9439 8660",
    "sg:postcode":"3095",
    "sg:province":"VIC",
    "sg:tags":[
        "podiatrist"
    ],
    "wof:name":"Cotsanis George",
    "wof:placetype":"venue"
},
  "geometry": {"coordinates":[145.13768005399999,-37.7198829651],"type":"Point"}
}