{
  "type": "Feature",
  "properties": {
    "addr:full":"1 Central Ave Thornleigh NSW 2120",
    "addr:housenumber":"1",
    "addr:postcode":"2120",
    "addr:street":"Central Ave",
    "iso:country":"AU",
    "sg:address":"1 Central Ave",
    "sg:city":"Thornleigh",
    "sg:classifiers":[
        {
            "category":"Building & Trades",
            "subcategory":"Construction",
            "type":"Services"
        }
    ],
    "sg:phone":"+61 2 9875 3043",
    "sg:postcode":"2120",
    "sg:province":"NSW",
    "sg:tags":[
        "pool",
        "swimming"
    ],
    "wof:name":"Commercial & Municipal Pool Services Pty Ltd",
    "wof:placetype":"venue"
},
  "geometry": {"coordinates":[151.08065795900001,-33.7302398682],"type":"Point"}
}