{
  "type": "Feature",
  "properties": {
    "iso:country":"AU",
    "sg:address":"107 Unley Rd",
    "sg:city":"Unley",
    "sg:classifiers":[
        {
            "category":"Shopping",
            "subcategory":"Antiques",
            "type":"Retail Goods"
        }
    ],
    "sg:phone":"+61 8 8272 3772",
    "sg:postcode":"5061",
    "sg:province":"SA",
    "wof:name":"Moghul Antiques",
    "wof:placetype":"venue"
},
  "geometry": {"coordinates":[138.607421875,-34.9478645325],"type":"Point"}
}