{
  "type": "Feature",
  "properties": {
    "iso:country":"AU",
    "sg:address":"4 Titan Crt",
    "sg:city":"Lavington",
    "sg:classifiers":[
        {
            "category":"Utilities",
            "subcategory":"Electric",
            "type":"Services"
        }
    ],
    "sg:phone":"+61 412 578 223",
    "sg:postcode":"2641",
    "sg:province":"NSW",
    "sg:tags":[
        "electrical",
        "contractor"
    ],
    "wof:name":"O&#039;Connor Electrics Pty Ltd",
    "wof:placetype":"venue"
},
  "geometry": {"coordinates":[146.94917297399999,-36.0375137329],"type":"Point"}
}