{
  "type": "Feature",
  "properties": {
    "addr:full":"6 Waratah Arc 1067 Old Princes Hwy Engadine NSW 2233",
    "addr:housenumber":"6;1067",
    "addr:postcode":"2233",
    "addr:street":"Waratah Arc;Old Princes Hwy",
    "iso:country":"AU",
    "sg:address":"6 Waratah Arc 1067 Old Princes Hwy",
    "sg:city":"Engadine",
    "sg:classifiers":[
        {
            "category":"Health Services",
            "subcategory":"Dentist",
            "type":"Services"
        }
    ],
    "sg:phone":"+61 2 9548 2055",
    "sg:postcode":"2233",
    "sg:province":"NSW",
    "wof:name":"Schwartz Mark Dr",
    "wof:placetype":"venue"
},
  "geometry": {"coordinates":[151.01269531200001,-34.0654716492],"type":"Point"}
}