{
  "type": "Feature",
  "properties": {
    "iso:country":"AU",
    "sg:address":"Murphy Rd",
    "sg:city":"Zillmere",
    "sg:classifiers":[
        {
            "category":"Education",
            "subcategory":"School",
            "type":"Public Place"
        }
    ],
    "sg:phone":"+61 7 3863 8333",
    "sg:postcode":"4034",
    "sg:province":"QLD",
    "sg:tags":[
        "state",
        "except",
        "nsw"
    ],
    "wof:name":"Zillmere Primary",
    "wof:placetype":"venue"
},
  "geometry": {"coordinates":[153.037125,-27.359734],"type":"Point"}
}