{
  "type": "Feature",
  "properties": {
    "addr:full":"12- 14 Ceylon St Nunawading VIC 3131",
    "addr:housenumber":"14",
    "addr:postcode":"3131",
    "addr:street":"Ceylon St",
    "iso:country":"AU",
    "sg:address":"12- 14 Ceylon St",
    "sg:city":"Nunawading",
    "sg:classifiers":[
        {
            "category":"Professional",
            "subcategory":"Detective & Security Services",
            "type":"Services"
        }
    ],
    "sg:phone":"+61 13 24 52",
    "sg:postcode":"3131",
    "sg:province":"VIC",
    "sg:tags":[
        "shuttering"
    ],
    "wof:name":"O&#039;Brien.",
    "wof:placetype":"venue"
},
  "geometry": {"coordinates":[145.16526794399999,-37.8197021484],"type":"Point"}
}