{
  "type": "Feature",
  "properties": {
    "addr:full":"44 Pittwin Rd Sth Capalaba QLD 4157",
    "addr:housenumber":"44",
    "addr:postcode":"4157",
    "addr:street":"Pittwin Rd Sth",
    "iso:country":"AU",
    "sg:address":"44 Pittwin Rd Sth",
    "sg:city":"Capalaba",
    "sg:classifiers":[
        {
            "category":"Building & Trades",
            "subcategory":"Plumbing",
            "type":"Services"
        }
    ],
    "sg:phone":"+61 408 746 109",
    "sg:postcode":"4157",
    "sg:province":"QLD",
    "sg:tags":[
        "plumber",
        "gasfitters"
    ],
    "wof:name":"Kingsley Samuels",
    "wof:placetype":"venue"
},
  "geometry": {"coordinates":[153.187789917,-27.527130127],"type":"Point"}
}