{
  "type": "Feature",
  "properties": {
    "addr:full":"Shop-11 Cnr Downs & Terrace St North Ipswich QLD 4305",
    "addr:postcode":"4305",
    "addr:street":"Cnr;St",
    "iso:country":"AU",
    "sg:address":"Shop-11 Cnr Downs & Terrace St",
    "sg:city":"North Ipswich",
    "sg:classifiers":[
        {
            "category":"Shopping",
            "subcategory":"Clothing, Apparel, & Fashions",
            "type":"Retail Goods"
        }
    ],
    "sg:phone":"+61 7 3812 1987",
    "sg:postcode":"4305",
    "sg:province":"QLD",
    "sg:tags":[
        "menswear"
    ],
    "wof:name":"Mensland",
    "wof:placetype":"venue"
},
  "geometry": {"coordinates":[152.762817383,-27.5972614288],"type":"Point"}
}