{
  "type": "Feature",
  "properties": {
    "addr:full":"Unit 25, 42- 50 Hampstead Rd Homebush West NSW 2140",
    "addr:housenumber":"42 50",
    "addr:postcode":"2140",
    "addr:street":"Hampstead Rd",
    "iso:country":"AU",
    "sg:address":"Unit 25, 42- 50 Hampstead Rd",
    "sg:city":"Homebush West",
    "sg:phone":"+61 2 9476 1788",
    "sg:postcode":"2140",
    "sg:province":"NSW",
    "wof:name":"Bermad Water Technologies",
    "wof:placetype":"venue"
},
  "geometry": {"coordinates":[151.070480347,-33.8681221008],"type":"Point"}
}