{
  "type": "Feature",
  "properties": {
    "iso:country":"AU",
    "sg:address":"2 121 Newmarket Rd",
    "sg:city":"Windsor",
    "sg:classifiers":[
        {
            "category":"Professional",
            "subcategory":"Printing & Photocopies",
            "type":"Services"
        }
    ],
    "sg:phone":"+61 7 3357 7277",
    "sg:postcode":"4030",
    "sg:province":"QLD",
    "sg:tags":[
        "embroidery"
    ],
    "wof:name":"Austitch/ALZ Embroidery Pty Ltd",
    "wof:placetype":"venue"
},
  "geometry": {"coordinates":[153.02380400000001,-27.436901],"type":"Point"}
}