{
  "type": "Feature",
  "properties": {
    "iso:country":"AU",
    "sg:address":"15 Drake St",
    "sg:city":"Osborne Park",
    "sg:classifiers":[
        {
            "category":"Food & Beverages",
            "subcategory":"Specialty",
            "type":"Retail Goods"
        }
    ],
    "sg:phone":"+61 8 9242 3511",
    "sg:postcode":"6017",
    "sg:province":"WA",
    "sg:tags":[
        "delicacy"
    ],
    "wof:name":"Normandie Foods",
    "wof:placetype":"venue"
},
  "geometry": {"coordinates":[115.81477356000001,-31.9095287323],"type":"Point"}
}