{
  "type": "Feature",
  "properties": {
    "addr:full":"Crn 565 Brunswick and Kent St New Farm New Farm QLD 4005",
    "addr:housenumber":"565",
    "addr:postcode":"4005",
    "addr:street":"Crn;Kent St",
    "iso:country":"AU",
    "sg:address":"Crn 565 Brunswick and Kent St",
    "sg:city":"New Farm New Farm",
    "sg:classifiers":[
        {
            "category":"Arts & Performance",
            "subcategory":"Art Gallery",
            "type":"Entertainment"
        }
    ],
    "sg:phone":"+61 419 739 347",
    "sg:postcode":"4005",
    "sg:province":"QLD",
    "wof:name":"Tracey Keller Gallery",
    "wof:placetype":"venue"
},
  "geometry": {"coordinates":[153.04133605999999,-27.4606781006],"type":"Point"}
}