{
  "type": "Feature",
  "properties": {
    "addr:full":"Suite 6/35- 37 Railway Pde Engadine NSW 2233",
    "addr:housenumber":"37",
    "addr:postcode":"2233",
    "addr:street":"Railway Pde",
    "iso:country":"AU",
    "sg:address":"Suite 6/35- 37 Railway Pde",
    "sg:city":"Engadine",
    "sg:classifiers":[
        {
            "category":"Banks & Credit Unions",
            "subcategory":"Financial Services",
            "type":"Services"
        }
    ],
    "sg:phone":"+61 2 9548 3344",
    "sg:postcode":"2233",
    "sg:province":"NSW",
    "sg:tags":[
        "annuity",
        "rollover",
        "superannuation",
        "consultant"
    ],
    "wof:name":"Moore Peter",
    "wof:placetype":"venue"
},
  "geometry": {"coordinates":[151.01417541500001,-34.0677680969],"type":"Point"}
}