{
  "type": "Feature",
  "properties": {
    "addr:full":"Layman Rd Busselton WA 6280",
    "addr:postcode":"6280",
    "addr:street":"Layman Rd",
    "iso:country":"AU",
    "sg:address":"Layman Rd",
    "sg:city":"Busselton",
    "sg:classifiers":[
        {
            "category":"Communications",
            "subcategory":"News Services",
            "type":"Services"
        }
    ],
    "sg:phone":"+61 8 9752 2039",
    "sg:postcode":"6280",
    "sg:province":"WA",
    "sg:tags":[
        "information",
        "tourist",
        "attractions"
    ],
    "wof:name":"Wonnerup House",
    "wof:placetype":"venue"
},
  "geometry": {"coordinates":[115.361793518,-33.6489372253],"type":"Point"}
}