{
  "type": "Feature",
  "properties": {
    "iso:country":"AU",
    "sg:address":"269 Shute Harbour Rd",
    "sg:city":"Airlie Beach",
    "sg:classifiers":[
        {
            "category":"Travel",
            "subcategory":"Hotels & Motels",
            "type":"Entertainment"
        }
    ],
    "sg:phone":"+61 7 4946 6359",
    "sg:postcode":"4802",
    "sg:province":"QLD",
    "sg:website":"http://www.whitsunday.net.au/beach/beach.htm",
    "wof:name":"Whitsunday on the Beach",
    "wof:placetype":"venue"
},
  "geometry": {"coordinates":[148.717559814,-20.2681522369],"type":"Point"}
}