{
  "type": "Feature",
  "properties": {
    "addr:full":"Suite 14, Victoria Court 36- 40 Victoria St Gosford East NSW 2250",
    "addr:housenumber":"36 40",
    "addr:postcode":"2250",
    "addr:street":"Victoria Court;Victoria St",
    "iso:country":"AU",
    "sg:address":"Suite 14, Victoria Court 36- 40 Victoria St",
    "sg:city":"Gosford East",
    "sg:classifiers":[
        {
            "category":"Social Services",
            "subcategory":"Retirement Home",
            "type":"Services"
        }
    ],
    "sg:phone":"+61 2 4325 5125",
    "sg:postcode":"2250",
    "sg:province":"NSW",
    "sg:tags":[
        "decoration",
        "supplier",
        "contractor"
    ],
    "wof:name":"Event Decorators The",
    "wof:placetype":"venue"
},
  "geometry": {"coordinates":[151.35401916500001,-33.4385375977],"type":"Point"}
}