{
  "type": "Feature",
  "properties": {
    "iso:country":"AU",
    "sg:address":"120 Swanston St",
    "sg:city":"New Town",
    "sg:classifiers":[
        {
            "category":"Travel",
            "subcategory":"Hostel",
            "type":"Entertainment"
        }
    ],
    "sg:phone":"+61 3 6228 2164",
    "sg:postcode":"7008",
    "sg:province":"TAS",
    "sg:tags":[
        "home"
    ],
    "wof:name":"Salvation Army",
    "wof:placetype":"venue"
},
  "geometry": {"coordinates":[147.30458068900001,-42.8534927368],"type":"Point"}
}