{
  "type": "Feature",
  "properties": {
    "addr:full":"62- 64 Latrobe Rd Morwell VIC 3840",
    "addr:housenumber":"64",
    "addr:postcode":"3840",
    "addr:street":"Latrobe Rd",
    "iso:country":"AU",
    "sg:address":"62- 64 Latrobe Rd",
    "sg:city":"Morwell",
    "sg:classifiers":[
        {
            "category":"Wholesale",
            "subcategory":"Auto Parts",
            "type":"Manufacturing & Wholesale Goods"
        }
    ],
    "sg:phone":"+61 3 5133 7511",
    "sg:postcode":"3840",
    "sg:province":"VIC",
    "sg:tags":[
        "recyclers"
    ],
    "wof:name":"Madden Auto Salvage",
    "wof:placetype":"venue"
},
  "geometry": {"coordinates":[146.39590454099999,-38.2296524048],"type":"Point"}
}