{
  "type": "Feature",
  "properties": {
    "addr:full":"PO Box 4094 McKinnon VIC 3204",
    "addr:postcode":"3204",
    "iso:country":"AU",
    "sg:address":"PO Box 4094",
    "sg:city":"McKinnon",
    "sg:classifiers":[
        {
            "category":"Professional",
            "subcategory":"Computer Services",
            "type":"Services"
        }
    ],
    "sg:phone":"+61 411 472 222",
    "sg:postcode":"3204",
    "sg:province":"VIC",
    "sg:tags":[
        "tele-communications",
        "consultant"
    ],
    "wof:name":"On-Line Concepts",
    "wof:placetype":"venue"
},
  "geometry": {"coordinates":[145.03956600000001,-37.911221],"type":"Point"}
}