{
  "type": "Feature",
  "properties": {
    "addr:full":"23 Stanley St Wallan VIC 3756",
    "addr:housenumber":"23",
    "addr:postcode":"3756",
    "addr:street":"Stanley St",
    "iso:country":"AU",
    "sg:address":"23 Stanley St",
    "sg:city":"Wallan",
    "sg:classifiers":[
        {
            "category":"Building & Trades",
            "subcategory":"Construction",
            "type":"Services"
        }
    ],
    "sg:phone":"+61 3 5783 1681",
    "sg:postcode":"3756",
    "sg:province":"VIC",
    "sg:tags":[
        "joiner",
        "carpenter"
    ],
    "wof:name":"Brown E & M",
    "wof:placetype":"venue"
},
  "geometry": {"coordinates":[144.976089,-37.414944],"type":"Point"}
}