{
  "type": "Feature",
  "properties": {
    "iso:country":"AU",
    "sg:address":"34 Bayview St",
    "sg:city":"Tennyson (Gladesville)",
    "sg:classifiers":[
        {
            "category":"Building & Trades",
            "subcategory":"Construction",
            "type":"Services"
        }
    ],
    "sg:phone":"+61 2 9802 8592",
    "sg:postcode":"2111",
    "sg:province":"NSW",
    "sg:tags":[
        "contractor"
    ],
    "wof:name":"Angel Constructions Pty Ltd",
    "wof:placetype":"venue"
},
  "geometry": {"coordinates":[151.11471557600001,-33.8306045532],"type":"Point"}
}