{
  "type": "Feature",
  "properties": {
    "addr:full":"Dumas St McKellar ACT 2617",
    "addr:postcode":"2617",
    "addr:street":"Dumas St",
    "iso:country":"AU",
    "sg:address":"Dumas St",
    "sg:city":"McKellar",
    "sg:classifiers":[
        {
            "category":"Insurance",
            "subcategory":"Hazard Insurance",
            "type":"Services"
        }
    ],
    "sg:phone":"+61 2 6259 1800",
    "sg:postcode":"2617",
    "sg:province":"ACT",
    "sg:tags":[
        "loss",
        "adjuster",
        "assessor"
    ],
    "wof:name":"Bell J D & Associates",
    "wof:placetype":"venue"
},
  "geometry": {"coordinates":[149.073776245,-35.2174835205],"type":"Point"}
}