{
  "type": "Feature",
  "properties": {
    "addr:full":"70 Albert St Revesby NSW 2212",
    "addr:housenumber":"70",
    "addr:postcode":"2212",
    "addr:street":"Albert St",
    "iso:country":"AU",
    "sg:address":"70 Albert St",
    "sg:city":"Revesby",
    "sg:classifiers":[
        {
            "category":"Building & Trades",
            "subcategory":"Landscaping Services",
            "type":"Services"
        }
    ],
    "sg:phone":"+61 2 9773 1868",
    "sg:postcode":"2212",
    "sg:province":"NSW",
    "sg:tags":[
        "stump",
        "tree",
        "felling",
        "removal"
    ],
    "wof:name":"A True Blue Tree Lopping",
    "wof:placetype":"venue"
},
  "geometry": {"coordinates":[151.01464799999999,-33.943951],"type":"Point"}
}