{
  "type": "Feature",
  "properties": {
    "addr:full":"Station Arcade 132 North Tce Adelaide SA 5000",
    "addr:housenumber":"132",
    "addr:postcode":"5000",
    "addr:street":"North Tce",
    "iso:country":"AU",
    "sg:address":"Station Arcade 132",
    "sg:city":"North Tce Adelaide",
    "sg:classifiers":[
        {
            "category":"Food & Beverages",
            "subcategory":"Liquor & Beverages",
            "type":"Retail Goods"
        }
    ],
    "sg:phone":"+61 8 8238 2999",
    "sg:postcode":"5000",
    "sg:province":"SA",
    "sg:tags":[
        "store"
    ],
    "wof:name":"Strathmore Cellars",
    "wof:placetype":"venue"
},
  "geometry": {"coordinates":[138.597854614,-34.9216308594],"type":"Point"}
}