{
  "type": "Feature",
  "properties": {
    "addr:full":"76 Bayfield St Bellerive TAS 7018",
    "addr:housenumber":"76",
    "addr:postcode":"7018",
    "addr:street":"Bayfield St",
    "iso:country":"AU",
    "sg:address":"76 Bayfield St",
    "sg:city":"Bellerive",
    "sg:classifiers":[
        {
            "category":"Home & Garden",
            "subcategory":"Carpets & Floor Coverings",
            "type":"Retail Goods"
        }
    ],
    "sg:phone":"+61 419 893 045",
    "sg:postcode":"7018",
    "sg:province":"TAS",
    "sg:tags":[
        "layer",
        "planner"
    ],
    "wof:name":"McHugo V G",
    "wof:placetype":"venue"
},
  "geometry": {"coordinates":[147.37692260700001,-42.8694190979],"type":"Point"}
}