{
  "type": "Feature",
  "properties": {
    "addr:full":"258 Argyle St Hobart TAS 7000",
    "addr:housenumber":"258",
    "addr:postcode":"7000",
    "addr:street":"Argyle St",
    "iso:country":"AU",
    "sg:address":"258 Argyle St",
    "sg:city":"Hobart",
    "sg:classifiers":[
        {
            "category":"Building & Trades",
            "subcategory":"Construction",
            "type":"Services"
        }
    ],
    "sg:phone":"+61 3 6231 5240",
    "sg:postcode":"7000",
    "sg:province":"TAS",
    "sg:tags":[
        "welding"
    ],
    "wof:name":"Fletcher Lewis Engineering & Welding",
    "wof:placetype":"venue"
},
  "geometry": {"coordinates":[147.319946289,-42.874206543],"type":"Point"}
}