{
  "type": "Feature",
  "properties": {
    "addr:full":"922 Port Rd Woodville SA 5011",
    "addr:housenumber":"922",
    "addr:postcode":"5011",
    "addr:street":"Port Rd",
    "iso:country":"AU",
    "sg:address":"922 Port Rd",
    "sg:city":"Woodville",
    "sg:classifiers":[
        {
            "category":"Fast Food",
            "type":"Food & Drink"
        }
    ],
    "sg:phone":"+61 8 8268 3474",
    "sg:postcode":"5011",
    "sg:province":"SA",
    "sg:tags":[
        "away",
        "take"
    ],
    "wof:name":"Barnacle Bill",
    "wof:placetype":"venue"
},
  "geometry": {"coordinates":[138.53070068400001,-34.8782806396],"type":"Point"}
}