{
  "type": "Feature",
  "properties": {
    "iso:country":"AU",
    "sg:address":"Unit 3 22a Tone Rd",
    "sg:city":"Wangaratta",
    "sg:classifiers":[
        {
            "category":"Retail",
            "subcategory":"Auto Repair",
            "type":"Services"
        }
    ],
    "sg:phone":"+61 3 5721 2422",
    "sg:postcode":"3677",
    "sg:province":"VIC",
    "sg:tags":[
        "testing",
        "inspection",
        "motor",
        "vehicle"
    ],
    "wof:name":"B Gottschling",
    "wof:placetype":"venue"
},
  "geometry": {"coordinates":[146.31121826200001,-36.3599128723],"type":"Point"}
}