{
  "type": "Feature",
  "properties": {
    "iso:country":"AU",
    "sg:address":"PO Box 5930",
    "sg:city":"West End (Brisbane)",
    "sg:classifiers":[
        {
            "category":"Banks & Credit Unions",
            "subcategory":"Investment Brokerage",
            "type":"Services"
        }
    ],
    "sg:phone":"+61 1300 886 557",
    "sg:postcode":"4101",
    "sg:province":"QLD",
    "sg:tags":[
        "management",
        "property"
    ],
    "wof:name":"Rent & Returns Property Management",
    "wof:placetype":"venue"
},
  "geometry": {"coordinates":[153.012161255,-27.4802494049],"type":"Point"}
}