{
  "type": "Feature",
  "properties": {
    "addr:full":"55 Lear Jet Drv Caboolture QLD 4510",
    "addr:housenumber":"55",
    "addr:postcode":"4510",
    "addr:street":"Lear Jet Drv",
    "iso:country":"AU",
    "sg:address":"55 Lear Jet Drv",
    "sg:city":"Caboolture",
    "sg:classifiers":[
        {
            "category":"Train Station",
            "subcategory":"Light Rail",
            "type":"Transportation"
        }
    ],
    "sg:phone":"+61 7 5495 6222",
    "sg:postcode":"4510",
    "sg:province":"QLD",
    "sg:tags":[
        "equipment",
        "energy",
        "solar"
    ],
    "wof:name":"Solar Panel Xpress",
    "wof:placetype":"venue"
},
  "geometry": {"coordinates":[152.97949199999999,-27.079998],"type":"Point"}
}