{
  "type": "Feature",
  "properties": {
    "addr:full":"Shop 4 Station Arcade/ 52 Hindley St Adelaide SA 5001",
    "addr:housenumber":"shop 4;52",
    "addr:postcode":"5001",
    "addr:street":"Station Arcade /;St",
    "iso:country":"AU",
    "sg:address":"Shop 4 Station Arcade/ 52 Hindley St",
    "sg:city":"Adelaide",
    "sg:classifiers":[
        {
            "category":"Personal",
            "subcategory":"Beauty Salon",
            "type":"Services"
        }
    ],
    "sg:phone":"+61 8 8231 3334",
    "sg:postcode":"5001",
    "sg:province":"SA",
    "sg:tags":[
        "hairdresser"
    ],
    "wof:name":"A Dolce Hair & Beauty",
    "wof:placetype":"venue"
},
  "geometry": {"coordinates":[138.597824097,-34.9229393005],"type":"Point"}
}