{
  "type": "Feature",
  "properties": {
    "addr:full":"Unit 1/ 128 Benowa Rd Southport QLD 4215",
    "addr:housenumber":"/ 128",
    "addr:postcode":"4215",
    "addr:street":"Benowa Rd",
    "iso:country":"AU",
    "sg:address":"Unit 1/ 128 Benowa Rd",
    "sg:city":"Southport",
    "sg:classifiers":[
        {
            "category":"Retail",
            "subcategory":"Auto Repair",
            "type":"Services"
        }
    ],
    "sg:phone":"+61 434 346 826",
    "sg:postcode":"4215",
    "sg:province":"QLD",
    "sg:tags":[
        "clutch",
        "brake"
    ],
    "wof:name":"A A A Brakes",
    "wof:placetype":"venue"
},
  "geometry": {"coordinates":[153.39805602999999,-27.9914798737],"type":"Point"}
}