{
  "type": "Feature",
  "properties": {
    "addr:full":"37 Vievers St Palm Cove QLD 4879",
    "addr:housenumber":"37",
    "addr:postcode":"4879",
    "addr:street":"Vievers St",
    "iso:country":"AU",
    "sg:address":"37 Vievers St",
    "sg:city":"Palm Cove",
    "sg:classifiers":[
        {
            "category":"Personal",
            "subcategory":"Massage",
            "type":"Services"
        }
    ],
    "sg:phone":"+61 400 580 929",
    "sg:postcode":"4879",
    "sg:province":"QLD",
    "sg:tags":[
        "therapy"
    ],
    "wof:name":"Bodyworks",
    "wof:placetype":"venue"
},
  "geometry": {"coordinates":[145.67100524899999,-16.7458992004],"type":"Point"}
}