{
  "type": "Feature",
  "properties": {
    "addr:full":"11 Monro Ave Kirrawee NSW 2232",
    "addr:housenumber":"11",
    "addr:postcode":"2232",
    "addr:street":"Monro Ave",
    "iso:country":"AU",
    "sg:address":"11 Monro Ave",
    "sg:city":"Kirrawee",
    "sg:classifiers":[
        {
            "category":"Transit Center",
            "subcategory":"Passenger",
            "type":"Transportation"
        }
    ],
    "sg:phone":"+61 2 9542 4735",
    "sg:postcode":"2232",
    "sg:province":"NSW",
    "sg:tags":[
        "packing",
        "gasket"
    ],
    "wof:name":"ACL Specialised Gaskets",
    "wof:placetype":"venue"
},
  "geometry": {"coordinates":[151.07533264200001,-34.0310516357],"type":"Point"}
}