{
  "type": "Feature",
  "properties": {
    "addr:full":"169 Malabar Rd Coogee NSW 2034",
    "addr:housenumber":"169",
    "addr:postcode":"2034",
    "addr:street":"Malabar Rd",
    "iso:country":"AU",
    "sg:address":"169 Malabar Rd",
    "sg:city":"Coogee",
    "sg:classifiers":[
        {
            "category":"Autos & Motor Vehicles",
            "subcategory":"Fuel & Gas Station",
            "type":"Retail Goods"
        }
    ],
    "sg:phone":"+61 2 9344 8314",
    "sg:postcode":"2034",
    "sg:province":"NSW",
    "wof:name":"Caltex Ampol Service Station",
    "wof:placetype":"venue"
},
  "geometry": {"coordinates":[151.257156372,-33.9322052002],"type":"Point"}
}