{
  "type": "Feature",
  "properties": {
    "addr:full":"1 Cataract St Kaleen ACT 2617",
    "addr:housenumber":"1",
    "addr:postcode":"2617",
    "addr:street":"Cataract St",
    "iso:country":"AU",
    "sg:address":"1 Cataract St",
    "sg:city":"Kaleen",
    "sg:classifiers":[
        {
            "category":"Building & Trades",
            "subcategory":"Construction",
            "type":"Services"
        }
    ],
    "sg:phone":"+61 414 414 390",
    "sg:postcode":"2617",
    "sg:province":"ACT",
    "sg:tags":[
        "renovation",
        "alterations",
        "extension",
        "contractor"
    ],
    "wof:name":"All Building Services",
    "wof:placetype":"venue"
},
  "geometry": {"coordinates":[149.096435547,-35.2342948914],"type":"Point"}
}