{
  "type": "Feature",
  "properties": {
    "addr:full":"168 Bryan 'O' Lynn Rd Purnim VIC 3278",
    "addr:housenumber":"168",
    "addr:postcode":"3278",
    "addr:street":"Bryan;Lynn Rd",
    "iso:country":"AU",
    "sg:address":"168 Bryan 'O' Lynn Rd",
    "sg:city":"Purnim",
    "sg:classifiers":[
        {
            "category":"Professional",
            "subcategory":"Art Services",
            "type":"Services"
        }
    ],
    "sg:phone":"+61 3 5567 1098",
    "sg:postcode":"3278",
    "sg:province":"VIC",
    "sg:tags":[
        "decorator",
        "painter"
    ],
    "wof:name":"Smith Paul & Russell",
    "wof:placetype":"venue"
},
  "geometry": {"coordinates":[142.619216919,-38.2804107666],"type":"Point"}
}