{
  "type": "Feature",
  "properties": {
    "addr:full":"Shop 17 Macedon Plaza S/C, 325-327 Manningham Rd Lower Templestowe VIC 3107",
    "addr:housenumber":"shop 17;/ c",
    "addr:postcode":"325-327;3107",
    "addr:street":"Plaza;Manningham Rd",
    "iso:country":"AU",
    "sg:address":"Shop 17 Macedon Plaza S/C, 325-327 Manningham Rd",
    "sg:city":"Lower Templestowe",
    "sg:classifiers":[
        {
            "category":"Food & Beverages",
            "subcategory":"Bakery",
            "type":"Retail Goods"
        }
    ],
    "sg:phone":"+61 3 9850 4822",
    "sg:postcode":"3107",
    "sg:province":"VIC",
    "sg:tags":[
        "baker"
    ],
    "wof:name":"Bakers Delight Ltd",
    "wof:placetype":"venue"
},
  "geometry": {"coordinates":[145.11329650900001,-37.7733879089],"type":"Point"}
}