{
  "type": "Feature",
  "properties": {
    "addr:full":"1- 5 West St Pymble NSW 2073",
    "addr:housenumber":"5",
    "addr:postcode":"2073",
    "addr:street":"West St",
    "iso:country":"AU",
    "sg:address":"1- 5 West St",
    "sg:city":"Pymble",
    "sg:classifiers":[
        {
            "category":"Government",
            "subcategory":"Post Office",
            "type":"Public Place"
        }
    ],
    "sg:phone":"+61 13 11 18",
    "sg:postcode":"2073",
    "sg:province":"NSW",
    "sg:tags":[
        "postal"
    ],
    "wof:name":"Australia Post Business Centre",
    "wof:placetype":"venue"
},
  "geometry": {"coordinates":[151.14402770999999,-33.7511940002],"type":"Point"}
}