{
  "type": "Feature",
  "properties": {
    "addr:full":"3 Collina Crt Langwarrin VIC 3910",
    "addr:housenumber":"3",
    "addr:postcode":"3910",
    "addr:street":"Collina Crt",
    "iso:country":"AU",
    "sg:address":"3 Collina Crt",
    "sg:city":"Langwarrin",
    "sg:classifiers":[
        {
            "category":"Structure",
            "subcategory":"Office Building",
            "type":"Public Place"
        }
    ],
    "sg:phone":"+61 400 034 267",
    "sg:postcode":"3910",
    "sg:province":"VIC",
    "sg:tags":[
        "slater",
        "tiler",
        "roof"
    ],
    "wof:name":"Woodside Roofing",
    "wof:placetype":"venue"
},
  "geometry": {"coordinates":[145.18685913100001,-38.1432037354],"type":"Point"}
}