{
  "type": "Feature",
  "properties": {
    "iso:country":"AU",
    "sg:address":"46 Novara Pde",
    "sg:city":"St Albans",
    "sg:classifiers":[
        {
            "category":"Building & Trades",
            "subcategory":"Construction",
            "type":"Services"
        }
    ],
    "sg:phone":"+61 3 9366 4686",
    "sg:postcode":"3021",
    "sg:province":"VIC",
    "sg:tags":[
        "industrial",
        "commercial",
        "air conditioning"
    ],
    "wof:name":"Cool Running Appliances",
    "wof:placetype":"venue"
},
  "geometry": {"coordinates":[144.81646699999999,-37.74762],"type":"Point"}
}