{
  "type": "Feature",
  "properties": {
    "addr:full":"39 Sandpiper Drv Taylors Lakes VIC 3038",
    "addr:housenumber":"39",
    "addr:postcode":"3038",
    "addr:street":"Sandpiper Drv",
    "iso:country":"AU",
    "sg:address":"39 Sandpiper Drv",
    "sg:city":"Taylors Lakes",
    "sg:classifiers":[
        {
            "category":"Travel",
            "subcategory":"Travel Agent",
            "type":"Entertainment"
        }
    ],
    "sg:phone":"+61 3 9449 3565",
    "sg:postcode":"3038",
    "sg:province":"VIC",
    "sg:tags":[
        "consultant"
    ],
    "wof:name":"Bula Travel",
    "wof:placetype":"venue"
},
  "geometry": {"coordinates":[144.78997799999999,-37.693905],"type":"Point"}
}