{
  "type": "Feature",
  "properties": {
    "addr:full":"88-90 Hanson St Corryong NSW 3707",
    "addr:housenumber":"88-90",
    "addr:postcode":"3707",
    "addr:street":"Hanson St",
    "iso:country":"AU",
    "sg:address":"88-90 Hanson St",
    "sg:city":"Corryong",
    "sg:classifiers":[
        {
            "category":"Retail",
            "subcategory":"Auto Repair",
            "type":"Services"
        }
    ],
    "sg:phone":"+61 2 6076 2544",
    "sg:postcode":"3707",
    "sg:province":"NSW",
    "sg:tags":[
        "repairer",
        "motor",
        "engineer"
    ],
    "wof:name":"Corryong Service Centre",
    "wof:placetype":"venue"
},
  "geometry": {"coordinates":[148.01678466800001,-36.1683044434],"type":"Point"}
}