{
  "type": "Feature",
  "properties": {
    "addr:full":"198 Pacific Hwy Tuggerah NSW 2259",
    "addr:housenumber":"198",
    "addr:postcode":"2259",
    "addr:street":"Pacific Hwy",
    "iso:country":"AU",
    "sg:address":"198 Pacific Hwy",
    "sg:city":"Tuggerah",
    "sg:classifiers":[
        {
            "category":"Retail",
            "subcategory":"Auto Repair",
            "type":"Services"
        }
    ],
    "sg:phone":"+61 2 4353 4242",
    "sg:postcode":"2259",
    "sg:province":"NSW",
    "sg:tags":[
        "body",
        "builder",
        "motor"
    ],
    "wof:name":"Best Price Auto Dismantlers",
    "wof:placetype":"venue"
},
  "geometry": {"coordinates":[151.41104125999999,-33.3160858154],"type":"Point"}
}