{
  "type": "Feature",
  "properties": {
    "iso:country":"AU",
    "sg:address":"56 John Dory Drv",
    "sg:city":"Ocean Grove",
    "sg:classifiers":[
        {
            "category":"Retail",
            "subcategory":"Driving School",
            "type":"Services"
        }
    ],
    "sg:phone":"+61 3 5256 1877",
    "sg:postcode":"3226",
    "sg:province":"VIC",
    "wof:name":"Jill Hopkins Driving School",
    "wof:placetype":"venue"
},
  "geometry": {"coordinates":[144.54139699999999,-38.261822],"type":"Point"}
}