{
  "type": "Feature",
  "properties": {
    "iso:country":"AU",
    "sg:address":"44 Fullarton Rd",
    "sg:city":"Norwood",
    "sg:classifiers":[
        {
            "category":"Real Estate",
            "subcategory":"Real Estate Agent",
            "type":"Services"
        }
    ],
    "sg:phone":"+61 418 850 494",
    "sg:postcode":"5067",
    "sg:province":"SA",
    "wof:name":"Barron Brenton",
    "wof:placetype":"venue"
},
  "geometry": {"coordinates":[138.62327575699999,-34.9202384949],"type":"Point"}
}