{
  "type": "Feature",
  "properties": {
    "iso:country":"AU",
    "sg:address":"207 Darlinghurst Rd",
    "sg:city":"Darlinghurst",
    "sg:classifiers":[
        {
            "category":"Travel",
            "subcategory":"Hotels & Motels",
            "type":"Entertainment"
        }
    ],
    "sg:phone":"+61 2 9360 6000",
    "sg:postcode":"2010",
    "sg:province":"NSW",
    "sg:tags":[
        "accommodation"
    ],
    "wof:name":"Hotel Altamont",
    "wof:placetype":"venue"
},
  "geometry": {"coordinates":[151.22044372600001,-33.8777503967],"type":"Point"}
}