{
  "type": "Feature",
  "properties": {
    "addr:full":"75 Belmore Rd Randwick NSW 2031",
    "addr:housenumber":"75",
    "addr:postcode":"2031",
    "addr:street":"Belmore Rd",
    "iso:country":"AU",
    "sg:address":"75 Belmore Rd",
    "sg:city":"Randwick",
    "sg:classifiers":[
        {
            "category":"Real Estate",
            "subcategory":"Real Estate Agent",
            "type":"Services"
        }
    ],
    "sg:phone":"+61 2 9326 7000",
    "sg:postcode":"2031",
    "sg:province":"NSW",
    "wof:name":"Ray White",
    "wof:placetype":"venue"
},
  "geometry": {"coordinates":[151.24034118599999,-33.9145545959],"type":"Point"}
}