{
  "type": "Feature",
  "properties": {
    "iso:country":"AU",
    "sg:address":"PO Box 1064",
    "sg:city":"Coorparoo BC",
    "sg:classifiers":[
        {
            "category":"Professional",
            "subcategory":"Detective & Security Services",
            "type":"Services"
        }
    ],
    "sg:phone":"+61 418 654 873",
    "sg:postcode":"4151",
    "sg:province":"QLD",
    "sg:tags":[
        "investigator"
    ],
    "wof:name":"Jomiza Investigations",
    "wof:placetype":"venue"
},
  "geometry": {"coordinates":[153.04835510300001,-27.4924507141],"type":"Point"}
}