{
  "type": "Feature",
  "properties": {
    "iso:country":"AU",
    "sg:address":"2/ 21 Enoggera Tce",
    "sg:city":"Red Hill",
    "sg:classifiers":[
        {
            "category":"Manufacturing",
            "subcategory":"Musical Instruments",
            "type":"Manufacturing & Wholesale Goods"
        }
    ],
    "sg:phone":"+61 7 3257 7786",
    "sg:postcode":"4059",
    "sg:province":"QLD",
    "sg:tags":[
        "repair",
        "maker"
    ],
    "wof:name":"Simmers Violin Makers Pty Ltd",
    "wof:placetype":"venue"
},
  "geometry": {"coordinates":[153.00378418,-27.4531555176],"type":"Point"}
}