{
  "type": "Feature",
  "properties": {
    "iso:country":"AU",
    "sg:address":"7 Jobert Crt",
    "sg:city":"Blackburn South",
    "sg:classifiers":[
        {
            "category":"Real Estate",
            "subcategory":"Architect",
            "type":"Services"
        }
    ],
    "sg:phone":"+61 3 9877 5828",
    "sg:postcode":"3130",
    "sg:province":"VIC",
    "wof:name":"Yap T C",
    "wof:placetype":"venue"
},
  "geometry": {"coordinates":[145.148712158,-37.8379707336],"type":"Point"}
}