{
  "type": "Feature",
  "properties": {
    "iso:country":"AU",
    "sg:address":"338 Griffith Rd",
    "sg:city":"Lavington",
    "sg:classifiers":[
        {
            "category":"Professional",
            "subcategory":"Accounting & Tax Preparation",
            "type":"Services"
        }
    ],
    "sg:phone":"+61 2 6025 7355",
    "sg:postcode":"2641",
    "sg:province":"NSW",
    "sg:tags":[
        "consultant",
        "taxation"
    ],
    "wof:name":"Worsley Partners",
    "wof:placetype":"venue"
},
  "geometry": {"coordinates":[146.94172668499999,-36.0447273254],"type":"Point"}
}