{
  "type": "Feature",
  "properties": {
    "addr:full":"PO Box 344 Wodonga VIC 3689",
    "addr:postcode":"3689",
    "iso:country":"AU",
    "sg:address":"PO Box 344",
    "sg:city":"Wodonga",
    "sg:classifiers":[
        {
            "category":"Education",
            "subcategory":"Special Training",
            "type":"Public Place"
        }
    ],
    "sg:phone":"+61 2 6027 0900",
    "sg:postcode":"3689",
    "sg:province":"VIC",
    "sg:tags":[
        "development"
    ],
    "wof:name":"Write On Q",
    "wof:placetype":"venue"
},
  "geometry": {"coordinates":[146.88806199999999,-36.125542],"type":"Point"}
}