{
  "type": "Feature",
  "properties": {
    "iso:country":"AU",
    "sg:address":"6 Overlord Pl",
    "sg:city":"Acacia Ridge",
    "sg:classifiers":[
        {
            "category":"Utilities",
            "subcategory":"Water",
            "type":"Services"
        }
    ],
    "sg:phone":"+61 7 3711 7053",
    "sg:postcode":"4110",
    "sg:province":"QLD",
    "sg:tags":[
        "equipment",
        "treatment"
    ],
    "wof:name":"Enviroflow Water Technology",
    "wof:placetype":"venue"
},
  "geometry": {"coordinates":[153.036819458,-27.5943527222],"type":"Point"}
}