{
  "type": "Feature",
  "properties": {
    "addr:full":"1- 5 Cheltenham Rd Dandenong VIC 3175",
    "addr:housenumber":"5",
    "addr:postcode":"3175",
    "addr:street":"Cheltenham Rd",
    "iso:country":"AU",
    "sg:address":"1- 5 Cheltenham Rd",
    "sg:city":"Dandenong",
    "sg:classifiers":[
        {
            "category":"Shopping",
            "subcategory":"Discount & Variety Stores",
            "type":"Retail Goods"
        }
    ],
    "sg:phone":"+61 3 9791 8410",
    "sg:postcode":"3175",
    "sg:province":"VIC",
    "sg:tags":[
        "shop",
        "adult"
    ],
    "wof:name":"Club X",
    "wof:placetype":"venue"
},
  "geometry": {"coordinates":[145.21191406200001,-37.990776062],"type":"Point"}
}