{
  "type": "Feature",
  "properties": {
    "addr:full":"Unit 3604/ 24 Jane Bell La Melbourne VIC 3000",
    "addr:housenumber":"3604 / 24",
    "addr:postcode":"3000",
    "addr:street":"Jane Bell La",
    "iso:country":"AU",
    "sg:address":"Unit 3604/ 24 Jane Bell La",
    "sg:city":"Melbourne",
    "sg:classifiers":[
        {
            "category":"Retail",
            "subcategory":"Auto Rental",
            "type":"Services"
        }
    ],
    "sg:phone":"+61 419 322 054",
    "sg:postcode":"3000",
    "sg:province":"VIC",
    "sg:tags":[
        "chauffeur",
        "car",
        "hire",
        "driven",
        "limousine"
    ],
    "wof:name":"GSB Hire cars",
    "wof:placetype":"venue"
},
  "geometry": {"coordinates":[144.966400147,-37.8101158142],"type":"Point"}
}