{
  "type": "Feature",
  "properties": {
    "addr:full":"73 Walker St Lismore NSW 2480",
    "addr:housenumber":"73",
    "addr:postcode":"2480",
    "addr:street":"Walker St",
    "iso:country":"AU",
    "sg:address":"73 Walker St",
    "sg:city":"Lismore",
    "sg:classifiers":[
        {
            "category":"Retail",
            "subcategory":"Driving School",
            "type":"Services"
        }
    ],
    "sg:phone":"+61 2 6622 4100",
    "sg:postcode":"2480",
    "sg:province":"NSW",
    "sg:website":"http://www.drive-rite.com",
    "wof:name":"Drive-Rite Driving School",
    "wof:placetype":"venue"
},
  "geometry": {"coordinates":[153.29608154300001,-28.8255462646],"type":"Point"}
}