{
  "type": "Feature",
  "properties": {
    "addr:full":"13 Lum St Export Park SA 5950",
    "addr:housenumber":"13",
    "addr:postcode":"5950",
    "addr:street":"Lum St",
    "iso:country":"AU",
    "sg:address":"13 Lum St",
    "sg:city":"Export Park",
    "sg:classifiers":[
        {
            "category":"Professional",
            "type":"Services"
        }
    ],
    "sg:phone":"+61 8 8355 9295",
    "sg:postcode":"5950",
    "sg:province":"SA",
    "sg:tags":[
        "transport"
    ],
    "wof:name":"In2store",
    "wof:placetype":"venue"
},
  "geometry": {"coordinates":[138.54283142099999,-34.9351997375],"type":"Point"}
}