{
  "type": "Feature",
  "properties": {
    "iso:country":"AU",
    "sg:address":"57 Port Curtis Rd",
    "sg:city":"Rockhampton",
    "sg:classifiers":[
        {
            "category":"Professional",
            "subcategory":"Business Services",
            "type":"Services"
        }
    ],
    "sg:phone":"+61 7 4927 7993",
    "sg:postcode":"4700",
    "sg:province":"QLD",
    "sg:tags":[
        "livestock",
        "transport"
    ],
    "wof:name":"Schirmer's True Blue Livestock & General Carrier & Pastoral Co",
    "wof:placetype":"venue"
},
  "geometry": {"coordinates":[150.50950622600001,-23.4070892334],"type":"Point"}
}