{
  "type": "Feature",
  "properties": {
    "addr:full":"36 Mellool St Barham NSW 2732",
    "addr:housenumber":"36",
    "addr:postcode":"2732",
    "addr:street":"Mellool St",
    "iso:country":"AU",
    "sg:address":"36 Mellool St",
    "sg:city":"Barham",
    "sg:classifiers":[
        {
            "category":"Professional",
            "subcategory":"Accounting & Tax Preparation",
            "type":"Services"
        }
    ],
    "sg:phone":"+61 3 5453 2288",
    "sg:postcode":"2732",
    "sg:province":"NSW",
    "sg:tags":[
        "accountant",
        "auditor"
    ],
    "wof:name":"O'Neill Wesley D Chartered Accountant",
    "wof:placetype":"venue"
},
  "geometry": {"coordinates":[144.12733499999999,-35.625256],"type":"Point"}
}