{
  "type": "Feature",
  "properties": {
    "addr:full":"297 Glen Osmond Rd Glenunga SA 5064",
    "addr:housenumber":"297",
    "addr:postcode":"5064",
    "addr:street":"Glen Osmond Rd",
    "iso:country":"AU",
    "sg:address":"297 Glen Osmond Rd",
    "sg:city":"Glenunga",
    "sg:classifiers":[
        {
            "category":"Food & Beverages",
            "subcategory":"Supermarket",
            "type":"Retail Goods"
        }
    ],
    "sg:phone":"+61 8 8379 9297",
    "sg:postcode":"5064",
    "sg:province":"SA",
    "sg:tags":[
        "grocery",
        "store"
    ],
    "wof:name":"Timesavers Supermarket",
    "wof:placetype":"venue"
},
  "geometry": {"coordinates":[138.63502502399999,-34.9522476196],"type":"Point"}
}