{
  "type": "Feature",
  "properties": {
    "addr:full":"920 Nudgee Rd Northgate QLD 4013",
    "addr:housenumber":"920",
    "addr:postcode":"4013",
    "addr:street":"Nudgee Rd",
    "iso:country":"AU",
    "sg:address":"920 Nudgee Rd",
    "sg:city":"Northgate",
    "sg:classifiers":[
        {
            "category":"Manufacturing",
            "subcategory":"Metals",
            "type":"Manufacturing & Wholesale Goods"
        }
    ],
    "sg:phone":"+61 13 72 82",
    "sg:postcode":"4013",
    "sg:province":"QLD",
    "sg:tags":[
        "wholesaler",
        "aluminium",
        "mfrs"
    ],
    "wof:name":"Smorgon Steelmark Metals",
    "wof:placetype":"venue"
},
  "geometry": {"coordinates":[153.08551025400001,-27.3885478973],"type":"Point"}
}