{
  "type": "Feature",
  "properties": {
    "addr:full":"11 Industrial Drive Drv Somerville VIC 3912",
    "addr:housenumber":"11",
    "addr:postcode":"3912",
    "addr:street":"Industrial Drive Drv",
    "iso:country":"AU",
    "sg:address":"11 Industrial Drive Drv",
    "sg:city":"Somerville",
    "sg:classifiers":[
        {
            "category":"Train Station",
            "subcategory":"Light Rail",
            "type":"Transportation"
        }
    ],
    "sg:phone":"+61 1800 786 832",
    "sg:postcode":"3912",
    "sg:province":"VIC",
    "sg:tags":[
        "equipment",
        "energy",
        "solar"
    ],
    "sg:website":"http://www.suntechaustralia.com.au",
    "wof:name":"Suntech Pty. Ltd.",
    "wof:placetype":"venue"
},
  "geometry": {"coordinates":[145.18067932100001,-38.2197380066],"type":"Point"}
}