{
  "type": "Feature",
  "properties": {
    "addr:full":"Suite 304, 447 Upper Edward St Brisbane QLD 4000",
    "addr:housenumber":"447",
    "addr:postcode":"4000",
    "addr:street":"Upper Edward St",
    "iso:country":"AU",
    "sg:address":"Suite 304, 447 Upper Edward St",
    "sg:city":"Brisbane",
    "sg:classifiers":[
        {
            "category":"Professional",
            "subcategory":"Computer Services",
            "type":"Services"
        }
    ],
    "sg:phone":"+61 1300 368 609",
    "sg:postcode":"4000",
    "sg:province":"QLD",
    "sg:tags":[
        "package",
        "software"
    ],
    "wof:name":"AEC Systems Pty Ltd",
    "wof:placetype":"venue"
},
  "geometry": {"coordinates":[153.024490356,-27.4638004303],"type":"Point"}
}