{
  "type": "Feature",
  "properties": {
    "addr:full":"2 Beech St Maleny QLD 4552",
    "addr:housenumber":"2",
    "addr:postcode":"4552",
    "addr:street":"Beech St",
    "iso:country":"AU",
    "sg:address":"2 Beech St",
    "sg:city":"Maleny",
    "sg:classifiers":[
        {
            "category":"Retail",
            "subcategory":"Veterinary Services",
            "type":"Services"
        }
    ],
    "sg:phone":"+61 7 5494 3622",
    "sg:postcode":"4552",
    "sg:province":"QLD",
    "sg:tags":[
        "surgeon"
    ],
    "wof:name":"Duggan Tom",
    "wof:placetype":"venue"
},
  "geometry": {"coordinates":[152.847930908,-26.7576503754],"type":"Point"}
}