{
  "type": "Feature",
  "properties": {
    "iso:country":"AU",
    "sg:address":"PO Box 1278",
    "sg:city":"Bribie Island",
    "sg:classifiers":[
        {
            "category":"Retail",
            "subcategory":"Auto Rental",
            "type":"Services"
        }
    ],
    "sg:phone":"+61 7 3408 1181",
    "sg:postcode":"4507",
    "sg:province":"QLD",
    "sg:tags":[
        "car",
        "wedding"
    ],
    "wof:name":"Bribie Island Limousine Service",
    "wof:placetype":"venue"
},
  "geometry": {"coordinates":[153.14137268100001,-26.9570903778],"type":"Point"}
}