{
  "type": "Feature",
  "properties": {
    "addr:full":"Unit 1, 93 Newton Rd Wetherill Park NSW 2164",
    "addr:housenumber":"93",
    "addr:postcode":"2164",
    "addr:street":"Newton Rd",
    "iso:country":"AU",
    "sg:address":"Unit 1, 93 Newton Rd",
    "sg:city":"Wetherill Park",
    "sg:classifiers":[
        {
            "category":"Wholesale",
            "subcategory":"Machinery & Supplies",
            "type":"Manufacturing & Wholesale Goods"
        }
    ],
    "sg:phone":"+61 2 9725 3955",
    "sg:postcode":"2164",
    "sg:province":"NSW",
    "sg:tags":[
        "belting",
        "mfrs"
    ],
    "wof:name":"Australian Belt & Hose Suppliers Pty Ltd",
    "wof:placetype":"venue"
},
  "geometry": {"coordinates":[150.891555786,-33.8476486206],"type":"Point"}
}