{
  "type": "Feature",
  "properties": {
    "addr:full":"197 Maidstone St Altona VIC 3018",
    "addr:housenumber":"197",
    "addr:postcode":"3018",
    "addr:street":"Maidstone St",
    "iso:country":"AU",
    "sg:address":"197 Maidstone St",
    "sg:city":"Altona",
    "sg:phone":"+61 3 9316 2601",
    "sg:postcode":"3018",
    "sg:province":"VIC",
    "wof:name":"Icon Industries",
    "wof:placetype":"venue"
},
  "geometry": {"coordinates":[144.81007385300001,-37.8584747314],"type":"Point"}
}