{
  "type": "Feature",
  "properties": {
    "addr:full":"Malibu Rd Safety Bay WA 6169",
    "addr:postcode":"6169",
    "addr:street":"Malibu Rd",
    "iso:country":"AU",
    "sg:address":"Malibu Rd",
    "sg:city":"Safety Bay",
    "sg:classifiers":[
        {
            "category":"Shopping",
            "subcategory":"Pets & Pet Supplies",
            "type":"Retail Goods"
        }
    ],
    "sg:phone":"+61 8 9528 3333",
    "sg:postcode":"6169",
    "sg:province":"WA",
    "sg:tags":[
        "food"
    ],
    "wof:name":"Malibu Veterinary Clinic",
    "wof:placetype":"venue"
},
  "geometry": {"coordinates":[115.732857,-32.308945],"type":"Point"}
}