{
  "type": "Feature",
  "properties": {
    "iso:country":"AU",
    "sg:address":"31 Barr Scott Drv",
    "sg:city":"Lismore Heights",
    "sg:classifiers":[
        {
            "category":"Professional",
            "subcategory":"Art Services",
            "type":"Services"
        }
    ],
    "sg:phone":"+61 2 6624 5820",
    "sg:postcode":"2480",
    "sg:province":"NSW",
    "sg:tags":[
        "decorator",
        "painter"
    ],
    "wof:name":"Doug Pollard Painting Pty Ltd",
    "wof:placetype":"venue"
},
  "geometry": {"coordinates":[153.30670165999999,-28.8081474304],"type":"Point"}
}