{
  "type": "Feature",
  "properties": {
    "iso:country":"AU",
    "sg:address":"Shop 3/ 11 Merimbula Drv",
    "sg:city":"Merimbula",
    "sg:classifiers":[
        {
            "category":"Professional",
            "subcategory":"Employment Agencies",
            "type":"Services"
        }
    ],
    "sg:phone":"+61 1800 069 050",
    "sg:postcode":"2548",
    "sg:province":"NSW",
    "sg:tags":[
        "provider",
        "internet"
    ],
    "wof:name":"Dragnet Internet Services Pty Ltd",
    "wof:placetype":"venue"
},
  "geometry": {"coordinates":[149.90943908700001,-36.8876876831],"type":"Point"}
}