{
  "type": "Feature",
  "properties": {
    "iso:country":"AU",
    "sg:address":"322 Darling St",
    "sg:city":"Balmain",
    "sg:classifiers":[
        {
            "category":"Health Services",
            "subcategory":"Dentist",
            "type":"Services"
        }
    ],
    "sg:phone":"+61 2 9555 7959",
    "sg:postcode":"2041",
    "sg:province":"NSW",
    "wof:name":"Barber Mark Dr",
    "wof:placetype":"venue"
},
  "geometry": {"coordinates":[151.17970299999999,-33.856968],"type":"Point"}
}