{
  "type": "Feature",
  "properties": {
    "addr:full":"Rear 1152 Burwood Hwy Ferntree Gully VIC 3156",
    "addr:housenumber":"1152",
    "addr:postcode":"3156",
    "addr:street":"Burwood Hwy",
    "iso:country":"AU",
    "sg:address":"Rear 1152 Burwood Hwy",
    "sg:city":"Ferntree Gully",
    "sg:classifiers":[
        {
            "category":"Wholesale",
            "subcategory":"Auto Parts",
            "type":"Manufacturing & Wholesale Goods"
        }
    ],
    "sg:phone":"+61 3 9758 6900",
    "sg:postcode":"3156",
    "sg:province":"VIC",
    "sg:tags":[
        "recyclers"
    ],
    "wof:name":"Falparts Autowreckers",
    "wof:placetype":"venue"
},
  "geometry": {"coordinates":[145.301605225,-37.8914833069],"type":"Point"}
}