{
  "type": "Feature",
  "properties": {
    "iso:country":"AU",
    "sg:address":"PO Box 244",
    "sg:city":"Terrigal",
    "sg:classifiers":[
        {
            "category":"Military Area",
            "subcategory":"Army Base",
            "type":"Public Place"
        }
    ],
    "sg:phone":"+61 2 4367 6700",
    "sg:postcode":"2260",
    "sg:province":"NSW",
    "sg:tags":[
        "concrete",
        "slab",
        "floor"
    ],
    "wof:name":"Lee T & M",
    "wof:placetype":"venue"
},
  "geometry": {"coordinates":[151.445709,-33.4478],"type":"Point"}
}