{
  "type": "Feature",
  "properties": {
    "addr:full":"383 Clayton Rd Clayton VIC 3168",
    "addr:housenumber":"383",
    "addr:postcode":"3168",
    "addr:street":"Clayton Rd",
    "iso:country":"AU",
    "sg:address":"383 Clayton Rd",
    "sg:city":"Clayton",
    "sg:classifiers":[
        {
            "category":"Shopping",
            "subcategory":"Shoes",
            "type":"Retail Goods"
        }
    ],
    "sg:phone":"+61 3 9544 6767",
    "sg:postcode":"3168",
    "sg:province":"VIC",
    "sg:tags":[
        "footwear"
    ],
    "wof:name":"I Shoes Factory Outlet",
    "wof:placetype":"venue"
},
  "geometry": {"coordinates":[145.11912536599999,-37.9272613525],"type":"Point"}
}