{
  "type": "Feature",
  "properties": {
    "addr:full":"PO Box 7382 Toowoomba Mail Centre QLD 4352",
    "addr:postcode":"4352",
    "iso:country":"AU",
    "sg:address":"PO Box 7382",
    "sg:city":"Toowoomba Mail Centre",
    "sg:classifiers":[
        {
            "category":"Farming",
            "subcategory":"Nursery",
            "type":"Manufacturing & Wholesale Goods"
        }
    ],
    "sg:phone":"+61 7 4630 9410",
    "sg:postcode":"4352",
    "sg:province":"QLD",
    "wof:name":"Toowoomba Wildflowers",
    "wof:placetype":"venue"
},
  "geometry": {"coordinates":[151.59376499999999,-28.363979],"type":"Point"}
}