{
  "type": "Feature",
  "properties": {
    "addr:full":"68 Shirley Rd Wollstonecraft NSW 2065",
    "addr:housenumber":"68",
    "addr:postcode":"2065",
    "addr:street":"Shirley Rd",
    "iso:country":"AU",
    "sg:address":"68 Shirley Rd",
    "sg:city":"Wollstonecraft",
    "sg:classifiers":[
        {
            "category":"Shopping",
            "subcategory":"Computers & Home Electronics",
            "type":"Retail Goods"
        }
    ],
    "sg:phone":"+61 1300 766 834",
    "sg:postcode":"2065",
    "sg:province":"NSW",
    "sg:tags":[
        "hardware",
        "equipment"
    ],
    "wof:name":"Compustore Australia",
    "wof:placetype":"venue"
},
  "geometry": {"coordinates":[151.194549561,-33.8317222595],"type":"Point"}
}