{
  "type": "Feature",
  "properties": {
    "iso:country":"AU",
    "sg:address":"4 Ballina St",
    "sg:city":"Kelvin Grove",
    "sg:classifiers":[
        {
            "category":"Building & Trades",
            "subcategory":"Cleaning & Sanitation",
            "type":"Services"
        }
    ],
    "sg:phone":"+61 7 3356 7110",
    "sg:postcode":"4059",
    "sg:province":"QLD",
    "sg:tags":[
        "industrial",
        "commercial",
        "contractor"
    ],
    "wof:name":"A & U Cleaning Services",
    "wof:placetype":"venue"
},
  "geometry": {"coordinates":[153.012771606,-27.4482593536],"type":"Point"}
}