{
  "type": "Feature",
  "properties": {
    "addr:full":"6 Smith St Charlestown NSW 2290",
    "addr:housenumber":"6",
    "addr:postcode":"2290",
    "addr:street":"Smith St",
    "iso:country":"AU",
    "sg:address":"6 Smith St",
    "sg:city":"Charlestown",
    "sg:classifiers":[
        {
            "category":"Retail",
            "subcategory":"Veterinary Services",
            "type":"Services"
        }
    ],
    "sg:phone":"+61 2 4943 6066",
    "sg:postcode":"2290",
    "sg:province":"NSW",
    "sg:tags":[
        "surgeon"
    ],
    "wof:name":"Warland Jenny",
    "wof:placetype":"venue"
},
  "geometry": {"coordinates":[151.69764709500001,-32.9617118835],"type":"Point"}
}