{
  "type": "Feature",
  "properties": {
    "addr:full":"Unit 11, 92 John Whiteway Drv Gosford NSW 2250",
    "addr:housenumber":"92",
    "addr:postcode":"2250",
    "addr:street":"John Whiteway Drv",
    "iso:country":"AU",
    "sg:address":"Unit 11, 92 John Whiteway Drv",
    "sg:city":"Gosford",
    "sg:classifiers":[
        {
            "category":"Professional",
            "subcategory":"Computer Services",
            "type":"Services"
        }
    ],
    "sg:phone":"+61 2 4324 8844",
    "sg:postcode":"2250",
    "sg:province":"NSW",
    "sg:tags":[
        "equipment",
        "networking",
        "installation"
    ],
    "wof:name":"Global Citytrade",
    "wof:placetype":"venue"
},
  "geometry": {"coordinates":[151.344192505,-33.4310951233],"type":"Point"}
}