{
  "type": "Feature",
  "properties": {
    "iso:country":"AU",
    "sg:address":"PO Box 584",
    "sg:city":"Applecross",
    "sg:classifiers":[
        {
            "category":"School Buses",
            "type":"Transportation"
        }
    ],
    "sg:phone":"+61 8 9330 8822",
    "sg:postcode":"6153",
    "sg:province":"WA",
    "sg:tags":[
        "nanny"
    ],
    "wof:name":"Europa Employment",
    "wof:placetype":"venue"
},
  "geometry": {"coordinates":[115.834808,-32.010342],"type":"Point"}
}