{
  "type": "Feature",
  "properties": {
    "iso:country":"AU",
    "sg:address":"111 Main St",
    "sg:city":"Lithgow",
    "sg:classifiers":[
        {
            "category":"Personal",
            "subcategory":"Hair Removal",
            "type":"Services"
        }
    ],
    "sg:phone":"+61 2 6352 2433",
    "sg:postcode":"2790",
    "sg:province":"NSW",
    "wof:name":"Silhouette Beauty Salon",
    "wof:placetype":"venue"
},
  "geometry": {"coordinates":[150.15397644000001,-33.4824142456],"type":"Point"}
}