{
  "type": "Feature",
  "properties": {
    "iso:country":"AU",
    "sg:address":"10 Pinetree Drv",
    "sg:city":"Carlingford",
    "sg:classifiers":[
        {
            "category":"Wholesale",
            "subcategory":"Painting Supplies",
            "type":"Manufacturing & Wholesale Goods"
        }
    ],
    "sg:phone":"+61 2 9871 2175",
    "sg:postcode":"2118",
    "sg:province":"NSW",
    "sg:tags":[
        "product",
        "cleaning"
    ],
    "wof:name":"Northwest Workshop Supplies",
    "wof:placetype":"venue"
},
  "geometry": {"coordinates":[151.04629516599999,-33.7645645142],"type":"Point"}
}