{
  "type": "Feature",
  "properties": {
    "addr:full":"4 Bennion St Trigg WA 6029",
    "addr:housenumber":"4",
    "addr:postcode":"6029",
    "addr:street":"Bennion St",
    "iso:country":"AU",
    "sg:address":"4 Bennion St",
    "sg:city":"Trigg",
    "sg:classifiers":[
        {
            "category":"Farming",
            "subcategory":"Farm & Veterinary Services",
            "type":"Manufacturing & Wholesale Goods"
        }
    ],
    "sg:phone":"+61 8 9447 8028",
    "sg:postcode":"6029",
    "sg:province":"WA",
    "sg:tags":[
        "irrigation",
        "reticulation",
        "system"
    ],
    "wof:name":"Field Plumbing & Reticulation Co.",
    "wof:placetype":"venue"
},
  "geometry": {"coordinates":[115.75316619900001,-31.8719558716],"type":"Point"}
}