{
  "type": "Feature",
  "properties": {
    "iso:country":"AU",
    "sg:address":"2 Lockhart Pl",
    "sg:city":"Gosnells",
    "sg:classifiers":[
        {
            "category":"Retail",
            "subcategory":"Veterinary Services",
            "type":"Services"
        }
    ],
    "sg:phone":"+61 8 9490 1812",
    "sg:postcode":"6110",
    "sg:province":"WA",
    "sg:tags":[
        "surgeon"
    ],
    "wof:name":"Deep Wood Veterinary Hospital",
    "wof:placetype":"venue"
},
  "geometry": {"coordinates":[116.01139831499999,-32.0835151672],"type":"Point"}
}