{
  "type": "Feature",
  "properties": {
    "addr:full":"PO Box 240 Hornsby NSW 2077",
    "addr:postcode":"2077",
    "iso:country":"AU",
    "sg:address":"PO Box 240",
    "sg:city":"Hornsby",
    "sg:phone":"+61 2 9477 7944",
    "sg:postcode":"2077",
    "sg:province":"NSW",
    "wof:name":"Permastore Tanks & Silos",
    "wof:placetype":"venue"
},
  "geometry": {"coordinates":[151.09687805199999,-33.7007789612],"type":"Point"}
}