{
  "type": "Feature",
  "properties": {
    "iso:country":"AU",
    "sg:address":"unit 1 \\\\ 59A Telopea St",
    "sg:city":"Mt Colah",
    "sg:classifiers":[
        {
            "category":"Professional",
            "subcategory":"Art Services",
            "type":"Services"
        }
    ],
    "sg:phone":"+61 2 9482 5741",
    "sg:postcode":"2079",
    "sg:province":"NSW",
    "sg:tags":[
        "interior",
        "designer"
    ],
    "wof:name":"Element Designgroup",
    "wof:placetype":"venue"
},
  "geometry": {"coordinates":[151.11857605,-33.6695556641],"type":"Point"}
}