{
  "type": "Feature",
  "properties": {
    "addr:full":"1909 Ipswich Rd Rocklea QLD 4106",
    "addr:housenumber":"1909",
    "addr:postcode":"4106",
    "addr:street":"Ipswich Rd",
    "iso:country":"AU",
    "sg:address":"1909 Ipswich Rd",
    "sg:city":"Rocklea",
    "sg:classifiers":[
        {
            "category":"Shopping",
            "subcategory":"Computers & Home Electronics",
            "type":"Retail Goods"
        }
    ],
    "sg:phone":"+61 7 3272 7466",
    "sg:postcode":"4106",
    "sg:province":"QLD",
    "sg:tags":[
        "hire",
        "video",
        "game"
    ],
    "wof:name":"Express Direct",
    "wof:placetype":"venue"
},
  "geometry": {"coordinates":[152.99528503400001,-27.5610332489],"type":"Point"}
}