{
  "type": "Feature",
  "properties": {
    "addr:full":"2nd Floor, 50 Grenfell St Adelaide SA 5000",
    "addr:housenumber":"50",
    "addr:postcode":"5000",
    "addr:street":"Grenfell St",
    "iso:country":"AU",
    "sg:address":"2nd Floor, 50 Grenfell St",
    "sg:city":"Adelaide",
    "sg:classifiers":[
        {
            "category":"Banks & Credit Unions",
            "subcategory":"Financial Services",
            "type":"Services"
        }
    ],
    "sg:phone":"+61 8 8203 0275",
    "sg:postcode":"5000",
    "sg:province":"SA",
    "sg:tags":[
        "planning"
    ],
    "wof:name":"Gillies R",
    "wof:placetype":"venue"
},
  "geometry": {"coordinates":[138.60154724099999,-34.924079895],"type":"Point"}
}