{
  "type": "Feature",
  "properties": {
    "iso:country":"AU",
    "sg:address":"30 Maud St",
    "sg:city":"Maroochydore",
    "sg:classifiers":[
        {
            "category":"Professional",
            "subcategory":"Printing & Photocopies",
            "type":"Services"
        }
    ],
    "sg:phone":"+61 7 5430 4844",
    "sg:postcode":"4558",
    "sg:province":"QLD",
    "sg:tags":[
        "photocopier"
    ],
    "wof:name":"Laser Change",
    "wof:placetype":"venue"
},
  "geometry": {"coordinates":[153.093673706,-26.6577701569],"type":"Point"}
}