{
  "type": "Feature",
  "properties": {
    "iso:country":"AU",
    "sg:address":"Shop 5 Craigieburn Plaza Craigieburn Rd",
    "sg:city":"Craigieburn",
    "sg:classifiers":[
        {
            "category":"Real Estate",
            "subcategory":"Real Estate Agent",
            "type":"Services"
        }
    ],
    "sg:phone":"+61 3 9308 3000",
    "sg:postcode":"3064",
    "sg:province":"VIC",
    "wof:name":"Ray White Craigieburn",
    "wof:placetype":"venue"
},
  "geometry": {"coordinates":[144.944854736,-37.5995178223],"type":"Point"}
}