{
  "type": "Feature",
  "properties": {
    "addr:full":"1/ 111 Industrial Rd Oak Flats NSW 2529",
    "addr:housenumber":"/ 111",
    "addr:postcode":"2529",
    "addr:street":"Industrial Rd",
    "iso:country":"AU",
    "sg:address":"1/ 111 Industrial Rd",
    "sg:city":"Oak Flats",
    "sg:classifiers":[
        {
            "category":"Retail",
            "subcategory":"Auto Repair",
            "type":"Services"
        }
    ],
    "sg:phone":"+61 2 4257 6042",
    "sg:postcode":"2529",
    "sg:province":"NSW",
    "sg:tags":[
        "electrical"
    ],
    "wof:name":"Apollo Batteries",
    "wof:placetype":"venue"
},
  "geometry": {"coordinates":[150.80984497099999,-34.5668373108],"type":"Point"}
}