{
  "type": "Feature",
  "properties": {
    "iso:country":"AU",
    "sg:address":"19- 23 Bolam St",
    "sg:city":"Garbutt",
    "sg:classifiers":[
        {
            "category":"Building & Trades",
            "subcategory":"Cleaning & Sanitation",
            "type":"Services"
        }
    ],
    "sg:phone":"+61 7 4774 7717",
    "sg:postcode":"4814",
    "sg:province":"QLD",
    "sg:tags":[
        "abrasive",
        "blasting"
    ],
    "wof:name":"Mobile Aqua Services Pty Ltd",
    "wof:placetype":"venue"
},
  "geometry": {"coordinates":[146.770248,-19.265593],"type":"Point"}
}