{
  "type": "Feature",
  "properties": {
    "addr:full":"219 Katoomba St Katoomba NSW 2780",
    "addr:housenumber":"219",
    "addr:postcode":"2780",
    "addr:street":"Katoomba St",
    "iso:country":"AU",
    "sg:address":"219 Katoomba St",
    "sg:city":"Katoomba",
    "sg:classifiers":[
        {
            "category":"Health Services",
            "subcategory":"Health Practitioner",
            "type":"Services"
        }
    ],
    "sg:phone":"+61 2 4787 7991",
    "sg:postcode":"2780",
    "sg:province":"NSW",
    "sg:tags":[
        "acupuncture"
    ],
    "wof:name":"Mayroz Ruth",
    "wof:placetype":"venue"
},
  "geometry": {"coordinates":[150.311447144,-33.7155838013],"type":"Point"}
}