{
  "type": "Feature",
  "properties": {
    "addr:full":"329 Murray St Perth WA 6000",
    "addr:housenumber":"329",
    "addr:postcode":"6000",
    "addr:street":"Murray St",
    "iso:country":"AU",
    "sg:address":"329 Murray St",
    "sg:city":"Perth",
    "sg:classifiers":[
        {
            "category":"Real Estate",
            "subcategory":"Real Estate Agent",
            "type":"Services"
        }
    ],
    "sg:phone":"+61 8 9481 5610",
    "sg:postcode":"6000",
    "sg:province":"WA",
    "sg:tags":[
        "consultant",
        "heritage"
    ],
    "wof:name":"Heritage & Conservation Professionals",
    "wof:placetype":"venue"
},
  "geometry": {"coordinates":[115.854019165,-31.9514408112],"type":"Point"}
}