{
  "type": "Feature",
  "properties": {
    "addr:full":"24 Wainhouse St Torrensville SA 5031",
    "addr:housenumber":"24",
    "addr:postcode":"5031",
    "addr:street":"Wainhouse St",
    "iso:country":"AU",
    "sg:address":"24 Wainhouse St",
    "sg:city":"Torrensville",
    "sg:classifiers":[
        {
            "category":"Professional",
            "subcategory":"Art Services",
            "type":"Services"
        }
    ],
    "sg:phone":"+61 8 8443 5524",
    "sg:postcode":"5031",
    "sg:province":"SA",
    "sg:tags":[
        "decorator",
        "painter"
    ],
    "wof:name":"Martino Painters",
    "wof:placetype":"venue"
},
  "geometry": {"coordinates":[138.56605529800001,-34.9215087891],"type":"Point"}
}