{
  "type": "Feature",
  "properties": {
    "addr:full":"68 Bathurst Rd Orange NSW 2800",
    "addr:housenumber":"68",
    "addr:postcode":"2800",
    "addr:street":"Bathurst Rd",
    "iso:country":"AU",
    "sg:address":"68 Bathurst Rd",
    "sg:city":"Orange",
    "sg:classifiers":[
        {
            "category":"Retail",
            "subcategory":"Auto Rental",
            "type":"Services"
        }
    ],
    "sg:phone":"+61 2 6362 9678",
    "sg:postcode":"2800",
    "sg:province":"NSW",
    "sg:tags":[
        "car",
        "hire",
        "minibus"
    ],
    "wof:name":"Rent Me",
    "wof:placetype":"venue"
},
  "geometry": {"coordinates":[149.10569763199999,-33.2853088379],"type":"Point"}
}