{
  "type": "Feature",
  "properties": {
    "addr:full":"150 Pakington St Geelong West VIC 3218",
    "addr:housenumber":"150",
    "addr:postcode":"3218",
    "addr:street":"Pakington St",
    "iso:country":"AU",
    "sg:address":"150 Pakington St",
    "sg:city":"Geelong West",
    "sg:classifiers":[
        {
            "category":"Food & Beverages",
            "subcategory":"Liquor & Beverages",
            "type":"Retail Goods"
        }
    ],
    "sg:phone":"+61 3 5229 5358",
    "sg:postcode":"3218",
    "sg:province":"VIC",
    "sg:tags":[
        "merchant",
        "spirit",
        "wine"
    ],
    "wof:name":"Bannockburn Cellars",
    "wof:placetype":"venue"
},
  "geometry": {"coordinates":[144.348556519,-38.1402397156],"type":"Point"}
}