{
  "type": "Feature",
  "properties": {
    "addr:full":"Shop 7/ 7 Gawler St Nuriootpa SA 5355",
    "addr:housenumber":"shop 7 / 7",
    "addr:postcode":"5355",
    "addr:street":"Gawler St",
    "iso:country":"AU",
    "sg:address":"Shop 7/ 7 Gawler St",
    "sg:city":"Nuriootpa",
    "sg:classifiers":[
        {
            "category":"Retail",
            "subcategory":"Laundry & Dry Cleaning",
            "type":"Services"
        }
    ],
    "sg:phone":"+61 8 8562 2344",
    "sg:postcode":"5355",
    "sg:province":"SA",
    "wof:name":"Barossa Dry Cleaners",
    "wof:placetype":"venue"
},
  "geometry": {"coordinates":[138.99378967300001,-34.4725608826],"type":"Point"}
}