{
  "type": "Feature",
  "properties": {
    "addr:full":"PO Box 694 Dalby QLD 4405",
    "addr:postcode":"4405",
    "iso:country":"AU",
    "sg:address":"PO Box 694",
    "sg:city":"Dalby",
    "sg:classifiers":[
        {
            "category":"Retail",
            "subcategory":"Storage",
            "type":"Services"
        }
    ],
    "sg:phone":"+61 7 4669 6183",
    "sg:postcode":"4405",
    "sg:province":"QLD",
    "sg:tags":[
        "removal",
        "furniture"
    ],
    "wof:name":"Dalby Removals",
    "wof:placetype":"venue"
},
  "geometry": {"coordinates":[151.273681641,-27.1841831207],"type":"Point"}
}