{
  "type": "Feature",
  "properties": {
    "addr:full":"396 High St Northcote VIC 3070",
    "addr:housenumber":"396",
    "addr:postcode":"3070",
    "addr:street":"High St",
    "iso:country":"AU",
    "sg:address":"396 High St",
    "sg:city":"Northcote",
    "sg:classifiers":[
        {
            "category":"Home & Garden",
            "subcategory":"Hardware",
            "type":"Retail Goods"
        }
    ],
    "sg:phone":"+61 3 9481 4930",
    "sg:postcode":"3070",
    "sg:province":"VIC",
    "sg:tags":[
        "plumber",
        "supply"
    ],
    "wof:name":"Red Star Plumbing & Hardware Supplies",
    "wof:placetype":"venue"
},
  "geometry": {"coordinates":[144.99939000000001,-37.768181],"type":"Point"}
}