{
  "type": "Feature",
  "properties": {
    "addr:full":"658 Windsor Rd Rouse Hill Windsor NSW 2756",
    "addr:housenumber":"658",
    "addr:postcode":"2756",
    "addr:street":"Windsor Rd",
    "iso:country":"AU",
    "sg:address":"658 Windsor Rd Rouse Hill",
    "sg:city":"Windsor",
    "sg:classifiers":[
        {
            "category":"Fast Food",
            "type":"Food & Drink"
        }
    ],
    "sg:phone":"+61 2 8824 3502",
    "sg:postcode":"2756",
    "sg:province":"NSW",
    "sg:tags":[
        "away",
        "take"
    ],
    "wof:name":"Red Rooster",
    "wof:placetype":"venue"
},
  "geometry": {"coordinates":[150.929443359,-33.6676673889],"type":"Point"}
}