{
  "type": "Feature",
  "properties": {
    "iso:country":"AU",
    "sg:address":"536 Midland Hwy",
    "sg:city":"Huntly",
    "sg:classifiers":[
        {
            "category":"Autos & Motor Vehicles",
            "subcategory":"Auto Supplies",
            "type":"Retail Goods"
        }
    ],
    "sg:phone":"+61 3 5448 8838",
    "sg:postcode":"3551",
    "sg:province":"VIC",
    "sg:tags":[
        "part",
        "cycles",
        "accessory"
    ],
    "wof:name":"Huntly Dirt Bikes",
    "wof:placetype":"venue"
},
  "geometry": {"coordinates":[144.324493408,-36.6725234985],"type":"Point"}
}