{
  "type": "Feature",
  "properties": {
    "iso:country":"AU",
    "sg:address":"3/ 73 Albert Ave",
    "sg:city":"Chatswood",
    "sg:classifiers":[
        {
            "category":"Government",
            "subcategory":"Court House",
            "type":"Public Place"
        }
    ],
    "sg:phone":"+61 2 9413 9711",
    "sg:postcode":"2067",
    "sg:province":"NSW",
    "sg:tags":[
        "personal",
        "marriage",
        "family",
        "counselling"
    ],
    "wof:name":"Helen Rutherford",
    "wof:placetype":"venue"
},
  "geometry": {"coordinates":[151.187011719,-33.7966461182],"type":"Point"}
}