{
  "type": "Feature",
  "properties": {
    "iso:country":"AU",
    "sg:address":"7 Second Ave",
    "sg:city":"Mt Lawley",
    "sg:classifiers":[
        {
            "category":"Professional",
            "subcategory":"Business Services",
            "type":"Services"
        }
    ],
    "sg:phone":"+61 8 9271 2844",
    "sg:postcode":"6050",
    "sg:province":"WA",
    "sg:tags":[
        "drafting"
    ],
    "wof:name":"Stuart Kessell Drafting",
    "wof:placetype":"venue"
},
  "geometry": {"coordinates":[115.88276672400001,-31.9322013855],"type":"Point"}
}