{
  "type": "Feature",
  "properties": {
    "addr:full":"126 Buchan St Cairns QLD 4870",
    "addr:housenumber":"126",
    "addr:postcode":"4870",
    "addr:street":"Buchan St",
    "iso:country":"AU",
    "sg:address":"126 Buchan St",
    "sg:city":"Cairns",
    "sg:classifiers":[
        {
            "category":"Professional",
            "subcategory":"Printing & Photocopies",
            "type":"Services"
        }
    ],
    "sg:phone":"+61 7 4035 3700",
    "sg:postcode":"4870",
    "sg:province":"QLD",
    "sg:tags":[
        "rubber",
        "stamp",
        "metal"
    ],
    "wof:name":"Print Force Queensland",
    "wof:placetype":"venue"
},
  "geometry": {"coordinates":[145.76530456500001,-16.9342193604],"type":"Point"}
}