{
  "type": "Feature",
  "properties": {
    "iso:country":"AU",
    "sg:address":"25 Portsmouth Rd",
    "sg:city":"Erina",
    "sg:classifiers":[
        {
            "category":"Retail",
            "subcategory":"Event Space",
            "type":"Services"
        }
    ],
    "sg:phone":"+61 2 4365 3968",
    "sg:postcode":"2250",
    "sg:province":"NSW",
    "sg:tags":[
        "venue",
        "reception",
        "wedding"
    ],
    "wof:name":"St Fiacre Distillery",
    "wof:placetype":"venue"
},
  "geometry": {"coordinates":[151.40277099599999,-33.4314346313],"type":"Point"}
}