{
  "type": "Feature",
  "properties": {
    "iso:country":"AU",
    "sg:address":"60 Enterprise St",
    "sg:city":"Mackay",
    "sg:classifiers":[
        {
            "category":"Home & Garden",
            "subcategory":"Hardware",
            "type":"Retail Goods"
        }
    ],
    "sg:phone":"+61 7 4952 4780",
    "sg:postcode":"4740",
    "sg:province":"QLD",
    "sg:tags":[
        "nut",
        "bolt"
    ],
    "wof:name":"Mullings Fasteners",
    "wof:placetype":"venue"
},
  "geometry": {"coordinates":[149.15933200000001,-21.184093],"type":"Point"}
}