{
  "type": "Feature",
  "properties": {
    "addr:full":"315 Coates Park Rd Cobbitty NSW 2570",
    "addr:housenumber":"315",
    "addr:postcode":"2570",
    "addr:street":"Coates Park Rd",
    "iso:country":"AU",
    "sg:address":"315 Coates Park Rd",
    "sg:city":"Cobbitty",
    "sg:classifiers":[
        {
            "category":"Farming",
            "subcategory":"Livestock Farm",
            "type":"Manufacturing & Wholesale Goods"
        }
    ],
    "sg:phone":"+61 2 4651 2489",
    "sg:postcode":"2570",
    "sg:province":"NSW",
    "sg:tags":[
        "agistment"
    ],
    "wof:name":"Sugar Loaf Equestrian Centre",
    "wof:placetype":"venue"
},
  "geometry": {"coordinates":[150.67427063,-33.9715919495],"type":"Point"}
}