{
  "type": "Feature",
  "properties": {
    "iso:country":"AU",
    "sg:address":"3/ 9 Carr Pl",
    "sg:city":"Myaree",
    "sg:classifiers":[
        {
            "category":"Autos & Motor Vehicles",
            "subcategory":"Automobile Sales",
            "type":"Retail Goods"
        }
    ],
    "sg:phone":"+61 8 9330 4522",
    "sg:postcode":"6154",
    "sg:province":"WA",
    "sg:tags":[
        "car",
        "new"
    ],
    "wof:name":"Harry Dutton Motor Co",
    "wof:placetype":"venue"
},
  "geometry": {"coordinates":[115.815262,-32.045143],"type":"Point"}
}