{
  "type": "Feature",
  "properties": {
    "addr:full":"Unit 18, 43- 45 College St Gladesville NSW 2111",
    "addr:housenumber":"43 45",
    "addr:postcode":"2111",
    "addr:street":"College St",
    "iso:country":"AU",
    "sg:address":"Unit 18, 43- 45 College St",
    "sg:city":"Gladesville",
    "sg:classifiers":[
        {
            "category":"Wholesale",
            "subcategory":"Construction Materials",
            "type":"Manufacturing & Wholesale Goods"
        }
    ],
    "sg:phone":"+61 2 9879 3699",
    "sg:postcode":"2111",
    "sg:province":"NSW",
    "sg:tags":[
        "wholesaler",
        "lighting",
        "mfrs",
        "accessory"
    ],
    "wof:name":"Composite Lighting Pty Ltd",
    "wof:placetype":"venue"
},
  "geometry": {"coordinates":[151.12150573700001,-33.8200912476],"type":"Point"}
}