{
  "type": "Feature",
  "properties": {
    "addr:full":"63 Waldheim St Annerley QLD 4103",
    "addr:housenumber":"63",
    "addr:postcode":"4103",
    "addr:street":"Waldheim St",
    "iso:country":"AU",
    "sg:address":"63 Waldheim St",
    "sg:city":"Annerley",
    "sg:classifiers":[
        {
            "category":"Sports & Exercise",
            "subcategory":"Gym",
            "type":"Entertainment"
        }
    ],
    "sg:phone":"+61 7 3892 5512",
    "sg:postcode":"4103",
    "sg:province":"QLD",
    "sg:tags":[
        "health",
        "fitness"
    ],
    "wof:name":"Annerley Yoga School",
    "wof:placetype":"venue"
},
  "geometry": {"coordinates":[153.036453247,-27.5102539062],"type":"Point"}
}