{
  "type": "Feature",
  "properties": {
    "iso:country":"AU",
    "sg:address":"21 Scotland St",
    "sg:city":"Bundaberg",
    "sg:classifiers":[
        {
            "category":"Wholesale",
            "subcategory":"Painting Supplies",
            "type":"Manufacturing & Wholesale Goods"
        }
    ],
    "sg:phone":"+61 7 4153 5733",
    "sg:postcode":"4670",
    "sg:province":"QLD",
    "sg:tags":[
        "painter"
    ],
    "wof:name":"Refinish Australia Pty Ltd",
    "wof:placetype":"venue"
},
  "geometry": {"coordinates":[152.366455078,-24.8614807129],"type":"Point"}
}