{
  "type": "Feature",
  "properties": {
    "addr:full":"92 Main St Lilydale VIC 3140",
    "addr:housenumber":"92",
    "addr:postcode":"3140",
    "addr:street":"Main St",
    "iso:country":"AU",
    "sg:address":"92 Main St",
    "sg:city":"Lilydale",
    "sg:classifiers":[
        {
            "category":"Health Services",
            "subcategory":"Dentist",
            "type":"Services"
        }
    ],
    "sg:phone":"+61 3 9735 1121",
    "sg:postcode":"3140",
    "sg:province":"VIC",
    "wof:name":"Ang C R Dr",
    "wof:placetype":"venue"
},
  "geometry": {"coordinates":[145.34678649899999,-37.7571182251],"type":"Point"}
}