{
  "type": "Feature",
  "properties": {
    "iso:country":"AU",
    "sg:address":"18 Hartley Drv",
    "sg:city":"Thornton",
    "sg:classifiers":[
        {
            "category":"Structure",
            "subcategory":"Tunnel",
            "type":"Public Place"
        }
    ],
    "sg:phone":"+61 2 4966 5505",
    "sg:postcode":"2322",
    "sg:province":"NSW",
    "sg:tags":[
        "cleaner",
        "industrial",
        "vacuum"
    ],
    "wof:name":"Mainstream Industries",
    "wof:placetype":"venue"
},
  "geometry": {"coordinates":[151.63856506400001,-32.7882881165],"type":"Point"}
}