{
  "type": "Feature",
  "properties": {
    "iso:country":"AU",
    "sg:address":"112 Northern Rd",
    "sg:city":"Heidelberg West",
    "sg:classifiers":[
        {
            "category":"Building & Trades",
            "subcategory":"Plumbing",
            "type":"Services"
        }
    ],
    "sg:phone":"+61 3 9457 1056",
    "sg:postcode":"3081",
    "sg:province":"VIC",
    "sg:tags":[
        "plumber",
        "gasfitters"
    ],
    "wof:name":"R C Urquhart Pty Ltd",
    "wof:placetype":"venue"
},
  "geometry": {"coordinates":[145.05393981899999,-37.7301025391],"type":"Point"}
}