{
  "type": "Feature",
  "properties": {
    "addr:full":"300 Main Rd St Albans VIC 3021",
    "addr:housenumber":"300",
    "addr:postcode":"3021",
    "addr:street":"Main Rd",
    "iso:country":"AU",
    "sg:address":"300 Main Rd",
    "sg:city":"St Albans",
    "sg:classifiers":[
        {
            "category":"Professional",
            "subcategory":"Art Services",
            "type":"Services"
        }
    ],
    "sg:phone":"+61 3 9366 3551",
    "sg:postcode":"3021",
    "sg:province":"VIC",
    "sg:tags":[
        "picture",
        "frame",
        "framing"
    ],
    "wof:name":"Cleopatra Picture Framing",
    "wof:placetype":"venue"
},
  "geometry": {"coordinates":[144.80209400000001,-37.744347],"type":"Point"}
}