{
  "type": "Feature",
  "properties": {
    "addr:full":"1A Bates St Homebush NSW 2140",
    "addr:housenumber":"1a",
    "addr:postcode":"2140",
    "addr:street":"Bates St",
    "iso:country":"AU",
    "sg:address":"1A Bates St",
    "sg:city":"Homebush",
    "sg:classifiers":[
        {
            "category":"Social Services",
            "subcategory":"Child Care",
            "type":"Services"
        }
    ],
    "sg:phone":"+61 2 9746 9441",
    "sg:postcode":"2140",
    "sg:province":"NSW",
    "wof:name":"Strathfield Sessional Pre School",
    "wof:placetype":"venue"
},
  "geometry": {"coordinates":[151.07539367699999,-33.8653678894],"type":"Point"}
}