{
  "type": "Feature",
  "properties": {
    "addr:full":"116b Fitzroy Rd Rivervale WA 6103",
    "addr:housenumber":"116b",
    "addr:postcode":"6103",
    "addr:street":"Fitzroy Rd",
    "iso:country":"AU",
    "sg:address":"116b Fitzroy Rd",
    "sg:city":"Rivervale",
    "sg:classifiers":[
        {
            "category":"Retail",
            "subcategory":"Repair Shop",
            "type":"Services"
        }
    ],
    "sg:phone":"+61 8 9355 1596",
    "sg:postcode":"6103",
    "sg:province":"WA",
    "sg:tags":[
        "repairing",
        "piano",
        "tuning"
    ],
    "wof:name":"Anthony Wheatley",
    "wof:placetype":"venue"
},
  "geometry": {"coordinates":[115.915679932,-31.9620285034],"type":"Point"}
}