{
  "type": "Feature",
  "properties": {
    "iso:country":"AU",
    "sg:address":"616A Princes Hwy",
    "sg:city":"Bairnsdale",
    "sg:classifiers":[
        {
            "category":"Building & Trades",
            "subcategory":"Equipment Rental",
            "type":"Services"
        }
    ],
    "sg:phone":"+61 3 5152 1001",
    "sg:postcode":"3875",
    "sg:province":"VIC",
    "sg:tags":[
        "saw"
    ],
    "wof:name":"East Gippsland Saw Service",
    "wof:placetype":"venue"
},
  "geometry": {"coordinates":[147.60578918499999,-37.8335609436],"type":"Point"}
}