{
  "type": "Feature",
  "properties": {
    "addr:full":"117 Greens Rd Dandenong South VIC 3164",
    "addr:housenumber":"117",
    "addr:postcode":"3164",
    "addr:street":"Greens Rd",
    "iso:country":"AU",
    "sg:address":"117 Greens Rd",
    "sg:city":"Dandenong South",
    "sg:classifiers":[
        {
            "category":"Fast Food",
            "type":"Food & Drink"
        }
    ],
    "sg:phone":"+61 3 9791 6014",
    "sg:postcode":"3164",
    "sg:province":"VIC",
    "sg:tags":[
        "away",
        "take"
    ],
    "wof:name":"Greens Road Takeaway",
    "wof:placetype":"venue"
},
  "geometry": {"coordinates":[145.212646484,-38.0141220093],"type":"Point"}
}