{
  "type": "Feature",
  "properties": {
    "addr:full":"Anglican Retirement Services 23 Buskeed St Red Hill ACT 2603",
    "addr:housenumber":"23",
    "addr:postcode":"2603",
    "addr:street":"Buskeed St",
    "iso:country":"AU",
    "sg:address":"Anglican Retirement Services 23 Buskeed St",
    "sg:city":"Red Hill",
    "sg:classifiers":[
        {
            "category":"Travel",
            "subcategory":"Hostel",
            "type":"Entertainment"
        }
    ],
    "sg:phone":"+61 2 6255 2588",
    "sg:postcode":"2603",
    "sg:province":"ACT",
    "sg:tags":[
        "home"
    ],
    "wof:name":"St David's Close",
    "wof:placetype":"venue"
},
  "geometry": {"coordinates":[149.12684631400001,-35.3397903442],"type":"Point"}
}