{
  "type": "Feature",
  "properties": {
    "iso:country":"AU",
    "sg:address":"Lvl2/ 1 Cavill Ave",
    "sg:city":"Surfers Paradise",
    "sg:classifiers":[
        {
            "category":"Professional",
            "subcategory":"Engineering",
            "type":"Services"
        }
    ],
    "sg:phone":"+61 7 5526 8003",
    "sg:postcode":"4217",
    "sg:province":"QLD",
    "sg:tags":[
        "engineer"
    ],
    "wof:name":"Specialized Electrical Engineering Pty Ltd",
    "wof:placetype":"venue"
},
  "geometry": {"coordinates":[153.429397583,-28.0020923615],"type":"Point"}
}