{
  "type": "Feature",
  "properties": {
    "addr:full":"284 Strickland Ave South Hobart TAS 7004",
    "addr:housenumber":"284",
    "addr:postcode":"7004",
    "addr:street":"Strickland Ave",
    "iso:country":"AU",
    "sg:address":"284 Strickland Ave",
    "sg:city":"South Hobart",
    "sg:classifiers":[
        {
            "category":"Train Station",
            "subcategory":"Light Rail",
            "type":"Transportation"
        }
    ],
    "sg:phone":"+61 417 363 872",
    "sg:postcode":"7004",
    "sg:province":"TAS",
    "sg:tags":[
        "equipment",
        "energy",
        "solar"
    ],
    "wof:name":"JB Electrical",
    "wof:placetype":"venue"
},
  "geometry": {"coordinates":[147.27682495100001,-42.9033317566],"type":"Point"}
}