{
  "type": "Feature",
  "properties": {
    "addr:full":"789 High St Armadale VIC 3143",
    "addr:housenumber":"789",
    "addr:postcode":"3143",
    "addr:street":"High St",
    "iso:country":"AU",
    "sg:address":"789 High St",
    "sg:city":"Armadale",
    "sg:classifiers":[
        {
            "category":"Health Services",
            "subcategory":"Health Practitioner",
            "type":"Services"
        }
    ],
    "sg:phone":"+61 3 9576 0500",
    "sg:postcode":"3143",
    "sg:province":"VIC",
    "sg:tags":[
        "physiotherapist"
    ],
    "wof:name":"David Williams Physiotherapy",
    "wof:placetype":"venue"
},
  "geometry": {"coordinates":[145.01431274399999,-37.8545341492],"type":"Point"}
}