{
  "type": "Feature",
  "properties": {
    "iso:country":"AU",
    "sg:address":"20 Viola St",
    "sg:city":"North Mackay",
    "sg:classifiers":[
        {
            "category":"Communications",
            "type":"Services"
        }
    ],
    "sg:phone":"+61 7 4942 5031",
    "sg:postcode":"4740",
    "sg:province":"QLD",
    "sg:tags":[
        "equipment",
        "radio"
    ],
    "wof:name":"Radiocare",
    "wof:placetype":"venue"
},
  "geometry": {"coordinates":[149.147369,-21.114792],"type":"Point"}
}