{
  "type": "Feature",
  "properties": {
    "iso:country":"AU",
    "sg:address":"2/ 12- 14 Norman St",
    "sg:city":"Peakhurst",
    "sg:classifiers":[
        {
            "category":"Professional",
            "subcategory":"Printing & Photocopies",
            "type":"Services"
        }
    ],
    "sg:phone":"+61 2 9153 8247",
    "sg:postcode":"2210",
    "sg:province":"NSW",
    "sg:tags":[
        "screen",
        "printer"
    ],
    "wof:name":"Awesome Screenprinting",
    "wof:placetype":"venue"
},
  "geometry": {"coordinates":[151.06579600000001,-33.963833],"type":"Point"}
}