{
  "type": "Feature",
  "properties": {
    "iso:country":"AU",
    "sg:address":"Shop 2333",
    "sg:city":"A Caneland Central Mackay",
    "sg:classifiers":[
        {
            "category":"Manufacturing",
            "subcategory":"Petroleum Products",
            "type":"Manufacturing & Wholesale Goods"
        }
    ],
    "sg:phone":"+61 7 4957 8299",
    "sg:postcode":"4740",
    "sg:province":"QLD",
    "sg:tags":[
        "wax"
    ],
    "wof:name":"Ella Bache Mackay",
    "wof:placetype":"venue"
},
  "geometry": {"coordinates":[149.111847,-21.15519],"type":"Point"}
}