{
  "type": "Feature",
  "properties": {
    "addr:full":"27 Jones Ave Primbee NSW 2502",
    "addr:housenumber":"27",
    "addr:postcode":"2502",
    "addr:street":"Jones Ave",
    "iso:country":"AU",
    "sg:address":"27 Jones Ave",
    "sg:city":"Primbee",
    "sg:classifiers":[
        {
            "category":"Building & Trades",
            "subcategory":"Plumbing",
            "type":"Services"
        }
    ],
    "sg:phone":"+61 418 288 975",
    "sg:postcode":"2502",
    "sg:province":"NSW",
    "sg:tags":[
        "plumber",
        "gasfitters"
    ],
    "wof:name":"Gould John Plumbing",
    "wof:placetype":"venue"
},
  "geometry": {"coordinates":[150.88093599999999,-34.502567],"type":"Point"}
}