{
  "type": "Feature",
  "properties": {
    "iso:country":"AU",
    "sg:address":"9 Duke St",
    "sg:city":"Grafton",
    "sg:classifiers":[
        {
            "category":"Health Services",
            "subcategory":"Doctor",
            "type":"Services"
        }
    ],
    "sg:phone":"+61 2 6642 1977",
    "sg:postcode":"2460",
    "sg:province":"NSW",
    "sg:tags":[
        "medical",
        "practitioner"
    ],
    "wof:name":"Duke Street Medical Centre",
    "wof:placetype":"venue"
},
  "geometry": {"coordinates":[152.93406677199999,-29.6928958893],"type":"Point"}
}