{
  "type": "Feature",
  "properties": {
    "addr:full":"Basement 3 Moranbah Fair Moranbah QLD 4744",
    "addr:housenumber":"3",
    "addr:postcode":"4744",
    "addr:street":"Moranbah Fair",
    "iso:country":"AU",
    "sg:address":"Basement 3",
    "sg:city":"Moranbah Fair Moranbah",
    "sg:classifiers":[
        {
            "category":"Communications",
            "subcategory":"Film & Video Production",
            "type":"Services"
        }
    ],
    "sg:phone":"+61 7 4941 8745",
    "sg:postcode":"4744",
    "sg:province":"QLD",
    "sg:tags":[
        "television",
        "system",
        "circuit",
        "closed"
    ],
    "wof:name":"Moranbah Electronics",
    "wof:placetype":"venue"
},
  "geometry": {"coordinates":[148.09439086899999,-22.1004600525],"type":"Point"}
}