{
  "type": "Feature",
  "properties": {
    "iso:country":"AU",
    "sg:address":"198a Wynnum Rd",
    "sg:city":"Norman Park",
    "sg:classifiers":[
        {
            "category":"Social Services",
            "type":"Services"
        }
    ],
    "sg:phone":"+61 7 3899 8233",
    "sg:postcode":"4170",
    "sg:province":"QLD",
    "sg:tags":[
        "domestic",
        "help"
    ],
    "wof:name":"Ironing Shop The",
    "wof:placetype":"venue"
},
  "geometry": {"coordinates":[153.05990600600001,-27.472454071],"type":"Point"}
}