{
  "type": "Feature",
  "properties": {
    "iso:country":"AU",
    "sg:address":"198 Collins St",
    "sg:city":"Thornbury",
    "sg:classifiers":[
        {
            "category":"Retail",
            "subcategory":"Auto Rental",
            "type":"Services"
        }
    ],
    "sg:phone":"+61 3 9484 3999",
    "sg:postcode":"3071",
    "sg:province":"VIC",
    "sg:tags":[
        "chauffeur",
        "car",
        "hire",
        "driven",
        "limousine"
    ],
    "sg:website":"http://www.imagelimousines.com.au",
    "wof:name":"Image Limousines",
    "wof:placetype":"venue"
},
  "geometry": {"coordinates":[145.02032470699999,-37.756275177],"type":"Point"}
}