{
  "type": "Feature",
  "properties": {
    "addr:full":"Unit 2, 575 Blaxland Rd Eastwood NSW 2122",
    "addr:housenumber":"575",
    "addr:postcode":"2122",
    "addr:street":"Blaxland Rd",
    "iso:country":"AU",
    "sg:address":"Unit 2, 575 Blaxland Rd",
    "sg:city":"Eastwood",
    "sg:classifiers":[
        {
            "category":"Utilities",
            "subcategory":"Electric",
            "type":"Services"
        }
    ],
    "sg:phone":"+61 410 556 300",
    "sg:postcode":"2122",
    "sg:province":"NSW",
    "sg:tags":[
        "electrical",
        "contractor"
    ],
    "wof:name":"Marston Electrical Pty Ltd",
    "wof:placetype":"venue"
},
  "geometry": {"coordinates":[151.08909606899999,-33.7917633057],"type":"Point"}
}