{
  "type": "Feature",
  "properties": {
    "iso:country":"AU",
    "sg:address":"27 Donnybrook Rd",
    "sg:city":"Norlane",
    "sg:classifiers":[
        {
            "category":"Personal",
            "subcategory":"Beauty Salon",
            "type":"Services"
        }
    ],
    "sg:phone":"+61 3 5275 8680",
    "sg:postcode":"3214",
    "sg:province":"VIC",
    "sg:tags":[
        "hairdresser"
    ],
    "wof:name":"Diva Kutz Hair & Beauty",
    "wof:placetype":"venue"
},
  "geometry": {"coordinates":[144.34368896500001,-38.0863189697],"type":"Point"}
}