{
  "type": "Feature",
  "properties": {
    "addr:full":"PO Box 107+Ulladulla 2539 Ulladulla NSW 2539",
    "addr:housenumber":"2539",
    "addr:postcode":"2539",
    "iso:country":"AU",
    "sg:address":"PO Box 107+Ulladulla 2539",
    "sg:city":"Ulladulla",
    "sg:classifiers":[
        {
            "category":"Real Estate",
            "subcategory":"Surveying",
            "type":"Services"
        }
    ],
    "sg:phone":"+61 2 4454 2137",
    "sg:postcode":"2539",
    "sg:province":"NSW",
    "sg:tags":[
        "surveyor",
        "land"
    ],
    "wof:name":"Rygate & West+",
    "wof:placetype":"venue"
},
  "geometry": {"coordinates":[150.475631714,-35.3509788513],"type":"Point"}
}