{
  "type": "Feature",
  "properties": {
    "addr:full":"Maia House, 152 Morrison Rd Midland WA 6056",
    "addr:housenumber":"152",
    "addr:postcode":"6056",
    "addr:street":"Morrison Rd",
    "iso:country":"AU",
    "sg:address":"Maia House, 152 Morrison Rd",
    "sg:city":"Midland",
    "sg:classifiers":[
        {
            "category":"Health Services",
            "subcategory":"Health Practitioner",
            "type":"Services"
        }
    ],
    "sg:phone":"+61 8 9274 7129",
    "sg:postcode":"6056",
    "sg:province":"WA",
    "sg:tags":[
        "psychologist"
    ],
    "wof:name":"Tsouvallas Moyra Dr",
    "wof:placetype":"venue"
},
  "geometry": {"coordinates":[116.01699829099999,-31.8863563538],"type":"Point"}
}