{
  "type": "Feature",
  "properties": {
    "iso:country":"AU",
    "sg:address":"Shop 5/ King St",
    "sg:city":"Warrawong",
    "sg:classifiers":[
        {
            "category":"Personal",
            "subcategory":"Beauty Salon",
            "type":"Services"
        }
    ],
    "sg:phone":"+61 405 904 421",
    "sg:postcode":"2502",
    "sg:province":"NSW",
    "wof:name":"Nails by Nicole",
    "wof:placetype":"venue"
},
  "geometry": {"coordinates":[150.88711499999999,-34.479916],"type":"Point"}
}