{
  "type": "Feature",
  "properties": {
    "addr:full":"12 Williamson Rd Ingleburn NSW 2565",
    "addr:housenumber":"12",
    "addr:postcode":"2565",
    "addr:street":"Williamson Rd",
    "iso:country":"AU",
    "sg:address":"12 Williamson Rd",
    "sg:city":"Ingleburn",
    "sg:classifiers":[
        {
            "category":"Shopping",
            "subcategory":"Pets & Pet Supplies",
            "type":"Retail Goods"
        }
    ],
    "sg:phone":"+61 2 9605 7377",
    "sg:postcode":"2565",
    "sg:province":"NSW",
    "sg:tags":[
        "food"
    ],
    "wof:name":"Bush's Pet Foods Pty Ltd Manufacturer",
    "wof:placetype":"venue"
},
  "geometry": {"coordinates":[150.848266602,-33.9991111755],"type":"Point"}
}