{
  "type": "Feature",
  "properties": {
    "addr:full":"135 Harbour Drv Coffs Harbour NSW 2450",
    "addr:housenumber":"135",
    "addr:postcode":"2450",
    "addr:street":"Harbour Drv",
    "iso:country":"AU",
    "sg:address":"135 Harbour Drv",
    "sg:city":"Coffs Harbour",
    "sg:classifiers":[
        {
            "category":"Food & Beverages",
            "subcategory":"Liquor & Beverages",
            "type":"Retail Goods"
        }
    ],
    "sg:phone":"+61 2 6652 3812",
    "sg:postcode":"2450",
    "sg:province":"NSW",
    "sg:tags":[
        "store"
    ],
    "wof:name":"Cellarbrations",
    "wof:placetype":"venue"
},
  "geometry": {"coordinates":[153.13369800000001,-30.305086],"type":"Point"}
}