{
  "type": "Feature",
  "properties": {
    "iso:country":"AU",
    "sg:address":"26 Carew St",
    "sg:city":"Dee Why",
    "sg:classifiers":[
        {
            "category":"Utilities",
            "subcategory":"Electric",
            "type":"Services"
        }
    ],
    "sg:phone":"+61 2 9982 9988",
    "sg:postcode":"2099",
    "sg:province":"NSW",
    "sg:tags":[
        "electrical",
        "contractor"
    ],
    "wof:name":"Newton Installation Services",
    "wof:placetype":"venue"
},
  "geometry": {"coordinates":[151.289596558,-33.7583770752],"type":"Point"}
}