{
  "type": "Feature",
  "properties": {
    "addr:full":"Farrington Rd Murdoch WA 6150",
    "addr:postcode":"6150",
    "addr:street":"Farrington Rd",
    "iso:country":"AU",
    "sg:address":"Farrington Rd",
    "sg:city":"Murdoch",
    "sg:classifiers":[
        {
            "category":"Education",
            "subcategory":"School",
            "type":"Public Place"
        }
    ],
    "sg:phone":"+61 8 9314 7722",
    "sg:postcode":"6150",
    "sg:province":"WA",
    "sg:tags":[
        "co-educational"
    ],
    "wof:name":"Winthrop Baptist College Inc",
    "wof:placetype":"venue"
},
  "geometry": {"coordinates":[115.831551,-32.073845],"type":"Point"}
}