{
  "type": "Feature",
  "properties": {
    "addr:full":"23 Weller Rd Tarragindi QLD 4121",
    "addr:housenumber":"23",
    "addr:postcode":"4121",
    "addr:street":"Weller Rd",
    "iso:country":"AU",
    "sg:address":"23 Weller Rd",
    "sg:city":"Tarragindi",
    "sg:classifiers":[
        {
            "category":"Health Services",
            "subcategory":"Health Practitioner",
            "type":"Services"
        }
    ],
    "sg:phone":"+61 7 3342 4284",
    "sg:postcode":"4121",
    "sg:province":"QLD",
    "sg:tags":[
        "physiotherapist"
    ],
    "wof:name":"Grimaldi Alison",
    "wof:placetype":"venue"
},
  "geometry": {"coordinates":[153.05325317399999,-27.5245609283],"type":"Point"}
}