{
  "type": "Feature",
  "properties": {
    "addr:full":"PO Box 337 Pambula NSW 2549",
    "addr:postcode":"2549",
    "iso:country":"AU",
    "sg:address":"PO Box 337",
    "sg:city":"Pambula",
    "sg:classifiers":[
        {
            "category":"Building & Trades",
            "subcategory":"Construction",
            "type":"Services"
        }
    ],
    "sg:phone":"+61 2 6495 7834",
    "sg:postcode":"2549",
    "sg:province":"NSW",
    "sg:tags":[
        "earth",
        "excavating",
        "moving",
        "contractor"
    ],
    "wof:name":"Parksies Bobcat and Tipper Hire",
    "wof:placetype":"venue"
},
  "geometry": {"coordinates":[149.87597656200001,-36.9282646179],"type":"Point"}
}