{
  "type": "Feature",
  "properties": {
    "iso:country":"AU",
    "sg:address":"21 Power Rd",
    "sg:city":"Bayswater",
    "sg:classifiers":[
        {
            "category":"Wholesale",
            "subcategory":"Machinery & Supplies",
            "type":"Manufacturing & Wholesale Goods"
        }
    ],
    "sg:phone":"+61 3 9729 8533",
    "sg:postcode":"3153",
    "sg:province":"VIC",
    "sg:tags":[
        "equipment",
        "hydraulic"
    ],
    "wof:name":"Enzed",
    "wof:placetype":"venue"
},
  "geometry": {"coordinates":[145.27215576200001,-37.8447113037],"type":"Point"}
}