{
  "type": "Feature",
  "properties": {
    "addr:full":"1 River Rd Woodford VIC 3281",
    "addr:housenumber":"1",
    "addr:postcode":"3281",
    "addr:street":"River Rd",
    "iso:country":"AU",
    "sg:address":"1 River Rd",
    "sg:city":"Woodford",
    "sg:classifiers":[
        {
            "category":"Building & Trades",
            "subcategory":"Construction",
            "type":"Services"
        }
    ],
    "sg:phone":"+61 3 5561 1970",
    "sg:postcode":"3281",
    "sg:province":"VIC",
    "sg:tags":[
        "stonework",
        "stone",
        "mason"
    ],
    "wof:name":"Dwyer Building Services",
    "wof:placetype":"venue"
},
  "geometry": {"coordinates":[142.48683166500001,-38.319606781],"type":"Point"}
}