{
  "type": "Feature",
  "properties": {
    "addr:full":"184 Quay St Rockhampton QLD 4700",
    "addr:housenumber":"184",
    "addr:postcode":"4700",
    "addr:street":"Quay St",
    "iso:country":"AU",
    "sg:address":"184 Quay St",
    "sg:city":"Rockhampton",
    "sg:classifiers":[
        {
            "category":"Professional",
            "subcategory":"Accounting & Tax Preparation",
            "type":"Services"
        }
    ],
    "sg:phone":"+61 7 4922 4244",
    "sg:postcode":"4700",
    "sg:province":"QLD",
    "sg:tags":[
        "accountant",
        "auditor"
    ],
    "wof:name":"Becker James & Co",
    "wof:placetype":"venue"
},
  "geometry": {"coordinates":[150.525146484,-23.3920402527],"type":"Point"}
}