{
  "type": "Feature",
  "properties": {
    "addr:full":"20 Mate St Humula NSW 2652",
    "addr:housenumber":"20",
    "addr:postcode":"2652",
    "addr:street":"Mate St",
    "iso:country":"AU",
    "sg:address":"20 Mate St",
    "sg:city":"Humula",
    "sg:classifiers":[
        {
            "category":"Food & Beverages",
            "subcategory":"Groceries & Convenience Stores",
            "type":"Retail Goods"
        }
    ],
    "sg:phone":"+61 2 6928 9258",
    "sg:postcode":"2652",
    "sg:province":"NSW",
    "wof:name":"Simpsons General Store",
    "wof:placetype":"venue"
},
  "geometry": {"coordinates":[147.764282227,-35.4833946228],"type":"Point"}
}