{
  "type": "Feature",
  "properties": {
    "addr:full":"30 Carstens Crs Wagaman NT 0810",
    "addr:housenumber":"30",
    "addr:postcode":"nt 0810",
    "addr:street":"Carstens Crs",
    "iso:country":"AU",
    "sg:address":"30 Carstens Crs",
    "sg:city":"Wagaman",
    "sg:classifiers":[
        {
            "category":"Professional",
            "subcategory":"Art Services",
            "type":"Services"
        }
    ],
    "sg:phone":"+61 418 892 563",
    "sg:postcode":"0810",
    "sg:province":"NT",
    "sg:tags":[
        "decorator",
        "painter"
    ],
    "wof:name":"Territory Painting Service",
    "wof:placetype":"venue"
},
  "geometry": {"coordinates":[130.88905334500001,-12.3814897537],"type":"Point"}
}