{
  "type": "Feature",
  "properties": {
    "addr:full":"1 Balaclava Rd St Kilda East VIC 3183",
    "addr:housenumber":"1",
    "addr:postcode":"3183",
    "addr:street":"Balaclava Rd",
    "iso:country":"AU",
    "sg:address":"1 Balaclava Rd",
    "sg:city":"St Kilda East",
    "sg:classifiers":[
        {
            "category":"Health Services",
            "subcategory":"Doctor",
            "type":"Services"
        }
    ],
    "sg:phone":"+61 3 9527 4209",
    "sg:postcode":"3183",
    "sg:province":"VIC",
    "sg:tags":[
        "medical",
        "practitioner"
    ],
    "wof:name":"Balaclava Road Medical Clinic",
    "wof:placetype":"venue"
},
  "geometry": {"coordinates":[144.99984741200001,-37.869682312],"type":"Point"}
}