{
  "type": "Feature",
  "properties": {
    "addr:full":"PO Box 506 Unanderra NSW 2526",
    "addr:postcode":"2526",
    "iso:country":"AU",
    "sg:address":"PO Box 506",
    "sg:city":"Unanderra",
    "sg:classifiers":[
        {
            "category":"Utilities",
            "subcategory":"Electric",
            "type":"Services"
        }
    ],
    "sg:phone":"+61 2 4271 6948",
    "sg:postcode":"2526",
    "sg:province":"NSW",
    "sg:tags":[
        "electrical",
        "contractor"
    ],
    "wof:name":"D.J. McCartney Electrical Contractors Pty. Ltd.",
    "wof:placetype":"venue"
},
  "geometry": {"coordinates":[150.82733154300001,-34.4404182434],"type":"Point"}
}