{
  "type": "Feature",
  "properties": {
    "addr:full":"22 Myrtle Drv Armidale NSW 2350",
    "addr:housenumber":"22",
    "addr:postcode":"2350",
    "addr:street":"Myrtle Drv",
    "iso:country":"AU",
    "sg:address":"22 Myrtle Drv",
    "sg:city":"Armidale",
    "sg:classifiers":[
        {
            "category":"Government",
            "subcategory":"Department Of Motor Vehicles",
            "type":"Public Place"
        }
    ],
    "sg:phone":"+61 2 6773 8500",
    "sg:postcode":"2350",
    "sg:province":"NSW",
    "sg:tags":[
        "wholesaler",
        "mfrs",
        "accessory"
    ],
    "wof:name":"Timberline Cabins",
    "wof:placetype":"venue"
},
  "geometry": {"coordinates":[151.677932739,-30.5387554169],"type":"Point"}
}