{
  "type": "Feature",
  "properties": {
    "addr:full":"Shop 9 2-12 Comenarra Pkwy Thornleigh NSW 2120",
    "addr:housenumber":"shop 9",
    "addr:postcode":"2-12;2120",
    "addr:street":"Comenarra Pkwy",
    "iso:country":"AU",
    "sg:address":"Shop 9 2-12 Comenarra Pkwy",
    "sg:city":"Thornleigh",
    "sg:classifiers":[
        {
            "category":"Personal",
            "subcategory":"Beauty Salon",
            "type":"Services"
        }
    ],
    "sg:phone":"+61 2 9875 4464",
    "sg:postcode":"2120",
    "sg:province":"NSW",
    "wof:name":"Beauty Spot",
    "wof:placetype":"venue"
},
  "geometry": {"coordinates":[151.08340454099999,-33.7282104492],"type":"Point"}
}