{
  "type": "Feature",
  "properties": {
    "addr:full":"Unit 2- 1 Balmain St Slacks Creek QLD 4127",
    "addr:housenumber":"1",
    "addr:postcode":"4127",
    "addr:street":"Balmain St",
    "iso:country":"AU",
    "sg:address":"Unit 2- 1 Balmain St",
    "sg:city":"Slacks Creek",
    "sg:classifiers":[
        {
            "category":"Government",
            "subcategory":"Fire Station",
            "type":"Public Place"
        }
    ],
    "sg:phone":"+61 7 3208 1922",
    "sg:postcode":"4127",
    "sg:province":"QLD",
    "sg:tags":[
        "equipment",
        "protection",
        "consultant"
    ],
    "wof:name":"Ziton Qld Pty Ltd",
    "wof:placetype":"venue"
},
  "geometry": {"coordinates":[153.11912536599999,-27.6176395416],"type":"Point"}
}