{
  "type": "Feature",
  "properties": {
    "addr:full":"245 Mt Crosby Rd Tivoli QLD 4305",
    "addr:housenumber":"245",
    "addr:postcode":"4305",
    "addr:street":"Mt Crosby Rd",
    "iso:country":"AU",
    "sg:address":"245 Mt Crosby Rd",
    "sg:city":"Tivoli",
    "sg:classifiers":[
        {
            "category":"Retail",
            "subcategory":"Auto Repair",
            "type":"Services"
        }
    ],
    "sg:phone":"+61 7 3812 1263",
    "sg:postcode":"4305",
    "sg:province":"QLD",
    "sg:tags":[
        "electrical"
    ],
    "wof:name":"Tivoli Auto Electrics",
    "wof:placetype":"venue"
},
  "geometry": {"coordinates":[152.78579711899999,-27.5753173828],"type":"Point"}
}