{
  "type": "Feature",
  "properties": {
    "addr:full":"486 Gympie Rd Strathpine QLD 4500",
    "addr:housenumber":"486",
    "addr:postcode":"4500",
    "addr:street":"Gympie Rd",
    "iso:country":"AU",
    "sg:address":"486 Gympie Rd",
    "sg:city":"Strathpine",
    "sg:classifiers":[
        {
            "category":"Food & Beverages",
            "subcategory":"Bakery",
            "type":"Retail Goods"
        }
    ],
    "sg:phone":"+61 7 3205 9088",
    "sg:postcode":"4500",
    "sg:province":"QLD",
    "sg:tags":[
        "cake",
        "shop",
        "pastry"
    ],
    "wof:name":"Cheesecake Shop The",
    "wof:placetype":"venue"
},
  "geometry": {"coordinates":[152.988845825,-27.3023986816],"type":"Point"}
}