{
  "type": "Feature",
  "properties": {
    "addr:full":"72b Irvine Drv Malaga WA 6090",
    "addr:housenumber":"72b",
    "addr:postcode":"6090",
    "addr:street":"Irvine Drv",
    "iso:country":"AU",
    "sg:address":"72b Irvine Drv",
    "sg:city":"Malaga",
    "sg:classifiers":[
        {
            "category":"Building & Trades",
            "subcategory":"Construction",
            "type":"Services"
        }
    ],
    "sg:phone":"+61 8 9248 5099",
    "sg:postcode":"6090",
    "sg:province":"WA",
    "sg:tags":[
        "contractor"
    ],
    "wof:name":"Lakis Constructions Pty Ltd",
    "wof:placetype":"venue"
},
  "geometry": {"coordinates":[115.884620666,-31.8547077179],"type":"Point"}
}