{
  "type": "Feature",
  "properties": {
    "iso:country":"AU",
    "sg:address":"11 Craigie Rd",
    "sg:city":"Newtown",
    "sg:classifiers":[
        {
            "category":"Utilities",
            "subcategory":"Electric",
            "type":"Services"
        }
    ],
    "sg:phone":"+61 3 5229 1410",
    "sg:postcode":"3220",
    "sg:province":"VIC",
    "sg:tags":[
        "electrical",
        "contractor"
    ],
    "wof:name":"Fantini E J & R A",
    "wof:placetype":"venue"
},
  "geometry": {"coordinates":[144.325638,-38.156441],"type":"Point"}
}