{
  "type": "Feature",
  "properties": {
    "iso:country":"AU",
    "sg:address":"5 Investigator St",
    "sg:city":"Nowra South",
    "sg:classifiers":[
        {
            "category":"Manufacturing",
            "subcategory":"Motor Vehicles & Parts",
            "type":"Manufacturing & Wholesale Goods"
        }
    ],
    "sg:phone":"+61 2 4421 8111",
    "sg:postcode":"2541",
    "sg:province":"NSW",
    "sg:tags":[
        "replacement"
    ],
    "wof:name":"Mascot Motors Pty Ltd",
    "wof:placetype":"venue"
},
  "geometry": {"coordinates":[150.58485412600001,-34.9094085693],"type":"Point"}
}