{
  "type": "Feature",
  "properties": {
    "iso:country":"AU",
    "sg:address":"19 Ashwood Ave",
    "sg:city":"Bright",
    "sg:classifiers":[
        {
            "category":"Retail",
            "subcategory":"Repair Shop",
            "type":"Services"
        }
    ],
    "sg:phone":"+61 3 5750 1800",
    "sg:postcode":"3741",
    "sg:province":"VIC",
    "sg:tags":[
        "machine",
        "repairs",
        "part",
        "dryer",
        "washing"
    ],
    "wof:name":"High Country Appliance Service",
    "wof:placetype":"venue"
},
  "geometry": {"coordinates":[146.946167,-36.72015],"type":"Point"}
}