{
  "type": "Feature",
  "properties": {
    "addr:full":"Shop 5/ 358 Galston Rd Galston NSW 2159",
    "addr:housenumber":"shop 5 / 358",
    "addr:postcode":"2159",
    "addr:street":"Galston Rd",
    "iso:country":"AU",
    "sg:address":"Shop 5/ 358 Galston Rd",
    "sg:city":"Galston",
    "sg:classifiers":[
        {
            "category":"Personal",
            "subcategory":"Beauty Salon",
            "type":"Services"
        }
    ],
    "sg:phone":"+61 2 9653 2659",
    "sg:postcode":"2159",
    "sg:province":"NSW",
    "wof:name":"Essentially Beautiful",
    "wof:placetype":"venue"
},
  "geometry": {"coordinates":[151.04547119099999,-33.6527938843],"type":"Point"}
}