{
  "type": "Feature",
  "properties": {
    "addr:full":"108 Clarendon St Maryborough VIC 3465",
    "addr:housenumber":"108",
    "addr:postcode":"3465",
    "addr:street":"Clarendon St",
    "iso:country":"AU",
    "sg:address":"108 Clarendon St",
    "sg:city":"Maryborough",
    "sg:classifiers":[
        {
            "category":"Retail",
            "subcategory":"Funeral Services",
            "type":"Services"
        }
    ],
    "sg:phone":"+61 3 5461 1979",
    "sg:postcode":"3465",
    "sg:province":"VIC",
    "sg:tags":[
        "director"
    ],
    "wof:name":"Maryborough & District Funeral Service",
    "wof:placetype":"venue"
},
  "geometry": {"coordinates":[143.739471436,-37.0419044495],"type":"Point"}
}