{
  "type": "Feature",
  "properties": {
    "addr:full":"147 Castlereagh St Sydney NSW 2000",
    "addr:housenumber":"147",
    "addr:postcode":"2000",
    "addr:street":"Castlereagh St",
    "iso:country":"AU",
    "sg:address":"147 Castlereagh St",
    "sg:city":"Sydney",
    "sg:classifiers":[
        {
            "category":"Personal",
            "subcategory":"Beauty Salon",
            "type":"Services"
        }
    ],
    "sg:phone":"+61 2 9264 5186",
    "sg:postcode":"2000",
    "sg:province":"NSW",
    "sg:tags":[
        "hair",
        "treatment",
        "replacement"
    ],
    "wof:name":"Djemil Coiffure - Hairdressing City",
    "wof:placetype":"venue"
},
  "geometry": {"coordinates":[151.209182739,-33.8718338013],"type":"Point"}
}