{
  "type": "Feature",
  "properties": {
    "iso:country":"AU",
    "sg:address":"PO Box 475",
    "sg:city":"Kings Langley",
    "sg:classifiers":[
        {
            "category":"Home & Garden",
            "subcategory":"Furniture",
            "type":"Retail Goods"
        }
    ],
    "sg:phone":"+61 409 157 711",
    "sg:postcode":"2147",
    "sg:province":"NSW",
    "sg:tags":[
        "business"
    ],
    "wof:name":"Internal Affairs",
    "wof:placetype":"venue"
},
  "geometry": {"coordinates":[150.92451477,-33.7456703186],"type":"Point"}
}