{
  "type": "Feature",
  "properties": {
    "addr:full":"44 Eyre Hwy Wudinna SA 5652",
    "addr:housenumber":"44",
    "addr:postcode":"5652",
    "addr:street":"Eyre Hwy",
    "iso:country":"AU",
    "sg:address":"44 Eyre Hwy",
    "sg:city":"Wudinna",
    "sg:classifiers":[
        {
            "category":"Professional",
            "subcategory":"Computer Services",
            "type":"Services"
        }
    ],
    "sg:phone":"+61 8 8680 2969",
    "sg:postcode":"5652",
    "sg:province":"SA",
    "sg:tags":[
        "training"
    ],
    "wof:name":"Wudinna & Districts Tele-Centre Incorporated",
    "wof:placetype":"venue"
},
  "geometry": {"coordinates":[135.45744323700001,-33.046333313],"type":"Point"}
}