{
  "type": "Feature",
  "properties": {
    "iso:country":"AU",
    "sg:address":"Hamilton Rd",
    "sg:city":"Fairfield West",
    "sg:classifiers":[
        {
            "category":"Education",
            "subcategory":"School",
            "type":"Public Place"
        }
    ],
    "sg:phone":"+61 2 9604 3333",
    "sg:postcode":"2165",
    "sg:province":"NSW",
    "sg:tags":[
        "state",
        "-",
        "nsw"
    ],
    "wof:name":"Westfields Sports High School",
    "wof:placetype":"venue"
},
  "geometry": {"coordinates":[150.92301940900001,-33.8691101074],"type":"Point"}
}