{
  "type": "Feature",
  "properties": {
    "addr:full":"Bannister Drv Erina NSW 2250",
    "addr:postcode":"2250",
    "addr:street":"Bannister Drv",
    "iso:country":"AU",
    "sg:address":"Bannister Drv",
    "sg:city":"Erina",
    "sg:classifiers":[
        {
            "category":"Building & Trades",
            "subcategory":"Construction",
            "type":"Services"
        }
    ],
    "sg:phone":"+61 2 4367 8111",
    "sg:postcode":"2250",
    "sg:province":"NSW",
    "sg:tags":[
        "contractor"
    ],
    "wof:name":"Clarendon Homes (NSW) Pty Ltd",
    "wof:placetype":"venue"
},
  "geometry": {"coordinates":[151.401153564,-33.437171936],"type":"Point"}
}