{
  "type": "Feature",
  "properties": {
    "addr:full":"181 Chapel St Prahran VIC 3181",
    "addr:housenumber":"181",
    "addr:postcode":"3181",
    "addr:street":"Chapel St",
    "iso:country":"AU",
    "sg:address":"181 Chapel St",
    "sg:city":"Prahran",
    "sg:classifiers":[
        {
            "category":"Casinos & Gambling",
            "type":"Entertainment"
        }
    ],
    "sg:phone":"+61 3 9510 2349",
    "sg:postcode":"3181",
    "sg:province":"VIC",
    "sg:tags":[
        "lottery",
        "agent"
    ],
    "wof:name":"Chapel Lotteries",
    "wof:placetype":"venue"
},
  "geometry": {"coordinates":[144.993209839,-37.8516807556],"type":"Point"}
}