{
  "type": "Feature",
  "properties": {
    "addr:full":"35 Lyons Ave Devonport TAS 7310",
    "addr:housenumber":"35",
    "addr:postcode":"7310",
    "addr:street":"Lyons Ave",
    "iso:country":"AU",
    "sg:address":"35 Lyons Ave",
    "sg:city":"Devonport",
    "sg:classifiers":[
        {
            "category":"Professional",
            "subcategory":"Art Services",
            "type":"Services"
        }
    ],
    "sg:phone":"+61 407 241 821",
    "sg:postcode":"7310",
    "sg:province":"TAS",
    "sg:tags":[
        "decorator",
        "painter"
    ],
    "wof:name":"Plapp James",
    "wof:placetype":"venue"
},
  "geometry": {"coordinates":[146.35699462900001,-41.1922912598],"type":"Point"}
}