{
  "type": "Feature",
  "properties": {
    "addr:full":"Shop 11 Glenrose Shpg Cntr, Glen St Belrose NSW 2085",
    "addr:housenumber":"shop 11",
    "addr:postcode":"2085",
    "addr:street":"Glen St",
    "iso:country":"AU",
    "sg:address":"Shop 11 Glenrose Shpg Cntr, Glen St",
    "sg:city":"Belrose",
    "sg:classifiers":[
        {
            "category":"Banks & Credit Unions",
            "subcategory":"Bank",
            "type":"Services"
        }
    ],
    "sg:phone":"+61 13 13 14",
    "sg:postcode":"2085",
    "sg:province":"NSW",
    "wof:name":"ANZ",
    "wof:placetype":"venue"
},
  "geometry": {"coordinates":[151.21975707999999,-33.7388648987],"type":"Point"}
}