{
  "type": "Feature",
  "properties": {
    "addr:full":"63 Bald Hill Rd Pakenham VIC 3810",
    "addr:housenumber":"63",
    "addr:postcode":"3810",
    "addr:street":"Bald Hill Rd",
    "iso:country":"AU",
    "sg:address":"63 Bald Hill Rd",
    "sg:city":"Pakenham",
    "sg:classifiers":[
        {
            "category":"Retail",
            "subcategory":"Car Wash",
            "type":"Services"
        }
    ],
    "sg:phone":"+61 3 5940 2233",
    "sg:postcode":"3810",
    "sg:province":"VIC",
    "sg:tags":[
        "truck",
        "cleaning"
    ],
    "wof:name":"S V Car Detailers",
    "wof:placetype":"venue"
},
  "geometry": {"coordinates":[145.48637400000001,-38.081345],"type":"Point"}
}