{
  "type": "Feature",
  "properties": {
    "iso:country":"AU",
    "sg:address":"36 Brentwood Ave",
    "sg:city":"Pascoe Vale South",
    "sg:classifiers":[
        {
            "category":"Education",
            "subcategory":"Kindergarten",
            "type":"Public Place"
        }
    ],
    "sg:phone":"+61 3 9386 3547",
    "sg:postcode":"3044",
    "sg:province":"VIC",
    "sg:tags":[
        "pre-schools"
    ],
    "wof:name":"Brentwood Kindergarten",
    "wof:placetype":"venue"
},
  "geometry": {"coordinates":[144.93162536599999,-37.7473716736],"type":"Point"}
}