{
  "type": "Feature",
  "properties": {
    "iso:country":"AU",
    "sg:address":"1/ 646 Grange Rd",
    "sg:city":"Henley Beach",
    "sg:classifiers":[
        {
            "category":"Personal",
            "subcategory":"Beauty Salon",
            "type":"Services"
        }
    ],
    "sg:phone":"+61 8 8235 0900",
    "sg:postcode":"5022",
    "sg:province":"SA",
    "wof:name":"Entirely Beautiful",
    "wof:placetype":"venue"
},
  "geometry": {"coordinates":[138.49249267600001,-34.9075546265],"type":"Point"}
}