{
  "type": "Feature",
  "properties": {
    "addr:full":"270 Bay St Port Melbourne VIC 3207",
    "addr:housenumber":"270",
    "addr:postcode":"3207",
    "addr:street":"Bay St",
    "iso:country":"AU",
    "sg:address":"270 Bay St",
    "sg:city":"Port Melbourne",
    "sg:classifiers":[
        {
            "category":"Professional",
            "subcategory":"Employment Agencies",
            "type":"Services"
        }
    ],
    "sg:phone":"+61 3 9646 0344",
    "sg:postcode":"3207",
    "sg:province":"VIC",
    "wof:name":"Legalink International",
    "wof:placetype":"venue"
},
  "geometry": {"coordinates":[144.943253,-37.837811],"type":"Point"}
}