{
  "type": "Feature",
  "properties": {
    "addr:full":"30 Ryley St Wangaratta VIC 3677",
    "addr:housenumber":"30",
    "addr:postcode":"3677",
    "addr:street":"Ryley St",
    "iso:country":"AU",
    "sg:address":"30 Ryley St",
    "sg:city":"Wangaratta",
    "sg:classifiers":[
        {
            "category":"Manufacturing",
            "subcategory":"Food",
            "type":"Manufacturing & Wholesale Goods"
        }
    ],
    "sg:phone":"+61 3 5721 3979",
    "sg:postcode":"3677",
    "sg:province":"VIC",
    "sg:tags":[
        "function",
        "catering"
    ],
    "wof:name":"Great Gourmet's Inn",
    "wof:placetype":"venue"
},
  "geometry": {"coordinates":[146.31916809099999,-36.3588104248],"type":"Point"}
}