{
  "type": "Feature",
  "properties": {
    "addr:full":"3 Rodwell Pl Kellyville NSW 2153",
    "addr:housenumber":"3",
    "addr:postcode":"2153",
    "addr:street":"Rodwell Pl",
    "iso:country":"AU",
    "sg:address":"3 Rodwell Pl",
    "sg:city":"Kellyville",
    "sg:classifiers":[
        {
            "category":"Building & Trades",
            "subcategory":"Construction",
            "type":"Services"
        }
    ],
    "sg:phone":"+61 2 9629 1931",
    "sg:postcode":"2153",
    "sg:province":"NSW",
    "sg:tags":[
        "contractor"
    ],
    "wof:name":"Stocker Building Services",
    "wof:placetype":"venue"
},
  "geometry": {"coordinates":[150.95750427199999,-33.7077102661],"type":"Point"}
}