{
  "type": "Feature",
  "properties": {
    "addr:full":"PO Box 5404 Canning Vale South WA 6155",
    "addr:postcode":"6155",
    "iso:country":"AU",
    "sg:address":"PO Box 5404",
    "sg:city":"Canning Vale South",
    "sg:classifiers":[
        {
            "category":"Shopping",
            "subcategory":"Music",
            "type":"Retail Goods"
        }
    ],
    "sg:phone":"+61 1300 663 279",
    "sg:postcode":"6155",
    "sg:province":"WA",
    "sg:tags":[
        "instrument",
        "musical"
    ],
    "wof:name":"IJAM Music Pty Ltd",
    "wof:placetype":"venue"
},
  "geometry": {"coordinates":[115.91773999999999,-32.098091],"type":"Point"}
}