{
  "type": "Feature",
  "properties": {
    "iso:country":"AU",
    "sg:address":"5a Clifton St",
    "sg:city":"Camden Park",
    "sg:classifiers":[
        {
            "category":"Arts & Performance",
            "subcategory":"Music",
            "type":"Entertainment"
        }
    ],
    "sg:phone":"+61 8 8376 1707",
    "sg:postcode":"5038",
    "sg:province":"SA",
    "sg:tags":[
        "mobile",
        "jockey",
        "disc"
    ],
    "wof:name":"Thoroly Good Mobile Disco & Karaoke",
    "wof:placetype":"venue"
},
  "geometry": {"coordinates":[138.541305542,-34.9706230164],"type":"Point"}
}