{
  "type": "Feature",
  "properties": {
    "addr:full":"32 Inthanoona Rd Gidgegannup WA 6083",
    "addr:housenumber":"32",
    "addr:postcode":"6083",
    "addr:street":"Inthanoona Rd",
    "iso:country":"AU",
    "sg:address":"32 Inthanoona Rd",
    "sg:city":"Gidgegannup",
    "sg:classifiers":[
        {
            "category":"Building & Trades",
            "subcategory":"Plumbing",
            "type":"Services"
        }
    ],
    "sg:phone":"+61 419 941 481",
    "sg:postcode":"6083",
    "sg:province":"WA",
    "sg:tags":[
        "plumber",
        "gasfitters"
    ],
    "wof:name":"Vottos Plumbing Contractors",
    "wof:placetype":"venue"
},
  "geometry": {"coordinates":[116.179138184,-31.8058280945],"type":"Point"}
}