{
  "type": "Feature",
  "properties": {
    "iso:country":"AU",
    "sg:address":"9 Bristol St",
    "sg:city":"Rosanna",
    "sg:classifiers":[
        {
            "category":"Building & Trades",
            "subcategory":"Plumbing",
            "type":"Services"
        }
    ],
    "sg:phone":"+61 3 9459 2252",
    "sg:postcode":"3084",
    "sg:province":"VIC",
    "sg:tags":[
        "plumber",
        "gasfitters"
    ],
    "wof:name":"Heneberry Plumbing",
    "wof:placetype":"venue"
},
  "geometry": {"coordinates":[145.08122253400001,-37.7456550598],"type":"Point"}
}