{
  "type": "Feature",
  "properties": {
    "iso:country":"AU",
    "sg:address":"52 Barnes St",
    "sg:city":"Taminda",
    "sg:classifiers":[
        {
            "category":"Food & Beverages",
            "subcategory":"Meat & Fish",
            "type":"Retail Goods"
        }
    ],
    "sg:phone":"+61 2 6762 5544",
    "sg:postcode":"2340",
    "sg:province":"NSW",
    "sg:tags":[
        "aquaculture"
    ],
    "wof:name":"Tamworth Finfarm",
    "wof:placetype":"venue"
},
  "geometry": {"coordinates":[150.91224670400001,-31.0915298462],"type":"Point"}
}