{
  "type": "Feature",
  "properties": {
    "addr:full":"Shop 10, 55 Mt Barker Rd Stirling SA 5152",
    "addr:housenumber":"shop 10 55",
    "addr:postcode":"5152",
    "addr:street":"Mt Barker Rd",
    "iso:country":"AU",
    "sg:address":"Shop 10, 55 Mt Barker Rd",
    "sg:city":"Stirling",
    "sg:classifiers":[
        {
            "category":"Health Services",
            "subcategory":"Doctor",
            "type":"Services"
        }
    ],
    "sg:phone":"+61 8 8339 7551",
    "sg:postcode":"5152",
    "sg:province":"SA",
    "sg:tags":[
        "podiatrist"
    ],
    "wof:name":"Adelaide Hills Family & Sports Podiatry Centre",
    "wof:placetype":"venue"
},
  "geometry": {"coordinates":[138.72195434599999,-35.0079421997],"type":"Point"}
}