{
  "type": "Feature",
  "properties": {
    "iso:country":"AU",
    "sg:address":"23 Gawler St",
    "sg:city":"Port Noarlunga",
    "sg:classifiers":[
        {
            "category":"Government",
            "subcategory":"Post Office",
            "type":"Public Place"
        }
    ],
    "sg:phone":"+61 8 8382 1230",
    "sg:postcode":"5167",
    "sg:province":"SA",
    "sg:tags":[
        "postal"
    ],
    "wof:name":"Australia Post",
    "wof:placetype":"venue"
},
  "geometry": {"coordinates":[138.47547912600001,-35.1479759216],"type":"Point"}
}