{
  "type": "Feature",
  "properties": {
    "addr:full":"110 Sydney Rd Coburg VIC 3058",
    "addr:housenumber":"110",
    "addr:postcode":"3058",
    "addr:street":"Sydney Rd",
    "iso:country":"AU",
    "sg:address":"110 Sydney Rd",
    "sg:city":"Coburg",
    "sg:classifiers":[
        {
            "category":"Retail",
            "subcategory":"Auto Repair",
            "type":"Services"
        }
    ],
    "sg:phone":"+61 3 9386 4220",
    "sg:postcode":"3058",
    "sg:province":"VIC",
    "sg:tags":[
        "body",
        "motor",
        "trimmer"
    ],
    "wof:name":"AAAA Cedar Motor Trimming",
    "wof:placetype":"venue"
},
  "geometry": {"coordinates":[144.96481323200001,-37.7524223328],"type":"Point"}
}