{
  "type": "Feature",
  "properties": {
    "iso:country":"AU",
    "sg:address":"7 Albion Rd",
    "sg:city":"Eatons Hill",
    "sg:classifiers":[
        {
            "category":"Retail",
            "subcategory":"Driving School",
            "type":"Services"
        }
    ],
    "sg:phone":"+61 7 3264 1777",
    "sg:postcode":"4037",
    "sg:province":"QLD",
    "sg:website":"http://www.morganandsons.com.au",
    "wof:name":"Morgan & Sons",
    "wof:placetype":"venue"
},
  "geometry": {"coordinates":[152.930466,-27.332359],"type":"Point"}
}