{
  "type": "Feature",
  "properties": {
    "iso:country":"AU",
    "sg:address":"Shp 256 Westlakes Mall",
    "sg:city":"West Lakes",
    "sg:classifiers":[
        {
            "category":"Shopping",
            "subcategory":"Mobile Phones",
            "type":"Retail Goods"
        }
    ],
    "sg:phone":"+61 8 8418 0303",
    "sg:postcode":"5021",
    "sg:province":"SA",
    "sg:tags":[
        "telephone",
        "accessory"
    ],
    "wof:name":"Vodafone",
    "wof:placetype":"venue"
},
  "geometry": {"coordinates":[138.501708984,-34.8476600647],"type":"Point"}
}