{
  "type": "Feature",
  "properties": {
    "addr:full":"23 Hope St Blaxland NSW 2774",
    "addr:housenumber":"23",
    "addr:postcode":"2774",
    "addr:street":"Hope St",
    "iso:country":"AU",
    "sg:address":"23 Hope St",
    "sg:city":"Blaxland",
    "sg:classifiers":[
        {
            "category":"Health Services",
            "subcategory":"Doctor",
            "type":"Services"
        }
    ],
    "sg:phone":"+61 2 4739 1096",
    "sg:postcode":"2774",
    "sg:province":"NSW",
    "sg:tags":[
        "medical",
        "practitioner"
    ],
    "wof:name":"Adusu-Milli H",
    "wof:placetype":"venue"
},
  "geometry": {"coordinates":[150.61073303200001,-33.74559021],"type":"Point"}
}