{
  "type": "Feature",
  "properties": {
    "addr:full":"400 Burwood Hwy crn Middleborough Rd Burwood VIC 3125",
    "addr:housenumber":"400",
    "addr:postcode":"3125",
    "addr:street":"Burwood Hwy Crn Middleborough Rd",
    "iso:country":"AU",
    "sg:address":"400 Burwood Hwy crn Middleborough Rd",
    "sg:city":"Burwood",
    "sg:classifiers":[
        {
            "category":"Health Services",
            "subcategory":"Health Practitioner",
            "type":"Services"
        }
    ],
    "sg:phone":"+61 3 9888 8177",
    "sg:postcode":"3125",
    "sg:province":"VIC",
    "sg:tags":[
        "physiotherapist"
    ],
    "wof:name":"Burwood East Physiotherapy",
    "wof:placetype":"venue"
},
  "geometry": {"coordinates":[145.13258361800001,-37.8506584167],"type":"Point"}
}