{
  "type": "Feature",
  "properties": {
    "iso:country":"AU",
    "sg:address":"63 Butterworth Rd",
    "sg:city":"Aldinga",
    "sg:classifiers":[
        {
            "category":"Education",
            "subcategory":"Kindergarten",
            "type":"Public Place"
        }
    ],
    "sg:phone":"+61 8 8556 5483",
    "sg:postcode":"5173",
    "sg:province":"SA",
    "sg:tags":[
        "pre-schools"
    ],
    "wof:name":"Aldinga Community Kindergarten",
    "wof:placetype":"venue"
},
  "geometry": {"coordinates":[138.45095825199999,-35.2744598389],"type":"Point"}
}