{
  "type": "Feature",
  "properties": {
    "addr:full":"Mona, Little River Rd Braidwood NSW 2622",
    "addr:postcode":"2622",
    "addr:street":"Little River Rd",
    "iso:country":"AU",
    "sg:address":"Mona, Little River Rd",
    "sg:city":"Braidwood",
    "sg:classifiers":[
        {
            "category":"Health Services",
            "subcategory":"Health Practitioner",
            "type":"Services"
        }
    ],
    "sg:phone":"+61 2 4842 2972",
    "sg:postcode":"2622",
    "sg:province":"NSW",
    "sg:tags":[
        "physiotherapist"
    ],
    "wof:name":"Schneider Greg",
    "wof:placetype":"venue"
},
  "geometry": {"coordinates":[149.80648803700001,-35.4426765442],"type":"Point"}
}