{
  "type": "Feature",
  "properties": {
    "addr:full":"38- 40 Denison St Gloucester NSW 2422",
    "addr:housenumber":"40",
    "addr:postcode":"2422",
    "addr:street":"Denison St",
    "iso:country":"AU",
    "sg:address":"38- 40 Denison St",
    "sg:city":"Gloucester",
    "sg:classifiers":[
        {
            "category":"Manufacturing",
            "subcategory":"Motor Vehicles & Parts",
            "type":"Manufacturing & Wholesale Goods"
        }
    ],
    "sg:phone":"+61 2 6558 1105",
    "sg:postcode":"2422",
    "sg:province":"NSW",
    "sg:tags":[
        "replacement"
    ],
    "wof:name":"Autopro",
    "wof:placetype":"venue"
},
  "geometry": {"coordinates":[151.96031199999999,-32.007393],"type":"Point"}
}