{
  "type": "Feature",
  "properties": {
    "addr:full":"495 Kingston Rd Kingston QLD 4114",
    "addr:housenumber":"495",
    "addr:postcode":"4114",
    "addr:street":"Kingston Rd",
    "iso:country":"AU",
    "sg:address":"495 Kingston Rd",
    "sg:city":"Kingston",
    "sg:classifiers":[
        {
            "category":"Building & Trades",
            "subcategory":"Construction",
            "type":"Services"
        }
    ],
    "sg:phone":"+61 13 88 31",
    "sg:postcode":"4114",
    "sg:province":"QLD",
    "sg:tags":[
        "window",
        "tinting"
    ],
    "wof:name":"SunGard",
    "wof:placetype":"venue"
},
  "geometry": {"coordinates":[153.11807250999999,-27.6617565155],"type":"Point"}
}