{
  "type": "Feature",
  "properties": {
    "addr:full":"5 Maunder St Slacks Creek QLD 4127",
    "addr:housenumber":"5",
    "addr:postcode":"4127",
    "addr:street":"Maunder St",
    "iso:country":"AU",
    "sg:address":"5 Maunder St",
    "sg:city":"Slacks Creek",
    "sg:classifiers":[
        {
            "category":"Home & Garden",
            "subcategory":"Carpets & Floor Coverings",
            "type":"Retail Goods"
        }
    ],
    "sg:phone":"+61 7 3423 1406",
    "sg:postcode":"4127",
    "sg:province":"QLD",
    "sg:tags":[
        "tile",
        "wall"
    ],
    "wof:name":"Slate & Stone Products Pty Ltd",
    "wof:placetype":"venue"
},
  "geometry": {"coordinates":[153.1277771,-27.6287479401],"type":"Point"}
}