{
  "type": "Feature",
  "properties": {
    "addr:full":"47 High St Southport QLD 4215",
    "addr:housenumber":"47",
    "addr:postcode":"4215",
    "addr:street":"High St",
    "iso:country":"AU",
    "sg:address":"47 High St",
    "sg:city":"Southport",
    "sg:classifiers":[
        {
            "category":"Government",
            "subcategory":"Post Office",
            "type":"Public Place"
        }
    ],
    "sg:phone":"+61 7 5531 0511",
    "sg:postcode":"4215",
    "sg:province":"QLD",
    "sg:tags":[
        "yoga"
    ],
    "wof:name":"Shanti Yoga",
    "wof:placetype":"venue"
},
  "geometry": {"coordinates":[153.410079956,-27.9689693451],"type":"Point"}
}