{
  "type": "Feature",
  "properties": {
    "addr:full":"24 Correys Ave Concord NSW 2137",
    "addr:housenumber":"24",
    "addr:postcode":"2137",
    "addr:street":"Correys Ave",
    "iso:country":"AU",
    "sg:address":"24 Correys Ave",
    "sg:city":"Concord",
    "sg:classifiers":[
        {
            "category":"Utilities",
            "subcategory":"Electric",
            "type":"Services"
        }
    ],
    "sg:phone":"+61 2 9743 2755",
    "sg:postcode":"2137",
    "sg:province":"NSW",
    "sg:tags":[
        "electrical",
        "contractor"
    ],
    "wof:name":"Annesley Electric Pty Ltd",
    "wof:placetype":"venue"
},
  "geometry": {"coordinates":[151.100219727,-33.8538513184],"type":"Point"}
}