{
  "type": "Feature",
  "properties": {
    "addr:full":"Shop 3 New World Arcade Biloela QLD 4715",
    "addr:housenumber":"shop 3",
    "addr:postcode":"4715",
    "addr:street":"New",
    "iso:country":"AU",
    "sg:address":"Shop 3",
    "sg:city":"New World Arcade Biloela",
    "sg:classifiers":[
        {
            "category":"Personal",
            "subcategory":"Massage",
            "type":"Services"
        }
    ],
    "sg:phone":"+61 7 4992 2120",
    "sg:postcode":"4715",
    "sg:province":"QLD",
    "sg:tags":[
        "therapy"
    ],
    "wof:name":"Byrd M & Weller H",
    "wof:placetype":"venue"
},
  "geometry": {"coordinates":[150.51252746599999,-24.4025592804],"type":"Point"}
}