{
  "type": "Feature",
  "properties": {
    "addr:full":"113 Smart Rd Modbury SA 5092",
    "addr:housenumber":"113",
    "addr:postcode":"5092",
    "addr:street":"Smart Rd",
    "iso:country":"AU",
    "sg:address":"113 Smart Rd",
    "sg:city":"Modbury",
    "sg:classifiers":[
        {
            "category":"Health Services",
            "subcategory":"Doctor",
            "type":"Services"
        }
    ],
    "sg:phone":"+61 8 8265 4022",
    "sg:postcode":"5092",
    "sg:province":"SA",
    "sg:tags":[
        "medical",
        "practitioner"
    ],
    "wof:name":"Robinson Martin K Dr",
    "wof:placetype":"venue"
},
  "geometry": {"coordinates":[138.69598388700001,-34.8330917358],"type":"Point"}
}