{
  "type": "Feature",
  "properties": {
    "addr:full":"10 Rice St Port Sorell TAS 7307",
    "addr:housenumber":"10",
    "addr:postcode":"7307",
    "addr:street":"Rice St",
    "iso:country":"AU",
    "sg:address":"10 Rice St",
    "sg:city":"Port Sorell",
    "sg:classifiers":[
        {
            "category":"Personal",
            "subcategory":"Massage",
            "type":"Services"
        }
    ],
    "sg:phone":"+61 3 6428 6831",
    "sg:postcode":"7307",
    "sg:province":"TAS",
    "sg:tags":[
        "therapy"
    ],
    "wof:name":"Matthews Robert",
    "wof:placetype":"venue"
},
  "geometry": {"coordinates":[146.55242899999999,-41.168514],"type":"Point"}
}