{
  "type": "Feature",
  "properties": {
    "iso:country":"AU",
    "sg:address":"533 Sandgate Rd",
    "sg:city":"Clayfield",
    "sg:classifiers":[
        {
            "category":"Health Services",
            "subcategory":"Doctor",
            "type":"Services"
        }
    ],
    "sg:phone":"+61 7 3262 1288",
    "sg:postcode":"4011",
    "sg:province":"QLD",
    "sg:tags":[
        "medical",
        "practitioner"
    ],
    "wof:name":"Clayfield Medical Centre",
    "wof:placetype":"venue"
},
  "geometry": {"coordinates":[153.05564899999999,-27.418087],"type":"Point"}
}