{
  "type": "Feature",
  "properties": {
    "iso:country":"AU",
    "sg:address":"Caris Park Rd",
    "sg:city":"Pinjarra",
    "sg:classifiers":[
        {
            "category":"Building & Trades",
            "subcategory":"Landscaping Services",
            "type":"Services"
        }
    ],
    "sg:phone":"+61 8 9531 1670",
    "sg:postcode":"6208",
    "sg:province":"WA",
    "sg:tags":[
        "grazier"
    ],
    "wof:name":"Brooks Rural",
    "wof:placetype":"venue"
},
  "geometry": {"coordinates":[115.819458,-32.666225],"type":"Point"}
}