{
  "type": "Feature",
  "properties": {
    "iso:country":"AU",
    "sg:address":"Jenkins St",
    "sg:city":"Cowandilla",
    "sg:classifiers":[
        {
            "category":"Education",
            "subcategory":"School",
            "type":"Public Place"
        }
    ],
    "sg:phone":"+61 8 8443 7800",
    "sg:postcode":"5033",
    "sg:province":"SA",
    "sg:tags":[
        "state",
        "except",
        "nsw"
    ],
    "wof:name":"Cowandilla Primary",
    "wof:placetype":"venue"
},
  "geometry": {"coordinates":[138.560714722,-34.9336967468],"type":"Point"}
}