{
  "type": "Feature",
  "properties": {
    "addr:full":"127 Canterbury Rd Heathmont VIC 3135",
    "addr:housenumber":"127",
    "addr:postcode":"3135",
    "addr:street":"Canterbury Rd",
    "iso:country":"AU",
    "sg:address":"127 Canterbury Rd",
    "sg:city":"Heathmont",
    "sg:classifiers":[
        {
            "category":"Building & Trades",
            "subcategory":"Construction",
            "type":"Services"
        }
    ],
    "sg:phone":"+61 3 9729 9355",
    "sg:postcode":"3135",
    "sg:province":"VIC",
    "sg:tags":[
        "pool",
        "swimming"
    ],
    "wof:name":"Pool Fab",
    "wof:placetype":"venue"
},
  "geometry": {"coordinates":[145.24557495100001,-37.8286247253],"type":"Point"}
}