{
  "type": "Feature",
  "properties": {
    "addr:full":"85 Ocean St Dudley NSW 2290",
    "addr:housenumber":"85",
    "addr:postcode":"2290",
    "addr:street":"Ocean St",
    "iso:country":"AU",
    "sg:address":"85 Ocean St",
    "sg:city":"Dudley",
    "sg:classifiers":[
        {
            "category":"Travel",
            "subcategory":"Hotels & Motels",
            "type":"Entertainment"
        }
    ],
    "sg:phone":"+61 2 4944 8736",
    "sg:postcode":"2290",
    "sg:province":"NSW",
    "sg:tags":[
        "accommodation"
    ],
    "wof:name":"Ocean View Hotel",
    "wof:placetype":"venue"
},
  "geometry": {"coordinates":[151.719512939,-32.9894714355],"type":"Point"}
}