{
  "type": "Feature",
  "properties": {
    "iso:country":"AU",
    "sg:address":"343 Neerim Rd",
    "sg:city":"Carnegie",
    "sg:classifiers":[
        {
            "category":"Professional",
            "subcategory":"Accounting & Tax Preparation",
            "type":"Services"
        }
    ],
    "sg:phone":"+61 3 9568 4329",
    "sg:postcode":"3163",
    "sg:province":"VIC",
    "sg:tags":[
        "accountant",
        "auditor"
    ],
    "wof:name":"McMaster G & Co",
    "wof:placetype":"venue"
},
  "geometry": {"coordinates":[145.059814453,-37.8896446228],"type":"Point"}
}