{
  "type": "Feature",
  "properties": {
    "addr:full":"Unit 4/ 121 Newton Rd Wetherill Park NSW 2164",
    "addr:housenumber":"/ 121",
    "addr:postcode":"2164",
    "addr:street":"Newton Rd",
    "iso:country":"AU",
    "sg:address":"Unit 4/ 121 Newton Rd",
    "sg:city":"Wetherill Park",
    "sg:classifiers":[
        {
            "category":"Transit Center",
            "subcategory":"Freight",
            "type":"Transportation"
        }
    ],
    "sg:phone":"+61 2 9756 0737",
    "sg:postcode":"2164",
    "sg:province":"NSW",
    "sg:tags":[
        "equipment",
        "transport",
        "road",
        "vehicle"
    ],
    "wof:name":"Grauer Truck & Trailer Gates Pty Ltd",
    "wof:placetype":"venue"
},
  "geometry": {"coordinates":[150.893508911,-33.8439826965],"type":"Point"}
}