{
  "type": "Feature",
  "properties": {
    "iso:country":"AU",
    "sg:address":"Shop 24 Cleveland Harbourside Shopping Centre",
    "sg:city":"Cleveland",
    "sg:classifiers":[
        {
            "category":"Food & Beverages",
            "subcategory":"Bakery",
            "type":"Retail Goods"
        }
    ],
    "sg:phone":"+61 7 3383 1255",
    "sg:postcode":"4163",
    "sg:province":"QLD",
    "sg:tags":[
        "baker"
    ],
    "wof:name":"Banjo's Bakehouse",
    "wof:placetype":"venue"
},
  "geometry": {"coordinates":[153.26051330600001,-27.5171585083],"type":"Point"}
}