{
  "type": "Feature",
  "properties": {
    "iso:country":"AU",
    "sg:address":"27 Poplar Crs",
    "sg:city":"Emerald",
    "sg:classifiers":[
        {
            "category":"Building & Trades",
            "subcategory":"Construction",
            "type":"Services"
        }
    ],
    "sg:phone":"+61 418 342 349",
    "sg:postcode":"3782",
    "sg:province":"VIC",
    "sg:tags":[
        "contractor"
    ],
    "wof:name":"Rosehaven Construction",
    "wof:placetype":"venue"
},
  "geometry": {"coordinates":[145.441025,-37.932072],"type":"Point"}
}