{
  "type": "Feature",
  "properties": {
    "addr:full":"18 Mallawa St Buddina QLD 4575",
    "addr:housenumber":"18",
    "addr:postcode":"4575",
    "addr:street":"Mallawa St",
    "iso:country":"AU",
    "sg:address":"18 Mallawa St",
    "sg:city":"Buddina",
    "sg:classifiers":[
        {
            "category":"Professional",
            "subcategory":"Art Services",
            "type":"Services"
        }
    ],
    "sg:phone":"+61 7 5444 3414",
    "sg:postcode":"4575",
    "sg:province":"QLD",
    "sg:tags":[
        "decorator",
        "painter"
    ],
    "wof:name":"Jefferies & Son",
    "wof:placetype":"venue"
},
  "geometry": {"coordinates":[153.134445,-26.696453],"type":"Point"}
}