{
  "type": "Feature",
  "properties": {
    "iso:country":"AU",
    "sg:address":"79- 81 Sinclair St",
    "sg:city":"Crows Nest",
    "sg:classifiers":[
        {
            "category":"Health Services",
            "subcategory":"Health Practitioner",
            "type":"Services"
        }
    ],
    "sg:phone":"+61 2 9436 4488",
    "sg:postcode":"2065",
    "sg:province":"NSW",
    "sg:tags":[
        "physiotherapist"
    ],
    "sg:website":"http:// www.northsydneyphysio.com.au",
    "wof:name":"North Sydney Orthopaedic & Sports Medicine Centre",
    "wof:placetype":"venue"
},
  "geometry": {"coordinates":[151.20021057100001,-33.8286705017],"type":"Point"}
}