{
  "type": "Feature",
  "properties": {
    "addr:full":"6a Beach Ave Mordialloc VIC 3195",
    "addr:housenumber":"6a",
    "addr:postcode":"3195",
    "addr:street":"Beach Ave",
    "iso:country":"AU",
    "sg:address":"6a Beach Ave",
    "sg:city":"Mordialloc",
    "sg:classifiers":[
        {
            "category":"Wholesale",
            "subcategory":"Auto Parts",
            "type":"Manufacturing & Wholesale Goods"
        }
    ],
    "sg:phone":"+61 1300 996 799",
    "sg:postcode":"3195",
    "sg:province":"VIC",
    "sg:tags":[
        "recyclers"
    ],
    "sg:website":"http://www.zworx.com.au",
    "wof:name":"Z Worx",
    "wof:placetype":"venue"
},
  "geometry": {"coordinates":[145.10069274899999,-38.0101203918],"type":"Point"}
}