{
  "type": "Feature",
  "properties": {
    "iso:country":"AU",
    "sg:address":"P2, 10- 16 South St",
    "sg:city":"Rydalmere",
    "sg:classifiers":[
        {
            "category":"Professional",
            "subcategory":"Detective & Security Services",
            "type":"Services"
        }
    ],
    "sg:phone":"+61 2 9638 6400",
    "sg:postcode":"2116",
    "sg:province":"NSW",
    "sg:tags":[
        "consultant",
        "system"
    ],
    "wof:name":"PACOM Pacific Communications Group",
    "wof:placetype":"venue"
},
  "geometry": {"coordinates":[151.01101684599999,-33.8332099915],"type":"Point"}
}