{
  "type": "Feature",
  "properties": {
    "iso:country":"AU",
    "sg:address":"2/ 286 Evans Rd",
    "sg:city":"Salisbury",
    "sg:classifiers":[
        {
            "category":"Manufacturing",
            "subcategory":"Retail Goods",
            "type":"Manufacturing & Wholesale Goods"
        }
    ],
    "sg:phone":"+61 7 3277 9118",
    "sg:postcode":"4107",
    "sg:province":"QLD",
    "sg:tags":[
        "merchant",
        "pump",
        "mfrs"
    ],
    "wof:name":"Haskel Australasia",
    "wof:placetype":"venue"
},
  "geometry": {"coordinates":[153.03741455100001,-27.545835495],"type":"Point"}
}