{
  "type": "Feature",
  "properties": {
    "iso:country":"AU",
    "sg:address":"Stanford Rd",
    "sg:city":"Salisbury Heights",
    "sg:classifiers":[
        {
            "category":"Education",
            "subcategory":"Kindergarten",
            "type":"Public Place"
        }
    ],
    "sg:phone":"+61 8 8281 7293",
    "sg:postcode":"5109",
    "sg:province":"SA",
    "sg:tags":[
        "pre-schools"
    ],
    "wof:name":"Salisbury Heights Preschool",
    "wof:placetype":"venue"
},
  "geometry": {"coordinates":[138.67864990199999,-34.7662391663],"type":"Point"}
}