{
  "type": "Feature",
  "properties": {
    "iso:country":"AU",
    "sg:address":"388 Forest Rd",
    "sg:city":"Bexley",
    "sg:classifiers":[
        {
            "category":"Shopping",
            "subcategory":"Baby Store",
            "type":"Retail Goods"
        }
    ],
    "sg:phone":"+61 2 9599 0018",
    "sg:postcode":"2207",
    "sg:province":"NSW",
    "sg:tags":[
        "wear"
    ],
    "wof:name":"Gowns By Vera Bridal, Christening & Communion Wear",
    "wof:placetype":"venue"
},
  "geometry": {"coordinates":[151.124344,-33.951736],"type":"Point"}
}