{
  "type": "Feature",
  "properties": {
    "addr:full":"32 Bonanza Rd Port Lincoln SA 5606",
    "addr:housenumber":"32",
    "addr:postcode":"5606",
    "addr:street":"Bonanza Rd",
    "iso:country":"AU",
    "sg:address":"32 Bonanza Rd",
    "sg:city":"Port Lincoln",
    "sg:classifiers":[
        {
            "category":"Farming",
            "subcategory":"Fish & Marine Products",
            "type":"Manufacturing & Wholesale Goods"
        }
    ],
    "sg:phone":"+61 8 8682 2218",
    "sg:postcode":"5606",
    "sg:province":"SA",
    "sg:tags":[
        "fisherman"
    ],
    "wof:name":"Satalic A",
    "wof:placetype":"venue"
},
  "geometry": {"coordinates":[135.84260599999999,-34.717098],"type":"Point"}
}