{
  "type": "Feature",
  "properties": {
    "addr:full":"20 Mullens St Balmain NSW 2041",
    "addr:housenumber":"20",
    "addr:postcode":"2041",
    "addr:street":"Mullens St",
    "iso:country":"AU",
    "sg:address":"20 Mullens St",
    "sg:city":"Balmain",
    "sg:classifiers":[
        {
            "category":"Professional",
            "subcategory":"Computer Services",
            "type":"Services"
        }
    ],
    "sg:phone":"+61 414 250 893",
    "sg:postcode":"2041",
    "sg:province":"NSW",
    "sg:tags":[
        "consultant",
        "system"
    ],
    "wof:name":"Casewood",
    "wof:placetype":"venue"
},
  "geometry": {"coordinates":[151.17752100000001,-33.85955],"type":"Point"}
}