{
  "type": "Feature",
  "properties": {
    "iso:country":"AU",
    "sg:address":"41 Howard Rd",
    "sg:city":"Padstow",
    "sg:classifiers":[
        {
            "category":"Shopping",
            "subcategory":"Clothing, Apparel, & Fashions",
            "type":"Retail Goods"
        }
    ],
    "sg:phone":"+61 2 9774 5452",
    "sg:postcode":"2211",
    "sg:province":"NSW",
    "sg:tags":[
        "recycled",
        "clothing"
    ],
    "wof:name":"Padstow Community Bargain Centre",
    "wof:placetype":"venue"
},
  "geometry": {"coordinates":[151.032684,-33.952297],"type":"Point"}
}