{
  "type": "Feature",
  "properties": {
    "iso:country":"AU",
    "sg:address":"321 Bay St",
    "sg:city":"Port Melbourne",
    "sg:classifiers":[
        {
            "category":"Bars & Pubs",
            "subcategory":"Wine Bar",
            "type":"Food & Drink"
        }
    ],
    "sg:phone":"+61 3 9645 2810",
    "sg:postcode":"3207",
    "sg:province":"VIC",
    "wof:name":"Eleven Bar Lounge",
    "wof:placetype":"venue"
},
  "geometry": {"coordinates":[144.94426,-37.836273],"type":"Point"}
}