{
  "type": "Feature",
  "properties": {
    "addr:full":"14 Dalton St Parkes NSW 2870",
    "addr:housenumber":"14",
    "addr:postcode":"2870",
    "addr:street":"Dalton St",
    "iso:country":"AU",
    "sg:address":"14 Dalton St",
    "sg:city":"Parkes",
    "sg:classifiers":[
        {
            "category":"Taxi",
            "type":"Transportation"
        }
    ],
    "sg:phone":"+61 2 6862 2222",
    "sg:postcode":"2870",
    "sg:province":"NSW",
    "sg:tags":[
        "cab"
    ],
    "wof:name":"Parkes Taxis",
    "wof:placetype":"venue"
},
  "geometry": {"coordinates":[148.17392000000001,-33.137215],"type":"Point"}
}