{
  "type": "Feature",
  "properties": {
    "iso:country":"AU",
    "sg:address":"77-83 Stokes St",
    "sg:city":"Edmonton",
    "sg:classifiers":[
        {
            "category":"Education",
            "subcategory":"School",
            "type":"Public Place"
        }
    ],
    "sg:phone":"+61 7 4040 8666",
    "sg:postcode":"4869",
    "sg:province":"QLD",
    "sg:tags":[
        "state",
        "except",
        "nsw"
    ],
    "wof:name":"Hambledon Primary School",
    "wof:placetype":"venue"
},
  "geometry": {"coordinates":[145.73570251500001,-17.0212459564],"type":"Point"}
}