{
  "type": "Feature",
  "properties": {
    "iso:country":"AU",
    "sg:address":"2 Parkland Drv",
    "sg:city":"Hamlyn Heights",
    "sg:classifiers":[
        {
            "category":"Travel",
            "subcategory":"Travel Agent",
            "type":"Entertainment"
        }
    ],
    "sg:phone":"+61 419 527 339",
    "sg:postcode":"3215",
    "sg:province":"VIC",
    "sg:tags":[
        "tour",
        "holiday",
        "adventure"
    ],
    "wof:name":"Firstcast Fishing Adventures",
    "wof:placetype":"venue"
},
  "geometry": {"coordinates":[144.32281494099999,-38.1112823486],"type":"Point"}
}