{
  "type": "Feature",
  "properties": {
    "iso:country":"AU",
    "sg:address":"92 Gellibrand St",
    "sg:city":"Colac",
    "sg:classifiers":[
        {
            "category":"Personal",
            "subcategory":"Beauty Salon",
            "type":"Services"
        }
    ],
    "sg:phone":"+61 3 5232 2002",
    "sg:postcode":"3250",
    "sg:province":"VIC",
    "sg:tags":[
        "hairdresser"
    ],
    "wof:name":"Colac Men Only",
    "wof:placetype":"venue"
},
  "geometry": {"coordinates":[143.58691400000001,-38.341679],"type":"Point"}
}