{
  "type": "Feature",
  "properties": {
    "addr:full":"39 Goold St Bairnsdale VIC 3875",
    "addr:housenumber":"39",
    "addr:postcode":"3875",
    "addr:street":"Goold St",
    "iso:country":"AU",
    "sg:address":"39 Goold St",
    "sg:city":"Bairnsdale",
    "sg:classifiers":[
        {
            "category":"Professional",
            "subcategory":"Art Services",
            "type":"Services"
        }
    ],
    "sg:phone":"+61 408 052 226",
    "sg:postcode":"3875",
    "sg:province":"VIC",
    "sg:tags":[
        "decorator",
        "painter"
    ],
    "wof:name":"Frank Aloisio Painter & Decorator",
    "wof:placetype":"venue"
},
  "geometry": {"coordinates":[147.61257934599999,-37.8258705139],"type":"Point"}
}