{
  "type": "Feature",
  "properties": {
    "addr:full":"U 3/ 55 Lumley St Upper Mt Gravatt QLD 4122",
    "addr:housenumber":"55",
    "addr:postcode":"4122",
    "addr:street":"Lumley St",
    "iso:country":"AU",
    "sg:address":"U 3/ 55 Lumley St",
    "sg:city":"Upper Mt Gravatt",
    "sg:classifiers":[
        {
            "category":"Wholesale",
            "subcategory":"Non-durable Goods",
            "type":"Manufacturing & Wholesale Goods"
        }
    ],
    "sg:phone":"+61 7 3216 8668",
    "sg:postcode":"4122",
    "sg:province":"QLD",
    "sg:tags":[
        "wholesaler",
        "mfrs",
        "cosmetic"
    ],
    "wof:name":"Syben Marketing Pty Ltd",
    "wof:placetype":"venue"
},
  "geometry": {"coordinates":[153.08297729500001,-27.5525951385],"type":"Point"}
}