{
  "type": "Feature",
  "properties": {
    "addr:full":"43 King St Warrawong NSW 2502",
    "addr:housenumber":"43",
    "addr:postcode":"2502",
    "addr:street":"King St",
    "iso:country":"AU",
    "sg:address":"43 King St",
    "sg:city":"Warrawong",
    "sg:classifiers":[
        {
            "category":"Health Services",
            "subcategory":"Doctor",
            "type":"Services"
        }
    ],
    "sg:phone":"+61 2 4275 1800",
    "sg:postcode":"2502",
    "sg:province":"NSW",
    "sg:tags":[
        "medical",
        "practitioner"
    ],
    "wof:name":"Bock S J",
    "wof:placetype":"venue"
},
  "geometry": {"coordinates":[150.88754299999999,-34.483093],"type":"Point"}
}