{
  "type": "Feature",
  "properties": {
    "iso:country":"AU",
    "sg:address":"22 John St",
    "sg:city":"Abermain",
    "sg:classifiers":[
        {
            "category":"Building & Trades",
            "subcategory":"Construction",
            "type":"Services"
        }
    ],
    "sg:phone":"+61 2 4930 8046",
    "sg:postcode":"2326",
    "sg:province":"NSW",
    "sg:tags":[
        "installation",
        "air conditioning"
    ],
    "wof:name":"Warren Allaway Air Conditioning Refrigeration & Electrical",
    "wof:placetype":"venue"
},
  "geometry": {"coordinates":[151.434692383,-32.8138046265],"type":"Point"}
}