{
  "type": "Feature",
  "properties": {
    "addr:full":"404 Scarborough Beach Rd Osborne Park WA 6017",
    "addr:housenumber":"404",
    "addr:postcode":"6017",
    "addr:street":"Scarborough Beach Rd",
    "iso:country":"AU",
    "sg:address":"404 Scarborough Beach Rd",
    "sg:city":"Osborne Park",
    "sg:classifiers":[
        {
            "category":"Retail",
            "subcategory":"Auto Repair",
            "type":"Services"
        }
    ],
    "sg:phone":"+61 8 9444 6511",
    "sg:postcode":"6017",
    "sg:province":"WA",
    "sg:tags":[
        "repairer",
        "motor",
        "engineer"
    ],
    "wof:name":"Midas",
    "wof:placetype":"venue"
},
  "geometry": {"coordinates":[115.813919067,-31.9099960327],"type":"Point"}
}