{
  "type": "Feature",
  "properties": {
    "iso:country":"AU",
    "sg:address":"1 Admiralty Rd",
    "sg:city":"Canning Vale",
    "sg:classifiers":[
        {
            "category":"Utilities",
            "subcategory":"Electric",
            "type":"Services"
        }
    ],
    "sg:phone":"+61 422 380 582",
    "sg:postcode":"6155",
    "sg:province":"WA",
    "sg:tags":[
        "electrical",
        "contractor"
    ],
    "wof:name":"May Electrical Services",
    "wof:placetype":"venue"
},
  "geometry": {"coordinates":[115.935959,-32.075371],"type":"Point"}
}