{
  "type": "Feature",
  "properties": {
    "addr:full":"Cnr Jaybel & Flanders Sts Salisbury QLD 4107",
    "addr:postcode":"4107",
    "addr:street":"Cnr",
    "iso:country":"AU",
    "sg:address":"Cnr Jaybel & Flanders Sts",
    "sg:city":"Salisbury",
    "sg:classifiers":[
        {
            "category":"Wholesale",
            "subcategory":"Machinery & Supplies",
            "type":"Manufacturing & Wholesale Goods"
        }
    ],
    "sg:phone":"+61 7 3216 7855",
    "sg:postcode":"4107",
    "sg:province":"QLD",
    "sg:tags":[
        "equipment",
        "hydraulic"
    ],
    "wof:name":"GFR Industries",
    "wof:placetype":"venue"
},
  "geometry": {"coordinates":[153.03802490199999,-27.5423412323],"type":"Point"}
}