{
  "type": "Feature",
  "properties": {
    "iso:country":"AU",
    "sg:address":"U/25 Mackie House 71 South Pine Rd",
    "sg:city":"Brendale",
    "sg:classifiers":[
        {
            "category":"Manufacturing",
            "subcategory":"Motor Vehicles & Parts",
            "type":"Manufacturing & Wholesale Goods"
        }
    ],
    "sg:phone":"+61 7 3205 2969",
    "sg:postcode":"4500",
    "sg:province":"QLD",
    "sg:tags":[
        "replacement"
    ],
    "wof:name":"Natrad",
    "wof:placetype":"venue"
},
  "geometry": {"coordinates":[152.989135742,-27.312702179],"type":"Point"}
}