{
  "type": "Feature",
  "properties": {
    "addr:full":"44 Otho St Inverell NSW 2360",
    "addr:housenumber":"44",
    "addr:postcode":"2360",
    "addr:street":"Otho St",
    "iso:country":"AU",
    "sg:address":"44 Otho St",
    "sg:city":"Inverell",
    "sg:classifiers":[
        {
            "category":"Shopping",
            "subcategory":"Shoes",
            "type":"Retail Goods"
        }
    ],
    "sg:phone":"+61 2 6722 4079",
    "sg:postcode":"2360",
    "sg:province":"NSW",
    "sg:tags":[
        "footwear"
    ],
    "wof:name":"Payless Shoes",
    "wof:placetype":"venue"
},
  "geometry": {"coordinates":[151.112350464,-29.7741546631],"type":"Point"}
}