{
  "type": "Feature",
  "properties": {
    "iso:country":"AU",
    "sg:address":"PO Box 293",
    "sg:city":"Port Douglas",
    "sg:classifiers":[
        {
            "category":"Recreation",
            "subcategory":"Boat Charter",
            "type":"Entertainment"
        }
    ],
    "sg:phone":"+61 418 300 764",
    "sg:postcode":"4877",
    "sg:province":"QLD",
    "wof:name":"Reel Screamer",
    "wof:placetype":"venue"
},
  "geometry": {"coordinates":[145.46543884299999,-16.4844493866],"type":"Point"}
}