{
  "type": "Feature",
  "properties": {
    "addr:full":"36 Duells Rd Rosebud South VIC 3939",
    "addr:housenumber":"36",
    "addr:postcode":"3939",
    "addr:street":"Duells Rd",
    "iso:country":"AU",
    "sg:address":"36 Duells Rd",
    "sg:city":"Rosebud South",
    "sg:classifiers":[
        {
            "category":"Social Services",
            "subcategory":"Child Care",
            "type":"Services"
        }
    ],
    "sg:phone":"+61 3 5986 7840",
    "sg:postcode":"3939",
    "sg:province":"VIC",
    "wof:name":"Peninsula Sands Pre School",
    "wof:placetype":"venue"
},
  "geometry": {"coordinates":[144.92703247099999,-38.3857574463],"type":"Point"}
}