{
  "type": "Feature",
  "properties": {
    "iso:country":"AU",
    "sg:address":"96 Brisbane St",
    "sg:city":"Launceston",
    "sg:classifiers":[
        {
            "category":"Professional",
            "subcategory":"Art Services",
            "type":"Services"
        }
    ],
    "sg:phone":"+61 3 6331 9604",
    "sg:postcode":"7250",
    "sg:province":"TAS",
    "sg:tags":[
        "picture",
        "frame",
        "framing"
    ],
    "wof:name":"Stallard's Camera House",
    "wof:placetype":"venue"
},
  "geometry": {"coordinates":[147.13917541500001,-41.4369735718],"type":"Point"}
}