{
  "type": "Feature",
  "properties": {
    "iso:country":"AU",
    "sg:address":"Unit 2, 13 Penny Pl",
    "sg:city":"Arndell Park",
    "sg:classifiers":[
        {
            "category":"Train Station",
            "subcategory":"Light Rail",
            "type":"Transportation"
        }
    ],
    "sg:phone":"+61 2 9676 3000",
    "sg:postcode":"2148",
    "sg:province":"NSW",
    "sg:tags":[
        "survey",
        "traffic"
    ],
    "wof:name":"TTM Data",
    "wof:placetype":"venue"
},
  "geometry": {"coordinates":[150.89503479000001,-33.7961196899],"type":"Point"}
}