{
  "type": "Feature",
  "properties": {
    "addr:full":"Industrial Estate Sweet St Warners Bay NSW 2282",
    "addr:postcode":"2282",
    "addr:street":"St",
    "iso:country":"AU",
    "sg:address":"Industrial Estate Sweet St",
    "sg:city":"Warners Bay",
    "sg:classifiers":[
        {
            "category":"Building & Trades",
            "subcategory":"Construction",
            "type":"Services"
        }
    ],
    "sg:phone":"+61 2 4948 7077",
    "sg:postcode":"2282",
    "sg:province":"NSW",
    "sg:tags":[
        "worker",
        "metal"
    ],
    "wof:name":"McKanna Fabrications Pty Ltd",
    "wof:placetype":"venue"
},
  "geometry": {"coordinates":[151.65101623499999,-32.9690704346],"type":"Point"}
}