{
  "type": "Feature",
  "properties": {
    "iso:country":"AU",
    "sg:address":"53 McCoy St",
    "sg:city":"Myaree",
    "sg:classifiers":[
        {
            "category":"Retail",
            "subcategory":"Auto Repair",
            "type":"Services"
        }
    ],
    "sg:phone":"+61 8 9317 2333",
    "sg:postcode":"6154",
    "sg:province":"WA",
    "sg:tags":[
        "repairer",
        "motor",
        "engineer"
    ],
    "sg:website":"http://www.melvilletoyota.com.au",
    "wof:name":"Melville Toyota",
    "wof:placetype":"venue"
},
  "geometry": {"coordinates":[115.813164,-32.043678],"type":"Point"}
}