{
  "type": "Feature",
  "properties": {
    "iso:country":"AU",
    "sg:address":"50 Claremont Ave",
    "sg:city":"Greenacre",
    "sg:classifiers":[
        {
            "category":"Home & Garden",
            "subcategory":"Building Materials",
            "type":"Retail Goods"
        }
    ],
    "sg:phone":"+61 2 9790 6655",
    "sg:postcode":"2190",
    "sg:province":"NSW",
    "sg:tags":[
        "merchant",
        "glass",
        "glazier"
    ],
    "wof:name":"F & H Aluminuim Windows & Doors",
    "wof:placetype":"venue"
},
  "geometry": {"coordinates":[151.03848300000001,-33.901466],"type":"Point"}
}