{
  "type": "Feature",
  "properties": {
    "iso:country":"AU",
    "sg:address":"Cnr. Meroo & Bunberra Sts",
    "sg:city":"Bomaderry",
    "sg:classifiers":[
        {
            "category":"Retail",
            "subcategory":"Repair Shop",
            "type":"Services"
        }
    ],
    "sg:phone":"+61 2 4423 0484",
    "sg:postcode":"2541",
    "sg:province":"NSW",
    "sg:tags":[
        "stove",
        "part",
        "range"
    ],
    "wof:name":"Dix Electrical South Coast",
    "wof:placetype":"venue"
},
  "geometry": {"coordinates":[150.610870361,-34.8507919312],"type":"Point"}
}