{
  "type": "Feature",
  "properties": {
    "addr:full":"114 Whitelaw St Meeniyan VIC 3956",
    "addr:housenumber":"114",
    "addr:postcode":"3956",
    "addr:street":"Whitelaw St",
    "iso:country":"AU",
    "sg:address":"114 Whitelaw St",
    "sg:city":"Meeniyan",
    "sg:classifiers":[
        {
            "category":"Wholesale",
            "subcategory":"Machinery & Supplies",
            "type":"Manufacturing & Wholesale Goods"
        }
    ],
    "sg:phone":"+61 3 5664 7365",
    "sg:postcode":"3956",
    "sg:province":"VIC",
    "sg:tags":[
        "agricultural"
    ],
    "wof:name":"Meeniyan Tractor Service",
    "wof:placetype":"venue"
},
  "geometry": {"coordinates":[145.91839599599999,-38.5414619446],"type":"Point"}
}