{
  "type": "Feature",
  "properties": {
    "iso:country":"AU",
    "sg:address":"15 Govan St",
    "sg:city":"Seaford",
    "sg:classifiers":[
        {
            "category":"Building & Trades",
            "subcategory":"Construction",
            "type":"Services"
        }
    ],
    "sg:phone":"+61 3 9786 6633",
    "sg:postcode":"3198",
    "sg:province":"VIC",
    "sg:tags":[
        "fencing",
        "contractor"
    ],
    "wof:name":"Phoenix Safety Rail Pty Ltd",
    "wof:placetype":"venue"
},
  "geometry": {"coordinates":[145.132156372,-38.1161499023],"type":"Point"}
}