{
  "type": "Feature",
  "properties": {
    "addr:full":"58 Brown Pde Ashgrove QLD 4060",
    "addr:housenumber":"58",
    "addr:postcode":"4060",
    "addr:street":"Brown Pde",
    "iso:country":"AU",
    "sg:address":"58 Brown Pde",
    "sg:city":"Ashgrove",
    "sg:classifiers":[
        {
            "category":"Professional",
            "subcategory":"Detective & Security Services",
            "type":"Services"
        }
    ],
    "sg:phone":"+61 403 120 888",
    "sg:postcode":"4060",
    "sg:province":"QLD",
    "sg:tags":[
        "guard",
        "patrol"
    ],
    "wof:name":"North City Suburban Security",
    "wof:placetype":"venue"
},
  "geometry": {"coordinates":[152.99270629899999,-27.435968399],"type":"Point"}
}