{
  "type": "Feature",
  "properties": {
    "iso:country":"AU",
    "sg:address":"300 Oxley Ave",
    "sg:city":"Margate",
    "sg:classifiers":[
        {
            "category":"Real Estate",
            "subcategory":"Real Estate Agent",
            "type":"Services"
        }
    ],
    "sg:phone":"+61 7 3284 7477",
    "sg:postcode":"4019",
    "sg:province":"QLD",
    "wof:name":"Nationwide/Advant Realty",
    "wof:placetype":"venue"
},
  "geometry": {"coordinates":[153.10746765100001,-27.2421760559],"type":"Point"}
}