{
  "type": "Feature",
  "properties": {
    "addr:full":"21 Green St Thomastown VIC 3074",
    "addr:housenumber":"21",
    "addr:postcode":"3074",
    "addr:street":"Green St",
    "iso:country":"AU",
    "sg:address":"21 Green St",
    "sg:city":"Thomastown",
    "sg:classifiers":[
        {
            "category":"Manufacturing",
            "subcategory":"Tools & Machinery",
            "type":"Manufacturing & Wholesale Goods"
        }
    ],
    "sg:phone":"+61 1300 731 360",
    "sg:postcode":"3074",
    "sg:province":"VIC",
    "sg:tags":[
        "equipment",
        "scale",
        "weighing"
    ],
    "sg:website":"http://www.ablescale.com.au",
    "wof:name":"Able Scale Company Pty Ltd",
    "wof:placetype":"venue"
},
  "geometry": {"coordinates":[145.037719727,-37.6924171448],"type":"Point"}
}