{
  "type": "Feature",
  "properties": {
    "addr:full":"PO Box 1048 Bridgetown WA 6255",
    "addr:postcode":"6255",
    "iso:country":"AU",
    "sg:address":"PO Box 1048",
    "sg:city":"Bridgetown",
    "sg:classifiers":[
        {
            "category":"Personal",
            "subcategory":"Massage",
            "type":"Services"
        }
    ],
    "sg:phone":"+61 429 111 828",
    "sg:postcode":"6255",
    "sg:province":"WA",
    "sg:tags":[
        "therapy"
    ],
    "wof:name":"Natural Senses",
    "wof:placetype":"venue"
},
  "geometry": {"coordinates":[116.13680267300001,-33.955909729],"type":"Point"}
}