{
  "type": "Feature",
  "properties": {
    "addr:full":"Level 8, 153 Walker St North Sydney NSW 2060",
    "addr:housenumber":"153",
    "addr:postcode":"2060",
    "addr:street":"Walker St",
    "iso:country":"AU",
    "sg:address":"Level 8, 153 Walker St",
    "sg:city":"North Sydney",
    "sg:classifiers":[
        {
            "category":"Professional",
            "subcategory":"Management & Consulting",
            "type":"Services"
        }
    ],
    "sg:phone":"+61 2 9377 1177",
    "sg:postcode":"2060",
    "sg:province":"NSW",
    "sg:tags":[
        "consultant"
    ],
    "wof:name":"Blue Grass Consulting",
    "wof:placetype":"venue"
},
  "geometry": {"coordinates":[151.209274292,-33.8375663757],"type":"Point"}
}