{
  "type": "Feature",
  "properties": {
    "iso:country":"AU",
    "sg:address":"Shop 5, 165- 171 Bloomfield St",
    "sg:city":"Cleveland",
    "sg:classifiers":[
        {
            "category":"Shopping",
            "subcategory":"Computers & Home Electronics",
            "type":"Retail Goods"
        }
    ],
    "sg:phone":"+61 7 3821 0033",
    "sg:postcode":"4163",
    "sg:province":"QLD",
    "sg:tags":[
        "equipment",
        "supply"
    ],
    "wof:name":"Raptek",
    "wof:placetype":"venue"
},
  "geometry": {"coordinates":[153.26675415,-27.5294017792],"type":"Point"}
}