{
  "type": "Feature",
  "properties": {
    "addr:full":"Shop 205 Morayfield SC Morayfield QLD 4506",
    "addr:housenumber":"205",
    "addr:postcode":"4506",
    "addr:street":"Morayfield",
    "iso:country":"AU",
    "sg:address":"Shop 205",
    "sg:city":"Morayfield SC Morayfield",
    "sg:classifiers":[
        {
            "category":"Health Services",
            "subcategory":"Optometrist",
            "type":"Services"
        }
    ],
    "sg:phone":"+61 7 5499 2585",
    "sg:postcode":"4506",
    "sg:province":"QLD",
    "wof:name":"Meagher Carey Optometrists",
    "wof:placetype":"venue"
},
  "geometry": {"coordinates":[152.947799683,-27.1067466736],"type":"Point"}
}