{
  "type": "Feature",
  "properties": {
    "iso:country":"AU",
    "sg:address":"Unit 4 22 Rendle St",
    "sg:city":"Aitkenvale",
    "sg:classifiers":[
        {
            "category":"Professional",
            "subcategory":"Detective & Security Services",
            "type":"Services"
        }
    ],
    "sg:phone":"+61 7 4728 1422",
    "sg:postcode":"4814",
    "sg:province":"QLD",
    "sg:tags":[
        "domestic",
        "alarm",
        "commercial",
        "burglar"
    ],
    "wof:name":"Freeman Electrical & Security Pty Ltd",
    "wof:placetype":"venue"
},
  "geometry": {"coordinates":[146.76887500000001,-19.292049],"type":"Point"}
}