{
  "type": "Feature",
  "properties": {
    "iso:country":"AU",
    "sg:address":"21 Roghan Rd",
    "sg:city":"Boondall",
    "sg:classifiers":[
        {
            "category":"Professional",
            "subcategory":"Printing & Photocopies",
            "type":"Services"
        }
    ],
    "sg:phone":"+61 1300 727 840",
    "sg:postcode":"4034",
    "sg:province":"QLD",
    "sg:tags":[
        "laminating"
    ],
    "wof:name":"Busy Bee",
    "wof:placetype":"venue"
},
  "geometry": {"coordinates":[153.058334,-27.343437],"type":"Point"}
}