{
  "type": "Feature",
  "properties": {
    "addr:full":"Lot 29 Wineglass Drv Hillcrest QLD 4118",
    "addr:postcode":"4118",
    "addr:street":"Wineglass Drv",
    "iso:country":"AU",
    "sg:address":"Lot 29 Wineglass Drv",
    "sg:city":"Hillcrest",
    "sg:classifiers":[
        {
            "category":"Sports & Exercise",
            "subcategory":"Gym",
            "type":"Entertainment"
        }
    ],
    "sg:phone":"+61 7 3800 7933",
    "sg:postcode":"4118",
    "sg:province":"QLD",
    "sg:tags":[
        "health",
        "fitness"
    ],
    "wof:name":"Logans Heros",
    "wof:placetype":"venue"
},
  "geometry": {"coordinates":[153.02821350100001,-27.6746997833],"type":"Point"}
}