{
  "type": "Feature",
  "properties": {
    "addr:full":"2 Hitchcock St Castlemaine VIC 3450",
    "addr:housenumber":"2",
    "addr:postcode":"3450",
    "addr:street":"Hitchcock St",
    "iso:country":"AU",
    "sg:address":"2 Hitchcock St",
    "sg:city":"Castlemaine",
    "sg:classifiers":[
        {
            "category":"Bars & Pubs",
            "subcategory":"Biergarten",
            "type":"Food & Drink"
        }
    ],
    "sg:phone":"+61 3 5470 5700",
    "sg:postcode":"3450",
    "sg:province":"VIC",
    "sg:tags":[
        "eucalyptus",
        "oil",
        "tree",
        "essential",
        "tea"
    ],
    "wof:name":"Australian Natural Essentials",
    "wof:placetype":"venue"
},
  "geometry": {"coordinates":[144.237228394,-37.0744247437],"type":"Point"}
}