{
  "type": "Feature",
  "properties": {
    "addr:full":"Building 11 Keiraville NSW 2500",
    "addr:postcode":"2500",
    "iso:country":"AU",
    "sg:address":"Building 11",
    "sg:city":"Keiraville",
    "sg:classifiers":[
        {
            "category":"Health Services",
            "subcategory":"Optometrist",
            "type":"Services"
        }
    ],
    "sg:phone":"+61 2 4226 2199",
    "sg:postcode":"2500",
    "sg:province":"NSW",
    "wof:name":"ProVision Optometrists",
    "wof:placetype":"venue"
},
  "geometry": {"coordinates":[150.88679500000001,-34.401531],"type":"Point"}
}