{
  "type": "Feature",
  "properties": {
    "iso:country":"AU",
    "sg:address":"67 Eley Rd",
    "sg:city":"Box Hill South",
    "sg:classifiers":[
        {
            "category":"Travel",
            "subcategory":"Travel Agent",
            "type":"Entertainment"
        }
    ],
    "sg:phone":"+61 3 9888 8580",
    "sg:postcode":"3128",
    "sg:province":"VIC",
    "sg:tags":[
        "consultant"
    ],
    "wof:name":"Tendai Travel",
    "wof:placetype":"venue"
},
  "geometry": {"coordinates":[145.12783813499999,-37.8450393677],"type":"Point"}
}