{
  "type": "Feature",
  "properties": {
    "addr:full":"Unit 1/ 68 Gordon Rd Mandurah WA 6210",
    "addr:housenumber":"68",
    "addr:postcode":"6210",
    "addr:street":"Gordon Rd",
    "iso:country":"AU",
    "sg:address":"Unit 1/ 68 Gordon Rd",
    "sg:city":"Mandurah",
    "sg:classifiers":[
        {
            "category":"Autos & Motor Vehicles",
            "subcategory":"Boat Sales",
            "type":"Retail Goods"
        }
    ],
    "sg:phone":"+61 8 9581 7224",
    "sg:postcode":"6210",
    "sg:province":"WA",
    "sg:tags":[
        "equipment",
        "yacht"
    ],
    "wof:name":"Mandurah Outboards & Sterndrive Service",
    "wof:placetype":"venue"
},
  "geometry": {"coordinates":[115.75430299999999,-32.510799],"type":"Point"}
}