{
  "type": "Feature",
  "properties": {
    "iso:country":"AU",
    "sg:address":"2 Burrandool Ave",
    "sg:city":"Bangalee",
    "sg:classifiers":[
        {
            "category":"Building & Trades",
            "subcategory":"Construction",
            "type":"Services"
        }
    ],
    "sg:phone":"+61 2 4421 5793",
    "sg:postcode":"2541",
    "sg:province":"NSW",
    "sg:tags":[
        "contractor"
    ],
    "wof:name":"Gibson W J",
    "wof:placetype":"venue"
},
  "geometry": {"coordinates":[150.56820678700001,-34.8466720581],"type":"Point"}
}