{
  "type": "Feature",
  "properties": {
    "addr:full":"6 Tenterden Rd Botany NSW 2019",
    "addr:housenumber":"6",
    "addr:postcode":"2019",
    "addr:street":"Tenterden Rd",
    "iso:country":"AU",
    "sg:address":"6 Tenterden Rd",
    "sg:city":"Botany",
    "sg:classifiers":[
        {
            "category":"Retail",
            "subcategory":"Auto Repair",
            "type":"Services"
        }
    ],
    "sg:phone":"+61 2 9341 7891",
    "sg:postcode":"2019",
    "sg:province":"NSW",
    "sg:tags":[
        "repairer",
        "motor",
        "engineer"
    ],
    "wof:name":"LR Prestige Performance",
    "wof:placetype":"venue"
},
  "geometry": {"coordinates":[151.19984435999999,-33.9514198303],"type":"Point"}
}