{
  "type": "Feature",
  "properties": {
    "addr:full":"7 Meekatharra Pl Yarrawarrah NSW 2233",
    "addr:housenumber":"7",
    "addr:postcode":"2233",
    "addr:street":"Meekatharra Pl",
    "iso:country":"AU",
    "sg:address":"7 Meekatharra Pl",
    "sg:city":"Yarrawarrah",
    "sg:classifiers":[
        {
            "category":"Utilities",
            "subcategory":"Electric",
            "type":"Services"
        }
    ],
    "sg:phone":"+61 2 9520 2565",
    "sg:postcode":"2233",
    "sg:province":"NSW",
    "sg:tags":[
        "electrical",
        "contractor"
    ],
    "wof:name":"Honey Electrical Services Pty Ltd",
    "wof:placetype":"venue"
},
  "geometry": {"coordinates":[151.03742980999999,-34.0529022217],"type":"Point"}
}