{
  "type": "Feature",
  "properties": {
    "addr:full":"17 Wellington St Brighton VIC 3186",
    "addr:housenumber":"17",
    "addr:postcode":"3186",
    "addr:street":"Wellington St",
    "iso:country":"AU",
    "sg:address":"17 Wellington St",
    "sg:city":"Brighton",
    "sg:classifiers":[
        {
            "category":"Professional",
            "subcategory":"Accounting & Tax Preparation",
            "type":"Services"
        }
    ],
    "sg:phone":"+61 3 9592 9821",
    "sg:postcode":"3186",
    "sg:province":"VIC",
    "sg:tags":[
        "accountant",
        "auditor"
    ],
    "wof:name":"Busietta J M",
    "wof:placetype":"venue"
},
  "geometry": {"coordinates":[144.99127197300001,-37.9157180786],"type":"Point"}
}