{
  "type": "Feature",
  "properties": {
    "addr:full":"Shop 2 217 The Entrance Rd The Entrance NSW 2261",
    "addr:housenumber":"shop 2 217",
    "addr:postcode":"2261",
    "addr:street":"The Entrance Rd",
    "iso:country":"AU",
    "sg:address":"Shop 2 217 The Entrance Rd",
    "sg:city":"The Entrance",
    "sg:classifiers":[
        {
            "category":"Fast Food",
            "type":"Food & Drink"
        }
    ],
    "sg:phone":"+61 2 4336 7111",
    "sg:postcode":"2261",
    "sg:province":"NSW",
    "sg:tags":[
        "away",
        "take"
    ],
    "wof:name":"Domino's Pizza",
    "wof:placetype":"venue"
},
  "geometry": {"coordinates":[151.49617000000001,-33.344681],"type":"Point"}
}