{
  "type": "Feature",
  "properties": {
    "addr:full":"71 Burdett St Hornsby NSW 2077",
    "addr:housenumber":"71",
    "addr:postcode":"2077",
    "addr:street":"Burdett St",
    "iso:country":"AU",
    "sg:address":"71 Burdett St",
    "sg:city":"Hornsby",
    "sg:classifiers":[
        {
            "category":"Building & Trades",
            "subcategory":"Landscaping Services",
            "type":"Services"
        }
    ],
    "sg:phone":"+61 439 983 445",
    "sg:postcode":"2077",
    "sg:province":"NSW",
    "sg:tags":[
        "stump",
        "tree",
        "felling",
        "removal"
    ],
    "wof:name":"Big Stump Removal",
    "wof:placetype":"venue"
},
  "geometry": {"coordinates":[151.10931396500001,-33.7035751343],"type":"Point"}
}