{
  "type": "Feature",
  "properties": {
    "addr:full":"Austin St Cue WA 6640",
    "addr:postcode":"6640",
    "addr:street":"Austin St",
    "iso:country":"AU",
    "sg:address":"Austin St",
    "sg:city":"Cue",
    "sg:classifiers":[
        {
            "category":"Autos & Motor Vehicles",
            "subcategory":"Fuel & Gas Station",
            "type":"Retail Goods"
        }
    ],
    "sg:phone":"+61 8 9963 1218",
    "sg:postcode":"6640",
    "sg:province":"WA",
    "wof:name":"Ampol",
    "wof:placetype":"venue"
},
  "geometry": {"coordinates":[117.898010254,-27.423614502],"type":"Point"}
}