{
  "type": "Feature",
  "properties": {
    "addr:full":"100 Yathong Rd Caringbah NSW 2229",
    "addr:housenumber":"100",
    "addr:postcode":"2229",
    "addr:street":"Yathong Rd",
    "iso:country":"AU",
    "sg:address":"100 Yathong Rd",
    "sg:city":"Caringbah",
    "sg:classifiers":[
        {
            "category":"Building & Trades",
            "subcategory":"Construction",
            "type":"Services"
        }
    ],
    "sg:phone":"+61 2 9525 1765",
    "sg:postcode":"2229",
    "sg:province":"NSW",
    "sg:tags":[
        "contractor"
    ],
    "wof:name":"Peter Tester Builder",
    "wof:placetype":"venue"
},
  "geometry": {"coordinates":[151.127685547,-34.0476303101],"type":"Point"}
}