{
  "type": "Feature",
  "properties": {
    "addr:full":"Shop 10b Ballantrae Drv St Andrews NSW 2566",
    "addr:housenumber":"10b",
    "addr:postcode":"2566",
    "addr:street":"Shop;Ballantrae Drv",
    "iso:country":"AU",
    "sg:address":"Shop 10b Ballantrae Drv",
    "sg:city":"St Andrews",
    "sg:classifiers":[
        {
            "category":"Retail",
            "subcategory":"Veterinary Services",
            "type":"Services"
        }
    ],
    "sg:phone":"+61 2 9820 2711",
    "sg:postcode":"2566",
    "sg:province":"NSW",
    "sg:tags":[
        "surgeon"
    ],
    "wof:name":"Ballantrae Drive Veterinary Clinic",
    "wof:placetype":"venue"
},
  "geometry": {"coordinates":[150.82797241200001,-34.0148391724],"type":"Point"}
}