{
  "type": "Feature",
  "properties": {
    "addr:full":"13a Davison St Maddington WA 6109",
    "addr:housenumber":"13a",
    "addr:postcode":"6109",
    "addr:street":"Davison St",
    "iso:country":"AU",
    "sg:address":"13a Davison St",
    "sg:city":"Maddington",
    "sg:classifiers":[
        {
            "category":"Banks & Credit Unions",
            "subcategory":"Bureau De Change",
            "type":"Services"
        }
    ],
    "sg:phone":"+61 8 9459 8010",
    "sg:postcode":"6109",
    "sg:province":"WA",
    "sg:tags":[
        "gas",
        "natural",
        "lp",
        "equipment"
    ],
    "wof:name":"Huntingdale Automotive Repairs",
    "wof:placetype":"venue"
},
  "geometry": {"coordinates":[115.986953735,-32.0433921814],"type":"Point"}
}