{
  "type": "Feature",
  "properties": {
    "iso:country":"AU",
    "sg:address":"21 Church St",
    "sg:city":"Parkes",
    "sg:classifiers":[
        {
            "category":"Health Services",
            "subcategory":"Dentist",
            "type":"Services"
        }
    ],
    "sg:phone":"+61 2 6862 1261",
    "sg:postcode":"2870",
    "sg:province":"NSW",
    "wof:name":"Richardson M B",
    "wof:placetype":"venue"
},
  "geometry": {"coordinates":[148.175522,-33.135593],"type":"Point"}
}