{
  "type": "Feature",
  "properties": {
    "addr:full":"507- 509 Pittwater Rd Brookvale NSW 2100",
    "addr:housenumber":"509",
    "addr:postcode":"2100",
    "addr:street":"Pittwater Rd",
    "iso:country":"AU",
    "sg:address":"507- 509 Pittwater Rd",
    "sg:city":"Brookvale",
    "sg:classifiers":[
        {
            "category":"Health Services",
            "subcategory":"Health Practitioner",
            "type":"Services"
        }
    ],
    "sg:phone":"+61 2 9938 4433",
    "sg:postcode":"2100",
    "sg:province":"NSW",
    "sg:tags":[
        "dietitian"
    ],
    "wof:name":"Jennie Lane APD",
    "wof:placetype":"venue"
},
  "geometry": {"coordinates":[151.271286011,-33.7638244629],"type":"Point"}
}