{
  "type": "Feature",
  "properties": {
    "iso:country":"AU",
    "sg:address":"Shop 7 Earlville Shopping Centre Mulgrave Rd",
    "sg:city":"Earlville",
    "sg:classifiers":[
        {
            "category":"Professional",
            "subcategory":"Art Services",
            "type":"Services"
        }
    ],
    "sg:phone":"+61 7 4033 2088",
    "sg:postcode":"4870",
    "sg:province":"QLD",
    "sg:tags":[
        "graphic",
        "designer"
    ],
    "wof:name":"Wide Open Edges",
    "wof:placetype":"venue"
},
  "geometry": {"coordinates":[145.73794555699999,-16.9455127716],"type":"Point"}
}