{
  "type": "Feature",
  "properties": {
    "addr:full":"2624 Wanneroo Rd Nowergup WA 6032",
    "addr:housenumber":"2624",
    "addr:postcode":"6032",
    "addr:street":"Wanneroo Rd",
    "iso:country":"AU",
    "sg:address":"2624 Wanneroo Rd",
    "sg:city":"Nowergup",
    "sg:classifiers":[
        {
            "category":"Autos & Motor Vehicles",
            "subcategory":"Auto Supplies",
            "type":"Retail Goods"
        }
    ],
    "sg:phone":"+61 8 9407 5042",
    "sg:postcode":"6032",
    "sg:province":"WA",
    "sg:tags":[
        "wheel",
        "four",
        "equipment",
        "drive",
        "accessory"
    ],
    "wof:name":"North Wanneroo Four Wheel Drive Centre",
    "wof:placetype":"venue"
},
  "geometry": {"coordinates":[115.740592956,-31.6654663086],"type":"Point"}
}