{
  "type": "Feature",
  "properties": {
    "addr:full":"76 Whitehorse Rd Balwyn VIC 3103",
    "addr:housenumber":"76",
    "addr:postcode":"3103",
    "addr:street":"Whitehorse Rd",
    "iso:country":"AU",
    "sg:address":"76 Whitehorse Rd",
    "sg:city":"Balwyn",
    "sg:classifiers":[
        {
            "category":"Health Services",
            "subcategory":"Dentist",
            "type":"Services"
        }
    ],
    "sg:phone":"+61 3 9817 2827",
    "sg:postcode":"3103",
    "sg:province":"VIC",
    "wof:name":"A.R. Solomon & S.Rostkier",
    "wof:placetype":"venue"
},
  "geometry": {"coordinates":[145.065750122,-37.8110771179],"type":"Point"}
}