{
  "type": "Feature",
  "properties": {
    "iso:country":"AU",
    "sg:address":"2086 Toodyay Rd",
    "sg:city":"Gidgegannup",
    "sg:classifiers":[
        {
            "category":"Home & Garden",
            "subcategory":"Building Materials",
            "type":"Retail Goods"
        }
    ],
    "sg:phone":"+61 8 9578 3220",
    "sg:postcode":"6083",
    "sg:province":"WA",
    "sg:tags":[
        "roofing"
    ],
    "wof:name":"Conquest Metal Roofing Pty Ltd",
    "wof:placetype":"venue"
},
  "geometry": {"coordinates":[116.196411133,-31.7931880951],"type":"Point"}
}