{
  "type": "Feature",
  "properties": {
    "addr:full":"7 Dale St Fairfield NSW 2165",
    "addr:housenumber":"7",
    "addr:postcode":"2165",
    "addr:street":"Dale St",
    "iso:country":"AU",
    "sg:address":"7 Dale St",
    "sg:city":"Fairfield",
    "sg:classifiers":[
        {
            "category":"Personal",
            "subcategory":"Beauty Salon",
            "type":"Services"
        }
    ],
    "sg:phone":"+61 2 9724 9432",
    "sg:postcode":"2165",
    "sg:province":"NSW",
    "sg:tags":[
        "hairdresser"
    ],
    "wof:name":"Precious Hair & Beauty",
    "wof:placetype":"venue"
},
  "geometry": {"coordinates":[150.957595825,-33.8726196289],"type":"Point"}
}