{
  "type": "Feature",
  "properties": {
    "addr:full":"PO Box 150 Narrabeen NSW 2101",
    "addr:postcode":"2101",
    "iso:country":"AU",
    "sg:address":"PO Box 150",
    "sg:city":"Narrabeen",
    "sg:classifiers":[
        {
            "category":"Real Estate",
            "subcategory":"Real Estate Agent",
            "type":"Services"
        }
    ],
    "sg:phone":"+61 2 9997 4555",
    "sg:postcode":"2101",
    "sg:province":"NSW",
    "wof:name":"Ray White Real Estate",
    "wof:placetype":"venue"
},
  "geometry": {"coordinates":[151.298416,-33.720211],"type":"Point"}
}