{
  "type": "Feature",
  "properties": {
    "addr:full":"Unit 4 2 Booran Drv Woodridge QLD 4114",
    "addr:housenumber":"2",
    "addr:postcode":"4114",
    "addr:street":"Booran Drv",
    "iso:country":"AU",
    "sg:address":"Unit 4 2 Booran Drv",
    "sg:city":"Woodridge",
    "sg:classifiers":[
        {
            "category":"Banks & Credit Unions",
            "subcategory":"Financial Services",
            "type":"Services"
        }
    ],
    "sg:phone":"+61 7 3387 8222",
    "sg:postcode":"4114",
    "sg:province":"QLD",
    "sg:tags":[
        "finance",
        "motor",
        "vehicle"
    ],
    "wof:name":"Aussie Bike Auto & Boat Loans",
    "wof:placetype":"venue"
},
  "geometry": {"coordinates":[153.11581420900001,-27.6232681274],"type":"Point"}
}