{
  "type": "Feature",
  "properties": {
    "addr:full":"1414 Pittwater Rd North Narrabeen NSW 2101",
    "addr:postcode":"1414;2101",
    "addr:street":"Pittwater Rd",
    "iso:country":"AU",
    "sg:address":"1414 Pittwater Rd",
    "sg:city":"North Narrabeen",
    "sg:classifiers":[
        {
            "category":"Wholesale",
            "subcategory":"Auto Parts",
            "type":"Manufacturing & Wholesale Goods"
        }
    ],
    "sg:phone":"+61 2 9999 0537",
    "sg:postcode":"2101",
    "sg:province":"NSW",
    "sg:tags":[
        "recyclers"
    ],
    "wof:name":"Northern Beaches Spares",
    "wof:placetype":"venue"
},
  "geometry": {"coordinates":[151.29705799999999,-33.712887],"type":"Point"}
}