{
  "type": "Feature",
  "properties": {
    "addr:full":"37 Brisbane St Ipswich QLD 4305",
    "addr:housenumber":"37",
    "addr:postcode":"4305",
    "addr:street":"Brisbane St",
    "iso:country":"AU",
    "sg:address":"37 Brisbane St",
    "sg:city":"Ipswich",
    "sg:classifiers":[
        {
            "category":"Cafe",
            "type":"Food & Drink"
        }
    ],
    "sg:phone":"+61 7 3281 0400",
    "sg:postcode":"4305",
    "sg:province":"QLD",
    "wof:name":"Central Cafe & Bake House",
    "wof:placetype":"venue"
},
  "geometry": {"coordinates":[152.76351928700001,-27.6150054932],"type":"Point"}
}