{
  "type": "Feature",
  "properties": {
    "iso:country":"AU",
    "sg:address":"Suite 11, 15 - 17 Ocean St",
    "sg:city":"Maroochydore",
    "sg:classifiers":[
        {
            "category":"Real Estate",
            "subcategory":"Real Estate Agent",
            "type":"Services"
        }
    ],
    "sg:phone":"+61 7 5479 1400",
    "sg:postcode":"4558",
    "sg:province":"QLD",
    "wof:name":"Real Way Property Consultants",
    "wof:placetype":"venue"
},
  "geometry": {"coordinates":[153.090118408,-26.6523723602],"type":"Point"}
}