{
  "type": "Feature",
  "properties": {
    "addr:full":"Unit 1 7 Orchard St Brookvale NSW 2100",
    "addr:housenumber":"7",
    "addr:postcode":"2100",
    "addr:street":"Orchard St",
    "iso:country":"AU",
    "sg:address":"Unit 1 7 Orchard St",
    "sg:city":"Brookvale",
    "sg:classifiers":[
        {
            "category":"Communications",
            "subcategory":"Film & Video Production",
            "type":"Services"
        }
    ],
    "sg:phone":"+61 2 9907 1977",
    "sg:postcode":"2100",
    "sg:province":"NSW",
    "sg:tags":[
        "fan",
        "blower"
    ],
    "wof:name":"Lightpower Pty Ltd",
    "wof:placetype":"venue"
},
  "geometry": {"coordinates":[151.27206420900001,-33.7651138306],"type":"Point"}
}