{
  "type": "Feature",
  "properties": {
    "iso:country":"AU",
    "sg:address":"27 Talbragar St",
    "sg:city":"Dubbo",
    "sg:classifiers":[
        {
            "category":"Shopping",
            "subcategory":"Jewelry",
            "type":"Retail Goods"
        }
    ],
    "sg:phone":"+61 2 6882 3173",
    "sg:postcode":"2830",
    "sg:province":"NSW",
    "sg:tags":[
        "jeweller"
    ],
    "wof:name":"Aurora Accessories & Designs",
    "wof:placetype":"venue"
},
  "geometry": {"coordinates":[148.60151672399999,-32.2468147278],"type":"Point"}
}