{
  "type": "Feature",
  "properties": {
    "addr:full":"34A Blackwall Rd Woy Woy NSW 2256",
    "addr:housenumber":"34a",
    "addr:postcode":"2256",
    "addr:street":"Blackwall Rd",
    "iso:country":"AU",
    "sg:address":"34A Blackwall Rd",
    "sg:city":"Woy Woy",
    "sg:classifiers":[
        {
            "category":"Food & Beverages",
            "subcategory":"Bakery",
            "type":"Retail Goods"
        }
    ],
    "sg:phone":"+61 2 4341 7040",
    "sg:postcode":"2256",
    "sg:province":"NSW",
    "sg:tags":[
        "cake",
        "shop",
        "pastry"
    ],
    "wof:name":"Cheesecake Shop The",
    "wof:placetype":"venue"
},
  "geometry": {"coordinates":[151.32484435999999,-33.4856262207],"type":"Point"}
}