{
  "type": "Feature",
  "properties": {
    "addr:full":"U2/ 7 Carson Rd Malaga WA 6090",
    "addr:housenumber":"7",
    "addr:postcode":"6090",
    "addr:street":"U2 /;Carson Rd",
    "iso:country":"AU",
    "sg:address":"U2/ 7 Carson Rd",
    "sg:city":"Malaga",
    "sg:classifiers":[
        {
            "category":"Retail",
            "subcategory":"Auto Rental",
            "type":"Services"
        }
    ],
    "sg:phone":"+61 8 9249 9443",
    "sg:postcode":"6090",
    "sg:province":"WA",
    "sg:tags":[
        "car",
        "hire",
        "minibus"
    ],
    "wof:name":"Join Gold",
    "wof:placetype":"venue"
},
  "geometry": {"coordinates":[115.88008117699999,-31.8552799225],"type":"Point"}
}