{
  "type": "Feature",
  "properties": {
    "addr:full":"2 Breakwater Rd Thomson VIC 3219",
    "addr:housenumber":"2",
    "addr:postcode":"3219",
    "addr:street":"Breakwater Rd",
    "iso:country":"AU",
    "sg:address":"2 Breakwater Rd",
    "sg:city":"Thomson",
    "sg:classifiers":[
        {
            "category":"Food & Beverages",
            "subcategory":"Groceries & Convenience Stores",
            "type":"Retail Goods"
        }
    ],
    "sg:phone":"+61 3 5224 1038",
    "sg:postcode":"3219",
    "sg:province":"VIC",
    "wof:name":"Food Shop The",
    "wof:placetype":"venue"
},
  "geometry": {"coordinates":[144.37274169899999,-38.1637878418],"type":"Point"}
}