{
  "type": "Feature",
  "properties": {
    "iso:country":"AU",
    "sg:address":"652A High St",
    "sg:city":"Kew East",
    "sg:classifiers":[
        {
            "category":"Professional",
            "subcategory":"Business Services",
            "type":"Services"
        }
    ],
    "sg:phone":"+61 3 9859 1862",
    "sg:postcode":"3102",
    "sg:province":"VIC",
    "sg:tags":[
        "drafting"
    ],
    "wof:name":"Flexsteel Drafting Services",
    "wof:placetype":"venue"
},
  "geometry": {"coordinates":[145.051803589,-37.7989273071],"type":"Point"}
}