{
  "type": "Feature",
  "properties": {
    "addr:full":"97- 99 Corinna St Woden ACT 2606",
    "addr:housenumber":"99",
    "addr:postcode":"2606",
    "addr:street":"Corinna St",
    "iso:country":"AU",
    "sg:address":"97- 99 Corinna St",
    "sg:city":"Woden",
    "sg:classifiers":[
        {
            "category":"Fast Food",
            "type":"Food & Drink"
        }
    ],
    "sg:phone":"+61 2 6260 3016",
    "sg:postcode":"2606",
    "sg:province":"ACT",
    "sg:tags":[
        "away",
        "take"
    ],
    "wof:name":"Turkish Pide House Restaurant",
    "wof:placetype":"venue"
},
  "geometry": {"coordinates":[149.08883667000001,-35.3476791382],"type":"Point"}
}