{
  "type": "Feature",
  "properties": {
    "iso:country":"AU",
    "sg:address":"39 Mandilla Pde",
    "sg:city":"Malaga",
    "sg:classifiers":[
        {
            "category":"Professional",
            "subcategory":"Detective & Security Services",
            "type":"Services"
        }
    ],
    "sg:phone":"+61 8 9375 1722",
    "sg:postcode":"6090",
    "sg:province":"WA",
    "sg:tags":[
        "domestic",
        "alarm",
        "commercial",
        "burglar"
    ],
    "wof:name":"All Ness 5000 Sales & Service",
    "wof:placetype":"venue"
},
  "geometry": {"coordinates":[115.91414642300001,-31.8466796875],"type":"Point"}
}