{
  "type": "Feature",
  "properties": {
    "addr:full":"172 Franklin St Melbourne VIC 3000",
    "addr:housenumber":"172",
    "addr:postcode":"3000",
    "addr:street":"Franklin St",
    "iso:country":"AU",
    "sg:address":"172 Franklin St",
    "sg:city":"Melbourne",
    "sg:classifiers":[
        {
            "category":"Building & Trades",
            "subcategory":"Pest Control",
            "type":"Services"
        }
    ],
    "sg:phone":"+61 3 9326 4599",
    "sg:postcode":"3000",
    "sg:province":"VIC",
    "sg:tags":[
        "wholesaler",
        "mfrs",
        "walking",
        "umbrella",
        "stick"
    ],
    "wof:name":"Cool & Unique Umbrellas",
    "wof:placetype":"venue"
},
  "geometry": {"coordinates":[144.956542969,-37.8090362549],"type":"Point"}
}