{
  "type": "Feature",
  "properties": {
    "iso:country":"AU",
    "sg:address":"59 Nelson Ave",
    "sg:city":"Belmore",
    "sg:classifiers":[
        {
            "category":"Personal",
            "subcategory":"Beauty Salon",
            "type":"Services"
        }
    ],
    "sg:phone":"+61 2 9758 4049",
    "sg:postcode":"2192",
    "sg:province":"NSW",
    "wof:name":"Zina's Nails & Waxing",
    "wof:placetype":"venue"
},
  "geometry": {"coordinates":[151.09376499999999,-33.929642],"type":"Point"}
}