{
  "type": "Feature",
  "properties": {
    "addr:full":"77 St George's Tce Perth WA 6000",
    "addr:housenumber":"77",
    "addr:postcode":"6000",
    "addr:street":"St George'S Tce",
    "iso:country":"AU",
    "sg:address":"77 St George's Tce",
    "sg:city":"Perth",
    "sg:classifiers":[
        {
            "category":"Airline",
            "type":"Transportation"
        }
    ],
    "sg:phone":"+61 8 9425 5333",
    "sg:postcode":"6000",
    "sg:province":"WA",
    "sg:tags":[
        "agent"
    ],
    "wof:name":"British Airways",
    "wof:placetype":"venue"
},
  "geometry": {"coordinates":[115.852546692,-31.9546794891],"type":"Point"}
}