{
  "type": "Feature",
  "properties": {
    "addr:full":"130 Lower York St Albany WA 6330",
    "addr:housenumber":"130",
    "addr:postcode":"6330",
    "addr:street":"Lower York St",
    "iso:country":"AU",
    "sg:address":"130 Lower York St",
    "sg:city":"Albany",
    "sg:classifiers":[
        {
            "category":"Shopping",
            "subcategory":"Shoes",
            "type":"Retail Goods"
        }
    ],
    "sg:phone":"+61 8 9841 1116",
    "sg:postcode":"6330",
    "sg:province":"WA",
    "sg:tags":[
        "footwear"
    ],
    "wof:name":"Mainstreet Shoes & Bags",
    "wof:placetype":"venue"
},
  "geometry": {"coordinates":[117.94029998800001,-34.8903007507],"type":"Point"}
}