{
  "type": "Feature",
  "properties": {
    "addr:full":"276 Burwood Hwy Burwood VIC 3125",
    "addr:housenumber":"276",
    "addr:postcode":"3125",
    "addr:street":"Burwood Hwy",
    "iso:country":"AU",
    "sg:address":"276 Burwood Hwy",
    "sg:city":"Burwood",
    "sg:classifiers":[
        {
            "category":"Health Services",
            "subcategory":"Dentist",
            "type":"Services"
        }
    ],
    "sg:phone":"+61 3 9808 3386",
    "sg:postcode":"3125",
    "sg:province":"VIC",
    "wof:name":"Para, Dr P.",
    "wof:placetype":"venue"
},
  "geometry": {"coordinates":[145.15802001899999,-37.8537254333],"type":"Point"}
}