{
  "type": "Feature",
  "properties": {
    "iso:country":"AU",
    "sg:address":"PO Box 5222",
    "sg:city":"Eagleby",
    "sg:classifiers":[
        {
            "category":"Building & Trades",
            "subcategory":"Pest Control",
            "type":"Services"
        }
    ],
    "sg:phone":"+61 423 017 744",
    "sg:postcode":"4207",
    "sg:province":"QLD",
    "wof:name":"Flies Away",
    "wof:placetype":"venue"
},
  "geometry": {"coordinates":[153.212615967,-27.7024803162],"type":"Point"}
}