{
  "type": "Feature",
  "properties": {
    "iso:country":"AU",
    "sg:address":"29A Main St",
    "sg:city":"Pialba",
    "sg:classifiers":[
        {
            "category":"Professional",
            "subcategory":"Accounting & Tax Preparation",
            "type":"Services"
        }
    ],
    "sg:phone":"+61 7 4124 4127",
    "sg:postcode":"4655",
    "sg:province":"QLD",
    "sg:tags":[
        "consultant",
        "taxation"
    ],
    "wof:name":"ITP The Income Tax Professionals",
    "wof:placetype":"venue"
},
  "geometry": {"coordinates":[152.837357,-25.29216],"type":"Point"}
}