{
  "type": "Feature",
  "properties": {
    "addr:full":"193 The Entrance Rd The Entrance NSW 2261",
    "addr:housenumber":"193",
    "addr:postcode":"2261",
    "addr:street":"The Entrance Rd",
    "iso:country":"AU",
    "sg:address":"193 The Entrance Rd",
    "sg:city":"The Entrance",
    "sg:classifiers":[
        {
            "category":"Personal",
            "subcategory":"Piercing",
            "type":"Services"
        }
    ],
    "sg:phone":"+61 2 4334 4119",
    "sg:postcode":"2261",
    "sg:province":"NSW",
    "sg:tags":[
        "body",
        "ear"
    ],
    "wof:name":"Accent On Beauty",
    "wof:placetype":"venue"
},
  "geometry": {"coordinates":[151.49603300000001,-33.3437],"type":"Point"}
}