{
  "type": "Feature",
  "properties": {
    "addr:full":"79 Nicholson St Bairnsdale VIC 3875",
    "addr:housenumber":"79",
    "addr:postcode":"3875",
    "addr:street":"Nicholson St",
    "iso:country":"AU",
    "sg:address":"79 Nicholson St",
    "sg:city":"Bairnsdale",
    "sg:classifiers":[
        {
            "category":"Shopping",
            "subcategory":"Clothing, Apparel, & Fashions",
            "type":"Retail Goods"
        }
    ],
    "sg:phone":"+61 3 5153 0311",
    "sg:postcode":"3875",
    "sg:province":"VIC",
    "sg:tags":[
        "lady",
        "wear"
    ],
    "wof:name":"Nicholson Place",
    "wof:placetype":"venue"
},
  "geometry": {"coordinates":[147.62989807100001,-37.8250312805],"type":"Point"}
}