{
  "type": "Feature",
  "properties": {
    "iso:country":"AU",
    "sg:address":"70 Fontainebleau St",
    "sg:city":"Sans Souci",
    "sg:classifiers":[
        {
            "category":"Personal",
            "subcategory":"Beauty Salon",
            "type":"Services"
        }
    ],
    "sg:phone":"+61 2 9529 7699",
    "sg:postcode":"2219",
    "sg:province":"NSW",
    "sg:tags":[
        "hairdresser"
    ],
    "wof:name":"Bubbles Haircutters",
    "wof:placetype":"venue"
},
  "geometry": {"coordinates":[151.134583,-34.002144],"type":"Point"}
}