{
  "type": "Feature",
  "properties": {
    "addr:full":"Naring Rd Numurkah VIC 3636",
    "addr:postcode":"3636",
    "addr:street":"Naring Rd",
    "iso:country":"AU",
    "sg:address":"Naring Rd",
    "sg:city":"Numurkah",
    "sg:classifiers":[
        {
            "category":"Commercial Area",
            "type":"Public Place"
        }
    ],
    "sg:phone":"+61 3 5862 2291",
    "sg:postcode":"3636",
    "sg:province":"VIC",
    "sg:tags":[
        "heavy",
        "carrier"
    ],
    "wof:name":"Graeme Sutton Transport Pty Ltd",
    "wof:placetype":"venue"
},
  "geometry": {"coordinates":[145.44099426299999,-36.0690116882],"type":"Point"}
}