{
  "type": "Feature",
  "properties": {
    "iso:country":"AU",
    "sg:address":"57 McLarty St",
    "sg:city":"Waroona",
    "sg:classifiers":[
        {
            "category":"Utilities",
            "subcategory":"Electric",
            "type":"Services"
        }
    ],
    "sg:phone":"+61 8 9733 1200",
    "sg:postcode":"6215",
    "sg:province":"WA",
    "sg:tags":[
        "electrical",
        "contractor"
    ],
    "wof:name":"Keith Landwehr & Co",
    "wof:placetype":"venue"
},
  "geometry": {"coordinates":[115.929031,-32.854908],"type":"Point"}
}