{
  "type": "Feature",
  "properties": {
    "addr:full":"1267 The Horsley Drv Wetherill Park NSW 2164",
    "addr:housenumber":"1267",
    "addr:postcode":"2164",
    "addr:street":"The Horsley Drv",
    "iso:country":"AU",
    "sg:address":"1267 The Horsley Drv",
    "sg:city":"Wetherill Park",
    "sg:classifiers":[
        {
            "category":"Shopping",
            "subcategory":"Clothing, Apparel, & Fashions",
            "type":"Retail Goods"
        }
    ],
    "sg:phone":"+61 2 9756 4245",
    "sg:postcode":"2164",
    "sg:province":"NSW",
    "sg:tags":[
        "hire",
        "men's",
        "wear",
        "formal"
    ],
    "wof:name":"Classics Formal Wear",
    "wof:placetype":"venue"
},
  "geometry": {"coordinates":[150.89149475100001,-33.8522109985],"type":"Point"}
}