{
  "type": "Feature",
  "properties": {
    "addr:full":"83 Ormond Rd East Geelong VIC 3219",
    "addr:housenumber":"83",
    "addr:postcode":"3219",
    "addr:street":"Ormond Rd",
    "iso:country":"AU",
    "sg:address":"83 Ormond Rd",
    "sg:city":"East Geelong",
    "sg:classifiers":[
        {
            "category":"Personal",
            "subcategory":"Massage",
            "type":"Services"
        }
    ],
    "sg:phone":"+61 3 5222 6449",
    "sg:postcode":"3219",
    "sg:province":"VIC",
    "sg:tags":[
        "therapy"
    ],
    "wof:name":"Studio On Ormond",
    "wof:placetype":"venue"
},
  "geometry": {"coordinates":[144.376785278,-38.1601715088],"type":"Point"}
}