{
  "type": "Feature",
  "properties": {
    "addr:full":"16 Hoddle St Abbotsford VIC 3067",
    "addr:housenumber":"16",
    "addr:postcode":"3067",
    "addr:street":"Hoddle St",
    "iso:country":"AU",
    "sg:address":"16 Hoddle St",
    "sg:city":"Abbotsford",
    "sg:classifiers":[
        {
            "category":"Education",
            "subcategory":"Special Training",
            "type":"Public Place"
        }
    ],
    "sg:phone":"+61 3 9416 3274",
    "sg:postcode":"3067",
    "sg:province":"VIC",
    "sg:tags":[
        "development"
    ],
    "wof:name":"Khuti Foundation The",
    "wof:placetype":"venue"
},
  "geometry": {"coordinates":[144.991744995,-37.808807373],"type":"Point"}
}