{
  "type": "Feature",
  "properties": {
    "addr:full":"284 Centre Rd Bentleigh VIC 3204",
    "addr:housenumber":"284",
    "addr:postcode":"3204",
    "addr:street":"Centre Rd",
    "iso:country":"AU",
    "sg:address":"284 Centre Rd",
    "sg:city":"Bentleigh",
    "sg:classifiers":[
        {
            "category":"Food & Beverages",
            "subcategory":"Fruits & Vegetables",
            "type":"Retail Goods"
        }
    ],
    "sg:phone":"+61 3 9557 9455",
    "sg:postcode":"3204",
    "sg:province":"VIC",
    "sg:tags":[
        "greengrocer",
        "fruiterer"
    ],
    "wof:name":"Extra Fresh Vegies & Fruit",
    "wof:placetype":"venue"
},
  "geometry": {"coordinates":[145.031982,-37.917759],"type":"Point"}
}