{
  "type": "Feature",
  "properties": {
    "addr:full":"7/- 84 Riverside Rd Chipping Norton NSW 2170",
    "addr:housenumber":"/ 84",
    "addr:postcode":"2170",
    "addr:street":"Riverside Rd",
    "iso:country":"AU",
    "sg:address":"7/- 84 Riverside Rd",
    "sg:city":"Chipping Norton",
    "sg:classifiers":[
        {
            "category":"Wholesale",
            "subcategory":"Machinery & Supplies",
            "type":"Manufacturing & Wholesale Goods"
        }
    ],
    "sg:phone":"+61 2 9755 2677",
    "sg:postcode":"2170",
    "sg:province":"NSW",
    "sg:tags":[
        "engineer"
    ],
    "wof:name":"Bolt-On Fasteners & Engg' Supplies Pty Ltd",
    "wof:placetype":"venue"
},
  "geometry": {"coordinates":[150.96810913100001,-33.9150505066],"type":"Point"}
}