{
  "type": "Feature",
  "properties": {
    "addr:full":"PO Box 645 Penrith NSW 2751",
    "addr:postcode":"2751",
    "iso:country":"AU",
    "sg:address":"PO Box 645",
    "sg:city":"Penrith",
    "sg:classifiers":[
        {
            "category":"Retail",
            "subcategory":"Event Space",
            "type":"Services"
        }
    ],
    "sg:phone":"+61 2 4731 4333",
    "sg:postcode":"2751",
    "sg:province":"NSW",
    "sg:tags":[
        "venue",
        "reception",
        "wedding"
    ],
    "wof:name":"Penrith RSL Club",
    "wof:placetype":"venue"
},
  "geometry": {"coordinates":[150.69601440400001,-33.7440681458],"type":"Point"}
}