{
  "type": "Feature",
  "properties": {
    "iso:country":"AU",
    "sg:address":"210 Oxford St",
    "sg:city":"Paddington",
    "sg:classifiers":[
        {
            "category":"Health Services",
            "subcategory":"Health Practitioner",
            "type":"Services"
        }
    ],
    "sg:phone":"+61 2 9360 1634",
    "sg:postcode":"2021",
    "sg:province":"NSW",
    "sg:tags":[
        "herbalist"
    ],
    "wof:name":"Lambert-Smith Rosalind",
    "wof:placetype":"venue"
},
  "geometry": {"coordinates":[151.22523498499999,-33.8847541809],"type":"Point"}
}