{
  "type": "Feature",
  "properties": {
    "addr:full":"98 Bloomfield St Cleveland QLD 4163",
    "addr:housenumber":"98",
    "addr:postcode":"4163",
    "addr:street":"Bloomfield St",
    "iso:country":"AU",
    "sg:address":"98 Bloomfield St",
    "sg:city":"Cleveland",
    "sg:classifiers":[
        {
            "category":"Personal",
            "type":"Services"
        }
    ],
    "sg:phone":"+61 7 3821 3370",
    "sg:postcode":"4163",
    "sg:province":"QLD",
    "sg:tags":[
        "gift"
    ],
    "wof:name":"Redlands Florist",
    "wof:placetype":"venue"
},
  "geometry": {"coordinates":[153.26719665499999,-27.5273132324],"type":"Point"}
}