{
  "type": "Feature",
  "properties": {
    "addr:full":"16 Bowen St Ipswich QLD 4305",
    "addr:housenumber":"16",
    "addr:postcode":"4305",
    "addr:street":"Bowen St",
    "iso:country":"AU",
    "sg:address":"16 Bowen St",
    "sg:city":"Ipswich",
    "sg:classifiers":[
        {
            "category":"Professional",
            "subcategory":"Art Services",
            "type":"Services"
        }
    ],
    "sg:phone":"+61 412 873 993",
    "sg:postcode":"4305",
    "sg:province":"QLD",
    "sg:tags":[
        "interior",
        "decorator"
    ],
    "wof:name":"Decor Solutions Qld",
    "wof:placetype":"venue"
},
  "geometry": {"coordinates":[152.75544738799999,-27.6040382385],"type":"Point"}
}