{
  "type": "Feature",
  "properties": {
    "addr:full":"400 Cranbourne Rd Langwarrin VIC 3910",
    "addr:housenumber":"400",
    "addr:postcode":"3910",
    "addr:street":"Cranbourne Rd",
    "iso:country":"AU",
    "sg:address":"400 Cranbourne Rd",
    "sg:city":"Langwarrin",
    "sg:classifiers":[
        {
            "category":"Health Services",
            "subcategory":"Medical Lab",
            "type":"Services"
        }
    ],
    "sg:phone":"+61 3 8790 0311",
    "sg:postcode":"3910",
    "sg:province":"VIC",
    "sg:tags":[
        "laboratory",
        "dental"
    ],
    "wof:name":"Complete Othodontic Lab",
    "wof:placetype":"venue"
},
  "geometry": {"coordinates":[145.21104431099999,-38.1420898438],"type":"Point"}
}