{
  "type": "Feature",
  "properties": {
    "iso:country":"AU",
    "sg:address":"PO Box 76",
    "sg:city":"Narellan",
    "sg:classifiers":[
        {
            "category":"Building & Trades",
            "subcategory":"Plumbing",
            "type":"Services"
        }
    ],
    "sg:phone":"+61 2 4625 4094",
    "sg:postcode":"2567",
    "sg:province":"NSW",
    "sg:tags":[
        "plumber",
        "gasfitters"
    ],
    "wof:name":"A1 Competitive Plumbing Services",
    "wof:placetype":"venue"
},
  "geometry": {"coordinates":[150.73526000999999,-34.0400390625],"type":"Point"}
}