{
  "type": "Feature",
  "properties": {
    "addr:full":"9 Michael Crt Berwick VIC 3806",
    "addr:housenumber":"9",
    "addr:postcode":"3806",
    "addr:street":"Michael Crt",
    "iso:country":"AU",
    "sg:address":"9 Michael Crt",
    "sg:city":"Berwick",
    "sg:classifiers":[
        {
            "category":"Wholesale",
            "subcategory":"Machinery & Supplies",
            "type":"Manufacturing & Wholesale Goods"
        }
    ],
    "sg:phone":"+61 409 166 835",
    "sg:postcode":"3806",
    "sg:province":"VIC",
    "sg:tags":[
        "equipment",
        "hydraulic"
    ],
    "wof:name":"Berwick Machinery Services",
    "wof:placetype":"venue"
},
  "geometry": {"coordinates":[145.36080932600001,-38.0274276733],"type":"Point"}
}