{
  "type": "Feature",
  "properties": {
    "addr:full":"99 Mount St North Sydney NSW 2060",
    "addr:housenumber":"99",
    "addr:postcode":"2060",
    "addr:street":"Mount St",
    "iso:country":"AU",
    "sg:address":"99 Mount St",
    "sg:city":"North Sydney",
    "sg:classifiers":[
        {
            "category":"Fast Food",
            "type":"Food & Drink"
        }
    ],
    "sg:phone":"+61 2 9923 1886",
    "sg:postcode":"2060",
    "sg:province":"NSW",
    "sg:tags":[
        "away",
        "take"
    ],
    "wof:name":"Malacca Straits Thai",
    "wof:placetype":"venue"
},
  "geometry": {"coordinates":[151.208618164,-33.8391838074],"type":"Point"}
}