{
  "type": "Feature",
  "properties": {
    "addr:full":"3 Nelson Rd Box Hill NSW 2765",
    "addr:housenumber":"3",
    "addr:postcode":"2765",
    "addr:street":"Nelson Rd",
    "iso:country":"AU",
    "sg:address":"3 Nelson Rd",
    "sg:city":"Box Hill",
    "sg:classifiers":[
        {
            "category":"Home & Garden",
            "subcategory":"Building Materials",
            "type":"Retail Goods"
        }
    ],
    "sg:phone":"+61 2 9679 1218",
    "sg:postcode":"2765",
    "sg:province":"NSW",
    "sg:tags":[
        "gate"
    ],
    "wof:name":"T Z Fencing",
    "wof:placetype":"venue"
},
  "geometry": {"coordinates":[150.90164184599999,-33.6667823792],"type":"Point"}
}