{
  "type": "Feature",
  "properties": {
    "iso:country":"AU",
    "sg:address":"1 Richard St",
    "sg:city":"Kyabram",
    "sg:classifiers":[
        {
            "category":"Social Services",
            "subcategory":"Child Care",
            "type":"Services"
        }
    ],
    "sg:phone":"+61 3 5852 1808",
    "sg:postcode":"3620",
    "sg:province":"VIC",
    "sg:tags":[
        "support",
        "health"
    ],
    "wof:name":"Maternal & Child Health Centres",
    "wof:placetype":"venue"
},
  "geometry": {"coordinates":[145.05055236800001,-36.3148002625],"type":"Point"}
}