{
  "type": "Feature",
  "properties": {
    "iso:country":"AU",
    "sg:address":"63 Lever St",
    "sg:city":"Albion",
    "sg:classifiers":[
        {
            "category":"Personal",
            "type":"Services"
        }
    ],
    "sg:phone":"+61 7 3862 3377",
    "sg:postcode":"4010",
    "sg:province":"QLD",
    "sg:tags":[
        "wallpapering",
        "wallcovering"
    ],
    "wof:name":"Cox Ray Painting Pty Ltd",
    "wof:placetype":"venue"
},
  "geometry": {"coordinates":[153.04548645,-27.4306240082],"type":"Point"}
}