{
  "type": "Feature",
  "properties": {
    "iso:country":"AU",
    "sg:address":"31 Kallista-Emerald Rd",
    "sg:city":"The Patch",
    "sg:classifiers":[
        {
            "category":"Farming",
            "subcategory":"Nursery",
            "type":"Manufacturing & Wholesale Goods"
        }
    ],
    "sg:phone":"+61 3 9752 0762",
    "sg:postcode":"3792",
    "sg:province":"VIC",
    "wof:name":"Knoxbrook Nursery",
    "wof:placetype":"venue"
},
  "geometry": {"coordinates":[145.40841674800001,-37.8977661133],"type":"Point"}
}