{
  "type": "Feature",
  "properties": {
    "addr:full":"6 Bruce St Preston VIC 3072",
    "addr:housenumber":"6",
    "addr:postcode":"3072",
    "addr:street":"Bruce St",
    "iso:country":"AU",
    "sg:address":"6 Bruce St",
    "sg:city":"Preston",
    "sg:classifiers":[
        {
            "category":"Retail",
            "subcategory":"Funeral Services",
            "type":"Services"
        }
    ],
    "sg:phone":"+61 3 9480 1477",
    "sg:postcode":"3072",
    "sg:province":"VIC",
    "sg:tags":[
        "director"
    ],
    "wof:name":"Amalgamated Funeral Services",
    "wof:placetype":"venue"
},
  "geometry": {"coordinates":[145.002487183,-37.7423324585],"type":"Point"}
}