{
  "type": "Feature",
  "properties": {
    "addr:full":"Kiosk 7, Sunnybank Plaza Shopping Centre, Cnr Mains Rd & McCullogh St Sunnybank QLD 4109",
    "addr:housenumber":"7",
    "addr:postcode":"4109",
    "addr:street":"Sunnybank Plaza;Cnr Mains Rd & Mccullogh St",
    "iso:country":"AU",
    "sg:address":"Kiosk 7, Sunnybank Plaza Shopping Centre, Cnr Mains Rd & McCullogh St",
    "sg:city":"Sunnybank",
    "sg:classifiers":[
        {
            "category":"Banks & Credit Unions",
            "subcategory":"Bureau De Change",
            "type":"Services"
        }
    ],
    "sg:phone":"+61 7 3375 8699",
    "sg:postcode":"4109",
    "sg:province":"QLD",
    "sg:tags":[
        "currency",
        "exchange",
        "foreign"
    ],
    "wof:name":"UAE Exchange Australia Pty Ltd",
    "wof:placetype":"venue"
},
  "geometry": {"coordinates":[153.06275939899999,-27.5783214569],"type":"Point"}
}