{
  "type": "Feature",
  "properties": {
    "iso:country":"AU",
    "sg:address":"56 Regulus St",
    "sg:city":"Erskine Park",
    "sg:classifiers":[
        {
            "category":"Professional",
            "type":"Services"
        }
    ],
    "sg:phone":"+61 2 9834 2766",
    "sg:postcode":"2759",
    "sg:province":"NSW",
    "sg:tags":[
        "transport"
    ],
    "wof:name":"Nolans Transport",
    "wof:placetype":"venue"
},
  "geometry": {"coordinates":[150.795211792,-33.8088951111],"type":"Point"}
}