{
  "type": "Feature",
  "properties": {
    "addr:full":"35 Lucas Ave Moorebank NSW 2170",
    "addr:housenumber":"35",
    "addr:postcode":"2170",
    "addr:street":"Lucas Ave",
    "iso:country":"AU",
    "sg:address":"35 Lucas Ave",
    "sg:city":"Moorebank",
    "sg:classifiers":[
        {
            "category":"Education",
            "subcategory":"Special Training",
            "type":"Public Place"
        }
    ],
    "sg:phone":"+61 417 265 010",
    "sg:postcode":"2170",
    "sg:province":"NSW",
    "sg:tags":[
        "tuition-educational"
    ],
    "wof:name":"Success Coaching College",
    "wof:placetype":"venue"
},
  "geometry": {"coordinates":[150.952636719,-33.9300041199],"type":"Point"}
}