{
  "type": "Feature",
  "properties": {
    "iso:country":"AU",
    "sg:address":"148 Lang St",
    "sg:city":"Kurri Kurri",
    "sg:classifiers":[
        {
            "category":"Real Estate",
            "subcategory":"Real Estate Agent",
            "type":"Services"
        }
    ],
    "sg:phone":"+61 2 4937 5660",
    "sg:postcode":"2327",
    "sg:province":"NSW",
    "wof:name":"HEZ",
    "wof:placetype":"venue"
},
  "geometry": {"coordinates":[151.479736328,-32.8192901611],"type":"Point"}
}