{
  "type": "Feature",
  "properties": {
    "addr:full":"Shop 6 Brook Rd Seaforth NSW 2092",
    "addr:housenumber":"shop 6",
    "addr:postcode":"2092",
    "addr:street":"Brook Rd",
    "iso:country":"AU",
    "sg:address":"Shop 6 Brook Rd",
    "sg:city":"Seaforth",
    "sg:classifiers":[
        {
            "category":"Personal",
            "subcategory":"Beauty Salon",
            "type":"Services"
        }
    ],
    "sg:phone":"+61 417 418 944",
    "sg:postcode":"2092",
    "sg:province":"NSW",
    "wof:name":"Designer Nails &#039;N&#039; Things",
    "wof:placetype":"venue"
},
  "geometry": {"coordinates":[151.250656128,-33.7927360535],"type":"Point"}
}