{
  "type": "Feature",
  "properties": {
    "addr:full":"Shop 2 Centrepoint Plaza Bowen QLD 4805",
    "addr:housenumber":"shop 2",
    "addr:postcode":"4805",
    "addr:street":"Centrepoint Plaza",
    "iso:country":"AU",
    "sg:address":"Shop 2 Centrepoint Plaza",
    "sg:city":"Bowen",
    "sg:classifiers":[
        {
            "category":"Personal",
            "subcategory":"Beauty Salon",
            "type":"Services"
        }
    ],
    "sg:phone":"+61 7 4786 2685",
    "sg:postcode":"4805",
    "sg:province":"QLD",
    "sg:tags":[
        "hairdresser"
    ],
    "wof:name":"Scamps Hair Stylist",
    "wof:placetype":"venue"
},
  "geometry": {"coordinates":[148.22084045400001,-20.0146598816],"type":"Point"}
}