{
  "type": "Feature",
  "properties": {
    "iso:country":"AU",
    "sg:address":"Level 1, 68 Mollison St",
    "sg:city":"Abbotsford",
    "sg:classifiers":[
        {
            "category":"Real Estate",
            "subcategory":"Real Estate Services",
            "type":"Services"
        }
    ],
    "sg:phone":"+61 3 9415 1332",
    "sg:postcode":"3067",
    "sg:province":"VIC",
    "sg:tags":[
        "consultant",
        "property"
    ],
    "wof:name":"ICR Property & Investment Group PTY LTD",
    "wof:placetype":"venue"
},
  "geometry": {"coordinates":[144.998901367,-37.8074455261],"type":"Point"}
}