{
  "type": "Feature",
  "properties": {
    "iso:country":"AU",
    "sg:address":"29 Skinner Ave",
    "sg:city":"Riverwood",
    "sg:classifiers":[
        {
            "category":"Home & Garden",
            "subcategory":"Home Furnishings",
            "type":"Retail Goods"
        }
    ],
    "sg:phone":"+61 2 9533 8106",
    "sg:postcode":"2210",
    "sg:province":"NSW",
    "sg:tags":[
        "candle"
    ],
    "sg:website":"http://www.elume.com.au",
    "wof:name":"Elume",
    "wof:placetype":"venue"
},
  "geometry": {"coordinates":[151.062103,-33.940117],"type":"Point"}
}