{
  "type": "Feature",
  "properties": {
    "addr:full":"Suite 105, Springwood Tower Hotel, 9 Murrajong Rd Springwood QLD 4127",
    "addr:housenumber":"9",
    "addr:postcode":"4127",
    "addr:street":"Murrajong Rd",
    "iso:country":"AU",
    "sg:address":"Suite 105, Springwood Tower Hotel, 9 Murrajong Rd",
    "sg:city":"Springwood",
    "sg:classifiers":[
        {
            "category":"Professional",
            "subcategory":"Business Services",
            "type":"Services"
        }
    ],
    "sg:phone":"+61 1300 783 228",
    "sg:postcode":"4127",
    "sg:province":"QLD",
    "sg:tags":[
        "broker"
    ],
    "wof:name":"National Business Sales",
    "wof:placetype":"venue"
},
  "geometry": {"coordinates":[153.126785278,-27.6180419922],"type":"Point"}
}