{
  "type": "Feature",
  "properties": {
    "addr:full":"315 Church St Parramatta NSW 2150",
    "addr:housenumber":"315",
    "addr:postcode":"2150",
    "addr:street":"Church St",
    "iso:country":"AU",
    "sg:address":"315 Church St",
    "sg:city":"Parramatta",
    "sg:classifiers":[
        {
            "category":"Shopping",
            "subcategory":"Computers & Home Electronics",
            "type":"Retail Goods"
        }
    ],
    "sg:phone":"+61 2 9633 9677",
    "sg:postcode":"2150",
    "sg:province":"NSW",
    "sg:tags":[
        "hardware",
        "equipment"
    ],
    "wof:name":"TodayTech Computers Pty Ltd",
    "wof:placetype":"venue"
},
  "geometry": {"coordinates":[151.004806519,-33.8260307312],"type":"Point"}
}