{
  "type": "Feature",
  "properties": {
    "iso:country":"AU",
    "sg:address":"16 Hill Rd",
    "sg:city":"Homebush Bay",
    "sg:classifiers":[
        {
            "category":"Building & Trades",
            "subcategory":"Construction",
            "type":"Services"
        }
    ],
    "sg:phone":"+61 2 9748 5100",
    "sg:postcode":"2127",
    "sg:province":"NSW",
    "sg:tags":[
        "concrete",
        "paving"
    ],
    "wof:name":"De Martin & Gasparini Pty Ltd",
    "wof:placetype":"venue"
},
  "geometry": {"coordinates":[151.07456970199999,-33.827255249],"type":"Point"}
}