{
  "type": "Feature",
  "properties": {
    "addr:full":"77 Ocean Ave Slade Point QLD 4740",
    "addr:housenumber":"77",
    "addr:postcode":"4740",
    "addr:street":"Ocean Ave",
    "iso:country":"AU",
    "sg:address":"77 Ocean Ave",
    "sg:city":"Slade Point",
    "sg:classifiers":[
        {
            "category":"Real Estate",
            "subcategory":"Architect",
            "type":"Services"
        }
    ],
    "sg:phone":"+61 7 4955 1318",
    "sg:postcode":"4740",
    "sg:province":"QLD",
    "sg:tags":[
        "building",
        "designer"
    ],
    "wof:name":"Derek Taylor Design",
    "wof:placetype":"venue"
},
  "geometry": {"coordinates":[149.222916,-21.066383],"type":"Point"}
}