{
  "type": "Feature",
  "properties": {
    "iso:country":"AU",
    "sg:address":"Unit 7 62 Glen Osmond Rd",
    "sg:city":"Parkside",
    "sg:classifiers":[
        {
            "category":"Professional",
            "subcategory":"Engineering",
            "type":"Services"
        }
    ],
    "sg:phone":"+61 8 8271 7053",
    "sg:postcode":"5063",
    "sg:province":"SA",
    "sg:tags":[
        "consulting",
        "engineer"
    ],
    "wof:name":"Optimatics Pty Ltd",
    "wof:placetype":"venue"
},
  "geometry": {"coordinates":[138.61929321299999,-34.9429130554],"type":"Point"}
}