{
  "type": "Feature",
  "properties": {
    "addr:full":"12 Selby Pl Minto NSW 2566",
    "addr:housenumber":"12",
    "addr:postcode":"2566",
    "addr:street":"Selby Pl",
    "iso:country":"AU",
    "sg:address":"12 Selby Pl",
    "sg:city":"Minto",
    "sg:classifiers":[
        {
            "category":"Building & Trades",
            "subcategory":"Plumbing",
            "type":"Services"
        }
    ],
    "sg:phone":"+61 411 219 107",
    "sg:postcode":"2566",
    "sg:province":"NSW",
    "sg:tags":[
        "plumber",
        "gasfitters"
    ],
    "wof:name":"S & L Green Plumbing",
    "wof:placetype":"venue"
},
  "geometry": {"coordinates":[150.85528564399999,-34.044757843],"type":"Point"}
}