{
  "type": "Feature",
  "properties": {
    "addr:full":"27 Alexandra Rd Ulverstone TAS 7315",
    "addr:housenumber":"27",
    "addr:postcode":"7315",
    "addr:street":"Alexandra Rd",
    "iso:country":"AU",
    "sg:address":"27 Alexandra Rd",
    "sg:city":"Ulverstone",
    "sg:classifiers":[
        {
            "category":"Food & Beverages",
            "subcategory":"Supermarket",
            "type":"Retail Goods"
        }
    ],
    "sg:phone":"+61 3 6425 2857",
    "sg:postcode":"7315",
    "sg:province":"TAS",
    "sg:tags":[
        "grocery",
        "store"
    ],
    "wof:name":"M.G.s Supermarket",
    "wof:placetype":"venue"
},
  "geometry": {"coordinates":[146.17703247099999,-41.1571578979],"type":"Point"}
}