{
  "type": "Feature",
  "properties": {
    "addr:full":"18 Third St Brompton SA 5007",
    "addr:housenumber":"18",
    "addr:postcode":"5007",
    "addr:street":"Third St",
    "iso:country":"AU",
    "sg:address":"18 Third St",
    "sg:city":"Brompton",
    "sg:classifiers":[
        {
            "category":"Personal",
            "type":"Services"
        }
    ],
    "sg:phone":"+61 8 8346 3255",
    "sg:postcode":"5007",
    "sg:province":"SA",
    "sg:tags":[
        "counselling",
        "alcohol",
        "drug"
    ],
    "wof:name":"Alcoholics Anonymous",
    "wof:placetype":"venue"
},
  "geometry": {"coordinates":[138.57627868599999,-34.8997650146],"type":"Point"}
}