{
  "type": "Feature",
  "properties": {
    "addr:full":"383 Dorsett Rd Croydon VIC 3136",
    "addr:housenumber":"383",
    "addr:postcode":"3136",
    "addr:street":"Dorsett Rd",
    "iso:country":"AU",
    "sg:address":"383 Dorsett Rd",
    "sg:city":"Croydon",
    "sg:classifiers":[
        {
            "category":"Health Services",
            "subcategory":"Health Practitioner",
            "type":"Services"
        }
    ],
    "sg:phone":"+61 3 9725 2444",
    "sg:postcode":"3136",
    "sg:province":"VIC",
    "sg:tags":[
        "physiotherapist"
    ],
    "wof:name":"Travis Melanie",
    "wof:placetype":"venue"
},
  "geometry": {"coordinates":[145.28871154800001,-37.8065872192],"type":"Point"}
}