{
  "type": "Feature",
  "properties": {
    "addr:full":"428 Princes Hwy Blakehurst NSW 2221",
    "addr:housenumber":"428",
    "addr:postcode":"2221",
    "addr:street":"Princes Hwy",
    "iso:country":"AU",
    "sg:address":"428 Princes Hwy",
    "sg:city":"Blakehurst",
    "sg:classifiers":[
        {
            "category":"Recreation",
            "subcategory":"Fishing",
            "type":"Entertainment"
        }
    ],
    "sg:phone":"+61 2 9546 1341",
    "sg:postcode":"2221",
    "sg:province":"NSW",
    "sg:tags":[
        "bait"
    ],
    "wof:name":"MacS Bait Bar",
    "wof:placetype":"venue"
},
  "geometry": {"coordinates":[151.11685180699999,-33.9966545105],"type":"Point"}
}