{
  "type": "Feature",
  "properties": {
    "addr:full":"208 Learmonth St Buninyong VIC 3357",
    "addr:housenumber":"208",
    "addr:postcode":"3357",
    "addr:street":"Learmonth St",
    "iso:country":"AU",
    "sg:address":"208 Learmonth St",
    "sg:city":"Buninyong",
    "sg:classifiers":[
        {
            "category":"Social Services",
            "subcategory":"Child Care",
            "type":"Services"
        }
    ],
    "sg:phone":"+61 3 5341 3749",
    "sg:postcode":"3357",
    "sg:province":"VIC",
    "sg:tags":[
        "support",
        "health"
    ],
    "wof:name":"Maternal & Child Health Centres",
    "wof:placetype":"venue"
},
  "geometry": {"coordinates":[143.88765000000001,-37.650791],"type":"Point"}
}