{
  "type": "Feature",
  "properties": {
    "addr:full":"85 Dailey St Glenroy VIC 3046",
    "addr:housenumber":"85",
    "addr:postcode":"3046",
    "addr:street":"Dailey St",
    "iso:country":"AU",
    "sg:address":"85 Dailey St",
    "sg:city":"Glenroy",
    "sg:classifiers":[
        {
            "category":"Utilities",
            "subcategory":"Natural Gas",
            "type":"Services"
        }
    ],
    "sg:phone":"+61 401 581 455",
    "sg:postcode":"3046",
    "sg:province":"VIC",
    "sg:tags":[
        "solid",
        "plasterer"
    ],
    "wof:name":"Feature Art Rendering",
    "wof:placetype":"venue"
},
  "geometry": {"coordinates":[144.93089294399999,-37.6974601746],"type":"Point"}
}