{
  "type": "Feature",
  "properties": {
    "addr:full":"141 Church St Brighton VIC 3186",
    "addr:housenumber":"141",
    "addr:postcode":"3186",
    "addr:street":"Church St",
    "iso:country":"AU",
    "sg:address":"141 Church St",
    "sg:city":"Brighton",
    "sg:classifiers":[
        {
            "category":"Shopping",
            "subcategory":"Clothing, Apparel, & Fashions",
            "type":"Retail Goods"
        }
    ],
    "sg:phone":"+61 3 9593 3338",
    "sg:postcode":"3186",
    "sg:province":"VIC",
    "sg:tags":[
        "sportswear"
    ],
    "wof:name":"H20 Sportswear (Aust)",
    "wof:placetype":"venue"
},
  "geometry": {"coordinates":[144.99661254899999,-37.9156913757],"type":"Point"}
}