{
  "type": "Feature",
  "properties": {
    "addr:full":"4/167 Westall Rd Clayton South VIC 3169",
    "addr:housenumber":"/ 167",
    "addr:postcode":"3169",
    "addr:street":"Westall Rd",
    "iso:country":"AU",
    "sg:address":"4/167 Westall Rd",
    "sg:city":"Clayton South",
    "sg:classifiers":[
        {
            "category":"Manufacturing",
            "subcategory":"Printing",
            "type":"Manufacturing & Wholesale Goods"
        }
    ],
    "sg:phone":"+61 3 9547 2777",
    "sg:postcode":"3169",
    "sg:province":"VIC",
    "sg:tags":[
        "wholesaler",
        "mfrs",
        "greeting",
        "card"
    ],
    "wof:name":"ABC DIRECT",
    "wof:placetype":"venue"
},
  "geometry": {"coordinates":[145.13739013700001,-37.953994751],"type":"Point"}
}