{
  "type": "Feature",
  "properties": {
    "addr:full":"55 Albert Rd Strathfield NSW 2135",
    "addr:housenumber":"55",
    "addr:postcode":"2135",
    "addr:street":"Albert Rd",
    "iso:country":"AU",
    "sg:address":"55 Albert Rd",
    "sg:city":"Strathfield",
    "sg:classifiers":[
        {
            "category":"Organizations",
            "subcategory":"Non-profit Organization",
            "type":"Services"
        }
    ],
    "sg:phone":"+61 2 9744 7366",
    "sg:postcode":"2135",
    "sg:province":"NSW",
    "sg:tags":[
        "support",
        "disability",
        "organisation"
    ],
    "wof:name":"National Federation Of Blind Citizens Of Australia",
    "wof:placetype":"venue"
},
  "geometry": {"coordinates":[151.088424683,-33.8716011047],"type":"Point"}
}