{
  "type": "Feature",
  "properties": {
    "addr:full":"161 Bradley St Guyra NSW 2365",
    "addr:housenumber":"161",
    "addr:postcode":"2365",
    "addr:street":"Bradley St",
    "iso:country":"AU",
    "sg:address":"161 Bradley St",
    "sg:city":"Guyra",
    "sg:classifiers":[
        {
            "category":"Building & Trades",
            "subcategory":"Cleaning & Sanitation",
            "type":"Services"
        }
    ],
    "sg:phone":"+61 2 6779 1131",
    "sg:postcode":"2365",
    "sg:province":"NSW",
    "sg:tags":[
        "tank",
        "septic"
    ],
    "wof:name":"Highland Hire Plus",
    "wof:placetype":"venue"
},
  "geometry": {"coordinates":[151.67155456500001,-30.2215538025],"type":"Point"}
}