{
  "type": "Feature",
  "properties": {
    "iso:country":"AU",
    "sg:address":"25 Ladbrooke St",
    "sg:city":"Burnie",
    "sg:classifiers":[
        {
            "category":"Banks & Credit Unions",
            "subcategory":"Financial Services",
            "type":"Services"
        }
    ],
    "sg:phone":"+61 3 6431 8155",
    "sg:postcode":"7320",
    "sg:province":"TAS",
    "sg:tags":[
        "financier"
    ],
    "wof:name":"Personal Finance Co",
    "wof:placetype":"venue"
},
  "geometry": {"coordinates":[145.905029,-41.054134],"type":"Point"}
}