{
  "type": "Feature",
  "properties": {
    "addr:full":"70 Howard St Nambour QLD 4560",
    "addr:housenumber":"70",
    "addr:postcode":"4560",
    "addr:street":"Howard St",
    "iso:country":"AU",
    "sg:address":"70 Howard St",
    "sg:city":"Nambour",
    "sg:classifiers":[
        {
            "category":"Professional",
            "subcategory":"Employment Agencies",
            "type":"Services"
        }
    ],
    "sg:phone":"+61 7 5441 2844",
    "sg:postcode":"4560",
    "sg:province":"QLD",
    "wof:name":"Career Solutions",
    "wof:placetype":"venue"
},
  "geometry": {"coordinates":[152.962722778,-26.6266689301],"type":"Point"}
}