{
  "type": "Feature",
  "properties": {
    "iso:country":"AU",
    "sg:address":"1312 Dungog Rd",
    "sg:city":"Wallarobba",
    "sg:classifiers":[
        {
            "category":"Communications",
            "subcategory":"News Services",
            "type":"Services"
        }
    ],
    "sg:phone":"+61 2 4995 6166",
    "sg:postcode":"2420",
    "sg:province":"NSW",
    "sg:tags":[
        "information",
        "tourist",
        "attractions"
    ],
    "wof:name":"Camelot Lavender & Llama Farm",
    "wof:placetype":"venue"
},
  "geometry": {"coordinates":[151.685745,-32.502007],"type":"Point"}
}