{
  "type": "Feature",
  "properties": {
    "addr:full":"58 Desmond St Merrylands NSW 2160",
    "addr:housenumber":"58",
    "addr:postcode":"2160",
    "addr:street":"Desmond St",
    "iso:country":"AU",
    "sg:address":"58 Desmond St",
    "sg:city":"Merrylands",
    "sg:classifiers":[
        {
            "category":"Retail",
            "subcategory":"Auto Repair",
            "type":"Services"
        }
    ],
    "sg:phone":"+61 2 9632 7821",
    "sg:postcode":"2160",
    "sg:province":"NSW",
    "sg:tags":[
        "body",
        "motor",
        "trimmer"
    ],
    "wof:name":"Wolfenden Motor Trimming",
    "wof:placetype":"venue"
},
  "geometry": {"coordinates":[150.97575378400001,-33.8382759094],"type":"Point"}
}