{
  "type": "Feature",
  "properties": {
    "addr:full":"201 Cleveland St Redfern NSW 2016",
    "addr:housenumber":"201",
    "addr:postcode":"2016",
    "addr:street":"Cleveland St",
    "iso:country":"AU",
    "sg:address":"201 Cleveland St",
    "sg:city":"Redfern",
    "sg:classifiers":[
        {
            "category":"Professional",
            "subcategory":"Art Services",
            "type":"Services"
        }
    ],
    "sg:phone":"+61 2 9699 9155",
    "sg:postcode":"2016",
    "sg:province":"NSW",
    "sg:tags":[
        "arranger",
        "music",
        "composer"
    ],
    "wof:name":"Human Music & Sound Design",
    "wof:placetype":"venue"
},
  "geometry": {"coordinates":[151.20353698700001,-33.8894386292],"type":"Point"}
}