{
  "type": "Feature",
  "properties": {
    "addr:full":"2/ 753 Kingsway Gymea NSW 2227",
    "addr:housenumber":"/ 753",
    "addr:postcode":"2227",
    "addr:street":"Kingsway",
    "iso:country":"AU",
    "sg:address":"2/ 753 Kingsway",
    "sg:city":"Gymea",
    "sg:classifiers":[
        {
            "category":"Professional",
            "subcategory":"Computer Services",
            "type":"Services"
        }
    ],
    "sg:phone":"+61 2 9521 1600",
    "sg:postcode":"2227",
    "sg:province":"NSW",
    "sg:tags":[
        "consultant",
        "system"
    ],
    "wof:name":"Daedal Services Pty Ltd",
    "wof:placetype":"venue"
},
  "geometry": {"coordinates":[151.079544067,-34.0314598083],"type":"Point"}
}