{
  "type": "Feature",
  "properties": {
    "addr:full":"525 High St Prahran VIC 3181",
    "addr:housenumber":"525",
    "addr:postcode":"3181",
    "addr:street":"High St",
    "iso:country":"AU",
    "sg:address":"525 High St",
    "sg:city":"Prahran",
    "sg:classifiers":[
        {
            "category":"Health Services",
            "subcategory":"Health Practitioner",
            "type":"Services"
        }
    ],
    "sg:phone":"+61 3 9510 4550",
    "sg:postcode":"3181",
    "sg:province":"VIC",
    "sg:tags":[
        "herbalist"
    ],
    "wof:name":"Fiona Liang Chinese Medicine",
    "wof:placetype":"venue"
},
  "geometry": {"coordinates":[145.00570678700001,-37.8533859253],"type":"Point"}
}