{
  "type": "Feature",
  "properties": {
    "iso:country":"AU",
    "sg:address":"161 Oliver Rogers Rd",
    "sg:city":"Outer Harbor",
    "sg:classifiers":[
        {
            "category":"Retail",
            "subcategory":"Event Space",
            "type":"Services"
        }
    ],
    "sg:phone":"+61 8 8341 8600",
    "sg:postcode":"5018",
    "sg:province":"SA",
    "sg:tags":[
        "venue",
        "reception",
        "wedding"
    ],
    "wof:name":"Royal South Australian Yacht Squadron",
    "wof:placetype":"venue"
},
  "geometry": {"coordinates":[138.485397339,-34.7766571045],"type":"Point"}
}