{
  "type": "Feature",
  "properties": {
    "addr:full":"28 Nelson St Fairfield NSW 2165",
    "addr:housenumber":"28",
    "addr:postcode":"2165",
    "addr:street":"Nelson St",
    "iso:country":"AU",
    "sg:address":"28 Nelson St",
    "sg:city":"Fairfield",
    "sg:classifiers":[
        {
            "category":"Health Services",
            "subcategory":"Doctor",
            "type":"Services"
        }
    ],
    "sg:phone":"+61 2 9727 7290",
    "sg:postcode":"2165",
    "sg:province":"NSW",
    "sg:tags":[
        "medical",
        "practitioner"
    ],
    "wof:name":"Rodriguez Lilia",
    "wof:placetype":"venue"
},
  "geometry": {"coordinates":[150.95436096200001,-33.868938446],"type":"Point"}
}