{
  "type": "Feature",
  "properties": {
    "addr:full":"Unit 3/ 148 Toongabbie Rd Toongabbie NSW 2146",
    "addr:housenumber":"/ 148",
    "addr:postcode":"2146",
    "addr:street":"Toongabbie Rd",
    "iso:country":"AU",
    "sg:address":"Unit 3/ 148 Toongabbie Rd",
    "sg:city":"Toongabbie",
    "sg:classifiers":[
        {
            "category":"Manufacturing",
            "subcategory":"Tools & Machinery",
            "type":"Manufacturing & Wholesale Goods"
        }
    ],
    "sg:phone":"+61 2 9896 0266",
    "sg:postcode":"2146",
    "sg:province":"NSW",
    "sg:tags":[
        "equipment",
        "scale",
        "weighing"
    ],
    "wof:name":"All Major Brands",
    "wof:placetype":"venue"
},
  "geometry": {"coordinates":[150.93942260700001,-33.7942237854],"type":"Point"}
}