{
  "type": "Feature",
  "properties": {
    "addr:full":"271 Oxford St Bulimba QLD 4171",
    "addr:housenumber":"271",
    "addr:postcode":"4171",
    "addr:street":"Oxford St",
    "iso:country":"AU",
    "sg:address":"271 Oxford St",
    "sg:city":"Bulimba",
    "sg:classifiers":[
        {
            "category":"Education",
            "subcategory":"School",
            "type":"Public Place"
        }
    ],
    "sg:phone":"+61 7 3395 5954",
    "sg:postcode":"4171",
    "sg:province":"QLD",
    "sg:tags":[
        "state",
        "except",
        "nsw"
    ],
    "wof:name":"Bulimba Preschool",
    "wof:placetype":"venue"
},
  "geometry": {"coordinates":[153.06480407699999,-27.4521121979],"type":"Point"}
}