{
  "type": "Feature",
  "properties": {
    "iso:country":"AU",
    "sg:address":"79 Prince St",
    "sg:city":"Grafton",
    "sg:classifiers":[
        {
            "category":"Shopping",
            "subcategory":"Shoes",
            "type":"Retail Goods"
        }
    ],
    "sg:phone":"+61 2 6643 5321",
    "sg:postcode":"2460",
    "sg:province":"NSW",
    "sg:tags":[
        "footwear"
    ],
    "wof:name":"Clarence Shoex",
    "wof:placetype":"venue"
},
  "geometry": {"coordinates":[152.934158325,-29.6899814606],"type":"Point"}
}