{
  "type": "Feature",
  "properties": {
    "iso:country":"AU",
    "sg:address":"Level1/ 355 Centre Rd",
    "sg:city":"Bentleigh",
    "sg:classifiers":[
        {
            "category":"Banks & Credit Unions",
            "subcategory":"Investment Brokerage",
            "type":"Services"
        }
    ],
    "sg:phone":"+61 3 9557 9916",
    "sg:postcode":"3204",
    "sg:province":"VIC",
    "wof:name":"Simply Property",
    "wof:placetype":"venue"
},
  "geometry": {"coordinates":[145.03611799999999,-37.917969],"type":"Point"}
}