{
  "type": "Feature",
  "properties": {
    "addr:full":"86 Springvale Drv Hawker ACT 2614",
    "addr:housenumber":"86",
    "addr:postcode":"2614",
    "addr:street":"Springvale Drv",
    "iso:country":"AU",
    "sg:address":"86 Springvale Drv",
    "sg:city":"Hawker",
    "sg:classifiers":[
        {
            "category":"Personal",
            "subcategory":"Tattoo Parlor",
            "type":"Services"
        }
    ],
    "sg:phone":"+61 417 719 110",
    "sg:postcode":"2614",
    "sg:province":"ACT",
    "sg:tags":[
        "resume"
    ],
    "wof:name":"Your Career - A Roadmap to Success",
    "wof:placetype":"venue"
},
  "geometry": {"coordinates":[149.04360961899999,-35.2530174255],"type":"Point"}
}