{
  "type": "Feature",
  "properties": {
    "iso:country":"AU",
    "sg:address":"PO Box 156",
    "sg:city":"E Earlville",
    "sg:classifiers":[
        {
            "category":"Building & Trades",
            "subcategory":"Construction",
            "type":"Services"
        }
    ],
    "sg:phone":"+61 7 4035 1417",
    "sg:postcode":"4870",
    "sg:province":"QLD",
    "sg:tags":[
        "contractor"
    ],
    "wof:name":"Pratt D.S. & L.J.",
    "wof:placetype":"venue"
},
  "geometry": {"coordinates":[145.736206055,-16.9474105835],"type":"Point"}
}