{
  "type": "Feature",
  "properties": {
    "addr:full":"401 Monbulk Rd Monbulk VIC 3793",
    "addr:housenumber":"401",
    "addr:postcode":"3793",
    "addr:street":"Monbulk Rd",
    "iso:country":"AU",
    "sg:address":"401 Monbulk Rd",
    "sg:city":"Monbulk",
    "sg:classifiers":[
        {
            "category":"Wholesale",
            "subcategory":"Plants",
            "type":"Manufacturing & Wholesale Goods"
        }
    ],
    "sg:phone":"+61 3 9213 6200",
    "sg:postcode":"3793",
    "sg:province":"VIC",
    "sg:tags":[
        "florist"
    ],
    "wof:name":"Tesselaar Flowers",
    "wof:placetype":"venue"
},
  "geometry": {"coordinates":[145.41914367699999,-37.8549232483],"type":"Point"}
}