{
  "type": "Feature",
  "properties": {
    "iso:country":"AU",
    "sg:address":"Shop 8 Ferrodale Rd",
    "sg:city":"Medowie",
    "sg:classifiers":[
        {
            "category":"Personal",
            "subcategory":"Massage",
            "type":"Services"
        }
    ],
    "sg:phone":"+61 2 4981 7855",
    "sg:postcode":"2318",
    "sg:province":"NSW",
    "sg:tags":[
        "therapy"
    ],
    "wof:name":"Kearns Margaret",
    "wof:placetype":"venue"
},
  "geometry": {"coordinates":[151.880203,-32.743183],"type":"Point"}
}