{
  "type": "Feature",
  "properties": {
    "addr:full":"6 Thames St MacGregor QLD 4109",
    "addr:housenumber":"6",
    "addr:postcode":"4109",
    "addr:street":"Thames St",
    "iso:country":"AU",
    "sg:address":"6 Thames St",
    "sg:city":"MacGregor",
    "sg:classifiers":[
        {
            "category":"Personal",
            "subcategory":"Skin Care",
            "type":"Services"
        }
    ],
    "sg:phone":"+61 7 3344 2310",
    "sg:postcode":"4109",
    "sg:province":"QLD",
    "sg:tags":[
        "treatment"
    ],
    "wof:name":"Sonja's Beauty & Therapy Centre",
    "wof:placetype":"venue"
},
  "geometry": {"coordinates":[153.06996154800001,-27.5703659058],"type":"Point"}
}