{
  "type": "Feature",
  "properties": {
    "addr:full":"4 Welch St Southport QLD 4215",
    "addr:housenumber":"4",
    "addr:postcode":"4215",
    "addr:street":"Welch St",
    "iso:country":"AU",
    "sg:address":"4 Welch St",
    "sg:city":"Southport",
    "sg:classifiers":[
        {
            "category":"Personal",
            "subcategory":"Beauty Salon",
            "type":"Services"
        }
    ],
    "sg:phone":"+61 7 5531 2933",
    "sg:postcode":"4215",
    "sg:province":"QLD",
    "sg:tags":[
        "hairdresser"
    ],
    "wof:name":"Wayne Price Hairdressing",
    "wof:placetype":"venue"
},
  "geometry": {"coordinates":[153.41404724099999,-27.9639911652],"type":"Point"}
}