{
  "type": "Feature",
  "properties": {
    "addr:full":"101 Prince St Waratah NSW 2298",
    "addr:housenumber":"101",
    "addr:postcode":"2298",
    "addr:street":"Prince St",
    "iso:country":"AU",
    "sg:address":"101 Prince St",
    "sg:city":"Waratah",
    "sg:classifiers":[
        {
            "category":"Shopping",
            "subcategory":"Clothing, Apparel, & Fashions",
            "type":"Retail Goods"
        }
    ],
    "sg:phone":"+61 2 4960 2774",
    "sg:postcode":"2298",
    "sg:province":"NSW",
    "sg:tags":[
        "lady",
        "wear"
    ],
    "wof:name":"Undercoverwear Collection Angel Montague",
    "wof:placetype":"venue"
},
  "geometry": {"coordinates":[151.72390747099999,-32.8965492249],"type":"Point"}
}