{
  "type": "Feature",
  "properties": {
    "addr:full":"Hangar 71 RAAF Base Amberley QLD 4306",
    "addr:postcode":"4306",
    "iso:country":"AU",
    "sg:address":"Hangar 71 RAAF Base",
    "sg:city":"Amberley",
    "sg:classifiers":[
        {
            "category":"Manufacturing",
            "subcategory":"Aerospace",
            "type":"Manufacturing & Wholesale Goods"
        }
    ],
    "sg:phone":"+61 7 3282 9911",
    "sg:postcode":"4306",
    "sg:province":"QLD",
    "sg:tags":[
        "equipment",
        "aircraft",
        "maintenance"
    ],
    "wof:name":"Tasman Aviation Enterprises (Qld) Pty Ltd",
    "wof:placetype":"venue"
},
  "geometry": {"coordinates":[152.700515747,-27.657869339],"type":"Point"}
}