{
  "type": "Feature",
  "properties": {
    "addr:full":"135 Penshurst St Penshurst NSW 2222",
    "addr:housenumber":"135",
    "addr:postcode":"2222",
    "addr:street":"Penshurst St",
    "iso:country":"AU",
    "sg:address":"135 Penshurst St",
    "sg:city":"Penshurst",
    "sg:classifiers":[
        {
            "category":"Health Services",
            "subcategory":"Chiropractor",
            "type":"Services"
        }
    ],
    "sg:phone":"+61 2 9570 5999",
    "sg:postcode":"2222",
    "sg:province":"NSW",
    "wof:name":"Goldsworthy Simon J",
    "wof:placetype":"venue"
},
  "geometry": {"coordinates":[151.08076477,-33.9568901062],"type":"Point"}
}