{
  "type": "Feature",
  "properties": {
    "addr:full":"Unit D/30-32 Skarratt (North) St Silverwater NSW 2128",
    "addr:housenumber":"unit;/ 30-32",
    "addr:postcode":"2128",
    "iso:country":"AU",
    "sg:address":"Unit D/30-32 Skarratt (North) St",
    "sg:city":"Silverwater",
    "sg:classifiers":[
        {
            "category":"Wholesale",
            "subcategory":"Toys & Hobbies",
            "type":"Manufacturing & Wholesale Goods"
        }
    ],
    "sg:phone":"+61 2 9748 0727",
    "sg:postcode":"2128",
    "sg:province":"NSW",
    "wof:name":"Ryan's Toys Pty Ltd",
    "wof:placetype":"venue"
},
  "geometry": {"coordinates":[151.03721618599999,-33.8349266052],"type":"Point"}
}