{
  "type": "Feature",
  "properties": {
    "iso:country":"AU",
    "sg:address":"70 Macquarie Rd",
    "sg:city":"Springwood",
    "sg:classifiers":[
        {
            "category":"Organizations",
            "subcategory":"Non-profit Organization",
            "type":"Services"
        }
    ],
    "sg:phone":"+61 2 4751 4642",
    "sg:postcode":"2777",
    "sg:province":"NSW",
    "sg:tags":[
        "support",
        "disability",
        "organisation"
    ],
    "wof:name":"Springwood Childrens Centre",
    "wof:placetype":"venue"
},
  "geometry": {"coordinates":[150.571975708,-33.6999053955],"type":"Point"}
}