{
  "type": "Feature",
  "properties": {
    "addr:full":"303 Middleton Rd Albany WA 6330",
    "addr:housenumber":"303",
    "addr:postcode":"6330",
    "addr:street":"Middleton Rd",
    "iso:country":"AU",
    "sg:address":"303 Middleton Rd",
    "sg:city":"Albany",
    "sg:classifiers":[
        {
            "category":"Travel",
            "subcategory":"Hotels & Motels",
            "type":"Entertainment"
        }
    ],
    "sg:phone":"+61 8 9841 4422",
    "sg:postcode":"6330",
    "sg:province":"WA",
    "wof:name":"Dog Rock Motel",
    "wof:placetype":"venue"
},
  "geometry": {"coordinates":[117.88945007300001,-35.0174369812],"type":"Point"}
}