{
  "type": "Feature",
  "properties": {
    "iso:country":"AU",
    "sg:address":"6 Elfreda Ave",
    "sg:city":"Sorrento",
    "sg:classifiers":[
        {
            "category":"Banks & Credit Unions",
            "subcategory":"Financial Services",
            "type":"Services"
        }
    ],
    "sg:phone":"+61 8 9448 3813",
    "sg:postcode":"6020",
    "sg:province":"WA",
    "sg:tags":[
        "advisory",
        "planning",
        "retirement"
    ],
    "wof:name":"Gardner Peter & Associates",
    "wof:placetype":"venue"
},
  "geometry": {"coordinates":[115.759498596,-31.8310031891],"type":"Point"}
}