{
  "type": "Feature",
  "properties": {
    "addr:full":"18 Curzon St Browns Plains QLD 4118",
    "addr:housenumber":"18",
    "addr:postcode":"4118",
    "addr:street":"Curzon St",
    "iso:country":"AU",
    "sg:address":"18 Curzon St",
    "sg:city":"Browns Plains",
    "sg:classifiers":[
        {
            "category":"Building & Trades",
            "subcategory":"Construction",
            "type":"Services"
        }
    ],
    "sg:phone":"+61 7 3806 7102",
    "sg:postcode":"4118",
    "sg:province":"QLD",
    "sg:tags":[
        "joiner",
        "carpenter"
    ],
    "wof:name":"King, Brian",
    "wof:placetype":"venue"
},
  "geometry": {"coordinates":[153.05752563499999,-27.6685962677],"type":"Point"}
}