{
  "type": "Feature",
  "properties": {
    "iso:country":"AU",
    "sg:address":"55 Cambridge Rd",
    "sg:city":"Bellerive",
    "sg:classifiers":[
        {
            "category":"Shopping",
            "subcategory":"Clothing, Apparel, & Fashions",
            "type":"Retail Goods"
        }
    ],
    "sg:phone":"+61 3 6244 8883",
    "sg:postcode":"7018",
    "sg:province":"TAS",
    "sg:tags":[
        "wholesaler",
        "children's",
        "mfrs",
        "wear"
    ],
    "wof:name":"Adina Agencies",
    "wof:placetype":"venue"
},
  "geometry": {"coordinates":[147.36958313,-42.872882843],"type":"Point"}
}