{
  "type": "Feature",
  "properties": {
    "iso:country":"AU",
    "sg:address":"Pizzoni Rd",
    "sg:city":"Toowoomba",
    "sg:classifiers":[
        {
            "category":"Building & Trades",
            "subcategory":"Construction",
            "type":"Services"
        }
    ],
    "sg:phone":"+61 7 4634 8838",
    "sg:postcode":"4350",
    "sg:province":"QLD",
    "sg:tags":[
        "earth",
        "excavating",
        "moving",
        "contractor"
    ],
    "wof:name":"All Site Earthworks",
    "wof:placetype":"venue"
},
  "geometry": {"coordinates":[151.886795,-27.563938],"type":"Point"}
}