{
  "type": "Feature",
  "properties": {
    "iso:country":"AU",
    "sg:address":"135 Kings Way",
    "sg:city":"Southbank",
    "sg:classifiers":[
        {
            "category":"Retail",
            "subcategory":"Auto Repair",
            "type":"Services"
        }
    ],
    "sg:phone":"+61 3 9698 1175",
    "sg:postcode":"3006",
    "sg:province":"VIC",
    "sg:tags":[
        "repairer",
        "motor",
        "engineer"
    ],
    "wof:name":"Smart Centre Melbourne",
    "wof:placetype":"venue"
},
  "geometry": {"coordinates":[144.96656799300001,-37.8255767822],"type":"Point"}
}