{
  "type": "Feature",
  "properties": {
    "addr:full":"114 Main North Rd Prospect SA 5082",
    "addr:housenumber":"114",
    "addr:postcode":"5082",
    "addr:street":"Main North Rd",
    "iso:country":"AU",
    "sg:address":"114 Main North Rd",
    "sg:city":"Prospect",
    "sg:classifiers":[
        {
            "category":"Education",
            "subcategory":"School",
            "type":"Public Place"
        }
    ],
    "sg:phone":"+61 8 8344 6508",
    "sg:postcode":"5082",
    "sg:province":"SA",
    "sg:tags":[
        "state",
        "except",
        "nsw"
    ],
    "wof:name":"Prospect Centre",
    "wof:placetype":"venue"
},
  "geometry": {"coordinates":[138.60289001500001,-34.8892822266],"type":"Point"}
}