{
  "type": "Feature",
  "properties": {
    "addr:full":"113/ 20 Dale St Brookvale NSW 2100",
    "addr:housenumber":"113 / 20",
    "addr:postcode":"2100",
    "addr:street":"Dale St",
    "iso:country":"AU",
    "sg:address":"113/ 20 Dale St",
    "sg:city":"Brookvale",
    "sg:classifiers":[
        {
            "category":"Professional",
            "subcategory":"Employment Agencies",
            "type":"Services"
        }
    ],
    "sg:phone":"+61 2 9939 3188",
    "sg:postcode":"2100",
    "sg:province":"NSW",
    "wof:name":"MAX Employment",
    "wof:placetype":"venue"
},
  "geometry": {"coordinates":[151.268234253,-33.7652168274],"type":"Point"}
}