{
  "type": "Feature",
  "properties": {
    "addr:full":"5 Sunrise Crt Epping VIC 3076",
    "addr:housenumber":"5",
    "addr:postcode":"3076",
    "addr:street":"Sunrise Crt",
    "iso:country":"AU",
    "sg:address":"5 Sunrise Crt",
    "sg:city":"Epping",
    "sg:classifiers":[
        {
            "category":"Home & Garden",
            "subcategory":"Building Materials",
            "type":"Retail Goods"
        }
    ],
    "sg:phone":"+61 3 9408 7557",
    "sg:postcode":"3076",
    "sg:province":"VIC",
    "sg:tags":[
        "merchant",
        "glass",
        "glazier"
    ],
    "wof:name":"Done Right Pty Ltd",
    "wof:placetype":"venue"
},
  "geometry": {"coordinates":[145.03593444800001,-37.6527404785],"type":"Point"}
}