{
  "type": "Feature",
  "properties": {
    "addr:full":"Lvl 12/ 468 St Kilda Rd Melbourne VIC 3000",
    "addr:housenumber":"/ 468",
    "addr:postcode":"3000",
    "addr:street":"St Kilda Rd",
    "iso:country":"AU",
    "sg:address":"Lvl 12/ 468 St Kilda Rd",
    "sg:city":"Melbourne",
    "sg:classifiers":[
        {
            "category":"Professional",
            "subcategory":"Accounting & Tax Preparation",
            "type":"Services"
        }
    ],
    "sg:phone":"+61 3 8517 2200",
    "sg:postcode":"3000",
    "sg:province":"VIC",
    "sg:tags":[
        "deduction",
        "payroll"
    ],
    "wof:name":"Empower Masterpay Pty Ltd",
    "wof:placetype":"venue"
},
  "geometry": {"coordinates":[144.98109435999999,-37.8524551392],"type":"Point"}
}