{
  "type": "Feature",
  "properties": {
    "addr:full":"11 Railway St Emu Plains NSW 2750",
    "addr:housenumber":"11",
    "addr:postcode":"2750",
    "addr:street":"Railway St",
    "iso:country":"AU",
    "sg:address":"11 Railway St",
    "sg:city":"Emu Plains",
    "sg:classifiers":[
        {
            "category":"Retail",
            "subcategory":"Auto Repair",
            "type":"Services"
        }
    ],
    "sg:phone":"+61 2 4735 2438",
    "sg:postcode":"2750",
    "sg:province":"NSW",
    "sg:tags":[
        "electrical"
    ],
    "wof:name":"Emu Plains Auto Electrical",
    "wof:placetype":"venue"
},
  "geometry": {"coordinates":[150.671707153,-33.7433242798],"type":"Point"}
}