{
  "type": "Feature",
  "properties": {
    "iso:country":"AU",
    "sg:address":"Lvl 1, 11 Lonsdale St",
    "sg:city":"Braddon",
    "sg:classifiers":[
        {
            "category":"Real Estate",
            "subcategory":"Architect",
            "type":"Services"
        }
    ],
    "sg:phone":"+61 2 6230 4881",
    "sg:postcode":"2612",
    "sg:province":"ACT",
    "sg:tags":[
        "building",
        "designer"
    ],
    "wof:name":"Dub Design Pty Ltd",
    "wof:placetype":"venue"
},
  "geometry": {"coordinates":[149.132415772,-35.2745742798],"type":"Point"}
}