{
  "type": "Feature",
  "properties": {
    "iso:country":"AU",
    "sg:address":"47 Kent St",
    "sg:city":"Warragul",
    "sg:classifiers":[
        {
            "category":"Retail",
            "subcategory":"Repair Shop",
            "type":"Services"
        }
    ],
    "sg:phone":"+61 3 5623 1277",
    "sg:postcode":"3820",
    "sg:province":"VIC",
    "sg:tags":[
        "machine",
        "repairs",
        "part",
        "dryer",
        "washing"
    ],
    "wof:name":"Alecton TV Service",
    "wof:placetype":"venue"
},
  "geometry": {"coordinates":[145.935867,-38.157272],"type":"Point"}
}