{
  "type": "Feature",
  "properties": {
    "addr:full":"Suite 6E Villiers St North Parramatta NSW 2151",
    "addr:postcode":"2151",
    "addr:street":"St",
    "iso:country":"AU",
    "sg:address":"Suite 6E Villiers St",
    "sg:city":"North Parramatta",
    "sg:classifiers":[
        {
            "category":"Real Estate",
            "subcategory":"Architect",
            "type":"Services"
        }
    ],
    "sg:phone":"+61 2 9683 4800",
    "sg:postcode":"2151",
    "sg:province":"NSW",
    "wof:name":"Abstract Group",
    "wof:placetype":"venue"
},
  "geometry": {"coordinates":[151.00465393100001,-33.8064002991],"type":"Point"}
}