{
  "type": "Feature",
  "properties": {
    "addr:full":"Cnr Heatherton & Matthew Flinders Ave Endeavour Hills VIC 3802",
    "addr:postcode":"3802",
    "addr:street":"Cnr Heatherton &;Flinders Ave",
    "iso:country":"AU",
    "sg:address":"Cnr Heatherton & Matthew Flinders Ave",
    "sg:city":"Endeavour Hills",
    "sg:classifiers":[
        {
            "category":"Autos & Motor Vehicles",
            "subcategory":"Fuel & Gas Station",
            "type":"Retail Goods"
        }
    ],
    "sg:phone":"+61 3 9706 0352",
    "sg:postcode":"3802",
    "sg:province":"VIC",
    "wof:name":"Plus Petrol",
    "wof:placetype":"venue"
},
  "geometry": {"coordinates":[145.25526428200001,-37.9744415283],"type":"Point"}
}