{
  "type": "Feature",
  "properties": {
    "addr:full":"56 Hume St Goulburn NSW 2580",
    "addr:housenumber":"56",
    "addr:postcode":"2580",
    "addr:street":"Hume St",
    "iso:country":"AU",
    "sg:address":"56 Hume St",
    "sg:city":"Goulburn",
    "sg:classifiers":[
        {
            "category":"Building & Trades",
            "subcategory":"Plumbing",
            "type":"Services"
        }
    ],
    "sg:phone":"+61 416 162 590",
    "sg:postcode":"2580",
    "sg:province":"NSW",
    "sg:tags":[
        "plumber",
        "gasfitters"
    ],
    "wof:name":"Scott Reid Plumbing",
    "wof:placetype":"venue"
},
  "geometry": {"coordinates":[149.702667236,-34.764667511],"type":"Point"}
}