{
  "type": "Feature",
  "properties": {
    "addr:full":"52 Elizabeth St Holmesville NSW 2286",
    "addr:housenumber":"52",
    "addr:postcode":"2286",
    "addr:street":"Elizabeth St",
    "iso:country":"AU",
    "sg:address":"52 Elizabeth St",
    "sg:city":"Holmesville",
    "sg:classifiers":[
        {
            "category":"Retail",
            "subcategory":"Repair Shop",
            "type":"Services"
        }
    ],
    "sg:phone":"+61 421 401 679",
    "sg:postcode":"2286",
    "sg:province":"NSW",
    "sg:tags":[
        "leadlights"
    ],
    "wof:name":"Ricky Burton Leadlighting",
    "wof:placetype":"venue"
},
  "geometry": {"coordinates":[151.57572937,-32.9127082825],"type":"Point"}
}