{
  "type": "Feature",
  "properties": {
    "addr:full":"8 George St Swan Hill VIC 3585",
    "addr:housenumber":"8",
    "addr:postcode":"3585",
    "addr:street":"George St",
    "iso:country":"AU",
    "sg:address":"8 George St",
    "sg:city":"Swan Hill",
    "sg:classifiers":[
        {
            "category":"Building & Trades",
            "subcategory":"Construction",
            "type":"Services"
        }
    ],
    "sg:phone":"+61 3 5033 0069",
    "sg:postcode":"3585",
    "sg:province":"VIC",
    "sg:tags":[
        "joinery"
    ],
    "wof:name":"Rogers Furniture & Joinery",
    "wof:placetype":"venue"
},
  "geometry": {"coordinates":[143.55311599999999,-35.330414],"type":"Point"}
}