{
  "type": "Feature",
  "properties": {
    "iso:country":"AU",
    "sg:address":"88 Durlacher St",
    "sg:city":"Geraldton",
    "sg:classifiers":[
        {
            "category":"Government",
            "subcategory":"City Hall",
            "type":"Public Place"
        }
    ],
    "sg:phone":"+61 8 9921 2684",
    "sg:postcode":"6530",
    "sg:province":"WA",
    "wof:name":"Queen Elizabeth II Centre",
    "wof:placetype":"venue"
},
  "geometry": {"coordinates":[114.614532471,-28.7760925293],"type":"Point"}
}