{
  "type": "Feature",
  "properties": {
    "addr:full":"Ridley St Edgeworth NSW 2285",
    "addr:postcode":"2285",
    "addr:street":"Ridley St",
    "iso:country":"AU",
    "sg:address":"Ridley St",
    "sg:city":"Edgeworth",
    "sg:classifiers":[
        {
            "category":"Education",
            "subcategory":"School",
            "type":"Public Place"
        }
    ],
    "sg:phone":"+61 2 4958 1180",
    "sg:postcode":"2285",
    "sg:province":"NSW",
    "sg:tags":[
        "state",
        "-",
        "nsw"
    ],
    "wof:name":"Edgeworth Heights Public",
    "wof:placetype":"venue"
},
  "geometry": {"coordinates":[151.610473633,-32.9244270325],"type":"Point"}
}