{
  "type": "Feature",
  "properties": {
    "iso:country":"AU",
    "sg:address":"5 Ethell Rd",
    "sg:city":"Kirrawee",
    "sg:classifiers":[
        {
            "category":"Retail",
            "subcategory":"Auto Repair",
            "type":"Services"
        }
    ],
    "sg:phone":"+61 2 9521 8555",
    "sg:postcode":"2232",
    "sg:province":"NSW",
    "sg:tags":[
        "gas",
        "conversion",
        "natural",
        "lp",
        "vehicle"
    ],
    "wof:name":"All Gas Conversions",
    "wof:placetype":"venue"
},
  "geometry": {"coordinates":[151.08125305199999,-34.0240592957],"type":"Point"}
}