{
  "type": "Feature",
  "properties": {
    "addr:full":"88 Observation Drv Rye VIC 3941",
    "addr:housenumber":"88",
    "addr:postcode":"3941",
    "addr:street":"Observation Drv",
    "iso:country":"AU",
    "sg:address":"88 Observation Drv",
    "sg:city":"Rye",
    "sg:classifiers":[
        {
            "category":"Professional",
            "subcategory":"Art Services",
            "type":"Services"
        }
    ],
    "sg:phone":"+61 438 853 683",
    "sg:postcode":"3941",
    "sg:province":"VIC",
    "sg:tags":[
        "decorator",
        "painter"
    ],
    "wof:name":"Barry Heath",
    "wof:placetype":"venue"
},
  "geometry": {"coordinates":[144.82684326200001,-38.3824920654],"type":"Point"}
}