{
  "type": "Feature",
  "properties": {
    "addr:full":"U2/ 24 Thorne St Wynnum QLD 4178",
    "addr:housenumber":"24",
    "addr:postcode":"4178",
    "addr:street":"U2 /;Thorne St",
    "iso:country":"AU",
    "sg:address":"U2/ 24 Thorne St",
    "sg:city":"Wynnum",
    "sg:classifiers":[
        {
            "category":"Building & Trades",
            "subcategory":"Pest Control",
            "type":"Services"
        }
    ],
    "sg:phone":"+61 1800 625 600",
    "sg:postcode":"4178",
    "sg:province":"QLD",
    "wof:name":"Termite Patrol",
    "wof:placetype":"venue"
},
  "geometry": {"coordinates":[153.16754150400001,-27.4394359589],"type":"Point"}
}