{
  "type": "Feature",
  "properties": {
    "addr:full":"U3/ 151 Martyn St Parramatta Park QLD 4870",
    "addr:housenumber":"151",
    "addr:postcode":"4870",
    "addr:street":"U3 /;Martyn St",
    "iso:country":"AU",
    "sg:address":"U3/ 151 Martyn St",
    "sg:city":"Parramatta Park",
    "sg:classifiers":[
        {
            "category":"Organizations",
            "subcategory":"Professional Association",
            "type":"Services"
        }
    ],
    "sg:phone":"+61 7 4051 3030",
    "sg:postcode":"4870",
    "sg:province":"QLD",
    "sg:tags":[
        "web",
        "internet"
    ],
    "wof:name":"Ann Web Design & Hosting",
    "wof:placetype":"venue"
},
  "geometry": {"coordinates":[145.75933837900001,-16.9154415131],"type":"Point"}
}