{
  "type": "Feature",
  "properties": {
    "addr:full":"2488 River Rd Wisemans Ferry NSW 2775",
    "addr:housenumber":"2488",
    "addr:postcode":"2775",
    "addr:street":"River Rd",
    "iso:country":"AU",
    "sg:address":"2488 River Rd",
    "sg:city":"Wisemans Ferry",
    "sg:classifiers":[
        {
            "category":"Recreation",
            "subcategory":"Water Park",
            "type":"Entertainment"
        }
    ],
    "sg:phone":"+61 2 4566 4588",
    "sg:postcode":"2775",
    "sg:province":"NSW",
    "sg:tags":[
        "resort",
        "skiing"
    ],
    "wof:name":"Sydney Ski School",
    "wof:placetype":"venue"
},
  "geometry": {"coordinates":[150.953811645,-33.4161262512],"type":"Point"}
}