{
  "type": "Feature",
  "properties": {
    "iso:country":"AU",
    "sg:address":"53 Cliff Ave",
    "sg:city":"Port Noarlunga South",
    "sg:classifiers":[
        {
            "category":"Deli",
            "type":"Food & Drink"
        }
    ],
    "sg:phone":"+61 8 8386 1868",
    "sg:postcode":"5167",
    "sg:province":"SA",
    "sg:tags":[
        "delicatessen"
    ],
    "wof:name":"Cliff Ave Deli",
    "wof:placetype":"venue"
},
  "geometry": {"coordinates":[138.46917724599999,-35.1725311279],"type":"Point"}
}