{
  "type": "Feature",
  "properties": {
    "iso:country":"AU",
    "sg:address":"85 Hindley St",
    "sg:city":"Adelaide",
    "sg:classifiers":[
        {
            "category":"Travel",
            "subcategory":"Hotels & Motels",
            "type":"Entertainment"
        }
    ],
    "sg:phone":"+61 8 8231 6371",
    "sg:postcode":"5000",
    "sg:province":"SA",
    "sg:tags":[
        "accommodation"
    ],
    "sg:website":"http://www.plazahotel.com.au",
    "wof:name":"Plaza Hotel",
    "wof:placetype":"venue"
},
  "geometry": {"coordinates":[138.59628295900001,-34.9232788086],"type":"Point"}
}