{
  "type": "Feature",
  "properties": {
    "addr:full":"1303 Nepean Hwy Cheltenham VIC 3192",
    "addr:housenumber":"1303",
    "addr:postcode":"3192",
    "addr:street":"Nepean Hwy",
    "iso:country":"AU",
    "sg:address":"1303 Nepean Hwy",
    "sg:city":"Cheltenham",
    "sg:classifiers":[
        {
            "category":"Sports & Exercise",
            "subcategory":"Gym",
            "type":"Entertainment"
        }
    ],
    "sg:phone":"+61 3 9211 0631",
    "sg:postcode":"3192",
    "sg:province":"VIC",
    "sg:tags":[
        "health",
        "fitness"
    ],
    "wof:name":"Pilates Bayside",
    "wof:placetype":"venue"
},
  "geometry": {"coordinates":[145.05862426799999,-37.9660453796],"type":"Point"}
}