{
  "type": "Feature",
  "properties": {
    "addr:full":"12 Bunratty St The Gap QLD 4061",
    "addr:housenumber":"12",
    "addr:postcode":"4061",
    "addr:street":"Bunratty St",
    "iso:country":"AU",
    "sg:address":"12 Bunratty St",
    "sg:city":"The Gap",
    "sg:classifiers":[
        {
            "category":"Professional",
            "subcategory":"Art Services",
            "type":"Services"
        }
    ],
    "sg:phone":"+61 7 3300 2566",
    "sg:postcode":"4061",
    "sg:province":"QLD",
    "sg:tags":[
        "decorator",
        "painter"
    ],
    "wof:name":"Davidson G J & J G",
    "wof:placetype":"venue"
},
  "geometry": {"coordinates":[152.92933654800001,-27.4363956451],"type":"Point"}
}