{
  "type": "Feature",
  "properties": {
    "iso:country":"AU",
    "sg:address":"PO Box 2012",
    "sg:city":"Deer Park North",
    "sg:classifiers":[
        {
            "category":"Building & Trades",
            "subcategory":"Plumbing",
            "type":"Services"
        }
    ],
    "sg:phone":"+61 412 353 993",
    "sg:postcode":"3023",
    "sg:province":"VIC",
    "sg:tags":[
        "plumber",
        "gasfitters"
    ],
    "wof:name":"Deer Park Plumbing",
    "wof:placetype":"venue"
},
  "geometry": {"coordinates":[144.756958,-37.769184],"type":"Point"}
}