{
  "type": "Feature",
  "properties": {
    "addr:full":"Centro Springwood Shopping Centre, cnr Rochedale Road and Fitzgerald Ave Springwood QLD 4127",
    "addr:postcode":"4127",
    "addr:street":"Cnr Rochedale Road;Ave",
    "iso:country":"AU",
    "sg:address":"Centro Springwood Shopping Centre, cnr Rochedale Road and Fitzgerald Ave",
    "sg:city":"Springwood",
    "sg:classifiers":[
        {
            "category":"Professional",
            "subcategory":"Printing & Photocopies",
            "type":"Services"
        }
    ],
    "sg:phone":"+61 7 3299 3400",
    "sg:postcode":"4127",
    "sg:province":"QLD",
    "sg:tags":[
        "screen",
        "printer"
    ],
    "wof:name":"Black Rock Surfwear",
    "wof:placetype":"venue"
},
  "geometry": {"coordinates":[153.125244141,-27.6167545319],"type":"Point"}
}