{
  "type": "Feature",
  "properties": {
    "addr:full":"4/ 1 Skyline Pl Frenchs Forest NSW 2086",
    "addr:housenumber":"/ 1",
    "addr:postcode":"2086",
    "addr:street":"Skyline Pl",
    "iso:country":"AU",
    "sg:address":"4/ 1 Skyline Pl",
    "sg:city":"Frenchs Forest",
    "sg:classifiers":[
        {
            "category":"Education",
            "subcategory":"School",
            "type":"Public Place"
        }
    ],
    "sg:phone":"+61 2 9975 5551",
    "sg:postcode":"2086",
    "sg:province":"NSW",
    "sg:tags":[
        "supply"
    ],
    "wof:name":"Educational Concepts (Sales) Pty Ltd",
    "wof:placetype":"venue"
},
  "geometry": {"coordinates":[151.238479614,-33.7507019043],"type":"Point"}
}