{
  "type": "Feature",
  "properties": {
    "iso:country":"AU",
    "sg:address":"Shop 4 B 125 Old Cleveland Rd",
    "sg:city":"Capalaba",
    "sg:classifiers":[
        {
            "category":"Personal",
            "subcategory":"Beauty Salon",
            "type":"Services"
        }
    ],
    "sg:phone":"+61 7 3823 1885",
    "sg:postcode":"4157",
    "sg:province":"QLD",
    "sg:tags":[
        "hairdresser"
    ],
    "wof:name":"Cirocco For Hair",
    "wof:placetype":"venue"
},
  "geometry": {"coordinates":[153.19955444300001,-27.5217685699],"type":"Point"}
}