{
  "type": "Feature",
  "properties": {
    "addr:full":"52 Durham St Bathurst NSW 2795",
    "addr:housenumber":"52",
    "addr:postcode":"2795",
    "addr:street":"Durham St",
    "iso:country":"AU",
    "sg:address":"52 Durham St",
    "sg:city":"Bathurst",
    "sg:classifiers":[
        {
            "category":"Fast Food",
            "type":"Food & Drink"
        }
    ],
    "sg:phone":"+61 2 6332 1221",
    "sg:postcode":"2795",
    "sg:province":"NSW",
    "sg:tags":[
        "away",
        "take"
    ],
    "wof:name":"Eagle Boys Pizza",
    "wof:placetype":"venue"
},
  "geometry": {"coordinates":[149.58502197300001,-33.4172363281],"type":"Point"}
}