{
  "type": "Feature",
  "properties": {
    "iso:country":"AU",
    "sg:address":"40 Cambourne Ave St",
    "sg:city":"Ives",
    "sg:classifiers":[
        {
            "category":"Building & Trades",
            "subcategory":"Landscaping Services",
            "type":"Services"
        }
    ],
    "sg:phone":"+61 2 9449 1437",
    "sg:postcode":"2075",
    "sg:province":"NSW",
    "sg:tags":[
        "consultant"
    ],
    "wof:name":"Pritchett Pty Ltd",
    "wof:placetype":"venue"
},
  "geometry": {"coordinates":[151.181915283,-33.7245178223],"type":"Point"}
}