{
  "type": "Feature",
  "properties": {
    "iso:country":"AU",
    "sg:address":"Suite 1 154 Hampden Rd",
    "sg:city":"Nedlands",
    "sg:classifiers":[
        {
            "category":"Professional",
            "subcategory":"Accounting & Tax Preparation",
            "type":"Services"
        }
    ],
    "sg:phone":"+61 8 6389 2090",
    "sg:postcode":"6009",
    "sg:province":"WA",
    "sg:tags":[
        "accountant",
        "auditor"
    ],
    "wof:name":"Braxford Consultancy Pty Ltd",
    "wof:placetype":"venue"
},
  "geometry": {"coordinates":[115.813622,-31.971685],"type":"Point"}
}