{
  "type": "Feature",
  "properties": {
    "iso:country":"AU",
    "sg:address":"Suite 5/ 11- 15 Florence St",
    "sg:city":"Hornsby",
    "sg:classifiers":[
        {
            "category":"Banks & Credit Unions",
            "subcategory":"Financial Services",
            "type":"Services"
        }
    ],
    "sg:phone":"+61 2 9482 9244",
    "sg:postcode":"2077",
    "sg:province":"NSW",
    "sg:tags":[
        "loan",
        "finance",
        "mortgage"
    ],
    "wof:name":"Brokers Choice Home Loans Pty Ltd",
    "wof:placetype":"venue"
},
  "geometry": {"coordinates":[151.09956359899999,-33.7036972046],"type":"Point"}
}