{
  "type": "Feature",
  "properties": {
    "iso:country":"AU",
    "sg:address":"Suite 1, 130 Argyle St",
    "sg:city":"Camden",
    "sg:classifiers":[
        {
            "category":"Health Services",
            "subcategory":"Doctor",
            "type":"Services"
        }
    ],
    "sg:phone":"+61 2 4655 6999",
    "sg:postcode":"2570",
    "sg:province":"NSW",
    "sg:tags":[
        "medical",
        "practitioner"
    ],
    "wof:name":"Camden Vein & Cosmetic Centre",
    "wof:placetype":"venue"
},
  "geometry": {"coordinates":[150.695404053,-34.0548973083],"type":"Point"}
}