{
  "type": "Feature",
  "properties": {
    "addr:full":"1- 3 Coverlid Pl Melbourne VIC 3000",
    "addr:housenumber":"3",
    "addr:postcode":"3000",
    "addr:street":"Coverlid Pl",
    "iso:country":"AU",
    "sg:address":"1- 3 Coverlid Pl",
    "sg:city":"Melbourne",
    "sg:classifiers":[
        {
            "category":"Personal",
            "subcategory":"Adult",
            "type":"Services"
        }
    ],
    "sg:phone":"+61 3 9663 2993",
    "sg:postcode":"3000",
    "sg:province":"VIC",
    "sg:tags":[
        "entertainment"
    ],
    "wof:name":"Dendy",
    "wof:placetype":"venue"
},
  "geometry": {"coordinates":[144.96833801299999,-37.8121910095],"type":"Point"}
}