{
  "type": "Feature",
  "properties": {
    "iso:country":"AU",
    "sg:address":"17 Thompson St",
    "sg:city":"Charters Towers",
    "sg:classifiers":[
        {
            "category":"Retail",
            "subcategory":"Storage",
            "type":"Services"
        }
    ],
    "sg:phone":"+61 7 4787 2518",
    "sg:postcode":"4820",
    "sg:province":"QLD",
    "wof:name":"Charters Towers Self Storage",
    "wof:placetype":"venue"
},
  "geometry": {"coordinates":[146.25924699999999,-20.093073],"type":"Point"}
}