{
  "type": "Feature",
  "properties": {
    "iso:country":"AU",
    "sg:address":"418 Gympie Rd",
    "sg:city":"Strathpine",
    "sg:classifiers":[
        {
            "category":"Shopping",
            "subcategory":"Bicycles & Sporting Goods",
            "type":"Retail Goods"
        }
    ],
    "sg:phone":"+61 7 3205 4263",
    "sg:postcode":"4500",
    "sg:province":"QLD",
    "sg:tags":[
        "chemical",
        "equipment",
        "pool",
        "swimming"
    ],
    "wof:name":"Irelands Pool Supplies",
    "wof:placetype":"venue"
},
  "geometry": {"coordinates":[152.98843383799999,-27.3024597168],"type":"Point"}
}