{
  "type": "Feature",
  "properties": {
    "addr:full":"12 Dennis St Campbellfield VIC 3061",
    "addr:housenumber":"12",
    "addr:postcode":"3061",
    "addr:street":"Dennis St",
    "iso:country":"AU",
    "sg:address":"12 Dennis St",
    "sg:city":"Campbellfield",
    "sg:classifiers":[
        {
            "category":"Retail",
            "subcategory":"Auto Repair",
            "type":"Services"
        }
    ],
    "sg:phone":"+61 3 9308 0310",
    "sg:postcode":"3061",
    "sg:province":"VIC",
    "sg:tags":[
        "bus",
        "truck"
    ],
    "sg:website":"http://www.glenroyexhaust.com.au",
    "wof:name":"Glenroy Exhaust Centre",
    "wof:placetype":"venue"
},
  "geometry": {"coordinates":[144.94108581500001,-37.6464653015],"type":"Point"}
}