{
  "type": "Feature",
  "properties": {
    "addr:full":"Suite 4/ 1 International Airport Newburn WA 6104",
    "addr:housenumber":"1",
    "addr:postcode":"6104",
    "addr:street":"International Airport",
    "iso:country":"AU",
    "sg:address":"Suite 4/ 1 International Airport",
    "sg:city":"Newburn",
    "sg:classifiers":[
        {
            "category":"Building & Trades",
            "subcategory":"Construction",
            "type":"Services"
        }
    ],
    "sg:phone":"+61 8 9477 5168",
    "sg:postcode":"6104",
    "sg:province":"WA",
    "sg:tags":[
        "bitumen",
        "paving",
        "asphalt"
    ],
    "wof:name":"Workforce International Pty. Ltd.",
    "wof:placetype":"venue"
},
  "geometry": {"coordinates":[115.997909546,-31.9442424774],"type":"Point"}
}