{
  "type": "Feature",
  "properties": {
    "addr:full":"Lv 1/ 8a Blackburn Rd Blackburn VIC 3130",
    "addr:housenumber":"8a",
    "addr:postcode":"3130",
    "addr:street":"Blackburn Rd",
    "iso:country":"AU",
    "sg:address":"Lv 1/ 8a Blackburn Rd",
    "sg:city":"Blackburn",
    "sg:classifiers":[
        {
            "category":"Sports & Exercise",
            "subcategory":"Gym",
            "type":"Entertainment"
        }
    ],
    "sg:phone":"+61 3 9877 1814",
    "sg:postcode":"3130",
    "sg:province":"VIC",
    "sg:tags":[
        "health",
        "fitness"
    ],
    "wof:name":"Curves Blackburn",
    "wof:placetype":"venue"
},
  "geometry": {"coordinates":[145.15286254899999,-37.8199691772],"type":"Point"}
}