{
  "type": "Feature",
  "properties": {
    "iso:country":"AU",
    "sg:address":"95 Elderslie St",
    "sg:city":"Winton",
    "sg:classifiers":[
        {
            "category":"Travel",
            "subcategory":"Hotels & Motels",
            "type":"Entertainment"
        }
    ],
    "sg:phone":"+61 7 4657 1422",
    "sg:postcode":"4735",
    "sg:province":"QLD",
    "wof:name":"Winton Outback Motel",
    "wof:placetype":"venue"
},
  "geometry": {"coordinates":[143.040237,-22.390179],"type":"Point"}
}