{
  "type": "Feature",
  "properties": {
    "addr:full":"52 Cooper Rd Jandakot WA 6164",
    "addr:housenumber":"52",
    "addr:postcode":"6164",
    "addr:street":"Cooper Rd",
    "iso:country":"AU",
    "sg:address":"52 Cooper Rd",
    "sg:city":"Jandakot",
    "sg:classifiers":[
        {
            "category":"Professional",
            "subcategory":"Employment Agencies",
            "type":"Services"
        }
    ],
    "sg:phone":"+61 8 9417 1466",
    "sg:postcode":"6164",
    "sg:province":"WA",
    "sg:tags":[
        "consultant",
        "corrosion"
    ],
    "wof:name":"Submar International",
    "wof:placetype":"venue"
},
  "geometry": {"coordinates":[115.846428,-32.125633],"type":"Point"}
}