{
  "type": "Feature",
  "properties": {
    "addr:full":"11 Randal Crs North Rocks NSW 2151",
    "addr:housenumber":"11",
    "addr:postcode":"2151",
    "addr:street":"Randal Crs",
    "iso:country":"AU",
    "sg:address":"11 Randal Crs",
    "sg:city":"North Rocks",
    "sg:classifiers":[
        {
            "category":"Building & Trades",
            "subcategory":"Construction",
            "type":"Services"
        }
    ],
    "sg:phone":"+61 2 9872 6813",
    "sg:postcode":"2151",
    "sg:province":"NSW",
    "sg:tags":[
        "fencing",
        "contractor"
    ],
    "wof:name":"Aquaguard Pool Safety Net",
    "wof:placetype":"venue"
},
  "geometry": {"coordinates":[151.021286011,-33.7750396729],"type":"Point"}
}