{
  "type": "Feature",
  "properties": {
    "addr:full":"9 Hinkler St Greenwich NSW 2065",
    "addr:housenumber":"9",
    "addr:postcode":"2065",
    "addr:street":"Hinkler St",
    "iso:country":"AU",
    "sg:address":"9 Hinkler St",
    "sg:city":"Greenwich",
    "sg:classifiers":[
        {
            "category":"Professional",
            "subcategory":"Management & Consulting",
            "type":"Services"
        }
    ],
    "sg:phone":"+61 2 9437 5131",
    "sg:postcode":"2065",
    "sg:province":"NSW",
    "sg:tags":[
        "consultant"
    ],
    "wof:name":"Child Care Solutions",
    "wof:placetype":"venue"
},
  "geometry": {"coordinates":[151.181243897,-33.823387146],"type":"Point"}
}