{
  "type": "Feature",
  "properties": {
    "addr:full":"Shop 3, 1051 Pacific Hwy Pymble NSW 2073",
    "addr:housenumber":"shop 3 1051",
    "addr:postcode":"2073",
    "addr:street":"Pacific Hwy",
    "iso:country":"AU",
    "sg:address":"Shop 3, 1051 Pacific Hwy",
    "sg:city":"Pymble",
    "sg:classifiers":[
        {
            "category":"Building & Trades",
            "subcategory":"Equipment Rental",
            "type":"Services"
        }
    ],
    "sg:phone":"+61 2 9988 3778",
    "sg:postcode":"2073",
    "sg:province":"NSW",
    "sg:tags":[
        "fitness"
    ],
    "wof:name":"Fitbiz Exercise Equipment",
    "wof:placetype":"venue"
},
  "geometry": {"coordinates":[151.13984680199999,-33.7425041199],"type":"Point"}
}