{
  "type": "Feature",
  "properties": {
    "addr:full":"34 Moloney Drv Wodonga VIC 3689",
    "addr:housenumber":"34",
    "addr:postcode":"3689",
    "addr:street":"Moloney Drv",
    "iso:country":"AU",
    "sg:address":"34 Moloney Drv",
    "sg:city":"Wodonga",
    "sg:classifiers":[
        {
            "category":"Professional",
            "subcategory":"Engineering",
            "type":"Services"
        }
    ],
    "sg:phone":"+61 2 6056 6271",
    "sg:postcode":"3689",
    "sg:province":"VIC",
    "sg:tags":[
        "engineer"
    ],
    "wof:name":"KVE Structural Steel Fabricators",
    "wof:placetype":"venue"
},
  "geometry": {"coordinates":[146.854309,-36.104172],"type":"Point"}
}