{
  "type": "Feature",
  "properties": {
    "addr:full":"86 Warwick Rd Ipswich QLD 4305",
    "addr:housenumber":"86",
    "addr:postcode":"4305",
    "addr:street":"Warwick Rd",
    "iso:country":"AU",
    "sg:address":"86 Warwick Rd",
    "sg:city":"Ipswich",
    "sg:classifiers":[
        {
            "category":"Travel",
            "subcategory":"Hotels & Motels",
            "type":"Entertainment"
        }
    ],
    "sg:phone":"+61 1800 806 344",
    "sg:postcode":"4305",
    "sg:province":"QLD",
    "wof:name":"Ipswich City Motel",
    "wof:placetype":"venue"
},
  "geometry": {"coordinates":[152.76017761200001,-27.6263370514],"type":"Point"}
}