{
  "type": "Feature",
  "properties": {
    "addr:full":"16 Thornton Crt Bouldercombe QLD 4702",
    "addr:housenumber":"16",
    "addr:postcode":"4702",
    "addr:street":"Thornton Crt",
    "iso:country":"AU",
    "sg:address":"16 Thornton Crt",
    "sg:city":"Bouldercombe",
    "sg:classifiers":[
        {
            "category":"Professional",
            "subcategory":"Engineering",
            "type":"Services"
        }
    ],
    "sg:phone":"+61 7 4934 0661",
    "sg:postcode":"4702",
    "sg:province":"QLD",
    "sg:tags":[
        "consulting",
        "engineer"
    ],
    "wof:name":"Leasing Exploration Legislative Administration",
    "wof:placetype":"venue"
},
  "geometry": {"coordinates":[150.477752686,-23.5492458344],"type":"Point"}
}