{
  "type": "Feature",
  "properties": {
    "iso:country":"AU",
    "sg:address":"58 Middle St",
    "sg:city":"Chinchilla",
    "sg:classifiers":[
        {
            "category":"Professional",
            "subcategory":"Employment Agencies",
            "type":"Services"
        }
    ],
    "sg:phone":"+61 7 4662 7980",
    "sg:postcode":"4413",
    "sg:province":"QLD",
    "sg:tags":[
        "occupational",
        "therapist"
    ],
    "wof:name":"Outback Occupational Therapy Services",
    "wof:placetype":"venue"
},
  "geometry": {"coordinates":[150.62721252399999,-26.7433071136],"type":"Point"}
}