{
  "type": "Feature",
  "properties": {
    "addr:full":"459 Stirling Hwy Cottesloe WA 6011",
    "addr:housenumber":"459",
    "addr:postcode":"6011",
    "addr:street":"Stirling Hwy",
    "iso:country":"AU",
    "sg:address":"459 Stirling Hwy",
    "sg:city":"Cottesloe",
    "sg:classifiers":[
        {
            "category":"Building & Trades",
            "subcategory":"Construction",
            "type":"Services"
        }
    ],
    "sg:phone":"+61 8 9383 2688",
    "sg:postcode":"6011",
    "sg:province":"WA",
    "sg:tags":[
        "contractor"
    ],
    "wof:name":"Icon Architect Designed and Built",
    "wof:placetype":"venue"
},
  "geometry": {"coordinates":[115.760383606,-32.0029335022],"type":"Point"}
}