{
  "type": "Feature",
  "properties": {
    "addr:full":"Level 1, 445 Victoria Ave Chatswood NSW 2067",
    "addr:housenumber":"445",
    "addr:postcode":"2067",
    "addr:street":"Victoria Ave",
    "iso:country":"AU",
    "sg:address":"Level 1, 445 Victoria Ave",
    "sg:city":"Chatswood",
    "sg:classifiers":[
        {
            "category":"Health Services",
            "subcategory":"Doctor",
            "type":"Services"
        }
    ],
    "sg:phone":"+61 2 9411 7700",
    "sg:postcode":"2067",
    "sg:province":"NSW",
    "sg:tags":[
        "medical",
        "practitioner"
    ],
    "wof:name":"Parker David Dr",
    "wof:placetype":"venue"
},
  "geometry": {"coordinates":[151.18255615199999,-33.796245575],"type":"Point"}
}