{
  "type": "Feature",
  "properties": {
    "iso:country":"AU",
    "sg:address":"94 Station Rd",
    "sg:city":"Deer Park",
    "sg:classifiers":[
        {
            "category":"Health Services",
            "subcategory":"Health Practitioner",
            "type":"Services"
        }
    ],
    "sg:phone":"+61 3 9363 0611",
    "sg:postcode":"3023",
    "sg:province":"VIC",
    "sg:tags":[
        "physiotherapist"
    ],
    "wof:name":"Gioskos Steve",
    "wof:placetype":"venue"
},
  "geometry": {"coordinates":[144.775406,-37.76786],"type":"Point"}
}