{
  "type": "Feature",
  "properties": {
    "addr:full":"136 Macquarie Rd Springwood NSW 2777",
    "addr:housenumber":"136",
    "addr:postcode":"2777",
    "addr:street":"Macquarie Rd",
    "iso:country":"AU",
    "sg:address":"136 Macquarie Rd",
    "sg:city":"Springwood",
    "sg:classifiers":[
        {
            "category":"Restaurant",
            "type":"Food & Drink"
        }
    ],
    "sg:phone":"+61 2 4751 2084",
    "sg:postcode":"2777",
    "sg:province":"NSW",
    "wof:name":"Blue Sky Chinese Cuisine",
    "wof:placetype":"venue"
},
  "geometry": {"coordinates":[150.56698608400001,-33.6991500854],"type":"Point"}
}