{
  "type": "Feature",
  "properties": {
    "iso:country":"AU",
    "sg:address":"Shop 1 120 Main Rd East",
    "sg:city":"St Albans",
    "sg:classifiers":[
        {
            "category":"Food & Beverages",
            "subcategory":"Bakery",
            "type":"Retail Goods"
        }
    ],
    "sg:phone":"+61 3 9364 2092",
    "sg:postcode":"3021",
    "sg:province":"VIC",
    "sg:tags":[
        "baker"
    ],
    "wof:name":"St Albans Hotbread",
    "wof:placetype":"venue"
},
  "geometry": {"coordinates":[144.820908,-37.746578],"type":"Point"}
}