{
  "type": "Feature",
  "properties": {
    "addr:full":"47 Green St Maroubra NSW 2035",
    "addr:housenumber":"47",
    "addr:postcode":"2035",
    "addr:street":"Green St",
    "iso:country":"AU",
    "sg:address":"47 Green St",
    "sg:city":"Maroubra",
    "sg:classifiers":[
        {
            "category":"Personal",
            "subcategory":"Massage",
            "type":"Services"
        }
    ],
    "sg:phone":"+61 2 9344 7533",
    "sg:postcode":"2035",
    "sg:province":"NSW",
    "sg:tags":[
        "therapy"
    ],
    "wof:name":"Maroubra Dynamic Physiotherapy Remedial Massage",
    "wof:placetype":"venue"
},
  "geometry": {"coordinates":[151.241577148,-33.9412384033],"type":"Point"}
}