{
  "type": "Feature",
  "properties": {
    "iso:country":"AU",
    "sg:address":"2/ 19- 23 Pittwater Rd",
    "sg:city":"Manly",
    "sg:classifiers":[
        {
            "category":"Health Services",
            "subcategory":"Clinic",
            "type":"Services"
        }
    ],
    "sg:phone":"+61 2 9977 0787",
    "sg:postcode":"2095",
    "sg:province":"NSW",
    "sg:tags":[
        "aromatherapy"
    ],
    "wof:name":"Aromatherapists, International Federation Of",
    "wof:placetype":"venue"
},
  "geometry": {"coordinates":[151.28504943900001,-33.7947807312],"type":"Point"}
}