{
  "type": "Feature",
  "properties": {
    "iso:country":"AU",
    "sg:address":"432 Fussell St",
    "sg:city":"Ballarat",
    "sg:classifiers":[
        {
            "category":"Building & Trades",
            "subcategory":"Construction",
            "type":"Services"
        }
    ],
    "sg:phone":"+61 3 5331 6362",
    "sg:postcode":"3350",
    "sg:province":"VIC",
    "sg:tags":[
        "contractor"
    ],
    "wof:name":"Adriaans Building Contractors Pty Ltd",
    "wof:placetype":"venue"
},
  "geometry": {"coordinates":[143.891266,-37.576614],"type":"Point"}
}