{
  "type": "Feature",
  "properties": {
    "addr:full":"6 Canham Way Greenwood WA 6024",
    "addr:housenumber":"6",
    "addr:postcode":"6024",
    "addr:street":"Canham Way",
    "iso:country":"AU",
    "sg:address":"6 Canham Way",
    "sg:city":"Greenwood",
    "sg:classifiers":[
        {
            "category":"Professional",
            "type":"Services"
        }
    ],
    "sg:phone":"+61 8 9342 4111",
    "sg:postcode":"6024",
    "sg:province":"WA",
    "sg:tags":[
        "transport"
    ],
    "sg:website":"http://www.butkotransport.com.au",
    "wof:name":"Butko Transport Pty Ltd",
    "wof:placetype":"venue"
},
  "geometry": {"coordinates":[115.816108704,-31.8213806152],"type":"Point"}
}