{
  "type": "Feature",
  "properties": {
    "addr:full":"85 East St Rockhampton QLD 4700",
    "addr:housenumber":"85",
    "addr:postcode":"4700",
    "addr:street":"East St",
    "iso:country":"AU",
    "sg:address":"85 East St",
    "sg:city":"Rockhampton",
    "sg:classifiers":[
        {
            "category":"Fast Food",
            "type":"Food & Drink"
        }
    ],
    "sg:phone":"+61 7 4927 5082",
    "sg:postcode":"4700",
    "sg:province":"QLD",
    "sg:tags":[
        "away",
        "take"
    ],
    "wof:name":"Fruit &#039;N&#039; Juice Bar",
    "wof:placetype":"venue"
},
  "geometry": {"coordinates":[150.521240234,-23.3890552521],"type":"Point"}
}