{
  "type": "Feature",
  "properties": {
    "addr:full":"256 Andrew Rd Greenbank QLD 4124",
    "addr:housenumber":"256",
    "addr:postcode":"4124",
    "addr:street":"Andrew Rd",
    "iso:country":"AU",
    "sg:address":"256 Andrew Rd",
    "sg:city":"Greenbank",
    "sg:classifiers":[
        {
            "category":"Retail",
            "subcategory":"Auto Repair",
            "type":"Services"
        }
    ],
    "sg:phone":"+61 7 3297 0466",
    "sg:postcode":"4124",
    "sg:province":"QLD",
    "sg:tags":[
        "engine",
        "reconditioning"
    ],
    "wof:name":"Bexo Motor Works",
    "wof:placetype":"venue"
},
  "geometry": {"coordinates":[153.009674072,-27.7076263428],"type":"Point"}
}