{
  "type": "Feature",
  "properties": {
    "addr:full":"Days Rd Regency Park SA 5010",
    "addr:postcode":"5010",
    "addr:street":"Days Rd",
    "iso:country":"AU",
    "sg:address":"Days Rd",
    "sg:city":"Regency Park",
    "sg:classifiers":[
        {
            "category":"Travel",
            "subcategory":"Hotels & Motels",
            "type":"Entertainment"
        }
    ],
    "sg:phone":"+61 8 8268 6754",
    "sg:postcode":"5010",
    "sg:province":"SA",
    "sg:tags":[
        "accommodation"
    ],
    "wof:name":"Regency Tavern",
    "wof:placetype":"venue"
},
  "geometry": {"coordinates":[138.56573486299999,-34.8580856323],"type":"Point"}
}