{
  "type": "Feature",
  "properties": {
    "iso:country":"AU",
    "sg:address":"Rotherwood Rd",
    "sg:city":"Cassilis",
    "sg:classifiers":[
        {
            "category":"Building & Trades",
            "subcategory":"Landscaping Services",
            "type":"Services"
        }
    ],
    "sg:phone":"+61 2 6376 4625",
    "sg:postcode":"2329",
    "sg:province":"NSW",
    "sg:tags":[
        "grazier"
    ],
    "wof:name":"Yarrawonga Station",
    "wof:placetype":"venue"
},
  "geometry": {"coordinates":[149.96452331500001,-32.000125885],"type":"Point"}
}