{
  "type": "Feature",
  "properties": {
    "addr:full":"Shp18a/ Argyle St Camden NSW 2570",
    "addr:postcode":"2570",
    "addr:street":"Argyle St",
    "iso:country":"AU",
    "sg:address":"Shp18a/ Argyle St",
    "sg:city":"Camden",
    "sg:classifiers":[
        {
            "category":"Retail",
            "subcategory":"Self-service Laundry",
            "type":"Services"
        }
    ],
    "sg:phone":"+61 2 4655 2008",
    "sg:postcode":"2570",
    "sg:province":"NSW",
    "wof:name":"Franzo's Laundromat & Drycleaning",
    "wof:placetype":"venue"
},
  "geometry": {"coordinates":[150.69418335,-34.0552787781],"type":"Point"}
}