{
  "type": "Feature",
  "properties": {
    "addr:full":"Pethick Rd Willunga SA 5172",
    "addr:postcode":"5172",
    "addr:street":"Pethick Rd",
    "iso:country":"AU",
    "sg:address":"Pethick Rd",
    "sg:city":"Willunga",
    "sg:classifiers":[
        {
            "category":"Building & Trades",
            "subcategory":"Cleaning & Sanitation",
            "type":"Services"
        }
    ],
    "sg:phone":"+61 408 068 557",
    "sg:postcode":"5172",
    "sg:province":"SA",
    "sg:tags":[
        "grease",
        "trap"
    ],
    "wof:name":"Compass Liquid Waste",
    "wof:placetype":"venue"
},
  "geometry": {"coordinates":[138.534713745,-35.268825531],"type":"Point"}
}