{
  "type": "Feature",
  "properties": {
    "addr:full":"24 Hanby St Brighton VIC 3186",
    "addr:housenumber":"24",
    "addr:postcode":"3186",
    "addr:street":"Hanby St",
    "iso:country":"AU",
    "sg:address":"24 Hanby St",
    "sg:city":"Brighton",
    "sg:classifiers":[
        {
            "category":"Building & Trades",
            "subcategory":"Construction",
            "type":"Services"
        }
    ],
    "sg:phone":"+61 3 9593 2272",
    "sg:postcode":"3186",
    "sg:province":"VIC",
    "sg:tags":[
        "contractor"
    ],
    "wof:name":"Alder Building Pty Ltd",
    "wof:placetype":"venue"
},
  "geometry": {"coordinates":[145.001190186,-37.9238777161],"type":"Point"}
}