{
  "type": "Feature",
  "properties": {
    "addr:full":"29 Scrivener St Warwick Farm NSW 2170",
    "addr:housenumber":"29",
    "addr:postcode":"2170",
    "addr:street":"Scrivener St",
    "iso:country":"AU",
    "sg:address":"29 Scrivener St",
    "sg:city":"Warwick Farm",
    "sg:classifiers":[
        {
            "category":"Retail",
            "subcategory":"Auto Repair",
            "type":"Services"
        }
    ],
    "sg:phone":"+61 2 9822 7911",
    "sg:postcode":"2170",
    "sg:province":"NSW",
    "sg:tags":[
        "beater",
        "painter",
        "panel"
    ],
    "wof:name":"A Won Smash Repairs",
    "wof:placetype":"venue"
},
  "geometry": {"coordinates":[150.93760681099999,-33.9189414978],"type":"Point"}
}