{
  "type": "Feature",
  "properties": {
    "addr:full":"172 Victoria Ave Chatswood NSW 2067",
    "addr:housenumber":"172",
    "addr:postcode":"2067",
    "addr:street":"Victoria Ave",
    "iso:country":"AU",
    "sg:address":"172 Victoria Ave",
    "sg:city":"Chatswood",
    "sg:classifiers":[
        {
            "category":"Restaurant",
            "type":"Food & Drink"
        }
    ],
    "sg:phone":"+61 2 9413 4306",
    "sg:postcode":"2067",
    "sg:province":"NSW",
    "wof:name":"Casa Bella Italian Restaurant & Pizzeria",
    "wof:placetype":"venue"
},
  "geometry": {"coordinates":[151.19221496599999,-33.793586731],"type":"Point"}
}