{
  "type": "Feature",
  "properties": {
    "iso:country":"AU",
    "sg:address":"55 Main St",
    "sg:city":"Blacktown",
    "sg:classifiers":[
        {
            "category":"Health Services",
            "subcategory":"Dentist",
            "type":"Services"
        }
    ],
    "sg:phone":"+61 2 9622 4225",
    "sg:postcode":"2148",
    "sg:province":"NSW",
    "wof:name":"Russ B",
    "wof:placetype":"venue"
},
  "geometry": {"coordinates":[150.90878295900001,-33.7695236206],"type":"Point"}
}