{
  "type": "Feature",
  "properties": {
    "addr:full":"Sports Clinic Western Ave Sydney University NSW 2006",
    "addr:postcode":"2006",
    "addr:street":"Western Ave",
    "iso:country":"AU",
    "sg:address":"Sports Clinic Western Ave",
    "sg:city":"Sydney University",
    "sg:classifiers":[
        {
            "category":"Health Services",
            "subcategory":"Doctor",
            "type":"Services"
        }
    ],
    "sg:phone":"+61 2 9351 8118",
    "sg:postcode":"2006",
    "sg:province":"NSW",
    "sg:tags":[
        "medical",
        "practitioner"
    ],
    "wof:name":"Castricum Adam Dr",
    "wof:placetype":"venue"
},
  "geometry": {"coordinates":[151.18692016599999,-33.8879203796],"type":"Point"}
}