{
  "type": "Feature",
  "properties": {
    "addr:full":"Bruce Hwy Bloomsbury QLD 4799",
    "addr:postcode":"4799",
    "addr:street":"Bruce Hwy",
    "iso:country":"AU",
    "sg:address":"Bruce Hwy",
    "sg:city":"Bloomsbury",
    "sg:classifiers":[
        {
            "category":"Autos & Motor Vehicles",
            "subcategory":"Fuel & Gas Station",
            "type":"Retail Goods"
        }
    ],
    "sg:phone":"+61 7 4947 5739",
    "sg:postcode":"4799",
    "sg:province":"QLD",
    "wof:name":"Mobil Bloomsbury",
    "wof:placetype":"venue"
},
  "geometry": {"coordinates":[148.59573364299999,-20.7038993835],"type":"Point"}
}