{
  "type": "Feature",
  "properties": {
    "addr:full":"76 Elderslie St Winton QLD 4735",
    "addr:housenumber":"76",
    "addr:postcode":"4735",
    "addr:street":"Elderslie St",
    "iso:country":"AU",
    "sg:address":"76 Elderslie St",
    "sg:city":"Winton",
    "sg:classifiers":[
        {
            "category":"Food & Beverages",
            "subcategory":"Groceries & Convenience Stores",
            "type":"Retail Goods"
        }
    ],
    "sg:phone":"+61 7 4657 1763",
    "sg:postcode":"4735",
    "sg:province":"QLD",
    "wof:name":"Winton General Store",
    "wof:placetype":"venue"
},
  "geometry": {"coordinates":[143.040436,-22.390207],"type":"Point"}
}