{
  "type": "Feature",
  "properties": {
    "iso:country":"AU",
    "sg:address":"Ground Floor, 634 Main St",
    "sg:city":"Kangaroo Point",
    "sg:classifiers":[
        {
            "category":"Health Services",
            "subcategory":"Doctor",
            "type":"Services"
        }
    ],
    "sg:phone":"+61 1300 786 078",
    "sg:postcode":"4169",
    "sg:province":"QLD",
    "sg:tags":[
        "medical",
        "practitioner"
    ],
    "wof:name":"Williams Linda",
    "wof:placetype":"venue"
},
  "geometry": {"coordinates":[153.035919189,-27.4796390533],"type":"Point"}
}