{
  "type": "Feature",
  "properties": {
    "iso:country":"AU",
    "sg:address":"86 Ascot Rd",
    "sg:city":"Bowral",
    "sg:classifiers":[
        {
            "category":"Health Services",
            "subcategory":"Health Practitioner",
            "type":"Services"
        }
    ],
    "sg:phone":"+61 2 4296 1489",
    "sg:postcode":"2576",
    "sg:province":"NSW",
    "sg:tags":[
        "naturopath"
    ],
    "wof:name":"Advanced Remedial Therapies",
    "wof:placetype":"venue"
},
  "geometry": {"coordinates":[150.43544006400001,-34.4876098633],"type":"Point"}
}