{
  "type": "Feature",
  "properties": {
    "iso:country":"AU",
    "sg:address":"7 Hudson Rd",
    "sg:city":"Albion",
    "sg:classifiers":[
        {
            "category":"Autos & Motor Vehicles",
            "subcategory":"Auto Supplies",
            "type":"Retail Goods"
        }
    ],
    "sg:phone":"+61 7 3262 4377",
    "sg:postcode":"4010",
    "sg:province":"QLD",
    "sg:tags":[
        "part",
        "cycles",
        "accessory"
    ],
    "wof:name":"Roadworthies For Bikes",
    "wof:placetype":"venue"
},
  "geometry": {"coordinates":[153.04086303700001,-27.4324684143],"type":"Point"}
}