{
  "type": "Feature",
  "properties": {
    "iso:country":"AU",
    "sg:address":"1st Floor 35 Park St",
    "sg:city":"Glenbrook",
    "sg:classifiers":[
        {
            "category":"Health Services",
            "subcategory":"Dentist",
            "type":"Services"
        }
    ],
    "sg:phone":"+61 2 4739 2509",
    "sg:postcode":"2773",
    "sg:province":"NSW",
    "wof:name":"Robinson Glen L",
    "wof:placetype":"venue"
},
  "geometry": {"coordinates":[150.62245178200001,-33.7668418884],"type":"Point"}
}