{
  "type": "Feature",
  "properties": {
    "addr:full":"115a Pittwater Rd Hunters Hill NSW 2110",
    "addr:housenumber":"115a",
    "addr:postcode":"2110",
    "addr:street":"Pittwater Rd",
    "iso:country":"AU",
    "sg:address":"115a Pittwater Rd",
    "sg:city":"Hunters Hill",
    "sg:classifiers":[
        {
            "category":"Real Estate",
            "subcategory":"Real Estate Services",
            "type":"Services"
        }
    ],
    "sg:phone":"+61 2 9816 5233",
    "sg:postcode":"2110",
    "sg:province":"NSW",
    "sg:tags":[
        "consultant",
        "property"
    ],
    "wof:name":"Diamond Industrial & Commercial P/L",
    "wof:placetype":"venue"
},
  "geometry": {"coordinates":[151.13713073700001,-33.8192253113],"type":"Point"}
}