{
  "type": "Feature",
  "properties": {
    "iso:country":"AU",
    "sg:address":"236 Coogee Bay Rd",
    "sg:city":"Coogee",
    "sg:classifiers":[
        {
            "category":"Fast Food",
            "type":"Food & Drink"
        }
    ],
    "sg:phone":"+61 2 9315 8137",
    "sg:postcode":"2034",
    "sg:province":"NSW",
    "sg:tags":[
        "away",
        "take"
    ],
    "wof:name":"Charcoal Charlie's",
    "wof:placetype":"venue"
},
  "geometry": {"coordinates":[151.25541687,-33.9204711914],"type":"Point"}
}