{
  "type": "Feature",
  "properties": {
    "addr:full":"Vulcan St Moruya NSW 2537",
    "addr:postcode":"2537",
    "addr:street":"Vulcan St",
    "iso:country":"AU",
    "sg:address":"Vulcan St",
    "sg:city":"Moruya",
    "sg:classifiers":[
        {
            "category":"Professional",
            "subcategory":"Employment Agencies",
            "type":"Services"
        }
    ],
    "sg:phone":"+61 2 4474 1365",
    "sg:postcode":"2537",
    "sg:province":"NSW",
    "sg:tags":[
        "hire",
        "labour",
        "contractor"
    ],
    "wof:name":"South East Regional Training & Enterprise Centre",
    "wof:placetype":"venue"
},
  "geometry": {"coordinates":[150.08018493599999,-35.9132499695],"type":"Point"}
}