{
  "type": "Feature",
  "properties": {
    "iso:country":"AU",
    "sg:address":"Olive St",
    "sg:city":"Mandurama",
    "sg:classifiers":[
        {
            "category":"Farming",
            "subcategory":"Farm & Veterinary Services",
            "type":"Manufacturing & Wholesale Goods"
        }
    ],
    "sg:phone":"+61 2 6367 5174",
    "sg:postcode":"2792",
    "sg:province":"NSW",
    "sg:tags":[
        "shearing",
        "contractor"
    ],
    "wof:name":"Andy Duggan",
    "wof:placetype":"venue"
},
  "geometry": {"coordinates":[148.98121643100001,-33.6480712891],"type":"Point"}
}