{
  "type": "Feature",
  "properties": {
    "iso:country":"AU",
    "sg:address":"Senior Citizens Centre 159",
    "sg:city":"Shaftsbury Eastwood",
    "sg:classifiers":[
        {
            "category":"Arena",
            "subcategory":"Sports Club",
            "type":"Entertainment"
        }
    ],
    "sg:phone":"+61 2 9639 7771",
    "sg:postcode":"2122",
    "sg:province":"NSW",
    "sg:tags":[
        "defence",
        "supply",
        "self",
        "instruction",
        "martial art"
    ],
    "wof:name":"Taekwondo World",
    "wof:placetype":"venue"
},
  "geometry": {"coordinates":[151.07717895499999,-33.7917366028],"type":"Point"}
}