{
  "type": "Feature",
  "properties": {
    "addr:full":"19 Halley Rd Balcatta WA 6021",
    "addr:housenumber":"19",
    "addr:postcode":"6021",
    "addr:street":"Halley Rd",
    "iso:country":"AU",
    "sg:address":"19 Halley Rd",
    "sg:city":"Balcatta",
    "sg:classifiers":[
        {
            "category":"Retail",
            "subcategory":"Repair Shop",
            "type":"Services"
        }
    ],
    "sg:phone":"+61 8 9344 6222",
    "sg:postcode":"6021",
    "sg:province":"WA",
    "sg:tags":[
        "cleaner",
        "part",
        "vacuum"
    ],
    "wof:name":"Electron",
    "wof:placetype":"venue"
},
  "geometry": {"coordinates":[115.82659149200001,-31.8608207703],"type":"Point"}
}