{
  "type": "Feature",
  "properties": {
    "iso:country":"AU",
    "sg:address":"Dream Haven Crt",
    "sg:city":"Epping",
    "sg:classifiers":[
        {
            "category":"Manufacturing",
            "subcategory":"Metals",
            "type":"Manufacturing & Wholesale Goods"
        }
    ],
    "sg:phone":"+61 3 9401 4088",
    "sg:postcode":"3076",
    "sg:province":"VIC",
    "sg:tags":[
        "steel",
        "fabricator",
        "mfrs"
    ],
    "wof:name":"Epping Structural Steel",
    "wof:placetype":"venue"
},
  "geometry": {"coordinates":[145.01902770999999,-37.6446342468],"type":"Point"}
}