{
  "type": "Feature",
  "properties": {
    "addr:full":"U5/ 171 Newton Rd Wetherill Park NSW 2164",
    "addr:housenumber":"171",
    "addr:postcode":"2164",
    "addr:street":"U5 /;Newton Rd",
    "iso:country":"AU",
    "sg:address":"U5/ 171 Newton Rd",
    "sg:city":"Wetherill Park",
    "sg:classifiers":[
        {
            "category":"Retail",
            "subcategory":"Auto Repair",
            "type":"Services"
        }
    ],
    "sg:phone":"+61 2 9756 3895",
    "sg:postcode":"2164",
    "sg:province":"NSW",
    "sg:tags":[
        "car",
        "restoration",
        "supply"
    ],
    "wof:name":"Repair & Resoration Services Pty Ltd",
    "wof:placetype":"venue"
},
  "geometry": {"coordinates":[150.89146423299999,-33.8389358521],"type":"Point"}
}