{
  "type": "Feature",
  "properties": {
    "iso:country":"AU",
    "sg:address":"56 Davenport St",
    "sg:city":"Southport",
    "sg:classifiers":[
        {
            "category":"Banks & Credit Unions",
            "subcategory":"Financial Services",
            "type":"Services"
        }
    ],
    "sg:phone":"+61 7 5531 3911",
    "sg:postcode":"4215",
    "sg:province":"QLD",
    "sg:tags":[
        "planning"
    ],
    "wof:name":"Total Financial Services (Aust) Pty Ltd",
    "wof:placetype":"venue"
},
  "geometry": {"coordinates":[153.411911011,-27.9666919708],"type":"Point"}
}