{
  "type": "Feature",
  "properties": {
    "iso:country":"AU",
    "sg:address":"822 Batar Creek Rd",
    "sg:city":"Kendall",
    "sg:classifiers":[
        {
            "category":"Shopping",
            "subcategory":"Hobbies, Toys, & Games",
            "type":"Retail Goods"
        }
    ],
    "sg:phone":"+61 2 6559 7586",
    "sg:postcode":"2439",
    "sg:province":"NSW",
    "sg:tags":[
        "farmer"
    ],
    "wof:name":"Kendall Rabbit Farm",
    "wof:placetype":"venue"
},
  "geometry": {"coordinates":[152.652344,-31.677883],"type":"Point"}
}