{
  "type": "Feature",
  "properties": {
    "addr:full":"903 Princes Hwy Engadine NSW 2233",
    "addr:housenumber":"903",
    "addr:postcode":"2233",
    "addr:street":"Princes Hwy",
    "iso:country":"AU",
    "sg:address":"903 Princes Hwy",
    "sg:city":"Engadine",
    "sg:classifiers":[
        {
            "category":"Retail",
            "subcategory":"Veterinary Services",
            "type":"Services"
        }
    ],
    "sg:phone":"+61 2 9548 3345",
    "sg:postcode":"2233",
    "sg:province":"NSW",
    "sg:tags":[
        "surgeon"
    ],
    "wof:name":"Engadine Veterinary Hospital Cattery",
    "wof:placetype":"venue"
},
  "geometry": {"coordinates":[151.02345275900001,-34.0609703064],"type":"Point"}
}