{
  "type": "Feature",
  "properties": {
    "iso:country":"AU",
    "sg:address":"228 HUME St",
    "sg:city":"Toowoomba",
    "sg:classifiers":[
        {
            "category":"Professional",
            "subcategory":"Accounting & Tax Preparation",
            "type":"Services"
        }
    ],
    "sg:phone":"+61 7 4638 5232",
    "sg:postcode":"4350",
    "sg:province":"QLD",
    "sg:tags":[
        "accountant",
        "auditor"
    ],
    "wof:name":"Lynda Steffens",
    "wof:placetype":"venue"
},
  "geometry": {"coordinates":[151.956085,-27.571852],"type":"Point"}
}