{
  "type": "Feature",
  "properties": {
    "addr:full":"219 Springwood Rd Springwood QLD 4127",
    "addr:housenumber":"219",
    "addr:postcode":"4127",
    "addr:street":"Springwood Rd",
    "iso:country":"AU",
    "sg:address":"219 Springwood Rd",
    "sg:city":"Springwood",
    "sg:classifiers":[
        {
            "category":"Utilities",
            "subcategory":"Electric",
            "type":"Services"
        }
    ],
    "sg:phone":"+61 7 3208 3608",
    "sg:postcode":"4127",
    "sg:province":"QLD",
    "sg:tags":[
        "electrical",
        "contractor"
    ],
    "wof:name":"Allan's Electrical & Refrigeration Service",
    "wof:placetype":"venue"
},
  "geometry": {"coordinates":[153.13636779800001,-27.6149692535],"type":"Point"}
}