{
  "type": "Feature",
  "properties": {
    "addr:full":"696 Maleny-Montville Rd Maleny QLD 4552",
    "addr:housenumber":"696",
    "addr:postcode":"4552",
    "addr:street":"Maleny-Montville Rd",
    "iso:country":"AU",
    "sg:address":"696 Maleny-Montville Rd",
    "sg:city":"Maleny",
    "sg:classifiers":[
        {
            "category":"Building & Trades",
            "subcategory":"Construction",
            "type":"Services"
        }
    ],
    "sg:phone":"+61 7 5494 2351",
    "sg:postcode":"4552",
    "sg:province":"QLD",
    "sg:tags":[
        "contractor"
    ],
    "wof:name":"Burgum B J",
    "wof:placetype":"venue"
},
  "geometry": {"coordinates":[152.88624572800001,-26.7634315491],"type":"Point"}
}