{
  "type": "Feature",
  "properties": {
    "iso:country":"AU",
    "sg:address":"McDougall Building Ellerslie Rd",
    "sg:city":"Battery Point",
    "sg:classifiers":[
        {
            "category":"Organizations",
            "subcategory":"Community Association",
            "type":"Services"
        }
    ],
    "sg:phone":"+61 1800 645 130",
    "sg:postcode":"7004",
    "sg:province":"TAS",
    "sg:tags":[
        "organisation",
        "family",
        "welfare"
    ],
    "wof:name":"Asthma Foundation Of Tasmania",
    "wof:placetype":"venue"
},
  "geometry": {"coordinates":[147.328659058,-42.8887672424],"type":"Point"}
}