{
  "type": "Feature",
  "properties": {
    "addr:full":"22 Young St Gympie QLD 4570",
    "addr:housenumber":"22",
    "addr:postcode":"4570",
    "addr:street":"Young St",
    "iso:country":"AU",
    "sg:address":"22 Young St",
    "sg:city":"Gympie",
    "sg:classifiers":[
        {
            "category":"Professional",
            "subcategory":"Accounting & Tax Preparation",
            "type":"Services"
        }
    ],
    "sg:phone":"+61 7 5482 4644",
    "sg:postcode":"4570",
    "sg:province":"QLD",
    "sg:tags":[
        "consultant",
        "taxation"
    ],
    "wof:name":"Michael Palmer",
    "wof:placetype":"venue"
},
  "geometry": {"coordinates":[152.66302490199999,-26.1910190582],"type":"Point"}
}