{
  "type": "Feature",
  "properties": {
    "iso:country":"AU",
    "sg:address":"5 Heatherbrae Pl",
    "sg:city":"Castle Hill",
    "sg:classifiers":[
        {
            "category":"Retail",
            "subcategory":"Repair Shop",
            "type":"Services"
        }
    ],
    "sg:phone":"+61 2 9634 2917",
    "sg:postcode":"2154",
    "sg:province":"NSW",
    "sg:tags":[
        "machine",
        "repairs",
        "part",
        "dryer",
        "washing"
    ],
    "wof:name":"Appliance Repair Specialists",
    "wof:placetype":"venue"
},
  "geometry": {"coordinates":[151.01010131800001,-33.7276496887],"type":"Point"}
}