{
  "type": "Feature",
  "properties": {
    "addr:full":"5 Dundas Rd Inglewood WA 6052",
    "addr:housenumber":"5",
    "addr:postcode":"6052",
    "addr:street":"Dundas Rd",
    "iso:country":"AU",
    "sg:address":"5 Dundas Rd",
    "sg:city":"Inglewood",
    "sg:classifiers":[
        {
            "category":"Health Services",
            "subcategory":"Health Practitioner",
            "type":"Services"
        }
    ],
    "sg:phone":"+61 8 9371 2429",
    "sg:postcode":"6052",
    "sg:province":"WA",
    "sg:tags":[
        "pathologist",
        "speech"
    ],
    "wof:name":"Tattletales",
    "wof:placetype":"venue"
},
  "geometry": {"coordinates":[115.88683319099999,-31.9195842743],"type":"Point"}
}