{
  "type": "Feature",
  "properties": {
    "iso:country":"AU",
    "sg:address":"21 Barclay St",
    "sg:city":"Heywood",
    "sg:classifiers":[
        {
            "category":"Travel",
            "subcategory":"Hostel",
            "type":"Entertainment"
        }
    ],
    "sg:phone":"+61 3 5527 0555",
    "sg:postcode":"3304",
    "sg:province":"VIC",
    "sg:tags":[
        "home"
    ],
    "wof:name":"Heywood Rural Health",
    "wof:placetype":"venue"
},
  "geometry": {"coordinates":[141.62513732900001,-38.1366958618],"type":"Point"}
}