{
  "type": "Feature",
  "properties": {
    "addr:full":"3/ 2 St Johns Ave Gordon NSW 2072",
    "addr:housenumber":"/ 2",
    "addr:postcode":"2072",
    "addr:street":"St Johns Ave",
    "iso:country":"AU",
    "sg:address":"3/ 2 St Johns Ave",
    "sg:city":"Gordon",
    "sg:classifiers":[
        {
            "category":"Health Services",
            "subcategory":"Dentist",
            "type":"Services"
        }
    ],
    "sg:phone":"+61 2 9498 8290",
    "sg:postcode":"2072",
    "sg:province":"NSW",
    "wof:name":"Chien David Dr",
    "wof:placetype":"venue"
},
  "geometry": {"coordinates":[151.153900147,-33.7563438416],"type":"Point"}
}