{
  "type": "Feature",
  "properties": {
    "addr:full":"Sunnyholt Rd Blacktown NSW 2148",
    "addr:postcode":"2148",
    "addr:street":"Sunnyholt Rd",
    "iso:country":"AU",
    "sg:address":"Sunnyholt Rd",
    "sg:city":"Blacktown",
    "sg:classifiers":[
        {
            "category":"Autos & Motor Vehicles",
            "subcategory":"Auto Supplies",
            "type":"Retail Goods"
        }
    ],
    "sg:phone":"+61 2 9421 0666",
    "sg:postcode":"2148",
    "sg:province":"NSW",
    "sg:tags":[
        "part",
        "cycles",
        "accessory"
    ],
    "wof:name":"Team Moto Motorcycles",
    "wof:placetype":"venue"
},
  "geometry": {"coordinates":[150.91163635300001,-33.7718315125],"type":"Point"}
}