{
  "type": "Feature",
  "properties": {
    "iso:country":"AU",
    "sg:address":"7 Eildon Crt",
    "sg:city":"Meadow Heights",
    "sg:classifiers":[
        {
            "category":"Building & Trades",
            "subcategory":"Cleaning & Sanitation",
            "type":"Services"
        }
    ],
    "sg:phone":"+61 3 9333 3433",
    "sg:postcode":"3048",
    "sg:province":"VIC",
    "sg:tags":[
        "industrial",
        "commercial",
        "contractor"
    ],
    "wof:name":"Jendi Cleaning Services",
    "wof:placetype":"venue"
},
  "geometry": {"coordinates":[144.920975,-37.645821],"type":"Point"}
}