{
  "type": "Feature",
  "properties": {
    "iso:country":"AU",
    "sg:address":"7- 15 Mimosa St",
    "sg:city":"Oatley",
    "sg:classifiers":[
        {
            "category":"Health Services",
            "subcategory":"Nursing And Care Facility",
            "type":"Services"
        }
    ],
    "sg:phone":"+61 2 9580 8946",
    "sg:postcode":"2223",
    "sg:province":"NSW",
    "sg:tags":[
        "home"
    ],
    "wof:name":"Hillcrest Nursing Home",
    "wof:placetype":"venue"
},
  "geometry": {"coordinates":[151.07713317899999,-33.9857711792],"type":"Point"}
}