{
  "type": "Feature",
  "properties": {
    "iso:country":"AU",
    "sg:address":"35 Anstruther Rd",
    "sg:city":"Mandurah",
    "sg:classifiers":[
        {
            "category":"Personal",
            "subcategory":"Massage",
            "type":"Services"
        }
    ],
    "sg:phone":"+61 8 9535 2690",
    "sg:postcode":"6210",
    "sg:province":"WA",
    "sg:tags":[
        "therapy"
    ],
    "wof:name":"Peel Back Care Clinic",
    "wof:placetype":"venue"
},
  "geometry": {"coordinates":[115.73268899999999,-32.529774],"type":"Point"}
}