{
  "type": "Feature",
  "properties": {
    "addr:full":"Shop 5 Concourse Arcade 15 Dumaresq St Campbelltown NSW 2560",
    "addr:housenumber":"shop 5;15",
    "addr:postcode":"2560",
    "addr:street":"Concourse Arcade;St",
    "iso:country":"AU",
    "sg:address":"Shop 5 Concourse Arcade 15 Dumaresq St",
    "sg:city":"Campbelltown",
    "sg:classifiers":[
        {
            "category":"Retail",
            "subcategory":"Self-service Laundry",
            "type":"Services"
        }
    ],
    "sg:phone":"+61 2 4626 8620",
    "sg:postcode":"2560",
    "sg:province":"NSW",
    "wof:name":"Dumaresq Street Laundromat & Linen Service",
    "wof:placetype":"venue"
},
  "geometry": {"coordinates":[150.81199645999999,-34.0670204163],"type":"Point"}
}