{
  "type": "Feature",
  "properties": {
    "addr:full":"16 Corsican St Frankston VIC 3199",
    "addr:housenumber":"16",
    "addr:postcode":"3199",
    "addr:street":"Corsican St",
    "iso:country":"AU",
    "sg:address":"16 Corsican St",
    "sg:city":"Frankston",
    "sg:classifiers":[
        {
            "category":"Professional",
            "subcategory":"Printing & Photocopies",
            "type":"Services"
        }
    ],
    "sg:phone":"+61 3 9776 9646",
    "sg:postcode":"3199",
    "sg:province":"VIC",
    "sg:tags":[
        "rubber",
        "stamp",
        "metal"
    ],
    "wof:name":"Peter Bradley",
    "wof:placetype":"venue"
},
  "geometry": {"coordinates":[145.15440368599999,-38.1171989441],"type":"Point"}
}