{
  "type": "Feature",
  "properties": {
    "iso:country":"AU",
    "sg:address":"253 Argent St",
    "sg:city":"Broken Hill",
    "sg:classifiers":[
        {
            "category":"Insurance",
            "subcategory":"Hazard Insurance",
            "type":"Services"
        }
    ],
    "sg:phone":"+61 8 8087 8011",
    "sg:postcode":"2880",
    "sg:province":"NSW",
    "sg:tags":[
        "fire",
        "accident",
        "marine"
    ],
    "wof:name":"McLoughlin Glen L & Associates",
    "wof:placetype":"venue"
},
  "geometry": {"coordinates":[141.46441650400001,-31.9591522217],"type":"Point"}
}