{
  "type": "Feature",
  "properties": {
    "iso:country":"AU",
    "sg:address":"4 Macquarie Ave",
    "sg:city":"Penrith",
    "sg:classifiers":[
        {
            "category":"Professional",
            "subcategory":"Engineering",
            "type":"Services"
        }
    ],
    "sg:phone":"+61 2 4731 3833",
    "sg:postcode":"2750",
    "sg:province":"NSW",
    "sg:tags":[
        "consulting",
        "engineer"
    ],
    "wof:name":"Kneebone Beretta & Hall Pty Ltd",
    "wof:placetype":"venue"
},
  "geometry": {"coordinates":[150.937423706,-33.7100944519],"type":"Point"}
}