{
  "type": "Feature",
  "properties": {
    "iso:country":"AU",
    "sg:address":"19 Bent St",
    "sg:city":"Greenwich",
    "sg:classifiers":[
        {
            "category":"Personal",
            "subcategory":"Hair Removal",
            "type":"Services"
        }
    ],
    "sg:phone":"+61 2 9438 3936",
    "sg:postcode":"2065",
    "sg:province":"NSW",
    "wof:name":"Irving Pamela Electrolysis",
    "wof:placetype":"venue"
},
  "geometry": {"coordinates":[151.18289184599999,-33.8314666748],"type":"Point"}
}