{
  "type": "Feature",
  "properties": {
    "iso:country":"AU",
    "sg:address":"9 Bedford St",
    "sg:city":"Invermay",
    "sg:classifiers":[
        {
            "category":"Building & Trades",
            "subcategory":"Locksmith",
            "type":"Services"
        }
    ],
    "sg:phone":"+61 1300 559 627",
    "sg:postcode":"7248",
    "sg:province":"TAS",
    "sg:tags":[
        "equipment",
        "operating",
        "door",
        "gate"
    ],
    "wof:name":"CBS Tasmania Pty Ltd",
    "wof:placetype":"venue"
},
  "geometry": {"coordinates":[147.137405395,-41.4275550842],"type":"Point"}
}