{
  "type": "Feature",
  "properties": {
    "iso:country":"AU",
    "sg:address":"423 King Georges Rd",
    "sg:city":"Beverly Hills",
    "sg:classifiers":[
        {
            "category":"Health Services",
            "subcategory":"Chiropractor",
            "type":"Services"
        }
    ],
    "sg:phone":"+61 2 9570 1478",
    "sg:postcode":"2209",
    "sg:province":"NSW",
    "wof:name":"Stevenson B J",
    "wof:placetype":"venue"
},
  "geometry": {"coordinates":[151.080734,-33.949657],"type":"Point"}
}