{
  "type": "Feature",
  "properties": {
    "addr:full":"103 Cleveland St Sydney NSW 2000",
    "addr:housenumber":"103",
    "addr:postcode":"2000",
    "addr:street":"Cleveland St",
    "iso:country":"AU",
    "sg:address":"103 Cleveland St",
    "sg:city":"Sydney",
    "sg:classifiers":[
        {
            "category":"Travel",
            "subcategory":"Hotels & Motels",
            "type":"Entertainment"
        }
    ],
    "sg:phone":"+61 2 9690 1200",
    "sg:postcode":"2000",
    "sg:province":"NSW",
    "sg:tags":[
        "accommodation"
    ],
    "wof:name":"Random Bar",
    "wof:placetype":"venue"
},
  "geometry": {"coordinates":[151.196533203,-33.8884124756],"type":"Point"}
}