{
  "type": "Feature",
  "properties": {
    "iso:country":"AU",
    "sg:address":"Rose River Rd",
    "sg:city":"Cheshunt",
    "sg:classifiers":[
        {
            "category":"Farming",
            "subcategory":"Vineyard",
            "type":"Manufacturing & Wholesale Goods"
        }
    ],
    "sg:phone":"+61 3 5729 8333",
    "sg:postcode":"3678",
    "sg:province":"VIC",
    "sg:tags":[
        "winery"
    ],
    "wof:name":"Carson R B",
    "wof:placetype":"venue"
},
  "geometry": {"coordinates":[146.432250977,-36.7992897034],"type":"Point"}
}