{
  "type": "Feature",
  "properties": {
    "addr:full":"12 Settlers St Carindale QLD 4152",
    "addr:housenumber":"12",
    "addr:postcode":"4152",
    "addr:street":"Settlers St",
    "iso:country":"AU",
    "sg:address":"12 Settlers St",
    "sg:city":"Carindale",
    "sg:classifiers":[
        {
            "category":"Personal",
            "subcategory":"Beauty Salon",
            "type":"Services"
        }
    ],
    "sg:phone":"+61 404 832 601",
    "sg:postcode":"4152",
    "sg:province":"QLD",
    "sg:tags":[
        "supply",
        "artist",
        "make-up"
    ],
    "wof:name":"Lachlan Wood Promotions",
    "wof:placetype":"venue"
},
  "geometry": {"coordinates":[153.116699219,-27.5002746582],"type":"Point"}
}