{
  "type": "Feature",
  "properties": {
    "addr:full":"12 Springside St Rozelle NSW 2039",
    "addr:housenumber":"12",
    "addr:postcode":"2039",
    "addr:street":"Springside St",
    "iso:country":"AU",
    "sg:address":"12 Springside St",
    "sg:city":"Rozelle",
    "sg:classifiers":[
        {
            "category":"Utilities",
            "subcategory":"Electric",
            "type":"Services"
        }
    ],
    "sg:phone":"+61 409 045 554",
    "sg:postcode":"2039",
    "sg:province":"NSW",
    "sg:tags":[
        "electrical",
        "contractor"
    ],
    "wof:name":"Emmanuel's Electrical Services",
    "wof:placetype":"venue"
},
  "geometry": {"coordinates":[151.16700744600001,-33.8628082275],"type":"Point"}
}