{
  "type": "Feature",
  "properties": {
    "addr:full":"3 Military Rd Avondale Heights VIC 3034",
    "addr:housenumber":"3",
    "addr:postcode":"3034",
    "addr:street":"Military Rd",
    "iso:country":"AU",
    "sg:address":"3 Military Rd",
    "sg:city":"Avondale Heights",
    "sg:classifiers":[
        {
            "category":"Food & Beverages",
            "subcategory":"Bakery",
            "type":"Retail Goods"
        }
    ],
    "sg:phone":"+61 3 9318 1377",
    "sg:postcode":"3034",
    "sg:province":"VIC",
    "sg:tags":[
        "cake",
        "shop",
        "pastry"
    ],
    "wof:name":"Cheesecake Shop The",
    "wof:placetype":"venue"
},
  "geometry": {"coordinates":[144.865387,-37.770439],"type":"Point"}
}