{
  "type": "Feature",
  "properties": {
    "addr:full":"33 Yando St Greensborough VIC 3088",
    "addr:housenumber":"33",
    "addr:postcode":"3088",
    "addr:street":"Yando St",
    "iso:country":"AU",
    "sg:address":"33 Yando St",
    "sg:city":"Greensborough",
    "sg:classifiers":[
        {
            "category":"Health Services",
            "subcategory":"Health Practitioner",
            "type":"Services"
        }
    ],
    "sg:phone":"+61 3 9444 6747",
    "sg:postcode":"3088",
    "sg:province":"VIC",
    "sg:tags":[
        "hypnotherapy"
    ],
    "wof:name":"My Hypnotherapist",
    "wof:placetype":"venue"
},
  "geometry": {"coordinates":[145.097000122,-37.697177887],"type":"Point"}
}