{
  "type": "Feature",
  "properties": {
    "addr:full":"7 Marymac Crt Narangba QLD 4504",
    "addr:housenumber":"7",
    "addr:postcode":"4504",
    "addr:street":"Marymac Crt",
    "iso:country":"AU",
    "sg:address":"7 Marymac Crt",
    "sg:city":"Narangba",
    "sg:classifiers":[
        {
            "category":"Education",
            "subcategory":"Special Training",
            "type":"Public Place"
        }
    ],
    "sg:phone":"+61 7 3886 9400",
    "sg:postcode":"4504",
    "sg:province":"QLD",
    "sg:tags":[
        "development"
    ],
    "wof:name":"GJR Consulting",
    "wof:placetype":"venue"
},
  "geometry": {"coordinates":[152.93870544399999,-27.1887969971],"type":"Point"}
}