{
  "type": "Feature",
  "properties": {
    "iso:country":"AU",
    "sg:address":"2 Sandalwood Drv",
    "sg:city":"Goondiwindi",
    "sg:classifiers":[
        {
            "category":"Farming",
            "subcategory":"Farm & Veterinary Services",
            "type":"Manufacturing & Wholesale Goods"
        }
    ],
    "sg:phone":"+61 7 4671 3626",
    "sg:postcode":"4390",
    "sg:province":"QLD",
    "sg:tags":[
        "contracting"
    ],
    "wof:name":"Barry O&#039;Byrne Contracting",
    "wof:placetype":"venue"
},
  "geometry": {"coordinates":[150.283294678,-28.5338935852],"type":"Point"}
}