{
  "type": "Feature",
  "properties": {
    "iso:country":"AU",
    "sg:address":"Craig St",
    "sg:city":"Tarlee",
    "sg:classifiers":[
        {
            "category":"Education",
            "subcategory":"School",
            "type":"Public Place"
        }
    ],
    "sg:phone":"+61 8 8528 5301",
    "sg:postcode":"5411",
    "sg:province":"SA",
    "sg:tags":[
        "state",
        "except",
        "nsw"
    ],
    "wof:name":"Tarlee Primary School",
    "wof:placetype":"venue"
},
  "geometry": {"coordinates":[138.77166748100001,-34.2744216919],"type":"Point"}
}