{
  "type": "Feature",
  "properties": {
    "iso:country":"AU",
    "sg:address":"PO Box 655",
    "sg:city":"Spring Hill",
    "sg:classifiers":[
        {
            "category":"Social Services",
            "subcategory":"Child Care",
            "type":"Services"
        }
    ],
    "sg:phone":"+61 7 3839 5883",
    "sg:postcode":"4004",
    "sg:province":"QLD",
    "sg:tags":[
        "childbirth"
    ],
    "wof:name":"Home Midwifery Association (Qld) Inc",
    "wof:placetype":"venue"
},
  "geometry": {"coordinates":[153.02444457999999,-27.4608707428],"type":"Point"}
}