{
  "type": "Feature",
  "properties": {
    "addr:full":"Triple Cee Shopping Centre Kingston Rd Woodridge QLD 4114",
    "addr:postcode":"4114",
    "addr:street":"Kingston Rd",
    "iso:country":"AU",
    "sg:address":"Triple Cee Shopping Centre Kingston Rd",
    "sg:city":"Woodridge",
    "sg:classifiers":[
        {
            "category":"Shopping",
            "subcategory":"Clothing, Apparel, & Fashions",
            "type":"Retail Goods"
        }
    ],
    "sg:phone":"+61 7 3808 8100",
    "sg:postcode":"4114",
    "sg:province":"QLD",
    "sg:tags":[
        "lady",
        "wear"
    ],
    "wof:name":"Supre Ladies Clothing",
    "wof:placetype":"venue"
},
  "geometry": {"coordinates":[153.11700439399999,-27.6256561279],"type":"Point"}
}