{
  "type": "Feature",
  "properties": {
    "addr:full":"46 Springfield Rd Blackburn VIC 3130",
    "addr:housenumber":"46",
    "addr:postcode":"3130",
    "addr:street":"Springfield Rd",
    "iso:country":"AU",
    "sg:address":"46 Springfield Rd",
    "sg:city":"Blackburn",
    "sg:classifiers":[
        {
            "category":"Freight",
            "type":"Transportation"
        }
    ],
    "sg:phone":"+61 3 9877 1418",
    "sg:postcode":"3130",
    "sg:province":"VIC",
    "sg:tags":[
        "transport",
        "refrigerated"
    ],
    "wof:name":"Jones W G & Sons Pty Ltd",
    "wof:placetype":"venue"
},
  "geometry": {"coordinates":[145.146682739,-37.8099136353],"type":"Point"}
}