{
  "type": "Feature",
  "properties": {
    "iso:country":"AU",
    "sg:address":"Shop 1/ 24 West St",
    "sg:city":"Mt Isa",
    "sg:classifiers":[
        {
            "category":"Arts & Performance",
            "subcategory":"Art Gallery",
            "type":"Entertainment"
        }
    ],
    "sg:phone":"+61 7 4743 4787",
    "sg:postcode":"4825",
    "sg:province":"QLD",
    "wof:name":"Outback Ceramics",
    "wof:placetype":"venue"
},
  "geometry": {"coordinates":[139.490616,-20.725588],"type":"Point"}
}