{
  "type": "Feature",
  "properties": {
    "iso:country":"AU",
    "sg:address":"Eyre Hwy",
    "sg:city":"Balladonia",
    "sg:classifiers":[
        {
            "category":"Travel",
            "subcategory":"Hotels & Motels",
            "type":"Entertainment"
        }
    ],
    "sg:phone":"+61 8 9039 3453",
    "sg:postcode":"6443",
    "sg:province":"WA",
    "wof:name":"Balladonia Hotel Motel",
    "wof:placetype":"venue"
},
  "geometry": {"coordinates":[123.619132996,-32.3544540405],"type":"Point"}
}