{
  "type": "Feature",
  "properties": {
    "addr:full":"444 Barry Rd Broadmeadows VIC 3047",
    "addr:housenumber":"444",
    "addr:postcode":"3047",
    "addr:street":"Barry Rd",
    "iso:country":"AU",
    "sg:address":"444 Barry Rd",
    "sg:city":"Broadmeadows",
    "sg:classifiers":[
        {
            "category":"Government",
            "subcategory":"Fire Station",
            "type":"Public Place"
        }
    ],
    "sg:phone":"+61 3 9302 2855",
    "sg:postcode":"3047",
    "sg:province":"VIC",
    "sg:tags":[
        "spring",
        "shock",
        "absorbers",
        "suspension"
    ],
    "wof:name":"Boronia Towbars",
    "wof:placetype":"venue"
},
  "geometry": {"coordinates":[144.937988281,-37.6654129028],"type":"Point"}
}