{
  "type": "Feature",
  "properties": {
    "iso:country":"AU",
    "sg:address":"119 Willoughby Rd",
    "sg:city":"Crows Nest",
    "sg:classifiers":[
        {
            "category":"Banks & Credit Unions",
            "subcategory":"Financial Services",
            "type":"Services"
        }
    ],
    "sg:phone":"+61 2 9956 3835",
    "sg:postcode":"2065",
    "sg:province":"NSW",
    "sg:tags":[
        "planning"
    ],
    "wof:name":"SIMFIN Pty Ltd",
    "wof:placetype":"venue"
},
  "geometry": {"coordinates":[151.201080322,-33.8226051331],"type":"Point"}
}