{
  "type": "Feature",
  "properties": {
    "addr:full":"12 Wood St South Geelong VIC 3220",
    "addr:housenumber":"12",
    "addr:postcode":"3220",
    "addr:street":"Wood St",
    "iso:country":"AU",
    "sg:address":"12 Wood St",
    "sg:city":"South Geelong",
    "sg:classifiers":[
        {
            "category":"Government",
            "subcategory":"Fire Station",
            "type":"Public Place"
        }
    ],
    "sg:phone":"+61 3 5221 1374",
    "sg:postcode":"3220",
    "sg:province":"VIC",
    "sg:tags":[
        "equipment",
        "protection",
        "consultant"
    ],
    "wof:name":"Elliots Fire And Safety Services",
    "wof:placetype":"venue"
},
  "geometry": {"coordinates":[144.36901900000001,-38.168064],"type":"Point"}
}