{
  "type": "Feature",
  "properties": {
    "iso:country":"AU",
    "sg:address":"Unit 4/ 1 Carnegie Pl",
    "sg:city":"Blacktown",
    "sg:classifiers":[
        {
            "category":"Professional",
            "type":"Services"
        }
    ],
    "sg:phone":"+61 2 9671 6002",
    "sg:postcode":"2148",
    "sg:province":"NSW",
    "sg:tags":[
        "courier"
    ],
    "wof:name":"K & J Transport Contractors",
    "wof:placetype":"venue"
},
  "geometry": {"coordinates":[150.90623474099999,-33.7542953491],"type":"Point"}
}