{
  "type": "Feature",
  "properties": {
    "iso:country":"AU",
    "sg:address":"320 Benalla Rd",
    "sg:city":"Shepparton",
    "sg:classifiers":[
        {
            "category":"Retail",
            "subcategory":"Auto Repair",
            "type":"Services"
        }
    ],
    "sg:phone":"+61 3 5820 7800",
    "sg:postcode":"3630",
    "sg:province":"VIC",
    "sg:tags":[
        "bus",
        "truck"
    ],
    "wof:name":"Hartwigs",
    "wof:placetype":"venue"
},
  "geometry": {"coordinates":[145.42852783199999,-36.3873329163],"type":"Point"}
}