{
  "type": "Feature",
  "properties": {
    "addr:full":"20 Elizabeth St Inglewood QLD 4387",
    "addr:housenumber":"20",
    "addr:postcode":"4387",
    "addr:street":"Elizabeth St",
    "iso:country":"AU",
    "sg:address":"20 Elizabeth St",
    "sg:city":"Inglewood",
    "sg:classifiers":[
        {
            "category":"Autos & Motor Vehicles",
            "subcategory":"Auto Supplies",
            "type":"Retail Goods"
        }
    ],
    "sg:phone":"+61 7 4652 1533",
    "sg:postcode":"4387",
    "sg:province":"QLD",
    "sg:tags":[
        "tyre"
    ],
    "wof:name":"Inglewood Tyre Centre",
    "wof:placetype":"venue"
},
  "geometry": {"coordinates":[151.08137500000001,-28.413973],"type":"Point"}
}