{
  "type": "Feature",
  "properties": {
    "addr:full":"6 Tabard Ave Brompton SA 5007",
    "addr:housenumber":"6",
    "addr:postcode":"5007",
    "addr:street":"Tabard Ave",
    "iso:country":"AU",
    "sg:address":"6 Tabard Ave",
    "sg:city":"Brompton",
    "sg:classifiers":[
        {
            "category":"Wholesale",
            "subcategory":"Non-durable Goods",
            "type":"Manufacturing & Wholesale Goods"
        }
    ],
    "sg:phone":"+61 8 8340 8553",
    "sg:postcode":"5007",
    "sg:province":"SA",
    "sg:tags":[
        "wholesaler",
        "craft",
        "mfrs"
    ],
    "wof:name":"Bentley Agencies",
    "wof:placetype":"venue"
},
  "geometry": {"coordinates":[138.574676514,-34.8953933716],"type":"Point"}
}