{
  "type": "Feature",
  "properties": {
    "addr:full":"Unit 7, 605 Kingsford Smith Drv Hamilton QLD 4007",
    "addr:housenumber":"605",
    "addr:postcode":"4007",
    "addr:street":"Kingsford Smith Drv",
    "iso:country":"AU",
    "sg:address":"Unit 7, 605 Kingsford Smith Drv",
    "sg:city":"Hamilton",
    "sg:classifiers":[
        {
            "category":"Professional",
            "subcategory":"Computer Services",
            "type":"Services"
        }
    ],
    "sg:phone":"+61 7 3268 6811",
    "sg:postcode":"4007",
    "sg:province":"QLD",
    "sg:tags":[
        "equipment",
        "networking",
        "installation"
    ],
    "wof:name":"Chloride Hytek Pty Ltd",
    "wof:placetype":"venue"
},
  "geometry": {"coordinates":[153.07565299999999,-27.435644],"type":"Point"}
}