{
  "type": "Feature",
  "properties": {
    "iso:country":"AU",
    "sg:address":"186A Burke St",
    "sg:city":"Glen Innes",
    "sg:classifiers":[
        {
            "category":"Health Services",
            "subcategory":"Chiropractor",
            "type":"Services"
        }
    ],
    "sg:phone":"+61 2 6732 5788",
    "sg:postcode":"2370",
    "sg:province":"NSW",
    "wof:name":"Thompson Wendy",
    "wof:placetype":"venue"
},
  "geometry": {"coordinates":[151.736602783,-29.7390785217],"type":"Point"}
}