{
  "type": "Feature",
  "properties": {
    "addr:full":"28 Baume Crs McKellar ACT 2617",
    "addr:housenumber":"28",
    "addr:postcode":"2617",
    "addr:street":"Baume Crs",
    "iso:country":"AU",
    "sg:address":"28 Baume Crs",
    "sg:city":"McKellar",
    "sg:classifiers":[
        {
            "category":"Home & Garden",
            "subcategory":"Carpets & Floor Coverings",
            "type":"Retail Goods"
        }
    ],
    "sg:phone":"+61 413 139 391",
    "sg:postcode":"2617",
    "sg:province":"ACT",
    "sg:tags":[
        "tile",
        "wall"
    ],
    "wof:name":"MKs Tiling",
    "wof:placetype":"venue"
},
  "geometry": {"coordinates":[149.073776245,-35.2174797058],"type":"Point"}
}