{
  "type": "Feature",
  "properties": {
    "addr:full":"PO Box 1745 Hervey Bay QLD 4655",
    "addr:postcode":"4655",
    "iso:country":"AU",
    "sg:address":"PO Box 1745",
    "sg:city":"Hervey Bay",
    "sg:classifiers":[
        {
            "category":"Industrial Area",
            "type":"Public Place"
        }
    ],
    "sg:phone":"+61 7 4124 6060",
    "sg:postcode":"4655",
    "sg:province":"QLD",
    "sg:tags":[
        "rural",
        "shed"
    ],
    "sg:website":"http://www.commericalconstructions.com.au",
    "wof:name":"Commerical Constructions Hervey Bay",
    "wof:placetype":"venue"
},
  "geometry": {"coordinates":[152.84141500000001,-25.288765],"type":"Point"}
}