{
  "type": "Feature",
  "properties": {
    "addr:full":"4 Linley St Dandenong VIC 3175",
    "addr:housenumber":"4",
    "addr:postcode":"3175",
    "addr:street":"Linley St",
    "iso:country":"AU",
    "sg:address":"4 Linley St",
    "sg:city":"Dandenong",
    "sg:classifiers":[
        {
            "category":"Retail",
            "subcategory":"Auto Repair",
            "type":"Services"
        }
    ],
    "sg:phone":"+61 3 9792 3558",
    "sg:postcode":"3175",
    "sg:province":"VIC",
    "sg:tags":[
        "repairer",
        "motor",
        "engineer"
    ],
    "wof:name":"Right Tune Motors",
    "wof:placetype":"venue"
},
  "geometry": {"coordinates":[145.22613525400001,-38.0000038147],"type":"Point"}
}