{
  "type": "Feature",
  "properties": {
    "addr:full":"Shop 1E 366 Geelong Rd Footscray West VIC 3012",
    "addr:housenumber":"1e",
    "addr:postcode":"366;3012",
    "addr:street":"Geelong Rd",
    "iso:country":"AU",
    "sg:address":"Shop 1E 366 Geelong Rd",
    "sg:city":"Footscray West",
    "sg:classifiers":[
        {
            "category":"Shopping",
            "subcategory":"Music",
            "type":"Retail Goods"
        }
    ],
    "sg:phone":"+61 3 9689 0600",
    "sg:postcode":"3012",
    "sg:province":"VIC",
    "sg:tags":[
        "store"
    ],
    "wof:name":"A-Creative CD Solution",
    "wof:placetype":"venue"
},
  "geometry": {"coordinates":[144.87413024899999,-37.8081665039],"type":"Point"}
}