{
  "type": "Feature",
  "properties": {
    "addr:full":"Suite C, 222 Church St Richmond VIC 3121",
    "addr:housenumber":"222",
    "addr:postcode":"3121",
    "addr:street":"C;Church St",
    "iso:country":"AU",
    "sg:address":"Suite C, 222 Church St",
    "sg:city":"Richmond",
    "sg:classifiers":[
        {
            "category":"Utilities",
            "subcategory":"Refuse",
            "type":"Services"
        }
    ],
    "sg:phone":"+61 3 9427 7045",
    "sg:postcode":"3121",
    "sg:province":"VIC",
    "sg:tags":[
        "boiler"
    ],
    "wof:name":"Thermogenics Australia",
    "wof:placetype":"venue"
},
  "geometry": {"coordinates":[144.99913024899999,-37.8178443909],"type":"Point"}
}