{
  "type": "Feature",
  "properties": {
    "addr:full":"15 Liddelow St Kenwick WA 6107",
    "addr:housenumber":"15",
    "addr:postcode":"6107",
    "addr:street":"Liddelow St",
    "iso:country":"AU",
    "sg:address":"15 Liddelow St",
    "sg:city":"Kenwick",
    "sg:classifiers":[
        {
            "category":"Wholesale",
            "subcategory":"Scrap",
            "type":"Manufacturing & Wholesale Goods"
        }
    ],
    "sg:phone":"+61 8 9397 7888",
    "sg:postcode":"6107",
    "sg:province":"WA",
    "sg:tags":[
        "merchant",
        "metal"
    ],
    "wof:name":"Bulk Metal Traders Australia",
    "wof:placetype":"venue"
},
  "geometry": {"coordinates":[115.970466614,-32.0421981812],"type":"Point"}
}