{
  "type": "Feature",
  "properties": {
    "addr:full":"PO Box 631 Brighton SA 5048",
    "addr:postcode":"5048",
    "iso:country":"AU",
    "sg:address":"PO Box 631",
    "sg:city":"Brighton",
    "sg:classifiers":[
        {
            "category":"Communications",
            "subcategory":"News Services",
            "type":"Services"
        }
    ],
    "sg:phone":"+61 1300 667 650",
    "sg:postcode":"5048",
    "sg:province":"SA",
    "sg:tags":[
        "information",
        "tourist",
        "attractions"
    ],
    "wof:name":"Prime Mini Tours",
    "wof:placetype":"venue"
},
  "geometry": {"coordinates":[138.51779199999999,-35.01717],"type":"Point"}
}