{
  "type": "Feature",
  "properties": {
    "addr:full":"202 Boundary Rd Oakville NSW 2765",
    "addr:housenumber":"202",
    "addr:postcode":"2765",
    "addr:street":"Boundary Rd",
    "iso:country":"AU",
    "sg:address":"202 Boundary Rd",
    "sg:city":"Oakville",
    "sg:classifiers":[
        {
            "category":"Building & Trades",
            "subcategory":"Landscaping Services",
            "type":"Services"
        }
    ],
    "sg:phone":"+61 411 727 481",
    "sg:postcode":"2765",
    "sg:province":"NSW",
    "sg:tags":[
        "designer",
        "landscape",
        "contractor"
    ],
    "wof:name":"Westscape Landscaping",
    "wof:placetype":"venue"
},
  "geometry": {"coordinates":[150.90257263199999,-33.6141166687],"type":"Point"}
}