{
  "type": "Feature",
  "properties": {
    "addr:full":"1/29 Victoria Hwy Katherine NT 0850",
    "addr:housenumber":"/ 29",
    "addr:postcode":"nt 0850",
    "addr:street":"Victoria Hwy",
    "iso:country":"AU",
    "sg:address":"1/29 Victoria Hwy",
    "sg:city":"Katherine",
    "sg:classifiers":[
        {
            "category":"Building & Trades",
            "subcategory":"Construction",
            "type":"Services"
        }
    ],
    "sg:phone":"+61 419 033 443",
    "sg:postcode":"0850",
    "sg:province":"NT",
    "sg:tags":[
        "contractor"
    ],
    "wof:name":"J & G Constructions Pty Ltd",
    "wof:placetype":"venue"
},
  "geometry": {"coordinates":[132.25993299999999,-14.468114],"type":"Point"}
}