{
  "type": "Feature",
  "properties": {
    "iso:country":"AU",
    "sg:address":"29 Murray St",
    "sg:city":"Pinjarra",
    "sg:classifiers":[
        {
            "category":"Health Services",
            "subcategory":"Health Practitioner",
            "type":"Services"
        }
    ],
    "sg:phone":"+61 8 9531 3045",
    "sg:postcode":"6208",
    "sg:province":"WA",
    "sg:tags":[
        "physiotherapist"
    ],
    "wof:name":"Murray Physiotherapy Clinic",
    "wof:placetype":"venue"
},
  "geometry": {"coordinates":[115.873459,-32.627468],"type":"Point"}
}