{
  "type": "Feature",
  "properties": {
    "addr:full":"6 May Rd Toorak VIC 3142",
    "addr:housenumber":"6",
    "addr:postcode":"3142",
    "addr:street":"May Rd",
    "iso:country":"AU",
    "sg:address":"6 May Rd",
    "sg:city":"Toorak",
    "sg:classifiers":[
        {
            "category":"Communications",
            "subcategory":"News Services",
            "type":"Services"
        }
    ],
    "sg:phone":"+61 3 9827 6944",
    "sg:postcode":"3142",
    "sg:province":"VIC",
    "sg:tags":[
        "information",
        "tourist",
        "attractions"
    ],
    "wof:name":"Caroline Davies Garden Tours",
    "wof:placetype":"venue"
},
  "geometry": {"coordinates":[145.00367736800001,-37.8472938538],"type":"Point"}
}