{
  "type": "Feature",
  "properties": {
    "addr:full":"1 Moree Rd Warialda NSW 2402",
    "addr:housenumber":"1",
    "addr:postcode":"2402",
    "addr:street":"Moree Rd",
    "iso:country":"AU",
    "sg:address":"1 Moree Rd",
    "sg:city":"Warialda",
    "sg:classifiers":[
        {
            "category":"Building & Trades",
            "subcategory":"Construction",
            "type":"Services"
        }
    ],
    "sg:phone":"+61 2 6729 0122",
    "sg:postcode":"2402",
    "sg:province":"NSW",
    "sg:tags":[
        "earth",
        "excavating",
        "moving",
        "contractor"
    ],
    "wof:name":"Bow & Co Bobcat & Mini Excavator Hire",
    "wof:placetype":"venue"
},
  "geometry": {"coordinates":[150.57289123499999,-29.5426692963],"type":"Point"}
}