{
  "type": "Feature",
  "properties": {
    "iso:country":"AU",
    "sg:address":"100 Fitzgerald Rd",
    "sg:city":"Bena",
    "sg:classifiers":[
        {
            "category":"Shopping",
            "subcategory":"Musical Instruments",
            "type":"Retail Goods"
        }
    ],
    "sg:phone":"+61 3 5657 2282",
    "sg:postcode":"3946",
    "sg:province":"VIC",
    "sg:tags":[
        "musician",
        "agent"
    ],
    "wof:name":"Frank Garners New Orleans Jazz Gents",
    "wof:placetype":"venue"
},
  "geometry": {"coordinates":[145.75840759299999,-38.4296035767],"type":"Point"}
}