{
  "type": "Feature",
  "properties": {
    "addr:full":"Newland St Bondi Junction NSW 2022",
    "addr:postcode":"2022",
    "addr:street":"Newland St",
    "iso:country":"AU",
    "sg:address":"Newland St",
    "sg:city":"Bondi Junction",
    "sg:classifiers":[
        {
            "category":"Social Services",
            "subcategory":"Child Care",
            "type":"Services"
        }
    ],
    "sg:phone":"+61 2 9386 9200",
    "sg:postcode":"2022",
    "sg:province":"NSW",
    "wof:name":"Waverley Child Care",
    "wof:placetype":"venue"
},
  "geometry": {"coordinates":[151.24720764200001,-33.8928337097],"type":"Point"}
}