{
  "type": "Feature",
  "properties": {
    "addr:full":"15 Flushcombe St Blacktown NSW 2148",
    "addr:housenumber":"15",
    "addr:postcode":"2148",
    "addr:street":"Flushcombe St",
    "iso:country":"AU",
    "sg:address":"15 Flushcombe St",
    "sg:city":"Blacktown",
    "sg:classifiers":[
        {
            "category":"Real Estate",
            "subcategory":"Developer",
            "type":"Services"
        }
    ],
    "sg:phone":"+61 2 9621 3900",
    "sg:postcode":"2148",
    "sg:province":"NSW",
    "sg:tags":[
        "development"
    ],
    "sg:website":"http://www.raywhite.com/nsw/blacktown",
    "wof:name":"Ray White Blacktown",
    "wof:placetype":"venue"
},
  "geometry": {"coordinates":[150.90554809599999,-33.7907905579],"type":"Point"}
}