{
  "type": "Feature",
  "properties": {
    "iso:country":"AU",
    "sg:address":"Nicholson St",
    "sg:city":"Balmain East",
    "sg:classifiers":[
        {
            "category":"Education",
            "subcategory":"School",
            "type":"Public Place"
        }
    ],
    "sg:phone":"+61 2 9810 2863",
    "sg:postcode":"2041",
    "sg:province":"NSW",
    "sg:tags":[
        "state",
        "-",
        "nsw"
    ],
    "wof:name":"Nicholson Street Public School",
    "wof:placetype":"venue"
},
  "geometry": {"coordinates":[151.193115,-33.856609],"type":"Point"}
}