{
  "type": "Feature",
  "properties": {
    "iso:country":"AU",
    "sg:address":"Shop 2 87 Railway St",
    "sg:city":"Corrimal",
    "sg:classifiers":[
        {
            "category":"Health Services",
            "subcategory":"Dentist",
            "type":"Services"
        }
    ],
    "sg:phone":"+61 1300 132 228",
    "sg:postcode":"2518",
    "sg:province":"NSW",
    "wof:name":"Van Vuuren Chris Dr",
    "wof:placetype":"venue"
},
  "geometry": {"coordinates":[150.895859,-34.373161],"type":"Point"}
}