{
  "type": "Feature",
  "properties": {
    "addr:full":"184 Adderley St Auburn NSW 2144",
    "addr:housenumber":"184",
    "addr:postcode":"2144",
    "addr:street":"Adderley St",
    "iso:country":"AU",
    "sg:address":"184 Adderley St",
    "sg:city":"Auburn",
    "sg:classifiers":[
        {
            "category":"Recreation",
            "type":"Entertainment"
        }
    ],
    "sg:phone":"+61 2 9737 8330",
    "sg:postcode":"2144",
    "sg:province":"NSW",
    "sg:tags":[
        "supply",
        "outdoor",
        "adventure",
        "activity"
    ],
    "wof:name":"Adventure Equipment",
    "wof:placetype":"venue"
},
  "geometry": {"coordinates":[151.03103637699999,-33.8368263245],"type":"Point"}
}