{
  "type": "Feature",
  "properties": {
    "addr:full":"Pacific Private Clinic, Suite 5 , Level 5, Southport QLD 4215",
    "addr:postcode":"4215",
    "iso:country":"AU",
    "sg:address":"Pacific Private Clinic, Suite 5",
    "sg:city":", Level 5, Southport",
    "sg:classifiers":[
        {
            "category":"Health Services",
            "subcategory":"Doctor",
            "type":"Services"
        }
    ],
    "sg:phone":"+61 408 264 699",
    "sg:postcode":"4215",
    "sg:province":"QLD",
    "sg:tags":[
        "medical",
        "practitioner"
    ],
    "wof:name":"Wilson Roger",
    "wof:placetype":"venue"
},
  "geometry": {"coordinates":[153.415557861,-27.9655303955],"type":"Point"}
}