{
  "type": "Feature",
  "properties": {
    "addr:full":"6 Congo Crt Roxburgh Park VIC 3064",
    "addr:housenumber":"6",
    "addr:postcode":"3064",
    "addr:street":"Congo Crt",
    "iso:country":"AU",
    "sg:address":"6 Congo Crt",
    "sg:city":"Roxburgh Park",
    "sg:classifiers":[
        {
            "category":"Manufacturing",
            "subcategory":"Motor Vehicles & Parts",
            "type":"Manufacturing & Wholesale Goods"
        }
    ],
    "sg:phone":"+61 1300 661 171",
    "sg:postcode":"3064",
    "sg:province":"VIC",
    "sg:tags":[
        "replacement"
    ],
    "wof:name":"A.S.P. Rubber Industries",
    "wof:placetype":"venue"
},
  "geometry": {"coordinates":[144.93635559099999,-37.6149864197],"type":"Point"}
}