{
  "type": "Feature",
  "properties": {
    "iso:country":"AU",
    "sg:address":"420 Upper Cornwall St",
    "sg:city":"Coorparoo",
    "sg:classifiers":[
        {
            "category":"Personal",
            "subcategory":"Tattoo Parlor",
            "type":"Services"
        }
    ],
    "sg:phone":"+61 7 3397 8839",
    "sg:postcode":"4151",
    "sg:province":"QLD",
    "sg:tags":[
        "resume"
    ],
    "wof:name":"Resumes Plus",
    "wof:placetype":"venue"
},
  "geometry": {"coordinates":[153.05450439399999,-27.5050182343],"type":"Point"}
}