{
  "type": "Feature",
  "properties": {
    "addr:full":"Basket Range Rd Uraidla SA 5142",
    "addr:postcode":"5142",
    "addr:street":"Basket Range Rd",
    "iso:country":"AU",
    "sg:address":"Basket Range Rd",
    "sg:city":"Uraidla",
    "sg:classifiers":[
        {
            "category":"Building & Trades",
            "subcategory":"Landscaping Services",
            "type":"Services"
        }
    ],
    "sg:phone":"+61 8 8390 1296",
    "sg:postcode":"5142",
    "sg:province":"SA",
    "sg:tags":[
        "stump",
        "tree",
        "felling",
        "removal"
    ],
    "wof:name":"Hunter Neil",
    "wof:placetype":"venue"
},
  "geometry": {"coordinates":[138.74603300000001,-34.957008],"type":"Point"}
}