{
  "type": "Feature",
  "properties": {
    "iso:country":"AU",
    "sg:address":"455 Congupna East Rd",
    "sg:city":"Congupna",
    "sg:classifiers":[
        {
            "category":"Retail",
            "subcategory":"Auto Repair",
            "type":"Services"
        }
    ],
    "sg:phone":"+61 3 5829 9312",
    "sg:postcode":"3633",
    "sg:province":"VIC",
    "sg:tags":[
        "repairer",
        "motor",
        "engineer"
    ],
    "wof:name":"Drum Vince & Ann",
    "wof:placetype":"venue"
},
  "geometry": {"coordinates":[145.48440551799999,-36.2991523743],"type":"Point"}
}