{
  "type": "Feature",
  "properties": {
    "iso:country":"AU",
    "sg:address":"142 Coode St",
    "sg:city":"South Perth",
    "sg:classifiers":[
        {
            "category":"Autos & Motor Vehicles",
            "subcategory":"Fuel & Gas Station",
            "type":"Retail Goods"
        }
    ],
    "sg:phone":"+61 8 9367 5097",
    "sg:postcode":"6151",
    "sg:province":"WA",
    "wof:name":"Shell Co Of Aust Ltd The",
    "wof:placetype":"venue"
},
  "geometry": {"coordinates":[115.86232,-31.988386],"type":"Point"}
}