{
  "type": "Feature",
  "properties": {
    "addr:full":"PO Box 689 Seymour VIC 3660",
    "addr:postcode":"3660",
    "iso:country":"AU",
    "sg:address":"PO Box 689",
    "sg:city":"Seymour",
    "sg:classifiers":[
        {
            "category":"Building & Trades",
            "subcategory":"Cleaning & Sanitation",
            "type":"Services"
        }
    ],
    "sg:phone":"+61 3 5794 2956",
    "sg:postcode":"3660",
    "sg:province":"VIC",
    "sg:tags":[
        "industrial",
        "commercial",
        "contractor"
    ],
    "wof:name":"Dean Brown",
    "wof:placetype":"venue"
},
  "geometry": {"coordinates":[145.14083862300001,-37.0149497986],"type":"Point"}
}