{
  "type": "Feature",
  "properties": {
    "addr:full":"PO Box 914 Mittagong NSW 2575",
    "addr:postcode":"2575",
    "iso:country":"AU",
    "sg:address":"PO Box 914",
    "sg:city":"Mittagong",
    "sg:classifiers":[
        {
            "category":"Home & Garden",
            "subcategory":"Building Materials",
            "type":"Retail Goods"
        }
    ],
    "sg:phone":"+61 2 4889 4560",
    "sg:postcode":"2575",
    "sg:province":"NSW",
    "sg:tags":[
        "shutter",
        "roller",
        "grille"
    ],
    "wof:name":"Kennedy Garage Doors",
    "wof:placetype":"venue"
},
  "geometry": {"coordinates":[150.44688415499999,-34.4510002136],"type":"Point"}
}