{
  "type": "Feature",
  "properties": {
    "iso:country":"AU",
    "sg:address":"254 Wardell Rd",
    "sg:city":"Marrickville",
    "sg:classifiers":[
        {
            "category":"Food & Beverages",
            "subcategory":"Liquor & Beverages",
            "type":"Retail Goods"
        }
    ],
    "sg:phone":"+61 2 9558 5341",
    "sg:postcode":"2204",
    "sg:province":"NSW",
    "sg:tags":[
        "store"
    ],
    "wof:name":"Wardell Liquor Supply",
    "wof:placetype":"venue"
},
  "geometry": {"coordinates":[151.144913,-33.907139],"type":"Point"}
}