{
  "type": "Feature",
  "properties": {
    "iso:country":"AU",
    "sg:address":"115 Sparks Rd",
    "sg:city":"Woongarrah",
    "sg:classifiers":[
        {
            "category":"Health Services",
            "subcategory":"Doctor",
            "type":"Services"
        }
    ],
    "sg:phone":"+61 2 4393 4200",
    "sg:postcode":"2259",
    "sg:province":"NSW",
    "sg:tags":[
        "medical",
        "practitioner"
    ],
    "wof:name":"Links To Health",
    "wof:placetype":"venue"
},
  "geometry": {"coordinates":[151.48374939000001,-33.2498970032],"type":"Point"}
}