{
  "type": "Feature",
  "properties": {
    "addr:full":"110a Belford St Broadmeadow NSW 2292",
    "addr:housenumber":"110a",
    "addr:postcode":"2292",
    "addr:street":"Belford St",
    "iso:country":"AU",
    "sg:address":"110a Belford St",
    "sg:city":"Broadmeadow",
    "sg:classifiers":[
        {
            "category":"Travel",
            "subcategory":"Travel Agent",
            "type":"Entertainment"
        }
    ],
    "sg:phone":"+61 2 4961 0834",
    "sg:postcode":"2292",
    "sg:province":"NSW",
    "sg:tags":[
        "consultant"
    ],
    "wof:name":"Great Events Kerry Phillips",
    "wof:placetype":"venue"
},
  "geometry": {"coordinates":[151.73765564000001,-32.9239692688],"type":"Point"}
}