{
  "type": "Feature",
  "properties": {
    "addr:full":"14 Stewart Ave Newcastle West NSW 2302",
    "addr:housenumber":"14",
    "addr:postcode":"2302",
    "addr:street":"Stewart Ave",
    "iso:country":"AU",
    "sg:address":"14 Stewart Ave",
    "sg:city":"Newcastle West",
    "sg:classifiers":[
        {
            "category":"Retail",
            "subcategory":"Car Wash",
            "type":"Services"
        }
    ],
    "sg:phone":"+61 2 4962 3126",
    "sg:postcode":"2302",
    "sg:province":"NSW",
    "sg:tags":[
        "truck",
        "cleaning"
    ],
    "wof:name":"Carlovers Carwash",
    "wof:placetype":"venue"
},
  "geometry": {"coordinates":[151.75846899999999,-32.926144],"type":"Point"}
}