{
  "type": "Feature",
  "properties": {
    "addr:full":"1440 Plumpton Rd Plumpton VIC 3037",
    "addr:housenumber":"1440",
    "addr:postcode":"3037",
    "addr:street":"Plumpton Rd",
    "iso:country":"AU",
    "sg:address":"1440 Plumpton Rd",
    "sg:city":"Plumpton",
    "sg:classifiers":[
        {
            "category":"Wholesale",
            "subcategory":"Construction Materials",
            "type":"Manufacturing & Wholesale Goods"
        }
    ],
    "sg:phone":"+61 3 9449 2166",
    "sg:postcode":"3037",
    "sg:province":"VIC",
    "sg:tags":[
        "wholesaler",
        "lighting",
        "mfrs",
        "accessory"
    ],
    "wof:name":"Ropelight Victorian Distributors Of Flexi Light",
    "wof:placetype":"venue"
},
  "geometry": {"coordinates":[144.75900300000001,-37.695461],"type":"Point"}
}