{
  "type": "Feature",
  "properties": {
    "addr:full":"17 Main St Romsey VIC 3434",
    "addr:housenumber":"17",
    "addr:postcode":"3434",
    "addr:street":"Main St",
    "iso:country":"AU",
    "sg:address":"17 Main St",
    "sg:city":"Romsey",
    "sg:classifiers":[
        {
            "category":"Building & Trades",
            "subcategory":"Construction",
            "type":"Services"
        }
    ],
    "sg:phone":"+61 3 5429 5931",
    "sg:postcode":"3434",
    "sg:province":"VIC",
    "sg:tags":[
        "plasterboard",
        "plasterer",
        "fixer"
    ],
    "wof:name":"Romsey Plaster Products",
    "wof:placetype":"venue"
},
  "geometry": {"coordinates":[144.74343872099999,-37.3568572998],"type":"Point"}
}