{
  "type": "Feature",
  "properties": {
    "addr:full":"Lvl 2/ 20 Falcon St Crows Nest NSW 2065",
    "addr:housenumber":"/ 20",
    "addr:postcode":"2065",
    "addr:street":"Falcon St",
    "iso:country":"AU",
    "sg:address":"Lvl 2/ 20 Falcon St",
    "sg:city":"Crows Nest",
    "sg:classifiers":[
        {
            "category":"Professional",
            "subcategory":"Computer Services",
            "type":"Services"
        }
    ],
    "sg:phone":"+61 2 9460 8077",
    "sg:postcode":"2065",
    "sg:province":"NSW",
    "sg:tags":[
        "consultant",
        "system"
    ],
    "wof:name":"Netway Networks Pty Ltd",
    "wof:placetype":"venue"
},
  "geometry": {"coordinates":[151.20225524899999,-33.8277397156],"type":"Point"}
}