{
  "type": "Feature",
  "properties": {
    "iso:country":"AU",
    "sg:address":"Office 1/ 92 Victoria St",
    "sg:city":"Mackay",
    "sg:classifiers":[
        {
            "category":"Health Services",
            "subcategory":"Health Practitioner",
            "type":"Services"
        }
    ],
    "sg:phone":"+61 7 4953 4344",
    "sg:postcode":"4740",
    "sg:province":"QLD",
    "sg:tags":[
        "homoeopath"
    ],
    "wof:name":"Greenwood Sylvia A",
    "wof:placetype":"venue"
},
  "geometry": {"coordinates":[149.18675200000001,-21.141136],"type":"Point"}
}