{
  "type": "Feature",
  "properties": {
    "addr:full":"28 Heyington Ave Thomastown VIC 3074",
    "addr:housenumber":"28",
    "addr:postcode":"3074",
    "addr:street":"Heyington Ave",
    "iso:country":"AU",
    "sg:address":"28 Heyington Ave",
    "sg:city":"Thomastown",
    "sg:classifiers":[
        {
            "category":"Professional",
            "subcategory":"Computer Services",
            "type":"Services"
        }
    ],
    "sg:phone":"+61 3 9465 0292",
    "sg:postcode":"3074",
    "sg:province":"VIC",
    "sg:tags":[
        "repairs",
        "upgrade",
        "equipment"
    ],
    "wof:name":"Flat Rate PC Repairs",
    "wof:placetype":"venue"
},
  "geometry": {"coordinates":[145.017944336,-37.6824913025],"type":"Point"}
}