{
  "type": "Feature",
  "properties": {
    "iso:country":"AU",
    "sg:address":"57 Grafton St",
    "sg:city":"Cairns",
    "sg:classifiers":[
        {
            "category":"Banks & Credit Unions",
            "subcategory":"Financial Services",
            "type":"Services"
        }
    ],
    "sg:phone":"+61 7 4041 2021",
    "sg:postcode":"4870",
    "sg:province":"QLD",
    "sg:tags":[
        "building",
        "society"
    ],
    "wof:name":"Pioneer Permanent Building Society Limited",
    "wof:placetype":"venue"
},
  "geometry": {"coordinates":[145.77589416500001,-16.9242954254],"type":"Point"}
}