{
  "type": "Feature",
  "properties": {
    "iso:country":"AU",
    "sg:address":"22 Taranto Rd",
    "sg:city":"Marsfield",
    "sg:classifiers":[
        {
            "category":"Utilities",
            "subcategory":"Natural Gas",
            "type":"Services"
        }
    ],
    "sg:phone":"+61 2 9876 3566",
    "sg:postcode":"2122",
    "sg:province":"NSW",
    "sg:tags":[
        "consultant",
        "resource"
    ],
    "wof:name":"Davies Ian & Associates Pty Ltd",
    "wof:placetype":"venue"
},
  "geometry": {"coordinates":[151.10804748499999,-33.7660942078],"type":"Point"}
}