{
  "type": "Feature",
  "properties": {
    "addr:full":"130 Stradbroke Ave Swan Hill VIC 3585",
    "addr:housenumber":"130",
    "addr:postcode":"3585",
    "addr:street":"Stradbroke Ave",
    "iso:country":"AU",
    "sg:address":"130 Stradbroke Ave",
    "sg:city":"Swan Hill",
    "sg:classifiers":[
        {
            "category":"Building & Trades",
            "subcategory":"Construction",
            "type":"Services"
        }
    ],
    "sg:phone":"+61 409 175 407",
    "sg:postcode":"3585",
    "sg:province":"VIC",
    "sg:tags":[
        "contractor"
    ],
    "wof:name":"Glenn Roberts Builder",
    "wof:placetype":"venue"
},
  "geometry": {"coordinates":[143.551086,-35.339092],"type":"Point"}
}