{
  "type": "Feature",
  "properties": {
    "addr:full":"59 Bonville Ave Thornton NSW 2322",
    "addr:housenumber":"59",
    "addr:postcode":"2322",
    "addr:street":"Bonville Ave",
    "iso:country":"AU",
    "sg:address":"59 Bonville Ave",
    "sg:city":"Thornton",
    "sg:classifiers":[
        {
            "category":"Health Services",
            "subcategory":"Doctor",
            "type":"Services"
        }
    ],
    "sg:phone":"+61 2 4978 4013",
    "sg:postcode":"2322",
    "sg:province":"NSW",
    "sg:tags":[
        "occupational",
        "safety"
    ],
    "wof:name":"Hunter Councils Learning And Development",
    "wof:placetype":"venue"
},
  "geometry": {"coordinates":[151.633743286,-32.784362793],"type":"Point"}
}