{
  "type": "Feature",
  "properties": {
    "addr:full":"19 Cromie St Rupanyup VIC 3388",
    "addr:housenumber":"19",
    "addr:postcode":"3388",
    "addr:street":"Cromie St",
    "iso:country":"AU",
    "sg:address":"19 Cromie St",
    "sg:city":"Rupanyup",
    "sg:classifiers":[
        {
            "category":"Fast Food",
            "type":"Food & Drink"
        }
    ],
    "sg:phone":"+61 3 5385 5380",
    "sg:postcode":"3388",
    "sg:province":"VIC",
    "sg:tags":[
        "away",
        "take"
    ],
    "wof:name":"Boydys",
    "wof:placetype":"venue"
},
  "geometry": {"coordinates":[142.63153076200001,-36.6306304932],"type":"Point"}
}