{
  "type": "Feature",
  "properties": {
    "addr:full":"245 Douglas Pde Newport VIC 3015",
    "addr:housenumber":"245",
    "addr:postcode":"3015",
    "addr:street":"Douglas Pde",
    "iso:country":"AU",
    "sg:address":"245 Douglas Pde",
    "sg:city":"Newport",
    "sg:classifiers":[
        {
            "category":"Professional",
            "subcategory":"Art Services",
            "type":"Services"
        }
    ],
    "sg:phone":"+61 3 9391 5762",
    "sg:postcode":"3015",
    "sg:province":"VIC",
    "sg:tags":[
        "artist"
    ],
    "wof:name":"Ramon Hewitt",
    "wof:placetype":"venue"
},
  "geometry": {"coordinates":[144.89273071299999,-37.848400116],"type":"Point"}
}