{
  "type": "Feature",
  "properties": {
    "addr:full":"9 Tarwhine Pl Golden Bay WA 6174",
    "addr:housenumber":"9",
    "addr:postcode":"6174",
    "addr:street":"Tarwhine Pl",
    "iso:country":"AU",
    "sg:address":"9 Tarwhine Pl",
    "sg:city":"Golden Bay",
    "sg:classifiers":[
        {
            "category":"Retail",
            "subcategory":"Storage",
            "type":"Services"
        }
    ],
    "sg:phone":"+61 400 065 665",
    "sg:postcode":"6174",
    "sg:province":"WA",
    "sg:tags":[
        "removal",
        "furniture"
    ],
    "wof:name":"White N",
    "wof:placetype":"venue"
},
  "geometry": {"coordinates":[115.755211,-32.432522],"type":"Point"}
}