{
  "type": "Feature",
  "properties": {
    "iso:country":"AU",
    "sg:address":"246 North St",
    "sg:city":"Albury",
    "sg:classifiers":[
        {
            "category":"Commercial Area",
            "type":"Public Place"
        }
    ],
    "sg:phone":"+61 2 6021 5855",
    "sg:postcode":"2640",
    "sg:province":"NSW",
    "sg:tags":[
        "heavy",
        "carrier"
    ],
    "wof:name":"W. A. Pickles (NSW) Pty Ltd",
    "wof:placetype":"venue"
},
  "geometry": {"coordinates":[146.91255188,-36.0668029785],"type":"Point"}
}