{
  "type": "Feature",
  "properties": {
    "addr:full":"34 Sloane St Stawell VIC 3380",
    "addr:housenumber":"34",
    "addr:postcode":"3380",
    "addr:street":"Sloane St",
    "iso:country":"AU",
    "sg:address":"34 Sloane St",
    "sg:city":"Stawell",
    "sg:classifiers":[
        {
            "category":"Health Services",
            "subcategory":"Doctor",
            "type":"Services"
        }
    ],
    "sg:phone":"+61 3 5358 1377",
    "sg:postcode":"3380",
    "sg:province":"VIC",
    "sg:tags":[
        "medical",
        "practitioner"
    ],
    "wof:name":"Sloane St Clinic",
    "wof:placetype":"venue"
},
  "geometry": {"coordinates":[142.780395508,-37.0589370728],"type":"Point"}
}