{
  "type": "Feature",
  "properties": {
    "addr:full":"164-170 Flinders St Melbourne VIC 3000",
    "addr:housenumber":"164-170",
    "addr:postcode":"3000",
    "addr:street":"Flinders St",
    "iso:country":"AU",
    "sg:address":"164-170 Flinders St",
    "sg:city":"Melbourne",
    "sg:classifiers":[
        {
            "category":"Restaurant",
            "type":"Food & Drink"
        }
    ],
    "sg:phone":"+61 3 9654 7638",
    "sg:postcode":"3000",
    "sg:province":"VIC",
    "wof:name":"Da Marconi Pizza & Pasta",
    "wof:placetype":"venue"
},
  "geometry": {"coordinates":[144.96885681099999,-37.8168983459],"type":"Point"}
}