{
  "type": "Feature",
  "properties": {
    "iso:country":"AU",
    "sg:address":"8/ 14 Waterloo St",
    "sg:city":"Carlton",
    "sg:classifiers":[
        {
            "category":"Manufacturing",
            "subcategory":"Leather Goods",
            "type":"Manufacturing & Wholesale Goods"
        }
    ],
    "sg:phone":"+61 3 9347 5519",
    "sg:postcode":"3053",
    "sg:province":"VIC",
    "sg:tags":[
        "wholesaler",
        "mfrs"
    ],
    "wof:name":"Braun Buffel",
    "wof:placetype":"venue"
},
  "geometry": {"coordinates":[144.96713256800001,-37.7950706482],"type":"Point"}
}