{
  "type": "Feature",
  "properties": {
    "addr:full":"Suite 202/51 Locked Bag 1, Varsity Lakes QLD 4227",
    "addr:housenumber":"/ 51;1",
    "addr:postcode":"4227",
    "addr:street":"Locked",
    "iso:country":"AU",
    "sg:address":"Suite 202/51",
    "sg:city":"Locked Bag 1, Varsity Lakes",
    "sg:classifiers":[
        {
            "category":"Building & Trades",
            "subcategory":"Cleaning & Sanitation",
            "type":"Services"
        }
    ],
    "sg:phone":"+61 414 786 868",
    "sg:postcode":"4227",
    "sg:province":"QLD",
    "sg:tags":[
        "chemical",
        "pressure",
        "steam",
        "contractor"
    ],
    "wof:name":"Extreme Waterblasting",
    "wof:placetype":"venue"
},
  "geometry": {"coordinates":[153.41003418,-28.0855197906],"type":"Point"}
}