{
  "type": "Feature",
  "properties": {
    "addr:full":"22 Lanyon St Bracken Ridge QLD 4017",
    "addr:housenumber":"22",
    "addr:postcode":"4017",
    "addr:street":"Lanyon St",
    "iso:country":"AU",
    "sg:address":"22 Lanyon St",
    "sg:city":"Bracken Ridge",
    "sg:classifiers":[
        {
            "category":"Professional",
            "subcategory":"Art Services",
            "type":"Services"
        }
    ],
    "sg:phone":"+61 7 3269 9560",
    "sg:postcode":"4017",
    "sg:province":"QLD",
    "sg:tags":[
        "decorator",
        "painter"
    ],
    "wof:name":"Wet Paint-ting Contractors",
    "wof:placetype":"venue"
},
  "geometry": {"coordinates":[153.04005432100001,-27.3266353607],"type":"Point"}
}