{
  "type": "Feature",
  "properties": {
    "iso:country":"AU",
    "sg:address":"260 Newnham Rd",
    "sg:city":"Mt Gravatt",
    "sg:classifiers":[
        {
            "category":"Home & Garden",
            "subcategory":"Hardware",
            "type":"Retail Goods"
        }
    ],
    "sg:phone":"+61 7 3422 2499",
    "sg:postcode":"4122",
    "sg:province":"QLD",
    "sg:tags":[
        "plumber",
        "supply"
    ],
    "wof:name":"K & R Plumbing Supplies",
    "wof:placetype":"venue"
},
  "geometry": {"coordinates":[153.092163086,-27.5455951691],"type":"Point"}
}