{
  "type": "Feature",
  "properties": {
    "iso:country":"AU",
    "sg:address":"Monbulk/Seville Rd",
    "sg:city":"Silvan",
    "sg:classifiers":[
        {
            "category":"Wholesale",
            "subcategory":"Plants",
            "type":"Manufacturing & Wholesale Goods"
        }
    ],
    "sg:phone":"+61 3 9737 9727",
    "sg:postcode":"3795",
    "sg:province":"VIC",
    "sg:tags":[
        "florist"
    ],
    "wof:name":"Tulip Garden Nursery Pty Ltd The",
    "wof:placetype":"venue"
},
  "geometry": {"coordinates":[145.43780517600001,-37.8470420837],"type":"Point"}
}