{
  "type": "Feature",
  "properties": {
    "iso:country":"AU",
    "sg:address":"77 Enmore Rd",
    "sg:city":"Enmore",
    "sg:classifiers":[
        {
            "category":"Personal",
            "subcategory":"Massage",
            "type":"Services"
        }
    ],
    "sg:phone":"+61 2 9550 3356",
    "sg:postcode":"2042",
    "sg:province":"NSW",
    "sg:tags":[
        "therapy"
    ],
    "sg:website":"http://www.thaimassage.com.au",
    "wof:name":"The Thai Massage Centre - Enmore",
    "wof:placetype":"venue"
},
  "geometry": {"coordinates":[151.175003,-33.898556],"type":"Point"}
}