{
  "type": "Feature",
  "properties": {
    "iso:country":"AU",
    "sg:address":"North Haven Shopng Cntr Osborne Rd",
    "sg:city":"North Haven",
    "sg:classifiers":[
        {
            "category":"Health Services",
            "subcategory":"Dentist",
            "type":"Services"
        }
    ],
    "sg:phone":"+61 8 8248 3967",
    "sg:postcode":"5018",
    "sg:province":"SA",
    "wof:name":"Wright Philip Dr",
    "wof:placetype":"venue"
},
  "geometry": {"coordinates":[138.492263794,-34.7924880981],"type":"Point"}
}