{
  "type": "Feature",
  "properties": {
    "iso:country":"AU",
    "sg:address":"Werrell Reserve Great North Rd",
    "sg:city":"Abbotsford",
    "sg:classifiers":[
        {
            "category":"Recreation",
            "subcategory":"Sailing Club",
            "type":"Entertainment"
        }
    ],
    "sg:phone":"+61 2 9713 2048",
    "sg:postcode":"2046",
    "sg:province":"NSW",
    "sg:tags":[
        "yacht"
    ],
    "wof:name":"Abbotsford 12ft Sailing Club",
    "wof:placetype":"venue"
},
  "geometry": {"coordinates":[151.12855500000001,-33.850609],"type":"Point"}
}