{
  "type": "Feature",
  "properties": {
    "iso:country":"AU",
    "sg:address":"6 Acacia St",
    "sg:city":"Rydalmere",
    "sg:classifiers":[
        {
            "category":"Manufacturing",
            "subcategory":"Food",
            "type":"Manufacturing & Wholesale Goods"
        }
    ],
    "sg:phone":"+61 2 9638 4301",
    "sg:postcode":"2116",
    "sg:province":"NSW",
    "sg:tags":[
        "function",
        "catering"
    ],
    "wof:name":"Cook & Carve",
    "wof:placetype":"venue"
},
  "geometry": {"coordinates":[151.04766845699999,-33.8089561462],"type":"Point"}
}