{
  "type": "Feature",
  "properties": {
    "iso:country":"AU",
    "sg:address":"6 Ragless St",
    "sg:city":"St Marys",
    "sg:classifiers":[
        {
            "category":"Building & Trades",
            "subcategory":"Landscaping Services",
            "type":"Services"
        }
    ],
    "sg:phone":"+61 8 8177 1622",
    "sg:postcode":"5042",
    "sg:province":"SA",
    "sg:tags":[
        "designer",
        "landscape",
        "contractor"
    ],
    "wof:name":"Consolidated Landscape Services Pty Ltd",
    "wof:placetype":"venue"
},
  "geometry": {"coordinates":[138.57637,-34.998985],"type":"Point"}
}