{
  "type": "Feature",
  "properties": {
    "iso:country":"AU",
    "sg:address":"271 Austinville Rd",
    "sg:city":"Mudgeeraba",
    "sg:classifiers":[
        {
            "category":"Travel",
            "subcategory":"Travel Agent",
            "type":"Entertainment"
        }
    ],
    "sg:phone":"+61 7 5530 5570",
    "sg:postcode":"4213",
    "sg:province":"QLD",
    "sg:tags":[
        "tour",
        "holiday",
        "adventure"
    ],
    "wof:name":"Mt Nimmel Lodge Camp Ground",
    "wof:placetype":"venue"
},
  "geometry": {"coordinates":[153.31292724599999,-28.139875412],"type":"Point"}
}