{
  "type": "Feature",
  "properties": {
    "addr:full":"36b South Rd Torrensville SA 5031",
    "addr:housenumber":"36b",
    "addr:postcode":"5031",
    "addr:street":"South Rd",
    "iso:country":"AU",
    "sg:address":"36b South Rd",
    "sg:city":"Torrensville",
    "sg:classifiers":[
        {
            "category":"Professional",
            "subcategory":"Detective & Security Services",
            "type":"Services"
        }
    ],
    "sg:phone":"+61 8 8354 3186",
    "sg:postcode":"5031",
    "sg:province":"SA",
    "sg:tags":[
        "guard",
        "patrol"
    ],
    "wof:name":"Allied Mobilized Protective Services",
    "wof:placetype":"venue"
},
  "geometry": {"coordinates":[138.56524658199999,-34.9136199951],"type":"Point"}
}