{
  "type": "Feature",
  "properties": {
    "addr:full":"9 Marlbrough St Sandy Bay TAS 7005",
    "addr:housenumber":"9",
    "addr:postcode":"7005",
    "addr:street":"Marlbrough St",
    "iso:country":"AU",
    "sg:address":"9 Marlbrough St",
    "sg:city":"Sandy Bay",
    "sg:classifiers":[
        {
            "category":"Building & Trades",
            "subcategory":"Construction",
            "type":"Services"
        }
    ],
    "sg:phone":"+61 3 6225 2525",
    "sg:postcode":"7005",
    "sg:province":"TAS",
    "sg:tags":[
        "contractor"
    ],
    "wof:name":"Dzelalija J & S Pty Ltd",
    "wof:placetype":"venue"
},
  "geometry": {"coordinates":[147.342453003,-42.9165496826],"type":"Point"}
}