{
  "type": "Feature",
  "properties": {
    "addr:full":"Cnr Michelle Drv & Homestead Rd Berwick VIC 3806",
    "addr:postcode":"3806",
    "addr:street":"Cnr Michelle Drv & Homestead Rd",
    "iso:country":"AU",
    "sg:address":"Cnr Michelle Drv & Homestead Rd",
    "sg:city":"Berwick",
    "sg:classifiers":[
        {
            "category":"Education",
            "subcategory":"Kindergarten",
            "type":"Public Place"
        }
    ],
    "sg:phone":"+61 3 9702 1601",
    "sg:postcode":"3806",
    "sg:province":"VIC",
    "sg:tags":[
        "pre-schools"
    ],
    "wof:name":"Caseys Child Care Centre & Kindergarten",
    "wof:placetype":"venue"
},
  "geometry": {"coordinates":[145.33770751899999,-38.055355072],"type":"Point"}
}