{
  "type": "Feature",
  "properties": {
    "addr:full":"60 Quay St Bundaberg QLD 4670",
    "addr:housenumber":"60",
    "addr:postcode":"4670",
    "addr:street":"Quay St",
    "iso:country":"AU",
    "sg:address":"60 Quay St",
    "sg:city":"Bundaberg",
    "sg:classifiers":[
        {
            "category":"Health Services",
            "subcategory":"Doctor",
            "type":"Services"
        }
    ],
    "sg:phone":"+61 7 4153 9500",
    "sg:postcode":"4670",
    "sg:province":"QLD",
    "sg:tags":[
        "medical",
        "practitioner"
    ],
    "wof:name":"Peers Marilyn",
    "wof:placetype":"venue"
},
  "geometry": {"coordinates":[152.34291076700001,-24.866558075],"type":"Point"}
}