{
  "type": "Feature",
  "properties": {
    "addr:full":"26 Blakey St Cobar NSW 2835",
    "addr:housenumber":"26",
    "addr:postcode":"2835",
    "addr:street":"Blakey St",
    "iso:country":"AU",
    "sg:address":"26 Blakey St",
    "sg:city":"Cobar",
    "sg:classifiers":[
        {
            "category":"Retail",
            "subcategory":"Funeral Services",
            "type":"Services"
        }
    ],
    "sg:phone":"+61 2 6836 2010",
    "sg:postcode":"2835",
    "sg:province":"NSW",
    "sg:tags":[
        "director"
    ],
    "wof:name":"Jermyn Terry",
    "wof:placetype":"venue"
},
  "geometry": {"coordinates":[145.83338900000001,-31.500942],"type":"Point"}
}