{
  "type": "Feature",
  "properties": {
    "addr:full":"74A Denison Rd Dulwich Hill NSW 2203",
    "addr:housenumber":"74a",
    "addr:postcode":"2203",
    "addr:street":"Denison Rd",
    "iso:country":"AU",
    "sg:address":"74A Denison Rd",
    "sg:city":"Dulwich Hill",
    "sg:classifiers":[
        {
            "category":"Health Services",
            "subcategory":"Health Practitioner",
            "type":"Services"
        }
    ],
    "sg:phone":"+61 2 9518 1261",
    "sg:postcode":"2203",
    "sg:province":"NSW",
    "sg:tags":[
        "alternative"
    ],
    "wof:name":"Kate McGregor",
    "wof:placetype":"venue"
},
  "geometry": {"coordinates":[151.144745,-33.896729],"type":"Point"}
}