{
  "type": "Feature",
  "properties": {
    "addr:full":"167 Fitzroy St Fitzroy VIC 3065",
    "addr:housenumber":"167",
    "addr:postcode":"3065",
    "addr:street":"Fitzroy St",
    "iso:country":"AU",
    "sg:address":"167 Fitzroy St",
    "sg:city":"Fitzroy",
    "sg:classifiers":[
        {
            "category":"Arena",
            "subcategory":"Indoor Arena",
            "type":"Entertainment"
        }
    ],
    "sg:phone":"+61 3 9416 4500",
    "sg:postcode":"3065",
    "sg:province":"VIC",
    "sg:tags":[
        "modelmakers"
    ],
    "wof:name":"Modelcraft (Vic) Pty Ltd",
    "wof:placetype":"venue"
},
  "geometry": {"coordinates":[144.97625732399999,-37.8038635254],"type":"Point"}
}