{
  "type": "Feature",
  "properties": {
    "iso:country":"AU",
    "sg:address":"9 Lenehan Rd",
    "sg:city":"Griffith",
    "sg:classifiers":[
        {
            "category":"Wholesale",
            "subcategory":"Machinery & Supplies",
            "type":"Manufacturing & Wholesale Goods"
        }
    ],
    "sg:phone":"+61 2 6964 5879",
    "sg:postcode":"2680",
    "sg:province":"NSW",
    "sg:tags":[
        "agricultural"
    ],
    "wof:name":"Agostini Ag",
    "wof:placetype":"venue"
},
  "geometry": {"coordinates":[146.060425,-34.293919],"type":"Point"}
}