{
  "type": "Feature",
  "properties": {
    "iso:country":"AU",
    "sg:address":"Suite 1/7- 13 Post Office Pl",
    "sg:city":"Traralgon",
    "sg:classifiers":[
        {
            "category":"Building & Trades",
            "subcategory":"Landscaping Services",
            "type":"Services"
        }
    ],
    "sg:phone":"+61 3 5176 1117",
    "sg:postcode":"3844",
    "sg:province":"VIC",
    "sg:tags":[
        "consultant"
    ],
    "wof:name":"J.J.C Design",
    "wof:placetype":"venue"
},
  "geometry": {"coordinates":[146.538894653,-38.1952476501],"type":"Point"}
}