{
  "type": "Feature",
  "properties": {
    "addr:full":"15 Bridgewater Crt Waikiki WA 6169",
    "addr:housenumber":"15",
    "addr:postcode":"6169",
    "addr:street":"Bridgewater Crt",
    "iso:country":"AU",
    "sg:address":"15 Bridgewater Crt",
    "sg:city":"Waikiki",
    "sg:classifiers":[
        {
            "category":"Retail",
            "subcategory":"Laundry & Dry Cleaning",
            "type":"Services"
        }
    ],
    "sg:phone":"+61 8 9527 7705",
    "sg:postcode":"6169",
    "sg:province":"WA",
    "sg:tags":[
        "cloth",
        "supply"
    ],
    "wof:name":"Waikiki Rag Supplies",
    "wof:placetype":"venue"
},
  "geometry": {"coordinates":[115.74764999999999,-32.312641],"type":"Point"}
}