{
  "type": "Feature",
  "properties": {
    "iso:country":"AU",
    "sg:address":"114 Queens Rd",
    "sg:city":"Five Dock",
    "sg:classifiers":[
        {
            "category":"Manufacturing",
            "subcategory":"Motor Vehicles & Parts",
            "type":"Manufacturing & Wholesale Goods"
        }
    ],
    "sg:phone":"+61 2 8753 0588",
    "sg:postcode":"2046",
    "sg:province":"NSW",
    "sg:tags":[
        "replacement"
    ],
    "wof:name":"Central Drive Shaft Services",
    "wof:placetype":"venue"
},
  "geometry": {"coordinates":[151.12037699999999,-33.869156],"type":"Point"}
}