{
  "type": "Feature",
  "properties": {
    "addr:full":"Shop 10 Loido Arcade 3155 Gold Coast Hwy Surfers Paradise QLD 4217",
    "addr:housenumber":"shop 10;3155",
    "addr:postcode":"4217",
    "addr:street":"Loido Arcade;Gold Coast Hwy",
    "iso:country":"AU",
    "sg:address":"Shop 10 Loido Arcade 3155 Gold Coast Hwy",
    "sg:city":"Surfers Paradise",
    "sg:classifiers":[
        {
            "category":"Shopping",
            "subcategory":"Jewelry",
            "type":"Retail Goods"
        }
    ],
    "sg:phone":"+61 7 5539 0313",
    "sg:postcode":"4217",
    "sg:province":"QLD",
    "sg:tags":[
        "jeweller"
    ],
    "wof:name":"JM Jewellers",
    "wof:placetype":"venue"
},
  "geometry": {"coordinates":[153.42953491200001,-28.0110912323],"type":"Point"}
}