{
  "type": "Feature",
  "properties": {
    "iso:country":"AU",
    "sg:address":"PO Box 500",
    "sg:city":"Hillarys",
    "sg:classifiers":[
        {
            "category":"Social Services",
            "subcategory":"Retirement Home",
            "type":"Services"
        }
    ],
    "sg:phone":"+61 8 9307 3080",
    "sg:postcode":"6923",
    "sg:province":"WA",
    "sg:tags":[
        "environmental",
        "consultant",
        "pollution"
    ],
    "wof:name":"Ecolo WA",
    "wof:placetype":"venue"
},
  "geometry": {"coordinates":[115.741539002,-31.809419632],"type":"Point"}
}