{
  "type": "Feature",
  "properties": {
    "iso:country":"AU",
    "sg:address":"Shop 19 Central Shopping Centr Torrens St",
    "sg:city":"Victor Harbor",
    "sg:classifiers":[
        {
            "category":"Wholesale",
            "subcategory":"Medical Equipment & Supplies",
            "type":"Manufacturing & Wholesale Goods"
        }
    ],
    "sg:phone":"+61 8 8552 4322",
    "sg:postcode":"5211",
    "sg:province":"SA",
    "sg:tags":[
        "aids",
        "hearing"
    ],
    "wof:name":"Hearing Life",
    "wof:placetype":"venue"
},
  "geometry": {"coordinates":[138.62290954599999,-35.5517539978],"type":"Point"}
}