{
  "type": "Feature",
  "properties": {
    "iso:country":"AU",
    "sg:address":"12 Main North Rd",
    "sg:city":"Gawler",
    "sg:classifiers":[
        {
            "category":"Wholesale",
            "subcategory":"Farm Supplies",
            "type":"Manufacturing & Wholesale Goods"
        }
    ],
    "sg:phone":"+61 8 8522 1458",
    "sg:postcode":"5118",
    "sg:province":"SA",
    "sg:tags":[
        "feed",
        "supplement",
        "stock"
    ],
    "wof:name":"Gawler Stock Feeds",
    "wof:placetype":"venue"
},
  "geometry": {"coordinates":[138.743942,-34.58754],"type":"Point"}
}