{
  "type": "Feature",
  "properties": {
    "iso:country":"AU",
    "sg:address":"PO Box 92",
    "sg:city":"F Freshwater",
    "sg:classifiers":[
        {
            "category":"Building & Trades",
            "subcategory":"Cleaning & Sanitation",
            "type":"Services"
        }
    ],
    "sg:phone":"+61 416 091 153",
    "sg:postcode":"4870",
    "sg:province":"QLD",
    "sg:tags":[
        "chemical",
        "pressure",
        "steam",
        "contractor"
    ],
    "wof:name":"Abelia Cleaning",
    "wof:placetype":"venue"
},
  "geometry": {"coordinates":[145.71005249000001,-16.8818206787],"type":"Point"}
}