{
  "type": "Feature",
  "properties": {
    "iso:country":"AU",
    "sg:address":"34 Blue Hills Drv",
    "sg:city":"Rangeville",
    "sg:classifiers":[
        {
            "category":"Education",
            "subcategory":"Music School",
            "type":"Public Place"
        }
    ],
    "sg:phone":"+61 7 4636 1127",
    "sg:postcode":"4350",
    "sg:province":"QLD",
    "sg:tags":[
        "teacher"
    ],
    "wof:name":"Bram Plant",
    "wof:placetype":"venue"
},
  "geometry": {"coordinates":[151.986923,-27.583872],"type":"Point"}
}