{
  "type": "Feature",
  "properties": {
    "addr:full":"5 Rose Crs Valley View SA 5093",
    "addr:housenumber":"5",
    "addr:postcode":"5093",
    "addr:street":"Rose Crs",
    "iso:country":"AU",
    "sg:address":"5 Rose Crs",
    "sg:city":"Valley View",
    "sg:classifiers":[
        {
            "category":"Building & Trades",
            "subcategory":"Landscaping Services",
            "type":"Services"
        }
    ],
    "sg:phone":"+61 8 8414 5773",
    "sg:postcode":"5093",
    "sg:province":"SA",
    "sg:tags":[
        "gardener"
    ],
    "wof:name":"Martin's Garden And Irrigation Services",
    "wof:placetype":"venue"
},
  "geometry": {"coordinates":[138.67445373499999,-34.834148407],"type":"Point"}
}