{
  "type": "Feature",
  "properties": {
    "iso:country":"AU",
    "sg:address":"9 Nelson Rd",
    "sg:city":"North Strathfield",
    "sg:classifiers":[
        {
            "category":"Professional",
            "subcategory":"Engineering",
            "type":"Services"
        }
    ],
    "sg:phone":"+61 2 9746 8995",
    "sg:postcode":"2137",
    "sg:province":"NSW",
    "sg:tags":[
        "consulting",
        "engineer"
    ],
    "wof:name":"Nicholson Robert",
    "wof:placetype":"venue"
},
  "geometry": {"coordinates":[151.091796875,-33.8607025146],"type":"Point"}
}