{
  "type": "Feature",
  "properties": {
    "iso:country":"AU",
    "sg:address":"4 Criterion St",
    "sg:city":"Hobart",
    "sg:classifiers":[
        {
            "category":"Health Services",
            "subcategory":"Dentist",
            "type":"Services"
        }
    ],
    "sg:phone":"+61 3 6234 2645",
    "sg:postcode":"7000",
    "sg:province":"TAS",
    "sg:tags":[
        "dental",
        "prosthetist"
    ],
    "wof:name":"Sue Graham",
    "wof:placetype":"venue"
},
  "geometry": {"coordinates":[147.326446533,-42.8817520142],"type":"Point"}
}