{
  "type": "Feature",
  "properties": {
    "iso:country":"AU",
    "sg:address":"10 Macquarie Ave",
    "sg:city":"Lemongrove",
    "sg:classifiers":[
        {
            "category":"Health Services",
            "subcategory":"Doctor",
            "type":"Services"
        }
    ],
    "sg:phone":"+61 2 4721 1150",
    "sg:postcode":"2750",
    "sg:province":"NSW",
    "sg:tags":[
        "medical",
        "practitioner"
    ],
    "wof:name":"Nepean Division Of General Practice",
    "wof:placetype":"venue"
},
  "geometry": {"coordinates":[150.703735352,-33.7513618469],"type":"Point"}
}