{
  "type": "Feature",
  "properties": {
    "iso:country":"AU",
    "sg:address":"6a, 41 Tompson St",
    "sg:city":"Wagga Wagga",
    "sg:classifiers":[
        {
            "category":"Banks & Credit Unions",
            "subcategory":"Investment Brokerage",
            "type":"Services"
        }
    ],
    "sg:phone":"+61 1800 641 617",
    "sg:postcode":"2650",
    "sg:province":"NSW",
    "sg:tags":[
        "debt",
        "collection"
    ],
    "wof:name":"Prushka Fast Debt Recovery",
    "wof:placetype":"venue"
},
  "geometry": {"coordinates":[147.37240600600001,-35.1120376587],"type":"Point"}
}