{
  "type": "Feature",
  "properties": {
    "iso:country":"AU",
    "sg:address":"107 Jubilee St, Shed 4",
    "sg:city":"Maclean",
    "sg:classifiers":[
        {
            "category":"Utilities",
            "subcategory":"Recycling",
            "type":"Services"
        }
    ],
    "sg:phone":"+61 413 333 500",
    "sg:postcode":"2463",
    "sg:province":"NSW",
    "wof:name":"Scrappy Joes Metal Recycling",
    "wof:placetype":"venue"
},
  "geometry": {"coordinates":[153.220413208,-29.4657554626],"type":"Point"}
}