{
  "type": "Feature",
  "properties": {
    "addr:full":"U7/ 43 Norma Rd Myaree WA 6154",
    "addr:housenumber":"43",
    "addr:postcode":"6154",
    "addr:street":"U7 /;Norma Rd",
    "iso:country":"AU",
    "sg:address":"U7/ 43 Norma Rd",
    "sg:city":"Myaree",
    "sg:classifiers":[
        {
            "category":"Retail",
            "subcategory":"Auto Repair",
            "type":"Services"
        }
    ],
    "sg:phone":"+61 8 9317 4492",
    "sg:postcode":"6154",
    "sg:province":"WA",
    "sg:tags":[
        "repairer",
        "motor",
        "engineer"
    ],
    "wof:name":"Sovereign Automotive",
    "wof:placetype":"venue"
},
  "geometry": {"coordinates":[115.82215100000001,-32.036961],"type":"Point"}
}