{
  "type": "Feature",
  "properties": {
    "addr:full":"18 Woodhurst Ave Hyde Park SA 5061",
    "addr:housenumber":"18",
    "addr:postcode":"5061",
    "addr:street":"Woodhurst Ave",
    "iso:country":"AU",
    "sg:address":"18 Woodhurst Ave",
    "sg:city":"Hyde Park",
    "sg:classifiers":[
        {
            "category":"Health Services",
            "subcategory":"Health Practitioner",
            "type":"Services"
        }
    ],
    "sg:phone":"+61 417 058 706",
    "sg:postcode":"5061",
    "sg:province":"SA",
    "sg:tags":[
        "bowen",
        "therapy"
    ],
    "wof:name":"Genevieve Miller",
    "wof:placetype":"venue"
},
  "geometry": {"coordinates":[138.59840393100001,-34.9569892883],"type":"Point"}
}