{
  "type": "Feature",
  "properties": {
    "addr:full":"2 Bluegum Pl Laurieton NSW 2443",
    "addr:housenumber":"2",
    "addr:postcode":"2443",
    "addr:street":"Bluegum Pl",
    "iso:country":"AU",
    "sg:address":"2 Bluegum Pl",
    "sg:city":"Laurieton",
    "sg:classifiers":[
        {
            "category":"Retail",
            "subcategory":"Auto Rental",
            "type":"Services"
        }
    ],
    "sg:phone":"+61 2 6559 4448",
    "sg:postcode":"2443",
    "sg:province":"NSW",
    "sg:tags":[
        "home",
        "hire",
        "motor",
        "campervans"
    ],
    "wof:name":"Johnnos Camper Trailers",
    "wof:placetype":"venue"
},
  "geometry": {"coordinates":[152.74989299999999,-31.645239],"type":"Point"}
}