{
  "type": "Feature",
  "properties": {
    "iso:country":"AU",
    "sg:address":"Unit 11/ 25 Hanson St",
    "sg:city":"Maddington",
    "sg:classifiers":[
        {
            "category":"Retail",
            "subcategory":"Auto Repair",
            "type":"Services"
        }
    ],
    "sg:phone":"+61 8 9493 4272",
    "sg:postcode":"6109",
    "sg:province":"WA",
    "sg:tags":[
        "repairer",
        "motor",
        "engineer"
    ],
    "wof:name":"Skinner Auto Repairs",
    "wof:placetype":"venue"
},
  "geometry": {"coordinates":[115.99609375,-32.0326919556],"type":"Point"}
}