{
  "type": "Feature",
  "properties": {
    "addr:full":"155 Edgecliff Rd Woollahra NSW 2025",
    "addr:housenumber":"155",
    "addr:postcode":"2025",
    "addr:street":"Edgecliff Rd",
    "iso:country":"AU",
    "sg:address":"155 Edgecliff Rd",
    "sg:city":"Woollahra",
    "sg:classifiers":[
        {
            "category":"Shopping",
            "subcategory":"Antiques",
            "type":"Retail Goods"
        }
    ],
    "sg:phone":"+61 2 9387 3318",
    "sg:postcode":"2025",
    "sg:province":"NSW",
    "wof:name":"Edwards Chandelier Design",
    "wof:placetype":"venue"
},
  "geometry": {"coordinates":[151.24205017099999,-33.884803772],"type":"Point"}
}