{
  "type": "Feature",
  "properties": {
    "addr:full":"RMB 510 Williams WA 6391",
    "addr:postcode":"6391",
    "iso:country":"AU",
    "sg:address":"RMB 510",
    "sg:city":"Williams",
    "sg:classifiers":[
        {
            "category":"Farming",
            "subcategory":"Farm",
            "type":"Manufacturing & Wholesale Goods"
        }
    ],
    "sg:phone":"+61 8 9885 7094",
    "sg:postcode":"6391",
    "sg:province":"WA",
    "sg:tags":[
        "farmer"
    ],
    "wof:name":"Cowcher G B & A T",
    "wof:placetype":"venue"
},
  "geometry": {"coordinates":[116.87805938699999,-33.0242881775],"type":"Point"}
}