{
  "type": "Feature",
  "properties": {
    "addr:full":"991 South Pine Rd Everton Park QLD 4053",
    "addr:housenumber":"991",
    "addr:postcode":"4053",
    "addr:street":"South Pine Rd",
    "iso:country":"AU",
    "sg:address":"991 South Pine Rd",
    "sg:city":"Everton Park",
    "sg:classifiers":[
        {
            "category":"Retail",
            "subcategory":"Auto Repair",
            "type":"Services"
        }
    ],
    "sg:phone":"+61 7 3355 2248",
    "sg:postcode":"4053",
    "sg:province":"QLD",
    "sg:tags":[
        "clutch",
        "brake"
    ],
    "wof:name":"Rev-Tech Mechanical",
    "wof:placetype":"venue"
},
  "geometry": {"coordinates":[152.97471618599999,-27.3915348053],"type":"Point"}
}