{
  "type": "Feature",
  "properties": {
    "iso:country":"AU",
    "sg:address":"Unit 6, Northport Business Park 441 Nudgee Rd",
    "sg:city":"Hendra",
    "sg:classifiers":[
        {
            "category":"Wholesale",
            "subcategory":"Apparel",
            "type":"Manufacturing & Wholesale Goods"
        }
    ],
    "sg:phone":"+61 7 3868 1333",
    "sg:postcode":"4011",
    "sg:province":"QLD",
    "sg:tags":[
        "wholesaler",
        "mfrs",
        "uniform"
    ],
    "wof:name":"Totally Corporate Pty Ltd",
    "wof:placetype":"venue"
},
  "geometry": {"coordinates":[153.07453918499999,-27.4153118134],"type":"Point"}
}