{
  "type": "Feature",
  "properties": {
    "iso:country":"AU",
    "sg:address":"117 Barney St",
    "sg:city":"Armidale",
    "sg:classifiers":[
        {
            "category":"Professional",
            "subcategory":"Accounting & Tax Preparation",
            "type":"Services"
        }
    ],
    "sg:phone":"+61 2 6770 1000",
    "sg:postcode":"2350",
    "sg:province":"NSW",
    "sg:tags":[
        "consultant",
        "taxation"
    ],
    "wof:name":"Malcolm & Associates",
    "wof:placetype":"venue"
},
  "geometry": {"coordinates":[151.666625977,-30.5169029236],"type":"Point"}
}