{
  "type": "Feature",
  "properties": {
    "iso:country":"AU",
    "sg:address":"Unit 4 18-22 Rochester St",
    "sg:city":"Botany",
    "sg:classifiers":[
        {
            "category":"Shopping",
            "subcategory":"Stationery & Office Supplies",
            "type":"Retail Goods"
        }
    ],
    "sg:phone":"+61 2 9666 1842",
    "sg:postcode":"2019",
    "sg:province":"NSW",
    "sg:tags":[
        "partition"
    ],
    "wof:name":"Baxter Constructions (Aust) Pty Ltd",
    "wof:placetype":"venue"
},
  "geometry": {"coordinates":[151.19842529300001,-33.9488868713],"type":"Point"}
}