{
  "type": "Feature",
  "properties": {
    "iso:country":"AU",
    "sg:address":"18 Greenhaven Drv",
    "sg:city":"Palmview",
    "sg:classifiers":[
        {
            "category":"Farming",
            "subcategory":"Fish & Marine Products",
            "type":"Manufacturing & Wholesale Goods"
        }
    ],
    "sg:phone":"+61 7 5494 5699",
    "sg:postcode":"4553",
    "sg:province":"QLD",
    "sg:tags":[
        "fisherman"
    ],
    "wof:name":"Festive Seafood",
    "wof:placetype":"venue"
},
  "geometry": {"coordinates":[153.052231,-26.759777],"type":"Point"}
}