{
  "type": "Feature",
  "properties": {
    "addr:full":"Fairway Ave Bribie Island QLD 4507",
    "addr:postcode":"4507",
    "addr:street":"Fairway Ave Bribie",
    "iso:country":"AU",
    "sg:address":"Fairway Ave",
    "sg:city":"Bribie Island",
    "sg:classifiers":[
        {
            "category":"Home & Garden",
            "subcategory":"Garden Supply",
            "type":"Retail Goods"
        }
    ],
    "sg:phone":"+61 408 193 090",
    "sg:postcode":"4507",
    "sg:province":"QLD",
    "sg:tags":[
        "turf",
        "lawn"
    ],
    "wof:name":"Bribie Island Turf",
    "wof:placetype":"venue"
},
  "geometry": {"coordinates":[153.19854736299999,-27.0725326538],"type":"Point"}
}