{
  "type": "Feature",
  "properties": {
    "addr:full":"Un 3, 83 Centennial Cct Byron Bay NSW 2481",
    "addr:housenumber":"83",
    "addr:postcode":"2481",
    "addr:street":"Centennial Cct",
    "iso:country":"AU",
    "sg:address":"Un 3, 83",
    "sg:city":"Centennial Cct Byron Bay",
    "sg:classifiers":[
        {
            "category":"Arts & Performance",
            "subcategory":"Art Gallery",
            "type":"Entertainment"
        }
    ],
    "sg:phone":"+61 2 6680 8884",
    "sg:postcode":"2481",
    "sg:province":"NSW",
    "wof:name":"Jessiah Art",
    "wof:placetype":"venue"
},
  "geometry": {"coordinates":[153.57948303200001,-28.6370677948],"type":"Point"}
}