{
  "type": "Feature",
  "properties": {
    "addr:full":"South Of Cleveland St Redfern NSW 2016",
    "addr:postcode":"2016",
    "addr:street":"St",
    "iso:country":"AU",
    "sg:address":"South Of Cleveland St",
    "sg:city":"Redfern",
    "sg:classifiers":[
        {
            "category":"Social Services",
            "subcategory":"Adult Care",
            "type":"Services"
        }
    ],
    "sg:phone":"+61 2 9690 1108",
    "sg:postcode":"2016",
    "sg:province":"NSW",
    "sg:tags":[
        "aged"
    ],
    "wof:name":"Meals On Wheels South Sydney",
    "wof:placetype":"venue"
},
  "geometry": {"coordinates":[151.206787109,-33.8931007385],"type":"Point"}
}