{
  "type": "Feature",
  "properties": {
    "addr:full":"3 Huggard Drv Mooroopna VIC 3629",
    "addr:housenumber":"3",
    "addr:postcode":"3629",
    "addr:street":"Huggard Drv",
    "iso:country":"AU",
    "sg:address":"3 Huggard Drv",
    "sg:city":"Mooroopna",
    "sg:classifiers":[
        {
            "category":"Manufacturing",
            "subcategory":"Chemicals & Compounds",
            "type":"Manufacturing & Wholesale Goods"
        }
    ],
    "sg:phone":"+61 3 5825 3222",
    "sg:postcode":"3629",
    "sg:province":"VIC",
    "sg:tags":[
        "agricultural"
    ],
    "wof:name":"Daldy R & C Pty Ltd",
    "wof:placetype":"venue"
},
  "geometry": {"coordinates":[145.340744019,-36.3640861511],"type":"Point"}
}