{
  "type": "Feature",
  "properties": {
    "addr:full":"238 Swanston St Melbourne VIC 3000",
    "addr:housenumber":"238",
    "addr:postcode":"3000",
    "addr:street":"Swanston St",
    "iso:country":"AU",
    "sg:address":"238 Swanston St",
    "sg:city":"Melbourne",
    "sg:classifiers":[
        {
            "category":"Shopping",
            "subcategory":"Mobile Phones",
            "type":"Retail Goods"
        }
    ],
    "sg:phone":"+61 3 9650 6188",
    "sg:postcode":"3000",
    "sg:province":"VIC",
    "sg:tags":[
        "telephone",
        "accessory"
    ],
    "wof:name":"Jumbo Rich Melbourne",
    "wof:placetype":"venue"
},
  "geometry": {"coordinates":[144.96522522000001,-37.8122825623],"type":"Point"}
}