{
  "type": "Feature",
  "properties": {
    "addr:full":"Level 1, 12 Browne St Campbelltown NSW 2560",
    "addr:housenumber":"12",
    "addr:postcode":"2560",
    "addr:street":"Browne St",
    "iso:country":"AU",
    "sg:address":"Level 1, 12 Browne St",
    "sg:city":"Campbelltown",
    "sg:classifiers":[
        {
            "category":"Professional",
            "subcategory":"Engineering",
            "type":"Services"
        }
    ],
    "sg:phone":"+61 2 4620 6181",
    "sg:postcode":"2560",
    "sg:province":"NSW",
    "sg:tags":[
        "consulting",
        "engineer"
    ],
    "wof:name":"E M Consulting Engineers",
    "wof:placetype":"venue"
},
  "geometry": {"coordinates":[150.817138672,-34.0653839111],"type":"Point"}
}