{
  "type": "Feature",
  "properties": {
    "addr:full":"14 Park St Woodville Park SA 5011",
    "addr:housenumber":"14",
    "addr:postcode":"5011",
    "addr:street":"Park St",
    "iso:country":"AU",
    "sg:address":"14 Park St",
    "sg:city":"Woodville Park",
    "sg:classifiers":[
        {
            "category":"Building & Trades",
            "subcategory":"Plumbing",
            "type":"Services"
        }
    ],
    "sg:phone":"+61 417 083 017",
    "sg:postcode":"5011",
    "sg:province":"SA",
    "sg:tags":[
        "plumber",
        "gasfitters"
    ],
    "wof:name":"Need Plumbing & Roofing Services",
    "wof:placetype":"venue"
},
  "geometry": {"coordinates":[138.546218872,-34.8802108765],"type":"Point"}
}