{
  "type": "Feature",
  "properties": {
    "addr:full":"31 Harlond Ave Malaga WA 6090",
    "addr:housenumber":"31",
    "addr:postcode":"6090",
    "addr:street":"Harlond Ave",
    "iso:country":"AU",
    "sg:address":"31 Harlond Ave",
    "sg:city":"Malaga",
    "sg:classifiers":[
        {
            "category":"Building & Trades",
            "subcategory":"Construction",
            "type":"Services"
        }
    ],
    "sg:phone":"+61 8 9248 5666",
    "sg:postcode":"6090",
    "sg:province":"WA",
    "sg:tags":[
        "course",
        "golf",
        "equipment"
    ],
    "wof:name":"Turf Management Services W.A.",
    "wof:placetype":"venue"
},
  "geometry": {"coordinates":[115.890319824,-31.8572311401],"type":"Point"}
}