{
  "type": "Feature",
  "properties": {
    "addr:full":"31 Ellesmere Rd Gymea Bay NSW 2227",
    "addr:housenumber":"31",
    "addr:postcode":"2227",
    "addr:street":"Ellesmere Rd",
    "iso:country":"AU",
    "sg:address":"31 Ellesmere Rd",
    "sg:city":"Gymea Bay",
    "sg:classifiers":[
        {
            "category":"Education",
            "subcategory":"Vocational School",
            "type":"Public Place"
        }
    ],
    "sg:phone":"+61 2 9525 4295",
    "sg:postcode":"2227",
    "sg:province":"NSW",
    "sg:tags":[
        "cake",
        "decorating",
        "decorator"
    ],
    "wof:name":"Classical Cake Decorating School",
    "wof:placetype":"venue"
},
  "geometry": {"coordinates":[151.09017944300001,-34.0514945984],"type":"Point"}
}