{
  "type": "Feature",
  "properties": {
    "iso:country":"AU",
    "sg:address":"37 Finniss St",
    "sg:city":"Marion",
    "sg:classifiers":[
        {
            "category":"Education",
            "subcategory":"School",
            "type":"Public Place"
        }
    ],
    "sg:phone":"+61 8 8296 8777",
    "sg:postcode":"5043",
    "sg:province":"SA",
    "sg:tags":[
        "co-educational"
    ],
    "wof:name":"St Ann's Special School",
    "wof:placetype":"venue"
},
  "geometry": {"coordinates":[138.555984,-35.008427],"type":"Point"}
}