{
  "type": "Feature",
  "properties": {
    "iso:country":"AU",
    "sg:address":"PMB 30 via",
    "sg:city":"Alice Springs",
    "sg:classifiers":[
        {
            "category":"Education",
            "subcategory":"School",
            "type":"Public Place"
        }
    ],
    "sg:phone":"+61 8 8956 0960",
    "sg:postcode":"0872",
    "sg:province":"NT",
    "sg:tags":[
        "state",
        "except",
        "nsw"
    ],
    "wof:name":"Finke School",
    "wof:placetype":"venue"
},
  "geometry": {"coordinates":[133.880935669,-23.7033290863],"type":"Point"}
}