{
  "type": "Feature",
  "properties": {
    "iso:country":"AU",
    "sg:address":"15 Nepean Hwy",
    "sg:city":"Seaford",
    "sg:classifiers":[
        {
            "category":"Autos & Motor Vehicles",
            "subcategory":"Fuel & Gas Station",
            "type":"Retail Goods"
        }
    ],
    "sg:phone":"+61 3 9776 4274",
    "sg:postcode":"3198",
    "sg:province":"VIC",
    "wof:name":"Plus Petrol",
    "wof:placetype":"venue"
},
  "geometry": {"coordinates":[145.12503051799999,-38.0874404907],"type":"Point"}
}