{
  "type": "Feature",
  "properties": {
    "iso:country":"AU",
    "sg:address":"150 Warnbro Beach Rd",
    "sg:city":"Waikiki",
    "sg:classifiers":[
        {
            "category":"Education",
            "subcategory":"School",
            "type":"Public Place"
        }
    ],
    "sg:phone":"+61 8 9527 9008",
    "sg:postcode":"6169",
    "sg:province":"WA",
    "sg:tags":[
        "supply"
    ],
    "wof:name":"Wincanton Enterprises",
    "wof:placetype":"venue"
},
  "geometry": {"coordinates":[115.74231,-32.324127],"type":"Point"}
}