{
  "type": "Feature",
  "properties": {
    "addr:full":"213 Sydney Rd Coburg VIC 3058",
    "addr:housenumber":"213",
    "addr:postcode":"3058",
    "addr:street":"Sydney Rd",
    "iso:country":"AU",
    "sg:address":"213 Sydney Rd",
    "sg:city":"Coburg",
    "sg:classifiers":[
        {
            "category":"Professional",
            "subcategory":"Engineering",
            "type":"Services"
        }
    ],
    "sg:phone":"+61 3 9386 5651",
    "sg:postcode":"3058",
    "sg:province":"VIC",
    "sg:tags":[
        "engineer"
    ],
    "wof:name":"Peverell Engineering",
    "wof:placetype":"venue"
},
  "geometry": {"coordinates":[144.96502685600001,-37.7495193481],"type":"Point"}
}