{
  "type": "Feature",
  "properties": {
    "iso:country":"AU",
    "sg:address":"41 Peel St South",
    "sg:city":"Ballarat",
    "sg:classifiers":[
        {
            "category":"Utilities",
            "type":"Services"
        }
    ],
    "sg:phone":"+61 3 5332 7248",
    "sg:postcode":"3350",
    "sg:province":"VIC",
    "sg:tags":[
        "equipment",
        "towing"
    ],
    "wof:name":"Go-Towin",
    "wof:placetype":"venue"
},
  "geometry": {"coordinates":[143.863998,-37.560799],"type":"Point"}
}