{
  "type": "Feature",
  "properties": {
    "addr:full":"Shop T25 The Galleria Smith St Darwin NT 0800",
    "addr:postcode":"nt 0800",
    "addr:street":"Smith St",
    "iso:country":"AU",
    "sg:address":"Shop T25 The Galleria Smith St",
    "sg:city":"Darwin",
    "sg:classifiers":[
        {
            "category":"Cafe",
            "type":"Food & Drink"
        }
    ],
    "sg:phone":"+61 8 8981 3092",
    "sg:postcode":"0800",
    "sg:province":"NT",
    "wof:name":"Alfresco-Darwin",
    "wof:placetype":"venue"
},
  "geometry": {"coordinates":[130.84129333499999,-12.4626169205],"type":"Point"}
}