{
  "type": "Feature",
  "properties": {
    "iso:country":"AU",
    "sg:address":"631 Ballarat Rd",
    "sg:city":"Albion",
    "sg:classifiers":[
        {
            "category":"Home & Garden",
            "subcategory":"Hardware",
            "type":"Retail Goods"
        }
    ],
    "sg:phone":"+61 3 9312 7777",
    "sg:postcode":"3020",
    "sg:province":"VIC",
    "sg:tags":[
        "compressor",
        "air"
    ],
    "wof:name":"Air Master Compressors Pty Ltd",
    "wof:placetype":"venue"
},
  "geometry": {"coordinates":[144.809784,-37.775017],"type":"Point"}
}