{
  "type": "Feature",
  "properties": {
    "addr:full":"445 Townsend St Albury NSW 2640",
    "addr:housenumber":"445",
    "addr:postcode":"2640",
    "addr:street":"Townsend St",
    "iso:country":"AU",
    "sg:address":"445 Townsend St",
    "sg:city":"Albury",
    "sg:classifiers":[
        {
            "category":"Real Estate",
            "subcategory":"Surveying",
            "type":"Services"
        }
    ],
    "sg:phone":"+61 2 6041 2456",
    "sg:postcode":"2640",
    "sg:province":"NSW",
    "sg:tags":[
        "surveyor",
        "land"
    ],
    "wof:name":"Douglas Gow & Associates",
    "wof:placetype":"venue"
},
  "geometry": {"coordinates":[146.91290283199999,-36.0805664062],"type":"Point"}
}