{
  "type": "Feature",
  "properties": {
    "addr:full":"Bass Hwy Sassafras TAS 7307",
    "addr:postcode":"7307",
    "addr:street":"Bass Hwy",
    "iso:country":"AU",
    "sg:address":"Bass Hwy",
    "sg:city":"Sassafras",
    "sg:classifiers":[
        {
            "category":"Food & Beverages",
            "subcategory":"Fruits & Vegetables",
            "type":"Retail Goods"
        }
    ],
    "sg:phone":"+61 3 6426 7344",
    "sg:postcode":"7307",
    "sg:province":"TAS",
    "sg:tags":[
        "greengrocer",
        "fruiterer"
    ],
    "wof:name":"Big Spud",
    "wof:placetype":"venue"
},
  "geometry": {"coordinates":[146.494034,-41.283924],"type":"Point"}
}