{
  "type": "Feature",
  "properties": {
    "addr:full":"Cnr South Western Hwy & Needes Hill Rd Newlands WA 6251",
    "addr:postcode":"6251",
    "addr:street":"Cnr South Western Hwy & Needes Hill Rd",
    "iso:country":"AU",
    "sg:address":"Cnr South Western Hwy & Needes Hill Rd",
    "sg:city":"Newlands",
    "sg:classifiers":[
        {
            "category":"Farming",
            "subcategory":"Vineyard",
            "type":"Manufacturing & Wholesale Goods"
        }
    ],
    "sg:phone":"+61 8 9731 6349",
    "sg:postcode":"6251",
    "sg:province":"WA",
    "sg:tags":[
        "winery"
    ],
    "wof:name":"Donneybrook Valley Winery",
    "wof:placetype":"venue"
},
  "geometry": {"coordinates":[115.87689209,-33.6692504883],"type":"Point"}
}