{
  "type": "Feature",
  "properties": {
    "iso:country":"AU",
    "sg:address":"3/ 38 Scott St",
    "sg:city":"Elwood",
    "sg:classifiers":[
        {
            "category":"Building & Trades",
            "subcategory":"Construction",
            "type":"Services"
        }
    ],
    "sg:phone":"+61 419 330 820",
    "sg:postcode":"3184",
    "sg:province":"VIC",
    "sg:tags":[
        "window",
        "tinting"
    ],
    "wof:name":"Filmworx",
    "wof:placetype":"venue"
},
  "geometry": {"coordinates":[144.99009704599999,-37.880443573],"type":"Point"}
}