{
  "type": "Feature",
  "properties": {
    "addr:full":"83 Albury St Holbrook NSW 2644",
    "addr:housenumber":"83",
    "addr:postcode":"2644",
    "addr:street":"Albury St",
    "iso:country":"AU",
    "sg:address":"83 Albury St",
    "sg:city":"Holbrook",
    "sg:classifiers":[
        {
            "category":"Museum",
            "type":"Entertainment"
        }
    ],
    "sg:phone":"+61 2 6036 2131",
    "sg:postcode":"2644",
    "sg:province":"NSW",
    "wof:name":"Woolpack Inn Museum",
    "wof:placetype":"venue"
},
  "geometry": {"coordinates":[147.31758117699999,-35.7186012268],"type":"Point"}
}