{
  "type": "Feature",
  "properties": {
    "addr:full":"Kent St Maryborough QLD 4650",
    "addr:postcode":"4650",
    "addr:street":"Kent St",
    "iso:country":"AU",
    "sg:address":"Kent St",
    "sg:city":"Maryborough",
    "sg:classifiers":[
        {
            "category":"Utilities",
            "subcategory":"Fuel Oil & Lpg",
            "type":"Services"
        }
    ],
    "sg:phone":"+61 7 4121 3912",
    "sg:postcode":"4650",
    "sg:province":"QLD",
    "sg:tags":[
        "merchant"
    ],
    "wof:name":"BP Australia Limited",
    "wof:placetype":"venue"
},
  "geometry": {"coordinates":[152.694839,-25.532106],"type":"Point"}
}