{
  "type": "Feature",
  "properties": {
    "addr:full":"1 Livingston Rd Yarram VIC 3971",
    "addr:housenumber":"1",
    "addr:postcode":"3971",
    "addr:street":"Livingston Rd",
    "iso:country":"AU",
    "sg:address":"1 Livingston Rd",
    "sg:city":"Yarram",
    "sg:classifiers":[
        {
            "category":"Retail",
            "subcategory":"Auto Repair",
            "type":"Services"
        }
    ],
    "sg:phone":"+61 3 5182 5253",
    "sg:postcode":"3971",
    "sg:province":"VIC",
    "sg:tags":[
        "beater",
        "painter",
        "panel"
    ],
    "wof:name":"Yarram Body Works",
    "wof:placetype":"venue"
},
  "geometry": {"coordinates":[146.67555236800001,-38.5609664917],"type":"Point"}
}