{
  "type": "Feature",
  "properties": {
    "iso:country":"AU",
    "sg:address":"22 High St",
    "sg:city":"Kapunda",
    "sg:classifiers":[
        {
            "category":"Professional",
            "subcategory":"Detective & Security Services",
            "type":"Services"
        }
    ],
    "sg:phone":"+61 8 8566 2956",
    "sg:postcode":"5373",
    "sg:province":"SA",
    "sg:tags":[
        "domestic",
        "alarm",
        "commercial",
        "burglar"
    ],
    "wof:name":"Bolts Electrical Service & Technology",
    "wof:placetype":"venue"
},
  "geometry": {"coordinates":[138.91394043,-34.3345031738],"type":"Point"}
}