{
  "type": "Feature",
  "properties": {
    "iso:country":"AU",
    "sg:address":"22 Moppett Rd",
    "sg:city":"Port Pirie",
    "sg:classifiers":[
        {
            "category":"Food & Beverages",
            "subcategory":"Liquor & Beverages",
            "type":"Retail Goods"
        }
    ],
    "sg:phone":"+61 8 8632 2663",
    "sg:postcode":"5540",
    "sg:province":"SA",
    "sg:tags":[
        "store"
    ],
    "wof:name":"Risdon Hotel Liquorsmart",
    "wof:placetype":"venue"
},
  "geometry": {"coordinates":[138.00213623100001,-33.1851730347],"type":"Point"}
}