{
  "type": "Feature",
  "properties": {
    "iso:country":"AU",
    "sg:address":"Shp 2/ 1343 Princes Hwy",
    "sg:city":"Heathcote",
    "sg:classifiers":[
        {
            "category":"Food & Beverages",
            "subcategory":"Bakery",
            "type":"Retail Goods"
        }
    ],
    "sg:phone":"+61 2 9520 7754",
    "sg:postcode":"2233",
    "sg:province":"NSW",
    "sg:tags":[
        "baker"
    ],
    "wof:name":"Heathcote Bakehouse",
    "wof:placetype":"venue"
},
  "geometry": {"coordinates":[151.00822448700001,-34.0869102478],"type":"Point"}
}