{
  "type": "Feature",
  "properties": {
    "iso:country":"AU",
    "sg:address":"225 Goldsmith St",
    "sg:city":"Mackay",
    "sg:classifiers":[
        {
            "category":"Insurance",
            "subcategory":"Life Insurance",
            "type":"Services"
        }
    ],
    "sg:phone":"+61 7 4957 7907",
    "sg:postcode":"4740",
    "sg:province":"QLD",
    "wof:name":"Sam Curcuruto Financial Services",
    "wof:placetype":"venue"
},
  "geometry": {"coordinates":[149.19136,-21.165888],"type":"Point"}
}