{
  "type": "Feature",
  "properties": {
    "iso:country":"AU",
    "sg:address":"139 Wharf St",
    "sg:city":"Tweed Heads",
    "sg:classifiers":[
        {
            "category":"Autos & Motor Vehicles",
            "subcategory":"Automobile Sales",
            "type":"Retail Goods"
        }
    ],
    "sg:phone":"+61 7 5536 3533",
    "sg:postcode":"2485",
    "sg:province":"NSW",
    "sg:tags":[
        "car",
        "new"
    ],
    "wof:name":"Southcoast Automotive",
    "wof:placetype":"venue"
},
  "geometry": {"coordinates":[153.54367065400001,-28.1692829132],"type":"Point"}
}