{
  "type": "Feature",
  "properties": {
    "iso:country":"AU",
    "sg:address":"378 Chapel St",
    "sg:city":"South Yarra",
    "sg:classifiers":[
        {
            "category":"Shopping",
            "subcategory":"Jewelry",
            "type":"Retail Goods"
        }
    ],
    "sg:phone":"+61 3 9827 5007",
    "sg:postcode":"3141",
    "sg:province":"VIC",
    "sg:tags":[
        "jeweller"
    ],
    "wof:name":"C S P Jewellers",
    "wof:placetype":"venue"
},
  "geometry": {"coordinates":[144.99444580100001,-37.8461608887],"type":"Point"}
}