{
  "type": "Feature",
  "properties": {
    "iso:country":"AU",
    "sg:address":"Building P4 Bourke St",
    "sg:city":"Richmond",
    "sg:classifiers":[
        {
            "category":"Social Services",
            "subcategory":"Child Care",
            "type":"Services"
        }
    ],
    "sg:phone":"+61 2 4570 1617",
    "sg:postcode":"2753",
    "sg:province":"NSW",
    "wof:name":"University Of Western Sydney Hawkesbury Child Care Centre",
    "wof:placetype":"venue"
},
  "geometry": {"coordinates":[150.758743286,-33.6015510559],"type":"Point"}
}