{
  "type": "Feature",
  "properties": {
    "iso:country":"AU",
    "sg:address":"3 Arrunga Crt",
    "sg:city":"Patterson Lakes",
    "sg:classifiers":[
        {
            "category":"Professional",
            "subcategory":"Art Services",
            "type":"Services"
        }
    ],
    "sg:phone":"+61 407 722 416",
    "sg:postcode":"3197",
    "sg:province":"VIC",
    "sg:tags":[
        "graphic",
        "designer"
    ],
    "wof:name":"Design By Oaks",
    "wof:placetype":"venue"
},
  "geometry": {"coordinates":[145.14877319300001,-38.0746803284],"type":"Point"}
}