{
  "type": "Feature",
  "properties": {
    "addr:full":"3- 7 Grosvenor St Abbotsford VIC 3067",
    "addr:housenumber":"7",
    "addr:postcode":"3067",
    "addr:street":"Grosvenor St",
    "iso:country":"AU",
    "sg:address":"3- 7 Grosvenor St",
    "sg:city":"Abbotsford",
    "sg:classifiers":[
        {
            "category":"Communications",
            "type":"Services"
        }
    ],
    "sg:phone":"+61 3 8420 7768",
    "sg:postcode":"3067",
    "sg:province":"VIC",
    "sg:tags":[
        "public",
        "system",
        "address"
    ],
    "wof:name":"Emerald Hill Stationers Pty Ltd",
    "wof:placetype":"venue"
},
  "geometry": {"coordinates":[145.00619506800001,-37.8106460571],"type":"Point"}
}