{
  "type": "Feature",
  "properties": {
    "iso:country":"AU",
    "sg:address":"272 Waverly Rd",
    "sg:city":"Malvern East",
    "sg:classifiers":[
        {
            "category":"Fast Food",
            "type":"Food & Drink"
        }
    ],
    "sg:phone":"+61 3 9571 5334",
    "sg:postcode":"3145",
    "sg:province":"VIC",
    "sg:tags":[
        "away",
        "take"
    ],
    "wof:name":"Dine At Home",
    "wof:placetype":"venue"
},
  "geometry": {"coordinates":[145.05714416500001,-37.877166748],"type":"Point"}
}