{
  "type": "Feature",
  "properties": {
    "iso:country":"AU",
    "sg:address":"634- 726 Princes Hwy",
    "sg:city":"Tempe",
    "sg:classifiers":[
        {
            "category":"Autos & Motor Vehicles",
            "subcategory":"Auto Supplies",
            "type":"Retail Goods"
        }
    ],
    "sg:phone":"+61 2 9558 9055",
    "sg:postcode":"2044",
    "sg:province":"NSW",
    "sg:tags":[
        "wheel",
        "automotive",
        "rim"
    ],
    "wof:name":"Auscar Alloy Wheels",
    "wof:placetype":"venue"
},
  "geometry": {"coordinates":[151.16377299999999,-33.92244],"type":"Point"}
}