{
  "type": "Feature",
  "properties": {
    "addr:full":"191 Gouger St Adelaide SA 5000",
    "addr:housenumber":"191",
    "addr:postcode":"5000",
    "addr:street":"Gouger St",
    "iso:country":"AU",
    "sg:address":"191 Gouger St",
    "sg:city":"Adelaide",
    "sg:classifiers":[
        {
            "category":"Autos & Motor Vehicles",
            "subcategory":"Automobile Sales",
            "type":"Retail Goods"
        }
    ],
    "sg:phone":"+61 8 8231 0500",
    "sg:postcode":"5000",
    "sg:province":"SA",
    "sg:tags":[
        "car",
        "new"
    ],
    "wof:name":"BEA Motors",
    "wof:placetype":"venue"
},
  "geometry": {"coordinates":[138.592453003,-34.9306411743],"type":"Point"}
}