{
  "type": "Feature",
  "properties": {
    "iso:country":"AU",
    "sg:address":"127 Hogan St",
    "sg:city":"Tatura",
    "sg:classifiers":[
        {
            "category":"Professional",
            "subcategory":"Accounting & Tax Preparation",
            "type":"Services"
        }
    ],
    "sg:phone":"+61 3 5824 1311",
    "sg:postcode":"3616",
    "sg:province":"VIC",
    "sg:tags":[
        "consultant",
        "taxation"
    ],
    "wof:name":"Trevaskis Pty. Ltd.",
    "wof:placetype":"venue"
},
  "geometry": {"coordinates":[145.227294922,-36.4399757385],"type":"Point"}
}