{
  "type": "Feature",
  "properties": {
    "iso:country":"AU",
    "sg:address":"Gillespie St",
    "sg:city":"Moura",
    "sg:classifiers":[
        {
            "category":"Food & Beverages",
            "subcategory":"Supermarket",
            "type":"Retail Goods"
        }
    ],
    "sg:phone":"+61 7 4997 1601",
    "sg:postcode":"4718",
    "sg:province":"QLD",
    "sg:tags":[
        "grocery",
        "store"
    ],
    "wof:name":"Cornetts Supermarkets",
    "wof:placetype":"venue"
},
  "geometry": {"coordinates":[149.97471618599999,-24.5669994354],"type":"Point"}
}