{
  "type": "Feature",
  "properties": {
    "addr:full":"86 Chandos St Leonards NSW 2065",
    "addr:housenumber":"86",
    "addr:postcode":"2065",
    "addr:street":"Chandos",
    "iso:country":"AU",
    "sg:address":"86 Chandos",
    "sg:city":"St Leonards",
    "sg:classifiers":[
        {
            "category":"Wholesale",
            "subcategory":"Machinery & Supplies",
            "type":"Manufacturing & Wholesale Goods"
        }
    ],
    "sg:phone":"+61 2 9906 8355",
    "sg:postcode":"2065",
    "sg:province":"NSW",
    "sg:tags":[
        "instrument",
        "scientific"
    ],
    "wof:name":"Taylor Bryant Pty Ltd",
    "wof:placetype":"venue"
},
  "geometry": {"coordinates":[151.19955444300001,-33.8218994141],"type":"Point"}
}