{
  "type": "Feature",
  "properties": {
    "addr:full":"4 Trahlee Rd Bellevue Hill NSW 2023",
    "addr:housenumber":"4",
    "addr:postcode":"2023",
    "addr:street":"Trahlee Rd",
    "iso:country":"AU",
    "sg:address":"4 Trahlee Rd",
    "sg:city":"Bellevue Hill",
    "sg:classifiers":[
        {
            "category":"Professional",
            "subcategory":"Art Services",
            "type":"Services"
        }
    ],
    "sg:phone":"+61 2 9327 3050",
    "sg:postcode":"2023",
    "sg:province":"NSW",
    "wof:name":"Sharpe V",
    "wof:placetype":"venue"
},
  "geometry": {"coordinates":[151.24847412099999,-33.8764572144],"type":"Point"}
}