{
  "type": "Feature",
  "properties": {
    "addr:full":"100 Exhibition St Melbourne VIC 3000",
    "addr:housenumber":"100",
    "addr:postcode":"3000",
    "addr:street":"Exhibition St",
    "iso:country":"AU",
    "sg:address":"100 Exhibition St",
    "sg:city":"Melbourne",
    "sg:classifiers":[
        {
            "category":"Banks & Credit Unions",
            "subcategory":"Bank",
            "type":"Services"
        }
    ],
    "sg:phone":"+61 3 8633 5555",
    "sg:postcode":"3000",
    "sg:province":"VIC",
    "wof:name":"Bank of Queensland",
    "wof:placetype":"venue"
},
  "geometry": {"coordinates":[144.97134399399999,-37.8133926392],"type":"Point"}
}