{
  "type": "Feature",
  "properties": {
    "addr:full":"unit 2 \\\\ 8 Jacka Strs Macleod VIC 3085",
    "addr:postcode":"3085",
    "iso:country":"AU",
    "sg:address":"unit 2 \\\\ 8",
    "sg:city":"Jacka Strs Macleod",
    "sg:classifiers":[
        {
            "category":"Shopping",
            "subcategory":"Computers & Home Electronics",
            "type":"Retail Goods"
        }
    ],
    "sg:phone":"+61 414 622 096",
    "sg:postcode":"3085",
    "sg:province":"VIC",
    "sg:tags":[
        "equipment",
        "multimedia"
    ],
    "wof:name":"St. Wols",
    "wof:placetype":"venue"
},
  "geometry": {"coordinates":[145.067062378,-37.7294235229],"type":"Point"}
}