{
  "type": "Feature",
  "properties": {
    "addr:full":"92 Oxford St Woollahra NSW 2025",
    "addr:housenumber":"92",
    "addr:postcode":"2025",
    "addr:street":"Oxford St",
    "iso:country":"AU",
    "sg:address":"92 Oxford St",
    "sg:city":"Woollahra",
    "sg:classifiers":[
        {
            "category":"Retail",
            "subcategory":"Auto Repair",
            "type":"Services"
        }
    ],
    "sg:phone":"+61 2 9363 3177",
    "sg:postcode":"2025",
    "sg:province":"NSW",
    "sg:tags":[
        "repairer",
        "motor",
        "engineer"
    ],
    "wof:name":"Midas",
    "wof:placetype":"venue"
},
  "geometry": {"coordinates":[151.235565186,-33.8900337219],"type":"Point"}
}