{
  "type": "Feature",
  "properties": {
    "addr:full":"U8/ 42 Global Drv Westmeadows VIC 3049",
    "addr:housenumber":"42",
    "addr:postcode":"3049",
    "addr:street":"U8 /;Global Drv",
    "iso:country":"AU",
    "sg:address":"U8/ 42 Global Drv",
    "sg:city":"Westmeadows",
    "sg:classifiers":[
        {
            "category":"Farming",
            "subcategory":"Nursery",
            "type":"Manufacturing & Wholesale Goods"
        }
    ],
    "sg:phone":"+61 3 9330 4077",
    "sg:postcode":"3049",
    "sg:province":"VIC",
    "wof:name":"United Nurseries Pty Ltd",
    "wof:placetype":"venue"
},
  "geometry": {"coordinates":[144.877365,-37.68354],"type":"Point"}
}