{
  "type": "Feature",
  "properties": {
    "addr:full":"321 Malabar Rd Maroubra NSW 2035",
    "addr:housenumber":"321",
    "addr:postcode":"2035",
    "addr:street":"Malabar Rd",
    "iso:country":"AU",
    "sg:address":"321 Malabar Rd",
    "sg:city":"Maroubra",
    "sg:classifiers":[
        {
            "category":"Health Services",
            "subcategory":"Health Practitioner",
            "type":"Services"
        }
    ],
    "sg:phone":"+61 2 9349 4253",
    "sg:postcode":"2035",
    "sg:province":"NSW",
    "sg:tags":[
        "dietitian"
    ],
    "wof:name":"Alison Miles",
    "wof:placetype":"venue"
},
  "geometry": {"coordinates":[151.25733947800001,-33.938709259],"type":"Point"}
}