{
  "type": "Feature",
  "properties": {
    "addr:full":"170 South Creek Rd Dee Why NSW 2099",
    "addr:housenumber":"170",
    "addr:postcode":"2099",
    "addr:street":"South Creek Rd",
    "iso:country":"AU",
    "sg:address":"170 South Creek Rd",
    "sg:city":"Dee Why",
    "sg:classifiers":[
        {
            "category":"Retail",
            "subcategory":"Auto Repair",
            "type":"Services"
        }
    ],
    "sg:phone":"+61 402 727 040",
    "sg:postcode":"2099",
    "sg:province":"NSW",
    "sg:tags":[
        "beater",
        "painter",
        "panel"
    ],
    "wof:name":"Up-To-Scratch",
    "wof:placetype":"venue"
},
  "geometry": {"coordinates":[151.28004455600001,-33.7347373962],"type":"Point"}
}