{
  "type": "Feature",
  "properties": {
    "addr:full":"10 Roberts St West Osborne Park WA 6017",
    "addr:housenumber":"10",
    "addr:postcode":"6017",
    "addr:street":"Roberts St West",
    "iso:country":"AU",
    "sg:address":"10 Roberts St",
    "sg:city":"West Osborne Park",
    "sg:classifiers":[
        {
            "category":"Professional",
            "subcategory":"Computer Services",
            "type":"Services"
        }
    ],
    "sg:phone":"+61 8 9444 4522",
    "sg:postcode":"6017",
    "sg:province":"WA",
    "sg:tags":[
        "package",
        "software"
    ],
    "wof:name":"Project Software Solutions",
    "wof:placetype":"venue"
},
  "geometry": {"coordinates":[115.819007873,-31.907907486],"type":"Point"}
}