{
  "type": "Feature",
  "properties": {
    "iso:country":"AU",
    "sg:address":"187 James St",
    "sg:city":"Toowoomba",
    "sg:classifiers":[
        {
            "category":"Autos & Motor Vehicles",
            "subcategory":"Auto Supplies",
            "type":"Retail Goods"
        }
    ],
    "sg:phone":"+61 7 4632 5453",
    "sg:postcode":"4350",
    "sg:province":"QLD",
    "sg:tags":[
        "automotive",
        "stereo",
        "radio"
    ],
    "sg:website":"http://www.rodmeagherradio.com",
    "wof:name":"Rod Meagher Radio",
    "wof:placetype":"venue"
},
  "geometry": {"coordinates":[151.953156,-27.568687],"type":"Point"}
}