{
  "type": "Feature",
  "properties": {
    "addr:full":"8 Scott St Essendon VIC 3040",
    "addr:housenumber":"8",
    "addr:postcode":"3040",
    "addr:street":"Scott St",
    "iso:country":"AU",
    "sg:address":"8 Scott St",
    "sg:city":"Essendon",
    "sg:classifiers":[
        {
            "category":"Education",
            "subcategory":"Special Training",
            "type":"Public Place"
        }
    ],
    "sg:phone":"+61 3 9331 3350",
    "sg:postcode":"3040",
    "sg:province":"VIC",
    "sg:tags":[
        "development"
    ],
    "wof:name":"Davanna Consulting",
    "wof:placetype":"venue"
},
  "geometry": {"coordinates":[144.90815734899999,-37.7567520142],"type":"Point"}
}