{
  "type": "Feature",
  "properties": {
    "iso:country":"AU",
    "sg:address":"8 Allen Pl",
    "sg:city":"Wetherill Park",
    "sg:classifiers":[
        {
            "category":"Home & Garden",
            "subcategory":"Household Appliances",
            "type":"Retail Goods"
        }
    ],
    "sg:phone":"+61 2 9756 0388",
    "sg:postcode":"2164",
    "sg:province":"NSW",
    "sg:tags":[
        "equipment",
        "gas"
    ],
    "wof:name":"Nationwide Electrical Wholesale Pty Ltd",
    "wof:placetype":"venue"
},
  "geometry": {"coordinates":[150.899368286,-33.848072052],"type":"Point"}
}