{
  "type": "Feature",
  "properties": {
    "addr:full":"Lot 40 Farrall Rd North Midvale WA 6056",
    "addr:postcode":"6056",
    "addr:street":"Farrall Rd North",
    "iso:country":"AU",
    "sg:address":"Lot 40 Farrall Rd",
    "sg:city":"North Midvale",
    "sg:classifiers":[
        {
            "category":"Farming",
            "subcategory":"Fish & Marine Products",
            "type":"Manufacturing & Wholesale Goods"
        }
    ],
    "sg:phone":"+61 8 9250 4575",
    "sg:postcode":"6056",
    "sg:province":"WA",
    "sg:tags":[
        "organic"
    ],
    "wof:name":"Swan Garden Centre",
    "wof:placetype":"venue"
},
  "geometry": {"coordinates":[116.03362274200001,-31.8843612671],"type":"Point"}
}