{
  "type": "Feature",
  "properties": {
    "addr:full":"3 Alfred Ave Beverley SA 5009",
    "addr:housenumber":"3",
    "addr:postcode":"5009",
    "addr:street":"Alfred Ave Beverley",
    "iso:country":"AU",
    "sg:address":"3 Alfred Ave",
    "sg:city":"Beverley",
    "sg:classifiers":[
        {
            "category":"Manufacturing",
            "subcategory":"Tools & Machinery",
            "type":"Manufacturing & Wholesale Goods"
        }
    ],
    "sg:phone":"+61 8 8268 4495",
    "sg:postcode":"5009",
    "sg:province":"SA",
    "sg:tags":[
        "toolmaker"
    ],
    "wof:name":"Lepol Tooling & Engineering",
    "wof:placetype":"venue"
},
  "geometry": {"coordinates":[138.546112061,-34.8945236206],"type":"Point"}
}