{
  "type": "Feature",
  "properties": {
    "iso:country":"AU",
    "sg:address":"34 Spindrift Rd",
    "sg:city":"Port Macquarie",
    "sg:classifiers":[
        {
            "category":"Professional",
            "subcategory":"Employment Agencies",
            "type":"Services"
        }
    ],
    "sg:phone":"+61 2 6583 5554",
    "sg:postcode":"2444",
    "sg:province":"NSW",
    "wof:name":"WTSD Pty Ltd",
    "wof:placetype":"venue"
},
  "geometry": {"coordinates":[152.919327,-31.474705],"type":"Point"}
}