{
  "type": "Feature",
  "properties": {
    "addr:full":"68 Albany St Coffs Harbour NSW 2450",
    "addr:housenumber":"68",
    "addr:postcode":"2450",
    "addr:street":"Albany St",
    "iso:country":"AU",
    "sg:address":"68 Albany St",
    "sg:city":"Coffs Harbour",
    "sg:classifiers":[
        {
            "category":"Government",
            "subcategory":"Court House",
            "type":"Public Place"
        }
    ],
    "sg:phone":"+61 2 6652 2825",
    "sg:postcode":"2450",
    "sg:province":"NSW",
    "sg:tags":[
        "personal",
        "marriage",
        "family",
        "counselling"
    ],
    "wof:name":"C & I McCombie",
    "wof:placetype":"venue"
},
  "geometry": {"coordinates":[153.11540199999999,-30.300514],"type":"Point"}
}