{
  "type": "Feature",
  "properties": {
    "iso:country":"AU",
    "sg:address":"49 Peel St",
    "sg:city":"Mackay",
    "sg:classifiers":[
        {
            "category":"Organizations",
            "subcategory":"Non-profit Organization",
            "type":"Services"
        }
    ],
    "sg:phone":"+61 7 4953 5118",
    "sg:postcode":"4740",
    "sg:province":"QLD",
    "sg:tags":[
        "support",
        "disability",
        "organisation"
    ],
    "wof:name":"Mainstream Community Association Inc",
    "wof:placetype":"venue"
},
  "geometry": {"coordinates":[149.178894,-21.146351],"type":"Point"}
}