{
  "type": "Feature",
  "properties": {
    "iso:country":"AU",
    "sg:address":"19 Lurline St",
    "sg:city":"Albany",
    "sg:classifiers":[
        {
            "category":"Professional",
            "type":"Services"
        }
    ],
    "sg:phone":"+61 419 834 185",
    "sg:postcode":"6330",
    "sg:province":"WA",
    "sg:tags":[
        "spray",
        "painting"
    ],
    "wof:name":"Rainbow Coast Mobile Spray Painting",
    "wof:placetype":"venue"
},
  "geometry": {"coordinates":[117.852653503,-34.998916626],"type":"Point"}
}