{
  "type": "Feature",
  "properties": {
    "iso:country":"AU",
    "sg:address":"49 Bundock St",
    "sg:city":"Belgian Gardens",
    "sg:classifiers":[
        {
            "category":"Professional",
            "subcategory":"Engineering",
            "type":"Services"
        }
    ],
    "sg:phone":"+61 7 4772 4722",
    "sg:postcode":"4810",
    "sg:province":"QLD",
    "sg:tags":[
        "consulting",
        "engineer"
    ],
    "wof:name":"Glynn Tucker Consulting Engineers",
    "wof:placetype":"venue"
},
  "geometry": {"coordinates":[146.795486,-19.246086],"type":"Point"}
}