{
  "type": "Feature",
  "properties": {
    "addr:full":"21-23 Chapel St Windsor VIC 3181",
    "addr:housenumber":"21-23",
    "addr:postcode":"3181",
    "addr:street":"Chapel St",
    "iso:country":"AU",
    "sg:address":"21-23 Chapel St",
    "sg:city":"Windsor",
    "sg:classifiers":[
        {
            "category":"Food & Beverages",
            "subcategory":"Groceries & Convenience Stores",
            "type":"Retail Goods"
        }
    ],
    "sg:phone":"+61 3 9521 3667",
    "sg:postcode":"3181",
    "sg:province":"VIC",
    "wof:name":"Chapel Convenience Store",
    "wof:placetype":"venue"
},
  "geometry": {"coordinates":[144.992263794,-37.856842041],"type":"Point"}
}