{
  "type": "Feature",
  "properties": {
    "addr:full":"Lot 8 Phillip Pde Churchill VIC 3842",
    "addr:postcode":"3842",
    "addr:street":"Phillip Pde",
    "iso:country":"AU",
    "sg:address":"Lot 8 Phillip Pde",
    "sg:city":"Churchill",
    "sg:classifiers":[
        {
            "category":"Retail",
            "subcategory":"Auto Repair",
            "type":"Services"
        }
    ],
    "sg:phone":"+61 3 5122 1380",
    "sg:postcode":"3842",
    "sg:province":"VIC",
    "sg:tags":[
        "repairer",
        "motor",
        "engineer"
    ],
    "wof:name":"Churchill Motors (New)",
    "wof:placetype":"venue"
},
  "geometry": {"coordinates":[146.421340942,-38.3145675659],"type":"Point"}
}