{
  "type": "Feature",
  "properties": {
    "iso:country":"AU",
    "sg:address":"80 Marsden St",
    "sg:city":"Parramatta",
    "sg:classifiers":[
        {
            "category":"Health Services",
            "subcategory":"Dentist",
            "type":"Services"
        }
    ],
    "sg:phone":"+61 2 9893 9377",
    "sg:postcode":"2150",
    "sg:province":"NSW",
    "wof:name":"Ng J",
    "wof:placetype":"venue"
},
  "geometry": {"coordinates":[151.04623413100001,-33.8655014038],"type":"Point"}
}