{
  "type": "Feature",
  "properties": {
    "iso:country":"AU",
    "sg:address":"103 Balga Ave",
    "sg:city":"Balga",
    "sg:classifiers":[
        {
            "category":"Education",
            "subcategory":"Kindergarten",
            "type":"Public Place"
        }
    ],
    "sg:phone":"+61 8 9342 2897",
    "sg:postcode":"6061",
    "sg:province":"WA",
    "sg:tags":[
        "pre-schools"
    ],
    "wof:name":"Warriapendi Kindergarten",
    "wof:placetype":"venue"
},
  "geometry": {"coordinates":[115.847831726,-31.856967926],"type":"Point"}
}