{
  "type": "Feature",
  "properties": {
    "addr:full":"PO Box 332 Goulburn NSW 2580",
    "addr:postcode":"2580",
    "iso:country":"AU",
    "sg:address":"PO Box 332",
    "sg:city":"Goulburn",
    "sg:classifiers":[
        {
            "category":"Building & Trades",
            "subcategory":"Construction",
            "type":"Services"
        }
    ],
    "sg:phone":"+61 2 4821 2000",
    "sg:postcode":"2580",
    "sg:province":"NSW",
    "sg:tags":[
        "contractor"
    ],
    "wof:name":"Anable & Ridley Constructions Pty. Ltd.",
    "wof:placetype":"venue"
},
  "geometry": {"coordinates":[149.716262817,-34.7571792603],"type":"Point"}
}