{
  "type": "Feature",
  "properties": {
    "iso:country":"AU",
    "sg:address":"Lvl1/ 170 Buckhurst St",
    "sg:city":"South Melbourne",
    "sg:classifiers":[
        {
            "category":"Professional",
            "subcategory":"Computer Services",
            "type":"Services"
        }
    ],
    "sg:phone":"+61 3 9686 7630",
    "sg:postcode":"3205",
    "sg:province":"VIC",
    "sg:tags":[
        "on-line",
        "provider"
    ],
    "wof:name":"Interact Pacific Pty Ltd",
    "wof:placetype":"venue"
},
  "geometry": {"coordinates":[144.948395,-37.832043],"type":"Point"}
}