{
  "type": "Feature",
  "properties": {
    "addr:full":"9 Hospital St Mossman QLD 4873",
    "addr:housenumber":"9",
    "addr:postcode":"4873",
    "addr:street":"Hospital St",
    "iso:country":"AU",
    "sg:address":"9 Hospital St",
    "sg:city":"Mossman",
    "sg:classifiers":[
        {
            "category":"Health Services",
            "subcategory":"Dentist",
            "type":"Services"
        }
    ],
    "sg:phone":"+61 7 4084 1269",
    "sg:postcode":"4873",
    "sg:province":"QLD",
    "wof:name":"Mossman Hospital Dental Clinic",
    "wof:placetype":"venue"
},
  "geometry": {"coordinates":[145.36903381400001,-16.4636936188],"type":"Point"}
}