{
  "type": "Feature",
  "properties": {
    "addr:full":"252 Illawarra Rd Marrickville NSW 2204",
    "addr:housenumber":"252",
    "addr:postcode":"2204",
    "addr:street":"Illawarra Rd",
    "iso:country":"AU",
    "sg:address":"252 Illawarra Rd",
    "sg:city":"Marrickville",
    "sg:classifiers":[
        {
            "category":"Shopping",
            "subcategory":"Shoes",
            "type":"Retail Goods"
        }
    ],
    "sg:phone":"+61 2 9559 8918",
    "sg:postcode":"2204",
    "sg:province":"NSW",
    "sg:tags":[
        "footwear"
    ],
    "wof:name":"Direct Shoe Warehouse",
    "wof:placetype":"venue"
},
  "geometry": {"coordinates":[151.15565490700001,-33.9110946655],"type":"Point"}
}