{
  "type": "Feature",
  "properties": {
    "addr:full":"262 Hindley St Adelaide SA 5000",
    "addr:housenumber":"262",
    "addr:postcode":"5000",
    "addr:street":"Hindley St",
    "iso:country":"AU",
    "sg:address":"262 Hindley St",
    "sg:city":"Adelaide",
    "sg:classifiers":[
        {
            "category":"Travel",
            "subcategory":"Hotels & Motels",
            "type":"Entertainment"
        }
    ],
    "sg:phone":"+61 8 8231 9524",
    "sg:postcode":"5000",
    "sg:province":"SA",
    "sg:tags":[
        "accommodation"
    ],
    "wof:name":"Princes Arcade Motel / Kiwi Lodge",
    "wof:placetype":"venue"
},
  "geometry": {"coordinates":[138.58953857399999,-34.9233665466],"type":"Point"}
}