{
  "type": "Feature",
  "properties": {
    "addr:full":"138 Greenhill Rd Unley SA 5061",
    "addr:housenumber":"138",
    "addr:postcode":"5061",
    "addr:street":"Greenhill Rd",
    "iso:country":"AU",
    "sg:address":"138 Greenhill Rd",
    "sg:city":"Unley",
    "sg:classifiers":[
        {
            "category":"Farming",
            "subcategory":"Farm & Veterinary Services",
            "type":"Manufacturing & Wholesale Goods"
        }
    ],
    "sg:phone":"+61 8 8271 6000",
    "sg:postcode":"5061",
    "sg:province":"SA",
    "sg:tags":[
        "seedsman"
    ],
    "wof:name":"Harvey Seeds Pty Ltd",
    "wof:placetype":"venue"
},
  "geometry": {"coordinates":[138.60606384299999,-34.9411582947],"type":"Point"}
}