{
  "type": "Feature",
  "properties": {
    "addr:full":"305d Buckley St Essendon VIC 3040",
    "addr:housenumber":"305d",
    "addr:postcode":"3040",
    "addr:street":"Buckley St",
    "iso:country":"AU",
    "sg:address":"305d Buckley St",
    "sg:city":"Essendon",
    "sg:classifiers":[
        {
            "category":"Fast Food",
            "type":"Food & Drink"
        }
    ],
    "sg:phone":"+61 3 9331 4222",
    "sg:postcode":"3040",
    "sg:province":"VIC",
    "sg:tags":[
        "away",
        "take"
    ],
    "wof:name":"Fisichella",
    "wof:placetype":"venue"
},
  "geometry": {"coordinates":[144.90116882300001,-37.7553443909],"type":"Point"}
}