{
  "type": "Feature",
  "properties": {
    "iso:country":"AU",
    "sg:address":"29b Musgrave Ave",
    "sg:city":"Chirn Park",
    "sg:classifiers":[
        {
            "category":"Shopping",
            "subcategory":"Clothing, Apparel, & Fashions",
            "type":"Retail Goods"
        }
    ],
    "sg:phone":"+61 7 5528 0414",
    "sg:postcode":"4215",
    "sg:province":"QLD",
    "sg:tags":[
        "menswear"
    ],
    "wof:name":"Luxe Store",
    "wof:placetype":"venue"
},
  "geometry": {"coordinates":[153.38665771500001,-27.9544906616],"type":"Point"}
}