{
  "type": "Feature",
  "properties": {
    "addr:full":"School Rd Capalaba QLD 4157",
    "addr:postcode":"4157",
    "addr:street":"School Rd",
    "iso:country":"AU",
    "sg:address":"School Rd",
    "sg:city":"Capalaba",
    "sg:classifiers":[
        {
            "category":"Arena",
            "subcategory":"Sports Club",
            "type":"Entertainment"
        }
    ],
    "sg:phone":"+61 7 3245 0288",
    "sg:postcode":"4157",
    "sg:province":"QLD",
    "sg:tags":[
        "organisation",
        "sporting"
    ],
    "wof:name":"Metropolitan East School Sport",
    "wof:placetype":"venue"
},
  "geometry": {"coordinates":[153.19999694800001,-27.5358467102],"type":"Point"}
}