{
  "type": "Feature",
  "properties": {
    "addr:full":"Unit 5/ 80 Gipps St East Melbourne VIC 3002",
    "addr:housenumber":"80",
    "addr:postcode":"3002",
    "addr:street":"Gipps St",
    "iso:country":"AU",
    "sg:address":"Unit 5/ 80 Gipps St",
    "sg:city":"East Melbourne",
    "sg:classifiers":[
        {
            "category":"Health Services",
            "subcategory":"Health Practitioner",
            "type":"Services"
        }
    ],
    "sg:phone":"+61 3 9415 8812",
    "sg:postcode":"3002",
    "sg:province":"VIC",
    "sg:tags":[
        "physiotherapist"
    ],
    "wof:name":"Knowbody Physiotherapy, Pilates & Alexander Studio",
    "wof:placetype":"venue"
},
  "geometry": {"coordinates":[144.9868927,-37.8129692078],"type":"Point"}
}