{
  "type": "Feature",
  "properties": {
    "addr:full":"14 Hepburn Rd Doncaster VIC 3108",
    "addr:housenumber":"14",
    "addr:postcode":"3108",
    "addr:street":"Hepburn Rd",
    "iso:country":"AU",
    "sg:address":"14 Hepburn Rd",
    "sg:city":"Doncaster",
    "sg:classifiers":[
        {
            "category":"Education",
            "subcategory":"University",
            "type":"Public Place"
        }
    ],
    "sg:phone":"+61 3 9840 7629",
    "sg:postcode":"3108",
    "sg:province":"VIC",
    "sg:tags":[
        "sewing",
        "dressmaking",
        "tuition"
    ],
    "wof:name":"Henry Kelvin Design",
    "wof:placetype":"venue"
},
  "geometry": {"coordinates":[145.130401611,-37.7885284424],"type":"Point"}
}