{
  "type": "Feature",
  "properties": {
    "iso:country":"AU",
    "sg:address":"9 Cecil Pl",
    "sg:city":"South Melbourne",
    "sg:classifiers":[
        {
            "category":"Real Estate",
            "subcategory":"Architect",
            "type":"Services"
        }
    ],
    "sg:phone":"+61 3 9682 6099",
    "sg:postcode":"3205",
    "sg:province":"VIC",
    "wof:name":"Miles Robert Architects",
    "wof:placetype":"venue"
},
  "geometry": {"coordinates":[144.961166,-37.838284],"type":"Point"}
}