{
  "type": "Feature",
  "properties": {
    "addr:full":"Clarkes Rd Upper Plenty VIC 3756",
    "addr:postcode":"3756",
    "addr:street":"Clarkes Rd",
    "iso:country":"AU",
    "sg:address":"Clarkes Rd",
    "sg:city":"Upper Plenty",
    "sg:classifiers":[
        {
            "category":"Education",
            "subcategory":"School",
            "type":"Public Place"
        }
    ],
    "sg:phone":"+61 3 5783 1358",
    "sg:postcode":"3756",
    "sg:province":"VIC",
    "sg:tags":[
        "state",
        "except",
        "nsw"
    ],
    "wof:name":"Upper Plenty Primary School",
    "wof:placetype":"venue"
},
  "geometry": {"coordinates":[145.063568,-37.417362],"type":"Point"}
}