{
  "type": "Feature",
  "properties": {
    "addr:full":"6 Caporn Rd Parkhurst QLD 4702",
    "addr:housenumber":"6",
    "addr:postcode":"4702",
    "addr:street":"Caporn Rd",
    "iso:country":"AU",
    "sg:address":"6 Caporn Rd",
    "sg:city":"Parkhurst",
    "sg:classifiers":[
        {
            "category":"Organizations",
            "subcategory":"Professional Association",
            "type":"Services"
        }
    ],
    "sg:phone":"+61 7 4936 3535",
    "sg:postcode":"4702",
    "sg:province":"QLD",
    "sg:tags":[
        "rural",
        "organisation",
        "production",
        "primary"
    ],
    "wof:name":"Charbray Society Of Australia Ltd The",
    "wof:placetype":"venue"
},
  "geometry": {"coordinates":[150.583694458,-23.2754554749],"type":"Point"}
}