{
  "type": "Feature",
  "properties": {
    "addr:full":"Happy Valley Rd Robinvale VIC 3549",
    "addr:postcode":"3549",
    "addr:street":"Happy Valley Rd",
    "iso:country":"AU",
    "sg:address":"Happy Valley Rd",
    "sg:city":"Robinvale",
    "sg:classifiers":[
        {
            "category":"Home & Garden",
            "subcategory":"Kitchen Supply",
            "type":"Retail Goods"
        }
    ],
    "sg:phone":"+61 3 5026 4138",
    "sg:postcode":"3549",
    "sg:province":"VIC",
    "sg:tags":[
        "vegetable",
        "fruit",
        "grain",
        "exporter"
    ],
    "wof:name":"Cordoma International",
    "wof:placetype":"venue"
},
  "geometry": {"coordinates":[142.767669678,-34.6226081848],"type":"Point"}
}