{
  "type": "Feature",
  "properties": {
    "iso:country":"AU",
    "sg:address":"PO Box 404",
    "sg:city":"Rockingham Private Boxes",
    "sg:classifiers":[
        {
            "category":"Building & Trades",
            "subcategory":"Plumbing",
            "type":"Services"
        }
    ],
    "sg:phone":"+61 8 9593 0600",
    "sg:postcode":"6968",
    "sg:province":"WA",
    "sg:tags":[
        "plumber",
        "gasfitters"
    ],
    "wof:name":"Sound Plumbing",
    "wof:placetype":"venue"
},
  "geometry": {"coordinates":[115.757622,-32.250061],"type":"Point"}
}