{
  "type": "Feature",
  "properties": {
    "iso:country":"AU",
    "sg:address":"9 Aylward Ave",
    "sg:city":"Thomastown",
    "sg:classifiers":[
        {
            "category":"Education",
            "subcategory":"Junior College",
            "type":"Public Place"
        }
    ],
    "sg:phone":"+61 3 9460 8683",
    "sg:postcode":"3074",
    "sg:province":"VIC",
    "sg:tags":[
        "wholesaler",
        "school",
        "mfrs",
        "uniform"
    ],
    "wof:name":"Twisting By The Spool",
    "wof:placetype":"venue"
},
  "geometry": {"coordinates":[144.99299621599999,-37.6916847229],"type":"Point"}
}