{
  "type": "Feature",
  "properties": {
    "addr:full":"47 Moreton St Heathwood QLD 4110",
    "addr:housenumber":"47",
    "addr:postcode":"4110",
    "addr:street":"Moreton St",
    "iso:country":"AU",
    "sg:address":"47 Moreton St",
    "sg:city":"Heathwood",
    "sg:classifiers":[
        {
            "category":"Home & Garden",
            "subcategory":"Hardware",
            "type":"Retail Goods"
        }
    ],
    "sg:phone":"+61 7 3372 1890",
    "sg:postcode":"4110",
    "sg:province":"QLD",
    "sg:tags":[
        "nut",
        "bolt"
    ],
    "wof:name":"Brighton Best Socket Screw Mfg Pty Ltd",
    "wof:placetype":"venue"
},
  "geometry": {"coordinates":[152.97740173299999,-27.6405963898],"type":"Point"}
}