{
  "type": "Feature",
  "properties": {
    "addr:full":"Unit 3/ 1 Jubilee Ave Warriewood NSW 2102",
    "addr:housenumber":"1",
    "addr:postcode":"2102",
    "addr:street":"Jubilee Ave",
    "iso:country":"AU",
    "sg:address":"Unit 3/ 1 Jubilee Ave",
    "sg:city":"Warriewood",
    "sg:classifiers":[
        {
            "category":"Manufacturing",
            "subcategory":"Rubber & Plastics",
            "type":"Manufacturing & Wholesale Goods"
        }
    ],
    "sg:phone":"+61 2 9979 7089",
    "sg:postcode":"2102",
    "sg:province":"NSW",
    "sg:tags":[
        "wholesaler",
        "product",
        "mfrs"
    ],
    "wof:name":"Brookvale Plastic & Rubber Services",
    "wof:placetype":"venue"
},
  "geometry": {"coordinates":[151.28564499999999,-33.679611],"type":"Point"}
}