{
  "type": "Feature",
  "properties": {
    "addr:full":"Unit 1, Lyell Centre Cnr Lyell & Newcastle Sts Fyshwick ACT 2609",
    "addr:postcode":"2609",
    "addr:street":"Cnr;Sts",
    "iso:country":"AU",
    "sg:address":"Unit 1, Lyell Centre Cnr Lyell & Newcastle Sts",
    "sg:city":"Fyshwick",
    "sg:classifiers":[
        {
            "category":"Insurance",
            "subcategory":"Insurance Agent",
            "type":"Services"
        }
    ],
    "sg:phone":"+61 2 6280 5477",
    "sg:postcode":"2609",
    "sg:province":"ACT",
    "sg:tags":[
        "broker"
    ],
    "wof:name":"Austbrokers Canberra",
    "wof:placetype":"venue"
},
  "geometry": {"coordinates":[149.17408752399999,-35.3280334473],"type":"Point"}
}