{
  "type": "Feature",
  "properties": {
    "iso:country":"AU",
    "sg:address":"24 Mc Curdy Rd",
    "sg:city":"Herne Hill",
    "sg:classifiers":[
        {
            "category":"Building & Trades",
            "subcategory":"Construction",
            "type":"Services"
        }
    ],
    "sg:phone":"+61 3 5272 2106",
    "sg:postcode":"3218",
    "sg:province":"VIC",
    "sg:tags":[
        "contractor"
    ],
    "wof:name":"Lopez A",
    "wof:placetype":"venue"
},
  "geometry": {"coordinates":[144.31968689000001,-38.1300354004],"type":"Point"}
}