{
  "type": "Feature",
  "properties": {
    "addr:full":"12 Katoomba St Moorabbin VIC 3189",
    "addr:housenumber":"12",
    "addr:postcode":"3189",
    "addr:street":"Katoomba St",
    "iso:country":"AU",
    "sg:address":"12 Katoomba St",
    "sg:city":"Moorabbin",
    "sg:classifiers":[
        {
            "category":"Professional",
            "subcategory":"Computer Services",
            "type":"Services"
        }
    ],
    "sg:phone":"+61 3 9555 6560",
    "sg:postcode":"3189",
    "sg:province":"VIC",
    "sg:tags":[
        "information"
    ],
    "wof:name":"Community Information Centres",
    "wof:placetype":"venue"
},
  "geometry": {"coordinates":[145.03474426299999,-37.9351921082],"type":"Point"}
}