{
  "type": "Feature",
  "properties": {
    "addr:full":"72 Racecourse Rd North Melbourne VIC 3051",
    "addr:housenumber":"72",
    "addr:postcode":"3051",
    "addr:street":"Racecourse Rd",
    "iso:country":"AU",
    "sg:address":"72 Racecourse Rd",
    "sg:city":"North Melbourne",
    "sg:classifiers":[
        {
            "category":"Shopping",
            "subcategory":"Discount & Variety Stores",
            "type":"Retail Goods"
        }
    ],
    "sg:phone":"+61 3 9326 6231",
    "sg:postcode":"3051",
    "sg:province":"VIC",
    "sg:tags":[
        "shop",
        "adult"
    ],
    "wof:name":"Calvista Wholesale Pty Ltd",
    "wof:placetype":"venue"
},
  "geometry": {"coordinates":[144.93939209000001,-37.7889633179],"type":"Point"}
}