{
  "type": "Feature",
  "properties": {
    "iso:country":"AU",
    "sg:address":"Shop 1/ 63 Market St",
    "sg:city":"Mudgee",
    "sg:classifiers":[
        {
            "category":"Wholesale",
            "subcategory":"Non-durable Goods",
            "type":"Manufacturing & Wholesale Goods"
        }
    ],
    "sg:phone":"+61 2 6372 7444",
    "sg:postcode":"2850",
    "sg:province":"NSW",
    "sg:tags":[
        "wholesaler",
        "mfrs",
        "cosmetic"
    ],
    "wof:name":"Two Eight Five Zero",
    "wof:placetype":"venue"
},
  "geometry": {"coordinates":[149.575623,-32.587906],"type":"Point"}
}