{
  "type": "Feature",
  "properties": {
    "addr:full":"8/ 177 Beavers Rd Northcote VIC 3070",
    "addr:housenumber":"/ 177",
    "addr:postcode":"3070",
    "addr:street":"Beavers Rd",
    "iso:country":"AU",
    "sg:address":"8/ 177 Beavers Rd",
    "sg:city":"Northcote",
    "sg:classifiers":[
        {
            "category":"Home & Garden",
            "subcategory":"Household Appliances",
            "type":"Retail Goods"
        }
    ],
    "sg:phone":"+61 3 9482 4900",
    "sg:postcode":"3070",
    "sg:province":"VIC",
    "sg:tags":[
        "chemical",
        "equipment",
        "steam",
        "cleaning",
        "pressure"
    ],
    "wof:name":"Duplex Cleaning Machines Pty Ltd",
    "wof:placetype":"venue"
},
  "geometry": {"coordinates":[144.98613,-37.765373],"type":"Point"}
}