{
  "type": "Feature",
  "properties": {
    "addr:full":"14 Rowsley Rd Mt Eliza VIC 3930",
    "addr:housenumber":"14",
    "addr:postcode":"3930",
    "addr:street":"Rowsley Rd",
    "iso:country":"AU",
    "sg:address":"14 Rowsley Rd",
    "sg:city":"Mt Eliza",
    "sg:classifiers":[
        {
            "category":"Utilities",
            "subcategory":"Electric",
            "type":"Services"
        }
    ],
    "sg:phone":"+61 418 140 094",
    "sg:postcode":"3930",
    "sg:province":"VIC",
    "sg:tags":[
        "electrical",
        "contractor"
    ],
    "wof:name":"Cater Electrics Pty Ltd",
    "wof:placetype":"venue"
},
  "geometry": {"coordinates":[145.07893371599999,-38.1870155334],"type":"Point"}
}