{
  "type": "Feature",
  "properties": {
    "addr:full":"29 Windsor Rd Kellyville NSW 2153",
    "addr:housenumber":"29",
    "addr:postcode":"2153",
    "addr:street":"Windsor Rd",
    "iso:country":"AU",
    "sg:address":"29 Windsor Rd",
    "sg:city":"Kellyville",
    "sg:classifiers":[
        {
            "category":"Restaurant",
            "type":"Food & Drink"
        }
    ],
    "sg:phone":"+61 2 9629 1224",
    "sg:postcode":"2153",
    "sg:province":"NSW",
    "wof:name":"Arthurs Restaurant",
    "wof:placetype":"venue"
},
  "geometry": {"coordinates":[150.981567383,-33.745677948],"type":"Point"}
}