{
  "type": "Feature",
  "properties": {
    "addr:full":"11 Maurice Crt Nunawading VIC 3131",
    "addr:housenumber":"11",
    "addr:postcode":"3131",
    "addr:street":"Maurice Crt",
    "iso:country":"AU",
    "sg:address":"11 Maurice Crt",
    "sg:city":"Nunawading",
    "sg:classifiers":[
        {
            "category":"Home & Garden",
            "subcategory":"Hardware",
            "type":"Retail Goods"
        }
    ],
    "sg:phone":"+61 3 9873 4433",
    "sg:postcode":"3131",
    "sg:province":"VIC",
    "sg:tags":[
        "battery",
        "dry",
        "rechargeable",
        "cell"
    ],
    "wof:name":"Sonnenschein Batteries",
    "wof:placetype":"venue"
},
  "geometry": {"coordinates":[145.18429565400001,-37.8240776062],"type":"Point"}
}