{
  "type": "Feature",
  "properties": {
    "addr:full":"124 Auburn St Goulburn NSW 2580",
    "addr:housenumber":"124",
    "addr:postcode":"2580",
    "addr:street":"Auburn St",
    "iso:country":"AU",
    "sg:address":"124 Auburn St",
    "sg:city":"Goulburn",
    "sg:classifiers":[
        {
            "category":"Banks & Credit Unions",
            "subcategory":"Bank",
            "type":"Services"
        }
    ],
    "sg:phone":"+61 13 20 32",
    "sg:postcode":"2580",
    "sg:province":"NSW",
    "wof:name":"Westpac",
    "wof:placetype":"venue"
},
  "geometry": {"coordinates":[149.716873169,-34.7561988831],"type":"Point"}
}