{
  "type": "Feature",
  "properties": {
    "iso:country":"AU",
    "sg:address":"1 Inglis St",
    "sg:city":"Wynyard",
    "sg:classifiers":[
        {
            "category":"Travel",
            "subcategory":"Hotels & Motels",
            "type":"Entertainment"
        }
    ],
    "sg:phone":"+61 3 6442 2048",
    "sg:postcode":"7325",
    "sg:province":"TAS",
    "sg:tags":[
        "accommodation"
    ],
    "wof:name":"Wynyard Top Hotel",
    "wof:placetype":"venue"
},
  "geometry": {"coordinates":[145.724976,-40.989685],"type":"Point"}
}