{
  "type": "Feature",
  "properties": {
    "iso:country":"AU",
    "sg:address":"Lot 2 Dignams Creek Rd",
    "sg:city":"Dignam's Creek",
    "sg:classifiers":[
        {
            "category":"Building & Trades",
            "subcategory":"Construction",
            "type":"Services"
        }
    ],
    "sg:phone":"+61 2 6493 6797",
    "sg:postcode":"2546",
    "sg:province":"NSW",
    "sg:tags":[
        "contractor"
    ],
    "wof:name":"Rogers R K",
    "wof:placetype":"venue"
},
  "geometry": {"coordinates":[149.97714233400001,-36.345905304],"type":"Point"}
}