{
  "type": "Feature",
  "properties": {
    "addr:full":"58 Collins Crs Berwick VIC 3806",
    "addr:housenumber":"58",
    "addr:postcode":"3806",
    "addr:street":"Collins Crs",
    "iso:country":"AU",
    "sg:address":"58 Collins Crs",
    "sg:city":"Berwick",
    "sg:classifiers":[
        {
            "category":"Personal",
            "subcategory":"Hair Removal",
            "type":"Services"
        }
    ],
    "sg:phone":"+61 3 9769 5251",
    "sg:postcode":"3806",
    "sg:province":"VIC",
    "wof:name":"Aesthetic Touch Beauty",
    "wof:placetype":"venue"
},
  "geometry": {"coordinates":[145.34732055699999,-38.0306282043],"type":"Point"}
}