{
  "type": "Feature",
  "properties": {
    "addr:full":"PO Box 986 Hyde Park QLD 4812",
    "addr:postcode":"4812",
    "iso:country":"AU",
    "sg:address":"PO Box 986",
    "sg:city":"Hyde Park",
    "sg:classifiers":[
        {
            "category":"Shopping",
            "subcategory":"Party Supplies",
            "type":"Retail Goods"
        }
    ],
    "sg:phone":"+61 408 548 984",
    "sg:postcode":"4812",
    "sg:province":"QLD",
    "sg:tags":[
        "selling",
        "plan"
    ],
    "wof:name":"Blue Feather Crystal Jewellery",
    "wof:placetype":"venue"
},
  "geometry": {"coordinates":[146.79513499999999,-19.27693],"type":"Point"}
}