{
  "type": "Feature",
  "properties": {
    "addr:full":"PO Box 146 Riddells Creek VIC 3431",
    "addr:postcode":"3431",
    "iso:country":"AU",
    "sg:address":"PO Box 146",
    "sg:city":"Riddells Creek",
    "sg:classifiers":[
        {
            "category":"Education",
            "subcategory":"Special Training",
            "type":"Public Place"
        }
    ],
    "sg:phone":"+61 1800 622 010",
    "sg:postcode":"3431",
    "sg:province":"VIC",
    "sg:tags":[
        "development"
    ],
    "wof:name":"AITAC Pty Ltd",
    "wof:placetype":"venue"
},
  "geometry": {"coordinates":[144.682937622,-37.4472885132],"type":"Point"}
}