{
  "type": "Feature",
  "properties": {
    "addr:full":"25 Parramatta Rd Underwood QLD 4119",
    "addr:housenumber":"25",
    "addr:postcode":"4119",
    "addr:street":"Parramatta Rd",
    "iso:country":"AU",
    "sg:address":"25 Parramatta Rd",
    "sg:city":"Underwood",
    "sg:classifiers":[
        {
            "category":"Shopping",
            "subcategory":"Party Supplies",
            "type":"Retail Goods"
        }
    ],
    "sg:phone":"+61 7 3209 4500",
    "sg:postcode":"4119",
    "sg:province":"QLD",
    "wof:name":"Party Bake",
    "wof:placetype":"venue"
},
  "geometry": {"coordinates":[153.11659240700001,-27.6147289276],"type":"Point"}
}