{
  "type": "Feature",
  "properties": {
    "iso:country":"AU",
    "sg:address":"Front St",
    "sg:city":"Mossman",
    "sg:classifiers":[
        {
            "category":"Autos & Motor Vehicles",
            "subcategory":"Fuel & Gas Station",
            "type":"Retail Goods"
        }
    ],
    "sg:phone":"+61 7 4098 2528",
    "sg:postcode":"4873",
    "sg:province":"QLD",
    "wof:name":"BP Australia Limited",
    "wof:placetype":"venue"
},
  "geometry": {"coordinates":[145.37359619099999,-16.4611625671],"type":"Point"}
}