{
  "type": "Feature",
  "properties": {
    "addr:full":"78 Majors Bay Rd Concord NSW 2137",
    "addr:housenumber":"78",
    "addr:postcode":"2137",
    "addr:street":"Majors Bay Rd",
    "iso:country":"AU",
    "sg:address":"78 Majors Bay Rd",
    "sg:city":"Concord",
    "sg:classifiers":[
        {
            "category":"Personal",
            "subcategory":"Beauty Salon",
            "type":"Services"
        }
    ],
    "sg:phone":"+61 2 9743 2211",
    "sg:postcode":"2137",
    "sg:province":"NSW",
    "wof:name":"BeautyWell Concord",
    "wof:placetype":"venue"
},
  "geometry": {"coordinates":[151.10316467300001,-33.8564796448],"type":"Point"}
}