{
  "type": "Feature",
  "properties": {
    "addr:full":"21 Blacks Camp Rd Somerville VIC 3912",
    "addr:housenumber":"21",
    "addr:postcode":"3912",
    "addr:street":"Blacks Camp Rd",
    "iso:country":"AU",
    "sg:address":"21 Blacks Camp Rd",
    "sg:city":"Somerville",
    "sg:classifiers":[
        {
            "category":"Banks & Credit Unions",
            "subcategory":"Investment Brokerage",
            "type":"Services"
        }
    ],
    "sg:phone":"+61 3 5977 5094",
    "sg:postcode":"3912",
    "sg:province":"VIC",
    "sg:tags":[
        "care",
        "day",
        "family",
        "child"
    ],
    "wof:name":"Annie Sage Child Care Centre",
    "wof:placetype":"venue"
},
  "geometry": {"coordinates":[145.170288086,-38.230846405],"type":"Point"}
}