{
  "type": "Feature",
  "properties": {
    "iso:country":"AU",
    "sg:address":"419 Bay St",
    "sg:city":"Brighton",
    "sg:classifiers":[
        {
            "category":"Ferry Terminal",
            "type":"Transportation"
        }
    ],
    "sg:phone":"+61 3 9596 8333",
    "sg:postcode":"3186",
    "sg:province":"VIC",
    "sg:tags":[
        "raised",
        "floor"
    ],
    "wof:name":"Tasman Access Floors",
    "wof:placetype":"venue"
},
  "geometry": {"coordinates":[145.00596618599999,-37.9058227539],"type":"Point"}
}