{
  "type": "Feature",
  "properties": {
    "iso:country":"AU",
    "sg:address":"282 Nicklin Way",
    "sg:city":"Bokarina",
    "sg:classifiers":[
        {
            "category":"Home & Garden",
            "subcategory":"Carpets & Floor Coverings",
            "type":"Retail Goods"
        }
    ],
    "sg:phone":"+61 7 5493 3555",
    "sg:postcode":"4575",
    "sg:province":"QLD",
    "sg:tags":[
        "tile",
        "wall"
    ],
    "sg:website":"http://www.tilewizards.com.au",
    "wof:name":"Tile Wizards",
    "wof:placetype":"venue"
},
  "geometry": {"coordinates":[153.12889100000001,-26.732862],"type":"Point"}
}