{
  "type": "Feature",
  "properties": {
    "iso:country":"AU",
    "sg:address":"PO Box 42",
    "sg:city":"Warren",
    "sg:classifiers":[
        {
            "category":"Farming",
            "subcategory":"Farm & Veterinary Services",
            "type":"Manufacturing & Wholesale Goods"
        }
    ],
    "sg:phone":"+61 428 474 151",
    "sg:postcode":"2824",
    "sg:province":"NSW",
    "sg:tags":[
        "agricultural",
        "advisory"
    ],
    "wof:name":"NTS Ag Services",
    "wof:placetype":"venue"
},
  "geometry": {"coordinates":[147.835662842,-31.7004299164],"type":"Point"}
}