{
  "type": "Feature",
  "properties": {
    "iso:country":"AU",
    "sg:address":"Lindsay St",
    "sg:city":"Blayney",
    "sg:classifiers":[
        {
            "category":"Education",
            "subcategory":"School",
            "type":"Public Place"
        }
    ],
    "sg:phone":"+61 2 6368 2154",
    "sg:postcode":"2799",
    "sg:province":"NSW",
    "sg:tags":[
        "state",
        "-",
        "nsw"
    ],
    "wof:name":"Blayney Public School",
    "wof:placetype":"venue"
},
  "geometry": {"coordinates":[149.250885,-33.528885],"type":"Point"}
}