{
  "type": "Feature",
  "properties": {
    "iso:country":"AU",
    "sg:address":"1- 21 Percival Rd",
    "sg:city":"Smithfield",
    "sg:classifiers":[
        {
            "category":"Building & Trades",
            "subcategory":"Plumbing",
            "type":"Services"
        }
    ],
    "sg:phone":"+61 2 9612 2323",
    "sg:postcode":"2164",
    "sg:province":"NSW",
    "sg:tags":[
        "equipment",
        "valves"
    ],
    "wof:name":"Keystone Valves & Controls",
    "wof:placetype":"venue"
},
  "geometry": {"coordinates":[150.95025634800001,-33.8448219299],"type":"Point"}
}