{
  "type": "Feature",
  "properties": {
    "addr:full":"9 Elizabeth Drv Lalor VIC 3075",
    "addr:housenumber":"9",
    "addr:postcode":"3075",
    "addr:street":"Elizabeth Drv",
    "iso:country":"AU",
    "sg:address":"9 Elizabeth Drv",
    "sg:city":"Lalor",
    "sg:classifiers":[
        {
            "category":"Home & Garden",
            "subcategory":"Building Materials",
            "type":"Retail Goods"
        }
    ],
    "sg:phone":"+61 401 917 973",
    "sg:postcode":"3075",
    "sg:province":"VIC",
    "sg:tags":[
        "fitting",
        "door"
    ],
    "wof:name":"Melbournes Cheapest Doors",
    "wof:placetype":"venue"
},
  "geometry": {"coordinates":[145.00538635300001,-37.6617202759],"type":"Point"}
}