{
  "type": "Feature",
  "properties": {
    "addr:full":"353 Commercial Rd West Mt Gambier SA 5290",
    "addr:housenumber":"353",
    "addr:postcode":"5290",
    "addr:street":"Commercial Rd West",
    "iso:country":"AU",
    "sg:address":"353 Commercial Rd West",
    "sg:city":"Mt Gambier",
    "sg:classifiers":[
        {
            "category":"Professional",
            "subcategory":"Art Services",
            "type":"Services"
        }
    ],
    "sg:phone":"+61 8 8724 8887",
    "sg:postcode":"5290",
    "sg:province":"SA",
    "sg:tags":[
        "decorator",
        "painter"
    ],
    "wof:name":"G Weyers Painting Service",
    "wof:placetype":"venue"
},
  "geometry": {"coordinates":[140.78964199999999,-37.814178],"type":"Point"}
}