{
  "type": "Feature",
  "properties": {
    "addr:full":"2 Cornell St Camberwell VIC 3124",
    "addr:housenumber":"2",
    "addr:postcode":"3124",
    "addr:street":"Cornell St",
    "iso:country":"AU",
    "sg:address":"2 Cornell St",
    "sg:city":"Camberwell",
    "sg:classifiers":[
        {
            "category":"Building & Trades",
            "subcategory":"Construction",
            "type":"Services"
        }
    ],
    "sg:phone":"+61 3 9888 5227",
    "sg:postcode":"3124",
    "sg:province":"VIC",
    "sg:tags":[
        "plasterboard",
        "plasterer",
        "fixer"
    ],
    "wof:name":"S. J.?Young & Associates Pty Ltd",
    "wof:placetype":"venue"
},
  "geometry": {"coordinates":[145.08717346200001,-37.8382873535],"type":"Point"}
}