{
  "type": "Feature",
  "properties": {
    "addr:full":"Calderwood Rd Albion Park NSW 2527",
    "addr:postcode":"2527",
    "addr:street":"Calderwood Rd",
    "iso:country":"AU",
    "sg:address":"Calderwood Rd",
    "sg:city":"Albion Park",
    "sg:classifiers":[
        {
            "category":"Farming",
            "subcategory":"Dairy Farm",
            "type":"Manufacturing & Wholesale Goods"
        }
    ],
    "sg:phone":"+61 2 4256 2083",
    "sg:postcode":"2527",
    "sg:province":"NSW",
    "wof:name":"Grey Dairies",
    "wof:placetype":"venue"
},
  "geometry": {"coordinates":[150.765167236,-34.5711593628],"type":"Point"}
}