{
  "type": "Feature",
  "properties": {
    "addr:full":"45 Bourke St Carrington NSW 2294",
    "addr:housenumber":"45",
    "addr:postcode":"2294",
    "addr:street":"Bourke St",
    "iso:country":"AU",
    "sg:address":"45 Bourke St",
    "sg:city":"Carrington",
    "sg:classifiers":[
        {
            "category":"Professional",
            "subcategory":"Business Services",
            "type":"Services"
        }
    ],
    "sg:phone":"+61 409 391 241",
    "sg:postcode":"2294",
    "sg:province":"NSW",
    "sg:tags":[
        "small",
        "advisory"
    ],
    "wof:name":"dgb Business Solutions",
    "wof:placetype":"venue"
},
  "geometry": {"coordinates":[151.76719665499999,-32.9096069336],"type":"Point"}
}