{
  "type": "Feature",
  "properties": {
    "addr:full":"128b Ramsgate Ave Bondi NSW 2026",
    "addr:housenumber":"128b",
    "addr:postcode":"2026",
    "addr:street":"Ramsgate Ave",
    "iso:country":"AU",
    "sg:address":"128b Ramsgate Ave",
    "sg:city":"Bondi",
    "sg:classifiers":[
        {
            "category":"Cafe",
            "type":"Food & Drink"
        }
    ],
    "sg:phone":"+61 2 9300 8778",
    "sg:postcode":"2026",
    "sg:province":"NSW",
    "wof:name":"Wet Espresso Bar",
    "wof:placetype":"venue"
},
  "geometry": {"coordinates":[151.28256225600001,-33.8904151917],"type":"Point"}
}