{
  "type": "Feature",
  "properties": {
    "iso:country":"AU",
    "sg:address":"81 Stanbel Rd",
    "sg:city":"Salisbury Plain",
    "sg:classifiers":[
        {
            "category":"Wholesale",
            "subcategory":"Wine & Distilled Alcoholic Beverages",
            "type":"Manufacturing & Wholesale Goods"
        }
    ],
    "sg:phone":"+61 8 8258 1424",
    "sg:postcode":"5109",
    "sg:province":"SA",
    "sg:tags":[
        "collector",
        "bottle"
    ],
    "wof:name":"Scout Recycling Centres",
    "wof:placetype":"venue"
},
  "geometry": {"coordinates":[138.663238525,-34.7719078064],"type":"Point"}
}