{
  "type": "Feature",
  "properties": {
    "addr:full":"Cnr Turton & Griffith Rds New Lambton NSW 2305",
    "addr:postcode":"2305",
    "addr:street":"Cnr",
    "iso:country":"AU",
    "sg:address":"Cnr Turton & Griffith Rds",
    "sg:city":"New Lambton",
    "sg:classifiers":[
        {
            "category":"Autos & Motor Vehicles",
            "subcategory":"Auto Supplies",
            "type":"Retail Goods"
        }
    ],
    "sg:phone":"+61 401 257 187",
    "sg:postcode":"2305",
    "sg:province":"NSW",
    "sg:tags":[
        "battery",
        "automotive"
    ],
    "wof:name":"Betta Ride Mobile Tyre & Battery Services",
    "wof:placetype":"venue"
},
  "geometry": {"coordinates":[151.72285500000001,-32.922935],"type":"Point"}
}