{
  "type": "Feature",
  "properties": {
    "iso:country":"AU",
    "sg:address":"69 Spencer St",
    "sg:city":"Bunbury",
    "sg:classifiers":[
        {
            "category":"Building & Trades",
            "subcategory":"Construction",
            "type":"Services"
        }
    ],
    "sg:phone":"+61 1800 066 509",
    "sg:postcode":"6230",
    "sg:province":"WA",
    "sg:tags":[
        "home",
        "air conditioning"
    ],
    "wof:name":"Jarrahdale Heating & Cooling",
    "wof:placetype":"venue"
},
  "geometry": {"coordinates":[115.641571,-33.346764],"type":"Point"}
}