{
  "type": "Feature",
  "properties": {
    "iso:country":"AU",
    "sg:address":"Raymond St",
    "sg:city":"Henley Beach",
    "sg:classifiers":[
        {
            "category":"Arena",
            "subcategory":"Sports Club",
            "type":"Entertainment"
        }
    ],
    "sg:phone":"+61 8 8356 4825",
    "sg:postcode":"5022",
    "sg:province":"SA",
    "sg:tags":[
        "australian",
        "football",
        "rule"
    ],
    "wof:name":"Henley Football Club Inc",
    "wof:placetype":"venue"
},
  "geometry": {"coordinates":[138.497772217,-34.9186096191],"type":"Point"}
}