{
  "type": "Feature",
  "properties": {
    "addr:full":"Shp 10/ 79 Buckingham Drv Wangara WA 6065",
    "addr:housenumber":"10 / 79",
    "addr:postcode":"6065",
    "addr:street":"Buckingham Drv",
    "iso:country":"AU",
    "sg:address":"Shp 10/ 79 Buckingham Drv",
    "sg:city":"Wangara",
    "sg:classifiers":[
        {
            "category":"Fast Food",
            "type":"Food & Drink"
        }
    ],
    "sg:phone":"+61 8 9302 1898",
    "sg:postcode":"6065",
    "sg:province":"WA",
    "sg:tags":[
        "away",
        "take"
    ],
    "wof:name":"Auto Plaza Lunches",
    "wof:placetype":"venue"
},
  "geometry": {"coordinates":[115.82837677000001,-31.7884292603],"type":"Point"}
}