{
  "type": "Feature",
  "properties": {
    "iso:country":"AU",
    "sg:address":"Ste43/ 90 Mona Vale Rd",
    "sg:city":"Mona Vale",
    "sg:classifiers":[
        {
            "category":"Building & Trades",
            "subcategory":"Construction",
            "type":"Services"
        }
    ],
    "sg:phone":"+61 2 9999 3430",
    "sg:postcode":"2103",
    "sg:province":"NSW",
    "sg:tags":[
        "contractor"
    ],
    "wof:name":"Rowestyle Constructions",
    "wof:placetype":"venue"
},
  "geometry": {"coordinates":[151.28941345199999,-33.6761665344],"type":"Point"}
}