{
  "type": "Feature",
  "properties": {
    "addr:full":"6 Libbett Ave Clayton South VIC 3169",
    "addr:housenumber":"6",
    "addr:postcode":"3169",
    "addr:street":"Libbett Ave",
    "iso:country":"AU",
    "sg:address":"6 Libbett Ave",
    "sg:city":"Clayton South",
    "sg:classifiers":[
        {
            "category":"Home & Garden",
            "subcategory":"Building Materials",
            "type":"Retail Goods"
        }
    ],
    "sg:phone":"+61 3 9546 0979",
    "sg:postcode":"3169",
    "sg:province":"VIC",
    "sg:tags":[
        "supply"
    ],
    "wof:name":"Living Choice Group Pty Ltd",
    "wof:placetype":"venue"
},
  "geometry": {"coordinates":[145.136352539,-37.9519195557],"type":"Point"}
}