{
  "type": "Feature",
  "properties": {
    "iso:country":"AU",
    "sg:address":"PO Box 730",
    "sg:city":"Vaucluse",
    "sg:classifiers":[
        {
            "category":"Building & Trades",
            "subcategory":"Construction",
            "type":"Services"
        }
    ],
    "sg:phone":"+61 2 9802 6771",
    "sg:postcode":"2030",
    "sg:province":"NSW",
    "sg:tags":[
        "contractor"
    ],
    "wof:name":"The Rix Group Pty Ltd",
    "wof:placetype":"venue"
},
  "geometry": {"coordinates":[151.28192138700001,-33.8597106934],"type":"Point"}
}