{
  "type": "Feature",
  "properties": {
    "iso:country":"AU",
    "sg:address":"1 Ardmillan Rd",
    "sg:city":"Moonee Ponds",
    "sg:classifiers":[
        {
            "category":"Retail",
            "subcategory":"Event Space",
            "type":"Services"
        }
    ],
    "sg:phone":"+61 3 9370 6755",
    "sg:postcode":"3039",
    "sg:province":"VIC",
    "sg:tags":[
        "venue",
        "reception",
        "wedding"
    ],
    "wof:name":"Ardmillan House",
    "wof:placetype":"venue"
},
  "geometry": {"coordinates":[144.917404,-37.763699],"type":"Point"}
}