{
  "type": "Feature",
  "properties": {
    "iso:country":"AU",
    "sg:address":"Calder Hwy",
    "sg:city":"Lockwood South",
    "sg:classifiers":[
        {
            "category":"Education",
            "subcategory":"School",
            "type":"Public Place"
        }
    ],
    "sg:phone":"+61 3 5435 3293",
    "sg:postcode":"3551",
    "sg:province":"VIC",
    "sg:tags":[
        "state",
        "except",
        "nsw"
    ],
    "wof:name":"Lockwood South Primary School",
    "wof:placetype":"venue"
},
  "geometry": {"coordinates":[144.219604492,-36.8647537231],"type":"Point"}
}