{
  "type": "Feature",
  "properties": {
    "iso:country":"AU",
    "sg:address":"2 Burrows Rd",
    "sg:city":"St Peters",
    "sg:classifiers":[
        {
            "category":"Shopping",
            "subcategory":"Pets & Pet Supplies",
            "type":"Retail Goods"
        }
    ],
    "sg:phone":"+61 2 9516 2766",
    "sg:postcode":"2044",
    "sg:province":"NSW",
    "sg:tags":[
        "shop",
        "supplier"
    ],
    "wof:name":"Dogtainers NSW",
    "wof:placetype":"venue"
},
  "geometry": {"coordinates":[151.17871099999999,-33.919483],"type":"Point"}
}