{
  "type": "Feature",
  "properties": {
    "iso:country":"AU",
    "sg:address":"140 Main Rd",
    "sg:city":"Moonah",
    "sg:classifiers":[
        {
            "category":"Home & Garden",
            "subcategory":"Mobile Homes",
            "type":"Retail Goods"
        }
    ],
    "sg:phone":"+61 3 6273 0628",
    "sg:postcode":"7009",
    "sg:province":"TAS",
    "sg:tags":[
        "motor",
        "campervans"
    ],
    "wof:name":"A&#039;Van Tasmania",
    "wof:placetype":"venue"
},
  "geometry": {"coordinates":[147.29318237300001,-42.8446655273],"type":"Point"}
}