{
  "type": "Feature",
  "properties": {
    "addr:full":"7/ 39 Barrie Rd Tullamarine VIC 3043",
    "addr:housenumber":"/ 39",
    "addr:postcode":"3043",
    "addr:street":"Barrie Rd",
    "iso:country":"AU",
    "sg:address":"7/ 39 Barrie Rd",
    "sg:city":"Tullamarine",
    "sg:classifiers":[
        {
            "category":"Professional",
            "type":"Services"
        }
    ],
    "sg:phone":"+61 3 9338 5558",
    "sg:postcode":"3043",
    "sg:province":"VIC",
    "sg:tags":[
        "auctioneer"
    ],
    "wof:name":"National Auctioneers & Valuers Pty Ltd",
    "wof:placetype":"venue"
},
  "geometry": {"coordinates":[144.87388610799999,-37.714138031],"type":"Point"}
}