{
  "type": "Feature",
  "properties": {
    "addr:full":"1/3- 5 Norfolk St Liverpool NSW 2170",
    "addr:housenumber":"/ 3 5",
    "addr:postcode":"2170",
    "addr:street":"Norfolk St",
    "iso:country":"AU",
    "sg:address":"1/3- 5 Norfolk St",
    "sg:city":"Liverpool",
    "sg:classifiers":[
        {
            "category":"Professional",
            "subcategory":"Accounting & Tax Preparation",
            "type":"Services"
        }
    ],
    "sg:phone":"+61 2 9602 5799",
    "sg:postcode":"2170",
    "sg:province":"NSW",
    "sg:tags":[
        "accountant",
        "auditor"
    ],
    "wof:name":"Demasi & Company Services Pty Ltd",
    "wof:placetype":"venue"
},
  "geometry": {"coordinates":[150.92027282699999,-33.9253158569],"type":"Point"}
}