{
  "type": "Feature",
  "properties": {
    "addr:full":"Kiosk 35 Werribee Plaza Shopping Centre Werribee VIC 3030",
    "addr:postcode":"3030",
    "iso:country":"AU",
    "sg:address":"Kiosk 35 Werribee Plaza Shopping Centre",
    "sg:city":"Werribee",
    "sg:classifiers":[
        {
            "category":"Fast Food",
            "type":"Food & Drink"
        }
    ],
    "sg:phone":"+61 3 9749 0556",
    "sg:postcode":"3030",
    "sg:province":"VIC",
    "sg:tags":[
        "away",
        "take"
    ],
    "wof:name":"Donut King",
    "wof:placetype":"venue"
},
  "geometry": {"coordinates":[144.659637,-37.903702],"type":"Point"}
}