{
  "type": "Feature",
  "properties": {
    "addr:full":"470 Ruthven St Toowoomba QLD 4350",
    "addr:housenumber":"470",
    "addr:postcode":"4350",
    "addr:street":"Ruthven St",
    "iso:country":"AU",
    "sg:address":"470 Ruthven St",
    "sg:city":"Toowoomba",
    "sg:classifiers":[
        {
            "category":"Banks & Credit Unions",
            "subcategory":"Financial Services",
            "type":"Services"
        }
    ],
    "sg:phone":"+61 7 4638 5676",
    "sg:postcode":"4350",
    "sg:province":"QLD",
    "sg:tags":[
        "annuity",
        "rollover",
        "superannuation",
        "consultant"
    ],
    "wof:name":"PMA Financial Services",
    "wof:placetype":"venue"
},
  "geometry": {"coordinates":[151.95230100000001,-27.568184],"type":"Point"}
}