{
  "type": "Feature",
  "properties": {
    "addr:full":"Shp 4/ 153 Oxford St Bulimba QLD 4171",
    "addr:housenumber":"/ 153",
    "addr:postcode":"4171",
    "addr:street":"Oxford St",
    "iso:country":"AU",
    "sg:address":"Shp 4/ 153 Oxford St",
    "sg:city":"Bulimba",
    "sg:classifiers":[
        {
            "category":"Shopping",
            "subcategory":"Bridal",
            "type":"Retail Goods"
        }
    ],
    "sg:phone":"+61 7 3899 4742",
    "sg:postcode":"4171",
    "sg:province":"QLD",
    "sg:tags":[
        "hire",
        "wear"
    ],
    "wof:name":"Ann Stein Design",
    "wof:placetype":"venue"
},
  "geometry": {"coordinates":[153.05926513700001,-27.4512138367],"type":"Point"}
}