{
  "type": "Feature",
  "properties": {
    "addr:full":"202 Albion St Brunswick VIC 3056",
    "addr:housenumber":"202",
    "addr:postcode":"3056",
    "addr:street":"Albion St",
    "iso:country":"AU",
    "sg:address":"202 Albion St",
    "sg:city":"Brunswick",
    "sg:classifiers":[
        {
            "category":"Home & Garden",
            "subcategory":"Carpets & Floor Coverings",
            "type":"Retail Goods"
        }
    ],
    "sg:phone":"+61 3 9384 6464",
    "sg:postcode":"3056",
    "sg:province":"VIC",
    "sg:tags":[
        "tile",
        "wall",
        "layer"
    ],
    "wof:name":"Top Notch Tiling",
    "wof:placetype":"venue"
},
  "geometry": {"coordinates":[144.962615967,-37.7608146667],"type":"Point"}
}