{
  "type": "Feature",
  "properties": {
    "addr:full":"12 Hamer St Brunswick East VIC 3057",
    "addr:housenumber":"12",
    "addr:postcode":"3057",
    "addr:street":"Hamer St",
    "iso:country":"AU",
    "sg:address":"12 Hamer St",
    "sg:city":"Brunswick East",
    "sg:classifiers":[
        {
            "category":"Professional",
            "subcategory":"Art Services",
            "type":"Services"
        }
    ],
    "sg:phone":"+61 3 9380 2872",
    "sg:postcode":"3057",
    "sg:province":"VIC",
    "sg:tags":[
        "arranger",
        "music",
        "composer"
    ],
    "wof:name":"Bon Bon Creative Productions",
    "wof:placetype":"venue"
},
  "geometry": {"coordinates":[144.97654724099999,-37.767616272],"type":"Point"}
}