{
  "type": "Feature",
  "properties": {
    "addr:full":"12 Castlereagh St Sydney NSW 2000",
    "addr:housenumber":"12",
    "addr:postcode":"2000",
    "addr:street":"Castlereagh St",
    "iso:country":"AU",
    "sg:address":"12 Castlereagh St",
    "sg:city":"Sydney",
    "sg:classifiers":[
        {
            "category":"Banks & Credit Unions",
            "subcategory":"Financial Services",
            "type":"Services"
        }
    ],
    "sg:phone":"+61 2 9226 9700",
    "sg:postcode":"2000",
    "sg:province":"NSW",
    "sg:tags":[
        "loan",
        "finance",
        "mortgage"
    ],
    "wof:name":"Mortgage Asset Management Pty Ltd",
    "wof:placetype":"venue"
},
  "geometry": {"coordinates":[151.210113525,-33.8669242859],"type":"Point"}
}