{
  "type": "Feature",
  "properties": {
    "addr:full":"6 Cambourne Ave St Ives NSW 2075",
    "addr:housenumber":"6",
    "addr:postcode":"2075",
    "addr:street":"Cambourne Ave",
    "iso:country":"AU",
    "sg:address":"6 Cambourne Ave",
    "sg:city":"St Ives",
    "sg:classifiers":[
        {
            "category":"Health Services",
            "subcategory":"Doctor",
            "type":"Services"
        }
    ],
    "sg:phone":"+61 2 9449 8800",
    "sg:postcode":"2075",
    "sg:province":"NSW",
    "sg:tags":[
        "medical",
        "practitioner"
    ],
    "wof:name":"Staraj S",
    "wof:placetype":"venue"
},
  "geometry": {"coordinates":[151.17904663100001,-33.7181510925],"type":"Point"}
}