{
  "type": "Feature",
  "properties": {
    "iso:country":"AU",
    "sg:address":"Ste 44/ 13 Larkin St",
    "sg:city":"Camperdown",
    "sg:classifiers":[
        {
            "category":"Professional",
            "subcategory":"Business Services",
            "type":"Services"
        }
    ],
    "sg:phone":"+61 2 9557 7752",
    "sg:postcode":"2050",
    "sg:province":"NSW",
    "sg:tags":[
        "management",
        "event"
    ],
    "wof:name":"Events with Moore Pty Ltd",
    "wof:placetype":"venue"
},
  "geometry": {"coordinates":[151.18045000000001,-33.88459],"type":"Point"}
}