{
  "type": "Feature",
  "properties": {
    "iso:country":"AU",
    "sg:address":"1 Bridge St",
    "sg:city":"Hamilton",
    "sg:classifiers":[
        {
            "category":"Real Estate",
            "subcategory":"Architect",
            "type":"Services"
        }
    ],
    "sg:phone":"+61 2 4962 1298",
    "sg:postcode":"2303",
    "sg:province":"NSW",
    "wof:name":"Ackland, Roger",
    "wof:placetype":"venue"
},
  "geometry": {"coordinates":[151.74494899999999,-32.92289],"type":"Point"}
}