{
  "type": "Feature",
  "properties": {
    "iso:country":"AU",
    "sg:address":"Shop 33",
    "sg:city":"a Westfield Shoppingtown Oaklands",
    "sg:classifiers":[
        {
            "category":"Shopping",
            "subcategory":"Clothing, Apparel, & Fashions",
            "type":"Retail Goods"
        }
    ],
    "sg:phone":"+61 8 8377 1100",
    "sg:postcode":"5046",
    "sg:province":"SA",
    "sg:tags":[
        "lingerie",
        "hosiery",
        "sleepwear"
    ],
    "wof:name":"Bras &#039;N&#039; Things",
    "wof:placetype":"venue"
},
  "geometry": {"coordinates":[138.53732299999999,-35.002277],"type":"Point"}
}