{
  "type": "Feature",
  "properties": {
    "addr:full":"102 Collins St Hobart TAS 7000",
    "addr:housenumber":"102",
    "addr:postcode":"7000",
    "addr:street":"Collins St",
    "iso:country":"AU",
    "sg:address":"102 Collins St",
    "sg:city":"Hobart",
    "sg:classifiers":[
        {
            "category":"Health Services",
            "subcategory":"Chiropractor",
            "type":"Services"
        }
    ],
    "sg:phone":"+61 3 6224 9349",
    "sg:postcode":"7000",
    "sg:province":"TAS",
    "wof:name":"Chirolife Chiropractic Centre",
    "wof:placetype":"venue"
},
  "geometry": {"coordinates":[147.328857422,-42.8823165894],"type":"Point"}
}