{
  "type": "Feature",
  "properties": {
    "addr:full":"Victoria Rd Ryde NSW 2112",
    "addr:postcode":"2112",
    "addr:street":"Victoria Rd",
    "iso:country":"AU",
    "sg:address":"Victoria Rd",
    "sg:city":"Ryde",
    "sg:classifiers":[
        {
            "category":"Education",
            "subcategory":"School",
            "type":"Public Place"
        }
    ],
    "sg:phone":"+61 2 9809 4238",
    "sg:postcode":"2112",
    "sg:province":"NSW",
    "wof:name":"St Charles' Primary School",
    "wof:placetype":"venue"
},
  "geometry": {"coordinates":[151.11097717300001,-33.8165283203],"type":"Point"}
}