{
  "type": "Feature",
  "properties": {
    "addr:full":"Unit 1, 16 Tyre Ave Riverton WA 6148",
    "addr:housenumber":"16",
    "addr:postcode":"6148",
    "addr:street":"Tyre Ave",
    "iso:country":"AU",
    "sg:address":"Unit 1, 16 Tyre Ave",
    "sg:city":"Riverton",
    "sg:classifiers":[
        {
            "category":"Personal",
            "subcategory":"Massage",
            "type":"Services"
        }
    ],
    "sg:phone":"+61 8 9457 1227",
    "sg:postcode":"6148",
    "sg:province":"WA",
    "sg:tags":[
        "therapy"
    ],
    "wof:name":"Morcom David",
    "wof:placetype":"venue"
},
  "geometry": {"coordinates":[115.90057400000001,-32.032494],"type":"Point"}
}