{
  "type": "Feature",
  "properties": {
    "addr:full":"23- 25 Collie St Fyshwick ACT 2609",
    "addr:housenumber":"25",
    "addr:postcode":"2609",
    "addr:street":"Collie St",
    "iso:country":"AU",
    "sg:address":"23- 25 Collie St",
    "sg:city":"Fyshwick",
    "sg:classifiers":[
        {
            "category":"Manufacturing",
            "subcategory":"Building Materials",
            "type":"Manufacturing & Wholesale Goods"
        }
    ],
    "sg:phone":"+61 2 6280 6047",
    "sg:postcode":"2609",
    "sg:province":"ACT",
    "sg:tags":[
        "concrete",
        "product"
    ],
    "wof:name":"Fyshwick Cement Products",
    "wof:placetype":"venue"
},
  "geometry": {"coordinates":[149.18020629899999,-35.3273048401],"type":"Point"}
}