{
  "type": "Feature",
  "properties": {
    "addr:full":"15 Pring St Ipswich QLD 4305",
    "addr:housenumber":"15",
    "addr:postcode":"4305",
    "addr:street":"Pring St",
    "iso:country":"AU",
    "sg:address":"15 Pring St",
    "sg:city":"Ipswich",
    "sg:classifiers":[
        {
            "category":"Health Services",
            "subcategory":"Dentist",
            "type":"Services"
        }
    ],
    "sg:phone":"+61 7 3812 3409",
    "sg:postcode":"4305",
    "sg:province":"QLD",
    "sg:tags":[
        "qld",
        "orthodontist"
    ],
    "wof:name":"Cavallaro A",
    "wof:placetype":"venue"
},
  "geometry": {"coordinates":[152.762252808,-27.6196613312],"type":"Point"}
}