{
  "type": "Feature",
  "properties": {
    "addr:full":"222 Adidi St Bamaga QLD 4876",
    "addr:housenumber":"222",
    "addr:postcode":"4876",
    "addr:street":"Adidi St",
    "iso:country":"AU",
    "sg:address":"222 Adidi St",
    "sg:city":"Bamaga",
    "sg:classifiers":[
        {
            "category":"Food & Beverages",
            "subcategory":"Bakery",
            "type":"Retail Goods"
        }
    ],
    "sg:phone":"+61 7 4069 3168",
    "sg:postcode":"4876",
    "sg:province":"QLD",
    "sg:tags":[
        "baker"
    ],
    "wof:name":"Bamaga Bakehaus",
    "wof:placetype":"venue"
},
  "geometry": {"coordinates":[142.38783264200001,-10.8883724213],"type":"Point"}
}