{
  "type": "Feature",
  "properties": {
    "iso:country":"AU",
    "sg:address":"Suite 6 738 Main St",
    "sg:city":"Kangaroo Point",
    "sg:classifiers":[
        {
            "category":"Personal",
            "subcategory":"Beauty Salon",
            "type":"Services"
        }
    ],
    "sg:phone":"+61 7 3891 3700",
    "sg:postcode":"4169",
    "sg:province":"QLD",
    "sg:tags":[
        "hairdresser"
    ],
    "wof:name":"Kangaroo Point Hair Design",
    "wof:placetype":"venue"
},
  "geometry": {"coordinates":[153.03596496599999,-27.4820346832],"type":"Point"}
}