{
  "type": "Feature",
  "properties": {
    "addr:full":"6 Belfree Drv Green Fields SA 5107",
    "addr:housenumber":"6",
    "addr:postcode":"5107",
    "addr:street":"Belfree Drv Green",
    "iso:country":"AU",
    "sg:address":"6 Belfree Drv",
    "sg:city":"Green Fields",
    "sg:classifiers":[
        {
            "category":"Wholesale",
            "subcategory":"Machinery & Supplies",
            "type":"Manufacturing & Wholesale Goods"
        }
    ],
    "sg:phone":"+61 8 8283 3310",
    "sg:postcode":"5107",
    "sg:province":"SA",
    "wof:name":"CNC Machinery Sales Aust P/L",
    "wof:placetype":"venue"
},
  "geometry": {"coordinates":[138.603225708,-34.7967414856],"type":"Point"}
}