{
  "type": "Feature",
  "properties": {
    "iso:country":"AU",
    "sg:address":"4 Edwards Drv",
    "sg:city":"Albany Creek",
    "sg:classifiers":[
        {
            "category":"Health Services",
            "subcategory":"Health Practitioner",
            "type":"Services"
        }
    ],
    "sg:phone":"+61 404 883 659",
    "sg:postcode":"4035",
    "sg:province":"QLD",
    "sg:tags":[
        "naturopath"
    ],
    "wof:name":"Turner Donna",
    "wof:placetype":"venue"
},
  "geometry": {"coordinates":[152.96719400000001,-27.358871],"type":"Point"}
}