{
  "type": "Feature",
  "properties": {
    "addr:full":"45 Main St Buderim QLD 4556",
    "addr:housenumber":"45",
    "addr:postcode":"4556",
    "addr:street":"Main St",
    "iso:country":"AU",
    "sg:address":"45 Main St",
    "sg:city":"Buderim",
    "sg:classifiers":[
        {
            "category":"Banks & Credit Unions",
            "subcategory":"Bank",
            "type":"Services"
        }
    ],
    "sg:phone":"+61 7 5476 9333",
    "sg:postcode":"4556",
    "sg:province":"QLD",
    "sg:tags":[
        "broker",
        "mortgage"
    ],
    "wof:name":"Mortgage Choice",
    "wof:placetype":"venue"
},
  "geometry": {"coordinates":[153.055084228,-26.6843338013],"type":"Point"}
}