{
  "type": "Feature",
  "properties": {
    "addr:full":"34 Ord St West Perth WA 6005",
    "addr:housenumber":"34",
    "addr:postcode":"6005",
    "addr:street":"Ord St",
    "iso:country":"AU",
    "sg:address":"34 Ord St",
    "sg:city":"West Perth",
    "sg:classifiers":[
        {
            "category":"Health Services",
            "subcategory":"Doctor",
            "type":"Services"
        }
    ],
    "sg:phone":"+61 8 9481 1822",
    "sg:postcode":"6005",
    "sg:province":"WA",
    "sg:tags":[
        "medical",
        "practitioner"
    ],
    "wof:name":"Malone Quentin Dr",
    "wof:placetype":"venue"
},
  "geometry": {"coordinates":[115.840370178,-31.9503059387],"type":"Point"}
}