{
  "type": "Feature",
  "properties": {
    "addr:full":"Shop GF 24, \"Broadway on the Mall\" Brisbane QLD 4000",
    "addr:postcode":"4000",
    "addr:street":"Broadway",
    "iso:country":"AU",
    "sg:address":"Shop GF 24, \"Broadway on the Mall\"",
    "sg:city":"Brisbane",
    "sg:classifiers":[
        {
            "category":"Shopping",
            "subcategory":"Jewelry",
            "type":"Retail Goods"
        }
    ],
    "sg:phone":"+61 7 3012 8833",
    "sg:postcode":"4000",
    "sg:province":"QLD",
    "sg:tags":[
        "jeweller"
    ],
    "wof:name":"Secrets Shhh",
    "wof:placetype":"venue"
},
  "geometry": {"coordinates":[153.02607727,-27.4688072205],"type":"Point"}
}