{
  "type": "Feature",
  "properties": {
    "addr:full":"Shop 4, 18 Stamford Rd Indooroopilly QLD 4068",
    "addr:housenumber":"shop;18",
    "addr:postcode":"4068",
    "addr:street":"Stamford Rd",
    "iso:country":"AU",
    "sg:address":"Shop 4, 18 Stamford Rd",
    "sg:city":"Indooroopilly",
    "sg:classifiers":[
        {
            "category":"Food & Beverages",
            "subcategory":"Bakery",
            "type":"Retail Goods"
        }
    ],
    "sg:phone":"+61 7 3878 1166",
    "sg:postcode":"4068",
    "sg:province":"QLD",
    "sg:tags":[
        "baker"
    ],
    "wof:name":"Brumby's Bakeries",
    "wof:placetype":"venue"
},
  "geometry": {"coordinates":[152.97398376500001,-27.4981899261],"type":"Point"}
}