{
  "type": "Feature",
  "properties": {
    "iso:country":"AU",
    "sg:address":"Avoca Rd",
    "sg:city":"Ararat",
    "sg:classifiers":[
        {
            "category":"Building & Trades",
            "subcategory":"Landscaping Services",
            "type":"Services"
        }
    ],
    "sg:phone":"+61 3 5352 1334",
    "sg:postcode":"3377",
    "sg:province":"VIC",
    "sg:tags":[
        "grazier"
    ],
    "wof:name":"Shea Gerald J",
    "wof:placetype":"venue"
},
  "geometry": {"coordinates":[142.93130493199999,-37.2824211121],"type":"Point"}
}