{
  "type": "Feature",
  "properties": {
    "iso:country":"AU",
    "sg:address":"14 Lightfoot St",
    "sg:city":"Mont Albert",
    "sg:classifiers":[
        {
            "category":"Retail",
            "subcategory":"Auto Repair",
            "type":"Services"
        }
    ],
    "sg:phone":"+61 3 9898 3677",
    "sg:postcode":"3127",
    "sg:province":"VIC",
    "sg:tags":[
        "repairer",
        "motor",
        "engineer"
    ],
    "wof:name":"Lightfoot Engineering",
    "wof:placetype":"venue"
},
  "geometry": {"coordinates":[145.10455322300001,-37.8130569458],"type":"Point"}
}