{
  "type": "Feature",
  "properties": {
    "addr:full":"Lot2/ Currall St Narembeen WA 6369",
    "addr:postcode":"6369",
    "addr:street":"St",
    "iso:country":"AU",
    "sg:address":"Lot2/ Currall St",
    "sg:city":"Narembeen",
    "sg:classifiers":[
        {
            "category":"Shopping",
            "subcategory":"Computers & Home Electronics",
            "type":"Retail Goods"
        }
    ],
    "sg:phone":"+61 8 9064 7859",
    "sg:postcode":"6369",
    "sg:province":"WA",
    "sg:tags":[
        "equipment",
        "multimedia"
    ],
    "wof:name":"Inspirations Ink",
    "wof:placetype":"venue"
},
  "geometry": {"coordinates":[118.39576700000001,-32.065517],"type":"Point"}
}