{
  "type": "Feature",
  "properties": {
    "iso:country":"AU",
    "sg:address":"132 Gabriel St",
    "sg:city":"Cloverdale",
    "sg:classifiers":[
        {
            "category":"Arena",
            "subcategory":"Sports Club",
            "type":"Entertainment"
        }
    ],
    "sg:phone":"+61 8 9277 7781",
    "sg:postcode":"6105",
    "sg:province":"WA",
    "sg:tags":[
        "organisation",
        "sporting"
    ],
    "wof:name":"All-Round Weightlifting WA",
    "wof:placetype":"venue"
},
  "geometry": {"coordinates":[115.942459106,-31.9641895294],"type":"Point"}
}