{
  "type": "Feature",
  "properties": {
    "addr:full":"3/ 22 Woodburn St Evans Head NSW 2473",
    "addr:housenumber":"/ 22",
    "addr:postcode":"2473",
    "addr:street":"Woodburn St Evans",
    "iso:country":"AU",
    "sg:address":"3/ 22 Woodburn St",
    "sg:city":"Evans Head",
    "sg:classifiers":[
        {
            "category":"Health Services",
            "subcategory":"Dentist",
            "type":"Services"
        }
    ],
    "sg:phone":"+61 2 6682 6704",
    "sg:postcode":"2473",
    "sg:province":"NSW",
    "sg:tags":[
        "dental",
        "prosthetist"
    ],
    "wof:name":"Evans Head Casino Denture Clinic",
    "wof:placetype":"venue"
},
  "geometry": {"coordinates":[153.42999267600001,-29.1175689697],"type":"Point"}
}