{
  "type": "Feature",
  "properties": {
    "addr:full":"40 Moore St Leichhardt NSW 2040",
    "addr:housenumber":"40",
    "addr:postcode":"2040",
    "addr:street":"Moore St",
    "iso:country":"AU",
    "sg:address":"40 Moore St",
    "sg:city":"Leichhardt",
    "sg:classifiers":[
        {
            "category":"Real Estate",
            "subcategory":"Real Estate Operator",
            "type":"Services"
        }
    ],
    "sg:phone":"+61 2 9692 9190",
    "sg:postcode":"2040",
    "sg:province":"NSW",
    "sg:tags":[
        "concrete",
        "pumping"
    ],
    "wof:name":"Arrow Concrete Placing Pty Ltd",
    "wof:placetype":"venue"
},
  "geometry": {"coordinates":[151.165176,-33.879597],"type":"Point"}
}