{
  "type": "Feature",
  "properties": {
    "iso:country":"AU",
    "sg:address":"154- 156 Gaffney St",
    "sg:city":"Coburg",
    "sg:classifiers":[
        {
            "category":"Home & Garden",
            "subcategory":"Garden Supply",
            "type":"Retail Goods"
        }
    ],
    "sg:phone":"+61 3 9354 2299",
    "sg:postcode":"3058",
    "sg:province":"VIC",
    "sg:tags":[
        "equipment"
    ],
    "wof:name":"Coburg Sand & Soil",
    "wof:placetype":"venue"
},
  "geometry": {"coordinates":[144.95280456500001,-37.7326622009],"type":"Point"}
}