{
  "type": "Feature",
  "properties": {
    "iso:country":"AU",
    "sg:address":"127 Mangles St",
    "sg:city":"Bunbury",
    "sg:classifiers":[
        {
            "category":"Utilities",
            "subcategory":"Refuse",
            "type":"Services"
        }
    ],
    "sg:phone":"+61 8 9725 0725",
    "sg:postcode":"6230",
    "sg:province":"WA",
    "sg:tags":[
        "disposal",
        "reduction",
        "waste"
    ],
    "wof:name":"Bunbury Ezy Bins",
    "wof:placetype":"venue"
},
  "geometry": {"coordinates":[115.640419,-33.349617],"type":"Point"}
}