{
  "type": "Feature",
  "properties": {
    "addr:full":"15 Colgan St Cobram VIC 3644",
    "addr:housenumber":"15",
    "addr:postcode":"3644",
    "addr:street":"Colgan St",
    "iso:country":"AU",
    "sg:address":"15 Colgan St",
    "sg:city":"Cobram",
    "sg:classifiers":[
        {
            "category":"Coffee & Tea",
            "type":"Food & Drink"
        }
    ],
    "sg:phone":"+61 3 5871 1711",
    "sg:postcode":"3644",
    "sg:province":"VIC",
    "sg:tags":[
        "kayak",
        "canoe"
    ],
    "wof:name":"Competition Kayaks Pty Ltd",
    "wof:placetype":"venue"
},
  "geometry": {"coordinates":[145.64414977999999,-35.9199867249],"type":"Point"}
}