{
  "type": "Feature",
  "properties": {
    "iso:country":"AU",
    "sg:address":"78 Woodlands Drv",
    "sg:city":"Braeside",
    "sg:classifiers":[
        {
            "category":"Shopping",
            "subcategory":"Computers & Home Electronics",
            "type":"Retail Goods"
        }
    ],
    "sg:phone":"+61 3 9587 1443",
    "sg:postcode":"3195",
    "sg:province":"VIC",
    "sg:tags":[
        "equipment",
        "supply"
    ],
    "wof:name":"IT Exchange",
    "wof:placetype":"venue"
},
  "geometry": {"coordinates":[145.11827087399999,-37.9929542542],"type":"Point"}
}