{
  "type": "Feature",
  "properties": {
    "addr:full":"23 David St Mullaloo WA 6027",
    "addr:housenumber":"23",
    "addr:postcode":"6027",
    "addr:street":"David St",
    "iso:country":"AU",
    "sg:address":"23 David St",
    "sg:city":"Mullaloo",
    "sg:classifiers":[
        {
            "category":"Utilities",
            "subcategory":"Electric",
            "type":"Services"
        }
    ],
    "sg:phone":"+61 408 952 236",
    "sg:postcode":"6027",
    "sg:province":"WA",
    "sg:tags":[
        "electrical",
        "contractor"
    ],
    "wof:name":"Oceanic Electrics",
    "wof:placetype":"venue"
},
  "geometry": {"coordinates":[115.738380432,-31.7790584564],"type":"Point"}
}