{
  "type": "Feature",
  "properties": {
    "iso:country":"AU",
    "sg:address":"Flinders St",
    "sg:city":"Wollongong",
    "sg:classifiers":[
        {
            "category":"Retail",
            "subcategory":"Event Space",
            "type":"Services"
        }
    ],
    "sg:phone":"+61 2 4228 6222",
    "sg:postcode":"2500",
    "sg:province":"NSW",
    "sg:tags":[
        "venue",
        "reception",
        "wedding"
    ],
    "wof:name":"Villa D&#039;Oro",
    "wof:placetype":"venue"
},
  "geometry": {"coordinates":[150.89250200000001,-34.411362],"type":"Point"}
}