{
  "type": "Feature",
  "properties": {
    "addr:full":"6 Eighth St Home Hill QLD 4806",
    "addr:housenumber":"6",
    "addr:postcode":"4806",
    "addr:street":"Eighth St",
    "iso:country":"AU",
    "sg:address":"6 Eighth St",
    "sg:city":"Home Hill",
    "sg:classifiers":[
        {
            "category":"Professional",
            "subcategory":"Art Services",
            "type":"Services"
        }
    ],
    "sg:phone":"+61 7 4782 2433",
    "sg:postcode":"4806",
    "sg:province":"QLD",
    "sg:tags":[
        "decorator",
        "painter"
    ],
    "wof:name":"Merv Milburn",
    "wof:placetype":"venue"
},
  "geometry": {"coordinates":[147.41148376500001,-19.6651382446],"type":"Point"}
}