{
  "type": "Feature",
  "properties": {
    "addr:full":"127 Gatton Laidley Rd Laidley Heights QLD 4341",
    "addr:housenumber":"127",
    "addr:postcode":"4341",
    "addr:street":"Gatton Laidley Rd",
    "iso:country":"AU",
    "sg:address":"127 Gatton Laidley Rd",
    "sg:city":"Laidley Heights",
    "sg:classifiers":[
        {
            "category":"Farming",
            "subcategory":"Farm",
            "type":"Manufacturing & Wholesale Goods"
        }
    ],
    "sg:phone":"+61 7 5465 1444",
    "sg:postcode":"4341",
    "sg:province":"QLD",
    "sg:tags":[
        "farmer"
    ],
    "wof:name":"Jackwitz D H",
    "wof:placetype":"venue"
},
  "geometry": {"coordinates":[152.364501953,-27.6043014526],"type":"Point"}
}