{
  "type": "Feature",
  "properties": {
    "iso:country":"AU",
    "sg:address":"1 Harper Pl",
    "sg:city":"Mill Park",
    "sg:classifiers":[
        {
            "category":"Building & Trades",
            "subcategory":"Construction",
            "type":"Services"
        }
    ],
    "sg:phone":"+61 3 9404 4949",
    "sg:postcode":"3082",
    "sg:province":"VIC",
    "sg:tags":[
        "fencing",
        "contractor"
    ],
    "wof:name":"JDM Fencing",
    "wof:placetype":"venue"
},
  "geometry": {"coordinates":[145.06973266599999,-37.6614265442],"type":"Point"}
}