{
  "type": "Feature",
  "properties": {
    "iso:country":"AU",
    "sg:address":"247 Victoria St",
    "sg:city":"Taree",
    "sg:classifiers":[
        {
            "category":"Health Services",
            "subcategory":"Doctor",
            "type":"Services"
        }
    ],
    "sg:phone":"+61 2 6552 5151",
    "sg:postcode":"2430",
    "sg:province":"NSW",
    "sg:tags":[
        "reflexology"
    ],
    "wof:name":"Albert Smith",
    "wof:placetype":"venue"
},
  "geometry": {"coordinates":[152.456726,-31.915684],"type":"Point"}
}