{
  "type": "Feature",
  "properties": {
    "addr:full":"Suite G2 657 Chapel St South Yarra VIC 3141",
    "addr:housenumber":"657",
    "addr:postcode":"3141",
    "addr:street":"Chapel St",
    "iso:country":"AU",
    "sg:address":"Suite G2 657 Chapel St",
    "sg:city":"South Yarra",
    "sg:classifiers":[
        {
            "category":"Health Services",
            "subcategory":"Doctor",
            "type":"Services"
        }
    ],
    "sg:phone":"+61 3 9826 1866",
    "sg:postcode":"3141",
    "sg:province":"VIC",
    "sg:tags":[
        "medical",
        "practitioner"
    ],
    "wof:name":"Bishop J.M.",
    "wof:placetype":"venue"
},
  "geometry": {"coordinates":[144.99595642099999,-37.836971283],"type":"Point"}
}