{
  "type": "Feature",
  "properties": {
    "addr:full":"59 Feltham St North Hobart TAS 7000",
    "addr:housenumber":"59",
    "addr:postcode":"7000",
    "addr:street":"Feltham St",
    "iso:country":"AU",
    "sg:address":"59 Feltham St",
    "sg:city":"North Hobart",
    "sg:classifiers":[
        {
            "category":"Professional",
            "subcategory":"Art Services",
            "type":"Services"
        }
    ],
    "sg:phone":"+61 3 6231 0832",
    "sg:postcode":"7000",
    "sg:province":"TAS",
    "sg:tags":[
        "graphic",
        "designer"
    ],
    "wof:name":"Hobart Sign - FX",
    "wof:placetype":"venue"
},
  "geometry": {"coordinates":[147.317504883,-42.8708114624],"type":"Point"}
}