{
  "type": "Feature",
  "properties": {
    "addr:full":"10 Taronga Pl Mona Vale NSW 2103",
    "addr:housenumber":"10",
    "addr:postcode":"2103",
    "addr:street":"Taronga Pl",
    "iso:country":"AU",
    "sg:address":"10 Taronga Pl",
    "sg:city":"Mona Vale",
    "sg:classifiers":[
        {
            "category":"Home & Garden",
            "subcategory":"Hardware",
            "type":"Retail Goods"
        }
    ],
    "sg:phone":"+61 2 9997 4831",
    "sg:postcode":"2103",
    "sg:province":"NSW",
    "sg:tags":[
        "plumber",
        "supply"
    ],
    "wof:name":"Reece Pty Ltd",
    "wof:placetype":"venue"
},
  "geometry": {"coordinates":[151.30621337900001,-33.674621582],"type":"Point"}
}