{
  "type": "Feature",
  "properties": {
    "iso:country":"AU",
    "sg:address":"Murrays Rd",
    "sg:city":"Moorooduc",
    "sg:classifiers":[
        {
            "category":"Farming",
            "subcategory":"Farm",
            "type":"Manufacturing & Wholesale Goods"
        }
    ],
    "sg:phone":"+61 3 5978 8292",
    "sg:postcode":"3933",
    "sg:province":"VIC",
    "sg:tags":[
        "farmer"
    ],
    "wof:name":"Kasickis A A",
    "wof:placetype":"venue"
},
  "geometry": {"coordinates":[145.134231567,-38.2540855408],"type":"Point"}
}