{
  "type": "Feature",
  "properties": {
    "iso:country":"AU",
    "sg:address":"11 Brampton Ave",
    "sg:city":"Cranbrook",
    "sg:classifiers":[
        {
            "category":"Building & Trades",
            "subcategory":"Construction",
            "type":"Services"
        }
    ],
    "sg:phone":"+61 403 044 415",
    "sg:postcode":"4814",
    "sg:province":"QLD",
    "sg:tags":[
        "plasterboard",
        "plasterer",
        "fixer"
    ],
    "wof:name":"Rob Wilcomes",
    "wof:placetype":"venue"
},
  "geometry": {"coordinates":[146.758942,-19.296015],"type":"Point"}
}