{
  "type": "Feature",
  "properties": {
    "iso:country":"AU",
    "sg:address":"23 Charles St",
    "sg:city":"South Perth",
    "sg:classifiers":[
        {
            "category":"Professional",
            "subcategory":"Accounting & Tax Preparation",
            "type":"Services"
        }
    ],
    "sg:phone":"+61 8 9368 1088",
    "sg:postcode":"6151",
    "sg:province":"WA",
    "sg:tags":[
        "consultant",
        "taxation"
    ],
    "wof:name":"TA Mairs & Co Pty Ltd",
    "wof:placetype":"venue"
},
  "geometry": {"coordinates":[115.85105900000001,-31.976383],"type":"Point"}
}