{
  "type": "Feature",
  "properties": {
    "addr:full":"51 Cowie St Geelong North VIC 3215",
    "addr:housenumber":"51",
    "addr:postcode":"3215",
    "addr:street":"Cowie St",
    "iso:country":"AU",
    "sg:address":"51 Cowie St",
    "sg:city":"Geelong North",
    "sg:classifiers":[
        {
            "category":"Wholesale",
            "subcategory":"Metals & Minerals",
            "type":"Manufacturing & Wholesale Goods"
        }
    ],
    "sg:phone":"+61 3 5247 4100",
    "sg:postcode":"3215",
    "sg:province":"VIC",
    "sg:tags":[
        "steel",
        "merchant"
    ],
    "wof:name":"Metalcorp New Steel Sales",
    "wof:placetype":"venue"
},
  "geometry": {"coordinates":[144.34677124000001,-38.1056098938],"type":"Point"}
}