{
  "type": "Feature",
  "properties": {
    "iso:country":"AU",
    "sg:address":"3 - 5 Loop Road",
    "sg:city":"Airlie Beach",
    "sg:classifiers":[
        {
            "category":"Retail",
            "subcategory":"Storage",
            "type":"Services"
        }
    ],
    "sg:phone":"+61 7 4948 2752",
    "sg:postcode":"4802",
    "sg:province":"QLD",
    "sg:website":"http://www.selfstorage.com.au/quote.php",
    "wof:name":"Storage World Whitsunday",
    "wof:placetype":"venue"
},
  "geometry": {"coordinates":[148.73057556099999,-20.2798671722],"type":"Point"}
}