{
  "type": "Feature",
  "properties": {
    "iso:country":"AU",
    "sg:address":"160 Cowper St",
    "sg:city":"Warrawong",
    "sg:classifiers":[
        {
            "category":"Health Services",
            "subcategory":"Doctor",
            "type":"Services"
        }
    ],
    "sg:phone":"+61 2 4276 1333",
    "sg:postcode":"2502",
    "sg:province":"NSW",
    "sg:tags":[
        "medical",
        "practitioner"
    ],
    "wof:name":"Lenehan J R",
    "wof:placetype":"venue"
},
  "geometry": {"coordinates":[150.890518,-34.485149],"type":"Point"}
}