{
  "type": "Feature",
  "properties": {
    "addr:full":"Cnr Thynne Rd & Ison St Morningside QLD 4170",
    "addr:postcode":"4170",
    "addr:street":"Cnr Thynne Rd & Ison St",
    "iso:country":"AU",
    "sg:address":"Cnr Thynne Rd & Ison St",
    "sg:city":"Morningside",
    "sg:classifiers":[
        {
            "category":"Health Services",
            "subcategory":"Health Practitioner",
            "type":"Services"
        }
    ],
    "sg:phone":"+61 7 3899 1833",
    "sg:postcode":"4170",
    "sg:province":"QLD",
    "sg:tags":[
        "physiotherapist"
    ],
    "wof:name":"BrisHealth Physiotherapy",
    "wof:placetype":"venue"
},
  "geometry": {"coordinates":[153.07043457,-27.4674530029],"type":"Point"}
}