{
  "type": "Feature",
  "properties": {
    "addr:full":"Unit 8, 62-66 Hume Hwy Green Valley NSW 2168",
    "addr:housenumber":"62-66",
    "addr:postcode":"2168",
    "addr:street":"Hume Hwy",
    "iso:country":"AU",
    "sg:address":"Unit 8, 62-66 Hume Hwy",
    "sg:city":"Green Valley",
    "sg:classifiers":[
        {
            "category":"Wholesale",
            "subcategory":"Construction Materials",
            "type":"Manufacturing & Wholesale Goods"
        }
    ],
    "sg:phone":"+61 2 9728 9666",
    "sg:postcode":"2168",
    "sg:province":"NSW",
    "sg:tags":[
        "wholesaler",
        "lighting",
        "mfrs",
        "accessory"
    ],
    "wof:name":"Kialeena Pty Ltd",
    "wof:placetype":"venue"
},
  "geometry": {"coordinates":[150.86651611299999,-33.9027404785],"type":"Point"}
}