{
  "type": "Feature",
  "properties": {
    "addr:full":"126 Eastern Ave Kingsford NSW 2032",
    "addr:housenumber":"126",
    "addr:postcode":"2032",
    "addr:street":"Eastern Ave",
    "iso:country":"AU",
    "sg:address":"126 Eastern Ave",
    "sg:city":"Kingsford",
    "sg:classifiers":[
        {
            "category":"Home & Garden",
            "subcategory":"Building Materials",
            "type":"Retail Goods"
        }
    ],
    "sg:phone":"+61 23286778",
    "sg:postcode":"2032",
    "sg:province":"NSW",
    "sg:tags":[
        "lawn",
        "cutting",
        "maintenance"
    ],
    "wof:name":"Precision Lawnmowing",
    "wof:placetype":"venue"
},
  "geometry": {"coordinates":[151.21888732900001,-33.922996521],"type":"Point"}
}