{
  "type": "Feature",
  "properties": {
    "addr:full":"6 Short St Enfield NSW 2136",
    "addr:housenumber":"6",
    "addr:postcode":"2136",
    "addr:street":"Short St",
    "iso:country":"AU",
    "sg:address":"6 Short St",
    "sg:city":"Enfield",
    "sg:classifiers":[
        {
            "category":"Professional",
            "subcategory":"Business Services",
            "type":"Services"
        }
    ],
    "sg:phone":"+61 2 9747 6153",
    "sg:postcode":"2136",
    "sg:province":"NSW",
    "sg:tags":[
        "exporter"
    ],
    "wof:name":"Soon Fang Trading Company",
    "wof:placetype":"venue"
},
  "geometry": {"coordinates":[151.097198486,-33.8911209106],"type":"Point"}
}