{
  "type": "Feature",
  "properties": {
    "addr:full":"Atlantis Shopping Centre Cnr Sovereign Drv & Enter Two Rocks WA 6037",
    "addr:postcode":"6037",
    "addr:street":"Cnr Sovereign Drv &;Two Rocks",
    "iso:country":"AU",
    "sg:address":"Atlantis Shopping Centre Cnr Sovereign Drv & Enter",
    "sg:city":"Two Rocks",
    "sg:classifiers":[
        {
            "category":"Fast Food",
            "type":"Food & Drink"
        }
    ],
    "sg:phone":"+61 8 9561 6070",
    "sg:postcode":"6037",
    "sg:province":"WA",
    "sg:tags":[
        "away",
        "take"
    ],
    "wof:name":"Eagle Boys Pizza",
    "wof:placetype":"venue"
},
  "geometry": {"coordinates":[115.585739136,-31.4941940308],"type":"Point"}
}