{
  "type": "Feature",
  "properties": {
    "iso:country":"AU",
    "sg:address":"524 Centre Rd",
    "sg:city":"Bentleigh",
    "sg:classifiers":[
        {
            "category":"Food & Beverages",
            "subcategory":"Liquor & Beverages",
            "type":"Retail Goods"
        }
    ],
    "sg:phone":"+61 3 9557 6821",
    "sg:postcode":"3204",
    "sg:province":"VIC",
    "sg:tags":[
        "store"
    ],
    "wof:name":"Safeway Liquor",
    "wof:placetype":"venue"
},
  "geometry": {"coordinates":[145.041794,-37.918953],"type":"Point"}
}