{
  "type": "Feature",
  "properties": {
    "addr:full":"Level 1, 195 Hume St Toowoomba QLD 4350",
    "addr:housenumber":"195",
    "addr:postcode":"4350",
    "addr:street":"Hume St",
    "iso:country":"AU",
    "sg:address":"Level 1, 195 Hume St",
    "sg:city":"Toowoomba",
    "sg:classifiers":[
        {
            "category":"Banks & Credit Unions",
            "subcategory":"Investment Brokerage",
            "type":"Services"
        }
    ],
    "sg:phone":"+61 7 4613 0808",
    "sg:postcode":"4350",
    "sg:province":"QLD",
    "sg:tags":[
        "finance",
        "broker"
    ],
    "wof:name":"Ernst & Jones Finance",
    "wof:placetype":"venue"
},
  "geometry": {"coordinates":[151.956512,-27.567734],"type":"Point"}
}