{
  "type": "Feature",
  "properties": {
    "iso:country":"AU",
    "sg:address":"Unit 3 65 Pilkington St",
    "sg:city":"Garbutt",
    "sg:classifiers":[
        {
            "category":"Building & Trades",
            "subcategory":"Construction",
            "type":"Services"
        }
    ],
    "sg:phone":"+61 405 562 463",
    "sg:postcode":"4814",
    "sg:province":"QLD",
    "sg:tags":[
        "fencing",
        "contractor"
    ],
    "wof:name":"Xpert Fencing",
    "wof:placetype":"venue"
},
  "geometry": {"coordinates":[146.766876,-19.271261],"type":"Point"}
}