{
  "type": "Feature",
  "properties": {
    "iso:country":"AU",
    "sg:address":"Suite 303, 460 Pacific Hwy",
    "sg:city":"St Leonards",
    "sg:classifiers":[
        {
            "category":"Professional",
            "subcategory":"Computer Services",
            "type":"Services"
        }
    ],
    "sg:phone":"+61 2 9438 3940",
    "sg:postcode":"2065",
    "sg:province":"NSW",
    "sg:tags":[
        "package",
        "software"
    ],
    "wof:name":"Cortell Australia Pty Ltd",
    "wof:placetype":"venue"
},
  "geometry": {"coordinates":[151.19764709500001,-33.8244934082],"type":"Point"}
}