{
  "type": "Feature",
  "properties": {
    "addr:full":"138 Macrossan Ave Norman Park QLD 4170",
    "addr:housenumber":"138",
    "addr:postcode":"4170",
    "addr:street":"Macrossan Ave",
    "iso:country":"AU",
    "sg:address":"138 Macrossan Ave",
    "sg:city":"Norman Park",
    "sg:classifiers":[
        {
            "category":"Building & Trades",
            "subcategory":"Construction",
            "type":"Services"
        }
    ],
    "sg:phone":"+61 7 3843 2810",
    "sg:postcode":"4170",
    "sg:province":"QLD",
    "sg:tags":[
        "concrete",
        "contractor"
    ],
    "wof:name":"New Image Concrete Services",
    "wof:placetype":"venue"
},
  "geometry": {"coordinates":[153.071899414,-27.4842147827],"type":"Point"}
}