{
  "type": "Feature",
  "properties": {
    "addr:full":"57 Railway Pde Lithgow NSW 2790",
    "addr:housenumber":"57",
    "addr:postcode":"2790",
    "addr:street":"Railway Pde",
    "iso:country":"AU",
    "sg:address":"57 Railway Pde",
    "sg:city":"Lithgow",
    "sg:classifiers":[
        {
            "category":"Health Services",
            "subcategory":"Chiropractor",
            "type":"Services"
        }
    ],
    "sg:phone":"+61 2 6352 3824",
    "sg:postcode":"2790",
    "sg:province":"NSW",
    "wof:name":"Erikson Peter",
    "wof:placetype":"venue"
},
  "geometry": {"coordinates":[150.156616211,-33.4802742004],"type":"Point"}
}