{
  "type": "Feature",
  "properties": {
    "addr:full":"103 Binalong Rd Toongabbie NSW 2146",
    "addr:housenumber":"103",
    "addr:postcode":"2146",
    "addr:street":"Binalong Rd",
    "iso:country":"AU",
    "sg:address":"103 Binalong Rd",
    "sg:city":"Toongabbie",
    "sg:classifiers":[
        {
            "category":"Personal",
            "subcategory":"Hair Removal",
            "type":"Services"
        }
    ],
    "sg:phone":"+61 2 9631 2132",
    "sg:postcode":"2146",
    "sg:province":"NSW",
    "wof:name":"Ballards Margaret House Of Health & Beauty",
    "wof:placetype":"venue"
},
  "geometry": {"coordinates":[150.96446227999999,-33.7934188843],"type":"Point"}
}