{
  "type": "Feature",
  "properties": {
    "addr:full":"3 Centre Kirkham Rd Dandenong VIC 3175",
    "addr:housenumber":"3",
    "addr:postcode":"3175",
    "addr:street":"Centre Kirkham Rd",
    "iso:country":"AU",
    "sg:address":"3 Centre Kirkham Rd",
    "sg:city":"Dandenong",
    "sg:classifiers":[
        {
            "category":"Utilities",
            "subcategory":"Refuse",
            "type":"Services"
        }
    ],
    "sg:phone":"+61 3 9793 8001",
    "sg:postcode":"3175",
    "sg:province":"VIC",
    "sg:tags":[
        "remover",
        "rubbish"
    ],
    "wof:name":"AAAACCESS Bins - Corio Waste",
    "wof:placetype":"venue"
},
  "geometry": {"coordinates":[145.194381714,-37.996887207],"type":"Point"}
}