{
  "type": "Feature",
  "properties": {
    "addr:full":"Hassell Hwy Jerramungup WA 6337",
    "addr:postcode":"6337",
    "addr:street":"Hassell Hwy",
    "iso:country":"AU",
    "sg:address":"Hassell Hwy",
    "sg:city":"Jerramungup",
    "sg:classifiers":[
        {
            "category":"Autos & Motor Vehicles",
            "subcategory":"Fuel & Gas Station",
            "type":"Retail Goods"
        }
    ],
    "sg:phone":"+61 8 9835 1159",
    "sg:postcode":"6337",
    "sg:province":"WA",
    "wof:name":"Ampol",
    "wof:placetype":"venue"
},
  "geometry": {"coordinates":[118.920837402,-33.9384307861],"type":"Point"}
}