{
  "type": "Feature",
  "properties": {
    "iso:country":"AU",
    "sg:address":"180- 202 George St",
    "sg:city":"Redfern",
    "sg:classifiers":[
        {
            "category":"Social Services",
            "subcategory":"Child Care",
            "type":"Services"
        }
    ],
    "sg:phone":"+61 2 9319 4566",
    "sg:postcode":"2016",
    "sg:province":"NSW",
    "wof:name":"Murawina Limited Multi-Purpose Aboriginal Education Centre",
    "wof:placetype":"venue"
},
  "geometry": {"coordinates":[151.20181274399999,-33.8954315186],"type":"Point"}
}