{
  "type": "Feature",
  "properties": {
    "addr:full":"11 Tawny Crt Bray Park QLD 4500",
    "addr:housenumber":"11",
    "addr:postcode":"4500",
    "addr:street":"Tawny Crt Bray Park",
    "iso:country":"AU",
    "sg:address":"11 Tawny Crt",
    "sg:city":"Bray Park",
    "sg:classifiers":[
        {
            "category":"Building & Trades",
            "subcategory":"Equipment Rental",
            "type":"Services"
        }
    ],
    "sg:phone":"+61 7 3882 0398",
    "sg:postcode":"4500",
    "sg:province":"QLD",
    "sg:tags":[
        "crane",
        "hire"
    ],
    "wof:name":"R & B Crane Hire (Queensland) Pty Ltd",
    "wof:placetype":"venue"
},
  "geometry": {"coordinates":[152.952194214,-27.2850952148],"type":"Point"}
}