{
  "type": "Feature",
  "properties": {
    "addr:full":"PO Box 451 Woodend VIC 3442",
    "addr:postcode":"3442",
    "iso:country":"AU",
    "sg:address":"PO Box 451",
    "sg:city":"Woodend",
    "sg:classifiers":[
        {
            "category":"Professional",
            "subcategory":"Printing & Photocopies",
            "type":"Services"
        }
    ],
    "sg:phone":"+61 3 5422 3253",
    "sg:postcode":"3442",
    "sg:province":"VIC",
    "sg:tags":[
        "publishing",
        "desktop"
    ],
    "wof:name":"Imaginative Desktop Presentations",
    "wof:placetype":"venue"
},
  "geometry": {"coordinates":[144.53222656200001,-37.3525390625],"type":"Point"}
}