{
  "type": "Feature",
  "properties": {
    "iso:country":"AU",
    "sg:address":"12 Armstrong St (North)",
    "sg:city":"Ballarat",
    "sg:classifiers":[
        {
            "category":"Building & Trades",
            "subcategory":"Equipment Rental",
            "type":"Services"
        }
    ],
    "sg:phone":"+61 1800 895 099",
    "sg:postcode":"3350",
    "sg:province":"VIC",
    "sg:tags":[
        "supply",
        "catering"
    ],
    "wof:name":"Thomas Catering Equipment",
    "wof:placetype":"venue"
},
  "geometry": {"coordinates":[143.856247,-37.562859],"type":"Point"}
}