{
  "type": "Feature",
  "properties": {
    "addr:full":"4 Railway St Nemingha NSW 2340",
    "addr:housenumber":"4",
    "addr:postcode":"2340",
    "addr:street":"Railway St",
    "iso:country":"AU",
    "sg:address":"4 Railway St",
    "sg:city":"Nemingha",
    "sg:classifiers":[
        {
            "category":"Social Services",
            "subcategory":"Adult Care",
            "type":"Services"
        }
    ],
    "sg:phone":"+61 2 6760 9194",
    "sg:postcode":"2340",
    "sg:province":"NSW",
    "sg:tags":[
        "towing"
    ],
    "wof:name":"Mahers Smash Repairs",
    "wof:placetype":"venue"
},
  "geometry": {"coordinates":[150.99020385700001,-31.1234264374],"type":"Point"}
}