{
  "type": "Feature",
  "properties": {
    "addr:full":"17a Goodwood St Richmond VIC 3121",
    "addr:housenumber":"17a",
    "addr:postcode":"3121",
    "addr:street":"Goodwood St",
    "iso:country":"AU",
    "sg:address":"17a Goodwood St",
    "sg:city":"Richmond",
    "sg:classifiers":[
        {
            "category":"Professional",
            "subcategory":"Art Services",
            "type":"Services"
        }
    ],
    "sg:phone":"+61 3 9429 4147",
    "sg:postcode":"3121",
    "sg:province":"VIC",
    "sg:tags":[
        "graphic",
        "designer"
    ],
    "wof:name":"Returb Studios",
    "wof:placetype":"venue"
},
  "geometry": {"coordinates":[144.99403381400001,-37.8195266724],"type":"Point"}
}