{
  "type": "Feature",
  "properties": {
    "iso:country":"AU",
    "sg:address":"Unit 2/6 Rothesay Hts (Cnr Anchorage Drv)",
    "sg:city":"Mindarie",
    "sg:classifiers":[
        {
            "category":"Health Services",
            "subcategory":"Health Practitioner",
            "type":"Services"
        }
    ],
    "sg:phone":"+61 8 9407 7311",
    "sg:postcode":"6030",
    "sg:province":"WA",
    "sg:tags":[
        "physiotherapist"
    ],
    "wof:name":"Mindarie Keys Medical Centre",
    "wof:placetype":"venue"
},
  "geometry": {"coordinates":[115.712020874,-31.6932106018],"type":"Point"}
}