{
  "type": "Feature",
  "properties": {
    "addr:full":"Level 7, 50 Carrington St Sydney NSW 2000",
    "addr:housenumber":"50",
    "addr:postcode":"2000",
    "addr:street":"Carrington St",
    "iso:country":"AU",
    "sg:address":"Level 7, 50 Carrington St",
    "sg:city":"Sydney",
    "sg:classifiers":[
        {
            "category":"Professional",
            "subcategory":"Computer Services",
            "type":"Services"
        }
    ],
    "sg:phone":"+61 2 9290 3949",
    "sg:postcode":"2000",
    "sg:province":"NSW",
    "sg:tags":[
        "package",
        "software"
    ],
    "wof:name":"Capital Flow Software Australia Pty Limited",
    "wof:placetype":"venue"
},
  "geometry": {"coordinates":[151.20643615700001,-33.8667373657],"type":"Point"}
}