{
  "type": "Feature",
  "properties": {
    "addr:full":"6/ 151 Robinson Rd Geebung QLD 4034",
    "addr:housenumber":"/ 151",
    "addr:postcode":"4034",
    "addr:street":"Robinson Rd",
    "iso:country":"AU",
    "sg:address":"6/ 151 Robinson Rd",
    "sg:city":"Geebung",
    "sg:classifiers":[
        {
            "category":"Professional",
            "type":"Services"
        }
    ],
    "sg:phone":"+61 13 15 21",
    "sg:postcode":"4034",
    "sg:province":"QLD",
    "sg:tags":[
        "courier"
    ],
    "wof:name":"CTI Logistics",
    "wof:placetype":"venue"
},
  "geometry": {"coordinates":[153.05401599999999,-27.369165],"type":"Point"}
}