{
  "type": "Feature",
  "properties": {
    "addr:full":"2 Maleny Pl Helensvale QLD 4212",
    "addr:housenumber":"2",
    "addr:postcode":"4212",
    "addr:street":"Maleny Pl",
    "iso:country":"AU",
    "sg:address":"2 Maleny Pl",
    "sg:city":"Helensvale",
    "sg:classifiers":[
        {
            "category":"Professional",
            "subcategory":"Art Services",
            "type":"Services"
        }
    ],
    "sg:phone":"+61 7 5573 5109",
    "sg:postcode":"4212",
    "sg:province":"QLD",
    "sg:tags":[
        "decorator",
        "painter"
    ],
    "wof:name":"Adams Michael",
    "wof:placetype":"venue"
},
  "geometry": {"coordinates":[153.33795165999999,-27.9054546356],"type":"Point"}
}