{
  "type": "Feature",
  "properties": {
    "iso:country":"AU",
    "sg:address":"92 Carlingsford St",
    "sg:city":"Caulfield South",
    "sg:classifiers":[
        {
            "category":"Wholesale",
            "subcategory":"Machinery & Supplies",
            "type":"Manufacturing & Wholesale Goods"
        }
    ],
    "sg:phone":"+61 3 9505 3635",
    "sg:postcode":"3162",
    "sg:province":"VIC",
    "wof:name":"R.B. Tools",
    "wof:placetype":"venue"
},
  "geometry": {"coordinates":[145.016555786,-37.8898963928],"type":"Point"}
}