{
  "type": "Feature",
  "properties": {
    "iso:country":"AU",
    "sg:address":"213 Newlands Rd",
    "sg:city":"Coburg",
    "sg:classifiers":[
        {
            "category":"Home & Garden",
            "subcategory":"Building Materials",
            "type":"Retail Goods"
        }
    ],
    "sg:phone":"+61 3 9354 3345",
    "sg:postcode":"3058",
    "sg:province":"VIC",
    "sg:tags":[
        "secondhand"
    ],
    "wof:name":"A. Mitsakis Holdings",
    "wof:placetype":"venue"
},
  "geometry": {"coordinates":[144.97715759299999,-37.7205886841],"type":"Point"}
}