{
  "type": "Feature",
  "properties": {
    "addr:full":"24- 28 Childs Rd Chipping Norton NSW 2170",
    "addr:housenumber":"28",
    "addr:postcode":"2170",
    "addr:street":"Childs Rd",
    "iso:country":"AU",
    "sg:address":"24- 28 Childs Rd",
    "sg:city":"Chipping Norton",
    "sg:classifiers":[
        {
            "category":"Manufacturing",
            "subcategory":"Metals",
            "type":"Manufacturing & Wholesale Goods"
        }
    ],
    "sg:phone":"+61 2 9725 6411",
    "sg:postcode":"2170",
    "sg:province":"NSW",
    "sg:tags":[
        "merchant"
    ],
    "wof:name":"Barca Metals",
    "wof:placetype":"venue"
},
  "geometry": {"coordinates":[150.96218872099999,-33.9191055298],"type":"Point"}
}