{
  "type": "Feature",
  "properties": {
    "addr:full":"40 Glencoe St Kennington VIC 3550",
    "addr:housenumber":"40",
    "addr:postcode":"3550",
    "addr:street":"Glencoe St",
    "iso:country":"AU",
    "sg:address":"40 Glencoe St",
    "sg:city":"Kennington",
    "sg:classifiers":[
        {
            "category":"Professional",
            "subcategory":"Art Services",
            "type":"Services"
        }
    ],
    "sg:phone":"+61 3 5442 6290",
    "sg:postcode":"3550",
    "sg:province":"VIC",
    "sg:tags":[
        "decorator",
        "painter"
    ],
    "wof:name":"Stevenson David I",
    "wof:placetype":"venue"
},
  "geometry": {"coordinates":[144.29818725600001,-36.7620429993],"type":"Point"}
}