{
  "type": "Feature",
  "properties": {
    "addr:full":"12 Chapman Ave Salisbury Heights SA 5109",
    "addr:housenumber":"12",
    "addr:postcode":"5109",
    "addr:street":"Chapman Ave",
    "iso:country":"AU",
    "sg:address":"12 Chapman Ave",
    "sg:city":"Salisbury Heights",
    "sg:classifiers":[
        {
            "category":"Home & Garden",
            "subcategory":"Building Materials",
            "type":"Retail Goods"
        }
    ],
    "sg:phone":"+61 8 8250 6248",
    "sg:postcode":"5109",
    "sg:province":"SA",
    "sg:tags":[
        "lawn",
        "cutting",
        "maintenance"
    ],
    "wof:name":"Brady W & O",
    "wof:placetype":"venue"
},
  "geometry": {"coordinates":[138.68356323200001,-34.7658348083],"type":"Point"}
}