{
  "type": "Feature",
  "properties": {
    "addr:full":"11 Burnett St Buderim QLD 4556",
    "addr:housenumber":"11",
    "addr:postcode":"4556",
    "addr:street":"Burnett St",
    "iso:country":"AU",
    "sg:address":"11 Burnett St",
    "sg:city":"Buderim",
    "sg:classifiers":[
        {
            "category":"Personal",
            "subcategory":"Barber",
            "type":"Services"
        }
    ],
    "sg:phone":"+61 7 5445 1926",
    "sg:postcode":"4556",
    "sg:province":"QLD",
    "wof:name":"David McDonald",
    "wof:placetype":"venue"
},
  "geometry": {"coordinates":[153.04881286599999,-26.6876907349],"type":"Point"}
}