{
  "type": "Feature",
  "properties": {
    "iso:country":"AU",
    "sg:address":"85b Jetty Rd",
    "sg:city":"Glenelg",
    "sg:classifiers":[
        {
            "category":"Manufacturing",
            "subcategory":"Food",
            "type":"Manufacturing & Wholesale Goods"
        }
    ],
    "sg:phone":"+61 8 8376 9088",
    "sg:postcode":"5045",
    "sg:province":"SA",
    "sg:tags":[
        "product",
        "nut",
        "edible"
    ],
    "wof:name":"Ditters Nuts",
    "wof:placetype":"venue"
},
  "geometry": {"coordinates":[138.516953,-34.980061],"type":"Point"}
}