{
  "type": "Feature",
  "properties": {
    "iso:country":"AU",
    "sg:address":"15/ 12 Tranmere St",
    "sg:city":"Drummoyne",
    "sg:classifiers":[
        {
            "category":"Autos & Motor Vehicles",
            "subcategory":"Auto Supplies",
            "type":"Retail Goods"
        }
    ],
    "sg:phone":"+61 2 9719 2546",
    "sg:postcode":"2047",
    "sg:province":"NSW",
    "sg:tags":[
        "car",
        "alarm"
    ],
    "wof:name":"Parking Guard",
    "wof:placetype":"venue"
},
  "geometry": {"coordinates":[151.154663,-33.855663],"type":"Point"}
}