{
  "type": "Feature",
  "properties": {
    "addr:full":"Wairere Rd Booroolite VIC 3723",
    "addr:postcode":"3723",
    "addr:street":"Wairere Rd",
    "iso:country":"AU",
    "sg:address":"Wairere Rd",
    "sg:city":"Booroolite",
    "sg:classifiers":[
        {
            "category":"Farming",
            "subcategory":"Vineyard",
            "type":"Manufacturing & Wholesale Goods"
        }
    ],
    "sg:phone":"+61 3 5777 3447",
    "sg:postcode":"3723",
    "sg:province":"VIC",
    "sg:tags":[
        "winery"
    ],
    "wof:name":"Kinloch Wines Pty Ltd",
    "wof:placetype":"venue"
},
  "geometry": {"coordinates":[146.17344665499999,-37.1673049927],"type":"Point"}
}