{
  "type": "Feature",
  "properties": {
    "addr:full":"Tilston Ave Palmerston NT 0830",
    "addr:postcode":"nt 0830",
    "addr:street":"Tilston Ave",
    "iso:country":"AU",
    "sg:address":"Tilston Ave",
    "sg:city":"Palmerston",
    "sg:classifiers":[
        {
            "category":"Sports & Exercise",
            "subcategory":"Gym",
            "type":"Entertainment"
        }
    ],
    "sg:phone":"+61 8 8932 3474",
    "sg:postcode":"0830",
    "sg:province":"NT",
    "sg:tags":[
        "health",
        "fitness"
    ],
    "wof:name":"Palmerston Leisure Centre YMCA",
    "wof:placetype":"venue"
},
  "geometry": {"coordinates":[130.97503699999999,-12.496076],"type":"Point"}
}