{
  "type": "Feature",
  "properties": {
    "addr:full":"12 Laurette St Thornlands QLD 4164",
    "addr:housenumber":"12",
    "addr:postcode":"4164",
    "addr:street":"Laurette St",
    "iso:country":"AU",
    "sg:address":"12 Laurette St",
    "sg:city":"Thornlands",
    "sg:classifiers":[
        {
            "category":"Retail",
            "subcategory":"Repair Shop",
            "type":"Services"
        }
    ],
    "sg:phone":"+61 7 3286 9111",
    "sg:postcode":"4164",
    "sg:province":"QLD",
    "sg:tags":[
        "restorer",
        "repairer",
        "carpet"
    ],
    "wof:name":"Dry As A Bone Carpet Drying",
    "wof:placetype":"venue"
},
  "geometry": {"coordinates":[153.26405334500001,-27.5501823425],"type":"Point"}
}