{
  "type": "Feature",
  "properties": {
    "iso:country":"AU",
    "sg:address":"PO Box 295",
    "sg:city":"Sylvania",
    "sg:classifiers":[
        {
            "category":"Personal",
            "subcategory":"Nail Salon",
            "type":"Services"
        }
    ],
    "sg:phone":"+61 2 9544 8013",
    "sg:postcode":"2224",
    "sg:province":"NSW",
    "sg:tags":[
        "artificial"
    ],
    "wof:name":"Nail Makers Australia Pty Ltd The",
    "wof:placetype":"venue"
},
  "geometry": {"coordinates":[151.095993042,-34.0087585449],"type":"Point"}
}