{
  "type": "Feature",
  "properties": {
    "iso:country":"AU",
    "sg:address":"38 Francis St",
    "sg:city":"St Agnes",
    "sg:classifiers":[
        {
            "category":"Retail",
            "subcategory":"Repair Shop",
            "type":"Services"
        }
    ],
    "sg:phone":"+61 8 8265 6436",
    "sg:postcode":"5097",
    "sg:province":"SA",
    "sg:tags":[
        "machine",
        "repairs",
        "part",
        "dryer",
        "washing"
    ],
    "wof:name":"Complete Appliance Service",
    "wof:placetype":"venue"
},
  "geometry": {"coordinates":[138.713821411,-34.824092865],"type":"Point"}
}