{
  "type": "Feature",
  "properties": {
    "addr:full":"8 Arthurton Rd Northcote VIC 3070",
    "addr:housenumber":"8",
    "addr:postcode":"3070",
    "addr:street":"Arthurton Rd",
    "iso:country":"AU",
    "sg:address":"8 Arthurton Rd",
    "sg:city":"Northcote",
    "sg:classifiers":[
        {
            "category":"Personal",
            "subcategory":"Shoe Repair & Shine",
            "type":"Services"
        }
    ],
    "sg:phone":"+61 3 9481 7787",
    "sg:postcode":"3070",
    "sg:province":"VIC",
    "sg:tags":[
        "footwear"
    ],
    "wof:name":"Sensational Seconds Shoe Shop The",
    "wof:placetype":"venue"
},
  "geometry": {"coordinates":[144.997894,-37.769035],"type":"Point"}
}