{
  "type": "Feature",
  "properties": {
    "addr:full":"115 Main St Peterborough SA 5422",
    "addr:housenumber":"115",
    "addr:postcode":"5422",
    "addr:street":"Main St",
    "iso:country":"AU",
    "sg:address":"115 Main St",
    "sg:city":"Peterborough",
    "sg:classifiers":[
        {
            "category":"Retail",
            "subcategory":"Auto Repair",
            "type":"Services"
        }
    ],
    "sg:phone":"+61 8 8651 3123",
    "sg:postcode":"5422",
    "sg:province":"SA",
    "sg:tags":[
        "repairer",
        "motor",
        "engineer"
    ],
    "wof:name":"Repco Auto Repair",
    "wof:placetype":"venue"
},
  "geometry": {"coordinates":[138.83972168,-32.9729919434],"type":"Point"}
}