{
  "type": "Feature",
  "properties": {
    "addr:full":"25 Fromelles Ave Seaforth NSW 2092",
    "addr:housenumber":"25",
    "addr:postcode":"2092",
    "addr:street":"Fromelles Ave",
    "iso:country":"AU",
    "sg:address":"25 Fromelles Ave",
    "sg:city":"Seaforth",
    "sg:classifiers":[
        {
            "category":"Social Services",
            "subcategory":"Child Care",
            "type":"Services"
        }
    ],
    "sg:phone":"+61 2 9949 5008",
    "sg:postcode":"2092",
    "sg:province":"NSW",
    "wof:name":"Jacaranda Creative Play Centre",
    "wof:placetype":"venue"
},
  "geometry": {"coordinates":[151.24281310999999,-33.7897987366],"type":"Point"}
}