{
  "type": "Feature",
  "properties": {
    "addr:full":"6-8a Inglewood Drv Thomastown VIC 3074",
    "addr:housenumber":"6-8a",
    "addr:postcode":"3074",
    "addr:street":"Inglewood Drv",
    "iso:country":"AU",
    "sg:address":"6-8a Inglewood Drv",
    "sg:city":"Thomastown",
    "sg:classifiers":[
        {
            "category":"Wholesale",
            "subcategory":"Furniture",
            "type":"Manufacturing & Wholesale Goods"
        }
    ],
    "sg:phone":"+61 3 9464 4487",
    "sg:postcode":"3074",
    "sg:province":"VIC",
    "sg:tags":[
        "wholesaler",
        "mfrs"
    ],
    "wof:name":"Comfort Plus Sofas Pty Ltd",
    "wof:placetype":"venue"
},
  "geometry": {"coordinates":[145.032348633,-37.6895904541],"type":"Point"}
}