{
  "type": "Feature",
  "properties": {
    "addr:full":"80 Latrobe Rd Morwell VIC 3840",
    "addr:housenumber":"80",
    "addr:postcode":"3840",
    "addr:street":"Latrobe Rd",
    "iso:country":"AU",
    "sg:address":"80 Latrobe Rd",
    "sg:city":"Morwell",
    "sg:classifiers":[
        {
            "category":"Banks & Credit Unions",
            "subcategory":"Bank",
            "type":"Services"
        }
    ],
    "sg:phone":"+61 3 5134 3899",
    "sg:postcode":"3840",
    "sg:province":"VIC",
    "sg:tags":[
        "concrete",
        "reinforcement"
    ],
    "wof:name":"A.K.Z. Engineering Pty Ltd",
    "wof:placetype":"venue"
},
  "geometry": {"coordinates":[146.39581298799999,-38.2284507751],"type":"Point"}
}