{
  "type": "Feature",
  "properties": {
    "addr:full":"PO Box 4207 Edgeworth NSW 2285",
    "addr:postcode":"2285",
    "iso:country":"AU",
    "sg:address":"PO Box 4207",
    "sg:city":"Edgeworth",
    "sg:classifiers":[
        {
            "category":"Building & Trades",
            "subcategory":"Construction",
            "type":"Services"
        }
    ],
    "sg:phone":"+61 400 365 365",
    "sg:postcode":"2285",
    "sg:province":"NSW",
    "sg:tags":[
        "fencing",
        "contractor"
    ],
    "wof:name":"365 Temporary Fencing",
    "wof:placetype":"venue"
},
  "geometry": {"coordinates":[151.612884522,-32.9235305786],"type":"Point"}
}