{
  "type": "Feature",
  "properties": {
    "iso:country":"AU",
    "sg:address":"Goldsmith St",
    "sg:city":"Mackay",
    "sg:classifiers":[
        {
            "category":"Professional",
            "subcategory":"Art Services",
            "type":"Services"
        }
    ],
    "sg:phone":"+61 7 4957 5185",
    "sg:postcode":"4740",
    "sg:province":"QLD",
    "sg:tags":[
        "decorator",
        "painter"
    ],
    "wof:name":"Thommos Painting Service",
    "wof:placetype":"venue"
},
  "geometry": {"coordinates":[149.191254,-21.16564],"type":"Point"}
}