{
  "type": "Feature",
  "properties": {
    "iso:country":"AU",
    "sg:address":"44 Branson St",
    "sg:city":"Dunlop",
    "sg:classifiers":[
        {
            "category":"Home & Garden",
            "subcategory":"Carpets & Floor Coverings",
            "type":"Retail Goods"
        }
    ],
    "sg:phone":"+61 2 6259 9596",
    "sg:postcode":"2615",
    "sg:province":"ACT",
    "sg:tags":[
        "double",
        "window",
        "glazed"
    ],
    "wof:name":"Q Projects Pty Ltd",
    "wof:placetype":"venue"
},
  "geometry": {"coordinates":[149.029220581,-35.1879043579],"type":"Point"}
}