{
  "type": "Feature",
  "properties": {
    "addr:full":"22 Bell St Chinchilla QLD 4413",
    "addr:housenumber":"22",
    "addr:postcode":"4413",
    "addr:street":"Bell St",
    "iso:country":"AU",
    "sg:address":"22 Bell St",
    "sg:city":"Chinchilla",
    "sg:classifiers":[
        {
            "category":"Shopping",
            "subcategory":"Crafts & Fabrics",
            "type":"Retail Goods"
        }
    ],
    "sg:phone":"+61 7 4669 1047",
    "sg:postcode":"4413",
    "sg:province":"QLD",
    "sg:tags":[
        "material",
        "dress"
    ],
    "wof:name":"Dizzi D Creations",
    "wof:placetype":"venue"
},
  "geometry": {"coordinates":[150.62754821799999,-26.7410411835],"type":"Point"}
}