{
  "type": "Feature",
  "properties": {
    "addr:full":"208 Morrison Rd Ryde NSW 2112",
    "addr:housenumber":"208",
    "addr:postcode":"2112",
    "addr:street":"Morrison Rd",
    "iso:country":"AU",
    "sg:address":"208 Morrison Rd",
    "sg:city":"Ryde",
    "sg:classifiers":[
        {
            "category":"Building & Trades",
            "subcategory":"Construction",
            "type":"Services"
        }
    ],
    "sg:phone":"+61 2 9809 3180",
    "sg:postcode":"2112",
    "sg:province":"NSW",
    "sg:tags":[
        "concrete",
        "contractor"
    ],
    "wof:name":"Gubert A Concrete & Building Maintenance Pty Ltd",
    "wof:placetype":"venue"
},
  "geometry": {"coordinates":[151.11033630399999,-33.8251075745],"type":"Point"}
}