{
  "type": "Feature",
  "properties": {
    "iso:country":"AU",
    "sg:address":"40 Radford (cnr Parer) Rd",
    "sg:city":"Reservoir",
    "sg:classifiers":[
        {
            "category":"Shopping",
            "subcategory":"Crafts & Fabrics",
            "type":"Retail Goods"
        }
    ],
    "sg:phone":"+61 3 9478 4294",
    "sg:postcode":"3073",
    "sg:province":"VIC",
    "sg:tags":[
        "synthetic",
        "canvas",
        "product"
    ],
    "wof:name":"O&#039;Briens Caravan Accessories",
    "wof:placetype":"venue"
},
  "geometry": {"coordinates":[144.98294067399999,-37.7093238831],"type":"Point"}
}