{
  "type": "Feature",
  "properties": {
    "iso:country":"AU",
    "sg:address":"Lot 6 Apprentice Drv",
    "sg:city":"Berkeley Vale",
    "sg:classifiers":[
        {
            "category":"Commercial Area",
            "type":"Public Place"
        }
    ],
    "sg:phone":"+61 2 4388 3266",
    "sg:postcode":"2261",
    "sg:province":"NSW",
    "sg:tags":[
        "heavy",
        "carrier"
    ],
    "wof:name":"Coastal Express",
    "wof:placetype":"venue"
},
  "geometry": {"coordinates":[151.42205799999999,-33.328636],"type":"Point"}
}