{
  "type": "Feature",
  "properties": {
    "addr:full":"24 Neville St Cockatoo VIC 3781",
    "addr:housenumber":"24",
    "addr:postcode":"3781",
    "addr:street":"Neville St",
    "iso:country":"AU",
    "sg:address":"24 Neville St",
    "sg:city":"Cockatoo",
    "sg:classifiers":[
        {
            "category":"Utilities",
            "subcategory":"Telephone",
            "type":"Services"
        }
    ],
    "sg:phone":"+61 3 5968 9580",
    "sg:postcode":"3781",
    "sg:province":"VIC",
    "sg:tags":[
        "installation",
        "system",
        "maintenance"
    ],
    "wof:name":"BudgetCom",
    "wof:placetype":"venue"
},
  "geometry": {"coordinates":[145.49061599999999,-37.939419],"type":"Point"}
}