{
  "type": "Feature",
  "properties": {
    "iso:country":"AU",
    "sg:address":"Suite 115 Shenton Ave",
    "sg:city":"Joondalup",
    "sg:classifiers":[
        {
            "category":"Health Services",
            "subcategory":"Doctor",
            "type":"Services"
        }
    ],
    "sg:phone":"+61 8 9400 9628",
    "sg:postcode":"6027",
    "sg:province":"WA",
    "sg:tags":[
        "medical",
        "practitioner"
    ],
    "wof:name":"Mr Geoff Cooper",
    "wof:placetype":"venue"
},
  "geometry": {"coordinates":[115.764961243,-31.7391014099],"type":"Point"}
}