{
  "type": "Feature",
  "properties": {
    "addr:full":"439 Main Rd Glendale NSW 2285",
    "addr:housenumber":"439",
    "addr:postcode":"2285",
    "addr:street":"Main Rd",
    "iso:country":"AU",
    "sg:address":"439 Main Rd",
    "sg:city":"Glendale",
    "sg:classifiers":[
        {
            "category":"Retail",
            "subcategory":"Driving School",
            "type":"Services"
        }
    ],
    "sg:phone":"+61 2 4954 5373",
    "sg:postcode":"2285",
    "sg:province":"NSW",
    "wof:name":"Ezy-Learn Driving School",
    "wof:placetype":"venue"
},
  "geometry": {"coordinates":[151.65231323200001,-32.9315032959],"type":"Point"}
}