{
  "type": "Feature",
  "properties": {
    "addr:full":"57B Patrick St Hobart TAS 7000",
    "addr:housenumber":"57b",
    "addr:postcode":"7000",
    "addr:street":"Patrick St",
    "iso:country":"AU",
    "sg:address":"57B Patrick St",
    "sg:city":"Hobart",
    "sg:classifiers":[
        {
            "category":"Professional",
            "subcategory":"Printing & Photocopies",
            "type":"Services"
        }
    ],
    "sg:phone":"+61 3 6234 2627",
    "sg:postcode":"7000",
    "sg:province":"TAS",
    "sg:tags":[
        "embroidery"
    ],
    "wof:name":"L T Little Pty. Ltd.",
    "wof:placetype":"venue"
},
  "geometry": {"coordinates":[147.32139587399999,-42.8784828186],"type":"Point"}
}