{
  "type": "Feature",
  "properties": {
    "addr:full":"13 Conway St Dandenong VIC 3175",
    "addr:housenumber":"13",
    "addr:postcode":"3175",
    "addr:street":"Conway St",
    "iso:country":"AU",
    "sg:address":"13 Conway St",
    "sg:city":"Dandenong",
    "sg:classifiers":[
        {
            "category":"Travel",
            "subcategory":"Hostel",
            "type":"Entertainment"
        }
    ],
    "sg:phone":"+61 3 9793 5955",
    "sg:postcode":"3175",
    "sg:province":"VIC",
    "sg:tags":[
        "home"
    ],
    "wof:name":"St John Of Kronstadt Russian Welfare Society",
    "wof:placetype":"venue"
},
  "geometry": {"coordinates":[145.20289611800001,-37.9967689514],"type":"Point"}
}