{
  "type": "Feature",
  "properties": {
    "iso:country":"AU",
    "sg:address":"10 Barter St",
    "sg:city":"Gympie",
    "sg:classifiers":[
        {
            "category":"Retail",
            "subcategory":"Auto Repair",
            "type":"Services"
        }
    ],
    "sg:phone":"+61 7 5482 4058",
    "sg:postcode":"4570",
    "sg:province":"QLD",
    "sg:tags":[
        "repairer",
        "motor",
        "engineer"
    ],
    "wof:name":"Georges Radiator & Auto Repairs Gympie",
    "wof:placetype":"venue"
},
  "geometry": {"coordinates":[152.65823364299999,-26.1905593872],"type":"Point"}
}