{
  "type": "Feature",
  "properties": {
    "iso:country":"AU",
    "sg:address":"Shop 131 Westfield Centre Bunnerong Rd",
    "sg:city":"Pagewood",
    "sg:classifiers":[
        {
            "category":"Health Services",
            "subcategory":"Medical Lab",
            "type":"Services"
        }
    ],
    "sg:phone":"+61 2 9314 3348",
    "sg:postcode":"2035",
    "sg:province":"NSW",
    "sg:tags":[
        "laboratory",
        "pathology"
    ],
    "wof:name":"Australian Diagnostic Laboratories Pty Ltd",
    "wof:placetype":"venue"
},
  "geometry": {"coordinates":[151.22682189899999,-33.9439659119],"type":"Point"}
}