{
  "type": "Feature",
  "properties": {
    "addr:full":"6 Marungi St Shepparton VIC 3630",
    "addr:housenumber":"6",
    "addr:postcode":"3630",
    "addr:street":"Marungi St",
    "iso:country":"AU",
    "sg:address":"6 Marungi St",
    "sg:city":"Shepparton",
    "sg:classifiers":[
        {
            "category":"Health Services",
            "subcategory":"Doctor",
            "type":"Services"
        }
    ],
    "sg:phone":"+61 3 5821 8641",
    "sg:postcode":"3630",
    "sg:province":"VIC",
    "sg:tags":[
        "medical",
        "practitioner"
    ],
    "wof:name":"Chew David",
    "wof:placetype":"venue"
},
  "geometry": {"coordinates":[145.39764404300001,-36.374080658],"type":"Point"}
}