{
  "type": "Feature",
  "properties": {
    "iso:country":"AU",
    "sg:address":"15- 21 Breaker St",
    "sg:city":"Main Beach",
    "sg:classifiers":[
        {
            "category":"Travel",
            "subcategory":"Hotels & Motels",
            "type":"Entertainment"
        }
    ],
    "sg:phone":"+61 7 5552 6200",
    "sg:postcode":"4217",
    "sg:province":"QLD",
    "sg:tags":[
        "accommodation"
    ],
    "wof:name":"The Crest Apartments",
    "wof:placetype":"venue"
},
  "geometry": {"coordinates":[153.42672729500001,-27.9814090729],"type":"Point"}
}