{
  "type": "Feature",
  "properties": {
    "iso:country":"AU",
    "sg:address":"PO Box 503, 379",
    "sg:city":"Raglan St, Sale",
    "sg:classifiers":[
        {
            "category":"Utilities",
            "subcategory":"Electric",
            "type":"Services"
        }
    ],
    "sg:phone":"+61 3 5144 3053",
    "sg:postcode":"3850",
    "sg:province":"VIC",
    "sg:tags":[
        "electrical",
        "contractor"
    ],
    "wof:name":"Civil & Electrical Power Pty Ltd",
    "wof:placetype":"venue"
},
  "geometry": {"coordinates":[147.094650269,-38.1014328003],"type":"Point"}
}