{
  "type": "Feature",
  "properties": {
    "iso:country":"AU",
    "sg:address":"12 York Rd",
    "sg:city":"Northam",
    "sg:classifiers":[
        {
            "category":"Home & Garden",
            "subcategory":"Carpets & Floor Coverings",
            "type":"Retail Goods"
        }
    ],
    "sg:phone":"+61 8 9622 7747",
    "sg:postcode":"6401",
    "sg:province":"WA",
    "sg:tags":[
        "wood"
    ],
    "wof:name":"Wallis Timber Floors",
    "wof:placetype":"venue"
},
  "geometry": {"coordinates":[116.689949036,-31.6511592865],"type":"Point"}
}