{
  "type": "Feature",
  "properties": {
    "addr:full":"4 MacIntosh Drv Cannonvale QLD 4802",
    "addr:housenumber":"4",
    "addr:postcode":"4802",
    "addr:street":"Macintosh Drv",
    "iso:country":"AU",
    "sg:address":"4 MacIntosh Drv",
    "sg:city":"Cannonvale",
    "sg:classifiers":[
        {
            "category":"Shopping",
            "subcategory":"Bicycles & Sporting Goods",
            "type":"Retail Goods"
        }
    ],
    "sg:phone":"+61 7 4946 7859",
    "sg:postcode":"4802",
    "sg:province":"QLD",
    "sg:tags":[
        "chemical",
        "equipment",
        "pool",
        "swimming"
    ],
    "wof:name":"Whitsunday Pool Service",
    "wof:placetype":"venue"
},
  "geometry": {"coordinates":[148.68125915499999,-20.2853164673],"type":"Point"}
}