{
  "type": "Feature",
  "properties": {
    "addr:full":"87 Port Hacking Rd Sylvania NSW 2224",
    "addr:housenumber":"87",
    "addr:postcode":"2224",
    "addr:street":"Port Hacking Rd",
    "iso:country":"AU",
    "sg:address":"87 Port Hacking Rd",
    "sg:city":"Sylvania",
    "sg:classifiers":[
        {
            "category":"Building & Trades",
            "subcategory":"Construction",
            "type":"Services"
        }
    ],
    "sg:phone":"+61 412 964 795",
    "sg:postcode":"2224",
    "sg:province":"NSW",
    "sg:tags":[
        "waterproofing",
        "contractor"
    ],
    "wof:name":"The Ultimate Connection Pty Ltd",
    "wof:placetype":"venue"
},
  "geometry": {"coordinates":[151.10589599599999,-34.0161132812],"type":"Point"}
}