{
  "type": "Feature",
  "properties": {
    "addr:full":"1348 North East Rd Tea Tree Gully SA 5091",
    "addr:housenumber":"1348",
    "addr:postcode":"5091",
    "addr:street":"North East Rd Tea Tree",
    "iso:country":"AU",
    "sg:address":"1348 North East Rd",
    "sg:city":"Tea Tree Gully",
    "sg:classifiers":[
        {
            "category":"Banks & Credit Unions",
            "subcategory":"Investment Brokerage",
            "type":"Services"
        }
    ],
    "sg:phone":"+61 8 8395 5789",
    "sg:postcode":"5091",
    "sg:province":"SA",
    "sg:tags":[
        "management",
        "property"
    ],
    "wof:name":"Focus Property Management",
    "wof:placetype":"venue"
},
  "geometry": {"coordinates":[138.726959228,-34.8209075928],"type":"Point"}
}