{
  "type": "Feature",
  "properties": {
    "addr:full":"Level 1, 95 Tamar St Ballina NSW 2478",
    "addr:housenumber":"95",
    "addr:postcode":"2478",
    "addr:street":"Tamar St",
    "iso:country":"AU",
    "sg:address":"Level 1, 95 Tamar St",
    "sg:city":"Ballina",
    "sg:classifiers":[
        {
            "category":"Professional",
            "subcategory":"Accounting & Tax Preparation",
            "type":"Services"
        }
    ],
    "sg:phone":"+61 2 6686 2622",
    "sg:postcode":"2478",
    "sg:province":"NSW",
    "sg:tags":[
        "accountant",
        "auditor"
    ],
    "wof:name":"Marriott Bryan",
    "wof:placetype":"venue"
},
  "geometry": {"coordinates":[153.558761597,-28.8682003021],"type":"Point"}
}