{
  "type": "Feature",
  "properties": {
    "addr:full":"PMB 96 via Winnellie Winnellie NT 0820",
    "addr:postcode":"nt 0820",
    "addr:street":"Via Winnellie",
    "iso:country":"AU",
    "sg:address":"PMB 96 via Winnellie",
    "sg:city":"Winnellie",
    "sg:classifiers":[
        {
            "category":"Education",
            "subcategory":"School",
            "type":"Public Place"
        }
    ],
    "sg:phone":"+61 8 8978 3960",
    "sg:postcode":"0820",
    "sg:province":"NT",
    "sg:tags":[
        "state",
        "except",
        "nsw"
    ],
    "wof:name":"Milikapiti School",
    "wof:placetype":"venue"
},
  "geometry": {"coordinates":[130.89242553700001,-12.4266233444],"type":"Point"}
}