{
  "type": "Feature",
  "properties": {
    "iso:country":"AU",
    "sg:address":"Lot 21 St Andrews Rd",
    "sg:city":"Varroville",
    "sg:classifiers":[
        {
            "category":"Real Estate",
            "subcategory":"Architect",
            "type":"Services"
        }
    ],
    "sg:phone":"+61 417 247 324",
    "sg:postcode":"2566",
    "sg:province":"NSW",
    "wof:name":"Pearson - Smith & Associates Pty Ltd",
    "wof:placetype":"venue"
},
  "geometry": {"coordinates":[150.82383727999999,-34.0069236755],"type":"Point"}
}