{
  "type": "Feature",
  "properties": {
    "addr:full":"7 Eulalia St West Ryde NSW 2114",
    "addr:housenumber":"7",
    "addr:postcode":"2114",
    "addr:street":"Eulalia St",
    "iso:country":"AU",
    "sg:address":"7 Eulalia St",
    "sg:city":"West Ryde",
    "sg:classifiers":[
        {
            "category":"Education",
            "subcategory":"Special Training",
            "type":"Public Place"
        }
    ],
    "sg:phone":"+61 2 9804 1837",
    "sg:postcode":"2114",
    "sg:province":"NSW",
    "sg:tags":[
        "development"
    ],
    "wof:name":"Spirit Endeavours Pty Ltd",
    "wof:placetype":"venue"
},
  "geometry": {"coordinates":[151.07258605999999,-33.8055229187],"type":"Point"}
}