{
  "type": "Feature",
  "properties": {
    "iso:country":"AU",
    "sg:address":"120 Nicholson Pde",
    "sg:city":"Cronulla",
    "sg:classifiers":[
        {
            "category":"Education",
            "subcategory":"School",
            "type":"Public Place"
        }
    ],
    "sg:phone":"+61 2 9523 5397",
    "sg:postcode":"2230",
    "sg:province":"NSW",
    "wof:name":"Cronulla Pre-School Kindergarten Inc",
    "wof:placetype":"venue"
},
  "geometry": {"coordinates":[151.149124145,-34.0665168762],"type":"Point"}
}