{
  "type": "Feature",
  "properties": {
    "addr:full":"Sloane St Stawell VIC 3380",
    "addr:postcode":"3380",
    "addr:street":"Sloane St",
    "iso:country":"AU",
    "sg:address":"Sloane St",
    "sg:city":"Stawell",
    "sg:classifiers":[
        {
            "category":"Food & Beverages",
            "subcategory":"Groceries & Convenience Stores",
            "type":"Retail Goods"
        }
    ],
    "sg:phone":"+61 3 5358 1606",
    "sg:postcode":"3380",
    "sg:province":"VIC",
    "wof:name":"Parsons D & M",
    "wof:placetype":"venue"
},
  "geometry": {"coordinates":[142.77467346200001,-37.0660972595],"type":"Point"}
}