{
  "type": "Feature",
  "properties": {
    "addr:full":"L3 Shop 338 Greensborough Plaza Greensborough VIC 3088",
    "addr:housenumber":"338",
    "addr:postcode":"3088",
    "addr:street":"Greensborough Plaza",
    "iso:country":"AU",
    "sg:address":"L3 Shop 338 Greensborough Plaza",
    "sg:city":"Greensborough",
    "sg:classifiers":[
        {
            "category":"Shopping",
            "subcategory":"Shoes",
            "type":"Retail Goods"
        }
    ],
    "sg:phone":"+61 3 9434 7419",
    "sg:postcode":"3088",
    "sg:province":"VIC",
    "sg:tags":[
        "footwear"
    ],
    "wof:name":"Ghetto Sport & Street",
    "wof:placetype":"venue"
},
  "geometry": {"coordinates":[145.08198547399999,-37.7140045166],"type":"Point"}
}