{
  "type": "Feature",
  "properties": {
    "addr:full":"110 Spencer Rd Nerang QLD 4211",
    "addr:housenumber":"110",
    "addr:postcode":"4211",
    "addr:street":"Spencer Rd",
    "iso:country":"AU",
    "sg:address":"110 Spencer Rd",
    "sg:city":"Nerang",
    "sg:classifiers":[
        {
            "category":"Retail",
            "subcategory":"Auto Repair",
            "type":"Services"
        }
    ],
    "sg:phone":"+61 7 5596 6555",
    "sg:postcode":"4211",
    "sg:province":"QLD",
    "sg:tags":[
        "automotive",
        "air conditioning"
    ],
    "wof:name":"Auto Leaders Car Air Conditioning",
    "wof:placetype":"venue"
},
  "geometry": {"coordinates":[153.34548950199999,-28.0079898834],"type":"Point"}
}