{
  "type": "Feature",
  "properties": {
    "iso:country":"AU",
    "sg:address":"40-44 Christabel St",
    "sg:city":"Lawson",
    "sg:classifiers":[
        {
            "category":"Retail",
            "subcategory":"Auto Repair",
            "type":"Services"
        }
    ],
    "sg:phone":"+61 2 4759 1451",
    "sg:postcode":"2783",
    "sg:province":"NSW",
    "sg:tags":[
        "repairer",
        "motor",
        "engineer"
    ],
    "wof:name":"Lawson Car Care",
    "wof:placetype":"venue"
},
  "geometry": {"coordinates":[150.42898559599999,-33.7200012207],"type":"Point"}
}