{
  "type": "Feature",
  "properties": {
    "iso:country":"AU",
    "sg:address":"Hume Hwy",
    "sg:city":"Sutton Forest",
    "sg:classifiers":[
        {
            "category":"Fast Food",
            "type":"Food & Drink"
        }
    ],
    "sg:phone":"+61 2 4878 9399",
    "sg:postcode":"2577",
    "sg:province":"NSW",
    "sg:tags":[
        "away",
        "take"
    ],
    "wof:name":"McDonald's Family Restaurants",
    "wof:placetype":"venue"
},
  "geometry": {"coordinates":[150.24974060100001,-34.5865974426],"type":"Point"}
}