{
  "type": "Feature",
  "properties": {
    "addr:full":"Level 5, Suite 501, 88 Phillip St Parramatta NSW 2150",
    "addr:housenumber":"88",
    "addr:postcode":"2150",
    "addr:street":"Phillip St",
    "iso:country":"AU",
    "sg:address":"Level 5, Suite 501, 88 Phillip St",
    "sg:city":"Parramatta",
    "sg:classifiers":[
        {
            "category":"Professional",
            "subcategory":"Employment Agencies",
            "type":"Services"
        }
    ],
    "sg:phone":"+61 2 9865 8333",
    "sg:postcode":"2150",
    "sg:province":"NSW",
    "wof:name":"Kelly Engineering Resources",
    "wof:placetype":"venue"
},
  "geometry": {"coordinates":[150.964767456,-33.8522377014],"type":"Point"}
}