{
  "type": "Feature",
  "properties": {
    "addr:full":"51 Duck Creek Rd Murdunna TAS 7178",
    "addr:housenumber":"51",
    "addr:postcode":"7178",
    "addr:street":"Duck Creek Rd",
    "iso:country":"AU",
    "sg:address":"51 Duck Creek Rd",
    "sg:city":"Murdunna",
    "sg:classifiers":[
        {
            "category":"Autos & Motor Vehicles",
            "subcategory":"Boat Sales",
            "type":"Retail Goods"
        }
    ],
    "sg:phone":"+61 3 6253 5117",
    "sg:postcode":"7178",
    "sg:province":"TAS",
    "sg:tags":[
        "equipment",
        "yacht"
    ],
    "wof:name":"Mariner Aluminium",
    "wof:placetype":"venue"
},
  "geometry": {"coordinates":[147.86819457999999,-42.9555206299],"type":"Point"}
}