{
  "type": "Feature",
  "properties": {
    "addr:full":"Unit 2/ 68 Blanck St Ormeau QLD 4208",
    "addr:housenumber":"68",
    "addr:postcode":"4208",
    "addr:street":"Blanck St",
    "iso:country":"AU",
    "sg:address":"Unit 2/ 68 Blanck St",
    "sg:city":"Ormeau",
    "sg:classifiers":[
        {
            "category":"Communications",
            "type":"Services"
        }
    ],
    "sg:phone":"+61 1300 889 096",
    "sg:postcode":"4208",
    "sg:province":"QLD",
    "sg:tags":[
        "data"
    ],
    "wof:name":"Media Control Services Pty Ltd",
    "wof:placetype":"venue"
},
  "geometry": {"coordinates":[153.25581359899999,-27.7824382782],"type":"Point"}
}