{
  "type": "Feature",
  "properties": {
    "iso:country":"AU",
    "sg:address":"88 Blackwood Ave",
    "sg:city":"Augusta",
    "sg:classifiers":[
        {
            "category":"Travel",
            "subcategory":"Hotels & Motels",
            "type":"Entertainment"
        }
    ],
    "sg:phone":"+61 8 9758 1290",
    "sg:postcode":"6290",
    "sg:province":"WA",
    "wof:name":"Augusta Baywatch Manor",
    "wof:placetype":"venue"
},
  "geometry": {"coordinates":[115.158462524,-34.3136253357],"type":"Point"}
}