{
  "type": "Feature",
  "properties": {
    "iso:country":"AU",
    "sg:address":"1 Fauna Ave",
    "sg:city":"Dingley Village",
    "sg:classifiers":[
        {
            "category":"Utilities",
            "subcategory":"Electric",
            "type":"Services"
        }
    ],
    "sg:phone":"+61 3 9558 1322",
    "sg:postcode":"3172",
    "sg:province":"VIC",
    "sg:tags":[
        "electrical",
        "contractor"
    ],
    "wof:name":"Brian Benton",
    "wof:placetype":"venue"
},
  "geometry": {"coordinates":[145.14140319800001,-37.9876213074],"type":"Point"}
}