{
  "type": "Feature",
  "properties": {
    "iso:country":"AU",
    "sg:address":"47 Sturt St",
    "sg:city":"Echuca",
    "sg:classifiers":[
        {
            "category":"Home & Garden",
            "subcategory":"Garden Supply",
            "type":"Retail Goods"
        }
    ],
    "sg:phone":"+61 3 5480 6665",
    "sg:postcode":"3564",
    "sg:province":"VIC",
    "sg:tags":[
        "equipment"
    ],
    "wof:name":"Echuca Mini Mix & Garden Supplies Pty Ltd",
    "wof:placetype":"venue"
},
  "geometry": {"coordinates":[144.754837036,-36.1371917725],"type":"Point"}
}