{
  "type": "Feature",
  "properties": {
    "addr:full":"Shp8/ 50-54 Prince St Grafton NSW 2460",
    "addr:housenumber":"50-54",
    "addr:postcode":"2460",
    "addr:street":"Prince St",
    "iso:country":"AU",
    "sg:address":"Shp8/ 50-54 Prince St",
    "sg:city":"Grafton",
    "sg:classifiers":[
        {
            "category":"Professional",
            "subcategory":"Advertising",
            "type":"Services"
        }
    ],
    "sg:phone":"+61 2 6642 2929",
    "sg:postcode":"2460",
    "sg:province":"NSW",
    "sg:tags":[
        "balloon",
        "novelty"
    ],
    "wof:name":"Grafton Pink Petals Florist",
    "wof:placetype":"venue"
},
  "geometry": {"coordinates":[152.93392944300001,-29.6907100677],"type":"Point"}
}