{
  "type": "Feature",
  "properties": {
    "addr:full":"Buffalo Rd Gladesville NSW 2111",
    "addr:postcode":"2111",
    "addr:street":"Buffalo Rd",
    "iso:country":"AU",
    "sg:address":"Buffalo Rd",
    "sg:city":"Gladesville",
    "sg:classifiers":[
        {
            "category":"Utilities",
            "subcategory":"Electric",
            "type":"Services"
        }
    ],
    "sg:phone":"+61 1800 809 977",
    "sg:postcode":"2111",
    "sg:province":"NSW",
    "sg:tags":[
        "electrical",
        "contractor"
    ],
    "wof:name":"Bell Contracting Co Pty Ltd",
    "wof:placetype":"venue"
},
  "geometry": {"coordinates":[151.12637329099999,-33.8210067749],"type":"Point"}
}