{
  "type": "Feature",
  "properties": {
    "addr:full":"172 Eastfield Rd Croydon VIC 3136",
    "addr:housenumber":"172",
    "addr:postcode":"3136",
    "addr:street":"Eastfield Rd",
    "iso:country":"AU",
    "sg:address":"172 Eastfield Rd",
    "sg:city":"Croydon",
    "sg:classifiers":[
        {
            "category":"Health Services",
            "subcategory":"Health Practitioner",
            "type":"Services"
        }
    ],
    "sg:phone":"+61 417 386 242",
    "sg:postcode":"3136",
    "sg:province":"VIC",
    "sg:tags":[
        "psychologist"
    ],
    "wof:name":"Georgiou Elizabeth",
    "wof:placetype":"venue"
},
  "geometry": {"coordinates":[145.28341674800001,-37.8129425049],"type":"Point"}
}