{
  "type": "Feature",
  "properties": {
    "iso:country":"AU",
    "sg:address":"9/ 435 King William St",
    "sg:city":"Adelaide",
    "sg:classifiers":[
        {
            "category":"Airline",
            "type":"Transportation"
        }
    ],
    "sg:phone":"+61 1800 105 503",
    "sg:postcode":"5000",
    "sg:province":"SA",
    "sg:tags":[
        "aircraft",
        "rental",
        "charter"
    ],
    "wof:name":"National Jet",
    "wof:placetype":"venue"
},
  "geometry": {"coordinates":[138.60067749000001,-34.9345703125],"type":"Point"}
}