{
  "type": "Feature",
  "properties": {
    "iso:country":"AU",
    "sg:address":"20 Atbara Rd",
    "sg:city":"Kalgoorlie",
    "sg:classifiers":[
        {
            "category":"Retail",
            "subcategory":"Storage",
            "type":"Services"
        }
    ],
    "sg:phone":"+61 8 9021 3683",
    "sg:postcode":"6430",
    "sg:province":"WA",
    "sg:tags":[
        "removal",
        "furniture"
    ],
    "wof:name":"Wridgways",
    "wof:placetype":"venue"
},
  "geometry": {"coordinates":[121.443763733,-30.7756824493],"type":"Point"}
}