{
  "type": "Feature",
  "properties": {
    "iso:country":"AU",
    "sg:address":"GPO Box 5131",
    "sg:city":"Sydney",
    "sg:classifiers":[
        {
            "category":"Retail",
            "subcategory":"Event Space",
            "type":"Services"
        }
    ],
    "sg:phone":"+61 2 9298 3777",
    "sg:postcode":"2001",
    "sg:province":"NSW",
    "sg:tags":[
        "venue",
        "reception",
        "wedding"
    ],
    "wof:name":"Australian National Maritime Museum",
    "wof:placetype":"venue"
},
  "geometry": {"coordinates":[151.207107544,-33.8671417236],"type":"Point"}
}