{
  "type": "Feature",
  "properties": {
    "addr:full":"Wewak St Trinity Beach QLD 4879",
    "addr:postcode":"4879",
    "addr:street":"St",
    "iso:country":"AU",
    "sg:address":"Wewak St",
    "sg:city":"Trinity Beach",
    "sg:classifiers":[
        {
            "category":"Education",
            "subcategory":"School",
            "type":"Public Place"
        }
    ],
    "sg:phone":"+61 7 4057 1444",
    "sg:postcode":"4879",
    "sg:province":"QLD",
    "sg:tags":[
        "state",
        "except",
        "nsw"
    ],
    "wof:name":"Trinity Beach Primary School",
    "wof:placetype":"venue"
},
  "geometry": {"coordinates":[145.689376831,-16.7948932648],"type":"Point"}
}