{
  "type": "Feature",
  "properties": {
    "addr:full":"PO Box 1289 North Haven SA 5018",
    "addr:postcode":"5018",
    "iso:country":"AU",
    "sg:address":"PO Box 1289",
    "sg:city":"North Haven",
    "sg:classifiers":[
        {
            "category":"Manufacturing",
            "subcategory":"Watercraft",
            "type":"Manufacturing & Wholesale Goods"
        }
    ],
    "sg:phone":"+61 8 8248 2966",
    "sg:postcode":"5018",
    "sg:province":"SA",
    "sg:tags":[
        "sail",
        "marine",
        "maker"
    ],
    "wof:name":"Barry Hugh Quin Marine",
    "wof:placetype":"venue"
},
  "geometry": {"coordinates":[138.49134826700001,-34.7935714722],"type":"Point"}
}