{
  "type": "Feature",
  "properties": {
    "addr:full":"172 Queen St Campbelltown NSW 2560",
    "addr:housenumber":"172",
    "addr:postcode":"2560",
    "addr:street":"Queen St",
    "iso:country":"AU",
    "sg:address":"172 Queen St",
    "sg:city":"Campbelltown",
    "sg:classifiers":[
        {
            "category":"Shopping",
            "subcategory":"Clothing, Apparel, & Fashions",
            "type":"Retail Goods"
        }
    ],
    "sg:phone":"+61 2 4620 0413",
    "sg:postcode":"2560",
    "sg:province":"NSW",
    "sg:tags":[
        "lady",
        "wear"
    ],
    "wof:name":"Luciana Collection",
    "wof:placetype":"venue"
},
  "geometry": {"coordinates":[150.814453125,-34.0666809082],"type":"Point"}
}