{
  "type": "Feature",
  "properties": {
    "addr:full":"44 Watermoor Ave Kilsyth VIC 3137",
    "addr:housenumber":"44",
    "addr:postcode":"3137",
    "addr:street":"Watermoor Ave",
    "iso:country":"AU",
    "sg:address":"44 Watermoor Ave",
    "sg:city":"Kilsyth",
    "sg:classifiers":[
        {
            "category":"Professional",
            "subcategory":"Printing & Photocopies",
            "type":"Services"
        }
    ],
    "sg:phone":"+61 3 9762 6160",
    "sg:postcode":"3137",
    "sg:province":"VIC",
    "sg:tags":[
        "publishing",
        "desktop"
    ],
    "wof:name":"Grand Graphix Pty Ltd",
    "wof:placetype":"venue"
},
  "geometry": {"coordinates":[145.304077148,-37.8375434875],"type":"Point"}
}