{
  "type": "Feature",
  "properties": {
    "iso:country":"AU",
    "sg:address":"37 Turf St",
    "sg:city":"Grafton",
    "sg:classifiers":[
        {
            "category":"Arena",
            "subcategory":"Sports Club",
            "type":"Entertainment"
        }
    ],
    "sg:phone":"+61 2 6642 2811",
    "sg:postcode":"2460",
    "sg:province":"NSW",
    "sg:tags":[
        "organisation",
        "sporting"
    ],
    "wof:name":"NSW Country Racing Council Grafton Regional Office",
    "wof:placetype":"venue"
},
  "geometry": {"coordinates":[152.926071167,-29.6838283539],"type":"Point"}
}