{
  "type": "Feature",
  "properties": {
    "addr:full":"17 Clark St Nedlands WA 6009",
    "addr:housenumber":"17",
    "addr:postcode":"6009",
    "addr:street":"Clark St",
    "iso:country":"AU",
    "sg:address":"17 Clark St",
    "sg:city":"Nedlands",
    "sg:classifiers":[
        {
            "category":"Real Estate",
            "subcategory":"Surveying",
            "type":"Services"
        }
    ],
    "sg:phone":"+61 8 9386 1130",
    "sg:postcode":"6009",
    "sg:province":"WA",
    "sg:tags":[
        "surveyor",
        "land"
    ],
    "wof:name":"McMahon Kevin",
    "wof:placetype":"venue"
},
  "geometry": {"coordinates":[115.813812,-31.979237],"type":"Point"}
}