{
  "type": "Feature",
  "properties": {
    "iso:country":"AU",
    "sg:address":"Dederang Rd",
    "sg:city":"Yackandandah",
    "sg:classifiers":[
        {
            "category":"Farming",
            "subcategory":"Farm",
            "type":"Manufacturing & Wholesale Goods"
        }
    ],
    "sg:phone":"+61 2 6027 1374",
    "sg:postcode":"3749",
    "sg:province":"VIC",
    "sg:tags":[
        "farmer"
    ],
    "wof:name":"Clark T J",
    "wof:placetype":"venue"
},
  "geometry": {"coordinates":[146.84007299999999,-36.314724],"type":"Point"}
}