{
  "type": "Feature",
  "properties": {
    "addr:full":"Springvale Eye Clinic, 2/879 Springvale Rd Mulgrave VIC 3170",
    "addr:housenumber":"2 / 879",
    "addr:postcode":"3170",
    "addr:street":"Springvale Rd",
    "iso:country":"AU",
    "sg:address":"Springvale Eye Clinic, 2/879 Springvale Rd",
    "sg:city":"Mulgrave",
    "sg:classifiers":[
        {
            "category":"Health Services",
            "subcategory":"Doctor",
            "type":"Services"
        }
    ],
    "sg:phone":"+61 3 9546 4533",
    "sg:postcode":"3170",
    "sg:province":"VIC",
    "sg:tags":[
        "medical",
        "practitioner"
    ],
    "wof:name":"Su Charles Dr",
    "wof:placetype":"venue"
},
  "geometry": {"coordinates":[145.156173706,-37.9303894043],"type":"Point"}
}