{
  "type": "Feature",
  "properties": {
    "iso:country":"AU",
    "sg:address":"158 Victoria St",
    "sg:city":"Richmond",
    "sg:classifiers":[
        {
            "category":"Food & Beverages",
            "subcategory":"Meat & Fish",
            "type":"Retail Goods"
        }
    ],
    "sg:phone":"+61 3 9428 1590",
    "sg:postcode":"3121",
    "sg:province":"VIC",
    "sg:tags":[
        "seafood"
    ],
    "wof:name":"Hai Xuong Fresh Fish",
    "wof:placetype":"venue"
},
  "geometry": {"coordinates":[144.996749878,-37.8102722168],"type":"Point"}
}