{
  "type": "Feature",
  "properties": {
    "addr:full":"682 Axedale Goornong Rd Fosterville VIC 3557",
    "addr:housenumber":"682",
    "addr:postcode":"3557",
    "addr:street":"Axedale Goornong Rd",
    "iso:country":"AU",
    "sg:address":"682 Axedale Goornong Rd",
    "sg:city":"Fosterville",
    "sg:classifiers":[
        {
            "category":"Farming",
            "subcategory":"Vineyard",
            "type":"Manufacturing & Wholesale Goods"
        }
    ],
    "sg:phone":"+61 3 5439 7444",
    "sg:postcode":"3557",
    "sg:province":"VIC",
    "sg:tags":[
        "winery"
    ],
    "wof:name":"Wirrawilla Estate Limited",
    "wof:placetype":"venue"
},
  "geometry": {"coordinates":[144.514892578,-36.7006988525],"type":"Point"}
}