{
  "type": "Feature",
  "properties": {
    "iso:country":"AU",
    "sg:address":"110 Morayfield Rd",
    "sg:city":"Morayfield",
    "sg:classifiers":[
        {
            "category":"Professional",
            "subcategory":"Computer Services",
            "type":"Services"
        }
    ],
    "sg:phone":"+61 7 5499 0822",
    "sg:postcode":"4506",
    "sg:province":"QLD",
    "sg:tags":[
        "consultant",
        "system"
    ],
    "wof:name":"Micro-ed Pty Ltd",
    "wof:placetype":"venue"
},
  "geometry": {"coordinates":[152.950317383,-27.110742569],"type":"Point"}
}