{
  "type": "Feature",
  "properties": {
    "addr:full":"98 Albion Rd Box Hill VIC 3128",
    "addr:housenumber":"98",
    "addr:postcode":"3128",
    "addr:street":"Albion Rd",
    "iso:country":"AU",
    "sg:address":"98 Albion Rd",
    "sg:city":"Box Hill",
    "sg:classifiers":[
        {
            "category":"Farming",
            "subcategory":"Livestock Farm",
            "type":"Manufacturing & Wholesale Goods"
        }
    ],
    "sg:phone":"+61 3 9890 3771",
    "sg:postcode":"3128",
    "sg:province":"VIC",
    "sg:tags":[
        "school",
        "theological"
    ],
    "wof:name":"Yarra Theological Union",
    "wof:placetype":"venue"
},
  "geometry": {"coordinates":[145.133468628,-37.8255805969],"type":"Point"}
}