{
  "type": "Feature",
  "properties": {
    "addr:full":"82a Hakone Rd Warnervale NSW 2259",
    "addr:housenumber":"82a",
    "addr:postcode":"2259",
    "addr:street":"Hakone Rd",
    "iso:country":"AU",
    "sg:address":"82a Hakone Rd",
    "sg:city":"Warnervale",
    "sg:classifiers":[
        {
            "category":"Wholesale",
            "subcategory":"Plants",
            "type":"Manufacturing & Wholesale Goods"
        }
    ],
    "sg:phone":"+61 2 4392 4155",
    "sg:postcode":"2259",
    "sg:province":"NSW",
    "sg:tags":[
        "florist"
    ],
    "wof:name":"Tyrade",
    "wof:placetype":"venue"
},
  "geometry": {"coordinates":[151.483917236,-33.2382087708],"type":"Point"}
}