{
  "type": "Feature",
  "properties": {
    "addr:full":"485 Moorabool St South Geelong VIC 3220",
    "addr:housenumber":"485",
    "addr:postcode":"3220",
    "addr:street":"Moorabool St",
    "iso:country":"AU",
    "sg:address":"485 Moorabool St",
    "sg:city":"South Geelong",
    "sg:classifiers":[
        {
            "category":"Fast Food",
            "type":"Food & Drink"
        }
    ],
    "sg:phone":"+61 3 5222 3148",
    "sg:postcode":"3220",
    "sg:province":"VIC",
    "sg:tags":[
        "away",
        "take"
    ],
    "wof:name":"Lorm Thai Restaurant",
    "wof:placetype":"venue"
},
  "geometry": {"coordinates":[144.354095,-38.162109],"type":"Point"}
}