{
  "type": "Feature",
  "properties": {
    "addr:full":"Cnr Eastwood & Sharwood Sts Ballarat VIC 3350",
    "addr:postcode":"3350",
    "addr:street":"Cnr;Sts",
    "iso:country":"AU",
    "sg:address":"Cnr Eastwood & Sharwood Sts",
    "sg:city":"Ballarat",
    "sg:classifiers":[
        {
            "category":"Food & Beverages",
            "subcategory":"Supermarket",
            "type":"Retail Goods"
        }
    ],
    "sg:phone":"+61 3 5331 7466",
    "sg:postcode":"3350",
    "sg:province":"VIC",
    "sg:tags":[
        "grocery",
        "store"
    ],
    "wof:name":"Safeway",
    "wof:placetype":"venue"
},
  "geometry": {"coordinates":[143.860794,-37.564575],"type":"Point"}
}