{
  "type": "Feature",
  "properties": {
    "addr:full":"245D Musgrave St North Rockhampton QLD 4701",
    "addr:housenumber":"245d",
    "addr:postcode":"4701",
    "addr:street":"Musgrave St North",
    "iso:country":"AU",
    "sg:address":"245D Musgrave St",
    "sg:city":"North Rockhampton",
    "sg:classifiers":[
        {
            "category":"Shopping",
            "subcategory":"Clothing, Apparel, & Fashions",
            "type":"Retail Goods"
        }
    ],
    "sg:phone":"+61 7 4922 3555",
    "sg:postcode":"4701",
    "sg:province":"QLD",
    "sg:tags":[
        "hire",
        "men's",
        "wear",
        "formal"
    ],
    "wof:name":"Bridal Affair",
    "wof:placetype":"venue"
},
  "geometry": {"coordinates":[150.52328491200001,-23.357793808],"type":"Point"}
}