{
  "type": "Feature",
  "properties": {
    "addr:full":"31 Darling St Abbotsbury NSW 2176",
    "addr:housenumber":"31",
    "addr:postcode":"2176",
    "addr:street":"Darling St",
    "iso:country":"AU",
    "sg:address":"31 Darling St",
    "sg:city":"Abbotsbury",
    "sg:classifiers":[
        {
            "category":"Park",
            "subcategory":"County",
            "type":"Public Place"
        }
    ],
    "sg:phone":"+61 2 9823 3222",
    "sg:postcode":"2176",
    "sg:province":"NSW",
    "sg:tags":[
        "sanctuary",
        "zoos",
        "animal"
    ],
    "wof:name":"Fairfield City Farm",
    "wof:placetype":"venue"
},
  "geometry": {"coordinates":[150.86190795900001,-33.8682518005],"type":"Point"}
}