{
  "type": "Feature",
  "properties": {
    "iso:country":"AU",
    "sg:address":"86 Murray St",
    "sg:city":"Hobart",
    "sg:classifiers":[
        {
            "category":"Cinema",
            "subcategory":"Movie Theater",
            "type":"Entertainment"
        }
    ],
    "sg:phone":"+61 3 6234 5818",
    "sg:postcode":"7000",
    "sg:province":"TAS",
    "wof:name":"The Star Cinema",
    "wof:placetype":"venue"
},
  "geometry": {"coordinates":[147.32612609899999,-42.8829994202],"type":"Point"}
}