{
  "type": "Feature",
  "properties": {
    "addr:full":"Cnr Royal St & Sovereign Cl East Perth WA 6004",
    "addr:postcode":"6004",
    "addr:street":"Royal St & Sovereign Cl East",
    "iso:country":"AU",
    "sg:address":"Cnr Royal St & Sovereign Cl",
    "sg:city":"East Perth",
    "sg:classifiers":[
        {
            "category":"Food & Beverages",
            "subcategory":"Liquor & Beverages",
            "type":"Retail Goods"
        }
    ],
    "sg:phone":"+61 8 9221 0008",
    "sg:postcode":"6004",
    "sg:province":"WA",
    "sg:tags":[
        "store"
    ],
    "wof:name":"Vintage Cellars",
    "wof:placetype":"venue"
},
  "geometry": {"coordinates":[115.87732696499999,-31.953168869],"type":"Point"}
}