{
  "type": "Feature",
  "properties": {
    "addr:full":"9 Bungan St Mona Vale NSW 2103",
    "addr:housenumber":"9",
    "addr:postcode":"2103",
    "addr:street":"Bungan St",
    "iso:country":"AU",
    "sg:address":"9 Bungan St",
    "sg:city":"Mona Vale",
    "sg:classifiers":[
        {
            "category":"Health Services",
            "subcategory":"Chiropractor",
            "type":"Services"
        }
    ],
    "sg:phone":"+61 2 9997 5372",
    "sg:postcode":"2103",
    "sg:province":"NSW",
    "wof:name":"Coroneos Manny A",
    "wof:placetype":"venue"
},
  "geometry": {"coordinates":[151.30247497600001,-33.6766891479],"type":"Point"}
}