{
  "type": "Feature",
  "properties": {
    "addr:full":"Factory 4/ 393 Dorset Rd Boronia VIC 3155",
    "addr:housenumber":"/ 393",
    "addr:postcode":"3155",
    "addr:street":"Dorset Rd",
    "iso:country":"AU",
    "sg:address":"Factory 4/ 393 Dorset Rd",
    "sg:city":"Boronia",
    "sg:classifiers":[
        {
            "category":"Retail",
            "subcategory":"Car Wash",
            "type":"Services"
        }
    ],
    "sg:phone":"+61 3 9762 5500",
    "sg:postcode":"3155",
    "sg:province":"VIC",
    "sg:tags":[
        "truck",
        "cleaning"
    ],
    "wof:name":"Protech Car Care Centre",
    "wof:placetype":"venue"
},
  "geometry": {"coordinates":[145.28619384800001,-37.8453063965],"type":"Point"}
}