{
  "type": "Feature",
  "properties": {
    "addr:full":"100 Bank St Picton WA 6229",
    "addr:housenumber":"100",
    "addr:postcode":"6229",
    "addr:street":"Bank St",
    "iso:country":"AU",
    "sg:address":"100 Bank St",
    "sg:city":"Picton",
    "sg:classifiers":[
        {
            "category":"Manufacturing",
            "subcategory":"Buildings",
            "type":"Manufacturing & Wholesale Goods"
        }
    ],
    "sg:phone":"+61 427 424 959",
    "sg:postcode":"6229",
    "sg:province":"WA",
    "sg:tags":[
        "transportable",
        "domestic",
        "relocatable"
    ],
    "wof:name":"Southwest Solid Caravan Annexes",
    "wof:placetype":"venue"
},
  "geometry": {"coordinates":[115.692787,-33.35088],"type":"Point"}
}