{
  "type": "Feature",
  "properties": {
    "addr:full":"214 Military Rd Neutral Bay NSW 2089",
    "addr:housenumber":"214",
    "addr:postcode":"2089",
    "addr:street":"Military Rd",
    "iso:country":"AU",
    "sg:address":"214 Military Rd",
    "sg:city":"Neutral Bay",
    "sg:classifiers":[
        {
            "category":"Health Services",
            "subcategory":"Doctor",
            "type":"Services"
        }
    ],
    "sg:phone":"+61 2 9953 9388",
    "sg:postcode":"2089",
    "sg:province":"NSW",
    "sg:tags":[
        "nurse",
        "nursing"
    ],
    "wof:name":"Gordon Trained Nurses' Club",
    "wof:placetype":"venue"
},
  "geometry": {"coordinates":[151.22291564899999,-33.8314208984],"type":"Point"}
}