{
  "type": "Feature",
  "properties": {
    "iso:country":"AU",
    "sg:address":"144 Trailwood Drv",
    "sg:city":"Woodvale",
    "sg:classifiers":[
        {
            "category":"Professional",
            "subcategory":"Accounting & Tax Preparation",
            "type":"Services"
        }
    ],
    "sg:phone":"+61 8 9309 9212",
    "sg:postcode":"6026",
    "sg:province":"WA",
    "sg:tags":[
        "bookkeeping"
    ],
    "wof:name":"Computer Bookkeeping Services",
    "wof:placetype":"venue"
},
  "geometry": {"coordinates":[115.786941528,-31.792673111],"type":"Point"}
}