{
  "type": "Feature",
  "properties": {
    "iso:country":"AU",
    "sg:address":"7-19 Ballantyne St",
    "sg:city":"Southbank",
    "sg:classifiers":[
        {
            "category":"Wholesale",
            "subcategory":"Apparel",
            "type":"Manufacturing & Wholesale Goods"
        }
    ],
    "sg:phone":"+61 3 8633 8888",
    "sg:postcode":"3006",
    "sg:province":"VIC",
    "sg:tags":[
        "wholesaler",
        "mfrs",
        "glove"
    ],
    "wof:name":"Engelite Pty Ltd",
    "wof:placetype":"venue"
},
  "geometry": {"coordinates":[144.95761108400001,-37.8289413452],"type":"Point"}
}