{
  "type": "Feature",
  "properties": {
    "addr:full":"U25/ 378 Parramatta Rd Homebush NSW 2140",
    "addr:housenumber":"378",
    "addr:postcode":"2140",
    "addr:street":"/;Parramatta Rd",
    "iso:country":"AU",
    "sg:address":"U25/ 378 Parramatta Rd",
    "sg:city":"Homebush",
    "sg:classifiers":[
        {
            "category":"Government",
            "subcategory":"Fire Station",
            "type":"Public Place"
        }
    ],
    "sg:phone":"+61 2 9764 5555",
    "sg:postcode":"2140",
    "sg:province":"NSW",
    "sg:tags":[
        "equipment",
        "protection",
        "consultant"
    ],
    "wof:name":"Base Fire Protection Pty Ltd",
    "wof:placetype":"venue"
},
  "geometry": {"coordinates":[151.064086914,-33.8563613892],"type":"Point"}
}