{
  "type": "Feature",
  "properties": {
    "addr:full":"456 Tooronga Rd Hawthorn East VIC 3123",
    "addr:housenumber":"456",
    "addr:postcode":"3123",
    "addr:street":"Tooronga Rd",
    "iso:country":"AU",
    "sg:address":"456 Tooronga Rd",
    "sg:city":"Hawthorn East",
    "sg:classifiers":[
        {
            "category":"Education",
            "subcategory":"Music School",
            "type":"Public Place"
        }
    ],
    "sg:phone":"+61 3 9813 5934",
    "sg:postcode":"3123",
    "sg:province":"VIC",
    "sg:tags":[
        "teacher"
    ],
    "wof:name":"Kodaly Music For Children Classes",
    "wof:placetype":"venue"
},
  "geometry": {"coordinates":[145.046707153,-37.8366928101],"type":"Point"}
}