{
  "type": "Feature",
  "properties": {
    "addr:full":"125 High St Shepparton VIC 3630",
    "addr:housenumber":"125",
    "addr:postcode":"3630",
    "addr:street":"High St",
    "iso:country":"AU",
    "sg:address":"125 High St",
    "sg:city":"Shepparton",
    "sg:classifiers":[
        {
            "category":"Fast Food",
            "type":"Food & Drink"
        }
    ],
    "sg:phone":"+61 3 5821 1115",
    "sg:postcode":"3630",
    "sg:province":"VIC",
    "sg:tags":[
        "away",
        "take"
    ],
    "wof:name":"Casablanca Pizza & Pasta Restaurant",
    "wof:placetype":"venue"
},
  "geometry": {"coordinates":[145.40264892600001,-36.3813323975],"type":"Point"}
}