{
  "type": "Feature",
  "properties": {
    "addr:full":"26 Bedford Crs Eagleby QLD 4207",
    "addr:housenumber":"26",
    "addr:postcode":"4207",
    "addr:street":"Bedford Crs",
    "iso:country":"AU",
    "sg:address":"26 Bedford Crs",
    "sg:city":"Eagleby",
    "sg:classifiers":[
        {
            "category":"Personal",
            "subcategory":"Beauty Salon",
            "type":"Services"
        }
    ],
    "sg:phone":"+61 401 905 994",
    "sg:postcode":"4207",
    "sg:province":"QLD",
    "sg:tags":[
        "hair",
        "wedding"
    ],
    "wof:name":"Grecilda Peace",
    "wof:placetype":"venue"
},
  "geometry": {"coordinates":[153.212615967,-27.7024803162],"type":"Point"}
}