{
  "type": "Feature",
  "properties": {
    "iso:country":"AU",
    "sg:address":"3 Hender Ave",
    "sg:city":"Magill",
    "sg:classifiers":[
        {
            "category":"Home & Garden",
            "subcategory":"Building Materials",
            "type":"Retail Goods"
        }
    ],
    "sg:phone":"+61 8 8333 0777",
    "sg:postcode":"5072",
    "sg:province":"SA",
    "sg:tags":[
        "merchant",
        "glass",
        "glazier"
    ],
    "wof:name":"Pribetic Architectural Glazing & Glass",
    "wof:placetype":"venue"
},
  "geometry": {"coordinates":[138.68119812,-34.9092407227],"type":"Point"}
}