{
  "type": "Feature",
  "properties": {
    "addr:full":"Level 1, 202 Glenferrie Rd Malvern VIC 3144",
    "addr:housenumber":"202",
    "addr:postcode":"3144",
    "addr:street":"Glenferrie Rd",
    "iso:country":"AU",
    "sg:address":"Level 1, 202 Glenferrie Rd",
    "sg:city":"Malvern",
    "sg:classifiers":[
        {
            "category":"Personal",
            "subcategory":"Beauty Salon",
            "type":"Services"
        }
    ],
    "sg:phone":"+61 3 9576 3269",
    "sg:postcode":"3144",
    "sg:province":"VIC",
    "wof:name":"Wax&#039;N Polish At Brush",
    "wof:placetype":"venue"
},
  "geometry": {"coordinates":[145.029022217,-37.8592758179],"type":"Point"}
}