{
  "type": "Feature",
  "properties": {
    "addr:full":"40 Belmont Ave Rivervale WA 6103",
    "addr:housenumber":"40",
    "addr:postcode":"6103",
    "addr:street":"Belmont Ave",
    "iso:country":"AU",
    "sg:address":"40 Belmont Ave",
    "sg:city":"Rivervale",
    "sg:classifiers":[
        {
            "category":"Wholesale",
            "subcategory":"Electrical",
            "type":"Manufacturing & Wholesale Goods"
        }
    ],
    "sg:phone":"+61 8 9478 3341",
    "sg:postcode":"6103",
    "sg:province":"WA",
    "sg:tags":[
        "control",
        "equipment",
        "switch"
    ],
    "wof:name":"Heineman Electric Pty Ltd",
    "wof:placetype":"venue"
},
  "geometry": {"coordinates":[115.920280456,-31.9546813965],"type":"Point"}
}