{
  "type": "Feature",
  "properties": {
    "iso:country":"AU",
    "sg:address":"5/ 47 Overlord Pl",
    "sg:city":"Acacia Ridge",
    "sg:classifiers":[
        {
            "category":"Government",
            "subcategory":"Department Of Motor Vehicles",
            "type":"Public Place"
        }
    ],
    "sg:phone":"+61 7 3273 5911",
    "sg:postcode":"4110",
    "sg:province":"QLD",
    "sg:tags":[
        "mfrs",
        "clutch",
        "brake",
        "lining",
        "wholesaler",
        "pad"
    ],
    "wof:name":"Disc Brakes Aust P/ L",
    "wof:placetype":"venue"
},
  "geometry": {"coordinates":[153.03918457,-27.5970077515],"type":"Point"}
}