{
  "type": "Feature",
  "properties": {
    "iso:country":"AU",
    "sg:address":"32 Cuzco St",
    "sg:city":"Coogee",
    "sg:classifiers":[
        {
            "category":"Health Services",
            "subcategory":"Health Practitioner",
            "type":"Services"
        }
    ],
    "sg:phone":"+61 2 9349 6940",
    "sg:postcode":"2034",
    "sg:province":"NSW",
    "sg:tags":[
        "physiotherapist"
    ],
    "wof:name":"Coorey Christine",
    "wof:placetype":"venue"
},
  "geometry": {"coordinates":[151.26010131800001,-33.93409729],"type":"Point"}
}