{
  "type": "Feature",
  "properties": {
    "addr:full":"G613/ 780 Bourke St Redfern NSW 2016",
    "addr:housenumber":"g613 / 780",
    "addr:postcode":"2016",
    "addr:street":"Bourke St",
    "iso:country":"AU",
    "sg:address":"G613/ 780 Bourke St",
    "sg:city":"Redfern",
    "sg:classifiers":[
        {
            "category":"Real Estate",
            "subcategory":"Architect",
            "type":"Services"
        }
    ],
    "sg:phone":"+61 2 9698 7986",
    "sg:postcode":"2016",
    "sg:province":"NSW",
    "wof:name":"Gianni Iacovazzi Architect",
    "wof:placetype":"venue"
},
  "geometry": {"coordinates":[151.21348571799999,-33.8965301514],"type":"Point"}
}