{
  "type": "Feature",
  "properties": {
    "addr:full":"16 Smithfield Rd Smithfield NSW 2164",
    "addr:housenumber":"16",
    "addr:postcode":"2164",
    "addr:street":"Smithfield Rd",
    "iso:country":"AU",
    "sg:address":"16 Smithfield Rd",
    "sg:city":"Smithfield",
    "sg:classifiers":[
        {
            "category":"Retail",
            "subcategory":"Auto Repair",
            "type":"Services"
        }
    ],
    "sg:phone":"+61 2 9725 5855",
    "sg:postcode":"2164",
    "sg:province":"NSW",
    "sg:tags":[
        "transmission",
        "automotive",
        "car"
    ],
    "wof:name":"Motospecs",
    "wof:placetype":"venue"
},
  "geometry": {"coordinates":[150.9243927,-33.8614616394],"type":"Point"}
}