{
  "type": "Feature",
  "properties": {
    "iso:country":"AU",
    "sg:address":"Suite 7, 2nd Floor, Neeta City Shopping Centre, Smart St",
    "sg:city":"Fairfield",
    "sg:classifiers":[
        {
            "category":"Wholesale",
            "subcategory":"Medical Equipment & Supplies",
            "type":"Manufacturing & Wholesale Goods"
        }
    ],
    "sg:phone":"+61 2 8264 3570",
    "sg:postcode":"2165",
    "sg:province":"NSW",
    "sg:tags":[
        "aids",
        "hearing"
    ],
    "wof:name":"National Hearing Care",
    "wof:placetype":"venue"
},
  "geometry": {"coordinates":[150.948852539,-33.8643684387],"type":"Point"}
}