{
  "type": "Feature",
  "properties": {
    "addr:full":"105 Lovell St Young NSW 2594",
    "addr:housenumber":"105",
    "addr:postcode":"2594",
    "addr:street":"Lovell St",
    "iso:country":"AU",
    "sg:address":"105 Lovell St",
    "sg:city":"Young",
    "sg:classifiers":[
        {
            "category":"Organizations",
            "subcategory":"Professional Association",
            "type":"Services"
        }
    ],
    "sg:phone":"+61 2 6382 4900",
    "sg:postcode":"2594",
    "sg:province":"NSW",
    "sg:tags":[
        "rural",
        "organisation",
        "production",
        "primary"
    ],
    "wof:name":"AWB Limited",
    "wof:placetype":"venue"
},
  "geometry": {"coordinates":[148.291671753,-34.3106803894],"type":"Point"}
}