{
  "type": "Feature",
  "properties": {
    "addr:full":"Cnr Dalton & Cavendish St Mittagong NSW 2575",
    "addr:postcode":"2575",
    "addr:street":"St",
    "iso:country":"AU",
    "sg:address":"Cnr Dalton & Cavendish St",
    "sg:city":"Mittagong",
    "sg:classifiers":[
        {
            "category":"Food & Beverages",
            "subcategory":"Bakery",
            "type":"Retail Goods"
        }
    ],
    "sg:phone":"+61 2 4872 2172",
    "sg:postcode":"2575",
    "sg:province":"NSW",
    "sg:tags":[
        "cake",
        "shop",
        "pastry"
    ],
    "wof:name":"Gumnut Patisserie Pty Ltd The",
    "wof:placetype":"venue"
},
  "geometry": {"coordinates":[150.433868408,-34.4485092163],"type":"Point"}
}