{
  "type": "Feature",
  "properties": {
    "addr:full":"371-373 Bourke St Darlinghurst NSW 2010",
    "addr:housenumber":"371-373",
    "addr:postcode":"2010",
    "addr:street":"Bourke St",
    "iso:country":"AU",
    "sg:address":"371-373 Bourke St",
    "sg:city":"Darlinghurst",
    "sg:classifiers":[
        {
            "category":"Health Services",
            "subcategory":"Health Practitioner",
            "type":"Services"
        }
    ],
    "sg:phone":"+61 2 9380 6522",
    "sg:postcode":"2010",
    "sg:province":"NSW",
    "sg:tags":[
        "alternative"
    ],
    "wof:name":"Salt Clinic",
    "wof:placetype":"venue"
},
  "geometry": {"coordinates":[151.21615600600001,-33.8826370239],"type":"Point"}
}