{
  "type": "Feature",
  "properties": {
    "addr:full":"1572 Princes Hwy Oakleigh VIC 3166",
    "addr:housenumber":"1572",
    "addr:postcode":"3166",
    "addr:street":"Princes Hwy",
    "iso:country":"AU",
    "sg:address":"1572 Princes Hwy",
    "sg:city":"Oakleigh",
    "sg:classifiers":[
        {
            "category":"Health Services",
            "subcategory":"Health Practitioner",
            "type":"Services"
        }
    ],
    "sg:phone":"+61 3 9543 3866",
    "sg:postcode":"3166",
    "sg:province":"VIC",
    "sg:tags":[
        "acupuncture"
    ],
    "wof:name":"Gu Dong Quan (Peter)",
    "wof:placetype":"venue"
},
  "geometry": {"coordinates":[145.107254028,-37.9022827148],"type":"Point"}
}