{
  "type": "Feature",
  "properties": {
    "addr:full":"Lvl 2 25 Cooper St Surry Hills NSW 2010",
    "addr:housenumber":"25",
    "addr:postcode":"2010",
    "addr:street":"Cooper St",
    "iso:country":"AU",
    "sg:address":"Lvl 2 25 Cooper St",
    "sg:city":"Surry Hills",
    "sg:classifiers":[
        {
            "category":"Shopping",
            "subcategory":"News",
            "type":"Retail Goods"
        }
    ],
    "sg:phone":"+61 2 9211 1068",
    "sg:postcode":"2010",
    "sg:province":"NSW",
    "sg:tags":[
        "magazine",
        "periodical"
    ],
    "wof:name":"Oyster Magazine",
    "wof:placetype":"venue"
},
  "geometry": {"coordinates":[151.20953369099999,-33.8857765198],"type":"Point"}
}