{
  "type": "Feature",
  "properties": {
    "iso:country":"AU",
    "sg:address":"Trangmar St",
    "sg:city":"Portland",
    "sg:classifiers":[
        {
            "category":"Education",
            "subcategory":"School",
            "type":"Public Place"
        }
    ],
    "sg:phone":"+61 3 5523 3833",
    "sg:postcode":"3305",
    "sg:province":"VIC",
    "sg:tags":[
        "co-educational"
    ],
    "wof:name":"St John's Lutheran Primary School",
    "wof:placetype":"venue"
},
  "geometry": {"coordinates":[141.592651367,-38.3560142517],"type":"Point"}
}