{
  "type": "Feature",
  "properties": {
    "iso:country":"AU",
    "sg:address":"St",
    "sg:city":"Kilda",
    "sg:classifiers":[
        {
            "category":"Utilities",
            "subcategory":"Electric",
            "type":"Services"
        }
    ],
    "sg:phone":"+61 1800 610 510",
    "sg:postcode":"3182",
    "sg:province":"VIC",
    "sg:tags":[
        "electrical",
        "contractor"
    ],
    "wof:name":"Electrical Professionals",
    "wof:placetype":"venue"
},
  "geometry": {"coordinates":[144.97959899899999,-37.8584403992],"type":"Point"}
}