{
  "type": "Feature",
  "properties": {
    "addr:full":"14 Walz St Rockdale NSW 2216",
    "addr:housenumber":"14",
    "addr:postcode":"2216",
    "addr:street":"Walz St",
    "iso:country":"AU",
    "sg:address":"14 Walz St",
    "sg:city":"Rockdale",
    "sg:classifiers":[
        {
            "category":"Shopping",
            "subcategory":"Clothing, Apparel, & Fashions",
            "type":"Retail Goods"
        }
    ],
    "sg:phone":"+61 2 9599 0223",
    "sg:postcode":"2216",
    "sg:province":"NSW",
    "sg:tags":[
        "boutique"
    ],
    "wof:name":"Boutique Fatima",
    "wof:placetype":"venue"
},
  "geometry": {"coordinates":[151.13563500000001,-33.951775],"type":"Point"}
}