{
  "type": "Feature",
  "properties": {
    "addr:full":"201 Murrumbeena Rd Murrumbeena VIC 3163",
    "addr:housenumber":"201",
    "addr:postcode":"3163",
    "addr:street":"Murrumbeena Rd",
    "iso:country":"AU",
    "sg:address":"201 Murrumbeena Rd",
    "sg:city":"Murrumbeena",
    "sg:classifiers":[
        {
            "category":"Professional",
            "subcategory":"Computer Services",
            "type":"Services"
        }
    ],
    "sg:phone":"+61 402 044 586",
    "sg:postcode":"3163",
    "sg:province":"VIC",
    "sg:tags":[
        "consultant",
        "system"
    ],
    "wof:name":"Mangtech Enterprises",
    "wof:placetype":"venue"
},
  "geometry": {"coordinates":[145.06959533700001,-37.903011322],"type":"Point"}
}