{
  "type": "Feature",
  "properties": {
    "addr:full":"50 Grosvenor Rd Lindfield NSW 2070",
    "addr:housenumber":"50",
    "addr:postcode":"2070",
    "addr:street":"Grosvenor Rd",
    "iso:country":"AU",
    "sg:address":"50 Grosvenor Rd",
    "sg:city":"Lindfield",
    "sg:classifiers":[
        {
            "category":"Professional",
            "subcategory":"Computer Services",
            "type":"Services"
        }
    ],
    "sg:phone":"+61 2 9924 2770",
    "sg:postcode":"2070",
    "sg:province":"NSW",
    "sg:tags":[
        "consultant",
        "system"
    ],
    "wof:name":"Natcom Consulting Pty Ltd",
    "wof:placetype":"venue"
},
  "geometry": {"coordinates":[151.16336059599999,-33.7842330933],"type":"Point"}
}