{
  "type": "Feature",
  "properties": {
    "addr:full":"Unit 4 8 Northcote St St Leonards NSW 2065",
    "addr:housenumber":"8",
    "addr:postcode":"2065",
    "addr:street":"Northcote St",
    "iso:country":"AU",
    "sg:address":"Unit 4 8 Northcote St",
    "sg:city":"St Leonards",
    "sg:classifiers":[
        {
            "category":"Utilities",
            "subcategory":"Electric",
            "type":"Services"
        }
    ],
    "sg:phone":"+61 2 9437 9809",
    "sg:postcode":"2065",
    "sg:province":"NSW",
    "sg:tags":[
        "electrical",
        "contractor"
    ],
    "wof:name":"Archetype Electrical Pty Ltd",
    "wof:placetype":"venue"
},
  "geometry": {"coordinates":[151.1953125,-33.820728302],"type":"Point"}
}