{
  "type": "Feature",
  "properties": {
    "iso:country":"AU",
    "sg:address":"61 Railway. St",
    "sg:city":"Mudgeeraba",
    "sg:classifiers":[
        {
            "category":"Real Estate",
            "subcategory":"Real Estate Agent",
            "type":"Services"
        }
    ],
    "sg:phone":"+61 7 5530 4400",
    "sg:postcode":"4213",
    "sg:province":"QLD",
    "wof:name":"Mudgeeraba Somerset Realty",
    "wof:placetype":"venue"
},
  "geometry": {"coordinates":[153.364624023,-28.0792217255],"type":"Point"}
}