{
  "type": "Feature",
  "properties": {
    "addr:full":"2b Bridge Rd Richmond VIC 3121",
    "addr:housenumber":"2b",
    "addr:postcode":"3121",
    "addr:street":"Bridge Rd",
    "iso:country":"AU",
    "sg:address":"2b Bridge Rd",
    "sg:city":"Richmond",
    "sg:classifiers":[
        {
            "category":"Retail",
            "subcategory":"Repair Shop",
            "type":"Services"
        }
    ],
    "sg:phone":"+61 3 9428 6060",
    "sg:postcode":"3121",
    "sg:province":"VIC",
    "sg:tags":[
        "mending",
        "clothing",
        "alteration"
    ],
    "wof:name":"Sewfit Clothing Alterations",
    "wof:placetype":"venue"
},
  "geometry": {"coordinates":[144.99119567899999,-37.8177833557],"type":"Point"}
}