{
  "type": "Feature",
  "properties": {
    "addr:full":"Shop 8 Seven Hills Rd Baulkham Hills NSW 2153",
    "addr:housenumber":"shop 8",
    "addr:postcode":"2153",
    "addr:street":"Seven Hills Rd",
    "iso:country":"AU",
    "sg:address":"Shop 8 Seven Hills Rd",
    "sg:city":"Baulkham Hills",
    "sg:classifiers":[
        {
            "category":"Real Estate",
            "subcategory":"Real Estate Agent",
            "type":"Services"
        }
    ],
    "sg:phone":"+61 2 9639 2000",
    "sg:postcode":"2153",
    "sg:province":"NSW",
    "wof:name":"Walsh & Sullivan First National",
    "wof:placetype":"venue"
},
  "geometry": {"coordinates":[150.95692443900001,-33.7561607361],"type":"Point"}
}