{
  "type": "Feature",
  "properties": {
    "addr:full":"96 Arthur St St George QLD 4487",
    "addr:housenumber":"96",
    "addr:postcode":"4487",
    "addr:street":"Arthur St",
    "iso:country":"AU",
    "sg:address":"96 Arthur St St",
    "sg:city":"George",
    "sg:classifiers":[
        {
            "category":"Building & Trades",
            "subcategory":"Construction",
            "type":"Services"
        }
    ],
    "sg:phone":"+61 7 4625 1305",
    "sg:postcode":"4487",
    "sg:province":"QLD",
    "sg:tags":[
        "earth",
        "excavating",
        "moving",
        "contractor"
    ],
    "wof:name":"O&#039;Neil Guy Earthmoving Pty Ltd",
    "wof:placetype":"venue"
},
  "geometry": {"coordinates":[148.5884552,-28.0411205292],"type":"Point"}
}