{
  "type": "Feature",
  "properties": {
    "addr:full":"171 Hart St Colac VIC 3250",
    "addr:housenumber":"171",
    "addr:postcode":"3250",
    "addr:street":"Hart St",
    "iso:country":"AU",
    "sg:address":"171 Hart St",
    "sg:city":"Colac",
    "sg:classifiers":[
        {
            "category":"Building & Trades",
            "subcategory":"Construction",
            "type":"Services"
        }
    ],
    "sg:phone":"+61 3 5231 4877",
    "sg:postcode":"3250",
    "sg:province":"VIC",
    "sg:tags":[
        "earth",
        "excavating",
        "moving",
        "contractor"
    ],
    "wof:name":"McNaughton John",
    "wof:placetype":"venue"
},
  "geometry": {"coordinates":[143.57782,-38.357437],"type":"Point"}
}