{
  "type": "Feature",
  "properties": {
    "addr:full":"52 Cook St Flinders VIC 3929",
    "addr:housenumber":"52",
    "addr:postcode":"3929",
    "addr:street":"Cook St",
    "iso:country":"AU",
    "sg:address":"52 Cook St",
    "sg:city":"Flinders",
    "sg:classifiers":[
        {
            "category":"Manufacturing",
            "subcategory":"Glass & Minerals",
            "type":"Manufacturing & Wholesale Goods"
        }
    ],
    "sg:phone":"+61 3 5989 0626",
    "sg:postcode":"3929",
    "sg:province":"VIC",
    "sg:tags":[
        "stained"
    ],
    "wof:name":"Wright, David",
    "wof:placetype":"venue"
},
  "geometry": {"coordinates":[145.01654052699999,-38.473613739],"type":"Point"}
}