{
  "type": "Feature",
  "properties": {
    "iso:country":"AU",
    "sg:address":"113 Thompson St",
    "sg:city":"Williamstown",
    "sg:classifiers":[
        {
            "category":"Food & Beverages",
            "subcategory":"Specialty",
            "type":"Retail Goods"
        }
    ],
    "sg:phone":"+61 3 9397 4313",
    "sg:postcode":"3016",
    "sg:province":"VIC",
    "sg:tags":[
        "product",
        "health"
    ],
    "wof:name":"Herbalife Williamstown",
    "wof:placetype":"venue"
},
  "geometry": {"coordinates":[144.901901245,-37.8703613281],"type":"Point"}
}