{
  "type": "Feature",
  "properties": {
    "addr:full":"123 The Entrance Rd The Entrance NSW 2261",
    "addr:housenumber":"123",
    "addr:postcode":"2261",
    "addr:street":"The Entrance Rd",
    "iso:country":"AU",
    "sg:address":"123 The Entrance Rd",
    "sg:city":"The Entrance",
    "sg:classifiers":[
        {
            "category":"Recreation",
            "subcategory":"Fishing",
            "type":"Entertainment"
        }
    ],
    "sg:phone":"+61 2 4333 3500",
    "sg:postcode":"2261",
    "sg:province":"NSW",
    "sg:tags":[
        "tackle"
    ],
    "wof:name":"Fishing-R-Us",
    "wof:placetype":"venue"
},
  "geometry": {"coordinates":[151.494675,-33.345852],"type":"Point"}
}