{
  "type": "Feature",
  "properties": {
    "iso:country":"AU",
    "sg:address":"174 High St",
    "sg:city":"Maitland",
    "sg:classifiers":[
        {
            "category":"Autos & Motor Vehicles",
            "subcategory":"Automobile Sales",
            "type":"Retail Goods"
        }
    ],
    "sg:phone":"+61 2 4933 5233",
    "sg:postcode":"2320",
    "sg:province":"NSW",
    "sg:tags":[
        "car",
        "new"
    ],
    "wof:name":"Hunter Subaru",
    "wof:placetype":"venue"
},
  "geometry": {"coordinates":[151.55354309099999,-32.7311973572],"type":"Point"}
}