{
  "type": "Feature",
  "properties": {
    "addr:full":"46C Menai Market Place, Allison Crs Menai NSW 2234",
    "addr:housenumber":"46c",
    "addr:postcode":"2234",
    "addr:street":"Menai Market Place Allison Crs",
    "iso:country":"AU",
    "sg:address":"46C Menai Market Place, Allison Crs",
    "sg:city":"Menai",
    "sg:classifiers":[
        {
            "category":"Real Estate",
            "subcategory":"Real Estate Agent",
            "type":"Services"
        }
    ],
    "sg:phone":"+61 2 9543 0333",
    "sg:postcode":"2234",
    "sg:province":"NSW",
    "wof:name":"Ray White Menai",
    "wof:placetype":"venue"
},
  "geometry": {"coordinates":[151.04296875,-34.0198402405],"type":"Point"}
}