{
  "type": "Feature",
  "properties": {
    "addr:full":"30- 40 Alfred St Chipping Norton NSW 2170",
    "addr:housenumber":"40",
    "addr:postcode":"2170",
    "addr:street":"Alfred St",
    "iso:country":"AU",
    "sg:address":"30- 40 Alfred St",
    "sg:city":"Chipping Norton",
    "sg:classifiers":[
        {
            "category":"Autos & Motor Vehicles",
            "subcategory":"Fuel & Gas Station",
            "type":"Retail Goods"
        }
    ],
    "sg:phone":"+61 2 9755 1760",
    "sg:postcode":"2170",
    "sg:province":"NSW",
    "wof:name":"Southern Cross & Diner",
    "wof:placetype":"venue"
},
  "geometry": {"coordinates":[150.96348571799999,-33.9232635498],"type":"Point"}
}