{
  "type": "Feature",
  "properties": {
    "iso:country":"AU",
    "sg:address":"100 Johnston St",
    "sg:city":"Southport",
    "sg:classifiers":[
        {
            "category":"Health Services",
            "subcategory":"Dentist",
            "type":"Services"
        }
    ],
    "sg:phone":"+61 7 5571 1199",
    "sg:postcode":"4215",
    "sg:province":"QLD",
    "sg:tags":[
        "dental",
        "prosthetist"
    ],
    "wof:name":"Chirn Park Denture Studio",
    "wof:placetype":"venue"
},
  "geometry": {"coordinates":[153.40138244600001,-27.9647502899],"type":"Point"}
}