{
  "type": "Feature",
  "properties": {
    "addr:full":"94 Musgrave Rd Coopers Plains QLD 4108",
    "addr:housenumber":"94",
    "addr:postcode":"4108",
    "addr:street":"Musgrave Rd",
    "iso:country":"AU",
    "sg:address":"94 Musgrave Rd",
    "sg:city":"Coopers Plains",
    "sg:classifiers":[
        {
            "category":"Manufacturing",
            "subcategory":"Motor Vehicles & Parts",
            "type":"Manufacturing & Wholesale Goods"
        }
    ],
    "sg:phone":"+61 7 3277 8926",
    "sg:postcode":"4108",
    "sg:province":"QLD",
    "sg:tags":[
        "replacement"
    ],
    "sg:website":"http://www.autopartsrecyclers.com/a1nissan/",
    "wof:name":"A1 Nissan Wrecking",
    "wof:placetype":"venue"
},
  "geometry": {"coordinates":[153.027618408,-27.5613231659],"type":"Point"}
}