{
  "type": "Feature",
  "properties": {
    "addr:full":"13/ 85 Queens Cliff Rd Queenscliff NSW 2096",
    "addr:housenumber":"13 / 85",
    "addr:postcode":"2096",
    "addr:street":"Cliff Rd",
    "iso:country":"AU",
    "sg:address":"13/ 85 Queens Cliff Rd",
    "sg:city":"Queenscliff",
    "sg:classifiers":[
        {
            "category":"Sports & Exercise",
            "subcategory":"Gym",
            "type":"Entertainment"
        }
    ],
    "sg:phone":"+61 412 662 088",
    "sg:postcode":"2096",
    "sg:province":"NSW",
    "sg:tags":[
        "health",
        "fitness"
    ],
    "wof:name":"Apollo Personal Fitness Management",
    "wof:placetype":"venue"
},
  "geometry": {"coordinates":[151.28529357900001,-33.7828826904],"type":"Point"}
}