{
  "type": "Feature",
  "properties": {
    "addr:full":"32 Container St Tingalpa QLD 4173",
    "addr:postcode":"4173",
    "addr:street":"St",
    "iso:country":"AU",
    "sg:address":"32 Container St",
    "sg:city":"Tingalpa",
    "sg:classifiers":[
        {
            "category":"Home & Garden",
            "subcategory":"Carpets & Floor Coverings",
            "type":"Retail Goods"
        }
    ],
    "sg:phone":"+61 7 3390 8611",
    "sg:postcode":"4173",
    "sg:province":"QLD",
    "sg:tags":[
        "wood"
    ],
    "wof:name":"Wunderlay Natural Timber Floor Covering",
    "wof:placetype":"venue"
},
  "geometry": {"coordinates":[153.109176636,-27.4744224548],"type":"Point"}
}