{
  "type": "Feature",
  "properties": {
    "iso:country":"AU",
    "sg:address":"163 Lord St",
    "sg:city":"Perth",
    "sg:classifiers":[
        {
            "category":"Home & Garden",
            "subcategory":"Kitchen Supply",
            "type":"Retail Goods"
        }
    ],
    "sg:phone":"+61 8 9228 4366",
    "sg:postcode":"6000",
    "sg:province":"WA",
    "sg:tags":[
        "photocopying"
    ],
    "sg:website":"http://www.copyfax.com.au",
    "wof:name":"Copyfax",
    "wof:placetype":"venue"
},
  "geometry": {"coordinates":[115.869789123,-31.9482593536],"type":"Point"}
}