{
  "type": "Feature",
  "properties": {
    "iso:country":"AU",
    "sg:address":"49 Burroway St",
    "sg:city":"Narromine",
    "sg:classifiers":[
        {
            "category":"Autos & Motor Vehicles",
            "subcategory":"Fuel & Gas Station",
            "type":"Retail Goods"
        }
    ],
    "sg:phone":"+61 2 6889 1569",
    "sg:postcode":"2821",
    "sg:province":"NSW",
    "wof:name":"Caltex",
    "wof:placetype":"venue"
},
  "geometry": {"coordinates":[148.25242614699999,-32.2116622925],"type":"Point"}
}