{
  "type": "Feature",
  "properties": {
    "iso:country":"AU",
    "sg:address":"104 Canterbury Rd",
    "sg:city":"Middle Park",
    "sg:classifiers":[
        {
            "category":"Personal",
            "subcategory":"Beauty Salon",
            "type":"Services"
        }
    ],
    "sg:phone":"+61 3 9699 7733",
    "sg:postcode":"3206",
    "sg:province":"VIC",
    "sg:tags":[
        "hair",
        "treatment",
        "replacement"
    ],
    "sg:website":"http://www.newhair.com.au",
    "wof:name":"National Hair Institute",
    "wof:placetype":"venue"
},
  "geometry": {"coordinates":[144.96530200000001,-37.849991],"type":"Point"}
}