{
  "type": "Feature",
  "properties": {
    "iso:country":"AU",
    "sg:address":"64 Arve Rd",
    "sg:city":"Geeveston",
    "sg:classifiers":[
        {
            "category":"Fast Food",
            "type":"Food & Drink"
        }
    ],
    "sg:phone":"+61 3 6297 1459",
    "sg:postcode":"7116",
    "sg:province":"TAS",
    "sg:tags":[
        "away",
        "take"
    ],
    "wof:name":"Geeveston One Stop Supermarket & Takeaway",
    "wof:placetype":"venue"
},
  "geometry": {"coordinates":[146.92054748499999,-43.1613349915],"type":"Point"}
}