{
  "type": "Feature",
  "properties": {
    "iso:country":"AU",
    "sg:address":"New Farm Rd",
    "sg:city":"Werribee",
    "sg:classifiers":[
        {
            "category":"Organizations",
            "subcategory":"Non-profit Organization",
            "type":"Services"
        }
    ],
    "sg:phone":"+61 3 9731 0288",
    "sg:postcode":"3030",
    "sg:province":"VIC",
    "sg:tags":[
        "environmental",
        "organisation",
        "conservation"
    ],
    "wof:name":"Western Region Environment Centre",
    "wof:placetype":"venue"
},
  "geometry": {"coordinates":[144.644531,-37.916389],"type":"Point"}
}