{
  "type": "Feature",
  "properties": {
    "addr:full":"23 Adelaide Rd Gawler SA 5118",
    "addr:housenumber":"23",
    "addr:postcode":"5118",
    "addr:street":"Adelaide Rd",
    "iso:country":"AU",
    "sg:address":"23 Adelaide Rd",
    "sg:city":"Gawler",
    "sg:classifiers":[
        {
            "category":"Health Services",
            "subcategory":"Chiropractor",
            "type":"Services"
        }
    ],
    "sg:phone":"+61 8 8522 3922",
    "sg:postcode":"5118",
    "sg:province":"SA",
    "wof:name":"Dr Keswani & Associates",
    "wof:placetype":"venue"
},
  "geometry": {"coordinates":[138.74517800000001,-34.605667],"type":"Point"}
}