{
  "type": "Feature",
  "properties": {
    "iso:country":"AU",
    "sg:address":"6 Pacific St",
    "sg:city":"Newcastle",
    "sg:classifiers":[
        {
            "category":"Retail",
            "subcategory":"Self-service Laundry",
            "type":"Services"
        }
    ],
    "sg:phone":"+61 2 4925 2188",
    "sg:postcode":"2300",
    "sg:province":"NSW",
    "wof:name":"East End Laundry",
    "wof:placetype":"venue"
},
  "geometry": {"coordinates":[151.78535500000001,-32.928871],"type":"Point"}
}