{
  "type": "Feature",
  "properties": {
    "iso:country":"AU",
    "sg:address":"Level 1, 77 Ridge St",
    "sg:city":"Gordon",
    "sg:classifiers":[
        {
            "category":"Shopping",
            "subcategory":"Optical Goods",
            "type":"Retail Goods"
        }
    ],
    "sg:phone":"+61 1800 266 111",
    "sg:postcode":"2072",
    "sg:province":"NSW",
    "sg:tags":[
        "supply"
    ],
    "sg:website":"http://www.amo-inc.com",
    "wof:name":"Advanced Medical Optics",
    "wof:placetype":"venue"
},
  "geometry": {"coordinates":[151.14530944800001,-33.7529220581],"type":"Point"}
}