{
  "type": "Feature",
  "properties": {
    "addr:full":"North Arm Rd Chillingham NSW 2484",
    "addr:postcode":"2484",
    "addr:street":"North Arm Rd",
    "iso:country":"AU",
    "sg:address":"North Arm Rd",
    "sg:city":"Chillingham",
    "sg:classifiers":[
        {
            "category":"Building & Trades",
            "subcategory":"Construction",
            "type":"Services"
        }
    ],
    "sg:phone":"+61 2 6679 1452",
    "sg:postcode":"2484",
    "sg:province":"NSW",
    "sg:tags":[
        "earth",
        "excavating",
        "moving",
        "contractor"
    ],
    "wof:name":"Mitchell A G & D M",
    "wof:placetype":"venue"
},
  "geometry": {"coordinates":[153.345581055,-28.3243350983],"type":"Point"}
}