{
  "type": "Feature",
  "properties": {
    "addr:full":"Shop 18 Northcote Central High St Northcote VIC 3070",
    "addr:housenumber":"shop 18",
    "addr:postcode":"3070",
    "addr:street":"High St",
    "iso:country":"AU",
    "sg:address":"Shop 18 Northcote Central High St",
    "sg:city":"Northcote",
    "sg:classifiers":[
        {
            "category":"Cafe",
            "type":"Food & Drink"
        }
    ],
    "sg:phone":"+61 3 9489 4491",
    "sg:postcode":"3070",
    "sg:province":"VIC",
    "wof:name":"Cafe Inn",
    "wof:placetype":"venue"
},
  "geometry": {"coordinates":[145.00817900000001,-37.773674],"type":"Point"}
}