{
  "type": "Feature",
  "properties": {
    "addr:full":"2 Clark St Horsham VIC 3400",
    "addr:housenumber":"2",
    "addr:postcode":"3400",
    "addr:street":"Clark St",
    "iso:country":"AU",
    "sg:address":"2 Clark St",
    "sg:city":"Horsham",
    "sg:classifiers":[
        {
            "category":"Personal",
            "subcategory":"Beauty Salon",
            "type":"Services"
        }
    ],
    "sg:phone":"+61 3 5382 3658",
    "sg:postcode":"3400",
    "sg:province":"VIC",
    "sg:tags":[
        "hairdresser"
    ],
    "wof:name":"Turnstyles Hair Design",
    "wof:placetype":"venue"
},
  "geometry": {"coordinates":[142.20346069300001,-36.7179641724],"type":"Point"}
}