{
  "type": "Feature",
  "properties": {
    "iso:country":"AU",
    "sg:address":"Unit 3 & 4/ 17 Villiers Drv",
    "sg:city":"Currumbin",
    "sg:classifiers":[
        {
            "category":"Retail",
            "subcategory":"Auto Repair",
            "type":"Services"
        }
    ],
    "sg:phone":"+61 7 5525 7770",
    "sg:postcode":"4223",
    "sg:province":"QLD",
    "sg:tags":[
        "repairer",
        "motor",
        "engineer"
    ],
    "wof:name":"All Transmissions",
    "wof:placetype":"venue"
},
  "geometry": {"coordinates":[153.472732544,-28.1512241364],"type":"Point"}
}