{
  "type": "Feature",
  "properties": {
    "addr:full":"Kurrajong Rd Horningsea Park NSW 2171",
    "addr:postcode":"2171",
    "addr:street":"Kurrajong Rd",
    "iso:country":"AU",
    "sg:address":"Kurrajong Rd",
    "sg:city":"Horningsea Park",
    "sg:classifiers":[
        {
            "category":"Health Services",
            "subcategory":"Dentist",
            "type":"Services"
        }
    ],
    "sg:phone":"+61 2 8783 0123",
    "sg:postcode":"2171",
    "sg:province":"NSW",
    "wof:name":"Carnes Hill Dental Centre",
    "wof:placetype":"venue"
},
  "geometry": {"coordinates":[150.846633911,-33.9361991882],"type":"Point"}
}