{
  "type": "Feature",
  "properties": {
    "addr:full":"Cnr Halford St 64 Newstead Tce Newstead QLD 4006",
    "addr:housenumber":"64",
    "addr:postcode":"4006",
    "addr:street":"Cnr Halford St;Newstead Tce",
    "iso:country":"AU",
    "sg:address":"Cnr Halford St 64 Newstead Tce",
    "sg:city":"Newstead",
    "sg:classifiers":[
        {
            "category":"Personal",
            "subcategory":"Skin Care",
            "type":"Services"
        }
    ],
    "sg:phone":"+61 7 3852 4036",
    "sg:postcode":"4006",
    "sg:province":"QLD",
    "sg:tags":[
        "hair",
        "product"
    ],
    "wof:name":"Luka Hair Care",
    "wof:placetype":"venue"
},
  "geometry": {"coordinates":[153.04473876899999,-27.4436855316],"type":"Point"}
}