{
  "type": "Feature",
  "properties": {
    "iso:country":"AU",
    "sg:address":"51 Hanbury St",
    "sg:city":"Greystanes",
    "sg:classifiers":[
        {
            "category":"Building & Trades",
            "subcategory":"Construction",
            "type":"Services"
        }
    ],
    "sg:phone":"+61 2 8704 1136",
    "sg:postcode":"2145",
    "sg:province":"NSW",
    "sg:tags":[
        "repair",
        "maintenance",
        "contractor"
    ],
    "wof:name":"Professional Building Team P/L",
    "wof:placetype":"venue"
},
  "geometry": {"coordinates":[150.956375122,-33.8249778748],"type":"Point"}
}