{
  "type": "Feature",
  "properties": {
    "iso:country":"AU",
    "sg:address":"36 Fairbairn Pl",
    "sg:city":"Kyneton",
    "sg:classifiers":[
        {
            "category":"Park",
            "subcategory":"County",
            "type":"Public Place"
        }
    ],
    "sg:phone":"+61 3 5422 1668",
    "sg:postcode":"3444",
    "sg:province":"VIC",
    "sg:tags":[
        "sanctuary",
        "zoos",
        "animal"
    ],
    "wof:name":"Farmer Darryl's Mobile Animal Farm",
    "wof:placetype":"venue"
},
  "geometry": {"coordinates":[144.475143433,-37.2627029419],"type":"Point"}
}