{
  "type": "Feature",
  "properties": {
    "addr:full":"36 Bell St Heidelberg Heights VIC 3081",
    "addr:housenumber":"36",
    "addr:postcode":"3081",
    "addr:street":"Bell St",
    "iso:country":"AU",
    "sg:address":"36 Bell St",
    "sg:city":"Heidelberg Heights",
    "sg:classifiers":[
        {
            "category":"Health Services",
            "subcategory":"Health Practitioner",
            "type":"Services"
        }
    ],
    "sg:phone":"+61 3 9455 1177",
    "sg:postcode":"3081",
    "sg:province":"VIC",
    "sg:tags":[
        "physiotherapist"
    ],
    "wof:name":"Warringal Physiotherapy & Sports Centre",
    "wof:placetype":"venue"
},
  "geometry": {"coordinates":[145.05543518100001,-37.7545013428],"type":"Point"}
}