{
  "type": "Feature",
  "properties": {
    "iso:country":"AU",
    "sg:address":"539 Royal Pde",
    "sg:city":"Parkville",
    "sg:classifiers":[
        {
            "category":"Travel",
            "subcategory":"Hotels & Motels",
            "type":"Entertainment"
        }
    ],
    "sg:phone":"+61 3 9380 8131",
    "sg:postcode":"3052",
    "sg:province":"VIC",
    "wof:name":"Ramada Inn",
    "wof:placetype":"venue"
},
  "geometry": {"coordinates":[144.959747314,-37.778717041],"type":"Point"}
}