{
  "type": "Feature",
  "properties": {
    "addr:full":"U16/ 2 Techno Park Drv Williamstown VIC 3016",
    "addr:postcode":"3016",
    "addr:street":"/;Techno Park Drv",
    "iso:country":"AU",
    "sg:address":"U16/ 2 Techno Park Drv",
    "sg:city":"Williamstown",
    "sg:classifiers":[
        {
            "category":"Professional",
            "subcategory":"Accounting & Tax Preparation",
            "type":"Services"
        }
    ],
    "sg:phone":"+61 3 9397 7780",
    "sg:postcode":"3016",
    "sg:province":"VIC",
    "sg:tags":[
        "bookkeeping"
    ],
    "wof:name":"Supreme Office Solutions",
    "wof:placetype":"venue"
},
  "geometry": {"coordinates":[144.85873413100001,-37.8545455933],"type":"Point"}
}