{
  "type": "Feature",
  "properties": {
    "addr:full":"Ste 47 Lvl 2 Oasis Shopping Centre Victoria Ave Broadbeach QLD 4218",
    "addr:postcode":"4218",
    "addr:street":"Victoria Ave",
    "iso:country":"AU",
    "sg:address":"Ste 47 Lvl 2 Oasis Shopping Centre Victoria Ave",
    "sg:city":"Broadbeach",
    "sg:classifiers":[
        {
            "category":"Health Services",
            "subcategory":"Health Practitioner",
            "type":"Services"
        }
    ],
    "sg:phone":"+61 1300 884 966",
    "sg:postcode":"4218",
    "sg:province":"QLD",
    "sg:tags":[
        "hypnotherapy"
    ],
    "wof:name":"Martin St James",
    "wof:placetype":"venue"
},
  "geometry": {"coordinates":[153.43032836899999,-28.0295200348],"type":"Point"}
}