{
  "type": "Feature",
  "properties": {
    "addr:full":"17 Hunter St Brassall QLD 4305",
    "addr:housenumber":"17",
    "addr:postcode":"4305",
    "addr:street":"Hunter St",
    "iso:country":"AU",
    "sg:address":"17 Hunter St",
    "sg:city":"Brassall",
    "sg:classifiers":[
        {
            "category":"Retail",
            "subcategory":"Veterinary Services",
            "type":"Services"
        }
    ],
    "sg:phone":"+61 7 3201 6464",
    "sg:postcode":"4305",
    "sg:province":"QLD",
    "sg:tags":[
        "surgeon"
    ],
    "wof:name":"Smith Craig",
    "wof:placetype":"venue"
},
  "geometry": {"coordinates":[152.74607849099999,-27.5931777954],"type":"Point"}
}