{
  "type": "Feature",
  "properties": {
    "addr:full":"255 Ann St Brisbane QLD 4000",
    "addr:housenumber":"255",
    "addr:postcode":"4000",
    "addr:street":"Ann St",
    "iso:country":"AU",
    "sg:address":"255 Ann St",
    "sg:city":"Brisbane",
    "sg:classifiers":[
        {
            "category":"Restaurant",
            "type":"Food & Drink"
        }
    ],
    "sg:phone":"+61 7 3220 1022",
    "sg:postcode":"4000",
    "sg:province":"QLD",
    "sg:website":"http://www.berkleys.com.au",
    "wof:name":"Berkleys On Ann",
    "wof:placetype":"venue"
},
  "geometry": {"coordinates":[153.026046753,-27.4665393829],"type":"Point"}
}