{
  "type": "Feature",
  "properties": {
    "iso:country":"AU",
    "sg:address":"1/ 11 Eastgate Crt",
    "sg:city":"Wantirna South",
    "sg:classifiers":[
        {
            "category":"Retail",
            "subcategory":"Auto Repair",
            "type":"Services"
        }
    ],
    "sg:phone":"+61 3 9801 8283",
    "sg:postcode":"3152",
    "sg:province":"VIC",
    "sg:tags":[
        "repairer",
        "motor",
        "engineer"
    ],
    "wof:name":"Knoxfield Automotive Repairs",
    "wof:placetype":"venue"
},
  "geometry": {"coordinates":[145.24827575699999,-37.870891571],"type":"Point"}
}