{
  "type": "Feature",
  "properties": {
    "addr:full":"4 Sinclair St Drouin VIC 3818",
    "addr:housenumber":"4",
    "addr:postcode":"3818",
    "addr:street":"Sinclair St",
    "iso:country":"AU",
    "sg:address":"4 Sinclair St",
    "sg:city":"Drouin",
    "sg:classifiers":[
        {
            "category":"Retail",
            "subcategory":"Veterinary Services",
            "type":"Services"
        }
    ],
    "sg:phone":"+61 3 5625 2002",
    "sg:postcode":"3818",
    "sg:province":"VIC",
    "sg:tags":[
        "surgeon"
    ],
    "wof:name":"Drouin Vet Clinic",
    "wof:placetype":"venue"
},
  "geometry": {"coordinates":[145.85493500000001,-38.133846],"type":"Point"}
}