{
  "type": "Feature",
  "properties": {
    "addr:full":"Cnr Frankston Dandenong Rd & Klauer St Frankston VIC 3199",
    "addr:postcode":"3199",
    "addr:street":"Cnr;Dandenong Rd & Klauer St",
    "iso:country":"AU",
    "sg:address":"Cnr Frankston Dandenong Rd & Klauer St",
    "sg:city":"Frankston",
    "sg:classifiers":[
        {
            "category":"Autos & Motor Vehicles",
            "subcategory":"Automobile Sales",
            "type":"Retail Goods"
        }
    ],
    "sg:phone":"+61 3 9773 6888",
    "sg:postcode":"3199",
    "sg:province":"VIC",
    "sg:tags":[
        "car",
        "new"
    ],
    "wof:name":"Stewart Webster Land Rover",
    "wof:placetype":"venue"
},
  "geometry": {"coordinates":[145.14662170400001,-38.1198692322],"type":"Point"}
}