{
  "type": "Feature",
  "properties": {
    "addr:full":"844 King Georges Rd South Hurstville NSW 2221",
    "addr:housenumber":"844",
    "addr:postcode":"2221",
    "addr:street":"King Georges Rd",
    "iso:country":"AU",
    "sg:address":"844 King Georges Rd",
    "sg:city":"South Hurstville",
    "sg:classifiers":[
        {
            "category":"Home & Garden",
            "subcategory":"Hardware",
            "type":"Retail Goods"
        }
    ],
    "sg:phone":"+61 2 9547 1222",
    "sg:postcode":"2221",
    "sg:province":"NSW",
    "sg:tags":[
        "repair",
        "tool",
        "power"
    ],
    "wof:name":"Dragon Power Tools",
    "wof:placetype":"venue"
},
  "geometry": {"coordinates":[151.10528564399999,-33.9776077271],"type":"Point"}
}