{
  "type": "Feature",
  "properties": {
    "addr:full":"1/ 11 Church St Moruya NSW 2537",
    "addr:housenumber":"/ 11",
    "addr:postcode":"2537",
    "addr:street":"Church St",
    "iso:country":"AU",
    "sg:address":"1/ 11 Church St",
    "sg:city":"Moruya",
    "sg:classifiers":[
        {
            "category":"Health Services",
            "subcategory":"Health Practitioner",
            "type":"Services"
        }
    ],
    "sg:phone":"+61 2 4474 0500",
    "sg:postcode":"2537",
    "sg:province":"NSW",
    "sg:tags":[
        "physiotherapist"
    ],
    "wof:name":"Cunningham Rachel",
    "wof:placetype":"venue"
},
  "geometry": {"coordinates":[150.082305908,-35.9093971252],"type":"Point"}
}