{
  "type": "Feature",
  "properties": {
    "addr:full":"Shop 2, 41 Pacific Hwy Ourimbah NSW 2258",
    "addr:housenumber":"shop;41",
    "addr:postcode":"2258",
    "addr:street":"Pacific Hwy",
    "iso:country":"AU",
    "sg:address":"Shop 2, 41 Pacific Hwy",
    "sg:city":"Ourimbah",
    "sg:classifiers":[
        {
            "category":"Food & Beverages",
            "subcategory":"Bakery",
            "type":"Retail Goods"
        }
    ],
    "sg:phone":"+61 2 4362 1955",
    "sg:postcode":"2258",
    "sg:province":"NSW",
    "sg:tags":[
        "baker"
    ],
    "wof:name":"Vilis Caf? & Bakery",
    "wof:placetype":"venue"
},
  "geometry": {"coordinates":[151.369903564,-33.3608551025],"type":"Point"}
}