{
  "type": "Feature",
  "properties": {
    "addr:full":"Shop 2 / 136 Main Street Lithgow NSW 2790",
    "addr:housenumber":"shop 2 / 136",
    "addr:postcode":"2790",
    "addr:street":"Main Street",
    "iso:country":"AU",
    "sg:address":"Shop 2 / 136",
    "sg:city":"Main Street Lithgow",
    "sg:classifiers":[
        {
            "category":"Shopping",
            "subcategory":"Music",
            "type":"Retail Goods"
        }
    ],
    "sg:phone":"+61 2 6351 2563",
    "sg:postcode":"2790",
    "sg:province":"NSW",
    "sg:tags":[
        "store"
    ],
    "wof:name":"Garys Sounds &#039;N Systems",
    "wof:placetype":"venue"
},
  "geometry": {"coordinates":[150.15481567399999,-33.4821166992],"type":"Point"}
}