{
  "type": "Feature",
  "properties": {
    "iso:country":"AU",
    "sg:address":"Unit 6/ 85 Broun Ave",
    "sg:city":"Morley",
    "sg:classifiers":[
        {
            "category":"Professional",
            "subcategory":"Computer Services",
            "type":"Services"
        }
    ],
    "sg:phone":"+61 8 9271 8188",
    "sg:postcode":"6062",
    "sg:province":"WA",
    "sg:tags":[
        "repairs",
        "upgrade",
        "equipment"
    ],
    "wof:name":"Net Solution Computers.",
    "wof:placetype":"venue"
},
  "geometry": {"coordinates":[115.904800415,-31.9014320374],"type":"Point"}
}