{
  "type": "Feature",
  "properties": {
    "addr:full":"1 Nanda St Marmong Point NSW 2284",
    "addr:housenumber":"1",
    "addr:postcode":"2284",
    "addr:street":"Nanda St",
    "iso:country":"AU",
    "sg:address":"1 Nanda St",
    "sg:city":"Marmong Point",
    "sg:classifiers":[
        {
            "category":"Autos & Motor Vehicles",
            "subcategory":"Boat Sales",
            "type":"Retail Goods"
        }
    ],
    "sg:phone":"+61 401 902 118",
    "sg:postcode":"2284",
    "sg:province":"NSW",
    "sg:tags":[
        "builder",
        "yacht",
        "repairer"
    ],
    "wof:name":"Coastal Shipwright Service",
    "wof:placetype":"venue"
},
  "geometry": {"coordinates":[151.619049072,-32.9781074524],"type":"Point"}
}