{
  "type": "Feature",
  "properties": {
    "iso:country":"AU",
    "sg:address":"Suite 18 81 Waratah Ave",
    "sg:city":"Dalkeith",
    "sg:classifiers":[
        {
            "category":"Health Services",
            "subcategory":"Health Practitioner",
            "type":"Services"
        }
    ],
    "sg:phone":"+61 8 9386 5333",
    "sg:postcode":"6009",
    "sg:province":"WA",
    "sg:tags":[
        "physiotherapist"
    ],
    "wof:name":"Andrew Bell",
    "wof:placetype":"venue"
},
  "geometry": {"coordinates":[115.798332,-31.994621],"type":"Point"}
}