{
  "type": "Feature",
  "properties": {
    "iso:country":"AU",
    "sg:address":"163 Wharf St",
    "sg:city":"Brisbane",
    "sg:classifiers":[
        {
            "category":"Professional",
            "subcategory":"Employment Agencies",
            "type":"Services"
        }
    ],
    "sg:phone":"+61 7 3220 3722",
    "sg:postcode":"4000",
    "sg:province":"QLD",
    "wof:name":"Trojan Workforce",
    "wof:placetype":"venue"
},
  "geometry": {"coordinates":[153.02749633799999,-27.4626064301],"type":"Point"}
}