{
  "type": "Feature",
  "properties": {
    "addr:full":"Cnr Princess Drv & Tramway Rd Morwell VIC 3840",
    "addr:postcode":"3840",
    "addr:street":"Princess Drv & Tramway Rd",
    "iso:country":"AU",
    "sg:address":"Cnr Princess Drv & Tramway Rd",
    "sg:city":"Morwell",
    "sg:classifiers":[
        {
            "category":"Education",
            "subcategory":"Junior College",
            "type":"Public Place"
        }
    ],
    "sg:phone":"+61 3 5133 9667",
    "sg:postcode":"3840",
    "sg:province":"VIC",
    "sg:tags":[
        "business"
    ],
    "wof:name":"Mackintosh International College",
    "wof:placetype":"venue"
},
  "geometry": {"coordinates":[146.42604064899999,-38.2941703796],"type":"Point"}
}