{
  "type": "Feature",
  "properties": {
    "iso:country":"AU",
    "sg:address":"2/ 91 Victoria St",
    "sg:city":"Victor Harbor",
    "sg:classifiers":[
        {
            "category":"Professional",
            "type":"Services"
        }
    ],
    "sg:phone":"+61 8 8551 0760",
    "sg:postcode":"5211",
    "sg:province":"SA",
    "sg:tags":[
        "transport"
    ],
    "wof:name":"Southern Communities Transport Scheme (Medi-Ride)",
    "wof:placetype":"venue"
},
  "geometry": {"coordinates":[138.611495972,-35.5574913025],"type":"Point"}
}