{
  "type": "Feature",
  "properties": {
    "iso:country":"AU",
    "sg:address":"Shp 9/ 132 Rouse St",
    "sg:city":"Port Melbourne",
    "sg:classifiers":[
        {
            "category":"Personal",
            "subcategory":"Beauty Salon",
            "type":"Services"
        }
    ],
    "sg:phone":"+61 3 9681 8922",
    "sg:postcode":"3207",
    "sg:province":"VIC",
    "wof:name":"Oxygen Skin Centre",
    "wof:placetype":"venue"
},
  "geometry": {"coordinates":[144.939514,-37.841969],"type":"Point"}
}