{
  "type": "Feature",
  "properties": {
    "addr:full":"Blue Gum Tennis Crt Disney St Brentwood WA 6153",
    "addr:postcode":"6153",
    "addr:street":"St",
    "iso:country":"AU",
    "sg:address":"Blue Gum Tennis Crt Disney St",
    "sg:city":"Brentwood",
    "sg:classifiers":[
        {
            "category":"Sports & Exercise",
            "subcategory":"Sports Center",
            "type":"Entertainment"
        }
    ],
    "sg:phone":"+61 8 9316 9705",
    "sg:postcode":"6153",
    "sg:province":"WA",
    "sg:tags":[
        "coach",
        "tennis"
    ],
    "wof:name":"Mastastroke Tennis System Blue Gum Park",
    "wof:placetype":"venue"
},
  "geometry": {"coordinates":[115.848488,-32.041599],"type":"Point"}
}