{
  "type": "Feature",
  "properties": {
    "addr:full":"82 Bage St Nundah QLD 4012",
    "addr:housenumber":"82",
    "addr:postcode":"4012",
    "addr:street":"Bage St",
    "iso:country":"AU",
    "sg:address":"82 Bage St",
    "sg:city":"Nundah",
    "sg:classifiers":[
        {
            "category":"Building & Trades",
            "subcategory":"Construction",
            "type":"Services"
        }
    ],
    "sg:phone":"+61 408 733 024",
    "sg:postcode":"4012",
    "sg:province":"QLD",
    "sg:tags":[
        "contractor"
    ],
    "wof:name":"Clacher Anthony J",
    "wof:placetype":"venue"
},
  "geometry": {"coordinates":[153.058303833,-27.4055156708],"type":"Point"}
}