{
  "type": "Feature",
  "properties": {
    "addr:full":"473 High St Maitland NSW 2320",
    "addr:housenumber":"473",
    "addr:postcode":"2320",
    "addr:street":"High St",
    "iso:country":"AU",
    "sg:address":"473 High St",
    "sg:city":"Maitland",
    "sg:classifiers":[
        {
            "category":"Fast Food",
            "type":"Food & Drink"
        }
    ],
    "sg:phone":"+61 2 4933 1717",
    "sg:postcode":"2320",
    "sg:province":"NSW",
    "sg:tags":[
        "away",
        "take"
    ],
    "wof:name":"Maneeya Thai Restaurant",
    "wof:placetype":"venue"
},
  "geometry": {"coordinates":[151.55323791500001,-32.7313041687],"type":"Point"}
}