{
  "type": "Feature",
  "properties": {
    "addr:full":"18 Valley View Crs Epping NSW 2121",
    "addr:housenumber":"18",
    "addr:postcode":"2121",
    "addr:street":"Valley View Crs",
    "iso:country":"AU",
    "sg:address":"18 Valley View Crs",
    "sg:city":"Epping",
    "sg:classifiers":[
        {
            "category":"Professional",
            "subcategory":"Management & Consulting",
            "type":"Services"
        }
    ],
    "sg:phone":"+61 2 9869 2411",
    "sg:postcode":"2121",
    "sg:province":"NSW",
    "sg:tags":[
        "consultant",
        "educational"
    ],
    "wof:name":"Margaret Gillespie Educational & Psychological Assessment",
    "wof:placetype":"venue"
},
  "geometry": {"coordinates":[151.082473755,-33.7727890015],"type":"Point"}
}