{
  "type": "Feature",
  "properties": {
    "addr:full":"13 Wolff Crt Windaroo QLD 4207",
    "addr:housenumber":"13",
    "addr:postcode":"4207",
    "addr:street":"Wolff Crt",
    "iso:country":"AU",
    "sg:address":"13 Wolff Crt",
    "sg:city":"Windaroo",
    "sg:classifiers":[
        {
            "category":"Building & Trades",
            "subcategory":"Pest Control",
            "type":"Services"
        }
    ],
    "sg:phone":"+61 7 3804 1915",
    "sg:postcode":"4207",
    "sg:province":"QLD",
    "wof:name":"A P Pest Control",
    "wof:placetype":"venue"
},
  "geometry": {"coordinates":[153.188964844,-27.7468338013],"type":"Point"}
}