{
  "type": "Feature",
  "properties": {
    "iso:country":"AU",
    "sg:address":"17 Tolson Rd",
    "sg:city":"Glenview",
    "sg:classifiers":[
        {
            "category":"Building & Trades",
            "subcategory":"Landscaping Services",
            "type":"Services"
        }
    ],
    "sg:phone":"+61 407 575 667",
    "sg:postcode":"4553",
    "sg:province":"QLD",
    "sg:tags":[
        "control",
        "weed"
    ],
    "wof:name":"Guilfoyle P & J",
    "wof:placetype":"venue"
},
  "geometry": {"coordinates":[152.988327,-26.75721],"type":"Point"}
}