{
  "type": "Feature",
  "properties": {
    "addr:full":"250 Lower Dandenong Rd Mordialloc VIC 3195",
    "addr:housenumber":"250",
    "addr:postcode":"3195",
    "addr:street":"Lower Dandenong Rd",
    "iso:country":"AU",
    "sg:address":"250 Lower Dandenong Rd",
    "sg:city":"Mordialloc",
    "sg:classifiers":[
        {
            "category":"Health Services",
            "subcategory":"Health Practitioner",
            "type":"Services"
        }
    ],
    "sg:phone":"+61 3 9580 4458",
    "sg:postcode":"3195",
    "sg:province":"VIC",
    "sg:tags":[
        "psychologist"
    ],
    "wof:name":"Pat's Pets",
    "wof:placetype":"venue"
},
  "geometry": {"coordinates":[145.09852600100001,-37.9853935242],"type":"Point"}
}