{
  "type": "Feature",
  "properties": {
    "addr:full":"Cnr Newcastle Rd & Melbourne St East Maitland NSW 2323",
    "addr:postcode":"2323",
    "addr:street":"Cnr Newcastle Rd & Melbourne St",
    "iso:country":"AU",
    "sg:address":"Cnr Newcastle Rd & Melbourne St",
    "sg:city":"East Maitland",
    "sg:classifiers":[
        {
            "category":"Wholesale",
            "subcategory":"Electrical",
            "type":"Manufacturing & Wholesale Goods"
        }
    ],
    "sg:phone":"+61 2 4934 3011",
    "sg:postcode":"2323",
    "sg:province":"NSW",
    "sg:tags":[
        "wholesaler",
        "mfrs",
        "accessory"
    ],
    "wof:name":"Cetnaj Pty Ltd",
    "wof:placetype":"venue"
},
  "geometry": {"coordinates":[151.58038330100001,-32.7475547791],"type":"Point"}
}