{
  "type": "Feature",
  "properties": {
    "iso:country":"AU",
    "sg:address":"25 Toohey Rd",
    "sg:city":"Wetherill Park",
    "sg:classifiers":[
        {
            "category":"Manufacturing",
            "subcategory":"Tools & Machinery",
            "type":"Manufacturing & Wholesale Goods"
        }
    ],
    "sg:phone":"+61 427 409 430",
    "sg:postcode":"2164",
    "sg:province":"NSW",
    "sg:tags":[
        "crankshaft",
        "cylinder",
        "grinding"
    ],
    "wof:name":"Hanks not Hinks",
    "wof:placetype":"venue"
},
  "geometry": {"coordinates":[150.88157653799999,-33.851348877],"type":"Point"}
}