{
  "type": "Feature",
  "properties": {
    "iso:country":"AU",
    "sg:address":"26 Collingwood St",
    "sg:city":"Osborne Park",
    "sg:classifiers":[
        {
            "category":"Manufacturing",
            "subcategory":"Apparel",
            "type":"Manufacturing & Wholesale Goods"
        }
    ],
    "sg:phone":"+61 8 9244 3114",
    "sg:postcode":"6017",
    "sg:province":"WA",
    "sg:tags":[
        "makers-up",
        "clothing"
    ],
    "wof:name":"Camel Clothing Manufacturers",
    "wof:placetype":"venue"
},
  "geometry": {"coordinates":[115.81590271,-31.903547287],"type":"Point"}
}