{
  "type": "Feature",
  "properties": {
    "addr:full":"Unit 14 1 Bennelong Rd Homebush Bay NSW 2127",
    "addr:housenumber":"1",
    "addr:postcode":"2127",
    "addr:street":"Bennelong Rd",
    "iso:country":"AU",
    "sg:address":"Unit 14 1 Bennelong Rd",
    "sg:city":"Homebush Bay",
    "sg:classifiers":[
        {
            "category":"Manufacturing",
            "subcategory":"Retail Goods",
            "type":"Manufacturing & Wholesale Goods"
        }
    ],
    "sg:phone":"+61 2 9748 1790",
    "sg:postcode":"2127",
    "sg:province":"NSW",
    "sg:tags":[
        "merchant",
        "tallow"
    ],
    "wof:name":"Premat Australia Pty Ltd",
    "wof:placetype":"venue"
},
  "geometry": {"coordinates":[151.07632446299999,-33.8350524902],"type":"Point"}
}