{
  "type": "Feature",
  "properties": {
    "addr:full":"Suite 3, 280 Dorset Rd Boronia VIC 3155",
    "addr:housenumber":"280",
    "addr:postcode":"3155",
    "addr:street":"Dorset Rd",
    "iso:country":"AU",
    "sg:address":"Suite 3, 280 Dorset Rd",
    "sg:city":"Boronia",
    "sg:classifiers":[
        {
            "category":"Professional",
            "subcategory":"Accounting & Tax Preparation",
            "type":"Services"
        }
    ],
    "sg:phone":"+61 3 9762 5366",
    "sg:postcode":"3155",
    "sg:province":"VIC",
    "sg:tags":[
        "accountant",
        "auditor"
    ],
    "wof:name":"Miller & Associates Pty Ltd",
    "wof:placetype":"venue"
},
  "geometry": {"coordinates":[145.285980225,-37.8584823608],"type":"Point"}
}