{
  "type": "Feature",
  "properties": {
    "addr:full":"Lvl 1/ 790 Hay St Perth WA 6000",
    "addr:housenumber":"/ 790",
    "addr:postcode":"6000",
    "addr:street":"Hay St",
    "iso:country":"AU",
    "sg:address":"Lvl 1/ 790 Hay St",
    "sg:city":"Perth",
    "sg:classifiers":[
        {
            "category":"Shopping",
            "subcategory":"Music",
            "type":"Retail Goods"
        }
    ],
    "sg:phone":"+61 8 9322 7171",
    "sg:postcode":"6000",
    "sg:province":"WA",
    "sg:tags":[
        "store"
    ],
    "wof:name":"CD Warehouse",
    "wof:placetype":"venue"
},
  "geometry": {"coordinates":[115.854873657,-31.9530029297],"type":"Point"}
}