{
  "type": "Feature",
  "properties": {
    "addr:full":"134 Kingston Rd Port Pirie SA 5540",
    "addr:housenumber":"134",
    "addr:postcode":"5540",
    "addr:street":"Kingston Rd",
    "iso:country":"AU",
    "sg:address":"134 Kingston Rd",
    "sg:city":"Port Pirie",
    "sg:classifiers":[
        {
            "category":"Building & Trades",
            "subcategory":"Construction",
            "type":"Services"
        }
    ],
    "sg:phone":"+61 8 8632 3414",
    "sg:postcode":"5540",
    "sg:province":"SA",
    "sg:tags":[
        "contractor"
    ],
    "wof:name":"Collins Greg",
    "wof:placetype":"venue"
},
  "geometry": {"coordinates":[137.99473571799999,-33.2038574219],"type":"Point"}
}