{
  "type": "Feature",
  "properties": {
    "iso:country":"AU",
    "sg:address":"138 Cumberland St",
    "sg:city":"The Rocks",
    "sg:classifiers":[
        {
            "category":"Professional",
            "subcategory":"Employment Agencies",
            "type":"Services"
        }
    ],
    "sg:phone":"+61 2 8298 3111",
    "sg:postcode":"2000",
    "sg:province":"NSW",
    "sg:tags":[
        "hire",
        "labour",
        "contractor"
    ],
    "wof:name":"Pinnacle Hospitality & Travel People",
    "wof:placetype":"venue"
},
  "geometry": {"coordinates":[151.206588745,-33.8605728149],"type":"Point"}
}