{
  "type": "Feature",
  "properties": {
    "addr:full":"16- 28 Macedon St Sunbury VIC 3429",
    "addr:housenumber":"28",
    "addr:postcode":"3429",
    "addr:street":"Macedon St",
    "iso:country":"AU",
    "sg:address":"16- 28 Macedon St",
    "sg:city":"Sunbury",
    "sg:classifiers":[
        {
            "category":"Health Services",
            "subcategory":"Doctor",
            "type":"Services"
        }
    ],
    "sg:phone":"+61 3 9744 8999",
    "sg:postcode":"3429",
    "sg:province":"VIC",
    "sg:tags":[
        "medical",
        "practitioner"
    ],
    "wof:name":"Sunbury Medical Centre",
    "wof:placetype":"venue"
},
  "geometry": {"coordinates":[144.73280334500001,-37.5778656006],"type":"Point"}
}