{
  "type": "Feature",
  "properties": {
    "iso:country":"AU",
    "sg:address":"7 Sydney St",
    "sg:city":"Mackay",
    "sg:classifiers":[
        {
            "category":"Professional",
            "subcategory":"Accounting & Tax Preparation",
            "type":"Services"
        }
    ],
    "sg:phone":"+61 7 4953 2533",
    "sg:postcode":"4740",
    "sg:province":"QLD",
    "sg:tags":[
        "consultant",
        "taxation"
    ],
    "wof:name":"Poole Williams",
    "wof:placetype":"venue"
},
  "geometry": {"coordinates":[149.187393,-21.139732],"type":"Point"}
}