{
  "type": "Feature",
  "properties": {
    "iso:country":"AU",
    "sg:address":"417 High St",
    "sg:city":"Preston",
    "sg:classifiers":[
        {
            "category":"Shopping",
            "subcategory":"Jewelry",
            "type":"Retail Goods"
        }
    ],
    "sg:phone":"+61 3 9471 8085",
    "sg:postcode":"3072",
    "sg:province":"VIC",
    "sg:tags":[
        "jeweller"
    ],
    "wof:name":"Kim Jeweller",
    "wof:placetype":"venue"
},
  "geometry": {"coordinates":[145.00357055699999,-37.7397041321],"type":"Point"}
}