{
  "type": "Feature",
  "properties": {
    "addr:full":"Shop 98 Waverley Gardens Shopping Centre Mulgrave VIC 3170",
    "addr:housenumber":"shop 98",
    "addr:postcode":"3170",
    "addr:street":"Waverley Gardens",
    "iso:country":"AU",
    "sg:address":"Shop 98 Waverley Gardens Shopping Centre",
    "sg:city":"Mulgrave",
    "sg:classifiers":[
        {
            "category":"Shopping",
            "subcategory":"Clothing, Apparel, & Fashions",
            "type":"Retail Goods"
        }
    ],
    "sg:phone":"+61 3 9540 3505",
    "sg:postcode":"3170",
    "sg:province":"VIC",
    "sg:tags":[
        "sportswear"
    ],
    "wof:name":"Boardworx",
    "wof:placetype":"venue"
},
  "geometry": {"coordinates":[145.12411499000001,-37.8844299316],"type":"Point"}
}