{
  "type": "Feature",
  "properties": {
    "iso:country":"AU",
    "sg:address":"Manns Rd",
    "sg:city":"Gosford West",
    "sg:classifiers":[
        {
            "category":"Autos & Motor Vehicles",
            "subcategory":"Auto Supplies",
            "type":"Retail Goods"
        }
    ],
    "sg:phone":"+61 2 4324 0661",
    "sg:postcode":"2250",
    "sg:province":"NSW",
    "sg:tags":[
        "part",
        "cycles",
        "accessory"
    ],
    "wof:name":"Blackeys Bikes",
    "wof:placetype":"venue"
},
  "geometry": {"coordinates":[151.31933593799999,-33.4242172241],"type":"Point"}
}