{
  "type": "Feature",
  "properties": {
    "iso:country":"AU",
    "sg:address":"58 Bridge St",
    "sg:city":"Muswellbrook",
    "sg:classifiers":[
        {
            "category":"Cafe",
            "type":"Food & Drink"
        }
    ],
    "sg:phone":"+61 2 6543 1702",
    "sg:postcode":"2333",
    "sg:province":"NSW",
    "wof:name":"Silver Grill Cafe",
    "wof:placetype":"venue"
},
  "geometry": {"coordinates":[150.88835144000001,-32.2648239136],"type":"Point"}
}