{
  "type": "Feature",
  "properties": {
    "iso:country":"AU",
    "sg:address":"Suite 1/ 7 Hertford St",
    "sg:city":"St Kilda East",
    "sg:classifiers":[
        {
            "category":"Real Estate",
            "subcategory":"Surveying",
            "type":"Services"
        }
    ],
    "sg:phone":"+61 3 9527 8770",
    "sg:postcode":"3183",
    "sg:province":"VIC",
    "sg:tags":[
        "surveyor",
        "quantity"
    ],
    "wof:name":"Alpine Cost Research",
    "wof:placetype":"venue"
},
  "geometry": {"coordinates":[145.00547790499999,-37.8645896912],"type":"Point"}
}