{
  "type": "Feature",
  "properties": {
    "addr:full":"176 Queen St Ayr QLD 4807",
    "addr:housenumber":"176",
    "addr:postcode":"4807",
    "addr:street":"Queen St",
    "iso:country":"AU",
    "sg:address":"176 Queen St",
    "sg:city":"Ayr",
    "sg:classifiers":[
        {
            "category":"Personal",
            "subcategory":"Beauty Salon",
            "type":"Services"
        }
    ],
    "sg:phone":"+61 7 4783 3616",
    "sg:postcode":"4807",
    "sg:province":"QLD",
    "sg:tags":[
        "hairdresser"
    ],
    "wof:name":"Headlines",
    "wof:placetype":"venue"
},
  "geometry": {"coordinates":[147.40443420400001,-19.577129364],"type":"Point"}
}