{
  "type": "Feature",
  "properties": {
    "iso:country":"AU",
    "sg:address":"13 Werril St",
    "sg:city":"Swan Hill",
    "sg:classifiers":[
        {
            "category":"Building & Trades",
            "subcategory":"Construction",
            "type":"Services"
        }
    ],
    "sg:phone":"+61 3 5032 4123",
    "sg:postcode":"3585",
    "sg:province":"VIC",
    "sg:tags":[
        "contractor"
    ],
    "wof:name":"D M & P M Carmichael",
    "wof:placetype":"venue"
},
  "geometry": {"coordinates":[143.560318,-35.359325],"type":"Point"}
}