{
  "type": "Feature",
  "properties": {
    "addr:full":"5 Wingara Drv Coffs Harbour NSW 2450",
    "addr:housenumber":"5",
    "addr:postcode":"2450",
    "addr:street":"Wingara Drv",
    "iso:country":"AU",
    "sg:address":"5 Wingara Drv",
    "sg:city":"Coffs Harbour",
    "sg:classifiers":[
        {
            "category":"Professional",
            "type":"Services"
        }
    ],
    "sg:phone":"+61 2 6652 5812",
    "sg:postcode":"2450",
    "sg:province":"NSW",
    "sg:tags":[
        "transport"
    ],
    "wof:name":"Fews Transport Pty Ltd",
    "wof:placetype":"venue"
},
  "geometry": {"coordinates":[153.100281,-30.316345],"type":"Point"}
}