{
  "type": "Feature",
  "properties": {
    "iso:country":"AU",
    "sg:address":"Unit 5, 42-46 South Hallam Rd",
    "sg:city":"Hallam",
    "sg:classifiers":[
        {
            "category":"Home & Garden",
            "subcategory":"Hardware",
            "type":"Retail Goods"
        }
    ],
    "sg:phone":"+61 3 9796 5531",
    "sg:postcode":"3803",
    "sg:province":"VIC",
    "sg:tags":[
        "compressor",
        "air"
    ],
    "wof:name":"Able Air Compressors",
    "wof:placetype":"venue"
},
  "geometry": {"coordinates":[145.27215576200001,-38.0125541687],"type":"Point"}
}