{
  "type": "Feature",
  "properties": {
    "addr:full":"30 Palmerston Rd Ferntree Gully VIC 3156",
    "addr:housenumber":"30",
    "addr:postcode":"3156",
    "addr:street":"Palmerston Rd",
    "iso:country":"AU",
    "sg:address":"30 Palmerston Rd",
    "sg:city":"Ferntree Gully",
    "sg:classifiers":[
        {
            "category":"Professional",
            "subcategory":"Accounting & Tax Preparation",
            "type":"Services"
        }
    ],
    "sg:phone":"+61 3 9752 8514",
    "sg:postcode":"3156",
    "sg:province":"VIC",
    "sg:tags":[
        "accountant",
        "auditor"
    ],
    "wof:name":"Scharnbock V.J & Associates",
    "wof:placetype":"venue"
},
  "geometry": {"coordinates":[145.28082275400001,-37.9117240906],"type":"Point"}
}