{
  "type": "Feature",
  "properties": {
    "addr:full":"McLeod St Murwillumbah NSW 2484",
    "addr:postcode":"2484",
    "addr:street":"Mcleod St",
    "iso:country":"AU",
    "sg:address":"McLeod St",
    "sg:city":"Murwillumbah",
    "sg:classifiers":[
        {
            "category":"Farming",
            "subcategory":"Crops",
            "type":"Manufacturing & Wholesale Goods"
        }
    ],
    "sg:phone":"+61 2 6672 2244",
    "sg:postcode":"2484",
    "sg:province":"NSW",
    "sg:tags":[
        "sugarcane",
        "mill",
        "grower"
    ],
    "wof:name":"New South Wales Sugar Milling Co-Operative Ltd",
    "wof:placetype":"venue"
},
  "geometry": {"coordinates":[153.434249878,-28.3152313232],"type":"Point"}
}