{
  "type": "Feature",
  "properties": {
    "addr:full":"Hume Hwy Wangaratta VIC 3677",
    "addr:postcode":"3677",
    "addr:street":"Hume Hwy",
    "iso:country":"AU",
    "sg:address":"Hume Hwy",
    "sg:city":"Wangaratta",
    "sg:classifiers":[
        {
            "category":"Autos & Motor Vehicles",
            "subcategory":"Auto Supplies",
            "type":"Retail Goods"
        }
    ],
    "sg:phone":"+61 3 5721 8372",
    "sg:postcode":"3677",
    "sg:province":"VIC",
    "sg:tags":[
        "tyre"
    ],
    "wof:name":"Kmart Tyre & Auto Service",
    "wof:placetype":"venue"
},
  "geometry": {"coordinates":[146.34605407699999,-36.3896331787],"type":"Point"}
}