{
  "type": "Feature",
  "properties": {
    "addr:full":"43 Moreton Bay Drv Highton VIC 3216",
    "addr:housenumber":"43",
    "addr:postcode":"3216",
    "addr:street":"Moreton Bay Drv",
    "iso:country":"AU",
    "sg:address":"43 Moreton Bay Drv",
    "sg:city":"Highton",
    "sg:classifiers":[
        {
            "category":"Professional",
            "subcategory":"Business Services",
            "type":"Services"
        }
    ],
    "sg:phone":"+61 418 521 599",
    "sg:postcode":"3216",
    "sg:province":"VIC",
    "sg:tags":[
        "drafting"
    ],
    "wof:name":"Arcsync",
    "wof:placetype":"venue"
},
  "geometry": {"coordinates":[144.31585693400001,-38.1788902283],"type":"Point"}
}