{
  "type": "Feature",
  "properties": {
    "addr:full":"295 Pocket Rd Billinudgel NSW 2483",
    "addr:housenumber":"295",
    "addr:postcode":"2483",
    "addr:street":"Pocket Rd",
    "iso:country":"AU",
    "sg:address":"295 Pocket Rd",
    "sg:city":"Billinudgel",
    "sg:classifiers":[
        {
            "category":"Home & Garden",
            "subcategory":"Building Materials",
            "type":"Retail Goods"
        }
    ],
    "sg:phone":"+61 2 6680 2694",
    "sg:postcode":"2483",
    "sg:province":"NSW",
    "sg:tags":[
        "fencing"
    ],
    "wof:name":"Dave Clothier Fencing & 4WD Slashing Contractor",
    "wof:placetype":"venue"
},
  "geometry": {"coordinates":[153.51637268100001,-28.4881706238],"type":"Point"}
}