{
  "type": "Feature",
  "properties": {
    "addr:full":"43 Jane St Cunnamulla QLD 4490",
    "addr:housenumber":"43",
    "addr:postcode":"4490",
    "addr:street":"Jane St",
    "iso:country":"AU",
    "sg:address":"43 Jane St",
    "sg:city":"Cunnamulla",
    "sg:classifiers":[
        {
            "category":"Food & Beverages",
            "subcategory":"Bakery",
            "type":"Retail Goods"
        }
    ],
    "sg:phone":"+61 7 4655 1270",
    "sg:postcode":"4490",
    "sg:province":"QLD",
    "sg:tags":[
        "baker"
    ],
    "wof:name":"Cunnamulla Bakery Cafe",
    "wof:placetype":"venue"
},
  "geometry": {"coordinates":[145.687744141,-28.0657310486],"type":"Point"}
}