{
  "type": "Feature",
  "properties": {
    "addr:full":"572 Burwood Rd Hawthorn VIC 3122",
    "addr:housenumber":"572",
    "addr:postcode":"3122",
    "addr:street":"Burwood Rd",
    "iso:country":"AU",
    "sg:address":"572 Burwood Rd",
    "sg:city":"Hawthorn",
    "sg:classifiers":[
        {
            "category":"Shopping",
            "subcategory":"Computers & Home Electronics",
            "type":"Retail Goods"
        }
    ],
    "sg:phone":"+61 3 9819 1224",
    "sg:postcode":"3122",
    "sg:province":"VIC",
    "sg:tags":[
        "equipment",
        "multimedia"
    ],
    "wof:name":"Medi World Pty Ltd",
    "wof:placetype":"venue"
},
  "geometry": {"coordinates":[145.04403686500001,-37.8237342834],"type":"Point"}
}