{
  "type": "Feature",
  "properties": {
    "iso:country":"AU",
    "sg:address":"Level 3 551 Pacific Hwy",
    "sg:city":"St Leonards",
    "sg:classifiers":[
        {
            "category":"Organizations",
            "subcategory":"Professional Association",
            "type":"Services"
        }
    ],
    "sg:phone":"+61 2 9439 6209",
    "sg:postcode":"2065",
    "sg:province":"NSW",
    "sg:tags":[
        "organisation",
        "business"
    ],
    "wof:name":"Baking Industry Association (N.S.W. Employers)",
    "wof:placetype":"venue"
},
  "geometry": {"coordinates":[151.19801330600001,-33.8245010376],"type":"Point"}
}