{
  "type": "Feature",
  "properties": {
    "addr:full":"1 Katherine St Fullarton SA 5063",
    "addr:housenumber":"1",
    "addr:postcode":"5063",
    "addr:street":"Katherine St",
    "iso:country":"AU",
    "sg:address":"1 Katherine St",
    "sg:city":"Fullarton",
    "sg:classifiers":[
        {
            "category":"Arts & Performance",
            "subcategory":"Music",
            "type":"Entertainment"
        }
    ],
    "sg:phone":"+61 412 184 982",
    "sg:postcode":"5063",
    "sg:province":"SA",
    "sg:tags":[
        "mobile",
        "jockey",
        "disc"
    ],
    "wof:name":"Mane Events",
    "wof:placetype":"venue"
},
  "geometry": {"coordinates":[138.634277344,-34.9520454407],"type":"Point"}
}