{
  "type": "Feature",
  "properties": {
    "addr:full":"12 Archer St Rockhampton QLD 4700",
    "addr:housenumber":"12",
    "addr:postcode":"4700",
    "addr:street":"Archer St",
    "iso:country":"AU",
    "sg:address":"12 Archer St",
    "sg:city":"Rockhampton",
    "sg:classifiers":[
        {
            "category":"Travel",
            "subcategory":"Hostel",
            "type":"Entertainment"
        }
    ],
    "sg:phone":"+61 7 4922 1532",
    "sg:postcode":"4700",
    "sg:province":"QLD",
    "sg:tags":[
        "home"
    ],
    "wof:name":"QCWA",
    "wof:placetype":"venue"
},
  "geometry": {"coordinates":[150.49520874000001,-23.3847236633],"type":"Point"}
}