{
  "type": "Feature",
  "properties": {
    "iso:country":"AU",
    "sg:address":"Lvl 1/ 868 Anzac Pde",
    "sg:city":"Maroubra",
    "sg:classifiers":[
        {
            "category":"Personal",
            "subcategory":"Beauty Salon",
            "type":"Services"
        }
    ],
    "sg:phone":"+61 2 9344 4999",
    "sg:postcode":"2035",
    "sg:province":"NSW",
    "wof:name":"Self Face & Body",
    "wof:placetype":"venue"
},
  "geometry": {"coordinates":[151.23953247099999,-33.9406738281],"type":"Point"}
}