{
  "type": "Feature",
  "properties": {
    "addr:full":"30 Canton Beach Rd Toukley NSW 2263",
    "addr:housenumber":"30",
    "addr:postcode":"2263",
    "addr:street":"Canton Beach Rd",
    "iso:country":"AU",
    "sg:address":"30 Canton Beach Rd",
    "sg:city":"Toukley",
    "sg:classifiers":[
        {
            "category":"Cafe",
            "type":"Food & Drink"
        }
    ],
    "sg:phone":"+61 2 4396 5314",
    "sg:postcode":"2263",
    "sg:province":"NSW",
    "wof:name":"Bevs Donut & Coffee Shop",
    "wof:placetype":"venue"
},
  "geometry": {"coordinates":[151.54075599999999,-33.264404],"type":"Point"}
}