{
  "type": "Feature",
  "properties": {
    "addr:full":"Unit 6/ 1 Bounty Cls Tuggerah Business Park Tuggerah NSW 2259",
    "addr:housenumber":"1;business",
    "addr:postcode":"2259",
    "addr:street":"Bounty Cls",
    "iso:country":"AU",
    "sg:address":"Unit 6/ 1",
    "sg:city":"Bounty Cls Tuggerah Business Park Tuggerah",
    "sg:classifiers":[
        {
            "category":"Professional",
            "subcategory":"Computer Services",
            "type":"Services"
        }
    ],
    "sg:phone":"+61 2 4353 4713",
    "sg:postcode":"2259",
    "sg:province":"NSW",
    "sg:tags":[
        "repairs",
        "upgrade",
        "equipment"
    ],
    "wof:name":"Coastec Computers",
    "wof:placetype":"venue"
},
  "geometry": {"coordinates":[151.420410156,-33.3050003052],"type":"Point"}
}