{
  "type": "Feature",
  "properties": {
    "iso:country":"AU",
    "sg:address":"7/ 102 Wises Rd",
    "sg:city":"Maroochydore",
    "sg:classifiers":[
        {
            "category":"Health Services",
            "subcategory":"Doctor",
            "type":"Services"
        }
    ],
    "sg:phone":"+61 7 5443 9228",
    "sg:postcode":"4558",
    "sg:province":"QLD",
    "sg:tags":[
        "medical",
        "practitioner"
    ],
    "wof:name":"Draper Dan Dr",
    "wof:placetype":"venue"
},
  "geometry": {"coordinates":[153.08258056599999,-26.6709346771],"type":"Point"}
}