{
  "type": "Feature",
  "properties": {
    "iso:country":"AU",
    "sg:address":"10 Birdwood Ave",
    "sg:city":"Stanhope",
    "sg:classifiers":[
        {
            "category":"Food & Beverages",
            "subcategory":"Fruits & Vegetables",
            "type":"Retail Goods"
        }
    ],
    "sg:phone":"+61 3 5857 2667",
    "sg:postcode":"3623",
    "sg:province":"VIC",
    "sg:tags":[
        "greengrocer",
        "fruiterer"
    ],
    "wof:name":"Andersons Fruit & Veg Stanhope",
    "wof:placetype":"venue"
},
  "geometry": {"coordinates":[144.98306274399999,-36.4460449219],"type":"Point"}
}