{
  "type": "Feature",
  "properties": {
    "iso:country":"AU",
    "sg:address":"11 Hallstrom St",
    "sg:city":"Wetherill Park",
    "sg:classifiers":[
        {
            "category":"Manufacturing",
            "subcategory":"Electronics",
            "type":"Manufacturing & Wholesale Goods"
        }
    ],
    "sg:phone":"+61 2 9756 1511",
    "sg:postcode":"2164",
    "sg:province":"NSW",
    "sg:tags":[
        "oven",
        "microwave"
    ],
    "wof:name":"Blanco",
    "wof:placetype":"venue"
},
  "geometry": {"coordinates":[150.88507080100001,-33.8448448181],"type":"Point"}
}