{
  "type": "Feature",
  "properties": {
    "addr:full":"20 Watson St Ryde NSW 2112",
    "addr:housenumber":"20",
    "addr:postcode":"2112",
    "addr:street":"Watson St",
    "iso:country":"AU",
    "sg:address":"20 Watson St",
    "sg:city":"Ryde",
    "sg:classifiers":[
        {
            "category":"Landmark",
            "subcategory":"Scenic View",
            "type":"Public Place"
        }
    ],
    "sg:phone":"+61 2 9808 1042",
    "sg:postcode":"2112",
    "sg:province":"NSW",
    "sg:tags":[
        "staircase",
        "handrail"
    ],
    "wof:name":"Brian & Philip Walsh",
    "wof:placetype":"venue"
},
  "geometry": {"coordinates":[151.10235595699999,-33.8259315491],"type":"Point"}
}