{
  "type": "Feature",
  "properties": {
    "iso:country":"AU",
    "sg:address":"616 Ballina Rd",
    "sg:city":"Goonellabah",
    "sg:classifiers":[
        {
            "category":"Health Services",
            "subcategory":"Health Practitioner",
            "type":"Services"
        }
    ],
    "sg:phone":"+61 2 6625 0000",
    "sg:postcode":"2480",
    "sg:province":"NSW",
    "sg:tags":[
        "psychologist"
    ],
    "wof:name":"Jill Sloan",
    "wof:placetype":"venue"
},
  "geometry": {"coordinates":[153.33895874000001,-28.8122406006],"type":"Point"}
}