{
  "type": "Feature",
  "properties": {
    "addr:full":"58- 60 Easey St Collingwood VIC 3066",
    "addr:housenumber":"60",
    "addr:postcode":"3066",
    "addr:street":"Easey St",
    "iso:country":"AU",
    "sg:address":"58- 60 Easey St",
    "sg:city":"Collingwood",
    "sg:classifiers":[
        {
            "category":"Manufacturing",
            "subcategory":"Apparel",
            "type":"Manufacturing & Wholesale Goods"
        }
    ],
    "sg:phone":"+61 1800 623 423",
    "sg:postcode":"3066",
    "sg:province":"VIC",
    "sg:tags":[
        "wholesaler",
        "mfrs",
        "footwear"
    ],
    "wof:name":"Birkenstock Australia Pty Ltd",
    "wof:placetype":"venue"
},
  "geometry": {"coordinates":[144.98739624000001,-37.7976989746],"type":"Point"}
}