{
  "type": "Feature",
  "properties": {
    "addr:full":"Level 6, 246 Bourke St Melbourne VIC 3000",
    "addr:housenumber":"246",
    "addr:postcode":"3000",
    "addr:street":"Bourke St",
    "iso:country":"AU",
    "sg:address":"Level 6, 246 Bourke St",
    "sg:city":"Melbourne",
    "sg:classifiers":[
        {
            "category":"Shopping",
            "subcategory":"Party Supplies",
            "type":"Retail Goods"
        }
    ],
    "sg:phone":"+61 3 9654 0999",
    "sg:postcode":"3000",
    "sg:province":"VIC",
    "sg:tags":[
        "children's"
    ],
    "wof:name":"Suzan Johnston Training Organization",
    "wof:placetype":"venue"
},
  "geometry": {"coordinates":[144.965774536,-37.8133468628],"type":"Point"}
}