{
  "type": "Feature",
  "properties": {
    "addr:full":"29 Sheaffe St Cloncurry QLD 4824",
    "addr:housenumber":"29",
    "addr:postcode":"4824",
    "addr:street":"Sheaffe St",
    "iso:country":"AU",
    "sg:address":"29 Sheaffe St",
    "sg:city":"Cloncurry",
    "sg:classifiers":[
        {
            "category":"Professional",
            "subcategory":"Computer Services",
            "type":"Services"
        }
    ],
    "sg:phone":"+61 429 421 746",
    "sg:postcode":"4824",
    "sg:province":"QLD",
    "sg:tags":[
        "tele-communications",
        "consultant"
    ],
    "wof:name":"Ernst Communications",
    "wof:placetype":"venue"
},
  "geometry": {"coordinates":[140.50552400000001,-20.704922],"type":"Point"}
}