{
  "type": "Feature",
  "properties": {
    "iso:country":"AU",
    "sg:address":"Rocklands Drv Darwin Private Hospital",
    "sg:city":"Tiwi",
    "sg:classifiers":[
        {
            "category":"Wholesale",
            "subcategory":"Medical Equipment & Supplies",
            "type":"Manufacturing & Wholesale Goods"
        }
    ],
    "sg:phone":"+61 8 8945 6177",
    "sg:postcode":"0810",
    "sg:province":"NT",
    "sg:tags":[
        "dental"
    ],
    "wof:name":"Medical Equipment Management",
    "wof:placetype":"venue"
},
  "geometry": {"coordinates":[130.87594604500001,-12.3598403931],"type":"Point"}
}