{
  "type": "Feature",
  "properties": {
    "iso:country":"AU",
    "sg:address":"171 Five Islands Rd",
    "sg:city":"Unanderra",
    "sg:classifiers":[
        {
            "category":"Manufacturing",
            "subcategory":"Motor Vehicles & Parts",
            "type":"Manufacturing & Wholesale Goods"
        }
    ],
    "sg:phone":"+61 413 956 101",
    "sg:postcode":"2526",
    "sg:province":"NSW",
    "sg:tags":[
        "engine",
        "equipment",
        "diesel"
    ],
    "wof:name":"Doug Wheeler Truck Repairs",
    "wof:placetype":"venue"
},
  "geometry": {"coordinates":[150.860671997,-34.4569664001],"type":"Point"}
}