{
  "type": "Feature",
  "properties": {
    "addr:full":"206 High St Ashburton VIC 3147",
    "addr:housenumber":"206",
    "addr:postcode":"3147",
    "addr:street":"High St",
    "iso:country":"AU",
    "sg:address":"206 High St",
    "sg:city":"Ashburton",
    "sg:classifiers":[
        {
            "category":"Fast Food",
            "type":"Food & Drink"
        }
    ],
    "sg:phone":"+61 3 9885 9044",
    "sg:postcode":"3147",
    "sg:province":"VIC",
    "sg:tags":[
        "away",
        "take"
    ],
    "wof:name":"Charcoal Chicken Haven",
    "wof:placetype":"venue"
},
  "geometry": {"coordinates":[145.07901000999999,-37.8634529114],"type":"Point"}
}