{
  "type": "Feature",
  "properties": {
    "addr:full":"51 Woodville Rd Woodville SA 5011",
    "addr:housenumber":"51",
    "addr:postcode":"5011",
    "addr:street":"Woodville Rd",
    "iso:country":"AU",
    "sg:address":"51 Woodville Rd",
    "sg:city":"Woodville",
    "sg:classifiers":[
        {
            "category":"Banks & Credit Unions",
            "subcategory":"Bank",
            "type":"Services"
        }
    ],
    "sg:phone":"+61 8 8244 1155",
    "sg:postcode":"5011",
    "sg:province":"SA",
    "sg:tags":[
        "broker",
        "mortgage"
    ],
    "wof:name":"Jet Lending",
    "wof:placetype":"venue"
},
  "geometry": {"coordinates":[138.53610229500001,-34.879524231],"type":"Point"}
}