{
  "type": "Feature",
  "properties": {
    "addr:full":"115 Powlett St Kilmore VIC 3764",
    "addr:housenumber":"115",
    "addr:postcode":"3764",
    "addr:street":"Powlett St",
    "iso:country":"AU",
    "sg:address":"115 Powlett St",
    "sg:city":"Kilmore",
    "sg:classifiers":[
        {
            "category":"Home & Garden",
            "subcategory":"Garden Supply",
            "type":"Retail Goods"
        }
    ],
    "sg:phone":"+61 3 5782 1088",
    "sg:postcode":"3764",
    "sg:province":"VIC",
    "sg:tags":[
        "equipment"
    ],
    "wof:name":"Mitre 10 Solutions",
    "wof:placetype":"venue"
},
  "geometry": {"coordinates":[144.94993591299999,-37.3071517944],"type":"Point"}
}