{
  "type": "Feature",
  "properties": {
    "addr:full":"44 Katandra Crs Bellbird Park QLD 4300",
    "addr:housenumber":"44",
    "addr:postcode":"4300",
    "addr:street":"Katandra Crs",
    "iso:country":"AU",
    "sg:address":"44 Katandra Crs",
    "sg:city":"Bellbird Park",
    "sg:classifiers":[
        {
            "category":"Building & Trades",
            "subcategory":"Construction",
            "type":"Services"
        }
    ],
    "sg:phone":"+61 7 3818 9522",
    "sg:postcode":"4300",
    "sg:province":"QLD",
    "sg:tags":[
        "earth",
        "excavating",
        "moving",
        "contractor"
    ],
    "wof:name":"Don Meredith Plant Hire",
    "wof:placetype":"venue"
},
  "geometry": {"coordinates":[152.87286376899999,-27.646780014],"type":"Point"}
}