{
  "type": "Feature",
  "properties": {
    "addr:full":"Lvl 1, 47 Kiora Rd Miranda NSW 2228",
    "addr:housenumber":"47",
    "addr:postcode":"2228",
    "addr:street":"Kiora Rd",
    "iso:country":"AU",
    "sg:address":"Lvl 1, 47 Kiora Rd",
    "sg:city":"Miranda",
    "sg:classifiers":[
        {
            "category":"Banks & Credit Unions",
            "subcategory":"Bank",
            "type":"Services"
        }
    ],
    "sg:phone":"+61 2 9526 7888",
    "sg:postcode":"2228",
    "sg:province":"NSW",
    "sg:tags":[
        "broker",
        "mortgage"
    ],
    "wof:name":"Mortgage Choice",
    "wof:placetype":"venue"
},
  "geometry": {"coordinates":[151.10194397000001,-34.0349388123],"type":"Point"}
}