{
  "type": "Feature",
  "properties": {
    "iso:country":"AU",
    "sg:address":"Berry's Beach Rd",
    "sg:city":"Ventnor",
    "sg:classifiers":[
        {
            "category":"Farming",
            "subcategory":"Vineyard",
            "type":"Manufacturing & Wholesale Goods"
        }
    ],
    "sg:phone":"+61 3 5956 8465",
    "sg:postcode":"3922",
    "sg:province":"VIC",
    "sg:tags":[
        "winery"
    ],
    "wof:name":"Phillip Island Vineyard & Winery",
    "wof:placetype":"venue"
},
  "geometry": {"coordinates":[145.229812622,-38.4509963989],"type":"Point"}
}