{
  "type": "Feature",
  "properties": {
    "iso:country":"AU",
    "sg:address":"1/ 45 King St",
    "sg:city":"Warrawong",
    "sg:classifiers":[
        {
            "category":"Personal",
            "subcategory":"Massage",
            "type":"Services"
        }
    ],
    "sg:phone":"+61 2 4274 2781",
    "sg:postcode":"2502",
    "sg:province":"NSW",
    "sg:tags":[
        "therapy"
    ],
    "wof:name":"Janelle Ward",
    "wof:placetype":"venue"
},
  "geometry": {"coordinates":[150.88758899999999,-34.483433],"type":"Point"}
}