{
  "type": "Feature",
  "properties": {
    "addr:full":"17 Chatham Ave Taree NSW 2430",
    "addr:housenumber":"17",
    "addr:postcode":"2430",
    "addr:street":"Chatham Ave",
    "iso:country":"AU",
    "sg:address":"17 Chatham Ave",
    "sg:city":"Taree",
    "sg:classifiers":[
        {
            "category":"Education",
            "subcategory":"School",
            "type":"Public Place"
        }
    ],
    "sg:phone":"+61 2 6551 1081",
    "sg:postcode":"2430",
    "sg:province":"NSW",
    "sg:tags":[
        "state",
        "-",
        "nsw"
    ],
    "wof:name":"Chatham Primary School",
    "wof:placetype":"venue"
},
  "geometry": {"coordinates":[152.482956,-31.900192],"type":"Point"}
}