{
  "type": "Feature",
  "properties": {
    "iso:country":"AU",
    "sg:address":"6 Kennedy St",
    "sg:city":"Melville",
    "sg:classifiers":[
        {
            "category":"Education",
            "subcategory":"Music School",
            "type":"Public Place"
        }
    ],
    "sg:phone":"+61 8 9330 4177",
    "sg:postcode":"6156",
    "sg:province":"WA",
    "sg:tags":[
        "hi-fi",
        "equipment",
        "wholesaler",
        "mfrs"
    ],
    "wof:name":"Audiofurn",
    "wof:placetype":"venue"
},
  "geometry": {"coordinates":[115.80371100000001,-32.034588],"type":"Point"}
}