{
  "type": "Feature",
  "properties": {
    "iso:country":"AU",
    "sg:address":"175 Main St",
    "sg:city":"Mornington",
    "sg:classifiers":[
        {
            "category":"Shopping",
            "subcategory":"Mobile Phones",
            "type":"Retail Goods"
        }
    ],
    "sg:phone":"+61 3 5976 1500",
    "sg:postcode":"3931",
    "sg:province":"VIC",
    "sg:tags":[
        "telephone",
        "accessory"
    ],
    "wof:name":"Cell Point Communications P/L",
    "wof:placetype":"venue"
},
  "geometry": {"coordinates":[145.039993286,-38.2219161987],"type":"Point"}
}