{
  "type": "Feature",
  "properties": {
    "addr:full":"Suite 7, Level 10 , Australia Fair Southport QLD 4215",
    "addr:postcode":"4215",
    "addr:street":"Level",
    "iso:country":"AU",
    "sg:address":"Suite 7, Level 10",
    "sg:city":", Australia Fair Southport",
    "sg:classifiers":[
        {
            "category":"Wholesale",
            "subcategory":"Medical Equipment & Supplies",
            "type":"Manufacturing & Wholesale Goods"
        }
    ],
    "sg:phone":"+61 7 5591 7688",
    "sg:postcode":"4215",
    "sg:province":"QLD",
    "sg:tags":[
        "aids",
        "hearing"
    ],
    "wof:name":"AAA AudioActive Hearing Aids",
    "wof:placetype":"venue"
},
  "geometry": {"coordinates":[153.411575317,-27.9700565338],"type":"Point"}
}