{
  "type": "Feature",
  "properties": {
    "iso:country":"AU",
    "sg:address":"3 Bow Pl",
    "sg:city":"Fadden",
    "sg:classifiers":[
        {
            "category":"Building & Trades",
            "subcategory":"Landscaping Services",
            "type":"Services"
        }
    ],
    "sg:phone":"+61 2 6291 6183",
    "sg:postcode":"2904",
    "sg:province":"ACT",
    "sg:tags":[
        "designer",
        "landscape",
        "contractor"
    ],
    "wof:name":"Bruce Finlayson Landscaping Services",
    "wof:placetype":"venue"
},
  "geometry": {"coordinates":[149.11859130900001,-35.3998069763],"type":"Point"}
}