{
  "type": "Feature",
  "properties": {
    "addr:full":"435 Crown St Surry Hills NSW 2010",
    "addr:housenumber":"435",
    "addr:postcode":"2010",
    "addr:street":"Crown St",
    "iso:country":"AU",
    "sg:address":"435 Crown St",
    "sg:city":"Surry Hills",
    "sg:classifiers":[
        {
            "category":"Food & Beverages",
            "subcategory":"Supermarket",
            "type":"Retail Goods"
        }
    ],
    "sg:phone":"+61 2 9319 5211",
    "sg:postcode":"2010",
    "sg:province":"NSW",
    "sg:tags":[
        "grocery",
        "store"
    ],
    "wof:name":"IGA Xpress",
    "wof:placetype":"venue"
},
  "geometry": {"coordinates":[151.213546753,-33.8868370056],"type":"Point"}
}