{
  "type": "Feature",
  "properties": {
    "iso:country":"AU",
    "sg:address":"251 Richmond Rd",
    "sg:city":"Morningside",
    "sg:classifiers":[
        {
            "category":"Health Services",
            "subcategory":"Dentist",
            "type":"Services"
        }
    ],
    "sg:phone":"+61 7 3399 6988",
    "sg:postcode":"4170",
    "sg:province":"QLD",
    "wof:name":"Wright Patricia",
    "wof:placetype":"venue"
},
  "geometry": {"coordinates":[153.083328247,-27.473236084],"type":"Point"}
}