{
  "type": "Feature",
  "properties": {
    "iso:country":"AU",
    "sg:address":"181 Seacombe Rd",
    "sg:city":"South Brighton",
    "sg:classifiers":[
        {
            "category":"Home & Garden",
            "subcategory":"Garden Supply",
            "type":"Retail Goods"
        }
    ],
    "sg:phone":"+61 8 8377 1200",
    "sg:postcode":"5048",
    "sg:province":"SA",
    "sg:tags":[
        "equipment"
    ],
    "wof:name":"Hydro Warehouse",
    "wof:placetype":"venue"
},
  "geometry": {"coordinates":[138.532639,-35.029633],"type":"Point"}
}