{
  "type": "Feature",
  "properties": {
    "addr:full":"7 Cameron St Alice Springs NT 0870",
    "addr:housenumber":"7",
    "addr:postcode":"nt 0870",
    "addr:street":"Cameron St",
    "iso:country":"AU",
    "sg:address":"7 Cameron St",
    "sg:city":"Alice Springs",
    "sg:classifiers":[
        {
            "category":"Wholesale",
            "subcategory":"Meat",
            "type":"Manufacturing & Wholesale Goods"
        }
    ],
    "sg:phone":"+61 8 8953 6912",
    "sg:postcode":"0870",
    "sg:province":"NT",
    "sg:tags":[
        "packing",
        "exporting"
    ],
    "wof:name":"Waite River Holdings Pty Ltd",
    "wof:placetype":"venue"
},
  "geometry": {"coordinates":[133.86978149399999,-23.6730575562],"type":"Point"}
}