{
  "type": "Feature",
  "properties": {
    "addr:full":"37 Wyong Rd Tumbi Umbi NSW 2261",
    "addr:housenumber":"37",
    "addr:postcode":"2261",
    "addr:street":"Wyong Rd",
    "iso:country":"AU",
    "sg:address":"37 Wyong Rd",
    "sg:city":"Tumbi Umbi",
    "sg:classifiers":[
        {
            "category":"Professional",
            "subcategory":"Computer Services",
            "type":"Services"
        }
    ],
    "sg:phone":"+61 2 4389 1858",
    "sg:postcode":"2261",
    "sg:province":"NSW",
    "sg:tags":[
        "repairs",
        "upgrade",
        "equipment"
    ],
    "wof:name":"LDR Computers",
    "wof:placetype":"venue"
},
  "geometry": {"coordinates":[151.446686,-33.362431],"type":"Point"}
}