{
  "type": "Feature",
  "properties": {
    "addr:full":"Level 1, 231 Burwood Rd Hawthorn VIC 3122",
    "addr:housenumber":"231",
    "addr:postcode":"3122",
    "addr:street":"Burwood Rd",
    "iso:country":"AU",
    "sg:address":"Level 1, 231 Burwood Rd",
    "sg:city":"Hawthorn",
    "sg:classifiers":[
        {
            "category":"Professional",
            "subcategory":"Accounting & Tax Preparation",
            "type":"Services"
        }
    ],
    "sg:phone":"+61 3 9420 7700",
    "sg:postcode":"3122",
    "sg:province":"VIC",
    "sg:tags":[
        "bookkeeping"
    ],
    "wof:name":"Accounts Direct Pty Ltd",
    "wof:placetype":"venue"
},
  "geometry": {"coordinates":[145.03021240199999,-37.821849823],"type":"Point"}
}