{
  "type": "Feature",
  "properties": {
    "addr:full":"2nd Floor, Cnr George & Church Sts Parramatta NSW 2150",
    "addr:housenumber":"cnr",
    "addr:postcode":"2150",
    "addr:street":"George & Church Sts",
    "iso:country":"AU",
    "sg:address":"2nd Floor, Cnr George & Church Sts",
    "sg:city":"Parramatta",
    "sg:classifiers":[
        {
            "category":"Health Services",
            "subcategory":"Doctor",
            "type":"Services"
        }
    ],
    "sg:phone":"+61 2 9689 3244",
    "sg:postcode":"2150",
    "sg:province":"NSW",
    "sg:tags":[
        "medical",
        "practitioner"
    ],
    "wof:name":"Parramatta Cosmetic Clinic",
    "wof:placetype":"venue"
},
  "geometry": {"coordinates":[151.00668335,-33.81483078],"type":"Point"}
}