{
  "type": "Feature",
  "properties": {
    "iso:country":"AU",
    "sg:address":"3/ 222a Hutt St",
    "sg:city":"Adelaide",
    "sg:classifiers":[
        {
            "category":"Shopping",
            "subcategory":"Mobile Phones",
            "type":"Retail Goods"
        }
    ],
    "sg:phone":"+61 8 8232 8383",
    "sg:postcode":"5000",
    "sg:province":"SA",
    "sg:tags":[
        "telephone",
        "accessory"
    ],
    "wof:name":"Adelaide Mobilecom Pty Ltd",
    "wof:placetype":"venue"
},
  "geometry": {"coordinates":[138.61257934599999,-34.9320755005],"type":"Point"}
}