{
  "type": "Feature",
  "properties": {
    "iso:country":"AU",
    "sg:address":"61 Station St",
    "sg:city":"Malvern",
    "sg:classifiers":[
        {
            "category":"Real Estate",
            "subcategory":"Architect",
            "type":"Services"
        }
    ],
    "sg:phone":"+61 3 9500 1062",
    "sg:postcode":"3144",
    "sg:province":"VIC",
    "wof:name":"Baranyay Ferencz",
    "wof:placetype":"venue"
},
  "geometry": {"coordinates":[145.02972412099999,-37.8659858704],"type":"Point"}
}