{
  "type": "Feature",
  "properties": {
    "iso:country":"AU",
    "sg:address":"115 Yulara Drv",
    "sg:city":"Yulara",
    "sg:classifiers":[
        {
            "category":"Autos & Motor Vehicles",
            "subcategory":"Fuel & Gas Station",
            "type":"Retail Goods"
        }
    ],
    "sg:phone":"+61 8 8956 2229",
    "sg:postcode":"0872",
    "sg:province":"NT",
    "wof:name":"Mobil Oil Aust Pty Ltd",
    "wof:placetype":"venue"
},
  "geometry": {"coordinates":[130.985107422,-25.2417354584],"type":"Point"}
}