{
  "type": "Feature",
  "properties": {
    "iso:country":"AU",
    "sg:address":"West Brook Rd",
    "sg:city":"Cawdor",
    "sg:classifiers":[
        {
            "category":"Building & Trades",
            "subcategory":"Construction",
            "type":"Services"
        }
    ],
    "sg:phone":"+61 2 4654 5343",
    "sg:postcode":"2570",
    "sg:province":"NSW",
    "sg:tags":[
        "contractor"
    ],
    "wof:name":"Fahey S J",
    "wof:placetype":"venue"
},
  "geometry": {"coordinates":[150.672485352,-34.0975189209],"type":"Point"}
}