{
  "type": "Feature",
  "properties": {
    "addr:full":"PO Box 1495 Caringbah NSW 2229",
    "addr:postcode":"2229",
    "iso:country":"AU",
    "sg:address":"PO Box 1495",
    "sg:city":"Caringbah",
    "sg:classifiers":[
        {
            "category":"Personal",
            "type":"Services"
        }
    ],
    "sg:phone":"+61 405 186 123",
    "sg:postcode":"2229",
    "sg:province":"NSW",
    "sg:tags":[
        "gift"
    ],
    "wof:name":"Fling Unique Gift Ware",
    "wof:placetype":"venue"
},
  "geometry": {"coordinates":[151.12121582,-34.0429000854],"type":"Point"}
}