{
  "type": "Feature",
  "properties": {
    "addr:full":"76 Pilkington St Garbutt QLD 4814",
    "addr:housenumber":"76",
    "addr:postcode":"4814",
    "addr:street":"Pilkington St",
    "iso:country":"AU",
    "sg:address":"76 Pilkington St",
    "sg:city":"Garbutt",
    "sg:classifiers":[
        {
            "category":"Autos & Motor Vehicles",
            "subcategory":"Fuel & Gas Station",
            "type":"Retail Goods"
        }
    ],
    "sg:phone":"+61 7 4779 2119",
    "sg:postcode":"4814",
    "sg:province":"QLD",
    "wof:name":"BP Dalrymple",
    "wof:placetype":"venue"
},
  "geometry": {"coordinates":[146.76676900000001,-19.274549],"type":"Point"}
}