{
  "type": "Feature",
  "properties": {
    "iso:country":"AU",
    "sg:address":"32 Goodman St",
    "sg:city":"Nakara",
    "sg:classifiers":[
        {
            "category":"Social Services",
            "subcategory":"Retirement Home",
            "type":"Services"
        }
    ],
    "sg:phone":"+61 8 8927 3116",
    "sg:postcode":"0810",
    "sg:province":"NT",
    "sg:tags":[
        "environmental",
        "consultant",
        "pollution"
    ],
    "wof:name":"Kraatz M",
    "wof:placetype":"venue"
},
  "geometry": {"coordinates":[130.87786865199999,-12.3724050522],"type":"Point"}
}