{
  "type": "Feature",
  "properties": {
    "iso:country":"AU",
    "sg:address":"Shop 1/ 19 Young St",
    "sg:city":"Southport",
    "sg:classifiers":[
        {
            "category":"Personal",
            "subcategory":"Beauty Salon",
            "type":"Services"
        }
    ],
    "sg:phone":"+61 7 5561 1313",
    "sg:postcode":"4215",
    "sg:province":"QLD",
    "wof:name":"Classy",
    "wof:placetype":"venue"
},
  "geometry": {"coordinates":[153.41268920900001,-27.9694805145],"type":"Point"}
}