{
  "type": "Feature",
  "properties": {
    "iso:country":"AU",
    "sg:address":"132 Norton St",
    "sg:city":"Leichhardt",
    "sg:classifiers":[
        {
            "category":"Restaurant",
            "type":"Food & Drink"
        }
    ],
    "sg:phone":"+61 2 9560 7957",
    "sg:postcode":"2040",
    "sg:province":"NSW",
    "wof:name":"At Fernando's",
    "wof:placetype":"venue"
},
  "geometry": {"coordinates":[151.156784,-33.882717],"type":"Point"}
}