{
  "type": "Feature",
  "properties": {
    "iso:country":"AU",
    "sg:address":"324 Danks St",
    "sg:city":"Middle Park",
    "sg:classifiers":[
        {
            "category":"Health Services",
            "subcategory":"Doctor",
            "type":"Services"
        }
    ],
    "sg:phone":"+61 3 9645 0038",
    "sg:postcode":"3206",
    "sg:province":"VIC",
    "sg:tags":[
        "occupational",
        "safety"
    ],
    "wof:name":"Corporate Emergency Planning ( Aust.) Pty Ltd",
    "wof:placetype":"venue"
},
  "geometry": {"coordinates":[144.95871,-37.851139],"type":"Point"}
}