{
  "type": "Feature",
  "properties": {
    "iso:country":"AU",
    "sg:address":"Wilsonton Medical Centre, Richmond Drv",
    "sg:city":"Toowoomba",
    "sg:classifiers":[
        {
            "category":"Health Services",
            "subcategory":"Doctor",
            "type":"Services"
        }
    ],
    "sg:phone":"+61 7 4633 1939",
    "sg:postcode":"4350",
    "sg:province":"QLD",
    "sg:tags":[
        "medical",
        "practitioner"
    ],
    "wof:name":"CAREY Cormac Dr",
    "wof:placetype":"venue"
},
  "geometry": {"coordinates":[151.924072,-27.541397],"type":"Point"}
}