{
  "type": "Feature",
  "properties": {
    "addr:full":"145 Keira St Wollongong NSW 2500",
    "addr:housenumber":"145",
    "addr:postcode":"2500",
    "addr:street":"Keira St",
    "iso:country":"AU",
    "sg:address":"145 Keira St",
    "sg:city":"Wollongong",
    "sg:classifiers":[
        {
            "category":"Food & Beverages",
            "subcategory":"Supermarket",
            "type":"Retail Goods"
        }
    ],
    "sg:phone":"+61 2 4228 0260",
    "sg:postcode":"2500",
    "sg:province":"NSW",
    "sg:tags":[
        "grocery",
        "store"
    ],
    "wof:name":"Wollongong Orient Trading",
    "wof:placetype":"venue"
},
  "geometry": {"coordinates":[150.89372299999999,-34.422825],"type":"Point"}
}