{
  "type": "Feature",
  "properties": {
    "iso:country":"AU",
    "sg:address":"4/ 39 Clarke St",
    "sg:city":"Norwood",
    "sg:classifiers":[
        {
            "category":"Social Services",
            "subcategory":"Child Care",
            "type":"Services"
        }
    ],
    "sg:phone":"+61 1300 138 235",
    "sg:postcode":"5067",
    "sg:province":"SA",
    "sg:tags":[
        "fleet",
        "management"
    ],
    "wof:name":"Fleet Australia",
    "wof:placetype":"venue"
},
  "geometry": {"coordinates":[138.62457275400001,-34.9273910522],"type":"Point"}
}