{
  "type": "Feature",
  "properties": {
    "iso:country":"AU",
    "sg:address":"233 Crown St",
    "sg:city":"Wollongong",
    "sg:classifiers":[
        {
            "category":"Education",
            "subcategory":"Special Training",
            "type":"Public Place"
        }
    ],
    "sg:phone":"+61 2 4228 7011",
    "sg:postcode":"2500",
    "sg:province":"NSW",
    "sg:tags":[
        "development"
    ],
    "wof:name":"IPC Employment",
    "wof:placetype":"venue"
},
  "geometry": {"coordinates":[150.89212000000001,-34.425159],"type":"Point"}
}