{
  "type": "Feature",
  "properties": {
    "iso:country":"AU",
    "sg:address":"372 Flinders St",
    "sg:city":"Townsville",
    "sg:classifiers":[
        {
            "category":"Shopping",
            "subcategory":"Luggage & Leather Goods",
            "type":"Retail Goods"
        }
    ],
    "sg:phone":"+61 7 4771 2595",
    "sg:postcode":"4810",
    "sg:province":"QLD",
    "wof:name":"Norm Lewis Bag Shop",
    "wof:placetype":"venue"
},
  "geometry": {"coordinates":[146.809631,-19.266743],"type":"Point"}
}