{
  "type": "Feature",
  "properties": {
    "addr:full":"Suite 8, 90 Mona Vale Rd Mona Vale NSW 2103",
    "addr:housenumber":"90",
    "addr:postcode":"2103",
    "addr:street":"Mona Vale Rd",
    "iso:country":"AU",
    "sg:address":"Suite 8, 90 Mona Vale Rd",
    "sg:city":"Mona Vale",
    "sg:classifiers":[
        {
            "category":"Banks & Credit Unions",
            "subcategory":"Financial Services",
            "type":"Services"
        }
    ],
    "sg:phone":"+61 2 9999 2344",
    "sg:postcode":"2103",
    "sg:province":"NSW",
    "sg:tags":[
        "annuity",
        "rollover",
        "superannuation",
        "consultant"
    ],
    "wof:name":"Northstar Super",
    "wof:placetype":"venue"
},
  "geometry": {"coordinates":[151.28941345199999,-33.6761665344],"type":"Point"}
}