{
  "type": "Feature",
  "properties": {
    "addr:full":"69 William St Launceston TAS 7250",
    "addr:housenumber":"69",
    "addr:postcode":"7250",
    "addr:street":"William St",
    "iso:country":"AU",
    "sg:address":"69 William St",
    "sg:city":"Launceston",
    "sg:classifiers":[
        {
            "category":"Sports & Exercise",
            "subcategory":"Gym",
            "type":"Entertainment"
        }
    ],
    "sg:phone":"+61 3 6334 2559",
    "sg:postcode":"7250",
    "sg:province":"TAS",
    "sg:tags":[
        "health",
        "fitness"
    ],
    "wof:name":"Fernwood",
    "wof:placetype":"venue"
},
  "geometry": {"coordinates":[147.138504028,-41.4452018738],"type":"Point"}
}