{
  "type": "Feature",
  "properties": {
    "addr:full":"84 Jijaws St Sumner Park QLD 4074",
    "addr:housenumber":"84",
    "addr:postcode":"4074",
    "addr:street":"Jijaws St",
    "iso:country":"AU",
    "sg:address":"84 Jijaws St",
    "sg:city":"Sumner Park",
    "sg:classifiers":[
        {
            "category":"Home & Garden",
            "subcategory":"Furniture",
            "type":"Retail Goods"
        }
    ],
    "sg:phone":"+61 7 3376 4555",
    "sg:postcode":"4074",
    "sg:province":"QLD",
    "sg:tags":[
        "business"
    ],
    "wof:name":"Queensland Factory Direct Office Furniture",
    "wof:placetype":"venue"
},
  "geometry": {"coordinates":[152.93623352,-27.5616455078],"type":"Point"}
}