{
  "type": "Feature",
  "properties": {
    "iso:country":"AU",
    "sg:address":"11/43 Berrimah Rd",
    "sg:city":"(Strath Village) Berrimah",
    "sg:classifiers":[
        {
            "category":"Manufacturing",
            "subcategory":"Motor Vehicles & Parts",
            "type":"Manufacturing & Wholesale Goods"
        }
    ],
    "sg:phone":"+61 8 8947 2803",
    "sg:postcode":"0828",
    "sg:province":"NT",
    "sg:tags":[
        "replacement"
    ],
    "wof:name":"Darwin 4WD Spares",
    "wof:placetype":"venue"
},
  "geometry": {"coordinates":[130.923706055,-12.4451570511],"type":"Point"}
}