{
  "type": "Feature",
  "properties": {
    "addr:full":"Darley Rd Caboolture QLD 4510",
    "addr:postcode":"4510",
    "addr:street":"Darley Rd",
    "iso:country":"AU",
    "sg:address":"Darley Rd",
    "sg:city":"Caboolture",
    "sg:classifiers":[
        {
            "category":"Personal",
            "subcategory":"Beauty Salon",
            "type":"Services"
        }
    ],
    "sg:phone":"+61 7 5497 0005",
    "sg:postcode":"4510",
    "sg:province":"QLD",
    "wof:name":"Brushpoint Makeup Artists",
    "wof:placetype":"venue"
},
  "geometry": {"coordinates":[152.90939299999999,-27.105873],"type":"Point"}
}