{
  "type": "Feature",
  "properties": {
    "addr:full":"Level 3, Menzies House 640 Murray St West Perth WA 6872",
    "addr:housenumber":"640",
    "addr:postcode":"6872",
    "addr:street":"Murray St",
    "iso:country":"AU",
    "sg:address":"Level 3, Menzies House 640 Murray St",
    "sg:city":"West Perth",
    "sg:classifiers":[
        {
            "category":"Mining & Drilling",
            "type":"Manufacturing & Wholesale Goods"
        }
    ],
    "sg:phone":"+61 8 9375 2299",
    "sg:postcode":"6872",
    "sg:province":"WA",
    "sg:tags":[
        "geologist"
    ],
    "wof:name":"Carras Mining Pty Ltd",
    "wof:placetype":"venue"
},
  "geometry": {"coordinates":[115.845039,-31.948252],"type":"Point"}
}