{
  "type": "Feature",
  "properties": {
    "addr:full":"16 4 Avenue of Americas Newington NSW 2127",
    "addr:housenumber":"4",
    "addr:postcode":"2127",
    "addr:street":"16;Avenue Of Americas",
    "iso:country":"AU",
    "sg:address":"16 4",
    "sg:city":"Avenue of Americas Newington",
    "sg:classifiers":[
        {
            "category":"Wholesale",
            "subcategory":"Electrical",
            "type":"Manufacturing & Wholesale Goods"
        }
    ],
    "sg:phone":"+61 2 9737 8262",
    "sg:postcode":"2127",
    "sg:province":"NSW",
    "sg:tags":[
        "wholesaler"
    ],
    "wof:name":"Industrial Electrical Suppliers",
    "wof:placetype":"venue"
},
  "geometry": {"coordinates":[151.05632019000001,-33.8324699402],"type":"Point"}
}