{
  "type": "Feature",
  "properties": {
    "iso:country":"AU",
    "sg:address":"Main St",
    "sg:city":"Woolooga",
    "sg:classifiers":[
        {
            "category":"Professional",
            "subcategory":"Business Services",
            "type":"Services"
        }
    ],
    "sg:phone":"+61 7 5484 7239",
    "sg:postcode":"4570",
    "sg:province":"QLD",
    "sg:tags":[
        "livestock",
        "transport"
    ],
    "wof:name":"Stegemann M E",
    "wof:placetype":"venue"
},
  "geometry": {"coordinates":[152.66921997099999,-26.1777496338],"type":"Point"}
}