{
  "type": "Feature",
  "properties": {
    "addr:full":"Shop 1/ 215 Charters Towers Rd Hermit Park QLD 4812",
    "addr:housenumber":"shop 1 / 215",
    "addr:postcode":"4812",
    "addr:street":"Charters Towers Rd",
    "iso:country":"AU",
    "sg:address":"Shop 1/ 215 Charters Towers Rd",
    "sg:city":"Hermit Park",
    "sg:classifiers":[
        {
            "category":"Professional",
            "subcategory":"Business Services",
            "type":"Services"
        }
    ],
    "sg:phone":"+61 7 4779 4199",
    "sg:postcode":"4812",
    "sg:province":"QLD",
    "sg:tags":[
        "drafting"
    ],
    "wof:name":"C & B Designs Pty Ltd",
    "wof:placetype":"venue"
},
  "geometry": {"coordinates":[146.796997,-19.285383],"type":"Point"}
}