{
  "type": "Feature",
  "properties": {
    "iso:country":"AU",
    "sg:address":"25 Cameron St",
    "sg:city":"Brunswick",
    "sg:classifiers":[
        {
            "category":"Professional",
            "subcategory":"Engineering",
            "type":"Services"
        }
    ],
    "sg:phone":"+61 3 9386 5232",
    "sg:postcode":"3056",
    "sg:province":"VIC",
    "sg:tags":[
        "engineer"
    ],
    "wof:name":"Saville L B Pty Ltd",
    "wof:placetype":"venue"
},
  "geometry": {"coordinates":[144.96194457999999,-37.75730896],"type":"Point"}
}