{
  "type": "Feature",
  "properties": {
    "addr:full":"34 Doag Pl Beaconsfield WA 6162",
    "addr:housenumber":"34",
    "addr:postcode":"6162",
    "addr:street":"Doag Pl",
    "iso:country":"AU",
    "sg:address":"34 Doag Pl",
    "sg:city":"Beaconsfield",
    "sg:classifiers":[
        {
            "category":"Home & Garden",
            "subcategory":"Carpets & Floor Coverings",
            "type":"Retail Goods"
        }
    ],
    "sg:phone":"+61 412 824 254",
    "sg:postcode":"6162",
    "sg:province":"WA",
    "sg:tags":[
        "tile",
        "wall",
        "layer"
    ],
    "wof:name":"Tiler Craftsman",
    "wof:placetype":"venue"
},
  "geometry": {"coordinates":[115.771629,-32.066147],"type":"Point"}
}