{
  "type": "Feature",
  "properties": {
    "addr:full":"16 Isdell St Algester QLD 4115",
    "addr:housenumber":"16",
    "addr:postcode":"4115",
    "addr:street":"Isdell St",
    "iso:country":"AU",
    "sg:address":"16 Isdell St",
    "sg:city":"Algester",
    "sg:classifiers":[
        {
            "category":"Professional",
            "subcategory":"Engineering",
            "type":"Services"
        }
    ],
    "sg:phone":"+61 7 3273 1409",
    "sg:postcode":"4115",
    "sg:province":"QLD",
    "sg:tags":[
        "electronic",
        "engineer"
    ],
    "wof:name":"Cybertronics",
    "wof:placetype":"venue"
},
  "geometry": {"coordinates":[153.02700805699999,-27.6202430725],"type":"Point"}
}