{
  "type": "Feature",
  "properties": {
    "addr:full":"37 Crendon St Burpengary QLD 4505",
    "addr:housenumber":"37",
    "addr:postcode":"4505",
    "addr:street":"Crendon St",
    "iso:country":"AU",
    "sg:address":"37 Crendon St",
    "sg:city":"Burpengary",
    "sg:classifiers":[
        {
            "category":"Freight",
            "type":"Transportation"
        }
    ],
    "sg:phone":"+61 419 710 655",
    "sg:postcode":"4505",
    "sg:province":"QLD",
    "sg:tags":[
        "light",
        "carrier"
    ],
    "wof:name":"Heitmann Carriers",
    "wof:placetype":"venue"
},
  "geometry": {"coordinates":[152.96217346200001,-27.1654529572],"type":"Point"}
}