{
  "type": "Feature",
  "properties": {
    "iso:country":"AU",
    "sg:address":"Shop 6, 55 Littlecroft Ave",
    "sg:city":"Narre Warren South",
    "sg:classifiers":[
        {
            "category":"Food & Beverages",
            "subcategory":"Bakery",
            "type":"Retail Goods"
        }
    ],
    "sg:phone":"+61 3 8790 3055",
    "sg:postcode":"3805",
    "sg:province":"VIC",
    "sg:tags":[
        "cake",
        "shop",
        "pastry"
    ],
    "wof:name":"Sun Bakery",
    "wof:placetype":"venue"
},
  "geometry": {"coordinates":[145.30226135300001,-38.0655288696],"type":"Point"}
}