{
  "type": "Feature",
  "properties": {
    "iso:country":"AU",
    "sg:address":"27 Duke St",
    "sg:city":"Mt Isa",
    "sg:classifiers":[
        {
            "category":"Building & Trades",
            "subcategory":"Construction",
            "type":"Services"
        }
    ],
    "sg:phone":"+61 7 4743 3199",
    "sg:postcode":"4825",
    "sg:province":"QLD",
    "sg:tags":[
        "home",
        "air conditioning"
    ],
    "wof:name":"James L Williams Pty Ltd",
    "wof:placetype":"venue"
},
  "geometry": {"coordinates":[139.496109,-20.742916],"type":"Point"}
}