{
  "type": "Feature",
  "properties": {
    "iso:country":"AU",
    "sg:address":"2 Stratford Rd",
    "sg:city":"Tahmoor",
    "sg:classifiers":[
        {
            "category":"Arena",
            "subcategory":"Sports Club",
            "type":"Entertainment"
        }
    ],
    "sg:phone":"+61 2 4681 9002",
    "sg:postcode":"2573",
    "sg:province":"NSW",
    "sg:tags":[
        "defence",
        "supply",
        "self",
        "instruction",
        "martial art"
    ],
    "wof:name":"Arthur Moulas Martial Arts Academy",
    "wof:placetype":"venue"
},
  "geometry": {"coordinates":[150.58636474599999,-34.2315483093],"type":"Point"}
}