{
  "type": "Feature",
  "properties": {
    "iso:country":"AU",
    "sg:address":"214B Great Western Hwy",
    "sg:city":"Kingswood",
    "sg:classifiers":[
        {
            "category":"Shopping",
            "subcategory":"Party Supplies",
            "type":"Retail Goods"
        }
    ],
    "sg:phone":"+61 2 4722 9607",
    "sg:postcode":"2747",
    "sg:province":"NSW",
    "sg:tags":[
        "hire",
        "costume"
    ],
    "wof:name":"Costumes &#039;N&#039; Things",
    "wof:placetype":"venue"
},
  "geometry": {"coordinates":[150.71875,-33.7585220337],"type":"Point"}
}