{
  "type": "Feature",
  "properties": {
    "iso:country":"AU",
    "sg:address":"14 Doolan St",
    "sg:city":"Reservoir",
    "sg:classifiers":[
        {
            "category":"Train Station",
            "subcategory":"Light Rail",
            "type":"Transportation"
        }
    ],
    "sg:phone":"+61 3 9471 1248",
    "sg:postcode":"3073",
    "sg:province":"VIC",
    "sg:tags":[
        "survey",
        "traffic"
    ],
    "wof:name":"Trafficworks Pty Ltd",
    "wof:placetype":"venue"
},
  "geometry": {"coordinates":[145.018508911,-37.726020813],"type":"Point"}
}