{
  "type": "Feature",
  "properties": {
    "addr:full":"PO Box 673 Lilydale VIC 3140",
    "addr:postcode":"3140",
    "iso:country":"AU",
    "sg:address":"PO Box 673",
    "sg:city":"Lilydale",
    "sg:classifiers":[
        {
            "category":"Train Station",
            "subcategory":"Rail",
            "type":"Transportation"
        }
    ],
    "sg:phone":"+61 3 9735 4114",
    "sg:postcode":"3140",
    "sg:province":"VIC",
    "sg:tags":[
        "consultant"
    ],
    "wof:name":"CORDETT",
    "wof:placetype":"venue"
},
  "geometry": {"coordinates":[145.37161254899999,-37.7617797852],"type":"Point"}
}