{
  "type": "Feature",
  "properties": {
    "iso:country":"AU",
    "sg:address":"PO Box 133",
    "sg:city":"Ingle Farm",
    "sg:classifiers":[
        {
            "category":"Food & Beverages",
            "subcategory":"Specialty",
            "type":"Retail Goods"
        }
    ],
    "sg:phone":"+61 8 8265 4399",
    "sg:postcode":"5098",
    "sg:province":"SA",
    "sg:tags":[
        "delicacy"
    ],
    "wof:name":"Inka Fine Foods",
    "wof:placetype":"venue"
},
  "geometry": {"coordinates":[138.650756836,-34.8287086487],"type":"Point"}
}