{
  "type": "Feature",
  "properties": {
    "iso:country":"AU",
    "sg:address":"6 Falcon St",
    "sg:city":"Narrogin",
    "sg:classifiers":[
        {
            "category":"Health Services",
            "subcategory":"Doctor",
            "type":"Services"
        }
    ],
    "sg:phone":"+61 8 9881 6008",
    "sg:postcode":"6312",
    "sg:province":"WA",
    "sg:tags":[
        "medical",
        "practitioner"
    ],
    "wof:name":"Lai Steven C L Dr",
    "wof:placetype":"venue"
},
  "geometry": {"coordinates":[117.17778015099999,-32.9369888306],"type":"Point"}
}