{
  "type": "Feature",
  "properties": {
    "iso:country":"AU",
    "sg:address":"94 / 96 Kortum Drv",
    "sg:city":"Burleigh",
    "sg:classifiers":[
        {
            "category":"Home & Garden",
            "subcategory":"Carpets & Floor Coverings",
            "type":"Retail Goods"
        }
    ],
    "sg:phone":"+61 7 5520 1551",
    "sg:postcode":"4220",
    "sg:province":"QLD",
    "sg:tags":[
        "wood"
    ],
    "sg:website":"http://www.harmonytimberfloors.com",
    "wof:name":"Timber Floors Direct",
    "wof:placetype":"venue"
},
  "geometry": {"coordinates":[153.42913818400001,-28.1022644043],"type":"Point"}
}