{
  "type": "Feature",
  "properties": {
    "addr:full":"683 Ruthven St Toowoomba QLD 4350",
    "addr:housenumber":"683",
    "addr:postcode":"4350",
    "addr:street":"Ruthven St",
    "iso:country":"AU",
    "sg:address":"683 Ruthven St",
    "sg:city":"Toowoomba",
    "sg:classifiers":[
        {
            "category":"Travel",
            "subcategory":"Hotels & Motels",
            "type":"Entertainment"
        }
    ],
    "sg:phone":"+61 7 4638 3466",
    "sg:postcode":"4350",
    "sg:province":"QLD",
    "wof:name":"Glennon House Motel",
    "wof:placetype":"venue"
},
  "geometry": {"coordinates":[151.951233,-27.572758],"type":"Point"}
}