{
  "type": "Feature",
  "properties": {
    "addr:full":"18 Elma Rd Cheltenham VIC 3192",
    "addr:housenumber":"18",
    "addr:postcode":"3192",
    "addr:street":"Elma Rd",
    "iso:country":"AU",
    "sg:address":"18 Elma Rd",
    "sg:city":"Cheltenham",
    "sg:classifiers":[
        {
            "category":"Military Area",
            "subcategory":"Army Base",
            "type":"Public Place"
        }
    ],
    "sg:phone":"+61 3 9532 3666",
    "sg:postcode":"3192",
    "sg:province":"VIC",
    "sg:tags":[
        "concrete",
        "slab",
        "floor"
    ],
    "wof:name":"Carron Concrete Services Pty Ltd",
    "wof:placetype":"venue"
},
  "geometry": {"coordinates":[145.073196411,-37.9495849609],"type":"Point"}
}