{
  "type": "Feature",
  "properties": {
    "addr:full":"25 Hurley Drv Coffs Harbour NSW 2450",
    "addr:housenumber":"25",
    "addr:postcode":"2450",
    "addr:street":"Hurley Drv",
    "iso:country":"AU",
    "sg:address":"25 Hurley Drv",
    "sg:city":"Coffs Harbour",
    "sg:classifiers":[
        {
            "category":"Professional",
            "subcategory":"Printing & Photocopies",
            "type":"Services"
        }
    ],
    "sg:phone":"+61 2 6651 1844",
    "sg:postcode":"2450",
    "sg:province":"NSW",
    "sg:tags":[
        "photocopier"
    ],
    "wof:name":"Colourworks",
    "wof:placetype":"venue"
},
  "geometry": {"coordinates":[153.10110499999999,-30.309151],"type":"Point"}
}