{
  "type": "Feature",
  "properties": {
    "addr:full":"Unit 11, 237 Brisbane Rd Biggera Waters QLD 4216",
    "addr:housenumber":"237",
    "addr:postcode":"4216",
    "addr:street":"Brisbane Rd",
    "iso:country":"AU",
    "sg:address":"Unit 11, 237 Brisbane Rd",
    "sg:city":"Biggera Waters",
    "sg:classifiers":[
        {
            "category":"Shopping",
            "subcategory":"Antiques",
            "type":"Retail Goods"
        }
    ],
    "sg:phone":"+61 7 5537 2485",
    "sg:postcode":"4216",
    "sg:province":"QLD",
    "sg:tags":[
        "restoration",
        "reproduction"
    ],
    "wof:name":"New Life Upholstery",
    "wof:placetype":"venue"
},
  "geometry": {"coordinates":[153.37640380900001,-27.9314460754],"type":"Point"}
}