{
  "type": "Feature",
  "properties": {
    "addr:full":"4 Hammersley Crt Taylors Lakes VIC 3038",
    "addr:housenumber":"4",
    "addr:postcode":"3038",
    "addr:street":"Hammersley Crt",
    "iso:country":"AU",
    "sg:address":"4 Hammersley Crt",
    "sg:city":"Taylors Lakes",
    "sg:classifiers":[
        {
            "category":"Home & Garden",
            "subcategory":"Building Materials",
            "type":"Retail Goods"
        }
    ],
    "sg:phone":"+61 3 9390 3880",
    "sg:postcode":"3038",
    "sg:province":"VIC",
    "sg:tags":[
        "shutter",
        "roller",
        "grille"
    ],
    "wof:name":"Villani Window Shutters",
    "wof:placetype":"venue"
},
  "geometry": {"coordinates":[144.80195599999999,-37.709476],"type":"Point"}
}