{
  "type": "Feature",
  "properties": {
    "addr:full":"173 Old Maryborough Rd Gympie QLD 4570",
    "addr:housenumber":"173",
    "addr:postcode":"4570",
    "addr:street":"Old Maryborough Rd",
    "iso:country":"AU",
    "sg:address":"173 Old Maryborough Rd",
    "sg:city":"Gympie",
    "sg:classifiers":[
        {
            "category":"Education",
            "subcategory":"School",
            "type":"Public Place"
        }
    ],
    "sg:phone":"+61 7 5482 8206",
    "sg:postcode":"4570",
    "sg:province":"QLD",
    "wof:name":"Victory College",
    "wof:placetype":"venue"
},
  "geometry": {"coordinates":[152.671585083,-26.1740112305],"type":"Point"}
}