{
  "type": "Feature",
  "properties": {
    "addr:full":"7 Wickham St Gympie QLD 4570",
    "addr:housenumber":"7",
    "addr:postcode":"4570",
    "addr:street":"Wickham St",
    "iso:country":"AU",
    "sg:address":"7 Wickham St",
    "sg:city":"Gympie",
    "sg:classifiers":[
        {
            "category":"Autos & Motor Vehicles",
            "subcategory":"Fuel & Gas Station",
            "type":"Retail Goods"
        }
    ],
    "sg:phone":"+61 7 5482 2401",
    "sg:postcode":"4570",
    "sg:province":"QLD",
    "wof:name":"Shell Gympie Driveway",
    "wof:placetype":"venue"
},
  "geometry": {"coordinates":[152.65786743199999,-26.1922664642],"type":"Point"}
}