{
  "type": "Feature",
  "properties": {
    "addr:full":"649 Glenferrie Rd Hawthorn VIC 3122",
    "addr:housenumber":"649",
    "addr:postcode":"3122",
    "addr:street":"Glenferrie Rd",
    "iso:country":"AU",
    "sg:address":"649 Glenferrie Rd",
    "sg:city":"Hawthorn",
    "sg:classifiers":[
        {
            "category":"Building & Trades",
            "subcategory":"Locksmith",
            "type":"Services"
        }
    ],
    "sg:phone":"+61 3 9819 4635",
    "sg:postcode":"3122",
    "sg:province":"VIC",
    "sg:tags":[
        "strongroom",
        "safe",
        "door"
    ],
    "wof:name":"Laszlo Security Alarms",
    "wof:placetype":"venue"
},
  "geometry": {"coordinates":[145.03541564899999,-37.8213386536],"type":"Point"}
}