{
  "type": "Feature",
  "properties": {
    "addr:full":"40 Landsborough Pde Golden Beach QLD 4551",
    "addr:housenumber":"40",
    "addr:postcode":"4551",
    "addr:street":"Landsborough Pde",
    "iso:country":"AU",
    "sg:address":"40 Landsborough Pde",
    "sg:city":"Golden Beach",
    "sg:classifiers":[
        {
            "category":"Fast Food",
            "type":"Food & Drink"
        }
    ],
    "sg:phone":"+61 7 5492 2666",
    "sg:postcode":"4551",
    "sg:province":"QLD",
    "sg:tags":[
        "away",
        "take"
    ],
    "wof:name":"Golden Grill",
    "wof:placetype":"venue"
},
  "geometry": {"coordinates":[153.119995117,-26.8204841614],"type":"Point"}
}