{
  "type": "Feature",
  "properties": {
    "addr:full":"Factory 4, 20 Station St Dandenong VIC 3175",
    "addr:housenumber":"20",
    "addr:postcode":"3175",
    "addr:street":"Station St",
    "iso:country":"AU",
    "sg:address":"Factory 4, 20 Station St",
    "sg:city":"Dandenong",
    "sg:classifiers":[
        {
            "category":"Retail",
            "subcategory":"Auto Repair",
            "type":"Services"
        }
    ],
    "sg:phone":"+61 3 9769 2422",
    "sg:postcode":"3175",
    "sg:province":"VIC",
    "sg:tags":[
        "repairer",
        "motor",
        "engineer"
    ],
    "wof:name":"Pronto Automotive Pty Ltd",
    "wof:placetype":"venue"
},
  "geometry": {"coordinates":[145.20872497600001,-37.9919166565],"type":"Point"}
}