{
  "type": "Feature",
  "properties": {
    "addr:full":"435 Nepean Hwy Frankston VIC 3199",
    "addr:housenumber":"435",
    "addr:postcode":"3199",
    "addr:street":"Nepean Hwy",
    "iso:country":"AU",
    "sg:address":"435 Nepean Hwy",
    "sg:city":"Frankston",
    "sg:classifiers":[
        {
            "category":"Education",
            "subcategory":"Dance Studio",
            "type":"Public Place"
        }
    ],
    "sg:phone":"+61 3 9770 2311",
    "sg:postcode":"3199",
    "sg:province":"VIC",
    "sg:tags":[
        "venue",
        "tuition"
    ],
    "wof:name":"Take Five Dance & Fitness Studios",
    "wof:placetype":"venue"
},
  "geometry": {"coordinates":[145.00953674300001,-37.9069061279],"type":"Point"}
}