{
  "type": "Feature",
  "properties": {
    "addr:full":"Nature Care Holistic & Medical Centre, Level 2 , Crows Nest NSW 2065",
    "addr:postcode":"2065",
    "iso:country":"AU",
    "sg:address":"Nature Care Holistic & Medical Centre, Level 2",
    "sg:city":", Crows Nest",
    "sg:classifiers":[
        {
            "category":"Health Services",
            "subcategory":"Health Practitioner",
            "type":"Services"
        }
    ],
    "sg:phone":"+61 2 9966 8666",
    "sg:postcode":"2065",
    "sg:province":"NSW",
    "sg:tags":[
        "naturopath"
    ],
    "wof:name":"Gagnon Carl",
    "wof:placetype":"venue"
},
  "geometry": {"coordinates":[151.19818115199999,-33.8367576599],"type":"Point"}
}