{
  "type": "Feature",
  "properties": {
    "addr:full":"9/ 191 St Georges Tce Perth WA 6000",
    "addr:housenumber":"/ 191",
    "addr:postcode":"6000",
    "addr:street":"St Georges Tce",
    "iso:country":"AU",
    "sg:address":"9/ 191 St Georges Tce",
    "sg:city":"Perth",
    "sg:classifiers":[
        {
            "category":"Professional",
            "subcategory":"Engineering",
            "type":"Services"
        }
    ],
    "sg:phone":"+61 8 9429 5800",
    "sg:postcode":"6000",
    "sg:province":"WA",
    "sg:tags":[
        "consulting",
        "engineer"
    ],
    "wof:name":"Kvaerner",
    "wof:placetype":"venue"
},
  "geometry": {"coordinates":[115.853172302,-31.9536991119],"type":"Point"}
}