{
  "type": "Feature",
  "properties": {
    "iso:country":"AU",
    "sg:address":"590 Mt Gravatt-Capalaba Rd",
    "sg:city":"Wishart",
    "sg:classifiers":[
        {
            "category":"Autos & Motor Vehicles",
            "subcategory":"Automobile Sales",
            "type":"Retail Goods"
        }
    ],
    "sg:phone":"+61 7 3422 2722",
    "sg:postcode":"4122",
    "sg:province":"QLD",
    "sg:tags":[
        "equipment",
        "trailer"
    ],
    "wof:name":"U-Haul Trailers",
    "wof:placetype":"venue"
},
  "geometry": {"coordinates":[153.091033936,-27.5552711487],"type":"Point"}
}