{
  "type": "Feature",
  "properties": {
    "iso:country":"AU",
    "sg:address":"22 Main St",
    "sg:city":"Derrinallum",
    "sg:classifiers":[
        {
            "category":"Professional",
            "subcategory":"Accounting & Tax Preparation",
            "type":"Services"
        }
    ],
    "sg:phone":"+61 3 5597 6666",
    "sg:postcode":"3325",
    "sg:province":"VIC",
    "sg:tags":[
        "accountant",
        "auditor"
    ],
    "wof:name":"Mahar & Associates",
    "wof:placetype":"venue"
},
  "geometry": {"coordinates":[143.223785,-37.947727],"type":"Point"}
}