{
  "type": "Feature",
  "properties": {
    "addr:full":"22 Harriette St North Rockhampton QLD 4701",
    "addr:housenumber":"22",
    "addr:postcode":"4701",
    "addr:street":"Harriette St North",
    "iso:country":"AU",
    "sg:address":"22 Harriette St",
    "sg:city":"North Rockhampton",
    "sg:classifiers":[
        {
            "category":"Commercial Area",
            "type":"Public Place"
        }
    ],
    "sg:phone":"+61 7 4922 2031",
    "sg:postcode":"4701",
    "sg:province":"QLD",
    "sg:tags":[
        "heavy",
        "carrier"
    ],
    "wof:name":"Watts Pat",
    "wof:placetype":"venue"
},
  "geometry": {"coordinates":[150.508255005,-23.3532333374],"type":"Point"}
}