{
  "type": "Feature",
  "properties": {
    "addr:full":"41 Lowry St Rochester VIC 3561",
    "addr:housenumber":"41",
    "addr:postcode":"3561",
    "addr:street":"Lowry St",
    "iso:country":"AU",
    "sg:address":"41 Lowry St",
    "sg:city":"Rochester",
    "sg:classifiers":[
        {
            "category":"Food & Beverages",
            "subcategory":"Groceries & Convenience Stores",
            "type":"Retail Goods"
        }
    ],
    "sg:phone":"+61 3 5484 2282",
    "sg:postcode":"3561",
    "sg:province":"VIC",
    "wof:name":"The Willow Milkbar",
    "wof:placetype":"venue"
},
  "geometry": {"coordinates":[144.698318481,-36.3600311279],"type":"Point"}
}