{
  "type": "Feature",
  "properties": {
    "addr:full":"Ste107/ 26 Gibbs St Miranda NSW 2228",
    "addr:housenumber":"26",
    "addr:postcode":"2228",
    "addr:street":"Gibbs St Miranda",
    "iso:country":"AU",
    "sg:address":"Ste107/ 26 Gibbs St",
    "sg:city":"Miranda",
    "sg:classifiers":[
        {
            "category":"Health Services",
            "subcategory":"Doctor",
            "type":"Services"
        }
    ],
    "sg:phone":"+61 2 9526 7333",
    "sg:postcode":"2228",
    "sg:province":"NSW",
    "sg:tags":[
        "medical",
        "practitioner"
    ],
    "wof:name":"Vickers Dr R.",
    "wof:placetype":"venue"
},
  "geometry": {"coordinates":[151.10282898,-34.0367546082],"type":"Point"}
}