{
  "type": "Feature",
  "properties": {
    "addr:full":"126 Nelson Pl Williamstown VIC 3016",
    "addr:housenumber":"126",
    "addr:postcode":"3016",
    "addr:street":"Nelson Pl",
    "iso:country":"AU",
    "sg:address":"126 Nelson Pl",
    "sg:city":"Williamstown",
    "sg:classifiers":[
        {
            "category":"Shopping",
            "subcategory":"Jewelry",
            "type":"Retail Goods"
        }
    ],
    "sg:phone":"+61 3 9399 9888",
    "sg:postcode":"3016",
    "sg:province":"VIC",
    "sg:tags":[
        "jeweller"
    ],
    "wof:name":"J & J Gem Craft",
    "wof:placetype":"venue"
},
  "geometry": {"coordinates":[144.90521240199999,-37.8631744385],"type":"Point"}
}