{
  "type": "Feature",
  "properties": {
    "iso:country":"AU",
    "sg:address":"1163 Mamre Rd",
    "sg:city":"Kemps Creek",
    "sg:classifiers":[
        {
            "category":"Retail",
            "subcategory":"Auto Repair",
            "type":"Services"
        }
    ],
    "sg:phone":"+61 2 9826 2170",
    "sg:postcode":"2171",
    "sg:province":"NSW",
    "sg:tags":[
        "repairer",
        "motor",
        "engineer"
    ],
    "wof:name":"Barone Motor Works",
    "wof:placetype":"venue"
},
  "geometry": {"coordinates":[150.79681396500001,-33.8691368103],"type":"Point"}
}