{
  "type": "Feature",
  "properties": {
    "addr:full":"1 Great Eastern Hwy Cunderdin WA 6407",
    "addr:housenumber":"1",
    "addr:postcode":"6407",
    "addr:street":"Great Eastern Hwy",
    "iso:country":"AU",
    "sg:address":"1 Great Eastern Hwy",
    "sg:city":"Cunderdin",
    "sg:classifiers":[
        {
            "category":"Wholesale",
            "subcategory":"Machinery & Supplies",
            "type":"Manufacturing & Wholesale Goods"
        }
    ],
    "sg:phone":"+61 8 9635 1364",
    "sg:postcode":"6407",
    "sg:province":"WA",
    "sg:tags":[
        "agricultural"
    ],
    "wof:name":"Avon Tractor & Implement",
    "wof:placetype":"venue"
},
  "geometry": {"coordinates":[117.22920227,-31.6517925262],"type":"Point"}
}