{
  "type": "Feature",
  "properties": {
    "addr:full":"K.P. Centre Shop 6 Chatswood Rd Shailer Park QLD 4128",
    "addr:housenumber":"shop 6",
    "addr:postcode":"4128",
    "addr:street":"Chatswood Rd",
    "iso:country":"AU",
    "sg:address":"K.P. Centre Shop 6 Chatswood Rd",
    "sg:city":"Shailer Park",
    "sg:classifiers":[
        {
            "category":"Manufacturing",
            "subcategory":"Food",
            "type":"Manufacturing & Wholesale Goods"
        }
    ],
    "sg:phone":"+61 7 3801 3535",
    "sg:postcode":"4128",
    "sg:province":"QLD",
    "sg:tags":[
        "function",
        "catering"
    ],
    "wof:name":"Good Times Gourmet",
    "wof:placetype":"venue"
},
  "geometry": {"coordinates":[153.16770935100001,-27.6379318237],"type":"Point"}
}