{
  "type": "Feature",
  "properties": {
    "addr:full":"1 Varsity Pde Robina QLD 4226",
    "addr:housenumber":"1",
    "addr:postcode":"4226",
    "addr:street":"Varsity Pde",
    "iso:country":"AU",
    "sg:address":"1 Varsity Pde",
    "sg:city":"Robina",
    "sg:classifiers":[
        {
            "category":"Professional",
            "subcategory":"Computer Services",
            "type":"Services"
        }
    ],
    "sg:phone":"+61 7 5593 2511",
    "sg:postcode":"4226",
    "sg:province":"QLD",
    "sg:tags":[
        "repairs",
        "upgrade",
        "equipment"
    ],
    "wof:name":"Solaris IT",
    "wof:placetype":"venue"
},
  "geometry": {"coordinates":[153.40182495100001,-28.0842571259],"type":"Point"}
}