{
  "type": "Feature",
  "properties": {
    "addr:full":"18 Kingston Ave Richmond SA 5033",
    "addr:housenumber":"18",
    "addr:postcode":"5033",
    "addr:street":"Kingston Ave",
    "iso:country":"AU",
    "sg:address":"18 Kingston Ave",
    "sg:city":"Richmond",
    "sg:classifiers":[
        {
            "category":"Military Area",
            "subcategory":"Air Force Base",
            "type":"Public Place"
        }
    ],
    "sg:phone":"+61 8 8234 6588",
    "sg:postcode":"5033",
    "sg:province":"SA",
    "sg:tags":[
        "wholesaler",
        "bag",
        "mfrs",
        "sack"
    ],
    "wof:name":"Bulk Handling Australia Pty. Ltd.",
    "wof:placetype":"venue"
},
  "geometry": {"coordinates":[138.566696167,-34.9395370483],"type":"Point"}
}