{
  "type": "Feature",
  "properties": {
    "iso:country":"AU",
    "sg:address":"14 Pirie St",
    "sg:city":"Fyshwick",
    "sg:classifiers":[
        {
            "category":"Professional",
            "type":"Services"
        }
    ],
    "sg:phone":"+61 2 6280 9811",
    "sg:postcode":"2609",
    "sg:province":"ACT",
    "sg:tags":[
        "mail",
        "contractor"
    ],
    "wof:name":"Complete Mail And Warehousing",
    "wof:placetype":"venue"
},
  "geometry": {"coordinates":[149.170013428,-35.3260879517],"type":"Point"}
}