{
  "type": "Feature",
  "properties": {
    "addr:full":"19 Burke St Woolloongabba QLD 4102",
    "addr:housenumber":"19",
    "addr:postcode":"4102",
    "addr:street":"Burke St",
    "iso:country":"AU",
    "sg:address":"19 Burke St",
    "sg:city":"Woolloongabba",
    "sg:classifiers":[
        {
            "category":"Education",
            "subcategory":"Dance Studio",
            "type":"Public Place"
        }
    ],
    "sg:phone":"+61 7 3391 1864",
    "sg:postcode":"4102",
    "sg:province":"QLD",
    "sg:tags":[
        "venue",
        "tuition"
    ],
    "wof:name":"Dance Works The",
    "wof:placetype":"venue"
},
  "geometry": {"coordinates":[153.03208923299999,-27.4943180084],"type":"Point"}
}