{
  "type": "Feature",
  "properties": {
    "iso:country":"AU",
    "sg:address":"Cnr Marshall & Farrar Sts",
    "sg:city":"Gilgandra",
    "sg:classifiers":[
        {
            "category":"Farming",
            "subcategory":"Nursery",
            "type":"Manufacturing & Wholesale Goods"
        }
    ],
    "sg:phone":"+61 2 6847 2473",
    "sg:postcode":"2827",
    "sg:province":"NSW",
    "wof:name":"McReaddie's Nursery Wholesale",
    "wof:placetype":"venue"
},
  "geometry": {"coordinates":[148.65005493199999,-31.707611084],"type":"Point"}
}