{
  "type": "Feature",
  "properties": {
    "addr:full":"Unit 5/ 517 St Kilda St Elwood VIC 3184",
    "addr:housenumber":"/ 517",
    "addr:postcode":"3184",
    "addr:street":"St Kilda St",
    "iso:country":"AU",
    "sg:address":"Unit 5/ 517 St Kilda St",
    "sg:city":"Elwood",
    "sg:classifiers":[
        {
            "category":"Home & Garden",
            "subcategory":"Garden Supply",
            "type":"Retail Goods"
        }
    ],
    "sg:phone":"+61 419 574 575",
    "sg:postcode":"3184",
    "sg:province":"VIC",
    "sg:tags":[
        "equipment",
        "hydroponics"
    ],
    "wof:name":"Paterson Alasdair",
    "wof:placetype":"venue"
},
  "geometry": {"coordinates":[144.99200439399999,-37.8837051392],"type":"Point"}
}