{
  "type": "Feature",
  "properties": {
    "addr:full":"123 Duntroon St Hurlstone Park NSW 2193",
    "addr:housenumber":"123",
    "addr:postcode":"2193",
    "addr:street":"Duntroon St",
    "iso:country":"AU",
    "sg:address":"123 Duntroon St",
    "sg:city":"Hurlstone Park",
    "sg:classifiers":[
        {
            "category":"Professional",
            "subcategory":"Art Services",
            "type":"Services"
        }
    ],
    "sg:phone":"+61 2 9559 4905",
    "sg:postcode":"2193",
    "sg:province":"NSW",
    "sg:tags":[
        "decorator",
        "painter"
    ],
    "wof:name":"Harte Bros",
    "wof:placetype":"venue"
},
  "geometry": {"coordinates":[151.132126,-33.91127],"type":"Point"}
}