{
  "type": "Feature",
  "properties": {
    "iso:country":"AU",
    "sg:address":"Suite 10 297 Old Cleveland Rd",
    "sg:city":"Coorparoo",
    "sg:classifiers":[
        {
            "category":"Professional",
            "subcategory":"Detective & Security Services",
            "type":"Services"
        }
    ],
    "sg:phone":"+61 7 3847 6097",
    "sg:postcode":"4151",
    "sg:province":"QLD",
    "sg:tags":[
        "guard",
        "patrol"
    ],
    "wof:name":"Hunter Security & Detection Services Pty Ltd",
    "wof:placetype":"venue"
},
  "geometry": {"coordinates":[153.059036255,-27.49467659],"type":"Point"}
}