{
  "type": "Feature",
  "properties": {
    "addr:full":"Chesterfield Drv (Cnr Yirrigan Drv) Mirrabooka WA 6061",
    "addr:postcode":"6061",
    "addr:street":"Chesterfield Drv Cnr Yirrigan Drv",
    "iso:country":"AU",
    "sg:address":"Chesterfield Drv (Cnr Yirrigan Drv)",
    "sg:city":"Mirrabooka",
    "sg:classifiers":[
        {
            "category":"Travel",
            "subcategory":"Hotels & Motels",
            "type":"Entertainment"
        }
    ],
    "sg:phone":"+61 8 9344 5050",
    "sg:postcode":"6061",
    "sg:province":"WA",
    "sg:tags":[
        "accommodation"
    ],
    "wof:name":"Brindusa",
    "wof:placetype":"venue"
},
  "geometry": {"coordinates":[115.863586426,-31.8698768616],"type":"Point"}
}