{
  "type": "Feature",
  "properties": {
    "addr:full":"Chirnside Park Shopping Centre Level 1, 150 Maroondah Hwy Chirnside Park VIC 3116",
    "addr:housenumber":"150",
    "addr:postcode":"3116",
    "addr:street":"Maroondah Hwy",
    "iso:country":"AU",
    "sg:address":"Chirnside Park Shopping Centre Level 1, 150 Maroondah Hwy",
    "sg:city":"Chirnside Park",
    "sg:classifiers":[
        {
            "category":"Retail",
            "subcategory":"Repair Shop",
            "type":"Services"
        }
    ],
    "sg:phone":"+61 3 9726 7576",
    "sg:postcode":"3116",
    "sg:province":"VIC",
    "sg:tags":[
        "mending",
        "clothing",
        "alteration"
    ],
    "wof:name":"Alter It Clothing Alterations",
    "wof:placetype":"venue"
},
  "geometry": {"coordinates":[145.355072022,-37.7574462891],"type":"Point"}
}