{
  "type": "Feature",
  "properties": {
    "addr:full":"Unit 1/ 11 Christine Pl Capalaba QLD 4157",
    "addr:housenumber":"11",
    "addr:postcode":"4157",
    "addr:street":"Christine Pl",
    "iso:country":"AU",
    "sg:address":"Unit 1/ 11 Christine Pl",
    "sg:city":"Capalaba",
    "sg:classifiers":[
        {
            "category":"Wholesale",
            "subcategory":"Non-durable Goods",
            "type":"Manufacturing & Wholesale Goods"
        }
    ],
    "sg:phone":"+61 7 3823 5009",
    "sg:postcode":"4157",
    "sg:province":"QLD",
    "sg:tags":[
        "wholesaler",
        "craft",
        "mfrs"
    ],
    "wof:name":"Downunder Direct Wholesale Scrapbook Supplies",
    "wof:placetype":"venue"
},
  "geometry": {"coordinates":[153.20510864299999,-27.532037735],"type":"Point"}
}