{
  "type": "Feature",
  "properties": {
    "addr:full":"PO Box 476 Merimbula NSW 2548",
    "addr:postcode":"2548",
    "iso:country":"AU",
    "sg:address":"PO Box 476",
    "sg:city":"Merimbula",
    "sg:classifiers":[
        {
            "category":"Banks & Credit Unions",
            "subcategory":"Bank",
            "type":"Services"
        }
    ],
    "sg:phone":"+61 2 6494 1561",
    "sg:postcode":"2548",
    "sg:province":"NSW",
    "sg:tags":[
        "broker",
        "mortgage"
    ],
    "wof:name":"Austin Finance",
    "wof:placetype":"venue"
},
  "geometry": {"coordinates":[149.905792236,-36.8883018494],"type":"Point"}
}