{
  "type": "Feature",
  "properties": {
    "addr:full":"3 Sandakan Rd Revesby NSW 2212",
    "addr:housenumber":"3",
    "addr:postcode":"2212",
    "addr:street":"Sandakan Rd",
    "iso:country":"AU",
    "sg:address":"3 Sandakan Rd",
    "sg:city":"Revesby",
    "sg:classifiers":[
        {
            "category":"Building & Trades",
            "subcategory":"Construction",
            "type":"Services"
        }
    ],
    "sg:phone":"+61 2 9773 5019",
    "sg:postcode":"2212",
    "sg:province":"NSW",
    "sg:tags":[
        "contractor"
    ],
    "wof:name":"Bell Ron Constructions",
    "wof:placetype":"venue"
},
  "geometry": {"coordinates":[151.015793,-33.96701],"type":"Point"}
}