{
  "type": "Feature",
  "properties": {
    "iso:country":"AU",
    "sg:address":"Shop 116, Paradise Centre Surfers Paradise",
    "sg:city":"Surfers Paradise",
    "sg:classifiers":[
        {
            "category":"Personal",
            "subcategory":"Beauty Salon",
            "type":"Services"
        }
    ],
    "sg:phone":"+61 7 5592 1433",
    "sg:postcode":"4217",
    "sg:province":"QLD",
    "wof:name":"Boldly Beautiful Beauty Salon",
    "wof:placetype":"venue"
},
  "geometry": {"coordinates":[153.42854309099999,-28.00233078],"type":"Point"}
}