{
  "type": "Feature",
  "properties": {
    "addr:full":"PO Box 1165 Noosaville QLD 4566",
    "addr:postcode":"4566",
    "iso:country":"AU",
    "sg:address":"PO Box 1165",
    "sg:city":"Noosaville",
    "sg:classifiers":[
        {
            "category":"Building & Trades",
            "subcategory":"Construction",
            "type":"Services"
        }
    ],
    "sg:phone":"+61 7 5474 4470",
    "sg:postcode":"4566",
    "sg:province":"QLD",
    "sg:tags":[
        "home",
        "air conditioning"
    ],
    "wof:name":"Laser Electrical Noosa",
    "wof:placetype":"venue"
},
  "geometry": {"coordinates":[153.05848693900001,-26.4247493744],"type":"Point"}
}