{
  "type": "Feature",
  "properties": {
    "addr:full":"1/ 52 Alfred Rd Chipping Norton NSW 2170",
    "addr:housenumber":"/ 52",
    "addr:postcode":"2170",
    "addr:street":"Alfred Rd",
    "iso:country":"AU",
    "sg:address":"1/ 52 Alfred Rd",
    "sg:city":"Chipping Norton",
    "sg:classifiers":[
        {
            "category":"Wholesale",
            "subcategory":"Non-durable Goods",
            "type":"Manufacturing & Wholesale Goods"
        }
    ],
    "sg:phone":"+61 2 9755 3327",
    "sg:postcode":"2170",
    "sg:province":"NSW",
    "sg:tags":[
        "wholesaler",
        "craft",
        "mfrs"
    ],
    "wof:name":"Paper and Beads",
    "wof:placetype":"venue"
},
  "geometry": {"coordinates":[150.96246337900001,-33.9230232239],"type":"Point"}
}