{
  "type": "Feature",
  "properties": {
    "addr:full":"143 Woodlands Drv Braeside VIC 3195",
    "addr:housenumber":"143",
    "addr:postcode":"3195",
    "addr:street":"Woodlands Drv",
    "iso:country":"AU",
    "sg:address":"143 Woodlands Drv",
    "sg:city":"Braeside",
    "sg:classifiers":[
        {
            "category":"Shopping",
            "subcategory":"Stationery & Office Supplies",
            "type":"Retail Goods"
        }
    ],
    "sg:phone":"+61 3 9587 2600",
    "sg:postcode":"3195",
    "sg:province":"VIC",
    "sg:tags":[
        "screen",
        "printing"
    ],
    "wof:name":"TAS Screen Printing Equipment Pty Ltd",
    "wof:placetype":"venue"
},
  "geometry": {"coordinates":[145.119232178,-37.9986495972],"type":"Point"}
}