{
  "type": "Feature",
  "properties": {
    "iso:country":"AU",
    "sg:address":"14 Lady Williams Pl",
    "sg:city":"Golden Grove",
    "sg:classifiers":[
        {
            "category":"Home & Garden",
            "subcategory":"Building Materials",
            "type":"Retail Goods"
        }
    ],
    "sg:phone":"+61 412 813 666",
    "sg:postcode":"5125",
    "sg:province":"SA",
    "sg:tags":[
        "lawn",
        "cutting",
        "maintenance"
    ],
    "wof:name":"Mick's Lawnmowing Service",
    "wof:placetype":"venue"
},
  "geometry": {"coordinates":[138.708832,-34.784191],"type":"Point"}
}