{
  "type": "Feature",
  "properties": {
    "iso:country":"AU",
    "sg:address":"Shop 8 Tannum Central",
    "sg:city":"Tannum Sands",
    "sg:classifiers":[
        {
            "category":"Real Estate",
            "subcategory":"Real Estate Agent",
            "type":"Services"
        }
    ],
    "sg:phone":"+61 7 4973 8777",
    "sg:postcode":"4680",
    "sg:province":"QLD",
    "wof:name":"Elders Real Estate",
    "wof:placetype":"venue"
},
  "geometry": {"coordinates":[151.36920165999999,-24.0320892334],"type":"Point"}
}