{
  "type": "Feature",
  "properties": {
    "iso:country":"AU",
    "sg:address":"Unit 2, 4 Wade Crt",
    "sg:city":"Girrawheen",
    "sg:classifiers":[
        {
            "category":"Health Services",
            "subcategory":"Dentist",
            "type":"Services"
        }
    ],
    "sg:phone":"+61 8 9342 2205",
    "sg:postcode":"6064",
    "sg:province":"WA",
    "wof:name":"Red Apple Dental Care",
    "wof:placetype":"venue"
},
  "geometry": {"coordinates":[115.839233398,-31.838054657],"type":"Point"}
}