{
  "type": "Feature",
  "properties": {
    "iso:country":"AU",
    "sg:address":"69- 75 Campbell St",
    "sg:city":"Swan Hill",
    "sg:classifiers":[
        {
            "category":"Retail",
            "subcategory":"Auto Repair",
            "type":"Services"
        }
    ],
    "sg:phone":"+61 3 5032 1064",
    "sg:postcode":"3585",
    "sg:province":"VIC",
    "sg:tags":[
        "gas",
        "conversion",
        "natural",
        "lp",
        "vehicle"
    ],
    "wof:name":"Holts Auto Service Pty Ltd",
    "wof:placetype":"venue"
},
  "geometry": {"coordinates":[143.559067,-35.336246],"type":"Point"}
}