{
  "type": "Feature",
  "properties": {
    "iso:country":"AU",
    "sg:address":"First Floor 451- 459 Hunter St",
    "sg:city":"Newcastle",
    "sg:classifiers":[
        {
            "category":"Health Services",
            "subcategory":"Dentist",
            "type":"Services"
        }
    ],
    "sg:phone":"+61 2 4926 5499",
    "sg:postcode":"2300",
    "sg:province":"NSW",
    "wof:name":"Hill G S",
    "wof:placetype":"venue"
},
  "geometry": {"coordinates":[151.770905,-32.926968],"type":"Point"}
}