{
  "type": "Feature",
  "properties": {
    "addr:full":"35 High St Mansfield VIC 3722",
    "addr:housenumber":"35",
    "addr:postcode":"3722",
    "addr:street":"High St",
    "iso:country":"AU",
    "sg:address":"35 High St",
    "sg:city":"Mansfield",
    "sg:classifiers":[
        {
            "category":"Shopping",
            "subcategory":"Clothing, Apparel, & Fashions",
            "type":"Retail Goods"
        }
    ],
    "sg:phone":"+61 3 5775 2932",
    "sg:postcode":"3722",
    "sg:province":"VIC",
    "sg:tags":[
        "jean"
    ],
    "wof:name":"Mansfield Menswear",
    "wof:placetype":"venue"
},
  "geometry": {"coordinates":[146.09063720699999,-37.0522422791],"type":"Point"}
}