{
  "type": "Feature",
  "properties": {
    "addr:full":"9 Bowers Pl Queanbeyan NSW 2620",
    "addr:housenumber":"9",
    "addr:postcode":"2620",
    "addr:street":"Bowers Pl",
    "iso:country":"AU",
    "sg:address":"9 Bowers Pl",
    "sg:city":"Queanbeyan",
    "sg:classifiers":[
        {
            "category":"Building & Trades",
            "subcategory":"Plumbing",
            "type":"Services"
        }
    ],
    "sg:phone":"+61 2 6299 1995",
    "sg:postcode":"2620",
    "sg:province":"NSW",
    "sg:tags":[
        "drainers"
    ],
    "wof:name":"ACT Septic Cleaning Services",
    "wof:placetype":"venue"
},
  "geometry": {"coordinates":[149.222900391,-35.3618240356],"type":"Point"}
}