{
  "type": "Feature",
  "properties": {
    "iso:country":"AU",
    "sg:address":"Allora Drv",
    "sg:city":"Maroochydore",
    "sg:classifiers":[
        {
            "category":"Banks & Credit Unions",
            "subcategory":"Financial Services",
            "type":"Services"
        }
    ],
    "sg:phone":"+61 7 5443 5422",
    "sg:postcode":"4558",
    "sg:province":"QLD",
    "sg:tags":[
        "advisory",
        "planning",
        "retirement"
    ],
    "wof:name":"Allora Gardens",
    "wof:placetype":"venue"
},
  "geometry": {"coordinates":[153.06776428200001,-26.6594276428],"type":"Point"}
}