{
  "type": "Feature",
  "properties": {
    "iso:country":"AU",
    "sg:address":"Podium Level, Mincom Building 192 Ann St",
    "sg:city":"Brisbane",
    "sg:classifiers":[
        {
            "category":"Military Area",
            "subcategory":"Armory",
            "type":"Public Place"
        }
    ],
    "sg:phone":"+61 1800 624 977",
    "sg:postcode":"4000",
    "sg:province":"QLD",
    "sg:tags":[
        "teleconferencing"
    ],
    "sg:website":"http://www.ivision.com.au",
    "wof:name":"Integrated Vision",
    "wof:placetype":"venue"
},
  "geometry": {"coordinates":[153.02517700199999,-27.4669017792],"type":"Point"}
}