{
  "type": "Feature",
  "properties": {
    "iso:country":"AU",
    "sg:address":"91 Wembley Rd",
    "sg:city":"Woodridge",
    "sg:classifiers":[
        {
            "category":"Organizations",
            "subcategory":"Non-profit Organization",
            "type":"Services"
        }
    ],
    "sg:phone":"+61 7 3208 7944",
    "sg:postcode":"4114",
    "sg:province":"QLD",
    "sg:tags":[
        "support",
        "disability",
        "organisation"
    ],
    "wof:name":"Nova Employment and Training Program Inc",
    "wof:placetype":"venue"
},
  "geometry": {"coordinates":[153.10989379899999,-27.6414909363],"type":"Point"}
}