{
  "type": "Feature",
  "properties": {
    "addr:full":"378 Payneham Rd Payneham SA 5070",
    "addr:housenumber":"378",
    "addr:postcode":"5070",
    "addr:street":"Payneham Rd",
    "iso:country":"AU",
    "sg:address":"378 Payneham Rd",
    "sg:city":"Payneham",
    "sg:classifiers":[
        {
            "category":"Real Estate",
            "subcategory":"Real Estate Agent",
            "type":"Services"
        }
    ],
    "sg:phone":"+61 8 8337 4441",
    "sg:postcode":"5070",
    "sg:province":"SA",
    "wof:name":"Brock Harcourts",
    "wof:placetype":"venue"
},
  "geometry": {"coordinates":[138.64244079599999,-34.895198822],"type":"Point"}
}