{
  "type": "Feature",
  "properties": {
    "addr:full":"133 Frost Rd Salisbury South SA 5106",
    "addr:housenumber":"133",
    "addr:postcode":"5106",
    "addr:street":"Frost Rd",
    "iso:country":"AU",
    "sg:address":"133 Frost Rd",
    "sg:city":"Salisbury South",
    "sg:classifiers":[
        {
            "category":"Health Services",
            "subcategory":"Doctor",
            "type":"Services"
        }
    ],
    "sg:phone":"+61 8 8250 8687",
    "sg:postcode":"5106",
    "sg:province":"SA",
    "sg:tags":[
        "medical",
        "practitioner"
    ],
    "wof:name":"Miller, Moore & Partners Drs",
    "wof:placetype":"venue"
},
  "geometry": {"coordinates":[138.65249600000001,-34.782215],"type":"Point"}
}