{
  "type": "Feature",
  "properties": {
    "addr:full":"Treeview Pl Tuggerah NSW 2259",
    "addr:postcode":"2259",
    "addr:street":"Treeview Pl",
    "iso:country":"AU",
    "sg:address":"Treeview Pl",
    "sg:city":"Tuggerah",
    "sg:classifiers":[
        {
            "category":"Wholesale",
            "subcategory":"Apparel",
            "type":"Manufacturing & Wholesale Goods"
        }
    ],
    "sg:phone":"+61 2 4353 7633",
    "sg:postcode":"2259",
    "sg:province":"NSW",
    "sg:tags":[
        "wholesaler",
        "men's",
        "mfrs",
        "sportswear"
    ],
    "wof:name":"Playmore Sportswear (Aus)",
    "wof:placetype":"venue"
},
  "geometry": {"coordinates":[151.41177368199999,-33.3038368225],"type":"Point"}
}