{
  "type": "Feature",
  "properties": {
    "iso:country":"AU",
    "sg:address":"221 Waymouth St",
    "sg:city":"Adelaide",
    "sg:classifiers":[
        {
            "category":"Personal",
            "subcategory":"Adult",
            "type":"Services"
        }
    ],
    "sg:phone":"+61 8 8231 0065",
    "sg:postcode":"5000",
    "sg:province":"SA",
    "sg:tags":[
        "product"
    ],
    "wof:name":"Bad Boyz Australia",
    "wof:placetype":"venue"
},
  "geometry": {"coordinates":[138.59889221200001,-34.9259414673],"type":"Point"}
}