{
  "type": "Feature",
  "properties": {
    "addr:full":"4 Borden Rd Marangaroo WA 6064",
    "addr:housenumber":"4",
    "addr:postcode":"6064",
    "addr:street":"Borden Rd",
    "iso:country":"AU",
    "sg:address":"4 Borden Rd",
    "sg:city":"Marangaroo",
    "sg:classifiers":[
        {
            "category":"Building & Trades",
            "subcategory":"Construction",
            "type":"Services"
        }
    ],
    "sg:phone":"+61 419 865 865",
    "sg:postcode":"6064",
    "sg:province":"WA",
    "sg:tags":[
        "earth",
        "excavating",
        "moving",
        "contractor"
    ],
    "wof:name":"Gopher Earthmoving",
    "wof:placetype":"venue"
},
  "geometry": {"coordinates":[115.822189331,-31.8332462311],"type":"Point"}
}