{
  "type": "Feature",
  "properties": {
    "iso:country":"AU",
    "sg:address":"55 Willonga St",
    "sg:city":"Essendon North",
    "sg:classifiers":[
        {
            "category":"Building & Trades",
            "subcategory":"Construction",
            "type":"Services"
        }
    ],
    "sg:phone":"+61 3 9379 8730",
    "sg:postcode":"3041",
    "sg:province":"VIC",
    "sg:tags":[
        "plasterboard",
        "plasterer",
        "fixer"
    ],
    "wof:name":"Dennerley's Plastering",
    "wof:placetype":"venue"
},
  "geometry": {"coordinates":[144.913986206,-37.7251777649],"type":"Point"}
}