{
  "type": "Feature",
  "properties": {
    "addr:full":"Elizabeth City Centre Cnr Main North Rd & Phillip Hwy Elizabeth SA 5112",
    "addr:postcode":"5112",
    "addr:street":"Cnr Main North Rd & Phillip Hwy",
    "iso:country":"AU",
    "sg:address":"Elizabeth City Centre Cnr Main North Rd & Phillip Hwy",
    "sg:city":"Elizabeth",
    "sg:classifiers":[
        {
            "category":"Shopping",
            "subcategory":"Optical Goods",
            "type":"Retail Goods"
        }
    ],
    "sg:phone":"+61 8 8255 9755",
    "sg:postcode":"5112",
    "sg:province":"SA",
    "sg:tags":[
        "dispenser",
        "prescription"
    ],
    "wof:name":"National Pharmacies Optical",
    "wof:placetype":"venue"
},
  "geometry": {"coordinates":[138.67356872600001,-34.7219696045],"type":"Point"}
}