{
  "type": "Feature",
  "properties": {
    "iso:country":"AU",
    "sg:address":"49 Salamanca Pl",
    "sg:city":"Hobart",
    "sg:classifiers":[
        {
            "category":"Communications",
            "type":"Services"
        }
    ],
    "sg:phone":"+61 3 6223 5195",
    "sg:postcode":"7000",
    "sg:province":"TAS",
    "sg:tags":[
        "translation"
    ],
    "wof:name":"AJPR Australia Japan Public Relations Pty Ltd",
    "wof:placetype":"venue"
},
  "geometry": {"coordinates":[147.33262634299999,-42.8868026733],"type":"Point"}
}