{
  "type": "Feature",
  "properties": {
    "addr:full":"Shop 4, 37 Alexandra St Hunters Hill NSW 2110",
    "addr:housenumber":"shop;37",
    "addr:postcode":"2110",
    "addr:street":"Alexandra St",
    "iso:country":"AU",
    "sg:address":"Shop 4, 37 Alexandra St",
    "sg:city":"Hunters Hill",
    "sg:classifiers":[
        {
            "category":"Health Services",
            "subcategory":"Health Practitioner",
            "type":"Services"
        }
    ],
    "sg:phone":"+61 2 9817 2566",
    "sg:postcode":"2110",
    "sg:province":"NSW",
    "sg:tags":[
        "naturopath"
    ],
    "sg:website":"http://www.justforyourhealth.com.au",
    "wof:name":"Just For Your Health",
    "wof:placetype":"venue"
},
  "geometry": {"coordinates":[151.15565490700001,-33.8351478577],"type":"Point"}
}