{
  "type": "Feature",
  "properties": {
    "addr:full":"508 Freemans Drv Cooranbong NSW 2265",
    "addr:housenumber":"508",
    "addr:postcode":"2265",
    "addr:street":"Freemans Drv",
    "iso:country":"AU",
    "sg:address":"508 Freemans Drv",
    "sg:city":"Cooranbong",
    "sg:classifiers":[
        {
            "category":"Manufacturing",
            "subcategory":"Food",
            "type":"Manufacturing & Wholesale Goods"
        }
    ],
    "sg:phone":"+61 2 4977 2128",
    "sg:postcode":"2265",
    "sg:province":"NSW",
    "sg:tags":[
        "function",
        "catering"
    ],
    "wof:name":"Spiffy Spit Roasts And Party Hire",
    "wof:placetype":"venue"
},
  "geometry": {"coordinates":[151.46933000000001,-33.065273],"type":"Point"}
}