{
  "type": "Feature",
  "properties": {
    "addr:full":"3/ 135 Ferny Way Ferny Hills QLD 4055",
    "addr:housenumber":"/ 135",
    "addr:postcode":"4055",
    "addr:street":"Ferny Way",
    "iso:country":"AU",
    "sg:address":"3/ 135 Ferny Way",
    "sg:city":"Ferny Hills",
    "sg:classifiers":[
        {
            "category":"Health Services",
            "subcategory":"Chiropractor",
            "type":"Services"
        }
    ],
    "sg:phone":"+61 7 3351 0933",
    "sg:postcode":"4055",
    "sg:province":"QLD",
    "wof:name":"Travis West",
    "wof:placetype":"venue"
},
  "geometry": {"coordinates":[152.93760681099999,-27.4007339478],"type":"Point"}
}