{
  "type": "Feature",
  "properties": {
    "addr:full":"Unit 1/ 14 Rodwell St Archerfield QLD 4108",
    "addr:housenumber":"14",
    "addr:postcode":"4108",
    "addr:street":"Rodwell St",
    "iso:country":"AU",
    "sg:address":"Unit 1/ 14 Rodwell St",
    "sg:city":"Archerfield",
    "sg:classifiers":[
        {
            "category":"Retail",
            "subcategory":"Auto Repair",
            "type":"Services"
        }
    ],
    "sg:phone":"+61 7 3277 9123",
    "sg:postcode":"4108",
    "sg:province":"QLD",
    "sg:tags":[
        "sport",
        "motor"
    ],
    "wof:name":"Competition Coatings Qld",
    "wof:placetype":"venue"
},
  "geometry": {"coordinates":[153.017044067,-27.5602855682],"type":"Point"}
}