{
  "type": "Feature",
  "properties": {
    "addr:full":"88 Hanson Rd Gladstone QLD 4680",
    "addr:housenumber":"88",
    "addr:postcode":"4680",
    "addr:street":"Hanson Rd",
    "iso:country":"AU",
    "sg:address":"88 Hanson Rd",
    "sg:city":"Gladstone",
    "sg:classifiers":[
        {
            "category":"Utilities",
            "type":"Services"
        }
    ],
    "sg:phone":"+61 7 4972 7218",
    "sg:postcode":"4680",
    "sg:province":"QLD",
    "sg:tags":[
        "refrigeration",
        "industrial",
        "commercial",
        "retail"
    ],
    "wof:name":"Gladstone Refrigeration & Air-Conditioning",
    "wof:placetype":"venue"
},
  "geometry": {"coordinates":[151.24223327600001,-23.8405361176],"type":"Point"}
}