{
  "type": "Feature",
  "properties": {
    "addr:full":"30- 32 Adderley St East Lidcombe NSW 2141",
    "addr:housenumber":"32",
    "addr:postcode":"2141",
    "addr:street":"Adderley St East",
    "iso:country":"AU",
    "sg:address":"30- 32 Adderley St East",
    "sg:city":"Lidcombe",
    "sg:classifiers":[
        {
            "category":"Manufacturing",
            "subcategory":"Metals",
            "type":"Manufacturing & Wholesale Goods"
        }
    ],
    "sg:phone":"+61 2 9748 0660",
    "sg:postcode":"2141",
    "sg:province":"NSW",
    "sg:tags":[
        "sheet",
        "worker"
    ],
    "wof:name":"Hy-Way Sheetmetal Work",
    "wof:placetype":"venue"
},
  "geometry": {"coordinates":[151.045852661,-33.8446235657],"type":"Point"}
}