{
  "type": "Feature",
  "properties": {
    "addr:full":"3 Forsyth St Willoughby NSW 2068",
    "addr:housenumber":"3",
    "addr:postcode":"2068",
    "addr:street":"Forsyth St",
    "iso:country":"AU",
    "sg:address":"3 Forsyth St",
    "sg:city":"Willoughby",
    "sg:classifiers":[
        {
            "category":"Government",
            "subcategory":"Court House",
            "type":"Public Place"
        }
    ],
    "sg:phone":"+61 2 9967 0801",
    "sg:postcode":"2068",
    "sg:province":"NSW",
    "sg:tags":[
        "personal",
        "marriage",
        "family",
        "counselling"
    ],
    "wof:name":"Margaret McGovern Counselling",
    "wof:placetype":"venue"
},
  "geometry": {"coordinates":[151.20045471200001,-33.7967262268],"type":"Point"}
}