{
  "type": "Feature",
  "properties": {
    "addr:full":"30 Teasdale Drv Nerang QLD 4211",
    "addr:housenumber":"30",
    "addr:postcode":"4211",
    "addr:street":"Teasdale Drv",
    "iso:country":"AU",
    "sg:address":"30 Teasdale Drv",
    "sg:city":"Nerang",
    "sg:classifiers":[
        {
            "category":"Real Estate",
            "subcategory":"Real Estate Agent",
            "type":"Services"
        }
    ],
    "sg:phone":"+61 7 5527 3254",
    "sg:postcode":"4211",
    "sg:province":"QLD",
    "wof:name":"Glenn Ferguson Independent Real Estate",
    "wof:placetype":"venue"
},
  "geometry": {"coordinates":[153.30926513700001,-28.0065135956],"type":"Point"}
}