{
  "type": "Feature",
  "properties": {
    "iso:country":"AU",
    "sg:address":"22 Durham Rd",
    "sg:city":"Cooee",
    "sg:classifiers":[
        {
            "category":"Professional",
            "subcategory":"Engineering",
            "type":"Services"
        }
    ],
    "sg:phone":"+61 3 6431 5089",
    "sg:postcode":"7320",
    "sg:province":"TAS",
    "sg:tags":[
        "diesel",
        "engineer"
    ],
    "wof:name":"Burnie Fuel Injection Service",
    "wof:placetype":"venue"
},
  "geometry": {"coordinates":[145.87402299999999,-41.043804],"type":"Point"}
}