{
  "type": "Feature",
  "properties": {
    "iso:country":"AU",
    "sg:address":"1037 Centre Rd",
    "sg:city":"Knoxfield",
    "sg:classifiers":[
        {
            "category":"Retail",
            "subcategory":"Auto Repair",
            "type":"Services"
        }
    ],
    "sg:phone":"+61 3 9579 3099",
    "sg:postcode":"3180",
    "sg:province":"VIC",
    "sg:tags":[
        "bus",
        "truck"
    ],
    "wof:name":"Eastcoast Truck and Bus Service Centres",
    "wof:placetype":"venue"
},
  "geometry": {"coordinates":[145.233032227,-37.903087616],"type":"Point"}
}