{
  "type": "Feature",
  "properties": {
    "addr:full":"RMB 11 Manypeaks WA 6328",
    "addr:housenumber":"11",
    "addr:postcode":"6328",
    "addr:street":"Manypeaks",
    "iso:country":"AU",
    "sg:address":"RMB 11",
    "sg:city":"Manypeaks",
    "sg:classifiers":[
        {
            "category":"Farming",
            "subcategory":"Farm",
            "type":"Manufacturing & Wholesale Goods"
        }
    ],
    "sg:phone":"+61 8 9846 1219",
    "sg:postcode":"6328",
    "sg:province":"WA",
    "sg:tags":[
        "farmer"
    ],
    "wof:name":"Blight R O",
    "wof:placetype":"venue"
},
  "geometry": {"coordinates":[118.17420959499999,-34.8376312256],"type":"Point"}
}