{
  "type": "Feature",
  "properties": {
    "addr:full":"PO Box 11 Woodbridge TAS 7162",
    "addr:postcode":"7162",
    "iso:country":"AU",
    "sg:address":"PO Box 11",
    "sg:city":"Woodbridge",
    "sg:classifiers":[
        {
            "category":"Building & Trades",
            "subcategory":"Landscaping Services",
            "type":"Services"
        }
    ],
    "sg:phone":"+61 427 873 648",
    "sg:postcode":"7162",
    "sg:province":"TAS",
    "sg:tags":[
        "stump",
        "tree",
        "felling",
        "removal"
    ],
    "wof:name":"Ron Short",
    "wof:placetype":"venue"
},
  "geometry": {"coordinates":[147.23794555699999,-43.1596488953],"type":"Point"}
}