{
  "type": "Feature",
  "properties": {
    "iso:country":"AU",
    "sg:address":"Smith St",
    "sg:city":"Daylesford",
    "sg:classifiers":[
        {
            "category":"Education",
            "subcategory":"School",
            "type":"Public Place"
        }
    ],
    "sg:phone":"+61 3 5348 1261",
    "sg:postcode":"3460",
    "sg:province":"VIC",
    "sg:tags":[
        "co-educational"
    ],
    "wof:name":"St Michael's",
    "wof:placetype":"venue"
},
  "geometry": {"coordinates":[144.150482178,-37.3393440247],"type":"Point"}
}