{
  "type": "Feature",
  "properties": {
    "iso:country":"AU",
    "sg:address":"Shop 2, Cnr Freshwater & Bideford Sts",
    "sg:city":"Torquay",
    "sg:classifiers":[
        {
            "category":"Personal",
            "subcategory":"Beauty Salon",
            "type":"Services"
        }
    ],
    "sg:phone":"+61 7 4125 4220",
    "sg:postcode":"4655",
    "sg:province":"QLD",
    "sg:tags":[
        "hairdresser"
    ],
    "wof:name":"Headlines For Hair & Beauty",
    "wof:placetype":"venue"
},
  "geometry": {"coordinates":[152.86767599999999,-25.285353],"type":"Point"}
}