{
  "type": "Feature",
  "properties": {
    "addr:full":"192 Canley Vale Rd Canley Heights NSW 2166",
    "addr:housenumber":"192",
    "addr:postcode":"2166",
    "addr:street":"Canley Vale Rd",
    "iso:country":"AU",
    "sg:address":"192 Canley Vale Rd",
    "sg:city":"Canley Heights",
    "sg:classifiers":[
        {
            "category":"Professional",
            "subcategory":"Computer Services",
            "type":"Services"
        }
    ],
    "sg:phone":"+61 2 9724 7979",
    "sg:postcode":"2166",
    "sg:province":"NSW",
    "sg:tags":[
        "package",
        "software"
    ],
    "wof:name":"Sydney Realty Administration Pty Ltd",
    "wof:placetype":"venue"
},
  "geometry": {"coordinates":[150.92669677699999,-33.8841285706],"type":"Point"}
}