{
  "type": "Feature",
  "properties": {
    "iso:country":"AU",
    "sg:address":"39b Macedonia St",
    "sg:city":"Naval Base",
    "sg:classifiers":[
        {
            "category":"Building & Trades",
            "subcategory":"Construction",
            "type":"Services"
        }
    ],
    "sg:phone":"+61 8 9437 1101",
    "sg:postcode":"6165",
    "sg:province":"WA",
    "sg:tags":[
        "renovation",
        "alterations",
        "extension",
        "contractor"
    ],
    "wof:name":"P.F.M. Construction",
    "wof:placetype":"venue"
},
  "geometry": {"coordinates":[115.781799,-32.201588],"type":"Point"}
}