{
  "type": "Feature",
  "properties": {
    "iso:country":"AU",
    "sg:address":"16 Lohse St",
    "sg:city":"Laverton",
    "sg:classifiers":[
        {
            "category":"Health Services",
            "subcategory":"Health Practitioner",
            "type":"Services"
        }
    ],
    "sg:phone":"+61 3 9931 0866",
    "sg:postcode":"3028",
    "sg:province":"VIC",
    "sg:tags":[
        "naturopath"
    ],
    "wof:name":"Wilson Wendy",
    "wof:placetype":"venue"
},
  "geometry": {"coordinates":[144.77143899999999,-37.86319],"type":"Point"}
}