{
  "type": "Feature",
  "properties": {
    "addr:full":"27 Dalby St Jandowae QLD 4410",
    "addr:housenumber":"27",
    "addr:postcode":"4410",
    "addr:street":"Dalby St",
    "iso:country":"AU",
    "sg:address":"27 Dalby St",
    "sg:city":"Jandowae",
    "sg:classifiers":[
        {
            "category":"Retail",
            "subcategory":"Veterinary Services",
            "type":"Services"
        }
    ],
    "sg:phone":"+61 7 4663 1315",
    "sg:postcode":"4410",
    "sg:province":"QLD",
    "sg:tags":[
        "surgeon"
    ],
    "wof:name":"Bell Veterinary Services",
    "wof:placetype":"venue"
},
  "geometry": {"coordinates":[151.108154297,-26.7796516418],"type":"Point"}
}