{
  "type": "Feature",
  "properties": {
    "addr:full":"Suite 11 56 Creaney Drv Kingsley WA 6026",
    "addr:housenumber":"56",
    "addr:postcode":"6026",
    "addr:street":"Creaney Drv",
    "iso:country":"AU",
    "sg:address":"Suite 11 56 Creaney Drv",
    "sg:city":"Kingsley",
    "sg:classifiers":[
        {
            "category":"Banks & Credit Unions",
            "subcategory":"Financial Services",
            "type":"Services"
        }
    ],
    "sg:phone":"+61 8 9309 3606",
    "sg:postcode":"6026",
    "sg:province":"WA",
    "sg:tags":[
        "planning"
    ],
    "wof:name":"James & Assoc",
    "wof:placetype":"venue"
},
  "geometry": {"coordinates":[115.790412903,-31.8077640533],"type":"Point"}
}