{
  "type": "Feature",
  "properties": {
    "iso:country":"AU",
    "sg:address":"54 Edinburgh Rd",
    "sg:city":"Forrestfield",
    "sg:classifiers":[
        {
            "category":"Health Services",
            "subcategory":"Doctor",
            "type":"Services"
        }
    ],
    "sg:phone":"+61 8 9453 6999",
    "sg:postcode":"6058",
    "sg:province":"WA",
    "sg:tags":[
        "medical",
        "practitioner"
    ],
    "wof:name":"Wignell S. Dr",
    "wof:placetype":"venue"
},
  "geometry": {"coordinates":[116.010719299,-31.9955787659],"type":"Point"}
}