{
  "type": "Feature",
  "properties": {
    "iso:country":"AU",
    "sg:address":"Ingham Rd",
    "sg:city":"Townsville",
    "sg:classifiers":[
        {
            "category":"Manufacturing",
            "subcategory":"Retail Goods",
            "type":"Manufacturing & Wholesale Goods"
        }
    ],
    "sg:phone":"+61 429 786 748",
    "sg:postcode":"4810",
    "sg:province":"QLD",
    "sg:tags":[
        "merchant",
        "pump",
        "mfrs"
    ],
    "wof:name":"Paramount Hire",
    "wof:placetype":"venue"
},
  "geometry": {"coordinates":[146.752869,-19.261929],"type":"Point"}
}