{
  "type": "Feature",
  "properties": {
    "iso:country":"AU",
    "sg:address":"252 Eglinton Rd",
    "sg:city":"Bathurst",
    "sg:classifiers":[
        {
            "category":"Government",
            "subcategory":"Customs House",
            "type":"Public Place"
        }
    ],
    "sg:phone":"+61 2 6332 1104",
    "sg:postcode":"2795",
    "sg:province":"NSW",
    "sg:tags":[
        "title",
        "management",
        "stratum"
    ],
    "wof:name":"Sharyn Hanrahan Strata Services",
    "wof:placetype":"venue"
},
  "geometry": {"coordinates":[149.54586792000001,-33.3841018677],"type":"Point"}
}