{
  "type": "Feature",
  "properties": {
    "addr:full":"Lvl 17/ 330 Collins St Melbourne VIC 3000",
    "addr:housenumber":"/ 330",
    "addr:postcode":"3000",
    "addr:street":"Collins St",
    "iso:country":"AU",
    "sg:address":"Lvl 17/ 330 Collins St",
    "sg:city":"Melbourne",
    "sg:classifiers":[
        {
            "category":"Banks & Credit Unions",
            "subcategory":"Investment Brokerage",
            "type":"Services"
        }
    ],
    "sg:phone":"+61 3 9618 7575",
    "sg:postcode":"3000",
    "sg:province":"VIC",
    "sg:tags":[
        "share",
        "broker",
        "stock"
    ],
    "wof:name":"Opes Prime Stockbroking Ltd",
    "wof:placetype":"venue"
},
  "geometry": {"coordinates":[144.963287353,-37.8163032532],"type":"Point"}
}