{
  "type": "Feature",
  "properties": {
    "iso:country":"AU",
    "sg:address":"PO Box 2564",
    "sg:city":"Boulder",
    "sg:classifiers":[
        {
            "category":"Utilities",
            "subcategory":"Refuse",
            "type":"Services"
        }
    ],
    "sg:phone":"+61 427 213 100",
    "sg:postcode":"6432",
    "sg:province":"WA",
    "sg:tags":[
        "remover",
        "rubbish"
    ],
    "wof:name":"Kal Bins",
    "wof:placetype":"venue"
},
  "geometry": {"coordinates":[121.489463806,-30.7818393707],"type":"Point"}
}