{
  "type": "Feature",
  "properties": {
    "addr:full":"Unit 7 161 James St Toowoomba QLD 4350",
    "addr:housenumber":"161",
    "addr:postcode":"4350",
    "addr:street":"James St",
    "iso:country":"AU",
    "sg:address":"Unit 7 161 James St",
    "sg:city":"Toowoomba",
    "sg:classifiers":[
        {
            "category":"Autos & Motor Vehicles",
            "subcategory":"Auto Supplies",
            "type":"Retail Goods"
        }
    ],
    "sg:phone":"+61 7 4638 2922",
    "sg:postcode":"4350",
    "sg:province":"QLD",
    "sg:tags":[
        "accessory"
    ],
    "wof:name":"Autozone Performance",
    "wof:placetype":"venue"
},
  "geometry": {"coordinates":[151.95579499999999,-27.569012],"type":"Point"}
}