{
  "type": "Feature",
  "properties": {
    "addr:full":"272 Hay St Kalgoorlie WA 6430",
    "addr:housenumber":"272",
    "addr:postcode":"6430",
    "addr:street":"Hay St",
    "iso:country":"AU",
    "sg:address":"272 Hay St",
    "sg:city":"Kalgoorlie",
    "sg:classifiers":[
        {
            "category":"Professional",
            "subcategory":"Employment Agencies",
            "type":"Services"
        }
    ],
    "sg:phone":"+61 8 9021 6961",
    "sg:postcode":"6430",
    "sg:province":"WA",
    "sg:tags":[
        "provider",
        "internet"
    ],
    "wof:name":"Main Link",
    "wof:placetype":"venue"
},
  "geometry": {"coordinates":[121.46505737299999,-30.7521495819],"type":"Point"}
}