{
  "type": "Feature",
  "properties": {
    "iso:country":"AU",
    "sg:address":"190-202 Cumberland Rd",
    "sg:city":"Pascoe Vale",
    "sg:classifiers":[
        {
            "category":"Travel",
            "subcategory":"Hostel",
            "type":"Entertainment"
        }
    ],
    "sg:phone":"+61 3 9306 8584",
    "sg:postcode":"3044",
    "sg:province":"VIC",
    "sg:tags":[
        "home"
    ],
    "wof:name":"Dorothy Impey Home",
    "wof:placetype":"venue"
},
  "geometry": {"coordinates":[144.93986511200001,-37.7243614197],"type":"Point"}
}