{
  "type": "Feature",
  "properties": {
    "addr:full":"18 Farrow St Daisy Hill QLD 4127",
    "addr:housenumber":"18",
    "addr:postcode":"4127",
    "addr:street":"Farrow St",
    "iso:country":"AU",
    "sg:address":"18 Farrow St",
    "sg:city":"Daisy Hill",
    "sg:classifiers":[
        {
            "category":"Arts & Performance",
            "subcategory":"Music",
            "type":"Entertainment"
        }
    ],
    "sg:phone":"+61 7 3808 6160",
    "sg:postcode":"4127",
    "sg:province":"QLD",
    "sg:tags":[
        "mobile",
        "jockey",
        "disc"
    ],
    "wof:name":"Richard Reardon DJ Services",
    "wof:placetype":"venue"
},
  "geometry": {"coordinates":[153.14550781200001,-27.6393051147],"type":"Point"}
}