{
  "type": "Feature",
  "properties": {
    "addr:full":"Sandilong Ave Irymple VIC 3498",
    "addr:postcode":"3498",
    "addr:street":"Sandilong Ave",
    "iso:country":"AU",
    "sg:address":"Sandilong Ave",
    "sg:city":"Irymple",
    "sg:classifiers":[
        {
            "category":"Professional",
            "subcategory":"Engineering",
            "type":"Services"
        }
    ],
    "sg:phone":"+61 3 5024 6464",
    "sg:postcode":"3498",
    "sg:province":"VIC",
    "sg:tags":[
        "building",
        "prefabricated",
        "transportable",
        "industrial",
        "commercial"
    ],
    "wof:name":"Giffos",
    "wof:placetype":"venue"
},
  "geometry": {"coordinates":[142.15965270999999,-34.2284431458],"type":"Point"}
}