{
  "type": "Feature",
  "properties": {
    "addr:full":"Unit 12a, 3 Kenneth Rd Manly Vale NSW 2093",
    "addr:housenumber":"unit 12a 3",
    "addr:postcode":"2093",
    "addr:street":"Kenneth Rd",
    "iso:country":"AU",
    "sg:address":"Unit 12a, 3 Kenneth Rd",
    "sg:city":"Manly Vale",
    "sg:classifiers":[
        {
            "category":"Banks & Credit Unions",
            "subcategory":"Atm",
            "type":"Services"
        }
    ],
    "sg:phone":"+61 2 9907 9411",
    "sg:postcode":"2093",
    "sg:province":"NSW",
    "sg:tags":[
        "detector",
        "gas"
    ],
    "wof:name":"A.I. Industrial Pty Ltd",
    "wof:placetype":"venue"
},
  "geometry": {"coordinates":[151.26614379899999,-33.7865638733],"type":"Point"}
}