{
  "type": "Feature",
  "properties": {
    "iso:country":"AU",
    "sg:address":"3 Gleeson Ave",
    "sg:city":"Condell Park",
    "sg:classifiers":[
        {
            "category":"Building & Trades",
            "subcategory":"Construction",
            "type":"Services"
        }
    ],
    "sg:phone":"+61 418 240 582",
    "sg:postcode":"2200",
    "sg:province":"NSW",
    "sg:tags":[
        "rendering",
        "cement"
    ],
    "wof:name":"Apollo Construction & Cement Rendering Pty Ltd",
    "wof:placetype":"venue"
},
  "geometry": {"coordinates":[151.01945499999999,-33.926144],"type":"Point"}
}