{
  "type": "Feature",
  "properties": {
    "addr:full":"8 Robin Ave Sorrento WA 6020",
    "addr:housenumber":"8",
    "addr:postcode":"6020",
    "addr:street":"Robin Ave",
    "iso:country":"AU",
    "sg:address":"8 Robin Ave",
    "sg:city":"Sorrento",
    "sg:classifiers":[
        {
            "category":"Professional",
            "subcategory":"Art Services",
            "type":"Services"
        }
    ],
    "sg:phone":"+61 8 9447 8488",
    "sg:postcode":"6020",
    "sg:province":"WA",
    "sg:tags":[
        "graphic",
        "designer"
    ],
    "wof:name":"Design Station",
    "wof:placetype":"venue"
},
  "geometry": {"coordinates":[115.74925231900001,-31.833656311],"type":"Point"}
}