{
  "type": "Feature",
  "properties": {
    "iso:country":"AU",
    "sg:address":"Unit 2, 12-18 Victoria St",
    "sg:city":"East Lidcombe",
    "sg:classifiers":[
        {
            "category":"Shopping",
            "subcategory":"Stationery & Office Supplies",
            "type":"Retail Goods"
        }
    ],
    "sg:phone":"+61 2 9643 2201",
    "sg:postcode":"2141",
    "sg:province":"NSW",
    "sg:tags":[
        "equipment",
        "badge",
        "making"
    ],
    "wof:name":"DJs Badges",
    "wof:placetype":"venue"
},
  "geometry": {"coordinates":[151.04551696799999,-33.8689689636],"type":"Point"}
}