{
  "type": "Feature",
  "properties": {
    "addr:full":"PO Box 3112 Glendale NSW 2285",
    "addr:postcode":"2285",
    "iso:country":"AU",
    "sg:address":"PO Box 3112",
    "sg:city":"Glendale",
    "sg:classifiers":[
        {
            "category":"Train Station",
            "subcategory":"Light Rail",
            "type":"Transportation"
        }
    ],
    "sg:phone":"+61 406 150 166",
    "sg:postcode":"2285",
    "sg:province":"NSW",
    "sg:tags":[
        "equipment",
        "energy",
        "solar"
    ],
    "wof:name":"Buffalo Solar",
    "wof:placetype":"venue"
},
  "geometry": {"coordinates":[151.649734497,-32.9301300049],"type":"Point"}
}