{
  "type": "Feature",
  "properties": {
    "iso:country":"AU",
    "sg:address":"241 Bridge St",
    "sg:city":"Toowoomba",
    "sg:classifiers":[
        {
            "category":"Building & Trades",
            "subcategory":"Construction",
            "type":"Services"
        }
    ],
    "sg:phone":"+61 7 4632 3978",
    "sg:postcode":"4350",
    "sg:province":"QLD",
    "sg:tags":[
        "renovation",
        "alterations",
        "extension",
        "contractor"
    ],
    "wof:name":"G. Hediger",
    "wof:placetype":"venue"
},
  "geometry": {"coordinates":[151.899963,-27.533468],"type":"Point"}
}