{
  "type": "Feature",
  "properties": {
    "addr:full":"Level 4, 44 Caroline South Yarra VIC 3141",
    "addr:housenumber":"44",
    "addr:postcode":"3141",
    "addr:street":"Caroline",
    "iso:country":"AU",
    "sg:address":"Level 4, 44 Caroline",
    "sg:city":"South Yarra",
    "sg:classifiers":[
        {
            "category":"Real Estate",
            "subcategory":"Developer",
            "type":"Services"
        }
    ],
    "sg:phone":"+61 3 9867 3688",
    "sg:postcode":"3141",
    "sg:province":"VIC",
    "sg:tags":[
        "development"
    ],
    "wof:name":"Headland Properties Pty Ltd",
    "wof:placetype":"venue"
},
  "geometry": {"coordinates":[144.98822021500001,-37.8383712769],"type":"Point"}
}