{
  "type": "Feature",
  "properties": {
    "addr:full":"16 Dandenong St Dandenong VIC 3175",
    "addr:housenumber":"16",
    "addr:postcode":"3175",
    "addr:street":"Dandenong St",
    "iso:country":"AU",
    "sg:address":"16 Dandenong St",
    "sg:city":"Dandenong",
    "sg:classifiers":[
        {
            "category":"Retail",
            "subcategory":"Auto Repair",
            "type":"Services"
        }
    ],
    "sg:phone":"+61 3 9794 7850",
    "sg:postcode":"3175",
    "sg:province":"VIC",
    "sg:tags":[
        "repairer",
        "motor",
        "engineer"
    ],
    "wof:name":"Dandenong Service Centre",
    "wof:placetype":"venue"
},
  "geometry": {"coordinates":[145.19976806599999,-37.9920768738],"type":"Point"}
}