{
  "type": "Feature",
  "properties": {
    "addr:full":"9b North Rd Leinster WA 6437",
    "addr:housenumber":"9b",
    "addr:postcode":"6437",
    "addr:street":"North Rd",
    "iso:country":"AU",
    "sg:address":"9b North Rd",
    "sg:city":"Leinster",
    "sg:classifiers":[
        {
            "category":"Professional",
            "subcategory":"Employment Agencies",
            "type":"Services"
        }
    ],
    "sg:phone":"+61 8 9037 3373",
    "sg:postcode":"6437",
    "sg:province":"WA",
    "sg:tags":[
        "hire",
        "labour",
        "contractor"
    ],
    "wof:name":"Eagletime Pty Ltd",
    "wof:placetype":"venue"
},
  "geometry": {"coordinates":[120.69526672400001,-27.9378890991],"type":"Point"}
}