{
  "type": "Feature",
  "properties": {
    "addr:full":"306 Elizabeth St Sydney NSW 2000",
    "addr:housenumber":"306",
    "addr:postcode":"2000",
    "addr:street":"Elizabeth St",
    "iso:country":"AU",
    "sg:address":"306 Elizabeth St",
    "sg:city":"Sydney",
    "sg:classifiers":[
        {
            "category":"Communications",
            "type":"Services"
        }
    ],
    "sg:phone":"+61 2 9211 2177",
    "sg:postcode":"2000",
    "sg:province":"NSW",
    "sg:tags":[
        "data"
    ],
    "wof:name":"Cosmos E-C Commerce Ltd",
    "wof:placetype":"venue"
},
  "geometry": {"coordinates":[151.20846557600001,-33.8834342957],"type":"Point"}
}