{
  "type": "Feature",
  "properties": {
    "iso:country":"AU",
    "sg:address":"30 Cowper St",
    "sg:city":"Parramatta",
    "sg:classifiers":[
        {
            "category":"Professional",
            "subcategory":"Detective & Security Services",
            "type":"Services"
        }
    ],
    "sg:phone":"+61 2 8835 4938",
    "sg:postcode":"2150",
    "sg:province":"NSW",
    "sg:tags":[
        "guard",
        "patrol"
    ],
    "wof:name":"City Protection Security",
    "wof:placetype":"venue"
},
  "geometry": {"coordinates":[151.01344299300001,-33.8321304321],"type":"Point"}
}