{
  "type": "Feature",
  "properties": {
    "iso:country":"AU",
    "sg:address":"16 Takanna Ave",
    "sg:city":"Clifton Springs",
    "sg:classifiers":[
        {
            "category":"Building & Trades",
            "subcategory":"Construction",
            "type":"Services"
        }
    ],
    "sg:phone":"+61 411 354 573",
    "sg:postcode":"3222",
    "sg:province":"VIC",
    "sg:tags":[
        "plasterboard",
        "plasterer",
        "fixer"
    ],
    "wof:name":"Troy Grundy Plastering",
    "wof:placetype":"venue"
},
  "geometry": {"coordinates":[144.578094,-38.152691],"type":"Point"}
}