{
  "type": "Feature",
  "properties": {
    "addr:full":"217 Allan St Kyabram VIC 3620",
    "addr:housenumber":"217",
    "addr:postcode":"3620",
    "addr:street":"Allan St",
    "iso:country":"AU",
    "sg:address":"217 Allan St",
    "sg:city":"Kyabram",
    "sg:classifiers":[
        {
            "category":"Restaurant",
            "type":"Food & Drink"
        }
    ],
    "sg:phone":"+61 3 5852 1005",
    "sg:postcode":"3620",
    "sg:province":"VIC",
    "wof:name":"Commercial Hotel Motel",
    "wof:placetype":"venue"
},
  "geometry": {"coordinates":[145.048217773,-36.3133125305],"type":"Point"}
}