{
  "type": "Feature",
  "properties": {
    "addr:full":"16 Illawara Rd Balwyn North VIC 3104",
    "addr:housenumber":"16",
    "addr:postcode":"3104",
    "addr:street":"Illawara Rd",
    "iso:country":"AU",
    "sg:address":"16 Illawara Rd",
    "sg:city":"Balwyn North",
    "sg:classifiers":[
        {
            "category":"Utilities",
            "subcategory":"Electric",
            "type":"Services"
        }
    ],
    "sg:phone":"+61 3 9859 3811",
    "sg:postcode":"3104",
    "sg:province":"VIC",
    "sg:tags":[
        "electrical",
        "contractor"
    ],
    "wof:name":"Tepper J & Co Pty Ltd",
    "wof:placetype":"venue"
},
  "geometry": {"coordinates":[145.081344605,-37.7983932495],"type":"Point"}
}