{
  "type": "Feature",
  "properties": {
    "addr:full":"351 Maroondah Hwy Lilydale VIC 3140",
    "addr:housenumber":"351",
    "addr:postcode":"3140",
    "addr:street":"Maroondah Hwy",
    "iso:country":"AU",
    "sg:address":"351 Maroondah Hwy",
    "sg:city":"Lilydale",
    "sg:classifiers":[
        {
            "category":"Health Services",
            "subcategory":"Dentist",
            "type":"Services"
        }
    ],
    "sg:phone":"+61 3 9735 7755",
    "sg:postcode":"3140",
    "sg:province":"VIC",
    "wof:name":"Lilydale Dentistry Centre",
    "wof:placetype":"venue"
},
  "geometry": {"coordinates":[145.29197692899999,-37.7766838074],"type":"Point"}
}