{
  "type": "Feature",
  "properties": {
    "addr:full":"7-11 Hume St Tamworth NSW 2340",
    "addr:housenumber":"7-11",
    "addr:postcode":"2340",
    "addr:street":"Hume St",
    "iso:country":"AU",
    "sg:address":"7-11 Hume St",
    "sg:city":"Tamworth",
    "sg:classifiers":[
        {
            "category":"Building & Trades",
            "subcategory":"Construction",
            "type":"Services"
        }
    ],
    "sg:phone":"+61 2 6765 4066",
    "sg:postcode":"2340",
    "sg:province":"NSW",
    "sg:tags":[
        "window",
        "aluminium"
    ],
    "wof:name":"Trend Windows & Doors",
    "wof:placetype":"venue"
},
  "geometry": {"coordinates":[150.91371154800001,-31.0993671417],"type":"Point"}
}