{
  "type": "Feature",
  "properties": {
    "addr:full":"50 Hoddle St Abbotsford VIC 3067",
    "addr:housenumber":"50",
    "addr:postcode":"3067",
    "addr:street":"Hoddle St",
    "iso:country":"AU",
    "sg:address":"50 Hoddle St",
    "sg:city":"Abbotsford",
    "sg:classifiers":[
        {
            "category":"Professional",
            "subcategory":"Engineering",
            "type":"Services"
        }
    ],
    "sg:phone":"+61 3 9418 4000",
    "sg:postcode":"3067",
    "sg:province":"VIC",
    "sg:tags":[
        "engineer"
    ],
    "wof:name":"Bonacci Group Pty Ltd",
    "wof:placetype":"venue"
},
  "geometry": {"coordinates":[144.99205017099999,-37.8070487976],"type":"Point"}
}