{
  "type": "Feature",
  "properties": {
    "iso:country":"AU",
    "sg:address":"340 Oxley Drv",
    "sg:city":"Runaway Bay",
    "sg:classifiers":[
        {
            "category":"Health Services",
            "subcategory":"Dentist",
            "type":"Services"
        }
    ],
    "sg:phone":"+61 7 5563 7177",
    "sg:postcode":"4216",
    "sg:province":"QLD",
    "wof:name":"Strachan George W",
    "wof:placetype":"venue"
},
  "geometry": {"coordinates":[153.38763427699999,-27.9213447571],"type":"Point"}
}