{
  "type": "Feature",
  "properties": {
    "addr:full":"2 Hi-Tech Pl Rowville VIC 3178",
    "addr:housenumber":"2",
    "addr:postcode":"3178",
    "addr:street":"Hi-Tech Pl",
    "iso:country":"AU",
    "sg:address":"2 Hi-Tech Pl",
    "sg:city":"Rowville",
    "sg:classifiers":[
        {
            "category":"Industrial Area",
            "type":"Public Place"
        }
    ],
    "sg:phone":"+61 1800 460 700",
    "sg:postcode":"3178",
    "sg:province":"VIC",
    "sg:tags":[
        "rural",
        "shed"
    ],
    "wof:name":"A-Line Building Systems",
    "wof:placetype":"venue"
},
  "geometry": {"coordinates":[145.244628906,-37.9106025696],"type":"Point"}
}