{
  "type": "Feature",
  "properties": {
    "addr:full":"7/ 424 Gympie Rd Strathpine QLD 4500",
    "addr:housenumber":"/ 424",
    "addr:postcode":"4500",
    "addr:street":"Gympie Rd",
    "iso:country":"AU",
    "sg:address":"7/ 424 Gympie Rd",
    "sg:city":"Strathpine",
    "sg:classifiers":[
        {
            "category":"Banks & Credit Unions",
            "subcategory":"Bank",
            "type":"Services"
        }
    ],
    "sg:phone":"+61 7 3889 9544",
    "sg:postcode":"4500",
    "sg:province":"QLD",
    "sg:tags":[
        "broker",
        "mortgage"
    ],
    "wof:name":"Wizard",
    "wof:placetype":"venue"
},
  "geometry": {"coordinates":[152.98843383799999,-27.3024711609],"type":"Point"}
}