{
  "type": "Feature",
  "properties": {
    "addr:full":"13 Lyons St Dover Heights NSW 2030",
    "addr:housenumber":"13",
    "addr:postcode":"2030",
    "addr:street":"Lyons St Dover",
    "iso:country":"AU",
    "sg:address":"13 Lyons St",
    "sg:city":"Dover Heights",
    "sg:classifiers":[
        {
            "category":"Building & Trades",
            "subcategory":"Cleaning & Sanitation",
            "type":"Services"
        }
    ],
    "sg:phone":"+61 418 273 777",
    "sg:postcode":"2030",
    "sg:province":"NSW",
    "sg:tags":[
        "chemical",
        "pressure",
        "steam",
        "contractor"
    ],
    "wof:name":"Concorde Jet Waterblasting",
    "wof:placetype":"venue"
},
  "geometry": {"coordinates":[151.28262329099999,-33.8755493164],"type":"Point"}
}