{
  "type": "Feature",
  "properties": {
    "addr:full":"7 Isabella St Balmain NSW 2041",
    "addr:housenumber":"7",
    "addr:postcode":"2041",
    "addr:street":"Isabella St",
    "iso:country":"AU",
    "sg:address":"7 Isabella St",
    "sg:city":"Balmain",
    "sg:classifiers":[
        {
            "category":"Education",
            "subcategory":"Special Training",
            "type":"Public Place"
        }
    ],
    "sg:phone":"+61 2 9810 9044",
    "sg:postcode":"2041",
    "sg:province":"NSW",
    "sg:tags":[
        "development"
    ],
    "wof:name":"Image & Attitude Pty Limited",
    "wof:placetype":"venue"
},
  "geometry": {"coordinates":[151.17433199999999,-33.857513],"type":"Point"}
}