{
  "type": "Feature",
  "properties": {
    "addr:full":"41- 53 Miller St Epping VIC 3076",
    "addr:housenumber":"53",
    "addr:postcode":"3076",
    "addr:street":"Miller St",
    "iso:country":"AU",
    "sg:address":"41- 53 Miller St",
    "sg:city":"Epping",
    "sg:classifiers":[
        {
            "category":"Sports & Exercise",
            "subcategory":"Sports Center",
            "type":"Entertainment"
        }
    ],
    "sg:phone":"+61 3 9401 2222",
    "sg:postcode":"3076",
    "sg:province":"VIC",
    "sg:tags":[
        "coach",
        "tennis"
    ],
    "wof:name":"Leisure City Epping",
    "wof:placetype":"venue"
},
  "geometry": {"coordinates":[144.99229431099999,-37.7515411377],"type":"Point"}
}