{
  "type": "Feature",
  "properties": {
    "addr:full":"Lot 2 Martin Drv Tomago NSW 2322",
    "addr:housenumber":"2",
    "addr:postcode":"2322",
    "addr:street":"Martin Drv",
    "iso:country":"AU",
    "sg:address":"Lot 2 Martin Drv",
    "sg:city":"Tomago",
    "sg:classifiers":[
        {
            "category":"Professional",
            "subcategory":"Engineering",
            "type":"Services"
        }
    ],
    "sg:phone":"+61 2 4913 7000",
    "sg:postcode":"2322",
    "sg:province":"NSW",
    "sg:tags":[
        "electrical",
        "engineer"
    ],
    "wof:name":"J.A. Martin Electrical Pty Ltd",
    "wof:placetype":"venue"
},
  "geometry": {"coordinates":[151.70489501899999,-32.820980072],"type":"Point"}
}