{
  "type": "Feature",
  "properties": {
    "iso:country":"AU",
    "sg:address":"29 Alice St",
    "sg:city":"Moree",
    "sg:classifiers":[
        {
            "category":"Retail",
            "subcategory":"Auto Rental",
            "type":"Services"
        }
    ],
    "sg:phone":"+61 2 6752 4977",
    "sg:postcode":"2400",
    "sg:province":"NSW",
    "sg:tags":[
        "bus",
        "truck"
    ],
    "wof:name":"Avis",
    "wof:placetype":"venue"
},
  "geometry": {"coordinates":[149.84622192399999,-29.4711055756],"type":"Point"}
}