{
  "type": "Feature",
  "properties": {
    "addr:full":"9 Greenwood Ave Belmont NSW 2280",
    "addr:housenumber":"9",
    "addr:postcode":"2280",
    "addr:street":"Greenwood Ave",
    "iso:country":"AU",
    "sg:address":"9 Greenwood Ave",
    "sg:city":"Belmont",
    "sg:classifiers":[
        {
            "category":"Real Estate",
            "subcategory":"Developer",
            "type":"Services"
        }
    ],
    "sg:phone":"+61 418 461 132",
    "sg:postcode":"2280",
    "sg:province":"NSW",
    "sg:tags":[
        "development"
    ],
    "wof:name":"Seastone Pty Ltd",
    "wof:placetype":"venue"
},
  "geometry": {"coordinates":[151.65304565400001,-33.0241737366],"type":"Point"}
}