{
  "type": "Feature",
  "properties": {
    "iso:country":"AU",
    "sg:address":"U2/ 157 Lurline St",
    "sg:city":"Katoomba",
    "sg:classifiers":[
        {
            "category":"Education",
            "subcategory":"Music School",
            "type":"Public Place"
        }
    ],
    "sg:phone":"+61 2 4782 5517",
    "sg:postcode":"2780",
    "sg:province":"NSW",
    "sg:tags":[
        "teacher"
    ],
    "wof:name":"Robertson Mary",
    "wof:placetype":"venue"
},
  "geometry": {"coordinates":[150.31095886200001,-33.7242431641],"type":"Point"}
}