{
  "type": "Feature",
  "properties": {
    "addr:full":"Sixteenth St Irymple VIC 3498",
    "addr:postcode":"3498",
    "addr:street":"Sixteenth St",
    "iso:country":"AU",
    "sg:address":"Sixteenth St",
    "sg:city":"Irymple",
    "sg:classifiers":[
        {
            "category":"Professional",
            "subcategory":"Business Services",
            "type":"Services"
        }
    ],
    "sg:phone":"+61 3 5024 6544",
    "sg:postcode":"3498",
    "sg:province":"VIC",
    "sg:tags":[
        "broker"
    ],
    "wof:name":"Murray Consulting Group",
    "wof:placetype":"venue"
},
  "geometry": {"coordinates":[142.16200256400001,-34.245388031],"type":"Point"}
}