{
  "type": "Feature",
  "properties": {
    "addr:full":"13 Kratzke Rd Highfields QLD 4352",
    "addr:housenumber":"13",
    "addr:postcode":"4352",
    "addr:street":"Kratzke Rd",
    "iso:country":"AU",
    "sg:address":"13 Kratzke Rd",
    "sg:city":"Highfields",
    "sg:classifiers":[
        {
            "category":"Building & Trades",
            "subcategory":"Construction",
            "type":"Services"
        }
    ],
    "sg:phone":"+61 7 4630 8780",
    "sg:postcode":"4352",
    "sg:province":"QLD",
    "sg:tags":[
        "renovation",
        "alterations",
        "extension",
        "contractor"
    ],
    "wof:name":"Siebuhr E J & D M",
    "wof:placetype":"venue"
},
  "geometry": {"coordinates":[151.94189499999999,-27.454899],"type":"Point"}
}