{
  "type": "Feature",
  "properties": {
    "iso:country":"AU",
    "sg:address":"34 Greenway Drv",
    "sg:city":"Pymble",
    "sg:classifiers":[
        {
            "category":"Health Services",
            "subcategory":"Dentist",
            "type":"Services"
        }
    ],
    "sg:phone":"+61 2 9440 8477",
    "sg:postcode":"2073",
    "sg:province":"NSW",
    "wof:name":"Bennett J",
    "wof:placetype":"venue"
},
  "geometry": {"coordinates":[151.132125855,-33.7514610291],"type":"Point"}
}