{
  "type": "Feature",
  "properties": {
    "addr:full":"533 Keilor Rd Niddrie VIC 3042",
    "addr:housenumber":"533",
    "addr:postcode":"3042",
    "addr:street":"Keilor Rd",
    "iso:country":"AU",
    "sg:address":"533 Keilor Rd",
    "sg:city":"Niddrie",
    "sg:classifiers":[
        {
            "category":"Home & Garden",
            "subcategory":"Carpets & Floor Coverings",
            "type":"Retail Goods"
        }
    ],
    "sg:phone":"+61 3 9379 9016",
    "sg:postcode":"3042",
    "sg:province":"VIC",
    "sg:tags":[
        "tile",
        "wall"
    ],
    "wof:name":"Estilco Ceramics",
    "wof:placetype":"venue"
},
  "geometry": {"coordinates":[144.88490295400001,-37.7345581055],"type":"Point"}
}