{
  "type": "Feature",
  "properties": {
    "iso:country":"AU",
    "sg:address":"PO Box 467 Haberfield",
    "sg:city":"Wareemba",
    "sg:classifiers":[
        {
            "category":"Building & Trades",
            "subcategory":"Construction",
            "type":"Services"
        }
    ],
    "sg:phone":"+61 2 9564 0779",
    "sg:postcode":"2046",
    "sg:province":"NSW",
    "sg:tags":[
        "contractor"
    ],
    "wof:name":"Jo Alexander Carpenter & Building Service",
    "wof:placetype":"venue"
},
  "geometry": {"coordinates":[151.131012,-33.858139],"type":"Point"}
}