{
  "type": "Feature",
  "properties": {
    "addr:full":"307 Preston Point Rd Attadale WA 6156",
    "addr:housenumber":"307",
    "addr:postcode":"6156",
    "addr:street":"Preston Point Rd",
    "iso:country":"AU",
    "sg:address":"307 Preston Point Rd",
    "sg:city":"Attadale",
    "sg:classifiers":[
        {
            "category":"Shopping",
            "subcategory":"Bicycles & Sporting Goods",
            "type":"Retail Goods"
        }
    ],
    "sg:phone":"+61 8 9330 9386",
    "sg:postcode":"6156",
    "sg:province":"WA",
    "sg:tags":[
        "chemical",
        "equipment",
        "pool",
        "swimming"
    ],
    "wof:name":"WA Vinyl Systems",
    "wof:placetype":"venue"
},
  "geometry": {"coordinates":[115.79422,-32.029202],"type":"Point"}
}