{
  "type": "Feature",
  "properties": {
    "addr:full":"Mayers St Cairns QLD 4870",
    "addr:postcode":"4870",
    "addr:street":"Mayers St",
    "iso:country":"AU",
    "sg:address":"Mayers St",
    "sg:city":"Cairns",
    "sg:classifiers":[
        {
            "category":"Personal",
            "subcategory":"Massage",
            "type":"Services"
        }
    ],
    "sg:phone":"+61 429 647 777",
    "sg:postcode":"4870",
    "sg:province":"QLD",
    "sg:tags":[
        "therapy"
    ],
    "wof:name":"Thai Massage Centre-+Coyle Tom",
    "wof:placetype":"venue"
},
  "geometry": {"coordinates":[145.741912842,-16.9255123138],"type":"Point"}
}