{
  "type": "Feature",
  "properties": {
    "iso:country":"AU",
    "sg:address":"331 Saltwater Rd",
    "sg:city":"Wallabi Point",
    "sg:classifiers":[
        {
            "category":"Home & Garden",
            "subcategory":"Building Materials",
            "type":"Retail Goods"
        }
    ],
    "sg:phone":"+61 2 6553 7759",
    "sg:postcode":"2430",
    "sg:province":"NSW",
    "sg:tags":[
        "insect",
        "screen"
    ],
    "wof:name":"Postcode Maintenance",
    "wof:placetype":"venue"
},
  "geometry": {"coordinates":[152.569199,-31.995857],"type":"Point"}
}