{
  "type": "Feature",
  "properties": {
    "iso:country":"AU",
    "sg:address":"31 Blackall St",
    "sg:city":"Woombye",
    "sg:classifiers":[
        {
            "category":"Banks & Credit Unions",
            "subcategory":"Financial Services",
            "type":"Services"
        }
    ],
    "sg:phone":"+61 7 5442 3243",
    "sg:postcode":"4559",
    "sg:province":"QLD",
    "sg:tags":[
        "loan",
        "finance",
        "mortgage"
    ],
    "wof:name":"Loanrite (QLD) Pty Ltd",
    "wof:placetype":"venue"
},
  "geometry": {"coordinates":[152.96420288100001,-26.6606292725],"type":"Point"}
}