{
  "type": "Feature",
  "properties": {
    "addr:full":"11 Bevtre St Sebastopol VIC 3356",
    "addr:housenumber":"11",
    "addr:postcode":"3356",
    "addr:street":"Bevtre St",
    "iso:country":"AU",
    "sg:address":"11 Bevtre St",
    "sg:city":"Sebastopol",
    "sg:classifiers":[
        {
            "category":"Utilities",
            "subcategory":"Electric",
            "type":"Services"
        }
    ],
    "sg:phone":"+61 3 5336 2637",
    "sg:postcode":"3356",
    "sg:province":"VIC",
    "sg:tags":[
        "electrical",
        "contractor"
    ],
    "wof:name":"Ritchie Phil",
    "wof:placetype":"venue"
},
  "geometry": {"coordinates":[143.83253500000001,-37.584846],"type":"Point"}
}