{
  "type": "Feature",
  "properties": {
    "addr:full":"Shp1/ 512 Malvern Rd Prahran VIC 3181",
    "addr:housenumber":"512",
    "addr:postcode":"3181",
    "addr:street":"Malvern Rd",
    "iso:country":"AU",
    "sg:address":"Shp1/ 512 Malvern Rd",
    "sg:city":"Prahran",
    "sg:classifiers":[
        {
            "category":"Shopping",
            "subcategory":"Baby Store",
            "type":"Retail Goods"
        }
    ],
    "sg:phone":"+61 3 9533 2439",
    "sg:postcode":"3181",
    "sg:province":"VIC",
    "sg:tags":[
        "children's",
        "wear"
    ],
    "wof:name":"La Compagnie Des Petits",
    "wof:placetype":"venue"
},
  "geometry": {"coordinates":[145.00343322800001,-37.8482475281],"type":"Point"}
}