{
  "type": "Feature",
  "properties": {
    "iso:country":"AU",
    "sg:address":"Shop 3/ 37 Forest Rd",
    "sg:city":"Arncliffe",
    "sg:classifiers":[
        {
            "category":"Building & Trades",
            "subcategory":"Construction",
            "type":"Services"
        }
    ],
    "sg:phone":"+61 2 9597 1003",
    "sg:postcode":"2205",
    "sg:province":"NSW",
    "sg:tags":[
        "window",
        "timber"
    ],
    "wof:name":"M&C Aluminium",
    "wof:placetype":"venue"
},
  "geometry": {"coordinates":[151.14518699999999,-33.939075],"type":"Point"}
}