{
  "type": "Feature",
  "properties": {
    "addr:full":"74 Park Rd Bulli NSW 2516",
    "addr:housenumber":"74",
    "addr:postcode":"2516",
    "addr:street":"Park Rd",
    "iso:country":"AU",
    "sg:address":"74 Park Rd",
    "sg:city":"Bulli",
    "sg:classifiers":[
        {
            "category":"Health Services",
            "subcategory":"Doctor",
            "type":"Services"
        }
    ],
    "sg:phone":"+61 2 4284 4622",
    "sg:postcode":"2516",
    "sg:province":"NSW",
    "sg:tags":[
        "medical",
        "practitioner"
    ],
    "wof:name":"Bulli Medical Practice",
    "wof:placetype":"venue"
},
  "geometry": {"coordinates":[150.91416899999999,-34.333439],"type":"Point"}
}