{
  "type": "Feature",
  "properties": {
    "addr:full":"269 Lyons Rd Five Dock NSW 2046",
    "addr:housenumber":"269",
    "addr:postcode":"2046",
    "addr:street":"Lyons Rd",
    "iso:country":"AU",
    "sg:address":"269 Lyons Rd",
    "sg:city":"Five Dock",
    "sg:classifiers":[
        {
            "category":"Personal",
            "type":"Services"
        }
    ],
    "sg:phone":"+61 2 9712 1144",
    "sg:postcode":"2046",
    "sg:province":"NSW",
    "sg:tags":[
        "gift"
    ],
    "wof:name":"Christophe...ses chocolats",
    "wof:placetype":"venue"
},
  "geometry": {"coordinates":[151.14213599999999,-33.85989],"type":"Point"}
}