{
  "type": "Feature",
  "properties": {
    "addr:full":"46 Bushs La Gunnedah NSW 2380",
    "addr:housenumber":"46",
    "addr:postcode":"2380",
    "addr:street":"Bushs La",
    "iso:country":"AU",
    "sg:address":"46 Bushs La",
    "sg:city":"Gunnedah",
    "sg:classifiers":[
        {
            "category":"Building & Trades",
            "subcategory":"Cleaning & Sanitation",
            "type":"Services"
        }
    ],
    "sg:phone":"+61 2 6742 2554",
    "sg:postcode":"2380",
    "sg:province":"NSW",
    "sg:tags":[
        "tank",
        "septic"
    ],
    "wof:name":"M. Jaeger",
    "wof:placetype":"venue"
},
  "geometry": {"coordinates":[150.260421753,-30.987663269],"type":"Point"}
}