{
  "type": "Feature",
  "properties": {
    "addr:full":"42 Florence St Wynnum Central QLD 4178",
    "addr:housenumber":"42",
    "addr:postcode":"4178",
    "addr:street":"Florence St",
    "iso:country":"AU",
    "sg:address":"42 Florence St",
    "sg:city":"Wynnum Central",
    "sg:classifiers":[
        {
            "category":"Personal",
            "subcategory":"Shoe Repair & Shine",
            "type":"Services"
        }
    ],
    "sg:phone":"+61 7 3396 7934",
    "sg:postcode":"4178",
    "sg:province":"QLD",
    "sg:tags":[
        "footwear"
    ],
    "wof:name":"Shoe Hospital",
    "wof:placetype":"venue"
},
  "geometry": {"coordinates":[153.173828125,-27.4436264038],"type":"Point"}
}