{
  "type": "Feature",
  "properties": {
    "iso:country":"AU",
    "sg:address":"31 Bay Rd",
    "sg:city":"Sandringham",
    "sg:classifiers":[
        {
            "category":"Health Services",
            "subcategory":"Dentist",
            "type":"Services"
        }
    ],
    "sg:phone":"+61 3 9533 1444",
    "sg:postcode":"3191",
    "sg:province":"VIC",
    "wof:name":"Bay Road Dental Centre",
    "wof:placetype":"venue"
},
  "geometry": {"coordinates":[145.00552368199999,-37.9517440796],"type":"Point"}
}