{
  "type": "Feature",
  "properties": {
    "iso:country":"AU",
    "sg:address":"1 Manchester Rd",
    "sg:city":"Gymea",
    "sg:classifiers":[
        {
            "category":"Utilities",
            "subcategory":"Electric",
            "type":"Services"
        }
    ],
    "sg:phone":"+61 2 9524 9170",
    "sg:postcode":"2227",
    "sg:province":"NSW",
    "sg:tags":[
        "electrical",
        "contractor"
    ],
    "wof:name":"Bayside Electric Pty Ltd",
    "wof:placetype":"venue"
},
  "geometry": {"coordinates":[151.089935303,-34.0278549194],"type":"Point"}
}