{
  "type": "Feature",
  "properties": {
    "addr:full":"65 Bowen St Goondiwindi QLD 4390",
    "addr:housenumber":"65",
    "addr:postcode":"4390",
    "addr:street":"Bowen St",
    "iso:country":"AU",
    "sg:address":"65 Bowen St",
    "sg:city":"Goondiwindi",
    "sg:classifiers":[
        {
            "category":"Health Services",
            "subcategory":"Health Practitioner",
            "type":"Services"
        }
    ],
    "sg:phone":"+61 7 4671 2980",
    "sg:postcode":"4390",
    "sg:province":"QLD",
    "sg:tags":[
        "physiotherapist"
    ],
    "wof:name":"Hill Kirsten",
    "wof:placetype":"venue"
},
  "geometry": {"coordinates":[150.309158325,-28.5483818054],"type":"Point"}
}