{
  "type": "Feature",
  "properties": {
    "iso:country":"AU",
    "sg:address":"Centenary House 23 Hospital Rd",
    "sg:city":"Emerald",
    "sg:classifiers":[
        {
            "category":"Professional",
            "subcategory":"Employment Agencies",
            "type":"Services"
        }
    ],
    "sg:phone":"+61 7 4980 6666",
    "sg:postcode":"4720",
    "sg:province":"QLD",
    "sg:tags":[
        "hire",
        "labour",
        "contractor"
    ],
    "wof:name":"IPA Personnel Pty Ltd",
    "wof:placetype":"venue"
},
  "geometry": {"coordinates":[148.15715,-23.518444],"type":"Point"}
}