{
  "type": "Feature",
  "properties": {
    "iso:country":"AU",
    "sg:address":"Rowes Arcade 235 Edward St",
    "sg:city":"Brisbane",
    "sg:classifiers":[
        {
            "category":"Health Services",
            "subcategory":"Optometrist",
            "type":"Services"
        }
    ],
    "sg:phone":"+61 7 3221 8499",
    "sg:postcode":"4000",
    "sg:province":"QLD",
    "wof:name":"Optical Edge",
    "wof:placetype":"venue"
},
  "geometry": {"coordinates":[153.02687072800001,-27.4680538177],"type":"Point"}
}