{
  "type": "Feature",
  "properties": {
    "addr:full":"25 Hartnett Drv Seaford VIC 3198",
    "addr:housenumber":"25",
    "addr:postcode":"3198",
    "addr:street":"Hartnett Drv",
    "iso:country":"AU",
    "sg:address":"25 Hartnett Drv",
    "sg:city":"Seaford",
    "sg:classifiers":[
        {
            "category":"Fast Food",
            "type":"Food & Drink"
        }
    ],
    "sg:phone":"+61 3 9786 9190",
    "sg:postcode":"3198",
    "sg:province":"VIC",
    "sg:tags":[
        "away",
        "take"
    ],
    "wof:name":"Hartnett Takeaway",
    "wof:placetype":"venue"
},
  "geometry": {"coordinates":[145.141967773,-38.1129417419],"type":"Point"}
}