{
  "type": "Feature",
  "properties": {
    "addr:full":"210 Gugeri Rd Herne Hill WA 6056",
    "addr:housenumber":"210",
    "addr:postcode":"6056",
    "addr:street":"Gugeri Rd",
    "iso:country":"AU",
    "sg:address":"210 Gugeri Rd",
    "sg:city":"Herne Hill",
    "sg:classifiers":[
        {
            "category":"Professional",
            "type":"Services"
        }
    ],
    "sg:phone":"+61 8 9296 4022",
    "sg:postcode":"6056",
    "sg:province":"WA",
    "sg:tags":[
        "transport"
    ],
    "wof:name":"Campbell Wally Pty Ltd",
    "wof:placetype":"venue"
},
  "geometry": {"coordinates":[116.037757873,-31.8346099854],"type":"Point"}
}