{
  "type": "Feature",
  "properties": {
    "addr:full":"66 Macquarie Rd Fennell Bay NSW 2283",
    "addr:housenumber":"66",
    "addr:postcode":"2283",
    "addr:street":"Macquarie Rd",
    "iso:country":"AU",
    "sg:address":"66 Macquarie Rd",
    "sg:city":"Fennell Bay",
    "sg:classifiers":[
        {
            "category":"Taxi",
            "type":"Transportation"
        }
    ],
    "sg:phone":"+61 2 4950 4111",
    "sg:postcode":"2283",
    "sg:province":"NSW",
    "sg:tags":[
        "cab"
    ],
    "wof:name":"Toronto Hire Cars",
    "wof:placetype":"venue"
},
  "geometry": {"coordinates":[151.59254455600001,-32.9887886047],"type":"Point"}
}