{
  "type": "Feature",
  "properties": {
    "addr:full":"13- 17 Yamma St Sefton NSW 2162",
    "addr:housenumber":"17",
    "addr:postcode":"2162",
    "addr:street":"Yamma St",
    "iso:country":"AU",
    "sg:address":"13- 17 Yamma St",
    "sg:city":"Sefton",
    "sg:classifiers":[
        {
            "category":"Utilities",
            "subcategory":"Recycling",
            "type":"Services"
        }
    ],
    "sg:phone":"+61 2 9645 1444",
    "sg:postcode":"2162",
    "sg:province":"NSW",
    "wof:name":"Southern Cross Metals",
    "wof:placetype":"venue"
},
  "geometry": {"coordinates":[151.01353454599999,-33.883228302],"type":"Point"}
}