{
  "type": "Feature",
  "properties": {
    "iso:country":"AU",
    "sg:address":"3 Bisley St",
    "sg:city":"Warwick",
    "sg:classifiers":[
        {
            "category":"Building & Trades",
            "subcategory":"Plumbing",
            "type":"Services"
        }
    ],
    "sg:phone":"+61 7 4661 7983",
    "sg:postcode":"4370",
    "sg:province":"QLD",
    "sg:tags":[
        "plumber",
        "gasfitters"
    ],
    "wof:name":"Keogh Plumbing & Gasfitting Pty Ltd",
    "wof:placetype":"venue"
},
  "geometry": {"coordinates":[152.017852783,-28.2279396057],"type":"Point"}
}