{
  "type": "Feature",
  "properties": {
    "addr:full":"25 Lawson Ave Beresfield NSW 2322",
    "addr:housenumber":"25",
    "addr:postcode":"2322",
    "addr:street":"Lawson Ave",
    "iso:country":"AU",
    "sg:address":"25 Lawson Ave",
    "sg:city":"Beresfield",
    "sg:classifiers":[
        {
            "category":"Banks & Credit Unions",
            "subcategory":"Financial Services",
            "type":"Services"
        }
    ],
    "sg:phone":"+61 2 4921 9946",
    "sg:postcode":"2322",
    "sg:province":"NSW",
    "sg:tags":[
        "building",
        "society"
    ],
    "wof:name":"Greater Building Society Ltd",
    "wof:placetype":"venue"
},
  "geometry": {"coordinates":[151.65814209000001,-32.8007507324],"type":"Point"}
}