{
  "type": "Feature",
  "properties": {
    "iso:country":"AU",
    "sg:address":"41 Como Pde",
    "sg:city":"East Mentone",
    "sg:classifiers":[
        {
            "category":"Health Services",
            "subcategory":"Doctor",
            "type":"Services"
        }
    ],
    "sg:phone":"+61 3 9585 1911",
    "sg:postcode":"3194",
    "sg:province":"VIC",
    "sg:tags":[
        "medical",
        "practitioner"
    ],
    "wof:name":"Sitzler Paul J Mr",
    "wof:placetype":"venue"
},
  "geometry": {"coordinates":[145.0703125,-37.9873352051],"type":"Point"}
}