{
  "type": "Feature",
  "properties": {
    "addr:full":"9/ 27 Market St Fremantle WA 6160",
    "addr:housenumber":"/ 27",
    "addr:postcode":"6160",
    "addr:street":"Market St",
    "iso:country":"AU",
    "sg:address":"9/ 27 Market St",
    "sg:city":"Fremantle",
    "sg:classifiers":[
        {
            "category":"Health Services",
            "subcategory":"Health Practitioner",
            "type":"Services"
        }
    ],
    "sg:phone":"+61 417 958 658",
    "sg:postcode":"6160",
    "sg:province":"WA",
    "sg:tags":[
        "psychotherapist"
    ],
    "wof:name":"Brittain Garrett",
    "wof:placetype":"venue"
},
  "geometry": {"coordinates":[115.746101,-32.053993],"type":"Point"}
}