{
  "type": "Feature",
  "properties": {
    "addr:full":"Unit 2/ 41c Munibung Rd Cardiff NSW 2285",
    "addr:housenumber":"41c",
    "addr:postcode":"2285",
    "addr:street":"Munibung Rd",
    "iso:country":"AU",
    "sg:address":"Unit 2/ 41c Munibung Rd",
    "sg:city":"Cardiff",
    "sg:classifiers":[
        {
            "category":"Professional",
            "subcategory":"Printing & Photocopies",
            "type":"Services"
        }
    ],
    "sg:phone":"+61 2 4954 2142",
    "sg:postcode":"2285",
    "sg:province":"NSW",
    "sg:tags":[
        "screen",
        "printer"
    ],
    "wof:name":"Screen Signs",
    "wof:placetype":"venue"
},
  "geometry": {"coordinates":[151.650024414,-32.9429397583],"type":"Point"}
}