{
  "type": "Feature",
  "properties": {
    "iso:country":"AU",
    "sg:address":"613 Learmonth St",
    "sg:city":"Buninyong",
    "sg:classifiers":[
        {
            "category":"Sports & Exercise",
            "subcategory":"Golf",
            "type":"Entertainment"
        }
    ],
    "sg:phone":"+61 3 5341 3217",
    "sg:postcode":"3357",
    "sg:province":"VIC",
    "sg:tags":[
        "club"
    ],
    "wof:name":"Buninyong Golf Club",
    "wof:placetype":"venue"
},
  "geometry": {"coordinates":[143.87681599999999,-37.649036],"type":"Point"}
}