{
  "type": "Feature",
  "properties": {
    "addr:full":"145 Christmas St Fairfield VIC 3078",
    "addr:housenumber":"145",
    "addr:postcode":"3078",
    "addr:street":"Christmas St",
    "iso:country":"AU",
    "sg:address":"145 Christmas St",
    "sg:city":"Fairfield",
    "sg:classifiers":[
        {
            "category":"Wholesale",
            "subcategory":"Medical Equipment & Supplies",
            "type":"Manufacturing & Wholesale Goods"
        }
    ],
    "sg:phone":"+61 3 9481 6224",
    "sg:postcode":"3078",
    "sg:province":"VIC",
    "sg:tags":[
        "aid",
        "care",
        "health",
        "home"
    ],
    "wof:name":"Lenlok Hales",
    "wof:placetype":"venue"
},
  "geometry": {"coordinates":[145.02215576200001,-37.7675018311],"type":"Point"}
}