{
  "type": "Feature",
  "properties": {
    "addr:full":"Lot 6 Tallebudgera Creek Rd Tallebudgera QLD 4228",
    "addr:postcode":"4228",
    "addr:street":"Creek Rd",
    "iso:country":"AU",
    "sg:address":"Lot 6 Tallebudgera Creek Rd",
    "sg:city":"Tallebudgera",
    "sg:classifiers":[
        {
            "category":"Building & Trades",
            "subcategory":"Construction",
            "type":"Services"
        }
    ],
    "sg:phone":"+61 412 101 220",
    "sg:postcode":"4228",
    "sg:province":"QLD",
    "sg:tags":[
        "renovation",
        "alterations",
        "extension",
        "contractor"
    ],
    "wof:name":"Drayton J.R & K.A",
    "wof:placetype":"venue"
},
  "geometry": {"coordinates":[153.40162658700001,-28.1533145905],"type":"Point"}
}