{
  "type": "Feature",
  "properties": {
    "addr:full":"Shop 3020, Level 3, Indooroopilly Shopping Centre, Indooroopilly QLD 4068",
    "addr:housenumber":"3020 level 3",
    "addr:postcode":"shopping;4068",
    "iso:country":"AU",
    "sg:address":"Shop 3020, Level 3, Indooroopilly Shopping Centre,",
    "sg:city":"Indooroopilly",
    "sg:classifiers":[
        {
            "category":"Personal",
            "subcategory":"Hair Removal",
            "type":"Services"
        }
    ],
    "sg:phone":"+61 7 3720 0283",
    "sg:postcode":"4068",
    "sg:province":"QLD",
    "wof:name":"Ella Bache Indooroopilly",
    "wof:placetype":"venue"
},
  "geometry": {"coordinates":[152.974487305,-27.4973583221],"type":"Point"}
}