{
  "type": "Feature",
  "properties": {
    "addr:full":"182 Victoria Pde East Melbourne VIC 3002",
    "addr:housenumber":"182",
    "addr:postcode":"3002",
    "addr:street":"Victoria Pde",
    "iso:country":"AU",
    "sg:address":"182 Victoria Pde",
    "sg:city":"East Melbourne",
    "sg:classifiers":[
        {
            "category":"Health Services",
            "subcategory":"Doctor",
            "type":"Services"
        }
    ],
    "sg:phone":"+61 3 9639 4177",
    "sg:postcode":"3002",
    "sg:province":"VIC",
    "sg:tags":[
        "medical",
        "practitioner"
    ],
    "wof:name":"Jenner David A",
    "wof:placetype":"venue"
},
  "geometry": {"coordinates":[144.97819519000001,-37.808757782],"type":"Point"}
}