{
  "type": "Feature",
  "properties": {
    "addr:full":"3 Ela St Leeming WA 6149",
    "addr:housenumber":"3",
    "addr:postcode":"6149",
    "addr:street":"Ela St",
    "iso:country":"AU",
    "sg:address":"3 Ela St",
    "sg:city":"Leeming",
    "sg:classifiers":[
        {
            "category":"Building & Trades",
            "subcategory":"Cleaning & Sanitation",
            "type":"Services"
        }
    ],
    "sg:phone":"+61 414 373 783",
    "sg:postcode":"6149",
    "sg:province":"WA",
    "sg:tags":[
        "industrial",
        "commercial",
        "contractor"
    ],
    "wof:name":"Adedicom",
    "wof:placetype":"venue"
},
  "geometry": {"coordinates":[115.85891700000001,-32.070244],"type":"Point"}
}