{
  "type": "Feature",
  "properties": {
    "iso:country":"AU",
    "sg:address":"Shop 12a Traveltown , 21 Lake St",
    "sg:city":"Cairns",
    "sg:classifiers":[
        {
            "category":"Shopping",
            "subcategory":"Clothing, Apparel, & Fashions",
            "type":"Retail Goods"
        }
    ],
    "sg:phone":"+61 7 4031 8066",
    "sg:postcode":"4870",
    "sg:province":"QLD",
    "sg:tags":[
        "recycled",
        "clothing"
    ],
    "wof:name":"Cover Up",
    "wof:placetype":"venue"
},
  "geometry": {"coordinates":[145.77679443400001,-16.9234466553],"type":"Point"}
}