{
  "type": "Feature",
  "properties": {
    "iso:country":"AU",
    "sg:address":"6 McDonalds Crs",
    "sg:city":"Bassendean",
    "sg:classifiers":[
        {
            "category":"Manufacturing",
            "subcategory":"Building Materials",
            "type":"Manufacturing & Wholesale Goods"
        }
    ],
    "sg:phone":"+61 8 9377 3171",
    "sg:postcode":"6054",
    "sg:province":"WA",
    "sg:tags":[
        "stone",
        "product",
        "supply"
    ],
    "wof:name":"Exclusive Sandstone Products",
    "wof:placetype":"venue"
},
  "geometry": {"coordinates":[115.942138672,-31.9080696106],"type":"Point"}
}