{
  "type": "Feature",
  "properties": {
    "addr:full":"56 Brushy Park Rd Wonga Park VIC 3115",
    "addr:housenumber":"56",
    "addr:postcode":"3115",
    "addr:street":"Brushy Park Rd",
    "iso:country":"AU",
    "sg:address":"56 Brushy Park Rd",
    "sg:city":"Wonga Park",
    "sg:classifiers":[
        {
            "category":"Professional",
            "subcategory":"Business Services",
            "type":"Services"
        }
    ],
    "sg:phone":"+61 422 413 080",
    "sg:postcode":"3115",
    "sg:province":"VIC",
    "sg:tags":[
        "livestock",
        "transport"
    ],
    "wof:name":"Melbourne Horse Transport",
    "wof:placetype":"venue"
},
  "geometry": {"coordinates":[145.283813477,-37.7465705872],"type":"Point"}
}