{
  "type": "Feature",
  "properties": {
    "addr:full":"Shp 36, The Willows Shopngtown, Herveys Range Rd Townsville QLD 4810",
    "addr:housenumber":"36",
    "addr:postcode":"4810",
    "addr:street":"The Willows;Range Rd",
    "iso:country":"AU",
    "sg:address":"Shp 36, The Willows Shopngtown, Herveys Range Rd",
    "sg:city":"Townsville",
    "sg:classifiers":[
        {
            "category":"Shopping",
            "subcategory":"Shoes",
            "type":"Retail Goods"
        }
    ],
    "sg:phone":"+61 7 4723 0399",
    "sg:postcode":"4810",
    "sg:province":"QLD",
    "sg:tags":[
        "footwear"
    ],
    "wof:name":"Payless Shoes",
    "wof:placetype":"venue"
},
  "geometry": {"coordinates":[146.79965200000001,-19.282095],"type":"Point"}
}