{
  "type": "Feature",
  "properties": {
    "iso:country":"AU",
    "sg:address":"Shp 4/ 102 Hawthorn Rd",
    "sg:city":"Caulfield North",
    "sg:classifiers":[
        {
            "category":"Personal",
            "subcategory":"Beauty Salon",
            "type":"Services"
        }
    ],
    "sg:phone":"+61 3 9533 0778",
    "sg:postcode":"3161",
    "sg:province":"VIC",
    "sg:tags":[
        "hairdresser"
    ],
    "wof:name":"Mi Hairko",
    "wof:placetype":"venue"
},
  "geometry": {"coordinates":[145.02452087399999,-37.8728065491],"type":"Point"}
}