{
  "type": "Feature",
  "properties": {
    "iso:country":"AU",
    "sg:address":"11 Leichardt St",
    "sg:city":"Bunbury",
    "sg:classifiers":[
        {
            "category":"Manufacturing",
            "subcategory":"Motor Vehicles & Parts",
            "type":"Manufacturing & Wholesale Goods"
        }
    ],
    "sg:phone":"+61 8 9726 0744",
    "sg:postcode":"6230",
    "sg:province":"WA",
    "sg:tags":[
        "wholesaler",
        "cycle",
        "mfrs",
        "accessory"
    ],
    "wof:name":"MX Retreads Australia",
    "wof:placetype":"venue"
},
  "geometry": {"coordinates":[115.678139,-33.35479],"type":"Point"}
}