{
  "type": "Feature",
  "properties": {
    "iso:country":"AU",
    "sg:address":"Suite 11 Enterprise House 3 Stanley St",
    "sg:city":"Wodonga",
    "sg:classifiers":[
        {
            "category":"Personal",
            "type":"Services"
        }
    ],
    "sg:phone":"+61 2 6024 0443",
    "sg:postcode":"3690",
    "sg:province":"NSW",
    "sg:tags":[
        "reducing",
        "treatment",
        "weight"
    ],
    "wof:name":"Jan's Weight Achievers",
    "wof:placetype":"venue"
},
  "geometry": {"coordinates":[146.877349853,-36.1208457947],"type":"Point"}
}