{
  "type": "Feature",
  "properties": {
    "addr:full":"Azalea St Colo Vale NSW 2575",
    "addr:postcode":"2575",
    "addr:street":"Azalea St",
    "iso:country":"AU",
    "sg:address":"Azalea St",
    "sg:city":"Colo Vale",
    "sg:classifiers":[
        {
            "category":"Autos & Motor Vehicles",
            "subcategory":"Auto Supplies",
            "type":"Retail Goods"
        }
    ],
    "sg:phone":"+61 2 4889 5005",
    "sg:postcode":"2575",
    "sg:province":"NSW",
    "sg:tags":[
        "part",
        "cycles",
        "accessory"
    ],
    "wof:name":"Motorcycles Alternator & Stator Rewinds",
    "wof:placetype":"venue"
},
  "geometry": {"coordinates":[150.48716735799999,-34.4057235718],"type":"Point"}
}