{
  "type": "Feature",
  "properties": {
    "iso:country":"AU",
    "sg:address":"6 Curringa Rd",
    "sg:city":"Kariong",
    "sg:classifiers":[
        {
            "category":"Retail",
            "subcategory":"Auto Repair",
            "type":"Services"
        }
    ],
    "sg:phone":"+61 2 4340 0295",
    "sg:postcode":"2250",
    "sg:province":"NSW",
    "sg:tags":[
        "repairer",
        "motor",
        "engineer"
    ],
    "wof:name":"Kariong Automotive",
    "wof:placetype":"venue"
},
  "geometry": {"coordinates":[151.29623413100001,-33.4341964722],"type":"Point"}
}