{
  "type": "Feature",
  "properties": {
    "addr:full":"1345 The Horsley Dve Wetherill Park NSW 2164",
    "addr:housenumber":"1345",
    "addr:postcode":"2164",
    "addr:street":"The Horsley Dve",
    "iso:country":"AU",
    "sg:address":"1345 The Horsley Dve",
    "sg:city":"Wetherill Park",
    "sg:classifiers":[
        {
            "category":"Wholesale",
            "subcategory":"Furniture",
            "type":"Manufacturing & Wholesale Goods"
        }
    ],
    "sg:phone":"+61 2 9604 0641",
    "sg:postcode":"2164",
    "sg:province":"NSW",
    "sg:tags":[
        "wholesaler",
        "mfrs"
    ],
    "wof:name":"Ricmar Commercial Furniture & Upholstery",
    "wof:placetype":"venue"
},
  "geometry": {"coordinates":[150.883056641,-33.852432251],"type":"Point"}
}