{
  "type": "Feature",
  "properties": {
    "iso:country":"AU",
    "sg:address":"Cnr Bong Bong & Banyette Sts",
    "sg:city":"Bowral",
    "sg:classifiers":[
        {
            "category":"Professional",
            "subcategory":"Art Services",
            "type":"Services"
        }
    ],
    "sg:phone":"+61 2 4861 3214",
    "sg:postcode":"2576",
    "sg:province":"NSW",
    "sg:tags":[
        "picture",
        "frame",
        "framing"
    ],
    "wof:name":"Bowral Paper Place",
    "wof:placetype":"venue"
},
  "geometry": {"coordinates":[150.41839599599999,-34.4763565063],"type":"Point"}
}