{
  "type": "Feature",
  "properties": {
    "addr:full":"79 Burringbar St Mullumbimby NSW 2482",
    "addr:housenumber":"79",
    "addr:postcode":"2482",
    "addr:street":"Burringbar St",
    "iso:country":"AU",
    "sg:address":"79 Burringbar St",
    "sg:city":"Mullumbimby",
    "sg:classifiers":[
        {
            "category":"Real Estate",
            "subcategory":"Real Estate Agent",
            "type":"Services"
        }
    ],
    "sg:phone":"+61 2 6684 2200",
    "sg:postcode":"2482",
    "sg:province":"NSW",
    "wof:name":"Sean Kenny Real Estate",
    "wof:placetype":"venue"
},
  "geometry": {"coordinates":[153.50198364299999,-28.5535888672],"type":"Point"}
}