{
  "type": "Feature",
  "properties": {
    "iso:country":"AU",
    "sg:address":"12 Victoria Ave",
    "sg:city":"Ballarat",
    "sg:classifiers":[
        {
            "category":"Building & Trades",
            "subcategory":"Construction",
            "type":"Services"
        }
    ],
    "sg:phone":"+61 417 587 659",
    "sg:postcode":"3350",
    "sg:province":"VIC",
    "sg:tags":[
        "contractor"
    ],
    "wof:name":"DPR Building Pty. Ltd.",
    "wof:placetype":"venue"
},
  "geometry": {"coordinates":[143.847717,-37.555202],"type":"Point"}
}