{
  "type": "Feature",
  "properties": {
    "addr:full":"Shop 5 Noosa Professional Centre, Lanyana Way Noosa QLD 4567",
    "addr:housenumber":"shop 5",
    "addr:postcode":"4567",
    "addr:street":"Lanyana Way",
    "iso:country":"AU",
    "sg:address":"Shop 5",
    "sg:city":"Noosa Professional Centre, Lanyana Way Noosa",
    "sg:classifiers":[
        {
            "category":"Health Services",
            "subcategory":"Dentist",
            "type":"Services"
        }
    ],
    "sg:phone":"+61 7 5455 3577",
    "sg:postcode":"4567",
    "sg:province":"QLD",
    "wof:name":"Morton Peter, Richard Jon & Lynda Swaddling",
    "wof:placetype":"venue"
},
  "geometry": {"coordinates":[153.08978271500001,-26.3975486755],"type":"Point"}
}