{
  "type": "Feature",
  "properties": {
    "iso:country":"AU",
    "sg:address":"169 Hilma St",
    "sg:city":"Sunshine West",
    "sg:classifiers":[
        {
            "category":"Manufacturing",
            "subcategory":"Glass & Minerals",
            "type":"Manufacturing & Wholesale Goods"
        }
    ],
    "sg:phone":"+61 411 867 866",
    "sg:postcode":"3020",
    "sg:province":"VIC",
    "sg:tags":[
        "merchant",
        "granite",
        "marble"
    ],
    "wof:name":"G.V Marble & Building Contractors Pty Ltd",
    "wof:placetype":"venue"
},
  "geometry": {"coordinates":[144.79068000000001,-37.790394],"type":"Point"}
}