{
  "type": "Feature",
  "properties": {
    "addr:full":"26 Minerva St Albany WA 6330",
    "addr:housenumber":"26",
    "addr:postcode":"6330",
    "addr:street":"Minerva St",
    "iso:country":"AU",
    "sg:address":"26 Minerva St",
    "sg:city":"Albany",
    "sg:classifiers":[
        {
            "category":"Personal",
            "type":"Services"
        }
    ],
    "sg:phone":"+61 8 9841 3013",
    "sg:postcode":"6330",
    "sg:province":"WA",
    "sg:tags":[
        "wallpapering",
        "wallcovering"
    ],
    "wof:name":"A & S Edwards",
    "wof:placetype":"venue"
},
  "geometry": {"coordinates":[117.870903015,-35.0019607544],"type":"Point"}
}