{
  "type": "Feature",
  "properties": {
    "addr:full":"32 Hilton St Birkenhead SA 5015",
    "addr:housenumber":"32",
    "addr:postcode":"5015",
    "addr:street":"Hilton St",
    "iso:country":"AU",
    "sg:address":"32 Hilton St",
    "sg:city":"Birkenhead",
    "sg:classifiers":[
        {
            "category":"Professional",
            "subcategory":"Art Services",
            "type":"Services"
        }
    ],
    "sg:phone":"+61 8 8449 3987",
    "sg:postcode":"5015",
    "sg:province":"SA",
    "sg:tags":[
        "artist"
    ],
    "wof:name":"Ford John A",
    "wof:placetype":"venue"
},
  "geometry": {"coordinates":[138.50123596200001,-34.8338241577],"type":"Point"}
}