{
  "type": "Feature",
  "properties": {
    "addr:full":"182 Patton St Broken Hill NSW 2880",
    "addr:housenumber":"182",
    "addr:postcode":"2880",
    "addr:street":"Patton St",
    "iso:country":"AU",
    "sg:address":"182 Patton St",
    "sg:city":"Broken Hill",
    "sg:classifiers":[
        {
            "category":"Shopping",
            "subcategory":"Clothing, Apparel, & Fashions",
            "type":"Retail Goods"
        }
    ],
    "sg:phone":"+61 8 8088 5954",
    "sg:postcode":"2880",
    "sg:province":"NSW",
    "sg:tags":[
        "hire",
        "men's",
        "wear",
        "formal"
    ],
    "wof:name":"Alagich Rudolph",
    "wof:placetype":"venue"
},
  "geometry": {"coordinates":[141.46197509800001,-31.9791164398],"type":"Point"}
}