{
  "type": "Feature",
  "properties": {
    "addr:full":"416 Newcastle St Perth WA 6000",
    "addr:housenumber":"416",
    "addr:postcode":"6000",
    "addr:street":"Newcastle St",
    "iso:country":"AU",
    "sg:address":"416 Newcastle St",
    "sg:city":"Perth",
    "sg:classifiers":[
        {
            "category":"Shopping",
            "subcategory":"Gifts & Souvenirs",
            "type":"Retail Goods"
        }
    ],
    "sg:phone":"+61 8 9227 8248",
    "sg:postcode":"6000",
    "sg:province":"WA",
    "sg:tags":[
        "shop",
        "supply"
    ],
    "wof:name":"Davis J Agencies",
    "wof:placetype":"venue"
},
  "geometry": {"coordinates":[115.853157044,-31.9424724579],"type":"Point"}
}