{
  "type": "Feature",
  "properties": {
    "iso:country":"AU",
    "sg:address":"154 Taylor St",
    "sg:city":"Toowoomba",
    "sg:classifiers":[
        {
            "category":"Food & Beverages",
            "subcategory":"Fruits & Vegetables",
            "type":"Retail Goods"
        }
    ],
    "sg:phone":"+61 7 4634 7575",
    "sg:postcode":"4350",
    "sg:province":"QLD",
    "sg:tags":[
        "greengrocer",
        "fruiterer"
    ],
    "wof:name":"Taylor St Fruit Mart",
    "wof:placetype":"venue"
},
  "geometry": {"coordinates":[151.92842099999999,-27.553953],"type":"Point"}
}