{
  "type": "Feature",
  "properties": {
    "addr:full":"Main St Derby TAS 7264",
    "addr:postcode":"7264",
    "addr:street":"Main St",
    "iso:country":"AU",
    "sg:address":"Main St",
    "sg:city":"Derby",
    "sg:classifiers":[
        {
            "category":"Travel",
            "subcategory":"Hotels & Motels",
            "type":"Entertainment"
        }
    ],
    "sg:phone":"+61 3 6354 2360",
    "sg:postcode":"7264",
    "sg:province":"TAS",
    "sg:tags":[
        "accommodation"
    ],
    "wof:name":"Dorset Hotel",
    "wof:placetype":"venue"
},
  "geometry": {"coordinates":[147.79968299999999,-41.144634],"type":"Point"}
}