{
  "type": "Feature",
  "properties": {
    "iso:country":"AU",
    "sg:address":"16 Staple St",
    "sg:city":"Seventeen Mile Rocks",
    "sg:classifiers":[
        {
            "category":"Building & Trades",
            "subcategory":"Construction",
            "type":"Services"
        }
    ],
    "sg:phone":"+61 7 3376 3655",
    "sg:postcode":"4073",
    "sg:province":"QLD",
    "sg:tags":[
        "earth",
        "excavating",
        "moving",
        "contractor"
    ],
    "wof:name":"A Moggill Plant Hire",
    "wof:placetype":"venue"
},
  "geometry": {"coordinates":[152.95364379899999,-27.5439853668],"type":"Point"}
}