{
  "type": "Feature",
  "properties": {
    "addr:full":"9 Hibiscus Ave Ashgrove QLD 4060",
    "addr:housenumber":"9",
    "addr:postcode":"4060",
    "addr:street":"Hibiscus Ave",
    "iso:country":"AU",
    "sg:address":"9 Hibiscus Ave",
    "sg:city":"Ashgrove",
    "sg:classifiers":[
        {
            "category":"Utilities",
            "subcategory":"Electric",
            "type":"Services"
        }
    ],
    "sg:phone":"+61 7 3366 3240",
    "sg:postcode":"4060",
    "sg:province":"QLD",
    "sg:tags":[
        "electrical",
        "contractor"
    ],
    "wof:name":"Red Hill & Ashgrove Electrical Telephone Data & Antenna Installations",
    "wof:placetype":"venue"
},
  "geometry": {"coordinates":[152.984939575,-27.4460926056],"type":"Point"}
}