{
  "type": "Feature",
  "properties": {
    "addr:full":"47 Jack St Atherton QLD 4883",
    "addr:housenumber":"47",
    "addr:postcode":"4883",
    "addr:street":"Jack St",
    "iso:country":"AU",
    "sg:address":"47 Jack St",
    "sg:city":"Atherton",
    "sg:classifiers":[
        {
            "category":"Health Services",
            "subcategory":"Doctor",
            "type":"Services"
        }
    ],
    "sg:phone":"+61 7 4091 1800",
    "sg:postcode":"4883",
    "sg:province":"QLD",
    "sg:tags":[
        "medical",
        "practitioner"
    ],
    "wof:name":"Green A J",
    "wof:placetype":"venue"
},
  "geometry": {"coordinates":[145.47708129899999,-17.2644252777],"type":"Point"}
}