{
  "type": "Feature",
  "properties": {
    "iso:country":"AU",
    "sg:address":"Cnr Graham St",
    "sg:city":"& Raymond Tce South Brisbane",
    "sg:classifiers":[
        {
            "category":"Travel",
            "subcategory":"Hotels & Motels",
            "type":"Entertainment"
        }
    ],
    "sg:phone":"+61 7 3034 8300",
    "sg:postcode":"4101",
    "sg:province":"QLD",
    "wof:name":"South Bank Mater Motel",
    "wof:placetype":"venue"
},
  "geometry": {"coordinates":[153.02557373100001,-27.4835720062],"type":"Point"}
}