{
  "type": "Feature",
  "properties": {
    "addr:full":"PO Box 1060 Buderim QLD 4556",
    "addr:postcode":"4556",
    "iso:country":"AU",
    "sg:address":"PO Box 1060",
    "sg:city":"Buderim",
    "sg:classifiers":[
        {
            "category":"Real Estate",
            "subcategory":"Architect",
            "type":"Services"
        }
    ],
    "sg:phone":"+61 419 686 999",
    "sg:postcode":"4556",
    "sg:province":"QLD",
    "sg:tags":[
        "building",
        "designer"
    ],
    "wof:name":"Mitchell Walsh Designer Homes",
    "wof:placetype":"venue"
},
  "geometry": {"coordinates":[153.09310913100001,-26.6773891449],"type":"Point"}
}