{
  "type": "Feature",
  "properties": {
    "addr:full":"739 Burwood Hwy Ferntree Gully VIC 3156",
    "addr:housenumber":"739",
    "addr:postcode":"3156",
    "addr:street":"Burwood Hwy",
    "iso:country":"AU",
    "sg:address":"739 Burwood Hwy",
    "sg:city":"Ferntree Gully",
    "sg:classifiers":[
        {
            "category":"Manufacturing",
            "subcategory":"Food",
            "type":"Manufacturing & Wholesale Goods"
        }
    ],
    "sg:phone":"+61 3 9525 3750",
    "sg:postcode":"3156",
    "sg:province":"VIC",
    "sg:tags":[
        "function",
        "catering"
    ],
    "wof:name":"Barbeque King",
    "wof:placetype":"venue"
},
  "geometry": {"coordinates":[145.26739501899999,-37.8789596558],"type":"Point"}
}