{
  "type": "Feature",
  "properties": {
    "iso:country":"AU",
    "sg:address":"1302 Centre Rd",
    "sg:city":"Clayton",
    "sg:classifiers":[
        {
            "category":"Fast Food",
            "type":"Food & Drink"
        }
    ],
    "sg:phone":"+61 3 9544 9398",
    "sg:postcode":"3168",
    "sg:province":"VIC",
    "sg:tags":[
        "away",
        "take"
    ],
    "wof:name":"Y & W Fish & Chip Shop",
    "wof:placetype":"venue"
},
  "geometry": {"coordinates":[145.11579895,-37.9282302856],"type":"Point"}
}