{
  "type": "Feature",
  "properties": {
    "iso:country":"AU",
    "sg:address":"10/ 58 Lyons Rd",
    "sg:city":"Holden Hill",
    "sg:classifiers":[
        {
            "category":"Sports & Exercise",
            "subcategory":"Gym",
            "type":"Entertainment"
        }
    ],
    "sg:phone":"+61 8 8261 6362",
    "sg:postcode":"5088",
    "sg:province":"SA",
    "sg:tags":[
        "meditation"
    ],
    "wof:name":"Science Of Spirituality",
    "wof:placetype":"venue"
},
  "geometry": {"coordinates":[138.659469605,-34.8576812744],"type":"Point"}
}