{
  "type": "Feature",
  "properties": {
    "addr:full":"976 High St Reservoir VIC 3073",
    "addr:housenumber":"976",
    "addr:postcode":"3073",
    "addr:street":"High St",
    "iso:country":"AU",
    "sg:address":"976 High St",
    "sg:city":"Reservoir",
    "sg:classifiers":[
        {
            "category":"Personal",
            "subcategory":"Beauty Salon",
            "type":"Services"
        }
    ],
    "sg:phone":"+61 3 9478 2407",
    "sg:postcode":"3073",
    "sg:province":"VIC",
    "sg:tags":[
        "hairdresser"
    ],
    "wof:name":"Mama Africa",
    "wof:placetype":"venue"
},
  "geometry": {"coordinates":[145.00755310100001,-37.717048645],"type":"Point"}
}