{
  "type": "Feature",
  "properties": {
    "addr:full":"Shop 3 , Dunsborough Village Dunsborough WA 6281",
    "addr:housenumber":"shop 3",
    "addr:postcode":"6281",
    "addr:street":"Dunsborough Village",
    "iso:country":"AU",
    "sg:address":"Shop 3",
    "sg:city":", Dunsborough Village Dunsborough",
    "sg:classifiers":[
        {
            "category":"Real Estate",
            "subcategory":"Real Estate Agent",
            "type":"Services"
        }
    ],
    "sg:phone":"+61 8 9755 3555",
    "sg:postcode":"6281",
    "sg:province":"WA",
    "wof:name":"Cape Naturaliste First National Real Estate",
    "wof:placetype":"venue"
},
  "geometry": {"coordinates":[115.107513428,-33.6170043945],"type":"Point"}
}