{
  "type": "Feature",
  "properties": {
    "addr:full":"165 Main St Stawell VIC 3380",
    "addr:housenumber":"165",
    "addr:postcode":"3380",
    "addr:street":"Main St",
    "iso:country":"AU",
    "sg:address":"165 Main St",
    "sg:city":"Stawell",
    "sg:classifiers":[
        {
            "category":"Shopping",
            "subcategory":"Party Supplies",
            "type":"Retail Goods"
        }
    ],
    "sg:phone":"+61 3 5358 5614",
    "sg:postcode":"3380",
    "sg:province":"VIC",
    "sg:tags":[
        "hire",
        "costume"
    ],
    "wof:name":"Party People",
    "wof:placetype":"venue"
},
  "geometry": {"coordinates":[142.765625,-37.0643806458],"type":"Point"}
}