{
  "type": "Feature",
  "properties": {
    "addr:full":"317a Pakington St Newtown VIC 3220",
    "addr:housenumber":"317a",
    "addr:postcode":"3220",
    "addr:street":"Pakington St",
    "iso:country":"AU",
    "sg:address":"317a Pakington St",
    "sg:city":"Newtown",
    "sg:classifiers":[
        {
            "category":"Deli",
            "type":"Food & Drink"
        }
    ],
    "sg:phone":"+61 3 5221 5654",
    "sg:postcode":"3220",
    "sg:province":"VIC",
    "sg:tags":[
        "delicatessen"
    ],
    "wof:name":"Newtown Provedore The",
    "wof:placetype":"venue"
},
  "geometry": {"coordinates":[144.34532200000001,-38.155571],"type":"Point"}
}