{
  "type": "Feature",
  "properties": {
    "iso:country":"AU",
    "sg:address":"168 Swan St",
    "sg:city":"Morpeth",
    "sg:classifiers":[
        {
            "category":"Shopping",
            "subcategory":"Crafts & Fabrics",
            "type":"Retail Goods"
        }
    ],
    "sg:phone":"+61 2 4934 8234",
    "sg:postcode":"2321",
    "sg:province":"NSW",
    "sg:tags":[
        "supply"
    ],
    "wof:name":"Anlaby Designs",
    "wof:placetype":"venue"
},
  "geometry": {"coordinates":[151.623703003,-32.7249298096],"type":"Point"}
}