{
  "type": "Feature",
  "properties": {
    "addr:full":"4 Rubie Crs Gosford East NSW 2250",
    "addr:housenumber":"4",
    "addr:postcode":"2250",
    "addr:street":"Rubie Crs",
    "iso:country":"AU",
    "sg:address":"4 Rubie Crs",
    "sg:city":"Gosford East",
    "sg:classifiers":[
        {
            "category":"Professional",
            "subcategory":"Accounting & Tax Preparation",
            "type":"Services"
        }
    ],
    "sg:phone":"+61 417 409 728",
    "sg:postcode":"2250",
    "sg:province":"NSW",
    "sg:tags":[
        "bookkeeping"
    ],
    "wof:name":"Rubie Computer Accounting Resources",
    "wof:placetype":"venue"
},
  "geometry": {"coordinates":[151.32798767099999,-33.4495162964],"type":"Point"}
}