{
  "type": "Feature",
  "properties": {
    "addr:full":"199 Rundle St Adelaide SA 5000",
    "addr:housenumber":"199",
    "addr:postcode":"5000",
    "addr:street":"Rundle St",
    "iso:country":"AU",
    "sg:address":"199 Rundle St",
    "sg:city":"Adelaide",
    "sg:classifiers":[
        {
            "category":"Shopping",
            "subcategory":"Mobile Phones",
            "type":"Retail Goods"
        }
    ],
    "sg:phone":"+61 404 481 504",
    "sg:postcode":"5000",
    "sg:province":"SA",
    "sg:tags":[
        "telephone",
        "accessory"
    ],
    "wof:name":"Vodafone Adelaide",
    "wof:placetype":"venue"
},
  "geometry": {"coordinates":[138.60720825199999,-34.9227294922],"type":"Point"}
}