{
  "type": "Feature",
  "properties": {
    "addr:full":"11 Burradoo Rd Bowral NSW 2576",
    "addr:housenumber":"11",
    "addr:postcode":"2576",
    "addr:street":"Burradoo Rd",
    "iso:country":"AU",
    "sg:address":"11 Burradoo Rd",
    "sg:city":"Bowral",
    "sg:classifiers":[
        {
            "category":"Utilities",
            "subcategory":"Electric",
            "type":"Services"
        }
    ],
    "sg:phone":"+61 410 680 955",
    "sg:postcode":"2576",
    "sg:province":"NSW",
    "sg:tags":[
        "electrical",
        "contractor"
    ],
    "wof:name":"Full Boar Electrical & Heating Pty Ltd",
    "wof:placetype":"venue"
},
  "geometry": {"coordinates":[150.39825439399999,-34.4942245483],"type":"Point"}
}