{
  "type": "Feature",
  "properties": {
    "iso:country":"AU",
    "sg:address":"86 Davrod St",
    "sg:city":"Robertson",
    "sg:classifiers":[
        {
            "category":"Food & Beverages",
            "subcategory":"Meat & Fish",
            "type":"Retail Goods"
        }
    ],
    "sg:phone":"+61 7 3345 9390",
    "sg:postcode":"4109",
    "sg:province":"QLD",
    "sg:tags":[
        "aquaculture"
    ],
    "wof:name":"Croxway Pty Ltd",
    "wof:placetype":"venue"
},
  "geometry": {"coordinates":[153.058517456,-27.5644073486],"type":"Point"}
}