{
  "type": "Feature",
  "properties": {
    "addr:full":"375 Malvern Rd South Yarra VIC 3141",
    "addr:housenumber":"375",
    "addr:postcode":"3141",
    "addr:street":"Malvern Rd",
    "iso:country":"AU",
    "sg:address":"375 Malvern Rd",
    "sg:city":"South Yarra",
    "sg:classifiers":[
        {
            "category":"Communications",
            "subcategory":"Film & Video Production",
            "type":"Services"
        }
    ],
    "sg:phone":"+61 3 9826 9910",
    "sg:postcode":"3141",
    "sg:province":"VIC",
    "sg:tags":[
        "plating",
        "silver"
    ],
    "wof:name":"A.B.L.E. Tyson China Repairs",
    "wof:placetype":"venue"
},
  "geometry": {"coordinates":[144.99925231899999,-37.8474159241],"type":"Point"}
}