{
  "type": "Feature",
  "properties": {
    "addr:full":"119 Risdon Rd New Town TAS 7008",
    "addr:housenumber":"119",
    "addr:postcode":"7008",
    "addr:street":"Risdon Rd",
    "iso:country":"AU",
    "sg:address":"119 Risdon Rd",
    "sg:city":"New Town",
    "sg:classifiers":[
        {
            "category":"Professional",
            "subcategory":"Art Services",
            "type":"Services"
        }
    ],
    "sg:phone":"+61 3 6228 6969",
    "sg:postcode":"7008",
    "sg:province":"TAS",
    "sg:tags":[
        "artist"
    ],
    "wof:name":"Just For You Flowers & Crafts",
    "wof:placetype":"venue"
},
  "geometry": {"coordinates":[147.312133789,-42.8497848511],"type":"Point"}
}