{
  "type": "Feature",
  "properties": {
    "addr:full":"Shop 1, 60 Commercial Rd Salisbury SA 5108",
    "addr:housenumber":"shop;60",
    "addr:postcode":"5108",
    "addr:street":"Commercial Rd",
    "iso:country":"AU",
    "sg:address":"Shop 1, 60 Commercial Rd",
    "sg:city":"Salisbury",
    "sg:classifiers":[
        {
            "category":"Retail",
            "subcategory":"Repair Shop",
            "type":"Services"
        }
    ],
    "sg:phone":"+61 8 8281 8700",
    "sg:postcode":"5108",
    "sg:province":"SA",
    "sg:tags":[
        "cleaner",
        "part",
        "vacuum"
    ],
    "wof:name":"Godfreys",
    "wof:placetype":"venue"
},
  "geometry": {"coordinates":[138.649124145,-34.7555122375],"type":"Point"}
}