{
  "type": "Feature",
  "properties": {
    "addr:full":"15 Caloundra Rd Caloundra West QLD 4551",
    "addr:housenumber":"15",
    "addr:postcode":"4551",
    "addr:street":"Caloundra Rd",
    "iso:country":"AU",
    "sg:address":"15 Caloundra Rd",
    "sg:city":"Caloundra West",
    "sg:classifiers":[
        {
            "category":"Autos & Motor Vehicles",
            "subcategory":"Auto Supplies",
            "type":"Retail Goods"
        }
    ],
    "sg:phone":"+61 7 5499 6606",
    "sg:postcode":"4551",
    "sg:province":"QLD",
    "sg:tags":[
        "camper-trailers",
        "caravan",
        "equipment"
    ],
    "wof:name":"Australian Offroad Campers",
    "wof:placetype":"venue"
},
  "geometry": {"coordinates":[153.10916137699999,-26.7930755615],"type":"Point"}
}