{
  "type": "Feature",
  "properties": {
    "iso:country":"AU",
    "sg:address":"4/ 120 8th St",
    "sg:city":"Mildura",
    "sg:classifiers":[
        {
            "category":"Banks & Credit Unions",
            "subcategory":"Financial Services",
            "type":"Services"
        }
    ],
    "sg:phone":"+61 3 5021 0522",
    "sg:postcode":"3500",
    "sg:province":"VIC",
    "sg:tags":[
        "planning"
    ],
    "wof:name":"Charter Financial Planning Ltd",
    "wof:placetype":"venue"
},
  "geometry": {"coordinates":[142.154098511,-34.2107391357],"type":"Point"}
}