{
  "type": "Feature",
  "properties": {
    "iso:country":"AU",
    "sg:address":"PO Box 36923",
    "sg:city":"Winnellie",
    "sg:classifiers":[
        {
            "category":"Communications",
            "subcategory":"News Services",
            "type":"Services"
        }
    ],
    "sg:phone":"+61 8 8981 9702",
    "sg:postcode":"0820",
    "sg:province":"NT",
    "sg:tags":[
        "information",
        "tourist",
        "attractions"
    ],
    "wof:name":"East Point Military Museum",
    "wof:placetype":"venue"
},
  "geometry": {"coordinates":[130.819915772,-12.413643837],"type":"Point"}
}