{
  "type": "Feature",
  "properties": {
    "addr:full":"PO Box 2052 Tuggeranong ACT 2900",
    "addr:postcode":"2900",
    "iso:country":"AU",
    "sg:address":"PO Box 2052",
    "sg:city":"Tuggeranong",
    "sg:classifiers":[
        {
            "category":"Building & Trades",
            "subcategory":"Locksmith",
            "type":"Services"
        }
    ],
    "sg:phone":"+61 439 465 081",
    "sg:postcode":"2900",
    "sg:province":"ACT",
    "sg:tags":[
        "lock"
    ],
    "wof:name":"Access Lock & Key",
    "wof:placetype":"venue"
},
  "geometry": {"coordinates":[149.065795898,-35.4151611328],"type":"Point"}
}