{
  "type": "Feature",
  "properties": {
    "addr:full":"36 Greville St Prahran VIC 3181",
    "addr:housenumber":"36",
    "addr:postcode":"3181",
    "addr:street":"Greville St",
    "iso:country":"AU",
    "sg:address":"36 Greville St",
    "sg:city":"Prahran",
    "sg:classifiers":[
        {
            "category":"Travel",
            "subcategory":"Hotels & Motels",
            "type":"Entertainment"
        }
    ],
    "sg:phone":"+61 3 9810 0074",
    "sg:postcode":"3181",
    "sg:province":"VIC",
    "sg:tags":[
        "accommodation"
    ],
    "wof:name":"College Lawn Hotel",
    "wof:placetype":"venue"
},
  "geometry": {"coordinates":[144.987426758,-37.8488349915],"type":"Point"}
}