{
  "type": "Feature",
  "properties": {
    "iso:country":"AU",
    "sg:address":"70 Panorama Drv",
    "sg:city":"Dundowran",
    "sg:classifiers":[
        {
            "category":"Building & Trades",
            "subcategory":"Landscaping Services",
            "type":"Services"
        }
    ],
    "sg:phone":"+61 7 4128 7073",
    "sg:postcode":"4655",
    "sg:province":"QLD",
    "sg:tags":[
        "slashing",
        "contractor"
    ],
    "wof:name":"Coastline Slashing",
    "wof:placetype":"venue"
},
  "geometry": {"coordinates":[152.761597,-25.279396],"type":"Point"}
}