{
  "type": "Feature",
  "properties": {
    "addr:full":"1/ 70 Davidson Tce Joondalup WA 6027",
    "addr:housenumber":"/ 70",
    "addr:postcode":"6027",
    "addr:street":"Davidson Tce",
    "iso:country":"AU",
    "sg:address":"1/ 70",
    "sg:city":"Davidson Tce Joondalup",
    "sg:classifiers":[
        {
            "category":"Personal",
            "type":"Services"
        }
    ],
    "sg:phone":"+61 8 9300 7200",
    "sg:postcode":"6027",
    "sg:province":"WA",
    "sg:tags":[
        "career",
        "counselling"
    ],
    "wof:name":"Transitions Counselling Services",
    "wof:placetype":"venue"
},
  "geometry": {"coordinates":[115.759986877,-31.7324905396],"type":"Point"}
}