{
  "type": "Feature",
  "properties": {
    "iso:country":"AU",
    "sg:address":"80 Bridgewater Drv",
    "sg:city":"Kallaroo",
    "sg:classifiers":[
        {
            "category":"Health Services",
            "subcategory":"Health Practitioner",
            "type":"Services"
        }
    ],
    "sg:phone":"+61 8 9402 3741",
    "sg:postcode":"6025",
    "sg:province":"WA",
    "sg:tags":[
        "consultant",
        "conservation",
        "hearing"
    ],
    "wof:name":"Western Risk Management",
    "wof:placetype":"venue"
},
  "geometry": {"coordinates":[115.747779846,-31.78997612],"type":"Point"}
}