{
  "type": "Feature",
  "properties": {
    "addr:full":"2a Victoria Rd Castle Hill NSW 2154",
    "addr:housenumber":"2a",
    "addr:postcode":"2154",
    "addr:street":"Victoria Rd",
    "iso:country":"AU",
    "sg:address":"2a Victoria Rd",
    "sg:city":"Castle Hill",
    "sg:classifiers":[
        {
            "category":"Building & Trades",
            "subcategory":"Construction",
            "type":"Services"
        }
    ],
    "sg:phone":"+61 13 63 60",
    "sg:postcode":"2154",
    "sg:province":"NSW",
    "sg:tags":[
        "window",
        "tinting"
    ],
    "wof:name":"Sol-Ace The Glass Tinting Professionals",
    "wof:placetype":"venue"
},
  "geometry": {"coordinates":[150.97406005900001,-33.7201843262],"type":"Point"}
}