{
  "type": "Feature",
  "properties": {
    "addr:full":"30 Ballantyne Crs Kilsyth VIC 3137",
    "addr:housenumber":"30",
    "addr:postcode":"3137",
    "addr:street":"Ballantyne Crs",
    "iso:country":"AU",
    "sg:address":"30 Ballantyne Crs",
    "sg:city":"Kilsyth",
    "sg:classifiers":[
        {
            "category":"Home & Garden",
            "subcategory":"Household Appliances",
            "type":"Retail Goods"
        }
    ],
    "sg:phone":"+61 3 9725 0771",
    "sg:postcode":"3137",
    "sg:province":"VIC",
    "sg:tags":[
        "heating",
        "system"
    ],
    "wof:name":"Goodman R H&B D",
    "wof:placetype":"venue"
},
  "geometry": {"coordinates":[145.31497192399999,-37.8026504517],"type":"Point"}
}