{
  "type": "Feature",
  "properties": {
    "addr:full":"Shop 18 Paralowie Plaza 337 Whites Road Paralowie SA 5108",
    "addr:housenumber":"shop 18;337",
    "addr:postcode":"5108",
    "addr:street":"Paralowie Plaza;Whites Road",
    "iso:country":"AU",
    "sg:address":"Shop 18 Paralowie Plaza 337 Whites Road",
    "sg:city":"Paralowie",
    "sg:classifiers":[
        {
            "category":"Real Estate",
            "subcategory":"Real Estate Agent",
            "type":"Services"
        }
    ],
    "sg:phone":"+61 8 8250 1111",
    "sg:postcode":"5108",
    "sg:province":"SA",
    "wof:name":"Ray White South Australia",
    "wof:placetype":"venue"
},
  "geometry": {"coordinates":[138.621704102,-34.7491874695],"type":"Point"}
}