{
  "type": "Feature",
  "properties": {
    "addr:full":"Wilson St Collarenebri NSW 2833",
    "addr:postcode":"2833",
    "addr:street":"Wilson St",
    "iso:country":"AU",
    "sg:address":"Wilson St",
    "sg:city":"Collarenebri",
    "sg:classifiers":[
        {
            "category":"Food & Beverages",
            "subcategory":"Groceries & Convenience Stores",
            "type":"Retail Goods"
        }
    ],
    "sg:phone":"+61 2 6756 2142",
    "sg:postcode":"2833",
    "sg:province":"NSW",
    "wof:name":"Khans",
    "wof:placetype":"venue"
},
  "geometry": {"coordinates":[148.576263428,-29.5447788239],"type":"Point"}
}