{
  "type": "Feature",
  "properties": {
    "iso:country":"AU",
    "sg:address":"PO Box 62",
    "sg:city":"Corryong",
    "sg:classifiers":[
        {
            "category":"Building & Trades",
            "subcategory":"Landscaping Services",
            "type":"Services"
        }
    ],
    "sg:phone":"+61 2 6076 1295",
    "sg:postcode":"3707",
    "sg:province":"NSW",
    "sg:tags":[
        "control",
        "weed"
    ],
    "wof:name":"R & M Collins",
    "wof:placetype":"venue"
},
  "geometry": {"coordinates":[148.01678466800001,-36.1683044434],"type":"Point"}
}