{
  "type": "Feature",
  "properties": {
    "iso:country":"AU",
    "sg:address":"U14/ 71 Milperra Rd",
    "sg:city":"Revesby",
    "sg:classifiers":[
        {
            "category":"Home & Garden",
            "subcategory":"Building Materials",
            "type":"Retail Goods"
        }
    ],
    "sg:phone":"+61 2 9773 9288",
    "sg:postcode":"2212",
    "sg:province":"NSW",
    "sg:tags":[
        "supply"
    ],
    "wof:name":"Auschin Group Investment Pty Ltd",
    "wof:placetype":"venue"
},
  "geometry": {"coordinates":[151.01306199999999,-33.936646],"type":"Point"}
}