{
  "type": "Feature",
  "properties": {
    "iso:country":"AU",
    "sg:address":"Suite 6, 58 Great Ocean Rd",
    "sg:city":"Apollo Bay",
    "sg:classifiers":[
        {
            "category":"Government",
            "subcategory":"Court House",
            "type":"Public Place"
        }
    ],
    "sg:phone":"+61 3 5237 7446",
    "sg:postcode":"3233",
    "sg:province":"VIC",
    "sg:tags":[
        "personal",
        "marriage",
        "family",
        "counselling"
    ],
    "wof:name":"Popko P.G. Psychologist",
    "wof:placetype":"venue"
},
  "geometry": {"coordinates":[143.66517639200001,-38.7682876587],"type":"Point"}
}