{
  "type": "Feature",
  "properties": {
    "iso:country":"AU",
    "sg:address":"Settlement Rd",
    "sg:city":"Swan Marsh",
    "sg:classifiers":[
        {
            "category":"Farming",
            "subcategory":"Farm",
            "type":"Manufacturing & Wholesale Goods"
        }
    ],
    "sg:phone":"+61 3 5235 1362",
    "sg:postcode":"3249",
    "sg:province":"VIC",
    "sg:tags":[
        "farmer"
    ],
    "wof:name":"Melville M J & J M",
    "wof:placetype":"venue"
},
  "geometry": {"coordinates":[143.362991333,-38.3767662048],"type":"Point"}
}