{
  "type": "Feature",
  "properties": {
    "addr:full":"5/ 53 Dundas Crt Phillip ACT 2606",
    "addr:housenumber":"/ 53",
    "addr:postcode":"2606",
    "addr:street":"Dundas Crt",
    "iso:country":"AU",
    "sg:address":"5/ 53 Dundas Crt",
    "sg:city":"Phillip",
    "sg:classifiers":[
        {
            "category":"Personal",
            "type":"Services"
        }
    ],
    "sg:phone":"+61 2 6282 0234",
    "sg:postcode":"2606",
    "sg:province":"ACT",
    "sg:tags":[
        "career",
        "counselling"
    ],
    "wof:name":"Dupont & Associates",
    "wof:placetype":"venue"
},
  "geometry": {"coordinates":[149.09027099599999,-35.3536758423],"type":"Point"}
}