{
  "type": "Feature",
  "properties": {
    "addr:full":"Napier Rd Eumundi QLD 4562",
    "addr:postcode":"4562",
    "addr:street":"Napier Rd",
    "iso:country":"AU",
    "sg:address":"Napier Rd",
    "sg:city":"Eumundi",
    "sg:classifiers":[
        {
            "category":"Farming",
            "subcategory":"Farm",
            "type":"Manufacturing & Wholesale Goods"
        }
    ],
    "sg:phone":"+61 7 5442 8217",
    "sg:postcode":"4562",
    "sg:province":"QLD",
    "sg:tags":[
        "farmer"
    ],
    "wof:name":"Napier Janice",
    "wof:placetype":"venue"
},
  "geometry": {"coordinates":[152.95214843799999,-26.475063324],"type":"Point"}
}