{
  "type": "Feature",
  "properties": {
    "iso:country":"AU",
    "sg:address":"321 Sturt St",
    "sg:city":"Townsville",
    "sg:classifiers":[
        {
            "category":"Banks & Credit Unions",
            "subcategory":"Financial Services",
            "type":"Services"
        }
    ],
    "sg:phone":"+61 7 4772 3660",
    "sg:postcode":"4810",
    "sg:province":"QLD",
    "sg:tags":[
        "annuity",
        "rollover",
        "superannuation",
        "consultant"
    ],
    "wof:name":"Supa-Funds Management Pty Ltd",
    "wof:placetype":"venue"
},
  "geometry": {"coordinates":[146.812607,-19.262636],"type":"Point"}
}