{
  "type": "Feature",
  "properties": {
    "addr:full":"78 Darby St Cooks Hill NSW 2300",
    "addr:housenumber":"78",
    "addr:postcode":"2300",
    "addr:street":"Darby St",
    "iso:country":"AU",
    "sg:address":"78 Darby St",
    "sg:city":"Cooks Hill",
    "sg:classifiers":[
        {
            "category":"Shopping",
            "subcategory":"Clothing, Apparel, & Fashions",
            "type":"Retail Goods"
        }
    ],
    "sg:phone":"+61 2 4926 2839",
    "sg:postcode":"2300",
    "sg:province":"NSW",
    "sg:tags":[
        "menswear"
    ],
    "wof:name":"Ramjet Assortments",
    "wof:placetype":"venue"
},
  "geometry": {"coordinates":[151.768631,-32.934605],"type":"Point"}
}