{
  "type": "Feature",
  "properties": {
    "addr:full":"53 Kelleway Ave Nicholls ACT 2913",
    "addr:housenumber":"53",
    "addr:postcode":"2913",
    "addr:street":"Kelleway Ave",
    "iso:country":"AU",
    "sg:address":"53 Kelleway Ave",
    "sg:city":"Nicholls",
    "sg:classifiers":[
        {
            "category":"Professional",
            "subcategory":"Computer Services",
            "type":"Services"
        }
    ],
    "sg:phone":"+61 405 043 033",
    "sg:postcode":"2913",
    "sg:province":"ACT",
    "sg:tags":[
        "consultant",
        "system"
    ],
    "wof:name":"Taurus Computer Consultancy & Services",
    "wof:placetype":"venue"
},
  "geometry": {"coordinates":[149.10052490199999,-35.1828842163],"type":"Point"}
}