{
  "type": "Feature",
  "properties": {
    "addr:full":"37 Ruby St Emerald QLD 4720",
    "addr:housenumber":"37",
    "addr:postcode":"4720",
    "addr:street":"Ruby St",
    "iso:country":"AU",
    "sg:address":"37 Ruby St",
    "sg:city":"Emerald",
    "sg:classifiers":[
        {
            "category":"Real Estate",
            "subcategory":"Surveying",
            "type":"Services"
        }
    ],
    "sg:phone":"+61 7 4982 1208",
    "sg:postcode":"4720",
    "sg:province":"QLD",
    "sg:tags":[
        "surveyor",
        "land"
    ],
    "wof:name":"T.R. Baillie Consulting Surveyors",
    "wof:placetype":"venue"
},
  "geometry": {"coordinates":[148.15853899999999,-23.523727],"type":"Point"}
}