{
  "type": "Feature",
  "properties": {
    "addr:full":"200 Woorarra Ave Elanora Heights NSW 2101",
    "addr:housenumber":"200",
    "addr:postcode":"2101",
    "addr:street":"Woorarra Ave",
    "iso:country":"AU",
    "sg:address":"200 Woorarra Ave",
    "sg:city":"Elanora Heights",
    "sg:classifiers":[
        {
            "category":"Home & Garden",
            "subcategory":"Carpets & Floor Coverings",
            "type":"Retail Goods"
        }
    ],
    "sg:phone":"+61 412 974 790",
    "sg:postcode":"2101",
    "sg:province":"NSW",
    "sg:tags":[
        "layer",
        "planner"
    ],
    "wof:name":"Peninsula Carpet Laying Pty Ltd",
    "wof:placetype":"venue"
},
  "geometry": {"coordinates":[151.279053,-33.705368],"type":"Point"}
}