{
  "type": "Feature",
  "properties": {
    "addr:full":"Hesse St Queenscliff VIC 3225",
    "addr:postcode":"3225",
    "addr:street":"Hesse St",
    "iso:country":"AU",
    "sg:address":"Hesse St",
    "sg:city":"Queenscliff",
    "sg:classifiers":[
        {
            "category":"Education",
            "subcategory":"University",
            "type":"Public Place"
        }
    ],
    "sg:phone":"+61 3 5258 2511",
    "sg:postcode":"3225",
    "sg:province":"VIC",
    "sg:tags":[
        "educational",
        "organisation",
        "cultural"
    ],
    "wof:name":"Queenscliff Historical Society",
    "wof:placetype":"venue"
},
  "geometry": {"coordinates":[144.66096496599999,-38.2676391602],"type":"Point"}
}