{
  "type": "Feature",
  "properties": {
    "iso:country":"AU",
    "sg:address":"329b Wharf St",
    "sg:city":"Queens Park",
    "sg:classifiers":[
        {
            "category":"Government",
            "subcategory":"Post Office",
            "type":"Public Place"
        }
    ],
    "sg:phone":"+61 8 9458 1100",
    "sg:postcode":"6107",
    "sg:province":"WA",
    "sg:tags":[
        "postal"
    ],
    "wof:name":"Australia Post",
    "wof:placetype":"venue"
},
  "geometry": {"coordinates":[115.95214843799999,-31.9999961853],"type":"Point"}
}