{
  "type": "Feature",
  "properties": {
    "addr:full":"383 Old Five Islands Rd Unanderra NSW 2526",
    "addr:housenumber":"383",
    "addr:postcode":"2526",
    "addr:street":"Old Five Islands Rd",
    "iso:country":"AU",
    "sg:address":"383 Old Five Islands Rd",
    "sg:city":"Unanderra",
    "sg:classifiers":[
        {
            "category":"Building & Trades",
            "subcategory":"Construction",
            "type":"Services"
        }
    ],
    "sg:phone":"+61 2 4272 7670",
    "sg:postcode":"2526",
    "sg:province":"NSW",
    "sg:tags":[
        "renovation",
        "alterations",
        "extension",
        "contractor"
    ],
    "wof:name":"Heffernans Building & Plumbing Service Pty. Ltd.",
    "wof:placetype":"venue"
},
  "geometry": {"coordinates":[150.852416992,-34.4487953186],"type":"Point"}
}