{
  "type": "Feature",
  "properties": {
    "addr:full":"Unit 1, 61 Albert Rd Bunbury WA 6230",
    "addr:housenumber":"61",
    "addr:postcode":"6230",
    "addr:street":"Albert Rd",
    "iso:country":"AU",
    "sg:address":"Unit 1, 61 Albert Rd",
    "sg:city":"Bunbury",
    "sg:classifiers":[
        {
            "category":"Home & Garden",
            "subcategory":"Hardware",
            "type":"Retail Goods"
        }
    ],
    "sg:phone":"+61 8 9791 1433",
    "sg:postcode":"6230",
    "sg:province":"WA",
    "sg:tags":[
        "repair",
        "tool",
        "power"
    ],
    "wof:name":"Power Tools And Machinery Sales",
    "wof:placetype":"venue"
},
  "geometry": {"coordinates":[115.648422,-33.336048],"type":"Point"}
}