{
  "type": "Feature",
  "properties": {
    "addr:full":"Mosey St Landsdale WA 6065",
    "addr:postcode":"6065",
    "addr:street":"St",
    "iso:country":"AU",
    "sg:address":"Mosey St",
    "sg:city":"Landsdale",
    "sg:classifiers":[
        {
            "category":"Retail",
            "subcategory":"Auto Repair",
            "type":"Services"
        }
    ],
    "sg:phone":"+61 8 9409 9944",
    "sg:postcode":"6065",
    "sg:province":"WA",
    "sg:tags":[
        "beater",
        "painter",
        "panel"
    ],
    "wof:name":"Adaptable Panel Beaters",
    "wof:placetype":"venue"
},
  "geometry": {"coordinates":[115.84121704099999,-31.8042392731],"type":"Point"}
}