{
  "type": "Feature",
  "properties": {
    "addr:full":"Ste 101/ 35 Spring St Bondi Junction NSW 1355",
    "addr:housenumber":"/ 35",
    "addr:postcode":"1355",
    "addr:street":"Spring St",
    "iso:country":"AU",
    "sg:address":"Ste 101/ 35 Spring St",
    "sg:city":"Bondi Junction",
    "sg:classifiers":[
        {
            "category":"Travel",
            "subcategory":"Travel Agent",
            "type":"Entertainment"
        }
    ],
    "sg:phone":"+61 2 9388 0220",
    "sg:postcode":"1355",
    "sg:province":"NSW",
    "sg:tags":[
        "consultant"
    ],
    "wof:name":"Travel Blitz",
    "wof:placetype":"venue"
},
  "geometry": {"coordinates":[151.246948242,-33.892326355],"type":"Point"}
}