{
  "type": "Feature",
  "properties": {
    "addr:full":"Cnr McBurney Rd & Railway Pde Cabramatta NSW 2166",
    "addr:postcode":"2166",
    "addr:street":"Cnr Mcburney Rd & Railway Pde",
    "iso:country":"AU",
    "sg:address":"Cnr McBurney Rd & Railway Pde",
    "sg:city":"Cabramatta",
    "sg:classifiers":[
        {
            "category":"Social Services",
            "subcategory":"Child Care",
            "type":"Services"
        }
    ],
    "sg:phone":"+61 2 9727 8723",
    "sg:postcode":"2166",
    "sg:province":"NSW",
    "wof:name":"Cabramatta Occasional Child Care Centre",
    "wof:placetype":"venue"
},
  "geometry": {"coordinates":[150.93849182100001,-33.8920707703],"type":"Point"}
}