{
  "type": "Feature",
  "properties": {
    "addr:full":"46 Claremont Ave Greenacre NSW 2190",
    "addr:housenumber":"46",
    "addr:postcode":"2190",
    "addr:street":"Claremont Ave",
    "iso:country":"AU",
    "sg:address":"46 Claremont Ave",
    "sg:city":"Greenacre",
    "sg:classifiers":[
        {
            "category":"Wholesale",
            "subcategory":"Auto Parts",
            "type":"Manufacturing & Wholesale Goods"
        }
    ],
    "sg:phone":"+61 2 9709 2800",
    "sg:postcode":"2190",
    "sg:province":"NSW",
    "sg:tags":[
        "recyclers"
    ],
    "wof:name":"Sydney Auto Dismantlers",
    "wof:placetype":"venue"
},
  "geometry": {"coordinates":[151.03851299999999,-33.901295],"type":"Point"}
}