{
  "type": "Feature",
  "properties": {
    "iso:country":"AU",
    "sg:address":"4/ 9 Hutton St",
    "sg:city":"Osborne Park",
    "sg:classifiers":[
        {
            "category":"Retail",
            "subcategory":"Auto Repair",
            "type":"Services"
        }
    ],
    "sg:phone":"+61 8 9201 9998",
    "sg:postcode":"6017",
    "sg:province":"WA",
    "sg:tags":[
        "sport",
        "motor"
    ],
    "wof:name":"Revolution Racegear",
    "wof:placetype":"venue"
},
  "geometry": {"coordinates":[115.817359924,-31.9042930603],"type":"Point"}
}