{
  "type": "Feature",
  "properties": {
    "addr:full":"180 Queen St Brisbane QLD 4000",
    "addr:housenumber":"180",
    "addr:postcode":"4000",
    "addr:street":"Queen St",
    "iso:country":"AU",
    "sg:address":"180 Queen St",
    "sg:city":"Brisbane",
    "sg:classifiers":[
        {
            "category":"Manufacturing",
            "subcategory":"Jewelry",
            "type":"Manufacturing & Wholesale Goods"
        }
    ],
    "sg:phone":"+61 7 3221 6497",
    "sg:postcode":"4000",
    "sg:province":"QLD",
    "sg:tags":[
        "mfrg",
        "jeweller"
    ],
    "wof:name":"Marion Schweitzer",
    "wof:placetype":"venue"
},
  "geometry": {"coordinates":[153.02630615199999,-27.4686336517],"type":"Point"}
}