{
  "type": "Feature",
  "properties": {
    "iso:country":"AU",
    "sg:address":"Purvis La",
    "sg:city":"Dubbo",
    "sg:classifiers":[
        {
            "category":"Mining & Drilling",
            "type":"Manufacturing & Wholesale Goods"
        }
    ],
    "sg:phone":"+61 2 6884 4355",
    "sg:postcode":"2830",
    "sg:province":"NSW",
    "sg:tags":[
        "boring",
        "contractor"
    ],
    "wof:name":"State Wide Sheds",
    "wof:placetype":"venue"
},
  "geometry": {"coordinates":[148.616653442,-32.2206230164],"type":"Point"}
}