{
  "type": "Feature",
  "properties": {
    "iso:country":"AU",
    "sg:address":"307 Fullarton Rd",
    "sg:city":"Parkside",
    "sg:classifiers":[
        {
            "category":"Government",
            "subcategory":"Post Office",
            "type":"Public Place"
        }
    ],
    "sg:phone":"+61 8 8272 7002",
    "sg:postcode":"5063",
    "sg:province":"SA",
    "sg:tags":[
        "house",
        "doll"
    ],
    "wof:name":"Dolls House Gallery",
    "wof:placetype":"venue"
},
  "geometry": {"coordinates":[138.625198364,-34.9499931335],"type":"Point"}
}