{
  "type": "Feature",
  "properties": {
    "addr:full":"49- 59 Albert Ave Chatswood NSW 2067",
    "addr:housenumber":"59",
    "addr:postcode":"2067",
    "addr:street":"Albert Ave",
    "iso:country":"AU",
    "sg:address":"49- 59 Albert Ave",
    "sg:city":"Chatswood",
    "sg:classifiers":[
        {
            "category":"Shopping",
            "subcategory":"Department Store",
            "type":"Retail Goods"
        }
    ],
    "sg:phone":"+61 2 9412 0111",
    "sg:postcode":"2067",
    "sg:province":"NSW",
    "wof:name":"Myer Pty Ltd",
    "wof:placetype":"venue"
},
  "geometry": {"coordinates":[151.183105469,-33.7978820801],"type":"Point"}
}