{
  "type": "Feature",
  "properties": {
    "iso:country":"AU",
    "sg:address":"5/ 285 Canberra Ave",
    "sg:city":"Fyshwick",
    "sg:classifiers":[
        {
            "category":"Professional",
            "subcategory":"Art Services",
            "type":"Services"
        }
    ],
    "sg:phone":"+61 2 6280 9690",
    "sg:postcode":"2609",
    "sg:province":"ACT",
    "sg:tags":[
        "graphic",
        "designer"
    ],
    "wof:name":"BerrySmith",
    "wof:placetype":"venue"
},
  "geometry": {"coordinates":[149.16874694800001,-35.3335494995],"type":"Point"}
}