{
  "type": "Feature",
  "properties": {
    "addr:full":"Shop 318 Southland Shopng Cntr Cheltenham VIC 3192",
    "addr:housenumber":"318",
    "addr:postcode":"3192",
    "addr:street":"Southland Shopng Cntr",
    "iso:country":"AU",
    "sg:address":"Shop 318",
    "sg:city":"Southland Shopng Cntr Cheltenham",
    "sg:classifiers":[
        {
            "category":"Personal",
            "subcategory":"Beauty Salon",
            "type":"Services"
        }
    ],
    "sg:phone":"+61 3 9583 9148",
    "sg:postcode":"3192",
    "sg:province":"VIC",
    "sg:tags":[
        "hairdresser"
    ],
    "wof:name":"John Morrey",
    "wof:placetype":"venue"
},
  "geometry": {"coordinates":[145.073852539,-37.9676208496],"type":"Point"}
}