{
  "type": "Feature",
  "properties": {
    "addr:full":"Cnr The Esplanade & Florence St Cairns QLD 4870",
    "addr:postcode":"4870",
    "addr:street":"Cnr The Esplanade & Florence St",
    "iso:country":"AU",
    "sg:address":"Cnr The Esplanade & Florence St",
    "sg:city":"Cairns",
    "sg:classifiers":[
        {
            "category":"Food & Beverages",
            "subcategory":"Liquor & Beverages",
            "type":"Retail Goods"
        }
    ],
    "sg:phone":"+61 7 4050 6070",
    "sg:postcode":"4870",
    "sg:province":"QLD",
    "sg:tags":[
        "store"
    ],
    "wof:name":"Holiday Inn Cairns Liquor Store",
    "wof:placetype":"venue"
},
  "geometry": {"coordinates":[145.76673889200001,-16.9236412048],"type":"Point"}
}