{
  "type": "Feature",
  "properties": {
    "addr:full":"8 Hawthorn Pl Cherrybrook NSW 2126",
    "addr:housenumber":"8",
    "addr:postcode":"2126",
    "addr:street":"Hawthorn Pl",
    "iso:country":"AU",
    "sg:address":"8 Hawthorn Pl",
    "sg:city":"Cherrybrook",
    "sg:classifiers":[
        {
            "category":"Professional",
            "subcategory":"Computer Services",
            "type":"Services"
        }
    ],
    "sg:phone":"+61 2 9484 0144",
    "sg:postcode":"2126",
    "sg:province":"NSW",
    "sg:tags":[
        "consultant",
        "system"
    ],
    "wof:name":"Wilderbeast Computing Pty Ltd",
    "wof:placetype":"venue"
},
  "geometry": {"coordinates":[151.053665161,-33.714553833],"type":"Point"}
}