{
  "type": "Feature",
  "properties": {
    "iso:country":"AU",
    "sg:address":"2 Macpherson Pl",
    "sg:city":"Werribee",
    "sg:classifiers":[
        {
            "category":"Building & Trades",
            "subcategory":"Construction",
            "type":"Services"
        }
    ],
    "sg:phone":"+61 412 803 806",
    "sg:postcode":"3030",
    "sg:province":"VIC",
    "sg:tags":[
        "contractor"
    ],
    "wof:name":"Wade Builders Pty Ltd",
    "wof:placetype":"venue"
},
  "geometry": {"coordinates":[144.649567,-37.910099],"type":"Point"}
}