{
  "type": "Feature",
  "properties": {
    "addr:full":"2 Macpherson Pl Werribee VIC 3030",
    "addr:housenumber":"2",
    "addr:postcode":"3030",
    "addr:street":"Macpherson Pl",
    "iso:country":"AU",
    "sg:address":"2 Macpherson Pl",
    "sg:city":"Werribee",
    "sg:classifiers":[
        {
            "category":"Building & Trades",
            "subcategory":"Construction",
            "type":"Services"
        }
    ],
    "sg:phone":"+61 412 803 806",
    "sg:postcode":"3030",
    "sg:province":"VIC",
    "sg:tags":[
        "contractor"
    ],
    "wof:name":"Wade Builders Pty Ltd",
    "wof:placetype":"venue"
},
  "geometry": {"coordinates":[144.64956699999999,-37.910099],"type":"Point"}
}