{
  "type": "Feature",
  "properties": {
    "iso:country":"AU",
    "sg:address":"93 Watton St",
    "sg:city":"Werribee",
    "sg:classifiers":[
        {
            "category":"Shopping",
            "subcategory":"Bridal",
            "type":"Retail Goods"
        }
    ],
    "sg:phone":"+61 3 9741 3211",
    "sg:postcode":"3030",
    "sg:province":"VIC",
    "sg:tags":[
        "hire",
        "wear"
    ],
    "wof:name":"Rushford's Formal Wear",
    "wof:placetype":"venue"
},
  "geometry": {"coordinates":[144.660675,-37.901825],"type":"Point"}
}