{
  "type": "Feature",
  "properties": {
    "addr:full":"25 Boscawan Crs Bellbird Park QLD 4300",
    "addr:housenumber":"25",
    "addr:postcode":"4300",
    "addr:street":"Boscawan Crs",
    "iso:country":"AU",
    "sg:address":"25 Boscawan Crs",
    "sg:city":"Bellbird Park",
    "sg:classifiers":[
        {
            "category":"Professional",
            "subcategory":"Art Services",
            "type":"Services"
        }
    ],
    "sg:phone":"+61 418 887 158",
    "sg:postcode":"4300",
    "sg:province":"QLD",
    "sg:tags":[
        "decorator",
        "painter"
    ],
    "wof:name":"Faux Finishes",
    "wof:placetype":"venue"
},
  "geometry": {"coordinates":[152.87286376899999,-27.646780014],"type":"Point"}
}