{
  "type": "Feature",
  "properties": {
    "addr:full":"34 Dominions Rd Ashmore QLD 4214",
    "addr:housenumber":"34",
    "addr:postcode":"4214",
    "addr:street":"Dominions Rd",
    "iso:country":"AU",
    "sg:address":"34 Dominions Rd",
    "sg:city":"Ashmore",
    "sg:classifiers":[
        {
            "category":"Professional",
            "subcategory":"Detective & Security Services",
            "type":"Services"
        }
    ],
    "sg:phone":"+61 7 5597 2302",
    "sg:postcode":"4214",
    "sg:province":"QLD",
    "sg:tags":[
        "guard",
        "patrol"
    ],
    "wof:name":"Qld Property Surveillance Group",
    "wof:placetype":"venue"
},
  "geometry": {"coordinates":[153.38392639200001,-27.9806404114],"type":"Point"}
}