{
  "type": "Feature",
  "properties": {
    "addr:full":"945 Pelias St Exmouth WA 6707",
    "addr:housenumber":"945",
    "addr:postcode":"6707",
    "addr:street":"Pelias St",
    "iso:country":"AU",
    "sg:address":"945 Pelias St",
    "sg:city":"Exmouth",
    "sg:classifiers":[
        {
            "category":"Building & Trades",
            "subcategory":"Construction",
            "type":"Services"
        }
    ],
    "sg:phone":"+61 8 9949 1181",
    "sg:postcode":"6707",
    "sg:province":"WA",
    "sg:tags":[
        "contractor"
    ],
    "wof:name":"Norcape Carpentry & Joinery Pty Ltd",
    "wof:placetype":"venue"
},
  "geometry": {"coordinates":[114.128547669,-21.9378452301],"type":"Point"}
}