{
  "type": "Feature",
  "properties": {
    "iso:country":"AU",
    "sg:address":"86 Port Rd",
    "sg:city":"Kadina",
    "sg:classifiers":[
        {
            "category":"Building & Trades",
            "subcategory":"Construction",
            "type":"Services"
        }
    ],
    "sg:phone":"+61 8 8821 2077",
    "sg:postcode":"5554",
    "sg:province":"SA",
    "sg:tags":[
        "brick",
        "paving"
    ],
    "wof:name":"Australian Paving Centre",
    "wof:placetype":"venue"
},
  "geometry": {"coordinates":[137.69337463400001,-33.957950592],"type":"Point"}
}