{
  "type": "Feature",
  "properties": {
    "addr:full":"376 Water St Fortitude Valley QLD 4006",
    "addr:housenumber":"376",
    "addr:postcode":"4006",
    "addr:street":"Water St",
    "iso:country":"AU",
    "sg:address":"376 Water St",
    "sg:city":"Fortitude Valley",
    "sg:classifiers":[
        {
            "category":"Professional",
            "subcategory":"Art Services",
            "type":"Services"
        }
    ],
    "sg:phone":"+61 7 3257 4484",
    "sg:postcode":"4006",
    "sg:province":"QLD",
    "sg:tags":[
        "product",
        "industrial",
        "designer"
    ],
    "wof:name":"CLUI URBAN",
    "wof:placetype":"venue"
},
  "geometry": {"coordinates":[153.03216552699999,-27.4533443451],"type":"Point"}
}