{
  "type": "Feature",
  "properties": {
    "addr:full":"Corner Main Road & Tamborine QLD 4270",
    "addr:postcode":"4270",
    "addr:street":"Main Road & Tamborine",
    "iso:country":"AU",
    "sg:address":"Corner Main Road",
    "sg:city":"& Tamborine",
    "sg:classifiers":[
        {
            "category":"Cafe",
            "type":"Food & Drink"
        }
    ],
    "sg:phone":"+61 419 614 021",
    "sg:postcode":"4270",
    "sg:province":"QLD",
    "wof:name":"Alumbre Literary Cafe",
    "wof:placetype":"venue"
},
  "geometry": {"coordinates":[153.13044738799999,-27.8806591034],"type":"Point"}
}