{
  "type": "Feature",
  "properties": {
    "iso:country":"AU",
    "sg:address":"38 Rose St",
    "sg:city":"Annandale",
    "sg:classifiers":[
        {
            "category":"Travel",
            "subcategory":"Travel Agent",
            "type":"Entertainment"
        }
    ],
    "sg:phone":"+61 2 9660 6397",
    "sg:postcode":"2038",
    "sg:province":"NSW",
    "sg:tags":[
        "consultant"
    ],
    "wof:name":"Trekaway Pty Ltd",
    "wof:placetype":"venue"
},
  "geometry": {"coordinates":[151.173294067,-33.87657547],"type":"Point"}
}