{
  "type": "Feature",
  "properties": {
    "iso:country":"AU",
    "sg:address":"Shp1/ 291 Clyde St",
    "sg:city":"Granville",
    "sg:classifiers":[
        {
            "category":"Food & Beverages",
            "subcategory":"Bakery",
            "type":"Retail Goods"
        }
    ],
    "sg:phone":"+61 2 9682 4111",
    "sg:postcode":"2142",
    "sg:province":"NSW",
    "sg:tags":[
        "baker"
    ],
    "wof:name":"Rawda Bakery",
    "wof:placetype":"venue"
},
  "geometry": {"coordinates":[151.010986328,-33.8575210571],"type":"Point"}
}