{
  "type": "Feature",
  "properties": {
    "iso:country":"AU",
    "sg:address":"237 Canterbury Rd",
    "sg:city":"Canterbury",
    "sg:classifiers":[
        {
            "category":"Shopping",
            "subcategory":"Antiques",
            "type":"Retail Goods"
        }
    ],
    "sg:phone":"+61 3 9836 2301",
    "sg:postcode":"3126",
    "sg:province":"VIC",
    "wof:name":"Dalbry Antiques & Collectables",
    "wof:placetype":"venue"
},
  "geometry": {"coordinates":[145.08151245100001,-37.8239097595],"type":"Point"}
}