{
  "type": "Feature",
  "properties": {
    "addr:full":"21 Lusty St Arncliffe NSW 2205",
    "addr:housenumber":"21",
    "addr:postcode":"2205",
    "addr:street":"Lusty St",
    "iso:country":"AU",
    "sg:address":"21 Lusty St",
    "sg:city":"Arncliffe",
    "sg:classifiers":[
        {
            "category":"Shopping",
            "subcategory":"Gifts & Souvenirs",
            "type":"Retail Goods"
        }
    ],
    "sg:phone":"+61 2 9597 5888",
    "sg:postcode":"2205",
    "sg:province":"NSW",
    "sg:tags":[
        "shop",
        "supply"
    ],
    "wof:name":"Robert Blau (Aust) Pty Ltd",
    "wof:placetype":"venue"
},
  "geometry": {"coordinates":[151.149765,-33.9291],"type":"Point"}
}