{
  "type": "Feature",
  "properties": {
    "iso:country":"AU",
    "sg:address":"4/ 165 Rookwood Rd",
    "sg:city":"Bankstown",
    "sg:classifiers":[
        {
            "category":"Home & Garden",
            "subcategory":"Carpets & Floor Coverings",
            "type":"Retail Goods"
        }
    ],
    "sg:phone":"+61 2 9796 7833",
    "sg:postcode":"2200",
    "sg:province":"NSW",
    "wof:name":"Rainbow Floor Services P / L",
    "wof:placetype":"venue"
},
  "geometry": {"coordinates":[151.037354,-33.899933],"type":"Point"}
}