{
  "type": "Feature",
  "properties": {
    "iso:country":"AU",
    "sg:address":"Shop 8 Greenfield Village Shopping Centre",
    "sg:city":"Greenfield Park",
    "sg:classifiers":[
        {
            "category":"Deli",
            "type":"Food & Drink"
        }
    ],
    "sg:phone":"+61 2 9610 9727",
    "sg:postcode":"2176",
    "sg:province":"NSW",
    "sg:tags":[
        "delicatessen"
    ],
    "wof:name":"Rite Deli",
    "wof:placetype":"venue"
},
  "geometry": {"coordinates":[150.89369201700001,-33.8716850281],"type":"Point"}
}