{
  "type": "Feature",
  "properties": {
    "addr:full":"4 Toonburra St Bundaberg QLD 4670",
    "addr:housenumber":"4",
    "addr:postcode":"4670",
    "addr:street":"Toonburra St",
    "iso:country":"AU",
    "sg:address":"4 Toonburra St",
    "sg:city":"Bundaberg",
    "sg:classifiers":[
        {
            "category":"Autos & Motor Vehicles",
            "subcategory":"Auto Supplies",
            "type":"Retail Goods"
        }
    ],
    "sg:phone":"+61 7 4151 2381",
    "sg:postcode":"4670",
    "sg:province":"QLD",
    "sg:tags":[
        "oil",
        "spirit"
    ],
    "wof:name":"Castrol Australia Pty Ltd",
    "wof:placetype":"venue"
},
  "geometry": {"coordinates":[152.35644531200001,-24.8634548187],"type":"Point"}
}