{
  "type": "Feature",
  "properties": {
    "addr:full":"Shop 4, Dural Mall, Round Corner. Dural NSW 2158",
    "addr:housenumber":"shop 4",
    "addr:postcode":"2158",
    "addr:street":"Dural Mall Round Corner.",
    "iso:country":"AU",
    "sg:address":"Shop 4, Dural Mall, Round Corner.",
    "sg:city":"Dural",
    "sg:classifiers":[
        {
            "category":"Health Services",
            "subcategory":"Doctor",
            "type":"Services"
        }
    ],
    "sg:phone":"+61 2 9651 1269",
    "sg:postcode":"2158",
    "sg:province":"NSW",
    "sg:tags":[
        "medical",
        "practitioner"
    ],
    "wof:name":"Szekely Ilona Dr",
    "wof:placetype":"venue"
},
  "geometry": {"coordinates":[151.00428772000001,-33.6645622253],"type":"Point"}
}