{
  "type": "Feature",
  "properties": {
    "addr:full":"81 Leopold St Aitkenvale QLD 4814",
    "addr:housenumber":"81",
    "addr:postcode":"4814",
    "addr:street":"Leopold St",
    "iso:country":"AU",
    "sg:address":"81 Leopold St",
    "sg:city":"Aitkenvale",
    "sg:classifiers":[
        {
            "category":"Retail",
            "subcategory":"Auto Repair",
            "type":"Services"
        }
    ],
    "sg:phone":"+61 418 777 077",
    "sg:postcode":"4814",
    "sg:province":"QLD",
    "sg:tags":[
        "repairer",
        "motor",
        "engineer"
    ],
    "wof:name":"Arrows Mobile Brake Repairs",
    "wof:placetype":"venue"
},
  "geometry": {"coordinates":[146.77032500000001,-19.305853],"type":"Point"}
}