{
  "type": "Feature",
  "properties": {
    "addr:full":"24 McCourt St West Leederville WA 6007",
    "addr:housenumber":"24",
    "addr:postcode":"6007",
    "addr:street":"Mccourt St West",
    "iso:country":"AU",
    "sg:address":"24 McCourt St",
    "sg:city":"West Leederville",
    "sg:classifiers":[
        {
            "category":"Health Services",
            "subcategory":"Doctor",
            "type":"Services"
        }
    ],
    "sg:phone":"+61 8 9381 7011",
    "sg:postcode":"6007",
    "sg:province":"WA",
    "sg:tags":[
        "medical",
        "practitioner"
    ],
    "wof:name":"Toussaint R L Serge Dr.",
    "wof:placetype":"venue"
},
  "geometry": {"coordinates":[115.827819824,-31.9416866302],"type":"Point"}
}