{
  "type": "Feature",
  "properties": {
    "addr:full":"1a Cleveland Rd Ashwood VIC 3147",
    "addr:housenumber":"1a",
    "addr:postcode":"3147",
    "addr:street":"Cleveland Rd",
    "iso:country":"AU",
    "sg:address":"1a Cleveland Rd",
    "sg:city":"Ashwood",
    "sg:classifiers":[
        {
            "category":"Personal",
            "subcategory":"Beauty Salon",
            "type":"Services"
        }
    ],
    "sg:phone":"+61 3 9807 1641",
    "sg:postcode":"3147",
    "sg:province":"VIC",
    "sg:tags":[
        "hairdresser"
    ],
    "wof:name":"Empire Hair",
    "wof:placetype":"venue"
},
  "geometry": {"coordinates":[145.10540771500001,-37.8673324585],"type":"Point"}
}