{
  "type": "Feature",
  "properties": {
    "addr:full":"503a Bluff St Hampton VIC 3188",
    "addr:housenumber":"503a",
    "addr:postcode":"3188",
    "addr:street":"Bluff St",
    "iso:country":"AU",
    "sg:address":"503a Bluff St",
    "sg:city":"Hampton",
    "sg:classifiers":[
        {
            "category":"Building & Trades",
            "subcategory":"Construction",
            "type":"Services"
        }
    ],
    "sg:phone":"+61 3 9533 5841",
    "sg:postcode":"3188",
    "sg:province":"VIC",
    "sg:tags":[
        "polishing",
        "sanding",
        "floor"
    ],
    "wof:name":"JJA Floor Services",
    "wof:placetype":"venue"
},
  "geometry": {"coordinates":[145.02444457999999,-37.9336204529],"type":"Point"}
}