{
  "type": "Feature",
  "properties": {
    "iso:country":"AU",
    "sg:address":"418 Roper Rd",
    "sg:city":"Colyton",
    "sg:classifiers":[
        {
            "category":"Building & Trades",
            "subcategory":"Construction",
            "type":"Services"
        }
    ],
    "sg:phone":"+61 2 9623 6177",
    "sg:postcode":"2760",
    "sg:province":"NSW",
    "sg:tags":[
        "earth",
        "excavating",
        "moving",
        "contractor"
    ],
    "wof:name":"Bryant Group Earth Boring",
    "wof:placetype":"venue"
},
  "geometry": {"coordinates":[150.802337647,-33.7794265747],"type":"Point"}
}