{
  "type": "Feature",
  "properties": {
    "iso:country":"AU",
    "sg:address":"90 Morphett Rd",
    "sg:city":"Glengowrie",
    "sg:classifiers":[
        {
            "category":"Retail",
            "subcategory":"Veterinary Services",
            "type":"Services"
        }
    ],
    "sg:phone":"+61 8 8294 8444",
    "sg:postcode":"5044",
    "sg:province":"SA",
    "sg:tags":[
        "surgeon"
    ],
    "wof:name":"Byrne Robin",
    "wof:placetype":"venue"
},
  "geometry": {"coordinates":[138.53894,-34.993168],"type":"Point"}
}