{
  "type": "Feature",
  "properties": {
    "addr:full":"9a Wittenoom St Bunbury WA 6230",
    "addr:housenumber":"9a",
    "addr:postcode":"6230",
    "addr:street":"Wittenoom St",
    "iso:country":"AU",
    "sg:address":"9a Wittenoom St",
    "sg:city":"Bunbury",
    "sg:classifiers":[
        {
            "category":"Arts & Performance",
            "subcategory":"Art Gallery",
            "type":"Entertainment"
        }
    ],
    "sg:phone":"+61 407 443 104",
    "sg:postcode":"6230",
    "sg:province":"WA",
    "wof:name":"Steve Sheehan",
    "wof:placetype":"venue"
},
  "geometry": {"coordinates":[115.63565800000001,-33.320293],"type":"Point"}
}