{
  "type": "Feature",
  "properties": {
    "addr:full":"295 Warick Rd Greenwood WA 6024",
    "addr:housenumber":"295",
    "addr:postcode":"6024",
    "addr:street":"Warick Rd",
    "iso:country":"AU",
    "sg:address":"295 Warick Rd",
    "sg:city":"Greenwood",
    "sg:classifiers":[
        {
            "category":"Health Services",
            "subcategory":"Health Practitioner",
            "type":"Services"
        }
    ],
    "sg:phone":"+61 400 485 121",
    "sg:postcode":"6024",
    "sg:province":"WA",
    "sg:tags":[
        "psychologist"
    ],
    "wof:name":"Cain Anna",
    "wof:placetype":"venue"
},
  "geometry": {"coordinates":[115.796173096,-31.8374118805],"type":"Point"}
}