{
  "type": "Feature",
  "properties": {
    "addr:full":"Suite 5, Cabrini Medical Centre,177 Wattletree Road Malvern VIC 3144",
    "addr:housenumber":"177",
    "addr:postcode":"3144",
    "addr:street":"Wattletree Road",
    "iso:country":"AU",
    "sg:address":"Suite 5, Cabrini Medical Centre,177 Wattletree Road",
    "sg:city":"Malvern",
    "sg:classifiers":[
        {
            "category":"Health Services",
            "subcategory":"Doctor",
            "type":"Services"
        }
    ],
    "sg:phone":"+61 3 9500 2919",
    "sg:postcode":"3144",
    "sg:province":"VIC",
    "sg:tags":[
        "medical",
        "practitioner"
    ],
    "wof:name":"Chu Peter Mr",
    "wof:placetype":"venue"
},
  "geometry": {"coordinates":[145.032669067,-37.8628005981],"type":"Point"}
}