{
  "type": "Feature",
  "properties": {
    "addr:full":"48 Leichhardt St Katoomba NSW 2780",
    "addr:housenumber":"48",
    "addr:postcode":"2780",
    "addr:street":"Leichhardt St",
    "iso:country":"AU",
    "sg:address":"48 Leichhardt St",
    "sg:city":"Katoomba",
    "sg:classifiers":[
        {
            "category":"Building & Trades",
            "subcategory":"Construction",
            "type":"Services"
        }
    ],
    "sg:phone":"+61 2 4782 9636",
    "sg:postcode":"2780",
    "sg:province":"NSW",
    "sg:tags":[
        "fencing",
        "contractor"
    ],
    "wof:name":"Katoomba Fencing",
    "wof:placetype":"venue"
},
  "geometry": {"coordinates":[150.31712341299999,-33.7161102295],"type":"Point"}
}