{
  "type": "Feature",
  "properties": {
    "iso:country":"AU",
    "sg:address":"394 Belgrave-Gembrook Rd",
    "sg:city":"Emerald",
    "sg:classifiers":[
        {
            "category":"Cafe",
            "type":"Food & Drink"
        }
    ],
    "sg:phone":"+61 3 5968 6655",
    "sg:postcode":"3782",
    "sg:province":"VIC",
    "wof:name":"Suitably Mellow Cafe",
    "wof:placetype":"venue"
},
  "geometry": {"coordinates":[145.444565,-37.93005],"type":"Point"}
}