{
  "type": "Feature",
  "properties": {
    "iso:country":"AU",
    "sg:address":"4 Armstrong St",
    "sg:city":"Geraldton",
    "sg:classifiers":[
        {
            "category":"Manufacturing",
            "subcategory":"Motor Vehicles & Parts",
            "type":"Manufacturing & Wholesale Goods"
        }
    ],
    "sg:phone":"+61 8 9965 7000",
    "sg:postcode":"6530",
    "sg:province":"WA",
    "sg:tags":[
        "replacement"
    ],
    "wof:name":"Auto One Parts And Accessories",
    "wof:placetype":"venue"
},
  "geometry": {"coordinates":[114.611236572,-28.774061203],"type":"Point"}
}