{
  "type": "Feature",
  "properties": {
    "addr:full":"31 Warwick St Hobart TAS 7000",
    "addr:housenumber":"31",
    "addr:postcode":"7000",
    "addr:street":"Warwick St",
    "iso:country":"AU",
    "sg:address":"31 Warwick St",
    "sg:city":"Hobart",
    "sg:classifiers":[
        {
            "category":"Social Services",
            "subcategory":"Adult Care",
            "type":"Services"
        }
    ],
    "sg:phone":"+61 3 6272 7433",
    "sg:postcode":"7000",
    "sg:province":"TAS",
    "sg:tags":[
        "towing"
    ],
    "wof:name":"Hobart Smash Repairs",
    "wof:placetype":"venue"
},
  "geometry": {"coordinates":[147.322433472,-42.875125885],"type":"Point"}
}