{
  "type": "Feature",
  "properties": {
    "addr:full":"Cnr Kingsford Smith Drv & Nudgee Rd Hamilton QLD 4007",
    "addr:postcode":"4007",
    "addr:street":"Kingsford Smith Drv & Nudgee Rd",
    "iso:country":"AU",
    "sg:address":"Cnr Kingsford Smith Drv & Nudgee Rd",
    "sg:city":"Hamilton",
    "sg:classifiers":[
        {
            "category":"Travel",
            "subcategory":"Hotels & Motels",
            "type":"Entertainment"
        }
    ],
    "sg:phone":"+61 7 3868 4444",
    "sg:postcode":"4007",
    "sg:province":"QLD",
    "sg:website":"http://www.kingsfordsmithmotel.com.au",
    "wof:name":"Kingsford Smith Motel",
    "wof:placetype":"venue"
},
  "geometry": {"coordinates":[153.072845,-27.436596],"type":"Point"}
}