{
  "type": "Feature",
  "properties": {
    "addr:full":"26 William St Brookvale NSW 2100",
    "addr:housenumber":"26",
    "addr:postcode":"2100",
    "addr:street":"William St",
    "iso:country":"AU",
    "sg:address":"26 William St",
    "sg:city":"Brookvale",
    "sg:classifiers":[
        {
            "category":"Building & Trades",
            "subcategory":"Construction",
            "type":"Services"
        }
    ],
    "sg:phone":"+61 2 9939 7271",
    "sg:postcode":"2100",
    "sg:province":"NSW",
    "sg:tags":[
        "concrete",
        "contractor"
    ],
    "wof:name":"Sten-Crete Pty Limited",
    "wof:placetype":"venue"
},
  "geometry": {"coordinates":[151.27088928200001,-33.7684402466],"type":"Point"}
}