{
  "type": "Feature",
  "properties": {
    "addr:full":"36 Econo Pl Silverdale NSW 2752",
    "addr:housenumber":"36",
    "addr:postcode":"2752",
    "addr:street":"Econo Pl",
    "iso:country":"AU",
    "sg:address":"36 Econo Pl",
    "sg:city":"Silverdale",
    "sg:classifiers":[
        {
            "category":"Wholesale",
            "subcategory":"Auto Parts",
            "type":"Manufacturing & Wholesale Goods"
        }
    ],
    "sg:phone":"+61 2 4774 1741",
    "sg:postcode":"2752",
    "sg:province":"NSW",
    "sg:tags":[
        "recyclers"
    ],
    "sg:website":"http://www.landvehiclespares.com",
    "wof:name":"Land Vehicle Spares",
    "wof:placetype":"venue"
},
  "geometry": {"coordinates":[150.61331176799999,-33.8922157288],"type":"Point"}
}