{
  "type": "Feature",
  "properties": {
    "iso:country":"AU",
    "sg:address":"Waikiki Village Shopng Cntr 7 Read St",
    "sg:city":"Waikiki",
    "sg:classifiers":[
        {
            "category":"Food & Beverages",
            "subcategory":"Meat & Fish",
            "type":"Retail Goods"
        }
    ],
    "sg:phone":"+61 8 9591 1227",
    "sg:postcode":"6169",
    "sg:province":"WA",
    "sg:tags":[
        "seafood"
    ],
    "wof:name":"Read Street Fish Supply",
    "wof:placetype":"venue"
},
  "geometry": {"coordinates":[115.753372,-32.31662],"type":"Point"}
}