{
  "type": "Feature",
  "properties": {
    "iso:country":"AU",
    "sg:address":"1st Floor 832 Anzac Parade St",
    "sg:city":"Maroubra",
    "sg:classifiers":[
        {
            "category":"Health Services",
            "subcategory":"Doctor",
            "type":"Services"
        }
    ],
    "sg:phone":"+61 2 9344 0200",
    "sg:postcode":"2035",
    "sg:province":"NSW",
    "sg:tags":[
        "medical",
        "practitioner"
    ],
    "wof:name":"X-Ray Practice Maroubra Junction",
    "wof:placetype":"venue"
},
  "geometry": {"coordinates":[151.23942565900001,-33.940322876],"type":"Point"}
}