{
  "type": "Feature",
  "properties": {
    "addr:full":"Unit 30 MIAC Building International Drv Tullamarine VIC 3043",
    "addr:postcode":"3043",
    "addr:street":"International Drv",
    "iso:country":"AU",
    "sg:address":"Unit 30 MIAC Building International Drv",
    "sg:city":"Tullamarine",
    "sg:classifiers":[
        {
            "category":"Professional",
            "subcategory":"Employment Agencies",
            "type":"Services"
        }
    ],
    "sg:phone":"+61 3 9338 9355",
    "sg:postcode":"3043",
    "sg:province":"VIC",
    "sg:tags":[
        "broker",
        "custom"
    ],
    "wof:name":"Braywin (Vic) Pty Ltd",
    "wof:placetype":"venue"
},
  "geometry": {"coordinates":[144.917404175,-37.6747131348],"type":"Point"}
}