{
  "type": "Feature",
  "properties": {
    "addr:full":"Shop 2/ 32 Sumners Rd Sumner QLD 4074",
    "addr:housenumber":"shop 2 / 32",
    "addr:postcode":"4074",
    "addr:street":"Sumners Rd",
    "iso:country":"AU",
    "sg:address":"Shop 2/ 32 Sumners Rd",
    "sg:city":"Sumner",
    "sg:phone":"+61 7 3279 5600",
    "sg:postcode":"4074",
    "sg:province":"QLD",
    "sg:website":"http://www.designerwatering.com.au",
    "wof:name":"Designer Watering Systems",
    "wof:placetype":"venue"
},
  "geometry": {"coordinates":[152.93682861299999,-27.559885025],"type":"Point"}
}