{
  "type": "Feature",
  "properties": {
    "addr:full":"Dandenong Hwy Airport West VIC 3042",
    "addr:postcode":"3042",
    "addr:street":"Dandenong Hwy",
    "iso:country":"AU",
    "sg:address":"Dandenong Hwy",
    "sg:city":"Airport West",
    "sg:classifiers":[
        {
            "category":"Fast Food",
            "type":"Food & Drink"
        }
    ],
    "sg:phone":"+61 3 8336 1234",
    "sg:postcode":"3042",
    "sg:province":"VIC",
    "sg:tags":[
        "away",
        "take"
    ],
    "wof:name":"Sushi Sushi",
    "wof:placetype":"venue"
},
  "geometry": {"coordinates":[144.88563537600001,-37.7126159668],"type":"Point"}
}