{
  "type": "Feature",
  "properties": {
    "addr:full":"363 Parramatta Rd Leichhardt NSW 2040",
    "addr:housenumber":"363",
    "addr:postcode":"2040",
    "addr:street":"Parramatta Rd",
    "iso:country":"AU",
    "sg:address":"363 Parramatta Rd",
    "sg:city":"Leichhardt",
    "sg:classifiers":[
        {
            "category":"Health Services",
            "subcategory":"Optometrist",
            "type":"Services"
        }
    ],
    "sg:phone":"+61 2 9560 4507",
    "sg:postcode":"2040",
    "sg:province":"NSW",
    "wof:name":"Mangraviti Michael",
    "wof:placetype":"venue"
},
  "geometry": {"coordinates":[151.15858499999999,-33.887856],"type":"Point"}
}