{
  "type": "Feature",
  "properties": {
    "addr:full":"Shop 20, Castletown Shopping Centre 35 Kings Rd Pimlico QLD 4812",
    "addr:housenumber":"shop 20;35",
    "addr:postcode":"4812",
    "addr:street":"Castletown Shopping;Kings Rd",
    "iso:country":"AU",
    "sg:address":"Shop 20, Castletown Shopping Centre 35 Kings Rd",
    "sg:city":"Pimlico",
    "sg:classifiers":[
        {
            "category":"Personal",
            "subcategory":"Beauty Salon",
            "type":"Services"
        }
    ],
    "sg:phone":"+61 7 4721 1866",
    "sg:postcode":"4812",
    "sg:province":"QLD",
    "sg:tags":[
        "hairdresser"
    ],
    "wof:name":"TMH Salons",
    "wof:placetype":"venue"
},
  "geometry": {"coordinates":[146.79217499999999,-19.27426],"type":"Point"}
}