{
  "type": "Feature",
  "properties": {
    "iso:country":"AU",
    "sg:address":"Shp 1",
    "sg:city":"55, Level 1, Melbourne Central Shopping Cntr",
    "sg:classifiers":[
        {
            "category":"Shopping",
            "subcategory":"Computers & Home Electronics",
            "type":"Retail Goods"
        }
    ],
    "sg:phone":"+61 3 9650 8144",
    "sg:postcode":"3000",
    "sg:province":"VIC",
    "sg:tags":[
        "hi-fi",
        "equipment"
    ],
    "wof:name":"Go Audio Visual",
    "wof:placetype":"venue"
},
  "geometry": {"coordinates":[144.968505859,-37.8133964539],"type":"Point"}
}