{
  "type": "Feature",
  "properties": {
    "addr:full":"Somerville Rd Hampton Park VIC 3976",
    "addr:postcode":"3976",
    "addr:street":"Somerville Rd",
    "iso:country":"AU",
    "sg:address":"Somerville Rd",
    "sg:city":"Hampton Park",
    "sg:classifiers":[
        {
            "category":"Arena",
            "subcategory":"Sports Club",
            "type":"Entertainment"
        }
    ],
    "sg:phone":"+61 3 9799 0486",
    "sg:postcode":"3976",
    "sg:province":"VIC",
    "sg:tags":[
        "australian",
        "football",
        "rule"
    ],
    "wof:name":"Hampton Park Football Club",
    "wof:placetype":"venue"
},
  "geometry": {"coordinates":[145.26742553700001,-38.0321273804],"type":"Point"}
}