{
  "type": "Feature",
  "properties": {
    "addr:full":"Cnr Riverbend Ave and Nerang Broadbeach Rd Carrara QLD 4211",
    "addr:postcode":"4211",
    "addr:street":"Cnr Riverbend Ave And Nerang Broadbeach Rd",
    "iso:country":"AU",
    "sg:address":"Cnr Riverbend Ave and Nerang Broadbeach Rd",
    "sg:city":"Carrara",
    "sg:classifiers":[
        {
            "category":"Professional",
            "type":"Services"
        }
    ],
    "sg:phone":"+61 7 5559 1999",
    "sg:postcode":"4211",
    "sg:province":"QLD",
    "sg:tags":[
        "auctioneer"
    ],
    "wof:name":"Lloyds Auctioneers & Valuers",
    "wof:placetype":"venue"
},
  "geometry": {"coordinates":[153.366653442,-28.0085773468],"type":"Point"}
}