{
  "type": "Feature",
  "properties": {
    "addr:full":"28 Michael St Pakenham VIC 3810",
    "addr:housenumber":"28",
    "addr:postcode":"3810",
    "addr:street":"Michael St",
    "iso:country":"AU",
    "sg:address":"28 Michael St",
    "sg:city":"Pakenham",
    "sg:classifiers":[
        {
            "category":"Retail",
            "subcategory":"Auto Repair",
            "type":"Services"
        }
    ],
    "sg:phone":"+61 3 5941 2369",
    "sg:postcode":"3810",
    "sg:province":"VIC",
    "sg:tags":[
        "bus",
        "truck"
    ],
    "wof:name":"RMB Truck Repairs",
    "wof:placetype":"venue"
},
  "geometry": {"coordinates":[145.45901499999999,-38.059219],"type":"Point"}
}