{
  "type": "Feature",
  "properties": {
    "iso:country":"AU",
    "sg:address":"22 Brentwood Ave",
    "sg:city":"Lalor",
    "sg:classifiers":[
        {
            "category":"Government",
            "subcategory":"Fire Station",
            "type":"Public Place"
        }
    ],
    "sg:phone":"+61 3 9464 4077",
    "sg:postcode":"3075",
    "sg:province":"VIC",
    "sg:tags":[
        "equipment",
        "protection",
        "consultant"
    ],
    "wof:name":"Prevention Fire Protection Services",
    "wof:placetype":"venue"
},
  "geometry": {"coordinates":[144.93324279800001,-37.7475662231],"type":"Point"}
}