{
  "type": "Feature",
  "properties": {
    "addr:full":"Country Court 172 Fourteenth St Renmark SA 5341",
    "addr:housenumber":"172",
    "addr:postcode":"5341",
    "addr:street":"Country Court;Fourteenth St",
    "iso:country":"AU",
    "sg:address":"Country Court 172 Fourteenth St",
    "sg:city":"Renmark",
    "sg:classifiers":[
        {
            "category":"Health Services",
            "subcategory":"Health Practitioner",
            "type":"Services"
        }
    ],
    "sg:phone":"+61 8 8586 5126",
    "sg:postcode":"5341",
    "sg:province":"SA",
    "sg:tags":[
        "physiotherapist"
    ],
    "wof:name":"Bolton Joanne",
    "wof:placetype":"venue"
},
  "geometry": {"coordinates":[140.74783325199999,-34.1711006165],"type":"Point"}
}