{
  "type": "Feature",
  "properties": {
    "addr:full":"171 A Storey St Maroubra NSW 2035",
    "addr:housenumber":"171 a",
    "addr:postcode":"2035",
    "addr:street":"Storey St",
    "iso:country":"AU",
    "sg:address":"171 A Storey St",
    "sg:city":"Maroubra",
    "sg:classifiers":[
        {
            "category":"Personal",
            "subcategory":"Beauty Salon",
            "type":"Services"
        }
    ],
    "sg:phone":"+61 2 9314 3777",
    "sg:postcode":"2035",
    "sg:province":"NSW",
    "sg:tags":[
        "hairdresser"
    ],
    "wof:name":"Medusa Hair & Beauty",
    "wof:placetype":"venue"
},
  "geometry": {"coordinates":[151.23828125,-33.9370002747],"type":"Point"}
}