{
  "type": "Feature",
  "properties": {
    "addr:full":"161 Trimmer Pde Seaton SA 5023",
    "addr:housenumber":"161",
    "addr:postcode":"5023",
    "addr:street":"Trimmer Pde",
    "iso:country":"AU",
    "sg:address":"161 Trimmer Pde",
    "sg:city":"Seaton",
    "sg:classifiers":[
        {
            "category":"Deli",
            "type":"Food & Drink"
        }
    ],
    "sg:phone":"+61 8 8347 4712",
    "sg:postcode":"5023",
    "sg:province":"SA",
    "sg:tags":[
        "delicatessen"
    ],
    "wof:name":"Seaton Supreme Foods",
    "wof:placetype":"venue"
},
  "geometry": {"coordinates":[138.51593017600001,-34.8918952942],"type":"Point"}
}