{
  "type": "Feature",
  "properties": {
    "addr:full":"156 Millers Rd Altona North VIC 3025",
    "addr:housenumber":"156",
    "addr:postcode":"3025",
    "addr:street":"Millers Rd",
    "iso:country":"AU",
    "sg:address":"156 Millers Rd",
    "sg:city":"Altona North",
    "sg:classifiers":[
        {
            "category":"Health Services",
            "subcategory":"Doctor",
            "type":"Services"
        }
    ],
    "sg:phone":"+61 3 9315 2277",
    "sg:postcode":"3025",
    "sg:province":"VIC",
    "sg:tags":[
        "medical",
        "practitioner"
    ],
    "wof:name":"Bell Imaging Group",
    "wof:placetype":"venue"
},
  "geometry": {"coordinates":[144.84816000000001,-37.830616],"type":"Point"}
}