{
  "type": "Feature",
  "properties": {
    "iso:country":"AU",
    "sg:address":"125 Comur St",
    "sg:city":"Yass",
    "sg:classifiers":[
        {
            "category":"Home & Garden",
            "subcategory":"Carpets & Floor Coverings",
            "type":"Retail Goods"
        }
    ],
    "sg:phone":"+61 2 6226 3655",
    "sg:postcode":"2582",
    "sg:province":"NSW",
    "wof:name":"Ron Firth Furnishings",
    "wof:placetype":"venue"
},
  "geometry": {"coordinates":[148.9115448,-34.842666626],"type":"Point"}
}