{
  "type": "Feature",
  "properties": {
    "addr:full":"24 Blackwood St Mitchelton QLD 4053",
    "addr:housenumber":"24",
    "addr:postcode":"4053",
    "addr:street":"Blackwood St",
    "iso:country":"AU",
    "sg:address":"24 Blackwood St",
    "sg:city":"Mitchelton",
    "sg:classifiers":[
        {
            "category":"Health Services",
            "subcategory":"Doctor",
            "type":"Services"
        }
    ],
    "sg:phone":"+61 7 3355 5555",
    "sg:postcode":"4053",
    "sg:province":"QLD",
    "sg:tags":[
        "medical",
        "practitioner"
    ],
    "wof:name":"Mitchelton Family Practice",
    "wof:placetype":"venue"
},
  "geometry": {"coordinates":[152.974075317,-27.4124450684],"type":"Point"}
}