{
  "type": "Feature",
  "properties": {
    "addr:full":"Unit 1 - 193a Lennox St Richmond VIC 3121",
    "addr:housenumber":"193a",
    "addr:postcode":"3121",
    "addr:street":"Lennox St",
    "iso:country":"AU",
    "sg:address":"Unit 1 - 193a Lennox St",
    "sg:city":"Richmond",
    "sg:classifiers":[
        {
            "category":"Health Services",
            "subcategory":"Doctor",
            "type":"Services"
        }
    ],
    "sg:phone":"+61 3 9427 0055",
    "sg:postcode":"3121",
    "sg:province":"VIC",
    "sg:tags":[
        "medical",
        "practitioner"
    ],
    "wof:name":"Marsh David G",
    "wof:placetype":"venue"
},
  "geometry": {"coordinates":[144.994537353,-37.8194770813],"type":"Point"}
}