{
  "type": "Feature",
  "properties": {
    "addr:full":"29 Falmouth St Somerset TAS 7322",
    "addr:housenumber":"29",
    "addr:postcode":"7322",
    "addr:street":"Falmouth St",
    "iso:country":"AU",
    "sg:address":"29 Falmouth St",
    "sg:city":"Somerset",
    "sg:classifiers":[
        {
            "category":"Retail",
            "subcategory":"Veterinary Services",
            "type":"Services"
        }
    ],
    "sg:phone":"+61 3 6435 2504",
    "sg:postcode":"7322",
    "sg:province":"TAS",
    "sg:tags":[
        "surgeon"
    ],
    "wof:name":"Town & Country Veterinary Service",
    "wof:placetype":"venue"
},
  "geometry": {"coordinates":[145.833496,-41.040668],"type":"Point"}
}