{
  "type": "Feature",
  "properties": {
    "addr:full":"40 Lockheed St Raby NSW 2566",
    "addr:housenumber":"40",
    "addr:postcode":"2566",
    "addr:street":"Lockheed St",
    "iso:country":"AU",
    "sg:address":"40 Lockheed St",
    "sg:city":"Raby",
    "sg:classifiers":[
        {
            "category":"Building & Trades",
            "subcategory":"Construction",
            "type":"Services"
        }
    ],
    "sg:phone":"+61 415 676 392",
    "sg:postcode":"2566",
    "sg:province":"NSW",
    "sg:tags":[
        "earth",
        "excavating",
        "moving",
        "contractor"
    ],
    "wof:name":"Bob's Ripper Tipper & Bobcat Hire",
    "wof:placetype":"venue"
},
  "geometry": {"coordinates":[150.82264709500001,-34.0269126892],"type":"Point"}
}