{
  "type": "Feature",
  "properties": {
    "addr:full":"105 Queens Pde Clifton Hill VIC 3068",
    "addr:housenumber":"105",
    "addr:postcode":"3068",
    "addr:street":"Queens Pde",
    "iso:country":"AU",
    "sg:address":"105 Queens Pde",
    "sg:city":"Clifton Hill",
    "sg:classifiers":[
        {
            "category":"Health Services",
            "subcategory":"Health Practitioner",
            "type":"Services"
        }
    ],
    "sg:phone":"+61 3 9489 1509",
    "sg:postcode":"3068",
    "sg:province":"VIC",
    "sg:tags":[
        "psychologist"
    ],
    "wof:name":"Best Psychology",
    "wof:placetype":"venue"
},
  "geometry": {"coordinates":[144.989746094,-37.7894744873],"type":"Point"}
}