{
  "type": "Feature",
  "properties": {
    "addr:full":"186 Fernleigh Rd Wagga Wagga NSW 2650",
    "addr:housenumber":"186",
    "addr:postcode":"2650",
    "addr:street":"Fernleigh Rd",
    "iso:country":"AU",
    "sg:address":"186 Fernleigh Rd",
    "sg:city":"Wagga Wagga",
    "sg:classifiers":[
        {
            "category":"Health Services",
            "subcategory":"Doctor",
            "type":"Services"
        }
    ],
    "sg:phone":"+61 2 6922 6144",
    "sg:postcode":"2650",
    "sg:province":"NSW",
    "sg:tags":[
        "medical",
        "practitioner"
    ],
    "wof:name":"Antoun Victor Dr",
    "wof:placetype":"venue"
},
  "geometry": {"coordinates":[147.34393310600001,-35.1307907104],"type":"Point"}
}