{
  "type": "Feature",
  "properties": {
    "iso:country":"AU",
    "sg:address":"83 Mount Barker Rd",
    "sg:city":"Stirling",
    "sg:classifiers":[
        {
            "category":"Health Services",
            "subcategory":"Chiropractor",
            "type":"Services"
        }
    ],
    "sg:phone":"+61 8 8370 9611",
    "sg:postcode":"5152",
    "sg:province":"SA",
    "wof:name":"Priest David A Dr",
    "wof:placetype":"venue"
},
  "geometry": {"coordinates":[138.72218322800001,-35.0080299377],"type":"Point"}
}