{
  "type": "Feature",
  "properties": {
    "addr:full":"PO Box 268 Bli Bli QLD 4560",
    "addr:postcode":"4560",
    "iso:country":"AU",
    "sg:address":"PO Box 268",
    "sg:city":"Bli Bli",
    "sg:classifiers":[
        {
            "category":"Professional",
            "subcategory":"Employment Agencies",
            "type":"Services"
        }
    ],
    "sg:phone":"+61 7 5475 4460",
    "sg:postcode":"4560",
    "sg:province":"QLD",
    "sg:tags":[
        "hire",
        "labour",
        "contractor"
    ],
    "wof:name":"JE H.R. Solutions",
    "wof:placetype":"venue"
},
  "geometry": {"coordinates":[152.98306274399999,-26.6161994934],"type":"Point"}
}