{
  "type": "Feature",
  "properties": {
    "iso:country":"AU",
    "sg:address":"381 Port Hacking Rd",
    "sg:city":"Caringbah",
    "sg:classifiers":[
        {
            "category":"Utilities",
            "subcategory":"Electric",
            "type":"Services"
        }
    ],
    "sg:phone":"+61 1800 191 040",
    "sg:postcode":"1495",
    "sg:province":"NSW",
    "sg:tags":[
        "electrical",
        "contractor"
    ],
    "wof:name":"A.Ace 24Hr Electricalprompt Efficient Inexpensive Domestic & Commercial Repairs",
    "wof:placetype":"venue"
},
  "geometry": {"coordinates":[151.123093,-34.045074],"type":"Point"}
}