{
  "type": "Feature",
  "properties": {
    "addr:full":"33 Yoogali St Merrylands NSW 2160",
    "addr:housenumber":"33",
    "addr:postcode":"2160",
    "addr:street":"Yoogali St",
    "iso:country":"AU",
    "sg:address":"33 Yoogali St",
    "sg:city":"Merrylands",
    "sg:classifiers":[
        {
            "category":"Building & Trades",
            "subcategory":"Construction",
            "type":"Services"
        }
    ],
    "sg:phone":"+61 2 9896 4714",
    "sg:postcode":"2160",
    "sg:province":"NSW",
    "sg:tags":[
        "joiner",
        "carpenter"
    ],
    "wof:name":"Baltasar Carpentry & Joinery",
    "wof:placetype":"venue"
},
  "geometry": {"coordinates":[150.964599609,-33.8304100037],"type":"Point"}
}