{
  "type": "Feature",
  "properties": {
    "addr:full":"467 Forest Rd Bexley NSW 2207",
    "addr:housenumber":"467",
    "addr:postcode":"2207",
    "addr:street":"Forest Rd",
    "iso:country":"AU",
    "sg:address":"467 Forest Rd",
    "sg:city":"Bexley",
    "sg:classifiers":[
        {
            "category":"Travel",
            "subcategory":"Hotels & Motels",
            "type":"Entertainment"
        }
    ],
    "sg:phone":"+61 2 9567 1284",
    "sg:postcode":"2207",
    "sg:province":"NSW",
    "sg:tags":[
        "pub"
    ],
    "wof:name":"Forest Inn Hotel",
    "wof:placetype":"venue"
},
  "geometry": {"coordinates":[151.12402299999999,-33.951904],"type":"Point"}
}