{
  "type": "Feature",
  "properties": {
    "iso:country":"AU",
    "sg:address":"24 Crofton St",
    "sg:city":"Benalla",
    "sg:classifiers":[
        {
            "category":"Utilities",
            "subcategory":"Water",
            "type":"Services"
        }
    ],
    "sg:phone":"+61 3 5762 1528",
    "sg:postcode":"3672",
    "sg:province":"VIC",
    "sg:tags":[
        "cartage"
    ],
    "wof:name":"Symes Water Cartage",
    "wof:placetype":"venue"
},
  "geometry": {"coordinates":[145.969055,-36.556873],"type":"Point"}
}