{
  "type": "Feature",
  "properties": {
    "addr:full":"14-16 Ropes Creek Rd Mt Druitt NSW 2770",
    "addr:housenumber":"14-16",
    "addr:postcode":"2770",
    "addr:street":"Ropes Creek Rd",
    "iso:country":"AU",
    "sg:address":"14-16 Ropes Creek Rd",
    "sg:city":"Mt Druitt",
    "sg:classifiers":[
        {
            "category":"Professional",
            "subcategory":"Computer Services",
            "type":"Services"
        }
    ],
    "sg:phone":"+61 2 9864 6044",
    "sg:postcode":"2770",
    "sg:province":"NSW",
    "sg:tags":[
        "consultant",
        "system"
    ],
    "wof:name":"Phillica Pty Ltd",
    "wof:placetype":"venue"
},
  "geometry": {"coordinates":[150.81376648,-33.7753868103],"type":"Point"}
}