{
  "type": "Feature",
  "properties": {
    "addr:full":"324 Harcourt St Teneriffe QLD 4005",
    "addr:housenumber":"324",
    "addr:postcode":"4005",
    "addr:street":"Harcourt St",
    "iso:country":"AU",
    "sg:address":"324 Harcourt St",
    "sg:city":"Teneriffe",
    "sg:classifiers":[
        {
            "category":"Real Estate",
            "subcategory":"Architect",
            "type":"Services"
        }
    ],
    "sg:phone":"+61 7 3254 1196",
    "sg:postcode":"4005",
    "sg:province":"QLD",
    "wof:name":"Shutter Leigh",
    "wof:placetype":"venue"
},
  "geometry": {"coordinates":[153.045852661,-27.4542636871],"type":"Point"}
}