{
  "type": "Feature",
  "properties": {
    "addr:full":"12 Union St Parramatta NSW 2150",
    "addr:housenumber":"12",
    "addr:postcode":"2150",
    "addr:street":"Union St",
    "iso:country":"AU",
    "sg:address":"12 Union St",
    "sg:city":"Parramatta",
    "sg:classifiers":[
        {
            "category":"Real Estate",
            "subcategory":"Architect",
            "type":"Services"
        }
    ],
    "sg:phone":"+61 2 9635 5211",
    "sg:postcode":"2150",
    "sg:province":"NSW",
    "wof:name":"Australian Consultant Architects P/L",
    "wof:placetype":"venue"
},
  "geometry": {"coordinates":[151.00161743199999,-33.8306274414],"type":"Point"}
}