{
  "type": "Feature",
  "properties": {
    "addr:full":"27 Adele Crs Bahrs Scrub QLD 4207",
    "addr:housenumber":"27",
    "addr:postcode":"4207",
    "addr:street":"Adele Crs",
    "iso:country":"AU",
    "sg:address":"27 Adele Crs",
    "sg:city":"Bahrs Scrub",
    "sg:classifiers":[
        {
            "category":"Home & Garden",
            "subcategory":"Hardware",
            "type":"Retail Goods"
        }
    ],
    "sg:phone":"+61 7 3804 1211",
    "sg:postcode":"4207",
    "sg:province":"QLD",
    "sg:tags":[
        "plumber",
        "supply"
    ],
    "wof:name":"Rock Top Marketing Pty Ltd",
    "wof:placetype":"venue"
},
  "geometry": {"coordinates":[153.18716430699999,-27.7437705994],"type":"Point"}
}