{
  "type": "Feature",
  "properties": {
    "addr:full":"2 Raleigh St Blakehurst NSW 2221",
    "addr:housenumber":"2",
    "addr:postcode":"2221",
    "addr:street":"Raleigh St",
    "iso:country":"AU",
    "sg:address":"2 Raleigh St",
    "sg:city":"Blakehurst",
    "sg:classifiers":[
        {
            "category":"Utilities",
            "subcategory":"Electric",
            "type":"Services"
        }
    ],
    "sg:phone":"+61 2 9547 1706",
    "sg:postcode":"2221",
    "sg:province":"NSW",
    "sg:tags":[
        "electrical",
        "contractor"
    ],
    "wof:name":"Mick Acimov",
    "wof:placetype":"venue"
},
  "geometry": {"coordinates":[151.113891602,-33.994178772],"type":"Point"}
}