{
  "type": "Feature",
  "properties": {
    "addr:full":"13- 15 Havelock St Beaufort VIC 3373",
    "addr:housenumber":"15",
    "addr:postcode":"3373",
    "addr:street":"Havelock St",
    "iso:country":"AU",
    "sg:address":"13- 15 Havelock St",
    "sg:city":"Beaufort",
    "sg:classifiers":[
        {
            "category":"Home & Garden",
            "subcategory":"Household Appliances",
            "type":"Retail Goods"
        }
    ],
    "sg:phone":"+61 3 5349 2400",
    "sg:postcode":"3373",
    "sg:province":"VIC",
    "sg:tags":[
        "equipment",
        "gas"
    ],
    "wof:name":"Beaufort Hardware",
    "wof:placetype":"venue"
},
  "geometry": {"coordinates":[143.38145446799999,-37.4298057556],"type":"Point"}
}