{
  "type": "Feature",
  "properties": {
    "addr:full":"31 Gravelpit Rd Darra QLD 4076",
    "addr:housenumber":"31",
    "addr:postcode":"4076",
    "addr:street":"Gravelpit Rd",
    "iso:country":"AU",
    "sg:address":"31 Gravelpit Rd",
    "sg:city":"Darra",
    "sg:classifiers":[
        {
            "category":"Shopping",
            "subcategory":"Computers & Home Electronics",
            "type":"Retail Goods"
        }
    ],
    "sg:phone":"+61 1300 363 066",
    "sg:postcode":"4076",
    "sg:province":"QLD",
    "sg:tags":[
        "equipment",
        "supply"
    ],
    "wof:name":"Australian Toner Cartridge",
    "wof:placetype":"venue"
},
  "geometry": {"coordinates":[152.943435669,-27.5629253387],"type":"Point"}
}