{
  "type": "Feature",
  "properties": {
    "addr:full":"90-92 Bell St Heidelberg Heights VIC 3081",
    "addr:housenumber":"90-92",
    "addr:postcode":"3081",
    "addr:street":"Bell St",
    "iso:country":"AU",
    "sg:address":"90-92 Bell St",
    "sg:city":"Heidelberg Heights",
    "sg:classifiers":[
        {
            "category":"Autos & Motor Vehicles",
            "subcategory":"Auto Supplies",
            "type":"Retail Goods"
        }
    ],
    "sg:phone":"+61 3 9459 3427",
    "sg:postcode":"3081",
    "sg:province":"VIC",
    "sg:tags":[
        "part",
        "cycles",
        "accessory"
    ],
    "wof:name":"Stafford Yamaha / Hyosung",
    "wof:placetype":"venue"
},
  "geometry": {"coordinates":[145.052856445,-37.7535629272],"type":"Point"}
}