{
  "type": "Feature",
  "properties": {
    "addr:full":"Cnr Monash Way & Georgina Pl Churchill VIC 3842",
    "addr:postcode":"3842",
    "addr:street":"Cnr Monash Way &;Pl",
    "iso:country":"AU",
    "sg:address":"Cnr Monash Way & Georgina Pl",
    "sg:city":"Churchill",
    "sg:classifiers":[
        {
            "category":"Autos & Motor Vehicles",
            "subcategory":"Fuel & Gas Station",
            "type":"Retail Goods"
        }
    ],
    "sg:phone":"+61 3 5122 3663",
    "sg:postcode":"3842",
    "sg:province":"VIC",
    "wof:name":"Shell Churchill",
    "wof:placetype":"venue"
},
  "geometry": {"coordinates":[146.419265747,-38.3148803711],"type":"Point"}
}