{
  "type": "Feature",
  "properties": {
    "addr:full":"24 Eileen Rd Clayton South VIC 3169",
    "addr:housenumber":"24",
    "addr:postcode":"3169",
    "addr:street":"Eileen Rd",
    "iso:country":"AU",
    "sg:address":"24 Eileen Rd",
    "sg:city":"Clayton South",
    "sg:classifiers":[
        {
            "category":"Retail",
            "subcategory":"Auto Repair",
            "type":"Services"
        }
    ],
    "sg:phone":"+61 3 9574 1900",
    "sg:postcode":"3169",
    "sg:province":"VIC",
    "sg:tags":[
        "camper-trailers",
        "caravan",
        "servicing"
    ],
    "wof:name":"Caravan Refrigeration Services",
    "wof:placetype":"venue"
},
  "geometry": {"coordinates":[145.13656616200001,-37.9509124756],"type":"Point"}
}