{
  "type": "Feature",
  "properties": {
    "addr:full":"PO Box 252 Kings Meadows TAS 7249",
    "addr:postcode":"7249",
    "iso:country":"AU",
    "sg:address":"PO Box 252",
    "sg:city":"Kings Meadows",
    "sg:classifiers":[
        {
            "category":"Taxi",
            "type":"Transportation"
        }
    ],
    "sg:phone":"+61 408 321 006",
    "sg:postcode":"7249",
    "sg:province":"TAS",
    "sg:tags":[
        "cab"
    ],
    "wof:name":"Country Cabs",
    "wof:placetype":"venue"
},
  "geometry": {"coordinates":[147.16050720199999,-41.4677696228],"type":"Point"}
}