{
  "type": "Feature",
  "properties": {
    "addr:full":"244 Forest Rd Hurstville NSW 2220",
    "addr:housenumber":"244",
    "addr:postcode":"2220",
    "addr:street":"Forest Rd",
    "iso:country":"AU",
    "sg:address":"244 Forest Rd",
    "sg:city":"Hurstville",
    "sg:classifiers":[
        {
            "category":"Banks & Credit Unions",
            "subcategory":"Bureau De Change",
            "type":"Services"
        }
    ],
    "sg:phone":"+61 1300 139 060",
    "sg:postcode":"2220",
    "sg:province":"NSW",
    "sg:tags":[
        "currency",
        "exchange",
        "foreign"
    ],
    "wof:name":"American Express Foreign Exchange Service",
    "wof:placetype":"venue"
},
  "geometry": {"coordinates":[151.10401916500001,-33.9673233032],"type":"Point"}
}