{
  "type": "Feature",
  "properties": {
    "addr:full":"Mount Ernest Crs Murwillumbah NSW 2484",
    "addr:postcode":"2484",
    "addr:street":"Ernest Crs",
    "iso:country":"AU",
    "sg:address":"Mount Ernest Crs",
    "sg:city":"Murwillumbah",
    "sg:classifiers":[
        {
            "category":"Building & Trades",
            "subcategory":"Construction",
            "type":"Services"
        }
    ],
    "sg:phone":"+61 404 479 262",
    "sg:postcode":"2484",
    "sg:province":"NSW",
    "sg:tags":[
        "bitumen",
        "paving",
        "asphalt"
    ],
    "wof:name":"Pacific Bitumen",
    "wof:placetype":"venue"
},
  "geometry": {"coordinates":[153.39169311500001,-28.3299503326],"type":"Point"}
}