{
  "type": "Feature",
  "properties": {
    "iso:country":"AU",
    "sg:address":"42 Oroya St",
    "sg:city":"Boulder",
    "sg:classifiers":[
        {
            "category":"Professional",
            "subcategory":"Employment Agencies",
            "type":"Services"
        }
    ],
    "sg:phone":"+61 8 9093 2784",
    "sg:postcode":"6432",
    "sg:province":"WA",
    "sg:tags":[
        "hire",
        "labour",
        "contractor"
    ],
    "wof:name":"Haynes Mechanical Pty Ltd",
    "wof:placetype":"venue"
},
  "geometry": {"coordinates":[121.495826721,-30.7917251587],"type":"Point"}
}