{
  "type": "Feature",
  "properties": {
    "addr:full":"Unit 3 Centrepoint Mall, 12 Denny Street Berri SA 5343",
    "addr:housenumber":"12",
    "addr:postcode":"5343",
    "addr:street":"Denny Street",
    "iso:country":"AU",
    "sg:address":"Unit 3 Centrepoint Mall, 12",
    "sg:city":"Denny Street Berri",
    "sg:classifiers":[
        {
            "category":"Wholesale",
            "subcategory":"Medical Equipment & Supplies",
            "type":"Manufacturing & Wholesale Goods"
        }
    ],
    "sg:phone":"+61 8 8582 2599",
    "sg:postcode":"5343",
    "sg:province":"SA",
    "sg:tags":[
        "aids",
        "hearing"
    ],
    "wof:name":"Riverland Hearing Solutions",
    "wof:placetype":"venue"
},
  "geometry": {"coordinates":[140.601119995,-34.2870101929],"type":"Point"}
}