{
  "type": "Feature",
  "properties": {
    "addr:full":"752 Malvern Rd Armadale VIC 3143",
    "addr:housenumber":"752",
    "addr:postcode":"3143",
    "addr:street":"Malvern Rd",
    "iso:country":"AU",
    "sg:address":"752 Malvern Rd",
    "sg:city":"Armadale",
    "sg:classifiers":[
        {
            "category":"Health Services",
            "subcategory":"Health Practitioner",
            "type":"Services"
        }
    ],
    "sg:phone":"+61 3 9824 8144",
    "sg:postcode":"3143",
    "sg:province":"VIC",
    "sg:tags":[
        "psychologist"
    ],
    "wof:name":"Dain Susan",
    "wof:placetype":"venue"
},
  "geometry": {"coordinates":[145.01368713400001,-37.8495635986],"type":"Point"}
}