{
  "type": "Feature",
  "properties": {
    "addr:full":"82- 84 Glen Innes Rd Armidale NSW 2350",
    "addr:housenumber":"84",
    "addr:postcode":"2350",
    "addr:street":"Glen Innes Rd",
    "iso:country":"AU",
    "sg:address":"82- 84 Glen Innes Rd",
    "sg:city":"Armidale",
    "sg:classifiers":[
        {
            "category":"Professional",
            "subcategory":"Testing Lab",
            "type":"Services"
        }
    ],
    "sg:phone":"+61 1800 663 379",
    "sg:postcode":"2350",
    "sg:province":"NSW",
    "sg:tags":[
        "soil",
        "investigation"
    ],
    "wof:name":"GroundTruth Pty Ltd",
    "wof:placetype":"venue"
},
  "geometry": {"coordinates":[151.67103576700001,-30.4916343689],"type":"Point"}
}