{
  "type": "Feature",
  "properties": {
    "addr:full":"7 Robe St Port Adelaide SA 5015",
    "addr:housenumber":"7",
    "addr:postcode":"5015",
    "addr:street":"Robe St",
    "iso:country":"AU",
    "sg:address":"7 Robe St",
    "sg:city":"Port Adelaide",
    "sg:classifiers":[
        {
            "category":"Food & Beverages",
            "subcategory":"Fruits & Vegetables",
            "type":"Retail Goods"
        }
    ],
    "sg:phone":"+61 8 8241 0601",
    "sg:postcode":"5015",
    "sg:province":"SA",
    "sg:tags":[
        "greengrocer",
        "fruiterer"
    ],
    "wof:name":"Farmer Joe's Fresh Food Barn",
    "wof:placetype":"venue"
},
  "geometry": {"coordinates":[138.50331115700001,-34.8444633484],"type":"Point"}
}