{
  "type": "Feature",
  "properties": {
    "iso:country":"AU",
    "sg:address":"11 Macbeth Gr",
    "sg:city":"St Clair",
    "sg:classifiers":[
        {
            "category":"Building & Trades",
            "subcategory":"Construction",
            "type":"Services"
        }
    ],
    "sg:phone":"+61 418 973 195",
    "sg:postcode":"2759",
    "sg:province":"NSW",
    "sg:tags":[
        "joiner",
        "carpenter"
    ],
    "wof:name":"M.J.H. Classic Constructions Pty Ltd",
    "wof:placetype":"venue"
},
  "geometry": {"coordinates":[150.78936767600001,-33.8037490845],"type":"Point"}
}