{
  "type": "Feature",
  "properties": {
    "addr:full":"Bird St Ayr QLD 4807",
    "addr:postcode":"4807",
    "addr:street":"Bird St",
    "iso:country":"AU",
    "sg:address":"Bird St",
    "sg:city":"Ayr",
    "sg:classifiers":[
        {
            "category":"Professional",
            "subcategory":"Engineering",
            "type":"Services"
        }
    ],
    "sg:phone":"+61 7 4783 5722",
    "sg:postcode":"4807",
    "sg:province":"QLD",
    "sg:tags":[
        "engineer"
    ],
    "wof:name":"Larry Hudson Engineering",
    "wof:placetype":"venue"
},
  "geometry": {"coordinates":[147.39169311500001,-19.5614547729],"type":"Point"}
}