{
  "type": "Feature",
  "properties": {
    "addr:full":"105 Bundall Rd Bundall QLD 4217",
    "addr:housenumber":"105",
    "addr:postcode":"4217",
    "addr:street":"Bundall Rd",
    "iso:country":"AU",
    "sg:address":"105 Bundall Rd",
    "sg:city":"Bundall",
    "sg:classifiers":[
        {
            "category":"Banks & Credit Unions",
            "subcategory":"Investment Brokerage",
            "type":"Services"
        }
    ],
    "sg:phone":"+61 7 5531 7400",
    "sg:postcode":"4217",
    "sg:province":"QLD",
    "sg:tags":[
        "finance",
        "broker"
    ],
    "wof:name":"Superior Finance Solutions",
    "wof:placetype":"venue"
},
  "geometry": {"coordinates":[153.413497925,-28.0046348572],"type":"Point"}
}