{
  "type": "Feature",
  "properties": {
    "iso:country":"AU",
    "sg:address":"3 Sharpe St",
    "sg:city":"Brassall",
    "sg:classifiers":[
        {
            "category":"Retail",
            "subcategory":"Driving School",
            "type":"Services"
        }
    ],
    "sg:phone":"+61 7 3201 6666",
    "sg:postcode":"4305",
    "sg:province":"QLD",
    "wof:name":"Ipswich Driving School",
    "wof:placetype":"venue"
},
  "geometry": {"coordinates":[152.74061584500001,-27.5982398987],"type":"Point"}
}