{
  "type": "Feature",
  "properties": {
    "addr:full":"120 Grant St Alexandra VIC 3714",
    "addr:housenumber":"120",
    "addr:postcode":"3714",
    "addr:street":"Grant St",
    "iso:country":"AU",
    "sg:address":"120 Grant St",
    "sg:city":"Alexandra",
    "sg:classifiers":[
        {
            "category":"Autos & Motor Vehicles",
            "subcategory":"Auto Supplies",
            "type":"Retail Goods"
        }
    ],
    "sg:phone":"+61 3 5772 1588",
    "sg:postcode":"3714",
    "sg:province":"VIC",
    "sg:tags":[
        "tyre"
    ],
    "wof:name":"Alexandra Tyre Service",
    "wof:placetype":"venue"
},
  "geometry": {"coordinates":[145.71061706500001,-37.1944770813],"type":"Point"}
}