{
  "type": "Feature",
  "properties": {
    "iso:country":"AU",
    "sg:address":"461 Brighton Rd",
    "sg:city":"Brighton",
    "sg:classifiers":[
        {
            "category":"Wholesale",
            "subcategory":"Apparel",
            "type":"Manufacturing & Wholesale Goods"
        }
    ],
    "sg:phone":"+61 8 8382 1003",
    "sg:postcode":"5048",
    "sg:province":"SA",
    "sg:tags":[
        "wholesaler",
        "mfrs",
        "dress"
    ],
    "wof:name":"Hirsch J R Pty Ltd",
    "wof:placetype":"venue"
},
  "geometry": {"coordinates":[138.522842,-35.017384],"type":"Point"}
}