{
  "type": "Feature",
  "properties": {
    "iso:country":"AU",
    "sg:address":"81 Glenferrie Rd",
    "sg:city":"Malvern",
    "sg:classifiers":[
        {
            "category":"Personal",
            "subcategory":"Nail Salon",
            "type":"Services"
        }
    ],
    "sg:phone":"+61 3 9509 0729",
    "sg:postcode":"3144",
    "sg:province":"VIC",
    "sg:tags":[
        "artificial"
    ],
    "wof:name":"Finesse Skin & Body Care",
    "wof:placetype":"venue"
},
  "geometry": {"coordinates":[145.028076172,-37.8628997803],"type":"Point"}
}