{
  "type": "Feature",
  "properties": {
    "iso:country":"AU",
    "sg:address":"32 Arkwright Crs",
    "sg:city":"Taree",
    "sg:classifiers":[
        {
            "category":"Manufacturing",
            "subcategory":"Tools & Machinery",
            "type":"Manufacturing & Wholesale Goods"
        }
    ],
    "sg:phone":"+61 2 6551 2635",
    "sg:postcode":"2430",
    "sg:province":"NSW",
    "sg:tags":[
        "toolmaker"
    ],
    "wof:name":"John Elliott Toolmaking & Machining",
    "wof:placetype":"venue"
},
  "geometry": {"coordinates":[152.46151699999999,-31.91313],"type":"Point"}
}