{
  "type": "Feature",
  "properties": {
    "iso:country":"AU",
    "sg:address":"183 Great North Rd",
    "sg:city":"Five Dock",
    "sg:classifiers":[
        {
            "category":"Food & Beverages",
            "subcategory":"Fruits & Vegetables",
            "type":"Retail Goods"
        }
    ],
    "sg:phone":"+61 2 9713 7108",
    "sg:postcode":"2046",
    "sg:province":"NSW",
    "sg:tags":[
        "greengrocer",
        "fruiterer"
    ],
    "wof:name":"Kangmar Holding Pty Ltd",
    "wof:placetype":"venue"
},
  "geometry": {"coordinates":[151.129974,-33.866447],"type":"Point"}
}