{
  "type": "Feature",
  "properties": {
    "addr:full":"35 Windemere Ave Northmead NSW 2152",
    "addr:housenumber":"35",
    "addr:postcode":"2152",
    "addr:street":"Windemere Ave",
    "iso:country":"AU",
    "sg:address":"35 Windemere Ave",
    "sg:city":"Northmead",
    "sg:classifiers":[
        {
            "category":"Professional",
            "subcategory":"Art Services",
            "type":"Services"
        }
    ],
    "sg:phone":"+61 2 9639 4102",
    "sg:postcode":"2152",
    "sg:province":"NSW",
    "sg:tags":[
        "interior",
        "designer"
    ],
    "wof:name":"Nielsen Constructions & Interiors",
    "wof:placetype":"venue"
},
  "geometry": {"coordinates":[151.004074097,-33.7781600952],"type":"Point"}
}