{
  "type": "Feature",
  "properties": {
    "addr:full":"229 Franklin St Melbourne VIC 3000",
    "addr:housenumber":"229",
    "addr:postcode":"3000",
    "addr:street":"Franklin St",
    "iso:country":"AU",
    "sg:address":"229 Franklin St",
    "sg:city":"Melbourne",
    "sg:classifiers":[
        {
            "category":"Home & Garden",
            "subcategory":"Carpets & Floor Coverings",
            "type":"Retail Goods"
        }
    ],
    "sg:phone":"+61 3 9329 8640",
    "sg:postcode":"3000",
    "sg:province":"VIC",
    "sg:tags":[
        "tile",
        "wall"
    ],
    "wof:name":"Rock Emporio",
    "wof:placetype":"venue"
},
  "geometry": {"coordinates":[144.957427978,-37.809513092],"type":"Point"}
}