{
  "type": "Feature",
  "properties": {
    "addr:full":"Factory 4/ 10 Peninsula Blv Seaford VIC 3198",
    "addr:housenumber":"/ 10",
    "addr:postcode":"3198",
    "addr:street":"Peninsula Blv",
    "iso:country":"AU",
    "sg:address":"Factory 4/ 10 Peninsula Blv",
    "sg:city":"Seaford",
    "sg:classifiers":[
        {
            "category":"Retail",
            "subcategory":"Auto Repair",
            "type":"Services"
        }
    ],
    "sg:phone":"+61 3 9785 3987",
    "sg:postcode":"3198",
    "sg:province":"VIC",
    "sg:tags":[
        "testing",
        "inspection",
        "motor",
        "vehicle"
    ],
    "wof:name":"Seaford A-Z Automotive Repairs",
    "wof:placetype":"venue"
},
  "geometry": {"coordinates":[145.140014648,-38.1147384644],"type":"Point"}
}