{
  "type": "Feature",
  "properties": {
    "addr:full":"PO Box 2106 Hobart TAS 7001",
    "addr:postcode":"7001",
    "iso:country":"AU",
    "sg:address":"PO Box 2106",
    "sg:city":"Hobart",
    "sg:classifiers":[
        {
            "category":"Personal",
            "type":"Services"
        }
    ],
    "sg:phone":"+61 403 158 094",
    "sg:postcode":"7001",
    "sg:province":"TAS",
    "sg:tags":[
        "gift"
    ],
    "wof:name":"Tasmanian Gourmet Gifts.",
    "wof:placetype":"venue"
},
  "geometry": {"coordinates":[147.51083374000001,-42.8352508545],"type":"Point"}
}