{
  "type": "Feature",
  "properties": {
    "addr:full":"28 Arafura Ave Loganholme QLD 4129",
    "addr:housenumber":"28",
    "addr:postcode":"4129",
    "addr:street":"Arafura Ave",
    "iso:country":"AU",
    "sg:address":"28 Arafura Ave",
    "sg:city":"Loganholme",
    "sg:classifiers":[
        {
            "category":"Professional",
            "subcategory":"Computer Services",
            "type":"Services"
        }
    ],
    "sg:phone":"+61 7 3209 8031",
    "sg:postcode":"4129",
    "sg:province":"QLD",
    "sg:tags":[
        "training"
    ],
    "wof:name":"Mobile Learning Centre",
    "wof:placetype":"venue"
},
  "geometry": {"coordinates":[153.18281555199999,-27.6676826477],"type":"Point"}
}