{
  "type": "Feature",
  "properties": {
    "addr:full":"91 Maitland St Narrabri NSW 2390",
    "addr:housenumber":"91",
    "addr:postcode":"2390",
    "addr:street":"Maitland St",
    "iso:country":"AU",
    "sg:address":"91 Maitland St",
    "sg:city":"Narrabri",
    "sg:classifiers":[
        {
            "category":"Personal",
            "subcategory":"Beauty Salon",
            "type":"Services"
        }
    ],
    "sg:phone":"+61 2 6792 5022",
    "sg:postcode":"2390",
    "sg:province":"NSW",
    "sg:tags":[
        "hairdresser"
    ],
    "wof:name":"Exclusive Image Hair Studio",
    "wof:placetype":"venue"
},
  "geometry": {"coordinates":[149.78137207,-30.3219146729],"type":"Point"}
}