{
  "type": "Feature",
  "properties": {
    "addr:full":"PO Box 836 Campsie NSW 2194",
    "addr:postcode":"2194",
    "iso:country":"AU",
    "sg:address":"PO Box 836",
    "sg:city":"Campsie",
    "sg:classifiers":[
        {
            "category":"Home & Garden",
            "subcategory":"Carpets & Floor Coverings",
            "type":"Retail Goods"
        }
    ],
    "sg:phone":"+61 410 639 949",
    "sg:postcode":"2194",
    "sg:province":"NSW",
    "sg:tags":[
        "tile",
        "wall",
        "layer"
    ],
    "wof:name":"A.M.I. Tiling",
    "wof:placetype":"venue"
},
  "geometry": {"coordinates":[151.103455,-33.914371],"type":"Point"}
}