{
  "type": "Feature",
  "properties": {
    "iso:country":"AU",
    "sg:address":"88 Power St",
    "sg:city":"Baralaba",
    "sg:classifiers":[
        {
            "category":"Home & Garden",
            "subcategory":"Building Materials",
            "type":"Retail Goods"
        }
    ],
    "sg:phone":"+61 7 4998 1452",
    "sg:postcode":"4702",
    "sg:province":"QLD",
    "sg:tags":[
        "concrete",
        "gutter",
        "kerb"
    ],
    "wof:name":"Kwik Kerb",
    "wof:placetype":"venue"
},
  "geometry": {"coordinates":[149.811477661,-24.177947998],"type":"Point"}
}