{
  "type": "Feature",
  "properties": {
    "iso:country":"AU",
    "sg:address":"14- 24 Pearl St",
    "sg:city":"Northcote",
    "sg:classifiers":[
        {
            "category":"Travel",
            "subcategory":"Hostel",
            "type":"Entertainment"
        }
    ],
    "sg:phone":"+61 3 9488 2588",
    "sg:postcode":"3070",
    "sg:province":"VIC",
    "sg:tags":[
        "home"
    ],
    "wof:name":"Ruckers Hill Aged Care Facility",
    "wof:placetype":"venue"
},
  "geometry": {"coordinates":[144.997742,-37.777973],"type":"Point"}
}