{
  "type": "Feature",
  "properties": {
    "iso:country":"AU",
    "sg:address":"35 Rochdale Drv",
    "sg:city":"Burwood East",
    "sg:classifiers":[
        {
            "category":"Professional",
            "type":"Services"
        }
    ],
    "sg:phone":"+61 412 551 278",
    "sg:postcode":"3151",
    "sg:province":"VIC",
    "sg:tags":[
        "spray",
        "painting"
    ],
    "wof:name":"Wizard Auto Finish",
    "wof:placetype":"venue"
},
  "geometry": {"coordinates":[145.139602661,-37.8476448059],"type":"Point"}
}