{
  "type": "Feature",
  "properties": {
    "addr:full":"St Clair NSW 2759",
    "addr:postcode":"2759",
    "iso:country":"AU",
    "sg:address":"St",
    "sg:city":"Clair",
    "sg:classifiers":[
        {
            "category":"Building & Trades",
            "subcategory":"Cleaning & Sanitation",
            "type":"Services"
        }
    ],
    "sg:phone":"+61 419 465 091",
    "sg:postcode":"2759",
    "sg:province":"NSW",
    "sg:tags":[
        "sweeping",
        "machine"
    ],
    "wof:name":"Dashas Sweeper Hire",
    "wof:placetype":"venue"
},
  "geometry": {"coordinates":[150.77980041500001,-33.7973594666],"type":"Point"}
}