{
  "type": "Feature",
  "properties": {
    "addr:full":"14 Oberon Crt Dynnyrne TAS 7005",
    "addr:housenumber":"14",
    "addr:postcode":"7005",
    "addr:street":"Oberon Crt",
    "iso:country":"AU",
    "sg:address":"14 Oberon Crt",
    "sg:city":"Dynnyrne",
    "sg:classifiers":[
        {
            "category":"Real Estate",
            "subcategory":"Architect",
            "type":"Services"
        }
    ],
    "sg:phone":"+61 402 826 589",
    "sg:postcode":"7005",
    "sg:province":"TAS",
    "wof:name":"Tarros Antonio",
    "wof:placetype":"venue"
},
  "geometry": {"coordinates":[147.316116333,-42.9069900513],"type":"Point"}
}