{
  "type": "Feature",
  "properties": {
    "iso:country":"AU",
    "sg:address":"22 Egerton St",
    "sg:city":"Silverwater",
    "sg:classifiers":[
        {
            "category":"Shopping",
            "subcategory":"Crafts & Fabrics",
            "type":"Retail Goods"
        }
    ],
    "sg:phone":"+61 2 9648 3138",
    "sg:postcode":"2128",
    "sg:province":"NSW",
    "sg:tags":[
        "bonding",
        "coating"
    ],
    "wof:name":"Textile Bonding Services",
    "wof:placetype":"venue"
},
  "geometry": {"coordinates":[151.05137634299999,-33.8366775513],"type":"Point"}
}