{
  "type": "Feature",
  "properties": {
    "iso:country":"AU",
    "sg:address":"209 Pallas St",
    "sg:city":"Maryborough",
    "sg:classifiers":[
        {
            "category":"Personal",
            "subcategory":"Beauty Salon",
            "type":"Services"
        }
    ],
    "sg:phone":"+61 7 4122 4841",
    "sg:postcode":"4650",
    "sg:province":"QLD",
    "sg:tags":[
        "hairdresser"
    ],
    "wof:name":"Barber Shop The",
    "wof:placetype":"venue"
},
  "geometry": {"coordinates":[152.699966,-25.524479],"type":"Point"}
}