{
  "type": "Feature",
  "properties": {
    "addr:full":"198 Balaclava Rd Caulfield VIC 3162",
    "addr:housenumber":"198",
    "addr:postcode":"3162",
    "addr:street":"Balaclava Rd",
    "iso:country":"AU",
    "sg:address":"198 Balaclava Rd",
    "sg:city":"Caulfield",
    "sg:classifiers":[
        {
            "category":"Real Estate",
            "subcategory":"Real Estate Agent",
            "type":"Services"
        }
    ],
    "sg:phone":"+61 3 9576 0993",
    "sg:postcode":"3162",
    "sg:province":"VIC",
    "wof:name":"Raine & Horne",
    "wof:placetype":"venue"
},
  "geometry": {"coordinates":[145.022613525,-37.872253418],"type":"Point"}
}