{
  "type": "Feature",
  "properties": {
    "iso:country":"AU",
    "sg:address":"PO Box 1189",
    "sg:city":"Bibra Lake",
    "sg:classifiers":[
        {
            "category":"Professional",
            "subcategory":"Printing & Photocopies",
            "type":"Services"
        }
    ],
    "sg:phone":"+61 8 9434 1501",
    "sg:postcode":"6163",
    "sg:province":"WA",
    "sg:tags":[
        "embroidery"
    ],
    "wof:name":"EmbroiderTech",
    "wof:placetype":"venue"
},
  "geometry": {"coordinates":[115.81240099999999,-32.08992],"type":"Point"}
}