{
  "type": "Feature",
  "properties": {
    "addr:full":"45 Toolooa St South Gladstone QLD 4680",
    "addr:housenumber":"45",
    "addr:postcode":"4680",
    "addr:street":"Toolooa St South",
    "iso:country":"AU",
    "sg:address":"45 Toolooa St",
    "sg:city":"South Gladstone",
    "sg:classifiers":[
        {
            "category":"Home & Garden",
            "subcategory":"Building Materials",
            "type":"Retail Goods"
        }
    ],
    "sg:phone":"+61 7 4972 9993",
    "sg:postcode":"4680",
    "sg:province":"QLD",
    "sg:tags":[
        "anti-corrosive",
        "composition",
        "flooring"
    ],
    "wof:name":"Janamist Seamles Flooring",
    "wof:placetype":"venue"
},
  "geometry": {"coordinates":[151.269699097,-23.8583660126],"type":"Point"}
}