{
  "type": "Feature",
  "properties": {
    "iso:country":"AU",
    "sg:address":"50 a&b Darld St",
    "sg:city":"Horsham",
    "sg:classifiers":[
        {
            "category":"Food & Beverages",
            "subcategory":"Bakery",
            "type":"Retail Goods"
        }
    ],
    "sg:phone":"+61 3 5381 2115",
    "sg:postcode":"3400",
    "sg:province":"VIC",
    "sg:tags":[
        "baker"
    ],
    "wof:name":"Bakers Delight",
    "wof:placetype":"venue"
},
  "geometry": {"coordinates":[142.19619750999999,-36.7172393799],"type":"Point"}
}