{
  "type": "Feature",
  "properties": {
    "iso:country":"AU",
    "sg:address":"Cnr Western Hwy & Horsham Rd",
    "sg:city":"Dimboola",
    "sg:classifiers":[
        {
            "category":"Farming",
            "subcategory":"Farm & Veterinary Services",
            "type":"Manufacturing & Wholesale Goods"
        }
    ],
    "sg:phone":"+61 3 5389 1727",
    "sg:postcode":"3414",
    "sg:province":"VIC",
    "sg:tags":[
        "drying",
        "seed",
        "cleaning",
        "grading"
    ],
    "wof:name":"Frahn Grain Cleaning & Bagging",
    "wof:placetype":"venue"
},
  "geometry": {"coordinates":[142.04296875,-36.4428787231],"type":"Point"}
}