{
  "type": "Feature",
  "properties": {
    "addr:full":"3 Hawthorn Ave Sunshine VIC 3020",
    "addr:housenumber":"3",
    "addr:postcode":"3020",
    "addr:street":"Hawthorn Ave",
    "iso:country":"AU",
    "sg:address":"3 Hawthorn Ave",
    "sg:city":"Sunshine",
    "sg:classifiers":[
        {
            "category":"Shopping",
            "type":"Retail Goods"
        }
    ],
    "sg:phone":"+61 3 9310 2666",
    "sg:postcode":"3020",
    "sg:province":"VIC",
    "sg:tags":[
        "product",
        "plastic"
    ],
    "wof:name":"H C & D C Trading Pty Ltd",
    "wof:placetype":"venue"
},
  "geometry": {"coordinates":[144.83616599999999,-37.762535],"type":"Point"}
}