{
  "type": "Feature",
  "properties": {
    "addr:full":"35 Havelock St West Perth WA 6005",
    "addr:housenumber":"35",
    "addr:postcode":"6005",
    "addr:street":"Havelock St",
    "iso:country":"AU",
    "sg:address":"35 Havelock St",
    "sg:city":"West Perth",
    "sg:classifiers":[
        {
            "category":"Organizations",
            "subcategory":"Professional Association",
            "type":"Services"
        }
    ],
    "sg:phone":"+61 8 9322 5133",
    "sg:postcode":"6005",
    "sg:province":"WA",
    "sg:tags":[
        "organisation",
        "business"
    ],
    "wof:name":"Master Builders Association Of WA",
    "wof:placetype":"venue"
},
  "geometry": {"coordinates":[115.84487915,-31.9478645325],"type":"Point"}
}