{
  "type": "Feature",
  "properties": {
    "addr:full":"8 Muirfield Ave Success WA 6164",
    "addr:housenumber":"8",
    "addr:postcode":"6164",
    "addr:street":"Muirfield Ave",
    "iso:country":"AU",
    "sg:address":"8 Muirfield Ave",
    "sg:city":"Success",
    "sg:classifiers":[
        {
            "category":"Building & Trades",
            "subcategory":"Landscaping Services",
            "type":"Services"
        }
    ],
    "sg:phone":"+61 8 9498 6005",
    "sg:postcode":"6164",
    "sg:province":"WA",
    "sg:tags":[
        "designer",
        "landscape",
        "contractor"
    ],
    "wof:name":"Landscape Success",
    "wof:placetype":"venue"
},
  "geometry": {"coordinates":[115.846458,-32.144344],"type":"Point"}
}