{
  "type": "Feature",
  "properties": {
    "iso:country":"AU",
    "sg:address":"201 Commercial St",
    "sg:city":"(West) Mt Gambier",
    "sg:classifiers":[
        {
            "category":"Industrial Area",
            "type":"Public Place"
        }
    ],
    "sg:phone":"+61 8 8725 9244",
    "sg:postcode":"5290",
    "sg:province":"SA",
    "sg:tags":[
        "protective",
        "clothing"
    ],
    "wof:name":"Lawrence & Hanson",
    "wof:placetype":"venue"
},
  "geometry": {"coordinates":[140.79595900000001,-37.833141],"type":"Point"}
}