{
  "type": "Feature",
  "properties": {
    "iso:country":"AU",
    "sg:address":"Shop 1 Tramway Arc",
    "sg:city":"Rockdale",
    "sg:classifiers":[
        {
            "category":"Autos & Motor Vehicles",
            "subcategory":"Automobile Sales",
            "type":"Retail Goods"
        }
    ],
    "sg:phone":"+61 2 9556 1699",
    "sg:postcode":"2216",
    "sg:province":"NSW",
    "sg:tags":[
        "car",
        "used"
    ],
    "wof:name":"A Rockdale Locksmith Late Model Cars Used & Programmed",
    "wof:placetype":"venue"
},
  "geometry": {"coordinates":[151.137161,-33.952553],"type":"Point"}
}