{
  "type": "Feature",
  "properties": {
    "iso:country":"AU",
    "sg:address":"199-215 Englands Rd",
    "sg:city":"Boambee",
    "sg:classifiers":[
        {
            "category":"Farming",
            "subcategory":"Nursery",
            "type":"Manufacturing & Wholesale Goods"
        }
    ],
    "sg:phone":"+61 2 6651 3955",
    "sg:postcode":"2450",
    "sg:province":"NSW",
    "wof:name":"Big Boambee Palms",
    "wof:placetype":"venue"
},
  "geometry": {"coordinates":[153.07974200000001,-30.316786],"type":"Point"}
}