{
  "type": "Feature",
  "properties": {
    "addr:full":"PO Box 51 Glenbrook NSW 2773",
    "addr:postcode":"2773",
    "iso:country":"AU",
    "sg:address":"PO Box 51",
    "sg:city":"Glenbrook",
    "sg:classifiers":[
        {
            "category":"Social Services",
            "subcategory":"Child Care",
            "type":"Services"
        }
    ],
    "sg:phone":"+61 2 4739 1042",
    "sg:postcode":"2773",
    "sg:province":"NSW",
    "wof:name":"Hawkesbury SUPS",
    "wof:placetype":"venue"
},
  "geometry": {"coordinates":[150.621170044,-33.7665481567],"type":"Point"}
}