{
  "type": "Feature",
  "properties": {
    "addr:full":"231 Upper Dawson Rd Rockhampton QLD 4700",
    "addr:housenumber":"231",
    "addr:postcode":"4700",
    "addr:street":"Upper Dawson Rd",
    "iso:country":"AU",
    "sg:address":"231 Upper Dawson Rd",
    "sg:city":"Rockhampton",
    "sg:classifiers":[
        {
            "category":"Building & Trades",
            "subcategory":"Pest Control",
            "type":"Services"
        }
    ],
    "sg:phone":"+61 1800 687 565",
    "sg:postcode":"4700",
    "sg:province":"QLD",
    "wof:name":"Natraspray Pest Control",
    "wof:placetype":"venue"
},
  "geometry": {"coordinates":[150.500442505,-23.404340744],"type":"Point"}
}