{
  "type": "Feature",
  "properties": {
    "addr:full":"Shp2/ 35 Nicholson St Bairnsdale VIC 3875",
    "addr:housenumber":"35",
    "addr:postcode":"3875",
    "addr:street":"Nicholson St",
    "iso:country":"AU",
    "sg:address":"Shp2/ 35 Nicholson St",
    "sg:city":"Bairnsdale",
    "sg:classifiers":[
        {
            "category":"Food & Beverages",
            "subcategory":"Specialty",
            "type":"Retail Goods"
        }
    ],
    "sg:phone":"+61 3 5152 3611",
    "sg:postcode":"3875",
    "sg:province":"VIC",
    "sg:tags":[
        "product",
        "health"
    ],
    "wof:name":"Gippsland Gluten Free Foods",
    "wof:placetype":"venue"
},
  "geometry": {"coordinates":[147.62979125999999,-37.824798584],"type":"Point"}
}