{
  "type": "Feature",
  "properties": {
    "addr:full":"Carolans Arcade, 114 Currie St Nambour QLD 4560",
    "addr:housenumber":"114",
    "addr:postcode":"4560",
    "addr:street":"Currie St",
    "iso:country":"AU",
    "sg:address":"Carolans Arcade, 114 Currie St",
    "sg:city":"Nambour",
    "sg:classifiers":[
        {
            "category":"Shopping",
            "type":"Retail Goods"
        }
    ],
    "sg:phone":"+61 7 5441 1448",
    "sg:postcode":"4560",
    "sg:province":"QLD",
    "sg:tags":[
        "new age",
        "product"
    ],
    "wof:name":"Spellmakers Beads & Crystals",
    "wof:placetype":"venue"
},
  "geometry": {"coordinates":[152.959060669,-26.6275787354],"type":"Point"}
}