{
  "type": "Feature",
  "properties": {
    "addr:full":"Thozet Rd Mt Archer QLD 4514",
    "addr:postcode":"4514",
    "addr:street":"Thozet Rd",
    "iso:country":"AU",
    "sg:address":"Thozet Rd",
    "sg:city":"Mt Archer",
    "sg:classifiers":[
        {
            "category":"Education",
            "subcategory":"School",
            "type":"Public Place"
        }
    ],
    "sg:phone":"+61 7 4923 5222",
    "sg:postcode":"4514",
    "sg:province":"QLD",
    "sg:tags":[
        "state",
        "except",
        "nsw"
    ],
    "wof:name":"Mt Archer Special Education Unit",
    "wof:placetype":"venue"
},
  "geometry": {"coordinates":[152.662048,-26.97159],"type":"Point"}
}