{
  "type": "Feature",
  "properties": {
    "addr:full":"Suite 14, 1st Floor 27 Evans St Maroochydore QLD 4558",
    "addr:housenumber":"27",
    "addr:postcode":"4558",
    "addr:street":"Evans St",
    "iso:country":"AU",
    "sg:address":"Suite 14, 1st Floor 27 Evans St",
    "sg:city":"Maroochydore",
    "sg:classifiers":[
        {
            "category":"Banks & Credit Unions",
            "subcategory":"Financial Services",
            "type":"Services"
        }
    ],
    "sg:phone":"+61 7 5479 5826",
    "sg:postcode":"4558",
    "sg:province":"QLD",
    "sg:tags":[
        "loan",
        "finance",
        "mortgage"
    ],
    "wof:name":"Yes Total Finance Group P/L",
    "wof:placetype":"venue"
},
  "geometry": {"coordinates":[153.08216857900001,-26.6554450989],"type":"Point"}
}