{
  "type": "Feature",
  "properties": {
    "iso:country":"AU",
    "sg:address":"4b Eaton Pl",
    "sg:city":"Geraldton",
    "sg:classifiers":[
        {
            "category":"Professional",
            "subcategory":"Engineering",
            "type":"Services"
        }
    ],
    "sg:phone":"+61 8 9965 4243",
    "sg:postcode":"6530",
    "sg:province":"WA",
    "sg:tags":[
        "engineer"
    ],
    "wof:name":"Encore (WA) Pty Ltd",
    "wof:placetype":"venue"
},
  "geometry": {"coordinates":[114.626457214,-28.7715587616],"type":"Point"}
}