{
  "type": "Feature",
  "properties": {
    "addr:full":"332 Darling St Balmain NSW 2041",
    "addr:housenumber":"332",
    "addr:postcode":"2041",
    "addr:street":"Darling St",
    "iso:country":"AU",
    "sg:address":"332 Darling St",
    "sg:city":"Balmain",
    "sg:classifiers":[
        {
            "category":"Professional",
            "subcategory":"Employment Agencies",
            "type":"Services"
        }
    ],
    "sg:phone":"+61 2 9555 4321",
    "sg:postcode":"2041",
    "sg:province":"NSW",
    "sg:tags":[
        "provider",
        "internet"
    ],
    "wof:name":"Balmain.com",
    "wof:placetype":"venue"
},
  "geometry": {"coordinates":[151.17936700000001,-33.856861],"type":"Point"}
}