{
  "type": "Feature",
  "properties": {
    "addr:full":"Fyansford Manor Hamilton Hwy Fyansford VIC 3221",
    "addr:postcode":"3221",
    "addr:street":"Hamilton Hwy",
    "iso:country":"AU",
    "sg:address":"Fyansford Manor Hamilton Hwy",
    "sg:city":"Fyansford",
    "sg:classifiers":[
        {
            "category":"Building & Trades",
            "subcategory":"Equipment Rental",
            "type":"Services"
        }
    ],
    "sg:phone":"+61 419 370 310",
    "sg:postcode":"3221",
    "sg:province":"VIC",
    "sg:tags":[
        "demolition",
        "contractor"
    ],
    "wof:name":"A. 1 Stop Demolition & Recycling",
    "wof:placetype":"venue"
},
  "geometry": {"coordinates":[144.30998199999999,-38.141628],"type":"Point"}
}