{
  "type": "Feature",
  "properties": {
    "addr:full":"299 Cambridge Rd Mornington TAS 7018",
    "addr:housenumber":"299",
    "addr:postcode":"7018",
    "addr:street":"Cambridge Rd",
    "iso:country":"AU",
    "sg:address":"299 Cambridge Rd",
    "sg:city":"Mornington",
    "sg:classifiers":[
        {
            "category":"Banks & Credit Unions",
            "subcategory":"Investment Brokerage",
            "type":"Services"
        }
    ],
    "sg:phone":"+61 3 6244 4496",
    "sg:postcode":"7018",
    "sg:province":"TAS",
    "sg:tags":[
        "equipment",
        "spray",
        "painting",
        "supply"
    ],
    "wof:name":"3D Paint Stores",
    "wof:placetype":"venue"
},
  "geometry": {"coordinates":[147.391311645,-42.8576278687],"type":"Point"}
}