{
  "type": "Feature",
  "properties": {
    "iso:country":"AU",
    "sg:address":"3/ 77 Jardine St",
    "sg:city":"Fairy Meadow",
    "sg:classifiers":[
        {
            "category":"Home & Garden",
            "subcategory":"Carpets & Floor Coverings",
            "type":"Retail Goods"
        }
    ],
    "sg:phone":"+61 2 4285 4551",
    "sg:postcode":"2519",
    "sg:province":"NSW",
    "wof:name":"B & D Carpets Galore Pty. Ltd.",
    "wof:placetype":"venue"
},
  "geometry": {"coordinates":[150.89386,-34.387852],"type":"Point"}
}