{
  "type": "Feature",
  "properties": {
    "addr:full":"Markwell St Kingaroy QLD 4610",
    "addr:postcode":"4610",
    "addr:street":"Markwell St",
    "iso:country":"AU",
    "sg:address":"Markwell St",
    "sg:city":"Kingaroy",
    "sg:classifiers":[
        {
            "category":"Education",
            "subcategory":"School",
            "type":"Public Place"
        }
    ],
    "sg:phone":"+61 7 4162 1825",
    "sg:postcode":"4610",
    "sg:province":"QLD",
    "sg:tags":[
        "state",
        "except",
        "nsw"
    ],
    "wof:name":"Kingaroy Preschool (Unit 1)",
    "wof:placetype":"venue"
},
  "geometry": {"coordinates":[151.83680725100001,-26.5424213409],"type":"Point"}
}