{
  "type": "Feature",
  "properties": {
    "iso:country":"AU",
    "sg:address":"25 Trade Winds Drv",
    "sg:city":"Safety Bay",
    "sg:classifiers":[
        {
            "category":"Health Services",
            "subcategory":"Health Practitioner",
            "type":"Services"
        }
    ],
    "sg:phone":"+61 8 9592 1613",
    "sg:postcode":"6169",
    "sg:province":"WA",
    "sg:tags":[
        "physiotherapist"
    ],
    "wof:name":"Heath Ben",
    "wof:placetype":"venue"
},
  "geometry": {"coordinates":[115.74166099999999,-32.307812],"type":"Point"}
}