{
  "type": "Feature",
  "properties": {
    "addr:full":"1 - 5 Anzac Ave Smeaton Grange NSW 2567",
    "addr:housenumber":"5",
    "addr:postcode":"2567",
    "addr:street":"Anzac Ave",
    "iso:country":"AU",
    "sg:address":"1 - 5 Anzac Ave",
    "sg:city":"Smeaton Grange",
    "sg:phone":"+61 1800 041 111",
    "sg:postcode":"2567",
    "sg:province":"NSW",
    "wof:name":"Sydney Water Tanks",
    "wof:placetype":"venue"
},
  "geometry": {"coordinates":[150.754394531,-34.0412330627],"type":"Point"}
}