{
  "type": "Feature",
  "properties": {
    "addr:full":"622 Hodge St Albury NSW 2640",
    "addr:housenumber":"622",
    "addr:postcode":"2640",
    "addr:street":"Hodge St",
    "iso:country":"AU",
    "sg:address":"622 Hodge St",
    "sg:city":"Albury",
    "sg:classifiers":[
        {
            "category":"Building & Trades",
            "subcategory":"Construction",
            "type":"Services"
        }
    ],
    "sg:phone":"+61 2 6025 2074",
    "sg:postcode":"2640",
    "sg:province":"NSW",
    "sg:tags":[
        "contractor"
    ],
    "wof:name":"Symmons J V & V T",
    "wof:placetype":"venue"
},
  "geometry": {"coordinates":[146.91438293499999,-36.0634651184],"type":"Point"}
}