{
  "type": "Feature",
  "properties": {
    "iso:country":"AU",
    "sg:address":"1260 Hay St",
    "sg:city":"West Perth",
    "sg:classifiers":[
        {
            "category":"Health Services",
            "subcategory":"Dentist",
            "type":"Services"
        }
    ],
    "sg:phone":"+61 8 9324 2390",
    "sg:postcode":"6005",
    "sg:province":"WA",
    "wof:name":"Hansen Mark G",
    "wof:placetype":"venue"
},
  "geometry": {"coordinates":[115.840118408,-31.94789505],"type":"Point"}
}