{
  "type": "Feature",
  "properties": {
    "iso:country":"AU",
    "sg:address":"Level 6 4",
    "sg:city":"Riverside Quay Southbank Melbourne",
    "sg:classifiers":[
        {
            "category":"Banks & Credit Unions",
            "subcategory":"Financial Services",
            "type":"Services"
        }
    ],
    "sg:phone":"+61 1300 650 161",
    "sg:postcode":"3004",
    "sg:province":"VIC",
    "sg:tags":[
        "annuity",
        "rollover",
        "superannuation",
        "consultant"
    ],
    "wof:name":"Emergency Services Superannuation Scheme",
    "wof:placetype":"venue"
},
  "geometry": {"coordinates":[144.963256836,-37.8214607239],"type":"Point"}
}