{
  "type": "Feature",
  "properties": {
    "iso:country":"AU",
    "sg:address":"PO Box 283",
    "sg:city":"Cooroy",
    "sg:classifiers":[
        {
            "category":"Building & Trades",
            "subcategory":"Pest Control",
            "type":"Services"
        }
    ],
    "sg:phone":"+61 7 5485 2472",
    "sg:postcode":"4563",
    "sg:province":"QLD",
    "wof:name":"Cooroy Pest Control",
    "wof:placetype":"venue"
},
  "geometry": {"coordinates":[152.91003418,-26.419549942],"type":"Point"}
}