{
  "type": "Feature",
  "properties": {
    "addr:full":"PO Box 63 Mt Kuring-gai NSW 2080",
    "addr:postcode":"2080",
    "iso:country":"AU",
    "sg:address":"PO Box 63",
    "sg:city":"Mt Kuring-gai",
    "sg:classifiers":[
        {
            "category":"Utilities",
            "subcategory":"Refuse",
            "type":"Services"
        }
    ],
    "sg:phone":"+61 407 908 935",
    "sg:postcode":"2080",
    "sg:province":"NSW",
    "sg:tags":[
        "remover",
        "rubbish"
    ],
    "wof:name":"Skip To It",
    "wof:placetype":"venue"
},
  "geometry": {"coordinates":[151.13221740700001,-33.6463508606],"type":"Point"}
}