{
  "type": "Feature",
  "properties": {
    "addr:full":"528 Bayswater Rd Mt Louisa QLD 4814",
    "addr:housenumber":"528",
    "addr:postcode":"4814",
    "addr:street":"Bayswater Rd",
    "iso:country":"AU",
    "sg:address":"528 Bayswater Rd",
    "sg:city":"Mt Louisa",
    "sg:classifiers":[
        {
            "category":"Home & Garden",
            "subcategory":"Carpets & Floor Coverings",
            "type":"Retail Goods"
        }
    ],
    "sg:phone":"+61 417 616 915",
    "sg:postcode":"4814",
    "sg:province":"QLD",
    "sg:tags":[
        "tile",
        "wall",
        "layer"
    ],
    "wof:name":"Kelvin Lingard Tiling",
    "wof:placetype":"venue"
},
  "geometry": {"coordinates":[146.742142,-19.271217],"type":"Point"}
}