{
  "type": "Feature",
  "properties": {
    "iso:country":"AU",
    "sg:address":"PO Box 172",
    "sg:city":"Toronto",
    "sg:classifiers":[
        {
            "category":"Autos & Motor Vehicles",
            "subcategory":"Boat Sales",
            "type":"Retail Goods"
        }
    ],
    "sg:phone":"+61 2 4950 5706",
    "sg:postcode":"2283",
    "sg:province":"NSW",
    "sg:tags":[
        "yacht"
    ],
    "wof:name":"R.A. Mackay Yacht Brokerage",
    "wof:placetype":"venue"
},
  "geometry": {"coordinates":[151.585083008,-33.0113792419],"type":"Point"}
}