{
  "type": "Feature",
  "properties": {
    "addr:full":"449 Warringah Rd Frenchs Forest NSW 2086",
    "addr:housenumber":"449",
    "addr:postcode":"2086",
    "addr:street":"Warringah Rd",
    "iso:country":"AU",
    "sg:address":"449 Warringah Rd",
    "sg:city":"Frenchs Forest",
    "sg:classifiers":[
        {
            "category":"Health Services",
            "subcategory":"Doctor",
            "type":"Services"
        }
    ],
    "sg:phone":"+61 2 9452 6065",
    "sg:postcode":"2086",
    "sg:province":"NSW",
    "sg:tags":[
        "medical",
        "practitioner"
    ],
    "wof:name":"Abbott Sue",
    "wof:placetype":"venue"
},
  "geometry": {"coordinates":[151.23275756800001,-33.752204895],"type":"Point"}
}