{
  "type": "Feature",
  "properties": {
    "iso:country":"AU",
    "sg:address":"North Rd Cnr Lion St",
    "sg:city":"Albany",
    "sg:classifiers":[
        {
            "category":"Sports & Exercise",
            "subcategory":"Gym",
            "type":"Entertainment"
        }
    ],
    "sg:phone":"+61 8 9842 2762",
    "sg:postcode":"6330",
    "sg:province":"WA",
    "sg:tags":[
        "health",
        "fitness"
    ],
    "wof:name":"Bodycare Health Club",
    "wof:placetype":"venue"
},
  "geometry": {"coordinates":[117.87220001199999,-35.0051727295],"type":"Point"}
}