{
  "type": "Feature",
  "properties": {
    "addr:full":"Shop 1 109 Thuringowa Drv Thuringowa Central QLD 4817",
    "addr:housenumber":"shop 1",
    "addr:postcode":"109;4817",
    "addr:street":"Thuringowa Drv",
    "iso:country":"AU",
    "sg:address":"Shop 1 109 Thuringowa Drv",
    "sg:city":"Thuringowa Central",
    "sg:classifiers":[
        {
            "category":"Fast Food",
            "type":"Food & Drink"
        }
    ],
    "sg:phone":"+61 7 4773 2777",
    "sg:postcode":"4817",
    "sg:province":"QLD",
    "sg:tags":[
        "away",
        "take"
    ],
    "wof:name":"Eagle Boys Pizza",
    "wof:placetype":"venue"
},
  "geometry": {"coordinates":[146.72744800000001,-19.317715],"type":"Point"}
}