{
  "type": "Feature",
  "properties": {
    "addr:full":"108 Reservoir Rd Modbury SA 5092",
    "addr:housenumber":"108",
    "addr:postcode":"5092",
    "addr:street":"Reservoir Rd",
    "iso:country":"AU",
    "sg:address":"108 Reservoir Rd",
    "sg:city":"Modbury",
    "sg:classifiers":[
        {
            "category":"Real Estate",
            "subcategory":"Real Estate Agent",
            "type":"Services"
        }
    ],
    "sg:phone":"+61 8 8397 0000",
    "sg:postcode":"5092",
    "sg:province":"SA",
    "wof:name":"Brock Real Estate",
    "wof:placetype":"venue"
},
  "geometry": {"coordinates":[138.68783569300001,-34.8331718445],"type":"Point"}
}