{
  "type": "Feature",
  "properties": {
    "addr:full":"10- 14 Martin Pl Sydney NSW 2000",
    "addr:housenumber":"14",
    "addr:postcode":"2000",
    "addr:street":"Martin Pl",
    "iso:country":"AU",
    "sg:address":"10- 14 Martin Pl",
    "sg:city":"Sydney",
    "sg:classifiers":[
        {
            "category":"Shopping",
            "subcategory":"Clothing, Apparel, & Fashions",
            "type":"Retail Goods"
        }
    ],
    "sg:phone":"+61 2 9235 2496",
    "sg:postcode":"2000",
    "sg:province":"NSW",
    "sg:tags":[
        "lady",
        "wear"
    ],
    "wof:name":"Witchery",
    "wof:placetype":"venue"
},
  "geometry": {"coordinates":[151.2081604,-33.8673744202],"type":"Point"}
}