{
  "type": "Feature",
  "properties": {
    "addr:full":"10 Duke Rd Wilberforce NSW 2756",
    "addr:housenumber":"10",
    "addr:postcode":"2756",
    "addr:street":"Duke Rd",
    "iso:country":"AU",
    "sg:address":"10 Duke Rd",
    "sg:city":"Wilberforce",
    "sg:classifiers":[
        {
            "category":"Building & Trades",
            "subcategory":"Plumbing",
            "type":"Services"
        }
    ],
    "sg:phone":"+61 2 4575 2112",
    "sg:postcode":"2756",
    "sg:province":"NSW",
    "sg:tags":[
        "plumber",
        "gasfitters"
    ],
    "wof:name":"Gardner Plumbing",
    "wof:placetype":"venue"
},
  "geometry": {"coordinates":[150.844146728,-33.5580368042],"type":"Point"}
}