{
  "type": "Feature",
  "properties": {
    "iso:country":"AU",
    "sg:address":"28 Waterside Pde",
    "sg:city":"Peakhurst",
    "sg:classifiers":[
        {
            "category":"Government",
            "subcategory":"Post Office",
            "type":"Public Place"
        }
    ],
    "sg:phone":"+61 2 9533 3379",
    "sg:postcode":"2210",
    "sg:province":"NSW",
    "sg:tags":[
        "yoga"
    ],
    "wof:name":"Judith Sanchez Yoga",
    "wof:placetype":"venue"
},
  "geometry": {"coordinates":[151.057343,-33.977936],"type":"Point"}
}