{
  "type": "Feature",
  "properties": {
    "addr:full":"23 Harold St Parramatta NSW 2150",
    "addr:housenumber":"23",
    "addr:postcode":"2150",
    "addr:street":"Harold St",
    "iso:country":"AU",
    "sg:address":"23 Harold St",
    "sg:city":"Parramatta",
    "sg:classifiers":[
        {
            "category":"Health Services",
            "subcategory":"Doctor",
            "type":"Services"
        }
    ],
    "sg:phone":"+61 2 9327 5599",
    "sg:postcode":"2150",
    "sg:province":"NSW",
    "sg:tags":[
        "medical",
        "practitioner"
    ],
    "wof:name":"De Torres Clinic",
    "wof:placetype":"venue"
},
  "geometry": {"coordinates":[151.00619506800001,-33.8047676086],"type":"Point"}
}