{
  "type": "Feature",
  "properties": {
    "addr:full":"66 New St Ringwood VIC 3134",
    "addr:housenumber":"66",
    "addr:postcode":"3134",
    "addr:street":"New St",
    "iso:country":"AU",
    "sg:address":"66 New St",
    "sg:city":"Ringwood",
    "sg:classifiers":[
        {
            "category":"Structure",
            "subcategory":"Bridge",
            "type":"Public Place"
        }
    ],
    "sg:phone":"+61 3 9870 8803",
    "sg:postcode":"3134",
    "sg:province":"VIC",
    "sg:tags":[
        "chainsaw",
        "brushcutters"
    ],
    "wof:name":"Murphys Mower Repairs",
    "wof:placetype":"venue"
},
  "geometry": {"coordinates":[145.220306397,-37.8188476562],"type":"Point"}
}