{
  "type": "Feature",
  "properties": {
    "iso:country":"AU",
    "sg:address":"2 Clayton Rd",
    "sg:city":"Clayton",
    "sg:classifiers":[
        {
            "category":"Banks & Credit Unions",
            "subcategory":"Atm",
            "type":"Services"
        }
    ],
    "sg:phone":"+61 1300 735 295",
    "sg:postcode":"3168",
    "sg:province":"VIC",
    "sg:tags":[
        "detector",
        "gas"
    ],
    "sg:website":"http://www.sensor-tech.com.au",
    "wof:name":"Sensor Technologies",
    "wof:placetype":"venue"
},
  "geometry": {"coordinates":[145.12442016599999,-37.9009056091],"type":"Point"}
}