{
  "type": "Feature",
  "properties": {
    "iso:country":"AU",
    "sg:address":"Level 1",
    "sg:city":"Paradise Point",
    "sg:classifiers":[
        {
            "category":"Professional",
            "subcategory":"Engineering",
            "type":"Services"
        }
    ],
    "sg:phone":"+61 7 5501 5887",
    "sg:postcode":"4216",
    "sg:province":"QLD",
    "sg:tags":[
        "consulting",
        "engineer"
    ],
    "wof:name":"Pacific Consulting Engineers",
    "wof:placetype":"venue"
},
  "geometry": {"coordinates":[153.39494323700001,-27.8765697479],"type":"Point"}
}