{
  "type": "Feature",
  "properties": {
    "iso:country":"AU",
    "sg:address":"2 Charles St",
    "sg:city":"Parramatta",
    "sg:classifiers":[
        {
            "category":"Manufacturing",
            "subcategory":"Chemicals & Compounds",
            "type":"Manufacturing & Wholesale Goods"
        }
    ],
    "sg:phone":"+61 433 463 101",
    "sg:postcode":"2150",
    "sg:province":"NSW",
    "sg:tags":[
        "dyestuff",
        "dye"
    ],
    "wof:name":"Dye- Plus Chemical Suppliers",
    "wof:placetype":"venue"
},
  "geometry": {"coordinates":[151.025146484,-33.7967300415],"type":"Point"}
}