{
  "type": "Feature",
  "properties": {
    "addr:full":"Aspect Drv Victoria Point QLD 4165",
    "addr:postcode":"4165",
    "addr:street":"Aspect Drv",
    "iso:country":"AU",
    "sg:address":"Aspect Drv",
    "sg:city":"Victoria Point",
    "sg:classifiers":[
        {
            "category":"Health Services",
            "subcategory":"Health Practitioner",
            "type":"Services"
        }
    ],
    "sg:phone":"+61 411 748 186",
    "sg:postcode":"4165",
    "sg:province":"QLD",
    "sg:tags":[
        "hypnotherapy"
    ],
    "wof:name":"Lewis Angela",
    "wof:placetype":"venue"
},
  "geometry": {"coordinates":[153.29566955600001,-27.5815124512],"type":"Point"}
}