{
  "type": "Feature",
  "properties": {
    "addr:full":"Shop 9, 99 Caridean St Heathridge WA 6027",
    "addr:housenumber":"shop;99",
    "addr:postcode":"6027",
    "addr:street":"Caridean St",
    "iso:country":"AU",
    "sg:address":"Shop 9, 99 Caridean St",
    "sg:city":"Heathridge",
    "sg:classifiers":[
        {
            "category":"Sports & Exercise",
            "subcategory":"Gym",
            "type":"Entertainment"
        }
    ],
    "sg:phone":"+61 8 9403 5512",
    "sg:postcode":"6027",
    "sg:province":"WA",
    "sg:tags":[
        "health",
        "fitness"
    ],
    "wof:name":"Curves",
    "wof:placetype":"venue"
},
  "geometry": {"coordinates":[115.762046814,-31.7592411041],"type":"Point"}
}