{
  "type": "Feature",
  "properties": {
    "addr:full":"888 Stanley St East Brisbane QLD 4169",
    "addr:housenumber":"888",
    "addr:postcode":"4169",
    "addr:street":"Stanley St",
    "iso:country":"AU",
    "sg:address":"888 Stanley St",
    "sg:city":"East Brisbane",
    "sg:classifiers":[
        {
            "category":"Fast Food",
            "type":"Food & Drink"
        }
    ],
    "sg:phone":"+61 7 3391 4102",
    "sg:postcode":"4169",
    "sg:province":"QLD",
    "sg:tags":[
        "away",
        "take"
    ],
    "wof:name":"Maxim's Chinese & Thai Restaurant",
    "wof:placetype":"venue"
},
  "geometry": {"coordinates":[153.042037964,-27.487569809],"type":"Point"}
}