{
  "type": "Feature",
  "properties": {
    "addr:full":"South Ave Bordertown SA 5268",
    "addr:postcode":"5268",
    "addr:street":"South Ave",
    "iso:country":"AU",
    "sg:address":"South Ave",
    "sg:city":"Bordertown",
    "sg:classifiers":[
        {
            "category":"Professional",
            "type":"Services"
        }
    ],
    "sg:phone":"+61 8 8752 2733",
    "sg:postcode":"5268",
    "sg:province":"SA",
    "sg:tags":[
        "spray",
        "painting"
    ],
    "wof:name":"Border Blasting",
    "wof:placetype":"venue"
},
  "geometry": {"coordinates":[140.77131700000001,-36.31958],"type":"Point"}
}