{
  "type": "Feature",
  "properties": {
    "addr:full":"Norman St Clifton QLD 4361",
    "addr:postcode":"4361",
    "addr:street":"Norman St",
    "iso:country":"AU",
    "sg:address":"Norman St",
    "sg:city":"Clifton",
    "sg:classifiers":[
        {
            "category":"Health Services",
            "subcategory":"Nursing And Care Facility",
            "type":"Services"
        }
    ],
    "sg:phone":"+61 7 4697 3499",
    "sg:postcode":"4361",
    "sg:province":"QLD",
    "sg:tags":[
        "home"
    ],
    "wof:name":"Clifton Nursing Home",
    "wof:placetype":"venue"
},
  "geometry": {"coordinates":[151.91093444800001,-27.9284133911],"type":"Point"}
}