{
  "type": "Feature",
  "properties": {
    "iso:country":"AU",
    "sg:address":"33 Richard St",
    "sg:city":"Bridport",
    "sg:classifiers":[
        {
            "category":"Retail",
            "subcategory":"Auto Repair",
            "type":"Services"
        }
    ],
    "sg:phone":"+61 3 6356 1215",
    "sg:postcode":"7262",
    "sg:province":"TAS",
    "sg:tags":[
        "repairer",
        "motor",
        "engineer"
    ],
    "wof:name":"Jensen I A",
    "wof:placetype":"venue"
},
  "geometry": {"coordinates":[147.386627,-40.996525],"type":"Point"}
}