{
  "type": "Feature",
  "properties": {
    "iso:country":"AU",
    "sg:address":"5 Gordon St",
    "sg:city":"Sorell",
    "sg:classifiers":[
        {
            "category":"Shopping",
            "subcategory":"Department Store",
            "type":"Retail Goods"
        }
    ],
    "sg:phone":"+61 3 6265 2021",
    "sg:postcode":"7172",
    "sg:province":"TAS",
    "wof:name":"Sorell Department Store",
    "wof:placetype":"venue"
},
  "geometry": {"coordinates":[147.562408447,-42.781917572],"type":"Point"}
}