{
  "type": "Feature",
  "properties": {
    "addr:full":"659 Grose Vale Rd Grose Vale NSW 2753",
    "addr:housenumber":"659",
    "addr:postcode":"2753",
    "addr:street":"Grose Vale Rd",
    "iso:country":"AU",
    "sg:address":"659 Grose Vale Rd",
    "sg:city":"Grose Vale",
    "sg:classifiers":[
        {
            "category":"Food & Beverages",
            "subcategory":"Groceries & Convenience Stores",
            "type":"Retail Goods"
        }
    ],
    "sg:phone":"+61 2 4572 1390",
    "sg:postcode":"2753",
    "sg:province":"NSW",
    "wof:name":"Cook's Corner Store",
    "wof:placetype":"venue"
},
  "geometry": {"coordinates":[150.65643310600001,-33.5822715759],"type":"Point"}
}