{
  "type": "Feature",
  "properties": {
    "iso:country":"AU",
    "sg:address":"88 B Main St",
    "sg:city":"Alstonville",
    "sg:classifiers":[
        {
            "category":"Professional",
            "subcategory":"Management & Consulting",
            "type":"Services"
        }
    ],
    "sg:phone":"+61 2 6628 6528",
    "sg:postcode":"2477",
    "sg:province":"NSW",
    "sg:tags":[
        "consultant",
        "energy"
    ],
    "wof:name":"BASIX Sustainable Solutions",
    "wof:placetype":"venue"
},
  "geometry": {"coordinates":[153.43585205100001,-28.8379325867],"type":"Point"}
}