{
  "type": "Feature",
  "properties": {
    "addr:full":"4/ 59 Anderson St Manunda QLD 4870",
    "addr:housenumber":"/ 59",
    "addr:postcode":"4870",
    "addr:street":"Anderson St",
    "iso:country":"AU",
    "sg:address":"4/ 59 Anderson St",
    "sg:city":"Manunda",
    "sg:classifiers":[
        {
            "category":"Professional",
            "subcategory":"Printing & Photocopies",
            "type":"Services"
        }
    ],
    "sg:phone":"+61 7 4051 8979",
    "sg:postcode":"4870",
    "sg:province":"QLD",
    "sg:tags":[
        "embroidery"
    ],
    "wof:name":"Total Embroidery",
    "wof:placetype":"venue"
},
  "geometry": {"coordinates":[145.749603272,-16.9147891998],"type":"Point"}
}