{
  "type": "Feature",
  "properties": {
    "iso:country":"AU",
    "sg:address":"14 Waverley Ridge Rd",
    "sg:city":"Stirling",
    "sg:classifiers":[
        {
            "category":"Government",
            "subcategory":"Court House",
            "type":"Public Place"
        }
    ],
    "sg:phone":"+61 8 8339 2483",
    "sg:postcode":"5152",
    "sg:province":"SA",
    "sg:tags":[
        "personal",
        "marriage",
        "family",
        "counselling"
    ],
    "wof:name":"Gabriele B Fitzgerald",
    "wof:placetype":"venue"
},
  "geometry": {"coordinates":[138.703399658,-35.0010223389],"type":"Point"}
}