{
  "type": "Feature",
  "properties": {
    "addr:full":"12/ 3 Abbotsford Cove Drv Abbotsford NSW 2046",
    "addr:housenumber":"12 / 3",
    "addr:postcode":"2046",
    "addr:street":"Abbotsford Cove Drv",
    "iso:country":"AU",
    "sg:address":"12/ 3 Abbotsford Cove Drv",
    "sg:city":"Abbotsford",
    "sg:classifiers":[
        {
            "category":"Utilities",
            "subcategory":"Electric",
            "type":"Services"
        }
    ],
    "sg:phone":"+61 419 250 263",
    "sg:postcode":"2046",
    "sg:province":"NSW",
    "sg:tags":[
        "electrical",
        "contractor"
    ],
    "wof:name":"McKay John",
    "wof:placetype":"venue"
},
  "geometry": {"coordinates":[151.130875,-33.850639],"type":"Point"}
}