{
  "type": "Feature",
  "properties": {
    "addr:full":"Pacific Hwy Kangy Angy NSW 2258",
    "addr:postcode":"2258",
    "addr:street":"Pacific Hwy",
    "iso:country":"AU",
    "sg:address":"Pacific Hwy",
    "sg:city":"Kangy Angy",
    "sg:classifiers":[
        {
            "category":"Place Of Worship",
            "subcategory":"Monastery",
            "type":"Public Place"
        }
    ],
    "sg:phone":"+61 2 4362 2444",
    "sg:postcode":"2258",
    "sg:province":"NSW",
    "sg:tags":[
        "residential",
        "village"
    ],
    "wof:name":"Tuggerah Village",
    "wof:placetype":"venue"
},
  "geometry": {"coordinates":[151.39556884800001,-33.322013855],"type":"Point"}
}