{
  "type": "Feature",
  "properties": {
    "addr:full":"Shop T8, Moonee Ponds Central Shopping Centre, 20 Homer St Moonee Ponds VIC 3039",
    "addr:housenumber":"20",
    "addr:postcode":"3039",
    "addr:street":"Homer St",
    "iso:country":"AU",
    "sg:address":"Shop T8, Moonee Ponds Central Shopping Centre, 20 Homer St",
    "sg:city":"Moonee Ponds",
    "sg:classifiers":[
        {
            "category":"Food & Beverages",
            "subcategory":"Bakery",
            "type":"Retail Goods"
        }
    ],
    "sg:phone":"+61 3 9370 0373",
    "sg:postcode":"3039",
    "sg:province":"VIC",
    "sg:tags":[
        "baker"
    ],
    "wof:name":"Bakers Delight Ltd",
    "wof:placetype":"venue"
},
  "geometry": {"coordinates":[144.91963200000001,-37.764854],"type":"Point"}
}