{
  "type": "Feature",
  "properties": {
    "iso:country":"AU",
    "sg:address":"Unit 1/ 89 Bowen St",
    "sg:city":"Broken Hill",
    "sg:classifiers":[
        {
            "category":"Retail",
            "subcategory":"Storage",
            "type":"Services"
        }
    ],
    "sg:phone":"+61 8 8087 4924",
    "sg:postcode":"2880",
    "sg:province":"NSW",
    "sg:tags":[
        "removal",
        "furniture"
    ],
    "wof:name":"Ray Giblett Removals Pty Ltd",
    "wof:placetype":"venue"
},
  "geometry": {"coordinates":[141.454147339,-31.9532718658],"type":"Point"}
}