{
  "type": "Feature",
  "properties": {
    "addr:full":"U2/ 108 Toongabbie Rd Girraween NSW 2145",
    "addr:housenumber":"108",
    "addr:postcode":"2145",
    "addr:street":"U2 /;Toongabbie Rd",
    "iso:country":"AU",
    "sg:address":"U2/ 108 Toongabbie Rd",
    "sg:city":"Girraween",
    "sg:classifiers":[
        {
            "category":"Manufacturing",
            "subcategory":"Metals",
            "type":"Manufacturing & Wholesale Goods"
        }
    ],
    "sg:phone":"+61 2 9636 3300",
    "sg:postcode":"2145",
    "sg:province":"NSW",
    "sg:tags":[
        "wholesaler",
        "aluminium",
        "mfrs"
    ],
    "wof:name":"Trango Aluminium",
    "wof:placetype":"venue"
},
  "geometry": {"coordinates":[150.940719605,-33.7934112549],"type":"Point"}
}