{
  "type": "Feature",
  "properties": {
    "addr:full":"3 Fairview St Moonee NSW 2450",
    "addr:housenumber":"3",
    "addr:postcode":"2450",
    "addr:street":"Fairview St",
    "iso:country":"AU",
    "sg:address":"3 Fairview St",
    "sg:city":"Moonee",
    "sg:classifiers":[
        {
            "category":"Bars & Pubs",
            "subcategory":"Lounge",
            "type":"Food & Drink"
        }
    ],
    "sg:phone":"+61 2 6656 4411",
    "sg:postcode":"2450",
    "sg:province":"NSW",
    "sg:tags":[
        "water",
        "filter",
        "drinking"
    ],
    "wof:name":"Tank Water Specialists",
    "wof:placetype":"venue"
},
  "geometry": {"coordinates":[153.14283800000001,-30.217012],"type":"Point"}
}