{
  "type": "Feature",
  "properties": {
    "addr:full":"Suite 6/11- 13 Hartill-Law Ave Bardwell Park NSW 2207",
    "addr:housenumber":"13",
    "addr:postcode":"2207",
    "addr:street":"Hartill-Law Ave Bardwell Park",
    "iso:country":"AU",
    "sg:address":"Suite 6/11- 13 Hartill-Law Ave",
    "sg:city":"Bardwell Park",
    "sg:classifiers":[
        {
            "category":"Banks & Credit Unions",
            "subcategory":"Financial Services",
            "type":"Services"
        }
    ],
    "sg:phone":"+61 2 9556 2010",
    "sg:postcode":"2207",
    "sg:province":"NSW",
    "sg:tags":[
        "loan",
        "finance",
        "mortgage"
    ],
    "wof:name":"City Pacific Finance",
    "wof:placetype":"venue"
},
  "geometry": {"coordinates":[151.12562600000001,-33.931461],"type":"Point"}
}