{
  "type": "Feature",
  "properties": {
    "addr:full":"14 Flamingo Drv Wantirna South VIC 3152",
    "addr:housenumber":"14",
    "addr:postcode":"3152",
    "addr:street":"Flamingo Drv",
    "iso:country":"AU",
    "sg:address":"14 Flamingo Drv",
    "sg:city":"Wantirna South",
    "sg:classifiers":[
        {
            "category":"Professional",
            "subcategory":"Art Services",
            "type":"Services"
        }
    ],
    "sg:phone":"+61 3 9800 4882",
    "sg:postcode":"3152",
    "sg:province":"VIC",
    "sg:tags":[
        "decorator",
        "painter"
    ],
    "wof:name":"Timber Recovery Service",
    "wof:placetype":"venue"
},
  "geometry": {"coordinates":[145.223342895,-37.8693504333],"type":"Point"}
}