{
  "type": "Feature",
  "properties": {
    "addr:full":"28 Woodville St Indooroopilly QLD 4068",
    "addr:housenumber":"28",
    "addr:postcode":"4068",
    "addr:street":"Woodville St",
    "iso:country":"AU",
    "sg:address":"28 Woodville St",
    "sg:city":"Indooroopilly",
    "sg:classifiers":[
        {
            "category":"Building & Trades",
            "subcategory":"Cleaning & Sanitation",
            "type":"Services"
        }
    ],
    "sg:phone":"+61 407 370 334",
    "sg:postcode":"4068",
    "sg:province":"QLD",
    "sg:tags":[
        "commercial",
        "maintenance"
    ],
    "wof:name":"Christian's Property Maintenance",
    "wof:placetype":"venue"
},
  "geometry": {"coordinates":[152.967926025,-27.5002574921],"type":"Point"}
}