{
  "type": "Feature",
  "properties": {
    "addr:full":"91 Dover Rd Williamstown VIC 3016",
    "addr:housenumber":"91",
    "addr:postcode":"3016",
    "addr:street":"Dover Rd",
    "iso:country":"AU",
    "sg:address":"91 Dover Rd",
    "sg:city":"Williamstown",
    "sg:classifiers":[
        {
            "category":"Building & Trades",
            "subcategory":"Construction",
            "type":"Services"
        }
    ],
    "sg:phone":"+61 412 755 049",
    "sg:postcode":"3016",
    "sg:province":"VIC",
    "sg:tags":[
        "contractor"
    ],
    "wof:name":"J.M. & N. Wilson Constructions",
    "wof:placetype":"venue"
},
  "geometry": {"coordinates":[144.89755249000001,-37.8527870178],"type":"Point"}
}