{
  "type": "Feature",
  "properties": {
    "addr:full":"PO Box 206 Jabiru NT 0886",
    "addr:postcode":"nt 0886",
    "iso:country":"AU",
    "sg:address":"PO Box 206",
    "sg:city":"Jabiru",
    "sg:classifiers":[
        {
            "category":"Arts & Performance",
            "subcategory":"Art Gallery",
            "type":"Entertainment"
        }
    ],
    "sg:phone":"+61 8 8979 2777",
    "sg:postcode":"0886",
    "sg:province":"NT",
    "sg:tags":[
        "aboriginal",
        "craft"
    ],
    "wof:name":"Marrawuddi Gallery",
    "wof:placetype":"venue"
},
  "geometry": {"coordinates":[132.83616599999999,-12.67414],"type":"Point"}
}