{
  "type": "Feature",
  "properties": {
    "iso:country":"AU",
    "sg:address":"Level 4 56 Railway Pde",
    "sg:city":"Burwood",
    "sg:classifiers":[
        {
            "category":"Professional",
            "subcategory":"Employment Agencies",
            "type":"Services"
        }
    ],
    "sg:phone":"+61 2 8922 5000",
    "sg:postcode":"2134",
    "sg:province":"NSW",
    "wof:name":"McCormack Employment Services",
    "wof:placetype":"venue"
},
  "geometry": {"coordinates":[151.100265503,-33.8769645691],"type":"Point"}
}