{
  "type": "Feature",
  "properties": {
    "addr:full":"Shop 26a, Albany Village Shopping Centre, 700 Alba Albany Creek QLD 4035",
    "addr:housenumber":"26a;700",
    "addr:postcode":"4035",
    "addr:street":"Albany Village;Alba",
    "iso:country":"AU",
    "sg:address":"Shop 26a, Albany Village Shopping Centre, 700 Alba",
    "sg:city":"Albany Creek",
    "sg:classifiers":[
        {
            "category":"Real Estate",
            "subcategory":"Real Estate Agent",
            "type":"Services"
        }
    ],
    "sg:phone":"+61 7 3264 9000",
    "sg:postcode":"4035",
    "sg:province":"QLD",
    "wof:name":"L J Hooker",
    "wof:placetype":"venue"
},
  "geometry": {"coordinates":[152.96582000000001,-27.345341],"type":"Point"}
}