{
  "type": "Feature",
  "properties": {
    "addr:full":"1039 Mt Alexander Rd Essendon VIC 3040",
    "addr:housenumber":"1039",
    "addr:postcode":"3040",
    "addr:street":"Mt Alexander Rd",
    "iso:country":"AU",
    "sg:address":"1039 Mt Alexander Rd",
    "sg:city":"Essendon",
    "sg:classifiers":[
        {
            "category":"Cafe",
            "type":"Food & Drink"
        }
    ],
    "sg:phone":"+61 3 9379 7452",
    "sg:postcode":"3040",
    "sg:province":"VIC",
    "wof:name":"Woodlands Cafe",
    "wof:placetype":"venue"
},
  "geometry": {"coordinates":[144.911254883,-37.7466087341],"type":"Point"}
}