{
  "type": "Feature",
  "properties": {
    "iso:country":"AU",
    "sg:address":"Campbelltown Mall",
    "sg:city":"Campbelltown",
    "sg:classifiers":[
        {
            "category":"Cafe",
            "type":"Food & Drink"
        }
    ],
    "sg:phone":"+61 2 4628 3282",
    "sg:postcode":"2560",
    "sg:province":"NSW",
    "wof:name":"Perfect Blend",
    "wof:placetype":"venue"
},
  "geometry": {"coordinates":[150.810302734,-34.0710601807],"type":"Point"}
}