{
  "type": "Feature",
  "properties": {
    "iso:country":"AU",
    "sg:address":"2/ 44 Cambridge St",
    "sg:city":"Port Melbourne",
    "sg:classifiers":[
        {
            "category":"Professional",
            "subcategory":"Printing & Photocopies",
            "type":"Services"
        }
    ],
    "sg:phone":"+61 3 9646 1007",
    "sg:postcode":"3207",
    "sg:province":"VIC",
    "sg:tags":[
        "screen",
        "printer"
    ],
    "wof:name":"Melbourne Promotions & Screen Printers",
    "wof:placetype":"venue"
},
  "geometry": {"coordinates":[144.937515,-37.833954],"type":"Point"}
}