{
  "type": "Feature",
  "properties": {
    "addr:full":"134 Glenhaven Rd Dural NSW 2158",
    "addr:housenumber":"134",
    "addr:postcode":"2158",
    "addr:street":"Glenhaven Rd",
    "iso:country":"AU",
    "sg:address":"134 Glenhaven Rd",
    "sg:city":"Dural",
    "sg:classifiers":[
        {
            "category":"Health Services",
            "subcategory":"Chiropractor",
            "type":"Services"
        }
    ],
    "sg:phone":"+61 2 9634 6683",
    "sg:postcode":"2158",
    "sg:province":"NSW",
    "wof:name":"Mazzotti Dennis",
    "wof:placetype":"venue"
},
  "geometry": {"coordinates":[150.995635986,-33.696849823],"type":"Point"}
}