{
  "type": "Feature",
  "properties": {
    "addr:full":"Drummond Drv Gympie QLD 4570",
    "addr:postcode":"4570",
    "addr:street":"Drummond Drv",
    "iso:country":"AU",
    "sg:address":"Drummond Drv",
    "sg:city":"Gympie",
    "sg:classifiers":[
        {
            "category":"Manufacturing",
            "subcategory":"Food",
            "type":"Manufacturing & Wholesale Goods"
        }
    ],
    "sg:phone":"+61 7 5482 7599",
    "sg:postcode":"4570",
    "sg:province":"QLD",
    "sg:tags":[
        "product",
        "nut",
        "edible"
    ],
    "wof:name":"Suncoast Gold Macadamias",
    "wof:placetype":"venue"
},
  "geometry": {"coordinates":[152.694488525,-26.222442627],"type":"Point"}
}