{
  "type": "Feature",
  "properties": {
    "addr:full":"16 Monoplane St Ashgrove QLD 4060",
    "addr:housenumber":"16",
    "addr:postcode":"4060",
    "addr:street":"Monoplane St",
    "iso:country":"AU",
    "sg:address":"16 Monoplane St",
    "sg:city":"Ashgrove",
    "sg:classifiers":[
        {
            "category":"Professional",
            "subcategory":"Accounting & Tax Preparation",
            "type":"Services"
        }
    ],
    "sg:phone":"+61 7 3311 2547",
    "sg:postcode":"4060",
    "sg:province":"QLD",
    "sg:tags":[
        "bookkeeping"
    ],
    "wof:name":"Inner North West Bookkeeping",
    "wof:placetype":"venue"
},
  "geometry": {"coordinates":[152.97439575199999,-27.4496154785],"type":"Point"}
}