{
  "type": "Feature",
  "properties": {
    "addr:full":"155 Christine Ave Burleigh Heads QLD 4220",
    "addr:housenumber":"155",
    "addr:postcode":"4220",
    "addr:street":"Christine Ave",
    "iso:country":"AU",
    "sg:address":"155 Christine Ave",
    "sg:city":"Burleigh Heads",
    "sg:classifiers":[
        {
            "category":"Professional",
            "subcategory":"Art Services",
            "type":"Services"
        }
    ],
    "sg:phone":"+61 403 198 763",
    "sg:postcode":"4220",
    "sg:province":"QLD",
    "sg:tags":[
        "decorator",
        "painter"
    ],
    "wof:name":"M Painting",
    "wof:placetype":"venue"
},
  "geometry": {"coordinates":[153.43966674800001,-28.0779857635],"type":"Point"}
}