{
  "type": "Feature",
  "properties": {
    "iso:country":"AU",
    "sg:address":"7 Parramatta Rd",
    "sg:city":"Concord",
    "sg:classifiers":[
        {
            "category":"Manufacturing",
            "subcategory":"Motor Vehicles & Parts",
            "type":"Manufacturing & Wholesale Goods"
        }
    ],
    "sg:phone":"+61 2 9744 2266",
    "sg:postcode":"2137",
    "sg:province":"NSW",
    "sg:tags":[
        "replacement"
    ],
    "wof:name":"Mus Secret",
    "wof:placetype":"venue"
},
  "geometry": {"coordinates":[151.10708618199999,-33.8689346313],"type":"Point"}
}