{
  "type": "Feature",
  "properties": {
    "addr:full":"3 Alban St Lidcombe NSW 2141",
    "addr:housenumber":"3",
    "addr:postcode":"2141",
    "addr:street":"St",
    "iso:country":"AU",
    "sg:address":"3 Alban St",
    "sg:city":"Lidcombe",
    "sg:classifiers":[
        {
            "category":"Retail",
            "subcategory":"Auto Repair",
            "type":"Services"
        }
    ],
    "sg:phone":"+61 2 9748 2034",
    "sg:postcode":"2141",
    "sg:province":"NSW",
    "sg:tags":[
        "beater",
        "painter",
        "panel"
    ],
    "wof:name":"Holden Tony",
    "wof:placetype":"venue"
},
  "geometry": {"coordinates":[151.045578003,-33.8463592529],"type":"Point"}
}