{
  "type": "Feature",
  "properties": {
    "addr:full":"Rose St Birchgrove NSW 2041",
    "addr:postcode":"2041",
    "addr:street":"Rose St",
    "iso:country":"AU",
    "sg:address":"Rose St",
    "sg:city":"Birchgrove",
    "sg:classifiers":[
        {
            "category":"Sports & Exercise",
            "subcategory":"Sports Center",
            "type":"Entertainment"
        }
    ],
    "sg:phone":"+61 2 9810 0110",
    "sg:postcode":"2041",
    "sg:province":"NSW",
    "sg:tags":[
        "coach",
        "tennis"
    ],
    "wof:name":"Rocavert Terry",
    "wof:placetype":"venue"
},
  "geometry": {"coordinates":[151.180847,-33.851192],"type":"Point"}
}