{
  "type": "Feature",
  "properties": {
    "addr:full":"Lindsay St Gosford NSW 2250",
    "addr:postcode":"2250",
    "addr:street":"Lindsay St",
    "iso:country":"AU",
    "sg:address":"Lindsay St",
    "sg:city":"Gosford",
    "sg:classifiers":[
        {
            "category":"Autos & Motor Vehicles",
            "subcategory":"Automobile Sales",
            "type":"Retail Goods"
        }
    ],
    "sg:phone":"+61 2 4323 9444",
    "sg:postcode":"2250",
    "sg:province":"NSW",
    "sg:tags":[
        "car",
        "new"
    ],
    "wof:name":"Central Coast Subaru",
    "wof:placetype":"venue"
},
  "geometry": {"coordinates":[151.48106384299999,-33.3693237305],"type":"Point"}
}