{
  "type": "Feature",
  "properties": {
    "iso:country":"AU",
    "sg:address":"Kay Crt via Bruce Hwy",
    "sg:city":"North Mackay",
    "sg:classifiers":[
        {
            "category":"Autos & Motor Vehicles",
            "subcategory":"Automobile Sales",
            "type":"Retail Goods"
        }
    ],
    "sg:phone":"+61 7 4942 2633",
    "sg:postcode":"4740",
    "sg:province":"QLD",
    "sg:tags":[
        "car",
        "used"
    ],
    "wof:name":"Honeycombes Used Cars Mackay",
    "wof:placetype":"venue"
},
  "geometry": {"coordinates":[149.164948,-21.130846],"type":"Point"}
}