{
  "type": "Feature",
  "properties": {
    "addr:full":"Shp 7 Northcote Plz Shopng Cntr Northcote VIC 3070",
    "addr:housenumber":"7",
    "addr:postcode":"3070",
    "addr:street":"Northcote Plz Shopng Cntr",
    "iso:country":"AU",
    "sg:address":"Shp 7 Northcote Plz Shopng Cntr",
    "sg:city":"Northcote",
    "sg:classifiers":[
        {
            "category":"Shopping",
            "subcategory":"Jewelry",
            "type":"Retail Goods"
        }
    ],
    "sg:phone":"+61 3 9481 7965",
    "sg:postcode":"3070",
    "sg:province":"VIC",
    "sg:tags":[
        "jeweller"
    ],
    "wof:name":"Effy Fine Jewellery",
    "wof:placetype":"venue"
},
  "geometry": {"coordinates":[145.00770600000001,-37.774391],"type":"Point"}
}