{
  "type": "Feature",
  "properties": {
    "addr:full":"&#039;Hillsia&#039; Warral Rd Tamworth NSW 2340",
    "addr:postcode":"2340",
    "addr:street":"Warral Rd",
    "iso:country":"AU",
    "sg:address":"&#039;Hillsia&#039; Warral Rd",
    "sg:city":"Tamworth",
    "sg:classifiers":[
        {
            "category":"Building & Trades",
            "subcategory":"Construction",
            "type":"Services"
        }
    ],
    "sg:phone":"+61 2 6762 1109",
    "sg:postcode":"2340",
    "sg:province":"NSW",
    "sg:tags":[
        "contractor"
    ],
    "wof:name":"Adrian Dernee",
    "wof:placetype":"venue"
},
  "geometry": {"coordinates":[150.90289306599999,-31.1020374298],"type":"Point"}
}