{
  "type": "Feature",
  "properties": {
    "addr:full":"Cameron St Mt Barker SA 5251",
    "addr:postcode":"5251",
    "addr:street":"Cameron St Mt",
    "iso:country":"AU",
    "sg:address":"Cameron St",
    "sg:city":"Mt Barker",
    "sg:classifiers":[
        {
            "category":"Food & Beverages",
            "subcategory":"Supermarket",
            "type":"Retail Goods"
        }
    ],
    "sg:phone":"+61 8 8391 2722",
    "sg:postcode":"5251",
    "sg:province":"SA",
    "sg:tags":[
        "grocery",
        "store"
    ],
    "wof:name":"Bi-Lo",
    "wof:placetype":"venue"
},
  "geometry": {"coordinates":[138.86329650900001,-35.0572738647],"type":"Point"}
}