{
  "type": "Feature",
  "properties": {
    "addr:full":"14 Walter Crt Glenore Grove QLD 4342",
    "addr:housenumber":"14",
    "addr:postcode":"4342",
    "addr:street":"Walter Crt",
    "iso:country":"AU",
    "sg:address":"14 Walter Crt",
    "sg:city":"Glenore Grove",
    "sg:classifiers":[
        {
            "category":"Banks & Credit Unions",
            "subcategory":"Financial Services",
            "type":"Services"
        }
    ],
    "sg:phone":"+61 7 5466 5900",
    "sg:postcode":"4342",
    "sg:province":"QLD",
    "sg:tags":[
        "loan",
        "finance",
        "mortgage"
    ],
    "wof:name":"Fasta Mortgage Solutions",
    "wof:placetype":"venue"
},
  "geometry": {"coordinates":[152.407272339,-27.5340080261],"type":"Point"}
}