{
  "type": "Feature",
  "properties": {
    "addr:full":"198 Mary St Wanneroo WA 6065",
    "addr:housenumber":"198",
    "addr:postcode":"6065",
    "addr:street":"Mary St",
    "iso:country":"AU",
    "sg:address":"198 Mary St",
    "sg:city":"Wanneroo",
    "sg:classifiers":[
        {
            "category":"Retail",
            "subcategory":"Event Space",
            "type":"Services"
        }
    ],
    "sg:phone":"+61 8 9306 1011",
    "sg:postcode":"6065",
    "sg:province":"WA",
    "sg:tags":[
        "venue",
        "reception",
        "wedding"
    ],
    "wof:name":"Bridgeleigh",
    "wof:placetype":"venue"
},
  "geometry": {"coordinates":[115.83592224100001,-31.7854156494],"type":"Point"}
}