{
  "type": "Feature",
  "properties": {
    "iso:country":"AU",
    "sg:address":"Unit 4, Block 6 Mawson Pl Southlands",
    "sg:city":"Mawson",
    "sg:classifiers":[
        {
            "category":"Personal",
            "subcategory":"Tanning Parlor",
            "type":"Services"
        }
    ],
    "sg:phone":"+61 2 6286 8150",
    "sg:postcode":"2607",
    "sg:province":"ACT",
    "sg:tags":[
        "solarium"
    ],
    "wof:name":"Belle La Vie",
    "wof:placetype":"venue"
},
  "geometry": {"coordinates":[149.09513855,-35.3667602539],"type":"Point"}
}