{
  "type": "Feature",
  "properties": {
    "iso:country":"AU",
    "sg:address":"86 Mitchell St",
    "sg:city":"Maidstone",
    "sg:classifiers":[
        {
            "category":"Manufacturing",
            "subcategory":"Metals",
            "type":"Manufacturing & Wholesale Goods"
        }
    ],
    "sg:phone":"+61 3 9317 4096",
    "sg:postcode":"3012",
    "sg:province":"VIC",
    "sg:tags":[
        "steel",
        "fabricator",
        "mfrs"
    ],
    "wof:name":"ICR Group",
    "wof:placetype":"venue"
},
  "geometry": {"coordinates":[144.880004883,-37.7823562622],"type":"Point"}
}