{
  "type": "Feature",
  "properties": {
    "addr:full":"119 Princes Hwy Yarragon VIC 3823",
    "addr:housenumber":"119",
    "addr:postcode":"3823",
    "addr:street":"Princes Hwy",
    "iso:country":"AU",
    "sg:address":"119 Princes Hwy",
    "sg:city":"Yarragon",
    "sg:classifiers":[
        {
            "category":"Travel",
            "subcategory":"Hotels & Motels",
            "type":"Entertainment"
        }
    ],
    "sg:phone":"+61 3 5634 2655",
    "sg:postcode":"3823",
    "sg:province":"VIC",
    "wof:name":"Golden Chain Yarragon Motel",
    "wof:placetype":"venue"
},
  "geometry": {"coordinates":[146.07884200000001,-38.20462],"type":"Point"}
}