{
  "type": "Feature",
  "properties": {
    "addr:full":"67c Railway Ave Railway Estate QLD 4810",
    "addr:housenumber":"67c",
    "addr:postcode":"4810",
    "addr:street":"Railway Ave Railway",
    "iso:country":"AU",
    "sg:address":"67c Railway Ave",
    "sg:city":"Railway Estate",
    "sg:classifiers":[
        {
            "category":"Banks & Credit Unions",
            "subcategory":"Bank",
            "type":"Services"
        }
    ],
    "sg:phone":"+61 7 4771 6744",
    "sg:postcode":"4810",
    "sg:province":"QLD",
    "sg:tags":[
        "equipment",
        "sale",
        "point"
    ],
    "wof:name":"Accurate Systems",
    "wof:placetype":"venue"
},
  "geometry": {"coordinates":[146.815933,-19.277803],"type":"Point"}
}