{
  "type": "Feature",
  "properties": {
    "addr:full":"Lot 11, Micalo Rd Yamba NSW 2464",
    "addr:postcode":"2464",
    "addr:street":"Micalo Rd",
    "iso:country":"AU",
    "sg:address":"Lot 11, Micalo Rd",
    "sg:city":"Yamba",
    "sg:classifiers":[
        {
            "category":"Building & Trades",
            "subcategory":"Construction",
            "type":"Services"
        }
    ],
    "sg:phone":"+61 2 6646 0469",
    "sg:postcode":"2464",
    "sg:province":"NSW",
    "sg:tags":[
        "contractor"
    ],
    "wof:name":"E & L Spears Builder",
    "wof:placetype":"venue"
},
  "geometry": {"coordinates":[153.313552856,-29.438577652],"type":"Point"}
}