{
  "type": "Feature",
  "properties": {
    "addr:full":"328 Oxley Ave Margate QLD 4019",
    "addr:housenumber":"328",
    "addr:postcode":"4019",
    "addr:street":"Oxley Ave",
    "iso:country":"AU",
    "sg:address":"328 Oxley Ave",
    "sg:city":"Margate",
    "sg:classifiers":[
        {
            "category":"Health Services",
            "subcategory":"Doctor",
            "type":"Services"
        }
    ],
    "sg:phone":"+61 7 3284 6383",
    "sg:postcode":"4019",
    "sg:province":"QLD",
    "sg:tags":[
        "occupational",
        "safety"
    ],
    "wof:name":"Entire Health Occupational Therapy",
    "wof:placetype":"venue"
},
  "geometry": {"coordinates":[153.107910156,-27.2374687195],"type":"Point"}
}