{
  "type": "Feature",
  "properties": {
    "addr:full":"19 Curlew Crs Tamworth NSW 2340",
    "addr:housenumber":"19",
    "addr:postcode":"2340",
    "addr:street":"Curlew Crs",
    "iso:country":"AU",
    "sg:address":"19 Curlew Crs",
    "sg:city":"Tamworth",
    "sg:classifiers":[
        {
            "category":"Professional",
            "subcategory":"Engineering",
            "type":"Services"
        }
    ],
    "sg:phone":"+61 428 627 273",
    "sg:postcode":"2340",
    "sg:province":"NSW",
    "sg:tags":[
        "engineer"
    ],
    "wof:name":"Tamworth Precision Engineering",
    "wof:placetype":"venue"
},
  "geometry": {"coordinates":[150.92852783199999,-31.0906391144],"type":"Point"}
}