{
  "type": "Feature",
  "properties": {
    "addr:full":"180 Burton Rd Paralowie SA 5108",
    "addr:housenumber":"180",
    "addr:postcode":"5108",
    "addr:street":"Burton Rd",
    "iso:country":"AU",
    "sg:address":"180 Burton Rd",
    "sg:city":"Paralowie",
    "sg:classifiers":[
        {
            "category":"Fast Food",
            "type":"Food & Drink"
        }
    ],
    "sg:phone":"+61 8 8281 5590",
    "sg:postcode":"5108",
    "sg:province":"SA",
    "sg:tags":[
        "away",
        "take"
    ],
    "wof:name":"Woks On Chinese Takeaway",
    "wof:placetype":"venue"
},
  "geometry": {"coordinates":[138.609619141,-34.7561302185],"type":"Point"}
}