{
  "type": "Feature",
  "properties": {
    "addr:full":"75 Main St Lowood QLD 4311",
    "addr:housenumber":"75",
    "addr:postcode":"4311",
    "addr:street":"Main St",
    "iso:country":"AU",
    "sg:address":"75 Main St",
    "sg:city":"Lowood",
    "sg:classifiers":[
        {
            "category":"Personal",
            "subcategory":"Beauty Salon",
            "type":"Services"
        }
    ],
    "sg:phone":"+61 7 5426 1434",
    "sg:postcode":"4311",
    "sg:province":"QLD",
    "sg:tags":[
        "hairdresser"
    ],
    "wof:name":"Lowood Hair Stylists",
    "wof:placetype":"venue"
},
  "geometry": {"coordinates":[152.58003234899999,-27.465057373],"type":"Point"}
}