{
  "type": "Feature",
  "properties": {
    "iso:country":"AU",
    "sg:address":"P O Box 15",
    "sg:city":"Wirrabara",
    "sg:classifiers":[
        {
            "category":"Farming",
            "subcategory":"Farm",
            "type":"Manufacturing & Wholesale Goods"
        }
    ],
    "sg:phone":"+61 8 8668 4197",
    "sg:postcode":"5481",
    "sg:province":"SA",
    "sg:tags":[
        "farmer"
    ],
    "wof:name":"Carman C R",
    "wof:placetype":"venue"
},
  "geometry": {"coordinates":[138.26817321799999,-33.0319900513],"type":"Point"}
}