{
  "type": "Feature",
  "properties": {
    "addr:full":"Cnr Springvale & Waverley Rds Glen Waverley VIC 3150",
    "addr:postcode":"3150",
    "addr:street":"Cnr;Rds",
    "iso:country":"AU",
    "sg:address":"Cnr Springvale & Waverley Rds",
    "sg:city":"Glen Waverley",
    "sg:classifiers":[
        {
            "category":"Autos & Motor Vehicles",
            "subcategory":"Automobile Sales",
            "type":"Retail Goods"
        }
    ],
    "sg:phone":"+61 3 8544 2288",
    "sg:postcode":"3150",
    "sg:province":"VIC",
    "sg:tags":[
        "car",
        "used"
    ],
    "wof:name":"Lane Toyota",
    "wof:placetype":"venue"
},
  "geometry": {"coordinates":[145.16513061500001,-37.8829498291],"type":"Point"}
}