{
  "type": "Feature",
  "properties": {
    "iso:country":"AU",
    "sg:address":"U14/ 99 Stanley St",
    "sg:city":"Darlinghurst",
    "sg:classifiers":[
        {
            "category":"Building & Trades",
            "subcategory":"Landscaping Services",
            "type":"Services"
        }
    ],
    "sg:phone":"+61 2 9357 2598",
    "sg:postcode":"2010",
    "sg:province":"NSW",
    "sg:tags":[
        "designer",
        "landscape",
        "contractor"
    ],
    "wof:name":"David Burnett Design",
    "wof:placetype":"venue"
},
  "geometry": {"coordinates":[151.21653747600001,-33.876083374],"type":"Point"}
}