{
  "type": "Feature",
  "properties": {
    "iso:country":"AU",
    "sg:address":"13 Nambour Rd",
    "sg:city":"Templestowe",
    "sg:classifiers":[
        {
            "category":"Personal",
            "type":"Services"
        }
    ],
    "sg:phone":"+61 3 9846 1319",
    "sg:postcode":"3106",
    "sg:province":"VIC",
    "sg:tags":[
        "career",
        "counselling"
    ],
    "wof:name":"Gordon Young & Associates",
    "wof:placetype":"venue"
},
  "geometry": {"coordinates":[145.12840270999999,-37.763710022],"type":"Point"}
}