{
  "type": "Feature",
  "properties": {
    "addr:full":"13 Phillips St Kaniva VIC 3419",
    "addr:housenumber":"13",
    "addr:postcode":"3419",
    "addr:street":"Phillips St",
    "iso:country":"AU",
    "sg:address":"13 Phillips St",
    "sg:city":"Kaniva",
    "sg:classifiers":[
        {
            "category":"Building & Trades",
            "subcategory":"Plumbing",
            "type":"Services"
        }
    ],
    "sg:phone":"+61 3 5392 2630",
    "sg:postcode":"3419",
    "sg:province":"VIC",
    "sg:tags":[
        "plumber",
        "gasfitters"
    ],
    "wof:name":"Mills Gary R",
    "wof:placetype":"venue"
},
  "geometry": {"coordinates":[141.237548828,-36.3795585632],"type":"Point"}
}