{
  "type": "Feature",
  "properties": {
    "iso:country":"AU",
    "sg:address":"8 McNab St",
    "sg:city":"Rosalie",
    "sg:classifiers":[
        {
            "category":"Building & Trades",
            "subcategory":"Landscaping Services",
            "type":"Services"
        }
    ],
    "sg:phone":"+61 411 124 440",
    "sg:postcode":"4064",
    "sg:province":"QLD",
    "sg:tags":[
        "inspection"
    ],
    "wof:name":"Farlow Trevor",
    "wof:placetype":"venue"
},
  "geometry": {"coordinates":[152.99452209500001,-27.4671649933],"type":"Point"}
}