{
  "type": "Feature",
  "properties": {
    "addr:full":"1555 Dandenong Rd Oakleigh VIC 3166",
    "addr:housenumber":"1555",
    "addr:postcode":"3166",
    "addr:street":"Dandenong Rd",
    "iso:country":"AU",
    "sg:address":"1555 Dandenong Rd",
    "sg:city":"Oakleigh",
    "sg:classifiers":[
        {
            "category":"Travel",
            "subcategory":"Hotels & Motels",
            "type":"Entertainment"
        }
    ],
    "sg:phone":"+61 3 9569 9954",
    "sg:postcode":"3166",
    "sg:province":"VIC",
    "sg:tags":[
        "pub"
    ],
    "wof:name":"Leighoak Hotel",
    "wof:placetype":"venue"
},
  "geometry": {"coordinates":[145.09327697800001,-37.8933486938],"type":"Point"}
}