{
  "type": "Feature",
  "properties": {
    "addr:full":"31 Mahoneys Rd Forest Hill VIC 3131",
    "addr:housenumber":"31",
    "addr:postcode":"3131",
    "addr:street":"Mahoneys Rd",
    "iso:country":"AU",
    "sg:address":"31 Mahoneys Rd",
    "sg:city":"Forest Hill",
    "sg:classifiers":[
        {
            "category":"Real Estate",
            "subcategory":"Real Estate Agent",
            "type":"Services"
        }
    ],
    "sg:phone":"+61 3 9894 2300",
    "sg:postcode":"3131",
    "sg:province":"VIC",
    "wof:name":"Eastern Central Real Estate",
    "wof:placetype":"venue"
},
  "geometry": {"coordinates":[145.16653442399999,-37.835067749],"type":"Point"}
}