{
  "type": "Feature",
  "properties": {
    "addr:full":"1st Flr 82 Mitchell St Bendigo VIC 3550",
    "addr:housenumber":"82",
    "addr:postcode":"3550",
    "addr:street":"Mitchell St",
    "iso:country":"AU",
    "sg:address":"1st Flr 82 Mitchell St",
    "sg:city":"Bendigo",
    "sg:classifiers":[
        {
            "category":"Professional",
            "subcategory":"Accounting & Tax Preparation",
            "type":"Services"
        }
    ],
    "sg:phone":"+61 3 5441 6503",
    "sg:postcode":"3550",
    "sg:province":"VIC",
    "sg:tags":[
        "consultant",
        "taxation"
    ],
    "wof:name":"H&R Block",
    "wof:placetype":"venue"
},
  "geometry": {"coordinates":[144.28125,-36.762260437],"type":"Point"}
}