{
  "type": "Feature",
  "properties": {
    "iso:country":"AU",
    "sg:address":"24- 26 Dalton St",
    "sg:city":"Parkes",
    "sg:classifiers":[
        {
            "category":"Wholesale",
            "subcategory":"Electrical",
            "type":"Manufacturing & Wholesale Goods"
        }
    ],
    "sg:phone":"+61 2 6862 6100",
    "sg:postcode":"2870",
    "sg:province":"NSW",
    "sg:tags":[
        "wholesaler"
    ],
    "wof:name":"Auslec",
    "wof:placetype":"venue"
},
  "geometry": {"coordinates":[148.17332500000001,-33.137314],"type":"Point"}
}