{
  "type": "Feature",
  "properties": {
    "addr:full":"15 Caribou Crs Upper Coomera QLD 4209",
    "addr:housenumber":"15",
    "addr:postcode":"4209",
    "addr:street":"Caribou Crs",
    "iso:country":"AU",
    "sg:address":"15 Caribou Crs",
    "sg:city":"Upper Coomera",
    "sg:classifiers":[
        {
            "category":"Utilities",
            "subcategory":"Electric",
            "type":"Services"
        }
    ],
    "sg:phone":"+61 416 140 948",
    "sg:postcode":"4209",
    "sg:province":"QLD",
    "sg:tags":[
        "electrical",
        "contractor"
    ],
    "wof:name":"Bruce, M A Electrician",
    "wof:placetype":"venue"
},
  "geometry": {"coordinates":[153.29867553700001,-27.8690700531],"type":"Point"}
}