{
  "type": "Feature",
  "properties": {
    "iso:country":"AU",
    "sg:address":"Fcty13/ 22 Redland Drv",
    "sg:city":"Mitcham",
    "sg:classifiers":[
        {
            "category":"Utilities",
            "subcategory":"Electric",
            "type":"Services"
        }
    ],
    "sg:phone":"+61 3 9873 8258",
    "sg:postcode":"3132",
    "sg:province":"VIC",
    "sg:tags":[
        "electrical",
        "contractor"
    ],
    "wof:name":"Bell Wiggins Pty Ltd",
    "wof:placetype":"venue"
},
  "geometry": {"coordinates":[145.19015502900001,-37.8301277161],"type":"Point"}
}