{
  "type": "Feature",
  "properties": {
    "addr:full":"Lot 16/ 18 High Vista Drv Mt Louisa QLD 4814",
    "addr:housenumber":"/ 18",
    "addr:postcode":"4814",
    "addr:street":"High Vista Drv Mt Louisa",
    "iso:country":"AU",
    "sg:address":"Lot 16/ 18 High Vista Drv",
    "sg:city":"Mt Louisa",
    "sg:classifiers":[
        {
            "category":"Building & Trades",
            "subcategory":"Construction",
            "type":"Services"
        }
    ],
    "sg:phone":"+61 7 4774 4474",
    "sg:postcode":"4814",
    "sg:province":"QLD",
    "sg:tags":[
        "renovation",
        "alterations",
        "extension",
        "contractor"
    ],
    "wof:name":"Walsh Homes Pty Ltd",
    "wof:placetype":"venue"
},
  "geometry": {"coordinates":[146.74838299999999,-19.279932],"type":"Point"}
}