{
  "type": "Feature",
  "properties": {
    "iso:country":"AU",
    "sg:address":"Lot 16/ 18 High Vista Drv",
    "sg:city":"Mt Louisa",
    "sg:classifiers":[
        {
            "category":"Building & Trades",
            "subcategory":"Construction",
            "type":"Services"
        }
    ],
    "sg:phone":"+61 7 4774 4474",
    "sg:postcode":"4814",
    "sg:province":"QLD",
    "sg:tags":[
        "renovation",
        "alterations",
        "extension",
        "contractor"
    ],
    "wof:name":"Walsh Homes Pty Ltd",
    "wof:placetype":"venue"
},
  "geometry": {"coordinates":[146.748383,-19.279932],"type":"Point"}
}