{
  "type": "Feature",
  "properties": {
    "iso:country":"AU",
    "sg:address":"19 Nilands La",
    "sg:city":"Woodberry",
    "sg:classifiers":[
        {
            "category":"Building & Trades",
            "subcategory":"Construction",
            "type":"Services"
        }
    ],
    "sg:phone":"+61 2 4964 1542",
    "sg:postcode":"2322",
    "sg:province":"NSW",
    "sg:tags":[
        "earth",
        "excavating",
        "moving",
        "contractor"
    ],
    "wof:name":"B & L Weir",
    "wof:placetype":"venue"
},
  "geometry": {"coordinates":[151.68168640100001,-32.789691925],"type":"Point"}
}