{
  "type": "Feature",
  "properties": {
    "addr:full":"1 Golfers Pde Kiama Downs NSW 2533",
    "addr:housenumber":"1",
    "addr:postcode":"2533",
    "addr:street":"Golfers Pde",
    "iso:country":"AU",
    "sg:address":"1 Golfers Pde",
    "sg:city":"Kiama Downs",
    "sg:classifiers":[
        {
            "category":"Building & Trades",
            "subcategory":"Construction",
            "type":"Services"
        }
    ],
    "sg:phone":"+61 2 4237 7137",
    "sg:postcode":"2533",
    "sg:province":"NSW",
    "sg:tags":[
        "contractor"
    ],
    "wof:name":"Gibson A J & A G",
    "wof:placetype":"venue"
},
  "geometry": {"coordinates":[150.852752686,-34.6330108643],"type":"Point"}
}