{
  "type": "Feature",
  "properties": {
    "addr:full":"25 Laurina Dr Traralgon VIC 3844",
    "addr:housenumber":"25",
    "addr:postcode":"3844",
    "addr:street":"Laurina Dr",
    "iso:country":"AU",
    "sg:address":"25 Laurina Dr",
    "sg:city":"Traralgon",
    "sg:classifiers":[
        {
            "category":"Building & Trades",
            "subcategory":"Construction",
            "type":"Services"
        }
    ],
    "sg:phone":"+61 3 5176 5217",
    "sg:postcode":"3844",
    "sg:province":"VIC",
    "sg:tags":[
        "earth",
        "excavating",
        "moving",
        "contractor"
    ],
    "wof:name":"Nicholls Earthmoving & Contracting Pty Ltd",
    "wof:placetype":"venue"
},
  "geometry": {"coordinates":[146.569946289,-38.1987724304],"type":"Point"}
}