{
  "type": "Feature",
  "properties": {
    "addr:full":"Alexandra St Eaglehawk VIC 3556",
    "addr:postcode":"3556",
    "addr:street":"Alexandra St",
    "iso:country":"AU",
    "sg:address":"Alexandra St",
    "sg:city":"Eaglehawk",
    "sg:classifiers":[
        {
            "category":"Utilities",
            "subcategory":"Recycling",
            "type":"Services"
        }
    ],
    "sg:phone":"+61 3 5446 1292",
    "sg:postcode":"3556",
    "sg:province":"VIC",
    "wof:name":"Allstone Quarries",
    "wof:placetype":"venue"
},
  "geometry": {"coordinates":[144.24717712399999,-36.728729248],"type":"Point"}
}