{
  "type": "Feature",
  "properties": {
    "iso:country":"AU",
    "sg:address":"U23/ 7 Victoria Ave",
    "sg:city":"Castle Hill",
    "sg:classifiers":[
        {
            "category":"Retail",
            "subcategory":"Car Wash",
            "type":"Services"
        }
    ],
    "sg:phone":"+61 2 9899 1807",
    "sg:postcode":"2154",
    "sg:province":"NSW",
    "sg:tags":[
        "truck",
        "cleaning"
    ],
    "wof:name":"Hills Prestige Car Care Detailing",
    "wof:placetype":"venue"
},
  "geometry": {"coordinates":[150.980743408,-33.7328033447],"type":"Point"}
}