{
  "type": "Feature",
  "properties": {
    "iso:country":"AU",
    "sg:address":"Saviges Rd",
    "sg:city":"Moe",
    "sg:classifiers":[
        {
            "category":"Wholesale",
            "subcategory":"Farm Supplies",
            "type":"Manufacturing & Wholesale Goods"
        }
    ],
    "sg:phone":"+61 3 5127 8044",
    "sg:postcode":"3825",
    "sg:province":"VIC",
    "sg:tags":[
        "equipment"
    ],
    "wof:name":"YGP Grain & Hardware Pty Ltd",
    "wof:placetype":"venue"
},
  "geometry": {"coordinates":[146.25773599999999,-38.175758],"type":"Point"}
}