{
  "type": "Feature",
  "properties": {
    "addr:full":"329 Thomas St Dandenong VIC 3175",
    "addr:housenumber":"329",
    "addr:postcode":"3175",
    "addr:street":"Thomas St",
    "iso:country":"AU",
    "sg:address":"329 Thomas St",
    "sg:city":"Dandenong",
    "sg:classifiers":[
        {
            "category":"Insurance",
            "subcategory":"Hazard Insurance",
            "type":"Services"
        }
    ],
    "sg:phone":"+61 3 9767 3888",
    "sg:postcode":"3175",
    "sg:province":"VIC",
    "sg:tags":[
        "fire",
        "accident",
        "marine"
    ],
    "wof:name":"Zurich Australian Insurance Limited",
    "wof:placetype":"venue"
},
  "geometry": {"coordinates":[145.21220398,-37.984752655],"type":"Point"}
}