{
  "type": "Feature",
  "properties": {
    "iso:country":"AU",
    "sg:address":"333 Station St",
    "sg:city":"Chelsea",
    "sg:classifiers":[
        {
            "category":"Food & Beverages",
            "subcategory":"Bakery",
            "type":"Retail Goods"
        }
    ],
    "sg:phone":"+61 3 9772 3077",
    "sg:postcode":"3196",
    "sg:province":"VIC",
    "sg:tags":[
        "cake",
        "shop",
        "pastry"
    ],
    "wof:name":"Cheesecake Shop The",
    "wof:placetype":"venue"
},
  "geometry": {"coordinates":[145.116744995,-38.052570343],"type":"Point"}
}