{
  "type": "Feature",
  "properties": {
    "iso:country":"AU",
    "sg:address":"26 John Fisher Rd",
    "sg:city":"Belmont North",
    "sg:classifiers":[
        {
            "category":"Social Services",
            "type":"Services"
        }
    ],
    "sg:phone":"+61 2 4945 1292",
    "sg:postcode":"2280",
    "sg:province":"NSW",
    "sg:tags":[
        "disabled",
        "person",
        "equipment"
    ],
    "wof:name":"Surething Marketing",
    "wof:placetype":"venue"
},
  "geometry": {"coordinates":[151.668731689,-33.0226631165],"type":"Point"}
}