{
  "type": "Feature",
  "properties": {
    "addr:full":"73 Auburn St Wollongong NSW 2500",
    "addr:housenumber":"73",
    "addr:postcode":"2500",
    "addr:street":"Auburn St",
    "iso:country":"AU",
    "sg:address":"73 Auburn St",
    "sg:city":"Wollongong",
    "sg:classifiers":[
        {
            "category":"Professional",
            "subcategory":"Accounting & Tax Preparation",
            "type":"Services"
        }
    ],
    "sg:phone":"+61 2 4226 5333",
    "sg:postcode":"2500",
    "sg:province":"NSW",
    "sg:tags":[
        "consultant",
        "taxation"
    ],
    "wof:name":"Michele Dunn",
    "wof:placetype":"venue"
},
  "geometry": {"coordinates":[150.88824500000001,-34.433567],"type":"Point"}
}