{
  "type": "Feature",
  "properties": {
    "addr:full":"10 Winifred St Preston VIC 3072",
    "addr:housenumber":"10",
    "addr:postcode":"3072",
    "addr:street":"Winifred St",
    "iso:country":"AU",
    "sg:address":"10 Winifred St",
    "sg:city":"Preston",
    "sg:classifiers":[
        {
            "category":"Shopping",
            "subcategory":"Stationery & Office Supplies",
            "type":"Retail Goods"
        }
    ],
    "sg:phone":"+61 418 567 245",
    "sg:postcode":"3072",
    "sg:province":"VIC",
    "sg:tags":[
        "partition"
    ],
    "wof:name":"Mojo Interiors By Design",
    "wof:placetype":"venue"
},
  "geometry": {"coordinates":[145.00694274899999,-37.7307777405],"type":"Point"}
}