{
  "type": "Feature",
  "properties": {
    "iso:country":"AU",
    "sg:address":"85 Leicester St",
    "sg:city":"Parkside",
    "sg:classifiers":[
        {
            "category":"Travel",
            "subcategory":"Hotels & Motels",
            "type":"Entertainment"
        }
    ],
    "sg:phone":"+61 8 8271 5700",
    "sg:postcode":"5063",
    "sg:province":"SA",
    "sg:tags":[
        "pub"
    ],
    "wof:name":"Leicester Hotel",
    "wof:placetype":"venue"
},
  "geometry": {"coordinates":[138.6146698,-34.9463768005],"type":"Point"}
}