{
  "type": "Feature",
  "properties": {
    "iso:country":"AU",
    "sg:address":"47 Kiama St",
    "sg:city":"Greystanes",
    "sg:classifiers":[
        {
            "category":"Professional",
            "subcategory":"Engineering",
            "type":"Services"
        }
    ],
    "sg:phone":"+61 2 9896 5522",
    "sg:postcode":"2145",
    "sg:province":"NSW",
    "sg:tags":[
        "consulting",
        "engineer"
    ],
    "wof:name":"Zo Oz Projects",
    "wof:placetype":"venue"
},
  "geometry": {"coordinates":[150.93800354000001,-33.8110923767],"type":"Point"}
}