{
  "type": "Feature",
  "properties": {
    "iso:country":"AU",
    "sg:address":"47 Kingsmill St",
    "sg:city":"Port Hedland",
    "sg:classifiers":[
        {
            "category":"Professional",
            "type":"Services"
        }
    ],
    "sg:phone":"+61 8 9173 2076",
    "sg:postcode":"6721",
    "sg:province":"WA",
    "sg:tags":[
        "auctioneer"
    ],
    "wof:name":"Port Hedland Auction Centre",
    "wof:placetype":"venue"
},
  "geometry": {"coordinates":[118.578552246,-20.3101215363],"type":"Point"}
}