{
  "type": "Feature",
  "properties": {
    "addr:full":"Horsburgh Rd Nyora VIC 3987",
    "addr:postcode":"3987",
    "addr:street":"Horsburgh Rd",
    "iso:country":"AU",
    "sg:address":"Horsburgh Rd",
    "sg:city":"Nyora",
    "sg:classifiers":[
        {
            "category":"Farming",
            "subcategory":"Farm",
            "type":"Manufacturing & Wholesale Goods"
        }
    ],
    "sg:phone":"+61 3 5659 6314",
    "sg:postcode":"3987",
    "sg:province":"VIC",
    "sg:tags":[
        "farmer"
    ],
    "wof:name":"Glover G",
    "wof:placetype":"venue"
},
  "geometry": {"coordinates":[145.67774963400001,-38.3005523682],"type":"Point"}
}