{
  "type": "Feature",
  "properties": {
    "iso:country":"AU",
    "sg:address":"3 Surrey Rd",
    "sg:city":"Keswick",
    "sg:classifiers":[
        {
            "category":"Building & Trades",
            "subcategory":"Construction",
            "type":"Services"
        }
    ],
    "sg:phone":"+61 8 8297 4874",
    "sg:postcode":"5035",
    "sg:province":"SA",
    "sg:tags":[
        "polishing",
        "sanding",
        "floor"
    ],
    "wof:name":"Bretts Floor Sanding",
    "wof:placetype":"venue"
},
  "geometry": {"coordinates":[138.572463989,-34.9423789978],"type":"Point"}
}