{
  "type": "Feature",
  "properties": {
    "iso:country":"AU",
    "sg:address":"675 Glenhuntly Rd",
    "sg:city":"Caulfield South",
    "sg:classifiers":[
        {
            "category":"Shopping",
            "subcategory":"Antiques",
            "type":"Retail Goods"
        }
    ],
    "sg:phone":"+61 3 9528 1483",
    "sg:postcode":"3162",
    "sg:province":"VIC",
    "wof:name":"Town & Country Antiques & Collectables",
    "wof:placetype":"venue"
},
  "geometry": {"coordinates":[145.01754760700001,-37.8861999512],"type":"Point"}
}