{
  "type": "Feature",
  "properties": {
    "iso:country":"AU",
    "sg:address":"56 Willsmere Rd",
    "sg:city":"Kew",
    "sg:classifiers":[
        {
            "category":"Professional",
            "subcategory":"Art Services",
            "type":"Services"
        }
    ],
    "sg:phone":"+61 3 9855 1244",
    "sg:postcode":"3101",
    "sg:province":"VIC",
    "sg:tags":[
        "graphic",
        "designer"
    ],
    "wof:name":"kbr design Pty Ltd",
    "wof:placetype":"venue"
},
  "geometry": {"coordinates":[145.03541564899999,-37.7965545654],"type":"Point"}
}