{
  "type": "Feature",
  "properties": {
    "addr:full":"81 Church St Brighton VIC 3186",
    "addr:housenumber":"81",
    "addr:postcode":"3186",
    "addr:street":"Church St",
    "iso:country":"AU",
    "sg:address":"81 Church St",
    "sg:city":"Brighton",
    "sg:classifiers":[
        {
            "category":"Shopping",
            "subcategory":"Clothing, Apparel, & Fashions",
            "type":"Retail Goods"
        }
    ],
    "sg:phone":"+61 3 9592 4753",
    "sg:postcode":"3186",
    "sg:province":"VIC",
    "sg:tags":[
        "lingerie",
        "hosiery",
        "sleepwear"
    ],
    "wof:name":"Elizabeth Anne Lingerie",
    "wof:placetype":"venue"
},
  "geometry": {"coordinates":[144.99517822300001,-37.9143486023],"type":"Point"}
}