{
  "type": "Feature",
  "properties": {
    "iso:country":"AU",
    "sg:address":"2 Malone Ct",
    "sg:city":"Gosnells",
    "sg:classifiers":[
        {
            "category":"Building & Trades",
            "subcategory":"Cleaning & Sanitation",
            "type":"Services"
        }
    ],
    "sg:phone":"+61 8 9490 9235",
    "sg:postcode":"6110",
    "sg:province":"WA",
    "sg:tags":[
        "industrial",
        "commercial",
        "contractor"
    ],
    "wof:name":"Seven Hill Cleaning Service",
    "wof:placetype":"venue"
},
  "geometry": {"coordinates":[116.004768372,-32.0736885071],"type":"Point"}
}