{
  "type": "Feature",
  "properties": {
    "addr:full":"3/ 46 Abernathy Rd Belmont WA 6104",
    "addr:housenumber":"/ 46",
    "addr:postcode":"6104",
    "addr:street":"Abernathy Rd",
    "iso:country":"AU",
    "sg:address":"3/ 46 Abernathy Rd",
    "sg:city":"Belmont",
    "sg:classifiers":[
        {
            "category":"Professional",
            "subcategory":"Detective & Security Services",
            "type":"Services"
        }
    ],
    "sg:phone":"+61 8 9478 6411",
    "sg:postcode":"6104",
    "sg:province":"WA",
    "sg:tags":[
        "consultant",
        "system"
    ],
    "wof:name":"Electrocraft",
    "wof:placetype":"venue"
},
  "geometry": {"coordinates":[115.919372559,-31.9538993835],"type":"Point"}
}