{
  "type": "Feature",
  "properties": {
    "iso:country":"AU",
    "sg:address":"Kingaroy St",
    "sg:city":"Kingaroy",
    "sg:classifiers":[
        {
            "category":"Travel",
            "subcategory":"Hotels & Motels",
            "type":"Entertainment"
        }
    ],
    "sg:phone":"+61 1800 766 376",
    "sg:postcode":"4610",
    "sg:province":"QLD",
    "wof:name":"Ascot Lodge Motor Inn",
    "wof:placetype":"venue"
},
  "geometry": {"coordinates":[151.83883667000001,-26.5438289642],"type":"Point"}
}