{
  "type": "Feature",
  "properties": {
    "iso:country":"AU",
    "sg:address":"66 Epson Rd",
    "sg:city":"Waterloo",
    "sg:classifiers":[
        {
            "category":"Farming",
            "subcategory":"Farm & Veterinary Services",
            "type":"Manufacturing & Wholesale Goods"
        }
    ],
    "sg:phone":"+61 2 9697 0357",
    "sg:postcode":"2017",
    "sg:province":"NSW",
    "sg:tags":[
        "poultry",
        "processing",
        "supply"
    ],
    "wof:name":"Farmers Best Chickens Pty Ltd",
    "wof:placetype":"venue"
},
  "geometry": {"coordinates":[151.20512390100001,-33.9103736877],"type":"Point"}
}