{
  "type": "Feature",
  "properties": {
    "iso:country":"AU",
    "sg:address":"12 Woorang St",
    "sg:city":"Eastwood",
    "sg:classifiers":[
        {
            "category":"Professional",
            "subcategory":"Printing & Photocopies",
            "type":"Services"
        }
    ],
    "sg:phone":"+61 2 9889 4265",
    "sg:postcode":"2122",
    "sg:province":"NSW",
    "sg:tags":[
        "embroidery"
    ],
    "wof:name":"Sun Embroidery",
    "wof:placetype":"venue"
},
  "geometry": {"coordinates":[151.10240173299999,-33.7890853882],"type":"Point"}
}