{
  "type": "Feature",
  "properties": {
    "iso:country":"AU",
    "sg:address":"603 Richards St",
    "sg:city":"Canadian",
    "sg:classifiers":[
        {
            "category":"Building & Trades",
            "subcategory":"Plumbing",
            "type":"Services"
        }
    ],
    "sg:phone":"+61 408 289 347",
    "sg:postcode":"3350",
    "sg:province":"VIC",
    "sg:tags":[
        "plumber",
        "gasfitters"
    ],
    "wof:name":"Bramble Plumbing",
    "wof:placetype":"venue"
},
  "geometry": {"coordinates":[143.886108,-37.581589],"type":"Point"}
}