{
  "type": "Feature",
  "properties": {
    "addr:full":"5 Haven Crt Werribee VIC 3030",
    "addr:housenumber":"5",
    "addr:postcode":"3030",
    "addr:street":"Haven Crt",
    "iso:country":"AU",
    "sg:address":"5 Haven Crt",
    "sg:city":"Werribee",
    "sg:classifiers":[
        {
            "category":"Retail",
            "subcategory":"Driving School",
            "type":"Services"
        }
    ],
    "sg:phone":"+61 3 9974 0888",
    "sg:postcode":"3030",
    "sg:province":"VIC",
    "wof:name":"Diploma Driving School",
    "wof:placetype":"venue"
},
  "geometry": {"coordinates":[144.66975400000001,-37.900406],"type":"Point"}
}