{
  "type": "Feature",
  "properties": {
    "addr:full":"Pelican St North Ipswich QLD 4305",
    "addr:postcode":"4305",
    "addr:street":"Pelican St",
    "iso:country":"AU",
    "sg:address":"Pelican St",
    "sg:city":"North Ipswich",
    "sg:classifiers":[
        {
            "category":"Sports & Exercise",
            "subcategory":"Playing Field",
            "type":"Entertainment"
        }
    ],
    "sg:phone":"+61 7 3281 6989",
    "sg:postcode":"4305",
    "sg:province":"QLD",
    "sg:tags":[
        "gaming",
        "venue"
    ],
    "wof:name":"Northern Suburbs Leagues Club",
    "wof:placetype":"venue"
},
  "geometry": {"coordinates":[152.76625060999999,-27.6041870117],"type":"Point"}
}