{
  "type": "Feature",
  "properties": {
    "iso:country":"AU",
    "sg:address":"281 Grey St",
    "sg:city":"Glen Innes",
    "sg:classifiers":[
        {
            "category":"Cafe",
            "type":"Food & Drink"
        }
    ],
    "sg:phone":"+61 2 6732 6080",
    "sg:postcode":"2370",
    "sg:province":"NSW",
    "wof:name":"KJ's Popular Cafe",
    "wof:placetype":"venue"
},
  "geometry": {"coordinates":[151.73617553700001,-29.7359142303],"type":"Point"}
}