{
  "type": "Feature",
  "properties": {
    "iso:country":"AU",
    "sg:address":"21 School Drv",
    "sg:city":"Tomago",
    "sg:classifiers":[
        {
            "category":"Retail",
            "subcategory":"Auto Repair",
            "type":"Services"
        }
    ],
    "sg:phone":"+61 2 4964 0400",
    "sg:postcode":"2322",
    "sg:province":"NSW",
    "sg:tags":[
        "body",
        "builder",
        "motor"
    ],
    "wof:name":"Varley Specialised Vehicles",
    "wof:placetype":"venue"
},
  "geometry": {"coordinates":[151.72894287099999,-32.830871582],"type":"Point"}
}