{
  "type": "Feature",
  "properties": {
    "iso:country":"AU",
    "sg:address":"295 Bay St",
    "sg:city":"Brighton-le-Sands",
    "sg:classifiers":[
        {
            "category":"Cafe",
            "type":"Food & Drink"
        }
    ],
    "sg:phone":"+61 2 9567 8657",
    "sg:postcode":"2216",
    "sg:province":"NSW",
    "wof:name":"Bay Espresso",
    "wof:placetype":"venue"
},
  "geometry": {"coordinates":[151.15377799999999,-33.959976],"type":"Point"}
}