{
  "type": "Feature",
  "properties": {
    "iso:country":"AU",
    "sg:address":"Lvl 8, 128 Marsden St",
    "sg:city":"Parramatta",
    "sg:classifiers":[
        {
            "category":"Real Estate",
            "subcategory":"Surveying",
            "type":"Services"
        }
    ],
    "sg:phone":"+61 2 9633 2277",
    "sg:postcode":"2150",
    "sg:province":"NSW",
    "sg:tags":[
        "surveyor",
        "land"
    ],
    "wof:name":"Bowdens Group",
    "wof:placetype":"venue"
},
  "geometry": {"coordinates":[151.00097656200001,-33.816608429],"type":"Point"}
}