{
  "type": "Feature",
  "properties": {
    "addr:full":"7 Broadbent St Scullin ACT 2614",
    "addr:housenumber":"7",
    "addr:postcode":"2614",
    "addr:street":"Broadbent St",
    "iso:country":"AU",
    "sg:address":"7 Broadbent St",
    "sg:city":"Scullin",
    "sg:classifiers":[
        {
            "category":"Real Estate",
            "subcategory":"Architect",
            "type":"Services"
        }
    ],
    "sg:phone":"+61 2 6278 3055",
    "sg:postcode":"2614",
    "sg:province":"ACT",
    "wof:name":"Wombey & Godfrey Architects",
    "wof:placetype":"venue"
},
  "geometry": {"coordinates":[149.04029846200001,-35.2386627197],"type":"Point"}
}