{
  "type": "Feature",
  "properties": {
    "addr:full":"639 Main Rd Ballarat VIC 3350",
    "addr:housenumber":"639",
    "addr:postcode":"3350",
    "addr:street":"Main Rd",
    "iso:country":"AU",
    "sg:address":"639 Main Rd",
    "sg:city":"Ballarat",
    "sg:classifiers":[
        {
            "category":"Travel",
            "subcategory":"Hotels & Motels",
            "type":"Entertainment"
        }
    ],
    "sg:phone":"+61 3 5333 5955",
    "sg:postcode":"3350",
    "sg:province":"VIC",
    "sg:tags":[
        "accommodation"
    ],
    "wof:name":"Zagames Ballarat Hotel",
    "wof:placetype":"venue"
},
  "geometry": {"coordinates":[143.864777,-37.563141],"type":"Point"}
}