{
  "type": "Feature",
  "properties": {
    "iso:country":"AU",
    "sg:address":"Level 3, 39 Park St",
    "sg:city":"South Melbourne",
    "sg:classifiers":[
        {
            "category":"Professional",
            "subcategory":"Computer Services",
            "type":"Services"
        }
    ],
    "sg:phone":"+61 3 8695 3600",
    "sg:postcode":"3205",
    "sg:province":"VIC",
    "sg:tags":[
        "consultant",
        "system"
    ],
    "wof:name":"Volante Solutions",
    "wof:placetype":"venue"
},
  "geometry": {"coordinates":[144.969131,-37.833164],"type":"Point"}
}