{
  "type": "Feature",
  "properties": {
    "addr:full":"157 Mort St Lithgow NSW 2790",
    "addr:housenumber":"157",
    "addr:postcode":"2790",
    "addr:street":"Mort St",
    "iso:country":"AU",
    "sg:address":"157 Mort St",
    "sg:city":"Lithgow",
    "sg:classifiers":[
        {
            "category":"Retail",
            "subcategory":"Funeral Services",
            "type":"Services"
        }
    ],
    "sg:phone":"+61 2 6351 2661",
    "sg:postcode":"2790",
    "sg:province":"NSW",
    "sg:tags":[
        "director"
    ],
    "wof:name":"Wood & Wood",
    "wof:placetype":"venue"
},
  "geometry": {"coordinates":[150.15951538100001,-33.4814071655],"type":"Point"}
}