{
  "type": "Feature",
  "properties": {
    "addr:full":"472 Pacific Hwy St Leonards NSW 2065",
    "addr:housenumber":"472",
    "addr:postcode":"2065",
    "addr:street":"Pacific Hwy",
    "iso:country":"AU",
    "sg:address":"472 Pacific Hwy",
    "sg:city":"St Leonards",
    "sg:classifiers":[
        {
            "category":"Professional",
            "subcategory":"Engineering",
            "type":"Services"
        }
    ],
    "sg:phone":"+61 2 9925 6666",
    "sg:postcode":"2065",
    "sg:province":"NSW",
    "sg:tags":[
        "civil",
        "engineer"
    ],
    "wof:name":"Leighton Contractors Central Engineering",
    "wof:placetype":"venue"
},
  "geometry": {"coordinates":[151.19749450699999,-33.8243255615],"type":"Point"}
}