{
  "type": "Feature",
  "properties": {
    "iso:country":"AU",
    "sg:address":"52 High St",
    "sg:city":"Oatlands",
    "sg:classifiers":[
        {
            "category":"Autos & Motor Vehicles",
            "subcategory":"Fuel & Gas Station",
            "type":"Retail Goods"
        }
    ],
    "sg:phone":"+61 3 6254 1533",
    "sg:postcode":"7120",
    "sg:province":"TAS",
    "wof:name":"BP",
    "wof:placetype":"venue"
},
  "geometry": {"coordinates":[147.369430542,-42.3010559082],"type":"Point"}
}