{
  "type": "Feature",
  "properties": {
    "addr:full":"192 Merrylands Rd Merrylands NSW 2160",
    "addr:housenumber":"192",
    "addr:postcode":"2160",
    "addr:street":"Merrylands Rd",
    "iso:country":"AU",
    "sg:address":"192 Merrylands Rd",
    "sg:city":"Merrylands",
    "sg:classifiers":[
        {
            "category":"Shopping",
            "subcategory":"Shoes",
            "type":"Retail Goods"
        }
    ],
    "sg:phone":"+61 2 9637 0592",
    "sg:postcode":"2160",
    "sg:province":"NSW",
    "sg:tags":[
        "footwear"
    ],
    "wof:name":"Allstyle Shoe Warehouse",
    "wof:placetype":"venue"
},
  "geometry": {"coordinates":[150.989471436,-33.8365287781],"type":"Point"}
}