{
  "type": "Feature",
  "properties": {
    "addr:full":"5 Lennox St Moorabbin VIC 3189",
    "addr:housenumber":"5",
    "addr:postcode":"3189",
    "addr:street":"Lennox St",
    "iso:country":"AU",
    "sg:address":"5 Lennox St",
    "sg:city":"Moorabbin",
    "sg:classifiers":[
        {
            "category":"Shopping",
            "subcategory":"Jewelry",
            "type":"Retail Goods"
        }
    ],
    "sg:phone":"+61 3 9553 1660",
    "sg:postcode":"3189",
    "sg:province":"VIC",
    "sg:tags":[
        "fashion",
        "jewellery"
    ],
    "wof:name":"John D.Francis & Assoc",
    "wof:placetype":"venue"
},
  "geometry": {"coordinates":[145.06573486299999,-37.9420127869],"type":"Point"}
}