{
  "type": "Feature",
  "properties": {
    "addr:full":"22 Scott St Kew VIC 3101",
    "addr:housenumber":"22",
    "addr:postcode":"3101",
    "addr:street":"Scott St",
    "iso:country":"AU",
    "sg:address":"22 Scott St",
    "sg:city":"Kew",
    "sg:classifiers":[
        {
            "category":"Health Services",
            "subcategory":"Doctor",
            "type":"Services"
        }
    ],
    "sg:phone":"+61 3 9818 5088",
    "sg:postcode":"3101",
    "sg:province":"VIC",
    "sg:tags":[
        "medical",
        "practitioner"
    ],
    "wof:name":"Buckle Louise G",
    "wof:placetype":"venue"
},
  "geometry": {"coordinates":[145.04234314000001,-37.8113288879],"type":"Point"}
}