{
  "type": "Feature",
  "properties": {
    "addr:full":"2/ 1825 Ferntree Gully Rd Ferntree Gully VIC 3156",
    "addr:housenumber":"/ 1825",
    "addr:postcode":"3156",
    "addr:street":"Ferntree Gully Rd",
    "iso:country":"AU",
    "sg:address":"2/ 1825 Ferntree Gully Rd",
    "sg:city":"Ferntree Gully",
    "sg:classifiers":[
        {
            "category":"Structure",
            "subcategory":"Office Building",
            "type":"Public Place"
        }
    ],
    "sg:phone":"+61 3 9752 3001",
    "sg:postcode":"3156",
    "sg:province":"VIC",
    "sg:tags":[
        "serviced"
    ],
    "wof:name":"Burdens Serviced Offices",
    "wof:placetype":"venue"
},
  "geometry": {"coordinates":[145.26995849599999,-37.8838005066],"type":"Point"}
}