{
  "type": "Feature",
  "properties": {
    "addr:full":"2 Hollyberry St Eight Mile Plains QLD 4113",
    "addr:housenumber":"2",
    "addr:postcode":"4113",
    "addr:street":"Hollyberry St",
    "iso:country":"AU",
    "sg:address":"2 Hollyberry St",
    "sg:city":"Eight Mile Plains",
    "sg:classifiers":[
        {
            "category":"Wholesale",
            "subcategory":"Machinery & Supplies",
            "type":"Manufacturing & Wholesale Goods"
        }
    ],
    "sg:phone":"+61 7 3219 8134",
    "sg:postcode":"4113",
    "sg:province":"QLD",
    "sg:tags":[
        "process",
        "instrument",
        "control"
    ],
    "wof:name":"GCIC Pty Limited",
    "wof:placetype":"venue"
},
  "geometry": {"coordinates":[153.09248352,-27.5892429352],"type":"Point"}
}