{
  "type": "Feature",
  "properties": {
    "addr:full":"4 Windsor Rd Kellyville NSW 2153",
    "addr:housenumber":"4",
    "addr:postcode":"2153",
    "addr:street":"Windsor Rd",
    "iso:country":"AU",
    "sg:address":"4 Windsor Rd",
    "sg:city":"Kellyville",
    "sg:classifiers":[
        {
            "category":"Health Services",
            "subcategory":"Chiropractor",
            "type":"Services"
        }
    ],
    "sg:phone":"+61 2 9629 1717",
    "sg:postcode":"2153",
    "sg:province":"NSW",
    "wof:name":"Kellyville Chiropractic",
    "wof:placetype":"venue"
},
  "geometry": {"coordinates":[150.99746704099999,-33.7665596008],"type":"Point"}
}