{
  "type": "Feature",
  "properties": {
    "iso:country":"AU",
    "sg:address":"Tor St",
    "sg:city":"Gundagai",
    "sg:classifiers":[
        {
            "category":"Health Services",
            "subcategory":"Hospital",
            "type":"Services"
        }
    ],
    "sg:phone":"+61 13 12 33",
    "sg:postcode":"2722",
    "sg:province":"NSW",
    "sg:tags":[
        "ambulance"
    ],
    "wof:name":"Ambulance Service of NSW",
    "wof:placetype":"venue"
},
  "geometry": {"coordinates":[148.101715,-35.058002],"type":"Point"}
}