{
  "type": "Feature",
  "properties": {
    "iso:country":"AU",
    "sg:address":"Level 2 18 Elizabeth St",
    "sg:city":"Hobart",
    "sg:classifiers":[
        {
            "category":"Health Services",
            "subcategory":"Doctor",
            "type":"Services"
        }
    ],
    "sg:phone":"+61 3 6224 0899",
    "sg:postcode":"7000",
    "sg:province":"TAS",
    "sg:tags":[
        "medical",
        "practitioner"
    ],
    "wof:name":"Medical Defence Association Of Victoria Limited The",
    "wof:placetype":"venue"
},
  "geometry": {"coordinates":[147.329986572,-42.8827476501],"type":"Point"}
}