{
  "type": "Feature",
  "properties": {
    "addr:full":"Discovery Drv Thornlie WA 6108",
    "addr:postcode":"6108",
    "addr:street":"Discovery Drv",
    "iso:country":"AU",
    "sg:address":"Discovery Drv",
    "sg:city":"Thornlie",
    "sg:classifiers":[
        {
            "category":"Education",
            "subcategory":"Kindergarten",
            "type":"Public Place"
        }
    ],
    "sg:phone":"+61 8 9459 7222",
    "sg:postcode":"6108",
    "sg:province":"WA",
    "sg:tags":[
        "pre-schools"
    ],
    "wof:name":"Catholic Church",
    "wof:placetype":"venue"
},
  "geometry": {"coordinates":[115.95778656,-32.0674057007],"type":"Point"}
}