{
  "type": "Feature",
  "properties": {
    "iso:country":"AU",
    "sg:address":"515 Alderley St",
    "sg:city":"Toowoomba",
    "sg:classifiers":[
        {
            "category":"Shopping",
            "subcategory":"Computers & Home Electronics",
            "type":"Retail Goods"
        }
    ],
    "sg:phone":"+61 7 4636 4625",
    "sg:postcode":"4350",
    "sg:province":"QLD",
    "sg:tags":[
        "small",
        "equipment",
        "business"
    ],
    "wof:name":"Independent Computer Retailers Pty. Ltd.",
    "wof:placetype":"venue"
},
  "geometry": {"coordinates":[151.922195,-27.580921],"type":"Point"}
}