{
  "type": "Feature",
  "properties": {
    "iso:country":"AU",
    "sg:address":"102 Munro St",
    "sg:city":"Babinda",
    "sg:classifiers":[
        {
            "category":"Personal",
            "subcategory":"Beauty Salon",
            "type":"Services"
        }
    ],
    "sg:phone":"+61 7 4067 1414",
    "sg:postcode":"4861",
    "sg:province":"QLD",
    "sg:tags":[
        "hairdresser"
    ],
    "wof:name":"The Hair Barrack's",
    "wof:placetype":"venue"
},
  "geometry": {"coordinates":[145.92002868599999,-17.3436279297],"type":"Point"}
}