{
  "type": "Feature",
  "properties": {
    "iso:country":"AU",
    "sg:address":"44 Hamilton St",
    "sg:city":"Mont Albert",
    "sg:classifiers":[
        {
            "category":"Retail",
            "subcategory":"Laundry & Dry Cleaning",
            "type":"Services"
        }
    ],
    "sg:phone":"+61 3 9890 1177",
    "sg:postcode":"3127",
    "sg:province":"VIC",
    "wof:name":"Mont Albert Laundromat & Dry Cleaners",
    "wof:placetype":"venue"
},
  "geometry": {"coordinates":[145.105377197,-37.8200874329],"type":"Point"}
}