{
  "type": "Feature",
  "properties": {
    "addr:full":"974 South Rd Edwardstown SA 5039",
    "addr:housenumber":"974",
    "addr:postcode":"5039",
    "addr:street":"South Rd",
    "iso:country":"AU",
    "sg:address":"974 South Rd",
    "sg:city":"Edwardstown",
    "sg:classifiers":[
        {
            "category":"Organizations",
            "subcategory":"Community Association",
            "type":"Services"
        }
    ],
    "sg:phone":"+61 8 8293 1877",
    "sg:postcode":"5039",
    "sg:province":"SA",
    "sg:tags":[
        "organisation",
        "family",
        "welfare"
    ],
    "wof:name":"St Vincent De Paul Society",
    "wof:placetype":"venue"
},
  "geometry": {"coordinates":[138.57363891599999,-34.979221344],"type":"Point"}
}