{
  "type": "Feature",
  "properties": {
    "addr:full":"185 Hoskins St Temora NSW 2666",
    "addr:housenumber":"185",
    "addr:postcode":"2666",
    "addr:street":"Hoskins St",
    "iso:country":"AU",
    "sg:address":"185 Hoskins St",
    "sg:city":"Temora",
    "sg:classifiers":[
        {
            "category":"Professional",
            "subcategory":"Accounting & Tax Preparation",
            "type":"Services"
        }
    ],
    "sg:phone":"+61 2 6977 1194",
    "sg:postcode":"2666",
    "sg:province":"NSW",
    "sg:tags":[
        "consultant",
        "taxation"
    ],
    "wof:name":"Colin G McCrone & Co",
    "wof:placetype":"venue"
},
  "geometry": {"coordinates":[147.533599853,-34.4467544556],"type":"Point"}
}