{
  "type": "Feature",
  "properties": {
    "addr:full":"9 Sandeland Ave Mandurah WA 6210",
    "addr:housenumber":"9",
    "addr:postcode":"6210",
    "addr:street":"Sandeland Ave",
    "iso:country":"AU",
    "sg:address":"9 Sandeland Ave",
    "sg:city":"Mandurah",
    "sg:classifiers":[
        {
            "category":"Retail",
            "subcategory":"Auto Repair",
            "type":"Services"
        }
    ],
    "sg:phone":"+61 419 831 788",
    "sg:postcode":"6210",
    "sg:province":"WA",
    "sg:tags":[
        "repairer",
        "motor",
        "engineer"
    ],
    "wof:name":"Freedom Mobile Mechanics",
    "wof:placetype":"venue"
},
  "geometry": {"coordinates":[115.74266799999999,-32.543495],"type":"Point"}
}