{
  "type": "Feature",
  "properties": {
    "iso:country":"AU",
    "sg:address":"25 Derwent Park Rd",
    "sg:city":"North Hobart",
    "sg:classifiers":[
        {
            "category":"Professional",
            "subcategory":"Detective & Security Services",
            "type":"Services"
        }
    ],
    "sg:phone":"+61 1300 304 400",
    "sg:postcode":"7000",
    "sg:province":"TAS",
    "sg:tags":[
        "consultant",
        "system"
    ],
    "wof:name":"CopyVision",
    "wof:placetype":"venue"
},
  "geometry": {"coordinates":[147.31809997600001,-42.8742141724],"type":"Point"}
}