{
  "type": "Feature",
  "properties": {
    "addr:full":"25 Wattle St Ascot QLD 4007",
    "addr:housenumber":"25",
    "addr:postcode":"4007",
    "addr:street":"Wattle St",
    "iso:country":"AU",
    "sg:address":"25 Wattle St",
    "sg:city":"Ascot",
    "sg:classifiers":[
        {
            "category":"Professional",
            "subcategory":"Management & Consulting",
            "type":"Services"
        }
    ],
    "sg:phone":"+61 7 3262 4909",
    "sg:postcode":"4007",
    "sg:province":"QLD",
    "sg:tags":[
        "consultant"
    ],
    "wof:name":"Sandford & Associates",
    "wof:placetype":"venue"
},
  "geometry": {"coordinates":[153.06205700000001,-27.424753],"type":"Point"}
}