{
  "type": "Feature",
  "properties": {
    "addr:full":"43 Jacka Blv St Kilda VIC 3182",
    "addr:housenumber":"43",
    "addr:postcode":"3182",
    "addr:street":"Jacka Blv",
    "iso:country":"AU",
    "sg:address":"43 Jacka Blv",
    "sg:city":"St Kilda",
    "sg:classifiers":[
        {
            "category":"Arena",
            "subcategory":"Sports Club",
            "type":"Entertainment"
        }
    ],
    "sg:phone":"+61 3 9534 4465",
    "sg:postcode":"3182",
    "sg:province":"VIC",
    "sg:tags":[
        "life",
        "surfing",
        "saving"
    ],
    "wof:name":"St Kilda Life Saving Club",
    "wof:placetype":"venue"
},
  "geometry": {"coordinates":[144.975372314,-37.8688354492],"type":"Point"}
}