{
  "type": "Feature",
  "properties": {
    "addr:full":"411 West Botany St Botany NSW 2019",
    "addr:housenumber":"411",
    "addr:postcode":"2019",
    "addr:street":"West Botany St",
    "iso:country":"AU",
    "sg:address":"411 West Botany St",
    "sg:city":"Botany",
    "sg:classifiers":[
        {
            "category":"Home & Garden",
            "subcategory":"Furniture",
            "type":"Retail Goods"
        }
    ],
    "sg:phone":"+61 1300 301 254",
    "sg:postcode":"2019",
    "sg:province":"NSW",
    "sg:tags":[
        "outdoor"
    ],
    "wof:name":"Naume Holdings Pty Ltd",
    "wof:placetype":"venue"
},
  "geometry": {"coordinates":[151.19543457,-33.9424095154],"type":"Point"}
}