{
  "type": "Feature",
  "properties": {
    "addr:full":"Shp5/ 207 Jones St Balcatta WA 6021",
    "addr:housenumber":"207",
    "addr:postcode":"6021",
    "addr:street":"Jones St",
    "iso:country":"AU",
    "sg:address":"Shp5/ 207 Jones St",
    "sg:city":"Balcatta",
    "sg:classifiers":[
        {
            "category":"Manufacturing",
            "subcategory":"Food",
            "type":"Manufacturing & Wholesale Goods"
        }
    ],
    "sg:phone":"+61 8 9349 9449",
    "sg:postcode":"6021",
    "sg:province":"WA",
    "sg:tags":[
        "function",
        "catering"
    ],
    "wof:name":"Curry Corner",
    "wof:placetype":"venue"
},
  "geometry": {"coordinates":[115.820640564,-31.8716106415],"type":"Point"}
}