{
  "type": "Feature",
  "properties": {
    "addr:full":"2 Middleton St Ashmore QLD 4214",
    "addr:housenumber":"2",
    "addr:postcode":"4214",
    "addr:street":"Middleton St",
    "iso:country":"AU",
    "sg:address":"2 Middleton St",
    "sg:city":"Ashmore",
    "sg:classifiers":[
        {
            "category":"Retail",
            "subcategory":"Storage",
            "type":"Services"
        }
    ],
    "sg:phone":"+61 1300 790 246",
    "sg:postcode":"4214",
    "sg:province":"QLD",
    "wof:name":"Ausdoc Information Management",
    "wof:placetype":"venue"
},
  "geometry": {"coordinates":[153.39143371599999,-27.9808292389],"type":"Point"}
}