{
  "type": "Feature",
  "properties": {
    "addr:full":"122 Main Hurstbridge Rd Diamond Creek VIC 3089",
    "addr:housenumber":"122",
    "addr:postcode":"3089",
    "addr:street":"Main Hurstbridge Rd",
    "iso:country":"AU",
    "sg:address":"122 Main Hurstbridge Rd",
    "sg:city":"Diamond Creek",
    "sg:classifiers":[
        {
            "category":"Health Services",
            "subcategory":"Chiropractor",
            "type":"Services"
        }
    ],
    "sg:phone":"+61 3 9438 1412",
    "sg:postcode":"3089",
    "sg:province":"VIC",
    "wof:name":"Turley Kevin Dr",
    "wof:placetype":"venue"
},
  "geometry": {"coordinates":[145.16444397000001,-37.6749382019],"type":"Point"}
}