{
  "type": "Feature",
  "properties": {
    "addr:full":"1 Development Crt Caloundra QLD 4551",
    "addr:housenumber":"1",
    "addr:postcode":"4551",
    "addr:street":"Development Crt",
    "iso:country":"AU",
    "sg:address":"1 Development Crt",
    "sg:city":"Caloundra",
    "sg:classifiers":[
        {
            "category":"Home & Garden",
            "subcategory":"Building Materials",
            "type":"Retail Goods"
        }
    ],
    "sg:phone":"+61 7 5499 6889",
    "sg:postcode":"4551",
    "sg:province":"QLD",
    "sg:tags":[
        "secondhand"
    ],
    "wof:name":"Caloundra Demolition & Salvage",
    "wof:placetype":"venue"
},
  "geometry": {"coordinates":[153.116653442,-26.7962875366],"type":"Point"}
}