{
  "type": "Feature",
  "properties": {
    "addr:full":"71 Commercial Rd Port Adelaide SA 5015",
    "addr:housenumber":"71",
    "addr:postcode":"5015",
    "addr:street":"Commercial Rd",
    "iso:country":"AU",
    "sg:address":"71 Commercial Rd",
    "sg:city":"Port Adelaide",
    "sg:classifiers":[
        {
            "category":"Real Estate",
            "subcategory":"Real Estate Agent",
            "type":"Services"
        }
    ],
    "sg:phone":"+61 8 8200 9888",
    "sg:postcode":"5015",
    "sg:province":"SA",
    "wof:name":"Toop & Toop",
    "wof:placetype":"venue"
},
  "geometry": {"coordinates":[138.50572204599999,-34.844417572],"type":"Point"}
}