{
  "type": "Feature",
  "properties": {
    "addr:full":"78 Station Rd Bethania QLD 4205",
    "addr:housenumber":"78",
    "addr:postcode":"4205",
    "addr:street":"Station Rd",
    "iso:country":"AU",
    "sg:address":"78 Station Rd",
    "sg:city":"Bethania",
    "sg:classifiers":[
        {
            "category":"Health Services",
            "subcategory":"Health Practitioner",
            "type":"Services"
        }
    ],
    "sg:phone":"+61 7 3200 4100",
    "sg:postcode":"4205",
    "sg:province":"QLD",
    "sg:tags":[
        "alternative"
    ],
    "wof:name":"Brian Morley",
    "wof:placetype":"venue"
},
  "geometry": {"coordinates":[153.15721130399999,-27.6880168915],"type":"Point"}
}