{
  "type": "Feature",
  "properties": {
    "addr:full":"80b Main Rd Monbulk VIC 3793",
    "addr:housenumber":"80b",
    "addr:postcode":"3793",
    "addr:street":"Main Rd",
    "iso:country":"AU",
    "sg:address":"80b Main Rd",
    "sg:city":"Monbulk",
    "sg:classifiers":[
        {
            "category":"Deli",
            "type":"Food & Drink"
        }
    ],
    "sg:phone":"+61 3 9756 7802",
    "sg:postcode":"3793",
    "sg:province":"VIC",
    "sg:tags":[
        "delicatessen"
    ],
    "wof:name":"Blue Gum Deli",
    "wof:placetype":"venue"
},
  "geometry": {"coordinates":[145.33265685999999,-37.9050788879],"type":"Point"}
}