{
  "type": "Feature",
  "properties": {
    "addr:full":"224 Bluff Rd Sandringham VIC 3191",
    "addr:housenumber":"224",
    "addr:postcode":"3191",
    "addr:street":"Bluff Rd",
    "iso:country":"AU",
    "sg:address":"224 Bluff Rd",
    "sg:city":"Sandringham",
    "sg:classifiers":[
        {
            "category":"Building & Trades",
            "subcategory":"Construction",
            "type":"Services"
        }
    ],
    "sg:phone":"+61 3 9533 4291",
    "sg:postcode":"3191",
    "sg:province":"VIC",
    "sg:tags":[
        "contractor"
    ],
    "wof:name":"Byde Constructions Pty Ltd",
    "wof:placetype":"venue"
},
  "geometry": {"coordinates":[145.019622803,-37.959602356],"type":"Point"}
}