{
  "type": "Feature",
  "properties": {
    "addr:full":"3 Gavin St Norlane VIC 3214",
    "addr:housenumber":"3",
    "addr:postcode":"3214",
    "addr:street":"Gavin St",
    "iso:country":"AU",
    "sg:address":"3 Gavin St",
    "sg:city":"Norlane",
    "sg:classifiers":[
        {
            "category":"Home & Garden",
            "subcategory":"Carpets & Floor Coverings",
            "type":"Retail Goods"
        }
    ],
    "sg:phone":"+61 3 5278 6232",
    "sg:postcode":"3214",
    "sg:province":"VIC",
    "sg:tags":[
        "tile",
        "wall",
        "layer"
    ],
    "wof:name":"Pauls Tiling Service",
    "wof:placetype":"venue"
},
  "geometry": {"coordinates":[144.35902404800001,-38.0968208313],"type":"Point"}
}