{
  "type": "Feature",
  "properties": {
    "iso:country":"AU",
    "sg:address":"74 Tingal Rd",
    "sg:city":"Wynnum",
    "sg:classifiers":[
        {
            "category":"Education",
            "subcategory":"School",
            "type":"Public Place"
        }
    ],
    "sg:phone":"+61 7 3396 4825",
    "sg:postcode":"4178",
    "sg:province":"QLD",
    "sg:tags":[
        "supply"
    ],
    "wof:name":"Bayside School Supplies",
    "wof:placetype":"venue"
},
  "geometry": {"coordinates":[153.17250060999999,-27.4471244812],"type":"Point"}
}