{
  "type": "Feature",
  "properties": {
    "iso:country":"AU",
    "sg:address":"Shop 6/ 92 Hampton Drv",
    "sg:city":"Tannum Sands",
    "sg:classifiers":[
        {
            "category":"Shopping",
            "subcategory":"Clothing, Apparel, & Fashions",
            "type":"Retail Goods"
        }
    ],
    "sg:phone":"+61 7 4973 7370",
    "sg:postcode":"4680",
    "sg:province":"QLD",
    "sg:tags":[
        "boutique"
    ],
    "wof:name":"Coastline",
    "wof:placetype":"venue"
},
  "geometry": {"coordinates":[151.36845398,-23.9501571655],"type":"Point"}
}