{
  "type": "Feature",
  "properties": {
    "addr:full":"120 Parasol St Ashmore QLD 4214",
    "addr:housenumber":"120",
    "addr:postcode":"4214",
    "addr:street":"Parasol St",
    "iso:country":"AU",
    "sg:address":"120 Parasol St",
    "sg:city":"Ashmore",
    "sg:classifiers":[
        {
            "category":"Professional",
            "subcategory":"Art Services",
            "type":"Services"
        }
    ],
    "sg:phone":"+61 417 759 885",
    "sg:postcode":"4214",
    "sg:province":"QLD",
    "sg:tags":[
        "decorator",
        "painter"
    ],
    "wof:name":"Fine Edge",
    "wof:placetype":"venue"
},
  "geometry": {"coordinates":[153.38835144000001,-27.9885005951],"type":"Point"}
}