{
  "type": "Feature",
  "properties": {
    "iso:country":"AU",
    "sg:address":"18 Streeton Rd",
    "sg:city":"Bayswater",
    "sg:classifiers":[
        {
            "category":"Building & Trades",
            "subcategory":"Cleaning & Sanitation",
            "type":"Services"
        }
    ],
    "sg:phone":"+61 3 9720 4383",
    "sg:postcode":"3153",
    "sg:province":"VIC",
    "sg:tags":[
        "industrial",
        "commercial",
        "contractor"
    ],
    "wof:name":"Barrs Cleaning & Maintenance",
    "wof:placetype":"venue"
},
  "geometry": {"coordinates":[145.28492736800001,-37.8364105225],"type":"Point"}
}