{
  "type": "Feature",
  "properties": {
    "iso:country":"AU",
    "sg:address":"79 Kite St",
    "sg:city":"Orange",
    "sg:classifiers":[
        {
            "category":"Organizations",
            "subcategory":"Community Association",
            "type":"Services"
        }
    ],
    "sg:phone":"+61 2 6361 2339",
    "sg:postcode":"2800",
    "sg:province":"NSW",
    "sg:tags":[
        "organisation",
        "family",
        "welfare"
    ],
    "wof:name":"Central Tablelands Housing Association Inc",
    "wof:placetype":"venue"
},
  "geometry": {"coordinates":[149.09710693400001,-33.2851600647],"type":"Point"}
}