{
  "type": "Feature",
  "properties": {
    "iso:country":"AU",
    "sg:address":"William St",
    "sg:city":"Bankstown",
    "sg:classifiers":[
        {
            "category":"Education",
            "subcategory":"School",
            "type":"Public Place"
        }
    ],
    "sg:phone":"+61 2 9790 6158",
    "sg:postcode":"2200",
    "sg:province":"NSW",
    "sg:tags":[
        "state",
        "-",
        "nsw"
    ],
    "wof:name":"Bankstown West Public School",
    "wof:placetype":"venue"
},
  "geometry": {"coordinates":[151.01829499999999,-33.917755],"type":"Point"}
}