{
  "type": "Feature",
  "properties": {
    "addr:full":"PO Box 3774 Loganholme QLD 4129",
    "addr:postcode":"4129",
    "iso:country":"AU",
    "sg:address":"PO Box 3774",
    "sg:city":"Loganholme",
    "sg:classifiers":[
        {
            "category":"Personal",
            "subcategory":"Massage",
            "type":"Services"
        }
    ],
    "sg:phone":"+61 7 3245 6881",
    "sg:postcode":"4129",
    "sg:province":"QLD",
    "sg:tags":[
        "therapy"
    ],
    "wof:name":"4mums2B",
    "wof:placetype":"venue"
},
  "geometry": {"coordinates":[153.185791016,-27.6725502014],"type":"Point"}
}