{
  "type": "Feature",
  "properties": {
    "iso:country":"AU",
    "sg:address":"Unit 3/ 10 Pacific Ave",
    "sg:city":"Miami",
    "sg:classifiers":[
        {
            "category":"Professional",
            "subcategory":"Detective & Security Services",
            "type":"Services"
        }
    ],
    "sg:phone":"+61 7 5526 6622",
    "sg:postcode":"4220",
    "sg:province":"QLD",
    "sg:tags":[
        "consultant",
        "system"
    ],
    "wof:name":"Gold Coast Guards",
    "wof:placetype":"venue"
},
  "geometry": {"coordinates":[153.43734741200001,-28.0635623932],"type":"Point"}
}