{
  "type": "Feature",
  "properties": {
    "addr:full":"35 Gladstone St Glenrowan VIC 3675",
    "addr:housenumber":"35",
    "addr:postcode":"3675",
    "addr:street":"Gladstone St",
    "iso:country":"AU",
    "sg:address":"35 Gladstone St",
    "sg:city":"Glenrowan",
    "sg:classifiers":[
        {
            "category":"Communications",
            "subcategory":"News Services",
            "type":"Services"
        }
    ],
    "sg:phone":"+61 3 5766 2448",
    "sg:postcode":"3675",
    "sg:province":"VIC",
    "sg:tags":[
        "information",
        "tourist",
        "attractions"
    ],
    "wof:name":"Kates Cottage Gifts & Souvenirs Homestead & Museum",
    "wof:placetype":"venue"
},
  "geometry": {"coordinates":[146.22148100000001,-36.463894],"type":"Point"}
}