{
  "type": "Feature",
  "properties": {
    "addr:full":"871 Wynnum Rd Cannon Hill QLD 4170",
    "addr:housenumber":"871",
    "addr:postcode":"4170",
    "addr:street":"Wynnum Rd",
    "iso:country":"AU",
    "sg:address":"871 Wynnum Rd",
    "sg:city":"Cannon Hill",
    "sg:classifiers":[
        {
            "category":"Autos & Motor Vehicles",
            "subcategory":"Automobile Sales",
            "type":"Retail Goods"
        }
    ],
    "sg:phone":"+61 7 3395 6040",
    "sg:postcode":"4170",
    "sg:province":"QLD",
    "sg:tags":[
        "car",
        "used"
    ],
    "wof:name":"Dave George Cars",
    "wof:placetype":"venue"
},
  "geometry": {"coordinates":[153.07992553700001,-27.4671802521],"type":"Point"}
}