{
  "type": "Feature",
  "properties": {
    "addr:full":"161 Richardson St Boulder WA 6432",
    "addr:housenumber":"161",
    "addr:postcode":"6432",
    "addr:street":"Richardson St",
    "iso:country":"AU",
    "sg:address":"161 Richardson St",
    "sg:city":"Boulder",
    "sg:classifiers":[
        {
            "category":"Building & Trades",
            "subcategory":"Construction",
            "type":"Services"
        }
    ],
    "sg:phone":"+61 8 9093 0666",
    "sg:postcode":"6432",
    "sg:province":"WA",
    "sg:tags":[
        "welding"
    ],
    "wof:name":"Gregory Welding Services",
    "wof:placetype":"venue"
},
  "geometry": {"coordinates":[121.48416137700001,-30.7844352722],"type":"Point"}
}