{
  "type": "Feature",
  "properties": {
    "addr:full":"3/ 8 Franklin St Melbourne VIC 3000",
    "addr:housenumber":"/ 8",
    "addr:postcode":"3000",
    "addr:street":"Franklin St",
    "iso:country":"AU",
    "sg:address":"3/ 8 Franklin St",
    "sg:city":"Melbourne",
    "sg:classifiers":[
        {
            "category":"Retail",
            "subcategory":"Auto Rental",
            "type":"Services"
        }
    ],
    "sg:phone":"+61 3 9203 4844",
    "sg:postcode":"3000",
    "sg:province":"VIC",
    "sg:tags":[
        "bus",
        "truck"
    ],
    "wof:name":"Budget Truck Rental",
    "wof:placetype":"venue"
},
  "geometry": {"coordinates":[144.963546753,-37.8071098328],"type":"Point"}
}