{
  "type": "Feature",
  "properties": {
    "iso:country":"AU",
    "sg:address":"32 Rosen St",
    "sg:city":"Epping",
    "sg:classifiers":[
        {
            "category":"Travel",
            "subcategory":"Travel Agent",
            "type":"Entertainment"
        }
    ],
    "sg:phone":"+61 2 9876 3863",
    "sg:postcode":"2121",
    "sg:province":"NSW",
    "sg:tags":[
        "consultant"
    ],
    "wof:name":"Inbound Operator",
    "wof:placetype":"venue"
},
  "geometry": {"coordinates":[151.07618713400001,-33.7688217163],"type":"Point"}
}