{
  "type": "Feature",
  "properties": {
    "addr:full":"Shp 2/ 328 Hobart Rd Youngtown TAS 7249",
    "addr:housenumber":"/ 328",
    "addr:postcode":"7249",
    "addr:street":"Hobart Rd",
    "iso:country":"AU",
    "sg:address":"Shp 2/ 328 Hobart Rd",
    "sg:city":"Youngtown",
    "sg:classifiers":[
        {
            "category":"Personal",
            "subcategory":"Massage",
            "type":"Services"
        }
    ],
    "sg:phone":"+61 3 6343 7999",
    "sg:postcode":"7249",
    "sg:province":"TAS",
    "sg:tags":[
        "therapy"
    ],
    "wof:name":"Youngtown Chronic Pain Relief Centre",
    "wof:placetype":"venue"
},
  "geometry": {"coordinates":[147.167312622,-41.4822845459],"type":"Point"}
}