{
  "type": "Feature",
  "properties": {
    "addr:full":"PO Box 103 Harbord NSW 2096",
    "addr:postcode":"2096",
    "iso:country":"AU",
    "sg:address":"PO Box 103",
    "sg:city":"Harbord",
    "sg:classifiers":[
        {
            "category":"Professional",
            "subcategory":"Employment Agencies",
            "type":"Services"
        }
    ],
    "sg:phone":"+61 2 9905 2883",
    "sg:postcode":"2096",
    "sg:province":"NSW",
    "sg:tags":[
        "provider",
        "internet"
    ],
    "wof:name":"A.Y. Communications",
    "wof:placetype":"venue"
},
  "geometry": {"coordinates":[151.28416442899999,-33.7750587463],"type":"Point"}
}