{
  "type": "Feature",
  "properties": {
    "addr:full":"Shed 7 Gaulds Estate, Kingston Drive Maryborough QLD 4650",
    "addr:housenumber":"7",
    "addr:postcode":"4650",
    "addr:street":"Gaulds Estate Kingston Drive",
    "iso:country":"AU",
    "sg:address":"Shed 7",
    "sg:city":"Gaulds Estate, Kingston Drive Maryborough",
    "sg:classifiers":[
        {
            "category":"Freight",
            "type":"Transportation"
        }
    ],
    "sg:phone":"+61 13 23 45",
    "sg:postcode":"4650",
    "sg:province":"QLD",
    "sg:tags":[
        "light",
        "carrier"
    ],
    "wof:name":"Star Track Express",
    "wof:placetype":"venue"
},
  "geometry": {"coordinates":[152.677628,-25.516701],"type":"Point"}
}