{
  "type": "Feature",
  "properties": {
    "iso:country":"AU",
    "sg:address":"36 Smith St",
    "sg:city":"Healesville",
    "sg:classifiers":[
        {
            "category":"Manufacturing",
            "subcategory":"Lumber",
            "type":"Manufacturing & Wholesale Goods"
        }
    ],
    "sg:phone":"+61 401 448 239",
    "sg:postcode":"3777",
    "sg:province":"VIC",
    "sg:tags":[
        "sawmillers"
    ],
    "wof:name":"AmberWood",
    "wof:placetype":"venue"
},
  "geometry": {"coordinates":[145.508636,-37.659988],"type":"Point"}
}