{
  "type": "Feature",
  "properties": {
    "iso:country":"AU",
    "sg:address":"Suite 6, 45 Nind St",
    "sg:city":"Southport",
    "sg:classifiers":[
        {
            "category":"Professional",
            "subcategory":"Employment Agencies",
            "type":"Services"
        }
    ],
    "sg:phone":"+61 1300 363 050",
    "sg:postcode":"4215",
    "sg:province":"QLD",
    "wof:name":"Busy At Work",
    "wof:placetype":"venue"
},
  "geometry": {"coordinates":[153.40980529800001,-27.9650382996],"type":"Point"}
}