{
  "type": "Feature",
  "properties": {
    "iso:country":"AU",
    "sg:address":"8 Parkinson La",
    "sg:city":"Kardinya",
    "sg:classifiers":[
        {
            "category":"Building & Trades",
            "subcategory":"Plumbing",
            "type":"Services"
        }
    ],
    "sg:phone":"+61 8 9331 3966",
    "sg:postcode":"6163",
    "sg:province":"WA",
    "sg:tags":[
        "fitting",
        "hose",
        "supply"
    ],
    "wof:name":"Hecs Fire",
    "wof:placetype":"venue"
},
  "geometry": {"coordinates":[115.804062,-32.061436],"type":"Point"}
}