{
  "type": "Feature",
  "properties": {
    "addr:full":"159 Airds Rd Campbelltown NSW 2560",
    "addr:housenumber":"159",
    "addr:postcode":"2560",
    "addr:street":"Airds Rd",
    "iso:country":"AU",
    "sg:address":"159 Airds Rd",
    "sg:city":"Campbelltown",
    "sg:classifiers":[
        {
            "category":"Retail",
            "subcategory":"Storage",
            "type":"Services"
        }
    ],
    "sg:phone":"+61 2 4626 1995",
    "sg:postcode":"2560",
    "sg:province":"NSW",
    "wof:name":"Kennards Self Storage",
    "wof:placetype":"venue"
},
  "geometry": {"coordinates":[150.831665039,-34.0422058105],"type":"Point"}
}