{
  "type": "Feature",
  "properties": {
    "addr:full":"156 Henley Beach Rd Torrensville SA 5031",
    "addr:housenumber":"156",
    "addr:postcode":"5031",
    "addr:street":"Henley Beach Rd",
    "iso:country":"AU",
    "sg:address":"156 Henley Beach Rd",
    "sg:city":"Torrensville",
    "sg:classifiers":[
        {
            "category":"Real Estate",
            "subcategory":"Real Estate Agent",
            "type":"Services"
        }
    ],
    "sg:phone":"+61 8 8352 2265",
    "sg:postcode":"5031",
    "sg:province":"SA",
    "wof:name":"Peter Wundersitz First National",
    "wof:placetype":"venue"
},
  "geometry": {"coordinates":[138.56381225600001,-34.9238204956],"type":"Point"}
}