{
  "type": "Feature",
  "properties": {
    "addr:full":"78 Calder Rd Rydalmere NSW 2116",
    "addr:housenumber":"78",
    "addr:postcode":"2116",
    "addr:street":"Calder Rd",
    "iso:country":"AU",
    "sg:address":"78 Calder Rd",
    "sg:city":"Rydalmere",
    "sg:classifiers":[
        {
            "category":"Autos & Motor Vehicles",
            "subcategory":"Auto Supplies",
            "type":"Retail Goods"
        }
    ],
    "sg:phone":"+61 412 364 983",
    "sg:postcode":"2116",
    "sg:province":"NSW",
    "sg:tags":[
        "accessory"
    ],
    "wof:name":"Unique Steering Wheel Security",
    "wof:placetype":"venue"
},
  "geometry": {"coordinates":[151.039993286,-33.8061332703],"type":"Point"}
}