{
  "type": "Feature",
  "properties": {
    "addr:full":"154 Springvale Rd Nunawading VIC 3131",
    "addr:housenumber":"154",
    "addr:postcode":"3131",
    "addr:street":"Springvale Rd",
    "iso:country":"AU",
    "sg:address":"154 Springvale Rd",
    "sg:city":"Nunawading",
    "sg:classifiers":[
        {
            "category":"Food & Beverages",
            "subcategory":"Specialty",
            "type":"Retail Goods"
        }
    ],
    "sg:phone":"+61 3 9878 6232",
    "sg:postcode":"3131",
    "sg:province":"VIC",
    "sg:tags":[
        "product",
        "health"
    ],
    "wof:name":"Health Muscle Body",
    "wof:placetype":"venue"
},
  "geometry": {"coordinates":[145.17547607399999,-37.8198356628],"type":"Point"}
}