{
  "type": "Feature",
  "properties": {
    "iso:country":"AU",
    "sg:address":"27 Were St",
    "sg:city":"Montmorency",
    "sg:classifiers":[
        {
            "category":"Personal",
            "type":"Services"
        }
    ],
    "sg:phone":"+61 3 9434 2382",
    "sg:postcode":"3094",
    "sg:province":"VIC",
    "sg:tags":[
        "gift"
    ],
    "wof:name":"Montflora Florist",
    "wof:placetype":"venue"
},
  "geometry": {"coordinates":[145.12095642099999,-37.7168617249],"type":"Point"}
}