{
  "type": "Feature",
  "properties": {
    "addr:full":"PO Box 318 Nowra NSW 2541",
    "addr:postcode":"2541",
    "iso:country":"AU",
    "sg:address":"PO Box 318",
    "sg:city":"Nowra",
    "sg:classifiers":[
        {
            "category":"Utilities",
            "subcategory":"Electric",
            "type":"Services"
        }
    ],
    "sg:phone":"+61 428 511 919",
    "sg:postcode":"2541",
    "sg:province":"NSW",
    "sg:tags":[
        "electrical",
        "contractor"
    ],
    "wof:name":"Integritec Pty Ltd",
    "wof:placetype":"venue"
},
  "geometry": {"coordinates":[150.59387207,-34.8777999878],"type":"Point"}
}