{
  "type": "Feature",
  "properties": {
    "addr:full":"6 Myee Pl Blue Haven NSW 2262",
    "addr:housenumber":"6",
    "addr:postcode":"2262",
    "addr:street":"Myee Pl",
    "iso:country":"AU",
    "sg:address":"6 Myee Pl",
    "sg:city":"Blue Haven",
    "sg:classifiers":[
        {
            "category":"Arts & Performance",
            "subcategory":"Music",
            "type":"Entertainment"
        }
    ],
    "sg:phone":"+61 402 257 782",
    "sg:postcode":"2262",
    "sg:province":"NSW",
    "sg:tags":[
        "mobile",
        "jockey",
        "disc"
    ],
    "wof:name":"Xtreme Partyz",
    "wof:placetype":"venue"
},
  "geometry": {"coordinates":[151.502441,-33.208435],"type":"Point"}
}