{
  "type": "Feature",
  "properties": {
    "iso:country":"AU",
    "sg:address":"526 Murray St",
    "sg:city":"Perth",
    "sg:classifiers":[
        {
            "category":"Shopping",
            "subcategory":"Mobile Phones",
            "type":"Retail Goods"
        }
    ],
    "sg:phone":"+61 8 9481 8668",
    "sg:postcode":"6000",
    "sg:province":"WA",
    "sg:tags":[
        "telephone",
        "accessory"
    ],
    "wof:name":"SPYTEL Telecommunications Australia",
    "wof:placetype":"venue"
},
  "geometry": {"coordinates":[115.85945892300001,-31.9532051086],"type":"Point"}
}