{
  "type": "Feature",
  "properties": {
    "addr:full":"Macquarie St Dubbo NSW 2830",
    "addr:postcode":"2830",
    "addr:street":"Macquarie St",
    "iso:country":"AU",
    "sg:address":"Macquarie St",
    "sg:city":"Dubbo",
    "sg:classifiers":[
        {
            "category":"Shopping",
            "subcategory":"Department Store",
            "type":"Retail Goods"
        }
    ],
    "sg:phone":"+61 2 6826 7211",
    "sg:postcode":"2830",
    "sg:province":"NSW",
    "wof:name":"Myer Stores Ltd",
    "wof:placetype":"venue"
},
  "geometry": {"coordinates":[148.60118102999999,-32.2478790283],"type":"Point"}
}