{
  "type": "Feature",
  "properties": {
    "iso:country":"AU",
    "sg:address":"3 Adeney St",
    "sg:city":"Balwyn North",
    "sg:classifiers":[
        {
            "category":"Professional",
            "subcategory":"Accounting & Tax Preparation",
            "type":"Services"
        }
    ],
    "sg:phone":"+61 3 9857 4451",
    "sg:postcode":"3104",
    "sg:province":"VIC",
    "sg:tags":[
        "accountant",
        "auditor"
    ],
    "wof:name":"Budget Accounting Solutions",
    "wof:placetype":"venue"
},
  "geometry": {"coordinates":[145.10038757300001,-37.8021774292],"type":"Point"}
}