{
  "type": "Feature",
  "properties": {
    "iso:country":"AU",
    "sg:address":"1 Cowper St",
    "sg:city":"Carrington",
    "sg:classifiers":[
        {
            "category":"Professional",
            "subcategory":"Business Services",
            "type":"Services"
        }
    ],
    "sg:phone":"+61 2 4961 1606",
    "sg:postcode":"2294",
    "sg:province":"NSW",
    "sg:tags":[
        "consultant",
        "promoter",
        "entertainment"
    ],
    "wof:name":"Big Apachee",
    "wof:placetype":"venue"
},
  "geometry": {"coordinates":[151.76521301299999,-32.9160118103],"type":"Point"}
}