{
  "type": "Feature",
  "properties": {
    "addr:full":"590 Dibble St Mt Helena WA 6082",
    "addr:housenumber":"590",
    "addr:postcode":"6082",
    "addr:street":"Dibble St",
    "iso:country":"AU",
    "sg:address":"590 Dibble St",
    "sg:city":"Mt Helena",
    "sg:classifiers":[
        {
            "category":"Building & Trades",
            "subcategory":"Construction",
            "type":"Services"
        }
    ],
    "sg:phone":"+61 8 9572 1903",
    "sg:postcode":"6082",
    "sg:province":"WA",
    "sg:tags":[
        "earth",
        "excavating",
        "moving",
        "contractor"
    ],
    "wof:name":"Kimbow Contracting",
    "wof:placetype":"venue"
},
  "geometry": {"coordinates":[116.20767211899999,-31.8737659454],"type":"Point"}
}