{
  "type": "Feature",
  "properties": {
    "addr:full":"185 Whitehorse Rd Balwyn VIC 3103",
    "addr:housenumber":"185",
    "addr:postcode":"3103",
    "addr:street":"Whitehorse Rd",
    "iso:country":"AU",
    "sg:address":"185 Whitehorse Rd",
    "sg:city":"Balwyn",
    "sg:classifiers":[
        {
            "category":"Retail",
            "subcategory":"Veterinary Services",
            "type":"Services"
        }
    ],
    "sg:phone":"+61 3 9817 4561",
    "sg:postcode":"3103",
    "sg:province":"VIC",
    "sg:tags":[
        "surgeon"
    ],
    "wof:name":"Balwyn Veterinary Surgery",
    "wof:placetype":"venue"
},
  "geometry": {"coordinates":[145.07019043,-37.8113365173],"type":"Point"}
}