{
  "type": "Feature",
  "properties": {
    "addr:full":"PO Box 456 Tugun QLD 4224",
    "addr:postcode":"4224",
    "iso:country":"AU",
    "sg:address":"PO Box 456",
    "sg:city":"Tugun",
    "sg:phone":"+61 404 852 390",
    "sg:postcode":"4224",
    "sg:province":"QLD",
    "wof:name":"Johnston Plumbing & Gasfitting",
    "wof:placetype":"venue"
},
  "geometry": {"coordinates":[153.49212646500001,-28.1418399811],"type":"Point"}
}