{
  "type": "Feature",
  "properties": {
    "addr:full":"25 Twine St Spring Hill QLD 4000",
    "addr:housenumber":"25",
    "addr:postcode":"4000",
    "addr:street":"Twine St",
    "iso:country":"AU",
    "sg:address":"25 Twine St",
    "sg:city":"Spring Hill",
    "sg:classifiers":[
        {
            "category":"Organizations",
            "subcategory":"Professional Association",
            "type":"Services"
        }
    ],
    "sg:phone":"+61 7 3831 9811",
    "sg:postcode":"4000",
    "sg:province":"QLD",
    "sg:tags":[
        "web",
        "internet"
    ],
    "sg:website":"http://www.jmgarnsworthy.com",
    "wof:name":"John Garnsworthy & Associates",
    "wof:placetype":"venue"
},
  "geometry": {"coordinates":[153.021682739,-27.4633598328],"type":"Point"}
}