{
  "type": "Feature",
  "properties": {
    "addr:full":"16 Thesiger Crt Deakin ACT 2600",
    "addr:housenumber":"16",
    "addr:postcode":"2600",
    "addr:street":"Thesiger Crt",
    "iso:country":"AU",
    "sg:address":"16 Thesiger Crt",
    "sg:city":"Deakin",
    "sg:classifiers":[
        {
            "category":"Organizations",
            "subcategory":"Professional Association",
            "type":"Services"
        }
    ],
    "sg:phone":"+61 2 6281 1588",
    "sg:postcode":"2600",
    "sg:province":"ACT",
    "sg:tags":[
        "organisation",
        "business"
    ],
    "wof:name":"National Office Services Pty Ltd",
    "wof:placetype":"venue"
},
  "geometry": {"coordinates":[149.095245361,-35.3176383972],"type":"Point"}
}