{
  "type": "Feature",
  "properties": {
    "iso:country":"AU",
    "sg:address":"70 Burdett St",
    "sg:city":"Hornsby",
    "sg:classifiers":[
        {
            "category":"Health Services",
            "subcategory":"Doctor",
            "type":"Services"
        }
    ],
    "sg:phone":"+61 2 9477 7707",
    "sg:postcode":"2077",
    "sg:province":"NSW",
    "sg:tags":[
        "medical",
        "practitioner"
    ],
    "wof:name":"Hornsby Orthopaedic & Sports Medicine Centre",
    "wof:placetype":"venue"
},
  "geometry": {"coordinates":[151.109542847,-33.7038650513],"type":"Point"}
}