{
  "type": "Feature",
  "properties": {
    "iso:country":"AU",
    "sg:address":"120 Kildare Rd",
    "sg:city":"Blacktown",
    "sg:classifiers":[
        {
            "category":"Structure",
            "subcategory":"Building",
            "type":"Public Place"
        }
    ],
    "sg:phone":"+61 2 9990 8761",
    "sg:postcode":"2148",
    "sg:province":"NSW",
    "sg:tags":[
        "sail",
        "shade"
    ],
    "wof:name":"West Sydney Shade & Sails",
    "wof:placetype":"venue"
},
  "geometry": {"coordinates":[150.894989014,-33.7696685791],"type":"Point"}
}