{
  "type": "Feature",
  "properties": {
    "addr:full":"Shop 3 264 Peel St Tamworth NSW 2340",
    "addr:housenumber":"shop 3 264",
    "addr:postcode":"2340",
    "addr:street":"Peel St",
    "iso:country":"AU",
    "sg:address":"Shop 3 264 Peel St",
    "sg:city":"Tamworth",
    "sg:classifiers":[
        {
            "category":"Government",
            "subcategory":"Customs House",
            "type":"Public Place"
        }
    ],
    "sg:phone":"+61 2 6766 6003",
    "sg:postcode":"2340",
    "sg:province":"NSW",
    "sg:tags":[
        "title",
        "management",
        "stratum"
    ],
    "wof:name":"Maxwell & Pevy Real Estate",
    "wof:placetype":"venue"
},
  "geometry": {"coordinates":[150.93318176299999,-31.094078064],"type":"Point"}
}