{
  "type": "Feature",
  "properties": {
    "addr:full":"PO Box 2 Melbourne VIC 8060",
    "addr:postcode":"8060",
    "iso:country":"AU",
    "sg:address":"PO Box 2",
    "sg:city":"Melbourne",
    "sg:classifiers":[
        {
            "category":"Professional",
            "subcategory":"Art Services",
            "type":"Services"
        }
    ],
    "sg:phone":"+61 1800 030 066",
    "sg:postcode":"8060",
    "sg:province":"VIC",
    "sg:tags":[
        "decorator",
        "painter"
    ],
    "wof:name":"Bourjon Contracting Group",
    "wof:placetype":"venue"
},
  "geometry": {"coordinates":[144.963165283,-37.814250946],"type":"Point"}
}