{
  "type": "Feature",
  "properties": {
    "addr:full":"PO Box 417 Double Bay NSW 1360",
    "addr:postcode":"1360",
    "iso:country":"AU",
    "sg:address":"PO Box 417",
    "sg:city":"Double Bay",
    "sg:classifiers":[
        {
            "category":"Wholesale",
            "subcategory":"Stationery",
            "type":"Manufacturing & Wholesale Goods"
        }
    ],
    "sg:phone":"+61 2 9371 5486",
    "sg:postcode":"1360",
    "sg:province":"NSW",
    "sg:tags":[
        "mfrg"
    ],
    "wof:name":"Stationery Solutions",
    "wof:placetype":"venue"
},
  "geometry": {"coordinates":[151.24476623499999,-33.8771896362],"type":"Point"}
}