{
  "type": "Feature",
  "properties": {
    "iso:country":"AU",
    "sg:address":"Suite 6",
    "sg:city":"/Kingsley Professional Cntr Kingsley",
    "sg:classifiers":[
        {
            "category":"Professional",
            "subcategory":"Computer Services",
            "type":"Services"
        }
    ],
    "sg:phone":"+61 8 9409 8704",
    "sg:postcode":"6026",
    "sg:province":"WA",
    "sg:tags":[
        "package",
        "software"
    ],
    "wof:name":"Osipos Pty Ltd",
    "wof:placetype":"venue"
},
  "geometry": {"coordinates":[115.78865051299999,-31.7998943329],"type":"Point"}
}