{
  "type": "Feature",
  "properties": {
    "addr:full":"25 Mulley St Holder ACT 2611",
    "addr:housenumber":"25",
    "addr:postcode":"2611",
    "addr:street":"Mulley St",
    "iso:country":"AU",
    "sg:address":"25 Mulley St",
    "sg:city":"Holder",
    "sg:classifiers":[
        {
            "category":"Professional",
            "subcategory":"Research",
            "type":"Services"
        }
    ],
    "sg:phone":"+61 2 6205 8704",
    "sg:postcode":"2611",
    "sg:province":"ACT",
    "sg:tags":[
        "analyst"
    ],
    "wof:name":"ACT Government Analytical Laboratory",
    "wof:placetype":"venue"
},
  "geometry": {"coordinates":[149.04847717300001,-35.3304252625],"type":"Point"}
}