{
  "type": "Feature",
  "properties": {
    "addr:full":"Suite 1/ 322 Old Cleveland Rd Coorparoo QLD 4151",
    "addr:housenumber":"/ 322",
    "addr:postcode":"4151",
    "addr:street":"Old Cleveland Rd",
    "iso:country":"AU",
    "sg:address":"Suite 1/ 322 Old Cleveland Rd",
    "sg:city":"Coorparoo",
    "sg:classifiers":[
        {
            "category":"Professional",
            "subcategory":"Business Services",
            "type":"Services"
        }
    ],
    "sg:phone":"+61 7 3324 1317",
    "sg:postcode":"4151",
    "sg:province":"QLD",
    "sg:tags":[
        "broker"
    ],
    "wof:name":"Donnelly Brokers",
    "wof:placetype":"venue"
},
  "geometry": {"coordinates":[153.05996704099999,-27.4938812256],"type":"Point"}
}