{
  "type": "Feature",
  "properties": {
    "addr:full":"8- 12 Nixon Rd Wingfield SA 5013",
    "addr:housenumber":"12",
    "addr:postcode":"5013",
    "addr:street":"8;Nixon Rd",
    "iso:country":"AU",
    "sg:address":"8- 12 Nixon Rd",
    "sg:city":"Wingfield",
    "sg:classifiers":[
        {
            "category":"Professional",
            "subcategory":"Detective & Security Services",
            "type":"Services"
        }
    ],
    "sg:phone":"+61 8 8345 2088",
    "sg:postcode":"5013",
    "sg:province":"SA",
    "sg:tags":[
        "equipment",
        "window",
        "doors"
    ],
    "wof:name":"George The Window Man",
    "wof:placetype":"venue"
},
  "geometry": {"coordinates":[138.557907105,-34.8362541199],"type":"Point"}
}