{
  "type": "Feature",
  "properties": {
    "iso:country":"AU",
    "sg:address":"57 Terrigal Drv",
    "sg:city":"Terrigal",
    "sg:classifiers":[
        {
            "category":"Health Services",
            "subcategory":"Chiropractor",
            "type":"Services"
        }
    ],
    "sg:phone":"+61 2 4385 4468",
    "sg:postcode":"2260",
    "sg:province":"NSW",
    "wof:name":"Messthaler, Wolf",
    "wof:placetype":"venue"
},
  "geometry": {"coordinates":[151.433487,-33.43969],"type":"Point"}
}