{
  "type": "Feature",
  "properties": {
    "iso:country":"AU",
    "sg:address":"86 Brunel Rd",
    "sg:city":"Seaford",
    "sg:classifiers":[
        {
            "category":"Professional",
            "subcategory":"Engineering",
            "type":"Services"
        }
    ],
    "sg:phone":"+61 3 9776 4600",
    "sg:postcode":"3198",
    "sg:province":"VIC",
    "sg:tags":[
        "civil",
        "engineer"
    ],
    "wof:name":"Select Contractors Pty Ltd",
    "wof:placetype":"venue"
},
  "geometry": {"coordinates":[145.153030395,-38.1014137268],"type":"Point"}
}