{
  "type": "Feature",
  "properties": {
    "addr:full":"6 Gilgandra Rd Dubbo NSW 2830",
    "addr:housenumber":"6",
    "addr:postcode":"2830",
    "addr:street":"Gilgandra Rd",
    "iso:country":"AU",
    "sg:address":"6 Gilgandra Rd",
    "sg:city":"Dubbo",
    "sg:classifiers":[
        {
            "category":"Wholesale",
            "subcategory":"Painting Supplies",
            "type":"Manufacturing & Wholesale Goods"
        }
    ],
    "sg:phone":"+61 2 6882 0313",
    "sg:postcode":"2830",
    "sg:province":"NSW",
    "sg:tags":[
        "equipment",
        "spraying"
    ],
    "wof:name":"SprayerBarn",
    "wof:placetype":"venue"
},
  "geometry": {"coordinates":[148.60118102999999,-32.2478713989],"type":"Point"}
}