{
  "type": "Feature",
  "properties": {
    "addr:full":"41 Susan St Annandale NSW 2038",
    "addr:housenumber":"41",
    "addr:postcode":"2038",
    "addr:street":"Susan St",
    "iso:country":"AU",
    "sg:address":"41 Susan St",
    "sg:city":"Annandale",
    "sg:classifiers":[
        {
            "category":"Health Services",
            "subcategory":"Health Practitioner",
            "type":"Services"
        }
    ],
    "sg:phone":"+61 2 9519 1954",
    "sg:postcode":"2038",
    "sg:province":"NSW",
    "sg:tags":[
        "acupuncture"
    ],
    "wof:name":"Hoad Annette",
    "wof:placetype":"venue"
},
  "geometry": {"coordinates":[151.17312622099999,-33.8851165771],"type":"Point"}
}