{
  "type": "Feature",
  "properties": {
    "addr:full":"197A Macquarie St Hobart TAS 7000",
    "addr:housenumber":"197a",
    "addr:postcode":"7000",
    "addr:street":"Macquarie St",
    "iso:country":"AU",
    "sg:address":"197A Macquarie St",
    "sg:city":"Hobart",
    "sg:classifiers":[
        {
            "category":"Health Services",
            "subcategory":"Doctor",
            "type":"Services"
        }
    ],
    "sg:phone":"+61 3 6224 2866",
    "sg:postcode":"7000",
    "sg:province":"TAS",
    "sg:tags":[
        "occupational",
        "safety"
    ],
    "wof:name":"Inergise Australia Pty Ltd",
    "wof:placetype":"venue"
},
  "geometry": {"coordinates":[147.32424926799999,-42.8871192932],"type":"Point"}
}