{
  "type": "Feature",
  "properties": {
    "iso:country":"AU",
    "sg:address":"Rear of 33 The Avenue",
    "sg:city":"Windsor",
    "sg:classifiers":[
        {
            "category":"Health Services",
            "subcategory":"Health Practitioner",
            "type":"Services"
        }
    ],
    "sg:phone":"+61 3 9510 8999",
    "sg:postcode":"3181",
    "sg:province":"VIC",
    "sg:tags":[
        "physiotherapist"
    ],
    "wof:name":"Watson Lyn",
    "wof:placetype":"venue"
},
  "geometry": {"coordinates":[144.997879028,-37.8549728394],"type":"Point"}
}