{
  "type": "Feature",
  "properties": {
    "addr:full":"Shop 27C, 37 Walanna Drv Manning WA 6152",
    "addr:housenumber":"27c 37",
    "addr:postcode":"6152",
    "addr:street":"Shop;Walanna Drv",
    "iso:country":"AU",
    "sg:address":"Shop 27C, 37 Walanna Drv",
    "sg:city":"Manning",
    "sg:classifiers":[
        {
            "category":"Restaurant",
            "type":"Food & Drink"
        }
    ],
    "sg:phone":"+61 8 9313 1799",
    "sg:postcode":"6152",
    "sg:province":"WA",
    "sg:tags":[
        "pizza"
    ],
    "wof:name":"Eagle Boys Pizza",
    "wof:placetype":"venue"
},
  "geometry": {"coordinates":[115.88462800000001,-32.011562],"type":"Point"}
}