{
  "type": "Feature",
  "properties": {
    "iso:country":"AU",
    "sg:address":"17 Cathpole Ave",
    "sg:city":"Richmond",
    "sg:classifiers":[
        {
            "category":"Professional",
            "subcategory":"Testing Lab",
            "type":"Services"
        }
    ],
    "sg:phone":"+61 405 502 284",
    "sg:postcode":"2753",
    "sg:province":"NSW",
    "sg:tags":[
        "inspection"
    ],
    "wof:name":"Arrow Test & Tag",
    "wof:placetype":"venue"
},
  "geometry": {"coordinates":[150.74276733400001,-33.6026763916],"type":"Point"}
}