{
  "type": "Feature",
  "properties": {
    "addr:full":"49- 53 Dandenong St Dandenong VIC 3175",
    "addr:housenumber":"53",
    "addr:postcode":"3175",
    "addr:street":"Dandenong St",
    "iso:country":"AU",
    "sg:address":"49- 53 Dandenong St",
    "sg:city":"Dandenong",
    "sg:classifiers":[
        {
            "category":"Manufacturing",
            "subcategory":"Textiles",
            "type":"Manufacturing & Wholesale Goods"
        }
    ],
    "sg:phone":"+61 3 9791 8351",
    "sg:postcode":"3175",
    "sg:province":"VIC",
    "sg:tags":[
        "dyer"
    ],
    "wof:name":"Colorstrand Dyeworks Pty Ltd",
    "wof:placetype":"venue"
},
  "geometry": {"coordinates":[145.19943237300001,-37.9950866699],"type":"Point"}
}