{
  "type": "Feature",
  "properties": {
    "addr:full":"79 Flores Rd Webberton WA 6530",
    "addr:housenumber":"79",
    "addr:postcode":"6530",
    "addr:street":"Flores Rd",
    "iso:country":"AU",
    "sg:address":"79 Flores Rd",
    "sg:city":"Webberton",
    "sg:classifiers":[
        {
            "category":"Manufacturing",
            "subcategory":"Building Materials",
            "type":"Manufacturing & Wholesale Goods"
        }
    ],
    "sg:phone":"+61 8 9964 4234",
    "sg:postcode":"6530",
    "sg:province":"WA",
    "sg:tags":[
        "stone",
        "product",
        "supply"
    ],
    "wof:name":"Carabooda Limestone Co",
    "wof:placetype":"venue"
},
  "geometry": {"coordinates":[114.630859375,-28.7562465668],"type":"Point"}
}