{
  "type": "Feature",
  "properties": {
    "addr:full":"5 Ware St Fairfield NSW 2165",
    "addr:housenumber":"5",
    "addr:postcode":"2165",
    "addr:street":"Ware St",
    "iso:country":"AU",
    "sg:address":"5 Ware St",
    "sg:city":"Fairfield",
    "sg:classifiers":[
        {
            "category":"Food & Beverages",
            "subcategory":"Supermarket",
            "type":"Retail Goods"
        }
    ],
    "sg:phone":"+61 2 9755 0040",
    "sg:postcode":"2165",
    "sg:province":"NSW",
    "sg:tags":[
        "grocery",
        "store"
    ],
    "wof:name":"Al Nakheel Market",
    "wof:placetype":"venue"
},
  "geometry": {"coordinates":[150.955566406,-33.8726005554],"type":"Point"}
}