{
  "type": "Feature",
  "properties": {
    "addr:full":"31 Rennie St Thornbury VIC 3071",
    "addr:housenumber":"31",
    "addr:postcode":"3071",
    "addr:street":"Rennie St",
    "iso:country":"AU",
    "sg:address":"31 Rennie St",
    "sg:city":"Thornbury",
    "sg:classifiers":[
        {
            "category":"Professional",
            "subcategory":"Management & Consulting",
            "type":"Services"
        }
    ],
    "sg:phone":"+61 3 9443 8500",
    "sg:postcode":"3071",
    "sg:province":"VIC",
    "sg:tags":[
        "consultant"
    ],
    "wof:name":"Groupwork Institute",
    "wof:placetype":"venue"
},
  "geometry": {"coordinates":[144.99102783199999,-37.7532043457],"type":"Point"}
}