{
  "type": "Feature",
  "properties": {
    "addr:full":"17 Bussell Hwy Busselton WA 6280",
    "addr:housenumber":"17",
    "addr:postcode":"6280",
    "addr:street":"Bussell Hwy",
    "iso:country":"AU",
    "sg:address":"17 Bussell Hwy",
    "sg:city":"Busselton",
    "sg:classifiers":[
        {
            "category":"Fast Food",
            "type":"Food & Drink"
        }
    ],
    "sg:phone":"+61 8 9754 1222",
    "sg:postcode":"6280",
    "sg:province":"WA",
    "sg:tags":[
        "away",
        "take"
    ],
    "wof:name":"Subway",
    "wof:placetype":"venue"
},
  "geometry": {"coordinates":[115.339683533,-33.6530570984],"type":"Point"}
}