{
  "type": "Feature",
  "properties": {
    "addr:full":"80 Bundall Rd Bundall QLD 4217",
    "addr:housenumber":"80",
    "addr:postcode":"4217",
    "addr:street":"Bundall Rd",
    "iso:country":"AU",
    "sg:address":"80 Bundall Rd",
    "sg:city":"Bundall",
    "sg:classifiers":[
        {
            "category":"Home & Garden",
            "subcategory":"Carpets & Floor Coverings",
            "type":"Retail Goods"
        }
    ],
    "sg:phone":"+61 7 5538 6011",
    "sg:postcode":"4217",
    "sg:province":"QLD",
    "sg:tags":[
        "tile",
        "wall"
    ],
    "wof:name":"Metro Tiles",
    "wof:placetype":"venue"
},
  "geometry": {"coordinates":[153.41262817399999,-28.0070781708],"type":"Point"}
}