{
  "type": "Feature",
  "properties": {
    "addr:full":"55 Thorpe St Rockingham WA 6168",
    "addr:housenumber":"55",
    "addr:postcode":"6168",
    "addr:street":"Thorpe St",
    "iso:country":"AU",
    "sg:address":"55 Thorpe St",
    "sg:city":"Rockingham",
    "sg:classifiers":[
        {
            "category":"Health Services",
            "subcategory":"Doctor",
            "type":"Services"
        }
    ],
    "sg:phone":"+61 8 9527 1555",
    "sg:postcode":"6168",
    "sg:province":"WA",
    "sg:tags":[
        "medical",
        "practitioner"
    ],
    "wof:name":"Rasool E",
    "wof:placetype":"venue"
},
  "geometry": {"coordinates":[115.730118,-32.278355],"type":"Point"}
}