{
  "type": "Feature",
  "properties": {
    "iso:country":"AU",
    "sg:address":"Bli Bli Rd",
    "sg:city":"Nambour",
    "sg:classifiers":[
        {
            "category":"Building & Trades",
            "subcategory":"Equipment Rental",
            "type":"Services"
        }
    ],
    "sg:phone":"+61 7 5441 1211",
    "sg:postcode":"4560",
    "sg:province":"QLD",
    "sg:tags":[
        "builder",
        "contractor"
    ],
    "wof:name":"JC Hire Service",
    "wof:placetype":"venue"
},
  "geometry": {"coordinates":[152.969207764,-26.6166877747],"type":"Point"}
}