{
  "type": "Feature",
  "properties": {
    "iso:country":"AU",
    "sg:address":"Cnr Stafford & Shafton Sts",
    "sg:city":"Huntingdale",
    "sg:classifiers":[
        {
            "category":"Retail",
            "subcategory":"Auto Repair",
            "type":"Services"
        }
    ],
    "sg:phone":"+61 3 9543 3110",
    "sg:postcode":"3166",
    "sg:province":"VIC",
    "sg:tags":[
        "repairer",
        "motor",
        "engineer"
    ],
    "wof:name":"Goodyear Auto Service Centre",
    "wof:placetype":"venue"
},
  "geometry": {"coordinates":[145.105194092,-37.9101715088],"type":"Point"}
}