{
  "type": "Feature",
  "properties": {
    "addr:full":"Bath St Dental Clinic 19 Bath St Glenelg SA 5045",
    "addr:housenumber":"19",
    "addr:postcode":"5045",
    "addr:street":"Bath;Bath St",
    "iso:country":"AU",
    "sg:address":"Bath St Dental Clinic 19 Bath St",
    "sg:city":"Glenelg",
    "sg:classifiers":[
        {
            "category":"Health Services",
            "subcategory":"Dentist",
            "type":"Services"
        }
    ],
    "sg:phone":"+61 407 394 841",
    "sg:postcode":"5045",
    "sg:province":"SA",
    "wof:name":"Freeman Guy Dr",
    "wof:placetype":"venue"
},
  "geometry": {"coordinates":[138.51707500000001,-34.990273],"type":"Point"}
}