{
  "type": "Feature",
  "properties": {
    "iso:country":"AU",
    "sg:address":"1350B Toorak Rd",
    "sg:city":"Camberwell",
    "sg:classifiers":[
        {
            "category":"Retail",
            "subcategory":"Auto Repair",
            "type":"Services"
        }
    ],
    "sg:phone":"+61 3 9889 0400",
    "sg:postcode":"3124",
    "sg:province":"VIC",
    "sg:tags":[
        "electrical"
    ],
    "wof:name":"Fieldforce Auto Electrics",
    "wof:placetype":"venue"
},
  "geometry": {"coordinates":[145.092529297,-37.850189209],"type":"Point"}
}