{
  "type": "Feature",
  "properties": {
    "addr:full":"105 - 107 Reserve Rd Artarmon NSW 2064",
    "addr:housenumber":"105 107",
    "addr:postcode":"2064",
    "addr:street":"Reserve Rd",
    "iso:country":"AU",
    "sg:address":"105 - 107 Reserve Rd",
    "sg:city":"Artarmon",
    "sg:classifiers":[
        {
            "category":"Autos & Motor Vehicles",
            "subcategory":"Auto Supplies",
            "type":"Retail Goods"
        }
    ],
    "sg:phone":"+61 2 9437 0266",
    "sg:postcode":"2064",
    "sg:province":"NSW",
    "sg:tags":[
        "wheel",
        "automotive",
        "rim"
    ],
    "wof:name":"JAXQuickfit Tyres",
    "wof:placetype":"venue"
},
  "geometry": {"coordinates":[151.18614196799999,-33.814617157],"type":"Point"}
}