{
  "type": "Feature",
  "properties": {
    "iso:country":"AU",
    "sg:address":"208 Blues Point Rd",
    "sg:city":"North Sydney",
    "sg:classifiers":[
        {
            "category":"Personal",
            "subcategory":"Beauty Salon",
            "type":"Services"
        }
    ],
    "sg:phone":"+61 2 9964 0426",
    "sg:postcode":"2060",
    "sg:province":"NSW",
    "sg:tags":[
        "hairdresser"
    ],
    "wof:name":"Industry Cutters Hair Salon",
    "wof:placetype":"venue"
},
  "geometry": {"coordinates":[151.205368042,-33.8420944214],"type":"Point"}
}