{
  "type": "Feature",
  "properties": {
    "addr:full":"90 Mt Vernon Rd Mt Vernon NSW 2178",
    "addr:housenumber":"90",
    "addr:postcode":"2178",
    "addr:street":"Mt Vernon Rd",
    "iso:country":"AU",
    "sg:address":"90 Mt Vernon Rd",
    "sg:city":"Mt Vernon",
    "sg:classifiers":[
        {
            "category":"Professional",
            "type":"Services"
        }
    ],
    "sg:phone":"+61 2 9826 1386",
    "sg:postcode":"2178",
    "sg:province":"NSW",
    "sg:tags":[
        "transport"
    ],
    "wof:name":"Danix Haulage",
    "wof:placetype":"venue"
},
  "geometry": {"coordinates":[150.808197022,-33.8622741699],"type":"Point"}
}