{
  "type": "Feature",
  "properties": {
    "addr:full":"9 Brolga Crt Little Mountain QLD 4551",
    "addr:housenumber":"9",
    "addr:postcode":"4551",
    "addr:street":"Brolga Crt",
    "iso:country":"AU",
    "sg:address":"9 Brolga Crt",
    "sg:city":"Little Mountain",
    "sg:classifiers":[
        {
            "category":"Professional",
            "subcategory":"Art Services",
            "type":"Services"
        }
    ],
    "sg:phone":"+61 418 779 355",
    "sg:postcode":"4551",
    "sg:province":"QLD",
    "sg:tags":[
        "decorator",
        "painter"
    ],
    "wof:name":"Reymow Painting & Decorating",
    "wof:placetype":"venue"
},
  "geometry": {"coordinates":[153.111495972,-26.7694988251],"type":"Point"}
}