{
  "type": "Feature",
  "properties": {
    "addr:full":"Unit 30/ 93 Newton Rd Wetherill Park NSW 2164",
    "addr:housenumber":"/ 93",
    "addr:postcode":"2164",
    "addr:street":"Newton Rd",
    "iso:country":"AU",
    "sg:address":"Unit 30/ 93 Newton Rd",
    "sg:city":"Wetherill Park",
    "sg:classifiers":[
        {
            "category":"Building & Trades",
            "subcategory":"Construction",
            "type":"Services"
        }
    ],
    "sg:phone":"+61 2 9756 4796",
    "sg:postcode":"2164",
    "sg:province":"NSW",
    "sg:tags":[
        "joinery"
    ],
    "wof:name":"MCS Joinery & Interior Construction",
    "wof:placetype":"venue"
},
  "geometry": {"coordinates":[150.891555786,-33.8476486206],"type":"Point"}
}