{
  "type": "Feature",
  "properties": {
    "addr:full":"101 Wellington Pde East Melbourne VIC 3002",
    "addr:housenumber":"101",
    "addr:postcode":"3002",
    "addr:street":"Wellington Pde",
    "iso:country":"AU",
    "sg:address":"101 Wellington Pde",
    "sg:city":"East Melbourne",
    "sg:classifiers":[
        {
            "category":"Organizations",
            "subcategory":"Non-profit Organization",
            "type":"Services"
        }
    ],
    "sg:phone":"+61 3 9657 8117",
    "sg:postcode":"3002",
    "sg:province":"VIC",
    "sg:tags":[
        "support",
        "disability",
        "organisation"
    ],
    "wof:name":"Victorian Deaf Society",
    "wof:placetype":"venue"
},
  "geometry": {"coordinates":[144.981155395,-37.8167877197],"type":"Point"}
}