{
  "type": "Feature",
  "properties": {
    "addr:full":"3 Carrington Ave Caringbah NSW 2229",
    "addr:housenumber":"3",
    "addr:postcode":"2229",
    "addr:street":"Carrington Ave",
    "iso:country":"AU",
    "sg:address":"3 Carrington Ave",
    "sg:city":"Caringbah",
    "sg:classifiers":[
        {
            "category":"Building & Trades",
            "subcategory":"Pest Control",
            "type":"Services"
        }
    ],
    "sg:phone":"+61 2 9524 5514",
    "sg:postcode":"2229",
    "sg:province":"NSW",
    "wof:name":"Johnson Doug Pest Control Services",
    "wof:placetype":"venue"
},
  "geometry": {"coordinates":[151.11717224099999,-34.0318450928],"type":"Point"}
}