{
  "type": "Feature",
  "properties": {
    "addr:full":"\"Mudeye\" Champagane Drv Tweed Heads South NSW 2486",
    "addr:postcode":"2486",
    "addr:street":"Champagane Drv",
    "iso:country":"AU",
    "sg:address":"\"Mudeye\" Champagane Drv",
    "sg:city":"Tweed Heads South",
    "sg:classifiers":[
        {
            "category":"Real Estate",
            "subcategory":"Real Estate Agent",
            "type":"Services"
        }
    ],
    "sg:phone":"+61 439 033 331",
    "sg:postcode":"2486",
    "sg:province":"NSW",
    "wof:name":"Mason Peter Real Estate",
    "wof:placetype":"venue"
},
  "geometry": {"coordinates":[153.52195739699999,-28.2078323364],"type":"Point"}
}