{
  "type": "Feature",
  "properties": {
    "addr:full":"10 Woodriffe St Penrith NSW 2750",
    "addr:housenumber":"10",
    "addr:postcode":"2750",
    "addr:street":"Woodriffe St",
    "iso:country":"AU",
    "sg:address":"10 Woodriffe St",
    "sg:city":"Penrith",
    "sg:classifiers":[
        {
            "category":"Donuts",
            "subcategory":"None",
            "type":"Food & Drink"
        }
    ],
    "sg:phone":"+61 2 4721 2110",
    "sg:postcode":"2750",
    "sg:province":"NSW",
    "sg:tags":[
        "die",
        "engraver",
        "sinker"
    ],
    "wof:name":"Reliable Shoe Repair",
    "wof:placetype":"venue"
},
  "geometry": {"coordinates":[150.69789123499999,-33.7534103394],"type":"Point"}
}