{
  "type": "Feature",
  "properties": {
    "addr:full":"13a Herberton Rd Atherton QLD 4883",
    "addr:housenumber":"13a",
    "addr:postcode":"4883",
    "addr:street":"Herberton Rd",
    "iso:country":"AU",
    "sg:address":"13a Herberton Rd",
    "sg:city":"Atherton",
    "sg:classifiers":[
        {
            "category":"Insurance",
            "subcategory":"Insurance Agent",
            "type":"Services"
        }
    ],
    "sg:phone":"+61 7 4091 3488",
    "sg:postcode":"4883",
    "sg:province":"QLD",
    "wof:name":"Bannam Doug Financial Services",
    "wof:placetype":"venue"
},
  "geometry": {"coordinates":[145.470458984,-17.2859516144],"type":"Point"}
}