{
  "type": "Feature",
  "properties": {
    "addr:full":"186 Highbury Rd Mt Waverley VIC 3149",
    "addr:housenumber":"186",
    "addr:postcode":"3149",
    "addr:street":"Highbury Rd",
    "iso:country":"AU",
    "sg:address":"186 Highbury Rd",
    "sg:city":"Mt Waverley",
    "sg:classifiers":[
        {
            "category":"Health Services",
            "subcategory":"Dentist",
            "type":"Services"
        }
    ],
    "sg:phone":"+61 3 9808 9253",
    "sg:postcode":"3149",
    "sg:province":"VIC",
    "wof:name":"Fionna Soh Dr",
    "wof:placetype":"venue"
},
  "geometry": {"coordinates":[145.11585998499999,-37.855796814],"type":"Point"}
}