{
  "type": "Feature",
  "properties": {
    "addr:full":"26 Garden St Geelong VIC 3220",
    "addr:housenumber":"26",
    "addr:postcode":"3220",
    "addr:street":"Garden St",
    "iso:country":"AU",
    "sg:address":"26 Garden St",
    "sg:city":"Geelong",
    "sg:classifiers":[
        {
            "category":"Cafe",
            "type":"Food & Drink"
        }
    ],
    "sg:phone":"+61 3 5224 1661",
    "sg:postcode":"3220",
    "sg:province":"VIC",
    "wof:name":"CJs Espresso & Deli",
    "wof:placetype":"venue"
},
  "geometry": {"coordinates":[144.37316899999999,-38.150597],"type":"Point"}
}