{
  "type": "Feature",
  "properties": {
    "addr:full":"30 Bridge St Waratah NSW 2298",
    "addr:housenumber":"30",
    "addr:postcode":"2298",
    "addr:street":"Bridge St",
    "iso:country":"AU",
    "sg:address":"30 Bridge St",
    "sg:city":"Waratah",
    "sg:classifiers":[
        {
            "category":"Education",
            "subcategory":"Kindergarten",
            "type":"Public Place"
        }
    ],
    "sg:phone":"+61 2 4968 2693",
    "sg:postcode":"2298",
    "sg:province":"NSW",
    "sg:tags":[
        "pre-schools"
    ],
    "wof:name":"Narnia Christian Pre-School",
    "wof:placetype":"venue"
},
  "geometry": {"coordinates":[151.72181701700001,-32.902305603],"type":"Point"}
}