{
  "type": "Feature",
  "properties": {
    "addr:full":"18 Panorama St Bayview Heights QLD 4868",
    "addr:housenumber":"18",
    "addr:postcode":"4868",
    "addr:street":"Panorama St",
    "iso:country":"AU",
    "sg:address":"18 Panorama St",
    "sg:city":"Bayview Heights",
    "sg:classifiers":[
        {
            "category":"Building & Trades",
            "subcategory":"Construction",
            "type":"Services"
        }
    ],
    "sg:phone":"+61 7 4054 3428",
    "sg:postcode":"4868",
    "sg:province":"QLD",
    "sg:tags":[
        "contractor"
    ],
    "wof:name":"Crawford H F",
    "wof:placetype":"venue"
},
  "geometry": {"coordinates":[145.72866821299999,-16.9601402283],"type":"Point"}
}