{
  "type": "Feature",
  "properties": {
    "iso:country":"AU",
    "sg:address":"Mt Buffalo Rd",
    "sg:city":"Porepunkah",
    "sg:classifiers":[
        {
            "category":"Recreation",
            "subcategory":"Amusement Park",
            "type":"Entertainment"
        }
    ],
    "sg:phone":"+61 3 5756 2478",
    "sg:postcode":"3740",
    "sg:province":"VIC",
    "wof:name":"U.F.O. Park Pty Ltd",
    "wof:placetype":"venue"
},
  "geometry": {"coordinates":[146.90419,-36.696098],"type":"Point"}
}