{
  "type": "Feature",
  "properties": {
    "iso:country":"AU",
    "sg:address":"156c King William Rd",
    "sg:city":"Hyde Park",
    "sg:classifiers":[
        {
            "category":"Cafe",
            "type":"Food & Drink"
        }
    ],
    "sg:phone":"+61 8 8373 7454",
    "sg:postcode":"5061",
    "sg:province":"SA",
    "wof:name":"Walters 156",
    "wof:placetype":"venue"
},
  "geometry": {"coordinates":[138.599884033,-34.954410553],"type":"Point"}
}