{
  "type": "Feature",
  "properties": {
    "iso:country":"AU",
    "sg:address":"436 Victoria St",
    "sg:city":"North Melbourne",
    "sg:classifiers":[
        {
            "category":"Health Services",
            "subcategory":"Doctor",
            "type":"Services"
        }
    ],
    "sg:phone":"+61 3 9328 4034",
    "sg:postcode":"3051",
    "sg:province":"VIC",
    "sg:tags":[
        "medical",
        "practitioner"
    ],
    "wof:name":"Lee Maylin Dr",
    "wof:placetype":"venue"
},
  "geometry": {"coordinates":[144.951568603,-37.805229187],"type":"Point"}
}