{
  "type": "Feature",
  "properties": {
    "iso:country":"AU",
    "sg:address":"55 Old Northern Rd",
    "sg:city":"Everton Park",
    "sg:classifiers":[
        {
            "category":"Professional",
            "subcategory":"Art Services",
            "type":"Services"
        }
    ],
    "sg:phone":"+61 7 3855 3413",
    "sg:postcode":"4053",
    "sg:province":"QLD",
    "sg:tags":[
        "artist"
    ],
    "wof:name":"Geoff Hale",
    "wof:placetype":"venue"
},
  "geometry": {"coordinates":[152.98719787600001,-27.39727211],"type":"Point"}
}