{
  "type": "Feature",
  "properties": {
    "addr:full":"80 Devonshire St Surry Hills NSW 2010",
    "addr:housenumber":"80",
    "addr:postcode":"2010",
    "addr:street":"Devonshire St",
    "iso:country":"AU",
    "sg:address":"80 Devonshire St",
    "sg:city":"Surry Hills",
    "sg:classifiers":[
        {
            "category":"Health Services",
            "subcategory":"Optometrist",
            "type":"Services"
        }
    ],
    "sg:phone":"+61 2 9281 4334",
    "sg:postcode":"2010",
    "sg:province":"NSW",
    "wof:name":"Surry Hills Optical",
    "wof:placetype":"venue"
},
  "geometry": {"coordinates":[151.20814514200001,-33.8862113953],"type":"Point"}
}