{
  "type": "Feature",
  "properties": {
    "iso:country":"AU",
    "sg:address":"Unit 4 10 Saggart Field Rd",
    "sg:city":"Minto",
    "sg:classifiers":[
        {
            "category":"Professional",
            "type":"Services"
        }
    ],
    "sg:phone":"+61 2 9820 4111",
    "sg:postcode":"2566",
    "sg:province":"NSW",
    "sg:tags":[
        "transport"
    ],
    "wof:name":"Devlin Specialised Transport Pty Ltd",
    "wof:placetype":"venue"
},
  "geometry": {"coordinates":[150.83773803700001,-34.0236930847],"type":"Point"}
}