{
  "type": "Feature",
  "properties": {
    "iso:country":"AU",
    "sg:address":"15 Kalimna Ave",
    "sg:city":"Mulgrave",
    "sg:classifiers":[
        {
            "category":"Building & Trades",
            "subcategory":"Construction",
            "type":"Services"
        }
    ],
    "sg:phone":"+61 3 9562 3219",
    "sg:postcode":"3170",
    "sg:province":"VIC",
    "sg:tags":[
        "contractor"
    ],
    "wof:name":"Excel Stone",
    "wof:placetype":"venue"
},
  "geometry": {"coordinates":[145.14976501500001,-37.9260559082],"type":"Point"}
}