{
  "type": "Feature",
  "properties": {
    "addr:full":"50 Florizel St Burwood VIC 3125",
    "addr:housenumber":"50",
    "addr:postcode":"3125",
    "addr:street":"Florizel St",
    "iso:country":"AU",
    "sg:address":"50 Florizel St",
    "sg:city":"Burwood",
    "sg:classifiers":[
        {
            "category":"Professional",
            "subcategory":"Management & Consulting",
            "type":"Services"
        }
    ],
    "sg:phone":"+61 417 700 611",
    "sg:postcode":"3125",
    "sg:province":"VIC",
    "sg:tags":[
        "consultant",
        "business"
    ],
    "wof:name":"Food Advantage Consultancy",
    "wof:placetype":"venue"
},
  "geometry": {"coordinates":[145.07901000999999,-37.8569526672],"type":"Point"}
}