{
  "type": "Feature",
  "properties": {
    "iso:country":"AU",
    "sg:address":"1 Perricoota Rd",
    "sg:city":"Moama",
    "sg:classifiers":[
        {
            "category":"Travel",
            "subcategory":"Hotels & Motels",
            "type":"Entertainment"
        }
    ],
    "sg:phone":"+61 3 5482 4366",
    "sg:postcode":"2731",
    "sg:province":"NSW",
    "wof:name":"Sportslander Motor Inn",
    "wof:placetype":"venue"
},
  "geometry": {"coordinates":[144.732635,-36.094696],"type":"Point"}
}