{
  "type": "Feature",
  "properties": {
    "addr:full":"1 Perricoota Rd Moama NSW 2731",
    "addr:housenumber":"1",
    "addr:postcode":"2731",
    "addr:street":"Perricoota Rd",
    "iso:country":"AU",
    "sg:address":"1 Perricoota Rd",
    "sg:city":"Moama",
    "sg:classifiers":[
        {
            "category":"Travel",
            "subcategory":"Hotels & Motels",
            "type":"Entertainment"
        }
    ],
    "sg:phone":"+61 3 5482 4366",
    "sg:postcode":"2731",
    "sg:province":"NSW",
    "wof:name":"Sportslander Motor Inn",
    "wof:placetype":"venue"
},
  "geometry": {"coordinates":[144.73263499999999,-36.094696],"type":"Point"}
}