{
  "type": "Feature",
  "properties": {
    "addr:full":"McIntyre Rd Millicent SA 5280",
    "addr:postcode":"5280",
    "addr:street":"Mcintyre Rd",
    "iso:country":"AU",
    "sg:address":"McIntyre Rd",
    "sg:city":"Millicent",
    "sg:classifiers":[
        {
            "category":"Professional",
            "subcategory":"Engineering",
            "type":"Services"
        }
    ],
    "sg:phone":"+61 8 8733 3332",
    "sg:postcode":"5280",
    "sg:province":"SA",
    "sg:tags":[
        "engineer"
    ],
    "wof:name":"J & M Shanks Pty Ltd",
    "wof:placetype":"venue"
},
  "geometry": {"coordinates":[140.336533,-37.587082],"type":"Point"}
}