{
  "type": "Feature",
  "properties": {
    "iso:country":"AU",
    "sg:address":"83 Florence St",
    "sg:city":"Port Pirie",
    "sg:classifiers":[
        {
            "category":"Personal",
            "subcategory":"Beauty Salon",
            "type":"Services"
        }
    ],
    "sg:phone":"+61 8 8633 1554",
    "sg:postcode":"5540",
    "sg:province":"SA",
    "wof:name":"Beauty By Selina",
    "wof:placetype":"venue"
},
  "geometry": {"coordinates":[138.008865356,-33.17735672],"type":"Point"}
}