{
  "type": "Feature",
  "properties": {
    "addr:full":"12 Charles St Forestville SA 5035",
    "addr:housenumber":"12",
    "addr:postcode":"5035",
    "addr:street":"Charles St",
    "iso:country":"AU",
    "sg:address":"12 Charles St",
    "sg:city":"Forestville",
    "sg:classifiers":[
        {
            "category":"Communications",
            "subcategory":"Film & Video Production",
            "type":"Services"
        }
    ],
    "sg:phone":"+61 421 321 544",
    "sg:postcode":"5035",
    "sg:province":"SA",
    "sg:tags":[
        "equipment",
        "amplification",
        "music"
    ],
    "wof:name":"Pro Harmonic Techical Services",
    "wof:placetype":"venue"
},
  "geometry": {"coordinates":[138.58198547399999,-34.9500427246],"type":"Point"}
}