{
  "type": "Feature",
  "properties": {
    "addr:full":"110 Lambert St Kangaroo Point QLD 4169",
    "addr:housenumber":"110",
    "addr:postcode":"4169",
    "addr:street":"Lambert St",
    "iso:country":"AU",
    "sg:address":"110 Lambert St",
    "sg:city":"Kangaroo Point",
    "sg:classifiers":[
        {
            "category":"Wholesale",
            "subcategory":"Apparel",
            "type":"Manufacturing & Wholesale Goods"
        }
    ],
    "sg:phone":"+61 409 473 474",
    "sg:postcode":"4169",
    "sg:province":"QLD",
    "sg:tags":[
        "wholesaler",
        "mfrs",
        "dress"
    ],
    "wof:name":"Pertama Imports Pty Ltd",
    "wof:placetype":"venue"
},
  "geometry": {"coordinates":[153.03848266599999,-27.4754924774],"type":"Point"}
}