{
  "type": "Feature",
  "properties": {
    "iso:country":"AU",
    "sg:address":"73 Parks St",
    "sg:city":"Oak Flats",
    "sg:classifiers":[
        {
            "category":"Home & Garden",
            "subcategory":"Carpets & Floor Coverings",
            "type":"Retail Goods"
        }
    ],
    "sg:phone":"+61 411 189 237",
    "sg:postcode":"2529",
    "sg:province":"NSW",
    "sg:tags":[
        "wood"
    ],
    "wof:name":"Leisure Coast Bamboo Flooring Pty Ltd",
    "wof:placetype":"venue"
},
  "geometry": {"coordinates":[150.80825805699999,-34.5581092834],"type":"Point"}
}