{
  "type": "Feature",
  "properties": {
    "iso:country":"AU",
    "sg:address":"206 Canterbury Rd",
    "sg:city":"Bayswater North",
    "sg:classifiers":[
        {
            "category":"Home & Garden",
            "subcategory":"Building Materials",
            "type":"Retail Goods"
        }
    ],
    "sg:phone":"+61 3 9720 1377",
    "sg:postcode":"3153",
    "sg:province":"VIC",
    "sg:tags":[
        "fencing"
    ],
    "wof:name":"Redgum Timber Centre Pty Ltd",
    "wof:placetype":"venue"
},
  "geometry": {"coordinates":[145.28157043499999,-37.827835083],"type":"Point"}
}