{
  "type": "Feature",
  "properties": {
    "addr:full":"Shed 1/ 62 Mount Plesant Rd Gympie QLD 4570",
    "addr:housenumber":"1 / 62",
    "addr:postcode":"4570",
    "addr:street":"Mount Plesant Rd",
    "iso:country":"AU",
    "sg:address":"Shed 1/ 62 Mount Plesant Rd",
    "sg:city":"Gympie",
    "sg:classifiers":[
        {
            "category":"Manufacturing",
            "subcategory":"Metals",
            "type":"Manufacturing & Wholesale Goods"
        }
    ],
    "sg:phone":"+61 7 5482 5977",
    "sg:postcode":"4570",
    "sg:province":"QLD",
    "sg:tags":[
        "steel",
        "fabricator",
        "mfrs"
    ],
    "wof:name":"Gympie Sheet Metal Pty Ltd",
    "wof:placetype":"venue"
},
  "geometry": {"coordinates":[152.67323303200001,-26.2009925842],"type":"Point"}
}