{
  "type": "Feature",
  "properties": {
    "iso:country":"AU",
    "sg:address":"67 Harvey St",
    "sg:city":"Dumbleyung",
    "sg:classifiers":[
        {
            "category":"Building & Trades",
            "subcategory":"Construction",
            "type":"Services"
        }
    ],
    "sg:phone":"+61 8 9863 4066",
    "sg:postcode":"6350",
    "sg:province":"WA",
    "sg:tags":[
        "earth",
        "excavating",
        "moving",
        "contractor"
    ],
    "wof:name":"Parnell G W & O H",
    "wof:placetype":"venue"
},
  "geometry": {"coordinates":[117.736214,-33.313423],"type":"Point"}
}