{
  "type": "Feature",
  "properties": {
    "addr:full":"35 Boyanna Rd Glen Waverley VIC 3150",
    "addr:housenumber":"35",
    "addr:postcode":"3150",
    "addr:street":"Boyanna Rd",
    "iso:country":"AU",
    "sg:address":"35 Boyanna Rd",
    "sg:city":"Glen Waverley",
    "sg:classifiers":[
        {
            "category":"Social Services",
            "subcategory":"Child Care",
            "type":"Services"
        }
    ],
    "sg:phone":"+61 3 9802 8836",
    "sg:postcode":"3150",
    "sg:province":"VIC",
    "sg:tags":[
        "support",
        "health"
    ],
    "wof:name":"Maternal & Child Health Centres",
    "wof:placetype":"venue"
},
  "geometry": {"coordinates":[145.17729187,-37.8769302368],"type":"Point"}
}