{
  "type": "Feature",
  "properties": {
    "iso:country":"AU",
    "sg:address":"49 Hudson St",
    "sg:city":"Bayswater",
    "sg:classifiers":[
        {
            "category":"Building & Trades",
            "subcategory":"Landscaping Services",
            "type":"Services"
        }
    ],
    "sg:phone":"+61 401 384 924",
    "sg:postcode":"6053",
    "sg:province":"WA",
    "sg:tags":[
        "designer",
        "landscape",
        "contractor"
    ],
    "wof:name":"Mr Green Lawns & Landscapes",
    "wof:placetype":"venue"
},
  "geometry": {"coordinates":[115.908790588,-31.9094657898],"type":"Point"}
}