{
  "type": "Feature",
  "properties": {
    "iso:country":"AU",
    "sg:address":"Unit 6, 113 High Rd",
    "sg:city":"Willetton",
    "sg:classifiers":[
        {
            "category":"Manufacturing",
            "subcategory":"Retail Goods",
            "type":"Manufacturing & Wholesale Goods"
        }
    ],
    "sg:phone":"+61 13 20 09",
    "sg:postcode":"6155",
    "sg:province":"WA",
    "sg:tags":[
        "merchant",
        "pump",
        "mfrs"
    ],
    "wof:name":"Hugall & Hoile",
    "wof:placetype":"venue"
},
  "geometry": {"coordinates":[115.890411,-32.038761],"type":"Point"}
}