{
  "type": "Feature",
  "properties": {
    "addr:full":"11 Compass Crt Somerville VIC 3912",
    "addr:housenumber":"11",
    "addr:postcode":"3912",
    "addr:street":"Compass Crt",
    "iso:country":"AU",
    "sg:address":"11 Compass Crt",
    "sg:city":"Somerville",
    "sg:classifiers":[
        {
            "category":"Building & Trades",
            "subcategory":"Construction",
            "type":"Services"
        }
    ],
    "sg:phone":"+61 3 5977 5029",
    "sg:postcode":"3912",
    "sg:province":"VIC",
    "sg:tags":[
        "concrete",
        "contractor"
    ],
    "wof:name":"Gray P R Concreting Pty Ltdd",
    "wof:placetype":"venue"
},
  "geometry": {"coordinates":[145.18731689399999,-38.2350196838],"type":"Point"}
}