{
  "type": "Feature",
  "properties": {
    "iso:country":"AU",
    "sg:address":"445-447 Goulburn Valley Hwy",
    "sg:city":"Shepparton",
    "sg:classifiers":[
        {
            "category":"Wholesale",
            "subcategory":"Metals & Minerals",
            "type":"Manufacturing & Wholesale Goods"
        }
    ],
    "sg:phone":"+61 3 5821 6100",
    "sg:postcode":"3630",
    "sg:province":"VIC",
    "sg:tags":[
        "steel",
        "stainless",
        "product",
        "equipment"
    ],
    "wof:name":"Fagersta Steels Pty Ltd",
    "wof:placetype":"venue"
},
  "geometry": {"coordinates":[145.409500122,-36.3885993958],"type":"Point"}
}