{
  "type": "Feature",
  "properties": {
    "addr:full":"Central Market - Stall 57 Adelaide SA 5000",
    "addr:housenumber":"57",
    "addr:postcode":"5000",
    "iso:country":"AU",
    "sg:address":"Central Market - Stall 57",
    "sg:city":"Adelaide",
    "sg:classifiers":[
        {
            "category":"Food & Beverages",
            "subcategory":"Fruits & Vegetables",
            "type":"Retail Goods"
        }
    ],
    "sg:phone":"+61 8 8231 4994",
    "sg:postcode":"5000",
    "sg:province":"SA",
    "sg:tags":[
        "greengrocer",
        "fruiterer"
    ],
    "wof:name":"Aubergine's Fresh Produce",
    "wof:placetype":"venue"
},
  "geometry": {"coordinates":[138.60076904300001,-34.9256401062],"type":"Point"}
}