{
  "type": "Feature",
  "properties": {
    "iso:country":"AU",
    "sg:address":"51 Sixth Ave",
    "sg:city":"Maylands",
    "sg:classifiers":[
        {
            "category":"Travel",
            "subcategory":"Hostel",
            "type":"Entertainment"
        }
    ],
    "sg:phone":"+61 8 9370 2455",
    "sg:postcode":"6051",
    "sg:province":"WA",
    "sg:tags":[
        "home"
    ],
    "wof:name":"Ida Mann Hostel",
    "wof:placetype":"venue"
},
  "geometry": {"coordinates":[115.889153,-31.92964],"type":"Point"}
}