{
  "type": "Feature",
  "properties": {
    "addr:full":"409 Mains Rd MacGregor QLD 4109",
    "addr:housenumber":"409",
    "addr:postcode":"4109",
    "addr:street":"Mains Rd",
    "iso:country":"AU",
    "sg:address":"409 Mains Rd",
    "sg:city":"MacGregor",
    "sg:classifiers":[
        {
            "category":"Travel",
            "subcategory":"Travel Agent",
            "type":"Entertainment"
        }
    ],
    "sg:phone":"+61 7 3343 8088",
    "sg:postcode":"4109",
    "sg:province":"QLD",
    "sg:tags":[
        "consultant"
    ],
    "wof:name":"Jet Travel Pty Ltd",
    "wof:placetype":"venue"
},
  "geometry": {"coordinates":[153.06483459500001,-27.5690193176],"type":"Point"}
}