{
  "type": "Feature",
  "properties": {
    "addr:full":"262 Johnston St Fitzroy VIC 3065",
    "addr:housenumber":"262",
    "addr:postcode":"3065",
    "addr:street":"Johnston St",
    "iso:country":"AU",
    "sg:address":"262 Johnston St",
    "sg:city":"Fitzroy",
    "sg:classifiers":[
        {
            "category":"Fast Food",
            "type":"Food & Drink"
        }
    ],
    "sg:phone":"+61 3 9419 1164",
    "sg:postcode":"3065",
    "sg:province":"VIC",
    "sg:tags":[
        "away",
        "take"
    ],
    "wof:name":"Mario's Pizza",
    "wof:placetype":"venue"
},
  "geometry": {"coordinates":[144.98367309599999,-37.7990112305],"type":"Point"}
}