{
  "type": "Feature",
  "properties": {
    "addr:full":"Unit 10, 9 Powells Rd Brookvale NSW 2100",
    "addr:housenumber":"9",
    "addr:postcode":"2100",
    "addr:street":"Powells Rd",
    "iso:country":"AU",
    "sg:address":"Unit 10, 9 Powells Rd",
    "sg:city":"Brookvale",
    "sg:classifiers":[
        {
            "category":"Manufacturing",
            "subcategory":"Metals",
            "type":"Manufacturing & Wholesale Goods"
        }
    ],
    "sg:phone":"+61 2 9907 3200",
    "sg:postcode":"2100",
    "sg:province":"NSW",
    "sg:tags":[
        "sheet",
        "worker"
    ],
    "wof:name":"Viking Sheet Metal & Engineering",
    "wof:placetype":"venue"
},
  "geometry": {"coordinates":[151.27342224099999,-33.7666625977],"type":"Point"}
}