{
  "type": "Feature",
  "properties": {
    "addr:full":"7 Farrall Rd Midvale WA 6056",
    "addr:housenumber":"7",
    "addr:postcode":"6056",
    "addr:street":"Farrall Rd",
    "iso:country":"AU",
    "sg:address":"7 Farrall Rd",
    "sg:city":"Midvale",
    "sg:classifiers":[
        {
            "category":"Building & Trades",
            "subcategory":"Construction",
            "type":"Services"
        }
    ],
    "sg:phone":"+61 8 9250 1147",
    "sg:postcode":"6056",
    "sg:province":"WA",
    "sg:tags":[
        "fencing",
        "contractor"
    ],
    "wof:name":"Country Leisure Centre",
    "wof:placetype":"venue"
},
  "geometry": {"coordinates":[116.03256225600001,-31.893863678],"type":"Point"}
}