{
  "type": "Feature",
  "properties": {
    "iso:country":"AU",
    "sg:address":"Rear of 29 Allawah St",
    "sg:city":"Blacktown",
    "sg:classifiers":[
        {
            "category":"Personal",
            "subcategory":"Massage",
            "type":"Services"
        }
    ],
    "sg:phone":"+61 2 9671 1282",
    "sg:postcode":"2148",
    "sg:province":"NSW",
    "sg:tags":[
        "therapy"
    ],
    "wof:name":"Virgos Beauty & Skin Care",
    "wof:placetype":"venue"
},
  "geometry": {"coordinates":[150.90028381400001,-33.7705612183],"type":"Point"}
}