{
  "type": "Feature",
  "properties": {
    "addr:full":"54-58 Payneham Rd Stepney SA 5069",
    "addr:housenumber":"54-58",
    "addr:postcode":"5069",
    "addr:street":"Payneham Rd",
    "iso:country":"AU",
    "sg:address":"54-58 Payneham Rd",
    "sg:city":"Stepney",
    "sg:classifiers":[
        {
            "category":"Military Area",
            "subcategory":"Air Force Base",
            "type":"Public Place"
        }
    ],
    "sg:phone":"+61 8 8363 1606",
    "sg:postcode":"5069",
    "sg:province":"SA",
    "sg:tags":[
        "men's",
        "tailor"
    ],
    "wof:name":"Gerry's Tailoring",
    "wof:placetype":"venue"
},
  "geometry": {"coordinates":[138.62699890100001,-34.9107780457],"type":"Point"}
}