{
  "type": "Feature",
  "properties": {
    "addr:full":"298 Main Rd Glenorchy TAS 7010",
    "addr:housenumber":"298",
    "addr:postcode":"7010",
    "addr:street":"Main Rd",
    "iso:country":"AU",
    "sg:address":"298 Main Rd",
    "sg:city":"Glenorchy",
    "sg:classifiers":[
        {
            "category":"Fast Food",
            "type":"Food & Drink"
        }
    ],
    "sg:phone":"+61 3 6272 7073",
    "sg:postcode":"7010",
    "sg:province":"TAS",
    "sg:tags":[
        "away",
        "take"
    ],
    "wof:name":"New Elwick Takeaway Kebab & Fish N Chips",
    "wof:placetype":"venue"
},
  "geometry": {"coordinates":[147.28335571299999,-42.8346366882],"type":"Point"}
}