{
  "type": "Feature",
  "properties": {
    "addr:full":"Sutherland Rd Jannali NSW 2226",
    "addr:postcode":"2226",
    "addr:street":"Sutherland Rd",
    "iso:country":"AU",
    "sg:address":"Sutherland Rd",
    "sg:city":"Jannali",
    "sg:classifiers":[
        {
            "category":"Education",
            "subcategory":"School",
            "type":"Public Place"
        }
    ],
    "sg:phone":"+61 2 9528 9315",
    "sg:postcode":"2226",
    "sg:province":"NSW",
    "sg:tags":[
        "state",
        "-",
        "nsw"
    ],
    "wof:name":"Jannali Primary School",
    "wof:placetype":"venue"
},
  "geometry": {"coordinates":[151.062057495,-34.0165061951],"type":"Point"}
}