{
  "type": "Feature",
  "properties": {
    "addr:full":"97 Cathies La Wantirna South VIC 3152",
    "addr:housenumber":"97",
    "addr:postcode":"3152",
    "addr:street":"Cathies La",
    "iso:country":"AU",
    "sg:address":"97 Cathies La",
    "sg:city":"Wantirna South",
    "sg:classifiers":[
        {
            "category":"Health Services",
            "subcategory":"Dentist",
            "type":"Services"
        }
    ],
    "sg:phone":"+61 3 9800 2288",
    "sg:postcode":"3152",
    "sg:province":"VIC",
    "wof:name":"Irving Graham Dr B.D.Sc(Melb) L.D.S.(Vic)",
    "wof:placetype":"venue"
},
  "geometry": {"coordinates":[145.21470642099999,-37.8705558777],"type":"Point"}
}