{
  "type": "Feature",
  "properties": {
    "addr:full":"181 Walnut Ave Mildura VIC 3500",
    "addr:housenumber":"181",
    "addr:postcode":"3500",
    "addr:street":"Walnut Ave",
    "iso:country":"AU",
    "sg:address":"181 Walnut Ave",
    "sg:city":"Mildura",
    "sg:classifiers":[
        {
            "category":"Real Estate",
            "subcategory":"Architect",
            "type":"Services"
        }
    ],
    "sg:phone":"+61 3 5022 2224",
    "sg:postcode":"3500",
    "sg:province":"VIC",
    "sg:tags":[
        "building",
        "designer"
    ],
    "wof:name":"Gsd Architects",
    "wof:placetype":"venue"
},
  "geometry": {"coordinates":[142.15150451700001,-34.185749054],"type":"Point"}
}