{
  "type": "Feature",
  "properties": {
    "addr:full":"Shop 22 Britannia Mall Mitcham VIC 3132",
    "addr:housenumber":"shop 22 britannia mall",
    "addr:postcode":"3132",
    "iso:country":"AU",
    "sg:address":"Shop 22",
    "sg:city":"Britannia Mall Mitcham",
    "sg:classifiers":[
        {
            "category":"Personal",
            "subcategory":"Beauty Salon",
            "type":"Services"
        }
    ],
    "sg:phone":"+61 3 9874 6318",
    "sg:postcode":"3132",
    "sg:province":"VIC",
    "wof:name":"Tropical Body Anti-Aging Clinic",
    "wof:placetype":"venue"
},
  "geometry": {"coordinates":[145.192062378,-37.8160820007],"type":"Point"}
}