{
  "type": "Feature",
  "properties": {
    "addr:full":"Unumgar St Woodenbong NSW 2476",
    "addr:postcode":"2476",
    "addr:street":"Unumgar St",
    "iso:country":"AU",
    "sg:address":"Unumgar St",
    "sg:city":"Woodenbong",
    "sg:classifiers":[
        {
            "category":"Education",
            "subcategory":"School",
            "type":"Public Place"
        }
    ],
    "sg:phone":"+61 2 6635 1281",
    "sg:postcode":"2476",
    "sg:province":"NSW",
    "sg:tags":[
        "state",
        "-",
        "nsw"
    ],
    "wof:name":"Woodenbong Central School",
    "wof:placetype":"venue"
},
  "geometry": {"coordinates":[152.61280822800001,-28.3889427185],"type":"Point"}
}