{
  "type": "Feature",
  "properties": {
    "addr:full":"Unit 8/ 925 Wanneroo Rd Wanneroo WA 6065",
    "addr:housenumber":"/ 925",
    "addr:postcode":"6065",
    "addr:street":"Wanneroo Rd",
    "iso:country":"AU",
    "sg:address":"Unit 8/ 925 Wanneroo Rd",
    "sg:city":"Wanneroo",
    "sg:classifiers":[
        {
            "category":"Personal",
            "subcategory":"Piercing",
            "type":"Services"
        }
    ],
    "sg:phone":"+61 8 9306 8090",
    "sg:postcode":"6065",
    "sg:province":"WA",
    "sg:tags":[
        "body",
        "ear"
    ],
    "wof:name":"Abandon Tattoo Studio",
    "wof:placetype":"venue"
},
  "geometry": {"coordinates":[115.80484008800001,-31.754699707],"type":"Point"}
}