{
  "type": "Feature",
  "properties": {
    "addr:full":"2 / 31 Colin Jamieson Drv Welshpool WA 6106",
    "addr:housenumber":"/ 31",
    "addr:postcode":"6106",
    "addr:street":"Colin Jamieson Drv",
    "iso:country":"AU",
    "sg:address":"2 / 31 Colin Jamieson Drv",
    "sg:city":"Welshpool",
    "sg:classifiers":[
        {
            "category":"Manufacturing",
            "subcategory":"Retail Goods",
            "type":"Manufacturing & Wholesale Goods"
        }
    ],
    "sg:phone":"+61 8 9451 3800",
    "sg:postcode":"6106",
    "sg:province":"WA",
    "sg:tags":[
        "merchant",
        "pump",
        "mfrs"
    ],
    "sg:website":"http://www.advancedpumps.com.au",
    "wof:name":"Advanced Pump Technologies Pty Ltd",
    "wof:placetype":"venue"
},
  "geometry": {"coordinates":[115.936698914,-31.9930839539],"type":"Point"}
}