{
  "type": "Feature",
  "properties": {
    "addr:full":"9 Federation Pl Nowra North NSW 2541",
    "addr:housenumber":"9",
    "addr:postcode":"2541",
    "addr:street":"Pl",
    "iso:country":"AU",
    "sg:address":"9 Federation Pl",
    "sg:city":"Nowra North",
    "sg:classifiers":[
        {
            "category":"Building & Trades",
            "subcategory":"Construction",
            "type":"Services"
        }
    ],
    "sg:phone":"+61 2 4421 8406",
    "sg:postcode":"2541",
    "sg:province":"NSW",
    "sg:tags":[
        "contractor"
    ],
    "wof:name":"Daley Brian Building & Design",
    "wof:placetype":"venue"
},
  "geometry": {"coordinates":[150.584716797,-34.8575363159],"type":"Point"}
}