{
  "type": "Feature",
  "properties": {
    "addr:full":"PO Box 2733 Kent Town SA 5071",
    "addr:postcode":"5071",
    "iso:country":"AU",
    "sg:address":"PO Box 2733",
    "sg:city":"Kent Town",
    "sg:classifiers":[
        {
            "category":"Professional",
            "subcategory":"Computer Services",
            "type":"Services"
        }
    ],
    "sg:phone":"+61 8 8228 2010",
    "sg:postcode":"5071",
    "sg:province":"SA",
    "sg:tags":[
        "information"
    ],
    "wof:name":"The Australian Wine & Brandy Corporation Information Centre",
    "wof:placetype":"venue"
},
  "geometry": {"coordinates":[138.616363525,-34.9215393066],"type":"Point"}
}