{
  "type": "Feature",
  "properties": {
    "addr:full":"82 Lantana Rd Engadine NSW 2233",
    "addr:housenumber":"82",
    "addr:postcode":"2233",
    "addr:street":"Lantana Rd",
    "iso:country":"AU",
    "sg:address":"82 Lantana Rd",
    "sg:city":"Engadine",
    "sg:classifiers":[
        {
            "category":"Building & Trades",
            "subcategory":"Plumbing",
            "type":"Services"
        }
    ],
    "sg:phone":"+61 2 9520 3180",
    "sg:postcode":"2233",
    "sg:province":"NSW",
    "sg:tags":[
        "plumber",
        "gasfitters"
    ],
    "wof:name":"Minton Greg",
    "wof:placetype":"venue"
},
  "geometry": {"coordinates":[151.014526367,-34.0548706055],"type":"Point"}
}