{
  "type": "Feature",
  "properties": {
    "addr:full":"Cnr Bendooley St & Hume Hwy Welby NSW 2575",
    "addr:postcode":"2575",
    "addr:street":"Cnr Bendooley St & Hume Hwy",
    "iso:country":"AU",
    "sg:address":"Cnr Bendooley St & Hume Hwy",
    "sg:city":"Welby",
    "sg:classifiers":[
        {
            "category":"Organizations",
            "subcategory":"Non-profit Organization",
            "type":"Services"
        }
    ],
    "sg:phone":"+61 2 4872 1247",
    "sg:postcode":"2575",
    "sg:province":"NSW",
    "sg:tags":[
        "support",
        "disability",
        "organisation"
    ],
    "wof:name":"Challenge Foundation Southern Highlands",
    "wof:placetype":"venue"
},
  "geometry": {"coordinates":[150.42027282699999,-34.4382362366],"type":"Point"}
}