{
  "type": "Feature",
  "properties": {
    "addr:full":"1172 Creek Rd Carindale QLD 4152",
    "addr:housenumber":"1172",
    "addr:postcode":"4152",
    "addr:street":"Creek Rd",
    "iso:country":"AU",
    "sg:address":"1172 Creek Rd",
    "sg:city":"Carindale",
    "sg:classifiers":[
        {
            "category":"Health Services",
            "subcategory":"Dentist",
            "type":"Services"
        }
    ],
    "sg:phone":"+61 7 3843 1155",
    "sg:postcode":"4152",
    "sg:province":"QLD",
    "wof:name":"Hammond Roland MS",
    "wof:placetype":"venue"
},
  "geometry": {"coordinates":[153.099700928,-27.5035400391],"type":"Point"}
}