{
  "type": "Feature",
  "properties": {
    "addr:full":"12 Hercules St Murrumbateman NSW 2582",
    "addr:housenumber":"12",
    "addr:postcode":"2582",
    "addr:street":"Hercules St",
    "iso:country":"AU",
    "sg:address":"12 Hercules St",
    "sg:city":"Murrumbateman",
    "sg:classifiers":[
        {
            "category":"Insurance",
            "subcategory":"Insurance Agent",
            "type":"Services"
        }
    ],
    "sg:phone":"+61 2 6226 8777",
    "sg:postcode":"2582",
    "sg:province":"NSW",
    "wof:name":"Landmark",
    "wof:placetype":"venue"
},
  "geometry": {"coordinates":[149.02894592300001,-34.9694747925],"type":"Point"}
}