{
  "type": "Feature",
  "properties": {
    "addr:full":"1 Burlington Pl Rutherford NSW 2320",
    "addr:housenumber":"1",
    "addr:postcode":"2320",
    "addr:street":"Burlington Pl",
    "iso:country":"AU",
    "sg:address":"1 Burlington Pl",
    "sg:city":"Rutherford",
    "sg:classifiers":[
        {
            "category":"Retail",
            "subcategory":"Auto Rental",
            "type":"Services"
        }
    ],
    "sg:phone":"+61 1800 077 353",
    "sg:postcode":"2320",
    "sg:province":"NSW",
    "sg:tags":[
        "car",
        "hire",
        "minibus"
    ],
    "wof:name":"Four Wheel Drive Hire Service",
    "wof:placetype":"venue"
},
  "geometry": {"coordinates":[151.505584717,-32.7143173218],"type":"Point"}
}