{
  "type": "Feature",
  "properties": {
    "addr:full":"1/57 Nealdon Drv Meadowbrook QLD 4131",
    "addr:housenumber":"/ 57",
    "addr:postcode":"4131",
    "addr:street":"Nealdon Drv",
    "iso:country":"AU",
    "sg:address":"1/57 Nealdon Drv",
    "sg:city":"Meadowbrook",
    "sg:classifiers":[
        {
            "category":"Real Estate",
            "subcategory":"Architect",
            "type":"Services"
        }
    ],
    "sg:phone":"+61 7 3451 8888",
    "sg:postcode":"4131",
    "sg:province":"QLD",
    "sg:tags":[
        "building",
        "designer"
    ],
    "wof:name":"BMW Homes Pty Ltd",
    "wof:placetype":"venue"
},
  "geometry": {"coordinates":[153.13421630900001,-27.6667327881],"type":"Point"}
}