{
  "type": "Feature",
  "properties": {
    "iso:country":"AU",
    "sg:address":"103 Victoria Ave",
    "sg:city":"Albert Park",
    "sg:classifiers":[
        {
            "category":"Personal",
            "subcategory":"Day Spa",
            "type":"Services"
        }
    ],
    "sg:phone":"+61 3 9686 6000",
    "sg:postcode":"3206",
    "sg:province":"VIC",
    "wof:name":"Endota Spa",
    "wof:placetype":"venue"
},
  "geometry": {"coordinates":[144.95082099999999,-37.844868],"type":"Point"}
}