{
  "type": "Feature",
  "properties": {
    "addr:full":"Level 1 Menai Marketplace Allison Cres Menai NSW 2234",
    "addr:postcode":"2234",
    "addr:street":"Allison Cres",
    "iso:country":"AU",
    "sg:address":"Level 1",
    "sg:city":"Menai Marketplace Allison Cres Menai",
    "sg:classifiers":[
        {
            "category":"Health Services",
            "subcategory":"Doctor",
            "type":"Services"
        }
    ],
    "sg:phone":"+61 2 9532 1350",
    "sg:postcode":"2234",
    "sg:province":"NSW",
    "sg:tags":[
        "medical",
        "practitioner"
    ],
    "wof:name":"Southern Radiology",
    "wof:placetype":"venue"
},
  "geometry": {"coordinates":[151.013671875,-34.0159759521],"type":"Point"}
}