{
  "type": "Feature",
  "properties": {
    "iso:country":"AU",
    "sg:address":"PO Box 3142",
    "sg:city":"Prahran East",
    "sg:classifiers":[
        {
            "category":"Manufacturing",
            "subcategory":"Food",
            "type":"Manufacturing & Wholesale Goods"
        }
    ],
    "sg:phone":"+61 419 899 919",
    "sg:postcode":"3181",
    "sg:province":"VIC",
    "sg:tags":[
        "function",
        "catering"
    ],
    "wof:name":"Quintessence Foods",
    "wof:placetype":"venue"
},
  "geometry": {"coordinates":[144.99708557100001,-37.8529281616],"type":"Point"}
}