{
  "type": "Feature",
  "properties": {
    "iso:country":"AU",
    "sg:address":"8a Albert St",
    "sg:city":"North Perth",
    "sg:classifiers":[
        {
            "category":"Professional",
            "subcategory":"Computer Services",
            "type":"Services"
        }
    ],
    "sg:phone":"+61 418 930 425",
    "sg:postcode":"6006",
    "sg:province":"WA",
    "sg:tags":[
        "consultant",
        "system"
    ],
    "wof:name":"Hensley High Technology",
    "wof:placetype":"venue"
},
  "geometry": {"coordinates":[115.85041809099999,-31.9299659729],"type":"Point"}
}