{
  "type": "Feature",
  "properties": {
    "iso:country":"AU",
    "sg:address":"4 Dashwood Rd",
    "sg:city":"Beaumont",
    "sg:classifiers":[
        {
            "category":"Banks & Credit Unions",
            "subcategory":"Financial Services",
            "type":"Services"
        }
    ],
    "sg:phone":"+61 8 8379 0088",
    "sg:postcode":"5066",
    "sg:province":"SA",
    "sg:tags":[
        "planning"
    ],
    "wof:name":"Budget Planners",
    "wof:placetype":"venue"
},
  "geometry": {"coordinates":[138.659881592,-34.9507865906],"type":"Point"}
}