{
  "type": "Feature",
  "properties": {
    "iso:country":"AU",
    "sg:address":"3 Stewart St",
    "sg:city":"Randwick",
    "sg:classifiers":[
        {
            "category":"Wholesale",
            "subcategory":"Apparel",
            "type":"Manufacturing & Wholesale Goods"
        }
    ],
    "sg:phone":"+61 2 9399 3299",
    "sg:postcode":"2031",
    "sg:province":"NSW",
    "sg:tags":[
        "wholesaler",
        "mfrs",
        "sportswear",
        "women's"
    ],
    "wof:name":"U Design Clothing Company Pty Ltd",
    "wof:placetype":"venue"
},
  "geometry": {"coordinates":[151.24392700199999,-33.9211120605],"type":"Point"}
}