{
  "type": "Feature",
  "properties": {
    "addr:full":"39 Wright St Sunshine VIC 3020",
    "addr:housenumber":"39",
    "addr:postcode":"3020",
    "addr:street":"Wright St",
    "iso:country":"AU",
    "sg:address":"39 Wright St",
    "sg:city":"Sunshine",
    "sg:classifiers":[
        {
            "category":"Wholesale",
            "subcategory":"Farm Supplies",
            "type":"Manufacturing & Wholesale Goods"
        }
    ],
    "sg:phone":"+61 3 9311 5343",
    "sg:postcode":"3020",
    "sg:province":"VIC",
    "sg:tags":[
        "feed",
        "supplement",
        "stock"
    ],
    "wof:name":"Specialty Mix Stock Food Pty Ltd",
    "wof:placetype":"venue"
},
  "geometry": {"coordinates":[144.83485400000001,-37.796532],"type":"Point"}
}