{
  "type": "Feature",
  "properties": {
    "iso:country":"AU",
    "sg:address":"1549 Anzac Pde",
    "sg:city":"La Perouse",
    "sg:classifiers":[
        {
            "category":"Professional",
            "subcategory":"Secretarial Services",
            "type":"Services"
        }
    ],
    "sg:phone":"+61 2 9694 1001",
    "sg:postcode":"2036",
    "sg:province":"NSW",
    "sg:tags":[
        "typing"
    ],
    "wof:name":"AlphaNumeric Business Services",
    "wof:placetype":"venue"
},
  "geometry": {"coordinates":[151.235671997,-33.9827384949],"type":"Point"}
}