{
  "type": "Feature",
  "properties": {
    "addr:full":"24 Box Rd Caringbah NSW 2229",
    "addr:housenumber":"24",
    "addr:postcode":"2229",
    "addr:street":"Box Rd",
    "iso:country":"AU",
    "sg:address":"24 Box Rd",
    "sg:city":"Caringbah",
    "sg:classifiers":[
        {
            "category":"Building & Trades",
            "subcategory":"Equipment Rental",
            "type":"Services"
        }
    ],
    "sg:phone":"+61 2 9525 0357",
    "sg:postcode":"2229",
    "sg:province":"NSW",
    "sg:tags":[
        "supply",
        "catering"
    ],
    "sg:website":"http://www.cateringequip.com.au",
    "wof:name":"Catering Equipment Specialists The",
    "wof:placetype":"venue"
},
  "geometry": {"coordinates":[151.12403869600001,-34.0247955322],"type":"Point"}
}