{
  "type": "Feature",
  "properties": {
    "addr:full":"21 Sydenham Rd Norwood SA 5067",
    "addr:housenumber":"21",
    "addr:postcode":"5067",
    "addr:street":"Sydenham Rd",
    "iso:country":"AU",
    "sg:address":"21 Sydenham Rd",
    "sg:city":"Norwood",
    "sg:classifiers":[
        {
            "category":"Wholesale",
            "subcategory":"Drugs",
            "type":"Manufacturing & Wholesale Goods"
        }
    ],
    "sg:phone":"+61 8 8363 0465",
    "sg:postcode":"5067",
    "sg:province":"SA",
    "sg:tags":[
        "wholesaler",
        "pharmaceutical",
        "product",
        "mfrs"
    ],
    "wof:name":"Pharmabroker Sales Pty Ltd",
    "wof:placetype":"venue"
},
  "geometry": {"coordinates":[138.627120972,-34.9173240662],"type":"Point"}
}