{
  "type": "Feature",
  "properties": {
    "addr:full":"69 Willington St Turrella NSW 2205",
    "addr:housenumber":"69",
    "addr:postcode":"2205",
    "addr:street":"Willington St",
    "iso:country":"AU",
    "sg:address":"69 Willington St",
    "sg:city":"Turrella",
    "sg:classifiers":[
        {
            "category":"Retail",
            "subcategory":"Repair Shop",
            "type":"Services"
        }
    ],
    "sg:phone":"+61 2 9567 1767",
    "sg:postcode":"2205",
    "sg:province":"NSW",
    "sg:tags":[
        "maintenance",
        "pool",
        "swimming"
    ],
    "wof:name":"Mike Cooper",
    "wof:placetype":"venue"
},
  "geometry": {"coordinates":[151.13978599999999,-33.93187],"type":"Point"}
}