{
  "type": "Feature",
  "properties": {
    "iso:country":"AU",
    "sg:address":"69 Taylors Rd",
    "sg:city":"St Albans",
    "sg:classifiers":[
        {
            "category":"Health Services",
            "subcategory":"Dentist",
            "type":"Services"
        }
    ],
    "sg:phone":"+61 3 9367 5087",
    "sg:postcode":"3021",
    "sg:province":"VIC",
    "sg:tags":[
        "technician",
        "dental"
    ],
    "wof:name":"M & L Dental Laboratories",
    "wof:placetype":"venue"
},
  "geometry": {"coordinates":[144.80744899999999,-37.728962],"type":"Point"}
}