{
  "type": "Feature",
  "properties": {
    "addr:full":"11 Lissner Crs Earlville QLD 4870",
    "addr:housenumber":"11",
    "addr:postcode":"4870",
    "addr:street":"Lissner Crs",
    "iso:country":"AU",
    "sg:address":"11 Lissner Crs",
    "sg:city":"Earlville",
    "sg:classifiers":[
        {
            "category":"Health Services",
            "subcategory":"Health Practitioner",
            "type":"Services"
        }
    ],
    "sg:phone":"+61 7 4033 6794",
    "sg:postcode":"4870",
    "sg:province":"QLD",
    "sg:tags":[
        "osteopath"
    ],
    "wof:name":"Margaret Martin",
    "wof:placetype":"venue"
},
  "geometry": {"coordinates":[145.736206055,-16.9474105835],"type":"Point"}
}