{
  "type": "Feature",
  "properties": {
    "iso:country":"AU",
    "sg:address":"1202 Hume Hwy",
    "sg:city":"Fawkner",
    "sg:classifiers":[
        {
            "category":"Autos & Motor Vehicles",
            "subcategory":"Automobile Sales",
            "type":"Retail Goods"
        }
    ],
    "sg:phone":"+61 3 9359 1188",
    "sg:postcode":"3060",
    "sg:province":"VIC",
    "sg:tags":[
        "car",
        "used"
    ],
    "wof:name":"Fawkner Discount Cars",
    "wof:placetype":"venue"
},
  "geometry": {"coordinates":[144.9609375,-37.7058105469],"type":"Point"}
}