{
  "type": "Feature",
  "properties": {
    "addr:full":"57 Seymour St Traralgon VIC 3844",
    "addr:housenumber":"57",
    "addr:postcode":"3844",
    "addr:street":"Seymour St",
    "iso:country":"AU",
    "sg:address":"57 Seymour St",
    "sg:city":"Traralgon",
    "sg:classifiers":[
        {
            "category":"Shopping",
            "subcategory":"Clothing, Apparel, & Fashions",
            "type":"Retail Goods"
        }
    ],
    "sg:phone":"+61 3 5174 8700",
    "sg:postcode":"3844",
    "sg:province":"VIC",
    "sg:tags":[
        "lady",
        "wear"
    ],
    "wof:name":"Bella Fashions",
    "wof:placetype":"venue"
},
  "geometry": {"coordinates":[146.537200928,-38.1962509155],"type":"Point"}
}