{
  "type": "Feature",
  "properties": {
    "addr:full":"Shop 5/68- 72 The Entrance Rd The Entrance NSW 2261",
    "addr:housenumber":"shop 5 / 68 72",
    "addr:postcode":"2261",
    "addr:street":"The Entrance Rd",
    "iso:country":"AU",
    "sg:address":"Shop 5/68- 72 The Entrance Rd",
    "sg:city":"The Entrance",
    "sg:classifiers":[
        {
            "category":"Autos & Motor Vehicles",
            "subcategory":"Boat Sales",
            "type":"Retail Goods"
        }
    ],
    "sg:phone":"+61 2 4334 1611",
    "sg:postcode":"2261",
    "sg:province":"NSW",
    "sg:tags":[
        "equipment",
        "yacht"
    ],
    "wof:name":"Twilight Marine Electronics",
    "wof:placetype":"venue"
},
  "geometry": {"coordinates":[151.49664300000001,-33.344574],"type":"Point"}
}