{
  "type": "Feature",
  "properties": {
    "iso:country":"AU",
    "sg:address":"272 Greensborough Hwy",
    "sg:city":"Macleod",
    "sg:classifiers":[
        {
            "category":"Building & Trades",
            "subcategory":"Construction",
            "type":"Services"
        }
    ],
    "sg:phone":"+61 3 9432 3966",
    "sg:postcode":"3085",
    "sg:province":"VIC",
    "sg:tags":[
        "pool",
        "swimming"
    ],
    "wof:name":"Better Built Pools",
    "wof:placetype":"venue"
},
  "geometry": {"coordinates":[145.081665039,-37.7168540955],"type":"Point"}
}