{
  "type": "Feature",
  "properties": {
    "addr:full":"Watt St Wonthaggi VIC 3995",
    "addr:postcode":"3995",
    "addr:street":"Watt St",
    "iso:country":"AU",
    "sg:address":"Watt St",
    "sg:city":"Wonthaggi",
    "sg:classifiers":[
        {
            "category":"Professional",
            "subcategory":"Computer Services",
            "type":"Services"
        }
    ],
    "sg:phone":"+61 3 5672 2484",
    "sg:postcode":"3995",
    "sg:province":"VIC",
    "sg:tags":[
        "information"
    ],
    "wof:name":"Wonthaggi Information Centre",
    "wof:placetype":"venue"
},
  "geometry": {"coordinates":[145.59431499999999,-38.606949],"type":"Point"}
}