{
  "type": "Feature",
  "properties": {
    "iso:country":"AU",
    "sg:address":"Suite 4006, Level 4, Highpoint Shopng Cntr, Rosamo",
    "sg:city":"Maribyrnong",
    "sg:classifiers":[
        {
            "category":"Professional",
            "subcategory":"Employment Agencies",
            "type":"Services"
        }
    ],
    "sg:phone":"+61 3 9201 5611",
    "sg:postcode":"3032",
    "sg:province":"VIC",
    "wof:name":"Manpower",
    "wof:placetype":"venue"
},
  "geometry": {"coordinates":[144.88632200000001,-37.771435],"type":"Point"}
}