{
  "type": "Feature",
  "properties": {
    "addr:full":"34 Davenport St Port Augusta SA 5700",
    "addr:housenumber":"34",
    "addr:postcode":"5700",
    "addr:street":"Davenport St",
    "iso:country":"AU",
    "sg:address":"34 Davenport St",
    "sg:city":"Port Augusta",
    "sg:classifiers":[
        {
            "category":"Food & Beverages",
            "subcategory":"Meat & Fish",
            "type":"Retail Goods"
        }
    ],
    "sg:phone":"+61 8 8642 2510",
    "sg:postcode":"5700",
    "sg:province":"SA",
    "sg:tags":[
        "seafood"
    ],
    "wof:name":"Gills Fisheries",
    "wof:placetype":"venue"
},
  "geometry": {"coordinates":[137.77525329599999,-32.4893074036],"type":"Point"}
}