{
  "type": "Feature",
  "properties": {
    "addr:full":"70 McEwen Rd Kyabram VIC 3620",
    "addr:housenumber":"70",
    "addr:postcode":"3620",
    "addr:street":"Mcewen Rd",
    "iso:country":"AU",
    "sg:address":"70 McEwen Rd",
    "sg:city":"Kyabram",
    "sg:classifiers":[
        {
            "category":"Manufacturing",
            "subcategory":"Building Materials",
            "type":"Manufacturing & Wholesale Goods"
        }
    ],
    "sg:phone":"+61 1300 367 587",
    "sg:postcode":"3620",
    "sg:province":"VIC",
    "sg:tags":[
        "equipment",
        "handling"
    ],
    "wof:name":"Harvey Smith Automotive",
    "wof:placetype":"venue"
},
  "geometry": {"coordinates":[145.03225707999999,-36.3060188293],"type":"Point"}
}