{
  "type": "Feature",
  "properties": {
    "addr:full":"106- 110 Parramatta Rd Stanmore NSW 2048",
    "addr:housenumber":"110",
    "addr:postcode":"2048",
    "addr:street":"Parramatta Rd",
    "iso:country":"AU",
    "sg:address":"106- 110 Parramatta Rd",
    "sg:city":"Stanmore",
    "sg:classifiers":[
        {
            "category":"Professional",
            "subcategory":"Accounting & Tax Preparation",
            "type":"Services"
        }
    ],
    "sg:phone":"+61 2 9565 1824",
    "sg:postcode":"2048",
    "sg:province":"NSW",
    "sg:tags":[
        "consultant",
        "taxation"
    ],
    "wof:name":"Kotselas Ramswarup Pty Ltd",
    "wof:placetype":"venue"
},
  "geometry": {"coordinates":[151.16894500000001,-33.887959],"type":"Point"}
}