{
  "type": "Feature",
  "properties": {
    "addr:full":"11 Lithgow St Fyshwick ACT 2609",
    "addr:housenumber":"11",
    "addr:postcode":"2609",
    "addr:street":"Lithgow St",
    "iso:country":"AU",
    "sg:address":"11 Lithgow St",
    "sg:city":"Fyshwick",
    "sg:classifiers":[
        {
            "category":"Manufacturing",
            "subcategory":"Metals",
            "type":"Manufacturing & Wholesale Goods"
        }
    ],
    "sg:phone":"+61 2 6280 0471",
    "sg:postcode":"2609",
    "sg:province":"ACT",
    "sg:tags":[
        "sheet",
        "worker"
    ],
    "wof:name":"Still Standing Sheetmetal Pty Ltd",
    "wof:placetype":"venue"
},
  "geometry": {"coordinates":[149.16510009800001,-35.3299217224],"type":"Point"}
}