{
  "type": "Feature",
  "properties": {
    "iso:country":"AU",
    "sg:address":"Cnr Maroondah Hwy & Hill Rd",
    "sg:city":"Coldstream",
    "sg:classifiers":[
        {
            "category":"Farming",
            "subcategory":"Vineyard",
            "type":"Manufacturing & Wholesale Goods"
        }
    ],
    "sg:phone":"+61 3 5962 2119",
    "sg:postcode":"3770",
    "sg:province":"VIC",
    "sg:tags":[
        "winery"
    ],
    "wof:name":"Rochford Wines",
    "wof:placetype":"venue"
},
  "geometry": {"coordinates":[145.37854,-37.724922],"type":"Point"}
}