{
  "type": "Feature",
  "properties": {
    "iso:country":"AU",
    "sg:address":"45 Station St",
    "sg:city":"Nerang",
    "sg:classifiers":[
        {
            "category":"Personal",
            "subcategory":"Barber",
            "type":"Services"
        }
    ],
    "sg:phone":"+61 7 5596 0672",
    "sg:postcode":"4211",
    "sg:province":"QLD",
    "wof:name":"Close Shaves Mens Hairdressing",
    "wof:placetype":"venue"
},
  "geometry": {"coordinates":[153.33932495100001,-27.9955806732],"type":"Point"}
}