{
  "type": "Feature",
  "properties": {
    "addr:full":"13 Ilmenite Crs Capel WA 6271",
    "addr:housenumber":"13",
    "addr:postcode":"6271",
    "addr:street":"Ilmenite Crs",
    "iso:country":"AU",
    "sg:address":"13 Ilmenite Crs",
    "sg:city":"Capel",
    "sg:classifiers":[
        {
            "category":"Retail",
            "subcategory":"Storage",
            "type":"Services"
        }
    ],
    "sg:phone":"+61 8 9727 3048",
    "sg:postcode":"6271",
    "sg:province":"WA",
    "wof:name":"Bigbox Self Storage",
    "wof:placetype":"venue"
},
  "geometry": {"coordinates":[115.55467224100001,-33.5524711609],"type":"Point"}
}