{
  "type": "Feature",
  "properties": {
    "addr:full":"98 Elizabeth St Ashfield NSW 2131",
    "addr:housenumber":"98",
    "addr:postcode":"2131",
    "addr:street":"Elizabeth St",
    "iso:country":"AU",
    "sg:address":"98 Elizabeth St",
    "sg:city":"Ashfield",
    "sg:classifiers":[
        {
            "category":"Health Services",
            "subcategory":"Health Practitioner",
            "type":"Services"
        }
    ],
    "sg:phone":"+61 2 9799 2385",
    "sg:postcode":"2131",
    "sg:province":"NSW",
    "sg:tags":[
        "bowen",
        "therapy"
    ],
    "wof:name":"Maloney Mary",
    "wof:placetype":"venue"
},
  "geometry": {"coordinates":[151.122802734,-33.8854446411],"type":"Point"}
}