{
  "type": "Feature",
  "properties": {
    "addr:full":"259 Queen St Brisbane QLD 4000",
    "addr:housenumber":"259",
    "addr:postcode":"4000",
    "addr:street":"Queen St",
    "iso:country":"AU",
    "sg:address":"259 Queen St",
    "sg:city":"Brisbane",
    "sg:classifiers":[
        {
            "category":"Food & Beverages",
            "subcategory":"Liquor & Beverages",
            "type":"Retail Goods"
        }
    ],
    "sg:phone":"+61 7 3299 1444",
    "sg:postcode":"4000",
    "sg:province":"QLD",
    "sg:tags":[
        "store"
    ],
    "wof:name":"Liquor Legends",
    "wof:placetype":"venue"
},
  "geometry": {"coordinates":[153.027832031,-27.4677867889],"type":"Point"}
}