{
  "type": "Feature",
  "properties": {
    "addr:full":"350 Blackshaws Rd Altona North VIC 3025",
    "addr:housenumber":"350",
    "addr:postcode":"3025",
    "addr:street":"Blackshaws Rd",
    "iso:country":"AU",
    "sg:address":"350 Blackshaws Rd",
    "sg:city":"Altona North",
    "sg:classifiers":[
        {
            "category":"Health Services",
            "subcategory":"Doctor",
            "type":"Services"
        }
    ],
    "sg:phone":"+61 3 9391 3244",
    "sg:postcode":"3025",
    "sg:province":"VIC",
    "sg:tags":[
        "medical",
        "practitioner"
    ],
    "wof:name":"Korman Maurice",
    "wof:placetype":"venue"
},
  "geometry": {"coordinates":[144.850494,-37.83131],"type":"Point"}
}