{
  "type": "Feature",
  "properties": {
    "addr:full":"51 Vineyard Rd Sunbury VIC 3429",
    "addr:housenumber":"51",
    "addr:postcode":"3429",
    "addr:street":"Vineyard Rd",
    "iso:country":"AU",
    "sg:address":"51 Vineyard Rd",
    "sg:city":"Sunbury",
    "sg:classifiers":[
        {
            "category":"Home & Garden",
            "subcategory":"Carpets & Floor Coverings",
            "type":"Retail Goods"
        }
    ],
    "sg:phone":"+61 3 9744 7565",
    "sg:postcode":"3429",
    "sg:province":"VIC",
    "sg:tags":[
        "tile",
        "wall"
    ],
    "wof:name":"P J Ceramics & Slate",
    "wof:placetype":"venue"
},
  "geometry": {"coordinates":[144.718658447,-37.5867996216],"type":"Point"}
}