{
  "type": "Feature",
  "properties": {
    "addr:full":"306A Bourke St Darlinghurst NSW 2010",
    "addr:housenumber":"306a",
    "addr:postcode":"2010",
    "addr:street":"Bourke St",
    "iso:country":"AU",
    "sg:address":"306A Bourke St",
    "sg:city":"Darlinghurst",
    "sg:classifiers":[
        {
            "category":"Personal",
            "subcategory":"Barber",
            "type":"Services"
        }
    ],
    "sg:phone":"+61 2 9361 6827",
    "sg:postcode":"2010",
    "sg:province":"NSW",
    "wof:name":"Individual Hair Stylist",
    "wof:placetype":"venue"
},
  "geometry": {"coordinates":[151.21673584000001,-33.8815803528],"type":"Point"}
}