{
  "type": "Feature",
  "properties": {
    "addr:full":"21 Mounts Bay Rd Perth WA 6000",
    "addr:housenumber":"21",
    "addr:postcode":"6000",
    "addr:street":"Mounts Bay Rd",
    "iso:country":"AU",
    "sg:address":"21 Mounts Bay Rd",
    "sg:city":"Perth",
    "sg:classifiers":[
        {
            "category":"Retail",
            "subcategory":"Event Space",
            "type":"Services"
        }
    ],
    "sg:phone":"+61 8 9288 1222",
    "sg:postcode":"6000",
    "sg:province":"WA",
    "sg:tags":[
        "function",
        "organiser"
    ],
    "wof:name":"Spotless Perth Convention & Exhibition Centre",
    "wof:placetype":"venue"
},
  "geometry": {"coordinates":[115.852920532,-31.9552993774],"type":"Point"}
}