{
  "type": "Feature",
  "properties": {
    "addr:full":"84 Main St Mornington VIC 3931",
    "addr:housenumber":"84",
    "addr:postcode":"3931",
    "addr:street":"Main St",
    "iso:country":"AU",
    "sg:address":"84 Main St",
    "sg:city":"Mornington",
    "sg:classifiers":[
        {
            "category":"Health Services",
            "subcategory":"Health Practitioner",
            "type":"Services"
        }
    ],
    "sg:phone":"+61 3 5977 0117",
    "sg:postcode":"3931",
    "sg:province":"VIC",
    "sg:tags":[
        "naturopath"
    ],
    "wof:name":"Peninsula Herbal Dispensary",
    "wof:placetype":"venue"
},
  "geometry": {"coordinates":[145.03848266599999,-38.2191696167],"type":"Point"}
}