{
  "type": "Feature",
  "properties": {
    "addr:full":"318 Great Western Hwy Wentworthville NSW 2145",
    "addr:housenumber":"318",
    "addr:postcode":"2145",
    "addr:street":"Great Western Hwy",
    "iso:country":"AU",
    "sg:address":"318 Great Western Hwy",
    "sg:city":"Wentworthville",
    "sg:classifiers":[
        {
            "category":"Autos & Motor Vehicles",
            "subcategory":"Fuel & Gas Station",
            "type":"Retail Goods"
        }
    ],
    "sg:phone":"+61 2 9689 1699",
    "sg:postcode":"2145",
    "sg:province":"NSW",
    "wof:name":"Wentworthville Self Serve",
    "wof:placetype":"venue"
},
  "geometry": {"coordinates":[150.96983337399999,-33.8153991699],"type":"Point"}
}