{
  "type": "Feature",
  "properties": {
    "iso:country":"AU",
    "sg:address":"Brookside Shpng Cntr Osborne Rd",
    "sg:city":"Mitchelton",
    "sg:classifiers":[
        {
            "category":"Travel",
            "subcategory":"Travel Agent",
            "type":"Entertainment"
        }
    ],
    "sg:phone":"+61 1300 888 449",
    "sg:postcode":"4053",
    "sg:province":"QLD",
    "sg:tags":[
        "consultant"
    ],
    "wof:name":"RACQ Travel Service",
    "wof:placetype":"venue"
},
  "geometry": {"coordinates":[152.976928711,-27.4133472443],"type":"Point"}
}