{
  "type": "Feature",
  "properties": {
    "addr:full":"167 View St Bendigo VIC 3550",
    "addr:housenumber":"167",
    "addr:postcode":"3550",
    "addr:street":"View St",
    "iso:country":"AU",
    "sg:address":"167 View St",
    "sg:city":"Bendigo",
    "sg:classifiers":[
        {
            "category":"Professional",
            "subcategory":"Employment Agencies",
            "type":"Services"
        }
    ],
    "sg:phone":"+61 3 5443 3855",
    "sg:postcode":"3550",
    "sg:province":"VIC",
    "sg:tags":[
        "provider",
        "internet"
    ],
    "wof:name":"Hotkey Bendigo",
    "wof:placetype":"venue"
},
  "geometry": {"coordinates":[144.27482605,-36.7562789917],"type":"Point"}
}