{
  "type": "Feature",
  "properties": {
    "iso:country":"AU",
    "sg:address":"Shed 3/ 157 Mark Rd",
    "sg:city":"Caloundra",
    "sg:classifiers":[
        {
            "category":"Autos & Motor Vehicles",
            "subcategory":"Automobile Sales",
            "type":"Retail Goods"
        }
    ],
    "sg:phone":"+61 7 5491 4733",
    "sg:postcode":"4551",
    "sg:province":"QLD",
    "sg:tags":[
        "equipment",
        "trailer"
    ],
    "wof:name":"Best Trailers and Campers",
    "wof:placetype":"venue"
},
  "geometry": {"coordinates":[153.112594605,-26.792137146],"type":"Point"}
}