{
  "type": "Feature",
  "properties": {
    "addr:full":"Suite 2, The Bay 29 Bentham St Yarralumla ACT 2600",
    "addr:housenumber":"29",
    "addr:postcode":"2600",
    "addr:street":"Bentham St",
    "iso:country":"AU",
    "sg:address":"Suite 2, The Bay 29 Bentham St",
    "sg:city":"Yarralumla",
    "sg:classifiers":[
        {
            "category":"Banks & Credit Unions",
            "subcategory":"Financial Services",
            "type":"Services"
        }
    ],
    "sg:phone":"+61 2 6285 2755",
    "sg:postcode":"2600",
    "sg:province":"ACT",
    "sg:tags":[
        "advisory",
        "planning",
        "retirement"
    ],
    "wof:name":"Lorimar Associates",
    "wof:placetype":"venue"
},
  "geometry": {"coordinates":[149.09718322800001,-35.3075294495],"type":"Point"}
}