{
  "type": "Feature",
  "properties": {
    "addr:full":"95 Arthur St Fortitude Valley QLD 4006",
    "addr:housenumber":"95",
    "addr:postcode":"4006",
    "addr:street":"Arthur St",
    "iso:country":"AU",
    "sg:address":"95 Arthur St",
    "sg:city":"Fortitude Valley",
    "sg:classifiers":[
        {
            "category":"Organizations",
            "subcategory":"Membership Organization",
            "type":"Services"
        }
    ],
    "sg:phone":"+61 7 3358 4424",
    "sg:postcode":"4006",
    "sg:province":"QLD",
    "sg:tags":[
        "support",
        "health",
        "organisation"
    ],
    "wof:name":"Schizophrenia Fellowship Of Queensland Inc",
    "wof:placetype":"venue"
},
  "geometry": {"coordinates":[153.03993225100001,-27.4591217041],"type":"Point"}
}