{
  "type": "Feature",
  "properties": {
    "iso:country":"AU",
    "sg:address":"Suite 2, 6 Faraday Rd",
    "sg:city":"Padstow",
    "sg:classifiers":[
        {
            "category":"Banks & Credit Unions",
            "subcategory":"Bank",
            "type":"Services"
        }
    ],
    "sg:phone":"+61 2 9792 5799",
    "sg:postcode":"2211",
    "sg:province":"NSW",
    "sg:tags":[
        "sealing",
        "compound"
    ],
    "wof:name":"Valiant Environment Compounds Pty Ltd",
    "wof:placetype":"venue"
},
  "geometry": {"coordinates":[151.034256,-33.953407],"type":"Point"}
}