{
  "type": "Feature",
  "properties": {
    "addr:full":"25 Donnelly Ave Norlane VIC 3214",
    "addr:housenumber":"25",
    "addr:postcode":"3214",
    "addr:street":"Donnelly Ave",
    "iso:country":"AU",
    "sg:address":"25 Donnelly Ave",
    "sg:city":"Norlane",
    "sg:classifiers":[
        {
            "category":"Building & Trades",
            "subcategory":"Cleaning & Sanitation",
            "type":"Services"
        }
    ],
    "sg:phone":"+61 13 15 46",
    "sg:postcode":"3214",
    "sg:province":"VIC",
    "sg:tags":[
        "industrial",
        "commercial",
        "contractor"
    ],
    "wof:name":"Jim's Cleaning",
    "wof:placetype":"venue"
},
  "geometry": {"coordinates":[144.35989379899999,-38.0935249329],"type":"Point"}
}