{
  "type": "Feature",
  "properties": {
    "addr:full":"30 Dean St South Strathfield NSW 2136",
    "addr:housenumber":"30",
    "addr:postcode":"2136",
    "addr:street":"Dean St South",
    "iso:country":"AU",
    "sg:address":"30 Dean St",
    "sg:city":"South Strathfield",
    "sg:classifiers":[
        {
            "category":"Government",
            "subcategory":"Department Of Motor Vehicles",
            "type":"Public Place"
        }
    ],
    "sg:phone":"+61 2 9742 6929",
    "sg:postcode":"2136",
    "sg:province":"NSW",
    "sg:tags":[
        "wholesaler",
        "mfrs",
        "accessory"
    ],
    "wof:name":"Hansa Parts NSW Sales Office",
    "wof:placetype":"venue"
},
  "geometry": {"coordinates":[151.08741760300001,-33.8950386047],"type":"Point"}
}