{
  "type": "Feature",
  "properties": {
    "addr:full":"Hill St Beaufort VIC 3373",
    "addr:postcode":"3373",
    "addr:street":"Hill St",
    "iso:country":"AU",
    "sg:address":"Hill St",
    "sg:city":"Beaufort",
    "sg:classifiers":[
        {
            "category":"Education",
            "subcategory":"School",
            "type":"Public Place"
        }
    ],
    "sg:phone":"+61 3 5349 2490",
    "sg:postcode":"3373",
    "sg:province":"VIC",
    "sg:tags":[
        "state",
        "except",
        "nsw"
    ],
    "wof:name":"Beaufort Primary School",
    "wof:placetype":"venue"
},
  "geometry": {"coordinates":[143.387619019,-37.4305343628],"type":"Point"}
}