{
  "type": "Feature",
  "properties": {
    "addr:full":"44- 46 Bungil St Roma QLD 4455",
    "addr:housenumber":"46",
    "addr:postcode":"4455",
    "addr:street":"Bungil St",
    "iso:country":"AU",
    "sg:address":"44- 46 Bungil St",
    "sg:city":"Roma",
    "sg:classifiers":[
        {
            "category":"Education",
            "subcategory":"University",
            "type":"Public Place"
        }
    ],
    "sg:phone":"+61 7 4622 9711",
    "sg:postcode":"4455",
    "sg:province":"QLD",
    "sg:tags":[
        "educational",
        "organisation",
        "cultural"
    ],
    "wof:name":"Education Queensland Roma District Office",
    "wof:placetype":"venue"
},
  "geometry": {"coordinates":[148.78965759299999,-26.5696277618],"type":"Point"}
}