{
  "type": "Feature",
  "properties": {
    "addr:full":"Nelson St Mornington VIC 3931",
    "addr:postcode":"3931",
    "addr:street":"Nelson St",
    "iso:country":"AU",
    "sg:address":"Nelson St",
    "sg:city":"Mornington",
    "sg:classifiers":[
        {
            "category":"Utilities",
            "type":"Services"
        }
    ],
    "sg:phone":"+61 418 533 576",
    "sg:postcode":"3931",
    "sg:province":"VIC",
    "sg:tags":[
        "equipment",
        "towing"
    ],
    "wof:name":"Carbars",
    "wof:placetype":"venue"
},
  "geometry": {"coordinates":[145.030593872,-38.2305107117],"type":"Point"}
}