{
  "type": "Feature",
  "properties": {
    "iso:country":"AU",
    "sg:address":"4 Dawson St North",
    "sg:city":"Ballarat",
    "sg:classifiers":[
        {
            "category":"Manufacturing",
            "subcategory":"Electronics",
            "type":"Manufacturing & Wholesale Goods"
        }
    ],
    "sg:phone":"+61 3 5331 3099",
    "sg:postcode":"3350",
    "sg:province":"VIC",
    "sg:tags":[
        "oven",
        "microwave"
    ],
    "wof:name":"John Thomas Electrical",
    "wof:placetype":"venue"
},
  "geometry": {"coordinates":[143.85339400000001,-37.561871],"type":"Point"}
}