{
  "type": "Feature",
  "properties": {
    "addr:full":"267 O&#039; Hea St Pascoe Vale South VIC 3044",
    "addr:housenumber":"267",
    "addr:postcode":"3044",
    "addr:street":"O &;Hea St",
    "iso:country":"AU",
    "sg:address":"267 O&#039; Hea St",
    "sg:city":"Pascoe Vale South",
    "sg:classifiers":[
        {
            "category":"Professional",
            "subcategory":"Accounting & Tax Preparation",
            "type":"Services"
        }
    ],
    "sg:phone":"+61 3 9354 3416",
    "sg:postcode":"3044",
    "sg:province":"VIC",
    "sg:tags":[
        "accountant",
        "auditor"
    ],
    "wof:name":"Michael Perta & Associates",
    "wof:placetype":"venue"
},
  "geometry": {"coordinates":[144.944747925,-37.7354927063],"type":"Point"}
}