{
  "type": "Feature",
  "properties": {
    "addr:full":"PO Box 5144 Brendale QLD 4500",
    "addr:postcode":"4500",
    "iso:country":"AU",
    "sg:address":"PO Box 5144",
    "sg:city":"Brendale",
    "sg:classifiers":[
        {
            "category":"Home & Garden",
            "subcategory":"Building Materials",
            "type":"Retail Goods"
        }
    ],
    "sg:phone":"+61 7 5493 0000",
    "sg:postcode":"4500",
    "sg:province":"QLD",
    "sg:tags":[
        "shutter",
        "roller",
        "grille"
    ],
    "wof:name":"Queensland Roller Doors",
    "wof:placetype":"venue"
},
  "geometry": {"coordinates":[152.982345581,-27.32695961],"type":"Point"}
}