{
  "type": "Feature",
  "properties": {
    "iso:country":"AU",
    "sg:address":"23 Lambeck Drv",
    "sg:city":"Tullamarine",
    "sg:classifiers":[
        {
            "category":"Wholesale",
            "subcategory":"Plants",
            "type":"Manufacturing & Wholesale Goods"
        }
    ],
    "sg:phone":"+61 3 9335 1890",
    "sg:postcode":"3043",
    "sg:province":"VIC",
    "sg:tags":[
        "florist"
    ],
    "wof:name":"Buy-Wise Import & Wholesale",
    "wof:placetype":"venue"
},
  "geometry": {"coordinates":[144.851852417,-37.7038917542],"type":"Point"}
}