{
  "type": "Feature",
  "properties": {
    "addr:full":"148 Brisbane St Launceston TAS 7250",
    "addr:housenumber":"148",
    "addr:postcode":"7250",
    "addr:street":"Brisbane St",
    "iso:country":"AU",
    "sg:address":"148 Brisbane St",
    "sg:city":"Launceston",
    "sg:classifiers":[
        {
            "category":"Professional",
            "subcategory":"Computer Services",
            "type":"Services"
        }
    ],
    "sg:phone":"+61 3 6333 0100",
    "sg:postcode":"7250",
    "sg:province":"TAS",
    "sg:tags":[
        "repairs",
        "upgrade",
        "equipment"
    ],
    "wof:name":"P. C. Connection",
    "wof:placetype":"venue"
},
  "geometry": {"coordinates":[147.137115478,-41.4381446838],"type":"Point"}
}