{
  "type": "Feature",
  "properties": {
    "addr:full":"6 Monahan Ave Banksia NSW 2216",
    "addr:housenumber":"6",
    "addr:postcode":"2216",
    "addr:street":"Monahan Ave",
    "iso:country":"AU",
    "sg:address":"6 Monahan Ave",
    "sg:city":"Banksia",
    "sg:classifiers":[
        {
            "category":"Building & Trades",
            "subcategory":"Construction",
            "type":"Services"
        }
    ],
    "sg:phone":"+61 2 9556 1925",
    "sg:postcode":"2216",
    "sg:province":"NSW",
    "sg:tags":[
        "roof"
    ],
    "wof:name":"Met Frame Systems Pty Ltd",
    "wof:placetype":"venue"
},
  "geometry": {"coordinates":[151.14047199999999,-33.947495],"type":"Point"}
}