{
  "type": "Feature",
  "properties": {
    "addr:full":"1988 Old Maitland Rd Cessnock NSW 2325",
    "addr:housenumber":"1988",
    "addr:postcode":"2325",
    "addr:street":"Old Maitland Rd",
    "iso:country":"AU",
    "sg:address":"1988 Old Maitland Rd",
    "sg:city":"Cessnock",
    "sg:classifiers":[
        {
            "category":"Farming",
            "subcategory":"Livestock Farm",
            "type":"Manufacturing & Wholesale Goods"
        }
    ],
    "sg:phone":"+61 2 4990 2934",
    "sg:postcode":"2325",
    "sg:province":"NSW",
    "sg:tags":[
        "breeder",
        "horse",
        "stud"
    ],
    "wof:name":"Weebelong Miniature Horse Stud",
    "wof:placetype":"venue"
},
  "geometry": {"coordinates":[151.3671875,-32.828414917],"type":"Point"}
}