{
  "type": "Feature",
  "properties": {
    "addr:full":"20 Vincent St Oak Park VIC 3046",
    "addr:housenumber":"20",
    "addr:postcode":"3046",
    "addr:street":"Vincent St",
    "iso:country":"AU",
    "sg:address":"20 Vincent St",
    "sg:city":"Oak Park",
    "sg:classifiers":[
        {
            "category":"Health Services",
            "subcategory":"Health Practitioner",
            "type":"Services"
        }
    ],
    "sg:phone":"+61 403 019 872",
    "sg:postcode":"3046",
    "sg:province":"VIC",
    "sg:tags":[
        "pathologist",
        "speech"
    ],
    "wof:name":"Jacobs W Diane",
    "wof:placetype":"venue"
},
  "geometry": {"coordinates":[144.917312622,-37.7199935913],"type":"Point"}
}