{
  "type": "Feature",
  "properties": {
    "addr:full":"Shp11/ 980 Brickworks Rd Kallangur QLD 4503",
    "addr:housenumber":"980",
    "addr:postcode":"4503",
    "addr:street":"Brickworks Rd",
    "iso:country":"AU",
    "sg:address":"Shp11/ 980 Brickworks Rd",
    "sg:city":"Kallangur",
    "sg:classifiers":[
        {
            "category":"Food & Beverages",
            "subcategory":"Bakery",
            "type":"Retail Goods"
        }
    ],
    "sg:phone":"+61 7 3491 9845",
    "sg:postcode":"4503",
    "sg:province":"QLD",
    "sg:tags":[
        "baker"
    ],
    "wof:name":"Sunshine Fun Pie Bakey",
    "wof:placetype":"venue"
},
  "geometry": {"coordinates":[152.993606567,-27.2424678802],"type":"Point"}
}