{
  "type": "Feature",
  "properties": {
    "iso:country":"AU",
    "sg:address":"397 North Beach Rd",
    "sg:city":"Carine",
    "sg:classifiers":[
        {
            "category":"Government",
            "subcategory":"Court House",
            "type":"Public Place"
        }
    ],
    "sg:phone":"+61 8 9448 0313",
    "sg:postcode":"6020",
    "sg:province":"WA",
    "sg:tags":[
        "personal",
        "marriage",
        "family",
        "counselling"
    ],
    "wof:name":"McDowall Penelope",
    "wof:placetype":"venue"
},
  "geometry": {"coordinates":[115.785652161,-31.8593158722],"type":"Point"}
}