{
  "type": "Feature",
  "properties": {
    "addr:full":"Lady Denman Drv Yarralumla ACT 2600",
    "addr:postcode":"2600",
    "addr:street":"Denman Drv",
    "iso:country":"AU",
    "sg:address":"Lady Denman Drv",
    "sg:city":"Yarralumla",
    "sg:classifiers":[
        {
            "category":"Park",
            "subcategory":"County",
            "type":"Public Place"
        }
    ],
    "sg:phone":"+61 2 6287 8400",
    "sg:postcode":"2600",
    "sg:province":"ACT",
    "sg:tags":[
        "sanctuary",
        "zoos",
        "animal"
    ],
    "wof:name":"National Zoo & Aquarium",
    "wof:placetype":"venue"
},
  "geometry": {"coordinates":[149.07508850100001,-35.3066864014],"type":"Point"}
}