{
  "type": "Feature",
  "properties": {
    "addr:full":"32 Colebard St East Acacia Ridge QLD 4110",
    "addr:housenumber":"32",
    "addr:postcode":"4110",
    "addr:street":"Colebard St East",
    "iso:country":"AU",
    "sg:address":"32 Colebard St East",
    "sg:city":"Acacia Ridge",
    "sg:classifiers":[
        {
            "category":"Professional",
            "type":"Services"
        }
    ],
    "sg:phone":"+61 7 3274 6344",
    "sg:postcode":"4110",
    "sg:province":"QLD",
    "sg:tags":[
        "coating",
        "powder"
    ],
    "wof:name":"Queensland Powder Coating",
    "wof:placetype":"venue"
},
  "geometry": {"coordinates":[153.005203247,-27.5811157227],"type":"Point"}
}