{
  "type": "Feature",
  "properties": {
    "addr:full":"Goulburn Valley Hwy Yea VIC 3717",
    "addr:postcode":"3717",
    "addr:street":"Valley Hwy",
    "iso:country":"AU",
    "sg:address":"Goulburn Valley Hwy",
    "sg:city":"Yea",
    "sg:classifiers":[
        {
            "category":"Building & Trades",
            "subcategory":"Landscaping Services",
            "type":"Services"
        }
    ],
    "sg:phone":"+61 3 5797 2870",
    "sg:postcode":"3717",
    "sg:province":"VIC",
    "sg:tags":[
        "designer",
        "landscape",
        "contractor"
    ],
    "wof:name":"P & S Bobcat Hire",
    "wof:placetype":"venue"
},
  "geometry": {"coordinates":[145.41664123499999,-37.2135124207],"type":"Point"}
}