{
  "type": "Feature",
  "properties": {
    "addr:full":"269a Centre Rd Bentleigh VIC 3204",
    "addr:housenumber":"269a",
    "addr:postcode":"3204",
    "addr:street":"Centre Rd",
    "iso:country":"AU",
    "sg:address":"269a Centre Rd",
    "sg:city":"Bentleigh",
    "sg:classifiers":[
        {
            "category":"Professional",
            "subcategory":"Art Services",
            "type":"Services"
        }
    ],
    "sg:phone":"+61 3 9576 5311",
    "sg:postcode":"3204",
    "sg:province":"VIC",
    "sg:tags":[
        "graphic",
        "designer"
    ],
    "wof:name":"Dan Grafix Solutions Pty Ltd",
    "wof:placetype":"venue"
},
  "geometry": {"coordinates":[145.032104,-37.917519],"type":"Point"}
}