{
  "type": "Feature",
  "properties": {
    "iso:country":"AU",
    "sg:address":"35 Queen St",
    "sg:city":"Ravensthorpe",
    "sg:classifiers":[
        {
            "category":"Farming",
            "subcategory":"Farm",
            "type":"Manufacturing & Wholesale Goods"
        }
    ],
    "sg:phone":"+61 8 9838 1236",
    "sg:postcode":"6346",
    "sg:province":"WA",
    "sg:tags":[
        "farmer"
    ],
    "wof:name":"Biddulph J K & R & Sons",
    "wof:placetype":"venue"
},
  "geometry": {"coordinates":[120.044579,-33.582134],"type":"Point"}
}