{
  "type": "Feature",
  "properties": {
    "addr:full":"Unit 4, 2-10 Fountain St Alexandria NSW 2015",
    "addr:housenumber":"2-10",
    "addr:postcode":"2015",
    "addr:street":"Fountain St",
    "iso:country":"AU",
    "sg:address":"Unit 4, 2-10 Fountain St",
    "sg:city":"Alexandria",
    "sg:classifiers":[
        {
            "category":"Personal",
            "subcategory":"Skin Care",
            "type":"Services"
        }
    ],
    "sg:phone":"+61 414 430 998",
    "sg:postcode":"2015",
    "sg:province":"NSW",
    "sg:tags":[
        "leather",
        "merchant"
    ],
    "wof:name":"Contemporary Leathers",
    "wof:placetype":"venue"
},
  "geometry": {"coordinates":[151.19526672399999,-33.9024200439],"type":"Point"}
}