{
  "type": "Feature",
  "properties": {
    "iso:country":"AU",
    "sg:address":"Shop 6/155, King William Road",
    "sg:city":"Hyde Park",
    "sg:classifiers":[
        {
            "category":"Shopping",
            "subcategory":"Clothing, Apparel, & Fashions",
            "type":"Retail Goods"
        }
    ],
    "sg:phone":"+61 8 8271 4800",
    "sg:postcode":"5061",
    "sg:province":"SA",
    "sg:tags":[
        "lingerie",
        "hosiery",
        "sleepwear"
    ],
    "wof:name":"Fifi Blue",
    "wof:placetype":"venue"
},
  "geometry": {"coordinates":[138.60038757300001,-34.9564590454],"type":"Point"}
}