{
  "type": "Feature",
  "properties": {
    "addr:full":"83 Raeside St Westlake QLD 4074",
    "addr:housenumber":"83",
    "addr:postcode":"4074",
    "addr:street":"Raeside St",
    "iso:country":"AU",
    "sg:address":"83 Raeside St",
    "sg:city":"Westlake",
    "sg:classifiers":[
        {
            "category":"Social Services",
            "type":"Services"
        }
    ],
    "sg:phone":"+61 7 3279 5099",
    "sg:postcode":"4074",
    "sg:province":"QLD",
    "sg:tags":[
        "worker"
    ],
    "wof:name":"Bates Merrelyn",
    "wof:placetype":"venue"
},
  "geometry": {"coordinates":[152.910598755,-27.5519695282],"type":"Point"}
}