{
  "type": "Feature",
  "properties": {
    "addr:full":"28 The Point Rd Woolwich NSW 2110",
    "addr:housenumber":"28",
    "addr:postcode":"2110",
    "addr:street":"The Point Rd",
    "iso:country":"AU",
    "sg:address":"28 The Point Rd",
    "sg:city":"Woolwich",
    "sg:classifiers":[
        {
            "category":"Health Services",
            "subcategory":"Doctor",
            "type":"Services"
        }
    ],
    "sg:phone":"+61 2 9879 4476",
    "sg:postcode":"2110",
    "sg:province":"NSW",
    "sg:tags":[
        "medical",
        "practitioner"
    ],
    "wof:name":"Bailey Ian K",
    "wof:placetype":"venue"
},
  "geometry": {"coordinates":[151.17483520499999,-33.8375511169],"type":"Point"}
}