{
  "type": "Feature",
  "properties": {
    "iso:country":"AU",
    "sg:address":"PO Box 1409",
    "sg:city":"Coffs Harbour",
    "sg:classifiers":[
        {
            "category":"Shopping",
            "subcategory":"Computers & Home Electronics",
            "type":"Retail Goods"
        }
    ],
    "sg:phone":"+61 2 6658 2224",
    "sg:postcode":"2450",
    "sg:province":"NSW",
    "sg:tags":[
        "small",
        "equipment",
        "business"
    ],
    "wof:name":"AAAiT",
    "wof:placetype":"venue"
},
  "geometry": {"coordinates":[153.115158,-30.29701],"type":"Point"}
}