{
  "type": "Feature",
  "properties": {
    "iso:country":"AU",
    "sg:address":"113 Wingewarra St",
    "sg:city":"Dubbo",
    "sg:classifiers":[
        {
            "category":"Travel",
            "subcategory":"Hotels & Motels",
            "type":"Entertainment"
        }
    ],
    "sg:phone":"+61 2 6882 0666",
    "sg:postcode":"2830",
    "sg:province":"NSW",
    "wof:name":"Best Western Blue Diamond Motor Inn",
    "wof:placetype":"venue"
},
  "geometry": {"coordinates":[148.601486206,-32.2489128113],"type":"Point"}
}