{
  "type": "Feature",
  "properties": {
    "iso:country":"AU",
    "sg:address":"7 Gorge Rd",
    "sg:city":"Morang South",
    "sg:classifiers":[
        {
            "category":"Food & Beverages",
            "subcategory":"Bakery",
            "type":"Retail Goods"
        }
    ],
    "sg:phone":"+61 3 9404 1828",
    "sg:postcode":"3752",
    "sg:province":"VIC",
    "sg:tags":[
        "cake",
        "shop",
        "pastry"
    ],
    "wof:name":"Nine Star Hot Bread & Cake Shop",
    "wof:placetype":"venue"
},
  "geometry": {"coordinates":[145.088593,-37.651398],"type":"Point"}
}