{
  "type": "Feature",
  "properties": {
    "iso:country":"AU",
    "sg:address":"50 Young Rd",
    "sg:city":"Lambton",
    "sg:classifiers":[
        {
            "category":"Retail",
            "subcategory":"Auto Repair",
            "type":"Services"
        }
    ],
    "sg:phone":"+61 2 4952 5833",
    "sg:postcode":"2299",
    "sg:province":"NSW",
    "sg:tags":[
        "repairer",
        "motor",
        "engineer"
    ],
    "wof:name":"Hawkins Mechanical",
    "wof:placetype":"venue"
},
  "geometry": {"coordinates":[151.72012329099999,-32.9158859253],"type":"Point"}
}