{
  "type": "Feature",
  "properties": {
    "iso:country":"AU",
    "sg:address":"794 Glen Huntly Rd",
    "sg:city":"Caulfield South",
    "sg:classifiers":[
        {
            "category":"Personal",
            "subcategory":"Beauty Salon",
            "type":"Services"
        }
    ],
    "sg:phone":"+61 3 9523 9950",
    "sg:postcode":"3162",
    "sg:province":"VIC",
    "sg:tags":[
        "hairdresser"
    ],
    "wof:name":"Divas Hairdressing Salon",
    "wof:placetype":"venue"
},
  "geometry": {"coordinates":[145.02220153799999,-37.8870277405],"type":"Point"}
}