{
  "type": "Feature",
  "properties": {
    "addr:full":"204 Brooklyn Rd Brooklyn NSW 2083",
    "addr:housenumber":"204",
    "addr:postcode":"2083",
    "addr:street":"Brooklyn Rd",
    "iso:country":"AU",
    "sg:address":"204 Brooklyn Rd",
    "sg:city":"Brooklyn",
    "sg:classifiers":[
        {
            "category":"Professional",
            "subcategory":"Testing Lab",
            "type":"Services"
        }
    ],
    "sg:phone":"+61 2 9985 7662",
    "sg:postcode":"2083",
    "sg:province":"NSW",
    "sg:tags":[
        "equipment",
        "motor"
    ],
    "wof:name":"Emtech Associates Pty Ltd",
    "wof:placetype":"venue"
},
  "geometry": {"coordinates":[151.22445678700001,-33.548160553],"type":"Point"}
}