{
  "type": "Feature",
  "properties": {
    "iso:country":"AU",
    "sg:address":"14 Capricorn Ave",
    "sg:city":"Doncaster East",
    "sg:classifiers":[
        {
            "category":"Personal",
            "type":"Services"
        }
    ],
    "sg:phone":"+61 3 9842 5913",
    "sg:postcode":"3109",
    "sg:province":"VIC",
    "sg:tags":[
        "career",
        "counselling"
    ],
    "wof:name":"Coaching For Success",
    "wof:placetype":"venue"
},
  "geometry": {"coordinates":[145.16868591299999,-37.7805938721],"type":"Point"}
}