{
  "type": "Feature",
  "properties": {
    "addr:full":"Shp 2/ 10 Park Rd Cheltenham VIC 3192",
    "addr:housenumber":"/ 10",
    "addr:postcode":"3192",
    "addr:street":"Park Rd",
    "iso:country":"AU",
    "sg:address":"Shp 2/ 10 Park Rd",
    "sg:city":"Cheltenham",
    "sg:classifiers":[
        {
            "category":"Shopping",
            "subcategory":"Pets & Pet Supplies",
            "type":"Retail Goods"
        }
    ],
    "sg:phone":"+61 3 9584 6409",
    "sg:postcode":"3192",
    "sg:province":"VIC",
    "sg:tags":[
        "food"
    ],
    "wof:name":"Bow Wow Meow Pet Boutique",
    "wof:placetype":"venue"
},
  "geometry": {"coordinates":[145.05601501500001,-37.9655532837],"type":"Point"}
}