{
  "type": "Feature",
  "properties": {
    "iso:country":"AU",
    "sg:address":"15a Forrest Ave",
    "sg:city":"Bunbury",
    "sg:classifiers":[
        {
            "category":"Health Services",
            "subcategory":"Dentist",
            "type":"Services"
        }
    ],
    "sg:phone":"+61 8 9791 2270",
    "sg:postcode":"6230",
    "sg:province":"WA",
    "wof:name":"Tran Minh",
    "wof:placetype":"venue"
},
  "geometry": {"coordinates":[115.642303,-33.337662],"type":"Point"}
}