{
  "type": "Feature",
  "properties": {
    "addr:full":"85 Queen St North Strathfield NSW 2137",
    "addr:housenumber":"85",
    "addr:postcode":"2137",
    "addr:street":"Queen St",
    "iso:country":"AU",
    "sg:address":"85 Queen St",
    "sg:city":"North Strathfield",
    "sg:classifiers":[
        {
            "category":"Professional",
            "subcategory":"Printing & Photocopies",
            "type":"Services"
        }
    ],
    "sg:phone":"+61 2 9736 3777",
    "sg:postcode":"2137",
    "sg:province":"NSW",
    "sg:tags":[
        "publishing",
        "desktop"
    ],
    "wof:name":"JMR Creative Design Pty Ltd",
    "wof:placetype":"venue"
},
  "geometry": {"coordinates":[151.08900451700001,-33.8590393066],"type":"Point"}
}