{
  "type": "Feature",
  "properties": {
    "addr:full":"17 Link Crt Brooklyn VIC 3025",
    "addr:housenumber":"17",
    "addr:postcode":"3025",
    "addr:street":"Link Crt",
    "iso:country":"AU",
    "sg:address":"17 Link Crt",
    "sg:city":"Brooklyn",
    "sg:classifiers":[
        {
            "category":"Building & Trades",
            "subcategory":"Equipment Rental",
            "type":"Services"
        }
    ],
    "sg:phone":"+61 3 9325 1190",
    "sg:postcode":"3025",
    "sg:province":"VIC",
    "sg:tags":[
        "crane",
        "hire"
    ],
    "wof:name":"Crane & Access Hire Pty Ltd",
    "wof:placetype":"venue"
},
  "geometry": {"coordinates":[144.85682700000001,-37.822651],"type":"Point"}
}