{
  "type": "Feature",
  "properties": {
    "addr:full":"3 Dargie Pl Eagle Vale NSW 2558",
    "addr:housenumber":"3",
    "addr:postcode":"2558",
    "addr:street":"Dargie Pl",
    "iso:country":"AU",
    "sg:address":"3 Dargie Pl",
    "sg:city":"Eagle Vale",
    "sg:classifiers":[
        {
            "category":"Health Services",
            "subcategory":"Health Practitioner",
            "type":"Services"
        }
    ],
    "sg:phone":"+61 2 4628 7788",
    "sg:postcode":"2558",
    "sg:province":"NSW",
    "sg:tags":[
        "bowen",
        "therapy"
    ],
    "wof:name":"Advanced Bowen Marisa Swifte",
    "wof:placetype":"venue"
},
  "geometry": {"coordinates":[150.80317688,-34.0419311523],"type":"Point"}
}