{
  "type": "Feature",
  "properties": {
    "addr:full":"31a Ogilvy St Peakhurst NSW 2210",
    "addr:housenumber":"31a",
    "addr:postcode":"2210",
    "addr:street":"Ogilvy St",
    "iso:country":"AU",
    "sg:address":"31a Ogilvy St",
    "sg:city":"Peakhurst",
    "sg:classifiers":[
        {
            "category":"Deli",
            "type":"Food & Drink"
        }
    ],
    "sg:phone":"+61 2 9153 5550",
    "sg:postcode":"2210",
    "sg:province":"NSW",
    "sg:tags":[
        "delicatessen"
    ],
    "wof:name":"Sinkit Pty Ltd",
    "wof:placetype":"venue"
},
  "geometry": {"coordinates":[151.04847699999999,-33.961166],"type":"Point"}
}