{
  "type": "Feature",
  "properties": {
    "addr:full":"43 Outram St West Perth WA 6005",
    "addr:housenumber":"43",
    "addr:postcode":"6005",
    "addr:street":"Outram St",
    "iso:country":"AU",
    "sg:address":"43 Outram St",
    "sg:city":"West Perth",
    "sg:classifiers":[
        {
            "category":"Health Services",
            "subcategory":"Optometrist",
            "type":"Services"
        }
    ],
    "sg:phone":"+61 8 9322 4443",
    "sg:postcode":"6005",
    "sg:province":"WA",
    "sg:website":"http://www.optometrists.asn.au",
    "wof:name":"Ezekiel Optometrists",
    "wof:placetype":"venue"
},
  "geometry": {"coordinates":[115.839408874,-31.9488353729],"type":"Point"}
}