{
  "type": "Feature",
  "properties": {
    "addr:full":"236a Illawarra Rd Marrickville NSW 2204",
    "addr:housenumber":"236a",
    "addr:postcode":"2204",
    "addr:street":"Illawarra Rd",
    "iso:country":"AU",
    "sg:address":"236a Illawarra Rd",
    "sg:city":"Marrickville",
    "sg:classifiers":[
        {
            "category":"Shopping",
            "subcategory":"Mobile Phones",
            "type":"Retail Goods"
        }
    ],
    "sg:phone":"+61 2 9559 8866",
    "sg:postcode":"2204",
    "sg:province":"NSW",
    "sg:tags":[
        "telephone",
        "accessory"
    ],
    "wof:name":"Phones By Australia",
    "wof:placetype":"venue"
},
  "geometry": {"coordinates":[151.156113,-33.910633],"type":"Point"}
}