{
  "type": "Feature",
  "properties": {
    "addr:full":"143 Gillan Rd Belgrave South VIC 3160",
    "addr:housenumber":"143",
    "addr:postcode":"3160",
    "addr:street":"Gillan Rd",
    "iso:country":"AU",
    "sg:address":"143 Gillan Rd",
    "sg:city":"Belgrave South",
    "sg:classifiers":[
        {
            "category":"Home & Garden",
            "subcategory":"Carpets & Floor Coverings",
            "type":"Retail Goods"
        }
    ],
    "sg:phone":"+61 3 9754 5649",
    "sg:postcode":"3160",
    "sg:province":"VIC",
    "sg:tags":[
        "layer"
    ],
    "wof:name":"O&#039;Meara A J",
    "wof:placetype":"venue"
},
  "geometry": {"coordinates":[145.36883544899999,-37.938129425],"type":"Point"}
}