{
  "type": "Feature",
  "properties": {
    "addr:full":"U7, 10 Hudson Ave Castle Hill NSW 2154",
    "addr:housenumber":"10",
    "addr:postcode":"2154",
    "addr:street":"U7;Hudson Ave",
    "iso:country":"AU",
    "sg:address":"U7, 10 Hudson Ave",
    "sg:city":"Castle Hill",
    "sg:classifiers":[
        {
            "category":"Health Services",
            "subcategory":"Health Practitioner",
            "type":"Services"
        }
    ],
    "sg:phone":"+61 2 9659 4540",
    "sg:postcode":"2154",
    "sg:province":"NSW",
    "sg:tags":[
        "physiotherapist"
    ],
    "wof:name":"Darren Taylor Physiotherapists",
    "wof:placetype":"venue"
},
  "geometry": {"coordinates":[150.97450256400001,-33.7294998169],"type":"Point"}
}