{
  "type": "Feature",
  "properties": {
    "addr:full":"9/ 33a Garden St Belmore NSW 2192",
    "addr:housenumber":"/ 33a",
    "addr:postcode":"2192",
    "addr:street":"Garden St",
    "iso:country":"AU",
    "sg:address":"9/ 33a Garden St",
    "sg:city":"Belmore",
    "sg:classifiers":[
        {
            "category":"Retail",
            "subcategory":"Auto Rental",
            "type":"Services"
        }
    ],
    "sg:phone":"+61 410 523 145",
    "sg:postcode":"2192",
    "sg:province":"NSW",
    "sg:tags":[
        "car",
        "hire",
        "minibus"
    ],
    "wof:name":"El Cheapo Car Rental",
    "wof:placetype":"venue"
},
  "geometry": {"coordinates":[151.091431,-33.926788],"type":"Point"}
}