{
  "type": "Feature",
  "properties": {
    "iso:country":"AU",
    "sg:address":"Grd Fl 107 Queen St",
    "sg:city":"Woollahra",
    "sg:classifiers":[
        {
            "category":"Cafe",
            "type":"Food & Drink"
        }
    ],
    "sg:phone":"+61 2 9326 2337",
    "sg:postcode":"2025",
    "sg:province":"NSW",
    "wof:name":"Zigolini's",
    "wof:placetype":"venue"
},
  "geometry": {"coordinates":[151.23747253400001,-33.8884963989],"type":"Point"}
}