{
  "type": "Feature",
  "properties": {
    "addr:full":"17 Altona St West Perth WA 6005",
    "addr:housenumber":"17",
    "addr:postcode":"6005",
    "addr:street":"Altona St",
    "iso:country":"AU",
    "sg:address":"17 Altona St",
    "sg:city":"West Perth",
    "sg:classifiers":[
        {
            "category":"Insurance",
            "subcategory":"Insurance Agent",
            "type":"Services"
        }
    ],
    "sg:phone":"+61 8 9483 8888",
    "sg:postcode":"6005",
    "sg:province":"WA",
    "sg:tags":[
        "broker"
    ],
    "wof:name":"Strategic Claims Solutions",
    "wof:placetype":"venue"
},
  "geometry": {"coordinates":[115.839698791,-31.9510593414],"type":"Point"}
}