{
  "type": "Feature",
  "properties": {
    "iso:country":"AU",
    "sg:address":"Abbotts Rd",
    "sg:city":"Palmwoods",
    "sg:classifiers":[
        {
            "category":"Building & Trades",
            "subcategory":"Landscaping Services",
            "type":"Services"
        }
    ],
    "sg:phone":"+61 7 5445 7400",
    "sg:postcode":"4555",
    "sg:province":"QLD",
    "sg:tags":[
        "stump",
        "tree",
        "felling",
        "removal"
    ],
    "wof:name":"Mulch-It Vegetation Management",
    "wof:placetype":"venue"
},
  "geometry": {"coordinates":[152.96987915,-26.6811523438],"type":"Point"}
}