{
  "type": "Feature",
  "properties": {
    "addr:full":"226 Hay St Subiaco WA 6008",
    "addr:housenumber":"226",
    "addr:postcode":"6008",
    "addr:street":"Hay St",
    "iso:country":"AU",
    "sg:address":"226 Hay St",
    "sg:city":"Subiaco",
    "sg:classifiers":[
        {
            "category":"Retail",
            "subcategory":"Event Space",
            "type":"Services"
        }
    ],
    "sg:phone":"+61 1300 730 868",
    "sg:postcode":"6008",
    "sg:province":"WA",
    "sg:tags":[
        "venue",
        "reception",
        "wedding"
    ],
    "wof:name":"Black Toms Bar & Grill",
    "wof:placetype":"venue"
},
  "geometry": {"coordinates":[115.831230164,-31.9469337463],"type":"Point"}
}