{
  "type": "Feature",
  "properties": {
    "iso:country":"AU",
    "sg:address":"PO Box 333",
    "sg:city":", Plumpton",
    "sg:classifiers":[
        {
            "category":"Manufacturing",
            "subcategory":"Motor Vehicles & Parts",
            "type":"Manufacturing & Wholesale Goods"
        }
    ],
    "sg:phone":"+61 413 185 994",
    "sg:postcode":"2761",
    "sg:province":"NSW",
    "sg:tags":[
        "wholesaler",
        "cycle",
        "mfrs",
        "accessory"
    ],
    "wof:name":"Furromi Global Services Pty Ltd",
    "wof:placetype":"venue"
},
  "geometry": {"coordinates":[150.834213,-33.747028],"type":"Point"}
}