{
  "type": "Feature",
  "properties": {
    "iso:country":"AU",
    "sg:address":"Unit 3/ 60 Raglan Rd",
    "sg:city":"Mt Lawley",
    "sg:classifiers":[
        {
            "category":"Professional",
            "subcategory":"Art Services",
            "type":"Services"
        }
    ],
    "sg:phone":"+61 8 9227 6933",
    "sg:postcode":"6050",
    "sg:province":"WA",
    "sg:tags":[
        "graphic",
        "designer"
    ],
    "wof:name":"Chemistry Design",
    "wof:placetype":"venue"
},
  "geometry": {"coordinates":[115.867156982,-31.9337253571],"type":"Point"}
}