{
  "type": "Feature",
  "properties": {
    "addr:full":"2/ 35 Enterprise St Kunda Park QLD 4556",
    "addr:housenumber":"/ 35",
    "addr:postcode":"4556",
    "addr:street":"Enterprise St",
    "iso:country":"AU",
    "sg:address":"2/ 35 Enterprise St",
    "sg:city":"Kunda Park",
    "sg:classifiers":[
        {
            "category":"Building & Trades",
            "subcategory":"Construction",
            "type":"Services"
        }
    ],
    "sg:phone":"+61 7 5476 9415",
    "sg:postcode":"4556",
    "sg:province":"QLD",
    "sg:tags":[
        "plasterboard",
        "plasterer",
        "fixer"
    ],
    "wof:name":"Quinlan Interior Linings",
    "wof:placetype":"venue"
},
  "geometry": {"coordinates":[153.030197144,-26.666469574],"type":"Point"}
}