{
  "type": "Feature",
  "properties": {
    "addr:full":"Grey St Kapunda SA 5373",
    "addr:postcode":"5373",
    "addr:street":"Grey St",
    "iso:country":"AU",
    "sg:address":"Grey St",
    "sg:city":"Kapunda",
    "sg:classifiers":[
        {
            "category":"Retail",
            "subcategory":"Auto Repair",
            "type":"Services"
        }
    ],
    "sg:phone":"+61 8 8566 2435",
    "sg:postcode":"5373",
    "sg:province":"SA",
    "sg:tags":[
        "repairer",
        "motor",
        "engineer"
    ],
    "wof:name":"Pfitzner Motor Co Pty Ltd",
    "wof:placetype":"venue"
},
  "geometry": {"coordinates":[138.90956115700001,-34.3382949829],"type":"Point"}
}