{
  "type": "Feature",
  "properties": {
    "iso:country":"AU",
    "sg:address":"Shop 7 King Arthur Blv",
    "sg:city":"Bethania",
    "sg:classifiers":[
        {
            "category":"Personal",
            "subcategory":"Beauty Salon",
            "type":"Services"
        }
    ],
    "sg:phone":"+61 7 3200 9493",
    "sg:postcode":"4205",
    "sg:province":"QLD",
    "sg:tags":[
        "hairdresser"
    ],
    "wof:name":"Diva Hair & Beauty",
    "wof:placetype":"venue"
},
  "geometry": {"coordinates":[153.15779113799999,-27.6957645416],"type":"Point"}
}