{
  "type": "Feature",
  "properties": {
    "addr:full":"140 Manilla St Manilla NSW 2346",
    "addr:housenumber":"140",
    "addr:postcode":"2346",
    "addr:street":"Manilla St",
    "iso:country":"AU",
    "sg:address":"140 Manilla St",
    "sg:city":"Manilla",
    "sg:classifiers":[
        {
            "category":"Banks & Credit Unions",
            "subcategory":"Investment Brokerage",
            "type":"Services"
        }
    ],
    "sg:phone":"+61 2 6785 2233",
    "sg:postcode":"2346",
    "sg:province":"NSW",
    "sg:tags":[
        "sewing",
        "thread"
    ],
    "wof:name":"Sew&#039;n&#039;Craftarama",
    "wof:placetype":"venue"
},
  "geometry": {"coordinates":[150.720245361,-30.7479553223],"type":"Point"}
}