{
  "type": "Feature",
  "properties": {
    "addr:full":"96 riversdale Drv Tarneit VIC 3029",
    "addr:housenumber":"96",
    "addr:postcode":"3029",
    "addr:street":"Riversdale Drv",
    "iso:country":"AU",
    "sg:address":"96 riversdale Drv",
    "sg:city":"Tarneit",
    "sg:classifiers":[
        {
            "category":"Social Services",
            "type":"Services"
        }
    ],
    "sg:phone":"+61 414 863 335",
    "sg:postcode":"3029",
    "sg:province":"VIC",
    "sg:tags":[
        "kinesiology"
    ],
    "wof:name":"Rebecca Richards",
    "wof:placetype":"venue"
},
  "geometry": {"coordinates":[144.654358,-37.867191],"type":"Point"}
}