{
  "type": "Feature",
  "properties": {
    "iso:country":"AU",
    "sg:address":"898 Wynnum Rd",
    "sg:city":"Cannon Hill",
    "sg:classifiers":[
        {
            "category":"Arena",
            "subcategory":"Sports Club",
            "type":"Entertainment"
        }
    ],
    "sg:phone":"+61 7 3399 9473",
    "sg:postcode":"4170",
    "sg:province":"QLD",
    "sg:tags":[
        "league",
        "rugby"
    ],
    "wof:name":"Cannon Hill Stars Junior Rugby League Football Club",
    "wof:placetype":"venue"
},
  "geometry": {"coordinates":[153.083862305,-27.4673614502],"type":"Point"}
}