{
  "type": "Feature",
  "properties": {
    "addr:full":"72 Woongarra St Bundaberg QLD 4670",
    "addr:housenumber":"72",
    "addr:postcode":"4670",
    "addr:street":"Woongarra St",
    "iso:country":"AU",
    "sg:address":"72 Woongarra St",
    "sg:city":"Bundaberg",
    "sg:classifiers":[
        {
            "category":"Wholesale",
            "subcategory":"Medical Equipment & Supplies",
            "type":"Manufacturing & Wholesale Goods"
        }
    ],
    "sg:phone":"+61 7 4152 1566",
    "sg:postcode":"4670",
    "sg:province":"QLD",
    "sg:tags":[
        "aid",
        "care",
        "health",
        "home"
    ],
    "wof:name":"Robert Cullen Pharmacy",
    "wof:placetype":"venue"
},
  "geometry": {"coordinates":[152.34893798799999,-24.8674736023],"type":"Point"}
}