{
  "type": "Feature",
  "properties": {
    "iso:country":"AU",
    "sg:address":"200 Springvale Rd",
    "sg:city":"Springvale",
    "sg:classifiers":[
        {
            "category":"Manufacturing",
            "subcategory":"Furniture",
            "type":"Manufacturing & Wholesale Goods"
        }
    ],
    "sg:phone":"+61 3 9547 5643",
    "sg:postcode":"3171",
    "sg:province":"VIC",
    "sg:tags":[
        "builder",
        "designer",
        "custom"
    ],
    "wof:name":"Roma Furniture",
    "wof:placetype":"venue"
},
  "geometry": {"coordinates":[145.15269470199999,-37.9480171204],"type":"Point"}
}