{
  "type": "Feature",
  "properties": {
    "iso:country":"AU",
    "sg:address":"Old Coach Pl",
    "sg:city":"Roleystone",
    "sg:classifiers":[
        {
            "category":"Building & Trades",
            "subcategory":"Construction",
            "type":"Services"
        }
    ],
    "sg:phone":"+61 8 9397 5877",
    "sg:postcode":"6111",
    "sg:province":"WA",
    "sg:tags":[
        "joiner",
        "carpenter"
    ],
    "wof:name":"Hills To Coast Carpentry Service",
    "wof:placetype":"venue"
},
  "geometry": {"coordinates":[116.055969238,-32.1246681213],"type":"Point"}
}