{
  "type": "Feature",
  "properties": {
    "addr:full":"1 Whitestone Drv Austins Ferry TAS 7011",
    "addr:housenumber":"1",
    "addr:postcode":"7011",
    "addr:street":"Whitestone Drv",
    "iso:country":"AU",
    "sg:address":"1 Whitestone Drv",
    "sg:city":"Austins Ferry",
    "sg:classifiers":[
        {
            "category":"Home & Garden",
            "subcategory":"Building Materials",
            "type":"Retail Goods"
        }
    ],
    "sg:phone":"+61 3 6249 4988",
    "sg:postcode":"7011",
    "sg:province":"TAS",
    "sg:tags":[
        "roofing"
    ],
    "wof:name":"Steeline Roofing Hobart",
    "wof:placetype":"venue"
},
  "geometry": {"coordinates":[147.245407105,-42.7661933899],"type":"Point"}
}