{
  "type": "Feature",
  "properties": {
    "iso:country":"AU",
    "sg:address":"Shop 2/ 161 New South Head Rd",
    "sg:city":"Edgecliff",
    "sg:classifiers":[
        {
            "category":"Education",
            "subcategory":"Vocational School",
            "type":"Public Place"
        }
    ],
    "sg:phone":"+61 2 9326 2211",
    "sg:postcode":"2027",
    "sg:province":"NSW",
    "sg:tags":[
        "beauty"
    ],
    "wof:name":"Fuss Beauty College",
    "wof:placetype":"venue"
},
  "geometry": {"coordinates":[151.23449707,-33.8780708313],"type":"Point"}
}