{
  "type": "Feature",
  "properties": {
    "iso:country":"AU",
    "sg:address":"30 Lime St",
    "sg:city":"Marrar",
    "sg:classifiers":[
        {
            "category":"Building & Trades",
            "subcategory":"Construction",
            "type":"Services"
        }
    ],
    "sg:phone":"+61 427 261 490",
    "sg:postcode":"2652",
    "sg:province":"NSW",
    "sg:tags":[
        "earth",
        "excavating",
        "moving",
        "contractor"
    ],
    "wof:name":"Bidgee Mini Diggers",
    "wof:placetype":"venue"
},
  "geometry": {"coordinates":[147.34727477999999,-34.8253288269],"type":"Point"}
}