{
  "type": "Feature",
  "properties": {
    "iso:country":"AU",
    "sg:address":"1/ 127 Charlestown Rd",
    "sg:city":"Kotara",
    "sg:classifiers":[
        {
            "category":"Organizations",
            "subcategory":"Membership Organization",
            "type":"Services"
        }
    ],
    "sg:phone":"+61 2 4942 1555",
    "sg:postcode":"2289",
    "sg:province":"NSW",
    "sg:tags":[
        "equipment",
        "inter-communication",
        "system"
    ],
    "wof:name":"Bruker Intercoms",
    "wof:placetype":"venue"
},
  "geometry": {"coordinates":[151.686157227,-32.9475440979],"type":"Point"}
}