{
  "type": "Feature",
  "properties": {
    "addr:full":"292 Church St Richmond VIC 3121",
    "addr:housenumber":"292",
    "addr:postcode":"3121",
    "addr:street":"Church St",
    "iso:country":"AU",
    "sg:address":"292 Church St",
    "sg:city":"Richmond",
    "sg:classifiers":[
        {
            "category":"Food & Beverages",
            "subcategory":"Liquor & Beverages",
            "type":"Retail Goods"
        }
    ],
    "sg:phone":"+61 3 8420 6363",
    "sg:postcode":"3121",
    "sg:province":"VIC",
    "sg:tags":[
        "merchant",
        "spirit",
        "wine"
    ],
    "wof:name":"Winestock",
    "wof:placetype":"venue"
},
  "geometry": {"coordinates":[144.99873352,-37.8201828003],"type":"Point"}
}