{
  "type": "Feature",
  "properties": {
    "addr:full":"286 Dorset Rd Boronia VIC 3155",
    "addr:housenumber":"286",
    "addr:postcode":"3155",
    "addr:street":"Dorset Rd",
    "iso:country":"AU",
    "sg:address":"286 Dorset Rd",
    "sg:city":"Boronia",
    "sg:classifiers":[
        {
            "category":"Health Services",
            "subcategory":"Dentist",
            "type":"Services"
        }
    ],
    "sg:phone":"+61 3 9762 5177",
    "sg:postcode":"3155",
    "sg:province":"VIC",
    "wof:name":"Daniel C. R. Robin Dr",
    "wof:placetype":"venue"
},
  "geometry": {"coordinates":[145.28602600100001,-37.8577842712],"type":"Point"}
}