{
  "type": "Feature",
  "properties": {
    "addr:full":"Unit 2/ 39 Elgin St Alderley QLD 4051",
    "addr:housenumber":"39",
    "addr:postcode":"4051",
    "addr:street":"Elgin St",
    "iso:country":"AU",
    "sg:address":"Unit 2/ 39 Elgin St",
    "sg:city":"Alderley",
    "sg:classifiers":[
        {
            "category":"Professional",
            "subcategory":"Art Services",
            "type":"Services"
        }
    ],
    "sg:phone":"+61 7 3356 9033",
    "sg:postcode":"4051",
    "sg:province":"QLD",
    "sg:tags":[
        "graphic",
        "designer"
    ],
    "wof:name":"See-Saw Illustration & Design",
    "wof:placetype":"venue"
},
  "geometry": {"coordinates":[153.00086975100001,-27.4265785217],"type":"Point"}
}