{
  "type": "Feature",
  "properties": {
    "iso:country":"AU",
    "sg:address":"34-36 Townsville St",
    "sg:city":"Fyshwick",
    "sg:classifiers":[
        {
            "category":"Food & Beverages",
            "subcategory":"Liquor & Beverages",
            "type":"Retail Goods"
        }
    ],
    "sg:phone":"+61 2 6280 6329",
    "sg:postcode":"2609",
    "sg:province":"ACT",
    "sg:tags":[
        "merchant",
        "spirit",
        "wine"
    ],
    "wof:name":"Mc Laren Vale Cellars Pty Ltd",
    "wof:placetype":"venue"
},
  "geometry": {"coordinates":[149.18318176299999,-35.3286399841],"type":"Point"}
}