{
  "type": "Feature",
  "properties": {
    "addr:full":"40 Auburn Rd Auburn NSW 2144",
    "addr:housenumber":"40",
    "addr:postcode":"2144",
    "addr:street":"Auburn Rd",
    "iso:country":"AU",
    "sg:address":"40 Auburn Rd",
    "sg:city":"Auburn",
    "sg:classifiers":[
        {
            "category":"Food & Beverages",
            "subcategory":"Bakery",
            "type":"Retail Goods"
        }
    ],
    "sg:phone":"+61 2 9749 2523",
    "sg:postcode":"2144",
    "sg:province":"NSW",
    "sg:tags":[
        "baker"
    ],
    "wof:name":"Menzil Turkish Bakehouse",
    "wof:placetype":"venue"
},
  "geometry": {"coordinates":[151.03269958499999,-33.852771759],"type":"Point"}
}