{
  "type": "Feature",
  "properties": {
    "iso:country":"AU",
    "sg:address":"PO Box 674",
    "sg:city":"Redbank Plains",
    "sg:classifiers":[
        {
            "category":"Home & Garden",
            "subcategory":"Building Materials",
            "type":"Retail Goods"
        }
    ],
    "sg:phone":"+61 7 3389 2344",
    "sg:postcode":"4301",
    "sg:province":"QLD",
    "sg:tags":[
        "merchant",
        "glass",
        "glazier"
    ],
    "wof:name":"A Poyner Glass",
    "wof:placetype":"venue"
},
  "geometry": {"coordinates":[152.872589111,-27.6409301758],"type":"Point"}
}