{
  "type": "Feature",
  "properties": {
    "addr:full":"637 Forest Rd Peakhurst NSW 2210",
    "addr:housenumber":"637",
    "addr:postcode":"2210",
    "addr:street":"Forest Rd",
    "iso:country":"AU",
    "sg:address":"637 Forest Rd",
    "sg:city":"Peakhurst",
    "sg:classifiers":[
        {
            "category":"Wholesale",
            "subcategory":"Auto Parts",
            "type":"Manufacturing & Wholesale Goods"
        }
    ],
    "sg:phone":"+61 2 9584 9077",
    "sg:postcode":"2210",
    "sg:province":"NSW",
    "sg:tags":[
        "tyre"
    ],
    "wof:name":"Competitive Tyres",
    "wof:placetype":"venue"
},
  "geometry": {"coordinates":[151.068726,-33.958069],"type":"Point"}
}