{
  "type": "Feature",
  "properties": {
    "iso:country":"AU",
    "sg:address":"191 Magellan St",
    "sg:city":"Lismore",
    "sg:classifiers":[
        {
            "category":"Arts & Performance",
            "subcategory":"Dance",
            "type":"Entertainment"
        }
    ],
    "sg:phone":"+61 416 094 283",
    "sg:postcode":"2480",
    "sg:province":"NSW",
    "sg:tags":[
        "theatrical",
        "ballet",
        "tuition"
    ],
    "wof:name":"Karen Ireland Dance Centre",
    "wof:placetype":"venue"
},
  "geometry": {"coordinates":[153.283004761,-28.8126525879],"type":"Point"}
}