{
  "type": "Feature",
  "properties": {
    "iso:country":"AU",
    "sg:address":"385 Duthie Ave",
    "sg:city":"North Rockhampton",
    "sg:classifiers":[
        {
            "category":"Education",
            "subcategory":"Kindergarten",
            "type":"Public Place"
        }
    ],
    "sg:phone":"+61 7 4926 5552",
    "sg:postcode":"4701",
    "sg:province":"QLD",
    "sg:tags":[
        "pre-schools"
    ],
    "wof:name":"Skippy's Early Learning Centre",
    "wof:placetype":"venue"
},
  "geometry": {"coordinates":[150.5418396,-23.3483772278],"type":"Point"}
}