{
  "type": "Feature",
  "properties": {
    "addr:full":"547 Keilor Rd Niddrie VIC 3042",
    "addr:housenumber":"547",
    "addr:postcode":"3042",
    "addr:street":"Keilor Rd",
    "iso:country":"AU",
    "sg:address":"547 Keilor Rd",
    "sg:city":"Niddrie",
    "sg:classifiers":[
        {
            "category":"Shopping",
            "subcategory":"Bicycles & Sporting Goods",
            "type":"Retail Goods"
        }
    ],
    "sg:phone":"+61 3 9379 1144",
    "sg:postcode":"3042",
    "sg:province":"VIC",
    "sg:tags":[
        "chemical",
        "equipment",
        "pool",
        "swimming"
    ],
    "wof:name":"Kreepy Krauly",
    "wof:placetype":"venue"
},
  "geometry": {"coordinates":[144.88345336899999,-37.7341537476],"type":"Point"}
}