{
  "type": "Feature",
  "properties": {
    "addr:full":"499 Zillmere Rd Zillmere QLD 4034",
    "addr:housenumber":"499",
    "addr:postcode":"4034",
    "addr:street":"Zillmere Rd",
    "iso:country":"AU",
    "sg:address":"499 Zillmere Rd",
    "sg:city":"Zillmere",
    "sg:classifiers":[
        {
            "category":"Manufacturing",
            "subcategory":"Paper Products",
            "type":"Manufacturing & Wholesale Goods"
        }
    ],
    "sg:phone":"+61 7 3263 5022",
    "sg:postcode":"4034",
    "sg:province":"QLD",
    "sg:tags":[
        "box",
        "fibre",
        "carton",
        "cardboard"
    ],
    "wof:name":"Amcor Cartons",
    "wof:placetype":"venue"
},
  "geometry": {"coordinates":[153.03277600000001,-27.358467],"type":"Point"}
}