{
  "type": "Feature",
  "properties": {
    "addr:full":"PO Box 357 Black Rock VIC 3193",
    "addr:postcode":"3193",
    "iso:country":"AU",
    "sg:address":"PO Box 357",
    "sg:city":"Black Rock",
    "sg:classifiers":[
        {
            "category":"Home & Garden",
            "subcategory":"Building Materials",
            "type":"Retail Goods"
        }
    ],
    "sg:phone":"+61 3 9533 1215",
    "sg:postcode":"3193",
    "sg:province":"VIC",
    "sg:tags":[
        "lawn",
        "cutting",
        "maintenance"
    ],
    "wof:name":"Greenright",
    "wof:placetype":"venue"
},
  "geometry": {"coordinates":[145.03004455600001,-37.9695014954],"type":"Point"}
}