{
  "type": "Feature",
  "properties": {
    "iso:country":"AU",
    "sg:address":"3/ 7 Pendrigh Pl St",
    "sg:city":"Helens",
    "sg:classifiers":[
        {
            "category":"Professional",
            "subcategory":"Accounting & Tax Preparation",
            "type":"Services"
        }
    ],
    "sg:phone":"+61 3 6376 1422",
    "sg:postcode":"7216",
    "sg:province":"TAS",
    "sg:tags":[
        "consultant",
        "taxation"
    ],
    "wof:name":"East Coast Accounting",
    "wof:placetype":"venue"
},
  "geometry": {"coordinates":[148.250748,-41.322685],"type":"Point"}
}