{
  "type": "Feature",
  "properties": {
    "iso:country":"AU",
    "sg:address":"84 Hume Hwy",
    "sg:city":"Lansvale",
    "sg:classifiers":[
        {
            "category":"Building & Trades",
            "subcategory":"Construction",
            "type":"Services"
        }
    ],
    "sg:phone":"+61 2 9794 5200",
    "sg:postcode":"2166",
    "sg:province":"NSW",
    "sg:tags":[
        "window",
        "timber"
    ],
    "sg:website":"http://www.stegbar.com.au",
    "wof:name":"Stegbar",
    "wof:placetype":"venue"
},
  "geometry": {"coordinates":[150.96214294399999,-33.8928451538],"type":"Point"}
}