{
  "type": "Feature",
  "properties": {
    "addr:full":"4/ 2211 Gold Coast Hwy Nobby Beach QLD 4218",
    "addr:housenumber":"/ 2211",
    "addr:postcode":"4218",
    "addr:street":"Gold Coast Hwy",
    "iso:country":"AU",
    "sg:address":"4/ 2211 Gold Coast Hwy",
    "sg:city":"Nobby Beach",
    "sg:classifiers":[
        {
            "category":"Personal",
            "subcategory":"Beauty Salon",
            "type":"Services"
        }
    ],
    "sg:phone":"+61 7 5572 2781",
    "sg:postcode":"4218",
    "sg:province":"QLD",
    "sg:tags":[
        "hairdresser"
    ],
    "wof:name":"New Lengths Hair & Beauty",
    "wof:placetype":"venue"
},
  "geometry": {"coordinates":[153.438064575,-28.0600948334],"type":"Point"}
}