{
  "type": "Feature",
  "properties": {
    "iso:country":"AU",
    "sg:address":"7 Eckersall St",
    "sg:city":"Brunswick",
    "sg:classifiers":[
        {
            "category":"Professional",
            "subcategory":"Art Services",
            "type":"Services"
        }
    ],
    "sg:phone":"+61 424 349 920",
    "sg:postcode":"3056",
    "sg:province":"VIC",
    "sg:tags":[
        "graphic",
        "designer"
    ],
    "wof:name":"Push Creative",
    "wof:placetype":"venue"
},
  "geometry": {"coordinates":[144.9637146,-37.7627983093],"type":"Point"}
}