{
  "type": "Feature",
  "properties": {
    "iso:country":"AU",
    "sg:address":"32 Orwell St",
    "sg:city":"Potts Point",
    "sg:classifiers":[
        {
            "category":"Health Services",
            "subcategory":"Doctor",
            "type":"Services"
        }
    ],
    "sg:phone":"+61 2 9368 1501",
    "sg:postcode":"2011",
    "sg:province":"NSW",
    "sg:tags":[
        "nurse",
        "nursing"
    ],
    "wof:name":"Allied Medistaff Nursing Service",
    "wof:placetype":"venue"
},
  "geometry": {"coordinates":[151.22482299800001,-33.8719863892],"type":"Point"}
}