{
  "type": "Feature",
  "properties": {
    "iso:country":"AU",
    "sg:address":"Burwood Heights Shopping Centre, Cnr Burwood Hwy & Middleborough Rd",
    "sg:city":"Burwood East",
    "sg:classifiers":[
        {
            "category":"Health Services",
            "subcategory":"Optometrist",
            "type":"Services"
        }
    ],
    "sg:phone":"+61 3 9808 2691",
    "sg:postcode":"3151",
    "sg:province":"VIC",
    "wof:name":"Spectacles Plus (Visioncare)",
    "wof:placetype":"venue"
},
  "geometry": {"coordinates":[145.15034484899999,-37.8537216187],"type":"Point"}
}