{
  "type": "Feature",
  "properties": {
    "addr:full":"833A Burke Rd Camberwell VIC 3124",
    "addr:housenumber":"833a",
    "addr:postcode":"3124",
    "addr:street":"Burke Rd",
    "iso:country":"AU",
    "sg:address":"833A Burke Rd",
    "sg:city":"Camberwell",
    "sg:classifiers":[
        {
            "category":"Banks & Credit Unions",
            "subcategory":"Bureau De Change",
            "type":"Services"
        }
    ],
    "sg:phone":"+61 1300 139 060",
    "sg:postcode":"3124",
    "sg:province":"VIC",
    "sg:tags":[
        "currency",
        "exchange",
        "foreign"
    ],
    "wof:name":"American Express Foreign Exchange Services",
    "wof:placetype":"venue"
},
  "geometry": {"coordinates":[145.05711364699999,-37.8282737732],"type":"Point"}
}