{
  "type": "Feature",
  "properties": {
    "addr:full":"Old Peachester Rd Beerwah QLD 4519",
    "addr:postcode":"4519",
    "addr:street":"Peachester Rd",
    "iso:country":"AU",
    "sg:address":"Old Peachester Rd",
    "sg:city":"Beerwah",
    "sg:classifiers":[
        {
            "category":"Farming",
            "subcategory":"Farm",
            "type":"Manufacturing & Wholesale Goods"
        }
    ],
    "sg:phone":"+61 7 5494 9529",
    "sg:postcode":"4519",
    "sg:province":"QLD",
    "sg:tags":[
        "farmer"
    ],
    "wof:name":"Walton's Ginger-Pine Pty Ltd",
    "wof:placetype":"venue"
},
  "geometry": {"coordinates":[152.90992700000001,-26.848303],"type":"Point"}
}