{
  "type": "Feature",
  "properties": {
    "addr:full":"181- 183 Forest Rd Hurstville NSW 1493",
    "addr:housenumber":"183",
    "addr:postcode":"1493",
    "addr:street":"Forest Rd",
    "iso:country":"AU",
    "sg:address":"181- 183 Forest Rd",
    "sg:city":"Hurstville",
    "sg:classifiers":[
        {
            "category":"Professional",
            "subcategory":"Accounting & Tax Preparation",
            "type":"Services"
        }
    ],
    "sg:phone":"+61 1300 856 181",
    "sg:postcode":"1493",
    "sg:province":"NSW",
    "sg:tags":[
        "bookkeeping"
    ],
    "wof:name":"The Institute Of Certified Bookkeepers",
    "wof:placetype":"venue"
},
  "geometry": {"coordinates":[151.103149,-33.967178],"type":"Point"}
}