{
  "type": "Feature",
  "properties": {
    "addr:full":"1104 Blunder Rd Doolandella QLD 4077",
    "addr:housenumber":"1104",
    "addr:postcode":"4077",
    "addr:street":"Blunder Rd",
    "iso:country":"AU",
    "sg:address":"1104 Blunder Rd",
    "sg:city":"Doolandella",
    "sg:classifiers":[
        {
            "category":"Professional",
            "type":"Services"
        }
    ],
    "sg:phone":"+61 7 3879 9917",
    "sg:postcode":"4077",
    "sg:province":"QLD",
    "sg:tags":[
        "transport"
    ],
    "wof:name":"Ace Ways Trucking",
    "wof:placetype":"venue"
},
  "geometry": {"coordinates":[152.98626709000001,-27.61510849],"type":"Point"}
}