{
  "type": "Feature",
  "properties": {
    "addr:full":"8 James Crt Tottenham VIC 3012",
    "addr:housenumber":"8",
    "addr:postcode":"3012",
    "addr:street":"James Crt",
    "iso:country":"AU",
    "sg:address":"8 James Crt",
    "sg:city":"Tottenham",
    "sg:classifiers":[
        {
            "category":"Shopping",
            "subcategory":"Stationery & Office Supplies",
            "type":"Retail Goods"
        }
    ],
    "sg:phone":"+61 3 9315 2533",
    "sg:postcode":"3012",
    "sg:province":"VIC",
    "sg:tags":[
        "partition"
    ],
    "wof:name":"Criterion Industries",
    "wof:placetype":"venue"
},
  "geometry": {"coordinates":[144.848556519,-37.7995033264],"type":"Point"}
}