{
  "type": "Feature",
  "properties": {
    "addr:full":"PO Box 233 Terrey Hills NSW 2084",
    "addr:postcode":"2084",
    "iso:country":"AU",
    "sg:address":"PO Box 233",
    "sg:city":"Terrey Hills",
    "sg:classifiers":[
        {
            "category":"Wholesale",
            "subcategory":"Machinery & Supplies",
            "type":"Manufacturing & Wholesale Goods"
        }
    ],
    "sg:phone":"+61 1300 555 977",
    "sg:postcode":"2084",
    "sg:province":"NSW",
    "sg:tags":[
        "equipment",
        "laboratory"
    ],
    "wof:name":"LABLINK Electrodes Meters Titration",
    "wof:placetype":"venue"
},
  "geometry": {"coordinates":[151.229705811,-33.6837692261],"type":"Point"}
}