{
  "type": "Feature",
  "properties": {
    "iso:country":"AU",
    "sg:address":"323 Blackburn Rd",
    "sg:city":"Burwood",
    "sg:classifiers":[
        {
            "category":"Government",
            "subcategory":"Court House",
            "type":"Public Place"
        }
    ],
    "sg:phone":"+61 3 9893 5995",
    "sg:postcode":"3125",
    "sg:province":"VIC",
    "sg:tags":[
        "personal",
        "marriage",
        "family",
        "counselling"
    ],
    "wof:name":"Abate Marisa",
    "wof:placetype":"venue"
},
  "geometry": {"coordinates":[145.15284729000001,-37.8494377136],"type":"Point"}
}