{
  "type": "Feature",
  "properties": {
    "iso:country":"AU",
    "sg:address":"19 Beh St",
    "sg:city":"Toowoomba",
    "sg:classifiers":[
        {
            "category":"Professional",
            "subcategory":"Printing & Photocopies",
            "type":"Services"
        }
    ],
    "sg:phone":"+61 7 4636 1935",
    "sg:postcode":"4350",
    "sg:province":"QLD",
    "sg:tags":[
        "equipment",
        "plan"
    ],
    "wof:name":"Toowoomba Office Supplies",
    "wof:placetype":"venue"
},
  "geometry": {"coordinates":[151.935257,-27.588902],"type":"Point"}
}