{
  "type": "Feature",
  "properties": {
    "addr:full":"80 High St Southport QLD 4215",
    "addr:housenumber":"80",
    "addr:postcode":"4215",
    "addr:street":"High St",
    "iso:country":"AU",
    "sg:address":"80 High St",
    "sg:city":"Southport",
    "sg:classifiers":[
        {
            "category":"Autos & Motor Vehicles",
            "subcategory":"Automobile Sales",
            "type":"Retail Goods"
        }
    ],
    "sg:phone":"+61 7 5532 4000",
    "sg:postcode":"4215",
    "sg:province":"QLD",
    "sg:tags":[
        "car",
        "new"
    ],
    "wof:name":"Euromarque Gold Coast",
    "wof:placetype":"venue"
},
  "geometry": {"coordinates":[153.408935547,-27.96641922],"type":"Point"}
}