{
  "type": "Feature",
  "properties": {
    "addr:full":"Mons Rd Forest Glen QLD 4556",
    "addr:postcode":"4556",
    "addr:street":"Mons Rd",
    "iso:country":"AU",
    "sg:address":"Mons Rd",
    "sg:city":"Forest Glen",
    "sg:classifiers":[
        {
            "category":"Shopping",
            "subcategory":"Clothing, Apparel, & Fashions",
            "type":"Retail Goods"
        }
    ],
    "sg:phone":"+61 7 5445 3311",
    "sg:postcode":"4556",
    "sg:province":"QLD",
    "sg:tags":[
        "style",
        "clothing",
        "western",
        "accessory"
    ],
    "wof:name":"Horseland",
    "wof:placetype":"venue"
},
  "geometry": {"coordinates":[153.009963989,-26.6886234283],"type":"Point"}
}