{
  "type": "Feature",
  "properties": {
    "addr:full":"Shop 1/ 1 Heathwood St Dayboro QLD 4521",
    "addr:housenumber":"shop 1 / 1",
    "addr:postcode":"4521",
    "addr:street":"Heathwood St",
    "iso:country":"AU",
    "sg:address":"Shop 1/ 1 Heathwood St",
    "sg:city":"Dayboro",
    "sg:classifiers":[
        {
            "category":"Restaurant",
            "type":"Food & Drink"
        }
    ],
    "sg:phone":"+61 7 3425 1510",
    "sg:postcode":"4521",
    "sg:province":"QLD",
    "wof:name":"Amore Cafe & Restaurant",
    "wof:placetype":"venue"
},
  "geometry": {"coordinates":[152.82429500000001,-27.195902],"type":"Point"}
}