{
  "type": "Feature",
  "properties": {
    "addr:full":"45 Beane St Gosford NSW 2250",
    "addr:housenumber":"45",
    "addr:postcode":"2250",
    "addr:street":"Beane St",
    "iso:country":"AU",
    "sg:address":"45 Beane St",
    "sg:city":"Gosford",
    "sg:classifiers":[
        {
            "category":"Professional",
            "subcategory":"Business Services",
            "type":"Services"
        }
    ],
    "sg:phone":"+61 2 4324 4714",
    "sg:postcode":"2250",
    "sg:province":"NSW",
    "sg:tags":[
        "drafting"
    ],
    "wof:name":"Mepstead & Associates",
    "wof:placetype":"venue"
},
  "geometry": {"coordinates":[151.34478759800001,-33.4213676453],"type":"Point"}
}