{
  "type": "Feature",
  "properties": {
    "addr:full":"140 Bondi Rd Bondi NSW 2026",
    "addr:housenumber":"140",
    "addr:postcode":"2026",
    "addr:street":"Bondi Rd",
    "iso:country":"AU",
    "sg:address":"140 Bondi Rd",
    "sg:city":"Bondi",
    "sg:classifiers":[
        {
            "category":"Government",
            "subcategory":"City Hall",
            "type":"Public Place"
        }
    ],
    "sg:phone":"+61 2 9387 3663",
    "sg:postcode":"2026",
    "sg:province":"NSW",
    "wof:name":"Masonic Halls & Centres",
    "wof:placetype":"venue"
},
  "geometry": {"coordinates":[151.26014709500001,-33.8932342529],"type":"Point"}
}