{
  "type": "Feature",
  "properties": {
    "addr:full":"14 Hawtin Rd Maida Vale WA 6057",
    "addr:housenumber":"14",
    "addr:postcode":"6057",
    "addr:street":"Hawtin Rd",
    "iso:country":"AU",
    "sg:address":"14 Hawtin Rd",
    "sg:city":"Maida Vale",
    "sg:classifiers":[
        {
            "category":"Banks & Credit Unions",
            "subcategory":"Financial Services",
            "type":"Services"
        }
    ],
    "sg:phone":"+61 8 9454 6322",
    "sg:postcode":"6057",
    "sg:province":"WA",
    "sg:tags":[
        "settlement",
        "nt",
        "agent",
        "wa"
    ],
    "wof:name":"Kalamunda Settlements",
    "wof:placetype":"venue"
},
  "geometry": {"coordinates":[116.022666931,-31.9541282654],"type":"Point"}
}