{
  "type": "Feature",
  "properties": {
    "addr:full":"4- 6 Purdy St Minchinbury NSW 2770",
    "addr:housenumber":"6",
    "addr:postcode":"2770",
    "addr:street":"Purdy St",
    "iso:country":"AU",
    "sg:address":"4- 6 Purdy St",
    "sg:city":"Minchinbury",
    "sg:classifiers":[
        {
            "category":"Utilities",
            "type":"Services"
        }
    ],
    "sg:phone":"+61 2 9832 1711",
    "sg:postcode":"2770",
    "sg:province":"NSW",
    "sg:tags":[
        "refrigeration",
        "industrial",
        "commercial",
        "retail"
    ],
    "wof:name":"Kingloc Commercial Equipment Pty Ltd",
    "wof:placetype":"venue"
},
  "geometry": {"coordinates":[150.81559753400001,-33.7818183899],"type":"Point"}
}