{
  "type": "Feature",
  "properties": {
    "addr:full":"Shop 2, 62 Manning St Tuncurry NSW 2428",
    "addr:housenumber":"shop;62",
    "addr:postcode":"2428",
    "addr:street":"Manning St",
    "iso:country":"AU",
    "sg:address":"Shop 2, 62 Manning St",
    "sg:city":"Tuncurry",
    "sg:classifiers":[
        {
            "category":"Health Services",
            "subcategory":"Optometrist",
            "type":"Services"
        }
    ],
    "sg:phone":"+61 2 6555 8233",
    "sg:postcode":"2428",
    "sg:province":"NSW",
    "wof:name":"Rolfe D G",
    "wof:placetype":"venue"
},
  "geometry": {"coordinates":[152.49984699999999,-32.176098],"type":"Point"}
}