{
  "type": "Feature",
  "properties": {
    "addr:full":"352 New South Head Rd Double Bay NSW 2028",
    "addr:housenumber":"352",
    "addr:postcode":"2028",
    "addr:street":"New South Head Rd",
    "iso:country":"AU",
    "sg:address":"352 New South Head Rd",
    "sg:city":"Double Bay",
    "sg:classifiers":[
        {
            "category":"Real Estate",
            "subcategory":"Real Estate Agent",
            "type":"Services"
        }
    ],
    "sg:phone":"+61 2 9327 5825",
    "sg:postcode":"2028",
    "sg:province":"NSW",
    "wof:name":"Richardson & Wrench Pty Ltd",
    "wof:placetype":"venue"
},
  "geometry": {"coordinates":[151.24270629899999,-33.8777084351],"type":"Point"}
}