{
  "type": "Feature",
  "properties": {
    "addr:full":"2F Mountain Rd Austinmer NSW 2515",
    "addr:housenumber":"2f",
    "addr:postcode":"2515",
    "addr:street":"Mountain Rd",
    "iso:country":"AU",
    "sg:address":"2F Mountain Rd",
    "sg:city":"Austinmer",
    "sg:classifiers":[
        {
            "category":"Building & Trades",
            "subcategory":"Construction",
            "type":"Services"
        }
    ],
    "sg:phone":"+61 408 426 321",
    "sg:postcode":"2515",
    "sg:province":"NSW",
    "sg:tags":[
        "contractor"
    ],
    "wof:name":"Clayton Constructions",
    "wof:placetype":"venue"
},
  "geometry": {"coordinates":[150.931366,-34.311039],"type":"Point"}
}