{
  "type": "Feature",
  "properties": {
    "addr:full":"Shop T49 Cherrybrook Plz 41- 47 Shepards Drv Cherrybrook NSW 2126",
    "addr:housenumber":"t49;41 47",
    "addr:postcode":"2126",
    "addr:street":"Cherrybrook Plz;Shepards Drv",
    "iso:country":"AU",
    "sg:address":"Shop T49 Cherrybrook Plz 41- 47 Shepards Drv",
    "sg:city":"Cherrybrook",
    "sg:classifiers":[
        {
            "category":"Cafe",
            "type":"Food & Drink"
        }
    ],
    "sg:phone":"+61 2 9980 9922",
    "sg:postcode":"2126",
    "sg:province":"NSW",
    "wof:name":"Gloria Jean's Coffees",
    "wof:placetype":"venue"
},
  "geometry": {"coordinates":[151.054077148,-33.7325439453],"type":"Point"}
}