{
  "type": "Feature",
  "properties": {
    "addr:full":"Shop 3 117 Koornang Rd Carnegie VIC 3163",
    "addr:housenumber":"shop 3",
    "addr:postcode":"117;3163",
    "addr:street":"Koornang Rd",
    "iso:country":"AU",
    "sg:address":"Shop 3 117 Koornang Rd",
    "sg:city":"Carnegie",
    "sg:classifiers":[
        {
            "category":"Shopping",
            "subcategory":"Jewelry",
            "type":"Retail Goods"
        }
    ],
    "sg:phone":"+61 3 9572 0433",
    "sg:postcode":"3163",
    "sg:province":"VIC",
    "sg:tags":[
        "jeweller"
    ],
    "wof:name":"Granek",
    "wof:placetype":"venue"
},
  "geometry": {"coordinates":[145.05706787099999,-37.8883094788],"type":"Point"}
}