{
  "type": "Feature",
  "properties": {
    "addr:full":"33 Harte St Chelmer QLD 4068",
    "addr:housenumber":"33",
    "addr:postcode":"4068",
    "addr:street":"Harte St",
    "iso:country":"AU",
    "sg:address":"33 Harte St",
    "sg:city":"Chelmer",
    "sg:classifiers":[
        {
            "category":"Banks & Credit Unions",
            "subcategory":"Investment Brokerage",
            "type":"Services"
        }
    ],
    "sg:phone":"+61 7 3278 2095",
    "sg:postcode":"4068",
    "sg:province":"QLD",
    "sg:tags":[
        "water",
        "reticulation",
        "contractor"
    ],
    "wof:name":"Autorain Irrigation Systems",
    "wof:placetype":"venue"
},
  "geometry": {"coordinates":[152.97848510700001,-27.5146713257],"type":"Point"}
}