{
  "type": "Feature",
  "properties": {
    "addr:full":"3/ 806 Beaudesert Rd Coopers Plains QLD 4108",
    "addr:housenumber":"/ 806",
    "addr:postcode":"4108",
    "addr:street":"Beaudesert Rd",
    "iso:country":"AU",
    "sg:address":"3/ 806 Beaudesert Rd",
    "sg:city":"Coopers Plains",
    "sg:classifiers":[
        {
            "category":"Government",
            "subcategory":"Department Of Motor Vehicles",
            "type":"Public Place"
        }
    ],
    "sg:phone":"+61 7 3272 9666",
    "sg:postcode":"4108",
    "sg:province":"QLD",
    "sg:tags":[
        "wholesaler",
        "mfrs",
        "accessory"
    ],
    "wof:name":"K.L.S. (Motorsports) QLD Pty Ltd",
    "wof:placetype":"venue"
},
  "geometry": {"coordinates":[153.021286011,-27.5590076447],"type":"Point"}
}