{
  "type": "Feature",
  "properties": {
    "addr:full":"36 Wharf St Forster NSW 2428",
    "addr:housenumber":"36",
    "addr:postcode":"2428",
    "addr:street":"Wharf St",
    "iso:country":"AU",
    "sg:address":"36 Wharf St",
    "sg:city":"Forster",
    "sg:classifiers":[
        {
            "category":"Banks & Credit Unions",
            "subcategory":"Bank",
            "type":"Services"
        }
    ],
    "sg:phone":"+61 2 6554 7055",
    "sg:postcode":"2428",
    "sg:province":"NSW",
    "wof:name":"Westpac Banking Corporation",
    "wof:placetype":"venue"
},
  "geometry": {"coordinates":[152.51101700000001,-32.18021],"type":"Point"}
}