{
  "type": "Feature",
  "properties": {
    "addr:full":"37 Kingsford St Fairy Meadow NSW 2519",
    "addr:housenumber":"37",
    "addr:postcode":"2519",
    "addr:street":"Kingsford St",
    "iso:country":"AU",
    "sg:address":"37 Kingsford St",
    "sg:city":"Fairy Meadow",
    "sg:classifiers":[
        {
            "category":"Retail",
            "subcategory":"Auto Repair",
            "type":"Services"
        }
    ],
    "sg:phone":"+61 2 4283 7199",
    "sg:postcode":"2519",
    "sg:province":"NSW",
    "sg:tags":[
        "sport",
        "motor"
    ],
    "wof:name":"Ballistic Performance",
    "wof:placetype":"venue"
},
  "geometry": {"coordinates":[150.89425700000001,-34.389084],"type":"Point"}
}