{
  "type": "Feature",
  "properties": {
    "iso:country":"AU",
    "sg:address":"34 Pearcea Rd",
    "sg:city":"Quakers Hill",
    "sg:classifiers":[
        {
            "category":"Building & Trades",
            "subcategory":"Cleaning & Sanitation",
            "type":"Services"
        }
    ],
    "sg:phone":"+61 2 9626 6509",
    "sg:postcode":"2763",
    "sg:province":"NSW",
    "sg:tags":[
        "industrial",
        "commercial",
        "contractor"
    ],
    "wof:name":"Haber Cleaning Service",
    "wof:placetype":"venue"
},
  "geometry": {"coordinates":[150.88734435999999,-33.7281684875],"type":"Point"}
}