{
  "type": "Feature",
  "properties": {
    "addr:full":"59 Reeves Rd Somersby NSW 2250",
    "addr:housenumber":"59",
    "addr:postcode":"2250",
    "addr:street":"Reeves Rd",
    "iso:country":"AU",
    "sg:address":"59 Reeves Rd",
    "sg:city":"Somersby",
    "sg:classifiers":[
        {
            "category":"Building & Trades",
            "subcategory":"Construction",
            "type":"Services"
        }
    ],
    "sg:phone":"+61 418 326 744",
    "sg:postcode":"2250",
    "sg:province":"NSW",
    "sg:tags":[
        "earth",
        "excavating",
        "moving",
        "contractor"
    ],
    "wof:name":"David Grant Earth Moving",
    "wof:placetype":"venue"
},
  "geometry": {"coordinates":[151.30000305199999,-33.3949737549],"type":"Point"}
}