{
  "type": "Feature",
  "properties": {
    "addr:full":"43a Thomas St Parramatta NSW 2150",
    "addr:housenumber":"43a",
    "addr:postcode":"2150",
    "addr:street":"Thomas St",
    "iso:country":"AU",
    "sg:address":"43a Thomas St",
    "sg:city":"Parramatta",
    "sg:classifiers":[
        {
            "category":"Health Services",
            "subcategory":"Nursing And Care Facility",
            "type":"Services"
        }
    ],
    "sg:phone":"+61 2 9630 1125",
    "sg:postcode":"2150",
    "sg:province":"NSW",
    "sg:tags":[
        "home"
    ],
    "wof:name":"Parramatta Nursing Home",
    "wof:placetype":"venue"
},
  "geometry": {"coordinates":[150.99197387699999,-33.8274269104],"type":"Point"}
}