{
  "type": "Feature",
  "properties": {
    "addr:full":"5/ 48 Watonga St Port Macquarie NSW 2444",
    "addr:housenumber":"/ 48",
    "addr:postcode":"2444",
    "addr:street":"Watonga St",
    "iso:country":"AU",
    "sg:address":"5/ 48 Watonga St",
    "sg:city":"Port Macquarie",
    "sg:classifiers":[
        {
            "category":"Building & Trades",
            "subcategory":"Locksmith",
            "type":"Services"
        }
    ],
    "sg:phone":"+61 2 6582 2311",
    "sg:postcode":"2444",
    "sg:province":"NSW",
    "sg:tags":[
        "lock"
    ],
    "wof:name":"Robert Hannon",
    "wof:placetype":"venue"
},
  "geometry": {"coordinates":[152.926559,-31.477896],"type":"Point"}
}