{
  "type": "Feature",
  "properties": {
    "addr:full":"53 Lindsay St Hamilton NSW 2303",
    "addr:housenumber":"53",
    "addr:postcode":"2303",
    "addr:street":"Lindsay St",
    "iso:country":"AU",
    "sg:address":"53 Lindsay St",
    "sg:city":"Hamilton",
    "sg:classifiers":[
        {
            "category":"Professional",
            "subcategory":"Accounting & Tax Preparation",
            "type":"Services"
        }
    ],
    "sg:phone":"+61 2 4961 6811",
    "sg:postcode":"2303",
    "sg:province":"NSW",
    "sg:tags":[
        "consultant",
        "taxation"
    ],
    "wof:name":"Walker & Company",
    "wof:placetype":"venue"
},
  "geometry": {"coordinates":[151.74774199999999,-32.922073],"type":"Point"}
}