{
  "type": "Feature",
  "properties": {
    "addr:full":"PO Box 690 Beaudesert QLD 4285",
    "addr:postcode":"4285",
    "iso:country":"AU",
    "sg:address":"PO Box 690",
    "sg:city":"Beaudesert",
    "sg:classifiers":[
        {
            "category":"Manufacturing",
            "subcategory":"Building Materials",
            "type":"Manufacturing & Wholesale Goods"
        }
    ],
    "sg:phone":"+61 7 5541 4838",
    "sg:postcode":"4285",
    "sg:province":"QLD",
    "sg:tags":[
        "concrete",
        "product"
    ],
    "wof:name":"Quickcell Technology Products Pty Ltd",
    "wof:placetype":"venue"
},
  "geometry": {"coordinates":[152.99581900000001,-27.98781],"type":"Point"}
}