{
  "type": "Feature",
  "properties": {
    "addr:full":"35-37 Bolong Rd Bomaderry NSW 2541",
    "addr:housenumber":"35-37",
    "addr:postcode":"2541",
    "addr:street":"Bolong Rd",
    "iso:country":"AU",
    "sg:address":"35-37 Bolong Rd",
    "sg:city":"Bomaderry",
    "sg:classifiers":[
        {
            "category":"Building & Trades",
            "subcategory":"Plumbing",
            "type":"Services"
        }
    ],
    "sg:phone":"+61 401 007 729",
    "sg:postcode":"2541",
    "sg:province":"NSW",
    "sg:tags":[
        "drainers"
    ],
    "wof:name":"A Action Plus Plumbing Services",
    "wof:placetype":"venue"
},
  "geometry": {"coordinates":[150.61024475100001,-34.8559036255],"type":"Point"}
}