{
  "type": "Feature",
  "properties": {
    "addr:full":"9 George Rd Salamander Bay NSW 2317",
    "addr:housenumber":"9",
    "addr:postcode":"2317",
    "addr:street":"George Rd",
    "iso:country":"AU",
    "sg:address":"9 George Rd",
    "sg:city":"Salamander Bay",
    "sg:classifiers":[
        {
            "category":"Utilities",
            "type":"Services"
        }
    ],
    "sg:phone":"+61 2 4984 6522",
    "sg:postcode":"2317",
    "sg:province":"NSW",
    "sg:tags":[
        "refrigeration",
        "industrial",
        "commercial",
        "retail"
    ],
    "wof:name":"Nelson Bay Refrigeration & Air Conditioning",
    "wof:placetype":"venue"
},
  "geometry": {"coordinates":[152.074997,-32.726624],"type":"Point"}
}