{
  "type": "Feature",
  "properties": {
    "addr:full":"16 Fullarton Rd Norwood SA 5067",
    "addr:housenumber":"16",
    "addr:postcode":"5067",
    "addr:street":"Fullarton Rd",
    "iso:country":"AU",
    "sg:address":"16 Fullarton Rd",
    "sg:city":"Norwood",
    "sg:classifiers":[
        {
            "category":"Building & Trades",
            "subcategory":"Landscaping Services",
            "type":"Services"
        }
    ],
    "sg:phone":"+61 8 8132 4000",
    "sg:postcode":"5067",
    "sg:province":"SA",
    "sg:tags":[
        "inspection"
    ],
    "wof:name":"Complete Pest Control",
    "wof:placetype":"venue"
},
  "geometry": {"coordinates":[138.623291016,-34.9204711914],"type":"Point"}
}