{
  "type": "Feature",
  "properties": {
    "addr:full":"7 Short St Scone NSW 2337",
    "addr:housenumber":"7",
    "addr:postcode":"2337",
    "addr:street":"Short St",
    "iso:country":"AU",
    "sg:address":"7 Short St",
    "sg:city":"Scone",
    "sg:classifiers":[
        {
            "category":"Professional",
            "subcategory":"Business Services",
            "type":"Services"
        }
    ],
    "sg:phone":"+61 2 6545 2108",
    "sg:postcode":"2337",
    "sg:province":"NSW",
    "sg:tags":[
        "drafting"
    ],
    "wof:name":"P. B. Eveleigh Plan Service",
    "wof:placetype":"venue"
},
  "geometry": {"coordinates":[150.87077331500001,-32.0538482666],"type":"Point"}
}