{
  "type": "Feature",
  "properties": {
    "iso:country":"AU",
    "sg:address":"11 Crows Rd",
    "sg:city":"Belmont",
    "sg:classifiers":[
        {
            "category":"Utilities",
            "subcategory":"Refuse",
            "type":"Services"
        }
    ],
    "sg:phone":"+61 3 5244 3386",
    "sg:postcode":"3216",
    "sg:province":"VIC",
    "sg:tags":[
        "remover",
        "rubbish"
    ],
    "wof:name":"Teddys",
    "wof:placetype":"venue"
},
  "geometry": {"coordinates":[144.35151672399999,-38.1844291687],"type":"Point"}
}