{
  "type": "Feature",
  "properties": {
    "addr:full":"3rd Floor 169 King St Newcastle NSW 2300",
    "addr:housenumber":"169",
    "addr:postcode":"2300",
    "addr:street":"King St",
    "iso:country":"AU",
    "sg:address":"3rd Floor 169 King St",
    "sg:city":"Newcastle",
    "sg:classifiers":[
        {
            "category":"Professional",
            "subcategory":"Accounting & Tax Preparation",
            "type":"Services"
        }
    ],
    "sg:phone":"+61 2 4926 4155",
    "sg:postcode":"2300",
    "sg:province":"NSW",
    "sg:tags":[
        "accountant",
        "auditor"
    ],
    "wof:name":"Simpson D",
    "wof:placetype":"venue"
},
  "geometry": {"coordinates":[151.77706900000001,-32.927219],"type":"Point"}
}