{
  "type": "Feature",
  "properties": {
    "addr:full":"134g Great Western Hwy Blaxland NSW 2774",
    "addr:housenumber":"134g",
    "addr:postcode":"2774",
    "addr:street":"Great Western Hwy",
    "iso:country":"AU",
    "sg:address":"134g Great Western Hwy",
    "sg:city":"Blaxland",
    "sg:classifiers":[
        {
            "category":"Shopping",
            "subcategory":"Clothing, Apparel, & Fashions",
            "type":"Retail Goods"
        }
    ],
    "sg:phone":"+61 2 4739 4111",
    "sg:postcode":"2774",
    "sg:province":"NSW",
    "sg:tags":[
        "boutique"
    ],
    "wof:name":"Venessa's Boutique",
    "wof:placetype":"venue"
},
  "geometry": {"coordinates":[150.61070251500001,-33.744884491],"type":"Point"}
}