{
  "type": "Feature",
  "properties": {
    "addr:full":"3/ 1 Koonya Crt Caringbah NSW 2229",
    "addr:housenumber":"/ 1",
    "addr:postcode":"2229",
    "addr:street":"Koonya Crt",
    "iso:country":"AU",
    "sg:address":"3/ 1 Koonya Crt",
    "sg:city":"Caringbah",
    "sg:classifiers":[
        {
            "category":"Building & Trades",
            "subcategory":"Construction",
            "type":"Services"
        }
    ],
    "sg:phone":"+61 2 9531 7787",
    "sg:postcode":"2229",
    "sg:province":"NSW",
    "sg:tags":[
        "insulation",
        "contractor"
    ],
    "wof:name":"Icynene",
    "wof:placetype":"venue"
},
  "geometry": {"coordinates":[151.12272644000001,-34.0273704529],"type":"Point"}
}