{
  "type": "Feature",
  "properties": {
    "addr:full":"392 Henley Beach Rd Lockleys SA 5032",
    "addr:housenumber":"392",
    "addr:postcode":"5032",
    "addr:street":"Henley Beach Rd",
    "iso:country":"AU",
    "sg:address":"392 Henley Beach Rd",
    "sg:city":"Lockleys",
    "sg:classifiers":[
        {
            "category":"Health Services",
            "subcategory":"Dentist",
            "type":"Services"
        }
    ],
    "sg:phone":"+61 8 8443 7634",
    "sg:postcode":"5032",
    "sg:province":"SA",
    "wof:name":"Kotanidis Dianne Dr",
    "wof:placetype":"venue"
},
  "geometry": {"coordinates":[138.53477477999999,-34.9268074036],"type":"Point"}
}