{
  "type": "Feature",
  "properties": {
    "addr:full":"29 River Rd Shoalhaven Heads NSW 2535",
    "addr:housenumber":"29",
    "addr:postcode":"2535",
    "addr:street":"River Rd",
    "iso:country":"AU",
    "sg:address":"29 River Rd",
    "sg:city":"Shoalhaven Heads",
    "sg:classifiers":[
        {
            "category":"Professional",
            "subcategory":"Art Services",
            "type":"Services"
        }
    ],
    "sg:phone":"+61 428 671 027",
    "sg:postcode":"2535",
    "sg:province":"NSW",
    "sg:tags":[
        "interior",
        "decorator"
    ],
    "wof:name":"Coleman N J & W C",
    "wof:placetype":"venue"
},
  "geometry": {"coordinates":[150.73739624000001,-34.8561820984],"type":"Point"}
}