{
  "type": "Feature",
  "properties": {
    "addr:full":"Zurich House, Level 5, 201 Leichhardt St Spring Hill QLD 4004",
    "addr:housenumber":"201",
    "addr:postcode":"4004",
    "addr:street":"Leichhardt St",
    "iso:country":"AU",
    "sg:address":"Zurich House, Level 5, 201 Leichhardt St",
    "sg:city":"Spring Hill",
    "sg:classifiers":[
        {
            "category":"Education",
            "subcategory":"University",
            "type":"Public Place"
        }
    ],
    "sg:phone":"+61 7 3832 0383",
    "sg:postcode":"4004",
    "sg:province":"QLD",
    "sg:tags":[
        "college",
        "tertiary"
    ],
    "wof:name":"Commercial Arts Training College",
    "wof:placetype":"venue"
},
  "geometry": {"coordinates":[153.02636718799999,-27.4621200562],"type":"Point"}
}