{
  "type": "Feature",
  "properties": {
    "iso:country":"AU",
    "sg:address":"21 Lantana St",
    "sg:city":"Blackburn",
    "sg:classifiers":[
        {
            "category":"Professional",
            "subcategory":"Accounting & Tax Preparation",
            "type":"Services"
        }
    ],
    "sg:phone":"+61 3 9877 0801",
    "sg:postcode":"3130",
    "sg:province":"VIC",
    "sg:tags":[
        "accountant",
        "auditor"
    ],
    "wof:name":"Austra Accounting Pty Ltd",
    "wof:placetype":"venue"
},
  "geometry": {"coordinates":[145.150299072,-37.8067245483],"type":"Point"}
}