{
  "type": "Feature",
  "properties": {
    "iso:country":"AU",
    "sg:address":"621 Malvern Rd",
    "sg:city":"Toorak",
    "sg:classifiers":[
        {
            "category":"Health Services",
            "subcategory":"Doctor",
            "type":"Services"
        }
    ],
    "sg:phone":"+61 3 9826 8437",
    "sg:postcode":"3142",
    "sg:province":"VIC",
    "sg:tags":[
        "medical",
        "practitioner"
    ],
    "wof:name":"Macneil Sophie Dr",
    "wof:placetype":"venue"
},
  "geometry": {"coordinates":[145.00700378400001,-37.848449707],"type":"Point"}
}