{
  "type": "Feature",
  "properties": {
    "addr:full":"15- 17 Dowling St Forbes NSW 2871",
    "addr:housenumber":"17",
    "addr:postcode":"2871",
    "addr:street":"Dowling St",
    "iso:country":"AU",
    "sg:address":"15- 17 Dowling St",
    "sg:city":"Forbes",
    "sg:classifiers":[
        {
            "category":"Fast Food",
            "type":"Food & Drink"
        }
    ],
    "sg:phone":"+61 2 6851 4540",
    "sg:postcode":"2871",
    "sg:province":"NSW",
    "sg:tags":[
        "away",
        "take"
    ],
    "wof:name":"McDonald's Family Restaurants",
    "wof:placetype":"venue"
},
  "geometry": {"coordinates":[148.01142899999999,-33.380432],"type":"Point"}
}