{
  "type": "Feature",
  "properties": {
    "addr:full":"47 George Mobbs Drv Castle Hill NSW 2154",
    "addr:housenumber":"47",
    "addr:postcode":"2154",
    "addr:street":"George Mobbs Drv",
    "iso:country":"AU",
    "sg:address":"47 George Mobbs Drv",
    "sg:city":"Castle Hill",
    "sg:classifiers":[
        {
            "category":"Retail",
            "subcategory":"Auto Repair",
            "type":"Services"
        }
    ],
    "sg:phone":"+61 2 9634 7472",
    "sg:postcode":"2154",
    "sg:province":"NSW",
    "sg:tags":[
        "repairer",
        "motor",
        "engineer"
    ],
    "wof:name":"Home Tune (NSW)",
    "wof:placetype":"venue"
},
  "geometry": {"coordinates":[151.002883911,-33.7495193481],"type":"Point"}
}