{
  "type": "Feature",
  "properties": {
    "addr:full":"PO Box 365 Eltham VIC 3095",
    "addr:postcode":"3095",
    "iso:country":"AU",
    "sg:address":"PO Box 365",
    "sg:city":"Eltham",
    "sg:classifiers":[
        {
            "category":"Building & Trades",
            "subcategory":"Construction",
            "type":"Services"
        }
    ],
    "sg:phone":"+61 414 518 164",
    "sg:postcode":"3095",
    "sg:province":"VIC",
    "sg:tags":[
        "earth",
        "excavating",
        "moving",
        "contractor"
    ],
    "wof:name":"Dingo Mini Excavations",
    "wof:placetype":"venue"
},
  "geometry": {"coordinates":[145.144363403,-37.6945762634],"type":"Point"}
}