{
  "type": "Feature",
  "properties": {
    "iso:country":"AU",
    "sg:address":"143a High St",
    "sg:city":"Heathcote",
    "sg:classifiers":[
        {
            "category":"Communications",
            "subcategory":"Film & Video Production",
            "type":"Services"
        }
    ],
    "sg:phone":"+61 3 5433 2773",
    "sg:postcode":"3523",
    "sg:province":"VIC",
    "sg:tags":[
        "dvd",
        "library"
    ],
    "wof:name":"Country Video-Heathcote",
    "wof:placetype":"venue"
},
  "geometry": {"coordinates":[144.708572,-36.921753],"type":"Point"}
}