{
  "type": "Feature",
  "properties": {
    "addr:full":"28 Eastern Rd Traralgon VIC 3844",
    "addr:housenumber":"28",
    "addr:postcode":"3844",
    "addr:street":"Eastern Rd",
    "iso:country":"AU",
    "sg:address":"28 Eastern Rd",
    "sg:city":"Traralgon",
    "sg:classifiers":[
        {
            "category":"Wholesale",
            "subcategory":"Construction Materials",
            "type":"Manufacturing & Wholesale Goods"
        }
    ],
    "sg:phone":"+61 3 5176 1442",
    "sg:postcode":"3844",
    "sg:province":"VIC",
    "sg:tags":[
        "protective",
        "coating"
    ],
    "wof:name":"Traralgon Paints Pty Ltd",
    "wof:placetype":"venue"
},
  "geometry": {"coordinates":[146.56338500999999,-38.185874939],"type":"Point"}
}