{
  "type": "Feature",
  "properties": {
    "iso:country":"AU",
    "sg:address":"144 Park St",
    "sg:city":"Rockhampton",
    "sg:classifiers":[
        {
            "category":"Professional",
            "subcategory":"Engineering",
            "type":"Services"
        }
    ],
    "sg:phone":"+61 7 4928 0061",
    "sg:postcode":"4700",
    "sg:province":"QLD",
    "sg:tags":[
        "building",
        "cladding",
        "industrial",
        "commercial"
    ],
    "wof:name":"Queensland Exterior Improvements",
    "wof:placetype":"venue"
},
  "geometry": {"coordinates":[150.51689148,-23.3561306],"type":"Point"}
}