{
  "type": "Feature",
  "properties": {
    "addr:full":"25 Wesley St Bendigo VIC 3550",
    "addr:housenumber":"25",
    "addr:postcode":"3550",
    "addr:street":"Wesley St",
    "iso:country":"AU",
    "sg:address":"25 Wesley St",
    "sg:city":"Bendigo",
    "sg:classifiers":[
        {
            "category":"Building & Trades",
            "subcategory":"Construction",
            "type":"Services"
        }
    ],
    "sg:phone":"+61 3 5447 9535",
    "sg:postcode":"3550",
    "sg:province":"VIC",
    "sg:tags":[
        "contractor"
    ],
    "wof:name":"C J & K L McEwan",
    "wof:placetype":"venue"
},
  "geometry": {"coordinates":[144.23832702600001,-36.8022193909],"type":"Point"}
}