{
  "type": "Feature",
  "properties": {
    "addr:full":"5 Corcet Rd Lockrose QLD 4342",
    "addr:housenumber":"5",
    "addr:postcode":"4342",
    "addr:street":"Corcet Rd",
    "iso:country":"AU",
    "sg:address":"5 Corcet Rd",
    "sg:city":"Lockrose",
    "sg:classifiers":[
        {
            "category":"Farming",
            "subcategory":"Farm",
            "type":"Manufacturing & Wholesale Goods"
        }
    ],
    "sg:phone":"+61 7 5465 8243",
    "sg:postcode":"4342",
    "sg:province":"QLD",
    "sg:tags":[
        "farmer"
    ],
    "wof:name":"Stegemann L J & M L",
    "wof:placetype":"venue"
},
  "geometry": {"coordinates":[152.46405029300001,-27.4928340912],"type":"Point"}
}