{
  "type": "Feature",
  "properties": {
    "iso:country":"AU",
    "sg:address":"136 Main St",
    "sg:city":"Yankalilla",
    "sg:classifiers":[
        {
            "category":"Organizations",
            "subcategory":"Community Association",
            "type":"Services"
        }
    ],
    "sg:phone":"+61 8 8558 2930",
    "sg:postcode":"5203",
    "sg:province":"SA",
    "sg:tags":[
        "organisation",
        "family",
        "welfare"
    ],
    "wof:name":"Meals On Wheels Incorporated",
    "wof:placetype":"venue"
},
  "geometry": {"coordinates":[138.351074219,-35.4582901001],"type":"Point"}
}