{
  "type": "Feature",
  "properties": {
    "addr:full":"11 Arnott St Manjimup WA 6258",
    "addr:housenumber":"11",
    "addr:postcode":"6258",
    "addr:street":"Arnott St",
    "iso:country":"AU",
    "sg:address":"11 Arnott St",
    "sg:city":"Manjimup",
    "sg:classifiers":[
        {
            "category":"Professional",
            "subcategory":"Art Services",
            "type":"Services"
        }
    ],
    "sg:phone":"+61 8 9771 1063",
    "sg:postcode":"6258",
    "sg:province":"WA",
    "sg:tags":[
        "decorator",
        "painter"
    ],
    "wof:name":"James F G",
    "wof:placetype":"venue"
},
  "geometry": {"coordinates":[116.137939453,-34.2402648926],"type":"Point"}
}