{
  "type": "Feature",
  "properties": {
    "iso:country":"AU",
    "sg:address":"4/78 Bundall Rd",
    "sg:city":"Bundall",
    "sg:classifiers":[
        {
            "category":"Shopping",
            "subcategory":"Pets & Pet Supplies",
            "type":"Retail Goods"
        }
    ],
    "sg:phone":"+61 7 5592 5265",
    "sg:postcode":"4217",
    "sg:province":"QLD",
    "sg:tags":[
        "shop",
        "supplier"
    ],
    "wof:name":"Purebred Products Pty Ltd",
    "wof:placetype":"venue"
},
  "geometry": {"coordinates":[153.412597656,-28.0072402954],"type":"Point"}
}