{
  "type": "Feature",
  "properties": {
    "iso:country":"AU",
    "sg:address":"Shed 9 Central Pier, 161 Harbour Esp,",
    "sg:city":"Docklands",
    "sg:classifiers":[
        {
            "category":"Retail",
            "subcategory":"Event Space",
            "type":"Services"
        }
    ],
    "sg:phone":"+61 3 8606 4444",
    "sg:postcode":"3008",
    "sg:province":"VIC",
    "sg:tags":[
        "venue",
        "reception",
        "wedding"
    ],
    "sg:website":"http://www.atlanticgroupv.com.au",
    "wof:name":"Atlantic Group (V)",
    "wof:placetype":"venue"
},
  "geometry": {"coordinates":[144.94331359899999,-37.8166313171],"type":"Point"}
}