{
  "type": "Feature",
  "properties": {
    "addr:full":"5 Eyre St Rivervale WA 6103",
    "addr:housenumber":"5",
    "addr:postcode":"6103",
    "addr:street":"Eyre St",
    "iso:country":"AU",
    "sg:address":"5 Eyre St",
    "sg:city":"Rivervale",
    "sg:classifiers":[
        {
            "category":"Taxi",
            "type":"Transportation"
        }
    ],
    "sg:phone":"+61 8 9478 3088",
    "sg:postcode":"6103",
    "sg:province":"WA",
    "sg:tags":[
        "truck"
    ],
    "wof:name":"Foxnet Taxi Trucks",
    "wof:placetype":"venue"
},
  "geometry": {"coordinates":[115.91940307599999,-31.954328537],"type":"Point"}
}