{
  "type": "Feature",
  "properties": {
    "addr:full":"2/ 229 Gnangara Rd Wangara WA 6065",
    "addr:housenumber":"/ 229",
    "addr:postcode":"6065",
    "addr:street":"Gnangara Rd",
    "iso:country":"AU",
    "sg:address":"2/ 229 Gnangara Rd",
    "sg:city":"Wangara",
    "sg:classifiers":[
        {
            "category":"Building & Trades",
            "subcategory":"Construction",
            "type":"Services"
        }
    ],
    "sg:phone":"+61 8 9303 4433",
    "sg:postcode":"6065",
    "sg:province":"WA",
    "sg:tags":[
        "brick",
        "paving"
    ],
    "wof:name":"Castlestone",
    "wof:placetype":"venue"
},
  "geometry": {"coordinates":[115.84220886200001,-31.8003120422],"type":"Point"}
}