{
  "type": "Feature",
  "properties": {
    "addr:full":"3 Battunga Crt Strathfieldsaye VIC 3551",
    "addr:housenumber":"3",
    "addr:postcode":"3551",
    "addr:street":"Battunga Crt",
    "iso:country":"AU",
    "sg:address":"3 Battunga Crt",
    "sg:city":"Strathfieldsaye",
    "sg:classifiers":[
        {
            "category":"Communications",
            "type":"Services"
        }
    ],
    "sg:phone":"+61 409 452 732",
    "sg:postcode":"3551",
    "sg:province":"VIC",
    "sg:tags":[
        "public",
        "system",
        "address"
    ],
    "wof:name":"Dewars Audio Systems",
    "wof:placetype":"venue"
},
  "geometry": {"coordinates":[144.334594727,-36.800994873],"type":"Point"}
}