{
  "type": "Feature",
  "properties": {
    "addr:full":"Australia II Drv Crawley WA 6009",
    "addr:postcode":"6009",
    "addr:street":"Ii Drv",
    "iso:country":"AU",
    "sg:address":"Australia II Drv",
    "sg:city":"Crawley",
    "sg:classifiers":[
        {
            "category":"Recreation",
            "subcategory":"Sailing Club",
            "type":"Entertainment"
        }
    ],
    "sg:phone":"+61 8 9389 1555",
    "sg:postcode":"6009",
    "sg:province":"WA",
    "sg:tags":[
        "yacht"
    ],
    "wof:name":"Royal Perth Yacht Club Of W.A. (Inc)",
    "wof:placetype":"venue"
},
  "geometry": {"coordinates":[115.82257799999999,-31.985289],"type":"Point"}
}