{
  "type": "Feature",
  "properties": {
    "iso:country":"AU",
    "sg:address":"28 Catalina Rd",
    "sg:city":"Elizabeth",
    "sg:classifiers":[
        {
            "category":"Social Services",
            "subcategory":"Retirement Home",
            "type":"Services"
        }
    ],
    "sg:phone":"+61 8 8256 3050",
    "sg:postcode":"5112",
    "sg:province":"SA",
    "sg:tags":[
        "village"
    ],
    "wof:name":"Dutton Court (Angelicare SA)",
    "wof:placetype":"venue"
},
  "geometry": {"coordinates":[138.67556762699999,-34.7221107483],"type":"Point"}
}