{
  "type": "Feature",
  "properties": {
    "addr:full":"Duke St Jondaryan QLD 4403",
    "addr:postcode":"4403",
    "addr:street":"Duke St",
    "iso:country":"AU",
    "sg:address":"Duke St",
    "sg:city":"Jondaryan",
    "sg:classifiers":[
        {
            "category":"Travel",
            "subcategory":"Hotels & Motels",
            "type":"Entertainment"
        }
    ],
    "sg:phone":"+61 7 4692 2202",
    "sg:postcode":"4403",
    "sg:province":"QLD",
    "wof:name":"Jondaryan Hotel",
    "wof:placetype":"venue"
},
  "geometry": {"coordinates":[151.59388732900001,-27.3693084717],"type":"Point"}
}