{
  "type": "Feature",
  "properties": {
    "addr:full":"10 Johnson St Rutherford NSW 2320",
    "addr:housenumber":"10",
    "addr:postcode":"2320",
    "addr:street":"Johnson St",
    "iso:country":"AU",
    "sg:address":"10 Johnson St",
    "sg:city":"Rutherford",
    "sg:classifiers":[
        {
            "category":"Retail",
            "subcategory":"Auto Repair",
            "type":"Services"
        }
    ],
    "sg:phone":"+61 2 4932 7578",
    "sg:postcode":"2320",
    "sg:province":"NSW",
    "sg:tags":[
        "repairer",
        "motor",
        "engineer"
    ],
    "wof:name":"Cant's Motor Repairs",
    "wof:placetype":"venue"
},
  "geometry": {"coordinates":[151.540405273,-32.7230758667],"type":"Point"}
}