{
  "type": "Feature",
  "properties": {
    "iso:country":"AU",
    "sg:address":"39 Murilla St",
    "sg:city":"Miles",
    "sg:classifiers":[
        {
            "category":"Travel",
            "subcategory":"Hotels & Motels",
            "type":"Entertainment"
        }
    ],
    "sg:phone":"+61 7 4627 1159",
    "sg:postcode":"4415",
    "sg:province":"QLD",
    "sg:tags":[
        "accommodation"
    ],
    "wof:name":"Windsor Hotel",
    "wof:placetype":"venue"
},
  "geometry": {"coordinates":[150.184280395,-26.6590099335],"type":"Point"}
}