{
  "type": "Feature",
  "properties": {
    "addr:full":"209 Oxford St Darlinghurst NSW 2010",
    "addr:housenumber":"209",
    "addr:postcode":"2010",
    "addr:street":"Oxford St",
    "iso:country":"AU",
    "sg:address":"209 Oxford St",
    "sg:city":"Darlinghurst",
    "sg:classifiers":[
        {
            "category":"Restaurant",
            "type":"Food & Drink"
        }
    ],
    "sg:phone":"+61 2 9360 4970",
    "sg:postcode":"2010",
    "sg:province":"NSW",
    "wof:name":"Balkan Continental Restaurant Pty Ltd",
    "wof:placetype":"venue"
},
  "geometry": {"coordinates":[151.21749877900001,-33.8810501099],"type":"Point"}
}