{
  "type": "Feature",
  "properties": {
    "iso:country":"AU",
    "sg:address":"1 Sycamore Ave",
    "sg:city":"Bateau Bay",
    "sg:classifiers":[
        {
            "category":"Education",
            "subcategory":"School",
            "type":"Public Place"
        }
    ],
    "sg:phone":"+61 2 4332 4224",
    "sg:postcode":"2261",
    "sg:province":"NSW",
    "sg:tags":[
        "teaching",
        "aid"
    ],
    "wof:name":"Intensive Reading Programs Pty Ltd",
    "wof:placetype":"venue"
},
  "geometry": {"coordinates":[151.476181,-33.389996],"type":"Point"}
}