{
  "type": "Feature",
  "properties": {
    "iso:country":"AU",
    "sg:address":"21 Feathertail Crt",
    "sg:city":"Tewantin",
    "sg:classifiers":[
        {
            "category":"Building & Trades",
            "subcategory":"Construction",
            "type":"Services"
        }
    ],
    "sg:phone":"+61 409 052 936",
    "sg:postcode":"4565",
    "sg:province":"QLD",
    "sg:tags":[
        "fencing",
        "contractor"
    ],
    "wof:name":"Johnno's Fencing",
    "wof:placetype":"venue"
},
  "geometry": {"coordinates":[153.00517273,-26.3853721619],"type":"Point"}
}