{
  "type": "Feature",
  "properties": {
    "iso:country":"AU",
    "sg:address":"37 Brougham St",
    "sg:city":"Eltham",
    "sg:classifiers":[
        {
            "category":"Personal",
            "subcategory":"Beauty Salon",
            "type":"Services"
        }
    ],
    "sg:phone":"+61 3 9431 2871",
    "sg:postcode":"3095",
    "sg:province":"VIC",
    "sg:tags":[
        "hairdresser"
    ],
    "wof:name":"T.J.' s Hairdressing & Beauty Supplies",
    "wof:placetype":"venue"
},
  "geometry": {"coordinates":[145.140228272,-37.7217979431],"type":"Point"}
}