{
  "type": "Feature",
  "properties": {
    "iso:country":"AU",
    "sg:address":"388-390 Gilbert Rd",
    "sg:city":"Preston",
    "sg:classifiers":[
        {
            "category":"Shopping",
            "subcategory":"Baby Store",
            "type":"Retail Goods"
        }
    ],
    "sg:phone":"+61 3 9471 2761",
    "sg:postcode":"3072",
    "sg:province":"VIC",
    "sg:tags":[
        "children's",
        "wear"
    ],
    "wof:name":"Preston Clothing Factory Outlet",
    "wof:placetype":"venue"
},
  "geometry": {"coordinates":[144.99061584500001,-37.7354316711],"type":"Point"}
}