{
  "type": "Feature",
  "properties": {
    "addr:full":"398 Lonsdale St Melbourne VIC 3000",
    "addr:housenumber":"398",
    "addr:postcode":"3000",
    "addr:street":"Lonsdale St",
    "iso:country":"AU",
    "sg:address":"398 Lonsdale St",
    "sg:city":"Melbourne",
    "sg:classifiers":[
        {
            "category":"Shopping",
            "subcategory":"Computers & Home Electronics",
            "type":"Retail Goods"
        }
    ],
    "sg:phone":"+61 3 9642 4254",
    "sg:postcode":"3000",
    "sg:province":"VIC",
    "sg:tags":[
        "hardware",
        "equipment"
    ],
    "wof:name":"Fast Pace Computers (Melbourne)",
    "wof:placetype":"venue"
},
  "geometry": {"coordinates":[144.96058654800001,-37.8126296997],"type":"Point"}
}