{
  "type": "Feature",
  "properties": {
    "addr:full":"86 High St Mansfield VIC 3722",
    "addr:housenumber":"86",
    "addr:postcode":"3722",
    "addr:street":"High St",
    "iso:country":"AU",
    "sg:address":"86 High St",
    "sg:city":"Mansfield",
    "sg:classifiers":[
        {
            "category":"Travel",
            "subcategory":"Hotels & Motels",
            "type":"Entertainment"
        }
    ],
    "sg:phone":"+61 3 5775 2101",
    "sg:postcode":"3722",
    "sg:province":"VIC",
    "wof:name":"Mansfield Hotel",
    "wof:placetype":"venue"
},
  "geometry": {"coordinates":[146.088653564,-37.0525283813],"type":"Point"}
}