{
  "type": "Feature",
  "properties": {
    "addr:full":"36 Mocatta St Goombungee QLD 4354",
    "addr:housenumber":"36",
    "addr:postcode":"4354",
    "addr:street":"Mocatta St",
    "iso:country":"AU",
    "sg:address":"36 Mocatta St",
    "sg:city":"Goombungee",
    "sg:classifiers":[
        {
            "category":"Building & Trades",
            "subcategory":"Construction",
            "type":"Services"
        }
    ],
    "sg:phone":"+61 428 965 378",
    "sg:postcode":"4354",
    "sg:province":"QLD",
    "sg:tags":[
        "earth",
        "excavating",
        "moving",
        "contractor"
    ],
    "wof:name":"GLEN ROWE",
    "wof:placetype":"venue"
},
  "geometry": {"coordinates":[151.85278299999999,-27.299814],"type":"Point"}
}