{
  "type": "Feature",
  "properties": {
    "addr:full":"239 River St West Kempsey NSW 2440",
    "addr:housenumber":"239",
    "addr:postcode":"2440",
    "addr:street":"River St West",
    "iso:country":"AU",
    "sg:address":"239 River St",
    "sg:city":"West Kempsey",
    "sg:classifiers":[
        {
            "category":"Home & Garden",
            "subcategory":"Carpets & Floor Coverings",
            "type":"Retail Goods"
        }
    ],
    "sg:phone":"+61 2 6562 8252",
    "sg:postcode":"2440",
    "sg:province":"NSW",
    "sg:tags":[
        "wood"
    ],
    "wof:name":"The Green Mill",
    "wof:placetype":"venue"
},
  "geometry": {"coordinates":[152.80256700000001,-31.059366],"type":"Point"}
}