{
  "type": "Feature",
  "properties": {
    "addr:full":"8 Hope St Geelong West VIC 3218",
    "addr:housenumber":"8",
    "addr:postcode":"3218",
    "addr:street":"Hope St",
    "iso:country":"AU",
    "sg:address":"8 Hope St",
    "sg:city":"Geelong West",
    "sg:classifiers":[
        {
            "category":"Health Services",
            "subcategory":"Health Practitioner",
            "type":"Services"
        }
    ],
    "sg:phone":"+61 3 5229 4420",
    "sg:postcode":"3218",
    "sg:province":"VIC",
    "sg:tags":[
        "osteopath"
    ],
    "sg:website":"http://www.geelongosteopath.com",
    "wof:name":"The Osteopath",
    "wof:placetype":"venue"
},
  "geometry": {"coordinates":[144.35244750999999,-38.1424980164],"type":"Point"}
}