{
  "type": "Feature",
  "properties": {
    "addr:full":"1 / 47 Acland St St Kilda VIC 3182",
    "addr:housenumber":"/ 47",
    "addr:postcode":"3182",
    "addr:street":"Acland St",
    "iso:country":"AU",
    "sg:address":"1 / 47 Acland St",
    "sg:city":"St Kilda",
    "sg:classifiers":[
        {
            "category":"Professional",
            "subcategory":"Management & Consulting",
            "type":"Services"
        }
    ],
    "sg:phone":"+61 3 9593 6903",
    "sg:postcode":"3182",
    "sg:province":"VIC",
    "sg:tags":[
        "consultant"
    ],
    "wof:name":"Rocket Science ABC",
    "wof:placetype":"venue"
},
  "geometry": {"coordinates":[144.97491455100001,-37.8631668091],"type":"Point"}
}