{
  "type": "Feature",
  "properties": {
    "addr:full":"9 Inglebrae Crt Essendon VIC 3040",
    "addr:housenumber":"9",
    "addr:postcode":"3040",
    "addr:street":"Inglebrae Crt",
    "iso:country":"AU",
    "sg:address":"9 Inglebrae Crt",
    "sg:city":"Essendon",
    "sg:classifiers":[
        {
            "category":"Building & Trades",
            "subcategory":"Construction",
            "type":"Services"
        }
    ],
    "sg:phone":"+61 418 581 844",
    "sg:postcode":"3040",
    "sg:province":"VIC",
    "sg:tags":[
        "contractor"
    ],
    "wof:name":"Toohey Building Services Pty Ltd",
    "wof:placetype":"venue"
},
  "geometry": {"coordinates":[144.91458129899999,-37.7606315613],"type":"Point"}
}