{
  "type": "Feature",
  "properties": {
    "addr:full":"Suite 5, 85 Silverwater Rd Silverwater NSW 2128",
    "addr:housenumber":"85",
    "addr:postcode":"2128",
    "addr:street":"Silverwater Rd",
    "iso:country":"AU",
    "sg:address":"Suite 5, 85 Silverwater Rd",
    "sg:city":"Silverwater",
    "sg:classifiers":[
        {
            "category":"Real Estate",
            "subcategory":"Real Estate Agent",
            "type":"Services"
        }
    ],
    "sg:phone":"+61 2 9748 4448",
    "sg:postcode":"2128",
    "sg:province":"NSW",
    "wof:name":"L J Hooker",
    "wof:placetype":"venue"
},
  "geometry": {"coordinates":[151.04852294899999,-33.8328590393],"type":"Point"}
}