{
  "type": "Feature",
  "properties": {
    "iso:country":"AU",
    "sg:address":"21 Bennett St",
    "sg:city":"Cremorne",
    "sg:classifiers":[
        {
            "category":"Professional",
            "subcategory":"Art Services",
            "type":"Services"
        }
    ],
    "sg:phone":"+61 2 9909 8742",
    "sg:postcode":"2090",
    "sg:province":"NSW",
    "sg:tags":[
        "decorator",
        "painter"
    ],
    "wof:name":"Valenti M & R",
    "wof:placetype":"venue"
},
  "geometry": {"coordinates":[151.223587036,-33.8345184326],"type":"Point"}
}