{
  "type": "Feature",
  "properties": {
    "iso:country":"AU",
    "sg:address":"\"Wonganong\" Watson Rd",
    "sg:city":"Tongala",
    "sg:classifiers":[
        {
            "category":"Farming",
            "subcategory":"Farm",
            "type":"Manufacturing & Wholesale Goods"
        }
    ],
    "sg:phone":"+61 3 5859 6255",
    "sg:postcode":"3621",
    "sg:province":"VIC",
    "sg:tags":[
        "farmer"
    ],
    "wof:name":"Osment R S",
    "wof:placetype":"venue"
},
  "geometry": {"coordinates":[144.93122863799999,-36.2984733582],"type":"Point"}
}