{
  "type": "Feature",
  "properties": {
    "iso:country":"AU",
    "sg:address":"Shop 2, 52 Lewis St",
    "sg:city":"Mudgee",
    "sg:classifiers":[
        {
            "category":"Health Services",
            "subcategory":"Doctor",
            "type":"Services"
        }
    ],
    "sg:phone":"+61 2 6372 2872",
    "sg:postcode":"2850",
    "sg:province":"NSW",
    "sg:tags":[
        "reflexology"
    ],
    "wof:name":"Lloma Taylor",
    "wof:placetype":"venue"
},
  "geometry": {"coordinates":[149.589752,-32.597328],"type":"Point"}
}