{
  "type": "Feature",
  "properties": {
    "addr:full":"Shop 221, Epping Plaza, Cnr High & Cooper Sts Epping VIC 3076",
    "addr:housenumber":"221",
    "addr:postcode":"3076",
    "addr:street":"Epping Plaza Cnr High",
    "iso:country":"AU",
    "sg:address":"Shop 221, Epping Plaza, Cnr High & Cooper Sts",
    "sg:city":"Epping",
    "sg:classifiers":[
        {
            "category":"Travel",
            "subcategory":"Travel Agent",
            "type":"Entertainment"
        }
    ],
    "sg:phone":"+61 3 9408 7688",
    "sg:postcode":"3076",
    "sg:province":"VIC",
    "sg:tags":[
        "consultant"
    ],
    "wof:name":"Harvey World Travel",
    "wof:placetype":"venue"
},
  "geometry": {"coordinates":[145.009490967,-37.6383590698],"type":"Point"}
}