{
  "type": "Feature",
  "properties": {
    "addr:full":"3/ 116 Kurraba Rd Neutral Bay NSW 2089",
    "addr:housenumber":"/ 116",
    "addr:postcode":"2089",
    "addr:street":"Kurraba Rd",
    "iso:country":"AU",
    "sg:address":"3/ 116 Kurraba Rd",
    "sg:city":"Neutral Bay",
    "sg:classifiers":[
        {
            "category":"Real Estate",
            "subcategory":"Architect",
            "type":"Services"
        }
    ],
    "sg:phone":"+61 412 533 422",
    "sg:postcode":"2089",
    "sg:province":"NSW",
    "wof:name":"Lahoud Joseph & Associates",
    "wof:placetype":"venue"
},
  "geometry": {"coordinates":[151.22076415999999,-33.8400688171],"type":"Point"}
}