{
  "type": "Feature",
  "properties": {
    "addr:full":"57- 59 Fryers St Shepparton VIC 3630",
    "addr:housenumber":"59",
    "addr:postcode":"3630",
    "addr:street":"Fryers St",
    "iso:country":"AU",
    "sg:address":"57- 59 Fryers St",
    "sg:city":"Shepparton",
    "sg:classifiers":[
        {
            "category":"Shopping",
            "subcategory":"Crafts & Fabrics",
            "type":"Retail Goods"
        }
    ],
    "sg:phone":"+61 3 5822 1524",
    "sg:postcode":"3630",
    "sg:province":"VIC",
    "sg:tags":[
        "synthetic",
        "canvas",
        "product"
    ],
    "wof:name":"Aussie Disposals",
    "wof:placetype":"venue"
},
  "geometry": {"coordinates":[145.40045165999999,-36.3789176941],"type":"Point"}
}