{
  "type": "Feature",
  "properties": {
    "iso:country":"AU",
    "sg:address":"44 Currumbin Creek Rd",
    "sg:city":"Currumbin",
    "sg:classifiers":[
        {
            "category":"Manufacturing",
            "subcategory":"Metals",
            "type":"Manufacturing & Wholesale Goods"
        }
    ],
    "sg:phone":"+61 7 5598 1866",
    "sg:postcode":"4223",
    "sg:province":"QLD",
    "sg:tags":[
        "steel",
        "fabricator",
        "mfrs"
    ],
    "wof:name":"Sirco Engineering",
    "wof:placetype":"venue"
},
  "geometry": {"coordinates":[153.47271728499999,-28.143327713],"type":"Point"}
}