{
  "type": "Feature",
  "properties": {
    "iso:country":"AU",
    "sg:address":"1 Sadie St",
    "sg:city":"Mt Waverley",
    "sg:classifiers":[
        {
            "category":"Education",
            "subcategory":"Kindergarten",
            "type":"Public Place"
        }
    ],
    "sg:phone":"+61 3 9807 5250",
    "sg:postcode":"3149",
    "sg:province":"VIC",
    "sg:tags":[
        "pre-schools"
    ],
    "wof:name":"Nara Pre-School Centre",
    "wof:placetype":"venue"
},
  "geometry": {"coordinates":[145.117385864,-37.8897285461],"type":"Point"}
}