{
  "type": "Feature",
  "properties": {
    "addr:full":"11 Verrell St Wetherill Park NSW 2164",
    "addr:housenumber":"11",
    "addr:postcode":"2164",
    "addr:street":"Verrell St",
    "iso:country":"AU",
    "sg:address":"11 Verrell St",
    "sg:city":"Wetherill Park",
    "sg:classifiers":[
        {
            "category":"Manufacturing",
            "subcategory":"Motor Vehicles & Parts",
            "type":"Manufacturing & Wholesale Goods"
        }
    ],
    "sg:phone":"+61 2 9609 4633",
    "sg:postcode":"2164",
    "sg:province":"NSW",
    "sg:tags":[
        "wholesaler",
        "cycle",
        "mfrs",
        "accessory"
    ],
    "wof:name":"Eurotred (Aust) Pty Ltd",
    "wof:placetype":"venue"
},
  "geometry": {"coordinates":[150.92202758799999,-33.8438682556],"type":"Point"}
}