{
  "type": "Feature",
  "properties": {
    "iso:country":"AU",
    "sg:address":"26 Silver St",
    "sg:city":"St Peters",
    "sg:classifiers":[
        {
            "category":"Professional",
            "subcategory":"Lawyer & Legal Services",
            "type":"Services"
        }
    ],
    "sg:phone":"+61 2 9517 1988",
    "sg:postcode":"2044",
    "sg:province":"NSW",
    "sg:tags":[
        "wills",
        "probate",
        "estate"
    ],
    "wof:name":"Tony Valentine & Co",
    "wof:placetype":"venue"
},
  "geometry": {"coordinates":[151.175537,-33.913921],"type":"Point"}
}