{
  "type": "Feature",
  "properties": {
    "addr:full":"23 Kanimbla Rd Nedlands WA 6009",
    "addr:housenumber":"23",
    "addr:postcode":"6009",
    "addr:street":"Kanimbla Rd",
    "iso:country":"AU",
    "sg:address":"23 Kanimbla Rd",
    "sg:city":"Nedlands",
    "sg:classifiers":[
        {
            "category":"Arts & Performance",
            "subcategory":"Music",
            "type":"Entertainment"
        }
    ],
    "sg:phone":"+61 408 812 221",
    "sg:postcode":"6009",
    "sg:province":"WA",
    "sg:tags":[
        "mobile",
        "jockey",
        "disc"
    ],
    "wof:name":"Jol DJ",
    "wof:placetype":"venue"
},
  "geometry": {"coordinates":[115.81545300000001,-31.972603],"type":"Point"}
}