{
  "type": "Feature",
  "properties": {
    "addr:full":"GPO Box 1772 Brisbane QLD 4001",
    "addr:postcode":"4001",
    "iso:country":"AU",
    "sg:address":"GPO Box 1772",
    "sg:city":"Brisbane",
    "sg:classifiers":[
        {
            "category":"Food & Beverages",
            "subcategory":"Specialty",
            "type":"Retail Goods"
        }
    ],
    "sg:phone":"+61 7 3824 1465",
    "sg:postcode":"4001",
    "sg:province":"QLD",
    "sg:tags":[
        "product",
        "health"
    ],
    "wof:name":"Hawes Michael",
    "wof:placetype":"venue"
},
  "geometry": {"coordinates":[152.88902282699999,-27.5977077484],"type":"Point"}
}