{
  "type": "Feature",
  "properties": {
    "addr:full":"Lot 3 South Western Hwy North Dandalup WA 6207",
    "addr:postcode":"6207",
    "addr:street":"South Western Hwy North",
    "iso:country":"AU",
    "sg:address":"Lot 3 South Western Hwy",
    "sg:city":"North Dandalup",
    "sg:classifiers":[
        {
            "category":"Autos & Motor Vehicles",
            "subcategory":"Fuel & Gas Station",
            "type":"Retail Goods"
        }
    ],
    "sg:phone":"+61 8 9530 1245",
    "sg:postcode":"6207",
    "sg:province":"WA",
    "wof:name":"Floopers North Dandelup",
    "wof:placetype":"venue"
},
  "geometry": {"coordinates":[115.980118,-32.475849],"type":"Point"}
}