{
  "type": "Feature",
  "properties": {
    "addr:full":"Kingsbury Drv Bundoora VIC 3083",
    "addr:postcode":"3083",
    "addr:street":"Kingsbury Drv",
    "iso:country":"AU",
    "sg:address":"Kingsbury Drv",
    "sg:city":"Bundoora",
    "sg:classifiers":[
        {
            "category":"Banks & Credit Unions",
            "subcategory":"Bank",
            "type":"Services"
        }
    ],
    "sg:phone":"+61 3 9478 8222",
    "sg:postcode":"3083",
    "sg:province":"VIC",
    "sg:tags":[
        "society"
    ],
    "sg:website":"http://www.latrobeunicredit.com.au",
    "wof:name":"La Trobe University Credit Union",
    "wof:placetype":"venue"
},
  "geometry": {"coordinates":[145.043991089,-37.7175216675],"type":"Point"}
}