{
  "type": "Feature",
  "properties": {
    "addr:full":"23 George St Woodford QLD 4514",
    "addr:housenumber":"23",
    "addr:postcode":"4514",
    "addr:street":"George St",
    "iso:country":"AU",
    "sg:address":"23 George St",
    "sg:city":"Woodford",
    "sg:classifiers":[
        {
            "category":"Building & Trades",
            "subcategory":"Construction",
            "type":"Services"
        }
    ],
    "sg:phone":"+61 7 5496 1421",
    "sg:postcode":"4514",
    "sg:province":"QLD",
    "sg:tags":[
        "fencing",
        "contractor"
    ],
    "wof:name":"Allan Draper",
    "wof:placetype":"venue"
},
  "geometry": {"coordinates":[152.78126499999999,-26.952848],"type":"Point"}
}