{
  "type": "Feature",
  "properties": {
    "addr:full":"Pacific Hwy Somersby NSW 2250",
    "addr:postcode":"2250",
    "addr:street":"Pacific Hwy",
    "iso:country":"AU",
    "sg:address":"Pacific Hwy",
    "sg:city":"Somersby",
    "sg:classifiers":[
        {
            "category":"Park",
            "subcategory":"County",
            "type":"Public Place"
        }
    ],
    "sg:phone":"+61 2 4340 1022",
    "sg:postcode":"2250",
    "sg:province":"NSW",
    "sg:tags":[
        "sanctuary",
        "zoos",
        "animal"
    ],
    "wof:name":"Australian Reptile Park",
    "wof:placetype":"venue"
},
  "geometry": {"coordinates":[151.28558349599999,-33.4196586609],"type":"Point"}
}