{
  "type": "Feature",
  "properties": {
    "addr:full":"2967 Murray Valley Hwy Ebden VIC 3691",
    "addr:housenumber":"2967",
    "addr:postcode":"3691",
    "addr:street":"Murray Valley Hwy",
    "iso:country":"AU",
    "sg:address":"2967 Murray Valley Hwy",
    "sg:city":"Ebden",
    "sg:classifiers":[
        {
            "category":"Professional",
            "subcategory":"Computer Services",
            "type":"Services"
        }
    ],
    "sg:phone":"+61 2 6020 6567",
    "sg:postcode":"3691",
    "sg:province":"VIC",
    "sg:tags":[
        "consultant",
        "system"
    ],
    "wof:name":"Blue Digital",
    "wof:placetype":"venue"
},
  "geometry": {"coordinates":[147.00787399999999,-36.141495],"type":"Point"}
}