{
  "type": "Feature",
  "properties": {
    "addr:full":"11 Musgrave Rd Indooroopilly QLD 4068",
    "addr:housenumber":"11",
    "addr:postcode":"4068",
    "addr:street":"Musgrave Rd",
    "iso:country":"AU",
    "sg:address":"11 Musgrave Rd",
    "sg:city":"Indooroopilly",
    "sg:classifiers":[
        {
            "category":"Shopping",
            "subcategory":"Clothing, Apparel, & Fashions",
            "type":"Retail Goods"
        }
    ],
    "sg:phone":"+61 7 3378 2399",
    "sg:postcode":"4068",
    "sg:province":"QLD",
    "sg:tags":[
        "boutique"
    ],
    "wof:name":"Mombasa Clothing Store",
    "wof:placetype":"venue"
},
  "geometry": {"coordinates":[152.972000122,-27.498260498],"type":"Point"}
}