{
  "type": "Feature",
  "properties": {
    "iso:country":"AU",
    "sg:address":"33 Castle Hill St",
    "sg:city":"Holland Park",
    "sg:classifiers":[
        {
            "category":"Social Services",
            "subcategory":"Retirement Home",
            "type":"Services"
        }
    ],
    "sg:phone":"+61 7 3849 4466",
    "sg:postcode":"4121",
    "sg:province":"QLD",
    "sg:tags":[
        "environmental",
        "consultant",
        "pollution"
    ],
    "wof:name":"Ison Environmental Planners",
    "wof:placetype":"venue"
},
  "geometry": {"coordinates":[153.067703247,-27.5277748108],"type":"Point"}
}