{
  "type": "Feature",
  "properties": {
    "addr:full":"10/ 139 Murray St Perth WA 6000",
    "addr:housenumber":"10 / 139",
    "addr:postcode":"6000",
    "addr:street":"Murray St",
    "iso:country":"AU",
    "sg:address":"10/ 139 Murray St",
    "sg:city":"Perth",
    "sg:classifiers":[
        {
            "category":"Autos & Motor Vehicles",
            "subcategory":"Auto Supplies",
            "type":"Retail Goods"
        }
    ],
    "sg:phone":"+61 413 422 010",
    "sg:postcode":"6000",
    "sg:province":"WA",
    "sg:tags":[
        "accessory"
    ],
    "wof:name":"Aspec Auto Accessories",
    "wof:placetype":"venue"
},
  "geometry": {"coordinates":[115.854530334,-31.951593399],"type":"Point"}
}