{
  "type": "Feature",
  "properties": {
    "iso:country":"AU",
    "sg:address":"U 5/12- 18 Victoria St East",
    "sg:city":"Lidcombe",
    "sg:classifiers":[
        {
            "category":"Health Services",
            "subcategory":"Optometrist",
            "type":"Services"
        }
    ],
    "sg:phone":"+61 1800 224 081",
    "sg:postcode":"2141",
    "sg:province":"NSW",
    "wof:name":"Elite Optical",
    "wof:placetype":"venue"
},
  "geometry": {"coordinates":[151.04551696799999,-33.8689689636],"type":"Point"}
}