{
  "type": "Feature",
  "properties": {
    "addr:full":"485 Warrandyte Rd Langwarrin South VIC 3911",
    "addr:housenumber":"485",
    "addr:postcode":"3911",
    "addr:street":"Warrandyte Rd",
    "iso:country":"AU",
    "sg:address":"485 Warrandyte Rd",
    "sg:city":"Langwarrin South",
    "sg:classifiers":[
        {
            "category":"Building & Trades",
            "subcategory":"Landscaping Services",
            "type":"Services"
        }
    ],
    "sg:phone":"+61 407 689 150",
    "sg:postcode":"3911",
    "sg:province":"VIC",
    "sg:tags":[
        "stump",
        "tree",
        "felling",
        "removal"
    ],
    "wof:name":"BCL Tree Stump Removal",
    "wof:placetype":"venue"
},
  "geometry": {"coordinates":[145.182495117,-38.1948471069],"type":"Point"}
}