{
  "type": "Feature",
  "properties": {
    "addr:full":"216 Liverpool St Hobart TAS 7000",
    "addr:housenumber":"216",
    "addr:postcode":"7000",
    "addr:street":"Liverpool St",
    "iso:country":"AU",
    "sg:address":"216 Liverpool St",
    "sg:city":"Hobart",
    "sg:classifiers":[
        {
            "category":"Shopping",
            "subcategory":"Stationery & Office Supplies",
            "type":"Retail Goods"
        }
    ],
    "sg:phone":"+61 3 6231 1831",
    "sg:postcode":"7000",
    "sg:province":"TAS",
    "wof:name":"Tecnomics",
    "wof:placetype":"venue"
},
  "geometry": {"coordinates":[147.323364258,-42.8849906921],"type":"Point"}
}