{
  "type": "Feature",
  "properties": {
    "addr:full":"shop 1/ 63 Albert St Taree NSW 2430",
    "addr:housenumber":"shop 1 / 63",
    "addr:postcode":"2430",
    "addr:street":"Albert St",
    "iso:country":"AU",
    "sg:address":"shop 1/ 63 Albert St",
    "sg:city":"Taree",
    "sg:classifiers":[
        {
            "category":"Personal",
            "subcategory":"Skin Care",
            "type":"Services"
        }
    ],
    "sg:phone":"+61 2 6550 1733",
    "sg:postcode":"2430",
    "sg:province":"NSW",
    "sg:tags":[
        "treatment"
    ],
    "wof:name":"Molescan",
    "wof:placetype":"venue"
},
  "geometry": {"coordinates":[152.46148700000001,-31.910782],"type":"Point"}
}