{
  "type": "Feature",
  "properties": {
    "addr:full":"1a Robert St Atherton QLD 4883",
    "addr:housenumber":"1a",
    "addr:postcode":"4883",
    "addr:street":"Robert St",
    "iso:country":"AU",
    "sg:address":"1a Robert St",
    "sg:city":"Atherton",
    "sg:classifiers":[
        {
            "category":"Professional",
            "subcategory":"Computer Services",
            "type":"Services"
        }
    ],
    "sg:phone":"+61 7 4091 7732",
    "sg:postcode":"4883",
    "sg:province":"QLD",
    "sg:tags":[
        "repairs",
        "upgrade",
        "equipment"
    ],
    "wof:name":"Pc-Protect",
    "wof:placetype":"venue"
},
  "geometry": {"coordinates":[145.47535705600001,-17.2685604095],"type":"Point"}
}