{
  "type": "Feature",
  "properties": {
    "addr:full":"5 White St Jannali NSW 2226",
    "addr:housenumber":"5",
    "addr:postcode":"2226",
    "addr:street":"White St",
    "iso:country":"AU",
    "sg:address":"5 White St",
    "sg:city":"Jannali",
    "sg:classifiers":[
        {
            "category":"Health Services",
            "subcategory":"Doctor",
            "type":"Services"
        }
    ],
    "sg:phone":"+61 2 9528 5266",
    "sg:postcode":"2226",
    "sg:province":"NSW",
    "sg:tags":[
        "medical",
        "practitioner"
    ],
    "wof:name":"Patterson M",
    "wof:placetype":"venue"
},
  "geometry": {"coordinates":[151.066009522,-34.0170555115],"type":"Point"}
}