{
  "type": "Feature",
  "properties": {
    "addr:full":"63 Glen Harrow Heights Rd Belgrave VIC 3160",
    "addr:housenumber":"63",
    "addr:postcode":"3160",
    "addr:street":"Glen Harrow Heights Rd",
    "iso:country":"AU",
    "sg:address":"63 Glen Harrow Heights Rd",
    "sg:city":"Belgrave",
    "sg:classifiers":[
        {
            "category":"Professional",
            "subcategory":"Art Services",
            "type":"Services"
        }
    ],
    "sg:phone":"+61 3 9754 4744",
    "sg:postcode":"3160",
    "sg:province":"VIC",
    "sg:tags":[
        "graphic",
        "designer"
    ],
    "wof:name":"Insight Graphics",
    "wof:placetype":"venue"
},
  "geometry": {"coordinates":[145.361694336,-37.9044303894],"type":"Point"}
}