{
  "type": "Feature",
  "properties": {
    "iso:country":"AU",
    "sg:address":"U1/ 4 Kalamunda Rd",
    "sg:city":"South Guildford",
    "sg:classifiers":[
        {
            "category":"Manufacturing",
            "subcategory":"Tools & Machinery",
            "type":"Manufacturing & Wholesale Goods"
        }
    ],
    "sg:phone":"+61 8 9379 0616",
    "sg:postcode":"6055",
    "sg:province":"WA",
    "sg:tags":[
        "earth",
        "excavating",
        "moving",
        "equipment"
    ],
    "wof:name":"WA Machinery Glass",
    "wof:placetype":"venue"
},
  "geometry": {"coordinates":[115.971672,-31.91398],"type":"Point"}
}