{
  "type": "Feature",
  "properties": {
    "addr:full":"20 Wing St Wingfield SA 5013",
    "addr:housenumber":"20",
    "addr:postcode":"5013",
    "addr:street":"Wing St",
    "iso:country":"AU",
    "sg:address":"20 Wing St",
    "sg:city":"Wingfield",
    "sg:classifiers":[
        {
            "category":"Professional",
            "subcategory":"Engineering",
            "type":"Services"
        }
    ],
    "sg:phone":"+61 8 8268 8884",
    "sg:postcode":"5013",
    "sg:province":"SA",
    "sg:tags":[
        "engineer"
    ],
    "wof:name":"J.N. Engineering Pty Ltd",
    "wof:placetype":"venue"
},
  "geometry": {"coordinates":[138.558883667,-34.8366355896],"type":"Point"}
}