{
  "type": "Feature",
  "properties": {
    "addr:full":"11 Gambier Ave Sandy Point NSW 2171",
    "addr:housenumber":"11",
    "addr:postcode":"2171",
    "addr:street":"Gambier Ave",
    "iso:country":"AU",
    "sg:address":"11 Gambier Ave",
    "sg:city":"Sandy Point",
    "sg:classifiers":[
        {
            "category":"Structure",
            "subcategory":"Office Building",
            "type":"Public Place"
        }
    ],
    "sg:phone":"+61 2 9773 7440",
    "sg:postcode":"2171",
    "sg:province":"NSW",
    "sg:tags":[
        "tie",
        "concrete",
        "formwork",
        "form",
        "accessory"
    ],
    "wof:name":"Italform Pty Ltd",
    "wof:placetype":"venue"
},
  "geometry": {"coordinates":[150.99250793499999,-33.9742393494],"type":"Point"}
}