{
  "type": "Feature",
  "properties": {
    "iso:country":"AU",
    "sg:address":"7 Dowell Crt",
    "sg:city":"Dandenong North",
    "sg:classifiers":[
        {
            "category":"Insurance",
            "subcategory":"Hazard Insurance",
            "type":"Services"
        }
    ],
    "sg:phone":"+61 3 9790 1888",
    "sg:postcode":"3175",
    "sg:province":"VIC",
    "sg:tags":[
        "loss",
        "adjuster",
        "assessor"
    ],
    "wof:name":"Australasian Associated Assessors",
    "wof:placetype":"venue"
},
  "geometry": {"coordinates":[145.22059631400001,-37.9558143616],"type":"Point"}
}