{
  "type": "Feature",
  "properties": {
    "addr:full":"342 Elizabeth St Surry Hills NSW 2010",
    "addr:housenumber":"342",
    "addr:postcode":"2010",
    "addr:street":"Elizabeth St",
    "iso:country":"AU",
    "sg:address":"342 Elizabeth St",
    "sg:city":"Surry Hills",
    "sg:classifiers":[
        {
            "category":"Professional",
            "subcategory":"Detective & Security Services",
            "type":"Services"
        }
    ],
    "sg:phone":"+61 2 9211 4361",
    "sg:postcode":"2010",
    "sg:province":"NSW",
    "sg:tags":[
        "wholesaler",
        "button",
        "mfrs",
        "buckle"
    ],
    "wof:name":"Betty's Belts Manufacturing",
    "wof:placetype":"venue"
},
  "geometry": {"coordinates":[151.20831298799999,-33.8845901489],"type":"Point"}
}