{
  "type": "Feature",
  "properties": {
    "iso:country":"AU",
    "sg:address":"12 Anzac Ave",
    "sg:city":"Seymour",
    "sg:classifiers":[
        {
            "category":"Health Services",
            "subcategory":"Chiropractor",
            "type":"Services"
        }
    ],
    "sg:phone":"+61 3 5792 1248",
    "sg:postcode":"3660",
    "sg:province":"VIC",
    "wof:name":"Seymour Chiropractic Clinic",
    "wof:placetype":"venue"
},
  "geometry": {"coordinates":[145.136886597,-37.026260376],"type":"Point"}
}