{
  "type": "Feature",
  "properties": {
    "addr:full":"Shp1/ 18 Deepwater Rd Castle Cove NSW 2069",
    "addr:housenumber":"18",
    "addr:postcode":"2069",
    "addr:street":"Deepwater Rd",
    "iso:country":"AU",
    "sg:address":"Shp1/ 18 Deepwater Rd",
    "sg:city":"Castle Cove",
    "sg:classifiers":[
        {
            "category":"Personal",
            "subcategory":"Beauty Salon",
            "type":"Services"
        }
    ],
    "sg:phone":"+61 2 9417 7744",
    "sg:postcode":"2069",
    "sg:province":"NSW",
    "wof:name":"In Style Beauty Room",
    "wof:placetype":"venue"
},
  "geometry": {"coordinates":[151.200042725,-33.7824325562],"type":"Point"}
}