{
  "type": "Feature",
  "properties": {
    "addr:full":"138 Gipps Rd Smithfield NSW 2164",
    "addr:housenumber":"138",
    "addr:postcode":"2164",
    "addr:street":"Gipps Rd",
    "iso:country":"AU",
    "sg:address":"138 Gipps Rd",
    "sg:city":"Smithfield",
    "sg:classifiers":[
        {
            "category":"Wholesale",
            "subcategory":"Machinery & Supplies",
            "type":"Manufacturing & Wholesale Goods"
        }
    ],
    "sg:phone":"+61 2 9604 4996",
    "sg:postcode":"2164",
    "sg:province":"NSW",
    "sg:tags":[
        "machine",
        "tool",
        "engineer"
    ],
    "wof:name":"Superior Saws Pty Ltd",
    "wof:placetype":"venue"
},
  "geometry": {"coordinates":[150.92715454099999,-33.8400001526],"type":"Point"}
}