{
  "type": "Feature",
  "properties": {
    "addr:full":"Shop 2/ 27 Belmore Rd Lorn NSW 2320",
    "addr:housenumber":"shop 2 / 27",
    "addr:postcode":"2320",
    "addr:street":"Belmore Rd",
    "iso:country":"AU",
    "sg:address":"Shop 2/ 27 Belmore Rd",
    "sg:city":"Lorn",
    "sg:classifiers":[
        {
            "category":"Food & Beverages",
            "subcategory":"Bakery",
            "type":"Retail Goods"
        }
    ],
    "sg:phone":"+61 2 4933 1201",
    "sg:postcode":"2320",
    "sg:province":"NSW",
    "sg:tags":[
        "cake",
        "shop",
        "pastry"
    ],
    "wof:name":"Lorn Bakery",
    "wof:placetype":"venue"
},
  "geometry": {"coordinates":[151.55995178200001,-32.7270507812],"type":"Point"}
}