{
  "type": "Feature",
  "properties": {
    "addr:full":"288a Glenrock Pde Tascott NSW 2250",
    "addr:housenumber":"288a",
    "addr:postcode":"2250",
    "addr:street":"Glenrock Pde",
    "iso:country":"AU",
    "sg:address":"288a Glenrock Pde",
    "sg:city":"Tascott",
    "sg:classifiers":[
        {
            "category":"Building & Trades",
            "subcategory":"Construction",
            "type":"Services"
        }
    ],
    "sg:phone":"+61 2 4323 2580",
    "sg:postcode":"2250",
    "sg:province":"NSW",
    "sg:tags":[
        "concrete",
        "contractor"
    ],
    "wof:name":"Bob & Amelia Stillaway",
    "wof:placetype":"venue"
},
  "geometry": {"coordinates":[151.313690186,-33.4573364258],"type":"Point"}
}