{
  "type": "Feature",
  "properties": {
    "addr:full":"PO Box 629 Potts Point NSW 2011",
    "addr:postcode":"2011",
    "iso:country":"AU",
    "sg:address":"PO Box 629",
    "sg:city":"Potts Point",
    "sg:classifiers":[
        {
            "category":"Real Estate",
            "subcategory":"Real Estate Agent",
            "type":"Services"
        }
    ],
    "sg:phone":"+61 2 9358 4255",
    "sg:postcode":"2011",
    "sg:province":"NSW",
    "wof:name":"Eastern Network Realty",
    "wof:placetype":"venue"
},
  "geometry": {"coordinates":[151.222854614,-33.8715896606],"type":"Point"}
}