{
  "type": "Feature",
  "properties": {
    "iso:country":"AU",
    "sg:address":"39 Bentley St",
    "sg:city":"Wetherill Park",
    "sg:classifiers":[
        {
            "category":"Manufacturing",
            "subcategory":"Tools & Machinery",
            "type":"Manufacturing & Wholesale Goods"
        }
    ],
    "sg:phone":"+61 2 9756 5333",
    "sg:postcode":"2164",
    "sg:province":"NSW",
    "sg:tags":[
        "fastener",
        "industrial"
    ],
    "wof:name":"Blitz Fasteners",
    "wof:placetype":"venue"
},
  "geometry": {"coordinates":[150.88381957999999,-33.8445739746],"type":"Point"}
}