{
  "type": "Feature",
  "properties": {
    "addr:full":"31 Recreation Drv Eaton WA 6232",
    "addr:housenumber":"31",
    "addr:postcode":"6232",
    "addr:street":"Recreation Drv",
    "iso:country":"AU",
    "sg:address":"31 Recreation Drv",
    "sg:city":"Eaton",
    "sg:classifiers":[
        {
            "category":"Retail",
            "subcategory":"Repair Shop",
            "type":"Services"
        }
    ],
    "sg:phone":"+61 418 931 123",
    "sg:postcode":"6232",
    "sg:province":"WA",
    "sg:tags":[
        "machine",
        "repairs",
        "part",
        "dryer",
        "washing"
    ],
    "wof:name":"Shane's Gas & Electrical Services",
    "wof:placetype":"venue"
},
  "geometry": {"coordinates":[115.72189299999999,-33.319767],"type":"Point"}
}