{
  "type": "Feature",
  "properties": {
    "addr:full":"Doyles Rd Shepparton VIC 3630",
    "addr:postcode":"3630",
    "addr:street":"Doyles Rd",
    "iso:country":"AU",
    "sg:address":"Doyles Rd",
    "sg:city":"Shepparton",
    "sg:classifiers":[
        {
            "category":"Commercial Area",
            "type":"Public Place"
        }
    ],
    "sg:phone":"+61 407 575 961",
    "sg:postcode":"3630",
    "sg:province":"VIC",
    "sg:tags":[
        "heavy",
        "carrier"
    ],
    "wof:name":"D & D Roadtrans",
    "wof:placetype":"venue"
},
  "geometry": {"coordinates":[145.43179321299999,-36.4350242615],"type":"Point"}
}