{
  "type": "Feature",
  "properties": {
    "addr:full":"Unit 11/ 30 Erindale Rd Balcatta WA 6021",
    "addr:housenumber":"/ 30",
    "addr:postcode":"6021",
    "addr:street":"Erindale Rd",
    "iso:country":"AU",
    "sg:address":"Unit 11/ 30 Erindale Rd",
    "sg:city":"Balcatta",
    "sg:classifiers":[
        {
            "category":"Home & Garden",
            "subcategory":"Carpets & Floor Coverings",
            "type":"Retail Goods"
        }
    ],
    "sg:phone":"+61 8 9240 4888",
    "sg:postcode":"6021",
    "sg:province":"WA",
    "sg:tags":[
        "tile",
        "wall"
    ],
    "wof:name":"Stamford Ceramics",
    "wof:placetype":"venue"
},
  "geometry": {"coordinates":[115.803497315,-31.8671760559],"type":"Point"}
}