{
  "type": "Feature",
  "properties": {
    "iso:country":"AU",
    "sg:address":"Ritchie St",
    "sg:city":"Waratah",
    "sg:classifiers":[
        {
            "category":"Education",
            "subcategory":"School",
            "type":"Public Place"
        }
    ],
    "sg:phone":"+61 3 6439 1208",
    "sg:postcode":"7321",
    "sg:province":"TAS",
    "sg:tags":[
        "state",
        "except",
        "nsw"
    ],
    "wof:name":"Waratah Primary",
    "wof:placetype":"venue"
},
  "geometry": {"coordinates":[145.525208,-41.444664],"type":"Point"}
}