{
  "type": "Feature",
  "properties": {
    "addr:full":"65 Chapman Ave Beecroft NSW 2119",
    "addr:housenumber":"65",
    "addr:postcode":"2119",
    "addr:street":"Chapman Ave",
    "iso:country":"AU",
    "sg:address":"65 Chapman Ave",
    "sg:city":"Beecroft",
    "sg:classifiers":[
        {
            "category":"Professional",
            "subcategory":"Management & Consulting",
            "type":"Services"
        }
    ],
    "sg:phone":"+61 2 9484 8740",
    "sg:postcode":"2119",
    "sg:province":"NSW",
    "sg:tags":[
        "consultant"
    ],
    "wof:name":"Pulse Consultants Pty Ltd",
    "wof:placetype":"venue"
},
  "geometry": {"coordinates":[151.056243897,-33.7491340637],"type":"Point"}
}