{
  "type": "Feature",
  "properties": {
    "iso:country":"AU",
    "sg:address":"54 Dragon St",
    "sg:city":"Warwick",
    "sg:classifiers":[
        {
            "category":"Education",
            "subcategory":"Kindergarten",
            "type":"Public Place"
        }
    ],
    "sg:phone":"+61 7 4661 2138",
    "sg:postcode":"4370",
    "sg:province":"QLD",
    "sg:tags":[
        "pre-schools"
    ],
    "wof:name":"Warwick Community Kindergarten",
    "wof:placetype":"venue"
},
  "geometry": {"coordinates":[152.027740478,-28.2173690796],"type":"Point"}
}