{
  "type": "Feature",
  "properties": {
    "addr:full":"RSD Kentish Rd One Tree Hill SA 5114",
    "addr:postcode":"5114",
    "addr:street":"Kentish Rd One",
    "iso:country":"AU",
    "sg:address":"RSD Kentish Rd",
    "sg:city":"One Tree Hill",
    "sg:classifiers":[
        {
            "category":"Home & Garden",
            "subcategory":"Building Materials",
            "type":"Retail Goods"
        }
    ],
    "sg:phone":"+61 8 8239 8466",
    "sg:postcode":"5114",
    "sg:province":"SA",
    "sg:tags":[
        "lawn",
        "cutting",
        "maintenance"
    ],
    "wof:name":"Andrew Spurling",
    "wof:placetype":"venue"
},
  "geometry": {"coordinates":[138.69032287600001,-34.7053375244],"type":"Point"}
}