{
  "type": "Feature",
  "properties": {
    "iso:country":"AU",
    "sg:address":"127 Galah St",
    "sg:city":"Longreach",
    "sg:classifiers":[
        {
            "category":"Professional",
            "subcategory":"Computer Services",
            "type":"Services"
        }
    ],
    "sg:phone":"+61 7 4658 3937",
    "sg:postcode":"4730",
    "sg:province":"QLD",
    "sg:tags":[
        "repairs",
        "upgrade",
        "equipment"
    ],
    "wof:name":"Outback Queensland Internet",
    "wof:placetype":"venue"
},
  "geometry": {"coordinates":[144.249207,-23.443995],"type":"Point"}
}