{
  "type": "Feature",
  "properties": {
    "addr:full":"3 Gibbens Rd Gosford West NSW 2250",
    "addr:housenumber":"3",
    "addr:postcode":"2250",
    "addr:street":"Gibbens Rd",
    "iso:country":"AU",
    "sg:address":"3 Gibbens Rd",
    "sg:city":"Gosford West",
    "sg:classifiers":[
        {
            "category":"Manufacturing",
            "subcategory":"Tools & Machinery",
            "type":"Manufacturing & Wholesale Goods"
        }
    ],
    "sg:phone":"+61 2 4322 1466",
    "sg:postcode":"2250",
    "sg:province":"NSW",
    "sg:tags":[
        "earth",
        "excavating",
        "moving",
        "equipment"
    ],
    "wof:name":"Leader Hydraulics Pty Ltd",
    "wof:placetype":"venue"
},
  "geometry": {"coordinates":[151.32415771500001,-33.4152755737],"type":"Point"}
}