{
  "type": "Feature",
  "properties": {
    "iso:country":"AU",
    "sg:address":"337 Toorak Rd",
    "sg:city":"South Yarra",
    "sg:classifiers":[
        {
            "category":"Fast Food",
            "type":"Food & Drink"
        }
    ],
    "sg:phone":"+61 3 9826 6338",
    "sg:postcode":"3141",
    "sg:province":"VIC",
    "sg:tags":[
        "away",
        "take"
    ],
    "wof:name":"Thai Takeaway & Cafe",
    "wof:placetype":"venue"
},
  "geometry": {"coordinates":[144.998504639,-37.8396911621],"type":"Point"}
}