{
  "type": "Feature",
  "properties": {
    "iso:country":"AU",
    "sg:address":"Shop 7 175 Currumburra Rd",
    "sg:city":"Ashmore",
    "sg:classifiers":[
        {
            "category":"Organizations",
            "subcategory":"Membership Organization",
            "type":"Services"
        }
    ],
    "sg:phone":"+61 7 5564 8122",
    "sg:postcode":"4214",
    "sg:province":"QLD",
    "sg:tags":[
        "equipment",
        "inter-communication",
        "system"
    ],
    "wof:name":"Joe Lowe",
    "wof:placetype":"venue"
},
  "geometry": {"coordinates":[153.38247680699999,-27.9801673889],"type":"Point"}
}