{
  "type": "Feature",
  "properties": {
    "addr:full":"15 Nockolds St Walpole WA 6398",
    "addr:housenumber":"15",
    "addr:postcode":"6398",
    "addr:street":"Nockolds St",
    "iso:country":"AU",
    "sg:address":"15 Nockolds St",
    "sg:city":"Walpole",
    "sg:classifiers":[
        {
            "category":"Real Estate",
            "subcategory":"Real Estate Agent",
            "type":"Services"
        }
    ],
    "sg:phone":"+61 8 9840 1231",
    "sg:postcode":"6398",
    "sg:province":"WA",
    "wof:name":"Walpole Real Estate",
    "wof:placetype":"venue"
},
  "geometry": {"coordinates":[116.730667114,-34.9764595032],"type":"Point"}
}