{
  "type": "Feature",
  "properties": {
    "addr:full":"Lvl1/ 132 Melrose Drv Phillip ACT 2606",
    "addr:housenumber":"132",
    "addr:postcode":"2606",
    "addr:street":"Melrose Drv",
    "iso:country":"AU",
    "sg:address":"Lvl1/ 132 Melrose Drv",
    "sg:city":"Phillip",
    "sg:classifiers":[
        {
            "category":"Professional",
            "subcategory":"Accounting & Tax Preparation",
            "type":"Services"
        }
    ],
    "sg:phone":"+61 2 6281 1555",
    "sg:postcode":"2606",
    "sg:province":"ACT",
    "sg:tags":[
        "accountant",
        "auditor"
    ],
    "wof:name":"Corporate Accounting Solutions",
    "wof:placetype":"venue"
},
  "geometry": {"coordinates":[149.088256836,-35.350276947],"type":"Point"}
}