{
  "type": "Feature",
  "properties": {
    "iso:country":"AU",
    "sg:address":"309 Crestwood Drv",
    "sg:city":"Port Macquarie",
    "sg:classifiers":[
        {
            "category":"Health Services",
            "subcategory":"Doctor",
            "type":"Services"
        }
    ],
    "sg:phone":"+61 2 6582 5900",
    "sg:postcode":"2444",
    "sg:province":"NSW",
    "sg:tags":[
        "reflexology"
    ],
    "wof:name":"ROBYN GOLDSMITH",
    "wof:placetype":"venue"
},
  "geometry": {"coordinates":[152.905716,-31.468412],"type":"Point"}
}