{
  "type": "Feature",
  "properties": {
    "addr:full":"3 Warbungle St Gunnedah NSW 2380",
    "addr:housenumber":"3",
    "addr:postcode":"2380",
    "addr:street":"Warbungle St",
    "iso:country":"AU",
    "sg:address":"3 Warbungle St",
    "sg:city":"Gunnedah",
    "sg:classifiers":[
        {
            "category":"Wholesale",
            "subcategory":"Machinery & Supplies",
            "type":"Manufacturing & Wholesale Goods"
        }
    ],
    "sg:phone":"+61 2 6742 2775",
    "sg:postcode":"2380",
    "sg:province":"NSW",
    "sg:tags":[
        "equipment",
        "hydraulic"
    ],
    "wof:name":"Ag Fix",
    "wof:placetype":"venue"
},
  "geometry": {"coordinates":[150.243972778,-30.9751472473],"type":"Point"}
}