{
  "type": "Feature",
  "properties": {
    "addr:full":"17 Ruthven Ave Adelaide SA 5000",
    "addr:housenumber":"17",
    "addr:postcode":"5000",
    "addr:street":"Ruthven Ave",
    "iso:country":"AU",
    "sg:address":"17 Ruthven Ave",
    "sg:city":"Adelaide",
    "sg:classifiers":[
        {
            "category":"Personal",
            "subcategory":"Adult",
            "type":"Services"
        }
    ],
    "sg:phone":"+61 8 8212 0525",
    "sg:postcode":"5000",
    "sg:province":"SA",
    "sg:tags":[
        "vic",
        "except",
        "state",
        "escort",
        "social",
        "qld"
    ],
    "wof:name":"Adeles",
    "wof:placetype":"venue"
},
  "geometry": {"coordinates":[138.59034729000001,-34.9285888672],"type":"Point"}
}