{
  "type": "Feature",
  "properties": {
    "addr:full":"1 Grant Crs Macksville NSW 2447",
    "addr:housenumber":"1",
    "addr:postcode":"2447",
    "addr:street":"Grant Crs",
    "iso:country":"AU",
    "sg:address":"1 Grant Crs",
    "sg:city":"Macksville",
    "sg:classifiers":[
        {
            "category":"Education",
            "subcategory":"Vocational School",
            "type":"Public Place"
        }
    ],
    "sg:phone":"+61 2 6568 4181",
    "sg:postcode":"2447",
    "sg:province":"NSW",
    "sg:tags":[
        "cake",
        "decorating",
        "decorator"
    ],
    "wof:name":"Sugar n Spice Cakes & Pastries",
    "wof:placetype":"venue"
},
  "geometry": {"coordinates":[152.920624,-30.707781],"type":"Point"}
}