{
  "type": "Feature",
  "properties": {
    "addr:full":"45 Main Rd Huonville TAS 7109",
    "addr:housenumber":"45",
    "addr:postcode":"7109",
    "addr:street":"Main Rd",
    "iso:country":"AU",
    "sg:address":"45 Main Rd",
    "sg:city":"Huonville",
    "sg:classifiers":[
        {
            "category":"Autos & Motor Vehicles",
            "subcategory":"Fuel & Gas Station",
            "type":"Retail Goods"
        }
    ],
    "sg:phone":"+61 3 6264 1806",
    "sg:postcode":"7109",
    "sg:province":"TAS",
    "wof:name":"Plus Petrol",
    "wof:placetype":"venue"
},
  "geometry": {"coordinates":[147.048553467,-43.0303153992],"type":"Point"}
}