{
  "type": "Feature",
  "properties": {
    "iso:country":"AU",
    "sg:address":"50a Campbell St",
    "sg:city":"Glebe",
    "sg:classifiers":[
        {
            "category":"Professional",
            "subcategory":"Employment Agencies",
            "type":"Services"
        }
    ],
    "sg:phone":"+61 2 9660 7735",
    "sg:postcode":"2037",
    "sg:province":"NSW",
    "sg:tags":[
        "entertainer",
        "agent"
    ],
    "wof:name":"Hoola's Hollywood Hawaiians",
    "wof:placetype":"venue"
},
  "geometry": {"coordinates":[151.19012451200001,-33.881526947],"type":"Point"}
}