{
  "type": "Feature",
  "properties": {
    "addr:full":"Cnr Veivers Rd & Cook Hwy Palm Cove QLD 4879",
    "addr:postcode":"4879",
    "addr:street":"Cnr Veivers Rd & Cook Hwy",
    "iso:country":"AU",
    "sg:address":"Cnr Veivers Rd & Cook Hwy",
    "sg:city":"Palm Cove",
    "sg:classifiers":[
        {
            "category":"Real Estate",
            "subcategory":"Real Estate Agent",
            "type":"Services"
        }
    ],
    "sg:phone":"+61 7 4055 3233",
    "sg:postcode":"4879",
    "sg:province":"QLD",
    "wof:name":"Raine & Horne Qld",
    "wof:placetype":"venue"
},
  "geometry": {"coordinates":[145.67033386200001,-16.7495708466],"type":"Point"}
}