{
  "type": "Feature",
  "properties": {
    "addr:full":"Unit 12 Hale St Botany NSW 2019",
    "addr:postcode":"2019",
    "addr:street":"Hale St",
    "iso:country":"AU",
    "sg:address":"Unit 12 Hale St",
    "sg:city":"Botany",
    "sg:classifiers":[
        {
            "category":"Manufacturing",
            "subcategory":"Metals",
            "type":"Manufacturing & Wholesale Goods"
        }
    ],
    "sg:phone":"+61 2 9316 5600",
    "sg:postcode":"2019",
    "sg:province":"NSW",
    "sg:tags":[
        "steel",
        "fabricator",
        "mfrs"
    ],
    "wof:name":"Krimguard",
    "wof:placetype":"venue"
},
  "geometry": {"coordinates":[151.19366455100001,-33.9462585449],"type":"Point"}
}