{
  "type": "Feature",
  "properties": {
    "addr:full":"Queen St Maffra VIC 3860",
    "addr:postcode":"3860",
    "addr:street":"Queen St",
    "iso:country":"AU",
    "sg:address":"Queen St",
    "sg:city":"Maffra",
    "sg:classifiers":[
        {
            "category":"Education",
            "subcategory":"Kindergarten",
            "type":"Public Place"
        }
    ],
    "sg:phone":"+61 3 5147 1266",
    "sg:postcode":"3860",
    "sg:province":"VIC",
    "sg:tags":[
        "pre-schools"
    ],
    "wof:name":"Queen Street Kindergarten",
    "wof:placetype":"venue"
},
  "geometry": {"coordinates":[146.98414611800001,-37.9699745178],"type":"Point"}
}