{
  "type": "Feature",
  "properties": {
    "iso:country":"AU",
    "sg:address":"222 Ingles St",
    "sg:city":"Port Melbourne",
    "sg:classifiers":[
        {
            "category":"School Buses",
            "type":"Transportation"
        }
    ],
    "sg:phone":"+61 3 9681 9722",
    "sg:postcode":"3207",
    "sg:province":"VIC",
    "sg:tags":[
        "brick"
    ],
    "wof:name":"Heritage Stone",
    "wof:placetype":"venue"
},
  "geometry": {"coordinates":[144.941147,-37.828709],"type":"Point"}
}