{
  "type": "Feature",
  "properties": {
    "addr:full":"40 Main St Mornington VIC 3931",
    "addr:housenumber":"40",
    "addr:postcode":"3931",
    "addr:street":"Main St",
    "iso:country":"AU",
    "sg:address":"40 Main St",
    "sg:city":"Mornington",
    "sg:classifiers":[
        {
            "category":"Shopping",
            "subcategory":"Clothing, Apparel, & Fashions",
            "type":"Retail Goods"
        }
    ],
    "sg:phone":"+61 3 5975 7955",
    "sg:postcode":"3931",
    "sg:province":"VIC",
    "sg:tags":[
        "menswear"
    ],
    "wof:name":"Daniel Regan Male Fashion",
    "wof:placetype":"venue"
},
  "geometry": {"coordinates":[145.03752136200001,-38.2176856995],"type":"Point"}
}