{
  "type": "Feature",
  "properties": {
    "addr:full":"PO Box 31 Cremorne Junction NSW 2090",
    "addr:postcode":"2090",
    "iso:country":"AU",
    "sg:address":"PO Box 31",
    "sg:city":"Cremorne Junction",
    "sg:classifiers":[
        {
            "category":"Banks & Credit Unions",
            "subcategory":"Investment Brokerage",
            "type":"Services"
        }
    ],
    "sg:phone":"+61 2 9953 9664",
    "sg:postcode":"2090",
    "sg:province":"NSW",
    "wof:name":"Hungerford Financial Management",
    "wof:placetype":"venue"
},
  "geometry": {"coordinates":[151.22792053200001,-33.832359314],"type":"Point"}
}