{
  "type": "Feature",
  "properties": {
    "iso:country":"AU",
    "sg:address":"28 Woodbine Rd",
    "sg:city":"Forestdale",
    "sg:classifiers":[
        {
            "category":"Professional",
            "type":"Services"
        }
    ],
    "sg:phone":"+61 7 3800 2780",
    "sg:postcode":"4118",
    "sg:province":"QLD",
    "sg:tags":[
        "transport"
    ],
    "wof:name":"Casaceli Matt & Rick",
    "wof:placetype":"venue"
},
  "geometry": {"coordinates":[153.011062622,-27.6657276154],"type":"Point"}
}