{
  "type": "Feature",
  "properties": {
    "iso:country":"AU",
    "sg:address":"103 Bowen Rd",
    "sg:city":"Rosslea",
    "sg:classifiers":[
        {
            "category":"Retail",
            "subcategory":"Auto Repair",
            "type":"Services"
        }
    ],
    "sg:phone":"+61 7 4779 1357",
    "sg:postcode":"4812",
    "sg:province":"QLD",
    "sg:tags":[
        "wheel",
        "balancing",
        "alignment"
    ],
    "wof:name":"Bahrs Automotive Service Centre",
    "wof:placetype":"venue"
},
  "geometry": {"coordinates":[146.80003400000001,-19.301023],"type":"Point"}
}