{
  "type": "Feature",
  "properties": {
    "addr:full":"Shop 1161/2 Westfield Shopping Town 1328 Albany Highway Cannington WA 6107",
    "addr:housenumber":"1161 / 2;1328",
    "addr:postcode":"6107",
    "addr:street":"Westfield;Albany Highway",
    "iso:country":"AU",
    "sg:address":"Shop 1161/2 Westfield Shopping Town 1328 Albany Highway",
    "sg:city":"Cannington",
    "sg:classifiers":[
        {
            "category":"Personal",
            "subcategory":"Beauty Salon",
            "type":"Services"
        }
    ],
    "sg:phone":"+61 8 9356 7766",
    "sg:postcode":"6107",
    "sg:province":"WA",
    "sg:tags":[
        "hairdresser"
    ],
    "wof:name":"Price Attack",
    "wof:placetype":"venue"
},
  "geometry": {"coordinates":[115.990112305,-32.0450820923],"type":"Point"}
}