{
  "type": "Feature",
  "properties": {
    "addr:full":"27 Caledonian Ave Winston Hills NSW 2153",
    "addr:housenumber":"27",
    "addr:postcode":"2153",
    "addr:street":"Caledonian Ave",
    "iso:country":"AU",
    "sg:address":"27 Caledonian Ave",
    "sg:city":"Winston Hills",
    "sg:classifiers":[
        {
            "category":"Banks & Credit Unions",
            "subcategory":"Financial Services",
            "type":"Services"
        }
    ],
    "sg:phone":"+61 2 9639 0514",
    "sg:postcode":"2153",
    "sg:province":"NSW",
    "sg:tags":[
        "planning"
    ],
    "wof:name":"Count Wealth Accountants",
    "wof:placetype":"venue"
},
  "geometry": {"coordinates":[150.982177734,-33.7780075073],"type":"Point"}
}