{
  "type": "Feature",
  "properties": {
    "addr:full":"47 Tingira St Portsmith QLD 4870",
    "addr:housenumber":"47",
    "addr:postcode":"4870",
    "addr:street":"Tingira St Portsmith",
    "iso:country":"AU",
    "sg:address":"47 Tingira St",
    "sg:city":"Portsmith",
    "sg:classifiers":[
        {
            "category":"Farming",
            "subcategory":"Fish & Marine Products",
            "type":"Manufacturing & Wholesale Goods"
        }
    ],
    "sg:phone":"+61 7 4035 1262",
    "sg:postcode":"4870",
    "sg:province":"QLD",
    "sg:tags":[
        "fisherman"
    ],
    "wof:name":"Horizon Seafood Pty Ltd",
    "wof:placetype":"venue"
},
  "geometry": {"coordinates":[145.77127075199999,-16.9469299316],"type":"Point"}
}