{
  "type": "Feature",
  "properties": {
    "addr:full":"Cnr Carlingford & Pennant Hills Rds Carlingford NSW 2118",
    "addr:postcode":"2118",
    "addr:street":"Cnr",
    "iso:country":"AU",
    "sg:address":"Cnr Carlingford & Pennant Hills Rds",
    "sg:city":"Carlingford",
    "sg:classifiers":[
        {
            "category":"Shopping",
            "subcategory":"Bridal",
            "type":"Retail Goods"
        }
    ],
    "sg:phone":"+61 2 9872 6111",
    "sg:postcode":"2118",
    "sg:province":"NSW",
    "sg:tags":[
        "hire",
        "wear"
    ],
    "wof:name":"Grace Bros Formal Hire",
    "wof:placetype":"venue"
},
  "geometry": {"coordinates":[151.05491638199999,-33.7770309448],"type":"Point"}
}