{
  "type": "Feature",
  "properties": {
    "iso:country":"AU",
    "sg:address":"13 Stinton St",
    "sg:city":"Mandurah",
    "sg:classifiers":[
        {
            "category":"Mining & Drilling",
            "type":"Manufacturing & Wholesale Goods"
        }
    ],
    "sg:phone":"+61 8 9535 2508",
    "sg:postcode":"6210",
    "sg:province":"WA",
    "sg:tags":[
        "boring",
        "contractor"
    ],
    "wof:name":"Peel Water Boring",
    "wof:placetype":"venue"
},
  "geometry": {"coordinates":[115.735161,-32.525185],"type":"Point"}
}