{
  "type": "Feature",
  "properties": {
    "iso:country":"AU",
    "sg:address":"2/ 23 Mclean St",
    "sg:city":"Bundaberg",
    "sg:classifiers":[
        {
            "category":"Utilities",
            "subcategory":"Water",
            "type":"Services"
        }
    ],
    "sg:phone":"+61 7 4153 1960",
    "sg:postcode":"4670",
    "sg:province":"QLD",
    "sg:tags":[
        "hot",
        "system"
    ],
    "wof:name":"Express Plumbing",
    "wof:placetype":"venue"
},
  "geometry": {"coordinates":[152.34718322800001,-24.8730010986],"type":"Point"}
}