{
  "type": "Feature",
  "properties": {
    "addr:full":"7 Jannali Pl Robina QLD 4226",
    "addr:housenumber":"7",
    "addr:postcode":"4226",
    "addr:street":"Jannali Pl",
    "iso:country":"AU",
    "sg:address":"7 Jannali Pl",
    "sg:city":"Robina",
    "sg:classifiers":[
        {
            "category":"Professional",
            "subcategory":"Computer Services",
            "type":"Services"
        }
    ],
    "sg:phone":"+61 7 5593 2868",
    "sg:postcode":"4226",
    "sg:province":"QLD",
    "sg:tags":[
        "consultant",
        "system"
    ],
    "wof:name":"Sandor Consultancy Service",
    "wof:placetype":"venue"
},
  "geometry": {"coordinates":[153.408370972,-28.0552711487],"type":"Point"}
}