{
  "type": "Feature",
  "properties": {
    "addr:full":"129 Magill Rd Stepney SA 5069",
    "addr:housenumber":"129",
    "addr:postcode":"5069",
    "addr:street":"Magill Rd",
    "iso:country":"AU",
    "sg:address":"129 Magill Rd",
    "sg:city":"Stepney",
    "sg:classifiers":[
        {
            "category":"Shopping",
            "subcategory":"Antiques",
            "type":"Retail Goods"
        }
    ],
    "sg:phone":"+61 8 8363 3413",
    "sg:postcode":"5069",
    "sg:province":"SA",
    "wof:name":"Mid Century Modern",
    "wof:placetype":"venue"
},
  "geometry": {"coordinates":[138.632125855,-34.9150695801],"type":"Point"}
}