{
  "type": "Feature",
  "properties": {
    "addr:full":"494 Boundary Rd Archerfield QLD 4108",
    "addr:housenumber":"494",
    "addr:postcode":"4108",
    "addr:street":"Boundary Rd",
    "iso:country":"AU",
    "sg:address":"494 Boundary Rd",
    "sg:city":"Archerfield",
    "sg:classifiers":[
        {
            "category":"Professional",
            "subcategory":"Printing & Photocopies",
            "type":"Services"
        }
    ],
    "sg:phone":"+61 7 3277 8429",
    "sg:postcode":"4108",
    "sg:province":"QLD",
    "sg:tags":[
        "screen",
        "printer"
    ],
    "wof:name":"Commodore Printing & Graphics",
    "wof:placetype":"venue"
},
  "geometry": {"coordinates":[153.01622009299999,-27.5670089722],"type":"Point"}
}