{
  "type": "Feature",
  "properties": {
    "iso:country":"AU",
    "sg:address":"295 Marrickville Rd",
    "sg:city":"Marrickville",
    "sg:classifiers":[
        {
            "category":"Personal",
            "subcategory":"Beauty Salon",
            "type":"Services"
        }
    ],
    "sg:phone":"+61 2 9569 2664",
    "sg:postcode":"2204",
    "sg:province":"NSW",
    "wof:name":"Skin Care Clinic",
    "wof:placetype":"venue"
},
  "geometry": {"coordinates":[151.154831,-33.909943],"type":"Point"}
}