{
  "type": "Feature",
  "properties": {
    "addr:full":"206 Kingaroy Barkers Creek Rd Kingaroy QLD 4610",
    "addr:housenumber":"206",
    "addr:postcode":"4610",
    "addr:street":"Kingaroy Barkers Creek Rd",
    "iso:country":"AU",
    "sg:address":"206 Kingaroy Barkers Creek Rd",
    "sg:city":"Kingaroy",
    "sg:classifiers":[
        {
            "category":"Wholesale",
            "subcategory":"Meat",
            "type":"Manufacturing & Wholesale Goods"
        }
    ],
    "sg:phone":"+61 7 4164 9500",
    "sg:postcode":"4610",
    "sg:province":"QLD",
    "sg:tags":[
        "abattoir"
    ],
    "wof:name":"Swickers Kingaroy Bacon Factory Pty Ltd",
    "wof:placetype":"venue"
},
  "geometry": {"coordinates":[151.85780334500001,-26.5416965485],"type":"Point"}
}