{
  "type": "Feature",
  "properties": {
    "addr:full":"Grampians Rd Halls Gap VIC 3381",
    "addr:postcode":"3381",
    "addr:street":"Grampians Rd",
    "iso:country":"AU",
    "sg:address":"Grampians Rd",
    "sg:city":"Halls Gap",
    "sg:classifiers":[
        {
            "category":"Cafe",
            "type":"Food & Drink"
        }
    ],
    "sg:phone":"+61 3 5356 4400",
    "sg:postcode":"3381",
    "sg:province":"VIC",
    "wof:name":"Flying Emu Cafe The",
    "wof:placetype":"venue"
},
  "geometry": {"coordinates":[142.524902344,-37.1499862671],"type":"Point"}
}