{
  "type": "Feature",
  "properties": {
    "addr:full":"Fact 1 29 Culverlands St Heidelberg West VIC 3081",
    "addr:housenumber":"1 29",
    "addr:postcode":"3081",
    "addr:street":"Fact;Culverlands St",
    "iso:country":"AU",
    "sg:address":"Fact 1 29 Culverlands St",
    "sg:city":"Heidelberg West",
    "sg:classifiers":[
        {
            "category":"Professional",
            "subcategory":"Engineering",
            "type":"Services"
        }
    ],
    "sg:phone":"+61 3 9459 4143",
    "sg:postcode":"3081",
    "sg:province":"VIC",
    "sg:tags":[
        "engineer"
    ],
    "wof:name":"F Gary Engineering",
    "wof:placetype":"venue"
},
  "geometry": {"coordinates":[145.05555725100001,-37.7303848267],"type":"Point"}
}