{
  "type": "Feature",
  "properties": {
    "addr:full":"28 Allen Drv Mt Eliza VIC 3930",
    "addr:housenumber":"28",
    "addr:postcode":"3930",
    "addr:street":"Allen Drv",
    "iso:country":"AU",
    "sg:address":"28 Allen Drv",
    "sg:city":"Mt Eliza",
    "sg:classifiers":[
        {
            "category":"Banks & Credit Unions",
            "subcategory":"Financial Services",
            "type":"Services"
        }
    ],
    "sg:phone":"+61 3 9775 4888",
    "sg:postcode":"3930",
    "sg:province":"VIC",
    "sg:tags":[
        "planning"
    ],
    "wof:name":"Grosvenor Securities Pty Ltd",
    "wof:placetype":"venue"
},
  "geometry": {"coordinates":[145.09469604500001,-38.1813964844],"type":"Point"}
}