{
  "type": "Feature",
  "properties": {
    "iso:country":"AU",
    "sg:address":"10 Rundle Pl",
    "sg:city":"Carindale",
    "sg:classifiers":[
        {
            "category":"Building & Trades",
            "subcategory":"Construction",
            "type":"Services"
        }
    ],
    "sg:phone":"+61 7 3849 6031",
    "sg:postcode":"4152",
    "sg:province":"QLD",
    "sg:tags":[
        "renovation",
        "alterations",
        "extension",
        "contractor"
    ],
    "wof:name":"Christofis J & P Builders",
    "wof:placetype":"venue"
},
  "geometry": {"coordinates":[153.11073303200001,-27.5226764679],"type":"Point"}
}