{
  "type": "Feature",
  "properties": {
    "iso:country":"AU",
    "sg:address":"3 Marion St",
    "sg:city":"Altona North",
    "sg:classifiers":[
        {
            "category":"Building & Trades",
            "subcategory":"Construction",
            "type":"Services"
        }
    ],
    "sg:phone":"+61 3 9391 3079",
    "sg:postcode":"3025",
    "sg:province":"VIC",
    "sg:tags":[
        "joiner",
        "carpenter"
    ],
    "wof:name":"Batzogiannis T",
    "wof:placetype":"venue"
},
  "geometry": {"coordinates":[144.86082500000001,-37.836288],"type":"Point"}
}