{
  "type": "Feature",
  "properties": {
    "addr:full":"71 Arabella St Longueville NSW 2066",
    "addr:housenumber":"71",
    "addr:postcode":"2066",
    "addr:street":"Arabella St",
    "iso:country":"AU",
    "sg:address":"71 Arabella St",
    "sg:city":"Longueville",
    "sg:classifiers":[
        {
            "category":"Manufacturing",
            "subcategory":"Food",
            "type":"Manufacturing & Wholesale Goods"
        }
    ],
    "sg:phone":"+61 2 9418 6949",
    "sg:postcode":"2066",
    "sg:province":"NSW",
    "sg:tags":[
        "function",
        "catering"
    ],
    "wof:name":"All Catering Essentials",
    "wof:placetype":"venue"
},
  "geometry": {"coordinates":[151.169265747,-33.8304862976],"type":"Point"}
}