{
  "type": "Feature",
  "properties": {
    "addr:full":"965 Whitehorse Rd Box Hill VIC 3128",
    "addr:housenumber":"965",
    "addr:postcode":"3128",
    "addr:street":"Whitehorse Rd",
    "iso:country":"AU",
    "sg:address":"965 Whitehorse Rd",
    "sg:city":"Box Hill",
    "sg:classifiers":[
        {
            "category":"Personal",
            "subcategory":"Beauty Salon",
            "type":"Services"
        }
    ],
    "sg:phone":"+61 3 9898 3144",
    "sg:postcode":"3128",
    "sg:province":"VIC",
    "wof:name":"Madison Avenue Skin & Spa Body Therapy",
    "wof:placetype":"venue"
},
  "geometry": {"coordinates":[145.124267578,-37.8178291321],"type":"Point"}
}