{
  "type": "Feature",
  "properties": {
    "addr:full":"Palmer Rd Murray Bridge SA 5253",
    "addr:postcode":"5253",
    "addr:street":"Palmer Rd",
    "iso:country":"AU",
    "sg:address":"Palmer Rd",
    "sg:city":"Murray Bridge",
    "sg:classifiers":[
        {
            "category":"Education",
            "subcategory":"Special Training",
            "type":"Public Place"
        }
    ],
    "sg:phone":"+61 8 8531 1744",
    "sg:postcode":"5253",
    "sg:province":"SA",
    "sg:tags":[
        "school",
        "flying"
    ],
    "wof:name":"Murray Bridge Light Aircraft Flying School",
    "wof:placetype":"venue"
},
  "geometry": {"coordinates":[139.25022888199999,-35.0904579163],"type":"Point"}
}