{
  "type": "Feature",
  "properties": {
    "addr:full":"Lot 4 Vine Drv Jindera NSW 2642",
    "addr:postcode":"2642",
    "addr:street":"Vine Drv",
    "iso:country":"AU",
    "sg:address":"Lot 4 Vine Drv",
    "sg:city":"Jindera",
    "sg:classifiers":[
        {
            "category":"Building & Trades",
            "subcategory":"Construction",
            "type":"Services"
        }
    ],
    "sg:phone":"+61 2 6026 3412",
    "sg:postcode":"2642",
    "sg:province":"NSW",
    "sg:tags":[
        "earth",
        "excavating",
        "moving",
        "contractor"
    ],
    "wof:name":"Cart-Right Earthmoving P/L",
    "wof:placetype":"venue"
},
  "geometry": {"coordinates":[146.90248107900001,-35.9622268677],"type":"Point"}
}