{
  "type": "Feature",
  "properties": {
    "addr:full":"148 Bell St Heidelberg Heights VIC 3081",
    "addr:housenumber":"148",
    "addr:postcode":"3081",
    "addr:street":"Bell St",
    "iso:country":"AU",
    "sg:address":"148 Bell St",
    "sg:city":"Heidelberg Heights",
    "sg:classifiers":[
        {
            "category":"Personal",
            "subcategory":"Beauty Salon",
            "type":"Services"
        }
    ],
    "sg:phone":"+61 3 9459 9260",
    "sg:postcode":"3081",
    "sg:province":"VIC",
    "wof:name":"Cosmopolitan Beauty Lounge",
    "wof:placetype":"venue"
},
  "geometry": {"coordinates":[145.050872803,-37.7528266907],"type":"Point"}
}