{
  "type": "Feature",
  "properties": {
    "iso:country":"AU",
    "sg:address":"Shop 4/ 4 Alexander Rd",
    "sg:city":"Padbury",
    "sg:classifiers":[
        {
            "category":"Fast Food",
            "type":"Food & Drink"
        }
    ],
    "sg:phone":"+61 8 9307 4755",
    "sg:postcode":"6025",
    "sg:province":"WA",
    "sg:tags":[
        "away",
        "take"
    ],
    "wof:name":"Padbury Pizza",
    "wof:placetype":"venue"
},
  "geometry": {"coordinates":[115.762710571,-31.8004608154],"type":"Point"}
}