{
  "type": "Feature",
  "properties": {
    "addr:full":"32 Gladeswood Drv Mulgrave VIC 3170",
    "addr:housenumber":"32",
    "addr:postcode":"3170",
    "addr:street":"Gladeswood Drv",
    "iso:country":"AU",
    "sg:address":"32 Gladeswood Drv",
    "sg:city":"Mulgrave",
    "sg:classifiers":[
        {
            "category":"Building & Trades",
            "subcategory":"Construction",
            "type":"Services"
        }
    ],
    "sg:phone":"+61 3 9795 6936",
    "sg:postcode":"3170",
    "sg:province":"VIC",
    "sg:tags":[
        "contractor"
    ],
    "wof:name":"Avwood Pty Ltd",
    "wof:placetype":"venue"
},
  "geometry": {"coordinates":[145.19760131800001,-37.9332504272],"type":"Point"}
}