{
  "type": "Feature",
  "properties": {
    "iso:country":"AU",
    "sg:address":"Shop 5/ 1",
    "sg:city":"Bridge Mall Ballarat",
    "sg:classifiers":[
        {
            "category":"Personal",
            "type":"Services"
        }
    ],
    "sg:phone":"+61 3 5332 7389",
    "sg:postcode":"3350",
    "sg:province":"VIC",
    "sg:tags":[
        "reducing",
        "treatment",
        "weight"
    ],
    "wof:name":"Tony Ferguson Weight Loss & Wellness Centre",
    "wof:placetype":"venue"
},
  "geometry": {"coordinates":[143.861633,-37.562405],"type":"Point"}
}