{
  "type": "Feature",
  "properties": {
    "addr:full":"Unit 2/ 3 Fox St Narellan NSW 2567",
    "addr:postcode":"2567",
    "addr:street":"Fox St",
    "iso:country":"AU",
    "sg:address":"Unit 2/ 3 Fox St",
    "sg:city":"Narellan",
    "sg:classifiers":[
        {
            "category":"Building & Trades",
            "subcategory":"Cleaning & Sanitation",
            "type":"Services"
        }
    ],
    "sg:phone":"+61 2 4655 9936",
    "sg:postcode":"2567",
    "sg:province":"NSW",
    "sg:tags":[
        "abrasive",
        "blasting"
    ],
    "wof:name":"A-1 Abrasive Blasting (Aust) Pty Ltd",
    "wof:placetype":"venue"
},
  "geometry": {"coordinates":[150.732589722,-34.0393981934],"type":"Point"}
}