{
  "type": "Feature",
  "properties": {
    "addr:full":"PO Box 425 Port Melbourne VIC 3207",
    "addr:postcode":"3207",
    "iso:country":"AU",
    "sg:address":"PO Box 425",
    "sg:city":"Port Melbourne",
    "sg:classifiers":[
        {
            "category":"Building & Trades",
            "subcategory":"Cleaning & Sanitation",
            "type":"Services"
        }
    ],
    "sg:phone":"+61 402 648 355",
    "sg:postcode":"3207",
    "sg:province":"VIC",
    "sg:tags":[
        "window"
    ],
    "wof:name":"Visual Window Cleaning",
    "wof:placetype":"venue"
},
  "geometry": {"coordinates":[144.92337000000001,-37.83424],"type":"Point"}
}