{
  "type": "Feature",
  "properties": {
    "addr:full":"96 St Pauls St Randwick NSW 2031",
    "addr:housenumber":"96",
    "addr:postcode":"2031",
    "addr:street":"St Pauls St",
    "iso:country":"AU",
    "sg:address":"96 St Pauls St",
    "sg:city":"Randwick",
    "sg:classifiers":[
        {
            "category":"Travel",
            "subcategory":"Hotels & Motels",
            "type":"Entertainment"
        }
    ],
    "sg:phone":"+61 2 9398 7022",
    "sg:postcode":"2031",
    "sg:province":"NSW",
    "wof:name":"Esron Motel",
    "wof:placetype":"venue"
},
  "geometry": {"coordinates":[151.246582031,-33.9209442139],"type":"Point"}
}