{
  "type": "Feature",
  "properties": {
    "iso:country":"AU",
    "sg:address":"290 High St",
    "sg:city":"Northcote",
    "sg:classifiers":[
        {
            "category":"Banks & Credit Unions",
            "subcategory":"Bank",
            "type":"Services"
        }
    ],
    "sg:phone":"+61 13 20 32",
    "sg:postcode":"3070",
    "sg:province":"VIC",
    "wof:name":"Westpac",
    "wof:placetype":"venue"
},
  "geometry": {"coordinates":[144.99868799999999,-37.771748],"type":"Point"}
}