{
  "type": "Feature",
  "properties": {
    "iso:country":"AU",
    "sg:address":"380 Goodwood Rd",
    "sg:city":"Cumberland Park",
    "sg:classifiers":[
        {
            "category":"Health Services",
            "subcategory":"Health Practitioner",
            "type":"Services"
        }
    ],
    "sg:phone":"+61 8 8373 0562",
    "sg:postcode":"5041",
    "sg:province":"SA",
    "sg:tags":[
        "physiotherapist"
    ],
    "wof:name":"McKeough Tim",
    "wof:placetype":"venue"
},
  "geometry": {"coordinates":[138.59111,-34.968288],"type":"Point"}
}