{
  "type": "Feature",
  "properties": {
    "addr:full":"99 Bathurst St Sydney NSW 2000",
    "addr:housenumber":"99",
    "addr:postcode":"2000",
    "addr:street":"Bathurst St",
    "iso:country":"AU",
    "sg:address":"99 Bathurst St",
    "sg:city":"Sydney",
    "sg:classifiers":[
        {
            "category":"Shopping",
            "type":"Retail Goods"
        }
    ],
    "sg:phone":"+61 2 9267 8509",
    "sg:postcode":"2000",
    "sg:province":"NSW",
    "sg:tags":[
        "new age",
        "product"
    ],
    "wof:name":"Adyar Bookshop",
    "wof:placetype":"venue"
},
  "geometry": {"coordinates":[151.20585632300001,-33.8725013733],"type":"Point"}
}