{
  "type": "Feature",
  "properties": {
    "addr:full":"1765 Mt Gravatt Capalaba Rd Capalaba QLD 4157",
    "addr:housenumber":"1765",
    "addr:postcode":"4157",
    "addr:street":"Mt;Capalaba Rd",
    "iso:country":"AU",
    "sg:address":"1765 Mt Gravatt Capalaba Rd",
    "sg:city":"Capalaba",
    "sg:classifiers":[
        {
            "category":"Home & Garden",
            "subcategory":"Building Materials",
            "type":"Retail Goods"
        }
    ],
    "sg:phone":"+61 7 3390 3989",
    "sg:postcode":"4157",
    "sg:province":"QLD",
    "sg:tags":[
        "lawn",
        "cutting",
        "maintenance"
    ],
    "wof:name":"Dobias Bill",
    "wof:placetype":"venue"
},
  "geometry": {"coordinates":[153.176635742,-27.5229148865],"type":"Point"}
}