{
  "type": "Feature",
  "properties": {
    "addr:full":"145 Rainbow St Sandgate QLD 4017",
    "addr:housenumber":"145",
    "addr:postcode":"4017",
    "addr:street":"Rainbow St",
    "iso:country":"AU",
    "sg:address":"145 Rainbow St",
    "sg:city":"Sandgate",
    "sg:classifiers":[
        {
            "category":"Professional",
            "type":"Services"
        }
    ],
    "sg:phone":"+61 7 3869 4922",
    "sg:postcode":"4017",
    "sg:province":"QLD",
    "sg:tags":[
        "shop",
        "fitting"
    ],
    "wof:name":"RW Retail Pty Ltd",
    "wof:placetype":"venue"
},
  "geometry": {"coordinates":[153.07273864699999,-27.3221359253],"type":"Point"}
}