{
  "type": "Feature",
  "properties": {
    "addr:full":"516 Brighton Rd Brighton SA 5048",
    "addr:housenumber":"516",
    "addr:postcode":"5048",
    "addr:street":"Brighton Rd",
    "iso:country":"AU",
    "sg:address":"516 Brighton Rd",
    "sg:city":"Brighton",
    "sg:classifiers":[
        {
            "category":"Home & Garden",
            "subcategory":"Furniture",
            "type":"Retail Goods"
        }
    ],
    "sg:phone":"+61 8 8296 0065",
    "sg:postcode":"5048",
    "sg:province":"SA",
    "sg:tags":[
        "business"
    ],
    "sg:website":"http://www.tanticonstructions.com",
    "wof:name":"Tanti Commercial Interiors",
    "wof:placetype":"venue"
},
  "geometry": {"coordinates":[138.52356,-35.021759],"type":"Point"}
}