{
  "type": "Feature",
  "properties": {
    "iso:country":"AU",
    "sg:address":"Shp 3/ 459 Hay St",
    "sg:city":"Perth",
    "sg:classifiers":[
        {
            "category":"Cafe",
            "type":"Food & Drink"
        }
    ],
    "sg:phone":"+61 8 9325 7175",
    "sg:postcode":"6000",
    "sg:province":"WA",
    "wof:name":"Shiraz Coffee Lounge",
    "wof:placetype":"venue"
},
  "geometry": {"coordinates":[115.85572052000001,-31.9532585144],"type":"Point"}
}