{
  "type": "Feature",
  "properties": {
    "addr:full":"PO Box 440 Hoxton Park NSW 2171",
    "addr:postcode":"2171",
    "iso:country":"AU",
    "sg:address":"PO Box 440",
    "sg:city":"Hoxton Park",
    "sg:classifiers":[
        {
            "category":"Utilities",
            "subcategory":"Electric",
            "type":"Services"
        }
    ],
    "sg:phone":"+61 2 8784 1900",
    "sg:postcode":"2171",
    "sg:province":"NSW",
    "sg:tags":[
        "electrical",
        "contractor"
    ],
    "wof:name":"C J Doyle Contracting Services",
    "wof:placetype":"venue"
},
  "geometry": {"coordinates":[150.84803772000001,-33.9280090332],"type":"Point"}
}