{
  "type": "Feature",
  "properties": {
    "addr:full":"Suite 1 & 2/ 108 Hunter St Newcastle NSW 2300",
    "addr:housenumber":"& 2 / 108",
    "addr:postcode":"2300",
    "addr:street":"Hunter St",
    "iso:country":"AU",
    "sg:address":"Suite 1 & 2/ 108 Hunter St",
    "sg:city":"Newcastle",
    "sg:classifiers":[
        {
            "category":"Organizations",
            "subcategory":"Membership Organization",
            "type":"Services"
        }
    ],
    "sg:phone":"+61 2 4925 2811",
    "sg:postcode":"2300",
    "sg:province":"NSW",
    "sg:tags":[
        "support",
        "health",
        "organisation"
    ],
    "wof:name":"Care Assist",
    "wof:placetype":"venue"
},
  "geometry": {"coordinates":[151.782837,-32.927307],"type":"Point"}
}