{
  "type": "Feature",
  "properties": {
    "addr:full":"17 Blackwood Park Rd Ferntree Gully VIC 3156",
    "addr:housenumber":"17",
    "addr:postcode":"3156",
    "addr:street":"Blackwood Park Rd",
    "iso:country":"AU",
    "sg:address":"17 Blackwood Park Rd",
    "sg:city":"Ferntree Gully",
    "sg:classifiers":[
        {
            "category":"Building & Trades",
            "subcategory":"Construction",
            "type":"Services"
        }
    ],
    "sg:phone":"+61 3 9758 5867",
    "sg:postcode":"3156",
    "sg:province":"VIC",
    "sg:tags":[
        "plasterboard",
        "plasterer",
        "fixer"
    ],
    "wof:name":"Knox Plastering",
    "wof:placetype":"venue"
},
  "geometry": {"coordinates":[145.28736877399999,-37.8926086426],"type":"Point"}
}