{
  "type": "Feature",
  "properties": {
    "iso:country":"AU",
    "sg:address":"73 Wallaroo St",
    "sg:city":"Moonta",
    "sg:classifiers":[
        {
            "category":"Autos & Motor Vehicles",
            "subcategory":"Auto Supplies",
            "type":"Retail Goods"
        }
    ],
    "sg:phone":"+61 8 8825 3184",
    "sg:postcode":"5558",
    "sg:province":"SA",
    "sg:tags":[
        "tyre"
    ],
    "wof:name":"Moonta Tyre Service",
    "wof:placetype":"venue"
},
  "geometry": {"coordinates":[137.591186523,-34.06823349],"type":"Point"}
}