{
  "type": "Feature",
  "properties": {
    "addr:full":"9 Faulkner St Deeragun QLD 4818",
    "addr:housenumber":"9",
    "addr:postcode":"4818",
    "addr:street":"Faulkner St",
    "iso:country":"AU",
    "sg:address":"9 Faulkner St",
    "sg:city":"Deeragun",
    "sg:classifiers":[
        {
            "category":"Mining & Drilling",
            "type":"Manufacturing & Wholesale Goods"
        }
    ],
    "sg:phone":"+61 7 4774 5216",
    "sg:postcode":"4818",
    "sg:province":"QLD",
    "sg:tags":[
        "equipment",
        "quarrying",
        "supply"
    ],
    "wof:name":"Global Mining & Industrial Services Pty Ltd",
    "wof:placetype":"venue"
},
  "geometry": {"coordinates":[146.686508,-19.244539],"type":"Point"}
}