{
  "type": "Feature",
  "properties": {
    "addr:full":"Suite 7 Newmarket Pl, 76 Enoggera Rd Newmarket QLD 4051",
    "addr:housenumber":"76",
    "addr:postcode":"4051",
    "addr:street":"Pl;Enoggera Rd",
    "iso:country":"AU",
    "sg:address":"Suite 7 Newmarket Pl, 76 Enoggera Rd",
    "sg:city":"Newmarket",
    "sg:classifiers":[
        {
            "category":"Health Services",
            "subcategory":"Health Practitioner",
            "type":"Services"
        }
    ],
    "sg:phone":"+61 7 3856 6505",
    "sg:postcode":"4051",
    "sg:province":"QLD",
    "sg:tags":[
        "physiotherapist"
    ],
    "wof:name":"Synergy Health Group",
    "wof:placetype":"venue"
},
  "geometry": {"coordinates":[153.00706481899999,-27.4381427765],"type":"Point"}
}