{
  "type": "Feature",
  "properties": {
    "addr:full":"4 St Paul's Pl Chester Hill NSW 2162",
    "addr:housenumber":"4",
    "addr:postcode":"2162",
    "addr:street":"St;Pl",
    "iso:country":"AU",
    "sg:address":"4 St Paul's Pl",
    "sg:city":"Chester Hill",
    "sg:classifiers":[
        {
            "category":"Autos & Motor Vehicles",
            "subcategory":"Auto Supplies",
            "type":"Retail Goods"
        }
    ],
    "sg:phone":"+61 433 203 661",
    "sg:postcode":"2162",
    "sg:province":"NSW",
    "sg:tags":[
        "garage",
        "equipment"
    ],
    "wof:name":"Special Calibrators",
    "wof:placetype":"venue"
},
  "geometry": {"coordinates":[151.00013732900001,-33.8829994202],"type":"Point"}
}