{
  "type": "Feature",
  "properties": {
    "iso:country":"AU",
    "sg:address":"11/ 37 St Georges Tce",
    "sg:city":"Perth",
    "sg:classifiers":[
        {
            "category":"Professional",
            "subcategory":"Accounting & Tax Preparation",
            "type":"Services"
        }
    ],
    "sg:phone":"+61 8 9221 6999",
    "sg:postcode":"6000",
    "sg:province":"WA",
    "sg:tags":[
        "accountant",
        "auditor"
    ],
    "wof:name":"Louis Nilant & Oren Zohar Chartered Accountants",
    "wof:placetype":"venue"
},
  "geometry": {"coordinates":[115.859542847,-31.9558258057],"type":"Point"}
}