{
  "type": "Feature",
  "properties": {
    "iso:country":"AU",
    "sg:address":"6 Prospect St",
    "sg:city":"Fortitude Valley",
    "sg:classifiers":[
        {
            "category":"Real Estate",
            "subcategory":"Architect",
            "type":"Services"
        }
    ],
    "sg:phone":"+61 7 3252 8912",
    "sg:postcode":"4006",
    "sg:province":"QLD",
    "wof:name":"Reddog Architects Pty Ltd",
    "wof:placetype":"venue"
},
  "geometry": {"coordinates":[153.037017822,-27.4522342682],"type":"Point"}
}