{
  "type": "Feature",
  "properties": {
    "addr:full":"McCarthy Rd Harvey WA 6220",
    "addr:postcode":"6220",
    "addr:street":"Mccarthy Rd",
    "iso:country":"AU",
    "sg:address":"McCarthy Rd",
    "sg:city":"Harvey",
    "sg:classifiers":[
        {
            "category":"Farming",
            "subcategory":"Farm",
            "type":"Manufacturing & Wholesale Goods"
        }
    ],
    "sg:phone":"+61 8 9729 1476",
    "sg:postcode":"6220",
    "sg:province":"WA",
    "sg:tags":[
        "farmer"
    ],
    "wof:name":"Hanks R R",
    "wof:placetype":"venue"
},
  "geometry": {"coordinates":[115.90010100000001,-33.028191],"type":"Point"}
}