{
  "type": "Feature",
  "properties": {
    "iso:country":"AU",
    "sg:address":"Unit 18, 62 Keane St",
    "sg:city":"Currajong",
    "sg:classifiers":[
        {
            "category":"Real Estate",
            "subcategory":"Architect",
            "type":"Services"
        }
    ],
    "sg:phone":"+61 7 4725 7711",
    "sg:postcode":"4812",
    "sg:province":"QLD",
    "sg:tags":[
        "magnet",
        "magnetic",
        "material"
    ],
    "wof:name":"N.Q. Coastal Sign Products",
    "wof:placetype":"venue"
},
  "geometry": {"coordinates":[146.775543,-19.271448],"type":"Point"}
}