{
  "type": "Feature",
  "properties": {
    "addr:full":"2 Fenwick Crs Goulburn NSW 2580",
    "addr:housenumber":"2",
    "addr:postcode":"2580",
    "addr:street":"Fenwick Crs",
    "iso:country":"AU",
    "sg:address":"2 Fenwick Crs",
    "sg:city":"Goulburn",
    "sg:classifiers":[
        {
            "category":"Autos & Motor Vehicles",
            "subcategory":"Automobile Sales",
            "type":"Retail Goods"
        }
    ],
    "sg:phone":"+61 2 4822 4900",
    "sg:postcode":"2580",
    "sg:province":"NSW",
    "sg:tags":[
        "car",
        "used"
    ],
    "wof:name":"Goulburn Wholesale Cars & Commercials",
    "wof:placetype":"venue"
},
  "geometry": {"coordinates":[149.663986206,-34.6597213745],"type":"Point"}
}