{
  "type": "Feature",
  "properties": {
    "iso:country":"AU",
    "sg:address":"19 Fairbank Crt",
    "sg:city":"Bentleigh",
    "sg:classifiers":[
        {
            "category":"Autos & Motor Vehicles",
            "subcategory":"Auto Supplies",
            "type":"Retail Goods"
        }
    ],
    "sg:phone":"+61 3 9557 6356",
    "sg:postcode":"3204",
    "sg:province":"VIC",
    "sg:tags":[
        "equipment",
        "part",
        "truck"
    ],
    "wof:name":"DriveLine Imports Australia Pty Ltd",
    "wof:placetype":"venue"
},
  "geometry": {"coordinates":[145.04196200000001,-37.932667],"type":"Point"}
}