{
  "type": "Feature",
  "properties": {
    "iso:country":"AU",
    "sg:address":"16 May St",
    "sg:city":"Dulwich Hill",
    "sg:classifiers":[
        {
            "category":"Education",
            "subcategory":"School",
            "type":"Public Place"
        }
    ],
    "sg:phone":"+61 2 9558 5308",
    "sg:postcode":"2203",
    "sg:province":"NSW",
    "wof:name":"St Pauls School",
    "wof:placetype":"venue"
},
  "geometry": {"coordinates":[151.13458299999999,-33.905243],"type":"Point"}
}