{
  "type": "Feature",
  "properties": {
    "addr:full":"Unit 10 / 25 Hargrave St Tamworth NSW 2340",
    "addr:housenumber":"/ 25",
    "addr:postcode":"2340",
    "addr:street":"Hargrave St",
    "iso:country":"AU",
    "sg:address":"Unit 10 / 25 Hargrave St",
    "sg:city":"Tamworth",
    "sg:classifiers":[
        {
            "category":"Manufacturing",
            "subcategory":"Tools & Machinery",
            "type":"Manufacturing & Wholesale Goods"
        }
    ],
    "sg:phone":"+61 2 6765 4818",
    "sg:postcode":"2340",
    "sg:province":"NSW",
    "sg:tags":[
        "equipment",
        "scale",
        "weighing"
    ],
    "wof:name":"Avery Tamworth",
    "wof:placetype":"venue"
},
  "geometry": {"coordinates":[150.901153564,-31.096824646],"type":"Point"}
}