{
  "type": "Feature",
  "properties": {
    "addr:full":"29 Horton St Port Macquarie NSW 2444",
    "addr:housenumber":"29",
    "addr:postcode":"2444",
    "addr:street":"Horton St",
    "iso:country":"AU",
    "sg:address":"29 Horton St",
    "sg:city":"Port Macquarie",
    "sg:classifiers":[
        {
            "category":"Health Services",
            "subcategory":"Optometrist",
            "type":"Services"
        }
    ],
    "sg:phone":"+61 2 6584 3948",
    "sg:postcode":"2444",
    "sg:province":"NSW",
    "wof:name":"Farmer C",
    "wof:placetype":"venue"
},
  "geometry": {"coordinates":[152.908005,-31.429247],"type":"Point"}
}