{
  "type": "Feature",
  "properties": {
    "iso:country":"AU",
    "sg:address":"173 Arthur Kaine Drv",
    "sg:city":"Pambula",
    "sg:classifiers":[
        {
            "category":"Retail",
            "subcategory":"Event Space",
            "type":"Services"
        }
    ],
    "sg:phone":"+61 2 6495 6154",
    "sg:postcode":"2549",
    "sg:province":"NSW",
    "sg:tags":[
        "venue",
        "reception",
        "wedding"
    ],
    "wof:name":"Pambula-Merimbula Golf Club",
    "wof:placetype":"venue"
},
  "geometry": {"coordinates":[149.87986755399999,-36.9296684265],"type":"Point"}
}