{
  "type": "Feature",
  "properties": {
    "addr:full":"53 Albert St Creswick VIC 3363",
    "addr:housenumber":"53",
    "addr:postcode":"3363",
    "addr:street":"Albert St",
    "iso:country":"AU",
    "sg:address":"53 Albert St",
    "sg:city":"Creswick",
    "sg:classifiers":[
        {
            "category":"Cafe",
            "type":"Food & Drink"
        }
    ],
    "sg:phone":"+61 3 5345 1559",
    "sg:postcode":"3363",
    "sg:province":"VIC",
    "wof:name":"Persephone's Garden",
    "wof:placetype":"venue"
},
  "geometry": {"coordinates":[143.89483642600001,-37.4229431152],"type":"Point"}
}