{
  "type": "Feature",
  "properties": {
    "addr:full":"PO Box 524 Echuca VIC 3564",
    "addr:postcode":"3564",
    "iso:country":"AU",
    "sg:address":"PO Box 524",
    "sg:city":"Echuca",
    "sg:classifiers":[
        {
            "category":"Health Services",
            "subcategory":"Doctor",
            "type":"Services"
        }
    ],
    "sg:phone":"+61 419 122 275",
    "sg:postcode":"3564",
    "sg:province":"VIC",
    "sg:tags":[
        "reflexology"
    ],
    "wof:name":"Thrive Natural Therapies",
    "wof:placetype":"venue"
},
  "geometry": {"coordinates":[144.74836730999999,-36.1293907166],"type":"Point"}
}