{
  "type": "Feature",
  "properties": {
    "iso:country":"AU",
    "sg:address":"7b John St",
    "sg:city":"Lidcombe",
    "sg:classifiers":[
        {
            "category":"Real Estate",
            "subcategory":"Real Estate Agent",
            "type":"Services"
        }
    ],
    "sg:phone":"+61 2 9749 1886",
    "sg:postcode":"2141",
    "sg:province":"NSW",
    "wof:name":"J & L Realty",
    "wof:placetype":"venue"
},
  "geometry": {"coordinates":[151.044677734,-33.8629608154],"type":"Point"}
}