{
  "type": "Feature",
  "properties": {
    "addr:full":"151 Mc Kean St Fitzroy North VIC 3068",
    "addr:housenumber":"151",
    "addr:postcode":"3068",
    "addr:street":"Mc Kean St",
    "iso:country":"AU",
    "sg:address":"151 Mc Kean St",
    "sg:city":"Fitzroy North",
    "sg:classifiers":[
        {
            "category":"Real Estate",
            "subcategory":"Architect",
            "type":"Services"
        }
    ],
    "sg:phone":"+61 3 9489 8492",
    "sg:postcode":"3068",
    "sg:province":"VIC",
    "wof:name":"Willingham A F",
    "wof:placetype":"venue"
},
  "geometry": {"coordinates":[144.98768615700001,-37.7883529663],"type":"Point"}
}