{
  "type": "Feature",
  "properties": {
    "iso:country":"AU",
    "sg:address":"139- 141 Koornang Rd",
    "sg:city":"Carnegie",
    "sg:classifiers":[
        {
            "category":"Real Estate",
            "subcategory":"Real Estate Agent",
            "type":"Services"
        }
    ],
    "sg:phone":"+61 418 328 218",
    "sg:postcode":"3163",
    "sg:province":"VIC",
    "wof:name":"Hodges",
    "wof:placetype":"venue"
},
  "geometry": {"coordinates":[145.05696105999999,-37.8889579773],"type":"Point"}
}