{
  "type": "Feature",
  "properties": {
    "iso:country":"AU",
    "sg:address":"37-39 Elliott Rd",
    "sg:city":"Dandenong",
    "sg:classifiers":[
        {
            "category":"Building & Trades",
            "subcategory":"Landscaping Services",
            "type":"Services"
        }
    ],
    "sg:phone":"+61 3 9701 7305",
    "sg:postcode":"3175",
    "sg:province":"VIC",
    "sg:tags":[
        "horticultural",
        "consultant"
    ],
    "wof:name":"Girotto Technology Pty Ltd",
    "wof:placetype":"venue"
},
  "geometry": {"coordinates":[145.20692443900001,-38.0230140686],"type":"Point"}
}