{
  "type": "Feature",
  "properties": {
    "addr:full":"83 Taunton Drive, Cheltenham VIC 3192",
    "addr:housenumber":"83",
    "addr:postcode":"3192",
    "addr:street":"Taunton Drive",
    "iso:country":"AU",
    "sg:address":"83 Taunton Drive,",
    "sg:city":"Cheltenham",
    "sg:classifiers":[
        {
            "category":"Shopping",
            "subcategory":"Gifts & Souvenirs",
            "type":"Retail Goods"
        }
    ],
    "sg:phone":"+61 3 9583 3499",
    "sg:postcode":"3192",
    "sg:province":"VIC",
    "sg:tags":[
        "wrapping"
    ],
    "sg:website":"http://www.barama.com.au",
    "wof:name":"Barama",
    "wof:placetype":"venue"
},
  "geometry": {"coordinates":[145.08357238799999,-37.9691009521],"type":"Point"}
}