{
  "type": "Feature",
  "properties": {
    "addr:full":"210 Beechworth Rd Wodonga VIC 3690",
    "addr:housenumber":"210",
    "addr:postcode":"3690",
    "addr:street":"Beechworth Rd",
    "iso:country":"AU",
    "sg:address":"210 Beechworth Rd",
    "sg:city":"Wodonga",
    "sg:classifiers":[
        {
            "category":"Professional",
            "subcategory":"Engineering",
            "type":"Services"
        }
    ],
    "sg:phone":"+61 2 6056 2242",
    "sg:postcode":"3690",
    "sg:province":"VIC",
    "sg:tags":[
        "consulting",
        "engineer"
    ],
    "wof:name":"Gordon Gibson Nominees Pty Ltd",
    "wof:placetype":"venue"
},
  "geometry": {"coordinates":[146.88548278799999,-36.1244735718],"type":"Point"}
}