{
  "type": "Feature",
  "properties": {
    "iso:country":"AU",
    "sg:address":"205 Railway Rd",
    "sg:city":"Subiaco",
    "sg:classifiers":[
        {
            "category":"Professional",
            "subcategory":"Detective & Security Services",
            "type":"Services"
        }
    ],
    "sg:phone":"+61 8 9381 6711",
    "sg:postcode":"6008",
    "sg:province":"WA",
    "sg:tags":[
        "guard",
        "patrol"
    ],
    "sg:website":"http://www.baxsecurity.com.au",
    "wof:name":"Baxendale Securities.",
    "wof:placetype":"venue"
},
  "geometry": {"coordinates":[115.813056946,-31.9525375366],"type":"Point"}
}