{
  "type": "Feature",
  "properties": {
    "addr:full":"260 Pier St Perth WA 6000",
    "addr:housenumber":"260",
    "addr:postcode":"6000",
    "addr:street":"Pier St",
    "iso:country":"AU",
    "sg:address":"260 Pier St",
    "sg:city":"Perth",
    "sg:classifiers":[
        {
            "category":"Health Services",
            "subcategory":"Doctor",
            "type":"Services"
        }
    ],
    "sg:phone":"+61 8 9218 9444",
    "sg:postcode":"6000",
    "sg:province":"WA",
    "sg:tags":[
        "nurse",
        "nursing"
    ],
    "wof:name":"Australian Nursing Federation",
    "wof:placetype":"venue"
},
  "geometry": {"coordinates":[115.86627960200001,-31.9488143921],"type":"Point"}
}