{
  "type": "Feature",
  "properties": {
    "addr:full":"Shop 47 Adelaide Arc Adelaide SA 5000",
    "addr:housenumber":"shop 47",
    "addr:postcode":"5000",
    "addr:street":"Adelaide Arc",
    "iso:country":"AU",
    "sg:address":"Shop 47 Adelaide Arc",
    "sg:city":"Adelaide",
    "sg:classifiers":[
        {
            "category":"Shopping",
            "subcategory":"Clothing, Apparel, & Fashions",
            "type":"Retail Goods"
        }
    ],
    "sg:phone":"+61 8 8224 0131",
    "sg:postcode":"5000",
    "sg:province":"SA",
    "sg:tags":[
        "millinery"
    ],
    "wof:name":"Adelaide Hatters",
    "wof:placetype":"venue"
},
  "geometry": {"coordinates":[138.603683472,-34.9234390259],"type":"Point"}
}