{
  "type": "Feature",
  "properties": {
    "addr:full":"Hoddle St Burrawang NSW 2577",
    "addr:postcode":"2577",
    "addr:street":"Hoddle St",
    "iso:country":"AU",
    "sg:address":"Hoddle St",
    "sg:city":"Burrawang",
    "sg:classifiers":[
        {
            "category":"Travel",
            "subcategory":"Hotels & Motels",
            "type":"Entertainment"
        }
    ],
    "sg:phone":"+61 2 4886 4206",
    "sg:postcode":"2577",
    "sg:province":"NSW",
    "sg:tags":[
        "accommodation"
    ],
    "wof:name":"Burrawang Village Hotel",
    "wof:placetype":"venue"
},
  "geometry": {"coordinates":[150.519729614,-34.593421936],"type":"Point"}
}