{
  "type": "Feature",
  "properties": {
    "addr:full":"10 Longworth Ave Cardiff NSW 2285",
    "addr:housenumber":"10",
    "addr:postcode":"2285",
    "addr:street":"Longworth Ave",
    "iso:country":"AU",
    "sg:address":"10 Longworth Ave",
    "sg:city":"Cardiff",
    "sg:classifiers":[
        {
            "category":"Building & Trades",
            "subcategory":"Construction",
            "type":"Services"
        }
    ],
    "sg:phone":"+61 401 352 645",
    "sg:postcode":"2285",
    "sg:province":"NSW",
    "sg:tags":[
        "earth",
        "excavating",
        "moving",
        "contractor"
    ],
    "wof:name":"R & G Crawford",
    "wof:placetype":"venue"
},
  "geometry": {"coordinates":[151.663040161,-32.9306983948],"type":"Point"}
}