{
  "type": "Feature",
  "properties": {
    "addr:full":"54 Salisbury Ave Valley View SA 5093",
    "addr:housenumber":"54",
    "addr:postcode":"5093",
    "addr:street":"Salisbury Ave",
    "iso:country":"AU",
    "sg:address":"54 Salisbury Ave",
    "sg:city":"Valley View",
    "sg:classifiers":[
        {
            "category":"Professional",
            "subcategory":"Art Services",
            "type":"Services"
        }
    ],
    "sg:phone":"+61 8 8264 4768",
    "sg:postcode":"5093",
    "sg:province":"SA",
    "sg:tags":[
        "decorator",
        "painter"
    ],
    "wof:name":"Tilley Garey D",
    "wof:placetype":"venue"
},
  "geometry": {"coordinates":[138.67434692399999,-34.8359260559],"type":"Point"}
}