{
  "type": "Feature",
  "properties": {
    "addr:full":"115 Coles Rd Three Bridges VIC 3797",
    "addr:housenumber":"115",
    "addr:postcode":"3797",
    "addr:street":"Coles Rd",
    "iso:country":"AU",
    "sg:address":"115 Coles Rd",
    "sg:city":"Three Bridges",
    "sg:classifiers":[
        {
            "category":"Manufacturing",
            "subcategory":"Musical Instruments",
            "type":"Manufacturing & Wholesale Goods"
        }
    ],
    "sg:phone":"+61 3 5966 6356",
    "sg:postcode":"3797",
    "sg:province":"VIC",
    "sg:tags":[
        "logging",
        "timber"
    ],
    "wof:name":"McConachy P C & B J Pty Ltd",
    "wof:placetype":"venue"
},
  "geometry": {"coordinates":[145.684646606,-37.8394584656],"type":"Point"}
}