{
  "type": "Feature",
  "properties": {
    "iso:country":"AU",
    "sg:address":"Cnr South Rd & Tikala St",
    "sg:city":"Regency Park",
    "sg:classifiers":[
        {
            "category":"Manufacturing",
            "subcategory":"Rubber & Plastics",
            "type":"Manufacturing & Wholesale Goods"
        }
    ],
    "sg:phone":"+61 8 8348 2237",
    "sg:postcode":"5010",
    "sg:province":"SA",
    "sg:tags":[
        "wholesaler",
        "product",
        "mfrs"
    ],
    "wof:name":"Ludowici Rubber & Plastics",
    "wof:placetype":"venue"
},
  "geometry": {"coordinates":[138.566894531,-34.859462738],"type":"Point"}
}