{
  "type": "Feature",
  "properties": {
    "addr:full":"62 Alma St St Arnaud VIC 3478",
    "addr:housenumber":"62",
    "addr:postcode":"3478",
    "addr:street":"Alma St",
    "iso:country":"AU",
    "sg:address":"62 Alma St",
    "sg:city":"St Arnaud",
    "sg:classifiers":[
        {
            "category":"Building & Trades",
            "subcategory":"Construction",
            "type":"Services"
        }
    ],
    "sg:phone":"+61 3 5495 1696",
    "sg:postcode":"3478",
    "sg:province":"VIC",
    "sg:tags":[
        "contractor"
    ],
    "wof:name":"P J & A J Tyler Builders",
    "wof:placetype":"venue"
},
  "geometry": {"coordinates":[143.24945068400001,-36.6172332764],"type":"Point"}
}