{
  "type": "Feature",
  "properties": {
    "addr:full":"36 Kalang Rd Edensor Park NSW 2176",
    "addr:housenumber":"36",
    "addr:postcode":"2176",
    "addr:street":"Kalang Rd",
    "iso:country":"AU",
    "sg:address":"36 Kalang Rd",
    "sg:city":"Edensor Park",
    "sg:classifiers":[
        {
            "category":"Building & Trades",
            "subcategory":"Pest Control",
            "type":"Services"
        }
    ],
    "sg:phone":"+61 2 9823 5939",
    "sg:postcode":"2176",
    "sg:province":"NSW",
    "wof:name":"Crackdown Pest Control",
    "wof:placetype":"venue"
},
  "geometry": {"coordinates":[150.86863708499999,-33.8818893433],"type":"Point"}
}