{
  "type": "Feature",
  "properties": {
    "addr:full":"11 Nellbern Rd Moorabbin VIC 3189",
    "addr:housenumber":"11",
    "addr:postcode":"3189",
    "addr:street":"Nellbern Rd",
    "iso:country":"AU",
    "sg:address":"11 Nellbern Rd",
    "sg:city":"Moorabbin",
    "sg:classifiers":[
        {
            "category":"Wholesale",
            "subcategory":"Machinery & Supplies",
            "type":"Manufacturing & Wholesale Goods"
        }
    ],
    "sg:phone":"+61 3 9555 2350",
    "sg:postcode":"3189",
    "sg:province":"VIC",
    "sg:tags":[
        "equipment",
        "welding"
    ],
    "wof:name":"Jugs Australia",
    "wof:placetype":"venue"
},
  "geometry": {"coordinates":[145.066482544,-37.9382362366],"type":"Point"}
}