{
  "type": "Feature",
  "properties": {
    "addr:full":"177 Woolaware Rd Cronulla NSW 2230",
    "addr:housenumber":"177",
    "addr:postcode":"2230",
    "addr:street":"Woolaware Rd",
    "iso:country":"AU",
    "sg:address":"177 Woolaware Rd",
    "sg:city":"Cronulla",
    "sg:classifiers":[
        {
            "category":"Shopping",
            "subcategory":"Stationery & Office Supplies",
            "type":"Retail Goods"
        }
    ],
    "sg:phone":"+61 2 9523 6943",
    "sg:postcode":"2230",
    "sg:province":"NSW",
    "sg:tags":[
        "packaging",
        "material"
    ],
    "wof:name":"D.R.P. Cartons (NSW)",
    "wof:placetype":"venue"
},
  "geometry": {"coordinates":[151.13949585,-34.0565071106],"type":"Point"}
}