{
  "type": "Feature",
  "properties": {
    "iso:country":"AU",
    "sg:address":"19 Noordenne Ave",
    "sg:city":"Seaholme",
    "sg:classifiers":[
        {
            "category":"Home & Garden",
            "subcategory":"Building Materials",
            "type":"Retail Goods"
        }
    ],
    "sg:phone":"+61 3 9398 3200",
    "sg:postcode":"3018",
    "sg:province":"VIC",
    "sg:tags":[
        "merchant",
        "glass",
        "glazier"
    ],
    "wof:name":"Hobsons Bay Glass & Glazing",
    "wof:placetype":"venue"
},
  "geometry": {"coordinates":[144.84489440900001,-37.8597869873],"type":"Point"}
}