{
  "type": "Feature",
  "properties": {
    "iso:country":"AU",
    "sg:address":"24 Sharp Crt",
    "sg:city":"Cavan",
    "sg:classifiers":[
        {
            "category":"Structure",
            "subcategory":"Factory",
            "type":"Public Place"
        }
    ],
    "sg:phone":"+61 8 8359 7600",
    "sg:postcode":"5094",
    "sg:province":"SA",
    "sg:tags":[
        "seating",
        "system"
    ],
    "wof:name":"Pro Stage Australia Pty Ltd",
    "wof:placetype":"venue"
},
  "geometry": {"coordinates":[138.607696533,-34.8232002258],"type":"Point"}
}