{
  "type": "Feature",
  "properties": {
    "addr:full":"102 Mornington St Geelong North VIC 3215",
    "addr:housenumber":"102",
    "addr:postcode":"3215",
    "addr:street":"Mornington St",
    "iso:country":"AU",
    "sg:address":"102 Mornington St",
    "sg:city":"Geelong North",
    "sg:classifiers":[
        {
            "category":"Autos & Motor Vehicles",
            "subcategory":"Auto Supplies",
            "type":"Retail Goods"
        }
    ],
    "sg:phone":"+61 3 5278 2953",
    "sg:postcode":"3215",
    "sg:province":"VIC",
    "sg:tags":[
        "tyre"
    ],
    "wof:name":"Craddock Rob Tyre Service",
    "wof:placetype":"venue"
},
  "geometry": {"coordinates":[144.34840393100001,-38.1133308411],"type":"Point"}
}