{
  "type": "Feature",
  "properties": {
    "addr:full":"128 Main North Rd Prospect SA 5082",
    "addr:housenumber":"128",
    "addr:postcode":"5082",
    "addr:street":"Main North Rd",
    "iso:country":"AU",
    "sg:address":"128 Main North Rd",
    "sg:city":"Prospect",
    "sg:classifiers":[
        {
            "category":"Shopping",
            "subcategory":"Party Supplies",
            "type":"Retail Goods"
        }
    ],
    "sg:phone":"+61 8 8344 4339",
    "sg:postcode":"5082",
    "sg:province":"SA",
    "wof:name":"The Party Superstore",
    "wof:placetype":"venue"
},
  "geometry": {"coordinates":[138.60276794399999,-34.887752533],"type":"Point"}
}