{
  "type": "Feature",
  "properties": {
    "addr:full":"Fourth St Katherine NT 0850",
    "addr:postcode":"nt 0850",
    "addr:street":"Fourth",
    "iso:country":"AU",
    "sg:address":"Fourth St",
    "sg:city":"Katherine",
    "sg:classifiers":[
        {
            "category":"Wholesale",
            "subcategory":"Painting Supplies",
            "type":"Manufacturing & Wholesale Goods"
        }
    ],
    "sg:phone":"+61 8 8972 1988",
    "sg:postcode":"0850",
    "sg:province":"NT",
    "sg:tags":[
        "equipment",
        "spraying"
    ],
    "wof:name":"B.C. Machinery",
    "wof:placetype":"venue"
},
  "geometry": {"coordinates":[132.26608300000001,-14.460288],"type":"Point"}
}