{
  "type": "Feature",
  "properties": {
    "iso:country":"AU",
    "sg:address":"19 Albert Rd",
    "sg:city":"Drouin",
    "sg:classifiers":[
        {
            "category":"Health Services",
            "subcategory":"Doctor",
            "type":"Services"
        }
    ],
    "sg:phone":"+61 3 5625 3355",
    "sg:postcode":"3818",
    "sg:province":"VIC",
    "sg:tags":[
        "medical",
        "practitioner"
    ],
    "wof:name":"Atapattu Paba Dr",
    "wof:placetype":"venue"
},
  "geometry": {"coordinates":[145.854401,-38.129459],"type":"Point"}
}