{
  "type": "Feature",
  "properties": {
    "addr:full":"PO Box 3330 Midland WA 6056",
    "addr:postcode":"6056",
    "iso:country":"AU",
    "sg:address":"PO Box 3330",
    "sg:city":"Midland",
    "sg:classifiers":[
        {
            "category":"Building & Trades",
            "subcategory":"Construction",
            "type":"Services"
        }
    ],
    "sg:phone":"+61 418 902 545",
    "sg:postcode":"6056",
    "sg:province":"WA",
    "sg:tags":[
        "repair",
        "maintenance",
        "contractor"
    ],
    "wof:name":"Essex Maintenance",
    "wof:placetype":"venue"
},
  "geometry": {"coordinates":[116.009643555,-31.8911304474],"type":"Point"}
}