{
  "type": "Feature",
  "properties": {
    "addr:full":"Bath La Bendigo VIC 3539",
    "addr:postcode":"3539",
    "iso:country":"AU",
    "sg:address":"Bath La",
    "sg:city":"Bendigo",
    "sg:classifiers":[
        {
            "category":"Travel",
            "subcategory":"Travel Agent",
            "type":"Entertainment"
        }
    ],
    "sg:phone":"+61 3 5442 1522",
    "sg:postcode":"3539",
    "sg:province":"VIC",
    "sg:tags":[
        "consultant"
    ],
    "wof:name":"Travelscene American Express",
    "wof:placetype":"venue"
},
  "geometry": {"coordinates":[144.28143299999999,-36.757511],"type":"Point"}
}