{
  "type": "Feature",
  "properties": {
    "addr:full":"40 Gladstone St Fyshwick ACT 2609",
    "addr:housenumber":"40",
    "addr:postcode":"2609",
    "addr:street":"Gladstone St",
    "iso:country":"AU",
    "sg:address":"40 Gladstone St",
    "sg:city":"Fyshwick",
    "sg:classifiers":[
        {
            "category":"Home & Garden",
            "subcategory":"Carpets & Floor Coverings",
            "type":"Retail Goods"
        }
    ],
    "sg:phone":"+61 2 6228 1066",
    "sg:postcode":"2609",
    "sg:province":"ACT",
    "wof:name":"Canberra Ceramics",
    "wof:placetype":"venue"
},
  "geometry": {"coordinates":[149.174926758,-35.322303772],"type":"Point"}
}