{
  "type": "Feature",
  "properties": {
    "addr:full":"251 George St Liverpool NSW 2170",
    "addr:housenumber":"251",
    "addr:postcode":"2170",
    "addr:street":"George St",
    "iso:country":"AU",
    "sg:address":"251 George St",
    "sg:city":"Liverpool",
    "sg:classifiers":[
        {
            "category":"Food & Beverages",
            "subcategory":"Specialty",
            "type":"Retail Goods"
        }
    ],
    "sg:phone":"+61 2 9602 7584",
    "sg:postcode":"2170",
    "sg:province":"NSW",
    "sg:tags":[
        "product",
        "health"
    ],
    "wof:name":"Vita Plus",
    "wof:placetype":"venue"
},
  "geometry": {"coordinates":[150.924438477,-33.9242744446],"type":"Point"}
}