{
  "type": "Feature",
  "properties": {
    "addr:full":"Suite 3 60 Bryants Rd Loganholme QLD 4129",
    "addr:housenumber":"60",
    "addr:postcode":"4129",
    "addr:street":"Bryants Rd",
    "iso:country":"AU",
    "sg:address":"Suite 3 60 Bryants Rd",
    "sg:city":"Loganholme",
    "sg:classifiers":[
        {
            "category":"Insurance",
            "subcategory":"Insurance Agent",
            "type":"Services"
        }
    ],
    "sg:phone":"+61 7 3388 0670",
    "sg:postcode":"4129",
    "sg:province":"QLD",
    "wof:name":"Living Financial Services",
    "wof:placetype":"venue"
},
  "geometry": {"coordinates":[153.176391602,-27.6626358032],"type":"Point"}
}