{
  "type": "Feature",
  "properties": {
    "addr:full":"352 - 354 Princes Hwy Noble Park VIC 3174",
    "addr:housenumber":"354",
    "addr:postcode":"3174",
    "addr:street":"Princes Hwy",
    "iso:country":"AU",
    "sg:address":"352 - 354 Princes Hwy",
    "sg:city":"Noble Park",
    "sg:classifiers":[
        {
            "category":"Social Services",
            "subcategory":"Child Care",
            "type":"Services"
        }
    ],
    "sg:phone":"+61 3 9769 2053",
    "sg:postcode":"3174",
    "sg:province":"VIC",
    "wof:name":"Top Start Early Learning Centre",
    "wof:placetype":"venue"
},
  "geometry": {"coordinates":[145.19143676799999,-37.9637145996],"type":"Point"}
}