{
  "type": "Feature",
  "properties": {
    "iso:country":"AU",
    "sg:address":"36 Grantham St",
    "sg:city":"Brunswick West",
    "sg:classifiers":[
        {
            "category":"Travel",
            "subcategory":"Travel Agent",
            "type":"Entertainment"
        }
    ],
    "sg:phone":"+61 3 9380 8933",
    "sg:postcode":"3055",
    "sg:province":"VIC",
    "sg:tags":[
        "consultant"
    ],
    "wof:name":"Brunswick Travel & Tour",
    "wof:placetype":"venue"
},
  "geometry": {"coordinates":[144.94952392600001,-37.7724761963],"type":"Point"}
}