{
  "type": "Feature",
  "properties": {
    "addr:full":"Imperial Arcade 83 Castlereagh St Sydney NSW 2000",
    "addr:housenumber":"83",
    "addr:postcode":"2000",
    "addr:street":"Castlereagh St",
    "iso:country":"AU",
    "sg:address":"Imperial Arcade 83 Castlereagh St",
    "sg:city":"Sydney",
    "sg:classifiers":[
        {
            "category":"Shopping",
            "subcategory":"Clothing, Apparel, & Fashions",
            "type":"Retail Goods"
        }
    ],
    "sg:phone":"+61 2 9221 3237",
    "sg:postcode":"2000",
    "sg:province":"NSW",
    "sg:tags":[
        "lady",
        "wear"
    ],
    "wof:name":"Double Bay Clothing Warehouse",
    "wof:placetype":"venue"
},
  "geometry": {"coordinates":[151.209442139,-33.8697052002],"type":"Point"}
}