{
  "type": "Feature",
  "properties": {
    "iso:country":"AU",
    "sg:address":"251 West Coast Hwy",
    "sg:city":"Scarborough",
    "sg:classifiers":[
        {
            "category":"Travel",
            "subcategory":"Hotels & Motels",
            "type":"Entertainment"
        }
    ],
    "sg:phone":"+61 8 9341 6122",
    "sg:postcode":"6019",
    "sg:province":"WA",
    "wof:name":"West Beach Lagoon",
    "wof:placetype":"venue"
},
  "geometry": {"coordinates":[115.758079529,-31.8982906342],"type":"Point"}
}