{
  "type": "Feature",
  "properties": {
    "addr:full":"Kiosk 3A, Stockland Wetherill Park, Polding St Wetherill Park NSW 2164",
    "addr:housenumber":"3a",
    "addr:postcode":"2164",
    "addr:street":"Polding St",
    "iso:country":"AU",
    "sg:address":"Kiosk 3A, Stockland Wetherill Park, Polding St",
    "sg:city":"Wetherill Park",
    "sg:classifiers":[
        {
            "category":"Shopping",
            "subcategory":"Mobile Phones",
            "type":"Retail Goods"
        }
    ],
    "sg:phone":"+61 2 9604 9855",
    "sg:postcode":"2164",
    "sg:province":"NSW",
    "sg:tags":[
        "telephone",
        "accessory"
    ],
    "wof:name":"TeleChoice",
    "wof:placetype":"venue"
},
  "geometry": {"coordinates":[150.916915894,-33.8568878174],"type":"Point"}
}