{
  "type": "Feature",
  "properties": {
    "addr:full":"208 Dangar St Armidale NSW 2350",
    "addr:housenumber":"208",
    "addr:postcode":"2350",
    "addr:street":"Dangar St",
    "iso:country":"AU",
    "sg:address":"208 Dangar St",
    "sg:city":"Armidale",
    "sg:classifiers":[
        {
            "category":"Retail",
            "subcategory":"Event Space",
            "type":"Services"
        }
    ],
    "sg:phone":"+61 2 6772 9800",
    "sg:postcode":"2350",
    "sg:province":"NSW",
    "sg:tags":[
        "venue",
        "reception",
        "wedding"
    ],
    "wof:name":"Armidale Regency Hallmark Inn",
    "wof:placetype":"venue"
},
  "geometry": {"coordinates":[151.66163635300001,-30.5229034424],"type":"Point"}
}