{
  "type": "Feature",
  "properties": {
    "iso:country":"AU",
    "sg:address":"PO Box 1943",
    "sg:city":"Bakery Hill",
    "sg:classifiers":[
        {
            "category":"Professional",
            "subcategory":"Detective & Security Services",
            "type":"Services"
        }
    ],
    "sg:phone":"+61 3 5330 7048",
    "sg:postcode":"3354",
    "sg:province":"VIC",
    "sg:tags":[
        "guard",
        "patrol"
    ],
    "wof:name":"Sovereign Protective Services",
    "wof:placetype":"venue"
},
  "geometry": {"coordinates":[143.863708,-37.56332],"type":"Point"}
}