{
  "type": "Feature",
  "properties": {
    "addr:full":"33 Shelley St Tea Tree Gully SA 5091",
    "addr:housenumber":"33",
    "addr:postcode":"5091",
    "addr:street":"Shelley St",
    "iso:country":"AU",
    "sg:address":"33 Shelley St",
    "sg:city":"Tea Tree Gully",
    "sg:classifiers":[
        {
            "category":"Retail",
            "subcategory":"Repair Shop",
            "type":"Services"
        }
    ],
    "sg:phone":"+61 8 8264 6436",
    "sg:postcode":"5091",
    "sg:province":"SA",
    "sg:tags":[
        "machine",
        "repairs",
        "part",
        "dryer",
        "washing"
    ],
    "wof:name":"Beaumonts Washing Machines",
    "wof:placetype":"venue"
},
  "geometry": {"coordinates":[138.72157287600001,-34.8182067871],"type":"Point"}
}