{
  "type": "Feature",
  "properties": {
    "addr:full":"4 Victoria Rd Hawthorn East VIC 3123",
    "addr:housenumber":"4",
    "addr:postcode":"3123",
    "addr:street":"Victoria Rd",
    "iso:country":"AU",
    "sg:address":"4 Victoria Rd",
    "sg:city":"Hawthorn East",
    "sg:classifiers":[
        {
            "category":"Professional",
            "subcategory":"Engineering",
            "type":"Services"
        }
    ],
    "sg:phone":"+61 3 9882 3242",
    "sg:postcode":"3123",
    "sg:province":"VIC",
    "sg:tags":[
        "engineer",
        "mechanical"
    ],
    "wof:name":"A & F Driveshaft Repair",
    "wof:placetype":"venue"
},
  "geometry": {"coordinates":[145.046386719,-37.8221817017],"type":"Point"}
}