{
  "type": "Feature",
  "properties": {
    "iso:country":"AU",
    "sg:address":"11 Hallett St",
    "sg:city":"Kadina",
    "sg:classifiers":[
        {
            "category":"Professional",
            "subcategory":"Employment Agencies",
            "type":"Services"
        }
    ],
    "sg:phone":"+61 8 8821 2513",
    "sg:postcode":"5554",
    "sg:province":"SA",
    "sg:tags":[
        "hire",
        "labour",
        "contractor"
    ],
    "wof:name":"Crew2u",
    "wof:placetype":"venue"
},
  "geometry": {"coordinates":[137.71267700199999,-33.9627227783],"type":"Point"}
}