{
  "type": "Feature",
  "properties": {
    "addr:full":"245 High St Preston VIC 3072",
    "addr:housenumber":"245",
    "addr:postcode":"3072",
    "addr:street":"High St",
    "iso:country":"AU",
    "sg:address":"245 High St",
    "sg:city":"Preston",
    "sg:classifiers":[
        {
            "category":"Shopping",
            "subcategory":"Mobile Phones",
            "type":"Retail Goods"
        }
    ],
    "sg:phone":"+61 3 9484 9444",
    "sg:postcode":"3072",
    "sg:province":"VIC",
    "sg:tags":[
        "telephone",
        "accessory"
    ],
    "wof:name":"Optus World",
    "wof:placetype":"venue"
},
  "geometry": {"coordinates":[145.002975464,-37.7433204651],"type":"Point"}
}