{
  "type": "Feature",
  "properties": {
    "iso:country":"AU",
    "sg:address":"329 Oxford St",
    "sg:city":"Leederville",
    "sg:classifiers":[
        {
            "category":"Health Services",
            "subcategory":"Doctor",
            "type":"Services"
        }
    ],
    "sg:phone":"+61 8 9444 3700",
    "sg:postcode":"6007",
    "sg:province":"WA",
    "sg:tags":[
        "medical",
        "practitioner"
    ],
    "wof:name":"Martin Sue Dr",
    "wof:placetype":"venue"
},
  "geometry": {"coordinates":[115.841072083,-31.9280147552],"type":"Point"}
}