{
  "type": "Feature",
  "properties": {
    "iso:country":"AU",
    "sg:address":"G10A Peninsula Fair Anzac Ave",
    "sg:city":"Kippa-Ring",
    "sg:classifiers":[
        {
            "category":"Shopping",
            "subcategory":"Clothing, Apparel, & Fashions",
            "type":"Retail Goods"
        }
    ],
    "sg:phone":"+61 7 3284 5144",
    "sg:postcode":"4021",
    "sg:province":"QLD",
    "sg:tags":[
        "lingerie",
        "hosiery",
        "sleepwear"
    ],
    "wof:name":"Mesmerize",
    "wof:placetype":"venue"
},
  "geometry": {"coordinates":[153.077881,-27.219027],"type":"Point"}
}