{
  "type": "Feature",
  "properties": {
    "addr:full":"12 Wilgah St Thomastown VIC 3074",
    "addr:housenumber":"12",
    "addr:postcode":"3074",
    "addr:street":"Wilgah St",
    "iso:country":"AU",
    "sg:address":"12 Wilgah St",
    "sg:city":"Thomastown",
    "sg:classifiers":[
        {
            "category":"Professional",
            "subcategory":"Accounting & Tax Preparation",
            "type":"Services"
        }
    ],
    "sg:phone":"+61 3 9464 2922",
    "sg:postcode":"3074",
    "sg:province":"VIC",
    "sg:tags":[
        "accountant",
        "auditor"
    ],
    "wof:name":"Cugno Frank & Co",
    "wof:placetype":"venue"
},
  "geometry": {"coordinates":[145.01968383799999,-37.6777763367],"type":"Point"}
}