{
  "type": "Feature",
  "properties": {
    "addr:full":"30 Bentley St Wetherill Park NSW 2164",
    "addr:housenumber":"30",
    "addr:postcode":"2164",
    "addr:street":"Bentley St",
    "iso:country":"AU",
    "sg:address":"30 Bentley St",
    "sg:city":"Wetherill Park",
    "sg:classifiers":[
        {
            "category":"Autos & Motor Vehicles",
            "subcategory":"Auto Supplies",
            "type":"Retail Goods"
        }
    ],
    "sg:phone":"+61 2 9756 4047",
    "sg:postcode":"2164",
    "sg:province":"NSW",
    "sg:tags":[
        "part",
        "cycles",
        "accessory"
    ],
    "wof:name":"Freedo Motors",
    "wof:placetype":"venue"
},
  "geometry": {"coordinates":[150.883636475,-33.845451355],"type":"Point"}
}