{
  "type": "Feature",
  "properties": {
    "addr:full":"Shop 30 Stockland Shellharbour Square Cntr Lakes Entrance Rd Barrack Heights NSW 2528",
    "addr:housenumber":"shop 30;shellharbour",
    "addr:postcode":"2528",
    "addr:street":"Square Cntr Lakes Entrance Rd",
    "iso:country":"AU",
    "sg:address":"Shop 30 Stockland Shellharbour Square Cntr Lakes Entrance Rd",
    "sg:city":"Barrack Heights",
    "sg:classifiers":[
        {
            "category":"Shopping",
            "subcategory":"Department Store",
            "type":"Retail Goods"
        }
    ],
    "sg:phone":"+61 2 4296 7566",
    "sg:postcode":"2528",
    "sg:province":"NSW",
    "wof:name":"Best & Less Retail Store",
    "wof:placetype":"venue"
},
  "geometry": {"coordinates":[150.859451294,-34.5582313538],"type":"Point"}
}