{
  "type": "Feature",
  "properties": {
    "addr:full":"21 Station St Bacchus Marsh VIC 3340",
    "addr:housenumber":"21",
    "addr:postcode":"3340",
    "addr:street":"Station St",
    "iso:country":"AU",
    "sg:address":"21 Station St",
    "sg:city":"Bacchus Marsh",
    "sg:classifiers":[
        {
            "category":"Professional",
            "subcategory":"Engineering",
            "type":"Services"
        }
    ],
    "sg:phone":"+61 3 5367 2599",
    "sg:postcode":"3340",
    "sg:province":"VIC",
    "sg:tags":[
        "engineer"
    ],
    "wof:name":"Marshall Engineering Pty Ltd",
    "wof:placetype":"venue"
},
  "geometry": {"coordinates":[144.44212300000001,-37.687668],"type":"Point"}
}