{
  "type": "Feature",
  "properties": {
    "iso:country":"AU",
    "sg:address":"19 Queensway St",
    "sg:city":"Upper Mt Gravatt",
    "sg:classifiers":[
        {
            "category":"Professional",
            "subcategory":"Employment Agencies",
            "type":"Services"
        }
    ],
    "sg:phone":"+61 7 3343 7093",
    "sg:postcode":"4122",
    "sg:province":"QLD",
    "sg:tags":[
        "provider",
        "internet"
    ],
    "wof:name":"Grafted Webdesign",
    "wof:placetype":"venue"
},
  "geometry": {"coordinates":[153.08836364699999,-27.5458431244],"type":"Point"}
}