{
  "type": "Feature",
  "properties": {
    "iso:country":"AU",
    "sg:address":"47 Anderson St",
    "sg:city":"Fortitude Valley",
    "sg:classifiers":[
        {
            "category":"Real Estate",
            "subcategory":"Architect",
            "type":"Services"
        }
    ],
    "sg:phone":"+61 7 3852 1299",
    "sg:postcode":"4006",
    "sg:province":"QLD",
    "wof:name":"Guymer Bailey Architects Pty Ltd",
    "wof:placetype":"venue"
},
  "geometry": {"coordinates":[153.03140258799999,-27.4525413513],"type":"Point"}
}