{
  "type": "Feature",
  "properties": {
    "addr:full":"3A Feathertop Ave Lower Templestowe VIC 3107",
    "addr:housenumber":"3a",
    "addr:postcode":"3107",
    "addr:street":"Feathertop Ave Lower",
    "iso:country":"AU",
    "sg:address":"3A Feathertop Ave",
    "sg:city":"Lower Templestowe",
    "sg:classifiers":[
        {
            "category":"Home & Garden",
            "subcategory":"Household Appliances",
            "type":"Retail Goods"
        }
    ],
    "sg:phone":"+61 3 9850 1343",
    "sg:postcode":"3107",
    "sg:province":"VIC",
    "sg:tags":[
        "heating",
        "system"
    ],
    "wof:name":"Gem Heating & Cooling",
    "wof:placetype":"venue"
},
  "geometry": {"coordinates":[145.10763549800001,-37.7666053772],"type":"Point"}
}