{
  "type": "Feature",
  "properties": {
    "iso:country":"AU",
    "sg:address":"Cnr Lancaster & Racecourse Rds",
    "sg:city":"Ascot",
    "sg:classifiers":[
        {
            "category":"Personal",
            "subcategory":"Beauty Salon",
            "type":"Services"
        }
    ],
    "sg:phone":"+61 7 3268 6897",
    "sg:postcode":"4007",
    "sg:province":"QLD",
    "sg:tags":[
        "hairdresser"
    ],
    "wof:name":"Haircut The",
    "wof:placetype":"venue"
},
  "geometry": {"coordinates":[153.0616,-27.430607],"type":"Point"}
}