{
  "type": "Feature",
  "properties": {
    "iso:country":"AU",
    "sg:address":"11 Twenty Second Ave",
    "sg:city":"Sawtell",
    "sg:classifiers":[
        {
            "category":"Sports & Exercise",
            "subcategory":"Playing Field",
            "type":"Entertainment"
        }
    ],
    "sg:phone":"+61 2 6658 4980",
    "sg:postcode":"2452",
    "sg:province":"NSW",
    "sg:tags":[
        "net",
        "fishing"
    ],
    "wof:name":"Net Tech Fishing Nets",
    "wof:placetype":"venue"
},
  "geometry": {"coordinates":[153.103226,-30.363092],"type":"Point"}
}