{
  "type": "Feature",
  "properties": {
    "iso:country":"AU",
    "sg:address":"7 Denison St",
    "sg:city":"Tamworth",
    "sg:classifiers":[
        {
            "category":"Retail",
            "subcategory":"Auto Repair",
            "type":"Services"
        }
    ],
    "sg:phone":"+61 2 6765 8251",
    "sg:postcode":"2340",
    "sg:province":"NSW",
    "sg:tags":[
        "repairer",
        "motor",
        "engineer"
    ],
    "wof:name":"Tallar M. H. Automotive Repairs",
    "wof:placetype":"venue"
},
  "geometry": {"coordinates":[150.91510009800001,-31.0872383118],"type":"Point"}
}