{
  "type": "Feature",
  "properties": {
    "addr:full":"PO Box 348 Cabramatta NSW 2166",
    "addr:postcode":"2166",
    "iso:country":"AU",
    "sg:address":"PO Box 348",
    "sg:city":"Cabramatta",
    "sg:classifiers":[
        {
            "category":"Autos & Motor Vehicles",
            "subcategory":"Auto Supplies",
            "type":"Retail Goods"
        }
    ],
    "sg:phone":"+61 419 445 321",
    "sg:postcode":"2166",
    "sg:province":"NSW",
    "sg:tags":[
        "accessory"
    ],
    "wof:name":"Revhead Auto Accessories",
    "wof:placetype":"venue"
},
  "geometry": {"coordinates":[150.93850707999999,-33.8950386047],"type":"Point"}
}