{
  "type": "Feature",
  "properties": {
    "iso:country":"AU",
    "sg:address":"UG18/ 2a Victoria St",
    "sg:city":"Castle Hill",
    "sg:classifiers":[
        {
            "category":"Building & Trades",
            "subcategory":"Construction",
            "type":"Services"
        }
    ],
    "sg:phone":"+61 2 8850 7089",
    "sg:postcode":"2154",
    "sg:province":"NSW",
    "sg:tags":[
        "window",
        "tinting"
    ],
    "wof:name":"Tintmart Castle Hill",
    "wof:placetype":"venue"
},
  "geometry": {"coordinates":[150.97406005900001,-33.7201843262],"type":"Point"}
}