{
  "type": "Feature",
  "properties": {
    "addr:full":"532 Cockatoo Gully Rd Elderslie TAS 7030",
    "addr:housenumber":"532",
    "addr:postcode":"7030",
    "addr:street":"Cockatoo Gully Rd",
    "iso:country":"AU",
    "sg:address":"532 Cockatoo Gully Rd",
    "sg:city":"Elderslie",
    "sg:classifiers":[
        {
            "category":"Building & Trades",
            "subcategory":"Pest Control",
            "type":"Services"
        }
    ],
    "sg:phone":"+61 429 038 238",
    "sg:postcode":"7030",
    "sg:province":"TAS",
    "wof:name":"Total Pest Management",
    "wof:placetype":"venue"
},
  "geometry": {"coordinates":[147.130661011,-42.5956268311],"type":"Point"}
}