{
  "type": "Feature",
  "properties": {
    "addr:full":"Welshpool Depot 85 Sheffield Rd Welshpool WA 6106",
    "addr:housenumber":"85",
    "addr:postcode":"6106",
    "addr:street":"Sheffield Rd",
    "iso:country":"AU",
    "sg:address":"Welshpool Depot 85 Sheffield Rd",
    "sg:city":"Welshpool",
    "sg:classifiers":[
        {
            "category":"Professional",
            "type":"Services"
        }
    ],
    "sg:phone":"+61 8 9358 7600",
    "sg:postcode":"6106",
    "sg:province":"WA",
    "sg:tags":[
        "transport"
    ],
    "sg:website":"http://www.skippers-transport.com.au",
    "wof:name":"Skippers Transport",
    "wof:placetype":"venue"
},
  "geometry": {"coordinates":[115.97392273,-31.9945697784],"type":"Point"}
}