{
  "type": "Feature",
  "properties": {
    "iso:country":"AU",
    "sg:address":"5 / 21 Carlo Drv",
    "sg:city":"Cannonvale",
    "sg:classifiers":[
        {
            "category":"Structure",
            "subcategory":"Building",
            "type":"Public Place"
        }
    ],
    "sg:phone":"+61 7 4946 1125",
    "sg:postcode":"4802",
    "sg:province":"QLD",
    "sg:tags":[
        "sail",
        "shade"
    ],
    "wof:name":"Airlie Sail & Shade Solutions",
    "wof:placetype":"venue"
},
  "geometry": {"coordinates":[148.67405700699999,-20.2859363556],"type":"Point"}
}