{
  "type": "Feature",
  "properties": {
    "addr:full":"U5/ 1 Moree St Gordon NSW 2072",
    "addr:housenumber":"1",
    "addr:postcode":"2072",
    "addr:street":"U5 /;St",
    "iso:country":"AU",
    "sg:address":"U5/ 1 Moree St",
    "sg:city":"Gordon",
    "sg:classifiers":[
        {
            "category":"Cafe",
            "type":"Food & Drink"
        }
    ],
    "sg:phone":"+61 2 9498 5826",
    "sg:postcode":"2072",
    "sg:province":"NSW",
    "wof:name":"Chatterbox Cafe",
    "wof:placetype":"venue"
},
  "geometry": {"coordinates":[151.152542114,-33.7555503845],"type":"Point"}
}