{
  "type": "Feature",
  "properties": {
    "iso:country":"AU",
    "sg:address":"227 Belmont Avenue, Shop 91 Belmont Forum",
    "sg:city":"Cloverdale",
    "sg:classifiers":[
        {
            "category":"Retail",
            "subcategory":"Repair Shop",
            "type":"Services"
        }
    ],
    "sg:phone":"+61 8 9478 5855",
    "sg:postcode":"6105",
    "sg:province":"WA",
    "sg:tags":[
        "mending",
        "clothing",
        "alteration"
    ],
    "wof:name":"Looksmart Alterations",
    "wof:placetype":"venue"
},
  "geometry": {"coordinates":[115.924629211,-31.9580192566],"type":"Point"}
}