{
  "type": "Feature",
  "properties": {
    "iso:country":"AU",
    "sg:address":"Shop 19 Runaway Bay Shopping Village Lae Drv",
    "sg:city":"Runaway Bay",
    "sg:classifiers":[
        {
            "category":"Shopping",
            "subcategory":"Clothing, Apparel, & Fashions",
            "type":"Retail Goods"
        }
    ],
    "sg:phone":"+61 7 5529 1922",
    "sg:postcode":"4216",
    "sg:province":"QLD",
    "sg:tags":[
        "boutique"
    ],
    "wof:name":"Monsoon Resortwear",
    "wof:placetype":"venue"
},
  "geometry": {"coordinates":[153.405593872,-27.9106426239],"type":"Point"}
}