{
  "type": "Feature",
  "properties": {
    "iso:country":"AU",
    "sg:address":"16 Russell St",
    "sg:city":"Evandale",
    "sg:classifiers":[
        {
            "category":"Food & Beverages",
            "subcategory":"Groceries & Convenience Stores",
            "type":"Retail Goods"
        }
    ],
    "sg:phone":"+61 3 6391 8251",
    "sg:postcode":"7212",
    "sg:province":"TAS",
    "wof:name":"Evandale General Store",
    "wof:placetype":"venue"
},
  "geometry": {"coordinates":[147.25010700000001,-41.571045],"type":"Point"}
}