{
  "type": "Feature",
  "properties": {
    "iso:country":"AU",
    "sg:address":"Unit 102 45 Gilby Rd",
    "sg:city":"Mt Waverley",
    "sg:classifiers":[
        {
            "category":"Wholesale",
            "subcategory":"Machinery & Supplies",
            "type":"Manufacturing & Wholesale Goods"
        }
    ],
    "sg:phone":"+61 3 9558 9929",
    "sg:postcode":"3149",
    "sg:province":"VIC",
    "sg:tags":[
        "instrument",
        "scientific"
    ],
    "wof:name":"Shimadzu Scientific Instruments (Oceania) Pty Ltd",
    "wof:placetype":"venue"
},
  "geometry": {"coordinates":[145.13653564399999,-37.8993797302],"type":"Point"}
}