{
  "type": "Feature",
  "properties": {
    "addr:full":"197 Para Rd Greensborough VIC 3088",
    "addr:housenumber":"197",
    "addr:postcode":"3088",
    "addr:street":"Para Rd",
    "iso:country":"AU",
    "sg:address":"197 Para Rd",
    "sg:city":"Greensborough",
    "sg:classifiers":[
        {
            "category":"Wholesale",
            "subcategory":"Metals & Minerals",
            "type":"Manufacturing & Wholesale Goods"
        }
    ],
    "sg:phone":"+61 3 9432 4800",
    "sg:postcode":"3088",
    "sg:province":"VIC",
    "sg:tags":[
        "steel",
        "stainless",
        "product",
        "equipment"
    ],
    "wof:name":"Bryston Stainless Steel Fabrication",
    "wof:placetype":"venue"
},
  "geometry": {"coordinates":[145.11080932600001,-37.7077407837],"type":"Point"}
}