{
  "type": "Feature",
  "properties": {
    "iso:country":"AU",
    "sg:address":"100 Byron St",
    "sg:city":"Inverell",
    "sg:classifiers":[
        {
            "category":"Insurance",
            "subcategory":"Insurance Agent",
            "type":"Services"
        }
    ],
    "sg:phone":"+61 2 6722 3577",
    "sg:postcode":"2360",
    "sg:province":"NSW",
    "wof:name":"Orchard I G",
    "wof:placetype":"venue"
},
  "geometry": {"coordinates":[151.11207580600001,-29.7729587555],"type":"Point"}
}