{
  "type": "Feature",
  "properties": {
    "addr:full":"233 Bulwara Rd Ultimo NSW 2007",
    "addr:housenumber":"233",
    "addr:postcode":"2007",
    "addr:street":"Bulwara Rd",
    "iso:country":"AU",
    "sg:address":"233 Bulwara Rd",
    "sg:city":"Ultimo",
    "sg:classifiers":[
        {
            "category":"Professional",
            "subcategory":"Business Services",
            "type":"Services"
        }
    ],
    "sg:phone":"+61 2 9552 4433",
    "sg:postcode":"2007",
    "sg:province":"NSW",
    "sg:tags":[
        "drafting"
    ],
    "wof:name":"D.E.S. Pty Ltd",
    "wof:placetype":"venue"
},
  "geometry": {"coordinates":[151.19619750999999,-33.8758964539],"type":"Point"}
}