{
  "type": "Feature",
  "properties": {
    "addr:full":"598-602 Forest Rd Penshurst NSW 2222",
    "addr:housenumber":"598-602",
    "addr:postcode":"2222",
    "addr:street":"Forest Rd",
    "iso:country":"AU",
    "sg:address":"598-602 Forest Rd",
    "sg:city":"Penshurst",
    "sg:classifiers":[
        {
            "category":"Manufacturing",
            "subcategory":"Motor Vehicles & Parts",
            "type":"Manufacturing & Wholesale Goods"
        }
    ],
    "sg:phone":"+61 2 9570 8844",
    "sg:postcode":"2222",
    "sg:province":"NSW",
    "sg:tags":[
        "replacement"
    ],
    "wof:name":"RPM Auto Spares",
    "wof:placetype":"venue"
},
  "geometry": {"coordinates":[151.07974243199999,-33.9620857239],"type":"Point"}
}