{
  "type": "Feature",
  "properties": {
    "iso:country":"AU",
    "sg:address":"25 Graydon Ave",
    "sg:city":"Denhams Beach",
    "sg:classifiers":[
        {
            "category":"Building & Trades",
            "subcategory":"Construction",
            "type":"Services"
        }
    ],
    "sg:phone":"+61 414 712 441",
    "sg:postcode":"2536",
    "sg:province":"NSW",
    "sg:tags":[
        "contractor"
    ],
    "wof:name":"Ian Filmer Constructions Pty Ltd",
    "wof:placetype":"venue"
},
  "geometry": {"coordinates":[150.211395264,-35.7512931824],"type":"Point"}
}