{
  "type": "Feature",
  "properties": {
    "addr:full":"1/ 35 Wyandra St Newstead QLD 4006",
    "addr:housenumber":"/ 35",
    "addr:postcode":"4006",
    "addr:street":"Wyandra St",
    "iso:country":"AU",
    "sg:address":"1/ 35 Wyandra St",
    "sg:city":"Newstead",
    "sg:classifiers":[
        {
            "category":"Real Estate",
            "subcategory":"Surveying",
            "type":"Services"
        }
    ],
    "sg:phone":"+61 7 3666 0514",
    "sg:postcode":"4006",
    "sg:province":"QLD",
    "sg:tags":[
        "surveyor",
        "land"
    ],
    "wof:name":"Tong Town Planning & Development Services",
    "wof:placetype":"venue"
},
  "geometry": {"coordinates":[153.04588317899999,-27.4524326324],"type":"Point"}
}