{
  "type": "Feature",
  "properties": {
    "addr:full":"Shp 1/ 2 Carmody St Logan Central QLD 4114",
    "addr:housenumber":"/ 2",
    "addr:postcode":"4114",
    "addr:street":"Carmody St",
    "iso:country":"AU",
    "sg:address":"Shp 1/ 2 Carmody St",
    "sg:city":"Logan Central",
    "sg:classifiers":[
        {
            "category":"Cafe",
            "type":"Food & Drink"
        }
    ],
    "sg:phone":"+61 7 3208 2677",
    "sg:postcode":"4114",
    "sg:province":"QLD",
    "wof:name":"Logan Central Cafe",
    "wof:placetype":"venue"
},
  "geometry": {"coordinates":[153.10658264200001,-27.6400146484],"type":"Point"}
}