{
  "type": "Feature",
  "properties": {
    "addr:full":"1236 High St Armadale VIC 3143",
    "addr:housenumber":"1236",
    "addr:postcode":"3143",
    "addr:street":"High St",
    "iso:country":"AU",
    "sg:address":"1236 High St",
    "sg:city":"Armadale",
    "sg:classifiers":[
        {
            "category":"Personal",
            "subcategory":"Beauty Salon",
            "type":"Services"
        }
    ],
    "sg:phone":"+61 3 9500 9322",
    "sg:postcode":"3143",
    "sg:province":"VIC",
    "sg:tags":[
        "hairdresser"
    ],
    "wof:name":"Semaarn Salons",
    "wof:placetype":"venue"
},
  "geometry": {"coordinates":[145.02804565400001,-37.8565597534],"type":"Point"}
}