{
  "type": "Feature",
  "properties": {
    "addr:full":"27 Doyle Ave Unanderra NSW 2526",
    "addr:housenumber":"27",
    "addr:postcode":"2526",
    "addr:street":"Doyle Ave",
    "iso:country":"AU",
    "sg:address":"27 Doyle Ave",
    "sg:city":"Unanderra",
    "sg:classifiers":[
        {
            "category":"Retail",
            "subcategory":"Auto Repair",
            "type":"Services"
        }
    ],
    "sg:phone":"+61 2 4272 8400",
    "sg:postcode":"2526",
    "sg:province":"NSW",
    "sg:tags":[
        "body",
        "builder",
        "motor"
    ],
    "wof:name":"Berry Howe Industries",
    "wof:placetype":"venue"
},
  "geometry": {"coordinates":[150.838653564,-34.4666900635],"type":"Point"}
}