{
  "type": "Feature",
  "properties": {
    "addr:full":"25 Sundercombe St Osborne Park WA 6017",
    "addr:housenumber":"25",
    "addr:postcode":"6017",
    "addr:street":"Sundercombe St",
    "iso:country":"AU",
    "sg:address":"25 Sundercombe St",
    "sg:city":"Osborne Park",
    "sg:classifiers":[
        {
            "category":"Wholesale",
            "subcategory":"Metals & Minerals",
            "type":"Manufacturing & Wholesale Goods"
        }
    ],
    "sg:phone":"+61 8 9242 8555",
    "sg:postcode":"6017",
    "sg:province":"WA",
    "sg:tags":[
        "steel",
        "merchant"
    ],
    "wof:name":"Lazer Asset Pty Ltd",
    "wof:placetype":"venue"
},
  "geometry": {"coordinates":[115.81391143800001,-31.902885437],"type":"Point"}
}