{
  "type": "Feature",
  "properties": {
    "addr:full":"U18/ 17 Bowden St Alexandria NSW 2015",
    "addr:postcode":"2015",
    "addr:street":"/ 17 Bowden St",
    "iso:country":"AU",
    "sg:address":"U18/ 17 Bowden St",
    "sg:city":"Alexandria",
    "sg:classifiers":[
        {
            "category":"Shopping",
            "subcategory":"Shoes",
            "type":"Retail Goods"
        }
    ],
    "sg:phone":"+61 2 9698 4700",
    "sg:postcode":"2015",
    "sg:province":"NSW",
    "sg:tags":[
        "footwear"
    ],
    "wof:name":"Flojos",
    "wof:placetype":"venue"
},
  "geometry": {"coordinates":[151.19563293499999,-33.9041900635],"type":"Point"}
}