{
  "type": "Feature",
  "properties": {
    "addr:full":"8 Warner Ave Ashburton VIC 3147",
    "addr:housenumber":"8",
    "addr:postcode":"3147",
    "addr:street":"Warner Ave",
    "iso:country":"AU",
    "sg:address":"8 Warner Ave",
    "sg:city":"Ashburton",
    "sg:classifiers":[
        {
            "category":"Health Services",
            "subcategory":"Health Practitioner",
            "type":"Services"
        }
    ],
    "sg:phone":"+61 3 9885 0695",
    "sg:postcode":"3147",
    "sg:province":"VIC",
    "sg:tags":[
        "physiotherapist"
    ],
    "wof:name":"Wigg Simon",
    "wof:placetype":"venue"
},
  "geometry": {"coordinates":[145.08628845199999,-37.8645935059],"type":"Point"}
}