{
  "type": "Feature",
  "properties": {
    "addr:full":"PO Box 3509 Erina NSW 2250",
    "addr:postcode":"2250",
    "iso:country":"AU",
    "sg:address":"PO Box 3509",
    "sg:city":"Erina",
    "sg:phone":"+61 2 4368 4872",
    "sg:postcode":"2250",
    "sg:province":"NSW",
    "wof:name":"Freewater Plumbing Pty Ltd",
    "wof:placetype":"venue"
},
  "geometry": {"coordinates":[151.395217895,-33.4346389771],"type":"Point"}
}