{
  "type": "Feature",
  "properties": {
    "iso:country":"AU",
    "sg:address":"7/ 37-39 Highclaire Ave",
    "sg:city":"Punchbowl",
    "sg:classifiers":[
        {
            "category":"Professional",
            "subcategory":"Art Services",
            "type":"Services"
        }
    ],
    "sg:phone":"+61 415 999 062",
    "sg:postcode":"2196",
    "sg:province":"NSW",
    "sg:tags":[
        "decorator",
        "painter"
    ],
    "wof:name":"A Purely Paint",
    "wof:placetype":"venue"
},
  "geometry": {"coordinates":[151.055878,-33.923206],"type":"Point"}
}