{
  "type": "Feature",
  "properties": {
    "addr:full":"1/ 492 Ocean Beach Rd Umina Beach NSW 2257",
    "addr:housenumber":"/ 492",
    "addr:postcode":"2257",
    "addr:street":"Ocean Beach Rd",
    "iso:country":"AU",
    "sg:address":"1/ 492 Ocean Beach Rd",
    "sg:city":"Umina Beach",
    "sg:classifiers":[
        {
            "category":"Personal",
            "subcategory":"Massage",
            "type":"Services"
        }
    ],
    "sg:phone":"+61 2 4341 9905",
    "sg:postcode":"2257",
    "sg:province":"NSW",
    "sg:tags":[
        "therapy"
    ],
    "wof:name":"Gillett Diane",
    "wof:placetype":"venue"
},
  "geometry": {"coordinates":[151.31619262699999,-33.5250663757],"type":"Point"}
}