{
  "type": "Feature",
  "properties": {
    "addr:full":"64a Smith St Wollongong NSW 2500",
    "addr:housenumber":"64a",
    "addr:postcode":"2500",
    "addr:street":"Smith St",
    "iso:country":"AU",
    "sg:address":"64a Smith St",
    "sg:city":"Wollongong",
    "sg:classifiers":[
        {
            "category":"Social Services",
            "subcategory":"Child Care",
            "type":"Services"
        }
    ],
    "sg:phone":"+61 2 4228 7795",
    "sg:postcode":"2500",
    "sg:province":"NSW",
    "wof:name":"Smith Street Child Care Centre",
    "wof:placetype":"venue"
},
  "geometry": {"coordinates":[150.89532500000001,-34.421516],"type":"Point"}
}