{
  "type": "Feature",
  "properties": {
    "iso:country":"AU",
    "sg:address":"7 MacIntosh St",
    "sg:city":"Tamworth",
    "sg:classifiers":[
        {
            "category":"Retail",
            "subcategory":"Auto Repair",
            "type":"Services"
        }
    ],
    "sg:phone":"+61 2 6762 3636",
    "sg:postcode":"2340",
    "sg:province":"NSW",
    "sg:tags":[
        "engine",
        "reconditioning"
    ],
    "wof:name":"Liberty Speed",
    "wof:placetype":"venue"
},
  "geometry": {"coordinates":[150.90118408199999,-31.0980987549],"type":"Point"}
}