{
  "type": "Feature",
  "properties": {
    "addr:full":"26 Potters La Talbot VIC 3371",
    "addr:housenumber":"26",
    "addr:postcode":"3371",
    "addr:street":"Potters La Talbot",
    "iso:country":"AU",
    "sg:address":"26 Potters La",
    "sg:city":"Talbot",
    "sg:classifiers":[
        {
            "category":"Utilities",
            "subcategory":"Refuse",
            "type":"Services"
        }
    ],
    "sg:phone":"+61 3 5463 2006",
    "sg:postcode":"3371",
    "sg:province":"VIC",
    "sg:tags":[
        "remover",
        "rubbish"
    ],
    "wof:name":"A & G Recycling",
    "wof:placetype":"venue"
},
  "geometry": {"coordinates":[143.706756592,-37.166759491],"type":"Point"}
}