{
  "type": "Feature",
  "properties": {
    "iso:country":"AU",
    "sg:address":"Shop 17 Capalaba Central, Moreton Bay Rd",
    "sg:city":"Capalaba",
    "sg:classifiers":[
        {
            "category":"Shopping",
            "type":"Retail Goods"
        }
    ],
    "sg:phone":"+61 7 3823 1989",
    "sg:postcode":"4157",
    "sg:province":"QLD",
    "sg:tags":[
        "repair",
        "travel"
    ],
    "wof:name":"Bagstop Stores",
    "wof:placetype":"venue"
},
  "geometry": {"coordinates":[153.199981689,-27.5226707458],"type":"Point"}
}