{
  "type": "Feature",
  "properties": {
    "addr:full":"3 Middleton Rd Cromer NSW 2099",
    "addr:housenumber":"3",
    "addr:postcode":"2099",
    "addr:street":"Middleton Rd",
    "iso:country":"AU",
    "sg:address":"3 Middleton Rd",
    "sg:city":"Cromer",
    "sg:classifiers":[
        {
            "category":"Manufacturing",
            "subcategory":"Metals",
            "type":"Manufacturing & Wholesale Goods"
        }
    ],
    "sg:phone":"+61 2 9971 5000",
    "sg:postcode":"2099",
    "sg:province":"NSW",
    "sg:tags":[
        "spinner"
    ],
    "wof:name":"A.D.N. Spunware",
    "wof:placetype":"venue"
},
  "geometry": {"coordinates":[151.280563355,-33.7352561951],"type":"Point"}
}