{
  "type": "Feature",
  "properties": {
    "addr:full":"17 Broadwood St Broadwood WA 6430",
    "addr:housenumber":"17",
    "addr:postcode":"6430",
    "addr:street":"Broadwood St",
    "iso:country":"AU",
    "sg:address":"17 Broadwood St",
    "sg:city":"Broadwood",
    "sg:classifiers":[
        {
            "category":"Mining & Drilling",
            "type":"Manufacturing & Wholesale Goods"
        }
    ],
    "sg:phone":"+61 8 9091 9955",
    "sg:postcode":"6430",
    "sg:province":"WA",
    "sg:tags":[
        "boring",
        "contractor"
    ],
    "wof:name":"360 Drilling Pty Ltd",
    "wof:placetype":"venue"
},
  "geometry": {"coordinates":[121.44490051299999,-30.778503418],"type":"Point"}
}