{
  "type": "Feature",
  "properties": {
    "addr:full":"6 Garrick Rd St Clair NSW 2759",
    "addr:housenumber":"6",
    "addr:postcode":"2759",
    "addr:street":"Garrick Rd",
    "iso:country":"AU",
    "sg:address":"6 Garrick Rd",
    "sg:city":"St Clair",
    "sg:classifiers":[
        {
            "category":"Retail",
            "subcategory":"Driving School",
            "type":"Services"
        }
    ],
    "sg:phone":"+61 2 9670 5309",
    "sg:postcode":"2759",
    "sg:province":"NSW",
    "wof:name":"Premier Driving School",
    "wof:placetype":"venue"
},
  "geometry": {"coordinates":[150.77452087399999,-33.7868614197],"type":"Point"}
}