{
  "type": "Feature",
  "properties": {
    "addr:full":"5 Coominyah St Sunnybank Hills QLD 4109",
    "addr:housenumber":"5",
    "addr:postcode":"4109",
    "addr:street":"Coominyah St",
    "iso:country":"AU",
    "sg:address":"5 Coominyah St",
    "sg:city":"Sunnybank Hills",
    "sg:classifiers":[
        {
            "category":"Shopping",
            "subcategory":"Gifts & Souvenirs",
            "type":"Retail Goods"
        }
    ],
    "sg:phone":"+61 7 3345 7077",
    "sg:postcode":"4109",
    "sg:province":"QLD",
    "sg:tags":[
        "shop",
        "supply"
    ],
    "wof:name":"Anthony International Trading Pty Ltd",
    "wof:placetype":"venue"
},
  "geometry": {"coordinates":[153.04841613799999,-27.589931488],"type":"Point"}
}