{
  "type": "Feature",
  "properties": {
    "addr:full":"11 Carrington St Crookwell NSW 2583",
    "addr:housenumber":"11",
    "addr:postcode":"2583",
    "addr:street":"Carrington St",
    "iso:country":"AU",
    "sg:address":"11 Carrington St",
    "sg:city":"Crookwell",
    "sg:classifiers":[
        {
            "category":"Wholesale",
            "subcategory":"Farm Supplies",
            "type":"Manufacturing & Wholesale Goods"
        }
    ],
    "sg:phone":"+61 2 4832 1073",
    "sg:postcode":"2583",
    "sg:province":"NSW",
    "sg:tags":[
        "equipment"
    ],
    "wof:name":"Nicholson Farm Machinery",
    "wof:placetype":"venue"
},
  "geometry": {"coordinates":[149.45809936500001,-34.4545059204],"type":"Point"}
}