{
  "type": "Feature",
  "properties": {
    "addr:full":"5 Market St Kyneton VIC 3444",
    "addr:housenumber":"5",
    "addr:postcode":"3444",
    "addr:street":"Market St",
    "iso:country":"AU",
    "sg:address":"5 Market St",
    "sg:city":"Kyneton",
    "sg:classifiers":[
        {
            "category":"Wholesale",
            "subcategory":"Farm Supplies",
            "type":"Manufacturing & Wholesale Goods"
        }
    ],
    "sg:phone":"+61 3 5422 2217",
    "sg:postcode":"3444",
    "sg:province":"VIC",
    "sg:tags":[
        "feed",
        "supplement",
        "stock"
    ],
    "wof:name":"Perrys Quality Stockfeeds",
    "wof:placetype":"venue"
},
  "geometry": {"coordinates":[144.45344543499999,-37.2484512329],"type":"Point"}
}