{
  "type": "Feature",
  "properties": {
    "addr:full":"22 Mavis Ave Beaconsfield VIC 3807",
    "addr:housenumber":"22",
    "addr:postcode":"3807",
    "addr:street":"Mavis Ave",
    "iso:country":"AU",
    "sg:address":"22 Mavis Ave",
    "sg:city":"Beaconsfield",
    "sg:classifiers":[
        {
            "category":"Cinema",
            "subcategory":"Movie Theater",
            "type":"Entertainment"
        }
    ],
    "sg:phone":"+61 417 109 019",
    "sg:postcode":"3807",
    "sg:province":"VIC",
    "wof:name":"Movies On The Move",
    "wof:placetype":"venue"
},
  "geometry": {"coordinates":[145.38746643100001,-38.031791687],"type":"Point"}
}