{
  "type": "Feature",
  "properties": {
    "iso:country":"AU",
    "sg:address":"Unit 3, 105 Mulgrave Rd",
    "sg:city":"Mulgrave",
    "sg:classifiers":[
        {
            "category":"Utilities",
            "subcategory":"Electric",
            "type":"Services"
        }
    ],
    "sg:phone":"+61 2 4577 3135",
    "sg:postcode":"2756",
    "sg:province":"NSW",
    "sg:tags":[
        "electrical",
        "contractor"
    ],
    "wof:name":"Mr. G. Electrics Pty Ltd",
    "wof:placetype":"venue"
},
  "geometry": {"coordinates":[150.830276489,-33.6250762939],"type":"Point"}
}