{
  "type": "Feature",
  "properties": {
    "addr:full":"47 Burwood Rd Burwood NSW 2134",
    "addr:housenumber":"47",
    "addr:postcode":"2134",
    "addr:street":"Burwood Rd",
    "iso:country":"AU",
    "sg:address":"47 Burwood Rd",
    "sg:city":"Burwood",
    "sg:classifiers":[
        {
            "category":"Shopping",
            "subcategory":"Clothing, Apparel, & Fashions",
            "type":"Retail Goods"
        }
    ],
    "sg:phone":"+61 2 9747 5931",
    "sg:postcode":"2134",
    "sg:province":"NSW",
    "sg:tags":[
        "lady",
        "wear"
    ],
    "wof:name":"Decadence Burwood",
    "wof:placetype":"venue"
},
  "geometry": {"coordinates":[151.10406494099999,-33.8746871948],"type":"Point"}
}