{
  "type": "Feature",
  "properties": {
    "addr:full":"9 Sussex St Glenorchy TAS 7010",
    "addr:housenumber":"9",
    "addr:postcode":"7010",
    "addr:street":"Sussex St",
    "iso:country":"AU",
    "sg:address":"9 Sussex St",
    "sg:city":"Glenorchy",
    "sg:classifiers":[
        {
            "category":"Taxi",
            "type":"Transportation"
        }
    ],
    "sg:phone":"+61 3 6273 0221",
    "sg:postcode":"7010",
    "sg:province":"TAS",
    "sg:tags":[
        "cab"
    ],
    "wof:name":"WeGitUthAir Taxi Service",
    "wof:placetype":"venue"
},
  "geometry": {"coordinates":[147.26295471200001,-42.8327026367],"type":"Point"}
}