{
  "type": "Feature",
  "properties": {
    "iso:country":"AU",
    "sg:address":"35 Covehill Rd",
    "sg:city":"Bridgewater",
    "sg:classifiers":[
        {
            "category":"Freight",
            "type":"Transportation"
        }
    ],
    "sg:phone":"+61 3 6263 6777",
    "sg:postcode":"7030",
    "sg:province":"TAS",
    "sg:tags":[
        "light",
        "carrier"
    ],
    "wof:name":"Greg Worsley Transport Services",
    "wof:placetype":"venue"
},
  "geometry": {"coordinates":[147.24349975600001,-42.7342720032],"type":"Point"}
}