{
  "type": "Feature",
  "properties": {
    "iso:country":"AU",
    "sg:address":"379 Bournes La",
    "sg:city":"Tamworth",
    "sg:classifiers":[
        {
            "category":"Retail",
            "subcategory":"Auto Rental",
            "type":"Services"
        }
    ],
    "sg:phone":"+61 2 6760 8403",
    "sg:postcode":"2340",
    "sg:province":"NSW",
    "sg:tags":[
        "camper-trailers",
        "caravan",
        "hire"
    ],
    "wof:name":"Tamworth Caravan Hire & Sales",
    "wof:placetype":"venue"
},
  "geometry": {"coordinates":[150.88377380399999,-31.0252971649],"type":"Point"}
}