{
  "type": "Feature",
  "properties": {
    "addr:full":"13A Bass Hwy Deloraine TAS 7304",
    "addr:housenumber":"13a",
    "addr:postcode":"7304",
    "addr:street":"Bass Hwy",
    "iso:country":"AU",
    "sg:address":"13A Bass Hwy",
    "sg:city":"Deloraine",
    "sg:classifiers":[
        {
            "category":"Retail",
            "subcategory":"Auto Repair",
            "type":"Services"
        }
    ],
    "sg:phone":"+61 3 6362 2632",
    "sg:postcode":"7304",
    "sg:province":"TAS",
    "sg:tags":[
        "repairer",
        "motor",
        "engineer"
    ],
    "wof:name":"Woods Auto Centre",
    "wof:placetype":"venue"
},
  "geometry": {"coordinates":[146.66743500000001,-41.515396],"type":"Point"}
}