{
  "type": "Feature",
  "properties": {
    "iso:country":"AU",
    "sg:address":"10 Ormiston St",
    "sg:city":"Gunn",
    "sg:classifiers":[
        {
            "category":"Building & Trades",
            "subcategory":"Landscaping Services",
            "type":"Services"
        }
    ],
    "sg:phone":"+61 8 8932 7805",
    "sg:postcode":"0832",
    "sg:province":"NT",
    "sg:tags":[
        "gardener"
    ],
    "wof:name":"Green Vision",
    "wof:placetype":"venue"
},
  "geometry": {"coordinates":[130.990509,-12.487566],"type":"Point"}
}