{
  "type": "Feature",
  "properties": {
    "addr:full":"11 Johnston Crt Dandenong South VIC 3164",
    "addr:housenumber":"11",
    "addr:postcode":"3164",
    "addr:street":"Johnston Crt",
    "iso:country":"AU",
    "sg:address":"11 Johnston Crt",
    "sg:city":"Dandenong South",
    "sg:classifiers":[
        {
            "category":"Manufacturing",
            "subcategory":"Metals",
            "type":"Manufacturing & Wholesale Goods"
        }
    ],
    "sg:phone":"+61 3 9792 0854",
    "sg:postcode":"3164",
    "sg:province":"VIC",
    "sg:tags":[
        "steel",
        "fabricator",
        "mfrs"
    ],
    "wof:name":"Melbourne Structural Steel",
    "wof:placetype":"venue"
},
  "geometry": {"coordinates":[145.21804809599999,-38.0066604614],"type":"Point"}
}