{
  "type": "Feature",
  "properties": {
    "addr:full":"Level 10, 71 Queens Rd Melbourne VIC 3000",
    "addr:housenumber":"71",
    "addr:postcode":"3000",
    "addr:street":"Queens Rd",
    "iso:country":"AU",
    "sg:address":"Level 10, 71 Queens Rd",
    "sg:city":"Melbourne",
    "sg:classifiers":[
        {
            "category":"Health Services",
            "subcategory":"Doctor",
            "type":"Services"
        }
    ],
    "sg:phone":"+61 3 9642 2200",
    "sg:postcode":"3000",
    "sg:province":"VIC",
    "sg:tags":[
        "occupational",
        "safety"
    ],
    "wof:name":"Richard Oliver International Pty Ltd",
    "wof:placetype":"venue"
},
  "geometry": {"coordinates":[144.97877502399999,-37.8514328003],"type":"Point"}
}