{
  "type": "Feature",
  "properties": {
    "addr:full":"ShopG70A Karrinyup Shopping Cntr 200 Karrinyup Rd Karrinyup WA 6018",
    "addr:housenumber":"200",
    "addr:postcode":"6018",
    "addr:street":"Karrinyup Rd",
    "iso:country":"AU",
    "sg:address":"ShopG70A Karrinyup Shopping Cntr 200 Karrinyup Rd",
    "sg:city":"Karrinyup",
    "sg:classifiers":[
        {
            "category":"Shopping",
            "subcategory":"Jewelry",
            "type":"Retail Goods"
        }
    ],
    "sg:phone":"+61 8 9204 5325",
    "sg:postcode":"6018",
    "sg:province":"WA",
    "sg:tags":[
        "jeweller"
    ],
    "wof:name":"Shiels Jewellers",
    "wof:placetype":"venue"
},
  "geometry": {"coordinates":[115.770820618,-31.8734607697],"type":"Point"}
}