{
  "type": "Feature",
  "properties": {
    "addr:full":"Shop 1/ 2155 Albany Hwy Gosnells WA 6110",
    "addr:housenumber":"shop 1 / 2155",
    "addr:postcode":"6110",
    "addr:street":"Albany Hwy",
    "iso:country":"AU",
    "sg:address":"Shop 1/ 2155 Albany Hwy",
    "sg:city":"Gosnells",
    "sg:classifiers":[
        {
            "category":"Wholesale",
            "subcategory":"Medical Equipment & Supplies",
            "type":"Manufacturing & Wholesale Goods"
        }
    ],
    "sg:phone":"+61 8 9398 2043",
    "sg:postcode":"6110",
    "sg:province":"WA",
    "sg:tags":[
        "aid",
        "care",
        "health",
        "home"
    ],
    "wof:name":"Gosnells Scooters & Mobility For Seniors",
    "wof:placetype":"venue"
},
  "geometry": {"coordinates":[116.004402161,-32.0737609863],"type":"Point"}
}