{
  "type": "Feature",
  "properties": {
    "addr:full":"35 Hancock St South Melbourne VIC 3205",
    "addr:housenumber":"35",
    "addr:postcode":"3205",
    "addr:street":"Hancock St",
    "iso:country":"AU",
    "sg:address":"35 Hancock St",
    "sg:city":"South Melbourne",
    "sg:classifiers":[
        {
            "category":"Retail",
            "subcategory":"Auto Repair",
            "type":"Services"
        }
    ],
    "sg:phone":"+61 3 9699 7959",
    "sg:postcode":"3205",
    "sg:province":"VIC",
    "sg:tags":[
        "beater",
        "painter",
        "panel"
    ],
    "wof:name":"S & K Motors",
    "wof:placetype":"venue"
},
  "geometry": {"coordinates":[144.95901499999999,-37.827927],"type":"Point"}
}