{
  "type": "Feature",
  "properties": {
    "iso:country":"AU",
    "sg:address":"Fcty2/ 50 Agosta Drv",
    "sg:city":"Laverton North",
    "sg:classifiers":[
        {
            "category":"Manufacturing",
            "subcategory":"Paper Products",
            "type":"Manufacturing & Wholesale Goods"
        }
    ],
    "sg:phone":"+61 3 8360 9444",
    "sg:postcode":"3026",
    "sg:province":"VIC",
    "sg:tags":[
        "tube",
        "cardboard"
    ],
    "wof:name":"P.G. Paper Tubes Pty Ltd",
    "wof:placetype":"venue"
},
  "geometry": {"coordinates":[144.801636,-37.820835],"type":"Point"}
}