{
  "type": "Feature",
  "properties": {
    "addr:full":"34a Merton St Laverton VIC 3028",
    "addr:housenumber":"34a",
    "addr:postcode":"3028",
    "addr:street":"Merton St",
    "iso:country":"AU",
    "sg:address":"34a Merton St",
    "sg:city":"Laverton",
    "sg:classifiers":[
        {
            "category":"Utilities",
            "subcategory":"Electric",
            "type":"Services"
        }
    ],
    "sg:phone":"+61 3 9369 4979",
    "sg:postcode":"3028",
    "sg:province":"VIC",
    "sg:tags":[
        "electrical",
        "contractor"
    ],
    "wof:name":"Spiteri Frank",
    "wof:placetype":"venue"
},
  "geometry": {"coordinates":[144.77821399999999,-37.865215],"type":"Point"}
}