{
  "type": "Feature",
  "properties": {
    "iso:country":"AU",
    "sg:address":"1/81 Barrack St",
    "sg:city":"Perth",
    "sg:classifiers":[
        {
            "category":"Utilities",
            "subcategory":"Refuse",
            "type":"Services"
        }
    ],
    "sg:phone":"+61 8 9325 4419",
    "sg:postcode":"6000",
    "sg:province":"WA",
    "sg:tags":[
        "leather",
        "retail",
        "clothing"
    ],
    "wof:name":"G R Brown Tailors",
    "wof:placetype":"venue"
},
  "geometry": {"coordinates":[115.860412598,-31.9539737701],"type":"Point"}
}