{
  "type": "Feature",
  "properties": {
    "addr:full":"1694 Burwood Hwy Belgrave VIC 3160",
    "addr:housenumber":"1694",
    "addr:postcode":"3160",
    "addr:street":"Burwood Hwy",
    "iso:country":"AU",
    "sg:address":"1694 Burwood Hwy",
    "sg:city":"Belgrave",
    "sg:classifiers":[
        {
            "category":"Shopping",
            "subcategory":"Clothing, Apparel, & Fashions",
            "type":"Retail Goods"
        }
    ],
    "sg:phone":"+61 3 9752 6069",
    "sg:postcode":"3160",
    "sg:province":"VIC",
    "sg:tags":[
        "recycled",
        "clothing"
    ],
    "wof:name":"Sherbrooke Community Information Centre Opportunity Shop",
    "wof:placetype":"venue"
},
  "geometry": {"coordinates":[145.35476684599999,-37.9090042114],"type":"Point"}
}