{
  "type": "Feature",
  "properties": {
    "iso:country":"AU",
    "sg:address":"24- 26 Victoria Ave",
    "sg:city":"Penshurst",
    "sg:classifiers":[
        {
            "category":"Social Services",
            "subcategory":"Child Care",
            "type":"Services"
        }
    ],
    "sg:phone":"+61 2 9585 8574",
    "sg:postcode":"2222",
    "sg:province":"NSW",
    "wof:name":"My Little Sunshine",
    "wof:placetype":"venue"
},
  "geometry": {"coordinates":[151.08648681599999,-33.9655723572],"type":"Point"}
}