{
  "type": "Feature",
  "properties": {
    "addr:full":"85a Heeney St Chinchilla QLD 4413",
    "addr:housenumber":"85a",
    "addr:postcode":"4413",
    "addr:street":"Heeney St",
    "iso:country":"AU",
    "sg:address":"85a Heeney St",
    "sg:city":"Chinchilla",
    "sg:classifiers":[
        {
            "category":"Professional",
            "subcategory":"Printing & Photocopies",
            "type":"Services"
        }
    ],
    "sg:phone":"+61 7 4662 7226",
    "sg:postcode":"4413",
    "sg:province":"QLD",
    "sg:tags":[
        "trophy"
    ],
    "wof:name":"Chinchilla Jewellers",
    "wof:placetype":"venue"
},
  "geometry": {"coordinates":[150.62467956500001,-26.7404003143],"type":"Point"}
}