{
  "type": "Feature",
  "properties": {
    "iso:country":"AU",
    "sg:address":"77 Hughes Ave",
    "sg:city":"Paringa",
    "sg:classifiers":[
        {
            "category":"Arts & Performance",
            "subcategory":"Art Gallery",
            "type":"Entertainment"
        }
    ],
    "sg:phone":"+61 8 8595 5420",
    "sg:postcode":"5340",
    "sg:province":"SA",
    "wof:name":"Goanna Hill Gallery",
    "wof:placetype":"venue"
},
  "geometry": {"coordinates":[140.791748047,-34.1821479797],"type":"Point"}
}