{
  "type": "Feature",
  "properties": {
    "addr:full":"257 A Forrest St Kalgoorlie WA 6430",
    "addr:housenumber":"257 a",
    "addr:postcode":"6430",
    "addr:street":"Forrest St",
    "iso:country":"AU",
    "sg:address":"257 A Forrest St",
    "sg:city":"Kalgoorlie",
    "sg:classifiers":[
        {
            "category":"Manufacturing",
            "subcategory":"Tools & Machinery",
            "type":"Manufacturing & Wholesale Goods"
        }
    ],
    "sg:phone":"+61 439 520 093",
    "sg:postcode":"6430",
    "sg:province":"WA",
    "sg:tags":[
        "earth",
        "excavating",
        "moving",
        "equipment"
    ],
    "wof:name":"Prompt Mechanical",
    "wof:placetype":"venue"
},
  "geometry": {"coordinates":[121.462440491,-30.7509632111],"type":"Point"}
}