{
  "type": "Feature",
  "properties": {
    "addr:full":"26 Melaleuca Crs Scarness QLD 4655",
    "addr:housenumber":"26",
    "addr:postcode":"4655",
    "addr:street":"Melaleuca Crs",
    "iso:country":"AU",
    "sg:address":"26 Melaleuca Crs",
    "sg:city":"Scarness",
    "sg:classifiers":[
        {
            "category":"Utilities",
            "subcategory":"Telephone",
            "type":"Services"
        }
    ],
    "sg:phone":"+61 411 806 923",
    "sg:postcode":"4655",
    "sg:province":"QLD",
    "sg:tags":[
        "installation",
        "system",
        "maintenance"
    ],
    "wof:name":"Fraser Coast Cabling Services",
    "wof:placetype":"venue"
},
  "geometry": {"coordinates":[152.84939600000001,-25.28974],"type":"Point"}
}