{
  "type": "Feature",
  "properties": {
    "addr:full":"16 St Georges Tce Perth WA 6000",
    "addr:housenumber":"16",
    "addr:postcode":"6000",
    "addr:street":"St Georges Tce",
    "iso:country":"AU",
    "sg:address":"16 St",
    "sg:city":"Georges Tce Perth",
    "sg:classifiers":[
        {
            "category":"Professional",
            "subcategory":"Business Services",
            "type":"Services"
        }
    ],
    "sg:phone":"+61 8 9262 1702",
    "sg:postcode":"6000",
    "sg:province":"WA",
    "sg:tags":[
        "management",
        "event"
    ],
    "wof:name":"Eventscorp",
    "wof:placetype":"venue"
},
  "geometry": {"coordinates":[115.86406707800001,-31.9570007324],"type":"Point"}
}