{
  "type": "Feature",
  "properties": {
    "addr:full":"3/ 35 Notar Drv Ormeau QLD 4208",
    "addr:housenumber":"/ 35",
    "addr:postcode":"4208",
    "addr:street":"Notar Drv",
    "iso:country":"AU",
    "sg:address":"3/ 35 Notar Drv",
    "sg:city":"Ormeau",
    "sg:classifiers":[
        {
            "category":"Manufacturing",
            "subcategory":"Motor Vehicles & Parts",
            "type":"Manufacturing & Wholesale Goods"
        }
    ],
    "sg:phone":"+61 7 5540 7500",
    "sg:postcode":"4208",
    "sg:province":"QLD",
    "sg:tags":[
        "engine",
        "equipment",
        "diesel"
    ],
    "wof:name":"Gold Coast Small Engine Services",
    "wof:placetype":"venue"
},
  "geometry": {"coordinates":[153.25003051799999,-27.7608089447],"type":"Point"}
}