{
  "type": "Feature",
  "properties": {
    "iso:country":"AU",
    "sg:address":"Vivian St",
    "sg:city":"Inverell",
    "sg:classifiers":[
        {
            "category":"Manufacturing",
            "subcategory":"Motor Vehicles & Parts",
            "type":"Manufacturing & Wholesale Goods"
        }
    ],
    "sg:phone":"+61 2 6722 2722",
    "sg:postcode":"2360",
    "sg:province":"NSW",
    "sg:tags":[
        "replacement"
    ],
    "wof:name":"Gaukrogers",
    "wof:placetype":"venue"
},
  "geometry": {"coordinates":[151.11465454099999,-29.7755947113],"type":"Point"}
}