{
  "type": "Feature",
  "properties": {
    "iso:country":"AU",
    "sg:address":"135 Macleay St",
    "sg:city":"Frederickton",
    "sg:classifiers":[
        {
            "category":"Building & Trades",
            "subcategory":"Pest Control",
            "type":"Services"
        }
    ],
    "sg:phone":"+61 2 6566 8514",
    "sg:postcode":"2440",
    "sg:province":"NSW",
    "wof:name":"Tru Pest Management",
    "wof:placetype":"venue"
},
  "geometry": {"coordinates":[152.864838,-31.035196],"type":"Point"}
}