{
  "type": "Feature",
  "properties": {
    "addr:full":"13 Vincent Ave Somerton Park SA 5044",
    "addr:housenumber":"13",
    "addr:postcode":"5044",
    "addr:street":"Vincent Ave Somerton",
    "iso:country":"AU",
    "sg:address":"13 Vincent Ave",
    "sg:city":"Somerton Park",
    "sg:classifiers":[
        {
            "category":"Building & Trades",
            "subcategory":"Construction",
            "type":"Services"
        }
    ],
    "sg:phone":"+61 8 8294 7069",
    "sg:postcode":"5044",
    "sg:province":"SA",
    "sg:tags":[
        "contractor"
    ],
    "wof:name":"Manca E & J",
    "wof:placetype":"venue"
},
  "geometry": {"coordinates":[138.52453600000001,-34.999294],"type":"Point"}
}