{
  "type": "Feature",
  "properties": {
    "addr:full":"49-61 Stephen Rd Botany NSW 2019",
    "addr:housenumber":"49-61",
    "addr:postcode":"2019",
    "addr:street":"Stephen Rd",
    "iso:country":"AU",
    "sg:address":"49-61 Stephen Rd",
    "sg:city":"Botany",
    "sg:classifiers":[
        {
            "category":"Manufacturing",
            "subcategory":"Wood Products",
            "type":"Manufacturing & Wholesale Goods"
        }
    ],
    "sg:phone":"+61 2 9666 0331",
    "sg:postcode":"2019",
    "sg:province":"NSW",
    "sg:tags":[
        "resin"
    ],
    "wof:name":"Nuplex Industries (Aust) Pty Ltd",
    "wof:placetype":"venue"
},
  "geometry": {"coordinates":[151.208786011,-33.953086853],"type":"Point"}
}