{
  "type": "Feature",
  "properties": {
    "addr:full":"46 Butler Crs Penrith NSW 2750",
    "addr:housenumber":"46",
    "addr:postcode":"2750",
    "addr:street":"Butler Crs",
    "iso:country":"AU",
    "sg:address":"46 Butler Crs",
    "sg:city":"Penrith",
    "sg:classifiers":[
        {
            "category":"Building & Trades",
            "subcategory":"Construction",
            "type":"Services"
        }
    ],
    "sg:phone":"+61 2 4722 6407",
    "sg:postcode":"2750",
    "sg:province":"NSW",
    "sg:tags":[
        "concrete",
        "contractor"
    ],
    "wof:name":"Boxman Pty Ltd",
    "wof:placetype":"venue"
},
  "geometry": {"coordinates":[150.89256286599999,-33.8573303223],"type":"Point"}
}