{
  "type": "Feature",
  "properties": {
    "iso:country":"AU",
    "sg:address":"33 Euroka St",
    "sg:city":"Northbridge",
    "sg:classifiers":[
        {
            "category":"Real Estate",
            "subcategory":"Architect",
            "type":"Services"
        }
    ],
    "sg:phone":"+61 2 9967 4116",
    "sg:postcode":"2063",
    "sg:province":"NSW",
    "wof:name":"Alexander Tim",
    "wof:placetype":"venue"
},
  "geometry": {"coordinates":[151.21383667000001,-33.8084602356],"type":"Point"}
}