{
  "type": "Feature",
  "properties": {
    "addr:full":"6 Valley View Pde Korumburra VIC 3950",
    "addr:housenumber":"6",
    "addr:postcode":"3950",
    "addr:street":"Valley View Pde",
    "iso:country":"AU",
    "sg:address":"6 Valley View Pde",
    "sg:city":"Korumburra",
    "sg:classifiers":[
        {
            "category":"Building & Trades",
            "subcategory":"Construction",
            "type":"Services"
        }
    ],
    "sg:phone":"+61 3 5655 2442",
    "sg:postcode":"3950",
    "sg:province":"VIC",
    "sg:tags":[
        "brick",
        "paving"
    ],
    "wof:name":"John Mackie",
    "wof:placetype":"venue"
},
  "geometry": {"coordinates":[145.81607055699999,-38.432346344],"type":"Point"}
}