{
  "type": "Feature",
  "properties": {
    "addr:full":"27 Gibdon St Burnley VIC 3121",
    "addr:housenumber":"27",
    "addr:postcode":"3121",
    "addr:street":"Gibdon St",
    "iso:country":"AU",
    "sg:address":"27 Gibdon St",
    "sg:city":"Burnley",
    "sg:classifiers":[
        {
            "category":"Professional",
            "subcategory":"Testing Lab",
            "type":"Services"
        }
    ],
    "sg:phone":"+61 3 9429 6168",
    "sg:postcode":"3121",
    "sg:province":"VIC",
    "sg:tags":[
        "soil",
        "investigation"
    ],
    "wof:name":"Hardrock Geotechnical Pty Ltd",
    "wof:placetype":"venue"
},
  "geometry": {"coordinates":[145.010818481,-37.8294258118],"type":"Point"}
}