{
  "type": "Feature",
  "properties": {
    "iso:country":"AU",
    "sg:address":"58a Mt Dandenong Rd",
    "sg:city":"Ringwood East",
    "sg:classifiers":[
        {
            "category":"Autos & Motor Vehicles",
            "subcategory":"Fuel & Gas Station",
            "type":"Retail Goods"
        }
    ],
    "sg:phone":"+61 3 9870 6091",
    "sg:postcode":"3135",
    "sg:province":"VIC",
    "wof:name":"Cleijne Motors",
    "wof:placetype":"venue"
},
  "geometry": {"coordinates":[145.249725342,-37.8088607788],"type":"Point"}
}