{
  "type": "Feature",
  "properties": {
    "iso:country":"AU",
    "sg:address":"146 Railway Pde",
    "sg:city":"Kogarah",
    "sg:classifiers":[
        {
            "category":"Building & Trades",
            "subcategory":"Construction",
            "type":"Services"
        }
    ],
    "sg:phone":"+61 2 9588 9289",
    "sg:postcode":"2217",
    "sg:province":"NSW",
    "sg:tags":[
        "installation",
        "air conditioning"
    ],
    "wof:name":"Holiday Airconditioning & Refrigeration Engineering",
    "wof:placetype":"venue"
},
  "geometry": {"coordinates":[151.13188199999999,-33.965321],"type":"Point"}
}