{
  "type": "Feature",
  "properties": {
    "addr:full":"Pakenham Shopping Centre 9 Pakenham Place Pakenham VIC 3810",
    "addr:housenumber":"9",
    "addr:postcode":"3810",
    "addr:street":"Pakenham Place",
    "iso:country":"AU",
    "sg:address":"Pakenham Shopping Centre 9",
    "sg:city":"Pakenham Place Pakenham",
    "sg:classifiers":[
        {
            "category":"Shopping",
            "subcategory":"Jewelry",
            "type":"Retail Goods"
        }
    ],
    "sg:phone":"+61 3 5941 1853",
    "sg:postcode":"3810",
    "sg:province":"VIC",
    "sg:tags":[
        "jeweller"
    ],
    "wof:name":"Pakenham Jewellers & Watchmakers",
    "wof:placetype":"venue"
},
  "geometry": {"coordinates":[145.46759,-38.065758],"type":"Point"}
}