{
  "type": "Feature",
  "properties": {
    "iso:country":"AU",
    "sg:address":"190 Harvey Range Rd",
    "sg:city":"Kirwan",
    "sg:classifiers":[
        {
            "category":"Travel",
            "subcategory":"Hostel",
            "type":"Entertainment"
        }
    ],
    "sg:phone":"+61 7 4750 3430",
    "sg:postcode":"4817",
    "sg:province":"QLD",
    "sg:tags":[
        "home"
    ],
    "wof:name":"Shalom Elders Village",
    "wof:placetype":"venue"
},
  "geometry": {"coordinates":[146.726807,-19.31781],"type":"Point"}
}