{
  "type": "Feature",
  "properties": {
    "addr:full":"78 North Rd Lilydale VIC 3140",
    "addr:housenumber":"78",
    "addr:postcode":"3140",
    "addr:street":"North Rd",
    "iso:country":"AU",
    "sg:address":"78 North Rd",
    "sg:city":"Lilydale",
    "sg:classifiers":[
        {
            "category":"Retail",
            "subcategory":"Auto Repair",
            "type":"Services"
        }
    ],
    "sg:phone":"+61 3 9739 5145",
    "sg:postcode":"3140",
    "sg:province":"VIC",
    "sg:tags":[
        "beater",
        "painter",
        "panel"
    ],
    "wof:name":"Reform Industries",
    "wof:placetype":"venue"
},
  "geometry": {"coordinates":[145.37135314899999,-37.7570457458],"type":"Point"}
}