{
  "type": "Feature",
  "properties": {
    "addr:full":"115 Breakfast Creek Rd Newstead QLD 4006",
    "addr:housenumber":"115",
    "addr:postcode":"4006",
    "addr:street":"Breakfast Creek Rd",
    "iso:country":"AU",
    "sg:address":"115 Breakfast Creek Rd",
    "sg:city":"Newstead",
    "sg:classifiers":[
        {
            "category":"Social Services",
            "subcategory":"Adult Care",
            "type":"Services"
        }
    ],
    "sg:phone":"+61 7 3265 6700",
    "sg:postcode":"4006",
    "sg:province":"QLD",
    "sg:tags":[
        "towing"
    ],
    "wof:name":"City Auto Towing",
    "wof:placetype":"venue"
},
  "geometry": {"coordinates":[153.04307556099999,-27.4452133179],"type":"Point"}
}