{
  "type": "Feature",
  "properties": {
    "addr:full":"Unit 1, 8 Furniss Rd Landsdale WA 6065",
    "addr:housenumber":"8",
    "addr:postcode":"6065",
    "addr:street":"Furniss Rd",
    "iso:country":"AU",
    "sg:address":"Unit 1, 8 Furniss Rd",
    "sg:city":"Landsdale",
    "sg:classifiers":[
        {
            "category":"Building & Trades",
            "subcategory":"Construction",
            "type":"Services"
        }
    ],
    "sg:phone":"+61 8 9309 4099",
    "sg:postcode":"6065",
    "sg:province":"WA",
    "sg:tags":[
        "concrete",
        "treatment",
        "repair"
    ],
    "wof:name":"Gecko Special Coatings Pty Ltd",
    "wof:placetype":"venue"
},
  "geometry": {"coordinates":[115.841506958,-31.8046684265],"type":"Point"}
}