{
  "type": "Feature",
  "properties": {
    "addr:full":"448 Old Cleveland Rd Camp Hill QLD 4152",
    "addr:housenumber":"448",
    "addr:postcode":"4152",
    "addr:street":"Old Cleveland Rd",
    "iso:country":"AU",
    "sg:address":"448 Old Cleveland Rd",
    "sg:city":"Camp Hill",
    "sg:classifiers":[
        {
            "category":"Real Estate",
            "subcategory":"Real Estate Agent",
            "type":"Services"
        }
    ],
    "sg:phone":"+61 7 3843 1222",
    "sg:postcode":"4152",
    "sg:province":"QLD",
    "wof:name":"Camp Hill Real Estate",
    "wof:placetype":"venue"
},
  "geometry": {"coordinates":[153.06617736800001,-27.4917106628],"type":"Point"}
}