{
  "type": "Feature",
  "properties": {
    "addr:full":"7 Hilly St Mortlake NSW 2137",
    "addr:housenumber":"7",
    "addr:postcode":"2137",
    "addr:street":"Hilly St",
    "iso:country":"AU",
    "sg:address":"7 Hilly St",
    "sg:city":"Mortlake",
    "sg:classifiers":[
        {
            "category":"Wholesale",
            "subcategory":"Construction Materials",
            "type":"Manufacturing & Wholesale Goods"
        }
    ],
    "sg:phone":"+61 2 9743 2700",
    "sg:postcode":"2137",
    "sg:province":"NSW",
    "sg:tags":[
        "wholesaler",
        "lighting",
        "mfrs",
        "accessory"
    ],
    "wof:name":"Lighting 2000 NSW",
    "wof:placetype":"venue"
},
  "geometry": {"coordinates":[151.10661315900001,-33.841129303],"type":"Point"}
}