{
  "type": "Feature",
  "properties": {
    "iso:country":"AU",
    "sg:address":"265 St Georges Rd",
    "sg:city":"Northcote",
    "sg:classifiers":[
        {
            "category":"Shopping",
            "subcategory":"Clothing, Apparel, & Fashions",
            "type":"Retail Goods"
        }
    ],
    "sg:phone":"+61 3 9482 7577",
    "sg:postcode":"3070",
    "sg:province":"VIC",
    "sg:tags":[
        "menswear"
    ],
    "wof:name":"The Menswear Warehouse",
    "wof:placetype":"venue"
},
  "geometry": {"coordinates":[144.991913,-37.763874],"type":"Point"}
}