{
  "type": "Feature",
  "properties": {
    "addr:full":"Shop 8/362- 372 Kingsway Caringbah NSW 2229",
    "addr:housenumber":"shop 8 / 362 372",
    "addr:postcode":"2229",
    "addr:street":"Kingsway",
    "iso:country":"AU",
    "sg:address":"Shop 8/362- 372",
    "sg:city":"Kingsway Caringbah",
    "sg:classifiers":[
        {
            "category":"Personal",
            "subcategory":"Beauty Salon",
            "type":"Services"
        }
    ],
    "sg:phone":"+61 2 9526 2277",
    "sg:postcode":"2229",
    "sg:province":"NSW",
    "wof:name":"Mesmerise Nails & Beauty",
    "wof:placetype":"venue"
},
  "geometry": {"coordinates":[151.12057495100001,-34.0405578613],"type":"Point"}
}