{
  "type": "Feature",
  "properties": {
    "iso:country":"AU",
    "sg:address":"Illawarra Hwy",
    "sg:city":"Sutton Forest",
    "sg:classifiers":[
        {
            "category":"Education",
            "subcategory":"School",
            "type":"Public Place"
        }
    ],
    "sg:phone":"+61 2 4868 1430",
    "sg:postcode":"2577",
    "sg:province":"NSW",
    "sg:tags":[
        "state",
        "-",
        "nsw"
    ],
    "wof:name":"Sutton Forest Public School",
    "wof:placetype":"venue"
},
  "geometry": {"coordinates":[150.24922180199999,-34.5861167908],"type":"Point"}
}