{
  "type": "Feature",
  "properties": {
    "iso:country":"AU",
    "sg:address":"2/ 490 David St",
    "sg:city":"Albury",
    "sg:classifiers":[
        {
            "category":"Professional",
            "subcategory":"Engineering",
            "type":"Services"
        }
    ],
    "sg:phone":"+61 2 6021 7233",
    "sg:postcode":"2640",
    "sg:province":"NSW",
    "sg:tags":[
        "civil",
        "engineer"
    ],
    "wof:name":"SJE Consulting",
    "wof:placetype":"venue"
},
  "geometry": {"coordinates":[146.92083740199999,-36.0815429688],"type":"Point"}
}