{
  "type": "Feature",
  "properties": {
    "iso:country":"AU",
    "sg:address":"22 Dudley St",
    "sg:city":"Coogee",
    "sg:classifiers":[
        {
            "category":"Shopping",
            "subcategory":"Jewelry",
            "type":"Retail Goods"
        }
    ],
    "sg:phone":"+61 2 9665 3712",
    "sg:postcode":"2034",
    "sg:province":"NSW",
    "sg:tags":[
        "jeweller"
    ],
    "wof:name":"Frilly Lizard Enterprises",
    "wof:placetype":"venue"
},
  "geometry": {"coordinates":[151.24800109899999,-33.9221839905],"type":"Point"}
}