{
  "type": "Feature",
  "properties": {
    "iso:country":"AU",
    "sg:address":"675 Gympie Rd",
    "sg:city":"Strathpine",
    "sg:classifiers":[
        {
            "category":"Professional",
            "subcategory":"Accounting & Tax Preparation",
            "type":"Services"
        }
    ],
    "sg:phone":"+61 7 3205 5522",
    "sg:postcode":"4500",
    "sg:province":"QLD",
    "sg:tags":[
        "consultant",
        "taxation"
    ],
    "wof:name":"Di Tommaso Peter",
    "wof:placetype":"venue"
},
  "geometry": {"coordinates":[152.98883056599999,-27.3023834229],"type":"Point"}
}