{
  "type": "Feature",
  "properties": {
    "addr:full":"9 Rowan St Derby WA 6728",
    "addr:housenumber":"9",
    "addr:postcode":"6728",
    "addr:street":"Rowan St",
    "iso:country":"AU",
    "sg:address":"9 Rowan St",
    "sg:city":"Derby",
    "sg:classifiers":[
        {
            "category":"Travel",
            "subcategory":"Travel Agent",
            "type":"Entertainment"
        }
    ],
    "sg:phone":"+61 8 9193 2144",
    "sg:postcode":"6728",
    "sg:province":"WA",
    "sg:tags":[
        "tour",
        "holiday",
        "adventure"
    ],
    "wof:name":"Big River Adventure Tours & Holidays",
    "wof:placetype":"venue"
},
  "geometry": {"coordinates":[123.62647247300001,-17.3048171997],"type":"Point"}
}