{
  "type": "Feature",
  "properties": {
    "iso:country":"AU",
    "sg:address":"Shop 4 121 The Cove Rd",
    "sg:city":"Hallett Cove",
    "sg:classifiers":[
        {
            "category":"Health Services",
            "subcategory":"Doctor",
            "type":"Services"
        }
    ],
    "sg:phone":"+61 8 8387 3040",
    "sg:postcode":"5158",
    "sg:province":"SA",
    "sg:tags":[
        "medical",
        "practitioner"
    ],
    "wof:name":"Bilski Arthur G",
    "wof:placetype":"venue"
},
  "geometry": {"coordinates":[138.505584717,-35.0650024414],"type":"Point"}
}