{
  "type": "Feature",
  "properties": {
    "addr:full":"Cnr Bond St & Boundary Rd Mordialloc VIC 3195",
    "addr:postcode":"3195",
    "addr:street":"Cnr Bond St & Boundary Rd",
    "iso:country":"AU",
    "sg:address":"Cnr Bond St & Boundary Rd",
    "sg:city":"Mordialloc",
    "sg:classifiers":[
        {
            "category":"Retail",
            "subcategory":"Auto Repair",
            "type":"Services"
        }
    ],
    "sg:phone":"+61 3 9588 0550",
    "sg:postcode":"3195",
    "sg:province":"VIC",
    "sg:tags":[
        "clutch",
        "brake"
    ],
    "wof:name":"Brakes Plus",
    "wof:placetype":"venue"
},
  "geometry": {"coordinates":[145.10647582999999,-37.9925384521],"type":"Point"}
}