{
  "type": "Feature",
  "properties": {
    "addr:full":"U2/ 8 Royal St Kenwick WA 6107",
    "addr:housenumber":"8",
    "addr:postcode":"6107",
    "addr:street":"U2 /;Royal St",
    "iso:country":"AU",
    "sg:address":"U2/ 8 Royal St",
    "sg:city":"Kenwick",
    "sg:classifiers":[
        {
            "category":"Building & Trades",
            "subcategory":"Cleaning & Sanitation",
            "type":"Services"
        }
    ],
    "sg:phone":"+61 8 9452 3338",
    "sg:postcode":"6107",
    "sg:province":"WA",
    "sg:tags":[
        "commercial",
        "maintenance"
    ],
    "wof:name":"Emmanual Property Maintenance",
    "wof:placetype":"venue"
},
  "geometry": {"coordinates":[115.96824646,-32.0377616882],"type":"Point"}
}