{
  "type": "Feature",
  "properties": {
    "addr:full":"Level 6, The Atrium, 211 La Trobe St Melbourne VIC 3000",
    "addr:housenumber":"211",
    "addr:postcode":"3000",
    "addr:street":"La Trobe St",
    "iso:country":"AU",
    "sg:address":"Level 6, The Atrium, 211 La Trobe St",
    "sg:city":"Melbourne",
    "sg:classifiers":[
        {
            "category":"Shopping",
            "subcategory":"Department Store",
            "type":"Retail Goods"
        }
    ],
    "sg:phone":"+61 3 9922 1100",
    "sg:postcode":"3000",
    "sg:province":"VIC",
    "wof:name":"Melbourne Central",
    "wof:placetype":"venue"
},
  "geometry": {"coordinates":[144.963424683,-37.8098258972],"type":"Point"}
}