{
  "type": "Feature",
  "properties": {
    "addr:full":"PO Box 367 Horsley Park NSW 2175",
    "addr:postcode":"2175",
    "iso:country":"AU",
    "sg:address":"PO Box 367",
    "sg:city":"Horsley Park",
    "sg:classifiers":[
        {
            "category":"Professional",
            "subcategory":"Business Services",
            "type":"Services"
        }
    ],
    "sg:phone":"+61 418 295 425",
    "sg:postcode":"2175",
    "sg:province":"NSW",
    "sg:tags":[
        "management",
        "event"
    ],
    "wof:name":"WOW Factor Events",
    "wof:placetype":"venue"
},
  "geometry": {"coordinates":[150.85403442399999,-33.8411483765],"type":"Point"}
}