{
  "type": "Feature",
  "properties": {
    "addr:full":"17 Johnston St Collie WA 6225",
    "addr:housenumber":"17",
    "addr:postcode":"6225",
    "addr:street":"Johnston St",
    "iso:country":"AU",
    "sg:address":"17 Johnston St",
    "sg:city":"Collie",
    "sg:classifiers":[
        {
            "category":"Health Services",
            "subcategory":"Doctor",
            "type":"Services"
        }
    ],
    "sg:phone":"+61 8 9734 1233",
    "sg:postcode":"6225",
    "sg:province":"WA",
    "sg:tags":[
        "medical",
        "practitioner"
    ],
    "wof:name":"Collie Medical Group",
    "wof:placetype":"venue"
},
  "geometry": {"coordinates":[116.157028,-33.358654],"type":"Point"}
}