{
  "type": "Feature",
  "properties": {
    "iso:country":"AU",
    "sg:address":"unit 4/ 10 Combarton St",
    "sg:city":"Brendale",
    "sg:classifiers":[
        {
            "category":"Wholesale",
            "subcategory":"Durable Goods & Equipment",
            "type":"Manufacturing & Wholesale Goods"
        }
    ],
    "sg:phone":"+61 1800 640 113",
    "sg:postcode":"4500",
    "sg:province":"QLD",
    "sg:tags":[
        "abrasive",
        "blasting"
    ],
    "wof:name":"Blasto Industries",
    "wof:placetype":"venue"
},
  "geometry": {"coordinates":[152.98359680199999,-27.3216934204],"type":"Point"}
}