{
  "type": "Feature",
  "properties": {
    "iso:country":"AU",
    "sg:address":"16 Hargraves St",
    "sg:city":"The Entrance North",
    "sg:classifiers":[
        {
            "category":"Recreation",
            "subcategory":"Fishing",
            "type":"Entertainment"
        }
    ],
    "sg:phone":"+61 2 4332 8183",
    "sg:postcode":"2261",
    "sg:province":"NSW",
    "sg:tags":[
        "tackle"
    ],
    "wof:name":"Vonnis Convenience Store",
    "wof:placetype":"venue"
},
  "geometry": {"coordinates":[151.503418,-33.337021],"type":"Point"}
}