{
  "type": "Feature",
  "properties": {
    "iso:country":"AU",
    "sg:address":"Disney St",
    "sg:city":"Brentwood",
    "sg:classifiers":[
        {
            "category":"Sports & Exercise",
            "subcategory":"Sports Center",
            "type":"Entertainment"
        }
    ],
    "sg:phone":"+61 8 9364 2874",
    "sg:postcode":"6153",
    "sg:province":"WA",
    "sg:tags":[
        "ground"
    ],
    "wof:name":"Blue Gum Park Squash Centre",
    "wof:placetype":"venue"
},
  "geometry": {"coordinates":[115.845688,-32.041031],"type":"Point"}
}