{
  "type": "Feature",
  "properties": {
    "addr:full":"35 Hargreaves St White Rock QLD 4868",
    "addr:housenumber":"35",
    "addr:postcode":"4868",
    "addr:street":"Hargreaves St",
    "iso:country":"AU",
    "sg:address":"35 Hargreaves St",
    "sg:city":"White Rock",
    "sg:classifiers":[
        {
            "category":"Wholesale",
            "subcategory":"Electrical",
            "type":"Manufacturing & Wholesale Goods"
        }
    ],
    "sg:phone":"+61 7 4045 0488",
    "sg:postcode":"4868",
    "sg:province":"QLD",
    "sg:tags":[
        "wholesaler"
    ],
    "wof:name":"Southside Electrical Wholesalers",
    "wof:placetype":"venue"
},
  "geometry": {"coordinates":[145.7447052,-17.0005493164],"type":"Point"}
}