{
  "type": "Feature",
  "properties": {
    "addr:full":"82 Oliver St Inverell NSW 2360",
    "addr:housenumber":"82",
    "addr:postcode":"2360",
    "addr:street":"Oliver St",
    "iso:country":"AU",
    "sg:address":"82 Oliver St",
    "sg:city":"Inverell",
    "sg:classifiers":[
        {
            "category":"Retail",
            "subcategory":"Auto Repair",
            "type":"Services"
        }
    ],
    "sg:phone":"+61 2 6722 3502",
    "sg:postcode":"2360",
    "sg:province":"NSW",
    "sg:tags":[
        "gas",
        "conversion",
        "natural",
        "lp",
        "vehicle"
    ],
    "wof:name":"Doug Lowry Automotive",
    "wof:placetype":"venue"
},
  "geometry": {"coordinates":[151.12086486800001,-29.7691688538],"type":"Point"}
}