{
  "type": "Feature",
  "properties": {
    "addr:full":"42 River St Maclean NSW 2463",
    "addr:housenumber":"42",
    "addr:postcode":"2463",
    "addr:street":"River St",
    "iso:country":"AU",
    "sg:address":"42 River St",
    "sg:city":"Maclean",
    "sg:classifiers":[
        {
            "category":"Retail",
            "subcategory":"Veterinary Services",
            "type":"Services"
        }
    ],
    "sg:phone":"+61 2 6645 2864",
    "sg:postcode":"2463",
    "sg:province":"NSW",
    "sg:tags":[
        "surgeon"
    ],
    "wof:name":"Maclean Veterinary Clinic",
    "wof:placetype":"venue"
},
  "geometry": {"coordinates":[153.20234680199999,-29.4482917786],"type":"Point"}
}