{
  "type": "Feature",
  "properties": {
    "iso:country":"AU",
    "sg:address":"28 Clianthus Rd",
    "sg:city":"Kambalda West",
    "sg:classifiers":[
        {
            "category":"Mining & Drilling",
            "type":"Manufacturing & Wholesale Goods"
        }
    ],
    "sg:phone":"+61 8 9027 0303",
    "sg:postcode":"6444",
    "sg:province":"WA",
    "sg:tags":[
        "equipment",
        "quarrying",
        "supply"
    ],
    "wof:name":"Kambalda Bits Sharpening & Supplies",
    "wof:placetype":"venue"
},
  "geometry": {"coordinates":[121.610717773,-31.2098007202],"type":"Point"}
}