{
  "type": "Feature",
  "properties": {
    "addr:full":"54 Neich Rd Maraylya NSW 2765",
    "addr:housenumber":"54",
    "addr:postcode":"2765",
    "addr:street":"Neich Rd",
    "iso:country":"AU",
    "sg:address":"54 Neich Rd",
    "sg:city":"Maraylya",
    "sg:classifiers":[
        {
            "category":"Personal",
            "type":"Services"
        }
    ],
    "sg:phone":"+61 2 4573 6129",
    "sg:postcode":"2765",
    "sg:province":"NSW",
    "sg:tags":[
        "dressmaker"
    ],
    "wof:name":"Andrea Andrejas",
    "wof:placetype":"venue"
},
  "geometry": {"coordinates":[150.910064697,-33.5911331177],"type":"Point"}
}