{
  "type": "Feature",
  "properties": {
    "addr:full":"90B Oldaker St Devonport TAS 7310",
    "addr:housenumber":"90b",
    "addr:postcode":"7310",
    "addr:street":"Oldaker St",
    "iso:country":"AU",
    "sg:address":"90B Oldaker St",
    "sg:city":"Devonport",
    "sg:classifiers":[
        {
            "category":"Shopping",
            "subcategory":"Clothing, Apparel, & Fashions",
            "type":"Retail Goods"
        }
    ],
    "sg:phone":"+61 3 6423 1231",
    "sg:postcode":"7310",
    "sg:province":"TAS",
    "sg:tags":[
        "recycled",
        "clothing"
    ],
    "wof:name":"Second Time Around Fashions",
    "wof:placetype":"venue"
},
  "geometry": {"coordinates":[146.36015319800001,-41.1811943054],"type":"Point"}
}