{
  "type": "Feature",
  "properties": {
    "addr:full":"24 Barnet St Yarraville VIC 3013",
    "addr:housenumber":"24",
    "addr:postcode":"3013",
    "addr:street":"Barnet St",
    "iso:country":"AU",
    "sg:address":"24 Barnet St",
    "sg:city":"Yarraville",
    "sg:classifiers":[
        {
            "category":"Real Estate",
            "subcategory":"Architect",
            "type":"Services"
        }
    ],
    "sg:phone":"+61 3 9687 9349",
    "sg:postcode":"3013",
    "sg:province":"VIC",
    "wof:name":"Tom Bulic",
    "wof:placetype":"venue"
},
  "geometry": {"coordinates":[144.89222717300001,-37.811504364],"type":"Point"}
}