{
  "type": "Feature",
  "properties": {
    "addr:full":"PO Box 573 Nightcliff Private Boxes NT 0814",
    "addr:postcode":"nt 0814",
    "iso:country":"AU",
    "sg:address":"PO Box 573",
    "sg:city":"Nightcliff Private Boxes",
    "sg:classifiers":[
        {
            "category":"Education",
            "subcategory":"University",
            "type":"Public Place"
        }
    ],
    "sg:phone":"+61 8 8948 0555",
    "sg:postcode":"0814",
    "sg:province":"NT",
    "sg:tags":[
        "educational",
        "organisation",
        "cultural"
    ],
    "wof:name":"LIFE EDUCATION TOP END",
    "wof:placetype":"venue"
},
  "geometry": {"coordinates":[130.856064,-12.387455],"type":"Point"}
}