{
  "type": "Feature",
  "properties": {
    "addr:full":"10 Rooney St Everton Park QLD 4053",
    "addr:housenumber":"10",
    "addr:postcode":"4053",
    "addr:street":"Rooney St",
    "iso:country":"AU",
    "sg:address":"10 Rooney St",
    "sg:city":"Everton Park",
    "sg:classifiers":[
        {
            "category":"Education",
            "subcategory":"Music School",
            "type":"Public Place"
        }
    ],
    "sg:phone":"+61 7 3355 3665",
    "sg:postcode":"4053",
    "sg:province":"QLD",
    "sg:tags":[
        "teacher"
    ],
    "wof:name":"JNJ Creative",
    "wof:placetype":"venue"
},
  "geometry": {"coordinates":[152.99473571799999,-27.3990955353],"type":"Point"}
}