{
  "type": "Feature",
  "properties": {
    "addr:full":"413 Princes Hwy Rockdale NSW 2216",
    "addr:housenumber":"413",
    "addr:postcode":"2216",
    "addr:street":"Princes Hwy",
    "iso:country":"AU",
    "sg:address":"413 Princes Hwy",
    "sg:city":"Rockdale",
    "sg:classifiers":[
        {
            "category":"Home & Garden",
            "subcategory":"Carpets & Floor Coverings",
            "type":"Retail Goods"
        }
    ],
    "sg:phone":"+61 2 9567 8971",
    "sg:postcode":"2216",
    "sg:province":"NSW",
    "sg:tags":[
        "tile",
        "wall"
    ],
    "wof:name":"Crown Tiles",
    "wof:placetype":"venue"
},
  "geometry": {"coordinates":[151.139206,-33.949352],"type":"Point"}
}