{
  "type": "Feature",
  "properties": {
    "iso:country":"AU",
    "sg:address":"121 Mackie Rd",
    "sg:city":"Narangba",
    "sg:classifiers":[
        {
            "category":"Professional",
            "subcategory":"Detective & Security Services",
            "type":"Services"
        }
    ],
    "sg:phone":"+61 7 3888 0111",
    "sg:postcode":"4504",
    "sg:province":"QLD",
    "sg:tags":[
        "equipment",
        "window",
        "doors"
    ],
    "wof:name":"Blinds By Ken",
    "wof:placetype":"venue"
},
  "geometry": {"coordinates":[152.972732544,-27.1996707916],"type":"Point"}
}