{
  "type": "Feature",
  "properties": {
    "addr:full":"97 Mary St Grafton NSW 2460",
    "addr:housenumber":"97",
    "addr:postcode":"2460",
    "addr:street":"Mary St",
    "iso:country":"AU",
    "sg:address":"97 Mary St",
    "sg:city":"Grafton",
    "sg:classifiers":[
        {
            "category":"Education",
            "subcategory":"School",
            "type":"Public Place"
        }
    ],
    "sg:phone":"+61 2 6642 3355",
    "sg:postcode":"2460",
    "sg:province":"NSW",
    "sg:tags":[
        "state",
        "-",
        "nsw"
    ],
    "wof:name":"Grafton High School",
    "wof:placetype":"venue"
},
  "geometry": {"coordinates":[152.93417358400001,-29.68217659],"type":"Point"}
}