{
  "type": "Feature",
  "properties": {
    "addr:full":"Ste2/ 321 Camberwell Rd Camberwell VIC 3124",
    "addr:housenumber":"321",
    "addr:postcode":"3124",
    "addr:street":"Camberwell Rd",
    "iso:country":"AU",
    "sg:address":"Ste2/ 321 Camberwell Rd",
    "sg:city":"Camberwell",
    "sg:classifiers":[
        {
            "category":"Health Services",
            "subcategory":"Doctor",
            "type":"Services"
        }
    ],
    "sg:phone":"+61 3 9813 5700",
    "sg:postcode":"3124",
    "sg:province":"VIC",
    "sg:tags":[
        "medical",
        "practitioner"
    ],
    "wof:name":"Melbourne Children's Clinic The",
    "wof:placetype":"venue"
},
  "geometry": {"coordinates":[145.059326172,-37.8333053589],"type":"Point"}
}