{
  "type": "Feature",
  "properties": {
    "addr:full":"PO Box 182 St Peters NSW 2044",
    "addr:postcode":"2044",
    "iso:country":"AU",
    "sg:address":"PO Box 182",
    "sg:city":"St Peters",
    "sg:classifiers":[
        {
            "category":"Shopping",
            "subcategory":"Pets & Pet Supplies",
            "type":"Retail Goods"
        }
    ],
    "sg:phone":"+61 2 9550 3890",
    "sg:postcode":"2044",
    "sg:province":"NSW",
    "sg:tags":[
        "shop",
        "supplier"
    ],
    "wof:name":"Botany Bay Imports Exports",
    "wof:placetype":"venue"
},
  "geometry": {"coordinates":[151.17735300000001,-33.914299],"type":"Point"}
}