{
  "type": "Feature",
  "properties": {
    "addr:full":"1 Peninsula Drv Batemans Bay NSW 2536",
    "addr:housenumber":"1",
    "addr:postcode":"2536",
    "addr:street":"Peninsula Drv",
    "iso:country":"AU",
    "sg:address":"1 Peninsula Drv",
    "sg:city":"Batemans Bay",
    "sg:classifiers":[
        {
            "category":"Retail",
            "subcategory":"Veterinary Services",
            "type":"Services"
        }
    ],
    "sg:phone":"+61 2 4472 8877",
    "sg:postcode":"2536",
    "sg:province":"NSW",
    "sg:tags":[
        "surgeon"
    ],
    "wof:name":"Roberts Paula Dr",
    "wof:placetype":"venue"
},
  "geometry": {"coordinates":[150.184158325,-35.7002296448],"type":"Point"}
}