{
  "type": "Feature",
  "properties": {
    "addr:full":"2400 Warburton Hwy Yarra Junction VIC 3797",
    "addr:housenumber":"2400",
    "addr:postcode":"3797",
    "addr:street":"Warburton Hwy",
    "iso:country":"AU",
    "sg:address":"2400 Warburton Hwy",
    "sg:city":"Yarra Junction",
    "sg:classifiers":[
        {
            "category":"Home & Garden",
            "subcategory":"Household Appliances",
            "type":"Retail Goods"
        }
    ],
    "sg:phone":"+61 3 5967 1003",
    "sg:postcode":"3797",
    "sg:province":"VIC",
    "sg:tags":[
        "equipment",
        "gas"
    ],
    "wof:name":"Yarra Junction Hardware",
    "wof:placetype":"venue"
},
  "geometry": {"coordinates":[145.61239624000001,-37.7815704346],"type":"Point"}
}