{
  "type": "Feature",
  "properties": {
    "addr:full":"Coolum Shopping Village Birtwill St Coolum Beach QLD 4573",
    "addr:postcode":"4573",
    "addr:street":"St",
    "iso:country":"AU",
    "sg:address":"Coolum Shopping Village Birtwill St",
    "sg:city":"Coolum Beach",
    "sg:classifiers":[
        {
            "category":"Communications",
            "subcategory":"Film & Video Production",
            "type":"Services"
        }
    ],
    "sg:phone":"+61 7 5446 1698",
    "sg:postcode":"4573",
    "sg:province":"QLD",
    "sg:tags":[
        "dvd",
        "library"
    ],
    "wof:name":"Video Ezy",
    "wof:placetype":"venue"
},
  "geometry": {"coordinates":[153.08812,-26.526852],"type":"Point"}
}