{
  "type": "Feature",
  "properties": {
    "iso:country":"AU",
    "sg:address":"130 Francisco St",
    "sg:city":"Belmont",
    "sg:classifiers":[
        {
            "category":"Wholesale",
            "subcategory":"Painting Supplies",
            "type":"Manufacturing & Wholesale Goods"
        }
    ],
    "sg:phone":"+61 8 9475 0633",
    "sg:postcode":"6104",
    "sg:province":"WA",
    "sg:tags":[
        "equipment",
        "tiling"
    ],
    "wof:name":"DTA Australia Pty Ltd",
    "wof:placetype":"venue"
},
  "geometry": {"coordinates":[115.922203064,-31.954536438],"type":"Point"}
}