{
  "type": "Feature",
  "properties": {
    "addr:full":"8 Cumbee La Caringbah NSW 2229",
    "addr:housenumber":"8",
    "addr:postcode":"2229",
    "addr:street":"Cumbee La",
    "iso:country":"AU",
    "sg:address":"8 Cumbee La",
    "sg:city":"Caringbah",
    "sg:classifiers":[
        {
            "category":"Building & Trades",
            "subcategory":"Plumbing",
            "type":"Services"
        }
    ],
    "sg:phone":"+61 418 233 217",
    "sg:postcode":"2229",
    "sg:province":"NSW",
    "sg:tags":[
        "plumber",
        "gasfitters"
    ],
    "wof:name":"Lous Drainage Pty Ltd",
    "wof:placetype":"venue"
},
  "geometry": {"coordinates":[151.131347656,-34.0637397766],"type":"Point"}
}