{
  "type": "Feature",
  "properties": {
    "addr:full":"30 Graham Rd View Bank VIC 3084",
    "addr:housenumber":"30",
    "addr:postcode":"3084",
    "addr:street":"Graham Rd View",
    "iso:country":"AU",
    "sg:address":"30 Graham Rd",
    "sg:city":"View Bank",
    "sg:classifiers":[
        {
            "category":"Real Estate",
            "subcategory":"Real Estate Operator",
            "type":"Services"
        }
    ],
    "sg:phone":"+61 430 359 094",
    "sg:postcode":"3084",
    "sg:province":"VIC",
    "sg:tags":[
        "concrete",
        "pumping"
    ],
    "wof:name":"Rincon Concrete Pumping",
    "wof:placetype":"venue"
},
  "geometry": {"coordinates":[145.083694458,-37.7422409058],"type":"Point"}
}