{
  "type": "Feature",
  "properties": {
    "iso:country":"AU",
    "sg:address":"PO Box 57",
    "sg:city":"Gibson",
    "sg:classifiers":[
        {
            "category":"Professional",
            "subcategory":"Research",
            "type":"Services"
        }
    ],
    "sg:phone":"+61 8 9075 4061",
    "sg:postcode":"6448",
    "sg:province":"WA",
    "sg:tags":[
        "industrial",
        "scientific"
    ],
    "wof:name":"Esperance Downs Research Station",
    "wof:placetype":"venue"
},
  "geometry": {"coordinates":[121.810836792,-33.646320343],"type":"Point"}
}