{
  "type": "Feature",
  "properties": {
    "iso:country":"AU",
    "sg:address":"53- 55 Captain Cook Drv",
    "sg:city":"Caringbah",
    "sg:classifiers":[
        {
            "category":"Autos & Motor Vehicles",
            "subcategory":"Auto Supplies",
            "type":"Retail Goods"
        }
    ],
    "sg:phone":"+61 2 9524 6456",
    "sg:postcode":"2229",
    "sg:province":"NSW",
    "sg:tags":[
        "part",
        "cycles",
        "accessory"
    ],
    "wof:name":"Caringbah Motorcycles",
    "wof:placetype":"venue"
},
  "geometry": {"coordinates":[151.12184143100001,-34.031955719],"type":"Point"}
}