{
  "type": "Feature",
  "properties": {
    "addr:full":"Lot 12, Roh's Rd Bendigo VIC 3550",
    "addr:postcode":"3550",
    "addr:street":"Roh'S Rd",
    "iso:country":"AU",
    "sg:address":"Lot 12, Roh's Rd",
    "sg:city":"Bendigo",
    "sg:classifiers":[
        {
            "category":"Building & Trades",
            "subcategory":"Plumbing",
            "type":"Services"
        }
    ],
    "sg:phone":"+61 418 333 652",
    "sg:postcode":"3550",
    "sg:province":"VIC",
    "sg:tags":[
        "plumber",
        "gasfitters"
    ],
    "wof:name":"Strathfieldsaye Plumbing",
    "wof:placetype":"venue"
},
  "geometry": {"coordinates":[144.28622436500001,-36.7638511658],"type":"Point"}
}