{
  "type": "Feature",
  "properties": {
    "iso:country":"AU",
    "sg:address":"Suite 7, The Chancellory, 155 Missenden Rd",
    "sg:city":"Newtown",
    "sg:classifiers":[
        {
            "category":"Health Services",
            "subcategory":"Health Practitioner",
            "type":"Services"
        }
    ],
    "sg:phone":"+61 1300 133 277",
    "sg:postcode":"2042",
    "sg:province":"NSW",
    "sg:tags":[
        "consultant",
        "conservation",
        "hearing"
    ],
    "wof:name":"McNeill Celene",
    "wof:placetype":"venue"
},
  "geometry": {"coordinates":[151.182831,-33.892147],"type":"Point"}
}