{
  "type": "Feature",
  "properties": {
    "iso:country":"AU",
    "sg:address":"Shop 5/ 55 Princes Hwy",
    "sg:city":"Beaconsfield",
    "sg:classifiers":[
        {
            "category":"Fast Food",
            "type":"Food & Drink"
        }
    ],
    "sg:phone":"+61 3 9769 7720",
    "sg:postcode":"3807",
    "sg:province":"VIC",
    "sg:tags":[
        "away",
        "take"
    ],
    "wof:name":"Chick N Feed",
    "wof:placetype":"venue"
},
  "geometry": {"coordinates":[145.36958313,-38.0477333069],"type":"Point"}
}