{
  "type": "Feature",
  "properties": {
    "addr:full":"202 McPherson Rd Tuggerah NSW 2259",
    "addr:housenumber":"202",
    "addr:postcode":"2259",
    "addr:street":"Mcpherson Rd",
    "iso:country":"AU",
    "sg:address":"202 McPherson Rd",
    "sg:city":"Tuggerah",
    "sg:classifiers":[
        {
            "category":"Retail",
            "subcategory":"Car Wash",
            "type":"Services"
        }
    ],
    "sg:phone":"+61 2 4351 0718",
    "sg:postcode":"2259",
    "sg:province":"NSW",
    "sg:tags":[
        "truck",
        "cleaning"
    ],
    "wof:name":"Coastal Car Detailing",
    "wof:placetype":"venue"
},
  "geometry": {"coordinates":[151.395263672,-33.2889404297],"type":"Point"}
}