{
  "type": "Feature",
  "properties": {
    "addr:full":"1899 Ipswich Rd Rocklea QLD 4106",
    "addr:housenumber":"1899",
    "addr:postcode":"4106",
    "addr:street":"Ipswich Rd",
    "iso:country":"AU",
    "sg:address":"1899 Ipswich Rd",
    "sg:city":"Rocklea",
    "sg:classifiers":[
        {
            "category":"Retail",
            "subcategory":"Auto Repair",
            "type":"Services"
        }
    ],
    "sg:phone":"+61 7 3308 5388",
    "sg:postcode":"4106",
    "sg:province":"QLD",
    "sg:tags":[
        "clutch",
        "brake"
    ],
    "wof:name":"Bridgestone Tyre Centres",
    "wof:placetype":"venue"
},
  "geometry": {"coordinates":[152.995635986,-27.5608215332],"type":"Point"}
}