{
  "type": "Feature",
  "properties": {
    "addr:full":"24 Bellara Ave North Narrabeen NSW 2101",
    "addr:housenumber":"24",
    "addr:postcode":"2101",
    "addr:street":"Bellara Ave",
    "iso:country":"AU",
    "sg:address":"24 Bellara Ave",
    "sg:city":"North Narrabeen",
    "sg:classifiers":[
        {
            "category":"Utilities",
            "subcategory":"Electric",
            "type":"Services"
        }
    ],
    "sg:phone":"+61 2 9913 2650",
    "sg:postcode":"2101",
    "sg:province":"NSW",
    "sg:tags":[
        "electrical",
        "contractor"
    ],
    "wof:name":"Kelleher D J",
    "wof:placetype":"venue"
},
  "geometry": {"coordinates":[151.287766,-33.701603],"type":"Point"}
}