{
  "type": "Feature",
  "properties": {
    "iso:country":"AU",
    "sg:address":"11 Wimborne Ave",
    "sg:city":"Mt Eliza",
    "sg:classifiers":[
        {
            "category":"Banks & Credit Unions",
            "subcategory":"Bureau De Change",
            "type":"Services"
        }
    ],
    "sg:phone":"+61 3 9787 7566",
    "sg:postcode":"3930",
    "sg:province":"VIC",
    "sg:tags":[
        "wheel",
        "industrial"
    ],
    "wof:name":"Australian Wheel & Castor",
    "wof:placetype":"venue"
},
  "geometry": {"coordinates":[145.08049011200001,-38.1804428101],"type":"Point"}
}