{
  "type": "Feature",
  "properties": {
    "addr:full":"12 Old Creswick Rd Ballarat VIC 3350",
    "addr:housenumber":"12",
    "addr:postcode":"3350",
    "addr:street":"Old Creswick Rd",
    "iso:country":"AU",
    "sg:address":"12 Old Creswick Rd",
    "sg:city":"Ballarat",
    "sg:classifiers":[
        {
            "category":"Professional",
            "subcategory":"Printing & Photocopies",
            "type":"Services"
        }
    ],
    "sg:phone":"+61 3 5339 9840",
    "sg:postcode":"3350",
    "sg:province":"VIC",
    "sg:tags":[
        "plaque"
    ],
    "wof:name":"Grigsby's Foundry",
    "wof:placetype":"venue"
},
  "geometry": {"coordinates":[143.84930399999999,-37.525589],"type":"Point"}
}