{
  "type": "Feature",
  "properties": {
    "addr:full":"12 Second Ave Victor Harbor SA 5211",
    "addr:housenumber":"12",
    "addr:postcode":"5211",
    "addr:street":"Second Ave",
    "iso:country":"AU",
    "sg:address":"12 Second Ave",
    "sg:city":"Victor Harbor",
    "sg:classifiers":[
        {
            "category":"Professional",
            "type":"Services"
        }
    ],
    "sg:phone":"+61 412 834 666",
    "sg:postcode":"5211",
    "sg:province":"SA",
    "sg:tags":[
        "transport"
    ],
    "wof:name":"Steve Martin's Transport",
    "wof:placetype":"venue"
},
  "geometry": {"coordinates":[138.650314331,-35.53515625],"type":"Point"}
}