{
  "type": "Feature",
  "properties": {
    "addr:full":"Shp2/ 33 Railway Pde Eastwood NSW 2122",
    "addr:housenumber":"33",
    "addr:postcode":"2122",
    "addr:street":"Railway Pde",
    "iso:country":"AU",
    "sg:address":"Shp2/ 33 Railway Pde",
    "sg:city":"Eastwood",
    "sg:classifiers":[
        {
            "category":"Personal",
            "subcategory":"Beauty Salon",
            "type":"Services"
        }
    ],
    "sg:phone":"+61 2 9858 1299",
    "sg:postcode":"2122",
    "sg:province":"NSW",
    "sg:tags":[
        "hairdresser"
    ],
    "wof:name":"Carlino Hairdressing",
    "wof:placetype":"venue"
},
  "geometry": {"coordinates":[151.082962036,-33.789642334],"type":"Point"}
}