{
  "type": "Feature",
  "properties": {
    "addr:full":"177 Bussell Hwy Margaret River WA 6285",
    "addr:housenumber":"177",
    "addr:postcode":"6285",
    "addr:street":"Bussell Hwy",
    "iso:country":"AU",
    "sg:address":"177 Bussell Hwy",
    "sg:city":"Margaret River",
    "sg:classifiers":[
        {
            "category":"Banks & Credit Unions",
            "subcategory":"Financial Services",
            "type":"Services"
        }
    ],
    "sg:phone":"+61 8 9757 3253",
    "sg:postcode":"6285",
    "sg:province":"WA",
    "sg:tags":[
        "settlement",
        "nt",
        "agent",
        "wa"
    ],
    "wof:name":"Brennan Damien Barrister & Solicitor & Settlements",
    "wof:placetype":"venue"
},
  "geometry": {"coordinates":[115.07459258999999,-33.9566993713],"type":"Point"}
}