{
  "type": "Feature",
  "properties": {
    "addr:full":"21a Wright St Adelaide SA 5000",
    "addr:housenumber":"21a",
    "addr:postcode":"5000",
    "addr:street":"Wright St",
    "iso:country":"AU",
    "sg:address":"21a Wright St",
    "sg:city":"Adelaide",
    "sg:classifiers":[
        {
            "category":"Utilities",
            "subcategory":"Refuse",
            "type":"Services"
        }
    ],
    "sg:phone":"+61 8 8212 7802",
    "sg:postcode":"5000",
    "sg:province":"SA",
    "sg:tags":[
        "wholesale",
        "glassware",
        "china",
        "earthenware"
    ],
    "wof:name":"H.A.G. Import Corp (Australia) Pty Ltd",
    "wof:placetype":"venue"
},
  "geometry": {"coordinates":[138.59922790499999,-34.9316902161],"type":"Point"}
}