{
  "type": "Feature",
  "properties": {
    "addr:full":"14 William St Balaclava VIC 3183",
    "addr:housenumber":"14",
    "addr:postcode":"3183",
    "addr:street":"William St",
    "iso:country":"AU",
    "sg:address":"14 William St",
    "sg:city":"Balaclava",
    "sg:classifiers":[
        {
            "category":"Shopping",
            "subcategory":"Computers & Home Electronics",
            "type":"Retail Goods"
        }
    ],
    "sg:phone":"+61 3 9525 9012",
    "sg:postcode":"3183",
    "sg:province":"VIC",
    "sg:tags":[
        "equipment",
        "supply"
    ],
    "wof:name":"Fixdata Computer Supplies",
    "wof:placetype":"venue"
},
  "geometry": {"coordinates":[144.994415283,-37.8694877625],"type":"Point"}
}