{
  "type": "Feature",
  "properties": {
    "addr:full":"Minnesota Rd Wyong North NSW 2259",
    "addr:postcode":"2259",
    "addr:street":"Minnesota Rd",
    "iso:country":"AU",
    "sg:address":"Minnesota Rd",
    "sg:city":"Wyong North",
    "sg:classifiers":[
        {
            "category":"Place Of Worship",
            "subcategory":"Monastery",
            "type":"Public Place"
        }
    ],
    "sg:phone":"+61 2 4392 7855",
    "sg:postcode":"2259",
    "sg:province":"NSW",
    "sg:tags":[
        "residential",
        "village"
    ],
    "wof:name":"Palm Springs Mobile Home Village",
    "wof:placetype":"venue"
},
  "geometry": {"coordinates":[151.468460083,-33.2447128296],"type":"Point"}
}