{
  "type": "Feature",
  "properties": {
    "iso:country":"AU",
    "sg:address":"PO Box 593",
    "sg:city":"Sandgate",
    "sg:classifiers":[
        {
            "category":"Building & Trades",
            "subcategory":"Equipment Rental",
            "type":"Services"
        }
    ],
    "sg:phone":"+61 418 873 927",
    "sg:postcode":"4017",
    "sg:province":"QLD",
    "sg:tags":[
        "platform",
        "hire",
        "work",
        "elevating"
    ],
    "wof:name":"Brisbane Scissor Lift Hire",
    "wof:placetype":"venue"
},
  "geometry": {"coordinates":[153.06629943900001,-27.3157997131],"type":"Point"}
}