{
  "type": "Feature",
  "properties": {
    "addr:full":"Cnr Warrigal & Dandenong Rds Oakleigh VIC 3166",
    "addr:postcode":"3166",
    "addr:street":"Cnr",
    "iso:country":"AU",
    "sg:address":"Cnr Warrigal & Dandenong Rds",
    "sg:city":"Oakleigh",
    "sg:classifiers":[
        {
            "category":"Autos & Motor Vehicles",
            "subcategory":"Auto Supplies",
            "type":"Retail Goods"
        }
    ],
    "sg:phone":"+61 3 9568 4366",
    "sg:postcode":"3166",
    "sg:province":"VIC",
    "sg:tags":[
        "wheel",
        "four",
        "equipment",
        "drive",
        "accessory"
    ],
    "wof:name":"Bob Jane T-Marts",
    "wof:placetype":"venue"
},
  "geometry": {"coordinates":[145.08705139200001,-37.9002838135],"type":"Point"}
}