{
  "type": "Feature",
  "properties": {
    "addr:full":"31 Jellicoe Ave Monbulk VIC 3793",
    "addr:housenumber":"31",
    "addr:postcode":"3793",
    "addr:street":"Jellicoe Ave",
    "iso:country":"AU",
    "sg:address":"31 Jellicoe Ave",
    "sg:city":"Monbulk",
    "sg:classifiers":[
        {
            "category":"Professional",
            "subcategory":"Management & Consulting",
            "type":"Services"
        }
    ],
    "sg:phone":"+61 418 501 211",
    "sg:postcode":"3793",
    "sg:province":"VIC",
    "sg:tags":[
        "consultant"
    ],
    "wof:name":"Langworthy Anne",
    "wof:placetype":"venue"
},
  "geometry": {"coordinates":[145.41894531200001,-37.8754234314],"type":"Point"}
}