{
  "type": "Feature",
  "properties": {
    "addr:full":"PO Box 2625 Fitzroy VIC 3065",
    "addr:postcode":"3065",
    "iso:country":"AU",
    "sg:address":"PO Box 2625",
    "sg:city":"Fitzroy",
    "sg:classifiers":[
        {
            "category":"Education",
            "subcategory":"Special Training",
            "type":"Public Place"
        }
    ],
    "sg:phone":"+61 3 9481 4948",
    "sg:postcode":"3065",
    "sg:province":"VIC",
    "sg:tags":[
        "drama",
        "tuition"
    ],
    "wof:name":"Melbourne Arts Factory",
    "wof:placetype":"venue"
},
  "geometry": {"coordinates":[144.97915649399999,-37.8009185791],"type":"Point"}
}