{
  "type": "Feature",
  "properties": {
    "addr:full":"39 Beech St Langwarrin VIC 3910",
    "addr:housenumber":"39",
    "addr:postcode":"3910",
    "addr:street":"Beech St",
    "iso:country":"AU",
    "sg:address":"39 Beech St",
    "sg:city":"Langwarrin",
    "sg:classifiers":[
        {
            "category":"Building & Trades",
            "subcategory":"Construction",
            "type":"Services"
        }
    ],
    "sg:phone":"+61 3 9789 4256",
    "sg:postcode":"3910",
    "sg:province":"VIC",
    "sg:tags":[
        "joiner",
        "carpenter"
    ],
    "wof:name":"B & J Stone",
    "wof:placetype":"venue"
},
  "geometry": {"coordinates":[145.17805480999999,-38.1526107788],"type":"Point"}
}