{
  "type": "Feature",
  "properties": {
    "iso:country":"AU",
    "sg:address":"7 Selkirk Crt",
    "sg:city":"Highfields",
    "sg:classifiers":[
        {
            "category":"Banks & Credit Unions",
            "subcategory":"Bureau De Change",
            "type":"Services"
        }
    ],
    "sg:phone":"+61 7 4630 8093",
    "sg:postcode":"4352",
    "sg:province":"QLD",
    "sg:tags":[
        "repairs",
        "part",
        "appliance",
        "electrical"
    ],
    "wof:name":"Hobson Bob Electrical",
    "wof:placetype":"venue"
},
  "geometry": {"coordinates":[151.934189,-27.464066],"type":"Point"}
}