{
  "type": "Feature",
  "properties": {
    "addr:full":"Shop 135a Westfield Belconnen ACT 2617",
    "addr:housenumber":"135a",
    "addr:postcode":"2617",
    "addr:street":"Westfield",
    "iso:country":"AU",
    "sg:address":"Shop 135a Westfield",
    "sg:city":"Belconnen",
    "sg:classifiers":[
        {
            "category":"Shopping",
            "subcategory":"Computers & Home Electronics",
            "type":"Retail Goods"
        }
    ],
    "sg:phone":"+61 2 6251 8666",
    "sg:postcode":"2617",
    "sg:province":"ACT",
    "sg:tags":[
        "hire",
        "video",
        "game"
    ],
    "wof:name":"The Games Wizards Pty Ltd",
    "wof:placetype":"venue"
},
  "geometry": {"coordinates":[149.06353759800001,-35.239730835],"type":"Point"}
}