{
  "type": "Feature",
  "properties": {
    "iso:country":"AU",
    "sg:address":"152-154 Findon Rd",
    "sg:city":"Findon",
    "sg:classifiers":[
        {
            "category":"Retail",
            "subcategory":"Repair Shop",
            "type":"Services"
        }
    ],
    "sg:phone":"+61 8 8347 1405",
    "sg:postcode":"5023",
    "sg:province":"SA",
    "sg:tags":[
        "machine",
        "repairs",
        "part",
        "dryer",
        "washing"
    ],
    "wof:name":"Wilbys Washing Machine & Fridge Repairs",
    "wof:placetype":"venue"
},
  "geometry": {"coordinates":[138.53224182100001,-34.9029541016],"type":"Point"}
}