{
  "type": "Feature",
  "properties": {
    "iso:country":"AU",
    "sg:address":"283 Sir Donald Bradman Drv",
    "sg:city":"Brooklyn Park",
    "sg:classifiers":[
        {
            "category":"Professional",
            "subcategory":"Computer Services",
            "type":"Services"
        }
    ],
    "sg:phone":"+61 8 8238 3406",
    "sg:postcode":"5032",
    "sg:province":"SA",
    "sg:tags":[
        "consultant",
        "system"
    ],
    "wof:name":"Lansol Computers",
    "wof:placetype":"venue"
},
  "geometry": {"coordinates":[138.552490234,-34.9325561523],"type":"Point"}
}