{
  "type": "Feature",
  "properties": {
    "addr:full":"22 Laurel Oak Drv Algester QLD 4115",
    "addr:housenumber":"22",
    "addr:postcode":"4115",
    "addr:street":"Laurel Oak Drv",
    "iso:country":"AU",
    "sg:address":"22 Laurel Oak Drv",
    "sg:city":"Algester",
    "sg:phone":"+61 7 3273 4255",
    "sg:postcode":"4115",
    "sg:province":"QLD",
    "wof:name":"Ultrafilter Pty Ltd",
    "wof:placetype":"venue"
},
  "geometry": {"coordinates":[153.032440186,-27.624124527],"type":"Point"}
}