{
  "type": "Feature",
  "properties": {
    "addr:full":"4 Treeby Crt Springvale South VIC 3172",
    "addr:housenumber":"4",
    "addr:postcode":"3172",
    "addr:street":"Treeby Crt",
    "iso:country":"AU",
    "sg:address":"4 Treeby Crt",
    "sg:city":"Springvale South",
    "sg:classifiers":[
        {
            "category":"Building & Trades",
            "subcategory":"Construction",
            "type":"Services"
        }
    ],
    "sg:phone":"+61 3 9546 5391",
    "sg:postcode":"3172",
    "sg:province":"VIC",
    "sg:tags":[
        "fencing",
        "contractor"
    ],
    "wof:name":"A & A Fencing",
    "wof:placetype":"venue"
},
  "geometry": {"coordinates":[145.15406799300001,-37.9725151062],"type":"Point"}
}