{
  "type": "Feature",
  "properties": {
    "iso:country":"AU",
    "sg:address":"7 Ashby Drv",
    "sg:city":"Dandenong",
    "sg:classifiers":[
        {
            "category":"Professional",
            "subcategory":"Computer Services",
            "type":"Services"
        }
    ],
    "sg:phone":"+61 412 347 147",
    "sg:postcode":"3175",
    "sg:province":"VIC",
    "sg:tags":[
        "consultant",
        "system"
    ],
    "wof:name":"Thorux Pty Ltd",
    "wof:placetype":"venue"
},
  "geometry": {"coordinates":[145.21293640100001,-37.94789505],"type":"Point"}
}