{
  "type": "Feature",
  "properties": {
    "addr:full":"79 High St New Norfolk TAS 7140",
    "addr:housenumber":"79",
    "addr:postcode":"7140",
    "addr:street":"High St",
    "iso:country":"AU",
    "sg:address":"79 High St",
    "sg:city":"New Norfolk",
    "sg:classifiers":[
        {
            "category":"Food & Beverages",
            "subcategory":"Liquor & Beverages",
            "type":"Retail Goods"
        }
    ],
    "sg:phone":"+61 3 6261 5266",
    "sg:postcode":"7140",
    "sg:province":"TAS",
    "sg:tags":[
        "store"
    ],
    "wof:name":"BWS Beer Wine Spirits",
    "wof:placetype":"venue"
},
  "geometry": {"coordinates":[147.06558200000001,-42.780193],"type":"Point"}
}