{
  "type": "Feature",
  "properties": {
    "iso:country":"AU",
    "sg:address":"Suite 27 Pegasus Centre 42 Bundall Rd",
    "sg:city":"Bundall",
    "sg:classifiers":[
        {
            "category":"Social Services",
            "subcategory":"Child Care",
            "type":"Services"
        }
    ],
    "sg:phone":"+61 7 5581 5300",
    "sg:postcode":"4217",
    "sg:province":"QLD",
    "wof:name":"Early Learning Services",
    "wof:placetype":"venue"
},
  "geometry": {"coordinates":[153.41184997600001,-28.0108375549],"type":"Point"}
}