{
  "type": "Feature",
  "properties": {
    "iso:country":"AU",
    "sg:address":"1425 Mt Cotton Rd",
    "sg:city":"Burbank",
    "sg:classifiers":[
        {
            "category":"Retail",
            "subcategory":"Laundry & Dry Cleaning",
            "type":"Services"
        }
    ],
    "sg:phone":"+61 417 648 886",
    "sg:postcode":"4156",
    "sg:province":"QLD",
    "sg:tags":[
        "truck",
        "tip",
        "contractor"
    ],
    "wof:name":"Wayne Williams Tipper Hire",
    "wof:placetype":"venue"
},
  "geometry": {"coordinates":[153.18949890100001,-27.5254459381],"type":"Point"}
}