{
  "type": "Feature",
  "properties": {
    "addr:full":"14 Mt Gravatt-Capalaba Rd Upper Mt Gravatt QLD 4122",
    "addr:housenumber":"14",
    "addr:postcode":"4122",
    "addr:street":"Mt Gravatt-Capalaba Rd Upper",
    "iso:country":"AU",
    "sg:address":"14 Mt Gravatt-Capalaba Rd",
    "sg:city":"Upper Mt Gravatt",
    "sg:classifiers":[
        {
            "category":"Professional",
            "subcategory":"Accounting & Tax Preparation",
            "type":"Services"
        }
    ],
    "sg:phone":"+61 7 3849 6586",
    "sg:postcode":"4122",
    "sg:province":"QLD",
    "sg:tags":[
        "consultant",
        "taxation"
    ],
    "wof:name":"Cox Graeme",
    "wof:placetype":"venue"
},
  "geometry": {"coordinates":[153.081787109,-27.5594844818],"type":"Point"}
}