{
  "type": "Feature",
  "properties": {
    "addr:full":"92 Clyde St St Kilda VIC 3182",
    "addr:housenumber":"92",
    "addr:postcode":"3182",
    "addr:street":"Clyde St",
    "iso:country":"AU",
    "sg:address":"92 Clyde St",
    "sg:city":"St Kilda",
    "sg:classifiers":[
        {
            "category":"Professional",
            "subcategory":"Art Services",
            "type":"Services"
        }
    ],
    "sg:phone":"+61 3 9534 0388",
    "sg:postcode":"3182",
    "sg:province":"VIC",
    "sg:tags":[
        "graphic",
        "designer"
    ],
    "wof:name":"Wilson Hill Pty Ltd",
    "wof:placetype":"venue"
},
  "geometry": {"coordinates":[144.981079102,-37.8638496399],"type":"Point"}
}