{
  "type": "Feature",
  "properties": {
    "iso:country":"AU",
    "sg:address":"PO Box 502",
    "sg:city":"Charleville",
    "sg:classifiers":[
        {
            "category":"Professional",
            "subcategory":"Business Services",
            "type":"Services"
        }
    ],
    "sg:phone":"+61 7 4654 1644",
    "sg:postcode":"4470",
    "sg:province":"QLD",
    "sg:tags":[
        "livestock",
        "transport"
    ],
    "wof:name":"Castles L G & C",
    "wof:placetype":"venue"
},
  "geometry": {"coordinates":[146.24801635700001,-26.4039592743],"type":"Point"}
}