{
  "type": "Feature",
  "properties": {
    "addr:full":"63- 65 Bridge St Bendigo VIC 3550",
    "addr:housenumber":"65",
    "addr:postcode":"3550",
    "addr:street":"Bridge St",
    "iso:country":"AU",
    "sg:address":"63- 65 Bridge St",
    "sg:city":"Bendigo",
    "sg:classifiers":[
        {
            "category":"Health Services",
            "subcategory":"Doctor",
            "type":"Services"
        }
    ],
    "sg:phone":"+61 3 5454 2300",
    "sg:postcode":"3550",
    "sg:province":"VIC",
    "sg:tags":[
        "medical",
        "practitioner"
    ],
    "wof:name":"Van Der Spek A C",
    "wof:placetype":"venue"
},
  "geometry": {"coordinates":[144.284057617,-36.751701355],"type":"Point"}
}