{
  "type": "Feature",
  "properties": {
    "iso:country":"AU",
    "sg:address":"13 Oppermann Drv",
    "sg:city":"Ormeau",
    "sg:classifiers":[
        {
            "category":"Building & Trades",
            "subcategory":"Construction",
            "type":"Services"
        }
    ],
    "sg:phone":"+61 7 5546 7017",
    "sg:postcode":"4208",
    "sg:province":"QLD",
    "sg:tags":[
        "contractor"
    ],
    "wof:name":"Jarrah Homes",
    "wof:placetype":"venue"
},
  "geometry": {"coordinates":[153.2449646,-27.7883720398],"type":"Point"}
}