{
  "type": "Feature",
  "properties": {
    "addr:full":"226 Morrison Rd Midvale WA 6056",
    "addr:housenumber":"226",
    "addr:postcode":"6056",
    "addr:street":"Morrison Rd",
    "iso:country":"AU",
    "sg:address":"226 Morrison Rd",
    "sg:city":"Midvale",
    "sg:classifiers":[
        {
            "category":"Autos & Motor Vehicles",
            "subcategory":"Fuel & Gas Station",
            "type":"Retail Goods"
        }
    ],
    "sg:phone":"+61 8 9250 1776",
    "sg:postcode":"6056",
    "sg:province":"WA",
    "wof:name":"BP Midvale",
    "wof:placetype":"venue"
},
  "geometry": {"coordinates":[116.031799316,-31.8860149384],"type":"Point"}
}