{
  "type": "Feature",
  "properties": {
    "addr:full":"125 Baker St Gosford NSW 2250",
    "addr:housenumber":"125",
    "addr:postcode":"2250",
    "addr:street":"Baker St",
    "iso:country":"AU",
    "sg:address":"125 Baker St",
    "sg:city":"Gosford",
    "sg:classifiers":[
        {
            "category":"Health Services",
            "subcategory":"Doctor",
            "type":"Services"
        }
    ],
    "sg:phone":"+61 2 4324 6722",
    "sg:postcode":"2250",
    "sg:province":"NSW",
    "sg:tags":[
        "medical",
        "practitioner"
    ],
    "wof:name":"Breasts Screening (Northern Program)",
    "wof:placetype":"venue"
},
  "geometry": {"coordinates":[151.34124755900001,-33.4258422852],"type":"Point"}
}