{
  "type": "Feature",
  "properties": {
    "addr:full":"1 Canopus Drv Doncaster East VIC 3109",
    "addr:housenumber":"1",
    "addr:postcode":"3109",
    "addr:street":"Canopus Drv",
    "iso:country":"AU",
    "sg:address":"1 Canopus Drv",
    "sg:city":"Doncaster East",
    "sg:classifiers":[
        {
            "category":"Health Services",
            "subcategory":"Dentist",
            "type":"Services"
        }
    ],
    "sg:phone":"+61 3 9842 2658",
    "sg:postcode":"3109",
    "sg:province":"VIC",
    "wof:name":"B Dental",
    "wof:placetype":"venue"
},
  "geometry": {"coordinates":[145.16427612300001,-37.7760887146],"type":"Point"}
}