{
  "type": "Feature",
  "properties": {
    "addr:full":"14 Bondi Rd Bonbeach VIC 3196",
    "addr:housenumber":"14",
    "addr:postcode":"3196",
    "addr:street":"Bondi Rd",
    "iso:country":"AU",
    "sg:address":"14 Bondi Rd",
    "sg:city":"Bonbeach",
    "sg:classifiers":[
        {
            "category":"Professional",
            "subcategory":"Art Services",
            "type":"Services"
        }
    ],
    "sg:phone":"+61 3 9773 2896",
    "sg:postcode":"3196",
    "sg:province":"VIC",
    "sg:tags":[
        "decorator",
        "painter"
    ],
    "wof:name":"Brian's One Call Painting & Maintenance",
    "wof:placetype":"venue"
},
  "geometry": {"coordinates":[145.12164306599999,-38.0632095337],"type":"Point"}
}