{
  "type": "Feature",
  "properties": {
    "iso:country":"AU",
    "sg:address":"34 High Range Rd",
    "sg:city":"Thuringowa Central",
    "sg:classifiers":[
        {
            "category":"Retail",
            "subcategory":"Repair Shop",
            "type":"Services"
        }
    ],
    "sg:phone":"+61 7 4773 7006",
    "sg:postcode":"4817",
    "sg:province":"QLD",
    "sg:tags":[
        "machine",
        "sewing"
    ],
    "wof:name":"Janome Townsville",
    "wof:placetype":"venue"
},
  "geometry": {"coordinates":[146.724823,-19.319843],"type":"Point"}
}