{
  "type": "Feature",
  "properties": {
    "addr:full":"400 Oxford St Paddington NSW 2021",
    "addr:housenumber":"400",
    "addr:postcode":"2021",
    "addr:street":"Oxford St",
    "iso:country":"AU",
    "sg:address":"400 Oxford St",
    "sg:city":"Paddington",
    "sg:classifiers":[
        {
            "category":"Shopping",
            "subcategory":"Clothing, Apparel, & Fashions",
            "type":"Retail Goods"
        }
    ],
    "sg:phone":"+61 2 9356 3191",
    "sg:postcode":"2021",
    "sg:province":"NSW",
    "sg:tags":[
        "lady",
        "wear"
    ],
    "wof:name":"Bardot",
    "wof:placetype":"venue"
},
  "geometry": {"coordinates":[151.230545044,-33.887046814],"type":"Point"}
}