{
  "type": "Feature",
  "properties": {
    "addr:full":"100 Bolderwood Drv South Lake WA 6164",
    "addr:housenumber":"100",
    "addr:postcode":"6164",
    "addr:street":"Bolderwood Drv",
    "iso:country":"AU",
    "sg:address":"100 Bolderwood Drv",
    "sg:city":"South Lake",
    "sg:classifiers":[
        {
            "category":"Health Services",
            "subcategory":"Health Practitioner",
            "type":"Services"
        }
    ],
    "sg:phone":"+61 411 017 916",
    "sg:postcode":"6164",
    "sg:province":"WA",
    "sg:tags":[
        "bowen",
        "therapy"
    ],
    "wof:name":"David Moreschi",
    "wof:placetype":"venue"
},
  "geometry": {"coordinates":[115.847717285,-32.1028251648],"type":"Point"}
}