{
  "type": "Feature",
  "properties": {
    "iso:country":"AU",
    "sg:address":"53 Phillip St",
    "sg:city":"St Marys",
    "sg:classifiers":[
        {
            "category":"Health Services",
            "subcategory":"Doctor",
            "type":"Services"
        }
    ],
    "sg:phone":"+61 2 9623 4288",
    "sg:postcode":"2760",
    "sg:province":"NSW",
    "sg:tags":[
        "medical",
        "practitioner"
    ],
    "wof:name":"St Marys Medical Centre",
    "wof:placetype":"venue"
},
  "geometry": {"coordinates":[150.77537536599999,-33.763633728],"type":"Point"}
}