{
  "type": "Feature",
  "properties": {
    "addr:full":"11A Northumberland St Heathpool SA 5068",
    "addr:housenumber":"11a",
    "addr:postcode":"5068",
    "addr:street":"Northumberland St",
    "iso:country":"AU",
    "sg:address":"11A Northumberland St",
    "sg:city":"Heathpool",
    "sg:classifiers":[
        {
            "category":"Professional",
            "subcategory":"Art Services",
            "type":"Services"
        }
    ],
    "sg:phone":"+61 8 8431 7201",
    "sg:postcode":"5068",
    "sg:province":"SA",
    "sg:tags":[
        "interior",
        "designer"
    ],
    "wof:name":"Lulu Design",
    "wof:placetype":"venue"
},
  "geometry": {"coordinates":[138.649734497,-34.9311065674],"type":"Point"}
}