{
  "type": "Feature",
  "properties": {
    "addr:full":"14 Embling St Wanniassa ACT 2903",
    "addr:housenumber":"14",
    "addr:postcode":"2903",
    "addr:street":"Embling St",
    "iso:country":"AU",
    "sg:address":"14 Embling St",
    "sg:city":"Wanniassa",
    "sg:classifiers":[
        {
            "category":"Professional",
            "subcategory":"Engineering",
            "type":"Services"
        }
    ],
    "sg:phone":"+61 2 6296 3530",
    "sg:postcode":"2903",
    "sg:province":"ACT",
    "sg:tags":[
        "consulting",
        "engineer"
    ],
    "wof:name":"Sanchjack Consulting Services",
    "wof:placetype":"venue"
},
  "geometry": {"coordinates":[149.09548950199999,-35.3981666565],"type":"Point"}
}