{
  "type": "Feature",
  "properties": {
    "addr:full":"255 Colchester Rd Kilsyth VIC 3137",
    "addr:housenumber":"255",
    "addr:postcode":"3137",
    "addr:street":"Colchester Rd",
    "iso:country":"AU",
    "sg:address":"255 Colchester Rd",
    "sg:city":"Kilsyth",
    "sg:classifiers":[
        {
            "category":"Sports & Exercise",
            "subcategory":"Gym",
            "type":"Entertainment"
        }
    ],
    "sg:phone":"+61 3 9761 5077",
    "sg:postcode":"3137",
    "sg:province":"VIC",
    "sg:tags":[
        "health",
        "fitness"
    ],
    "wof:name":"Spartans Gym & Fitness",
    "wof:placetype":"venue"
},
  "geometry": {"coordinates":[145.304031372,-37.8235702515],"type":"Point"}
}