{
  "type": "Feature",
  "properties": {
    "iso:country":"AU",
    "sg:address":"150 St. Andrews Drv",
    "sg:city":"Port Lincoln",
    "sg:classifiers":[
        {
            "category":"Wholesale",
            "subcategory":"Machinery & Supplies",
            "type":"Manufacturing & Wholesale Goods"
        }
    ],
    "sg:phone":"+61 8 8683 0099",
    "sg:postcode":"5606",
    "sg:province":"SA",
    "sg:tags":[
        "equipment",
        "hydraulic"
    ],
    "wof:name":"Diesel & Marine Services",
    "wof:placetype":"venue"
},
  "geometry": {"coordinates":[135.869766,-34.743382],"type":"Point"}
}