{
  "type": "Feature",
  "properties": {
    "addr:full":"U8/ 56 Foundary Rd Seven Hills NSW 2147",
    "addr:housenumber":"56",
    "addr:postcode":"2147",
    "addr:street":"U8 /;Foundary Rd",
    "iso:country":"AU",
    "sg:address":"U8/ 56 Foundary Rd",
    "sg:city":"Seven Hills",
    "sg:classifiers":[
        {
            "category":"Building & Trades",
            "subcategory":"Construction",
            "type":"Services"
        }
    ],
    "sg:phone":"+61 2 9793 8808",
    "sg:postcode":"2147",
    "sg:province":"NSW",
    "sg:tags":[
        "joinery"
    ],
    "wof:name":"Acute Joinery Australia",
    "wof:placetype":"venue"
},
  "geometry": {"coordinates":[150.95588684099999,-33.7697486877],"type":"Point"}
}