{
  "type": "Feature",
  "properties": {
    "addr:full":"431 Lakes Creek Rd North Rockhampton QLD 4701",
    "addr:housenumber":"431",
    "addr:postcode":"4701",
    "addr:street":"Lakes Creek Rd North",
    "iso:country":"AU",
    "sg:address":"431 Lakes Creek Rd",
    "sg:city":"North Rockhampton",
    "sg:classifiers":[
        {
            "category":"Travel",
            "subcategory":"Hotels & Motels",
            "type":"Entertainment"
        }
    ],
    "sg:phone":"+61 7 4928 3050",
    "sg:postcode":"4701",
    "sg:province":"QLD",
    "sg:tags":[
        "accommodation"
    ],
    "wof:name":"Lakes Creek Hotel",
    "wof:placetype":"venue"
},
  "geometry": {"coordinates":[150.55821227999999,-23.3759727478],"type":"Point"}
}