{
  "type": "Feature",
  "properties": {
    "addr:full":"8 Riseley St Applecross WA 6153",
    "addr:housenumber":"8",
    "addr:postcode":"6153",
    "addr:street":"Riseley St",
    "iso:country":"AU",
    "sg:address":"8 Riseley St",
    "sg:city":"Applecross",
    "sg:classifiers":[
        {
            "category":"Health Services",
            "subcategory":"Health Practitioner",
            "type":"Services"
        }
    ],
    "sg:phone":"+61 8 9364 4073",
    "sg:postcode":"6153",
    "sg:province":"WA",
    "sg:tags":[
        "physiotherapist"
    ],
    "wof:name":"Riseley",
    "wof:placetype":"venue"
},
  "geometry": {"coordinates":[115.83387,-32.019905],"type":"Point"}
}