{
  "type": "Feature",
  "properties": {
    "iso:country":"AU",
    "sg:address":"30 Webber Pde",
    "sg:city":"Keilor East",
    "sg:classifiers":[
        {
            "category":"Shopping",
            "subcategory":"Crafts & Fabrics",
            "type":"Retail Goods"
        }
    ],
    "sg:phone":"+61 3 9331 6888",
    "sg:postcode":"3033",
    "sg:province":"VIC",
    "sg:tags":[
        "adhesive"
    ],
    "wof:name":"Architectural & Structural Adhesives",
    "wof:placetype":"venue"
},
  "geometry": {"coordinates":[144.855896,-37.735703],"type":"Point"}
}